Workbook
Name Sectors: '[1]Sector Impact'!$K$4:$K$16
Name Sectors: 'Sector Impact'!$K$4:$K$16

Sheet OP
B2: 45039 | C2: Team 1 | E2: =Inputs!H3 -> #VALUE! | L2: NYSE | M2: SIC:
D3: COMPANY DESCRIPTION | H3: CEO & BOARD OF DIRECTORS
D4: {=_FV(Inputs!H3,"Description")} -> Advanced Micro Devices, Inc. is a global semiconductor company. The Company is focused on high-performance computing, graphics and visualization technologies. Its segments include Data Center, Client, Gaming and Embedded. The Data Center segment includes server central processing unit (CPUs), graphics processing units (GPUs), accelerated processing units (APUs), data processing units (DPUs), field programmable gate arrays (FPGAs), smart network interface cards (SmartNICs), artificial intelligence (AI) accelerators and adaptive system-on-chip (SoC) products for data centers. The Client segment includes CPUs, APUs, and chipsets for desktop, notebook and handheld personal computers. The Gaming segment includes discrete GPUs, semi-custom SoC products and development services. The Embedded segment includes embedded CPUs, GPUs, APUs, FPGAs, system on modules (SOMs), and adaptive SoC products. The Company's products include AMD Ryzen AI, Radeon PRO and AMD Advantage Premium. | H4: Name | I4: Gender | J4: Age | K4: Tenure | L4: Executive? | M4: Other roles
B17: USD MILLIONS
B18: COMPANY OVERVIEW
B19: Stock | D19: Liquidity and Solvency | F19: Segments | I19: Profitability (2022) | L19: Multiples
B20: Last Price | C20: {=_FV(E2,"Price")} -> 146.64 | D20: Total Assets | E20: =_xlfn.XLOOKUP(D20,'Fin. Data'!A:A,'Fin. Data'!B:B,,0) -> 67885 | F20: Regions | H20: % Sales | I20: Reporting Year | J20: 2023 | L20: Float
B21: Outstanding Shares | C21: {=_FV(E2,"Shares outstanding",TRUE)} -> 1616140000 | D21: Total Liabilities | E21: =_xlfn.XLOOKUP(D21,'Fin. Data'!A:A,'Fin. Data'!B:B,,0) -> 11993 | F21: =Segments!C5 -> United States | H21: =Segments!B5 -> 0.34554674 | I21: End of Year | J21: 45291 | L21: Insiders Own
B22: Market Cap. | C22: =C20*C21/1000000 -> 236990.77 | D22: Cash/Share | E22: =_xlfn.XLOOKUP("Cash & Eq.",'Fin. Data'!A:A,'Fin. Data'!B:B,,0)*1000000/C21 -> 2.4335763 | F22: =Segments!C6 -> Japan | H22: =Segments!B6 -> 0.20410053 | I22: EBITDA | K22: =_xlfn.XLOOKUP(I22,'Fin. Data'!A:A,'Fin. Data'!B:B,,0) -> 3846 | L22: b (Yahoo)
B23: +Total Debt | C23: ='Fin. Data'!B58 -> 2252 | D23: EBITDA/Net Financial Cost (NFC) | E23: =_xlfn.XLOOKUP("EBITDA",'Fin. Data'!A:A,'Fin. Data'!B:B,,0)/_xlfn.XLOOKUP("Net Financial Cost",'Fin. Data'!A:A,'Fin. Data'!B:B,,0) -> 38.848485 | F23: =Segments!C7 -> China (including Hong Kong) | H23: =Segments!B7 -> 0.15066138 | I23: Depreciation & Amortization | K23: =_xlfn.XLOOKUP(I23,'Fin. Data'!A:A,'Fin. Data'!B:B,,0) -> 3453 | L23: Score (S&P)
B24: -Cash | C24: ='Fin. Data'!B39 -> 3933 | D24: Debt/EBITDA | E24: =_xlfn.XLOOKUP("Total Debt",'Fin. Data'!A:A,'Fin. Data'!B:B,,0)/_xlfn.XLOOKUP("EBITDA",'Fin. Data'!A:A,'Fin. Data'!B:B,,0) -> 0.58554342 | F24: =Segments!C8 -> Singapore | H24: =Segments!B8 -> 0.098368607 | I24: EBIT | K24: =_xlfn.XLOOKUP(I24,'Fin. Data'!A:A,'Fin. Data'!B:B,,0) -> 393 | L24: Price/Book Value | M24: =IFERROR((C20*C21/(E20-E21))/1000000,"") -> 4.2401555
B25: =Enterprise Value | C25: =C22+C23-C24 -> 235309.77 | D25: "Others Assets"/Asset | E25: =_xlfn.XLOOKUP("Other Assets",'Fin. Data'!A:A,'Fin. Data'!B:B,,0)/_xlfn.XLOOKUP("Total Assets",'Fin. Data'!A:A,'Fin. Data'!B:B,,0) -> 0.76458717 | F25: =Segments!C9 -> Europe | H25: =Segments!B9 -> 0.089506173 | I25: Net Income | K25: =_xlfn.XLOOKUP(I25,'Fin. Data'!A:A,'Fin. Data'!B:B,,0) -> 854 | L25: NCF(3y avg)/Asset | M25: =IFERROR(K31/E20,"") -> 0.026201174
B26: Holdings (nac/int'l) | C26: - | D26: Debt/Assets | E26: =_xlfn.XLOOKUP(D26,'Fin. Data'!A:A,'Fin. Data'!B:B,,0) -> 0.03317375 | F26: Categories | H26: % Sales | I26: EPS | K26: =1000000*K25/C21 -> 0.52841957 | L26: Price/Net Inc. (3y avg) | M26: =IFERROR(C22/K30,"") -> 133.24069
B27: t liq. (Holdings/Vol.) | C27: - | D27: EBITDA Margin (average) | E27: =AVERAGE(_xlfn.XLOOKUP("EBITDA Margin",'Fin. Data'!A:A,'Fin. Data'!B:D,,0)) -> 0.21508695 | F27: =Segments!C19 -> Data Center | H27: =Segments!B19 -> 0.28641975 | I27: ROA | K27: =K25/E20 -> 0.012580099 | L27: EV/Asset | M27: =IFERROR(C25/E20,"") -> 3.4662999
B28: % Short | D28: Operating Margin (average) | E28: =AVERAGE(_xlfn.XLOOKUP("Operating Margin",'Fin. Data'!A:A,'Fin. Data'!B:D,,0)) -> 0.097596902 | F28: =Segments!C21 -> Gaming | H28: =Segments!B21 -> 0.27389771 | I28: ROIC | K28: =Peers!C18 -> 0.012515762 | L28: EV/Ebitda (3y average) | M28: =IFERROR(C25/K29,"") -> 53.041499
B29: Traffic ESG | D29: Net Income Margin (average) | E29: =AVERAGE(_xlfn.XLOOKUP("Net Income Margin",'Fin. Data'!A:A,'Fin. Data'!B:D,,0)) -> 0.095330047 | F29: =Segments!C22 -> Embedded | H29: =Segments!B22 -> 0.23461199 | I29: EBITDA (3y average) | K29: =AVERAGE(_xlfn.XLOOKUP("EBITDA",'Fin. Data'!A:A,'Fin. Data'!B:D,,0)) -> 4436.3333 | L29: Price/NCF (3y average) | M29: =IFERROR(C22/K31,"") -> 133.24069
B30: E | F30: =Segments!C20 -> Client | H30: =Segments!B20 -> 0.20507055 | I30: Net Income (3y average) | K30: =AVERAGE(_xlfn.XLOOKUP("Net Income",'Fin. Data'!A:A,'Fin. Data'!B:D,,0)) -> 1778.6667 | L30: Bonds 1,3,5a (USD) | M30: -
B31: S | D31: Net Financial Cost/Avg Net Debt | E31: =-_xlfn.XLOOKUP("Net Financial Cost",'Fin. Data'!A:A,'Fin. Data'!B:B,,0)/AVERAGE(_xlfn.XLOOKUP("Net Debt",'Fin. Data'!A:A,'Fin. Data'!B:D,,0)) -> 0.050864874 | F31: =Segments!#REF! -> #REF! | H31: =Segments!#REF! -> #REF! | I31: NCF (3y average) | K31: =AVERAGE(_xlfn.XLOOKUP("Net Income",'Fin. Data'!A:A,'Fin. Data'!B:D,,0)) -> 1778.6667 | L31: Div+Rep.(3y avg)/Price | M31: =-IFERROR(SUM(E52:E54)/(3*C22),"") -> 0.0090706768
B32: G | L32: Div. Yield | M32: =-IFERROR(L53/C22,"") -> 0
B33: INVESTMENT THESIS
B34: Pillars of Recommendation | H34: Recommendation | I34: Valuation Assumptions
B35: Pillar | C35: Explanation
B39: Risks of Investment | H39: Price Target | I39: Valuation
B40: Risk | C40: Explanation | H40: =DCF!D75 -> #DIV/0! | I40: Discount Rate | J40: =DCF!F50 -> 0 | L40: Price M. Upside | M40: =SARD!AJ14 -> #NUM!
I42: Upside | J42: =DCF!D74 -> #DIV/0! | L42: EV M. Upside | M42: =SARD!AM14 -> #NUM!
B44: FINANCIAL PERFORMANCE
B45: Year | C45: Net Sales | D45: Operating Margin | E45: Dividends + Share Buyback | F45: Net Cash Flow | G45: Debt/Assets | H45: Depreciation & Amortization | I45: Capex + Investments | J45: Cash Flow
B46: =B47-1 -> 2015 | C46: {=_xlfn.SORTBY(TRANSPOSE(_xlfn.XLOOKUP(C$45,'Fin. Data'!$A:$A,'Fin. Data'!$B:$J,,0)),$B$46:$B$54,-1)} -> 3991 | D46: {=_xlfn.SORTBY(TRANSPOSE(_xlfn.XLOOKUP(D$45,'Fin. Data'!$A:$A,'Fin. Data'!$B:$J,,0)),$B$46:$B$54,-1)} -> -0.12052117 | E46: {=_xlfn.SORTBY(TRANSPOSE(_xlfn.XLOOKUP(E$45,'Fin. Data'!$A:$A,'Fin. Data'!$B:$J,,0)),$B$46:$B$54,-1)} -> 0 | F46: =Inputs!J77 -> -20 | G46: {=_xlfn.SORTBY(TRANSPOSE(_xlfn.XLOOKUP(G$45,'Fin. Data'!$A:$A,'Fin. Data'!$B:$J,,0)),$B$46:$B$54,-1)} -> 0.72535668 | H46: {=_xlfn.SORTBY(TRANSPOSE(_xlfn.XLOOKUP(H$45,'Fin. Data'!$A:$A,'Fin. Data'!$B:$J,,0)),$B$46:$B$54,-1)} -> 167 | I46: {=_xlfn.SORTBY(TRANSPOSE(_xlfn.XLOOKUP(I$45,'Fin. Data'!$A:$A,'Fin. Data'!$B:$J,,0)),$B$46:$B$54,-1)} -> 147 | L46: =J20 -> 2023 | M46: =L46-1 -> 2022
B47: =B48-1 -> 2016 | C47: 4272 | D47: -0.10299625 | E47: 0 | F47: =Inputs!I77 -> 479 | G47: 0.43209877 | H47: 133 | I47: 265 | J47: Net Income | L47: =_xlfn.XLOOKUP($J47,'Fin. Data'!$A:$A,'Fin. Data'!B:B,,0) -> 854 | M47: =_xlfn.XLOOKUP($J47,'Fin. Data'!$A:$A,'Fin. Data'!C:C,,0) -> 1320 | N47: =(C47/C46)-1 -> 0.070408419 | O47: =(D47/D46)-1 -> -0.14540945
B48: =B49-1 -> 2017 | C48: 5253 | D48: 0.021892252 | E48: 0 | F48: =Inputs!H77 -> -75 | G48: 0.39273649 | H48: 144 | I48: -112 | J48: Operating CF | L48: =_xlfn.XLOOKUP($J48,'Fin. Data'!$A:$A,'Fin. Data'!B:B,,0) -> 1667 | M48: =_xlfn.XLOOKUP($J48,'Fin. Data'!$A:$A,'Fin. Data'!C:C,,0) -> 3565 | N48: =(C48/C47)-1 -> 0.22963483 | O48: =(D48/D47)-1 -> -1.2125539 | Q48: =F48/F47-1 -> -1.1565762 | R48: =H48/H47-1 -> 0.082706767 | S48: =I48/I47-1 -> -1.4226415
B49: =B50-1 -> 2018 | C49: 6475 | D49: 0.067799228 | E49: 0 | F49: =Inputs!G77 -> -108 | G49: 0.27436348 | H49: 170 | I49: -241 | J49: Investing CF | L49: =_xlfn.XLOOKUP($J49,'Fin. Data'!$A:$A,'Fin. Data'!B:B,,0) -> -1423 | M49: =_xlfn.XLOOKUP($J49,'Fin. Data'!$A:$A,'Fin. Data'!C:C,,0) -> 1999 | N49: =(C49/C48)-1 -> 0.23262897 | O49: =(D49/D48)-1 -> 2.0969508 | Q49: =F49/F48-1 -> 0.44 | R49: =H49/H48-1 -> 0.18055556 | S49: =I49/I48-1 -> 1.1517857
B50: =B51-1 -> 2019 | C50: 6731 | D50: 0.067597682 | E50: 0 | F50: =Inputs!F77 -> 387 | G50: 0.11363636 | H50: 222 | I50: -176 | J50: Net Capex | L50: =_xlfn.XLOOKUP($J50,'Fin. Data'!$A:$A,'Fin. Data'!B:B,,0) -> -546 | M50: =_xlfn.XLOOKUP($J50,'Fin. Data'!$A:$A,'Fin. Data'!C:C,,0) -> -450 | N50: =(C50/C49)-1 -> 0.03953668 | O50: =(D50/D49)-1 -> -0.0029726804 | Q50: =F50/F49-1 -> -4.5833333 | R50: =H50/H49-1 -> 0.30588235 | S50: =I50/I49-1 -> -0.26970954
B51: =B52-1 -> 2020 | C51: 9763 | D51: 0.13469221 | E51: 0 | F51: =Inputs!E77 -> 125 | G51: 0.059250167 | H51: 312 | I51: -952 | J51: Investments & Acquisitions | L51: =_xlfn.XLOOKUP($J51,'Fin. Data'!$A:$A,'Fin. Data'!B:B,,0) -> -866 | M51: =_xlfn.XLOOKUP($J51,'Fin. Data'!$A:$A,'Fin. Data'!C:C,,0) -> 2465 | N51: =(C51/C50)-1 -> 0.45045313 | O51: =(D51/D50)-1 -> 0.99255656 | Q51: =F51/F50-1 -> -0.67700258 | R51: =H51/H50-1 -> 0.40540541 | S51: =I51/I50-1 -> 4.4090909
B52: =B53-1 -> 2021 | C52: 16434 | D52: 0.22155288 | E52: -1762 | F52: =Inputs!D77 -> 940 | G52: 0.028102102 | H52: 407 | I52: -679 | J52: Financing CF | L52: =_xlfn.XLOOKUP($J52,'Fin. Data'!$A:$A,'Fin. Data'!B:B,,0) -> -1146 | M52: =_xlfn.XLOOKUP($J52,'Fin. Data'!$A:$A,'Fin. Data'!C:C,,0) -> -3264 | N52: =(C52/C51)-1 -> 0.68329407 | O52: =(D52/D51)-1 -> 0.6448827 | Q52: =F52/F51-1 -> 6.52 | R52: =H52/H51-1 -> 0.30448718 | S52: =I52/I51-1 -> -0.28676471
B53: =B54-1 -> 2022 | C53: 23601 | D53: 0.053557053 | E53: -3702 | F53: =Inputs!C$77 -> 2300 | G53: 0.042364605 | H53: 4174 | I53: 2015 | J53: Dividends | L53: =_xlfn.XLOOKUP($J53,'Fin. Data'!$A:$A,'Fin. Data'!B:B,,0) -> 0 | M53: =_xlfn.XLOOKUP($J53,'Fin. Data'!$A:$A,'Fin. Data'!C:C,,0) -> 0 | N53: =(C53/C52)-1 -> 0.43610807 | O53: =(D53/D52)-1 -> -0.75826515 | Q53: =F53/F52-1 -> 1.4468085 | R53: =H53/H52-1 -> 9.2555283 | S53: =I53/I52-1 -> -3.9675994
B54: =J20 -> 2023 | C54: 22680 | D54: 0.017680776 | E54: -985 | F54: =Inputs!B77 -> -902 | G54: 0.03317375 | H54: 3453 | I54: -1412 | J54: Share Buyback | L54: =_xlfn.XLOOKUP($J54,'Fin. Data'!$A:$A,'Fin. Data'!B:B,,0) -> -985 | M54: =_xlfn.XLOOKUP($J54,'Fin. Data'!$A:$A,'Fin. Data'!C:C,,0) -> -3702 | N54: =(C54/C53)-1 -> -0.03902377 | O54: =(D54/D53)-1 -> -0.66987026 | Q54: =F54/F53-1 -> -1.3921739 | R54: =H54/H53-1 -> -0.17273598 | S54: =I54/I53-1 -> -1.7007444
B55: Annual Growth Rate | C55: =IFERROR((C54/C46)^(1/8)-1,"") -> 0.242568 | D55: =IFERROR((D54/D46)^(1/8)-1,"") | F55: =IFERROR((F54/F46)^(1/8)-1,"") -> 0.60980054 | H55: =IFERROR((H54/H46)^(1/8)-1,"") -> 0.46027622 | J55: FX | L55: =_xlfn.XLOOKUP($J55,'Fin. Data'!$A:$A,'Fin. Data'!B:B,,0) -> 0 | M55: =_xlfn.XLOOKUP($J55,'Fin. Data'!$A:$A,'Fin. Data'!C:C,,0) -> 0 | N55: =(C55/C54)-1 -> -0.9999893 | O55: =(D55/D54)-1 -> #VALUE!
B56: Average Growth Rate | C56: =IFERROR(AVERAGE(N47:N54),"") -> 0.26288005 | D56: =IFERROR(AVERAGE(O47:O54),"") -> 0.11816483 | F56: =IFERROR(AVERAGE(Q47:Q54),"") -> 0.085388926 | H56: =IFERROR(AVERAGE(S47:S54),"") -> -0.29808328 | J56: Changes in Cash | L56: =L48-L49+L52-L53-L54 -> 2929 | M56: =M48-M49+M52-M53-M54 -> 2004
B57: CVAR | C57: =IFERROR(STDEV(C47:C54)/AVERAGE(C47:C54),"") -> 0.66372218 | D57: =IFERROR(STDEV(D46:D54)/AVERAGE(D46:D54),"") -> 2.6525091 | F57: =IFERROR(STDEV(F46:F54)/AVERAGE(F46:F54),"") -> 2.5577588 | H57: =IFERROR(STDEV(H46:H54)/AVERAGE(H46:H54),"") -> 1.5646555 | J57: Inventory/D Revenues | L57: =IFERROR(SUM(I51:I54)/(C54-C50),"") -> -0.064455452 | M57: =IFERROR((SUM(I51:I54)-SUM(H51:H54))/(C54-C50),"") -> -0.58774845
B58: Last Year | C58: =IFERROR(C54/C53-1,"") -> -0.03902377 | D58: =IFERROR(D54/D53-1,"") -> -0.66987026 | F58: =IFERROR(1-(F54/F53),"") -> 1.3921739 | H58: =IFERROR(1-(H54/H53),"") -> 0.17273598 | J58: t inversiones; t adq. neto dep. | L58: =IFERROR(L57/E27,"") -> -0.29967161 | M58: =IFERROR(M57/E27,"") -> -2.7326086
B59: QUALITATIVE ANALYSIS
B60: SWOT ANALYSIS | J60: HOLDERS
B61: Pros | E61: Cons | J61: Name | M61: % Stake
B72: Opportunities | E72: Risks
B82: NOTES | G82: STOCK PERFORMANCE (5 years)

Sheet Segments
B2: ="Regions "&"("&OP!$J$20&")" -> Regions (2023) | Q2: Products
D3: Nominal value | K3: YoY Growth
B4: Weight | C4: Region | D4: =OP!J20 -> 2023 | E4: =D4-1 -> 2022 | F4: =E4-1 -> 2021 | G4: =F4-1 -> 2020 | H4: =G4-1 -> 2019 | I4: =H4-1 -> 2018 | K4: =OP!J20 -> 2023 | L4: =K4-1 -> 2022 | M4: =L4-1 -> 2021 | N4: =M4-1 -> 2020 | O4: =N4-1 -> 2019 | P4: =O4-1 -> 2018
B5: =IFERROR(D5/$D$14,"") -> 0.34554674 | C5: United States | D5: 7837 | E5: 8049 | F5: 4656 | G5: 2294 | H5: 1764 | I5: 1327 | K5: =(D5-E5)/E5 -> -0.026338676 | L5: =(E5-F5)/F5 -> 0.72873711 | M5: =(F5-G5)/G5 -> 1.0296425 | N5: =(G5-H5)/H5 -> 0.30045351 | O5: =(H5-I5)/I5 -> 0.32931424 | P5: -
B6: =IFERROR(D6/$D$14,"") -> 0.20410053 | C6: Japan | D6: 4629 | E6: 4177 | F6: 2381 | G6: 1033 | H6: 840 | I6: 1225 | K6: =(D6-E6)/E6 -> 0.10821164 | L6: =(E6-F6)/F6 -> 0.75430491 | M6: =(F6-G6)/G6 -> 1.3049371 | N6: =(G6-H6)/H6 -> 0.2297619 | O6: =(H6-I6)/I6 -> -0.31428571 | P6: -
B7: =IFERROR(D7/$D$14,"") -> 0.15066138 | C7: China (including Hong Kong) | D7: 3417 | E7: 5207 | F7: 4096 | G7: 2329 | H7: 1736 | I7: 1319 | K7: =(D7-E7)/E7 -> -0.343768 | L7: =(E7-F7)/F7 -> 0.27124023 | M7: =(F7-G7)/G7 -> 0.75869472 | N7: =(G7-H7)/H7 -> 0.34158986 | O7: =(H7-I7)/I7 -> 0.3161486 | P7: -
B8: =IFERROR(D8/$D$14,"") -> 0.098368607 | C8: Singapore | D8: 2231 | E8: 1380 | F8: 1389 | G8: 1096 | H8: 597 | I8: 728 | K8: =(D8-E8)/E8 -> 0.61666667 | L8: =(E8-F8)/F8 -> -0.0064794816 | M8: =(F8-G8)/G8 -> 0.26733577 | N8: =(G8-H8)/H8 -> 0.8358459 | O8: =(H8-I8)/I8 -> -0.17994505 | P8: -
B9: =IFERROR(D9/$D$14,"") -> 0.089506173 | C9: Europe | D9: 2030 | E9: 1773 | F9: 1249 | G9: 1108 | H9: 762 | I9: 470 | K9: =(D9-E9)/E9 -> 0.14495206 | L9: =(E9-F9)/F9 -> 0.41953563 | M9: =(F9-G9)/G9 -> 0.12725632 | N9: =(G9-H9)/H9 -> 0.45406824 | O9: =(H9-I9)/I9 -> 0.6212766 | P9: -
B10: =IFERROR(D10/$D$14,"") -> 0.08117284 | C10: Taiwan | D10: 1841 | E10: 2369 | F10: 2091 | G10: 1187 | H10: 719 | I10: 1197 | K10: =(D10-E10)/E10 -> -0.22287885 | L10: =(E10-F10)/F10 -> 0.13295074 | M10: =(F10-G10)/G10 -> 0.76158382 | N10: =(G10-H10)/H10 -> 0.65090403 | O10: =(H10-I10)/I10 -> -0.39933166 | P10: -
B11: =IFERROR(D11/$D$14,"") -> 0 | C11: Taiwan | K11: =(D11-E11)/E11 -> #DIV/0! | L11: =(E11-F11)/F11 -> #DIV/0! | M11: =(F11-G11)/G11 -> #DIV/0! | N11: =(G11-H11)/H11 -> #DIV/0! | O11: =(H11-I11)/I11 -> #DIV/0!
B12: =IFERROR(D12/$D$14,"") -> 0 | C12: Taiwan | K12: =(D12-E12)/E12 -> #DIV/0! | L12: =(E12-F12)/F12 -> #DIV/0! | M12: =(F12-G12)/G12 -> #DIV/0! | N12: =(G12-H12)/H12 -> #DIV/0! | O12: =(H12-I12)/I12 -> #DIV/0!
B13: =IFERROR(D13/$D$14,"") -> 0.030643739 | C13: Other countries | D13: 695 | E13: 646 | F13: 572 | G13: 716 | H13: 313 | I13: 0 | K13: =(D13-E13)/E13 -> 0.075851393 | L13: =(E13-F13)/F13 -> 0.12937063 | M13: =(F13-G13)/G13 -> -0.20111732 | N13: =(G13-H13)/H13 -> 1.2875399 | O13: =(H13-I13)/I13 -> #DIV/0! | P13: -
B14: =SUM(B5:B12) -> 0.96935626 | C14: TOTAL | D14: =SUM(D5:D13) -> 22680 | E14: =SUM(E5:E13) -> 23601 | F14: =SUM(F5:F13) -> 16434 | G14: =SUM(G5:G13) -> 9763 | H14: =SUM(H5:H13) -> 6731 | I14: =SUM(I5:I13) -> 6266 | K14: =(D14-E14)/E14 -> -0.03902377 | L14: =(E14-F14)/F14 -> 0.43610807 | M14: =(F14-G14)/G14 -> 0.68329407 | N14: =(G14-H14)/H14 -> 0.45045313 | O14: =(H14-I14)/I14 -> 0.074210022 | P14: -
B16: ="Categories "&"("&OP!$J$20&")" -> Categories (2023)
D17: Nominal value | K17: YoY Growth
B18: Weight | C18: Category | D18: =OP!J20 -> 2023 | E18: =D18-1 -> 2022 | F18: =E18-1 -> 2021 | G18: =F18-1 -> 2020 | H18: =G18-1 -> 2019 | I18: =H18-1 -> 2018 | K18: =OP!J20 -> 2023 | L18: =K18-1 -> 2022 | M18: =L18-1 -> 2021 | N18: =M18-1 -> 2020 | O18: =N18-1 -> 2019 | P18: =O18-1 -> 2018
B19: =IFERROR(D19/$D$23,"") -> 0.28641975 | C19: Data Center | D19: 6496 | E19: 6043 | F19: 3694 | K19: =(D19-E19)/E19 -> 0.074962767 | L19: =(E19-F19)/F19 -> 0.63589605 | M19: =(F19-G19)/G19 -> #DIV/0! | N19: =(G19-H19)/H19 -> #DIV/0! | O19: =(H19-I19)/I19 -> #DIV/0! | P19: -
B20: =IFERROR(D20/$D$23,"") -> 0.20507055 | C20: Client | D20: 4651 | E20: 6201 | F20: 6887 | K20: =(D20-E20)/E20 -> -0.24995968 | L20: =(E20-F20)/F20 -> -0.099607957 | M20: =(F20-G20)/G20 -> #DIV/0! | N20: =(G20-H20)/H20 -> #DIV/0! | O20: =(H20-I20)/I20 -> #DIV/0! | P20: -
B21: =IFERROR(D21/$D$23,"") -> 0.27389771 | C21: Gaming | D21: 6212 | E21: 6805 | F21: 5607 | K21: =(D21-E21)/E21 -> -0.087141807 | L21: =(E21-F21)/F21 -> 0.21366149 | M21: =(F21-G21)/G21 -> #DIV/0! | N21: =(G21-H21)/H21 -> #DIV/0! | O21: =(H21-I21)/I21 -> #DIV/0! | P21: -
B22: =IFERROR(D22/$D$23,"") -> 0.23461199 | C22: Embedded | D22: 5321 | E22: 4552 | F22: 246 | K22: =(D22-E22)/E22 -> 0.16893673 | L22: =(E22-F22)/F22 -> 17.504065 | M22: =(F22-G22)/G22 -> #DIV/0! | N22: =(G22-H22)/H22 -> #DIV/0! | O22: =(H22-I22)/I22 -> #DIV/0! | P22: -
B23: =SUM(B19:B22) -> 1 | C23: TOTAL | D23: =SUM(D19:D22) -> 22680 | E23: =SUM(E19:E22) -> 23601 | F23: =SUM(F19:F22) -> 16434 | G23: =SUM(G19:G22) -> 0 | H23: =SUM(H19:H22) -> 0 | I23: =SUM(I19:I22) -> 0 | K23: =(D23-E23)/E23 -> -0.03902377 | L23: =(E23-F23)/F23 -> 0.43610807 | M23: =(F23-G23)/G23 -> #DIV/0! | N23: =(G23-H23)/H23 -> #DIV/0! | O23: =(H23-I23)/I23 -> #DIV/0! | P23: -
B25: Categories | D25: Description | I25: Graphs
B26: Data Center | D26: Data Center segment offers products for data center market to address the computational, visual data processing and AI workload acceleration needs. Data centers require high performance, energy efficient, scalable and adaptable compute engines to meet the demand driven by the growing amount of data. Products are Server CPU, Data Center GPUs, FPGAs and Adaptive SoCs, and DPUs.
B27: Client
B28: Gaming
B29: Embedded
B32: Industry | J32: Graphs (Industry Forecasts)
B33: Drivers | D33: Description
B36: Sales forecast
B37: Source | D37: Market Growth CAGR | G37: Period
B41: Average | D41: =AVERAGE(D38:F40) -> #DIV/0!
B42: Company's Strategy / Extra Notes

Sheet Acuerdo
A1: Invertir
A2: NO invertir
A3: Mantener sin elevar posición
A4: Mantener (y seguir comprando)
A5: Liquidar
A6: PENDIENTE

Sheet Peers
B1: Peer Logo | C1: Peer Name | D1: Description
B2: #VALUE! | C2: nvidia | D2: {=_FV(C2,"Description")} -> #VALUE!
A3: Intel Corporation is an American multinational corporation and technology company headquartered in Santa Clara, California, and incorporated in Delaware.[3] Intel is one of the world's largest semiconductor chip manufacturers by revenue[4][5] and ranked in the Fortune 500 list of the largest United States corporations by revenue for nearly a decade, from 2007 to 2016 fiscal years, until it was removed from the ranking in 2018.[6] In 2020, it was reinstated and ranked 45th, being the 7th-largest technology company in the ranking. | B3: #VALUE! | C3: intel | D3: {=_FV(C3,"Description")} -> #VALUE!
A4: Intel supplies microprocessors for most manufacturers of computer systems, and is one of the developers of the x86 series of instruction sets found in most personal computers (PCs). It also manufactures chipsets, network interface controllers, flash memory, graphics processing units (GPUs), field-programmable gate arrays (FPGAs), and other devices related to communications and computing. Intel has a strong presence in the high-performance general-purpose and gaming PC market with its Intel Core line of CPUs, whose high-end models are among the fastest consumer CPUs, as well as its Intel Arc series of GPUs, and sponsors the Intel Extreme Masters, a series of international esports tournaments. The Open Source Technology Center at Intel hosts PowerTOP and LatencyTOP, and supports other open source projects such as Wayland, Mesa, Threading Building Blocks (TBB), and Xen.[7] | D4: {=_FV(C4,"Description")} -> #VALUE!
A5: Intel (Integrated electronics) was founded on July 18, 1968, by semiconductor pioneers Gordon Moore (of Moore's law) and Robert Noyce, along with investor Arthur Rock, and is associated with the executive leadership and vision of Andrew Grove.[ | D5: {=_FV(C5,"Description")} -> #VALUE!
D6: {=_FV(C6,"Description")} -> #VALUE!
B8: In Millions USD | C8: =OP!E2 -> #VALUE! | D8: =C2 -> nvidia | E8: =C3 -> intel | F8: =C4 -> 0 | G8: =C5 -> 0 | H8: =C6 -> 0 | I8: AVERAGE | J8: Deviation from Average
B9: Company Info | I9: =IFERROR(AVERAGE(C9:H9),"") | L9: TRAFFIC
B10: Market Cap | C10: {=_FV(C8,"Market cap",TRUE)/1000000} -> 236990.8 | D10: {=_FV(D8,"Market cap",TRUE)/1000000} -> #VALUE! | E10: =4228*E45 -> 212457 | F10: {=_FV(F8,"Market cap",TRUE)/1000000} -> #VALUE! | G10: {=_FV(G8,"Market cap",TRUE)/1000000} -> #VALUE! | H10: {=_FV(H8,"Market cap",TRUE)/1000000} -> #VALUE! | I10: =IFERROR(AVERAGE(C10:H10),"") | J10: =SQRT((C10-I10)^2) -> #VALUE! | M10: Best Value
B11: Net Sales (current) | C11: =C56 -> 22680 | D11: =D56 -> 60922 | E11: =E56 -> 54228 | F11: =F56 -> 0 | G11: =G56 -> 0 | H11: =H56 -> 0 | I11: =IFERROR(AVERAGE(C11:H11),"") -> 22971.667 | J11: =SQRT((C11-I11)^2) -> 291.66667
B12: Profitability | I12: =IFERROR(AVERAGE(C12:H12),"") | M12: Important Value
B13: Sales Growth (ttm) | C13: =C56/C55-1 -> -0.03902377 | D13: =D56/D55-1 -> 1.2585453 | E13: =E56/E55-1 -> -0.13997526 | F13: =F56/F55-1 -> #DIV/0! | G13: =G56/G55-1 -> #DIV/0! | H13: =H56/H55-1 -> #DIV/0! | I13: =IFERROR(AVERAGE(C13:H13),"") | J13: =SQRT((C13-I13)^2) -> #VALUE!
B14: Sales Growth (36m) | C14: =C56/C54-1 -> 1.3230564 | D14: =D56/D54-1 -> #DIV/0! | E14: =E56/E54-1 -> -0.30358175 | F14: =F56/F54-1 -> #DIV/0! | G14: =G56/G54-1 -> #DIV/0! | H14: =H56/H54-1 -> #DIV/0! | I14: =IFERROR(AVERAGE(C14:H14),"") | J14: =SQRT((C14-I14)^2) -> #VALUE! | M14: Worst Value
B15: Operating Margin | C15: =C59/C56 -> 0.017680776 | D15: =D59/D56 -> 0 | E15: =E59/E56 -> 0.0017149812 | F15: =F59/F56 -> #DIV/0! | G15: =G59/G56 -> #DIV/0! | H15: =H59/H56 -> #DIV/0! | I15: =IFERROR(AVERAGE(C15:H15),"") | J15: =SQRT((C15-I15)^2) -> #VALUE!
B16: Net Income Margin | C16: =C62/C56 -> 0.037654321 | D16: =D62/D56 -> 0 | E16: =E62/E56 -> 0.030888102 | F16: =F62/F56 -> #DIV/0! | G16: =G62/G56 -> #DIV/0! | H16: =H62/H56 -> #DIV/0! | I16: =IFERROR(AVERAGE(C16:H16),"") | J16: =SQRT((C16-I16)^2) -> #VALUE!
B17: Return on Equity (RoE) | C17: =C62/C74 -> 0.015279468 | D17: =D62/D74 -> #DIV/0! | E17: =E62/E74 -> 0.015863245 | F17: =F62/F74 -> #DIV/0! | G17: =G62/G74 -> #DIV/0! | H17: =H62/H74 -> #DIV/0! | I17: =IFERROR(AVERAGE(C17:H17),"") | J17: =SQRT((C17-I17)^2) -> #VALUE!
B18: Return on Invested Capital (ROIC) | C18: =(1+C61/(C59+C60))*C59/(C73+C74-C65) -> 0.012515762 | D18: =(1+D61/(D59+D60))*D59/(D73+D74-D65) -> #DIV/0! | E18: =(1+E61/(E59+E60))*E59/(E73+E74-E65) -> 0.0014251372 | F18: =(1+F61/(F59+F60))*F59/(F73+F74-F65) -> #DIV/0! | G18: =(1+G61/(G59+G60))*G59/(G73+G74-G65) -> #DIV/0! | H18: =(1+H61/(H59+H60))*H59/(H73+H74-H65) -> #DIV/0! | I18: =IFERROR(AVERAGE(C18:H18),"") | J18: =SQRT((C18-I18)^2) -> #VALUE!
B19: Solvency | I19: =IFERROR(AVERAGE(C19:H19),"")
B20: Debt/Assets | C20: =C73/C70 -> 0.03317375 | D20: =D73/D70 -> #DIV/0! | E20: =E73/E70 -> 0.25716702 | F20: =F73/F70 -> #DIV/0! | G20: =G73/G70 -> #DIV/0! | H20: =H73/H70 -> #DIV/0! | I20: =IFERROR(AVERAGE(C20:H20),"") | J20: =SQRT((C20-I20)^2) -> #VALUE!
B21: Net Debt/EBITDA | C21: =(C73-C65)/C58 -> -0.43707748 | D21: =(D73-D65)/D58 -> #DIV/0! | E21: =(E73-E65)/E58 -> 5.3132242 | F21: =(F73-F65)/F58 -> #DIV/0! | G21: =(G73-G65)/G58 -> #DIV/0! | H21: =(H73-H65)/H58 -> #DIV/0! | I21: =IFERROR(AVERAGE(C21:H21),"") | J21: =SQRT((C21-I21)^2) -> #VALUE!
B22: Interest Coverage Ratio | C22: =-C58/C60 -> -38.848485 | D22: =-D58/D60 -> #DIV/0! | E22: =-E58/E60 -> -12.623211 | F22: =-F58/F60 -> #DIV/0! | G22: =-G58/G60 -> #DIV/0! | H22: =-H58/H60 -> #DIV/0! | I22: =IFERROR(AVERAGE(C22:H22),"") | J22: =SQRT((C22-I22)^2) -> #VALUE!
B23: Liquidity
B24: Current Ratio | C24: =C68/C72 -> 2.5068022 | D24: =D68/D72 -> #DIV/0! | E24: =E68/E72 -> 1.5424019 | F24: =F68/F72 -> #DIV/0! | G24: =G68/G72 -> #DIV/0! | H24: =H68/H72 -> #DIV/0! | I24: =IFERROR(AVERAGE(C24:H24),"") | J24: =SQRT((C24-I24)^2) -> #VALUE!
B25: Quick Ratio | C25: =(C65+C66)/C72 -> 1.3916878 | D25: =(D65+D66)/D72 -> #DIV/0! | E25: =(E65+E66)/E72 -> 0.37361423 | F25: =(F65+F66)/F72 -> #DIV/0! | G25: =(G65+G66)/G72 -> #DIV/0! | H25: =(H65+H66)/H72 -> #DIV/0! | I25: =IFERROR(AVERAGE(C25:H25),"") | J25: =SQRT((C25-I25)^2) -> #VALUE!
B26: Activity | I26: =IFERROR(AVERAGE(C26:H26),"")
B27: Inventory Turnover | C27: =C57/C67 -> 2.8085498 | D27: =D57/D67 -> #DIV/0! | E27: =E57/E67 -> 2.922351 | F27: =F57/F67 -> #DIV/0! | G27: =G57/G67 -> #DIV/0! | H27: =H57/H67 -> #DIV/0! | I27: =IFERROR(AVERAGE(C27:H27),"") | J27: =SQRT((C27-I27)^2) -> #VALUE!
B28: Acc. Receivable Turnover | C28: =C56/C66 -> 4.21875 | D28: =D56/D66 -> #DIV/0! | E28: =E56/E66 -> 15.940035 | F28: =F56/F66 -> #DIV/0! | G28: =G56/G66 -> #DIV/0! | H28: =H56/H66 -> #DIV/0! | I28: =IFERROR(AVERAGE(C28:H28),"") | J28: =SQRT((C28-I28)^2) -> #VALUE!
A29: Price/Sales | B29: Payables Turnover | C29: =C57/C71 -> 5.0537634 | D29: =D57/D71 -> #DIV/0! | E29: =E57/E71 -> 3.7907438 | F29: =F57/F71 -> #DIV/0! | G29: =G57/G71 -> #DIV/0! | H29: =H57/H71 -> #DIV/0! | I29: =IFERROR(AVERAGE(C29:H29),"") | J29: =SQRT((C29-I29)^2) -> #VALUE!
B30: Fixed Asset Turnover | C30: =C56/C69 -> 14.273128 | D30: =D56/D69 -> #DIV/0! | E30: =E56/E69 -> 0.56109346 | F30: =F56/F69 -> #DIV/0! | G30: =G56/G69 -> #DIV/0! | H30: =H56/H69 -> #DIV/0! | I30: =IFERROR(AVERAGE(C30:H30),"") | J30: =SQRT((C30-I30)^2) -> #VALUE!
B31: Total Asset Turnover | C31: =C56/C70 -> 0.33409442 | D31: =D56/D70 -> #DIV/0! | E31: =E56/E70 -> 0.28306851 | F31: =F56/F70 -> #DIV/0! | G31: =G56/G70 -> #DIV/0! | H31: =H56/H70 -> #DIV/0! | I31: =IFERROR(AVERAGE(C31:H31),"") | J31: =SQRT((C31-I31)^2) -> #VALUE!
B32: Valuation | I32: =IFERROR(AVERAGE(C32:H32),"")
B33: Price/Earnings | C33: =C10/C62 -> 277.50679 | D33: =D10/D62 -> #VALUE! | E33: =E10/E62 -> 126.84 | F33: =F10/F62 -> #VALUE! | G33: =G10/G62 -> #VALUE! | H33: =H10/H62 -> #VALUE! | I33: =IFERROR(AVERAGE(C33:H33),"") | J33: =SQRT((C33-I33)^2) -> #VALUE!
B34: Price/Sales | C34: =C10/C56 -> 10.44933 | D34: =D10/D56 -> #VALUE! | E34: =E10/E56 -> 3.9178469 | F34: =F10/F56 -> #VALUE! | G34: =G10/G56 -> #VALUE! | H34: =H10/H56 -> #VALUE! | I34: =IFERROR(AVERAGE(C34:H34),"") | J34: =SQRT((C34-I34)^2) -> #VALUE!
B35: Price/Book | C35: =C10/C74 -> 4.240156 | D35: =D10/D74 -> #VALUE! | E35: =E10/E74 -> 2.0120939 | F35: =F10/F74 -> #VALUE! | G35: =G10/G74 -> #VALUE! | H35: =H10/H74 -> #VALUE! | I35: =IFERROR(AVERAGE(C35:H35),"") | J35: =SQRT((C35-I35)^2) -> #VALUE!
B36: EV/Sales | C36: =(C73+C10-C65)/C56 -> 10.375212 | D36: =(D73+D10-D65)/D56 -> #VALUE! | E36: =(E73+E10-E65)/E56 -> 4.6958029 | F36: =(F73+F10-F65)/F56 -> #VALUE! | G36: =(G73+G10-G65)/G56 -> #VALUE! | H36: =(H73+H10-H65)/H56 -> #VALUE! | I36: =IFERROR(AVERAGE(C36:H36),"") | J36: =SQRT((C36-I36)^2) -> #VALUE!
B37: EV/EBITDA | C37: =(C73+C10-C65)/C58 -> 61.182995 | D37: =(D73+D10-D65)/D58 -> #VALUE! | E37: =(E73+E10-E65)/E58 -> 32.071033 | F37: =(F73+F10-F65)/F58 -> #VALUE! | G37: =(G73+G10-G65)/G58 -> #VALUE! | H37: =(H73+H10-H65)/H58 -> #VALUE! | I37: =IFERROR(AVERAGE(C37:H37),"") | J37: =SQRT((C37-I37)^2) -> #VALUE!
B38: Stock Info | I38: =IFERROR(AVERAGE(C38:H38),"")
B39: Float | C39: =1.6/1.62 -> 0.98765432 | E39: =4.22/4.26 -> 0.99061033 | I39: =IFERROR(AVERAGE(C39:H39),"") -> 0.98913232 | J39: =SQRT((C39-I39)^2) -> 0.0014780038
B40: b (Yahoo) | C40: 1.63 | E40: 1.01 | I40: =IFERROR(AVERAGE(C40:H40),"") -> 1.32 | J40: =SQRT((C40-I40)^2) -> 0.31
B41: Dividend Yield (yahoo finance) | C41: =OP!M32 -> 0 | E41: 0.0211 | I41: =IFERROR(AVERAGE(C41:H41),"") -> 0.01055 | J41: =SQRT((C41-I41)^2) -> 0.01055
B42: Stock Performance
B43: 1y | C43: 0.6745 | E43: 0.1531 | I43: =IFERROR(AVERAGE(C43:H43),"") -> 0.4138 | J43: =SQRT((C43-I43)^2) -> 0.2607
B44: 3y | I44: =IFERROR(AVERAGE(C44:H44),"") | J44: =SQRT((C44-I44)^2) -> #VALUE!
B45: Current Price | C45: {=_FV(C8,"Price")} -> 146.64 | D45: {=_FV(D8,"Price")} -> #VALUE! | E45: 50.25 | F45: {=_FV(F8,"Price")} -> #VALUE! | G45: {=_FV(G8,"Price")} -> #VALUE! | H45: {=_FV(H8,"Price")} -> #VALUE! | I45: =IFERROR(AVERAGE(C45:H45),"") | J45: =SQRT((C45-I45)^2) -> #VALUE!
B46: Average Target Price | I46: =IFERROR(AVERAGE(C46:H46),"") | J46: =SQRT((C46-I46)^2) -> #VALUE!
B47: Upside/Downside | C47: =C46/C45-1 -> -1 | D47: =D46/D45-1 -> #VALUE! | E47: =E46/E45-1 -> -1 | F47: =F46/F45-1 -> #VALUE! | G47: =G46/G45-1 -> #VALUE! | H47: =H46/H45-1 -> #VALUE! | I47: =IFERROR(AVERAGE(C47:H47),"") | J47: =SQRT((C47-I47)^2) -> #VALUE!
B48: Extra | I48: =IFERROR(AVERAGE(C48:H48),"")
B49: 3y Operating Cash Flow | C49: =(Inputs!B59-Inputs!E59)/Inputs!E59 -> 0.55648926 | I49: =IFERROR(AVERAGE(C49:H49),"") -> 0.55648926 | J49: =SQRT((C49-I49)^2) -> 0
B50: R&D/Net Sales | C50: =C63/C11 -> 0 | D50: =D63/D11 -> 0 | E50: =E63/E11 -> 0 | F50: =F63/F11 -> #DIV/0! | G50: =G63/G11 -> #DIV/0! | H50: =H63/H11 -> #DIV/0! | I50: =IFERROR(AVERAGE(C50:H50),"") | J50: =SQRT((C50-I50)^2) -> #VALUE!
B52: Financial Data | C52: =OP!E2 -> #VALUE! | D52: =D8 -> nvidia | E52: =E8 -> intel | F52: =F8 -> 0 | G52: =G8 -> 0 | H52: =H8 -> 0
B53: IS
B54: Net Sales (36m ago) | C54: ='Fin. Data'!E5 -> 9763 | E54: 77867
B55: Net Sales (12m ago) | C55: ='Fin. Data'!C5 -> 23601 | D55: 26974 | E55: 63054
B56: Net Sales (current) | C56: ='Fin. Data'!B5 -> 22680 | D56: 60922 | E56: 54228
B57: COGS | C57: ='Fin. Data'!B5-'Fin. Data'!B7 -> 12220 | E57: 32517
B58: EBITDA | C58: ='Fin. Data'!B19 -> 3846 | E58: =7847+E59 -> 7940
B59: Operating Income | C59: ='Fin. Data'!B11 -> 401 | E59: 93
B60: Net Financial Cost | C60: ='Fin. Data'!B14 -> 99 | E60: 629
B61: Taxes | C61: ='Fin. Data'!B21 -> 346 | E61: 913
B62: Net Income | C62: ='Fin. Data'!B23 -> 854 | E62: 1675
B63: R&D
B64: BS
B65: Cash & Eq. | C65: ='Fin. Data'!B39 -> 3933 | E65: 7079
B66: Acc. Receivables | C66: ='Fin. Data'!B40 -> 5376 | E66: 3402
B67: Inventory | C67: ='Fin. Data'!B41 -> 4351 | E67: 11127
B68: Current Assets | C68: =Inputs!B27 -> 16768 | E68: 43269
B69: Fixed Assets | C69: ='Fin. Data'!B42 -> 1589 | E69: 96647
B70: Total Assets | C70: ='Fin. Data'!B44 -> 67885 | E70: 191572
B71: Acc. Payable | C71: =Inputs!B43 -> 2418 | E71: 8578
B72: Current Liabilities | C72: =Inputs!B42 -> 6689 | E72: 28053
B73: Total Debt | C73: ='Fin. Data'!B58 -> 2252 | E73: =46978+2288 -> 49266
B74: Total Equity | C74: ='Fin. Data'!B64 -> 55892 | E74: 105590

Sheet SARD
F1: Variables | K1: Rankings | P1: Difference | U1: Results | Y1: Additional Information | AD1: =B3 -> 0 | AE1: Selected Peers | AJ1: Price Multiples (TTM) | AM1: Enterprise Value Multiples (TTM)
B2: Ticker | C2: Company Name | D2: TRBC Industry | E2: Country | F2: ROE | G2: DEBT/EBIT | H2: Market Cap | I2: EPS Growth (2019-2023) (Refinitiv Smart Estimate) | J2: EBIT Margin | K2: ROE | L2: DEBT/EBIT | M2: Market Cap | N2: EPS Growth | O2: EBIT Margin | P2: ROE | Q2: DEBT/EBIT | R2: Market Cap | S2: EPS Growth | T2: EBIT Margin | U2: SARD Result | V2: SARD Peers | W2: SARD Peers adjusted Rank | Y2: Suitability | Z2: Relevant Information Missing | AA2: Author's Override | AB2: Observations | AE2: SARD Peers adjusted Rank | AF2: SARD Result | AG2: Ticker | AH2: Company Name | AI2: Country | AJ2: P / E | AK2: P / B | AL2: Price / Sales | AM2: EV / Sales | AN2: EV / EBITDA
A3: Benchmark | K3: =IFERROR(_xlfn.RANK.EQ(F3,F$3:F$61),"N/A") -> N/A | L3: =IFERROR(_xlfn.RANK.EQ(G3,G$3:G$61),"N/A") -> N/A | M3: =IFERROR(_xlfn.RANK.EQ(H3,H$3:H$61),"N/A") -> N/A | N3: =IFERROR(_xlfn.RANK.EQ(I3,I$3:I$61),"N/A") -> N/A | O3: =IFERROR(_xlfn.RANK.EQ(J3,J$3:J$61),"N/A") -> N/A | P3: - | Q3: - | R3: - | S3: - | T3: - | U3: - | V3: - | W3: - | Y3: =IF(OR(Z3="Y",AA3="Y"),"Not suitable","") -> Not suitable | Z3: =IF(N3="N/A","Y","") -> Y | AE3: {=_xlfn._xlws.SORT(_xlfn._xlws.FILTER(SARD!W3:W61,SARD!W3:W61<=SMALL(W3:W61,6)),,1)} -> #NUM! | AF3: =_xlfn.XLOOKUP($AE3,$W:$W,U:U,,0) -> #NUM! | AG3: =_xlfn.XLOOKUP($AE3,$W:$W,B:B,,0) -> #NUM! | AH3: =_xlfn.XLOOKUP($AE3,$W:$W,C:C,,0) -> #NUM! | AI3: =_xlfn.XLOOKUP($AE3,$W:$W,E:E,,0) -> #NUM!
A4: Comparison | K4: =IFERROR(_xlfn.RANK.EQ(F4,F$3:F$61),"N/A") -> N/A | L4: =IFERROR(_xlfn.RANK.EQ(G4,G$3:G$61),"N/A") -> N/A | M4: =IFERROR(_xlfn.RANK.EQ(H4,H$3:H$61),"N/A") -> N/A | N4: =IFERROR(_xlfn.RANK.EQ(I4,I$3:I$61),"N/A") -> N/A | O4: =IFERROR(_xlfn.RANK.EQ(J4,J$3:J$61),"N/A") -> N/A | P4: =IFERROR(ABS(K$3-K4),"N/A") -> N/A | Q4: =IFERROR(ABS(L$3-L4),"N/A") -> N/A | R4: =IFERROR(ABS(M$3-M4),"N/A") -> N/A | S4: =IFERROR(ABS(N$3-N4),"N/A") -> N/A | T4: =IFERROR(ABS(O$3-O4),"N/A") -> N/A | U4: =SUM(P4:T4) -> 0 | V4: =_xlfn.RANK.EQ(U4,$U$4:$U$61,1) -> 1 | W4: =IF(Y4="Not suitable","-",V4) -> - | Y4: =IF(OR(Z4="Y",AA4="Y"),"Not suitable","") -> Not suitable | Z4: =IF(N4="N/A","Y","") -> Y | AF4: =_xlfn.XLOOKUP($AE4,$W:$W,U:U,,0) -> Results | AG4: =_xlfn.XLOOKUP($AE4,$W:$W,B:B,,0) -> 0 | AH4: =_xlfn.XLOOKUP($AE4,$W:$W,C:C,,0) -> 0 | AI4: =_xlfn.XLOOKUP($AE4,$W:$W,E:E,,0) -> 0
K5: =IFERROR(_xlfn.RANK.EQ(F5,F$3:F$61),"N/A") -> N/A | L5: =IFERROR(_xlfn.RANK.EQ(G5,G$3:G$61),"N/A") -> N/A | M5: =IFERROR(_xlfn.RANK.EQ(H5,H$3:H$61),"N/A") -> N/A | N5: =IFERROR(_xlfn.RANK.EQ(I5,I$3:I$61),"N/A") -> N/A | O5: =IFERROR(_xlfn.RANK.EQ(J5,J$3:J$61),"N/A") -> N/A | P5: =IFERROR(ABS(K$3-K5),"N/A") -> N/A | Q5: =IFERROR(ABS(L$3-L5),"N/A") -> N/A | R5: =IFERROR(ABS(M$3-M5),"N/A") -> N/A | S5: =IFERROR(ABS(N$3-N5),"N/A") -> N/A | T5: =IFERROR(ABS(O$3-O5),"N/A") -> N/A | U5: =SUM(P5:T5) -> 0 | V5: =_xlfn.RANK.EQ(U5,$U$4:$U$61,1) -> 1 | W5: =IF(Y5="Not suitable","-",V5) -> - | Y5: =IF(OR(Z5="Y",AA5="Y"),"Not suitable","") -> Not suitable | Z5: =IF(N5="N/A","Y","") -> Y | AF5: =_xlfn.XLOOKUP($AE5,$W:$W,U:U,,0) -> Results | AG5: =_xlfn.XLOOKUP($AE5,$W:$W,B:B,,0) -> 0 | AH5: =_xlfn.XLOOKUP($AE5,$W:$W,C:C,,0) -> 0 | AI5: =_xlfn.XLOOKUP($AE5,$W:$W,E:E,,0) -> 0
K6: =IFERROR(_xlfn.RANK.EQ(F6,F$3:F$61),"N/A") -> N/A | L6: =IFERROR(_xlfn.RANK.EQ(G6,G$3:G$61),"N/A") -> N/A | M6: =IFERROR(_xlfn.RANK.EQ(H6,H$3:H$61),"N/A") -> N/A | N6: =IFERROR(_xlfn.RANK.EQ(I6,I$3:I$61),"N/A") -> N/A | O6: =IFERROR(_xlfn.RANK.EQ(J6,J$3:J$61),"N/A") -> N/A | P6: =IFERROR(ABS(K$3-K6),"N/A") -> N/A | Q6: =IFERROR(ABS(L$3-L6),"N/A") -> N/A | R6: =IFERROR(ABS(M$3-M6),"N/A") -> N/A | S6: =IFERROR(ABS(N$3-N6),"N/A") -> N/A | T6: =IFERROR(ABS(O$3-O6),"N/A") -> N/A | U6: =SUM(P6:T6) -> 0 | V6: =_xlfn.RANK.EQ(U6,$U$4:$U$61,1) -> 1 | W6: =IF(Y6="Not suitable","-",V6) -> - | Y6: =IF(OR(Z6="Y",AA6="Y"),"Not suitable","") -> Not suitable | Z6: =IF(N6="N/A","Y","") -> Y | AF6: =_xlfn.XLOOKUP($AE6,$W:$W,U:U,,0) -> Results | AG6: =_xlfn.XLOOKUP($AE6,$W:$W,B:B,,0) -> 0 | AH6: =_xlfn.XLOOKUP($AE6,$W:$W,C:C,,0) -> 0 | AI6: =_xlfn.XLOOKUP($AE6,$W:$W,E:E,,0) -> 0
K7: =IFERROR(_xlfn.RANK.EQ(F7,F$3:F$61),"N/A") -> N/A | L7: =IFERROR(_xlfn.RANK.EQ(G7,G$3:G$61),"N/A") -> N/A | M7: =IFERROR(_xlfn.RANK.EQ(H7,H$3:H$61),"N/A") -> N/A | N7: =IFERROR(_xlfn.RANK.EQ(I7,I$3:I$61),"N/A") -> N/A | O7: =IFERROR(_xlfn.RANK.EQ(J7,J$3:J$61),"N/A") -> N/A | P7: =IFERROR(ABS(K$3-K7),"N/A") -> N/A | Q7: =IFERROR(ABS(L$3-L7),"N/A") -> N/A | R7: =IFERROR(ABS(M$3-M7),"N/A") -> N/A | S7: =IFERROR(ABS(N$3-N7),"N/A") -> N/A | T7: =IFERROR(ABS(O$3-O7),"N/A") -> N/A | U7: =SUM(P7:T7) -> 0 | V7: =_xlfn.RANK.EQ(U7,$U$4:$U$61,1) -> 1 | W7: =IF(Y7="Not suitable","-",V7) -> - | Y7: =IF(OR(Z7="Y",AA7="Y"),"Not suitable","") -> Not suitable | Z7: =IF(N7="N/A","Y","") -> Y | AF7: =_xlfn.XLOOKUP($AE7,$W:$W,U:U,,0) -> Results | AG7: =_xlfn.XLOOKUP($AE7,$W:$W,B:B,,0) -> 0 | AH7: =_xlfn.XLOOKUP($AE7,$W:$W,C:C,,0) -> 0 | AI7: =_xlfn.XLOOKUP($AE7,$W:$W,E:E,,0) -> 0
K8: =IFERROR(_xlfn.RANK.EQ(F8,F$3:F$61),"N/A") -> N/A | L8: =IFERROR(_xlfn.RANK.EQ(G8,G$3:G$61),"N/A") -> N/A | M8: =IFERROR(_xlfn.RANK.EQ(H8,H$3:H$61),"N/A") -> N/A | N8: =IFERROR(_xlfn.RANK.EQ(I8,I$3:I$61),"N/A") -> N/A | O8: =IFERROR(_xlfn.RANK.EQ(J8,J$3:J$61),"N/A") -> N/A | P8: =IFERROR(ABS(K$3-K8),"N/A") -> N/A | Q8: =IFERROR(ABS(L$3-L8),"N/A") -> N/A | R8: =IFERROR(ABS(M$3-M8),"N/A") -> N/A | S8: =IFERROR(ABS(N$3-N8),"N/A") -> N/A | T8: =IFERROR(ABS(O$3-O8),"N/A") -> N/A | U8: =SUM(P8:T8) -> 0 | V8: =_xlfn.RANK.EQ(U8,$U$4:$U$61,1) -> 1 | W8: =IF(Y8="Not suitable","-",V8) -> - | Y8: =IF(OR(Z8="Y",AA8="Y"),"Not suitable","") -> Not suitable | Z8: =IF(N8="N/A","Y","") -> Y | AF8: =_xlfn.XLOOKUP($AE8,$W:$W,U:U,,0) -> Results | AG8: =_xlfn.XLOOKUP($AE8,$W:$W,B:B,,0) -> 0 | AH8: =_xlfn.XLOOKUP($AE8,$W:$W,C:C,,0) -> 0 | AI8: =_xlfn.XLOOKUP($AE8,$W:$W,E:E,,0) -> 0
K9: =IFERROR(_xlfn.RANK.EQ(F9,F$3:F$61),"N/A") -> N/A | L9: =IFERROR(_xlfn.RANK.EQ(G9,G$3:G$61),"N/A") -> N/A | M9: =IFERROR(_xlfn.RANK.EQ(H9,H$3:H$61),"N/A") -> N/A | N9: =IFERROR(_xlfn.RANK.EQ(I9,I$3:I$61),"N/A") -> N/A | O9: =IFERROR(_xlfn.RANK.EQ(J9,J$3:J$61),"N/A") -> N/A | P9: =IFERROR(ABS(K$3-K9),"N/A") -> N/A | Q9: =IFERROR(ABS(L$3-L9),"N/A") -> N/A | R9: =IFERROR(ABS(M$3-M9),"N/A") -> N/A | S9: =IFERROR(ABS(N$3-N9),"N/A") -> N/A | T9: =IFERROR(ABS(O$3-O9),"N/A") -> N/A | U9: =SUM(P9:T9) -> 0 | V9: =_xlfn.RANK.EQ(U9,$U$4:$U$61,1) -> 1 | W9: =IF(Y9="Not suitable","-",V9) -> - | Y9: =IF(OR(Z9="Y",AA9="Y"),"Not suitable","") -> Not suitable | Z9: =IF(N9="N/A","Y","") -> Y | AE9: Median | AJ9: =MEDIAN(AJ3:AJ8) -> #NUM! | AK9: =MEDIAN(AK3:AK8) -> #NUM! | AL9: =MEDIAN(AL3:AL8) -> #NUM! | AM9: =MEDIAN(AM3:AM8) -> #NUM! | AN9: =MEDIAN(AN3:AN8) -> #NUM!
K10: =IFERROR(_xlfn.RANK.EQ(F10,F$3:F$61),"N/A") -> N/A | L10: =IFERROR(_xlfn.RANK.EQ(G10,G$3:G$61),"N/A") -> N/A | M10: =IFERROR(_xlfn.RANK.EQ(H10,H$3:H$61),"N/A") -> N/A | N10: =IFERROR(_xlfn.RANK.EQ(I10,I$3:I$61),"N/A") -> N/A | O10: =IFERROR(_xlfn.RANK.EQ(J10,J$3:J$61),"N/A") -> N/A | P10: =IFERROR(ABS(K$3-K10),"N/A") -> N/A | Q10: =IFERROR(ABS(L$3-L10),"N/A") -> N/A | R10: =IFERROR(ABS(M$3-M10),"N/A") -> N/A | S10: =IFERROR(ABS(N$3-N10),"N/A") -> N/A | T10: =IFERROR(ABS(O$3-O10),"N/A") -> N/A | U10: =SUM(P10:T10) -> 0 | V10: =_xlfn.RANK.EQ(U10,$U$4:$U$61,1) -> 1 | W10: =IF(Y10="Not suitable","-",V10) -> - | Y10: =IF(OR(Z10="Y",AA10="Y"),"Not suitable","") -> Not suitable | Z10: =IF(N10="N/A","Y","") -> Y | AE10: Benchmark Data | AJ10: Price / Share
K11: =IFERROR(_xlfn.RANK.EQ(F11,F$3:F$61),"N/A") -> N/A | L11: =IFERROR(_xlfn.RANK.EQ(G11,G$3:G$61),"N/A") -> N/A | M11: =IFERROR(_xlfn.RANK.EQ(H11,H$3:H$61),"N/A") -> N/A | N11: =IFERROR(_xlfn.RANK.EQ(I11,I$3:I$61),"N/A") -> N/A | O11: =IFERROR(_xlfn.RANK.EQ(J11,J$3:J$61),"N/A") -> N/A | P11: =IFERROR(ABS(K$3-K11),"N/A") -> N/A | Q11: =IFERROR(ABS(L$3-L11),"N/A") -> N/A | R11: =IFERROR(ABS(M$3-M11),"N/A") -> N/A | S11: =IFERROR(ABS(N$3-N11),"N/A") -> N/A | T11: =IFERROR(ABS(O$3-O11),"N/A") -> N/A | U11: =SUM(P11:T11) -> 0 | V11: =_xlfn.RANK.EQ(U11,$U$4:$U$61,1) -> 1 | W11: =IF(Y11="Not suitable","-",V11) -> - | Y11: =IF(OR(Z11="Y",AA11="Y"),"Not suitable","") -> Not suitable | Z11: =IF(N11="N/A","Y","") -> Y | AE11: Benchmark | AF11: Multiplier | AG11: # Shares | AH11: -Debt + Cash | AJ11: P / E | AK11: P / B | AL11: Price / Sales | AM11: EV / Sales | AN11: EV / EBITDA
K12: =IFERROR(_xlfn.RANK.EQ(F12,F$3:F$61),"N/A") -> N/A | L12: =IFERROR(_xlfn.RANK.EQ(G12,G$3:G$61),"N/A") -> N/A | M12: =IFERROR(_xlfn.RANK.EQ(H12,H$3:H$61),"N/A") -> N/A | N12: =IFERROR(_xlfn.RANK.EQ(I12,I$3:I$61),"N/A") -> N/A | O12: =IFERROR(_xlfn.RANK.EQ(J12,J$3:J$61),"N/A") -> N/A | P12: =IFERROR(ABS(K$3-K12),"N/A") -> N/A | Q12: =IFERROR(ABS(L$3-L12),"N/A") -> N/A | R12: =IFERROR(ABS(M$3-M12),"N/A") -> N/A | S12: =IFERROR(ABS(N$3-N12),"N/A") -> N/A | T12: =IFERROR(ABS(O$3-O12),"N/A") -> N/A | U12: =SUM(P12:T12) -> 0 | V12: =_xlfn.RANK.EQ(U12,$U$4:$U$61,1) -> 1 | W12: =IF(Y12="Not suitable","-",V12) -> - | Y12: =IF(OR(Z12="Y",AA12="Y"),"Not suitable","") -> Not suitable | Z12: =IF(N12="N/A","Y","") -> Y | AE12: =C3 -> 0 | AF12: 1000000 | AG12: =OP!C21 -> 1616140000 | AH12: =-'Fin. Data'!B58*SARD!AF12+'Fin. Data'!B39*SARD!AF12 -> 1681000000 | AJ12: =AJ9*'Fin. Data'!B23*AF$12/AG$12 -> #NUM! | AK12: =AK9*'Fin. Data'!B64*AF$12/AG$12 -> #NUM! | AL12: =AL9*'Fin. Data'!B5*AF$12/AG$12 -> #NUM! | AM12: =(AM9*'Fin. Data'!B5*$AF12+$AH12)/$AG12 -> #NUM! | AN12: =(AN9*'Fin. Data'!B19*$AF12+$AH12)/$AG12 -> #NUM!
K13: =IFERROR(_xlfn.RANK.EQ(F13,F$3:F$61),"N/A") -> N/A | L13: =IFERROR(_xlfn.RANK.EQ(G13,G$3:G$61),"N/A") -> N/A | M13: =IFERROR(_xlfn.RANK.EQ(H13,H$3:H$61),"N/A") -> N/A | N13: =IFERROR(_xlfn.RANK.EQ(I13,I$3:I$61),"N/A") -> N/A | O13: =IFERROR(_xlfn.RANK.EQ(J13,J$3:J$61),"N/A") -> N/A | P13: =IFERROR(ABS(K$3-K13),"N/A") -> N/A | Q13: =IFERROR(ABS(L$3-L13),"N/A") -> N/A | R13: =IFERROR(ABS(M$3-M13),"N/A") -> N/A | S13: =IFERROR(ABS(N$3-N13),"N/A") -> N/A | T13: =IFERROR(ABS(O$3-O13),"N/A") -> N/A | U13: =SUM(P13:T13) -> 0 | V13: =_xlfn.RANK.EQ(U13,$U$4:$U$61,1) -> 1 | W13: =IF(Y13="Not suitable","-",V13) -> - | Y13: =IF(OR(Z13="Y",AA13="Y"),"Not suitable","") -> Not suitable | Z13: =IF(N13="N/A","Y","") -> Y | AE13: By Consolidated Average | AJ13: =AVERAGE(AJ12:AL12) -> #NUM! | AM13: =AVERAGE(AM12:AN12) -> #NUM!
K14: =IFERROR(_xlfn.RANK.EQ(F14,F$3:F$61),"N/A") -> N/A | L14: =IFERROR(_xlfn.RANK.EQ(G14,G$3:G$61),"N/A") -> N/A | M14: =IFERROR(_xlfn.RANK.EQ(H14,H$3:H$61),"N/A") -> N/A | N14: =IFERROR(_xlfn.RANK.EQ(I14,I$3:I$61),"N/A") -> N/A | O14: =IFERROR(_xlfn.RANK.EQ(J14,J$3:J$61),"N/A") -> N/A | P14: =IFERROR(ABS(K$3-K14),"N/A") -> N/A | Q14: =IFERROR(ABS(L$3-L14),"N/A") -> N/A | R14: =IFERROR(ABS(M$3-M14),"N/A") -> N/A | S14: =IFERROR(ABS(N$3-N14),"N/A") -> N/A | T14: =IFERROR(ABS(O$3-O14),"N/A") -> N/A | U14: =SUM(P14:T14) -> 0 | V14: =_xlfn.RANK.EQ(U14,$U$4:$U$61,1) -> 1 | W14: =IF(Y14="Not suitable","-",V14) -> - | Y14: =IF(OR(Z14="Y",AA14="Y"),"Not suitable","") -> Not suitable | Z14: =IF(N14="N/A","Y","") -> Y | AE14: Upside | AJ14: =AJ13/OP!C20-1 -> #NUM! | AM14: =AM13/OP!C20-1 -> #NUM!
K15: =IFERROR(_xlfn.RANK.EQ(F15,F$3:F$61),"N/A") -> N/A | L15: =IFERROR(_xlfn.RANK.EQ(G15,G$3:G$61),"N/A") -> N/A | M15: =IFERROR(_xlfn.RANK.EQ(H15,H$3:H$61),"N/A") -> N/A | N15: =IFERROR(_xlfn.RANK.EQ(I15,I$3:I$61),"N/A") -> N/A | O15: =IFERROR(_xlfn.RANK.EQ(J15,J$3:J$61),"N/A") -> N/A | P15: =IFERROR(ABS(K$3-K15),"N/A") -> N/A | Q15: =IFERROR(ABS(L$3-L15),"N/A") -> N/A | R15: =IFERROR(ABS(M$3-M15),"N/A") -> N/A | S15: =IFERROR(ABS(N$3-N15),"N/A") -> N/A | T15: =IFERROR(ABS(O$3-O15),"N/A") -> N/A | U15: =SUM(P15:T15) -> 0 | V15: =_xlfn.RANK.EQ(U15,$U$4:$U$61,1) -> 1 | W15: =IF(Y15="Not suitable","-",V15) -> - | Y15: =IF(OR(Z15="Y",AA15="Y"),"Not suitable","") -> Not suitable | Z15: =IF(N15="N/A","Y","") -> Y
K16: =IFERROR(_xlfn.RANK.EQ(F16,F$3:F$61),"N/A") -> N/A | L16: =IFERROR(_xlfn.RANK.EQ(G16,G$3:G$61),"N/A") -> N/A | M16: =IFERROR(_xlfn.RANK.EQ(H16,H$3:H$61),"N/A") -> N/A | N16: =IFERROR(_xlfn.RANK.EQ(I16,I$3:I$61),"N/A") -> N/A | O16: =IFERROR(_xlfn.RANK.EQ(J16,J$3:J$61),"N/A") -> N/A | P16: =IFERROR(ABS(K$3-K16),"N/A") -> N/A | Q16: =IFERROR(ABS(L$3-L16),"N/A") -> N/A | R16: =IFERROR(ABS(M$3-M16),"N/A") -> N/A | S16: =IFERROR(ABS(N$3-N16),"N/A") -> N/A | T16: =IFERROR(ABS(O$3-O16),"N/A") -> N/A | U16: =SUM(P16:T16) -> 0 | V16: =_xlfn.RANK.EQ(U16,$U$4:$U$61,1) -> 1 | W16: =IF(Y16="Not suitable","-",V16) -> - | Y16: =IF(OR(Z16="Y",AA16="Y"),"Not suitable","") -> Not suitable | Z16: =IF(N16="N/A","Y","") -> Y
K17: =IFERROR(_xlfn.RANK.EQ(F17,F$3:F$61),"N/A") -> N/A | L17: =IFERROR(_xlfn.RANK.EQ(G17,G$3:G$61),"N/A") -> N/A | M17: =IFERROR(_xlfn.RANK.EQ(H17,H$3:H$61),"N/A") -> N/A | N17: =IFERROR(_xlfn.RANK.EQ(I17,I$3:I$61),"N/A") -> N/A | O17: =IFERROR(_xlfn.RANK.EQ(J17,J$3:J$61),"N/A") -> N/A | P17: =IFERROR(ABS(K$3-K17),"N/A") -> N/A | Q17: =IFERROR(ABS(L$3-L17),"N/A") -> N/A | R17: =IFERROR(ABS(M$3-M17),"N/A") -> N/A | S17: =IFERROR(ABS(N$3-N17),"N/A") -> N/A | T17: =IFERROR(ABS(O$3-O17),"N/A") -> N/A | U17: =SUM(P17:T17) -> 0 | V17: =_xlfn.RANK.EQ(U17,$U$4:$U$61,1) -> 1 | W17: =IF(Y17="Not suitable","-",V17) -> - | Y17: =IF(OR(Z17="Y",AA17="Y"),"Not suitable","") -> Not suitable | Z17: =IF(N17="N/A","Y","") -> Y
K18: =IFERROR(_xlfn.RANK.EQ(F18,F$3:F$61),"N/A") -> N/A | L18: =IFERROR(_xlfn.RANK.EQ(G18,G$3:G$61),"N/A") -> N/A | M18: =IFERROR(_xlfn.RANK.EQ(H18,H$3:H$61),"N/A") -> N/A | N18: =IFERROR(_xlfn.RANK.EQ(I18,I$3:I$61),"N/A") -> N/A | O18: =IFERROR(_xlfn.RANK.EQ(J18,J$3:J$61),"N/A") -> N/A | P18: =IFERROR(ABS(K$3-K18),"N/A") -> N/A | Q18: =IFERROR(ABS(L$3-L18),"N/A") -> N/A | R18: =IFERROR(ABS(M$3-M18),"N/A") -> N/A | S18: =IFERROR(ABS(N$3-N18),"N/A") -> N/A | T18: =IFERROR(ABS(O$3-O18),"N/A") -> N/A | U18: =SUM(P18:T18) -> 0 | V18: =_xlfn.RANK.EQ(U18,$U$4:$U$61,1) -> 1 | W18: =IF(Y18="Not suitable","-",V18) -> - | Y18: =IF(OR(Z18="Y",AA18="Y"),"Not suitable","") -> Not suitable | Z18: =IF(N18="N/A","Y","") -> Y
K19: =IFERROR(_xlfn.RANK.EQ(F19,F$3:F$61),"N/A") -> N/A | L19: =IFERROR(_xlfn.RANK.EQ(G19,G$3:G$61),"N/A") -> N/A | M19: =IFERROR(_xlfn.RANK.EQ(H19,H$3:H$61),"N/A") -> N/A | N19: =IFERROR(_xlfn.RANK.EQ(I19,I$3:I$61),"N/A") -> N/A | O19: =IFERROR(_xlfn.RANK.EQ(J19,J$3:J$61),"N/A") -> N/A | P19: =IFERROR(ABS(K$3-K19),"N/A") -> N/A | Q19: =IFERROR(ABS(L$3-L19),"N/A") -> N/A | R19: =IFERROR(ABS(M$3-M19),"N/A") -> N/A | S19: =IFERROR(ABS(N$3-N19),"N/A") -> N/A | T19: =IFERROR(ABS(O$3-O19),"N/A") -> N/A | U19: =SUM(P19:T19) -> 0 | V19: =_xlfn.RANK.EQ(U19,$U$4:$U$61,1) -> 1 | W19: =IF(Y19="Not suitable","-",V19) -> - | Y19: =IF(OR(Z19="Y",AA19="Y"),"Not suitable","") -> Not suitable | Z19: =IF(N19="N/A","Y","") -> Y
K20: =IFERROR(_xlfn.RANK.EQ(F20,F$3:F$61),"N/A") -> N/A | L20: =IFERROR(_xlfn.RANK.EQ(G20,G$3:G$61),"N/A") -> N/A | M20: =IFERROR(_xlfn.RANK.EQ(H20,H$3:H$61),"N/A") -> N/A | N20: =IFERROR(_xlfn.RANK.EQ(I20,I$3:I$61),"N/A") -> N/A | O20: =IFERROR(_xlfn.RANK.EQ(J20,J$3:J$61),"N/A") -> N/A | P20: =IFERROR(ABS(K$3-K20),"N/A") -> N/A | Q20: =IFERROR(ABS(L$3-L20),"N/A") -> N/A | R20: =IFERROR(ABS(M$3-M20),"N/A") -> N/A | S20: =IFERROR(ABS(N$3-N20),"N/A") -> N/A | T20: =IFERROR(ABS(O$3-O20),"N/A") -> N/A | U20: =SUM(P20:T20) -> 0 | V20: =_xlfn.RANK.EQ(U20,$U$4:$U$61,1) -> 1 | W20: =IF(Y20="Not suitable","-",V20) -> - | Y20: =IF(OR(Z20="Y",AA20="Y"),"Not suitable","") -> Not suitable | Z20: =IF(N20="N/A","Y","") -> Y
K21: =IFERROR(_xlfn.RANK.EQ(F21,F$3:F$61),"N/A") -> N/A | L21: =IFERROR(_xlfn.RANK.EQ(G21,G$3:G$61),"N/A") -> N/A | M21: =IFERROR(_xlfn.RANK.EQ(H21,H$3:H$61),"N/A") -> N/A | N21: =IFERROR(_xlfn.RANK.EQ(I21,I$3:I$61),"N/A") -> N/A | O21: =IFERROR(_xlfn.RANK.EQ(J21,J$3:J$61),"N/A") -> N/A | P21: =IFERROR(ABS(K$3-K21),"N/A") -> N/A | Q21: =IFERROR(ABS(L$3-L21),"N/A") -> N/A | R21: =IFERROR(ABS(M$3-M21),"N/A") -> N/A | S21: =IFERROR(ABS(N$3-N21),"N/A") -> N/A | T21: =IFERROR(ABS(O$3-O21),"N/A") -> N/A | U21: =SUM(P21:T21) -> 0 | V21: =_xlfn.RANK.EQ(U21,$U$4:$U$61,1) -> 1 | W21: =IF(Y21="Not suitable","-",V21) -> - | Y21: =IF(OR(Z21="Y",AA21="Y"),"Not suitable","") -> Not suitable | Z21: =IF(N21="N/A","Y","") -> Y
K22: =IFERROR(_xlfn.RANK.EQ(F22,F$3:F$61),"N/A") -> N/A | L22: =IFERROR(_xlfn.RANK.EQ(G22,G$3:G$61),"N/A") -> N/A | M22: =IFERROR(_xlfn.RANK.EQ(H22,H$3:H$61),"N/A") -> N/A | N22: =IFERROR(_xlfn.RANK.EQ(I22,I$3:I$61),"N/A") -> N/A | O22: =IFERROR(_xlfn.RANK.EQ(J22,J$3:J$61),"N/A") -> N/A | P22: =IFERROR(ABS(K$3-K22),"N/A") -> N/A | Q22: =IFERROR(ABS(L$3-L22),"N/A") -> N/A | R22: =IFERROR(ABS(M$3-M22),"N/A") -> N/A | S22: =IFERROR(ABS(N$3-N22),"N/A") -> N/A | T22: =IFERROR(ABS(O$3-O22),"N/A") -> N/A | U22: =SUM(P22:T22) -> 0 | V22: =_xlfn.RANK.EQ(U22,$U$4:$U$61,1) -> 1 | W22: =IF(Y22="Not suitable","-",V22) -> - | Y22: =IF(OR(Z22="Y",AA22="Y"),"Not suitable","") -> Not suitable | Z22: =IF(N22="N/A","Y","") -> Y
K23: =IFERROR(_xlfn.RANK.EQ(F23,F$3:F$61),"N/A") -> N/A | L23: =IFERROR(_xlfn.RANK.EQ(G23,G$3:G$61),"N/A") -> N/A | M23: =IFERROR(_xlfn.RANK.EQ(H23,H$3:H$61),"N/A") -> N/A | N23: =IFERROR(_xlfn.RANK.EQ(I23,I$3:I$61),"N/A") -> N/A | O23: =IFERROR(_xlfn.RANK.EQ(J23,J$3:J$61),"N/A") -> N/A | P23: =IFERROR(ABS(K$3-K23),"N/A") -> N/A | Q23: =IFERROR(ABS(L$3-L23),"N/A") -> N/A | R23: =IFERROR(ABS(M$3-M23),"N/A") -> N/A | S23: =IFERROR(ABS(N$3-N23),"N/A") -> N/A | T23: =IFERROR(ABS(O$3-O23),"N/A") -> N/A | U23: =SUM(P23:T23) -> 0 | V23: =_xlfn.RANK.EQ(U23,$U$4:$U$61,1) -> 1 | W23: =IF(Y23="Not suitable","-",V23) -> - | Y23: =IF(OR(Z23="Y",AA23="Y"),"Not suitable","") -> Not suitable | Z23: =IF(N23="N/A","Y","") -> Y
K24: =IFERROR(_xlfn.RANK.EQ(F24,F$3:F$61),"N/A") -> N/A | L24: =IFERROR(_xlfn.RANK.EQ(G24,G$3:G$61),"N/A") -> N/A | M24: =IFERROR(_xlfn.RANK.EQ(H24,H$3:H$61),"N/A") -> N/A | N24: =IFERROR(_xlfn.RANK.EQ(I24,I$3:I$61),"N/A") -> N/A | O24: =IFERROR(_xlfn.RANK.EQ(J24,J$3:J$61),"N/A") -> N/A | P24: =IFERROR(ABS(K$3-K24),"N/A") -> N/A | Q24: =IFERROR(ABS(L$3-L24),"N/A") -> N/A | R24: =IFERROR(ABS(M$3-M24),"N/A") -> N/A | S24: =IFERROR(ABS(N$3-N24),"N/A") -> N/A | T24: =IFERROR(ABS(O$3-O24),"N/A") -> N/A | U24: =SUM(P24:T24) -> 0 | V24: =_xlfn.RANK.EQ(U24,$U$4:$U$61,1) -> 1 | W24: =IF(Y24="Not suitable","-",V24) -> - | Y24: =IF(OR(Z24="Y",AA24="Y"),"Not suitable","") -> Not suitable | Z24: =IF(N24="N/A","Y","") -> Y
K25: =IFERROR(_xlfn.RANK.EQ(F25,F$3:F$61),"N/A") -> N/A | L25: =IFERROR(_xlfn.RANK.EQ(G25,G$3:G$61),"N/A") -> N/A | M25: =IFERROR(_xlfn.RANK.EQ(H25,H$3:H$61),"N/A") -> N/A | N25: =IFERROR(_xlfn.RANK.EQ(I25,I$3:I$61),"N/A") -> N/A | O25: =IFERROR(_xlfn.RANK.EQ(J25,J$3:J$61),"N/A") -> N/A | P25: =IFERROR(ABS(K$3-K25),"N/A") -> N/A | Q25: =IFERROR(ABS(L$3-L25),"N/A") -> N/A | R25: =IFERROR(ABS(M$3-M25),"N/A") -> N/A | S25: =IFERROR(ABS(N$3-N25),"N/A") -> N/A | T25: =IFERROR(ABS(O$3-O25),"N/A") -> N/A | U25: =SUM(P25:T25) -> 0 | V25: =_xlfn.RANK.EQ(U25,$U$4:$U$61,1) -> 1 | W25: =IF(Y25="Not suitable","-",V25) -> - | Y25: =IF(OR(Z25="Y",AA25="Y"),"Not suitable","") -> Not suitable | Z25: =IF(N25="N/A","Y","") -> Y
K26: =IFERROR(_xlfn.RANK.EQ(F26,F$3:F$61),"N/A") -> N/A | L26: =IFERROR(_xlfn.RANK.EQ(G26,G$3:G$61),"N/A") -> N/A | M26: =IFERROR(_xlfn.RANK.EQ(H26,H$3:H$61),"N/A") -> N/A | N26: =IFERROR(_xlfn.RANK.EQ(I26,I$3:I$61),"N/A") -> N/A | O26: =IFERROR(_xlfn.RANK.EQ(J26,J$3:J$61),"N/A") -> N/A | P26: =IFERROR(ABS(K$3-K26),"N/A") -> N/A | Q26: =IFERROR(ABS(L$3-L26),"N/A") -> N/A | R26: =IFERROR(ABS(M$3-M26),"N/A") -> N/A | S26: =IFERROR(ABS(N$3-N26),"N/A") -> N/A | T26: =IFERROR(ABS(O$3-O26),"N/A") -> N/A | U26: =SUM(P26:T26) -> 0 | V26: =_xlfn.RANK.EQ(U26,$U$4:$U$61,1) -> 1 | W26: =IF(Y26="Not suitable","-",V26) -> - | Y26: =IF(OR(Z26="Y",AA26="Y"),"Not suitable","") -> Not suitable | Z26: =IF(N26="N/A","Y","") -> Y
... K100: =IFERROR(_xlfn.RANK.EQ(F100,F$3:F$61),"N/A") -> N/A | L100: =IFERROR(_xlfn.RANK.EQ(G100,G$3:G$61),"N/A") -> N/A | M100: =IFERROR(_xlfn.RANK.EQ(H100,H$3:H$61),"N/A") -> N/A | N100: =IFERROR(_xlfn.RANK.EQ(I100,I$3:I$61),"N/A") -> N/A | O100: =IFERROR(_xlfn.RANK.EQ(J100,J$3:J$61),"N/A") -> N/A | P100: =IFERROR(ABS(K$3-K100),"N/A") -> N/A | Q100: =IFERROR(ABS(L$3-L100),"N/A") -> N/A | R100: =IFERROR(ABS(M$3-M100),"N/A") -> N/A | S100: =IFERROR(ABS(N$3-N100),"N/A") -> N/A | T100: =IFERROR(ABS(O$3-O100),"N/A") -> N/A | U100: =SUM(P100:T100) -> 0 | V100: =_xlfn.RANK.EQ(U100,$U$4:$U$61,1) -> 1 | W100: =IF(Y100="Not suitable","-",V100) -> - | Y100: =IF(OR(Z100="Y",AA100="Y"),"Not suitable","") -> Not suitable | Z100: =IF(N100="N/A","Y","") -> Y

Sheet ESG
B1: Company GICS Sector: | T1: Yes
B2: Renewable Energy | C2: <- Select Industry | T2: No
B3: ESG Analysis | K3: Relative ESG Analysis
B4: Parameters | C4: Impact | D4: Do they report? | E4: Ranking | F4: Mitigation Plan | G4: Traffic Lights | H4: Improvement over time? | I4: Targets / Goals? | J4: Comments | K4: Parameters | L4: =Peers!C8 -> #VALUE! | M4: =Peers!D8 -> nvidia | N4: =Peers!E8 -> intel | O4: =Peers!F8 -> 0 | P4: =Peers!G8 -> 0 | Q4: =Peers!H8 -> 0 | R4: AVERAGE
B5: Environmental | K5: Ratios
A6: 1 | B6: CO2 Direct Emissions | C6: =VLOOKUP($B$2,'Sector Impact'!$K$4:$AA$16,A6+1,FALSE) -> Low | K6: CO2 Emissions/$M Sales | L6: =L12/L$11 -> #DIV/0! | M6: =M12/M$11 -> #DIV/0! | N6: =N12/N$11 -> #DIV/0! | O6: =O12/O$11 -> #DIV/0! | P6: =P12/P$11 -> #DIV/0! | Q6: =Q12/Q$11 -> #DIV/0! | R6: =IFERROR(AVERAGE(L6:Q6),"")
A7: 2 | B7: Total Water Consumption | C7: =VLOOKUP($B$2,'Sector Impact'!$K$4:$AA$16,A7+1,FALSE) -> Low | K7: Water Consumption/$M Sales | L7: =L13/L$11 -> #DIV/0! | M7: =M13/M$11 -> #DIV/0! | N7: =N13/N$11 -> #DIV/0! | O7: =O13/O$11 -> #DIV/0! | P7: =P13/P$11 -> #DIV/0! | Q7: =Q13/Q$11 -> #DIV/0! | R7: =IFERROR(AVERAGE(L7:Q7),"")
A8: 3 | B8: Total Energy Consumption | C8: =VLOOKUP($B$2,'Sector Impact'!$K$4:$AA$16,A8+1,FALSE) -> Low | K8: Energy Consumption/$M Sales | L8: =L14/L$11 -> #DIV/0! | M8: =M14/M$11 -> #DIV/0! | N8: =N14/N$11 -> #DIV/0! | O8: =O14/O$11 -> #DIV/0! | P8: =P14/P$11 -> #DIV/0! | Q8: =Q14/Q$11 -> #DIV/0! | R8: =IFERROR(AVERAGE(L8:Q8),"")
A9: 4 | B9: Waste Management | C9: =VLOOKUP($B$2,'Sector Impact'!$K$4:$AA$16,A9+1,FALSE) -> Medium | K9: Waste Production/$M Sales | L9: =L15/L$11 -> #DIV/0! | M9: =M15/M$11 -> #DIV/0! | N9: =N15/N$11 -> #DIV/0! | O9: =O15/O$11 -> #DIV/0! | P9: =P15/P$11 -> #DIV/0! | Q9: =Q15/Q$11 -> #DIV/0! | R9: =IFERROR(AVERAGE(L9:Q9),"")
A10: 5 | B10: Land Degradation/Deforestation/Biodiversity loss/Animal sufering/… | C10: =VLOOKUP($B$2,'Sector Impact'!$K$4:$AA$16,A10+1,FALSE) -> Medium | K10: Inputs
B11: Social | K11: Net Sales ($M)
A12: 6 | B12: Employee Turnover % | C12: =VLOOKUP($B$2,'Sector Impact'!$K$4:$AA$16,A12+1,FALSE) -> Low | K12: CO2 Emissions Total (Tonnes)
A13: 7 | B13: Salaries & Compensation | C13: =VLOOKUP($B$2,'Sector Impact'!$K$4:$AA$16,A13+1,FALSE) -> Medium | K13: Water Consumption Total (Cubic Meters)
A14: 8 | B14: Reputation | C14: =VLOOKUP($B$2,'Sector Impact'!$K$4:$AA$16,A14+1,FALSE) -> Medium | K14: Energy Consumption Total (Gigajoules)
A15: 9 | B15: Discrimination Events | C15: =VLOOKUP($B$2,'Sector Impact'!$K$4:$AA$16,A15+1,FALSE) -> High | F15: Yes | K15: Waste Production Total (Tonnes)
A16: 10 | B16: Work Safety | C16: =VLOOKUP($B$2,'Sector Impact'!$K$4:$AA$16,A16+1,FALSE) -> Medium | K16: ESG Scores
A17: 11 | B17: Damage to consumer health | C17: =VLOOKUP($B$2,'Sector Impact'!$K$4:$AA$16,A17+1,FALSE) -> Low | K17: Refinitiv
A18: 12 | B18: PXP? | C18: =VLOOKUP($B$2,'Sector Impact'!$K$4:$AA$16,A18+1,FALSE) -> Low | K18: Sustainalytics
A19: 13 | B19: Supply chain | C19: =VLOOKUP($B$2,'Sector Impact'!$K$4:$AA$16,A19+1,FALSE) -> Medium | K19: ISS
A20: 14 | B20: Community involvement | C20: =VLOOKUP($B$2,'Sector Impact'!$K$4:$AA$16,A20+1,FALSE) -> Medium | K20: CDP
A21: 15 | B21: Public Sector | C21: =VLOOKUP($B$2,'Sector Impact'!$K$4:$AA$16,A21+1,FALSE) -> High
A22: 16 | B22: Litigation | C22: =VLOOKUP($B$2,'Sector Impact'!$K$4:$AA$16,A22+1,FALSE) -> Low | D22: Yes
B23: Corporate Governance | K23: PARAMETERS
A24: 17 | B24: Diversity (Gender, Age, Industry, Region) | K24: IMPACT | L24: RANKING | M24: MITIGATION PLAN | O24: TRAFFIC
A25: 18 | B25: % Independence | K25: Low | L25: "Best in class" | M25: Is there evidence of a plan/program ?
A26: 19 | B26: average time as independent directors | K26: Medium | L26: Medium High
A27: 20 | B27: Recent departures of directors / C-level executives? | K27: High | L27: Medium
A28: 21 | B28: CEO/Chairman duality | K28: Very high | L28: "Villain"
A29: 22 | B29: Transparency (ESG, segments, acquisitions, other)
A30: 23 | B30: Time taken to report after the end of the quarter / year
A31: 24 | B31: Additional participation of the CEO in other boards or excessive participation of Ch.
A32: 25 | B32: Audit / Consulting
A33: 26 | B33: ESG-compensation related
A34: 27 | B34: Management compensation schemes

Sheet DCF
A1: VALUATION MODEL
G3: Short Term | K3: Long Term
A4: Section | B4: Line # | C4: ITEM | D4: 2021 (Real) | E4: 2022 (Real) | F4: 2023 (Real) | G4: 2024 | H4: =G4+1 -> 2025 | I4: =H4+1 -> 2026 | J4: =I4+1 -> 2027 | K4: =J4+1 -> 2028 | L4: =K4+1 -> 2029 | M4: =L4+1 -> 2030 | N4: =M4+1 -> 2031 | O4: =N4+1 -> 2032 | ... AF4: =AE4+1 -> 2049
A5: INCOME STATEMENT | B5: 1 | C5: Growth | D5: ='Fin. Data'!D6 -> 0.68329407 | E5: =+E6/D6-1 -> 0.43610807 | F5: =+F6/E6-1 -> -0.03902377 | G5: =+G6/F6-1 -> -1 | H5: =+H6/G6-1 -> #DIV/0! | I5: =+I6/H6-1 -> #DIV/0! | J5: =+J6/I6-1 -> #DIV/0! | K5: =+K6/J6-1 -> #DIV/0! | L5: =+L6/K6-1 -> #DIV/0! | ... AF5: =+AF6/AE6-1 -> #DIV/0!
B6: 2 | C6: Revenues/Sales | D6: =Inputs!D6 -> 16434 | E6: =Inputs!C6 -> 23601 | F6: =Inputs!B6 -> 22680
B7: 3 | C7: EBIT/Operating Margin | D7: =D8/D6 -> 0.22155288 | E7: =E8/E6 -> 0.053557053 | F7: =F8/F6 -> 0.017680776
B8: 4 | C8: EBIT | D8: ='Fin. Data'!D11 -> 3641 | E8: ='Fin. Data'!C11 -> 1264 | F8: ='Fin. Data'!B11 -> 401 | G8: =G7*G6 -> 0 | H8: =H7*H6 -> 0 | I8: =I7*I6 -> 0 | J8: =J7*J6 -> 0 | K8: =K7*K6 -> 0 | L8: =L7*L6 -> 0 | M8: =M7*M6 -> 0 | N8: =N7*N6 -> 0 | ... AF8: =AF7*AF6 -> 0
B9: 5a | C9: (Dep) | G9: =$D$53*DCF!F40 -> 0 | H9: =$D$53*DCF!G40 -> 0 | I9: =$D$53*DCF!H40 -> 0 | J9: =$D$53*DCF!I40 -> 0 | K9: =$E$53*DCF!J40 -> 0 | L9: =$E$53*DCF!K40 -> 0 | M9: =$E$53*DCF!L40 -> 0 | N9: =$E$53*DCF!M40 -> 0 | O9: =$E$53*DCF!N40 -> 0 | P9: =$E$53*DCF!O40 -> 0 | Q9: =$E$53*DCF!P40 -> 0 | R9: =$E$53*DCF!Q40 -> 0 | ... AF9: =$E$53*DCF!AE40 -> 0 | AG9: =SUM(D9:AF9) -> 0
B10: 5b | C10: (Amort) | G10: =F38*$D$54 -> 0 | H10: =G38*$D$54 -> 0 | I10: =H38*$D$54 -> 0 | J10: =I38*$D$54 -> 0 | K10: =J38*$E$54 -> 0 | L10: =K38*$E$54 -> 0 | M10: =L38*$E$54 -> 0 | N10: =M38*$E$54 -> 0 | O10: =N38*$E$54 -> 0 | P10: =O38*$E$54 -> 0 | Q10: =P38*$E$54 -> 0 | R10: =Q38*$E$54 -> 0 | ... AF10: =AE38*$E$54 -> 0
B11: 5c | C11: (Stock based compensation) | D11: =D20 -> 0 | E11: =E20 -> 0 | F11: =F20 -> 0 | G11: =G6*$D$55 -> 0 | H11: =H6*$D$55 -> 0 | I11: =I6*$D$55 -> 0 | J11: =J6*$D$55 -> 0 | K11: =K6*$D$55 -> 0 | L11: =L6*$D$55 -> 0 | M11: =M6*$D$55 -> 0 | N11: =N6*$D$55 -> 0 | ... AF11: =AF6*$D$55 -> 0
B12: 6 | C12: EBITDA | D12: =D8-D9-D10 -> 3641 | E12: =E8-E9-E10 -> 1264 | F12: =F8-F9-F10 -> 401 | G12: =G8-G9-G10 -> 0 | H12: =H8-H9-H10 -> 0 | I12: =I8-I9-I10 -> 0 | J12: =J8-J9-J10 -> 0 | K12: =K8-K9-K10 -> 0 | ... AF12: =AF8-AF9-AF10 -> 0
B13: 7 | C13: (Net financing cost) | D13: ='Fin. Data'!D14 -> 30 | E13: ='Fin. Data'!C14 -> -85 | F13: ='Fin. Data'!B14 -> 99 | G13: =F43*$D$58-F44*$D$57 -> 0 | H13: =G43*$D$58-G44*$D$57 -> 0 | I13: =H43*$D$58-H44*$D$57 -> #DIV/0! | J13: =I43*$D$58-I44*$D$57 -> #DIV/0! | K13: =J43*$E$58-J44*$E$57 -> #DIV/0! | L13: =K43*$E$58-K44*$E$57 -> #DIV/0! | M13: =L43*$E$58-L44*$E$57 -> #DIV/0! | N13: =M43*$E$58-M44*$E$57 -> #DIV/0! | O13: =N43*$E$58-N44*$E$57 -> #DIV/0! | P13: =O43*$E$58-O44*$E$57 -> #DIV/0! | Q13: =P43*$E$58-P44*$E$57 -> #DIV/0! | R13: =Q43*$E$58-Q44*$E$57 -> #DIV/0! | ... AF13: =AE43*$E$58-AE44*$E$57 -> #DIV/0!
B14: 8 | C14: Other income/(cost) | D14: ='Fin. Data'!D15 -> 4 | E14: ='Fin. Data'!C15 -> 19 | F14: ='Fin. Data'!B15 -> 8 | G14: =AVERAGE(D14:F14)*(1+G5) -> 0 | H14: =AVERAGE(E14:G14)*(1+H5) -> #DIV/0! | I14: =AVERAGE(F14:H14)*(1+I5) -> #DIV/0! | J14: =AVERAGE(G14:I14)*(1+J5) -> #DIV/0! | K14: =AVERAGE(H14:J14)*(1+K5) -> #DIV/0! | L14: =AVERAGE(I14:K14)*(1+L5) -> #DIV/0! | M14: =AVERAGE(J14:L14)*(1+M5) -> #DIV/0! | N14: =AVERAGE(K14:M14)*(1+N5) -> #DIV/0! | ... AF14: =AVERAGE(AC14:AE14)*(1+AF5) -> #DIV/0!
B15: 9 | C15: Earnings before taxes | D15: =D8+D13+D14 -> 3675 | E15: =E8+E13+E14 -> 1198 | F15: =F8+F13+F14 -> 508 | G15: =G8+G13+G14 -> 0 | H15: =H8+H13+H14 -> #DIV/0! | I15: =I8+I13+I14 -> #DIV/0! | J15: =J8+J13+J14 -> #DIV/0! | K15: =K8+K13+K14 -> #DIV/0! | ... AF15: =AF8+AF13+AF14 -> #DIV/0!
B16: 10 | C16: (Income tax) | D16: ='Fin. Data'!D21 -> -513 | E16: ='Fin. Data'!C21 -> 122 | F16: ='Fin. Data'!B21 -> 346 | G16: =-$D$56*G15 -> 0 | H16: =-$D$56*H15 -> #DIV/0! | I16: =-$D$56*I15 -> #DIV/0! | J16: =-$D$56*J15 -> #DIV/0! | K16: =-$E$56*K15 -> #DIV/0! | L16: =-$E$56*L15 -> #DIV/0! | M16: =-$E$56*M15 -> #DIV/0! | N16: =-$E$56*N15 -> #DIV/0! | O16: =-$E$56*O15 -> #DIV/0! | P16: =-$E$56*P15 -> #DIV/0! | Q16: =-$E$56*Q15 -> #DIV/0! | R16: =-$E$56*R15 -> #DIV/0! | ... AF16: =-$E$56*AF15 -> #DIV/0!
B17: 11 | C17: Net income | D17: ='Fin. Data'!D23 -> 3162 | E17: ='Fin. Data'!C23 -> 1320 | F17: ='Fin. Data'!B23 -> 854 | G17: =G16+G15 -> 0 | H17: =H16+H15 -> #DIV/0! | I17: =I16+I15 -> #DIV/0! | J17: =J16+J15 -> #DIV/0! | K17: =K16+K15 -> #DIV/0! | L17: =L16+L15 -> #DIV/0! | M17: =M16+M15 -> #DIV/0! | N17: =N16+N15 -> #DIV/0! | ... AF17: =AF16+AF15 -> #DIV/0!
A19: CASH FLOW STATEMENT | B19: 12 | C19: Operating cash flows before WK | G19: =G17-G10-G9-G11 -> 0 | H19: =H17-H10-H9-H11 -> #DIV/0! | I19: =I17-I10-I9-I11 -> #DIV/0! | J19: =J17-J10-J9-J11 -> #DIV/0! | K19: =K17-K10-K9-K11 -> #DIV/0! | L19: =L17-L10-L9-L11 -> #DIV/0! | M19: =M17-M10-M9-M11 -> #DIV/0! | N19: =N17-N10-N9-N11 -> #DIV/0! | ... AF19: =AF17-AF10-AF9-AF11 -> #DIV/0!
B20: 13 | C20: (Stock-based compensation) | G20: =G11 -> 0 | H20: =H11 -> 0 | I20: =I11 -> 0 | J20: =J11 -> 0 | K20: =K11 -> 0 | L20: =L11 -> 0 | M20: =M11 -> 0 | N20: =N11 -> 0 | ... AF20: =AF11 -> 0
B21: 14 | C21: (Working Capital Flows) | D21: =Inputs!D62 -> -774 | E21: =Inputs!C62 -> -1846 | F21: =Inputs!B62 -> -3049 | G21: =$D$60*(G6-F6) -> 0 | H21: =$D$60*(H6-G6) -> 0 | I21: =$D$60*(I6-H6) -> 0 | J21: =$D$60*(J6-I6) -> 0 | K21: =$E$60*(K6-J6) -> 0 | L21: =$E$60*(L6-K6) -> 0 | M21: =$E$60*(M6-L6) -> 0 | N21: =$E$60*(N6-M6) -> 0 | O21: =$E$60*(O6-N6) -> 0 | P21: =$E$60*(P6-O6) -> 0 | Q21: =$E$60*(Q6-P6) -> 0 | R21: =$E$60*(R6-Q6) -> 0 | ... AF21: =$E$60*(AF6-AE6) -> 0
B22: 15 | C22: -Total Operating Cash Flow | D22: =D19+D20+D21 -> -774 | E22: =E19+E20+E21 -> -1846 | F22: =F19+F20+F21 -> -3049 | G22: =G19+G20+G21 -> 0 | H22: =H19+H20+H21 -> #DIV/0! | I22: =I19+I20+I21 -> #DIV/0! | J22: =J19+J20+J21 -> #DIV/0! | K22: =K19+K20+K21 -> #DIV/0! | ... AF22: =AF19+AF20+AF21 -> #DIV/0!
B23: 16 | C23: (CAPEX) | D23: ='Fin. Data'!D32 -> -301 | E23: ='Fin. Data'!C32 -> -450 | F23: ='Fin. Data'!B32 -> -546 | G23: =G6*$D$62 -> 0 | H23: =H6*$D$62 -> 0 | I23: =I6*$D$62 -> 0 | J23: =J6*$D$62 -> 0 | K23: =K6*$E$62 -> 0 | L23: =L6*$E$62 -> 0 | M23: =M6*$E$62 -> 0 | N23: =N6*$E$62 -> 0 | O23: =O6*$E$62 -> 0 | P23: =P6*$E$62 -> 0 | Q23: =Q6*$E$62 -> 0 | R23: =R6*$E$62 -> 0 | ... AF23: =AF6*$E$62 -> 0 | AG23: =SUM(D23:AF23) -> -1297
B24: 17 | C24: Adq | D24: =Inputs!D66 -> -378 | E24: ='Fin. Data'!C33 -> 2465 | F24: ='Fin. Data'!B33 -> -866 | G24: =G6*$D$63 -> 0 | H24: =H6*$D$63 -> 0 | I24: =I6*$D$63 -> 0 | J24: =J6*$D$63 -> 0 | K24: =K6*$E$63 -> 0 | L24: =L6*$E$63 -> 0 | M24: =M6*$E$63 -> 0 | N24: =N6*$E$63 -> 0 | O24: =O6*$E$63 -> 0 | P24: =P6*$E$63 -> 0 | Q24: =Q6*$E$63 -> 0 | R24: =R6*$E$63 -> 0 | ... AF24: =AF6*$E$63 -> 0 | AH24: =AG9-AG23 -> 1297
B25: 18 | C25: (Other investing flows) | D25: =Inputs!D67 -> -7 | E25: =Inputs!C67 -> -16 | F25: =Inputs!B67 -> -11 | G25: =(1+G5)*AVERAGE(D25:F25) -> 0 | H25: =(1+H5)*AVERAGE(E25:G25) -> #DIV/0! | I25: =(1+I5)*AVERAGE(F25:H25) -> #DIV/0! | J25: =(1+J5)*AVERAGE(G25:I25) -> #DIV/0! | K25: =(1+K5)*AVERAGE(H25:J25) -> #DIV/0! | L25: =(1+L5)*AVERAGE(I25:K25) -> #DIV/0! | M25: =(1+M5)*AVERAGE(J25:L25) -> #DIV/0! | N25: =(1+N5)*AVERAGE(K25:M25) -> #DIV/0! | ... AF25: =(1+AF5)*AVERAGE(AC25:AE25) -> #DIV/0!
B26: 19 | C26: -Total Investing Flows | D26: =D23+D24+D25 -> -686 | E26: =E23+E24+E25 -> 1999 | F26: =F23+F24+F25 -> -1423 | G26: =G23+G24+G25 -> 0 | H26: =H23+H24+H25 -> #DIV/0! | I26: =I23+I24+I25 -> #DIV/0! | J26: =J23+J24+J25 -> #DIV/0! | K26: =K23+K24+K25 -> #DIV/0! | ... AF26: =AF23+AF24+AF25 -> #DIV/0!
B27: 20 | C27: (Flows related to leases) | D27: =Inputs!D71+Inputs!D72 -> 0 | E27: =Inputs!C71+Inputs!C72 -> 0 | F27: =Inputs!B71+Inputs!B72 -> 0 | G27: =G6*$D$66 -> 0 | H27: =H6*$D$66 -> 0 | I27: =I6*$D$66 -> 0 | J27: =J6*$D$66 -> 0 | K27: =$E$66*K6 -> 0 | L27: =$E$66*L6 -> 0 | M27: =$E$66*M6 -> 0 | N27: =$E$66*N6 -> 0 | O27: =$E$66*O6 -> 0 | P27: =$E$66*P6 -> 0 | Q27: =$E$66*Q6 -> 0 | R27: =$E$66*R6 -> 0 | ... AF27: =$E$66*AF6 -> 0
B28: 21 | C28: Flows related to debt | D28: =+SUM(Inputs!D69:D70) -> 0 | E28: =+SUM(Inputs!C69:C70) -> 679 | F28: =+SUM(Inputs!B69:B70) -> 0 | G28: =G44-F44 -> -2252 | H28: =H44-G44 -> 0 | I28: =I44-H44 -> 0 | J28: =J44-I44 -> 0 | K28: =K44-J44 -> 0 | L28: =L44-K44 -> 0 | M28: =M44-L44 -> 0 | N28: =N44-M44 -> 0 | ... AF28: =AF44-AE44 -> 0
B29: 22 | C29: (Repurchases)/Issuance of stock | D29: ='Fin. Data'!D28 -> -1762 | E29: ='Fin. Data'!C28 -> -3702 | F29: ='Fin. Data'!B28 -> -985 | G29: =-G17*$D$65 -> 0 | H29: =-H17*$D$65 -> #DIV/0! | I29: =-I17*$D$65 -> #DIV/0! | J29: =-J17*$D$65 -> #DIV/0! | K29: =-K17*$E$65 -> #DIV/0! | L29: =-L17*$E$65 -> #DIV/0! | M29: =-M17*$E$65 -> #DIV/0! | N29: =-N17*$E$65 -> #DIV/0! | O29: =-O17*$E$65 -> #DIV/0! | P29: =-P17*$E$65 -> #DIV/0! | Q29: =-Q17*$E$65 -> #DIV/0! | R29: =-R17*$E$65 -> #DIV/0! | ... AF29: =-AF17*$E$65 -> #DIV/0!
B30: 23 | C30: (Dividends) | D30: ='Fin. Data'!D27 -> 0 | E30: ='Fin. Data'!C27 -> 0 | F30: ='Fin. Data'!B27 -> 0 | G30: =-$D$64*G17 -> 0 | H30: =-$D$64*H17 -> #DIV/0! | I30: =-$D$64*I17 -> #DIV/0! | J30: =-$D$64*J17 -> #DIV/0! | K30: =-$E$64*K17 -> #DIV/0! | L30: =-$E$64*L17 -> #DIV/0! | M30: =-$E$64*M17 -> #DIV/0! | N30: =-$E$64*N17 -> #DIV/0! | O30: =-$E$64*O17 -> #DIV/0! | P30: =-$E$64*P17 -> #DIV/0! | Q30: =-$E$64*Q17 -> #DIV/0! | R30: =-$E$64*R17 -> #DIV/0! | ... AF30: =-$E$64*AF17 -> #DIV/0!
B31: 24 | C31: Other financing flows | D31: =Inputs!D75 -> -133 | E31: =Inputs!C75 -> -241 | F31: =Inputs!B75 -> -161 | G31: =(1+G5)*AVERAGE(D31:F31) -> 0 | H31: =(1+H5)*AVERAGE(E31:G31) -> #DIV/0! | I31: =(1+I5)*AVERAGE(F31:H31) -> #DIV/0! | J31: =(1+J5)*AVERAGE(G31:I31) -> #DIV/0! | K31: =(1+K5)*AVERAGE(H31:J31) -> #DIV/0! | L31: =(1+L5)*AVERAGE(I31:K31) -> #DIV/0! | M31: =(1+M5)*AVERAGE(J31:L31) -> #DIV/0! | N31: =(1+N5)*AVERAGE(K31:M31) -> #DIV/0! | ... AF31: =(1+AF5)*AVERAGE(AC31:AE31) -> #DIV/0!
B32: 25 | C32: -Total Financing flows | D32: =D27+D28+D29+D30+D31 -> -1895 | E32: =E27+E28+E29+E30+E31 -> -3264 | F32: =F27+F28+F29+F30+F31 -> -1146 | G32: =G27+G28+G29+G30+G31 -> -2252 | H32: =H27+H28+H29+H30+H31 -> #DIV/0! | I32: =I27+I28+I29+I30+I31 -> #DIV/0! | J32: =J27+J28+J29+J30+J31 -> #DIV/0! | K32: =K27+K28+K29+K30+K31 -> #DIV/0! | ... AF32: =AF27+AF28+AF29+AF30+AF31 -> #DIV/0!
A34: SUMMARY | B34: 26 | C34: Cash before shareholder returns | D34: =D22+D26+D27+D28+D31 -> -1593 | E34: =E22+E26+E27+E28+E31 -> 591 | F34: =F22+F26+F27+F28+F31 -> -4633 | G34: =G22+G26+G27+G28+G31 -> -2252 | H34: =H22+H26+H27+H28+H31 -> #DIV/0! | I34: =I22+I26+I27+I28+I31 -> #DIV/0! | J34: =J22+J26+J27+J28+J31 -> #DIV/0! | K34: =K22+K26+K27+K28+K31 -> #DIV/0! | ... AF34: =AF22+AF26+AF27+AF28+AF31 -> #DIV/0!
B35: 27 | C35: Returns to shareholders | D35: =-1*(D29+D30) -> 1762 | E35: =-1*(E29+E30) -> 3702 | F35: =-1*(F29+F30) -> 985 | G35: =-1*(G29+G30) -> 0 | H35: =-1*(H29+H30) -> #DIV/0! | I35: =-1*(I29+I30) -> #DIV/0! | J35: =-1*(J29+J30) -> #DIV/0! | K35: =-1*(K29+K30) -> #DIV/0! | ... AF35: =-1*(AF29+AF30) -> #DIV/0!
B36: 28 | C36: Excess cash acumulation | D36: =D34-D35 -> -3355 | E36: =E34-E35 -> -3111 | F36: =F34-F35 -> -5618 | G36: =G34-G35 -> -2252 | H36: =H34-H35 -> #DIV/0! | I36: =I34-I35 -> #DIV/0! | J36: =J34-J35 -> #DIV/0! | K36: =K34-K35 -> #DIV/0! | ... AF36: =AF34-AF35 -> #DIV/0!
A38: BALANCE SHEET | B38: 29 | C38: Intangible assets | G38: =+F38+(-G10) -> 0 | H38: =+G38+(-H10) -> 0 | I38: =+H38+(-I10) -> 0 | J38: =+I38+(-J10) -> 0 | K38: =+J38+(-K10) -> 0 | L38: =+K38+(-L10) -> 0 | M38: =+L38+(-M10) -> 0 | N38: =+M38+(-N10) -> 0 | ... AF38: =+AE38+(-AF10) -> 0 | AG38: =SUM(G38:AF38) -> 0
B39: 30 | C39: Accumulated amortization | G39: =F39-G10 -> 0 | H39: =G39-H10 -> 0 | I39: =H39-I10 -> 0 | J39: =I39-J10 -> 0 | K39: =J39-K10 -> 0 | L39: =K39-L10 -> 0 | M39: =L39-M10 -> 0 | N39: =M39-N10 -> 0 | ... AF39: =AE39-AF10 -> 0 | AG39: =SUM(G39:AF39) -> 0
B40: 31 | C40: PPE+Right of use Assets | G40: =F40+(-G23) -> 0 | H40: =G40+(-H23) -> 0 | I40: =H40+(-I23) -> 0 | J40: =I40+(-J23) -> 0 | K40: =J40+(-K23) -> 0 | L40: =K40+(-L23) -> 0 | M40: =L40+(-M23) -> 0 | N40: =M40+(-N23) -> 0 | ... AF40: =AE40+(-AF23) -> 0 | AG40: =SUM(G40:AF40) -> 0
B41: 32 | C41: Accumulated depreciation | G41: =F41-G9 -> 0 | H41: =G41-H9 -> 0 | I41: =H41-I9 -> 0 | J41: =I41-J9 -> 0 | K41: =J41-K9 -> 0 | L41: =K41-L9 -> 0 | M41: =L41-M9 -> 0 | N41: =M41-N9 -> 0 | ... AF41: =AE41-AF9 -> 0 | AG41: =SUM(G41:AF41) -> 0
A43: CASH & DEBT & DISCOUNTING | B43: 33 | C43: Ending cash balance | D43: ='Fin. Data'!D39 -> 2535 | E43: =E36+D43 -> -576 | F43: =F36+E43 -> -6194 | G43: =G36+F43 -> -8446 | H43: =H36+G43 -> #DIV/0! | I43: =I36+H43 -> #DIV/0! | J43: =J36+I43 -> #DIV/0! | K43: =K36+J43 -> #DIV/0! | L43: =L36+K43 -> #DIV/0! | ... AF43: =AF36+AE43 -> #DIV/0!
B44: 34 | C44: Total Debt | D44: ='Fin. Data'!D58 -> 349 | E44: ='Fin. Data'!C58 -> 2863 | F44: ='Fin. Data'!B58 -> 2252 | G44: =G12*$D$67 -> 0 | H44: =H12*$D$67 -> 0 | I44: =I12*$D$67 -> 0 | J44: =J12*$D$67 -> 0 | K44: =K12*$E$67 -> 0 | L44: =L12*$E$67 -> 0 | M44: =M12*$E$67 -> 0 | N44: =N12*$E$67 -> 0 | O44: =O12*$E$67 -> 0 | P44: =P12*$E$67 -> 0 | Q44: =Q12*$E$67 -> 0 | R44: =R12*$E$67 -> 0 | ... AF44: =AF12*$E$67 -> 0
B45: 35 | C45: Discount factor | F45: =1/((1+$F$50)^G50) -> 1 | G45: =1/((1+$F$50)^G49) -> 1 | H45: =1/((1+$F$50)^H49) -> 1 | I45: =1/((1+$F$50)^I49) -> 1 | J45: =1/((1+$F$50)^J49) -> 1 | K45: =1/((1+$F$50)^K49) -> 1 | L45: =1/((1+$F$50)^L49) -> 1 | M45: =1/((1+$F$50)^M49) -> 1 | N45: =1/((1+$F$50)^N49) -> 1 | ... AF45: =1/((1+$F$50)^AF49) -> 1
B46: 36 | C46: DF + 0.1% | E46: +0.1% | F46: =1/((1+$F$50+0.001)^G50) -> 1 | G46: =1/((1+$F$50+0.001)^G49) -> 0.999001 | H46: =1/((1+$F$50+0.001)^H49) -> 0.998003 | I46: =1/((1+$F$50+0.001)^I49) -> 0.99700599 | J46: =1/((1+$F$50+0.001)^J49) -> 0.99600998 | K46: =1/((1+$F$50+0.001)^K49) -> 0.99501497 | L46: =1/((1+$F$50+0.001)^L49) -> 0.99402094 | M46: =1/((1+$F$50+0.001)^M49) -> 0.99302792 | N46: =1/((1+$F$50+0.001)^N49) -> 0.99203588 | ... AF46: =1/((1+$F$50+0.001)^AF49) -> 0.97434775
B47: 37 | C47: DF+0.5% | E47: +0.5% | F47: =1/((1+$F$50+0.005)^G50) -> 1 | G47: =1/((1+$F$50+0.005)^G49) -> 0.99502488 | H47: =1/((1+$F$50+0.005)^H49) -> 0.9900745 | I47: =1/((1+$F$50+0.005)^I49) -> 0.98514876 | J47: =1/((1+$F$50+0.005)^J49) -> 0.98024752 | K47: =1/((1+$F$50+0.005)^K49) -> 0.97537067 | L47: =1/((1+$F$50+0.005)^L49) -> 0.97051808 | M47: =1/((1+$F$50+0.005)^M49) -> 0.96568963 | N47: =1/((1+$F$50+0.005)^N49) -> 0.9608852 | ... AF47: =1/((1+$F$50+0.005)^AF49) -> 0.87837991
A49: Discount Rate | C49: Risk free rate | D49: Equity premium | E49: Firm premium | F49: Total | G49: 1 | H49: 2 | I49: 3 | J49: 4 | K49: 5 | L49: 6 | M49: 7 | N49: 8 | O49: 9 | P49: 10 | Q49: 11 | R49: 12 | S49: 13 | T49: 14 | U49: 15 | V49: 16 | W49: 17 | X49: 18 | Y49: 19 | Z49: 20 | AA49: 21 | AB49: 22 | AC49: 23 | AD49: 24 | AE49: 25 | AF49: 26
F50: =E50+D50+C50 -> 0 | G50: 0
A52: Modelling factors | D52: Short Term | E52: Long Term | F52: Reference (line)
C53: Depreciation factor | D53: =Assumptions!S17 -> 0 | E53: =Assumptions!T17 -> 0 | F53: =Assumptions!V17 -> % PPE
C54: Amortization factor | D54: =Assumptions!S18 -> 0 | E54: =Assumptions!T18 -> 0 | F54: =Assumptions!V18 -> % IA
C55: Stock-based comp | D55: =Assumptions!S19 -> 0 | E55: =Assumptions!T19 -> 0 | F55: =Assumptions!V19 -> % Revenue
C56: Tax Rate | D56: =Assumptions!S20 -> 0 | E56: =Assumptions!T20 -> 0 | F56: =Assumptions!V20 -> % EBT
C57: Interest Rate on debt | D57: =Assumptions!S21 -> 0 | E57: =Assumptions!T21 -> 0 | F57: =Assumptions!V21 -> % Debt
C58: Interest Rate on cash | D58: =Assumptions!S22 -> 0 | E58: =Assumptions!T22 -> 0 | F58: =Assumptions!V22 -> % Cash
C59: PPE+ROA | D59: =Assumptions!S23 -> - - | E59: =Assumptions!T23 -> - - | F59: =Assumptions!V23 -> Growing with CAPEX
C60: Working capital flows | D60: =Assumptions!S24 -> 0 | E60: =Assumptions!T24 -> 0 | F60: =Assumptions!V24 -> % Change in Revenues
C61: Intangible Assets | D61: =Assumptions!S25 -> - - | E61: =Assumptions!T25 -> - - | F61: =Assumptions!V25 -> Growing with Amortization
C62: Capex | D62: =Assumptions!S26 -> 0 | E62: =Assumptions!T26 -> 0 | F62: =Assumptions!V26 -> % Revenue
C63: Acquisition factor | D63: =Assumptions!S27 -> 0 | E63: =Assumptions!T27 -> 0 | F63: =Assumptions!V27 -> % Revenue
C64: Dividends | D64: =Assumptions!S28 -> 0 | E64: =Assumptions!T28 -> 0 | F64: =Assumptions!V28 -> % Net Income
... C67: Total Debt | D67: =Assumptions!S31 -> 0 | E67: =Assumptions!T31 -> 0 | F67: =Assumptions!V31 -> % EBITDA
A69: Valuation | D69: $ millions
C70: Value of flows | D70: =SUMPRODUCT(G35:AF35,G45:AF45)+((AF43-AF44)*AF45) -> #DIV/0! | E70: =D70/D72 -> #DIV/0!
C71: Value of perpetuity | D71: =(AF34/(F50-AF5))*AF45 -> #DIV/0! | E71: =D71/D72 -> #DIV/0!
C72: Total Value | D72: =D70+D71 -> #DIV/0!
C73: Actual share price | D73: =OP!C20 -> 146.64
C74: Total value vs Mkt Cap | D74: =D75/D73-1 -> #DIV/0!
C75: Estimated NPV per share | D75: =D72*1000000/OP!C21 -> #DIV/0!
A77: Sensibility | C77: Sensitivity +0.1% | D77: =(SUMPRODUCT(G35:AF35,G45:AF45)+((AF43-AF44)*AF45)+(AF34/(F50+0.001-AF5))*AF45)*1000000/OP!C21 -> #DIV/0! | E77: =D77/D75-1 -> #DIV/0!
C78: Sensitivity +0.5% | D78: =(SUMPRODUCT(G35:AF35,G45:AF45)+((AF43-AF44)*AF45)+(AF34/(F50+0.005-AF5))*AF45)*1000000/OP!C21 -> #DIV/0! | E78: =D78/D75-1 -> #DIV/0!
A80: Notes | C80: Price where it'd be a "BUY" | D80: =D75/1.15 -> #DIV/0!

Sheet Assumptions
B2: Assumptions
B4: Prospects:
B6: Links:
C8: 2023 | D8: =C8-1 -> 2022 | E8: =D8-1 -> 2021 | F8: =E8-1 -> 2020 | G8: =F8-1 -> 2019 | H8: =G8-1 -> 2018 | I8: =H8-1 -> 2017 | J8: =I8-1 -> 2016 | K8: =J8-1 -> 2015 | ... M8: =L8-1 -> 2013 | O8: 10Y Average | P8: 5Y Average | Q8: 3Y Average | S8: Short Term Forecast | T8: Long Term Forecast
B9: Revenue growth | C9: =(Inputs!B6-Inputs!C6)/Inputs!C6 -> -0.03902377 | D9: =(Inputs!C6-Inputs!D6)/Inputs!D6 -> 0.43610807 | E9: =(Inputs!D6-Inputs!E6)/Inputs!E6 -> 0.68329407 | F9: =(Inputs!E6-Inputs!F6)/Inputs!F6 -> 0.45045313 | G9: =(Inputs!F6-Inputs!G6)/Inputs!G6 -> 0.03953668 | H9: =(Inputs!G6-Inputs!H6)/Inputs!H6 -> 0.23262897 | I9: =(Inputs!H6-Inputs!I6)/Inputs!I6 -> 0.22963483 | J9: =(Inputs!I6-Inputs!J6)/Inputs!J6 -> 0.070408419 | ... M9: =(Inputs!L6-Inputs!M6)/Inputs!M6 -> -0.022685356 | O9: =AVERAGE(C9:M9) -> 0.16766042 | P9: =AVERAGE(C9:G9) -> 0.31407363 | Q9: =AVERAGE(C9:E9) -> 0.36012612
B10: Operating Margin | C10: =Inputs!B8/Inputs!B6 -> 0.017680776 | D10: =Inputs!C8/Inputs!C6 -> 0.053557053 | E10: =Inputs!D8/Inputs!D6 -> 0.22155288 | F10: =Inputs!E8/Inputs!E6 -> 0.13469221 | G10: =Inputs!F8/Inputs!F6 -> 0.067597682 | H10: =Inputs!G8/Inputs!G6 -> 0.067799228 | I10: =Inputs!H8/Inputs!H6 -> 0.021892252 | J10: =Inputs!I8/Inputs!I6 -> -0.10299625 | ... M10: =Inputs!L8/Inputs!L6 -> 0.019248915 | O10: =AVERAGE(C10:M10) -> 0.031024876 | P10: =AVERAGE(C10:G10) -> 0.099016119 | Q10: =AVERAGE(C10:E10) -> 0.097596902
B13: Modelling Factors
C15: Last 10 Years
C16: =C8 -> 2023 | D16: =D8 -> 2022 | E16: =E8 -> 2021 | F16: =F8 -> 2020 | G16: =G8 -> 2019 | H16: =H8 -> 2018 | I16: =I8 -> 2017 | J16: =J8 -> 2016 | ... M16: =M8 -> 2013 | O16: =O8 -> 10Y Average | P16: =P8 -> 5Y Average | Q16: =Q8 -> 3Y Average | S16: Short Term Forecast | T16: Long Term Forecast | V16: Reference
B17: Depreciation factor | O17: =AVERAGE(C17:M17) -> #DIV/0! | P17: =AVERAGE(C17:G17) -> #DIV/0! | Q17: =AVERAGE(C17:E17) -> #DIV/0! | V17: % PPE
B18: Amortization factor | O18: =AVERAGE(C18:M18) -> #DIV/0! | P18: =AVERAGE(C18:G18) -> #DIV/0! | Q18: =AVERAGE(C18:E18) -> #DIV/0! | V18: % IA
B19: Stock-based comp | O19: =AVERAGE(C19:M19) -> #DIV/0! | P19: =AVERAGE(C19:G19) -> #DIV/0! | Q19: =AVERAGE(C19:E19) -> #DIV/0! | V19: % Revenue
B20: Tax Rate | C20: ='Fin. Data'!B21/('Fin. Data'!B21+'Fin. Data'!B23) -> 0.28833333 | D20: ='Fin. Data'!C21/('Fin. Data'!C21+'Fin. Data'!C23) -> 0.084604716 | E20: ='Fin. Data'!D21/('Fin. Data'!D21+'Fin. Data'!D23) -> -0.19365798 | F20: ='Fin. Data'!E21/('Fin. Data'!E21+'Fin. Data'!E23) -> 0.32702703 | G20: ='Fin. Data'!F21/('Fin. Data'!F21+'Fin. Data'!F23) -> -0.14814815 | H20: ='Fin. Data'!G21/('Fin. Data'!G21+'Fin. Data'!G23) -> 0.061281337 | I20: ='Fin. Data'!H21/('Fin. Data'!H21+'Fin. Data'!H23) -> 0.97205758 | J20: ='Fin. Data'!I21/('Fin. Data'!I21+'Fin. Data'!I23) -> 0.072761194 | ... M20: ='Fin. Data'!L21/('Fin. Data'!L21+'Fin. Data'!L23) -> 0.097826087 | O20: =AVERAGE(C20:M20) -> 0.14501014 | P20: =AVERAGE(C20:G20) -> 0.071631789 | Q20: =AVERAGE(C20:E20) -> 0.059760022 | V20: % EBT
B21: Interest Rate on debt | O21: =AVERAGE(C21:M21) -> #DIV/0! | P21: =AVERAGE(C21:G21) -> #DIV/0! | Q21: =AVERAGE(C21:E21) -> #DIV/0! | V21: % Debt
B22: Interest Rate on cash | O22: =AVERAGE(C22:M22) -> #DIV/0! | P22: =AVERAGE(C22:G22) -> #DIV/0! | Q22: =AVERAGE(C22:E22) -> #DIV/0! | V22: % Cash
B23: PPE+ROA | C23: =Inputs!B33/Inputs!C33-1 -> 0.050231328 | D23: =Inputs!C33/Inputs!D33-1 -> 1.1552707 | E23: =Inputs!D33/Inputs!E33-1 -> 0.095163807 | F23: =Inputs!E33/Inputs!F33-1 -> 0.282 | G23: =Inputs!F33/Inputs!G33-1 -> 0.43678161 | H23: =Inputs!G33/Inputs!H33-1 -> 0.33333333 | I23: =Inputs!H33/Inputs!I33-1 -> 0.59146341 | J23: =Inputs!I33/Inputs!J33-1 -> -0.12765957 | ... M23: =Inputs!L33/Inputs!M33-1 -> -0.47416413 | O23: =AVERAGE(C23:M23) -> 0.16706994 | P23: =AVERAGE(C23:G23) -> 0.40388948 | Q23: =AVERAGE(C23:E23) -> 0.43355526 | S23: - - | T23: - - | V23: Growing with CAPEX
B24: Working capital flows | O24: =AVERAGE(C24:M24) -> #DIV/0! | P24: =AVERAGE(C24:G24) -> #DIV/0! | Q24: =AVERAGE(C24:E24) -> #DIV/0! | V24: % Change in Revenues
B25: Intangible Assets | O25: =AVERAGE(C25:M25) -> #DIV/0! | P25: =AVERAGE(C25:G25) -> #DIV/0! | Q25: =AVERAGE(C25:E25) -> #DIV/0! | S25: - - | T25: - - | V25: Growing with Amortization
B26: CAPEX | C26: =Inputs!B65/Inputs!B6 -> -0.024074074 | D26: =Inputs!C65/Inputs!C6 -> -0.019066989 | E26: =Inputs!D65/Inputs!D6 -> -0.018315687 | F26: =Inputs!E65/Inputs!E6 -> -0.030113695 | G26: =Inputs!F65/Inputs!F6 -> -0.032238895 | H26: =Inputs!G65/Inputs!G6 -> -0.025173745 | I26: =Inputs!H65/Inputs!H6 -> -0.021511517 | J26: =Inputs!I65/Inputs!I6 -> -0.018024345 | ... M26: =Inputs!L65/Inputs!L6 -> -0.015852048 | O26: =AVERAGE(C26:M26) -> -0.022334456 | P26: =AVERAGE(C26:G26) -> -0.024761868 | Q26: =AVERAGE(C26:E26) -> -0.020485583 | V26: % Revenue
B27: Acquisition factor | C27: =Inputs!B66/Inputs!B6 -> -0.038183422 | D27: =Inputs!C66/Inputs!C6 -> 0.10444473 | E27: =Inputs!D66/Inputs!D6 -> -0.023001095 | F27: =Inputs!E66/Inputs!E6 -> -0.067397316 | G27: =Inputs!F66/Inputs!F6 -> 0.0060912197 | H27: =Inputs!G66/Inputs!G6 -> -0.012046332 | I27: =Inputs!H66/Inputs!H6 -> 0.00019036741 | J27: =Inputs!I66/Inputs!I6 -> 0.08005618 | ... M27: =Inputs!L66/Inputs!L6 -> 0.10171731 | O27: =AVERAGE(C27:M27) -> 0.020712099 | P27: =AVERAGE(C27:G27) -> -0.0036091773 | Q27: =AVERAGE(C27:E27) -> 0.01442007 | V27: % Revenue
B28: Dividends | C28: =Inputs!B73/Inputs!B6 -> 0 | D28: =Inputs!C73/Inputs!C6 -> 0 | E28: =Inputs!D73/Inputs!D6 -> 0 | F28: =Inputs!E73/Inputs!E6 -> 0 | G28: =Inputs!F73/Inputs!F6 -> 0 | H28: =Inputs!G73/Inputs!G6 -> 0 | I28: =Inputs!H73/Inputs!H6 -> 0 | J28: =Inputs!I73/Inputs!I6 -> 0 | ... M28: =Inputs!L73/Inputs!L6 -> 0 | O28: =AVERAGE(C28:M28) -> 0 | P28: =AVERAGE(C28:G28) -> 0 | Q28: =AVERAGE(C28:E28) -> 0 | V28: % Net Income
B29: Repurchases | C29: =Inputs!B74/Inputs!B6 -> -0.043430335 | D29: =Inputs!C74/Inputs!C6 -> -0.15685776 | E29: =Inputs!D74/Inputs!D6 -> -0.10721675 | F29: =Inputs!E74/Inputs!E6 -> 0 | G29: =Inputs!F74/Inputs!F6 -> 0 | H29: =Inputs!G74/Inputs!G6 -> 0 | I29: =Inputs!H74/Inputs!H6 -> 0 | J29: =Inputs!I74/Inputs!I6 -> 0 | ... M29: =Inputs!L74/Inputs!L6 -> 0 | O29: =AVERAGE(C29:M29) -> -0.027954986 | P29: =AVERAGE(C29:G29) -> -0.061500968 | Q29: =AVERAGE(C29:E29) -> -0.10250161 | V29: % Net Income
B30: Leases | O30: =AVERAGE(C30:M30) -> #DIV/0! | P30: =AVERAGE(C30:G30) -> #DIV/0! | Q30: =AVERAGE(C30:E30) -> #DIV/0! | V30: % Revenue
B31: Total Debt | C31: ='Fin. Data'!B58/'Fin. Data'!B19 -> 0.58554342 | D31: ='Fin. Data'!C58/'Fin. Data'!C19 -> 0.52832626 | E31: ='Fin. Data'!D58/'Fin. Data'!D19 -> 0.086300692 | F31: ='Fin. Data'!E58/'Fin. Data'!E19 -> 0.3271719 | G31: ='Fin. Data'!F58/'Fin. Data'!F19 -> 1.0269865 | H31: ='Fin. Data'!G58/'Fin. Data'!G19 -> 1.9936204 | I31: ='Fin. Data'!H58/'Fin. Data'!H19 -> -1.6145833 | J31: ='Fin. Data'!I58/'Fin. Data'!I19 -> -3.2466063 | ... M31: ='Fin. Data'!L58/'Fin. Data'!L19 -> 6.0529412 | O31: =AVERAGE(C31:M31) -> -25.266379 | P31: =AVERAGE(C31:G31) -> 0.51086576 | Q31: =AVERAGE(C31:E31) -> 0.40005679 | V31: % EBITDA
B40: Year | C40: Market Value | D40: YoY Growth | F40: Year | G40: Revenue Projections | H40: YoY Growth | I40: Market Share | J40: Market Share Growth | K40: Outperformance
B41: 2016 | F41: 2016
B42: 2017 | F42: 2017
B43: 2018 | F43: 2018
B44: 2019 | F44: 2019
B45: 2020 | F45: 2020
B46: 2021 | F46: 2021
B47: 2022 | F47: 2022
B48: 2023 | F48: 2023
B49: 2024E | F49: 2024E (guidence)
B50: 2025E | F50: 2025E
B51: 2026E | F51: 2026E
B52: 2027E | F52: 2027E
B53: 2028E | F53: 2028E
B54: 2029E | F54: 2029E
B55: 2030E | F55: 2030E
B56: 2031E | F56: 2031E
B57: 2032E | F57: 2032E
B58: 2033E | F58: 2033E
B59: 2034E | F59: 2034E
B60: 2035E | F60: 2035E
... B73: 2048E | F73: 2048E
W106: Historical Data | AA106: Averages | AB106: Short-term | AF106: Medium-term | AK106: Long-term
W107: 2020 | X107: 2021 | Y107: 2022 | Z107: 2023 | AB107: 2024 | AC107: 2025 | AD107: 2026 | AE107: 2027 | AF107: 2028 | AG107: 2029 | AH107: 2030 | AI107: 2031 | AJ107: 2032 | AK107: 2033 | AL107: 2034 | AM107: 2035 | AN107: 2036 | AO107: 2037 | AP107: 2038 | AQ107: 2039 | AR107: 2040 | AS107: 2041 | AT107: 2042 | AU107: 2043 | AV107: 2044 | AW107: 2045 | AX107: 2046 | AY107: 2047 | AZ107: 2048
V108: Revenue
V109: COGS
V110: % of revenue
V111: Gross Profit
V112: % of revenue
V113: Sales and marketing
V114: % of revenue
V115: R&D
V116: % of revenue
V117: General and admin
V118: % of revenue
V119: Operating expenses
... V122: % of revenue
B127: Tax Rate | D127: 2023 | E127: 2022 | F127: 2021 | G127: 2020 | H127: 2019 | I127: 4Y Average | L127: Amortization factor | N127: 2023 | O127: 2022 | P127: 2021 | Q127: 2020 | R127: 2019 | S127: 4Y Average
B128: Net income | L128: Amortization
B129: Tax | L129: Gross intangible assets
B130: Effective Tax Rate | L130: Gross Developed technology
L131: Gross Developed technology/Gross intangible assets
L132: Amortization/gross intangible assets
L133: Revenue
L134: Ratio average
C142: Historical Data | G142: Averages | H142: Short-term | L142: Medium-term | Q142: Long-term
C143: 2020 | D143: 2021 | E143: 2022 | F143: 2023 | H143: 2024 | I143: 2025 | J143: 2026 | K143: 2027 | L143: 2028 | M143: 2029 | N143: 2030 | O143: 2031 | P143: 2032 | Q143: 2033 | R143: 2034 | S143: 2035 | T143: 2036 | U143: 2037 | V143: 2038 | W143: 2039 | X143: 2040 | Y143: 2041 | Z143: 2042 | AA143: 2043 | AB143: 2044 | AC143: 2045 | AD143: 2046 | AE143: 2047 | AF143: 2048
B144: Revenue
B145: Growth
B146: Changes in Operating assets and liabilities
B147: Accounts receivables
B148: % of revenue
B149: Deferred costs
B150: % of revenue
B151: Prepaids and other
B152: % of revenue
B153: Accounts payable
B154: % of revenue
B155: Accrued expenses
... B165: % of changes in revenue
B169: Depreciation factor | D169: 2023 | E169: 2022 | F169: 2021 | G169: 2020 | H169: 2019 | I169: 2018
B170: Depreciation
B171: Gross PPE
B172: Account with heighest weight
B173: Net PPE
B174: Net Hardware as % of net PPE
B175: Dep/Gross PPE ratio

Sheet Fin. Data
A1: =Inputs!H3 -> #VALUE!
A2: =Inputs!G2 -> Figures in Millions of USD
A3: Results
B4: =OP!J20 -> 2023 | C4: =B4-1 -> 2022 | D4: =C4-1 -> 2021 | E4: =D4-1 -> 2020 | F4: =E4-1 -> 2019 | G4: =F4-1 -> 2018 | H4: =G4-1 -> 2017 | I4: =H4-1 -> 2016 | J4: =I4-1 -> 2015 | ... M4: =L4-1 -> 2012
A5: Net Sales | B5: =_xlfn.XLOOKUP($A5,Inputs!$A:$A,Inputs!B:B,,0) -> 22680 | C5: =_xlfn.XLOOKUP($A5,Inputs!$A:$A,Inputs!C:C,,0) -> 23601 | D5: =_xlfn.XLOOKUP($A5,Inputs!$A:$A,Inputs!D:D,,0) -> 16434 | E5: =_xlfn.XLOOKUP($A5,Inputs!$A:$A,Inputs!E:E,,0) -> 9763 | F5: =_xlfn.XLOOKUP($A5,Inputs!$A:$A,Inputs!F:F,,0) -> 6731 | G5: =_xlfn.XLOOKUP($A5,Inputs!$A:$A,Inputs!G:G,,0) -> 6475 | H5: =_xlfn.XLOOKUP($A5,Inputs!$A:$A,Inputs!H:H,,0) -> 5253 | I5: =_xlfn.XLOOKUP($A5,Inputs!$A:$A,Inputs!I:I,,0) -> 4272 | J5: =_xlfn.XLOOKUP($A5,Inputs!$A:$A,Inputs!J:J,,0) -> 3991 | K5: =_xlfn.XLOOKUP($A5,Inputs!$A:$A,Inputs!K:K,,0) -> 5506 | L5: =_xlfn.XLOOKUP($A5,Inputs!$A:$A,Inputs!L:L,,0) -> 5299 | M5: =_xlfn.XLOOKUP($A5,Inputs!$A:$A,Inputs!M:M,,0) -> 5422
A6: Growth vs. Previous year | B6: =IFERROR(B5/C5-1,"-") -> -0.03902377 | C6: =IFERROR(C5/D5-1,"-") -> 0.43610807 | D6: =IFERROR(D5/E5-1,"-") -> 0.68329407 | E6: =IFERROR(E5/F5-1,"-") -> 0.45045313 | F6: =IFERROR(F5/G5-1,"-") -> 0.03953668 | G6: =IFERROR(G5/H5-1,"-") -> 0.23262897 | H6: =IFERROR(H5/I5-1,"-") -> 0.22963483 | I6: =IFERROR(I5/J5-1,"-") -> 0.070408419 | ... L6: =IFERROR(L5/M5-1,"-") -> -0.022685356 | M6: =IFERROR(M5/#REF!-1,"-") -> -
A7: Gross Profit | B7: =_xlfn.XLOOKUP($A7,Inputs!$A:$A,Inputs!B:B,,0) -> 10460 | C7: =_xlfn.XLOOKUP($A7,Inputs!$A:$A,Inputs!C:C,,0) -> 10603 | D7: =_xlfn.XLOOKUP($A7,Inputs!$A:$A,Inputs!D:D,,0) -> 7929 | E7: =_xlfn.XLOOKUP($A7,Inputs!$A:$A,Inputs!E:E,,0) -> 4347 | F7: =_xlfn.XLOOKUP($A7,Inputs!$A:$A,Inputs!F:F,,0) -> 2868 | G7: =_xlfn.XLOOKUP($A7,Inputs!$A:$A,Inputs!G:G,,0) -> 2447 | H7: =_xlfn.XLOOKUP($A7,Inputs!$A:$A,Inputs!H:H,,0) -> 1787 | I7: =_xlfn.XLOOKUP($A7,Inputs!$A:$A,Inputs!I:I,,0) -> 998 | J7: =_xlfn.XLOOKUP($A7,Inputs!$A:$A,Inputs!J:J,,0) -> 1080 | K7: =_xlfn.XLOOKUP($A7,Inputs!$A:$A,Inputs!K:K,,0) -> 1839 | L7: =_xlfn.XLOOKUP($A7,Inputs!$A:$A,Inputs!L:L,,0) -> 1978 | M7: =_xlfn.XLOOKUP($A7,Inputs!$A:$A,Inputs!M:M,,0) -> 1235
A8: % over sales | B8: =IFERROR(B7/B$5,"-") -> 0.46119929 | C8: =IFERROR(C7/C$5,"-") -> 0.44926062 | D8: =IFERROR(D7/D$5,"-") -> 0.48247536 | E8: =IFERROR(E7/E$5,"-") -> 0.44525248 | F8: =IFERROR(F7/F$5,"-") -> 0.42608825 | G8: =IFERROR(G7/G$5,"-") -> 0.37791506 | H8: =IFERROR(H7/H$5,"-") -> 0.34018656 | I8: =IFERROR(I7/I$5,"-") -> 0.23361423 | ... M8: =IFERROR(M7/M$5,"-") -> 0.22777573
A9: Operating expenses | B9: =B5-B11 -> 22279 | C9: =C5-C11 -> 22337 | D9: =D5-D11 -> 12793 | E9: =E5-E11 -> 8448 | F9: =F5-F11 -> 6276 | G9: =G5-G11 -> 6036 | H9: =H5-H11 -> 5138 | I9: =I5-I11 -> 4712 | ... M9: =M5-M11 -> 6482
A10: % over sales | B10: =IFERROR(B9/B$5,"-") -> 0.98231922 | C10: =IFERROR(C9/C$5,"-") -> 0.94644295 | D10: =IFERROR(D9/D$5,"-") -> 0.77844712 | E10: =IFERROR(E9/E$5,"-") -> 0.86530779 | F10: =IFERROR(F9/F$5,"-") -> 0.93240232 | G10: =IFERROR(G9/G$5,"-") -> 0.93220077 | H10: =IFERROR(H9/H$5,"-") -> 0.97810775 | I10: =IFERROR(I9/I$5,"-") -> 1.1029963 | ... M10: =IFERROR(M9/M$5,"-") -> 1.1954998
A11: Operating Income | B11: =_xlfn.XLOOKUP($A11,Inputs!$A:$A,Inputs!B:B,,0) -> 401 | C11: =_xlfn.XLOOKUP($A11,Inputs!$A:$A,Inputs!C:C,,0) -> 1264 | D11: =_xlfn.XLOOKUP($A11,Inputs!$A:$A,Inputs!D:D,,0) -> 3641 | E11: =_xlfn.XLOOKUP($A11,Inputs!$A:$A,Inputs!E:E,,0) -> 1315 | F11: =_xlfn.XLOOKUP($A11,Inputs!$A:$A,Inputs!F:F,,0) -> 455 | G11: =_xlfn.XLOOKUP($A11,Inputs!$A:$A,Inputs!G:G,,0) -> 439 | H11: =_xlfn.XLOOKUP($A11,Inputs!$A:$A,Inputs!H:H,,0) -> 115 | I11: =_xlfn.XLOOKUP($A11,Inputs!$A:$A,Inputs!I:I,,0) -> -440 | J11: =_xlfn.XLOOKUP($A11,Inputs!$A:$A,Inputs!J:J,,0) -> -481 | K11: =_xlfn.XLOOKUP($A11,Inputs!$A:$A,Inputs!K:K,,0) -> -216 | L11: =_xlfn.XLOOKUP($A11,Inputs!$A:$A,Inputs!L:L,,0) -> 102 | M11: =_xlfn.XLOOKUP($A11,Inputs!$A:$A,Inputs!M:M,,0) -> -1060
A12: Operating Margin | B12: =IFERROR(B11/B$5,"-") -> 0.017680776 | C12: =IFERROR(C11/C$5,"-") -> 0.053557053 | D12: =IFERROR(D11/D$5,"-") -> 0.22155288 | E12: =IFERROR(E11/E$5,"-") -> 0.13469221 | F12: =IFERROR(F11/F$5,"-") -> 0.067597682 | G12: =IFERROR(G11/G$5,"-") -> 0.067799228 | H12: =IFERROR(H11/H$5,"-") -> 0.021892252 | I12: =IFERROR(I11/I$5,"-") -> -0.10299625 | ... M12: =IFERROR(M11/M$5,"-") -> -0.19549982
A13: Growth vs. Previous year | B13: =IFERROR(B12/C12-1,"-") -> -0.66987026 | C13: =IFERROR(C12/D12-1,"-") -> -0.75826515 | D13: =IFERROR(D12/E12-1,"-") -> 0.6448827 | E13: =IFERROR(E12/F12-1,"-") -> 0.99255656 | F13: =IFERROR(F12/G12-1,"-") -> -0.0029726804 | G13: =IFERROR(G12/H12-1,"-") -> 2.0969508 | H13: =IFERROR(H12/I12-1,"-") -> -1.2125539 | I13: =IFERROR(I12/J12-1,"-") -> -0.14540945 | ... L13: =IFERROR(L12/M12-1,"-") -> -1.09846 | M13: =IFERROR(M12/#REF!-1,"-") -> -
A14: Net Financial Cost | B14: =_xlfn.XLOOKUP($A14,Inputs!$A:$A,Inputs!B:B,,0) -> 99 | C14: =_xlfn.XLOOKUP($A14,Inputs!$A:$A,Inputs!C:C,,0) -> -85 | D14: =_xlfn.XLOOKUP($A14,Inputs!$A:$A,Inputs!D:D,,0) -> 30 | E14: =_xlfn.XLOOKUP($A14,Inputs!$A:$A,Inputs!E:E,,0) -> -39 | F14: =_xlfn.XLOOKUP($A14,Inputs!$A:$A,Inputs!F:F,,0) -> -80 | G14: =_xlfn.XLOOKUP($A14,Inputs!$A:$A,Inputs!G:G,,0) -> -106 | H14: =_xlfn.XLOOKUP($A14,Inputs!$A:$A,Inputs!H:H,,0) -> -123 | I14: =_xlfn.XLOOKUP($A14,Inputs!$A:$A,Inputs!I:I,,0) -> -153 | J14: =_xlfn.XLOOKUP($A14,Inputs!$A:$A,Inputs!J:J,,0) -> -163 | K14: =_xlfn.XLOOKUP($A14,Inputs!$A:$A,Inputs!K:K,,0) -> -177 | L14: =_xlfn.XLOOKUP($A14,Inputs!$A:$A,Inputs!L:L,,0) -> -174 | M14: =_xlfn.XLOOKUP($A14,Inputs!$A:$A,Inputs!M:M,,0) -> -167
A15: Other Expenses (Revenues) | B15: =_xlfn.XLOOKUP($A15,Inputs!$A:$A,Inputs!B:B,,0) -> 8 | C15: =_xlfn.XLOOKUP($A15,Inputs!$A:$A,Inputs!C:C,,0) -> 19 | D15: =_xlfn.XLOOKUP($A15,Inputs!$A:$A,Inputs!D:D,,0) -> 4 | E15: =_xlfn.XLOOKUP($A15,Inputs!$A:$A,Inputs!E:E,,0) -> 4 | F15: =_xlfn.XLOOKUP($A15,Inputs!$A:$A,Inputs!F:F,,0) -> 10 | G15: =_xlfn.XLOOKUP($A15,Inputs!$A:$A,Inputs!G:G,,0) -> -18 | H15: =_xlfn.XLOOKUP($A15,Inputs!$A:$A,Inputs!H:H,,0) -> 1123 | I15: =_xlfn.XLOOKUP($A15,Inputs!$A:$A,Inputs!I:I,,0) -> 135 | J15: =_xlfn.XLOOKUP($A15,Inputs!$A:$A,Inputs!J:J,,0) -> -2 | K15: =_xlfn.XLOOKUP($A15,Inputs!$A:$A,Inputs!K:K,,0) -> -5 | L15: =_xlfn.XLOOKUP($A15,Inputs!$A:$A,Inputs!L:L,,0) -> -2 | M15: =_xlfn.XLOOKUP($A15,Inputs!$A:$A,Inputs!M:M,,0) -> 10
A16: EBIT | B16: =B11-B15 -> 393 | C16: =C11-C15 -> 1245 | D16: =D11-D15 -> 3637 | E16: =E11-E15 -> 1311 | F16: =F11-F15 -> 445 | G16: =G11-G15 -> 457 | H16: =H11-H15 -> -1008 | I16: =I11-I15 -> -575 | ... M16: =M11-M15 -> -1070
A17: Depreciation & Amortization | B17: =_xlfn.XLOOKUP($A17,Inputs!$A:$A,Inputs!B:B,,0) -> 3453 | C17: =_xlfn.XLOOKUP($A17,Inputs!$A:$A,Inputs!C:C,,0) -> 4174 | D17: =_xlfn.XLOOKUP($A17,Inputs!$A:$A,Inputs!D:D,,0) -> 407 | E17: =_xlfn.XLOOKUP($A17,Inputs!$A:$A,Inputs!E:E,,0) -> 312 | F17: =_xlfn.XLOOKUP($A17,Inputs!$A:$A,Inputs!F:F,,0) -> 222 | G17: =_xlfn.XLOOKUP($A17,Inputs!$A:$A,Inputs!G:G,,0) -> 170 | H17: =_xlfn.XLOOKUP($A17,Inputs!$A:$A,Inputs!H:H,,0) -> 144 | I17: =_xlfn.XLOOKUP($A17,Inputs!$A:$A,Inputs!I:I,,0) -> 133 | J17: =_xlfn.XLOOKUP($A17,Inputs!$A:$A,Inputs!J:J,,0) -> 167 | K17: =_xlfn.XLOOKUP($A17,Inputs!$A:$A,Inputs!K:K,,0) -> 203 | L17: =_xlfn.XLOOKUP($A17,Inputs!$A:$A,Inputs!L:L,,0) -> 236 | M17: =_xlfn.XLOOKUP($A17,Inputs!$A:$A,Inputs!M:M,,0) -> 260
A18: Changes Net Working Capital | B18: =_xlfn.XLOOKUP($A18,Inputs!$A:$A,Inputs!B:B,,0) -> 2331 | C18: =_xlfn.XLOOKUP($A18,Inputs!$A:$A,Inputs!C:C,,0) -> 2007 | D18: =_xlfn.XLOOKUP($A18,Inputs!$A:$A,Inputs!D:D,,0) -> -323 | E18: =_xlfn.XLOOKUP($A18,Inputs!$A:$A,Inputs!E:E,,0) -> 1359 | F18: =_xlfn.XLOOKUP($A18,Inputs!$A:$A,Inputs!F:F,,0) -> 294 | G18: =_xlfn.XLOOKUP($A18,Inputs!$A:$A,Inputs!G:G,,0) -> 542 | H18: =_xlfn.XLOOKUP($A18,Inputs!$A:$A,Inputs!H:H,,0) -> 16 | I18: =_xlfn.XLOOKUP($A18,Inputs!$A:$A,Inputs!I:I,,0) -> -212 | J18: =_xlfn.XLOOKUP($A18,Inputs!$A:$A,Inputs!J:J,,0) -> -359 | K18: =_xlfn.XLOOKUP($A18,Inputs!$A:$A,Inputs!K:K,,0) -> 94 | L18: =_xlfn.XLOOKUP($A18,Inputs!$A:$A,Inputs!L:L,,0) -> 78 | M18: =_xlfn.XLOOKUP($A18,Inputs!$A:$A,Inputs!M:M,,0) -> 319
A19: EBITDA | B19: =B11-B15+B17 -> 3846 | C19: =C11-C15+C17 -> 5419 | D19: =D11-D15+D17 -> 4044 | E19: =E11-E15+E17 -> 1623 | F19: =F11-F15+F17 -> 667 | G19: =G11-G15+G17 -> 627 | H19: =H11-H15+H17 -> -864 | I19: =I11-I15+I17 -> -442 | ... M19: =M11-M15+M17 -> -810
A20: EBITDA Margin | B20: =IFERROR(B19/B$5,"-") -> 0.16957672 | C20: =IFERROR(C19/C$5,"-") -> 0.22960891 | D20: =IFERROR(D19/D$5,"-") -> 0.24607521 | E20: =IFERROR(E19/E$5,"-") -> 0.16623989 | F20: =IFERROR(F19/F$5,"-") -> 0.099093745 | G20: =IFERROR(G19/G$5,"-") -> 0.096833977 | H20: =IFERROR(H19/H$5,"-") -> -0.16447744 | I20: =IFERROR(I19/I$5,"-") -> -0.10346442 | ... M20: =IFERROR(M19/M$5,"-") -> -0.14939137
A21: Taxes | B21: =_xlfn.XLOOKUP($A21,Inputs!$A:$A,Inputs!B:B,,0) -> 346 | C21: =_xlfn.XLOOKUP($A21,Inputs!$A:$A,Inputs!C:C,,0) -> 122 | D21: =_xlfn.XLOOKUP($A21,Inputs!$A:$A,Inputs!D:D,,0) -> -513 | E21: =_xlfn.XLOOKUP($A21,Inputs!$A:$A,Inputs!E:E,,0) -> 1210 | F21: =_xlfn.XLOOKUP($A21,Inputs!$A:$A,Inputs!F:F,,0) -> -44 | G21: =_xlfn.XLOOKUP($A21,Inputs!$A:$A,Inputs!G:G,,0) -> 22 | H21: =_xlfn.XLOOKUP($A21,Inputs!$A:$A,Inputs!H:H,,0) -> -1148 | I21: =_xlfn.XLOOKUP($A21,Inputs!$A:$A,Inputs!I:I,,0) -> -39 | J21: =_xlfn.XLOOKUP($A21,Inputs!$A:$A,Inputs!J:J,,0) -> -14 | K21: =_xlfn.XLOOKUP($A21,Inputs!$A:$A,Inputs!K:K,,0) -> -5 | L21: =_xlfn.XLOOKUP($A21,Inputs!$A:$A,Inputs!L:L,,0) -> -9 | M21: =_xlfn.XLOOKUP($A21,Inputs!$A:$A,Inputs!M:M,,0) -> 34
A22: % Tax | B22: =IFERROR(B21/B$5,"-") -> 0.015255732 | C22: =IFERROR(C21/C$5,"-") -> 0.0051692725 | D22: =IFERROR(D21/D$5,"-") -> -0.031215772 | E22: =IFERROR(E21/E$5,"-") -> 0.12393731 | F22: =IFERROR(F21/F$5,"-") -> -0.0065369187 | G22: =IFERROR(G21/G$5,"-") -> 0.0033976834 | H22: =IFERROR(H21/H$5,"-") -> -0.21854179 | I22: =IFERROR(I21/I$5,"-") -> -0.0091292135 | ... M22: =IFERROR(M21/M$5,"-") -> 0.0062707488
A23: Net Income | B23: =_xlfn.XLOOKUP($A23,Inputs!$A:$A,Inputs!B:B,,0) -> 854 | C23: =_xlfn.XLOOKUP($A23,Inputs!$A:$A,Inputs!C:C,,0) -> 1320 | D23: =_xlfn.XLOOKUP($A23,Inputs!$A:$A,Inputs!D:D,,0) -> 3162 | E23: =_xlfn.XLOOKUP($A23,Inputs!$A:$A,Inputs!E:E,,0) -> 2490 | F23: =_xlfn.XLOOKUP($A23,Inputs!$A:$A,Inputs!F:F,,0) -> 341 | G23: =_xlfn.XLOOKUP($A23,Inputs!$A:$A,Inputs!G:G,,0) -> 337 | H23: =_xlfn.XLOOKUP($A23,Inputs!$A:$A,Inputs!H:H,,0) -> -33 | I23: =_xlfn.XLOOKUP($A23,Inputs!$A:$A,Inputs!I:I,,0) -> -497 | J23: =_xlfn.XLOOKUP($A23,Inputs!$A:$A,Inputs!J:J,,0) -> -660 | K23: =_xlfn.XLOOKUP($A23,Inputs!$A:$A,Inputs!K:K,,0) -> -403 | L23: =_xlfn.XLOOKUP($A23,Inputs!$A:$A,Inputs!L:L,,0) -> -83 | M23: =_xlfn.XLOOKUP($A23,Inputs!$A:$A,Inputs!M:M,,0) -> -1183
A24: Net Income Margin | B24: =IFERROR(B23/B$5,"-") -> 0.037654321 | C24: =IFERROR(C23/C$5,"-") -> 0.055929833 | D24: =IFERROR(D23/D$5,"-") -> 0.19240599 | E24: =IFERROR(E23/E$5,"-") -> 0.25504456 | F24: =IFERROR(F23/F$5,"-") -> 0.05066112 | G24: =IFERROR(G23/G$5,"-") -> 0.052046332 | H24: =IFERROR(H23/H$5,"-") -> -0.0062821245 | I24: =IFERROR(I23/I$5,"-") -> -0.11633895 | ... M24: =IFERROR(M23/M$5,"-") -> -0.21818517
A25: Growth vs. Previous year | B25: =IFERROR(B24/C24-1,"-") -> -0.32675786 | C25: =IFERROR(C24/D24-1,"-") -> -0.70931345 | D25: =IFERROR(D24/E24-1,"-") -> -0.24559853 | E25: =IFERROR(E24/F24-1,"-") -> 4.0343252 | F25: =IFERROR(F24/G24-1,"-") -> -0.026614976 | G25: =IFERROR(G24/H24-1,"-") -> -9.2848298 | H25: =IFERROR(H24/I24-1,"-") -> -0.94600154 | I25: =IFERROR(I24/J24-1,"-") -> -0.29650189 | ... L25: =IFERROR(L24/M24-1,"-") -> -0.92821083 | M25: =IFERROR(M24/#REF!-1,"-") -> -
A26: Cash Generated | B26: =B39-C39 -> -902 | C26: =C39-D39 -> 2300 | D26: =D39-E39 -> 940 | E26: =E39-F39 -> 129 | F26: =F39-G39 -> 388 | G26: =G39-H39 -> -107 | H26: =H39-I39 -> -79 | I26: =I39-J39 -> 479 | ... M26: =M39-N39 -> 549
A27: Dividends | B27: =_xlfn.XLOOKUP($A27,Inputs!$A:$A,Inputs!B:B,,0) -> 0 | C27: =_xlfn.XLOOKUP($A27,Inputs!$A:$A,Inputs!C:C,,0) -> 0 | D27: =_xlfn.XLOOKUP($A27,Inputs!$A:$A,Inputs!D:D,,0) -> 0 | E27: =_xlfn.XLOOKUP($A27,Inputs!$A:$A,Inputs!E:E,,0) -> 0 | F27: =_xlfn.XLOOKUP($A27,Inputs!$A:$A,Inputs!F:F,,0) -> 0 | G27: =_xlfn.XLOOKUP($A27,Inputs!$A:$A,Inputs!G:G,,0) -> 0 | H27: =_xlfn.XLOOKUP($A27,Inputs!$A:$A,Inputs!H:H,,0) -> 0 | I27: =_xlfn.XLOOKUP($A27,Inputs!$A:$A,Inputs!I:I,,0) -> 0 | J27: =_xlfn.XLOOKUP($A27,Inputs!$A:$A,Inputs!J:J,,0) -> 0 | K27: =_xlfn.XLOOKUP($A27,Inputs!$A:$A,Inputs!K:K,,0) -> 0 | L27: =_xlfn.XLOOKUP($A27,Inputs!$A:$A,Inputs!L:L,,0) -> 0 | M27: =_xlfn.XLOOKUP($A27,Inputs!$A:$A,Inputs!M:M,,0) -> 0
A28: Share buyback | B28: =_xlfn.XLOOKUP($A28,Inputs!$A:$A,Inputs!B:B,,0) -> -985 | C28: =_xlfn.XLOOKUP($A28,Inputs!$A:$A,Inputs!C:C,,0) -> -3702 | D28: =_xlfn.XLOOKUP($A28,Inputs!$A:$A,Inputs!D:D,,0) -> -1762 | E28: =_xlfn.XLOOKUP($A28,Inputs!$A:$A,Inputs!E:E,,0) -> 0 | F28: =_xlfn.XLOOKUP($A28,Inputs!$A:$A,Inputs!F:F,,0) -> 0 | G28: =_xlfn.XLOOKUP($A28,Inputs!$A:$A,Inputs!G:G,,0) -> 0 | H28: =_xlfn.XLOOKUP($A28,Inputs!$A:$A,Inputs!H:H,,0) -> 0 | I28: =_xlfn.XLOOKUP($A28,Inputs!$A:$A,Inputs!I:I,,0) -> 0 | J28: =_xlfn.XLOOKUP($A28,Inputs!$A:$A,Inputs!J:J,,0) -> 0 | K28: =_xlfn.XLOOKUP($A28,Inputs!$A:$A,Inputs!K:K,,0) -> 0 | L28: =_xlfn.XLOOKUP($A28,Inputs!$A:$A,Inputs!L:L,,0) -> 0 | M28: =_xlfn.XLOOKUP($A28,Inputs!$A:$A,Inputs!M:M,,0) -> 0
A29: Net Cash Flow | B29: =SUM(B26:B28) -> -1887 | C29: =SUM(C26:C28) -> -1402 | D29: =SUM(D26:D28) -> -822 | E29: =SUM(E26:E28) -> 129 | F29: =SUM(F26:F28) -> 388 | G29: =SUM(G26:G28) -> -107 | H29: =SUM(H26:H28) -> -79 | I29: =SUM(I26:I28) -> 479 | ... M29: =SUM(M26:M28) -> 549
A30: FNP'' | B30: =+B29-(B58-C29) -> -5541 | C30: =+C29-(C58-D29) -> -5087 | D30: =+D29-(D58-E29) -> -1042 | E30: =+E29-(E58-F29) -> -14 | F30: =+F29-(F58-G29) -> -404 | G30: =+G29-(G58-H29) -> -1436 | H30: =+H29-(H58-I29) -> -995 | I30: =+I29-(I58-J29) -> -976 | ... M30: =+M29-(M58-N29) -> -1488
A31: FNP' | B31: =+B30+B33 -> -6407 | C31: =+C30+C33 -> -2622 | D31: =+D30+D33 -> -1420 | E31: =+E30+E33 -> -672 | F31: =+F30+F33 -> -363 | G31: =+G30+G33 -> -1514 | H31: =+H30+H33 -> -994 | I31: =+I30+I33 -> -634 | ... M31: =+M30+M33 -> -1365
A32: Net Capex | B32: =_xlfn.XLOOKUP($A32,Inputs!$A:$A,Inputs!B:B,,0) -> -546 | C32: =_xlfn.XLOOKUP($A32,Inputs!$A:$A,Inputs!C:C,,0) -> -450 | D32: =_xlfn.XLOOKUP($A32,Inputs!$A:$A,Inputs!D:D,,0) -> -301 | E32: =_xlfn.XLOOKUP($A32,Inputs!$A:$A,Inputs!E:E,,0) -> -294 | F32: =_xlfn.XLOOKUP($A32,Inputs!$A:$A,Inputs!F:F,,0) -> -217 | G32: =_xlfn.XLOOKUP($A32,Inputs!$A:$A,Inputs!G:G,,0) -> -163 | H32: =_xlfn.XLOOKUP($A32,Inputs!$A:$A,Inputs!H:H,,0) -> -113 | I32: =_xlfn.XLOOKUP($A32,Inputs!$A:$A,Inputs!I:I,,0) -> -77 | J32: =_xlfn.XLOOKUP($A32,Inputs!$A:$A,Inputs!J:J,,0) -> -96 | K32: =_xlfn.XLOOKUP($A32,Inputs!$A:$A,Inputs!K:K,,0) -> -95 | L32: =_xlfn.XLOOKUP($A32,Inputs!$A:$A,Inputs!L:L,,0) -> -84 | M32: =_xlfn.XLOOKUP($A32,Inputs!$A:$A,Inputs!M:M,,0) -> -133
A33: Investments & Acquisitions | B33: =_xlfn.XLOOKUP($A33,Inputs!$A:$A,Inputs!B:B,,0) -> -866 | C33: =_xlfn.XLOOKUP($A33,Inputs!$A:$A,Inputs!C:C,,0) -> 2465 | D33: =_xlfn.XLOOKUP($A33,Inputs!$A:$A,Inputs!D:D,,0) -> -378 | E33: =_xlfn.XLOOKUP($A33,Inputs!$A:$A,Inputs!E:E,,0) -> -658 | F33: =_xlfn.XLOOKUP($A33,Inputs!$A:$A,Inputs!F:F,,0) -> 41 | G33: =_xlfn.XLOOKUP($A33,Inputs!$A:$A,Inputs!G:G,,0) -> -78 | H33: =_xlfn.XLOOKUP($A33,Inputs!$A:$A,Inputs!H:H,,0) -> 1 | I33: =_xlfn.XLOOKUP($A33,Inputs!$A:$A,Inputs!I:I,,0) -> 342 | J33: =_xlfn.XLOOKUP($A33,Inputs!$A:$A,Inputs!J:J,,0) -> 243 | K33: =_xlfn.XLOOKUP($A33,Inputs!$A:$A,Inputs!K:K,,0) -> 83 | L33: =_xlfn.XLOOKUP($A33,Inputs!$A:$A,Inputs!L:L,,0) -> 539 | M33: =_xlfn.XLOOKUP($A33,Inputs!$A:$A,Inputs!M:M,,0) -> 123
A34: Capex + Investments | B34: =+B32+B33 -> -1412 | C34: =+C32+C33 -> 2015 | D34: =+D32+D33 -> -679 | E34: =+E32+E33 -> -952 | F34: =+F32+F33 -> -176 | G34: =+G32+G33 -> -241 | H34: =+H32+H33 -> -112 | I34: =+I32+I33 -> 265 | ... M34: =+M32+M33 -> -10
A35: Dividends + Share Buyback | B35: =+B27+B28 -> -985 | C35: =+C27+C28 -> -3702 | D35: =+D27+D28 -> -1762 | E35: =+E27+E28 -> 0 | F35: =+F27+F28 -> 0 | G35: =+G27+G28 -> 0 | H35: =+H27+H28 -> 0 | I35: =+I27+I28 -> 0 | ... M35: =+M27+M28 -> 0
A36: Payout Ratio | B36: =IFERROR(B35/B23,"-") -> -1.1533958 | C36: =IFERROR(C35/C23,"-") -> -2.8045455 | D36: =IFERROR(D35/D23,"-") -> -0.55724225 | E36: =IFERROR(E35/E23,"-") -> 0 | F36: =IFERROR(F35/F23,"-") -> 0 | G36: =IFERROR(G35/G23,"-") -> 0 | H36: =IFERROR(H35/H23,"-") -> 0 | I36: =IFERROR(I35/I23,"-") -> 0 | ... M36: =IFERROR(M35/M23,"-") -> 0
A38: Assets
A39: Cash & Eq. | B39: =_xlfn.XLOOKUP($A39,Inputs!$A:$A,Inputs!B:B,,0) -> 3933 | C39: =_xlfn.XLOOKUP($A39,Inputs!$A:$A,Inputs!C:C,,0) -> 4835 | D39: =_xlfn.XLOOKUP($A39,Inputs!$A:$A,Inputs!D:D,,0) -> 2535 | E39: =_xlfn.XLOOKUP($A39,Inputs!$A:$A,Inputs!E:E,,0) -> 1595 | F39: =_xlfn.XLOOKUP($A39,Inputs!$A:$A,Inputs!F:F,,0) -> 1466 | G39: =_xlfn.XLOOKUP($A39,Inputs!$A:$A,Inputs!G:G,,0) -> 1078 | H39: =_xlfn.XLOOKUP($A39,Inputs!$A:$A,Inputs!H:H,,0) -> 1185 | I39: =_xlfn.XLOOKUP($A39,Inputs!$A:$A,Inputs!I:I,,0) -> 1264 | J39: =_xlfn.XLOOKUP($A39,Inputs!$A:$A,Inputs!J:J,,0) -> 785 | K39: =_xlfn.XLOOKUP($A39,Inputs!$A:$A,Inputs!K:K,,0) -> 805 | L39: =_xlfn.XLOOKUP($A39,Inputs!$A:$A,Inputs!L:L,,0) -> 869 | M39: =_xlfn.XLOOKUP($A39,Inputs!$A:$A,Inputs!M:M,,0) -> 549
A40: Accounts Receivable | B40: =_xlfn.XLOOKUP($A40,Inputs!$A:$A,Inputs!B:B,,0) -> 5376 | C40: =_xlfn.XLOOKUP($A40,Inputs!$A:$A,Inputs!C:C,,0) -> 4128 | D40: =_xlfn.XLOOKUP($A40,Inputs!$A:$A,Inputs!D:D,,0) -> 2706 | E40: =_xlfn.XLOOKUP($A40,Inputs!$A:$A,Inputs!E:E,,0) -> 2066 | F40: =_xlfn.XLOOKUP($A40,Inputs!$A:$A,Inputs!F:F,,0) -> 1859 | G40: =_xlfn.XLOOKUP($A40,Inputs!$A:$A,Inputs!G:G,,0) -> 1235 | H40: =_xlfn.XLOOKUP($A40,Inputs!$A:$A,Inputs!H:H,,0) -> 454 | I40: =_xlfn.XLOOKUP($A40,Inputs!$A:$A,Inputs!I:I,,0) -> 311 | J40: =_xlfn.XLOOKUP($A40,Inputs!$A:$A,Inputs!J:J,,0) -> 533 | K40: =_xlfn.XLOOKUP($A40,Inputs!$A:$A,Inputs!K:K,,0) -> 818 | L40: =_xlfn.XLOOKUP($A40,Inputs!$A:$A,Inputs!L:L,,0) -> 832 | M40: =_xlfn.XLOOKUP($A40,Inputs!$A:$A,Inputs!M:M,,0) -> 630
A41: Inventory | B41: =_xlfn.XLOOKUP($A41,Inputs!$A:$A,Inputs!B:B,,0) -> 4351 | C41: =_xlfn.XLOOKUP($A41,Inputs!$A:$A,Inputs!C:C,,0) -> 3771 | D41: =_xlfn.XLOOKUP($A41,Inputs!$A:$A,Inputs!D:D,,0) -> 1955 | E41: =_xlfn.XLOOKUP($A41,Inputs!$A:$A,Inputs!E:E,,0) -> 1399 | F41: =_xlfn.XLOOKUP($A41,Inputs!$A:$A,Inputs!F:F,,0) -> 982 | G41: =_xlfn.XLOOKUP($A41,Inputs!$A:$A,Inputs!G:G,,0) -> 845 | H41: =_xlfn.XLOOKUP($A41,Inputs!$A:$A,Inputs!H:H,,0) -> 694 | I41: =_xlfn.XLOOKUP($A41,Inputs!$A:$A,Inputs!I:I,,0) -> 751 | J41: =_xlfn.XLOOKUP($A41,Inputs!$A:$A,Inputs!J:J,,0) -> 678 | K41: =_xlfn.XLOOKUP($A41,Inputs!$A:$A,Inputs!K:K,,0) -> 685 | L41: =_xlfn.XLOOKUP($A41,Inputs!$A:$A,Inputs!L:L,,0) -> 884 | M41: =_xlfn.XLOOKUP($A41,Inputs!$A:$A,Inputs!M:M,,0) -> 562
A42: Property, Plant and Equipment | B42: =_xlfn.XLOOKUP($A42,Inputs!$A:$A,Inputs!B:B,,0) -> 1589 | C42: =_xlfn.XLOOKUP($A42,Inputs!$A:$A,Inputs!C:C,,0) -> 1513 | D42: =_xlfn.XLOOKUP($A42,Inputs!$A:$A,Inputs!D:D,,0) -> 702 | E42: =_xlfn.XLOOKUP($A42,Inputs!$A:$A,Inputs!E:E,,0) -> 641 | F42: =_xlfn.XLOOKUP($A42,Inputs!$A:$A,Inputs!F:F,,0) -> 500 | G42: =_xlfn.XLOOKUP($A42,Inputs!$A:$A,Inputs!G:G,,0) -> 348 | H42: =_xlfn.XLOOKUP($A42,Inputs!$A:$A,Inputs!H:H,,0) -> 261 | I42: =_xlfn.XLOOKUP($A42,Inputs!$A:$A,Inputs!I:I,,0) -> 164 | J42: =_xlfn.XLOOKUP($A42,Inputs!$A:$A,Inputs!J:J,,0) -> 188 | K42: =_xlfn.XLOOKUP($A42,Inputs!$A:$A,Inputs!K:K,,0) -> 302 | L42: =_xlfn.XLOOKUP($A42,Inputs!$A:$A,Inputs!L:L,,0) -> 346 | M42: =_xlfn.XLOOKUP($A42,Inputs!$A:$A,Inputs!M:M,,0) -> 658
A43: Other Assets | B43: =_xlfn.XLOOKUP($A43,Inputs!$A:$A,Inputs!B:B,,0) -> 51904 | C43: =_xlfn.XLOOKUP($A43,Inputs!$A:$A,Inputs!C:C,,0) -> 52790 | D43: =_xlfn.XLOOKUP($A43,Inputs!$A:$A,Inputs!D:D,,0) -> 4085 | E43: =_xlfn.XLOOKUP($A43,Inputs!$A:$A,Inputs!E:E,,0) -> 2990 | F43: =_xlfn.XLOOKUP($A43,Inputs!$A:$A,Inputs!F:F,,0) -> 958 | G43: =_xlfn.XLOOKUP($A43,Inputs!$A:$A,Inputs!G:G,,0) -> 992 | H43: =_xlfn.XLOOKUP($A43,Inputs!$A:$A,Inputs!H:H,,0) -> 900 | I43: =_xlfn.XLOOKUP($A43,Inputs!$A:$A,Inputs!I:I,,0) -> 772 | J43: =_xlfn.XLOOKUP($A43,Inputs!$A:$A,Inputs!J:J,,0) -> 900 | K43: =_xlfn.XLOOKUP($A43,Inputs!$A:$A,Inputs!K:K,,0) -> 1157 | L43: =_xlfn.XLOOKUP($A43,Inputs!$A:$A,Inputs!L:L,,0) -> 1316 | M43: =_xlfn.XLOOKUP($A43,Inputs!$A:$A,Inputs!M:M,,0) -> 1420
A44: Total Assets | B44: =_xlfn.XLOOKUP($A44,Inputs!$A:$A,Inputs!B:B,,0) -> 67885 | C44: =_xlfn.XLOOKUP($A44,Inputs!$A:$A,Inputs!C:C,,0) -> 67580 | D44: =_xlfn.XLOOKUP($A44,Inputs!$A:$A,Inputs!D:D,,0) -> 12419 | E44: =_xlfn.XLOOKUP($A44,Inputs!$A:$A,Inputs!E:E,,0) -> 8962 | F44: =_xlfn.XLOOKUP($A44,Inputs!$A:$A,Inputs!F:F,,0) -> 6028 | G44: =_xlfn.XLOOKUP($A44,Inputs!$A:$A,Inputs!G:G,,0) -> 4556 | H44: =_xlfn.XLOOKUP($A44,Inputs!$A:$A,Inputs!H:H,,0) -> 3552 | I44: =_xlfn.XLOOKUP($A44,Inputs!$A:$A,Inputs!I:I,,0) -> 3321 | J44: =_xlfn.XLOOKUP($A44,Inputs!$A:$A,Inputs!J:J,,0) -> 3084 | K44: =_xlfn.XLOOKUP($A44,Inputs!$A:$A,Inputs!K:K,,0) -> 3767 | L44: =_xlfn.XLOOKUP($A44,Inputs!$A:$A,Inputs!L:L,,0) -> 4337 | M44: =_xlfn.XLOOKUP($A44,Inputs!$A:$A,Inputs!M:M,,0) -> 4000
A47: Liabilities
A48: Current Liabilities | B48: =_xlfn.XLOOKUP($A48,Inputs!$A:$A,Inputs!B:B,,0) -> 6689 | C48: =_xlfn.XLOOKUP($A48,Inputs!$A:$A,Inputs!C:C,,0) -> 6369 | D48: =_xlfn.XLOOKUP($A48,Inputs!$A:$A,Inputs!D:D,,0) -> 4240 | E48: =_xlfn.XLOOKUP($A48,Inputs!$A:$A,Inputs!E:E,,0) -> 2417 | F48: =_xlfn.XLOOKUP($A48,Inputs!$A:$A,Inputs!F:F,,0) -> 2359 | G48: =_xlfn.XLOOKUP($A48,Inputs!$A:$A,Inputs!G:G,,0) -> 1984 | H48: =_xlfn.XLOOKUP($A48,Inputs!$A:$A,Inputs!H:H,,0) -> 1513 | I48: =_xlfn.XLOOKUP($A48,Inputs!$A:$A,Inputs!I:I,,0) -> 1346 | J48: =_xlfn.XLOOKUP($A48,Inputs!$A:$A,Inputs!J:J,,0) -> 1403 | K48: =_xlfn.XLOOKUP($A48,Inputs!$A:$A,Inputs!K:K,,0) -> 1440 | L48: =_xlfn.XLOOKUP($A48,Inputs!$A:$A,Inputs!L:L,,0) -> 1618 | M48: =_xlfn.XLOOKUP($A48,Inputs!$A:$A,Inputs!M:M,,0) -> 1397
A49: Short-Term Debt | B49: =_xlfn.XLOOKUP($A49,Inputs!$A:$A,Inputs!B:B,,0) -> 0 | C49: =_xlfn.XLOOKUP($A49,Inputs!$A:$A,Inputs!C:C,,0) -> 0 | D49: =_xlfn.XLOOKUP($A49,Inputs!$A:$A,Inputs!D:D,,0) -> 0 | E49: =_xlfn.XLOOKUP($A49,Inputs!$A:$A,Inputs!E:E,,0) -> 0 | F49: =_xlfn.XLOOKUP($A49,Inputs!$A:$A,Inputs!F:F,,0) -> 0 | G49: =_xlfn.XLOOKUP($A49,Inputs!$A:$A,Inputs!G:G,,0) -> 136 | H49: =_xlfn.XLOOKUP($A49,Inputs!$A:$A,Inputs!H:H,,0) -> 70 | I49: =_xlfn.XLOOKUP($A49,Inputs!$A:$A,Inputs!I:I,,0) -> 0 | J49: =_xlfn.XLOOKUP($A49,Inputs!$A:$A,Inputs!J:J,,0) -> 230 | K49: =_xlfn.XLOOKUP($A49,Inputs!$A:$A,Inputs!K:K,,0) -> 177 | L49: =_xlfn.XLOOKUP($A49,Inputs!$A:$A,Inputs!L:L,,0) -> 60 | M49: =_xlfn.XLOOKUP($A49,Inputs!$A:$A,Inputs!M:M,,0) -> 0
A50: Short-Term Leases | B50: =_xlfn.XLOOKUP($A50,Inputs!$A:$A,Inputs!B:B,,0) -> 0 | C50: =_xlfn.XLOOKUP($A50,Inputs!$A:$A,Inputs!C:C,,0) -> 0 | D50: =_xlfn.XLOOKUP($A50,Inputs!$A:$A,Inputs!D:D,,0) -> 0 | E50: =_xlfn.XLOOKUP($A50,Inputs!$A:$A,Inputs!E:E,,0) -> 0 | F50: =_xlfn.XLOOKUP($A50,Inputs!$A:$A,Inputs!F:F,,0) -> 0 | G50: =_xlfn.XLOOKUP($A50,Inputs!$A:$A,Inputs!G:G,,0) -> 0 | H50: =_xlfn.XLOOKUP($A50,Inputs!$A:$A,Inputs!H:H,,0) -> 0 | I50: =_xlfn.XLOOKUP($A50,Inputs!$A:$A,Inputs!I:I,,0) -> 0 | J50: =_xlfn.XLOOKUP($A50,Inputs!$A:$A,Inputs!J:J,,0) -> 0 | K50: =_xlfn.XLOOKUP($A50,Inputs!$A:$A,Inputs!K:K,,0) -> 0 | L50: =_xlfn.XLOOKUP($A50,Inputs!$A:$A,Inputs!L:L,,0) -> 0 | M50: =_xlfn.XLOOKUP($A50,Inputs!$A:$A,Inputs!M:M,,0) -> 0
A51: Other current liabilities | B51: =_xlfn.XLOOKUP($A51,Inputs!$A:$A,Inputs!B:B,,0) -> 4271 | C51: =_xlfn.XLOOKUP($A51,Inputs!$A:$A,Inputs!C:C,,0) -> 3413 | D51: =_xlfn.XLOOKUP($A51,Inputs!$A:$A,Inputs!D:D,,0) -> 2834 | E51: =_xlfn.XLOOKUP($A51,Inputs!$A:$A,Inputs!E:E,,0) -> 1871 | F51: =_xlfn.XLOOKUP($A51,Inputs!$A:$A,Inputs!F:F,,0) -> 1158 | G51: =_xlfn.XLOOKUP($A51,Inputs!$A:$A,Inputs!G:G,,0) -> 807 | H51: =_xlfn.XLOOKUP($A51,Inputs!$A:$A,Inputs!H:H,,0) -> 647 | I51: =_xlfn.XLOOKUP($A51,Inputs!$A:$A,Inputs!I:I,,0) -> 523 | J51: =_xlfn.XLOOKUP($A51,Inputs!$A:$A,Inputs!J:J,,0) -> 649 | K51: =_xlfn.XLOOKUP($A51,Inputs!$A:$A,Inputs!K:K,,0) -> 630 | L51: =_xlfn.XLOOKUP($A51,Inputs!$A:$A,Inputs!L:L,,0) -> 675 | M51: =_xlfn.XLOOKUP($A51,Inputs!$A:$A,Inputs!M:M,,0) -> 665
A52: Non-current Liabilities | B52: =_xlfn.XLOOKUP($A52,Inputs!$A:$A,Inputs!B:B,,0) -> 5304 | C52: =_xlfn.XLOOKUP($A52,Inputs!$A:$A,Inputs!C:C,,0) -> 6461 | D52: =_xlfn.XLOOKUP($A52,Inputs!$A:$A,Inputs!D:D,,0) -> 682 | E52: =_xlfn.XLOOKUP($A52,Inputs!$A:$A,Inputs!E:E,,0) -> 708 | F52: =_xlfn.XLOOKUP($A52,Inputs!$A:$A,Inputs!F:F,,0) -> 842 | G52: =_xlfn.XLOOKUP($A52,Inputs!$A:$A,Inputs!G:G,,0) -> 1306 | H52: =_xlfn.XLOOKUP($A52,Inputs!$A:$A,Inputs!H:H,,0) -> 1443 | I52: =_xlfn.XLOOKUP($A52,Inputs!$A:$A,Inputs!I:I,,0) -> 1559 | J52: =_xlfn.XLOOKUP($A52,Inputs!$A:$A,Inputs!J:J,,0) -> 2093 | K52: =_xlfn.XLOOKUP($A52,Inputs!$A:$A,Inputs!K:K,,0) -> 2140 | L52: =_xlfn.XLOOKUP($A52,Inputs!$A:$A,Inputs!L:L,,0) -> 2175 | M52: =_xlfn.XLOOKUP($A52,Inputs!$A:$A,Inputs!M:M,,0) -> 2065
A53: Long-Term Debt | B53: =_xlfn.XLOOKUP($A53,Inputs!$A:$A,Inputs!B:B,,0) -> 1717 | C53: =_xlfn.XLOOKUP($A53,Inputs!$A:$A,Inputs!C:C,,0) -> 2467 | D53: =_xlfn.XLOOKUP($A53,Inputs!$A:$A,Inputs!D:D,,0) -> 1 | E53: =_xlfn.XLOOKUP($A53,Inputs!$A:$A,Inputs!E:E,,0) -> 330 | F53: =_xlfn.XLOOKUP($A53,Inputs!$A:$A,Inputs!F:F,,0) -> 486 | G53: =_xlfn.XLOOKUP($A53,Inputs!$A:$A,Inputs!G:G,,0) -> 1114 | H53: =_xlfn.XLOOKUP($A53,Inputs!$A:$A,Inputs!H:H,,0) -> 1325 | I53: =_xlfn.XLOOKUP($A53,Inputs!$A:$A,Inputs!I:I,,0) -> 1435 | J53: =_xlfn.XLOOKUP($A53,Inputs!$A:$A,Inputs!J:J,,0) -> 2007 | K53: =_xlfn.XLOOKUP($A53,Inputs!$A:$A,Inputs!K:K,,0) -> 2035 | L53: =_xlfn.XLOOKUP($A53,Inputs!$A:$A,Inputs!L:L,,0) -> 1998 | M53: =_xlfn.XLOOKUP($A53,Inputs!$A:$A,Inputs!M:M,,0) -> 2037
A54: Long-Term Leases | B54: =_xlfn.XLOOKUP($A54,Inputs!$A:$A,Inputs!B:B,,0) -> 535 | C54: =_xlfn.XLOOKUP($A54,Inputs!$A:$A,Inputs!C:C,,0) -> 396 | D54: =_xlfn.XLOOKUP($A54,Inputs!$A:$A,Inputs!D:D,,0) -> 348 | E54: =_xlfn.XLOOKUP($A54,Inputs!$A:$A,Inputs!E:E,,0) -> 201 | F54: =_xlfn.XLOOKUP($A54,Inputs!$A:$A,Inputs!F:F,,0) -> 199 | G54: =_xlfn.XLOOKUP($A54,Inputs!$A:$A,Inputs!G:G,,0) -> 0 | H54: =_xlfn.XLOOKUP($A54,Inputs!$A:$A,Inputs!H:H,,0) -> 0 | I54: =_xlfn.XLOOKUP($A54,Inputs!$A:$A,Inputs!I:I,,0) -> 0 | J54: =_xlfn.XLOOKUP($A54,Inputs!$A:$A,Inputs!J:J,,0) -> 0 | K54: =_xlfn.XLOOKUP($A54,Inputs!$A:$A,Inputs!K:K,,0) -> 0 | L54: =_xlfn.XLOOKUP($A54,Inputs!$A:$A,Inputs!L:L,,0) -> 0 | M54: =_xlfn.XLOOKUP($A54,Inputs!$A:$A,Inputs!M:M,,0) -> 0
A55: Other non-current liabilities | B55: =_xlfn.XLOOKUP($A55,Inputs!$A:$A,Inputs!B:B,,0) -> 3052 | C55: =_xlfn.XLOOKUP($A55,Inputs!$A:$A,Inputs!C:C,,0) -> 3598 | D55: =_xlfn.XLOOKUP($A55,Inputs!$A:$A,Inputs!D:D,,0) -> 333 | E55: =_xlfn.XLOOKUP($A55,Inputs!$A:$A,Inputs!E:E,,0) -> 177 | F55: =_xlfn.XLOOKUP($A55,Inputs!$A:$A,Inputs!F:F,,0) -> 157 | G55: =_xlfn.XLOOKUP($A55,Inputs!$A:$A,Inputs!G:G,,0) -> 192 | H55: =_xlfn.XLOOKUP($A55,Inputs!$A:$A,Inputs!H:H,,0) -> 118 | I55: =_xlfn.XLOOKUP($A55,Inputs!$A:$A,Inputs!I:I,,0) -> 124 | J55: =_xlfn.XLOOKUP($A55,Inputs!$A:$A,Inputs!J:J,,0) -> 86 | K55: =_xlfn.XLOOKUP($A55,Inputs!$A:$A,Inputs!K:K,,0) -> 105 | L55: =_xlfn.XLOOKUP($A55,Inputs!$A:$A,Inputs!L:L,,0) -> 177 | M55: =_xlfn.XLOOKUP($A55,Inputs!$A:$A,Inputs!M:M,,0) -> 28
A56: Total Liabilities | B56: =_xlfn.XLOOKUP($A56,Inputs!$A:$A,Inputs!B:B,,0) -> 11993 | C56: =_xlfn.XLOOKUP($A56,Inputs!$A:$A,Inputs!C:C,,0) -> 12830 | D56: =_xlfn.XLOOKUP($A56,Inputs!$A:$A,Inputs!D:D,,0) -> 4922 | E56: =_xlfn.XLOOKUP($A56,Inputs!$A:$A,Inputs!E:E,,0) -> 3125 | F56: =_xlfn.XLOOKUP($A56,Inputs!$A:$A,Inputs!F:F,,0) -> 3201 | G56: =_xlfn.XLOOKUP($A56,Inputs!$A:$A,Inputs!G:G,,0) -> 3290 | H56: =_xlfn.XLOOKUP($A56,Inputs!$A:$A,Inputs!H:H,,0) -> 2956 | I56: =_xlfn.XLOOKUP($A56,Inputs!$A:$A,Inputs!I:I,,0) -> 2905 | J56: =_xlfn.XLOOKUP($A56,Inputs!$A:$A,Inputs!J:J,,0) -> 3496 | K56: =_xlfn.XLOOKUP($A56,Inputs!$A:$A,Inputs!K:K,,0) -> 3580 | L56: =_xlfn.XLOOKUP($A56,Inputs!$A:$A,Inputs!L:L,,0) -> 3793 | M56: =_xlfn.XLOOKUP($A56,Inputs!$A:$A,Inputs!M:M,,0) -> 3462
A58: Total Debt | B58: =B49+B53+B50+B54 -> 2252 | C58: =C49+C53+C50+C54 -> 2863 | D58: =D49+D53+D50+D54 -> 349 | E58: =E49+E53+E50+E54 -> 531 | F58: =F49+F53+F50+F54 -> 685 | G58: =G49+G53+G50+G54 -> 1250 | H58: =H49+H53+H50+H54 -> 1395 | I58: =I49+I53+I50+I54 -> 1435 | ... M58: =M49+M53+M50+M54 -> 2037
A59: Debt/Assets | B59: =IFERROR(B58/B44,"-") -> 0.03317375 | C59: =IFERROR(C58/C44,"-") -> 0.042364605 | D59: =IFERROR(D58/D44,"-") -> 0.028102102 | E59: =IFERROR(E58/E44,"-") -> 0.059250167 | F59: =IFERROR(F58/F44,"-") -> 0.11363636 | G59: =IFERROR(G58/G44,"-") -> 0.27436348 | H59: =IFERROR(H58/H44,"-") -> 0.39273649 | I59: =IFERROR(I58/I44,"-") -> 0.43209877 | ... M59: =IFERROR(M58/M44,"-") -> 0.50925
A60: Net Debt | B60: =B58-B39 -> -1681 | C60: =C58-C39 -> -1972 | D60: =D58-D39 -> -2186 | E60: =E58-E39 -> -1064 | F60: =F58-F39 -> -781 | G60: =G58-G39 -> 172 | H60: =H58-H39 -> 210 | I60: =I58-I39 -> 171 | ... M60: =M58-M39 -> 1488
A62: Minority Interest | B62: =_xlfn.XLOOKUP($A62,Inputs!$A:$A,Inputs!B:B,,0) -> 0 | C62: =_xlfn.XLOOKUP($A62,Inputs!$A:$A,Inputs!C:C,,0) -> 0 | D62: =_xlfn.XLOOKUP($A62,Inputs!$A:$A,Inputs!D:D,,0) -> 0 | E62: =_xlfn.XLOOKUP($A62,Inputs!$A:$A,Inputs!E:E,,0) -> 0 | F62: =_xlfn.XLOOKUP($A62,Inputs!$A:$A,Inputs!F:F,,0) -> 0 | G62: =_xlfn.XLOOKUP($A62,Inputs!$A:$A,Inputs!G:G,,0) -> 0 | H62: =_xlfn.XLOOKUP($A62,Inputs!$A:$A,Inputs!H:H,,0) -> 0 | I62: =_xlfn.XLOOKUP($A62,Inputs!$A:$A,Inputs!I:I,,0) -> 0 | J62: =_xlfn.XLOOKUP($A62,Inputs!$A:$A,Inputs!J:J,,0) -> 0 | K62: =_xlfn.XLOOKUP($A62,Inputs!$A:$A,Inputs!K:K,,0) -> 0 | L62: =_xlfn.XLOOKUP($A62,Inputs!$A:$A,Inputs!L:L,,0) -> 0 | M62: =_xlfn.XLOOKUP($A62,Inputs!$A:$A,Inputs!M:M,,0) -> 0
A64: Shareholder's Equity | B64: =_xlfn.XLOOKUP($A64,Inputs!$A:$A,Inputs!B:B,,0) -> 55892 | C64: =_xlfn.XLOOKUP($A64,Inputs!$A:$A,Inputs!C:C,,0) -> 54750 | D64: =_xlfn.XLOOKUP($A64,Inputs!$A:$A,Inputs!D:D,,0) -> 7497 | E64: =_xlfn.XLOOKUP($A64,Inputs!$A:$A,Inputs!E:E,,0) -> 5837 | F64: =_xlfn.XLOOKUP($A64,Inputs!$A:$A,Inputs!F:F,,0) -> 2827 | G64: =_xlfn.XLOOKUP($A64,Inputs!$A:$A,Inputs!G:G,,0) -> 1266 | H64: =_xlfn.XLOOKUP($A64,Inputs!$A:$A,Inputs!H:H,,0) -> 596 | I64: =_xlfn.XLOOKUP($A64,Inputs!$A:$A,Inputs!I:I,,0) -> 416 | J64: =_xlfn.XLOOKUP($A64,Inputs!$A:$A,Inputs!J:J,,0) -> -412 | K64: =_xlfn.XLOOKUP($A64,Inputs!$A:$A,Inputs!K:K,,0) -> 187 | L64: =_xlfn.XLOOKUP($A64,Inputs!$A:$A,Inputs!L:L,,0) -> 544 | M64: =_xlfn.XLOOKUP($A64,Inputs!$A:$A,Inputs!M:M,,0) -> 538
A66: Cash Flow
A67: Operating CF | B67: =_xlfn.XLOOKUP($A67,Inputs!$A:$A,Inputs!B:B,,0) -> 1667 | C67: =_xlfn.XLOOKUP($A67,Inputs!$A:$A,Inputs!C:C,,0) -> 3565 | D67: =_xlfn.XLOOKUP($A67,Inputs!$A:$A,Inputs!D:D,,0) -> 3521 | E67: =_xlfn.XLOOKUP($A67,Inputs!$A:$A,Inputs!E:E,,0) -> 1071 | F67: =_xlfn.XLOOKUP($A67,Inputs!$A:$A,Inputs!F:F,,0) -> 493 | G67: =_xlfn.XLOOKUP($A67,Inputs!$A:$A,Inputs!G:G,,0) -> 34 | H67: =_xlfn.XLOOKUP($A67,Inputs!$A:$A,Inputs!H:H,,0) -> 12 | I67: =_xlfn.XLOOKUP($A67,Inputs!$A:$A,Inputs!I:I,,0) -> 90 | J67: =_xlfn.XLOOKUP($A67,Inputs!$A:$A,Inputs!J:J,,0) -> -226 | K67: =_xlfn.XLOOKUP($A67,Inputs!$A:$A,Inputs!K:K,,0) -> -98 | L67: =_xlfn.XLOOKUP($A67,Inputs!$A:$A,Inputs!L:L,,0) -> -148 | M67: =_xlfn.XLOOKUP($A67,Inputs!$A:$A,Inputs!M:M,,0) -> -338
A68: Investing CF | B68: =_xlfn.XLOOKUP($A68,Inputs!$A:$A,Inputs!B:B,,0) -> -1423 | C68: =_xlfn.XLOOKUP($A68,Inputs!$A:$A,Inputs!C:C,,0) -> 1999 | D68: =_xlfn.XLOOKUP($A68,Inputs!$A:$A,Inputs!D:D,,0) -> -686 | E68: =_xlfn.XLOOKUP($A68,Inputs!$A:$A,Inputs!E:E,,0) -> -952 | F68: =_xlfn.XLOOKUP($A68,Inputs!$A:$A,Inputs!F:F,,0) -> -149 | G68: =_xlfn.XLOOKUP($A68,Inputs!$A:$A,Inputs!G:G,,0) -> -170 | H68: =_xlfn.XLOOKUP($A68,Inputs!$A:$A,Inputs!H:H,,0) -> -54 | I68: =_xlfn.XLOOKUP($A68,Inputs!$A:$A,Inputs!I:I,,0) -> 267 | J68: =_xlfn.XLOOKUP($A68,Inputs!$A:$A,Inputs!J:J,,0) -> 147 | K68: =_xlfn.XLOOKUP($A68,Inputs!$A:$A,Inputs!K:K,,0) -> -12 | L68: =_xlfn.XLOOKUP($A68,Inputs!$A:$A,Inputs!L:L,,0) -> 455 | M68: =_xlfn.XLOOKUP($A68,Inputs!$A:$A,Inputs!M:M,,0) -> -19
A69: Net Capex | B69: =_xlfn.XLOOKUP($A69,Inputs!$A:$A,Inputs!B:B,,0) -> -546 | C69: =_xlfn.XLOOKUP($A69,Inputs!$A:$A,Inputs!C:C,,0) -> -450 | D69: =_xlfn.XLOOKUP($A69,Inputs!$A:$A,Inputs!D:D,,0) -> -301 | E69: =_xlfn.XLOOKUP($A69,Inputs!$A:$A,Inputs!E:E,,0) -> -294 | F69: =_xlfn.XLOOKUP($A69,Inputs!$A:$A,Inputs!F:F,,0) -> -217 | G69: =_xlfn.XLOOKUP($A69,Inputs!$A:$A,Inputs!G:G,,0) -> -163 | H69: =_xlfn.XLOOKUP($A69,Inputs!$A:$A,Inputs!H:H,,0) -> -113 | I69: =_xlfn.XLOOKUP($A69,Inputs!$A:$A,Inputs!I:I,,0) -> -77 | J69: =_xlfn.XLOOKUP($A69,Inputs!$A:$A,Inputs!J:J,,0) -> -96 | K69: =_xlfn.XLOOKUP($A69,Inputs!$A:$A,Inputs!K:K,,0) -> -95 | L69: =_xlfn.XLOOKUP($A69,Inputs!$A:$A,Inputs!L:L,,0) -> -84 | M69: =_xlfn.XLOOKUP($A69,Inputs!$A:$A,Inputs!M:M,,0) -> -133
A70: Investments & Acquisitions | B70: =_xlfn.XLOOKUP($A70,Inputs!$A:$A,Inputs!B:B,,0) -> -866 | C70: =_xlfn.XLOOKUP($A70,Inputs!$A:$A,Inputs!C:C,,0) -> 2465 | D70: =_xlfn.XLOOKUP($A70,Inputs!$A:$A,Inputs!D:D,,0) -> -378 | E70: =_xlfn.XLOOKUP($A70,Inputs!$A:$A,Inputs!E:E,,0) -> -658 | F70: =_xlfn.XLOOKUP($A70,Inputs!$A:$A,Inputs!F:F,,0) -> 41 | G70: =_xlfn.XLOOKUP($A70,Inputs!$A:$A,Inputs!G:G,,0) -> -78 | H70: =_xlfn.XLOOKUP($A70,Inputs!$A:$A,Inputs!H:H,,0) -> 1 | I70: =_xlfn.XLOOKUP($A70,Inputs!$A:$A,Inputs!I:I,,0) -> 342 | J70: =_xlfn.XLOOKUP($A70,Inputs!$A:$A,Inputs!J:J,,0) -> 243 | K70: =_xlfn.XLOOKUP($A70,Inputs!$A:$A,Inputs!K:K,,0) -> 83 | L70: =_xlfn.XLOOKUP($A70,Inputs!$A:$A,Inputs!L:L,,0) -> 539 | M70: =_xlfn.XLOOKUP($A70,Inputs!$A:$A,Inputs!M:M,,0) -> 123
A71: Financing CF | B71: =_xlfn.XLOOKUP($A71,Inputs!$A:$A,Inputs!B:B,,0) -> -1146 | C71: =_xlfn.XLOOKUP($A71,Inputs!$A:$A,Inputs!C:C,,0) -> -3264 | D71: =_xlfn.XLOOKUP($A71,Inputs!$A:$A,Inputs!D:D,,0) -> -1895 | E71: =_xlfn.XLOOKUP($A71,Inputs!$A:$A,Inputs!E:E,,0) -> 6 | F71: =_xlfn.XLOOKUP($A71,Inputs!$A:$A,Inputs!F:F,,0) -> 43 | G71: =_xlfn.XLOOKUP($A71,Inputs!$A:$A,Inputs!G:G,,0) -> 28 | H71: =_xlfn.XLOOKUP($A71,Inputs!$A:$A,Inputs!H:H,,0) -> -33 | I71: =_xlfn.XLOOKUP($A71,Inputs!$A:$A,Inputs!I:I,,0) -> 122 | J71: =_xlfn.XLOOKUP($A71,Inputs!$A:$A,Inputs!J:J,,0) -> 59 | K71: =_xlfn.XLOOKUP($A71,Inputs!$A:$A,Inputs!K:K,,0) -> 46 | L71: =_xlfn.XLOOKUP($A71,Inputs!$A:$A,Inputs!L:L,,0) -> 13 | M71: =_xlfn.XLOOKUP($A71,Inputs!$A:$A,Inputs!M:M,,0) -> 37
A72: Dividends | B72: =_xlfn.XLOOKUP($A72,Inputs!$A:$A,Inputs!B:B,,0) -> 0 | C72: =_xlfn.XLOOKUP($A72,Inputs!$A:$A,Inputs!C:C,,0) -> 0 | D72: =_xlfn.XLOOKUP($A72,Inputs!$A:$A,Inputs!D:D,,0) -> 0 | E72: =_xlfn.XLOOKUP($A72,Inputs!$A:$A,Inputs!E:E,,0) -> 0 | F72: =_xlfn.XLOOKUP($A72,Inputs!$A:$A,Inputs!F:F,,0) -> 0 | G72: =_xlfn.XLOOKUP($A72,Inputs!$A:$A,Inputs!G:G,,0) -> 0 | H72: =_xlfn.XLOOKUP($A72,Inputs!$A:$A,Inputs!H:H,,0) -> 0 | I72: =_xlfn.XLOOKUP($A72,Inputs!$A:$A,Inputs!I:I,,0) -> 0 | J72: =_xlfn.XLOOKUP($A72,Inputs!$A:$A,Inputs!J:J,,0) -> 0 | K72: =_xlfn.XLOOKUP($A72,Inputs!$A:$A,Inputs!K:K,,0) -> 0 | L72: =_xlfn.XLOOKUP($A72,Inputs!$A:$A,Inputs!L:L,,0) -> 0 | M72: =_xlfn.XLOOKUP($A72,Inputs!$A:$A,Inputs!M:M,,0) -> 0
A73: Share buyback | B73: =_xlfn.XLOOKUP($A73,Inputs!$A:$A,Inputs!B:B,,0) -> -985 | C73: =_xlfn.XLOOKUP($A73,Inputs!$A:$A,Inputs!C:C,,0) -> -3702 | D73: =_xlfn.XLOOKUP($A73,Inputs!$A:$A,Inputs!D:D,,0) -> -1762 | E73: =_xlfn.XLOOKUP($A73,Inputs!$A:$A,Inputs!E:E,,0) -> 0 | F73: =_xlfn.XLOOKUP($A73,Inputs!$A:$A,Inputs!F:F,,0) -> 0 | G73: =_xlfn.XLOOKUP($A73,Inputs!$A:$A,Inputs!G:G,,0) -> 0 | H73: =_xlfn.XLOOKUP($A73,Inputs!$A:$A,Inputs!H:H,,0) -> 0 | I73: =_xlfn.XLOOKUP($A73,Inputs!$A:$A,Inputs!I:I,,0) -> 0 | J73: =_xlfn.XLOOKUP($A73,Inputs!$A:$A,Inputs!J:J,,0) -> 0 | K73: =_xlfn.XLOOKUP($A73,Inputs!$A:$A,Inputs!K:K,,0) -> 0 | L73: =_xlfn.XLOOKUP($A73,Inputs!$A:$A,Inputs!L:L,,0) -> 0 | M73: =_xlfn.XLOOKUP($A73,Inputs!$A:$A,Inputs!M:M,,0) -> 0
A74: FX | B74: =_xlfn.XLOOKUP($A74,Inputs!$A:$A,Inputs!B:B,,0) -> 0 | C74: =_xlfn.XLOOKUP($A74,Inputs!$A:$A,Inputs!C:C,,0) -> 0 | D74: =_xlfn.XLOOKUP($A74,Inputs!$A:$A,Inputs!D:D,,0) -> 0 | E74: =_xlfn.XLOOKUP($A74,Inputs!$A:$A,Inputs!E:E,,0) -> 0 | F74: =_xlfn.XLOOKUP($A74,Inputs!$A:$A,Inputs!F:F,,0) -> 0 | G74: =_xlfn.XLOOKUP($A74,Inputs!$A:$A,Inputs!G:G,,0) -> 0 | H74: =_xlfn.XLOOKUP($A74,Inputs!$A:$A,Inputs!H:H,,0) -> 0 | I74: =_xlfn.XLOOKUP($A74,Inputs!$A:$A,Inputs!I:I,,0) -> 0 | J74: =_xlfn.XLOOKUP($A74,Inputs!$A:$A,Inputs!J:J,,0) -> 0 | K74: =_xlfn.XLOOKUP($A74,Inputs!$A:$A,Inputs!K:K,,0) -> 0 | L74: =_xlfn.XLOOKUP($A74,Inputs!$A:$A,Inputs!L:L,,0) -> 0 | M74: =_xlfn.XLOOKUP($A74,Inputs!$A:$A,Inputs!M:M,,0) -> 0
A75: Changes in cash | B75: =_xlfn.XLOOKUP($A75,Inputs!$A:$A,Inputs!B:B,,0) -> -902 | C75: =_xlfn.XLOOKUP($A75,Inputs!$A:$A,Inputs!C:C,,0) -> 2300 | D75: =_xlfn.XLOOKUP($A75,Inputs!$A:$A,Inputs!D:D,,0) -> 940 | E75: =_xlfn.XLOOKUP($A75,Inputs!$A:$A,Inputs!E:E,,0) -> 125 | F75: =_xlfn.XLOOKUP($A75,Inputs!$A:$A,Inputs!F:F,,0) -> 387 | G75: =_xlfn.XLOOKUP($A75,Inputs!$A:$A,Inputs!G:G,,0) -> -108 | H75: =_xlfn.XLOOKUP($A75,Inputs!$A:$A,Inputs!H:H,,0) -> -75 | I75: =_xlfn.XLOOKUP($A75,Inputs!$A:$A,Inputs!I:I,,0) -> 479 | J75: =_xlfn.XLOOKUP($A75,Inputs!$A:$A,Inputs!J:J,,0) -> -20 | K75: =_xlfn.XLOOKUP($A75,Inputs!$A:$A,Inputs!K:K,,0) -> -64 | L75: =_xlfn.XLOOKUP($A75,Inputs!$A:$A,Inputs!L:L,,0) -> 320 | M75: =_xlfn.XLOOKUP($A75,Inputs!$A:$A,Inputs!M:M,,0) -> -320
A77: Other Data
A78: Number of employees | B78: =_xlfn.XLOOKUP($A78,Inputs!$A:$A,Inputs!B:B,,0) -> #N/A | C78: =_xlfn.XLOOKUP($A78,Inputs!$A:$A,Inputs!C:C,,0) -> #N/A | D78: =_xlfn.XLOOKUP($A78,Inputs!$A:$A,Inputs!D:D,,0) -> #N/A | E78: =_xlfn.XLOOKUP($A78,Inputs!$A:$A,Inputs!E:E,,0) -> #N/A | F78: =_xlfn.XLOOKUP($A78,Inputs!$A:$A,Inputs!F:F,,0) -> #N/A | G78: =_xlfn.XLOOKUP($A78,Inputs!$A:$A,Inputs!G:G,,0) -> #N/A | H78: =_xlfn.XLOOKUP($A78,Inputs!$A:$A,Inputs!H:H,,0) -> #N/A | I78: =_xlfn.XLOOKUP($A78,Inputs!$A:$A,Inputs!I:I,,0) -> #N/A | J78: =_xlfn.XLOOKUP($A78,Inputs!$A:$A,Inputs!J:J,,0) -> #N/A | K78: =_xlfn.XLOOKUP($A78,Inputs!$A:$A,Inputs!K:K,,0) -> #N/A | L78: =_xlfn.XLOOKUP($A78,Inputs!$A:$A,Inputs!L:L,,0) -> #N/A | M78: =_xlfn.XLOOKUP($A78,Inputs!$A:$A,Inputs!M:M,,0) -> #N/A
A79: Shares Outstanding | B79: =_xlfn.XLOOKUP($A79,Inputs!$A:$A,Inputs!B:B,,0) -> #N/A | C79: =_xlfn.XLOOKUP($A79,Inputs!$A:$A,Inputs!C:C,,0) -> #N/A | D79: =_xlfn.XLOOKUP($A79,Inputs!$A:$A,Inputs!D:D,,0) -> #N/A | E79: =_xlfn.XLOOKUP($A79,Inputs!$A:$A,Inputs!E:E,,0) -> #N/A | F79: =_xlfn.XLOOKUP($A79,Inputs!$A:$A,Inputs!F:F,,0) -> #N/A | G79: =_xlfn.XLOOKUP($A79,Inputs!$A:$A,Inputs!G:G,,0) -> #N/A | H79: =_xlfn.XLOOKUP($A79,Inputs!$A:$A,Inputs!H:H,,0) -> #N/A | I79: =_xlfn.XLOOKUP($A79,Inputs!$A:$A,Inputs!I:I,,0) -> #N/A | J79: =_xlfn.XLOOKUP($A79,Inputs!$A:$A,Inputs!J:J,,0) -> #N/A | K79: =_xlfn.XLOOKUP($A79,Inputs!$A:$A,Inputs!K:K,,0) -> #N/A | L79: =_xlfn.XLOOKUP($A79,Inputs!$A:$A,Inputs!L:L,,0) -> #N/A | M79: =_xlfn.XLOOKUP($A79,Inputs!$A:$A,Inputs!M:M,,0) -> #N/A
A80: Float | B80: =_xlfn.XLOOKUP($A80,Inputs!$A:$A,Inputs!B:B,,0) -> 0.9946 | C80: =_xlfn.XLOOKUP($A80,Inputs!$A:$A,Inputs!C:C,,0) -> Yahoo finance | D80: =_xlfn.XLOOKUP($A80,Inputs!$A:$A,Inputs!D:D,,0) -> 0 | E80: =_xlfn.XLOOKUP($A80,Inputs!$A:$A,Inputs!E:E,,0) -> 0 | F80: =_xlfn.XLOOKUP($A80,Inputs!$A:$A,Inputs!F:F,,0) -> 0 | G80: =_xlfn.XLOOKUP($A80,Inputs!$A:$A,Inputs!G:G,,0) -> 0 | H80: =_xlfn.XLOOKUP($A80,Inputs!$A:$A,Inputs!H:H,,0) -> 0 | I80: =_xlfn.XLOOKUP($A80,Inputs!$A:$A,Inputs!I:I,,0) -> 0 | J80: =_xlfn.XLOOKUP($A80,Inputs!$A:$A,Inputs!J:J,,0) -> 0 | K80: =_xlfn.XLOOKUP($A80,Inputs!$A:$A,Inputs!K:K,,0) -> 0 | L80: =_xlfn.XLOOKUP($A80,Inputs!$A:$A,Inputs!L:L,,0) -> 0 | M80: =_xlfn.XLOOKUP($A80,Inputs!$A:$A,Inputs!M:M,,0) -> 0
A81: Insiders Own | B81: =_xlfn.XLOOKUP($A81,Inputs!$A:$A,Inputs!B:B,,0) -> 0.0048 | C81: =_xlfn.XLOOKUP($A81,Inputs!$A:$A,Inputs!C:C,,0) -> Yahoo finance | D81: =_xlfn.XLOOKUP($A81,Inputs!$A:$A,Inputs!D:D,,0) -> 0 | E81: =_xlfn.XLOOKUP($A81,Inputs!$A:$A,Inputs!E:E,,0) -> 0 | F81: =_xlfn.XLOOKUP($A81,Inputs!$A:$A,Inputs!F:F,,0) -> 0 | G81: =_xlfn.XLOOKUP($A81,Inputs!$A:$A,Inputs!G:G,,0) -> 0 | H81: =_xlfn.XLOOKUP($A81,Inputs!$A:$A,Inputs!H:H,,0) -> 0 | I81: =_xlfn.XLOOKUP($A81,Inputs!$A:$A,Inputs!I:I,,0) -> 0 | J81: =_xlfn.XLOOKUP($A81,Inputs!$A:$A,Inputs!J:J,,0) -> 0 | K81: =_xlfn.XLOOKUP($A81,Inputs!$A:$A,Inputs!K:K,,0) -> 0 | L81: =_xlfn.XLOOKUP($A81,Inputs!$A:$A,Inputs!L:L,,0) -> 0 | M81: =_xlfn.XLOOKUP($A81,Inputs!$A:$A,Inputs!M:M,,0) -> 0
A82: Fitch/ S&P Rating | B82: =_xlfn.XLOOKUP($A82,Inputs!$A:$A,Inputs!B:B,,0) -> A- | C82: =_xlfn.XLOOKUP($A82,Inputs!$A:$A,Inputs!C:C,,0) -> 10-K | D82: =_xlfn.XLOOKUP($A82,Inputs!$A:$A,Inputs!D:D,,0) -> 0 | E82: =_xlfn.XLOOKUP($A82,Inputs!$A:$A,Inputs!E:E,,0) -> 0 | F82: =_xlfn.XLOOKUP($A82,Inputs!$A:$A,Inputs!F:F,,0) -> 0 | G82: =_xlfn.XLOOKUP($A82,Inputs!$A:$A,Inputs!G:G,,0) -> 0 | H82: =_xlfn.XLOOKUP($A82,Inputs!$A:$A,Inputs!H:H,,0) -> 0 | I82: =_xlfn.XLOOKUP($A82,Inputs!$A:$A,Inputs!I:I,,0) -> 0 | J82: =_xlfn.XLOOKUP($A82,Inputs!$A:$A,Inputs!J:J,,0) -> 0 | K82: =_xlfn.XLOOKUP($A82,Inputs!$A:$A,Inputs!K:K,,0) -> 0 | L82: =_xlfn.XLOOKUP($A82,Inputs!$A:$A,Inputs!L:L,,0) -> 0 | M82: =_xlfn.XLOOKUP($A82,Inputs!$A:$A,Inputs!M:M,,0) -> 0
A83: Dividend Yield | B83: =_xlfn.XLOOKUP($A83,Inputs!$A:$A,Inputs!B:B,,0) -> #N/A | C83: =_xlfn.XLOOKUP($A83,Inputs!$A:$A,Inputs!C:C,,0) -> #N/A | D83: =_xlfn.XLOOKUP($A83,Inputs!$A:$A,Inputs!D:D,,0) -> #N/A | E83: =_xlfn.XLOOKUP($A83,Inputs!$A:$A,Inputs!E:E,,0) -> #N/A | F83: =_xlfn.XLOOKUP($A83,Inputs!$A:$A,Inputs!F:F,,0) -> #N/A | G83: =_xlfn.XLOOKUP($A83,Inputs!$A:$A,Inputs!G:G,,0) -> #N/A | H83: =_xlfn.XLOOKUP($A83,Inputs!$A:$A,Inputs!H:H,,0) -> #N/A | I83: =_xlfn.XLOOKUP($A83,Inputs!$A:$A,Inputs!I:I,,0) -> #N/A | J83: =_xlfn.XLOOKUP($A83,Inputs!$A:$A,Inputs!J:J,,0) -> #N/A | K83: =_xlfn.XLOOKUP($A83,Inputs!$A:$A,Inputs!K:K,,0) -> #N/A | L83: =_xlfn.XLOOKUP($A83,Inputs!$A:$A,Inputs!L:L,,0) -> #N/A | M83: =_xlfn.XLOOKUP($A83,Inputs!$A:$A,Inputs!M:M,,0) -> #N/A
A84: Daily Volume in Millions of USD | B84: =_xlfn.XLOOKUP($A84,Inputs!$A:$A,Inputs!B:B,,0) -> 74.76 | C84: =_xlfn.XLOOKUP($A84,Inputs!$A:$A,Inputs!C:C,,0) -> Yahoo Finance | D84: =_xlfn.XLOOKUP($A84,Inputs!$A:$A,Inputs!D:D,,0) -> 0 | E84: =_xlfn.XLOOKUP($A84,Inputs!$A:$A,Inputs!E:E,,0) -> 0 | F84: =_xlfn.XLOOKUP($A84,Inputs!$A:$A,Inputs!F:F,,0) -> 0 | G84: =_xlfn.XLOOKUP($A84,Inputs!$A:$A,Inputs!G:G,,0) -> 0 | H84: =_xlfn.XLOOKUP($A84,Inputs!$A:$A,Inputs!H:H,,0) -> 0 | I84: =_xlfn.XLOOKUP($A84,Inputs!$A:$A,Inputs!I:I,,0) -> 0 | J84: =_xlfn.XLOOKUP($A84,Inputs!$A:$A,Inputs!J:J,,0) -> 0 | K84: =_xlfn.XLOOKUP($A84,Inputs!$A:$A,Inputs!K:K,,0) -> 0 | L84: =_xlfn.XLOOKUP($A84,Inputs!$A:$A,Inputs!L:L,,0) -> 0 | M84: =_xlfn.XLOOKUP($A84,Inputs!$A:$A,Inputs!M:M,,0) -> 0
B86: 2020 | C86: 2021 | D86: 2022
A87: Short % of Float | B87: 0 | C87: 0 | D87: 0
A88: EPS | B88: 0 | C88: 0 | D88: 0
A90: Corporate Bonds 3, 5 Y 10 | B90: Average Price | C90: Moody's | D90: YTM | E90: DIVISA
B91: =VLOOKUP($A91,Inputs!$A$5:$M$107,MATCH(B$4,Inputs!$B$5:$M$5,0)+1,FALSE) -> #N/A | C91: =VLOOKUP($A91,Inputs!$A$5:$M$107,MATCH(C$4,Inputs!$B$5:$M$5,0)+1,FALSE) -> #N/A | D91: =VLOOKUP($A91,Inputs!$A$5:$M$107,MATCH(D$4,Inputs!$B$5:$M$5,0)+1,FALSE) -> #N/A | E91: =VLOOKUP($A91,Inputs!$A$5:$M$107,MATCH(E$4,Inputs!$B$5:$M$5,0)+1,FALSE) -> #N/A

Sheet Sector Impact
E2: Sector | F2: Sub-Industry | H2: Low | K2: Sector | L2: Environment | Q2: Social
E3: Communication Services | F3: Interactive Home Entertainment | H3: Medium | L3: CO2 | M3: Water | N3: Energy | O3: Waste | P3: Degradation | Q3: Turnover | R3: Compensation | S3: Reputation | T3: Discrimination | U3: Security | V3: Damage | W3: Pension | X3: Supply | Y3: Community | Z3: Public | AA3: Litigation
E4: Communication Services | F4: Interactive Media & Services | H4: High | K4: Communication Services | L4: Low | M4: Low | N4: Medium | O4: Low | P4: Low | Q4: Medium | R4: Medium | S4: Low | T4: Low | U4: High | V4: Low | W4: Low | X4: Low | Y4: Low | Z4: Low | AA4: Medium
B5: Environmental | E5: Communication Services | F5: Integrated Telecommunication Services | H5: Very High | K5: Consumer Discretionary | L5: Low | M5: Low | N5: Medium | O5: Medium | P5: Low | Q5: Medium | R5: Medium | S5: Low | T5: Low | U5: Medium | V5: Medium | W5: Medium | X5: High | Y5: Low | Z5: High | AA5: Low
B6: Direct CO2 emissions | E6: Communication Services | F6: Cable & Satellite | K6: Consumer Staples | L6: High | M6: Very High | N6: High | O6: High | P6: High | Q6: Medium | R6: High | S6: High | T6: Low | U6: Medium | V6: Medium | W6: Low | X6: High | Y6: Low | Z6: Very High | AA6: Low
B7: Total Water Use | E7: Communication Services | F7: Broadcasting | K7: Energy | L7: Very High | M7: Very High | N7: Medium | O7: Very High | P7: High | Q7: High | R7: Medium | S7: Medium | T7: Medium | U7: Medium | V7: High | W7: Medium | X7: Medium | Y7: High | Z7: High | AA7: Low
K8: Renewable Energy | L8: Low | M8: Low | N8: Low | O8: Medium | P8: Medium | Q8: Low | R8: Medium | S8: Medium | T8: High | U8: Medium | V8: Low | W8: Low | X8: Medium | Y8: Medium | Z8: High | AA8: Low
B9: Total Energy Consumption | E9: Communication Services | F9: Movies & Entertainment | K9: Financials | L9: Low | M9: Low | N9: Low | O9: Low | P9: Low | Q9: Low | R9: Low | S9: Medium | T9: High | U9: Medium | V9: Low | W9: Low | X9: Low | Y9: Low | Z9: Medium | AA9: Low
K10: Forestry | L10: Low | M10: Medium | N10: Low | O10: Medium | P10: High | Q10: Low | R10: Low | S10: Low | T10: Low | U10: Low | V10: Low | W10: Low | X10: Low | Y10: Medium | Z10: Low | AA10: Low
B11: Waste Management | E11: Communication Services | F11: Advertising | K11: Health Care | L11: Low | M11: Medium | N11: Low | O11: Low | P11: Low | Q11: Low | R11: Low | S11: Medium | T11: Low | U11: High | V11: Low | W11: Low | X11: Low | Y11: Low | Z11: Low | AA11: Low
B12: Land Degradation/Deforestation/Biodiversity loss/Animal sufering/... | E12: Communication Services | F12: Alternative Carriers | K12: Industrials | L12: Very High | M12: Very High | N12: Very High | O12: High | P12: High | Q12: Low | R12: Medium | S12: High | T12: Very High | U12: Medium | V12: Very High | W12: Medium | X12: Very High | Y12: Very High | Z12: Very High | AA12: High
B13: Social | E13: Communication Services | F13: Publishing | K13: Information Technology | L13: Medium | M13: Low | N13: High | O13: Low | P13: Low | Q13: Low | R13: Low | S13: Low | T13: Low | U13: High | V13: Low | W13: Low | X13: Low | Y13: Low | Z13: Medium | AA13: Very High
B14: Employee turnover | E14: Communication Services | F14: Wireless Telecommunication Services | K14: Materials | L14: Very High | M14: Very High | N14: Very High | O14: Very High | P14: High | Q14: High | R14: High | S14: Medium | T14: High | U14: Low | V14: Very High | W14: Medium | X14: Medium | Y14: Very High | Z14: High | AA14: Medium
B15: Salaries and compensation | E15: Consumer Discretionary | F15: Automotive Retail | K15: Real Estate | L15: Low | M15: Low | N15: Medium | O15: Low | P15: Low | Q15: Medium | R15: Low | S15: Low | T15: Low | U15: High | V15: Low | W15: Medium | X15: Low | Y15: Medium | Z15: Low | AA15: Low
B16: Reputational issues | E16: Consumer Discretionary | F16: Internet & Direct Marketing Retail | K16: Utilities | L16: Very High | M16: High | N16: High | O16: Medium | P16: High | Q16: Low | R16: Medium | S16: Medium | T16: Low | U16: Medium | V16: Medium | W16: Medium | X16: Medium | Y16: Low | Z16: Medium | AA16: Low
B17: Discrimination issues | E17: Consumer Discretionary | F17: Auto Parts & Equipment
B18: Job security | E18: Consumer Discretionary | F18: Specialty Stores
B19: Health injuries | E19: Consumer Discretionary | F19: Computer & Electronics Retail | L19: Communication Services | M19: Consumer Discretionary | N19: Consumer Staples | O19: Energy | P19: Financials | Q19: Health Care | R19: Industrials | S19: Information Technology | T19: Materials | U19: Real Estate | V19: Utilities
B20: PXP? | E20: Consumer Discretionary | F20: Hotels, Resorts & Cruise Lines | L20: Interactive Home Entertainment | M20: Automotive Retail | N20: Tobacco | O20: Oil & Gas Exploration & Production | P20: Life & Health Insurance | Q20: Health Care Equipment | R20: Industrial Conglomerates | S20: IT Consulting & Other Services | T20: Industrial Gases | U20: Office REITs | V20: Independent Power Producers & Energy Traders
B21: Supply chain | E21: Consumer Discretionary | F21: Restaurants | L21: Interactive Media & Services | M21: Internet & Direct Marketing Retail | N21: Agricultural Products | O21: Oil & Gas Equipment & Services | P21: Property & Casualty Insurance | Q21: Pharmaceuticals | R21: Airlines | S21: Application Software | T21: Specialty Chemicals | U21: Specialized REITs | V21: Electric Utilities
B22: Community involvement | E22: Consumer Discretionary | F22: Homebuilding | L22: Integrated Telecommunication Services | M22: Auto Parts & Equipment | N22: Distillers & Vintners | O22: Integrated Oil & Gas | P22: Consumer Finance | Q22: Health Care Supplies | R22: Building Products | S22: Semiconductors | T22: Paper Packaging | U22: Residential REITs | V22: Multi-Utilities
B23: Public Sector | E23: Consumer Discretionary | F23: General Merchandise Stores | L23: Cable & Satellite | M23: Specialty Stores | N23: Packaged Foods & Meats | O23: Oil & Gas Refining & Marketing | P23: Asset Management & Custody Banks | Q23: Health Care Distributors | R23: Electrical Components & Equipment | S23: Internet Services & Infrastructure | T23: Metal & Glass Containers | U23: Real Estate Services | V23: Water Utilities
B24: Litigation | E24: Consumer Discretionary | F24: Automobile Manufacturers | L24: Broadcasting | M24: Computer & Electronics Retail | N24: Household Products | O24: Oil & Gas Storage & Transportation | P24: Insurance Brokers | Q24: Biotechnology | R24: Aerospace & Defense | S24: Electronic Components | T24: Fertilizers & Agricultural Chemicals | U24: Industrial REITs | V24: Gas Utilities
E25: Consumer Discretionary | F25: Apparel Retail | L25: Movies & Entertainment | M25: Hotels, Resorts & Cruise Lines | N25: Soft Drinks | P25: Multi-line Insurance | Q25: Managed Health Care | R25: Air Freight & Logistics | S25: Technology Hardware, Storage & Peripherals | T25: Commodity Chemicals | U25: Retail REITs
E26: Consumer Discretionary | F26: Consumer Electronics | L26: Advertising | M26: Restaurants | N26: Hypermarkets & Super Centers | P26: Diversified Banks | Q26: Life Sciences Tools & Services | R26: Construction Machinery & Heavy Trucks | S26: Semiconductor Equipment | T26: Diversified Chemicals | U26: Health Care REITs
E27: Consumer Discretionary | F27: Apparel, Accessories & Luxury Goods | L27: Alternative Carriers | M27: Homebuilding | N27: Personal Products | P27: Multi-Sector Holdings | Q27: Health Care Technology | R27: Diversified Support Services | S27: Communications Equipment | T27: Copper | U27: Hotel & Resort REITs
E28: Consumer Discretionary | F28: Leisure Products | L28: Publishing | M28: General Merchandise Stores | N28: Food Retail | P28: Financial Exchanges & Data | Q28: Health Care Services | R28: Railroads | S28: Data Processing & Outsourced Services | T28: Construction Materials
E29: Consumer Discretionary | F29: Home Improvement Retail | L29: Wireless Telecommunication Services | M29: Automobile Manufacturers | N29: Brewers | P29: Investment Banking & Brokerage | Q29: Health Care Facilities | R29: Industrial Machinery | S29: Technology Distributors | T29: Gold
E30: Consumer Discretionary | F30: Casinos & Gaming | M30: Apparel Retail | N30: Food Distributors | P30: Regional Banks | R30: Agricultural & Farm Machinery | S30: Electronic Equipment & Instruments | T30: Steel
E31: Consumer Discretionary | F31: Home Furnishings | M31: Consumer Electronics | N31: Drug Retail | P31: Reinsurance | R31: Research & Consulting Services | S31: Systems Software
E32: Consumer Discretionary | F32: Distributors | M32: Apparel, Accessories & Luxury Goods | P32: Thrifts & Mortgage Finance | R32: Construction & Engineering | S32: Electronic Manufacturing Services
E33: Consumer Discretionary | F33: Housewares & Specialties | M33: Leisure Products | R33: Trucking
E34: Consumer Discretionary | F34: Household Appliances | M34: Home Improvement Retail | R34: Environmental & Facilities Services
E35: Consumer Staples | F35: Tobacco | M35: Casinos & Gaming | R35: Human Resource & Employment Services
E36: Consumer Staples | F36: Agricultural Products | M36: Home Furnishings | R36: Trading Companies & Distributors
E37: Consumer Staples | F37: Distillers & Vintners | M37: Distributors
E38: Consumer Staples | F38: Packaged Foods & Meats | M38: Housewares & Specialties
E39: Consumer Staples | F39: Household Products | M39: Household Appliances
E40: Consumer Staples | F40: Soft Drinks
E41: Consumer Staples | F41: Hypermarkets & Super Centers
E42: Consumer Staples | F42: Personal Products
E43: Consumer Staples | F43: Food Retail
E44: Consumer Staples | F44: Brewers
E45: Consumer Staples | F45: Food Distributors
E46: Consumer Staples | F46: Drug Retail
E47: Energy | F47: Oil & Gas Exploration & Production
E48: Energy | F48: Oil & Gas Equipment & Services
E49: Energy | F49: Integrated Oil & Gas
E50: Energy | F50: Oil & Gas Refining & Marketing
E51: Energy | F51: Oil & Gas Storage & Transportation
... E128: Utilities | F128: Gas Utilities

Sheet Inputs
E2: =1369-1315 -> 54 | G2: Figures in Millions of USD
G3: Company | H3: #VALUE!
D4: Report in millions
A5: RESULTS | B5: 2023 | C5: =B5-1 -> 2022 | D5: =C5-1 -> 2021 | E5: =D5-1 -> 2020 | F5: =E5-1 -> 2019 | G5: =F5-1 -> 2018 | H5: =G5-1 -> 2017 | I5: =H5-1 -> 2016 | J5: =I5-1 -> 2015 | ... M5: =L5-1 -> 2012 | Q5: Hoja | R5: Nombre campo Bloomberg | T5: Cambio de signo | Z5: 2016 | AA5: 2015 | AB5: 2014 | AC5: 2013 | AD5: 2012 | AE5: 2011 | AF5: 2010 | AG5: 2009
A6: Net Sales | B6: 22680 | C6: 23601 | D6: 16434 | E6: 9763 | F6: 6731 | G6: 6475 | H6: 5253 | I6: 4272 | J6: 3991 | K6: 5506 | L6: 5299 | M6: 5422 | N6: Income Statement | O6: Sales | Q6: Ingreso | R6: Ingreso | Z6: 38537 | AA6: 47011 | AB6: 55184 | AC6: 55656 | AD6: 65875 | AE6: 60138 | AF6: 42588 | AG6: 32396
A7: Gross Profit | B7: 10460 | C7: 10603 | D7: 7929 | E7: 4347 | F7: 2868 | G7: 2447 | H7: 1787 | I7: 998 | J7: 1080 | K7: 1839 | L7: 1978 | M7: 1235 | N7: Income Statement | O7: =+A7 -> Gross Profit | Q7: Ingreso | R7: + Coste de bienes y servicios | Z7: =Z6-28044 -> 10493 | AA7: =AA6-33546 -> 13465 | AB7: =AB6-40718 -> 14466 | AC7: =AC6-40727 -> 14929 | AD7: =+AD6-47055 -> 18820 | AE7: =+AE6-43578 -> 16560 | AF7: =+AF6-30367 -> 12221 | AG7: =+AG6-23886 -> 8510
A8: Operating Income | B8: 401 | C8: 1264 | D8: 3641 | E8: 1315 | F8: 455 | G8: 439 | H8: 115 | I8: -440 | J8: -481 | K8: -216 | L8: 102 | M8: -1060 | N8: Income Statement | O8: Operating Income | Q8: Ingreso | R8: + Ventas, generales y admin | Z8: =Z7-4383 -> 6110 | AA8: =AA7-4951 -> 8514 | AB8: =AB7-6529 -> 7937 | AC8: =AC7-5547 -> 9382 | AD8: =AD7-5919-2466-797-580-485 -> 8573 | AE8: =+AE7-5203-2297-826-1081 -> 7153 | AF8: =+AF7-4248-1905-914-1191 -> 3963 | AG8: =+AG7-3645-1421-1045-1822 -> 577
A9: Other Expenses (Revenues) | B9: 8 | C9: 19 | D9: 4 | E9: 4 | F9: =-3+13 -> 10 | G9: =-5-13 -> -18 | H9: =-7+1130 -> 1123 | I9: 135 | J9: -2 | K9: -5 | L9: -2 | M9: 10 | N9: Income Statement | O9: investment income+other income expense+income loss+minority interest+non controlling interest+share onf net profit+gain8losses) on equity investments+share of result from associates nd joint ventures+non operating profit+ | Q9: Ingreso | R9: + Investigación y desarrollo | S9: + Coste de financiación de beneficio | T9: + Otro gasto operativo | U9: - Beneficio (pérdida) de filiales | V9: - Minoritarios | Z9: =1853+596+595+1904+6+8 -> 4962 | AA9: =2119+587+2023+11 -> 4740 | AB9: =2380+624+1619-8+16 -> 4631 | AC9: =2046+727+981+6+14 -> 3774 | AD9: =-14+41 -> 27 | AE9: 53 | AF9: =58+24 -> 82 | AG9: =12-68 -> -56
A10: Net Financial Cost | B10: 99 | C10: -85 | D10: 30 | E10: -39 | F10: -80 | G10: -106 | H10: -123 | I10: -153 | J10: -163 | K10: -177 | L10: -174 | M10: -167 | N10: Income Statement | O10: interest expense+financial income and expenses+other financial expense-income+interest and other net+ | Q10: Ingreso | R10: - Ingreso (pérdida) no operacional | Z10: =505+518 -> 1023 | AA10: =507-161 -> 346 | AB10: =484-322 -> 162 | AC10: =465+35 -> 500 | AD10: =467-130 -> 337 | AE10: =396+32 -> 428 | AF10: =343-130 -> 213 | AG10: =389-381 -> 8
A11: Taxes | B11: 346 | C11: 122 | D11: -513 | E11: 1210 | F11: -44 | G11: 22 | H11: -1148 | I11: -39 | J11: -14 | K11: -5 | L11: -9 | M11: 34 | N11: Income Statement | O11: Taxes | Q11: Ingreso | R11: - Gasto de impuesto a la renta (Beneficio) | Z11: 192 | AA11: 916 | AB11: 692 | AC11: 1319 | AD11: =2528 -> 2528 | AE11: =1720 -> 1720 | AF11: =968 -> 968 | AG11: =-270 -> -270
A12: Net Income | B12: 854 | C12: 1320 | D12: 3162 | E12: 2490 | F12: 341 | G12: 337 | H12: -33 | I12: -497 | J12: -660 | K12: -403 | L12: -83 | M12: -1183 | N12: Income Statement | O12: Net Income | Q12: Flujo de caja | R12: + Ingreso neto | Z12: -67 | AA12: 2512 | AB12: 2452 | AC12: 3789 | AD12: 5681 | AE12: =4928+24 -> 4952 | AF12: 2700 | AG12: 895
Z13: =Z8-Z10-Z9-Z11 -> -67 | AA13: =AA8-AA10-AA9-AA11 -> 2512 | AB13: =AB8-AB10-AB9-AB11 -> 2452 | AC13: =AC8-AC10-AC9-AC11 -> 3789 | AD13: =AD8-AD10-AD9-AD11 -> 5681 | AE13: =AE8-AE10-AE9-AE11 -> 4952 | AF13: =AF8-AF10-AF9-AF11 -> 2700 | AG13: =AG8-AG10-AG9-AG11 -> 895
A14: FINANCIAL POSITION | B14: =B12-B13 -> 854 | C14: =C12-C13 -> 1320 | D14: =D12-D13 -> 3162 | E14: =E12-E13 -> 2490 | F14: =F12-F13 -> 341 | G14: =G12-G13 -> 337 | H14: =H12-H13 -> -33 | I14: =I12-I13 -> -497 | ... M14: =M12-M13 -> -1183 | Z14: =Z12-Z13 -> 0 | AA14: =AA12-AA13 -> 0 | AB14: =AB12-AB13 -> 0 | AC14: =AC12-AC13 -> 0 | AD14: =AD12-AD13 -> 0 | AE14: =AE12-AE13 -> 0 | AF14: =AF12-AF13 -> 0 | AG14: =AG12-AG13 -> 0
A16: Weighted Average Shares (Basic NI) | B16: 1614 | C16: 1561 | D16: 1213 | E16: 1184 | F16: 1091 | G16: 982 | H16: 952 | I16: 835 | J16: 783 | K16: 768 | L16: 754 | M16: 741
A17: Weighted Average Shares (Diluted NI) | B17: 1625 | C17: 1571 | D17: 1229 | E17: 1207 | F17: 1120 | G17: 1064 | H17: 952 | I17: 835 | J17: 783 | K17: 768 | L17: 754 | M17: 741
A19: Net gains (losses) from ForEx | B19: 31 | C19: -38 | D19: -20 | E19: 17 | F19: 8 | G19: -14 | H19: 11 | I19: 3 | J19: -1 | K19: -3 | L19: 0 | M19: 1
A20: Total Comprehensive Income | B20: 885 | C20: 1282 | D20: 3142 | E20: 2507 | F20: 349 | G20: 325 | H20: -22 | I20: -494 | J20: -663 | K20: -406 | L20: -82 | M20: -1181
A22: Changes Net Working Capital | B22: =B23-C23 -> 2331 | C22: =C23-D23 -> 2007 | D22: =D23-E23 -> -323 | E22: =E23-F23 -> 1359 | F22: =F23-G23 -> 294 | G22: =G23-H23 -> 542 | H22: =H23-I23 -> 16 | I22: =I23-J23 -> -212 | ... M22: =M23-N23 -> 319 | N22: cash flows | O22: NWC | Q22: Flujo de caja
A23: Net Working Capital | B23: =B27-B42-B28 -> 6146 | C23: =C27-C42-C28 -> 3815 | D23: =D27-D42-D28 -> 1808 | E23: =E27-E42-E28 -> 2131 | F23: =F27-F42-F28 -> 772 | G23: =G27-G42-G28 -> 478 | H23: =H27-H42-H28 -> -64 | I23: =I27-I42-I28 -> -80 | ... M23: =M27-M42-M28 -> 319
A24: 2625 | B24: 2625 | C24: 2625 | D24: 2625 | E24: 2625 | F24: 2625 | G24: 2625 | H24: 2625 | I24: 2625 | J24: 2625 | K24: 2625 | L24: 2625 | M24: 2625 | N24: 2625 | Q24: Flujo de caja | R24: + Dividendos pagados | T24: Cambiar signo | Z24: 1799 | AA24: 1757 | AB24: 1620 | AC24: 1111 | AD24: 1617 | AE24: 1159 | AF24: 1084 | AG24: 1029
A25: BALANCE SHEET | B25: 2625 | C25: 2625 | D25: 2625 | E25: 2625 | F25: 2625 | G25: 2625 | H25: 2625 | I25: 2625 | J25: 2625 | K25: 2625 | L25: 2625 | M25: 2625 | N25: 2625 | Q25: Flujo de caja | R25: + Aumento en capital | S25: + Baja en capital | T25: Cambiar signo y hacer suma | Z25: 23 | AA25: =-33+2025 -> 1992 | AB25: 3817 | AC25: 1776 | AD25: -244 | AE25: -312 | AF25: -449 | AG25: -110
A26: ASSETS | N26: 1922 | O26: 2625
A27: Current | B27: =SUM(B28:B31) -> 16768 | C27: =SUM(C28:C31) -> 15019 | D27: =SUM(D28:D31) -> 8583 | E27: =SUM(E28:E31) -> 6143 | F27: =SUM(F28:F31) -> 4597 | G27: =SUM(G28:G31) -> 3540 | H27: =SUM(H28:H31) -> 2634 | I27: =SUM(I28:I31) -> 2530 | ... M27: =SUM(M28:M31) -> 2265
A28: Cash & Eq. | B28: 3933 | C28: 4835 | D28: 2535 | E28: 1595 | F28: 1466 | G28: 1078 | H28: 1185 | I28: 1264 | J28: 785 | K28: 805 | L28: 869 | M28: 549 | N28: Balance Sheet | O28: Cash & Eq.
A29: Accounts Receivable | B29: 5376 | C29: 4128 | D29: 2706 | E29: 2066 | F29: 1859 | G29: 1235 | H29: 454 | I29: 311 | J29: 533 | K29: 818 | L29: 832 | M29: 630 | N29: Balance Sheet | O29: Accounts Receivable
A30: Inventory | B30: 4351 | C30: 3771 | D30: 1955 | E30: 1399 | F30: 982 | G30: 845 | H30: 694 | I30: 751 | J30: 678 | K30: 685 | L30: 884 | M30: 562 | N30: Balance Sheet | O30: Inventory | Q30: Balance | R30: + Efectivo, equivalentes y STI | Z30: 7168 | AA30: 6460 | AB30: 7341 | AC30: 6081 | AD30: 5490 | AE30: 3057 | AF30: 3592 | AG30: 4867
A31: Other Current Assets | B31: 3108 | C31: 2285 | D31: 1387 | E31: 1083 | F31: 290 | G31: 382 | H31: 301 | I31: 204 | J31: 324 | K31: 428 | L31: 299 | M31: 524 | N31: Balance Sheet | O31: Inventory | Q31: Balance | R31: + Cuentas y notas por cobrar | S31: + Activos derivados y de cobertura | T31: + Inversiones y cuentas por cobrar a LP | Z31: =5981+8522+1029+13556 -> 29088 | AA31: =6695+8991+1170+13651 -> 30507 | AB31: =7737+9027+1364+14644 -> 32772 | AC31: 33499 | AD31: 33911 | AE31: 31031 | AF31: 28849 | AG31: 27162
A32: Non-current | B32: =B38-B27 -> 51117 | C32: =C38-C27 -> 52561 | D32: =D38-D27 -> 3836 | E32: =E38-E27 -> 2819 | F32: =F38-F27 -> 1431 | G32: =G38-G27 -> 1016 | H32: =H38-H27 -> 918 | I32: =I38-I27 -> 791 | ... M32: =M38-M27 -> 1735
A33: Property, Plant and Equipment | B33: 1589 | C33: 1513 | D33: 702 | E33: 641 | F33: 500 | G33: 348 | H33: 261 | I33: 164 | J33: 188 | K33: 302 | L33: 346 | M33: 658 | Q33: Balance | R33: + Inventarios | Z33: 8614 | AA33: 9700 | AB33: 12205 | AC33: 12625 | AD33: 15547 | AE33: 14544 | AF33: 9587 | AG33: 6360
A34: Operating leases | B34: 633 | C34: 460 | D34: 367 | E34: 208 | F34: 205 | G34: 0 | H34: 0 | I34: 0 | J34: 0 | K34: 0 | L34: 0 | M34: 0
A35: Equity Method Investments | B35: 99 | C35: 83 | D35: 69 | E35: 63 | F35: 58 | G35: 58 | H35: 58 | I35: 59 | J35: 0 | K35: 0 | L35: 90 | M35: 181
A36: Other Non-Current Assets | B36: =B32-SUM(B33:B35) -> 48796 | C36: =C32-SUM(C33:C35) -> 50505 | D36: =D32-SUM(D33:D35) -> 2698 | E36: =E32-SUM(E33:E35) -> 1907 | F36: =F32-SUM(F33:F35) -> 668 | G36: =G32-SUM(G33:G35) -> 610 | H36: =H32-SUM(H33:H35) -> 599 | I36: =I32-SUM(I33:I35) -> 568 | ... M36: =M32-SUM(M33:M35) -> 896 | N36: Balance Sheet | O36: Property, Plant and Equipment
A37: Other Assets | B37: =B31+B36 -> 51904 | C37: =C31+C36 -> 52790 | D37: =D31+D36 -> 4085 | E37: =E31+E36 -> 2990 | F37: =F31+F36 -> 958 | G37: =G31+G36 -> 992 | H37: =H31+H36 -> 900 | I37: =I31+I36 -> 772 | ... M37: =M31+M36 -> 1420 | N37: Balance Sheet
A38: Total Assets | B38: 67885 | C38: 67580 | D38: 12419 | E38: 8962 | F38: 6028 | G38: 4556 | H38: 3552 | I38: 3321 | J38: 3084 | K38: 3767 | L38: 4337 | M38: 4000 | N38: Balance Sheet | O38: Total Assets | Q38: Balance | R38: + Propiedad, planta y equipo; neto | Z38: 15322 | AA38: 16090 | AB38: =16577 -> 16577 | AC38: 17075 | AD38: 16461 | AE38: 14395 | AF38: 12539 | AG38: 12386
N39: Balance Sheet | Z39: =Z40-SUM(Z30:Z38) -> 14512 | AA39: =AA40-SUM(AA30:AA38) -> 15585 | AB39: =AB40-SUM(AB30:AB38) -> 15786 | AC39: =AC40-SUM(AC30:AC38) -> 15616 | AD39: =AD40-SUM(AD30:AD38) -> 17947 | AE39: =AE40-SUM(AE30:AE38) -> 18419 | AF39: =AF40-SUM(AF30:AF38) -> 9453 | AG39: =AG40-SUM(AG30:AG38) -> 9263
N40: Balance Sheet | Q40: Balance | R40: Activos totales | Z40: 74704 | AA40: 78342 | AB40: 84681 | AC40: 84896 | AD40: 89356 | AE40: 81446 | AF40: 64020 | AG40: 60038
A41: LIABILITIES | N41: Balance Sheet
A42: Current Liabilities | B42: 6689 | C42: 6369 | D42: 4240 | E42: 2417 | F42: 2359 | G42: 1984 | H42: 1513 | I42: 1346 | J42: 1403 | K42: 1440 | L42: 1618 | M42: 1397 | N42: Balance Sheet | O42: Current Liabilities
A43: Payables | B43: 2418 | C43: 2956 | D43: 1406 | E43: 546 | F43: 1201 | G43: 1041 | H43: 796 | I43: 823 | J43: 524 | K43: 633 | L43: 883 | M43: 732
A44: Short-Term Debt | B44: 0 | C44: 0 | D44: 0 | E44: 0 | F44: 0 | G44: 136 | H44: 70 | I44: 0 | J44: 230 | K44: 177 | L44: 60 | M44: 0 | N44: Balance Sheet | O44: Short term Debt | Q44: Balance | R44: Pasivos totales corrientes | Z44: 26132 | AA44: 26242 | AB44: 27877 | AC44: 27297 | AD44: 29415 | AE44: =93+3895+8161+3386+2410+2691+298+1967+558+5102 -> 28561 | AF44: =204+3852+5856+2880+1670+1831+281+1521+495+3430 -> 22020 | AG44: =433+3650+2993+3351+797+1217+262+888+302+5399 -> 19292
A45: Short-Term Leases | B45: 0 | C45: 0 | D45: 0 | E45: 0 | F45: 0 | G45: 0 | H45: 0 | I45: 0 | J45: 0 | K45: 0 | L45: 0 | M45: 0
A46: Other current liabilities | B46: =B42-SUM(B43:B45) -> 4271 | C46: =C42-SUM(C43:C45) -> 3413 | D46: =D42-SUM(D43:D45) -> 2834 | E46: =E42-SUM(E43:E45) -> 1871 | F46: =F42-SUM(F43:F45) -> 1158 | G46: =G42-SUM(G43:G45) -> 807 | H46: =H42-SUM(H43:H45) -> 647 | I46: =I42-SUM(I43:I45) -> 523 | ... M46: =M42-SUM(M43:M45) -> 665 | N46: Balance Sheet | R46: + Préstamos CP | Z46: 7303 | AA46: 6967 | AB46: 4708 | AC46: 3679 | AD46: 5287 | AE46: 5660 | AF46: 3925 | AG46: 5701
A47: Non-current Liabilities | B47: =B51-B42 -> 5304 | C47: =C51-C42 -> 6461 | D47: =D51-D42 -> 682 | E47: =E51-E42 -> 708 | F47: =F51-F42 -> 842 | G47: =G51-G42 -> 1306 | H47: =H51-H42 -> 1443 | I47: =I51-I42 -> 1559 | ... M47: =M51-M42 -> 2065 | N47: Balance Sheet | O47: Total non current liabilities
A48: Long-Term Debt | B48: 1717 | C48: 2467 | D48: 1 | E48: 330 | F48: 486 | G48: 1114 | H48: 1325 | I48: 1435 | J48: 2007 | K48: 2035 | L48: 1998 | M48: 2037 | N48: Balance Sheet | O48: Long term debt | Z48: =Z44-Z46 -> 18829 | AA48: =AA44-AA46 -> 19275 | AB48: =AB44-AB46 -> 23169 | AC48: =AC44-AC46 -> 23618 | AD48: =AD44-AD46 -> 24128 | AE48: =AE44-AE46 -> 22901 | AF48: =AF44-AF46 -> 18095 | AG48: =AG44-AG46 -> 13591
A49: Long-Term Leases | B49: 535 | C49: 396 | D49: 348 | E49: 201 | F49: 199 | G49: 0 | H49: 0 | I49: 0 | J49: 0 | K49: 0 | L49: 0 | M49: 0 | Q49: Balance | R49: Pasivos totales no corrientes | Z49: =61491-Z44 -> 35359 | AA49: =63457-AA44 -> 37215 | AB49: =67855-AB44 -> 39978 | AC49: 36721 | AD49: 41973 | AE49: =8415+16529+10956+3583 -> 39483 | AF49: =4505+15932+7584+2654 -> 30675 | AG49: =5652+16195+7420+2179 -> 31446
A50: Other non-current liabilities | B50: =B47-SUM(B48:B49) -> 3052 | C50: =C47-SUM(C48:C49) -> 3598 | D50: =D47-SUM(D48:D49) -> 333 | E50: =E47-SUM(E48:E49) -> 177 | F50: =F47-SUM(F48:F49) -> 157 | G50: =G47-SUM(G48:G49) -> 192 | H50: =H47-SUM(H48:H49) -> 118 | I50: =I47-SUM(I48:I49) -> 124 | ... M50: =M47-SUM(M48:M49) -> 28 | N50: Balance Sheet | O50: Other non current Liabilities | R50: + Préstamos a largo plazo | Z50: 22818 | AA50: 25169 | AB50: 27784 | AC50: 26719 | AD50: 27752 | AE50: 24944 | AF50: 20437 | AG50: 21847
A51: Total Liabilities | B51: 11993 | C51: 12830 | D51: 4922 | E51: 3125 | F51: 3201 | G51: 3290 | H51: 2956 | I51: 2905 | J51: 3496 | K51: 3580 | L51: 3793 | M51: 3462 | N51: Balance Sheet | O51: Total Liabilities
N52: Balance Sheet | Z52: =Z49-Z50 -> 12541 | AA52: =AA49-AA50 -> 12046 | AB52: =AB49-AB50 -> 12194 | AC52: =AC49-AC50 -> 10002 | AD52: =AD49-AD50 -> 14221 | AE52: =AE49-AE50 -> 14539 | AF52: =AF49-AF50 -> 10238 | AG52: =AG49-AG50 -> 9599
N53: Balance Sheet | Z53: =+Z49+Z44 -> 61491 | AA53: =+AA49+AA44 -> 63457 | AB53: =+AB49+AB44 -> 67855 | AC53: =AC44+AC49 -> 64018 | AD53: =AD49+AD44 -> 71388 | AE53: =AE49+AE44 -> 68044 | AF53: =AF49+AF44 -> 52695 | AG53: =AG49+AG44 -> 50738
A54: Minority Interest | B54: 0 | C54: 0 | D54: 0 | E54: 0 | F54: 0 | G54: 0 | H54: 0 | I54: 0 | J54: 0 | K54: 0 | L54: 0 | M54: 0 | N54: Balance Sheet | O54: Minority Interest
N55: Balance Sheet
A56: Shareholder's Equity | B56: =B38-B51-B54 -> 55892 | C56: =C38-C51-C54 -> 54750 | D56: =D38-D51-D54 -> 7497 | E56: =E38-E51-E54 -> 5837 | F56: =F38-F51-F54 -> 2827 | G56: =G38-G51-G54 -> 1266 | H56: =H38-H51-H54 -> 596 | I56: =I38-I51-I54 -> 416 | ... M56: =M38-M51-M54 -> 538 | N56: Balance Sheet | Q56: Balance | R56: + Participación minoritaria/no dominante
A58: CASH FLOW
A59: Operating CF | B59: 1667 | C59: 3565 | D59: 3521 | E59: 1071 | F59: 493 | G59: 34 | H59: 12 | I59: 90 | J59: -226 | K59: -98 | L59: -148 | M59: -338
A60: Net Income | B60: =B12 -> 854 | C60: =C12 -> 1320 | D60: =D12 -> 3162 | E60: =E12 -> 2490 | F60: =F12 -> 341 | G60: =G12 -> 337 | H60: =H12 -> -33 | I60: =I12 -> -497 | ... M60: =M12 -> -1183
A61: Depreciation & Amortization | B61: 3453 | C61: 4174 | D61: 407 | E61: 312 | F61: 222 | G61: 170 | H61: 144 | I61: 133 | J61: 167 | K61: 203 | L61: 236 | M61: 260
A62: Changes in assets and liabilities | B62: -3049 | C62: -1846 | D62: -774 | E62: -931 | F62: -542 | G62: -727 | H62: -244 | I62: 180 | J62: 113 | K62: -291 | L62: -448 | M62: 220
A63: Other Adjustments | B63: =B59-B60-B61-B62 -> 409 | C63: =C59-C60-C61-C62 -> -83 | D63: =D59-D60-D61-D62 -> 726 | E63: =E59-E60-E61-E62 -> -800 | F63: =F59-F60-F61-F62 -> 472 | G63: =G59-G60-G61-G62 -> 254 | H63: =H59-H60-H61-H62 -> 145 | I63: =I59-I60-I61-I62 -> 274 | ... M63: =M59-M60-M61-M62 -> 365
A64: Investing CF | B64: -1423 | C64: 1999 | D64: -686 | E64: -952 | F64: -149 | G64: -170 | H64: -54 | I64: 267 | J64: 147 | K64: -12 | L64: 455 | M64: -19
A65: Net Capex | B65: -546 | C65: -450 | D65: -301 | E65: -294 | F65: -217 | G65: -163 | H65: -113 | I65: -77 | J65: -96 | K65: -95 | L65: -84 | M65: -133
A66: Investments & Acquisitions | B66: -866 | C66: 2465 | D66: -378 | E66: -658 | F66: 41 | G66: -78 | H66: 1 | I66: 342 | J66: 243 | K66: 83 | L66: 539 | M66: 123
A67: Other Inflows (Outflows) | B67: =B64-B65-B66 -> -11 | C67: =C64-C65-C66 -> -16 | D67: =D64-D65-D66 -> -7 | E67: =E64-E65-E66 -> 0 | F67: =F64-F65-F66 -> 27 | G67: =G64-G65-G66 -> 71 | H67: =H64-H65-H66 -> 58 | I67: =I64-I65-I66 -> 2 | ... M67: =M64-M65-M66 -> -9
A68: Financing CF | B68: -1146 | C68: -3264 | D68: -1895 | E68: 6 | F68: 43 | G68: 28 | H68: -33 | I68: 122 | J68: 59 | K68: 46 | L68: 13 | M68: 37
A69: Debt Borrowing | B69: 0 | C69: 991 | D69: 0 | E69: 200 | F69: 0 | G69: 0 | H69: 0 | I69: 782 | J69: 100 | K69: 0 | L69: 55 | M69: 0
A70: Debt Repayment | B70: 0 | C70: -312 | D70: 0 | E70: -200 | F70: -473 | G70: -41 | H70: -110 | I70: -1113 | J70: -44 | K70: -1115 | L70: -55 | M70: -489
A71: Lease Increases | B71: 0 | C71: 0 | D71: 0 | E71: 0 | F71: 0 | G71: 0 | H71: 0 | I71: 0 | J71: 0 | K71: 0 | L71: 0 | M71: 0
A72: Lease Payments | B72: 0 | C72: 0 | D72: 0 | E72: 0 | F72: 0 | G72: 0 | H72: 0 | I72: 0 | J72: 0 | K72: 0 | L72: 0 | M72: 0
A73: Dividends | B73: 0 | C73: 0 | D73: 0 | E73: 0 | F73: 0 | G73: 0 | H73: 0 | I73: 0 | J73: 0 | K73: 0 | L73: 0 | M73: 0 | N73: cash flows FINANCING | O73: Dividends paid
A74: Share buyback | B74: -985 | C74: -3702 | D74: -1762 | E74: 0 | F74: 0 | G74: 0 | H74: 0 | I74: 0 | J74: 0 | K74: 0 | L74: 0 | M74: 0 | N74: cash flows FINANCING | O74: =+A74 -> Share buyback
A75: Other Inflows (Outflows) | B75: =B68-B69-B70-B71-B72-B73-B74 -> -161 | C75: =C68-C69-C70-C71-C72-C73-C74 -> -241 | D75: =D68-D69-D70-D71-D72-D73-D74 -> -133 | E75: =E68-E69-E70-E71-E72-E73-E74 -> 6 | F75: =F68-F69-F70-F71-F72-F73-F74 -> 516 | G75: =G68-G69-G70-G71-G72-G73-G74 -> 69 | H75: =H68-H69-H70-H71-H72-H73-H74 -> 77 | I75: =I68-I69-I70-I71-I72-I73-I74 -> 453 | ... M75: =M68-M69-M70-M71-M72-M73-M74 -> 526
A76: FX
A77: Changes in cash | B77: =B59+B64+B68+B76 -> -902 | C77: =C59+C64+C68+C76 -> 2300 | D77: =D59+D64+D68+D76 -> 940 | E77: =E59+E64+E68+E76 -> 125 | F77: =F59+F64+F68+F76 -> 387 | G77: =G59+G64+G68+G76 -> -108 | H77: =H59+H64+H68+H76 -> -75 | I77: =I59+I64+I68+I76 -> 479 | ... M77: =M59+M64+M68+M76 -> -320
O78: (Vitalis will later fill this info)
A79: Other Data | E79: Corporate Bonds 3, 5 Y 10 | H79: Average Price | J79: Moody's | K79: YTM | L79: DIVISA
A80: Number of employees | B80: 26000 | C80: 10-K | N80: bloomberg
A81: Shares Outstanding (Thousands) | B81: 1615787 | C81: Yahoo finance | N81: bloomberg
A82: Float | B82: 0.9946 | C82: Yahoo finance | N82: bloomberg
A83: Insiders Own | B83: 0.0048 | C83: Yahoo finance | N83: bloomberg
A84: Fitch/ S&P Rating | B84: A- | C84: 10-K | N84: bloomberg
A85: Dividend Yield(Yahoo Finance) | B85: 0 | C85: Yahoo finance | N85: bloomberg
A86: Daily Volume in Millions of USD | B86: 74.76 | C86: Yahoo Finance | N86: bloomberg
B87: =B5 -> 2023 | C87: =C5 -> 2022 | D87: =D5 -> 2021
A88: Short % of Float | B88: 0.0204 | E88: Yahoo Finance
A89: EPS | E89: Yahoo Finance
A92: Interest Expense
A93: Derive interest rate from bonds current yields (weighted average)
Z94: 2006 | AA94: 2005 | AB94: 2005 | AC94: 2004 | AD94: 2004
Z95: 5649 | AA95: 5848 | AB95: 5848 | AC95: 5001 | AD95: 5001
Z96: -- | AA96: -- | AB96: -- | AC96: -- | AD96: --
Z97: 2856 | AA97: 3456 | AB97: 3456 | AC97: 3033 | AD97: 3033
Z98: 2793 | AA98: 2392 | AB98: 2392 | AC98: 1968 | AD98: 1968
Z99: 1140 | AA99: 1016 | AB99: 1016 | AC99: 812 | AD99: 807
Z100: 1140 | AA100: 1016 | AB100: 1016 | AC100: 812 | AD100: 807
Z101: -- | AA101: -- | AB101: -- | AC101: -- | AD101: --
Z102: -- | AA102: -- | AB102: -- | AC102: -- | AD102: --
A103: Normalized Income Statement Financials | C103: 2023 | D103: 2022 | E103: 2021 | F103: 2020 | G103: 2019 | H103: 2018 | I103: 2017 | J103: 2017 | K103: 2016 | L103: 2015 | M103: 2014 | N103: 2013 | O103: 2012 | P103: 2011 | Q103: 2010 | R103: 2009 | S103: 2009 | T103: 2008 | U103: 2008 | V103: 2007 | W103: 2007 | X103: 2007 | Y103: 2006 | Z103: 1205 | AA103: 1144 | AB103: 1144 | AC103: 934 | AD103: 935
A104: Net Sales | C104: 22680 | D104: 23601 | E104: 16434 | F104: 9763 | G104: 6731 | H104: 6475 | I104: 5253 | J104: 5329 | K104: 4272 | L104: 3991 | M104: 5506 | N104: 5299 | O104: 5422 | P104: 6568 | Q104: 6494 | R104: 5403 | S104: 5403 | T104: 5808 | U104: 5808 | V104: 5858 | W104: 5858 | X104: 6013 | Y104: 5627 | Z104: 79 | AA104: 0 | AB104: 0 | AC104: 0 | AD104: --
A105: Non Recurring Revenue (engineering fees) | C105: 258 | D105: 452 | E105: -- | F105: 14 | G105: -- | H105: -- | I105: -- | J105: -- | K105: -- | L105: -- | M105: -- | N105: -- | O105: -- | P105: 0 | Q105: -- | R105: -- | S105: -- | T105: -- | U105: -- | V105: -- | W105: -- | X105: -- | Y105: -- | Z105: 416 | AA105: 0 | AB105: 0 | AC105: 0 | AD105: 5
A106: COGS | C106: 12220 | D106: 12998 | E106: 8505 | F106: 5416 | G106: 3863 | H106: 4028 | I106: 3466 | J106: 3506 | K106: 3274 | L106: 2911 | M106: 3667 | N106: 3321 | O106: 4187 | P106: 3628 | Q106: 3533 | R106: 3131 | S106: 3131 | T106: 3488 | U106: 3488 | V106: 3669 | W106: 3669 | X106: 3751 | Y106: 2833 | Z106: 369 | AA106: 232 | AB106: 232 | AC106: 222 | AD106: 226
A107: Adjusted Gross Income | C107: 10718 | D107: 11055 | E107: 7929 | F107: 4361 | G107: 2868 | H107: 2447 | I107: 1787 | J107: 1823 | K107: 998 | L107: 1080 | M107: 1839 | N107: 1978 | O107: 1235 | P107: 2940 | Q107: 2961 | R107: 2272 | S107: 2272 | T107: 2320 | U107: 2320 | V107: 2189 | W107: 2189 | X107: 2262 | Y107: 2794 | Z107: -- | AA107: -- | AB107: -- | AC107: -- | AD107: --
...
