Workbook
Name Sectors: '[1]Sector Impact'!$K$4:$K$16
Name Sectors: 'Sector Impact'!$K$4:$K$16

Sheet OP
B2: 45039 | C2: Team 1 | E2: =Inputs!H3 -> #VALUE! | L2: NYSE | M2: SIC:
D3: COMPANY DESCRIPTION | H3: CEO & BOARD OF DIRECTORS
D4: {=_FV(Inputs!H3,"Description")} -> Advanced Micro Devices, Inc. is a global semiconductor company. It is focused on high-performance computing, graphics and visualization technologies. It operates in four segments. The Data Center segment includes artificial intelligence (AI) accelerators, server central processing units (CPUs), graphics processing units (GPUs), accelerated processing units (APUs), data processing units (DPUs), field programmable gate arrays (FPGAs), smart network interface cards (SmartNICs), and Adaptive system-on-chip (SoC) products for data centers. The Client segment primarily includes CPUs, APUs, and chipsets for desktops and notebooks. The Gaming segment primarily includes discrete GPUs, semi-custom SoC products and development services. The Embedded segment includes embedded CPUs, GPUs, APUs, FPGAs, system on modules (SOMs), and Adaptive SoC products. It markets and sells its products under the AMD trademark. Its products include AMD EPYC, AMD Ryzen, AMD Ryzen PRO, Virtex UltraScale+ and others. | H4: Name | I4: Gender | J4: Age | K4: Tenure | L4: Executive? | M4: Other roles
H5: Dr. Lisa T. Su | I5: Female | J5: 54 | K5: 12 years | L5: MD’s Chair, President and Chief Executive Officer | M5: Chief Operating Officer, Senior Vice President and General Manager,
H6: Nora M. Denzel | I6: Female | J6: 61 | K6: 10 years | M6: Lead Independent Director
H7: Mark Durcan | I7: Male | J7: 62 | K7: 7 years | M7: Independent Director
H8: Mike P. Gregoire | I8: Male | J8: 58 | K8: 5 years | M8: Independent Director
H9: Joseph A. Householder | I9: Male | J9: 64 | K9: 10 years | M9: Independent Director
H10: John Marren | I10: Male | J10: 57 | K10: 7 years | M10: Independent Director
H11: Jon A. Olson | I11: Male | J11: 70 | K11: 2 years | M11: Independent Director
H12: Abhi Talwalkar | I12: Male | J12: 59 | K12: 7 years | M12: Independent Director
H13: Elizabeth (Beth) Vanderslice | I13: Female | J13: 59 | K13: 2 years | M13: Independent Director
B17: USD MILLIONS
B18: COMPANY OVERVIEW
B19: Stock | D19: Liquidity and Solvency | F19: Segments | I19: Profitability (2022) | L19: Multiples
B20: Last Price | C20: {=_FV(E2,"Price")} -> 78.21 | D20: Total Assets | E20: =_xlfn.XLOOKUP(D20,'Fin. Data'!A:A,'Fin. Data'!B:B,,0) -> 67885 | F20: Regions | H20: % Sales | I20: Reporting Year | J20: 2023 | L20: Float
B21: Outstanding Shares | C21: {=_FV(E2,"Shares outstanding",TRUE)} -> 1616297000 | D21: Total Liabilities | E21: =_xlfn.XLOOKUP(D21,'Fin. Data'!A:A,'Fin. Data'!B:B,,0) -> 11993 | F21: =Segments!C5 -> United States | H21: =Segments!B5 -> 0.34554674 | I21: End of Year | J21: 45291 | L21: Insiders Own
B22: Market Cap. | C22: =C20*C21/1000000 -> 126410.59 | D22: Cash/Share | E22: =_xlfn.XLOOKUP("Cash & Eq.",'Fin. Data'!A:A,'Fin. Data'!B:B,,0)*1000000/C21 -> 2.4333399 | F22: =Segments!C6 -> Japan | H22: =Segments!B6 -> 0.20410053 | I22: EBITDA | K22: =_xlfn.XLOOKUP(I22,'Fin. Data'!A:A,'Fin. Data'!B:B,,0) -> 3846 | L22: b (Yahoo)
B23: +Total Debt | C23: ='Fin. Data'!B58 -> 2252 | D23: EBITDA/Net Financial Cost (NFC) | E23: =_xlfn.XLOOKUP("EBITDA",'Fin. Data'!A:A,'Fin. Data'!B:B,,0)/_xlfn.XLOOKUP("Net Financial Cost",'Fin. Data'!A:A,'Fin. Data'!B:B,,0) -> 38.848485 | F23: =Segments!C7 -> China (including Hong Kong) | H23: =Segments!B7 -> 0.15066138 | I23: Depreciation & Amortization | K23: =_xlfn.XLOOKUP(I23,'Fin. Data'!A:A,'Fin. Data'!B:B,,0) -> 3453 | L23: Score (S&P)
B24: -Cash | C24: ='Fin. Data'!B39 -> 3933 | D24: Debt/EBITDA | E24: =_xlfn.XLOOKUP("Total Debt",'Fin. Data'!A:A,'Fin. Data'!B:B,,0)/_xlfn.XLOOKUP("EBITDA",'Fin. Data'!A:A,'Fin. Data'!B:B,,0) -> 0.58554342 | F24: =Segments!C8 -> Singapore | H24: =Segments!B8 -> 0.098368607 | I24: EBIT | K24: =_xlfn.XLOOKUP(I24,'Fin. Data'!A:A,'Fin. Data'!B:B,,0) -> 393 | L24: Price/Book Value | M24: =IFERROR((C20*C21/(E20-E21))/1000000,"") -> 2.2616938
B25: =Enterprise Value | C25: =C22+C23-C24 -> 124729.59 | D25: "Others Assets"/Asset | E25: =_xlfn.XLOOKUP("Other Assets",'Fin. Data'!A:A,'Fin. Data'!B:B,,0)/_xlfn.XLOOKUP("Total Assets",'Fin. Data'!A:A,'Fin. Data'!B:B,,0) -> 0.76458717 | F25: =Segments!C9 -> Europe | H25: =Segments!B9 -> 0.089506173 | I25: Net Income | K25: =_xlfn.XLOOKUP(I25,'Fin. Data'!A:A,'Fin. Data'!B:B,,0) -> 854 | L25: NCF(3y avg)/Asset | M25: =IFERROR(K31/E20,"") -> 0.026201174
B26: Holdings (nac/int'l) | C26: - | D26: Debt/Assets | E26: =_xlfn.XLOOKUP(D26,'Fin. Data'!A:A,'Fin. Data'!B:B,,0) -> 0.03317375 | F26: Categories | H26: % Sales | I26: EPS | K26: =1000000*K25/C21 -> 0.52836824 | L26: Price/Net Inc. (3y avg) | M26: =IFERROR(C22/K30,"") -> 71.070421
B27: t liq. (Holdings/Vol.) | C27: - | D27: EBITDA Margin (average) | E27: =AVERAGE(_xlfn.XLOOKUP("EBITDA Margin",'Fin. Data'!A:A,'Fin. Data'!B:D,,0)) -> 0.21508695 | F27: =Segments!C19 -> Data Center | H27: =Segments!B19 -> 0.28641975 | I27: ROA | K27: =K25/E20 -> 0.012580099 | L27: EV/Asset | M27: =IFERROR(C25/E20,"") -> 1.837366
B28: % Short | D28: Operating Margin (average) | E28: =AVERAGE(_xlfn.XLOOKUP("Operating Margin",'Fin. Data'!A:A,'Fin. Data'!B:D,,0)) -> 0.097596902 | F28: =Segments!C21 -> Gaming | H28: =Segments!B21 -> 0.27389771 | I28: ROIC | K28: =Peers!C16 -> 0.016072853 | L28: EV/Ebitda (3y average) | M28: =IFERROR(C25/K29,"") -> 28.115468
B29: Traffic ESG | D29: Net Income Margin (average) | E29: =AVERAGE(_xlfn.XLOOKUP("Net Income Margin",'Fin. Data'!A:A,'Fin. Data'!B:D,,0)) -> 0.095330047 | F29: =Segments!C22 -> Embedded | H29: =Segments!B22 -> 0.23461199 | I29: EBITDA (3y average) | K29: =AVERAGE(_xlfn.XLOOKUP("EBITDA",'Fin. Data'!A:A,'Fin. Data'!B:D,,0)) -> 4436.3333 | L29: Price/NCF (3y average) | M29: =IFERROR(C22/K31,"") -> 71.070421
B30: E | F30: =Segments!C20 -> Client | H30: =Segments!B20 -> 0.20507055 | I30: Net Income (3y average) | K30: =AVERAGE(_xlfn.XLOOKUP("Net Income",'Fin. Data'!A:A,'Fin. Data'!B:D,,0)) -> 1778.6667 | L30: Bonds 1,3,5a (USD) | M30: -
B31: S | D31: Net Financial Cost/Avg Net Debt | E31: =-_xlfn.XLOOKUP("Net Financial Cost",'Fin. Data'!A:A,'Fin. Data'!B:B,,0)/AVERAGE(_xlfn.XLOOKUP("Net Debt",'Fin. Data'!A:A,'Fin. Data'!B:D,,0)) -> 0.050864874 | F31: =Segments!#REF! -> #REF! | H31: =Segments!#REF! -> #REF! | I31: NCF (3y average) | K31: =AVERAGE(_xlfn.XLOOKUP("Net Income",'Fin. Data'!A:A,'Fin. Data'!B:D,,0)) -> 1778.6667 | L31: Div+Rep.(3y avg)/Price | M31: =-IFERROR(SUM(E52:E54)/(3*C22),"") -> 0.017005432
B32: G | L32: Div. Yield | M32: =-IFERROR(L53/C22,"") -> 0
B33: INVESTMENT THESIS
B34: Pillars of Recommendation | H34: Recommendation | I34: Valuation Assumptions
B35: Pillar | C35: Explanation | H35: Buy
B36: High growth potential | C36: Increase in demand for AI chips to feed computing needs for generative lenguage models
B37: Special positioning in AI | C37: The company is posing itself to compete with NVIDIA and breaking it's competitive advantage of vertical integration of software and hardware
B38: Future technologies | C38: The company is posed to capitalize on future technologies such as Quantum computers or VR hardware chips might be capitlized and can't be counted on for current projections.
B39: Risks of Investment | H39: Price Target | I39: Valuation
B40: Risk | C40: Explanation | H40: ='Base Case'!D76 -> 183.58063 | I40: Discount Rate | J40: 0.18 | L40: Price M. Upside | M40: =SARD!AJ14 -> #NUM!
B41: Uncertainty | C41: The AI chips industry is not estabeished and the market dynamics projections are merely based on scenarios
B42: High valuation | C42: If the company fails to position itself in the datacenter segment, it's current valuation is too high | I42: Upside | J42: ='Base Case'!D75 -> 1.3472782 | L42: EV M. Upside | M42: =SARD!AM14 -> #NUM!
B43: Geopolitical | C43: High relience on TSMC to outsource production and exposure to chinese market
B44: FINANCIAL PERFORMANCE
B45: Year | C45: Net Sales | D45: Operating Margin | E45: Dividends + Share Buyback | F45: Net Cash Flow | G45: Debt/Assets | H45: Depreciation & Amortization | I45: Capex + Investments | J45: Cash Flow
B46: =B47-1 -> 2015 | C46: {=_xlfn.SORTBY(TRANSPOSE(_xlfn.XLOOKUP(C$45,'Fin. Data'!$A:$A,'Fin. Data'!$B:$J,,0)),$B$46:$B$54,-1)} -> 3991 | D46: {=_xlfn.SORTBY(TRANSPOSE(_xlfn.XLOOKUP(D$45,'Fin. Data'!$A:$A,'Fin. Data'!$B:$J,,0)),$B$46:$B$54,-1)} -> -0.12052117 | E46: {=_xlfn.SORTBY(TRANSPOSE(_xlfn.XLOOKUP(E$45,'Fin. Data'!$A:$A,'Fin. Data'!$B:$J,,0)),$B$46:$B$54,-1)} -> 0 | F46: =Inputs!J77 -> -20 | G46: {=_xlfn.SORTBY(TRANSPOSE(_xlfn.XLOOKUP(G$45,'Fin. Data'!$A:$A,'Fin. Data'!$B:$J,,0)),$B$46:$B$54,-1)} -> 0.72535668 | H46: {=_xlfn.SORTBY(TRANSPOSE(_xlfn.XLOOKUP(H$45,'Fin. Data'!$A:$A,'Fin. Data'!$B:$J,,0)),$B$46:$B$54,-1)} -> 167 | I46: {=_xlfn.SORTBY(TRANSPOSE(_xlfn.XLOOKUP(I$45,'Fin. Data'!$A:$A,'Fin. Data'!$B:$J,,0)),$B$46:$B$54,-1)} -> 147 | L46: =J20 -> 2023 | M46: =L46-1 -> 2022
B47: =B48-1 -> 2016 | C47: 4272 | D47: -0.10299625 | E47: 0 | F47: =Inputs!I77 -> 479 | G47: 0.43209877 | H47: 133 | I47: 265 | J47: Net Income | L47: =_xlfn.XLOOKUP($J47,'Fin. Data'!$A:$A,'Fin. Data'!B:B,,0) -> 854 | M47: =_xlfn.XLOOKUP($J47,'Fin. Data'!$A:$A,'Fin. Data'!C:C,,0) -> 1320 | N47: =(C47/C46)-1 -> 0.070408419 | O47: =(D47/D46)-1 -> -0.14540945
B48: =B49-1 -> 2017 | C48: 5253 | D48: 0.021892252 | E48: 0 | F48: =Inputs!H77 -> -75 | G48: 0.39273649 | H48: 144 | I48: -112 | J48: Operating CF | L48: =_xlfn.XLOOKUP($J48,'Fin. Data'!$A:$A,'Fin. Data'!B:B,,0) -> 1667 | M48: =_xlfn.XLOOKUP($J48,'Fin. Data'!$A:$A,'Fin. Data'!C:C,,0) -> 3565 | N48: =(C48/C47)-1 -> 0.22963483 | O48: =(D48/D47)-1 -> -1.2125539 | Q48: =F48/F47-1 -> -1.1565762 | R48: =H48/H47-1 -> 0.082706767 | S48: =I48/I47-1 -> -1.4226415
B49: =B50-1 -> 2018 | C49: 6475 | D49: 0.067799228 | E49: 0 | F49: =Inputs!G77 -> -108 | G49: 0.27436348 | H49: 170 | I49: -241 | J49: Investing CF | L49: =_xlfn.XLOOKUP($J49,'Fin. Data'!$A:$A,'Fin. Data'!B:B,,0) -> -1423 | M49: =_xlfn.XLOOKUP($J49,'Fin. Data'!$A:$A,'Fin. Data'!C:C,,0) -> 1999 | N49: =(C49/C48)-1 -> 0.23262897 | O49: =(D49/D48)-1 -> 2.0969508 | Q49: =F49/F48-1 -> 0.44 | R49: =H49/H48-1 -> 0.18055556 | S49: =I49/I48-1 -> 1.1517857
B50: =B51-1 -> 2019 | C50: 6731 | D50: 0.067597682 | E50: 0 | F50: =Inputs!F77 -> 387 | G50: 0.11363636 | H50: 222 | I50: -176 | J50: Net Capex | L50: =_xlfn.XLOOKUP($J50,'Fin. Data'!$A:$A,'Fin. Data'!B:B,,0) -> -546 | M50: =_xlfn.XLOOKUP($J50,'Fin. Data'!$A:$A,'Fin. Data'!C:C,,0) -> -450 | N50: =(C50/C49)-1 -> 0.03953668 | O50: =(D50/D49)-1 -> -0.0029726804 | Q50: =F50/F49-1 -> -4.5833333 | R50: =H50/H49-1 -> 0.30588235 | S50: =I50/I49-1 -> -0.26970954
B51: =B52-1 -> 2020 | C51: 9763 | D51: 0.13469221 | E51: 0 | F51: =Inputs!E77 -> 125 | G51: 0.059250167 | H51: 312 | I51: -952 | J51: Investments & Acquisitions | L51: =_xlfn.XLOOKUP($J51,'Fin. Data'!$A:$A,'Fin. Data'!B:B,,0) -> -866 | M51: =_xlfn.XLOOKUP($J51,'Fin. Data'!$A:$A,'Fin. Data'!C:C,,0) -> 2465 | N51: =(C51/C50)-1 -> 0.45045313 | O51: =(D51/D50)-1 -> 0.99255656 | Q51: =F51/F50-1 -> -0.67700258 | R51: =H51/H50-1 -> 0.40540541 | S51: =I51/I50-1 -> 4.4090909
B52: =B53-1 -> 2021 | C52: 16434 | D52: 0.22155288 | E52: -1762 | F52: =Inputs!D77 -> 940 | G52: 0.028102102 | H52: 407 | I52: -679 | J52: Financing CF | L52: =_xlfn.XLOOKUP($J52,'Fin. Data'!$A:$A,'Fin. Data'!B:B,,0) -> -1146 | M52: =_xlfn.XLOOKUP($J52,'Fin. Data'!$A:$A,'Fin. Data'!C:C,,0) -> -3264 | N52: =(C52/C51)-1 -> 0.68329407 | O52: =(D52/D51)-1 -> 0.6448827 | Q52: =F52/F51-1 -> 6.52 | R52: =H52/H51-1 -> 0.30448718 | S52: =I52/I51-1 -> -0.28676471
B53: =B54-1 -> 2022 | C53: 23601 | D53: 0.053557053 | E53: -3702 | F53: =Inputs!C$77 -> 2300 | G53: 0.042364605 | H53: 4174 | I53: 2015 | J53: Dividends | L53: =_xlfn.XLOOKUP($J53,'Fin. Data'!$A:$A,'Fin. Data'!B:B,,0) -> 0 | M53: =_xlfn.XLOOKUP($J53,'Fin. Data'!$A:$A,'Fin. Data'!C:C,,0) -> 0 | N53: =(C53/C52)-1 -> 0.43610807 | O53: =(D53/D52)-1 -> -0.75826515 | Q53: =F53/F52-1 -> 1.4468085 | R53: =H53/H52-1 -> 9.2555283 | S53: =I53/I52-1 -> -3.9675994
B54: =J20 -> 2023 | C54: 22680 | D54: 0.017680776 | E54: -985 | F54: =Inputs!B77 -> -902 | G54: 0.03317375 | H54: 3453 | I54: -1412 | J54: Share Buyback | L54: =_xlfn.XLOOKUP($J54,'Fin. Data'!$A:$A,'Fin. Data'!B:B,,0) -> -985 | M54: =_xlfn.XLOOKUP($J54,'Fin. Data'!$A:$A,'Fin. Data'!C:C,,0) -> -3702 | N54: =(C54/C53)-1 -> -0.03902377 | O54: =(D54/D53)-1 -> -0.66987026 | Q54: =F54/F53-1 -> -1.3921739 | R54: =H54/H53-1 -> -0.17273598 | S54: =I54/I53-1 -> -1.7007444
B55: Annual Growth Rate | C55: =IFERROR((C54/C46)^(1/8)-1,"") -> 0.242568 | D55: =IFERROR((D54/D46)^(1/8)-1,"") | F55: =IFERROR((F54/F46)^(1/8)-1,"") -> 0.60980054 | H55: =IFERROR((H54/H46)^(1/8)-1,"") -> 0.46027622 | J55: FX | L55: =_xlfn.XLOOKUP($J55,'Fin. Data'!$A:$A,'Fin. Data'!B:B,,0) -> 0 | M55: =_xlfn.XLOOKUP($J55,'Fin. Data'!$A:$A,'Fin. Data'!C:C,,0) -> 0 | N55: =(C55/C54)-1 -> -0.9999893 | O55: =(D55/D54)-1 -> #VALUE!
B56: Average Growth Rate | C56: =IFERROR(AVERAGE(N47:N54),"") -> 0.26288005 | D56: =IFERROR(AVERAGE(O47:O54),"") -> 0.11816483 | F56: =IFERROR(AVERAGE(Q47:Q54),"") -> 0.085388926 | H56: =IFERROR(AVERAGE(S47:S54),"") -> -0.29808328 | J56: Changes in Cash | L56: =L48-L49+L52-L53-L54 -> 2929 | M56: =M48-M49+M52-M53-M54 -> 2004
B57: CVAR | C57: =IFERROR(STDEV(C47:C54)/AVERAGE(C47:C54),"") -> 0.66372218 | D57: =IFERROR(STDEV(D46:D54)/AVERAGE(D46:D54),"") -> 2.6525091 | F57: =IFERROR(STDEV(F46:F54)/AVERAGE(F46:F54),"") -> 2.5577588 | H57: =IFERROR(STDEV(H46:H54)/AVERAGE(H46:H54),"") -> 1.5646555 | J57: Inventory/D Revenues | L57: =IFERROR(SUM(I51:I54)/(C54-C50),"") -> -0.064455452 | M57: =IFERROR((SUM(I51:I54)-SUM(H51:H54))/(C54-C50),"") -> -0.58774845
B58: Last Year | C58: =IFERROR(C54/C53-1,"") -> -0.03902377 | D58: =IFERROR(D54/D53-1,"") -> -0.66987026 | F58: =IFERROR(1-(F54/F53),"") -> 1.3921739 | H58: =IFERROR(1-(H54/H53),"") -> 0.17273598 | J58: t inversiones; t adq. neto dep. | L58: =IFERROR(L57/E27,"") -> -0.29967161 | M58: =IFERROR(M57/E27,"") -> -2.7326086
B59: QUALITATIVE ANALYSIS
B60: SWOT ANALYSIS | J60: HOLDERS
B61: Pros | E61: Cons | J61: Name | M61: % Stake
B62: Strong brand- AMD has been one of the industry leaders for a while, maintaining a respected brand name and constantly innovating their products Lower pricing comparing to Intel- Especially in the mid range prices, AMD has cheaper prices with the same perfomance as Intel Product inovation(chips)- For example the Ryzen 8000GE series, are chips from AMD that are more energy-efficient, used in mobile devices and some desktop devices. | E62: Reliance on the PC market Volatile stock, Beta of 1.63 Lack of presence in the mobile devices industry | J62: Vanguard Group Inc | M62: 8,81
J63: Blackrock Inc. | M63: 7,65
J64: State Street Corporation | M64: 4,10
J65: FMR, LLC | M65: 2,5
J66: JP Morgan Chase & Company | M66: 2,23
J67: Geode Capital Management, LLC | M67: 1,97
J68: Fisher Asset Management, LLC | M68: 1,75
J69: Price (T.Rowe) Associates Inc | M69: 1,71
J70: Jennison Associates LLC | M70: 1,66
J71: Morgan Stanley | M71: 1,65
B72: Opportunities | E72: Risks
B73: Increased demand of chips Rise of mobile devices for gaming and work | E73: Strong competition between brands Environmental Regulations Supply chain risk
E74: Environmental Regulations
B82: NOTES | G82: STOCK PERFORMANCE (5 years)
B83: Through our analysis, we have concluded that there is a high dispersion of possibilities for AMD earnings and it's intrinsic value. Given the higher potential for upside, we recomend a buy with caution. We also think that AMD's stock should be bought togheter with other AI stocks as a way to diversify exposure.

Sheet Segments
B2: ="Regions "&"("&OP!$J$20&")" -> Regions (2023) | Q2: Products
D3: Nominal value | K3: YoY Growth
B4: Weight | C4: Region | D4: =OP!J20 -> 2023 | E4: =D4-1 -> 2022 | F4: =E4-1 -> 2021 | G4: =F4-1 -> 2020 | H4: =G4-1 -> 2019 | I4: =H4-1 -> 2018 | K4: =OP!J20 -> 2023 | L4: =K4-1 -> 2022 | M4: =L4-1 -> 2021 | N4: =M4-1 -> 2020 | O4: =N4-1 -> 2019 | P4: =O4-1 -> 2018
B5: =IFERROR(D5/$D$14,"") -> 0.34554674 | C5: United States | D5: 7837 | E5: 8049 | F5: 4656 | G5: 2294 | H5: 1764 | I5: 1327 | K5: =(D5-E5)/E5 -> -0.026338676 | L5: =(E5-F5)/F5 -> 0.72873711 | M5: =(F5-G5)/G5 -> 1.0296425 | N5: =(G5-H5)/H5 -> 0.30045351 | O5: =(H5-I5)/I5 -> 0.32931424 | P5: -
B6: =IFERROR(D6/$D$14,"") -> 0.20410053 | C6: Japan | D6: 4629 | E6: 4177 | F6: 2381 | G6: 1033 | H6: 840 | I6: 1225 | K6: =(D6-E6)/E6 -> 0.10821164 | L6: =(E6-F6)/F6 -> 0.75430491 | M6: =(F6-G6)/G6 -> 1.3049371 | N6: =(G6-H6)/H6 -> 0.2297619 | O6: =(H6-I6)/I6 -> -0.31428571 | P6: -
B7: =IFERROR(D7/$D$14,"") -> 0.15066138 | C7: China (including Hong Kong) | D7: 3417 | E7: 5207 | F7: 4096 | G7: 2329 | H7: 1736 | I7: 1319 | K7: =(D7-E7)/E7 -> -0.343768 | L7: =(E7-F7)/F7 -> 0.27124023 | M7: =(F7-G7)/G7 -> 0.75869472 | N7: =(G7-H7)/H7 -> 0.34158986 | O7: =(H7-I7)/I7 -> 0.3161486 | P7: -
B8: =IFERROR(D8/$D$14,"") -> 0.098368607 | C8: Singapore | D8: 2231 | E8: 1380 | F8: 1389 | G8: 1096 | H8: 597 | I8: 728 | K8: =(D8-E8)/E8 -> 0.61666667 | L8: =(E8-F8)/F8 -> -0.0064794816 | M8: =(F8-G8)/G8 -> 0.26733577 | N8: =(G8-H8)/H8 -> 0.8358459 | O8: =(H8-I8)/I8 -> -0.17994505 | P8: -
B9: =IFERROR(D9/$D$14,"") -> 0.089506173 | C9: Europe | D9: 2030 | E9: 1773 | F9: 1249 | G9: 1108 | H9: 762 | I9: 470 | K9: =(D9-E9)/E9 -> 0.14495206 | L9: =(E9-F9)/F9 -> 0.41953563 | M9: =(F9-G9)/G9 -> 0.12725632 | N9: =(G9-H9)/H9 -> 0.45406824 | O9: =(H9-I9)/I9 -> 0.6212766 | P9: -
B10: =IFERROR(D10/$D$14,"") -> 0.08117284 | C10: Taiwan | D10: 1841 | E10: 2369 | F10: 2091 | G10: 1187 | H10: 719 | I10: 1197 | K10: =(D10-E10)/E10 -> -0.22287885 | L10: =(E10-F10)/F10 -> 0.13295074 | M10: =(F10-G10)/G10 -> 0.76158382 | N10: =(G10-H10)/H10 -> 0.65090403 | O10: =(H10-I10)/I10 -> -0.39933166 | P10: -
B11: =IFERROR(D11/$D$14,"") -> 0 | C11: Taiwan | K11: =(D11-E11)/E11 -> #DIV/0! | L11: =(E11-F11)/F11 -> #DIV/0! | M11: =(F11-G11)/G11 -> #DIV/0! | N11: =(G11-H11)/H11 -> #DIV/0! | O11: =(H11-I11)/I11 -> #DIV/0!
B12: =IFERROR(D12/$D$14,"") -> 0 | C12: Taiwan | K12: =(D12-E12)/E12 -> #DIV/0! | L12: =(E12-F12)/F12 -> #DIV/0! | M12: =(F12-G12)/G12 -> #DIV/0! | N12: =(G12-H12)/H12 -> #DIV/0! | O12: =(H12-I12)/I12 -> #DIV/0!
B13: =IFERROR(D13/$D$14,"") -> 0.030643739 | C13: Other countries | D13: 695 | E13: 646 | F13: 572 | G13: 716 | H13: 313 | I13: 0 | K13: =(D13-E13)/E13 -> 0.075851393 | L13: =(E13-F13)/F13 -> 0.12937063 | M13: =(F13-G13)/G13 -> -0.20111732 | N13: =(G13-H13)/H13 -> 1.2875399 | O13: =(H13-I13)/I13 -> #DIV/0! | P13: -
B14: =SUM(B5:B12) -> 0.96935626 | C14: TOTAL | D14: =SUM(D5:D13) -> 22680 | E14: =SUM(E5:E13) -> 23601 | F14: =SUM(F5:F13) -> 16434 | G14: =SUM(G5:G13) -> 9763 | H14: =SUM(H5:H13) -> 6731 | I14: =SUM(I5:I13) -> 6266 | K14: =(D14-E14)/E14 -> -0.03902377 | L14: =(E14-F14)/F14 -> 0.43610807 | M14: =(F14-G14)/G14 -> 0.68329407 | N14: =(G14-H14)/H14 -> 0.45045313 | O14: =(H14-I14)/I14 -> 0.074210022 | P14: -
B16: ="Categories "&"("&OP!$J$20&")" -> Categories (2023)
D17: Nominal value | K17: YoY Growth
B18: Weight | C18: Category | D18: =OP!J20 -> 2023 | E18: =D18-1 -> 2022 | F18: =E18-1 -> 2021 | G18: =F18-1 -> 2020 | H18: =G18-1 -> 2019 | I18: =H18-1 -> 2018 | K18: =OP!J20 -> 2023 | L18: =K18-1 -> 2022 | M18: =L18-1 -> 2021 | N18: =M18-1 -> 2020 | O18: =N18-1 -> 2019 | P18: =O18-1 -> 2018
B19: =IFERROR(D19/$D$23,"") -> 0.28641975 | C19: Data Center | D19: 6496 | E19: 6043 | F19: 3694 | K19: =(D19-E19)/E19 -> 0.074962767 | L19: =(E19-F19)/F19 -> 0.63589605 | M19: =(F19-G19)/G19 -> #DIV/0! | N19: =(G19-H19)/H19 -> #DIV/0! | O19: =(H19-I19)/I19 -> #DIV/0! | P19: -
B20: =IFERROR(D20/$D$23,"") -> 0.20507055 | C20: Client | D20: 4651 | E20: 6201 | F20: 6887 | K20: =(D20-E20)/E20 -> -0.24995968 | L20: =(E20-F20)/F20 -> -0.099607957 | M20: =(F20-G20)/G20 -> #DIV/0! | N20: =(G20-H20)/H20 -> #DIV/0! | O20: =(H20-I20)/I20 -> #DIV/0! | P20: -
B21: =IFERROR(D21/$D$23,"") -> 0.27389771 | C21: Gaming | D21: 6212 | E21: 6805 | F21: 5607 | K21: =(D21-E21)/E21 -> -0.087141807 | L21: =(E21-F21)/F21 -> 0.21366149 | M21: =(F21-G21)/G21 -> #DIV/0! | N21: =(G21-H21)/H21 -> #DIV/0! | O21: =(H21-I21)/I21 -> #DIV/0! | P21: -
B22: =IFERROR(D22/$D$23,"") -> 0.23461199 | C22: Embedded | D22: 5321 | E22: 4552 | F22: 246 | K22: =(D22-E22)/E22 -> 0.16893673 | L22: =(E22-F22)/F22 -> 17.504065 | M22: =(F22-G22)/G22 -> #DIV/0! | N22: =(G22-H22)/H22 -> #DIV/0! | O22: =(H22-I22)/I22 -> #DIV/0! | P22: -
B23: =SUM(B19:B22) -> 1 | C23: TOTAL | D23: =SUM(D19:D22) -> 22680 | E23: =SUM(E19:E22) -> 23601 | F23: =SUM(F19:F22) -> 16434 | G23: =G14 -> 9763 | H23: =H14 -> 6731 | I23: =I14 -> 6266 | K23: =(D23-E23)/E23 -> -0.03902377 | L23: =(E23-F23)/F23 -> 0.43610807 | M23: =(F23-G23)/G23 -> 0.68329407 | N23: =(G23-H23)/H23 -> 0.45045313 | O23: =(H23-I23)/I23 -> 0.074210022 | P23: -
B25: Categories | D25: Description | I25: Graphs
B26: Data Center | D26: Data Center segment offers products for data center market to address the computational, visual data processing and AI workload acceleration needs. Products are Server CPU, Data Center GPUs, FPGAs and Adaptive SoCs, and DPUs.
B27: Client | D27: Client segment offers CPUs and chipsets for computing platforms such as desktops, notebooks, and commercial PCs solutions.
B28: Gaming | D28: AMD produces GPUs and CPUs for gaming industry specifically adressing graphic improvements.
B29: Embedded | D29: The Embedded segment primarily includes embedded CPUs, GPUs, APUs, FPGAs, and Adaptive SoC products. Embedded products address specific computing needs in automotive, industrial, medical and 12 other markets.
B32: Industry | J32: Graphs (Industry Forecasts)
B33: Drivers | D33: Description
B34: Automative industry | D34: The automotive industry's increasing demand for chips, driven by electric vehicles and autonomous features, is a major force in the semiconductor sector. Semiconductors are essential for powering functions like sensors, connectivity systems, and advanced driver-assistance systems. Regulatory mandates for electric vehicle production and the trend towards vehicle electrification further propel this reliance on semiconductors. Consequently, automotive applications have become a crucial focus area for semiconductor companies, expected to drive significant revenue growth in the industry.
B35: AI Chips | D35: AI chips represent a key driver in the semiconductor industry, catering to the growing demand for artificial intelligence (AI) technologies across various sectors. These specialized chips are designed to optimize the performance of AI algorithms, enabling faster processing speeds and energy efficiency for tasks like machine learning, deep learning, and neural network computations. The increasing adoption of AI in applications such as data centers, autonomous vehicles, healthcare, and smart devices has fueled the demand for AI chips.
B36: Wireless Industries | D36: Semiconductors play a crucial role in enabling wireless communication technologies such as Wi-Fi, Bluetooth, cellular networks, and emerging standards like 5G. With the proliferation of mobile devices, smart homes, Internet of Things (IoT) devices, and the digitization of industries, the demand for wireless semiconductor solutions continues to grow.
B37: Cloud/Data Centers | D37: Semiconductors are essential components in the infrastructure of cloud computing and data centers, powering servers, networking equipment, storage devices, and other critical systems. As businesses and consumers rely more on cloud services for data storage, processing, and analytics, the demand for high-performance and energy-efficient semiconductor solutions continues to rise.
B38: Sales forecast
B39: Source | D39: Market Growth CAGR | G39: Period
B40: Statista | D40: 0.063 | G40: 2024-2027
B41: Precedence Research | D41: 0.0764 | G41: 2024-2033
B42: DataHorizzon Research | D42: 0.08 | G42: 2023-2032
B43: Average | D43: =AVERAGE(D40:F42) -> 0.073133333
B44: Company's Strategy / Extra Notes
B47: AMD's strategy is focused on five strategic pillars: extend leadership in foundational technology and IP, provide competitive software, tools and open-source enablement, re-use core technology across platforms to achieve economies of scale, build effective ecosystems with disciplined partnerships, and drive customer-centric go-to-market that leverages all of AMD’s capabilities. They understand the potential of AI and expect this part of their business to grow. AMD offers products that include capabilities to support AI deployment. With the acquisitions of Mipsology SAS and Nod, Inc. in 2023, they expanded their AI software capabilities to accelerate their AI growth strategy centered on an open software ecosystem to help lower the barriers of entry for customers through developer tools, libraries and models. Moreover, AMD develop software platforms that are used to enable high-performance products. These software platforms include development tools, compilers, and drivers for our CPUs, APUs, GPUs and FPGAs. They work closely with customers to define and develop customized solutions to precisely match their requirements. In other words, they focus on industry specific customer orientation.

Sheet Acuerdo
A1: Invertir
A2: NO invertir
A3: Mantener sin elevar posición
A4: Mantener (y seguir comprando)
A5: Liquidar
A6: PENDIENTE

Sheet Peers
B1: Peer Logo | C1: Peer Name | D1: Description
B2: #VALUE! | C2: #VALUE! | D2: Nvidia Corporation is an American multinational corporation and technology company headquartered in Santa Clara, California. It is a software and fabless company which designs and supplies GPUs, APIs for data science and high-performance computing as well as system on a chip unit for the mobile computing and automotive market. Nvidia is also a dominant supplier of artificial intelligence, hardware and software.
A3: Intel Corporation is an American multinational corporation and technology company headquartered in Santa Clara, California, and incorporated in Delaware.[3] Intel is one of the world's largest semiconductor chip manufacturers by revenue[4][5] and ranked in the Fortune 500 list of the largest United States corporations by revenue for nearly a decade, from 2007 to 2016 fiscal years, until it was removed from the ranking in 2018.[6] In 2020, it was reinstated and ranked 45th, being the 7th-largest technology company in the ranking. | B3: #VALUE! | C3: #VALUE! | D3: Intel Corporation is an American multinational corporation and technology company founded in 1968 headquartered in Santa Clara, California. Intel supplies microprocessors for most manufacturers of computer systems, and is one of the developers of the x86 series of instruction sets found in most personal computers (PCs). It also manufactures chipsets, network interface controllers, flash memory, GPUs, FPGAs, it has a strong presence in the high-performance general-purpose and gaming PC market.
A4: Intel supplies microprocessors for most manufacturers of computer systems, and is one of the developers of the x86 series of instruction sets found in most personal computers (PCs). It also manufactures chipsets, network interface controllers, flash memory, graphics processing units (GPUs), field-programmable gate arrays (FPGAs), and other devices related to communications and computing. Intel has a strong presence in the high-performance general-purpose and gaming PC market with its Intel Core line of CPUs, whose high-end models are among the fastest consumer CPUs, as well as its Intel Arc series of GPUs, and sponsors the Intel Extreme Masters, a series of international esports tournaments. The Open Source Technology Center at Intel hosts PowerTOP and LatencyTOP, and supports other open source projects such as Wayland, Mesa, Threading Building Blocks (TBB), and Xen.[7] | B4: #VALUE! | C4: #VALUE! | D4: Qualcomm Incorporated is an American multinational corporation headquartered in San Diego, California. It creates semiconductors, software, and services related to wireless technology. It owns patents critical to the 5G, 4G, CDMA2000, TD-SCDMA and WCDMA mobile communications standards. Over the years, Qualcomm has expanded into selling semiconductor products in a predominantly fabless manufacturing model. It also developed semiconductor components or software for vehicles, watches, laptops, wi-fi, smartphones, and other devices.
B6: In Millions USD | C6: =OP!E2 -> #VALUE! | D6: =C2 -> #VALUE! | E6: =C3 -> #VALUE! | F6: =C4 -> #VALUE! | G6: AVERAGE | H6: Deviation from Average
B7: Company Info | F7: =1113*F43 -> 138746.58 | G7: =IFERROR(AVERAGE(C7:F7),"") -> 138746.58 | K7: TRAFFIC
B8: Market Cap | C8: {=_FV(C6,"Market cap",TRUE)/1000000} -> 126410.59 | D8: =2500.75*D43 -> 240822.23 | E8: =4264*E43 -> 77306.32 | G8: =IFERROR(AVERAGE(C8:F8),"") -> 148179.71 | H8: =SQRT((C8-G8)^2) -> 21769.123 | L8: Best Value
B9: Net Sales (current) | C9: =C55 -> 22680 | D9: =D55 -> 60922 | E9: =E55 -> 54228 | F9: =F55 -> 35820 | G9: =IFERROR(AVERAGE(C9:F9),"") -> 43412.5 | H9: =SQRT((C9-G9)^2) -> 20732.5
B10: Profitability | G10: =IFERROR(AVERAGE(C10:F10),"") | L10: Important Value
B11: Sales Growth (ttm) | C11: =C55/C54-1 -> -0.03902377 | D11: =D55/D54-1 -> 1.2585453 | E11: =E55/E54-1 -> -0.13997526 | F11: =F55/F54-1 -> -0.18959276 | G11: =IFERROR(AVERAGE(C11:F11),"") -> 0.22248837 | H11: =SQRT((C11-G11)^2) -> 0.26151214
B12: Sales Growth (36m) | C12: =C55/C53-1 -> 1.3230564 | D12: =D55/D53-1 -> 2.6534933 | E12: =E55/E53-1 -> -0.30358175 | F12: =F55/F53-1 -> 0.52224725 | G12: =IFERROR(AVERAGE(C12:F12),"") -> 1.0488038 | H12: =SQRT((C12-G12)^2) -> 0.27425264 | L12: Worst Value
B13: Operating Margin | C13: =C59/C55 -> 0.017680776 | D13: =D59/D55 -> 0.54121664 | E13: =E59/E55 -> 0.0017149812 | F13: =F59/F55 -> 0.21742044 | G13: =IFERROR(AVERAGE(C13:F13),"") -> 0.19450821 | H13: =SQRT((C13-G13)^2) -> 0.17682743
B14: Net Income Margin | C14: =C62/C55 -> 0.037654321 | D14: =D62/D55 -> 0.48849348 | E14: =E62/E55 -> 0.030888102 | F14: =F62/F55 -> 0.20189838 | G14: =IFERROR(AVERAGE(C14:F14),"") -> 0.18973357 | H14: =SQRT((C14-G14)^2) -> 0.15207925
B15: Return on Equity (RoE) | C15: =C62/C75 -> 0.015279468 | D15: =D62/D75 -> 0.6924473 | E15: =E62/E75 -> 0.015232119 | F15: =F62/F75 -> 0.33510959 | G15: =IFERROR(AVERAGE(C15:F15),"") -> 0.26451712 | H15: =SQRT((C15-G15)^2) -> 0.24923765
B16: Return on Invested Capital (ROIC) | C16: =(1+C61/(C59+C60))*C59/(C74+C75-C66) -> 0.016072853 | D16: =(1+D61/(D59+D60))*D59/(D74+D75-D66) -> 0.79658424 | E16: =(1+E61/(E59+E60))*E59/(E74+E75-E66) -> -9.9665671e-05 | F16: =(1+F61/(F59+F60))*F59/(F74+F75-F66) -> 0.27490604 | G16: =IFERROR(AVERAGE(C16:F16),"") -> 0.27186587 | H16: =SQRT((C16-G16)^2) -> 0.25579302
B17: Solvency | G17: =IFERROR(AVERAGE(C17:F17),"")
B18: Debt/Assets | C18: =C74/C71 -> 0.03317375 | D18: =D74/D71 -> 0.16473953 | E18: =E74/E71 -> 0.25716702 | F18: =F74/F71 -> 0.30591693 | G18: =IFERROR(AVERAGE(C18:F18),"") -> 0.19024931 | H18: =SQRT((C18-G18)^2) -> 0.15707556
B19: Net Debt/EBITDA | C19: =(C74-C66)/C58 -> -0.43707748 | D19: =(D74-D66)/D58 -> 0.10290023 | E19: =(E74-E66)/E58 -> 5.3132242 | F19: =(F74-F66)/F58 -> 0.74648328 | G19: =IFERROR(AVERAGE(C19:F19),"") -> 1.4313826 | H19: =SQRT((C19-G19)^2) -> 1.86846
B20: Interest Coverage Ratio | C20: =-C58/C60 -> 36.283019 | D20: =-D58/D60 -> 134.16342 | E20: =-E58/E60 -> 9.0432802 | F20: =-F58/F60 -> 13.82853 | G20: =IFERROR(AVERAGE(C20:F20),"") -> 48.329563 | H20: =SQRT((C20-G20)^2) -> 12.046544
B21: Liquidity
B22: Current Ratio | C22: =C69/C73 -> 2.5068022 | D22: =D69/D73 -> 4.1712915 | E22: =E69/E73 -> 1.5424019 | F22: =F69/F73 -> 2.3331948 | G22: =IFERROR(AVERAGE(C22:F22),"") -> 2.6384226 | H22: =SQRT((C22-G22)^2) -> 0.1316204
B23: Quick Ratio | C23: =(C66+C67)/C73 -> 1.3916878 | D23: =(D66+D67)/D73 -> 1.625341 | E23: =(E66+E67)/E73 -> 0.37361423 | F23: =(F66+F67)/F73 -> 1.2082468 | G23: =IFERROR(AVERAGE(C23:F23),"") -> 1.1497225 | H23: =SQRT((C23-G23)^2) -> 0.24196539
B24: Activity | G24: =IFERROR(AVERAGE(C24:F24),"")
B25: Inventory Turnover | C25: =C56/C68 -> 2.8085498 | D25: =D56/D68 -> 3.1467247 | E25: =E56/E68 -> 2.922351 | F25: =F56/F68 -> 2.4710371 | G25: =IFERROR(AVERAGE(C25:F25),"") -> 2.8371656 | H25: =SQRT((C25-G25)^2) -> 0.028615887
B26: Acc. Receivable Turnover | C26: =C55/C67 -> 4.21875 | D26: =D55/D67 -> 6.0928093 | E26: =E55/E67 -> 15.940035 | F26: =F55/F67 -> 11.253534 | G26: =IFERROR(AVERAGE(C26:F26),"") -> 9.3762822 | H26: =SQRT((C26-G26)^2) -> 5.1575322
A27: Price/Sales | B27: Payables Turnover | C27: =C56/C72 -> 5.0537634 | D27: =D56/D72 -> 6.1582067 | E27: =E56/E72 -> 3.7907438 | F27: =F56/F72 -> 8.2996862 | G27: =IFERROR(AVERAGE(C27:F27),"") -> 5.8256 | H27: =SQRT((C27-G27)^2) -> 0.77183659
B28: Fixed Asset Turnover | C28: =C55/C70 -> 14.273128 | D28: =D55/D70 -> 15.565151 | E28: =E55/E70 -> 0.56109346 | F28: =F55/F70 -> 7.1043237 | G28: =IFERROR(AVERAGE(C28:F28),"") -> 9.3759239 | H28: =SQRT((C28-G28)^2) -> 4.8972038
B29: Total Asset Turnover | C29: =C55/C71 -> 0.33409442 | D29: =D55/D71 -> 0.92688048 | E29: =E55/E71 -> 0.28306851 | F29: =F55/F71 -> 0.70180251 | G29: =IFERROR(AVERAGE(C29:F29),"") -> 0.56146148 | H29: =SQRT((C29-G29)^2) -> 0.22736705
B30: Valuation | G30: =IFERROR(AVERAGE(C30:F30),"")
B31: Price/Earnings | C31: =C8/C62 -> 148.02177 | D31: =D8/D62 -> 8.0921447 | E31: =E8/E62 -> 46.153027 | F31: =F7/F62 -> 19.185091 | G31: =IFERROR(AVERAGE(C31:F31),"") -> 55.363007 | H31: =SQRT((C31-G31)^2) -> 92.658759
B32: Price/Sales | C32: =C8/C55 -> 5.5736591 | D32: =D8/D55 -> 3.9529599 | E32: =E8/E55 -> 1.4255794 | F32: =F7/F55 -> 3.8734389 | G32: =IFERROR(AVERAGE(C32:F32),"") -> 3.7064093 | H32: =SQRT((C32-G32)^2) -> 1.8672498
B33: Price/Book | C33: =C8/C75 -> 2.2616938 | D33: =D8/D75 -> 5.6033837 | E33: =E8/E75 -> 0.70300841 | F33: =F7/F75 -> 6.429108 | G33: =IFERROR(AVERAGE(C33:F33),"") -> 3.7492985 | H33: =SQRT((C33-G33)^2) -> 1.4876047
B34: EV/Sales | C34: =(C74+C8-C66)/C55 -> 5.4995409 | D34: =(D74+D8-D66)/D55 -> 4.0111983 | E34: =(E74+E8-E66)/E55 -> 2.2035354 | F34: =(F74+F7-F66)/F55 -> 4.0734389 | G34: =IFERROR(AVERAGE(C34:F34),"") -> 3.9469284 | H34: =SQRT((C34-G34)^2) -> 1.5526125
B35: EV/EBITDA | C35: =(C74+C8-C66)/C58 -> 32.43099 | D35: =(D74+D8-D66)/D58 -> 7.0873035 | E35: =(E74+E8-E66)/E58 -> 15.049537 | F35: =(F74+F7-F66)/F58 -> 15.20377 | G35: =IFERROR(AVERAGE(C35:F35),"") -> 17.4429 | H35: =SQRT((C35-G35)^2) -> 14.98809
B36: Stock Info | G36: =IFERROR(AVERAGE(C36:F36),"")
B37: Float | C37: =1.6/1.62 -> 0.98765432 | D37: =2.4/2.5 -> 0.96 | E37: =4.22/4.26 -> 0.99061033 | F37: =1.11/1.12 -> 0.99107143 | G37: =IFERROR(AVERAGE(C37:F37),"") -> 0.98233402 | H37: =SQRT((C37-G37)^2) -> 0.0053203014
B38: b (Yahoo) | C38: 1.63 | D38: 1.74 | E38: 1.01 | F38: 1.34 | G38: =IFERROR(AVERAGE(C38:F38),"") -> 1.43 | H38: =SQRT((C38-G38)^2) -> 0.2
B39: Dividend Yield (yahoo finance) | C39: =OP!M32 -> 0 | D39: 0.0002 | E39: 0.0211 | F39: 0.02 | G39: =IFERROR(AVERAGE(C39:F39),"") -> 0.010325 | H39: =SQRT((C39-G39)^2) -> 0.010325
B40: Stock Performance
B41: 1y | C41: =(C43-87.44)/87.44 -> -0.1055581 | D41: =(D43-272.26)/272.26 -> -0.64629398 | E41: =(E43-29.86)/29.86 -> -0.39283322 | F41: =(F43-113.92)/113.92 -> 0.094276685 | G41: =IFERROR(AVERAGE(C41:F41),"") -> -0.26260215 | H41: =SQRT((C41-G41)^2) -> 0.15704406
B42: 3y | C42: =(C43-85.21)/85.21 -> -0.082149982 | D42: =(D43-153.82)/153.82 -> -0.37394357 | E42: =(E43-58.76)/58.76 -> -0.69145677 | F42: =(F43-138.01)/138.01 -> -0.096732121 | G42: =IFERROR(AVERAGE(C42:F42),"") -> -0.31107061 | H42: =SQRT((C42-G42)^2) -> 0.22892063
B43: Current Price | C43: {=_FV(C6,"Price")} -> 78.21 | D43: {=_FV(D6,"Preço")} -> 96.3 | E43: {=_FV(E6,"Preço")} -> 18.13 | F43: {=_FV(F6,"Preço")} -> 124.66 | G43: =IFERROR(AVERAGE(C43:F43),"") -> 79.325 | H43: =SQRT((C43-G43)^2) -> 1.115
B44: Average Target Price | C44: 192.2 | D44: 1003.3 | E44: 44.5 | F44: 169.64 | G44: =IFERROR(AVERAGE(C44:F44),"") -> 352.41 | H44: =SQRT((C44-G44)^2) -> 160.21
B45: Upside/Downside | C45: =C44/C43-1 -> 1.4574863 | D45: =D44/D43-1 -> 9.4184839 | E45: =E44/E43-1 -> 1.4544953 | F45: =F44/F43-1 -> 0.36082143 | G45: =IFERROR(AVERAGE(C45:F45),"") -> 3.1728217 | H45: =SQRT((C45-G45)^2) -> 1.7153355
B46: Extra | G46: =IFERROR(AVERAGE(C46:F46),"")
B47: 3y Operating Cash Flow | C47: =(Inputs!B59-Inputs!E59)/Inputs!E59 -> 0.55648926 | D47: =(28090-5822)/5822 -> 3.8248025 | E47: =(11471-35384)/35384 -> -0.67581393 | F47: =(11299-5814)/5814 -> 0.94341245 | G47: =IFERROR(AVERAGE(C47:F47),"") -> 1.1622226 | H47: =SQRT((C47-G47)^2) -> 0.6057333
B48: R&D/Net Sales | C48: =C63/C9 -> 0.25890653 | D48: =D63/D9 -> 0.142 | E48: =E63/E9 -> 0.2958988 | F48: =F63/F9 -> 0.24617532 | G48: =IFERROR(AVERAGE(C48:F48),"") -> 0.23574516 | H48: =SQRT((C48-G48)^2) -> 0.023161365
A49: ROR | B49: RORC | C49: =C57/C64 -> 2.0899101 | D49: =D57/D64 -> 6.0380857 | E49: =E57/E64 -> 1.2386467 | F49: =F57/F64 -> 2.4348304 | G49: =IFERROR(AVERAGE(C49:F49),"") -> 2.9503682 | H49: =SQRT((C49-G49)^2) -> 0.86045813
B51: Financial Data | C51: =OP!E2 -> #VALUE! | D51: =D6 -> #VALUE! | E51: =E6 -> #VALUE! | F51: =F6 -> #VALUE!
B52: IS
B53: Net Sales (36m ago) | C53: ='Fin. Data'!E5 -> 9763 | D53: 16675 | E53: 77867 | F53: 23531
B54: Net Sales (12m ago) | C54: ='Fin. Data'!C5 -> 23601 | D54: 26974 | E54: 63054 | F54: 44200
B55: Net Sales (current) | C55: ='Fin. Data'!B5 -> 22680 | D55: 60922 | E55: 54228 | F55: 35820
B56: COGS | C56: ='Fin. Data'!B5-'Fin. Data'!B7 -> 12220 | D56: 16621 | E56: 32517 | F56: 15869
B57: Gross profit | C57: =C55-C56 -> 10460 | D57: =D55-D56 -> 44301 | E57: =E55-E56 -> 21711 | F57: =F55-F56 -> 19951
B58: EBITDA | C58: ='Fin. Data'!B19 -> 3846 | D58: =D59+1508 -> 34480 | E58: =7847+E59 -> 7940 | F58: =F59+1809 -> 9597
B59: Operating Income | C59: ='Fin. Data'!B11 -> 401 | D59: 32972 | E59: 93 | F59: 7788
B60: Net Financial Cost | C60: -106 | D60: -257 | E60: -878 | F60: -694
B61: Taxes | C61: ='Fin. Data'!B21 -> 346 | D61: 4058 | E61: 913 | F61: 104
B62: Net Income | C62: ='Fin. Data'!B23 -> 854 | D62: 29760 | E62: 1675 | F62: 7232
B63: R&D | C63: 5872 | D63: =D55*0.142 -> 8650.924 | E63: 16046 | F63: 8818
B64: 2022 R&D | C64: 5005 | D64: =D54*0.272 -> 7336.928 | E64: 17528 | F64: 8194
B65: BS
B66: Cash & Eq. | C66: ='Fin. Data'!B39 -> 3933 | D66: 7280 | E66: 7079 | F66: 8450
B67: Acc. Receivables | C67: ='Fin. Data'!B40 -> 5376 | D67: 9999 | E67: 3402 | F67: 3183
B68: Inventory | C68: ='Fin. Data'!B41 -> 4351 | D68: 5282 | E68: 11127 | F68: 6422
B69: Current Assets | C69: =Inputs!B27 -> 16768 | D69: 44345 | E69: 43269 | F69: 22464
B70: Fixed Assets | C70: ='Fin. Data'!B42 -> 1589 | D70: 3914 | E70: 96647 | F70: 5042
B71: Total Assets | C71: ='Fin. Data'!B44 -> 67885 | D71: 65728 | E71: 191572 | F71: 51040
B72: Acc. Payable | C72: =Inputs!B43 -> 2418 | D72: 2699 | E72: 8578 | F72: 1912
B73: Current Liabilities | C73: =Inputs!B42 -> 6689 | D73: 10631 | E73: 28053 | F73: 9628
B74: Total Debt | C74: ='Fin. Data'!B58 -> 2252 | D74: =1250+1119+8459 -> 10828 | E74: =46978+2288 -> 49266 | F74: =14484+914+216 -> 15614
B75: Total Equity | C75: ='Fin. Data'!B64 -> 55892 | D75: 42978 | E75: 109965 | F75: 21581
B79: AMD | D79: Nominal value | G79: YoY Growth
B80: Weight | C80: Category | D80: 2023 | E80: =D80-1 -> 2022 | F80: =E80-1 -> 2021 | G80: 2023 | H80: =G80-1 -> 2022
B81: 0.29 | C81: Data Center | D81: 6496 | E81: 6043 | F81: 3694 | G81: =(D81-E81)/E81 -> 0.074962767 | H81: =(E81-F81)/F81 -> 0.63589605
B82: 0.21 | C82: Client | D82: 4651 | E82: 6201 | F82: 6887 | G82: =(D82-E82)/E82 -> -0.24995968 | H82: =(E82-F82)/F82 -> -0.099607957
B83: 0.27 | C83: Gaming | D83: 6212 | E83: 6805 | F83: 5607 | G83: =(D83-E83)/E83 -> -0.087141807 | H83: =(E83-F83)/F83 -> 0.21366149
B84: 0.23 | C84: Embedded | D84: 5321 | E84: 4552 | F84: 246 | G84: =(D84-E84)/E84 -> 0.16893673 | H84: =(E84-F84)/F84 -> 17.504065
B85: =SUM(B81:B84) -> 1 | C85: TOTAL | D85: =SUM(D81:D84) -> 22680 | E85: =SUM(E81:E84) -> 23601 | F85: =SUM(F81:F84) -> 16434 | G85: =(D85-E85)/E85 -> -0.03902377 | H85: =(E85-F85)/F85 -> 0.43610807
B88: Nvidia | D88: Nominal value | G88: YoY Growth
B89: Weight | C89: Category | D89: 2023 | E89: =D89-1 -> 2022 | F89: =E89-1 -> 2021 | G89: 2023 | H89: =G89-1 -> 2022
B90: =D90/$D$95 -> 0.78009586 | C90: Data center | D90: 47525 | E90: 15005 | F90: 10613 | G90: =(D90-E90)/E90 -> 2.1672776 | H90: =(E90-F90)/F90 -> 0.41383209
B91: =D91/$D$95 -> 0.17148157 | C91: Gaming | D91: 10447 | E91: 9067 | F91: 12462 | G91: =(D91-E91)/E91 -> 0.15220029 | H91: =(E91-F91)/F91 -> -0.27242818
B92: =D92/$D$95 -> 0.025491612 | C92: Professional visualization | D92: 1553 | E92: 1544 | F92: 2111 | G92: =(D92-E92)/E92 -> 0.0058290155 | H92: =(E92-F92)/F92 -> -0.26859308
B93: =D93/$D$95 -> 0.017908145 | C93: Automotive | D93: 1091 | E93: 903 | F93: 566 | G93: =(D93-E93)/E93 -> 0.20819491 | H93: =(E93-F93)/F93 -> 0.59540636
B94: =D94/$D$95 -> 0.0050228161 | C94: OEM and other | D94: 306 | E94: 455 | F94: 1162 | G94: =(D94-E94)/E94 -> -0.32747253 | H94: =(E94-F94)/F94 -> -0.60843373
B95: =D95/$D$95 -> 1 | C95: TOTAL | D95: =SUM(D90:D94) -> 60922 | E95: =SUM(E90:E94) -> 26974 | F95: =SUM(F90:F94) -> 26914 | G95: =(D95-E95)/E95 -> 1.2585453 | H95: =(E95-F95)/F95 -> 0.002229323
B98: Intel | D98: Nominal value | G98: YoY Growth
B99: Weight | C99: Category | D99: 2023 | E99: =D99-1 -> 2022 | F99: =E99-1 -> 2021 | G99: 2023 | H99: =G99-1 -> 2022
B100: =D100/$D$106 -> 0.53953677 | C100: Client computing | D100: 29258 | E100: 31773 | F100: 41081 | G100: =(D100-E100)/E100 -> -0.079155258 | H100: =(E100-F100)/F100 -> -0.22657676
B101: =D101/$D$106 -> 0.28621745 | C101: Data center and AI | D101: 15521 | E101: 19445 | F101: 22774 | G101: =(D101-E101)/E101 -> -0.20179995 | H101: =(E101-F101)/F101 -> -0.14617546
B102: =D102/$D$106 -> 0.10647636 | C102: Network and edge | D102: 5774 | E102: 8409 | F102: 7665 | G102: =(D102-E102)/E102 -> -0.31335474 | H102: =(E102-F102)/F102 -> 0.097064579
B103: =D103/$D$106 -> 0.038338128 | C103: Mobileye | D103: 2079 | E103: 1869 | F103: 1386 | G103: =(D103-E103)/E103 -> 0.11235955 | H103: =(E103-F103)/F103 -> 0.34848485
B104: =D104/$D$106 -> 0.017555506 | C104: Intel foundry services | D104: 952 | E104: 469 | F104: 347 | G104: =(D104-E104)/E104 -> 1.0298507 | H104: =(E104-F104)/F104 -> 0.35158501
B105: =D105/$D$106 -> 0.011875784 | C105: All other | D105: 644 | E105: 1089 | F105: 5771 | G105: =(D105-E105)/E105 -> -0.40863177 | H105: =(E105-F105)/F105 -> -0.81129787
B106: =D106/$D$106 -> 1 | C106: TOTAL | D106: =SUM(D100:D105) -> 54228 | E106: =SUM(E100:E105) -> 63054 | F106: =SUM(F100:F105) -> 79024 | G106: =(D106-E106)/E106 -> -0.13997526 | H106: =(E106-F106)/F106 -> -0.2020905
B110: Qualcomm | D110: Nominal value | G110: YoY Growth
B111: Weight | C111: Category | D111: 2023 | E111: =D111-1 -> 2022 | F111: =E111-1 -> 2021 | G111: 2023 | H111: =G111-1 -> 2022
B112: =D112/$D$116 -> 0.84818537 | C112: QCT | D112: 30382 | E112: 37677 | F112: 27019 | G112: =(D112-E112)/E112 -> -0.19361945 | H112: =(E112-F112)/F112 -> 0.39446316
...

Sheet SARD
F1: Variables | K1: Rankings | P1: Difference | U1: Results | Y1: Additional Information | AD1: =B3 -> 0 | AE1: Selected Peers | AJ1: Price Multiples (TTM) | AM1: Enterprise Value Multiples (TTM)
B2: Ticker | C2: Company Name | D2: TRBC Industry | E2: Country | F2: ROE | G2: DEBT/EBIT | H2: Market Cap | I2: EPS Growth (2019-2023) (Refinitiv Smart Estimate) | J2: EBIT Margin | K2: ROE | L2: DEBT/EBIT | M2: Market Cap | N2: EPS Growth | O2: EBIT Margin | P2: ROE | Q2: DEBT/EBIT | R2: Market Cap | S2: EPS Growth | T2: EBIT Margin | U2: SARD Result | V2: SARD Peers | W2: SARD Peers adjusted Rank | Y2: Suitability | Z2: Relevant Information Missing | AA2: Author's Override | AB2: Observations | AE2: SARD Peers adjusted Rank | AF2: SARD Result | AG2: Ticker | AH2: Company Name | AI2: Country | AJ2: P / E | AK2: P / B | AL2: Price / Sales | AM2: EV / Sales | AN2: EV / EBITDA
A3: Benchmark | K3: =IFERROR(_xlfn.RANK.EQ(F3,F$3:F$61),"N/A") -> N/A | L3: =IFERROR(_xlfn.RANK.EQ(G3,G$3:G$61),"N/A") -> N/A | M3: =IFERROR(_xlfn.RANK.EQ(H3,H$3:H$61),"N/A") -> N/A | N3: =IFERROR(_xlfn.RANK.EQ(I3,I$3:I$61),"N/A") -> N/A | O3: =IFERROR(_xlfn.RANK.EQ(J3,J$3:J$61),"N/A") -> N/A | P3: - | Q3: - | R3: - | S3: - | T3: - | U3: - | V3: - | W3: - | Y3: =IF(OR(Z3="Y",AA3="Y"),"Not suitable","") -> Not suitable | Z3: =IF(N3="N/A","Y","") -> Y | AE3: {=_xlfn._xlws.SORT(_xlfn._xlws.FILTER(SARD!W3:W61,SARD!W3:W61<=SMALL(W3:W61,6)),,1)} -> #NUM! | AF3: =_xlfn.XLOOKUP($AE3,$W:$W,U:U,,0) -> #NUM! | AG3: =_xlfn.XLOOKUP($AE3,$W:$W,B:B,,0) -> #NUM! | AH3: =_xlfn.XLOOKUP($AE3,$W:$W,C:C,,0) -> #NUM! | AI3: =_xlfn.XLOOKUP($AE3,$W:$W,E:E,,0) -> #NUM!
A4: Comparison | K4: =IFERROR(_xlfn.RANK.EQ(F4,F$3:F$61),"N/A") -> N/A | L4: =IFERROR(_xlfn.RANK.EQ(G4,G$3:G$61),"N/A") -> N/A | M4: =IFERROR(_xlfn.RANK.EQ(H4,H$3:H$61),"N/A") -> N/A | N4: =IFERROR(_xlfn.RANK.EQ(I4,I$3:I$61),"N/A") -> N/A | O4: =IFERROR(_xlfn.RANK.EQ(J4,J$3:J$61),"N/A") -> N/A | P4: =IFERROR(ABS(K$3-K4),"N/A") -> N/A | Q4: =IFERROR(ABS(L$3-L4),"N/A") -> N/A | R4: =IFERROR(ABS(M$3-M4),"N/A") -> N/A | S4: =IFERROR(ABS(N$3-N4),"N/A") -> N/A | T4: =IFERROR(ABS(O$3-O4),"N/A") -> N/A | U4: =SUM(P4:T4) -> 0 | V4: =_xlfn.RANK.EQ(U4,$U$4:$U$61,1) -> 1 | W4: =IF(Y4="Not suitable","-",V4) -> - | Y4: =IF(OR(Z4="Y",AA4="Y"),"Not suitable","") -> Not suitable | Z4: =IF(N4="N/A","Y","") -> Y | AF4: =_xlfn.XLOOKUP($AE4,$W:$W,U:U,,0) -> Results | AG4: =_xlfn.XLOOKUP($AE4,$W:$W,B:B,,0) -> 0 | AH4: =_xlfn.XLOOKUP($AE4,$W:$W,C:C,,0) -> 0 | AI4: =_xlfn.XLOOKUP($AE4,$W:$W,E:E,,0) -> 0
K5: =IFERROR(_xlfn.RANK.EQ(F5,F$3:F$61),"N/A") -> N/A | L5: =IFERROR(_xlfn.RANK.EQ(G5,G$3:G$61),"N/A") -> N/A | M5: =IFERROR(_xlfn.RANK.EQ(H5,H$3:H$61),"N/A") -> N/A | N5: =IFERROR(_xlfn.RANK.EQ(I5,I$3:I$61),"N/A") -> N/A | O5: =IFERROR(_xlfn.RANK.EQ(J5,J$3:J$61),"N/A") -> N/A | P5: =IFERROR(ABS(K$3-K5),"N/A") -> N/A | Q5: =IFERROR(ABS(L$3-L5),"N/A") -> N/A | R5: =IFERROR(ABS(M$3-M5),"N/A") -> N/A | S5: =IFERROR(ABS(N$3-N5),"N/A") -> N/A | T5: =IFERROR(ABS(O$3-O5),"N/A") -> N/A | U5: =SUM(P5:T5) -> 0 | V5: =_xlfn.RANK.EQ(U5,$U$4:$U$61,1) -> 1 | W5: =IF(Y5="Not suitable","-",V5) -> - | Y5: =IF(OR(Z5="Y",AA5="Y"),"Not suitable","") -> Not suitable | Z5: =IF(N5="N/A","Y","") -> Y | AF5: =_xlfn.XLOOKUP($AE5,$W:$W,U:U,,0) -> Results | AG5: =_xlfn.XLOOKUP($AE5,$W:$W,B:B,,0) -> 0 | AH5: =_xlfn.XLOOKUP($AE5,$W:$W,C:C,,0) -> 0 | AI5: =_xlfn.XLOOKUP($AE5,$W:$W,E:E,,0) -> 0
K6: =IFERROR(_xlfn.RANK.EQ(F6,F$3:F$61),"N/A") -> N/A | L6: =IFERROR(_xlfn.RANK.EQ(G6,G$3:G$61),"N/A") -> N/A | M6: =IFERROR(_xlfn.RANK.EQ(H6,H$3:H$61),"N/A") -> N/A | N6: =IFERROR(_xlfn.RANK.EQ(I6,I$3:I$61),"N/A") -> N/A | O6: =IFERROR(_xlfn.RANK.EQ(J6,J$3:J$61),"N/A") -> N/A | P6: =IFERROR(ABS(K$3-K6),"N/A") -> N/A | Q6: =IFERROR(ABS(L$3-L6),"N/A") -> N/A | R6: =IFERROR(ABS(M$3-M6),"N/A") -> N/A | S6: =IFERROR(ABS(N$3-N6),"N/A") -> N/A | T6: =IFERROR(ABS(O$3-O6),"N/A") -> N/A | U6: =SUM(P6:T6) -> 0 | V6: =_xlfn.RANK.EQ(U6,$U$4:$U$61,1) -> 1 | W6: =IF(Y6="Not suitable","-",V6) -> - | Y6: =IF(OR(Z6="Y",AA6="Y"),"Not suitable","") -> Not suitable | Z6: =IF(N6="N/A","Y","") -> Y | AF6: =_xlfn.XLOOKUP($AE6,$W:$W,U:U,,0) -> Results | AG6: =_xlfn.XLOOKUP($AE6,$W:$W,B:B,,0) -> 0 | AH6: =_xlfn.XLOOKUP($AE6,$W:$W,C:C,,0) -> 0 | AI6: =_xlfn.XLOOKUP($AE6,$W:$W,E:E,,0) -> 0
K7: =IFERROR(_xlfn.RANK.EQ(F7,F$3:F$61),"N/A") -> N/A | L7: =IFERROR(_xlfn.RANK.EQ(G7,G$3:G$61),"N/A") -> N/A | M7: =IFERROR(_xlfn.RANK.EQ(H7,H$3:H$61),"N/A") -> N/A | N7: =IFERROR(_xlfn.RANK.EQ(I7,I$3:I$61),"N/A") -> N/A | O7: =IFERROR(_xlfn.RANK.EQ(J7,J$3:J$61),"N/A") -> N/A | P7: =IFERROR(ABS(K$3-K7),"N/A") -> N/A | Q7: =IFERROR(ABS(L$3-L7),"N/A") -> N/A | R7: =IFERROR(ABS(M$3-M7),"N/A") -> N/A | S7: =IFERROR(ABS(N$3-N7),"N/A") -> N/A | T7: =IFERROR(ABS(O$3-O7),"N/A") -> N/A | U7: =SUM(P7:T7) -> 0 | V7: =_xlfn.RANK.EQ(U7,$U$4:$U$61,1) -> 1 | W7: =IF(Y7="Not suitable","-",V7) -> - | Y7: =IF(OR(Z7="Y",AA7="Y"),"Not suitable","") -> Not suitable | Z7: =IF(N7="N/A","Y","") -> Y | AF7: =_xlfn.XLOOKUP($AE7,$W:$W,U:U,,0) -> Results | AG7: =_xlfn.XLOOKUP($AE7,$W:$W,B:B,,0) -> 0 | AH7: =_xlfn.XLOOKUP($AE7,$W:$W,C:C,,0) -> 0 | AI7: =_xlfn.XLOOKUP($AE7,$W:$W,E:E,,0) -> 0
K8: =IFERROR(_xlfn.RANK.EQ(F8,F$3:F$61),"N/A") -> N/A | L8: =IFERROR(_xlfn.RANK.EQ(G8,G$3:G$61),"N/A") -> N/A | M8: =IFERROR(_xlfn.RANK.EQ(H8,H$3:H$61),"N/A") -> N/A | N8: =IFERROR(_xlfn.RANK.EQ(I8,I$3:I$61),"N/A") -> N/A | O8: =IFERROR(_xlfn.RANK.EQ(J8,J$3:J$61),"N/A") -> N/A | P8: =IFERROR(ABS(K$3-K8),"N/A") -> N/A | Q8: =IFERROR(ABS(L$3-L8),"N/A") -> N/A | R8: =IFERROR(ABS(M$3-M8),"N/A") -> N/A | S8: =IFERROR(ABS(N$3-N8),"N/A") -> N/A | T8: =IFERROR(ABS(O$3-O8),"N/A") -> N/A | U8: =SUM(P8:T8) -> 0 | V8: =_xlfn.RANK.EQ(U8,$U$4:$U$61,1) -> 1 | W8: =IF(Y8="Not suitable","-",V8) -> - | Y8: =IF(OR(Z8="Y",AA8="Y"),"Not suitable","") -> Not suitable | Z8: =IF(N8="N/A","Y","") -> Y | AF8: =_xlfn.XLOOKUP($AE8,$W:$W,U:U,,0) -> Results | AG8: =_xlfn.XLOOKUP($AE8,$W:$W,B:B,,0) -> 0 | AH8: =_xlfn.XLOOKUP($AE8,$W:$W,C:C,,0) -> 0 | AI8: =_xlfn.XLOOKUP($AE8,$W:$W,E:E,,0) -> 0
K9: =IFERROR(_xlfn.RANK.EQ(F9,F$3:F$61),"N/A") -> N/A | L9: =IFERROR(_xlfn.RANK.EQ(G9,G$3:G$61),"N/A") -> N/A | M9: =IFERROR(_xlfn.RANK.EQ(H9,H$3:H$61),"N/A") -> N/A | N9: =IFERROR(_xlfn.RANK.EQ(I9,I$3:I$61),"N/A") -> N/A | O9: =IFERROR(_xlfn.RANK.EQ(J9,J$3:J$61),"N/A") -> N/A | P9: =IFERROR(ABS(K$3-K9),"N/A") -> N/A | Q9: =IFERROR(ABS(L$3-L9),"N/A") -> N/A | R9: =IFERROR(ABS(M$3-M9),"N/A") -> N/A | S9: =IFERROR(ABS(N$3-N9),"N/A") -> N/A | T9: =IFERROR(ABS(O$3-O9),"N/A") -> N/A | U9: =SUM(P9:T9) -> 0 | V9: =_xlfn.RANK.EQ(U9,$U$4:$U$61,1) -> 1 | W9: =IF(Y9="Not suitable","-",V9) -> - | Y9: =IF(OR(Z9="Y",AA9="Y"),"Not suitable","") -> Not suitable | Z9: =IF(N9="N/A","Y","") -> Y | AE9: Median | AJ9: =MEDIAN(AJ3:AJ8) -> #NUM! | AK9: =MEDIAN(AK3:AK8) -> #NUM! | AL9: =MEDIAN(AL3:AL8) -> #NUM! | AM9: =MEDIAN(AM3:AM8) -> #NUM! | AN9: =MEDIAN(AN3:AN8) -> #NUM!
K10: =IFERROR(_xlfn.RANK.EQ(F10,F$3:F$61),"N/A") -> N/A | L10: =IFERROR(_xlfn.RANK.EQ(G10,G$3:G$61),"N/A") -> N/A | M10: =IFERROR(_xlfn.RANK.EQ(H10,H$3:H$61),"N/A") -> N/A | N10: =IFERROR(_xlfn.RANK.EQ(I10,I$3:I$61),"N/A") -> N/A | O10: =IFERROR(_xlfn.RANK.EQ(J10,J$3:J$61),"N/A") -> N/A | P10: =IFERROR(ABS(K$3-K10),"N/A") -> N/A | Q10: =IFERROR(ABS(L$3-L10),"N/A") -> N/A | R10: =IFERROR(ABS(M$3-M10),"N/A") -> N/A | S10: =IFERROR(ABS(N$3-N10),"N/A") -> N/A | T10: =IFERROR(ABS(O$3-O10),"N/A") -> N/A | U10: =SUM(P10:T10) -> 0 | V10: =_xlfn.RANK.EQ(U10,$U$4:$U$61,1) -> 1 | W10: =IF(Y10="Not suitable","-",V10) -> - | Y10: =IF(OR(Z10="Y",AA10="Y"),"Not suitable","") -> Not suitable | Z10: =IF(N10="N/A","Y","") -> Y | AE10: Benchmark Data | AJ10: Price / Share
K11: =IFERROR(_xlfn.RANK.EQ(F11,F$3:F$61),"N/A") -> N/A | L11: =IFERROR(_xlfn.RANK.EQ(G11,G$3:G$61),"N/A") -> N/A | M11: =IFERROR(_xlfn.RANK.EQ(H11,H$3:H$61),"N/A") -> N/A | N11: =IFERROR(_xlfn.RANK.EQ(I11,I$3:I$61),"N/A") -> N/A | O11: =IFERROR(_xlfn.RANK.EQ(J11,J$3:J$61),"N/A") -> N/A | P11: =IFERROR(ABS(K$3-K11),"N/A") -> N/A | Q11: =IFERROR(ABS(L$3-L11),"N/A") -> N/A | R11: =IFERROR(ABS(M$3-M11),"N/A") -> N/A | S11: =IFERROR(ABS(N$3-N11),"N/A") -> N/A | T11: =IFERROR(ABS(O$3-O11),"N/A") -> N/A | U11: =SUM(P11:T11) -> 0 | V11: =_xlfn.RANK.EQ(U11,$U$4:$U$61,1) -> 1 | W11: =IF(Y11="Not suitable","-",V11) -> - | Y11: =IF(OR(Z11="Y",AA11="Y"),"Not suitable","") -> Not suitable | Z11: =IF(N11="N/A","Y","") -> Y | AE11: Benchmark | AF11: Multiplier | AG11: # Shares | AH11: -Debt + Cash | AJ11: P / E | AK11: P / B | AL11: Price / Sales | AM11: EV / Sales | AN11: EV / EBITDA
K12: =IFERROR(_xlfn.RANK.EQ(F12,F$3:F$61),"N/A") -> N/A | L12: =IFERROR(_xlfn.RANK.EQ(G12,G$3:G$61),"N/A") -> N/A | M12: =IFERROR(_xlfn.RANK.EQ(H12,H$3:H$61),"N/A") -> N/A | N12: =IFERROR(_xlfn.RANK.EQ(I12,I$3:I$61),"N/A") -> N/A | O12: =IFERROR(_xlfn.RANK.EQ(J12,J$3:J$61),"N/A") -> N/A | P12: =IFERROR(ABS(K$3-K12),"N/A") -> N/A | Q12: =IFERROR(ABS(L$3-L12),"N/A") -> N/A | R12: =IFERROR(ABS(M$3-M12),"N/A") -> N/A | S12: =IFERROR(ABS(N$3-N12),"N/A") -> N/A | T12: =IFERROR(ABS(O$3-O12),"N/A") -> N/A | U12: =SUM(P12:T12) -> 0 | V12: =_xlfn.RANK.EQ(U12,$U$4:$U$61,1) -> 1 | W12: =IF(Y12="Not suitable","-",V12) -> - | Y12: =IF(OR(Z12="Y",AA12="Y"),"Not suitable","") -> Not suitable | Z12: =IF(N12="N/A","Y","") -> Y | AE12: =C3 -> 0 | AF12: 1000000 | AG12: =OP!C21 -> 1616297000 | AH12: =-'Fin. Data'!B58*SARD!AF12+'Fin. Data'!B39*SARD!AF12 -> 1681000000 | AJ12: =AJ9*'Fin. Data'!B23*AF$12/AG$12 -> #NUM! | AK12: =AK9*'Fin. Data'!B64*AF$12/AG$12 -> #NUM! | AL12: =AL9*'Fin. Data'!B5*AF$12/AG$12 -> #NUM! | AM12: =(AM9*'Fin. Data'!B5*$AF12+$AH12)/$AG12 -> #NUM! | AN12: =(AN9*'Fin. Data'!B19*$AF12+$AH12)/$AG12 -> #NUM!
K13: =IFERROR(_xlfn.RANK.EQ(F13,F$3:F$61),"N/A") -> N/A | L13: =IFERROR(_xlfn.RANK.EQ(G13,G$3:G$61),"N/A") -> N/A | M13: =IFERROR(_xlfn.RANK.EQ(H13,H$3:H$61),"N/A") -> N/A | N13: =IFERROR(_xlfn.RANK.EQ(I13,I$3:I$61),"N/A") -> N/A | O13: =IFERROR(_xlfn.RANK.EQ(J13,J$3:J$61),"N/A") -> N/A | P13: =IFERROR(ABS(K$3-K13),"N/A") -> N/A | Q13: =IFERROR(ABS(L$3-L13),"N/A") -> N/A | R13: =IFERROR(ABS(M$3-M13),"N/A") -> N/A | S13: =IFERROR(ABS(N$3-N13),"N/A") -> N/A | T13: =IFERROR(ABS(O$3-O13),"N/A") -> N/A | U13: =SUM(P13:T13) -> 0 | V13: =_xlfn.RANK.EQ(U13,$U$4:$U$61,1) -> 1 | W13: =IF(Y13="Not suitable","-",V13) -> - | Y13: =IF(OR(Z13="Y",AA13="Y"),"Not suitable","") -> Not suitable | Z13: =IF(N13="N/A","Y","") -> Y | AE13: By Consolidated Average | AJ13: =AVERAGE(AJ12:AL12) -> #NUM! | AM13: =AVERAGE(AM12:AN12) -> #NUM!
K14: =IFERROR(_xlfn.RANK.EQ(F14,F$3:F$61),"N/A") -> N/A | L14: =IFERROR(_xlfn.RANK.EQ(G14,G$3:G$61),"N/A") -> N/A | M14: =IFERROR(_xlfn.RANK.EQ(H14,H$3:H$61),"N/A") -> N/A | N14: =IFERROR(_xlfn.RANK.EQ(I14,I$3:I$61),"N/A") -> N/A | O14: =IFERROR(_xlfn.RANK.EQ(J14,J$3:J$61),"N/A") -> N/A | P14: =IFERROR(ABS(K$3-K14),"N/A") -> N/A | Q14: =IFERROR(ABS(L$3-L14),"N/A") -> N/A | R14: =IFERROR(ABS(M$3-M14),"N/A") -> N/A | S14: =IFERROR(ABS(N$3-N14),"N/A") -> N/A | T14: =IFERROR(ABS(O$3-O14),"N/A") -> N/A | U14: =SUM(P14:T14) -> 0 | V14: =_xlfn.RANK.EQ(U14,$U$4:$U$61,1) -> 1 | W14: =IF(Y14="Not suitable","-",V14) -> - | Y14: =IF(OR(Z14="Y",AA14="Y"),"Not suitable","") -> Not suitable | Z14: =IF(N14="N/A","Y","") -> Y | AE14: Upside | AJ14: =AJ13/OP!C20-1 -> #NUM! | AM14: =AM13/OP!C20-1 -> #NUM!
K15: =IFERROR(_xlfn.RANK.EQ(F15,F$3:F$61),"N/A") -> N/A | L15: =IFERROR(_xlfn.RANK.EQ(G15,G$3:G$61),"N/A") -> N/A | M15: =IFERROR(_xlfn.RANK.EQ(H15,H$3:H$61),"N/A") -> N/A | N15: =IFERROR(_xlfn.RANK.EQ(I15,I$3:I$61),"N/A") -> N/A | O15: =IFERROR(_xlfn.RANK.EQ(J15,J$3:J$61),"N/A") -> N/A | P15: =IFERROR(ABS(K$3-K15),"N/A") -> N/A | Q15: =IFERROR(ABS(L$3-L15),"N/A") -> N/A | R15: =IFERROR(ABS(M$3-M15),"N/A") -> N/A | S15: =IFERROR(ABS(N$3-N15),"N/A") -> N/A | T15: =IFERROR(ABS(O$3-O15),"N/A") -> N/A | U15: =SUM(P15:T15) -> 0 | V15: =_xlfn.RANK.EQ(U15,$U$4:$U$61,1) -> 1 | W15: =IF(Y15="Not suitable","-",V15) -> - | Y15: =IF(OR(Z15="Y",AA15="Y"),"Not suitable","") -> Not suitable | Z15: =IF(N15="N/A","Y","") -> Y
K16: =IFERROR(_xlfn.RANK.EQ(F16,F$3:F$61),"N/A") -> N/A | L16: =IFERROR(_xlfn.RANK.EQ(G16,G$3:G$61),"N/A") -> N/A | M16: =IFERROR(_xlfn.RANK.EQ(H16,H$3:H$61),"N/A") -> N/A | N16: =IFERROR(_xlfn.RANK.EQ(I16,I$3:I$61),"N/A") -> N/A | O16: =IFERROR(_xlfn.RANK.EQ(J16,J$3:J$61),"N/A") -> N/A | P16: =IFERROR(ABS(K$3-K16),"N/A") -> N/A | Q16: =IFERROR(ABS(L$3-L16),"N/A") -> N/A | R16: =IFERROR(ABS(M$3-M16),"N/A") -> N/A | S16: =IFERROR(ABS(N$3-N16),"N/A") -> N/A | T16: =IFERROR(ABS(O$3-O16),"N/A") -> N/A | U16: =SUM(P16:T16) -> 0 | V16: =_xlfn.RANK.EQ(U16,$U$4:$U$61,1) -> 1 | W16: =IF(Y16="Not suitable","-",V16) -> - | Y16: =IF(OR(Z16="Y",AA16="Y"),"Not suitable","") -> Not suitable | Z16: =IF(N16="N/A","Y","") -> Y
K17: =IFERROR(_xlfn.RANK.EQ(F17,F$3:F$61),"N/A") -> N/A | L17: =IFERROR(_xlfn.RANK.EQ(G17,G$3:G$61),"N/A") -> N/A | M17: =IFERROR(_xlfn.RANK.EQ(H17,H$3:H$61),"N/A") -> N/A | N17: =IFERROR(_xlfn.RANK.EQ(I17,I$3:I$61),"N/A") -> N/A | O17: =IFERROR(_xlfn.RANK.EQ(J17,J$3:J$61),"N/A") -> N/A | P17: =IFERROR(ABS(K$3-K17),"N/A") -> N/A | Q17: =IFERROR(ABS(L$3-L17),"N/A") -> N/A | R17: =IFERROR(ABS(M$3-M17),"N/A") -> N/A | S17: =IFERROR(ABS(N$3-N17),"N/A") -> N/A | T17: =IFERROR(ABS(O$3-O17),"N/A") -> N/A | U17: =SUM(P17:T17) -> 0 | V17: =_xlfn.RANK.EQ(U17,$U$4:$U$61,1) -> 1 | W17: =IF(Y17="Not suitable","-",V17) -> - | Y17: =IF(OR(Z17="Y",AA17="Y"),"Not suitable","") -> Not suitable | Z17: =IF(N17="N/A","Y","") -> Y
K18: =IFERROR(_xlfn.RANK.EQ(F18,F$3:F$61),"N/A") -> N/A | L18: =IFERROR(_xlfn.RANK.EQ(G18,G$3:G$61),"N/A") -> N/A | M18: =IFERROR(_xlfn.RANK.EQ(H18,H$3:H$61),"N/A") -> N/A | N18: =IFERROR(_xlfn.RANK.EQ(I18,I$3:I$61),"N/A") -> N/A | O18: =IFERROR(_xlfn.RANK.EQ(J18,J$3:J$61),"N/A") -> N/A | P18: =IFERROR(ABS(K$3-K18),"N/A") -> N/A | Q18: =IFERROR(ABS(L$3-L18),"N/A") -> N/A | R18: =IFERROR(ABS(M$3-M18),"N/A") -> N/A | S18: =IFERROR(ABS(N$3-N18),"N/A") -> N/A | T18: =IFERROR(ABS(O$3-O18),"N/A") -> N/A | U18: =SUM(P18:T18) -> 0 | V18: =_xlfn.RANK.EQ(U18,$U$4:$U$61,1) -> 1 | W18: =IF(Y18="Not suitable","-",V18) -> - | Y18: =IF(OR(Z18="Y",AA18="Y"),"Not suitable","") -> Not suitable | Z18: =IF(N18="N/A","Y","") -> Y
K19: =IFERROR(_xlfn.RANK.EQ(F19,F$3:F$61),"N/A") -> N/A | L19: =IFERROR(_xlfn.RANK.EQ(G19,G$3:G$61),"N/A") -> N/A | M19: =IFERROR(_xlfn.RANK.EQ(H19,H$3:H$61),"N/A") -> N/A | N19: =IFERROR(_xlfn.RANK.EQ(I19,I$3:I$61),"N/A") -> N/A | O19: =IFERROR(_xlfn.RANK.EQ(J19,J$3:J$61),"N/A") -> N/A | P19: =IFERROR(ABS(K$3-K19),"N/A") -> N/A | Q19: =IFERROR(ABS(L$3-L19),"N/A") -> N/A | R19: =IFERROR(ABS(M$3-M19),"N/A") -> N/A | S19: =IFERROR(ABS(N$3-N19),"N/A") -> N/A | T19: =IFERROR(ABS(O$3-O19),"N/A") -> N/A | U19: =SUM(P19:T19) -> 0 | V19: =_xlfn.RANK.EQ(U19,$U$4:$U$61,1) -> 1 | W19: =IF(Y19="Not suitable","-",V19) -> - | Y19: =IF(OR(Z19="Y",AA19="Y"),"Not suitable","") -> Not suitable | Z19: =IF(N19="N/A","Y","") -> Y
K20: =IFERROR(_xlfn.RANK.EQ(F20,F$3:F$61),"N/A") -> N/A | L20: =IFERROR(_xlfn.RANK.EQ(G20,G$3:G$61),"N/A") -> N/A | M20: =IFERROR(_xlfn.RANK.EQ(H20,H$3:H$61),"N/A") -> N/A | N20: =IFERROR(_xlfn.RANK.EQ(I20,I$3:I$61),"N/A") -> N/A | O20: =IFERROR(_xlfn.RANK.EQ(J20,J$3:J$61),"N/A") -> N/A | P20: =IFERROR(ABS(K$3-K20),"N/A") -> N/A | Q20: =IFERROR(ABS(L$3-L20),"N/A") -> N/A | R20: =IFERROR(ABS(M$3-M20),"N/A") -> N/A | S20: =IFERROR(ABS(N$3-N20),"N/A") -> N/A | T20: =IFERROR(ABS(O$3-O20),"N/A") -> N/A | U20: =SUM(P20:T20) -> 0 | V20: =_xlfn.RANK.EQ(U20,$U$4:$U$61,1) -> 1 | W20: =IF(Y20="Not suitable","-",V20) -> - | Y20: =IF(OR(Z20="Y",AA20="Y"),"Not suitable","") -> Not suitable | Z20: =IF(N20="N/A","Y","") -> Y
K21: =IFERROR(_xlfn.RANK.EQ(F21,F$3:F$61),"N/A") -> N/A | L21: =IFERROR(_xlfn.RANK.EQ(G21,G$3:G$61),"N/A") -> N/A | M21: =IFERROR(_xlfn.RANK.EQ(H21,H$3:H$61),"N/A") -> N/A | N21: =IFERROR(_xlfn.RANK.EQ(I21,I$3:I$61),"N/A") -> N/A | O21: =IFERROR(_xlfn.RANK.EQ(J21,J$3:J$61),"N/A") -> N/A | P21: =IFERROR(ABS(K$3-K21),"N/A") -> N/A | Q21: =IFERROR(ABS(L$3-L21),"N/A") -> N/A | R21: =IFERROR(ABS(M$3-M21),"N/A") -> N/A | S21: =IFERROR(ABS(N$3-N21),"N/A") -> N/A | T21: =IFERROR(ABS(O$3-O21),"N/A") -> N/A | U21: =SUM(P21:T21) -> 0 | V21: =_xlfn.RANK.EQ(U21,$U$4:$U$61,1) -> 1 | W21: =IF(Y21="Not suitable","-",V21) -> - | Y21: =IF(OR(Z21="Y",AA21="Y"),"Not suitable","") -> Not suitable | Z21: =IF(N21="N/A","Y","") -> Y
K22: =IFERROR(_xlfn.RANK.EQ(F22,F$3:F$61),"N/A") -> N/A | L22: =IFERROR(_xlfn.RANK.EQ(G22,G$3:G$61),"N/A") -> N/A | M22: =IFERROR(_xlfn.RANK.EQ(H22,H$3:H$61),"N/A") -> N/A | N22: =IFERROR(_xlfn.RANK.EQ(I22,I$3:I$61),"N/A") -> N/A | O22: =IFERROR(_xlfn.RANK.EQ(J22,J$3:J$61),"N/A") -> N/A | P22: =IFERROR(ABS(K$3-K22),"N/A") -> N/A | Q22: =IFERROR(ABS(L$3-L22),"N/A") -> N/A | R22: =IFERROR(ABS(M$3-M22),"N/A") -> N/A | S22: =IFERROR(ABS(N$3-N22),"N/A") -> N/A | T22: =IFERROR(ABS(O$3-O22),"N/A") -> N/A | U22: =SUM(P22:T22) -> 0 | V22: =_xlfn.RANK.EQ(U22,$U$4:$U$61,1) -> 1 | W22: =IF(Y22="Not suitable","-",V22) -> - | Y22: =IF(OR(Z22="Y",AA22="Y"),"Not suitable","") -> Not suitable | Z22: =IF(N22="N/A","Y","") -> Y
K23: =IFERROR(_xlfn.RANK.EQ(F23,F$3:F$61),"N/A") -> N/A | L23: =IFERROR(_xlfn.RANK.EQ(G23,G$3:G$61),"N/A") -> N/A | M23: =IFERROR(_xlfn.RANK.EQ(H23,H$3:H$61),"N/A") -> N/A | N23: =IFERROR(_xlfn.RANK.EQ(I23,I$3:I$61),"N/A") -> N/A | O23: =IFERROR(_xlfn.RANK.EQ(J23,J$3:J$61),"N/A") -> N/A | P23: =IFERROR(ABS(K$3-K23),"N/A") -> N/A | Q23: =IFERROR(ABS(L$3-L23),"N/A") -> N/A | R23: =IFERROR(ABS(M$3-M23),"N/A") -> N/A | S23: =IFERROR(ABS(N$3-N23),"N/A") -> N/A | T23: =IFERROR(ABS(O$3-O23),"N/A") -> N/A | U23: =SUM(P23:T23) -> 0 | V23: =_xlfn.RANK.EQ(U23,$U$4:$U$61,1) -> 1 | W23: =IF(Y23="Not suitable","-",V23) -> - | Y23: =IF(OR(Z23="Y",AA23="Y"),"Not suitable","") -> Not suitable | Z23: =IF(N23="N/A","Y","") -> Y
K24: =IFERROR(_xlfn.RANK.EQ(F24,F$3:F$61),"N/A") -> N/A | L24: =IFERROR(_xlfn.RANK.EQ(G24,G$3:G$61),"N/A") -> N/A | M24: =IFERROR(_xlfn.RANK.EQ(H24,H$3:H$61),"N/A") -> N/A | N24: =IFERROR(_xlfn.RANK.EQ(I24,I$3:I$61),"N/A") -> N/A | O24: =IFERROR(_xlfn.RANK.EQ(J24,J$3:J$61),"N/A") -> N/A | P24: =IFERROR(ABS(K$3-K24),"N/A") -> N/A | Q24: =IFERROR(ABS(L$3-L24),"N/A") -> N/A | R24: =IFERROR(ABS(M$3-M24),"N/A") -> N/A | S24: =IFERROR(ABS(N$3-N24),"N/A") -> N/A | T24: =IFERROR(ABS(O$3-O24),"N/A") -> N/A | U24: =SUM(P24:T24) -> 0 | V24: =_xlfn.RANK.EQ(U24,$U$4:$U$61,1) -> 1 | W24: =IF(Y24="Not suitable","-",V24) -> - | Y24: =IF(OR(Z24="Y",AA24="Y"),"Not suitable","") -> Not suitable | Z24: =IF(N24="N/A","Y","") -> Y
K25: =IFERROR(_xlfn.RANK.EQ(F25,F$3:F$61),"N/A") -> N/A | L25: =IFERROR(_xlfn.RANK.EQ(G25,G$3:G$61),"N/A") -> N/A | M25: =IFERROR(_xlfn.RANK.EQ(H25,H$3:H$61),"N/A") -> N/A | N25: =IFERROR(_xlfn.RANK.EQ(I25,I$3:I$61),"N/A") -> N/A | O25: =IFERROR(_xlfn.RANK.EQ(J25,J$3:J$61),"N/A") -> N/A | P25: =IFERROR(ABS(K$3-K25),"N/A") -> N/A | Q25: =IFERROR(ABS(L$3-L25),"N/A") -> N/A | R25: =IFERROR(ABS(M$3-M25),"N/A") -> N/A | S25: =IFERROR(ABS(N$3-N25),"N/A") -> N/A | T25: =IFERROR(ABS(O$3-O25),"N/A") -> N/A | U25: =SUM(P25:T25) -> 0 | V25: =_xlfn.RANK.EQ(U25,$U$4:$U$61,1) -> 1 | W25: =IF(Y25="Not suitable","-",V25) -> - | Y25: =IF(OR(Z25="Y",AA25="Y"),"Not suitable","") -> Not suitable | Z25: =IF(N25="N/A","Y","") -> Y
K26: =IFERROR(_xlfn.RANK.EQ(F26,F$3:F$61),"N/A") -> N/A | L26: =IFERROR(_xlfn.RANK.EQ(G26,G$3:G$61),"N/A") -> N/A | M26: =IFERROR(_xlfn.RANK.EQ(H26,H$3:H$61),"N/A") -> N/A | N26: =IFERROR(_xlfn.RANK.EQ(I26,I$3:I$61),"N/A") -> N/A | O26: =IFERROR(_xlfn.RANK.EQ(J26,J$3:J$61),"N/A") -> N/A | P26: =IFERROR(ABS(K$3-K26),"N/A") -> N/A | Q26: =IFERROR(ABS(L$3-L26),"N/A") -> N/A | R26: =IFERROR(ABS(M$3-M26),"N/A") -> N/A | S26: =IFERROR(ABS(N$3-N26),"N/A") -> N/A | T26: =IFERROR(ABS(O$3-O26),"N/A") -> N/A | U26: =SUM(P26:T26) -> 0 | V26: =_xlfn.RANK.EQ(U26,$U$4:$U$61,1) -> 1 | W26: =IF(Y26="Not suitable","-",V26) -> - | Y26: =IF(OR(Z26="Y",AA26="Y"),"Not suitable","") -> Not suitable | Z26: =IF(N26="N/A","Y","") -> Y
... K100: =IFERROR(_xlfn.RANK.EQ(F100,F$3:F$61),"N/A") -> N/A | L100: =IFERROR(_xlfn.RANK.EQ(G100,G$3:G$61),"N/A") -> N/A | M100: =IFERROR(_xlfn.RANK.EQ(H100,H$3:H$61),"N/A") -> N/A | N100: =IFERROR(_xlfn.RANK.EQ(I100,I$3:I$61),"N/A") -> N/A | O100: =IFERROR(_xlfn.RANK.EQ(J100,J$3:J$61),"N/A") -> N/A | P100: =IFERROR(ABS(K$3-K100),"N/A") -> N/A | Q100: =IFERROR(ABS(L$3-L100),"N/A") -> N/A | R100: =IFERROR(ABS(M$3-M100),"N/A") -> N/A | S100: =IFERROR(ABS(N$3-N100),"N/A") -> N/A | T100: =IFERROR(ABS(O$3-O100),"N/A") -> N/A | U100: =SUM(P100:T100) -> 0 | V100: =_xlfn.RANK.EQ(U100,$U$4:$U$61,1) -> 1 | W100: =IF(Y100="Not suitable","-",V100) -> - | Y100: =IF(OR(Z100="Y",AA100="Y"),"Not suitable","") -> Not suitable | Z100: =IF(N100="N/A","Y","") -> Y

Sheet ESG
B1: Company GICS Sector: | T1: Yes
B2: Information Technology | C2: <- Select Industry | T2: No
B3: ESG Analysis | K3: Relative ESG Analysis
B4: Parameters | C4: Impact | D4: Do they report? | E4: Ranking | F4: Mitigation Plan | G4: Traffic Lights | H4: Improvement over time? | I4: Targets / Goals? | J4: Comments | K4: Parameters | L4: =Peers!C6 -> #VALUE! | M4: =Peers!D6 -> #VALUE! | N4: =Peers!E6 -> #VALUE! | O4: =Peers!F6 -> #VALUE! | P4: =Peers!#REF! -> #REF! | Q4: =Peers!#REF! -> #REF! | R4: AVERAGE
B5: Environmental | K5: Ratios
A6: 1 | B6: CO2 Direct Emissions | C6: =VLOOKUP($B$2,'Sector Impact'!$K$4:$AA$16,A6+1,FALSE) -> Medium | D6: Yes | E6: Medium High | F6: Yes | H6: Scope 1 emissions stayed almost the same in 2021 compared with 2020 but increased 30% in 2022. Consistant decrease in scope 2 emissions over the 3 years | I6: 50% absolute reduction in greenhouse gas (GHG) emissions from AMD operations (Scope 1 and 2) by 2030 (base year 2020). 100% of AMD direct manufacturing suppliers to have a public GHG emissions reduction goal by 2025. | K6: CO2 Emissions/$M Sales | L6: =L12/L$11 -> 2.6546341 | M6: =M12/M$11 -> 6.4955322 | N6: =N12/N$11 -> 54.009112 | O6: =O12/O$11 -> 8.2997974 | P6: =P12/P$11 -> #DIV/0! | Q6: =Q12/Q$11 -> #DIV/0! | R6: =IFERROR(AVERAGE(L6:Q6),"") | X6: 2018 | Y6: 2019 | Z6: 2020 | AA6: 2021 | AB6: 2022
A7: 2 | B7: Total Water Consumption | C7: =VLOOKUP($B$2,'Sector Impact'!$K$4:$AA$16,A7+1,FALSE) -> Low | H7: Decreased between 2018-2021, increased in 2022 | I7: Aiming to reduce water use by a goal of at least 5 percent or more per AMD MI by 2025 compared to 2020. | K7: Water Consumption/$M Sales | L7: =L13/L$11 -> 4.5731707 | M7: =M13/M$11 -> 21.583268 | N7: =N13/N$11 -> 766.00861 | O7: =O13/O$11 -> 87.175118 | P7: =P13/P$11 -> #DIV/0! | Q7: =Q13/Q$11 -> #DIV/0! | R7: =IFERROR(AVERAGE(L7:Q7),"") | X7: 435600 | Y7: 457200 | Z7: 446400 | AA7: 388800 | AB7: 748800
A8: 3 | B8: Total Energy Consumption | C8: =VLOOKUP($B$2,'Sector Impact'!$K$4:$AA$16,A8+1,FALSE) -> High | D8: Yes | E8: Medium High | F8: Yes | H8: Almost the same between 2018-2021, increased in 2022 | I8: 30x increase in energy efficiency for AMD processors and accelerators powering servers for artificial intelligencetraining and high-performance computing by 2025 (base year 2020). 80% of AMD direct manufacturing suppliers to source renewable energy by 2025 | K8: Energy Consumption/$M Sales | L8: =L14/L$11 -> 23.707317 | M8: =M14/M$11 -> 70.35922 | N8: =N14/N$11 -> 530.24551 | O8: =O14/O$11 -> 97.97563 | P8: =P14/P$11 -> #DIV/0! | Q8: =Q14/Q$11 -> #DIV/0! | R8: =IFERROR(AVERAGE(L8:Q8),"") | X8: 192000 | Y8: 175000 | Z8: 151000 | AA8: 75000 | AB8: 183000
A9: 4 | B9: Waste Management | C9: =VLOOKUP($B$2,'Sector Impact'!$K$4:$AA$16,A9+1,FALSE) -> Low | H9: Decreased between 2019-2021, increased in 2022 | K9: Waste Production/$M Sales | L9: =L15/L$11 -> 0.027804878 | M9: =M15/M$11 -> 0.1665967 | N9: =N15/N$11 -> 4.3470008 | O9: =O15/O$11 -> 0.10305071 | P9: =P15/P$11 -> #DIV/0! | Q9: =Q15/Q$11 -> #DIV/0! | R9: =IFERROR(AVERAGE(L9:Q9),"") | X9: 3207 | Y9: 3358 | Z9: 2335 | AA9: 2892 | AB9: 8145
A10: 5 | B10: Land Degradation/Deforestation/Biodiversity loss/Animal sufering/… | C10: =VLOOKUP($B$2,'Sector Impact'!$K$4:$AA$16,A10+1,FALSE) -> Low | K10: Inputs | X10: 643 | Y10: 697 | Z10: 491 | AA10: 456 | AB10: 840
B11: Social | K11: Net Sales ($M) (2021) | L11: 16400 | M11: 16675 | N11: 79020 | O11: 33566
A12: 6 | B12: Employee Turnover % | C12: =VLOOKUP($B$2,'Sector Impact'!$K$4:$AA$16,A12+1,FALSE) -> Low | H12: In absolute terms no. The percentage of total turnover is is the same compared with 2021 (previous year). The turnover is at 10.6% wich is relatively high. | K12: CO2 Emissions Total (Tonnes) | L12: 43536 | M12: 108313 | N12: 4267800 | O12: 278591
A13: 7 | B13: Salaries & Compensation | C13: =VLOOKUP($B$2,'Sector Impact'!$K$4:$AA$16,A13+1,FALSE) -> Low | H13: N/A | I13: N/A | K13: Water Withdrawal Total (Cubic Meters) | L13: 75000 | M13: 359901 | N13: 60530000 | O13: 2926120
A14: 8 | B14: Reputation | C14: =VLOOKUP($B$2,'Sector Impact'!$K$4:$AA$16,A14+1,FALSE) -> Low | H14: N/A | I14: N/A | K14: Energy Consumption Total (Gigajoules) | L14: 388800 | M14: 1173240 | N14: 41900000 | O14: 3288650
A15: 9 | B15: Discrimination Events | C15: =VLOOKUP($B$2,'Sector Impact'!$K$4:$AA$16,A15+1,FALSE) -> Low | F15: Yes | K15: Waste Production Total (Tonnes) | L15: 456 | M15: 2778 | N15: 343500 | O15: 3459
A16: 10 | B16: Work Safety | C16: =VLOOKUP($B$2,'Sector Impact'!$K$4:$AA$16,A16+1,FALSE) -> High | D16: Yes | E16: "Best in class" | F16: Yes | H16: Yes, only 3 injured employees in 2023 | K16: ESG Scores
A17: 11 | B17: Damage to consumer health | C17: =VLOOKUP($B$2,'Sector Impact'!$K$4:$AA$16,A17+1,FALSE) -> Low | H17: N/A | I17: N/A | K17: Refinitiv | L17: 68 (42/255) 70/70/62 | M17: 76 (11/255) 67/73/90 | N17: 92 (1/255) 89/90/96 | O17: 73 (20/255) 70/90/48
A18: 12 | B18: PXP? | C18: =VLOOKUP($B$2,'Sector Impact'!$K$4:$AA$16,A18+1,FALSE) -> Low | K18: Sustainalytics | L18: 15.0 (low risk) | M18: 13.5 (low risk) | N18: 17.5 (low risk) | O18: 15.3 (low risk)
A19: 13 | B19: Supply chain | C19: =VLOOKUP($B$2,'Sector Impact'!$K$4:$AA$16,A19+1,FALSE) -> Low | I19: 100 percent of AMD direct supplier manufacturing factories to have a Responsible Business Alliance (RBA) audit or equivalent by 2025 (base year 2020) 80% of AMD direct manufacturing suppliers by spend to participate in a capacitybuilding activity by 2025 | K19: ISS | L19: B- | M19: C+ | N19: B- | O19: B-
A20: 14 | B20: Community involvement | C20: =VLOOKUP($B$2,'Sector Impact'!$K$4:$AA$16,A20+1,FALSE) -> Low | K20: CDP | L20: B/B | M20: B/B | N20: A/A/A | O20: B/B
A21: 15 | B21: Public Sector | C21: =VLOOKUP($B$2,'Sector Impact'!$K$4:$AA$16,A21+1,FALSE) -> Medium | D21: No | E21: Medium High | F21: No | H21: N/A | I21: N/A
A22: 16 | B22: Litigation | C22: =VLOOKUP($B$2,'Sector Impact'!$K$4:$AA$16,A22+1,FALSE) -> Very High | D22: No | E22: Medium High | F22: No | H22: N/A | I22: N/A | J22: Found several lawsuits against AMD in recent years but no signs of conviction
B23: Corporate Governance | K23: PARAMETERS
A24: 17 | B24: Diversity (Gender, Age, Industry, Region) | E24: "Villain" | F24: No | J24: 67% of the board is composed by males. 78% of the board is white and the other 22% is asian. All ages range between 53-69 year old (most members are between 57-62 years old) | K24: IMPACT | L24: RANKING | M24: MITIGATION PLAN | O24: TRAFFIC
A25: 18 | B25: % Independence | F25: No | H25: N/A | I25: N/A | K25: Low | L25: "Best in class" | M25: Is there evidence of a plan/program ?
A26: 19 | B26: average time as independent directors | E26: "Best in class" | F26: No | H26: N/A | I26: N/A | J26: 6.3 is the average tenure at AMD what is positive. | K26: Medium | L26: Medium High
A27: 20 | B27: Recent departures of directors / C-level executives? | E27: "Best in class" | F27: No | H27: N/A | I27: N/A | K27: High | L27: Medium
A28: 21 | B28: CEO/Chairman duality | E28: "Villain" | F28: No | H28: N/A | I28: N/A | J28: Before February 2022 the CEO and Chairman were different persons, since that date Lisa T. Su acummulated her CEO functions with "chair of the board" functions | K28: Very high | L28: "Villain"
A29: 22 | B29: Transparency (ESG, segments, acquisitions, other) | E29: Medium | F29: No | H29: N/A | I29: N/A | J29: The reports are complete and easy to read
A30: 23 | B30: Time taken to report after the end of the quarter / year | E30: "Villain" | F30: No | H30: N/A | I30: N/A | J30: The 2024 report (regarding the year 2023) hasn't been published
A31: 24 | B31: Additional participation of the CEO in other boards or excessive participation of Ch. | E31: "Best in class" | F31: No | H31: N/A | I31: N/A
A32: 25 | B32: Audit / Consulting | D32: Yes | E32: Medium | F32: No | H32: N/A | I32: N/A | J32: Bureau Veritas does the ESG audit. Other Audits are made internally. Consulted with Omdia for AI purposes and with BSR for ESG purposes
A33: 26 | B33: ESG-compensation related | D33: No | E33: "Villain" | F33: No | H33: N/A | I33: N/A
A34: 27 | B34: Management compensation schemes | D34: Yes | E34: Medium High | F34: Yes | H34: N/A | I34: N/A

Sheet Multiples valuation
L1: Enterprise Value Calculation
L2: In millions, except per share price | P2: Intel | R2: NVIDIA | T2: Qualcomm | V2: AMD
P3: 2022 | Q3: 2023 | R3: 2022 | S3: 2023 | T3: 2022 | U3: 2023 | V3: 2022 | W3: 2023
L4: Release date of 10-K report | P4: 45657 | Q4: 45657 | R4: 45322 | S4: 45322 | T4: 45565 | U4: 45565 | V4: 45565 | W4: 45565
B5: In millions, except ratio | C5: Intel | E5: NVIDIA | G5: Qualcomm | I5: AMD
C6: 2022 | D6: 2023 | E6: 2022 | F6: 2023 | G6: 2022 | H6: 2023 | I6: 2022 | J6: 2023 | L6: Closing price of shares ~7 days after report release | P6: 28.56 | Q6: 48.31 | R6: 221.62 | S6: 700.96 | T6: 116.42 | U6: 110.53 | V6: 85.91 | W6: 170.94
B7: Operating Cash Flow | C7: 15433 | D7: 11471 | E7: 5641 | F7: 28090 | G7: 9096 | H7: 11299 | I7: 3565 | J7: 1667 | L7: x Fully Diluted Shares Outstanding: | P7: 4456 | Q7: 4579 | R7: 2860 | S7: 2887 | T7: 1186 | U7: 1220 | V7: 1611388.2 | W7: 1615786.8
B8: Less: Capital Expenditure | C8: 25050 | D8: 25750 | E8: 1833 | F8: 1069 | G8: 2262 | H8: 1450 | I8: -450 | J8: -546 | M8: Basic shares outstanding | P8: 4137 | Q8: 4228 | R8: 2470 | S8: 2500 | T8: 1121 | U8: 1113
B9: Enterprise Value (see calc.) | C9: 159989 | D9: 267785 | E9: 642475 | F9: 2027448 | G9: 150783 | H9: 141795 | I9: 138432.68 | J9: 276200.63 | M9: Employee Equity Incentive Plan | P9: 119 | Q9: 194 | R9: 160 | S9: 160 | T9: 43 | U9: 88
B10: Free Cash Flow | C10: -9617 | D10: -14279 | E10: 3808 | F10: 27021 | G10: 6834 | H10: 9849 | I10: =I7+I8 -> 3115 | J10: =J7+J8 -> 1121 | M10: Employee Stock Purchase Plan | P10: 200 | Q10: 157 | R10: 230 | S10: 227 | T10: 22 | U10: 19
B11: EV/FCF | C11: -16.64 | D11: -18.75 | E11: 168.72 | F11: 75.03 | G11: 22.06 | H11: 14.4 | I11: =I9/I10 -> 44.440668 | J11: =J9/J10 -> 246.38772 | L11: Market Capitalization | P11: 127263.36 | Q11: 221211.49 | R11: 633833.2 | S11: 2023671.5 | T11: 138074.12 | U11: 134846.6 | V11: =V7*V6 -> 1.3843436e+08 | W11: =W6*W7 -> 2.762026e+08
B12: EV/FCF/Growth | D12: =D11/(D10/C10-1) -> -38.678411 | F12: =F11/(F10/E10-1) -> 12.308372 | H12: =H11/(H10/G10-1) -> 32.64 | J12: =J11/(J10/I10-1) -> -384.90358 | L12: Plus: Total Debt | P12: 42007 | Q12: 49278 | R12: 12031 | S12: 11056 | T12: 15482 | U12: 15398 | V12: 2252 | W12: 2863
L13: Plus: Noncontrolling Interest | P13: 1863 | Q13: 4375 | R13: 0 | S13: 0 | T13: 0 | U13: 0 | V13: 0 | W13: 0
L14: Less: Cash and Cash Equivalents | P14: 11144 | Q14: 7079 | R14: 3389 | S14: 7280 | T14: 2773 | U14: 8450 | V14: 3933 | W14: 4835
L15: Enterprise Value | P15: 159989.36 | Q15: 267785.49 | R15: 642475.2 | S15: 2027447.5 | T15: 150783.12 | U15: 141794.6 | V15: =V11+V12-V14 -> 1.3843268e+08 | W15: =W11+W12-W14 -> 2.7620063e+08

Sheet Assumptions
B2: Assumptions
B4: Prospects:
B6: Links:
C8: 2023 | D8: =C8-1 -> 2022 | E8: =D8-1 -> 2021 | F8: =E8-1 -> 2020 | G8: =F8-1 -> 2019 | H8: =G8-1 -> 2018 | I8: =H8-1 -> 2017 | J8: =I8-1 -> 2016 | K8: =J8-1 -> 2015 | ... M8: =L8-1 -> 2013 | O8: 10Y Average | P8: 5Y Average | Q8: 3Y Average | S8: Short Term Forecast | T8: Long Term Forecast
B9: Revenue growth | C9: =(Inputs!B6-Inputs!C6)/Inputs!C6 -> -0.03902377 | D9: =(Inputs!C6-Inputs!D6)/Inputs!D6 -> 0.43610807 | E9: =(Inputs!D6-Inputs!E6)/Inputs!E6 -> 0.68329407 | F9: =(Inputs!E6-Inputs!F6)/Inputs!F6 -> 0.45045313 | G9: =(Inputs!F6-Inputs!G6)/Inputs!G6 -> 0.03953668 | H9: =(Inputs!G6-Inputs!H6)/Inputs!H6 -> 0.23262897 | I9: =(Inputs!H6-Inputs!I6)/Inputs!I6 -> 0.22963483 | J9: =(Inputs!I6-Inputs!J6)/Inputs!J6 -> 0.070408419 | ... M9: =(Inputs!L6-Inputs!M6)/Inputs!M6 -> -0.022685356 | O9: =AVERAGE(C9:M9) -> 0.16766042 | P9: =AVERAGE(C9:G9) -> 0.31407363 | Q9: =AVERAGE(C9:E9) -> 0.36012612
B10: Operating Margin | C10: =Inputs!B8/Inputs!B6 -> 0.017680776 | D10: =Inputs!C8/Inputs!C6 -> 0.053557053 | E10: =Inputs!D8/Inputs!D6 -> 0.22155288 | F10: =Inputs!E8/Inputs!E6 -> 0.13469221 | G10: =Inputs!F8/Inputs!F6 -> 0.067597682 | H10: =Inputs!G8/Inputs!G6 -> 0.067799228 | I10: =Inputs!H8/Inputs!H6 -> 0.021892252 | J10: =Inputs!I8/Inputs!I6 -> -0.10299625 | ... M10: =Inputs!L8/Inputs!L6 -> 0.019248915 | O10: =AVERAGE(C10:M10) -> 0.031024876 | P10: =AVERAGE(C10:G10) -> 0.099016119 | Q10: =AVERAGE(C10:E10) -> 0.097596902
B13: Modelling Factors
B35: Revenues forecast
B37: Notes
J39: There are more than 200 million corporate computers that are over 4 years old
D41: NVIDIA Compute&Networking
E42: 2021 | F42: 2022 | G42: 2023 | R42: NOTE: Forecast Database growth for next year based on NVIDIA's growth | BI42: Note: 2.8B$ of acquisiton realted intangibles were amortized, hence reducing EBIT for 2023FY
D43: Revenue | E43: 11046 | F43: 15068 | G43: 47405 | I43: Other Risks: | J43: Recession risk (client and embedded segment would be the most affected)
D44: EBIT | E44: 4598 | F44: 5083 | G44: 32016
D45: Margin | E45: =E44/E43 -> 0.41625928 | F45: =F44/F43 -> 0.3373374 | G45: =G44/G43 -> 0.6753718
J46: Self-drviving, robotics and manufacturing automation are all industries set to grow at a CAGR of 12-15% with the chance of exponential growth in the longer term.
J48: Given the recent Sony's management downgrade of sales expectatitions for PS5 and the lack of new products releases, we are forecasting a decrease in consoles chips sales in the near term. However, the Global AR/VR chip market is set to grow at a CAGR of 18%
J49: Between 2024 and 2032, and AMD is a leader in VR Chips. That growth opportunity is set to cover the lack of it in the consoles space. Also, accordingly to AMD's guidance, demand for PC's gaming chips is strong and should offest the decrease in consoles related sales.
D51: Note: Cut projections for China (gov banned chips from intel and amd out of gov PCs) | J51: The recent launch of MI300X AI GPU to outcompete in the AI accelarator segment with NVIDIA stil hasn't been materialized in the company's balance sheet, but it certainly marks a shift of focus from PCs and gaming to AI. The company received 3.3B$ of orders after announcment (half the 23FY revenue for the segment)
D52: Tenstorrent Start-up | J52: The software engeneers at AMD are also smoothening techincal requirments to ease the transition between suppliers for cients.
J53: Despite the uncertainty, that leaves room for growth while shifting away from wekening segments.
D54: AI computers for developers and content creators | J54: Generative models will need a lot of processing power, which is controlled by Meta, Amazon, Googl and Microsoft cloud-based data-centers. For exemple, OpenAI's ChatGPT works on the MSFT Azzure Cloud. The recent innovations in AI chips
D55: Quantum computers? | J55: enable these data-bases to further escalate their processing capabilities and become more energy efficient. In that context, GPUs and AI accelators are the shovels for the gold rush that comes with AI.
D56: AGI?
J58: Given the large amplitude of possibilities in predicting a recently formed industry that assents in both the uncertainty of the innovation capabilities, exponential growth and business model adoption (AI still hasn't produced relevant revenue), the projection will
D59: NVIDIA 4Q 2023 | E59: 500000 | J59: count with 3 scenarios (optimistic, neutral and pessimistic).
D60: Number of H100 sod | E60: 14500000000
D61: Revenue | E61: =E60/E59 -> 29000
D62: Average price of sale | J62: Optimistic Case | K62: AMD and NVIDIA share the segment with same competitive dynamics in CPU market
J63: Neutral Scenario | K63: Intel and Qualcom are already delevoping their AI accelarators. The segment might get competitive in the next years
D64: Note: H100 chips price may vary between 20-40k | J64: Pessimistic | K64: Meta, Googl, Msft and amzn efforts of creating their own chips and outsource them to TSMC materialize and growth for chip providers is limited
D65: MSFT bought 150 000 of those chips at the price of 5B$
D66: which gives an average of 3300$. Amazon and Googl both bought 50k H100s | J66: It's worth noting that the PC industry is cyclical and using a moving average would give a skewed analysis given that the industry is in it's low.
J67: During the COVID, there was sky-high demand for new devices and sales grew exponentially. After that growth driver dried up, demand fell.
B68: There is going to be a huge increase in the short term given that the AI chips are in high demand (major tech companies are buying all the stock there is and TSMC is already expanding it's | J68: It's been 3 years since the industry all time high, and PC's got commoditazed with the new hibrid and remote work dynamic. There are also 200 million corporate
B69: production capacity, there will be a natural increase in the chips saes for AMD, which then should grow with the industry or in another specific way based on the forecast of industry dynamics | J69: PC's that have more than 4 years, so they should be replaced in the near term. But the biggest driver is expected to be AI computers, that will initially be sold
J70: at a premium. Because of those factors, we're bullish on the client segment to deliver high returns in 2024 and forward for AMD.
B71: The chips market is not very fragmented, and usually there is a main player who controls a big part of it. If the same competitive dynamic between Intel and AMD | J71: The difference between the scenarios is wether AMD mantains it's 90% share of AI-PCs and is able to capitalize on the increasing demand.
B72: is seen in the AI chips, NVIDIA would have aprox. 80% of the market and AMD 20%. Currently, NVIDIA controls about 80-90% of the market | J72: The forecasts for AI enabled PC's is consistent across different reports
B74: Optimistic
B76: CAGR for hardware: 33% | D76: 2028-2034
D77: Sales YoY growth at 42% (CapEx margins for data centers would remain constant after the initial increase)
D78: Broad adoption of AI in the next years and AMD becomes an important player (same Intel-AMD competitive dynamics)
B80: Li Su bullish projections
B81: AI chips | E81: Projections
B82: Year | C82: Market Value | D82: Implied CAGR | E82: Revenue from AI chips | F82: Implied share | G82: Implied CAGR
B83: 2023 | C83: 45
B84: 2024 | C84: =C83*(1+D84) -> 76.710583 | D84: =(C87/C83)^(1/4)-1 -> 0.70467963 | E84: 6 | F84: =E84/C84 -> 0.078216066
B85: 2025 | C85: =C84*(1+D85) -> 130.76697 | D85: 0.70467963 | E85: =E84*2 -> 12 | F85: =E85/C85 -> 0.091766294
B86: 2026 | C86: =C85*(1+D86) -> 222.91579 | D86: 0.70467963 | E86: =E85*2 -> 24 | F86: =E86/C86 -> 0.10766398
B87: 2027 | C87: 380 | D87: 0.70467963 | E87: =E86*1.8 -> 43.2 | F87: =E87/C87 -> 0.11368421 | G87: =(E87/E84)^(1/3)-1 -> 0.93097877
B89: Statista and The Brainy Insights project te chip market to be worth between 340-375 B$ in 2032
B90: Li Su forecasted the market to be 400B$ by 2027
N91: Company will need to close ecossystem and buy up possible disruprive start-ups to keep its products competitive in the market (increase Acq. factor and correlate with intangibles and PPE)
D93: 2021 | E93: 2022 | F93: 2023 | G93: 2024 | H93: 2025 | I93: 2026 | J93: 2027
C94: Revenue | D94: 3694 | E94: 6043 | F94: 6496 | G94: =F94*0.8 -> 5196.8 | H94: =G94*0.8 -> 4157.44 | I94: =H94*0.75 -> 3118.08 | J94: =I94*0.7 -> 2182.656
B95: Data center segment | C95: EBIT | D95: 991 | E95: 1081 | F95: 1267 | G95: =G94*G96 -> 1299.2 | H95: =H94*H96 -> 1164.0832 | I95: =I94*I96 -> 935.424 | J95: =J94*J96 -> 742.10304
B96: (does'nt include AI chips) | C96: Margin | D96: =D95/F94 -> 0.15255542 | E96: =E95/E94 -> 0.17888466 | F96: =F95/D94 -> 0.34298863 | G96: 0.25 | H96: 0.28 | I96: 0.3 | J96: 0.34
C97: Average | F97: =AVERAGE(D96:F96) -> 0.22480957
E98: AI Chips | F98: AI Chips Revenue | G98: 6000 | H98: 12000 | I98: 24000 | J98: 43000
F99: EBIT | G99: =G98*G100 -> 2400 | H99: =H98*H100 -> 4800 | I99: =I98*I100 -> 9600 | J99: =J98*J100 -> 19350
F100: EBIT Margin | G100: 0.4 | H100: 0.4 | I100: 0.4 | J100: 0.45 | K100: 2028E | L100: 2029E | M100: 2030E | N100: 2031 | O100: 2032 | P100: 2033 | Q100: 2034 | R100: 2035 | S100: 2036 | T100: 2037 | U100: 2038 | V100: 2039 | W100: 2040 | X100: 2041 | Y100: 2042 | Z100: 2043 | AA100: 2044 | AB100: 2045 | AC100: 2046 | AD100: 2047 | AE100: 2048 | AF100: 2049
E101: Data Center and AI segment | F101: Revenue | G101: =G98+G94 -> 11196.8 | H101: =H98+H94 -> 16157.44 | I101: =I98+I94 -> 27118.08 | J101: =J98+J94 -> 45182.656 | K101: =J101*(1+K102) -> 67773.984 | L101: =K101*(1+L102) -> 94883.578 | M101: =L101*(1+M102) -> 128092.83 | N101: =M101*(1+N102) -> 172925.32 | O101: =N101*(1+O102) -> 233449.18 | P101: =O101*(1+P102) -> 303483.94 | Q101: =P101*(1+Q102) -> 394529.12 | R101: =Q101*(1+R102) -> 473434.94 | ... AF101: =AE101*(1+AF102) -> 2662056.7
F102: YoY Growth | G102: =G101/F94-1 -> 0.72364532 | H102: =H101/G101-1 -> 0.44304087 | I102: =I101/H101-1 -> 0.67836489 | J102: =J101/I101-1 -> 0.6661451 | K102: 0.5 | L102: 0.4 | M102: 0.35 | N102: 0.35 | O102: 0.35 | P102: 0.3 | Q102: 0.3 | R102: 0.2 | S102: 0.2 | T102: 0.2 | U102: 0.2 | V102: 0.2 | W102: 0.15 | X102: 0.1 | Y102: 0.1 | Z102: 0.1 | AA102: 0.1 | AB102: 0.1 | AC102: 0.1 | AD102: 0.1 | AE102: 0.1 | AF102: 0.1
F103: EBIT | G103: =G99+G95 -> 3699.2 | H103: =H99+H95 -> 5964.0832 | I103: =I99+I95 -> 10535.424 | J103: =J99+J95 -> 20092.103 | K103: =K101*K104 -> 33886.992 | L103: =L101*L104 -> 47441.789 | M103: =M101*M104 -> 64046.415 | N103: =N101*N104 -> 86462.66 | O103: =O101*O104 -> 116724.59 | P103: =P101*P104 -> 151741.97 | Q103: =Q101*Q104 -> 197264.56 | R103: =R101*R104 -> 236717.47 | ... AF103: =AF101*AF104 -> 1331028.3
F104: Margin | G104: =G103/G101 -> 0.33038011 | H104: =H103/H101 -> 0.36912303 | I104: =I103/I101 -> 0.38850184 | J104: =J103/J101 -> 0.44468619 | K104: 0.5 | L104: 0.5 | M104: 0.5 | N104: 0.5 | O104: 0.5 | P104: 0.5 | Q104: 0.5 | R104: 0.5 | S104: 0.5 | T104: 0.5 | U104: 0.5 | V104: 0.5 | W104: 0.5 | X104: 0.5 | Y104: 0.5 | Z104: 0.5 | AA104: 0.5 | AB104: 0.5 | AC104: 0.5 | AD104: 0.5 | AE104: 0.5 | AF104: 0.5
D106: 2021 | E106: 2022 | F106: 2023 | G106: 2024E | H106: 2025E | I106: 2026E | J106: 2027E | K106: 2028E | L106: 2029E | M106: 2030E | N106: 2031 | O106: 2032 | P106: 2033 | Q106: 2034 | R106: 2035 | S106: 2036 | T106: 2037 | U106: 2038 | V106: 2039 | W106: 2040 | X106: 2041 | Y106: 2042 | Z106: 2043 | AA106: 2044 | AB106: 2045 | AC106: 2046 | AD106: 2047 | AE106: 2048 | AF106: 2049
B107: Client Segment | C107: Revenue | D107: 6887 | E107: 6201 | F107: 4651 | G107: =F107*(1+G108) -> 5116.1 | H107: =G107*(1+H108) -> 6395.125 | I107: =H107*(1+I108) -> 9208.98 | J107: =I107*(1+J108) -> 13260.931 | K107: =J107*(1+K108) -> 17239.211 | L107: =K107*(1+L108) -> 20687.053 | M107: =L107*(1+M108) -> 24824.463 | N107: =M107*(1+N108) -> 29789.356 | ... AF107: =AE107*(1+AF108) -> 251398.99
C108: YoY Growth | E108: =E107/D107-1 -> -0.099607957 | F108: =F107/E107-1 -> -0.24995968 | G108: 0.1 | H108: 0.25 | I108: 0.44 | J108: 0.44 | K108: 0.3 | L108: 0.2 | M108: 0.2 | N108: 0.2 | O108: 0.2 | P108: 0.2 | Q108: 0.2 | R108: 0.15 | S108: 0.15 | T108: 0.15 | U108: 0.15 | V108: 0.15 | W108: 0.15 | X108: 0.1 | Y108: 0.1 | Z108: 0.1 | AA108: 0.1 | AB108: 0.08 | AC108: 0.08 | AD108: 0.08 | AE108: 0.08 | AF108: 0.06
C109: EBIT | D109: 2088 | E109: 1190 | F109: -46 | G109: =G107*G110 -> 511.61 | H109: =H107*H110 -> 959.26875 | I109: =I107*I110 -> 3683.592 | J109: =J107*J110 -> 5304.3725 | K109: =K107*K110 -> 7757.6448 | L109: =L107*L110 -> 9309.1737 | M109: =M107*M110 -> 11171.008 | N109: =N107*N110 -> 13405.21 | ... AF109: =AF107*AF110 -> 113129.54
C110: Margin | D110: =D109/F107 -> 0.44893571 | E110: =E109/E107 -> 0.19190453 | F110: =F109/D107 -> -0.0066792508 | G110: 0.1 | H110: 0.15 | I110: 0.4 | J110: 0.4 | K110: 0.45 | L110: 0.45 | M110: 0.45 | N110: 0.45 | O110: 0.45 | P110: 0.45 | Q110: 0.5 | R110: 0.45 | S110: 0.45 | T110: 0.45 | U110: 0.45 | V110: 0.45 | W110: 0.45 | X110: 0.45 | Y110: 0.45 | Z110: 0.45 | AA110: 0.45 | AB110: 0.45 | AC110: 0.45 | AD110: 0.45 | AE110: 0.45 | AF110: 0.45
D112: 2021 | E112: 2022 | F112: 2023 | G112: 2024E | H112: 2025E | I112: 2026E | J112: 2027E | K112: 2028E | L112: 2029E | M112: 2030E | N112: 2031 | O112: 2032 | P112: 2033 | Q112: 2034 | R112: 2035 | S112: 2036 | T112: 2037 | U112: 2038 | V112: 2039 | W112: 2040 | X112: 2041 | Y112: 2042 | Z112: 2043 | AA112: 2044 | AB112: 2045 | AC112: 2046 | AD112: 2047 | AE112: 2048 | AF112: 2049
C113: Revenue | D113: 3694 | E113: 6043 | F113: 6496 | G113: =F113*(1+G114) -> 5846.4 | H113: =G113*(1+H114) -> 7308 | I113: =H113*(1+I114) -> 9135 | J113: =I113*(1+J114) -> 10962 | K113: =J113*(1+K114) -> 15346.8 | L113: =K113*(1+L114) -> 18416.16 | M113: =L113*(1+M114) -> 19336.968 | N113: =M113*(1+N114) -> 20303.816 | ... AF113: =AE113*(1+AF114) -> 107756.29
C114: YoY Growth | E114: =E113/D113-1 -> 0.63589605 | F114: =F113/E113-1 -> 0.074962767 | G114: -0.1 | H114: 0.25 | I114: 0.25 | J114: 0.2 | K114: 0.4 | L114: 0.2 | M114: 0.05 | N114: 0.05 | O114: 0.05 | P114: 0.1 | Q114: 0.1 | R114: 0.1 | S114: 0.1 | T114: 0.1 | U114: 0.1 | V114: 0.1 | W114: 0.1 | X114: 0.1 | Y114: 0.1 | Z114: 0.1 | AA114: 0.1 | AB114: 0.1 | AC114: 0.1 | AD114: 0.1 | AE114: 0.1 | AF114: 0.1
B115: Gaming | C115: EBIT | D115: 971 | E115: 953 | F115: 934 | G115: =G113*G116 -> 1461.6 | H115: =H113*H116 -> 2046.24 | I115: =I113*I116 -> 2740.5 | J115: =J113*J116 -> 3288.6 | K115: =K113*K116 -> 4604.04 | L115: =L113*L116 -> 5524.848 | M115: =M113*M116 -> 6767.9388 | N115: =N113*N116 -> 7106.3357 | ... AF115: =AF113*AF116 -> 43102.515
C116: Margin | D116: =D115/F113 -> 0.1494766 | E116: =E115/E113 -> 0.15770313 | F116: =F115/D113 -> 0.25284245 | G116: 0.25 | H116: 0.28 | I116: 0.3 | J116: 0.3 | K116: 0.3 | L116: 0.3 | M116: 0.35 | N116: 0.35 | O116: 0.4 | P116: 0.4 | Q116: 0.45 | R116: 0.45 | S116: 0.45 | T116: 0.45 | U116: 0.45 | V116: 0.45 | W116: 0.4 | X116: 0.4 | Y116: 0.4 | Z116: 0.4 | AA116: 0.4 | AB116: 0.4 | AC116: 0.4 | AD116: 0.4 | AE116: 0.4 | AF116: 0.4
D119: 2021 | E119: 2022 | F119: 2023 | G119: 2024E | H119: 2025E | I119: 2026E | J119: 2027E | K119: 2028E | L119: 2029E | M119: 2030E | N119: 2031 | O119: 2032 | P119: 2033 | Q119: 2034 | R119: 2035 | S119: 2036 | T119: 2037 | U119: 2038 | V119: 2039 | W119: 2040 | X119: 2041 | Y119: 2042 | Z119: 2043 | AA119: 2044 | AB119: 2045 | AC119: 2046 | AD119: 2047 | AE119: 2048 | AF119: 2049
C120: Revenue | D120: 246 | E120: 4552 | F120: 5321 | G120: =F120*1.17 -> 6225.57 | H120: =G120*1.17 -> 7283.9169 | I120: =H120*1.17 -> 8522.1828 | J120: =I120*1.17 -> 9970.9538 | K120: =J120*(1+K121) -> 11965.145 | L120: =K120*(1+L121) -> 14358.174 | M120: =L120*(1+M121) -> 17229.808 | N120: =M120*(1+N121) -> 20675.77 | O120: =N120*(1+O121) -> 24810.924 | P120: =O120*(1+P121) -> 29773.109 | Q120: =P120*(1+Q121) -> 35727.73 | R120: =Q120*(1+R121) -> 41086.89 | ... AF120: =AE120*(1+AF121) -> 278078.8
C121: YoY Growth | E121: =E120/D120-1 -> 17.504065 | F121: =F120/E120-1 -> 0.16893673 | G121: =G120/F120-1 -> 0.17 | H121: =H120/G120-1 -> 0.17 | I121: =I120/H120-1 -> 0.17 | J121: =J120/I120-1 -> 0.17 | K121: 0.2 | L121: 0.2 | M121: 0.2 | N121: 0.2 | O121: 0.2 | P121: 0.2 | Q121: 0.2 | R121: 0.15 | S121: 0.15 | T121: 0.15 | U121: 0.15 | V121: 0.15 | W121: 0.15 | X121: 0.15 | Y121: 0.15 | Z121: 0.15 | AA121: 0.15 | AB121: 0.15 | AC121: 0.15 | AD121: 0.15 | AE121: 0.15 | AF121: 0.1
B122: Embedded | C122: EBIT | D122: 44 | E122: 2254 | F122: 2628 | G122: =G120*G123 -> 3112.785 | H122: =H120*H123 -> 3641.9584 | I122: =I120*I123 -> 4261.0914 | J122: =J120*J123 -> 4985.4769 | K122: =K120*K123 -> 5982.5723 | L122: =L120*L123 -> 7179.0868 | M122: =M120*M123 -> 8614.9041 | N122: =N120*N123 -> 10337.885 | ... AF122: =AF120*AF123 -> 125135.46
C123: Margin | D123: =D122/D120 -> 0.17886179 | E123: =E122/E120 -> 0.49516696 | F123: =F122/F120 -> 0.49389213 | G123: 0.5 | H123: 0.5 | I123: 0.5 | J123: 0.5 | K123: 0.5 | L123: 0.5 | M123: 0.5 | N123: 0.5 | O123: 0.5 | P123: 0.55 | Q123: 0.55 | R123: 0.55 | S123: 0.55 | T123: 0.55 | U123: 0.55 | V123: 0.55 | W123: 0.55 | X123: 0.5 | Y123: 0.5 | Z123: 0.5 | AA123: 0.5 | AB123: 0.5 | AC123: 0.45 | AD123: 0.45 | AE123: 0.45 | AF123: 0.45
D126: 2021 | E126: 2022 | F126: 2023 | G126: 2024E | H126: 2025E | I126: 2026E | J126: 2027E | K126: 2028E | L126: 2029E | M126: 2030E | N126: 2031 | O126: 2032 | P126: 2033 | Q126: 2034 | R126: 2035 | S126: 2036 | T126: 2037 | U126: 2038 | V126: 2039 | W126: 2040 | X126: 2041 | Y126: 2042 | Z126: 2043 | AA126: 2044 | AB126: 2045 | AC126: 2046 | AD126: 2047 | AE126: 2048 | AF126: 2049
B127: Revenue and EBIT Projections | C127: Revenue | D127: =D120+D113+D107+D94 -> 14521 | E127: =E120+E113+E107+E94 -> 22839 | F127: =F120+F113+F107+F94 -> 22964 | G127: =G120+G113+G107+G101 -> 28384.87 | H127: =H120+H113+H107+H101 -> 37144.482 | I127: =I120+I113+I107+I101 -> 53984.243 | J127: =J120+J113+J107+J101 -> 79376.541 | K127: =K120+K113+K107+K101 -> 112325.14 | L127: =L120+L113+L107+L101 -> 148344.96 | M127: =M120+M113+M107+M101 -> 189484.07 | N127: =N120+N113+N107+N101 -> 243694.26 | ... AF127: =AF120+AF113+AF107+AF101 -> 3299290.8
C128: YoY Growth | E128: =E127/D127-1 -> 0.57282556 | F128: =F127/E127-1 -> 0.0054730943 | G128: =G127/F127-1 -> 0.23605948 | H128: =H127/G127-1 -> 0.30860145 | I128: =I127/H127-1 -> 0.45335835 | J128: =J127/I127-1 -> 0.470365 | K128: =K127/J127-1 -> 0.41509239 | L128: =L127/K127-1 -> 0.32067465 | ... AF128: =AF127/AE127-1 -> 0.096846137
C129: EBIT from segments | D129: 4094 | E129: =E109+E95+E115+E122 -> 5478 | F129: =F109+F95+F115+F122 -> 4783 | G129: =G122+G115+G109+G103 -> 8785.195 | H129: =H122+H115+H109+H103 -> 12611.55 | I129: =I122+I115+I109+I103 -> 21220.607 | J129: =J122+J115+J109+J103 -> 33670.552 | K129: =K122+K115+K109+K103 -> 52231.249 | L129: =L122+L115+L109+L103 -> 69454.897 | M129: =M122+M115+M109+M103 -> 90600.266 | N129: =N122+N115+N109+N103 -> 117312.09 | ... AF129: =AF122+AF115+AF109+AF103 -> 1612395.9
C130: Other operating costs | D130: -409 | E130: -4979 | F130: -4419 | G130: =G127*(-0.13-0.05-0.005) -> -5251.2009 | H130: =H127*(-0.13-0.05-0.005) -> -6871.7292 | I130: =I127*(-0.13-0.05-0.005) -> -9987.0849 | J130: =J127*(-0.13-0.05-0.005) -> -14684.66 | K130: =K127*(-0.12-0.06-0.005) -> -20780.151 | L130: =L127*(-0.12-0.06-0.005) -> -27443.818 | M130: =M127*(-0.12-0.06-0.005) -> -35054.553 | N130: =N127*(-0.035-0.06-0.12) -> -52394.266 | O130: =O127*(-0.035-0.06-0.12) -> -67795.163 | P130: =P127*(-0.035-0.06-0.12) -> -85914.995 | Q130: =Q127*(-0.035-0.06-0.12) -> -109118.7 | R130: =R127*(-0.12-0.04-0.035) -> -117408.49 | S130: =S127*(-0.12-0.04-0.035) -> -139359.1 | T130: =T127*(-0.12-0.04-0.035) -> -165497.82 | U130: =U127*(-0.12-0.04-0.035) -> -196634.76 | V130: =V127*(-0.12-0.04-0.035) -> -233738.17 | W130: =W127*(-0.12-0.04-0.035) -> -268393.83 | X130: =X127*(-0.12-0.04-0.035) -> -296038.96 | Y130: =Y127*(-0.12-0.04-0.035) -> -326569.46 | ... AF130: =AF127*(-0.12-0.04-0.035) -> -643361.7
C131: EBIT | D131: =D129+D130 -> 3685 | E131: =E129+E130 -> 499 | F131: =F129+F130 -> 364 | G131: =G129+G130 -> 3533.9941 | H131: =H129+H130 -> 5739.8212 | I131: =I129+I130 -> 11233.522 | J131: =J129+J130 -> 18985.892 | K131: =K129+K130 -> 31451.098 | ... AF131: =AF129+AF130 -> 969034.16
C132: EBIT margin | D132: =D131/D127 -> 0.2537704 | E132: =E131/E127 -> 0.021848592 | F132: =F131/F127 -> 0.015850897 | G132: =G131/G127 -> 0.12450274 | H132: =H131/H127 -> 0.15452689 | I132: =I131/I127 -> 0.20808891 | J132: =J131/J127 -> 0.2391877 | K132: =K131/K127 -> 0.28000053 | ... AF132: =AF131/AF127 -> 0.29370984
C133: Segments Margin | D133: =D129/D127 -> 0.28193651 | E133: =E129/E127 -> 0.23985288 | F133: =F129/F127 -> 0.20828253 | G133: =G129/G127 -> 0.30950274 | H133: =H129/H127 -> 0.33952689 | I133: =I129/I127 -> 0.39308891 | J133: =J129/J127 -> 0.4241877 | K133: =K129/K127 -> 0.46500053 | ... AF133: =AF129/AF127 -> 0.48870984
B136: Neutral
B138: Datacenter's infrastructure is not ready for full AI adoption
B140: Margin is derived based on the margin for each year with similar sales values for segment
M142: 2024-2027 | N142: 2028-2049
L143: Amortization projections | M143: 13%(IntangiblesN-Intangibles2023) | N143: 12% of intangibles
M144: adding guidance for each year
B145: Base Case
B146: Dell'Oro Group
B147: Data center IT Semiconductor Market | E147: AI Accelators Market | G147: Projections | M147: 0.13 | N147: 0.12
B148: Year | C148: Market Value | D148: Implied CAGR | E148: Market Size | F148: Implied CAGR | G148: Revenue from AI chips | H148: Implied share | I148: Implied CAGR
B149: 2023 | C149: =C150/(1+D149) -> 117.1456 | E149: 45
...

Sheet Pessimistic
A1: VALUATION MODEL
G3: Short Term | K3: Long Term
A4: Section | B4: Line # | C4: ITEM | D4: 2021 (Real) | E4: 2022 (Real) | F4: 2023 (Real) | G4: 2024 | H4: =G4+1 -> 2025 | I4: =H4+1 -> 2026 | J4: =I4+1 -> 2027 | K4: =J4+1 -> 2028 | L4: =K4+1 -> 2029 | M4: =L4+1 -> 2030 | N4: =M4+1 -> 2031 | O4: =N4+1 -> 2032 | ... AF4: =AE4+1 -> 2049
A5: INCOME STATEMENT | B5: 1 | C5: Growth | D5: 0.68329407 | E5: 0.43610807 | F5: -0.03902377 | G5: =G6/F6-1 -> 0.15562919 | H5: =H6/G6-1 -> 0.14582659 | I5: =I6/H6-1 -> 0.14849817 | J5: =J6/I6-1 -> 0.15345069 | K5: =K6/J6-1 -> 0.22628073 | L5: =L6/K6-1 -> 0.17330147 | M5: =M6/L6-1 -> 0.14427941 | N5: =N6/M6-1 -> 0.14821829 | ... AE5: =AE6/AD6-1 -> 0.11731885 | AF5: 0.0275
B6: 2 | C6: Revenues/Sales | D6: 16434 | E6: 23601 | F6: 22680 | G6: =Assumptions!G267 -> 26209.67 | H6: =Assumptions!H267 -> 30031.737 | I6: =Assumptions!I267 -> 34491.395 | J6: =Assumptions!J267 -> 39784.123 | K6: =Assumptions!K267 -> 48786.503 | L6: =Assumptions!L267 -> 57241.276 | M6: =Assumptions!M267 -> 65500.013 | N6: =Assumptions!N267 -> 75208.313 | ... AF6: =Assumptions!AF267 -> 632504.66
B7: 3 | C7: EBIT/Operating Margin | D7: =D8/D6 -> 0.22130948 | E7: =E8/E6 -> 0.052752002 | F7: =F8/F6 -> 0.017328042 | G7: =G8/G6 -> 0.092827039 | H7: =H8/H6 -> 0.12498393 | I7: =I8/I6 -> 0.15251881 | J7: =J8/J6 -> 0.1702577 | K7: =K8/K6 -> 0.19881167 | ... AF7: =AF8/AF6 -> 0.20592712
B8: 4 | C8: EBIT | D8: 3637 | E8: 1245 | F8: 393 | G8: =Assumptions!G271 -> 2432.966 | H8: =Assumptions!H271 -> 3753.4844 | I8: =Assumptions!I271 -> 5260.5864 | J8: =Assumptions!J271 -> 6773.5532 | K8: =Assumptions!K271 -> 9699.3261 | L8: =Assumptions!L271 -> 11416.048 | M8: =Assumptions!M271 -> 12386.969 | N8: =Assumptions!N271 -> 12313.335 | ... AF8: =Assumptions!AF271 -> 130249.86
B9: 5a | C9: (Dep) | D9: -407 | E9: -626 | F9: -642 | G9: =$D$54*Pessimistic!F41 -> -641.44 | H9: =$D$54*Pessimistic!G41 -> -740.32571 | I9: =$D$54*Pessimistic!H41 -> -853.63158 | J9: =$D$54*Pessimistic!I41 -> -983.76317 | K9: =$E$54*Pessimistic!J41 -> -1062.9971 | L9: =$E$54*Pessimistic!K41 -> -1282.5363 | M9: =$E$54*Pessimistic!L41 -> -1540.1221 | N9: =$E$54*Pessimistic!M41 -> -1834.8721 | O9: =$E$54*Pessimistic!N41 -> -2173.3095 | P9: =$F$54*Pessimistic!O41 -> -2563.1876 | Q9: =$F$54*Pessimistic!P41 -> -2912.2794 | R9: =$F$54*Pessimistic!Q41 -> -3320.5219 | S9: =$F$54*Pessimistic!R41 -> -3782.5873 | T9: =$F$54*Pessimistic!S41 -> -4305.8076 | U9: =$F$54*Pessimistic!T41 -> -4898.5407 | V9: =$F$54*Pessimistic!U41 -> -5559.9202 | W9: =$F$54*Pessimistic!V41 -> -6298.2169 | ... AF9: =$F$54*Pessimistic!AE41 -> -18283.842 | AG9: =SUM(D9:AF9) -> -154365.33
B10: 5b | C10: (Amort) | D10: 0 | E10: -3548 | F10: -2811 | G10: =F39*$D$55 -> -3603.86 | H10: =G39*$D$55 -> -3603.86 | I10: =H39*$D$55 -> -3603.86 | J10: =I39*$D$55 -> -4504.825 | K10: =J39*$F$55 -> -5197.875 | L10: =K39*$F$55 -> -6497.3438 | M10: =L39*$F$55 -> -8121.6797 | N10: =M39*$F$55 -> -10152.1 | O10: =N39*$F$55 -> -12690.125 | P10: =O39*$F$55 -> -15862.656 | Q10: =P39*$F$55 -> -19828.32 | R10: =Q39*$F$55 -> -24785.399 | ... AF10: =AE39*$F$55 -> -175374.19
B11: 5c | C11: (Stock based compensation) | D11: -379 | E11: -1081 | F11: -1384 | G11: =G6*$D$56 -> -1310.4835 | H11: =H6*$D$56 -> -1501.5868 | I11: =I6*$D$56 -> -1724.5697 | J11: =J6*$D$56 -> -1989.2062 | K11: =K6*$E$56 -> -2927.1902 | L11: =L6*$E$56 -> -3434.4766 | M11: =M6*$E$56 -> -3930.0008 | N11: =N6*$E$56 -> -4512.4988 | O11: =O6*$E$56 -> -5198.3743 | P11: =P6*$E$56 -> -6071.1618 | Q11: =Q6*$E$56 -> -7099.8693 | R11: =R6*$F$56 -> -5357.2796 | S11: =S6*$F$56 -> -6066.3227 | T11: =T6*$F$56 -> -6872.2674 | U11: =U6*$F$56 -> -7668.1689 | V11: =V6*$F$56 -> -8559.9619 | W11: =W6*$F$56 -> -9559.6805 | X11: =X6*$F$56 -> -10656.58 | Y11: =Y6*$F$56 -> -11886.014 | ... AF11: =AF6*$F$56 -> -25300.186
B12: 6 | C12: EBITDA | D12: =D8-D9-D10 -> 4044 | E12: =E8-E9-E10 -> 5419 | F12: =F8-F9-F10 -> 3846 | G12: =G8-G9-G10 -> 6678.2661 | H12: =H8-H9-H10 -> 8097.6701 | I12: =I8-I9-I10 -> 9718.0779 | J12: =J8-J9-J10 -> 12262.141 | K12: =K8-K9-K10 -> 15960.198 | ... AF12: =AF8-AF9-AF10 -> 323907.9
B13: 7 | C13: (Net financing cost) | D13: 30 | E13: -85 | F13: 99 | G13: =F44*$D$59+F45*$D$58 -> 117.078 | H13: =G44*$D$59+G45*$D$58 -> 275.20155 | I13: =H44*$D$59+H45*$D$58 -> 650.09955 | J13: =I44*$D$59+I45*$D$58 -> 916.45573 | K13: =J44*$D$59+J45*$D$58 -> 1208.5665 | L13: =K44*$D$59+K45*$D$58 -> 1554.191 | M13: =L44*$D$59+L45*$D$58 -> 447.04498 | N13: =M44*$D$59+M45*$D$58 -> 568.94465 | ... AF13: =AE44*$D$59+AE45*$D$58 -> 3263.1519
B14: 8 | C14: Other income/(cost) | D14: 4 | E14: 19 | F14: 8 | G14: =AVERAGE(D14:F14)*(1+G5) -> 11.941502 | H14: =AVERAGE(E14:G14)*(1+H5) -> 14.873403 | I14: =AVERAGE(F14:H14)*(1+I5) -> 13.328285 | J14: =AVERAGE(G14:I14)*(1+J5) -> 15.434396 | K14: =AVERAGE(H14:J14)*(1+K5) -> 17.836696 | L14: =AVERAGE(I14:K14)*(1+L5) -> 18.225039 | M14: =AVERAGE(J14:L14)*(1+M5) -> 19.641988 | N14: =AVERAGE(K14:M14)*(1+N5) -> 21.320011 | ... AF14: =AVERAGE(AC14:AE14)*(1+AF5) -> 57.147347
B15: 9 | C15: Earnings before taxes | D15: =D8+D13+D14 -> 3671 | E15: =E8+E13+E14 -> 1179 | F15: =F8+F13+F14 -> 500 | G15: =G8+G13+G14 -> 2561.9856 | H15: =H8+H13+H14 -> 4043.5594 | I15: =I8+I13+I14 -> 5924.0142 | J15: =J8+J13+J14 -> 7705.4434 | K15: =K8+K13+K14 -> 10925.729 | ... AF15: =AF8+AF13+AF14 -> 133570.16
B16: 10 | C16: (Income tax) | D16: -513 | E16: 122 | F16: 346 | G16: =$D$57*-G15 -> 128.09928 | H16: =$D$57*-H15 -> 202.17797 | I16: =$D$57*-I15 -> 296.20071 | J16: =$D$57*-J15 -> 385.27217 | K16: =K15*-$E$57 -> -218.51458 | L16: =L15*-$E$57 -> -259.76928 | M16: =M15*-$E$57 -> -257.07313 | N16: =N15*-$E$57 -> -258.072 | O16: =O15*-$E$57 -> -287.52929 | P16: =P15*-$E$57 -> -398.68161 | Q16: =Q15*-$E$57 -> -553.00622 | R16: =$F$57*-R15 -> -5034.7564 | S16: =$F$57*-S15 -> -5734.0818 | T16: =$F$57*-T15 -> -6539.2968 | U16: =$F$57*-U15 -> -7344.0082 | V16: =$F$57*-V15 -> -8246.5457 | W16: =$F$57*-W15 -> -9264.8489 | X16: =$F$57*-X15 -> -9630.3916 | Y16: =$F$57*-Y15 -> -10796.487 | ... AF16: =$F$57*-AF15 -> -21371.226
B17: 11 | C17: Net income | D17: =D15+D16+D14 -> 3162 | E17: =E15+E16+E14 -> 1320 | F17: =F15+F16+F14 -> 854 | G17: =G16+G15 -> 2690.0848 | H17: =H16+H15 -> 4245.7373 | I17: =I16+I15 -> 6220.2149 | J17: =J16+J15 -> 8090.7155 | K17: =K16+K15 -> 10707.215 | L17: =L16+L15 -> 12728.695 | M17: =M16+M15 -> 12596.583 | N17: =N16+N15 -> 12645.528 | ... AF17: =AF16+AF15 -> 112198.93
A19: CASH FLOW STATEMENT | B19: 12 | C19: Operating cash flows before WK | D19: 4674 | E19: 6492 | F19: 6100 | G19: =G17-G10-G9-G11 -> 8245.8683 | H19: =H17-H10-H9-H11 -> 10091.51 | I19: =I17-I10-I9-I11 -> 12402.276 | J19: =J17-J10-J9-J11 -> 15568.51 | K19: =K17-K10-K9-K11 -> 19895.277 | L19: =L17-L10-L9-L11 -> 23943.052 | M19: =M17-M10-M9-M11 -> 26188.386 | N19: =N17-N10-N9-N11 -> 29144.999 | ... AF19: =AF17-AF10-AF9-AF11 -> 331157.16
B20: 13 | C20: (Stock-based compensation) | D20: -379 | E20: -1081 | F20: -1384 | G20: =G11 -> -1310.4835 | H20: =H11 -> -1501.5868 | I20: =I11 -> -1724.5697 | J20: =J11 -> -1989.2062 | K20: =K11 -> -2927.1902 | L20: =L11 -> -3434.4766 | M20: =M11 -> -3930.0008 | N20: =N11 -> -4512.4988 | ... AF20: =AF11 -> -25300.186
B21: 14 | C21: (Working Capital Flows) | D21: -774 | E21: -1846 | F21: -3049 | G21: =G6*$D$61 -> -2620.967 | H21: =H6*$D$61 -> -3003.1737 | I21: =I6*$D$61 -> -3449.1395 | J21: =J6*$D$61 -> -3978.4123 | K21: =K6*$E$61 -> -3415.0552 | L21: =L6*$E$61 -> -4006.8893 | M21: =M6*$E$61 -> -4585.0009 | N21: =N6*$E$61 -> -5264.5819 | O21: =O6*$E$61 -> -6064.77 | P21: =P6*$E$61 -> -7083.0221 | Q21: =Q6*$E$61 -> -8283.1809 | R21: =R6*$F$61 -> -8035.9194 | S21: =S6*$F$61 -> -9099.4841 | T21: =T6*$F$61 -> -10308.401 | U21: =U6*$F$61 -> -11502.253 | V21: =V6*$F$61 -> -12839.943 | W21: =W6*$F$61 -> -14339.521 | X21: =X6*$F$61 -> -15984.87 | Y21: =Y6*$F$61 -> -17829.02 | ... AF21: =AF6*$F$61 -> -37950.28
B22: 15 | C22: -Total Operating Cash Flow | D22: =D19+D20+D21 -> 3521 | E22: =E19+E20+E21 -> 3565 | F22: =F19+F20+F21 -> 1667 | G22: =G19+G20+G21 -> 4314.4178 | H22: =H19+H20+H21 -> 5586.7494 | I22: =I19+I20+I21 -> 7228.567 | J22: =J19+J20+J21 -> 9600.8914 | K22: =K19+K20+K21 -> 13553.031 | ... AF22: =AF19+AF20+AF21 -> 267906.69
B23: 16 | C23: (CAPEX) | D23: -301 | E23: -450 | F23: -546 | G23: =G6*$D$63 -> -618.03568 | H23: =H6*$D$63 -> -708.16172 | I23: =I6*$D$63 -> -813.32243 | J23: =J6*$D$63 -> -938.12732 | K23: =K6*$E$63 -> -1463.5951 | L23: =L6*$E$63 -> -1717.2383 | M23: =M6*$E$63 -> -1965.0004 | N23: =N6*$E$63 -> -2256.2494 | O23: =O6*$E$63 -> -2599.1872 | P23: =P6*$F$63 -> -2327.2787 | Q23: =Q6*$F$63 -> -2721.6166 | R23: =R6*$F$63 -> -3080.4358 | S23: =S6*$F$63 -> -3488.1356 | T23: =T6*$F$63 -> -3951.5537 | U23: =U6*$F$63 -> -4409.1971 | V23: =V6*$F$63 -> -4921.9781 | W23: =W6*$F$63 -> -5496.8163 | ... AF23: =AF6*$F$63 -> -14547.607 | AG23: =SUM(D23:AF23) -> -133727.89
B24: 17 | C24: Acquistions | D24: -378 | E24: 2465 | F24: -866 | G24: =G6*$D$64 -> -131.04835 | H24: =H6*$D$64 -> -150.15868 | I24: =I6*$D$64 -> -172.45697 | J24: =J6*$D$64 -> -198.92062 | K24: =K6*$E$64 -> -243.93252 | L24: =L6*$E$64 -> -286.20638 | M24: =M6*$E$64 -> -327.50007 | N24: =N6*$F$64 -> -2256.2494 | O24: =O6*$F$64 -> -2599.1872 | P24: =P6*$F$64 -> -3035.5809 | Q24: =Q6*$F$64 -> -3549.9347 | R24: =R6*$F$64 -> -4017.9597 | S24: =S6*$F$64 -> -4549.742 | T24: =T6*$F$64 -> -5154.2005 | U24: =U6*$F$64 -> -5751.1267 | ... AF24: =AF6*$F$64 -> -18975.14 | AH24: =AG9-AG23 -> -20637.446
C25: Investments | D25: -7 | E25: -16 | F25: -11
B26: 18 | C26: (Other investing flows) | D26: -7 | E26: -16 | F26: -11 | H26: =(1+H5)*AVERAGE(E26:G26) -> -15.468659 | I26: =(1+I5)*AVERAGE(F26:H26) -> -15.199603 | J26: =(1+J5)*AVERAGE(G26:I26) -> -17.687164 | K26: =(1+K5)*AVERAGE(H26:J26) -> -19.765776 | L26: =(1+L5)*AVERAGE(I26:K26) -> -20.592435 | M26: =(1+M5)*AVERAGE(J26:L26) -> -22.140043 | N26: =(1+N5)*AVERAGE(K26:M26) -> -23.920546 | O26: =(1+O5)*AVERAGE(L26:N26) -> -25.594642 | ... AF26: =(1+AF5)*AVERAGE(AC26:AE26) -> -64.28634
B27: 19 | C27: -Total Investing Flows | D27: =SUM(D23:D26) -> -693 | E27: =SUM(E23:E26) -> 1983 | F27: =SUM(F23:F26) -> -1434 | G27: =G23+G24+G26 -> -749.08403 | H27: =H23+H24+H26 -> -873.78906 | I27: =I23+I24+I26 -> -1000.979 | J27: =J23+J24+J26 -> -1154.7351 | K27: =K23+K24+K26 -> -1727.2934 | L27: =L23+L24+L26 -> -2024.0371 | M27: =M23+M24+M26 -> -2314.6405 | N27: =N23+N24+N26 -> -4536.4193 | ... AF27: =AF23+AF24+AF26 -> -33587.033
B28: 20 | C28: (Flows related to leases) | D28: 0 | E28: 0 | F28: 0 | G28: 0 | H28: 0 | I28: 0 | J28: 0 | K28: 0 | L28: 0 | M28: 0 | N28: 0 | O28: 0 | P28: 0 | Q28: 0 | R28: 0 | S28: 0 | T28: 0 | U28: 0 | V28: 0 | W28: 0 | X28: 0 | Y28: 0 | Z28: 0 | AA28: 0 | AB28: 0 | AC28: 0 | AD28: 0 | AE28: 0 | AF28: 0
B29: 21 | C29: Net Flows related to debt | E29: 679 | G29: =G45-F45 -> 0 | H29: =H45-G45 -> 511.74328 | I29: =I45-H45 -> 609.26494 | J29: =J45-I45 -> 951.29889 | K29: =K45-J45 -> 1134.2356 | L29: =L45-K45 -> 1407.6956 | M29: =M45-L45 -> -447.53842 | N29: =N45-M45 -> 1475.0058 | ... AF29: =AF45-AE45 -> 15276.928
B30: 22 | C30: (Repurchases)/Issuance of stock | D30: -1762 | E30: -3702 | F30: -985 | G30: =IF(F44+G35>(G6-G8)*0.3,-G35-F44+(G6-G8)*0.3,G6*-0.1) -> -132.23541 | H30: =IF(G44+H35>(H6-H8)*0.3,-H35-G44+(H6-H8)*0.3,H6*-0.1) -> -4241.9849 | I30: =IF(H44+I35>(I6-I8)*0.3,-I35-H44+(I6-I8)*0.3,I6*-0.1) -> -12966.797 | J30: =IF(I44+J35>(J6-J8)*0.3,-J35-I44+(J6-J8)*0.3,J6*-0.1) -> -20212.326 | K30: =IF(J44+K35>(K6-K8)*0.3,-K35-J44+(K6-K8)*0.3,K6*-0.1) -> -28517.054 | L30: =IF(K44+L35>(L6-L8)*0.3,-L35-K44+(L6-L8)*0.3,L6*-0.1) -> -37227.111 | M30: =IF(L44+M35>(M6-M8)*0.3,-M35-L44+(M6-M8)*0.3,M6*-0.1) -> -12398.573 | N30: =IF(M44+N35>(N6-N8)*0.3,-N35-M44+(N6-N8)*0.3,N6*-0.1) -> -13017.9 | ... AF30: =IF(AE44+AF35>(AF6-AF8)*0.3,-AF35-AE44+(AF6-AF8)*0.3,AF6*-0.1) -> -235398.43
B31: 23 | C31: (Dividends) | D31: 0 | E31: 0 | F31: 0 | G31: =-$D$65*G17 -> 0 | H31: =-$D$65*H17 -> 0 | I31: =-$D$65*I17 -> 0 | J31: =-$D$65*J17 -> 0 | K31: =-$F$65*K17 -> 0 | L31: =-$F$65*L17 -> 0 | M31: =-$F$65*M17 -> 0 | N31: =-$F$65*N17 -> 0 | O31: =-$F$65*O17 -> 0 | P31: =-$F$65*P17 -> 0 | Q31: =-$F$65*Q17 -> 0 | R31: =-$F$65*R17 -> 0 | ... AF31: =-$F$65*AF17 -> 0
B32: 24 | C32: Other financing flows | D32: -133 | E32: -241 | F32: -161 | G32: =(1+G5)*AVERAGE(D32:F32) -> -206.08721 | H32: =(1+H5)*AVERAGE(E32:G32) -> -232.25416 | I32: =(1+I5)*AVERAGE(F32:H32) -> -229.44749 | J32: =(1+J5)*AVERAGE(G32:I32) -> -256.75384 | K32: =(1+K5)*AVERAGE(H32:J32) -> -293.67604 | L32: =(1+L5)*AVERAGE(I32:K32) -> -305.01042 | M32: =(1+M5)*AVERAGE(J32:L32) -> -326.28757 | N32: =(1+N5)*AVERAGE(K32:M32) -> -354.02403 | ... AF32: =(1+AF5)*AVERAGE(AC32:AE32) -> -950.23697
B33: 25 | C33: -Total Financing flows | D33: =D28+D29+D30+D31+D32 -> -1895 | E33: =E28+E29+E30+E31+E32 -> -3264 | F33: =F28+F29+F30+F31+F32 -> -1146 | G33: =G28+G29+G30+G31+G32 -> -338.32262 | H33: =H28+H29+H30+H31+H32 -> -3962.4957 | I33: =I28+I29+I30+I31+I32 -> -12586.98 | J33: =J28+J29+J30+J31+J32 -> -19517.781 | K33: =K28+K29+K30+K31+K32 -> -27676.495 | ... AF33: =AF28+AF29+AF30+AF31+AF32 -> -221071.74
A35: SUMMARY | B35: 26 | C35: Cash before shareholder returns | D35: =D22+D27+D28+D29+D32 -> 2695 | E35: =E22+E27+E28+E29+E32 -> 5986 | F35: =F22+F27+F28+F29+F32 -> 72 | G35: =G22+G27+G28+G29+G32 -> 3359.2466 | H35: =H22+H27+H28+H29+H32 -> 4992.4494 | I35: =I22+I27+I28+I29+I32 -> 6607.4054 | J35: =J22+J27+J28+J29+J32 -> 9140.7014 | K35: =K22+K27+K28+K29+K32 -> 12666.298 | ... AF35: =AF22+AF27+AF28+AF29+AF32 -> 248646.35
B36: 27 | C36: Returns to shareholders | D36: 1762 | E36: 3702 | F36: 985 | G36: =-1*(G30+G31) -> 132.23541 | H36: =IF(H35<0.2*(H6-H8),H6*-0.1,H35-0.2*(H6-H8)) -> -3003.1737 | I36: =IF(I35<0.2*(I6-I8),I6*-0.1,I35-0.2*(I6-I8)) -> 761.24376 | J36: =IF(J35<0.2*(J6-J8),J6*-0.1,J35-0.2*(J6-J8)) -> 2538.5874 | K36: =IF(K35<0.2*(K6-K8),K6*-0.1,K35-0.2*(K6-K8)) -> 4848.8623 | L36: =-1*(L30+L31) -> 37227.111 | M36: =-1*(M30+M31) -> 12398.573 | N36: =-1*(N30+N31) -> 13017.9 | O36: =-1*(O30+O31) -> 16112.665 | P36: =-1*(P30+P31) -> 24595.704 | Q36: =-1*(Q30+Q31) -> 34626.591 | R36: =-1*(R30+R31) -> 38636.395 | S36: =-1*(S30+S31) -> 43324.477 | ... AF36: =-1*(AF30+AF31) -> 235398.43
B37: 28 | C37: Excess cash acumulation | D37: =D35-D36 -> 933 | E37: =E35-E36 -> 2284 | F37: =F35-F36 -> -913 | G37: =G35-G36 -> 3227.0112 | H37: =H35-H36 -> 7995.6231 | I37: =I35-I36 -> 5846.1617 | J37: =J35-J36 -> 6602.114 | K37: =K35-K36 -> 7817.4354 | ... AF37: =AF35-AF36 -> 13247.918
A39: BALANCE SHEET | B39: 29 | C39: Intangible assets | D39: 328 | E39: 28028 | F39: 27722 | G39: =Assumptions!C329 -> 27722 | H39: =Assumptions!D329 -> 27722 | I39: =Assumptions!E329 -> 34652.5 | J39: =Assumptions!F329 -> 43315.625 | K39: =Assumptions!G329 -> 54144.531 | L39: =Assumptions!H329 -> 67680.664 | M39: =Assumptions!I329 -> 84600.83 | N39: =Assumptions!J329 -> 105751.04 | ... AF39: =Assumptions!AB329 -> 1680669.4 | AG39: =SUM(G39:AF39) -> 12251179
B40: 30 | C40: Accumulated amortization | D40: 0 | E40: -3548 | F40: -6359 | G40: =F40-G10 -> -2755.14 | H40: =G40-H10 -> 848.72 | I40: =H40-I10 -> 4452.58 | J40: =I40-J10 -> 8957.405 | K40: =J40-K10 -> 14155.28 | L40: =K40-L10 -> 20652.624 | M40: =L40-M10 -> 28774.303 | N40: =M40-N10 -> 38926.403 | ... AF40: =AE40-AF10 -> 1266607 | AG40: =SUM(G40:AF40) -> 8192784.1
B41: 31 | C41: PPE+Right of use Assets | D41: 2203 | E41: 3480 | F41: 4009 | G41: =F41+(-G23) -> 4627.0357 | H41: =G41+(-H23) -> 5335.1974 | I41: =H41+(-I23) -> 6148.5198 | J41: =I41+(-J23) -> 7086.6471 | K41: =J41+(-K23) -> 8550.2422 | L41: =K41+(-L23) -> 10267.481 | M41: =L41+(-M23) -> 12232.481 | N41: =M41+(-N23) -> 14488.73 | ... AF41: =AE41+(-AF23) -> 136439.89 | AG41: =SUM(G41:AF41) -> 1149025.1
B42: 32 | C42: Accumulated depreciation | D42: -1 134 | E42: -1 507 | F42: -1787 | G42: =F42-G9 -> -1145.56 | H42: =G42-H9 -> -405.23429 | I42: =H42-I9 -> 448.39729 | J42: =I42-J9 -> 1432.1605 | K42: =J42-K9 -> 2495.1575 | L42: =K42-L9 -> 3777.6939 | M42: =L42-M9 -> 5317.816 | N42: =M42-N9 -> 7152.6881 | ... AF42: =AE42-AF9 -> 150903.33 | AG42: =SUM(G42:AF42) -> 1075463.6
A44: CASH & DEBT & DISCOUNTING | B44: 33 | C44: Ending cash balance | D44: ='Fin. Data'!D39 -> 2535 | E44: =E37+D44 -> 4819 | F44: =F37+E44 -> 3906 | G44: =G37+F44 -> 7133.0112 | H44: =H37+G44 -> 15128.634 | I44: =I37+H44 -> 20974.796 | J44: =J37+I44 -> 27576.91 | K44: =K37+J44 -> 35394.345 | L44: =L37+K44 -> 13747.568 | ... AF44: =AF37+AE44 -> 150676.44
B45: 34 | C45: Total Debt | D45: ='Fin. Data'!D58 -> 349 | E45: ='Fin. Data'!C58 -> 2863 | F45: ='Fin. Data'!B58 -> 2252 | G45: =F45 -> 2252 | H45: =(G39+G44+G41)*0.07 -> 2763.7433 | I45: =(H39+H44+H41)*0.07 -> 3373.0082 | J45: =(I39+I44+I41)*0.07 -> 4324.3071 | K45: =(J39+J44+J41)*0.07 -> 5458.5427 | L45: =(K39+K44+K41)*0.07 -> 6866.2383 | M45: =(L39+L44+L41)*0.07 -> 6418.6999 | N45: =(M39+M44+M41)*0.07 -> 7893.7057 | O45: =(N39+N44+N41)*0.07 -> 9737.5783 | ... AF45: =(AE39+AE44+AE41)*0.07 -> 120454.07
B46: 35 | C46: Discount factor | F46: =1/((1+$F$51)^G51) -> 1 | G46: =1/((1+$F$51)^G50) -> 0.87749259 | H46: =1/((1+$F$51)^H50) -> 0.76999325 | I46: =1/((1+$F$51)^I50) -> 0.67566337 | J46: =1/((1+$F$51)^J50) -> 0.5928896 | K46: =1/((1+$F$51)^K50) -> 0.52025623 | L46: =1/((1+$F$51)^L50) -> 0.45652099 | M46: =1/((1+$F$51)^M50) -> 0.40059378 | N46: =1/((1+$F$51)^N50) -> 0.35151808 | ... AE46: =1/((1+$F$51)^AE50) -> 0.038114169 | AF46: =1/((1+$F$51)^25) -> 0.038114169
B47: 36 | C47: DF + 0.1% | E47: +0.1% | F47: =1/((1+$F$51+0.001)^G51) -> 1 | G47: =1/((1+$F$51+0.001)^G50) -> 0.87672327 | H47: =1/((1+$F$51+0.001)^H50) -> 0.7686437 | I47: =1/((1+$F$51+0.001)^I50) -> 0.67388782 | J47: =1/((1+$F$51+0.001)^J50) -> 0.59081313 | K47: =1/((1+$F$51+0.001)^K50) -> 0.51797962 | L47: =1/((1+$F$51+0.001)^L50) -> 0.45412479 | M47: =1/((1+$F$51+0.001)^M50) -> 0.39814177 | N47: =1/((1+$F$51+0.001)^N50) -> 0.34906016 | ... AE47: =1/((1+$F$51+0.001)^AE50) -> 0.037287509 | AF47: =1/((1+$F$51)^25) -> 0.038114169
B48: 37 | C48: DF+0.5% | E48: +0.5% | F48: =1/((1+$F$51+0.005)^G51) -> 1 | G48: =1/((1+$F$51+0.005)^G50) -> 0.87365944 | H48: =1/((1+$F$51+0.005)^H50) -> 0.76328082 | I48: =1/((1+$F$51+0.005)^I50) -> 0.6668475 | J48: =1/((1+$F$51+0.005)^J50) -> 0.58259761 | K48: =1/((1+$F$51+0.005)^K50) -> 0.5089919 | L48: =1/((1+$F$51+0.005)^L50) -> 0.44468558 | M48: =1/((1+$F$51+0.005)^M50) -> 0.38850376 | N48: =1/((1+$F$51+0.005)^N50) -> 0.33941998 | ... AE48: =1/((1+$F$51+0.005)^AE50) -> 0.034162872 | AF48: =1/((1+$F$51)^25) -> 0.038114169
A50: Discount Rate | C50: Risk free rate | D50: Equity premium | E50: Firm premium | F50: Total | G50: 1 | H50: 2 | I50: 3 | J50: 4 | K50: 5 | L50: 6 | M50: 7 | N50: 8 | O50: 9 | P50: 10 | Q50: 11 | R50: 12 | S50: 13 | T50: 14 | U50: 15 | V50: 16 | W50: 17 | X50: 18 | Y50: 19 | Z50: 20 | AA50: 21 | AB50: 22 | AC50: 23 | AD50: 24 | AE50: 25
F51: =Assumptions!C587 -> 0.13961076 | G51: 0 | I51: Implied DEBT/EBITDA | K51: =K45/K12 -> 0.34200971 | L51: =L45/L12 -> 0.35769244 | M51: =M45/M12 -> 0.29111372 | N51: =N45/N12 -> 0.32483975 | O51: =O45/O12 -> 0.34103393 | P51: =P45/P12 -> 0.31878683 | Q51: =Q45/Q12 -> 0.29560218 | R51: =R45/R12 -> 0.30553236 | ... AF51: =AF45/AF12 -> 0.37187753
A53: Modelling factors | D53: Short Term | E53: Medium Term | F53: Long Term | G53: Reference (line) | I53: Cash/Operational Costs | K53: =K44/(K6-K8) -> 0.90552319 | L53: =Assumptions!$G$600 -> 0.20494459 | M53: =Assumptions!$G$600 -> 0.20494459 | N53: =Assumptions!$G$600 -> 0.20494459 | O53: =Assumptions!$G$600 -> 0.20494459 | P53: =Assumptions!$G$600 -> 0.20494459 | Q53: =Assumptions!$G$600 -> 0.20494459 | R53: =Assumptions!$G$600 -> 0.20494459 | S53: =Assumptions!$G$600 -> 0.20494459 | ... AF53: =Assumptions!$G$600 -> 0.20494459
C54: Depreciation factor | D54: =Assumptions!K302 -> -0.16 | E54: =Assumptions!L302 -> -0.15 | F54: =Assumptions!M302 -> -0.15 | G54: % Gross PPE
C55: Amortization factor | D55: =Assumptions!L316 -> -0.13 | E55: =Assumptions!$M$316 -> -0.12 | F55: =Assumptions!$M$316 -> -0.12 | G55: % Gross Intangibles | I55: Cash/Sales | K55: =K44/K6 -> 0.72549461 | L55: =L44/L6 -> 0.2401688 | M55: =M44/M6 -> 0.2432658 | N55: =N44/N6 -> 0.25088308 | O55: =O44/O6 -> 0.25259785 | P55: =P44/P6 -> 0.24319889 | Q55: =Q44/Q6 -> 0.232022 | R55: =R44/R6 -> 0.23150872 | ... AF55: =AF44/AF6 -> 0.23822187
C56: Stock-based comp | D56: =Assumptions!C525 -> -0.05 | E56: =Assumptions!D525 -> -0.06 | F56: =Assumptions!E525 -> -0.04 | G56: % of Revenue
C57: Tax Rate | D57: =Assumptions!C365 -> -0.05 | E57: =Assumptions!D365 -> 0.02 | F57: =Assumptions!E365 -> 0.16 | G57: % EBT
C58: Interest Rate on debt | D58: =Assumptions!$F$401 -> -0.033 | E58: =Assumptions!$F$401 -> -0.033 | F58: =Assumptions!$F$401 -> -0.033 | G58: % Debt | I58: Important Note: medium-term might differ for each factor given it's specific projections. I recommend checking each one individually. | AF58: =AF44/AF6 -> 0.23822187
C59: Interest Rate on cash | D59: =Assumptions!C418 -> 0.049 | E59: =Assumptions!$D$418 -> 0.04 | F59: =Assumptions!$D$418 -> 0.04 | G59: % Cash
C60: PPE+ROA | D60: =Assumptions!S23 -> 0 | E60: =Assumptions!S23 -> 0 | F60: =Assumptions!T23 -> 0 | G60: Growing with CapEx
C61: Working capital flows | D61: =Assumptions!C509 -> -0.1 | E61: =Assumptions!D509 -> -0.07 | F61: =Assumptions!E509 -> -0.06 | G61: % of Revenue
C62: Intangible Assets | D62: =Assumptions!S25 -> 0 | E62: =Assumptions!S25 -> 0 | F62: =Assumptions!T25 -> 0 | G62: Costum growth (acq.) | O62: Sensitivity analysis
C63: Capex | D63: =Assumptions!$G$338 -> -0.023580445 | E63: =Assumptions!C340 -> -0.03 | F63: =Assumptions!I338 -> -0.023 | G63: % Revenue | O63: Tax
C64: Acquisition factor | D64: =Assumptions!$C$446 -> -0.005 | E64: =Assumptions!$C$446 -> -0.005 | F64: =Assumptions!B455 -> -0.03 | G64: % of Revenue | O64: =D76 -> 157.65974 | P64: 0.12 | Q64: =P64+1% -> 0.13 | R64: =Q64+1% -> 0.14 | S64: =R64+1% -> 0.15 | T64: =S64+1% -> 0.16 | U64: =T64+1% -> 0.17 | V64: =U64+1% -> 0.18 | W64: =V64+1% -> 0.19 | X64: =W64+1% -> 0.2
C65: Dividends | D65: =Assumptions!S29 -> 0 | E65: =Assumptions!S29 -> 0 | F65: =Assumptions!T29 -> 0 | G65: % of Revenue | N65: Discount Rate | O65: 0.16961076 | P65: 236.15625 | Q65: 190.39631 | R65: 155.69343 | S65: 128.9066 | T65: 107.91262 | U65: 91.237115 | V65: 77.832959 | W65: 66.941939 | X65: 58.005815
C66: Repurchases | D66: -- | E66: -- | F66: -- | G66: Custom formula | O66: 0.15961076 | P66: 237.4148 | Q66: 191.39696 | R66: 156.49845 | S66: 129.5608 | T66: 108.44893 | U66: 91.680204 | V66: 78.201568 | W66: 67.250502 | X66: 58.265576
C67: Leases | D67: 0 | E67: 0 | F67: 0 | G67: See A544 in Assumpt. | O67: 0.14961076 | P67: 238.67334 | Q67: 192.39762 | R67: 157.30347 | S67: 130.21499 | T67: 108.98524 | U67: 92.123293 | V67: 78.570177 | W67: 67.559065 | X67: 58.525337
C68: Total Debt | D68: -- | E68: -- | F68: -- | G68: Custom ratio | H68: =Assumptions!L403 -> 0.070270919 | O68: 0.13961076 | P68: 239.93189 | Q68: 193.39827 | R68: 158.10849 | S68: 130.86918 | T68: 109.52155 | U68: 92.566382 | V68: 78.938787 | W68: 67.867628 | X68: 58.785098
O69: 0.12961076 | P69: 241.19044 | Q69: 194.39892 | R69: 158.9135 | S69: 131.52337 | T69: 110.05786 | U69: 93.009471 | V69: 79.307396 | W69: 68.176191 | X69: 59.044859
A70: Valuation | D70: $ millions | F70: 2023 EV | G70: ='Multiples valuation'!$J$9 -> 276200.63 | O70: 0.11961076 | P70: 242.44898 | Q70: 195.39958 | R70: 159.71852 | S70: 132.17757 | T70: 110.59417 | U70: 93.45256 | V70: 79.676005 | W70: 68.484754 | X70: 59.30462
C71: Value of flows | D71: =SUMPRODUCT(G36:AF36,G46:AF46)+((AF44-AF45)*AF46) -> 170292.94 | E71: =D71/D73 -> 0.66827418 | O71: 0.10961076 | P71: 243.70753 | Q71: 196.40023 | R71: 160.52354 | S71: 132.83176 | T71: 111.13048 | U71: 93.895649 | V71: 80.044615 | W71: 68.793317 | X71: 59.564381
C72: Value of perpetuity | D72: =(AF35/(F51-AF5))*AF46 -> 84532.017 | E72: =D72/D73 -> 0.33172582 | F72: EV/FCF Ratio projection | G72: 2023 | H72: 2024 | I72: 2025 | J72: 2026
C73: Total Value | D73: =D71+D72 -> 254824.96 | F73: Implied EV/FCF | G73: =$G$70/(F22+F23) -> 246.38772 | H73: =$G$70/(G22+G23) -> 74.721882 | I73: =$G$70/(H22+H23) -> 56.614875 | J73: =$G$70/(I22+I23) -> 43.053796
C74: Actual share price | D74: =OP!C20 -> 78.21 | F74: Implied EV/FCF/Growth | H74: =H73/((G22+G23)/(F22+F23)-1) -> 32.524583 | I74: =I73/((H22+H23)/(G22+G23)-1) -> 177.01678 | J74: =J73/((I22+I23)/(H22+H23)-1) -> 136.68745
C75: Total value vs Mkt Cap | D75: =D76/D74-1 -> 1.0158514 | O75: Sensitivity analysis
C76: Estimated NPV per share | D76: =D73*1000000/OP!C21 -> 157.65974 | O76: Tax
O77: Implied Upside | P77: 0.12 | Q77: =P77+1% -> 0.13 | R77: =Q77+1% -> 0.14 | S77: =R77+1% -> 0.15 | T77: =S77+1% -> 0.16 | U77: =T77+1% -> 0.17 | V77: =U77+1% -> 0.18 | W77: =V77+1% -> 0.19 | X77: =W77+1% -> 0.2
A78: Sensibility | C78: Sensitivity +0.1% | D78: =(SUMPRODUCT(G36:AF36,G46:AF46)+((AF44-AF45)*AF46)+(AF35/(F51+0.001-AF5))*AF46)*1000000/OP!C21 -> 157.19736 | E78: =D78/D76-1 -> -0.002932752 | N78: Discount Rate | O78: 0.16961076 | P78: =P65/$D$74-1 -> 2.0195148 | Q78: =Q65/$D$74-1 -> 1.4344241 | R78: =R65/$D$74-1 -> 0.99070999 | S78: =S65/$D$74-1 -> 0.64821128 | T78: =T65/$D$74-1 -> 0.37978027 | U78: =U65/$D$74-1 -> 0.16656585 | V78: =V65/$D$74-1 -> -0.0048208819 | W78: =W65/$D$74-1 -> -0.14407443 | X78: =X65/$D$74-1 -> -0.2583325
C79: Sensitivity +0.5% | D79: =(SUMPRODUCT(G36:AF36,G46:AF46)+((AF44-AF45)*AF46)+(AF35/(F51+0.005-AF5))*AF46)*1000000/OP!C21 -> 155.42681 | E79: =D79/D76-1 -> -0.014162909 | O79: 0.15961076 | P79: =P66/$D$74-1 -> 2.0356067 | Q79: =Q66/$D$74-1 -> 1.4472186 | R79: =R66/$D$74-1 -> 1.001003 | S79: =S66/$D$74-1 -> 0.65657585 | T79: =T66/$D$74-1 -> 0.38663759 | U79: =U66/$D$74-1 -> 0.17223123 | V79: =V66/$D$74-1 -> -0.00010781073 | W79: =W66/$D$74-1 -> -0.14012912 | X79: =X66/$D$74-1 -> -0.25501117
O80: 0.14961076 | P80: =P67/$D$74-1 -> 2.0516985 | Q80: =Q67/$D$74-1 -> 1.460013 | R80: =R67/$D$74-1 -> 1.0112961 | S80: =S67/$D$74-1 -> 0.66494041 | T80: =T67/$D$74-1 -> 0.3934949 | U80: =U67/$D$74-1 -> 0.1778966 | V80: =V67/$D$74-1 -> 0.0046052604 | W80: =W67/$D$74-1 -> -0.1361838 | X80: =X67/$D$74-1 -> -0.25168985
A81: Notes | C81: Price where it'd be a "BUY" | D81: =D76/1.1 -> 143.32703 | O81: 0.13961076 | P81: =P68/$D$74-1 -> 2.0677904 | Q81: =Q68/$D$74-1 -> 1.4728074 | R81: =R68/$D$74-1 -> 1.0215891 | S81: =S68/$D$74-1 -> 0.67330497 | T81: =T68/$D$74-1 -> 0.40035222 | U81: =U68/$D$74-1 -> 0.18356198 | V81: =V68/$D$74-1 -> 0.0093183316 | W81: =W68/$D$74-1 -> -0.13223849 | X81: =X68/$D$74-1 -> -0.24836852
O82: 0.12961076 | P82: =P69/$D$74-1 -> 2.0838823 | Q82: =Q69/$D$74-1 -> 1.4856019 | R82: =R69/$D$74-1 -> 1.0318822 | S82: =S69/$D$74-1 -> 0.68166953 | T82: =T69/$D$74-1 -> 0.40720954 | U82: =U69/$D$74-1 -> 0.18922735 | V82: =V69/$D$74-1 -> 0.014031403 | W82: =W69/$D$74-1 -> -0.12829317 | X82: =X69/$D$74-1 -> -0.2450472
O83: 0.11961076 | P83: =P70/$D$74-1 -> 2.0999742 | Q83: =Q70/$D$74-1 -> 1.4983963 | R83: =R70/$D$74-1 -> 1.0421752 | S83: =S70/$D$74-1 -> 0.6900341 | T83: =T70/$D$74-1 -> 0.41406685 | U83: =U70/$D$74-1 -> 0.19489272 | V83: =V70/$D$74-1 -> 0.018744474 | W83: =W70/$D$74-1 -> -0.12434786 | X83: =X70/$D$74-1 -> -0.24172587
O84: 0.10961076 | P84: =P71/$D$74-1 -> 2.1160661 | Q84: =Q71/$D$74-1 -> 1.5111908 | R84: =R71/$D$74-1 -> 1.0524683 | S84: =S71/$D$74-1 -> 0.69839866 | T84: =T71/$D$74-1 -> 0.42092417 | U84: =U71/$D$74-1 -> 0.2005581 | V84: =V71/$D$74-1 -> 0.023457545 | W84: =W71/$D$74-1 -> -0.12040255 | X84: =X71/$D$74-1 -> -0.23840455

Sheet Optimistic
A1: VALUATION MODEL
G3: Short Term | K3: Long Term
A4: Section | B4: Line # | C4: ITEM | D4: 2021 (Real) | E4: 2022 (Real) | F4: 2023 (Real) | G4: 2024 | H4: =G4+1 -> 2025 | I4: =H4+1 -> 2026 | J4: =I4+1 -> 2027 | K4: =J4+1 -> 2028 | L4: =K4+1 -> 2029 | M4: =L4+1 -> 2030 | N4: =M4+1 -> 2031 | O4: =N4+1 -> 2032 | ... AF4: =AE4+1 -> 2049
A5: INCOME STATEMENT | B5: 1 | C5: Growth | D5: 0.68329407 | E5: 0.43610807 | F5: -0.03902377 | G5: =G6/F6-1 -> 0.25153748 | H5: =H6/G6-1 -> 0.30860145 | I5: =I6/H6-1 -> 0.45335835 | J5: =J6/I6-1 -> 0.470365 | K5: =K6/J6-1 -> 0.41509239 | L5: =L6/K6-1 -> 0.32067465 | M5: =M6/L6-1 -> 0.27732054 | N5: =N6/M6-1 -> 0.28609367 | ... AE5: =AE6/AD6-1 -> 0.10241861 | AF5: 0.025
B6: 2 | C6: Revenues/Sales | D6: 16434 | E6: 23601 | F6: 22680 | G6: =Assumptions!G127 -> 28384.87 | H6: =Assumptions!H127 -> 37144.482 | I6: =Assumptions!I127 -> 53984.243 | J6: =Assumptions!J127 -> 79376.541 | K6: =Assumptions!K127 -> 112325.14 | L6: =Assumptions!L127 -> 148344.96 | M6: =Assumptions!M127 -> 189484.07 | N6: =Assumptions!N127 -> 243694.26 | ... AF6: =Assumptions!AF127 -> 3299290.8
B7: 3 | C7: EBIT/Operating Margin | D7: =D8/D6 -> 0.22130948 | E7: =E8/E6 -> 0.052752002 | F7: =F8/F6 -> 0.017328042 | G7: =G8/G6 -> 0.12450274 | H7: =H8/H6 -> 0.15452689 | I7: =I8/I6 -> 0.20808891 | J7: =J8/J6 -> 0.2391877 | K7: =K8/K6 -> 0.28000053 | ... AF7: =AF8/AF6 -> 0.29370984
B8: 4 | C8: EBIT | D8: 3637 | E8: 1245 | F8: 393 | G8: =Assumptions!G131 -> 3533.9941 | H8: =Assumptions!H131 -> 5739.8212 | I8: =Assumptions!I131 -> 11233.522 | J8: =Assumptions!J131 -> 18985.892 | K8: =Assumptions!K131 -> 31451.098 | L8: =Assumptions!L131 -> 42011.079 | M8: =Assumptions!M131 -> 55545.713 | N8: =Assumptions!N131 -> 64917.825 | ... AF8: =Assumptions!AF131 -> 969034.16
B9: 5a | C9: (Dep) | D9: -407 | E9: -626 | F9: -642 | G9: =$D$54*Pessimistic!F41 -> -641.44 | H9: =$D$54*Pessimistic!G41 -> -740.32571 | I9: =$D$54*Pessimistic!H41 -> -853.63158 | J9: =$D$54*Pessimistic!I41 -> -983.76317 | K9: =$E$54*Pessimistic!J41 -> -1062.9971 | L9: =$E$54*Pessimistic!K41 -> -1282.5363 | M9: =$E$54*Pessimistic!L41 -> -1540.1221 | N9: =$E$54*Pessimistic!M41 -> -1834.8721 | O9: =$E$54*Pessimistic!N41 -> -2173.3095 | P9: =$F$54*Pessimistic!O41 -> -2563.1876 | Q9: =$F$54*Pessimistic!P41 -> -2912.2794 | R9: =$F$54*Pessimistic!Q41 -> -3320.5219 | S9: =$F$54*Pessimistic!R41 -> -3782.5873 | T9: =$F$54*Pessimistic!S41 -> -4305.8076 | U9: =$F$54*Pessimistic!T41 -> -4898.5407 | V9: =$F$54*Pessimistic!U41 -> -5559.9202 | W9: =$F$54*Pessimistic!V41 -> -6298.2169 | ... AF9: =$F$54*Pessimistic!AE41 -> -18283.842 | AG9: =SUM(D9:AF9) -> -154365.33
B10: 5b | C10: (Amort) | D10: 0 | E10: -3548 | F10: -2811 | G10: =F39*$D$55 -> -3603.86 | H10: =G39*$D$55 -> -3603.86 | I10: =H39*$D$55 -> -3603.86 | J10: =I39*$D$55 -> -4504.825 | K10: =J39*$F$55 -> -5197.875 | L10: =K39*$F$55 -> -6497.3438 | M10: =L39*$F$55 -> -8121.6797 | N10: =M39*$F$55 -> -10152.1 | O10: =N39*$F$55 -> -12690.125 | P10: =O39*$F$55 -> -15862.656 | Q10: =P39*$F$55 -> -19828.32 | R10: =Q39*$F$55 -> -24785.399 | ... AF10: =AE39*$F$55 -> -175374.19
B11: 5c | C11: (Stock based compensation) | D11: -379 | E11: -1081 | F11: -1384 | G11: =G6*$D$56 -> -1419.2435 | H11: =H6*$D$56 -> -1857.2241 | I11: =I6*$D$56 -> -2699.2121 | J11: =J6*$D$56 -> -3968.8271 | K11: =K6*$E$56 -> -6739.5084 | L11: =L6*$E$56 -> -8900.6978 | M11: =M6*$E$56 -> -11369.044 | N11: =N6*$E$56 -> -14621.656 | O11: =O6*$E$56 -> -18919.58 | P11: =P6*$E$56 -> -23976.278 | Q11: =Q6*$E$56 -> -30451.731 | R11: =R6*$F$56 -> -24083.794 | S11: =S6*$F$56 -> -28586.481 | T11: =T6*$F$56 -> -33948.271 | U11: =U6*$F$56 -> -40335.335 | V11: =V6*$F$56 -> -47946.291 | W11: =W6*$F$56 -> -55055.145 | X11: =X6*$F$56 -> -60725.94 | Y11: =Y6*$F$56 -> -66988.607 | ... AF11: =AF6*$F$56 -> -131971.63
B12: 6 | C12: EBITDA | D12: =D8-D9-D10 -> 4044 | E12: =E8-E9-E10 -> 5419 | F12: =F8-F9-F10 -> 3846 | G12: =G8-G9-G10 -> 7779.2941 | H12: =H8-H9-H10 -> 10084.007 | I12: =I8-I9-I10 -> 15691.014 | J12: =J8-J9-J10 -> 24474.481 | K12: =K8-K9-K10 -> 37711.97 | ... AF12: =AF8-AF9-AF10 -> 1162692.2
B13: 7 | C13: (Net financing cost) | D13: 30 | E13: -85 | F13: 99 | G13: =F44*$D$59+F45*$D$58 -> 117.078 | H13: =G44*$D$59+G45*$D$58 -> 290.99188 | I13: =H44*$D$59+H45*$D$58 -> 757.39772 | J13: =I44*$D$59+I45*$D$58 -> 1151.507 | K13: =J44*$D$59+J45*$D$58 -> 1704.6345 | L13: =K44*$D$59+K45*$D$58 -> 2444.9641 | M13: =L44*$D$59+L45*$D$58 -> 1285.0943 | N13: =M44*$D$59+M45*$D$58 -> 1700.7032 | ... AF13: =AE44*$D$59+AE45*$D$58 -> 25895.184
B14: 8 | C14: Other income/(cost) | D14: 4 | E14: 19 | F14: 8 | G14: =AVERAGE(D14:F14)*(1+G5) -> 12.932554 | H14: =AVERAGE(E14:G14)*(1+H5) -> 17.418599 | I14: =AVERAGE(F14:H14)*(1+I5) -> 18.579323 | J14: =AVERAGE(G14:I14)*(1+J5) -> 23.981886 | K14: =AVERAGE(H14:J14)*(1+K5) -> 28.292324 | L14: =AVERAGE(I14:K14)*(1+L5) -> 31.191488 | M14: =AVERAGE(J14:L14)*(1+M5) -> 35.537484 | N14: =AVERAGE(K14:M14)*(1+N5) -> 40.735429 | ... AF14: =AVERAGE(AC14:AE14)*(1+AF5) -> 134.74784
B15: 9 | C15: Earnings before taxes | D15: =D8+D13+D14 -> 3671 | E15: =E8+E13+E14 -> 1179 | F15: =F8+F13+F14 -> 500 | G15: =G8+G13+G14 -> 3664.0046 | H15: =H8+H13+H14 -> 6048.2317 | I15: =I8+I13+I14 -> 12009.5 | J15: =J8+J13+J14 -> 20161.381 | K15: =K8+K13+K14 -> 33184.025 | ... AF15: =AF8+AF13+AF14 -> 995064.09
B16: 10 | C16: (Income tax) | D16: -513 | E16: 122 | F16: 346 | G16: =$D$57*-G15 -> 183.20023 | H16: =$D$57*-H15 -> 302.41159 | I16: =$D$57*-I15 -> 600.47498 | J16: =$D$57*-J15 -> 1008.0691 | K16: =K15*-$E$57 -> -663.6805 | L16: =L15*-$E$57 -> -889.74469 | M16: =M15*-$E$57 -> -1137.3269 | N16: =N15*-$E$57 -> -1333.1853 | O16: =O15*-$E$57 -> -1765.6714 | P16: =P15*-$E$57 -> -2277.4669 | Q16: =Q15*-$E$57 -> -2977.8185 | R16: =$F$57*-R15 -> -29762.16 | S16: =$F$57*-S15 -> -35322.16 | T16: =$F$57*-T15 -> -41976.915 | U16: =$F$57*-U15 -> -49906.643 | V16: =$F$57*-V15 -> -59360.025 | W16: =$F$57*-W15 -> -67871.514 | X16: =$F$57*-X15 -> -74214.248 | Y16: =$F$57*-Y15 -> -81867.155 | ... AF16: =$F$57*-AF15 -> -159210.26
B17: 11 | C17: Net income | D17: =D15+D16+D14 -> 3162 | E17: =E15+E16+E14 -> 1320 | F17: =F15+F16+F14 -> 854 | G17: =G16+G15 -> 3847.2048 | H17: =H16+H15 -> 6350.6433 | I17: =I16+I15 -> 12609.974 | J17: =J16+J15 -> 21169.45 | K17: =K16+K15 -> 32520.345 | L17: =L16+L15 -> 43597.49 | M17: =M16+M15 -> 55729.018 | N17: =N16+N15 -> 65326.078 | ... AF17: =AF16+AF15 -> 835853.84
A19: CASH FLOW STATEMENT | B19: 12 | C19: Operating cash flows before WK | D19: 4674 | E19: 6492 | F19: 6100 | G19: =G17-G10-G9-G11 -> 9511.7483 | H19: =H17-H10-H9-H11 -> 12552.053 | I19: =I17-I10-I9-I11 -> 19766.678 | J19: =J17-J10-J9-J11 -> 30626.865 | K19: =K17-K10-K9-K11 -> 45520.725 | L19: =L17-L10-L9-L11 -> 60278.068 | M19: =M17-M10-M9-M11 -> 76759.864 | N19: =N17-N10-N9-N11 -> 91934.705 | ... AF19: =AF17-AF10-AF9-AF11 -> 1161483.5
B20: 13 | C20: (Stock-based compensation) | D20: -379 | E20: -1081 | F20: -1384 | G20: =G11 -> -1419.2435 | H20: =H11 -> -1857.2241 | I20: =I11 -> -2699.2121 | J20: =J11 -> -3968.8271 | K20: =K11 -> -6739.5084 | L20: =L11 -> -8900.6978 | M20: =M11 -> -11369.044 | N20: =N11 -> -14621.656 | ... AF20: =AF11 -> -131971.63
B21: 14 | C21: (Working Capital Flows) | D21: -774 | E21: -1846 | F21: -3049 | G21: =G6*$D$61 -> -2838.487 | H21: =H6*$D$61 -> -3714.4482 | I21: =I6*$D$61 -> -5398.4243 | J21: =J6*$D$61 -> -7937.6541 | K21: =K6*$E$61 -> -7862.7597 | L21: =L6*$E$61 -> -10384.147 | M21: =M6*$E$61 -> -13263.885 | N21: =N6*$E$61 -> -17058.598 | O21: =O6*$E$61 -> -22072.844 | P21: =P6*$E$61 -> -27972.324 | Q21: =Q6*$E$61 -> -35527.02 | R21: =R6*$F$61 -> -36125.69 | S21: =S6*$F$61 -> -42879.722 | T21: =T6*$F$61 -> -50922.406 | U21: =U6*$F$61 -> -60503.003 | V21: =V6*$F$61 -> -71919.436 | W21: =W6*$F$61 -> -82582.718 | X21: =X6*$F$61 -> -91088.911 | Y21: =Y6*$F$61 -> -100482.91 | ... AF21: =AF6*$F$61 -> -197957.45
B22: 15 | C22: -Total Operating Cash Flow | D22: =D19+D20+D21 -> 3521 | E22: =E19+E20+E21 -> 3565 | F22: =F19+F20+F21 -> 1667 | G22: =G19+G20+G21 -> 5254.0178 | H22: =H19+H20+H21 -> 6980.3808 | I22: =I19+I20+I21 -> 11669.042 | J22: =J19+J20+J21 -> 18720.384 | K22: =K19+K20+K21 -> 30918.457 | ... AF22: =AF19+AF20+AF21 -> 831554.43
B23: 16 | C23: (CAPEX) | D23: -301 | E23: -450 | F23: -546 | G23: =G6*$D$63 -> -669.32786 | H23: =H6*$D$63 -> -875.88341 | I23: =I6*$D$63 -> -1272.9725 | J23: =J6*$D$63 -> -1871.7341 | K23: =K6*$E$63 -> -3369.7542 | L23: =L6*$E$63 -> -4450.3489 | M23: =M6*$E$63 -> -5684.5221 | N23: =N6*$E$63 -> -7310.8279 | O23: =O6*$E$63 -> -9459.7902 | P23: =P6*$F$63 -> -7992.0925 | Q23: =Q6*$F$63 -> -10150.577 | R23: =R6*$F$63 -> -12041.897 | S23: =S6*$F$63 -> -14293.241 | T23: =T6*$F$63 -> -16974.135 | U23: =U6*$F$63 -> -20167.668 | V23: =V6*$F$63 -> -23973.145 | W23: =W6*$F$63 -> -27527.573 | ... AF23: =AF6*$F$63 -> -65985.815 | AG23: =SUM(D23:AF23) -> -586118.74
B24: 17 | C24: Acquistions | D24: -378 | E24: 2465 | F24: -866 | G24: =G6*$D$64 -> -141.92435 | H24: =H6*$D$64 -> -185.72241 | I24: =I6*$D$64 -> -269.92121 | J24: =J6*$D$64 -> -396.88271 | K24: =K6*$E$64 -> -561.6257 | L24: =L6*$E$64 -> -741.72482 | M24: =M6*$E$64 -> -947.42035 | N24: =N6*$F$64 -> -10966.242 | O24: =O6*$F$64 -> -14189.685 | P24: =P6*$F$64 -> -17982.208 | Q24: =Q6*$F$64 -> -22838.798 | R24: =R6*$F$64 -> -27094.268 | S24: =S6*$F$64 -> -32159.791 | T24: =T6*$F$64 -> -38191.805 | U24: =U6*$F$64 -> -45377.252 | ... AF24: =AF6*$F$64 -> -148468.08 | AH24: =AG9-AG23 -> 431753.41
C25: Investments | D25: -7 | E25: -16 | F25: -11
B26: 18 | C26: (Other investing flows) | D26: -7 | E26: -16 | F26: -11 | H26: =(1+H5)*AVERAGE(E26:G26) -> -17.66612 | I26: =(1+I5)*AVERAGE(F26:H26) -> -20.831072 | J26: =(1+J5)*AVERAGE(G26:I26) -> -28.302461 | K26: =(1+K5)*AVERAGE(H26:J26) -> -31.509227 | L26: =(1+L5)*AVERAGE(I26:K26) -> -35.50095 | M26: =(1+M5)*AVERAGE(J26:L26) -> -40.581597 | N26: =(1+N5)*AVERAGE(K26:M26) -> -46.124366 | O26: =(1+O5)*AVERAGE(L26:N26) -> -52.709569 | ... AF26: =(1+AF5)*AVERAGE(AC26:AE26) -> -153.11396
B27: 19 | C27: -Total Investing Flows | D27: =SUM(D23:D26) -> -693 | E27: =SUM(E23:E26) -> 1983 | F27: =SUM(F23:F26) -> -1434 | G27: =G23+G24+G26 -> -811.25221 | H27: =H23+H24+H26 -> -1079.2719 | I27: =I23+I24+I26 -> -1563.7247 | J27: =J23+J24+J26 -> -2296.9193 | K27: =K23+K24+K26 -> -3962.8891 | L27: =L23+L24+L26 -> -5227.5747 | M27: =M23+M24+M26 -> -6672.524 | N27: =N23+N24+N26 -> -18323.194 | ... AF27: =AF23+AF24+AF26 -> -214607.01
B28: 20 | C28: (Flows related to leases) | D28: 0 | E28: 0 | F28: 0 | G28: 0 | H28: 0 | I28: 0 | J28: 0 | K28: 0 | L28: 0 | M28: 0 | N28: 0 | O28: 0 | P28: 0 | Q28: 0 | R28: 0 | S28: 0 | T28: 0 | U28: 0 | V28: 0 | W28: 0 | X28: 0 | Y28: 0 | Z28: 0 | AA28: 0 | AB28: 0 | AC28: 0 | AD28: 0 | AE28: 0 | AF28: 0
B29: 21 | C29: Net Flows related to debt | E29: 679 | G29: =G45-F45 -> 0 | H29: =H45-G45 -> 537.89135 | I29: =I45-H45 -> 752.96363 | J29: =J45-I45 -> 1172.7532 | K29: =K45-J45 -> 1582.9092 | L29: =L45-K45 -> 2126.1428 | M29: =M45-L45 -> -297.67062 | N29: =N45-M45 -> 2162.0221 | ... AF29: =AF45-AE45 -> 21705.232
B30: 22 | C30: (Repurchases)/Issuance of stock | D30: -1762 | E30: -3702 | F30: -985 | G30: =IF(F44+G35>(G6-G8)*0.3,-G35-F44+(G6-G8)*0.3,G6*-0.1) -> -670.31199 | H30: =IF(G44+H35>(H6-H8)*0.3,-H35-G44+(H6-H8)*0.3,H6*-0.1) -> -4200.1563 | I30: =IF(H44+I35>(I6-I8)*0.3,-I35-H44+(I6-I8)*0.3,I6*-0.1) -> -15050.831 | J30: =IF(I44+J35>(J6-J8)*0.3,-J35-I44+(J6-J8)*0.3,J6*-0.1) -> -24966.145 | K30: 2 | L30: =IF(K44+L35>(L6-L8)*0.3,-L35-K44+(L6-L8)*0.3,L6*-0.1) -> -59609.383 | M30: =IF(L44+M35>(M6-M8)*0.3,-M35-L44+(M6-M8)*0.3,M6*-0.1) -> -36284.715 | N30: =IF(M44+N35>(N6-N8)*0.3,-N35-M44+(N6-N8)*0.3,N6*-0.1) -> -29964.95 | O30: =IF(N44+O35>(O6-O8)*0.3,-O35-N44+(O6-O8)*0.3,O6*-0.1) -> -42588.246 | P30: =IF(O44+P35>(P6-P8)*0.3,-P35-O44+(P6-P8)*0.3,P6*-0.1) -> -60927.965 | Q30: =IF(P44+Q35>(Q6-Q8)*0.3,-Q35-P44+(Q6-Q8)*0.3,Q6*-0.1) -> -81111.146 | R30: =IF(Q44+R35>(R6-R8)*0.3,-R35-Q44+(R6-R8)*0.3,R6*-0.1) -> -95623.505 | S30: =IF(R44+S35>(S6-S8)*0.3,-S35-R44+(S6-S8)*0.3,S6*-0.1) -> -107864.88 | ... AF30: =IF(AE44+AF35>(AF6-AF8)*0.3,-AF35-AE44+(AF6-AF8)*0.3,AF6*-0.1) -> -574786.45
B31: 23 | C31: (Dividends) | D31: 0 | E31: 0 | F31: 0 | G31: =-$D$65*G17 -> 0 | H31: =-$D$65*H17 -> 0 | I31: =-$D$65*I17 -> 0 | J31: =-$D$65*J17 -> 0 | K31: =-$F$65*K17 -> 0 | L31: =-$F$65*L17 -> 0 | M31: =-$F$65*M17 -> 0 | N31: =-$F$65*N17 -> 0 | O31: =-$F$65*O17 -> 0 | P31: =-$F$65*P17 -> 0 | Q31: =-$F$65*Q17 -> 0 | R31: =-$F$65*R17 -> 0 | ... AF31: =-$F$65*AF17 -> 0
B32: 24 | C32: Other financing flows | D32: -133 | E32: -241 | F32: -161 | G32: =(1+G5)*AVERAGE(D32:F32) -> -223.19085 | H32: =(1+H5)*AVERAGE(E32:G32) -> -272.70855 | I32: =(1+I5)*AVERAGE(F32:H32) -> -318.23674 | J32: =(1+J5)*AVERAGE(G32:I32) -> -399.02576 | K32: =(1+K5)*AVERAGE(H32:J32) -> -466.96684 | L32: =(1+L5)*AVERAGE(I32:K32) -> -521.32722 | M32: =(1+M5)*AVERAGE(J32:L32) -> -590.68403 | N32: =(1+N5)*AVERAGE(K32:M32) -> -676.90458 | ... AF32: =(1+AF5)*AVERAGE(AC32:AE32) -> -2241.2827
B33: 25 | C33: -Total Financing flows | D33: =D28+D29+D30+D31+D32 -> -1895 | E33: =E28+E29+E30+E31+E32 -> -3264 | F33: =F28+F29+F30+F31+F32 -> -1146 | G33: =G28+G29+G30+G31+G32 -> -893.50284 | H33: =H28+H29+H30+H31+H32 -> -3934.9735 | I33: =I28+I29+I30+I31+I32 -> -14616.104 | J33: =J28+J29+J30+J31+J32 -> -24192.417 | K33: =K28+K29+K30+K31+K32 -> 1117.9424 | ... AF33: =AF28+AF29+AF30+AF31+AF32 -> -555322.5
A35: SUMMARY | B35: 26 | C35: Cash before shareholder returns | D35: =D22+D27+D28+D29+D32 -> 2695 | E35: =E22+E27+E28+E29+E32 -> 5986 | F35: =F22+F27+F28+F29+F32 -> 72 | G35: =G22+G27+G28+G29+G32 -> 4219.5748 | H35: =H22+H27+H28+H29+H32 -> 6166.2917 | I35: =I22+I27+I28+I29+I32 -> 10540.044 | J35: =J22+J27+J28+J29+J32 -> 17197.192 | K35: =K22+K27+K28+K29+K32 -> 28071.51 | ... AF35: =AF22+AF27+AF28+AF29+AF32 -> 636411.37
B36: 27 | C36: Returns to shareholders | D36: 1762 | E36: 3702 | F36: 985 | G36: =-1*(G30+G31) -> 670.31199 | H36: =IF(H35<0.2*(H6-H8),H6*-0.1,H35-0.2*(H6-H8)) -> -3714.4482 | I36: =IF(I35<0.2*(I6-I8),I6*-0.1,I35-0.2*(I6-I8)) -> 1989.8999 | J36: =IF(J35<0.2*(J6-J8),J6*-0.1,J35-0.2*(J6-J8)) -> 5119.0627 | K36: =IF(K35<0.2*(K6-K8),K6*-0.1,K35-0.2*(K6-K8)) -> 11896.702 | L36: =-1*(L30+L31) -> 59609.383 | M36: =-1*(M30+M31) -> 36284.715 | N36: =-1*(N30+N31) -> 29964.95 | O36: =-1*(O30+O31) -> 42588.246 | P36: =-1*(P30+P31) -> 60927.965 | Q36: =-1*(Q30+Q31) -> 81111.146 | R36: =-1*(R30+R31) -> 95623.505 | S36: =-1*(S30+S31) -> 107864.88 | ... AF36: =-1*(AF30+AF31) -> 574786.45
B37: 28 | C37: Excess cash acumulation | D37: =D35-D36 -> 933 | E37: =E35-E36 -> 2284 | F37: =F35-F36 -> -913 | G37: =G35-G36 -> 3549.2628 | H37: =H35-H36 -> 9880.7399 | I37: =I35-I36 -> 8550.1441 | J37: =J35-J36 -> 12078.13 | K37: =K35-K36 -> 16174.808 | ... AF37: =AF35-AF36 -> 61624.917
AG38: =SUM(G38:AF38) -> 0
A39: BALANCE SHEET | B39: 29 | C39: Intangible assets | D39: 328 | E39: 28028 | F39: 27722 | G39: =Assumptions!C329 -> 27722 | H39: =Assumptions!D329 -> 27722 | I39: =Assumptions!E329 -> 34652.5 | J39: =Assumptions!F329 -> 43315.625 | K39: =Assumptions!G329 -> 54144.531 | L39: =Assumptions!H329 -> 67680.664 | M39: =Assumptions!I329 -> 84600.83 | N39: =Assumptions!J329 -> 105751.04 | ... AF39: =Assumptions!AB329 -> 1680669.4 | AG39: =SUM(G39:AF39) -> 12251179
B40: 30 | C40: Accumulated amortization | D40: 0 | E40: -3548 | F40: -6359 | G40: =F40-G10 -> -2755.14 | H40: =G40-H10 -> 848.72 | I40: =H40-I10 -> 4452.58 | J40: =I40-J10 -> 8957.405 | K40: =J40-K10 -> 14155.28 | L40: =K40-L10 -> 20652.624 | M40: =L40-M10 -> 28774.303 | N40: =M40-N10 -> 38926.403 | ... AF40: =AE40-AF10 -> 1266607 | AG40: =SUM(G40:AF40) -> 8192784.1
B41: 31 | C41: PPE+Right of use Assets | D41: 2203 | E41: 3480 | F41: 4009 | G41: =F41+(-G23) -> 4678.3279 | H41: =G41+(-H23) -> 5554.2113 | I41: =H41+(-I23) -> 6827.1837 | J41: =I41+(-J23) -> 8698.9179 | K41: =J41+(-K23) -> 12068.672 | L41: =K41+(-L23) -> 16519.021 | M41: =L41+(-M23) -> 22203.543 | N41: =M41+(-N23) -> 29514.371 | ... AF41: =AE41+(-AF23) -> 588830.74 | AG41: =SUM(G41:AF41) -> 4305487.1
B42: 32 | C42: Accumulated depreciation | D42: -1 134 | E42: -1 507 | F42: -1787 | G42: =F42-G9 -> -1145.56 | H42: =G42-H9 -> -405.23429 | I42: =H42-I9 -> 448.39729 | J42: =I42-J9 -> 1432.1605 | K42: =J42-K9 -> 2495.1575 | L42: =K42-L9 -> 3777.6939 | M42: =L42-M9 -> 5317.816 | N42: =M42-N9 -> 7152.6881 | ... AF42: =AE42-AF9 -> 150903.33
A44: CASH & DEBT & DISCOUNTING | B44: 33 | C44: Ending cash balance | D44: ='Fin. Data'!D39 -> 2535 | E44: =E37+D44 -> 4819 | F44: =F37+E44 -> 3906 | G44: =G37+F44 -> 7455.2628 | H44: =H37+G44 -> 17336.003 | I44: =I37+H44 -> 25886.147 | J44: =J37+I44 -> 37964.276 | K44: =K37+J44 -> 54139.085 | L44: =L37+K44 -> 31900.165 | ... AF44: =AF37+AE44 -> 699076.98
B45: 34 | C45: Total Debt | D45: ='Fin. Data'!D58 -> 349 | E45: ='Fin. Data'!C58 -> 2863 | F45: ='Fin. Data'!B58 -> 2252 | G45: =F45 -> 2252 | H45: =(G39+G44+G41)*0.07 -> 2789.8913 | I45: =(H39+H44+H41)*0.07 -> 3542.855 | J45: =(I39+I44+I41)*0.07 -> 4715.6081 | K45: =(J39+J44+J41)*0.07 -> 6298.5174 | L45: =(K39+K44+K41)*0.07 -> 8424.6602 | M45: =(L39+L44+L41)*0.07 -> 8126.9895 | N45: =(M39+M44+M41)*0.07 -> 10289.012 | O45: =(N39+N44+N41)*0.07 -> 13222.884 | ... AF45: =(AE39+AE44+AE41)*0.07 -> 183522.4
B46: 35 | C46: Discount factor | F46: =1/((1+$F$51)^G51) -> 1 | G46: =1/((1+$F$51)^G50) -> 0.87749259 | H46: =1/((1+$F$51)^H50) -> 0.76999325 | I46: =1/((1+$F$51)^I50) -> 0.67566337 | J46: =1/((1+$F$51)^J50) -> 0.5928896 | K46: =1/((1+$F$51)^K50) -> 0.52025623 | L46: =1/((1+$F$51)^L50) -> 0.45652099 | M46: =1/((1+$F$51)^M50) -> 0.40059378 | N46: =1/((1+$F$51)^N50) -> 0.35151808 | ... AE46: =1/((1+$F$51)^AE50) -> 0.038114169 | AF46: =1/((1+$F$51)^25) -> 0.038114169
B47: 36 | C47: DF + 0.1% | E47: +0.1% | F47: =1/((1+$F$51+0.001)^G51) -> 1 | G47: =1/((1+$F$51+0.001)^G50) -> 0.87672327 | H47: =1/((1+$F$51+0.001)^H50) -> 0.7686437 | I47: =1/((1+$F$51+0.001)^I50) -> 0.67388782 | J47: =1/((1+$F$51+0.001)^J50) -> 0.59081313 | K47: =1/((1+$F$51+0.001)^K50) -> 0.51797962 | L47: =1/((1+$F$51+0.001)^L50) -> 0.45412479 | M47: =1/((1+$F$51+0.001)^M50) -> 0.39814177 | N47: =1/((1+$F$51+0.001)^N50) -> 0.34906016 | ... AE47: =1/((1+$F$51+0.001)^AE50) -> 0.037287509 | AF47: =1/((1+$F$51)^25) -> 0.038114169
B48: 37 | C48: DF+0.5% | E48: +0.5% | F48: =1/((1+$F$51+0.005)^G51) -> 1 | G48: =1/((1+$F$51+0.005)^G50) -> 0.87365944 | H48: =1/((1+$F$51+0.005)^H50) -> 0.76328082 | I48: =1/((1+$F$51+0.005)^I50) -> 0.6668475 | J48: =1/((1+$F$51+0.005)^J50) -> 0.58259761 | K48: =1/((1+$F$51+0.005)^K50) -> 0.5089919 | L48: =1/((1+$F$51+0.005)^L50) -> 0.44468558 | M48: =1/((1+$F$51+0.005)^M50) -> 0.38850376 | N48: =1/((1+$F$51+0.005)^N50) -> 0.33941998 | ... AE48: =1/((1+$F$51+0.005)^AE50) -> 0.034162872 | AF48: =1/((1+$F$51)^25) -> 0.038114169
A50: Discount Rate | C50: Risk free rate | D50: Equity premium | E50: Firm premium | F50: Total | G50: 1 | H50: 2 | I50: 3 | J50: 4 | K50: 5 | L50: 6 | M50: 7 | N50: 8 | O50: 9 | P50: 10 | Q50: 11 | R50: 12 | S50: 13 | T50: 14 | U50: 15 | V50: 16 | W50: 17 | X50: 18 | Y50: 19 | Z50: 20 | AA50: 21 | AB50: 22 | AC50: 23 | AD50: 24 | AE50: 25
F51: =Assumptions!C587 -> 0.13961076 | G51: 0 | I51: Implied DEBT/EBITDA | K51: =K45/K12 -> 0.1670164 | L51: =L45/L12 -> 0.1692006 | M51: =M45/M12 -> 0.12463271 | N51: =N45/N12 -> 0.13378895 | O51: =O45/O12 -> 0.13116356 | P51: =P45/P12 -> 0.12990558 | Q51: =Q45/Q12 -> 0.12459426 | R51: =R45/R12 -> 0.12446938 | ... AF51: =AF45/AF12 -> 0.15784264
A53: Modelling factors | D53: Short Term | E53: Medium Term | F53: Long Term | G53: Reference (line) | I53: Cash/Operational Costs | K53: =K44/(K6-K8) -> 0.66942475 | L53: 0.3 | M53: 0.3 | N53: 0.25 | O53: 0.25 | P53: 0.25 | Q53: 0.25 | R53: =Assumptions!$G$600 -> 0.20494459 | S53: =Assumptions!$G$600 -> 0.20494459 | T53: =Assumptions!$G$600 -> 0.20494459 | U53: =Assumptions!$G$600 -> 0.20494459 | V53: =Assumptions!$G$600 -> 0.20494459 | W53: =Assumptions!$G$600 -> 0.20494459 | X53: =Assumptions!$G$600 -> 0.20494459 | Y53: =Assumptions!$G$600 -> 0.20494459 | ... AF53: =Assumptions!$G$600 -> 0.20494459
C54: Depreciation factor | D54: =Assumptions!K302 -> -0.16 | E54: =Assumptions!L302 -> -0.15 | F54: =Assumptions!M302 -> -0.15 | G54: % Gross PPE
C55: Amortization factor | D55: =Assumptions!L316 -> -0.13 | E55: =Assumptions!$M$316 -> -0.12 | F55: =Assumptions!$M$316 -> -0.12 | G55: % Gross Intangibles | I55: Cash/Sales | K55: =K44/K6 -> 0.48198547 | L55: =L44/L6 -> 0.21504043 | M55: =M44/M6 -> 0.21205744 | N55: =N44/N6 -> 0.22008286 | O55: =O44/O6 -> 0.21822877 | P55: =P44/P6 -> 0.21675318 | Q55: =Q44/Q6 -> 0.21420647 | R55: =R44/R6 -> 0.20965811 | ... AF55: =AF44/AF6 -> 0.21188705
C56: Stock-based comp | D56: =Assumptions!C525 -> -0.05 | E56: =Assumptions!D525 -> -0.06 | F56: =Assumptions!E525 -> -0.04 | G56: % of Revenue
C57: Tax Rate | D57: =Assumptions!C365 -> -0.05 | E57: =Assumptions!D365 -> 0.02 | F57: =Assumptions!E365 -> 0.16 | G57: % EBT
C58: Interest Rate on debt | D58: =Assumptions!$F$401 -> -0.033 | E58: =Assumptions!$F$401 -> -0.033 | F58: =Assumptions!$F$401 -> -0.033 | G58: % Debt | I58: Important Note: medium-term might differ for each factor given it's specific projections. I recommend checking each one individually. | AF58: =AF44/AF6 -> 0.21188705
C59: Interest Rate on cash | D59: =Assumptions!C418 -> 0.049 | E59: =Assumptions!$D$418 -> 0.04 | F59: =Assumptions!$D$418 -> 0.04 | G59: % Cash
C60: PPE+ROA | D60: =Assumptions!S23 -> 0 | E60: =Assumptions!S23 -> 0 | F60: =Assumptions!T23 -> 0 | G60: Growing with CapEx
C61: Working capital flows | D61: =Assumptions!C509 -> -0.1 | E61: =Assumptions!D509 -> -0.07 | F61: =Assumptions!E509 -> -0.06 | G61: % of Revenue
C62: Intangible Assets | D62: =Assumptions!S25 -> 0 | E62: =Assumptions!S25 -> 0 | F62: =Assumptions!T25 -> 0 | G62: Costum growth (acq.) | O62: Sensitivity analysis
C63: Capex | D63: =Assumptions!$G$338 -> -0.023580445 | E63: =Assumptions!C340 -> -0.03 | F63: =Assumptions!I336 -> -0.02 | G63: % Revenue | O63: Tax
C64: Acquisition factor | D64: =Assumptions!$C$446 -> -0.005 | E64: =Assumptions!$C$446 -> -0.005 | F64: =Assumptions!B453 -> -0.045 | G64: % of Revenue | O64: =D76 -> 407.053 | P64: 0.12 | Q64: =P64+1% -> 0.13 | R64: =Q64+1% -> 0.14 | S64: =R64+1% -> 0.15 | T64: =S64+1% -> 0.16 | U64: =T64+1% -> 0.17 | V64: =U64+1% -> 0.18 | W64: =V64+1% -> 0.19 | X64: =W64+1% -> 0.2
C65: Dividends | D65: =Assumptions!S29 -> 0 | E65: =Assumptions!S29 -> 0 | F65: =Assumptions!T29 -> 0 | G65: % of Revenue | N65: Discount Rate | O65: 0.16961076 | P65: 605.16496 | Q65: 487.79934 | R65: 398.40207 | S65: 329.18345 | T65: 274.82565 | U65: 231.60458 | V65: 196.85568 | W65: 168.63731 | X65: 145.51197
C66: Repurchases | D66: -- | E66: -- | F66: -- | G66: Custom formula | O66: 0.15961076 | P66: 614.20575 | Q66: 494.97991 | R66: 404.17003 | S66: 333.86203 | T66: 278.65309 | U66: 234.75945 | V66: 199.47382 | W66: 170.82334 | X66: 147.34741
C67: Leases | D67: 0 | E67: 0 | F67: 0 | G67: See A544 in Assumpt. | O67: 0.14961076 | P67: 623.24654 | Q67: 502.16048 | R67: 409.93798 | S67: 338.54062 | T67: 282.48053 | U67: 237.91431 | V67: 202.09195 | W67: 173.00937 | X67: 149.18284
C68: Total Debt | D68: -- | E68: -- | F68: -- | G68: Custom ratio | H68: =Assumptions!L403 -> 0.070270919 | O68: 0.13961076 | P68: 632.28733 | Q68: 509.34105 | R68: 415.70593 | S68: 343.2192 | T68: 286.30796 | U68: 241.06918 | V68: 204.71008 | W68: 175.19541 | X68: 151.01828
O69: 0.12961076 | P69: 641.32812 | Q69: 516.52161 | R69: 421.47388 | S69: 347.89778 | T69: 290.1354 | U69: 244.22405 | V69: 207.32821 | W69: 177.38144 | X69: 152.85372
A70: Valuation | D70: $ millions | F70: 2023 EV | G70: ='Multiples valuation'!$J$9 -> 276200.63 | O70: 0.11961076 | P70: 650.3689 | Q70: 523.70218 | R70: 427.24184 | S70: 352.57637 | T70: 293.96283 | U70: 247.37891 | V70: 209.94635 | W70: 179.56748 | X70: 154.68916
C71: Value of flows | D71: =SUMPRODUCT(G36:AF36,G46:AF46)+((AF44-AF45)*AF46) -> 446277.95 | E71: =D71/D73 -> 0.67831794 | O71: 0.10961076 | P71: 659.40969 | Q71: 530.88275 | R71: 433.00979 | S71: 357.25495 | T71: 297.79027 | U71: 250.53378 | V71: 212.56448 | W71: 181.75351 | X71: 156.52459
C72: Value of perpetuity | D72: =(AF35/(F51-AF5))*AF46 -> 211640.6 | E72: =D72/D73 -> 0.32168206 | F72: EV/FCF Ratio projection | G72: 2023 | H72: 2024 | I72: 2025 | J72: 2026
C73: Total Value | D73: =D71+D72 -> 657918.55 | F73: Implied EV/FCF | G73: =$G$70/(F22+F23) -> 246.38772 | H73: =$G$70/(G22+G23) -> 60.244124 | I73: =$G$70/(H22+H23) -> 45.245433 | J73: =$G$70/(I22+I23) -> 26.567794
C74: Actual share price | D74: =OP!C20 -> 78.21 | F74: Implied EV/FCF/Growth | H74: =H73/((G22+G23)/(F22+F23)-1) -> 19.497606 | I74: =I73/((H22+H23)/(G22+G23)-1) -> 136.48853 | J74: =J73/((I22+I23)/(H22+H23)-1) -> 37.791055
C75: Total value vs Mkt Cap | D75: =D76/D74-1 -> 4.2046158 | O75: Sensitivity analysis
C76: Estimated NPV per share | D76: =D73*1000000/OP!C21 -> 407.053 | O76: Tax
O77: Implied Upside | P77: 0.12 | Q77: =P77+1% -> 0.13 | R77: =Q77+1% -> 0.14 | S77: =R77+1% -> 0.15 | T77: =S77+1% -> 0.16 | U77: =T77+1% -> 0.17 | V77: =U77+1% -> 0.18 | W77: =V77+1% -> 0.19 | X77: =W77+1% -> 0.2
A78: Sensibility | C78: Sensitivity +0.1% | D78: =(SUMPRODUCT(G36:AF36,G46:AF46)+((AF44-AF45)*AF46)+(AF35/(F51+0.001-AF5))*AF46)*1000000/OP!C21 -> 405.9204 | E78: =D78/D76-1 -> -0.0027824578 | N78: Discount Rate | O78: 0.16961076 | P78: =P65/$D$74-1 -> 6.7376929 | Q78: =Q65/$D$74-1 -> 5.2370457 | R78: =R65/$D$74-1 -> 4.0940043 | S78: =S65/$D$74-1 -> 3.2089688 | T78: =T65/$D$74-1 -> 2.5139452 | U78: =U65/$D$74-1 -> 1.9613167 | V78: =V65/$D$74-1 -> 1.5170142 | W78: =W65/$D$74-1 -> 1.1562116 | X78: =X65/$D$74-1 -> 0.86052897
C79: Sensitivity +0.5% | D79: =(SUMPRODUCT(G36:AF36,G46:AF46)+((AF44-AF45)*AF46)+(AF35/(F51+0.005-AF5))*AF46)*1000000/OP!C21 -> 401.57935 | E79: =D79/D76-1 -> -0.013447037 | O79: 0.15961076 | P79: =P66/$D$74-1 -> 6.8532893 | Q79: =Q66/$D$74-1 -> 5.3288571 | R79: =R66/$D$74-1 -> 4.1677538 | S79: =S66/$D$74-1 -> 3.2687896 | T79: =T66/$D$74-1 -> 2.5628831 | U79: =U66/$D$74-1 -> 2.0016551 | V79: =V66/$D$74-1 -> 1.5504899 | W79: =W66/$D$74-1 -> 1.1841624 | X79: =X66/$D$74-1 -> 0.88399703
O80: 0.14961076 | P80: =P67/$D$74-1 -> 6.9688856 | Q80: =Q67/$D$74-1 -> 5.4206684 | R80: =R67/$D$74-1 -> 4.2415034 | S80: =S67/$D$74-1 -> 3.3286104 | T80: =T67/$D$74-1 -> 2.6118211 | U80: =U67/$D$74-1 -> 2.0419935 | V80: =V67/$D$74-1 -> 1.5839656 | W80: =W67/$D$74-1 -> 1.2121132 | X80: =X67/$D$74-1 -> 0.90746509
A81: Notes | C81: Price where it'd be a "BUY" | D81: =D76/1.1 -> 370.04819 | O81: 0.13961076 | P81: =P68/$D$74-1 -> 7.0844819 | Q81: =Q68/$D$74-1 -> 5.5124798 | R81: =R68/$D$74-1 -> 4.3152529 | S81: =S68/$D$74-1 -> 3.3884311 | T81: =T68/$D$74-1 -> 2.660759 | U81: =U68/$D$74-1 -> 2.0823319 | V81: =V68/$D$74-1 -> 1.6174412 | W81: =W68/$D$74-1 -> 1.240064 | X81: =X68/$D$74-1 -> 0.93093315
O82: 0.12961076 | P82: =P69/$D$74-1 -> 7.2000782 | Q82: =Q69/$D$74-1 -> 5.6042912 | R82: =R69/$D$74-1 -> 4.3890025 | S82: =S69/$D$74-1 -> 3.4482519 | T82: =T69/$D$74-1 -> 2.7096969 | U82: =U69/$D$74-1 -> 2.1226703 | V82: =V69/$D$74-1 -> 1.6509169 | W82: =W69/$D$74-1 -> 1.2680149 | X82: =X69/$D$74-1 -> 0.95440122
O83: 0.11961076 | P83: =P70/$D$74-1 -> 7.3156745 | Q83: =Q70/$D$74-1 -> 5.6961026 | R83: =R70/$D$74-1 -> 4.462752 | S83: =S70/$D$74-1 -> 3.5080727 | T83: =T70/$D$74-1 -> 2.7586349 | U83: =U70/$D$74-1 -> 2.1630088 | V83: =V70/$D$74-1 -> 1.6843926 | W83: =W70/$D$74-1 -> 1.2959657 | X83: =X70/$D$74-1 -> 0.97786928
O84: 0.10961076 | P84: =P71/$D$74-1 -> 7.4312708 | Q84: =Q71/$D$74-1 -> 5.7879139 | R84: =R71/$D$74-1 -> 4.5365016 | S84: =S71/$D$74-1 -> 3.5678935 | T84: =T71/$D$74-1 -> 2.8075728 | U84: =U71/$D$74-1 -> 2.2033472 | V84: =V71/$D$74-1 -> 1.7178683 | W84: =W71/$D$74-1 -> 1.3239165 | X84: =X71/$D$74-1 -> 1.0013373

Sheet Base Case
A1: VALUATION MODEL
G3: Short Term | K3: Long Term
A4: Section | B4: Line # | C4: ITEM | D4: 2021 (Real) | E4: 2022 (Real) | F4: 2023 (Real) | G4: 2024 | H4: =G4+1 -> 2025 | I4: =H4+1 -> 2026 | J4: =I4+1 -> 2027 | K4: =J4+1 -> 2028 | L4: =K4+1 -> 2029 | M4: =L4+1 -> 2030 | N4: =M4+1 -> 2031 | O4: =N4+1 -> 2032 | ... AF4: =AE4+1 -> 2049
A5: INCOME STATEMENT | B5: 1 | C5: Growth | D5: 0.68329407 | E5: 0.43610807 | F5: -0.03902377 | G5: =G6/F6-1 -> 0.17767504 | H5: =H6/G6-1 -> 0.22354196 | I5: =I6/H6-1 -> 0.24617602 | J5: =J6/I6-1 -> 0.22145645 | K5: =K6/J6-1 -> 0.27303276 | L5: =L6/K6-1 -> 0.21776882 | M5: =M6/L6-1 -> 0.18241783 | N5: =N6/M6-1 -> 0.1874719 | ... AE5: =AE6/AD6-1 -> 0.10913048 | AF5: 0.03
B6: 2 | C6: Revenues/Sales | D6: 16434 | E6: 23601 | F6: 22680 | G6: =Assumptions!G198 -> 26709.67 | H6: =Assumptions!H198 -> 32680.402 | I6: =Assumptions!I198 -> 40725.533 | J6: =Assumptions!J198 -> 49744.465 | K6: =Assumptions!K198 -> 63326.334 | L6: =Assumptions!L198 -> 77116.835 | M6: =Assumptions!M198 -> 91184.321 | N6: =Assumptions!N198 -> 108278.82 | ... AF6: =Assumptions!AF198 -> 1020813.3
B7: 3 | C7: EBIT/Operating Margin | D7: =D8/D6 -> 0.22130948 | E7: =E8/E6 -> 0.052752002 | F7: =F8/F6 -> 0.017328042 | G7: =G8/G6 -> 0.1170028 | H7: =H8/H6 -> 0.14429852 | I7: =I8/I6 -> 0.20427576 | J7: =J8/J6 -> 0.23532504 | K7: =K8/K6 -> 0.23809551 | ... AF7: =AF8/AF6 -> 0.2010142
B8: 4 | C8: EBIT | D8: 3637 | E8: 1245 | F8: 393 | G8: =Assumptions!G202 -> 3125.1061 | H8: =Assumptions!H202 -> 4715.7336 | I8: =Assumptions!I202 -> 8319.2391 | J8: =Assumptions!J202 -> 11706.119 | K8: =Assumptions!K202 -> 15077.716 | L8: =Assumptions!L202 -> 16174.321 | M8: =Assumptions!M202 -> 20360.762 | N8: =Assumptions!N202 -> 22708.15 | ... AF8: =Assumptions!AF202 -> 205197.98
B9: 5a | C9: (Dep) | D9: -407 | E9: -626 | F9: -642 | G9: =$D$54*Pessimistic!F41 -> -641.44 | H9: =$D$54*Pessimistic!G41 -> -740.32571 | I9: =$D$54*Pessimistic!H41 -> -853.63158 | J9: =$D$54*Pessimistic!I41 -> -983.76317 | K9: =$E$54*Pessimistic!J41 -> -1062.9971 | L9: =$E$54*Pessimistic!K41 -> -1282.5363 | M9: =$E$54*Pessimistic!L41 -> -1540.1221 | N9: =$E$54*Pessimistic!M41 -> -1834.8721 | O9: =$E$54*Pessimistic!N41 -> -2173.3095 | P9: =$F$54*Pessimistic!O41 -> -2563.1876 | Q9: =$F$54*Pessimistic!P41 -> -2912.2794 | R9: =$F$54*Pessimistic!Q41 -> -3320.5219 | S9: =$F$54*Pessimistic!R41 -> -3782.5873 | T9: =$F$54*Pessimistic!S41 -> -4305.8076 | U9: =$F$54*Pessimistic!T41 -> -4898.5407 | V9: =$F$54*Pessimistic!U41 -> -5559.9202 | W9: =$F$54*Pessimistic!V41 -> -6298.2169 | ... AF9: =$F$54*Pessimistic!AE41 -> -18283.842 | AG9: =SUM(D9:AF9) -> -154365.33
B10: 5b | C10: (Amort) | D10: 0 | E10: -3548 | F10: -2811 | G10: =F39*$D$55 -> -3603.86 | H10: =G39*$D$55 -> -3603.86 | I10: =H39*$D$55 -> -3603.86 | J10: =I39*$D$55 -> -4504.825 | K10: =J39*$F$55 -> -5197.875 | L10: =K39*$F$55 -> -6497.3438 | M10: =L39*$F$55 -> -8121.6797 | N10: =M39*$F$55 -> -10152.1 | O10: =N39*$F$55 -> -12690.125 | P10: =O39*$F$55 -> -15862.656 | Q10: =P39*$F$55 -> -19828.32 | R10: =Q39*$F$55 -> -24785.399 | ... AF10: =AE39*$F$55 -> -175374.19
B11: 5c | C11: (Stock based compensation) | D11: -379 | E11: -1081 | F11: -1384 | G11: =G6*$D$56 -> -1335.4835 | H11: =H6*$D$56 -> -1634.0201 | I11: =I6*$D$56 -> -2036.2767 | J11: =J6*$D$56 -> -2487.2233 | K11: =K6*$E$56 -> -3799.5801 | L11: =L6*$E$56 -> -4627.0101 | M11: =M6*$E$56 -> -5471.0593 | N11: =N6*$E$56 -> -6496.7292 | O11: =O6*$E$56 -> -7745.2041 | P11: =P6*$E$56 -> -9331.1601 | Q11: =Q6*$E$56 -> -11161.874 | R11: =R6*$F$56 -> -8677.5418 | S11: =S6*$F$56 -> -10128.458 | T11: =T6*$F$56 -> -11585.301 | U11: =U6*$F$56 -> -12970.097 | V11: =V6*$F$56 -> -14527.312 | W11: =W6*$F$56 -> -16279.279 | X11: =X6*$F$56 -> -18072.488 | Y11: =Y6*$F$56 -> -20069.81 | ... AF11: =AF6*$F$56 -> -40832.533
B12: 6 | C12: EBITDA | D12: =D8-D9-D10 -> 4044 | E12: =E8-E9-E10 -> 5419 | F12: =F8-F9-F10 -> 3846 | G12: =G8-G9-G10 -> 7370.4061 | H12: =H8-H9-H10 -> 9059.9194 | I12: =I8-I9-I10 -> 12776.731 | J12: =J8-J9-J10 -> 17194.707 | K12: =K8-K9-K10 -> 21338.588 | ... AF12: =AF8-AF9-AF10 -> 398856.01
B13: 7 | C13: (Net financing cost) | D13: 30 | E13: -85 | F13: 99 | G13: =F44*$D$59+F45*$D$58 -> 117.078 | H13: =G44*$D$59+G45*$D$58 -> 272.37709 | I13: =H44*$D$59+H45*$D$58 -> 529.64923 | J13: =I44*$D$59+I45*$D$58 -> 832.53111 | K13: =J44*$D$59+J45*$D$58 -> 1172.1074 | L13: =K44*$D$59+K45*$D$58 -> 1604.6487 | M13: =L44*$D$59+L45*$D$58 -> 664.86872 | N13: =M44*$D$59+M45*$D$58 -> 815.37433 | ... AF13: =AE44*$D$59+AE45*$D$58 -> 7060.514
B14: 8 | C14: Other income/(cost) | D14: 4 | E14: 19 | F14: 8 | G14: =AVERAGE(D14:F14)*(1+G5) -> 12.169309 | H14: =AVERAGE(E14:G14)*(1+H5) -> 15.975098 | I14: =AVERAGE(F14:H14)*(1+I5) -> 15.014098 | J14: =AVERAGE(G14:I14)*(1+J5) -> 17.572078 | K14: =AVERAGE(H14:J14)*(1+K5) -> 20.606697 | L14: =AVERAGE(I14:K14)*(1+L5) -> 21.592207 | M14: =AVERAGE(J14:L14)*(1+M5) -> 23.558092 | N14: =AVERAGE(K14:M14)*(1+N5) -> 26.028195 | ... AF14: =AVERAGE(AC14:AE14)*(1+AF5) -> 73.608781
B15: 9 | C15: Earnings before taxes | D15: =D8+D13+D14 -> 3671 | E15: =E8+E13+E14 -> 1179 | F15: =F8+F13+F14 -> 500 | G15: =G8+G13+G14 -> 3254.3534 | H15: =H8+H13+H14 -> 5004.0858 | I15: =I8+I13+I14 -> 8863.9025 | J15: =J8+J13+J14 -> 12556.222 | K15: =K8+K13+K14 -> 16270.43 | ... AF15: =AF8+AF13+AF14 -> 212332.1
B16: 10 | C16: (Income tax) | D16: -513 | E16: 122 | F16: 346 | G16: =$D$57*-G15 -> 162.71767 | H16: =$D$57*-H15 -> 250.20429 | I16: =$D$57*-I15 -> 443.19512 | J16: =$D$57*-J15 -> 627.81108 | K16: =K15*-$E$57 -> -325.4086 | L16: =L15*-$E$57 -> -356.01124 | M16: =M15*-$E$57 -> -420.98377 | N16: =N15*-$E$57 -> -470.99105 | O16: =O15*-$E$57 -> -586.13259 | P16: =P15*-$E$57 -> -768.37904 | Q16: =Q15*-$E$57 -> -895.52436 | R16: =$F$57*-R15 -> -7943.97 | S16: =$F$57*-S15 -> -9206.1641 | T16: =$F$57*-T15 -> -10530.706 | U16: =$F$57*-U15 -> -11866.563 | V16: =$F$57*-V15 -> -13364.982 | W16: =$F$57*-W15 -> -14695.221 | X16: =$F$57*-X15 -> -15644.326 | Y16: =$F$57*-Y15 -> -17443.739 | ... AF16: =$F$57*-AF15 -> -33973.136
B17: 11 | C17: Net income | D17: =D15+D16+D14 -> 3162 | E17: =E15+E16+E14 -> 1320 | F17: =F15+F16+F14 -> 854 | G17: =G16+G15 -> 3417.071 | H17: =H16+H15 -> 5254.2901 | I17: =I16+I15 -> 9307.0976 | J17: =J16+J15 -> 13184.033 | K17: =K16+K15 -> 15945.021 | L17: =L16+L15 -> 17444.551 | M17: =M16+M15 -> 20628.205 | N17: =N16+N15 -> 23078.562 | ... AF17: =AF16+AF15 -> 178358.96
A19: CASH FLOW STATEMENT | B19: 12 | C19: Operating cash flows before WK | D19: 4674 | E19: 6492 | F19: 6100 | G19: =G17-G10-G9-G11 -> 8997.8545 | H19: =H17-H10-H9-H11 -> 11232.496 | I19: =I17-I10-I9-I11 -> 15800.866 | J19: =J17-J10-J9-J11 -> 21159.844 | K19: =K17-K10-K9-K11 -> 26005.473 | L19: =L17-L10-L9-L11 -> 29851.441 | M19: =M17-M10-M9-M11 -> 35761.066 | N19: =N17-N10-N9-N11 -> 41562.262 | ... AF19: =AF17-AF10-AF9-AF11 -> 412849.53
B20: 13 | C20: (Stock-based compensation) | D20: -379 | E20: -1081 | F20: -1384 | G20: =G11 -> -1335.4835 | H20: =H11 -> -1634.0201 | I20: =I11 -> -2036.2767 | J20: =J11 -> -2487.2233 | K20: =K11 -> -3799.5801 | L20: =L11 -> -4627.0101 | M20: =M11 -> -5471.0593 | N20: =N11 -> -6496.7292 | ... AF20: =AF11 -> -40832.533
B21: 14 | C21: (Working Capital Flows) | D21: -774 | E21: -1846 | F21: -3049 | G21: =G6*$D$61 -> -2670.967 | H21: =H6*$D$61 -> -3268.0402 | I21: =I6*$D$61 -> -4072.5533 | J21: =J6*$D$61 -> -4974.4465 | K21: =K6*$E$61 -> -4432.8434 | L21: =L6*$E$61 -> -5398.1785 | M21: =M6*$E$61 -> -6382.9025 | N21: =N6*$E$61 -> -7579.5174 | O21: =O6*$E$61 -> -9036.0714 | P21: =P6*$E$61 -> -10886.353 | Q21: =Q6*$E$61 -> -13022.186 | R21: =R6*$F$61 -> -13016.313 | S21: =S6*$F$61 -> -15192.688 | T21: =T6*$F$61 -> -17377.951 | U21: =U6*$F$61 -> -19455.145 | V21: =V6*$F$61 -> -21790.967 | W21: =W6*$F$61 -> -24418.919 | X21: =X6*$F$61 -> -27108.732 | Y21: =Y6*$F$61 -> -30104.714 | ... AF21: =AF6*$F$61 -> -61248.799
B22: 15 | C22: -Total Operating Cash Flow | D22: =D19+D20+D21 -> 3521 | E22: =E19+E20+E21 -> 3565 | F22: =F19+F20+F21 -> 1667 | G22: =G19+G20+G21 -> 4991.404 | H22: =H19+H20+H21 -> 6330.4356 | I22: =I19+I20+I21 -> 9692.0358 | J22: =J19+J20+J21 -> 13698.174 | K22: =K19+K20+K21 -> 17773.05 | ... AF22: =AF19+AF20+AF21 -> 310768.2
B23: 16 | C23: (CAPEX) | D23: -301 | E23: -450 | F23: -546 | G23: =G6*$D$63 -> -629.8259 | H23: =H6*$D$63 -> -770.61842 | I23: =I6*$D$63 -> -960.32619 | J23: =J6*$D$63 -> -1172.9966 | K23: =K6*$E$63 -> -1899.79 | L23: =L6*$E$63 -> -2313.5051 | M23: =M6*$E$63 -> -2735.5296 | N23: =N6*$E$63 -> -3248.3646 | O23: =O6*$E$63 -> -3872.602 | P23: =P6*$F$63 -> -4665.58 | Q23: =Q6*$F$63 -> -5580.9369 | R23: =R6*$F$63 -> -6508.1563 | S23: =S6*$F$63 -> -7596.3438 | T23: =T6*$F$63 -> -8688.9756 | U23: =U6*$F$63 -> -9727.5724 | V23: =V6*$F$63 -> -10895.484 | W23: =W6*$F$63 -> -12209.459 | ... AF23: =AF6*$F$63 -> -30624.4 | AG23: =SUM(D23:AF23) -> -275998.61
B24: 17 | C24: Acquistions | D24: -378 | E24: 2465 | F24: -866 | G24: =G6*$D$64 -> -133.54835 | H24: =H6*$D$64 -> -163.40201 | I24: =I6*$D$64 -> -203.62767 | J24: =J6*$D$64 -> -248.72233 | K24: =K6*$E$64 -> -316.63167 | L24: =L6*$E$64 -> -385.58418 | M24: =M6*$E$64 -> -455.92161 | N24: =N6*$F$64 -> -2165.5764 | O24: =O6*$F$64 -> -2581.7347 | P24: =P6*$F$64 -> -3110.3867 | Q24: =Q6*$F$64 -> -3720.6246 | R24: =R6*$F$64 -> -4338.7709 | S24: =S6*$F$64 -> -5064.2292 | T24: =T6*$F$64 -> -5792.6504 | U24: =U6*$F$64 -> -6485.0483 | ... AF24: =AF6*$F$64 -> -20416.266 | AH24: =AG9-AG23 -> 121633.27
C25: Investments | D25: -7 | E25: -16 | F25: -11
B26: 18 | C26: (Other investing flows) | D26: -7 | E26: -16 | F26: -11 | H26: =(1+H5)*AVERAGE(E26:G26) -> -16.517816 | I26: =(1+I5)*AVERAGE(F26:H26) -> -17.146022 | J26: =(1+J5)*AVERAGE(G26:I26) -> -20.559456 | K26: =(1+K5)*AVERAGE(H26:J26) -> -23.009343 | L26: =(1+L5)*AVERAGE(I26:K26) -> -24.645539 | M26: =(1+M5)*AVERAGE(J26:L26) -> -26.88595 | N26: =(1+N5)*AVERAGE(K26:M26) -> -29.505048 | O26: =(1+O5)*AVERAGE(L26:N26) -> -32.203103 | ... AF26: =(1+AF5)*AVERAGE(AC26:AE26) -> -83.715706
B27: 19 | C27: -Total Investing Flows | D27: =SUM(D23:D26) -> -693 | E27: =SUM(E23:E26) -> 1983 | F27: =SUM(F23:F26) -> -1434 | G27: =G23+G24+G26 -> -763.37425 | H27: =H23+H24+H26 -> -950.53824 | I27: =I23+I24+I26 -> -1181.0999 | J27: =J23+J24+J26 -> -1442.2784 | K27: =K23+K24+K26 -> -2239.431 | L27: =L23+L24+L26 -> -2723.7348 | M27: =M23+M24+M26 -> -3218.3372 | N27: =N23+N24+N26 -> -5443.446 | ... AF27: =AF23+AF24+AF26 -> -51124.382
B28: 20 | C28: (Flows related to leases) | D28: 0 | E28: 0 | F28: 0 | G28: 0 | H28: 0 | I28: 0 | J28: 0 | K28: 0 | L28: 0 | M28: 0 | N28: 0 | O28: 0 | P28: 0 | Q28: 0 | R28: 0 | S28: 0 | T28: 0 | U28: 0 | V28: 0 | W28: 0 | X28: 0 | Y28: 0 | Z28: 0 | AA28: 0 | AB28: 0 | AC28: 0 | AD28: 0 | AE28: 0 | AF28: 0
B29: 21 | C29: Net Flows related to debt | E29: 679 | G29: =G45-F45 -> 0 | H29: =H45-G45 -> 508.53366 | I29: =I45-H45 -> 445.44864 | J29: =J45-I45 -> 1006.046 | K29: =K45-J45 -> 1221.0654 | L29: =L45-K45 -> 1566.4894 | M29: =M45-L45 -> -159.21938 | N29: =N45-M45 -> 1583.4007 | ... AF29: =AF45-AE45 -> 16841.067
B30: 22 | C30: (Repurchases)/Issuance of stock | D30: -1762 | E30: -3702 | F30: -985 | G30: =IF(F44+G35>(G6-G8)*0.3,-G35-F44+(G6-G8)*0.3,G6*-0.1) -> -848.64187 | H30: =IF(G44+H35>(H6-H8)*0.3,-H35-G44+(H6-H8)*0.3,H6*-0.1) -> -4324.7896 | I30: =IF(H44+I35>(I6-I8)*0.3,-I35-H44+(I6-I8)*0.3,I6*-0.1) -> -11644.995 | J30: =IF(I44+J35>(J6-J8)*0.3,-J35-I44+(J6-J8)*0.3,J6*-0.1) -> -20707.895 | K30: =IF(J44+K35>(K6-K8)*0.3,-K35-J44+(K6-K8)*0.3,K6*-0.1) -> -28698.059 | L30: =IF(K44+L35>(L6-L8)*0.3,-L35-K44+(L6-L8)*0.3,L6*-0.1) -> -36432.269 | M30: =IF(L44+M35>(M6-M8)*0.3,-M35-L44+(M6-M8)*0.3,M6*-0.1) -> -17174.124 | N30: =IF(M44+N35>(N6-N8)*0.3,-N35-M44+(N6-N8)*0.3,N6*-0.1) -> -18769.867 | ... AF30: =IF(AE44+AF35>(AF6-AF8)*0.3,-AF35-AE44+(AF6-AF8)*0.3,AF6*-0.1) -> -254475
B31: 23 | C31: (Dividends) | D31: 0 | E31: 0 | F31: 0 | G31: =-$D$65*G17 -> 0 | H31: =-$D$65*H17 -> 0 | I31: =-$D$65*I17 -> 0 | J31: =-$D$65*J17 -> 0 | K31: =-$F$65*K17 -> 0 | L31: =-$F$65*L17 -> 0 | M31: =-$F$65*M17 -> 0 | N31: =-$F$65*N17 -> 0 | O31: =-$F$65*O17 -> 0 | P31: =-$F$65*P17 -> 0 | Q31: =-$F$65*Q17 -> 0 | R31: =-$F$65*R17 -> 0 | ... AF31: =-$F$65*AF17 -> 0
B32: 24 | C32: Other financing flows | D32: -133 | E32: -241 | F32: -161 | G32: =(1+G5)*AVERAGE(D32:F32) -> -210.01872 | H32: =(1+H5)*AVERAGE(E32:G32) -> -249.61019 | I32: =(1+I5)*AVERAGE(F32:H32) -> -257.80429 | J32: =(1+J5)*AVERAGE(G32:I32) -> -292.10447 | K32: =(1+K5)*AVERAGE(H32:J32) -> -339.27127 | L32: =(1+L5)*AVERAGE(I32:K32) -> -360.93857 | M32: =(1+M5)*AVERAGE(J32:L32) -> -391.11005 | N32: =(1+N5)*AVERAGE(K32:M32) -> -431.97057 | ... AF32: =(1+AF5)*AVERAGE(AC32:AE32) -> -1223.1403
B33: 25 | C33: -Total Financing flows | D33: =D28+D29+D30+D31+D32 -> -1895 | E33: =E28+E29+E30+E31+E32 -> -3264 | F33: =F28+F29+F30+F31+F32 -> -1146 | G33: =G28+G29+G30+G31+G32 -> -1058.6606 | H33: =H28+H29+H30+H31+H32 -> -4065.8661 | I33: =I28+I29+I30+I31+I32 -> -11457.351 | J33: =J28+J29+J30+J31+J32 -> -19993.954 | K33: =K28+K29+K30+K31+K32 -> -27816.264 | ... AF33: =AF28+AF29+AF30+AF31+AF32 -> -238857.07
A35: SUMMARY | B35: 26 | C35: Cash before shareholder returns | D35: =D22+D27+D28+D29+D32 -> 2695 | E35: =E22+E27+E28+E29+E32 -> 5986 | F35: =F22+F27+F28+F29+F32 -> 72 | G35: =G22+G27+G28+G29+G32 -> 4018.0111 | H35: =H22+H27+H28+H29+H32 -> 5638.8209 | I35: =I22+I27+I28+I29+I32 -> 8698.5803 | J35: =J22+J27+J28+J29+J32 -> 12969.837 | K35: =K22+K27+K28+K29+K32 -> 16415.413 | ... AF35: =AF22+AF27+AF28+AF29+AF32 -> 275261.74
B36: 27 | C36: Returns to shareholders | D36: 1762 | E36: 3702 | F36: 985 | G36: =-1*(G30+G31) -> 848.64187 | H36: =IF(H35<0.2*(H6-H8),H6*-0.1,H35-0.2*(H6-H8)) -> 45.887218 | I36: =IF(I35<0.2*(I6-I8),I6*-0.1,I35-0.2*(I6-I8)) -> 2217.3215 | J36: =IF(J35<0.2*(J6-J8),J6*-0.1,J35-0.2*(J6-J8)) -> 5362.1681 | K36: =IF(K35<0.2*(K6-K8),K6*-0.1,K35-0.2*(K6-K8)) -> 6765.6893 | L36: =-1*(L30+L31) -> 36432.269 | M36: =-1*(M30+M31) -> 17174.124 | N36: =-1*(N30+N31) -> 18769.867 | O36: =-1*(O30+O31) -> 25043.104 | P36: =-1*(P30+P31) -> 34056.204 | Q36: =-1*(Q30+Q31) -> 39398.583 | R36: =-1*(R30+R31) -> 41206.832 | S36: =-1*(S30+S31) -> 46643.508 | ... AF36: =-1*(AF30+AF31) -> 254475
B37: 28 | C37: Excess cash acumulation | D37: =D35-D36 -> 933 | E37: =E35-E36 -> 2284 | F37: =F35-F36 -> -913 | G37: =G35-G36 -> 3169.3692 | H37: =H35-H36 -> 5592.9337 | I37: =I35-I36 -> 6481.2588 | J37: =J35-J36 -> 7607.6694 | K37: =K35-K36 -> 9649.7237 | ... AF37: =AF35-AF36 -> 20786.743
A39: BALANCE SHEET | B39: 29 | C39: Intangible assets | D39: 328 | E39: 28028 | F39: 27722 | G39: =Assumptions!C329 -> 27722 | H39: =Assumptions!D329 -> 27722 | I39: =Assumptions!E329 -> 34652.5 | J39: =Assumptions!F329 -> 43315.625 | K39: =Assumptions!G329 -> 54144.531 | L39: =Assumptions!H329 -> 67680.664 | M39: =Assumptions!I329 -> 84600.83 | N39: =Assumptions!J329 -> 105751.04 | ... AF39: =Assumptions!AB329 -> 1680669.4 | AG39: =SUM(G39:AF39) -> 12251179
B40: 30 | C40: Accumulated amortization | D40: 0 | E40: -3548 | F40: -6359 | G40: =F40-G10 -> -2755.14 | H40: =G40-H10 -> 848.72 | I40: =H40-I10 -> 4452.58 | J40: =I40-J10 -> 8957.405 | K40: =J40-K10 -> 14155.28 | L40: =K40-L10 -> 20652.624 | M40: =L40-M10 -> 28774.303 | N40: =M40-N10 -> 38926.403 | ... AF40: =AE40-AF10 -> 1266607 | AG40: =SUM(G40:AF40) -> 8192784.1
B41: 31 | C41: PPE+Right of use Assets | D41: 2203 | E41: 3480 | F41: 4009 | G41: =F41+(-G23) -> 4638.8259 | H41: =G41+(-H23) -> 5409.4443 | I41: =H41+(-I23) -> 6369.7705 | J41: =I41+(-J23) -> 7542.7671 | K41: =J41+(-K23) -> 9442.5572 | L41: =K41+(-L23) -> 11756.062 | M41: =L41+(-M23) -> 14491.592 | N41: =M41+(-N23) -> 17739.956 | ... AF41: =AE41+(-AF23) -> 278710.61 | AG41: =SUM(G41:AF41) -> 2138202.8
B42: 32 | C42: Accumulated depreciation | D42: -1 134 | E42: -1 507 | F42: -1787 | G42: =F42-G9 -> -1145.56 | H42: =G42-H9 -> -405.23429 | I42: =H42-I9 -> 448.39729 | J42: =I42-J9 -> 1432.1605 | K42: =J42-K9 -> 2495.1575 | L42: =K42-L9 -> 3777.6939 | M42: =L42-M9 -> 5317.816 | N42: =M42-N9 -> 7152.6881 | ... AF42: =AE42-AF9 -> 150903.33 | AG42: =SUM(G42:AF42) -> 1075463.6
A44: CASH & DEBT & DISCOUNTING | B44: 33 | C44: Ending cash balance | D44: ='Fin. Data'!D39 -> 2535 | E44: =E37+D44 -> 4819 | F44: =F37+E44 -> 3906 | G44: =G37+F44 -> 7075.3692 | H44: =H37+G44 -> 12668.303 | I44: =I37+H44 -> 19149.562 | J44: =J37+I44 -> 26757.231 | K44: =K37+J44 -> 36406.955 | L44: =L37+K44 -> 18282.754 | ... AF44: =AF37+AE44 -> 244684.6
B45: 34 | C45: Total Debt | D45: ='Fin. Data'!D58 -> 349 | E45: ='Fin. Data'!C58 -> 2863 | F45: ='Fin. Data'!B58 -> 2252 | G45: =F45 -> 2252 | H45: =(G39+G44+G41)*0.07 -> 2760.5337 | I45: =(H39+H44+H41)*0.07 -> 3205.9823 | J45: =(I39+I44+I41)*0.07 -> 4212.0283 | K45: =(J39+J44+J41)*0.07 -> 5433.0936 | L45: =(K39+K44+K41)*0.07 -> 6999.583 | M45: =(L39+L44+L41)*0.07 -> 6840.3636 | N45: =(M39+M44+M41)*0.07 -> 8423.7643 | O45: =(N39+N44+N41)*0.07 -> 10441.354 | ... AF45: =(AE39+AE44+AE41)*0.07 -> 135340.5
B46: 35 | C46: Discount factor | F46: =1/((1+$F$51)^G51) -> 1 | G46: =1/((1+$F$51)^G50) -> 0.87749259 | H46: =1/((1+$F$51)^H50) -> 0.76999325 | I46: =1/((1+$F$51)^I50) -> 0.67566337 | J46: =1/((1+$F$51)^J50) -> 0.5928896 | K46: =1/((1+$F$51)^K50) -> 0.52025623 | L46: =1/((1+$F$51)^L50) -> 0.45652099 | M46: =1/((1+$F$51)^M50) -> 0.40059378 | N46: =1/((1+$F$51)^N50) -> 0.35151808 | ... AE46: =1/((1+$F$51)^AE50) -> 0.038114169 | AF46: =1/((1+$F$51)^25) -> 0.038114169
B47: 36 | C47: DF + 0.1% | E47: +0.1% | F47: =1/((1+$F$51+0.001)^G51) -> 1 | G47: =1/((1+$F$51+0.001)^G50) -> 0.87672327 | H47: =1/((1+$F$51+0.001)^H50) -> 0.7686437 | I47: =1/((1+$F$51+0.001)^I50) -> 0.67388782 | J47: =1/((1+$F$51+0.001)^J50) -> 0.59081313 | K47: =1/((1+$F$51+0.001)^K50) -> 0.51797962 | L47: =1/((1+$F$51+0.001)^L50) -> 0.45412479 | M47: =1/((1+$F$51+0.001)^M50) -> 0.39814177 | N47: =1/((1+$F$51+0.001)^N50) -> 0.34906016 | ... AE47: =1/((1+$F$51+0.001)^AE50) -> 0.037287509 | AF47: =1/((1+$F$51)^25) -> 0.038114169
B48: 37 | C48: DF+0.5% | E48: +0.5% | F48: =1/((1+$F$51+0.005)^G51) -> 1 | G48: =1/((1+$F$51+0.005)^G50) -> 0.87365944 | H48: =1/((1+$F$51+0.005)^H50) -> 0.76328082 | I48: =1/((1+$F$51+0.005)^I50) -> 0.6668475 | J48: =1/((1+$F$51+0.005)^J50) -> 0.58259761 | K48: =1/((1+$F$51+0.005)^K50) -> 0.5089919 | L48: =1/((1+$F$51+0.005)^L50) -> 0.44468558 | M48: =1/((1+$F$51+0.005)^M50) -> 0.38850376 | N48: =1/((1+$F$51+0.005)^N50) -> 0.33941998 | ... AE48: =1/((1+$F$51+0.005)^AE50) -> 0.034162872 | AF48: =1/((1+$F$51)^25) -> 0.038114169
A50: Discount Rate | C50: Risk free rate | D50: Equity premium | E50: Firm premium | F50: Total | G50: 1 | H50: 2 | I50: 3 | J50: 4 | K50: 5 | L50: 6 | M50: 7 | N50: 8 | O50: 9 | P50: 10 | Q50: 11 | R50: 12 | S50: 13 | T50: 14 | U50: 15 | V50: 16 | W50: 17 | X50: 18 | Y50: 19 | Z50: 20 | AA50: 21 | AB50: 22 | AC50: 23 | AD50: 24 | AE50: 25
F51: =Assumptions!C587 -> 0.13961076 | G51: 0 | I51: Implied DEBT/EBITDA | K51: =K45/K12 -> 0.25461355 | L51: =L45/L12 -> 0.29220691 | M51: =M45/M12 -> 0.22784076 | N51: =N45/N12 -> 0.24279391 | O51: =O45/O12 -> 0.2419115 | P51: =P45/P12 -> 0.23138396 | Q51: =Q45/Q12 -> 0.24013612 | R51: =R45/R12 -> 0.25848465 | ... AF51: =AF45/AF12 -> 0.33932169
A53: Modelling factors | D53: Short Term | E53: Medium Term | F53: Long Term | G53: Reference (line) | I53: Cash/Operational Costs | K53: =K44/(K6-K8) -> 0.75456989 | L53: =Assumptions!$G$600 -> 0.20494459 | M53: =Assumptions!$G$600 -> 0.20494459 | N53: =Assumptions!$G$600 -> 0.20494459 | O53: =Assumptions!$G$600 -> 0.20494459 | P53: =Assumptions!$G$600 -> 0.20494459 | Q53: =Assumptions!$G$600 -> 0.20494459 | R53: =Assumptions!$G$600 -> 0.20494459 | S53: =Assumptions!$G$600 -> 0.20494459 | ... AF53: =Assumptions!$G$600 -> 0.20494459
C54: Depreciation factor | D54: =Assumptions!K302 -> -0.16 | E54: =Assumptions!L302 -> -0.15 | F54: =Assumptions!M302 -> -0.15 | G54: % Gross PPE
C55: Amortization factor | D55: =Assumptions!L316 -> -0.13 | E55: =Assumptions!$M$316 -> -0.12 | F55: =Assumptions!$M$316 -> -0.12 | G55: % Gross Intangibles | I55: Cash/Sales | K55: =K44/K6 -> 0.57491019 | L55: =L44/L6 -> 0.23707864 | M55: =M44/M6 -> 0.23301229 | N55: =N44/N6 -> 0.23708423 | O55: =O44/O6 -> 0.23423389 | P55: =P44/P6 -> 0.22814272 | Q55: =Q44/Q6 -> 0.22996552 | R55: =R44/R6 -> 0.23356437 | ... AF55: =AF44/AF6 -> 0.23969574
C56: Stock-based comp | D56: =Assumptions!C525 -> -0.05 | E56: =Assumptions!D525 -> -0.06 | F56: =Assumptions!E525 -> -0.04 | G56: % of Revenue
C57: Tax Rate | D57: =Assumptions!C365 -> -0.05 | E57: =Assumptions!D365 -> 0.02 | F57: 0.16 | G57: % EBT
C58: Interest Rate on debt | D58: =Assumptions!$F$401 -> -0.033 | E58: =Assumptions!$F$401 -> -0.033 | F58: =Assumptions!$F$401 -> -0.033 | G58: % Debt | I58: Important Note: medium-term might differ for each factor given it's specific projections. I recommend checking each one individually. | AF58: =AF44/AF6 -> 0.23969574
C59: Interest Rate on cash | D59: =Assumptions!C418 -> 0.049 | E59: =Assumptions!$D$418 -> 0.04 | F59: =Assumptions!$D$418 -> 0.04 | G59: % Cash
C60: PPE+ROA | D60: =Assumptions!S23 -> 0 | E60: =Assumptions!S23 -> 0 | F60: =Assumptions!T23 -> 0 | G60: Growing with CapEx
C61: Working capital flows | D61: =Assumptions!C509 -> -0.1 | E61: =Assumptions!D509 -> -0.07 | F61: =Assumptions!E509 -> -0.06 | G61: % of Revenue
C62: Intangible Assets | D62: =Assumptions!S25 -> 0 | E62: =Assumptions!S25 -> 0 | F62: =Assumptions!T25 -> 0 | G62: Costum growth (acq.) | O62: Sensitivity analysis | Z62: Variables
C63: Capex | D63: =Assumptions!$G$338 -> -0.023580445 | E63: =Assumptions!C340 -> -0.03 | F63: =Assumptions!I337 -> -0.03 | G63: % Revenue | O63: Tax | Z63: Discount Rate | AA63: =F51 -> 0.13961076
C64: Acquisition factor | D64: =Assumptions!$C$446 -> -0.005 | E64: =Assumptions!$C$446 -> -0.005 | F64: =Assumptions!B454 -> -0.02 | G64: % of Revenue | O64: =D76 -> 183.58063 | P64: 0.12 | Q64: =P64+1% -> 0.13 | R64: =Q64+1% -> 0.14 | S64: =R64+1% -> 0.15 | T64: =S64+1% -> 0.16 | U64: =T64+1% -> 0.17 | V64: =U64+1% -> 0.18 | W64: =V64+1% -> 0.19 | X64: =W64+1% -> 0.2 | Z64: Long-Term Tax | AA64: 0.16
C65: Dividends | D65: =Assumptions!S29 -> 0 | E65: =Assumptions!S29 -> 0 | F65: =Assumptions!T29 -> 0 | G65: % of Revenue | N65: Discount Rate | O65: 0.16961076 | P65: 272.85423 | Q65: 220.56019 | R65: 180.97088 | S65: 150.44038 | T65: 126.51896 | U65: 107.51355 | V65: 92.226084 | W65: 79.791616 | X65: 69.574799
C66: Repurchases | D66: -- | E66: -- | F66: -- | G66: Custom formula | O66: 0.15961076 | P66: 274.88873 | Q66: 222.175 | R66: 182.26828 | S66: 151.49364 | T66: 127.38176 | U66: 108.22594 | V66: 92.818434 | W66: 80.287278 | X66: 69.991935
C67: Leases | D67: 0 | E67: 0 | F67: 0 | G67: See A544 in Assumpt. | O67: 0.14961076 | P67: 276.92322 | Q67: 223.7898 | R67: 183.56568 | S67: 152.5469 | T67: 128.24455 | U67: 108.93832 | V67: 93.410784 | W67: 80.78294 | X67: 70.409071
C68: Total Debt | D68: -- | E68: -- | F68: -- | G68: Custom ratio | H68: =Assumptions!L403 -> 0.070270919 | O68: 0.13961076 | P68: 278.95771 | Q68: 225.40461 | R68: 184.86308 | S68: 153.60016 | T68: 129.10735 | U68: 109.65071 | V68: 94.003134 | W68: 81.278602 | X68: 70.826208
O69: 0.12961076 | P69: 280.9922 | Q69: 227.01941 | R69: 186.16048 | S69: 154.65342 | T69: 129.97014 | U69: 110.36309 | V69: 94.595483 | W69: 81.774264 | X69: 71.243344
A70: Valuation | D70: $ millions | F70: 2023 EV | G70: ='Multiples valuation'!$J$9 -> 276200.63 | O70: 0.11961076 | P70: 283.0267 | Q70: 228.63422 | R70: 187.45788 | S70: 155.70669 | T70: 130.83294 | U70: 111.07548 | V70: 95.187833 | W70: 82.269926 | X70: 71.66048
C71: Value of flows | D71: =SUMPRODUCT(G36:AF36,G46:AF46)+((AF44-AF45)*AF46) -> 201006.01 | E71: =D71/D73 -> 0.67742471 | O71: 0.10961076 | P71: 285.06119 | Q71: 230.24902 | R71: 188.75528 | S71: 156.75995 | T71: 131.69573 | U71: 111.78786 | V71: 95.780183 | W71: 82.765588 | X71: 72.077616
C72: Value of perpetuity | D72: =(AF35/(F51-AF5))*AF46 -> 95714.803 | E72: =D72/D73 -> 0.32257529 | F72: EV/FCF Ratio projection | G72: 2023 | H72: 2024 | I72: 2025 | J72: 2026
C73: Total Value | D73: =D71+D72 -> 296720.82 | F73: Implied EV/FCF | G73: =$G$70/(F22+F23) -> 246.38772 | H73: =$G$70/(G22+G23) -> 63.325847 | I73: =$G$70/(H22+H23) -> 49.678005 | J73: =$G$70/(I22+I23) -> 31.631907
C74: Actual share price | D74: =OP!C20 -> 78.21 | F74: Implied EV/FCF/Growth | H74: =H73/((G22+G23)/(F22+F23)-1) -> 21.906053 | I74: =I73/((H22+H23)/(G22+G23)-1) -> 180.82743 | J74: =J73/((I22+I23)/(H22+H23)-1) -> 55.445646
C75: Total value vs Mkt Cap | D75: =D76/D74-1 -> 1.3472782 | O75: Sensitivity analysis
C76: Estimated NPV per share | D76: =D73*1000000/OP!C21 -> 183.58063 | O76: Tax
O77: Implied Upside | P77: 0.12 | Q77: =P77+1% -> 0.13 | R77: =Q77+1% -> 0.14 | S77: =R77+1% -> 0.15 | T77: =S77+1% -> 0.16 | U77: =T77+1% -> 0.17 | V77: =U77+1% -> 0.18 | W77: =V77+1% -> 0.19 | X77: =W77+1% -> 0.2
A78: Sensibility | C78: Sensitivity +0.1% | D78: =(SUMPRODUCT(G36:AF36,G46:AF46)+((AF44-AF45)*AF46)+(AF35/(F51+0.001-AF5))*AF46)*1000000/OP!C21 -> 183.04525 | E78: =D78/D76-1 -> -0.0029163101 | N78: Discount Rate | O78: 0.16961076 | P78: =P65/$D$74-1 -> 2.4887384 | Q78: =Q65/$D$74-1 -> 1.8201022 | R78: =R65/$D$74-1 -> 1.3139097 | S78: =S65/$D$74-1 -> 0.92354399 | T78: =T65/$D$74-1 -> 0.61768266 | U78: =U65/$D$74-1 -> 0.37467781 | V78: =V65/$D$74-1 -> 0.1792109 | W78: =W65/$D$74-1 -> 0.020222677 | X78: =X65/$D$74-1 -> -0.11041045
C79: Sensitivity +0.5% | D79: =(SUMPRODUCT(G36:AF36,G46:AF46)+((AF44-AF45)*AF46)+(AF35/(F51+0.005-AF5))*AF46)*1000000/OP!C21 -> 180.99716 | E79: =D79/D76-1 -> -0.014072644 | O79: 0.15961076 | P79: =P66/$D$74-1 -> 2.5147516 | Q79: =Q66/$D$74-1 -> 1.8407493 | R79: =R66/$D$74-1 -> 1.3304984 | S79: =S66/$D$74-1 -> 0.93701109 | T79: =T66/$D$74-1 -> 0.62871443 | U79: =U66/$D$74-1 -> 0.38378643 | V79: =V66/$D$74-1 -> 0.18678473 | W79: =W66/$D$74-1 -> 0.026560257 | X79: =X66/$D$74-1 -> -0.10507691
O80: 0.14961076 | P80: =P67/$D$74-1 -> 2.5407648 | Q80: =Q67/$D$74-1 -> 1.8613963 | R80: =R67/$D$74-1 -> 1.3470871 | S80: =S67/$D$74-1 -> 0.95047819 | T80: =T67/$D$74-1 -> 0.63974621 | U80: =U67/$D$74-1 -> 0.39289506 | V80: =V67/$D$74-1 -> 0.19435857 | W80: =W67/$D$74-1 -> 0.032897837 | X80: =X67/$D$74-1 -> -0.099743365
A81: Notes | C81: Price where it'd be a "BUY" | D81: =D76/1.1 -> 166.89148 | O81: 0.13961076 | P81: =P68/$D$74-1 -> 2.566778 | Q81: =Q68/$D$74-1 -> 1.8820433 | R81: =R68/$D$74-1 -> 1.3636757 | S81: =S68/$D$74-1 -> 0.9639453 | T81: =T68/$D$74-1 -> 0.65077798 | U81: =U68/$D$74-1 -> 0.40200368 | V81: =V68/$D$74-1 -> 0.20193241 | W81: =W68/$D$74-1 -> 0.039235418 | X81: =X68/$D$74-1 -> -0.094409825
O82: 0.12961076 | P82: =P69/$D$74-1 -> 2.5927913 | Q82: =Q69/$D$74-1 -> 1.9026904 | R82: =R69/$D$74-1 -> 1.3802644 | S82: =S69/$D$74-1 -> 0.9774124 | T82: =T69/$D$74-1 -> 0.66180976 | U82: =U69/$D$74-1 -> 0.4111123 | V82: =V69/$D$74-1 -> 0.20950624 | W82: =W69/$D$74-1 -> 0.045572998 | X82: =X69/$D$74-1 -> -0.089076285
O83: 0.11961076 | P83: =P70/$D$74-1 -> 2.6188045 | Q83: =Q70/$D$74-1 -> 1.9233374 | R83: =R70/$D$74-1 -> 1.3968531 | S83: =S70/$D$74-1 -> 0.99087951 | T83: =T70/$D$74-1 -> 0.67284153 | U83: =U70/$D$74-1 -> 0.42022092 | V83: =V70/$D$74-1 -> 0.21708008 | W83: =W70/$D$74-1 -> 0.051910578 | X83: =X70/$D$74-1 -> -0.083742745
O84: 0.10961076 | P84: =P71/$D$74-1 -> 2.6448177 | Q84: =Q71/$D$74-1 -> 1.9439844 | R84: =R71/$D$74-1 -> 1.4134418 | S84: =S71/$D$74-1 -> 1.0043466 | T84: =T71/$D$74-1 -> 0.68387331 | U84: =U71/$D$74-1 -> 0.42932954 | V84: =V71/$D$74-1 -> 0.22465392 | W84: =W71/$D$74-1 -> 0.058248159 | X84: =X71/$D$74-1 -> -0.078409205

Sheet Inputs
E2: =1369-1315 -> 54 | G2: Figures in Millions of USD
A3: dep & amo | G3: Company | H3: #VALUE!
D4: Report in millions
A5: RESULTS | B5: 2023 | C5: =B5-1 -> 2022 | D5: =C5-1 -> 2021 | E5: =D5-1 -> 2020 | F5: =E5-1 -> 2019 | G5: =F5-1 -> 2018 | H5: =G5-1 -> 2017 | I5: =H5-1 -> 2016 | J5: =I5-1 -> 2015 | ... M5: =L5-1 -> 2012 | Q5: Hoja | R5: Nombre campo Bloomberg | T5: Cambio de signo | Z5: 2016 | AA5: 2015 | AB5: 2014 | AC5: 2013 | AD5: 2012 | AE5: 2011 | AF5: 2010 | AG5: 2009
A6: Net Sales | B6: 22680 | C6: 23601 | D6: 16434 | E6: 9763 | F6: 6731 | G6: 6475 | H6: 5253 | I6: 4272 | J6: 3991 | K6: 5506 | L6: 5299 | M6: 5422 | N6: Income Statement | O6: Sales | Q6: Ingreso | R6: Ingreso | Z6: 38537 | AA6: 47011 | AB6: 55184 | AC6: 55656 | AD6: 65875 | AE6: 60138 | AF6: 42588 | AG6: 32396
A7: Gross Profit | B7: 10460 | C7: 10603 | D7: 7929 | E7: 4347 | F7: 2868 | G7: 2447 | H7: 1787 | I7: 998 | J7: 1080 | K7: 1839 | L7: 1978 | M7: 1235 | N7: Income Statement | O7: =+A7 -> Gross Profit | Q7: Ingreso | R7: + Coste de bienes y servicios | Z7: =Z6-28044 -> 10493 | AA7: =AA6-33546 -> 13465 | AB7: =AB6-40718 -> 14466 | AC7: =AC6-40727 -> 14929 | AD7: =+AD6-47055 -> 18820 | AE7: =+AE6-43578 -> 16560 | AF7: =+AF6-30367 -> 12221 | AG7: =+AG6-23886 -> 8510
A8: Operating Income | B8: 401 | C8: 1264 | D8: 3641 | E8: 1315 | F8: 455 | G8: 439 | H8: 115 | I8: -440 | J8: -481 | K8: -216 | L8: 102 | M8: -1060 | N8: Income Statement | O8: Operating Income | Q8: Ingreso | R8: + Ventas, generales y admin | Z8: =Z7-4383 -> 6110 | AA8: =AA7-4951 -> 8514 | AB8: =AB7-6529 -> 7937 | AC8: =AC7-5547 -> 9382 | AD8: =AD7-5919-2466-797-580-485 -> 8573 | AE8: =+AE7-5203-2297-826-1081 -> 7153 | AF8: =+AF7-4248-1905-914-1191 -> 3963 | AG8: =+AG7-3645-1421-1045-1822 -> 577
A9: Other Expenses (Revenues) | B9: 8 | C9: 19 | D9: 4 | E9: 4 | F9: =-3+13 -> 10 | G9: =-5-13 -> -18 | H9: =-7+1130 -> 1123 | I9: 135 | J9: -2 | K9: -5 | L9: -2 | M9: 10 | N9: Income Statement | O9: investment income+other income expense+income loss+minority interest+non controlling interest+share onf net profit+gain8losses) on equity investments+share of result from associates nd joint ventures+non operating profit+ | Q9: Ingreso | R9: + Investigación y desarrollo | S9: + Coste de financiación de beneficio | T9: + Otro gasto operativo | U9: - Beneficio (pérdida) de filiales | V9: - Minoritarios | Z9: =1853+596+595+1904+6+8 -> 4962 | AA9: =2119+587+2023+11 -> 4740 | AB9: =2380+624+1619-8+16 -> 4631 | AC9: =2046+727+981+6+14 -> 3774 | AD9: =-14+41 -> 27 | AE9: 53 | AF9: =58+24 -> 82 | AG9: =12-68 -> -56
A10: Net Financial Cost | B10: 99 | C10: -85 | D10: 30 | E10: -39 | F10: -80 | G10: -106 | H10: -123 | I10: -153 | J10: -163 | K10: -177 | L10: -174 | M10: -167 | N10: Income Statement | O10: interest expense+financial income and expenses+other financial expense-income+interest and other net+ | Q10: Ingreso | R10: - Ingreso (pérdida) no operacional | Z10: =505+518 -> 1023 | AA10: =507-161 -> 346 | AB10: =484-322 -> 162 | AC10: =465+35 -> 500 | AD10: =467-130 -> 337 | AE10: =396+32 -> 428 | AF10: =343-130 -> 213 | AG10: =389-381 -> 8
A11: Taxes | B11: 346 | C11: 122 | D11: -513 | E11: 1210 | F11: -44 | G11: 22 | H11: -1148 | I11: -39 | J11: -14 | K11: -5 | L11: -9 | M11: 34 | N11: Income Statement | O11: Taxes | Q11: Ingreso | R11: - Gasto de impuesto a la renta (Beneficio) | Z11: 192 | AA11: 916 | AB11: 692 | AC11: 1319 | AD11: =2528 -> 2528 | AE11: =1720 -> 1720 | AF11: =968 -> 968 | AG11: =-270 -> -270
A12: Net Income | B12: 854 | C12: 1320 | D12: 3162 | E12: 2490 | F12: 341 | G12: 337 | H12: -33 | I12: -497 | J12: -660 | K12: -403 | L12: -83 | M12: -1183 | N12: Income Statement | O12: Net Income | Q12: Flujo de caja | R12: + Ingreso neto | Z12: -67 | AA12: 2512 | AB12: 2452 | AC12: 3789 | AD12: 5681 | AE12: =4928+24 -> 4952 | AF12: 2700 | AG12: 895
B13: =B28/(B6-B8) -> 0.17653396 | C13: =C28/(C6-C8) -> 0.216457 | D13: =D28/(D6-D8) -> 0.19815524 | E13: =E28/(E6-E8) -> 0.18880208 | F13: =F28/(F6-F8) -> 0.23358827 | Z13: =Z8-Z10-Z9-Z11 -> -67 | AA13: =AA8-AA10-AA9-AA11 -> 2512 | AB13: =AB8-AB10-AB9-AB11 -> 2452 | AC13: =AC8-AC10-AC9-AC11 -> 3789 | AD13: =AD8-AD10-AD9-AD11 -> 5681 | AE13: =AE8-AE10-AE9-AE11 -> 4952 | AF13: =AF8-AF10-AF9-AF11 -> 2700 | AG13: =AG8-AG10-AG9-AG11 -> 895
A14: FINANCIAL POSITION | Z14: =Z12-Z13 -> 0 | AA14: =AA12-AA13 -> 0 | AB14: =AB12-AB13 -> 0 | AC14: =AC12-AC13 -> 0 | AD14: =AD12-AD13 -> 0 | AE14: =AE12-AE13 -> 0 | AF14: =AF12-AF13 -> 0 | AG14: =AG12-AG13 -> 0
A16: Weighted Average Shares (Basic NI) | B16: 1614 | C16: 1561 | D16: 1213 | E16: 1184 | F16: 1091 | G16: 982 | H16: 952 | I16: 835 | J16: 783 | K16: 768 | L16: 754 | M16: 741
A17: Weighted Average Shares (Diluted NI) | B17: 1625 | C17: 1571 | D17: 1229 | E17: 1207 | F17: 1120 | G17: 1064 | H17: 952 | I17: 835 | J17: 783 | K17: 768 | L17: 754 | M17: 741
A19: Net gains (losses) from ForEx | B19: 31 | C19: -38 | D19: -20 | E19: 17 | F19: 8 | G19: -14 | H19: 11 | I19: 3 | J19: -1 | K19: -3 | L19: 0 | M19: 1
A20: Total Comprehensive Income | B20: 885 | C20: 1282 | D20: 3142 | E20: 2507 | F20: 349 | G20: 325 | H20: -22 | I20: -494 | J20: -663 | K20: -406 | L20: -82 | M20: -1181
A22: Changes Net Working Capital | B22: =B23-C23 -> 2331 | C22: =C23-D23 -> 2007 | D22: =D23-E23 -> -323 | E22: =E23-F23 -> 1359 | F22: =F23-G23 -> 294 | G22: =G23-H23 -> 542 | H22: =H23-I23 -> 16 | I22: =I23-J23 -> -212 | ... M22: =M23-N23 -> 319 | N22: cash flows | O22: NWC | Q22: Flujo de caja
A23: Net Working Capital | B23: =B27-B42-B28 -> 6146 | C23: =C27-C42-C28 -> 3815 | D23: =D27-D42-D28 -> 1808 | E23: =E27-E42-E28 -> 2131 | F23: =F27-F42-F28 -> 772 | G23: =G27-G42-G28 -> 478 | H23: =H27-H42-H28 -> -64 | I23: =I27-I42-I28 -> -80 | ... M23: =M27-M42-M28 -> 319
A24: 2625 | B24: 2625 | C24: 2625 | D24: 2625 | E24: 2625 | F24: 2625 | G24: 2625 | H24: 2625 | I24: 2625 | J24: 2625 | K24: 2625 | L24: 2625 | M24: 2625 | N24: 2625 | Q24: Flujo de caja | R24: + Dividendos pagados | T24: Cambiar signo | Z24: 1799 | AA24: 1757 | AB24: 1620 | AC24: 1111 | AD24: 1617 | AE24: 1159 | AF24: 1084 | AG24: 1029
A25: BALANCE SHEET | B25: 2625 | C25: 2625 | D25: 2625 | E25: 2625 | F25: 2625 | G25: 2625 | H25: 2625 | I25: 2625 | J25: 2625 | K25: 2625 | L25: 2625 | M25: 2625 | N25: 2625 | Q25: Flujo de caja | R25: + Aumento en capital | S25: + Baja en capital | T25: Cambiar signo y hacer suma | Z25: 23 | AA25: =-33+2025 -> 1992 | AB25: 3817 | AC25: 1776 | AD25: -244 | AE25: -312 | AF25: -449 | AG25: -110
A26: ASSETS | N26: 1922 | O26: 2625
A27: Current | B27: =SUM(B28:B31) -> 16768 | C27: =SUM(C28:C31) -> 15019 | D27: =SUM(D28:D31) -> 8583 | E27: =SUM(E28:E31) -> 6143 | F27: =SUM(F28:F31) -> 4597 | G27: =SUM(G28:G31) -> 3540 | H27: =SUM(H28:H31) -> 2634 | I27: =SUM(I28:I31) -> 2530 | ... M27: =SUM(M28:M31) -> 2265
A28: Cash & Eq. | B28: 3933 | C28: 4835 | D28: 2535 | E28: 1595 | F28: 1466 | G28: 1078 | H28: 1185 | I28: 1264 | J28: 785 | K28: 805 | L28: 869 | M28: 549 | N28: Balance Sheet | O28: Cash & Eq.
A29: Accounts Receivable | B29: 5376 | C29: 4128 | D29: 2706 | E29: 2066 | F29: 1859 | G29: 1235 | H29: 454 | I29: 311 | J29: 533 | K29: 818 | L29: 832 | M29: 630 | N29: Balance Sheet | O29: Accounts Receivable
A30: Inventory | B30: 4351 | C30: 3771 | D30: 1955 | E30: 1399 | F30: 982 | G30: 845 | H30: 694 | I30: 751 | J30: 678 | K30: 685 | L30: 884 | M30: 562 | N30: Balance Sheet | O30: Inventory | Q30: Balance | R30: + Efectivo, equivalentes y STI | Z30: 7168 | AA30: 6460 | AB30: 7341 | AC30: 6081 | AD30: 5490 | AE30: 3057 | AF30: 3592 | AG30: 4867
A31: Other Current Assets | B31: 3108 | C31: 2285 | D31: 1387 | E31: 1083 | F31: 290 | G31: 382 | H31: 301 | I31: 204 | J31: 324 | K31: 428 | L31: 299 | M31: 524 | N31: Balance Sheet | O31: Inventory | Q31: Balance | R31: + Cuentas y notas por cobrar | S31: + Activos derivados y de cobertura | T31: + Inversiones y cuentas por cobrar a LP | Z31: =5981+8522+1029+13556 -> 29088 | AA31: =6695+8991+1170+13651 -> 30507 | AB31: =7737+9027+1364+14644 -> 32772 | AC31: 33499 | AD31: 33911 | AE31: 31031 | AF31: 28849 | AG31: 27162
A32: Non-current | B32: =B38-B27 -> 51117 | C32: =C38-C27 -> 52561 | D32: =D38-D27 -> 3836 | E32: =E38-E27 -> 2819 | F32: =F38-F27 -> 1431 | G32: =G38-G27 -> 1016 | H32: =H38-H27 -> 918 | I32: =I38-I27 -> 791 | ... M32: =M38-M27 -> 1735
A33: Property, Plant and Equipment | B33: 1589 | C33: 1513 | D33: 702 | E33: 641 | F33: 500 | G33: 348 | H33: 261 | I33: 164 | J33: 188 | K33: 302 | L33: 346 | M33: 658 | Q33: Balance | R33: + Inventarios | Z33: 8614 | AA33: 9700 | AB33: 12205 | AC33: 12625 | AD33: 15547 | AE33: 14544 | AF33: 9587 | AG33: 6360
A34: Operating leases | B34: 633 | C34: 460 | D34: 367 | E34: 208 | F34: 205 | G34: 0 | H34: 0 | I34: 0 | J34: 0 | K34: 0 | L34: 0 | M34: 0
A35: Equity Method Investments | B35: 99 | C35: 83 | D35: 69 | E35: 63 | F35: 58 | G35: 58 | H35: 58 | I35: 59 | J35: 0 | K35: 0 | L35: 90 | M35: 181
A36: Other Non-Current Assets | B36: =B32-SUM(B33:B35) -> 48796 | C36: =C32-SUM(C33:C35) -> 50505 | D36: =D32-SUM(D33:D35) -> 2698 | E36: =E32-SUM(E33:E35) -> 1907 | F36: =F32-SUM(F33:F35) -> 668 | G36: =G32-SUM(G33:G35) -> 610 | H36: =H32-SUM(H33:H35) -> 599 | I36: =I32-SUM(I33:I35) -> 568 | ... M36: =M32-SUM(M33:M35) -> 896 | N36: Balance Sheet | O36: Property, Plant and Equipment
A37: Other Assets | B37: =B31+B36 -> 51904 | C37: =C31+C36 -> 52790 | D37: =D31+D36 -> 4085 | E37: =E31+E36 -> 2990 | F37: =F31+F36 -> 958 | G37: =G31+G36 -> 992 | H37: =H31+H36 -> 900 | I37: =I31+I36 -> 772 | ... M37: =M31+M36 -> 1420 | N37: Balance Sheet
A38: Total Assets | B38: 67885 | C38: 67580 | D38: 12419 | E38: 8962 | F38: 6028 | G38: 4556 | H38: 3552 | I38: 3321 | J38: 3084 | K38: 3767 | L38: 4337 | M38: 4000 | N38: Balance Sheet | O38: Total Assets | Q38: Balance | R38: + Propiedad, planta y equipo; neto | Z38: 15322 | AA38: 16090 | AB38: =16577 -> 16577 | AC38: 17075 | AD38: 16461 | AE38: 14395 | AF38: 12539 | AG38: 12386
N39: Balance Sheet | Z39: =Z40-SUM(Z30:Z38) -> 14512 | AA39: =AA40-SUM(AA30:AA38) -> 15585 | AB39: =AB40-SUM(AB30:AB38) -> 15786 | AC39: =AC40-SUM(AC30:AC38) -> 15616 | AD39: =AD40-SUM(AD30:AD38) -> 17947 | AE39: =AE40-SUM(AE30:AE38) -> 18419 | AF39: =AF40-SUM(AF30:AF38) -> 9453 | AG39: =AG40-SUM(AG30:AG38) -> 9263
N40: Balance Sheet | Q40: Balance | R40: Activos totales | Z40: 74704 | AA40: 78342 | AB40: 84681 | AC40: 84896 | AD40: 89356 | AE40: 81446 | AF40: 64020 | AG40: 60038
A41: LIABILITIES | N41: Balance Sheet
A42: Current Liabilities | B42: 6689 | C42: 6369 | D42: 4240 | E42: 2417 | F42: 2359 | G42: 1984 | H42: 1513 | I42: 1346 | J42: 1403 | K42: 1440 | L42: 1618 | M42: 1397 | N42: Balance Sheet | O42: Current Liabilities
A43: Payables | B43: 2418 | C43: 2956 | D43: 1406 | E43: 546 | F43: 1201 | G43: 1041 | H43: 796 | I43: 823 | J43: 524 | K43: 633 | L43: 883 | M43: 732
A44: Short-Term Debt | B44: 0 | C44: 0 | D44: 0 | E44: 0 | F44: 0 | G44: 136 | H44: 70 | I44: 0 | J44: 230 | K44: 177 | L44: 60 | M44: 0 | N44: Balance Sheet | O44: Short term Debt | Q44: Balance | R44: Pasivos totales corrientes | Z44: 26132 | AA44: 26242 | AB44: 27877 | AC44: 27297 | AD44: 29415 | AE44: =93+3895+8161+3386+2410+2691+298+1967+558+5102 -> 28561 | AF44: =204+3852+5856+2880+1670+1831+281+1521+495+3430 -> 22020 | AG44: =433+3650+2993+3351+797+1217+262+888+302+5399 -> 19292
A45: Short-Term Leases | B45: 0 | C45: 0 | D45: 0 | E45: 0 | F45: 0 | G45: 0 | H45: 0 | I45: 0 | J45: 0 | K45: 0 | L45: 0 | M45: 0
A46: Other current liabilities | B46: =B42-SUM(B43:B45) -> 4271 | C46: =C42-SUM(C43:C45) -> 3413 | D46: =D42-SUM(D43:D45) -> 2834 | E46: =E42-SUM(E43:E45) -> 1871 | F46: =F42-SUM(F43:F45) -> 1158 | G46: =G42-SUM(G43:G45) -> 807 | H46: =H42-SUM(H43:H45) -> 647 | I46: =I42-SUM(I43:I45) -> 523 | ... M46: =M42-SUM(M43:M45) -> 665 | N46: Balance Sheet | R46: + Préstamos CP | Z46: 7303 | AA46: 6967 | AB46: 4708 | AC46: 3679 | AD46: 5287 | AE46: 5660 | AF46: 3925 | AG46: 5701
A47: Non-current Liabilities | B47: =B51-B42 -> 5304 | C47: =C51-C42 -> 6461 | D47: =D51-D42 -> 682 | E47: =E51-E42 -> 708 | F47: =F51-F42 -> 842 | G47: =G51-G42 -> 1306 | H47: =H51-H42 -> 1443 | I47: =I51-I42 -> 1559 | ... M47: =M51-M42 -> 2065 | N47: Balance Sheet | O47: Total non current liabilities
A48: Long-Term Debt | B48: 1717 | C48: 2467 | D48: 1 | E48: 330 | F48: 486 | G48: 1114 | H48: 1325 | I48: 1435 | J48: 2007 | K48: 2035 | L48: 1998 | M48: 2037 | N48: Balance Sheet | O48: Long term debt | Z48: =Z44-Z46 -> 18829 | AA48: =AA44-AA46 -> 19275 | AB48: =AB44-AB46 -> 23169 | AC48: =AC44-AC46 -> 23618 | AD48: =AD44-AD46 -> 24128 | AE48: =AE44-AE46 -> 22901 | AF48: =AF44-AF46 -> 18095 | AG48: =AG44-AG46 -> 13591
A49: Long-Term Leases | B49: 535 | C49: 396 | D49: 348 | E49: 201 | F49: 199 | G49: 0 | H49: 0 | I49: 0 | J49: 0 | K49: 0 | L49: 0 | M49: 0 | Q49: Balance | R49: Pasivos totales no corrientes | Z49: =61491-Z44 -> 35359 | AA49: =63457-AA44 -> 37215 | AB49: =67855-AB44 -> 39978 | AC49: 36721 | AD49: 41973 | AE49: =8415+16529+10956+3583 -> 39483 | AF49: =4505+15932+7584+2654 -> 30675 | AG49: =5652+16195+7420+2179 -> 31446
A50: Other non-current liabilities | B50: =B47-SUM(B48:B49) -> 3052 | C50: =C47-SUM(C48:C49) -> 3598 | D50: =D47-SUM(D48:D49) -> 333 | E50: =E47-SUM(E48:E49) -> 177 | F50: =F47-SUM(F48:F49) -> 157 | G50: =G47-SUM(G48:G49) -> 192 | H50: =H47-SUM(H48:H49) -> 118 | I50: =I47-SUM(I48:I49) -> 124 | ... M50: =M47-SUM(M48:M49) -> 28 | N50: Balance Sheet | O50: Other non current Liabilities | R50: + Préstamos a largo plazo | Z50: 22818 | AA50: 25169 | AB50: 27784 | AC50: 26719 | AD50: 27752 | AE50: 24944 | AF50: 20437 | AG50: 21847
A51: Total Liabilities | B51: 11993 | C51: 12830 | D51: 4922 | E51: 3125 | F51: 3201 | G51: 3290 | H51: 2956 | I51: 2905 | J51: 3496 | K51: 3580 | L51: 3793 | M51: 3462 | N51: Balance Sheet | O51: Total Liabilities
N52: Balance Sheet | Z52: =Z49-Z50 -> 12541 | AA52: =AA49-AA50 -> 12046 | AB52: =AB49-AB50 -> 12194 | AC52: =AC49-AC50 -> 10002 | AD52: =AD49-AD50 -> 14221 | AE52: =AE49-AE50 -> 14539 | AF52: =AF49-AF50 -> 10238 | AG52: =AG49-AG50 -> 9599
N53: Balance Sheet | Z53: =+Z49+Z44 -> 61491 | AA53: =+AA49+AA44 -> 63457 | AB53: =+AB49+AB44 -> 67855 | AC53: =AC44+AC49 -> 64018 | AD53: =AD49+AD44 -> 71388 | AE53: =AE49+AE44 -> 68044 | AF53: =AF49+AF44 -> 52695 | AG53: =AG49+AG44 -> 50738
A54: Minority Interest | B54: 0 | C54: 0 | D54: 0 | E54: 0 | F54: 0 | G54: 0 | H54: 0 | I54: 0 | J54: 0 | K54: 0 | L54: 0 | M54: 0 | N54: Balance Sheet | O54: Minority Interest
N55: Balance Sheet
A56: Shareholder's Equity | B56: =B38-B51-B54 -> 55892 | C56: =C38-C51-C54 -> 54750 | D56: =D38-D51-D54 -> 7497 | E56: =E38-E51-E54 -> 5837 | F56: =F38-F51-F54 -> 2827 | G56: =G38-G51-G54 -> 1266 | H56: =H38-H51-H54 -> 596 | I56: =I38-I51-I54 -> 416 | ... M56: =M38-M51-M54 -> 538 | N56: Balance Sheet | Q56: Balance | R56: + Participación minoritaria/no dominante
A58: CASH FLOW
A59: Operating CF | B59: 1667 | C59: 3565 | D59: 3521 | E59: 1071 | F59: 493 | G59: 34 | H59: 12 | I59: 90 | J59: -226 | K59: -98 | L59: -148 | M59: -338
A60: Net Income | B60: =B12 -> 854 | C60: =C12 -> 1320 | D60: =D12 -> 3162 | E60: =E12 -> 2490 | F60: =F12 -> 341 | G60: =G12 -> 337 | H60: =H12 -> -33 | I60: =I12 -> -497 | ... M60: =M12 -> -1183
A61: Depreciation & Amortization | B61: 3453 | C61: 4174 | D61: 407 | E61: 312 | F61: 222 | G61: 170 | H61: 144 | I61: 133 | J61: 167 | K61: 203 | L61: 236 | M61: 260
A62: Changes in assets and liabilities | B62: -3049 | C62: -1846 | D62: -774 | E62: -931 | F62: -542 | G62: -727 | H62: -244 | I62: 180 | J62: 113 | K62: -291 | L62: -448 | M62: 220
A63: Other Adjustments | B63: =B59-B60-B61-B62 -> 409 | C63: =C59-C60-C61-C62 -> -83 | D63: =D59-D60-D61-D62 -> 726 | E63: =E59-E60-E61-E62 -> -800 | F63: =F59-F60-F61-F62 -> 472 | G63: =G59-G60-G61-G62 -> 254 | H63: =H59-H60-H61-H62 -> 145 | I63: =I59-I60-I61-I62 -> 274 | ... M63: =M59-M60-M61-M62 -> 365
A64: Investing CF | B64: -1423 | C64: 1999 | D64: -686 | E64: -952 | F64: -149 | G64: -170 | H64: -54 | I64: 267 | J64: 147 | K64: -12 | L64: 455 | M64: -19
A65: Net Capex | B65: -546 | C65: -450 | D65: -301 | E65: -294 | F65: -217 | G65: -163 | H65: -113 | I65: -77 | J65: -96 | K65: -95 | L65: -84 | M65: -133
A66: Investments & Acquisitions | B66: -866 | C66: 2465 | D66: -378 | E66: -658 | F66: 41 | G66: -78 | H66: 1 | I66: 342 | J66: 243 | K66: 83 | L66: 539 | M66: 123
A67: Other Inflows (Outflows) | B67: =B64-B65-B66 -> -11 | C67: =C64-C65-C66 -> -16 | D67: =D64-D65-D66 -> -7 | E67: =E64-E65-E66 -> 0 | F67: =F64-F65-F66 -> 27 | G67: =G64-G65-G66 -> 71 | H67: =H64-H65-H66 -> 58 | I67: =I64-I65-I66 -> 2 | ... M67: =M64-M65-M66 -> -9
A68: Financing CF | B68: -1146 | C68: -3264 | D68: -1895 | E68: 6 | F68: 43 | G68: 28 | H68: -33 | I68: 122 | J68: 59 | K68: 46 | L68: 13 | M68: 37
A69: Debt Borrowing | B69: 0 | C69: 991 | D69: 0 | E69: 200 | F69: 0 | G69: 0 | H69: 0 | I69: 782 | J69: 100 | K69: 0 | L69: 55 | M69: 0
A70: Debt Repayment | B70: 0 | C70: -312 | D70: 0 | E70: -200 | F70: -473 | G70: -41 | H70: -110 | I70: -1113 | J70: -44 | K70: -1115 | L70: -55 | M70: -489
A71: Lease Increases | B71: 0 | C71: 0 | D71: 0 | E71: 0 | F71: 0 | G71: 0 | H71: 0 | I71: 0 | J71: 0 | K71: 0 | L71: 0 | M71: 0
A72: Lease Payments | B72: 0 | C72: 0 | D72: 0 | E72: 0 | F72: 0 | G72: 0 | H72: 0 | I72: 0 | J72: 0 | K72: 0 | L72: 0 | M72: 0
A73: Dividends | B73: 0 | C73: 0 | D73: 0 | E73: 0 | F73: 0 | G73: 0 | H73: 0 | I73: 0 | J73: 0 | K73: 0 | L73: 0 | M73: 0 | N73: cash flows FINANCING | O73: Dividends paid
A74: Share buyback | B74: -985 | C74: -3702 | D74: -1762 | E74: 0 | F74: 0 | G74: 0 | H74: 0 | I74: 0 | J74: 0 | K74: 0 | L74: 0 | M74: 0 | N74: cash flows FINANCING | O74: =+A74 -> Share buyback
A75: Other Inflows (Outflows) | B75: =B68-B69-B70-B71-B72-B73-B74 -> -161 | C75: =C68-C69-C70-C71-C72-C73-C74 -> -241 | D75: =D68-D69-D70-D71-D72-D73-D74 -> -133 | E75: =E68-E69-E70-E71-E72-E73-E74 -> 6 | F75: =F68-F69-F70-F71-F72-F73-F74 -> 516 | G75: =G68-G69-G70-G71-G72-G73-G74 -> 69 | H75: =H68-H69-H70-H71-H72-H73-H74 -> 77 | I75: =I68-I69-I70-I71-I72-I73-I74 -> 453 | ... M75: =M68-M69-M70-M71-M72-M73-M74 -> 526
A76: FX
A77: Changes in cash | B77: =B59+B64+B68+B76 -> -902 | C77: =C59+C64+C68+C76 -> 2300 | D77: =D59+D64+D68+D76 -> 940 | E77: =E59+E64+E68+E76 -> 125 | F77: =F59+F64+F68+F76 -> 387 | G77: =G59+G64+G68+G76 -> -108 | H77: =H59+H64+H68+H76 -> -75 | I77: =I59+I64+I68+I76 -> 479 | ... M77: =M59+M64+M68+M76 -> -320
O78: (Vitalis will later fill this info)
A79: Other Data | E79: Corporate Bonds 3, 5 Y 10 | H79: Average Price | J79: Moody's | K79: YTM | L79: DIVISA
A80: Number of employees | B80: 26000 | C80: 10-K | E80: NO BONDS | N80: bloomberg
A81: Shares Outstanding (Thousands) | B81: 1615787 | C81: Yahoo finance | N81: bloomberg
A82: Float | B82: 0.9946 | C82: Yahoo finance | N82: bloomberg
A83: Insiders Own | B83: 0.0048 | C83: Yahoo finance | N83: bloomberg
A84: Fitch/ S&P Rating | B84: A- | C84: 10-K | N84: bloomberg
A85: Dividend Yield(Yahoo Finance) | B85: 0 | C85: Yahoo finance | N85: bloomberg
A86: Daily Volume in Millions of USD | B86: 74.76 | C86: Yahoo Finance | N86: bloomberg
B87: =B5 -> 2023 | C87: =C5 -> 2022 | D87: =D5 -> 2021
A88: Short % of Float | B88: 0.0204 | E88: Yahoo Finance
A89: EPS | E89: Yahoo Finance
A92: Interest Expense
A93: Derive interest rate from bonds current yields (weighted average)
Z94: 2006 | AA94: 2005 | AB94: 2005 | AC94: 2004 | AD94: 2004
Z95: 5649 | AA95: 5848 | AB95: 5848 | AC95: 5001 | AD95: 5001
Z96: -- | AA96: -- | AB96: -- | AC96: -- | AD96: --
Z97: 2856 | AA97: 3456 | AB97: 3456 | AC97: 3033 | AD97: 3033
Z98: 2793 | AA98: 2392 | AB98: 2392 | AC98: 1968 | AD98: 1968
Z99: 1140 | AA99: 1016 | AB99: 1016 | AC99: 812 | AD99: 807
Z100: 1140 | AA100: 1016 | AB100: 1016 | AC100: 812 | AD100: 807
Z101: -- | AA101: -- | AB101: -- | AC101: -- | AD101: --
Z102: -- | AA102: -- | AB102: -- | AC102: -- | AD102: --
