Workbook
Name COOLFUCNTION: _xlfn.LAMBDA(_xldudf_BOARDFLARE_EXEC("workbook-settings:coolfucntion"))
Name COOLFUCNTION: _xlfn.LAMBDA(_xldudf_BOARDFLARE_EXEC("workbook-settings:coolfucntion"))
Name COOLFUCNTION: _xlfn.LAMBDA(_xldudf_BOARDFLARE_EXEC("workbook-settings:coolfucntion"))
Name COOLFUCNTION: _xlfn.LAMBDA(_xldudf_BOARDFLARE_EXEC("workbook-settings:coolfucntion"))
Name COOLFUCNTION: _xlfn.LAMBDA(_xldudf_BOARDFLARE_EXEC("workbook-settings:coolfucntion"))
Name COOLFUCNTION: _xlfn.LAMBDA(_xldudf_BOARDFLARE_EXEC("workbook-settings:coolfucntion"))
Name COOLFUCNTION: _xlfn.LAMBDA(_xldudf_BOARDFLARE_EXEC("workbook-settings:coolfucntion"))
Name COOLFUCNTION: _xlfn.LAMBDA(_xldudf_BOARDFLARE_EXEC("workbook-settings:coolfucntion"))
Name COOLFUCNTION: _xlfn.LAMBDA(_xldudf_BOARDFLARE_EXEC("workbook-settings:coolfucntion"))
Name COOLFUCNTION: _xlfn.LAMBDA(_xldudf_BOARDFLARE_EXEC("workbook-settings:coolfucntion"))
Name Sectors: #REF!
Name Sectors: #REF!
Name Sectors: #REF!

Sheet Summary
E2: | EQUITY RESEARCH | U2: Lisbon Investment Society Equity Research
U3: April 5, 2025
D6: {=+_FV(DCF!R4,"Name")} -> ADOBE INC. | U6: Buy
D8: Adobe Inc. develops and sells software for creative design, document management, and digital marketing. Its core operations focus on subscription-based services through Creative Cloud (like Photoshop and Illustrator) and Experience Cloud for data-driven marketing. The company generates most of its revenue from digital media tools and operates globally, with a strong presence in the Americas, Europe, and Asia. | U8: EXCHANGE:(TICKER)
U9: {=+"Price (7 Mar 25): $"&_FV(DCF!$R$4,"Price")} -> Price (7 Mar 25): $365.9
D10: Investment Thesis | U10: ="Price Target: $" & ROUND(IF(Summary!G25="FCFF",DCF!Q208,IF(Summary!G25="FCFE",DCF!Q236,IF(Summary!G25="Tax Shield",DCF!#REF!,DCF!Q267))),2) &" "&IF(Summary!G25="FCFF","(FCFF)",IF(Summary!G25="FCFE","(FCFE)",IF(Summary!G25="Tax Shield","(APV)","(DDM)"))) -> Price Target: $669.54 (FCFF)
D11: Adobe Inc. is a market leader in creative and digital media software with a resilient subscription-based business model, strong free revenue generation, and growing digital solutions. The company's strategic integration of generative AI through Firefly, alongside continued expansion in Document and Experience Cloud, positions it to drive sustainable long-term growth. Despite short-term market volatility, Adobe’s innovation pipeline and pricing power support a favorable profile. | U11: =+"Upside (Downside): "&ROUND((DCF!$Q$211*100),2)&"%" -> Upside (Downside): 82.98%
U14: =+Industry!E28&", "&ESG!C9 -> USA,
U15: =+ESG!C10 -> Software Development
D17: Operating Metrics | F17: 2023 | G17: =+F17+1 -> 2024 | H17: =+G17+1 -> 2025 | I17: =+H17+1 -> 2026 | K17: Valuation Multiples | N17: 2022 | O17: =+N17+1 -> 2023 | P17: =+O17+1 -> 2024 | Q17: =+P17+1 -> 2025 | R17: =+Q17+1 -> 2026 | U17: Pedro Bordalo
K18: EV / Sales | N18: =IFERROR(_xlfn.XLOOKUP($K18,Multiples!$B:$B,Multiples!N:N),"") -> 0.66701863 | O18: =IFERROR(_xlfn.XLOOKUP($K18,Multiples!$B:$B,Multiples!O:O),"") -> 0.88313743 | P18: =IFERROR(_xlfn.XLOOKUP($K18,Multiples!$B:$B,Multiples!P:P),"") -> 9.1579614 | Q18: =IFERROR(_xlfn.XLOOKUP($K18,Multiples!$B:$B,Multiples!Q:Q),"") -> 12.668342 | R18: =IFERROR(_xlfn.XLOOKUP($K18,Multiples!$B:$B,Multiples!R:R),"") -> 12.303307
K19: Price / Sales | N19: =IFERROR(_xlfn.XLOOKUP($K19,Multiples!$B:$B,Multiples!N:N),"") -> 0.7501153 | O19: =IFERROR(_xlfn.XLOOKUP($K19,Multiples!$B:$B,Multiples!O:O),"") -> 1.076965 | P19: =IFERROR(_xlfn.XLOOKUP($K19,Multiples!$B:$B,Multiples!P:P),"") -> 9.2430579 | Q19: =IFERROR(_xlfn.XLOOKUP($K19,Multiples!$B:$B,Multiples!Q:Q),"") -> 13.509842 | R19: =IFERROR(_xlfn.XLOOKUP($K19,Multiples!$B:$B,Multiples!R:R),"") -> 13.658861
K20: EV / EBITDA | N20: =IFERROR(_xlfn.XLOOKUP($K20,Multiples!$B:$B,Multiples!N:N),"") -> 1.8984045 | O20: =IFERROR(_xlfn.XLOOKUP($K20,Multiples!$B:$B,Multiples!O:O),"") -> 2.5140532 | P20: =IFERROR(_xlfn.XLOOKUP($K20,Multiples!$B:$B,Multiples!P:P),"") -> 25.477614 | Q20: =IFERROR(_xlfn.XLOOKUP($K20,Multiples!$B:$B,Multiples!Q:Q),"") -> 22.20597 | R20: =IFERROR(_xlfn.XLOOKUP($K20,Multiples!$B:$B,Multiples!R:R),"") -> 21.35184 | U20: Patrícia Franco
K21: EV / EBIT | N21: =IFERROR(_xlfn.XLOOKUP($K21,Multiples!$B:$B,Multiples!N:N),"") -> 1.9258003 | O21: =IFERROR(_xlfn.XLOOKUP($K21,Multiples!$B:$B,Multiples!O:O),"") -> 2.8827471 | P21: =IFERROR(_xlfn.XLOOKUP($K21,Multiples!$B:$B,Multiples!P:P),"") -> 28.654439 | Q21: =IFERROR(_xlfn.XLOOKUP($K21,Multiples!$B:$B,Multiples!Q:Q),"") -> 23.694591 | R21: =IFERROR(_xlfn.XLOOKUP($K21,Multiples!$B:$B,Multiples!R:R),"") -> 23.074834
K22: Price / Earnings | N22: =IFERROR(_xlfn.XLOOKUP($K22,Multiples!$B:$B,Multiples!N:N),"") -> 2.7768146 | O22: =IFERROR(_xlfn.XLOOKUP($K22,Multiples!$B:$B,Multiples!O:O),"") -> 3.8509238 | P22: =IFERROR(_xlfn.XLOOKUP($K22,Multiples!$B:$B,Multiples!P:P),"") -> 35.750353 | Q22: =IFERROR(_xlfn.XLOOKUP($K22,Multiples!$B:$B,Multiples!Q:Q),"") -> 25.119795 | R22: =IFERROR(_xlfn.XLOOKUP($K22,Multiples!$B:$B,Multiples!R:R),"") -> 25.597311
K23: Price / Book | N23: =IFERROR(_xlfn.XLOOKUP($K23,Multiples!$B:$B,Multiples!N:N),"") -> 0.94745175 | O23: =IFERROR(_xlfn.XLOOKUP($K23,Multiples!$B:$B,Multiples!O:O),"") -> 1.2537677 | P23: =IFERROR(_xlfn.XLOOKUP($K23,Multiples!$B:$B,Multiples!P:P),"") -> 14.730396 | Q23: =IFERROR(_xlfn.XLOOKUP($K23,Multiples!$B:$B,Multiples!Q:Q),"") | R23: =IFERROR(_xlfn.XLOOKUP($K23,Multiples!$B:$B,Multiples!R:R),"") | U23: Alexandra Gonçalves
D25: Year | E25: Net Sales | F25: EBIT Margin | G25: FCFF | H25: =+IF(Summary!$G$25="FCFF",DCF!AB6,IF(Summary!$G$25="FCFE",DCF!AC6,DCF!AD6)) -> NOPAT | I25: Net Capex | K25: Profitability Ratios | N25: 2022 | O25: =+N25+1 -> 2023 | P25: =+O25+1 -> 2024 | Q25: =+P25+1 -> 2025 | R25: =+Q25+1 -> 2026
D26: 2022 | E26: =+DCF!E30 -> 17606 | F26: =+DCF!E60 -> 0.3463592 | G26: =+INDEX(DCF!X7:AA7,MATCH(Summary!$G$25,{"FCFF","FCFE","Tax Shield","Total Payout"},0)) -> 8662.8478 | H26: =+IF(Summary!$G$25="FCFF",DCF!AB7,IF(Summary!$G$25="FCFE",DCF!AC7,DCF!AD7)) -> 6076.8478 | I26: =+DCF!E134 -> -442 | K26: Return on Assets | N26: =IFERROR(_xlfn.XLOOKUP($K26,Multiples!$B:$B,Multiples!N:N),"") -> 0.17507823 | O26: =IFERROR(_xlfn.XLOOKUP($K26,Multiples!$B:$B,Multiples!O:O),"") -> 0.18215376 | P26: =IFERROR(_xlfn.XLOOKUP($K26,Multiples!$B:$B,Multiples!P:P),"") -> 0.18532098 | Q26: =IFERROR(_xlfn.XLOOKUP($K26,Multiples!$B:$B,Multiples!Q:Q),"") -> 0.25730394 | R26: =IFERROR(_xlfn.XLOOKUP($K26,Multiples!$B:$B,Multiples!R:R),"") -> 0.27311256 | U26: Manuel Jacó
D27: =+D26+1 -> 2023 | E27: =+DCF!F30 -> 19409 | F27: =+DCF!F60 -> 0.30635272 | G27: =+INDEX(DCF!X8:AA8,MATCH(Summary!$G$25,{"FCFF","FCFE","Tax Shield","Total Payout"},0)) -> 0 | H27: =+IF(Summary!$G$25="FCFF",DCF!AB8,IF(Summary!$G$25="FCFE",DCF!AC8,DCF!AD8)) -> 0 | I27: =+DCF!F134 -> -360 | K27: Return on Equity | N27: =IFERROR(_xlfn.XLOOKUP($K27,Multiples!$B:$B,Multiples!N:N),"") -> 0.34120095 | O27: =IFERROR(_xlfn.XLOOKUP($K27,Multiples!$B:$B,Multiples!O:O),"") -> 0.32557582 | P27: =IFERROR(_xlfn.XLOOKUP($K27,Multiples!$B:$B,Multiples!P:P),"") -> 0.41203498 | R27: =IFERROR(_xlfn.XLOOKUP($K27,Multiples!$B:$B,Multiples!R:R),"") -> -1.179012e-11
D28: =+D27+1 -> 2024 | E28: =+DCF!G30 -> 21505 | F28: =+DCF!G60 -> 0.31960009 | G28: =+INDEX(DCF!X9:AA9,MATCH(Summary!$G$25,{"FCFF","FCFE","Tax Shield","Total Payout"},0)) -> 9504.3855 | H28: =+IF(Summary!$G$25="FCFF",DCF!AB9,IF(Summary!$G$25="FCFE",DCF!AC9,DCF!AD9)) -> 6853.3855 | I28: =+DCF!G134 -> -183 | K28: Return on Total Capital | N28: =IFERROR(_xlfn.XLOOKUP($K28,Multiples!$B:$B,Multiples!N:N),"") -> 0.25992058 | O28: =IFERROR(_xlfn.XLOOKUP($K28,Multiples!$B:$B,Multiples!O:O),"") -> 0.22874928 | P28: =IFERROR(_xlfn.XLOOKUP($K28,Multiples!$B:$B,Multiples!P:P),"") -> 0.28201907 | Q28: =IFERROR(_xlfn.XLOOKUP($K28,Multiples!$B:$B,Multiples!Q:Q),"") -> -1.100811e-11 | R28: =IFERROR(_xlfn.XLOOKUP($K28,Multiples!$B:$B,Multiples!R:R),"") -> -1.1745971e-11
D29: =+D28+1 -> 2025 | E29: =+DCF!H30 -> 23001.039 | F29: =+DCF!H60 -> 0.53465122 | G29: =+INDEX(DCF!X10:AA10,MATCH(Summary!$G$25,{"FCFF","FCFE","Tax Shield","Total Payout"},0)) -> 17212.553 | H29: =+IF(Summary!$G$25="FCFF",DCF!AB10,IF(Summary!$G$25="FCFE",DCF!AC10,DCF!AD10)) -> 12259.462 | I29: =+DCF!H134 -> -1242.3248 | K29: EBITDA Margin | N29: =IFERROR(_xlfn.XLOOKUP($K29,Multiples!$B:$B,Multiples!N:N),"") -> 0.35135749 | O29: =IFERROR(_xlfn.XLOOKUP($K29,Multiples!$B:$B,Multiples!O:O),"") -> 0.35128033 | P29: =IFERROR(_xlfn.XLOOKUP($K29,Multiples!$B:$B,Multiples!P:P),"") -> 0.35945129 | Q29: =IFERROR(_xlfn.XLOOKUP($K29,Multiples!$B:$B,Multiples!Q:Q),"") -> 0.57049261 | R29: =IFERROR(_xlfn.XLOOKUP($K29,Multiples!$B:$B,Multiples!R:R),"") -> 0.57621766
D30: =+D29+1 -> 2026 | E30: =+DCF!I30 -> 24606.891 | F30: =+DCF!I60 -> 0.53319159 | G30: =+INDEX(DCF!X11:AA11,MATCH(Summary!$G$25,{"FCFF","FCFE","Tax Shield","Total Payout"},0)) -> 14132.394 | H30: =+IF(Summary!$G$25="FCFF",DCF!AB11,IF(Summary!$G$25="FCFE",DCF!AC11,DCF!AD11)) -> 13081.199 | I30: =+DCF!I134 -> -1333.3023 | K30: EBIT Margin | N30: =IFERROR(_xlfn.XLOOKUP($K30,Multiples!$B:$B,Multiples!N:N),"") -> 0.3463592 | O30: =IFERROR(_xlfn.XLOOKUP($K30,Multiples!$B:$B,Multiples!O:O),"") -> 0.30635272 | P30: =IFERROR(_xlfn.XLOOKUP($K30,Multiples!$B:$B,Multiples!P:P),"") -> 0.31960009 | Q30: =IFERROR(_xlfn.XLOOKUP($K30,Multiples!$B:$B,Multiples!Q:Q),"") -> 0.53465122 | R30: =IFERROR(_xlfn.XLOOKUP($K30,Multiples!$B:$B,Multiples!R:R),"") -> 0.53319159 | U30: Statistics
D31: =+D30+1 -> 2027 | E31: =+DCF!J30 -> 26330.095 | F31: =+DCF!J60 -> 0.51800526 | G31: =+INDEX(DCF!X12:AA12,MATCH(Summary!$G$25,{"FCFF","FCFE","Tax Shield","Total Payout"},0)) -> 14676.144 | H31: =+IF(Summary!$G$25="FCFF",DCF!AB12,IF(Summary!$G$25="FCFE",DCF!AC12,DCF!AD12)) -> 13598.568 | I31: =+DCF!J134 -> -1430.6334 | K31: Gross Profit Margin | N31: =IFERROR(_xlfn.XLOOKUP($K31,Multiples!$B:$B,Multiples!N:N),"") -> 0.87703056 | O31: =IFERROR(_xlfn.XLOOKUP($K31,Multiples!$B:$B,Multiples!O:O),"") -> 0.87871606 | P31: =IFERROR(_xlfn.XLOOKUP($K31,Multiples!$B:$B,Multiples!P:P),"") -> 0.88198093 | Q31: =IFERROR(_xlfn.XLOOKUP($K31,Multiples!$B:$B,Multiples!Q:Q),"") -> 0.87924252 | R31: =IFERROR(_xlfn.XLOOKUP($K31,Multiples!$B:$B,Multiples!R:R),"") -> 0.87997984 | U31: Beta | V31: =Peers!D73 -> 1.4977
D32: =+D31+1 -> 2028 | E32: =+DCF!K30 -> 28178.877 | F32: =+DCF!K60 -> 0.51876899 | G32: =+INDEX(DCF!X13:AA13,MATCH(Summary!$G$25,{"FCFF","FCFE","Tax Shield","Total Payout"},0)) -> 17527.7 | H32: =+IF(Summary!$G$25="FCFF",DCF!AB13,IF(Summary!$G$25="FCFE",DCF!AC13,DCF!AD13)) -> 14574.271 | I32: =+DCF!K134 -> -1535.0696 | K32: SG&A Margin | N32: =IFERROR(_xlfn.XLOOKUP($K32,Multiples!$B:$B,Multiples!N:N),"") -> 0.29364989 | O32: =IFERROR(_xlfn.XLOOKUP($K32,Multiples!$B:$B,Multiples!O:O),"") -> 0.34849812 | P32: =IFERROR(_xlfn.XLOOKUP($K32,Multiples!$B:$B,Multiples!P:P),"") -> 0.26803069 | Q32: =IFERROR(_xlfn.XLOOKUP($K32,Multiples!$B:$B,Multiples!Q:Q),"") -> 0.17 | R32: =IFERROR(_xlfn.XLOOKUP($K32,Multiples!$B:$B,Multiples!R:R),"") -> 0.26217627 | U32: % Float | V32: 0.1277
D33: =+D32+1 -> 2029 | E33: =+DCF!L30 -> 30162.063 | F33: =+DCF!L60 -> 0.51435356 | G33: =+INDEX(DCF!X14:AA14,MATCH(Summary!$G$25,{"FCFF","FCFE","Tax Shield","Total Payout"},0)) -> 17742.679 | H33: =+IF(Summary!$G$25="FCFF",DCF!AB14,IF(Summary!$G$25="FCFE",DCF!AC14,DCF!AD14)) -> 15467.633 | I33: =+DCF!L134 -> -1647.1297 | K33: Net Income Margin | N33: =IFERROR(_xlfn.XLOOKUP($K33,Multiples!$B:$B,Multiples!N:N),"") -> 0.27013518 | O33: =IFERROR(_xlfn.XLOOKUP($K33,Multiples!$B:$B,Multiples!O:O),"") -> 0.27966407 | P33: =IFERROR(_xlfn.XLOOKUP($K33,Multiples!$B:$B,Multiples!P:P),"") -> 0.25854452 | Q33: =IFERROR(_xlfn.XLOOKUP($K33,Multiples!$B:$B,Multiples!Q:Q),"") -> 0.53781657 | R33: =IFERROR(_xlfn.XLOOKUP($K33,Multiples!$B:$B,Multiples!R:R),"") -> 0.53360529 | U33: % Held by Insiders | V33: 0.0023
U34: % Held by Institutions | V34: 0.87
D35: SWOT Analysis | K35: Liquidity Ratios | N35: 2022 | O35: =+N35+1 -> 2023 | P35: =+O35+1 -> 2024 | Q35: =+P35+1 -> 2025 | R35: =+Q35+1 -> 2026 | U35: Short % of Float | V35: 0.0189
D36: Strengths | G36: Weaknesses | K36: Cash Ratio | N36: =IFERROR(_xlfn.XLOOKUP($K36,Multiples!$B:$B,Multiples!N:N),"") -> 0.52116142 | O36: =IFERROR(_xlfn.XLOOKUP($K36,Multiples!$B:$B,Multiples!O:O),"") -> 0.86547085 | P36: =IFERROR(_xlfn.XLOOKUP($K36,Multiples!$B:$B,Multiples!P:P),"") -> 0.72360042 | Q36: =IFERROR(_xlfn.XLOOKUP($K36,Multiples!$B:$B,Multiples!Q:Q),"") -> 1.7122454 | R36: =IFERROR(_xlfn.XLOOKUP($K36,Multiples!$B:$B,Multiples!R:R),"") -> 2.6823803 | W36: 120.87
D37: Market Leadership: The company is a market leader Financial Health: Srong debt management Subscription revenue: Sucessfully transitioned to subscription-based models. Strong profitability performance. | G37: High prices: Software complexity: | K37: Quick Ratio | N37: =IFERROR(_xlfn.XLOOKUP($K37,Multiples!$B:$B,Multiples!N:N),"") -> 1.00406 | O37: =IFERROR(_xlfn.XLOOKUP($K37,Multiples!$B:$B,Multiples!O:O),"") -> 1.2199733 | P37: =IFERROR(_xlfn.XLOOKUP($K37,Multiples!$B:$B,Multiples!P:P),"") -> 0.94648798 | Q37: =IFERROR(_xlfn.XLOOKUP($K37,Multiples!$B:$B,Multiples!Q:Q),"") -> 1.9056776 | R37: =IFERROR(_xlfn.XLOOKUP($K37,Multiples!$B:$B,Multiples!R:R),"") -> 2.8835673 | U37: Major Holders | W37: 113.63
K38: Current Ratio | N38: =IFERROR(_xlfn.XLOOKUP($K38,Multiples!$B:$B,Multiples!N:N),"") -> 1.1067913 | O38: =IFERROR(_xlfn.XLOOKUP($K38,Multiples!$B:$B,Multiples!O:O),"") -> 1.3433523 | P38: =IFERROR(_xlfn.XLOOKUP($K38,Multiples!$B:$B,Multiples!P:P),"") -> 1.0675791 | Q38: =IFERROR(_xlfn.XLOOKUP($K38,Multiples!$B:$B,Multiples!Q:Q),"") -> 1.9829281 | R38: =IFERROR(_xlfn.XLOOKUP($K38,Multiples!$B:$B,Multiples!R:R),"") -> 1.9829281 | U38: Vanguard Group | V38: 0.0961
U39: Blackrock Inc. | V39: 0.095
D40: Opportunities | G40: Threats | K40: Cash Flow Ratios | N40: 2022 | O40: =+N40+1 -> 2023 | P40: =+O40+1 -> 2024 | Q40: =+P40+1 -> 2025 | R40: =+Q40+1 -> 2026 | U40: State Street Corp. | V40: 0.0482
D41: Strenghtening mobile ecossystem: Importance of the digital world in real world applications is rising. Leveraging AI: for example, to reduce complexity of the programs Emerging needs of digital content: more diverse income streams in the digital world. | G41: Intense competition: Cybersecurity risks: Fast technological changes in the industry: The software industry is one of the most fast paced industries. | K41: Cash Conversion Cycle | N41: =IFERROR(_xlfn.XLOOKUP($K41,Multiples!$B:$B,Multiples!N:N),"") -> 34.953425 | O41: =IFERROR(_xlfn.XLOOKUP($K41,Multiples!$B:$B,Multiples!O:O),"") -> 35.918904 | P41: =IFERROR(_xlfn.XLOOKUP($K41,Multiples!$B:$B,Multiples!P:P),"") -> 29.040456 | Q41: =IFERROR(_xlfn.XLOOKUP($K41,Multiples!$B:$B,Multiples!Q:Q),"") -> -14.914648 | R41: =IFERROR(_xlfn.XLOOKUP($K41,Multiples!$B:$B,Multiples!R:R),"") -> -12.857737 | U41: Geode Capital | V41: 0.0251
K42: Net Income / Op Cash Flow | N42: =IFERROR(_xlfn.XLOOKUP($K42,Multiples!$B:$B,Multiples!N:N),"") -> 0.60678745 | O42: =IFERROR(_xlfn.XLOOKUP($K42,Multiples!$B:$B,Multiples!O:O),"") -> 0.74335798 | P42: =IFERROR(_xlfn.XLOOKUP($K42,Multiples!$B:$B,Multiples!P:P),"") -> 0.69016882 | Q42: =IFERROR(_xlfn.XLOOKUP($K42,Multiples!$B:$B,Multiples!Q:Q),"") -> 0.67885256 | R42: =IFERROR(_xlfn.XLOOKUP($K42,Multiples!$B:$B,Multiples!R:R),"") -> 0.87362437 | U42: Morgan Stanley | V42: 0.0195
K43: Chg in Cash / Op Cash Flow | N43: =IFERROR(_xlfn.XLOOKUP($K43,Multiples!$B:$B,Multiples!N:N),"") -> 0.050012758 | O43: =IFERROR(_xlfn.XLOOKUP($K43,Multiples!$B:$B,Multiples!O:O),"") -> 0.39783621 | P43: =IFERROR(_xlfn.XLOOKUP($K43,Multiples!$B:$B,Multiples!P:P),"") -> 0.058589871 | Q43: =IFERROR(_xlfn.XLOOKUP($K43,Multiples!$B:$B,Multiples!Q:Q),"") -> 0.93826075 | R43: =IFERROR(_xlfn.XLOOKUP($K43,Multiples!$B:$B,Multiples!R:R),"") -> 0.93152295 | U43: FMR | V43: 0.018
U44: NORGES BANK | V44: 0.0135
D45: Revenue by Region | G45: Revenue by Segment | K45: Leverage Ratios | N45: 2022 | O45: =+N45+1 -> 2023 | P45: =+O45+1 -> 2024 | Q45: =+P45+1 -> 2025 | R45: =+Q45+1 -> 2026 | U45: Bank of New York Mellon C. | V45: 0.0134
K46: Total Debt / Equity | N46: =IFERROR(_xlfn.XLOOKUP($K46,Multiples!$B:$B,Multiples!N:N),"") -> 332.37678 | O46: =IFERROR(_xlfn.XLOOKUP($K46,Multiples!$B:$B,Multiples!O:O),"") -> 244.72169 | P46: =IFERROR(_xlfn.XLOOKUP($K46,Multiples!$B:$B,Multiples!P:P),"") -> 448.79206 | Q46: =IFERROR(_xlfn.XLOOKUP($K46,Multiples!$B:$B,Multiples!Q:Q),"") -> -5.4378501e-12 | R46: =IFERROR(_xlfn.XLOOKUP($K46,Multiples!$B:$B,Multiples!R:R),"") -> -5.5458283e-12 | U46: Primecap Management | V46: 0.0129
K47: Total Debt / Capital | N47: =IFERROR(_xlfn.XLOOKUP($K47,Multiples!$B:$B,Multiples!N:N),"") -> 0.99700039 | O47: =IFERROR(_xlfn.XLOOKUP($K47,Multiples!$B:$B,Multiples!O:O),"") -> 0.99593036 | P47: =IFERROR(_xlfn.XLOOKUP($K47,Multiples!$B:$B,Multiples!P:P),"") -> 0.99777675 | Q47: =IFERROR(_xlfn.XLOOKUP($K47,Multiples!$B:$B,Multiples!Q:Q),"") -> -5.4378501e-12 | R47: =IFERROR(_xlfn.XLOOKUP($K47,Multiples!$B:$B,Multiples!R:R),"") -> -5.5458283e-12 | U47: UBS AM | V47: 0.0125
K48: Total Liabilities / Total Assets | N48: =IFERROR(_xlfn.XLOOKUP($K48,Multiples!$B:$B,Multiples!N:N),"") -> 0.4868765 | O48: =IFERROR(_xlfn.XLOOKUP($K48,Multiples!$B:$B,Multiples!O:O),"") -> 0.44051814 | P48: =IFERROR(_xlfn.XLOOKUP($K48,Multiples!$B:$B,Multiples!P:P),"") -> 0.55022998 | Q48: =IFERROR(_xlfn.XLOOKUP($K48,Multiples!$B:$B,Multiples!Q:Q),"") -> 2.3164527e+10 | R48: =IFERROR(_xlfn.XLOOKUP($K48,Multiples!$B:$B,Multiples!R:R),"") -> 2.3164527e+10
K49: Total Debt / EBITDA | N49: =IFERROR(_xlfn.XLOOKUP($K49,Multiples!$B:$B,Multiples!N:N),"") -> 0.74894924 | O49: =IFERROR(_xlfn.XLOOKUP($K49,Multiples!$B:$B,Multiples!O:O),"") -> 0.59841596 | P49: =IFERROR(_xlfn.XLOOKUP($K49,Multiples!$B:$B,Multiples!P:P),"") -> 0.78344114 | Q49: =IFERROR(_xlfn.XLOOKUP($K49,Multiples!$B:$B,Multiples!Q:Q),"") -> 0.46151772 | R49: =IFERROR(_xlfn.XLOOKUP($K49,Multiples!$B:$B,Multiples!R:R),"") -> 0.43559386 | U49: Board of Directors
K50: Total Debt / (EBITDA - Capex) | N50: =IFERROR(_xlfn.XLOOKUP($K50,Multiples!$B:$B,Multiples!N:N),"") -> 0.80658078 | O50: =IFERROR(_xlfn.XLOOKUP($K50,Multiples!$B:$B,Multiples!O:O),"") -> 0.63177454 | P50: =IFERROR(_xlfn.XLOOKUP($K50,Multiples!$B:$B,Multiples!P:P),"") -> 0.80243805 | Q50: =IFERROR(_xlfn.XLOOKUP($K50,Multiples!$B:$B,Multiples!Q:Q),"") -> 0.50978155 | R50: =IFERROR(_xlfn.XLOOKUP($K50,Multiples!$B:$B,Multiples!R:R),"") -> 0.48080601 | U50: S.Narayen (CEO 2007, Chairman 2017)[Non-Ind] C.Amon ( [Indep.], Comp.) A.Banse ( Nom. & Gov)[Indep.] B.Biggs Audit [Indep.] M.Boulden Comp.[Indep.] F.Calderoni [Indep.] Gov.Chair L.Desmond Comp., Chair Nom.,Gov.[Indep.] S.Neumann Audit [Indep.] K.Oberg Gov., Chair Audit D.Pandey Audit, Indep. D.Ricks Comp.[Indep]
K51: Net Debt / EBITDA | N51: =IFERROR(_xlfn.XLOOKUP($K50,Multiples!$B:$B,Multiples!N:N),"") -> 0.80658078 | O51: =IFERROR(_xlfn.XLOOKUP($K50,Multiples!$B:$B,Multiples!O:O),"") -> 0.63177454 | P51: =IFERROR(_xlfn.XLOOKUP($K50,Multiples!$B:$B,Multiples!P:P),"") -> 0.80243805 | Q51: =IFERROR(_xlfn.XLOOKUP($K50,Multiples!$B:$B,Multiples!Q:Q),"") -> 0.50978155 | R51: =IFERROR(_xlfn.XLOOKUP($K50,Multiples!$B:$B,Multiples!R:R),"") -> 0.48080601
K53: Solvency Ratios | N53: 2022 | O53: =+N53+1 -> 2023 | P53: =+O53+1 -> 2024 | Q53: =+P53+1 -> 2025 | R53: =+Q53+1 -> 2026
K54: EBIT / Interest Expense | N54: =IFERROR(_xlfn.XLOOKUP($K54,Multiples!$B:$B,Multiples!N:N),"") -> 54.446429 | O54: =IFERROR(_xlfn.XLOOKUP($K54,Multiples!$B:$B,Multiples!O:O),"") -> 52.619469 | P54: =IFERROR(_xlfn.XLOOKUP($K54,Multiples!$B:$B,Multiples!P:P),"") -> 40.668639 | Q54: =IFERROR(_xlfn.XLOOKUP($K54,Multiples!$B:$B,Multiples!Q:Q),"") -> N/A | R54: =IFERROR(_xlfn.XLOOKUP($K54,Multiples!$B:$B,Multiples!R:R),"") -> N/A
K55: EBITDA / Interest Expense | N55: =IFERROR(_xlfn.XLOOKUP($K55,Multiples!$B:$B,Multiples!N:N),"") -> 55.232143 | O55: =IFERROR(_xlfn.XLOOKUP($K55,Multiples!$B:$B,Multiples!O:O),"") -> 60.336283 | P55: =IFERROR(_xlfn.XLOOKUP($K55,Multiples!$B:$B,Multiples!P:P),"") -> 45.739645 | Q55: =IFERROR(_xlfn.XLOOKUP($K55,Multiples!$B:$B,Multiples!Q:Q),"") -> N/A | R55: =IFERROR(_xlfn.XLOOKUP($K55,Multiples!$B:$B,Multiples!R:R),"") -> N/A
K56: (EBITDA - Capex) / Interest Expense | N56: =IFERROR(_xlfn.XLOOKUP($K56,Multiples!$B:$B,Multiples!N:N),"") -> 59.178571 | O56: =IFERROR(_xlfn.XLOOKUP($K56,Multiples!$B:$B,Multiples!O:O),"") -> 63.522124 | P56: =IFERROR(_xlfn.XLOOKUP($K56,Multiples!$B:$B,Multiples!P:P),"") -> 46.822485 | Q56: =IFERROR(_xlfn.XLOOKUP($K56,Multiples!$B:$B,Multiples!Q:Q),"") -> N/A | R56: =IFERROR(_xlfn.XLOOKUP($K56,Multiples!$B:$B,Multiples!R:R),"") -> N/A
D58: Debt Schedule | K58: Stock Performance
U60: ESG Traffic Light
U61: LSEG ESG Score | V61: =ESG!C14 -> 68
U62: E-Score | V62: =ESG!C15 -> 75
U63: S-Score | V63: =ESG!C16 -> 77
U64: G-Score | V64: =ESG!C17 -> 59
U65: S&P Global ESG Score | V65: =ESG!C18 -> 55
U66: Environmental | V66: =ESG!C19 -> 66
U67: Social | V67: =ESG!C20 -> 45
U68: Governance & Economic | V68: =ESG!C21 -> 63
U69: Sustainalytics | V69: =ESG!C22 -> 14.2
U70: ISS ESG Corporate Rating | V70: =ESG!C23 -> B
U71: SDG Impact Rating | V71: =ESG!C24 -> 4.7
U72: Governance Quality Score | V72: =ESG!C25 -> 2
U73: MSCI ESG Ratings | V73: =ESG!C26 -> 0
U75: Disclaimer: This material has been prepared solely for educational and informational purposes, based on information available to the general public and from sources considered reliable. This research is part of the activities of the Lisbon Investment Society (LIS). It does not constitute, and should not be interpreted as, investment advice, financial advice, or a recommendation to buy or sell any financial instruments. The views expressed are those of the authors and do not necessarily reflect the official position of LIS. The authors assume no responsibility for the accuracy of the information provided, neither should anything contained herein be taken as an indication that any result will be achieved. Investors should conduct their own research and consult with qualified financial advisors before making any investment decisions.
D80: Extra Notes
D82: Debt Schedule

Sheet Segments
B2: Segments
B4: Regions | D4: Weight | E4: 2020 | F4: =+E4+1 -> 2021 | G4: =+F4+1 -> 2022 | H4: =+G4+1 -> 2023 | I4: =+H4+1 -> 2024 | J4: ="CAGR "&$G$4&" - "&$I$4 -> CAGR 2022 - 2024 | K4: 2021 | L4: =+K4+1 -> 2022 | M4: =+L4+1 -> 2023 | N4: =+M4+1 -> 2024
B6: North and South America | D6: =IFERROR(I6/SUM($I$6:$I$12),"") -> 0.59944199 | G6: 10251 | H6: 11654 | I6: 12891 | J6: =IFERROR((I6/G6)^(1/COUNT($G$4:$I$4))-1,"") -> 0.079377742 | L6: =IFERROR(G6-F6/F6,"") | M6: =IFERROR((H6-G6)/G6,"") -> 0.1368647 | N6: =IFERROR((I6-H6)/H6,"") -> 0.10614381
B7: APAC | D7: =IFERROR(I7/SUM($I$6:$I$12),"") -> 0.14229249 | G7: 2762 | H7: 2874 | I7: 3060 | J7: =IFERROR((I7/G7)^(1/COUNT($G$4:$I$4))-1,"") -> 0.034743207 | L7: =IFERROR(G7-F7/F7,"") | M7: =IFERROR((H7-G7)/G7,"") -> 0.040550326 | N7: =IFERROR((I7-H7)/H7,"") -> 0.064718163
B8: EMEA | D8: =IFERROR(I8/SUM($I$6:$I$12),"") -> 0.25826552 | G8: 4593 | H8: 4881 | I8: 5554 | J8: =IFERROR((I8/G8)^(1/COUNT($G$4:$I$4))-1,"") -> 0.065376575 | L8: =IFERROR(G8-F8/F8,"") | M8: =IFERROR((H8-G8)/G8,"") -> 0.062704115 | N8: =IFERROR((I8-H8)/H8,"") -> 0.13788158
J9: =IFERROR((I9/E9)^(1/COUNT($E$4:$I$4))-1,"") | L9: =IFERROR(G9-F9/F9,"") | M9: =IFERROR(H9-G9/G9,"") | N9: =IFERROR((I9-H9)/H9,"")
J10: =IFERROR((I10/E10)^(1/COUNT($E$4:$I$4))-1,"") | K10: =IFERROR(F10-E10/E10,"") | L10: =IFERROR(G10-F10/F10,"") | M10: =IFERROR(H10-G10/G10,"") | N10: =IFERROR((I10-H10)/H10,"")
B13: Total | D13: =SUM(D6:D12) -> 1 | E13: =SUM(E6:E10) -> 0 | F13: =SUM(F6:F10) -> 0 | G13: =SUM(G6:G10) -> 17606 | H13: =SUM(H6:H10) -> 19409 | I13: =SUM(I6:I10) -> 21505 | J13: =IFERROR((I13/G13)^(1/COUNT($G$4:$I$4))-1,"") -> 0.068955394 | K13: =IFERROR(F13-E13/E13,"") | L13: =IFERROR(G13-F13/F13,"") | M13: =IFERROR((H13-G13)/G13,"") -> 0.10240827 | N13: =IFERROR((I13-H13)/H13,"") -> 0.10799114
B15: Segments | D15: Weight | E15: 2020 | F15: =+E15+1 -> 2021 | G15: =+F15+1 -> 2022 | H15: =+G15+1 -> 2023 | I15: =+H15+1 -> 2024 | J15: ="CAGR "&$E$4&" - "&$I$4 -> CAGR 2020 - 2024 | K15: 2021 | L15: =+K15+1 -> 2022 | M15: =+L15+1 -> 2023 | N15: =+M15+1 -> 2024
B17: Digital Media | D17: =IFERROR(I17/SUM($I$17:$I$21),"") -> 0.73768891 | G17: 12842 | H17: 14216 | I17: 15864 | J17: =IFERROR((I17/G17)^(1/COUNT($G$4:$I$4))-1,"") -> 0.072984245 | K17: =IFERROR((F17-E17)/E17,"") | L17: =IFERROR((G17-F17)/F17,"") | M17: =IFERROR((H17-G17)/G17,"") -> 0.10699268 | N17: =IFERROR((I17-H17)/H17,"") -> 0.11592572
B18: Digital Experience | D18: =IFERROR(I18/SUM($I$17:$I$21),"") -> 0.24952337 | G18: 4422 | H18: 4893 | I18: 5366 | J18: =IFERROR((I18/G18)^(1/COUNT($G$4:$I$4))-1,"") -> 0.066622261 | K18: =IFERROR((F18-E18)/E18,"") | L18: =IFERROR((G18-F18)/F18,"") | M18: =IFERROR((H18-G18)/G18,"") -> 0.10651289 | N18: =IFERROR((I18-H18)/H18,"") -> 0.09666871
B19: Publishing & Advertising | D19: =IFERROR(I19/SUM($I$17:$I$21),"") -> 0.012787724 | G19: 342 | H19: 300 | I19: 275 | J19: =IFERROR((I19/G19)^(1/COUNT($G$4:$I$4))-1,"") -> -0.070101538 | K19: =IFERROR((F19-E19)/E19,"") | L19: =IFERROR((G19-F19)/F19,"") | M19: =IFERROR((H19-G19)/G19,"") -> -0.12280702 | N19: =IFERROR((I19-H19)/H19,"") -> -0.083333333
J20: =IFERROR((I20/E20)^(1/COUNT($E$4:$I$4))-1,"") | K20: =IFERROR((F20-E20)/E20,"") | L20: =IFERROR((G20-F20)/F20,"") | M20: =IFERROR((H20-G20)/G20,"") | N20: =IFERROR((I20-H20)/H20,"")
J21: =IFERROR((I21/E21)^(1/COUNT($E$4:$I$4))-1,"") | K21: =IFERROR((F21-E21)/E21,"") | L21: =IFERROR((G21-F21)/F21,"") | M21: =IFERROR((H21-G21)/G21,"") | N21: =IFERROR((I21-H21)/H21,"")
B22: Total | D22: =SUM(D17:D21) -> 1 | E22: =SUM(E17:E21) -> 0 | F22: =SUM(F17:F21) -> 0 | G22: =SUM(G17:G21) -> 17606 | H22: =SUM(H17:H21) -> 19409 | I22: =SUM(I17:I21) -> 21505 | J22: =IFERROR((I22/E22)^(1/COUNT($E$4:$I$4))-1,"") | K22: =IFERROR((F22-E22)/E22,"") | L22: =IFERROR((G22-F22)/F22,"") | M22: =IFERROR((H22-G22)/G22,"") -> 0.10240827 | N22: =IFERROR((I22-H22)/H22,"") -> 0.10799114
B24: Categories | D24: Description | J24: Graphs
B26: Content management | D26: Adobe offers enterprise-level content management through Adobe Experience Manager, which enables organizations to efficiently manage and deliver personalized digital content across web, mobile, and other platforms. It integrates seamlessly with Adobe’s creative and data platforms, helping brands deliver cohesive customer experiences.
B27: Creativity and Design | D27: Adobe’s Creativity and Design category, primarily delivered through Creative Cloud, includes industry-leading tools for graphic design, photography, video editing, illustration, 3D content, and generative AI. These applications empower individuals, teams, and enterprises to produce compelling digital content across platforms and formats.
B28: Data and analytics | D28: Adobe’s Data and Analytics solutions, offered through Adobe Experience Cloud, help businesses collect, analyze, and activate real-time customer data to deliver personalized digital experiences. These tools enable marketers and analysts to drive insights and optimize customer journeys at scale.
B29: =IF(B20=0,"",B20)
B30: =IF(B21=0,"",B21)
B31: Campaign management | D31: Adobe’s Campaign Management tools, led by Adobe Campaign, empower brands to design, orchestrate, and deliver personalized cross-channel marketing campaigns. These solutions enable marketers to automate messaging across email, mobile, web, and offline channels, optimizing engagement and customer lifecycle strategies.
B32: Document Productivity | D32: Adobe’s Document Productivity solutions, delivered through Adobe Document Cloud, streamline the creation, editing, sharing, and signing of digital documents. Powered by Adobe Acrobat and Adobe Sign, these tools help individuals and businesses accelerate workflows, reduce paperwork, and ensure secure, compliant document handling across devices.
B33: Workflow management | D33: This segment derives its revenue from software solutions that help enterprises streamline, coordinate, and automate work processes across teams. Adobe’s workflow management capabilities are primarily delivered through tools such as Adobe Workfront, enabling companies to plan projects, manage digital content workflows, and collaborate efficiently across marketing and creative departments.
B35: Products | D35: Weight | E35: 2020 | F35: =+E35+1 -> 2021 | G35: =+F35+1 -> 2022 | H35: =+G35+1 -> 2023 | I35: =+H35+1 -> 2024 | J35: =I35+1 -> 2025 | K35: =+J35+1 -> 2026 | L35: =+K35+1 -> 2027 | M35: =+L35+1 -> 2028 | N35: =+M35+1 -> 2029 | O35: =+N35+1 -> 2030 | P35: =+O35+1 -> 2031 | Q35: =+P35+1 -> 2032 | R35: =+Q35+1 -> 2033 | ... T35: =+S35+1 -> 2035
B37: Creative Cloud | D37: =I37/I$40 -> 0.79942007 | G37: 10459 | H37: 11517 | I37: 12682
B38: Document Cloud | D38: =I38/I$40 -> 0.20057993 | G38: 2383 | H38: 2699 | I38: 3182
B40: Total | D40: =SUM(D37:D39) -> 1 | E40: =SUM(E37:E39) -> 0 | F40: =SUM(F37:F39) -> 0 | G40: =SUM(G37:G39) -> 12842 | H40: =SUM(H37:H39) -> 14216 | I40: =SUM(I37:I39) -> 15864 | J40: =SUM(J37:J39) -> 0 | K40: =SUM(K37:K39) -> 0 | ... T40: =SUM(T37:T39) -> 0
B42: Company's Strategy / Extra Notes
B44: Dividends | E44: Adobe does not anticipate paying any cash dividends in the foreseeable future.
B45: Expansion | D45: Adobe is expanding product accessibility in regions like Southeast Asia, Latin America, and Africa through localized pricing, web-based tools, and mobile-first solutions.
B46: AI Investment | D46: The company’s flagship generative AI tool, trained on licensed and public domain content. It powers features like: Text-to-image generation Generative fill (Photoshop) Text-to-vector (Illustrator) Video extension and editing tools (Premiere Pro)

Sheet Industry
J1: Média
B2: Industry Overview | G2: =G11/F11-1 -> 0.097186701 | H2: =H11/G11-1 -> 0.1013986 | I2: =I11/H11-1 -> 0.076895944 | J2: =SUM(G2:I2)/3 -> 0.091827082
B4: Sales Growth Forecast | E4: Weight | F4: 2025 | G4: =+F4+1 -> 2026 | H4: =+G4+1 -> 2027 | I4: =+H4+1 -> 2028 | J4: =+I4+1 -> 2029 | K4: =+J4+1 -> 2030 | L4: =+K4+1 -> 2031 | M4: =+L4+1 -> 2032 | N4: =+M4+1 -> 2033 | ... P4: =+O4+1 -> 2035 | Q4: ="CAGR "&$F$4&" - "&$P$4 -> CAGR 2025 - 2035 | R4: Sources
B6: Digital Media | E6: =Segments!D17 -> 0.73768891 | F6: 17306.182 | G6: 18988.113 | H6: 20913.481 | I6: 22521.642 | J6: =I6*(1+$J$2) -> 24589.739 | K6: =J6*(1+$J$2) -> 26847.743 | L6: =K6*(1+$J$2) -> 29313.093 | M6: =L6*(1+$J$2) -> 32004.829 | N6: =M6*(1+$J$2) -> 34943.739 | O6: =N6*(1+$J$2) -> 38152.52 | P6: =O6*(1+$J$2) -> 41655.955 | Q6: =IFERROR((P6/F6)^(1/COUNT($F$4:$P$4))-1,"") -> 0.083127597 | R6: https://elite.finviz.com/quote.ashx?t=ADBE&p=m&ty=ea
B7: Digital Experience | E7: =Segments!D18 -> 0.24952337 | F7: 5853.8182 | G7: 6422.7315 | H7: 7073.9874 | I7: 7617.9484 | J7: =I7*(1+$J$2) -> 8317.4824 | K7: =J7*(1+$J$2) -> 9081.2525 | L7: =K7*(1+$J$2) -> 9915.1574 | M7: =L7*(1+$J$2) -> 10825.637 | N7: =M7*(1+$J$2) -> 11819.724 | O7: =N7*(1+$J$2) -> 12905.095 | P7: =O7*(1+$J$2) -> 14090.132 | Q7: =IFERROR((P7/F7)^(1/COUNT($F$4:$P$4))-1,"") -> 0.083127597
B8: Publishing & Advertising | E8: =Segments!D19 -> 0.012787724 | F8: 300 | G8: 329.15601 | H8: 362.53197 | I8: 390.40921 | J8: =I8*(1+$J$2) -> 426.25935 | K8: =J8*(1+$J$2) -> 465.4015 | L8: =K8*(1+$J$2) -> 508.13796 | M8: =L8*(1+$J$2) -> 554.79878 | N8: =M8*(1+$J$2) -> 605.74434 | O8: =N8*(1+$J$2) -> 661.36807 | P8: =O8*(1+$J$2) -> 722.09957 | Q8: =IFERROR((P8/F8)^(1/COUNT($F$4:$P$4))-1,"") -> 0.083127597
Q9: =IFERROR((P9/F9)^(1/COUNT($F$4:$P$4))-1,"")
D10: Total | Q10: =IFERROR((P10/F10)^(1/COUNT($F$4:$P$4))-1,"")
B11: Weighted Average | E11: =SUM(E6:E10) -> 1 | F11: =SUM(F6:F10) -> 23460 | G11: =SUM(G6:G10) -> 25740 | H11: =SUM(H6:H10) -> 28350 | I11: =SUM(I6:I10) -> 30530 | J11: =SUM(J6:J10) -> 33333.481 | K11: =SUM(K6:K10) -> 36394.397 | L11: =SUM(L6:L10) -> 39736.388 | ... P11: =SUM(P6:P10) -> 56468.187 | Q11: =IFERROR((P11/F11)^(1/COUNT($F$4:$P$4))-1,"") -> 0.083127597
B13: Key Drivers | E13: Description
B15: Creative Cloud Dominance | E15: Adobe's Creative Cloud (Photoshop, Illustrator, Premiere Pro, etc.) continues to be its core revenue engine. Subscriptions provide a recurring revenue model with high margins. The dominance in creative industries (design, video editing, digital media) gives Adobe a near-monopoly in many niches
B16: Digital Experience & Marketing Cloud | E16: Adobe's enterprise tools for data-driven marketing, AI personalization, and customer analytics are gaining traction. Competes with Salesforce and Oracle in this space. More businesses are investing in customer experience platforms, which boosts Adobe’s position.
B17: Strong Brand & Ecosystem Lock-in | E17: High brand loyalty + steep learning curves = low churn. Many users are deeply embedded in the Adobe ecosystem, making switching expensive or impractical.
B18: Global Expansion & Education Sector | E18: Growth in emerging markets and widespread adoption in schools/universities builds long-term user loyalty.
B20: Industry Trends | E20: Description
B22: Rise of the Creator Economy | E22: Millions of individuals now earn income as creators — from YouTubers and TikTokers to freelancers and educators which increases the demand for Adobe Creative Cloud tools like Photoshop, Premiere Pro, Illustrator, and Adobe Express.
B23: Shift Toward Paperless, Digital Workflows | E23: Remote work, regulatory compliance, and ESG goals are pushing businesses to digitize forms, contracts, and approvals. Supports growth of Adobe Document Cloud (Acrobat and Adobe Sign).
B25: Emerging Market Expansion | E25: Adobe is expanding product accessibility in regions like Southeast Asia, Latin America, and Africa through localized pricing, web-based tools, and mobile-first solutions. Growth opportunity for Adobe Express and mobile Acrobat.
B26: Market Share | E26: Headquarters | G26: Revenues | H26: (in MM of USD) | I26: Market Share
B28: =Peers!D91 -> #VALUE! | E28: USA | G28: {=TRANSPOSE(Peers!D97:N97)} -> 21505 | I28: =IFERROR(G28/$G$40,"") -> 0.053883603
B29: #VALUE! | G29: 37895 | I29: =IFERROR(G29/$G$40,"") -> 0.094950902
B30: #VALUE! | G30: 16285 | I30: =IFERROR(G30/$G$40,"") -> 0.040804207
B31: #VALUE! | G31: 8446 | I31: =IFERROR(G31/$G$40,"") -> 0.021162563
B32: #VALUE! | G32: 2684 | I32: =IFERROR(G32/$G$40,"") -> 0.0067251147
B33: #VALUE! | G33: 2628 | I33: =IFERROR(G33/$G$40,"") -> 0.0065847993
B34: #VALUE! | G34: 35543.04 | I34: =IFERROR(G34/$G$40,"") -> 0.089057757
B35: #VALUE! | G35: 10984 | I35: =IFERROR(G35/$G$40,"") -> 0.027521855
B36: #VALUE! | G36: 6131 | I36: =IFERROR(G36/$G$40,"") -> 0.015362026
B37: #VALUE! | G37: 3626 | I37: =IFERROR(G37/$G$40,"") -> 0.0090854195
B38: #VALUE! | G38: 4359 | I38: =IFERROR(G38/$G$40,"") -> 0.010922047
B39: Others | E39: -- | G39: =G40-SUM(G28:G38) -> 249014.96 | I39: =IFERROR(G39/$G$40,"") -> 0.6239397
B40: Industry Size | E40: -- | G40: 399101 | I40: =SUM(I28:I39) -> 1
B42: Porter's Five Forces Analysis | E42: Rating | H42: Graph
B44: Threat of New Entrants | E44: =IFERROR(AVERAGE(E45:E50),"") -> 1.8333333
B45: Economies of scale | E45: 2
B46: Product differentiation | E46: 2
B47: Capital requirements | E47: 2
B48: Access to distribution channels | E48: 2
B49: Regulations | E49: 1
B50: Switching costs | E50: 2
B51: Bargaining Power of Suppliers | E51: =IFERROR(AVERAGE(E52:E56),"") -> 2.2
B52: Number of suppliers | E52: 3
B53: Uniqueness | E53: 3
B54: Switching Costs | E54: 2
B55: Forward Integration | E55: 1
B56: Industry Importance | E56: 2
B57: Bargaining Power of Customers | E57: =IFERROR(AVERAGE(E58:E62),"") -> 2.2
B58: Number of buyers | E58: 1
B59: Purchase size | E59: 2
B60: Switching costs | E60: 2
B61: Price sensitivity | E61: 3
B62: Informed buyers | E62: 3
B63: Competitive Rivalry | E63: =IFERROR(AVERAGE(E64:E68),"") -> 2.2
B64: Number of competitors | E64: 4
B65: Industry growth | E65: 1
B66: Similarities in what's offered | E66: 1
B67: Exit barriers | E67: 2
B68: Fixed costs | E68: 3
B69: Threat of Substitutes | E69: =IFERROR(AVERAGE(E70:E74),"") -> 2.25
B70: Relative price performance | E70: 3
B71: Customer willingness to go elsewhere | E71: 2
B72: The sense that products are similar | E72: 2
B73: Availability of close substitutes | E73: 2

Sheet Peers
Q2: Market Cap
D3: Revenue Growth | F3: EBITDA Margin | H3: Profit Margin | J3: EV / Revenue | L3: EV / EBITDA | N3: Price / Earnings
B4: Peers | C4: Ticker | D4: =+Inputs!O4&"-"&Inputs!P4 -> 2022-2023 | E4: =+Inputs!P4&"-"&Inputs!Q4 -> 2023-2024 | F4: 2023 | G4: 2024 | H4: =+Inputs!O4&"-"&Inputs!P4 -> 2022-2023 | I4: =+Inputs!P4&"-"&Inputs!Q4 -> 2023-2024 | J4: 2023 | K4: 2024 | L4: 2023 | M4: 2024 | N4: 2023 | O4: 2024
A6: =+D91 -> #VALUE! | B6: {=IFERROR(_FV(A6,"Name"),"")} -> ADOBE INC. | C6: {=IFERROR(_FV(A6,"Ticker symbol",TRUE),"")} -> ADBE | D6: =IFERROR(D94/D93-1,"") -> 0.10240827 | E6: =IFERROR(D97/D94-1,"") -> 0.10799114 | F6: =IFERROR(D95/D94,"") -> 0.35128033 | G6: =IFERROR(D100/D97,"") -> 0.35945129 | H6: =IFERROR(D96/D94,"") -> 0.27966407 | I6: =IFERROR(D105/D97,"") -> 0.25854452 | J6: {=IFERROR((_FV(A6,"Market cap",TRUE)/1000000+D$121-D$111)/D$94,"")} -> 7.9168324 | K6: {=IFERROR((_FV(A6,"Market cap",TRUE)/1000000+D$121-D$111)/D$97,"")} -> 7.1452127 | L6: {=+IFERROR((_FV(A6,"Market cap",TRUE)/1000000+D$121-D$111)/D$95,"")} -> 22.537078 | M6: {=IFERROR((_FV(A6,"Market cap",TRUE)/1000000+D$121-D$111)/D$100,"")} -> 19.878111 | N6: {=IFERROR((_FV(A6,"Market cap",TRUE)/1000000)/D$96,"")} -> 28.59521 | O6: {=IFERROR((_FV(A6,"Market cap",TRUE)/1000000)/D$105,"")} -> 27.916331 | Q6: 150005000
A7: =+E91 -> #VALUE! | B7: {=IFERROR(_FV(A7,"Nome"),"")} -> SALESFORCE, INC. | C7: CRM | D7: =+IFERROR(E94/E93-1,"") -> 0.1117951 | E7: =IFERROR(E97/E94-1,"") -> 0.087156095 | F7: =IFERROR(E95/E94,"") -> 0.2856815 | G7: =+IFERROR(E100/E97,"") -> 0.29404935 | H7: =IFERROR(E96/E94,"") -> 0.11865622 | I7: =+IFERROR(E105/E97,"") -> 0.16353081 | J7: =+IFERROR((Q7/1000000+E$121-E$111)/E$94,"") -> 6.9786557 | K7: =IFERROR(+(Q7/1000000+E$121-E$111)/E$97,"") -> 6.4191846 | L7: =IFERROR(+(Q7/1000000+E$121-E$111)/E$95,"") -> 24.428098 | M7: =IFERROR(+(Q7/1000000+E$121-E$111)/E$100,"") -> 21.830297 | N7: =IFERROR(+(Q7/1000000)/E$96,"") -> 58.198985 | O7: =IFERROR(+(Q7/1000000)/E$105,"") -> 38.84315 | Q7: 240711000000
A8: =+F91 -> #VALUE! | B8: {=IFERROR(_FV(A8,"Nome"),"")} -> INTUIT INC. | C8: INTU | D8: =IFERROR(F94/F93-1,"") -> 0.12902719 | E8: =IFERROR(+F97/F94-1,"") -> 0.13342149 | F8: =IFERROR(F95/F94,"") -> 0.2813892 | G8: =IFERROR(F100/F97,"") -> 0.28130181 | H8: =IFERROR(F96/F94,"") -> 0.16592428 | I8: =+IFERROR(F105/F97,"") -> 0.18194658 | J8: =+IFERROR((Q8/1000000+E$121-E$111)/E$94,"") -> 4.8534584 | K8: =IFERROR(+(Q8/1000000+E$121-E$111)/E$97,"") -> 4.4643621 | L8: =IFERROR(+(Q8/1000000+E$121-E$111)/E$95,"") -> 16.989054 | M8: =IFERROR(+(Q8/1000000+E$121-E$111)/E$100,"") -> 15.182357 | N8: =IFERROR(+(Q8/1000000)/E$96,"") -> 40.288443 | O8: =IFERROR(+(Q8/1000000)/E$105,"") -> 26.889301 | Q8: 166633000000
A9: =+G91 -> #VALUE! | B9: {=IFERROR(_FV(A9,"Nome"),"")} -> WORKDAY, INC. | C9: WDAY | D9: =+IFERROR(G94/G93-1,"") -> 0.16779279 | E9: =IFERROR(G97/G94-1,"") -> 0.16352115 | F9: =IFERROR(G95/G94,"") -> 0.10359554 | G9: =IFERROR(G100/G97,"") -> 0.12763438 | H9: =IFERROR(G96/G94,"") -> 0.19024659 | I9: =+IFERROR(G105/G97,"") -> 0.062278001 | J9: =+IFERROR((Q9/1000000+E$121-E$111)/E$94,"") -> 1.788995 | K9: =IFERROR(+(Q9/1000000+E$121-E$111)/E$97,"") -> 1.6455733 | L9: =IFERROR(+(Q9/1000000+E$121-E$111)/E$95,"") -> 6.2622012 | M9: =IFERROR(+(Q9/1000000+E$121-E$111)/E$100,"") -> 5.5962488 | N9: =IFERROR(+(Q9/1000000)/E$96,"") -> 14.462041 | O9: =IFERROR(+(Q9/1000000)/E$105,"") -> 9.6522511 | Q9: 59815000000
A10: =+H91 -> #VALUE! | B10: {=IFERROR(_FV(A10,"Nome"),"")} -> DATADOG, INC. | C10: DDOG | D10: =IFERROR(H94/H93-1,"") -> 0.27044776 | E10: =IFERROR(H97/H94-1,"") -> 0.2612782 | F10: =IFERROR(H95/H94,"") -> 0.052161654 | G10: =IFERROR(H100/H97,"") -> 0.099105812 | H10: =IFERROR(H96/H94,"") -> 0.022556391 | I10: =+IFERROR(H105/H97,"") -> 0.068554396 | J10: =+IFERROR((Q10/1000000+E$121-E$111)/E$94,"") -> 1.0100123 | K10: =IFERROR(+(Q10/1000000+E$121-E$111)/E$97,"") -> 0.92904077 | L10: =IFERROR(+(Q10/1000000+E$121-E$111)/E$95,"") -> 3.5354489 | M10: =IFERROR(+(Q10/1000000+E$121-E$111)/E$100,"") -> 3.1594723 | N10: =IFERROR(+(Q10/1000000)/E$96,"") -> 7.8970019 | O10: =IFERROR(+(Q10/1000000)/E$105,"") -> 5.2706148 | Q10: 32662000000
A11: =+I91 -> #VALUE! | B11: {=IFERROR(_FV(A11,"Nome"),"")} -> HUBSPOT, INC. | C11: HUBS | D11: =+IFERROR(I94/I93-1,"") -> 0.25361063 | E11: =IFERROR(I97/I94-1,"") -> 0.21105991 | F11: =IFERROR(I95/I94,"") -> -0.034101382 | G11: =IFERROR(I100/I97,"") -> 0.049086758 | H11: =IFERROR(I96/I94,"") -> -0.076036866 | I11: =+IFERROR(I105/I97,"") -> 0.0019025875 | J11: =+IFERROR((Q11/1000000+E$121-E$111)/E$94,"") -> 0.91978656 | K11: =IFERROR(+(Q11/1000000+E$121-E$111)/E$97,"") -> 0.84604829 | L11: =IFERROR(+(Q11/1000000+E$121-E$111)/E$95,"") -> 3.2196224 | M11: =IFERROR(+(Q11/1000000+E$121-E$111)/E$100,"") -> 2.8772323 | N11: =IFERROR(+(Q11/1000000)/E$96,"") -> 7.1366054 | O11: =IFERROR(+(Q11/1000000)/E$105,"") -> 4.7631112 | Q11: 29517000000
A12: =+J91 -> #VALUE! | B12: {=IFERROR(_FV(A12,"Nome"),"")} -> Sap Se | C12: SAP | D12: =IFERROR(J94/J93-1,"") -> 0.086824168 | E12: =IFERROR(J97/J94-1,"") -> 0.035404061 | F12: =IFERROR(J95/J94,"") -> 0.24039478 | G12: =IFERROR(J100/J97,"") -> 0.1893434 | H12: =IFERROR(J96/J94,"") -> 0.10010575 | I12: =+IFERROR(J105/J97,"") -> 0.091409176 | J12: =+IFERROR((Q12/1000000+E$121-E$111)/E$94,"") -> 9.3438047 | K12: =IFERROR(+(Q12/1000000+E$121-E$111)/E$97,"") -> 8.5947223 | L12: =IFERROR(+(Q12/1000000+E$121-E$111)/E$95,"") -> 32.70707 | M12: =IFERROR(+(Q12/1000000+E$121-E$111)/E$100,"") -> 29.228843 | N12: =IFERROR(+(Q12/1000000)/E$96,"") -> 78.13177 | O12: =IFERROR(+(Q12/1000000)/E$105,"") -> 52.146684 | Q12: 323153000000
A13: =+K91 -> #VALUE! | B13: {=IFERROR(_FV(A13,"Nome"),"")} -> SERVICENOW, INC. | C13: NOW | D13: =IFERROR(K94/K93-1,"") -> 0.23823326 | E13: =IFERROR(K97/K94-1,"") -> 0.2243897 | F13: =+IFERROR(K95/K94,"") -> 0.17768365 | G13: =IFERROR(K100/K97,"") -> 0.21167152 | H13: =IFERROR(K96/K94,"") -> 0.19295508 | I13: =+IFERROR(K105/K97,"") -> 0.12973416 | J13: =+IFERROR((Q13/1000000+E$121-E$111)/E$94,"") -> 1.6889004 | K13: =IFERROR(+(Q13/1000000+E$121-E$111)/E$97,"") -> 1.5535031 | L13: =IFERROR(+(Q13/1000000+E$121-E$111)/E$95,"") -> 5.9118297 | M13: =IFERROR(+(Q13/1000000+E$121-E$111)/E$100,"") -> 5.2831374 | N13: =IFERROR(+(Q13/1000000)/E$96,"") -> 13.618472 | O13: =IFERROR(+(Q13/1000000)/E$105,"") -> 9.0892367 | Q13: 56326000000
A14: =+L91 -> #VALUE! | B14: {=IFERROR(_FV(A14,"Nome"),"")} -> AUTODESK, INC. | C14: ADSK | D14: =IFERROR(K94/K93-1,"") -> 0.23823326 | E14: =IFERROR(L97/L94-1,"") -> 0.11533564 | F14: =IFERROR(L95/L94,"") -> 0.22175732 | G14: =IFERROR(L100/L97,"") -> 0.25265046 | H14: =IFERROR(L96/L94,"") -> 0.16481717 | I14: =+IFERROR(L105/L97,"") -> 0.18137335 | J14: =+IFERROR((Q14/1000000+E$121-E$111)/E$94,"") -> 4.8993029 | K14: =IFERROR(+(Q14/1000000+E$121-E$111)/E$97,"") -> 4.5065312 | L14: =IFERROR(+(Q14/1000000+E$121-E$111)/E$95,"") -> 17.149528 | M14: =IFERROR(+(Q14/1000000+E$121-E$111)/E$100,"") -> 15.325765 | N14: =IFERROR(+(Q14/1000000)/E$96,"") -> 40.674807 | O14: =IFERROR(+(Q14/1000000)/E$105,"") -> 27.147168 | Q14: 168231000000
A15: =+M91 -> #VALUE! | B15: {=IFERROR(_FV(A15,"Nome"),"")} -> SNOWFLAKE INC. | C15: SNOW | D15: =IFERROR(M94/M93-1,"") -> 0.35818006 | E15: =IFERROR(M97/M94-1,"") -> 0.29223093 | F15: =IFERROR(M95/M94,"") -> -0.25980043 | G15: =IFERROR(M100/M97,"") -> -0.30336459 | H15: =IFERROR(M96/M94,"") -> -0.297933 | I15: =+IFERROR(M105/M97,"") -> -0.34721456 | J15: =+IFERROR((Q15/1000000+E$121-E$111)/E$94,"") -> 1.4856987 | K15: =IFERROR(+(Q15/1000000+E$121-E$111)/E$97,"") -> 1.3665919 | L15: =IFERROR(+(Q15/1000000+E$121-E$111)/E$95,"") -> 5.2005423 | M15: =IFERROR(+(Q15/1000000+E$121-E$111)/E$100,"") -> 4.6474917 | N15: =IFERROR(+(Q15/1000000)/E$96,"") -> 11.905948 | O15: =IFERROR(+(Q15/1000000)/E$105,"") -> 7.9462643 | Q15: 49243000000
A16: =+N91 -> #VALUE! | B16: {=IFERROR(_FV(A16,"Nome"),"")} -> ATLASSIAN CORPORATION | C16: TEAM | D16: =IFERROR(N94/N93-1,"") -> 0.26150553 | E16: =IFERROR(N97/N94-1,"") -> 0.23274887 | F16: =IFERROR(N95/N94,"") -> -0.056561086 | G16: =IFERROR(N100/N97,"") -> 0.0061940812 | H16: =IFERROR(N96/N94,"") -> -0.085124434 | I16: =+IFERROR(N105/N97,"") -> -0.069052535 | J16: =+IFERROR((Q16/1000000+E$121-E$111)/E$94,"") -> 1.638437 | K16: =IFERROR(+(Q16/1000000+E$121-E$111)/E$97,"") -> 1.5070854 | L16: =IFERROR(+(Q16/1000000+E$121-E$111)/E$95,"") -> 5.7351878 | M16: =IFERROR(+(Q16/1000000+E$121-E$111)/E$100,"") -> 5.1252804 | N16: =IFERROR(+(Q16/1000000)/E$96,"") -> 13.193182 | O16: =IFERROR(+(Q16/1000000)/E$105,"") -> 8.8053897 | Q16: 54567000000
B17: Average | C17: {=IFERROR(_FV(A17,"Ticker symbol",TRUE),"")} | D17: =IFERROR(AVERAGE(D6:D16),"") -> 0.20164164 | E17: =IFERROR(AVERAGE(E6:E16),"") -> 0.16950338 | F17: =IFERROR(AVERAGE(F6:F16),"") -> 0.12395283 | G17: =IFERROR(AVERAGE(G6:G16),"") -> 0.14246584 | H17: =IFERROR(AVERAGE(H6:H16),"") -> 0.070530114 | I17: =IFERROR(AVERAGE(I6:I16),"") -> 0.065727862 | J17: =IFERROR(AVERAGE(J6:J16),"") -> 3.8658076 | K17: =IFERROR(AVERAGE(K6:K16),"") -> 3.5434414 | ... O17: =IFERROR(AVERAGE(O6:O16),"") -> 19.860864
B18: Deviation from Average | D18: =IFERROR(+D17-D6,"") -> 0.099233369 | E18: =IFERROR(E17-E6,"") -> 0.061512242 | F18: =+IFERROR(F17-F6,"") -> -0.22732751 | G18: =IFERROR(G17-G6,"") -> -0.21698545 | H18: =IFERROR(+H6-H17,"") -> 0.20913396 | I18: =+IFERROR(I6-I17,"") -> 0.19281666 | J18: =+IFERROR(J6-J17,"") -> 4.0510248 | K18: =+IFERROR(K6-K17,"") -> 3.6017713 | L18: =IFERROR(+L6-L17,"") -> 9.4756547 | M18: =IFERROR(M6-M17,"") -> 8.2295443 | N18: =IFERROR(+N6-N17,"") -> 0.040440621 | O18: =IFERROR(+O6-O17,"") -> 8.0554671
D20: Trading Multiple | G20: Net | H20: Preferred | I20: Non-Controlling | J20: Equity Value | M20: Implied Upside (Downside)
B21: Implied Share Price | D21: Revenue | E21: EBITDA | F21: P/E | G21: Debt | H21: Stock | I21: Interest | J21: Revenue | K21: EBITDA | L21: P/E | M21: Revenue | N21: EBITDA | O21: P/E | Q21: Current Price
B23: Second Minimum | D23: =IFERROR(SMALL(K6:K16,2),"") -> 0.92904077 | E23: =IFERROR(SMALL(M6:M16,2),"") -> 3.1594723 | F23: =IFERROR(SMALL(O6:O16,2),"") -> 5.2706148 | G23: =-Inputs!$Q$99+Inputs!$Q$100 -> -1830 | H23: =+Inputs!$Q$101 -> 0 | I23: =+Inputs!$Q$102 -> 0 | J23: =IFERROR(+D23*$D$97+G23+H23+I23,"") -> 18149.022 | K23: =IFERROR(E23*$D$100+G23+H23+I23,"") -> 22592.721 | L23: =IFERROR(F23*$D$105,"") -> 29304.618 | M23: {=IFERROR(+(J23/_FV($A$6,"Shares outstanding",TRUE)*1000000)/$Q$23-1,"")} -> -0.88307156 | N23: {=IFERROR((+K23/_FV($A$6,"Shares outstanding",TRUE)*1000000)/$Q$23-1,"")} -> -0.85444221 | O23: {=IFERROR(+(L23/_FV($A$6,"Shares outstanding",TRUE)*1000000)/$Q$23-1,"")} -> -0.81119956 | Q23: {=+_FV(A6,"Price")} -> 365.9
B24: Average | D24: =+IFERROR(AVERAGE(K6:K16),"") -> 3.5434414 | E24: =IFERROR(+AVERAGE(M6:M16),"") -> 11.648567 | F24: =IFERROR(+AVERAGE(O6:O16),"") -> 19.860864 | G24: =-Inputs!$Q$99+Inputs!$Q$100 -> -1830 | H24: =+Inputs!$Q$101 -> 0 | I24: =+Inputs!$Q$102 -> 0 | J24: =IFERROR(+D24*$D$97+G24+H24+I24,"") -> 74371.708 | K24: =IFERROR(E24*$D$100+G24+H24+I24,"") -> 88213.422 | L24: =IFERROR(+F24*$D$105,"") -> 110426.4 | M24: {=IFERROR(+(J24/_FV($A$6,"Shares outstanding",TRUE)*1000000)/$Q$23-1,"")} -> -0.52084648 | N24: {=IFERROR((+K24/_FV($A$6,"Shares outstanding",TRUE)*1000000)/$Q$23-1,"")} -> -0.43166867 | O24: {=IFERROR(+(L24/_FV($A$6,"Shares outstanding",TRUE)*1000000)/$Q$23-1,"")} -> -0.28855743
B25: Median | D25: =IFERROR(MEDIAN(K6:K16),"") -> 1.6455733 | E25: =IFERROR(MEDIAN(M6:M16),"") -> 5.5962488 | F25: =IFERROR(MEDIAN(O6:O16),"") -> 9.6522511 | G25: =-Inputs!$Q$99+Inputs!$Q$100 -> -1830 | H25: =+Inputs!$Q$101 -> 0 | I25: =+Inputs!$Q$102 -> 0 | J25: =IFERROR(D25*$D$97+G25+H25+I25,"") -> 33558.054 | K25: =IFERROR(E25*$D$100+G25+H25+I25,"") -> 41429.003 | L25: =IFERROR(+F25*$D$105,"") -> 53666.516 | M25: {=IFERROR(+(J25/_FV($A$6,"Shares outstanding",TRUE)*1000000)/$Q$23-1,"")} -> -0.78379602 | N25: {=IFERROR((+K25/_FV($A$6,"Shares outstanding",TRUE)*1000000)/$Q$23-1,"")} -> -0.73308597 | O25: {=+IFERROR((L25/_FV($A$6,"Shares outstanding",TRUE)*1000000)/$Q$23-1,"")} -> -0.65424352
B26: Second Maximum | D26: =IFERROR(LARGE(K6:K16,2),"") -> 7.1452127 | E26: =IFERROR(LARGE(M6:M16,2),"") -> 21.830297 | F26: =IFERROR(LARGE(O6:O16,2),"") -> 38.84315 | G26: =-Inputs!$Q$99+Inputs!$Q$100 -> -1830 | H26: =+Inputs!$Q$101 -> 0 | I26: =+Inputs!$Q$102 -> 0 | J26: =IFERROR(+D26*$D$97+G26+H26+I26,"") -> 151827.8 | K26: =IFERROR(E26*$D$100+G26+H26+I26,"") -> 166918.2 | L26: =IFERROR(+F26*$D$105,"") -> 215967.91 | M26: {=IFERROR(+(J26/_FV($A$6,"Shares outstanding",TRUE)*1000000)/$Q$23-1,"")} -> -0.021821247 | N26: {=IFERROR((+K26/_FV($A$6,"Shares outstanding",TRUE)*1000000)/$Q$23-1,"")} -> 0.075401429 | O26: {=IFERROR(+(L26/_FV($A$6,"Shares outstanding",TRUE)*1000000)/$Q$23-1,"")} -> 0.39141333
B28: Profitability | D28: =+LEFT(B6, FIND(" ", B6 & " ") - 1) -> ADOBE | E28: =+LEFT(B7, FIND(" ", B7 & " ") - 1) -> SALESFORCE, | F28: =+LEFT(B8, FIND(" ", B8 & " ") - 1) -> INTUIT | G28: =+LEFT(B9, FIND(" ", B9 & " ") - 1) -> WORKDAY, | H28: =+LEFT(B10, FIND(" ", B10 & " ") - 1) -> DATADOG, | I28: =+LEFT(B11, FIND(" ", B11 & " ") - 1) -> HUBSPOT, | J28: =B12 -> Sap Se | K28: =+LEFT(B13, FIND(" ", B13 & " ") - 1) -> SERVICENOW, | L28: =+LEFT(B14, FIND(" ", B14 & " ") - 1) -> AUTODESK, | M28: =+LEFT(B15, FIND(" ", B15 & " ") - 1) -> SNOWFLAKE | N28: =+LEFT(B16, FIND(" ", B16 & " ") - 1) -> ATLASSIAN | O28: Average
B30: Operating Margin | D30: =IFERROR(D101/D97,"") -> 0.31960009 | E30: =IFERROR(E101/E97,"") -> 0.20229582 | F30: =IFERROR(F101/F97,"") -> 0.23807185 | G30: =IFERROR(G101/G97,"") -> 0.08903623 | H30: =IFERROR(H101/H97,"") -> 0.078614009 | I30: =IFERROR(I101/I97,"") -> 0.01217656 | J30: =IFERROR(J101/J97,"") -> 0.15189022 | K30: =IFERROR(K101/K97,"") -> 0.16032411 | ... N30: =IFERROR(N101/N97,"") -> -0.026841019 | O30: =IFERROR(+AVERAGE(D30:N30),"") -> 0.099536517
B31: Net Income Margin | D31: =IFERROR(D105/D97,"") -> 0.25854452 | E31: =IFERROR(E105/E97,"") -> 0.16353081 | F31: =IFERROR(F105/F97,"") -> 0.18194658 | G31: =IFERROR(G105/G97,"") -> 0.062278001 | H31: =IFERROR(H105/H97,"") -> 0.068554396 | I31: =IFERROR(I105/I97,"") -> 0.0019025875 | J31: =IFERROR(J105/J97,"") -> 0.091409176 | K31: =IFERROR(K105/K97,"") -> 0.12973416 | ... N31: =IFERROR(N105/N97,"") -> -0.069052535 | O31: =IFERROR(+AVERAGE(D31:N31),"") -> 0.065727862
B32: ROA (%) | D32: =IFERROR(D105/D117,"") -> 0.18532098 | E32: =IFERROR(E105/E117,"") -> 0.060207135 | F32: =IFERROR(F105/F117,"") -> 0.09221337 | G32: =IFERROR(G105/G117,"") -> 0.02925961 | H32: =IFERROR(H105/H117,"") -> 0.031806396 | I32: =IFERROR(I105/I117,"") -> 0.001317176 | J32: =IFERROR(J105/J117,"") -> 0.042146731 | K32: =IFERROR(K105/K117,"") -> 0.069911201 | ... N32: =IFERROR(N105/N117,"") -> -0.057751343 | O32: =IFERROR(+AVERAGE(D32:N32),"") -> 0.037974378
B33: Financial Cost of Debt | D33: =IFERROR(+(D102/D121)*(1-(D104/D103)),"") -> -0.022783554 | E33: =IFERROR(+(E102/E121)*(1-(E104/E103)),"") -> 0 | F33: =IFERROR(+(F102/F121)*(1-(F104/F103)),"") -> 0.012074242 | G33: =IFERROR(+(G102/G121)*(1-(G104/G103)),"") -> 0.057873448 | H33: =IFERROR(+(H102/H121)*(1-(H104/H103)),"") -> 0.072470248 | I33: =IFERROR(+(I102/I121)*(1-(I104/I103)),"") -> 0.018282805 | J33: =IFERROR(+(J102/J121)*(1-(J104/J103)),"") -> 0.014216212 | K33: =IFERROR(+(K102/K121)*(1-(K104/K103)),"") -> 0.14253009 | ... N33: =IFERROR(+(N102/N121)*(1-(N104/N103)),"") -> 0.17802477 | O33: =IFERROR(+AVERAGE(D33:N33),"") -> 0.048997672
B34: Return on Equity (RoE) | D34: =IFERROR(+D105/D122,"") -> 0.41203498 | E34: =IFERROR(+E105/E122,"") -> 0.10130286 | F34: =IFERROR(+F105/F122,"") -> 0.16071816 | G34: =IFERROR(+G105/G122,"") -> 0.058224485 | H34: =IFERROR(+H105/H122,"") -> 0.06779661 | I34: =IFERROR(+I105/I122,"") -> 0.0026205451 | J34: =IFERROR(+J105/J122,"") -> 0.06875 | K34: =IFERROR(+K105/K122,"") -> 0.14834478 | ... N34: =IFERROR(+N105/N122,"") -> -0.29138432 | O34: =IFERROR(+AVERAGE(D34:N34),"") -> 0.066636999
B35: Return on Invested Capital (ROIC) | D35: =IFERROR(+D105/(D121+D122),"") -> 0.28439898 | E35: =IFERROR(+E105/(E121+E122),"") -> 0.085399297 | F35: =IFERROR(+F105/(F121+F122),"") -> 0.11850578 | G35: =IFERROR(+G105/(G121+G122),"") -> 0.042433043 | H35: =IFERROR(+H105/(H121+H122),"") -> 0.040386304 | I35: =IFERROR(+I105/(I121+I122),"") -> 0.0018846589 | J35: =IFERROR(+J105/(J121+J122),"") -> 0.05569521 | K35: =IFERROR(+K105/(K121+K122),"") -> 0.11990912 | ... N35: =IFERROR(+N105/(N121+N122),"") -> -0.13190184 | O35: =IFERROR(+AVERAGE(D35:N35),"") -> 0.055447489
B37: Solvency | D37: =+D28 -> ADOBE | E37: =+E28 -> SALESFORCE, | F37: =+F28 -> INTUIT | G37: =+G28 -> WORKDAY, | H37: =+H28 -> DATADOG, | I37: =+I28 -> HUBSPOT, | J37: =+J28 -> Sap Se | K37: =+K28 -> SERVICENOW, | ... O37: =+O28 -> Average
B39: Debt/Assets | D39: =IFERROR(D121/D117,"") -> 0.20185321 | E39: =IFERROR(E121/E117,"") -> 0.11067931 | F39: =IFERROR(F121/F117,"") -> 0.2043757 | G39: =IFERROR(G121/G117,"") -> 0.18701674 | H39: =IFERROR(H121/H117,"") -> 0.31840968 | I39: =IFERROR(I121/I117,"") -> 0.19625922 | J39: =IFERROR(J121/J117,"") -> 0.14369553 | K39: =IFERROR(K121/K117,"") -> 0.1117598 | ... N39: =IFERROR(N121/N117,"") -> 0.23963929 | O39: =IFERROR(+AVERAGE(D39:N39),"") -> 0.20428379
B40: Net Debt/EBITDA | D40: =IFERROR(+(D121-D111)/D100,"") -> -0.20142303 | E40: =IFERROR(+(E121-E111)/E100,"") -> 0.22830477 | F40: =IFERROR(+(F121-F111)/F100,"") -> 0.64571054 | G40: =IFERROR(+(G121-G111)/G100,"") -> 1.687384 | H40: =IFERROR(+(H121-H111)/H100,"") -> 2.2368421 | I40: =IFERROR(+(I121-I111)/I100,"") -> -10.263566 | J40: =IFERROR(+(J121-J111)/J100,"") -> 0.16102612 | K40: =IFERROR(+(K121-K111)/K100,"") -> -0.011182796 | ... N40: =IFERROR(+(N121-N111)/N100,"") -> -34.37037 | O40: =IFERROR(+AVERAGE(D40:N40),"") -> -3.5744026
B41: Interest Coverage Ratio | D41: =IFERROR(D101/D102,"") -> -39.959302 | E41: =IFERROR(E101/E102,"") | F41: =IFERROR(F101/F102,"") -> 40.810526 | G41: =IFERROR(G101/G102,"") -> 3.1864407 | H41: =IFERROR(H101/H102,"") -> 1.4256757 | I41: =IFERROR(I101/I102,"") -> 0.40506329 | J41: =IFERROR(J101/J102,"") -> 22.668122 | K41: =IFERROR(K101/K102,"") -> 4.4469697 | ... N41: =IFERROR(N101/N102,"") -> -1.8571429 | O41: =IFERROR(+AVERAGE(D41:N41),"") -> -1.5361654
B43: Liquidity | D43: =+D28 -> ADOBE | E43: =+E28 -> SALESFORCE, | F43: =+F28 -> INTUIT | G43: =+G28 -> WORKDAY, | H43: =+H28 -> DATADOG, | I43: =+I28 -> HUBSPOT, | J43: =+J28 -> Sap Se | K43: =+K28 -> SERVICENOW, | ... O43: =+O28 -> Average
B45: Cash Ratio | D45: =IFERROR(D111/D119,"") -> 0.72360042 | E45: =IFERROR(E111/E119,"") -> 0.31622588 | F45: =IFERROR(F111/F119,"") -> 0.48177813 | G45: =IFERROR(G111/G119,"") -> 0.27811824 | H45: =IFERROR(H111/H119,"") -> 0.66935051 | I45: =IFERROR(I111/I119,"") -> 1.315321 | J45: =IFERROR(J111/J119,"") -> 0.50364275 | K45: =IFERROR(K111/K119,"") -> 0.27566403 | ... N45: =IFERROR(N111/N119,"") -> 0.83409962 | O45: =IFERROR(+AVERAGE(D45:N45),"") -> 0.59133192
B46: Quick Ratio | D46: =IFERROR(+(D111+D112)/D119,"") -> 0.92053987 | E46: =IFERROR(+(E111+E112)/E119,"") -> 0.74313796 | F46: =IFERROR(+(F111+F112)/F119,"") -> 0.54278467 | G46: =IFERROR(+(G111+G112)/G119,"") -> 0.62959625 | H46: =IFERROR(+(H111+H112)/H119,"") -> 0.99087493 | I46: =IFERROR(+(I111+I112)/I119,"") -> 1.5282899 | J46: =IFERROR(+(J111+J112)/J119,"") -> 0.83023219 | K46: =IFERROR(+(K111+K112)/K119,"") -> 0.54367073 | ... N46: =IFERROR(+(N111+N112)/N119,"") -> 1.0747126 | O46: =IFERROR(+AVERAGE(D46:N46),"") -> 0.853272
B47: Current Ratio | D47: =IFERROR(D115/D119,"") -> 1.0675791 | E47: =IFERROR(E115/E119,"") -> 1.0624375 | F47: =IFERROR(F115/F119,"") -> 1.2919503 | G47: =IFERROR(G115/G119,"") -> 1.9006849 | H47: =IFERROR(H115/H119,"") -> 2.6360709 | I47: =IFERROR(I115/I119,"") -> 1.6745073 | J47: =IFERROR(J115/J119,"") -> 1.1217045 | K47: =IFERROR(K115/K119,"") -> 1.0991864 | ... N47: =IFERROR(N115/N119,"") -> 1.1785441 | O47: =IFERROR(+AVERAGE(D47:N47),"") -> 1.4078724
B49: Activity | D49: =+D28 -> ADOBE | E49: =+E28 -> SALESFORCE, | F49: =+F28 -> INTUIT | G49: =+G28 -> WORKDAY, | H49: =+H28 -> DATADOG, | I49: =+I28 -> HUBSPOT, | J49: =+J28 -> Sap Se | K49: =+K28 -> SERVICENOW, | ... O49: =+O28 -> Average
B51: Inventory Turnover | D51: =IFERROR(D98/(AVERAGE(D113:D114)),"") | E51: =IFERROR(E98/(AVERAGE(E113:E114)),"") | F51: =IFERROR(F98/(AVERAGE(F113:F114)),"") | G51: =IFERROR(G98/(AVERAGE(G113:G114)),"") | H51: =IFERROR(H98/(AVERAGE(H113:H114)),"") | I51: =IFERROR(I98/(AVERAGE(I113:I114)),"") | J51: =IFERROR(J98/(AVERAGE(J113:J114)),"") | K51: =IFERROR(K98/(AVERAGE(K113:K114)),"") | ... N51: =IFERROR(N98/(AVERAGE(N113:N114)),"") | O51: =IFERROR(+AVERAGE(D51:N51),"")
B52: Acc. Receivable Turnover | D52: =IFERROR(D97/D112,"") -> 10.378861 | E52: =IFERROR(E97/E112,"") -> 3.1724571 | F52: =IFERROR(F97/F112,"") -> 35.634573 | G52: =IFERROR(G97/G112,"") -> 4.3312821 | H52: =IFERROR(H97/H112,"") -> 4.4808013 | I52: =IFERROR(I97/I112,"") -> 7.8447761 | J52: =IFERROR(J97/J112,"") -> 5.4848339 | K52: =IFERROR(K97/K112,"") -> 4.9035714 | ... N52: =IFERROR(N97/N112,"") -> 6.9410828 | O52: =IFERROR(+AVERAGE(D52:N52),"") -> 8.4711886
B53: Payables Turnover | D53: =IFERROR(D98/D118,"") -> 7.0304709 | E53: =IFERROR(E98/E118,"") -> 1.2981376 | F53: =IFERROR(F98/F118,"") -> 4.8058252 | G53: =IFERROR(G98/G118,"") -> 19.157407 | H53: =IFERROR(H98/H118,"") -> 4.7685185 | I53: =IFERROR(I98/I118,"") -> 98.25 | J53: =IFERROR(J98/J118,"") -> 4.6447236 | K53: =IFERROR(K98/K118,"") -> 33.632353 | ... N53: =IFERROR(N98/N118,"") -> 4.511236 | O53: =IFERROR(+AVERAGE(D53:N53),"") -> 17.013368
B54: Fixed Asset Turnover | D54: =IFERROR(D97/D116,"") -> 11.107955 | E54: =IFERROR(E97/E116,"") -> 7.0267013 | F54: =IFERROR(F97/F116,"") -> 11.46831 | G54: =IFERROR(G97/G116,"") -> 5.3625397 | H54: =IFERROR(H97/H116,"") -> 6.726817 | I54: =IFERROR(I97/I116,"") -> 7.9636364 | J54: =IFERROR(J97/J116,"") -> 7.606499 | K54: =IFERROR(K97/K116,"") -> 4.4723127 | ... N54: =IFERROR(N97/N116,"") -> 16.830116 | O54: =IFERROR(+AVERAGE(D54:N54),"") -> 9.7118704
B55: Total Asset Turnover | D55: =IFERROR(D97/D117,"") -> 0.71678555 | E55: =IFERROR(E97/E117,"") -> 0.36816998 | F55: =IFERROR(F97/F117,"") -> 0.50681564 | G55: =IFERROR(G97/G117,"") -> 0.46982255 | H55: =IFERROR(H97/H117,"") -> 0.46395851 | I55: =IFERROR(I97/I117,"") -> 0.69230769 | J55: =IFERROR(J97/J117,"") -> 0.46107768 | K55: =IFERROR(K97/K117,"") -> 0.53888044 | ... N55: =IFERROR(N97/N117,"") -> 0.83633922 | O55: =IFERROR(+AVERAGE(D55:N55),"") -> 0.54740779
B56: Cash Cycle (days) | D56: =IFERROR(365/D51+365/D52-365/D53,"") | E56: =IFERROR(365/E51+365/E52-365/E53,"") | F56: =IFERROR(365/F51+365/F52-365/F53,"") | G56: =IFERROR(365/G51+365/G52-365/G53,"") | H56: =IFERROR(365/H51+365/H52-365/H53,"") | I56: =IFERROR(365/I51+365/I52-365/I53,"") | J56: =IFERROR(365/J51+365/J52-365/J53,"") | K56: =IFERROR(365/K51+365/K52-365/K53,"") | ... N56: =IFERROR(365/N51+365/N52-365/N53,"") | O56: =IFERROR(+AVERAGE(D56:N56),"")
B58: Cash Flow | D58: =+D37 -> ADOBE | E58: =+E37 -> SALESFORCE, | F58: =+F37 -> INTUIT | G58: =+G37 -> WORKDAY, | H58: =+H37 -> DATADOG, | I58: =+I37 -> HUBSPOT, | J58: =+J37 -> Sap Se | K58: =+K37 -> SERVICENOW, | ... O58: =+O37 -> Average
B60: Cash Flow Margin | D60: =IFERROR(D132/D97,"") -> 0.021948384 | E60: =IFERROR(E132/E97,"") -> 0.0099221533 | F60: =IFERROR(F132/F97,"") -> 0.26079214 | G60: =IFERROR(G132/G97,"") -> -0.055647644 | H60: =IFERROR(H132/H97,"") -> 0.34165425 | I60: =IFERROR(I132/I97,"") -> 0.047564688 | J60: =IFERROR(J132/J97,"") -> 0.043451545 | K60: =IFERROR(K132/K97,"") -> 0.036962855 | ... N60: =IFERROR(N132/N97,"") -> 0 | O60: =IFERROR(+AVERAGE(D60:N60),"") -> 0.082911817
B61: Cash Flow to Net Income | D61: =IFERROR(D132/D96,"") -> 0.086956522 | E61: =IFERROR(E132/E96,"") -> 0.090909091 | F61: =IFERROR(F132/F96,"") -> 1.7814597 | G61: =IFERROR(G132/G96,"") -> -0.34033309 | H61: =IFERROR(H132/H96,"") -> 19.104167 | I61: =IFERROR(I132/I96,"") -> -0.75757576 | J61: =IFERROR(J132/J96,"") -> 0.44942382 | K61: =IFERROR(K132/K96,"") -> 0.2345465 | ... N61: =IFERROR(N132/N96,"") -> 0 | O61: =IFERROR(+AVERAGE(D61:N61),"") -> 1.7480062
B62: CFO to Net Income | D62: =+IFERROR(D126/D105,"") -> 1.4489209 | E62: =+IFERROR(E126/E105,"") -> 2.1126351 | F62: =+IFERROR(F126/F105,"") -> 1.6483294 | G62: =+IFERROR(G126/G105,"") -> 4.6787072 | H62: =+IFERROR(H126/H105,"") -> 4.7336957 | I62: =+IFERROR(I126/I105,"") -> 119.8 | J62: =+IFERROR(J126/J105,"") -> 1.6709347 | K62: =+IFERROR(K126/K105,"") -> 2.994386 | ... N62: =+IFERROR(N126/N105,"") -> -4.8106312 | O62: =IFERROR(+AVERAGE(D62:N62),"") -> 12.269056
B63: Net Capex to CFO | D63: =IFERROR(-D127/D126,"") -> 0.022715988 | E63: =IFERROR(-E127/E126,"") -> 0.050259701 | F63: =IFERROR(-F127/F126,"") -> 0.012080262 | G63: =IFERROR(-G127/G126,"") -> 0.11052418 | H63: =IFERROR(-H127/H126,"") -> 0.10907003 | I63: =IFERROR(-I127/I126,"") -> 0.21535893 | J63: =IFERROR(-J127/J126,"") -> 0.15268199 | K63: =IFERROR(-K127/K126,"") -> 0.20904617 | ... N63: =IFERROR(-N127/N126,"") -> 0.022790055 | O63: =IFERROR(+AVERAGE(D63:N63),"") -> 0.091689553
B64: CFI to CFO | D64: =IFERROR(-D128/D126,"") -> -0.018495531 | E64: =IFERROR(-E128/E126,"") -> 0.24159792 | F64: =IFERROR(-F128/F126,"") -> 0.046478296 | G64: =IFERROR(-G128/G126,"") -> 0.72368956 | H64: =IFERROR(-H128/H126,"") -> 0.84615385 | I64: =IFERROR(-I128/I126,"") -> 0.86143573 | J64: =IFERROR(-J128/J126,"") -> 0.1256705 | K64: =IFERROR(-K128/K126,"") -> 0.58612608 | ... N64: =IFERROR(-N128/N126,"") -> 0.66574586 | O64: =IFERROR(+AVERAGE(D64:N64),"") -> 0.40385475
B65: Net Financing to CFO | D65: =IFERROR((D129+D130)/D126,"") -> 0.24788977 | E65: =IFERROR((E129+E130)/E126,"") -> -0.12244119 | F65: =IFERROR((F129+F130)/F126,"") -> 0.0002047502 | G65: =IFERROR((G129+G130)/G126,"") -> 0 | H65: =IFERROR((H129+H130)/H126,"") -> 0.84500574 | I65: =IFERROR((I129+I130)/I126,"") -> -9.5158598e-05 | J65: =IFERROR((J129+J130)/J126,"") -> 0.24367816 | K65: =IFERROR((K129+K130)/K126,"") -> 0 | ... N65: =IFERROR((N129+N130)/N126,"") -> -0.0089779006 | O65: =IFERROR(+AVERAGE(D65:N65),"") -> 0.14441796
B66: Debt Borrowing to Debt Repayment | D66: =+IFERROR(-D130/D129,"") -> 0 | E66: =+IFERROR(-E130/E129,"") | F66: =+IFERROR(-F130/F129,"") -> 0.99976884 | G66: =+IFERROR(-G130/G129,"") | H66: =+IFERROR(-H130/H129,"") -> 0.28820116 | I66: =+IFERROR(-I130/I129,"") | J66: =+IFERROR(-J130/J129,"") -> 0.54029635 | K66: =+IFERROR(-K130/K129,"") | ... N66: =+IFERROR(-N130/N129,"") -> 1.0131712 | O66: =IFERROR(+AVERAGE(D66:N66),"") -> 0.61357293
B67: CFF to CFO | D67: =IFERROR(-D131/D126,"") -> 0.95878848 | E67: =IFERROR(-E131/E126,"") -> 0.72021082 | F67: =IFERROR(-F131/F126,"") -> 0.081285831 | G67: =IFERROR(-G131/G126,"") -> 0.46728972 | H67: =IFERROR(-H131/H126,"") -> -0.90355913 | I67: =IFERROR(-I131/I126,"") -> -0.088480801 | J67: =IFERROR(-J131/J126,"") -> 0.65363985 | K67: =IFERROR(-K131/K126,"") -> 0.31474104 | ... N67: =IFERROR(-N131/N126,"") -> 0.28176796 | O67: =IFERROR(+AVERAGE(D67:N67),"") -> 0.30330273
B68: Payout Ratio | O68: =IFERROR(+AVERAGE(D68:N68),"")
B70: Stock Information | D70: =+D28 -> ADOBE | E70: =+E28 -> SALESFORCE, | F70: =+F28 -> INTUIT | G70: =+G28 -> WORKDAY, | H70: =+H28 -> DATADOG, | I70: =+I28 -> HUBSPOT, | J70: =+J28 -> Sap Se | K70: =+K28 -> SERVICENOW, | ... O70: =+O28 -> Average
B72: (%) Float | D72: =Summary!V32 -> 0.1277 | O72: =IFERROR(+AVERAGE(D72:N72),"") -> 0.1277
B73: β (Levered) | D73: {=IFERROR(_FV(D91,"Beta"),"")} -> 1.4977 | E73: {=IFERROR(_FV(E91,"Beta"),"")} -> 1.205 | F73: {=IFERROR(_FV(F91,"Beta"),"")} -> 1.2562 | G73: {=IFERROR(_FV(G91,"Beta"),"")} -> 1.099 | H73: {=IFERROR(_FV(H91,"Beta"),"")} -> 1.2114 | I73: {=IFERROR(_FV(I91,"Beta"),"")} -> 1.6035 | J73: {=IFERROR(_FV(J91,"Beta"),"")} -> 1.2815 | K73: {=IFERROR(_FV(K91,"Beta"),"")} -> 0.9313 | ... N73: {=IFERROR(_FV(N91,"Beta"),"")} -> 0.9358 | O73: =IFERROR(+AVERAGE(D73:N73),"") -> 1.2482727
B74: β (Unlevered) | D74: =IFERROR(D73/(1+(1-D104/D103)*(D121/D122)),"") -> 1.1012355 | E74: =IFERROR(E73/(1+(1-E104/E103)*(E121/E122)),"") -> 1.0431501 | F74: =IFERROR(F73/(1+(1-F104/F103)*(F121/F122)),"") -> 0.96831437 | G74: =IFERROR(G73/(1+(1-G104/G103)*(G121/G122)),"") -> 0.84097319 | H74: =IFERROR(H73/(1+(1-H104/H103)*(H121/H122)),"") -> 0.75141262 | I74: =IFERROR(I73/(1+(1-I104/I103)*(I121/I122)),"") -> 1.5023598 | J74: =IFERROR(J73/(1+(1-J104/J103)*(J121/J122)),"") -> 1.1095378 | K74: =IFERROR(K73/(1+(1-K104/K103)*(K121/K122)),"") -> 0.77969867 | ... N74: =IFERROR(N73/(1+(1-N104/N103)*(N121/N122)),"") -> 0.17765844 | O74: =IFERROR(+AVERAGE(D74:N74),"") -> 0.88656064
B75: % Held by Insiders | D75: =Summary!V33 -> 0.0023 | E75: 0.0261 | F75: 0.0254 | G75: 0.0093 | H75: 0.0297 | I75: 0.0356 | J75: 0 | K75: 0.0017 | L75: 0.0022 | M75: 0.0449 | N75: 0.0034 | O75: =IFERROR(+AVERAGE(D75:N75),"") -> 0.016418182
B76: % Held by Institutions | D76: =Summary!V34 -> 0.87 | E76: 0.8286 | F76: 0.8771 | G76: 0.9562 | H76: 0.8857 | I76: 0.9361 | J76: 0.0628 | K76: 0.9208 | L76: 0.9565 | M76: 0.6529 | N76: 0.943 | O76: =IFERROR(+AVERAGE(D76:N76),"") -> 0.80815455
B77: Short % Float | D77: =Summary!V35 -> 0.0189 | E77: 0.0127 | F77: 0.0143 | G77: 0.0389 | H77: 0.0333 | I77: 0.022 | J77: 0.0033 | K77: 0.0204 | L77: 0.014 | M77: 0.0337 | N77: 0.0248 | O77: =IFERROR(+AVERAGE(D77:N77),"") -> 0.021481818
B79: Stock Performance | D79: =+D28 -> ADOBE | E79: =+E28 -> SALESFORCE, | F79: =+F28 -> INTUIT | G79: =+G28 -> WORKDAY, | H79: =+H28 -> DATADOG, | I79: =+I28 -> HUBSPOT, | J79: =+J28 -> Sap Se | K79: =+K28 -> SERVICENOW, | ... O79: =+O28 -> Average
B81: 1 day | D81: {=IFERROR((D84/_xlfn.STOCKHISTORY(C6,TODAY()-1,TODAY()-1,0,0,1))-1,"Non-trading days")} -> Non-trading days | E81: {=IFERROR((E84/_xlfn.STOCKHISTORY(C7,TODAY()-1,TODAY()-1,0,0,1))-1,"Non-trading days")} -> Non-trading days | F81: {=IFERROR((F84/_xlfn.STOCKHISTORY(C8,TODAY()-1,TODAY()-1,0,0,1))-1,"Non-trading days")} -> Non-trading days | G81: {=IFERROR((G84/_xlfn.STOCKHISTORY(C9,TODAY()-1,TODAY()-1,0,0,1))-1,"Non-trading days")} -> Non-trading days | H81: {=IFERROR((K84/_xlfn.STOCKHISTORY(C10,TODAY()-1,TODAY()-1,0,0,1))-1,"Non-trading days")} -> Non-trading days | I81: {=IFERROR((L84/_xlfn.STOCKHISTORY(C11,TODAY()-1,TODAY()-1,0,0,1))-1,"Non-trading days")} -> Non-trading days | J81: {=IFERROR((M84/_xlfn.STOCKHISTORY(C12,TODAY()-1,TODAY()-1,0,0,1))-1,"Non-trading days")} -> Non-trading days | K81: {=IFERROR((N84/_xlfn.STOCKHISTORY(C13,TODAY()-1,TODAY()-1,0,0,1))-1,"Non-trading days")} -> Non-trading days | L81: {=IFERROR((L84/_xlfn.STOCKHISTORY(C14,TODAY()-1,TODAY()-1,0,0,1))-1,"Non-trading days")} -> Non-trading days | M81: {=IFERROR((M84/_xlfn.STOCKHISTORY(C15,TODAY()-1,TODAY()-1,0,0,1))-1,"Non-trading days")} -> Non-trading days | N81: {=IFERROR((N84/_xlfn.STOCKHISTORY(C16,TODAY()-1,TODAY()-1,0,0,1))-1,"Non-trading days")} -> Non-trading days | O81: =IFERROR(+AVERAGE(D81:N81),"")
B82: 1 month | D82: {=IFERROR((D84/_xlfn.STOCKHISTORY(C6,TODAY()-29,TODAY()-29,0,0,1))-1,"Non-trading days")} -> Non-trading days | E82: {=IFERROR((E84/_xlfn.STOCKHISTORY(C7,TODAY()-29,TODAY()-29,0,0,1))-1,"Non-trading days")} -> Non-trading days | F82: {=IFERROR((F84/_xlfn.STOCKHISTORY(C8,TODAY()-29,TODAY()-29,0,0,1))-1,"Non-trading days")} -> Non-trading days | G82: {=IFERROR((G84/_xlfn.STOCKHISTORY(C9,TODAY()-29,TODAY()-29,0,0,1))-1,"Non-trading days")} -> Non-trading days | H82: {=IFERROR((K84/_xlfn.STOCKHISTORY(C10,TODAY()-29,TODAY()-29,0,0,1))-1,"Non-trading days")} -> Non-trading days | I82: {=IFERROR((L84/_xlfn.STOCKHISTORY(C11,TODAY()-29,TODAY()-29,0,0,1))-1,"Non-trading days")} -> Non-trading days | J82: {=IFERROR((M84/_xlfn.STOCKHISTORY(C12,TODAY()-29,TODAY()-29,0,0,1))-1,"Non-trading days")} -> Non-trading days | K82: {=IFERROR((N84/_xlfn.STOCKHISTORY(C13,TODAY()-29,TODAY()-29,0,0,1))-1,"Non-trading days")} -> Non-trading days | L82: {=IFERROR((L84/_xlfn.STOCKHISTORY(C14,TODAY()-29,TODAY()-29,0,0,1))-1,"Non-trading days")} -> Non-trading days | M82: {=IFERROR((M84/_xlfn.STOCKHISTORY(C15,TODAY()-29,TODAY()-29,0,0,1))-1,"Non-trading days")} -> Non-trading days | N82: {=IFERROR((N84/_xlfn.STOCKHISTORY(C16,TODAY()-29,TODAY()-29,0,0,1))-1,"Non-trading days")} -> Non-trading days | O82: =IFERROR(AVERAGE(D82:N82),"")
B83: YTD | D83: {=IFERROR((D84/_xlfn.STOCKHISTORY(C6,"2025-01-02","2025-01-02",0,0,1))-1,"Non-trading days")} -> -0.17029478 | E83: {=IFERROR((E84/_xlfn.STOCKHISTORY(C7,"2025-01-02","2025-01-02",0,0,1))-1,"Non-trading days")} -> -0.24248473 | F83: {=IFERROR((F84/_xlfn.STOCKHISTORY(C8,"2025-01-02","2025-01-02",0,0,1))-1,"Non-trading days")} -> -0.042935821 | G83: {=IFERROR((G84/_xlfn.STOCKHISTORY(C9,"2025-01-02","2025-01-02",0,0,1))-1,"Non-trading days")} -> -0.1070918 | H83: {=IFERROR((K84/_xlfn.STOCKHISTORY(C10,"2025-01-02","2025-01-02",0,0,1))-1,"Non-trading days")} -> 0.84111954 | I83: {=IFERROR((L84/_xlfn.STOCKHISTORY(C11,"2025-01-02","2025-01-02",0,0,1))-1,"Non-trading days")} -> 0.16527824 | J83: {=IFERROR((M84/_xlfn.STOCKHISTORY(C12,"2025-01-02","2025-01-02",0,0,1))-1,"Non-trading days")} -> -0.38214211 | K83: {=IFERROR((N84/_xlfn.STOCKHISTORY(C13,"2025-01-02","2025-01-02",0,0,1))-1,"Non-trading days")} -> -0.8024641 | L83: {=IFERROR((L84/_xlfn.STOCKHISTORY(C14,"2025-01-02","2025-01-02",0,0,1))-1,"Non-trading days")} -> 1.7706941 | M83: {=IFERROR((M84/_xlfn.STOCKHISTORY(C15,"2025-01-02","2025-01-02",0,0,1))-1,"Non-trading days")} -> -0.064249889 | N83: {=IFERROR((N84/_xlfn.STOCKHISTORY(C16,"2025-01-02","2025-01-02",0,0,1))-1,"Non-trading days")} -> -0.14076488 | O83: =IFERROR(AVERAGE(D83:N83),"") -> 0.074969435
B84: Current Price | D84: {=+IFERROR(_FV(D91,"Price"),"")} -> 365.9 | E84: 250.48 | F84: 596.05 | G84: 224.87 | H84: 94.58 | I84: 565.96 | J84: 271.48 | K84: 264.44 | L84: 812.7 | M84: 147.39 | N84: 208.27 | O84: =IFERROR(AVERAGE(D84:N84),"") -> 345.64727
B86: Extra
B88: Market Cap | D88: 150005000 | E88: 240711000 | F88: 166633000 | G88: 59815000 | H88: 32662000 | I88: 29517000 | J88: 323153000 | K88: 56326000 | L88: 168231000 | M88: 49243000 | N88: 54567000
B89: % Revenues in the US
B91: Income Statement | D91: =+DCF!R4 -> #VALUE! | E91: #VALUE! | F91: #VALUE! | G91: #VALUE! | H91: #VALUE! | I91: #VALUE! | J91: #VALUE! | K91: #VALUE! | L91: #VALUE! | M91: #VALUE! | N91: #VALUE! | AA91: w | AB91: SAP in EUR
B93: =+Inputs!$B$6&" ("&Inputs!O$4&")" -> Revenue (Sales) (2022) | D93: =+_xlfn.XLOOKUP("Revenue (Sales)",Inputs!$B:$B,Inputs!O:O) -> 17606 | E93: 31352 | F93: 12726 | G93: 6216 | H93: 1675 | I93: 1731 | J93: =AB93*J141 -> 31585.33 | K93: 7245 | L93: 5005 | M93: 2066 | N93: 2803 | AB93: 29519
B94: =+Inputs!$B$6&" ("&Inputs!P$4&")" -> Revenue (Sales) (2023) | D94: =+_xlfn.XLOOKUP("Revenue (Sales)",Inputs!$B:$B,Inputs!P:P) -> 19409 | E94: 34857 | F94: 14368 | G94: 7259 | H94: 2128 | I94: 2170 | J94: =AB94*$J$140 -> 34327.7 | K94: 8971 | L94: 5497 | M94: 2806 | N94: 3536 | AB94: 31207
B95: EBITDA (2023) | D95: =+_xlfn.XLOOKUP("EBITDA",Inputs!$B:$B,Inputs!P:P) -> 6818 | E95: 9958 | F95: 4043 | G95: 752 | H95: 111 | I95: -74 | J95: =AB95*$J$140 -> 8252.2 | K95: 1594 | L95: 1219 | M95: -729 | N95: -200 | AB95: 7502
B96: Net Income (2023) | D96: =+_xlfn.XLOOKUP("Net Income",Inputs!$B:$B,Inputs!P:P) -> 5428 | E96: 4136 | F96: 2384 | G96: 1381 | H96: 48 | I96: -165 | J96: =AB96*$J$140 -> 3436.4 | K96: 1731 | L96: 906 | M96: -836 | N96: -301 | AB96: 3124
B97: =+Inputs!$B$6&" ("&Inputs!Q$4&")" -> Revenue (Sales) (2024) | D97: =+_xlfn.XLOOKUP("Revenue (Sales)",Inputs!$B:$B,Inputs!Q:Q) -> 21505 | E97: 37895 | F97: 16285 | G97: 8446 | H97: 2684 | I97: 2628 | J97: =AB97*$J$139 -> 35543.04 | K97: 10984 | L97: 6131 | M97: 3626 | N97: 4359 | AB97: 34176
B98: COGS (Cost of Goods Sold) | D98: =+_xlfn.XLOOKUP($B98,Inputs!$B:$B,Inputs!Q:Q) -> 2538 | E98: 8643 | F98: 3465 | G98: 2069 | H98: 515 | I98: 393 | J98: =AB98*$J$139 -> 9612.72 | K98: 2287 | L98: 578 | M98: 1215 | N98: 803 | AB98: 9243
B99: Gross Profit | D99: =+_xlfn.XLOOKUP($B99,Inputs!$B:$B,Inputs!Q:Q) -> 18967 | E99: =+E97-E98 -> 29252 | F99: =+F97-F98 -> 12820 | G99: =+G97-G98 -> 6377 | H99: =+H97-H98 -> 2169 | I99: =+I97-I98 -> 2235 | J99: =AB99*$J$139 -> 25930.32 | K99: =+K97-K98 -> 8697 | L99: =L97-L98 -> 5553 | M99: =M97-M98 -> 2411 | N99: =N97-N98 -> 3556 | AB99: =AB97-AB98 -> 24933
B100: EBITDA | D100: =+_xlfn.XLOOKUP($B100,Inputs!$B:$B,Inputs!Q:Q) -> 7730 | E100: 11143 | F100: 4581 | G100: 1078 | H100: 266 | I100: 129 | J100: =AB100*$J$139 -> 6729.84 | K100: 2325 | L100: 1549 | M100: -1100 | N100: 27 | AB100: 6471
B101: Operating Income (EBIT) | D101: =+_xlfn.XLOOKUP($B101,Inputs!$B:$B,Inputs!Q:Q) -> 6873 | E101: 7666 | F101: 3877 | G101: 752 | H101: 211 | I101: 32 | J101: =AB101*$J$139 -> 5398.64 | K101: 1761 | L101: 1369 | M101: -1282 | N101: -117 | AB101: 5191
B102: Net Interest Expense (Income) | D102: =+_xlfn.XLOOKUP($B102,Inputs!$B:$B,Inputs!Q:Q) -> -172 | E102: 0 | F102: 95 | G102: 236 | H102: 148 | I102: 79 | J102: =AB102*$J$139 -> 238.16 | K102: 396 | L102: -34 | M102: 206 | N102: 63 | AB102: 229
B103: Pre-Tax Income (EBT) | D103: =+_xlfn.XLOOKUP($B103,Inputs!$B:$B,Inputs!Q:Q) -> 6931 | E103: 7438 | F103: 3550 | G103: 638 | H103: 204 | I103: 29 | J103: =AB103*$J$139 -> 4954.56 | K103: 1738 | L103: 1384 | M103: -1285 | N103: -85 | AB103: 4764
B104: Tax Expense (Benefits) | D104: =+_xlfn.XLOOKUP($B104,Inputs!$B:$B,Inputs!Q:Q) -> 1371 | E104: 1241 | F104: 587 | G104: 112 | H104: 20 | I104: 24 | J104: =AB104*$J$139 -> 1678.56 | K104: 313 | L104: 272 | M104: 4 | N104: 215 | AB104: 1614
B105: Net Income | D105: =+_xlfn.XLOOKUP($B105,Inputs!$B:$B,Inputs!Q:Q) -> 5560 | E105: 6197 | F105: 2963 | G105: 526 | H105: 184 | I105: 5 | J105: =AB105*$J$139 -> 3248.96 | K105: 1425 | L105: 1112 | M105: -1259 | N105: -301 | AB105: 3124
B106: EPS basic | D106: =+_xlfn.XLOOKUP($B106,Inputs!$B:$B,Inputs!Q:Q) -> 12.43 | E106: 6.44 | F106: 10.58 | G106: 1.98 | H106: 0.55 | I106: 0.09 | J106: =AB106*$J$139 -> 2.7872 | K106: 6.92 | L106: 5.17 | M106: -3.86 | N106: -1.16 | AB106: 2.68
B107: R&D (Research & Development) | D107: =+_xlfn.XLOOKUP($B107,Inputs!$B:$B,Inputs!Q:Q) -> 3944
J108: =AB108*$J$139 -> 0
B109: Balance Sheet
B111: Cash & Cash Equivalents | D111: =+_xlfn.XLOOKUP($B111,Inputs!$B:$B,Inputs!Q:Q) -> 7613 | E111: 8848 | F111: 3609 | G111: 1543 | H111: 1247 | I111: 2069 | J111: =AB111*$J$139 -> 9993.36 | K111: 2304 | L111: 1599 | M111: 2629 | N111: 2177 | AB111: 9609
B112: Accounts Receivable | D112: =+_xlfn.XLOOKUP($B112,Inputs!$B:$B,Inputs!Q:Q) -> 2072 | E112: 11945 | F112: 457 | G112: 1950 | H112: 599 | I112: 335 | J112: =AB112*$J$139 -> 6480.24 | K112: 2240 | L112: 1008 | M112: 923 | N112: 628 | AB112: 6231
B113: Beginning Inventory | D113: =+_xlfn.XLOOKUP("Inventory",Inputs!$B:$B,Inputs!P:P) -> 0 | E113: 0 | F113: 0 | G113: 0 | H113: 0 | I113: 0 | J113: =AB113*$J$139 -> 0 | K113: 0 | L113: 0 | M113: 0 | N113: 0 | AB113: 0
B114: Ending Inventory | D114: =+_xlfn.XLOOKUP("Inventory",Inputs!$B:$B,Inputs!Q:Q) -> 0 | E114: 0 | F114: 0 | G114: 0 | H114: 0 | I114: 0 | J114: =AB114*$J$139 -> 0 | K114: 0 | L114: 0 | M114: 0 | N114: 0 | AB114: 0
B115: Current Assets | D115: =+_xlfn.XLOOKUP($B115,Inputs!$B:$B,Inputs!Q:Q) -> 11232 | E115: 29727 | F115: 9678 | G115: 10545 | H115: 4911 | I115: 2634 | J115: =AB115*$J$139 -> 22257.04 | K115: 9187 | L115: 3482 | M115: 5869 | N115: 3076 | AB115: 21401
B116: Net PP&E (Property, Plant and Equipment) | D116: =+_xlfn.XLOOKUP($B116,Inputs!$B:$B,Inputs!Q:Q) -> 1936 | E116: 5393 | F116: 1420 | G116: 1575 | H116: 399 | I116: 330 | J116: =AB116*$J$139 -> 4672.72 | K116: 2456 | L116: 286 | M116: 531 | N116: 259 | AB116: 4493
B117: Total Assets | D117: =+_xlfn.XLOOKUP($B117,Inputs!$B:$B,Inputs!Q:Q) -> 30002 | E117: 102928 | F117: 32132 | G117: 17977 | H117: 5785 | I117: 3796 | J117: =AB117*$J$139 -> 77086.88 | K117: 20383 | L117: 10833 | M117: 9034 | N117: 5212 | AB117: 74122
B118: Accounts Payable | D118: =+_xlfn.XLOOKUP($B118,Inputs!$B:$B,Inputs!Q:Q) -> 361 | E118: 6658 | F118: 721 | G118: 108 | H118: 108 | I118: 4 | J118: =AB118*$J$139 -> 2069.6 | K118: 68 | L118: 304 | M118: 170 | N118: 178 | AB118: 1990
B119: Current Liabilities | D119: =+_xlfn.XLOOKUP($B119,Inputs!$B:$B,Inputs!Q:Q) -> 10521 | E119: 27980 | F119: 7491 | G119: 5548 | H119: 1863 | I119: 1573 | J119: =AB119*$J$139 -> 19842.16 | K119: 8358 | L119: 5151 | M119: 3301 | N119: 2610 | AB119: 19079
B120: Long-term debt | D120: =+_xlfn.XLOOKUP($B120,Inputs!$B:$B,Inputs!Q:Q) -> 4482 | E120: 8433 | F120: 5539 | G120: 2984 | H120: 979 | I120: 0 | J120: =AB120*$J$139 -> 5512 | K120: 1489 | L120: 1987 | M120: 2272 | N120: 986 | AB120: 5300
B121: Total Debt | D121: =+_xlfn.XLOOKUP($B121,Inputs!$B:$B,Inputs!Q:Q,,,-1) -> 6056 | E121: 11392 | F121: 6567 | G121: 3362 | H121: 1842 | I121: 745 | J121: =AB121*$J$139 -> 11077.04 | K121: 2278 | L121: 2559 | M121: 2685 | N121: 1249 | AB121: 10651
B122: Shareholder's Equity | D122: =+_xlfn.XLOOKUP($B122,Inputs!$B:$B,Inputs!Q:Q) -> 13494 | E122: 61173 | F122: 18436 | G122: 9034 | H122: 2714 | I122: 1908 | J122: =AB122*$J$139 -> 47257.6 | K122: 9606 | L122: 2621 | M122: 3000 | N122: 1033 | AB122: 45440
J123: =AB123*$J$139 -> 0
...

Sheet ESG
B2: Environmental, Social and Governance Analysis
B4: Author: | C4: Alexandra Gonçalves | E4: Highlights | N4: Recent News
B6: Overview | D6: .
B7: Last Update | C7: 45122 | D7: .
B8: Latest year with data | C8: 2023
B9: GICS Sector
B10: GICS Industry Group | C10: Software Development
B11: Final Review
B13: ESG Scores
B14: LSEG ESG Score | C14: 68
B15: E-Score | C15: 75
B16: S-Score | C16: 77 | E16: GHG Scope 1 and 2 Emissions: | N16: Water, Waste, Energy Management:
B17: G-Score | C17: 59
B18: S&P Global ESG Score | C18: 55
B19: Environmental | C19: 66
B20: Social | C20: 45
B21: Governance & Economic | C21: 63
B22: Sustainalytics | C22: 14.2
B23: ISS ESG Corporate Rating | C23: B
B24: SDG Impact Rating | C24: 4.7
B25: Governance Quality Score | C25: 2
B26: MSCI ESG Ratings
B29: Industry ESG Overview:
E33: ENVIRONMENTAL
G35: Overview | H35: Targets | K35: Improvements | O35: Comments
E36: GHG (or CO2) Scope 1 Emissions | H36: 42% reduction in absolute Scope 1 and 2 GHG emissions by FY 2030 from a FY 2022 base year | K36: Significant reduction in overall emissions | O36: Mantaining emissions but increasing revenues
E38: Water Consumption | H38: 25% reduction in global water usage per full time employee by 2025 | K38: Water usage going up
E40: Energy Consumption | H40: 80% of Adobe buildings, by square footage, are LEED or green building certified | K40: There isnt a relevant improvement
E42: Waste Management | H42: 90% global waste diversion rate annually through a combination of waste reduction, composting, reusing and responsible recycling | K42: There isnt a relevant improvement
E44: Other
E46: SOCIAL
B48: Important Sources: | G48: Overview | H48: Targets | K48: Improvements | O48: Comments
B49: Annual Report | C49: https://www.sec.gov/ix?doc=/Archives/edgar/data/0000796343/000079634325000004/adbe-20241129.htm | E49: Employee Turnover % | G49: Not reported | H49: Improve turnover and satisfaction | O49: 87% Employee satisfaction
B50: Sustainability Report | C50: https://www.adobe.com/corporate-responsibility/sustainability/corporate-policy.html | D50: .
B51: Proxy Statement | C51: https://www.sec.gov/ix?doc=/Archives/edgar/data/0000796343/000079634325000048/adbe-20250227.htm | D51: . | E51: Salaries & Compensation
E53: Reputation | O53: The brand has a very strong reputation
E55: Discrimination Events | G55: Not reported
E57: Work Safety | O57: There are no recent accidents to be reported
E59: Damage to consumer health | O59: Adobe's product does not cause harm to consumers
E61: Pension Plan | O61: Retired savings plan for US employees
E63: Supply chain | O63: 100% of suppliers comply with EICC and human right screenings
E65: Community involvement | H65: Not reported | O65: The company is involved with community projects investing around 100M every year
E67: Public Sector
E69: Litigation
E71: GOVERNANCE
G73: Overview | H73: Targets | K73: Improvements | O73: Comments
E74: Diversity (Gender, Age, Industry, Region) | O74: 35,3% of the global employee base was female and 29% of leadership roles are female; 11,6% of the U.S employee base are underrespresented minorities (such as Black/African American, Hispanic Latinx, Native American, Pacific Islander and/or two or more races); 58% of board of directors with gender or demographic diversity
E76: % Independence | O76: High independence rate of 91%
E78: Average time as independent directors | G78: Not reported
E80: Departures of C-level executives | O80: There have not been recent departures
E82: CEO/Chairman duality | O82: There is no separation
E84: Transparency when reporting | O84: The company provides detailed reports for ESG analysis
E86: Time taken to report | O86: Even though, the last CSR is from 2023
E88: CEO or Chairman in other boards? | O88: CEO not in other boards
E90: Audit / Consulting | O90: Audit done by KPMG
E92: ESG-compensation related | O92: Not reported
E94: Management compensation schemes

Sheet ESG Inputs
B2: ESG Inputs
A4: x | B4: Total GHG Scope 1 Emissions | G4: 2014 | H4: =+G4+1 -> 2015 | I4: =+H4+1 -> 2016 | J4: =+I4+1 -> 2017 | K4: =+J4+1 -> 2018 | L4: =+K4+1 -> 2019 | M4: =+L4+1 -> 2020 | N4: =+M4+1 -> 2021 | O4: =+N4+1 -> 2022 | ... Q4: =+P4+1 -> 2024 | R4: ="CAGR "&$G$4&" - "&$Q$4 -> CAGR 2014 - 2024
B6: =+Peers!B6 -> ADOBE INC. | G6: 10976 | H6: 12365 | I6: 11082 | J6: 14177 | K6: 12199 | L6: 11817 | M6: 9842 | N6: 4911 | O6: 6586 | P6: 7649 | Q6: 7649 | R6: =IFERROR((Q6/G6)^(1/COUNT($G$4:$Q$4))-1,"") -> -0.032297486
B7: =+Peers!B7 -> SALESFORCE, INC. | G7: 6000 | H7: 5000 | I7: 3000 | J7: 0 | K7: 0 | L7: 0 | M7: 6000 | N7: 1000 | O7: 6000 | P7: 4000 | Q7: 3000 | R7: =IFERROR((Q7/G7)^(1/COUNT($G$4:$Q$4))-1,"") -> -0.061069089
B8: =+Peers!B8 -> INTUIT INC. | R8: =IFERROR((Q8/G8)^(1/COUNT($G$4:$Q$4))-1,"")
B9: =+Peers!B9 -> WORKDAY, INC. | G9: 1186 | H9: 1186 | I9: 1186 | J9: 1420 | K9: 1816 | L9: 2040 | M9: 1730 | N9: 1471 | O9: 1834 | P9: 2660 | Q9: 2752 | R9: =IFERROR((Q9/G9)^(1/COUNT($G$4:$Q$4))-1,"") -> 0.079525902
B10: =+Peers!B10 -> DATADOG, INC. | R10: =IFERROR((Q10/G10)^(1/COUNT($G$4:$Q$4))-1,"")
B11: =+Peers!B11 -> HUBSPOT, INC. | R11: =IFERROR((Q11/G11)^(1/COUNT($G$4:$Q$4))-1,"")
B12: =+Peers!B12 -> Sap Se | R12: =IFERROR((Q12/G12)^(1/COUNT($G$4:$Q$4))-1,"")
B13: =+Peers!B13 -> SERVICENOW, INC. | R13: =IFERROR((Q13/G13)^(1/COUNT($G$4:$Q$4))-1,"")
B14: =+Peers!B14 -> AUTODESK, INC. | R14: =IFERROR((Q14/G14)^(1/COUNT($G$4:$Q$4))-1,"")
B15: =+Peers!B15 -> SNOWFLAKE INC. | R15: =IFERROR((Q15/G15)^(1/COUNT($G$4:$Q$4))-1,"")
B16: =+Peers!B16 -> ATLASSIAN CORPORATION | R16: =IFERROR((Q16/G16)^(1/COUNT($G$4:$Q$4))-1,"")
A18: x | B18: Total GHG Scope 2 (Location-Based) Emissions | G18: 2014 | H18: =+G18+1 -> 2015 | I18: =+H18+1 -> 2016 | J18: =+I18+1 -> 2017 | K18: =+J18+1 -> 2018 | L18: =+K18+1 -> 2019 | M18: =+L18+1 -> 2020 | N18: =+M18+1 -> 2021 | O18: =+N18+1 -> 2022 | ... Q18: =+P18+1 -> 2024 | R18: ="CAGR "&$G$4&" - "&$Q$4 -> CAGR 2014 - 2024
B20: =+$B$6 -> ADOBE INC. | G20: 61425 | H20: 64352 | I20: 61875 | J20: 66288 | K20: 58874 | L20: 56128 | M20: 51176 | N20: 61220 | O20: 57168 | P20: 62662 | Q20: 62662 | R20: =IFERROR((Q20/G20)^(1/COUNT($G$4:$Q$4))-1,"") -> 0.0018142151
B21: =+$B$7 -> SALESFORCE, INC. | G21: 48000 | H21: 71000 | I21: 132000 | J21: 138000 | K21: 143000 | L21: 163000 | M21: 291000 | N21: 292000 | O21: 286000 | P21: 280000 | Q21: 315000 | R21: =IFERROR((Q21/G21)^(1/COUNT($G$4:$Q$4))-1,"") -> 0.18653083
B22: =+$B$8 -> INTUIT INC. | R22: =IFERROR((Q22/G22)^(1/COUNT($G$4:$Q$4))-1,"")
B23: =+$B$9 -> WORKDAY, INC. | G23: 17743 | H23: 17743 | I23: 17743 | J23: 27792 | K23: 33894 | L23: 34330 | M23: 36811 | N23: 40584 | O23: 45821 | P23: 60927 | Q23: 67557 | R23: =IFERROR((Q23/G23)^(1/COUNT($G$4:$Q$4))-1,"") -> 0.1292387
B24: =+$B$10 -> DATADOG, INC. | R24: =IFERROR((Q24/G24)^(1/COUNT($G$4:$Q$4))-1,"")
B25: =+$B$11 -> HUBSPOT, INC. | R25: =IFERROR((Q25/G25)^(1/COUNT($G$4:$Q$4))-1,"")
B26: =+$B$12 -> Sap Se | R26: =IFERROR((Q26/G26)^(1/COUNT($G$4:$Q$4))-1,"")
B27: =+$B$13 -> SERVICENOW, INC. | R27: =IFERROR((Q27/G27)^(1/COUNT($G$4:$Q$4))-1,"")
B28: =+$B$14 -> AUTODESK, INC. | R28: =IFERROR((Q28/G28)^(1/COUNT($G$4:$Q$4))-1,"")
B29: =+$B$15 -> SNOWFLAKE INC. | R29: =IFERROR((Q29/G29)^(1/COUNT($G$4:$Q$4))-1,"")
B30: =+$B$16 -> ATLASSIAN CORPORATION | R30: =IFERROR((Q30/G30)^(1/COUNT($G$4:$Q$4))-1,"")
A32: x | B32: Total Energy Usage | G32: 2014 | H32: =+G32+1 -> 2015 | I32: =+H32+1 -> 2016 | J32: =+I32+1 -> 2017 | K32: =+J32+1 -> 2018 | L32: =+K32+1 -> 2019 | M32: =+L32+1 -> 2020 | N32: =+M32+1 -> 2021 | O32: =+N32+1 -> 2022 | ... Q32: =+P32+1 -> 2024 | R32: ="CAGR "&$G$4&" - "&$Q$4 -> CAGR 2014 - 2024
B34: =+$B$6 -> ADOBE INC. | G34: 214736 | H34: 211345 | I34: 212931 | J34: 236956 | K34: 223248 | L34: 221486 | M34: 208187 | N34: 240344 | O34: 213082 | P34: 230771 | Q34: 230771 | R34: =IFERROR((Q34/G34)^(1/COUNT($G$4:$Q$4))-1,"") -> 0.0065684336
B35: =+$B$7 -> SALESFORCE, INC. | G35: 265000 | H35: 140000 | I35: 101000 | J35: 371000 | K35: 514000 | L35: 628000 | M35: 710000 | N35: 777000 | O35: 826000 | P35: 869000 | Q35: 945000 | R35: =IFERROR((Q35/G35)^(1/COUNT($G$4:$Q$4))-1,"") -> 0.12253198
B36: =+$B$8 -> INTUIT INC. | R36: =IFERROR((Q36/G36)^(1/COUNT($G$4:$Q$4))-1,"")
B37: =+$B$9 -> WORKDAY, INC. | G37: 46840 | H37: 46840 | I37: 46840 | J37: 66138 | K37: 80471 | L37: 106084 | M37: 108245 | N37: 132423 | O37: 160889 | P37: 212489 | Q37: 228188 | R37: =IFERROR((Q37/G37)^(1/COUNT($G$4:$Q$4))-1,"") -> 0.15482451
B38: AUTODESK INC | G38: 42000 | H38: 37800 | I38: 55600 | J38: 71900 | K38: 57500 | L38: 57800 | M38: 85600 | N38: 118000 | O38: 118000 | P38: 141000 | Q38: 60500 | R38: =IFERROR((Q38/G38)^(1/COUNT($G$4:$Q$4))-1,"") -> 0.033736007
B39: DATADOG INC | R39: =IFERROR((Q39/G39)^(1/COUNT($G$4:$Q$4))-1,"")
B40: =+$B$12 -> Sap Se | R40: =IFERROR((Q40/G40)^(1/COUNT($G$4:$Q$4))-1,"")
B41: =+$B$13 -> SERVICENOW, INC. | R41: =IFERROR((Q41/G41)^(1/COUNT($G$4:$Q$4))-1,"")
B42: HUBSPOT | R42: =IFERROR((Q42/G42)^(1/COUNT($G$4:$Q$4))-1,"")
B43: =+$B$15 -> SNOWFLAKE INC. | R43: =IFERROR((Q43/G43)^(1/COUNT($G$4:$Q$4))-1,"")
B44: =+$B$16 -> ATLASSIAN CORPORATION | R44: =IFERROR((Q44/G44)^(1/COUNT($G$4:$Q$4))-1,"")
A46: x | B46: Total Water Consumption | G46: 2014 | H46: =+G46+1 -> 2015 | I46: =+H46+1 -> 2016 | J46: =+I46+1 -> 2017 | K46: =+J46+1 -> 2018 | L46: =+K46+1 -> 2019 | M46: =+L46+1 -> 2020 | N46: =+M46+1 -> 2021 | O46: =+N46+1 -> 2022 | ... Q46: =+P46+1 -> 2024 | R46: ="CAGR "&$G$4&" - "&$Q$4 -> CAGR 2014 - 2024
B48: =+$B$6 -> ADOBE INC. | G48: =132716/3785 -> 35.063672 | H48: =132716/3785 -> 35.063672 | I48: =132716/3785 -> 35.063672 | J48: =279000/3785 -> 73.712021 | K48: =251136/3785 -> 66.35033 | L48: =262413/3785 -> 69.329723 | M48: =260142/3785 -> 68.729723 | N48: =203958/3785 -> 53.885865 | O48: =264682/3785 -> 69.929194 | P48: =318834/3785 -> 84.236196 | Q48: 84 | R48: =IFERROR((Q48/G48)^(1/COUNT($G$4:$Q$4))-1,"") -> 0.082662012
B49: INTUIT INC. | R49: =IFERROR((Q49/G49)^(1/COUNT($G$4:$Q$4))-1,"")
B50: SALESFORCE, INC. | G50: 195 | H50: 195 | I50: 195 | J50: 195 | K50: 195 | L50: 195 | M50: 164 | N50: 120 | O50: 130 | P50: 126 | Q50: 153 | R50: =IFERROR((Q50/G50)^(1/COUNT($G$4:$Q$4))-1,"") -> -0.021809711
B51: =+$B$9 -> WORKDAY, INC. | G51: - | H51: - | I51: - | J51: - | K51: - | L51: - | M51: - | N51: - | O51: - | P51: - | Q51: - | R51: =IFERROR((Q51/G51)^(1/COUNT($G$4:$Q$4))-1,"")
B52: =+$B$10 -> DATADOG, INC. | R52: =IFERROR((Q52/G52)^(1/COUNT($G$4:$Q$4))-1,"")
B53: =+$B$11 -> HUBSPOT, INC. | R53: =IFERROR((Q53/G53)^(1/COUNT($G$4:$Q$4))-1,"")
B54: =+$B$12 -> Sap Se | R54: =IFERROR((Q54/G54)^(1/COUNT($G$4:$Q$4))-1,"")
B55: =+$B$13 -> SERVICENOW, INC. | R55: =IFERROR((Q55/G55)^(1/COUNT($G$4:$Q$4))-1,"")
B56: =+$B$14 -> AUTODESK, INC. | R56: =IFERROR((Q56/G56)^(1/COUNT($G$4:$Q$4))-1,"")
B57: =+$B$15 -> SNOWFLAKE INC. | R57: =IFERROR((Q57/G57)^(1/COUNT($G$4:$Q$4))-1,"")
B58: =+$B$16 -> ATLASSIAN CORPORATION | R58: =IFERROR((Q58/G58)^(1/COUNT($G$4:$Q$4))-1,"")
A60: x | B60: Total Waste Production | G60: 2014 | H60: =+G60+1 -> 2015 | I60: =+H60+1 -> 2016 | J60: =+I60+1 -> 2017 | K60: =+J60+1 -> 2018 | L60: =+K60+1 -> 2019 | M60: =+L60+1 -> 2020 | N60: =+M60+1 -> 2021 | O60: =+N60+1 -> 2022 | ... Q60: =+P60+1 -> 2024 | R60: ="CAGR "&$G$4&" - "&$Q$4 -> CAGR 2014 - 2024
B62: =+$B$6 -> ADOBE INC. | G62: 1225 | H62: 1254 | I62: 1111 | J62: 1669 | K62: 1802 | L62: 1850 | M62: 1581 | N62: 1189 | O62: 1992 | P62: 1607 | R62: =IFERROR((Q62/G62)^(1/COUNT($G$4:$Q$4))-1,"") -> -1
B63: =+$B$7 -> SALESFORCE, INC. | R63: =IFERROR((Q63/G63)^(1/COUNT($G$4:$Q$4))-1,"")
B64: =+$B$8 -> INTUIT INC. | R64: =IFERROR((Q64/G64)^(1/COUNT($G$4:$Q$4))-1,"")
B65: =+$B$9 -> WORKDAY, INC. | R65: =IFERROR((Q65/G65)^(1/COUNT($G$4:$Q$4))-1,"")
B66: =+$B$10 -> DATADOG, INC. | R66: =IFERROR((Q66/G66)^(1/COUNT($G$4:$Q$4))-1,"")
B67: =+$B$11 -> HUBSPOT, INC. | R67: =IFERROR((Q67/G67)^(1/COUNT($G$4:$Q$4))-1,"")
B68: =+$B$12 -> Sap Se | R68: =IFERROR((Q68/G68)^(1/COUNT($G$4:$Q$4))-1,"")
B69: =+$B$13 -> SERVICENOW, INC. | R69: =IFERROR((Q69/G69)^(1/COUNT($G$4:$Q$4))-1,"")
B70: =+$B$14 -> AUTODESK, INC. | G70: 477 | H70: 631 | I70: 919 | J70: 620 | K70: 630 | L70: 684 | M70: 2060 | N70: 526 | O70: 1480 | P70: 2080 | Q70: 625 | R70: =IFERROR((Q70/G70)^(1/COUNT($G$4:$Q$4))-1,"") -> 0.024871084
B71: =+$B$15 -> SNOWFLAKE INC. | R71: =IFERROR((Q71/G71)^(1/COUNT($G$4:$Q$4))-1,"")
B72: =+$B$16 -> ATLASSIAN CORPORATION | R72: =IFERROR((Q72/G72)^(1/COUNT($G$4:$Q$4))-1,"")
A74: x | B74: GHG Scope 1 and 2 Emissions | G74: 2014 | H74: =+G74+1 -> 2015 | I74: =+H74+1 -> 2016 | J74: =+I74+1 -> 2017 | K74: =+J74+1 -> 2018 | L74: =+K74+1 -> 2019 | M74: =+L74+1 -> 2020 | N74: =+M74+1 -> 2021 | O74: =+N74+1 -> 2022 | ... Q74: =+P74+1 -> 2024 | R74: ="CAGR "&$G$4&" - "&$Q$4 -> CAGR 2014 - 2024
B76: =+$B$6 -> ADOBE INC. | G76: =+G6+G20 -> 72401 | H76: =+H6+H20 -> 76717 | I76: =+I6+I20 -> 72957 | J76: =+J6+J20 -> 80465 | K76: =+K6+K20 -> 71073 | L76: =+L6+L20 -> 67945 | M76: =+M6+M20 -> 61018 | N76: =+N6+N20 -> 66131 | ... Q76: =+Q6+Q20 -> 70311 | R76: =IFERROR((Q76/G76)^(1/COUNT($G$4:$Q$4))-1,"") -> -0.0026593533
B77: =+$B$7 -> SALESFORCE, INC. | G77: =+G7+G21 -> 54000 | H77: =+H7+H21 -> 76000 | I77: =+I7+I21 -> 135000 | J77: =+J7+J21 -> 138000 | K77: =+K7+K21 -> 143000 | L77: =+L7+L21 -> 163000 | M77: =+M7+M21 -> 297000 | N77: =+N7+N21 -> 293000 | ... Q77: =+Q7+Q21 -> 318000 | R77: =IFERROR((Q77/G77)^(1/COUNT($G$4:$Q$4))-1,"") -> 0.17490576
B78: =+$B$8 -> INTUIT INC. | G78: =+G8+G22 -> 0 | H78: =+H8+H22 -> 0 | I78: =+I8+I22 -> 0 | J78: =+J8+J22 -> 0 | K78: =+K8+K22 -> 0 | L78: =+L8+L22 -> 0 | M78: =+M8+M22 -> 0 | N78: =+N8+N22 -> 0 | ... Q78: =+Q8+Q22 -> 0 | R78: =IFERROR((Q78/G78)^(1/COUNT($G$4:$Q$4))-1,"")
B79: =+$B$9 -> WORKDAY, INC. | G79: =+G9+G23 -> 18929 | H79: =+H9+H23 -> 18929 | I79: =+I9+I23 -> 18929 | J79: =+J9+J23 -> 29212 | K79: =+K9+K23 -> 35710 | L79: =+L9+L23 -> 36370 | M79: =+M9+M23 -> 38541 | N79: =+N9+N23 -> 42055 | ... Q79: =+Q9+Q23 -> 70309 | R79: =IFERROR((Q79/G79)^(1/COUNT($G$4:$Q$4))-1,"") -> 0.12669812
B80: =+$B$10 -> DATADOG, INC. | G80: =+G10+G24 -> 0 | H80: =+H10+H24 -> 0 | I80: =+I10+I24 -> 0 | J80: =+J10+J24 -> 0 | K80: =+K10+K24 -> 0 | L80: =+L10+L24 -> 0 | M80: =+M10+M24 -> 0 | N80: =+N10+N24 -> 0 | ... Q80: =+Q10+Q24 -> 0 | R80: =IFERROR((Q80/G80)^(1/COUNT($G$4:$Q$4))-1,"")
B81: =+$B$11 -> HUBSPOT, INC. | G81: =+G11+G25 -> 0 | H81: =+H11+H25 -> 0 | I81: =+I11+I25 -> 0 | J81: =+J11+J25 -> 0 | K81: =+K11+K25 -> 0 | L81: =+L11+L25 -> 0 | M81: =+M11+M25 -> 0 | N81: =+N11+N25 -> 0 | ... Q81: =+Q11+Q25 -> 0 | R81: =IFERROR((Q81/G81)^(1/COUNT($G$4:$Q$4))-1,"")
B82: =+$B$12 -> Sap Se | G82: =+G12+G26 -> 0 | H82: =+H12+H26 -> 0 | I82: =+I12+I26 -> 0 | J82: =+J12+J26 -> 0 | K82: =+K12+K26 -> 0 | L82: =+L12+L26 -> 0 | M82: =+M12+M26 -> 0 | N82: =+N12+N26 -> 0 | ... Q82: =+Q12+Q26 -> 0 | R82: =IFERROR((Q82/G82)^(1/COUNT($G$4:$Q$4))-1,"")
B83: =+$B$13 -> SERVICENOW, INC. | G83: =+G13+G27 -> 0 | H83: =+H13+H27 -> 0 | I83: =+I13+I27 -> 0 | J83: =+J13+J27 -> 0 | K83: =+K13+K27 -> 0 | L83: =+L13+L27 -> 0 | M83: =+M13+M27 -> 0 | N83: =+N13+N27 -> 0 | ... Q83: =+Q13+Q27 -> 0 | R83: =IFERROR((Q83/G83)^(1/COUNT($G$4:$Q$4))-1,"")
B84: =+$B$14 -> AUTODESK, INC. | G84: =+G14+G28 -> 0 | H84: =+H14+H28 -> 0 | I84: =+I14+I28 -> 0 | J84: =+J14+J28 -> 0 | K84: =+K14+K28 -> 0 | L84: =+L14+L28 -> 0 | M84: =+M14+M28 -> 0 | N84: =+N14+N28 -> 0 | ... Q84: =+Q14+Q28 -> 0 | R84: =IFERROR((Q84/G84)^(1/COUNT($G$4:$Q$4))-1,"")
B85: =+$B$15 -> SNOWFLAKE INC. | G85: =+G15+G29 -> 0 | H85: =+H15+H29 -> 0 | I85: =+I15+I29 -> 0 | J85: =+J15+J29 -> 0 | K85: =+K15+K29 -> 0 | L85: =+L15+L29 -> 0 | M85: =+M15+M29 -> 0 | N85: =+N15+N29 -> 0 | ... Q85: =+Q15+Q29 -> 0 | R85: =IFERROR((Q85/G85)^(1/COUNT($G$4:$Q$4))-1,"")
B86: =+$B$16 -> ATLASSIAN CORPORATION | G86: =+G16+G30 -> 0 | H86: =+H16+H30 -> 0 | I86: =+I16+I30 -> 0 | J86: =+J16+J30 -> 0 | K86: =+K16+K30 -> 0 | L86: =+L16+L30 -> 0 | M86: =+M16+M30 -> 0 | N86: =+N16+N30 -> 0 | ... Q86: =+Q16+Q30 -> 0 | R86: =IFERROR((Q86/G86)^(1/COUNT($G$4:$Q$4))-1,"")

Sheet DCF
B2: DCF
A4: x | B4: Key Assumptions | R4: #VALUE!
B6: Switches | E6: Bear Case | H6: Base Case | K6: Bull Case | X6: FCFF | Y6: FCFE | Z6: Tax Shield | AA6: Total Payout | AB6: NOPAT | AC6: Debt Borrowing | AD6: Cash Balance | AE6: Total Assets | AF6: Total Liabilities | AG6: Shareholder's Equity | AH6: Current Liabilities | AI6: Current Assets
B7: Revenue | C7: 2 | E7: Revenue | F7: -0.02 | H7: Revenue | K7: Revenue | L7: 0.02 | S7: Most Recent Fiscal Year | T7: 2024 | W7: 2022 | X7: =+E192 -> 8662.8478 | Y7: =+E229 -> 7342 | Z7: =+#REF! -> #REF! | AA7: =+#REF! -> #REF! | AB7: =+E182 -> 6076.8478 | AC7: =+E227 -> 0 | AD7: =+E88 -> 6096
B8: EBIT | C8: 2 | E8: EBIT | F8: -0.01 | H8: EBIT | K8: EBIT | L8: 0.01 | S8: End of Fiscal Year | T8: Nov 29th(2024)/ Dec1st(2023/ Dec2nd(2022)
B9: WACC | C9: 2 | E9: WACC | F9: =IFERROR(+I9+0.5%,"") -> 0.096279702 | H9: WACC | I9: =WACC!G25 -> 0.091279702 | K9: WACC | L9: =IFERROR(I9-0.5%,"") -> 0.086279702 | S9: Most Recent Quarter End Date | T9: Feb 28th, 2025 | W9: =+W8+1 -> 1 | X9: =+G192 -> 9504.3855 | Y9: =+G229 -> 10208 | Z9: =+#REF! -> #REF! | AA9: =+#REF! -> #REF! | AB9: =+G182 -> 6853.3855 | AC9: =+G227 -> 1997 | AD9: =+G88 -> 7886 | AE9: =Inputs!Q48 -> 30002 | AF9: =+Inputs!Q60 -> 16508 | AG9: =+AE9-AF9 -> 13494 | AH9: =+Inputs!Q54 -> 10521 | AI9: =+Inputs!Q38 -> 11232
B10: TGR | C10: 2 | E10: TGR | F10: =+I10-0.5% -> 0.018 | H10: TGR | I10: 0.023 | K10: TGR | L10: =+I10+0.5% -> 0.028 | S10: Valuation Date | T10: ? | W10: =+W9+1 -> 2 | X10: =+H192 -> 17212.553 | Y10: =+H229 -> 17323.432 | Z10: =+#REF! -> #REF! | AA10: =+#REF! -> #REF! | AB10: =+H182 -> 12259.462 | AC10: =+H227 -> 0 | AD10: =+H88 -> 24983.387 | AE10: =Inputs!Q48+DCF!H88+DCF!H90+DCF!H93+DCF!H96+DCF!H99+DCF!H105-DCF!G88-DCF!G90-DCF!G93-DCF!G96-DCF!G99-DCF!G105 -> 48076.761 | AF10: =+Inputs!Q60+(DCF!H110+DCF!H113+DCF!H116+DCF!H118*DCF!G110*DCF!G113*DCF!G116*DCF!G118) -> 1.1136754e+15 | AG10: =+AE10-AF10 -> -1.1136754e+15 | AH10: =+AH9+H110+H113-G110-G113 -> 14431.569 | AI10: =+H88+H90+H93+H96 -> 28616.763
W11: =+W10+1 -> 3 | X11: =+I192 -> 14132.394 | Y11: =+I229 -> 14181.562 | Z11: =+#REF! -> #REF! | AA11: =+#REF! -> #REF! | AB11: =+I182 -> 13081.199 | AC11: =+I227 -> 0 | AD11: =+I88 -> 38983.956 | AE11: =AE10+DCF!I88+DCF!I90+DCF!I93+DCF!I96+DCF!I99+DCF!I105-DCF!H88-DCF!H90-DCF!H93-DCF!H96-DCF!H99-DCF!H105 -> 62714.249 | AF11: =AF10+(DCF!I110+DCF!I113+DCF!I116+DCF!I118*DCF!H110*DCF!H113*DCF!H116*DCF!H118) -> 5.4786844e+15 | AG11: =+AE11-AF11 -> -5.4786844e+15 | AH11: =+AH10+I110+I113-H110-H113 -> 14088.485 | AI11: =+I88+I90+I93+I96 -> 42829.3
B12: WACC | C12: =CHOOSE(C9,F9,I9,L9) -> 0.091279702 | W12: =+W11+1 -> 4 | X12: =+J192 -> 14676.144 | Y12: =+J229 -> 14904.79 | Z12: =+#REF! -> #REF! | AA12: =+#REF! -> #REF! | AB12: =+J182 -> 13598.568 | AC12: =+J227 -> 0 | AD12: =+J88 -> 60395.012
B13: TGR | C13: =CHOOSE(C10,F10,I10,L10) -> 0.023 | W13: =+W12+1 -> 5 | X13: =+K192 -> 17527.7 | Y13: =+K229 -> 17666.362 | Z13: =+#REF! -> #REF! | AA13: =+#REF! -> #REF! | AB13: =+K182 -> 14574.271 | AC13: =+K227 -> 0 | AD13: =+K88 -> 77827.012
W14: =+W13+1 -> 6 | X14: =+L192 -> 17742.679 | Y14: =+L229 -> 17891.275 | Z14: =+#REF! -> #REF! | AA14: =+#REF! -> #REF! | AB14: =+L182 -> 15467.633 | AC14: =+L227 -> 0 | AD14: =+L88 -> 95481.575
A15: x | B15: Operating Assumptions | E15: 2022 | F15: =+E15+1 -> 2023 | G15: =+F15+1 -> 2024 | H15: =+G15+1 -> 2025 | I15: =+H15+1 -> 2026 | J15: =+I15+1 -> 2027 | K15: =+J15+1 -> 2028 | L15: =+K15+1 -> 2029 | M15: =+L15+1 -> 2030 | ... Q15: =+P15+1 -> 2034
B16: Operating Assumptions
B17: Revenue by Segments
B18: =Segments!B17 -> Digital Media | E18: =Segments!G17 -> 12842 | F18: =Segments!H17 -> 14216 | G18: =Segments!I17 -> 15864 | H18: =G18*(1+H19) -> 17021.822 | I18: =H18*(1+I19) -> 18264.415 | J18: =I18*(1+J19) -> 19597.717 | K18: =J18*(1+K19) -> 21028.351 | L18: =K18*(1+L19) -> 22563.42 | M18: =L18*(1+M19) -> 24210.55 | N18: =M18*(1+N19) -> 25977.92 | O18: =N18*(1+O19) -> 26497.479 | ... Q18: =P18*(1+Q19) -> 27567.977
B19: % of total growth | F19: =(F18-E18)/E18 -> 0.10699268 | G19: =(G18-F18)/F18 -> 0.11592572 | H19: =Segments!J17 -> 0.072984245 | I19: 0.073 | J19: 0.073 | K19: 0.073 | L19: 0.073 | M19: 0.073 | N19: 0.073 | O19: 0.02 | P19: 0.02 | Q19: 0.02
B21: =Segments!B18 -> Digital Experience | E21: =Segments!G18 -> 4422 | F21: =Segments!H18 -> 4893 | G21: =Segments!I18 -> 5366 | H21: =G21*(1+H22) -> 5723.4951 | I21: =H21*(1+I22) -> 6104.6798 | J21: =I21*(1+J22) -> 6511.2515 | K21: =J21*(1+K22) -> 6944.9008 | L21: =K21*(1+L22) -> 7407.4312 | M21: =L21*(1+M22) -> 7900.7662 | N21: =M21*(1+N22) -> 8426.9572 | O21: =N21*(1+O22) -> 8595.4963 | ... Q21: =P21*(1+Q22) -> 8942.7544
B22: % of total growth | F22: =(F21-E21)/E21 -> 0.10651289 | G22: =(G21-F21)/F21 -> 0.09666871 | H22: =Segments!J18 -> 0.066622261 | I22: 0.0666 | J22: 0.0666 | K22: 0.0666 | L22: 0.0666 | M22: 0.0666 | N22: 0.0666 | O22: 0.02 | P22: 0.02 | Q22: 0.02
B24: =Segments!B19 -> Publishing & Advertising | E24: =Segments!G19 -> 342 | F24: =Segments!H19 -> 300 | G24: =Segments!I19 -> 275 | H24: =G24*(1+H25) -> 255.72208 | I24: =H24*(1+I25) -> 237.79596 | J24: =I24*(1+J25) -> 221.12646 | K24: =J24*(1+K25) -> 205.6255 | L24: =K24*(1+L25) -> 191.21115 | M24: =L24*(1+M25) -> 177.80725 | N24: =M24*(1+N25) -> 165.34296 | O24: =N24*(1+O25) -> 153.75242 | ... Q24: =P24*(1+Q25) -> 132.95187
B25: % of total growth | F25: =(F24-E24)/E24 -> -0.12280702 | G25: =(G24-F24)/F24 -> -0.083333333 | H25: =Segments!J19 -> -0.070101538 | I25: -0.0701 | J25: -0.0701 | K25: -0.0701 | L25: -0.0701 | M25: -0.0701 | N25: -0.0701 | O25: -0.0701 | P25: -0.0701 | Q25: -0.0701
B26: Total | E26: =SUM(E17:E24) -> 17606 | F26: =SUM(F18,F21,F24) -> 19409 | G26: =SUM(G18,G21,G24) -> 21505 | H26: =SUM(H18,H21,H24) -> 23001.039 | I26: =SUM(I18,I21,I24) -> 24606.891 | J26: =SUM(J18,J21,J24) -> 26330.095 | K26: =SUM(K18,K21,K24) -> 28178.877 | L26: =SUM(L18,L21,L24) -> 30162.063 | M26: =SUM(M18,M21,M24) -> 32289.123 | ... Q26: =SUM(Q18,Q21,Q24) -> 36643.683
B27: In millions of USD
A28: x | B28: Income Statement | E28: 2022 | F28: =+E28+1 -> 2023 | G28: =+F28+1 -> 2024 | H28: =+G28+1 -> 2025 | I28: =+H28+1 -> 2026 | J28: =+I28+1 -> 2027 | K28: =+J28+1 -> 2028 | L28: =+K28+1 -> 2029 | M28: =+L28+1 -> 2030 | ... Q28: =+P28+1 -> 2034
B30: Revenue (Sales) | D30: =+_xlfn.XLOOKUP($B30,[1]Inputs!$B:$B,[1]Inputs!N:N) -> 67418 | E30: =+_xlfn.XLOOKUP($B30,Inputs!$B:$B,Inputs!O:O) -> 17606 | F30: =+_xlfn.XLOOKUP($B30,Inputs!$B:$B,Inputs!P:P) -> 19409 | G30: =+_xlfn.XLOOKUP($B30,Inputs!$B:$B,Inputs!Q:Q) -> 21505 | H30: =H26 -> 23001.039 | I30: =I26 -> 24606.891 | J30: =J26 -> 26330.095 | K30: =K26 -> 28178.877 | L30: =L26 -> 30162.063 | M30: =M26 -> 32289.123 | N30: =N26 -> 34570.22 | O30: =O26 -> 35246.727 | ... Q30: =Q26 -> 36643.683
B31: % of growth | F31: =IFERROR((F30-E30)/E30,"") -> 0.10240827 | G31: =IFERROR((G30-F30)/F30,"") -> 0.10799114 | H31: =IFERROR(H30/G30-1,"") -> 0.06956704 | I31: =IFERROR(I30/H30-1,"") -> 0.069816483 | J31: =IFERROR(J30/I30-1,"") -> 0.070029346 | K31: =IFERROR(K30/J30-1,"") -> 0.070215536 | L31: =IFERROR(L30/K30-1,"") -> 0.070378449 | M31: =IFERROR(M30/L30-1,"") -> 0.070521062 | N31: =IFERROR(N30/M30-1,"") -> 0.070645984 | O31: =IFERROR(O30/N30-1,"") -> 0.019569068 | ... Q31: =IFERROR(Q30/P30-1,"") -> 0.019641548
B33: COGS (Cost of Goods Sold) | E33: =+_xlfn.XLOOKUP($B33,Inputs!$B:$B,Inputs!O:O) -> 2165 | F33: =+_xlfn.XLOOKUP($B33,Inputs!$B:$B,Inputs!P:P) -> 2354 | G33: =+_xlfn.XLOOKUP($B33,Inputs!$B:$B,Inputs!Q:Q) -> 2538 | H33: =H34*H$30 -> 2777.5476 | I33: =I34*I$30 -> 2953.323 | J33: =J34*J$30 -> 3149.0505 | K33: =K34*K$30 -> 3385.0022 | L33: =L34*L$30 -> 3616.8796 | M33: =M34*M$30 -> 3870.8124 | N33: =N34*N$30 -> 4147.5062 | O33: =O34*O$30 -> 4226.8815 | ... Q33: =Q34*Q$30 -> 4395.0594
B34: % of revenue | E34: =IFERROR(E33/E$30,"") -> 0.12296944 | F34: =IFERROR(F33/F$30,"") -> 0.12128394 | G34: =IFERROR(G33/G$30,"") -> 0.11801907 | H34: =AVERAGE(E34:G34) -> 0.12075748 | I34: =AVERAGE(F34:H34) -> 0.12002016 | J34: =AVERAGE(G34:I34) -> 0.1195989 | K34: =AVERAGE(H34:J34) -> 0.12012552 | L34: =AVERAGE(I34:K34) -> 0.11991486 | M34: =AVERAGE(J34:L34) -> 0.11987976 | N34: =AVERAGE(K34:M34) -> 0.11997338 | O34: =AVERAGE(L34:N34) -> 0.11992267 | ... Q34: =AVERAGE(N34:P34) -> 0.11994044
B36: Gross Profit | E36: =+_xlfn.XLOOKUP($B36,Inputs!$B:$B,Inputs!O:O) -> 15441 | F36: =+_xlfn.XLOOKUP($B36,Inputs!$B:$B,Inputs!P:P) -> 17055 | G36: =+_xlfn.XLOOKUP($B36,Inputs!$B:$B,Inputs!Q:Q) -> 18967 | H36: =+H30-H33 -> 20223.492 | I36: =+I30-I33 -> 21653.568 | J36: =+J30-J33 -> 23181.045 | K36: =+K30-K33 -> 24793.875 | L36: =+L30-L33 -> 26545.183 | M36: =+M30-M33 -> 28418.311 | N36: =+N30-N33 -> 30422.714 | O36: =+O30-O33 -> 31019.846 | ... Q36: =+Q30-Q33 -> 32248.624
B37: Gross Profit Margin | E37: =IFERROR(E36/E$30,"") -> 0.87703056 | F37: =IFERROR(F36/F$30,"") -> 0.87871606 | G37: =IFERROR(G36/G$30,"") -> 0.88198093 | H37: =IFERROR(H36/H$30,"") -> 0.87924252 | I37: =IFERROR(I36/I$30,"") -> 0.87997984 | J37: =IFERROR(J36/J$30,"") -> 0.8804011 | K37: =IFERROR(K36/K$30,"") -> 0.87987448 | L37: =IFERROR(L36/L$30,"") -> 0.88008514 | ... Q37: =IFERROR(Q36/Q$30,"") -> 0.88005956
B39: SG&A (Selling, General & Administrative) | E39: =+_xlfn.XLOOKUP($B39,Inputs!$B:$B,Inputs!O:O) -> 5170 | F39: =+_xlfn.XLOOKUP($B39,Inputs!$B:$B,Inputs!P:P) -> 6764 | G39: =+_xlfn.XLOOKUP($B39,Inputs!$B:$B,Inputs!Q:Q) -> 5764 | H39: =IFERROR(G39*(1+H31),"") -> 6164.9844 | I39: =IFERROR(H39*(1+I31),"") -> 6595.4019 | J39: =IFERROR(I39*(1+J31),"") -> 7057.2736 | K39: =IFERROR(J39*(1+K31),"") -> 7552.8039 | L39: =IFERROR(K39*(1+L31),"") -> 8084.3585 | M39: =IFERROR(L39*(1+M31),"") -> 8654.4761 | N39: =IFERROR(M39*(1+N31),"") -> 9265.88 | O39: =IFERROR(N39*(1+O31),"") -> 9447.2047 | ... Q39: =IFERROR(P39*(1+Q31),"") -> 9821.6317
B40: SG&A Margin | E40: =IFERROR(E39/E$30,"") -> 0.29364989 | F40: =IFERROR(F39/F$30,"") -> 0.34849812 | G40: =IFERROR(G39/G$30,"") -> 0.26803069 | H40: 0.17 | I40: =IFERROR(AVERAGE(F40:H40),"") -> 0.26217627 | J40: =IFERROR(AVERAGE(G40:I40),"") -> 0.23340232 | K40: =IFERROR(AVERAGE(H40:J40),"") -> 0.22185953 | L40: =IFERROR(AVERAGE(I40:K40),"") -> 0.23914604 | M40: =IFERROR(AVERAGE(J40:L40),"") -> 0.2314693 | N40: =IFERROR(AVERAGE(K40:M40),"") -> 0.23082496 | O40: =IFERROR(AVERAGE(L40:N40),"") -> 0.23381343 | P40: =IFERROR(AVERAGE(M40:O40),"") -> 0.23203589 | Q40: =IFERROR(AVERAGE(N40:P40),"") -> 0.23222476
B42: R&D (Research & Development) | E42: =+_xlfn.XLOOKUP($B42,Inputs!$B:$B,Inputs!O:O) -> 2987 | F42: =+_xlfn.XLOOKUP($B42,Inputs!$B:$B,Inputs!P:P) -> 3473 | G42: =+_xlfn.XLOOKUP($B42,Inputs!$B:$B,Inputs!Q:Q) -> 3944 | H42: =H43*H$30 -> 0 | I42: =I43*I$30 -> 0 | J42: =J43*J$30 -> 0 | K42: =K43*K$30 -> 0 | L42: =L43*L$30 -> 0 | M42: =M43*M$30 -> 0 | N42: =N43*N$30 -> 0 | O42: =O43*O$30 -> 0 | ... Q42: =Q43*Q$30 -> 0
B43: % of revenue | E43: =IFERROR(E42/E30,"") -> 0.16965807 | F43: =IFERROR(F42/F30,"") -> 0.17893761 | G43: =IFERROR(G42/G30,"") -> 0.18339921 | H43: 0 | I43: 0 | J43: 0 | K43: 0 | L43: 0 | M43: 0 | N43: 0 | O43: 0 | P43: 0 | Q43: 0
B45: Other Operating (Income) Expenses | E45: =+_xlfn.XLOOKUP($B45,Inputs!$B:$B,Inputs!O:O) -> 1098 | F45: =+_xlfn.XLOOKUP($B45,Inputs!$B:$B,Inputs!P:P) -> 0 | G45: =+_xlfn.XLOOKUP($B45,Inputs!$B:$B,Inputs!Q:Q) -> 1529 | H45: =IFERROR(AVERAGE(E45:G45)*(1+H31),"") -> 936.5842 | I45: =IFERROR(AVERAGE(F45:H45)*(1+I31),"") -> 879.24087 | J45: =IFERROR(AVERAGE(G45:I45)*(1+J31),"") -> 1193.0203 | K45: =IFERROR(AVERAGE(H45:J45)*(1+K31),"") -> 1073.371 | L45: =IFERROR(AVERAGE(I45:K45)*(1+L31),"") -> 1122.339 | M45: =IFERROR(AVERAGE(J45:L45)*(1+M31),"") -> 1209.2357 | N45: =IFERROR(AVERAGE(K45:M45)*(1+N31),"") -> 1215.1638 | O45: =IFERROR(AVERAGE(L45:N45)*(1+O31),"") -> 1205.3816 | ... Q45: =IFERROR(AVERAGE(N45:P45)*(1+Q31),"") -> 1241.9899
B47: EBITDA | E47: =+_xlfn.XLOOKUP($B47,Inputs!$B:$B,Inputs!O:O) -> 6186 | F47: =+_xlfn.XLOOKUP($B47,Inputs!$B:$B,Inputs!P:P) -> 6818 | G47: =+_xlfn.XLOOKUP($B47,Inputs!$B:$B,Inputs!Q:Q) -> 7730 | H47: =IFERROR(H36-H39-H42-H45,"") -> 13121.923 | I47: =IFERROR(I36-I39-I42-I45,"") -> 14178.925 | J47: =IFERROR(J36-J39-J42-J45,"") -> 14930.751 | K47: =IFERROR(K36-K39-K42-K45,"") -> 16167.7 | L47: =IFERROR(L36-L39-L42-L45,"") -> 17338.486 | M47: =IFERROR(M36-M39-M42-M45,"") -> 18554.599 | N47: =IFERROR(N36-N39-N42-N45,"") -> 19941.67 | O47: =IFERROR(O36-O39-O42-O45,"") -> 20367.259 | ... Q47: =IFERROR(Q36-Q39-Q42-Q45,"") -> 21185.002
B48: EBITDA Margin | E48: =IFERROR(E47/E$30,"") -> 0.35135749 | F48: =IFERROR(F47/F$30,"") -> 0.35128033 | G48: =IFERROR(G47/G$30,"") -> 0.35945129 | H48: =IFERROR(H47/H$30,"") -> 0.57049261 | I48: =IFERROR(I47/I$30,"") -> 0.57621766 | J48: =IFERROR(J47/J$30,"") -> 0.56706026 | K48: =IFERROR(K47/K$30,"") -> 0.57375246 | L48: =IFERROR(L47/L$30,"") -> 0.57484416 | ... Q48: =IFERROR(Q47/Q$30,"") -> 0.57813517
B50: D&A (Depreciation & Amortization) | E50: =+_xlfn.XLOOKUP($B50,Inputs!$B:$B,Inputs!O:O) -> 856 | F50: =+_xlfn.XLOOKUP($B50,Inputs!$B:$B,Inputs!P:P) -> 872 | G50: =+_xlfn.XLOOKUP($B50,Inputs!$B:$B,Inputs!Q:Q) -> 857 | H50: =+IFERROR(H53+H56,"") -> 824.38943 | I50: =+IFERROR(I53+I56,"") -> 1058.7376 | J50: =+IFERROR(J53+J56,"") -> 1291.6229 | K50: =+IFERROR(K53+K56,"") -> 1549.3725 | L50: =+IFERROR(L53+L56,"") -> 1824.5214 | M50: =+IFERROR(M53+M56,"") -> 2118.059 | N50: =+IFERROR(N53+N56,"") -> 2435.5251 | O50: =+IFERROR(O53+O56,"") -> 2774.416 | ... Q50: =+IFERROR(Q53+Q56,"") -> 2966.4388
B51: % of PP&E+ROU Assets+Intangibles excl. Goodwill | E51: =IFERROR(E50/AVERAGE(Inputs!O39+Inputs!O42+Inputs!O44,Inputs!N39+Inputs!N42+Inputs!N44),"") -> 0.057378423 | F51: =IFERROR(F50/AVERAGE(Inputs!P39+Inputs!P42+Inputs!P44,Inputs!O39+Inputs!O42+Inputs!O44),"") -> 0.057567255 | G51: =IFERROR(G50/AVERAGE(Inputs!Q39+Inputs!Q42+Inputs!Q44,Inputs!P39+Inputs!P42+Inputs!P44),"") -> 0.056634946 | H51: =IFERROR(H50/(G99+G105),"") -> 0.24943704 | I51: =IFERROR(I50/(H99+H105),"") -> 0.26501582 | J51: =IFERROR(J50/(I99+I105),"") -> 0.29222577 | K51: =IFERROR(K50/(J99+J105),"") -> 0.3299197 | L51: =IFERROR(L50/(K99+K105),"") -> 0.37392936 | M51: =IFERROR(M50/(L99+L105),"") -> 0.43528408 | N51: =IFERROR(N50/(M99+M105),"") -> 0.51985948 | O51: =IFERROR(O50/(N99+N105),"") -> 0.64082225 | ... Q51: =IFERROR(Q50/(P99+P105),"") -> 55.713306
B53: Depreciation Expense | E53: =+_xlfn.XLOOKUP($B53,Inputs!$B:$B,Inputs!O:O) -> 687 | F53: =+_xlfn.XLOOKUP($B53,Inputs!$B:$B,Inputs!P:P) -> 704 | G53: =+_xlfn.XLOOKUP($B53,Inputs!$B:$B,Inputs!Q:Q) -> 690 | H53: =IFERROR(H54*(G100+G101),"") -> 688.18517 | I53: =IFERROR(I54*(H100+H101),"") -> 919.32384 | J53: =IFERROR(J54*(I100+I101),"") -> 1152.8843 | K53: =IFERROR(K54*(J100+J101),"") -> 1411.2537 | L53: =IFERROR(L54*(K100+K101),"") -> 1685.7643 | M53: =IFERROR(M54*(L100+L101),"") -> 1979.5208 | N53: =IFERROR(N54*(M100+M101),"") -> 2297.0537 | O53: =IFERROR(O54*(N100+N101),"") -> 2635.8272 | ... Q53: =IFERROR(Q54*(P100+P101),"") -> 2827.9078
B54: % of PP&E+ROU Assets | E54: =IFERROR(E53/AVERAGE(Inputs!O40+Inputs!O42,Inputs!N40+Inputs!N42),"") -> 0.18562551 | F54: =IFERROR(F53/AVERAGE(Inputs!P40+Inputs!P42,Inputs!O40+Inputs!O42),"") -> 0.17593402 | G54: =IFERROR(G53/AVERAGE(Inputs!Q40+Inputs!Q42,Inputs!P40+Inputs!P42),"") -> 0.17164179 | H54: =IFERROR(AVERAGE(E54:G54),"") -> 0.17773377 | I54: =IFERROR(AVERAGE(F54:H54),"") -> 0.1751032 | J54: =IFERROR(AVERAGE(G54:I54),"") -> 0.17482625 | K54: =IFERROR(AVERAGE(H54:J54),"") -> 0.17588774 | L54: =IFERROR(AVERAGE(I54:K54),"") -> 0.1752724 | M54: =IFERROR(AVERAGE(J54:L54),"") -> 0.1753288 | N54: =IFERROR(AVERAGE(K54:M54),"") -> 0.17549631 | O54: =IFERROR(AVERAGE(L54:N54),"") -> 0.17536584 | ... Q54: =IFERROR(AVERAGE(N54:P54),"") -> 0.17541971
B56: Amortization Expense | E56: =+_xlfn.XLOOKUP($B56,Inputs!$B:$B,Inputs!O:O) -> 169 | F56: =+_xlfn.XLOOKUP($B56,Inputs!$B:$B,Inputs!P:P) -> 168 | G56: =+_xlfn.XLOOKUP($B56,Inputs!$B:$B,Inputs!Q:Q) -> 167 | H56: =+H57*(G105+1) -> 136.20425 | I56: =+I57*(H105+1) -> 139.41379 | J56: =+J57*(I105+1) -> 138.73855 | K56: =+K57*(J105+1) -> 138.11886 | L56: =+L57*(K105+1) -> 138.75707 | M56: =+M57*(L105+1) -> 138.53816 | N56: =+N57*(M105+1) -> 138.47136 | O56: =+O57*(N105+1) -> 138.58886 | ... Q56: =+Q57*(P105+1) -> 138.53101
B57: % of Intangibles excl. Goodwill | E57: =IFERROR(E56/AVERAGE(Inputs!N45:O45),"") -> 0.11623109 | F57: =IFERROR(F56/AVERAGE(Inputs!O45:P45),"") -> 0.12988017 | G57: =IFERROR(G56/AVERAGE(Inputs!P45:Q45),"") -> 0.12910707 | H57: =AVERAGE(E57:G57) -> 0.12507278 | I57: =AVERAGE(F57:H57) -> 0.12802001 | J57: =AVERAGE(G57:I57) -> 0.12739995 | K57: =AVERAGE(H57:J57) -> 0.12683091 | L57: =AVERAGE(I57:K57) -> 0.12741696 | M57: =AVERAGE(J57:L57) -> 0.12721594 | N57: =AVERAGE(K57:M57) -> 0.1271546 | O57: =AVERAGE(L57:N57) -> 0.1272625 | ... Q57: =AVERAGE(N57:P57) -> 0.12720937
B59: Operating Income (EBIT) | E59: =+_xlfn.XLOOKUP($B59,Inputs!$B:$B,Inputs!O:O) -> 6098 | F59: =+_xlfn.XLOOKUP($B59,Inputs!$B:$B,Inputs!P:P) -> 5946 | G59: =+_xlfn.XLOOKUP($B59,Inputs!$B:$B,Inputs!Q:Q) -> 6873 | H59: =+IFERROR(H47-H50,"") -> 12297.534 | I59: =+IFERROR(I47-I50,"") -> 13120.187 | J59: =+IFERROR(J47-J50,"") -> 13639.128 | K59: =+IFERROR(K47-K50,"") -> 14618.327 | L59: =+IFERROR(L47-L50,"") -> 15513.964 | M59: =+IFERROR(M47-M50,"") -> 16436.54 | N59: =+IFERROR(N47-N50,"") -> 17506.145 | O59: =+IFERROR(O47-O50,"") -> 17592.843 | ... Q59: =+IFERROR(Q47-Q50,"") -> 18218.563
B60: Operating Margin | E60: =IFERROR(E59/E$30,"") -> 0.3463592 | F60: =IFERROR(F59/F$30,"") -> 0.30635272 | G60: =IFERROR(G59/G$30,"") -> 0.31960009 | H60: =IFERROR(H59/H30,"") -> 0.53465122 | I60: =IFERROR(I59/I30,"") -> 0.53319159 | J60: =IFERROR(J59/J30,"") -> 0.51800526 | K60: =IFERROR(K59/K30,"") -> 0.51876899 | L60: =IFERROR(L59/L30,"") -> 0.51435356 | M60: =IFERROR(M59/M30,"") -> 0.50904263 | N60: =IFERROR(N59/N30,"") -> 0.5063938 | O60: =IFERROR(O59/O30,"") -> 0.4991341 | ... Q60: =IFERROR(Q59/Q30,"") -> 0.49718155
B62: Net Interest Expense (Income) | E62: =+_xlfn.XLOOKUP($B62,Inputs!$B:$B,Inputs!O:O) -> 51 | F62: =+_xlfn.XLOOKUP($B62,Inputs!$B:$B,Inputs!P:P) -> -156 | G62: =+_xlfn.XLOOKUP($B62,Inputs!$B:$B,Inputs!Q:Q) -> -172 | H62: =-H65-H68 -> 0 | I62: =-I65-I68 -> 0 | J62: =-J65-J68 -> 0 | K62: =-K65-K68 -> 0 | L62: =-L65-L68 -> 0 | M62: =-M65-M68 -> 0 | N62: =-N65-N68 -> 0 | O62: =-O65-O68 -> 0 | ... Q62: =-Q65-Q68 -> 0
B63: % of Net Debt | E63: =IFERROR(E62/AVERAGE(Inputs!N118:O118),"") -> 0.010481715 | F63: =IFERROR(F62/AVERAGE(Inputs!O118:P118),"") -> -0.032587408 | G63: =IFERROR(G62/AVERAGE(Inputs!P118:Q118),"") -> -0.033526703 | H63: =IFERROR(H62/AVERAGE(G116+G118,H116+H118),"") -> 0 | I63: =IFERROR(I62/AVERAGE(H116+H118,I116+I118),"") -> 0 | J63: =IFERROR(J62/AVERAGE(I116+I118,J116+J118),"") -> 0 | K63: =IFERROR(K62/AVERAGE(J116+J118,K116+K118),"") -> 0 | L63: =IFERROR(L62/AVERAGE(K116+K118,L116+L118),"") -> 0 | M63: =IFERROR(M62/AVERAGE(L116+L118,M116+M118),"") -> 0 | N63: =IFERROR(N62/AVERAGE(M116+M118,N116+N118),"") -> 0 | O63: =IFERROR(O62/AVERAGE(N116+N118,O116+O118),"") -> 0 | ... Q63: =IFERROR(Q62/AVERAGE(P116+P118,Q116+Q118),"") -> 0
B65: Interest Expense | E65: =+_xlfn.XLOOKUP($B65,Inputs!$B:$B,Inputs!O:O) -> 112 | F65: =+_xlfn.XLOOKUP($B65,Inputs!$B:$B,Inputs!P:P) -> 113 | G65: =+_xlfn.XLOOKUP($B65,Inputs!$B:$B,Inputs!Q:Q) -> 169
B66: % of Debt | E66: =+IFERROR(E65/AVERAGE(Inputs!N115:O115),"") -> 0.21252372 | F66: =+IFERROR(F65/AVERAGE(Inputs!O115:P115),"") -> 0.23789474 | G66: =+IFERROR(G65/AVERAGE(Inputs!P115:Q115),"") -> 0.38672769 | H66: =AVERAGE(E66:G67) -> 0.27904871 | I66: =AVERAGE(F66:H67) -> 0.30122371 | J66: =AVERAGE(G66:I67) -> 0.32233337 | K66: =AVERAGE(H66:J67) -> 0.3008686 | L66: =AVERAGE(I66:K67) -> 0.3081419 | M66: =AVERAGE(J66:L67) -> 0.31044796 | N66: =AVERAGE(K66:M67) -> 0.30648615 | O66: =AVERAGE(L66:N67) -> 0.30835867 | ... Q66: =AVERAGE(N66:P67) -> 0.30775858
B68: Interest Income | E68: =+_xlfn.XLOOKUP($B68,Inputs!$B:$B,Inputs!O:O) -> 61 | F68: =+_xlfn.XLOOKUP($B68,Inputs!$B:$B,Inputs!P:P) -> 269 | G68: =+_xlfn.XLOOKUP($B68,Inputs!$B:$B,Inputs!Q:Q) -> 341
B69: % Cash & Cash Eq. & ST Investments | E69: =IFERROR(E68/+AVERAGE(Inputs!N32:O32),"") -> 0.010257273 | F69: =IFERROR(F68/+AVERAGE(Inputs!O32:P32),"") -> 0.038599512 | G69: =IFERROR(G68/+AVERAGE(Inputs!P32:Q32),"") -> 0.043362157 | H69: =AVERAGE(F69:G69) -> 0.040980834 | I69: =AVERAGE(G69:H69) -> 0.042171496 | J69: =AVERAGE(H69:I69) -> 0.041576165 | K69: =AVERAGE(I69:J69) -> 0.04187383 | L69: =AVERAGE(J69:K69) -> 0.041724998 | M69: =AVERAGE(K69:L69) -> 0.041799414 | N69: =AVERAGE(L69:M69) -> 0.041762206 | O69: =AVERAGE(M69:N69) -> 0.04178081 | ... Q69: =AVERAGE(O69:P69) -> 0.041776159
B71: FX (Gain) Loss | E71: =+_xlfn.XLOOKUP($B71,Inputs!$B:$B,Inputs!O:O) -> 21 | F71: =+_xlfn.XLOOKUP($B71,Inputs!$B:$B,Inputs!P:P) -> 17 | G71: =+_xlfn.XLOOKUP($B71,Inputs!$B:$B,Inputs!Q:Q) -> 29 | H71: =+H72*H$17 -> 0 | I71: =+I72*I$17 -> 0 | J71: =+J72*J$17 -> 0 | K71: =+K72*K$17 -> 0 | L71: =+L72*L$17 -> 0 | M71: =+M72*M$17 -> 0 | N71: =+N72*N$17 -> 0 | O71: =+O72*O$17 -> 0 | ... Q71: =+Q72*Q$17 -> 0
B72: % of revenue
B74: Other Non-Operating (Income) Expenses | E74: =+_xlfn.XLOOKUP($B74,Inputs!$B:$B,Inputs!O:O) -> -284 | F74: =+_xlfn.XLOOKUP($B74,Inputs!$B:$B,Inputs!P:P) -> 454 | G74: =+_xlfn.XLOOKUP($B74,Inputs!$B:$B,Inputs!Q:Q) -> -481 | H74: =IFERROR(AVERAGE(E74:G74)*(1+H31),"") -> -110.87845 | I74: =IFERROR(AVERAGE(F74:H74)*(1+I31),"") -> -49.168213 | J74: =IFERROR(AVERAGE(G74:I74)*(1+J31),"") -> -228.64625 | K74: =IFERROR(AVERAGE(H74:J74)*(1+K31),"") -> -138.66173 | L74: =IFERROR(AVERAGE(I74:K74)*(1+L31),"") -> -148.59571 | M74: =IFERROR(AVERAGE(J74:L74)*(1+M31),"") -> -184.09526 | N74: =IFERROR(AVERAGE(K74:M74)*(1+N31),"") -> -168.21729 | O74: =IFERROR(AVERAGE(L74:N74)*(1+O31),"") -> -170.23686 | ... Q74: =IFERROR(AVERAGE(N74:P74)*(1+Q31),"") -> -175.39618
B76: Pre-Tax Income (EBT) | E76: =+_xlfn.XLOOKUP($B76,Inputs!$B:$B,Inputs!O:O) -> 6008 | F76: =+_xlfn.XLOOKUP($B76,Inputs!$B:$B,Inputs!P:P) -> 6799 | G76: =+_xlfn.XLOOKUP($B76,Inputs!$B:$B,Inputs!Q:Q) -> 6931 | H76: =IFERROR(+H59-H62-H71-H74,"") -> 12408.412 | I76: =IFERROR(+I59-I62-I71-I74,"") -> 13169.356 | J76: =IFERROR(+J59-J62-J71-J74,"") -> 13867.774 | K76: =IFERROR(+K59-K62-K71-K74,"") -> 14756.989 | L76: =IFERROR(+L59-L62-L71-L74,"") -> 15662.56 | M76: =IFERROR(+M59-M62-M71-M74,"") -> 16620.636 | N76: =IFERROR(+N59-N62-N71-N74,"") -> 17674.363 | O76: =IFERROR(+O59-O62-O71-O74,"") -> 17763.08 | ... Q76: =IFERROR(+Q59-Q62-Q71-Q74,"") -> 18393.959
B78: Tax Expense (Benefit) | E78: =20.84 -> 20.84 | F78: =20.16 -> 20.16 | G78: =19.78 -> 19.78 | H78: =IFERROR(H79*H$59,"") -> 38.071915 | I78: =IFERROR(I79*I$59,"") -> 38.988322 | J78: =IFERROR(J79*J$59,"") -> 40.559911 | K78: =IFERROR(K79*K$59,"") -> 44.056314 | L78: =IFERROR(L79*L$59,"") -> 46.33086 | M78: =IFERROR(M79*M$59,"") -> 49.166954 | N78: =IFERROR(N79*N$59,"") -> 52.468776 | O78: =IFERROR(O79*O$59,"") -> 52.631224 | ... Q78: =IFERROR(Q79*Q$59,"") -> 54.547352
B79: % of EBT | E79: =IFERROR(E78/E76,"") -> 0.0034687084 | F79: =IFERROR(F78/F76,"") -> 0.0029651419 | G79: =IFERROR(G78/G76,"") -> 0.002853845 | H79: =IFERROR(AVERAGE(E79:G79),"") -> 0.0030958985 | I79: =IFERROR(AVERAGE(F79:H79),"") -> 0.0029716285 | J79: =IFERROR(AVERAGE(G79:I79),"") -> 0.0029737907 | K79: =IFERROR(AVERAGE(H79:J79),"") -> 0.0030137725 | L79: =IFERROR(AVERAGE(I79:K79),"") -> 0.0029863972 | M79: =IFERROR(AVERAGE(J79:L79),"") -> 0.0029913201 | N79: =IFERROR(AVERAGE(K79:M79),"") -> 0.0029971633 | O79: =IFERROR(AVERAGE(L79:N79),"") -> 0.0029916269 | ... Q79: =IFERROR(AVERAGE(N79:P79),"") -> 0.0029940534
B81: Net Income | E81: =+_xlfn.XLOOKUP($B81,Inputs!$B:$B,Inputs!O:O) -> 4756 | F81: =+_xlfn.XLOOKUP($B81,Inputs!$B:$B,Inputs!P:P) -> 5428 | G81: =+_xlfn.XLOOKUP($B81,Inputs!$B:$B,Inputs!Q:Q) -> 5560 | H81: =IFERROR(+H76-H78,"") -> 12370.34 | I81: =IFERROR(+I76-I78,"") -> 13130.367 | J81: =IFERROR(+J76-J78,"") -> 13827.214 | K81: =IFERROR(+K76-K78,"") -> 14712.933 | L81: =IFERROR(+L76-L78,"") -> 15616.229 | M81: =IFERROR(+M76-M78,"") -> 16571.469 | N81: =IFERROR(+N76-N78,"") -> 17621.894 | O81: =IFERROR(+O76-O78,"") -> 17710.449 | ... Q81: =IFERROR(+Q76-Q78,"") -> 18339.412
B82: Net Income Margin | E82: =IFERROR(E81/E$30,"") -> 0.27013518 | F82: =IFERROR(F81/F$30,"") -> 0.27966407 | G82: =IFERROR(G81/G$30,"") -> 0.25854452 | H82: =IFERROR(H81/H$30,"") -> 0.53781657 | I82: =IFERROR(I81/I$30,"") -> 0.53360529 | J82: =IFERROR(J81/J$30,"") -> 0.52514866 | K82: =IFERROR(K81/K$30,"") -> 0.5221263 | L82: =IFERROR(L81/L$30,"") -> 0.51774407 | ... Q82: =IFERROR(Q81/Q$30,"") -> 0.5004795
A84: x | B84: Balance Sheet | E84: =E28 -> 2022 | F84: =F28 -> 2023 | G84: =G28 -> 2024 | H84: =H28 -> 2025 | I84: =I28 -> 2026 | J84: =J28 -> 2027 | K84: =K28 -> 2028 | L84: =L28 -> 2029 | ... Q84: =Q28 -> 2034
B86: Assets
B88: Cash & Cash Equivalents & ST Investments | E88: =+_xlfn.XLOOKUP($B88,Inputs!$B:$B,Inputs!O:O) -> 6096 | F88: =+_xlfn.XLOOKUP($B88,Inputs!$B:$B,Inputs!P:P) -> 7842 | G88: =+_xlfn.XLOOKUP($B88,Inputs!$B:$B,Inputs!Q:Q) -> 7886 | H88: =IFERROR(G88+H165,"") -> 24983.387 | I88: =IFERROR(H88+I165,"") -> 38983.956 | J88: =IFERROR(I88+J165,"") -> 60395.012 | K88: =IFERROR(J88+K165,"") -> 77827.012 | L88: =IFERROR(K88+L165,"") -> 95481.575 | M88: =IFERROR(L88+M165,"") -> 122817.89 | N88: =IFERROR(M88+N165,"") -> 143532.93 | O88: =IFERROR(N88+O165,"") -> 165785.72 | ... Q88: =IFERROR(P88+Q165,"") -> 221082.96
B90: Accounts Receivable | E90: =+_xlfn.XLOOKUP($B90,Inputs!$B:$B,Inputs!O:O) -> 2065 | F90: =+_xlfn.XLOOKUP($B90,Inputs!$B:$B,Inputs!P:P) -> 2224 | G90: =+_xlfn.XLOOKUP($B90,Inputs!$B:$B,Inputs!Q:Q) -> 2072 | H90: =IFERROR(H91*H30/365,"") -> 2518.5313 | I90: =IFERROR(I91*I30/365,"") -> 2630.4445 | J90: =IFERROR(J91*J30/365,"") -> 2747.1835 | K90: =IFERROR(K91*K30/365,"") -> 3012.6165 | L90: =IFERROR(L91*L30/365,"") -> 3198.6406 | M90: =IFERROR(M91*M30/365,"") -> 3415.061 | N90: =IFERROR(N91*N30/365,"") -> 3672.7861 | O90: =IFERROR(O91*O30/365,"") -> 3736.7976 | ... Q90: =IFERROR(Q91*Q30/365,"") -> 3887.5019
B91: DSO | E91: =IFERROR(E90/E30*365,"") -> 42.81069 | F91: =IFERROR(F90/F30*365,"") -> 41.823896 | G91: =IFERROR(G90/G30*366,"") -> 35.263985 | H91: =IFERROR(AVERAGE(E91:G91),"") -> 39.96619 | I91: =IFERROR(AVERAGE(F91:H91),"") -> 39.018024 | J91: =IFERROR(AVERAGE(G91:I91),"") -> 38.082733 | K91: =IFERROR(AVERAGE(H91:J91),"") -> 39.022316 | L91: =IFERROR(AVERAGE(I91:K91),"") -> 38.707691 | M91: =IFERROR(AVERAGE(J91:L91),"") -> 38.604247 | N91: =IFERROR(AVERAGE(K91:M91),"") -> 38.778084 | O91: =IFERROR(AVERAGE(L91:N91),"") -> 38.696674 | ... Q91: =IFERROR(AVERAGE(N91:P91),"") -> 38.722587
B93: Inventory | E93: =+_xlfn.XLOOKUP($B93,Inputs!$B:$B,Inputs!O:O) -> 0 | F93: =+_xlfn.XLOOKUP($B93,Inputs!$B:$B,Inputs!P:P) -> 0 | G93: =+_xlfn.XLOOKUP($B93,Inputs!$B:$B,Inputs!Q:Q) -> 0 | H93: =+IFERROR(H94*H33/365,"") -> 0 | I93: =+IFERROR(I94*I33/365,"") -> 0 | J93: =+IFERROR(J94*J33/365,"") -> 0 | K93: =+IFERROR(K94*K33/365,"") -> 0 | L93: =+IFERROR(L94*L33/365,"") -> 0 | M93: =+IFERROR(M94*M33/365,"") -> 0 | N93: =+IFERROR(N94*N33/365,"") -> 0 | O93: =+IFERROR(O94*O33/365,"") -> 0 | ... Q93: =+IFERROR(Q94*Q33/365,"") -> 0
B94: DIH | E94: =IFERROR(E93/E33*365,"") -> 0 | F94: =IFERROR(F93/F33*365,"") -> 0 | G94: =IFERROR(G93/G33*365,"") -> 0 | H94: =IFERROR(AVERAGE(E94:G94),"") -> 0 | I94: =IFERROR(AVERAGE(F94:H94),"") -> 0 | J94: =IFERROR(AVERAGE(G94:I94),"") -> 0 | K94: =IFERROR(AVERAGE(H94:J94),"") -> 0 | L94: =IFERROR(AVERAGE(I94:K94),"") -> 0 | M94: =IFERROR(AVERAGE(J94:L94),"") -> 0 | N94: =IFERROR(AVERAGE(K94:M94),"") -> 0 | O94: =IFERROR(AVERAGE(L94:N94),"") -> 0 | ... Q94: =IFERROR(AVERAGE(N94:P94),"") -> 0
B96: Prepaid expenses and Other Current Assets | E96: =+_xlfn.XLOOKUP($B96,Inputs!$B:$B,Inputs!O:O) -> 835 | F96: =+_xlfn.XLOOKUP($B96,Inputs!$B:$B,Inputs!P:P) -> 1018 | G96: =+_xlfn.XLOOKUP($B96,Inputs!$B:$B,Inputs!Q:Q) -> 1274 | H96: =IFERROR(AVERAGE(E96:G96)*(1+H31),"") -> 1114.8454 | I96: =IFERROR(AVERAGE(F96:H96)*(1+I31),"") -> 1214.8998 | J96: =IFERROR(AVERAGE(G96:I96)*(1+J31),"") -> 1285.371 | K96: =IFERROR(AVERAGE(H96:J96)*(1+K31),"") -> 1289.6512 | L96: =IFERROR(AVERAGE(I96:K96)*(1+L31),"") -> 1352.2169 | M96: =IFERROR(AVERAGE(J96:L96)*(1+M31),"") -> 1401.3974 | N96: =IFERROR(AVERAGE(K96:M96)*(1+N31),"") -> 1442.9687 | O96: =IFERROR(AVERAGE(L96:N96)*(1+O31),"") -> 1426.2354 | ... Q96: =IFERROR(AVERAGE(N96:P96)*(1+Q31),"") -> 1468.5044
B97: % of revenue | E97: =IFERROR(E96/E$30,"") -> 0.047427014 | F97: =IFERROR(F96/F$30,"") -> 0.052449894 | G97: =IFERROR(G96/G$30,"") -> 0.059242037 | H97: =IFERROR(AVERAGE(E97:G97),"") -> 0.053039648 | I97: =IFERROR(AVERAGE(F97:H97),"") -> 0.054910526 | J97: =IFERROR(AVERAGE(G97:I97),"") -> 0.055730737 | K97: =IFERROR(AVERAGE(H97:J97),"") -> 0.054560304 | L97: =IFERROR(AVERAGE(I97:K97),"") -> 0.055067189 | M97: =IFERROR(AVERAGE(J97:L97),"") -> 0.05511941 | N97: =IFERROR(AVERAGE(K97:M97),"") -> 0.054915634 | O97: =IFERROR(AVERAGE(L97:N97),"") -> 0.055034078 | ... Q97: =IFERROR(AVERAGE(N97:P97),"") -> 0.054990918
B99: Net PP&E (Property, Plant and Equipment) + ROU Assets | E99: =+E100+E101-E103 -> 2266 | F99: =+F100+F101-F103 -> 2437 | G99: =+G100+G101-G103 -> 2217 | H99: =IFERROR(H100+H101-H103,"") -> 2906.9979 | I99: =IFERROR(I100+I101-I103,"") -> 3331.9486 | J99: =IFERROR(J100+J101-J103,"") -> 3608.211 | K99: =IFERROR(K100+K101-K103,"") -> 3791.321 | L99: =IFERROR(L100+L101-L103,"") -> 3777.9233 | M99: =IFERROR(M100+M101-M103,"") -> 3596.9681 | N99: =IFERROR(N100+N101-N103,"") -> 3241.4627 | O99: =IFERROR(O100+O101-O103,"") -> 1144.1686 | ... Q99: =IFERROR(Q100+Q101-Q103,"") -> -3298.0982
B100: Gross PP&E (Property, Plant and Equipment) + ROU Assets | E100: =+_xlfn.XLOOKUP("Gross PP&E (Property, Plant and Equipment)",Inputs!$B:$B,Inputs!O:O) -> 3477 | F100: =+_xlfn.XLOOKUP("Gross PP&E (Property, Plant and Equipment)",Inputs!$B:$B,Inputs!P:P) -> 3761 | G100: =+_xlfn.XLOOKUP("Gross PP&E (Property, Plant and Equipment)",Inputs!$B:$B,Inputs!Q:Q) -> 3591 | H100: =+IFERROR(G100-H134,"") -> 4833.3248 | I100: =+IFERROR(H100-I134,"") -> 6166.6271 | J100: =+IFERROR(I100-J134,"") -> 7597.2605 | K100: =+IFERROR(J100-K134,"") -> 9132.3301 | L100: =+IFERROR(K100-L134,"") -> 10779.46 | M100: =+IFERROR(L100-M134,"") -> 12546.83 | N100: =+IFERROR(M100-N134,"") -> 14443.218 | O100: =+IFERROR(N100-O134,"") -> 14973.168 | ... Q100: =+IFERROR(P100-Q134,"") -> 16065.076
B101: Right-of-Use Assets | E101: =+_xlfn.XLOOKUP("Right-of-Use Assets",Inputs!$B:$B,Inputs!O:O) -> 358 | F101: =+_xlfn.XLOOKUP("Right-of-Use Assets",Inputs!$B:$B,Inputs!P:P) -> 407 | G101: =+_xlfn.XLOOKUP("Right-of-Use Assets",Inputs!$B:$B,Inputs!Q:Q) -> 281 | H101: =IFERROR(H102*H$30,"") -> 416.85825 | I101: =IFERROR(I102*I$30,"") -> 427.83045 | J101: =IFERROR(J102*J$30,"") -> 426.34387 | K101: =IFERROR(K102*K$30,"") -> 485.63786 | L101: =IFERROR(L102*L$30,"") -> 510.87482 | M101: =IFERROR(M102*M$30,"") -> 542.07019 | N101: =IFERROR(N102*N$30,"") -> 587.23032 | O101: =IFERROR(O102*O$30,"") -> 595.81383 | ... Q101: =IFERROR(Q102*Q$30,"") -> 620.29917
B102: % of revenue | E102: =IFERROR(E101/E$30,"") -> 0.020333977 | F102: =IFERROR(F101/F$30,"") -> 0.020969653 | G102: =IFERROR(G101/G$30,"") -> 0.013066729 | H102: =IFERROR(AVERAGE(E102:G102),"") -> 0.018123453 | I102: =IFERROR(AVERAGE(F102:H102),"") -> 0.017386612 | J102: =IFERROR(AVERAGE(G102:I102),"") -> 0.016192264 | K102: =IFERROR(AVERAGE(H102:J102),"") -> 0.01723411 | L102: =IFERROR(AVERAGE(I102:K102),"") -> 0.016937662 | M102: =IFERROR(AVERAGE(J102:L102),"") -> 0.016788012 | N102: =IFERROR(AVERAGE(K102:M102),"") -> 0.016986595 | O102: =IFERROR(AVERAGE(L102:N102),"") -> 0.016904089 | ... Q102: =IFERROR(AVERAGE(N102:P102),"") -> 0.016927861
B103: Accumulated Depreciation | E103: =+_xlfn.XLOOKUP($B103,Inputs!$B:$B,Inputs!O:O) -> 1569 | F103: =+_xlfn.XLOOKUP($B103,Inputs!$B:$B,Inputs!P:P) -> 1731 | G103: =+_xlfn.XLOOKUP($B103,Inputs!$B:$B,Inputs!Q:Q) -> 1655 | H103: =+IFERROR(G103+H53,"") -> 2343.1852 | I103: =+IFERROR(H103+I53,"") -> 3262.509 | J103: =+IFERROR(I103+J53,"") -> 4415.3933 | K103: =+IFERROR(J103+K53,"") -> 5826.647 | L103: =+IFERROR(K103+L53,"") -> 7512.4113 | M103: =+IFERROR(L103+M53,"") -> 9491.9321 | N103: =+IFERROR(M103+N53,"") -> 11788.986 | O103: =+IFERROR(N103+O53,"") -> 14424.813 | ... Q103: =+IFERROR(P103+Q53,"") -> 19983.473
B105: Intangibles excl. Goodwill | E105: =+_xlfn.XLOOKUP($B105,Inputs!$B:$B,Inputs!O:O) -> 1088 | F105: =+_xlfn.XLOOKUP($B105,Inputs!$B:$B,Inputs!P:P) -> 1499 | G105: =+_xlfn.XLOOKUP($B105,Inputs!$B:$B,Inputs!Q:Q) -> 1088 | H105: =+G105+H106*H42 -> 1088 | I105: =+H105+I106*I42 -> 1088 | J105: =+I105+J106*J42 -> 1088 | K105: =+J105+K106*K42 -> 1088 | L105: =+K105+L106*L42 -> 1088 | M105: =+L105+M106*M42 -> 1088 | N105: =+M105+N106*N42 -> 1088 | O105: =+N105+O106*O42 -> 1088 | ... Q105: =+P105+Q106*Q42 -> 1088
B106: growing with % of R&D | E106: =+_xlfn.XLOOKUP($B105,Inputs!$B:$B,Inputs!O:O) -> 1088 | F106: =+_xlfn.XLOOKUP($B105,Inputs!$B:$B,Inputs!P:P) -> 1499 | G106: =+_xlfn.XLOOKUP($B105,Inputs!$B:$B,Inputs!Q:Q) -> 1088
B108: Liabilities
B110: Accounts Payable | E110: =+_xlfn.XLOOKUP($B110,Inputs!$B:$B,Inputs!O:O) -> 379 | F110: =+_xlfn.XLOOKUP($B110,Inputs!$B:$B,Inputs!P:P) -> 314 | G110: =+_xlfn.XLOOKUP($B110,Inputs!$B:$B,Inputs!Q:Q) -> 361 | H110: =+IFERROR(H111*H33/365,"") -> 417.62778 | I110: =+IFERROR(I111*I33/365,"") -> 419.74213 | J110: =+IFERROR(J111*J33/365,"") -> 456.72938 | K110: =+IFERROR(K111*K33/365,"") -> 493.66985 | L110: =+IFERROR(L111*L33/365,"") -> 522.03975 | M110: =+IFERROR(M111*M33/365,"") -> 561.54107 | N110: =+IFERROR(N111*N33/365,"") -> 601.72742 | O110: =+IFERROR(O111*O33/365,"") -> 612.17451 | ... Q110: =+IFERROR(Q111*Q33/365,"") -> 637.14349
B111: DPO | E111: =IFERROR(E110/E$33*365,"") -> 63.896074 | F111: =IFERROR(F110/F$33*365,"") -> 48.687341 | G111: =IFERROR(G110/G$33*366,"") -> 52.059102 | H111: =IFERROR(AVERAGE(E111:G111),"") -> 54.880839 | I111: =IFERROR(AVERAGE(F111:H111),"") -> 51.87576 | J111: =IFERROR(AVERAGE(G111:I111),"") -> 52.938567 | K111: =IFERROR(AVERAGE(H111:J111),"") -> 53.231722 | L111: =IFERROR(AVERAGE(I111:K111),"") -> 52.682016 | M111: =IFERROR(AVERAGE(J111:L111),"") -> 52.950768 | N111: =IFERROR(AVERAGE(K111:M111),"") -> 52.954836 | O111: =IFERROR(AVERAGE(L111:N111),"") -> 52.86254 | ... Q111: =IFERROR(AVERAGE(N111:P111),"") -> 52.913364
B113: Accrued Expenses and Other Current Liabilities | E113: =+_xlfn.XLOOKUP($B113,Inputs!$B:$B,Inputs!O:O) -> 7162 | F113: =+_xlfn.XLOOKUP($B113,Inputs!$B:$B,Inputs!P:P) -> 7864 | G113: =+_xlfn.XLOOKUP($B113,Inputs!$B:$B,Inputs!Q:Q) -> 2336 | H113: =IFERROR(AVERAGE(E113:G113)*(1+H31),"") -> 6189.941 | I113: =IFERROR(AVERAGE(F113:H113)*(1+I31),"") -> 5844.743 | J113: =IFERROR(AVERAGE(G113:I113)*(1+J31),"") -> 5125.6845 | K113: =IFERROR(AVERAGE(H113:J113)*(1+K31),"") -> 6121.7643 | L113: =IFERROR(AVERAGE(I113:K113)*(1+L31),"") -> 6098.3713 | M113: =IFERROR(AVERAGE(J113:L113)*(1+M31),"") -> 6189.6886 | N113: =IFERROR(AVERAGE(K113:M113)*(1+N31),"") -> 6570.1348 | O113: =IFERROR(AVERAGE(L113:N113)*(1+O31),"") -> 6409.0773 | ... Q113: =IFERROR(AVERAGE(N113:P113)*(1+Q31),"") -> 6625.6739
B114: growing with revenue | E114: =IFERROR(E113/E$30,"") -> 0.40679314 | F114: =IFERROR(F113/F$30,"") -> 0.40517286 | G114: =IFERROR(G113/G$30,"") -> 0.1086259 | H114: =G114*1.07/(1+H19) -> 0.10832378 | I114: =H114*1.07/(1+I19) -> 0.10802092 | J114: =I114*1.07/(1+J19) -> 0.10771891 | K114: =J114*1.07/(1+K19) -> 0.10741774 | L114: =K114*1.07/(1+L19) -> 0.10711741 | M114: =L114*1.07/(1+M19) -> 0.10681792 | N114: =M114*1.07/(1+N19) -> 0.10651926 | O114: =N114*1.07/(1+O19) -> 0.1117408 | ... Q114: =P114*1.07/(1+Q19) -> 0.12296428
B116: Total Borrowings | E116: =+_xlfn.XLOOKUP($B116,Inputs!$B:$B,Inputs!O:O) -> 4129 | F116: =+_xlfn.XLOOKUP($B116,Inputs!$B:$B,Inputs!P:P) -> 3634 | G116: =+_xlfn.XLOOKUP($B116,Inputs!$B:$B,Inputs!Q:Q) -> 5628 | H116: =IFERROR(G116+H156-H158,"") -> 5628 | I116: =IFERROR(H116+I156-I158,"") -> 5628 | J116: =IFERROR(I116+J156-J158,"") -> 5628 | K116: =IFERROR(J116+K156-K158,"") -> 5628 | L116: =IFERROR(K116+L156-L158,"") -> 5628 | M116: =IFERROR(L116+M156-M158,"") -> 5628 | N116: =IFERROR(M116+N156-N158,"") -> 5628 | O116: =IFERROR(N116+O156-O158,"") -> 5628 | ... Q116: =IFERROR(P116+Q156-Q158,"") -> 5628
B118: Total Leases | E118: =+_xlfn.XLOOKUP($B118,Inputs!$B:$B,Inputs!O:O) -> 504 | F118: =+_xlfn.XLOOKUP($B118,Inputs!$B:$B,Inputs!P:P) -> 446 | G118: =+_xlfn.XLOOKUP($B118,Inputs!$B:$B,Inputs!Q:Q) -> 428 | H118: =+IFERROR(H119*H30,"") -> 548.25264 | I118: =+IFERROR(I119*I30,"") -> 547.23571 | J118: =+IFERROR(J119*J30,"") -> 579.06433 | K118: =+IFERROR(K119*K30,"") -> 639.35625 | L118: =+IFERROR(L119*L30,"") -> 672.82328 | M118: =+IFERROR(M119*M30,"") -> 721.00138 | N118: =+IFERROR(N119*N30,"") -> 775.82125 | O118: =+IFERROR(O119*O30,"") -> 788.09775 | ... Q118: =+IFERROR(Q119*Q30,"") -> 820.55368
B119: % of revenues | E119: =IFERROR(E118/E$30,"") -> 0.028626605 | F119: =IFERROR(F118/F$30,"") -> 0.02297903 | G119: =IFERROR(G118/G$30,"") -> 0.019902348 | H119: =+IFERROR(AVERAGE(E119:G119),"") -> 0.023835994 | I119: =+IFERROR(AVERAGE(F119:H119),"") -> 0.022239124 | J119: =+IFERROR(AVERAGE(G119:I119),"") -> 0.021992489 | K119: =+IFERROR(AVERAGE(H119:J119),"") -> 0.022689203 | L119: =+IFERROR(AVERAGE(I119:K119),"") -> 0.022306939 | M119: =+IFERROR(AVERAGE(J119:L119),"") -> 0.022329543 | N119: =+IFERROR(AVERAGE(K119:M119),"") -> 0.022441895 | O119: =+IFERROR(AVERAGE(L119:N119),"") -> 0.022359459 | ... Q119: =+IFERROR(AVERAGE(N119:P119),"") -> 0.022392773
A121: x | B121: Cash Flow | E121: =E28 -> 2022 | F121: =F28 -> 2023 | G121: =G28 -> 2024 | H121: =H28 -> 2025 | I121: =I28 -> 2026 | J121: =J28 -> 2027 | K121: =K28 -> 2028 | L121: =L28 -> 2029 | ... Q121: =Q28 -> 2034
B123: D&A (Depreciation & Amortization) | E123: =+E50 -> 856 | F123: =+F50 -> 872 | G123: =+G50 -> 857 | H123: =+H50 -> 824.38943 | I123: =+I50 -> 1058.7376 | J123: =+J50 -> 1291.6229 | K123: =+K50 -> 1549.3725 | L123: =+L50 -> 1824.5214 | ... Q123: =+Q50 -> 2966.4388
B125: Stock Based Compensation | E125: =+_xlfn.XLOOKUP($B125,Inputs!$B:$B,Inputs!O:O) -> 1440 | F125: =+_xlfn.XLOOKUP($B125,Inputs!$B:$B,Inputs!P:P) -> 1718 | G125: =+_xlfn.XLOOKUP($B125,Inputs!$B:$B,Inputs!Q:Q) -> 1833 | H125: =IFERROR(H126*H39,"") -> 1747.8348 | I125: =IFERROR(I126*I39,"") -> 1880.8109 | J125: =IFERROR(J126*J39,"") -> 2085.8675 | K125: =IFERROR(K126*K39,"") -> 2175.8188 | L125: =IFERROR(L126*L39,"") -> 2341.2673 | M125: =IFERROR(M126*M39,"") -> 2519.1688 | N125: =IFERROR(N126*N39,"") -> 2683.3009 | O125: =IFERROR(O126*O39,"") -> 2740.5609 | ... Q125: =IFERROR(Q126*Q39,"") -> 2848.0653
B126: % of SG&A | E126: =+IFERROR(E125/E39,"") -> 0.27852998 | F126: =+IFERROR(F125/F39,"") -> 0.25399172 | G126: =+IFERROR(G125/G39,"") -> 0.31800833 | H126: =IFERROR(AVERAGE(E126:G126),"") -> 0.28351001 | I126: =IFERROR(AVERAGE(F126:H126),"") -> 0.28517002 | J126: =IFERROR(AVERAGE(G126:I126),"") -> 0.29556279 | K126: =IFERROR(AVERAGE(H126:J126),"") -> 0.28808094 | L126: =IFERROR(AVERAGE(I126:K126),"") -> 0.28960458 | M126: =IFERROR(AVERAGE(J126:L126),"") -> 0.29108277 | N126: =IFERROR(AVERAGE(K126:M126),"") -> 0.28958943 | O126: =IFERROR(AVERAGE(L126:N126),"") -> 0.29009226 | ... Q126: =IFERROR(AVERAGE(N126:P126),"") -> 0.28997884
B128: Changes in Net Working Capital | E128: =+_xlfn.XLOOKUP($B128,Inputs!$B:$B,Inputs!O:O) -> 732 | F128: =+_xlfn.XLOOKUP($B128,Inputs!$B:$B,Inputs!P:P) -> -37 | G128: =+_xlfn.XLOOKUP($B128,Inputs!$B:$B,Inputs!Q:Q) -> 144 | H128: =IFERROR(-((H90+H93+H96-H110-H113)-(G90+G93+G96-G110-G113)),"") -> 3623.1921 | I128: =IFERROR(-((I90+I93+I96-I110-I113)-(H90+H93+H96-H110-H113)),"") -> -555.0513 | J128: =IFERROR(-((J90+J93+J96-J110-J113)-(I90+I93+I96-I110-I113)),"") -> -869.28149 | K128: =IFERROR(-((K90+K93+K96-K110-K113)-(J90+J93+J96-J110-J113)),"") -> 763.30712 | L128: =IFERROR(-((L90+L93+L96-L110-L113)-(K90+K93+K96-K110-K113)),"") -> -243.61293 | M128: =IFERROR(-((M90+M93+M96-M110-M113)-(L90+L93+L96-L110-L113)),"") -> -134.78232 | N128: =IFERROR(-((N90+N93+N96-N110-N113)-(M90+M93+M96-M110-M113)),"") -> 121.33623 | O128: =IFERROR(-((O90+O93+O96-O110-O113)-(N90+N93+N96-N110-N113)),"") -> -197.88861 | ... Q128: =IFERROR(-((Q90+Q93+Q96-Q110-Q113)-(P90+P93+P96-P110-P113)),"") -> 28.143018
B130: Other Operating Adjustments | E130: =+_xlfn.XLOOKUP($B130,Inputs!$B:$B,Inputs!O:O) -> 54 | F130: =+_xlfn.XLOOKUP($B130,Inputs!$B:$B,Inputs!P:P) -> -679 | G130: =+_xlfn.XLOOKUP($B130,Inputs!$B:$B,Inputs!Q:Q) -> -338 | H130: =IFERROR(AVERAGE(E130:G130)*(1+H31),"") -> -343.33102 | I130: =IFERROR(AVERAGE(F130:H130)*(1+I31),"") -> -485.10152 | J130: =IFERROR(AVERAGE(G130:I130)*(1+J31),"") -> -416.03901 | K130: =IFERROR(AVERAGE(H130:J130)*(1+K31),"") -> -443.95093 | L130: =IFERROR(AVERAGE(I130:K130)*(1+L31),"") -> -479.91897 | M130: =IFERROR(AVERAGE(J130:L130)*(1+M31),"") -> -478.13357 | N130: =IFERROR(AVERAGE(K130:M130)*(1+N31),"") -> -500.34979 | O130: =IFERROR(AVERAGE(L130:N130)*(1+O31),"") -> -495.6473 | ... Q130: =IFERROR(AVERAGE(N130:P130)*(1+Q31),"") -> -508.80399
B132: Operating Cash Flow | E132: =+_xlfn.XLOOKUP($B132,Inputs!$B:$B,Inputs!O:O) -> 7838 | F132: =+_xlfn.XLOOKUP($B132,Inputs!$B:$B,Inputs!P:P) -> 7302 | G132: =+_xlfn.XLOOKUP($B132,Inputs!$B:$B,Inputs!Q:Q) -> 8056 | H132: =IFERROR(H81+H123+H125+H128+H130,"") -> 18222.425 | I132: =IFERROR(I81+I123+I125+I128+I130,"") -> 15029.763 | J132: =IFERROR(J81+J123+J125+J128+J130,"") -> 15919.384 | K132: =IFERROR(K81+K123+K125+K128+K130,"") -> 18757.48 | L132: =IFERROR(L81+L123+L125+L128+L130,"") -> 19058.486 | M132: =IFERROR(M81+M123+M125+M128+M130,"") -> 20595.781 | N132: =IFERROR(N81+N123+N125+N128+N130,"") -> 22361.706 | O132: =IFERROR(O81+O123+O125+O128+O130,"") -> 22531.89 | ... Q132: =IFERROR(Q81+Q123+Q125+Q128+Q130,"") -> 23673.255
B134: Net CapEx | E134: =+_xlfn.XLOOKUP($B134,Inputs!$B:$B,Inputs!O:O) -> -442 | F134: =+_xlfn.XLOOKUP($B134,Inputs!$B:$B,Inputs!P:P) -> -360 | G134: =+_xlfn.XLOOKUP($B134,Inputs!$B:$B,Inputs!Q:Q) -> -183 | H134: =IFERROR(H136+H138,"") -> -1242.3248 | I134: =IFERROR(I136+I138,"") -> -1333.3023 | J134: =IFERROR(J136+J138,"") -> -1430.6334 | K134: =IFERROR(K136+K138,"") -> -1535.0696 | L134: =IFERROR(L136+L138,"") -> -1647.1297 | M134: =IFERROR(M136+M138,"") -> -1767.3702 | N134: =IFERROR(N136+N138,"") -> -1896.3882 | O134: =IFERROR(O136+O138,"") -> -529.94957 | ... Q134: =IFERROR(Q136+Q138,"") -> -551.35953
B136: Acquisition of Fixed & Intangibles | E136: =+_xlfn.XLOOKUP($B136,Inputs!$B:$B,Inputs!O:O) -> -442 | F136: =+_xlfn.XLOOKUP($B136,Inputs!$B:$B,Inputs!P:P) -> -360 | G136: =+_xlfn.XLOOKUP($B136,Inputs!$B:$B,Inputs!Q:Q) -> -183 | H136: =-H19*H18 -> -1242.3248 | I136: =-I19*I18 -> -1333.3023 | J136: =-J19*J18 -> -1430.6334 | K136: =-K19*K18 -> -1535.0696 | L136: =-L19*L18 -> -1647.1297 | M136: =-M19*M18 -> -1767.3702 | N136: =-N19*N18 -> -1896.3882 | O136: =-O19*O18 -> -529.94957 | ... Q136: =-Q19*Q18 -> -551.35953
B138: Disposal of Fixed & Intangibles | E138: =+_xlfn.XLOOKUP($B138,Inputs!$B:$B,Inputs!O:O) -> 0 | F138: =+_xlfn.XLOOKUP($B138,Inputs!$B:$B,Inputs!P:P) -> 0 | G138: =+_xlfn.XLOOKUP($B138,Inputs!$B:$B,Inputs!Q:Q) -> 0 | H138: =IFERROR(H139*G100,"") -> 0 | I138: =IFERROR(I139*H100,"") -> 0 | J138: =IFERROR(J139*I100,"") -> 0 | K138: =IFERROR(K139*J100,"") -> 0 | L138: =IFERROR(L139*K100,"") -> 0 | M138: =IFERROR(M139*L100,"") -> 0 | N138: =IFERROR(N139*M100,"") -> 0 | O138: =IFERROR(O139*N100,"") -> 0 | ... Q138: =IFERROR(Q139*P100,"") -> 0
B139: Disposal Rate (% Gross PP&E) | E139: =IFERROR(E138/E100,"") -> 0 | F139: =IFERROR(F138/F100,"") -> 0 | G139: =IFERROR(G138/G100,"") -> 0 | H139: =IFERROR(AVERAGE(E139:G139),"") -> 0 | I139: =IFERROR(AVERAGE(F139:H139),"") -> 0 | J139: =IFERROR(AVERAGE(G139:I139),"") -> 0 | K139: =IFERROR(AVERAGE(H139:J139),"") -> 0 | L139: =IFERROR(AVERAGE(I139:K139),"") -> 0 | M139: =IFERROR(AVERAGE(J139:L139),"") -> 0 | N139: =IFERROR(AVERAGE(K139:M139),"") -> 0 | O139: =IFERROR(AVERAGE(L139:N139),"") -> 0 | ... Q139: =IFERROR(AVERAGE(N139:P139),"") -> 0
B141: Net Cash from Investments & Acquisitions | E141: =+_xlfn.XLOOKUP($B141,Inputs!$B:$B,Inputs!O:O) -> -172 | F141: =+_xlfn.XLOOKUP($B141,Inputs!$B:$B,Inputs!P:P) -> -53 | G141: =+_xlfn.XLOOKUP($B141,Inputs!$B:$B,Inputs!Q:Q) -> -108 | H141: 0 | I141: 0 | J141: 0 | K141: 0 | L141: 0 | M141: 0 | N141: 0 | O141: 0 | P141: 0 | Q141: 0
B143: Other Investing Inflows (Outflows) | E143: =+_xlfn.XLOOKUP($B143,Inputs!$B:$B,Inputs!O:O) -> 44 | F143: =+_xlfn.XLOOKUP($B143,Inputs!$B:$B,Inputs!P:P) -> 1189 | G143: =+_xlfn.XLOOKUP($B143,Inputs!$B:$B,Inputs!Q:Q) -> 440 | H143: =IFERROR(AVERAGE(E143:G143)*(1+H31),"") -> 596.46189 | I143: =IFERROR(AVERAGE(F143:H143)*(1+I31),"") -> 793.61194 | J143: =IFERROR(AVERAGE(G143:I143)*(1+J31),"") -> 652.74423 | K143: =IFERROR(AVERAGE(H143:J143)*(1+K31),"") -> 728.75187 | L143: =IFERROR(AVERAGE(I143:K143)*(1+L31),"") -> 776.06292 | M143: =IFERROR(AVERAGE(J143:L143)*(1+M31),"") -> 769.90413 | N143: =IFERROR(AVERAGE(K143:M143)*(1+N31),"") -> 811.80623 | O143: =IFERROR(AVERAGE(L143:N143)*(1+O31),"") -> 801.30423 | ... Q143: =IFERROR(AVERAGE(N143:P143)*(1+Q31),"") -> 823.53838
B145: Investing Cash Flow | E145: =+_xlfn.XLOOKUP($B145,Inputs!$B:$B,Inputs!O:O) -> -570 | F145: =+_xlfn.XLOOKUP($B145,Inputs!$B:$B,Inputs!P:P) -> 776 | G145: =+_xlfn.XLOOKUP($B145,Inputs!$B:$B,Inputs!Q:Q) -> 149 | H145: =IFERROR(+H134+H141+H143,"") -> -645.86295 | I145: =IFERROR(+I134+I141+I143,"") -> -539.69036 | J145: =IFERROR(+J134+J141+J143,"") -> -777.88914 | K145: =IFERROR(+K134+K141+K143,"") -> -806.31773 | L145: =IFERROR(+L134+L141+L143,"") -> -871.06676 | M145: =IFERROR(+M134+M141+M143,"") -> -997.46603 | N145: =IFERROR(+N134+N141+N143,"") -> -1084.5819 | O145: =IFERROR(+O134+O141+O143,"") -> 271.35466 | ... Q145: =IFERROR(+Q134+Q141+Q143,"") -> 272.17885
B147: Dividends | E147: =+_xlfn.XLOOKUP($B147,Inputs!$B:$B,Inputs!O:O) -> 0 | F147: =+_xlfn.XLOOKUP($B147,Inputs!$B:$B,Inputs!P:P) -> 0 | G147: =+_xlfn.XLOOKUP($B147,Inputs!$B:$B,Inputs!Q:Q) -> 0 | H147: =+IFERROR(H148*_xlfn.XLOOKUP("Net Income",$B:$B,$H:$H),"") -> 0 | I147: =+IFERROR(I148*_xlfn.XLOOKUP("Net Income",$B:$B,$H:$H),"") -> 0 | J147: =+IFERROR(J148*_xlfn.XLOOKUP("Net Income",$B:$B,$H:$H),"") -> 0 | K147: =+IFERROR(K148*_xlfn.XLOOKUP("Net Income",$B:$B,$H:$H),"") -> 0 | L147: =+IFERROR(L148*_xlfn.XLOOKUP("Net Income",$B:$B,$H:$H),"") -> 0 | M147: =+IFERROR(M148*_xlfn.XLOOKUP("Net Income",$B:$B,$H:$H),"") -> 0 | N147: =+IFERROR(N148*_xlfn.XLOOKUP("Net Income",$B:$B,$H:$H),"") -> 0 | O147: =+IFERROR(O148*_xlfn.XLOOKUP("Net Income",$B:$B,$H:$H),"") -> 0 | ... Q147: =+IFERROR(Q148*_xlfn.XLOOKUP("Net Income",$B:$B,$H:$H),"") -> 0
B148: Dividend payout | E148: =IFERROR(-E147/E$81,"") -> 0 | F148: =IFERROR(-F147/F$81,"") -> 0 | G148: =IFERROR(-G147/G$81,"") -> 0 | H148: =(G148*1.05) -> 0 | I148: =(H148*1.05) -> 0 | J148: =(I148*1.05) -> 0 | K148: =(J148*1.05) -> 0 | L148: =(K148*1.05) -> 0 | M148: =(L148*1.05) -> 0 | N148: =(M148*1.05) -> 0 | O148: =(N148*1.05) -> 0 | ... Q148: =(P148*1.05) -> 0
B150: Increase (Repurchase) of Shares | E150: =+_xlfn.XLOOKUP($B150,Inputs!$B:$B,Inputs!O:O) -> -6272 | F150: =+_xlfn.XLOOKUP($B150,Inputs!$B:$B,Inputs!P:P) -> -4126 | G150: =+_xlfn.XLOOKUP($B150,Inputs!$B:$B,Inputs!Q:Q) -> -9139 | H150: =IFERROR(-H151*_xlfn.XLOOKUP("Net Income",$B:$B,H:H),"") -> 123.7034 | I150: =IFERROR(-I151*_xlfn.XLOOKUP("Net Income",$B:$B,I:I),"") -> 131.30367 | J150: =IFERROR(-J151*_xlfn.XLOOKUP("Net Income",$B:$B,J:J),"") -> 6913.6072 | K150: =IFERROR(-K151*_xlfn.XLOOKUP("Net Income",$B:$B,K:K),"") -> 147.12933 | L150: =IFERROR(-L151*_xlfn.XLOOKUP("Net Income",$B:$B,L:L),"") -> 156.16229 | M150: =IFERROR(-M151*_xlfn.XLOOKUP("Net Income",$B:$B,M:M),"") -> 8451.449 | N150: =IFERROR(-N151*_xlfn.XLOOKUP("Net Income",$B:$B,N:N),"") -> 176.21894 | O150: =IFERROR(-O151*_xlfn.XLOOKUP("Net Income",$B:$B,O:O),"") -> 177.10449 | P150: =IFERROR(-P151*_xlfn.XLOOKUP("Net Income",$B:$B,P:P),"") -> 9188.4791 | Q150: =IFERROR(-Q151*_xlfn.XLOOKUP("Net Income",$B:$B,Q:Q),"") -> 183.39412
B151: Repurchase payout | E151: =IFERROR(-E150/E$81,"") -> 1.3187553 | F151: =IFERROR(-F150/F$81,"") -> 0.76013265 | G151: =IFERROR(-G150/G$81,"") -> 1.643705 | H151: -0.01 | I151: -0.01 | J151: -0.5 | K151: -0.01 | L151: -0.01 | M151: -0.51 | N151: -0.01 | O151: -0.01 | P151: -0.51 | Q151: -0.01
...

Sheet Inputs
B2: Inputs
B3: in millions of USD
A4: x | B4: Income Statement | G4: 2014 | H4: =+G4+1 -> 2015 | I4: =+H4+1 -> 2016 | J4: =+I4+1 -> 2017 | K4: =+J4+1 -> 2018 | L4: =+K4+1 -> 2019 | M4: =+L4+1 -> 2020 | N4: =+M4+1 -> 2021 | O4: =+N4+1 -> 2022 | ... Q4: =+P4+1 -> 2024 | R4: ="CAGR "&$G$4&" - "&$Q$4 -> CAGR 2014 - 2024
B6: Revenue (Sales) | G6: 4147 | H6: 4795 | I6: 5854 | J6: 7301 | K6: 9030 | L6: 11171 | M6: 12868 | N6: 15785 | O6: 17606 | P6: 19409 | Q6: 21505 | R6: =IFERROR((Q6/G6)^(1/COUNT($G$4:$Q$4))-1,"") -> 0.16140131
B7: COGS (Cost of Goods Sold) | G7: 622 | H7: 744 | I7: 820 | J7: 1010 | K7: 1194 | L7: 1673 | M7: 1722 | N7: 1865 | O7: 2165 | P7: 2354 | Q7: 2538 | R7: =IFERROR((Q7/G7)^(1/COUNT($G$4:$Q$4))-1,"") -> 0.13636616
B8: Gross Profit | G8: =G6-G7 -> 3525 | H8: =H6-H7 -> 4051 | I8: =I6-I7 -> 5034 | J8: =J6-J7 -> 6291 | K8: =K6-K7 -> 7836 | L8: =L6-L7 -> 9498 | M8: =M6-M7 -> 11146 | N8: =N6-N7 -> 13920 | ... Q8: =Q6-Q7 -> 18967 | R8: =IFERROR((Q8/G8)^(1/COUNT($G$4:$Q$4))-1,"") -> 0.16530593
B9: SG&A (Selling, General & Administrative) | G9: 1652 | H9: 1683 | I9: 1910 | J9: 2197 | K9: 2620 | L9: 3244 | M9: 3951 | N9: 4321 | O9: 5170 | P9: 6764 | Q9: 5764 | R9: =IFERROR((Q9/G9)^(1/COUNT($G$4:$Q$4))-1,"") -> 0.1203085
B10: R&D (Research & Development) | G10: 844 | H10: 862 | I10: 976 | J10: 1224 | K10: 1537 | L10: 1930 | M10: 2188 | N10: 2540 | O10: 2987 | P10: 3473 | Q10: 3944 | R10: =IFERROR((Q10/G10)^(1/COUNT($G$4:$Q$4))-1,"") -> 0.15046185
B11: Other Operating (Income) Expenses | G11: 543 | H11: 532 | I11: 576 | J11: 624 | K11: 744 | L11: 881 | M11: 968 | N11: 1085 | O11: 1098 | P11: 0 | Q11: 1529 | R11: =IFERROR((Q11/G11)^(1/COUNT($G$4:$Q$4))-1,"") -> 0.098685577
B12: EBITDA | G12: =+G8-G9-G10-G11 -> 486 | H12: =+H8-H9-H10-H11 -> 974 | I12: =+I8-I9-I10-I11 -> 1572 | J12: =+J8-J9-J10-J11 -> 2246 | K12: =+K8-K9-K10-K11 -> 2935 | L12: =+L8-L9-L10-L11 -> 3443 | M12: =+M8-M9-M10-M11 -> 4039 | N12: =+N8-N9-N10-N11 -> 5974 | ... Q12: =+Q8-Q9-Q10-Q11 -> 7730 | R12: =IFERROR((Q12/G12)^(1/COUNT($G$4:$Q$4))-1,"") -> 0.28597108
B13: D&A (Depreciation & Amortization) | G13: 312 | H13: 335 | I13: 332 | J13: 325 | K13: 346 | L13: 757 | M13: 757 | N13: 788 | O13: 856 | P13: 872 | Q13: 857 | R13: =IFERROR((Q13/G13)^(1/COUNT($G$4:$Q$4))-1,"") -> 0.096208824
B14: Depreciation Expense | G14: =G13-G15 -> 259 | H14: =H13-H15 -> 267 | I14: =I13-I15 -> 254 | J14: =J13-J15 -> 249 | K14: =K13-K15 -> 255 | L14: =L13-L15 -> 582 | M14: =M13-M15 -> 595 | N14: =N13-N15 -> 616 | ... Q14: =Q13-Q15 -> 690 | R14: =IFERROR((Q14/G14)^(1/COUNT($G$4:$Q$4))-1,"") -> 0.09316647
B15: Amortization Expense | G15: 53 | H15: 68 | I15: 78 | J15: 76 | K15: 91 | L15: 175 | M15: 162 | N15: 172 | O15: 169 | P15: 168 | Q15: 167 | R15: =IFERROR((Q15/G15)^(1/COUNT($G$4:$Q$4))-1,"") -> 0.10997394
B16: Operating Income (EBIT) | G16: =+G12-G13 -> 174 | H16: =+H12-H13 -> 639 | I16: =+I12-I13 -> 1240 | J16: =+J12-J13 -> 1921 | K16: =+K12-K13 -> 2589 | L16: =+L12-L13 -> 2686 | M16: =+M12-M13 -> 3282 | N16: 5802 | O16: 6098 | P16: =+P12-P13 -> 5946 | Q16: =+Q12-Q13 -> 6873 | R16: =IFERROR((Q16/G16)^(1/COUNT($G$4:$Q$4))-1,"") -> 0.39683526
B17: Net Interest Expense (Income) | G17: =+G18-G19 -> 60 | H17: =+H18-H19 -> 35 | I17: =+I18-I19 -> 23 | J17: =+J18-J19 -> 8 | K17: =+K18-K19 -> -3 | L17: =+L18-L19 -> 89 | M17: =+M18-M19 -> 73 | N17: =+N18-N19 -> 96 | ... Q17: =+Q18-Q19 -> -172 | R17: =IFERROR((Q17/G17)^(1/COUNT($G$4:$Q$4))-1,"") -> -2.1004739
B18: Interest Expense | G18: 60 | H18: 64 | I18: 70 | J18: 74 | K18: 89 | L18: 157 | M18: 116 | N18: 113 | O18: 112 | P18: 113 | Q18: 169 | R18: =IFERROR((Q18/G18)^(1/COUNT($G$4:$Q$4))-1,"") -> 0.098714969
B19: Interest Income | G19: 0 | H19: 29 | I19: 47 | J19: 66 | K19: 92 | L19: 68 | M19: 43 | N19: 17 | O19: 61 | P19: 269 | Q19: 341 | R19: =IFERROR((Q19/G19)^(1/COUNT($G$4:$Q$4))-1,"")
B20: FX (Gain) Loss | G20: 19 | H20: 20 | I20: 36 | J20: 31 | K20: 42 | L20: 26 | M20: 2 | N20: 17 | O20: 21 | P20: 17 | Q20: 29 | R20: =IFERROR((Q20/G20)^(1/COUNT($G$4:$Q$4))-1,"") -> 0.039189967
B21: Other Non-Operating (Income) Expenses | G21: =G22-G16-G18-G19-G20 -> 108 | H21: =H22-H16-H18-H19-H20 -> 122 | I21: =I22-I16-I18-I19-I20 -> 42 | J21: =J22-J16-J18-J19-J20 -> 45 | K21: =K22-K16-K18-K19-K20 -> -19 | L21: =L22-L16-L18-L19-L20 -> 268 | M21: =M22-M16-M18-M19-M20 -> 733 | N21: =N22-N16-N18-N19-N20 -> -244 | ... Q21: =Q22-Q16-Q18-Q19-Q20 -> -481 | R21: =IFERROR((Q21/G21)^(1/COUNT($G$4:$Q$4))-1,"") -> -2.1454461
B22: Pre-Tax Income (EBT) | G22: 361 | H22: 874 | I22: 1435 | J22: 2137 | K22: 2793 | L22: 3205 | M22: 4176 | N22: 5705 | O22: 6008 | P22: 6799 | Q22: 6931 | R22: =IFERROR((Q22/G22)^(1/COUNT($G$4:$Q$4))-1,"") -> 0.30816525
B23: Tax Expense (Benefits) | G23: 93 | H23: 244 | I23: 266 | J23: 443 | K23: 203 | L23: 254 | M23: -1084 | N23: 883 | O23: 1252 | P23: 1371 | Q23: 1371 | R23: =IFERROR((Q23/G23)^(1/COUNT($G$4:$Q$4))-1,"") -> 0.27712153
B24: Net Income | G24: =+G22-G23 -> 268 | H24: =+H22-H23 -> 630 | I24: =+I22-I23 -> 1169 | J24: =+J22-J23 -> 1694 | K24: =+K22-K23 -> 2590 | L24: =+L22-L23 -> 2951 | M24: =+M22-M23 -> 5260 | N24: =+N22-N23 -> 4822 | O24: =+O22-O23 -> 4756 | P24: 5428 | Q24: =+Q22-Q23 -> 5560 | R24: =IFERROR((Q24/G24)^(1/COUNT($G$4:$Q$4))-1,"") -> 0.31741262
B25: EPS basic | G25: 0.58 | H25: 1.26 | I25: 2.35 | J25: 3.43 | K25: 5.28 | L25: 6.07 | M25: 10.94 | N25: 10.1 | O25: 10.13 | P25: 11.87 | Q25: 12.43 | R25: =IFERROR((Q25/G25)^(1/COUNT($G$4:$Q$4))-1,"") -> 0.32130756
B26: EPS diluted | G26: 0.56 | H26: 1.24 | I26: 2.32 | J26: 3.38 | K26: 5.2 | L26: 6 | M26: 10.83 | N26: 10.02 | O26: 10.1 | P26: 11.82 | Q26: 12.36 | R26: =IFERROR((Q26/G26)^(1/COUNT($G$4:$Q$4))-1,"") -> 0.32484907
B27: Basic Weighted Average Shares | G27: 501 | H27: 498 | I27: 498 | J27: 493 | K27: 490 | L27: 486 | M27: 481 | N27: 477 | O27: 470 | P27: 457 | Q27: 447
B28: Diluted Weighted Average Shares | G28: 513 | H28: 507 | I28: 504 | J28: 501 | K28: 498 | L28: 492 | M28: 485 | N28: 481 | O28: 471 | P28: 459 | Q28: 450 | R28: =IFERROR((Q28/G28)^(1/COUNT($G$4:$Q$4))-1,"") -> -0.011840997
A30: x | B30: Balance Sheet | G30: 2014 | H30: =+G30+1 -> 2015 | I30: =+H30+1 -> 2016 | J30: =+I30+1 -> 2017 | K30: =+J30+1 -> 2018 | L30: =+K30+1 -> 2019 | M30: =+L30+1 -> 2020 | N30: =+M30+1 -> 2021 | O30: =+N30+1 -> 2022 | ... Q30: =+P30+1 -> 2024 | R30: ="CAGR "&$G$4&" - "&$Q$4 -> CAGR 2014 - 2024
B32: Cash & Cash Equivalents & ST Investments | G32: =+SUM(G33:G34) -> 3739 | H32: =+SUM(H33:H34) -> 3987 | I32: =+SUM(I33:I34) -> 4760 | J32: =+SUM(J33:J34) -> 5819 | K32: =+SUM(K33:K34) -> 3228 | L32: =+SUM(L33:L34) -> 4176 | M32: =+SUM(M33:M34) -> 5992 | N32: =+SUM(N33:N34) -> 5798 | ... Q32: =+SUM(Q33:Q34) -> 7886 | R32: =IFERROR((Q32/G32)^(1/COUNT($G$4:$Q$4))-1,"") -> 0.070197064
B33: Cash & Cash Equivalents | G33: 1117 | H33: 876 | I33: 1011 | J33: 2306 | K33: 1642 | L33: 2650 | M33: 4478 | N33: 3844 | O33: 4236 | P33: 7141 | Q33: 7613 | R33: =IFERROR((Q33/G33)^(1/COUNT($G$4:$Q$4))-1,"") -> 0.19061944
B34: Short-Term Investments | G34: 2622 | H34: 3111 | I34: 3749 | J34: 3513 | K34: 1586 | L34: 1526 | M34: 1514 | N34: 1954 | O34: 1860 | P34: 701 | Q34: 273 | R34: =IFERROR((Q34/G34)^(1/COUNT($G$4:$Q$4))-1,"") -> -0.18588728
B35: Accounts Receivable | G35: 592 | H35: 672 | I35: 833 | J35: 1218 | K35: 1315 | L35: 1534 | M35: 1398 | N35: 1878 | O35: 2065 | P35: 2224 | Q35: 2072 | R35: =IFERROR((Q35/G35)^(1/COUNT($G$4:$Q$4))-1,"") -> 0.1206261
B36: Inventory | G36: 0 | H36: 0 | I36: 0 | J36: 0 | K36: 0 | L36: 0 | M36: 0 | N36: 0 | O36: 0 | P36: 0 | Q36: 0 | R36: =IFERROR((Q36/G36)^(1/COUNT($G$4:$Q$4))-1,"")
B37: Prepaid expenses and Other Current Assets | G37: =+G38-G32-G35-G36 -> 271 | H37: =+H38-H32-H35-H36 -> 162 | I37: =+I38-I32-I35-I36 -> 247 | J37: =+J38-J32-J35-J36 -> 210 | K37: =+K38-K32-K35-K36 -> 314 | L37: =+L38-L32-L35-L36 -> 785 | M37: =+M38-M32-M35-M36 -> 756 | N37: =+N38-N32-N35-N36 -> 993 | O37: 835 | P37: 1018 | Q37: =+Q38-Q32-Q35-Q36 -> 1274 | R37: =IFERROR((Q37/G37)^(1/COUNT($G$4:$Q$4))-1,"") -> 0.15108953
B38: Current Assets | G38: 4602 | H38: 4821 | I38: 5840 | J38: 7247 | K38: 4857 | L38: 6495 | M38: 8146 | N38: 8669 | O38: 8996 | P38: 11084 | Q38: 11232 | R38: =IFERROR((Q38/G38)^(1/COUNT($G$4:$Q$4))-1,"") -> 0.084496677
B39: Net PP&E (Property, Plant and Equipment) | G39: =+G40-G41 -> 785 | H39: =+H40-H41 -> 787 | I39: =+I40-I41 -> 817 | J39: =+J40-J41 -> 937 | K39: =+K40-K41 -> 1075 | L39: =+L40-L41 -> 1293 | M39: =+M40-M41 -> 1517 | N39: =+N40-N41 -> 1673 | O39: 1908 | P39: 2030 | Q39: =+Q40-Q41 -> 1936 | R39: =IFERROR((Q39/G39)^(1/COUNT($G$4:$Q$4))-1,"") -> 0.085524447
B40: Gross PP&E (Property, Plant and Equipment) | G40: 1699 | H40: 1758 | I40: 1926 | J40: 2203 | K40: 2480 | L40: 2861 | M40: 2975 | N40: 3124 | O40: 3477 | P40: 3761 | Q40: 3591 | R40: =IFERROR((Q40/G40)^(1/COUNT($G$4:$Q$4))-1,"") -> 0.070403343
B41: Accumulated Depreciation | G41: 914 | H41: 971 | I41: 1109 | J41: 1266 | K41: 1405 | L41: 1568 | M41: 1458 | N41: 1451 | O41: 1569 | P41: 1731 | Q41: 1655 | R41: =IFERROR((Q41/G41)^(1/COUNT($G$4:$Q$4))-1,"") -> 0.055458284
B42: Right-of-Use Assets | G42: 0 | H42: 0 | I42: 0 | J42: 0 | K42: 0 | L42: 0 | M42: 487 | N42: 443 | O42: 358 | P42: 407 | Q42: 281 | R42: =IFERROR((Q42/G42)^(1/COUNT($G$4:$Q$4))-1,"")
B43: Intangibles | G43: =G44+G45 -> 5190 | H43: =H44+H45 -> 5877 | I43: =I44+I45 -> 5820 | J43: =J44+J45 -> 6207 | K43: =K44+K45 -> 12650 | L43: =L44+L45 -> 12411 | M43: =M44+M45 -> 12101 | N43: =N44+N45 -> 14488 | ... Q43: =Q44+Q45 -> 13893 | R43: =IFERROR((Q43/G43)^(1/COUNT($G$4:$Q$4))-1,"") -> 0.093642388
B44: Goodwill | G44: 4721 | H44: 5367 | I44: 5406 | J44: 5821 | K44: 10581 | L44: 10691 | M44: 10742 | N44: 12668 | O44: 12787 | P44: 12805 | Q44: 12805 | R44: =IFERROR((Q44/G44)^(1/COUNT($G$4:$Q$4))-1,"") -> 0.094951929
B45: Intangibles excl. Goodwill | G45: 469 | H45: 510 | I45: 414 | J45: 386 | K45: 2069 | L45: 1720 | M45: 1359 | N45: 1820 | O45: 1088 | P45: 1499 | Q45: 1088
B46: Other Non-Current Assets | G46: =G47-G43-G41-G39 -> -706 | H46: =H47-H43-H41-H39 -> -730 | I46: =I47-I43-I41-I39 -> -879 | J46: =J47-J43-J41-J39 -> -1304 | K46: =K47-K43-K41-K39 -> -1219 | L46: =L47-L43-L41-L39 -> -1004 | M46: =M47-M43-M41-M39 -> 1062 | N46: 1968 | O46: 841 | P46: 1223 | Q46: =Q47-Q45-Q44-Q42-Q40 -> 1005 | R46: =IFERROR((Q46/G46)^(1/COUNT($G$4:$Q$4))-1,"") -> -2.0326234
B47: Non-Current Assets | G47: =G48-G38 -> 6183 | H47: =H48-H38 -> 6905 | I47: =I48-I38 -> 6867 | J47: =J48-J38 -> 7106 | K47: =K48-K38 -> 13911 | L47: =L48-L38 -> 14268 | M47: =M48-M38 -> 16138 | N47: =N39+N42+N43+N46 -> 18572 | O47: =O39+O42+O43+O46 -> 16982 | P47: =P39+P42+P43+P46 -> 17964 | Q47: =Q48-Q38 -> 18770 | R47: =IFERROR((Q47/G47)^(1/COUNT($G$4:$Q$4))-1,"") -> 0.10622196
B48: Total Assets | G48: 10785 | H48: 11726 | I48: 12707 | J48: 14353 | K48: 18768 | L48: 20763 | M48: 24284 | N48: 27241 | O48: 27165 | P48: 29799 | Q48: 30002 | R48: =IFERROR((Q48/G48)^(1/COUNT($G$4:$Q$4))-1,"") -> 0.097472487
B49: Accounts Payable | G49: 68 | H49: 93 | I49: 88 | J49: 113 | K49: 186 | L49: 210 | M49: 306 | N49: 312 | O49: 379 | P49: 314 | Q49: 361 | R49: =IFERROR((Q49/G49)^(1/COUNT($G$4:$Q$4))-1,"") -> 0.16388196
B50: Short-Term Debt | G50: =+SUM(G51:G52) -> 660 | H50: =+SUM(H51:H52) -> 60 | I50: =+SUM(I51:I52) -> 60 | J50: =+SUM(J51:J52) -> 60 | K50: =+SUM(K51:K52) -> 60 | L50: =+SUM(L51:L52) -> 3210 | M50: =+SUM(M51:M52) -> 92 | N50: =+SUM(N51:N52) -> 97 | O50: 587 | P50: 73 | Q50: =Q51+Q52 -> 1574 | R50: =IFERROR((Q50/G50)^(1/COUNT($G$4:$Q$4))-1,"") -> 0.082217662
B51: Short-Term Borrowings | G51: 600 | H51: 0 | I51: 0 | J51: 0 | K51: 0 | L51: 3150 | M51: 0 | N51: 0 | O51: 500 | P51: 0 | Q51: 1499 | R51: =IFERROR((Q51/G51)^(1/COUNT($G$4:$Q$4))-1,"") -> 0.086801014
B52: Current Portion of Lease Liabilities | G52: 60 | H52: 60 | I52: 60 | J52: 60 | K52: 60 | L52: 60 | M52: 92 | N52: 97 | O52: 87 | P52: 73 | Q52: 75 | R52: =IFERROR((Q52/G52)^(1/COUNT($G$4:$Q$4))-1,"") -> 0.020492932
B53: Accrued Expenses and Other Current Liabilities | G53: =+G54-G49-G50 -> 1766 | H53: =+H54-H49-H50 -> 2060 | I53: =+I54-I49-I50 -> 2663 | J53: =+J54-J49-J50 -> 3354 | K53: =+K54-K49-K50 -> 4055 | L53: =+L54-L49-L50 -> 4771 | M53: =+M54-M49-M50 -> 5114 | N53: =+N54-N49-N50 -> 6523 | ... P53: =+P54-P49-P50 -> 7864 | Q53: 2336 | R53: =IFERROR((Q53/G53)^(1/COUNT($G$4:$Q$4))-1,"") -> 0.025755445
B54: Current Liabilities | G54: 2494 | H54: 2213 | I54: 2811 | J54: 3527 | K54: 4301 | L54: 8191 | M54: 5512 | N54: 6932 | O54: 8128 | P54: 8251 | Q54: 10521 | R54: =IFERROR((Q54/G54)^(1/COUNT($G$4:$Q$4))-1,"") -> 0.13981083
B55: Long-Term Debt | G55: =+SUM(G56:G57) -> 914 | H55: =+SUM(H56:H57) -> 1907 | I55: =+SUM(I56:I57) -> 1902 | J55: =+SUM(J56:J57) -> 1881 | K55: =+SUM(K56:K57) -> 4124 | L55: 988 | M55: =+SUM(M56:M57) -> 4616 | N55: =+SUM(N56:N57) -> 4576 | O55: =+SUM(O56:O57) -> 4046 | P55: =+SUM(P56:P57) -> 4007 | Q55: =+SUM(Q56:Q57) -> 4482 | R55: =IFERROR((Q55/G55)^(1/COUNT($G$4:$Q$4))-1,"") -> 0.1555136
B56: Long-Term Borrowings | G56: 911 | H56: 1907 | I56: 1902 | J56: 1881 | K56: 4124 | L56: 944 | M56: 4117 | N56: 4123 | O56: 3629 | P56: 3634 | Q56: 4129 | R56: =IFERROR((Q56/G56)^(1/COUNT($G$4:$Q$4))-1,"") -> 0.14727108
B57: Long-Term Operating Lease Liabilities | G57: 3 | H57: 0 | I57: 0 | J57: 0 | K57: 0 | L57: 0 | M57: 499 | N57: 453 | O57: 417 | P57: 373 | Q57: 353 | R57: =IFERROR((Q57/G57)^(1/COUNT($G$4:$Q$4))-1,"") -> 0.54255701
B58: Other Non-Current Liabilities | G58: =+G59-G55 -> 1329 | H58: =+H59-H55 -> 757 | I58: =+I59-I55 -> 717 | J58: =+J59-J55 -> 840 | K58: =+K59-K55 -> 1227 | L58: =+L59-L55 -> 4473 | M58: =+M59-M55 -> 892 | N58: =+N59-N55 -> 936 | ... Q58: =+Q59-Q55 -> 1505 | R58: =IFERROR((Q58/G58)^(1/COUNT($G$4:$Q$4))-1,"") -> 0.011370165
B59: Non-Current Liabilities | G59: =G60-G53 -> 2243 | H59: =H60-H53 -> 2664 | I59: =I60-I53 -> 2619 | J59: =J60-J53 -> 2721 | K59: =K60-K53 -> 5351 | L59: =L60-L53 -> 5461 | M59: =11020-5512 -> 5508 | N59: =12444-6932 -> 5512 | O59: 5098 | P59: 4876 | Q59: 5987 | R59: =IFERROR((Q59/G59)^(1/COUNT($G$4:$Q$4))-1,"") -> 0.093356564
B60: Total Liabilities | G60: 4009 | H60: 4724 | I60: 5282 | J60: 6075 | K60: 9406 | L60: 10232 | M60: =SUM(M59,M54) -> 11020 | N60: =SUM(N59,N54) -> 12444 | O60: =SUM(O59,O54) -> 13226 | P60: =SUM(P59,P54) -> 13127 | Q60: =SUM(Q59,Q54) -> 16508 | R60: =IFERROR((Q60/G60)^(1/COUNT($G$4:$Q$4))-1,"") -> 0.13730785
B61: Shareholder's Equity | G61: =G48-G60 -> 6776 | H61: =H48-H60 -> 7002 | I61: =I48-I60 -> 7425 | J61: =J48-J60 -> 8278 | K61: =K48-K60 -> 9362 | L61: =L48-L60 -> 10531 | M61: =M48-M60 -> 13264 | N61: =N48-N60 -> 14797 | ... Q61: =Q48-Q60 -> 13494 | R61: =IFERROR((Q61/G61)^(1/COUNT($G$4:$Q$4))-1,"") -> 0.064625902
B62: Non-Controlling Interest
A64: x | B64: Cash Flow | G64: 2014 | H64: =+G64+1 -> 2015 | I64: =+H64+1 -> 2016 | J64: =+I64+1 -> 2017 | K64: =+J64+1 -> 2018 | L64: =+K64+1 -> 2019 | M64: =+L64+1 -> 2020 | N64: =+M64+1 -> 2021 | O64: =+N64+1 -> 2022 | ... Q64: =+P64+1 -> 2024 | R64: ="CAGR "&$G$4&" - "&$Q$4 -> CAGR 2014 - 2024
B66: Net Income | G66: =G24 -> 268 | H66: =H24 -> 630 | I66: =I24 -> 1169 | J66: =J24 -> 1694 | K66: =K24 -> 2590 | L66: =L24 -> 2951 | M66: =M24 -> 5260 | N66: =N24 -> 4822 | ... Q66: =Q24 -> 5560 | R66: =IFERROR((Q66/G66)^(1/COUNT($G$4:$Q$4))-1,"") -> 0.31741262
B67: D&A (Depreciation and Amortization) | G67: =+G13 -> 312 | H67: =+H13 -> 335 | I67: =+I13 -> 332 | J67: =+J13 -> 325 | K67: =+K13 -> 346 | L67: =+L13 -> 757 | M67: =+M13 -> 757 | N67: =+N13 -> 788 | ... Q67: =+Q13 -> 857 | R67: =IFERROR((Q67/G67)^(1/COUNT($G$4:$Q$4))-1,"") -> 0.096208824
B68: Changes in Net Working Capital | G68: =+SUM(G69:G72) -> -6 | H68: =+SUM(H69:H72) -> 79 | I68: =+SUM(I69:I72) -> 160 | J68: =+SUM(J69:J72) -> 187 | K68: =+SUM(K69:K72) -> 2 | L68: =+SUM(L69:L72) -> 188 | M68: =+SUM(M69:M72) -> -106 | N68: =+SUM(N69:N72) -> 1152 | ... Q68: =+SUM(Q69:Q72) -> 144 | R68: =IFERROR((Q68/G68)^(1/COUNT($G$4:$Q$4))-1,"") -> -2.3349769
B69: (Increase) Decrease in Accounts Receivable | G69: -8 | H69: 79 | I69: 160 | J69: 187 | K69: 2 | L69: 188 | M69: -106 | N69: 430 | O69: 198 | P69: 159 | Q69: 143
B70: (Increase) Decrease in Inventories | G70: 0 | H70: 0 | I70: 0 | J70: 0 | K70: 0 | L70: 0 | M70: 0 | N70: 0 | O70: 0 | P70: 0 | Q70: 0
B71: Increase (Decrease) in Inventories | G71: 0 | H71: 0 | I71: 0 | J71: 0 | K71: 0 | L71: 0 | M71: 0 | N71: 0 | O71: 0 | P71: 0 | Q71: 0
B72: Increase (Decrease) in Other | G72: 2 | N72: 722 | O72: 534 | P72: -196 | Q72: 1
B73: Stock Based Compensation | G73: 333 | H73: 336 | I73: 349 | J73: 454 | K73: 609 | L73: 788 | M73: 909 | N73: 1069 | O73: 1440 | P73: 1718 | Q73: 1833
B74: Other Operating Adjustments | G74: =+G75-G66-G67-G68-G73 -> 380 | H74: =+H75-H66-H67-H68-H73 -> 89 | I74: =+I75-I66-I67-I68-I73 -> 189 | J74: =+J75-J66-J67-J68-J73 -> 252 | K74: =+K75-K66-K67-K68-K73 -> 482 | L74: =+L75-L66-L67-L68-L73 -> -262 | M74: =+M75-M66-M67-M68-M73 -> -1093 | N74: =+N75-N66-N67-N68-N73 -> -601 | ... Q74: =+Q75-Q66-Q67-Q68-Q73 -> -338 | R74: =IFERROR((Q74/G74)^(1/COUNT($G$4:$Q$4))-1,"") -> -1.9894087
B75: Operating Cash Flow | G75: 1287 | H75: 1469 | I75: 2199 | J75: 2912 | K75: 4029 | L75: 4422 | M75: 5727 | N75: 7230 | O75: 7838 | P75: 7302 | Q75: 8056 | R75: =IFERROR((Q75/G75)^(1/COUNT($G$4:$Q$4))-1,"") -> 0.1814431
B76: Net Capex | G76: -148 | H76: -184 | I76: -178 | J76: -266 | K76: -394 | L76: -395 | M76: -419 | N76: =+SUM(N77:N78) -> -348 | O76: =+SUM(O77:O78) -> -442 | P76: =+SUM(P77:P78) -> -360 | Q76: =+SUM(Q77:Q78) -> -183 | R76: =IFERROR((Q76/G76)^(1/COUNT($G$4:$Q$4))-1,"") -> 0.019485028
B77: Acquisition of Fixed & Intangibles | G77: -148 | H77: -184 | I77: -178 | J77: -266 | K77: -394 | L77: -395 | M77: -419 | N77: -348 | O77: -442 | P77: -360 | Q77: -183 | R77: =IFERROR((Q77/G77)^(1/COUNT($G$4:$Q$4))-1,"") -> 0.019485028
B78: Disposal of Fixed & Intangibles | G78: 0 | H78: 0 | I78: 0 | J78: 0 | K78: 0 | L78: 0 | M78: 0 | N78: 0 | O78: 0 | P78: 0 | Q78: 0 | R78: =IFERROR((Q78/G78)^(1/COUNT($G$4:$Q$4))-1,"")
B79: Net Cash from Investments & Acquisitions | G79: =+SUM(G80:G83) -> -13 | H79: =+SUM(H80:H83) -> -849 | I79: =+SUM(I80:I83) -> -106 | J79: =+SUM(J80:J83) -> -489 | K79: =+SUM(K80:K83) -> -6360 | L79: =+SUM(L80:L83) -> -150 | M79: =+SUM(M80:M83) -> -15 | N79: =+SUM(N80:N83) -> -2734 | ... Q79: =+SUM(Q80:Q83) -> -108 | R79: =IFERROR((Q79/G79)^(1/COUNT($G$4:$Q$4))-1,"") -> 0.21224144
B80: Acquisitions | G80: -30 | H80: -826 | I80: -48 | J80: -459 | K80: -6341 | L80: -101 | M80: 0 | N80: -2682 | O80: -126 | P80: 0 | Q80: 0 | R80: =IFERROR((Q80/G80)^(1/COUNT($G$4:$Q$4))-1,"") -> -1
B81: Divestitures | G81: 0 | H81: 0 | I81: 0 | J81: 0 | K81: 0 | L81: 0 | M81: 0 | N81: 0 | O81: 0 | P81: 0 | Q81: 0 | R81: =IFERROR((Q81/G81)^(1/COUNT($G$4:$Q$4))-1,"")
B82: Increase in LT Investment | G82: 17 | H82: -23 | I82: -58 | J82: -30 | K82: -19 | L82: -49 | M82: -15 | N82: -52 | O82: -46 | P82: -53 | Q82: -108 | R82: =IFERROR((Q82/G82)^(1/COUNT($G$4:$Q$4))-1,"") -> -2.1830353
B83: Decrease in LT Investment | G83: 0 | H83: 0 | I83: 0 | J83: 0 | K83: 0 | L83: 0 | M83: 0 | N83: 0 | O83: 0 | P83: 0 | Q83: 0 | R83: =IFERROR((Q83/G83)^(1/COUNT($G$4:$Q$4))-1,"")
B84: Other Investing Inflows (Outflows) | G84: =+G85-G76-G79 -> -329 | H84: =+H85-H76-H79 -> -455 | I84: =+I85-I76-I79 -> -676 | J84: =+J85-J76-J79 -> 312 | K84: =+K85-K76-K79 -> 2069 | L84: =+L85-L76-L79 -> 89 | M84: =+M85-M76-M79 -> 20 | N84: =+N85-N76-N79 -> -455 | ... Q84: =+Q85-Q76-Q79 -> 440 | R84: =IFERROR((Q84/G84)^(1/COUNT($G$4:$Q$4))-1,"") -> -2.0267812
B85: Investing Cash Flow | G85: -490 | H85: -1488 | I85: -960 | J85: -443 | K85: -4685 | L85: -456 | M85: -414 | N85: -3537 | O85: -570 | P85: 776 | Q85: 149 | R85: =IFERROR((Q85/G85)^(1/COUNT($G$4:$Q$4))-1,"") -> -1.897427
B86: Debt Borrowing | G86: 0 | H86: 990 | I86: 0 | K86: 2248 | L86: 0 | M86: 3144 | N86: 0 | O86: 0 | P86: 0 | Q86: 1997 | R86: =IFERROR((Q86/G86)^(1/COUNT($G$4:$Q$4))-1,"")
B87: Debt Repayment | G87: -14 | H87: -0.6 | I87: 0 | J87: 0 | K87: 0 | L87: 0 | M87: -3150 | N87: 0 | O87: 0 | P87: -500 | Q87: 0 | R87: =IFERROR((Q87/G87)^(1/COUNT($G$4:$Q$4))-1,"") -> -1
B88: Lease Payments | G88: -170 | H88: -230 | I88: -108 | J88: -1960 | K88: -1707 | L88: 0 | M88: 0 | N88: 0 | O88: 0 | P88: 0 | Q88: 0 | R88: =IFERROR((Q88/G88)^(1/COUNT($G$4:$Q$4))-1,"") -> -1
B89: Dividends | G89: 0 | H89: 0 | I89: 0 | J89: 0 | K89: 0 | L89: 0 | M89: 0 | N89: 0 | O89: 0 | P89: 0 | Q89: 0 | R89: =IFERROR((Q89/G89)^(1/COUNT($G$4:$Q$4))-1,"")
B90: Increase (Repurchase) of Shares | G90: =-600+227 -> -373 | H90: =-625+164 -> -461 | I90: =-1075+144 -> -931 | J90: =-1100+157 -> -943 | K90: =-2050+191 -> -1859 | L90: =-2750+233 -> -2517 | M90: =-3050+270 -> -2780 | N90: =-3950+291 -> -3659 | O90: =-6550+278 -> -6272 | P90: =-4440+314 -> -4126 | Q90: -9139 | R90: =IFERROR((Q90/G90)^(1/COUNT($G$4:$Q$4))-1,"") -> 0.33748828
B91: Other Financing Inflows (Outflows) | G91: =+G92-G86-G87-G88-G89-G90 -> 50 | H91: =+H92-H86-H87-H88-H89-H90 -> -498.4 | I91: =+I92-I86-I87-I88-I89-I90 -> -51 | J91: =+J92-J86-J87-J88-J89-J90 -> 1719 | K91: =+K92-K86-K87-K88-K89-K90 -> -4250 | L91: =+L92-L86-L87-L88-L89-L90 -> -429 | M91: =+M92-M86-M87-M88-M89-M90 -> -702 | N91: =+N92-N86-N87-N88-N89-N90 -> -642 | ... Q91: =+Q92-Q86-Q87-Q88-Q89-Q90 -> -582 | R91: =IFERROR((Q91/G91)^(1/COUNT($G$4:$Q$4))-1,"") -> -2.249985
B92: Financing Cash Flow | G92: -507 | H92: -200 | I92: -1090 | J92: -1184 | K92: -5568 | L92: -2946 | M92: -3488 | N92: -4301 | O92: -6825 | P92: -5182 | Q92: -7724 | R92: =IFERROR((Q92/G92)^(1/COUNT($G$4:$Q$4))-1,"") -> 0.28094473
B93: Effect of Foreign Exchange | G93: -6 | H93: -21 | I93: -14 | J93: 8 | K93: -1 | L93: -13 | M93: 3 | N93: -26 | O93: -51 | P93: 9 | Q93: -9 | R93: =IFERROR((Q93/G93)^(1/COUNT($G$4:$Q$4))-1,"") -> 0.037548236
B94: Net Changes in Cash | G94: 282 | H94: -240 | I94: 134 | J94: 1293 | K94: -663 | L94: 1007 | M94: 1821 | N94: -658 | O94: 392 | P94: 2905 | Q94: 472 | R94: =IFERROR((Q94/G94)^(1/COUNT($G$4:$Q$4))-1,"") -> 0.04793831
B95: in billionsof USD
A96: x | B96: Capital Structure | G96: 42004 | H96: 42369 | I96: 42735 | J96: 43100 | K96: 43465 | L96: 43830 | M96: 44196 | N96: 44561 | O96: 44926 | P96: 45291 | Q96: 45657
B98: Market Capitalization | G98: {=(IFERROR(_xlfn.STOCKHISTORY(DCF!$R$4, G96, G96, 0, 0, 1), IFERROR(_xlfn.STOCKHISTORY("CMG", G96+1, G96+1, 0, 0, 1), _xlfn.STOCKHISTORY("CMG", G96-2, G96-2, 0, 0, 1))))*_xlfn.XLOOKUP("Basic Weighted Average Shares",$B:$B,G:G)} -> 36422.7 | H98: {=(IFERROR(_xlfn.STOCKHISTORY(DCF!$R$4, H96, H96, 0, 0, 1), IFERROR(_xlfn.STOCKHISTORY("CMG", H96+1, H96+1, 0, 0, 1), _xlfn.STOCKHISTORY("CMG", H96-2, H96-2, 0, 0, 1))))*_xlfn.XLOOKUP("Basic Weighted Average Shares",$B:$B,H:H)} -> 46782.12 | I98: {=(IFERROR(_xlfn.STOCKHISTORY(DCF!$R$4, I96, I96, 0, 0, 1), IFERROR(_xlfn.STOCKHISTORY("CMG", I96+1, I96+1, 0, 0, 1), _xlfn.STOCKHISTORY("CMG", I96-2, I96-2, 0, 0, 1))))*_xlfn.XLOOKUP("Basic Weighted Average Shares",$B:$B,I:I)} -> 3751.0356 | J98: {=(IFERROR(_xlfn.STOCKHISTORY(DCF!$R$4, J96, J96, 0, 0, 1), IFERROR(_xlfn.STOCKHISTORY("CMG", J96+1, J96+1, 0, 0, 1), _xlfn.STOCKHISTORY("CMG", J96-2, J96-2, 0, 0, 1))))*_xlfn.XLOOKUP("Basic Weighted Average Shares",$B:$B,J:J)} -> 2849.8358 | K98: {=(IFERROR(_xlfn.STOCKHISTORY(DCF!$R$4, K96, K96, 0, 0, 1), IFERROR(_xlfn.STOCKHISTORY("CMG", K96+1, K96+1, 0, 0, 1), _xlfn.STOCKHISTORY("CMG", K96-2, K96-2, 0, 0, 1))))*_xlfn.XLOOKUP("Basic Weighted Average Shares",$B:$B,K:K)} -> 110857.6 | L98: {=(IFERROR(_xlfn.STOCKHISTORY(DCF!$R$4, L96, L96, 0, 0, 1), IFERROR(_xlfn.STOCKHISTORY("CMG", L96+1, L96+1, 0, 0, 1), _xlfn.STOCKHISTORY("CMG", L96-2, L96-2, 0, 0, 1))))*_xlfn.XLOOKUP("Basic Weighted Average Shares",$B:$B,L:L)} -> 160287.66 | M98: {=(IFERROR(_xlfn.STOCKHISTORY(DCF!$R$4, M96, M96, 0, 0, 1), IFERROR(_xlfn.STOCKHISTORY("CMG", M96+1, M96+1, 0, 0, 1), _xlfn.STOCKHISTORY("CMG", M96-2, M96-2, 0, 0, 1))))*_xlfn.XLOOKUP("Basic Weighted Average Shares",$B:$B,M:M)} -> 240557.72 | N98: {=(IFERROR(_xlfn.STOCKHISTORY(DCF!$R$4, N96, N96, 0, 0, 1), IFERROR(_xlfn.STOCKHISTORY("CMG", N96+1, N96+1, 0, 0, 1), _xlfn.STOCKHISTORY("CMG", N96-2, N96-2, 0, 0, 1))))*_xlfn.XLOOKUP("Basic Weighted Average Shares",$B:$B,N:N)} -> 270487.62 | O98: {=(IFERROR(_xlfn.STOCKHISTORY(DCF!$R$4, O96, O96, 0, 0, 1), IFERROR(_xlfn.STOCKHISTORY("CMG", O96+1, O96+1, 0, 0, 1), _xlfn.STOCKHISTORY("CMG", O96-2, O96-2, 0, 0, 1))))*_xlfn.XLOOKUP("Basic Weighted Average Shares",$B:$B,O:O)} -> 13206.53 | P98: {=(IFERROR(_xlfn.STOCKHISTORY(DCF!$R$4, P96, P96, 0, 0, 1), IFERROR(_xlfn.STOCKHISTORY("CMG", P96+1, P96+1, 0, 0, 1), _xlfn.STOCKHISTORY("CMG", P96-2, P96-2, 0, 0, 1))))*_xlfn.XLOOKUP("Basic Weighted Average Shares",$B:$B,P:P)} -> 20902.814 | Q98: {=(IFERROR(_xlfn.STOCKHISTORY(DCF!$R$4, Q96, Q96, 0, 0, 1), IFERROR(_xlfn.STOCKHISTORY("CMG", Q96+1, Q96+1, 0, 0, 1), _xlfn.STOCKHISTORY("CMG", Q96-2, Q96-2, 0, 0, 1))))*_xlfn.XLOOKUP("Basic Weighted Average Shares",$B:$B,Q:Q)} -> 198771.96
B99: Cash & Cash Equivalents | G99: =_xlfn.XLOOKUP("Cash & Cash Equivalents & ST Investments",$B$30:$B$62,G$30:G$62) -> 3739 | H99: =_xlfn.XLOOKUP("Cash & Cash Equivalents & ST Investments",$B$30:$B$62,H$30:H$62) -> 3987 | I99: =_xlfn.XLOOKUP("Cash & Cash Equivalents & ST Investments",$B$30:$B$62,I$30:I$62) -> 4760 | J99: =_xlfn.XLOOKUP("Cash & Cash Equivalents & ST Investments",$B$30:$B$62,J$30:J$62) -> 5819 | K99: =_xlfn.XLOOKUP("Cash & Cash Equivalents & ST Investments",$B$30:$B$62,K$30:K$62) -> 3228 | L99: =_xlfn.XLOOKUP("Cash & Cash Equivalents & ST Investments",$B$30:$B$62,L$30:L$62) -> 4176 | M99: =_xlfn.XLOOKUP("Cash & Cash Equivalents & ST Investments",$B$30:$B$62,M$30:M$62) -> 5992 | N99: =_xlfn.XLOOKUP("Cash & Cash Equivalents & ST Investments",$B$30:$B$62,N$30:N$62) -> 5798 | ... Q99: =_xlfn.XLOOKUP("Cash & Cash Equivalents & ST Investments",$B$30:$B$62,Q$30:Q$62) -> 7886
B100: Total Debt | G100: =(_xlfn.XLOOKUP("Short-Term Debt",$B$30:$B$62,G$30:G$62)+_xlfn.XLOOKUP("Long-Term Debt",$B$30:$B$62,G$30:G$62)) -> 1574 | H100: =(_xlfn.XLOOKUP("Short-Term Debt",$B$30:$B$62,H$30:H$62)+_xlfn.XLOOKUP("Long-Term Debt",$B$30:$B$62,H$30:H$62)) -> 1967 | I100: =(_xlfn.XLOOKUP("Short-Term Debt",$B$30:$B$62,I$30:I$62)+_xlfn.XLOOKUP("Long-Term Debt",$B$30:$B$62,I$30:I$62)) -> 1962 | J100: =(_xlfn.XLOOKUP("Short-Term Debt",$B$30:$B$62,J$30:J$62)+_xlfn.XLOOKUP("Long-Term Debt",$B$30:$B$62,J$30:J$62)) -> 1941 | K100: =(_xlfn.XLOOKUP("Short-Term Debt",$B$30:$B$62,K$30:K$62)+_xlfn.XLOOKUP("Long-Term Debt",$B$30:$B$62,K$30:K$62)) -> 4184 | L100: =(_xlfn.XLOOKUP("Short-Term Debt",$B$30:$B$62,L$30:L$62)+_xlfn.XLOOKUP("Long-Term Debt",$B$30:$B$62,L$30:L$62)) -> 4198 | M100: =(_xlfn.XLOOKUP("Short-Term Debt",$B$30:$B$62,M$30:M$62)+_xlfn.XLOOKUP("Long-Term Debt",$B$30:$B$62,M$30:M$62)) -> 4708 | N100: =(_xlfn.XLOOKUP("Short-Term Debt",$B$30:$B$62,N$30:N$62)+_xlfn.XLOOKUP("Long-Term Debt",$B$30:$B$62,N$30:N$62)) -> 4673 | ... Q100: =(_xlfn.XLOOKUP("Short-Term Debt",$B$30:$B$62,Q$30:Q$62)+_xlfn.XLOOKUP("Long-Term Debt",$B$30:$B$62,Q$30:Q$62)) -> 6056
B101: Preferred Stock
B102: Non-Controlling Interest | G102: =_xlfn.XLOOKUP("Non-Controlling Interest",$B$30:$B$62,G$30:G$62) -> 0 | H102: =_xlfn.XLOOKUP("Non-Controlling Interest",$B$30:$B$62,H$30:H$62) -> 0 | I102: =_xlfn.XLOOKUP("Non-Controlling Interest",$B$30:$B$62,I$30:I$62) -> 0 | J102: =_xlfn.XLOOKUP("Non-Controlling Interest",$B$30:$B$62,J$30:J$62) -> 0 | K102: =_xlfn.XLOOKUP("Non-Controlling Interest",$B$30:$B$62,K$30:K$62) -> 0 | L102: =_xlfn.XLOOKUP("Non-Controlling Interest",$B$30:$B$62,L$30:L$62) -> 0 | M102: =_xlfn.XLOOKUP("Non-Controlling Interest",$B$30:$B$62,M$30:M$62) -> 0 | N102: =_xlfn.XLOOKUP("Non-Controlling Interest",$B$30:$B$62,N$30:N$62) -> 0 | ... Q102: =_xlfn.XLOOKUP("Non-Controlling Interest",$B$30:$B$62,Q$30:Q$62) -> 0
B103: Enterprise Value | G103: =+G98-G99+G100+G101+G102 -> 34257.7 | H103: =+H98-H99+H100+H101+H102 -> 44762.12 | I103: =+I98-I99+I100+I101+I102 -> 953.0356 | J103: =+J98-J99+J100+J101+J102 -> -1028.1642 | K103: =+K98-K99+K100+K101+K102 -> 111813.6 | L103: =+L98-L99+L100+L101+L102 -> 160309.66 | M103: =+M98-M99+M100+M101+M102 -> 239273.72 | N103: =+N98-N99+N100+N101+N102 -> 269362.62 | ... Q103: =+Q98-Q99+Q100+Q101+Q102 -> 196941.96
A105: x | B105: Debt Schedule | G105: Cash | H105: 2025 | I105: =+H105+1 -> 2026 | J105: =+I105+1 -> 2027 | K105: =+J105+1 -> 2028 | L105: =+K105+1 -> 2029 | M105: =+L105+1 -> 2030 | N105: =+M105+1 -> 2031 | O105: =+N105+1 -> 2032 | P105: =+O105+1 -> 2033 | Q105: =+P105+1 -> 2034
B107: Cash
B108: Fixed
B109: Floating
...

Sheet WACC
B2: WACC
B4: WACC = % of Equity x Cost of Equity + % de Debt x Cost of Debt x (1 - Tax Rate)
B5: Cost of Equity = Risk-Free Rate + Beta x Equity Risk Premium
B7: WACC | I7: Region | J7: Weight | K7: ERP | M7: Peers | N7: Beta (Unlevered)
B9: Market Cap (in millions) | G9: {=+_FV(DCF!R4,"Market cap",TRUE)/1000000} -> 155214.8 | I9: Americas | J9: =Segments!D6 -> 0.59944199 | K9: 0.0517 | M9: =+Peers!B7 -> SALESFORCE, INC. | N9: =+Peers!E74 -> 1.0431501
B10: % of Equity | G10: =IFERROR(G9/G23,"") -> 0.96244825 | I10: APAC | J10: =Segments!D7 -> 0.14229249 | K10: 0.0585 | M10: =+Peers!B8 -> INTUIT INC. | N10: =+Peers!F74 -> 0.96831437
B11: Cost of Equity | G11: =IFERROR(G12+G14*G15,"") -> 0.09375571 | I11: EMEA | J11: =Segments!D8 -> 0.25826552 | K11: 0.0617 | M11: =+Peers!B9 -> WORKDAY, INC. | N11: =+Peers!G74 -> 0.84097319
B12: Risk-Free Rate | G12: 0.0441 | I12: Others | J12: =1-SUM(J9:J11) -> 0 | K12: =MAX(K9:K11) -> 0.0617 | M12: =+Peers!B10 -> DATADOG, INC. | N12: =+Peers!H74 -> 0.75141262
B13: Unlevered Beta | G13: =+N19 -> 0.86509316 | M13: =+Peers!B11 -> HUBSPOT, INC. | N13: =+Peers!I74 -> 1.5023598
B14: Beta | G14: =+IFERROR(G13*(1+(1-G21)*(G18/G9)),"") -> 0.89874191 | H14: Yahoo: 1,49 (5Y monthly) | M14: =+Peers!B12 -> Sap Se | N14: =+Peers!J74 -> 1.1095378
B15: Equity Risk Premium | G15: =SUMPRODUCT(J9:J14,K9:K14) -> 0.055250244 | M15: =+Peers!B13 -> SERVICENOW, INC. | N15: =+Peers!K74 -> 0.77969867
B16: Unlevered Cost of Equity | G16: =IFERROR(+G12+G13*G15,"") -> 0.091896608 | M16: =+Peers!B14 -> AUTODESK, INC. | N16: =+Peers!L74 -> 0.83829183
M17: =+Peers!B15 -> SNOWFLAKE INC. | N17: =+Peers!M74 -> 0.6395347
B18: Debt (in millions) | G18: =Inputs!Q113 -> 6056 | M18: =+Peers!B16 -> ATLASSIAN CORPORATION | N18: =+Peers!N74 -> 0.17765844
B19: % of Debt | G19: =IFERROR(G18/G23,"") -> 0.037551745 | M19: Average | N19: =IFERROR(+AVERAGEIF(N9:N18,">0"),"") -> 0.86509316
B20: Cost of debt | G20: =Inputs!Q18/WACC!G18 -> 0.027906209
B21: Tax Rate | G21: =+DCF!H79 -> 0.0030958985
B23: Total | G23: =+G9+G18 -> 161270.8
B25: WACC | G25: =IFERROR(G10*G11+G19*G20*(1-G21),"") -> 0.091279702

Sheet Multiples
B2: Multiples
B4: Valuation | F4: 2014 | G4: =+F4+1 -> 2015 | H4: =+G4+1 -> 2016 | I4: =+H4+1 -> 2017 | J4: =+I4+1 -> 2018 | K4: =+J4+1 -> 2019 | L4: =+K4+1 -> 2020 | M4: =+L4+1 -> 2021 | N4: 2022 | O4: =+N4+1 -> 2023 | P4: =+O4+1 -> 2024 | Q4: =+P4+1 -> 2025 | R4: =+Q4+1 -> 2026
B6: EV / Sales | F6: =IFERROR(_xlfn.XLOOKUP("Enterprise Value",Inputs!$B:$B,Inputs!G:G)/_xlfn.XLOOKUP("Revenue (Sales)",Inputs!$B:$B,Inputs!G:G),"") -> 8.2608392 | G6: =IFERROR(_xlfn.XLOOKUP("Enterprise Value",Inputs!$B:$B,Inputs!H:H)/_xlfn.XLOOKUP("Revenue (Sales)",Inputs!$B:$B,Inputs!H:H),"") -> 9.3351658 | H6: =IFERROR(_xlfn.XLOOKUP("Enterprise Value",Inputs!$B:$B,Inputs!I:I)/_xlfn.XLOOKUP("Revenue (Sales)",Inputs!$B:$B,Inputs!I:I),"") -> 0.16280075 | I6: =IFERROR(_xlfn.XLOOKUP("Enterprise Value",Inputs!$B:$B,Inputs!J:J)/_xlfn.XLOOKUP("Revenue (Sales)",Inputs!$B:$B,Inputs!J:J),"") -> -0.14082512 | J6: =IFERROR(_xlfn.XLOOKUP("Enterprise Value",Inputs!$B:$B,Inputs!K:K)/_xlfn.XLOOKUP("Revenue (Sales)",Inputs!$B:$B,Inputs!K:K),"") -> 12.382458 | K6: =IFERROR(_xlfn.XLOOKUP("Enterprise Value",Inputs!$B:$B,Inputs!L:L)/_xlfn.XLOOKUP("Revenue (Sales)",Inputs!$B:$B,Inputs!L:L),"") -> 14.35052 | L6: =IFERROR(_xlfn.XLOOKUP("Enterprise Value",Inputs!$B:$B,Inputs!M:M)/_xlfn.XLOOKUP("Revenue (Sales)",Inputs!$B:$B,Inputs!M:M),"") -> 18.594476 | M6: =IFERROR(_xlfn.XLOOKUP("Enterprise Value",Inputs!$B:$B,Inputs!N:N)/_xlfn.XLOOKUP("Revenue (Sales)",Inputs!$B:$B,Inputs!N:N),"") -> 17.064468 | N6: =IFERROR(_xlfn.XLOOKUP("Enterprise Value",Inputs!$B:$B,Inputs!O:O)/_xlfn.XLOOKUP("Revenue (Sales)",Inputs!$B:$B,Inputs!O:O),"") -> 0.66701863 | O6: =IFERROR(_xlfn.XLOOKUP("Enterprise Value",Inputs!$B:$B,Inputs!P:P)/_xlfn.XLOOKUP("Revenue (Sales)",Inputs!$B:$B,Inputs!P:P),"") -> 0.88313743 | P6: =IFERROR(_xlfn.XLOOKUP("Enterprise Value",Inputs!$B:$B,Inputs!Q:Q)/_xlfn.XLOOKUP("Revenue (Sales)",Inputs!$B:$B,Inputs!Q:Q),"") -> 9.1579614 | Q6: =IFERROR(_xlfn.XLOOKUP("Enterprise Value",DCF!$B:$B,DCF!R:R)/_xlfn.XLOOKUP("Revenue (Sales)",DCF!$B:$B,DCF!H:H),"") -> 12.668342 | R6: =IFERROR(_xlfn.XLOOKUP("Enterprise Value",DCF!$B:$B,DCF!S:S)/_xlfn.XLOOKUP("Revenue (Sales)",DCF!$B:$B,DCF!I:I),"") -> 12.303307
B7: Price / Sales | F7: =IFERROR(_xlfn.XLOOKUP("Market Capitalization",Inputs!$B:$B,Inputs!G:G)/_xlfn.XLOOKUP("Revenue (Sales)",Inputs!$B:$B,Inputs!G:G),"") -> 8.7829033 | G7: =IFERROR(_xlfn.XLOOKUP("Market Capitalization",Inputs!$B:$B,Inputs!H:H)/_xlfn.XLOOKUP("Revenue (Sales)",Inputs!$B:$B,Inputs!H:H),"") -> 9.756438 | H7: =IFERROR(_xlfn.XLOOKUP("Market Capitalization",Inputs!$B:$B,Inputs!I:I)/_xlfn.XLOOKUP("Revenue (Sales)",Inputs!$B:$B,Inputs!I:I),"") -> 0.64076454 | I7: =IFERROR(_xlfn.XLOOKUP("Market Capitalization",Inputs!$B:$B,Inputs!J:J)/_xlfn.XLOOKUP("Revenue (Sales)",Inputs!$B:$B,Inputs!J:J),"") -> 0.390335 | J7: =IFERROR(_xlfn.XLOOKUP("Market Capitalization",Inputs!$B:$B,Inputs!K:K)/_xlfn.XLOOKUP("Revenue (Sales)",Inputs!$B:$B,Inputs!K:K),"") -> 12.276589 | K7: =IFERROR(_xlfn.XLOOKUP("Market Capitalization",Inputs!$B:$B,Inputs!L:L)/_xlfn.XLOOKUP("Revenue (Sales)",Inputs!$B:$B,Inputs!L:L),"") -> 14.348551 | L7: =IFERROR(_xlfn.XLOOKUP("Market Capitalization",Inputs!$B:$B,Inputs!M:M)/_xlfn.XLOOKUP("Revenue (Sales)",Inputs!$B:$B,Inputs!M:M),"") -> 18.694259 | M7: =IFERROR(_xlfn.XLOOKUP("Market Capitalization",Inputs!$B:$B,Inputs!N:N)/_xlfn.XLOOKUP("Revenue (Sales)",Inputs!$B:$B,Inputs!N:N),"") -> 17.135738 | N7: =IFERROR(_xlfn.XLOOKUP("Market Capitalization",Inputs!$B:$B,Inputs!O:O)/_xlfn.XLOOKUP("Revenue (Sales)",Inputs!$B:$B,Inputs!O:O),"") -> 0.7501153 | O7: =IFERROR(_xlfn.XLOOKUP("Market Capitalization",Inputs!$B:$B,Inputs!P:P)/_xlfn.XLOOKUP("Revenue (Sales)",Inputs!$B:$B,Inputs!P:P),"") -> 1.076965 | P7: =IFERROR(_xlfn.XLOOKUP("Market Capitalization",Inputs!$B:$B,Inputs!Q:Q)/_xlfn.XLOOKUP("Revenue (Sales)",Inputs!$B:$B,Inputs!Q:Q),"") -> 9.2430579 | Q7: =IFERROR(_xlfn.XLOOKUP("Equity Value",DCF!$B:$B,DCF!R:R)/_xlfn.XLOOKUP("Revenue (Sales)",DCF!$B:$B,DCF!H:H),"") -> 13.509842 | R7: =IFERROR(_xlfn.XLOOKUP("Equity Value",DCF!$B:$B,DCF!S:S)/_xlfn.XLOOKUP("Revenue (Sales)",DCF!$B:$B,DCF!I:I),"") -> 13.658861
B8: EV / EBITDA | F8: =IFERROR(_xlfn.XLOOKUP("Enterprise Value",Inputs!$B:$B,Inputs!G:G)/_xlfn.XLOOKUP("EBITDA",Inputs!$B:$B,Inputs!G:G),"") -> 70.489095 | G8: =IFERROR(_xlfn.XLOOKUP("Enterprise Value",Inputs!$B:$B,Inputs!H:H)/_xlfn.XLOOKUP("EBITDA",Inputs!$B:$B,Inputs!H:H),"") -> 45.957002 | H8: =IFERROR(_xlfn.XLOOKUP("Enterprise Value",Inputs!$B:$B,Inputs!I:I)/_xlfn.XLOOKUP("EBITDA",Inputs!$B:$B,Inputs!I:I),"") -> 0.60625674 | I8: =IFERROR(_xlfn.XLOOKUP("Enterprise Value",Inputs!$B:$B,Inputs!J:J)/_xlfn.XLOOKUP("EBITDA",Inputs!$B:$B,Inputs!J:J),"") -> -0.45777569 | J8: =IFERROR(_xlfn.XLOOKUP("Enterprise Value",Inputs!$B:$B,Inputs!K:K)/_xlfn.XLOOKUP("EBITDA",Inputs!$B:$B,Inputs!K:K),"") -> 38.096627 | K8: =IFERROR(_xlfn.XLOOKUP("Enterprise Value",Inputs!$B:$B,Inputs!L:L)/_xlfn.XLOOKUP("EBITDA",Inputs!$B:$B,Inputs!L:L),"") -> 46.56104 | L8: =IFERROR(_xlfn.XLOOKUP("Enterprise Value",Inputs!$B:$B,Inputs!M:M)/_xlfn.XLOOKUP("EBITDA",Inputs!$B:$B,Inputs!M:M),"") -> 59.240832 | M8: =IFERROR(_xlfn.XLOOKUP("Enterprise Value",Inputs!$B:$B,Inputs!N:N)/_xlfn.XLOOKUP("EBITDA",Inputs!$B:$B,Inputs!N:N),"") -> 45.089156 | N8: =IFERROR(_xlfn.XLOOKUP("Enterprise Value",Inputs!$B:$B,Inputs!O:O)/_xlfn.XLOOKUP("EBITDA",Inputs!$B:$B,Inputs!O:O),"") -> 1.8984045 | O8: =IFERROR(_xlfn.XLOOKUP("Enterprise Value",Inputs!$B:$B,Inputs!P:P)/_xlfn.XLOOKUP("EBITDA",Inputs!$B:$B,Inputs!P:P),"") -> 2.5140532 | P8: =IFERROR(_xlfn.XLOOKUP("Enterprise Value",Inputs!$B:$B,Inputs!Q:Q)/_xlfn.XLOOKUP("EBITDA",Inputs!$B:$B,Inputs!Q:Q),"") -> 25.477614 | Q8: =IFERROR(_xlfn.XLOOKUP("Enterprise Value",DCF!$B:$B,DCF!R:R)/_xlfn.XLOOKUP("EBITDA",DCF!$B:$B,DCF!H:H),"") -> 22.20597 | R8: =IFERROR(_xlfn.XLOOKUP("Enterprise Value",DCF!$B:$B,DCF!S:S)/_xlfn.XLOOKUP("EBITDA",DCF!$B:$B,DCF!I:I),"") -> 21.35184
B9: EV / EBIT | F9: =IFERROR(_xlfn.XLOOKUP("Enterprise Value",Inputs!$B:$B,Inputs!G:G)/_xlfn.XLOOKUP("Operating Income (EBIT)",Inputs!$B:$B,Inputs!G:G),"") -> 196.88333 | G9: =IFERROR(_xlfn.XLOOKUP("Enterprise Value",Inputs!$B:$B,Inputs!H:H)/_xlfn.XLOOKUP("Operating Income (EBIT)",Inputs!$B:$B,Inputs!H:H),"") -> 70.050266 | H9: =IFERROR(_xlfn.XLOOKUP("Enterprise Value",Inputs!$B:$B,Inputs!I:I)/_xlfn.XLOOKUP("Operating Income (EBIT)",Inputs!$B:$B,Inputs!I:I),"") -> 0.7685771 | I9: =IFERROR(_xlfn.XLOOKUP("Enterprise Value",Inputs!$B:$B,Inputs!J:J)/_xlfn.XLOOKUP("Operating Income (EBIT)",Inputs!$B:$B,Inputs!J:J),"") -> -0.53522343 | J9: =IFERROR(_xlfn.XLOOKUP("Enterprise Value",Inputs!$B:$B,Inputs!K:K)/_xlfn.XLOOKUP("Operating Income (EBIT)",Inputs!$B:$B,Inputs!K:K),"") -> 43.187949 | K9: =IFERROR(_xlfn.XLOOKUP("Enterprise Value",Inputs!$B:$B,Inputs!L:L)/_xlfn.XLOOKUP("Operating Income (EBIT)",Inputs!$B:$B,Inputs!L:L),"") -> 59.683418 | L9: =IFERROR(_xlfn.XLOOKUP("Enterprise Value",Inputs!$B:$B,Inputs!M:M)/_xlfn.XLOOKUP("Operating Income (EBIT)",Inputs!$B:$B,Inputs!M:M),"") -> 72.904851 | M9: =IFERROR(_xlfn.XLOOKUP("Enterprise Value",Inputs!$B:$B,Inputs!N:N)/_xlfn.XLOOKUP("Operating Income (EBIT)",Inputs!$B:$B,Inputs!N:N),"") -> 46.425822 | N9: =IFERROR(_xlfn.XLOOKUP("Enterprise Value",Inputs!$B:$B,Inputs!O:O)/_xlfn.XLOOKUP("Operating Income (EBIT)",Inputs!$B:$B,Inputs!O:O),"") -> 1.9258003 | O9: =IFERROR(_xlfn.XLOOKUP("Enterprise Value",Inputs!$B:$B,Inputs!P:P)/_xlfn.XLOOKUP("Operating Income (EBIT)",Inputs!$B:$B,Inputs!P:P),"") -> 2.8827471 | P9: =IFERROR(_xlfn.XLOOKUP("Enterprise Value",Inputs!$B:$B,Inputs!Q:Q)/_xlfn.XLOOKUP("Operating Income (EBIT)",Inputs!$B:$B,Inputs!Q:Q),"") -> 28.654439 | Q9: =IFERROR(_xlfn.XLOOKUP("Enterprise Value",DCF!$B:$B,DCF!R:R)/_xlfn.XLOOKUP("Operating Income (EBIT)",DCF!$B:$B,DCF!H:H),"") -> 23.694591 | R9: =IFERROR(_xlfn.XLOOKUP("Enterprise Value",DCF!$B:$B,DCF!S:S)/_xlfn.XLOOKUP("Operating Income (EBIT)",DCF!$B:$B,DCF!I:I),"") -> 23.074834
B10: Price / Earnings | F10: =IFERROR(_xlfn.XLOOKUP("Market Capitalization",Inputs!$B:$B,Inputs!G:G)/_xlfn.XLOOKUP("Net Income",Inputs!$B:$B,Inputs!G:G),"") -> 135.9056 | G10: =IFERROR(_xlfn.XLOOKUP("Market Capitalization",Inputs!$B:$B,Inputs!H:H)/_xlfn.XLOOKUP("Net Income",Inputs!$B:$B,Inputs!H:H),"") -> 74.257333 | H10: =IFERROR(_xlfn.XLOOKUP("Market Capitalization",Inputs!$B:$B,Inputs!I:I)/_xlfn.XLOOKUP("Net Income",Inputs!$B:$B,Inputs!I:I),"") -> 3.2087559 | I10: =IFERROR(_xlfn.XLOOKUP("Market Capitalization",Inputs!$B:$B,Inputs!J:J)/_xlfn.XLOOKUP("Net Income",Inputs!$B:$B,Inputs!J:J),"") -> 1.6823116 | J10: =IFERROR(_xlfn.XLOOKUP("Market Capitalization",Inputs!$B:$B,Inputs!K:K)/_xlfn.XLOOKUP("Net Income",Inputs!$B:$B,Inputs!K:K),"") -> 42.802162 | K10: =IFERROR(_xlfn.XLOOKUP("Market Capitalization",Inputs!$B:$B,Inputs!L:L)/_xlfn.XLOOKUP("Net Income",Inputs!$B:$B,Inputs!L:L),"") -> 54.316388 | L10: =IFERROR(_xlfn.XLOOKUP("Market Capitalization",Inputs!$B:$B,Inputs!M:M)/_xlfn.XLOOKUP("Net Income",Inputs!$B:$B,Inputs!M:M),"") -> 45.733407 | M10: =IFERROR(_xlfn.XLOOKUP("Market Capitalization",Inputs!$B:$B,Inputs!N:N)/_xlfn.XLOOKUP("Net Income",Inputs!$B:$B,Inputs!N:N),"") -> 56.094488 | N10: =IFERROR(_xlfn.XLOOKUP("Market Capitalization",Inputs!$B:$B,Inputs!O:O)/_xlfn.XLOOKUP("Net Income",Inputs!$B:$B,Inputs!O:O),"") -> 2.7768146 | O10: =IFERROR(_xlfn.XLOOKUP("Market Capitalization",Inputs!$B:$B,Inputs!P:P)/_xlfn.XLOOKUP("Net Income",Inputs!$B:$B,Inputs!P:P),"") -> 3.8509238 | P10: =IFERROR(_xlfn.XLOOKUP("Market Capitalization",Inputs!$B:$B,Inputs!Q:Q)/_xlfn.XLOOKUP("Net Income",Inputs!$B:$B,Inputs!Q:Q),"") -> 35.750353 | Q10: =IFERROR(_xlfn.XLOOKUP("Equity Value",DCF!$B:$B,DCF!R:R)/_xlfn.XLOOKUP("Net Income",DCF!$B:$B,DCF!H:H),"") -> 25.119795 | R10: =IFERROR(_xlfn.XLOOKUP("Equity Value",DCF!$B:$B,DCF!S:S)/_xlfn.XLOOKUP("Net Income",DCF!$B:$B,DCF!I:I),"") -> 25.597311
B11: Price / Book | F11: =IFERROR(_xlfn.XLOOKUP("Market Capitalization",Inputs!$B:$B,Inputs!G:G)/_xlfn.XLOOKUP("Shareholder's Equity",Inputs!$B:$B,Inputs!G:G),"") -> 5.3752509 | G11: =IFERROR(_xlfn.XLOOKUP("Market Capitalization",Inputs!$B:$B,Inputs!H:H)/_xlfn.XLOOKUP("Shareholder's Equity",Inputs!$B:$B,Inputs!H:H),"") -> 6.6812511 | H11: =IFERROR(_xlfn.XLOOKUP("Market Capitalization",Inputs!$B:$B,Inputs!I:I)/_xlfn.XLOOKUP("Shareholder's Equity",Inputs!$B:$B,Inputs!I:I),"") -> 0.50518998 | I11: =IFERROR(_xlfn.XLOOKUP("Market Capitalization",Inputs!$B:$B,Inputs!J:J)/_xlfn.XLOOKUP("Shareholder's Equity",Inputs!$B:$B,Inputs!J:J),"") -> 0.34426622 | J11: =IFERROR(_xlfn.XLOOKUP("Market Capitalization",Inputs!$B:$B,Inputs!K:K)/_xlfn.XLOOKUP("Shareholder's Equity",Inputs!$B:$B,Inputs!K:K),"") -> 11.841231 | K11: =IFERROR(_xlfn.XLOOKUP("Market Capitalization",Inputs!$B:$B,Inputs!L:L)/_xlfn.XLOOKUP("Shareholder's Equity",Inputs!$B:$B,Inputs!L:L),"") -> 15.220555 | L11: =IFERROR(_xlfn.XLOOKUP("Market Capitalization",Inputs!$B:$B,Inputs!M:M)/_xlfn.XLOOKUP("Shareholder's Equity",Inputs!$B:$B,Inputs!M:M),"") -> 18.136137 | M11: =IFERROR(_xlfn.XLOOKUP("Market Capitalization",Inputs!$B:$B,Inputs!N:N)/_xlfn.XLOOKUP("Shareholder's Equity",Inputs!$B:$B,Inputs!N:N),"") -> 18.279896 | N11: =IFERROR(_xlfn.XLOOKUP("Market Capitalization",Inputs!$B:$B,Inputs!O:O)/_xlfn.XLOOKUP("Shareholder's Equity",Inputs!$B:$B,Inputs!O:O),"") -> 0.94745175 | O11: =IFERROR(_xlfn.XLOOKUP("Market Capitalization",Inputs!$B:$B,Inputs!P:P)/_xlfn.XLOOKUP("Shareholder's Equity",Inputs!$B:$B,Inputs!P:P),"") -> 1.2537677 | P11: =IFERROR(_xlfn.XLOOKUP("Market Capitalization",Inputs!$B:$B,Inputs!Q:Q)/_xlfn.XLOOKUP("Shareholder's Equity",Inputs!$B:$B,Inputs!Q:Q),"") -> 14.730396 | Q11: =IFERROR(+_xlfn.XLOOKUP("Equity Value",DCF!$B:$B,DCF!R:R)/(_xlfn.XLOOKUP("Shareholder's Equity",Inputs!$B:$B,Inputs!$Q:$Q)+_xlfn.XLOOKUP("Net Income",DCF!$B:$B,DCF!H:H)+_xlfn.XLOOKUP("Total Payout",DCF!$B:$B,DCF!H:H)),"") | R11: =IFERROR(+_xlfn.XLOOKUP("Equity Value",DCF!$B:$B,DCF!S:S)/(_xlfn.XLOOKUP("Shareholder's Equity",Inputs!$B:$B,Inputs!$Q:$Q)+_xlfn.XLOOKUP("Net Income",DCF!$B:$B,DCF!I:I)+_xlfn.XLOOKUP("Total Payout",DCF!$B:$B,DCF!I:I)),"")
B13: Profitability | F13: 2014 | G13: =+F13+1 -> 2015 | H13: =+G13+1 -> 2016 | I13: =+H13+1 -> 2017 | J13: =+I13+1 -> 2018 | K13: =+J13+1 -> 2019 | L13: =+K13+1 -> 2020 | M13: =+L13+1 -> 2021 | N13: 2022 | O13: =+N13+1 -> 2023 | P13: =+O13+1 -> 2024 | Q13: =+P13+1 -> 2025 | R13: =+Q13+1 -> 2026
B15: Return on Assets | F15: =+IFERROR(_xlfn.XLOOKUP("Net Income",Inputs!$B:$B,Inputs!G:G)/_xlfn.XLOOKUP("Total Assets",Inputs!$B:$B,Inputs!G:G),"") -> 0.024849328 | G15: =+IFERROR(_xlfn.XLOOKUP("Net Income",Inputs!$B:$B,Inputs!H:H)/_xlfn.XLOOKUP("Total Assets",Inputs!$B:$B,Inputs!H:H),"") -> 0.053726761 | H15: =+IFERROR(_xlfn.XLOOKUP("Net Income",Inputs!$B:$B,Inputs!I:I)/_xlfn.XLOOKUP("Total Assets",Inputs!$B:$B,Inputs!I:I),"") -> 0.091996537 | I15: =+IFERROR(_xlfn.XLOOKUP("Net Income",Inputs!$B:$B,Inputs!J:J)/_xlfn.XLOOKUP("Total Assets",Inputs!$B:$B,Inputs!J:J),"") -> 0.11802411 | J15: =+IFERROR(_xlfn.XLOOKUP("Net Income",Inputs!$B:$B,Inputs!K:K)/_xlfn.XLOOKUP("Total Assets",Inputs!$B:$B,Inputs!K:K),"") -> 0.13800085 | K15: =+IFERROR(_xlfn.XLOOKUP("Net Income",Inputs!$B:$B,Inputs!L:L)/_xlfn.XLOOKUP("Total Assets",Inputs!$B:$B,Inputs!L:L),"") -> 0.14212782 | L15: =+IFERROR(_xlfn.XLOOKUP("Net Income",Inputs!$B:$B,Inputs!M:M)/_xlfn.XLOOKUP("Total Assets",Inputs!$B:$B,Inputs!M:M),"") -> 0.21660352 | M15: =+IFERROR(_xlfn.XLOOKUP("Net Income",Inputs!$B:$B,Inputs!N:N)/_xlfn.XLOOKUP("Total Assets",Inputs!$B:$B,Inputs!N:N),"") -> 0.17701259 | N15: =+IFERROR(_xlfn.XLOOKUP("Net Income",Inputs!$B:$B,Inputs!O:O)/_xlfn.XLOOKUP("Total Assets",Inputs!$B:$B,Inputs!O:O),"") -> 0.17507823 | O15: =+IFERROR(_xlfn.XLOOKUP("Net Income",Inputs!$B:$B,Inputs!P:P)/_xlfn.XLOOKUP("Total Assets",Inputs!$B:$B,Inputs!P:P),"") -> 0.18215376 | P15: =+IFERROR(_xlfn.XLOOKUP("Net Income",Inputs!$B:$B,Inputs!Q:Q)/_xlfn.XLOOKUP("Total Assets",Inputs!$B:$B,Inputs!Q:Q),"") -> 0.18532098 | Q15: =IFERROR(_xlfn.XLOOKUP("Net Income",DCF!$B:$B,DCF!H:H)/_xlfn.XLOOKUP("Total assets",DCF!$6:$6,DCF!10:10),"") -> 0.25730394 | R15: =IFERROR(_xlfn.XLOOKUP("Net Income",DCF!$B:$B,DCF!I:I)/_xlfn.XLOOKUP("Total assets",DCF!$6:$6,DCF!10:10),"") -> 0.27311256
B16: Return on Equity | F16: =IFERROR(_xlfn.XLOOKUP("Net Income",Inputs!$B:$B,Inputs!G:G)/_xlfn.XLOOKUP("Shareholder's Equity",Inputs!$B:$B,Inputs!G:G),"") -> 0.039551358 | G16: =IFERROR(_xlfn.XLOOKUP("Net Income",Inputs!$B:$B,Inputs!H:H)/_xlfn.XLOOKUP("Shareholder's Equity",Inputs!$B:$B,Inputs!H:H),"") -> 0.089974293 | H16: =IFERROR(_xlfn.XLOOKUP("Net Income",Inputs!$B:$B,Inputs!I:I)/_xlfn.XLOOKUP("Shareholder's Equity",Inputs!$B:$B,Inputs!I:I),"") -> 0.15744108 | I16: =IFERROR(_xlfn.XLOOKUP("Net Income",Inputs!$B:$B,Inputs!J:J)/_xlfn.XLOOKUP("Shareholder's Equity",Inputs!$B:$B,Inputs!J:J),"") -> 0.2046388 | J16: =IFERROR(_xlfn.XLOOKUP("Net Income",Inputs!$B:$B,Inputs!K:K)/_xlfn.XLOOKUP("Shareholder's Equity",Inputs!$B:$B,Inputs!K:K),"") -> 0.27665029 | K16: =IFERROR(_xlfn.XLOOKUP("Net Income",Inputs!$B:$B,Inputs!L:L)/_xlfn.XLOOKUP("Shareholder's Equity",Inputs!$B:$B,Inputs!L:L),"") -> 0.2802203 | L16: =IFERROR(_xlfn.XLOOKUP("Net Income",Inputs!$B:$B,Inputs!M:M)/_xlfn.XLOOKUP("Shareholder's Equity",Inputs!$B:$B,Inputs!M:M),"") -> 0.39656212 | M16: =IFERROR(_xlfn.XLOOKUP("Net Income",Inputs!$B:$B,Inputs!N:N)/_xlfn.XLOOKUP("Shareholder's Equity",Inputs!$B:$B,Inputs!N:N),"") -> 0.32587687 | N16: =IFERROR(_xlfn.XLOOKUP("Net Income",Inputs!$B:$B,Inputs!O:O)/_xlfn.XLOOKUP("Shareholder's Equity",Inputs!$B:$B,Inputs!O:O),"") -> 0.34120095 | O16: =IFERROR(_xlfn.XLOOKUP("Net Income",Inputs!$B:$B,Inputs!P:P)/_xlfn.XLOOKUP("Shareholder's Equity",Inputs!$B:$B,Inputs!P:P),"") -> 0.32557582 | P16: =IFERROR(_xlfn.XLOOKUP("Net Income",Inputs!$B:$B,Inputs!Q:Q)/_xlfn.XLOOKUP("Shareholder's Equity",Inputs!$B:$B,Inputs!Q:Q),"") -> 0.41203498 | Q16: =IFERROR(_xlfn.XLOOKUP("Net Income",DCF!$B:$B,DCF!H:H)/_xlfn.XLOOKUP("Shareholder's Equity",DCF!$6:$6,DCF!10:10),"") -> -1.1107671e-11 | R16: =IFERROR(_xlfn.XLOOKUP("Net Income",DCF!$B:$B,DCF!I:I)/_xlfn.XLOOKUP("Shareholder's Equity",DCF!$6:$6,DCF!10:10),"") -> -1.179012e-11
B17: Return on Total Capital | F17: =IFERROR(_xlfn.XLOOKUP("NOPAT",Inputs!$B:$B,Inputs!G:G)/(_xlfn.XLOOKUP("Shareholder's Equity",Inputs!$B:$B,Inputs!G:G)+_xlfn.XLOOKUP("Total Debt",Inputs!$B:$B,Inputs!G:G,,,-1)),"") -> 0.015470002 | G17: =IFERROR(_xlfn.XLOOKUP("NOPAT",Inputs!$B:$B,Inputs!H:H)/(_xlfn.XLOOKUP("Shareholder's Equity",Inputs!$B:$B,Inputs!H:H)+_xlfn.XLOOKUP("Total Debt",Inputs!$B:$B,Inputs!H:H,,,-1)),"") -> 0.05135538 | H17: =IFERROR(_xlfn.XLOOKUP("NOPAT",Inputs!$B:$B,Inputs!I:I)/(_xlfn.XLOOKUP("Shareholder's Equity",Inputs!$B:$B,Inputs!I:I)+_xlfn.XLOOKUP("Total Debt",Inputs!$B:$B,Inputs!I:I,,,-1)),"") -> 0.1076112 | I17: =IFERROR(_xlfn.XLOOKUP("NOPAT",Inputs!$B:$B,Inputs!J:J)/(_xlfn.XLOOKUP("Shareholder's Equity",Inputs!$B:$B,Inputs!J:J)+_xlfn.XLOOKUP("Total Debt",Inputs!$B:$B,Inputs!J:J,,,-1)),"") -> 0.14901427 | J17: =IFERROR(_xlfn.XLOOKUP("NOPAT",Inputs!$B:$B,Inputs!K:K)/(_xlfn.XLOOKUP("Shareholder's Equity",Inputs!$B:$B,Inputs!K:K)+_xlfn.XLOOKUP("Total Debt",Inputs!$B:$B,Inputs!K:K,,,-1)),"") -> 0.17723513 | K17: =IFERROR(_xlfn.XLOOKUP("NOPAT",Inputs!$B:$B,Inputs!L:L)/(_xlfn.XLOOKUP("Shareholder's Equity",Inputs!$B:$B,Inputs!L:L)+_xlfn.XLOOKUP("Total Debt",Inputs!$B:$B,Inputs!L:L,,,-1)),"") -> 0.16790898 | L17: =IFERROR(_xlfn.XLOOKUP("NOPAT",Inputs!$B:$B,Inputs!M:M)/(_xlfn.XLOOKUP("Shareholder's Equity",Inputs!$B:$B,Inputs!M:M)+_xlfn.XLOOKUP("Total Debt",Inputs!$B:$B,Inputs!M:M,,,-1)),"") -> 0.23002096 | M17: =IFERROR(_xlfn.XLOOKUP("NOPAT",Inputs!$B:$B,Inputs!N:N)/(_xlfn.XLOOKUP("Shareholder's Equity",Inputs!$B:$B,Inputs!N:N)+_xlfn.XLOOKUP("Total Debt",Inputs!$B:$B,Inputs!N:N,,,-1)),"") -> 0.25187399 | N17: =IFERROR(_xlfn.XLOOKUP("NOPAT",Inputs!$B:$B,Inputs!O:O)/(_xlfn.XLOOKUP("Shareholder's Equity",Inputs!$B:$B,Inputs!O:O)+_xlfn.XLOOKUP("Total Debt",Inputs!$B:$B,Inputs!O:O,,,-1)),"") -> 0.25992058 | O17: =IFERROR(_xlfn.XLOOKUP("NOPAT",Inputs!$B:$B,Inputs!P:P)/(_xlfn.XLOOKUP("Shareholder's Equity",Inputs!$B:$B,Inputs!P:P)+_xlfn.XLOOKUP("Total Debt",Inputs!$B:$B,Inputs!P:P,,,-1)),"") -> 0.22874928 | P17: =IFERROR(_xlfn.XLOOKUP("NOPAT",Inputs!$B:$B,Inputs!Q:Q)/(_xlfn.XLOOKUP("Shareholder's Equity",Inputs!$B:$B,Inputs!Q:Q)+_xlfn.XLOOKUP("Total Debt",Inputs!$B:$B,Inputs!Q:Q,,,-1)),"") -> 0.28201907 | Q17: =+IFERROR(_xlfn.XLOOKUP("NOPAT",DCF!$B:$B,DCF!H:H)/(_xlfn.XLOOKUP("Shareholder's Equity",DCF!$6:$6,DCF!10:10)+_xlfn.XLOOKUP("Total Borrowings",DCF!$B:$B,DCF!H:H)+_xlfn.XLOOKUP("Total Leases",DCF!$B:$B,DCF!H:H)),"") -> -1.100811e-11 | R17: =+IFERROR(_xlfn.XLOOKUP("NOPAT",DCF!$B:$B,DCF!I:I)/(_xlfn.XLOOKUP("Shareholder's Equity",DCF!$6:$6,DCF!10:10)+_xlfn.XLOOKUP("Total Borrowings",DCF!$B:$B,DCF!I:I)+_xlfn.XLOOKUP("Total Leases",DCF!$B:$B,DCF!I:I)),"") -> -1.1745971e-11
B18: EBITDA Margin | F18: =+IFERROR(_xlfn.XLOOKUP("EBITDA",Inputs!$B:$B,Inputs!G:G)/_xlfn.XLOOKUP("Revenue (Sales)",Inputs!$B:$B,Inputs!G:G),"") -> 0.11719315 | G18: =+IFERROR(_xlfn.XLOOKUP("EBITDA",Inputs!$B:$B,Inputs!H:H)/_xlfn.XLOOKUP("Revenue (Sales)",Inputs!$B:$B,Inputs!H:H),"") -> 0.20312826 | H18: =+IFERROR(_xlfn.XLOOKUP("EBITDA",Inputs!$B:$B,Inputs!I:I)/_xlfn.XLOOKUP("Revenue (Sales)",Inputs!$B:$B,Inputs!I:I),"") -> 0.26853434 | I18: =+IFERROR(_xlfn.XLOOKUP("EBITDA",Inputs!$B:$B,Inputs!J:J)/_xlfn.XLOOKUP("Revenue (Sales)",Inputs!$B:$B,Inputs!J:J),"") -> 0.30762909 | J18: =+IFERROR(_xlfn.XLOOKUP("EBITDA",Inputs!$B:$B,Inputs!K:K)/_xlfn.XLOOKUP("Revenue (Sales)",Inputs!$B:$B,Inputs!K:K),"") -> 0.32502769 | K18: =+IFERROR(_xlfn.XLOOKUP("EBITDA",Inputs!$B:$B,Inputs!L:L)/_xlfn.XLOOKUP("Revenue (Sales)",Inputs!$B:$B,Inputs!L:L),"") -> 0.30820875 | L18: =+IFERROR(_xlfn.XLOOKUP("EBITDA",Inputs!$B:$B,Inputs!M:M)/_xlfn.XLOOKUP("Revenue (Sales)",Inputs!$B:$B,Inputs!M:M),"") -> 0.31387939 | M18: =+IFERROR(_xlfn.XLOOKUP("EBITDA",Inputs!$B:$B,Inputs!N:N)/_xlfn.XLOOKUP("Revenue (Sales)",Inputs!$B:$B,Inputs!N:N),"") -> 0.37846056 | N18: =+IFERROR(_xlfn.XLOOKUP("EBITDA",Inputs!$B:$B,Inputs!O:O)/_xlfn.XLOOKUP("Revenue (Sales)",Inputs!$B:$B,Inputs!O:O),"") -> 0.35135749 | O18: =+IFERROR(_xlfn.XLOOKUP("EBITDA",Inputs!$B:$B,Inputs!P:P)/_xlfn.XLOOKUP("Revenue (Sales)",Inputs!$B:$B,Inputs!P:P),"") -> 0.35128033 | P18: =+IFERROR(_xlfn.XLOOKUP("EBITDA",Inputs!$B:$B,Inputs!Q:Q)/_xlfn.XLOOKUP("Revenue (Sales)",Inputs!$B:$B,Inputs!Q:Q),"") -> 0.35945129 | Q18: =+_xlfn.XLOOKUP("EBITDA Margin",DCF!$B:$B,DCF!H:H) -> 0.57049261 | R18: =+_xlfn.XLOOKUP("EBITDA Margin",DCF!$B:$B,DCF!I:I) -> 0.57621766
B19: EBIT Margin | F19: =IFERROR(_xlfn.XLOOKUP("Operating Income (EBIT)",Inputs!$B:$B,Inputs!G:G)/_xlfn.XLOOKUP("Revenue (Sales)",Inputs!$B:$B,Inputs!G:G),"") -> 0.041958042 | G19: =IFERROR(_xlfn.XLOOKUP("Operating Income (EBIT)",Inputs!$B:$B,Inputs!H:H)/_xlfn.XLOOKUP("Revenue (Sales)",Inputs!$B:$B,Inputs!H:H),"") -> 0.13326382 | H19: =IFERROR(_xlfn.XLOOKUP("Operating Income (EBIT)",Inputs!$B:$B,Inputs!I:I)/_xlfn.XLOOKUP("Revenue (Sales)",Inputs!$B:$B,Inputs!I:I),"") -> 0.21182098 | I19: =IFERROR(_xlfn.XLOOKUP("Operating Income (EBIT)",Inputs!$B:$B,Inputs!J:J)/_xlfn.XLOOKUP("Revenue (Sales)",Inputs!$B:$B,Inputs!J:J),"") -> 0.26311464 | J19: =IFERROR(_xlfn.XLOOKUP("Operating Income (EBIT)",Inputs!$B:$B,Inputs!K:K)/_xlfn.XLOOKUP("Revenue (Sales)",Inputs!$B:$B,Inputs!K:K),"") -> 0.28671096 | K19: =IFERROR(_xlfn.XLOOKUP("Operating Income (EBIT)",Inputs!$B:$B,Inputs!L:L)/_xlfn.XLOOKUP("Revenue (Sales)",Inputs!$B:$B,Inputs!L:L),"") -> 0.24044401 | L19: =IFERROR(_xlfn.XLOOKUP("Operating Income (EBIT)",Inputs!$B:$B,Inputs!M:M)/_xlfn.XLOOKUP("Revenue (Sales)",Inputs!$B:$B,Inputs!M:M),"") -> 0.25505129 | M19: =IFERROR(_xlfn.XLOOKUP("Operating Income (EBIT)",Inputs!$B:$B,Inputs!N:N)/_xlfn.XLOOKUP("Revenue (Sales)",Inputs!$B:$B,Inputs!N:N),"") -> 0.36756414 | N19: =IFERROR(_xlfn.XLOOKUP("Operating Income (EBIT)",Inputs!$B:$B,Inputs!O:O)/_xlfn.XLOOKUP("Revenue (Sales)",Inputs!$B:$B,Inputs!O:O),"") -> 0.3463592 | O19: =IFERROR(_xlfn.XLOOKUP("Operating Income (EBIT)",Inputs!$B:$B,Inputs!P:P)/_xlfn.XLOOKUP("Revenue (Sales)",Inputs!$B:$B,Inputs!P:P),"") -> 0.30635272 | P19: =IFERROR(_xlfn.XLOOKUP("Operating Income (EBIT)",Inputs!$B:$B,Inputs!Q:Q)/_xlfn.XLOOKUP("Revenue (Sales)",Inputs!$B:$B,Inputs!Q:Q),"") -> 0.31960009 | Q19: =+_xlfn.XLOOKUP("Operating Margin",DCF!$B:$B,DCF!H:H) -> 0.53465122 | R19: =+_xlfn.XLOOKUP("Operating Margin",DCF!$B:$B,DCF!I:I) -> 0.53319159
B20: EBT Margin | F20: =IFERROR(_xlfn.XLOOKUP("Pre-Tax Income (EBT)",Inputs!$B:$B,Inputs!G:G)/_xlfn.XLOOKUP("Revenue (Sales)",Inputs!$B:$B,Inputs!G:G),"") -> 0.08705088 | G20: =IFERROR(_xlfn.XLOOKUP("Pre-Tax Income (EBT)",Inputs!$B:$B,Inputs!H:H)/_xlfn.XLOOKUP("Revenue (Sales)",Inputs!$B:$B,Inputs!H:H),"") -> 0.1822732 | H20: =IFERROR(_xlfn.XLOOKUP("Pre-Tax Income (EBT)",Inputs!$B:$B,Inputs!I:I)/_xlfn.XLOOKUP("Revenue (Sales)",Inputs!$B:$B,Inputs!I:I),"") -> 0.24513153 | I20: =IFERROR(_xlfn.XLOOKUP("Pre-Tax Income (EBT)",Inputs!$B:$B,Inputs!J:J)/_xlfn.XLOOKUP("Revenue (Sales)",Inputs!$B:$B,Inputs!J:J),"") -> 0.29269963 | J20: =IFERROR(_xlfn.XLOOKUP("Pre-Tax Income (EBT)",Inputs!$B:$B,Inputs!K:K)/_xlfn.XLOOKUP("Revenue (Sales)",Inputs!$B:$B,Inputs!K:K),"") -> 0.30930233 | K20: =IFERROR(_xlfn.XLOOKUP("Pre-Tax Income (EBT)",Inputs!$B:$B,Inputs!L:L)/_xlfn.XLOOKUP("Revenue (Sales)",Inputs!$B:$B,Inputs!L:L),"") -> 0.28690359 | L20: =IFERROR(_xlfn.XLOOKUP("Pre-Tax Income (EBT)",Inputs!$B:$B,Inputs!M:M)/_xlfn.XLOOKUP("Revenue (Sales)",Inputs!$B:$B,Inputs!M:M),"") -> 0.32452596 | M20: =IFERROR(_xlfn.XLOOKUP("Pre-Tax Income (EBT)",Inputs!$B:$B,Inputs!N:N)/_xlfn.XLOOKUP("Revenue (Sales)",Inputs!$B:$B,Inputs!N:N),"") -> 0.36141907 | N20: =IFERROR(_xlfn.XLOOKUP("Pre-Tax Income (EBT)",Inputs!$B:$B,Inputs!O:O)/_xlfn.XLOOKUP("Revenue (Sales)",Inputs!$B:$B,Inputs!O:O),"") -> 0.3412473 | O20: =IFERROR(_xlfn.XLOOKUP("Pre-Tax Income (EBT)",Inputs!$B:$B,Inputs!P:P)/_xlfn.XLOOKUP("Revenue (Sales)",Inputs!$B:$B,Inputs!P:P),"") -> 0.35030141 | P20: =IFERROR(_xlfn.XLOOKUP("Pre-Tax Income (EBT)",Inputs!$B:$B,Inputs!Q:Q)/_xlfn.XLOOKUP("Revenue (Sales)",Inputs!$B:$B,Inputs!Q:Q),"") -> 0.32229714 | Q20: =IFERROR(_xlfn.XLOOKUP("Pre-Tax Income (EBT)",DCF!$B:$B,DCF!H:H)/_xlfn.XLOOKUP("Revenue (Sales)",DCF!$B:$B,DCF!H:H),"") -> 0.5394718 | R20: =IFERROR(_xlfn.XLOOKUP("Pre-Tax Income (EBT)",DCF!$B:$B,DCF!I:I)/_xlfn.XLOOKUP("Revenue (Sales)",DCF!$B:$B,DCF!I:I),"") -> 0.53518974
B21: Gross Profit Margin | F21: =IFERROR(_xlfn.XLOOKUP("Gross Profit",Inputs!$B:$B,Inputs!G:G)/_xlfn.XLOOKUP("Revenue (Sales)",Inputs!$B:$B,Inputs!G:G),"") -> 0.85001206 | G21: =IFERROR(_xlfn.XLOOKUP("Gross Profit",Inputs!$B:$B,Inputs!H:H)/_xlfn.XLOOKUP("Revenue (Sales)",Inputs!$B:$B,Inputs!H:H),"") -> 0.84483837 | H21: =IFERROR(_xlfn.XLOOKUP("Gross Profit",Inputs!$B:$B,Inputs!I:I)/_xlfn.XLOOKUP("Revenue (Sales)",Inputs!$B:$B,Inputs!I:I),"") -> 0.85992484 | I21: =IFERROR(_xlfn.XLOOKUP("Gross Profit",Inputs!$B:$B,Inputs!J:J)/_xlfn.XLOOKUP("Revenue (Sales)",Inputs!$B:$B,Inputs!J:J),"") -> 0.86166279 | J21: =IFERROR(_xlfn.XLOOKUP("Gross Profit",Inputs!$B:$B,Inputs!K:K)/_xlfn.XLOOKUP("Revenue (Sales)",Inputs!$B:$B,Inputs!K:K),"") -> 0.86777409 | K21: =IFERROR(_xlfn.XLOOKUP("Gross Profit",Inputs!$B:$B,Inputs!L:L)/_xlfn.XLOOKUP("Revenue (Sales)",Inputs!$B:$B,Inputs!L:L),"") -> 0.85023722 | L21: =IFERROR(_xlfn.XLOOKUP("Gross Profit",Inputs!$B:$B,Inputs!M:M)/_xlfn.XLOOKUP("Revenue (Sales)",Inputs!$B:$B,Inputs!M:M),"") -> 0.86617967 | M21: =IFERROR(_xlfn.XLOOKUP("Gross Profit",Inputs!$B:$B,Inputs!N:N)/_xlfn.XLOOKUP("Revenue (Sales)",Inputs!$B:$B,Inputs!N:N),"") -> 0.88184986 | N21: =IFERROR(_xlfn.XLOOKUP("Gross Profit",Inputs!$B:$B,Inputs!O:O)/_xlfn.XLOOKUP("Revenue (Sales)",Inputs!$B:$B,Inputs!O:O),"") -> 0.87703056 | O21: =IFERROR(_xlfn.XLOOKUP("Gross Profit",Inputs!$B:$B,Inputs!P:P)/_xlfn.XLOOKUP("Revenue (Sales)",Inputs!$B:$B,Inputs!P:P),"") -> 0.87871606 | P21: =IFERROR(_xlfn.XLOOKUP("Gross Profit",Inputs!$B:$B,Inputs!Q:Q)/_xlfn.XLOOKUP("Revenue (Sales)",Inputs!$B:$B,Inputs!Q:Q),"") -> 0.88198093 | Q21: =+_xlfn.XLOOKUP("Gross Profit Margin",DCF!$B:$B,DCF!H:H) -> 0.87924252 | R21: =+_xlfn.XLOOKUP("Gross Profit Margin",DCF!$B:$B,DCF!I:I) -> 0.87997984
