Workbook
Name COOLFUCNTION: _xlfn.LAMBDA(_xldudf_BOARDFLARE_EXEC("workbook-settings:coolfucntion"))
Name COOLFUCNTION: _xlfn.LAMBDA(_xldudf_BOARDFLARE_EXEC("workbook-settings:coolfucntion"))
Name COOLFUCNTION: _xlfn.LAMBDA(_xldudf_BOARDFLARE_EXEC("workbook-settings:coolfucntion"))
Name COOLFUCNTION: _xlfn.LAMBDA(_xldudf_BOARDFLARE_EXEC("workbook-settings:coolfucntion"))
Name COOLFUCNTION: _xlfn.LAMBDA(_xldudf_BOARDFLARE_EXEC("workbook-settings:coolfucntion"))
Name COOLFUCNTION: _xlfn.LAMBDA(_xldudf_BOARDFLARE_EXEC("workbook-settings:coolfucntion"))
Name COOLFUCNTION: _xlfn.LAMBDA(_xldudf_BOARDFLARE_EXEC("workbook-settings:coolfucntion"))
Name COOLFUCNTION: _xlfn.LAMBDA(_xldudf_BOARDFLARE_EXEC("workbook-settings:coolfucntion"))
Name COOLFUCNTION: _xlfn.LAMBDA(_xldudf_BOARDFLARE_EXEC("workbook-settings:coolfucntion"))
Name COOLFUCNTION: _xlfn.LAMBDA(_xldudf_BOARDFLARE_EXEC("workbook-settings:coolfucntion"))
Name Sectors: #REF!
Name Sectors: #REF!
Name Sectors: #REF!

Sheet Summary
E2: | EQUITY RESEARCH | U2: Lisbon Investment Society Equity Research
U3: March XX, 2025
D6: {=+_FV(DCF!R4,"Name")} -> ADVANCED MICRO DEVICES, INC. | U6: Hold
U8: EXCHANGE:(TICKER)
U9: {=+"Price (7 Mar 25): $"&_FV(DCF!$R$4,"Price")} -> Price (7 Mar 25): $156,6514
D10: Investment Thesis | U10: ="Price Target: $" & ROUND(IF(Summary!G25="FCFF",DCF!Q208,IF(Summary!G25="FCFE",DCF!Q251,IF(Summary!G25="Tax Shield",DCF!Q224,DCF!Q267))),2) &" "&IF(Summary!G25="FCFF","(FCFF)",IF(Summary!G25="FCFE","(FCFE)",IF(Summary!G25="Tax Shield","(APV)","(DDM)"))) -> Price Target: $0 (FCFF)
U11: =+"Upside (Downside): "&ROUND((DCF!$Q$211*100),2)&"%" -> Upside (Downside): -100%
U14: =+Industry!E28&", "&ESG!C9 -> ,
U15: =+ESG!C10 -> 0
D17: Operating Metrics | F17: 2023 | G17: =+F17+1 -> 2024 | H17: =+G17+1 -> 2025 | I17: =+H17+1 -> 2026 | K17: Valuation Multiples | N17: 2022 | O17: =+N17+1 -> 2023 | P17: =+O17+1 -> 2024 | Q17: =+P17+1 -> 2025 | R17: =+Q17+1 -> 2026 | U17: Team Leader
K18: EV / Sales | N18: =IFERROR(_xlfn.XLOOKUP($K18,Multiples!$B:$B,Multiples!N:N),"") | O18: =IFERROR(_xlfn.XLOOKUP($K18,Multiples!$B:$B,Multiples!O:O),"") | P18: =IFERROR(_xlfn.XLOOKUP($K18,Multiples!$B:$B,Multiples!P:P),"") | Q18: =IFERROR(_xlfn.XLOOKUP($K18,Multiples!$B:$B,Multiples!Q:Q),"") | R18: =IFERROR(_xlfn.XLOOKUP($K18,Multiples!$B:$B,Multiples!R:R),"") | U18: email
K19: Price / Sales | N19: =IFERROR(_xlfn.XLOOKUP($K19,Multiples!$B:$B,Multiples!N:N),"") | O19: =IFERROR(_xlfn.XLOOKUP($K19,Multiples!$B:$B,Multiples!O:O),"") | P19: =IFERROR(_xlfn.XLOOKUP($K19,Multiples!$B:$B,Multiples!P:P),"") | Q19: =IFERROR(_xlfn.XLOOKUP($K19,Multiples!$B:$B,Multiples!Q:Q),"") | R19: =IFERROR(_xlfn.XLOOKUP($K19,Multiples!$B:$B,Multiples!R:R),"") | U19: (+351) 999 999 999
K20: EV / EBITDA | N20: =IFERROR(_xlfn.XLOOKUP($K20,Multiples!$B:$B,Multiples!N:N),"") | O20: =IFERROR(_xlfn.XLOOKUP($K20,Multiples!$B:$B,Multiples!O:O),"") | P20: =IFERROR(_xlfn.XLOOKUP($K20,Multiples!$B:$B,Multiples!P:P),"") | Q20: =IFERROR(_xlfn.XLOOKUP($K20,Multiples!$B:$B,Multiples!Q:Q),"") | R20: =IFERROR(_xlfn.XLOOKUP($K20,Multiples!$B:$B,Multiples!R:R),"") | U20: Analyst 1
K21: EV / EBIT | N21: =IFERROR(_xlfn.XLOOKUP($K21,Multiples!$B:$B,Multiples!N:N),"") | O21: =IFERROR(_xlfn.XLOOKUP($K21,Multiples!$B:$B,Multiples!O:O),"") | P21: =IFERROR(_xlfn.XLOOKUP($K21,Multiples!$B:$B,Multiples!P:P),"") | Q21: =IFERROR(_xlfn.XLOOKUP($K21,Multiples!$B:$B,Multiples!Q:Q),"") | R21: =IFERROR(_xlfn.XLOOKUP($K21,Multiples!$B:$B,Multiples!R:R),"") | U21: email
K22: Price / Earnings | N22: =IFERROR(_xlfn.XLOOKUP($K22,Multiples!$B:$B,Multiples!N:N),"") | O22: =IFERROR(_xlfn.XLOOKUP($K22,Multiples!$B:$B,Multiples!O:O),"") | P22: =IFERROR(_xlfn.XLOOKUP($K22,Multiples!$B:$B,Multiples!P:P),"") | Q22: =IFERROR(_xlfn.XLOOKUP($K22,Multiples!$B:$B,Multiples!Q:Q),"") | R22: =IFERROR(_xlfn.XLOOKUP($K22,Multiples!$B:$B,Multiples!R:R),"") | U22: (+351) 999 999 999
K23: Price / Book | N23: =IFERROR(_xlfn.XLOOKUP($K23,Multiples!$B:$B,Multiples!N:N),"") | O23: =IFERROR(_xlfn.XLOOKUP($K23,Multiples!$B:$B,Multiples!O:O),"") | P23: =IFERROR(_xlfn.XLOOKUP($K23,Multiples!$B:$B,Multiples!P:P),"") | Q23: =IFERROR(_xlfn.XLOOKUP($K23,Multiples!$B:$B,Multiples!Q:Q),"") | R23: =IFERROR(_xlfn.XLOOKUP($K23,Multiples!$B:$B,Multiples!R:R),"") | U23: Analyst 2
U24: email
D25: Year | E25: Net Sales | F25: EBIT Margin | G25: FCFF | H25: =+IF(Summary!$G$25="FCFF",DCF!AB6,IF(Summary!$G$25="FCFE",DCF!AC6,DCF!AD6)) -> NOPAT | I25: Net Capex | K25: Profitability Ratios | N25: 2022 | O25: =+N25+1 -> 2023 | P25: =+O25+1 -> 2024 | Q25: =+P25+1 -> 2025 | R25: =+Q25+1 -> 2026 | U25: (+351) 999 999 999
D26: 2022 | E26: =+DCF!E30 -> 0 | F26: =+DCF!E60 | G26: =+INDEX(DCF!X7:AA7,MATCH(Summary!$G$25,{"FCFF","FCFE","Tax Shield","Total Payout"},0)) | H26: =+IF(Summary!$G$25="FCFF",DCF!AB7,IF(Summary!$G$25="FCFE",DCF!AC7,DCF!AD7)) | I26: =+DCF!E134 -> 0 | K26: Return on Assets | N26: =IFERROR(_xlfn.XLOOKUP($K26,Multiples!$B:$B,Multiples!N:N),"") | O26: =IFERROR(_xlfn.XLOOKUP($K26,Multiples!$B:$B,Multiples!O:O),"") | P26: =IFERROR(_xlfn.XLOOKUP($K26,Multiples!$B:$B,Multiples!P:P),"") | Q26: =IFERROR(_xlfn.XLOOKUP($K26,Multiples!$B:$B,Multiples!Q:Q),"") | R26: =IFERROR(_xlfn.XLOOKUP($K26,Multiples!$B:$B,Multiples!R:R),"") | U26: Analyst 3
D27: =+D26+1 -> 2023 | E27: =+DCF!F30 -> 0 | F27: =+DCF!F60 | G27: =+INDEX(DCF!X8:AA8,MATCH(Summary!$G$25,{"FCFF","FCFE","Tax Shield","Total Payout"},0)) | H27: =+IF(Summary!$G$25="FCFF",DCF!AB8,IF(Summary!$G$25="FCFE",DCF!AC8,DCF!AD8)) | I27: =+DCF!F134 -> 0 | K27: Return on Equity | N27: =IFERROR(_xlfn.XLOOKUP($K27,Multiples!$B:$B,Multiples!N:N),"") | O27: =IFERROR(_xlfn.XLOOKUP($K27,Multiples!$B:$B,Multiples!O:O),"") | P27: =IFERROR(_xlfn.XLOOKUP($K27,Multiples!$B:$B,Multiples!P:P),"") | Q27: =IFERROR(_xlfn.XLOOKUP($K27,Multiples!$B:$B,Multiples!Q:Q),"") | R27: =IFERROR(_xlfn.XLOOKUP($K27,Multiples!$B:$B,Multiples!R:R),"") | U27: email
D28: =+D27+1 -> 2024 | E28: =+DCF!G30 -> 0 | F28: =+DCF!G60 | G28: =+INDEX(DCF!X9:AA9,MATCH(Summary!$G$25,{"FCFF","FCFE","Tax Shield","Total Payout"},0)) | H28: =+IF(Summary!$G$25="FCFF",DCF!AB9,IF(Summary!$G$25="FCFE",DCF!AC9,DCF!AD9)) | I28: =+DCF!G134 -> 0 | K28: Return on Total Capital | N28: =IFERROR(_xlfn.XLOOKUP($K28,Multiples!$B:$B,Multiples!N:N),"") | O28: =IFERROR(_xlfn.XLOOKUP($K28,Multiples!$B:$B,Multiples!O:O),"") | P28: =IFERROR(_xlfn.XLOOKUP($K28,Multiples!$B:$B,Multiples!P:P),"") | Q28: =IFERROR(_xlfn.XLOOKUP($K28,Multiples!$B:$B,Multiples!Q:Q),"") | R28: =IFERROR(_xlfn.XLOOKUP($K28,Multiples!$B:$B,Multiples!R:R),"") | U28: (+351) 999 999 999
D29: =+D28+1 -> 2025 | E29: =+DCF!H30 -> 0 | F29: =+DCF!H60 | G29: =+INDEX(DCF!X10:AA10,MATCH(Summary!$G$25,{"FCFF","FCFE","Tax Shield","Total Payout"},0)) | H29: =+IF(Summary!$G$25="FCFF",DCF!AB10,IF(Summary!$G$25="FCFE",DCF!AC10,DCF!AD10)) | I29: =+DCF!H134 | K29: EBITDA Margin | N29: =IFERROR(_xlfn.XLOOKUP($K29,Multiples!$B:$B,Multiples!N:N),"") | O29: =IFERROR(_xlfn.XLOOKUP($K29,Multiples!$B:$B,Multiples!O:O),"") | P29: =IFERROR(_xlfn.XLOOKUP($K29,Multiples!$B:$B,Multiples!P:P),"") | Q29: =IFERROR(_xlfn.XLOOKUP($K29,Multiples!$B:$B,Multiples!Q:Q),"") | R29: =IFERROR(_xlfn.XLOOKUP($K29,Multiples!$B:$B,Multiples!R:R),"")
D30: =+D29+1 -> 2026 | E30: =+DCF!I30 -> 0 | F30: =+DCF!I60 | G30: =+INDEX(DCF!X11:AA11,MATCH(Summary!$G$25,{"FCFF","FCFE","Tax Shield","Total Payout"},0)) | H30: =+IF(Summary!$G$25="FCFF",DCF!AB11,IF(Summary!$G$25="FCFE",DCF!AC11,DCF!AD11)) | I30: =+DCF!I134 | K30: EBIT Margin | N30: =IFERROR(_xlfn.XLOOKUP($K30,Multiples!$B:$B,Multiples!N:N),"") | O30: =IFERROR(_xlfn.XLOOKUP($K30,Multiples!$B:$B,Multiples!O:O),"") | P30: =IFERROR(_xlfn.XLOOKUP($K30,Multiples!$B:$B,Multiples!P:P),"") | Q30: =IFERROR(_xlfn.XLOOKUP($K30,Multiples!$B:$B,Multiples!Q:Q),"") | R30: =IFERROR(_xlfn.XLOOKUP($K30,Multiples!$B:$B,Multiples!R:R),"") | U30: Statistics
D31: =+D30+1 -> 2027 | E31: =+DCF!J30 -> 0 | F31: =+DCF!J60 | G31: =+INDEX(DCF!X12:AA12,MATCH(Summary!$G$25,{"FCFF","FCFE","Tax Shield","Total Payout"},0)) | H31: =+IF(Summary!$G$25="FCFF",DCF!AB12,IF(Summary!$G$25="FCFE",DCF!AC12,DCF!AD12)) | I31: =+DCF!J134 | K31: Gross Profit Margin | N31: =IFERROR(_xlfn.XLOOKUP($K31,Multiples!$B:$B,Multiples!N:N),"") | O31: =IFERROR(_xlfn.XLOOKUP($K31,Multiples!$B:$B,Multiples!O:O),"") | P31: =IFERROR(_xlfn.XLOOKUP($K31,Multiples!$B:$B,Multiples!P:P),"") | Q31: =IFERROR(_xlfn.XLOOKUP($K31,Multiples!$B:$B,Multiples!Q:Q),"") | R31: =IFERROR(_xlfn.XLOOKUP($K31,Multiples!$B:$B,Multiples!R:R),"") | U31: Beta | V31: =Peers!D74 -> 1.898
D32: =+D31+1 -> 2028 | E32: =+DCF!K30 -> 0 | F32: =+DCF!K60 | G32: =+INDEX(DCF!X13:AA13,MATCH(Summary!$G$25,{"FCFF","FCFE","Tax Shield","Total Payout"},0)) | H32: =+IF(Summary!$G$25="FCFF",DCF!AB13,IF(Summary!$G$25="FCFE",DCF!AC13,DCF!AD13)) | I32: =+DCF!K134 | K32: SG&A Margin | N32: =IFERROR(_xlfn.XLOOKUP($K32,Multiples!$B:$B,Multiples!N:N),"") | O32: =IFERROR(_xlfn.XLOOKUP($K32,Multiples!$B:$B,Multiples!O:O),"") | P32: =IFERROR(_xlfn.XLOOKUP($K32,Multiples!$B:$B,Multiples!P:P),"") | Q32: =IFERROR(_xlfn.XLOOKUP($K32,Multiples!$B:$B,Multiples!Q:Q),"") | R32: =IFERROR(_xlfn.XLOOKUP($K32,Multiples!$B:$B,Multiples!R:R),"") | U32: % Float | V32: =+Peers!D73 -> 0
D33: =+D32+1 -> 2029 | E33: =+DCF!L30 -> 0 | F33: =+DCF!L60 | G33: =+INDEX(DCF!X14:AA14,MATCH(Summary!$G$25,{"FCFF","FCFE","Tax Shield","Total Payout"},0)) | H33: =+IF(Summary!$G$25="FCFF",DCF!AB14,IF(Summary!$G$25="FCFE",DCF!AC14,DCF!AD14)) | I33: =+DCF!L134 | K33: Net Income Margin | N33: =IFERROR(_xlfn.XLOOKUP($K33,Multiples!$B:$B,Multiples!N:N),"") | O33: =IFERROR(_xlfn.XLOOKUP($K33,Multiples!$B:$B,Multiples!O:O),"") | P33: =IFERROR(_xlfn.XLOOKUP($K33,Multiples!$B:$B,Multiples!P:P),"") | Q33: =IFERROR(_xlfn.XLOOKUP($K33,Multiples!$B:$B,Multiples!Q:Q),"") | R33: =IFERROR(_xlfn.XLOOKUP($K33,Multiples!$B:$B,Multiples!R:R),"") | U33: % Held by Insiders | V33: =+Peers!D76 -> 0
U34: % Held by Institutions | V34: =+Peers!D77 -> 0
D35: SWOT Analysis | K35: Liquidity Ratios | N35: 2022 | O35: =+N35+1 -> 2023 | P35: =+O35+1 -> 2024 | Q35: =+P35+1 -> 2025 | R35: =+Q35+1 -> 2026 | U35: Short % of Float | V35: =+Peers!D78 -> 0
D36: Strengths | G36: Weaknesses | K36: Cash Ratio | N36: =IFERROR(_xlfn.XLOOKUP($K36,Multiples!$B:$B,Multiples!N:N),"") | O36: =IFERROR(_xlfn.XLOOKUP($K36,Multiples!$B:$B,Multiples!O:O),"") | P36: =IFERROR(_xlfn.XLOOKUP($K36,Multiples!$B:$B,Multiples!P:P),"") | Q36: =IFERROR(_xlfn.XLOOKUP($K36,Multiples!$B:$B,Multiples!Q:Q),"") | R36: =IFERROR(_xlfn.XLOOKUP($K36,Multiples!$B:$B,Multiples!R:R),"") | W36: 120.87
K37: Quick Ratio | N37: =IFERROR(_xlfn.XLOOKUP($K37,Multiples!$B:$B,Multiples!N:N),"") | O37: =IFERROR(_xlfn.XLOOKUP($K37,Multiples!$B:$B,Multiples!O:O),"") | P37: =IFERROR(_xlfn.XLOOKUP($K37,Multiples!$B:$B,Multiples!P:P),"") | Q37: =IFERROR(_xlfn.XLOOKUP($K37,Multiples!$B:$B,Multiples!Q:Q),"") | R37: =IFERROR(_xlfn.XLOOKUP($K37,Multiples!$B:$B,Multiples!R:R),"") | U37: Major Holders | W37: 113.63
K38: Current Ratio | N38: =IFERROR(_xlfn.XLOOKUP($K38,Multiples!$B:$B,Multiples!N:N),"") | O38: =IFERROR(_xlfn.XLOOKUP($K38,Multiples!$B:$B,Multiples!O:O),"") | P38: =IFERROR(_xlfn.XLOOKUP($K38,Multiples!$B:$B,Multiples!P:P),"") | Q38: =IFERROR(_xlfn.XLOOKUP($K38,Multiples!$B:$B,Multiples!Q:Q),"") | R38: =IFERROR(_xlfn.XLOOKUP($K38,Multiples!$B:$B,Multiples!R:R),"")
D40: Opportunities | G40: Threats | K40: Cash Flow Ratios | N40: 2022 | O40: =+N40+1 -> 2023 | P40: =+O40+1 -> 2024 | Q40: =+P40+1 -> 2025 | R40: =+Q40+1 -> 2026
K41: Cash Conversion Cycle | N41: =IFERROR(_xlfn.XLOOKUP($K41,Multiples!$B:$B,Multiples!N:N),"") | O41: =IFERROR(_xlfn.XLOOKUP($K41,Multiples!$B:$B,Multiples!O:O),"") | P41: =IFERROR(_xlfn.XLOOKUP($K41,Multiples!$B:$B,Multiples!P:P),"") | Q41: =IFERROR(_xlfn.XLOOKUP($K41,Multiples!$B:$B,Multiples!Q:Q),"") | R41: =IFERROR(_xlfn.XLOOKUP($K41,Multiples!$B:$B,Multiples!R:R),"")
K42: Net Income / Op Cash Flow | N42: =IFERROR(_xlfn.XLOOKUP($K42,Multiples!$B:$B,Multiples!N:N),"") | O42: =IFERROR(_xlfn.XLOOKUP($K42,Multiples!$B:$B,Multiples!O:O),"") | P42: =IFERROR(_xlfn.XLOOKUP($K42,Multiples!$B:$B,Multiples!P:P),"") | Q42: =IFERROR(_xlfn.XLOOKUP($K42,Multiples!$B:$B,Multiples!Q:Q),"") | R42: =IFERROR(_xlfn.XLOOKUP($K42,Multiples!$B:$B,Multiples!R:R),"")
K43: Chg in Cash / Op Cash Flow | N43: =IFERROR(_xlfn.XLOOKUP($K43,Multiples!$B:$B,Multiples!N:N),"") | O43: =IFERROR(_xlfn.XLOOKUP($K43,Multiples!$B:$B,Multiples!O:O),"") | P43: =IFERROR(_xlfn.XLOOKUP($K43,Multiples!$B:$B,Multiples!P:P),"") | Q43: =IFERROR(_xlfn.XLOOKUP($K43,Multiples!$B:$B,Multiples!Q:Q),"") | R43: =IFERROR(_xlfn.XLOOKUP($K43,Multiples!$B:$B,Multiples!R:R),"")
D45: Revenue by Region | G45: Revenue by Segment | K45: Leverage Ratios | N45: 2022 | O45: =+N45+1 -> 2023 | P45: =+O45+1 -> 2024 | Q45: =+P45+1 -> 2025 | R45: =+Q45+1 -> 2026
K46: Total Debt / Equity | N46: =IFERROR(_xlfn.XLOOKUP($K46,Multiples!$B:$B,Multiples!N:N),"") | O46: =IFERROR(_xlfn.XLOOKUP($K46,Multiples!$B:$B,Multiples!O:O),"") | P46: =IFERROR(_xlfn.XLOOKUP($K46,Multiples!$B:$B,Multiples!P:P),"") | Q46: =IFERROR(_xlfn.XLOOKUP($K46,Multiples!$B:$B,Multiples!Q:Q),"") | R46: =IFERROR(_xlfn.XLOOKUP($K46,Multiples!$B:$B,Multiples!R:R),"")
K47: Total Debt / Capital | N47: =IFERROR(_xlfn.XLOOKUP($K47,Multiples!$B:$B,Multiples!N:N),"") | O47: =IFERROR(_xlfn.XLOOKUP($K47,Multiples!$B:$B,Multiples!O:O),"") | P47: =IFERROR(_xlfn.XLOOKUP($K47,Multiples!$B:$B,Multiples!P:P),"") | Q47: =IFERROR(_xlfn.XLOOKUP($K47,Multiples!$B:$B,Multiples!Q:Q),"") | R47: =IFERROR(_xlfn.XLOOKUP($K47,Multiples!$B:$B,Multiples!R:R),"")
K48: Total Liabilities / Total Assets | N48: =IFERROR(_xlfn.XLOOKUP($K48,Multiples!$B:$B,Multiples!N:N),"") | O48: =IFERROR(_xlfn.XLOOKUP($K48,Multiples!$B:$B,Multiples!O:O),"") | P48: =IFERROR(_xlfn.XLOOKUP($K48,Multiples!$B:$B,Multiples!P:P),"") | Q48: =IFERROR(_xlfn.XLOOKUP($K48,Multiples!$B:$B,Multiples!Q:Q),"") | R48: =IFERROR(_xlfn.XLOOKUP($K48,Multiples!$B:$B,Multiples!R:R),"")
K49: Total Debt / EBITDA | N49: =IFERROR(_xlfn.XLOOKUP($K49,Multiples!$B:$B,Multiples!N:N),"") | O49: =IFERROR(_xlfn.XLOOKUP($K49,Multiples!$B:$B,Multiples!O:O),"") | P49: =IFERROR(_xlfn.XLOOKUP($K49,Multiples!$B:$B,Multiples!P:P),"") | Q49: =IFERROR(_xlfn.XLOOKUP($K49,Multiples!$B:$B,Multiples!Q:Q),"") | R49: =IFERROR(_xlfn.XLOOKUP($K49,Multiples!$B:$B,Multiples!R:R),"") | U49: Board of Directors
K50: Total Debt / (EBITDA - Capex) | N50: =IFERROR(_xlfn.XLOOKUP($K50,Multiples!$B:$B,Multiples!N:N),"") | O50: =IFERROR(_xlfn.XLOOKUP($K50,Multiples!$B:$B,Multiples!O:O),"") | P50: =IFERROR(_xlfn.XLOOKUP($K50,Multiples!$B:$B,Multiples!P:P),"") | Q50: =IFERROR(_xlfn.XLOOKUP($K50,Multiples!$B:$B,Multiples!Q:Q),"") | R50: =IFERROR(_xlfn.XLOOKUP($K50,Multiples!$B:$B,Multiples!R:R),"")
K51: Net Debt / EBITDA | N51: =IFERROR(_xlfn.XLOOKUP($K50,Multiples!$B:$B,Multiples!N:N),"") | O51: =IFERROR(_xlfn.XLOOKUP($K50,Multiples!$B:$B,Multiples!O:O),"") | P51: =IFERROR(_xlfn.XLOOKUP($K50,Multiples!$B:$B,Multiples!P:P),"") | Q51: =IFERROR(_xlfn.XLOOKUP($K50,Multiples!$B:$B,Multiples!Q:Q),"") | R51: =IFERROR(_xlfn.XLOOKUP($K50,Multiples!$B:$B,Multiples!R:R),"")
K53: Solvency Ratios | N53: 2022 | O53: =+N53+1 -> 2023 | P53: =+O53+1 -> 2024 | Q53: =+P53+1 -> 2025 | R53: =+Q53+1 -> 2026
K54: EBIT / Interest Expense | N54: =IFERROR(_xlfn.XLOOKUP($K54,Multiples!$B:$B,Multiples!N:N),"") -> N/A | O54: =IFERROR(_xlfn.XLOOKUP($K54,Multiples!$B:$B,Multiples!O:O),"") -> N/A | P54: =IFERROR(_xlfn.XLOOKUP($K54,Multiples!$B:$B,Multiples!P:P),"") -> N/A | Q54: =IFERROR(_xlfn.XLOOKUP($K54,Multiples!$B:$B,Multiples!Q:Q),"") -> N/A | R54: =IFERROR(_xlfn.XLOOKUP($K54,Multiples!$B:$B,Multiples!R:R),"") -> N/A
K55: EBITDA / Interest Expense | N55: =IFERROR(_xlfn.XLOOKUP($K55,Multiples!$B:$B,Multiples!N:N),"") -> N/A | O55: =IFERROR(_xlfn.XLOOKUP($K55,Multiples!$B:$B,Multiples!O:O),"") -> N/A | P55: =IFERROR(_xlfn.XLOOKUP($K55,Multiples!$B:$B,Multiples!P:P),"") -> N/A | Q55: =IFERROR(_xlfn.XLOOKUP($K55,Multiples!$B:$B,Multiples!Q:Q),"") -> N/A | R55: =IFERROR(_xlfn.XLOOKUP($K55,Multiples!$B:$B,Multiples!R:R),"") -> N/A
K56: (EBITDA - Capex) / Interest Expense | N56: =IFERROR(_xlfn.XLOOKUP($K56,Multiples!$B:$B,Multiples!N:N),"") -> N/A | O56: =IFERROR(_xlfn.XLOOKUP($K56,Multiples!$B:$B,Multiples!O:O),"") -> N/A | P56: =IFERROR(_xlfn.XLOOKUP($K56,Multiples!$B:$B,Multiples!P:P),"") -> N/A | Q56: =IFERROR(_xlfn.XLOOKUP($K56,Multiples!$B:$B,Multiples!Q:Q),"") -> N/A | R56: =IFERROR(_xlfn.XLOOKUP($K56,Multiples!$B:$B,Multiples!R:R),"") -> N/A
D58: Debt Schedule | K58: Stock Performance
U60: ESG Traffic Light
U61: LSEG ESG Score | V61: =ESG!C14 -> 0
U62: E-Score | V62: =ESG!C15 -> 0
U63: S-Score | V63: =ESG!C16 -> 0
U64: G-Score | V64: =ESG!C17 -> 0
U65: S&P Global ESG Score | V65: =ESG!C18 -> 0
U66: Environmental | V66: =ESG!C19 -> 0
U67: Social | V67: =ESG!C20 -> 0
U68: Governance & Economic | V68: =ESG!C21 -> 0
U69: Sustainalytics | V69: =ESG!C22 -> 0
U70: ISS ESG Corporate Rating | V70: =ESG!C23 -> 0
U71: SDG Impact Rating | V71: =ESG!C24 -> 0
U72: Governance Quality Score | V72: =ESG!C25 -> 0
U73: MSCI ESG Ratings | V73: =ESG!C26 -> 0
U75: Disclaimer: This material has been prepared solely for educational and informational purposes, based on information available to the general public and from sources considered reliable. This research is part of the activities of the Lisbon Investment Society (LIS). It does not constitute, and should not be interpreted as, investment advice, financial advice, or a recommendation to buy or sell any financial instruments. The views expressed are those of the authors and do not necessarily reflect the official position of LIS. The authors assume no responsibility for the accuracy of the information provided, neither should anything contained herein be taken as an indication that any result will be achieved. Investors should conduct their own research and consult with qualified financial advisors before making any investment decisions.
D80: Extra Notes

Sheet Segments
B2: Segments
B4: Regions | D4: Weight | E4: 2020 | F4: =+E4+1 -> 2021 | G4: =+F4+1 -> 2022 | H4: =+G4+1 -> 2023 | I4: =+H4+1 -> 2024 | J4: ="CAGR "&$G$4&" - "&$I$4 -> CAGR 2022 - 2024 | K4: 2021 | L4: =+K4+1 -> 2022 | M4: =+L4+1 -> 2023 | N4: =+M4+1 -> 2024
D6: =IFERROR(I6/SUM($I$6:$I$12),"") | J6: =IFERROR((I6/G6)^(1/COUNT($G$4:$I$4))-1,"") | K6: =IFERROR(F6-E6/E6,"") | L6: =IFERROR(G6-F6/F6,"") | M6: =IFERROR((H6-G6)/G6,"") | N6: =IFERROR((I6-H6)/H6,"")
D7: =IFERROR(I7/SUM($I$6:$I$12),"") | J7: =IFERROR((I7/G7)^(1/COUNT($G$4:$I$4))-1,"") | K7: =IFERROR(F7-E7/E7,"") | L7: =IFERROR(G7-F7/F7,"") | M7: =IFERROR((H7-G7)/G7,"") | N7: =IFERROR((I7-H7)/H7,"")
D8: =IFERROR(I8/SUM($I$6:$I$12),"") | J8: =IFERROR((I8/E8)^(1/COUNT($E$4:$I$4))-1,"") | K8: =IFERROR(F8-E8/E8,"") | L8: =IFERROR(G8-F8/F8,"") | M8: =IFERROR(H8-G8/G8,"") | N8: =IFERROR((I8-H8)/H8,"")
D9: =IFERROR(I9/SUM($I$6:$I$12),"") | J9: =IFERROR((I9/E9)^(1/COUNT($E$4:$I$4))-1,"") | K9: =IFERROR(F9-E9/E9,"") | L9: =IFERROR(G9-F9/F9,"") | M9: =IFERROR(H9-G9/G9,"") | N9: =IFERROR((I9-H9)/H9,"")
D10: =IFERROR(I10/SUM($I$6:$I$12),"") | J10: =IFERROR((I10/E10)^(1/COUNT($E$4:$I$4))-1,"") | K10: =IFERROR(F10-E10/E10,"") | L10: =IFERROR(G10-F10/F10,"") | M10: =IFERROR(H10-G10/G10,"") | N10: =IFERROR((I10-H10)/H10,"")
D11: =IFERROR(I11/SUM($I$6:$I$12),"")
D12: =IFERROR(I12/SUM($I$6:$I$12),"")
B13: Total | D13: =SUM(D6:D12) -> 0 | E13: =SUM(E6:E10) -> 0 | F13: =SUM(F6:F10) -> 0 | G13: =SUM(G6:G10) -> 0 | H13: =SUM(H6:H10) -> 0 | I13: =SUM(I6:I10) -> 0 | J13: =IFERROR((I13/G13)^(1/COUNT($G$4:$I$4))-1,"") | K13: =IFERROR(F13-E13/E13,"") | L13: =IFERROR(G13-F13/F13,"") | M13: =IFERROR((H13-G13)/G13,"") | N13: =IFERROR((I13-H13)/H13,"")
B15: Segments | D15: Weight | E15: 2020 | F15: =+E15+1 -> 2021 | G15: =+F15+1 -> 2022 | H15: =+G15+1 -> 2023 | I15: =+H15+1 -> 2024 | J15: ="CAGR "&$E$4&" - "&$I$4 -> CAGR 2020 - 2024 | K15: 2021 | L15: =+K15+1 -> 2022 | M15: =+L15+1 -> 2023 | N15: =+M15+1 -> 2024
D17: =IFERROR(I17/SUM($I$17:$I$21),"") | J17: =IFERROR((I17/E17)^(1/COUNT($E$4:$I$4))-1,"") | K17: =IFERROR((F17-E17)/E17,"") | L17: =IFERROR((G17-F17)/F17,"") | M17: =IFERROR((H17-G17)/G17,"") | N17: =IFERROR((I17-H17)/H17,"")
D18: =IFERROR(I18/SUM($I$17:$I$21),"") | J18: =IFERROR((I18/E18)^(1/COUNT($E$4:$I$4))-1,"") | K18: =IFERROR((F18-E18)/E18,"") | L18: =IFERROR((G18-F18)/F18,"") | M18: =IFERROR((H18-G18)/G18,"") | N18: =IFERROR((I18-H18)/H18,"")
D19: =IFERROR(I19/SUM($I$17:$I$21),"") | J19: =IFERROR((I19/E19)^(1/COUNT($E$4:$I$4))-1,"") | K19: =IFERROR((F19-E19)/E19,"") | L19: =IFERROR((G19-F19)/F19,"") | M19: =IFERROR((H19-G19)/G19,"") | N19: =IFERROR((I19-H19)/H19,"")
D20: =IFERROR(I20/SUM($I$17:$I$21),"") | J20: =IFERROR((I20/E20)^(1/COUNT($E$4:$I$4))-1,"") | K20: =IFERROR((F20-E20)/E20,"") | L20: =IFERROR((G20-F20)/F20,"") | M20: =IFERROR((H20-G20)/G20,"") | N20: =IFERROR((I20-H20)/H20,"")
D21: =IFERROR(I21/SUM($I$17:$I$21),"") | J21: =IFERROR((I21/E21)^(1/COUNT($E$4:$I$4))-1,"") | K21: =IFERROR((F21-E21)/E21,"") | L21: =IFERROR((G21-F21)/F21,"") | M21: =IFERROR((H21-G21)/G21,"") | N21: =IFERROR((I21-H21)/H21,"")
B22: Total | D22: =SUM(D17:D21) -> 0 | E22: =SUM(E17:E21) -> 0 | F22: =SUM(F17:F21) -> 0 | G22: =SUM(G17:G21) -> 0 | H22: =SUM(H17:H21) -> 0 | I22: =SUM(I17:I21) -> 0 | J22: =IFERROR((I22/E22)^(1/COUNT($E$4:$I$4))-1,"") | K22: =IFERROR((F22-E22)/E22,"") | L22: =IFERROR((G22-F22)/F22,"") | M22: =IFERROR((H22-G22)/G22,"") | N22: =IFERROR((I22-H22)/H22,"")
B24: Categories | D24: Description | J24: Graphs
B29: =IF(B20=0,"",B20)
B30: =IF(B21=0,"",B21)
B32: Products | D32: Weight | E32: 2020 | F32: =+E32+1 -> 2021 | G32: =+F32+1 -> 2022 | H32: =+G32+1 -> 2023 | I32: =+H32+1 -> 2024 | J32: =I32+1 -> 2025 | K32: =+J32+1 -> 2026 | L32: =+K32+1 -> 2027 | M32: =+L32+1 -> 2028 | N32: =+M32+1 -> 2029 | O32: =+N32+1 -> 2030 | P32: =+O32+1 -> 2031 | Q32: =+P32+1 -> 2032 | R32: =+Q32+1 -> 2033 | ... T32: =+S32+1 -> 2035
D34: =IFERROR(I34/$I$13,"")
D36: =IFERROR(I36/$I$13,"")
F37: =IFERROR((F36-E36)/E36,"") | G37: =IFERROR((G36-F36)/F36,"") | H37: =IFERROR((H36-G36)/G36,"") | I37: =IFERROR((I36-H36)/H36,"")
B38: Product 3 | D38: =IFERROR(I38/$I$13,"") | J38: =I38*(1+J39) -> 0 | K38: =J38*(1+K39) -> 0 | L38: =K38*(1+L39) -> 0 | M38: =L38*(1+M39) -> 0 | N38: =M38*(1+N39) -> 0 | O38: =N38*(1+O39) -> 0 | P38: =O38*(1+P39) -> 0 | Q38: =P38*(1+Q39) -> 0 | ... T38: =S38*(1+T39) -> 0
F39: =IFERROR(F38-E38/E38,"") | G39: =IFERROR(G38-F38/F38,"") | H39: =IFERROR(H38-G38/G38,"") | I39: =IFERROR(I38-H38/H38,"")
B40: Product 4 | D40: =IFERROR(I40/$I$13,"") | J40: =I40*(1+J41) -> 0 | K40: =J40*(1+K41) -> 0 | L40: =K40*(1+L41) -> 0 | M40: =L40*(1+M41) -> 0 | N40: =M40*(1+N41) -> 0 | O40: =N40*(1+O41) -> 0 | P40: =O40*(1+P41) -> 0 | Q40: =P40*(1+Q41) -> 0 | ... T40: =S40*(1+T41) -> 0
F41: =IFERROR(F40-E40/E40,"") | G41: =IFERROR(G40-F40/F40,"") | H41: =IFERROR(H40-G40/G40,"") | I41: =IFERROR(I40-H40/H40,"")
B42: Product 5 | D42: =IFERROR(I42/$I$13,"") | J42: =I42*(1+J43) -> 0 | K42: =J42*(1+K43) -> 0 | L42: =K42*(1+L43) -> 0 | M42: =L42*(1+M43) -> 0 | N42: =M42*(1+N43) -> 0 | O42: =N42*(1+O43) -> 0 | P42: =O42*(1+P43) -> 0 | Q42: =P42*(1+Q43) -> 0 | ... T42: =S42*(1+T43) -> 0
F43: =IFERROR(F42-E42/E42,"") | G43: =IFERROR(G42-F42/F42,"") | H43: =IFERROR(H42-G42/G42,"") | I43: =IFERROR(I42-H42/H42,"")
B44: Total | D44: =SUM(D34:D42) -> 0 | E44: =SUM(E34:E42) -> 0 | F44: =SUM(F34:F42) -> 0 | G44: =SUM(G34:G42) -> 0 | H44: =SUM(H34:H42) -> 0 | I44: =SUM(I34:I42) -> 0 | J44: =SUM(J34:J42) -> 0 | K44: =SUM(K34:K42) -> 0 | ... T44: =SUM(T34:T42) -> 0
B46: Company's Strategy / Extra Notes

Sheet Industry
B2: Industry Overview
B4: Sales Growth Forecast | E4: Weight | F4: 2025 | G4: =+F4+1 -> 2026 | H4: =+G4+1 -> 2027 | I4: =+H4+1 -> 2028 | J4: =+I4+1 -> 2029 | K4: =+J4+1 -> 2030 | L4: =+K4+1 -> 2031 | M4: =+L4+1 -> 2032 | N4: =+M4+1 -> 2033 | ... P4: =+O4+1 -> 2035 | Q4: ="CAGR "&$F$4&" - "&$P$4 -> CAGR 2025 - 2035 | R4: Sources
B11: Weighted Average | E11: =SUM(E6:E10) -> 0 | F11: =SUMPRODUCT(F6:F10,$E$6:$E$10) -> 0 | G11: =SUMPRODUCT(G6:G10,$E$6:$E$10) -> 0 | H11: =SUMPRODUCT(H6:H10,$E$6:$E$10) -> 0 | I11: =SUMPRODUCT(I6:I10,$E$6:$E$10) -> 0 | J11: =SUMPRODUCT(J6:J10,$E$6:$E$10) -> 0 | K11: =SUMPRODUCT(K6:K10,$E$6:$E$10) -> 0 | L11: =SUMPRODUCT(L6:L10,$E$6:$E$10) -> 0 | M11: =SUMPRODUCT(M6:M10,$E$6:$E$10) -> 0 | ... P11: =SUMPRODUCT(P6:P10,$E$6:$E$10) -> 0 | Q11: =IFERROR(((1+F11)*(1+G11)*(1+H11)*(1+I11)*(1+J11)*(1+K11)*(1+L11)*(1+M11)*(1+N11)*(1+O11)*(1+P11))^(1/COUNT($F$4:$P$4))-1,"") -> 0
B13: Key Drivers | E13: Description
B20: Industry Trends | E20: Description
B26: Market Share | E26: Headquarters | G26: Revenues | H26: (in MM of USD) | I26: Market Share
B28: {=+_FV(DCF!R4,"Name")} -> ADVANCED MICRO DEVICES, INC. | G28: {=TRANSPOSE(Peers!D97:N97)} -> 0 | I28: =IFERROR(G28/$G$40,"")
B29: {=+_FV(Peers!A8,"Name")} -> #VALUE! | G29: 0 | I29: =IFERROR(G29/$G$40,"")
B30: {=+_FV(Peers!A9,"Name")} -> #VALUE! | G30: 0 | I30: =IFERROR(G30/$G$40,"")
B31: {=+_FV(Peers!A10,"Name")} -> #VALUE! | G31: 0 | I31: =IFERROR(G31/$G$40,"")
B32: {=+_FV(Peers!A11,"Name")} -> #VALUE! | G32: 0 | I32: =IFERROR(G32/$G$40,"")
B33: {=+_FV(Peers!A12,"Name")} -> #VALUE! | G33: 0 | I33: =IFERROR(G33/$G$40,"")
B34: {=+_FV(Peers!A13,"Name")} -> #VALUE! | G34: 0 | I34: =IFERROR(G34/$G$40,"")
B35: {=+_FV(Peers!A14,"Name")} -> #VALUE! | G35: 0 | I35: =IFERROR(G35/$G$40,"")
B36: {=+_FV(Peers!A15,"Name")} -> #VALUE! | G36: 0 | I36: =IFERROR(G36/$G$40,"")
B37: {=+_FV(Peers!A16,"Name")} -> #VALUE! | G37: 0 | I37: =IFERROR(G37/$G$40,"")
B38: {=+_FV(Peers!A17,"Name")} -> #VALUE! | G38: 0 | I38: =IFERROR(G38/$G$40,"")
B39: Others | E39: -- | G39: =G40-SUM(G28:G38) -> 0 | I39: =IFERROR(G39/$G$40,"")
B40: Industry Size | E40: -- | I40: 1
B42: Porter's Five Forces Analysis | E42: Rating | H42: Graph
B44: Threat of New Entrants | E44: =IFERROR(AVERAGE(E45:E50),"")
B45: Economies of scale
B46: Product differentiation
B47: Capital requirements
B48: Access to distribution channels
B49: Regulations
B50: Switching costs
B51: Bargaining Power of Suppliers | E51: =IFERROR(AVERAGE(E52:E56),"")
B52: Number of suppliers
B53: Uniqueness
B54: Switching Costs
B55: Forward Integration
B56: Industry Importance
B57: Bargaining Power of Customers | E57: =IFERROR(AVERAGE(E58:E62),"")
B58: Number of buyers
B59: Purchase size
B60: Switching costs
B61: Price sensitivity
B62: Informed buyers
B63: Competitive Rivalry | E63: =IFERROR(AVERAGE(E64:E68),"")
B64: Number of competitors
B65: Industry growth
B66: Similarities in what's offered
B67: Exit barriers
B68: Fixed costs
B69: Threat of Substitutes | E69: =IFERROR(AVERAGE(E70:E74),"")
B70: Relative price performance
B71: Customer willingness to go elsewhere
B72: The sense that products are similar
B73: Availability of close substitutes

Sheet Peers
D3: Revenue Growth | F3: EBITDA Margin | H3: Profit Margin | J3: EV / Revenue | L3: EV / EBITDA | N3: Price / Earnings
B4: Peers | C4: Ticker | D4: =+Inputs!O4&"-"&Inputs!P4 -> 2022-2023 | E4: =+Inputs!P4&"-"&Inputs!Q4 -> 2023-2024 | F4: 2023 | G4: 2024 | H4: =+Inputs!O4&"-"&Inputs!P4 -> 2022-2023 | I4: =+Inputs!P4&"-"&Inputs!Q4 -> 2023-2024 | J4: 2023 | K4: 2024 | L4: 2023 | M4: 2024 | N4: 2023 | O4: 2024
A6: =+D91 -> #VALUE! | B6: {=IFERROR(_FV(A6,"Name"),"")} -> ADVANCED MICRO DEVICES, INC. | C6: {=IFERROR(_FV(A6,"Ticker symbol",TRUE),"")} -> AMD | D6: =IFERROR(D94/D93-1,"") | E6: =IFERROR(D97/D94-1,"") | F6: =IFERROR(D95/D94,"") | G6: =IFERROR(D100/D97,"") | H6: =IFERROR(D96/D94,"") | I6: =IFERROR(D105/D97,"") | J6: {=IFERROR((_FV(A6,"Market cap",TRUE)/1000000+D$121-D$111)/D$94,"")} | K6: {=IFERROR((_FV(A6,"Market cap",TRUE)/1000000+D$121-D$111)/D$97,"")} | L6: {=+IFERROR((_FV(A6,"Market cap",TRUE)/1000000+D$121-D$111)/D$95,"")} | M6: {=IFERROR((_FV(A6,"Market cap",TRUE)/1000000+D$121-D$111)/D$100,"")} | N6: {=IFERROR((_FV(A6,"Market cap",TRUE)/1000000)/D$96,"")} | O6: {=IFERROR((_FV(A6,"Market cap",TRUE)/1000000)/D$105,"")}
A8: =+E91 -> PEER 1 | B8: {=IFERROR(_FV(A8,"Name"),"")} | C8: {=+IFERROR(_FV(A8,"Ticker symbol",TRUE),"")} | D8: =+IFERROR(E94/E93-1,"") | E8: =IFERROR(E97/E94-1,"") | F8: =IFERROR(E95/E94,"") | G8: =+IFERROR(E100/E97,"") | H8: =IFERROR(E96/E94,"") | I8: =+IFERROR(D105/D99,"") | J8: {=+IFERROR((_FV(A8,"Market cap",TRUE)/1000000+E$121-E$111)/E$94,"")} | K8: {=IFERROR(+(_FV(A8,"Market cap",TRUE)/1000000+E$121-E$111)/E$97,"")} | L8: {=IFERROR(+(_FV(A8,"Market cap",TRUE)/1000000+E$121-E$111)/E$95,"")} | M8: {=IFERROR(+(_FV(A8,"Market cap",TRUE)/1000000+E$121-E$111)/E$100,"")} | N8: {=IFERROR(+(_FV(A8,"Market cap",TRUE)/1000000)/E$96,"")} | O8: {=IFERROR(+(_FV(A8,"Market cap",TRUE)/1000000)/E$105,"")}
A9: =+F91 -> PEER 2 | B9: {=IFERROR(_FV(A9,"Name"),"")} | C9: {=+IFERROR(_FV(A9,"Ticker symbol",TRUE),"")} | D9: =IFERROR(F94/F93-1,"") | E9: =IFERROR(+F97/F94-1,"") | F9: =IFERROR(F95/F94,"") | G9: =IFERROR(F100/F97,"") | H9: =IFERROR(F96/F94,"") | I9: =+IFERROR(F105/F97,"") | J9: {=IFERROR(+(_FV(A9,"Market cap",TRUE)/1000000+F$121-F$111)/F$94,"")} | K9: {=IFERROR(+(_FV(A9,"Market cap",TRUE)/1000000+F$121-F$111)/F$97,"")} | L9: {=IFERROR(+(_FV(A9,"Market cap",TRUE)/1000000+F$121-F$111)/F$95,"")} | M9: {=IFERROR(+(_FV(A9,"Market cap",TRUE)/1000000+F$121-F$111)/F$100,"")} | N9: {=IFERROR(+(_FV(A9,"Market cap",TRUE)/1000000)/F$96,"")} | O9: {=IFERROR(+(_FV(A9,"Market cap",TRUE)/1000000)/F$105,"")}
A10: =+G91 -> PEER 3 | B10: {=IFERROR(_FV(A10,"Name"),"")} | C10: {=IFERROR(_FV(A10,"Ticker symbol",TRUE),"")} | D10: =+IFERROR(G94/G93-1,"") | E10: =IFERROR(G97/G94-1,"") | F10: =IFERROR(G95/G94,"") | G10: =IFERROR(G100/G97,"") | H10: =IFERROR(G96/G94,"") | I10: =+IFERROR(G105/G97,"") | J10: {=IFERROR(+(_FV(A10,"Market cap",TRUE)/1000000+G$121-G$111)/G$94,"")} | K10: {=IFERROR(+(_FV(A10,"Market cap",TRUE)/1000000+G$121-G$111)/G$97,"")} | L10: {=IFERROR(+(_FV(A10,"Market cap",TRUE)/1000000+G$121-G$111)/G$95,"")} | M10: {=IFERROR(+(_FV(A10,"Market cap",TRUE)/1000000+G$121-G$111)/G$100,"")} | N10: {=IFERROR(+(_FV(A10,"Market cap",TRUE)/1000000)/G$96,"")} | O10: {=IFERROR(+(_FV(A10,"Market cap",TRUE)/1000000)/G$105,"")}
A11: =+H91 -> PEER 4 | B11: {=IFERROR(_FV(A11,"Name"),"")} | C11: {=IFERROR(_FV(A11,"Ticker symbol",TRUE),"")} | D11: =IFERROR(H94/H93-1,"") | E11: =IFERROR(H97/H94-1,"") | F11: =IFERROR(H95/H94,"") | G11: =IFERROR(H100/H97,"") | H11: =IFERROR(H96/H94,"") | I11: =+IFERROR(H105/H102,"") | J11: {=IFERROR((_FV(A11,"Market cap",TRUE)/1000000+H$121-H$111)/H$94,"")} | K11: {=IFERROR(+(_FV(A11,"Market cap",TRUE)/1000000+H$121-H$111)/H$97,"")} | L11: {=IFERROR(+(_FV(A11,"Market cap",TRUE)/1000000+H$121-H$111)/H$95,"")} | M11: {=IFERROR(+(_FV(A11,"Market cap",TRUE)/1000000+H$121-H$111)/H$100,"")} | N11: {=IFERROR(+(_FV(A11,"Market cap",TRUE)/1000000)/H$96,"")} | O11: {=IFERROR(+(_FV(A11,"Market cap",TRUE)/1000000)/H$105,"")}
A12: =+I91 -> PEER 5 | B12: {=IFERROR(_FV(A12,"Name"),"")} | C12: {=IFERROR(_FV(A12,"Ticker symbol",TRUE),"")} | D12: =+IFERROR(I94/I93-1,"") | E12: =IFERROR(I97/I94-1,"") | F12: =IFERROR(I95/I94,"") | G12: =IFERROR(I100/I97,"") | H12: =IFERROR(I96/I94,"") | I12: =+IFERROR(I105/I97,"") | J12: {=IFERROR((_FV(A12,"Market cap",TRUE)/1000000+I$121-I$111)/I$94,"")} | K12: {=IFERROR(+(_FV(A12,"Market cap",TRUE)/1000000+I$121-I$111)/I$97,"")} | L12: {=IFERROR(+(_FV(A12,"Market cap",TRUE)/1000000+I$121-I$111)/I$95,"")} | M12: {=IFERROR(+(_FV(A12,"Market cap",TRUE)/1000000+I$121-I$111)/I$100,"")} | N12: {=IFERROR(+(_FV(A12,"Market cap",TRUE)/1000000)/I$96,"")} | O12: {=IFERROR(+(_FV(A12,"Market cap",TRUE)/1000000)/I$105,"")}
A13: =+J91 -> PEER 6 | B13: {=IFERROR(_FV(A13,"Name"),"")} | C13: {=IFERROR(_FV(A13,"Ticker symbol",TRUE),"")} | D13: =IFERROR(J94/J93-1,"") | E13: =IFERROR(J97/J94-1,"") | F13: =IFERROR(J95/J94,"") | G13: =IFERROR(J100/J97,"") | H13: =IFERROR(J96/J94,"") | I13: =+IFERROR(J105/J97,"") | J13: {=IFERROR(+(_FV(A13,"Market cap",TRUE)/1000000+J$121-J$111)/J$94,"")} | K13: {=IFERROR(+(_FV(A13,"Market cap",TRUE)/1000000+J$121-J$111)/J$97,"")} | L13: {=IFERROR(+(_FV(A13,"Market cap",TRUE)/1000000+J$121-J$111)/J$95,"")} | M13: {=IFERROR(+(_FV(A13,"Market cap",TRUE)/1000000+J$121-J$111)/J$100,"")} | N13: {=IFERROR(+(_FV(A13,"Market cap",TRUE)/1000000)/J$96,"")} | O13: {=IFERROR(+(_FV(A13,"Market cap",TRUE)/1000000)/J$105,"")}
A14: =+K91 -> PEER 7 | B14: {=IFERROR(_FV(A14,"Name"),"")} | C14: {=IFERROR(_FV(A14,"Ticker symbol",TRUE),"")} | D14: =IFERROR(K94/K93-1,"") | E14: =IFERROR(K97/K94-1,"") | F14: =+IFERROR(K95/K94,"") | G14: =IFERROR(K100/K97,"") | H14: =IFERROR(K96/K94,"") | I14: =+IFERROR(K105/K97,"") | J14: {=IFERROR((_FV(A14,"Market cap",TRUE)/1000000+D$121-K$111)/K$94,"")} | K14: {=IFERROR(+(_FV(A14,"Market cap",TRUE)/1000000+D$121-K$111)/K$97,"")} | L14: {=IFERROR(+(_FV(A14,"Market cap",TRUE)/1000000+D$121-K$111)/K$95,"")} | M14: {=IFERROR(+(_FV(A14,"Market cap",TRUE)/1000000+D$121-K$111)/K$100,"")} | N14: {=IFERROR(+(_FV(A14,"Market cap",TRUE)/1000000)/K$96,"")} | O14: {=IFERROR(+(_FV(A14,"Market cap",TRUE)/1000000)/K$105,"")}
A15: =+L91 -> PEER 8 | B15: {=IFERROR(_FV(A15,"Name"),"")} | C15: {=IFERROR(_FV(A15,"Ticker symbol",TRUE),"")} | D15: =+IFERROR(L94/L93,"") | E15: =IFERROR(L97/L94,"") | F15: =IFERROR(L95/L94,"") | G15: =IFERROR(L100/L97,"") | H15: =IFERROR(L96/L94,"") | I15: =+IFERROR(L105/L97,"") | J15: {=IFERROR(+(_FV(A15,"Market cap",TRUE)/1000000+L$121-L$111)/L$94,"")} | K15: {=IFERROR(+(_FV(A15,"Market cap",TRUE)/1000000+L$121-L$111)/L$97,"")} | L15: {=IFERROR(+(_FV(A15,"Market cap",TRUE)/1000000+L$121-L$111)/L$95,"")} | M15: {=IFERROR(+(_FV(A15,"Market cap",TRUE)/1000000+L$121-L$111)/L$100,"")} | N15: {=IFERROR(+(_FV(A15,"Market cap",TRUE)/1000000)/L$96,"")} | O15: {=IFERROR(+(_FV(A15,"Market cap",TRUE)/1000000)/L$105,"")}
A16: =+M91 -> PEER 9 | B16: {=IFERROR(_FV(A16,"Name"),"")} | C16: {=IFERROR(_FV(A16,"Ticker symbol",TRUE),"")} | D16: =IFERROR(M94/M93-1,"") | E16: =IFERROR(M97/M94-1,"") | F16: =IFERROR(M95/M94,"") | G16: =IFERROR(M100/M97,"") | H16: =IFERROR(M96/M94,"") | I16: =+IFERROR(M105/M97,"") | J16: {=IFERROR(+(_FV(A16,"Market cap",TRUE)/1000000+M$121-M$111)/M$94,"")} | K16: {=IFERROR(+(_FV(A16,"Market cap",TRUE)/1000000+M$121-M$111)/M$97,"")} | L16: {=IFERROR(+(_FV(A16,"Market cap",TRUE)/1000000+M$121-M$111)/M$95,"")} | M16: {=IFERROR(+(_FV(A16,"Market cap",TRUE)/1000000+M$121-M$111)/M$100,"")} | N16: {=IFERROR(+(_FV(A16,"Market cap",TRUE)/1000000)/M$96,"")} | O16: {=IFERROR(+(_FV(A16,"Market cap",TRUE)/1000000)/M$105,"")}
A17: =+N91 -> PEER 10 | B17: {=IFERROR(_FV(A17,"Name"),"")} | C17: {=+IFERROR(_FV(A17,"Ticker symbol",TRUE),"")} | D17: =IFERROR(N94/N93-1,"") | E17: =IFERROR(N97/N94-1,"") | F17: =IFERROR(N95/N94,"") | G17: =IFERROR(N100/N97,"") | H17: =IFERROR(N96/N94,"") | I17: =+IFERROR(N105/N97,"") | J17: {=IFERROR(+(_FV(A17,"Market cap",TRUE)/1000000+N$121-N$111)/N$94,"")} | K17: {=IFERROR(+(_FV(A17,"Market cap",TRUE)/1000000+N$121-N$111)/N$97,"")} | L17: {=IFERROR(+(_FV(A17,"Market cap",TRUE)/1000000+N$121-N$111)/N$95,"")} | M17: {=IFERROR(+(_FV(A17,"Market cap",TRUE)/1000000+N$121-N$111)/N$100,"")} | N17: {=IFERROR(+(_FV(A17,"Market cap",TRUE)/1000000)/N$96,"")} | O17: {=IFERROR(+(_FV(A17,"Market cap",TRUE)/1000000)/N$105,"")}
B18: Average | D18: =IFERROR(AVERAGE(D6:D17),"") | E18: =IFERROR(AVERAGE(E6:E17),"") | F18: =IFERROR(AVERAGE(F6:F17),"") | G18: =IFERROR(AVERAGE(G6:G17),"") | H18: =IFERROR(AVERAGE(H6:H17),"") | I18: =IFERROR(AVERAGE(I6:I17),"") | J18: =IFERROR(AVERAGE(J6:J17),"") | K18: =IFERROR(AVERAGE(K6:K17),"") | ... O18: =IFERROR(AVERAGE(O6:O17),"")
B19: Deviation from Average | D19: =IFERROR(+D18-D6,"") | E19: =IFERROR(E18-E6,"") | F19: =+IFERROR(F18-F6,"") | G19: =IFERROR(G18-G6,"") | H19: =IFERROR(+H6-H18,"") | I19: =+IFERROR(I6-I18,"") | J19: =+IFERROR(J6-J18,"") | K19: =+IFERROR(K6-K18,"") | L19: =IFERROR(+L6-L18,"") | M19: =IFERROR(M6-M18,"") | N19: =IFERROR(+N6-N18,"") | O19: =IFERROR(+O6-O18,"")
D21: Trading Multiple | G21: Net | H21: Preferred | I21: Non-Controlling | J21: Equity Value | M21: Implied Upside (Downside)
B22: Implied Share Price | D22: Revenue | E22: EBITDA | F22: P/E | G22: Debt | H22: Stock | I22: Interest | J22: Revenue | K22: EBITDA | L22: P/E | M22: Revenue | N22: EBITDA | O22: P/E | P22: Current Price
B24: Second Minimum | D24: =IFERROR(SMALL(K6:K17,2),"") | E24: =IFERROR(SMALL(M6:M17,2),"") | F24: =IFERROR(SMALL(O6:O17,2),"") | G24: =-Inputs!$Q$99+Inputs!$Q$100 -> 0 | H24: =+Inputs!$Q$101 -> 0 | I24: =+Inputs!$Q$102 -> 0 | J24: =IFERROR(+D24*$D$97+G24+H24+I24,"") | K24: =IFERROR(E24*$D$100+G24+H24+I24,"") | L24: =IFERROR(F24*$D$105,"") | M24: {=IFERROR(+(J24/_FV($A$6,"Shares outstanding",TRUE)*1000000)/$P$24-1,"")} | N24: {=IFERROR((+K24/_FV($A$6,"Shares outstanding",TRUE)*1000000)/$P$24-1,"")} | O24: {=IFERROR(+(L24/_FV($A$6,"Shares outstanding",TRUE)*1000000)/$P$24-1,"")} | P24: {=+_FV(A6,"Price")} -> 156.6514
B25: Average | D25: =+IFERROR(AVERAGE(K6:K17),"") | E25: =IFERROR(+AVERAGE(M6:M17),"") | F25: =IFERROR(+AVERAGE(O6:O17),"") | G25: =-Inputs!$Q$99+Inputs!$Q$100 -> 0 | H25: =+Inputs!$Q$101 -> 0 | I25: =+Inputs!$Q$102 -> 0 | J25: =IFERROR(+D25*$D$97+G25+H25+I25,"") | K25: =IFERROR(E25*$D$100+G25+H25+I25,"") | L25: =IFERROR(+F25*$D$105,"") | M25: {=IFERROR(+(J25/_FV($A$6,"Shares outstanding",TRUE)*1000000)/$P$24-1,"")} | N25: {=IFERROR((+K25/_FV($A$6,"Shares outstanding",TRUE)*1000000)/$P$24-1,"")} | O25: {=IFERROR(+(L25/_FV($A$6,"Shares outstanding",TRUE)*1000000)/$P$24-1,"")}
B26: Median | D26: =IFERROR(MEDIAN(K6:K17),"") | E26: =IFERROR(MEDIAN(M6:M17),"") | F26: =IFERROR(MEDIAN(O6:O17),"") | G26: =-Inputs!$Q$99+Inputs!$Q$100 -> 0 | H26: =+Inputs!$Q$101 -> 0 | I26: =+Inputs!$Q$102 -> 0 | J26: =IFERROR(D26*$D$97+G26+H26+I26,"") | K26: =IFERROR(E26*$D$100+G26+H26+I26,"") | L26: =IFERROR(+F26*$D$105,"") | M26: {=IFERROR(+(J26/_FV($A$6,"Shares outstanding",TRUE)*1000000)/$P$24-1,"")} | N26: {=IFERROR((+K26/_FV($A$6,"Shares outstanding",TRUE)*1000000)/$P$24-1,"")} | O26: {=+IFERROR((L26/_FV($A$6,"Shares outstanding",TRUE)*1000000)/$P$24-1,"")}
B27: Second Maximum | D27: =IFERROR(LARGE(K6:K17,2),"") | E27: =IFERROR(LARGE(M6:M17,2),"") | F27: =IFERROR(LARGE(O6:O17,2),"") | G27: =-Inputs!$Q$99+Inputs!$Q$100 -> 0 | H27: =+Inputs!$Q$101 -> 0 | I27: =+Inputs!$Q$102 -> 0 | J27: =IFERROR(+D27*$D$97+G27+H27+I27,"") | K27: =IFERROR(E27*$D$100+G27+H27+I27,"") | L27: =IFERROR(+F27*$D$105,"") | M27: {=IFERROR(+(J27/_FV($A$6,"Shares outstanding",TRUE)*1000000)/$P$24-1,"")} | N27: {=IFERROR((+K27/_FV($A$6,"Shares outstanding",TRUE)*1000000)/$P$24-1,"")} | O27: {=IFERROR(+(L27/_FV($A$6,"Shares outstanding",TRUE)*1000000)/$P$24-1,"")}
B29: Profitability | D29: =+LEFT(B6, FIND(" ", B6 & " ") - 1) -> ADVANCED | E29: =+LEFT(B8, FIND(" ", B8 & " ") - 1) | F29: =+LEFT(B9, FIND(" ", B9 & " ") - 1) | G29: =+LEFT(B10, FIND(" ", B10 & " ") - 1) | H29: =+LEFT(B11, FIND(" ", B11 & " ") - 1) | I29: =+LEFT(B12, FIND(" ", B12 & " ") - 1) | J29: =+LEFT(C12, FIND(" ", C12 & " ") - 1) | K29: =+LEFT(B14, FIND(" ", B14 & " ") - 1) | L29: =+LEFT(B15, FIND(" ", B15 & " ") - 1) | M29: =+LEFT(B16, FIND(" ", B16 & " ") - 1) | N29: =+LEFT(B17, FIND(" ", B17 & " ") - 1) | O29: Average
B31: Operating Margin | D31: =IFERROR(D101/D97,"") | E31: =IFERROR(E101/E97,"") | F31: =IFERROR(F101/F97,"") | G31: =IFERROR(G101/G97,"") | H31: =IFERROR(H101/H97,"") | I31: =IFERROR(I101/I97,"") | J31: =IFERROR(J101/J97,"") | K31: =IFERROR(K101/K97,"") | ... N31: =IFERROR(N101/N97,"") | O31: =IFERROR(+AVERAGE(D31:N31),"")
B32: Net Income Margin | D32: =IFERROR(D105/D97,"") | E32: =IFERROR(E105/E97,"") | F32: =IFERROR(F105/F97,"") | G32: =IFERROR(G105/G97,"") | H32: =IFERROR(H105/H97,"") | I32: =IFERROR(I105/I97,"") | J32: =IFERROR(J105/J97,"") | K32: =IFERROR(K105/K97,"") | ... N32: =IFERROR(N105/N97,"") | O32: =IFERROR(+AVERAGE(D32:N32),"")
B33: ROA (%) | D33: =IFERROR(D105/D117,"") | E33: =IFERROR(E105/E117,"") | F33: =IFERROR(F105/F117,"") | G33: =IFERROR(G105/G117,"") | H33: =IFERROR(H105/H117,"") | I33: =IFERROR(I105/I117,"") | J33: =IFERROR(J105/J117,"") | K33: =IFERROR(K105/K117,"") | ... N33: =IFERROR(N105/N117,"") | O33: =IFERROR(+AVERAGE(D33:N33),"")
B34: Financial Cost of Debt | D34: =IFERROR(+(D102/D121)*(1-(D104/D103)),"") | E34: =IFERROR(+(E102/E121)*(1-(E104/E103)),"") | F34: =IFERROR(+(F102/F121)*(1-(F104/F103)),"") | G34: =IFERROR(+(G102/G121)*(1-(G104/G103)),"") | H34: =IFERROR(+(H102/H121)*(1-(H104/H103)),"") | I34: =IFERROR(+(I102/I121)*(1-(I104/I103)),"") | J34: =IFERROR(+(J102/J121)*(1-(J104/J103)),"") | K34: =IFERROR(+(K102/K121)*(1-(K104/K103)),"") | ... N34: =IFERROR(+(N102/N121)*(1-(N104/N103)),"") | O34: =IFERROR(+AVERAGE(D34:N34),"")
B35: Return on Equity (RoE) | D35: =IFERROR(+D105/D122,"") | E35: =IFERROR(+E105/E122,"") | F35: =IFERROR(+F105/F122,"") | G35: =IFERROR(+G105/G122,"") | H35: =IFERROR(+H105/H122,"") | I35: =IFERROR(+I105/I122,"") | J35: =IFERROR(+J105/J122,"") | K35: =IFERROR(+K105/K122,"") | ... N35: =IFERROR(+N105/N122,"") | O35: =IFERROR(+AVERAGE(D35:N35),"")
B36: Return on Invested Capital (ROIC) | D36: =IFERROR(+D105/(D121+D122),"") | E36: =IFERROR(+E105/(E121+E122),"") | F36: =IFERROR(+F105/(F121+F122),"") | G36: =IFERROR(+G105/(G121+G122),"") | H36: =IFERROR(+H105/(H121+H122),"") | I36: =IFERROR(+I105/(I121+I122),"") | J36: =IFERROR(+J105/(J121+J122),"") | K36: =IFERROR(+K105/(K121+K122),"") | ... N36: =IFERROR(+N105/(N121+N122),"") | O36: =IFERROR(+AVERAGE(D36:N36),"")
B38: Solvency | D38: =+D29 -> ADVANCED | E38: =+E29 | F38: =+F29 | G38: =+G29 | H38: =+H29 | I38: =+I29 | J38: =+J29 | K38: =+K29 | ... O38: =+O29 -> Average
B40: Debt/Assets | D40: =IFERROR(D121/D117,"") | E40: =IFERROR(E121/E117,"") | F40: =IFERROR(F121/F117,"") | G40: =IFERROR(G121/G117,"") | H40: =IFERROR(H121/H117,"") | I40: =IFERROR(I121/I117,"") | J40: =IFERROR(J121/J117,"") | K40: =IFERROR(K121/K117,"") | ... N40: =IFERROR(N121/N117,"") | O40: =IFERROR(+AVERAGE(D40:N40),"")
B41: Net Debt/EBITDA | D41: =IFERROR(+(D121-D111)/D100,"") | E41: =IFERROR(+(E121-E111)/E100,"") | F41: =IFERROR(+(F121-F111)/F100,"") | G41: =IFERROR(+(G121-G111)/G100,"") | H41: =IFERROR(+(H121-H111)/H100,"") | I41: =IFERROR(+(I121-I111)/I100,"") | J41: =IFERROR(+(J121-J111)/J100,"") | K41: =IFERROR(+(K121-K111)/K100,"") | ... N41: =IFERROR(+(N121-N111)/N100,"") | O41: =IFERROR(+AVERAGE(D41:N41),"")
B42: Interest Coverage Ratio | D42: =IFERROR(D101/D102,"") | E42: =IFERROR(E101/E102,"") | F42: =IFERROR(F101/F102,"") | G42: =IFERROR(G101/G102,"") | H42: =IFERROR(H101/H102,"") | I42: =IFERROR(I101/I102,"") | J42: =IFERROR(J101/J102,"") | K42: =IFERROR(K101/K102,"") | ... N42: =IFERROR(N101/N102,"") | O42: =IFERROR(+AVERAGE(D42:N42),"")
B44: Liquidity | D44: =+D29 -> ADVANCED | E44: =+E29 | F44: =+F29 | G44: =+G29 | H44: =+H29 | I44: =+I29 | J44: =+J29 | K44: =+K29 | ... O44: =+O29 -> Average
B46: Cash Ratio | D46: =IFERROR(D111/D119,"") | E46: =IFERROR(E111/E119,"") | F46: =IFERROR(F111/F119,"") | G46: =IFERROR(G111/G119,"") | H46: =IFERROR(H111/H119,"") | I46: =IFERROR(I111/I119,"") | J46: =IFERROR(J111/J119,"") | K46: =IFERROR(K111/K119,"") | ... N46: =IFERROR(N111/N119,"") | O46: =IFERROR(+AVERAGE(D46:N46),"")
B47: Quick Ratio | D47: =IFERROR(+(D111+D112)/D119,"") | E47: =IFERROR(+(E111+E112)/E119,"") | F47: =IFERROR(+(F111+F112)/F119,"") | G47: =IFERROR(+(G111+G112)/G119,"") | H47: =IFERROR(+(H111+H112)/H119,"") | I47: =IFERROR(+(I111+I112)/I119,"") | J47: =IFERROR(+(J111+J112)/J119,"") | K47: =IFERROR(+(K111+K112)/K119,"") | ... N47: =IFERROR(+(N111+N112)/N119,"") | O47: =IFERROR(+AVERAGE(D47:N47),"")
B48: Current Ratio | D48: =IFERROR(D115/D119,"") | E48: =IFERROR(E115/E119,"") | F48: =IFERROR(F115/F119,"") | G48: =IFERROR(G115/G119,"") | H48: =IFERROR(H115/H119,"") | I48: =IFERROR(I115/I119,"") | J48: =IFERROR(J115/J119,"") | K48: =IFERROR(K115/K119,"") | ... N48: =IFERROR(N115/N119,"") | O48: =IFERROR(+AVERAGE(D48:N48),"")
B50: Activity | D50: =+D29 -> ADVANCED | E50: =+E29 | F50: =+F29 | G50: =+G29 | H50: =+H29 | I50: =+I29 | J50: =+J29 | K50: =+K29 | ... O50: =+O29 -> Average
B52: Inventory Turnover | D52: =IFERROR(D98/(AVERAGE(D113:D114)),"") | E52: =IFERROR(E98/(AVERAGE(E113:E114)),"") | F52: =IFERROR(F98/(AVERAGE(F113:F114)),"") | G52: =IFERROR(G98/(AVERAGE(G113:G114)),"") | H52: =IFERROR(H98/(AVERAGE(H113:H114)),"") | I52: =IFERROR(I98/(AVERAGE(I113:I114)),"") | J52: =IFERROR(J98/(AVERAGE(J113:J114)),"") | K52: =IFERROR(K98/(AVERAGE(K113:K114)),"") | ... N52: =IFERROR(N98/(AVERAGE(N113:N114)),"") | O52: =IFERROR(+AVERAGE(D52:N52),"")
B53: Acc. Receivable Turnover | D53: =IFERROR(D97/D112,"") | E53: =IFERROR(E97/E112,"") | F53: =IFERROR(F97/F112,"") | G53: =IFERROR(G97/G112,"") | H53: =IFERROR(H97/H112,"") | I53: =IFERROR(I97/I112,"") | J53: =IFERROR(J97/J112,"") | K53: =IFERROR(K97/K112,"") | ... N53: =IFERROR(N97/N112,"") | O53: =IFERROR(+AVERAGE(D53:N53),"")
B54: Payables Turnover | D54: =IFERROR(D98/D118,"") | E54: =IFERROR(E98/E118,"") | F54: =IFERROR(F98/F118,"") | G54: =IFERROR(G98/G118,"") | H54: =IFERROR(H98/H118,"") | I54: =IFERROR(I98/I118,"") | J54: =IFERROR(J98/J118,"") | K54: =IFERROR(K98/K118,"") | ... N54: =IFERROR(N98/N118,"") | O54: =IFERROR(+AVERAGE(D54:N54),"")
B55: Fixed Asset Turnover | D55: =IFERROR(D97/D116,"") | E55: =IFERROR(E97/E116,"") | F55: =IFERROR(F97/F116,"") | G55: =IFERROR(G97/G116,"") | H55: =IFERROR(H97/H116,"") | I55: =IFERROR(I97/I116,"") | J55: =IFERROR(J97/J116,"") | K55: =IFERROR(K97/K116,"") | ... N55: =IFERROR(N97/N116,"") | O55: =IFERROR(+AVERAGE(D55:N55),"")
B56: Total Asset Turnover | D56: =IFERROR(D97/D117,"") | E56: =IFERROR(E97/E117,"") | F56: =IFERROR(F97/F117,"") | G56: =IFERROR(G97/G117,"") | H56: =IFERROR(H97/H117,"") | I56: =IFERROR(I97/I117,"") | J56: =IFERROR(J97/J117,"") | K56: =IFERROR(K97/K117,"") | ... N56: =IFERROR(N97/N117,"") | O56: =IFERROR(+AVERAGE(D56:N56),"")
B57: Cash Cycle (days) | D57: =IFERROR(365/D52+365/D53-365/D54,"") | E57: =IFERROR(365/E52+365/E53-365/E54,"") | F57: =IFERROR(365/F52+365/F53-365/F54,"") | G57: =IFERROR(365/G52+365/G53-365/G54,"") | H57: =IFERROR(365/H52+365/H53-365/H54,"") | I57: =IFERROR(365/I52+365/I53-365/I54,"") | J57: =IFERROR(365/J52+365/J53-365/J54,"") | K57: =IFERROR(365/K52+365/K53-365/K54,"") | ... N57: =IFERROR(365/N52+365/N53-365/N54,"") | O57: =IFERROR(+AVERAGE(D57:N57),"")
B59: Cash Flow | D59: =+D38 -> ADVANCED | E59: =+E38 | F59: =+F38 | G59: =+G38 | H59: =+H38 | I59: =+I38 | J59: =+J38 | K59: =+K38 | ... O59: =+O38 -> Average
B61: Cash Flow Margin | D61: =IFERROR(D132/D97,"") | E61: =IFERROR(E132/E97,"") | F61: =IFERROR(F132/F97,"") | G61: =IFERROR(G132/G97,"") | H61: =IFERROR(H132/H97,"") | I61: =IFERROR(I132/I97,"") | J61: =IFERROR(J132/J97,"") | K61: =IFERROR(K132/K97,"") | ... N61: =IFERROR(N132/N97,"") | O61: =IFERROR(+AVERAGE(D61:N61),"")
B62: Cash Flow to Net Income | D62: =IFERROR(D132/D96,"") | E62: =IFERROR(E132/E96,"") | F62: =IFERROR(F132/F96,"") | G62: =IFERROR(G132/G96,"") | H62: =IFERROR(H132/H96,"") | I62: =IFERROR(I132/I96,"") | J62: =IFERROR(J132/J96,"") | K62: =IFERROR(K132/K96,"") | ... N62: =IFERROR(N132/N96,"") | O62: =IFERROR(+AVERAGE(D62:N62),"")
B63: CFO to Net Income | D63: =+IFERROR(D126/D105,"") | E63: =+IFERROR(E126/E105,"") | F63: =+IFERROR(F126/F105,"") | G63: =+IFERROR(G126/G105,"") | H63: =+IFERROR(H126/H105,"") | I63: =+IFERROR(I126/I105,"") | J63: =+IFERROR(J126/J105,"") | K63: =+IFERROR(K126/K105,"") | ... N63: =+IFERROR(N126/N105,"") | O63: =IFERROR(+AVERAGE(D63:N63),"")
B64: Net Capex to CFO | D64: =IFERROR(-D127/D126,"") | E64: =IFERROR(-E127/E126,"") | F64: =IFERROR(-F127/F126,"") | G64: =IFERROR(-G127/G126,"") | H64: =IFERROR(-H127/H126,"") | I64: =IFERROR(-I127/I126,"") | J64: =IFERROR(-J127/J126,"") | K64: =IFERROR(-K127/K126,"") | ... N64: =IFERROR(-N127/N126,"") | O64: =IFERROR(+AVERAGE(D64:N64),"")
B65: CFI to CFO | D65: =IFERROR(-D128/D126,"") | E65: =IFERROR(-E128/E126,"") | F65: =IFERROR(-F128/F126,"") | G65: =IFERROR(-G128/G126,"") | H65: =IFERROR(-H128/H126,"") | I65: =IFERROR(-I128/I126,"") | J65: =IFERROR(-J128/J126,"") | K65: =IFERROR(-K128/K126,"") | ... N65: =IFERROR(-N128/N126,"") | O65: =IFERROR(+AVERAGE(D65:N65),"")
B66: Net Financing to CFO | D66: =IFERROR((D129+D130)/D126,"") | E66: =IFERROR((E129+E130)/E126,"") | F66: =IFERROR((F129+F130)/F126,"") | G66: =IFERROR((G129+G130)/G126,"") | H66: =IFERROR((H129+H130)/H126,"") | I66: =IFERROR((I129+I130)/I126,"") | J66: =IFERROR((J129+J130)/J126,"") | K66: =IFERROR((K129+K130)/K126,"") | ... N66: =IFERROR((N129+N130)/N126,"") | O66: =IFERROR(+AVERAGE(D66:N66),"")
B67: Debt Borrowing to Debt Repayment | D67: =+IFERROR(-D130/D129,"") | E67: =+IFERROR(-E130/E129,"") | F67: =+IFERROR(-F130/F129,"") | G67: =+IFERROR(-G130/G129,"") | H67: =+IFERROR(-H130/H129,"") | I67: =+IFERROR(-I130/I129,"") | J67: =+IFERROR(-J130/J129,"") | K67: =+IFERROR(-K130/K129,"") | ... N67: =+IFERROR(-N130/N129,"") | O67: =IFERROR(+AVERAGE(D67:N67),"")
B68: CFF to CFO | D68: =IFERROR(-D131/D126,"") | E68: =IFERROR(-E131/E126,"") | F68: =IFERROR(-F131/F126,"") | G68: =IFERROR(-G131/G126,"") | H68: =IFERROR(-H131/H126,"") | I68: =IFERROR(-I131/I126,"") | J68: =IFERROR(-J131/J126,"") | K68: =IFERROR(-K131/K126,"") | ... N68: =IFERROR(-N131/N126,"") | O68: =IFERROR(+AVERAGE(D68:N68),"")
B69: Payout Ratio | O69: =IFERROR(+AVERAGE(D69:N69),"")
B71: Stock Information | D71: =+D29 -> ADVANCED | E71: =+E29 | F71: =+F29 | G71: =+G29 | H71: =+H29 | I71: =+I29 | J71: =+J29 | K71: =+K29 | ... O71: =+O29 -> Average
B73: (%) Float | O73: =IFERROR(+AVERAGE(D73:N73),"")
B74: β (Levered) | D74: {=IFERROR(_FV(D91,"Beta"),"")} -> 1.898 | E74: {=IFERROR(_FV(E91,"Beta"),"")} | F74: {=IFERROR(_FV(F91,"Beta"),"")} | G74: {=IFERROR(_FV(G91,"Beta"),"")} | H74: {=IFERROR(_FV(H91,"Beta"),"")} | I74: {=IFERROR(_FV(I91,"Beta"),"")} | J74: {=IFERROR(_FV(J91,"Beta"),"")} | K74: {=IFERROR(_FV(K91,"Beta"),"")} | ... N74: {=IFERROR(_FV(N91,"Beta"),"")} | O74: =IFERROR(+AVERAGE(D74:N74),"") -> 1.898
B75: β (Unlevered) | D75: =IFERROR(D74/(1+(1-D104/D103)*(D121/D122)),"") | E75: =IFERROR(E74/(1+(1-E104/E103)*(E121/E122)),"") | F75: =IFERROR(F74/(1+(1-F104/F103)*(F121/F122)),"") | G75: =IFERROR(G74/(1+(1-G104/G103)*(G121/G122)),"") | H75: =IFERROR(H74/(1+(1-H104/H103)*(H121/H122)),"") | I75: =IFERROR(I74/(1+(1-I104/I103)*(I121/I122)),"") | J75: =IFERROR(J74/(1+(1-J104/J103)*(J121/J122)),"") | K75: =IFERROR(K74/(1+(1-K104/K103)*(K121/K122)),"") | ... N75: =IFERROR(N74/(1+(1-N104/N103)*(N121/N122)),"") | O75: =IFERROR(+AVERAGE(D75:N75),"")
B76: % Held by Insiders | O76: =IFERROR(+AVERAGE(D76:N76),"")
B77: % Held by Institutions | O77: =IFERROR(+AVERAGE(D77:N77),"")
B78: Short % Float | O78: =IFERROR(+AVERAGE(D78:N78),"")
B80: Stock Performance | D80: =+D29 -> ADVANCED | E80: =+E29 | F80: =+F29 | G80: =+G29 | H80: =+H29 | I80: =+I29 | J80: =+J29 | K80: =+K29 | ... O80: =+O29 -> Average
B82: 1 day | D82: {=IFERROR((D85/_xlfn.STOCKHISTORY(C6,TODAY()-1,TODAY()-1,0,0,1))-1,"Non-trading days")} -> 0.17853897 | E82: {=IFERROR((E85/_xlfn.STOCKHISTORY(C8,TODAY()-1,TODAY()-1,0,0,1))-1,"Non-trading days")} -> Non-trading days | F82: {=IFERROR((F85/_xlfn.STOCKHISTORY(C9,TODAY()-1,TODAY()-1,0,0,1))-1,"Non-trading days")} -> Non-trading days | G82: {=IFERROR((G85/_xlfn.STOCKHISTORY(C10,TODAY()-1,TODAY()-1,0,0,1))-1,"Non-trading days")} -> Non-trading days | H82: {=IFERROR((K85/_xlfn.STOCKHISTORY(C11,TODAY()-1,TODAY()-1,0,0,1))-1,"Non-trading days")} -> Non-trading days | I82: {=IFERROR((L85/_xlfn.STOCKHISTORY(C12,TODAY()-1,TODAY()-1,0,0,1))-1,"Non-trading days")} -> Non-trading days | J82: {=IFERROR((M85/_xlfn.STOCKHISTORY(C13,TODAY()-1,TODAY()-1,0,0,1))-1,"Non-trading days")} -> Non-trading days | K82: {=IFERROR((N85/_xlfn.STOCKHISTORY(C14,TODAY()-1,TODAY()-1,0,0,1))-1,"Non-trading days")} -> Non-trading days | L82: {=IFERROR((L85/_xlfn.STOCKHISTORY(C15,TODAY()-1,TODAY()-1,0,0,1))-1,"Non-trading days")} -> Non-trading days | M82: {=IFERROR((M85/_xlfn.STOCKHISTORY(C16,TODAY()-1,TODAY()-1,0,0,1))-1,"Non-trading days")} -> Non-trading days | N82: {=IFERROR((N85/_xlfn.STOCKHISTORY(C17,TODAY()-1,TODAY()-1,0,0,1))-1,"Non-trading days")} -> Non-trading days | O82: =IFERROR(+AVERAGE(D82:N82),"") -> 0.17853897
B83: 1 month | D83: {=IFERROR((D85/_xlfn.STOCKHISTORY(C6,TODAY()-29,TODAY()-29,0,0,1))-1,"Non-trading days")} -> -0.043116486 | E83: {=IFERROR((E85/_xlfn.STOCKHISTORY(C8,TODAY()-29,TODAY()-29,0,0,1))-1,"Non-trading days")} -> Non-trading days | F83: {=IFERROR((F85/_xlfn.STOCKHISTORY(C9,TODAY()-29,TODAY()-29,0,0,1))-1,"Non-trading days")} -> Non-trading days | G83: {=IFERROR((G85/_xlfn.STOCKHISTORY(C10,TODAY()-29,TODAY()-29,0,0,1))-1,"Non-trading days")} -> Non-trading days | H83: {=IFERROR((K85/_xlfn.STOCKHISTORY(C11,TODAY()-29,TODAY()-29,0,0,1))-1,"Non-trading days")} -> Non-trading days | I83: {=IFERROR((L85/_xlfn.STOCKHISTORY(C12,TODAY()-29,TODAY()-29,0,0,1))-1,"Non-trading days")} -> Non-trading days | J83: {=IFERROR((M85/_xlfn.STOCKHISTORY(C13,TODAY()-29,TODAY()-29,0,0,1))-1,"Non-trading days")} -> Non-trading days | K83: {=IFERROR((N85/_xlfn.STOCKHISTORY(C14,TODAY()-29,TODAY()-29,0,0,1))-1,"Non-trading days")} -> Non-trading days | L83: {=IFERROR((L85/_xlfn.STOCKHISTORY(C15,TODAY()-29,TODAY()-29,0,0,1))-1,"Non-trading days")} -> Non-trading days | M83: {=IFERROR((M85/_xlfn.STOCKHISTORY(C16,TODAY()-29,TODAY()-29,0,0,1))-1,"Non-trading days")} -> Non-trading days | N83: {=IFERROR((N85/_xlfn.STOCKHISTORY(C17,TODAY()-29,TODAY()-29,0,0,1))-1,"Non-trading days")} -> Non-trading days | O83: =IFERROR(AVERAGE(D83:N83),"") -> -0.043116486
B84: YTD | D84: {=IFERROR((D85/_xlfn.STOCKHISTORY(C6,"2025-01-02","2025-01-02",0,0,1))-1,"Non-trading days")} -> 0.29861063 | E84: {=IFERROR((E85/_xlfn.STOCKHISTORY(C8,"2025-01-02","2025-01-02",0,0,1))-1,"Non-trading days")} -> Non-trading days | F84: {=IFERROR((F85/_xlfn.STOCKHISTORY(C9,"2025-01-02","2025-01-02",0,0,1))-1,"Non-trading days")} -> Non-trading days | G84: {=IFERROR((G85/_xlfn.STOCKHISTORY(C10,"2025-01-02","2025-01-02",0,0,1))-1,"Non-trading days")} -> Non-trading days | H84: {=IFERROR((K85/_xlfn.STOCKHISTORY(C11,"2025-01-02","2025-01-02",0,0,1))-1,"Non-trading days")} -> Non-trading days | I84: {=IFERROR((L85/_xlfn.STOCKHISTORY(C12,"2025-01-02","2025-01-02",0,0,1))-1,"Non-trading days")} -> Non-trading days | J84: {=IFERROR((M85/_xlfn.STOCKHISTORY(C13,"2025-01-02","2025-01-02",0,0,1))-1,"Non-trading days")} -> Non-trading days | K84: {=IFERROR((N85/_xlfn.STOCKHISTORY(C14,"2025-01-02","2025-01-02",0,0,1))-1,"Non-trading days")} -> Non-trading days | L84: {=IFERROR((L85/_xlfn.STOCKHISTORY(C15,"2025-01-02","2025-01-02",0,0,1))-1,"Non-trading days")} -> Non-trading days | M84: {=IFERROR((M85/_xlfn.STOCKHISTORY(C16,"2025-01-02","2025-01-02",0,0,1))-1,"Non-trading days")} -> Non-trading days | N84: {=IFERROR((N85/_xlfn.STOCKHISTORY(C17,"2025-01-02","2025-01-02",0,0,1))-1,"Non-trading days")} -> Non-trading days | O84: =IFERROR(AVERAGE(D84:N84),"") -> 0.29861063
B85: Current Price | D85: {=+IFERROR(_FV(D91,"Price"),"")} -> 156.6514 | E85: {=+IFERROR(_FV(E91,"Price"),"")} | F85: {=+IFERROR(_FV(F91,"Price"),"")} | G85: {=+IFERROR(_FV(G91,"Price"),"")} | H85: {=+IFERROR(_FV(H91,"Price"),"")} | I85: {=+IFERROR(_FV(I91,"Price"),"")} | J85: {=+IFERROR(_FV(J91,"Price"),"")} | K85: {=+IFERROR(_FV(K91,"Price"),"")} | ... N85: {=+IFERROR(_FV(N91,"Price"),"")} | O85: =IFERROR(AVERAGE(D85:N85),"") -> 156.6514
B87: Extra
B89: % Revenues in the US
B91: Income Statement | D91: =+DCF!R4 -> #VALUE! | E91: PEER 1 | F91: PEER 2 | G91: PEER 3 | H91: PEER 4 | I91: PEER 5 | J91: PEER 6 | K91: PEER 7 | L91: PEER 8 | M91: PEER 9 | N91: PEER 10
B93: =+Inputs!$B$6&" ("&Inputs!O$4&")" -> Revenue (Sales) (2022) | D93: =+_xlfn.XLOOKUP("Revenue (Sales)",Inputs!$B:$B,Inputs!O:O) -> 0
B94: =+Inputs!$B$6&" ("&Inputs!P$4&")" -> Revenue (Sales) (2023) | D94: =+_xlfn.XLOOKUP("Revenue (Sales)",Inputs!$B:$B,Inputs!P:P) -> 0
B95: EBITDA (2023) | D95: =+_xlfn.XLOOKUP("EBITDA",Inputs!$B:$B,Inputs!P:P) -> 0
B96: Net Income (2023) | D96: =+_xlfn.XLOOKUP("Net Income",Inputs!$B:$B,Inputs!P:P) -> 0
B97: =+Inputs!$B$6&" ("&Inputs!Q$4&")" -> Revenue (Sales) (2024) | D97: =+_xlfn.XLOOKUP("Revenue (Sales)",Inputs!$B:$B,Inputs!Q:Q) -> 0
B98: COGS (Cost of Goods Sold) | D98: =+_xlfn.XLOOKUP($B98,Inputs!$B:$B,Inputs!Q:Q) -> 0
B99: Gross Profit | D99: =+_xlfn.XLOOKUP($B99,Inputs!$B:$B,Inputs!Q:Q) -> 0 | E99: =+E97-E98 -> 0 | F99: =+F97-F98 -> 0 | G99: =G97-G98 -> 0 | H99: =+H97-H98 -> 0 | I99: =I97-I98 -> 0 | J99: =+J97-J98 -> 0 | K99: =+K97-K98 -> 0 | L99: =+L97-L98 -> 0 | M99: =+M97-M98 -> 0 | N99: =+N97-N98 -> 0
B100: EBITDA | D100: =+_xlfn.XLOOKUP($B100,Inputs!$B:$B,Inputs!Q:Q) -> 0
B101: Operating Income (EBIT) | D101: =+_xlfn.XLOOKUP($B101,Inputs!$B:$B,Inputs!Q:Q) -> 0
B102: Net Interest Expense (Income) | D102: =+_xlfn.XLOOKUP($B102,Inputs!$B:$B,Inputs!Q:Q) -> 0
B103: Pre-Tax Income (EBT) | D103: =+_xlfn.XLOOKUP($B103,Inputs!$B:$B,Inputs!Q:Q) -> 0
B104: Tax Expense (Benefits) | D104: =+_xlfn.XLOOKUP($B104,Inputs!$B:$B,Inputs!Q:Q) -> 0
B105: Net Income | D105: =+_xlfn.XLOOKUP($B105,Inputs!$B:$B,Inputs!Q:Q) -> 0
B106: EPS basic | D106: =+_xlfn.XLOOKUP($B106,Inputs!$B:$B,Inputs!Q:Q) -> 0
B107: R&D (Research & Development) | D107: =+_xlfn.XLOOKUP($B107,Inputs!$B:$B,Inputs!Q:Q) -> 0
B109: Balance Sheet
B111: Cash & Cash Equivalents | D111: =+_xlfn.XLOOKUP($B111,Inputs!$B:$B,Inputs!Q:Q) -> 0
B112: Accounts Receivable | D112: =+_xlfn.XLOOKUP($B112,Inputs!$B:$B,Inputs!Q:Q) -> 0
B113: Beginning Inventory | D113: =+_xlfn.XLOOKUP("Inventory",Inputs!$B:$B,Inputs!P:P) -> 0
B114: Ending Inventory | D114: =+_xlfn.XLOOKUP("Inventory",Inputs!$B:$B,Inputs!Q:Q) -> 0
B115: Current Assets | D115: =+_xlfn.XLOOKUP($B115,Inputs!$B:$B,Inputs!Q:Q) -> 0
B116: Net PP&E (Property, Plant and Equipment) | D116: =+_xlfn.XLOOKUP($B116,Inputs!$B:$B,Inputs!Q:Q) -> 0
B117: Total Assets | D117: =+_xlfn.XLOOKUP($B117,Inputs!$B:$B,Inputs!Q:Q) -> 0
B118: Accounts Payable | D118: =+_xlfn.XLOOKUP($B118,Inputs!$B:$B,Inputs!Q:Q) -> 0
B119: Current Liabilities | D119: =+_xlfn.XLOOKUP($B119,Inputs!$B:$B,Inputs!Q:Q) -> 0
B120: Long-term debt | D120: =+_xlfn.XLOOKUP($B120,Inputs!$B:$B,Inputs!Q:Q) -> 0
B121: Total Debt | D121: =+_xlfn.XLOOKUP($B121,Inputs!$B:$B,Inputs!Q:Q,,,-1) -> 0
B122: Shareholder's Equity | D122: =+_xlfn.XLOOKUP($B122,Inputs!$B:$B,Inputs!Q:Q) -> 0
B124: Cash Flow Statement
B126: Operating Cash Flow | D126: =+_xlfn.XLOOKUP($B126,Inputs!$B:$B,Inputs!Q:Q) -> 0
B127: Net Capex | D127: =+_xlfn.XLOOKUP($B127,Inputs!$B:$B,Inputs!Q:Q) -> 0
B128: Investing Cash Flow | D128: =+_xlfn.XLOOKUP($B128,Inputs!$B:$B,Inputs!Q:Q) -> 0
...

Sheet ESG
B2: Environmental, Social and Governance Analysis
B4: Author: | E4: Highlights | N4: Recent News
B6: Overview | D6: .
B7: Last Update | D7: .
B8: Latest year with data
B9: GICS Sector
B10: GICS Industry Group
B11: Final Review
B13: ESG Scores
B14: LSEG ESG Score
B15: E-Score
B16: S-Score | E16: GHG Scope 1 and 2 Emissions: | N16: Water, Waste, Energy Management:
B17: G-Score
B18: S&P Global ESG Score
B19: Environmental
B20: Social
B21: Governance & Economic
B22: Sustainalytics
B23: ISS ESG Corporate Rating
B24: SDG Impact Rating
B25: Governance Quality Score
B26: MSCI ESG Ratings
B29: Industry ESG Overview:
E33: ENVIRONMENTAL
G35: Overview | H35: Targets | K35: Improvements | O35: Comments
E36: GHG (or CO2) Scope 1 Emissions
E38: Water Consumption
E40: Energy Consumption
E42: Waste Management
E44: Other
E46: SOCIAL
B48: Important Sources: | G48: Overview | H48: Targets | K48: Improvements | O48: Comments
B49: Annual Report | E49: Employee Turnover %
B50: Sustainability Report | D50: .
B51: Proxy Statement | D51: . | E51: Salaries & Compensation
E53: Reputation
E55: Discrimination Events
E57: Work Safety
E59: Damage to consumer health
E61: Pension Plan
E63: Supply chain
E65: Community involvement
E67: Public Sector
E69: Litigation
E71: GOVERNANCE
G73: Overview | H73: Targets | K73: Improvements | O73: Comments
E74: Diversity (Gender, Age, Industry, Region)
E76: % Independence
E78: Average time as independent directors
E80: Departures of C-level executives
E82: CEO/Chairman duality
E84: Transparency when reporting
E86: Time taken to report
E88: CEO or Chairman in other boards?
E90: Audit / Consulting
E92: ESG-compensation related
E94: Management compensation schemes

Sheet ESG Inputs
B2: ESG Inputs
A4: x | B4: Total GHG Scope 1 Emissions | G4: 2014 | H4: =+G4+1 -> 2015 | I4: =+H4+1 -> 2016 | J4: =+I4+1 -> 2017 | K4: =+J4+1 -> 2018 | L4: =+K4+1 -> 2019 | M4: =+L4+1 -> 2020 | N4: =+M4+1 -> 2021 | O4: =+N4+1 -> 2022 | ... Q4: =+P4+1 -> 2024 | R4: ="CAGR "&$G$4&" - "&$Q$4 -> CAGR 2014 - 2024
B6: =+Peers!B6 -> ADVANCED MICRO DEVICES, INC. | R6: =IFERROR((Q6/G6)^(1/COUNT($G$4:$Q$4))-1,"")
B7: =+Peers!B8 | R7: =IFERROR((Q7/G7)^(1/COUNT($G$4:$Q$4))-1,"")
B8: =+Peers!B9 | R8: =IFERROR((Q8/G8)^(1/COUNT($G$4:$Q$4))-1,"")
B9: =+Peers!B10 | R9: =IFERROR((Q9/G9)^(1/COUNT($G$4:$Q$4))-1,"")
B10: =+Peers!B11 | R10: =IFERROR((Q10/G10)^(1/COUNT($G$4:$Q$4))-1,"")
B11: =+Peers!B12 | R11: =IFERROR((Q11/G11)^(1/COUNT($G$4:$Q$4))-1,"")
B12: =+Peers!B13 | R12: =IFERROR((Q12/G12)^(1/COUNT($G$4:$Q$4))-1,"")
B13: =+Peers!B14 | R13: =IFERROR((Q13/G13)^(1/COUNT($G$4:$Q$4))-1,"")
B14: =+Peers!B15 | R14: =IFERROR((Q14/G14)^(1/COUNT($G$4:$Q$4))-1,"")
B15: =+Peers!B16 | R15: =IFERROR((Q15/G15)^(1/COUNT($G$4:$Q$4))-1,"")
B16: =+Peers!B17 | R16: =IFERROR((Q16/G16)^(1/COUNT($G$4:$Q$4))-1,"")
A18: x | B18: Total GHG Scope 2 (Location-Based) Emissions | G18: 2014 | H18: =+G18+1 -> 2015 | I18: =+H18+1 -> 2016 | J18: =+I18+1 -> 2017 | K18: =+J18+1 -> 2018 | L18: =+K18+1 -> 2019 | M18: =+L18+1 -> 2020 | N18: =+M18+1 -> 2021 | O18: =+N18+1 -> 2022 | ... Q18: =+P18+1 -> 2024 | R18: ="CAGR "&$G$4&" - "&$Q$4 -> CAGR 2014 - 2024
B20: =+$B$6 -> ADVANCED MICRO DEVICES, INC. | R20: =IFERROR((Q20/G20)^(1/COUNT($G$4:$Q$4))-1,"")
B21: =+$B$7 | R21: =IFERROR((Q21/G21)^(1/COUNT($G$4:$Q$4))-1,"")
B22: =+$B$8 | R22: =IFERROR((Q22/G22)^(1/COUNT($G$4:$Q$4))-1,"")
B23: =+$B$9 | R23: =IFERROR((Q23/G23)^(1/COUNT($G$4:$Q$4))-1,"")
B24: =+$B$10 | R24: =IFERROR((Q24/G24)^(1/COUNT($G$4:$Q$4))-1,"")
B25: =+$B$11 | R25: =IFERROR((Q25/G25)^(1/COUNT($G$4:$Q$4))-1,"")
B26: =+$B$12 | R26: =IFERROR((Q26/G26)^(1/COUNT($G$4:$Q$4))-1,"")
B27: =+$B$13 | R27: =IFERROR((Q27/G27)^(1/COUNT($G$4:$Q$4))-1,"")
B28: =+$B$14 | R28: =IFERROR((Q28/G28)^(1/COUNT($G$4:$Q$4))-1,"")
B29: =+$B$15 | R29: =IFERROR((Q29/G29)^(1/COUNT($G$4:$Q$4))-1,"")
B30: =+$B$16 | R30: =IFERROR((Q30/G30)^(1/COUNT($G$4:$Q$4))-1,"")
A32: x | B32: Total Energy Usage | G32: 2014 | H32: =+G32+1 -> 2015 | I32: =+H32+1 -> 2016 | J32: =+I32+1 -> 2017 | K32: =+J32+1 -> 2018 | L32: =+K32+1 -> 2019 | M32: =+L32+1 -> 2020 | N32: =+M32+1 -> 2021 | O32: =+N32+1 -> 2022 | ... Q32: =+P32+1 -> 2024 | R32: ="CAGR "&$G$4&" - "&$Q$4 -> CAGR 2014 - 2024
B34: =+$B$6 -> ADVANCED MICRO DEVICES, INC. | R34: =IFERROR((Q34/G34)^(1/COUNT($G$4:$Q$4))-1,"")
B35: =+$B$7 | R35: =IFERROR((Q35/G35)^(1/COUNT($G$4:$Q$4))-1,"")
B36: =+$B$8 | R36: =IFERROR((Q36/G36)^(1/COUNT($G$4:$Q$4))-1,"")
B37: =+$B$9 | R37: =IFERROR((Q37/G37)^(1/COUNT($G$4:$Q$4))-1,"")
B38: =+$B$10 | R38: =IFERROR((Q38/G38)^(1/COUNT($G$4:$Q$4))-1,"")
B39: =+$B$11 | R39: =IFERROR((Q39/G39)^(1/COUNT($G$4:$Q$4))-1,"")
B40: =+$B$12 | R40: =IFERROR((Q40/G40)^(1/COUNT($G$4:$Q$4))-1,"")
B41: =+$B$13 | R41: =IFERROR((Q41/G41)^(1/COUNT($G$4:$Q$4))-1,"")
B42: =+$B$14 | R42: =IFERROR((Q42/G42)^(1/COUNT($G$4:$Q$4))-1,"")
B43: =+$B$15 | R43: =IFERROR((Q43/G43)^(1/COUNT($G$4:$Q$4))-1,"")
B44: =+$B$16 | R44: =IFERROR((Q44/G44)^(1/COUNT($G$4:$Q$4))-1,"")
A46: x | B46: Total Water Consumption | G46: 2014 | H46: =+G46+1 -> 2015 | I46: =+H46+1 -> 2016 | J46: =+I46+1 -> 2017 | K46: =+J46+1 -> 2018 | L46: =+K46+1 -> 2019 | M46: =+L46+1 -> 2020 | N46: =+M46+1 -> 2021 | O46: =+N46+1 -> 2022 | ... Q46: =+P46+1 -> 2024 | R46: ="CAGR "&$G$4&" - "&$Q$4 -> CAGR 2014 - 2024
B48: =+$B$6 -> ADVANCED MICRO DEVICES, INC. | R48: =IFERROR((Q48/G48)^(1/COUNT($G$4:$Q$4))-1,"")
B49: =+$B$7 | R49: =IFERROR((Q49/G49)^(1/COUNT($G$4:$Q$4))-1,"")
B50: =+$B$8 | R50: =IFERROR((Q50/G50)^(1/COUNT($G$4:$Q$4))-1,"")
B51: =+$B$9 | R51: =IFERROR((Q51/G51)^(1/COUNT($G$4:$Q$4))-1,"")
B52: =+$B$10 | R52: =IFERROR((Q52/G52)^(1/COUNT($G$4:$Q$4))-1,"")
B53: =+$B$11 | R53: =IFERROR((Q53/G53)^(1/COUNT($G$4:$Q$4))-1,"")
B54: =+$B$12 | R54: =IFERROR((Q54/G54)^(1/COUNT($G$4:$Q$4))-1,"")
B55: =+$B$13 | R55: =IFERROR((Q55/G55)^(1/COUNT($G$4:$Q$4))-1,"")
B56: =+$B$14 | R56: =IFERROR((Q56/G56)^(1/COUNT($G$4:$Q$4))-1,"")
B57: =+$B$15 | R57: =IFERROR((Q57/G57)^(1/COUNT($G$4:$Q$4))-1,"")
B58: =+$B$16 | R58: =IFERROR((Q58/G58)^(1/COUNT($G$4:$Q$4))-1,"")
A60: x | B60: Total Waste Production | G60: 2014 | H60: =+G60+1 -> 2015 | I60: =+H60+1 -> 2016 | J60: =+I60+1 -> 2017 | K60: =+J60+1 -> 2018 | L60: =+K60+1 -> 2019 | M60: =+L60+1 -> 2020 | N60: =+M60+1 -> 2021 | O60: =+N60+1 -> 2022 | ... Q60: =+P60+1 -> 2024 | R60: ="CAGR "&$G$4&" - "&$Q$4 -> CAGR 2014 - 2024
B62: =+$B$6 -> ADVANCED MICRO DEVICES, INC. | R62: =IFERROR((Q62/G62)^(1/COUNT($G$4:$Q$4))-1,"")
B63: =+$B$7 | R63: =IFERROR((Q63/G63)^(1/COUNT($G$4:$Q$4))-1,"")
B64: =+$B$8 | R64: =IFERROR((Q64/G64)^(1/COUNT($G$4:$Q$4))-1,"")
B65: =+$B$9 | R65: =IFERROR((Q65/G65)^(1/COUNT($G$4:$Q$4))-1,"")
B66: =+$B$10 | R66: =IFERROR((Q66/G66)^(1/COUNT($G$4:$Q$4))-1,"")
B67: =+$B$11 | R67: =IFERROR((Q67/G67)^(1/COUNT($G$4:$Q$4))-1,"")
B68: =+$B$12 | R68: =IFERROR((Q68/G68)^(1/COUNT($G$4:$Q$4))-1,"")
B69: =+$B$13 | R69: =IFERROR((Q69/G69)^(1/COUNT($G$4:$Q$4))-1,"")
B70: =+$B$14 | R70: =IFERROR((Q70/G70)^(1/COUNT($G$4:$Q$4))-1,"")
B71: =+$B$15 | R71: =IFERROR((Q71/G71)^(1/COUNT($G$4:$Q$4))-1,"")
B72: =+$B$16 | R72: =IFERROR((Q72/G72)^(1/COUNT($G$4:$Q$4))-1,"")
A74: x | B74: GHG Scope 1 and 2 Emissions | G74: 2014 | H74: =+G74+1 -> 2015 | I74: =+H74+1 -> 2016 | J74: =+I74+1 -> 2017 | K74: =+J74+1 -> 2018 | L74: =+K74+1 -> 2019 | M74: =+L74+1 -> 2020 | N74: =+M74+1 -> 2021 | O74: =+N74+1 -> 2022 | ... Q74: =+P74+1 -> 2024 | R74: ="CAGR "&$G$4&" - "&$Q$4 -> CAGR 2014 - 2024
B76: =+$B$6 -> ADVANCED MICRO DEVICES, INC. | G76: =+G6+G20 -> 0 | H76: =+H6+H20 -> 0 | I76: =+I6+I20 -> 0 | J76: =+J6+J20 -> 0 | K76: =+K6+K20 -> 0 | L76: =+L6+L20 -> 0 | M76: =+M6+M20 -> 0 | N76: =+N6+N20 -> 0 | ... Q76: =+Q6+Q20 -> 0 | R76: =IFERROR((Q76/G76)^(1/COUNT($G$4:$Q$4))-1,"")
B77: =+$B$7 | G77: =+G7+G21 -> 0 | H77: =+H7+H21 -> 0 | I77: =+I7+I21 -> 0 | J77: =+J7+J21 -> 0 | K77: =+K7+K21 -> 0 | L77: =+L7+L21 -> 0 | M77: =+M7+M21 -> 0 | N77: =+N7+N21 -> 0 | ... Q77: =+Q7+Q21 -> 0 | R77: =IFERROR((Q77/G77)^(1/COUNT($G$4:$Q$4))-1,"")
B78: =+$B$8 | G78: =+G8+G22 -> 0 | H78: =+H8+H22 -> 0 | I78: =+I8+I22 -> 0 | J78: =+J8+J22 -> 0 | K78: =+K8+K22 -> 0 | L78: =+L8+L22 -> 0 | M78: =+M8+M22 -> 0 | N78: =+N8+N22 -> 0 | ... Q78: =+Q8+Q22 -> 0 | R78: =IFERROR((Q78/G78)^(1/COUNT($G$4:$Q$4))-1,"")
B79: =+$B$9 | G79: =+G9+G23 -> 0 | H79: =+H9+H23 -> 0 | I79: =+I9+I23 -> 0 | J79: =+J9+J23 -> 0 | K79: =+K9+K23 -> 0 | L79: =+L9+L23 -> 0 | M79: =+M9+M23 -> 0 | N79: =+N9+N23 -> 0 | ... Q79: =+Q9+Q23 -> 0 | R79: =IFERROR((Q79/G79)^(1/COUNT($G$4:$Q$4))-1,"")
B80: =+$B$10 | G80: =+G10+G24 -> 0 | H80: =+H10+H24 -> 0 | I80: =+I10+I24 -> 0 | J80: =+J10+J24 -> 0 | K80: =+K10+K24 -> 0 | L80: =+L10+L24 -> 0 | M80: =+M10+M24 -> 0 | N80: =+N10+N24 -> 0 | ... Q80: =+Q10+Q24 -> 0 | R80: =IFERROR((Q80/G80)^(1/COUNT($G$4:$Q$4))-1,"")
B81: =+$B$11 | G81: =+G11+G25 -> 0 | H81: =+H11+H25 -> 0 | I81: =+I11+I25 -> 0 | J81: =+J11+J25 -> 0 | K81: =+K11+K25 -> 0 | L81: =+L11+L25 -> 0 | M81: =+M11+M25 -> 0 | N81: =+N11+N25 -> 0 | ... Q81: =+Q11+Q25 -> 0 | R81: =IFERROR((Q81/G81)^(1/COUNT($G$4:$Q$4))-1,"")
B82: =+$B$12 | G82: =+G12+G26 -> 0 | H82: =+H12+H26 -> 0 | I82: =+I12+I26 -> 0 | J82: =+J12+J26 -> 0 | K82: =+K12+K26 -> 0 | L82: =+L12+L26 -> 0 | M82: =+M12+M26 -> 0 | N82: =+N12+N26 -> 0 | ... Q82: =+Q12+Q26 -> 0 | R82: =IFERROR((Q82/G82)^(1/COUNT($G$4:$Q$4))-1,"")
B83: =+$B$13 | G83: =+G13+G27 -> 0 | H83: =+H13+H27 -> 0 | I83: =+I13+I27 -> 0 | J83: =+J13+J27 -> 0 | K83: =+K13+K27 -> 0 | L83: =+L13+L27 -> 0 | M83: =+M13+M27 -> 0 | N83: =+N13+N27 -> 0 | ... Q83: =+Q13+Q27 -> 0 | R83: =IFERROR((Q83/G83)^(1/COUNT($G$4:$Q$4))-1,"")
B84: =+$B$14 | G84: =+G14+G28 -> 0 | H84: =+H14+H28 -> 0 | I84: =+I14+I28 -> 0 | J84: =+J14+J28 -> 0 | K84: =+K14+K28 -> 0 | L84: =+L14+L28 -> 0 | M84: =+M14+M28 -> 0 | N84: =+N14+N28 -> 0 | ... Q84: =+Q14+Q28 -> 0 | R84: =IFERROR((Q84/G84)^(1/COUNT($G$4:$Q$4))-1,"")
B85: =+$B$15 | G85: =+G15+G29 -> 0 | H85: =+H15+H29 -> 0 | I85: =+I15+I29 -> 0 | J85: =+J15+J29 -> 0 | K85: =+K15+K29 -> 0 | L85: =+L15+L29 -> 0 | M85: =+M15+M29 -> 0 | N85: =+N15+N29 -> 0 | ... Q85: =+Q15+Q29 -> 0 | R85: =IFERROR((Q85/G85)^(1/COUNT($G$4:$Q$4))-1,"")
B86: =+$B$16 | G86: =+G16+G30 -> 0 | H86: =+H16+H30 -> 0 | I86: =+I16+I30 -> 0 | J86: =+J16+J30 -> 0 | K86: =+K16+K30 -> 0 | L86: =+L16+L30 -> 0 | M86: =+M16+M30 -> 0 | N86: =+N16+N30 -> 0 | ... Q86: =+Q16+Q30 -> 0 | R86: =IFERROR((Q86/G86)^(1/COUNT($G$4:$Q$4))-1,"")

Sheet DCF
B2: DCF
A4: x | B4: Key Assumptions | R4: #VALUE!
B6: Switches | E6: Bear Case | H6: Base Case | K6: Bull Case | X6: FCFF | Y6: FCFE | Z6: Tax Shield | AA6: Total Payout | AB6: NOPAT | AC6: Debt Borrowing | AD6: Cash Balance | AE6: Total Assets | AF6: Total Liabilities | AG6: Shareholder's Equity | AH6: Current Liabilities | AI6: Current Assets
B7: Revenue | C7: 2 | E7: Revenue | F7: -0.02 | H7: Revenue | K7: Revenue | L7: 0.02 | S7: Most Recent Fiscal Year | W7: 2022 | X7: =+E192 | Y7: =+E244 -> 0 | Z7: =+H216 | AA7: =+E257 -> 0 | AB7: =+E182 | AC7: =+E242 -> 0 | AD7: =+E88 -> 0
B8: EBIT | C8: 2 | E8: EBIT | F8: -0.01 | H8: EBIT | K8: EBIT | L8: 0.01 | S8: End of Fiscal Year | W8: =+W7+1 -> 2023 | X8: =+F192 | Y8: =+F244 -> 0 | Z8: =+I216 | AA8: =+F257 -> 0 | AB8: =+F182 | AC8: =+F242 -> 0 | AD8: =+F88 -> 0
B9: WACC | C9: 2 | E9: WACC | F9: =IFERROR(+I9+0.5%,"") | H9: WACC | I9: =WACC!G25 | K9: WACC | L9: =IFERROR(I9-0.5%,"") | S9: Most Recent Quarter End Date | W9: =+W8+1 -> 2024 | X9: =+G192 | Y9: =+G244 -> 0 | Z9: =+J216 | AA9: =+G257 -> 0 | AB9: =+G182 | AC9: =+G242 -> 0 | AD9: =+G88 -> 0 | AE9: =Inputs!Q48 -> 0 | AF9: =+Inputs!Q60 -> 0 | AG9: =+AE9-AF9 -> 0 | AH9: =+Inputs!Q54 -> 0 | AI9: =+Inputs!Q38 -> 0
B10: TGR | C10: 2 | E10: TGR | F10: =+I10-0.5% -> -0.005 | H10: TGR | K10: TGR | L10: =+I10+0.5% -> 0.005 | S10: Valuation Date | W10: =+W9+1 -> 2025 | X10: =+H192 | Y10: =+H244 | Z10: =+K216 | AA10: =+H257 | AB10: =+H182 | AC10: =+H242 -> 0 | AD10: =+H88 | AE10: =Inputs!Q48+DCF!H88+DCF!H90+DCF!H93+DCF!H96+DCF!H99+DCF!H105-DCF!G88-DCF!G90-DCF!G93-DCF!G96-DCF!G99-DCF!G105 -> #VALUE! | AF10: =+Inputs!Q60+(DCF!H110+DCF!H113+DCF!H116+DCF!H118*DCF!G110*DCF!G113*DCF!G116*DCF!G118) -> #VALUE! | AG10: =+AE10-AF10 -> #VALUE! | AH10: =+AH9+H110+H113-G110-G113 -> #VALUE! | AI10: =+H88+H90+H93+H96 -> #VALUE!
W11: =+W10+1 -> 2026 | X11: =+I192 | Y11: =+I244 | Z11: =+L216 | AA11: =+I257 | AB11: =+I182 | AC11: =+I242 | AD11: =+I88 | AE11: =AE10+DCF!I88+DCF!I90+DCF!I93+DCF!I96+DCF!I99+DCF!I105-DCF!H88-DCF!H90-DCF!H93-DCF!H96-DCF!H99-DCF!H105 -> #VALUE! | AF11: =AF10+(DCF!I110+DCF!I113+DCF!I116+DCF!I118*DCF!H110*DCF!H113*DCF!H116*DCF!H118) -> #VALUE! | AG11: =+AE11-AF11 -> #VALUE! | AH11: =+AH10+I110+I113-H110-H113 -> #VALUE! | AI11: =+I88+I90+I93+I96 -> #VALUE!
B12: WACC | C12: =CHOOSE(C9,F9,I9,L9) | W12: =+W11+1 -> 2027 | X12: =+J192 | Y12: =+J244 | Z12: =+M216 | AA12: =+J257 | AB12: =+J182 | AC12: =+J242 | AD12: =+J88
B13: TGR | C13: =CHOOSE(C10,F10,I10,L10) -> 0 | W13: =+W12+1 -> 2028 | X13: =+K192 | Y13: =+K244 | Z13: =+N216 | AA13: =+K257 | AB13: =+K182 | AC13: =+K242 | AD13: =+K88
W14: =+W13+1 -> 2029 | X14: =+L192 | Y14: =+L244 | Z14: =+O216 | AA14: =+L257 | AB14: =+L182 | AC14: =+L242 | AD14: =+L88
A15: x | B15: Operating Assumptions | E15: 2022 | F15: =+E15+1 -> 2023 | G15: =+F15+1 -> 2024 | H15: =+G15+1 -> 2025 | I15: =+H15+1 -> 2026 | J15: =+I15+1 -> 2027 | K15: =+J15+1 -> 2028 | L15: =+K15+1 -> 2029 | M15: =+L15+1 -> 2030 | ... Q15: =+P15+1 -> 2034
B17: Number of Locations (Beginning)
B18: Net Locations Opened/Acquired
B19: Capex per Net Additions
B20: Locations Opened/Acquired
B21: Locations Closed/Sold
B22: Number of Locations (End)
B23: Average Sales per Location
B24: Same Store Sales Growth
B25: Beginning Locations Total Sales
B26: New Locations Total Sales (Estimate)
B27: In millions of USD
A28: x | B28: Income Statement | E28: 2022 | F28: =+E28+1 -> 2023 | G28: =+F28+1 -> 2024 | H28: =+G28+1 -> 2025 | I28: =+H28+1 -> 2026 | J28: =+I28+1 -> 2027 | K28: =+J28+1 -> 2028 | L28: =+K28+1 -> 2029 | M28: =+L28+1 -> 2030 | ... Q28: =+P28+1 -> 2034
B30: Revenue (Sales) | D30: =+_xlfn.XLOOKUP($B30,Inputs!$B:$B,Inputs!N:N) -> 0 | E30: =+_xlfn.XLOOKUP($B30,Inputs!$B:$B,Inputs!O:O) -> 0 | F30: =+_xlfn.XLOOKUP($B30,Inputs!$B:$B,Inputs!P:P) -> 0 | G30: =+_xlfn.XLOOKUP($B30,Inputs!$B:$B,Inputs!Q:Q) -> 0 | H30: =+H25+H26 -> 0 | I30: =+I25+I26 -> 0 | J30: =+J25+J26 -> 0 | K30: =+K25+K26 -> 0 | L30: =+L25+L26 -> 0 | M30: =+M25+M26 -> 0 | N30: =+N25+N26 -> 0 | O30: =+O25+O26 -> 0 | ... Q30: =+Q25+Q26 -> 0
B31: % of growth | E31: =IFERROR((E30-D30)/D30,"") | F31: =IFERROR((F30-E30)/E30,"") | G31: =IFERROR((G30-F30)/F30,"") | H31: =IFERROR(H30/G30-1,"") | I31: =IFERROR(I30/H30-1,"") | J31: =IFERROR(J30/I30-1,"") | K31: =IFERROR(K30/J30-1,"") | L31: =IFERROR(L30/K30-1,"") | M31: =IFERROR(M30/L30-1,"") | N31: =IFERROR(N30/M30-1,"") | O31: =IFERROR(O30/N30-1,"") | ... Q31: =IFERROR(Q30/P30-1,"")
B33: COGS (Cost of Goods Sold) | E33: =+_xlfn.XLOOKUP($B33,Inputs!$B:$B,Inputs!O:O) -> 0 | F33: =+_xlfn.XLOOKUP($B33,Inputs!$B:$B,Inputs!P:P) -> 0 | G33: =+_xlfn.XLOOKUP($B33,Inputs!$B:$B,Inputs!Q:Q) -> 0 | H33: =H34*H$30 -> 0 | I33: =I34*I$30 -> 0 | J33: =J34*J$30 -> 0 | K33: =K34*K$30 -> 0 | L33: =L34*L$30 -> 0 | M33: =M34*M$30 -> 0 | N33: =N34*N$30 -> 0 | O33: =O34*O$30 -> 0 | ... Q33: =Q34*Q$30 -> 0
B34: % of revenue | E34: =IFERROR(E33/E$30,"") | F34: =IFERROR(F33/F$30,"") | G34: =IFERROR(G33/G$30,"")
B36: Gross Profit | E36: =+_xlfn.XLOOKUP($B36,Inputs!$B:$B,Inputs!O:O) -> 0 | F36: =+_xlfn.XLOOKUP($B36,Inputs!$B:$B,Inputs!P:P) -> 0 | G36: =+_xlfn.XLOOKUP($B36,Inputs!$B:$B,Inputs!Q:Q) -> 0 | H36: =+H30-H33 -> 0 | I36: =+I30-I33 -> 0 | J36: =+J30-J33 -> 0 | K36: =+K30-K33 -> 0 | L36: =+L30-L33 -> 0 | M36: =+M30-M33 -> 0 | N36: =+N30-N33 -> 0 | O36: =+O30-O33 -> 0 | ... Q36: =+Q30-Q33 -> 0
B37: Gross Profit Margin | E37: =IFERROR(E36/E$30,"") | F37: =IFERROR(F36/F$30,"") | G37: =IFERROR(G36/G$30,"") | H37: =IFERROR(H36/H$30,"") | I37: =IFERROR(I36/I$30,"") | J37: =IFERROR(J36/J$30,"") | K37: =IFERROR(K36/K$30,"") | L37: =IFERROR(L36/L$30,"") | ... Q37: =IFERROR(Q36/Q$30,"")
B39: SG&A (Selling, General & Administrative) | E39: =+_xlfn.XLOOKUP($B39,Inputs!$B:$B,Inputs!O:O) -> 0 | F39: =+_xlfn.XLOOKUP($B39,Inputs!$B:$B,Inputs!P:P) -> 0 | G39: =+_xlfn.XLOOKUP($B39,Inputs!$B:$B,Inputs!Q:Q) -> 0 | H39: =IFERROR(G39*(1+H31),"") | I39: =IFERROR(H39*(1+I31),"") | J39: =IFERROR(I39*(1+J31),"") | K39: =IFERROR(J39*(1+K31),"") | L39: =IFERROR(K39*(1+L31),"") | M39: =IFERROR(L39*(1+M31),"") | N39: =IFERROR(M39*(1+N31),"") | O39: =IFERROR(N39*(1+O31),"") | ... Q39: =IFERROR(P39*(1+Q31),"")
B40: SG&A Margin | E40: =IFERROR(E39/E$30,"") | F40: =IFERROR(F39/F$30,"") | G40: =IFERROR(G39/G$30,"") | H40: =IFERROR(AVERAGE(E40:G40),"") | I40: =IFERROR(AVERAGE(F40:H40),"") | J40: =IFERROR(AVERAGE(G40:I40),"") | K40: =IFERROR(AVERAGE(H40:J40),"") | L40: =IFERROR(AVERAGE(I40:K40),"") | M40: =IFERROR(AVERAGE(J40:L40),"") | N40: =IFERROR(AVERAGE(K40:M40),"") | O40: =IFERROR(AVERAGE(L40:N40),"") | ... Q40: =IFERROR(AVERAGE(N40:P40),"")
B42: R&D (Research & Development) | E42: =+_xlfn.XLOOKUP($B42,Inputs!$B:$B,Inputs!O:O) -> 0 | F42: =+_xlfn.XLOOKUP($B42,Inputs!$B:$B,Inputs!P:P) -> 0 | G42: =+_xlfn.XLOOKUP($B42,Inputs!$B:$B,Inputs!Q:Q) -> 0 | H42: =H43*H$30 -> 0 | I42: =I43*I$30 -> 0 | J42: =J43*J$30 -> 0 | K42: =K43*K$30 -> 0 | L42: =L43*L$30 -> 0 | M42: =M43*M$30 -> 0 | N42: =N43*N$30 -> 0 | O42: =O43*O$30 -> 0 | ... Q42: =Q43*Q$30 -> 0
B43: % of revenue | E43: =IFERROR(E42/E30,"") | F43: =IFERROR(F42/F30,"") | G43: =IFERROR(G42/G30,"")
B45: Other Operating (Income) Expenses | E45: =+_xlfn.XLOOKUP($B45,Inputs!$B:$B,Inputs!O:O) -> 0 | F45: =+_xlfn.XLOOKUP($B45,Inputs!$B:$B,Inputs!P:P) -> 0 | G45: =+_xlfn.XLOOKUP($B45,Inputs!$B:$B,Inputs!Q:Q) -> 0 | H45: =IFERROR(AVERAGE(E45:G45)*(1+H31),"") | I45: =IFERROR(AVERAGE(F45:H45)*(1+I31),"") | J45: =IFERROR(AVERAGE(G45:I45)*(1+J31),"") | K45: =IFERROR(AVERAGE(H45:J45)*(1+K31),"") | L45: =IFERROR(AVERAGE(I45:K45)*(1+L31),"") | M45: =IFERROR(AVERAGE(J45:L45)*(1+M31),"") | N45: =IFERROR(AVERAGE(K45:M45)*(1+N31),"") | O45: =IFERROR(AVERAGE(L45:N45)*(1+O31),"") | ... Q45: =IFERROR(AVERAGE(N45:P45)*(1+Q31),"")
B47: EBITDA | E47: =+_xlfn.XLOOKUP($B47,Inputs!$B:$B,Inputs!O:O) -> 0 | F47: =+_xlfn.XLOOKUP($B47,Inputs!$B:$B,Inputs!P:P) -> 0 | G47: =+_xlfn.XLOOKUP($B47,Inputs!$B:$B,Inputs!Q:Q) -> 0 | H47: =IFERROR(H36-H39-H42-H45,"") | I47: =IFERROR(I36-I39-I42-I45,"") | J47: =IFERROR(J36-J39-J42-J45,"") | K47: =IFERROR(K36-K39-K42-K45,"") | L47: =IFERROR(L36-L39-L42-L45,"") | M47: =IFERROR(M36-M39-M42-M45,"") | N47: =IFERROR(N36-N39-N42-N45,"") | O47: =IFERROR(O36-O39-O42-O45,"") | ... Q47: =IFERROR(Q36-Q39-Q42-Q45,"")
B48: EBITDA Margin | E48: =IFERROR(E47/E$30,"") | F48: =IFERROR(F47/F$30,"") | G48: =IFERROR(G47/G$30,"") | H48: =IFERROR(H47/H$30,"") | I48: =IFERROR(I47/I$30,"") | J48: =IFERROR(J47/J$30,"") | K48: =IFERROR(K47/K$30,"") | L48: =IFERROR(L47/L$30,"") | ... Q48: =IFERROR(Q47/Q$30,"")
B50: D&A (Depreciation & Amortization) | E50: =+_xlfn.XLOOKUP($B50,Inputs!$B:$B,Inputs!O:O) -> 0 | F50: =+_xlfn.XLOOKUP($B50,Inputs!$B:$B,Inputs!P:P) -> 0 | G50: =+_xlfn.XLOOKUP($B50,Inputs!$B:$B,Inputs!Q:Q) -> 0 | H50: =+IFERROR(H53+H56,"") | I50: =+IFERROR(I53+I56,"") | J50: =+IFERROR(J53+J56,"") | K50: =+IFERROR(K53+K56,"") | L50: =+IFERROR(L53+L56,"") | M50: =+IFERROR(M53+M56,"") | N50: =+IFERROR(N53+N56,"") | O50: =+IFERROR(O53+O56,"") | ... Q50: =+IFERROR(Q53+Q56,"")
B51: % of PP&E+ROU Assets+Intangibles excl. Goodwill | E51: =IFERROR(E50/AVERAGE(Inputs!O39+Inputs!O42+Inputs!O44,Inputs!N39+Inputs!N42+Inputs!N44),"") | F51: =IFERROR(F50/AVERAGE(Inputs!P39+Inputs!P42+Inputs!P44,Inputs!O39+Inputs!O42+Inputs!O44),"") | G51: =IFERROR(G50/AVERAGE(Inputs!Q39+Inputs!Q42+Inputs!Q44,Inputs!P39+Inputs!P42+Inputs!P44),"") | H51: =IFERROR(H50/(G99+G105),"") | I51: =IFERROR(I50/(H99+H105),"") | J51: =IFERROR(J50/(I99+I105),"") | K51: =IFERROR(K50/(J99+J105),"") | L51: =IFERROR(L50/(K99+K105),"") | M51: =IFERROR(M50/(L99+L105),"") | N51: =IFERROR(N50/(M99+M105),"") | O51: =IFERROR(O50/(N99+N105),"") | ... Q51: =IFERROR(Q50/(P99+P105),"")
B53: Depreciation Expense | E53: =+_xlfn.XLOOKUP($B53,Inputs!$B:$B,Inputs!O:O) -> 0 | F53: =+_xlfn.XLOOKUP($B53,Inputs!$B:$B,Inputs!P:P) -> 0 | G53: =+_xlfn.XLOOKUP($B53,Inputs!$B:$B,Inputs!Q:Q) -> 0 | H53: =IFERROR(H54*(G100+G101),"") | I53: =IFERROR(I54*(H100+H101),"") | J53: =IFERROR(J54*(I100+I101),"") | K53: =IFERROR(K54*(J100+J101),"") | L53: =IFERROR(L54*(K100+K101),"") | M53: =IFERROR(M54*(L100+L101),"") | N53: =IFERROR(N54*(M100+M101),"") | O53: =IFERROR(O54*(N100+N101),"") | ... Q53: =IFERROR(Q54*(P100+P101),"")
B54: % of PP&E+ROU Assets | E54: =IFERROR(E53/AVERAGE(Inputs!O40+Inputs!O42,Inputs!N40+Inputs!N42),"") | F54: =IFERROR(F53/AVERAGE(Inputs!P40+Inputs!P42,Inputs!O40+Inputs!O42),"") | G54: =IFERROR(G53/AVERAGE(Inputs!Q40+Inputs!Q42,Inputs!P40+Inputs!P42),"") | H54: =IFERROR(AVERAGE(E54:G54),"") | I54: =IFERROR(AVERAGE(F54:H54),"") | J54: =IFERROR(AVERAGE(G54:I54),"") | K54: =IFERROR(AVERAGE(H54:J54),"") | L54: =IFERROR(AVERAGE(I54:K54),"") | M54: =IFERROR(AVERAGE(J54:L54),"") | N54: =IFERROR(AVERAGE(K54:M54),"") | O54: =IFERROR(AVERAGE(L54:N54),"") | ... Q54: =IFERROR(AVERAGE(N54:P54),"")
B56: Amortization Expense | E56: =+_xlfn.XLOOKUP($B56,Inputs!$B:$B,Inputs!O:O) -> 0 | F56: =+_xlfn.XLOOKUP($B56,Inputs!$B:$B,Inputs!P:P) -> 0 | G56: =+_xlfn.XLOOKUP($B56,Inputs!$B:$B,Inputs!Q:Q) -> 0 | H56: =+H57*G105 -> 0 | I56: =+I57*H105 -> 0 | J56: =+J57*I105 -> 0 | K56: =+K57*J105 -> 0 | L56: =+L57*K105 -> 0 | M56: =+M57*L105 -> 0 | N56: =+N57*M105 -> 0 | O56: =+O57*N105 -> 0 | ... Q56: =+Q57*P105 -> 0
B57: % of Intangibles excl. Goodwill | E57: =IFERROR(E56/AVERAGE(Inputs!N45:O45),"") | F57: =IFERROR(F56/AVERAGE(Inputs!O45:P45),"") | G57: =IFERROR(G56/AVERAGE(Inputs!P45:Q45),"")
B59: Operating Income (EBIT) | E59: =+_xlfn.XLOOKUP($B59,Inputs!$B:$B,Inputs!O:O) -> 0 | F59: =+_xlfn.XLOOKUP($B59,Inputs!$B:$B,Inputs!P:P) -> 0 | G59: =+_xlfn.XLOOKUP($B59,Inputs!$B:$B,Inputs!Q:Q) -> 0 | H59: =+IFERROR(H47-H50,"") | I59: =+IFERROR(I47-I50,"") | J59: =+IFERROR(J47-J50,"") | K59: =+IFERROR(K47-K50,"") | L59: =+IFERROR(L47-L50,"") | M59: =+IFERROR(M47-M50,"") | N59: =+IFERROR(N47-N50,"") | O59: =+IFERROR(O47-O50,"") | ... Q59: =+IFERROR(Q47-Q50,"")
B60: Operating Margin | E60: =IFERROR(E59/E$30,"") | F60: =IFERROR(F59/F$30,"") | G60: =IFERROR(G59/G$30,"") | H60: =IFERROR(H59/H30,"") | I60: =IFERROR(I59/I30,"") | J60: =IFERROR(J59/J30,"") | K60: =IFERROR(K59/K30,"") | L60: =IFERROR(L59/L30,"") | M60: =IFERROR(M59/M30,"") | N60: =IFERROR(N59/N30,"") | O60: =IFERROR(O59/O30,"") | ... Q60: =IFERROR(Q59/Q30,"")
B62: Net Interest Expense (Income) | E62: =+_xlfn.XLOOKUP($B62,Inputs!$B:$B,Inputs!O:O) -> 0 | F62: =+_xlfn.XLOOKUP($B62,Inputs!$B:$B,Inputs!P:P) -> 0 | G62: =+_xlfn.XLOOKUP($B62,Inputs!$B:$B,Inputs!Q:Q) -> 0 | H62: =-H65-H68 -> 0 | I62: =-I65-I68 -> 0 | J62: =-J65-J68 -> 0 | K62: =-K65-K68 -> 0 | L62: =-L65-L68 -> 0 | M62: =-M65-M68 -> 0 | N62: =-N65-N68 -> 0 | O62: =-O65-O68 -> 0 | ... Q62: =-Q65-Q68 -> 0
B63: % of Net Debt | E63: =IFERROR(E62/AVERAGE(Inputs!N116:O116),"") | F63: =IFERROR(F62/AVERAGE(Inputs!O116:P116),"") | G63: =IFERROR(G62/AVERAGE(Inputs!P116:Q116),"") | H63: =IFERROR(H62/AVERAGE(G116+G118,H116+H118),"") | I63: =IFERROR(I62/AVERAGE(H116+H118,I116+I118),"") | J63: =IFERROR(J62/AVERAGE(I116+I118,J116+J118),"") | K63: =IFERROR(K62/AVERAGE(J116+J118,K116+K118),"") | L63: =IFERROR(L62/AVERAGE(K116+K118,L116+L118),"") | M63: =IFERROR(M62/AVERAGE(L116+L118,M116+M118),"") | N63: =IFERROR(N62/AVERAGE(M116+M118,N116+N118),"") | O63: =IFERROR(O62/AVERAGE(N116+N118,O116+O118),"") | ... Q63: =IFERROR(Q62/AVERAGE(P116+P118,Q116+Q118),"")
B65: Interest Expense | E65: =+_xlfn.XLOOKUP($B65,Inputs!$B:$B,Inputs!O:O) -> 0 | F65: =+_xlfn.XLOOKUP($B65,Inputs!$B:$B,Inputs!P:P) -> 0 | G65: =+_xlfn.XLOOKUP($B65,Inputs!$B:$B,Inputs!Q:Q) -> 0
B66: % of Debt | E66: =+IFERROR(E65/AVERAGE(Inputs!N113:O113),"") | F66: =+IFERROR(F65/AVERAGE(Inputs!O113:P113),"") | G66: =+IFERROR(G65/AVERAGE(Inputs!P113:Q113),"")
B68: Interest Income | E68: =+_xlfn.XLOOKUP($B68,Inputs!$B:$B,Inputs!O:O) -> 0 | F68: =+_xlfn.XLOOKUP($B68,Inputs!$B:$B,Inputs!P:P) -> 0 | G68: =+_xlfn.XLOOKUP($B68,Inputs!$B:$B,Inputs!Q:Q) -> 0
B69: % Cash & Cash Eq. & ST Investments | E69: =IFERROR(E68/+AVERAGE(Inputs!N32:O32),"") | F69: =IFERROR(F68/+AVERAGE(Inputs!O32:P32),"") | G69: =IFERROR(G68/+AVERAGE(Inputs!P32:Q32),"")
B71: FX (Gain) Loss | E71: =+_xlfn.XLOOKUP($B71,Inputs!$B:$B,Inputs!O:O) -> 0 | F71: =+_xlfn.XLOOKUP($B71,Inputs!$B:$B,Inputs!P:P) -> 0 | G71: =+_xlfn.XLOOKUP($B71,Inputs!$B:$B,Inputs!Q:Q) -> 0 | H71: =+H72*H$17 -> 0 | I71: =+I72*I$17 -> 0 | J71: =+J72*J$17 -> 0 | K71: =+K72*K$17 -> 0 | L71: =+L72*L$17 -> 0 | M71: =+M72*M$17 -> 0 | N71: =+N72*N$17 -> 0 | O71: =+O72*O$17 -> 0 | ... Q71: =+Q72*Q$17 -> 0
B72: % of revenue
B74: Other Non-Operating (Income) Expenses | E74: =+_xlfn.XLOOKUP($B74,Inputs!$B:$B,Inputs!O:O) -> 0 | F74: =+_xlfn.XLOOKUP($B74,Inputs!$B:$B,Inputs!P:P) -> 0 | G74: =+_xlfn.XLOOKUP($B74,Inputs!$B:$B,Inputs!Q:Q) -> 0 | H74: =IFERROR(AVERAGE(E74:G74)*(1+H31),"") | I74: =IFERROR(AVERAGE(F74:H74)*(1+I31),"") | J74: =IFERROR(AVERAGE(G74:I74)*(1+J31),"") | K74: =IFERROR(AVERAGE(H74:J74)*(1+K31),"") | L74: =IFERROR(AVERAGE(I74:K74)*(1+L31),"") | M74: =IFERROR(AVERAGE(J74:L74)*(1+M31),"") | N74: =IFERROR(AVERAGE(K74:M74)*(1+N31),"") | O74: =IFERROR(AVERAGE(L74:N74)*(1+O31),"") | ... Q74: =IFERROR(AVERAGE(N74:P74)*(1+Q31),"")
B76: Pre-Tax Income (EBT) | E76: =+_xlfn.XLOOKUP($B76,Inputs!$B:$B,Inputs!O:O) -> 0 | F76: =+_xlfn.XLOOKUP($B76,Inputs!$B:$B,Inputs!P:P) -> 0 | G76: =+_xlfn.XLOOKUP($B76,Inputs!$B:$B,Inputs!Q:Q) -> 0 | H76: =IFERROR(+H59-H62-H71-H74,"") | I76: =IFERROR(+I59-I62-I71-I74,"") | J76: =IFERROR(+J59-J62-J71-J74,"") | K76: =IFERROR(+K59-K62-K71-K74,"") | L76: =IFERROR(+L59-L62-L71-L74,"") | M76: =IFERROR(+M59-M62-M71-M74,"") | N76: =IFERROR(+N59-N62-N71-N74,"") | O76: =IFERROR(+O59-O62-O71-O74,"") | ... Q76: =IFERROR(+Q59-Q62-Q71-Q74,"")
B78: Tax Expense (Benefits) | E78: =+_xlfn.XLOOKUP($B78,Inputs!$B:$B,Inputs!O:O) -> 0 | F78: =+_xlfn.XLOOKUP($B78,Inputs!$B:$B,Inputs!P:P) -> 0 | G78: =+_xlfn.XLOOKUP($B78,Inputs!$B:$B,Inputs!Q:Q) -> 0 | H78: =IFERROR(H79*H$59,"") | I78: =IFERROR(I79*I$59,"") | J78: =IFERROR(J79*J$59,"") | K78: =IFERROR(K79*K$59,"") | L78: =IFERROR(L79*L$59,"") | M78: =IFERROR(M79*M$59,"") | N78: =IFERROR(N79*N$59,"") | O78: =IFERROR(O79*O$59,"") | ... Q78: =IFERROR(Q79*Q$59,"")
B79: % of EBT | E79: =IFERROR(E78/E76,"") | F79: =IFERROR(F78/F76,"") | G79: =IFERROR(G78/G76,"") | H79: =IFERROR(AVERAGE(E79:G79),"") | I79: =IFERROR(AVERAGE(F79:H79),"") | J79: =IFERROR(AVERAGE(G79:I79),"") | K79: =IFERROR(AVERAGE(H79:J79),"") | L79: =IFERROR(AVERAGE(I79:K79),"") | M79: =IFERROR(AVERAGE(J79:L79),"") | N79: =IFERROR(AVERAGE(K79:M79),"") | O79: =IFERROR(AVERAGE(L79:N79),"") | ... Q79: =IFERROR(AVERAGE(N79:P79),"")
B81: Net Income | E81: =+_xlfn.XLOOKUP($B81,Inputs!$B:$B,Inputs!O:O) -> 0 | F81: =+_xlfn.XLOOKUP($B81,Inputs!$B:$B,Inputs!P:P) -> 0 | G81: =+_xlfn.XLOOKUP($B81,Inputs!$B:$B,Inputs!Q:Q) -> 0 | H81: =IFERROR(+H76-H78,"") | I81: =IFERROR(+I76-I78,"") | J81: =IFERROR(+J76-J78,"") | K81: =IFERROR(+K76-K78,"") | L81: =IFERROR(+L76-L78,"") | M81: =IFERROR(+M76-M78,"") | N81: =IFERROR(+N76-N78,"") | O81: =IFERROR(+O76-O78,"") | ... Q81: =IFERROR(+Q76-Q78,"")
B82: Net Income Margin | E82: =IFERROR(E81/E$30,"") | F82: =IFERROR(F81/F$30,"") | G82: =IFERROR(G81/G$30,"") | H82: =IFERROR(H81/H$30,"") | I82: =IFERROR(I81/I$30,"") | J82: =IFERROR(J81/J$30,"") | K82: =IFERROR(K81/K$30,"") | L82: =IFERROR(L81/L$30,"") | ... Q82: =IFERROR(Q81/Q$30,"")
A84: x | B84: Balance Sheet | E84: =E28 -> 2022 | F84: =F28 -> 2023 | G84: =G28 -> 2024 | H84: =H28 -> 2025 | I84: =I28 -> 2026 | J84: =J28 -> 2027 | K84: =K28 -> 2028 | L84: =L28 -> 2029 | ... Q84: =Q28 -> 2034
B86: Assets
B88: Cash & Cash Equivalents & ST Investments | E88: =+_xlfn.XLOOKUP($B88,Inputs!$B:$B,Inputs!O:O) -> 0 | F88: =+_xlfn.XLOOKUP($B88,Inputs!$B:$B,Inputs!P:P) -> 0 | G88: =+_xlfn.XLOOKUP($B88,Inputs!$B:$B,Inputs!Q:Q) -> 0 | H88: =IFERROR(G88+H165,"") | I88: =IFERROR(H88+I165,"") | J88: =IFERROR(I88+J165,"") | K88: =IFERROR(J88+K165,"") | L88: =IFERROR(K88+L165,"") | M88: =IFERROR(L88+M165,"") | N88: =IFERROR(M88+N165,"") | O88: =IFERROR(N88+O165,"") | ... Q88: =IFERROR(P88+Q165,"")
B90: Accounts Receivable | E90: =+_xlfn.XLOOKUP($B90,Inputs!$B:$B,Inputs!O:O) -> 0 | F90: =+_xlfn.XLOOKUP($B90,Inputs!$B:$B,Inputs!P:P) -> 0 | G90: =+_xlfn.XLOOKUP($B90,Inputs!$B:$B,Inputs!Q:Q) -> 0 | H90: =IFERROR(H91*H30/365,"") | I90: =IFERROR(I91*I30/365,"") | J90: =IFERROR(J91*J30/365,"") | K90: =IFERROR(K91*K30/365,"") | L90: =IFERROR(L91*L30/365,"") | M90: =IFERROR(M91*M30/365,"") | N90: =IFERROR(N91*N30/365,"") | O90: =IFERROR(O91*O30/365,"") | ... Q90: =IFERROR(Q91*Q30/365,"")
B91: DSO | E91: =IFERROR(E90/E30*365,"") | F91: =IFERROR(F90/F30*365,"") | G91: =IFERROR(G90/G30*366,"") | H91: =IFERROR(AVERAGE(E91:G91),"") | I91: =IFERROR(AVERAGE(F91:H91),"") | J91: =IFERROR(AVERAGE(G91:I91),"") | K91: =IFERROR(AVERAGE(H91:J91),"") | L91: =IFERROR(AVERAGE(I91:K91),"") | M91: =IFERROR(AVERAGE(J91:L91),"") | N91: =IFERROR(AVERAGE(K91:M91),"") | O91: =IFERROR(AVERAGE(L91:N91),"") | ... Q91: =IFERROR(AVERAGE(N91:P91),"")
B93: Inventory | E93: =+_xlfn.XLOOKUP($B93,Inputs!$B:$B,Inputs!O:O) -> 0 | F93: =+_xlfn.XLOOKUP($B93,Inputs!$B:$B,Inputs!P:P) -> 0 | G93: =+_xlfn.XLOOKUP($B93,Inputs!$B:$B,Inputs!Q:Q) -> 0 | H93: =+IFERROR(H94*H33/365,"") | I93: =+IFERROR(I94*I33/365,"") | J93: =+IFERROR(J94*J33/365,"") | K93: =+IFERROR(K94*K33/365,"") | L93: =+IFERROR(L94*L33/365,"") | M93: =+IFERROR(M94*M33/365,"") | N93: =+IFERROR(N94*N33/365,"") | O93: =+IFERROR(O94*O33/365,"") | ... Q93: =+IFERROR(Q94*Q33/365,"")
B94: DIH | E94: =IFERROR(E93/E33*365,"") | F94: =IFERROR(F93/F33*365,"") | G94: =IFERROR(G93/G33*365,"") | H94: =IFERROR(AVERAGE(E94:G94),"") | I94: =IFERROR(AVERAGE(F94:H94),"") | J94: =IFERROR(AVERAGE(G94:I94),"") | K94: =IFERROR(AVERAGE(H94:J94),"") | L94: =IFERROR(AVERAGE(I94:K94),"") | M94: =IFERROR(AVERAGE(J94:L94),"") | N94: =IFERROR(AVERAGE(K94:M94),"") | O94: =IFERROR(AVERAGE(L94:N94),"") | ... Q94: =IFERROR(AVERAGE(N94:P94),"")
B96: Prepaid expenses and Other Current Assets | E96: =+_xlfn.XLOOKUP($B96,Inputs!$B:$B,Inputs!O:O) -> 0 | F96: =+_xlfn.XLOOKUP($B96,Inputs!$B:$B,Inputs!P:P) -> 0 | G96: =+_xlfn.XLOOKUP($B96,Inputs!$B:$B,Inputs!Q:Q) -> 0 | H96: =IFERROR(AVERAGE(E96:G96)*(1+H31),"") | I96: =IFERROR(AVERAGE(F96:H96)*(1+I31),"") | J96: =IFERROR(AVERAGE(G96:I96)*(1+J31),"") | K96: =IFERROR(AVERAGE(H96:J96)*(1+K31),"") | L96: =IFERROR(AVERAGE(I96:K96)*(1+L31),"") | M96: =IFERROR(AVERAGE(J96:L96)*(1+M31),"") | N96: =IFERROR(AVERAGE(K96:M96)*(1+N31),"") | O96: =IFERROR(AVERAGE(L96:N96)*(1+O31),"") | ... Q96: =IFERROR(AVERAGE(N96:P96)*(1+Q31),"")
B97: % of revenue | E97: =IFERROR(E96/E$30,"") | F97: =IFERROR(F96/F$30,"") | G97: =IFERROR(G96/G$30,"") | H97: =IFERROR(AVERAGE(E97:G97),"") | I97: =IFERROR(AVERAGE(F97:H97),"") | J97: =IFERROR(AVERAGE(G97:I97),"") | K97: =IFERROR(AVERAGE(H97:J97),"") | L97: =IFERROR(AVERAGE(I97:K97),"") | M97: =IFERROR(AVERAGE(J97:L97),"") | N97: =IFERROR(AVERAGE(K97:M97),"") | O97: =IFERROR(AVERAGE(L97:N97),"") | ... Q97: =IFERROR(AVERAGE(N97:P97),"")
B99: Net PP&E (Property, Plant and Equipment) + ROU Assets | E99: =+E100+E101-E103 -> 0 | F99: =+F100+F101-F103 -> 0 | G99: =+G100+G101-G103 -> 0 | H99: =IFERROR(H100+H101-H103,"") | I99: =IFERROR(I100+I101-I103,"") | J99: =IFERROR(J100+J101-J103,"") | K99: =IFERROR(K100+K101-K103,"") | L99: =IFERROR(L100+L101-L103,"") | M99: =IFERROR(M100+M101-M103,"") | N99: =IFERROR(N100+N101-N103,"") | O99: =IFERROR(O100+O101-O103,"") | ... Q99: =IFERROR(Q100+Q101-Q103,"")
B100: Gross PP&E (Property, Plant and Equipment) + ROU Assets | E100: =+_xlfn.XLOOKUP("Gross PP&E (Property, Plant and Equipment)",Inputs!$B:$B,Inputs!O:O) -> 0 | F100: =+_xlfn.XLOOKUP("Gross PP&E (Property, Plant and Equipment)",Inputs!$B:$B,Inputs!P:P) -> 0 | G100: =+_xlfn.XLOOKUP("Gross PP&E (Property, Plant and Equipment)",Inputs!$B:$B,Inputs!Q:Q) -> 0 | H100: =+IFERROR(G100-H134,"") | I100: =+IFERROR(H100-I134,"") | J100: =+IFERROR(I100-J134,"") | K100: =+IFERROR(J100-K134,"") | L100: =+IFERROR(K100-L134,"") | M100: =+IFERROR(L100-M134,"") | N100: =+IFERROR(M100-N134,"") | O100: =+IFERROR(N100-O134,"") | ... Q100: =+IFERROR(P100-Q134,"")
B101: Right-of-Use Assets | E101: =+_xlfn.XLOOKUP("Right-of-Use Assets",Inputs!$B:$B,Inputs!O:O) -> 0 | F101: =+_xlfn.XLOOKUP("Right-of-Use Assets",Inputs!$B:$B,Inputs!P:P) -> 0 | G101: =+_xlfn.XLOOKUP("Right-of-Use Assets",Inputs!$B:$B,Inputs!Q:Q) -> 0 | H101: =IFERROR(H102*H$30,"") | I101: =IFERROR(I102*I$30,"") | J101: =IFERROR(J102*J$30,"") | K101: =IFERROR(K102*K$30,"") | L101: =IFERROR(L102*L$30,"") | M101: =IFERROR(M102*M$30,"") | N101: =IFERROR(N102*N$30,"") | O101: =IFERROR(O102*O$30,"") | ... Q101: =IFERROR(Q102*Q$30,"")
B102: % of revenue | E102: =IFERROR(E101/E$30,"") | F102: =IFERROR(F101/F$30,"") | G102: =IFERROR(G101/G$30,"") | H102: =IFERROR(AVERAGE(E102:G102),"") | I102: =IFERROR(AVERAGE(F102:H102),"") | J102: =IFERROR(AVERAGE(G102:I102),"") | K102: =IFERROR(AVERAGE(H102:J102),"") | L102: =IFERROR(AVERAGE(I102:K102),"") | M102: =IFERROR(AVERAGE(J102:L102),"") | N102: =IFERROR(AVERAGE(K102:M102),"") | O102: =IFERROR(AVERAGE(L102:N102),"") | ... Q102: =IFERROR(AVERAGE(N102:P102),"")
B103: Accumulated Depreciation | E103: =+_xlfn.XLOOKUP($B103,Inputs!$B:$B,Inputs!O:O) -> 0 | F103: =+_xlfn.XLOOKUP($B103,Inputs!$B:$B,Inputs!P:P) -> 0 | G103: =+_xlfn.XLOOKUP($B103,Inputs!$B:$B,Inputs!Q:Q) -> 0 | H103: =+IFERROR(G103+H53,"") | I103: =+IFERROR(H103+I53,"") | J103: =+IFERROR(I103+J53,"") | K103: =+IFERROR(J103+K53,"") | L103: =+IFERROR(K103+L53,"") | M103: =+IFERROR(L103+M53,"") | N103: =+IFERROR(M103+N53,"") | O103: =+IFERROR(N103+O53,"") | ... Q103: =+IFERROR(P103+Q53,"")
B105: Intangibles excl. Goodwill | E105: =+_xlfn.XLOOKUP($B105,Inputs!$B:$B,Inputs!O:O) -> 0 | F105: =+_xlfn.XLOOKUP($B105,Inputs!$B:$B,Inputs!P:P) -> 0 | G105: =+_xlfn.XLOOKUP($B105,Inputs!$B:$B,Inputs!Q:Q) -> 0 | H105: =+G105+H106*H42 -> 0 | I105: =+H105+I106*I42 -> 0 | J105: =+I105+J106*J42 -> 0 | K105: =+J105+K106*K42 -> 0 | L105: =+K105+L106*L42 -> 0 | M105: =+L105+M106*M42 -> 0 | N105: =+M105+N106*N42 -> 0 | O105: =+N105+O106*O42 -> 0 | ... Q105: =+P105+Q106*Q42 -> 0
B106: growing with % of R&D | E106: =IFERROR((E105-Inputs!N45)/E42,"") | F106: =IFERROR((F105-E105)/F42,"") | G106: =IFERROR((G105-F105)/G42,"")
B108: Liabilities
B110: Accounts Payable | E110: =+_xlfn.XLOOKUP($B110,Inputs!$B:$B,Inputs!O:O) -> 0 | F110: =+_xlfn.XLOOKUP($B110,Inputs!$B:$B,Inputs!P:P) -> 0 | G110: =+_xlfn.XLOOKUP($B110,Inputs!$B:$B,Inputs!Q:Q) -> 0 | H110: =+IFERROR(H111*H33/365,"") | I110: =+IFERROR(I111*I33/365,"") | J110: =+IFERROR(J111*J33/365,"") | K110: =+IFERROR(K111*K33/365,"") | L110: =+IFERROR(L111*L33/365,"") | M110: =+IFERROR(M111*M33/365,"") | N110: =+IFERROR(N111*N33/365,"") | O110: =+IFERROR(O111*O33/365,"") | ... Q110: =+IFERROR(Q111*Q33/365,"")
B111: DPO | E111: =IFERROR(E110/E$33*365,"") | F111: =IFERROR(F110/F$33*365,"") | G111: =IFERROR(G110/G$33*366,"") | H111: =IFERROR(AVERAGE(E111:G111),"") | I111: =IFERROR(AVERAGE(F111:H111),"") | J111: =IFERROR(AVERAGE(G111:I111),"") | K111: =IFERROR(AVERAGE(H111:J111),"") | L111: =IFERROR(AVERAGE(I111:K111),"") | M111: =IFERROR(AVERAGE(J111:L111),"") | N111: =IFERROR(AVERAGE(K111:M111),"") | O111: =IFERROR(AVERAGE(L111:N111),"") | ... Q111: =IFERROR(AVERAGE(N111:P111),"")
B113: Accrued Expenses and Other Current Liabilities | E113: =+_xlfn.XLOOKUP($B113,Inputs!$B:$B,Inputs!O:O) -> 0 | F113: =+_xlfn.XLOOKUP($B113,Inputs!$B:$B,Inputs!P:P) -> 0 | G113: =+_xlfn.XLOOKUP($B113,Inputs!$B:$B,Inputs!Q:Q) -> 0 | H113: =IFERROR(AVERAGE(E113:G113)*(1+H31),"") | I113: =IFERROR(AVERAGE(F113:H113)*(1+I31),"") | J113: =IFERROR(AVERAGE(G113:I113)*(1+J31),"") | K113: =IFERROR(AVERAGE(H113:J113)*(1+K31),"") | L113: =IFERROR(AVERAGE(I113:K113)*(1+L31),"") | M113: =IFERROR(AVERAGE(J113:L113)*(1+M31),"") | N113: =IFERROR(AVERAGE(K113:M113)*(1+N31),"") | O113: =IFERROR(AVERAGE(L113:N113)*(1+O31),"") | ... Q113: =IFERROR(AVERAGE(N113:P113)*(1+Q31),"")
B114: growing with revenue | E114: =IFERROR(E113/E$30,"") | F114: =IFERROR(F113/F$30,"") | G114: =IFERROR(G113/G$30,"") | H114: =IFERROR(H113/H$30,"") | I114: =IFERROR(I113/I$30,"") | J114: =IFERROR(J113/J$30,"") | K114: =IFERROR(K113/K$30,"") | L114: =IFERROR(L113/L$30,"") | ... Q114: =IFERROR(Q113/Q$30,"")
B116: Total Borrowings | E116: =+_xlfn.XLOOKUP($B116,Inputs!$B:$B,Inputs!O:O) -> 0 | F116: =+_xlfn.XLOOKUP($B116,Inputs!$B:$B,Inputs!P:P) -> 0 | G116: =+_xlfn.XLOOKUP($B116,Inputs!$B:$B,Inputs!Q:Q) -> 0 | H116: =IFERROR(G116+H156-H158,"") -> 0 | I116: =IFERROR(H116+I156-I158,"") | J116: =IFERROR(I116+J156-J158,"") | K116: =IFERROR(J116+K156-K158,"") | L116: =IFERROR(K116+L156-L158,"") | M116: =IFERROR(L116+M156-M158,"") | N116: =IFERROR(M116+N156-N158,"") | O116: =IFERROR(N116+O156-O158,"") | ... Q116: =IFERROR(P116+Q156-Q158,"")
B118: Total Leases | E118: =+_xlfn.XLOOKUP($B118,Inputs!$B:$B,Inputs!O:O) -> 0 | F118: =+_xlfn.XLOOKUP($B118,Inputs!$B:$B,Inputs!P:P) -> 0 | G118: =+_xlfn.XLOOKUP($B118,Inputs!$B:$B,Inputs!Q:Q) -> 0 | H118: =+IFERROR(H119*H30,"") | I118: =+IFERROR(I119*I30,"") | J118: =+IFERROR(J119*J30,"") | K118: =+IFERROR(K119*K30,"") | L118: =+IFERROR(L119*L30,"") | M118: =+IFERROR(M119*M30,"") | N118: =+IFERROR(N119*N30,"") | O118: =+IFERROR(O119*O30,"") | ... Q118: =+IFERROR(Q119*Q30,"")
B119: % of revenues | E119: =IFERROR(E118/E$30,"") | F119: =IFERROR(F118/F$30,"") | G119: =IFERROR(G118/G$30,"") | H119: =+IFERROR(AVERAGE(E119:G119),"") | I119: =+IFERROR(AVERAGE(F119:H119),"") | J119: =+IFERROR(AVERAGE(G119:I119),"") | K119: =+IFERROR(AVERAGE(H119:J119),"") | L119: =+IFERROR(AVERAGE(I119:K119),"") | M119: =+IFERROR(AVERAGE(J119:L119),"") | N119: =+IFERROR(AVERAGE(K119:M119),"") | O119: =+IFERROR(AVERAGE(L119:N119),"") | ... Q119: =+IFERROR(AVERAGE(N119:P119),"")
A121: x | B121: Cash Flow | E121: =E28 -> 2022 | F121: =F28 -> 2023 | G121: =G28 -> 2024 | H121: =H28 -> 2025 | I121: =I28 -> 2026 | J121: =J28 -> 2027 | K121: =K28 -> 2028 | L121: =L28 -> 2029 | ... Q121: =Q28 -> 2034
B123: D&A (Depreciation & Amortization) | E123: =+E50 -> 0 | F123: =+F50 -> 0 | G123: =+G50 -> 0 | H123: =+H50 | I123: =+I50 | J123: =+J50 | K123: =+K50 | L123: =+L50 | ... Q123: =+Q50
B125: Stock Based Compensation | E125: =+_xlfn.XLOOKUP($B125,Inputs!$B:$B,Inputs!O:O) -> 0 | F125: =+_xlfn.XLOOKUP($B125,Inputs!$B:$B,Inputs!P:P) -> 0 | G125: =+_xlfn.XLOOKUP($B125,Inputs!$B:$B,Inputs!Q:Q) -> 0 | H125: =IFERROR(H126*H39,"") | I125: =IFERROR(I126*I39,"") | J125: =IFERROR(J126*J39,"") | K125: =IFERROR(K126*K39,"") | L125: =IFERROR(L126*L39,"") | M125: =IFERROR(M126*M39,"") | N125: =IFERROR(N126*N39,"") | O125: =IFERROR(O126*O39,"") | ... Q125: =IFERROR(Q126*Q39,"")
B126: % of SG&A | E126: =+IFERROR(E125/E39,"") | F126: =+IFERROR(F125/F39,"") | G126: =+IFERROR(G125/G39,"") | H126: =IFERROR(AVERAGE(E126:G126),"") | I126: =IFERROR(AVERAGE(F126:H126),"") | J126: =IFERROR(AVERAGE(G126:I126),"") | K126: =IFERROR(AVERAGE(H126:J126),"") | L126: =IFERROR(AVERAGE(I126:K126),"") | M126: =IFERROR(AVERAGE(J126:L126),"") | N126: =IFERROR(AVERAGE(K126:M126),"") | O126: =IFERROR(AVERAGE(L126:N126),"") | ... Q126: =IFERROR(AVERAGE(N126:P126),"")
B128: Changes in Net Working Capital | E128: =+_xlfn.XLOOKUP($B128,Inputs!$B:$B,Inputs!O:O) -> 0 | F128: =+_xlfn.XLOOKUP($B128,Inputs!$B:$B,Inputs!P:P) -> 0 | G128: =+_xlfn.XLOOKUP($B128,Inputs!$B:$B,Inputs!Q:Q) -> 0 | H128: =IFERROR(-((H90+H93+H96-H110-H113)-(G90+G93+G96-G110-G113)),"") | I128: =IFERROR(-((I90+I93+I96-I110-I113)-(H90+H93+H96-H110-H113)),"") | J128: =IFERROR(-((J90+J93+J96-J110-J113)-(I90+I93+I96-I110-I113)),"") | K128: =IFERROR(-((K90+K93+K96-K110-K113)-(J90+J93+J96-J110-J113)),"") | L128: =IFERROR(-((L90+L93+L96-L110-L113)-(K90+K93+K96-K110-K113)),"") | M128: =IFERROR(-((M90+M93+M96-M110-M113)-(L90+L93+L96-L110-L113)),"") | N128: =IFERROR(-((N90+N93+N96-N110-N113)-(M90+M93+M96-M110-M113)),"") | O128: =IFERROR(-((O90+O93+O96-O110-O113)-(N90+N93+N96-N110-N113)),"") | ... Q128: =IFERROR(-((Q90+Q93+Q96-Q110-Q113)-(P90+P93+P96-P110-P113)),"")
B130: Other Operating Adjustments | E130: =+_xlfn.XLOOKUP($B130,Inputs!$B:$B,Inputs!O:O) -> 0 | F130: =+_xlfn.XLOOKUP($B130,Inputs!$B:$B,Inputs!P:P) -> 0 | G130: =+_xlfn.XLOOKUP($B130,Inputs!$B:$B,Inputs!Q:Q) -> 0 | H130: =IFERROR(AVERAGE(E130:G130)*(1+H31),"") | I130: =IFERROR(AVERAGE(F130:H130)*(1+I31),"") | J130: =IFERROR(AVERAGE(G130:I130)*(1+J31),"") | K130: =IFERROR(AVERAGE(H130:J130)*(1+K31),"") | L130: =IFERROR(AVERAGE(I130:K130)*(1+L31),"") | M130: =IFERROR(AVERAGE(J130:L130)*(1+M31),"") | N130: =IFERROR(AVERAGE(K130:M130)*(1+N31),"") | O130: =IFERROR(AVERAGE(L130:N130)*(1+O31),"") | ... Q130: =IFERROR(AVERAGE(N130:P130)*(1+Q31),"")
B132: Operating Cash Flow | E132: =+_xlfn.XLOOKUP($B132,Inputs!$B:$B,Inputs!O:O) -> 0 | F132: =+_xlfn.XLOOKUP($B132,Inputs!$B:$B,Inputs!P:P) -> 0 | G132: =+_xlfn.XLOOKUP($B132,Inputs!$B:$B,Inputs!Q:Q) -> 0 | H132: =IFERROR(H81+H123+H125+H128+H130,"") | I132: =IFERROR(I81+I123+I125+I128+I130,"") | J132: =IFERROR(J81+J123+J125+J128+J130,"") | K132: =IFERROR(K81+K123+K125+K128+K130,"") | L132: =IFERROR(L81+L123+L125+L128+L130,"") | M132: =IFERROR(M81+M123+M125+M128+M130,"") | N132: =IFERROR(N81+N123+N125+N128+N130,"") | O132: =IFERROR(O81+O123+O125+O128+O130,"") | ... Q132: =IFERROR(Q81+Q123+Q125+Q128+Q130,"")
B134: Net CapEx | E134: =+_xlfn.XLOOKUP($B134,Inputs!$B:$B,Inputs!O:O) -> 0 | F134: =+_xlfn.XLOOKUP($B134,Inputs!$B:$B,Inputs!P:P) -> 0 | G134: =+_xlfn.XLOOKUP($B134,Inputs!$B:$B,Inputs!Q:Q) -> 0 | H134: =IFERROR(H136+H138,"") | I134: =IFERROR(I136+I138,"") | J134: =IFERROR(J136+J138,"") | K134: =IFERROR(K136+K138,"") | L134: =IFERROR(L136+L138,"") | M134: =IFERROR(M136+M138,"") | N134: =IFERROR(N136+N138,"") | O134: =IFERROR(O136+O138,"") | ... Q134: =IFERROR(Q136+Q138,"")
B136: Acquisition of Fixed & Intangibles | E136: =+_xlfn.XLOOKUP($B136,Inputs!$B:$B,Inputs!O:O) -> 0 | F136: =+_xlfn.XLOOKUP($B136,Inputs!$B:$B,Inputs!P:P) -> 0 | G136: =+_xlfn.XLOOKUP($B136,Inputs!$B:$B,Inputs!Q:Q) -> 0 | H136: =+H19*H18 -> 0 | I136: =+I19*I18 -> 0 | J136: =+J19*J18 -> 0 | K136: =+K19*K18 -> 0 | L136: =+L19*L18 -> 0 | M136: =+M19*M18 -> 0 | N136: =+N19*N18 -> 0 | O136: =+O19*O18 -> 0 | ... Q136: =+Q19*Q18 -> 0
B138: Disposal of Fixed & Intangibles | E138: =+_xlfn.XLOOKUP($B138,Inputs!$B:$B,Inputs!O:O) -> 0 | F138: =+_xlfn.XLOOKUP($B138,Inputs!$B:$B,Inputs!P:P) -> 0 | G138: =+_xlfn.XLOOKUP($B138,Inputs!$B:$B,Inputs!Q:Q) -> 0 | H138: =IFERROR(H139*G100,"") | I138: =IFERROR(I139*H100,"") | J138: =IFERROR(J139*I100,"") | K138: =IFERROR(K139*J100,"") | L138: =IFERROR(L139*K100,"") | M138: =IFERROR(M139*L100,"") | N138: =IFERROR(N139*M100,"") | O138: =IFERROR(O139*N100,"") | ... Q138: =IFERROR(Q139*P100,"")
B139: Disposal Rate (% Gross PP&E) | E139: =IFERROR(E138/E100,"") | F139: =IFERROR(F138/F100,"") | G139: =IFERROR(G138/G100,"") | H139: =IFERROR(AVERAGE(E139:G139),"") | I139: =IFERROR(AVERAGE(F139:H139),"") | J139: =IFERROR(AVERAGE(G139:I139),"") | K139: =IFERROR(AVERAGE(H139:J139),"") | L139: =IFERROR(AVERAGE(I139:K139),"") | M139: =IFERROR(AVERAGE(J139:L139),"") | N139: =IFERROR(AVERAGE(K139:M139),"") | O139: =IFERROR(AVERAGE(L139:N139),"") | ... Q139: =IFERROR(AVERAGE(N139:P139),"")
B141: Net Cash from Investments & Acquisitions | E141: =+_xlfn.XLOOKUP($B141,Inputs!$B:$B,Inputs!O:O) -> 0 | F141: =+_xlfn.XLOOKUP($B141,Inputs!$B:$B,Inputs!P:P) -> 0 | G141: =+_xlfn.XLOOKUP($B141,Inputs!$B:$B,Inputs!Q:Q) -> 0 | H141: 0 | I141: 0 | J141: 0 | K141: 0 | L141: 0 | M141: 0 | N141: 0 | O141: 0 | P141: 0 | Q141: 0
B143: Other Investing Inflows (Outflows) | E143: =+_xlfn.XLOOKUP($B143,Inputs!$B:$B,Inputs!O:O) -> 0 | F143: =+_xlfn.XLOOKUP($B143,Inputs!$B:$B,Inputs!P:P) -> 0 | G143: =+_xlfn.XLOOKUP($B143,Inputs!$B:$B,Inputs!Q:Q) -> 0 | H143: =IFERROR(AVERAGE(E143:G143)*(1+H31),"") | I143: =IFERROR(AVERAGE(F143:H143)*(1+I31),"") | J143: =IFERROR(AVERAGE(G143:I143)*(1+J31),"") | K143: =IFERROR(AVERAGE(H143:J143)*(1+K31),"") | L143: =IFERROR(AVERAGE(I143:K143)*(1+L31),"") | M143: =IFERROR(AVERAGE(J143:L143)*(1+M31),"") | N143: =IFERROR(AVERAGE(K143:M143)*(1+N31),"") | O143: =IFERROR(AVERAGE(L143:N143)*(1+O31),"") | ... Q143: =IFERROR(AVERAGE(N143:P143)*(1+Q31),"")
B145: Investing Cash Flow | E145: =+_xlfn.XLOOKUP($B145,Inputs!$B:$B,Inputs!O:O) -> 0 | F145: =+_xlfn.XLOOKUP($B145,Inputs!$B:$B,Inputs!P:P) -> 0 | G145: =+_xlfn.XLOOKUP($B145,Inputs!$B:$B,Inputs!Q:Q) -> 0 | H145: =IFERROR(+H134+H141+H143,"") | I145: =IFERROR(+I134+I141+I143,"") | J145: =IFERROR(+J134+J141+J143,"") | K145: =IFERROR(+K134+K141+K143,"") | L145: =IFERROR(+L134+L141+L143,"") | M145: =IFERROR(+M134+M141+M143,"") | N145: =IFERROR(+N134+N141+N143,"") | O145: =IFERROR(+O134+O141+O143,"") | ... Q145: =IFERROR(+Q134+Q141+Q143,"")
B147: Dividends | E147: =+_xlfn.XLOOKUP($B147,Inputs!$B:$B,Inputs!O:O) -> 0 | F147: =+_xlfn.XLOOKUP($B147,Inputs!$B:$B,Inputs!P:P) -> 0 | G147: =+_xlfn.XLOOKUP($B147,Inputs!$B:$B,Inputs!Q:Q) -> 0 | H147: =+IFERROR(H148*_xlfn.XLOOKUP("Net Income",$B:$B,$H:$H),"") | I147: =+IFERROR(I148*_xlfn.XLOOKUP("Net Income",$B:$B,$H:$H),"") | J147: =+IFERROR(J148*_xlfn.XLOOKUP("Net Income",$B:$B,$H:$H),"") | K147: =+IFERROR(K148*_xlfn.XLOOKUP("Net Income",$B:$B,$H:$H),"") | L147: =+IFERROR(L148*_xlfn.XLOOKUP("Net Income",$B:$B,$H:$H),"") | M147: =+IFERROR(M148*_xlfn.XLOOKUP("Net Income",$B:$B,$H:$H),"") | N147: =+IFERROR(N148*_xlfn.XLOOKUP("Net Income",$B:$B,$H:$H),"") | O147: =+IFERROR(O148*_xlfn.XLOOKUP("Net Income",$B:$B,$H:$H),"") | ... Q147: =+IFERROR(Q148*_xlfn.XLOOKUP("Net Income",$B:$B,$H:$H),"")
B148: Dividend payout | E148: =IFERROR(-E147/E$81,"") | F148: =IFERROR(-F147/F$81,"") | G148: =IFERROR(-G147/G$81,"")
B150: Increase (Repurchase) of Shares | E150: =+_xlfn.XLOOKUP($B150,Inputs!$B:$B,Inputs!O:O) -> 0 | F150: =+_xlfn.XLOOKUP($B150,Inputs!$B:$B,Inputs!P:P) -> 0 | G150: =+_xlfn.XLOOKUP($B150,Inputs!$B:$B,Inputs!Q:Q) -> 0 | H150: =IFERROR(-H151*_xlfn.XLOOKUP("Net Income",$B:$B,H:H),"") | I150: =IFERROR(-I151*_xlfn.XLOOKUP("Net Income",$B:$B,I:I),"") | J150: =IFERROR(-J151*_xlfn.XLOOKUP("Net Income",$B:$B,J:J),"") | K150: =IFERROR(-K151*_xlfn.XLOOKUP("Net Income",$B:$B,K:K),"") | L150: =IFERROR(-L151*_xlfn.XLOOKUP("Net Income",$B:$B,L:L),"") | M150: =IFERROR(-M151*_xlfn.XLOOKUP("Net Income",$B:$B,M:M),"") | N150: =IFERROR(-N151*_xlfn.XLOOKUP("Net Income",$B:$B,N:N),"") | O150: =IFERROR(-O151*_xlfn.XLOOKUP("Net Income",$B:$B,O:O),"") | P150: =IFERROR(-P151*_xlfn.XLOOKUP("Net Income",$B:$B,P:P),"") | Q150: =IFERROR(-Q151*_xlfn.XLOOKUP("Net Income",$B:$B,Q:Q),"")
...

Sheet Inputs
B2: Inputs
B3: in millions of USD
A4: x | B4: Income Statement | G4: 2014 | H4: =+G4+1 -> 2015 | I4: =+H4+1 -> 2016 | J4: =+I4+1 -> 2017 | K4: =+J4+1 -> 2018 | L4: =+K4+1 -> 2019 | M4: =+L4+1 -> 2020 | N4: =+M4+1 -> 2021 | O4: =+N4+1 -> 2022 | ... Q4: =+P4+1 -> 2024 | R4: ="CAGR "&$G$4&" - "&$Q$4 -> CAGR 2014 - 2024
B6: Revenue (Sales) | R6: =IFERROR((Q6/G6)^(1/COUNT($G$4:$Q$4))-1,"")
B7: COGS (Cost of Goods Sold) | R7: =IFERROR((Q7/G7)^(1/COUNT($G$4:$Q$4))-1,"")
B8: Gross Profit | G8: =G6-G7 -> 0 | H8: =H6-H7 -> 0 | I8: =I6-I7 -> 0 | J8: =J6-J7 -> 0 | K8: =K6-K7 -> 0 | L8: =L6-L7 -> 0 | M8: =M6-M7 -> 0 | N8: =N6-N7 -> 0 | ... Q8: =Q6-Q7 -> 0 | R8: =IFERROR((Q8/G8)^(1/COUNT($G$4:$Q$4))-1,"")
B9: SG&A (Selling, General & Administrative) | R9: =IFERROR((Q9/G9)^(1/COUNT($G$4:$Q$4))-1,"")
B10: R&D (Research & Development) | R10: =IFERROR((Q10/G10)^(1/COUNT($G$4:$Q$4))-1,"")
B11: Other Operating (Income) Expenses | R11: =IFERROR((Q11/G11)^(1/COUNT($G$4:$Q$4))-1,"")
B12: EBITDA | G12: =+G8-G9-G10-G11 -> 0 | H12: =+H8-H9-H10-H11 -> 0 | I12: =+I8-I9-I10-I11 -> 0 | J12: =+J8-J9-J10-J11 -> 0 | K12: =+K8-K9-K10-K11 -> 0 | L12: =+L8-L9-L10-L11 -> 0 | M12: =+M8-M9-M10-M11 -> 0 | N12: =+N8-N9-N10-N11 -> 0 | ... Q12: =+Q8-Q9-Q10-Q11 -> 0 | R12: =IFERROR((Q12/G12)^(1/COUNT($G$4:$Q$4))-1,"")
B13: D&A (Depreciation & Amortization) | G13: =+SUM(G14:G15) -> 0 | H13: =+SUM(H14:H15) -> 0 | I13: =+SUM(I14:I15) -> 0 | J13: =+SUM(J14:J15) -> 0 | K13: =+SUM(K14:K15) -> 0 | L13: =+SUM(L14:L15) -> 0 | M13: =+SUM(M14:M15) -> 0 | N13: =+SUM(N14:N15) -> 0 | ... Q13: =+SUM(Q14:Q15) -> 0 | R13: =IFERROR((Q13/G13)^(1/COUNT($G$4:$Q$4))-1,"")
B14: Depreciation Expense | R14: =IFERROR((Q14/G14)^(1/COUNT($G$4:$Q$4))-1,"")
B15: Amortization Expense | R15: =IFERROR((Q15/G15)^(1/COUNT($G$4:$Q$4))-1,"")
B16: Operating Income (EBIT) | G16: =+G12-G13 -> 0 | H16: =+H12-H13 -> 0 | I16: =+I12-I13 -> 0 | J16: =+J12-J13 -> 0 | K16: =+K12-K13 -> 0 | L16: =+L12-L13 -> 0 | M16: =+M12-M13 -> 0 | N16: =+N12-N13 -> 0 | ... Q16: =+Q12-Q13 -> 0 | R16: =IFERROR((Q16/G16)^(1/COUNT($G$4:$Q$4))-1,"")
B17: Net Interest Expense (Income) | G17: =+G18-G19 -> 0 | H17: =+H18-H19 -> 0 | I17: =+I18-I19 -> 0 | J17: =+J18-J19 -> 0 | K17: =+K18-K19 -> 0 | L17: =+L18-L19 -> 0 | M17: =+M18-M19 -> 0 | N17: =+N18-N19 -> 0 | ... Q17: =+Q18-Q19 -> 0 | R17: =IFERROR((Q17/G17)^(1/COUNT($G$4:$Q$4))-1,"")
B18: Interest Expense | R18: =IFERROR((Q18/G18)^(1/COUNT($G$4:$Q$4))-1,"")
B19: Interest Income | R19: =IFERROR((Q19/G19)^(1/COUNT($G$4:$Q$4))-1,"")
B20: FX (Gain) Loss | R20: =IFERROR((Q20/G20)^(1/COUNT($G$4:$Q$4))-1,"")
B21: Other Non-Operating (Income) Expenses | R21: =IFERROR((Q21/G21)^(1/COUNT($G$4:$Q$4))-1,"")
B22: Pre-Tax Income (EBT) | G22: =+G16-G17-G20-G21 -> 0 | H22: =+H16-H17-H20-H21 -> 0 | I22: =+I16-I17-I20-I21 -> 0 | J22: =+J16-J17-J20-J21 -> 0 | K22: =+K16-K17-K20-K21 -> 0 | L22: =+L16-L17-L20-L21 -> 0 | M22: =+M16-M17-M20-M21 -> 0 | N22: =+N16-N17-N20-N21 -> 0 | ... Q22: =+Q16-Q17-Q20-Q21 -> 0 | R22: =IFERROR((Q22/G22)^(1/COUNT($G$4:$Q$4))-1,"")
B23: Tax Expense (Benefits) | R23: =IFERROR((Q23/G23)^(1/COUNT($G$4:$Q$4))-1,"")
B24: Net Income | G24: =+G22-G23 -> 0 | H24: =+H22-H23 -> 0 | I24: =+I22-I23 -> 0 | J24: =+J22-J23 -> 0 | K24: =+K22-K23 -> 0 | L24: =+L22-L23 -> 0 | M24: =+M22-M23 -> 0 | N24: =+N22-N23 -> 0 | ... Q24: =+Q22-Q23 -> 0 | R24: =IFERROR((Q24/G24)^(1/COUNT($G$4:$Q$4))-1,"")
B25: EPS basic | R25: =IFERROR((Q25/G25)^(1/COUNT($G$4:$Q$4))-1,"")
B26: EPS diluted | R26: =IFERROR((Q26/G26)^(1/COUNT($G$4:$Q$4))-1,"")
B27: Basic Weighted Average Shares
B28: Diluted Weighted Average Shares | R28: =IFERROR((Q28/G28)^(1/COUNT($G$4:$Q$4))-1,"")
A30: x | B30: Balance Sheet | G30: 2014 | H30: =+G30+1 -> 2015 | I30: =+H30+1 -> 2016 | J30: =+I30+1 -> 2017 | K30: =+J30+1 -> 2018 | L30: =+K30+1 -> 2019 | M30: =+L30+1 -> 2020 | N30: =+M30+1 -> 2021 | O30: =+N30+1 -> 2022 | ... Q30: =+P30+1 -> 2024 | R30: ="CAGR "&$G$4&" - "&$Q$4 -> CAGR 2014 - 2024
B32: Cash & Cash Equivalents & ST Investments | G32: =+SUM(G33:G34) -> 0 | H32: =+SUM(H33:H34) -> 0 | I32: =+SUM(I33:I34) -> 0 | J32: =+SUM(J33:J34) -> 0 | K32: =+SUM(K33:K34) -> 0 | L32: =+SUM(L33:L34) -> 0 | M32: =+SUM(M33:M34) -> 0 | N32: =+SUM(N33:N34) -> 0 | ... Q32: =+SUM(Q33:Q34) -> 0 | R32: =IFERROR((Q32/G32)^(1/COUNT($G$4:$Q$4))-1,"")
B33: Cash & Cash Equivalents | R33: =IFERROR((Q33/G33)^(1/COUNT($G$4:$Q$4))-1,"")
B34: Short-Term Investments | R34: =IFERROR((Q34/G34)^(1/COUNT($G$4:$Q$4))-1,"")
B35: Accounts Receivable | R35: =IFERROR((Q35/G35)^(1/COUNT($G$4:$Q$4))-1,"")
B36: Inventory | R36: =IFERROR((Q36/G36)^(1/COUNT($G$4:$Q$4))-1,"")
B37: Prepaid expenses and Other Current Assets | G37: =+G38-G32-G35-G36 -> 0 | H37: =+H38-H32-H35-H36 -> 0 | I37: =+I38-I32-I35-I36 -> 0 | J37: =+J38-J32-J35-J36 -> 0 | K37: =+K38-K32-K35-K36 -> 0 | L37: =+L38-L32-L35-L36 -> 0 | M37: =+M38-M32-M35-M36 -> 0 | N37: =+N38-N32-N35-N36 -> 0 | ... Q37: =+Q38-Q32-Q35-Q36 -> 0 | R37: =IFERROR((Q37/G37)^(1/COUNT($G$4:$Q$4))-1,"")
B38: Current Assets | R38: =IFERROR((Q38/G38)^(1/COUNT($G$4:$Q$4))-1,"")
B39: Net PP&E (Property, Plant and Equipment) | G39: =+G40-G41 -> 0 | H39: =+H40-H41 -> 0 | I39: =+I40-I41 -> 0 | J39: =+J40-J41 -> 0 | K39: =+K40-K41 -> 0 | L39: =+L40-L41 -> 0 | M39: =+M40-M41 -> 0 | N39: =+N40-N41 -> 0 | ... Q39: =+Q40-Q41 -> 0 | R39: =IFERROR((Q39/G39)^(1/COUNT($G$4:$Q$4))-1,"")
B40: Gross PP&E (Property, Plant and Equipment) | R40: =IFERROR((Q40/G40)^(1/COUNT($G$4:$Q$4))-1,"")
B41: Accumulated Depreciation | R41: =IFERROR((Q41/G41)^(1/COUNT($G$4:$Q$4))-1,"")
B42: Right-of-Use Assets | R42: =IFERROR((Q42/G42)^(1/COUNT($G$4:$Q$4))-1,"")
B43: Intangibles | R43: =IFERROR((Q43/G43)^(1/COUNT($G$4:$Q$4))-1,"")
B44: Goodwill | R44: =IFERROR((Q44/G44)^(1/COUNT($G$4:$Q$4))-1,"")
B45: Intangibles excl. Goodwill | G45: =+G43-G44 -> 0 | H45: =+H43-H44 -> 0 | I45: =+I43-I44 -> 0 | J45: =+J43-J44 -> 0 | K45: =+K43-K44 -> 0 | L45: =+L43-L44 -> 0 | M45: =+M43-M44 -> 0 | N45: =+N43-N44 -> 0 | ... Q45: =+Q43-Q44 -> 0
B46: Other Non-Current Assets | G46: =+G47-G39-G42-G43 -> 0 | H46: =+H47-H39-H42-H43 -> 0 | I46: =+I47-I39-I42-I43 -> 0 | J46: =+J47-J39-J42-J43 -> 0 | K46: =+K47-K39-K42-K43 -> 0 | L46: =+L47-L39-L42-L43 -> 0 | M46: =+M47-M39-M42-M43 -> 0 | N46: =+N47-N39-N42-N43 -> 0 | ... Q46: =+Q47-Q39-Q42-Q43 -> 0 | R46: =IFERROR((Q46/G46)^(1/COUNT($G$4:$Q$4))-1,"")
B47: Non-Current Assets | R47: =IFERROR((Q47/G47)^(1/COUNT($G$4:$Q$4))-1,"")
B48: Total Assets | G48: =SUM(G47,G38) -> 0 | H48: =SUM(H47,H38) -> 0 | I48: =SUM(I47,I38) -> 0 | J48: =SUM(J47,J38) -> 0 | K48: =SUM(K47,K38) -> 0 | L48: =SUM(L47,L38) -> 0 | M48: =SUM(M47,M38) -> 0 | N48: =SUM(N47,N38) -> 0 | ... Q48: =SUM(Q47,Q38) -> 0 | R48: =IFERROR((Q48/G48)^(1/COUNT($G$4:$Q$4))-1,"")
B49: Accounts Payable | R49: =IFERROR((Q49/G49)^(1/COUNT($G$4:$Q$4))-1,"")
B50: Short-Term Debt | G50: =+SUM(G51:G52) -> 0 | H50: =+SUM(H51:H52) -> 0 | I50: =+SUM(I51:I52) -> 0 | J50: =+SUM(J51:J52) -> 0 | K50: =+SUM(K51:K52) -> 0 | L50: =+SUM(L51:L52) -> 0 | M50: =+SUM(M51:M52) -> 0 | N50: =+SUM(N51:N52) -> 0 | ... Q50: =+SUM(Q51:Q52) -> 0 | R50: =IFERROR((Q50/G50)^(1/COUNT($G$4:$Q$4))-1,"")
B51: Short-Term Borrowings | R51: =IFERROR((Q51/G51)^(1/COUNT($G$4:$Q$4))-1,"")
B52: Current Portion of Lease Liabilities | R52: =IFERROR((Q52/G52)^(1/COUNT($G$4:$Q$4))-1,"")
B53: Accrued Expenses and Other Current Liabilities | G53: =+G54-G49-G50 -> 0 | H53: =+H54-H49-H50 -> 0 | I53: =+I54-I49-I50 -> 0 | J53: =+J54-J49-J50 -> 0 | K53: =+K54-K49-K50 -> 0 | L53: =+L54-L49-L50 -> 0 | M53: =+M54-M49-M50 -> 0 | N53: =+N54-N49-N50 -> 0 | ... Q53: =+Q54-Q49-Q50 -> 0 | R53: =IFERROR((Q53/G53)^(1/COUNT($G$4:$Q$4))-1,"")
B54: Current Liabilities | R54: =IFERROR((Q54/G54)^(1/COUNT($G$4:$Q$4))-1,"")
B55: Long-Term Debt | G55: =+SUM(G56:G57) -> 0 | H55: =+SUM(H56:H57) -> 0 | I55: =+SUM(I56:I57) -> 0 | J55: =+SUM(J56:J57) -> 0 | K55: =+SUM(K56:K57) -> 0 | L55: =+SUM(L56:L57) -> 0 | M55: =+SUM(M56:M57) -> 0 | N55: =+SUM(N56:N57) -> 0 | ... Q55: =+SUM(Q56:Q57) -> 0 | R55: =IFERROR((Q55/G55)^(1/COUNT($G$4:$Q$4))-1,"")
B56: Long-Term Borrowings | R56: =IFERROR((Q56/G56)^(1/COUNT($G$4:$Q$4))-1,"")
B57: Long-Term Operating Lease Liabilities | R57: =IFERROR((Q57/G57)^(1/COUNT($G$4:$Q$4))-1,"")
B58: Other Non-Current Liabilities | G58: =+G59-G55 -> 0 | H58: =+H59-H55 -> 0 | I58: =+I59-I55 -> 0 | J58: =+J59-J55 -> 0 | K58: =+K59-K55 -> 0 | L58: =+L59-L55 -> 0 | M58: =+M59-M55 -> 0 | N58: =+N59-N55 -> 0 | ... Q58: =+Q59-Q55 -> 0 | R58: =IFERROR((Q58/G58)^(1/COUNT($G$4:$Q$4))-1,"")
B59: Non-Current Liabilities | R59: =IFERROR((Q59/G59)^(1/COUNT($G$4:$Q$4))-1,"")
B60: Total Liabilities | G60: =SUM(G59,G54) -> 0 | H60: =SUM(H59,H54) -> 0 | I60: =SUM(I59,I54) -> 0 | J60: =SUM(J59,J54) -> 0 | K60: =SUM(K59,K54) -> 0 | L60: =SUM(L59,L54) -> 0 | M60: =SUM(M59,M54) -> 0 | N60: =SUM(N59,N54) -> 0 | ... Q60: =SUM(Q59,Q54) -> 0 | R60: =IFERROR((Q60/G60)^(1/COUNT($G$4:$Q$4))-1,"")
B61: Shareholder's Equity | G61: =G48-G60 -> 0 | H61: =H48-H60 -> 0 | I61: =I48-I60 -> 0 | J61: =J48-J60 -> 0 | K61: =K48-K60 -> 0 | L61: =L48-L60 -> 0 | M61: =M48-M60 -> 0 | N61: =N48-N60 -> 0 | ... Q61: =Q48-Q60 -> 0 | R61: =IFERROR((Q61/G61)^(1/COUNT($G$4:$Q$4))-1,"")
B62: Non-Controlling Interest
A64: x | B64: Cash Flow | G64: 2014 | H64: =+G64+1 -> 2015 | I64: =+H64+1 -> 2016 | J64: =+I64+1 -> 2017 | K64: =+J64+1 -> 2018 | L64: =+K64+1 -> 2019 | M64: =+L64+1 -> 2020 | N64: =+M64+1 -> 2021 | O64: =+N64+1 -> 2022 | ... Q64: =+P64+1 -> 2024 | R64: ="CAGR "&$G$4&" - "&$Q$4 -> CAGR 2014 - 2024
B66: Net Income | G66: =G24 -> 0 | H66: =H24 -> 0 | I66: =I24 -> 0 | J66: =J24 -> 0 | K66: =K24 -> 0 | L66: =L24 -> 0 | M66: =M24 -> 0 | N66: =N24 -> 0 | ... Q66: =Q24 -> 0 | R66: =IFERROR((Q66/G66)^(1/COUNT($G$4:$Q$4))-1,"")
B67: D&A (Depreciation and Amortization) | G67: =+G13 -> 0 | H67: =+H13 -> 0 | I67: =+I13 -> 0 | J67: =+J13 -> 0 | K67: =+K13 -> 0 | L67: =+L13 -> 0 | M67: =+M13 -> 0 | N67: =+N13 -> 0 | ... Q67: =+Q13 -> 0 | R67: =IFERROR((Q67/G67)^(1/COUNT($G$4:$Q$4))-1,"")
B68: Changes in Net Working Capital | G68: =+SUM(G69:G72) -> 0 | H68: =+SUM(H69:H72) -> 0 | I68: =+SUM(I69:I72) -> 0 | J68: =+SUM(J69:J72) -> 0 | K68: =+SUM(K69:K72) -> 0 | L68: =+SUM(L69:L72) -> 0 | M68: =+SUM(M69:M72) -> 0 | N68: =+SUM(N69:N72) -> 0 | ... Q68: =+SUM(Q69:Q72) -> 0 | R68: =IFERROR((Q68/G68)^(1/COUNT($G$4:$Q$4))-1,"")
B69: (Increase) Decrease in Accounts Receivable
B70: (Increase) Decrease in Inventories
B71: Increase (Decrease) in Inventories
B72: Increase (Decrease) in Other
B73: Stock Based Compensation
B74: Other Operating Adjustments | G74: =+G75-G66-G67-G68-G73 -> 0 | H74: =+H75-H66-H67-H68-H73 -> 0 | I74: =+I75-I66-I67-I68-I73 -> 0 | J74: =+J75-J66-J67-J68-J73 -> 0 | K74: =+K75-K66-K67-K68-K73 -> 0 | L74: =+L75-L66-L67-L68-L73 -> 0 | M74: =+M75-M66-M67-M68-M73 -> 0 | N74: =+N75-N66-N67-N68-N73 -> 0 | ... Q74: =+Q75-Q66-Q67-Q68-Q73 -> 0 | R74: =IFERROR((Q74/G74)^(1/COUNT($G$4:$Q$4))-1,"")
B75: Operating Cash Flow | R75: =IFERROR((Q75/G75)^(1/COUNT($G$4:$Q$4))-1,"")
B76: Net Capex | G76: =+SUM(G77:G78) -> 0 | H76: =+SUM(H77:H78) -> 0 | I76: =+SUM(I77:I78) -> 0 | J76: =+SUM(J77:J78) -> 0 | K76: =+SUM(K77:K78) -> 0 | L76: =+SUM(L77:L78) -> 0 | M76: =+SUM(M77:M78) -> 0 | N76: =+SUM(N77:N78) -> 0 | ... Q76: =+SUM(Q77:Q78) -> 0 | R76: =IFERROR((Q76/G76)^(1/COUNT($G$4:$Q$4))-1,"")
B77: Acquisition of Fixed & Intangibles | R77: =IFERROR((Q77/G77)^(1/COUNT($G$4:$Q$4))-1,"")
B78: Disposal of Fixed & Intangibles | R78: =IFERROR((Q78/G78)^(1/COUNT($G$4:$Q$4))-1,"")
B79: Net Cash from Investments & Acquisitions | G79: =+SUM(G80:G83) -> 0 | H79: =+SUM(H80:H83) -> 0 | I79: =+SUM(I80:I83) -> 0 | J79: =+SUM(J80:J83) -> 0 | K79: =+SUM(K80:K83) -> 0 | L79: =+SUM(L80:L83) -> 0 | M79: =+SUM(M80:M83) -> 0 | N79: =+SUM(N80:N83) -> 0 | ... Q79: =+SUM(Q80:Q83) -> 0 | R79: =IFERROR((Q79/G79)^(1/COUNT($G$4:$Q$4))-1,"")
B80: Acquisitions | R80: =IFERROR((Q80/G80)^(1/COUNT($G$4:$Q$4))-1,"")
B81: Divestitures | R81: =IFERROR((Q81/G81)^(1/COUNT($G$4:$Q$4))-1,"")
B82: Increase in LT Investment | R82: =IFERROR((Q82/G82)^(1/COUNT($G$4:$Q$4))-1,"")
B83: Decrease in LT Investment | R83: =IFERROR((Q83/G83)^(1/COUNT($G$4:$Q$4))-1,"")
B84: Other Investing Inflows (Outflows) | G84: =+G85-G76-G79 -> 0 | H84: =+H85-H76-H79 -> 0 | I84: =+I85-I76-I79 -> 0 | J84: =+J85-J76-J79 -> 0 | K84: =+K85-K76-K79 -> 0 | L84: =+L85-L76-L79 -> 0 | M84: =+M85-M76-M79 -> 0 | N84: =+N85-N76-N79 -> 0 | ... Q84: =+Q85-Q76-Q79 -> 0 | R84: =IFERROR((Q84/G84)^(1/COUNT($G$4:$Q$4))-1,"")
B85: Investing Cash Flow | R85: =IFERROR((Q85/G85)^(1/COUNT($G$4:$Q$4))-1,"")
B86: Debt Borrowing | R86: =IFERROR((Q86/G86)^(1/COUNT($G$4:$Q$4))-1,"")
B87: Debt Repayment | R87: =IFERROR((Q87/G87)^(1/COUNT($G$4:$Q$4))-1,"")
B88: Lease Payments | R88: =IFERROR((Q88/G88)^(1/COUNT($G$4:$Q$4))-1,"")
B89: Dividends | R89: =IFERROR((Q89/G89)^(1/COUNT($G$4:$Q$4))-1,"")
B90: Increase (Repurchase) of Shares | R90: =IFERROR((Q90/G90)^(1/COUNT($G$4:$Q$4))-1,"")
B91: Other Financing Inflows (Outflows) | G91: =+G92-G86-G87-G88-G89-G90 -> 0 | H91: =+H92-H86-H87-H88-H89-H90 -> 0 | I91: =+I92-I86-I87-I88-I89-I90 -> 0 | J91: =+J92-J86-J87-J88-J89-J90 -> 0 | K91: =+K92-K86-K87-K88-K89-K90 -> 0 | L91: =+L92-L86-L87-L88-L89-L90 -> 0 | M91: =+M92-M86-M87-M88-M89-M90 -> 0 | N91: =+N92-N86-N87-N88-N89-N90 -> 0 | ... Q91: =+Q92-Q86-Q87-Q88-Q89-Q90 -> 0 | R91: =IFERROR((Q91/G91)^(1/COUNT($G$4:$Q$4))-1,"")
B92: Financing Cash Flow | R92: =IFERROR((Q92/G92)^(1/COUNT($G$4:$Q$4))-1,"")
B93: Effect of Foreign Exchange | R93: =IFERROR((Q93/G93)^(1/COUNT($G$4:$Q$4))-1,"")
B94: Net Changes in Cash | R94: =IFERROR((Q94/G94)^(1/COUNT($G$4:$Q$4))-1,"")
B95: in billionsof USD
A96: x | B96: Capital Structure | G96: 42004 | H96: 42369 | I96: 42735 | J96: 43100 | K96: 43465 | L96: 43830 | M96: 44196 | N96: 44561 | O96: 44926 | P96: 45291 | Q96: 45657
B98: Market Capitalization | G98: {=(IFERROR(_xlfn.STOCKHISTORY("CMG", G96, G96, 0, 0, 1), IFERROR(_xlfn.STOCKHISTORY("CMG", G96+1, G96+1, 0, 0, 1), _xlfn.STOCKHISTORY("CMG", G96-2, G96-2, 0, 0, 1))))*_xlfn.XLOOKUP("Basic Weighted Average Shares",$B:$B,G:G)} -> 0 | H98: {=(IFERROR(_xlfn.STOCKHISTORY("CMG", H96, H96, 0, 0, 1), IFERROR(_xlfn.STOCKHISTORY("CMG", H96+1, H96+1, 0, 0, 1), _xlfn.STOCKHISTORY("CMG", H96-2, H96-2, 0, 0, 1))))*_xlfn.XLOOKUP("Basic Weighted Average Shares",$B:$B,H:H)} -> 0 | I98: {=(IFERROR(_xlfn.STOCKHISTORY("CMG", I96, I96, 0, 0, 1), IFERROR(_xlfn.STOCKHISTORY("CMG", I96+1, I96+1, 0, 0, 1), _xlfn.STOCKHISTORY("CMG", I96-2, I96-2, 0, 0, 1))))*_xlfn.XLOOKUP("Basic Weighted Average Shares",$B:$B,I:I)} -> 0 | J98: {=(IFERROR(_xlfn.STOCKHISTORY("CMG", J96, J96, 0, 0, 1), IFERROR(_xlfn.STOCKHISTORY("CMG", J96+1, J96+1, 0, 0, 1), _xlfn.STOCKHISTORY("CMG", J96-2, J96-2, 0, 0, 1))))*_xlfn.XLOOKUP("Basic Weighted Average Shares",$B:$B,J:J)} -> 0 | K98: {=(IFERROR(_xlfn.STOCKHISTORY("CMG", K96, K96, 0, 0, 1), IFERROR(_xlfn.STOCKHISTORY("CMG", K96+1, K96+1, 0, 0, 1), _xlfn.STOCKHISTORY("CMG", K96-2, K96-2, 0, 0, 1))))*_xlfn.XLOOKUP("Basic Weighted Average Shares",$B:$B,K:K)} -> 0 | L98: {=(IFERROR(_xlfn.STOCKHISTORY("CMG", L96, L96, 0, 0, 1), IFERROR(_xlfn.STOCKHISTORY("CMG", L96+1, L96+1, 0, 0, 1), _xlfn.STOCKHISTORY("CMG", L96-2, L96-2, 0, 0, 1))))*_xlfn.XLOOKUP("Basic Weighted Average Shares",$B:$B,L:L)} -> 0 | M98: {=(IFERROR(_xlfn.STOCKHISTORY("CMG", M96, M96, 0, 0, 1), IFERROR(_xlfn.STOCKHISTORY("CMG", M96+1, M96+1, 0, 0, 1), _xlfn.STOCKHISTORY("CMG", M96-2, M96-2, 0, 0, 1))))*_xlfn.XLOOKUP("Basic Weighted Average Shares",$B:$B,M:M)} -> 0 | N98: {=(IFERROR(_xlfn.STOCKHISTORY("CMG", N96, N96, 0, 0, 1), IFERROR(_xlfn.STOCKHISTORY("CMG", N96+1, N96+1, 0, 0, 1), _xlfn.STOCKHISTORY("CMG", N96-2, N96-2, 0, 0, 1))))*_xlfn.XLOOKUP("Basic Weighted Average Shares",$B:$B,N:N)} -> 0 | O98: {=(IFERROR(_xlfn.STOCKHISTORY("CMG", O96, O96, 0, 0, 1), IFERROR(_xlfn.STOCKHISTORY("CMG", O96+1, O96+1, 0, 0, 1), _xlfn.STOCKHISTORY("CMG", O96-2, O96-2, 0, 0, 1))))*_xlfn.XLOOKUP("Basic Weighted Average Shares",$B:$B,O:O)} -> 0 | P98: {=(IFERROR(_xlfn.STOCKHISTORY("CMG", P96, P96, 0, 0, 1), IFERROR(_xlfn.STOCKHISTORY("CMG", P96+1, P96+1, 0, 0, 1), _xlfn.STOCKHISTORY("CMG", P96-2, P96-2, 0, 0, 1))))*_xlfn.XLOOKUP("Basic Weighted Average Shares",$B:$B,P:P)} -> 0 | Q98: {=(IFERROR(_xlfn.STOCKHISTORY("CMG", Q96, Q96, 0, 0, 1), IFERROR(_xlfn.STOCKHISTORY("CMG", Q96+1, Q96+1, 0, 0, 1), _xlfn.STOCKHISTORY("CMG", Q96-2, Q96-2, 0, 0, 1))))*_xlfn.XLOOKUP("Basic Weighted Average Shares",$B:$B,Q:Q)} -> 0
B99: Cash & Cash Equivalents | G99: =_xlfn.XLOOKUP("Cash & Cash Equivalents & ST Investments",$B$30:$B$62,G$30:G$62)/1000 -> 0 | H99: =_xlfn.XLOOKUP("Cash & Cash Equivalents & ST Investments",$B$30:$B$62,H$30:H$62)/1000 -> 0 | I99: =_xlfn.XLOOKUP("Cash & Cash Equivalents & ST Investments",$B$30:$B$62,I$30:I$62)/1000 -> 0 | J99: =_xlfn.XLOOKUP("Cash & Cash Equivalents & ST Investments",$B$30:$B$62,J$30:J$62)/1000 -> 0 | K99: =_xlfn.XLOOKUP("Cash & Cash Equivalents & ST Investments",$B$30:$B$62,K$30:K$62)/1000 -> 0 | L99: =_xlfn.XLOOKUP("Cash & Cash Equivalents & ST Investments",$B$30:$B$62,L$30:L$62)/1000 -> 0 | M99: =_xlfn.XLOOKUP("Cash & Cash Equivalents & ST Investments",$B$30:$B$62,M$30:M$62)/1000 -> 0 | N99: =_xlfn.XLOOKUP("Cash & Cash Equivalents & ST Investments",$B$30:$B$62,N$30:N$62)/1000 -> 0 | ... Q99: =_xlfn.XLOOKUP("Cash & Cash Equivalents & ST Investments",$B$30:$B$62,Q$30:Q$62)/1000 -> 0
B100: Total Debt | G100: =(_xlfn.XLOOKUP("Short-Term Debt",$B$30:$B$62,G$30:G$62)+_xlfn.XLOOKUP("Long-Term Debt",$B$30:$B$62,G$30:G$62))/1000 -> 0 | H100: =(_xlfn.XLOOKUP("Short-Term Debt",$B$30:$B$62,H$30:H$62)+_xlfn.XLOOKUP("Long-Term Debt",$B$30:$B$62,H$30:H$62))/1000 -> 0 | I100: =(_xlfn.XLOOKUP("Short-Term Debt",$B$30:$B$62,I$30:I$62)+_xlfn.XLOOKUP("Long-Term Debt",$B$30:$B$62,I$30:I$62))/1000 -> 0 | J100: =(_xlfn.XLOOKUP("Short-Term Debt",$B$30:$B$62,J$30:J$62)+_xlfn.XLOOKUP("Long-Term Debt",$B$30:$B$62,J$30:J$62))/1000 -> 0 | K100: =(_xlfn.XLOOKUP("Short-Term Debt",$B$30:$B$62,K$30:K$62)+_xlfn.XLOOKUP("Long-Term Debt",$B$30:$B$62,K$30:K$62))/1000 -> 0 | L100: =(_xlfn.XLOOKUP("Short-Term Debt",$B$30:$B$62,L$30:L$62)+_xlfn.XLOOKUP("Long-Term Debt",$B$30:$B$62,L$30:L$62))/1000 -> 0 | M100: =(_xlfn.XLOOKUP("Short-Term Debt",$B$30:$B$62,M$30:M$62)+_xlfn.XLOOKUP("Long-Term Debt",$B$30:$B$62,M$30:M$62))/1000 -> 0 | N100: =(_xlfn.XLOOKUP("Short-Term Debt",$B$30:$B$62,N$30:N$62)+_xlfn.XLOOKUP("Long-Term Debt",$B$30:$B$62,N$30:N$62))/1000 -> 0 | ... Q100: =(_xlfn.XLOOKUP("Short-Term Debt",$B$30:$B$62,Q$30:Q$62)+_xlfn.XLOOKUP("Long-Term Debt",$B$30:$B$62,Q$30:Q$62))/1000 -> 0
B101: Preferred Stock
B102: Non-Controlling Interest | G102: =_xlfn.XLOOKUP("Non-Controlling Interest",$B$30:$B$62,G$30:G$62)/1000 -> 0 | H102: =_xlfn.XLOOKUP("Non-Controlling Interest",$B$30:$B$62,H$30:H$62)/1000 -> 0 | I102: =_xlfn.XLOOKUP("Non-Controlling Interest",$B$30:$B$62,I$30:I$62)/1000 -> 0 | J102: =_xlfn.XLOOKUP("Non-Controlling Interest",$B$30:$B$62,J$30:J$62)/1000 -> 0 | K102: =_xlfn.XLOOKUP("Non-Controlling Interest",$B$30:$B$62,K$30:K$62)/1000 -> 0 | L102: =_xlfn.XLOOKUP("Non-Controlling Interest",$B$30:$B$62,L$30:L$62)/1000 -> 0 | M102: =_xlfn.XLOOKUP("Non-Controlling Interest",$B$30:$B$62,M$30:M$62)/1000 -> 0 | N102: =_xlfn.XLOOKUP("Non-Controlling Interest",$B$30:$B$62,N$30:N$62)/1000 -> 0 | ... Q102: =_xlfn.XLOOKUP("Non-Controlling Interest",$B$30:$B$62,Q$30:Q$62)/1000 -> 0
B103: Enterprise Value | G103: =+G98-G99+G100+G101+G102 -> 0 | H103: =+H98-H99+H100+H101+H102 -> 0 | I103: =+I98-I99+I100+I101+I102 -> 0 | J103: =+J98-J99+J100+J101+J102 -> 0 | K103: =+K98-K99+K100+K101+K102 -> 0 | L103: =+L98-L99+L100+L101+L102 -> 0 | M103: =+M98-M99+M100+M101+M102 -> 0 | N103: =+N98-N99+N100+N101+N102 -> 0 | ... Q103: =+Q98-Q99+Q100+Q101+Q102 -> 0
A105: x | B105: Debt Schedule | G105: Cash | H105: 2025 | I105: =+H105+1 -> 2026 | J105: =+I105+1 -> 2027 | K105: =+J105+1 -> 2028 | L105: =+K105+1 -> 2029 | M105: =+L105+1 -> 2030 | N105: =+M105+1 -> 2031 | O105: =+N105+1 -> 2032 | P105: =+O105+1 -> 2033 | Q105: =+P105+1 -> 2034
L106: v | M106: v | N106: v | O106: v | P106: v | Q106: v
B107: Cash
B108: Fixed
...

Sheet WACC
B2: WACC
B4: WACC = % of Equity x Cost of Equity + % de Debt x Cost of Debt x (1 - Tax Rate)
B5: Cost of Equity = Risk-Free Rate + Beta x Equity Risk Premium
B7: WACC | I7: Region | J7: Weight | K7: ERP | M7: Peers | N7: Beta (Unlevered)
B9: Market Cap (in millions) | G9: {=+_FV(DCF!R4,"Market cap",TRUE)/1000000} -> 254220.78 | M9: =+Peers!B8 | N9: =+Peers!E75
B10: % of Equity | G10: =IFERROR(G9/G23,"") -> 1 | M10: =+Peers!B9 | N10: =+Peers!F75
B11: Cost of Equity | G11: =IFERROR(G12+G14*G15,"") | M11: =+Peers!B10 | N11: =+Peers!G75
B12: Risk-Free Rate | M12: =+Peers!B11 | N12: =+Peers!H75
B13: Unlevered Beta | G13: =+N19 | M13: =+Peers!B12 | N13: =+Peers!I75
B14: Beta | G14: =+IFERROR(G13*(1+(1-G21)*(G18/G9)),"") | I14: Others | J14: =1-SUM(J9:J13) -> 1 | K14: =MAX(K9:K13) -> 0 | M14: =+Peers!B13 | N14: =+Peers!J75
B15: Equity Risk Premium | G15: =SUMPRODUCT(J9:J14,K9:K14) -> 0 | M15: =+Peers!B14 | N15: =+Peers!K75
B16: Unlevered Cost of Equity | G16: =IFERROR(+G12+G13*G15,"") | M16: =+Peers!B15 | N16: =+Peers!L75
M17: =+Peers!B16 | N17: =+Peers!M75
B18: Debt (in millions) | G18: 0 | M18: =+Peers!B17 | N18: =+Peers!N75
B19: % of Debt | G19: =IFERROR(G18/G23,"") -> 0 | M19: Average | N19: =IFERROR(+AVERAGEIF(N9:N18,">0"),"")
B20: Cost of debt | G20: 0
B21: Tax Rate | G21: =+DCF!H79
B23: Total | G23: =+G9+G18 -> 254220.78
B25: WACC | G25: =IFERROR(G10*G11+G19*G20*(1-G21),"")

Sheet Multiples
B2: Multiples
B4: Valuation | F4: 2014 | G4: =+F4+1 -> 2015 | H4: =+G4+1 -> 2016 | I4: =+H4+1 -> 2017 | J4: =+I4+1 -> 2018 | K4: =+J4+1 -> 2019 | L4: =+K4+1 -> 2020 | M4: =+L4+1 -> 2021 | N4: 2022 | O4: =+N4+1 -> 2023 | P4: =+O4+1 -> 2024 | Q4: =+P4+1 -> 2025 | R4: =+Q4+1 -> 2026
B6: EV / Sales | F6: =IFERROR(_xlfn.XLOOKUP("Enterprise Value",Inputs!$B:$B,Inputs!G:G)/_xlfn.XLOOKUP("Revenue (Sales)",Inputs!$B:$B,Inputs!G:G),"") | G6: =IFERROR(_xlfn.XLOOKUP("Enterprise Value",Inputs!$B:$B,Inputs!H:H)/_xlfn.XLOOKUP("Revenue (Sales)",Inputs!$B:$B,Inputs!H:H),"") | H6: =IFERROR(_xlfn.XLOOKUP("Enterprise Value",Inputs!$B:$B,Inputs!I:I)/_xlfn.XLOOKUP("Revenue (Sales)",Inputs!$B:$B,Inputs!I:I),"") | I6: =IFERROR(_xlfn.XLOOKUP("Enterprise Value",Inputs!$B:$B,Inputs!J:J)/_xlfn.XLOOKUP("Revenue (Sales)",Inputs!$B:$B,Inputs!J:J),"") | J6: =IFERROR(_xlfn.XLOOKUP("Enterprise Value",Inputs!$B:$B,Inputs!K:K)/_xlfn.XLOOKUP("Revenue (Sales)",Inputs!$B:$B,Inputs!K:K),"") | K6: =IFERROR(_xlfn.XLOOKUP("Enterprise Value",Inputs!$B:$B,Inputs!L:L)/_xlfn.XLOOKUP("Revenue (Sales)",Inputs!$B:$B,Inputs!L:L),"") | L6: =IFERROR(_xlfn.XLOOKUP("Enterprise Value",Inputs!$B:$B,Inputs!M:M)/_xlfn.XLOOKUP("Revenue (Sales)",Inputs!$B:$B,Inputs!M:M),"") | M6: =IFERROR(_xlfn.XLOOKUP("Enterprise Value",Inputs!$B:$B,Inputs!N:N)/_xlfn.XLOOKUP("Revenue (Sales)",Inputs!$B:$B,Inputs!N:N),"") | N6: =IFERROR(_xlfn.XLOOKUP("Enterprise Value",Inputs!$B:$B,Inputs!O:O)/_xlfn.XLOOKUP("Revenue (Sales)",Inputs!$B:$B,Inputs!O:O),"") | O6: =IFERROR(_xlfn.XLOOKUP("Enterprise Value",Inputs!$B:$B,Inputs!P:P)/_xlfn.XLOOKUP("Revenue (Sales)",Inputs!$B:$B,Inputs!P:P),"") | P6: =IFERROR(_xlfn.XLOOKUP("Enterprise Value",Inputs!$B:$B,Inputs!Q:Q)/_xlfn.XLOOKUP("Revenue (Sales)",Inputs!$B:$B,Inputs!Q:Q),"") | Q6: =IFERROR(_xlfn.XLOOKUP("Enterprise Value",DCF!$B:$B,DCF!R:R)/_xlfn.XLOOKUP("Revenue (Sales)",DCF!$B:$B,DCF!H:H),"") | R6: =IFERROR(_xlfn.XLOOKUP("Enterprise Value",DCF!$B:$B,DCF!S:S)/_xlfn.XLOOKUP("Revenue (Sales)",DCF!$B:$B,DCF!I:I),"")
B7: Price / Sales | F7: =IFERROR(_xlfn.XLOOKUP("Market Capitalization",Inputs!$B:$B,Inputs!G:G)/_xlfn.XLOOKUP("Revenue (Sales)",Inputs!$B:$B,Inputs!G:G),"") | G7: =IFERROR(_xlfn.XLOOKUP("Market Capitalization",Inputs!$B:$B,Inputs!H:H)/_xlfn.XLOOKUP("Revenue (Sales)",Inputs!$B:$B,Inputs!H:H),"") | H7: =IFERROR(_xlfn.XLOOKUP("Market Capitalization",Inputs!$B:$B,Inputs!I:I)/_xlfn.XLOOKUP("Revenue (Sales)",Inputs!$B:$B,Inputs!I:I),"") | I7: =IFERROR(_xlfn.XLOOKUP("Market Capitalization",Inputs!$B:$B,Inputs!J:J)/_xlfn.XLOOKUP("Revenue (Sales)",Inputs!$B:$B,Inputs!J:J),"") | J7: =IFERROR(_xlfn.XLOOKUP("Market Capitalization",Inputs!$B:$B,Inputs!K:K)/_xlfn.XLOOKUP("Revenue (Sales)",Inputs!$B:$B,Inputs!K:K),"") | K7: =IFERROR(_xlfn.XLOOKUP("Market Capitalization",Inputs!$B:$B,Inputs!L:L)/_xlfn.XLOOKUP("Revenue (Sales)",Inputs!$B:$B,Inputs!L:L),"") | L7: =IFERROR(_xlfn.XLOOKUP("Market Capitalization",Inputs!$B:$B,Inputs!M:M)/_xlfn.XLOOKUP("Revenue (Sales)",Inputs!$B:$B,Inputs!M:M),"") | M7: =IFERROR(_xlfn.XLOOKUP("Market Capitalization",Inputs!$B:$B,Inputs!N:N)/_xlfn.XLOOKUP("Revenue (Sales)",Inputs!$B:$B,Inputs!N:N),"") | N7: =IFERROR(_xlfn.XLOOKUP("Market Capitalization",Inputs!$B:$B,Inputs!O:O)/_xlfn.XLOOKUP("Revenue (Sales)",Inputs!$B:$B,Inputs!O:O),"") | O7: =IFERROR(_xlfn.XLOOKUP("Market Capitalization",Inputs!$B:$B,Inputs!P:P)/_xlfn.XLOOKUP("Revenue (Sales)",Inputs!$B:$B,Inputs!P:P),"") | P7: =IFERROR(_xlfn.XLOOKUP("Market Capitalization",Inputs!$B:$B,Inputs!Q:Q)/_xlfn.XLOOKUP("Revenue (Sales)",Inputs!$B:$B,Inputs!Q:Q),"") | Q7: =IFERROR(_xlfn.XLOOKUP("Equity Value",DCF!$B:$B,DCF!R:R)/_xlfn.XLOOKUP("Revenue (Sales)",DCF!$B:$B,DCF!H:H),"") | R7: =IFERROR(_xlfn.XLOOKUP("Equity Value",DCF!$B:$B,DCF!S:S)/_xlfn.XLOOKUP("Revenue (Sales)",DCF!$B:$B,DCF!I:I),"")
B8: EV / EBITDA | F8: =IFERROR(_xlfn.XLOOKUP("Enterprise Value",Inputs!$B:$B,Inputs!G:G)/_xlfn.XLOOKUP("EBITDA",Inputs!$B:$B,Inputs!G:G),"") | G8: =IFERROR(_xlfn.XLOOKUP("Enterprise Value",Inputs!$B:$B,Inputs!H:H)/_xlfn.XLOOKUP("EBITDA",Inputs!$B:$B,Inputs!H:H),"") | H8: =IFERROR(_xlfn.XLOOKUP("Enterprise Value",Inputs!$B:$B,Inputs!I:I)/_xlfn.XLOOKUP("EBITDA",Inputs!$B:$B,Inputs!I:I),"") | I8: =IFERROR(_xlfn.XLOOKUP("Enterprise Value",Inputs!$B:$B,Inputs!J:J)/_xlfn.XLOOKUP("EBITDA",Inputs!$B:$B,Inputs!J:J),"") | J8: =IFERROR(_xlfn.XLOOKUP("Enterprise Value",Inputs!$B:$B,Inputs!K:K)/_xlfn.XLOOKUP("EBITDA",Inputs!$B:$B,Inputs!K:K),"") | K8: =IFERROR(_xlfn.XLOOKUP("Enterprise Value",Inputs!$B:$B,Inputs!L:L)/_xlfn.XLOOKUP("EBITDA",Inputs!$B:$B,Inputs!L:L),"") | L8: =IFERROR(_xlfn.XLOOKUP("Enterprise Value",Inputs!$B:$B,Inputs!M:M)/_xlfn.XLOOKUP("EBITDA",Inputs!$B:$B,Inputs!M:M),"") | M8: =IFERROR(_xlfn.XLOOKUP("Enterprise Value",Inputs!$B:$B,Inputs!N:N)/_xlfn.XLOOKUP("EBITDA",Inputs!$B:$B,Inputs!N:N),"") | N8: =IFERROR(_xlfn.XLOOKUP("Enterprise Value",Inputs!$B:$B,Inputs!O:O)/_xlfn.XLOOKUP("EBITDA",Inputs!$B:$B,Inputs!O:O),"") | O8: =IFERROR(_xlfn.XLOOKUP("Enterprise Value",Inputs!$B:$B,Inputs!P:P)/_xlfn.XLOOKUP("EBITDA",Inputs!$B:$B,Inputs!P:P),"") | P8: =IFERROR(_xlfn.XLOOKUP("Enterprise Value",Inputs!$B:$B,Inputs!Q:Q)/_xlfn.XLOOKUP("EBITDA",Inputs!$B:$B,Inputs!Q:Q),"") | Q8: =IFERROR(_xlfn.XLOOKUP("Enterprise Value",DCF!$B:$B,DCF!R:R)/_xlfn.XLOOKUP("EBITDA",DCF!$B:$B,DCF!H:H),"") | R8: =IFERROR(_xlfn.XLOOKUP("Enterprise Value",DCF!$B:$B,DCF!S:S)/_xlfn.XLOOKUP("EBITDA",DCF!$B:$B,DCF!I:I),"")
B9: EV / EBIT | F9: =IFERROR(_xlfn.XLOOKUP("Enterprise Value",Inputs!$B:$B,Inputs!G:G)/_xlfn.XLOOKUP("Operating Income (EBIT)",Inputs!$B:$B,Inputs!G:G),"") | G9: =IFERROR(_xlfn.XLOOKUP("Enterprise Value",Inputs!$B:$B,Inputs!H:H)/_xlfn.XLOOKUP("Operating Income (EBIT)",Inputs!$B:$B,Inputs!H:H),"") | H9: =IFERROR(_xlfn.XLOOKUP("Enterprise Value",Inputs!$B:$B,Inputs!I:I)/_xlfn.XLOOKUP("Operating Income (EBIT)",Inputs!$B:$B,Inputs!I:I),"") | I9: =IFERROR(_xlfn.XLOOKUP("Enterprise Value",Inputs!$B:$B,Inputs!J:J)/_xlfn.XLOOKUP("Operating Income (EBIT)",Inputs!$B:$B,Inputs!J:J),"") | J9: =IFERROR(_xlfn.XLOOKUP("Enterprise Value",Inputs!$B:$B,Inputs!K:K)/_xlfn.XLOOKUP("Operating Income (EBIT)",Inputs!$B:$B,Inputs!K:K),"") | K9: =IFERROR(_xlfn.XLOOKUP("Enterprise Value",Inputs!$B:$B,Inputs!L:L)/_xlfn.XLOOKUP("Operating Income (EBIT)",Inputs!$B:$B,Inputs!L:L),"") | L9: =IFERROR(_xlfn.XLOOKUP("Enterprise Value",Inputs!$B:$B,Inputs!M:M)/_xlfn.XLOOKUP("Operating Income (EBIT)",Inputs!$B:$B,Inputs!M:M),"") | M9: =IFERROR(_xlfn.XLOOKUP("Enterprise Value",Inputs!$B:$B,Inputs!N:N)/_xlfn.XLOOKUP("Operating Income (EBIT)",Inputs!$B:$B,Inputs!N:N),"") | N9: =IFERROR(_xlfn.XLOOKUP("Enterprise Value",Inputs!$B:$B,Inputs!O:O)/_xlfn.XLOOKUP("Operating Income (EBIT)",Inputs!$B:$B,Inputs!O:O),"") | O9: =IFERROR(_xlfn.XLOOKUP("Enterprise Value",Inputs!$B:$B,Inputs!P:P)/_xlfn.XLOOKUP("Operating Income (EBIT)",Inputs!$B:$B,Inputs!P:P),"") | P9: =IFERROR(_xlfn.XLOOKUP("Enterprise Value",Inputs!$B:$B,Inputs!Q:Q)/_xlfn.XLOOKUP("Operating Income (EBIT)",Inputs!$B:$B,Inputs!Q:Q),"") | Q9: =IFERROR(_xlfn.XLOOKUP("Enterprise Value",DCF!$B:$B,DCF!R:R)/_xlfn.XLOOKUP("Operating Income (EBIT)",DCF!$B:$B,DCF!H:H),"") | R9: =IFERROR(_xlfn.XLOOKUP("Enterprise Value",DCF!$B:$B,DCF!S:S)/_xlfn.XLOOKUP("Operating Income (EBIT)",DCF!$B:$B,DCF!I:I),"")
B10: Price / Earnings | F10: =IFERROR(_xlfn.XLOOKUP("Market Capitalization",Inputs!$B:$B,Inputs!G:G)/_xlfn.XLOOKUP("Net Income",Inputs!$B:$B,Inputs!G:G),"") | G10: =IFERROR(_xlfn.XLOOKUP("Market Capitalization",Inputs!$B:$B,Inputs!H:H)/_xlfn.XLOOKUP("Net Income",Inputs!$B:$B,Inputs!H:H),"") | H10: =IFERROR(_xlfn.XLOOKUP("Market Capitalization",Inputs!$B:$B,Inputs!I:I)/_xlfn.XLOOKUP("Net Income",Inputs!$B:$B,Inputs!I:I),"") | I10: =IFERROR(_xlfn.XLOOKUP("Market Capitalization",Inputs!$B:$B,Inputs!J:J)/_xlfn.XLOOKUP("Net Income",Inputs!$B:$B,Inputs!J:J),"") | J10: =IFERROR(_xlfn.XLOOKUP("Market Capitalization",Inputs!$B:$B,Inputs!K:K)/_xlfn.XLOOKUP("Net Income",Inputs!$B:$B,Inputs!K:K),"") | K10: =IFERROR(_xlfn.XLOOKUP("Market Capitalization",Inputs!$B:$B,Inputs!L:L)/_xlfn.XLOOKUP("Net Income",Inputs!$B:$B,Inputs!L:L),"") | L10: =IFERROR(_xlfn.XLOOKUP("Market Capitalization",Inputs!$B:$B,Inputs!M:M)/_xlfn.XLOOKUP("Net Income",Inputs!$B:$B,Inputs!M:M),"") | M10: =IFERROR(_xlfn.XLOOKUP("Market Capitalization",Inputs!$B:$B,Inputs!N:N)/_xlfn.XLOOKUP("Net Income",Inputs!$B:$B,Inputs!N:N),"") | N10: =IFERROR(_xlfn.XLOOKUP("Market Capitalization",Inputs!$B:$B,Inputs!O:O)/_xlfn.XLOOKUP("Net Income",Inputs!$B:$B,Inputs!O:O),"") | O10: =IFERROR(_xlfn.XLOOKUP("Market Capitalization",Inputs!$B:$B,Inputs!P:P)/_xlfn.XLOOKUP("Net Income",Inputs!$B:$B,Inputs!P:P),"") | P10: =IFERROR(_xlfn.XLOOKUP("Market Capitalization",Inputs!$B:$B,Inputs!Q:Q)/_xlfn.XLOOKUP("Net Income",Inputs!$B:$B,Inputs!Q:Q),"") | Q10: =IFERROR(_xlfn.XLOOKUP("Equity Value",DCF!$B:$B,DCF!R:R)/_xlfn.XLOOKUP("Net Income",DCF!$B:$B,DCF!H:H),"") | R10: =IFERROR(_xlfn.XLOOKUP("Equity Value",DCF!$B:$B,DCF!S:S)/_xlfn.XLOOKUP("Net Income",DCF!$B:$B,DCF!I:I),"")
B11: Price / Book | F11: =IFERROR(_xlfn.XLOOKUP("Market Capitalization",Inputs!$B:$B,Inputs!G:G)/_xlfn.XLOOKUP("Shareholder's Equity",Inputs!$B:$B,Inputs!G:G),"") | G11: =IFERROR(_xlfn.XLOOKUP("Market Capitalization",Inputs!$B:$B,Inputs!H:H)/_xlfn.XLOOKUP("Shareholder's Equity",Inputs!$B:$B,Inputs!H:H),"") | H11: =IFERROR(_xlfn.XLOOKUP("Market Capitalization",Inputs!$B:$B,Inputs!I:I)/_xlfn.XLOOKUP("Shareholder's Equity",Inputs!$B:$B,Inputs!I:I),"") | I11: =IFERROR(_xlfn.XLOOKUP("Market Capitalization",Inputs!$B:$B,Inputs!J:J)/_xlfn.XLOOKUP("Shareholder's Equity",Inputs!$B:$B,Inputs!J:J),"") | J11: =IFERROR(_xlfn.XLOOKUP("Market Capitalization",Inputs!$B:$B,Inputs!K:K)/_xlfn.XLOOKUP("Shareholder's Equity",Inputs!$B:$B,Inputs!K:K),"") | K11: =IFERROR(_xlfn.XLOOKUP("Market Capitalization",Inputs!$B:$B,Inputs!L:L)/_xlfn.XLOOKUP("Shareholder's Equity",Inputs!$B:$B,Inputs!L:L),"") | L11: =IFERROR(_xlfn.XLOOKUP("Market Capitalization",Inputs!$B:$B,Inputs!M:M)/_xlfn.XLOOKUP("Shareholder's Equity",Inputs!$B:$B,Inputs!M:M),"") | M11: =IFERROR(_xlfn.XLOOKUP("Market Capitalization",Inputs!$B:$B,Inputs!N:N)/_xlfn.XLOOKUP("Shareholder's Equity",Inputs!$B:$B,Inputs!N:N),"") | N11: =IFERROR(_xlfn.XLOOKUP("Market Capitalization",Inputs!$B:$B,Inputs!O:O)/_xlfn.XLOOKUP("Shareholder's Equity",Inputs!$B:$B,Inputs!O:O),"") | O11: =IFERROR(_xlfn.XLOOKUP("Market Capitalization",Inputs!$B:$B,Inputs!P:P)/_xlfn.XLOOKUP("Shareholder's Equity",Inputs!$B:$B,Inputs!P:P),"") | P11: =IFERROR(_xlfn.XLOOKUP("Market Capitalization",Inputs!$B:$B,Inputs!Q:Q)/_xlfn.XLOOKUP("Shareholder's Equity",Inputs!$B:$B,Inputs!Q:Q),"") | Q11: =IFERROR(+_xlfn.XLOOKUP("Equity Value",DCF!$B:$B,DCF!R:R)/(_xlfn.XLOOKUP("Shareholder's Equity",Inputs!$B:$B,Inputs!$Q:$Q)+_xlfn.XLOOKUP("Net Income",DCF!$B:$B,DCF!H:H)+_xlfn.XLOOKUP("Total Payout",DCF!$B:$B,DCF!H:H)),"") | R11: =IFERROR(+_xlfn.XLOOKUP("Equity Value",DCF!$B:$B,DCF!S:S)/(_xlfn.XLOOKUP("Shareholder's Equity",Inputs!$B:$B,Inputs!$Q:$Q)+_xlfn.XLOOKUP("Net Income",DCF!$B:$B,DCF!I:I)+_xlfn.XLOOKUP("Total Payout",DCF!$B:$B,DCF!I:I)),"")
B13: Profitability | F13: 2014 | G13: =+F13+1 -> 2015 | H13: =+G13+1 -> 2016 | I13: =+H13+1 -> 2017 | J13: =+I13+1 -> 2018 | K13: =+J13+1 -> 2019 | L13: =+K13+1 -> 2020 | M13: =+L13+1 -> 2021 | N13: 2022 | O13: =+N13+1 -> 2023 | P13: =+O13+1 -> 2024 | Q13: =+P13+1 -> 2025 | R13: =+Q13+1 -> 2026
B15: Return on Assets | F15: =+IFERROR(_xlfn.XLOOKUP("Net Income",Inputs!$B:$B,Inputs!G:G)/_xlfn.XLOOKUP("Total Assets",Inputs!$B:$B,Inputs!G:G),"") | G15: =+IFERROR(_xlfn.XLOOKUP("Net Income",Inputs!$B:$B,Inputs!H:H)/_xlfn.XLOOKUP("Total Assets",Inputs!$B:$B,Inputs!H:H),"") | H15: =+IFERROR(_xlfn.XLOOKUP("Net Income",Inputs!$B:$B,Inputs!I:I)/_xlfn.XLOOKUP("Total Assets",Inputs!$B:$B,Inputs!I:I),"") | I15: =+IFERROR(_xlfn.XLOOKUP("Net Income",Inputs!$B:$B,Inputs!J:J)/_xlfn.XLOOKUP("Total Assets",Inputs!$B:$B,Inputs!J:J),"") | J15: =+IFERROR(_xlfn.XLOOKUP("Net Income",Inputs!$B:$B,Inputs!K:K)/_xlfn.XLOOKUP("Total Assets",Inputs!$B:$B,Inputs!K:K),"") | K15: =+IFERROR(_xlfn.XLOOKUP("Net Income",Inputs!$B:$B,Inputs!L:L)/_xlfn.XLOOKUP("Total Assets",Inputs!$B:$B,Inputs!L:L),"") | L15: =+IFERROR(_xlfn.XLOOKUP("Net Income",Inputs!$B:$B,Inputs!M:M)/_xlfn.XLOOKUP("Total Assets",Inputs!$B:$B,Inputs!M:M),"") | M15: =+IFERROR(_xlfn.XLOOKUP("Net Income",Inputs!$B:$B,Inputs!N:N)/_xlfn.XLOOKUP("Total Assets",Inputs!$B:$B,Inputs!N:N),"") | N15: =+IFERROR(_xlfn.XLOOKUP("Net Income",Inputs!$B:$B,Inputs!O:O)/_xlfn.XLOOKUP("Total Assets",Inputs!$B:$B,Inputs!O:O),"") | O15: =+IFERROR(_xlfn.XLOOKUP("Net Income",Inputs!$B:$B,Inputs!P:P)/_xlfn.XLOOKUP("Total Assets",Inputs!$B:$B,Inputs!P:P),"") | P15: =+IFERROR(_xlfn.XLOOKUP("Net Income",Inputs!$B:$B,Inputs!Q:Q)/_xlfn.XLOOKUP("Total Assets",Inputs!$B:$B,Inputs!Q:Q),"") | Q15: =IFERROR(_xlfn.XLOOKUP("Net Income",DCF!$B:$B,DCF!H:H)/_xlfn.XLOOKUP("Total assets",DCF!$6:$6,DCF!10:10),"") | R15: =IFERROR(_xlfn.XLOOKUP("Net Income",DCF!$B:$B,DCF!I:I)/_xlfn.XLOOKUP("Total assets",DCF!$6:$6,DCF!10:10),"")
B16: Return on Equity | F16: =IFERROR(_xlfn.XLOOKUP("Net Income",Inputs!$B:$B,Inputs!G:G)/_xlfn.XLOOKUP("Shareholder's Equity",Inputs!$B:$B,Inputs!G:G),"") | G16: =IFERROR(_xlfn.XLOOKUP("Net Income",Inputs!$B:$B,Inputs!H:H)/_xlfn.XLOOKUP("Shareholder's Equity",Inputs!$B:$B,Inputs!H:H),"") | H16: =IFERROR(_xlfn.XLOOKUP("Net Income",Inputs!$B:$B,Inputs!I:I)/_xlfn.XLOOKUP("Shareholder's Equity",Inputs!$B:$B,Inputs!I:I),"") | I16: =IFERROR(_xlfn.XLOOKUP("Net Income",Inputs!$B:$B,Inputs!J:J)/_xlfn.XLOOKUP("Shareholder's Equity",Inputs!$B:$B,Inputs!J:J),"") | J16: =IFERROR(_xlfn.XLOOKUP("Net Income",Inputs!$B:$B,Inputs!K:K)/_xlfn.XLOOKUP("Shareholder's Equity",Inputs!$B:$B,Inputs!K:K),"") | K16: =IFERROR(_xlfn.XLOOKUP("Net Income",Inputs!$B:$B,Inputs!L:L)/_xlfn.XLOOKUP("Shareholder's Equity",Inputs!$B:$B,Inputs!L:L),"") | L16: =IFERROR(_xlfn.XLOOKUP("Net Income",Inputs!$B:$B,Inputs!M:M)/_xlfn.XLOOKUP("Shareholder's Equity",Inputs!$B:$B,Inputs!M:M),"") | M16: =IFERROR(_xlfn.XLOOKUP("Net Income",Inputs!$B:$B,Inputs!N:N)/_xlfn.XLOOKUP("Shareholder's Equity",Inputs!$B:$B,Inputs!N:N),"") | N16: =IFERROR(_xlfn.XLOOKUP("Net Income",Inputs!$B:$B,Inputs!O:O)/_xlfn.XLOOKUP("Shareholder's Equity",Inputs!$B:$B,Inputs!O:O),"") | O16: =IFERROR(_xlfn.XLOOKUP("Net Income",Inputs!$B:$B,Inputs!P:P)/_xlfn.XLOOKUP("Shareholder's Equity",Inputs!$B:$B,Inputs!P:P),"") | P16: =IFERROR(_xlfn.XLOOKUP("Net Income",Inputs!$B:$B,Inputs!Q:Q)/_xlfn.XLOOKUP("Shareholder's Equity",Inputs!$B:$B,Inputs!Q:Q),"") | Q16: =IFERROR(_xlfn.XLOOKUP("Net Income",DCF!$B:$B,DCF!H:H)/_xlfn.XLOOKUP("Shareholder's Equity",DCF!$6:$6,DCF!10:10),"") | R16: =IFERROR(_xlfn.XLOOKUP("Net Income",DCF!$B:$B,DCF!I:I)/_xlfn.XLOOKUP("Shareholder's Equity",DCF!$6:$6,DCF!10:10),"")
B17: Return on Total Capital | F17: =IFERROR(_xlfn.XLOOKUP("NOPAT",Inputs!$B:$B,Inputs!G:G)/(_xlfn.XLOOKUP("Shareholder's Equity",Inputs!$B:$B,Inputs!G:G)+_xlfn.XLOOKUP("Total Debt",Inputs!$B:$B,Inputs!G:G,,,-1)),"") | G17: =IFERROR(_xlfn.XLOOKUP("NOPAT",Inputs!$B:$B,Inputs!H:H)/(_xlfn.XLOOKUP("Shareholder's Equity",Inputs!$B:$B,Inputs!H:H)+_xlfn.XLOOKUP("Total Debt",Inputs!$B:$B,Inputs!H:H,,,-1)),"") | H17: =IFERROR(_xlfn.XLOOKUP("NOPAT",Inputs!$B:$B,Inputs!I:I)/(_xlfn.XLOOKUP("Shareholder's Equity",Inputs!$B:$B,Inputs!I:I)+_xlfn.XLOOKUP("Total Debt",Inputs!$B:$B,Inputs!I:I,,,-1)),"") | I17: =IFERROR(_xlfn.XLOOKUP("NOPAT",Inputs!$B:$B,Inputs!J:J)/(_xlfn.XLOOKUP("Shareholder's Equity",Inputs!$B:$B,Inputs!J:J)+_xlfn.XLOOKUP("Total Debt",Inputs!$B:$B,Inputs!J:J,,,-1)),"") | J17: =IFERROR(_xlfn.XLOOKUP("NOPAT",Inputs!$B:$B,Inputs!K:K)/(_xlfn.XLOOKUP("Shareholder's Equity",Inputs!$B:$B,Inputs!K:K)+_xlfn.XLOOKUP("Total Debt",Inputs!$B:$B,Inputs!K:K,,,-1)),"") | K17: =IFERROR(_xlfn.XLOOKUP("NOPAT",Inputs!$B:$B,Inputs!L:L)/(_xlfn.XLOOKUP("Shareholder's Equity",Inputs!$B:$B,Inputs!L:L)+_xlfn.XLOOKUP("Total Debt",Inputs!$B:$B,Inputs!L:L,,,-1)),"") | L17: =IFERROR(_xlfn.XLOOKUP("NOPAT",Inputs!$B:$B,Inputs!M:M)/(_xlfn.XLOOKUP("Shareholder's Equity",Inputs!$B:$B,Inputs!M:M)+_xlfn.XLOOKUP("Total Debt",Inputs!$B:$B,Inputs!M:M,,,-1)),"") | M17: =IFERROR(_xlfn.XLOOKUP("NOPAT",Inputs!$B:$B,Inputs!N:N)/(_xlfn.XLOOKUP("Shareholder's Equity",Inputs!$B:$B,Inputs!N:N)+_xlfn.XLOOKUP("Total Debt",Inputs!$B:$B,Inputs!N:N,,,-1)),"") | N17: =IFERROR(_xlfn.XLOOKUP("NOPAT",Inputs!$B:$B,Inputs!O:O)/(_xlfn.XLOOKUP("Shareholder's Equity",Inputs!$B:$B,Inputs!O:O)+_xlfn.XLOOKUP("Total Debt",Inputs!$B:$B,Inputs!O:O,,,-1)),"") | O17: =IFERROR(_xlfn.XLOOKUP("NOPAT",Inputs!$B:$B,Inputs!P:P)/(_xlfn.XLOOKUP("Shareholder's Equity",Inputs!$B:$B,Inputs!P:P)+_xlfn.XLOOKUP("Total Debt",Inputs!$B:$B,Inputs!P:P,,,-1)),"") | P17: =IFERROR(_xlfn.XLOOKUP("NOPAT",Inputs!$B:$B,Inputs!Q:Q)/(_xlfn.XLOOKUP("Shareholder's Equity",Inputs!$B:$B,Inputs!Q:Q)+_xlfn.XLOOKUP("Total Debt",Inputs!$B:$B,Inputs!Q:Q,,,-1)),"") | Q17: =+IFERROR(_xlfn.XLOOKUP("NOPAT",DCF!$B:$B,DCF!H:H)/(_xlfn.XLOOKUP("Shareholder's Equity",DCF!$6:$6,DCF!10:10)+_xlfn.XLOOKUP("Total Borrowings",DCF!$B:$B,DCF!H:H)+_xlfn.XLOOKUP("Total Leases",DCF!$B:$B,DCF!H:H)),"") | R17: =+IFERROR(_xlfn.XLOOKUP("NOPAT",DCF!$B:$B,DCF!I:I)/(_xlfn.XLOOKUP("Shareholder's Equity",DCF!$6:$6,DCF!10:10)+_xlfn.XLOOKUP("Total Borrowings",DCF!$B:$B,DCF!I:I)+_xlfn.XLOOKUP("Total Leases",DCF!$B:$B,DCF!I:I)),"")
B18: EBITDA Margin | F18: =+IFERROR(_xlfn.XLOOKUP("EBITDA",Inputs!$B:$B,Inputs!G:G)/_xlfn.XLOOKUP("Revenue (Sales)",Inputs!$B:$B,Inputs!G:G),"") | G18: =+IFERROR(_xlfn.XLOOKUP("EBITDA",Inputs!$B:$B,Inputs!H:H)/_xlfn.XLOOKUP("Revenue (Sales)",Inputs!$B:$B,Inputs!H:H),"") | H18: =+IFERROR(_xlfn.XLOOKUP("EBITDA",Inputs!$B:$B,Inputs!I:I)/_xlfn.XLOOKUP("Revenue (Sales)",Inputs!$B:$B,Inputs!I:I),"") | I18: =+IFERROR(_xlfn.XLOOKUP("EBITDA",Inputs!$B:$B,Inputs!J:J)/_xlfn.XLOOKUP("Revenue (Sales)",Inputs!$B:$B,Inputs!J:J),"") | J18: =+IFERROR(_xlfn.XLOOKUP("EBITDA",Inputs!$B:$B,Inputs!K:K)/_xlfn.XLOOKUP("Revenue (Sales)",Inputs!$B:$B,Inputs!K:K),"") | K18: =+IFERROR(_xlfn.XLOOKUP("EBITDA",Inputs!$B:$B,Inputs!L:L)/_xlfn.XLOOKUP("Revenue (Sales)",Inputs!$B:$B,Inputs!L:L),"") | L18: =+IFERROR(_xlfn.XLOOKUP("EBITDA",Inputs!$B:$B,Inputs!M:M)/_xlfn.XLOOKUP("Revenue (Sales)",Inputs!$B:$B,Inputs!M:M),"") | M18: =+IFERROR(_xlfn.XLOOKUP("EBITDA",Inputs!$B:$B,Inputs!N:N)/_xlfn.XLOOKUP("Revenue (Sales)",Inputs!$B:$B,Inputs!N:N),"") | N18: =+IFERROR(_xlfn.XLOOKUP("EBITDA",Inputs!$B:$B,Inputs!O:O)/_xlfn.XLOOKUP("Revenue (Sales)",Inputs!$B:$B,Inputs!O:O),"") | O18: =+IFERROR(_xlfn.XLOOKUP("EBITDA",Inputs!$B:$B,Inputs!P:P)/_xlfn.XLOOKUP("Revenue (Sales)",Inputs!$B:$B,Inputs!P:P),"") | P18: =+IFERROR(_xlfn.XLOOKUP("EBITDA",Inputs!$B:$B,Inputs!Q:Q)/_xlfn.XLOOKUP("Revenue (Sales)",Inputs!$B:$B,Inputs!Q:Q),"") | Q18: =+_xlfn.XLOOKUP("EBITDA Margin",DCF!$B:$B,DCF!H:H) | R18: =+_xlfn.XLOOKUP("EBITDA Margin",DCF!$B:$B,DCF!I:I)
B19: EBIT Margin | F19: =IFERROR(_xlfn.XLOOKUP("Operating Income (EBIT)",Inputs!$B:$B,Inputs!G:G)/_xlfn.XLOOKUP("Revenue (Sales)",Inputs!$B:$B,Inputs!G:G),"") | G19: =IFERROR(_xlfn.XLOOKUP("Operating Income (EBIT)",Inputs!$B:$B,Inputs!H:H)/_xlfn.XLOOKUP("Revenue (Sales)",Inputs!$B:$B,Inputs!H:H),"") | H19: =IFERROR(_xlfn.XLOOKUP("Operating Income (EBIT)",Inputs!$B:$B,Inputs!I:I)/_xlfn.XLOOKUP("Revenue (Sales)",Inputs!$B:$B,Inputs!I:I),"") | I19: =IFERROR(_xlfn.XLOOKUP("Operating Income (EBIT)",Inputs!$B:$B,Inputs!J:J)/_xlfn.XLOOKUP("Revenue (Sales)",Inputs!$B:$B,Inputs!J:J),"") | J19: =IFERROR(_xlfn.XLOOKUP("Operating Income (EBIT)",Inputs!$B:$B,Inputs!K:K)/_xlfn.XLOOKUP("Revenue (Sales)",Inputs!$B:$B,Inputs!K:K),"") | K19: =IFERROR(_xlfn.XLOOKUP("Operating Income (EBIT)",Inputs!$B:$B,Inputs!L:L)/_xlfn.XLOOKUP("Revenue (Sales)",Inputs!$B:$B,Inputs!L:L),"") | L19: =IFERROR(_xlfn.XLOOKUP("Operating Income (EBIT)",Inputs!$B:$B,Inputs!M:M)/_xlfn.XLOOKUP("Revenue (Sales)",Inputs!$B:$B,Inputs!M:M),"") | M19: =IFERROR(_xlfn.XLOOKUP("Operating Income (EBIT)",Inputs!$B:$B,Inputs!N:N)/_xlfn.XLOOKUP("Revenue (Sales)",Inputs!$B:$B,Inputs!N:N),"") | N19: =IFERROR(_xlfn.XLOOKUP("Operating Income (EBIT)",Inputs!$B:$B,Inputs!O:O)/_xlfn.XLOOKUP("Revenue (Sales)",Inputs!$B:$B,Inputs!O:O),"") | O19: =IFERROR(_xlfn.XLOOKUP("Operating Income (EBIT)",Inputs!$B:$B,Inputs!P:P)/_xlfn.XLOOKUP("Revenue (Sales)",Inputs!$B:$B,Inputs!P:P),"") | P19: =IFERROR(_xlfn.XLOOKUP("Operating Income (EBIT)",Inputs!$B:$B,Inputs!Q:Q)/_xlfn.XLOOKUP("Revenue (Sales)",Inputs!$B:$B,Inputs!Q:Q),"") | Q19: =+_xlfn.XLOOKUP("Operating Margin",DCF!$B:$B,DCF!H:H) | R19: =+_xlfn.XLOOKUP("Operating Margin",DCF!$B:$B,DCF!I:I)
B20: EBT Margin | F20: =IFERROR(_xlfn.XLOOKUP("Pre-Tax Income (EBT)",Inputs!$B:$B,Inputs!G:G)/_xlfn.XLOOKUP("Revenue (Sales)",Inputs!$B:$B,Inputs!G:G),"") | G20: =IFERROR(_xlfn.XLOOKUP("Pre-Tax Income (EBT)",Inputs!$B:$B,Inputs!H:H)/_xlfn.XLOOKUP("Revenue (Sales)",Inputs!$B:$B,Inputs!H:H),"") | H20: =IFERROR(_xlfn.XLOOKUP("Pre-Tax Income (EBT)",Inputs!$B:$B,Inputs!I:I)/_xlfn.XLOOKUP("Revenue (Sales)",Inputs!$B:$B,Inputs!I:I),"") | I20: =IFERROR(_xlfn.XLOOKUP("Pre-Tax Income (EBT)",Inputs!$B:$B,Inputs!J:J)/_xlfn.XLOOKUP("Revenue (Sales)",Inputs!$B:$B,Inputs!J:J),"") | J20: =IFERROR(_xlfn.XLOOKUP("Pre-Tax Income (EBT)",Inputs!$B:$B,Inputs!K:K)/_xlfn.XLOOKUP("Revenue (Sales)",Inputs!$B:$B,Inputs!K:K),"") | K20: =IFERROR(_xlfn.XLOOKUP("Pre-Tax Income (EBT)",Inputs!$B:$B,Inputs!L:L)/_xlfn.XLOOKUP("Revenue (Sales)",Inputs!$B:$B,Inputs!L:L),"") | L20: =IFERROR(_xlfn.XLOOKUP("Pre-Tax Income (EBT)",Inputs!$B:$B,Inputs!M:M)/_xlfn.XLOOKUP("Revenue (Sales)",Inputs!$B:$B,Inputs!M:M),"") | M20: =IFERROR(_xlfn.XLOOKUP("Pre-Tax Income (EBT)",Inputs!$B:$B,Inputs!N:N)/_xlfn.XLOOKUP("Revenue (Sales)",Inputs!$B:$B,Inputs!N:N),"") | N20: =IFERROR(_xlfn.XLOOKUP("Pre-Tax Income (EBT)",Inputs!$B:$B,Inputs!O:O)/_xlfn.XLOOKUP("Revenue (Sales)",Inputs!$B:$B,Inputs!O:O),"") | O20: =IFERROR(_xlfn.XLOOKUP("Pre-Tax Income (EBT)",Inputs!$B:$B,Inputs!P:P)/_xlfn.XLOOKUP("Revenue (Sales)",Inputs!$B:$B,Inputs!P:P),"") | P20: =IFERROR(_xlfn.XLOOKUP("Pre-Tax Income (EBT)",Inputs!$B:$B,Inputs!Q:Q)/_xlfn.XLOOKUP("Revenue (Sales)",Inputs!$B:$B,Inputs!Q:Q),"") | Q20: =IFERROR(_xlfn.XLOOKUP("Pre-Tax Income (EBT)",DCF!$B:$B,DCF!H:H)/_xlfn.XLOOKUP("Revenue (Sales)",DCF!$B:$B,DCF!H:H),"") | R20: =IFERROR(_xlfn.XLOOKUP("Pre-Tax Income (EBT)",DCF!$B:$B,DCF!I:I)/_xlfn.XLOOKUP("Revenue (Sales)",DCF!$B:$B,DCF!I:I),"")
B21: Gross Profit Margin | F21: =IFERROR(_xlfn.XLOOKUP("Gross Profit",Inputs!$B:$B,Inputs!G:G)/_xlfn.XLOOKUP("Revenue (Sales)",Inputs!$B:$B,Inputs!G:G),"") | G21: =IFERROR(_xlfn.XLOOKUP("Gross Profit",Inputs!$B:$B,Inputs!H:H)/_xlfn.XLOOKUP("Revenue (Sales)",Inputs!$B:$B,Inputs!H:H),"") | H21: =IFERROR(_xlfn.XLOOKUP("Gross Profit",Inputs!$B:$B,Inputs!I:I)/_xlfn.XLOOKUP("Revenue (Sales)",Inputs!$B:$B,Inputs!I:I),"") | I21: =IFERROR(_xlfn.XLOOKUP("Gross Profit",Inputs!$B:$B,Inputs!J:J)/_xlfn.XLOOKUP("Revenue (Sales)",Inputs!$B:$B,Inputs!J:J),"") | J21: =IFERROR(_xlfn.XLOOKUP("Gross Profit",Inputs!$B:$B,Inputs!K:K)/_xlfn.XLOOKUP("Revenue (Sales)",Inputs!$B:$B,Inputs!K:K),"") | K21: =IFERROR(_xlfn.XLOOKUP("Gross Profit",Inputs!$B:$B,Inputs!L:L)/_xlfn.XLOOKUP("Revenue (Sales)",Inputs!$B:$B,Inputs!L:L),"") | L21: =IFERROR(_xlfn.XLOOKUP("Gross Profit",Inputs!$B:$B,Inputs!M:M)/_xlfn.XLOOKUP("Revenue (Sales)",Inputs!$B:$B,Inputs!M:M),"") | M21: =IFERROR(_xlfn.XLOOKUP("Gross Profit",Inputs!$B:$B,Inputs!N:N)/_xlfn.XLOOKUP("Revenue (Sales)",Inputs!$B:$B,Inputs!N:N),"") | N21: =IFERROR(_xlfn.XLOOKUP("Gross Profit",Inputs!$B:$B,Inputs!O:O)/_xlfn.XLOOKUP("Revenue (Sales)",Inputs!$B:$B,Inputs!O:O),"") | O21: =IFERROR(_xlfn.XLOOKUP("Gross Profit",Inputs!$B:$B,Inputs!P:P)/_xlfn.XLOOKUP("Revenue (Sales)",Inputs!$B:$B,Inputs!P:P),"") | P21: =IFERROR(_xlfn.XLOOKUP("Gross Profit",Inputs!$B:$B,Inputs!Q:Q)/_xlfn.XLOOKUP("Revenue (Sales)",Inputs!$B:$B,Inputs!Q:Q),"") | Q21: =+_xlfn.XLOOKUP("Gross Profit Margin",DCF!$B:$B,DCF!H:H) | R21: =+_xlfn.XLOOKUP("Gross Profit Margin",DCF!$B:$B,DCF!I:I)
B22: SG&A Margin | F22: =IFERROR(+_xlfn.XLOOKUP("SG&A (Selling, General & Administrative)",Inputs!$B:$B,Inputs!G:G)/_xlfn.XLOOKUP("Revenue (Sales)",Inputs!$B:$B,Inputs!G:G),"") | G22: =IFERROR(+_xlfn.XLOOKUP("SG&A (Selling, General & Administrative)",Inputs!$B:$B,Inputs!H:H)/_xlfn.XLOOKUP("Revenue (Sales)",Inputs!$B:$B,Inputs!H:H),"") | H22: =IFERROR(+_xlfn.XLOOKUP("SG&A (Selling, General & Administrative)",Inputs!$B:$B,Inputs!I:I)/_xlfn.XLOOKUP("Revenue (Sales)",Inputs!$B:$B,Inputs!I:I),"") | I22: =IFERROR(+_xlfn.XLOOKUP("SG&A (Selling, General & Administrative)",Inputs!$B:$B,Inputs!J:J)/_xlfn.XLOOKUP("Revenue (Sales)",Inputs!$B:$B,Inputs!J:J),"") | J22: =IFERROR(+_xlfn.XLOOKUP("SG&A (Selling, General & Administrative)",Inputs!$B:$B,Inputs!K:K)/_xlfn.XLOOKUP("Revenue (Sales)",Inputs!$B:$B,Inputs!K:K),"") | K22: =IFERROR(+_xlfn.XLOOKUP("SG&A (Selling, General & Administrative)",Inputs!$B:$B,Inputs!L:L)/_xlfn.XLOOKUP("Revenue (Sales)",Inputs!$B:$B,Inputs!L:L),"") | L22: =IFERROR(+_xlfn.XLOOKUP("SG&A (Selling, General & Administrative)",Inputs!$B:$B,Inputs!M:M)/_xlfn.XLOOKUP("Revenue (Sales)",Inputs!$B:$B,Inputs!M:M),"") | M22: =IFERROR(+_xlfn.XLOOKUP("SG&A (Selling, General & Administrative)",Inputs!$B:$B,Inputs!N:N)/_xlfn.XLOOKUP("Revenue (Sales)",Inputs!$B:$B,Inputs!N:N),"") | N22: =IFERROR(+_xlfn.XLOOKUP("SG&A (Selling, General & Administrative)",Inputs!$B:$B,Inputs!O:O)/_xlfn.XLOOKUP("Revenue (Sales)",Inputs!$B:$B,Inputs!O:O),"") | O22: =IFERROR(+_xlfn.XLOOKUP("SG&A (Selling, General & Administrative)",Inputs!$B:$B,Inputs!P:P)/_xlfn.XLOOKUP("Revenue (Sales)",Inputs!$B:$B,Inputs!P:P),"") | P22: =IFERROR(+_xlfn.XLOOKUP("SG&A (Selling, General & Administrative)",Inputs!$B:$B,Inputs!Q:Q)/_xlfn.XLOOKUP("Revenue (Sales)",Inputs!$B:$B,Inputs!Q:Q),"") | Q22: =+_xlfn.XLOOKUP("SG&A Margin",DCF!$B:$B,DCF!H:H) | R22: =+_xlfn.XLOOKUP("SG&A Margin",DCF!$B:$B,DCF!I:I)
B23: Net Income Margin | F23: =IFERROR(_xlfn.XLOOKUP("Net Income",Inputs!$B:$B,Inputs!G:G)/_xlfn.XLOOKUP("Revenue (Sales)",Inputs!$B:$B,Inputs!G:G),"") | G23: =IFERROR(_xlfn.XLOOKUP("Net Income",Inputs!$B:$B,Inputs!H:H)/_xlfn.XLOOKUP("Revenue (Sales)",Inputs!$B:$B,Inputs!H:H),"") | H23: =IFERROR(_xlfn.XLOOKUP("Net Income",Inputs!$B:$B,Inputs!I:I)/_xlfn.XLOOKUP("Revenue (Sales)",Inputs!$B:$B,Inputs!I:I),"") | I23: =IFERROR(_xlfn.XLOOKUP("Net Income",Inputs!$B:$B,Inputs!J:J)/_xlfn.XLOOKUP("Revenue (Sales)",Inputs!$B:$B,Inputs!J:J),"") | J23: =IFERROR(_xlfn.XLOOKUP("Net Income",Inputs!$B:$B,Inputs!K:K)/_xlfn.XLOOKUP("Revenue (Sales)",Inputs!$B:$B,Inputs!K:K),"") | K23: =IFERROR(_xlfn.XLOOKUP("Net Income",Inputs!$B:$B,Inputs!L:L)/_xlfn.XLOOKUP("Revenue (Sales)",Inputs!$B:$B,Inputs!L:L),"") | L23: =IFERROR(_xlfn.XLOOKUP("Net Income",Inputs!$B:$B,Inputs!M:M)/_xlfn.XLOOKUP("Revenue (Sales)",Inputs!$B:$B,Inputs!M:M),"") | M23: =IFERROR(_xlfn.XLOOKUP("Net Income",Inputs!$B:$B,Inputs!N:N)/_xlfn.XLOOKUP("Revenue (Sales)",Inputs!$B:$B,Inputs!N:N),"") | N23: =IFERROR(_xlfn.XLOOKUP("Net Income",Inputs!$B:$B,Inputs!O:O)/_xlfn.XLOOKUP("Revenue (Sales)",Inputs!$B:$B,Inputs!O:O),"") | O23: =IFERROR(_xlfn.XLOOKUP("Net Income",Inputs!$B:$B,Inputs!P:P)/_xlfn.XLOOKUP("Revenue (Sales)",Inputs!$B:$B,Inputs!P:P),"") | P23: =IFERROR(_xlfn.XLOOKUP("Net Income",Inputs!$B:$B,Inputs!Q:Q)/_xlfn.XLOOKUP("Revenue (Sales)",Inputs!$B:$B,Inputs!Q:Q),"") | Q23: =+_xlfn.XLOOKUP("Net Income Margin",DCF!$B:$B,DCF!H:H) | R23: =+_xlfn.XLOOKUP("Net Income Margin",DCF!$B:$B,DCF!I:I)
B25: Liquidity | F25: 2014 | G25: =+F25+1 -> 2015 | H25: =+G25+1 -> 2016 | I25: =+H25+1 -> 2017 | J25: =+I25+1 -> 2018 | K25: =+J25+1 -> 2019 | L25: =+K25+1 -> 2020 | M25: =+L25+1 -> 2021 | N25: 2022 | O25: =+N25+1 -> 2023 | P25: =+O25+1 -> 2024 | Q25: =+P25+1 -> 2025 | R25: =+Q25+1 -> 2026
B27: Cash Ratio | F27: =+IFERROR(_xlfn.XLOOKUP("Cash & Cash Equivalents",Inputs!$B:$B,Inputs!G:G)/_xlfn.XLOOKUP("Current Liabilities",Inputs!$B:$B,Inputs!G:G),"") | G27: =+IFERROR(_xlfn.XLOOKUP("Cash & Cash Equivalents",Inputs!$B:$B,Inputs!H:H)/_xlfn.XLOOKUP("Current Liabilities",Inputs!$B:$B,Inputs!H:H),"") | H27: =+IFERROR(_xlfn.XLOOKUP("Cash & Cash Equivalents",Inputs!$B:$B,Inputs!I:I)/_xlfn.XLOOKUP("Current Liabilities",Inputs!$B:$B,Inputs!I:I),"") | I27: =+IFERROR(_xlfn.XLOOKUP("Cash & Cash Equivalents",Inputs!$B:$B,Inputs!J:J)/_xlfn.XLOOKUP("Current Liabilities",Inputs!$B:$B,Inputs!J:J),"") | J27: =+IFERROR(_xlfn.XLOOKUP("Cash & Cash Equivalents",Inputs!$B:$B,Inputs!K:K)/_xlfn.XLOOKUP("Current Liabilities",Inputs!$B:$B,Inputs!K:K),"") | K27: =+IFERROR(_xlfn.XLOOKUP("Cash & Cash Equivalents",Inputs!$B:$B,Inputs!L:L)/_xlfn.XLOOKUP("Current Liabilities",Inputs!$B:$B,Inputs!L:L),"") | L27: =+IFERROR(_xlfn.XLOOKUP("Cash & Cash Equivalents",Inputs!$B:$B,Inputs!M:M)/_xlfn.XLOOKUP("Current Liabilities",Inputs!$B:$B,Inputs!M:M),"") | M27: =+IFERROR(_xlfn.XLOOKUP("Cash & Cash Equivalents",Inputs!$B:$B,Inputs!N:N)/_xlfn.XLOOKUP("Current Liabilities",Inputs!$B:$B,Inputs!N:N),"") | N27: =+IFERROR(_xlfn.XLOOKUP("Cash & Cash Equivalents",Inputs!$B:$B,Inputs!O:O)/_xlfn.XLOOKUP("Current Liabilities",Inputs!$B:$B,Inputs!O:O),"") | O27: =+IFERROR(_xlfn.XLOOKUP("Cash & Cash Equivalents",Inputs!$B:$B,Inputs!P:P)/_xlfn.XLOOKUP("Current Liabilities",Inputs!$B:$B,Inputs!P:P),"") | P27: =+IFERROR(_xlfn.XLOOKUP("Cash & Cash Equivalents",Inputs!$B:$B,Inputs!Q:Q)/_xlfn.XLOOKUP("Current Liabilities",Inputs!$B:$B,Inputs!Q:Q),"") | Q27: =+IFERROR((_xlfn.XLOOKUP("Cash & Cash Equivalents & ST Investments",DCF!$B:$B,DCF!H:H)-_xlfn.XLOOKUP("Short-Term Investments",Inputs!$B:$B,Inputs!$Q:$Q))/_xlfn.XLOOKUP("Current Liabilities",DCF!$6:$6,DCF!10:10),"") | R27: =+IFERROR((_xlfn.XLOOKUP("Cash & Cash Equivalents & ST Investments",DCF!$B:$B,DCF!I:I)-_xlfn.XLOOKUP("Short-Term Investments",Inputs!$B:$B,Inputs!$Q:$Q))/_xlfn.XLOOKUP("Current Liabilities",DCF!$6:$6,DCF!10:10),"")
B28: Quick Ratio | F28: =IFERROR((_xlfn.XLOOKUP("Cash & Cash Equivalents & ST Investments",Inputs!$B:$B,Inputs!G:G)+_xlfn.XLOOKUP("Accounts Receivable",Inputs!$B:$B,Inputs!G:G))/_xlfn.XLOOKUP("Current Liabilities",Inputs!$B:$B,Inputs!G:G),"") | G28: =IFERROR((_xlfn.XLOOKUP("Cash & Cash Equivalents & ST Investments",Inputs!$B:$B,Inputs!H:H)+_xlfn.XLOOKUP("Accounts Receivable",Inputs!$B:$B,Inputs!H:H))/_xlfn.XLOOKUP("Current Liabilities",Inputs!$B:$B,Inputs!H:H),"") | H28: =IFERROR((_xlfn.XLOOKUP("Cash & Cash Equivalents & ST Investments",Inputs!$B:$B,Inputs!I:I)+_xlfn.XLOOKUP("Accounts Receivable",Inputs!$B:$B,Inputs!I:I))/_xlfn.XLOOKUP("Current Liabilities",Inputs!$B:$B,Inputs!I:I),"") | I28: =IFERROR((_xlfn.XLOOKUP("Cash & Cash Equivalents & ST Investments",Inputs!$B:$B,Inputs!J:J)+_xlfn.XLOOKUP("Accounts Receivable",Inputs!$B:$B,Inputs!J:J))/_xlfn.XLOOKUP("Current Liabilities",Inputs!$B:$B,Inputs!J:J),"") | J28: =IFERROR((_xlfn.XLOOKUP("Cash & Cash Equivalents & ST Investments",Inputs!$B:$B,Inputs!K:K)+_xlfn.XLOOKUP("Accounts Receivable",Inputs!$B:$B,Inputs!K:K))/_xlfn.XLOOKUP("Current Liabilities",Inputs!$B:$B,Inputs!K:K),"") | K28: =IFERROR((_xlfn.XLOOKUP("Cash & Cash Equivalents & ST Investments",Inputs!$B:$B,Inputs!L:L)+_xlfn.XLOOKUP("Accounts Receivable",Inputs!$B:$B,Inputs!L:L))/_xlfn.XLOOKUP("Current Liabilities",Inputs!$B:$B,Inputs!L:L),"") | L28: =IFERROR((_xlfn.XLOOKUP("Cash & Cash Equivalents & ST Investments",Inputs!$B:$B,Inputs!M:M)+_xlfn.XLOOKUP("Accounts Receivable",Inputs!$B:$B,Inputs!M:M))/_xlfn.XLOOKUP("Current Liabilities",Inputs!$B:$B,Inputs!M:M),"") | M28: =IFERROR((_xlfn.XLOOKUP("Cash & Cash Equivalents & ST Investments",Inputs!$B:$B,Inputs!N:N)+_xlfn.XLOOKUP("Accounts Receivable",Inputs!$B:$B,Inputs!N:N))/_xlfn.XLOOKUP("Current Liabilities",Inputs!$B:$B,Inputs!N:N),"") | N28: =IFERROR((_xlfn.XLOOKUP("Cash & Cash Equivalents & ST Investments",Inputs!$B:$B,Inputs!O:O)+_xlfn.XLOOKUP("Accounts Receivable",Inputs!$B:$B,Inputs!O:O))/_xlfn.XLOOKUP("Current Liabilities",Inputs!$B:$B,Inputs!O:O),"") | O28: =IFERROR((_xlfn.XLOOKUP("Cash & Cash Equivalents & ST Investments",Inputs!$B:$B,Inputs!P:P)+_xlfn.XLOOKUP("Accounts Receivable",Inputs!$B:$B,Inputs!P:P))/_xlfn.XLOOKUP("Current Liabilities",Inputs!$B:$B,Inputs!P:P),"") | P28: =IFERROR((_xlfn.XLOOKUP("Cash & Cash Equivalents & ST Investments",Inputs!$B:$B,Inputs!Q:Q)+_xlfn.XLOOKUP("Accounts Receivable",Inputs!$B:$B,Inputs!Q:Q))/_xlfn.XLOOKUP("Current Liabilities",Inputs!$B:$B,Inputs!Q:Q),"") | Q28: =+IFERROR((_xlfn.XLOOKUP("Cash & Cash Equivalents & ST Investments",DCF!$B:$B,DCF!H:H)+_xlfn.XLOOKUP("Accounts Receivable",DCF!$B:$B,DCF!H:H))/_xlfn.XLOOKUP("Current Liabilities",DCF!$6:$6,DCF!10:10),"") | R28: =+IFERROR((_xlfn.XLOOKUP("Cash & Cash Equivalents & ST Investments",DCF!$B:$B,DCF!I:I)+_xlfn.XLOOKUP("Accounts Receivable",DCF!$B:$B,DCF!I:I))/_xlfn.XLOOKUP("Current Liabilities",DCF!$6:$6,DCF!10:10),"")
B29: Current Ratio | F29: =IFERROR(_xlfn.XLOOKUP("Current Assets",Inputs!$B:$B,Inputs!G:G)/+_xlfn.XLOOKUP("Current Liabilities",Inputs!$B:$B,Inputs!G:G),"") | G29: =IFERROR(_xlfn.XLOOKUP("Current Assets",Inputs!$B:$B,Inputs!H:H)/+_xlfn.XLOOKUP("Current Liabilities",Inputs!$B:$B,Inputs!H:H),"") | H29: =IFERROR(_xlfn.XLOOKUP("Current Assets",Inputs!$B:$B,Inputs!I:I)/+_xlfn.XLOOKUP("Current Liabilities",Inputs!$B:$B,Inputs!I:I),"") | I29: =IFERROR(_xlfn.XLOOKUP("Current Assets",Inputs!$B:$B,Inputs!J:J)/+_xlfn.XLOOKUP("Current Liabilities",Inputs!$B:$B,Inputs!J:J),"") | J29: =IFERROR(_xlfn.XLOOKUP("Current Assets",Inputs!$B:$B,Inputs!K:K)/+_xlfn.XLOOKUP("Current Liabilities",Inputs!$B:$B,Inputs!K:K),"") | K29: =IFERROR(_xlfn.XLOOKUP("Current Assets",Inputs!$B:$B,Inputs!L:L)/+_xlfn.XLOOKUP("Current Liabilities",Inputs!$B:$B,Inputs!L:L),"") | L29: =IFERROR(_xlfn.XLOOKUP("Current Assets",Inputs!$B:$B,Inputs!M:M)/+_xlfn.XLOOKUP("Current Liabilities",Inputs!$B:$B,Inputs!M:M),"") | M29: =IFERROR(_xlfn.XLOOKUP("Current Assets",Inputs!$B:$B,Inputs!N:N)/+_xlfn.XLOOKUP("Current Liabilities",Inputs!$B:$B,Inputs!N:N),"") | N29: =IFERROR(_xlfn.XLOOKUP("Current Assets",Inputs!$B:$B,Inputs!O:O)/+_xlfn.XLOOKUP("Current Liabilities",Inputs!$B:$B,Inputs!O:O),"") | O29: =IFERROR(_xlfn.XLOOKUP("Current Assets",Inputs!$B:$B,Inputs!P:P)/+_xlfn.XLOOKUP("Current Liabilities",Inputs!$B:$B,Inputs!P:P),"") | P29: =IFERROR(_xlfn.XLOOKUP("Current Assets",Inputs!$B:$B,Inputs!Q:Q)/+_xlfn.XLOOKUP("Current Liabilities",Inputs!$B:$B,Inputs!Q:Q),"") | Q29: =+IFERROR(_xlfn.XLOOKUP("Current Assets",DCF!$6:$6,DCF!10:10)/_xlfn.XLOOKUP("Current Liabilities",DCF!$6:$6,DCF!10:10),"") | R29: =+IFERROR(_xlfn.XLOOKUP("Current Assets",DCF!$6:$6,DCF!10:10)/_xlfn.XLOOKUP("Current Liabilities",DCF!$6:$6,DCF!10:10),"")
B31: Efficiency | F31: 2014 | G31: =+F31+1 -> 2015 | H31: =+G31+1 -> 2016 | I31: =+H31+1 -> 2017 | J31: =+I31+1 -> 2018 | K31: =+J31+1 -> 2019 | L31: =+K31+1 -> 2020 | M31: =+L31+1 -> 2021 | N31: 2022 | O31: =+N31+1 -> 2023 | P31: =+O31+1 -> 2024 | Q31: =+P31+1 -> 2025 | R31: =+Q31+1 -> 2026
B33: Days Sales Outstanding | F33: =+_xlfn.XLOOKUP("DSO",Inputs!$B:$B,Inputs!G:G) | G33: =+_xlfn.XLOOKUP("DSO",Inputs!$B:$B,Inputs!H:H) | H33: =+_xlfn.XLOOKUP("DSO",Inputs!$B:$B,Inputs!I:I) | I33: =+_xlfn.XLOOKUP("DSO",Inputs!$B:$B,Inputs!J:J) | J33: =+_xlfn.XLOOKUP("DSO",Inputs!$B:$B,Inputs!K:K) | K33: =+_xlfn.XLOOKUP("DSO",Inputs!$B:$B,Inputs!L:L) | L33: =+_xlfn.XLOOKUP("DSO",Inputs!$B:$B,Inputs!M:M) | M33: =+_xlfn.XLOOKUP("DSO",Inputs!$B:$B,Inputs!N:N) | N33: =+_xlfn.XLOOKUP("DSO",Inputs!$B:$B,Inputs!O:O) | O33: =+_xlfn.XLOOKUP("DSO",Inputs!$B:$B,Inputs!P:P) | P33: =+_xlfn.XLOOKUP("DSO",Inputs!$B:$B,Inputs!Q:Q) | Q33: =+_xlfn.XLOOKUP("DSO",DCF!$B:$B,DCF!H:H) | R33: =+_xlfn.XLOOKUP("DSO",DCF!$B:$B,DCF!I:I)
B34: Days Payable Outstanding | F34: =+_xlfn.XLOOKUP("DPO",Inputs!$B:$B,Inputs!G:G) | G34: =+_xlfn.XLOOKUP("DPO",Inputs!$B:$B,Inputs!H:H) | H34: =+_xlfn.XLOOKUP("DPO",Inputs!$B:$B,Inputs!I:I) | I34: =+_xlfn.XLOOKUP("DPO",Inputs!$B:$B,Inputs!J:J) | J34: =+_xlfn.XLOOKUP("DPO",Inputs!$B:$B,Inputs!K:K) | K34: =+_xlfn.XLOOKUP("DPO",Inputs!$B:$B,Inputs!L:L) | L34: =+_xlfn.XLOOKUP("DPO",Inputs!$B:$B,Inputs!M:M) | M34: =+_xlfn.XLOOKUP("DPO",Inputs!$B:$B,Inputs!N:N) | N34: =+_xlfn.XLOOKUP("DPO",Inputs!$B:$B,Inputs!O:O) | O34: =+_xlfn.XLOOKUP("DPO",Inputs!$B:$B,Inputs!P:P) | P34: =+_xlfn.XLOOKUP("DPO",Inputs!$B:$B,Inputs!Q:Q) | Q34: =+_xlfn.XLOOKUP("DPO",DCF!$B:$B,DCF!H:H) | R34: =+_xlfn.XLOOKUP("DPO",DCF!$B:$B,DCF!I:I)
B35: Days Inventory Outstanding | F35: =+_xlfn.XLOOKUP("DIH",Inputs!$B:$B,Inputs!G:G) | G35: =+_xlfn.XLOOKUP("DIH",Inputs!$B:$B,Inputs!H:H) | H35: =+_xlfn.XLOOKUP("DIH",Inputs!$B:$B,Inputs!I:I) | I35: =+_xlfn.XLOOKUP("DIH",Inputs!$B:$B,Inputs!J:J) | J35: =+_xlfn.XLOOKUP("DIH",Inputs!$B:$B,Inputs!K:K) | K35: =+_xlfn.XLOOKUP("DIH",Inputs!$B:$B,Inputs!L:L) | L35: =+_xlfn.XLOOKUP("DIH",Inputs!$B:$B,Inputs!M:M) | M35: =+_xlfn.XLOOKUP("DIH",Inputs!$B:$B,Inputs!N:N) | N35: =+_xlfn.XLOOKUP("DIH",Inputs!$B:$B,Inputs!O:O) | O35: =+_xlfn.XLOOKUP("DIH",Inputs!$B:$B,Inputs!P:P) | P35: =+_xlfn.XLOOKUP("DIH",Inputs!$B:$B,Inputs!Q:Q) | Q35: =+_xlfn.XLOOKUP("DIH",DCF!$B:$B,DCF!H:H) | R35: =+_xlfn.XLOOKUP("DIH",DCF!$B:$B,DCF!I:I)
B36: Cash Conversion Cycle | F36: =IFERROR(F35+F33-F34,"") | G36: =IFERROR(G35+G33-G34,"") | H36: =IFERROR(H35+H33-H34,"") | I36: =IFERROR(I35+I33-I34,"") | J36: =IFERROR(J35+J33-J34,"") | K36: =IFERROR(K35+K33-K34,"") | L36: =IFERROR(L35+L33-L34,"") | M36: =IFERROR(M35+M33-M34,"") | ... R36: =IFERROR(R35+R33-R34,"")
B38: Leverage | F38: 2014 | G38: =+F38+1 -> 2015 | H38: =+G38+1 -> 2016 | I38: =+H38+1 -> 2017 | J38: =+I38+1 -> 2018 | K38: =+J38+1 -> 2019 | L38: =+K38+1 -> 2020 | M38: =+L38+1 -> 2021 | N38: 2022 | O38: =+N38+1 -> 2023 | P38: =+O38+1 -> 2024 | Q38: =+P38+1 -> 2025 | R38: =+Q38+1 -> 2026
B40: Total Debt / Equity | F40: =+IFERROR(_xlfn.XLOOKUP("Total Debt",Inputs!$B:$B,Inputs!G:G)*1000/+_xlfn.XLOOKUP("Shareholder's Equity",Inputs!$B:$B,Inputs!G:G),"") | G40: =+IFERROR(_xlfn.XLOOKUP("Total Debt",Inputs!$B:$B,Inputs!H:H)*1000/+_xlfn.XLOOKUP("Shareholder's Equity",Inputs!$B:$B,Inputs!H:H),"") | H40: =+IFERROR(_xlfn.XLOOKUP("Total Debt",Inputs!$B:$B,Inputs!I:I)*1000/+_xlfn.XLOOKUP("Shareholder's Equity",Inputs!$B:$B,Inputs!I:I),"") | I40: =+IFERROR(_xlfn.XLOOKUP("Total Debt",Inputs!$B:$B,Inputs!J:J)*1000/+_xlfn.XLOOKUP("Shareholder's Equity",Inputs!$B:$B,Inputs!J:J),"") | J40: =+IFERROR(_xlfn.XLOOKUP("Total Debt",Inputs!$B:$B,Inputs!K:K)*1000/+_xlfn.XLOOKUP("Shareholder's Equity",Inputs!$B:$B,Inputs!K:K),"") | K40: =+IFERROR(_xlfn.XLOOKUP("Total Debt",Inputs!$B:$B,Inputs!L:L)*1000/+_xlfn.XLOOKUP("Shareholder's Equity",Inputs!$B:$B,Inputs!L:L),"") | L40: =+IFERROR(_xlfn.XLOOKUP("Total Debt",Inputs!$B:$B,Inputs!M:M)*1000/+_xlfn.XLOOKUP("Shareholder's Equity",Inputs!$B:$B,Inputs!M:M),"") | M40: =+IFERROR(_xlfn.XLOOKUP("Total Debt",Inputs!$B:$B,Inputs!N:N)*1000/+_xlfn.XLOOKUP("Shareholder's Equity",Inputs!$B:$B,Inputs!N:N),"") | N40: =+IFERROR(_xlfn.XLOOKUP("Total Debt",Inputs!$B:$B,Inputs!O:O)*1000/+_xlfn.XLOOKUP("Shareholder's Equity",Inputs!$B:$B,Inputs!O:O),"") | O40: =+IFERROR(_xlfn.XLOOKUP("Total Debt",Inputs!$B:$B,Inputs!P:P)*1000/+_xlfn.XLOOKUP("Shareholder's Equity",Inputs!$B:$B,Inputs!P:P),"") | P40: =+IFERROR(_xlfn.XLOOKUP("Total Debt",Inputs!$B:$B,Inputs!Q:Q)*1000/+_xlfn.XLOOKUP("Shareholder's Equity",Inputs!$B:$B,Inputs!Q:Q),"") | Q40: =IFERROR((_xlfn.XLOOKUP("Total Borrowings",DCF!$B:$B,DCF!G:G)+_xlfn.XLOOKUP("Total Leases",DCF!$B:$B,DCF!G:G))/_xlfn.XLOOKUP("Shareholder's Equity",DCF!$6:$6,DCF!10:10),"") | R40: =IFERROR((_xlfn.XLOOKUP("Total Borrowings",DCF!$B:$B,DCF!H:H)+_xlfn.XLOOKUP("Total Leases",DCF!$B:$B,DCF!H:H))/_xlfn.XLOOKUP("Shareholder's Equity",DCF!$6:$6,DCF!10:10),"")
B41: Total Debt / Capital | F41: =+IFERROR(_xlfn.XLOOKUP("Total Debt",Inputs!$B:$B,Inputs!G:G)*1000/(+_xlfn.XLOOKUP("Shareholder's Equity",Inputs!$B:$B,Inputs!G:G)+_xlfn.XLOOKUP("Total Debt",Inputs!$B:$B,Inputs!G:G)*1000),"") | G41: =+IFERROR(_xlfn.XLOOKUP("Total Debt",Inputs!$B:$B,Inputs!H:H)*1000/(+_xlfn.XLOOKUP("Shareholder's Equity",Inputs!$B:$B,Inputs!H:H)+_xlfn.XLOOKUP("Total Debt",Inputs!$B:$B,Inputs!H:H)*1000),"") | H41: =+IFERROR(_xlfn.XLOOKUP("Total Debt",Inputs!$B:$B,Inputs!I:I)*1000/(+_xlfn.XLOOKUP("Shareholder's Equity",Inputs!$B:$B,Inputs!I:I)+_xlfn.XLOOKUP("Total Debt",Inputs!$B:$B,Inputs!I:I)*1000),"") | I41: =+IFERROR(_xlfn.XLOOKUP("Total Debt",Inputs!$B:$B,Inputs!J:J)*1000/(+_xlfn.XLOOKUP("Shareholder's Equity",Inputs!$B:$B,Inputs!J:J)+_xlfn.XLOOKUP("Total Debt",Inputs!$B:$B,Inputs!J:J)*1000),"") | J41: =+IFERROR(_xlfn.XLOOKUP("Total Debt",Inputs!$B:$B,Inputs!K:K)*1000/(+_xlfn.XLOOKUP("Shareholder's Equity",Inputs!$B:$B,Inputs!K:K)+_xlfn.XLOOKUP("Total Debt",Inputs!$B:$B,Inputs!K:K)*1000),"") | K41: =+IFERROR(_xlfn.XLOOKUP("Total Debt",Inputs!$B:$B,Inputs!L:L)*1000/(+_xlfn.XLOOKUP("Shareholder's Equity",Inputs!$B:$B,Inputs!L:L)+_xlfn.XLOOKUP("Total Debt",Inputs!$B:$B,Inputs!L:L)*1000),"") | L41: =+IFERROR(_xlfn.XLOOKUP("Total Debt",Inputs!$B:$B,Inputs!M:M)*1000/(+_xlfn.XLOOKUP("Shareholder's Equity",Inputs!$B:$B,Inputs!M:M)+_xlfn.XLOOKUP("Total Debt",Inputs!$B:$B,Inputs!M:M)*1000),"") | M41: =+IFERROR(_xlfn.XLOOKUP("Total Debt",Inputs!$B:$B,Inputs!N:N)*1000/(+_xlfn.XLOOKUP("Shareholder's Equity",Inputs!$B:$B,Inputs!N:N)+_xlfn.XLOOKUP("Total Debt",Inputs!$B:$B,Inputs!N:N)*1000),"") | N41: =+IFERROR(_xlfn.XLOOKUP("Total Debt",Inputs!$B:$B,Inputs!O:O)*1000/(+_xlfn.XLOOKUP("Shareholder's Equity",Inputs!$B:$B,Inputs!O:O)+_xlfn.XLOOKUP("Total Debt",Inputs!$B:$B,Inputs!O:O)*1000),"") | O41: =+IFERROR(_xlfn.XLOOKUP("Total Debt",Inputs!$B:$B,Inputs!P:P)*1000/(+_xlfn.XLOOKUP("Shareholder's Equity",Inputs!$B:$B,Inputs!P:P)+_xlfn.XLOOKUP("Total Debt",Inputs!$B:$B,Inputs!P:P)*1000),"") | P41: =+IFERROR(_xlfn.XLOOKUP("Total Debt",Inputs!$B:$B,Inputs!Q:Q)*1000/(+_xlfn.XLOOKUP("Shareholder's Equity",Inputs!$B:$B,Inputs!Q:Q)+_xlfn.XLOOKUP("Total Debt",Inputs!$B:$B,Inputs!Q:Q)*1000),"") | Q41: =IFERROR((_xlfn.XLOOKUP("Total Borrowings",DCF!$B:$B,DCF!G:G)+_xlfn.XLOOKUP("Total Leases",DCF!$B:$B,DCF!G:G))/(_xlfn.XLOOKUP("Shareholder's Equity",DCF!$6:$6,DCF!10:10)+_xlfn.XLOOKUP("Total Borrowings",DCF!$B:$B,DCF!G:G)+_xlfn.XLOOKUP("Total Leases",DCF!$B:$B,DCF!G:G)),"") | R41: =IFERROR((_xlfn.XLOOKUP("Total Borrowings",DCF!$B:$B,DCF!H:H)+_xlfn.XLOOKUP("Total Leases",DCF!$B:$B,DCF!H:H))/(_xlfn.XLOOKUP("Shareholder's Equity",DCF!$6:$6,DCF!10:10)+_xlfn.XLOOKUP("Total Borrowings",DCF!$B:$B,DCF!H:H)+_xlfn.XLOOKUP("Total Leases",DCF!$B:$B,DCF!H:H)),"")
B42: Total Liabilities / Total Assets | F42: =IFERROR(_xlfn.XLOOKUP("Total Liabilities",Inputs!$B:$B,Inputs!G:G)/_xlfn.XLOOKUP("Total Assets",Inputs!$B:$B,Inputs!G:G),"") | G42: =IFERROR(_xlfn.XLOOKUP("Total Liabilities",Inputs!$B:$B,Inputs!H:H)/_xlfn.XLOOKUP("Total Assets",Inputs!$B:$B,Inputs!H:H),"") | H42: =IFERROR(_xlfn.XLOOKUP("Total Liabilities",Inputs!$B:$B,Inputs!I:I)/_xlfn.XLOOKUP("Total Assets",Inputs!$B:$B,Inputs!I:I),"") | I42: =IFERROR(_xlfn.XLOOKUP("Total Liabilities",Inputs!$B:$B,Inputs!J:J)/_xlfn.XLOOKUP("Total Assets",Inputs!$B:$B,Inputs!J:J),"") | J42: =IFERROR(_xlfn.XLOOKUP("Total Liabilities",Inputs!$B:$B,Inputs!K:K)/_xlfn.XLOOKUP("Total Assets",Inputs!$B:$B,Inputs!K:K),"") | K42: =IFERROR(_xlfn.XLOOKUP("Total Liabilities",Inputs!$B:$B,Inputs!L:L)/_xlfn.XLOOKUP("Total Assets",Inputs!$B:$B,Inputs!L:L),"") | L42: =IFERROR(_xlfn.XLOOKUP("Total Liabilities",Inputs!$B:$B,Inputs!M:M)/_xlfn.XLOOKUP("Total Assets",Inputs!$B:$B,Inputs!M:M),"") | M42: =IFERROR(_xlfn.XLOOKUP("Total Liabilities",Inputs!$B:$B,Inputs!N:N)/_xlfn.XLOOKUP("Total Assets",Inputs!$B:$B,Inputs!N:N),"") | N42: =IFERROR(_xlfn.XLOOKUP("Total Liabilities",Inputs!$B:$B,Inputs!O:O)/_xlfn.XLOOKUP("Total Assets",Inputs!$B:$B,Inputs!O:O),"") | O42: =IFERROR(_xlfn.XLOOKUP("Total Liabilities",Inputs!$B:$B,Inputs!P:P)/_xlfn.XLOOKUP("Total Assets",Inputs!$B:$B,Inputs!P:P),"") | P42: =IFERROR(_xlfn.XLOOKUP("Total Liabilities",Inputs!$B:$B,Inputs!Q:Q)/_xlfn.XLOOKUP("Total Assets",Inputs!$B:$B,Inputs!Q:Q),"") | Q42: =IFERROR(+_xlfn.XLOOKUP("Total Liabilities",DCF!$6:$6,DCF!10:10)/_xlfn.XLOOKUP("Total Assets",DCF!$6:$6,DCF!10:10),"") | R42: =IFERROR(+_xlfn.XLOOKUP("Total Liabilities",DCF!$6:$6,DCF!10:10)/_xlfn.XLOOKUP("Total Assets",DCF!$6:$6,DCF!10:10),"")
B43: Total Debt / EBITDA | F43: =+IFERROR(_xlfn.XLOOKUP("Total Debt",Inputs!$B:$B,Inputs!G:G,,,-1)/_xlfn.XLOOKUP("EBITDA",Inputs!$B:$B,Inputs!G:G),"") | G43: =+IFERROR(_xlfn.XLOOKUP("Total Debt",Inputs!$B:$B,Inputs!H:H,,,-1)/_xlfn.XLOOKUP("EBITDA",Inputs!$B:$B,Inputs!H:H),"") | H43: =+IFERROR(_xlfn.XLOOKUP("Total Debt",Inputs!$B:$B,Inputs!I:I,,,-1)/_xlfn.XLOOKUP("EBITDA",Inputs!$B:$B,Inputs!I:I),"") | I43: =+IFERROR(_xlfn.XLOOKUP("Total Debt",Inputs!$B:$B,Inputs!J:J,,,-1)/_xlfn.XLOOKUP("EBITDA",Inputs!$B:$B,Inputs!J:J),"") | J43: =+IFERROR(_xlfn.XLOOKUP("Total Debt",Inputs!$B:$B,Inputs!K:K,,,-1)/_xlfn.XLOOKUP("EBITDA",Inputs!$B:$B,Inputs!K:K),"") | K43: =+IFERROR(_xlfn.XLOOKUP("Total Debt",Inputs!$B:$B,Inputs!L:L,,,-1)/_xlfn.XLOOKUP("EBITDA",Inputs!$B:$B,Inputs!L:L),"") | L43: =+IFERROR(_xlfn.XLOOKUP("Total Debt",Inputs!$B:$B,Inputs!M:M,,,-1)/_xlfn.XLOOKUP("EBITDA",Inputs!$B:$B,Inputs!M:M),"") | M43: =+IFERROR(_xlfn.XLOOKUP("Total Debt",Inputs!$B:$B,Inputs!N:N,,,-1)/_xlfn.XLOOKUP("EBITDA",Inputs!$B:$B,Inputs!N:N),"") | N43: =+IFERROR(_xlfn.XLOOKUP("Total Debt",Inputs!$B:$B,Inputs!O:O,,,-1)/_xlfn.XLOOKUP("EBITDA",Inputs!$B:$B,Inputs!O:O),"") | O43: =+IFERROR(_xlfn.XLOOKUP("Total Debt",Inputs!$B:$B,Inputs!P:P,,,-1)/_xlfn.XLOOKUP("EBITDA",Inputs!$B:$B,Inputs!P:P),"") | P43: =+IFERROR(_xlfn.XLOOKUP("Total Debt",Inputs!$B:$B,Inputs!Q:Q,,,-1)/_xlfn.XLOOKUP("EBITDA",Inputs!$B:$B,Inputs!Q:Q),"") | Q43: =IFERROR((_xlfn.XLOOKUP("Total Borrowings",DCF!$B:$B,DCF!G:G)+_xlfn.XLOOKUP("Total Leases",DCF!$B:$B,DCF!G:G))/_xlfn.XLOOKUP("EBITDA",DCF!$B:$B,DCF!H:H),"") | R43: =IFERROR((_xlfn.XLOOKUP("Total Borrowings",DCF!$B:$B,DCF!H:H)+_xlfn.XLOOKUP("Total Leases",DCF!$B:$B,DCF!H:H))/_xlfn.XLOOKUP("EBITDA",DCF!$B:$B,DCF!I:I),"")
B44: Total Debt / (EBITDA - Capex) | F44: =IFERROR(_xlfn.XLOOKUP("Total Debt",Inputs!$B:$B,Inputs!G:G,,,-1)/(_xlfn.XLOOKUP("EBITDA",Inputs!$B:$B,Inputs!G:G)+_xlfn.XLOOKUP("Net Capex",Inputs!$B:$B,Inputs!G:G)),"") | G44: =IFERROR(_xlfn.XLOOKUP("Total Debt",Inputs!$B:$B,Inputs!H:H,,,-1)/(_xlfn.XLOOKUP("EBITDA",Inputs!$B:$B,Inputs!H:H)+_xlfn.XLOOKUP("Net Capex",Inputs!$B:$B,Inputs!H:H)),"") | H44: =IFERROR(_xlfn.XLOOKUP("Total Debt",Inputs!$B:$B,Inputs!I:I,,,-1)/(_xlfn.XLOOKUP("EBITDA",Inputs!$B:$B,Inputs!I:I)+_xlfn.XLOOKUP("Net Capex",Inputs!$B:$B,Inputs!I:I)),"") | I44: =IFERROR(_xlfn.XLOOKUP("Total Debt",Inputs!$B:$B,Inputs!J:J,,,-1)/(_xlfn.XLOOKUP("EBITDA",Inputs!$B:$B,Inputs!J:J)+_xlfn.XLOOKUP("Net Capex",Inputs!$B:$B,Inputs!J:J)),"") | J44: =IFERROR(_xlfn.XLOOKUP("Total Debt",Inputs!$B:$B,Inputs!K:K,,,-1)/(_xlfn.XLOOKUP("EBITDA",Inputs!$B:$B,Inputs!K:K)+_xlfn.XLOOKUP("Net Capex",Inputs!$B:$B,Inputs!K:K)),"") | K44: =IFERROR(_xlfn.XLOOKUP("Total Debt",Inputs!$B:$B,Inputs!L:L,,,-1)/(_xlfn.XLOOKUP("EBITDA",Inputs!$B:$B,Inputs!L:L)+_xlfn.XLOOKUP("Net Capex",Inputs!$B:$B,Inputs!L:L)),"") | L44: =IFERROR(_xlfn.XLOOKUP("Total Debt",Inputs!$B:$B,Inputs!M:M,,,-1)/(_xlfn.XLOOKUP("EBITDA",Inputs!$B:$B,Inputs!M:M)+_xlfn.XLOOKUP("Net Capex",Inputs!$B:$B,Inputs!M:M)),"") | M44: =IFERROR(_xlfn.XLOOKUP("Total Debt",Inputs!$B:$B,Inputs!N:N,,,-1)/(_xlfn.XLOOKUP("EBITDA",Inputs!$B:$B,Inputs!N:N)+_xlfn.XLOOKUP("Net Capex",Inputs!$B:$B,Inputs!N:N)),"") | N44: =IFERROR(_xlfn.XLOOKUP("Total Debt",Inputs!$B:$B,Inputs!O:O,,,-1)/(_xlfn.XLOOKUP("EBITDA",Inputs!$B:$B,Inputs!O:O)+_xlfn.XLOOKUP("Net Capex",Inputs!$B:$B,Inputs!O:O)),"") | O44: =IFERROR(_xlfn.XLOOKUP("Total Debt",Inputs!$B:$B,Inputs!P:P,,,-1)/(_xlfn.XLOOKUP("EBITDA",Inputs!$B:$B,Inputs!P:P)+_xlfn.XLOOKUP("Net Capex",Inputs!$B:$B,Inputs!P:P)),"") | P44: =IFERROR(_xlfn.XLOOKUP("Total Debt",Inputs!$B:$B,Inputs!Q:Q,,,-1)/(_xlfn.XLOOKUP("EBITDA",Inputs!$B:$B,Inputs!Q:Q)+_xlfn.XLOOKUP("Net Capex",Inputs!$B:$B,Inputs!Q:Q)),"") | Q44: =IFERROR((_xlfn.XLOOKUP("Total Borrowings",DCF!$B:$B,DCF!G:G)+_xlfn.XLOOKUP("Total Leases",DCF!$B:$B,DCF!G:G))/(_xlfn.XLOOKUP("EBITDA",DCF!$B:$B,DCF!H:H)+_xlfn.XLOOKUP("Net Capex",DCF!$B:$B,DCF!H:H)),"") | R44: =IFERROR((_xlfn.XLOOKUP("Total Borrowings",DCF!$B:$B,DCF!H:H)+_xlfn.XLOOKUP("Total Leases",DCF!$B:$B,DCF!H:H))/(_xlfn.XLOOKUP("EBITDA",DCF!$B:$B,DCF!I:I)+_xlfn.XLOOKUP("Net Capex",DCF!$B:$B,DCF!I:I)),"")
B45: Net Debt / EBITDA | F45: =+IFERROR(_xlfn.XLOOKUP("Net Debt",Inputs!$B:$B,Inputs!G:G,,,-1)/_xlfn.XLOOKUP("EBITDA",Inputs!$B:$B,Inputs!G:G),"") | G45: =+IFERROR(_xlfn.XLOOKUP("Net Debt",Inputs!$B:$B,Inputs!H:H,,,-1)/_xlfn.XLOOKUP("EBITDA",Inputs!$B:$B,Inputs!H:H),"") | H45: =+IFERROR(_xlfn.XLOOKUP("Net Debt",Inputs!$B:$B,Inputs!I:I,,,-1)/_xlfn.XLOOKUP("EBITDA",Inputs!$B:$B,Inputs!I:I),"") | I45: =+IFERROR(_xlfn.XLOOKUP("Net Debt",Inputs!$B:$B,Inputs!J:J,,,-1)/_xlfn.XLOOKUP("EBITDA",Inputs!$B:$B,Inputs!J:J),"") | J45: =+IFERROR(_xlfn.XLOOKUP("Net Debt",Inputs!$B:$B,Inputs!K:K,,,-1)/_xlfn.XLOOKUP("EBITDA",Inputs!$B:$B,Inputs!K:K),"") | K45: =+IFERROR(_xlfn.XLOOKUP("Net Debt",Inputs!$B:$B,Inputs!L:L,,,-1)/_xlfn.XLOOKUP("EBITDA",Inputs!$B:$B,Inputs!L:L),"") | L45: =+IFERROR(_xlfn.XLOOKUP("Net Debt",Inputs!$B:$B,Inputs!M:M,,,-1)/_xlfn.XLOOKUP("EBITDA",Inputs!$B:$B,Inputs!M:M),"") | M45: =+IFERROR(_xlfn.XLOOKUP("Net Debt",Inputs!$B:$B,Inputs!N:N,,,-1)/_xlfn.XLOOKUP("EBITDA",Inputs!$B:$B,Inputs!N:N),"") | N45: =+IFERROR(_xlfn.XLOOKUP("Net Debt",Inputs!$B:$B,Inputs!O:O,,,-1)/_xlfn.XLOOKUP("EBITDA",Inputs!$B:$B,Inputs!O:O),"") | O45: =+IFERROR(_xlfn.XLOOKUP("Net Debt",Inputs!$B:$B,Inputs!P:P,,,-1)/_xlfn.XLOOKUP("EBITDA",Inputs!$B:$B,Inputs!P:P),"") | P45: =+IFERROR(_xlfn.XLOOKUP("Net Debt",Inputs!$B:$B,Inputs!Q:Q,,,-1)/_xlfn.XLOOKUP("EBITDA",Inputs!$B:$B,Inputs!Q:Q),"") | Q45: =IFERROR((_xlfn.XLOOKUP("Total Borrowings",DCF!$B:$B,DCF!G:G)+_xlfn.XLOOKUP("Total Leases",DCF!$B:$B,DCF!G:G)-_xlfn.XLOOKUP("Cash & Cash Equivalents & ST Investments",DCF!$B:$B,DCF!G:G))/_xlfn.XLOOKUP("EBITDA",DCF!$B:$B,DCF!H:H),"") | R45: =IFERROR((_xlfn.XLOOKUP("Total Borrowings",DCF!$B:$B,DCF!H:H)+_xlfn.XLOOKUP("Total Leases",DCF!$B:$B,DCF!H:H)-_xlfn.XLOOKUP("Cash & Cash Equivalents & ST Investments",DCF!$B:$B,DCF!H:H))/_xlfn.XLOOKUP("EBITDA",DCF!$B:$B,DCF!I:I),"")
B47: Interest Coverage | F47: 2014 | G47: =+F47+1 -> 2015 | H47: =+G47+1 -> 2016 | I47: =+H47+1 -> 2017 | J47: =+I47+1 -> 2018 | K47: =+J47+1 -> 2019 | L47: =+K47+1 -> 2020 | M47: =+L47+1 -> 2021 | N47: 2022 | O47: =+N47+1 -> 2023 | P47: =+O47+1 -> 2024 | Q47: =+P47+1 -> 2025 | R47: =+Q47+1 -> 2026
B49: EBIT / Interest Expense | F49: =IFERROR(_xlfn.XLOOKUP("Operating Income (EBIT)",Inputs!$B:$B,Inputs!G:G)/_xlfn.XLOOKUP("Interest Expense",Inputs!$B:$B,Inputs!G:G),"N/A") -> N/A | G49: =IFERROR(_xlfn.XLOOKUP("Operating Income (EBIT)",Inputs!$B:$B,Inputs!H:H)/_xlfn.XLOOKUP("Interest Expense",Inputs!$B:$B,Inputs!H:H),"N/A") -> N/A | H49: =IFERROR(_xlfn.XLOOKUP("Operating Income (EBIT)",Inputs!$B:$B,Inputs!I:I)/_xlfn.XLOOKUP("Interest Expense",Inputs!$B:$B,Inputs!I:I),"N/A") -> N/A | I49: =IFERROR(_xlfn.XLOOKUP("Operating Income (EBIT)",Inputs!$B:$B,Inputs!J:J)/_xlfn.XLOOKUP("Interest Expense",Inputs!$B:$B,Inputs!J:J),"N/A") -> N/A | J49: =IFERROR(_xlfn.XLOOKUP("Operating Income (EBIT)",Inputs!$B:$B,Inputs!K:K)/_xlfn.XLOOKUP("Interest Expense",Inputs!$B:$B,Inputs!K:K),"N/A") -> N/A | K49: =IFERROR(_xlfn.XLOOKUP("Operating Income (EBIT)",Inputs!$B:$B,Inputs!L:L)/_xlfn.XLOOKUP("Interest Expense",Inputs!$B:$B,Inputs!L:L),"N/A") -> N/A | L49: =IFERROR(_xlfn.XLOOKUP("Operating Income (EBIT)",Inputs!$B:$B,Inputs!M:M)/_xlfn.XLOOKUP("Interest Expense",Inputs!$B:$B,Inputs!M:M),"N/A") -> N/A | M49: =IFERROR(_xlfn.XLOOKUP("Operating Income (EBIT)",Inputs!$B:$B,Inputs!N:N)/_xlfn.XLOOKUP("Interest Expense",Inputs!$B:$B,Inputs!N:N),"N/A") -> N/A | N49: =IFERROR(_xlfn.XLOOKUP("Operating Income (EBIT)",Inputs!$B:$B,Inputs!O:O)/_xlfn.XLOOKUP("Interest Expense",Inputs!$B:$B,Inputs!O:O),"N/A") -> N/A | O49: =IFERROR(_xlfn.XLOOKUP("Operating Income (EBIT)",Inputs!$B:$B,Inputs!P:P)/_xlfn.XLOOKUP("Interest Expense",Inputs!$B:$B,Inputs!P:P),"N/A") -> N/A | P49: =IFERROR(_xlfn.XLOOKUP("Operating Income (EBIT)",Inputs!$B:$B,Inputs!Q:Q)/_xlfn.XLOOKUP("Interest Expense",Inputs!$B:$B,Inputs!Q:Q),"N/A") -> N/A | Q49: =IFERROR(_xlfn.XLOOKUP("EBIT",DCF!$B:$B,DCF!H:H)/_xlfn.XLOOKUP("Interest Expense",DCF!$B:$B,DCF!H:H),"N/A") -> N/A | R49: =IFERROR(_xlfn.XLOOKUP("EBIT",DCF!$B:$B,DCF!I:I)/_xlfn.XLOOKUP("Interest Expense",DCF!$B:$B,DCF!I:I),"N/A") -> N/A
B50: EBITDA / Interest Expense | F50: =IFERROR(_xlfn.XLOOKUP("EBITDA",Inputs!$B:$B,Inputs!G:G)/_xlfn.XLOOKUP("Interest Expense",Inputs!$B:$B,Inputs!G:G),"N/A") -> N/A | G50: =IFERROR(_xlfn.XLOOKUP("EBITDA",Inputs!$B:$B,Inputs!H:H)/_xlfn.XLOOKUP("Interest Expense",Inputs!$B:$B,Inputs!H:H),"N/A") -> N/A | H50: =IFERROR(_xlfn.XLOOKUP("EBITDA",Inputs!$B:$B,Inputs!I:I)/_xlfn.XLOOKUP("Interest Expense",Inputs!$B:$B,Inputs!I:I),"N/A") -> N/A | I50: =IFERROR(_xlfn.XLOOKUP("EBITDA",Inputs!$B:$B,Inputs!J:J)/_xlfn.XLOOKUP("Interest Expense",Inputs!$B:$B,Inputs!J:J),"N/A") -> N/A | J50: =IFERROR(_xlfn.XLOOKUP("EBITDA",Inputs!$B:$B,Inputs!K:K)/_xlfn.XLOOKUP("Interest Expense",Inputs!$B:$B,Inputs!K:K),"N/A") -> N/A | K50: =IFERROR(_xlfn.XLOOKUP("EBITDA",Inputs!$B:$B,Inputs!L:L)/_xlfn.XLOOKUP("Interest Expense",Inputs!$B:$B,Inputs!L:L),"N/A") -> N/A | L50: =IFERROR(_xlfn.XLOOKUP("EBITDA",Inputs!$B:$B,Inputs!M:M)/_xlfn.XLOOKUP("Interest Expense",Inputs!$B:$B,Inputs!M:M),"N/A") -> N/A | M50: =IFERROR(_xlfn.XLOOKUP("EBITDA",Inputs!$B:$B,Inputs!N:N)/_xlfn.XLOOKUP("Interest Expense",Inputs!$B:$B,Inputs!N:N),"N/A") -> N/A | N50: =IFERROR(_xlfn.XLOOKUP("EBITDA",Inputs!$B:$B,Inputs!O:O)/_xlfn.XLOOKUP("Interest Expense",Inputs!$B:$B,Inputs!O:O),"N/A") -> N/A | O50: =IFERROR(_xlfn.XLOOKUP("EBITDA",Inputs!$B:$B,Inputs!P:P)/_xlfn.XLOOKUP("Interest Expense",Inputs!$B:$B,Inputs!P:P),"N/A") -> N/A | P50: =IFERROR(_xlfn.XLOOKUP("EBITDA",Inputs!$B:$B,Inputs!Q:Q)/_xlfn.XLOOKUP("Interest Expense",Inputs!$B:$B,Inputs!Q:Q),"N/A") -> N/A | Q50: =IFERROR(_xlfn.XLOOKUP("EBITDA",DCF!$B:$B,DCF!H:H)/_xlfn.XLOOKUP("Interest Expense",DCF!$B:$B,DCF!H:H),"N/A") -> N/A | R50: =IFERROR(_xlfn.XLOOKUP("EBITDA",DCF!$B:$B,DCF!I:I)/_xlfn.XLOOKUP("Interest Expense",DCF!$B:$B,DCF!I:I),"N/A") -> N/A
B51: (EBITDA - Capex) / Interest Expense | F51: =IFERROR((_xlfn.XLOOKUP("EBITDA",Inputs!$B:$B,Inputs!G:G)-_xlfn.XLOOKUP("Net Capex",Inputs!$B:$B,Inputs!G:G))/_xlfn.XLOOKUP("Interest Expense",Inputs!$B:$B,Inputs!G:G),"N/A") -> N/A | G51: =IFERROR((_xlfn.XLOOKUP("EBITDA",Inputs!$B:$B,Inputs!H:H)-_xlfn.XLOOKUP("Net Capex",Inputs!$B:$B,Inputs!H:H))/_xlfn.XLOOKUP("Interest Expense",Inputs!$B:$B,Inputs!H:H),"N/A") -> N/A | H51: =IFERROR((_xlfn.XLOOKUP("EBITDA",Inputs!$B:$B,Inputs!I:I)-_xlfn.XLOOKUP("Net Capex",Inputs!$B:$B,Inputs!I:I))/_xlfn.XLOOKUP("Interest Expense",Inputs!$B:$B,Inputs!I:I),"N/A") -> N/A | I51: =IFERROR((_xlfn.XLOOKUP("EBITDA",Inputs!$B:$B,Inputs!J:J)-_xlfn.XLOOKUP("Net Capex",Inputs!$B:$B,Inputs!J:J))/_xlfn.XLOOKUP("Interest Expense",Inputs!$B:$B,Inputs!J:J),"N/A") -> N/A | J51: =IFERROR((_xlfn.XLOOKUP("EBITDA",Inputs!$B:$B,Inputs!K:K)-_xlfn.XLOOKUP("Net Capex",Inputs!$B:$B,Inputs!K:K))/_xlfn.XLOOKUP("Interest Expense",Inputs!$B:$B,Inputs!K:K),"N/A") -> N/A | K51: =IFERROR((_xlfn.XLOOKUP("EBITDA",Inputs!$B:$B,Inputs!L:L)-_xlfn.XLOOKUP("Net Capex",Inputs!$B:$B,Inputs!L:L))/_xlfn.XLOOKUP("Interest Expense",Inputs!$B:$B,Inputs!L:L),"N/A") -> N/A | L51: =IFERROR((_xlfn.XLOOKUP("EBITDA",Inputs!$B:$B,Inputs!M:M)-_xlfn.XLOOKUP("Net Capex",Inputs!$B:$B,Inputs!M:M))/_xlfn.XLOOKUP("Interest Expense",Inputs!$B:$B,Inputs!M:M),"N/A") -> N/A | M51: =IFERROR((_xlfn.XLOOKUP("EBITDA",Inputs!$B:$B,Inputs!N:N)-_xlfn.XLOOKUP("Net Capex",Inputs!$B:$B,Inputs!N:N))/_xlfn.XLOOKUP("Interest Expense",Inputs!$B:$B,Inputs!N:N),"N/A") -> N/A | N51: =IFERROR((_xlfn.XLOOKUP("EBITDA",Inputs!$B:$B,Inputs!O:O)-_xlfn.XLOOKUP("Net Capex",Inputs!$B:$B,Inputs!O:O))/_xlfn.XLOOKUP("Interest Expense",Inputs!$B:$B,Inputs!O:O),"N/A") -> N/A | O51: =IFERROR((_xlfn.XLOOKUP("EBITDA",Inputs!$B:$B,Inputs!P:P)-_xlfn.XLOOKUP("Net Capex",Inputs!$B:$B,Inputs!P:P))/_xlfn.XLOOKUP("Interest Expense",Inputs!$B:$B,Inputs!P:P),"N/A") -> N/A | P51: =IFERROR((_xlfn.XLOOKUP("EBITDA",Inputs!$B:$B,Inputs!Q:Q)-_xlfn.XLOOKUP("Net Capex",Inputs!$B:$B,Inputs!Q:Q))/_xlfn.XLOOKUP("Interest Expense",Inputs!$B:$B,Inputs!Q:Q),"N/A") -> N/A | Q51: =IFERROR((_xlfn.XLOOKUP("EBITDA",DCF!$B:$B,DCF!H:H)-_xlfn.XLOOKUP("Net Capex",DCF!$B:$B,DCF!H:H))/_xlfn.XLOOKUP("Interest Expense",DCF!$B:$B,DCF!H:H),"N/A") -> N/A | R51: =IFERROR((_xlfn.XLOOKUP("EBITDA",DCF!$B:$B,DCF!I:I)-_xlfn.XLOOKUP("Net Capex",DCF!$B:$B,DCF!I:I))/_xlfn.XLOOKUP("Interest Expense",DCF!$B:$B,DCF!I:I),"N/A") -> N/A
B53: Cash Flow Ratios | F53: 2014 | G53: =+F53+1 -> 2015 | H53: =+G53+1 -> 2016 | I53: =+H53+1 -> 2017 | J53: =+I53+1 -> 2018 | K53: =+J53+1 -> 2019 | L53: =+K53+1 -> 2020 | M53: =+L53+1 -> 2021 | N53: 2022 | O53: =+N53+1 -> 2023 | P53: =+O53+1 -> 2024 | Q53: =+P53+1 -> 2025 | R53: =+Q53+1 -> 2026
B55: Cash Flow Margin | F55: =+IFERROR(_xlfn.XLOOKUP("Operating Cash Flow",Inputs!$B:$B,Inputs!G:G,,,-1)/_xlfn.XLOOKUP("Revenue (Sales)",Inputs!$B:$B,Inputs!G:G),"") | G55: =+IFERROR(_xlfn.XLOOKUP("Operating Cash Flow",Inputs!$B:$B,Inputs!H:H,,,-1)/_xlfn.XLOOKUP("Revenue (Sales)",Inputs!$B:$B,Inputs!H:H),"") | H55: =+IFERROR(_xlfn.XLOOKUP("Operating Cash Flow",Inputs!$B:$B,Inputs!I:I,,,-1)/_xlfn.XLOOKUP("Revenue (Sales)",Inputs!$B:$B,Inputs!I:I),"") | I55: =+IFERROR(_xlfn.XLOOKUP("Operating Cash Flow",Inputs!$B:$B,Inputs!J:J,,,-1)/_xlfn.XLOOKUP("Revenue (Sales)",Inputs!$B:$B,Inputs!J:J),"") | J55: =+IFERROR(_xlfn.XLOOKUP("Operating Cash Flow",Inputs!$B:$B,Inputs!K:K,,,-1)/_xlfn.XLOOKUP("Revenue (Sales)",Inputs!$B:$B,Inputs!K:K),"") | K55: =+IFERROR(_xlfn.XLOOKUP("Operating Cash Flow",Inputs!$B:$B,Inputs!L:L,,,-1)/_xlfn.XLOOKUP("Revenue (Sales)",Inputs!$B:$B,Inputs!L:L),"") | L55: =+IFERROR(_xlfn.XLOOKUP("Operating Cash Flow",Inputs!$B:$B,Inputs!M:M,,,-1)/_xlfn.XLOOKUP("Revenue (Sales)",Inputs!$B:$B,Inputs!M:M),"") | M55: =+IFERROR(_xlfn.XLOOKUP("Operating Cash Flow",Inputs!$B:$B,Inputs!N:N,,,-1)/_xlfn.XLOOKUP("Revenue (Sales)",Inputs!$B:$B,Inputs!N:N),"") | N55: =+IFERROR(_xlfn.XLOOKUP("Operating Cash Flow",Inputs!$B:$B,Inputs!O:O,,,-1)/_xlfn.XLOOKUP("Revenue (Sales)",Inputs!$B:$B,Inputs!O:O),"") | O55: =+IFERROR(_xlfn.XLOOKUP("Operating Cash Flow",Inputs!$B:$B,Inputs!P:P,,,-1)/_xlfn.XLOOKUP("Revenue (Sales)",Inputs!$B:$B,Inputs!P:P),"") | P55: =+IFERROR(_xlfn.XLOOKUP("Operating Cash Flow",Inputs!$B:$B,Inputs!Q:Q,,,-1)/_xlfn.XLOOKUP("Revenue (Sales)",Inputs!$B:$B,Inputs!Q:Q),"") | Q55: =IFERROR(_xlfn.XLOOKUP("Operating Cash Flow",DCF!$B:$B,DCF!H:H)/_xlfn.XLOOKUP("Revenue (Sales)",DCF!$B:$B,DCF!H:H),"") | R55: =IFERROR(_xlfn.XLOOKUP("Operating Cash Flow",DCF!$B:$B,DCF!I:I)/_xlfn.XLOOKUP("Revenue (Sales)",DCF!$B:$B,DCF!I:I),"")
B56: Cash Flow to Net Income | F56: =IFERROR(_xlfn.XLOOKUP("Net Changes in Cash",Inputs!$B:$B,Inputs!G:G,,,-1)/_xlfn.XLOOKUP("Net Income",Inputs!$B:$B,Inputs!G:G),"") | G56: =IFERROR(_xlfn.XLOOKUP("Net Changes in Cash",Inputs!$B:$B,Inputs!H:H,,,-1)/_xlfn.XLOOKUP("Net Income",Inputs!$B:$B,Inputs!H:H),"") | H56: =IFERROR(_xlfn.XLOOKUP("Net Changes in Cash",Inputs!$B:$B,Inputs!I:I,,,-1)/_xlfn.XLOOKUP("Net Income",Inputs!$B:$B,Inputs!I:I),"") | I56: =IFERROR(_xlfn.XLOOKUP("Net Changes in Cash",Inputs!$B:$B,Inputs!J:J,,,-1)/_xlfn.XLOOKUP("Net Income",Inputs!$B:$B,Inputs!J:J),"") | J56: =IFERROR(_xlfn.XLOOKUP("Net Changes in Cash",Inputs!$B:$B,Inputs!K:K,,,-1)/_xlfn.XLOOKUP("Net Income",Inputs!$B:$B,Inputs!K:K),"") | K56: =IFERROR(_xlfn.XLOOKUP("Net Changes in Cash",Inputs!$B:$B,Inputs!L:L,,,-1)/_xlfn.XLOOKUP("Net Income",Inputs!$B:$B,Inputs!L:L),"") | L56: =IFERROR(_xlfn.XLOOKUP("Net Changes in Cash",Inputs!$B:$B,Inputs!M:M,,,-1)/_xlfn.XLOOKUP("Net Income",Inputs!$B:$B,Inputs!M:M),"") | M56: =IFERROR(_xlfn.XLOOKUP("Net Changes in Cash",Inputs!$B:$B,Inputs!N:N,,,-1)/_xlfn.XLOOKUP("Net Income",Inputs!$B:$B,Inputs!N:N),"") | N56: =IFERROR(_xlfn.XLOOKUP("Net Changes in Cash",Inputs!$B:$B,Inputs!O:O,,,-1)/_xlfn.XLOOKUP("Net Income",Inputs!$B:$B,Inputs!O:O),"") | O56: =IFERROR(_xlfn.XLOOKUP("Net Changes in Cash",Inputs!$B:$B,Inputs!P:P,,,-1)/_xlfn.XLOOKUP("Net Income",Inputs!$B:$B,Inputs!P:P),"") | P56: =IFERROR(_xlfn.XLOOKUP("Net Changes in Cash",Inputs!$B:$B,Inputs!Q:Q,,,-1)/_xlfn.XLOOKUP("Net Income",Inputs!$B:$B,Inputs!Q:Q),"") | Q56: =IFERROR(_xlfn.XLOOKUP("Net Changes in Cash",DCF!$B:$B,DCF!H:H)/_xlfn.XLOOKUP("Net Income",DCF!$B:$B,DCF!H:H),"") | R56: =IFERROR(_xlfn.XLOOKUP("Net Changes in Cash",DCF!$B:$B,DCF!I:I)/_xlfn.XLOOKUP("Net Income",DCF!$B:$B,DCF!I:I),"")
B57: CFO to Net Income | F57: =IFERROR(_xlfn.XLOOKUP("Operating Cash Flow",Inputs!$B:$B,Inputs!G:G,,,-1)/_xlfn.XLOOKUP("Net Income",Inputs!$B:$B,Inputs!G:G),"") | G57: =IFERROR(_xlfn.XLOOKUP("Operating Cash Flow",Inputs!$B:$B,Inputs!H:H,,,-1)/_xlfn.XLOOKUP("Net Income",Inputs!$B:$B,Inputs!H:H),"") | H57: =IFERROR(_xlfn.XLOOKUP("Operating Cash Flow",Inputs!$B:$B,Inputs!I:I,,,-1)/_xlfn.XLOOKUP("Net Income",Inputs!$B:$B,Inputs!I:I),"") | I57: =IFERROR(_xlfn.XLOOKUP("Operating Cash Flow",Inputs!$B:$B,Inputs!J:J,,,-1)/_xlfn.XLOOKUP("Net Income",Inputs!$B:$B,Inputs!J:J),"") | J57: =IFERROR(_xlfn.XLOOKUP("Operating Cash Flow",Inputs!$B:$B,Inputs!K:K,,,-1)/_xlfn.XLOOKUP("Net Income",Inputs!$B:$B,Inputs!K:K),"") | K57: =IFERROR(_xlfn.XLOOKUP("Operating Cash Flow",Inputs!$B:$B,Inputs!L:L,,,-1)/_xlfn.XLOOKUP("Net Income",Inputs!$B:$B,Inputs!L:L),"") | L57: =IFERROR(_xlfn.XLOOKUP("Operating Cash Flow",Inputs!$B:$B,Inputs!M:M,,,-1)/_xlfn.XLOOKUP("Net Income",Inputs!$B:$B,Inputs!M:M),"") | M57: =IFERROR(_xlfn.XLOOKUP("Operating Cash Flow",Inputs!$B:$B,Inputs!N:N,,,-1)/_xlfn.XLOOKUP("Net Income",Inputs!$B:$B,Inputs!N:N),"") | N57: =IFERROR(_xlfn.XLOOKUP("Operating Cash Flow",Inputs!$B:$B,Inputs!O:O,,,-1)/_xlfn.XLOOKUP("Net Income",Inputs!$B:$B,Inputs!O:O),"") | O57: =IFERROR(_xlfn.XLOOKUP("Operating Cash Flow",Inputs!$B:$B,Inputs!P:P,,,-1)/_xlfn.XLOOKUP("Net Income",Inputs!$B:$B,Inputs!P:P),"") | P57: =IFERROR(_xlfn.XLOOKUP("Operating Cash Flow",Inputs!$B:$B,Inputs!Q:Q,,,-1)/_xlfn.XLOOKUP("Net Income",Inputs!$B:$B,Inputs!Q:Q),"") | Q57: =IFERROR(_xlfn.XLOOKUP("Operating Cash Flow",DCF!$B:$B,DCF!H:H)/_xlfn.XLOOKUP("Net Income",DCF!$B:$B,DCF!H:H),"") | R57: =IFERROR(_xlfn.XLOOKUP("Operating Cash Flow",DCF!$B:$B,DCF!I:I)/_xlfn.XLOOKUP("Net Income",DCF!$B:$B,DCF!I:I),"")
B58: Net Capex to CFO | F58: =IFERROR(_xlfn.XLOOKUP("Net Capex",Inputs!$B:$B,Inputs!G:G,,,-1)/_xlfn.XLOOKUP("Operating Cash Flow",Inputs!$B:$B,Inputs!G:G),"") | G58: =IFERROR(_xlfn.XLOOKUP("Net Capex",Inputs!$B:$B,Inputs!H:H,,,-1)/_xlfn.XLOOKUP("Operating Cash Flow",Inputs!$B:$B,Inputs!H:H),"") | H58: =IFERROR(_xlfn.XLOOKUP("Net Capex",Inputs!$B:$B,Inputs!I:I,,,-1)/_xlfn.XLOOKUP("Operating Cash Flow",Inputs!$B:$B,Inputs!I:I),"") | I58: =IFERROR(_xlfn.XLOOKUP("Net Capex",Inputs!$B:$B,Inputs!J:J,,,-1)/_xlfn.XLOOKUP("Operating Cash Flow",Inputs!$B:$B,Inputs!J:J),"") | J58: =IFERROR(_xlfn.XLOOKUP("Net Capex",Inputs!$B:$B,Inputs!K:K,,,-1)/_xlfn.XLOOKUP("Operating Cash Flow",Inputs!$B:$B,Inputs!K:K),"") | K58: =IFERROR(_xlfn.XLOOKUP("Net Capex",Inputs!$B:$B,Inputs!L:L,,,-1)/_xlfn.XLOOKUP("Operating Cash Flow",Inputs!$B:$B,Inputs!L:L),"") | L58: =IFERROR(_xlfn.XLOOKUP("Net Capex",Inputs!$B:$B,Inputs!M:M,,,-1)/_xlfn.XLOOKUP("Operating Cash Flow",Inputs!$B:$B,Inputs!M:M),"") | M58: =IFERROR(_xlfn.XLOOKUP("Net Capex",Inputs!$B:$B,Inputs!N:N,,,-1)/_xlfn.XLOOKUP("Operating Cash Flow",Inputs!$B:$B,Inputs!N:N),"") | N58: =IFERROR(_xlfn.XLOOKUP("Net Capex",Inputs!$B:$B,Inputs!O:O,,,-1)/_xlfn.XLOOKUP("Operating Cash Flow",Inputs!$B:$B,Inputs!O:O),"") | O58: =IFERROR(_xlfn.XLOOKUP("Net Capex",Inputs!$B:$B,Inputs!P:P,,,-1)/_xlfn.XLOOKUP("Operating Cash Flow",Inputs!$B:$B,Inputs!P:P),"") | P58: =IFERROR(_xlfn.XLOOKUP("Net Capex",Inputs!$B:$B,Inputs!Q:Q,,,-1)/_xlfn.XLOOKUP("Operating Cash Flow",Inputs!$B:$B,Inputs!Q:Q),"") | Q58: =IFERROR(_xlfn.XLOOKUP("Net Capex",DCF!$B:$B,DCF!H:H)/_xlfn.XLOOKUP("Operating Cash Flow",DCF!$B:$B,DCF!H:H),"") | R58: =IFERROR(_xlfn.XLOOKUP("Net Capex",DCF!$B:$B,DCF!I:I)/_xlfn.XLOOKUP("Operating Cash Flow",DCF!$B:$B,DCF!I:I),"")
B59: CFI to CFO | F59: =IFERROR(_xlfn.XLOOKUP("Investing Cash Flow",Inputs!$B:$B,Inputs!G:G,,,-1)/_xlfn.XLOOKUP("Operating Cash Flow",Inputs!$B:$B,Inputs!G:G),"") | G59: =IFERROR(_xlfn.XLOOKUP("Investing Cash Flow",Inputs!$B:$B,Inputs!H:H,,,-1)/_xlfn.XLOOKUP("Operating Cash Flow",Inputs!$B:$B,Inputs!H:H),"") | H59: =IFERROR(_xlfn.XLOOKUP("Investing Cash Flow",Inputs!$B:$B,Inputs!I:I,,,-1)/_xlfn.XLOOKUP("Operating Cash Flow",Inputs!$B:$B,Inputs!I:I),"") | I59: =IFERROR(_xlfn.XLOOKUP("Investing Cash Flow",Inputs!$B:$B,Inputs!J:J,,,-1)/_xlfn.XLOOKUP("Operating Cash Flow",Inputs!$B:$B,Inputs!J:J),"") | J59: =IFERROR(_xlfn.XLOOKUP("Investing Cash Flow",Inputs!$B:$B,Inputs!K:K,,,-1)/_xlfn.XLOOKUP("Operating Cash Flow",Inputs!$B:$B,Inputs!K:K),"") | K59: =IFERROR(_xlfn.XLOOKUP("Investing Cash Flow",Inputs!$B:$B,Inputs!L:L,,,-1)/_xlfn.XLOOKUP("Operating Cash Flow",Inputs!$B:$B,Inputs!L:L),"") | L59: =IFERROR(_xlfn.XLOOKUP("Investing Cash Flow",Inputs!$B:$B,Inputs!M:M,,,-1)/_xlfn.XLOOKUP("Operating Cash Flow",Inputs!$B:$B,Inputs!M:M),"") | M59: =IFERROR(_xlfn.XLOOKUP("Investing Cash Flow",Inputs!$B:$B,Inputs!N:N,,,-1)/_xlfn.XLOOKUP("Operating Cash Flow",Inputs!$B:$B,Inputs!N:N),"") | N59: =IFERROR(_xlfn.XLOOKUP("Investing Cash Flow",Inputs!$B:$B,Inputs!O:O,,,-1)/_xlfn.XLOOKUP("Operating Cash Flow",Inputs!$B:$B,Inputs!O:O),"") | O59: =IFERROR(_xlfn.XLOOKUP("Investing Cash Flow",Inputs!$B:$B,Inputs!P:P,,,-1)/_xlfn.XLOOKUP("Operating Cash Flow",Inputs!$B:$B,Inputs!P:P),"") | P59: =IFERROR(_xlfn.XLOOKUP("Investing Cash Flow",Inputs!$B:$B,Inputs!Q:Q,,,-1)/_xlfn.XLOOKUP("Operating Cash Flow",Inputs!$B:$B,Inputs!Q:Q),"") | Q59: =IFERROR(_xlfn.XLOOKUP("Investing Cash Flow",DCF!$B:$B,DCF!H:H)/_xlfn.XLOOKUP("Operating Cash Flow",DCF!$B:$B,DCF!H:H),"") | R59: =IFERROR(_xlfn.XLOOKUP("Investing Cash Flow",DCF!$B:$B,DCF!I:I)/_xlfn.XLOOKUP("Operating Cash Flow",DCF!$B:$B,DCF!I:I),"")
B60: Net Financing to CFO | F60: =IFERROR((_xlfn.XLOOKUP("Debt Borrowing",Inputs!$B:$B,Inputs!G:G,,,-1)-_xlfn.XLOOKUP("Debt Repayment",Inputs!$B:$B,Inputs!G:G))/_xlfn.XLOOKUP("Operating Cash Flow",Inputs!$B:$B,Inputs!G:G),"") | G60: =IFERROR((_xlfn.XLOOKUP("Debt Borrowing",Inputs!$B:$B,Inputs!H:H,,,-1)-_xlfn.XLOOKUP("Debt Repayment",Inputs!$B:$B,Inputs!H:H))/_xlfn.XLOOKUP("Operating Cash Flow",Inputs!$B:$B,Inputs!H:H),"") | H60: =IFERROR((_xlfn.XLOOKUP("Debt Borrowing",Inputs!$B:$B,Inputs!I:I,,,-1)-_xlfn.XLOOKUP("Debt Repayment",Inputs!$B:$B,Inputs!I:I))/_xlfn.XLOOKUP("Operating Cash Flow",Inputs!$B:$B,Inputs!I:I),"") | I60: =IFERROR((_xlfn.XLOOKUP("Debt Borrowing",Inputs!$B:$B,Inputs!J:J,,,-1)-_xlfn.XLOOKUP("Debt Repayment",Inputs!$B:$B,Inputs!J:J))/_xlfn.XLOOKUP("Operating Cash Flow",Inputs!$B:$B,Inputs!J:J),"") | J60: =IFERROR((_xlfn.XLOOKUP("Debt Borrowing",Inputs!$B:$B,Inputs!K:K,,,-1)-_xlfn.XLOOKUP("Debt Repayment",Inputs!$B:$B,Inputs!K:K))/_xlfn.XLOOKUP("Operating Cash Flow",Inputs!$B:$B,Inputs!K:K),"") | K60: =IFERROR((_xlfn.XLOOKUP("Debt Borrowing",Inputs!$B:$B,Inputs!L:L,,,-1)-_xlfn.XLOOKUP("Debt Repayment",Inputs!$B:$B,Inputs!L:L))/_xlfn.XLOOKUP("Operating Cash Flow",Inputs!$B:$B,Inputs!L:L),"") | L60: =IFERROR((_xlfn.XLOOKUP("Debt Borrowing",Inputs!$B:$B,Inputs!M:M,,,-1)-_xlfn.XLOOKUP("Debt Repayment",Inputs!$B:$B,Inputs!M:M))/_xlfn.XLOOKUP("Operating Cash Flow",Inputs!$B:$B,Inputs!M:M),"") | M60: =IFERROR((_xlfn.XLOOKUP("Debt Borrowing",Inputs!$B:$B,Inputs!N:N,,,-1)-_xlfn.XLOOKUP("Debt Repayment",Inputs!$B:$B,Inputs!N:N))/_xlfn.XLOOKUP("Operating Cash Flow",Inputs!$B:$B,Inputs!N:N),"") | N60: =IFERROR((_xlfn.XLOOKUP("Debt Borrowing",Inputs!$B:$B,Inputs!O:O,,,-1)-_xlfn.XLOOKUP("Debt Repayment",Inputs!$B:$B,Inputs!O:O))/_xlfn.XLOOKUP("Operating Cash Flow",Inputs!$B:$B,Inputs!O:O),"") | O60: =IFERROR((_xlfn.XLOOKUP("Debt Borrowing",Inputs!$B:$B,Inputs!P:P,,,-1)-_xlfn.XLOOKUP("Debt Repayment",Inputs!$B:$B,Inputs!P:P))/_xlfn.XLOOKUP("Operating Cash Flow",Inputs!$B:$B,Inputs!P:P),"") | P60: =IFERROR((_xlfn.XLOOKUP("Debt Borrowing",Inputs!$B:$B,Inputs!Q:Q,,,-1)-_xlfn.XLOOKUP("Debt Repayment",Inputs!$B:$B,Inputs!Q:Q))/_xlfn.XLOOKUP("Operating Cash Flow",Inputs!$B:$B,Inputs!Q:Q),"") | Q60: =IFERROR((_xlfn.XLOOKUP("Debt Borrowing",DCF!$B:$B,DCF!H:H)-_xlfn.XLOOKUP("Debt Repayment",DCF!$B:$B,DCF!H:H))/_xlfn.XLOOKUP("Operating Cash Flow",DCF!$B:$B,DCF!H:H),"") | R60: =IFERROR((_xlfn.XLOOKUP("Debt Borrowing",DCF!$B:$B,DCF!I:I)-_xlfn.XLOOKUP("Debt Repayment",DCF!$B:$B,DCF!I:I))/_xlfn.XLOOKUP("Operating Cash Flow",DCF!$B:$B,DCF!I:I),"")
B61: Debt Repayment to Debt Borrowing | F61: =IFERROR(-_xlfn.XLOOKUP("Debt Repayment",Inputs!$B:$B,Inputs!G:G,,,-1)/_xlfn.XLOOKUP("Debt Borrowing",Inputs!$B:$B,Inputs!G:G),"") | G61: =IFERROR(-_xlfn.XLOOKUP("Debt Repayment",Inputs!$B:$B,Inputs!H:H,,,-1)/_xlfn.XLOOKUP("Debt Borrowing",Inputs!$B:$B,Inputs!H:H),"") | H61: =IFERROR(-_xlfn.XLOOKUP("Debt Repayment",Inputs!$B:$B,Inputs!I:I,,,-1)/_xlfn.XLOOKUP("Debt Borrowing",Inputs!$B:$B,Inputs!I:I),"") | I61: =IFERROR(-_xlfn.XLOOKUP("Debt Repayment",Inputs!$B:$B,Inputs!J:J,,,-1)/_xlfn.XLOOKUP("Debt Borrowing",Inputs!$B:$B,Inputs!J:J),"") | J61: =IFERROR(-_xlfn.XLOOKUP("Debt Repayment",Inputs!$B:$B,Inputs!K:K,,,-1)/_xlfn.XLOOKUP("Debt Borrowing",Inputs!$B:$B,Inputs!K:K),"") | K61: =IFERROR(-_xlfn.XLOOKUP("Debt Repayment",Inputs!$B:$B,Inputs!L:L,,,-1)/_xlfn.XLOOKUP("Debt Borrowing",Inputs!$B:$B,Inputs!L:L),"") | L61: =IFERROR(-_xlfn.XLOOKUP("Debt Repayment",Inputs!$B:$B,Inputs!M:M,,,-1)/_xlfn.XLOOKUP("Debt Borrowing",Inputs!$B:$B,Inputs!M:M),"") | M61: =IFERROR(-_xlfn.XLOOKUP("Debt Repayment",Inputs!$B:$B,Inputs!N:N,,,-1)/_xlfn.XLOOKUP("Debt Borrowing",Inputs!$B:$B,Inputs!N:N),"") | N61: =IFERROR(-_xlfn.XLOOKUP("Debt Repayment",Inputs!$B:$B,Inputs!O:O,,,-1)/_xlfn.XLOOKUP("Debt Borrowing",Inputs!$B:$B,Inputs!O:O),"") | O61: =IFERROR(-_xlfn.XLOOKUP("Debt Repayment",Inputs!$B:$B,Inputs!P:P,,,-1)/_xlfn.XLOOKUP("Debt Borrowing",Inputs!$B:$B,Inputs!P:P),"") | P61: =IFERROR(-_xlfn.XLOOKUP("Debt Repayment",Inputs!$B:$B,Inputs!Q:Q,,,-1)/_xlfn.XLOOKUP("Debt Borrowing",Inputs!$B:$B,Inputs!Q:Q),"") | Q61: =IFERROR(-_xlfn.XLOOKUP("Debt Repayment",DCF!$B:$B,DCF!H:H)/_xlfn.XLOOKUP("Debt Borrowing",DCF!$B:$B,DCF!H:H),"") | R61: =IFERROR(-_xlfn.XLOOKUP("Debt Repayment",DCF!$B:$B,DCF!I:I)/_xlfn.XLOOKUP("Debt Borrowing",DCF!$B:$B,DCF!I:I),"")
B62: CFF to CFO | F62: =IFERROR(_xlfn.XLOOKUP("Financing Cash Flow",Inputs!$B:$B,Inputs!G:G,,,-1)/_xlfn.XLOOKUP("Operating Cash Flow",Inputs!$B:$B,Inputs!G:G),"") | G62: =IFERROR(_xlfn.XLOOKUP("Financing Cash Flow",Inputs!$B:$B,Inputs!H:H,,,-1)/_xlfn.XLOOKUP("Operating Cash Flow",Inputs!$B:$B,Inputs!H:H),"") | H62: =IFERROR(_xlfn.XLOOKUP("Financing Cash Flow",Inputs!$B:$B,Inputs!I:I,,,-1)/_xlfn.XLOOKUP("Operating Cash Flow",Inputs!$B:$B,Inputs!I:I),"") | I62: =IFERROR(_xlfn.XLOOKUP("Financing Cash Flow",Inputs!$B:$B,Inputs!J:J,,,-1)/_xlfn.XLOOKUP("Operating Cash Flow",Inputs!$B:$B,Inputs!J:J),"") | J62: =IFERROR(_xlfn.XLOOKUP("Financing Cash Flow",Inputs!$B:$B,Inputs!K:K,,,-1)/_xlfn.XLOOKUP("Operating Cash Flow",Inputs!$B:$B,Inputs!K:K),"") | K62: =IFERROR(_xlfn.XLOOKUP("Financing Cash Flow",Inputs!$B:$B,Inputs!L:L,,,-1)/_xlfn.XLOOKUP("Operating Cash Flow",Inputs!$B:$B,Inputs!L:L),"") | L62: =IFERROR(_xlfn.XLOOKUP("Financing Cash Flow",Inputs!$B:$B,Inputs!M:M,,,-1)/_xlfn.XLOOKUP("Operating Cash Flow",Inputs!$B:$B,Inputs!M:M),"") | M62: =IFERROR(_xlfn.XLOOKUP("Financing Cash Flow",Inputs!$B:$B,Inputs!N:N,,,-1)/_xlfn.XLOOKUP("Operating Cash Flow",Inputs!$B:$B,Inputs!N:N),"") | N62: =IFERROR(_xlfn.XLOOKUP("Financing Cash Flow",Inputs!$B:$B,Inputs!O:O,,,-1)/_xlfn.XLOOKUP("Operating Cash Flow",Inputs!$B:$B,Inputs!O:O),"") | O62: =IFERROR(_xlfn.XLOOKUP("Financing Cash Flow",Inputs!$B:$B,Inputs!P:P,,,-1)/_xlfn.XLOOKUP("Operating Cash Flow",Inputs!$B:$B,Inputs!P:P),"") | P62: =IFERROR(_xlfn.XLOOKUP("Financing Cash Flow",Inputs!$B:$B,Inputs!Q:Q,,,-1)/_xlfn.XLOOKUP("Operating Cash Flow",Inputs!$B:$B,Inputs!Q:Q),"") | Q62: =IFERROR(_xlfn.XLOOKUP("Financing Cash Flow",DCF!$B:$B,DCF!H:H)/_xlfn.XLOOKUP("Operating Cash Flow",DCF!$B:$B,DCF!H:H),"") | R62: =IFERROR(_xlfn.XLOOKUP("Financing Cash Flow",DCF!$B:$B,DCF!I:I)/_xlfn.XLOOKUP("Operating Cash Flow",DCF!$B:$B,DCF!I:I),"")
