Workbook
Name COOLFUCNTION: _xlfn.LAMBDA(_xldudf_BOARDFLARE_EXEC("workbook-settings:coolfucntion"))
Name COOLFUCNTION: _xlfn.LAMBDA(_xldudf_BOARDFLARE_EXEC("workbook-settings:coolfucntion"))
Name COOLFUCNTION: _xlfn.LAMBDA(_xldudf_BOARDFLARE_EXEC("workbook-settings:coolfucntion"))
Name COOLFUCNTION: _xlfn.LAMBDA(_xldudf_BOARDFLARE_EXEC("workbook-settings:coolfucntion"))
Name COOLFUCNTION: _xlfn.LAMBDA(_xldudf_BOARDFLARE_EXEC("workbook-settings:coolfucntion"))
Name COOLFUCNTION: _xlfn.LAMBDA(_xldudf_BOARDFLARE_EXEC("workbook-settings:coolfucntion"))
Name COOLFUCNTION: _xlfn.LAMBDA(_xldudf_BOARDFLARE_EXEC("workbook-settings:coolfucntion"))
Name COOLFUCNTION: _xlfn.LAMBDA(_xldudf_BOARDFLARE_EXEC("workbook-settings:coolfucntion"))
Name COOLFUCNTION: _xlfn.LAMBDA(_xldudf_BOARDFLARE_EXEC("workbook-settings:coolfucntion"))
Name COOLFUCNTION: _xlfn.LAMBDA(_xldudf_BOARDFLARE_EXEC("workbook-settings:coolfucntion"))
Name Sectors: #REF!
Name Sectors: #REF!
Name Sectors: #REF!

Sheet Summary
E2: | EQUITY RESEARCH | U2: Lisbon Investment Society Equity Research
U3: March XX, 2025
D6: {=+_FV(DCF!R4,"Name")} -> ANALOG DEVICES, INC. | U6: Hold
U8: EXCHANGE:(TICKER)
U9: {=+"Price (7 Mar 25): $"&_FV(DCF!$R$4,"Price")} -> Price (7 Mar 25): $245,56
D10: Investment Thesis | U10: ="Price Target: $" & ROUND(IF(Summary!G25="FCFF",DCF!Q208,IF(Summary!G25="FCFE",DCF!Q251,IF(Summary!G25="Tax Shield",DCF!Q224,DCF!Q267))),2) &" "&IF(Summary!G25="FCFF","(FCFF)",IF(Summary!G25="FCFE","(FCFE)",IF(Summary!G25="Tax Shield","(APV)","(DDM)"))) -> Price Target: $127,94 (FCFF)
U11: =+"Upside (Downside): "&ROUND((DCF!$Q$211*100),2)&"%" -> Upside (Downside): -47,9%
U14: =+Industry!E28&", "&ESG!C9 -> , Semiconductor & Semiconductor components
U15: =+ESG!C10 -> Information technology
D17: Operating Metrics | F17: 2023 | G17: =+F17+1 -> 2024 | H17: =+G17+1 -> 2025 | I17: =+H17+1 -> 2026 | K17: Valuation Multiples | N17: 2022 | O17: =+N17+1 -> 2023 | P17: =+O17+1 -> 2024 | Q17: =+P17+1 -> 2025 | R17: =+Q17+1 -> 2026 | U17: Team Leader
K18: EV / Sales | N18: =IFERROR(_xlfn.XLOOKUP($K18,Multiples!$B:$B,Multiples!N:N),"") -> 7.5092738 | O18: =IFERROR(_xlfn.XLOOKUP($K18,Multiples!$B:$B,Multiples!O:O),"") -> 8.5902671 | P18: =IFERROR(_xlfn.XLOOKUP($K18,Multiples!$B:$B,Multiples!P:P),"") -> 11.736375 | Q18: =IFERROR(_xlfn.XLOOKUP($K18,Multiples!$B:$B,Multiples!Q:Q),"") -> 6.2024187 | R18: =IFERROR(_xlfn.XLOOKUP($K18,Multiples!$B:$B,Multiples!R:R),"") -> 5.625376 | U18: email
K19: Price / Sales | N19: =IFERROR(_xlfn.XLOOKUP($K19,Multiples!$B:$B,Multiples!N:N),"") -> 7.0866003 | O19: =IFERROR(_xlfn.XLOOKUP($K19,Multiples!$B:$B,Multiples!O:O),"") -> 8.103436 | P19: =IFERROR(_xlfn.XLOOKUP($K19,Multiples!$B:$B,Multiples!P:P),"") -> 11.182817 | Q19: =IFERROR(_xlfn.XLOOKUP($K19,Multiples!$B:$B,Multiples!Q:Q),"") | R19: =IFERROR(_xlfn.XLOOKUP($K19,Multiples!$B:$B,Multiples!R:R),"") | U19: (+351) 999 999 999
K20: EV / EBITDA | N20: =IFERROR(_xlfn.XLOOKUP($K20,Multiples!$B:$B,Multiples!N:N),"") -> 19.759169 | O20: =IFERROR(_xlfn.XLOOKUP($K20,Multiples!$B:$B,Multiples!O:O),"") -> 21.383568 | P20: =IFERROR(_xlfn.XLOOKUP($K20,Multiples!$B:$B,Multiples!P:P),"") -> 39.166396 | Q20: =IFERROR(_xlfn.XLOOKUP($K20,Multiples!$B:$B,Multiples!Q:Q),"") -> 17.89259 | R20: =IFERROR(_xlfn.XLOOKUP($K20,Multiples!$B:$B,Multiples!R:R),"") -> 15.997209 | U20: Analyst 1
K21: EV / EBIT | N21: =IFERROR(_xlfn.XLOOKUP($K21,Multiples!$B:$B,Multiples!N:N),"") -> 39.7727 | O21: =IFERROR(_xlfn.XLOOKUP($K21,Multiples!$B:$B,Multiples!O:O),"") -> 39.885119 | P21: =IFERROR(_xlfn.XLOOKUP($K21,Multiples!$B:$B,Multiples!P:P),"") -> 153.54032 | Q21: =IFERROR(_xlfn.XLOOKUP($K21,Multiples!$B:$B,Multiples!Q:Q),"") -> 40.042324 | R21: =IFERROR(_xlfn.XLOOKUP($K21,Multiples!$B:$B,Multiples!R:R),"") -> 31.014882 | U21: email
K22: Price / Earnings | N22: =IFERROR(_xlfn.XLOOKUP($K22,Multiples!$B:$B,Multiples!N:N),"") -> 42.893051 | O22: =IFERROR(_xlfn.XLOOKUP($K22,Multiples!$B:$B,Multiples!O:O),"") -> 41.431291 | P22: =IFERROR(_xlfn.XLOOKUP($K22,Multiples!$B:$B,Multiples!P:P),"") -> 163.62355 | Q22: =IFERROR(_xlfn.XLOOKUP($K22,Multiples!$B:$B,Multiples!Q:Q),"") | R22: =IFERROR(_xlfn.XLOOKUP($K22,Multiples!$B:$B,Multiples!R:R),"") | U22: (+351) 999 999 999
K23: Price / Book | N23: =IFERROR(_xlfn.XLOOKUP($K23,Multiples!$B:$B,Multiples!N:N),"") -> 2.334779 | O23: =IFERROR(_xlfn.XLOOKUP($K23,Multiples!$B:$B,Multiples!O:O),"") -> 2.8037833 | P23: =IFERROR(_xlfn.XLOOKUP($K23,Multiples!$B:$B,Multiples!P:P),"") -> 2.9969796 | Q23: =IFERROR(_xlfn.XLOOKUP($K23,Multiples!$B:$B,Multiples!Q:Q),"") | R23: =IFERROR(_xlfn.XLOOKUP($K23,Multiples!$B:$B,Multiples!R:R),"") | U23: Analyst 2
U24: email
D25: Year | E25: Net Sales | F25: EBIT Margin | G25: FCFF | H25: =+IF(Summary!$G$25="FCFF",DCF!AB6,IF(Summary!$G$25="FCFE",DCF!AC6,DCF!AD6)) -> NOPAT | I25: Net Capex | K25: Profitability Ratios | N25: 2022 | O25: =+N25+1 -> 2023 | P25: =+O25+1 -> 2024 | Q25: =+P25+1 -> 2025 | R25: =+Q25+1 -> 2026 | U25: (+351) 999 999 999
D26: 2022 | E26: =+DCF!E30 -> 12014 | F26: =+DCF!E60 -> 0.18880473 | G26: =+INDEX(DCF!X7:AA7,MATCH(Summary!$G$25,{"FCFF","FCFE","Tax Shield","Total Payout"},0)) -> 3743.8181 | H26: =+IF(Summary!$G$25="FCFF",DCF!AB7,IF(Summary!$G$25="FCFE",DCF!AC7,DCF!AD7)) -> 1928.1181 | I26: =+DCF!E134 -> -699 | K26: Return on Assets | N26: =IFERROR(_xlfn.XLOOKUP($K26,Multiples!$B:$B,Multiples!N:N),"") -> 0.03945935 | O26: =IFERROR(_xlfn.XLOOKUP($K26,Multiples!$B:$B,Multiples!O:O),"") -> 0.049325231 | P26: =IFERROR(_xlfn.XLOOKUP($K26,Multiples!$B:$B,Multiples!P:P),"") -> 0.013359376 | Q26: =IFERROR(_xlfn.XLOOKUP($K26,Multiples!$B:$B,Multiples!Q:Q),"") -> 0.026078652 | R26: =IFERROR(_xlfn.XLOOKUP($K26,Multiples!$B:$B,Multiples!R:R),"") -> 0.034349512 | U26: Analyst 3
D27: =+D26+1 -> 2023 | E27: =+DCF!F30 -> 12305.5 | F27: =+DCF!F60 -> 0.21537524 | G27: =+INDEX(DCF!X8:AA8,MATCH(Summary!$G$25,{"FCFF","FCFE","Tax Shield","Total Payout"},0)) -> 3404.7221 | H27: =+IF(Summary!$G$25="FCFF",DCF!AB8,IF(Summary!$G$25="FCFE",DCF!AC8,DCF!AD8)) -> 2362.3221 | I27: =+DCF!F134 -> -1261 | K27: Return on Equity | N27: =IFERROR(_xlfn.XLOOKUP($K27,Multiples!$B:$B,Multiples!N:N),"") -> 0.05443257 | O27: =IFERROR(_xlfn.XLOOKUP($K27,Multiples!$B:$B,Multiples!O:O),"") -> 0.067673084 | P27: =IFERROR(_xlfn.XLOOKUP($K27,Multiples!$B:$B,Multiples!P:P),"") -> 0.01831631 | Q27: =IFERROR(_xlfn.XLOOKUP($K27,Multiples!$B:$B,Multiples!Q:Q),"") | R27: =IFERROR(_xlfn.XLOOKUP($K27,Multiples!$B:$B,Multiples!R:R),"") | U27: email
D28: =+D27+1 -> 2024 | E28: =+DCF!G30 -> 9427.2 | F28: =+DCF!G60 -> 0.076438391 | G28: =+INDEX(DCF!X9:AA9,MATCH(Summary!$G$25,{"FCFF","FCFE","Tax Shield","Total Payout"},0)) -> 2284.4899 | H28: =+IF(Summary!$G$25="FCFF",DCF!AB9,IF(Summary!$G$25="FCFE",DCF!AC9,DCF!AD9)) -> 590.38985 | I28: =+DCF!G134 -> -730 | K28: Return on Total Capital | N28: =IFERROR(_xlfn.XLOOKUP($K28,Multiples!$B:$B,Multiples!N:N),"") -> 0.044825467 | O28: =IFERROR(_xlfn.XLOOKUP($K28,Multiples!$B:$B,Multiples!O:O),"") -> 0.055565875 | P28: =IFERROR(_xlfn.XLOOKUP($K28,Multiples!$B:$B,Multiples!P:P),"") -> 0.013807737 | Q28: =IFERROR(_xlfn.XLOOKUP($K28,Multiples!$B:$B,Multiples!Q:Q),"") | R28: =IFERROR(_xlfn.XLOOKUP($K28,Multiples!$B:$B,Multiples!R:R),"") | U28: (+351) 999 999 999
D29: =+D28+1 -> 2025 | E29: =+DCF!H30 -> 10336 | F29: =+DCF!H60 -> 0.15489657 | G29: =+INDEX(DCF!X10:AA10,MATCH(Summary!$G$25,{"FCFF","FCFE","Tax Shield","Total Payout"},0)) -> 3929.6086 | H29: =+IF(Summary!$G$25="FCFF",DCF!AB10,IF(Summary!$G$25="FCFE",DCF!AC10,DCF!AD10)) -> 1366.5525 | I29: =+DCF!H134 -> 0 | K29: EBITDA Margin | N29: =IFERROR(_xlfn.XLOOKUP($K29,Multiples!$B:$B,Multiples!N:N),"") -> 0.38003995 | O29: =IFERROR(_xlfn.XLOOKUP($K29,Multiples!$B:$B,Multiples!O:O),"") -> 0.40172281 | P29: =IFERROR(_xlfn.XLOOKUP($K29,Multiples!$B:$B,Multiples!P:P),"") -> 0.29965419 | Q29: =IFERROR(_xlfn.XLOOKUP($K29,Multiples!$B:$B,Multiples!Q:Q),"") -> 0.34664735 | R29: =IFERROR(_xlfn.XLOOKUP($K29,Multiples!$B:$B,Multiples!R:R),"") -> 0.35164735
D30: =+D29+1 -> 2026 | E30: =+DCF!I30 -> 11641.437 | F30: =+DCF!I60 -> 0.18137667 | G30: =+INDEX(DCF!X11:AA11,MATCH(Summary!$G$25,{"FCFF","FCFE","Tax Shield","Total Payout"},0)) -> 3827.6097 | H30: =+IF(Summary!$G$25="FCFF",DCF!AB11,IF(Summary!$G$25="FCFE",DCF!AC11,DCF!AD11)) -> 1804.7549 | I30: =+DCF!I134 -> 0 | K30: EBIT Margin | N30: =IFERROR(_xlfn.XLOOKUP($K30,Multiples!$B:$B,Multiples!N:N),"") -> 0.18880473 | O30: =IFERROR(_xlfn.XLOOKUP($K30,Multiples!$B:$B,Multiples!O:O),"") -> 0.21537524 | P30: =IFERROR(_xlfn.XLOOKUP($K30,Multiples!$B:$B,Multiples!P:P),"") -> 0.076438391 | Q30: =IFERROR(_xlfn.XLOOKUP($K30,Multiples!$B:$B,Multiples!Q:Q),"") -> 0.15489657 | R30: =IFERROR(_xlfn.XLOOKUP($K30,Multiples!$B:$B,Multiples!R:R),"") -> 0.18137667 | U30: Statistics
D31: =+D30+1 -> 2027 | E31: =+DCF!J30 -> 12772.984 | F31: =+DCF!J60 -> 0.19836328 | G31: =+INDEX(DCF!X12:AA12,MATCH(Summary!$G$25,{"FCFF","FCFE","Tax Shield","Total Payout"},0)) -> 4273.3142 | H31: =+IF(Summary!$G$25="FCFF",DCF!AB12,IF(Summary!$G$25="FCFE",DCF!AC12,DCF!AD12)) -> 2134.7109 | I31: =+DCF!J134 -> 0 | K31: Gross Profit Margin | N31: =IFERROR(_xlfn.XLOOKUP($K31,Multiples!$B:$B,Multiples!N:N),"") -> 0.62697686 | O31: =IFERROR(_xlfn.XLOOKUP($K31,Multiples!$B:$B,Multiples!O:O),"") -> 0.64013652 | P31: =IFERROR(_xlfn.XLOOKUP($K31,Multiples!$B:$B,Multiples!P:P),"") -> 0.57083758 | Q31: =IFERROR(_xlfn.XLOOKUP($K31,Multiples!$B:$B,Multiples!Q:Q),"") -> 0.62 | R31: =IFERROR(_xlfn.XLOOKUP($K31,Multiples!$B:$B,Multiples!R:R),"") -> 0.625 | U31: Beta | V31: =Peers!D74 -> 1.0961
D32: =+D31+1 -> 2028 | E32: =+DCF!K30 -> 13232.812 | F32: =+DCF!K60 -> 0.21058883 | G32: =+INDEX(DCF!X13:AA13,MATCH(Summary!$G$25,{"FCFF","FCFE","Tax Shield","Total Payout"},0)) -> 4670.9362 | H32: =+IF(Summary!$G$25="FCFF",DCF!AB13,IF(Summary!$G$25="FCFE",DCF!AC13,DCF!AD13)) -> 2369.4404 | I32: =+DCF!K134 -> 0 | K32: SG&A Margin | N32: =IFERROR(_xlfn.XLOOKUP($K32,Multiples!$B:$B,Multiples!N:N),"") -> 0.10539371 | O32: =IFERROR(_xlfn.XLOOKUP($K32,Multiples!$B:$B,Multiples!O:O),"") -> 0.10349844 | P32: =IFERROR(_xlfn.XLOOKUP($K32,Multiples!$B:$B,Multiples!P:P),"") -> 0.11335285 | Q32: =IFERROR(_xlfn.XLOOKUP($K32,Multiples!$B:$B,Multiples!Q:Q),"") -> 0.107415 | R32: =IFERROR(_xlfn.XLOOKUP($K32,Multiples!$B:$B,Multiples!R:R),"") -> 0.10808876 | U32: % Float | V32: =+Peers!D73 -> 0
D33: =+D32+1 -> 2029 | E33: =+DCF!L30 -> 13709.193 | F33: =+DCF!L60 -> 0.24093974 | G33: =+INDEX(DCF!X14:AA14,MATCH(Summary!$G$25,{"FCFF","FCFE","Tax Shield","Total Payout"},0)) -> 4757.8869 | H33: =+IF(Summary!$G$25="FCFF",DCF!AB14,IF(Summary!$G$25="FCFE",DCF!AC14,DCF!AD14)) -> 2804.9124 | I33: =+DCF!L134 -> 0 | K33: Net Income Margin | N33: =IFERROR(_xlfn.XLOOKUP($K33,Multiples!$B:$B,Multiples!N:N),"") -> 0.16521558 | O33: =IFERROR(_xlfn.XLOOKUP($K33,Multiples!$B:$B,Multiples!O:O),"") -> 0.19558734 | P33: =IFERROR(_xlfn.XLOOKUP($K33,Multiples!$B:$B,Multiples!P:P),"") -> 0.06834479 | Q33: =IFERROR(_xlfn.XLOOKUP($K33,Multiples!$B:$B,Multiples!Q:Q),"") -> 0.13255964 | R33: =IFERROR(_xlfn.XLOOKUP($K33,Multiples!$B:$B,Multiples!R:R),"") -> 0.15502176 | U33: % Held by Insiders | V33: =+Peers!D76 -> 0
U34: % Held by Institutions | V34: =+Peers!D77 -> 0
D35: SWOT Analysis | K35: Liquidity Ratios | N35: 2022 | O35: =+N35+1 -> 2023 | P35: =+O35+1 -> 2024 | Q35: =+P35+1 -> 2025 | R35: =+Q35+1 -> 2026 | U35: Short % of Float | V35: =+Peers!D78 -> 0
D36: Strengths | G36: Weaknesses | K36: Cash Ratio | N36: =IFERROR(_xlfn.XLOOKUP($K36,Multiples!$B:$B,Multiples!N:N),"") -> 0.60203873 | O36: =IFERROR(_xlfn.XLOOKUP($K36,Multiples!$B:$B,Multiples!O:O),"") -> 0.29931271 | P36: =IFERROR(_xlfn.XLOOKUP($K36,Multiples!$B:$B,Multiples!P:P),"") -> 0.66636549 | Q36: =IFERROR(_xlfn.XLOOKUP($K36,Multiples!$B:$B,Multiples!Q:Q),"") -> 2.0464792 | R36: =IFERROR(_xlfn.XLOOKUP($K36,Multiples!$B:$B,Multiples!R:R),"") -> 3.566234 | W36: 120.87
K37: Quick Ratio | N37: =IFERROR(_xlfn.XLOOKUP($K37,Multiples!$B:$B,Multiples!N:N),"") -> 1.3391329 | O37: =IFERROR(_xlfn.XLOOKUP($K37,Multiples!$B:$B,Multiples!O:O),"") -> 0.75845048 | P37: =IFERROR(_xlfn.XLOOKUP($K37,Multiples!$B:$B,Multiples!P:P),"") -> 1.2379614 | Q37: =IFERROR(_xlfn.XLOOKUP($K37,Multiples!$B:$B,Multiples!Q:Q),"") -> 2.5926227 | R37: =IFERROR(_xlfn.XLOOKUP($K37,Multiples!$B:$B,Multiples!R:R),"") -> 4.1519566 | U37: Major Holders | W37: 113.63
K38: Current Ratio | N38: =IFERROR(_xlfn.XLOOKUP($K38,Multiples!$B:$B,Multiples!N:N),"") -> 2.0215335 | O38: =IFERROR(_xlfn.XLOOKUP($K38,Multiples!$B:$B,Multiples!O:O),"") -> 1.369572 | P38: =IFERROR(_xlfn.XLOOKUP($K38,Multiples!$B:$B,Multiples!P:P),"") -> 1.8353914 | Q38: =IFERROR(_xlfn.XLOOKUP($K38,Multiples!$B:$B,Multiples!Q:Q),"") -> 3.1110933 | R38: =IFERROR(_xlfn.XLOOKUP($K38,Multiples!$B:$B,Multiples!R:R),"") -> 3.1110933
D40: Opportunities | G40: Threats | K40: Cash Flow Ratios | N40: 2022 | O40: =+N40+1 -> 2023 | P40: =+O40+1 -> 2024 | Q40: =+P40+1 -> 2025 | R40: =+Q40+1 -> 2026
K41: Cash Conversion Cycle | N41: =IFERROR(_xlfn.XLOOKUP($K41,Multiples!$B:$B,Multiples!N:N),"") -> 151.02962 | O41: =IFERROR(_xlfn.XLOOKUP($K41,Multiples!$B:$B,Multiples!O:O),"") -> 164.32778 | P41: =IFERROR(_xlfn.XLOOKUP($K41,Multiples!$B:$B,Multiples!P:P),"") -> 163.4708 | Q41: =IFERROR(_xlfn.XLOOKUP($K41,Multiples!$B:$B,Multiples!Q:Q),"") -> 132.6672 | R41: =IFERROR(_xlfn.XLOOKUP($K41,Multiples!$B:$B,Multiples!R:R),"") -> 136.45635
K42: Net Income / Op Cash Flow | N42: =IFERROR(_xlfn.XLOOKUP($K42,Multiples!$B:$B,Multiples!N:N),"") -> 0.44351343 | O42: =IFERROR(_xlfn.XLOOKUP($K42,Multiples!$B:$B,Multiples!O:O),"") -> 0.49958486 | P42: =IFERROR(_xlfn.XLOOKUP($K42,Multiples!$B:$B,Multiples!P:P),"") -> 0.16724205 | Q42: =IFERROR(_xlfn.XLOOKUP($K42,Multiples!$B:$B,Multiples!Q:Q),"") -> 0.32237277 | R42: =IFERROR(_xlfn.XLOOKUP($K42,Multiples!$B:$B,Multiples!R:R),"") -> 0.4215321
K43: Chg in Cash / Op Cash Flow | N43: =IFERROR(_xlfn.XLOOKUP($K43,Multiples!$B:$B,Multiples!N:N),"") -> -0.11337534 | O43: =IFERROR(_xlfn.XLOOKUP($K43,Multiples!$B:$B,Multiples!O:O),"") -> -0.10638077 | P43: =IFERROR(_xlfn.XLOOKUP($K43,Multiples!$B:$B,Multiples!P:P),"") -> 0.26821544 | Q43: =IFERROR(_xlfn.XLOOKUP($K43,Multiples!$B:$B,Multiples!Q:Q),"") -> 1.1090482 | R43: =IFERROR(_xlfn.XLOOKUP($K43,Multiples!$B:$B,Multiples!R:R),"") -> 1.1630332
D45: Revenue by Region | G45: Revenue by Segment | K45: Leverage Ratios | N45: 2022 | O45: =+N45+1 -> 2023 | P45: =+O45+1 -> 2024 | Q45: =+P45+1 -> 2025 | R45: =+Q45+1 -> 2026
K46: Total Debt / Equity | N46: =IFERROR(_xlfn.XLOOKUP($K46,Multiples!$B:$B,Multiples!N:N),"") -> 179.58443 | O46: =IFERROR(_xlfn.XLOOKUP($K46,Multiples!$B:$B,Multiples!O:O),"") -> 195.38255 | P46: =IFERROR(_xlfn.XLOOKUP($K46,Multiples!$B:$B,Multiples!P:P),"") -> 215.53148 | Q46: =IFERROR(_xlfn.XLOOKUP($K46,Multiples!$B:$B,Multiples!Q:Q),"") | R46: =IFERROR(_xlfn.XLOOKUP($K46,Multiples!$B:$B,Multiples!R:R),"")
K47: Total Debt / Capital | N47: =IFERROR(_xlfn.XLOOKUP($K47,Multiples!$B:$B,Multiples!N:N),"") -> 0.99446242 | O47: =IFERROR(_xlfn.XLOOKUP($K47,Multiples!$B:$B,Multiples!O:O),"") -> 0.9949079 | P47: =IFERROR(_xlfn.XLOOKUP($K47,Multiples!$B:$B,Multiples!P:P),"") -> 0.99538173 | Q47: =IFERROR(_xlfn.XLOOKUP($K47,Multiples!$B:$B,Multiples!Q:Q),"") | R47: =IFERROR(_xlfn.XLOOKUP($K47,Multiples!$B:$B,Multiples!R:R),"")
K48: Total Liabilities / Total Assets | N48: =IFERROR(_xlfn.XLOOKUP($K48,Multiples!$B:$B,Multiples!N:N),"") -> 0.27507833 | O48: =IFERROR(_xlfn.XLOOKUP($K48,Multiples!$B:$B,Multiples!O:O),"") -> 0.27112482 | P48: =IFERROR(_xlfn.XLOOKUP($K48,Multiples!$B:$B,Multiples!P:P),"") -> 0.27062949 | Q48: =IFERROR(_xlfn.XLOOKUP($K48,Multiples!$B:$B,Multiples!Q:Q),"") | R48: =IFERROR(_xlfn.XLOOKUP($K48,Multiples!$B:$B,Multiples!R:R),"")
K49: Total Debt / EBITDA | N49: =IFERROR(_xlfn.XLOOKUP($K49,Multiples!$B:$B,Multiples!N:N),"") -> 1.4342722 | O49: =IFERROR(_xlfn.XLOOKUP($K49,Multiples!$B:$B,Multiples!O:O),"") -> 1.4056722 | P49: =IFERROR(_xlfn.XLOOKUP($K49,Multiples!$B:$B,Multiples!P:P),"") -> 2.6838472 | Q49: =IFERROR(_xlfn.XLOOKUP($K49,Multiples!$B:$B,Multiples!Q:Q),"") | R49: =IFERROR(_xlfn.XLOOKUP($K49,Multiples!$B:$B,Multiples!R:R),"") | U49: Board of Directors
K50: Total Debt / (EBITDA - Capex) | N50: =IFERROR(_xlfn.XLOOKUP($K50,Multiples!$B:$B,Multiples!N:N),"") -> 1.6935451 | O50: =IFERROR(_xlfn.XLOOKUP($K50,Multiples!$B:$B,Multiples!O:O),"") -> 1.8870302 | P50: =IFERROR(_xlfn.XLOOKUP($K50,Multiples!$B:$B,Multiples!P:P),"") -> 3.6190749 | Q50: =IFERROR(_xlfn.XLOOKUP($K50,Multiples!$B:$B,Multiples!Q:Q),"") | R50: =IFERROR(_xlfn.XLOOKUP($K50,Multiples!$B:$B,Multiples!R:R),"")
K51: Net Debt / EBITDA | N51: =IFERROR(_xlfn.XLOOKUP($K50,Multiples!$B:$B,Multiples!N:N),"") -> 1.6935451 | O51: =IFERROR(_xlfn.XLOOKUP($K50,Multiples!$B:$B,Multiples!O:O),"") -> 1.8870302 | P51: =IFERROR(_xlfn.XLOOKUP($K50,Multiples!$B:$B,Multiples!P:P),"") -> 3.6190749 | Q51: =IFERROR(_xlfn.XLOOKUP($K50,Multiples!$B:$B,Multiples!Q:Q),"") | R51: =IFERROR(_xlfn.XLOOKUP($K50,Multiples!$B:$B,Multiples!R:R),"")
K53: Solvency Ratios | N53: 2022 | O53: =+N53+1 -> 2023 | P53: =+O53+1 -> 2024 | Q53: =+P53+1 -> 2025 | R53: =+Q53+1 -> 2026
K54: EBIT / Interest Expense | N54: =IFERROR(_xlfn.XLOOKUP($K54,Multiples!$B:$B,Multiples!N:N),"") -> 11.318862 | O54: =IFERROR(_xlfn.XLOOKUP($K54,Multiples!$B:$B,Multiples!O:O),"") -> 10.016251 | P54: =IFERROR(_xlfn.XLOOKUP($K54,Multiples!$B:$B,Multiples!P:P),"") -> 2.2364991 | Q54: =IFERROR(_xlfn.XLOOKUP($K54,Multiples!$B:$B,Multiples!Q:Q),"") -> N/A | R54: =IFERROR(_xlfn.XLOOKUP($K54,Multiples!$B:$B,Multiples!R:R),"") -> N/A
K55: EBITDA / Interest Expense | N55: =IFERROR(_xlfn.XLOOKUP($K55,Multiples!$B:$B,Multiples!N:N),"") -> 22.783433 | O55: =IFERROR(_xlfn.XLOOKUP($K55,Multiples!$B:$B,Multiples!O:O),"") -> 18.68254 | P55: =IFERROR(_xlfn.XLOOKUP($K55,Multiples!$B:$B,Multiples!P:P),"") -> 8.7675357 | Q55: =IFERROR(_xlfn.XLOOKUP($K55,Multiples!$B:$B,Multiples!Q:Q),"") -> N/A | R55: =IFERROR(_xlfn.XLOOKUP($K55,Multiples!$B:$B,Multiples!R:R),"") -> N/A
K56: (EBITDA - Capex) / Interest Expense | N56: =IFERROR(_xlfn.XLOOKUP($K56,Multiples!$B:$B,Multiples!N:N),"") -> 26.271457 | O56: =IFERROR(_xlfn.XLOOKUP($K56,Multiples!$B:$B,Multiples!O:O),"") -> 23.448224 | P56: =IFERROR(_xlfn.XLOOKUP($K56,Multiples!$B:$B,Multiples!P:P),"") -> 11.033209 | Q56: =IFERROR(_xlfn.XLOOKUP($K56,Multiples!$B:$B,Multiples!Q:Q),"") -> N/A | R56: =IFERROR(_xlfn.XLOOKUP($K56,Multiples!$B:$B,Multiples!R:R),"") -> N/A
D58: Debt Schedule | K58: Stock Performance
U60: ESG Traffic Light
U61: LSEG ESG Score | V61: =ESG!C14 -> 70
U62: E-Score | V62: =ESG!C15 -> 61
U63: S-Score | V63: =ESG!C16 -> 71
U64: G-Score | V64: =ESG!C17 -> 80
U65: S&P Global ESG Score | V65: =ESG!C18 -> 50
U66: Environmental | V66: =ESG!C19 -> 54
U67: Social | V67: =ESG!C20 -> 47
U68: Governance & Economic | V68: =ESG!C21 -> 47
U69: Sustainalytics | V69: =ESG!C22 -> 16.7
U70: ISS ESG Corporate Rating | V70: =ESG!C23 -> C+
U71: SDG Impact Rating | V71: =ESG!C24 -> 2.5
U72: Governance Quality Score | V72: =ESG!C25 -> 9
U73: MSCI ESG Ratings | V73: =ESG!C26 -> A
D80: Extra Notes

Sheet Segments
B2: Segments
B4: Regions | D4: Weight | E4: 2020 | F4: =+E4+1 -> 2021 | G4: =+F4+1 -> 2022 | H4: =+G4+1 -> 2023 | I4: =+H4+1 -> 2024 | J4: ="CAGR "&$G$4&" - "&$I$4 -> CAGR 2022 - 2024 | K4: 2021 | L4: =+K4+1 -> 2022 | M4: =+L4+1 -> 2023 | N4: =+M4+1 -> 2024
B6: China | D6: =IFERROR(I6/SUM($I$6:$I$12),"") -> 0.22581945 | E6: 1348 | F6: 1614.4 | G6: 2563.5 | H6: 2229.6 | I6: 2128.8 | J6: =IFERROR((I6/G6)^(1/COUNT($G$4:$I$4))-1,"") -> -0.060059174 | K6: =IFERROR(F6-E6/E6,"") -> 1613.4 | L6: =IFERROR(G6-F6/F6,"") -> 2562.5 | M6: =IFERROR((H6-G6)/G6,"") -> -0.13025161 | N6: =IFERROR((I6-H6)/H6,"") -> -0.045209903
B7: Europe | D7: =IFERROR(I7/SUM($I$6:$I$12),"") -> 0.22377214 | E7: 1245.7 | F7: 1593 | G7: 2534.4 | H7: 3001.9 | I7: 2109.5 | J7: =IFERROR((I7/G7)^(1/COUNT($G$4:$I$4))-1,"") -> -0.059335423 | K7: =IFERROR(F7-E7/E7,"") -> 1592 | L7: =IFERROR(G7-F7/F7,"") -> 2533.4 | M7: =IFERROR((H7-G7)/G7,"") -> 0.18446181 | N7: =IFERROR((I7-H7)/H7,"") -> -0.29727839
B8: Rest of Asia | D8: =IFERROR(I8/SUM($I$6:$I$12),"") -> 0.12733637 | E8: 558.9 | F8: 890.7 | G8: 1596.6 | H8: 1423 | I8: 1200.4 | J8: =IFERROR((I8/E8)^(1/COUNT($E$4:$I$4))-1,"") -> 0.16519436 | K8: =IFERROR(F8-E8/E8,"") -> 889.7 | L8: =IFERROR(G8-F8/F8,"") -> 1595.6 | M8: =IFERROR(H8-G8/G8,"") -> 1422 | N8: =IFERROR((I8-H8)/H8,"") -> -0.15643008
B9: Japan | D9: =IFERROR(I9/SUM($I$6:$I$12),"") -> 0.11515859 | E9: 521.7 | F9: 788 | G9: 1221.5 | H9: 1397.1 | I9: 1085.6 | J9: =IFERROR((I9/E9)^(1/COUNT($E$4:$I$4))-1,"") -> 0.15784333 | K9: =IFERROR(F9-E9/E9,"") -> 787 | L9: =IFERROR(G9-F9/F9,"") -> 1220.5 | M9: =IFERROR(H9-G9/G9,"") -> 1396.1 | N9: =IFERROR((I9-H9)/H9,"") -> -0.22296185
B10: Rest of North & South America | D10: =IFERROR(I10/SUM($I$6:$I$12),"") -> 0.0066086772 | E10: 41.3 | F10: 42.8 | G10: 72.5 | H10: 88.6 | I10: 62.3 | J10: =IFERROR((I10/E10)^(1/COUNT($E$4:$I$4))-1,"") -> 0.085694403 | K10: =IFERROR(F10-E10/E10,"") -> 41.8 | L10: =IFERROR(G10-F10/F10,"") -> 71.5 | M10: =IFERROR(H10-G10/G10,"") -> 87.6 | N10: =IFERROR((I10-H10)/H10,"") -> -0.29683973
B11: United States | D11: =IFERROR(I11/SUM($I$6:$I$12),"") -> 0.30130476 | E11: 1887.4 | F11: 2389.4 | G11: 4025.4 | H11: 4165.3 | I11: 2840.4 | J11: =IFERROR((I11/E11)^(1/COUNT($E$4:$I$4))-1,"") -> 0.085183322 | K11: =IFERROR(F11-E11/E11,"") -> 2388.4 | L11: =IFERROR(G11-F11/F11,"") -> 4024.4 | M11: =IFERROR(H11-G11/G11,"") -> 4164.3 | N11: =IFERROR((I11-H11)/H11,"") -> -0.31808033
D12: =IFERROR(I12/SUM($I$6:$I$12),"") -> 0
B13: Total | D13: =SUM(D6:D12) -> 1 | E13: =SUM(E6:E10) -> 3715.6 | F13: =SUM(F6:F10) -> 4928.9 | G13: =SUM(G6:G10) -> 7988.5 | H13: =SUM(H6:H10) -> 8140.2 | I13: =SUM(I6:I10) -> 6586.6 | J13: =IFERROR((I13/G13)^(1/COUNT($G$4:$I$4))-1,"") -> -0.062296904 | K13: =IFERROR(F13-E13/E13,"") -> 4927.9 | L13: =IFERROR(G13-F13/F13,"") -> 7987.5 | M13: =IFERROR((H13-G13)/G13,"") -> 0.018989798 | N13: =IFERROR((I13-H13)/H13,"") -> -0.19085526
B15: Segments | D15: Weight | E15: 2020 | F15: =+E15+1 -> 2021 | G15: =+F15+1 -> 2022 | H15: =+G15+1 -> 2023 | I15: =+H15+1 -> 2024 | J15: ="CAGR "&$E$4&" - "&$I$4 -> CAGR 2020 - 2024 | K15: 2021 | L15: =+K15+1 -> 2022 | M15: =+L15+1 -> 2023 | N15: =+M15+1 -> 2024
B17: Industrial | D17: =IFERROR(I17/SUM($I$17:$I$21),"") -> 0.45764869 | E17: 2998.3 | F17: 4026.9 | G17: 6069.3 | H17: 6555.2 | I17: 4314.3 | J17: =IFERROR((I17/E17)^(1/COUNT($E$4:$I$4))-1,"") -> 0.075491671 | K17: =IFERROR((F17-E17)/E17,"") -> 0.34306107 | L17: =IFERROR((G17-F17)/F17,"") -> 0.50718915 | M17: =IFERROR((H17-G17)/G17,"") -> 0.080058656 | N17: =IFERROR((I17-H17)/H17,"") -> -0.34185074
B18: Communications | D18: =IFERROR(I18/SUM($I$17:$I$21),"") -> 0.11461637 | E18: 1191.2 | F18: 1206.9 | G18: 1880.7 | H18: 1619.5 | I18: 1080.5 | J18: =IFERROR((I18/E18)^(1/COUNT($E$4:$I$4))-1,"") -> -0.019318422 | K18: =IFERROR((F18-E18)/E18,"") -> 0.013179987 | L18: =IFERROR((G18-F18)/F18,"") -> 0.55828983 | M18: =IFERROR((H18-G18)/G18,"") -> -0.13888446 | N18: =IFERROR((I18-H18)/H18,"") -> -0.33281877
B19: Consumer | D19: =IFERROR(I19/SUM($I$17:$I$21),"") -> 0.12781237 | E19: 635.3 | F19: 836.3 | G19: 1548.4 | H19: 1215.6 | I19: 1204.9 | J19: =IFERROR((I19/E19)^(1/COUNT($E$4:$I$4))-1,"") -> 0.1365654 | K19: =IFERROR((F19-E19)/E19,"") -> 0.31638596 | L19: =IFERROR((G19-F19)/F19,"") -> 0.8514887 | M19: =IFERROR((H19-G19)/G19,"") -> -0.21493154 | N19: =IFERROR((I19-H19)/H19,"") -> -0.0088022376
B20: Automotive | D20: =IFERROR(I20/SUM($I$17:$I$21),"") -> 0.29992256 | E20: 778.3 | F20: 1248.2 | G20: 2515.5 | H20: 2915.2 | I20: 2827.4 | J20: =IFERROR((I20/E20)^(1/COUNT($E$4:$I$4))-1,"") -> 0.29433902 | K20: =IFERROR((F20-E20)/E20,"") -> 0.60375177 | L20: =IFERROR((G20-F20)/F20,"") -> 1.015302 | M20: =IFERROR((H20-G20)/G20,"") -> 0.15889485 | N20: =IFERROR((I20-H20)/H20,"") -> -0.030118002
D21: =IFERROR(I21/SUM($I$17:$I$21),"") -> 0 | J21: =IFERROR((I21/E21)^(1/COUNT($E$4:$I$4))-1,"") | K21: =IFERROR((F21-E21)/E21,"") | L21: =IFERROR((G21-F21)/F21,"") | M21: =IFERROR((H21-G21)/G21,"") | N21: =IFERROR((I21-H21)/H21,"")
B22: Total | D22: =SUM(D17:D21) -> 1 | E22: =SUM(E17:E21) -> 5603.1 | F22: =SUM(F17:F21) -> 7318.3 | G22: =SUM(G17:G21) -> 12013.9 | H22: =SUM(H17:H21) -> 12305.5 | I22: =SUM(I17:I21) -> 9427.1 | J22: =IFERROR((I22/E22)^(1/COUNT($E$4:$I$4))-1,"") -> 0.10966004 | K22: =IFERROR((F22-E22)/E22,"") -> 0.30611626 | L22: =IFERROR((G22-F22)/F22,"") -> 0.64162442 | M22: =IFERROR((H22-G22)/G22,"") -> 0.024271885 | N22: =IFERROR((I22-H22)/H22,"") -> -0.23391167
B24: Categories | D24: Description | J24: Graphs
B26: Industrial | D26: Factory automation, energy systems, healthcare instrumentation.
B27: Automotive | D27: Advanced driver-assistance systems (ADAS), infotainment, vehicle electrification.
B28: Consumer | D28: Smartphones, wearable devices, smart home applications.
B29: =IF(B20=0,"",B20) -> Automotive
B30: =IF(B21=0,"",B21)

Sheet Industry
B2: Industry Overview
B4: Sales Growth Forecast | E4: Weight | F4: 2025 | G4: =+F4+1 -> 2026 | H4: =+G4+1 -> 2027 | I4: =+H4+1 -> 2028 | J4: =+I4+1 -> 2029 | K4: =+J4+1 -> 2030 | L4: =+K4+1 -> 2031 | M4: =+L4+1 -> 2032 | N4: =+M4+1 -> 2033 | ... P4: =+O4+1 -> 2035 | Q4: ="CAGR "&$F$4&" - "&$P$4 -> CAGR 2025 - 2035 | R4: Sources
B11: Weighted Average | E11: =SUM(E6:E10) -> 0 | F11: =SUMPRODUCT(F6:F10,$E$6:$E$10) -> 0 | G11: =SUMPRODUCT(G6:G10,$E$6:$E$10) -> 0 | H11: =SUMPRODUCT(H6:H10,$E$6:$E$10) -> 0 | I11: =SUMPRODUCT(I6:I10,$E$6:$E$10) -> 0 | J11: =SUMPRODUCT(J6:J10,$E$6:$E$10) -> 0 | K11: =SUMPRODUCT(K6:K10,$E$6:$E$10) -> 0 | L11: =SUMPRODUCT(L6:L10,$E$6:$E$10) -> 0 | M11: =SUMPRODUCT(M6:M10,$E$6:$E$10) -> 0 | ... P11: =SUMPRODUCT(P6:P10,$E$6:$E$10) -> 0 | Q11: =IFERROR(((1+F11)*(1+G11)*(1+H11)*(1+I11)*(1+J11)*(1+K11)*(1+L11)*(1+M11)*(1+N11)*(1+O11)*(1+P11))^(1/COUNT($F$4:$P$4))-1,"") -> 0
B13: Key Drivers | E13: Description
B15: Recovery in Industrial and Automotive Demand | E15: After a period of inventory corrections, demand in the industrial and automotive sectors is rebounding. Analog Devices is experiencing sequential growth in these markets, positioning the company to benefit from a multi-year semiconductor upcycle.
B16: Expansion in Consumer Electronics | E16: The consumer segment has shown robust growth, driven by increased demand for AI-driven devices, premium smartphones, and smart home products. In Q1 2025, Analog Devices' consumer segment revenue rose by 19%, highlighting the company's strength in this area.
B17: Advancements in AI and IoT Applications | E17: The proliferation of AI and IoT technologies is increasing the demand for analog and mixed-signal solutions. ADI's portfolio is well-suited to support these applications, providing opportunities for growth in various end markets.
B18: Strategic Acquisitions Enhancing Product Portfolio | E18: ADI's acquisitions, such as Maxim Integrated, have expanded its product offerings and market reach, particularly in power management and signal conditioning, strengthening its position in the analog semiconductor market.
B20: Industry Trends | E20: Description
B22: Growth in Analog Semiconductor Market | E22: The analog semiconductor market is projected to grow significantly, with an estimated increase of USD 35.1 billion from 2025 to 2029, at a CAGR of 6.9%. This growth is driven by demand across automotive, industrial, and consumer electronics sectors.
B23: Integration of AI in Edge Devices | E23: The integration of AI capabilities into edge devices, such as smartphones and IoT gadgets, is transforming the semiconductor landscape. This trend necessitates advanced analog solutions for efficient processing, an area where ADI is actively involve
B26: Market Share | E26: Headquarters | G26: Revenues | H26: (in MM of USD) | I26: Market Share
B28: {=+_FV(DCF!R4,"Name")} -> ANALOG DEVICES, INC. | G28: {=TRANSPOSE(Peers!D97:N97)} -> 9427.2 | I28: =IFERROR(G28/$G$40,"") -> 0.10059972
B29: {=+_FV(Peers!A8,"Name")} -> TEXAS INSTRUMENTS INCORPORATED | G29: 15641 | I29: =IFERROR(G29/$G$40,"") -> 0.16690855
B30: {=+_FV(Peers!A9,"Name")} -> MICROCHIP TECHNOLOGY INCORPORATED | G30: 7634.4 | I30: =IFERROR(G30/$G$40,"") -> 0.08146836
B31: {=+_FV(Peers!A10,"Name")} -> MONOLITHIC POWER SYSTEMS, INC. | G31: 2207.1 | I31: =IFERROR(G31/$G$40,"") -> 0.023552449
B32: {=+_FV(Peers!A11,"Name")} -> SKYWORKS SOLUTIONS, INC. | G32: 4178 | I32: =IFERROR(G32/$G$40,"") -> 0.044584356
B33: {=+_FV(Peers!A12,"Name")} -> MACOM TECHNOLOGY SOLUTIONS HOLDINGS, INC. | G33: 729.578 | I33: =IFERROR(G33/$G$40,"") -> 0.0077854871
B34: {=+_FV(Peers!A13,"Name")} -> MARVELL TECHNOLOGY, INC. | G34: 5508 | I34: =IFERROR(G34/$G$40,"") -> 0.058777078
B35: {=+_FV(Peers!A14,"Name")} -> #VALUE! | G35: 0 | I35: =IFERROR(G35/$G$40,"") -> 0
B36: {=+_FV(Peers!A15,"Name")} -> #VALUE! | G36: 0 | I36: =IFERROR(G36/$G$40,"") -> 0
B37: {=+_FV(Peers!A16,"Name")} -> #VALUE! | G37: 0 | I37: =IFERROR(G37/$G$40,"") -> 0
B38: {=+_FV(Peers!A17,"Name")} -> #VALUE! | G38: 0 | I38: =IFERROR(G38/$G$40,"") -> 0
B39: Others | E39: -- | G39: =G40-SUM(G28:G38) -> 48384.722 | I39: =IFERROR(G39/$G$40,"") -> 0.516324
B40: Industry Size | E40: -- | G40: 93710 | I40: 1
B42: Porter's Five Forces Analysis | E42: Rating | H42: Graph
B44: Threat of New Entrants | E44: =IFERROR(AVERAGE(E45:E50),"") -> 4
B45: Economies of scale | E45: 5
B46: Product differentiation | E46: 5
B47: Capital requirements | E47: 5
B48: Access to distribution channels | E48: 3
B49: Regulations | E49: 3
B50: Switching costs | E50: 3
B51: Bargaining Power of Suppliers | E51: =IFERROR(AVERAGE(E52:E56),"") -> 3
B52: Number of suppliers | E52: 3
B53: Uniqueness | E53: 3
B54: Switching Costs | E54: 3
B55: Forward Integration | E55: 1
B56: Industry Importance | E56: 5
B57: Bargaining Power of Customers | E57: =IFERROR(AVERAGE(E58:E62),"") -> 3
B58: Number of buyers | E58: 2
B59: Purchase size | E59: 3
B60: Switching costs | E60: 3
B61: Price sensitivity | E61: 3
B62: Informed buyers | E62: 4
B63: Competitive Rivalry | E63: =IFERROR(AVERAGE(E64:E68),"") -> 3.4
B64: Number of competitors | E64: 4
B65: Industry growth | E65: 2
B66: Similarities in what's offered | E66: 4
B67: Exit barriers | E67: 3
B68: Fixed costs | E68: 4
B69: Threat of Substitutes | E69: =IFERROR(AVERAGE(E70:E74),"") -> 2.25
B70: Relative price performance | E70: 2
B71: Customer willingness to go elsewhere | E71: 2
B72: The sense that products are similar | E72: 3
B73: Availability of close substitutes | E73: 2

Sheet Peers
D3: Revenue Growth | F3: EBITDA Margin | H3: Profit Margin | J3: EV / Revenue | L3: EV / EBITDA | N3: Price / Earnings
B4: Peers | C4: Ticker | D4: =+Inputs!O4&"-"&Inputs!P4 -> 2022-2023 | E4: =+Inputs!P4&"-"&Inputs!Q4 -> 2023-2024 | F4: 2023 | G4: 2024 | H4: =+Inputs!O4&"-"&Inputs!P4 -> 2022-2023 | I4: =+Inputs!P4&"-"&Inputs!Q4 -> 2023-2024 | J4: 2023 | K4: 2024 | L4: 2023 | M4: 2024 | N4: 2023 | O4: 2024
A6: =+D91 -> #VALUE! | B6: {=IFERROR(_FV(A6,"Name"),"")} -> ANALOG DEVICES, INC. | C6: {=IFERROR(_FV(A6,"Ticker symbol",TRUE),"")} -> ADI | D6: =IFERROR(D94/D93-1,"") -> 0.024263359 | E6: =IFERROR(D97/D94-1,"") -> -0.23390354 | F6: =IFERROR(D95/D94,"") -> 0.40172281 | G6: =IFERROR(D100/D97,"") -> 0.29965419 | H6: =IFERROR(D96/D94,"") -> 0.19558734 | I6: =IFERROR(D105/D97,"") -> 0.06834479 | J6: {=IFERROR((_FV(A6,"Market cap",TRUE)/1000000+D$121-D$111)/D$94,"")} -> 10.271413 | K6: {=IFERROR((_FV(A6,"Market cap",TRUE)/1000000+D$121-D$111)/D$97,"")} -> 13.407466 | L6: {=+IFERROR((_FV(A6,"Market cap",TRUE)/1000000+D$121-D$111)/D$95,"")} -> 25.568408 | M6: {=IFERROR((_FV(A6,"Market cap",TRUE)/1000000+D$121-D$111)/D$100,"")} -> 44.74313 | N6: {=IFERROR((_FV(A6,"Market cap",TRUE)/1000000)/D$96,"")} -> 50.193023 | O6: {=IFERROR((_FV(A6,"Market cap",TRUE)/1000000)/D$105,"")} -> 187.49739
A8: =+E91 -> #VALUE! | B8: {=IFERROR(_FV(A8,"Name"),"")} -> TEXAS INSTRUMENTS INCORPORATED | C8: {=+IFERROR(_FV(A8,"Ticker symbol",TRUE),"")} -> TXN | D8: =+IFERROR(E94/E93-1,"") -> -0.12527462 | E8: =IFERROR(E97/E94-1,"") -> -0.1071979 | F8: =IFERROR(E95/E94,"") -> 0.51424168 | G8: =+IFERROR(E100/E97,"") -> 0.4821303 | H8: =IFERROR(E96/E94,"") -> 0.37159655 | I8: =+IFERROR(D105/D99,"") -> 0.11972721 | J8: {=+IFERROR((_FV(A8,"Market cap",TRUE)/1000000+E$121-E$111)/E$94,"")} -> 9.8996265 | K8: {=IFERROR(+(_FV(A8,"Market cap",TRUE)/1000000+E$121-E$111)/E$97,"")} -> 11.088265 | L8: {=IFERROR(+(_FV(A8,"Market cap",TRUE)/1000000+E$121-E$111)/E$95,"")} -> 19.250922 | M8: {=IFERROR(+(_FV(A8,"Market cap",TRUE)/1000000+E$121-E$111)/E$100,"")} -> 22.998482 | N8: {=IFERROR(+(_FV(A8,"Market cap",TRUE)/1000000)/E$96,"")} -> 25.043864 | O8: {=IFERROR(+(_FV(A8,"Market cap",TRUE)/1000000)/E$105,"")} -> 33.972819
A9: =+F91 -> #VALUE! | B9: {=IFERROR(_FV(A9,"Name"),"")} -> MICROCHIP TECHNOLOGY INCORPORATED | C9: {=+IFERROR(_FV(A9,"Ticker symbol",TRUE),"")} -> MCHP | D9: =IFERROR(F94/F93-1,"") -> 0.23718278 | E9: =IFERROR(+F97/F94-1,"") -> -0.095310889 | F9: =IFERROR(F95/F94,"") -> 0.4946852 | G9: =IFERROR(F100/F97,"") -> 0.45870009 | H9: =IFERROR(F96/F94,"") -> 0.26517118 | I9: =+IFERROR(F105/F97,"") -> 0.24977732 | J9: {=IFERROR(+(_FV(A9,"Market cap",TRUE)/1000000+F$122-F$112)/F$94,"")} -> 4.7879056 | K9: {=IFERROR(+(_FV(A9,"Market cap",TRUE)/1000000+F$122-F$112)/F$97,"")} -> 5.2923215 | L9: {=IFERROR(+(_FV(A9,"Market cap",TRUE)/1000000+F$122-F$112)/F$95,"")} -> 9.6786918 | M9: {=IFERROR(+(_FV(A9,"Market cap",TRUE)/1000000+F$122-F$112)/F$100,"")} -> 11.537651 | N9: {=IFERROR(+(_FV(A9,"Market cap",TRUE)/1000000)/F$96,"")} -> 15.58721 | O9: {=IFERROR(+(_FV(A9,"Market cap",TRUE)/1000000)/F$105,"")} -> 18.291205
A10: =+G91 -> #VALUE! | B10: {=IFERROR(_FV(A10,"Name"),"")} -> MONOLITHIC POWER SYSTEMS, INC. | C10: {=IFERROR(_FV(A10,"Ticker symbol",TRUE),"")} -> MPWR | D10: =+IFERROR(G94/G93-1,"") -> 0.015006566 | E10: =IFERROR(G97/G94-1,"") -> 0.21197844 | F10: =IFERROR(G95/G94,"") -> 0.28830107 | G10: =IFERROR(G100/G97,"") -> 0.26264827 | H10: =IFERROR(G96/G94,"") -> 0.23468265 | I10: =+IFERROR(G105/G97,"") -> 0.80952381 | J10: {=IFERROR(+(_FV(A10,"Market cap",TRUE)/1000000+G$122-G$112)/G$94,"")} -> 24.026317 | K10: {=IFERROR(+(_FV(A10,"Market cap",TRUE)/1000000+G$122-G$112)/G$97,"")} -> 19.824046 | L10: {=IFERROR(+(_FV(A10,"Market cap",TRUE)/1000000+G$122-G$112)/G$95,"")} -> 83.337592 | M10: {=IFERROR(+(_FV(A10,"Market cap",TRUE)/1000000+G$122-G$112)/G$100,"")} -> 75.477543 | N10: {=IFERROR(+(_FV(A10,"Market cap",TRUE)/1000000)/G$96,"")} -> 102.3779 | O10: {=IFERROR(+(_FV(A10,"Market cap",TRUE)/1000000)/G$105,"")} -> 24.488528
A11: =+H91 -> #VALUE! | B11: {=IFERROR(_FV(A11,"Name"),"")} -> SKYWORKS SOLUTIONS, INC. | C11: {=IFERROR(_FV(A11,"Ticker symbol",TRUE),"")} -> SWKS | D11: =IFERROR(H94/H93-1,"") -> -0.12999727 | E11: =IFERROR(H97/H94-1,"") -> -0.12454949 | F11: =IFERROR(H95/H94,"") -> 0.39173162 | G11: =IFERROR(H100/H97,"") -> 0.34214935 | H11: =IFERROR(H96/H94,"") -> 0.20593412 | I11: =+IFERROR(H105/H102,"") -> 19.413681 | J11: {=IFERROR((_FV(A11,"Market cap",TRUE)/1000000+H$122-H$112)/H$94,"")} -> 2.4075477 | K11: {=IFERROR(+(_FV(A11,"Market cap",TRUE)/1000000+H$122-H$112)/H$97,"")} -> 2.7500671 | L11: {=IFERROR(+(_FV(A11,"Market cap",TRUE)/1000000+H$122-H$112)/H$95,"")} -> 6.1459109 | M11: {=IFERROR(+(_FV(A11,"Market cap",TRUE)/1000000+H$122-H$112)/H$100,"")} -> 8.0376219 | N11: {=IFERROR(+(_FV(A11,"Market cap",TRUE)/1000000)/H$96,"")} -> 11.690863 | O11: {=IFERROR(+(_FV(A11,"Market cap",TRUE)/1000000)/H$105,"")} -> 19.278155
A12: =+I91 -> #VALUE! | B12: {=IFERROR(_FV(A12,"Name"),"")} -> MACOM TECHNOLOGY SOLUTIONS HOLDINGS, INC. | C12: {=IFERROR(_FV(A12,"Ticker symbol",TRUE),"")} -> MTSI | D12: =+IFERROR(I94/I93-1,"") -> -0.039638906 | E12: =IFERROR(I97/I94-1,"") -> 0.12518526 | F12: =IFERROR(I95/I94,"") -> 0.27309853 | G12: =IFERROR(I100/I97,"") -> 0.23116788 | H12: =IFERROR(I96/I94,"") -> 0.14123382 | I12: =+IFERROR(I105/I97,"") -> 0.1053472 | J12: {=IFERROR((_FV(A12,"Market cap",TRUE)/1000000+I$122-I$112)/I$94,"")} -> 14.826906 | K12: {=IFERROR(+(_FV(A12,"Market cap",TRUE)/1000000+I$122-I$112)/I$97,"")} -> 13.177302 | L12: {=IFERROR(+(_FV(A12,"Market cap",TRUE)/1000000+I$122-I$112)/I$95,"")} -> 54.291417 | M12: {=IFERROR(+(_FV(A12,"Market cap",TRUE)/1000000+I$122-I$112)/I$100,"")} -> 57.003172 | N12: {=IFERROR(+(_FV(A12,"Market cap",TRUE)/1000000)/I$96,"")} -> 104.98127 | O12: {=IFERROR(+(_FV(A12,"Market cap",TRUE)/1000000)/I$105,"")} -> 125.0845
A13: =+J91 -> #VALUE! | B13: {=IFERROR(_FV(A13,"Name"),"")} -> MARVELL TECHNOLOGY, INC. | C13: {=IFERROR(_FV(A13,"Ticker symbol",TRUE),"")} -> MRVL | D13: =IFERROR(J94/J93-1,"") -> 0.3267593 | E13: =IFERROR(J97/J94-1,"") -> -0.069594595 | F13: =IFERROR(J95/J94,"") -> 0.27837838 | G13: =IFERROR(J100/J97,"") -> 0.15450254 | H13: =IFERROR(J96/J94,"") -> -0.027702703 | I13: =+IFERROR(J105/J97,"") -> -0.16938998 | J13: {=IFERROR(+(_FV(A13,"Market cap",TRUE)/1000000+J$121-J$111)/J$94,"")} -> 11.3542 | K13: {=IFERROR(+(_FV(A13,"Market cap",TRUE)/1000000+J$121-J$111)/J$97,"")} -> 12.203498 | L13: {=IFERROR(+(_FV(A13,"Market cap",TRUE)/1000000+J$121-J$111)/J$95,"")} -> 40.786932 | M13: {=IFERROR(+(_FV(A13,"Market cap",TRUE)/1000000+J$121-J$111)/J$100,"")} -> 78.98574 | N13: {=IFERROR(+(_FV(A13,"Market cap",TRUE)/1000000)/J$96,"")} -> -388.82234 | O13: {=IFERROR(+(_FV(A13,"Market cap",TRUE)/1000000)/J$105,"")} -> -68.34605
A14: =+K91 -> #VALUE! | B14: {=IFERROR(_FV(A14,"Nome"),"")} -> INTEL CORPORATION | C14: {=IFERROR(_FV(A14,"Símbolo do ticker",TRUE),"")} -> INTC | D14: =IFERROR(K94/K93-1,"") | E14: =IFERROR(K97/K94-1,"") | F14: =+IFERROR(K95/K94,"") | G14: =IFERROR(K100/K97,"") | H14: =IFERROR(K96/K94,"") | I14: =+IFERROR(K105/K97,"") | J14: {=IFERROR((_FV(A14,"Market cap",TRUE)/1000000+D$121-K$111)/K$94,"")} | K14: {=IFERROR(+(_FV(A14,"Market cap",TRUE)/1000000+D$121-K$111)/K$97,"")} | L14: {=IFERROR(+(_FV(A14,"Market cap",TRUE)/1000000+D$121-K$111)/K$95,"")} | M14: {=IFERROR(+(_FV(A14,"Market cap",TRUE)/1000000+D$121-K$111)/K$100,"")} | N14: {=IFERROR(+(_FV(A14,"Market cap",TRUE)/1000000)/K$96,"")} | O14: {=IFERROR(+(_FV(A14,"Market cap",TRUE)/1000000)/K$105,"")}
A15: =+L91 -> #VALUE! | B15: {=IFERROR(_FV(A15,"Nome"),"")} -> MICRON TECHNOLOGY, INC. | C15: {=IFERROR(_FV(A15,"Símbolo do ticker",TRUE),"")} -> MU | D15: =+IFERROR(L94/L93,"") | E15: =IFERROR(L97/L94,"") | F15: =IFERROR(L95/L94,"") | G15: =IFERROR(L100/L97,"") | H15: =IFERROR(L96/L94,"") | I15: =+IFERROR(L105/L97,"") | J15: {=IFERROR(+(_FV(A15,"Market cap",TRUE)/1000000+L$121-L$111)/L$94,"")} | K15: {=IFERROR(+(_FV(A15,"Market cap",TRUE)/1000000+L$121-L$111)/L$97,"")} | L15: {=IFERROR(+(_FV(A15,"Market cap",TRUE)/1000000+L$121-L$111)/L$95,"")} | M15: {=IFERROR(+(_FV(A15,"Market cap",TRUE)/1000000+L$121-L$111)/L$100,"")} | N15: {=IFERROR(+(_FV(A15,"Market cap",TRUE)/1000000)/L$96,"")} | O15: {=IFERROR(+(_FV(A15,"Market cap",TRUE)/1000000)/L$105,"")}
A16: =+M91 -> #VALUE! | B16: {=IFERROR(_FV(A16,"Nome"),"")} -> FIRST SOLAR, INC. | C16: {=IFERROR(_FV(A16,"Símbolo do ticker",TRUE),"")} -> FSLR | D16: =IFERROR(M94/M93-1,"") | E16: =IFERROR(M97/M94-1,"") | F16: =IFERROR(M95/M94,"") | G16: =IFERROR(M100/M97,"") | H16: =IFERROR(M96/M94,"") | I16: =+IFERROR(M105/M97,"") | J16: {=IFERROR(+(_FV(A16,"Market cap",TRUE)/1000000+M$121-M$111)/M$94,"")} | K16: {=IFERROR(+(_FV(A16,"Market cap",TRUE)/1000000+M$121-M$111)/M$97,"")} | L16: {=IFERROR(+(_FV(A16,"Market cap",TRUE)/1000000+M$121-M$111)/M$95,"")} | M16: {=IFERROR(+(_FV(A16,"Market cap",TRUE)/1000000+M$121-M$111)/M$100,"")} | N16: {=IFERROR(+(_FV(A16,"Market cap",TRUE)/1000000)/M$96,"")} | O16: {=IFERROR(+(_FV(A16,"Market cap",TRUE)/1000000)/M$105,"")}
A17: =+N91 -> #VALUE! | B17: {=IFERROR(_FV(A17,"Nome"),"")} -> ALTRI, S.G.P.S., S.A. | C17: {=+IFERROR(_FV(A17,"Símbolo do ticker",TRUE),"")} -> ALTR | D17: =IFERROR(N94/N93-1,"") | E17: =IFERROR(N97/N94-1,"") | F17: =IFERROR(N95/N94,"") | G17: =IFERROR(N100/N97,"") | H17: =IFERROR(N96/N94,"") | I17: =+IFERROR(N105/N97,"") | J17: {=IFERROR(+(_FV(A17,"Market cap",TRUE)/1000000+N$121-N$111)/N$94,"")} | K17: {=IFERROR(+(_FV(A17,"Market cap",TRUE)/1000000+N$121-N$111)/N$97,"")} | L17: {=IFERROR(+(_FV(A17,"Market cap",TRUE)/1000000+N$121-N$111)/N$95,"")} | M17: {=IFERROR(+(_FV(A17,"Market cap",TRUE)/1000000+N$121-N$111)/N$100,"")} | N17: {=IFERROR(+(_FV(A17,"Market cap",TRUE)/1000000)/N$96,"")} | O17: {=IFERROR(+(_FV(A17,"Market cap",TRUE)/1000000)/N$105,"")}
B18: Average | D18: =IFERROR(AVERAGE(D6:D17),"") -> 0.044043031 | E18: =IFERROR(AVERAGE(E6:E17),"") -> -0.041913245 | F18: =IFERROR(AVERAGE(F6:F17),"") -> 0.37745133 | G18: =IFERROR(AVERAGE(G6:G17),"") -> 0.31870752 | H18: =IFERROR(AVERAGE(H6:H17),"") -> 0.19807185 | I18: =IFERROR(AVERAGE(I6:I17),"") -> 2.9424302 | J18: =IFERROR(AVERAGE(J6:J17),"") -> 11.081988 | K18: =IFERROR(AVERAGE(K6:K17),"") -> 11.106138 | ... O18: =IFERROR(AVERAGE(O6:O17),"") -> 48.609507
B19: Deviation from Average | D19: =IFERROR(+D18-D6,"") -> 0.019779671 | E19: =IFERROR(E18-E6,"") -> 0.19199029 | F19: =+IFERROR(F18-F6,"") -> -0.02427148 | G19: =IFERROR(G18-G6,"") -> 0.019053327 | H19: =IFERROR(+H6-H18,"") -> -0.0024845121 | I19: =+IFERROR(I6-I18,"") -> -2.8740854 | J19: =+IFERROR(J6-J18,"") -> -0.81057529 | K19: =+IFERROR(K6-K18,"") -> 2.3013284 | L19: =IFERROR(+L6-L18,"") -> -8.5830026 | M19: =IFERROR(M6-M18,"") -> 2.0597959 | N19: =IFERROR(+N6-N18,"") -> 61.471339 | O19: =IFERROR(+O6-O18,"") -> 138.88788
D21: Trading Multiple | G21: Net | H21: Preferred | I21: Non-Controlling | J21: Equity Value | M21: Implied Upside (Downside)
B22: Implied Share Price | D22: Revenue | E22: EBITDA | F22: P/E | G22: Debt | H22: Stock | I22: Interest | J22: Revenue | K22: EBITDA | L22: P/E | M22: Revenue | N22: EBITDA | O22: P/E | P22: Current Price
B24: Second Minimum | D24: =IFERROR(SMALL(K6:K17,2),"") -> 5.2923215 | E24: =IFERROR(SMALL(M6:M17,2),"") -> 11.537651 | F24: =IFERROR(SMALL(O6:O17,2),"") -> 18.291205 | G24: =-Inputs!$Q$99+Inputs!$Q$100 -> 5218.5 | H24: =+Inputs!$Q$101 -> 0 | I24: =+Inputs!$Q$102 -> 0 | J24: =IFERROR(+D24*$D$97+G24+H24+I24,"") -> 55110.273 | K24: =IFERROR(E24*$D$100+G24+H24+I24,"") -> 37811.209 | L24: =IFERROR(F24*$D$105,"") -> 11785.023 | M24: {=IFERROR(+(J24/_FV($A$6,"Shares outstanding",TRUE)*1000000)/$P$24-1,"")} -> -0.54380638 | N24: {=IFERROR((+K24/_FV($A$6,"Shares outstanding",TRUE)*1000000)/$P$24-1,"")} -> -0.68700513 | O24: {=IFERROR(+(L24/_FV($A$6,"Shares outstanding",TRUE)*1000000)/$P$24-1,"")} -> -0.90244555 | P24: {=+_FV(A6,"Price")} -> 245.56
B25: Average | D25: =+IFERROR(AVERAGE(K6:K17),"") -> 11.106138 | E25: =IFERROR(+AVERAGE(M6:M17),"") -> 42.683334 | F25: =IFERROR(+AVERAGE(O6:O17),"") -> 48.609507 | G25: =-Inputs!$Q$99+Inputs!$Q$100 -> 5218.5 | H25: =+Inputs!$Q$101 -> 0 | I25: =+Inputs!$Q$102 -> 0 | J25: =IFERROR(+D25*$D$97+G25+H25+I25,"") -> 109918.28 | K25: =IFERROR(E25*$D$100+G25+H25+I25,"") -> 125794.65 | L25: =IFERROR(+F25*$D$105,"") -> 31319.105 | M25: {=IFERROR(+(J25/_FV($A$6,"Shares outstanding",TRUE)*1000000)/$P$24-1,"")} -> -0.090114832 | N25: {=IFERROR((+K25/_FV($A$6,"Shares outstanding",TRUE)*1000000)/$P$24-1,"")} -> 0.041307069 | O25: {=IFERROR(+(L25/_FV($A$6,"Shares outstanding",TRUE)*1000000)/$P$24-1,"")} -> -0.74074569
B26: Median | D26: =IFERROR(MEDIAN(K6:K17),"") -> 12.203498 | E26: =IFERROR(MEDIAN(M6:M17),"") -> 44.74313 | F26: =IFERROR(MEDIAN(O6:O17),"") -> 24.488528 | G26: =-Inputs!$Q$99+Inputs!$Q$100 -> 5218.5 | H26: =+Inputs!$Q$101 -> 0 | I26: =+Inputs!$Q$102 -> 0 | J26: =IFERROR(D26*$D$97+G26+H26+I26,"") -> 120263.31 | K26: =IFERROR(E26*$D$100+G26+H26+I26,"") -> 131613.37 | L26: =IFERROR(+F26*$D$105,"") -> 15777.958 | M26: {=IFERROR(+(J26/_FV($A$6,"Shares outstanding",TRUE)*1000000)/$P$24-1,"")} -> -0.0044804262 | N26: {=IFERROR((+K26/_FV($A$6,"Shares outstanding",TRUE)*1000000)/$P$24-1,"")} -> 0.089473438 | O26: {=+IFERROR((L26/_FV($A$6,"Shares outstanding",TRUE)*1000000)/$P$24-1,"")} -> -0.8693927
B27: Second Maximum | D27: =IFERROR(LARGE(K6:K17,2),"") -> 13.407466 | E27: =IFERROR(LARGE(M6:M17,2),"") -> 75.477543 | F27: =IFERROR(LARGE(O6:O17,2),"") -> 125.0845 | G27: =-Inputs!$Q$99+Inputs!$Q$100 -> 5218.5 | H27: =+Inputs!$Q$101 -> 0 | I27: =+Inputs!$Q$102 -> 0 | J27: =IFERROR(+D27*$D$97+G27+H27+I27,"") -> 131613.37 | K27: =IFERROR(E27*$D$100+G27+H27+I27,"") -> 218435.01 | L27: =IFERROR(+F27*$D$105,"") -> 80591.946 | M27: {=IFERROR(+(J27/_FV($A$6,"Shares outstanding",TRUE)*1000000)/$P$24-1,"")} -> 0.089473438 | N27: {=IFERROR((+K27/_FV($A$6,"Shares outstanding",TRUE)*1000000)/$P$24-1,"")} -> 0.80816847 | O27: {=IFERROR(+(L27/_FV($A$6,"Shares outstanding",TRUE)*1000000)/$P$24-1,"")} -> -0.33287336
B29: Profitability | D29: =+LEFT(B6, FIND(" ", B6 & " ") - 1) -> ANALOG | E29: =+LEFT(B8, FIND(" ", B8 & " ") - 1) -> TEXAS | F29: =+LEFT(B9, FIND(" ", B9 & " ") - 1) -> MICROCHIP | G29: =+LEFT(B10, FIND(" ", B10 & " ") - 1) -> MONOLITHIC | H29: =+LEFT(B11, FIND(" ", B11 & " ") - 1) -> SKYWORKS | I29: =+LEFT(B12, FIND(" ", B12 & " ") - 1) -> MACOM | J29: =+LEFT(C12, FIND(" ", C12 & " ") - 1) -> MTSI | K29: =+LEFT(B14, FIND(" ", B14 & " ") - 1) -> INTEL | L29: =+LEFT(B15, FIND(" ", B15 & " ") - 1) -> MICRON | M29: =+LEFT(B16, FIND(" ", B16 & " ") - 1) -> FIRST | N29: =+LEFT(B17, FIND(" ", B17 & " ") - 1) -> ALTRI, | O29: Average
B31: Operating Margin | D31: =IFERROR(D101/D97,"") -> 0.076438391 | E31: =IFERROR(E101/E97,"") -> 0.38111374 | F31: =IFERROR(F101/F97,"") -> 0.33558629 | G31: =IFERROR(G101/G97,"") -> 0.24437407 | H31: =IFERROR(H101/H97,"") -> 0.22565821 | I31: =IFERROR(I101/I97,"") -> 0.12671709 | J31: =IFERROR(J101/J97,"") -> -0.099491649 | K31: =IFERROR(K101/K97,"") | ... N31: =IFERROR(N101/N97,"") | O31: =IFERROR(+AVERAGE(D31:N31),"") -> 0.18434231
B32: Net Income Margin | D32: =IFERROR(D105/D97,"") -> 0.06834479 | E32: =IFERROR(E105/E97,"") -> 0.30682181 | F32: =IFERROR(F105/F97,"") -> 0.24977732 | G32: =IFERROR(G105/G97,"") -> 0.80952381 | H32: =IFERROR(H105/H97,"") -> 0.14265199 | I32: =IFERROR(I105/I97,"") -> 0.1053472 | J32: =IFERROR(J105/J97,"") -> -0.16938998 | K32: =IFERROR(K105/K97,"") | ... N32: =IFERROR(N105/N97,"") | O32: =IFERROR(+AVERAGE(D32:N32),"") -> 0.21615385
B33: ROA (%) | D33: =IFERROR(D105/D117,"") -> 0.013359376 | E33: =IFERROR(E105/E117,"") -> 0.13514884 | F33: =IFERROR(F105/F118,"") -> 8.9525822 | G33: =IFERROR(G105/G118,"") | H33: =IFERROR(H105/H118,"") | I33: =IFERROR(I105/I118,"") | J33: =IFERROR(J105/J117,"") -> -0.043949315 | K33: =IFERROR(K105/K117,"") | L33: =IFERROR(L105/L117,"") | M33: =IFERROR(M105/M117,"") | N33: =IFERROR(N105/N117,"") | O33: =IFERROR(+AVERAGE(D33:N33),"") -> 2.2642853
B34: Financial Cost of Debt | D34: =IFERROR(+(D102/D121)*(1-(D104/D103)),"") -> -0.0085154965 | E34: =IFERROR(+(E102/E121)*(1-(E104/E103)),"") -> 0.032882726 | F34: =IFERROR(+(F102/F122)*(1-(F104/F103)),"") -> 0.017662659 | G34: =IFERROR(+(G102/G122)*(1-(G104/G103)),"") | H34: =IFERROR(+(H102/H122)*(1-(H104/H103)),"") | I34: =IFERROR(+(I102/I122)*(1-(I104/I103)),"") | J34: =IFERROR(+(J102/J121)*(1-(J104/J103)),"") -> 0.053405637 | K34: =IFERROR(+(K102/K121)*(1-(K104/K103)),"") | L34: =IFERROR(+(L102/L121)*(1-(L104/L103)),"") | M34: =IFERROR(+(M102/M121)*(1-(M104/M103)),"") | N34: =IFERROR(+(N102/N121)*(1-(N104/N103)),"") | O34: =IFERROR(+AVERAGE(D34:N34),"") -> 0.023858881
B35: Return on Equity (RoE) | D35: =IFERROR(+D105/D122,"") -> 0.01831631 | E35: =IFERROR(+E105/E122,"") -> 0.2839141 | F35: =IFERROR(+F105/#REF!,"") | G35: =IFERROR(+G105/#REF!,"") | H35: =IFERROR(+H105/#REF!,"") | I35: =IFERROR(+I105/#REF!,"") | J35: =IFERROR(+J105/J122,"") -> -0.062908772 | K35: =IFERROR(+K105/K122,"") | L35: =IFERROR(+L105/L122,"") | M35: =IFERROR(+M105/M122,"") | N35: =IFERROR(+N105/N122,"") | O35: =IFERROR(+AVERAGE(D35:N35),"") -> 0.079773878
B36: Return on Invested Capital (ROIC) | D36: =IFERROR(+D105/(D121+D122),"") -> 0.01506856 | E36: =IFERROR(+E105/(E121+E122),"") -> 0.15734942 | F36: =IFERROR(+F105/(F122+#REF!),"") | G36: =IFERROR(+G105/(G122+#REF!),"") | H36: =IFERROR(+H105/(H122+#REF!),"") | I36: =IFERROR(+I105/(I122+#REF!),"") | J36: =IFERROR(+J105/(J121+J122),"") -> -0.048512895 | K36: =IFERROR(+K105/(K121+K122),"") | L36: =IFERROR(+L105/(L121+L122),"") | M36: =IFERROR(+M105/(M121+M122),"") | N36: =IFERROR(+N105/(N121+N122),"") | O36: =IFERROR(+AVERAGE(D36:N36),"") -> 0.041301696
B38: Solvency | D38: =+D29 -> ANALOG | E38: =+E29 -> TEXAS | F38: =+F29 -> MICROCHIP | G38: =+G29 -> MONOLITHIC | H38: =+H29 -> SKYWORKS | I38: =+I29 -> MACOM | J38: =+J29 -> MTSI | K38: =+K29 -> INTEL | ... O38: =+O29 -> Average
B40: Debt/Assets | D40: =IFERROR(D121/D117,"") -> 0.15720231 | E40: =IFERROR(E121/E117,"") -> 0.38288885 | F40: =IFERROR(F122/F118,"") -> 31.257277 | G40: =IFERROR(G122/G118,"") | H40: =IFERROR(H122/H118,"") | I40: =IFERROR(I122/I118,"") | J40: =IFERROR(J121/J117,"") -> 0.20731075 | K40: =IFERROR(K121/K117,"") | L40: =IFERROR(L121/L117,"") | M40: =IFERROR(M121/M117,"") | N40: =IFERROR(N121/N117,"") | O40: =IFERROR(+AVERAGE(D40:N40),"") -> 8.0011697
B41: Net Debt/EBITDA | D41: =IFERROR(+(D121-D111)/D100,"") -> 1.9789373 | E41: =IFERROR(+(E121-E111)/E100,"") -> 1.378597 | F41: =IFERROR(+(F122-F112)/F100,"") -> 1.5774865 | G41: =IFERROR(+(G122-G112)/G100,"") -> 0 | H41: =IFERROR(+(H122-H112)/H100,"") -> 0 | I41: =IFERROR(+(I122-I112)/I100,"") -> 0 | J41: =IFERROR(+(J121-J111)/J100,"") -> 4.0540541 | K41: =IFERROR(+(K121-K111)/K100,"") | L41: =IFERROR(+(L121-L111)/L100,"") | M41: =IFERROR(+(M121-M111)/M100,"") | N41: =IFERROR(+(N121-N111)/N100,"") | O41: =IFERROR(+AVERAGE(D41:N41),"") -> 1.2841536
B42: Interest Coverage Ratio | D42: =IFERROR(D101/D102,"") -> -9.1446701 | E42: =IFERROR(E101/E102,"") -> 11.734252 | F42: =IFERROR(F101/F102,"") -> 17.559973 | G42: =IFERROR(G101/G102,"") | H42: =IFERROR(H101/H102,"") -> 30.710098 | I42: =IFERROR(I101/I102,"") -> -5.1792717 | J42: =IFERROR(J101/J102,"") -> -2.8691099 | K42: =IFERROR(K101/K102,"") | ... N42: =IFERROR(N101/N102,"") | O42: =IFERROR(+AVERAGE(D42:N42),"") -> 7.1352118
B44: Liquidity | D44: =+D29 -> ANALOG | E44: =+E29 -> TEXAS | F44: =+F29 -> MICROCHIP | G44: =+G29 -> MONOLITHIC | H44: =+H29 -> SKYWORKS | I44: =+I29 -> MACOM | J44: =+J29 -> MTSI | K44: =+K29 -> INTEL | ... O44: =+O29 -> Average
B46: Cash Ratio | D46: =IFERROR(D111/D119,"") -> 0.66636549 | E46: =IFERROR(E111/E119,"") -> 0.87839693 | F46: =IFERROR(F112/F120,"") -> 0.22101343 | G46: =IFERROR(G112/G120,"") | H46: =IFERROR(H112/H120,"") | I46: =IFERROR(I112/I120,"") | J46: =IFERROR(J111/J119,"") -> 0.52425579 | K46: =IFERROR(K111/K119,"") | L46: =IFERROR(L111/L119,"") | M46: =IFERROR(M111/M119,"") | N46: =IFERROR(N111/N119,"") | O46: =IFERROR(+AVERAGE(D46:N46),"") -> 0.57250791
B47: Quick Ratio | D47: =IFERROR(+(D111+D112)/D119,"") -> 1.1135428 | E47: =IFERROR(+(E111+E112)/E119,"") -> 1.3502608 | F47: =IFERROR(+(F112+F113)/F120,"") -> 0.22101343 | G47: =IFERROR(+(G112+G113)/G120,"") | H47: =IFERROR(+(H112+H113)/H120,"") | I47: =IFERROR(+(I112+I113)/I120,"") | J47: =IFERROR(+(J111+J112)/J119,"") -> 1.1427784 | K47: =IFERROR(+(K111+K112)/K119,"") | L47: =IFERROR(+(L111+L112)/L119,"") | M47: =IFERROR(+(M111+M112)/M119,"") | N47: =IFERROR(+(N111+N112)/N119,"") | O47: =IFERROR(+AVERAGE(D47:N47),"") -> 0.95689885
B48: Current Ratio | D48: =IFERROR(D115/D119,"") -> 1.8353914 | E48: =IFERROR(E115/E119,"") -> 4.1246226 | F48: =IFERROR(F116/F120,"") -> 0.26337954 | G48: =IFERROR(G116/G120,"") | H48: =IFERROR(H116/H120,"") | I48: =IFERROR(I116/I120,"") | J48: =IFERROR(J115/J119,"") -> 1.6885336 | K48: =IFERROR(K115/K119,"") | L48: =IFERROR(L115/L119,"") | M48: =IFERROR(M115/M119,"") | N48: =IFERROR(N115/N119,"") | O48: =IFERROR(+AVERAGE(D48:N48),"") -> 1.9779818
B50: Activity | D50: =+D29 -> ANALOG | E50: =+E29 -> TEXAS | F50: =+F29 -> MICROCHIP | G50: =+G29 -> MONOLITHIC | H50: =+H29 -> SKYWORKS | I50: =+I29 -> MACOM | J50: =+J29 -> MTSI | K50: =+K29 -> INTEL | ... O50: =+O29 -> Average
B52: Inventory Turnover | D52: =IFERROR(D98/(AVERAGE(D113:D114)),"") -> 2.6187255 | E52: =IFERROR(E98/(AVERAGE(E113:E114)),"") -> 1.5357729 | F52: =IFERROR(F98/(AVERAGE(F114:F115)),"") -> 0.85037061 | G52: =IFERROR(G98/(AVERAGE(G114:G115)),"") | H52: =IFERROR(H98/(AVERAGE(H114:H115)),"") | I52: =IFERROR(I98/(AVERAGE(I114:I115)),"") | J52: =IFERROR(J98/(AVERAGE(J113:J114)),"") -> 3.3271222 | K52: =IFERROR(K98/(AVERAGE(K113:K114)),"") | L52: =IFERROR(L98/(AVERAGE(L113:L114)),"") | M52: =IFERROR(M98/(AVERAGE(M113:M114)),"") | N52: =IFERROR(N98/(AVERAGE(N113:N114)),"") | O52: =IFERROR(+AVERAGE(D52:N52),"") -> 2.0829978
B53: Acc. Receivable Turnover | D53: =IFERROR(D97/D112,"") -> 7.0547033 | E53: =IFERROR(E97/E112,"") -> 9.0988947 | F53: =IFERROR(F97/F113,"") | G53: =IFERROR(G97/G113,"") | H53: =IFERROR(H97/H113,"") | I53: =IFERROR(I97/I113,"") | J53: =IFERROR(J97/J112,"") -> 4.9090909 | K53: =IFERROR(K97/K112,"") | L53: =IFERROR(L97/L112,"") | M53: =IFERROR(M97/M112,"") | N53: =IFERROR(N97/N112,"") | O53: =IFERROR(+AVERAGE(D53:N53),"") -> 7.0208963
B54: Payables Turnover | D54: =IFERROR(D98/D118,"") -> 8.2990769 | E54: =IFERROR(E98/E118,"") -> 7.9841463 | F54: =IFERROR(F98/F119,"") -> 1.0475189 | G54: =IFERROR(G98/G119,"") | H54: =IFERROR(H98/H119,"") | I54: =IFERROR(I98/I119,"") | J54: =IFERROR(J98/J118,"") -> 7.8199513 | K54: =IFERROR(K98/K118,"") | L54: =IFERROR(L98/L118,"") | M54: =IFERROR(M98/M118,"") | N54: =IFERROR(N98/N118,"") | O54: =IFERROR(+AVERAGE(D54:N54),"") -> 6.2876734
B55: Fixed Asset Turnover | D55: =IFERROR(D97/D116,"") | E55: =IFERROR(E97/E116,"") -> 1.378426 | F55: =IFERROR(F97/F117,"") -> 0.48096162 | G55: =IFERROR(G97/G117,"") | H55: =IFERROR(H97/H117,"") | I55: =IFERROR(I97/I117,"") | J55: =IFERROR(J97/J116,"") -> 5.7375 | K55: =IFERROR(K97/K116,"") | L55: =IFERROR(L97/L116,"") | M55: =IFERROR(M97/M116,"") | N55: =IFERROR(N97/N116,"") | O55: =IFERROR(+AVERAGE(D55:N55),"") -> 2.5322959
B56: Total Asset Turnover | D56: =IFERROR(D97/D117,"") -> 0.19547029 | E56: =IFERROR(E97/E117,"") -> 0.44047988 | F56: =IFERROR(F97/F118,"") -> 35.842254 | G56: =IFERROR(G97/G118,"") | H56: =IFERROR(H97/H118,"") | I56: =IFERROR(I97/I118,"") | J56: =IFERROR(J97/J117,"") -> 0.2594564 | K56: =IFERROR(K97/K117,"") | L56: =IFERROR(L97/L117,"") | M56: =IFERROR(M97/M117,"") | N56: =IFERROR(N97/N117,"") | O56: =IFERROR(+AVERAGE(D56:N56),"") -> 9.184415
B57: Cash Cycle (days) | D57: =IFERROR(365/D52+365/D53-365/D54,"") -> 147.13852 | E57: =IFERROR(365/E52+365/E53-365/E54,"") -> 232.06451 | F57: =IFERROR(365/F52+365/F53-365/F54,"") | G57: =IFERROR(365/G52+365/G53-365/G54,"") | H57: =IFERROR(365/H52+365/H53-365/H54,"") | I57: =IFERROR(365/I52+365/I53-365/I54,"") | J57: =IFERROR(365/J52+365/J53-365/J54,"") -> 137.38079 | K57: =IFERROR(365/K52+365/K53-365/K54,"") | ... N57: =IFERROR(365/N52+365/N53-365/N54,"") | O57: =IFERROR(+AVERAGE(D57:N57),"") -> 172.1946
B59: Cash Flow | D59: =+D38 -> ANALOG | E59: =+E38 -> TEXAS | F59: =+F38 -> MICROCHIP | G59: =+G38 -> MONOLITHIC | H59: =+H38 -> SKYWORKS | I59: =+I38 -> MACOM | J59: =+J38 -> MTSI | K59: =+K38 -> INTEL | ... O59: =+O38 -> Average
B61: Cash Flow Margin | D61: =IFERROR(D132/D97,"") -> 0.10960837 | E61: =IFERROR(E132/E97,"") -> 0.015088549 | F61: =IFERROR(F132/F97,"") -> 0.011225506 | G61: =IFERROR(G132/G97,"") -> 0 | H61: =IFERROR(H132/H97,"") -> 0 | I61: =IFERROR(I132/I97,"") -> 0 | J61: =IFERROR(J132/J97,"") -> 0.0072621641 | K61: =IFERROR(K132/K97,"") | ... N61: =IFERROR(N132/N97,"") | O61: =IFERROR(+AVERAGE(D61:N61),"") -> 0.020454941
B62: Cash Flow to Net Income | D62: =IFERROR(D132/D96,"") -> 0.42932525 | E62: =IFERROR(E132/E96,"") -> 0.03625192 | F62: =IFERROR(F132/F96,"") -> 0.038298253 | G62: =IFERROR(G132/G96,"") -> 0 | H62: =IFERROR(H132/H96,"") -> 0 | I62: =IFERROR(I132/I96,"") -> 0 | J62: =IFERROR(J132/J96,"") -> -0.24390244 | K62: =IFERROR(K132/K96,"") | ... N62: =IFERROR(N132/N96,"") | O62: =IFERROR(+AVERAGE(D62:N62),"") -> 0.037138997
B63: CFO to Net Income | D63: =+IFERROR(D126/D105,"") -> 5.9793574 | E63: =+IFERROR(E126/E105,"") -> 1.3165243 | F63: =+IFERROR(F126/F105,"") -> 1.5169647 | G63: =+IFERROR(G126/G105,"") -> 0 | H63: =+IFERROR(H126/H105,"") -> 0 | I63: =+IFERROR(I126/I105,"") -> 0 | J63: =+IFERROR(J126/J105,"") -> -1.4694534 | K63: =+IFERROR(K126/K105,"") | ... N63: =+IFERROR(N126/N105,"") | O63: =IFERROR(+AVERAGE(D63:N63),"") -> 1.0490561
B64: Net Capex to CFO | D64: =IFERROR(-D127/D126,"") -> 0.18948735 | E64: =IFERROR(-E127/E126,"") -> 0 | F64: =IFERROR(-F127/F126,"") -> 0.098420161 | G64: =IFERROR(-G127/G126,"") | H64: =IFERROR(-H127/H126,"") | I64: =IFERROR(-I127/I126,"") | J64: =IFERROR(-J127/J126,"") -> 0 | K64: =IFERROR(-K127/K126,"") | ... N64: =IFERROR(-N127/N126,"") | O64: =IFERROR(+AVERAGE(D64:N64),"") -> 0.071976877
B65: CFI to CFO | D65: =IFERROR(-D128/D126,"") -> 0.28680078 | E65: =IFERROR(-E128/E126,"") -> 0.50680595 | F65: =IFERROR(-F128/F126,"") -> 0.1355481 | G65: =IFERROR(-G128/G126,"") | H65: =IFERROR(-H128/H126,"") | I65: =IFERROR(-I128/I126,"") | J65: =IFERROR(-J128/J126,"") -> 0.25601751 | K65: =IFERROR(-K128/K126,"") | ... N65: =IFERROR(-N128/N126,"") | O65: =IFERROR(+AVERAGE(D65:N65),"") -> 0.29629308
B66: Net Financing to CFO | D66: =IFERROR((D129+D130)/D126,"") -> -0.12977703 | E66: =IFERROR((E129+E130)/E126,"") -> 0.37670149 | F66: =IFERROR((F129+F130)/F126,"") -> 0 | G66: =IFERROR((G129+G130)/G126,"") | H66: =IFERROR((H129+H130)/H126,"") | I66: =IFERROR((I129+I130)/I126,"") | J66: =IFERROR((J129+J130)/J126,"") -> -0.23924143 | K66: =IFERROR((K129+K130)/K126,"") | ... N66: =IFERROR((N129+N130)/N126,"") | O66: =IFERROR(+AVERAGE(D66:N66),"") -> 0.0019207576
B67: Debt Borrowing to Debt Repayment | D67: =+IFERROR(-D130/D129,"") | E67: =+IFERROR(-E130/E129,"") -> 0.20134228 | F67: =+IFERROR(-F130/F129,"") | G67: =+IFERROR(-G130/G129,"") | H67: =+IFERROR(-H130/H129,"") | I67: =+IFERROR(-I130/I129,"") | J67: =+IFERROR(-J130/J129,"") -> 1.2532819 | K67: =+IFERROR(-K130/K129,"") | ... N67: =+IFERROR(-N130/N129,"") | O67: =IFERROR(+AVERAGE(D67:N67),"") -> 0.72731207
B68: CFF to CFO | D68: =IFERROR(-D131/D126,"") -> 0.44500973 | E68: =IFERROR(-E131/E126,"") -> 0.45584046 | F68: =IFERROR(-F131/F126,"") -> 0.8348256 | G68: =IFERROR(-G131/G126,"") | H68: =IFERROR(-H131/H126,"") | I68: =IFERROR(-I131/I126,"") | J68: =IFERROR(-J131/J126,"") -> 0.71480671 | K68: =IFERROR(-K131/K126,"") | ... N68: =IFERROR(-N131/N126,"") | O68: =IFERROR(+AVERAGE(D68:N68),"") -> 0.61262062
B69: Payout Ratio | O69: =IFERROR(+AVERAGE(D69:N69),"")
B71: Stock Information | D71: =+D29 -> ANALOG | E71: =+E29 -> TEXAS | F71: =+F29 -> MICROCHIP | G71: =+G29 -> MONOLITHIC | H71: =+H29 -> SKYWORKS | I71: =+I29 -> MACOM | J71: =+J29 -> MTSI | K71: =+K29 -> INTEL | ... O71: =+O29 -> Average
B73: (%) Float | O73: =IFERROR(+AVERAGE(D73:N73),"")
B74: β (Levered) | D74: {=IFERROR(_FV(D91,"Beta"),"")} -> 1.0961 | E74: {=IFERROR(_FV(E91,"Beta"),"")} -> 1.0106 | F74: {=IFERROR(_FV(F91,"Beta"),"")} -> 1.5443 | G74: {=IFERROR(_FV(G91,"Beta"),"")} -> 1.2726 | H74: {=IFERROR(_FV(H91,"Beta"),"")} -> 1.1957 | I74: {=IFERROR(_FV(I91,"Beta"),"")} -> 1.4886 | J74: {=IFERROR(_FV(J91,"Beta"),"")} -> 1.9052 | K74: {=IFERROR(_FV(K91,"Beta"),"")} -> 1.2929 | ... N74: {=IFERROR(_FV(N91,"Beta"),"")} -> 0.5469 | O74: =IFERROR(+AVERAGE(D74:N74),"") -> 1.2970364
B75: β (Unlevered) | D75: =IFERROR(D74/(1+(1-D104/D103)*(D121/D122)),"") -> 0.93159391 | E75: =IFERROR(E74/(1+(1-E104/E103)*(E121/E122)),"") -> 0.59172608 | F75: =IFERROR(F74/(1+(1-F104/F103)*(F121/F122)),"") -> 0.83740183 | G75: =IFERROR(G74/(1+(1-G104/G103)*(G121/G122)),"") | H75: =IFERROR(H74/(1+(1-H104/H103)*(H121/H122)),"") | I75: =IFERROR(I74/(1+(1-I104/I103)*(I121/I122)),"") | J75: =IFERROR(J74/(1+(1-J104/J103)*(J121/J122)),"") -> 1.3955849 | K75: =IFERROR(K74/(1+(1-K104/K103)*(K121/K122)),"") | ... N75: =IFERROR(N74/(1+(1-N104/N103)*(N121/N122)),"") | O75: =IFERROR(+AVERAGE(D75:N75),"") -> 0.93907668
B76: % Held by Insiders | O76: =IFERROR(+AVERAGE(D76:N76),"")
B77: % Held by Institutions | O77: =IFERROR(+AVERAGE(D77:N77),"")
B78: Short % Float | O78: =IFERROR(+AVERAGE(D78:N78),"")
B80: Stock Performance | D80: =+D29 -> ANALOG | E80: =+E29 -> TEXAS | F80: =+F29 -> MICROCHIP | G80: =+G29 -> MONOLITHIC | H80: =+H29 -> SKYWORKS | I80: =+I29 -> MACOM | J80: =+J29 -> MTSI | K80: =+K29 -> INTEL | ... O80: =+O29 -> Average
B82: 1 day | D82: {=IFERROR((D85/_xlfn.STOCKHISTORY(C6,TODAY()-1,TODAY()-1,0,0,1))-1,"Non-trading days")} -> -0.01401325 | E82: {=IFERROR((E85/_xlfn.STOCKHISTORY(C8,TODAY()-1,TODAY()-1,0,0,1))-1,"Non-trading days")} -> -0.012608744 | F82: {=IFERROR((F85/_xlfn.STOCKHISTORY(C9,TODAY()-1,TODAY()-1,0,0,1))-1,"Non-trading days")} -> -0.02460006 | G82: {=IFERROR((G85/_xlfn.STOCKHISTORY(C10,TODAY()-1,TODAY()-1,0,0,1))-1,"Non-trading days")} -> Non-trading days | H82: {=IFERROR((K85/_xlfn.STOCKHISTORY(C11,TODAY()-1,TODAY()-1,0,0,1))-1,"Non-trading days")} -> Non-trading days | I82: {=IFERROR((L85/_xlfn.STOCKHISTORY(C12,TODAY()-1,TODAY()-1,0,0,1))-1,"Non-trading days")} -> Non-trading days | J82: {=IFERROR((M85/_xlfn.STOCKHISTORY(C13,TODAY()-1,TODAY()-1,0,0,1))-1,"Non-trading days")} -> Non-trading days | K82: {=IFERROR((N85/_xlfn.STOCKHISTORY(C14,TODAY()-1,TODAY()-1,0,0,1))-1,"Non-trading days")} -> Non-trading days | L82: {=IFERROR((L85/_xlfn.STOCKHISTORY(C15,TODAY()-1,TODAY()-1,0,0,1))-1,"Non-trading days")} -> Non-trading days | M82: {=IFERROR((M85/_xlfn.STOCKHISTORY(C16,TODAY()-1,TODAY()-1,0,0,1))-1,"Non-trading days")} -> Non-trading days | N82: {=IFERROR((N85/_xlfn.STOCKHISTORY(C17,TODAY()-1,TODAY()-1,0,0,1))-1,"Non-trading days")} -> Non-trading days | O82: =IFERROR(+AVERAGE(D82:N82),"") -> -0.017074018
B83: 1 month | D83: {=IFERROR((D85/_xlfn.STOCKHISTORY(C6,TODAY()-29,TODAY()-29,0,0,1))-1,"Non-trading days")} -> -0.0056286698 | E83: {=IFERROR((E85/_xlfn.STOCKHISTORY(C8,TODAY()-29,TODAY()-29,0,0,1))-1,"Non-trading days")} -> -0.10652185 | F83: {=IFERROR((F85/_xlfn.STOCKHISTORY(C9,TODAY()-29,TODAY()-29,0,0,1))-1,"Non-trading days")} -> -0.022239032 | G83: {=IFERROR((G85/_xlfn.STOCKHISTORY(C10,TODAY()-29,TODAY()-29,0,0,1))-1,"Non-trading days")} -> 0.11312961 | H83: {=IFERROR((K85/_xlfn.STOCKHISTORY(C11,TODAY()-29,TODAY()-29,0,0,1))-1,"Non-trading days")} -> Non-trading days | I83: {=IFERROR((L85/_xlfn.STOCKHISTORY(C12,TODAY()-29,TODAY()-29,0,0,1))-1,"Non-trading days")} -> Non-trading days | J83: {=IFERROR((M85/_xlfn.STOCKHISTORY(C13,TODAY()-29,TODAY()-29,0,0,1))-1,"Non-trading days")} -> Non-trading days | K83: {=IFERROR((N85/_xlfn.STOCKHISTORY(C14,TODAY()-29,TODAY()-29,0,0,1))-1,"Non-trading days")} -> Non-trading days | L83: {=IFERROR((L85/_xlfn.STOCKHISTORY(C15,TODAY()-29,TODAY()-29,0,0,1))-1,"Non-trading days")} -> Non-trading days | M83: {=IFERROR((M85/_xlfn.STOCKHISTORY(C16,TODAY()-29,TODAY()-29,0,0,1))-1,"Non-trading days")} -> Non-trading days | N83: {=IFERROR((N85/_xlfn.STOCKHISTORY(C17,TODAY()-29,TODAY()-29,0,0,1))-1,"Non-trading days")} -> Non-trading days | O83: =IFERROR(AVERAGE(D83:N83),"") -> -0.0053149836
B84: YTD | D84: {=IFERROR((D85/_xlfn.STOCKHISTORY(C6,"2025-01-02","2025-01-02",0,0,1))-1,"Non-trading days")} -> 0.16186421 | E84: {=IFERROR((E85/_xlfn.STOCKHISTORY(C8,"2025-01-02","2025-01-02",0,0,1))-1,"Non-trading days")} -> -0.040759561 | F84: {=IFERROR((F85/_xlfn.STOCKHISTORY(C9,"2025-01-02","2025-01-02",0,0,1))-1,"Non-trading days")} -> 0.13625176 | G84: {=IFERROR((G85/_xlfn.STOCKHISTORY(C10,"2025-01-02","2025-01-02",0,0,1))-1,"Non-trading days")} -> 0.53746087 | H84: {=IFERROR((K85/_xlfn.STOCKHISTORY(C11,"2025-01-02","2025-01-02",0,0,1))-1,"Non-trading days")} -> Non-trading days | I84: {=IFERROR((L85/_xlfn.STOCKHISTORY(C12,"2025-01-02","2025-01-02",0,0,1))-1,"Non-trading days")} -> Non-trading days | J84: {=IFERROR((M85/_xlfn.STOCKHISTORY(C13,"2025-01-02","2025-01-02",0,0,1))-1,"Non-trading days")} -> Non-trading days | K84: {=IFERROR((N85/_xlfn.STOCKHISTORY(C14,"2025-01-02","2025-01-02",0,0,1))-1,"Non-trading days")} -> Non-trading days | L84: {=IFERROR((L85/_xlfn.STOCKHISTORY(C15,"2025-01-02","2025-01-02",0,0,1))-1,"Non-trading days")} -> Non-trading days | M84: {=IFERROR((M85/_xlfn.STOCKHISTORY(C16,"2025-01-02","2025-01-02",0,0,1))-1,"Non-trading days")} -> Non-trading days | N84: {=IFERROR((N85/_xlfn.STOCKHISTORY(C17,"2025-01-02","2025-01-02",0,0,1))-1,"Non-trading days")} -> Non-trading days | O84: =IFERROR(AVERAGE(D84:N84),"") -> 0.19870432
B85: Current Price | D85: {=+IFERROR(_FV(D91,"Price"),"")} -> 245.56 | E85: {=+IFERROR(_FV(E91,"Price"),"")} -> 179.33 | F85: {=+IFERROR(_FV(F91,"Price"),"")} -> 64.63 | G85: {=+IFERROR(_FV(G91,"Price"),"")} -> 913.59 | H85: {=+IFERROR(_FV(H91,"Price"),"")} -> 77.41 | I85: {=+IFERROR(_FV(I91,"Price"),"")} -> 129.095 | J85: {=+IFERROR(_FV(J91,"Price"),"")} -> 73.9669 | K85: {=+IFERROR(_FV(K91,"Price"),"")} | ... N85: {=+IFERROR(_FV(N91,"Price"),"")} | O85: =IFERROR(AVERAGE(D85:N85),"") -> 240.5117
B87: Extra
B89: % Revenues in the US
B91: Income Statement | D91: =+DCF!R4 -> #VALUE! | E91: #VALUE! | F91: #VALUE! | G91: #VALUE! | H91: #VALUE! | I91: #VALUE! | J91: #VALUE! | K91: #VALUE! | L91: #VALUE! | M91: #VALUE! | N91: #VALUE!
B93: =+Inputs!$B$6&" ("&Inputs!O$4&")" -> Revenue (Sales) (2022) | D93: =+_xlfn.XLOOKUP("Revenue (Sales)",Inputs!$B:$B,Inputs!O:O) -> 12014 | E93: 20028 | F93: 6820.9 | G93: 1794.148 | H93: 5485.5 | I93: 675.17 | J93: 4462
B94: =+Inputs!$B$6&" ("&Inputs!P$4&")" -> Revenue (Sales) (2023) | D94: =+_xlfn.XLOOKUP("Revenue (Sales)",Inputs!$B:$B,Inputs!P:P) -> 12305.5 | E94: 17519 | F94: 8438.7 | G94: 1821.072 | H94: 4772.4 | I94: 648.407 | J94: 5920
B95: EBITDA (2023) | D95: =+_xlfn.XLOOKUP("EBITDA",Inputs!$B:$B,Inputs!P:P) -> 4943.4 | E95: 9009 | F95: 4174.5 | G95: 525.017 | H95: 1869.5 | I95: 177.079 | J95: 1648
B96: Net Income (2023) | D96: =+_xlfn.XLOOKUP("Net Income",Inputs!$B:$B,Inputs!P:P) -> 2406.8 | E96: 6510 | F96: 2237.7 | G96: 427.374 | H96: 982.8 | I96: 91.577 | J96: -164
B97: =+Inputs!$B$6&" ("&Inputs!Q$4&")" -> Revenue (Sales) (2024) | D97: =+_xlfn.XLOOKUP("Revenue (Sales)",Inputs!$B:$B,Inputs!Q:Q) -> 9427.2 | E97: 15641 | F97: 7634.4 | G97: 2207.1 | H97: 4178 | I97: 729.578 | J97: 5508
B98: COGS (Cost of Goods Sold) | D98: =+_xlfn.XLOOKUP($B98,Inputs!$B:$B,Inputs!Q:Q) -> 4045.8 | E98: 6547 | F98: 2638.7 | G98: 986.23 | H98: 2457.2 | I98: 328.486 | J98: 3214
B99: Gross Profit | D99: =+_xlfn.XLOOKUP($B99,Inputs!$B:$B,Inputs!Q:Q) -> 5381.4 | E99: =+E97-E98 -> 9094 | F99: 4995.7 | G99: 1220.87 | H99: 1720.8 | I99: 401.092 | J99: 2294
B100: EBITDA | D100: =+_xlfn.XLOOKUP($B100,Inputs!$B:$B,Inputs!Q:Q) -> 2824.9 | E100: 7541 | F100: 3501.9 | G100: 579.691 | H100: 1429.5 | I100: 168.655 | J100: 851
B101: Operating Income (EBIT) | D101: =+_xlfn.XLOOKUP($B101,Inputs!$B:$B,Inputs!Q:Q) -> 720.6 | E101: 5961 | F101: 2562 | G101: 539.358 | H101: 942.8 | I101: 92.45 | J101: -548
B102: Net Interest Expense (Income) | D102: =+_xlfn.XLOOKUP($B102,Inputs!$B:$B,Inputs!Q:Q) -> -78.8 | E102: 508 | F102: 145.9 | H102: 30.7 | I102: -17.85 | J102: 191
B103: Pre-Tax Income (EBT) | D103: =+_xlfn.XLOOKUP($B103,Inputs!$B:$B,Inputs!Q:Q) -> 786.4 | E103: 5453 | F103: 2365.9 | G103: 572.912 | H103: 636.4 | I103: 91.526 | J103: -759
B104: Tax Expense (Benefits) | D104: =+_xlfn.XLOOKUP($B104,Inputs!$B:$B,Inputs!Q:Q) -> 142.1 | E104: 654 | F104: 459 | G104: -1213.788 | H104: 40.4 | I104: 14.667 | J104: 175
B105: Net Income | D105: =+_xlfn.XLOOKUP($B105,Inputs!$B:$B,Inputs!Q:Q) -> 644.3 | E105: 4799 | F105: 1906.9 | G105: 1786.7 | H105: 596 | I105: 76.859 | J105: -933
B106: EPS basic | D106: =+_xlfn.XLOOKUP($B106,Inputs!$B:$B,Inputs!Q:Q) -> 3.3 | F106: 3.52 | G106: 36.76 | H106: 3.72 | I106: 1.07 | J106: -1.08
B107: R&D (Research & Development) | D107: =+_xlfn.XLOOKUP($B107,Inputs!$B:$B,Inputs!Q:Q) -> 1487.9 | E107: 1959 | F107: 1096.9 | G107: 324.748 | H107: 631.7 | I107: 182.158 | J107: 1896
B109: Balance Sheet
B111: Cash & Cash Equivalents | D111: =+_xlfn.XLOOKUP($B111,Inputs!$B:$B,Inputs!Q:Q) -> 1991.3 | E111: 3200 | F111: 319.7 | J111: 951
B112: Accounts Receivable | D112: =+_xlfn.XLOOKUP($B112,Inputs!$B:$B,Inputs!Q:Q) -> 1336.3 | E112: 1719 | F112: 1133.6 | J112: 1122
B113: Beginning Inventory | D113: =+_xlfn.XLOOKUP("Inventory",Inputs!$B:$B,Inputs!P:P) -> 1642.2 | E113: 3999 | J113: 1068
B114: Ending Inventory | D114: =+_xlfn.XLOOKUP("Inventory",Inputs!$B:$B,Inputs!Q:Q) -> 1447.7 | E114: 4527 | J114: 864
B115: Current Assets | D115: =+_xlfn.XLOOKUP($B115,Inputs!$B:$B,Inputs!Q:Q) -> 5484.7 | E115: 15026 | F115: 3103 | J115: 3063
B116: Net PP&E (Property, Plant and Equipment) | D116: =+_xlfn.XLOOKUP($B116,Inputs!$B:$B,Inputs!Q:Q) -> 0 | E116: 11347 | F116: 1350.9 | J116: 960
B117: Total Assets | D117: =+_xlfn.XLOOKUP($B117,Inputs!$B:$B,Inputs!Q:Q) -> 48228.3 | E117: 35509 | F117: 15873.2 | J117: 21229
B118: Accounts Payable | D118: =+_xlfn.XLOOKUP($B118,Inputs!$B:$B,Inputs!Q:Q) -> 487.5 | E118: 820 | F118: 213 | J118: 411
B119: Current Liabilities | D119: =+_xlfn.XLOOKUP($B119,Inputs!$B:$B,Inputs!Q:Q) -> 2988.3 | E119: 3643 | F119: 2519 | J119: 1814
B120: Long-term debt | D120: =+_xlfn.XLOOKUP($B120,Inputs!$B:$B,Inputs!Q:Q) -> 6634.3 | E120: 12846 | F120: 5129.1 | J120: 4059
B121: Total Debt | D121: =+_xlfn.XLOOKUP($B121,Inputs!$B:$B,Inputs!Q:Q,,,-1) -> 7581.6 | E121: 13596 | F121: 6973.04 | J121: 4401
B122: Shareholder's Equity | D122: =+_xlfn.XLOOKUP($B122,Inputs!$B:$B,Inputs!Q:Q) -> 35176.3 | E122: 16903 | F122: 6657.8 | J122: 14831
B124: Cash Flow Statement
B126: Operating Cash Flow | D126: =+_xlfn.XLOOKUP($B126,Inputs!$B:$B,Inputs!Q:Q) -> 3852.5 | E126: 6318 | F126: 2892.7 | J126: 1371
B127: Net Capex | D127: =+_xlfn.XLOOKUP($B127,Inputs!$B:$B,Inputs!Q:Q) -> -730 | F127: =0.4-285.1 -> -284.7
B128: Investing Cash Flow | D128: =+_xlfn.XLOOKUP($B128,Inputs!$B:$B,Inputs!Q:Q) -> -1104.9 | E128: -3202 | F128: -392.1 | J128: -351
...

Sheet ESG
B2: Environmental, Social and Governance Analysis
B4: Author: | C4: Cristina Lin | E4: Highlights
G5: Analog is in a industry that faces some challenges to reduce its emissions and consumption. However, there is notable commitment of Analog Devices and significant improvement on emissions and water and energy cinsumption
B6: Overview | D6: . | E6: Environmental commitment
B7: Last Update | D7: . | G7: Analog Devices has a good interaction with their employees and has organized many activities and projects within the local community.
B8: Latest year with data | C8: 2024 | E8: Community involvement
B9: GICS Sector | C9: Semiconductor & Semiconductor components
B10: GICS Industry Group | C10: Information technology
B11: Final Review | C11: Good
B13: ESG Scores
B14: LSEG ESG Score | C14: 70
B15: E-Score | C15: 61
B16: S-Score | C16: 71 | E16: GHG Scope 1 and 2 Emissions: | N16: Water, Waste, Energy Management:
B17: G-Score | C17: 80
B18: S&P Global ESG Score | C18: 50
B19: Environmental | C19: 54
B20: Social | C20: 47
B21: Governance & Economic | C21: 47
B22: Sustainalytics | C22: 16.7
B23: ISS ESG Corporate Rating | C23: C+
B24: SDG Impact Rating | C24: 2.5
B25: Governance Quality Score | C25: 9
B26: MSCI ESG Ratings | C26: A
B29: Industry ESG Overview:
B30: While the IT and Semiconductor Components sectors face significant ESG challenges—ranging from high energy consumption and resource scarcity to labor practices and supply chain transparency—the industry is making notable progress in addressing these issues. Companies are increasingly adopting renewable energy, promoting diversity, improving supply chain traceability, and enhancing community engagement efforts. As ESG factors become more integral to the sector’s strategy, companies are thriving to achieve better sustainability performance and align with global ethical standards.
E33: ENVIRONMENTAL
G35: Overview | H35: Targets | K35: Improvements | O35: Comments
E36: GHG (or CO2) Scope 1 Emissions | H36: N/A | K36: Emissions have decreased 20% in scope 1, 6% in scope 2 and 12% in scope 3, in 2023 vs. 2022 | O36: N/A
E38: Water Consumption | H38: N/A | K38: Decreased significantly in 2023 and 2024. | O38: water withdrawn generally decreased.
E40: Energy Consumption | H40: N/a | K40: Renewable electricity from the purchase of unbundled Environmental Attribute Certificates increased 186% | O40: Natural gas heating consumption increased 3%, total electricity used increased 4%, non-renewable energy decreased 5.5%.
E42: Waste Management | H42: N/A | K42: N/A | O42: Total waste has increased 10%
E44: Other | H44: N/A | K44: N/a | O44: N/A
E46: SOCIAL
B48: Important Sources: | G48: Overview | H48: Targets | K48: Improvements | O48: Comments
B49: Annual Report | C49: https://investor.analog.com/static-files/cc2bbf08-9ebc-490b-8be3-e396d9ef5934 | E49: Employee Turnover % | H49: N/A | K49: N/A | O49: The company only discloses new hires percentage.
B50: Sustainability Report | C50: https://www.analog.com/media/en/company-csr/2023-esg-report.pdf | D50: .
B51: Proxy Statement | C51: https://investor.analog.com/static-files/8d9dcc9b-f9e5-492e-8a73-0b5ffc6a6c23 | D51: . | E51: Salaries & Compensation | H51: N/A | K51: In July 2023, implemented a new harmonized Global Recognition Program that resulted in more than 10,000 recorded recognition moments globally for the second half of 2023. Most recently, it has maintained a <1% pay equity difference for females and males globally. | O51: A portion of employees at professional levels are eligible for stock awards and Corporate Bonus Plans and Sales Incentive Plan link employees’ compensation to ADI’s revenue and operational performance goals.
E53: Reputation | H53: N/A | K53: N/A | O53: The company had some lawsuits related to semiconductor patent infringement with AMD, in 2022, and with Analog Technologies in 2024. (https://law.justia.com/cases/federal/appellate-courts/ca1/23-1822/23-1822-2024-06-18.html)
E55: Discrimination Events | H55: N/A | K55: N/A | O55: Analog Devices Inc. has settled with a former sales specialist who said a manager discriminated against her and the company retaliated against her for reporting it, in 2023.
E57: Work Safety | H57: N/A | K57: N/A | O57: Injury and illness recordable rate decreased 0.1 and lost workday incident rate decreased 0.04.
E59: Damage to consumer health | H59: N/A | K59: N/A | O59: N/A
E61: Pension Plan | H61: Retain executivetalentby providing financial protection and security | K61: N/A | O61: The company has broad-based benefits for all employees, including medical, dental, and vision insurance, life and disability insurance, and retirement plans. They maintain a Deferred Compensation Plan (DCP), under which executive officers and directors, along with employees, are eligible to defer receipt of some or all of their cash compensation. This plan offers many of the same investment options as 401(k) plan.
E63: Supply chain | H63: N/A | K63: adopted the RBA Code of Conduct and use it in conjunction with our Code of Corporate Social Responsibility. We've established standards for our suppliers to ensure that ethical and legal commitments are applied to their entire supply chain. | O63: collaborate with supply chain-related organizations, such as the Responsible Business Alliance, including its Responsible Minerals Initiative and Responsible Labor Initiative, and the Semiconductor Industry Association. Collaborates with supply chain-related organizations, such as the Responsible Business Alliance, including its Responsible Minerals Initiative and Responsible Labor Initiative, and the Semiconductor Industry Association.
E65: Community involvement | H65: N/A | K65: N/A | O65: Employee Networks foster community, accelerate professional development, and impact organizational policy. It currently has six networks organized around a dimension of diversity with dynamic activities and projects.
E67: Public Sector | H67: N/A | K67: N/A | O67: On January 16, 2025, the U.S. Department of Commerce and Analog Devices, Inc. (“ADI”) signed a non-binding preliminary memorandum of terms (PMT) to provide up to $105 million in proposed direct funding under the CHIPS and Science Act.
E69: Litigation | H69: N/A | K69: N/A | O69: Had a litigation related to 1 case of discrimitation in workplace
E71: GOVERNANCE
G73: Overview | H73: Targets | K73: Improvements | O73: Comments
E74: Diversity (Gender, Age, Industry, Region) | H74: achieve 29% in women people managers, 26% in women engeneers, 9% in Black, Hispanic, and Latinx employees (U.S. only) | K74: global female manager population has increased to 25% and global female engineering population has increased to 22%. | O74: Global leadership positions are ≈80% held by man. 36% of directors are female. Regarding ethnicity, the company has a great diversity (33% asian, 52% white, 2% black, 5% hispanic/latinx)
E76: % Independence | H76: N/A | K76: N/A | O76: 9of 11 directors are independent.
E78: Average time as independent directors | H78: N/A | K78: N/A | O78: Average time of tenure is 4.9 years
E80: Departures of C-level executives | H80: N/A | K80: N/A | O80: In May 2023, Prashanth Mahendra-Rajah announced his decision to step down as Executive Vice President and CFO after six years in the role. In January 2024, ADI appointed Richard C. Puccio, Jr. as the new Executive Vice President and CFO, effective February 5, 2024.
E82: CEO/Chairman duality | H82: N/A | K82: N/A | O82: The role both of CEO and Chairman are held by Vincent Roche.
E84: Transparency when reporting | H84: N/A | K84: N/A | O84: N/A
E86: Time taken to report | H86: N/A | K86: N/A | O86: The sustainability report of 2023 was released in May 2024.
E88: CEO or Chairman in other boards? | H88: N/A | K88: N/A | O88: Mr. Roche also serves on the Board of Directors of the Semiconductor Industry Association and the MIT Presidential CEO Advisory Board, and is a member of the Massachusetts High Tech Leadership Council.
E90: Audit / Consulting | H90: Plan to have RBA audits in facilities in Ireland, Philippines, and U.S. (Wilmington, Massachusetts, facilities) in 2024 | K90: The company has adopted and agreed to comply with the RBA Code of Conduct, and ensure our suppliers comply with the RBA Code as well | O90: ADI’s most recent RBA VAP audit score is compared with the industry standard, and ADI remains above the industry standard. ADI’s most recent RBA VAP audit average score is 190 out of a possible 200.
E92: ESG-compensation related | H92: N/A | K92: N/A | O92: While the Compensation and Talent Committee continues to evaluate whether to link compensation elements to ESG metrics, it determined to make no changes during fiscal year 2023 given the intense company focus on ESG performance as part of its short- and long-term strategy. The financial metrics underlying our incentive compensation and PRSUs not only drive our Leadership Team to achieve those specified financial metrics, but also ESG performance given the strong alignment between the two.
E94: Management compensation schemes | H94: N/A | K94: N/A | O94: The remuneration consists in base salary, bonus, stock awards, option awards, non-equity incentive plan compensation, where stock awards weight the most (≈80% of total reward).

Sheet ESG Inputs
B2: ESG Inputs
A4: x | B4: Total GHG Scope 1 Emissions | G4: 2014 | H4: =+G4+1 -> 2015 | I4: =+H4+1 -> 2016 | J4: =+I4+1 -> 2017 | K4: =+J4+1 -> 2018 | L4: =+K4+1 -> 2019 | M4: =+L4+1 -> 2020 | N4: =+M4+1 -> 2021 | O4: =+N4+1 -> 2022 | ... Q4: =+P4+1 -> 2024 | R4: ="CAGR "&$G$4&" - "&$Q$4 -> CAGR 2014 - 2024
B6: =+Peers!B6 -> ANALOG DEVICES, INC. | G6: — | H6: 133 | I6: 135 | J6: 50 | K6: 54 | L6: — | M6: — | N6: — | O6: 176 | P6: 138 | Q6: — | R6: =IFERROR((Q6/G6)^(1/COUNT($G$4:$Q$4))-1,"")
B7: =+Peers!B8 -> TEXAS INSTRUMENTS INCORPORATED | G7: 1056 | H7: 1086 | I7: 1077 | J7: 1162 | K7: 1130 | L7: 970 | M7: 940 | N7: 1040 | O7: 1112 | P7: 1120 | Q7: — | R7: =IFERROR((Q7/G7)^(1/COUNT($G$4:$Q$4))-1,"")
B8: =+Peers!B9 -> MICROCHIP TECHNOLOGY INCORPORATED | G8: 1041 | H8: 1053 | I8: 976 | J8: 1490 | K8: 940 | L8: 900 | M8: 1040 | N8: 1150 | O8: 1180 | P8: 845 | Q8: — | R8: =IFERROR((Q8/G8)^(1/COUNT($G$4:$Q$4))-1,"")
B9: =+Peers!B10 -> MONOLITHIC POWER SYSTEMS, INC. | G9: — | H9: 1415 | I9: 1724 | J9: 2844 | K9: 2946 | L9: 3195 | M9: 3048 | N9: 3340 | O9: 3478 | P9: 2699 | Q9: — | R9: =IFERROR((Q9/G9)^(1/COUNT($G$4:$Q$4))-1,"")
B10: =+Peers!B11 -> SKYWORKS SOLUTIONS, INC. | G10: — | H10: — | I10: — | J10: — | K10: — | L10: — | M10: — | N10: — | O10: — | P10: — | Q10: — | R10: =IFERROR((Q10/G10)^(1/COUNT($G$4:$Q$4))-1,"")
B11: =+Peers!B12 -> MACOM TECHNOLOGY SOLUTIONS HOLDINGS, INC. | G11: — | H11: — | I11: — | J11: 0 | K11: 0 | L11: 0 | M11: 0 | N11: 2 | O11: 4 | P11: 3 | Q11: — | R11: =IFERROR((Q11/G11)^(1/COUNT($G$4:$Q$4))-1,"")
B12: =+Peers!B13 -> MARVELL TECHNOLOGY, INC. | G12: 133 | H12: 170 | I12: 193 | J12: 451 | K12: 488 | L12: 529 | M12: 426 | N12: 348 | O12: 408 | P12: 424 | Q12: 440 | R12: =IFERROR((Q12/G12)^(1/COUNT($G$4:$Q$4))-1,"") -> 0.11490139
B13: =+Peers!B14 -> INTEL CORPORATION | G13: 11 | H13: 12 | I13: 15 | J13: 16 | K13: 22 | L13: 27 | M13: 7 | N13: 9 | O13: 8 | P13: 12 | Q13: — | R13: =IFERROR((Q13/G13)^(1/COUNT($G$4:$Q$4))-1,"")
B14: =+Peers!B15 -> MICRON TECHNOLOGY, INC. | G14: — | H14: — | I14: — | J14: — | K14: — | L14: — | M14: — | N14: — | O14: — | P14: — | Q14: — | R14: =IFERROR((Q14/G14)^(1/COUNT($G$4:$Q$4))-1,"")
B15: =+Peers!B16 -> FIRST SOLAR, INC. | G15: — | H15: — | I15: — | J15: — | K15: — | L15: — | M15: — | N15: — | O15: 38 | P15: 30 | Q15: — | R15: =IFERROR((Q15/G15)^(1/COUNT($G$4:$Q$4))-1,"")
B16: =+Peers!B17 -> ALTRI, S.G.P.S., S.A. | G16: — | H16: — | I16: — | J16: — | K16: — | L16: 11 | M16: 10 | N16: 9 | O16: 20 | P16: 21 | Q16: — | R16: =IFERROR((Q16/G16)^(1/COUNT($G$4:$Q$4))-1,"")
A18: x | B18: Total GHG Scope 2 (Location-Based) Emissions | G18: 2014 | H18: =+G18+1 -> 2015 | I18: =+H18+1 -> 2016 | J18: =+I18+1 -> 2017 | K18: =+J18+1 -> 2018 | L18: =+K18+1 -> 2019 | M18: =+L18+1 -> 2020 | N18: =+M18+1 -> 2021 | O18: =+N18+1 -> 2022 | ... Q18: =+P18+1 -> 2024 | R18: ="CAGR "&$G$4&" - "&$Q$4 -> CAGR 2014 - 2024
B20: =+$B$6 -> ANALOG DEVICES, INC. | G20: — | H20: 86 | I20: 83 | J20: 94 | K20: 94 | L20: — | M20: — | N20: — | O20: 149 | P20: 140 | Q20: — | R20: =IFERROR((Q20/G20)^(1/COUNT($G$4:$Q$4))-1,"")
B21: =+$B$7 -> TEXAS INSTRUMENTS INCORPORATED | G21: — | H21: 1385 | I21: 0 | J21: 22 | K21: 1120 | L21: 1100 | M21: 1010 | N21: 1040 | O21: 1057 | P21: 1100 | Q21: — | R21: =IFERROR((Q21/G21)^(1/COUNT($G$4:$Q$4))-1,"")
B22: =+$B$8 -> MICROCHIP TECHNOLOGY INCORPORATED | G22: — | H22: 946 | I22: 647 | J22: 971 | K22: 660 | L22: 660 | M22: 280 | N22: 350 | O22: 350 | P22: 48 | Q22: — | R22: =IFERROR((Q22/G22)^(1/COUNT($G$4:$Q$4))-1,"")
B23: =+$B$9 -> MONOLITHIC POWER SYSTEMS, INC. | G23: — | H23: 1755 | I23: 2060 | J23: 2997 | K23: 3178 | L23: 3503 | M23: 3622 | N23: 3807 | O23: 4132 | P23: 4138 | Q23: — | R23: =IFERROR((Q23/G23)^(1/COUNT($G$4:$Q$4))-1,"")
B24: =+$B$10 -> SKYWORKS SOLUTIONS, INC. | G24: — | H24: — | I24: — | J24: — | K24: — | L24: — | M24: — | N24: — | O24: — | P24: — | Q24: — | R24: =IFERROR((Q24/G24)^(1/COUNT($G$4:$Q$4))-1,"")
B25: =+$B$11 -> MACOM TECHNOLOGY SOLUTIONS HOLDINGS, INC. | G25: — | H25: — | I25: — | J25: — | K25: — | L25: — | M25: — | N25: 17 | O25: 26 | P25: 24 | Q25: — | R25: =IFERROR((Q25/G25)^(1/COUNT($G$4:$Q$4))-1,"")
B26: =+$B$12 -> MARVELL TECHNOLOGY, INC. | G26: — | H26: — | I26: — | J26: — | K26: — | L26: — | M26: — | N26: — | O26: — | P26: — | Q26: 274 | R26: =IFERROR((Q26/G26)^(1/COUNT($G$4:$Q$4))-1,"")
B27: =+$B$13 -> INTEL CORPORATION | G27: — | H27: 300 | I27: 391 | J27: 309 | K27: 334 | L27: 442 | M27: 345 | N27: 552 | O27: 564 | P27: 777 | Q27: — | R27: =IFERROR((Q27/G27)^(1/COUNT($G$4:$Q$4))-1,"")
B28: =+$B$14 -> MICRON TECHNOLOGY, INC. | G28: — | H28: — | I28: — | J28: — | K28: — | L28: — | M28: — | N28: — | O28: — | P28: — | Q28: — | R28: =IFERROR((Q28/G28)^(1/COUNT($G$4:$Q$4))-1,"")
B29: =+$B$15 -> FIRST SOLAR, INC. | G29: — | H29: — | I29: — | J29: — | K29: — | L29: — | M29: — | N29: — | O29: 120 | P29: 92 | Q29: — | R29: =IFERROR((Q29/G29)^(1/COUNT($G$4:$Q$4))-1,"")
B30: =+$B$16 -> ALTRI, S.G.P.S., S.A. | G30: — | H30: — | I30: — | J30: — | K30: — | L30: — | M30: — | N30: — | O30: — | P30: — | Q30: — | R30: =IFERROR((Q30/G30)^(1/COUNT($G$4:$Q$4))-1,"")
A32: x | B32: Total Energy Usage | G32: 2014 | H32: =+G32+1 -> 2015 | I32: =+H32+1 -> 2016 | J32: =+I32+1 -> 2017 | K32: =+J32+1 -> 2018 | L32: =+K32+1 -> 2019 | M32: =+L32+1 -> 2020 | N32: =+M32+1 -> 2021 | O32: =+N32+1 -> 2022 | ... Q32: =+P32+1 -> 2024 | R32: ="CAGR "&$G$4&" - "&$Q$4 -> CAGR 2014 - 2024
B34: =+$B$6 -> ANALOG DEVICES, INC. | G34: — | H34: — | I34: — | J34: — | K34: — | L34: — | M34: — | N34: — | O34: 1109 | P34: 833 | Q34: — | R34: =IFERROR((Q34/G34)^(1/COUNT($G$4:$Q$4))-1,"")
B35: =+$B$7 -> TEXAS INSTRUMENTS INCORPORATED | G35: — | H35: 25704 | I35: 25439 | J35: 25098 | K35: 2512 | L35: 3047 | M35: 2914 | N35: 3662 | O35: 5403 | P35: 4071 | Q35: — | R35: =IFERROR((Q35/G35)^(1/COUNT($G$4:$Q$4))-1,"")
B36: =+$B$8 -> MICROCHIP TECHNOLOGY INCORPORATED | G36: — | H36: 7465 | I36: 7083 | J36: 10289 | K36: 11541 | L36: 11028 | M36: 13020 | N36: 10791 | O36: 9971 | P36: 9860 | Q36: — | R36: =IFERROR((Q36/G36)^(1/COUNT($G$4:$Q$4))-1,"")
B37: =+$B$9 -> MONOLITHIC POWER SYSTEMS, INC. | G37: — | H37: — | I37: — | J37: — | K37: 10343 | L37: 11185 | M37: 12196 | N37: 12811 | O37: 14590 | P37: 14319 | Q37: — | R37: =IFERROR((Q37/G37)^(1/COUNT($G$4:$Q$4))-1,"")
B38: =+$B$10 -> SKYWORKS SOLUTIONS, INC. | G38: — | H38: — | I38: — | J38: — | K38: — | L38: — | M38: — | N38: — | O38: — | P38: — | Q38: — | R38: =IFERROR((Q38/G38)^(1/COUNT($G$4:$Q$4))-1,"")
B39: =+$B$11 -> MACOM TECHNOLOGY SOLUTIONS HOLDINGS, INC. | G39: — | H39: — | I39: — | J39: — | K39: — | L39: — | M39: — | N39: — | O39: — | P39: — | Q39: — | R39: =IFERROR((Q39/G39)^(1/COUNT($G$4:$Q$4))-1,"")
B40: =+$B$12 -> MARVELL TECHNOLOGY, INC. | G40: — | H40: — | I40: — | J40: — | K40: — | L40: — | M40: — | N40: 2088 | O40: 2088 | P40: 2339 | Q40: 3188 | R40: =IFERROR((Q40/G40)^(1/COUNT($G$4:$Q$4))-1,"")
B41: =+$B$13 -> INTEL CORPORATION | G41: — | H41: — | I41: — | J41: — | K41: — | L41: — | M41: — | N41: — | O41: — | P41: 2158 | Q41: — | R41: =IFERROR((Q41/G41)^(1/COUNT($G$4:$Q$4))-1,"")
B42: =+$B$14 -> MICRON TECHNOLOGY, INC. | G42: — | H42: — | I42: — | J42: — | K42: — | L42: — | M42: — | N42: — | O42: — | P42: — | Q42: — | R42: =IFERROR((Q42/G42)^(1/COUNT($G$4:$Q$4))-1,"")
B43: =+$B$15 -> FIRST SOLAR, INC. | G43: — | H43: — | I43: — | J43: — | K43: — | L43: — | M43: — | N43: — | O43: — | P43: — | Q43: — | R43: =IFERROR((Q43/G43)^(1/COUNT($G$4:$Q$4))-1,"")
B44: =+$B$16 -> ALTRI, S.G.P.S., S.A. | G44: — | H44: — | I44: — | J44: — | K44: — | L44: 27 | M44: 11 | N44: 9 | O44: 72 | P44: 55 | Q44: — | R44: =IFERROR((Q44/G44)^(1/COUNT($G$4:$Q$4))-1,"")
A46: x | B46: Total Water Consumption | G46: 2014 | H46: =+G46+1 -> 2015 | I46: =+H46+1 -> 2016 | J46: =+I46+1 -> 2017 | K46: =+J46+1 -> 2018 | L46: =+K46+1 -> 2019 | M46: =+L46+1 -> 2020 | N46: =+M46+1 -> 2021 | O46: =+N46+1 -> 2022 | ... Q46: =+P46+1 -> 2024 | R46: ="CAGR "&$G$4&" - "&$Q$4 -> CAGR 2014 - 2024
B48: =+$B$6 -> ANALOG DEVICES, INC. | G48: — | H48: — | I48: — | J48: — | K48: — | L48: — | M48: — | N48: — | O48: 1109 | P48: 833 | Q48: — | R48: =IFERROR((Q48/G48)^(1/COUNT($G$4:$Q$4))-1,"")
B49: =+$B$7 -> TEXAS INSTRUMENTS INCORPORATED | G49: — | H49: 25704 | I49: 25439 | J49: 25098 | K49: 2512 | L49: 3047 | M49: 2914 | N49: 3662 | O49: 5403 | P49: 4071 | Q49: — | R49: =IFERROR((Q49/G49)^(1/COUNT($G$4:$Q$4))-1,"")
B50: =+$B$8 -> MICROCHIP TECHNOLOGY INCORPORATED | G50: — | H50: 7465 | I50: 7083 | J50: 10289 | K50: 11541 | L50: 11028 | M50: 13020 | N50: 10791 | O50: 9971 | P50: 9860 | Q50: — | R50: =IFERROR((Q50/G50)^(1/COUNT($G$4:$Q$4))-1,"")
B51: =+$B$9 -> MONOLITHIC POWER SYSTEMS, INC. | G51: — | H51: — | I51: — | J51: — | K51: 10343 | L51: 11185 | M51: 12196 | N51: 12811 | O51: 14590 | P51: 14319 | Q51: — | R51: =IFERROR((Q51/G51)^(1/COUNT($G$4:$Q$4))-1,"")
B52: =+$B$10 -> SKYWORKS SOLUTIONS, INC. | G52: — | H52: — | I52: — | J52: — | K52: — | L52: — | M52: — | N52: — | O52: — | P52: — | Q52: — | R52: =IFERROR((Q52/G52)^(1/COUNT($G$4:$Q$4))-1,"")
B53: =+$B$11 -> MACOM TECHNOLOGY SOLUTIONS HOLDINGS, INC. | G53: — | H53: — | I53: — | J53: — | K53: — | L53: — | M53: — | N53: — | O53: — | P53: — | Q53: — | R53: =IFERROR((Q53/G53)^(1/COUNT($G$4:$Q$4))-1,"")
B54: =+$B$12 -> MARVELL TECHNOLOGY, INC. | G54: — | H54: — | I54: — | J54: — | K54: — | L54: — | M54: — | N54: 2088 | O54: 2088 | P54: 2339 | Q54: 3188 | R54: =IFERROR((Q54/G54)^(1/COUNT($G$4:$Q$4))-1,"")
B55: =+$B$13 -> INTEL CORPORATION | G55: — | H55: — | I55: — | J55: — | K55: — | L55: — | M55: — | N55: — | O55: — | P55: 2158 | Q55: — | R55: =IFERROR((Q55/G55)^(1/COUNT($G$4:$Q$4))-1,"")
B56: =+$B$14 -> MICRON TECHNOLOGY, INC. | G56: — | H56: — | I56: — | J56: — | K56: — | L56: — | M56: — | N56: — | O56: — | P56: — | Q56: — | R56: =IFERROR((Q56/G56)^(1/COUNT($G$4:$Q$4))-1,"")
B57: =+$B$15 -> FIRST SOLAR, INC. | G57: — | H57: — | I57: — | J57: — | K57: — | L57: — | M57: — | N57: — | O57: — | P57: — | Q57: — | R57: =IFERROR((Q57/G57)^(1/COUNT($G$4:$Q$4))-1,"")
B58: =+$B$16 -> ALTRI, S.G.P.S., S.A. | G58: — | H58: — | I58: — | J58: — | K58: — | L58: 27 | M58: 11 | N58: 9 | O58: 72 | P58: 55 | Q58: — | R58: =IFERROR((Q58/G58)^(1/COUNT($G$4:$Q$4))-1,"")
A60: x | B60: Total Waste Production | G60: 2014 | H60: =+G60+1 -> 2015 | I60: =+H60+1 -> 2016 | J60: =+I60+1 -> 2017 | K60: =+J60+1 -> 2018 | L60: =+K60+1 -> 2019 | M60: =+L60+1 -> 2020 | N60: =+M60+1 -> 2021 | O60: =+N60+1 -> 2022 | ... Q60: =+P60+1 -> 2024 | R60: ="CAGR "&$G$4&" - "&$Q$4 -> CAGR 2014 - 2024
B62: =+$B$6 -> ANALOG DEVICES, INC. | G62: — | H62: 3 | I62: 3 | J62: 3 | K62: 3 | L62: 5 | M62: 4 | N62: 5 | O62: 5 | P62: 6 | Q62: — | R62: =IFERROR((Q62/G62)^(1/COUNT($G$4:$Q$4))-1,"")
B63: =+$B$7 -> TEXAS INSTRUMENTS INCORPORATED | G63: 33 | H63: 33 | I63: 32 | J63: 37 | K63: 37 | L63: 37 | M63: 42 | N63: 46 | O63: 51 | P63: 51 | Q63: — | R63: =IFERROR((Q63/G63)^(1/COUNT($G$4:$Q$4))-1,"")
B64: =+$B$8 -> MICROCHIP TECHNOLOGY INCORPORATED | G64: 144 | H64: 129 | I64: 160 | J64: 183 | K64: 186 | L64: 351 | M64: 376 | N64: 312 | O64: 282 | P64: 265 | Q64: — | R64: =IFERROR((Q64/G64)^(1/COUNT($G$4:$Q$4))-1,"")
B65: =+$B$9 -> MONOLITHIC POWER SYSTEMS, INC. | G65: — | H65: 95 | I65: 131 | J65: 192 | K65: 163 | L65: 183 | M65: 198 | N65: 223 | O65: 234 | P65: 196 | Q65: — | R65: =IFERROR((Q65/G65)^(1/COUNT($G$4:$Q$4))-1,"")
B66: =+$B$10 -> SKYWORKS SOLUTIONS, INC. | G66: — | H66: — | I66: — | J66: — | K66: — | L66: — | M66: — | N66: — | O66: — | P66: — | Q66: — | R66: =IFERROR((Q66/G66)^(1/COUNT($G$4:$Q$4))-1,"")
B67: =+$B$11 -> MACOM TECHNOLOGY SOLUTIONS HOLDINGS, INC. | G67: — | H67: — | I67: — | J67: — | K67: — | L67: — | M67: — | N67: 0 | O67: 1 | P67: 1 | Q67: — | R67: =IFERROR((Q67/G67)^(1/COUNT($G$4:$Q$4))-1,"")
B68: =+$B$12 -> MARVELL TECHNOLOGY, INC. | G68: — | H68: — | I68: — | J68: — | K68: — | L68: — | M68: — | N68: 4 | O68: 4 | P68: 7 | Q68: 7 | R68: =IFERROR((Q68/G68)^(1/COUNT($G$4:$Q$4))-1,"")
B69: =+$B$13 -> INTEL CORPORATION | G69: 22 | H69: 22 | I69: 28 | J69: 22 | K69: 23 | L69: 42 | M69: 45 | N69: 53 | O69: 48 | P69: 52 | Q69: — | R69: =IFERROR((Q69/G69)^(1/COUNT($G$4:$Q$4))-1,"")
B70: =+$B$14 -> MICRON TECHNOLOGY, INC. | G70: — | H70: — | I70: — | J70: — | K70: — | L70: — | M70: — | N70: — | O70: — | P70: — | Q70: — | R70: =IFERROR((Q70/G70)^(1/COUNT($G$4:$Q$4))-1,"")
B71: =+$B$15 -> FIRST SOLAR, INC. | G71: — | H71: — | I71: — | J71: — | K71: — | L71: 3 | M71: — | N71: — | O71: — | P71: — | Q71: — | R71: =IFERROR((Q71/G71)^(1/COUNT($G$4:$Q$4))-1,"")
B72: =+$B$16 -> ALTRI, S.G.P.S., S.A. | G72: — | H72: — | I72: — | J72: — | K72: — | L72: — | M72: — | N72: — | O72: — | P72: — | Q72: — | R72: =IFERROR((Q72/G72)^(1/COUNT($G$4:$Q$4))-1,"")
A74: x | B74: GHG Scope 1 and 2 Emissions | G74: 2014 | H74: =+G74+1 -> 2015 | I74: =+H74+1 -> 2016 | J74: =+I74+1 -> 2017 | K74: =+J74+1 -> 2018 | L74: =+K74+1 -> 2019 | M74: =+L74+1 -> 2020 | N74: =+M74+1 -> 2021 | O74: =+N74+1 -> 2022 | ... Q74: =+P74+1 -> 2024 | R74: ="CAGR "&$G$4&" - "&$Q$4 -> CAGR 2014 - 2024
B76: =+$B$6 -> ANALOG DEVICES, INC. | G76: =+G6+G20 -> #VALUE! | H76: =+H6+H20 -> 219 | I76: =+I6+I20 -> 218 | J76: =+J6+J20 -> 144 | K76: =+K6+K20 -> 148 | L76: =+L6+L20 -> #VALUE! | M76: =+M6+M20 -> #VALUE! | N76: =+N6+N20 -> #VALUE! | ... Q76: =+Q6+Q20 -> #VALUE! | R76: =IFERROR((Q76/G76)^(1/COUNT($G$4:$Q$4))-1,"")
B77: =+$B$7 -> TEXAS INSTRUMENTS INCORPORATED | G77: =+G7+G21 -> #VALUE! | H77: =+H7+H21 -> 2471 | I77: =+I7+I21 -> 1077 | J77: =+J7+J21 -> 1184 | K77: =+K7+K21 -> 2250 | L77: =+L7+L21 -> 2070 | M77: =+M7+M21 -> 1950 | N77: =+N7+N21 -> 2080 | ... Q77: =+Q7+Q21 -> #VALUE! | R77: =IFERROR((Q77/G77)^(1/COUNT($G$4:$Q$4))-1,"")
B78: =+$B$8 -> MICROCHIP TECHNOLOGY INCORPORATED | G78: =+G8+G22 -> #VALUE! | H78: =+H8+H22 -> 1999 | I78: =+I8+I22 -> 1623 | J78: =+J8+J22 -> 2461 | K78: =+K8+K22 -> 1600 | L78: =+L8+L22 -> 1560 | M78: =+M8+M22 -> 1320 | N78: =+N8+N22 -> 1500 | ... Q78: =+Q8+Q22 -> #VALUE! | R78: =IFERROR((Q78/G78)^(1/COUNT($G$4:$Q$4))-1,"")
B79: =+$B$9 -> MONOLITHIC POWER SYSTEMS, INC. | G79: =+G9+G23 -> #VALUE! | H79: =+H9+H23 -> 3170 | I79: =+I9+I23 -> 3784 | J79: =+J9+J23 -> 5841 | K79: =+K9+K23 -> 6124 | L79: =+L9+L23 -> 6698 | M79: =+M9+M23 -> 6670 | N79: =+N9+N23 -> 7147 | ... Q79: =+Q9+Q23 -> #VALUE! | R79: =IFERROR((Q79/G79)^(1/COUNT($G$4:$Q$4))-1,"")
B80: =+$B$10 -> SKYWORKS SOLUTIONS, INC. | G80: =+G10+G24 -> #VALUE! | H80: =+H10+H24 -> #VALUE! | I80: =+I10+I24 -> #VALUE! | J80: =+J10+J24 -> #VALUE! | K80: =+K10+K24 -> #VALUE! | L80: =+L10+L24 -> #VALUE! | M80: =+M10+M24 -> #VALUE! | N80: =+N10+N24 -> #VALUE! | ... Q80: =+Q10+Q24 -> #VALUE! | R80: =IFERROR((Q80/G80)^(1/COUNT($G$4:$Q$4))-1,"")
B81: =+$B$11 -> MACOM TECHNOLOGY SOLUTIONS HOLDINGS, INC. | G81: =+G11+G25 -> #VALUE! | H81: =+H11+H25 -> #VALUE! | I81: =+I11+I25 -> #VALUE! | J81: =+J11+J25 -> #VALUE! | K81: =+K11+K25 -> #VALUE! | L81: =+L11+L25 -> #VALUE! | M81: =+M11+M25 -> #VALUE! | N81: =+N11+N25 -> 19 | ... Q81: =+Q11+Q25 -> #VALUE! | R81: =IFERROR((Q81/G81)^(1/COUNT($G$4:$Q$4))-1,"")
B82: =+$B$12 -> MARVELL TECHNOLOGY, INC. | G82: =+G12+G26 -> #VALUE! | H82: =+H12+H26 -> #VALUE! | I82: =+I12+I26 -> #VALUE! | J82: =+J12+J26 -> #VALUE! | K82: =+K12+K26 -> #VALUE! | L82: =+L12+L26 -> #VALUE! | M82: =+M12+M26 -> #VALUE! | N82: =+N12+N26 -> #VALUE! | ... Q82: =+Q12+Q26 -> 714 | R82: =IFERROR((Q82/G82)^(1/COUNT($G$4:$Q$4))-1,"")
B83: =+$B$13 -> INTEL CORPORATION | G83: =+G13+G27 -> #VALUE! | H83: =+H13+H27 -> 312 | I83: =+I13+I27 -> 406 | J83: =+J13+J27 -> 325 | K83: =+K13+K27 -> 356 | L83: =+L13+L27 -> 469 | M83: =+M13+M27 -> 352 | N83: =+N13+N27 -> 561 | ... Q83: =+Q13+Q27 -> #VALUE! | R83: =IFERROR((Q83/G83)^(1/COUNT($G$4:$Q$4))-1,"")
B84: =+$B$14 -> MICRON TECHNOLOGY, INC. | G84: =+G14+G28 -> #VALUE! | H84: =+H14+H28 -> #VALUE! | I84: =+I14+I28 -> #VALUE! | J84: =+J14+J28 -> #VALUE! | K84: =+K14+K28 -> #VALUE! | L84: =+L14+L28 -> #VALUE! | M84: =+M14+M28 -> #VALUE! | N84: =+N14+N28 -> #VALUE! | ... Q84: =+Q14+Q28 -> #VALUE! | R84: =IFERROR((Q84/G84)^(1/COUNT($G$4:$Q$4))-1,"")
B85: =+$B$15 -> FIRST SOLAR, INC. | G85: =+G15+G29 -> #VALUE! | H85: =+H15+H29 -> #VALUE! | I85: =+I15+I29 -> #VALUE! | J85: =+J15+J29 -> #VALUE! | K85: =+K15+K29 -> #VALUE! | L85: =+L15+L29 -> #VALUE! | M85: =+M15+M29 -> #VALUE! | N85: =+N15+N29 -> #VALUE! | ... Q85: =+Q15+Q29 -> #VALUE! | R85: =IFERROR((Q85/G85)^(1/COUNT($G$4:$Q$4))-1,"")
B86: =+$B$16 -> ALTRI, S.G.P.S., S.A. | G86: =+G16+G30 -> #VALUE! | H86: =+H16+H30 -> #VALUE! | I86: =+I16+I30 -> #VALUE! | J86: =+J16+J30 -> #VALUE! | K86: =+K16+K30 -> #VALUE! | L86: =+L16+L30 -> #VALUE! | M86: =+M16+M30 -> #VALUE! | N86: =+N16+N30 -> #VALUE! | ... Q86: =+Q16+Q30 -> #VALUE! | R86: =IFERROR((Q86/G86)^(1/COUNT($G$4:$Q$4))-1,"")

Sheet DCF
B2: DCF
A4: x | B4: Key Assumptions | R4: #VALUE!
B6: Switches | E6: Bear Case | H6: Base Case | K6: Bull Case | X6: FCFF | Y6: FCFE | Z6: Tax Shield | AA6: Total Payout | AB6: NOPAT | AC6: Debt Borrowing | AD6: Cash Balance | AE6: Total Assets | AF6: Total Liabilities | AG6: Shareholder's Equity | AH6: Current Liabilities | AI6: Current Assets
B7: Revenue | C7: 2 | E7: Revenue | F7: =I7-C7% -> -0.02 | H7: Revenue | K7: Revenue | L7: =I7+C7% -> 0.02 | S7: Most Recent Fiscal Year | W7: 2022 | X7: =+E192 -> 3743.8181 | Y7: =+E244 -> 3800.6 | Z7: =+H216 -> 0 | AA7: =+E257 -> -4121.6 | AB7: =+E182 -> 1928.1181 | AC7: =+E242 -> 0 | AD7: =+E88 -> 1470.6
B8: EBIT | C8: 2 | E8: EBIT | F8: -0.01 | H8: EBIT | K8: EBIT | L8: 0.01 | S8: End of Fiscal Year | W8: =+W7+1 -> 2023 | X8: =+F192 -> 3404.7221 | Y8: =+F244 -> 3449.2 | Z8: =+I216 -> 0 | AA8: =+F257 -> -4643.1 | AB8: =+F182 -> 2362.3221 | AC8: =+F242 -> 0 | AD8: =+F88 -> 958.1
B9: WACC | C9: 2 | E9: WACC | F9: =IFERROR(+I9+0.5%,"") -> 0.09058 | H9: WACC | I9: =WACC!G25 -> 0.08558 | K9: WACC | L9: =IFERROR(I9-0.5%,"") -> 0.08058 | S9: Most Recent Quarter End Date | W9: =+W8+1 -> 2024 | X9: =+G192 -> 2284.4899 | Y9: =+G244 -> 2838.366 | Z9: =+J216 -> 0 | AA9: =+G257 -> -2411.1 | AB9: =+G182 -> 590.38985 | AC9: =+G242 -> 499.966 | AD9: =+G88 -> 2363.1 | AE9: =Inputs!Q48 -> 48228.3 | AF9: =+Inputs!Q60 -> 13052 | AG9: =+AE9-AF9 -> 35176.3 | AH9: =+Inputs!Q54 -> 2988.3 | AI9: =+Inputs!Q38 -> 5484.7
B10: TGR | C10: 2 | E10: TGR | F10: =+I10-0.5% -> -0.005 | H10: TGR | K10: TGR | L10: =+I10+0.5% -> 0.005 | S10: Valuation Date | W10: =+W9+1 -> 2025 | X10: =+H192 -> 3929.6086 | Y10: =+H244 -> 3933.1926 | Z10: =+K216 -> 0 | AA10: =+H257 -> 0 | AB10: =+H182 -> 1366.5525 | AC10: =+H242 -> 0 | AD10: =+H88 -> 7076.7342 | AE10: =Inputs!Q48+DCF!H88+DCF!H90+DCF!H93+DCF!H96+DCF!H99+DCF!H105-DCF!G88-DCF!G90-DCF!G93-DCF!G96-DCF!G99-DCF!G105 -> 52538.622 | AF10: =+Inputs!Q60+(DCF!H110+DCF!H113+DCF!H116+DCF!H118*DCF!G110*DCF!G113*DCF!G116*DCF!G118) -> #VALUE! | AG10: =+AE10-AF10 -> #VALUE! | AH10: =+AH9+H110+H113-G110-G113 -> 3276.3266 | AI10: =+H88+H90+H93+H96 -> 10192.958
W11: =+W10+1 -> 2026 | X11: =+I192 -> 3827.6097 | Y11: =+I244 -> 3827.5308 | Z11: =+L216 -> 0 | AA11: =+I257 -> 0 | AB11: =+I182 -> 1804.7549 | AC11: =+I242 -> 0 | AD11: =+I88 -> 12055.947 | AE11: =AE10+DCF!I88+DCF!I90+DCF!I93+DCF!I96+DCF!I99+DCF!I105-DCF!H88-DCF!H90-DCF!H93-DCF!H96-DCF!H99-DCF!H105 -> 57436.62 | AF11: =AF10+(DCF!I110+DCF!I113+DCF!I116+DCF!I118*DCF!H110*DCF!H113*DCF!H116*DCF!H118) -> #VALUE! | AG11: =+AE11-AF11 -> #VALUE! | AH11: =+AH10+I110+I113-H110-H113 -> 3364.2728 | AI11: =+I88+I90+I93+I96 -> 15539.152
B12: WACC | C12: =CHOOSE(C9,F9,I9,L9) -> 0.08558 | W12: =+W11+1 -> 2027 | X12: =+J192 -> 4273.3142 | Y12: =+J244 -> 4270.209 | Z12: =+M216 -> 0 | AA12: =+J257 -> 0 | AB12: =+J182 -> 2134.7109 | AC12: =+J242 -> 0 | AD12: =+J88 -> 17620.117
B13: TGR | C13: =CHOOSE(C10,F10,I10,L10) -> 0 | W13: =+W12+1 -> 2028 | X13: =+K192 -> 4670.9362 | Y13: =+K244 -> 4671.0753 | Z13: =+N216 -> 0 | AA13: =+K257 -> 0 | AB13: =+K182 -> 2369.4404 | AC13: =+K242 -> 0 | AD13: =+K88 -> 23405.267
W14: =+W13+1 -> 2029 | X14: =+L192 -> 4757.8869 | Y14: =+L244 -> 4756.8365 | Z14: =+O216 -> 0 | AA14: =+L257 -> 0 | AB14: =+L182 -> 2804.9124 | AC14: =+L242 -> 0 | AD14: =+L88 -> 29391.392
A15: x | B15: Operating Assumptions | E15: 2022 | F15: =+E15+1 -> 2023 | G15: =+F15+1 -> 2024 | H15: =+G15+1 -> 2025 | I15: =+H15+1 -> 2026 | J15: =+I15+1 -> 2027 | K15: =+J15+1 -> 2028 | L15: =+K15+1 -> 2029 | M15: =+L15+1 -> 2030 | ... Q15: =+P15+1 -> 2034
B17: Number of Locations (Beginning)
B18: Net Locations Opened/Acquired
B19: Capex per Net Additions
B20: Locations Opened/Acquired
B21: Locations Closed/Sold
B22: Number of Locations (End)
B23: Average Sales per Location
B24: Same Store Sales Growth
B25: Beginning Locations Total Sales
B26: New Locations Total Sales (Estimate)
B27: In millions of USD
A28: x | B28: Income Statement | E28: 2022 | F28: =+E28+1 -> 2023 | G28: =+F28+1 -> 2024 | H28: =+G28+1 -> 2025 | I28: =+H28+1 -> 2026 | J28: =+I28+1 -> 2027 | K28: =+J28+1 -> 2028 | L28: =+K28+1 -> 2029 | M28: =+L28+1 -> 2030 | ... Q28: =+P28+1 -> 2034
B30: Revenue (Sales) | D30: =+_xlfn.XLOOKUP($B30,Inputs!$B:$B,Inputs!N:N) -> 7318.3 | E30: =+_xlfn.XLOOKUP($B30,Inputs!$B:$B,Inputs!O:O) -> 12014 | F30: =+_xlfn.XLOOKUP($B30,Inputs!$B:$B,Inputs!P:P) -> 12305.5 | G30: =+_xlfn.XLOOKUP($B30,Inputs!$B:$B,Inputs!Q:Q) -> 9427.2 | H30: 10336 | I30: =H30*(1+I31) -> 11641.437 | J30: =I30*(1+J31) -> 12772.984 | K30: =J30*(1+K31) -> 13232.812 | L30: =K30*(1+L31) -> 13709.193 | M30: =L30*(1+M31) -> 14202.724 | N30: =M30*(1+N31) -> 14714.022 | O30: =N30*(1+O31) -> 15243.727 | P30: =O30*(1+P31) -> 15792.501 | Q30: =P30*(1+Q31) -> 16361.031
B31: % of growth | E31: =IFERROR((E30-D30)/D30,"") -> 0.64163809 | F31: =IFERROR((F30-E30)/E30,"") -> 0.024263359 | G31: =IFERROR((G30-F30)/F30,"") -> -0.23390354 | H31: 0.0964 | I31: 0.1263 | J31: 0.0972 | K31: 0.036 | L31: 0.036 | M31: 0.036 | N31: 0.036 | O31: 0.036 | P31: 0.036 | Q31: 0.036
B33: COGS (Cost of Goods Sold) | E33: =+_xlfn.XLOOKUP($B33,Inputs!$B:$B,Inputs!O:O) -> 4481.5 | F33: =+_xlfn.XLOOKUP($B33,Inputs!$B:$B,Inputs!P:P) -> 4428.3 | G33: =+_xlfn.XLOOKUP($B33,Inputs!$B:$B,Inputs!Q:Q) -> 4045.8 | H33: =H34*H$30 -> 3927.68 | I33: =I34*I$30 -> 4365.5388 | J33: =J34*J$30 -> 4726.0042 | K33: =K34*K$30 -> 4856.442 | L33: =L34*L$30 -> 5003.8555 | M33: =M34*M$30 -> 5183.9943 | N33: =N34*N$30 -> 5370.6181 | O33: =O34*O$30 -> 5563.9603 | ... Q33: =Q34*Q$30 -> 5971.7764
B34: % of revenue | E34: =IFERROR(E33/E$30,"") -> 0.37302314 | F34: =IFERROR(F33/F$30,"") -> 0.35986348 | G34: =IFERROR(G33/G$30,"") -> 0.42916242 | H34: 0.38 | I34: 0.375 | J34: 0.37 | K34: 0.367 | L34: 0.365 | M34: 0.365 | N34: 0.365 | O34: 0.365 | P34: 0.365 | Q34: 0.365
B36: Gross Profit | E36: =+_xlfn.XLOOKUP($B36,Inputs!$B:$B,Inputs!O:O) -> 7532.5 | F36: =+_xlfn.XLOOKUP($B36,Inputs!$B:$B,Inputs!P:P) -> 7877.2 | G36: =+_xlfn.XLOOKUP($B36,Inputs!$B:$B,Inputs!Q:Q) -> 5381.4 | H36: =+H30-H33 -> 6408.32 | I36: =+I30-I33 -> 7275.898 | J36: =+J30-J33 -> 8046.9802 | K36: =+K30-K33 -> 8376.3699 | L36: =+L30-L33 -> 8705.3376 | M36: =+M30-M33 -> 9018.7298 | N36: =+N30-N33 -> 9343.4041 | O36: =+O30-O33 -> 9679.7666 | ... Q36: =+Q30-Q33 -> 10389.255
B37: Gross Profit Margin | E37: =IFERROR(E36/E$30,"") -> 0.62697686 | F37: =IFERROR(F36/F$30,"") -> 0.64013652 | G37: =IFERROR(G36/G$30,"") -> 0.57083758 | H37: =IFERROR(H36/H$30,"") -> 0.62 | I37: =IFERROR(I36/I$30,"") -> 0.625 | J37: =IFERROR(J36/J$30,"") -> 0.63 | K37: =IFERROR(K36/K$30,"") -> 0.633 | L37: =IFERROR(L36/L$30,"") -> 0.635 | ... Q37: =IFERROR(Q36/Q$30,"") -> 0.635
B39: SG&A (Selling, General & Administrative) | E39: =+_xlfn.XLOOKUP($B39,Inputs!$B:$B,Inputs!O:O) -> 1266.2 | F39: =+_xlfn.XLOOKUP($B39,Inputs!$B:$B,Inputs!P:P) -> 1273.6 | G39: =+_xlfn.XLOOKUP($B39,Inputs!$B:$B,Inputs!Q:Q) -> 1068.6 | H39: =IFERROR(G39*(1+H31),"") -> 1171.613 | I39: =IFERROR(H39*(1+I31),"") -> 1319.5878 | J39: =IFERROR(I39*(1+J31),"") -> 1447.8517 | K39: =IFERROR(J39*(1+K31),"") -> 1499.9744 | L39: =IFERROR(K39*(1+L31),"") -> 1553.9734 | M39: =IFERROR(L39*(1+M31),"") -> 1609.9165 | N39: =IFERROR(M39*(1+N31),"") -> 1667.8735 | O39: =IFERROR(N39*(1+O31),"") -> 1727.9169 | ... Q39: =IFERROR(P39*(1+Q31),"") -> 1854.5663
B40: SG&A Margin | E40: =IFERROR(E39/E$30,"") -> 0.10539371 | F40: =IFERROR(F39/F$30,"") -> 0.10349844 | G40: =IFERROR(G39/G$30,"") -> 0.11335285 | H40: =IFERROR(AVERAGE(E40:G40),"") -> 0.107415 | I40: =IFERROR(AVERAGE(F40:H40),"") -> 0.10808876 | J40: =IFERROR(AVERAGE(G40:I40),"") -> 0.10961887 | K40: =IFERROR(AVERAGE(H40:J40),"") -> 0.10837421 | L40: =IFERROR(AVERAGE(I40:K40),"") -> 0.10869395 | M40: =IFERROR(AVERAGE(J40:L40),"") -> 0.10889568 | N40: =IFERROR(AVERAGE(K40:M40),"") -> 0.10865461 | O40: =IFERROR(AVERAGE(L40:N40),"") -> 0.10874808 | ... Q40: =IFERROR(AVERAGE(N40:P40),"") -> 0.10872294
B42: R&D (Research & Development) | E42: =+_xlfn.XLOOKUP($B42,Inputs!$B:$B,Inputs!O:O) -> 1700.5 | F42: =+_xlfn.XLOOKUP($B42,Inputs!$B:$B,Inputs!P:P) -> 1660.2 | G42: =+_xlfn.XLOOKUP($B42,Inputs!$B:$B,Inputs!Q:Q) -> 1487.9 | H42: =H43*H$30 -> 1653.76 | I42: =I43*I$30 -> 1862.6299 | J42: =J43*J$30 -> 2043.6775 | K42: =K43*K$30 -> 2117.2499 | L42: =L43*L$30 -> 2193.4709 | M42: =M43*M$30 -> 2272.4359 | N42: =N43*N$30 -> 2354.2435 | O42: =O43*O$30 -> 2438.9963 | ... Q42: =Q43*Q$30 -> 2617.765
B43: % of revenue | E43: =IFERROR(E42/E30,"") -> 0.1415432 | F43: =IFERROR(F42/F30,"") -> 0.13491528 | G43: =IFERROR(G42/G30,"") -> 0.15783053 | H43: 0.16 | I43: 0.16 | J43: 0.16 | K43: 0.16 | L43: 0.16 | M43: 0.16 | N43: 0.16 | O43: 0.16 | P43: 0.16 | Q43: 0.16
B45: Other Operating (Income) Expenses | E45: =+_xlfn.XLOOKUP($B45,Inputs!$B:$B,Inputs!O:O) -> 0 | F45: =+_xlfn.XLOOKUP($B45,Inputs!$B:$B,Inputs!P:P) -> 0 | G45: =+_xlfn.XLOOKUP($B45,Inputs!$B:$B,Inputs!Q:Q) -> 0 | H45: =IFERROR(AVERAGE(E45:G45)*(1+H31),"") -> 0 | I45: =IFERROR(AVERAGE(F45:H45)*(1+I31),"") -> 0 | J45: =IFERROR(AVERAGE(G45:I45)*(1+J31),"") -> 0 | K45: =IFERROR(AVERAGE(H45:J45)*(1+K31),"") -> 0 | L45: =IFERROR(AVERAGE(I45:K45)*(1+L31),"") -> 0 | M45: =IFERROR(AVERAGE(J45:L45)*(1+M31),"") -> 0 | N45: =IFERROR(AVERAGE(K45:M45)*(1+N31),"") -> 0 | O45: =IFERROR(AVERAGE(L45:N45)*(1+O31),"") -> 0 | ... Q45: =IFERROR(AVERAGE(N45:P45)*(1+Q31),"") -> 0
B47: EBITDA | E47: =+_xlfn.XLOOKUP($B47,Inputs!$B:$B,Inputs!O:O) -> 4565.8 | F47: =+_xlfn.XLOOKUP($B47,Inputs!$B:$B,Inputs!P:P) -> 4943.4 | G47: =+_xlfn.XLOOKUP($B47,Inputs!$B:$B,Inputs!Q:Q) -> 2824.9 | H47: =IFERROR(H36-H39-H42-H45,"") -> 3582.947 | I47: =IFERROR(I36-I39-I42-I45,"") -> 4093.6803 | J47: =IFERROR(J36-J39-J42-J45,"") -> 4555.451 | K47: =IFERROR(K36-K39-K42-K45,"") -> 4759.1457 | L47: =IFERROR(L36-L39-L42-L45,"") -> 4957.8933 | M47: =IFERROR(M36-M39-M42-M45,"") -> 5136.3775 | N47: =IFERROR(N36-N39-N42-N45,"") -> 5321.287 | O47: =IFERROR(O36-O39-O42-O45,"") -> 5512.8534 | ... Q47: =IFERROR(Q36-Q39-Q42-Q45,"") -> 5916.9235
B48: EBITDA Margin | E48: =IFERROR(E47/E$30,"") -> 0.38003995 | F48: =IFERROR(F47/F$30,"") -> 0.40172281 | G48: =IFERROR(G47/G$30,"") -> 0.29965419 | H48: =IFERROR(H47/H$30,"") -> 0.34664735 | I48: =IFERROR(I47/I$30,"") -> 0.35164735 | J48: =IFERROR(J47/J$30,"") -> 0.35664735 | K48: =IFERROR(K47/K$30,"") -> 0.35964735 | L48: =IFERROR(L47/L$30,"") -> 0.36164735 | ... Q48: =IFERROR(Q47/Q$30,"") -> 0.36164735
B50: D&A (Depreciation & Amortization) | E50: =+_xlfn.XLOOKUP($B50,Inputs!$B:$B,Inputs!O:O) -> 2297.5 | F50: =+_xlfn.XLOOKUP($B50,Inputs!$B:$B,Inputs!P:P) -> 2293.1 | G50: =+_xlfn.XLOOKUP($B50,Inputs!$B:$B,Inputs!Q:Q) -> 2104.3 | H50: =+IFERROR(H53+H56,"") -> 1981.936 | I50: =+IFERROR(I53+I56,"") -> 1982.1953 | J50: =+IFERROR(J53+J56,"") -> 2021.7599 | K50: =+IFERROR(K53+K56,"") -> 1972.4633 | L50: =+IFERROR(L53+L56,"") -> 1654.8039 | M50: =+IFERROR(M53+M56,"") -> 1448.4049 | N50: =+IFERROR(N53+N56,"") -> 1287.7699 | O50: =+IFERROR(O53+O56,"") -> 1163.9075 | ... Q50: =+IFERROR(Q53+Q56,"") -> 999.19506
B51: % of PP&E+ROU Assets+Intangibles excl. Goodwill | E51: =IFERROR(E50/AVERAGE(Inputs!O39+Inputs!O42+Inputs!O44,Inputs!N39+Inputs!N42+Inputs!N44),"") -> 0.078935615 | F51: =IFERROR(F50/AVERAGE(Inputs!P39+Inputs!P42+Inputs!P44,Inputs!O39+Inputs!O42+Inputs!O44),"") -> 0.08156507 | G51: =IFERROR(G50/AVERAGE(Inputs!Q39+Inputs!Q42+Inputs!Q44,Inputs!P39+Inputs!P42+Inputs!P44),"") -> 0.078193483 | H51: =IFERROR(H50/(G99+G105),"") -> -0.11440208 | I51: =IFERROR(I50/(H99+H105),"") -> -0.11184792 | J51: =IFERROR(J50/(I99+I105),"") -> -0.11126648 | K51: =IFERROR(K50/(J99+J105),"") -> -0.10569302 | L51: =IFERROR(L50/(K99+K105),"") -> -0.086315135 | M51: =IFERROR(M50/(L99+L105),"") -> -0.073525112 | N51: =IFERROR(N50/(M99+M105),"") -> -0.06360531 | O51: =IFERROR(O50/(N99+N105),"") -> -0.055922803 | ... Q51: =IFERROR(Q50/(P99+P105),"") -> -0.045402174
B53: Depreciation Expense | E53: =+_xlfn.XLOOKUP($B53,Inputs!$B:$B,Inputs!O:O) -> 283.3 | F53: =+_xlfn.XLOOKUP($B53,Inputs!$B:$B,Inputs!P:P) -> 334.7 | G53: =+_xlfn.XLOOKUP($B53,Inputs!$B:$B,Inputs!Q:Q) -> 362.8 | H53: =H30*0.0385 -> 397.936 | I53: =I30*0.0385 -> 448.19532 | J53: =J30*0.0385 -> 491.7599 | K53: =K30*0.0385 -> 509.46326 | L53: =L30*0.0385 -> 527.80394 | M53: =M30*0.0385 -> 546.80488 | N53: =N30*0.0385 -> 566.48985 | O53: =O30*0.0385 -> 586.88349 | ... Q53: =Q30*0.0385 -> 629.8997
B54: % of PP&E+ROU Assets | E54: =IFERROR(E53/AVERAGE(Inputs!O40+Inputs!O42,Inputs!N40+Inputs!N42),"") -> 0.054040134 | F54: =IFERROR(F53/AVERAGE(Inputs!P40+Inputs!P42,Inputs!O40+Inputs!O42),"") -> 0.12062348 | G54: =IFERROR(G53/AVERAGE(Inputs!Q40+Inputs!Q42,Inputs!P40+Inputs!P42),"") | H54: =IFERROR(AVERAGE(E54:G54),"") -> 0.087331807 | I54: =IFERROR(AVERAGE(F54:H54),"") -> 0.10397764 | J54: =IFERROR(AVERAGE(G54:I54),"") -> 0.095654725 | K54: =IFERROR(AVERAGE(H54:J54),"") -> 0.095654725 | L54: =IFERROR(AVERAGE(I54:K54),"") -> 0.098429031 | M54: =IFERROR(AVERAGE(J54:L54),"") -> 0.096579494 | N54: =IFERROR(AVERAGE(K54:M54),"") -> 0.09688775 | O54: =IFERROR(AVERAGE(L54:N54),"") -> 0.097298758 | ... Q54: =IFERROR(AVERAGE(N54:P54),"") -> 0.09703617
B56: Amortization Expense | E56: =+_xlfn.XLOOKUP($B56,Inputs!$B:$B,Inputs!O:O) -> 2014.2 | F56: =+_xlfn.XLOOKUP($B56,Inputs!$B:$B,Inputs!P:P) -> 1958.4 | G56: =+_xlfn.XLOOKUP($B56,Inputs!$B:$B,Inputs!Q:Q) -> 1741.5 | H56: 1584 | I56: 1534 | J56: 1530 | K56: 1463 | L56: 1127 | M56: =L56*0.8 -> 901.6 | N56: =M56*0.8 -> 721.28 | O56: =N56*0.8 -> 577.024 | P56: =O56*0.8 -> 461.6192 | Q56: =P56*0.8 -> 369.29536
B57: % of Intangibles excl. Goodwill | E57: =IFERROR(E56/AVERAGE(Inputs!N45:O45),"") -> -0.15923159 | F57: =IFERROR(F56/AVERAGE(Inputs!O45:P45),"") -> -0.13391319 | G57: =IFERROR(G56/AVERAGE(Inputs!P45:Q45),"") -> -0.10578459
B59: Operating Income (EBIT) | E59: =+_xlfn.XLOOKUP($B59,Inputs!$B:$B,Inputs!O:O) -> 2268.3 | F59: =+_xlfn.XLOOKUP($B59,Inputs!$B:$B,Inputs!P:P) -> 2650.3 | G59: =+_xlfn.XLOOKUP($B59,Inputs!$B:$B,Inputs!Q:Q) -> 720.6 | H59: =+IFERROR(H47-H50,"") -> 1601.011 | I59: =+IFERROR(I47-I50,"") -> 2111.485 | J59: =+IFERROR(J47-J50,"") -> 2533.6911 | K59: =+IFERROR(K47-K50,"") -> 2786.6824 | L59: =+IFERROR(L47-L50,"") -> 3303.0894 | M59: =+IFERROR(M47-M50,"") -> 3687.9726 | N59: =+IFERROR(N47-N50,"") -> 4033.5172 | O59: =+IFERROR(O47-O50,"") -> 4348.9459 | ... Q59: =+IFERROR(Q47-Q50,"") -> 4917.7284
B60: Operating Margin | E60: =IFERROR(E59/E$30,"") -> 0.18880473 | F60: =IFERROR(F59/F$30,"") -> 0.21537524 | G60: =IFERROR(G59/G$30,"") -> 0.076438391 | H60: =IFERROR(H59/H30,"") -> 0.15489657 | I60: =IFERROR(I59/I30,"") -> 0.18137667 | J60: =IFERROR(J59/J30,"") -> 0.19836328 | K60: =IFERROR(K59/K30,"") -> 0.21058883 | L60: =IFERROR(L59/L30,"") -> 0.24093974 | M60: =IFERROR(M59/M30,"") -> 0.25966657 | N60: =IFERROR(N59/N30,"") -> 0.27412744 | O60: =IFERROR(O59/O30,"") -> 0.28529414 | ... Q60: =IFERROR(Q59/Q30,"") -> 0.3005757
B62: Net Interest Expense (Income) | E62: =+_xlfn.XLOOKUP($B62,Inputs!$B:$B,Inputs!O:O) -> -6.9 | F62: =+_xlfn.XLOOKUP($B62,Inputs!$B:$B,Inputs!P:P) -> -41.3 | G62: =+_xlfn.XLOOKUP($B62,Inputs!$B:$B,Inputs!Q:Q) -> -78.8 | H62: =-H65-H68 -> 0 | I62: =-I65-I68 -> 0 | J62: =-J65-J68 -> 0 | K62: =-K65-K68 -> 0 | L62: =-L65-L68 -> 0 | M62: =-M65-M68 -> 0 | N62: =-N65-N68 -> 0 | O62: =-O65-O68 -> 0 | ... Q62: =-Q65-Q68 -> 0
B63: % of Net Debt | E63: =IFERROR(E62/AVERAGE(Inputs!N116:O116),"") -> -0.0013981905 | F63: =IFERROR(F62/AVERAGE(Inputs!O116:P116),"") -> -0.0074624843 | G63: =IFERROR(G62/AVERAGE(Inputs!P116:Q116),"") -> -0.014059879 | H63: =IFERROR(H62/AVERAGE(G116+G118,H116+H118),"") | I63: =IFERROR(I62/AVERAGE(H116+H118,I116+I118),"") | J63: =IFERROR(J62/AVERAGE(I116+I118,J116+J118),"") | K63: =IFERROR(K62/AVERAGE(J116+J118,K116+K118),"") | L63: =IFERROR(L62/AVERAGE(K116+K118,L116+L118),"") | M63: =IFERROR(M62/AVERAGE(L116+L118,M116+M118),"") | N63: =IFERROR(N62/AVERAGE(M116+M118,N116+N118),"") | O63: =IFERROR(O62/AVERAGE(N116+N118,O116+O118),"") | ... Q63: =IFERROR(Q62/AVERAGE(P116+P118,Q116+Q118),"")
B65: Interest Expense | E65: =+_xlfn.XLOOKUP($B65,Inputs!$B:$B,Inputs!O:O) -> 200.4 | F65: =+_xlfn.XLOOKUP($B65,Inputs!$B:$B,Inputs!P:P) -> 264.6 | G65: =+_xlfn.XLOOKUP($B65,Inputs!$B:$B,Inputs!Q:Q) -> 322.2
B66: % of Debt | E66: =+IFERROR(E65/AVERAGE(Inputs!N113:O113),"") -> 0.030093479 | F66: =+IFERROR(F65/AVERAGE(Inputs!O113:P113),"") -> 0.039207551 | G66: =+IFERROR(G65/AVERAGE(Inputs!P113:Q113),"") -> 0.044348401 | H66: 0.0366 | I66: 0.0357 | J66: 0.0355 | K66: 0.0355 | L66: 0.0355 | M66: 0.0355 | N66: 0.0355 | O66: 0.0355 | P66: 0.0355 | Q66: 0.0355
B68: Interest Income | E68: =+_xlfn.XLOOKUP($B68,Inputs!$B:$B,Inputs!O:O) -> 207.3 | F68: =+_xlfn.XLOOKUP($B68,Inputs!$B:$B,Inputs!P:P) -> 305.9 | G68: =+_xlfn.XLOOKUP($B68,Inputs!$B:$B,Inputs!Q:Q) -> 401
B69: % Cash & Cash Eq. & ST Investments | E69: =IFERROR(E68/+AVERAGE(Inputs!N32:O32),"") -> 0.1202227 | F69: =IFERROR(F68/+AVERAGE(Inputs!O32:P32),"") -> 0.25190431 | G69: =IFERROR(G68/+AVERAGE(Inputs!P32:Q32),"") -> 0.24147898
B71: FX (Gain) Loss | E71: =+_xlfn.XLOOKUP($B71,Inputs!$B:$B,Inputs!O:O) -> -46.3 | F71: =+_xlfn.XLOOKUP($B71,Inputs!$B:$B,Inputs!P:P) -> -0.4 | G71: =+_xlfn.XLOOKUP($B71,Inputs!$B:$B,Inputs!Q:Q) -> 1 | H71: =+H72*H$17 -> 0 | I71: =+I72*I$17 -> 0 | J71: =+J72*J$17 -> 0 | K71: =+K72*K$17 -> 0 | L71: =+L72*L$17 -> 0 | M71: =+M72*M$17 -> 0 | N71: =+N72*N$17 -> 0 | O71: =+O72*O$17 -> 0 | ... Q71: =+Q72*Q$17 -> 0
B72: % of revenue
B74: Other Non-Operating (Income) Expenses | E74: =+_xlfn.XLOOKUP($B74,Inputs!$B:$B,Inputs!O:O) -> -13.6 | F74: =+_xlfn.XLOOKUP($B74,Inputs!$B:$B,Inputs!P:P) -> -8.2 | G74: =+_xlfn.XLOOKUP($B74,Inputs!$B:$B,Inputs!Q:Q) -> 12 | H74: =IFERROR(AVERAGE(E74:G74)*(1+H31),"") -> -3.5815733 | I74: =IFERROR(AVERAGE(F74:H74)*(1+I31),"") -> 0.082004652 | J74: =IFERROR(AVERAGE(G74:I74)*(1+J31),"") -> 3.1088911 | K74: =IFERROR(AVERAGE(H74:J74)*(1+K31),"") -> -0.134914 | L74: =IFERROR(AVERAGE(I74:K74)*(1+L31),"") -> 1.0553324 | M74: =IFERROR(AVERAGE(J74:L74)*(1+M31),"") -> 1.3914549 | N74: =IFERROR(AVERAGE(K74:M74)*(1+N31),"") -> 0.79836689 | O74: =IFERROR(AVERAGE(L74:N74)*(1+O31),"") -> 1.1206599 | ... Q74: =IFERROR(AVERAGE(N74:P74)*(1+Q31),"") -> 1.0574958
B76: Pre-Tax Income (EBT) | E76: =+_xlfn.XLOOKUP($B76,Inputs!$B:$B,Inputs!O:O) -> 2335.1 | F76: =+_xlfn.XLOOKUP($B76,Inputs!$B:$B,Inputs!P:P) -> 2700.2 | G76: =+_xlfn.XLOOKUP($B76,Inputs!$B:$B,Inputs!Q:Q) -> 786.4 | H76: =IFERROR(+H59-H62-H71-H74,"") -> 1604.5925 | I76: =IFERROR(+I59-I62-I71-I74,"") -> 2111.403 | J76: =IFERROR(+J59-J62-J71-J74,"") -> 2530.5822 | K76: =IFERROR(+K59-K62-K71-K74,"") -> 2786.8173 | L76: =IFERROR(+L59-L62-L71-L74,"") -> 3302.034 | M76: =IFERROR(+M59-M62-M71-M74,"") -> 3686.5811 | N76: =IFERROR(+N59-N62-N71-N74,"") -> 4032.7188 | O76: =IFERROR(+O59-O62-O71-O74,"") -> 4347.8252 | ... Q76: =IFERROR(+Q59-Q62-Q71-Q74,"") -> 4916.6709
B78: Tax Expense (Benefits) | E78: =+_xlfn.XLOOKUP($B78,Inputs!$B:$B,Inputs!O:O) -> 350.2 | F78: =+_xlfn.XLOOKUP($B78,Inputs!$B:$B,Inputs!P:P) -> 293.4 | G78: =+_xlfn.XLOOKUP($B78,Inputs!$B:$B,Inputs!Q:Q) -> 142.1 | H78: =IFERROR(H79*H$59,"") -> 234.45612 | I78: =IFERROR(I79*I$59,"") -> 306.72699 | J78: =IFERROR(J79*J$59,"") -> 398.97644 | K78: =IFERROR(K79*K$59,"") -> 417.23789 | L78: =IFERROR(L79*L$59,"") -> 498.17209 | M78: =IFERROR(M79*M$59,"") -> 563.04791 | N78: =IFERROR(N79*N$59,"") -> 609.353 | O78: =IFERROR(O79*O$59,"") -> 658.9578 | ... Q78: =IFERROR(Q79*Q$59,"") -> 744.78775
B79: % of EBT | E79: =IFERROR(E78/E76,"") -> 0.14997216 | F79: =IFERROR(F78/F76,"") -> 0.10865862 | G79: =IFERROR(G78/G76,"") -> 0.18069685 | H79: =IFERROR(AVERAGE(E79:G79),"") -> 0.14644254 | I79: =IFERROR(AVERAGE(F79:H79),"") -> 0.145266 | J79: =IFERROR(AVERAGE(G79:I79),"") -> 0.15746846 | K79: =IFERROR(AVERAGE(H79:J79),"") -> 0.14972567 | L79: =IFERROR(AVERAGE(I79:K79),"") -> 0.15082005 | M79: =IFERROR(AVERAGE(J79:L79),"") -> 0.15267139 | N79: =IFERROR(AVERAGE(K79:M79),"") -> 0.15107237 | O79: =IFERROR(AVERAGE(L79:N79),"") -> 0.15152127 | ... Q79: =IFERROR(AVERAGE(N79:P79),"") -> 0.15144955
B81: Net Income | E81: =+_xlfn.XLOOKUP($B81,Inputs!$B:$B,Inputs!O:O) -> 1984.9 | F81: =+_xlfn.XLOOKUP($B81,Inputs!$B:$B,Inputs!P:P) -> 2406.8 | G81: =+_xlfn.XLOOKUP($B81,Inputs!$B:$B,Inputs!Q:Q) -> 644.3 | H81: =IFERROR(+H76-H78,"") -> 1370.1364 | I81: =IFERROR(+I76-I78,"") -> 1804.676 | J81: =IFERROR(+J76-J78,"") -> 2131.6058 | K81: =IFERROR(+K76-K78,"") -> 2369.5794 | L81: =IFERROR(+L76-L78,"") -> 2803.8619 | M81: =IFERROR(+M76-M78,"") -> 3123.5332 | N81: =IFERROR(+N76-N78,"") -> 3423.3658 | O81: =IFERROR(+O76-O78,"") -> 3688.8674 | ... Q81: =IFERROR(+Q76-Q78,"") -> 4171.8832
B82: Net Income Margin | E82: =IFERROR(E81/E$30,"") -> 0.16521558 | F82: =IFERROR(F81/F$30,"") -> 0.19558734 | G82: =IFERROR(G81/G$30,"") -> 0.06834479 | H82: =IFERROR(H81/H$30,"") -> 0.13255964 | I82: =IFERROR(I81/I$30,"") -> 0.15502176 | J82: =IFERROR(J81/J$30,"") -> 0.16688392 | K82: =IFERROR(K81/K$30,"") -> 0.17906847 | L82: =IFERROR(L81/L$30,"") -> 0.20452421 | ... Q82: =IFERROR(Q81/Q$30,"") -> 0.25498901
A84: x | B84: Balance Sheet | E84: =E28 -> 2022 | F84: =F28 -> 2023 | G84: =G28 -> 2024 | H84: =H28 -> 2025 | I84: =I28 -> 2026 | J84: =J28 -> 2027 | K84: =K28 -> 2028 | L84: =L28 -> 2029 | ... Q84: =Q28 -> 2034
B86: Assets
B88: Cash & Cash Equivalents & ST Investments | E88: =+_xlfn.XLOOKUP($B88,Inputs!$B:$B,Inputs!O:O) -> 1470.6 | F88: =+_xlfn.XLOOKUP($B88,Inputs!$B:$B,Inputs!P:P) -> 958.1 | G88: =+_xlfn.XLOOKUP($B88,Inputs!$B:$B,Inputs!Q:Q) -> 2363.1 | H88: =IFERROR(G88+H165,"") -> 7076.7342 | I88: =IFERROR(H88+I165,"") -> 12055.947 | J88: =IFERROR(I88+J165,"") -> 17620.117 | K88: =IFERROR(J88+K165,"") -> 23405.267 | L88: =IFERROR(K88+L165,"") -> 29391.392 | M88: =IFERROR(L88+M165,"") -> 35528.468 | N88: =IFERROR(M88+N165,"") -> 41811.363 | O88: =IFERROR(N88+O165,"") -> 48282.977 | ... Q88: =IFERROR(P88+Q165,"") -> 61796.932
B90: Accounts Receivable | E90: =+_xlfn.XLOOKUP($B90,Inputs!$B:$B,Inputs!O:O) -> 1800.5 | F90: =+_xlfn.XLOOKUP($B90,Inputs!$B:$B,Inputs!P:P) -> 1469.7 | G90: =+_xlfn.XLOOKUP($B90,Inputs!$B:$B,Inputs!Q:Q) -> 1336.3 | H90: =IFERROR(H91*H30/365,"") -> 1417.5444 | I90: =IFERROR(I91*I30/365,"") -> 1547.2187 | J90: =IFERROR(J91*J30/365,"") -> 1754.9666 | K90: =IFERROR(K91*K30/365,"") -> 1797.233 | L90: =IFERROR(L91*L30/365,"") -> 1855.8561 | M90: =IFERROR(M91*M30/365,"") -> 1934.346 | N90: =IFERROR(N91*N30/365,"") -> 1998.0904 | O90: =IFERROR(O91*O30/365,"") -> 2069.9127 | ... Q90: =IFERROR(Q91*Q30/365,"") -> 2222.4219
B91: DSO | E91: =IFERROR(E90/E30*365,"") -> 54.70139 | F91: =IFERROR(F90/F30*365,"") -> 43.593556 | G91: =IFERROR(G90/G30*366,"") -> 51.880283 | H91: =IFERROR(AVERAGE(E91:G91),"") -> 50.058409 | I91: =IFERROR(AVERAGE(F91:H91),"") -> 48.510749 | J91: =IFERROR(AVERAGE(G91:I91),"") -> 50.149814 | K91: =IFERROR(AVERAGE(H91:J91),"") -> 49.572991 | L91: =IFERROR(AVERAGE(I91:K91),"") -> 49.411185 | M91: =IFERROR(AVERAGE(J91:L91),"") -> 49.71133 | N91: =IFERROR(AVERAGE(K91:M91),"") -> 49.565168 | O91: =IFERROR(AVERAGE(L91:N91),"") -> 49.562561 | ... Q91: =IFERROR(AVERAGE(N91:P91),"") -> 49.58025
B93: Inventory | E93: =+_xlfn.XLOOKUP($B93,Inputs!$B:$B,Inputs!O:O) -> 1399.9 | F93: =+_xlfn.XLOOKUP($B93,Inputs!$B:$B,Inputs!P:P) -> 1642.2 | G93: =+_xlfn.XLOOKUP($B93,Inputs!$B:$B,Inputs!Q:Q) -> 1447.7 | H93: =+IFERROR(H94*H33/365,"") -> 1362.9613 | I93: =+IFERROR(I94*I33/365,"") -> 1565.3139 | J93: =+IFERROR(J94*J33/365,"") -> 1675.2167 | K93: =+IFERROR(K94*K33/365,"") -> 1716.0135 | L93: =+IFERROR(L94*L33/365,"") -> 1778.6658 | M93: =+IFERROR(M94*M33/365,"") -> 1837.3369 | N93: =+IFERROR(N94*N33/365,"") -> 1903.4042 | O93: =+IFERROR(O94*O33/365,"") -> 1973.8977 | ... Q93: =+IFERROR(Q94*Q33/365,"") -> 2117.4108
B94: DIH | E94: =IFERROR(E93/E33*365,"") -> 114.01618 | F94: =IFERROR(F93/F33*365,"") -> 135.35736 | G94: =IFERROR(G93/G33*365,"") -> 130.60717 | H94: =IFERROR(AVERAGE(E94:G94),"") -> 126.66024 | I94: =IFERROR(AVERAGE(F94:H94),"") -> 130.87492 | J94: =IFERROR(AVERAGE(G94:I94),"") -> 129.38078 | K94: =IFERROR(AVERAGE(H94:J94),"") -> 128.97198 | L94: =IFERROR(AVERAGE(I94:K94),"") -> 129.74256 | M94: =IFERROR(AVERAGE(J94:L94),"") -> 129.36511 | N94: =IFERROR(AVERAGE(K94:M94),"") -> 129.35988 | O94: =IFERROR(AVERAGE(L94:N94),"") -> 129.48918 | ... Q94: =IFERROR(AVERAGE(N94:P94),"") -> 129.41793
B96: Prepaid expenses and Other Current Assets | E96: =+_xlfn.XLOOKUP($B96,Inputs!$B:$B,Inputs!O:O) -> 267 | F96: =+_xlfn.XLOOKUP($B96,Inputs!$B:$B,Inputs!P:P) -> 314 | G96: =+_xlfn.XLOOKUP($B96,Inputs!$B:$B,Inputs!Q:Q) -> 337.6 | H96: =IFERROR(AVERAGE(E96:G96)*(1+H31),"") -> 335.71768 | I96: =IFERROR(AVERAGE(F96:H96)*(1+I31),"") -> 370.67197 | J96: =IFERROR(AVERAGE(G96:I96)*(1+J31),"") -> 381.82181 | K96: =IFERROR(AVERAGE(H96:J96)*(1+K31),"") -> 375.79569 | L96: =IFERROR(AVERAGE(I96:K96)*(1+L31),"") -> 389.63596 | M96: =IFERROR(AVERAGE(J96:L96)*(1+M31),"") -> 396.18486 | N96: =IFERROR(AVERAGE(K96:M96)*(1+N31),"") -> 401.14491 | O96: =IFERROR(AVERAGE(L96:N96)*(1+O31),"") -> 409.89883 | ... Q96: =IFERROR(AVERAGE(N96:P96)*(1+Q31),"") -> 424.04862
B97: % of revenue | E97: =IFERROR(E96/E$30,"") -> 0.022224072 | F97: =IFERROR(F96/F$30,"") -> 0.025517045 | G97: =IFERROR(G96/G$30,"") -> 0.03581127 | H97: =IFERROR(AVERAGE(E97:G97),"") -> 0.027850796 | I97: =IFERROR(AVERAGE(F97:H97),"") -> 0.02972637 | J97: =IFERROR(AVERAGE(G97:I97),"") -> 0.031129478 | K97: =IFERROR(AVERAGE(H97:J97),"") -> 0.029568881 | L97: =IFERROR(AVERAGE(I97:K97),"") -> 0.030141577 | M97: =IFERROR(AVERAGE(J97:L97),"") -> 0.030279979 | N97: =IFERROR(AVERAGE(K97:M97),"") -> 0.029996812 | O97: =IFERROR(AVERAGE(L97:N97),"") -> 0.030139456 | ... Q97: =IFERROR(AVERAGE(N97:P97),"") -> 0.030091672
B99: Net PP&E (Property, Plant and Equipment) + ROU Assets | E99: =+E100+E101-E103 -> 2401.3 | F99: =+F100+F101-F103 -> 0 | G99: =+G100+G101-G103 -> 0 | H99: =IFERROR(H100+H101-H103,"") -> -397.936 | I99: =IFERROR(I100+I101-I103,"") -> -846.13132 | J99: =IFERROR(J100+J101-J103,"") -> -1337.8912 | K99: =IFERROR(K100+K101-K103,"") -> -1847.3545 | L99: =IFERROR(L100+L101-L103,"") -> -2375.1584 | M99: =IFERROR(M100+M101-M103,"") -> -2921.9633 | N99: =IFERROR(N100+N101-N103,"") -> -3488.4531 | O99: =IFERROR(O100+O101-O103,"") -> -4075.3366 | ... Q99: =IFERROR(Q100+Q101-Q103,"") -> -5313.2476
B100: Gross PP&E (Property, Plant and Equipment) + ROU Assets | E100: =+_xlfn.XLOOKUP("Gross PP&E (Property, Plant and Equipment)",Inputs!$B:$B,Inputs!O:O) -> 5549.5 | F100: =+_xlfn.XLOOKUP("Gross PP&E (Property, Plant and Equipment)",Inputs!$B:$B,Inputs!P:P) -> 0 | G100: =+_xlfn.XLOOKUP("Gross PP&E (Property, Plant and Equipment)",Inputs!$B:$B,Inputs!Q:Q) -> 0 | H100: =+IFERROR(G100-H134,"") -> 0 | I100: =+IFERROR(H100-I134,"") -> 0 | J100: =+IFERROR(I100-J134,"") -> 0 | K100: =+IFERROR(J100-K134,"") -> 0 | L100: =+IFERROR(K100-L134,"") -> 0 | M100: =+IFERROR(L100-M134,"") -> 0 | N100: =+IFERROR(M100-N134,"") -> 0 | O100: =+IFERROR(N100-O134,"") -> 0 | ... Q100: =+IFERROR(P100-Q134,"") -> 0
B101: Right-of-Use Assets | E101: =+_xlfn.XLOOKUP("Right-of-Use Assets",Inputs!$B:$B,Inputs!O:O) -> 0 | F101: =+_xlfn.XLOOKUP("Right-of-Use Assets",Inputs!$B:$B,Inputs!P:P) -> 0 | G101: =+_xlfn.XLOOKUP("Right-of-Use Assets",Inputs!$B:$B,Inputs!Q:Q) -> 0 | H101: =IFERROR(H102*H$30,"") -> 0 | I101: =IFERROR(I102*I$30,"") -> 0 | J101: =IFERROR(J102*J$30,"") -> 0 | K101: =IFERROR(K102*K$30,"") -> 0 | L101: =IFERROR(L102*L$30,"") -> 0 | M101: =IFERROR(M102*M$30,"") -> 0 | N101: =IFERROR(N102*N$30,"") -> 0 | O101: =IFERROR(O102*O$30,"") -> 0 | ... Q101: =IFERROR(Q102*Q$30,"") -> 0
B102: % of revenue | E102: =IFERROR(E101/E$30,"") -> 0 | F102: =IFERROR(F101/F$30,"") -> 0 | G102: =IFERROR(G101/G$30,"") -> 0 | H102: =IFERROR(AVERAGE(E102:G102),"") -> 0 | I102: =IFERROR(AVERAGE(F102:H102),"") -> 0 | J102: =IFERROR(AVERAGE(G102:I102),"") -> 0 | K102: =IFERROR(AVERAGE(H102:J102),"") -> 0 | L102: =IFERROR(AVERAGE(I102:K102),"") -> 0 | M102: =IFERROR(AVERAGE(J102:L102),"") -> 0 | N102: =IFERROR(AVERAGE(K102:M102),"") -> 0 | O102: =IFERROR(AVERAGE(L102:N102),"") -> 0 | ... Q102: =IFERROR(AVERAGE(N102:P102),"") -> 0
B103: Accumulated Depreciation | E103: =+_xlfn.XLOOKUP($B103,Inputs!$B:$B,Inputs!O:O) -> 3148.2 | F103: =+_xlfn.XLOOKUP($B103,Inputs!$B:$B,Inputs!P:P) -> 0 | G103: =+_xlfn.XLOOKUP($B103,Inputs!$B:$B,Inputs!Q:Q) -> 0 | H103: =+IFERROR(G103+H53,"") -> 397.936 | I103: =+IFERROR(H103+I53,"") -> 846.13132 | J103: =+IFERROR(I103+J53,"") -> 1337.8912 | K103: =+IFERROR(J103+K53,"") -> 1847.3545 | L103: =+IFERROR(K103+L53,"") -> 2375.1584 | M103: =+IFERROR(L103+M53,"") -> 2921.9633 | N103: =+IFERROR(M103+N53,"") -> 3488.4531 | O103: =+IFERROR(N103+O53,"") -> 4075.3366 | ... Q103: =+IFERROR(P103+Q53,"") -> 5313.2476
B105: Intangibles excl. Goodwill | E105: =+_xlfn.XLOOKUP($B105,Inputs!$B:$B,Inputs!O:O) -> -13647.7 | F105: =+_xlfn.XLOOKUP($B105,Inputs!$B:$B,Inputs!P:P) -> -15601.1 | G105: =+_xlfn.XLOOKUP($B105,Inputs!$B:$B,Inputs!Q:Q) -> -17324.3 | H105: =+G105+H106*H42 -> -17324.3 | I105: =+H105+I106*I42 -> -17324.3 | J105: =+I105+J106*J42 -> -17324.3 | K105: =+J105+K106*K42 -> -17324.3 | L105: =+K105+L106*L42 -> -17324.3 | M105: =+L105+M106*M42 -> -17324.3 | N105: =+M105+N106*N42 -> -17324.3 | O105: =+N105+O106*O42 -> -17324.3 | ... Q105: =+P105+Q106*Q42 -> -17324.3
B106: growing with % of R&D | E106: =IFERROR((E105-Inputs!N45)/E42,"") -> -1.1740076 | F106: =IFERROR((F105-E105)/F42,"") -> -1.1766052 | G106: =IFERROR((G105-F105)/G42,"") -> -1.1581423
B108: Liabilities
B110: Accounts Payable | E110: =+_xlfn.XLOOKUP($B110,Inputs!$B:$B,Inputs!O:O) -> 582.2 | F110: =+_xlfn.XLOOKUP($B110,Inputs!$B:$B,Inputs!P:P) -> 493 | G110: =+_xlfn.XLOOKUP($B110,Inputs!$B:$B,Inputs!Q:Q) -> 487.5 | H110: =+IFERROR(H111*H33/365,"") -> 474.0274 | I110: =+IFERROR(I111*I33/365,"") -> 513.45104 | J110: =+IFERROR(J111*J33/365,"") -> 565.74831 | K110: =+IFERROR(K111*K33/365,"") -> 579.55668 | L110: =+IFERROR(L111*L33/365,"") -> 594.89495 | M110: =+IFERROR(M111*M33/365,"") -> 618.51044 | N110: =+IFERROR(N111*N33/365,"") -> 640.06416 | O110: =+IFERROR(O111*O33/365,"") -> 662.81186 | ... Q110: =+IFERROR(Q111*Q33/365,"") -> 711.65703
B111: DPO | E111: =IFERROR(E110/E$33*365,"") -> 47.417829 | F111: =IFERROR(F110/F$33*365,"") -> 40.635232 | G111: =IFERROR(G110/G$33*366,"") -> 44.10129 | H111: =IFERROR(AVERAGE(E111:G111),"") -> 44.051451 | I111: =IFERROR(AVERAGE(F111:H111),"") -> 42.929324 | J111: =IFERROR(AVERAGE(G111:I111),"") -> 43.694022 | K111: =IFERROR(AVERAGE(H111:J111),"") -> 43.558266 | L111: =IFERROR(AVERAGE(I111:K111),"") -> 43.393871 | M111: =IFERROR(AVERAGE(J111:L111),"") -> 43.548719 | N111: =IFERROR(AVERAGE(K111:M111),"") -> 43.500285 | O111: =IFERROR(AVERAGE(L111:N111),"") -> 43.480958 | ... Q111: =IFERROR(AVERAGE(N111:P111),"") -> 43.497077
B113: Accrued Expenses and Other Current Liabilities | E113: =+_xlfn.XLOOKUP($B113,Inputs!$B:$B,Inputs!O:O) -> 1860.5 | F113: =+_xlfn.XLOOKUP($B113,Inputs!$B:$B,Inputs!P:P) -> 1661.7 | G113: =+_xlfn.XLOOKUP($B113,Inputs!$B:$B,Inputs!Q:Q) -> 1553.5 | H113: =IFERROR(AVERAGE(E113:G113)*(1+H31),"") -> 1854.9992 | I113: =IFERROR(AVERAGE(F113:H113)*(1+I31),"") -> 1903.5218 | J113: =IFERROR(AVERAGE(G113:I113)*(1+J31),"") -> 1942.7831 | K113: =IFERROR(AVERAGE(H113:J113)*(1+K31),"") -> 1968.8503 | L113: =IFERROR(AVERAGE(I113:K113)*(1+L31),"") -> 2008.1669 | M113: =IFERROR(AVERAGE(J113:L113)*(1+M31),"") -> 2044.3044 | N113: =IFERROR(AVERAGE(K113:M113)*(1+N31),"") -> 2079.3631 | O113: =IFERROR(AVERAGE(L113:N113)*(1+O31),"") -> 2117.5268 | ... Q113: =IFERROR(AVERAGE(N113:P113)*(1+Q31),"") -> 2193.6203
B114: growing with revenue | E114: =IFERROR(E113/E$30,"") -> 0.154861 | F114: =IFERROR(F113/F$30,"") -> 0.13503718 | G114: =IFERROR(G113/G$30,"") -> 0.16478912 | H114: =IFERROR(H113/H$30,"") -> 0.17946973 | I114: =IFERROR(I113/I$30,"") -> 0.16351261 | J114: =IFERROR(J113/J$30,"") -> 0.15210095 | K114: =IFERROR(K113/K$30,"") -> 0.14878548 | L114: =IFERROR(L113/L$30,"") -> 0.14648323 | ... Q114: =IFERROR(Q113/Q$30,"") -> 0.13407592
B116: Total Borrowings | E116: =+_xlfn.XLOOKUP($B116,Inputs!$B:$B,Inputs!O:O) -> 7095.8 | F116: =+_xlfn.XLOOKUP($B116,Inputs!$B:$B,Inputs!P:P) -> 6450.2 | G116: =+_xlfn.XLOOKUP($B116,Inputs!$B:$B,Inputs!Q:Q) | H116: =IFERROR(G116+H156-H158,"") | I116: =IFERROR(H116+I156-I158,"") | J116: =IFERROR(I116+J156-J158,"") | K116: =IFERROR(J116+K156-K158,"") | L116: =IFERROR(K116+L156-L158,"") | M116: =IFERROR(L116+M156-M158,"") | N116: =IFERROR(M116+N156-N158,"") | O116: =IFERROR(N116+O156-O158,"") | ... Q116: =IFERROR(P116+Q156-Q158,"")
B118: Total Leases | E118: =+_xlfn.XLOOKUP($B118,Inputs!$B:$B,Inputs!O:O) -> 0 | F118: =+_xlfn.XLOOKUP($B118,Inputs!$B:$B,Inputs!P:P) -> 499.1 | G118: =+_xlfn.XLOOKUP($B118,Inputs!$B:$B,Inputs!Q:Q) -> 399.6 | H118: =+IFERROR(H119*H30,"") -> 285.78035 | I118: =+IFERROR(I119*I30,"") -> 429.16588 | J118: =+IFERROR(J119*J30,"") -> 455.15415 | K118: =+IFERROR(K119*K30,"") -> 441.74887 | L118: =+IFERROR(L119*L30,"") -> 483.85381 | M118: =+IFERROR(M119*M30,"") -> 493.83384 | N118: =+IFERROR(N119*N30,"") -> 507.37536 | O118: =+IFERROR(O119*O30,"") -> 531.2282 | ... Q118: =+IFERROR(Q119*Q30,"") -> 567.35693
B119: % of revenues | E119: =IFERROR(E118/E$30,"") -> 0 | F119: =IFERROR(F118/F$30,"") -> 0.0405591 | G119: =IFERROR(G118/G$30,"") -> 0.042387984 | H119: =+IFERROR(AVERAGE(E119:G119),"") -> 0.027649028 | I119: =+IFERROR(AVERAGE(F119:H119),"") -> 0.03686537 | J119: =+IFERROR(AVERAGE(G119:I119),"") -> 0.035634127 | K119: =+IFERROR(AVERAGE(H119:J119),"") -> 0.033382842 | L119: =+IFERROR(AVERAGE(I119:K119),"") -> 0.035294113 | M119: =+IFERROR(AVERAGE(J119:L119),"") -> 0.034770361 | N119: =+IFERROR(AVERAGE(K119:M119),"") -> 0.034482439 | O119: =+IFERROR(AVERAGE(L119:N119),"") -> 0.034848971 | ... Q119: =+IFERROR(AVERAGE(N119:P119),"") -> 0.034677333
A121: x | B121: Cash Flow | E121: =E28 -> 2022 | F121: =F28 -> 2023 | G121: =G28 -> 2024 | H121: =H28 -> 2025 | I121: =I28 -> 2026 | J121: =J28 -> 2027 | K121: =K28 -> 2028 | L121: =L28 -> 2029 | ... Q121: =Q28 -> 2034
B123: D&A (Depreciation & Amortization) | E123: =+E50 -> 2297.5 | F123: =+F50 -> 2293.1 | G123: =+G50 -> 2104.3 | H123: =+H50 -> 1981.936 | I123: =+I50 -> 1982.1953 | J123: =+J50 -> 2021.7599 | K123: =+K50 -> 1972.4633 | L123: =+L50 -> 1654.8039 | ... Q123: =+Q50 -> 999.19506
B125: Stock Based Compensation | E125: =+_xlfn.XLOOKUP($B125,Inputs!$B:$B,Inputs!O:O) -> 323.5 | F125: =+_xlfn.XLOOKUP($B125,Inputs!$B:$B,Inputs!P:P) -> 299.8 | G125: =+_xlfn.XLOOKUP($B125,Inputs!$B:$B,Inputs!Q:Q) -> 262.7 | H125: =IFERROR(H126*H39,"") -> 287.71702 | I125: =IFERROR(I126*I39,"") -> 319.69425 | J125: =IFERROR(J126*J39,"") -> 354.08534 | K125: =IFERROR(K126*K39,"") -> 366.19415 | L125: =IFERROR(L126*L39,"") -> 378.63133 | M125: =IFERROR(M126*M39,"") -> 393.00551 | N125: =IFERROR(N126*N39,"") -> 406.90706 | O125: =IFERROR(O126*O39,"") -> 421.46008 | ... Q125: =IFERROR(Q126*Q39,"") -> 452.43891
B126: % of SG&A | E126: =+IFERROR(E125/E39,"") -> 0.25548886 | F126: =+IFERROR(F125/F39,"") -> 0.23539573 | G126: =+IFERROR(G125/G39,"") -> 0.24583567 | H126: =IFERROR(AVERAGE(E126:G126),"") -> 0.24557342 | I126: =IFERROR(AVERAGE(F126:H126),"") -> 0.24226827 | J126: =IFERROR(AVERAGE(G126:I126),"") -> 0.24455912 | K126: =IFERROR(AVERAGE(H126:J126),"") -> 0.24413361 | L126: =IFERROR(AVERAGE(I126:K126),"") -> 0.24365367 | M126: =IFERROR(AVERAGE(J126:L126),"") -> 0.24411547 | N126: =IFERROR(AVERAGE(K126:M126),"") -> 0.24396758 | O126: =IFERROR(AVERAGE(L126:N126),"") -> 0.24391224 | ... Q126: =IFERROR(AVERAGE(N126:P126),"") -> 0.24395942
B128: Changes in Net Working Capital | E128: =+_xlfn.XLOOKUP($B128,Inputs!$B:$B,Inputs!O:O) -> -106.3 | F128: =+_xlfn.XLOOKUP($B128,Inputs!$B:$B,Inputs!P:P) -> -289.5 | G128: =+_xlfn.XLOOKUP($B128,Inputs!$B:$B,Inputs!Q:Q) -> 57.1 | H128: =IFERROR(-((H90+H93+H96-H110-H113)-(G90+G93+G96-G110-G113)),"") -> 293.40313 | I128: =IFERROR(-((I90+I93+I96-I110-I113)-(H90+H93+H96-H110-H113)),"") -> -279.03482 | J128: =IFERROR(-((J90+J93+J96-J110-J113)-(I90+I93+I96-I110-I113)),"") -> -237.24197 | K128: =IFERROR(-((K90+K93+K96-K110-K113)-(J90+J93+J96-J110-J113)),"") -> -37.161577 | L128: =IFERROR(-((L90+L93+L96-L110-L113)-(K90+K93+K96-K110-K113)),"") -> -80.460737 | M128: =IFERROR(-((M90+M93+M96-M110-M113)-(L90+L93+L96-L110-L113)),"") -> -83.95697 | N128: =IFERROR(-((N90+N93+N96-N110-N113)-(M90+M93+M96-M110-M113)),"") -> -78.15925 | O128: =IFERROR(-((O90+O93+O96-O110-O113)-(N90+N93+N96-N110-N113)),"") -> -90.158426 | ... Q128: =IFERROR(-((Q90+Q93+Q96-Q110-Q113)-(P90+P93+P96-P110-P113)),"") -> -93.894656
B130: Other Operating Adjustments | E130: =+_xlfn.XLOOKUP($B130,Inputs!$B:$B,Inputs!O:O) -> -24.2 | F130: =+_xlfn.XLOOKUP($B130,Inputs!$B:$B,Inputs!P:P) -> 107.4 | G130: =+_xlfn.XLOOKUP($B130,Inputs!$B:$B,Inputs!Q:Q) -> 784.1 | H130: =IFERROR(AVERAGE(E130:G130)*(1+H31),"") -> 316.96924 | I130: =IFERROR(AVERAGE(F130:H130)*(1+I31),"") -> 453.69964 | J130: =IFERROR(AVERAGE(G130:I130)*(1+J31),"") -> 568.6308 | K130: =IFERROR(AVERAGE(H130:J130)*(1+K31),"") -> 462.50482 | L130: =IFERROR(AVERAGE(I130:K130)*(1+L31),"") -> 512.76311 | M130: =IFERROR(AVERAGE(J130:L130)*(1+M31),"") -> 533.1597 | N130: =IFERROR(AVERAGE(K130:M130)*(1+N31),"") -> 520.91034 | O130: =IFERROR(AVERAGE(L130:N130)*(1+O31),"") -> 541.07971 | ... Q130: =IFERROR(AVERAGE(N130:P130)*(1+Q31),"") -> 556.97033
B132: Operating Cash Flow | E132: =+_xlfn.XLOOKUP($B132,Inputs!$B:$B,Inputs!O:O) -> 4475.4 | F132: =+_xlfn.XLOOKUP($B132,Inputs!$B:$B,Inputs!P:P) -> 4817.6 | G132: =+_xlfn.XLOOKUP($B132,Inputs!$B:$B,Inputs!Q:Q) -> 3852.5 | H132: =IFERROR(H81+H123+H125+H128+H130,"") -> 4250.1618 | I132: =IFERROR(I81+I123+I125+I128+I130,"") -> 4281.2304 | J132: =IFERROR(J81+J123+J125+J128+J130,"") -> 4838.8398 | K132: =IFERROR(K81+K123+K125+K128+K130,"") -> 5133.5801 | L132: =IFERROR(L81+L123+L125+L128+L130,"") -> 5269.5996 | M132: =IFERROR(M81+M123+M125+M128+M130,"") -> 5414.1463 | N132: =IFERROR(N81+N123+N125+N128+N130,"") -> 5560.7938 | O132: =IFERROR(O81+O123+O125+O128+O130,"") -> 5725.1563 | ... Q132: =IFERROR(Q81+Q123+Q125+Q128+Q130,"") -> 6086.5928
B134: Net CapEx | E134: =+_xlfn.XLOOKUP($B134,Inputs!$B:$B,Inputs!O:O) -> -699 | F134: =+_xlfn.XLOOKUP($B134,Inputs!$B:$B,Inputs!P:P) -> -1261 | G134: =+_xlfn.XLOOKUP($B134,Inputs!$B:$B,Inputs!Q:Q) -> -730 | H134: =IFERROR(H136+H138,"") -> 0 | I134: =IFERROR(I136+I138,"") -> 0 | J134: =IFERROR(J136+J138,"") -> 0 | K134: =IFERROR(K136+K138,"") -> 0 | L134: =IFERROR(L136+L138,"") -> 0 | M134: =IFERROR(M136+M138,"") -> 0 | N134: =IFERROR(N136+N138,"") -> 0 | O134: =IFERROR(O136+O138,"") -> 0 | ... Q134: =IFERROR(Q136+Q138,"") -> 0
B136: Acquisition of Fixed & Intangibles | E136: =+_xlfn.XLOOKUP($B136,Inputs!$B:$B,Inputs!O:O) -> #N/A | F136: =+_xlfn.XLOOKUP($B136,Inputs!$B:$B,Inputs!P:P) -> #N/A | G136: =+_xlfn.XLOOKUP($B136,Inputs!$B:$B,Inputs!Q:Q) -> #N/A | H136: =+H19*H18 -> 0 | I136: =+I19*I18 -> 0 | J136: =+J19*J18 -> 0 | K136: =+K19*K18 -> 0 | L136: =+L19*L18 -> 0 | M136: =+M19*M18 -> 0 | N136: =+N19*N18 -> 0 | O136: =+O19*O18 -> 0 | ... Q136: =+Q19*Q18 -> 0
B138: Disposal of Fixed & Intangibles | E138: =+_xlfn.XLOOKUP($B138,Inputs!$B:$B,Inputs!O:O) -> 0 | F138: =+_xlfn.XLOOKUP($B138,Inputs!$B:$B,Inputs!P:P) -> 0 | G138: =+_xlfn.XLOOKUP($B138,Inputs!$B:$B,Inputs!Q:Q) -> 0 | H138: =IFERROR(H139*G100,"") -> 0 | I138: =IFERROR(I139*H100,"") -> 0 | J138: =IFERROR(J139*I100,"") -> 0 | K138: =IFERROR(K139*J100,"") -> 0 | L138: =IFERROR(L139*K100,"") -> 0 | M138: =IFERROR(M139*L100,"") -> 0 | N138: =IFERROR(N139*M100,"") -> 0 | O138: =IFERROR(O139*N100,"") -> 0 | ... Q138: =IFERROR(Q139*P100,"") -> 0
B139: Disposal Rate (% Gross PP&E) | E139: =IFERROR(E138/E100,"") -> 0 | F139: =IFERROR(F138/F100,"") | G139: =IFERROR(G138/G100,"") | H139: =IFERROR(AVERAGE(E139:G139),"") -> 0 | I139: =IFERROR(AVERAGE(F139:H139),"") -> 0 | J139: =IFERROR(AVERAGE(G139:I139),"") -> 0 | K139: =IFERROR(AVERAGE(H139:J139),"") -> 0 | L139: =IFERROR(AVERAGE(I139:K139),"") -> 0 | M139: =IFERROR(AVERAGE(J139:L139),"") -> 0 | N139: =IFERROR(AVERAGE(K139:M139),"") -> 0 | O139: =IFERROR(AVERAGE(L139:N139),"") -> 0 | ... Q139: =IFERROR(AVERAGE(N139:P139),"") -> 0
B141: Net Cash from Investments & Acquisitions | E141: =+_xlfn.XLOOKUP($B141,Inputs!$B:$B,Inputs!O:O) -> 0 | F141: =+_xlfn.XLOOKUP($B141,Inputs!$B:$B,Inputs!P:P) -> 0 | G141: =+_xlfn.XLOOKUP($B141,Inputs!$B:$B,Inputs!Q:Q) -> 0 | H141: 0 | I141: 0 | J141: 0 | K141: 0 | L141: 0 | M141: 0 | N141: 0 | O141: 0 | P141: 0 | Q141: 0
B143: Other Investing Inflows (Outflows) | E143: =+_xlfn.XLOOKUP($B143,Inputs!$B:$B,Inputs!O:O) -> 41.6 | F143: =+_xlfn.XLOOKUP($B143,Inputs!$B:$B,Inputs!P:P) -> -5.4 | G143: =+_xlfn.XLOOKUP($B143,Inputs!$B:$B,Inputs!Q:Q) -> -374.9 | H143: =IFERROR(AVERAGE(E143:G143)*(1+H31),"") -> -123.78356 | I143: =IFERROR(AVERAGE(F143:H143)*(1+I31),"") -> -189.24977 | J143: =IFERROR(AVERAGE(G143:I143)*(1+J31),"") -> -251.60015 | K143: =IFERROR(AVERAGE(H143:J143)*(1+K31),"") -> -194.98676 | L143: =IFERROR(AVERAGE(I143:K143)*(1+L31),"") -> -219.5756 | M143: =IFERROR(AVERAGE(J143:L143)*(1+M31),"") -> -230.04812 | N143: =IFERROR(AVERAGE(K143:M143)*(1+N31),"") -> -222.60549 | O143: =IFERROR(AVERAGE(L143:N143)*(1+O31),"") -> -232.14315 | ... Q143: =IFERROR(AVERAGE(N143:P143)*(1+Q31),"") -> -238.70538
B145: Investing Cash Flow | E145: =+_xlfn.XLOOKUP($B145,Inputs!$B:$B,Inputs!O:O) -> -657.4 | F145: =+_xlfn.XLOOKUP($B145,Inputs!$B:$B,Inputs!P:P) -> -1266.4 | G145: =+_xlfn.XLOOKUP($B145,Inputs!$B:$B,Inputs!Q:Q) -> -1104.9 | H145: =IFERROR(+H134+H141+H143,"") -> -123.78356 | I145: =IFERROR(+I134+I141+I143,"") -> -189.24977 | J145: =IFERROR(+J134+J141+J143,"") -> -251.60015 | K145: =IFERROR(+K134+K141+K143,"") -> -194.98676 | L145: =IFERROR(+L134+L141+L143,"") -> -219.5756 | M145: =IFERROR(+M134+M141+M143,"") -> -230.04812 | N145: =IFERROR(+N134+N141+N143,"") -> -222.60549 | O145: =IFERROR(+O134+O141+O143,"") -> -232.14315 | ... Q145: =IFERROR(+Q134+Q141+Q143,"") -> -238.70538
B147: Dividends | E147: =+_xlfn.XLOOKUP($B147,Inputs!$B:$B,Inputs!O:O) -> -1544.6 | F147: =+_xlfn.XLOOKUP($B147,Inputs!$B:$B,Inputs!P:P) -> -1679.1 | G147: =+_xlfn.XLOOKUP($B147,Inputs!$B:$B,Inputs!Q:Q) -> -1795.5 | H147: =+IFERROR(H148*_xlfn.XLOOKUP("Net Income",$B:$B,$H:$H),"") -> 0 | I147: =+IFERROR(I148*_xlfn.XLOOKUP("Net Income",$B:$B,$H:$H),"") -> 0 | J147: =+IFERROR(J148*_xlfn.XLOOKUP("Net Income",$B:$B,$H:$H),"") -> 0 | K147: =+IFERROR(K148*_xlfn.XLOOKUP("Net Income",$B:$B,$H:$H),"") -> 0 | L147: =+IFERROR(L148*_xlfn.XLOOKUP("Net Income",$B:$B,$H:$H),"") -> 0 | M147: =+IFERROR(M148*_xlfn.XLOOKUP("Net Income",$B:$B,$H:$H),"") -> 0 | N147: =+IFERROR(N148*_xlfn.XLOOKUP("Net Income",$B:$B,$H:$H),"") -> 0 | O147: =+IFERROR(O148*_xlfn.XLOOKUP("Net Income",$B:$B,$H:$H),"") -> 0 | ... Q147: =+IFERROR(Q148*_xlfn.XLOOKUP("Net Income",$B:$B,$H:$H),"") -> 0
B148: Dividend payout | E148: =IFERROR(-E147/E$81,"") -> 0.77817522 | F148: =IFERROR(-F147/F$81,"") -> 0.69764833 | G148: =IFERROR(-G147/G$81,"") -> 2.7867453
B150: Increase (Repurchase) of Shares | E150: =+_xlfn.XLOOKUP($B150,Inputs!$B:$B,Inputs!O:O) -> -2577 | F150: =+_xlfn.XLOOKUP($B150,Inputs!$B:$B,Inputs!P:P) -> -2964 | G150: =+_xlfn.XLOOKUP($B150,Inputs!$B:$B,Inputs!Q:Q) -> -615.6 | H150: =IFERROR(-H151*_xlfn.XLOOKUP("Net Income",$B:$B,H:H),"") -> 0 | I150: =IFERROR(-I151*_xlfn.XLOOKUP("Net Income",$B:$B,I:I),"") -> 0 | J150: =IFERROR(-J151*_xlfn.XLOOKUP("Net Income",$B:$B,J:J),"") -> 0 | K150: =IFERROR(-K151*_xlfn.XLOOKUP("Net Income",$B:$B,K:K),"") -> 0 | L150: =IFERROR(-L151*_xlfn.XLOOKUP("Net Income",$B:$B,L:L),"") -> 0 | M150: =IFERROR(-M151*_xlfn.XLOOKUP("Net Income",$B:$B,M:M),"") -> 0 | N150: =IFERROR(-N151*_xlfn.XLOOKUP("Net Income",$B:$B,N:N),"") -> 0 | O150: =IFERROR(-O151*_xlfn.XLOOKUP("Net Income",$B:$B,O:O),"") -> 0 | P150: =IFERROR(-P151*_xlfn.XLOOKUP("Net Income",$B:$B,P:P),"") -> 0 | Q150: =IFERROR(-Q151*_xlfn.XLOOKUP("Net Income",$B:$B,Q:Q),"") -> 0
...

Sheet Inputs
B2: Inputs
B3: in millions of USD
A4: x | B4: Income Statement | G4: 2014 | H4: =+G4+1 -> 2015 | I4: =+H4+1 -> 2016 | J4: =+I4+1 -> 2017 | K4: =+J4+1 -> 2018 | L4: =+K4+1 -> 2019 | M4: =+L4+1 -> 2020 | N4: =+M4+1 -> 2021 | O4: =+N4+1 -> 2022 | ... Q4: =+P4+1 -> 2024 | R4: ="CAGR "&$G$4&" - "&$Q$4 -> CAGR 2014 - 2024
B6: Revenue (Sales) | H6: 3435.1 | I6: 3421.4 | J6: 5107.5 | K6: 6224.7 | L6: 5991.1 | M6: 5603.1 | N6: 7318.3 | O6: 12014 | P6: 12305.5 | Q6: 9427.2 | R6: =IFERROR((Q6/H6)^(1/COUNT($H$4:$Q$4))-1,"") -> 0.1062272
B7: COGS (Cost of Goods Sold) | H7: 1175.8 | I7: 1194.2 | J7: 2045.9 | K7: 1974.3 | L7: 1977.3 | M7: 1912.6 | N7: 2793.3 | O7: 4481.5 | P7: 4428.3 | Q7: 4045.8 | R7: =IFERROR((Q7/H7)^(1/COUNT($H$4:$Q$4))-1,"") -> 0.13153266
B8: Gross Profit | G8: =G6-G7 -> 0 | H8: =H6-H7 -> 2259.3 | I8: =I6-I7 -> 2227.2 | J8: =J6-J7 -> 3061.6 | K8: =K6-K7 -> 4250.4 | L8: =L6-L7 -> 4013.8 | M8: =M6-M7 -> 3690.5 | N8: =N6-N7 -> 4525 | ... Q8: =Q6-Q7 -> 5381.4 | R8: =IFERROR((Q8/H8)^(1/COUNT($H$4:$Q$4))-1,"") -> 0.09066691
B9: SG&A (Selling, General & Administrative) | H9: 479 | I9: 461.4 | J9: 691 | K9: 695.5 | L9: 648.1 | M9: 659.9 | N9: 915.4 | O9: 1266.2 | P9: 1273.6 | Q9: 1068.6 | R9: =IFERROR((Q9/H9)^(1/COUNT($H$4:$Q$4))-1,"") -> 0.083547528
B10: R&D (Research & Development) | H10: 637.5 | I10: 653.8 | J10: 968.6 | K10: 1165 | L10: 1130.3 | M10: 1050.5 | N10: 1296.1 | O10: 1700.5 | P10: 1660.2 | Q10: 1487.9 | R10: =IFERROR((Q10/H10)^(1/COUNT($H$4:$Q$4))-1,"") -> 0.088452185
B11: Other Operating (Income) Expenses | H11: 223.7 | I11: 0 | J11: 0 | R11: =IFERROR((Q11/H11)^(1/COUNT($H$4:$Q$4))-1,"") -> -1
B12: EBITDA | G12: =+G8-G9-G10-G11 -> 0 | H12: =+H8-H9-H10-H11 -> 919.1 | I12: =+I8-I9-I10-I11 -> 1112 | J12: =+J8-J9-J10-J11 -> 1402 | K12: =+K8-K9-K10-K11 -> 2389.9 | L12: =+L8-L9-L10-L11 -> 2235.4 | M12: =+M8-M9-M10-M11 -> 1980.1 | N12: =+N8-N9-N10-N11 -> 2313.5 | ... Q12: =+Q8-Q9-Q10-Q11 -> 2824.9 | R12: =IFERROR((Q12/H12)^(1/COUNT($H$4:$Q$4))-1,"") -> 0.11882982
B13: D&A (Depreciation & Amortization) | G13: =+SUM(G14:G15) -> 0 | H13: =+SUM(H14:H15) -> 218.4 | I13: =+SUM(I14:I15) -> 134.5 | J13: =+SUM(J14:J15) -> 194.7 | K13: =+SUM(K14:K15) -> 799 | L13: =+SUM(L14:L15) -> 811.3 | M13: =+SUM(M14:M15) -> 810.9 | N13: =+SUM(N14:N15) -> 1074.7 | ... Q13: =+SUM(Q14:Q15) -> 2104.3 | R13: =IFERROR((Q13/H13)^(1/COUNT($H$4:$Q$4))-1,"") -> 0.25425402
B14: Depreciation Expense | H14: 130.1 | I14: 134.5 | J14: 194.7 | K14: 228.5 | L14: 240.7 | M14: 233.8 | N14: 231.3 | O14: 283.3 | P14: 334.7 | Q14: 362.8 | R14: =IFERROR((Q14/H14)^(1/COUNT($H$4:$Q$4))-1,"") -> 0.10799806
B15: Amortization Expense | H15: 88.3 | K15: 570.5 | L15: 570.6 | M15: 577.1 | N15: 843.4 | O15: 2014.2 | P15: 1958.4 | Q15: 1741.5 | R15: =IFERROR((Q15/H15)^(1/COUNT($H$4:$Q$4))-1,"") -> 0.34739918
B16: Operating Income (EBIT) | G16: =+G12-G13 -> 0 | H16: =+H12-H13 -> 700.7 | I16: =+I12-I13 -> 977.5 | J16: =+J12-J13 -> 1207.3 | K16: =+K12-K13 -> 1590.9 | L16: =+L12-L13 -> 1424.1 | M16: =+M12-M13 -> 1169.2 | N16: =+N12-N13 -> 1238.8 | ... Q16: =+Q12-Q13 -> 720.6 | R16: =IFERROR((Q16/H16)^(1/COUNT($H$4:$Q$4))-1,"") -> 0.0028043612
B17: Net Interest Expense (Income) | G17: =+G18-G19 -> 0 | H17: =+H18-H19 -> -8.6 | I17: =+I18-I19 -> -21.2 | J17: =+J18-J19 -> -30.3 | K17: =+K18-K19 -> -9.4 | L17: =+L18-L19 -> -10.2 | M17: =+M18-M19 -> -4.3 | N17: =+N18-N19 -> -1.2 | ... Q17: =+Q18-Q19 -> -78.8 | R17: =IFERROR((Q17/H17)^(1/COUNT($H$4:$Q$4))-1,"") -> 0.24796607
B18: Interest Expense | H18: 27 | I18: 88.8 | J18: 250.8 | K18: 253.6 | L18: 229.1 | M18: 193.3 | N18: 184.8 | O18: 200.4 | P18: 264.6 | Q18: 322.2 | R18: =IFERROR((Q18/H18)^(1/COUNT($H$4:$Q$4))-1,"") -> 0.2813748
B19: Interest Income | H19: 35.6 | I19: 110 | J19: 281.1 | K19: 263 | L19: 239.3 | M19: 197.6 | N19: 186 | O19: 207.3 | P19: 305.9 | Q19: 401 | R19: =IFERROR((Q19/H19)^(1/COUNT($H$4:$Q$4))-1,"") -> 0.27400003
B20: FX (Gain) Loss | H20: -12.9 | I20: -6 | J20: 1.6 | K20: -6.2 | L20: -1.4 | M20: 3.2 | N20: 1.1 | O20: -46.3 | P20: -0.4 | Q20: 1 | R20: =IFERROR((Q20/H20)^(1/COUNT($H$4:$Q$4))-1,"")
B21: Other Non-Operating (Income) Expenses | H21: 2.3 | I21: 3.7 | J21: 6.1 | K21: 0.1 | L21: 6 | M21: -2.4 | N21: -35.3 | O21: -13.6 | P21: -8.2 | Q21: 12 | R21: =IFERROR((Q21/H21)^(1/COUNT($H$4:$Q$4))-1,"") -> 0.17962873
B22: Pre-Tax Income (EBT) | G22: =+G16-G17-G20-G21 -> 0 | H22: =+H16-H17-H20-H21 -> 719.9 | I22: =+I16-I17-I20-I21 -> 1001 | J22: =+J16-J17-J20-J21 -> 1229.9 | K22: =+K16-K17-K20-K21 -> 1606.4 | L22: =+L16-L17-L20-L21 -> 1429.7 | M22: =+M16-M17-M20-M21 -> 1172.7 | N22: =+N16-N17-N20-N21 -> 1274.2 | ... Q22: =+Q16-Q17-Q20-Q21 -> 786.4 | R22: =IFERROR((Q22/H22)^(1/COUNT($H$4:$Q$4))-1,"") -> 0.0088744722
B23: Tax Expense (Benefits) | H23: 113.2 | I23: 95.3 | J23: 101.2 | L23: 122.7 | M23: 90.9 | N23: -61.7 | O23: 350.2 | P23: 293.4 | Q23: 142.1 | R23: =IFERROR((Q23/H23)^(1/COUNT($H$4:$Q$4))-1,"") -> 0.022997954
B24: Net Income | G24: =+G22-G23 -> 0 | H24: =+H22-H23 -> 606.7 | I24: =+I22-I23 -> 905.7 | J24: =+J22-J23 -> 1128.7 | K24: =+K22-K23 -> 1606.4 | L24: =+L22-L23 -> 1307 | M24: =+M22-M23 -> 1081.8 | N24: =+N22-N23 -> 1335.9 | ... Q24: =+Q22-Q23 -> 644.3 | R24: =IFERROR((Q24/H24)^(1/COUNT($H$4:$Q$4))-1,"") -> 0.0060311165
B25: EPS basic | H25: 2.23 | I25: 2.79 | J25: 2.09 | K25: 4.05 | L25: 3.68 | M25: 3.31 | N25: 3.5 | O25: 5.29 | P25: 6.6 | Q25: 3.3 | R25: =IFERROR((Q25/H25)^(1/COUNT($H$4:$Q$4))-1,"") -> 0.039970231
B26: EPS diluted | H26: 2.2 | I26: 2.76 | J26: 2.07 | K26: 4 | L26: 3.65 | M26: 3.28 | N26: 3.46 | O26: 5.25 | P26: 6.55 | Q26: 3.28 | R26: =IFERROR((Q26/H26)^(1/COUNT($H$4:$Q$4))-1,"") -> 0.040746877
B27: Basic Weighted Average Shares | H27: 312.7 | I27: 308.7 | J27: 346.4 | K27: 370.4 | L27: 369.1 | M27: 368.6 | N27: 397.5 | O27: 519.2 | P27: 502.2 | Q27: 496.2 | R27: =IFERROR((Q27/H27)^(1/COUNT($H$4:$Q$4))-1,"") -> 0.047256074
B28: Diluted Weighted Average Shares | H28: 316.9 | I28: 312.3 | J28: 350.5 | K28: 374.9 | L28: 372.9 | M28: 372 | N28: 401.3 | O28: 523.2 | P28: 506 | Q28: 498.7 | R28: =IFERROR((Q28/H28)^(1/COUNT($H$4:$Q$4))-1,"") -> 0.0463855
A30: x | B30: Balance Sheet | G30: 2014 | H30: =+G30+1 -> 2015 | I30: =+H30+1 -> 2016 | J30: =+I30+1 -> 2017 | K30: =+J30+1 -> 2018 | L30: =+K30+1 -> 2019 | M30: =+L30+1 -> 2020 | N30: =+M30+1 -> 2021 | O30: =+N30+1 -> 2022 | ... Q30: =+P30+1 -> 2024 | R30: ="CAGR "&$G$4&" - "&$Q$4 -> CAGR 2014 - 2024
B32: Cash & Cash Equivalents & ST Investments | G32: =+SUM(G33:G34) -> 0 | H32: =+SUM(H33:H34) -> 3029 | I32: =+SUM(I33:I34) -> 4055.8 | J32: =+SUM(J33:J34) -> 1047.8 | K32: =+SUM(K33:K34) -> 816.6 | L32: =+SUM(L33:L34) -> 648.3 | M32: =+SUM(M33:M34) -> 1055.9 | N32: =+SUM(N33:N34) -> 1978 | ... Q32: =+SUM(Q33:Q34) -> 2363.1 | R32: =IFERROR((Q32/H32)^(1/COUNT($G$4:$Q$4))-1,"") -> -0.022316156
B33: Cash & Cash Equivalents | H33: 884.4 | I33: 921.1 | J33: 1047.8 | K33: 816.6 | L33: 648.3 | M33: 1055.9 | N33: 1978 | O33: 1470.6 | P33: 958.1 | Q33: 1991.3 | R33: =IFERROR((Q33/H33)^(1/COUNT($G$4:$Q$4))-1,"") -> 0.076575172
B34: Short-Term Investments | H34: 2144.6 | I34: 3134.7 | J34: 0 | Q34: 371.8 | R34: =IFERROR((Q34/H34)^(1/COUNT($G$4:$Q$4))-1,"") -> -0.14726355
B35: Accounts Receivable | H35: 466.5 | I35: 477.6 | J35: 689 | K35: 639.7 | L35: 635.1 | M35: 737.5 | N35: 1459.1 | O35: 1800.5 | P35: 1469.7 | Q35: 1336.3 | R35: =IFERROR((Q35/H35)^(1/COUNT($G$4:$Q$4))-1,"") -> 0.10039906
B36: Inventory | H36: 412.3 | I36: 376.6 | J36: 550.8 | K36: 586.8 | L36: 609.9 | M36: 608.3 | N36: 1200.6 | O36: 1399.9 | P36: 1642.2 | Q36: 1447.7 | R36: =IFERROR((Q36/H36)^(1/COUNT($G$4:$Q$4))-1,"") -> 0.12095389
B37: Prepaid expenses and Other Current Assets | G37: =+G38-G32-G35-G36 -> 0 | H37: =+H38-H32-H35-H36 -> 171.7 | I37: =+I38-I32-I35-I36 -> 64.9 | J37: =+J38-J32-J35-J36 -> 63.7 | K37: =+K38-K32-K35-K36 -> 69 | L37: =+L38-L32-L35-L36 -> 91.8 | M37: =+M38-M32-M35-M36 -> 116 | N37: =+N38-N32-N35-N36 -> 740.6 | ... Q37: =+Q38-Q32-Q35-Q36 -> 337.6 | R37: =IFERROR((Q37/H37)^(1/COUNT($G$4:$Q$4))-1,"") -> 0.063393083
B38: Current Assets | H38: 4079.5 | I38: 4974.9 | J38: 2351.3 | K38: 2112.1 | L38: 1985.1 | M38: 2517.7 | N38: 5378.3 | O38: 4938 | P38: 4384 | Q38: 5484.7 | R38: =IFERROR((Q38/H38)^(1/COUNT($G$4:$Q$4))-1,"") -> 0.027273286
B39: Net PP&E (Property, Plant and Equipment) | G39: =+G40-G41 -> 0 | H39: =+H40-H41 -> 644.1 | I39: =+I40-I41 -> -2040.8 | J39: =+J40-J41 -> 1107.3 | K39: =+K40-K41 -> 1154.3 | L39: =+L40-L41 -> 1220 | M39: =+M40-M41 -> 1120.6 | N39: =+N40-N41 -> 1979.1 | ... Q39: =+Q40-Q41 -> 0 | R39: =IFERROR((Q39/H39)^(1/COUNT($G$4:$Q$4))-1,"") -> -1
B40: Gross PP&E (Property, Plant and Equipment) | H40: 2602.1 | J40: 3304.4 | K40: 3527.8 | L40: 3811.3 | M40: 3885.7 | N40: 4935.3 | O40: 5549.5 | R40: =IFERROR((Q40/H40)^(1/COUNT($G$4:$Q$4))-1,"") -> -1
B41: Accumulated Depreciation | H41: 1958 | I41: 2040.8 | J41: 2197.1 | K41: 2373.5 | L41: 2591.3 | M41: 2765.1 | N41: 2956.2 | O41: 3148.2 | R41: =IFERROR((Q41/H41)^(1/COUNT($G$4:$Q$4))-1,"") -> -1
B42: Right-of-Use Assets | R42: =IFERROR((Q42/H42)^(1/COUNT($G$4:$Q$4))-1,"")
B43: Intangibles | H43: 583.5 | I43: 549.4 | J43: 5319.4 | K43: 4778.2 | L43: 4217.2 | M43: 3650.3 | N43: 15267.2 | O43: 13265.4 | P43: 11312 | Q43: 9585.5 | R43: =IFERROR((Q43/H43)^(1/COUNT($G$4:$Q$4))-1,"") -> 0.28975351
B44: Goodwill | H44: 1636.5 | I44: 1679.1 | J44: 12217.5 | K44: 12252.6 | L44: 12256.9 | M44: 12278.4 | N44: 26918.5 | O44: 26913.1 | P44: 26913.1 | Q44: 26909.8 | R44: =IFERROR((Q44/H44)^(1/COUNT($G$4:$Q$4))-1,"") -> 0.28986706
B45: Intangibles excl. Goodwill | G45: =+G43-G44 -> 0 | H45: =+H43-H44 -> -1053 | I45: =+I43-I44 -> -1129.7 | J45: =+J43-J44 -> -6898.1 | K45: =+K43-K44 -> -7474.4 | L45: =+L43-L44 -> -8039.7 | M45: =+M43-M44 -> -8628.1 | N45: =+N43-N44 -> -11651.3 | ... Q45: =+Q43-Q44 -> -17324.3 | R45: =IFERROR((Q45/H45)^(1/COUNT($G$4:$Q$4))-1,"") -> 0.28992993
B46: Other Non-Current Assets | G46: =+G47-G39-G42-G43 -> 0 | H46: =+H47-H39-H42-H43 -> 1751.7 | I46: =+I47-I39-I42-I43 -> 4486.8 | J46: =+J47-J39-J42-J43 -> 12363 | K46: =+K47-K39-K42-K43 -> 12393.7 | L46: =+L47-L39-L42-L43 -> 12750.3 | M46: =+M47-M39-M42-M43 -> 14180 | N46: =+N47-N39-N42-N43 -> 29697.5 | ... Q46: =+Q47-Q39-Q42-Q43 -> 33158.1 | R46: =IFERROR((Q46/H46)^(1/COUNT($G$4:$Q$4))-1,"") -> 0.30647986
B47: Non-Current Assets | H47: =H48-H38 -> 2979.3 | I47: =I48-I38 -> 2995.4 | J47: =J48-J38 -> 18789.7 | K47: 18326.2 | L47: 18187.5 | M47: 18950.9 | N47: 46943.8 | O47: 45364.4 | P47: 44410.5 | Q47: 42743.6 | R47: =IFERROR((Q47/H47)^(1/COUNT($G$4:$Q$4))-1,"") -> 0.27397151
B48: Total Assets | G48: =SUM(G47,G38) -> 0 | H48: 7058.8 | I48: 7970.3 | J48: 21141 | K48: =SUM(K47,K38) -> 20438.3 | L48: =SUM(L47,L38) -> 20172.6 | M48: =SUM(M47,M38) -> 21468.6 | N48: =SUM(N47,N38) -> 52322.1 | O48: =SUM(O47,O38) -> 50302.4 | P48: =SUM(P47,P38) -> 48794.5 | Q48: =SUM(Q47,Q38) -> 48228.3 | R48: =IFERROR((Q48/H48)^(1/COUNT($G$4:$Q$4))-1,"") -> 0.19088575
B49: Accounts Payable | H49: 174.2 | I49: 171.4 | J49: 236.6 | K49: 260.9 | L49: 225.3 | M49: 227.3 | N49: 443.4 | O49: 582.2 | P49: 493 | Q49: 487.5 | R49: =IFERROR((Q49/H49)^(1/COUNT($G$4:$Q$4))-1,"") -> 0.098069121
B50: Short-Term Debt | G50: =+SUM(G51:G52) -> 0 | H50: =+SUM(H51:H52) -> 374.6 | I50: =+SUM(I51:I52) -> 0 | J50: =+SUM(J51:J52) -> 300 | K50: =+SUM(K51:K52) -> 67 | L50: =+SUM(L51:L52) -> 299.7 | M50: =+SUM(M51:M52) -> 0 | N50: =+SUM(N51:N52) -> 516.7 | ... Q50: =+SUM(Q51:Q52) -> 947.3 | R50: =IFERROR((Q50/H50)^(1/COUNT($G$4:$Q$4))-1,"") -> 0.088000436
B51: Short-Term Borrowings | P51: 547.2 | Q51: 547.7 | R51: =IFERROR((Q51/H51)^(1/COUNT($G$4:$Q$4))-1,"")
B52: Current Portion of Lease Liabilities | H52: 374.6 | I52: 0 | J52: 300 | K52: 67 | L52: 299.7 | M52: 0 | N52: 516.7 | O52: 0 | P52: 499.1 | Q52: 399.6 | R52: =IFERROR((Q52/H52)^(1/COUNT($G$4:$Q$4))-1,"") -> 0.0058904862
B53: Accrued Expenses and Other Current Liabilities | G53: =+G54-G49-G50 -> 0 | H53: =+H54-H49-H50 -> 564.8 | I53: =+I54-I49-I50 -> 611.5 | J53: =+J54-J49-J50 -> 1059.7 | K53: =+K54-K49-K50 -> 723.8 | L53: =+L54-L49-L50 -> 983.6 | M53: =+M54-M49-M50 -> 1137.7 | N53: =+N54-N49-N50 -> 1810.2 | ... Q53: =+Q54-Q49-Q50 -> 1553.5 | R53: =IFERROR((Q53/H53)^(1/COUNT($G$4:$Q$4))-1,"") -> 0.096344295
B54: Current Liabilities | H54: 1113.6 | I54: 782.9 | J54: 1596.3 | K54: 1051.7 | L54: 1508.6 | M54: 1365 | N54: 2770.3 | O54: 2442.7 | P54: 3201 | Q54: 2988.3 | R54: =IFERROR((Q54/H54)^(1/COUNT($G$4:$Q$4))-1,"") -> 0.093886519
B55: Long-Term Debt | G55: =+SUM(G56:G57) -> 0 | H55: =+SUM(H56:H57) -> 495.3 | I55: =+SUM(I56:I57) -> 1732.2 | J55: =+SUM(J56:J57) -> 7551.1 | K55: =+SUM(K56:K57) -> 6265.7 | L55: =+SUM(L56:L57) -> 5192.3 | M55: =+SUM(M56:M57) -> 5145.1 | N55: =+SUM(N56:N57) -> 6253.2 | ... Q55: =+SUM(Q56:Q57) -> 6634.3 | R55: =IFERROR((Q55/H55)^(1/COUNT($G$4:$Q$4))-1,"") -> 0.26604135
B56: Long-Term Borrowings | H56: 495.3 | I56: 1732.2 | J56: 7551.1 | K56: 6265.7 | L56: 5192.3 | M56: 5145.1 | N56: 6253.2 | O56: 6548.6 | P56: 5902.5 | Q56: 6634.3 | R56: =IFERROR((Q56/H56)^(1/COUNT($G$4:$Q$4))-1,"") -> 0.26604135
B57: Long-Term Operating Lease Liabilities | R57: =IFERROR((Q57/H57)^(1/COUNT($G$4:$Q$4))-1,"")
B58: Other Non-Current Liabilities | G58: =+G59-G55 -> 0 | H58: =+H59-H55 -> 376.9 | I58: =+I59-I55 -> 289.5 | J58: =+J59-J55 -> 1832.3 | K58: =+K59-K55 -> 1852.7 | L58: =+L59-L55 -> 2982.5 | M58: =+M59-M55 -> 2960.6 | N58: =+N59-N55 -> 5306 | ... Q58: =+Q59-Q55 -> 3429.4 | R58: =IFERROR((Q58/H58)^(1/COUNT($G$4:$Q$4))-1,"") -> 0.22230923
B59: Non-Current Liabilities | H59: 872.2 | I59: 2021.7 | J59: 9383.4 | K59: 8118.4 | L59: 8174.8 | M59: 8105.7 | N59: 11559.2 | O59: 11394.4 | P59: 10028.4 | Q59: 10063.7 | R59: =IFERROR((Q59/H59)^(1/COUNT($G$4:$Q$4))-1,"") -> 0.24898818
B60: Total Liabilities | G60: =SUM(G59,G54) -> 0 | H60: =SUM(H59,H54) -> 1985.8 | I60: =SUM(I59,I54) -> 2804.6 | J60: =SUM(J59,J54) -> 10979.7 | K60: =SUM(K59,K54) -> 9170.1 | L60: =SUM(L59,L54) -> 9683.4 | M60: =SUM(M59,M54) -> 9470.7 | N60: =SUM(N59,N54) -> 14329.5 | ... Q60: =SUM(Q59,Q54) -> 13052 | R60: =IFERROR((Q60/H60)^(1/COUNT($G$4:$Q$4))-1,"") -> 0.18669781
B61: Shareholder's Equity | G61: =G48-G60 -> 0 | H61: =H48-H60 -> 5073 | I61: =I48-I60 -> 5165.7 | J61: =J48-J60 -> 10161.3 | K61: =K48-K60 -> 11268.2 | L61: =L48-L60 -> 10489.2 | M61: =M48-M60 -> 11997.9 | N61: =N48-N60 -> 37992.6 | ... Q61: =Q48-Q60 -> 35176.3 | R61: =IFERROR((Q61/H61)^(1/COUNT($G$4:$Q$4))-1,"") -> 0.19248578
B62: Non-Controlling Interest | R62: =IFERROR((Q62/H62)^(1/COUNT($G$4:$Q$4))-1,"")
A64: x | B64: Cash Flow | G64: 2014 | H64: =+G64+1 -> 2015 | I64: =+H64+1 -> 2016 | J64: =+I64+1 -> 2017 | K64: =+J64+1 -> 2018 | L64: =+K64+1 -> 2019 | M64: =+L64+1 -> 2020 | N64: =+M64+1 -> 2021 | O64: =+N64+1 -> 2022 | ... Q64: =+P64+1 -> 2024 | R64: ="CAGR "&$G$4&" - "&$Q$4 -> CAGR 2014 - 2024
B66: Net Income | G66: =G24 -> 0 | H66: =H24 -> 606.7 | I66: =I24 -> 905.7 | J66: =J24 -> 1128.7 | K66: =K24 -> 1606.4 | L66: =L24 -> 1307 | M66: =M24 -> 1081.8 | N66: =N24 -> 1335.9 | ... Q66: =Q24 -> 644.3 | R66: =IFERROR((Q66/H66)^(1/COUNT($H$4:$Q$4))-1,"") -> 0.0060311165
B67: D&A (Depreciation and Amortization) | G67: =+G13 -> 0 | H67: =+H13 -> 218.4 | I67: =+I13 -> 134.5 | J67: =+J13 -> 194.7 | K67: =+K13 -> 799 | L67: =+L13 -> 811.3 | M67: =+M13 -> 810.9 | N67: =+N13 -> 1074.7 | ... Q67: =+Q13 -> 2104.3 | R67: =IFERROR((Q67/H67)^(1/COUNT($H$4:$Q$4))-1,"") -> 0.25425402
B68: Changes in Net Working Capital | G68: =+SUM(G69:G72) -> 0 | H68: =+SUM(H69:H72) -> 25.1 | I68: =+SUM(I69:I72) -> 10 | J68: =+SUM(J69:J72) -> 119.6 | K68: =+SUM(K69:K72) -> -8.5 | L68: =+SUM(L69:L72) -> 75 | M68: =+SUM(M69:M72) -> 29.4 | N68: =+SUM(N69:N72) -> -28.5 | ... Q68: =+SUM(Q69:Q72) -> 57.1 | R68: =IFERROR((Q68/H68)^(1/COUNT($H$4:$Q$4))-1,"") -> 0.085666004
B69: (Increase) Decrease in Accounts Receivable | H69: 25.1 | I69: 10 | J69: 119.6 | K69: -8.5 | L69: 75 | M69: 29.4 | N69: -6.8 | O69: -91.9 | P69: -263.7 | Q69: 91.6 | R69: =IFERROR((Q69/H69)^(1/COUNT($H$4:$Q$4))-1,"") -> 0.13820942
B70: (Increase) Decrease in Inventories | H70: 35.6 | I70: -38.2 | J70: 47.4 | K70: 34.6 | L70: 42.8 | M70: -1.8 | N70: 65.1 | O70: 470.7 | P70: 242.3 | Q70: -191.2 | R70: =IFERROR((Q70/H70)^(1/COUNT($H$4:$Q$4))-1,"")
B71: Increase (Decrease) in Inventories | H71: -35.6 | I71: 38.2 | J71: -47.4 | K71: -34.6 | L71: -42.8 | M71: 1.8 | N71: -65.1 | O71: -470.7 | P71: -242.3 | Q71: 191.2 | R71: =IFERROR((Q71/H71)^(1/COUNT($H$4:$Q$4))-1,"")
B72: Increase (Decrease) in Other | M72: 0 | N72: -21.7 | O72: -14.4 | P72: -25.8 | Q72: -34.5 | R72: =IFERROR((Q72/H72)^(1/COUNT($H$4:$Q$4))-1,"")
B73: Stock Based Compensation | H73: 68.9 | I73: 63.4 | J73: 104.2 | K73: 151.2 | L73: 150.3 | M73: 149.5 | N73: 243.6 | O73: 323.5 | P73: 299.8 | Q73: 262.7 | R73: =IFERROR((Q73/H73)^(1/COUNT($H$4:$Q$4))-1,"") -> 0.14320492
B74: Other Operating Adjustments | G74: =+G75-G66-G67-G68-G73 -> 0 | H74: =+H75-H66-H67-H68-H73 -> -11.3 | I74: =+I75-I66-I67-I68-I73 -> 177.7 | J74: =+J75-J66-J67-J68-J73 -> -392.8 | K74: =+K75-K66-K67-K68-K73 -> -105.7 | L74: =+L75-L66-L67-L68-L73 -> -90.5 | M74: =+M75-M66-M67-M68-M73 -> -63.1 | N74: =+N75-N66-N67-N68-N73 -> 109.4 | ... Q74: =+Q75-Q66-Q67-Q68-Q73 -> 784.1 | R74: =IFERROR((Q74/H74)^(1/COUNT($H$4:$Q$4))-1,"")
B75: Operating Cash Flow | H75: 907.8 | I75: 1291.3 | J75: 1154.4 | K75: 2442.4 | L75: 2253.1 | M75: 2008.5 | N75: 2735.1 | O75: 4475.4 | P75: 4817.6 | Q75: 3852.5 | R75: =IFERROR((Q75/H75)^(1/COUNT($H$4:$Q$4))-1,"") -> 0.15551409
B76: Net Capex | G76: =+SUM(G77:G78) -> 0 | H76: =+SUM(H77:H78) -> -154 | I76: =+SUM(I77:I78) -> -127 | J76: =+SUM(J77:J78) -> -204 | K76: =+SUM(K77:K78) -> -255 | L76: =+SUM(L77:L78) -> -275 | M76: =+SUM(M77:M78) -> -166 | N76: =+SUM(N77:N78) -> -344 | ... Q76: =+SUM(Q77:Q78) -> -730 | R76: =IFERROR((Q76/H76)^(1/COUNT($H$4:$Q$4))-1,"") -> 0.16836951
B77: Net Change In PPE | H77: -154 | I77: -127 | J77: -204 | K77: -255 | L77: -275 | M77: -166 | N77: -344 | O77: -699 | P77: -1261 | Q77: -730 | R77: =IFERROR((Q77/H77)^(1/COUNT($H$4:$Q$4))-1,"") -> 0.16836951
B78: Disposal of Fixed & Intangibles | R78: =IFERROR((Q78/H78)^(1/COUNT($H$4:$Q$4))-1,"")
B79: Net Cash from Investments & Acquisitions | G79: =+SUM(G80:G83) -> 0 | H79: =+SUM(H80:H83) -> -7.1 | I79: =+SUM(I80:I83) -> -83.2 | J79: =+SUM(J80:J83) -> -9632.6 | K79: =+SUM(K80:K83) -> -52.8 | L79: =+SUM(L80:L83) -> -11.2 | M79: =+SUM(M80:M83) -> -14.2 | N79: =+SUM(N80:N83) -> -25 | ... Q79: =+SUM(Q80:Q83) -> 0 | R79: =IFERROR((Q79/H79)^(1/COUNT($H$4:$Q$4))-1,"") -> -1
B80: Acquisitions | H80: -7.1 | I80: -83.2 | J80: -9632.6 | K80: -52.8 | L80: -11.2 | M80: -14.2 | N80: -25 | P80: 0 | R80: =IFERROR((Q80/H80)^(1/COUNT($H$4:$Q$4))-1,"") -> -1
B81: Divestitures | H81: 0 | I81: 0 | J81: 0 | K81: 0 | L81: 0 | N81: 0 | R81: =IFERROR((Q81/H81)^(1/COUNT($H$4:$Q$4))-1,"")
B82: Increase in LT Investment | R82: =IFERROR((Q82/H82)^(1/COUNT($H$4:$Q$4))-1,"")
B83: Decrease in LT Investment | R83: =IFERROR((Q83/H83)^(1/COUNT($H$4:$Q$4))-1,"")
B84: Other Investing Inflows (Outflows) | G84: =+G85-G76-G79 -> 0 | H84: =+H85-H76-H79 -> 144 | I84: =+I85-I76-I79 -> -1008.1 | J84: =+J85-J76-J79 -> 3218.6 | K84: =+K85-K76-K79 -> -6.2 | L84: =+L85-L76-L79 -> -7 | M84: =+M85-M76-M79 -> -0.3 | N84: =+N85-N76-N79 -> 2512.5 | ... Q84: =+Q85-Q76-Q79 -> -374.9 | R84: =IFERROR((Q84/H84)^(1/COUNT($H$4:$Q$4))-1,"")
B85: Investing Cash Flow | H85: -17.1 | I85: -1218.3 | J85: -6618 | K85: -314 | L85: -293.2 | M85: -180.5 | N85: 2143.5 | O85: -657.4 | P85: -1266.4 | Q85: -1104.9 | R85: =IFERROR((Q85/H85)^(1/COUNT($H$4:$Q$4))-1,"") -> 0.51716455
B86: Debt Borrowing | R86: =IFERROR((Q86/H86)^(1/COUNT($H$4:$Q$4))-1,"")
B87: Debt Repayment | Q87: -499.966 | R87: =IFERROR((Q87/H87)^(1/COUNT($H$4:$Q$4))-1,"")
B88: Lease Payments | R88: =IFERROR((Q88/H88)^(1/COUNT($H$4:$Q$4))-1,"")
B89: Dividends | H89: -491.1 | I89: -513.2 | J89: -602.1 | K89: -703.3 | L89: -777.5 | M89: -886.2 | N89: -1109.3 | O89: -1544.6 | P89: -1679.1 | Q89: -1795.5 | R89: =IFERROR((Q89/H89)^(1/COUNT($H$4:$Q$4))-1,"") -> 0.13841746
B90: Increase (Repurchase) of Shares | H90: -227 | I90: -370.1 | J90: -46.5 | K90: -226 | L90: -613 | M90: -244.5 | N90: -3105.1 | O90: -2577 | P90: -2964 | Q90: -615.6 | R90: =IFERROR((Q90/H90)^(1/COUNT($H$4:$Q$4))-1,"") -> 0.10491094
B91: Other Financing Inflows (Outflows) | G91: =+G92-G86-G87-G88-G89-G90 -> 0 | H91: =+H92-H86-H87-H88-H89-H90 -> 146.5 | I91: =+I92-I86-I87-I88-I89-I90 -> 849.9 | J91: =+J92-J86-J87-J88-J89-J90 -> 6235.4 | K91: =+K92-K86-K87-K88-K89-K90 -> -1428.7 | L91: =+L92-L86-L87-L88-L89-L90 -> -736.3 | M91: =+M92-M86-M87-M88-M89-M90 -> -289.9 | N91: =+N92-N86-N87-N88-N89-N90 -> 254.7 | ... Q91: =+Q92-Q86-Q87-Q88-Q89-Q90 -> 1196.666 | R91: =IFERROR((Q91/H91)^(1/COUNT($H$4:$Q$4))-1,"") -> 0.23371127
B92: Financing Cash Flow | H92: -571.6 | I92: -33.4 | J92: 5586.8 | K92: -2358 | L92: -2126.8 | M92: -1420.6 | N92: -3959.7 | O92: -4290.7 | P92: -4063.8 | Q92: -1714.4 | R92: =IFERROR((Q92/H92)^(1/COUNT($H$4:$Q$4))-1,"") -> 0.11609714
B93: Effect of Foreign Exchange | H93: -4 | I93: -2.9 | J93: 3.6 | K93: -1.6 | L93: -1.4 | M93: 0.2 | N93: 3.2 | O93: -34.7 | P93: 0 | Q93: 0 | R93: =IFERROR((Q93/H93)^(1/COUNT($H$4:$Q$4))-1,"") -> -1
B94: Net Changes in Cash | H94: 315.1 | I94: 36.8 | J94: 126.7 | K94: -231.2 | L94: -168.3 | M94: 407.5 | N94: 922.1 | O94: -507.4 | P94: -512.5 | Q94: 1033.3 | R94: =IFERROR((Q94/H94)^(1/COUNT($H$4:$Q$4))-1,"") -> 0.12610219
B95: in millionsof USD | R95: =IFERROR((Q95/H95)^(1/COUNT($H$4:$Q$4))-1,"")
A96: x | B96: Capital Structure | G96: 42004 | H96: 42369 | I96: 42735 | J96: 43100 | K96: 43465 | L96: 43830 | M96: 44196 | N96: 44561 | O96: 44926 | P96: 45291 | Q96: 45657
B98: Market Capitalization | G98: {=(IFERROR(_xlfn.STOCKHISTORY(DCF!$R$4, G96, G96, 0, 0, 1), IFERROR(_xlfn.STOCKHISTORY(DCF!$R$4, G96+1, G96+1, 0, 0, 1), _xlfn.STOCKHISTORY(DCF!$R$4, G96-2, G96-2, 0, 0, 1))))*_xlfn.XLOOKUP("Basic Weighted Average Shares",$B:$B,G:G)} -> 0 | H98: {=(IFERROR(_xlfn.STOCKHISTORY(DCF!$R$4, H96, H96, 0, 0, 1), IFERROR(_xlfn.STOCKHISTORY(DCF!$R$4, H96+1, H96+1, 0, 0, 1), _xlfn.STOCKHISTORY(DCF!$R$4, H96-2, H96-2, 0, 0, 1))))*_xlfn.XLOOKUP("Basic Weighted Average Shares",$B:$B,H:H)} -> 17298.564 | I98: {=(IFERROR(_xlfn.STOCKHISTORY(DCF!$R$4, I96, I96, 0, 0, 1), IFERROR(_xlfn.STOCKHISTORY(DCF!$R$4, I96+1, I96+1, 0, 0, 1), _xlfn.STOCKHISTORY(DCF!$R$4, I96-2, I96-2, 0, 0, 1))))*_xlfn.XLOOKUP("Basic Weighted Average Shares",$B:$B,I:I)} -> 22714.146 | J98: {=(IFERROR(_xlfn.STOCKHISTORY(DCF!$R$4, J96, J96, 0, 0, 1), IFERROR(_xlfn.STOCKHISTORY(DCF!$R$4, J96+1, J96+1, 0, 0, 1), _xlfn.STOCKHISTORY(DCF!$R$4, J96-2, J96-2, 0, 0, 1))))*_xlfn.XLOOKUP("Basic Weighted Average Shares",$B:$B,J:J)} -> 30839.992 | K98: {=(IFERROR(_xlfn.STOCKHISTORY(DCF!$R$4, K96, K96, 0, 0, 1), IFERROR(_xlfn.STOCKHISTORY(DCF!$R$4, K96+1, K96+1, 0, 0, 1), _xlfn.STOCKHISTORY(DCF!$R$4, K96-2, K96-2, 0, 0, 1))))*_xlfn.XLOOKUP("Basic Weighted Average Shares",$B:$B,K:K)} -> 31791.432 | L98: {=(IFERROR(_xlfn.STOCKHISTORY(DCF!$R$4, L96, L96, 0, 0, 1), IFERROR(_xlfn.STOCKHISTORY(DCF!$R$4, L96+1, L96+1, 0, 0, 1), _xlfn.STOCKHISTORY(DCF!$R$4, L96-2, L96-2, 0, 0, 1))))*_xlfn.XLOOKUP("Basic Weighted Average Shares",$B:$B,L:L)} -> 43863.844 | M98: {=(IFERROR(_xlfn.STOCKHISTORY(DCF!$R$4, M96, M96, 0, 0, 1), IFERROR(_xlfn.STOCKHISTORY(DCF!$R$4, M96+1, M96+1, 0, 0, 1), _xlfn.STOCKHISTORY(DCF!$R$4, M96-2, M96-2, 0, 0, 1))))*_xlfn.XLOOKUP("Basic Weighted Average Shares",$B:$B,M:M)} -> 54453.278 | N98: {=(IFERROR(_xlfn.STOCKHISTORY(DCF!$R$4, N96, N96, 0, 0, 1), IFERROR(_xlfn.STOCKHISTORY(DCF!$R$4, N96+1, N96+1, 0, 0, 1), _xlfn.STOCKHISTORY(DCF!$R$4, N96-2, N96-2, 0, 0, 1))))*_xlfn.XLOOKUP("Basic Weighted Average Shares",$B:$B,N:N)} -> 69868.575 | O98: {=(IFERROR(_xlfn.STOCKHISTORY(DCF!$R$4, O96, O96, 0, 0, 1), IFERROR(_xlfn.STOCKHISTORY(DCF!$R$4, O96+1, O96+1, 0, 0, 1), _xlfn.STOCKHISTORY(DCF!$R$4, O96-2, O96-2, 0, 0, 1))))*_xlfn.XLOOKUP("Basic Weighted Average Shares",$B:$B,O:O)} -> 85138.416 | P98: {=(IFERROR(_xlfn.STOCKHISTORY(DCF!$R$4, P96, P96, 0, 0, 1), IFERROR(_xlfn.STOCKHISTORY(DCF!$R$4, P96+1, P96+1, 0, 0, 1), _xlfn.STOCKHISTORY(DCF!$R$4, P96-2, P96-2, 0, 0, 1))))*_xlfn.XLOOKUP("Basic Weighted Average Shares",$B:$B,P:P)} -> 99716.832 | Q98: {=(IFERROR(_xlfn.STOCKHISTORY(DCF!$R$4, Q96, Q96, 0, 0, 1), IFERROR(_xlfn.STOCKHISTORY(DCF!$R$4, Q96+1, Q96+1, 0, 0, 1), _xlfn.STOCKHISTORY(DCF!$R$4, Q96-2, Q96-2, 0, 0, 1))))*_xlfn.XLOOKUP("Basic Weighted Average Shares",$B:$B,Q:Q)} -> 105422.65
B99: Cash & Cash Equivalents | G99: =_xlfn.XLOOKUP("Cash & Cash Equivalents & ST Investments",$B$30:$B$62,G$30:G$62) -> 0 | H99: =_xlfn.XLOOKUP("Cash & Cash Equivalents & ST Investments",$B$30:$B$62,H$30:H$62) -> 3029 | I99: =_xlfn.XLOOKUP("Cash & Cash Equivalents & ST Investments",$B$30:$B$62,I$30:I$62) -> 4055.8 | J99: =_xlfn.XLOOKUP("Cash & Cash Equivalents & ST Investments",$B$30:$B$62,J$30:J$62) -> 1047.8 | K99: =_xlfn.XLOOKUP("Cash & Cash Equivalents & ST Investments",$B$30:$B$62,K$30:K$62) -> 816.6 | L99: =_xlfn.XLOOKUP("Cash & Cash Equivalents & ST Investments",$B$30:$B$62,L$30:L$62) -> 648.3 | M99: =_xlfn.XLOOKUP("Cash & Cash Equivalents & ST Investments",$B$30:$B$62,M$30:M$62) -> 1055.9 | N99: =_xlfn.XLOOKUP("Cash & Cash Equivalents & ST Investments",$B$30:$B$62,N$30:N$62) -> 1978 | ... Q99: =_xlfn.XLOOKUP("Cash & Cash Equivalents & ST Investments",$B$30:$B$62,Q$30:Q$62) -> 2363.1
B100: Total Debt | G100: =(_xlfn.XLOOKUP("Short-Term Debt",$B$30:$B$62,G$30:G$62)+_xlfn.XLOOKUP("Long-Term Debt",$B$30:$B$62,G$30:G$62)) -> 0 | H100: =(_xlfn.XLOOKUP("Short-Term Debt",$B$30:$B$62,H$30:H$62)+_xlfn.XLOOKUP("Long-Term Debt",$B$30:$B$62,H$30:H$62)) -> 869.9 | I100: =(_xlfn.XLOOKUP("Short-Term Debt",$B$30:$B$62,I$30:I$62)+_xlfn.XLOOKUP("Long-Term Debt",$B$30:$B$62,I$30:I$62)) -> 1732.2 | J100: =(_xlfn.XLOOKUP("Short-Term Debt",$B$30:$B$62,J$30:J$62)+_xlfn.XLOOKUP("Long-Term Debt",$B$30:$B$62,J$30:J$62)) -> 7851.1 | K100: =(_xlfn.XLOOKUP("Short-Term Debt",$B$30:$B$62,K$30:K$62)+_xlfn.XLOOKUP("Long-Term Debt",$B$30:$B$62,K$30:K$62)) -> 6332.7 | L100: =(_xlfn.XLOOKUP("Short-Term Debt",$B$30:$B$62,L$30:L$62)+_xlfn.XLOOKUP("Long-Term Debt",$B$30:$B$62,L$30:L$62)) -> 5492 | M100: =(_xlfn.XLOOKUP("Short-Term Debt",$B$30:$B$62,M$30:M$62)+_xlfn.XLOOKUP("Long-Term Debt",$B$30:$B$62,M$30:M$62)) -> 5145.1 | N100: =(_xlfn.XLOOKUP("Short-Term Debt",$B$30:$B$62,N$30:N$62)+_xlfn.XLOOKUP("Long-Term Debt",$B$30:$B$62,N$30:N$62)) -> 6769.9 | ... Q100: =(_xlfn.XLOOKUP("Short-Term Debt",$B$30:$B$62,Q$30:Q$62)+_xlfn.XLOOKUP("Long-Term Debt",$B$30:$B$62,Q$30:Q$62)) -> 7581.6
B101: Preferred Stock
B102: Non-Controlling Interest | G102: =_xlfn.XLOOKUP("Non-Controlling Interest",$B$30:$B$62,G$30:G$62) -> 0 | H102: =_xlfn.XLOOKUP("Non-Controlling Interest",$B$30:$B$62,H$30:H$62) -> 0 | I102: =_xlfn.XLOOKUP("Non-Controlling Interest",$B$30:$B$62,I$30:I$62) -> 0 | J102: =_xlfn.XLOOKUP("Non-Controlling Interest",$B$30:$B$62,J$30:J$62) -> 0 | K102: =_xlfn.XLOOKUP("Non-Controlling Interest",$B$30:$B$62,K$30:K$62) -> 0 | L102: =_xlfn.XLOOKUP("Non-Controlling Interest",$B$30:$B$62,L$30:L$62) -> 0 | M102: =_xlfn.XLOOKUP("Non-Controlling Interest",$B$30:$B$62,M$30:M$62) -> 0 | N102: =_xlfn.XLOOKUP("Non-Controlling Interest",$B$30:$B$62,N$30:N$62) -> 0 | ... Q102: =_xlfn.XLOOKUP("Non-Controlling Interest",$B$30:$B$62,Q$30:Q$62) -> 0
B103: Enterprise Value | G103: =+G98-G99+G100+G101+G102 -> 0 | H103: =+H98-H99+H100+H101+H102 -> 15139.464 | I103: =+I98-I99+I100+I101+I102 -> 20390.546 | J103: =+J98-J99+J100+J101+J102 -> 37643.292 | K103: =+K98-K99+K100+K101+K102 -> 37307.532 | L103: =+L98-L99+L100+L101+L102 -> 48707.544 | M103: =+M98-M99+M100+M101+M102 -> 58542.478 | N103: =+N98-N99+N100+N101+N102 -> 74660.475 | ... Q103: =+Q98-Q99+Q100+Q101+Q102 -> 110641.15
A105: x | B105: Debt Schedule | G105: Cash | H105: 2025 | I105: =+H105+1 -> 2026 | J105: =+I105+1 -> 2027 | K105: =+J105+1 -> 2028 | L105: =+K105+1 -> 2029 | M105: =+L105+1 -> 2030 | N105: =+M105+1 -> 2031 | O105: =+N105+1 -> 2032 | P105: =+O105+1 -> 2033 | Q105: =+P105+1 -> 2034
L106: v | M106: v | N106: v | O106: v | P106: v | Q106: v
B107: Cash
B108: Fixed
...

Sheet WACC
B2: WACC
B4: WACC = % of Equity x Cost of Equity + % de Debt x Cost of Debt x (1 - Tax Rate)
B5: Cost of Equity = Risk-Free Rate + Beta x Equity Risk Premium
B7: WACC | I7: Region | J7: Weight | K7: ERP | M7: Peers | N7: Beta (Unlevered)
B9: Market Cap (in millions) | G9: {=+_FV(DCF!R4,"Market cap",TRUE)/1000000} -> 120804.57 | K9: 0.043 | M9: =+Peers!B8 -> TEXAS INSTRUMENTS INCORPORATED | N9: =+Peers!E75 -> 0.59172608
B10: % of Equity | G10: =IFERROR(G9/G23,"") -> 1 | M10: =+Peers!B9 -> MICROCHIP TECHNOLOGY INCORPORATED | N10: =+Peers!F75 -> 0.83740183
B11: Cost of Equity | G11: =IFERROR(G12+G14*G15,"") -> 0.08558 | M11: =+Peers!B10 -> MONOLITHIC POWER SYSTEMS, INC. | N11: =+Peers!G75
B12: Risk-Free Rate | G12: 0.04 | M12: =+Peers!B11 -> SKYWORKS SOLUTIONS, INC. | N12: =+Peers!H75
B13: Unlevered Beta | G13: =+N19 -> 0.94157093 | H13: 0,992 | M13: =+Peers!B12 -> MACOM TECHNOLOGY SOLUTIONS HOLDINGS, INC. | N13: =+Peers!I75
B14: Beta | G14: 1.06 | I14: Others | J14: =1-SUM(J9:J13) -> 1 | K14: =MAX(K9:K13) -> 0.043 | M14: =+Peers!B13 -> MARVELL TECHNOLOGY, INC. | N14: =+Peers!J75 -> 1.3955849
B15: Equity Risk Premium | G15: =SUMPRODUCT(J9:J14,K9:K14) -> 0.043 | M15: =+Peers!B14 -> INTEL CORPORATION | N15: =+Peers!K75
B16: Unlevered Cost of Equity | G16: =IFERROR(+G12+G13*G15,"") -> 0.08048755 | M16: =+Peers!B15 -> MICRON TECHNOLOGY, INC. | N16: =+Peers!L75
M17: =+Peers!B16 -> FIRST SOLAR, INC. | N17: =+Peers!M75
B18: Debt (in millions) | G18: 0 | M18: =+Peers!B17 -> ALTRI, S.G.P.S., S.A. | N18: =+Peers!N75
B19: % of Debt | G19: =IFERROR(G18/G23,"") -> 0 | M19: Average | N19: =IFERROR(+AVERAGEIF(N9:N18,">0"),"") -> 0.94157093
B20: Cost of debt | G20: 0
B21: Tax Rate | G21: =+DCF!H79 -> 0.14644254
B23: Total | G23: =+G9+G18 -> 120804.57
B25: WACC | G25: =IFERROR(G10*G11+G19*G20*(1-G21),"") -> 0.08558

Sheet Multiples
B2: Multiples
B4: Valuation | F4: 2014 | G4: =+F4+1 -> 2015 | H4: =+G4+1 -> 2016 | I4: =+H4+1 -> 2017 | J4: =+I4+1 -> 2018 | K4: =+J4+1 -> 2019 | L4: =+K4+1 -> 2020 | M4: =+L4+1 -> 2021 | N4: 2022 | O4: =+N4+1 -> 2023 | P4: =+O4+1 -> 2024 | Q4: =+P4+1 -> 2025 | R4: =+Q4+1 -> 2026
B6: EV / Sales | F6: =IFERROR(_xlfn.XLOOKUP("Enterprise Value",Inputs!$B:$B,Inputs!G:G)/_xlfn.XLOOKUP("Revenue (Sales)",Inputs!$B:$B,Inputs!G:G),"") | G6: =IFERROR(_xlfn.XLOOKUP("Enterprise Value",Inputs!$B:$B,Inputs!H:H)/_xlfn.XLOOKUP("Revenue (Sales)",Inputs!$B:$B,Inputs!H:H),"") -> 4.4072848 | H6: =IFERROR(_xlfn.XLOOKUP("Enterprise Value",Inputs!$B:$B,Inputs!I:I)/_xlfn.XLOOKUP("Revenue (Sales)",Inputs!$B:$B,Inputs!I:I),"") -> 5.9597083 | I6: =IFERROR(_xlfn.XLOOKUP("Enterprise Value",Inputs!$B:$B,Inputs!J:J)/_xlfn.XLOOKUP("Revenue (Sales)",Inputs!$B:$B,Inputs!J:J),"") -> 7.3701991 | J6: =IFERROR(_xlfn.XLOOKUP("Enterprise Value",Inputs!$B:$B,Inputs!K:K)/_xlfn.XLOOKUP("Revenue (Sales)",Inputs!$B:$B,Inputs!K:K),"") -> 5.9934667 | K6: =IFERROR(_xlfn.XLOOKUP("Enterprise Value",Inputs!$B:$B,Inputs!L:L)/_xlfn.XLOOKUP("Revenue (Sales)",Inputs!$B:$B,Inputs!L:L),"") -> 8.1299835 | L6: =IFERROR(_xlfn.XLOOKUP("Enterprise Value",Inputs!$B:$B,Inputs!M:M)/_xlfn.XLOOKUP("Revenue (Sales)",Inputs!$B:$B,Inputs!M:M),"") -> 10.44823 | M6: =IFERROR(_xlfn.XLOOKUP("Enterprise Value",Inputs!$B:$B,Inputs!N:N)/_xlfn.XLOOKUP("Revenue (Sales)",Inputs!$B:$B,Inputs!N:N),"") -> 10.201888 | N6: =IFERROR(_xlfn.XLOOKUP("Enterprise Value",Inputs!$B:$B,Inputs!O:O)/_xlfn.XLOOKUP("Revenue (Sales)",Inputs!$B:$B,Inputs!O:O),"") -> 7.5092738 | O6: =IFERROR(_xlfn.XLOOKUP("Enterprise Value",Inputs!$B:$B,Inputs!P:P)/_xlfn.XLOOKUP("Revenue (Sales)",Inputs!$B:$B,Inputs!P:P),"") -> 8.5902671 | P6: =IFERROR(_xlfn.XLOOKUP("Enterprise Value",Inputs!$B:$B,Inputs!Q:Q)/_xlfn.XLOOKUP("Revenue (Sales)",Inputs!$B:$B,Inputs!Q:Q),"") -> 11.736375 | Q6: =IFERROR(_xlfn.XLOOKUP("Enterprise Value",DCF!$B:$B,DCF!R:R)/_xlfn.XLOOKUP("Revenue (Sales)",DCF!$B:$B,DCF!H:H),"") -> 6.2024187 | R6: =IFERROR(_xlfn.XLOOKUP("Enterprise Value",DCF!$B:$B,DCF!S:S)/_xlfn.XLOOKUP("Revenue (Sales)",DCF!$B:$B,DCF!I:I),"") -> 5.625376
B7: Price / Sales | F7: =IFERROR(_xlfn.XLOOKUP("Market Capitalization",Inputs!$B:$B,Inputs!G:G)/_xlfn.XLOOKUP("Revenue (Sales)",Inputs!$B:$B,Inputs!G:G),"") | G7: =IFERROR(_xlfn.XLOOKUP("Market Capitalization",Inputs!$B:$B,Inputs!H:H)/_xlfn.XLOOKUP("Revenue (Sales)",Inputs!$B:$B,Inputs!H:H),"") -> 5.0358254 | H7: =IFERROR(_xlfn.XLOOKUP("Market Capitalization",Inputs!$B:$B,Inputs!I:I)/_xlfn.XLOOKUP("Revenue (Sales)",Inputs!$B:$B,Inputs!I:I),"") -> 6.6388455 | I7: =IFERROR(_xlfn.XLOOKUP("Market Capitalization",Inputs!$B:$B,Inputs!J:J)/_xlfn.XLOOKUP("Revenue (Sales)",Inputs!$B:$B,Inputs!J:J),"") -> 6.0381776 | J7: =IFERROR(_xlfn.XLOOKUP("Market Capitalization",Inputs!$B:$B,Inputs!K:K)/_xlfn.XLOOKUP("Revenue (Sales)",Inputs!$B:$B,Inputs!K:K),"") -> 5.1073035 | K7: =IFERROR(_xlfn.XLOOKUP("Market Capitalization",Inputs!$B:$B,Inputs!L:L)/_xlfn.XLOOKUP("Revenue (Sales)",Inputs!$B:$B,Inputs!L:L),"") -> 7.3215009 | L7: =IFERROR(_xlfn.XLOOKUP("Market Capitalization",Inputs!$B:$B,Inputs!M:M)/_xlfn.XLOOKUP("Revenue (Sales)",Inputs!$B:$B,Inputs!M:M),"") -> 9.7184198 | M7: =IFERROR(_xlfn.XLOOKUP("Market Capitalization",Inputs!$B:$B,Inputs!N:N)/_xlfn.XLOOKUP("Revenue (Sales)",Inputs!$B:$B,Inputs!N:N),"") -> 9.5471045 | N7: =IFERROR(_xlfn.XLOOKUP("Market Capitalization",Inputs!$B:$B,Inputs!O:O)/_xlfn.XLOOKUP("Revenue (Sales)",Inputs!$B:$B,Inputs!O:O),"") -> 7.0866003 | O7: =IFERROR(_xlfn.XLOOKUP("Market Capitalization",Inputs!$B:$B,Inputs!P:P)/_xlfn.XLOOKUP("Revenue (Sales)",Inputs!$B:$B,Inputs!P:P),"") -> 8.103436 | P7: =IFERROR(_xlfn.XLOOKUP("Market Capitalization",Inputs!$B:$B,Inputs!Q:Q)/_xlfn.XLOOKUP("Revenue (Sales)",Inputs!$B:$B,Inputs!Q:Q),"") -> 11.182817 | Q7: =IFERROR(_xlfn.XLOOKUP("Equity Value",DCF!$B:$B,DCF!R:R)/_xlfn.XLOOKUP("Revenue (Sales)",DCF!$B:$B,DCF!H:H),"") | R7: =IFERROR(_xlfn.XLOOKUP("Equity Value",DCF!$B:$B,DCF!S:S)/_xlfn.XLOOKUP("Revenue (Sales)",DCF!$B:$B,DCF!I:I),"")
B8: EV / EBITDA | F8: =IFERROR(_xlfn.XLOOKUP("Enterprise Value",Inputs!$B:$B,Inputs!G:G)/_xlfn.XLOOKUP("EBITDA",Inputs!$B:$B,Inputs!G:G),"") | G8: =IFERROR(_xlfn.XLOOKUP("Enterprise Value",Inputs!$B:$B,Inputs!H:H)/_xlfn.XLOOKUP("EBITDA",Inputs!$B:$B,Inputs!H:H),"") -> 16.472053 | H8: =IFERROR(_xlfn.XLOOKUP("Enterprise Value",Inputs!$B:$B,Inputs!I:I)/_xlfn.XLOOKUP("EBITDA",Inputs!$B:$B,Inputs!I:I),"") -> 18.336822 | I8: =IFERROR(_xlfn.XLOOKUP("Enterprise Value",Inputs!$B:$B,Inputs!J:J)/_xlfn.XLOOKUP("EBITDA",Inputs!$B:$B,Inputs!J:J),"") -> 26.849709 | J8: =IFERROR(_xlfn.XLOOKUP("Enterprise Value",Inputs!$B:$B,Inputs!K:K)/_xlfn.XLOOKUP("EBITDA",Inputs!$B:$B,Inputs!K:K),"") -> 15.610499 | K8: =IFERROR(_xlfn.XLOOKUP("Enterprise Value",Inputs!$B:$B,Inputs!L:L)/_xlfn.XLOOKUP("EBITDA",Inputs!$B:$B,Inputs!L:L),"") -> 21.789185 | L8: =IFERROR(_xlfn.XLOOKUP("Enterprise Value",Inputs!$B:$B,Inputs!M:M)/_xlfn.XLOOKUP("EBITDA",Inputs!$B:$B,Inputs!M:M),"") -> 29.565415 | M8: =IFERROR(_xlfn.XLOOKUP("Enterprise Value",Inputs!$B:$B,Inputs!N:N)/_xlfn.XLOOKUP("EBITDA",Inputs!$B:$B,Inputs!N:N),"") -> 32.271656 | N8: =IFERROR(_xlfn.XLOOKUP("Enterprise Value",Inputs!$B:$B,Inputs!O:O)/_xlfn.XLOOKUP("EBITDA",Inputs!$B:$B,Inputs!O:O),"") -> 19.759169 | O8: =IFERROR(_xlfn.XLOOKUP("Enterprise Value",Inputs!$B:$B,Inputs!P:P)/_xlfn.XLOOKUP("EBITDA",Inputs!$B:$B,Inputs!P:P),"") -> 21.383568 | P8: =IFERROR(_xlfn.XLOOKUP("Enterprise Value",Inputs!$B:$B,Inputs!Q:Q)/_xlfn.XLOOKUP("EBITDA",Inputs!$B:$B,Inputs!Q:Q),"") -> 39.166396 | Q8: =IFERROR(_xlfn.XLOOKUP("Enterprise Value",DCF!$B:$B,DCF!R:R)/_xlfn.XLOOKUP("EBITDA",DCF!$B:$B,DCF!H:H),"") -> 17.89259 | R8: =IFERROR(_xlfn.XLOOKUP("Enterprise Value",DCF!$B:$B,DCF!S:S)/_xlfn.XLOOKUP("EBITDA",DCF!$B:$B,DCF!I:I),"") -> 15.997209
B9: EV / EBIT | F9: =IFERROR(_xlfn.XLOOKUP("Enterprise Value",Inputs!$B:$B,Inputs!G:G)/_xlfn.XLOOKUP("Operating Income (EBIT)",Inputs!$B:$B,Inputs!G:G),"") | G9: =IFERROR(_xlfn.XLOOKUP("Enterprise Value",Inputs!$B:$B,Inputs!H:H)/_xlfn.XLOOKUP("Operating Income (EBIT)",Inputs!$B:$B,Inputs!H:H),"") -> 21.6062 | H9: =IFERROR(_xlfn.XLOOKUP("Enterprise Value",Inputs!$B:$B,Inputs!I:I)/_xlfn.XLOOKUP("Operating Income (EBIT)",Inputs!$B:$B,Inputs!I:I),"") -> 20.859894 | I9: =IFERROR(_xlfn.XLOOKUP("Enterprise Value",Inputs!$B:$B,Inputs!J:J)/_xlfn.XLOOKUP("Operating Income (EBIT)",Inputs!$B:$B,Inputs!J:J),"") -> 31.179733 | J9: =IFERROR(_xlfn.XLOOKUP("Enterprise Value",Inputs!$B:$B,Inputs!K:K)/_xlfn.XLOOKUP("Operating Income (EBIT)",Inputs!$B:$B,Inputs!K:K),"") -> 23.450583 | K9: =IFERROR(_xlfn.XLOOKUP("Enterprise Value",Inputs!$B:$B,Inputs!L:L)/_xlfn.XLOOKUP("Operating Income (EBIT)",Inputs!$B:$B,Inputs!L:L),"") -> 34.202334 | L9: =IFERROR(_xlfn.XLOOKUP("Enterprise Value",Inputs!$B:$B,Inputs!M:M)/_xlfn.XLOOKUP("Operating Income (EBIT)",Inputs!$B:$B,Inputs!M:M),"") -> 50.070542 | M9: =IFERROR(_xlfn.XLOOKUP("Enterprise Value",Inputs!$B:$B,Inputs!N:N)/_xlfn.XLOOKUP("Operating Income (EBIT)",Inputs!$B:$B,Inputs!N:N),"") -> 60.268385 | N9: =IFERROR(_xlfn.XLOOKUP("Enterprise Value",Inputs!$B:$B,Inputs!O:O)/_xlfn.XLOOKUP("Operating Income (EBIT)",Inputs!$B:$B,Inputs!O:O),"") -> 39.7727 | O9: =IFERROR(_xlfn.XLOOKUP("Enterprise Value",Inputs!$B:$B,Inputs!P:P)/_xlfn.XLOOKUP("Operating Income (EBIT)",Inputs!$B:$B,Inputs!P:P),"") -> 39.885119 | P9: =IFERROR(_xlfn.XLOOKUP("Enterprise Value",Inputs!$B:$B,Inputs!Q:Q)/_xlfn.XLOOKUP("Operating Income (EBIT)",Inputs!$B:$B,Inputs!Q:Q),"") -> 153.54032 | Q9: =IFERROR(_xlfn.XLOOKUP("Enterprise Value",DCF!$B:$B,DCF!R:R)/_xlfn.XLOOKUP("Operating Income (EBIT)",DCF!$B:$B,DCF!H:H),"") -> 40.042324 | R9: =IFERROR(_xlfn.XLOOKUP("Enterprise Value",DCF!$B:$B,DCF!S:S)/_xlfn.XLOOKUP("Operating Income (EBIT)",DCF!$B:$B,DCF!I:I),"") -> 31.014882
B10: Price / Earnings | F10: =IFERROR(_xlfn.XLOOKUP("Market Capitalization",Inputs!$B:$B,Inputs!G:G)/_xlfn.XLOOKUP("Net Income",Inputs!$B:$B,Inputs!G:G),"") | G10: =IFERROR(_xlfn.XLOOKUP("Market Capitalization",Inputs!$B:$B,Inputs!H:H)/_xlfn.XLOOKUP("Net Income",Inputs!$B:$B,Inputs!H:H),"") -> 28.51255 | H10: =IFERROR(_xlfn.XLOOKUP("Market Capitalization",Inputs!$B:$B,Inputs!I:I)/_xlfn.XLOOKUP("Net Income",Inputs!$B:$B,Inputs!I:I),"") -> 25.079106 | I10: =IFERROR(_xlfn.XLOOKUP("Market Capitalization",Inputs!$B:$B,Inputs!J:J)/_xlfn.XLOOKUP("Net Income",Inputs!$B:$B,Inputs!J:J),"") -> 27.323462 | J10: =IFERROR(_xlfn.XLOOKUP("Market Capitalization",Inputs!$B:$B,Inputs!K:K)/_xlfn.XLOOKUP("Net Income",Inputs!$B:$B,Inputs!K:K),"") -> 19.790483 | K10: =IFERROR(_xlfn.XLOOKUP("Market Capitalization",Inputs!$B:$B,Inputs!L:L)/_xlfn.XLOOKUP("Net Income",Inputs!$B:$B,Inputs!L:L),"") -> 33.560707 | L10: =IFERROR(_xlfn.XLOOKUP("Market Capitalization",Inputs!$B:$B,Inputs!M:M)/_xlfn.XLOOKUP("Net Income",Inputs!$B:$B,Inputs!M:M),"") -> 50.335809 | M10: =IFERROR(_xlfn.XLOOKUP("Market Capitalization",Inputs!$B:$B,Inputs!N:N)/_xlfn.XLOOKUP("Net Income",Inputs!$B:$B,Inputs!N:N),"") -> 52.300752 | N10: =IFERROR(_xlfn.XLOOKUP("Market Capitalization",Inputs!$B:$B,Inputs!O:O)/_xlfn.XLOOKUP("Net Income",Inputs!$B:$B,Inputs!O:O),"") -> 42.893051 | O10: =IFERROR(_xlfn.XLOOKUP("Market Capitalization",Inputs!$B:$B,Inputs!P:P)/_xlfn.XLOOKUP("Net Income",Inputs!$B:$B,Inputs!P:P),"") -> 41.431291 | P10: =IFERROR(_xlfn.XLOOKUP("Market Capitalization",Inputs!$B:$B,Inputs!Q:Q)/_xlfn.XLOOKUP("Net Income",Inputs!$B:$B,Inputs!Q:Q),"") -> 163.62355 | Q10: =IFERROR(_xlfn.XLOOKUP("Equity Value",DCF!$B:$B,DCF!R:R)/_xlfn.XLOOKUP("Net Income",DCF!$B:$B,DCF!H:H),"") | R10: =IFERROR(_xlfn.XLOOKUP("Equity Value",DCF!$B:$B,DCF!S:S)/_xlfn.XLOOKUP("Net Income",DCF!$B:$B,DCF!I:I),"")
B11: Price / Book | F11: =IFERROR(_xlfn.XLOOKUP("Market Capitalization",Inputs!$B:$B,Inputs!G:G)/_xlfn.XLOOKUP("Shareholder's Equity",Inputs!$B:$B,Inputs!G:G),"") | G11: =IFERROR(_xlfn.XLOOKUP("Market Capitalization",Inputs!$B:$B,Inputs!H:H)/_xlfn.XLOOKUP("Shareholder's Equity",Inputs!$B:$B,Inputs!H:H),"") -> 3.4099279 | H11: =IFERROR(_xlfn.XLOOKUP("Market Capitalization",Inputs!$B:$B,Inputs!I:I)/_xlfn.XLOOKUP("Shareholder's Equity",Inputs!$B:$B,Inputs!I:I),"") -> 4.397109 | I11: =IFERROR(_xlfn.XLOOKUP("Market Capitalization",Inputs!$B:$B,Inputs!J:J)/_xlfn.XLOOKUP("Shareholder's Equity",Inputs!$B:$B,Inputs!J:J),"") -> 3.0350439 | J11: =IFERROR(_xlfn.XLOOKUP("Market Capitalization",Inputs!$B:$B,Inputs!K:K)/_xlfn.XLOOKUP("Shareholder's Equity",Inputs!$B:$B,Inputs!K:K),"") -> 2.8213408 | K11: =IFERROR(_xlfn.XLOOKUP("Market Capitalization",Inputs!$B:$B,Inputs!L:L)/_xlfn.XLOOKUP("Shareholder's Equity",Inputs!$B:$B,Inputs!L:L),"") -> 4.1818102 | L11: =IFERROR(_xlfn.XLOOKUP("Market Capitalization",Inputs!$B:$B,Inputs!M:M)/_xlfn.XLOOKUP("Shareholder's Equity",Inputs!$B:$B,Inputs!M:M),"") -> 4.5385674 | M11: =IFERROR(_xlfn.XLOOKUP("Market Capitalization",Inputs!$B:$B,Inputs!N:N)/_xlfn.XLOOKUP("Shareholder's Equity",Inputs!$B:$B,Inputs!N:N),"") -> 1.8390048 | N11: =IFERROR(_xlfn.XLOOKUP("Market Capitalization",Inputs!$B:$B,Inputs!O:O)/_xlfn.XLOOKUP("Shareholder's Equity",Inputs!$B:$B,Inputs!O:O),"") -> 2.334779 | O11: =IFERROR(_xlfn.XLOOKUP("Market Capitalization",Inputs!$B:$B,Inputs!P:P)/_xlfn.XLOOKUP("Shareholder's Equity",Inputs!$B:$B,Inputs!P:P),"") -> 2.8037833 | P11: =IFERROR(_xlfn.XLOOKUP("Market Capitalization",Inputs!$B:$B,Inputs!Q:Q)/_xlfn.XLOOKUP("Shareholder's Equity",Inputs!$B:$B,Inputs!Q:Q),"") -> 2.9969796 | Q11: =IFERROR(+_xlfn.XLOOKUP("Equity Value",DCF!$B:$B,DCF!R:R)/(_xlfn.XLOOKUP("Shareholder's Equity",Inputs!$B:$B,Inputs!$Q:$Q)+_xlfn.XLOOKUP("Net Income",DCF!$B:$B,DCF!H:H)+_xlfn.XLOOKUP("Total Payout",DCF!$B:$B,DCF!H:H)),"") | R11: =IFERROR(+_xlfn.XLOOKUP("Equity Value",DCF!$B:$B,DCF!S:S)/(_xlfn.XLOOKUP("Shareholder's Equity",Inputs!$B:$B,Inputs!$Q:$Q)+_xlfn.XLOOKUP("Net Income",DCF!$B:$B,DCF!I:I)+_xlfn.XLOOKUP("Total Payout",DCF!$B:$B,DCF!I:I)),"")
B13: Profitability | F13: 2014 | G13: =+F13+1 -> 2015 | H13: =+G13+1 -> 2016 | I13: =+H13+1 -> 2017 | J13: =+I13+1 -> 2018 | K13: =+J13+1 -> 2019 | L13: =+K13+1 -> 2020 | M13: =+L13+1 -> 2021 | N13: 2022 | O13: =+N13+1 -> 2023 | P13: =+O13+1 -> 2024 | Q13: =+P13+1 -> 2025 | R13: =+Q13+1 -> 2026
B15: Return on Assets | F15: =+IFERROR(_xlfn.XLOOKUP("Net Income",Inputs!$B:$B,Inputs!G:G)/_xlfn.XLOOKUP("Total Assets",Inputs!$B:$B,Inputs!G:G),"") | G15: =+IFERROR(_xlfn.XLOOKUP("Net Income",Inputs!$B:$B,Inputs!H:H)/_xlfn.XLOOKUP("Total Assets",Inputs!$B:$B,Inputs!H:H),"") -> 0.085949453 | H15: =+IFERROR(_xlfn.XLOOKUP("Net Income",Inputs!$B:$B,Inputs!I:I)/_xlfn.XLOOKUP("Total Assets",Inputs!$B:$B,Inputs!I:I),"") -> 0.11363437 | I15: =+IFERROR(_xlfn.XLOOKUP("Net Income",Inputs!$B:$B,Inputs!J:J)/_xlfn.XLOOKUP("Total Assets",Inputs!$B:$B,Inputs!J:J),"") -> 0.053389149 | J15: =+IFERROR(_xlfn.XLOOKUP("Net Income",Inputs!$B:$B,Inputs!K:K)/_xlfn.XLOOKUP("Total Assets",Inputs!$B:$B,Inputs!K:K),"") -> 0.078597535 | K15: =+IFERROR(_xlfn.XLOOKUP("Net Income",Inputs!$B:$B,Inputs!L:L)/_xlfn.XLOOKUP("Total Assets",Inputs!$B:$B,Inputs!L:L),"") -> 0.064790855 | L15: =+IFERROR(_xlfn.XLOOKUP("Net Income",Inputs!$B:$B,Inputs!M:M)/_xlfn.XLOOKUP("Total Assets",Inputs!$B:$B,Inputs!M:M),"") -> 0.050389872 | M15: =+IFERROR(_xlfn.XLOOKUP("Net Income",Inputs!$B:$B,Inputs!N:N)/_xlfn.XLOOKUP("Total Assets",Inputs!$B:$B,Inputs!N:N),"") -> 0.025532232 | N15: =+IFERROR(_xlfn.XLOOKUP("Net Income",Inputs!$B:$B,Inputs!O:O)/_xlfn.XLOOKUP("Total Assets",Inputs!$B:$B,Inputs!O:O),"") -> 0.03945935 | O15: =+IFERROR(_xlfn.XLOOKUP("Net Income",Inputs!$B:$B,Inputs!P:P)/_xlfn.XLOOKUP("Total Assets",Inputs!$B:$B,Inputs!P:P),"") -> 0.049325231 | P15: =+IFERROR(_xlfn.XLOOKUP("Net Income",Inputs!$B:$B,Inputs!Q:Q)/_xlfn.XLOOKUP("Total Assets",Inputs!$B:$B,Inputs!Q:Q),"") -> 0.013359376 | Q15: =IFERROR(_xlfn.XLOOKUP("Net Income",DCF!$B:$B,DCF!H:H)/_xlfn.XLOOKUP("Total assets",DCF!$6:$6,DCF!10:10),"") -> 0.026078652 | R15: =IFERROR(_xlfn.XLOOKUP("Net Income",DCF!$B:$B,DCF!I:I)/_xlfn.XLOOKUP("Total assets",DCF!$6:$6,DCF!10:10),"") -> 0.034349512
B16: Return on Equity | F16: =IFERROR(_xlfn.XLOOKUP("Net Income",Inputs!$B:$B,Inputs!G:G)/_xlfn.XLOOKUP("Shareholder's Equity",Inputs!$B:$B,Inputs!G:G),"") | G16: =IFERROR(_xlfn.XLOOKUP("Net Income",Inputs!$B:$B,Inputs!H:H)/_xlfn.XLOOKUP("Shareholder's Equity",Inputs!$B:$B,Inputs!H:H),"") -> 0.11959393 | H16: =IFERROR(_xlfn.XLOOKUP("Net Income",Inputs!$B:$B,Inputs!I:I)/_xlfn.XLOOKUP("Shareholder's Equity",Inputs!$B:$B,Inputs!I:I),"") -> 0.17532958 | I16: =IFERROR(_xlfn.XLOOKUP("Net Income",Inputs!$B:$B,Inputs!J:J)/_xlfn.XLOOKUP("Shareholder's Equity",Inputs!$B:$B,Inputs!J:J),"") -> 0.11107831 | J16: =IFERROR(_xlfn.XLOOKUP("Net Income",Inputs!$B:$B,Inputs!K:K)/_xlfn.XLOOKUP("Shareholder's Equity",Inputs!$B:$B,Inputs!K:K),"") -> 0.14256048 | K16: =IFERROR(_xlfn.XLOOKUP("Net Income",Inputs!$B:$B,Inputs!L:L)/_xlfn.XLOOKUP("Shareholder's Equity",Inputs!$B:$B,Inputs!L:L),"") -> 0.12460435 | L16: =IFERROR(_xlfn.XLOOKUP("Net Income",Inputs!$B:$B,Inputs!M:M)/_xlfn.XLOOKUP("Shareholder's Equity",Inputs!$B:$B,Inputs!M:M),"") -> 0.090165779 | M16: =IFERROR(_xlfn.XLOOKUP("Net Income",Inputs!$B:$B,Inputs!N:N)/_xlfn.XLOOKUP("Shareholder's Equity",Inputs!$B:$B,Inputs!N:N),"") -> 0.035162111 | N16: =IFERROR(_xlfn.XLOOKUP("Net Income",Inputs!$B:$B,Inputs!O:O)/_xlfn.XLOOKUP("Shareholder's Equity",Inputs!$B:$B,Inputs!O:O),"") -> 0.05443257 | O16: =IFERROR(_xlfn.XLOOKUP("Net Income",Inputs!$B:$B,Inputs!P:P)/_xlfn.XLOOKUP("Shareholder's Equity",Inputs!$B:$B,Inputs!P:P),"") -> 0.067673084 | P16: =IFERROR(_xlfn.XLOOKUP("Net Income",Inputs!$B:$B,Inputs!Q:Q)/_xlfn.XLOOKUP("Shareholder's Equity",Inputs!$B:$B,Inputs!Q:Q),"") -> 0.01831631 | Q16: =IFERROR(_xlfn.XLOOKUP("Net Income",DCF!$B:$B,DCF!H:H)/_xlfn.XLOOKUP("Shareholder's Equity",DCF!$6:$6,DCF!10:10),"") | R16: =IFERROR(_xlfn.XLOOKUP("Net Income",DCF!$B:$B,DCF!I:I)/_xlfn.XLOOKUP("Shareholder's Equity",DCF!$6:$6,DCF!10:10),"")
B17: Return on Total Capital | F17: =IFERROR(_xlfn.XLOOKUP("NOPAT",Inputs!$B:$B,Inputs!G:G)/(_xlfn.XLOOKUP("Shareholder's Equity",Inputs!$B:$B,Inputs!G:G)+_xlfn.XLOOKUP("Total Debt",Inputs!$B:$B,Inputs!G:G,,,-1)),"") | G17: =IFERROR(_xlfn.XLOOKUP("NOPAT",Inputs!$B:$B,Inputs!H:H)/(_xlfn.XLOOKUP("Shareholder's Equity",Inputs!$B:$B,Inputs!H:H)+_xlfn.XLOOKUP("Total Debt",Inputs!$B:$B,Inputs!H:H,,,-1)),"") -> 0.099365476 | H17: =IFERROR(_xlfn.XLOOKUP("NOPAT",Inputs!$B:$B,Inputs!I:I)/(_xlfn.XLOOKUP("Shareholder's Equity",Inputs!$B:$B,Inputs!I:I)+_xlfn.XLOOKUP("Total Debt",Inputs!$B:$B,Inputs!I:I,,,-1)),"") -> 0.12821834 | I17: =IFERROR(_xlfn.XLOOKUP("NOPAT",Inputs!$B:$B,Inputs!J:J)/(_xlfn.XLOOKUP("Shareholder's Equity",Inputs!$B:$B,Inputs!J:J)+_xlfn.XLOOKUP("Total Debt",Inputs!$B:$B,Inputs!J:J,,,-1)),"") -> 0.061510937 | J17: =IFERROR(_xlfn.XLOOKUP("NOPAT",Inputs!$B:$B,Inputs!K:K)/(_xlfn.XLOOKUP("Shareholder's Equity",Inputs!$B:$B,Inputs!K:K)+_xlfn.XLOOKUP("Total Debt",Inputs!$B:$B,Inputs!K:K,,,-1)),"") -> 0.090387423 | K17: =IFERROR(_xlfn.XLOOKUP("NOPAT",Inputs!$B:$B,Inputs!L:L)/(_xlfn.XLOOKUP("Shareholder's Equity",Inputs!$B:$B,Inputs!L:L)+_xlfn.XLOOKUP("Total Debt",Inputs!$B:$B,Inputs!L:L,,,-1)),"") -> 0.081463257 | L17: =IFERROR(_xlfn.XLOOKUP("NOPAT",Inputs!$B:$B,Inputs!M:M)/(_xlfn.XLOOKUP("Shareholder's Equity",Inputs!$B:$B,Inputs!M:M)+_xlfn.XLOOKUP("Total Debt",Inputs!$B:$B,Inputs!M:M,,,-1)),"") -> 0.062916135 | M17: =IFERROR(_xlfn.XLOOKUP("NOPAT",Inputs!$B:$B,Inputs!N:N)/(_xlfn.XLOOKUP("Shareholder's Equity",Inputs!$B:$B,Inputs!N:N)+_xlfn.XLOOKUP("Total Debt",Inputs!$B:$B,Inputs!N:N,,,-1)),"") -> 0.029015043 | N17: =IFERROR(_xlfn.XLOOKUP("NOPAT",Inputs!$B:$B,Inputs!O:O)/(_xlfn.XLOOKUP("Shareholder's Equity",Inputs!$B:$B,Inputs!O:O)+_xlfn.XLOOKUP("Total Debt",Inputs!$B:$B,Inputs!O:O,,,-1)),"") -> 0.044825467 | O17: =IFERROR(_xlfn.XLOOKUP("NOPAT",Inputs!$B:$B,Inputs!P:P)/(_xlfn.XLOOKUP("Shareholder's Equity",Inputs!$B:$B,Inputs!P:P)+_xlfn.XLOOKUP("Total Debt",Inputs!$B:$B,Inputs!P:P,,,-1)),"") -> 0.055565875 | P17: =IFERROR(_xlfn.XLOOKUP("NOPAT",Inputs!$B:$B,Inputs!Q:Q)/(_xlfn.XLOOKUP("Shareholder's Equity",Inputs!$B:$B,Inputs!Q:Q)+_xlfn.XLOOKUP("Total Debt",Inputs!$B:$B,Inputs!Q:Q,,,-1)),"") -> 0.013807737 | Q17: =+IFERROR(_xlfn.XLOOKUP("NOPAT",DCF!$B:$B,DCF!H:H)/(_xlfn.XLOOKUP("Shareholder's Equity",DCF!$6:$6,DCF!10:10)+_xlfn.XLOOKUP("Total Borrowings",DCF!$B:$B,DCF!H:H)+_xlfn.XLOOKUP("Total Leases",DCF!$B:$B,DCF!H:H)),"") | R17: =+IFERROR(_xlfn.XLOOKUP("NOPAT",DCF!$B:$B,DCF!I:I)/(_xlfn.XLOOKUP("Shareholder's Equity",DCF!$6:$6,DCF!10:10)+_xlfn.XLOOKUP("Total Borrowings",DCF!$B:$B,DCF!I:I)+_xlfn.XLOOKUP("Total Leases",DCF!$B:$B,DCF!I:I)),"")
B18: EBITDA Margin | F18: =+IFERROR(_xlfn.XLOOKUP("EBITDA",Inputs!$B:$B,Inputs!G:G)/_xlfn.XLOOKUP("Revenue (Sales)",Inputs!$B:$B,Inputs!G:G),"") | G18: =+IFERROR(_xlfn.XLOOKUP("EBITDA",Inputs!$B:$B,Inputs!H:H)/_xlfn.XLOOKUP("Revenue (Sales)",Inputs!$B:$B,Inputs!H:H),"") -> 0.26756135 | H18: =+IFERROR(_xlfn.XLOOKUP("EBITDA",Inputs!$B:$B,Inputs!I:I)/_xlfn.XLOOKUP("Revenue (Sales)",Inputs!$B:$B,Inputs!I:I),"") -> 0.32501315 | I18: =+IFERROR(_xlfn.XLOOKUP("EBITDA",Inputs!$B:$B,Inputs!J:J)/_xlfn.XLOOKUP("Revenue (Sales)",Inputs!$B:$B,Inputs!J:J),"") -> 0.27449829 | J18: =+IFERROR(_xlfn.XLOOKUP("EBITDA",Inputs!$B:$B,Inputs!K:K)/_xlfn.XLOOKUP("Revenue (Sales)",Inputs!$B:$B,Inputs!K:K),"") -> 0.38393818 | K18: =+IFERROR(_xlfn.XLOOKUP("EBITDA",Inputs!$B:$B,Inputs!L:L)/_xlfn.XLOOKUP("Revenue (Sales)",Inputs!$B:$B,Inputs!L:L),"") -> 0.37312013 | L18: =+IFERROR(_xlfn.XLOOKUP("EBITDA",Inputs!$B:$B,Inputs!M:M)/_xlfn.XLOOKUP("Revenue (Sales)",Inputs!$B:$B,Inputs!M:M),"") -> 0.35339366 | M18: =+IFERROR(_xlfn.XLOOKUP("EBITDA",Inputs!$B:$B,Inputs!N:N)/_xlfn.XLOOKUP("Revenue (Sales)",Inputs!$B:$B,Inputs!N:N),"") -> 0.31612533 | N18: =+IFERROR(_xlfn.XLOOKUP("EBITDA",Inputs!$B:$B,Inputs!O:O)/_xlfn.XLOOKUP("Revenue (Sales)",Inputs!$B:$B,Inputs!O:O),"") -> 0.38003995 | O18: =+IFERROR(_xlfn.XLOOKUP("EBITDA",Inputs!$B:$B,Inputs!P:P)/_xlfn.XLOOKUP("Revenue (Sales)",Inputs!$B:$B,Inputs!P:P),"") -> 0.40172281 | P18: =+IFERROR(_xlfn.XLOOKUP("EBITDA",Inputs!$B:$B,Inputs!Q:Q)/_xlfn.XLOOKUP("Revenue (Sales)",Inputs!$B:$B,Inputs!Q:Q),"") -> 0.29965419 | Q18: =+_xlfn.XLOOKUP("EBITDA Margin",DCF!$B:$B,DCF!H:H) -> 0.34664735 | R18: =+_xlfn.XLOOKUP("EBITDA Margin",DCF!$B:$B,DCF!I:I) -> 0.35164735
B19: EBIT Margin | F19: =IFERROR(_xlfn.XLOOKUP("Operating Income (EBIT)",Inputs!$B:$B,Inputs!G:G)/_xlfn.XLOOKUP("Revenue (Sales)",Inputs!$B:$B,Inputs!G:G),"") | G19: =IFERROR(_xlfn.XLOOKUP("Operating Income (EBIT)",Inputs!$B:$B,Inputs!H:H)/_xlfn.XLOOKUP("Revenue (Sales)",Inputs!$B:$B,Inputs!H:H),"") -> 0.20398242 | H19: =IFERROR(_xlfn.XLOOKUP("Operating Income (EBIT)",Inputs!$B:$B,Inputs!I:I)/_xlfn.XLOOKUP("Revenue (Sales)",Inputs!$B:$B,Inputs!I:I),"") -> 0.28570176 | I19: =IFERROR(_xlfn.XLOOKUP("Operating Income (EBIT)",Inputs!$B:$B,Inputs!J:J)/_xlfn.XLOOKUP("Revenue (Sales)",Inputs!$B:$B,Inputs!J:J),"") -> 0.23637788 | J19: =IFERROR(_xlfn.XLOOKUP("Operating Income (EBIT)",Inputs!$B:$B,Inputs!K:K)/_xlfn.XLOOKUP("Revenue (Sales)",Inputs!$B:$B,Inputs!K:K),"") -> 0.25557858 | K19: =IFERROR(_xlfn.XLOOKUP("Operating Income (EBIT)",Inputs!$B:$B,Inputs!L:L)/_xlfn.XLOOKUP("Revenue (Sales)",Inputs!$B:$B,Inputs!L:L),"") -> 0.23770259 | L19: =IFERROR(_xlfn.XLOOKUP("Operating Income (EBIT)",Inputs!$B:$B,Inputs!M:M)/_xlfn.XLOOKUP("Revenue (Sales)",Inputs!$B:$B,Inputs!M:M),"") -> 0.2086702 | M19: =IFERROR(_xlfn.XLOOKUP("Operating Income (EBIT)",Inputs!$B:$B,Inputs!N:N)/_xlfn.XLOOKUP("Revenue (Sales)",Inputs!$B:$B,Inputs!N:N),"") -> 0.16927429 | N19: =IFERROR(_xlfn.XLOOKUP("Operating Income (EBIT)",Inputs!$B:$B,Inputs!O:O)/_xlfn.XLOOKUP("Revenue (Sales)",Inputs!$B:$B,Inputs!O:O),"") -> 0.18880473 | O19: =IFERROR(_xlfn.XLOOKUP("Operating Income (EBIT)",Inputs!$B:$B,Inputs!P:P)/_xlfn.XLOOKUP("Revenue (Sales)",Inputs!$B:$B,Inputs!P:P),"") -> 0.21537524 | P19: =IFERROR(_xlfn.XLOOKUP("Operating Income (EBIT)",Inputs!$B:$B,Inputs!Q:Q)/_xlfn.XLOOKUP("Revenue (Sales)",Inputs!$B:$B,Inputs!Q:Q),"") -> 0.076438391 | Q19: =+_xlfn.XLOOKUP("Operating Margin",DCF!$B:$B,DCF!H:H) -> 0.15489657 | R19: =+_xlfn.XLOOKUP("Operating Margin",DCF!$B:$B,DCF!I:I) -> 0.18137667
B20: EBT Margin | F20: =IFERROR(_xlfn.XLOOKUP("Pre-Tax Income (EBT)",Inputs!$B:$B,Inputs!G:G)/_xlfn.XLOOKUP("Revenue (Sales)",Inputs!$B:$B,Inputs!G:G),"") | G20: =IFERROR(_xlfn.XLOOKUP("Pre-Tax Income (EBT)",Inputs!$B:$B,Inputs!H:H)/_xlfn.XLOOKUP("Revenue (Sales)",Inputs!$B:$B,Inputs!H:H),"") -> 0.20957177 | H20: =IFERROR(_xlfn.XLOOKUP("Pre-Tax Income (EBT)",Inputs!$B:$B,Inputs!I:I)/_xlfn.XLOOKUP("Revenue (Sales)",Inputs!$B:$B,Inputs!I:I),"") -> 0.29257029 | I20: =IFERROR(_xlfn.XLOOKUP("Pre-Tax Income (EBT)",Inputs!$B:$B,Inputs!J:J)/_xlfn.XLOOKUP("Revenue (Sales)",Inputs!$B:$B,Inputs!J:J),"") -> 0.24080274 | J20: =IFERROR(_xlfn.XLOOKUP("Pre-Tax Income (EBT)",Inputs!$B:$B,Inputs!K:K)/_xlfn.XLOOKUP("Revenue (Sales)",Inputs!$B:$B,Inputs!K:K),"") -> 0.25806866 | K20: =IFERROR(_xlfn.XLOOKUP("Pre-Tax Income (EBT)",Inputs!$B:$B,Inputs!L:L)/_xlfn.XLOOKUP("Revenue (Sales)",Inputs!$B:$B,Inputs!L:L),"") -> 0.23863731 | L20: =IFERROR(_xlfn.XLOOKUP("Pre-Tax Income (EBT)",Inputs!$B:$B,Inputs!M:M)/_xlfn.XLOOKUP("Revenue (Sales)",Inputs!$B:$B,Inputs!M:M),"") -> 0.20929485 | M20: =IFERROR(_xlfn.XLOOKUP("Pre-Tax Income (EBT)",Inputs!$B:$B,Inputs!N:N)/_xlfn.XLOOKUP("Revenue (Sales)",Inputs!$B:$B,Inputs!N:N),"") -> 0.17411147 | N20: =IFERROR(_xlfn.XLOOKUP("Pre-Tax Income (EBT)",Inputs!$B:$B,Inputs!O:O)/_xlfn.XLOOKUP("Revenue (Sales)",Inputs!$B:$B,Inputs!O:O),"") -> 0.19436491 | O20: =IFERROR(_xlfn.XLOOKUP("Pre-Tax Income (EBT)",Inputs!$B:$B,Inputs!P:P)/_xlfn.XLOOKUP("Revenue (Sales)",Inputs!$B:$B,Inputs!P:P),"") -> 0.21943034 | P20: =IFERROR(_xlfn.XLOOKUP("Pre-Tax Income (EBT)",Inputs!$B:$B,Inputs!Q:Q)/_xlfn.XLOOKUP("Revenue (Sales)",Inputs!$B:$B,Inputs!Q:Q),"") -> 0.083418194 | Q20: =IFERROR(_xlfn.XLOOKUP("Pre-Tax Income (EBT)",DCF!$B:$B,DCF!H:H)/_xlfn.XLOOKUP("Revenue (Sales)",DCF!$B:$B,DCF!H:H),"") -> 0.15524309 | R20: =IFERROR(_xlfn.XLOOKUP("Pre-Tax Income (EBT)",DCF!$B:$B,DCF!I:I)/_xlfn.XLOOKUP("Revenue (Sales)",DCF!$B:$B,DCF!I:I),"") -> 0.18136962
B21: Gross Profit Margin | F21: =IFERROR(_xlfn.XLOOKUP("Gross Profit",Inputs!$B:$B,Inputs!G:G)/_xlfn.XLOOKUP("Revenue (Sales)",Inputs!$B:$B,Inputs!G:G),"") | G21: =IFERROR(_xlfn.XLOOKUP("Gross Profit",Inputs!$B:$B,Inputs!H:H)/_xlfn.XLOOKUP("Revenue (Sales)",Inputs!$B:$B,Inputs!H:H),"") -> 0.65771011 | H21: =IFERROR(_xlfn.XLOOKUP("Gross Profit",Inputs!$B:$B,Inputs!I:I)/_xlfn.XLOOKUP("Revenue (Sales)",Inputs!$B:$B,Inputs!I:I),"") -> 0.65096159 | I21: =IFERROR(_xlfn.XLOOKUP("Gross Profit",Inputs!$B:$B,Inputs!J:J)/_xlfn.XLOOKUP("Revenue (Sales)",Inputs!$B:$B,Inputs!J:J),"") -> 0.59943221 | J21: =IFERROR(_xlfn.XLOOKUP("Gross Profit",Inputs!$B:$B,Inputs!K:K)/_xlfn.XLOOKUP("Revenue (Sales)",Inputs!$B:$B,Inputs!K:K),"") -> 0.68282809 | K21: =IFERROR(_xlfn.XLOOKUP("Gross Profit",Inputs!$B:$B,Inputs!L:L)/_xlfn.XLOOKUP("Revenue (Sales)",Inputs!$B:$B,Inputs!L:L),"") -> 0.66996044 | L21: =IFERROR(_xlfn.XLOOKUP("Gross Profit",Inputs!$B:$B,Inputs!M:M)/_xlfn.XLOOKUP("Revenue (Sales)",Inputs!$B:$B,Inputs!M:M),"") -> 0.65865325 | M21: =IFERROR(_xlfn.XLOOKUP("Gross Profit",Inputs!$B:$B,Inputs!N:N)/_xlfn.XLOOKUP("Revenue (Sales)",Inputs!$B:$B,Inputs!N:N),"") -> 0.618313 | N21: =IFERROR(_xlfn.XLOOKUP("Gross Profit",Inputs!$B:$B,Inputs!O:O)/_xlfn.XLOOKUP("Revenue (Sales)",Inputs!$B:$B,Inputs!O:O),"") -> 0.62697686 | O21: =IFERROR(_xlfn.XLOOKUP("Gross Profit",Inputs!$B:$B,Inputs!P:P)/_xlfn.XLOOKUP("Revenue (Sales)",Inputs!$B:$B,Inputs!P:P),"") -> 0.64013652 | P21: =IFERROR(_xlfn.XLOOKUP("Gross Profit",Inputs!$B:$B,Inputs!Q:Q)/_xlfn.XLOOKUP("Revenue (Sales)",Inputs!$B:$B,Inputs!Q:Q),"") -> 0.57083758 | Q21: =+_xlfn.XLOOKUP("Gross Profit Margin",DCF!$B:$B,DCF!H:H) -> 0.62 | R21: =+_xlfn.XLOOKUP("Gross Profit Margin",DCF!$B:$B,DCF!I:I) -> 0.625
B22: SG&A Margin | F22: =IFERROR(+_xlfn.XLOOKUP("SG&A (Selling, General & Administrative)",Inputs!$B:$B,Inputs!G:G)/_xlfn.XLOOKUP("Revenue (Sales)",Inputs!$B:$B,Inputs!G:G),"") | G22: =IFERROR(+_xlfn.XLOOKUP("SG&A (Selling, General & Administrative)",Inputs!$B:$B,Inputs!H:H)/_xlfn.XLOOKUP("Revenue (Sales)",Inputs!$B:$B,Inputs!H:H),"") -> 0.13944281 | H22: =IFERROR(+_xlfn.XLOOKUP("SG&A (Selling, General & Administrative)",Inputs!$B:$B,Inputs!I:I)/_xlfn.XLOOKUP("Revenue (Sales)",Inputs!$B:$B,Inputs!I:I),"") -> 0.13485708 | I22: =IFERROR(+_xlfn.XLOOKUP("SG&A (Selling, General & Administrative)",Inputs!$B:$B,Inputs!J:J)/_xlfn.XLOOKUP("Revenue (Sales)",Inputs!$B:$B,Inputs!J:J),"") -> 0.13529124 | J22: =IFERROR(+_xlfn.XLOOKUP("SG&A (Selling, General & Administrative)",Inputs!$B:$B,Inputs!K:K)/_xlfn.XLOOKUP("Revenue (Sales)",Inputs!$B:$B,Inputs!K:K),"") -> 0.11173229 | K22: =IFERROR(+_xlfn.XLOOKUP("SG&A (Selling, General & Administrative)",Inputs!$B:$B,Inputs!L:L)/_xlfn.XLOOKUP("Revenue (Sales)",Inputs!$B:$B,Inputs!L:L),"") -> 0.10817713 | L22: =IFERROR(+_xlfn.XLOOKUP("SG&A (Selling, General & Administrative)",Inputs!$B:$B,Inputs!M:M)/_xlfn.XLOOKUP("Revenue (Sales)",Inputs!$B:$B,Inputs!M:M),"") -> 0.11777409 | M22: =IFERROR(+_xlfn.XLOOKUP("SG&A (Selling, General & Administrative)",Inputs!$B:$B,Inputs!N:N)/_xlfn.XLOOKUP("Revenue (Sales)",Inputs!$B:$B,Inputs!N:N),"") -> 0.12508369 | N22: =IFERROR(+_xlfn.XLOOKUP("SG&A (Selling, General & Administrative)",Inputs!$B:$B,Inputs!O:O)/_xlfn.XLOOKUP("Revenue (Sales)",Inputs!$B:$B,Inputs!O:O),"") -> 0.10539371 | O22: =IFERROR(+_xlfn.XLOOKUP("SG&A (Selling, General & Administrative)",Inputs!$B:$B,Inputs!P:P)/_xlfn.XLOOKUP("Revenue (Sales)",Inputs!$B:$B,Inputs!P:P),"") -> 0.10349844 | P22: =IFERROR(+_xlfn.XLOOKUP("SG&A (Selling, General & Administrative)",Inputs!$B:$B,Inputs!Q:Q)/_xlfn.XLOOKUP("Revenue (Sales)",Inputs!$B:$B,Inputs!Q:Q),"") -> 0.11335285 | Q22: =+_xlfn.XLOOKUP("SG&A Margin",DCF!$B:$B,DCF!H:H) -> 0.107415 | R22: =+_xlfn.XLOOKUP("SG&A Margin",DCF!$B:$B,DCF!I:I) -> 0.10808876
B23: Net Income Margin | F23: =IFERROR(_xlfn.XLOOKUP("Net Income",Inputs!$B:$B,Inputs!G:G)/_xlfn.XLOOKUP("Revenue (Sales)",Inputs!$B:$B,Inputs!G:G),"") | G23: =IFERROR(_xlfn.XLOOKUP("Net Income",Inputs!$B:$B,Inputs!H:H)/_xlfn.XLOOKUP("Revenue (Sales)",Inputs!$B:$B,Inputs!H:H),"") -> 0.17661786 | H23: =IFERROR(_xlfn.XLOOKUP("Net Income",Inputs!$B:$B,Inputs!I:I)/_xlfn.XLOOKUP("Revenue (Sales)",Inputs!$B:$B,Inputs!I:I),"") -> 0.2647162 | I23: =IFERROR(_xlfn.XLOOKUP("Net Income",Inputs!$B:$B,Inputs!J:J)/_xlfn.XLOOKUP("Revenue (Sales)",Inputs!$B:$B,Inputs!J:J),"") -> 0.22098874 | J23: =IFERROR(_xlfn.XLOOKUP("Net Income",Inputs!$B:$B,Inputs!K:K)/_xlfn.XLOOKUP("Revenue (Sales)",Inputs!$B:$B,Inputs!K:K),"") -> 0.25806866 | K23: =IFERROR(_xlfn.XLOOKUP("Net Income",Inputs!$B:$B,Inputs!L:L)/_xlfn.XLOOKUP("Revenue (Sales)",Inputs!$B:$B,Inputs!L:L),"") -> 0.21815693 | L23: =IFERROR(_xlfn.XLOOKUP("Net Income",Inputs!$B:$B,Inputs!M:M)/_xlfn.XLOOKUP("Revenue (Sales)",Inputs!$B:$B,Inputs!M:M),"") -> 0.19307169 | M23: =IFERROR(_xlfn.XLOOKUP("Net Income",Inputs!$B:$B,Inputs!N:N)/_xlfn.XLOOKUP("Revenue (Sales)",Inputs!$B:$B,Inputs!N:N),"") -> 0.18254239 | N23: =IFERROR(_xlfn.XLOOKUP("Net Income",Inputs!$B:$B,Inputs!O:O)/_xlfn.XLOOKUP("Revenue (Sales)",Inputs!$B:$B,Inputs!O:O),"") -> 0.16521558 | O23: =IFERROR(_xlfn.XLOOKUP("Net Income",Inputs!$B:$B,Inputs!P:P)/_xlfn.XLOOKUP("Revenue (Sales)",Inputs!$B:$B,Inputs!P:P),"") -> 0.19558734 | P23: =IFERROR(_xlfn.XLOOKUP("Net Income",Inputs!$B:$B,Inputs!Q:Q)/_xlfn.XLOOKUP("Revenue (Sales)",Inputs!$B:$B,Inputs!Q:Q),"") -> 0.06834479 | Q23: =+_xlfn.XLOOKUP("Net Income Margin",DCF!$B:$B,DCF!H:H) -> 0.13255964 | R23: =+_xlfn.XLOOKUP("Net Income Margin",DCF!$B:$B,DCF!I:I) -> 0.15502176
B25: Liquidity | F25: 2014 | G25: =+F25+1 -> 2015 | H25: =+G25+1 -> 2016 | I25: =+H25+1 -> 2017 | J25: =+I25+1 -> 2018 | K25: =+J25+1 -> 2019 | L25: =+K25+1 -> 2020 | M25: =+L25+1 -> 2021 | N25: 2022 | O25: =+N25+1 -> 2023 | P25: =+O25+1 -> 2024 | Q25: =+P25+1 -> 2025 | R25: =+Q25+1 -> 2026
