Workbook
Name COOLFUCNTION: _xlfn.LAMBDA(_xldudf_BOARDFLARE_EXEC("workbook-settings:coolfucntion"))
Name COOLFUCNTION: _xlfn.LAMBDA(_xldudf_BOARDFLARE_EXEC("workbook-settings:coolfucntion"))
Name COOLFUCNTION: _xlfn.LAMBDA(_xldudf_BOARDFLARE_EXEC("workbook-settings:coolfucntion"))
Name COOLFUCNTION: _xlfn.LAMBDA(_xldudf_BOARDFLARE_EXEC("workbook-settings:coolfucntion"))
Name COOLFUCNTION: _xlfn.LAMBDA(_xldudf_BOARDFLARE_EXEC("workbook-settings:coolfucntion"))
Name COOLFUCNTION: _xlfn.LAMBDA(_xldudf_BOARDFLARE_EXEC("workbook-settings:coolfucntion"))
Name COOLFUCNTION: _xlfn.LAMBDA(_xldudf_BOARDFLARE_EXEC("workbook-settings:coolfucntion"))
Name COOLFUCNTION: _xlfn.LAMBDA(_xldudf_BOARDFLARE_EXEC("workbook-settings:coolfucntion"))
Name COOLFUCNTION: _xlfn.LAMBDA(_xldudf_BOARDFLARE_EXEC("workbook-settings:coolfucntion"))
Name COOLFUCNTION: _xlfn.LAMBDA(_xldudf_BOARDFLARE_EXEC("workbook-settings:coolfucntion"))
Name Sectors: #REF!
Name Sectors: #REF!
Name Sectors: #REF!

Sheet Summary
E2: | EQUITY RESEARCH | U2: Lisbon Investment Society Equity Research
U3: March XX, 2025
D6: {=+_FV(DCF!R4,"Name")} -> D-WAVE QUANTUM INC. | U6: Hold
U8: EXCHANGE:(TICKER)
U9: {=+"Price (7 Mar 25): $"&_FV(DCF!$R$4,"Price")} -> Price (7 Mar 25): $24,7
D10: Investment Thesis | U10: ="Price Target: $" & ROUND(IF(Summary!G25="FCFF",DCF!Q207,IF(Summary!G25="FCFE",DCF!Q250,IF(Summary!G25="Tax Shield",DCF!Q223,DCF!Q266))),2) &" "&IF(Summary!G25="FCFF","(FCFF)",IF(Summary!G25="FCFE","(FCFE)",IF(Summary!G25="Tax Shield","(APV)","(DDM)"))) -> Price Target: $0 (FCFF)
U11: =+"Upside (Downside): "&ROUND((DCF!$Q$210*100),2)&"%" -> Upside (Downside): 0%
U14: =+Industry!E28&", "&ESG!C9 -> Canada,
U15: =+ESG!C10 -> 0
D17: Operating Metrics | F17: 2023 | G17: =+F17+1 -> 2024 | H17: =+G17+1 -> 2025 | I17: =+H17+1 -> 2026 | K17: Valuation Multiples | N17: 2022 | O17: =+N17+1 -> 2023 | P17: =+O17+1 -> 2024 | Q17: =+P17+1 -> 2025 | R17: =+Q17+1 -> 2026 | U17: Team Leader
K18: EV / Sales | N18: =IFERROR(_xlfn.XLOOKUP($K18,Multiples!$B:$B,Multiples!N:N),"") -> 24.922219 | O18: =IFERROR(_xlfn.XLOOKUP($K18,Multiples!$B:$B,Multiples!O:O),"") -> 10.296131 | P18: =IFERROR(_xlfn.XLOOKUP($K18,Multiples!$B:$B,Multiples!P:P),"") -> 167.01944 | Q18: =IFERROR(_xlfn.XLOOKUP($K18,Multiples!$B:$B,Multiples!Q:Q),"") -> 816.67187 | R18: =IFERROR(_xlfn.XLOOKUP($K18,Multiples!$B:$B,Multiples!R:R),"") -> 1811.9274 | U18: email
K19: Price / Sales | N19: =IFERROR(_xlfn.XLOOKUP($K19,Multiples!$B:$B,Multiples!N:N),"") -> 24.35328 | O19: =IFERROR(_xlfn.XLOOKUP($K19,Multiples!$B:$B,Multiples!O:O),"") -> 13.867152 | P19: =IFERROR(_xlfn.XLOOKUP($K19,Multiples!$B:$B,Multiples!P:P),"") -> 182.83489 | Q19: =IFERROR(_xlfn.XLOOKUP($K19,Multiples!$B:$B,Multiples!Q:Q),"") -> 0 | R19: =IFERROR(_xlfn.XLOOKUP($K19,Multiples!$B:$B,Multiples!R:R),"") -> 0 | U19: (+351) 999 999 999
K20: EV / EBITDA | N20: =IFERROR(_xlfn.XLOOKUP($K20,Multiples!$B:$B,Multiples!N:N),"") -> -3.1294018 | O20: =IFERROR(_xlfn.XLOOKUP($K20,Multiples!$B:$B,Multiples!O:O),"") -> -1.1955706 | P20: =IFERROR(_xlfn.XLOOKUP($K20,Multiples!$B:$B,Multiples!P:P),"") -> -21.275732 | Q20: =IFERROR(_xlfn.XLOOKUP($K20,Multiples!$B:$B,Multiples!Q:Q),"") -> -139.41592 | R20: =IFERROR(_xlfn.XLOOKUP($K20,Multiples!$B:$B,Multiples!R:R),"") -> -390.87 | U20: Analyst 1
K21: EV / EBIT | N21: =IFERROR(_xlfn.XLOOKUP($K21,Multiples!$B:$B,Multiples!N:N),"") -> 22.345885 | O21: =IFERROR(_xlfn.XLOOKUP($K21,Multiples!$B:$B,Multiples!O:O),"") -> -1.1670228 | P21: =IFERROR(_xlfn.XLOOKUP($K21,Multiples!$B:$B,Multiples!P:P),"") -> -20.255002 | Q21: =IFERROR(_xlfn.XLOOKUP($K21,Multiples!$B:$B,Multiples!Q:Q),"") -> -139.41592 | R21: =IFERROR(_xlfn.XLOOKUP($K21,Multiples!$B:$B,Multiples!R:R),"") -> -390.87 | U21: email
K22: Price / Earnings | N22: =IFERROR(_xlfn.XLOOKUP($K22,Multiples!$B:$B,Multiples!N:N),"") -> -3.2528785 | O22: =IFERROR(_xlfn.XLOOKUP($K22,Multiples!$B:$B,Multiples!O:O),"") -> -1.4682768 | P22: =IFERROR(_xlfn.XLOOKUP($K22,Multiples!$B:$B,Multiples!P:P),"") -> -11.21695 | Q22: =IFERROR(_xlfn.XLOOKUP($K22,Multiples!$B:$B,Multiples!Q:Q),"") -> 0 | R22: =IFERROR(_xlfn.XLOOKUP($K22,Multiples!$B:$B,Multiples!R:R),"") -> 0 | U22: (+351) 999 999 999
K23: Price / Book | N23: =IFERROR(_xlfn.XLOOKUP($K23,Multiples!$B:$B,Multiples!N:N),"") -> -5.9289984 | O23: =IFERROR(_xlfn.XLOOKUP($K23,Multiples!$B:$B,Multiples!O:O),"") -> -4.9609297 | P23: =IFERROR(_xlfn.XLOOKUP($K23,Multiples!$B:$B,Multiples!P:P),"") -> 25.761958 | Q23: =IFERROR(_xlfn.XLOOKUP($K23,Multiples!$B:$B,Multiples!Q:Q),"") -> 0 | R23: =IFERROR(_xlfn.XLOOKUP($K23,Multiples!$B:$B,Multiples!R:R),"") -> 0 | U23: Analyst 2
U24: email
D25: Year | E25: Net Sales | F25: EBIT Margin | G25: FCFF | H25: =+IF(Summary!$G$25="FCFF",DCF!AB6,IF(Summary!$G$25="FCFE",DCF!AC6,DCF!AD6)) -> NOPAT | I25: Net Capex | K25: Profitability Ratios | N25: 2022 | O25: =+N25+1 -> 2023 | P25: =+O25+1 -> 2024 | Q25: =+P25+1 -> 2025 | R25: =+Q25+1 -> 2026 | U25: (+351) 999 999 999
D26: 2022 | E26: =+DCF!E28 -> 7.173 | F26: =+DCF!E58 -> 1.1152935 | G26: =+INDEX(DCF!X7:AA7,MATCH(Summary!$G$25,{"FCFF","FCFE","Tax Shield","Total Payout"},0)) -> 22.096 | H26: =+IF(Summary!$G$25="FCFF",DCF!AB7,IF(Summary!$G$25="FCFE",DCF!AC7,DCF!AD7)) -> 8 | I26: =+DCF!E132 -> -0.423 | K26: Return on Assets | N26: =IFERROR(_xlfn.XLOOKUP($K26,Multiples!$B:$B,Multiples!N:N),"") -> -1.9928749 | O26: =IFERROR(_xlfn.XLOOKUP($K26,Multiples!$B:$B,Multiples!O:O),"") -> -1.3935407 | P26: =IFERROR(_xlfn.XLOOKUP($K26,Multiples!$B:$B,Multiples!P:P),"") -> -0.71992414 | Q26: =IFERROR(_xlfn.XLOOKUP($K26,Multiples!$B:$B,Multiples!Q:Q),"") -> -0.49141907 | R26: =IFERROR(_xlfn.XLOOKUP($K26,Multiples!$B:$B,Multiples!R:R),"") -> -0.68204232 | U26: Analyst 3
D27: =+D26+1 -> 2023 | E27: =+DCF!F28 -> 8.758 | F27: =+DCF!F58 -> -8.8225622 | G27: =+INDEX(DCF!X8:AA8,MATCH(Summary!$G$25,{"FCFF","FCFE","Tax Shield","Total Payout"},0)) -> -56.785 | H27: =+IF(Summary!$G$25="FCFF",DCF!AB8,IF(Summary!$G$25="FCFE",DCF!AC8,DCF!AD8)) -> -77.268 | I27: =+DCF!F132 -> -0.583 | K27: Return on Equity | N27: =IFERROR(_xlfn.XLOOKUP($K27,Multiples!$B:$B,Multiples!N:N),"") -> 1.8226929 | O27: =IFERROR(_xlfn.XLOOKUP($K27,Multiples!$B:$B,Multiples!O:O),"") -> 3.3787427 | P27: =IFERROR(_xlfn.XLOOKUP($K27,Multiples!$B:$B,Multiples!P:P),"") -> -2.2966989 | Q27: =IFERROR(_xlfn.XLOOKUP($K27,Multiples!$B:$B,Multiples!Q:Q),"") -> 0.011408475 | R27: =IFERROR(_xlfn.XLOOKUP($K27,Multiples!$B:$B,Multiples!R:R),"") -> 0.015833864 | U27: email
D28: =+D27+1 -> 2024 | E28: =+DCF!G28 -> 8.827 | F28: =+DCF!G58 -> -8.2458366 | G28: =+INDEX(DCF!X9:AA9,MATCH(Summary!$G$25,{"FCFF","FCFE","Tax Shield","Total Payout"},0)) -> -36.726 | H28: =+IF(Summary!$G$25="FCFF",DCF!AB9,IF(Summary!$G$25="FCFE",DCF!AC9,DCF!AD9)) -> -72.786 | I28: =+DCF!G132 -> -2.395 | K28: Return on Total Capital | N28: =IFERROR(_xlfn.XLOOKUP($K28,Multiples!$B:$B,Multiples!N:N),"") -> -0.43675274 | O28: =IFERROR(_xlfn.XLOOKUP($K28,Multiples!$B:$B,Multiples!O:O),"") -> 5.3476365 | P28: =IFERROR(_xlfn.XLOOKUP($K28,Multiples!$B:$B,Multiples!P:P),"") -> -0.72048939 | Q28: =IFERROR(_xlfn.XLOOKUP($K28,Multiples!$B:$B,Multiples!Q:Q),"") -> 0.0087592764 | R28: =IFERROR(_xlfn.XLOOKUP($K28,Multiples!$B:$B,Multiples!R:R),"") -> 0.011116745 | U28: (+351) 999 999 999
D29: =+D28+1 -> 2025 | E29: =+DCF!H28 -> 14.1232 | F29: =+DCF!H58 -> -5.8578094 | G29: =+INDEX(DCF!X10:AA10,MATCH(Summary!$G$25,{"FCFF","FCFE","Tax Shield","Total Payout"},0)) -> -70.28795 | H29: =+IF(Summary!$G$25="FCFF",DCF!AB10,IF(Summary!$G$25="FCFE",DCF!AC10,DCF!AD10)) -> -82.731013 | I29: =+DCF!H132 -> 0 | K29: EBITDA Margin | N29: =IFERROR(_xlfn.XLOOKUP($K29,Multiples!$B:$B,Multiples!N:N),"") -> -7.9638924 | O29: =IFERROR(_xlfn.XLOOKUP($K29,Multiples!$B:$B,Multiples!O:O),"") -> -8.6118977 | P29: =IFERROR(_xlfn.XLOOKUP($K29,Multiples!$B:$B,Multiples!P:P),"") -> -7.8502322 | Q29: =IFERROR(_xlfn.XLOOKUP($K29,Multiples!$B:$B,Multiples!Q:Q),"") -> -5.8578094 | R29: =IFERROR(_xlfn.XLOOKUP($K29,Multiples!$B:$B,Multiples!R:R),"") -> -4.6356267
D30: =+D29+1 -> 2026 | E30: =+DCF!I28 -> 22.59712 | F30: =+DCF!I58 -> -4.6356267 | G30: =+INDEX(DCF!X11:AA11,MATCH(Summary!$G$25,{"FCFF","FCFE","Tax Shield","Total Payout"},0)) -> -83.004918 | H30: =+IF(Summary!$G$25="FCFF",DCF!AB11,IF(Summary!$G$25="FCFE",DCF!AC11,DCF!AD11)) -> -104.75181 | I30: =+DCF!I132 -> 0 | K30: EBIT Margin | N30: =IFERROR(_xlfn.XLOOKUP($K30,Multiples!$B:$B,Multiples!N:N),"") -> 1.1152935 | O30: =IFERROR(_xlfn.XLOOKUP($K30,Multiples!$B:$B,Multiples!O:O),"") -> -8.8225622 | P30: =IFERROR(_xlfn.XLOOKUP($K30,Multiples!$B:$B,Multiples!P:P),"") -> -8.2458366 | Q30: =IFERROR(_xlfn.XLOOKUP($K30,Multiples!$B:$B,Multiples!Q:Q),"") -> -5.8578094 | R30: =IFERROR(_xlfn.XLOOKUP($K30,Multiples!$B:$B,Multiples!R:R),"") -> -4.6356267 | U30: Statistics
D31: =+D30+1 -> 2027 | E31: =+DCF!J28 -> 36.155392 | F31: =+DCF!J58 -> -3.6759376 | G31: =+INDEX(DCF!X12:AA12,MATCH(Summary!$G$25,{"FCFF","FCFE","Tax Shield","Total Payout"},0)) -> -108.3403 | H31: =+IF(Summary!$G$25="FCFF",DCF!AB12,IF(Summary!$G$25="FCFE",DCF!AC12,DCF!AD12)) -> -132.90496 | I31: =+DCF!J132 -> 0 | K31: Gross Profit Margin | N31: =IFERROR(_xlfn.XLOOKUP($K31,Multiples!$B:$B,Multiples!N:N),"") -> 0.59249965 | O31: =IFERROR(_xlfn.XLOOKUP($K31,Multiples!$B:$B,Multiples!O:O),"") -> 0.52774606 | P31: =IFERROR(_xlfn.XLOOKUP($K31,Multiples!$B:$B,Multiples!P:P),"") -> 0.63022544 | Q31: =IFERROR(_xlfn.XLOOKUP($K31,Multiples!$B:$B,Multiples!Q:Q),"") -> 0.6 | R31: =IFERROR(_xlfn.XLOOKUP($K31,Multiples!$B:$B,Multiples!R:R),"") -> 0.6 | U31: Beta | V31: =Peers!D74 -> 1.4737
D32: =+D31+1 -> 2028 | E32: =+DCF!K28 -> 57.848627 | F32: =+DCF!K58 -> -2.9140843 | G32: =+INDEX(DCF!X14:AA14,MATCH(Summary!$G$25,{"FCFF","FCFE","Tax Shield","Total Payout"},0)) -> -146.4819 | H32: =+IF(Summary!$G$25="FCFF",DCF!AB14,IF(Summary!$G$25="FCFE",DCF!AC14,DCF!AD14)) -> -168.57578 | I32: =+DCF!K132 -> 0 | K32: SG&A Margin | N32: =IFERROR(_xlfn.XLOOKUP($K32,Multiples!$B:$B,Multiples!N:N),"") -> 4.4063851 | O32: =IFERROR(_xlfn.XLOOKUP($K32,Multiples!$B:$B,Multiples!O:O),"") -> 5.3996346 | P32: =IFERROR(_xlfn.XLOOKUP($K32,Multiples!$B:$B,Multiples!P:P),"") -> 5.3796307 | Q32: =IFERROR(_xlfn.XLOOKUP($K32,Multiples!$B:$B,Multiples!Q:Q),"") -> 3 | R32: =IFERROR(_xlfn.XLOOKUP($K32,Multiples!$B:$B,Multiples!R:R),"") -> 2 | U32: % Float | V32: =+Peers!D73 -> 0.959
D33: =+D32+1 -> 2029 | E33: =+DCF!L28 -> 92.557804 | F33: =+DCF!L58 -> -2.1042317 | G33: =+INDEX(DCF!X15:AA15,MATCH(Summary!$G$25,{"FCFF","FCFE","Tax Shield","Total Payout"},0)) -> -171.10265 | H33: =+IF(Summary!$G$25="FCFF",DCF!AB15,IF(Summary!$G$25="FCFE",DCF!AC15,DCF!AD15)) -> -194.76307 | I33: =+DCF!L132 -> 0 | K33: Net Income Margin | N33: =IFERROR(_xlfn.XLOOKUP($K33,Multiples!$B:$B,Multiples!N:N),"") -> -7.4866862 | O33: =IFERROR(_xlfn.XLOOKUP($K33,Multiples!$B:$B,Multiples!O:O),"") -> -9.4445079 | P33: =IFERROR(_xlfn.XLOOKUP($K33,Multiples!$B:$B,Multiples!P:P),"") -> -16.299875 | Q33: =IFERROR(_xlfn.XLOOKUP($K33,Multiples!$B:$B,Multiples!Q:Q),"") -> -7.7556772 | R33: =IFERROR(_xlfn.XLOOKUP($K33,Multiples!$B:$B,Multiples!R:R),"") -> -6.7275829 | U33: % Held by Insiders | V33: =+Peers!D76 -> 0.0176
U34: % Held by Institutions | V34: =+Peers!D77 -> 0.1936
D35: SWOT Analysis | K35: Liquidity Ratios | N35: 2022 | O35: =+N35+1 -> 2023 | P35: =+O35+1 -> 2024 | Q35: =+P35+1 -> 2025 | R35: =+Q35+1 -> 2026 | U35: Short % of Float | V35: =+Peers!D78 -> 0.231
D36: Strengths | G36: Weaknesses | K36: Cash Ratio | N36: =IFERROR(_xlfn.XLOOKUP($K36,Multiples!$B:$B,Multiples!N:N),"") -> 0.44046135 | O36: =IFERROR(_xlfn.XLOOKUP($K36,Multiples!$B:$B,Multiples!O:O),"") -> 3.6717333 | P36: =IFERROR(_xlfn.XLOOKUP($K36,Multiples!$B:$B,Multiples!P:P),"") -> 5.90413 | Q36: =IFERROR(_xlfn.XLOOKUP($K36,Multiples!$B:$B,Multiples!Q:Q),"") -> 6.1449261 | R36: =IFERROR(_xlfn.XLOOKUP($K36,Multiples!$B:$B,Multiples!R:R),"") -> 4.2334192 | W36: 120.87
D37: Strong partnerships; Strategic facilities in North America; Business model transformation; Innovative partnerships; Intellectual property access; Improved financial position. | G37: History of net losses and expectation of continued financial losses; Dependence on securing additional financing to continue operations; Identified material weakness in internal control over financial reporting, leading to restatements; Risk of failure to secure or protect intellectual property, affecting competitive position; Obligations under government-funded IP development may limit asset flexibility; Anti-takeover provisions may limit shareholder influence and takeover opportunitie; Challenges in scaling supply chain, retaining talent, and maintaining equipment | K37: Quick Ratio | N37: =IFERROR(_xlfn.XLOOKUP($K37,Multiples!$B:$B,Multiples!N:N),"") -> 0.48765586 | O37: =IFERROR(_xlfn.XLOOKUP($K37,Multiples!$B:$B,Multiples!O:O),"") -> 3.8185778 | P37: =IFERROR(_xlfn.XLOOKUP($K37,Multiples!$B:$B,Multiples!P:P),"") -> 5.9512357 | Q37: =IFERROR(_xlfn.XLOOKUP($K37,Multiples!$B:$B,Multiples!Q:Q),"") -> 6.21416 | R37: =IFERROR(_xlfn.XLOOKUP($K37,Multiples!$B:$B,Multiples!R:R),"") -> 4.3554515 | U37: Major Holders | W37: 113.63
K38: Current Ratio | N38: =IFERROR(_xlfn.XLOOKUP($K38,Multiples!$B:$B,Multiples!N:N),"") -> 0.86814214 | O38: =IFERROR(_xlfn.XLOOKUP($K38,Multiples!$B:$B,Multiples!O:O),"") -> 4.1818667 | P38: =IFERROR(_xlfn.XLOOKUP($K38,Multiples!$B:$B,Multiples!P:P),"") -> 6.1383314 | Q38: =IFERROR(_xlfn.XLOOKUP($K38,Multiples!$B:$B,Multiples!Q:Q),"") -> 6.4917593 | R38: =IFERROR(_xlfn.XLOOKUP($K38,Multiples!$B:$B,Multiples!R:R),"") -> 6.4917593 | U38: Public Sector Pension Investment Board | V38: 0.1375
U39: Blackrock Inc. | V39: 0.0296
D40: Opportunities | G40: Threats | K40: Cash Flow Ratios | N40: 2022 | O40: =+N40+1 -> 2023 | P40: =+O40+1 -> 2024 | Q40: =+P40+1 -> 2025 | R40: =+Q40+1 -> 2026 | U40: Vanguard Group Inc | V40: 0.0244
D41: Growing global demand for quantum computing solutions across both private and public sectors; Unique positioning to deliver real-world applications with measurable value through annealing-based optimization; Future expansion into high-impact fields like generative AI, machine learning; increasing adoption of QCaaS (Quantum Computing as a Service) via the Leap™ platform, offering scalability and real-time access; Growing industry acknowledgment of quantum computing’s commercial viability in the near term (12–18 months) | G41: Uncertainty around meeting Term Loan conditions and covenants, despite current compliance; Material weakness in internal controls over financial reporting due to insufficient accounting expertise; Exposure to stock market volatility as a NYSE-listed company, including fluctuations in price and trading volume; Risks linked to government contracts, including audits, sanctions, early termination, and strict compliance requirements; Ongoing cybersecurity threats, including potential data breaches and system disruptions; Possibility of becoming a "controlled company" under NYSE rules, which could reduce transparency and weaken corporate governance standards | K41: Cash Conversion Cycle | N41: =IFERROR(_xlfn.XLOOKUP($K41,Multiples!$B:$B,Multiples!N:N),"") -> 121.61336 | O41: =IFERROR(_xlfn.XLOOKUP($K41,Multiples!$B:$B,Multiples!O:O),"") -> 191.17594 | P41: =IFERROR(_xlfn.XLOOKUP($K41,Multiples!$B:$B,Multiples!P:P),"") -> 213.5556 | Q41: =IFERROR(_xlfn.XLOOKUP($K41,Multiples!$B:$B,Multiples!Q:Q),"") -> 40.898488 | R41: =IFERROR(_xlfn.XLOOKUP($K41,Multiples!$B:$B,Multiples!R:R),"") -> 106.62456 | U41: UBS Group AG | V41: 0.0149
K42: Net Income / Op Cash Flow | N42: =IFERROR(_xlfn.XLOOKUP($K42,Multiples!$B:$B,Multiples!N:N),"") -> 1.1874143 | O42: =IFERROR(_xlfn.XLOOKUP($K42,Multiples!$B:$B,Multiples!O:O),"") -> 1.3638312 | P42: =IFERROR(_xlfn.XLOOKUP($K42,Multiples!$B:$B,Multiples!P:P),"") -> 3.3740356 | Q42: =IFERROR(_xlfn.XLOOKUP($K42,Multiples!$B:$B,Multiples!Q:Q),"") -> 1.6521533 | R42: =IFERROR(_xlfn.XLOOKUP($K42,Multiples!$B:$B,Multiples!R:R),"") -> 1.9041722 | U42: State Street Corporation | V42: 0.0106
K43: Chg in Cash / Op Cash Flow | N43: =IFERROR(_xlfn.XLOOKUP($K43,Multiples!$B:$B,Multiples!N:N),"") -> 0.053464821 | O43: =IFERROR(_xlfn.XLOOKUP($K43,Multiples!$B:$B,Multiples!O:O),"") -> -0.56459299 | P43: =IFERROR(_xlfn.XLOOKUP($K43,Multiples!$B:$B,Multiples!P:P),"") -> -3.2050512 | Q43: =IFERROR(_xlfn.XLOOKUP($K43,Multiples!$B:$B,Multiples!Q:Q),"") -> -0.18604821 | R43: =IFERROR(_xlfn.XLOOKUP($K43,Multiples!$B:$B,Multiples!R:R),"") -> 0.74152459 | U43: Geode Capital Management, LLC | V43: 0.0102
U44: Penserra Capital Management LLC | V44: 0.0097
D45: Revenue by Region | G45: Revenue by Segment | K45: Leverage Ratios | N45: 2022 | O45: =+N45+1 -> 2023 | P45: =+O45+1 -> 2024 | Q45: =+P45+1 -> 2025 | R45: =+Q45+1 -> 2026 | U45: Millennium Management Llc | V45: 0.0095
K46: Total Debt / Equity | N46: =IFERROR(_xlfn.XLOOKUP($K46,Multiples!$B:$B,Multiples!N:N),"") -> -378.30499 | O46: =IFERROR(_xlfn.XLOOKUP($K46,Multiples!$B:$B,Multiples!O:O),"") -> -409.78718 | P46: =IFERROR(_xlfn.XLOOKUP($K46,Multiples!$B:$B,Multiples!P:P),"") -> 612.60096 | Q46: =IFERROR(_xlfn.XLOOKUP($K46,Multiples!$B:$B,Multiples!Q:Q),"") -> -0.0073442844 | R46: =IFERROR(_xlfn.XLOOKUP($K46,Multiples!$B:$B,Multiples!R:R),"") -> -0.016272381 | U46: Bank of America Corporation | V46: 0.0087
K47: Total Debt / Capital | N47: =IFERROR(_xlfn.XLOOKUP($K47,Multiples!$B:$B,Multiples!N:N),"") -> 1.0026504 | O47: =IFERROR(_xlfn.XLOOKUP($K47,Multiples!$B:$B,Multiples!O:O),"") -> 1.0024463 | P47: =IFERROR(_xlfn.XLOOKUP($K47,Multiples!$B:$B,Multiples!P:P),"") -> 0.99837028 | Q47: =IFERROR(_xlfn.XLOOKUP($K47,Multiples!$B:$B,Multiples!Q:Q),"") -> -0.007398622 | R47: =IFERROR(_xlfn.XLOOKUP($K47,Multiples!$B:$B,Multiples!R:R),"") -> -0.016541551 | U47: Unicom Systems, Inc. | V47: 0.0083
K48: Total Liabilities / Total Assets | N48: =IFERROR(_xlfn.XLOOKUP($K48,Multiples!$B:$B,Multiples!N:N),"") -> 2.0933685 | O48: =IFERROR(_xlfn.XLOOKUP($K48,Multiples!$B:$B,Multiples!O:O),"") -> 1.4124436 | P48: =IFERROR(_xlfn.XLOOKUP($K48,Multiples!$B:$B,Multiples!P:P),"") -> 0.68653961 | Q48: =IFERROR(_xlfn.XLOOKUP($K48,Multiples!$B:$B,Multiples!Q:Q),"") -> 44.074914 | R48: =IFERROR(_xlfn.XLOOKUP($K48,Multiples!$B:$B,Multiples!R:R),"") -> 44.074914
K49: Total Debt / EBITDA | N49: =IFERROR(_xlfn.XLOOKUP($K49,Multiples!$B:$B,Multiples!N:N),"") -> -0.19511597 | O49: =IFERROR(_xlfn.XLOOKUP($K49,Multiples!$B:$B,Multiples!O:O),"") -> -0.13300982 | P49: =IFERROR(_xlfn.XLOOKUP($K49,Multiples!$B:$B,Multiples!P:P),"") -> -0.55382861 | Q49: =IFERROR(_xlfn.XLOOKUP($K49,Multiples!$B:$B,Multiples!Q:Q),"") -> -0.85232729 | R49: =IFERROR(_xlfn.XLOOKUP($K49,Multiples!$B:$B,Multiples!R:R),"") -> -1.491471 | U49: Board of Directors
K50: Total Debt / (EBITDA - Capex) | N50: =IFERROR(_xlfn.XLOOKUP($K50,Multiples!$B:$B,Multiples!N:N),"") -> -0.1936818 | O50: =IFERROR(_xlfn.XLOOKUP($K50,Multiples!$B:$B,Multiples!O:O),"") -> -0.13198958 | P50: =IFERROR(_xlfn.XLOOKUP($K50,Multiples!$B:$B,Multiples!P:P),"") -> -0.5353262 | Q50: =IFERROR(_xlfn.XLOOKUP($K50,Multiples!$B:$B,Multiples!Q:Q),"") -> -0.85232729 | R50: =IFERROR(_xlfn.XLOOKUP($K50,Multiples!$B:$B,Multiples!R:R),"") -> -1.491471 | U50: Alan Baratz (President, Chief Executive Officer and Director); Sharon Holt (Director) (Member of the Audit Committee) (Member of the Cybersecurity Committee); John DiLullo (Director) (Member of the Compensation Committee); Rohit Ghai (Director) (Member of the Nominating and Governance Committee) (Member of the Cybersecurity Committee); Steven M. West (Chair) (Member of the Audit Committee) (Member of the Nominating and Governance Committee); Kirstjen Nielsen (independent director) (Member of the Compensation Committee) (Member of the Cybersecurity Committee); Roger Biscay (independent director) (Member of the Audit Committee)
K51: Net Debt / EBITDA | N51: =IFERROR(_xlfn.XLOOKUP($K50,Multiples!$B:$B,Multiples!N:N),"") -> -0.1936818 | O51: =IFERROR(_xlfn.XLOOKUP($K50,Multiples!$B:$B,Multiples!O:O),"") -> -0.13198958 | P51: =IFERROR(_xlfn.XLOOKUP($K50,Multiples!$B:$B,Multiples!P:P),"") -> -0.5353262 | Q51: =IFERROR(_xlfn.XLOOKUP($K50,Multiples!$B:$B,Multiples!Q:Q),"") -> -0.85232729 | R51: =IFERROR(_xlfn.XLOOKUP($K50,Multiples!$B:$B,Multiples!R:R),"") -> -1.491471
K53: Solvency Ratios | N53: 2022 | O53: =+N53+1 -> 2023 | P53: =+O53+1 -> 2024 | Q53: =+P53+1 -> 2025 | R53: =+Q53+1 -> 2026
K54: EBIT / Interest Expense | N54: =IFERROR(_xlfn.XLOOKUP($K54,Multiples!$B:$B,Multiples!N:N),"") -> 3.4261242 | O54: =IFERROR(_xlfn.XLOOKUP($K54,Multiples!$B:$B,Multiples!O:O),"") -> -2088.3243 | P54: =IFERROR(_xlfn.XLOOKUP($K54,Multiples!$B:$B,Multiples!P:P),"") -> -18.677444 | Q54: =IFERROR(_xlfn.XLOOKUP($K54,Multiples!$B:$B,Multiples!Q:Q),"") -> N/A | R54: =IFERROR(_xlfn.XLOOKUP($K54,Multiples!$B:$B,Multiples!R:R),"") -> 0
K55: EBITDA / Interest Expense | N55: =IFERROR(_xlfn.XLOOKUP($K55,Multiples!$B:$B,Multiples!N:N),"") -> -24.464668 | O55: =IFERROR(_xlfn.XLOOKUP($K55,Multiples!$B:$B,Multiples!O:O),"") -> -2038.4595 | P55: =IFERROR(_xlfn.XLOOKUP($K55,Multiples!$B:$B,Multiples!P:P),"") -> -17.78137 | Q55: =IFERROR(_xlfn.XLOOKUP($K55,Multiples!$B:$B,Multiples!Q:Q),"") -> -19.299464 | R55: =IFERROR(_xlfn.XLOOKUP($K55,Multiples!$B:$B,Multiples!R:R),"") -> -22.214972
K56: (EBITDA - Capex) / Interest Expense | N56: =IFERROR(_xlfn.XLOOKUP($K56,Multiples!$B:$B,Multiples!N:N),"") -> -24.283512 | O56: =IFERROR(_xlfn.XLOOKUP($K56,Multiples!$B:$B,Multiples!O:O),"") -> -2022.7027 | P56: =IFERROR(_xlfn.XLOOKUP($K56,Multiples!$B:$B,Multiples!P:P),"") -> -17.166795 | Q56: =IFERROR(_xlfn.XLOOKUP($K56,Multiples!$B:$B,Multiples!Q:Q),"") -> -19.299464 | R56: =IFERROR(_xlfn.XLOOKUP($K56,Multiples!$B:$B,Multiples!R:R),"") -> -22.214972
D58: Debt Schedule | K58: Stock Performance
U60: ESG Traffic Light
U61: LSEG ESG Score | V61: =ESG!C14 -> 0
U62: E-Score | V62: =ESG!C15 -> 0
U63: S-Score | V63: =ESG!C16 -> 0
U64: G-Score | V64: =ESG!C17 -> 0
U65: S&P Global ESG Score | V65: =ESG!C18 -> 0
U66: Environmental | V66: =ESG!C19 -> 0
U67: Social | V67: =ESG!C20 -> 0
U68: Governance & Economic | V68: =ESG!C21 -> 0
U69: Sustainalytics | V69: =ESG!C22 -> 0
U70: ISS ESG Corporate Rating | V70: =ESG!C23 -> 0
U71: SDG Impact Rating | V71: =ESG!C24 -> 0
U72: Governance Quality Score | V72: =ESG!C25 -> 0
U73: MSCI ESG Ratings | V73: =ESG!C26 -> 0
U75: Disclaimer: This material has been prepared solely for educational and informational purposes, based on information available to the general public and from sources considered reliable. This research is part of the activities of the Lisbon Investment Society (LIS). It does not constitute, and should not be interpreted as, investment advice, financial advice, or a recommendation to buy or sell any financial instruments. The views expressed are those of the authors and do not necessarily reflect the official position of LIS. The authors assume no responsibility for the accuracy of the information provided, neither should anything contained herein be taken as an indication that any result will be achieved. Investors should conduct their own research and consult with qualified financial advisors before making any investment decisions.
D80: Extra Notes

Sheet Segments
B2: Segments | C2: (in thousands)
B4: Regions | D4: Weight | E4: 2020 | F4: =+E4+1 -> 2021 | G4: =+F4+1 -> 2022 | H4: =+G4+1 -> 2023 | I4: =+H4+1 -> 2024 | J4: ="CAGR "&$E$4&" - "&$I$4 -> CAGR 2020 - 2024 | K4: 2021 | L4: =+K4+1 -> 2022 | M4: =+L4+1 -> 2023 | N4: =+M4+1 -> 2024
B6: United States | D6: =IFERROR(I6/SUM($I$6:$I$12),"") -> 0.24368415 | E6: 3119 | F6: 3425 | G6: 3342 | H6: 3325 | I6: 2151 | J6: =IFERROR((I6/E6)^(1/COUNT($E$4:$I$4))-1,"") -> -0.071621643 | K6: =IFERROR((F6-E6)/E6,"") -> 0.098108368 | L6: =IFERROR((G6-F6)/F6,"") -> -0.024233577 | M6: =IFERROR((H6-G6)/G6,"") -> -0.0050867744 | N6: =IFERROR((I6-H6)/H6,"") -> -0.35308271
B7: Germany | D7: =IFERROR(I7/SUM($I$6:$I$12),"") -> 0.21456894 | E7: 155 | F7: 741 | G7: 1150 | H7: 1268 | I7: 1894 | J7: =IFERROR((I7/E7)^(1/COUNT($E$4:$I$4))-1,"") -> 0.64971778 | K7: =IFERROR((F7-E7)/E7,"") -> 3.7806452 | L7: =IFERROR((G7-F7)/F7,"") -> 0.55195682 | M7: =IFERROR((H7-G7)/G7,"") -> 0.1026087 | N7: =IFERROR((I7-H7)/H7,"") -> 0.49369085
B8: Japan | D8: =IFERROR(I8/SUM($I$6:$I$12),"") -> 0.12835618 | E8: 1630 | F8: 1614 | G8: 1241 | H8: 909 | I8: 1133 | J8: =IFERROR((I8/E8)^(1/COUNT($E$4:$I$4))-1,"") -> -0.070159494 | K8: =IFERROR((F8-E8)/E8,"") -> -0.0098159509 | L8: =IFERROR((G8-F8)/F8,"") -> -0.23110285 | M8: =IFERROR((H8-G8)/G8,"") -> -0.26752619 | N8: =IFERROR((I8-H8)/H8,"") -> 0.24642464
B9: Canada | D9: =IFERROR(I9/SUM($I$6:$I$12),"") -> 0.12473094 | E9: N/A | F9: N/A | G9: N/A | H9: N/A | I9: 1101 | J9: =IFERROR((I9/E9)^(1/COUNT($E$4:$I$4))-1,"") | K9: =IFERROR(F9-E9/E9,"") | L9: =IFERROR(G9-F9/F9,"") | M9: =IFERROR(H9-G9/G9,"") | N9: =IFERROR((I9-H9)/H9,"")
B10: Other | D10: =IFERROR(I10/SUM($I$6:$I$12),"") -> 0.28865979 | E10: 256 | F10: 499 | G10: 1440 | H10: 3256 | I10: 2548 | J10: =IFERROR((I10/E10)^(1/COUNT($E$4:$I$4))-1,"") -> 0.58340456 | K10: =IFERROR((F10-E10)/E10,"") -> 0.94921875 | L10: =IFERROR((G10-F10)/F10,"") -> 1.8857715 | M10: =IFERROR((H10-G10)/G10,"") -> 1.2611111 | N10: =IFERROR((I10-H10)/H10,"") -> -0.21744472
B11: - | D11: =IFERROR(I11/SUM($I$6:$I$12),"") -> 0
B12: - | D12: =IFERROR(I12/SUM($I$6:$I$12),"") -> 0
B13: Total | D13: =SUM(D6:D12) -> 1 | E13: =SUM(E6:E10) -> 5160 | F13: =SUM(F6:F10) -> 6279 | G13: =SUM(G6:G10) -> 7173 | H13: =SUM(H6:H10) -> 8758 | I13: =SUM(I6:I10) -> 8827 | J13: =IFERROR((I13/G13)^(1/COUNT($G$4:$I$4))-1,"") -> 0.071611664 | K13: =IFERROR(F13-E13/E13,"") -> 6278 | L13: =IFERROR(G13-F13/F13,"") -> 7172 | M13: =IFERROR((H13-G13)/G13,"") -> 0.22096752 | N13: =IFERROR((I13-H13)/H13,"") -> 0.0078785111
B15: Segments | D15: Weight | E15: 2020 | F15: =+E15+1 -> 2021 | G15: =+F15+1 -> 2022 | H15: =+G15+1 -> 2023 | I15: =+H15+1 -> 2024 | J15: ="CAGR "&$E$4&" - "&$I$4 -> CAGR 2020 - 2024 | K15: 2021 | L15: =+K15+1 -> 2022 | M15: =+L15+1 -> 2023 | N15: =+M15+1 -> 2024
B17: QCaaS | D17: =IFERROR(I17/SUM($I$17:$I$21),"") -> 0.76413277 | E17: 4313 | F17: 4424 | G17: 5616 | H17: 4895 | I17: 6745 | J17: =IFERROR((I17/E17)^(1/COUNT($E$4:$I$4))-1,"") -> 0.093554669 | K17: =IFERROR((F17-E17)/E17,"") -> 0.025736147 | L17: =IFERROR((G17-F17)/F17,"") -> 0.26943942 | M17: =IFERROR((H17-G17)/G17,"") -> -0.12838319 | N17: =IFERROR((I17-H17)/H17,"") -> 0.37793667
B18: Professional services | D18: =IFERROR(I18/SUM($I$17:$I$21),"") -> 0.21955364 | E18: 426 | F18: 1786 | G18: 1478 | H18: 3816 | I18: 1938 | J18: =IFERROR((I18/E18)^(1/COUNT($E$4:$I$4))-1,"") -> 0.353907 | K18: =IFERROR((F18-E18)/E18,"") -> 3.1924883 | L18: =IFERROR((G18-F18)/F18,"") -> -0.17245241 | M18: =IFERROR((H18-G18)/G18,"") -> 1.5818674 | N18: =IFERROR((I18-H18)/H18,"") -> -0.49213836
B19: Other | D19: =IFERROR(I19/SUM($I$17:$I$21),"") -> 0.016313583 | E19: 421 | F19: 69 | G19: 79 | H19: 47 | I19: 144 | J19: =IFERROR((I19/E19)^(1/COUNT($E$4:$I$4))-1,"") -> -0.19310676 | K19: =IFERROR((F19-E19)/E19,"") -> -0.83610451 | L19: =IFERROR((G19-F19)/F19,"") -> 0.14492754 | M19: =IFERROR((H19-G19)/G19,"") -> -0.40506329 | N19: =IFERROR((I19-H19)/H19,"") -> 2.0638298
D20: =IFERROR(I20/SUM($I$17:$I$21),"") -> 0 | J20: =IFERROR((I20/E20)^(1/COUNT($E$4:$I$4))-1,"") | K20: =IFERROR((F20-E20)/E20,"") | L20: =IFERROR((G20-F20)/F20,"") | M20: =IFERROR((H20-G20)/G20,"") | N20: =IFERROR((I20-H20)/H20,"")
D21: =IFERROR(I21/SUM($I$17:$I$21),"") -> 0 | J21: =IFERROR((I21/E21)^(1/COUNT($E$4:$I$4))-1,"") | K21: =IFERROR((F21-E21)/E21,"") | L21: =IFERROR((G21-F21)/F21,"") | M21: =IFERROR((H21-G21)/G21,"") | N21: =IFERROR((I21-H21)/H21,"")
B22: Total | D22: =SUM(D17:D21) -> 1 | E22: =SUM(E17:E21) -> 5160 | F22: =SUM(F17:F21) -> 6279 | G22: =SUM(G17:G21) -> 7173 | H22: =SUM(H17:H21) -> 8758 | I22: =SUM(I17:I21) -> 8827 | J22: =IFERROR((I22/E22)^(1/COUNT($E$4:$I$4))-1,"") -> 0.11335249 | K22: =IFERROR((F22-E22)/E22,"") -> 0.21686047 | L22: =IFERROR((G22-F22)/F22,"") -> 0.14237936 | M22: =IFERROR((H22-G22)/G22,"") -> 0.22096752 | N22: =IFERROR((I22-H22)/H22,"") -> 0.0078785111
B24: Categories | D24: Description | J24: Graphs
B26: QCaaS | D26: QCaaS stands for Quantum Computing as a Service and it provides cloud-based access to quantum computing resources, enabling users to run quantum algorithms without owning quantum hardware.
B27: Professional services | D27: This segment includes quantum consulting, custom algorithm development, and application integration. They also provide training, workshops, and technical support for leveraging quantum computing.
B28: Other | D28: This section often includes strategic partnerships, educational initiatives, and miscellaneous revenue streams. This covers collaborations, training programs, and experimental projects beyond core quantum products and services.
B29: =IF(B20=0,"",B20)
B30: =IF(B21=0,"",B21)
B32: Products | D32: Weight | E32: 2020 | F32: =+E32+1 -> 2021 | G32: =+F32+1 -> 2022 | H32: =+G32+1 -> 2023 | I32: =+H32+1 -> 2024 | J32: =I32+1 -> 2025 | K32: =+J32+1 -> 2026 | L32: =+K32+1 -> 2027 | M32: =+L32+1 -> 2028 | N32: =+M32+1 -> 2029 | O32: =+N32+1 -> 2030 | P32: =+O32+1 -> 2031 | Q32: =+P32+1 -> 2032 | R32: =+Q32+1 -> 2033 | ... T32: =+S32+1 -> 2035
B34: QCaaS | D34: =IFERROR(I34/$I$13,"") -> 0.76413277 | E34: =E17 -> 4313 | F34: =F17 -> 4424 | G34: =G17 -> 5616 | H34: =H17 -> 4895 | I34: =I17 -> 6745
B36: Professional services | D36: =IFERROR(I36/$I$13,"") -> 0.21955364 | E36: =E18 -> 426 | F36: =F18 -> 1786 | G36: =G18 -> 1478 | H36: =H18 -> 3816 | I36: =I18 -> 1938
D37: =IFERROR(I37/$I$13,"") -> -5.5753752e-05 | F37: =IFERROR((F36-E36)/E36,"") -> 3.1924883 | G37: =IFERROR((G36-F36)/F36,"") -> -0.17245241 | H37: =IFERROR((H36-G36)/G36,"") -> 1.5818674 | I37: =IFERROR((I36-H36)/H36,"") -> -0.49213836
B38: Product 3 | D38: =IFERROR(I38/$I$13,"") -> 0 | J38: =I38*(1+J39) -> 0 | K38: =J38*(1+K39) -> 0 | L38: =K38*(1+L39) -> 0 | M38: =L38*(1+M39) -> 0 | N38: =M38*(1+N39) -> 0 | O38: =N38*(1+O39) -> 0 | P38: =O38*(1+P39) -> 0 | Q38: =P38*(1+Q39) -> 0 | ... T38: =S38*(1+T39) -> 0
D39: =IFERROR(I39/$I$13,"") | F39: =IFERROR(F38-E38/E38,"") | G39: =IFERROR(G38-F38/F38,"") | H39: =IFERROR(H38-G38/G38,"") | I39: =IFERROR(I38-H38/H38,"")
B40: Product 4 | D40: =IFERROR(I40/$I$13,"") -> 0 | J40: =I40*(1+J41) -> 0 | K40: =J40*(1+K41) -> 0 | L40: =K40*(1+L41) -> 0 | M40: =L40*(1+M41) -> 0 | N40: =M40*(1+N41) -> 0 | O40: =N40*(1+O41) -> 0 | P40: =O40*(1+P41) -> 0 | Q40: =P40*(1+Q41) -> 0 | ... T40: =S40*(1+T41) -> 0
D41: =IFERROR(I41/$I$13,"") | F41: =IFERROR(F40-E40/E40,"") | G41: =IFERROR(G40-F40/F40,"") | H41: =IFERROR(H40-G40/G40,"") | I41: =IFERROR(I40-H40/H40,"")
B42: Product 5 | D42: =IFERROR(I42/$I$13,"") -> 0 | J42: =I42*(1+J43) -> 0 | K42: =J42*(1+K43) -> 0 | L42: =K42*(1+L43) -> 0 | M42: =L42*(1+M43) -> 0 | N42: =M42*(1+N43) -> 0 | O42: =N42*(1+O43) -> 0 | P42: =O42*(1+P43) -> 0 | Q42: =P42*(1+Q43) -> 0 | ... T42: =S42*(1+T43) -> 0
D43: =IFERROR(I43/$I$13,"") | F43: =IFERROR(F42-E42/E42,"") | G43: =IFERROR(G42-F42/F42,"") | H43: =IFERROR(H42-G42/G42,"") | I43: =IFERROR(I42-H42/H42,"")
B44: Other | D44: =IFERROR(I44/$I$13,"") -> 0.016313583 | E44: =E19 -> 421 | F44: =F19 -> 69 | G44: =G19 -> 79 | H44: =H19 -> 47 | I44: =I19 -> 144
B45: Total | D45: =SUM(D34:D44) -> 0.99994425 | E45: =SUM(E34:E42) -> 4739 | F45: =SUM(F34:F42) -> 6213.1925 | G45: =SUM(G34:G42) -> 7093.8275 | H45: =SUM(H34:H42) -> 8712.5819 | I45: =SUM(I34:I42) -> 8682.5079 | J45: =SUM(J34:J42) -> 0 | K45: =SUM(K34:K42) -> 0 | L45: =SUM(L34:L42) -> 0 | ... T45: =SUM(T34:T42) -> 0
B47: Company's Strategy / Extra Notes
B49: Expanding Quantum Computing Accessibility | D49: D-Wave provides cloud-based quantum services via their Leap™ platform, making quantum computing accessible to a broader range of users, including those without their own quantum hardware.
B50: Hybrid Quantum-Classical Solutions | D50: D-Wave has been pushing for hybrid solutions that combine quantum and classical computing to tackle complex problems that neither technology can handle alone, which is central to their business model.
B51: Partnerships and Collaborations | D51: D-Wave has formed collaborations with companies, academic institutions, and government entities to drive the adoption of quantum computing in various industries.
B52: Continuous Hardware Advancements | D52: D-Wave continues to improve their quantum annealing technology, focusing on increasing the size and capabilities of their quantum processors (like their Advantage system).

Sheet Industry
B2: Industry Overview
B4: Sales Growth Forecast | E4: Weight | F4: 2025 | G4: =+F4+1 -> 2026 | H4: =+G4+1 -> 2027 | I4: =+H4+1 -> 2028 | J4: =+I4+1 -> 2029 | K4: =+J4+1 -> 2030 | L4: =+K4+1 -> 2031 | M4: =+L4+1 -> 2032 | N4: =+M4+1 -> 2033 | ... P4: =+O4+1 -> 2035 | Q4: ="CAGR "&$F$4&" - "&$P$4 -> CAGR 2025 - 2035 | R4: Sources
B6: QCaaS | E6: 0.764 | Q6: 0.1938 | R6: Mordor Intelligence
B7: Professional Services | E7: 0.22 | Q7: 0
B11: Weighted Average | E11: =SUM(E6:E10) -> 0.984 | F11: =SUMPRODUCT(F6:F10,$E$6:$E$10) -> 0 | G11: =SUMPRODUCT(G6:G10,$E$6:$E$10) -> 0 | H11: =SUMPRODUCT(H6:H10,$E$6:$E$10) -> 0 | I11: =SUMPRODUCT(I6:I10,$E$6:$E$10) -> 0 | J11: =SUMPRODUCT(J6:J10,$E$6:$E$10) -> 0 | K11: =SUMPRODUCT(K6:K10,$E$6:$E$10) -> 0 | L11: =SUMPRODUCT(L6:L10,$E$6:$E$10) -> 0 | M11: =SUMPRODUCT(M6:M10,$E$6:$E$10) -> 0 | ... P11: =SUMPRODUCT(P6:P10,$E$6:$E$10) -> 0 | Q11: =IFERROR(((1+F11)*(1+G11)*(1+H11)*(1+I11)*(1+J11)*(1+K11)*(1+L11)*(1+M11)*(1+N11)*(1+O11)*(1+P11))^(1/COUNT($F$4:$P$4))-1,"") -> 0
B13: Key Drivers | E13: Description
B15: Advancements in Quantum Hardware | E15: Continuous improvements in qubit coherence, error correction, and scalability are driving the growth of quantum c
B16: Investment in Research and Development | E16: Both private companies (like D-Wave, IBM, Google) and governments are heavily investing in quantum computing R&D to unlock its potential for solving complex problems across industries.
B17: Hybrid Quantum-Classical Computing | E17: As pure quantum solutions are still maturing, hybrid systems that combine classical and quantum computing are becoming critical, enabling practical problem-solving with current technology.
B18: Quantum Software Development | E18: Progress in developing quantum algorithms, software tools, and quantum programming languages is vital for making quantum computing accessible and usable in various industries like cryptography, logistics, and pharmaceuticals.
B20: Industry Trends | E20: Description
B22: Increased Commercialization | E22: Companies are shifting from research-focused quantum solutions to commercial offerings, with platforms like D-Wave's Leap™ and IBM's Qiskit enabling businesses to access quantum computing as a service (QCaaS) for specific use cases.
B23: Government and Corporate Support | E23: Governments worldwide, particularly in the U.S., Europe, and China, are heavily funding quantum initiatives, recognizing the potential for quantum to revolutionize industries and national security (e.g., cryptography).
B26: Market Share | E26: Headquarters | G26: Revenues | H26: (in MM of USD) | I26: Market Share
B28: {=+_FV(DCF!R4,"Name")} -> D-WAVE QUANTUM INC. | E28: Canada | G28: 8.75 | I28: =IFERROR(G28/$G$40,"") -> 0.20325203
B29: IONQ INC. | E29: United States | G29: 22.04 | I29: =IFERROR(G29/$G$40,"") -> 0.51196283
B30: RIGETTI COMPUTING INC. | E30: United States | G30: 12 | I30: =IFERROR(G30/$G$40,"") -> 0.27874564
B31: QUANTUM COMPUTING INC. | E31: United States | G31: 0.3 | I31: =IFERROR(G31/$G$40,"") -> 0.0069686411
I32: =IFERROR(G32/$G$40,"") -> 0
I33: =IFERROR(G33/$G$40,"") -> 0
I34: =IFERROR(G34/$G$40,"") -> 0
I35: =IFERROR(G35/$G$40,"") -> 0
I36: =IFERROR(G36/$G$40,"") -> 0
I37: =IFERROR(G37/$G$40,"") -> 0
I38: =IFERROR(G38/$G$40,"") -> 0
B39: Others | E39: -- | G39: =G40-SUM(G28:G38) -> -0.04 | I39: =IFERROR(G39/$G$40,"") -> -0.00092915215
B40: Industry Size | E40: -- | G40: 43.05 | I40: 1
B42: Porter's Five Forces Analysis | E42: Rating | H42: Graph
B44: Threat of New Entrants | E44: 3.8
B45: Economies of scale | E45: 3
B46: Product differentiation | E46: 4
B47: Capital requirements | E47: 5
B48: Access to distribution channels | E48: 3
B49: Regulations | E49: 4
B50: Switching costs | E50: 3
B51: Bargaining Power of Suppliers | E51: 3.25
B52: Number of suppliers | E52: 4
B53: Uniqueness | E53: 3
B54: Switching Costs | E54: 3
B55: Forward Integration | E55: 2
... B73: Availability of close substitutes | E73: 4

Sheet Peers
D3: Revenue Growth | F3: EBITDA Margin | H3: Profit Margin | J3: EV / Revenue | L3: EV / EBITDA | N3: Price / Earnings
B4: Peers | C4: Ticker | D4: =+Inputs!O4&"-"&Inputs!P4 -> 2022-2023 | E4: =+Inputs!P4&"-"&Inputs!Q4 -> 2023-2024 | F4: 2023 | G4: 2024 | H4: =+Inputs!O4&"-"&Inputs!P4 -> 2022-2023 | I4: =+Inputs!P4&"-"&Inputs!Q4 -> 2023-2024 | J4: 2023 | K4: 2024 | L4: 2023 | M4: 2024 | N4: 2023 | O4: 2024
A6: =+D91 -> #VALUE! | B6: {=IFERROR(_FV(A6,"Name"),"")} -> D-WAVE QUANTUM INC. | C6: {=IFERROR(_FV(A6,"Ticker symbol",TRUE),"")} -> QBTS | D6: =IFERROR(D94/D93-1,"") -> 0.22096752 | E6: =IFERROR(D97/D94-1,"") -> 0.0078785111 | F6: =IFERROR(D95/D94,"") -> -8.6118977 | G6: =IFERROR(D100/D97,"") -> -7.8502322 | H6: =IFERROR(D96/D94,"") -> -9.4445079 | I6: =IFERROR(D105/D97,"") -> -16.299875 | J6: {=IFERROR((_FV(A6,"Market cap",TRUE)/1000000+D$121-D$111)/D$94,"")} -> -14.975468 | K6: {=IFERROR((_FV(A6,"Market cap",TRUE)/1000000+D$121-D$111)/D$97,"")} -> -14.858406 | L6: {=+IFERROR((_FV(A6,"Market cap",TRUE)/1000000+D$121-D$111)/D$95,"")} -> 1.7389278 | M6: {=IFERROR((_FV(A6,"Market cap",TRUE)/1000000+D$121-D$111)/D$100,"")} -> 1.8927346 | N6: {=IFERROR((_FV(A6,"Market cap",TRUE)/1000000)/D$96,"")} -> -0.10213204 | O6: {=IFERROR((_FV(A6,"Market cap",TRUE)/1000000)/D$105,"")} -> -0.058714976
A8: =+E91 -> #VALUE! | B8: IONQ INC. | C8: IONQ | D8: =+IFERROR(E94/E93-1,"") -> 0.98023538 | E8: =IFERROR(E97/E94-1,"") -> 0.95413302 | F8: =IFERROR(E95/E94,"") -> -6.6862807 | G8: =+IFERROR(E100/E97,"") -> -4.9636896 | H8: =IFERROR(E96/E94,"") -> -7.1577443 | I8: =+IFERROR(E105/E97,"") -> -7.6996494 | J8: {=IFERROR((_FV(A8,"Capitalização de mercado",TRUE)/1000000+E$121-E$111)/E$94,"")} -> -0.76277399 | K8: {=IFERROR(+(_FV(A8,"Capitalização de mercado",TRUE)/1000000+E$121-E$111)/E$97,"")} -> -0.39033883 | L8: {=IFERROR(+(_FV(A8,"Capitalização de mercado",TRUE)/1000000+E$121-E$111)/E$95,"")} -> 0.11408046 | M8: {=IFERROR(+(_FV(A8,"Capitalização de mercado",TRUE)/1000000+E$121-E$111)/E$100,"")} -> 0.078638848 | N8: {=IFERROR(+(_FV(A8,"Capitalização de mercado",TRUE)/1000000)/E$96,"")} -> -0.12584655 | O8: {=IFERROR(+(_FV(A8,"Capitalização de mercado",TRUE)/1000000)/E$105,"")} -> -0.059867678
A9: =+F91 -> #VALUE! | B9: RIGETTI COMPUTING INC. | C9: RGTI | D9: =IFERROR(F94/F93-1,"") -> -0.083498702 | E9: =IFERROR(F97/F94-1,"") -> -0.10143238 | F9: =IFERROR(F95/F94,"") -> -5.1550633 | G9: =IFERROR(F100/F97,"") -> -17.685542 | H9: =IFERROR(F96/F94,"") -> -6.2547468 | I9: =+IFERROR(F105/F97,"") -> -18.627247 | J9: {=IFERROR((_FV(A9,"Capitalização de mercado",TRUE)/1000000+E$121-E$111)/E$94,"")} -> -1.2254386 | K9: {=IFERROR(+(_FV(A9,"Capitalização de mercado",TRUE)/1000000+E$121-E$111)/E$97,"")} -> -0.62710094 | L9: {=IFERROR(+(_FV(A9,"Capitalização de mercado",TRUE)/1000000+E$121-E$111)/E$95,"")} -> 0.18327658 | M9: {=IFERROR(+(_FV(A9,"Capitalização de mercado",TRUE)/1000000+E$121-E$111)/E$100,"")} -> 0.12633766 | N9: {=IFERROR(+(_FV(A9,"Capitalização de mercado",TRUE)/1000000)/E$96,"")} -> -0.061208215 | O9: {=IFERROR(+(_FV(A9,"Capitalização de mercado",TRUE)/1000000)/E$105,"")} -> -0.029117952
A10: =+G91 -> #VALUE! | B10: QUANTUM COMPUTING INC. | C10: QUBT | D10: =+IFERROR(G94/G93-1,"") -> 1.6323529 | E10: =+IFERROR(G97/G94-1,"") -> 0.041899441 | F10: =IFERROR(G95/G94,"") -> -71.005587 | G10: =IFERROR(G100/G97,"") -> -166.88472 | H10: =IFERROR(G96/G94,"") -> -75.480447 | I10: =+IFERROR(G105/G97,"") -> -183.75871 | J10: {=IFERROR((_FV(A10,"Capitalização de mercado",TRUE)/1000000+E$121-E$111)/E$94,"")} -> -1.507573 | K10: {=IFERROR(+(_FV(A10,"Capitalização de mercado",TRUE)/1000000+E$121-E$111)/E$97,"")} -> -0.77147919 | L10: {=IFERROR(+(_FV(A10,"Capitalização de mercado",TRUE)/1000000+E$121-E$111)/E$95,"")} -> 0.22547258 | M10: {=IFERROR(+(_FV(A10,"Capitalização de mercado",TRUE)/1000000+E$121-E$111)/E$100,"")} -> 0.15542455 | N10: {=IFERROR(+(_FV(A10,"Capitalização de mercado",TRUE)/1000000)/E$96,"")} -> -0.021791563 | O10: {=IFERROR(+(_FV(A10,"Capitalização de mercado",TRUE)/1000000)/E$105,"")} -> -0.010366675
A11: =+H91 -> PEER 4 | B11: {=IFERROR(_FV(A11,"Name"),"")} | C11: {=IFERROR(_FV(A11,"Ticker symbol",TRUE),"")} | D11: =IFERROR(H94/H93-1,"") | E11: =IFERROR(H97/H94-1,"") | F11: =IFERROR(H95/H94,"") | G11: =IFERROR(H100/H97,"") | H11: =IFERROR(H96/H94,"") | I11: =+IFERROR(H105/H102,"") | J11: {=IFERROR((_FV(A11,"Market cap",TRUE)/1000000+H$121-H$111)/H$94,"")} | K11: {=IFERROR(+(_FV(A11,"Market cap",TRUE)/1000000+H$121-H$111)/H$97,"")} | L11: {=IFERROR(+(_FV(A11,"Market cap",TRUE)/1000000+H$121-H$111)/H$95,"")} | M11: {=IFERROR(+(_FV(A11,"Market cap",TRUE)/1000000+H$121-H$111)/H$100,"")} | N11: {=IFERROR(+(_FV(A11,"Market cap",TRUE)/1000000)/H$96,"")} | O11: {=IFERROR(+(_FV(A11,"Market cap",TRUE)/1000000)/H$105,"")}
A12: =+I91 -> PEER 5 | B12: {=IFERROR(_FV(A12,"Name"),"")} | C12: {=IFERROR(_FV(A12,"Ticker symbol",TRUE),"")} | D12: =+IFERROR(I94/I93-1,"") | E12: =IFERROR(I97/I94-1,"") | F12: =IFERROR(I95/I94,"") | G12: =IFERROR(I100/I97,"") | H12: =IFERROR(I96/I94,"") | I12: =+IFERROR(I105/I97,"") | J12: {=IFERROR((_FV(A12,"Market cap",TRUE)/1000000+I$121-I$111)/I$94,"")} | K12: {=IFERROR(+(_FV(A12,"Market cap",TRUE)/1000000+I$121-I$111)/I$97,"")} | L12: {=IFERROR(+(_FV(A12,"Market cap",TRUE)/1000000+I$121-I$111)/I$95,"")} | M12: {=IFERROR(+(_FV(A12,"Market cap",TRUE)/1000000+I$121-I$111)/I$100,"")} | N12: {=IFERROR(+(_FV(A12,"Market cap",TRUE)/1000000)/I$96,"")} | O12: {=IFERROR(+(_FV(A12,"Market cap",TRUE)/1000000)/I$105,"")}
A13: =+J91 -> PEER 6 | B13: {=IFERROR(_FV(A13,"Name"),"")} | C13: {=IFERROR(_FV(A13,"Ticker symbol",TRUE),"")} | D13: =IFERROR(J94/J93-1,"") | E13: =IFERROR(J97/J94-1,"") | G13: =IFERROR(J100/J97,"") | H13: =IFERROR(J96/J94,"") | I13: =+IFERROR(J105/J97,"") | J13: {=IFERROR(+(_FV(A13,"Market cap",TRUE)/1000000+J$121-J$111)/J$94,"")} | K13: {=IFERROR(+(_FV(A13,"Market cap",TRUE)/1000000+J$121-J$111)/J$97,"")} | L13: {=IFERROR(+(_FV(A13,"Market cap",TRUE)/1000000+J$121-J$111)/J$95,"")} | M13: {=IFERROR(+(_FV(A13,"Market cap",TRUE)/1000000+J$121-J$111)/J$100,"")} | N13: {=IFERROR(+(_FV(A13,"Market cap",TRUE)/1000000)/J$96,"")} | O13: {=IFERROR(+(_FV(A13,"Market cap",TRUE)/1000000)/J$105,"")}
A14: =+K91 -> PEER 7 | B14: {=IFERROR(_FV(A14,"Name"),"")} | C14: {=IFERROR(_FV(A14,"Ticker symbol",TRUE),"")} | D14: =IFERROR(K94/K93-1,"") | E14: =IFERROR(K97/K94-1,"") | F14: =+IFERROR(K95/K94,"") | G14: =IFERROR(K100/K97,"") | H14: =IFERROR(K96/K94,"") | I14: =+IFERROR(K105/K97,"") | J14: {=IFERROR((_FV(A14,"Market cap",TRUE)/1000000+D$121-K$111)/K$94,"")} | K14: {=IFERROR(+(_FV(A14,"Market cap",TRUE)/1000000+D$121-K$111)/K$97,"")} | L14: {=IFERROR(+(_FV(A14,"Market cap",TRUE)/1000000+D$121-K$111)/K$95,"")} | M14: {=IFERROR(+(_FV(A14,"Market cap",TRUE)/1000000+D$121-K$111)/K$100,"")} | N14: {=IFERROR(+(_FV(A14,"Market cap",TRUE)/1000000)/K$96,"")} | O14: {=IFERROR(+(_FV(A14,"Market cap",TRUE)/1000000)/K$105,"")}
A15: =+L91 -> PEER 8 | B15: {=IFERROR(_FV(A15,"Name"),"")} | C15: {=IFERROR(_FV(A15,"Ticker symbol",TRUE),"")} | D15: =+IFERROR(L94/L93,"") | E15: =IFERROR(L97/L94,"") | F15: =IFERROR(L95/L94,"") | G15: =IFERROR(L100/L97,"") | H15: =IFERROR(L96/L94,"") | I15: =+IFERROR(L105/L97,"") | J15: {=IFERROR(+(_FV(A15,"Market cap",TRUE)/1000000+L$121-L$111)/L$94,"")} | K15: {=IFERROR(+(_FV(A15,"Market cap",TRUE)/1000000+L$121-L$111)/L$97,"")} | L15: {=IFERROR(+(_FV(A15,"Market cap",TRUE)/1000000+L$121-L$111)/L$95,"")} | M15: {=IFERROR(+(_FV(A15,"Market cap",TRUE)/1000000+L$121-L$111)/L$100,"")} | N15: {=IFERROR(+(_FV(A15,"Market cap",TRUE)/1000000)/L$96,"")} | O15: {=IFERROR(+(_FV(A15,"Market cap",TRUE)/1000000)/L$105,"")}
A16: =+M91 -> PEER 9 | B16: {=IFERROR(_FV(A16,"Name"),"")} | C16: {=IFERROR(_FV(A16,"Ticker symbol",TRUE),"")} | D16: =IFERROR(M94/M93-1,"") | E16: =IFERROR(M97/M94-1,"") | F16: =IFERROR(M95/M94,"") | G16: =IFERROR(M100/M97,"") | H16: =IFERROR(M96/M94,"") | I16: =+IFERROR(M105/M97,"") | J16: {=IFERROR(+(_FV(A16,"Market cap",TRUE)/1000000+M$121-M$111)/M$94,"")} | K16: {=IFERROR(+(_FV(A16,"Market cap",TRUE)/1000000+M$121-M$111)/M$97,"")} | L16: {=IFERROR(+(_FV(A16,"Market cap",TRUE)/1000000+M$121-M$111)/M$95,"")} | M16: {=IFERROR(+(_FV(A16,"Market cap",TRUE)/1000000+M$121-M$111)/M$100,"")} | N16: {=IFERROR(+(_FV(A16,"Market cap",TRUE)/1000000)/M$96,"")} | O16: {=IFERROR(+(_FV(A16,"Market cap",TRUE)/1000000)/M$105,"")}
A17: =+N91 -> PEER 10 | B17: {=IFERROR(_FV(A17,"Name"),"")} | C17: {=+IFERROR(_FV(A17,"Ticker symbol",TRUE),"")} | D17: =IFERROR(N94/N93-1,"") | E17: =IFERROR(N97/N94-1,"") | F17: =IFERROR(N95/N94,"") | G17: =IFERROR(N100/N97,"") | H17: =IFERROR(N96/N94,"") | I17: =+IFERROR(N105/N97,"") | J17: {=IFERROR(+(_FV(A17,"Market cap",TRUE)/1000000+N$121-N$111)/N$94,"")} | K17: {=IFERROR(+(_FV(A17,"Market cap",TRUE)/1000000+N$121-N$111)/N$97,"")} | L17: {=IFERROR(+(_FV(A17,"Market cap",TRUE)/1000000+N$121-N$111)/N$95,"")} | M17: {=IFERROR(+(_FV(A17,"Market cap",TRUE)/1000000+N$121-N$111)/N$100,"")} | N17: {=IFERROR(+(_FV(A17,"Market cap",TRUE)/1000000)/N$96,"")} | O17: {=IFERROR(+(_FV(A17,"Market cap",TRUE)/1000000)/N$105,"")}
B18: Average | D18: =IFERROR(AVERAGE(D6:D17),"") -> 0.68751428 | E18: =IFERROR(AVERAGE(E6:E17),"") -> 0.22561965 | F18: =IFERROR(AVERAGE(F6:F17),"") -> -22.864707 | G18: =IFERROR(AVERAGE(G6:G17),"") -> -49.346046 | H18: =IFERROR(AVERAGE(H6:H17),"") -> -24.584361 | I18: =IFERROR(AVERAGE(I6:I17),"") -> -56.596371 | J18: =IFERROR(AVERAGE(J6:J17),"") -> -4.6178134 | K18: =IFERROR(AVERAGE(K6:K17),"") -> -4.1618312 | ... O18: =IFERROR(AVERAGE(O6:O17),"") -> -0.03951682
B19: Deviation from Average | D19: =IFERROR(+D18-D6,"") -> 0.46654677 | E19: =IFERROR(E18-E6,"") -> 0.21774114 | F19: =+IFERROR(F18-F6,"") -> -14.252809 | G19: =IFERROR(G18-G6,"") -> -41.495813 | H19: =IFERROR(+H6-H18,"") -> 15.139854 | I19: =+IFERROR(I6-I18,"") -> 40.296496 | J19: =+IFERROR(J6-J18,"") -> -10.357655 | K19: =+IFERROR(K6-K18,"") -> -10.696575 | L19: =IFERROR(+L6-L18,"") -> 1.1734884 | M19: =IFERROR(M6-M18,"") -> 1.3294506 | N19: =IFERROR(+N6-N18,"") -> -0.024387451 | O19: =IFERROR(+O6-O18,"") -> -0.019198156
D21: Trading Multiple | G21: Net | H21: Preferred | I21: Non-Controlling | J21: Equity Value | M21: Implied Upside (Downside)
B22: Implied Share Price | D22: Revenue | E22: EBITDA | F22: P/E | G22: Debt | H22: Stock | I22: Interest | J22: Revenue | K22: EBITDA | L22: P/E | M22: Revenue | N22: EBITDA | O22: P/E | P22: Current Price
B24: Second Minimum | D24: =IFERROR(SMALL(K6:K17,2),"") -> -0.77147919 | E24: =IFERROR(SMALL(M6:M17,2),"") -> 0.12633766 | F24: =IFERROR(SMALL(O6:O17,2),"") -> -0.058714976 | G24: =-Inputs!$Q$99+Inputs!$Q$100 -> -139.603 | H24: =+Inputs!$Q$101 -> 0 | I24: =+Inputs!$Q$102 -> 0 | J24: =IFERROR(+D24*$D$97+G24+H24+I24,"") -> -6949.4498 | K24: =IFERROR(E24*$D$100+G24+H24+I24,"") -> -8894.045 | L24: =IFERROR(F24*$D$105,"") -> 8447.852 | M24: {=IFERROR(+(J24/_FV($A$6,"Shares outstanding",TRUE)*1000000)/$P$24-1,"")} -> -1.8226292 | N24: {=IFERROR((+K24/_FV($A$6,"Shares outstanding",TRUE)*1000000)/$P$24-1,"")} -> -2.0528173 | O24: {=IFERROR(+(L24/_FV($A$6,"Shares outstanding",TRUE)*1000000)/$P$24-1,"")} -> 0 | P24: {=+_FV(A6,"Price")} -> 24.7
B25: Average | D25: =+IFERROR(AVERAGE(K6:K17),"") -> -4.1618312 | E25: =IFERROR(+AVERAGE(M6:M17),"") -> 0.5632839 | F25: =IFERROR(+AVERAGE(O6:O17),"") -> -0.03951682 | G25: =-Inputs!$Q$99+Inputs!$Q$100 -> -139.603 | H25: =+Inputs!$Q$101 -> 0 | I25: =+Inputs!$Q$102 -> 0 | J25: =IFERROR(+D25*$D$97+G25+H25+I25,"") -> -36876.087 | K25: =IFERROR(E25*$D$100+G25+H25+I25,"") -> -39171.798 | L25: =IFERROR(+F25*$D$105,"") -> 5685.6406 | M25: {=IFERROR(+(J25/_FV($A$6,"Shares outstanding",TRUE)*1000000)/$P$24-1,"")} -> -5.3651436 | N25: {=IFERROR((+K25/_FV($A$6,"Shares outstanding",TRUE)*1000000)/$P$24-1,"")} -> -5.6368944 | O25: {=IFERROR(+(L25/_FV($A$6,"Shares outstanding",TRUE)*1000000)/$P$24-1,"")} -> -0.32697205
B26: Median | D26: =IFERROR(MEDIAN(K6:K17),"") -> -0.69929007 | E26: =IFERROR(MEDIAN(M6:M17),"") -> 0.1408811 | F26: =IFERROR(MEDIAN(O6:O17),"") -> -0.043916464 | G26: =-Inputs!$Q$99+Inputs!$Q$100 -> -139.603 | H26: =+Inputs!$Q$101 -> 0 | I26: =+Inputs!$Q$102 -> 0 | J26: =IFERROR(D26*$D$97+G26+H26+I26,"") -> -6312.2364 | K26: =IFERROR(E26*$D$100+G26+H26+I26,"") -> -9901.8182 | L26: =IFERROR(+F26*$D$105,"") -> 6318.6569 | M26: {=IFERROR(+(J26/_FV($A$6,"Shares outstanding",TRUE)*1000000)/$P$24-1,"")} -> -1.7472002 | N26: {=IFERROR((+K26/_FV($A$6,"Shares outstanding",TRUE)*1000000)/$P$24-1,"")} -> -2.1721108 | O26: {=+IFERROR((L26/_FV($A$6,"Shares outstanding",TRUE)*1000000)/$P$24-1,"")} -> -0.25203982
B27: Second Maximum | D27: =IFERROR(LARGE(K6:K17,2),"") -> -0.62710094 | E27: =IFERROR(LARGE(M6:M17,2),"") -> 0.15542455 | F27: =IFERROR(LARGE(O6:O17,2),"") -> -0.029117952 | G27: =-Inputs!$Q$99+Inputs!$Q$100 -> -139.603 | H27: =+Inputs!$Q$101 -> 0 | I27: =+Inputs!$Q$102 -> 0 | J27: =IFERROR(+D27*$D$97+G27+H27+I27,"") -> -5675.023 | K27: =IFERROR(E27*$D$100+G27+H27+I27,"") -> -10909.591 | L27: =IFERROR(+F27*$D$105,"") -> 4189.4618 | M27: {=IFERROR(+(J27/_FV($A$6,"Shares outstanding",TRUE)*1000000)/$P$24-1,"")} -> -1.6717711 | N27: {=IFERROR((+K27/_FV($A$6,"Shares outstanding",TRUE)*1000000)/$P$24-1,"")} -> -2.2914042 | O27: {=IFERROR(+(L27/_FV($A$6,"Shares outstanding",TRUE)*1000000)/$P$24-1,"")} -> -0.50407965
B29: Profitability | D29: =+LEFT(B6, FIND(" ", B6 & " ") - 1) -> D-WAVE | E29: =+LEFT(B8, FIND(" ", B8 & " ") - 1) -> IONQ | F29: =+LEFT(B9, FIND(" ", B9 & " ") - 1) -> RIGETTI | G29: =+LEFT(B10, FIND(" ", B10 & " ") - 1) -> QUANTUM | H29: =+LEFT(B11, FIND(" ", B11 & " ") - 1) | I29: =+LEFT(B12, FIND(" ", B12 & " ") - 1) | J29: =+LEFT(C12, FIND(" ", C12 & " ") - 1) | K29: =+LEFT(B14, FIND(" ", B14 & " ") - 1) | L29: =+LEFT(B15, FIND(" ", B15 & " ") - 1) | M29: =+LEFT(B16, FIND(" ", B16 & " ") - 1) | N29: =+LEFT(B17, FIND(" ", B17 & " ") - 1) | O29: Average
B31: Operating Margin | D31: =IFERROR(D101/D97,"") -> -8.2458366 | E31: =IFERROR(E101/E97,"") -> -5.3967683 | F31: =IFERROR(F101/F97,"") -> -18.325579 | G31: =IFERROR(G101/G97,"") -> -177.06702 | H31: =IFERROR(H101/H97,"") | I31: =IFERROR(I101/I97,"") | J31: =IFERROR(J101/J97,"") | K31: =IFERROR(K101/K97,"") | ... N31: =IFERROR(N101/N97,"") | O31: =IFERROR(+AVERAGE(D31:N31),"") -> -52.258802
B32: Net Income Margin | D32: =IFERROR(D105/D97,"") -> -16.299875 | E32: =IFERROR(E105/E97,"") -> -7.6996494 | F32: =IFERROR(F105/F97,"") -> -18.627247 | G32: =IFERROR(G105/G97,"") -> -183.75871 | H32: =IFERROR(H105/H97,"") | I32: =IFERROR(I105/I97,"") | J32: =IFERROR(J105/J97,"") | K32: =IFERROR(K105/K97,"") | ... N32: =IFERROR(N105/N97,"") | O32: =IFERROR(+AVERAGE(D32:N32),"") -> -56.596371
B33: ROA (%) | D33: =IFERROR(D105/D117,"") -> -0.71992414 | E33: =IFERROR(E105/E117,"") -> -0.65235017 | F33: =IFERROR(F105/F117,"") -> -0.70574851 | G33: =IFERROR(G105/G117,"") -> -0.44635612 | H33: =IFERROR(H105/H117,"") | I33: =IFERROR(I105/I117,"") | J33: =IFERROR(J105/J117,"") | K33: =IFERROR(K105/K117,"") | ... N33: =IFERROR(N105/N117,"") | O33: =IFERROR(+AVERAGE(D33:N33),"") -> -0.63109474
B34: Financial Cost of Debt | D34: =IFERROR((D102/D121)*(1-(D104/D103)),(D102/D121)) -> 0.1015452 | E34: =IFERROR(+(E102/E121)*(1-(E104/E103)),+(E102/E121)*(1-(0.1/E103))) -> 0.0010155151 | F34: =IFERROR(+(F102/F121)*(1-(F104/F103)),+(F102/F121)) -> 0.36988636 | G34: =IFERROR(+(G102/G121)*(1-(G104/G103)),+(G102/G121)) -> -1.7552921 | H34: =IFERROR(+(H102/H121)*(1-(H104/H103)),"") | I34: =IFERROR(+(I102/I121)*(1-(I104/I103)),"") | J34: =IFERROR(+(J102/J121)*(1-(J104/J103)),"") | K34: =IFERROR(+(K102/K121)*(1-(K104/K103)),"") | L34: =IFERROR(+(L102/L121)*(1-(L104/L103)),"") | M34: =IFERROR(+(M102/M121)*(1-(M104/M103)),"") | N34: =IFERROR(+(N102/N121)*(1-(N104/N103)),"") | O34: =IFERROR(+AVERAGE(D34:N34),"") -> -0.32071126
B35: Return on Equity (RoE) | D35: =IFERROR(+D105/D122,"") -> -2.2966989 | E35: =IFERROR(+E105/E122,"") -> -0.86397455 | F35: =IFERROR(+F105/F122,"") -> -1.5877209 | G35: =IFERROR(+G105/G122,"") -> -0.63886585 | H35: =IFERROR(+H105/H122,"") | I35: =IFERROR(+I105/I122,"") | J35: =IFERROR(+J105/J122,"") | K35: =IFERROR(+K105/K122,"") | ... N35: =IFERROR(+N105/N122,"") | O35: =IFERROR(+AVERAGE(D35:N35),"") -> -1.3468151
B36: Return on Invested Capital (ROIC) | D36: =IFERROR(+D105/(D121+D122),"") -> -1.4242202 | E36: =IFERROR(+E105/(E121+E122),"") -> -0.82584098 | F36: =IFERROR(+F105/(F121+F122),"") -> -1.4845224 | G36: =IFERROR(+G105/(G121+G122),"") -> -0.63190987 | H36: =IFERROR(+H105/(H121+H122),"") | I36: =IFERROR(+I105/(I121+I122),"") | J36: =IFERROR(+J105/(J121+J122),"") | K36: =IFERROR(+K105/(K121+K122),"") | ... N36: =IFERROR(+N105/(N121+N122),"") | O36: =IFERROR(+AVERAGE(D36:N36),"") -> -1.0916234
B38: Solvency | D38: =+D29 -> D-WAVE | E38: =+E29 -> IONQ | F38: =+F29 -> RIGETTI | G38: =+G29 -> QUANTUM | H38: =+H29 | I38: =+I29 | J38: =+J29 | K38: =+K29 | ... O38: =+O29 -> Average
B40: Debt/Assets | D40: =IFERROR(D121/D117,"") -> 0.19202614 | E40: =IFERROR(E121/E117,"") -> 0.034865103 | F40: =IFERROR(F121/F117,"") -> 0.030900287 | G40: =IFERROR(G121/G117,"") -> 0.007690855 | H40: =IFERROR(H121/H117,"") | I40: =IFERROR(I121/I117,"") | J40: =IFERROR(J121/J117,"") | K40: =IFERROR(K121/K117,"") | ... N40: =IFERROR(N121/N117,"") | O40: =IFERROR(+AVERAGE(D40:N40),"") -> 0.066370596
B41: Net Debt/EBITDA | D41: =IFERROR(+(D121-D111)/D100,"") -> 2.0146477 | E41: =IFERROR(+(E121-E111)/E100,"") -> 0.17150528 | F41: =IFERROR(+(F121-F111)/F100,"") -> 0.30852028 | G41: =IFERROR(+(G121-G111)/G100,"") -> 1.249261 | H41: =IFERROR(+(H121-H111)/H100,"") | I41: =IFERROR(+(I121-I111)/I100,"") | J41: =IFERROR(+(J121-J111)/J100,"") | K41: =IFERROR(+(K121-K111)/K100,"") | ... N41: =IFERROR(+(N121-N111)/N100,"") | O41: =IFERROR(+AVERAGE(D41:N41),"") -> 0.93598358
B42: Interest Coverage Ratio | D42: =IFERROR(D101/D102,"") -> -18.677444 | E42: =IFERROR(E101/E102,"") -> -12914.167 | F42: =IFERROR(F101/F102,"") -> -60.747465 | G42: =IFERROR(G101/G102,"") -> 31.860106 | H42: =IFERROR(H101/H102,"") | I42: =IFERROR(I101/I102,"") | J42: =IFERROR(J101/J102,"") | K42: =IFERROR(K101/K102,"") | ... N42: =IFERROR(N101/N102,"") | O42: =IFERROR(+AVERAGE(D42:N42),"") -> -3240.4329
B44: Liquidity | D44: =+D29 -> D-WAVE | E44: =+E29 -> IONQ | F44: =+F29 -> RIGETTI | G44: =+G29 -> QUANTUM | H44: =+H29 | I44: =+I29 | J44: =+J29 | K44: =+K29 | ... O44: =+O29 -> Average
B46: Cash Ratio | D46: =IFERROR(D111/D119,"") -> 5.90413 | E46: =IFERROR(E111/E119,"") -> 1507.3576 | F46: =IFERROR(F111/F119,"") -> 5702.705 | G46: =IFERROR(G111/G119,"") -> 17316.297 | H46: =IFERROR(H111/H119,"") | I46: =IFERROR(I111/I119,"") | J46: =IFERROR(J111/J119,"") | K46: =IFERROR(K111/K119,"") | ... N46: =IFERROR(N111/N119,"") | O46: =IFERROR(+AVERAGE(D46:N46),"") -> 6133.066
B47: Quick Ratio | D47: =IFERROR(+(D111+D112)/D119,"") -> 5.9512357 | E47: =IFERROR(+(E111+E112)/E119,"") -> 1687.9313 | F47: =IFERROR(+(F111+F112)/F119,"") -> 5907.2217 | G47: =IFERROR(+(G111+G112)/G119,"") -> 17322.22 | H47: =IFERROR(+(H111+H112)/H119,"") | I47: =IFERROR(+(I111+I112)/I119,"") | J47: =IFERROR(+(J111+J112)/J119,"") | K47: =IFERROR(+(K111+K112)/K119,"") | ... N47: =IFERROR(+(N111+N112)/N119,"") | O47: =IFERROR(+AVERAGE(D47:N47),"") -> 6230.831
B48: Current Ratio | D48: =IFERROR(D115/D119,"") -> 6.1383314 | E48: =IFERROR(E115/E119,"") -> 10497.492 | F48: =IFERROR(F115/F119,"") -> 17422.938 | G48: =IFERROR(G115/G119,"") -> 17361.483 | H48: =IFERROR(H115/H119,"") | I48: =IFERROR(I115/I119,"") | J48: =IFERROR(J115/J119,"") | K48: =IFERROR(K115/K119,"") | ... N48: =IFERROR(N115/N119,"") | O48: =IFERROR(+AVERAGE(D48:N48),"") -> 11322.013
B50: Activity | D50: =+D29 -> D-WAVE | E50: =+E29 -> IONQ | F50: =+F29 -> RIGETTI | G50: =+G29 -> QUANTUM | H50: =+H29 | I50: =+I29 | J50: =+J29 | K50: =+K29 | ... O50: =+O29 -> Average
B52: Inventory Turnover | D52: =IFERROR(D98/(AVERAGE(D113:D114)),"") -> 1.7343252 | E52: =IFERROR(E98/(AVERAGE(E113:E114)),"") -> 1.3490075 | F52: =IFERROR(F98/(AVERAGE(F113:F114)),"") | G52: =IFERROR(G98/(AVERAGE(G113:G114)),"") -> 5.7142857 | H52: =IFERROR(H98/(AVERAGE(H113:H114)),"") | I52: =IFERROR(I98/(AVERAGE(I113:I114)),"") | J52: =IFERROR(J98/(AVERAGE(J113:J114)),"") | K52: =IFERROR(K98/(AVERAGE(K113:K114)),"") | ... N52: =IFERROR(N98/(AVERAGE(N113:N114)),"") | O52: =IFERROR(+AVERAGE(D52:N52),"") -> 2.9325395
B53: Acc. Receivable Turnover | D53: =IFERROR(D97/D112,"") -> 6.2161972 | E53: =IFERROR(E97/E112,"") -> 6.6103438 | F53: =IFERROR(F97/F112,"") -> 4.4458179 | G53: =IFERROR(G97/G112,"") -> 13.814815 | H53: =IFERROR(H97/H112,"") | I53: =IFERROR(I97/I112,"") | J53: =IFERROR(J97/J112,"") | K53: =IFERROR(K97/K112,"") | ... N53: =IFERROR(N97/N112,"") | O53: =IFERROR(+AVERAGE(D53:N53),"") -> 7.7717934
B54: Payables Turnover | D54: =IFERROR(D98/D118,"") -> 4.004908 | E54: =IFERROR(E98/E118,"") -> 4015.2964 | F54: =IFERROR(F98/F118,"") -> 2574.4573 | G54: =IFERROR(G98/G118,"") -> 189.50437 | H54: =IFERROR(H98/H118,"") | I54: =IFERROR(I98/I118,"") | J54: =IFERROR(J98/J118,"") | K54: =IFERROR(K98/K118,"") | ... N54: =IFERROR(N98/N118,"") | O54: =IFERROR(+AVERAGE(D54:N54),"") -> 1695.8157
B55: Fixed Asset Turnover | D55: =IFERROR(D97/D116,"") -> 0.77470599 | E55: =IFERROR(E97/E116,"") -> 692.147 | F55: =IFERROR(F97/F116,"") -> 204.99278 | G55: =IFERROR(G97/G116,"") -> 38.319293 | H55: =IFERROR(H97/H116,"") | I55: =IFERROR(I97/I116,"") | J55: =IFERROR(J97/J116,"") | K55: =IFERROR(K97/K116,"") | ... N55: =IFERROR(N97/N116,"") | O55: =IFERROR(+AVERAGE(D55:N55),"") -> 234.05845
B56: Total Asset Turnover | D56: =IFERROR(D97/D117,"") -> 0.044167463 | E56: =IFERROR(E97/E117,"") -> 0.084724659 | F56: =IFERROR(F97/F117,"") -> 0.037887965 | G56: =IFERROR(G97/G117,"") -> 0.0024290338 | H56: =IFERROR(H97/H117,"") | I56: =IFERROR(I97/I117,"") | J56: =IFERROR(J97/J117,"") | K56: =IFERROR(K97/K117,"") | ... N56: =IFERROR(N97/N117,"") | O56: =IFERROR(+AVERAGE(D56:N56),"") -> 0.04230228
B57: Cash Cycle (days) | D57: =IFERROR(365/D52+365/D53-365/D54,"") -> 178.03589 | E57: =IFERROR(365/E52+365/E53-365/E54,"") -> 325.69488 | F57: =IFERROR(365/F52+365/F53-365/F54,"") | G57: =IFERROR(365/G52+365/G53-365/G54,"") -> 88.369835 | H57: =IFERROR(365/H52+365/H53-365/H54,"") | I57: =IFERROR(365/I52+365/I53-365/I54,"") | J57: =IFERROR(365/J52+365/J53-365/J54,"") | K57: =IFERROR(365/K52+365/K53-365/K54,"") | ... N57: =IFERROR(365/N52+365/N53-365/N54,"") | O57: =IFERROR(+AVERAGE(D57:N57),"") -> 197.36687
B59: Cash Flow | D59: =+D38 -> D-WAVE | E59: =+E38 -> IONQ | F59: =+F38 -> RIGETTI | G59: =+G38 -> QUANTUM | H59: =+H38 | I59: =+I38 | J59: =+J38 | K59: =+K38 | ... O59: =+O38 -> Average
B61: Cash Flow Margin | D61: =IFERROR(D132/D97,"") -> 15.483516 | E61: =IFERROR(E132/E97,"") -> 0.43493604 | F61: =IFERROR(F132/F97,"") -> 4.3067655 | G61: =IFERROR(G132/G97,"") -> 206.12869 | H61: =IFERROR(H132/H97,"") | I61: =IFERROR(I132/I97,"") | J61: =IFERROR(J132/J97,"") | K61: =IFERROR(K132/K97,"") | ... N61: =IFERROR(N132/N97,"") | O61: =IFERROR(+AVERAGE(D61:N61),"") -> 56.588476
B62: Cash Flow to Net Income | D62: =IFERROR(D132/D96,"") -> -1.6523363 | E62: =IFERROR(E132/E96,"") -> -0.11874172 | F62: =IFERROR(F132/F96,"") -> -0.6187173 | G62: =IFERROR(G132/G96,"") -> -2.8453112 | H62: =IFERROR(H132/H96,"") | I62: =IFERROR(I132/I96,"") | J62: =IFERROR(J132/J96,"") | K62: =IFERROR(K132/K96,"") | ... N62: =IFERROR(N132/N96,"") | O62: =IFERROR(+AVERAGE(D62:N62),"") -> -1.3087766
B63: CFO to Net Income | D63: =+IFERROR(D126/D105,"") -> 0.29638099 | E63: =+IFERROR(E126/E105,"") -> 0.31920385 | F63: =+IFERROR(F126/F105,"") -> 0.25189066 | G63: =+IFERROR(G126/G105,"") -> 0.2365411 | H63: =+IFERROR(H126/H105,"") | I63: =+IFERROR(I126/I105,"") | J63: =+IFERROR(J126/J105,"") | K63: =+IFERROR(K126/K105,"") | ... N63: =+IFERROR(N126/N105,"") | O63: =IFERROR(+AVERAGE(D63:N63),"") -> 0.27600415
B64: Net Capex to CFO | D64: =IFERROR(-D127/D126,"") -> -0.056163966 | E64: =IFERROR(-E127/E126,"") -> -0.17003108 | F64: =IFERROR(-F127/F126,"") -> -0.2192506 | G64: =IFERROR(-G127/G126,"") -> -0.3700734 | H64: =IFERROR(-H127/H126,"") | I64: =IFERROR(-I127/I126,"") | J64: =IFERROR(-J127/J126,"") | K64: =IFERROR(-K127/K126,"") | ... N64: =IFERROR(-N127/N126,"") | O64: =IFERROR(+AVERAGE(D64:N64),"") -> -0.20387976
B65: CFI to CFO | D65: =IFERROR(-D128/D126,"") -> -0.073658045 | E65: =IFERROR(-E128/E126,"") -> 0.78148173 | F65: =IFERROR(-F128/F126,"") -> -1.5478302 | G65: =IFERROR(-G128/G126,"") -> -0.3922778 | H65: =IFERROR(-H128/H126,"") | I65: =IFERROR(-I128/I126,"") | J65: =IFERROR(-J128/J126,"") | K65: =IFERROR(-K128/K126,"") | ... N65: =IFERROR(-N128/N126,"") | O65: =IFERROR(+AVERAGE(D65:N65),"") -> -0.30807108
B66: Net Financing to CFO | D66: =IFERROR((D129+D130)/D126,"") -> 0.71219192 | E66: =IFERROR((E129+E130)/E126,"") -> 0 | F66: =IFERROR((F129+F130)/F126,"") -> 0.4607818 | G66: =IFERROR((G129+G130)/G126,"") -> 0 | H66: =IFERROR((H129+H130)/H126,"") | I66: =IFERROR((I129+I130)/I126,"") | J66: =IFERROR((J129+J130)/J126,"") | K66: =IFERROR((K129+K130)/K126,"") | ... N66: =IFERROR((N129+N130)/N126,"") | O66: =IFERROR(+AVERAGE(D66:N66),"") -> 0.29324343
B67: Debt Borrowing to Debt Repayment | D67: =+IFERROR(-D130/D129,"") | E67: =+IFERROR(-E130/E129,"") | F67: =+IFERROR(-F130/F129,"") | G67: =+IFERROR(-G130/G129,"") | H67: =+IFERROR(-H130/H129,"") | I67: =+IFERROR(-I130/I129,"") | J67: =+IFERROR(-J130/J129,"") | K67: =+IFERROR(-K130/K129,"") | ... N67: =+IFERROR(-N130/N129,"") | O67: =IFERROR(+AVERAGE(D67:N67),"")
B68: CFF to CFO | D68: =IFERROR(-D131/D126,"") -> 4.2785451 | E68: =IFERROR(-E131/E126,"") -> 0.39378253 | F68: =IFERROR(-F131/F126,"") -> 3.4657199 | G68: =IFERROR(-G131/G126,"") -> 6.1145377 | H68: =IFERROR(-H131/H126,"") | I68: =IFERROR(-I131/I126,"") | J68: =IFERROR(-J131/J126,"") | K68: =IFERROR(-K131/K126,"") | ... N68: =IFERROR(-N131/N126,"") | O68: =IFERROR(+AVERAGE(D68:N68),"") -> 3.5631463
B69: Payout Ratio | O69: =IFERROR(+AVERAGE(D69:N69),"")
B71: Stock Information | D71: =+D29 -> D-WAVE | E71: =+E29 -> IONQ | F71: =+F29 -> RIGETTI | G71: =+G29 -> QUANTUM | H71: =+H29 | I71: =+I29 | J71: =+J29 | K71: =+K29 | ... O71: =+O29 -> Average
B73: (%) Float | D73: 0.959 | E73: 0.853 | F73: 0.988 | G73: 0.825 | O73: =IFERROR(+AVERAGE(D73:N73),"") -> 0.90625
B74: β (Levered) | D74: {=IFERROR(_FV(D91,"Beta"),"")} -> 1.4737 | E74: {=IFERROR(_FV(E91,"Beta"),"")} -> 2.6035 | F74: {=IFERROR(_FV(F91,"Beta"),"")} -> 1.5813 | G74: {=IFERROR(_FV(G91,"Beta"),"")} -> 3.8656 | H74: {=IFERROR(_FV(H91,"Beta"),"")} | I74: {=IFERROR(_FV(I91,"Beta"),"")} | J74: {=IFERROR(_FV(J91,"Beta"),"")} | K74: {=IFERROR(_FV(K91,"Beta"),"")} | ... N74: {=IFERROR(_FV(N91,"Beta"),"")} | O74: =IFERROR(+AVERAGE(D74:N74),"") -> 2.381025
B75: β (Unlevered) | D75: =IFERROR(D74/(1+(1-0/D103)*(D121/D122)),"") -> 0.91386526 | E75: =IFERROR(E74/(1+(1-0.1/E103)*(E121/E122)),"") -> 2.4885883 | F75: =IFERROR(F74/(1+(1-0/F103)*(F121/F122)),"") -> 1.4785188 | G75: =IFERROR(G74/(1+(1-0/G103)*(G121/G122)),"") -> 3.8235113 | H75: =IFERROR(H74/(1+(1-H104/H103)*(H121/H122)),"") | I75: =IFERROR(I74/(1+(1-I104/I103)*(I121/I122)),"") | J75: =IFERROR(J74/(1+(1-J104/J103)*(J121/J122)),"") | K75: =IFERROR(K74/(1+(1-K104/K103)*(K121/K122)),"") | L75: =IFERROR(L74/(1+(1-L104/L103)*(L121/L122)),"") | M75: =IFERROR(M74/(1+(1-M104/M103)*(M121/M122)),"") | N75: =IFERROR(N74/(1+(1-N104/N103)*(N121/N122)),"") | O75: =IFERROR(+AVERAGE(D75:N75),"") -> 2.1761209
B76: % Held by Insiders | D76: 0.0176 | E76: 0.0854 | F76: 0.0108 | G76: 0.1725 | O76: =IFERROR(+AVERAGE(D76:N76),"") -> 0.071575
B77: % Held by Institutions | D77: 0.1936 | E77: 0.3741 | F77: 0.2406 | G77: 0.1652 | O77: =IFERROR(+AVERAGE(D77:N77),"") -> 0.243375
B78: Short % Float | D78: 0.231 | E78: 0.127 | F78: 0.2608 | G78: 0.19 | O78: =IFERROR(+AVERAGE(D78:N78),"") -> 0.2022
B80: Stock Performance | D80: =+D29 -> D-WAVE | E80: =+E29 -> IONQ | F80: =+F29 -> RIGETTI | G80: =+G29 -> QUANTUM | H80: =+H29 | I80: =+I29 | J80: =+J29 | K80: =+K29 | ... O80: =+O29 -> Average
B82: 1 day | D82: {=IFERROR((D85/_xlfn.STOCKHISTORY(C6,TODAY()-1,TODAY()-1,0,0,1))-1,"Non-trading days")} -> -0.024101146 | E82: {=IFERROR((E85/_xlfn.STOCKHISTORY(C8,TODAY()-1,TODAY()-1,0,0,1))-1,"Non-trading days")} -> Non-trading days | F82: {=IFERROR((F85/_xlfn.STOCKHISTORY(C9,TODAY()-1,TODAY()-1,0,0,1))-1,"Non-trading days")} -> Non-trading days | G82: {=IFERROR((G85/_xlfn.STOCKHISTORY(C10,TODAY()-1,TODAY()-1,0,0,1))-1,"Non-trading days")} -> Non-trading days | H82: {=IFERROR((K85/_xlfn.STOCKHISTORY(C11,TODAY()-1,TODAY()-1,0,0,1))-1,"Non-trading days")} -> Non-trading days | I82: {=IFERROR((L85/_xlfn.STOCKHISTORY(C12,TODAY()-1,TODAY()-1,0,0,1))-1,"Non-trading days")} -> Non-trading days | J82: {=IFERROR((M85/_xlfn.STOCKHISTORY(C13,TODAY()-1,TODAY()-1,0,0,1))-1,"Non-trading days")} -> Non-trading days | K82: {=IFERROR((N85/_xlfn.STOCKHISTORY(C14,TODAY()-1,TODAY()-1,0,0,1))-1,"Non-trading days")} -> Non-trading days | L82: {=IFERROR((L85/_xlfn.STOCKHISTORY(C15,TODAY()-1,TODAY()-1,0,0,1))-1,"Non-trading days")} -> Non-trading days | M82: {=IFERROR((M85/_xlfn.STOCKHISTORY(C16,TODAY()-1,TODAY()-1,0,0,1))-1,"Non-trading days")} -> Non-trading days | N82: {=IFERROR((N85/_xlfn.STOCKHISTORY(C17,TODAY()-1,TODAY()-1,0,0,1))-1,"Non-trading days")} -> Non-trading days | O82: =IFERROR(+AVERAGE(D82:N82),"") -> -0.024101146
B83: 1 month | D83: {=IFERROR((D85/_xlfn.STOCKHISTORY(C6,TODAY()-29,TODAY()-29,0,0,1))-1,"Non-trading days")} -> Non-trading days | E83: {=IFERROR((E85/_xlfn.STOCKHISTORY(C8,TODAY()-29,TODAY()-29,0,0,1))-1,"Non-trading days")} -> Non-trading days | F83: {=IFERROR((F85/_xlfn.STOCKHISTORY(C9,TODAY()-29,TODAY()-29,0,0,1))-1,"Non-trading days")} -> Non-trading days | G83: {=IFERROR((G85/_xlfn.STOCKHISTORY(C10,TODAY()-29,TODAY()-29,0,0,1))-1,"Non-trading days")} -> Non-trading days | H83: {=IFERROR((K85/_xlfn.STOCKHISTORY(C11,TODAY()-29,TODAY()-29,0,0,1))-1,"Non-trading days")} -> Non-trading days | I83: {=IFERROR((L85/_xlfn.STOCKHISTORY(C12,TODAY()-29,TODAY()-29,0,0,1))-1,"Non-trading days")} -> Non-trading days | J83: {=IFERROR((M85/_xlfn.STOCKHISTORY(C13,TODAY()-29,TODAY()-29,0,0,1))-1,"Non-trading days")} -> Non-trading days | K83: {=IFERROR((N85/_xlfn.STOCKHISTORY(C14,TODAY()-29,TODAY()-29,0,0,1))-1,"Non-trading days")} -> Non-trading days | L83: {=IFERROR((L85/_xlfn.STOCKHISTORY(C15,TODAY()-29,TODAY()-29,0,0,1))-1,"Non-trading days")} -> Non-trading days | M83: {=IFERROR((M85/_xlfn.STOCKHISTORY(C16,TODAY()-29,TODAY()-29,0,0,1))-1,"Non-trading days")} -> Non-trading days | N83: {=IFERROR((N85/_xlfn.STOCKHISTORY(C17,TODAY()-29,TODAY()-29,0,0,1))-1,"Non-trading days")} -> Non-trading days | O83: =IFERROR(AVERAGE(D83:N83),"")
B84: YTD | D84: {=IFERROR((D85/_xlfn.STOCKHISTORY(C6,"2025-01-02","2025-01-02",0,0,1))-1,"Non-trading days")} -> 1.5702393 | E84: {=IFERROR((E85/_xlfn.STOCKHISTORY(C8,"2025-01-02","2025-01-02",0,0,1))-1,"Non-trading days")} -> Non-trading days | F84: {=IFERROR((F85/_xlfn.STOCKHISTORY(C9,"2025-01-02","2025-01-02",0,0,1))-1,"Non-trading days")} -> Non-trading days | G84: {=IFERROR((G85/_xlfn.STOCKHISTORY(C10,"2025-01-02","2025-01-02",0,0,1))-1,"Non-trading days")} -> Non-trading days | H84: {=IFERROR((K85/_xlfn.STOCKHISTORY(C11,"2025-01-02","2025-01-02",0,0,1))-1,"Non-trading days")} -> Non-trading days | I84: {=IFERROR((L85/_xlfn.STOCKHISTORY(C12,"2025-01-02","2025-01-02",0,0,1))-1,"Non-trading days")} -> Non-trading days | J84: {=IFERROR((M85/_xlfn.STOCKHISTORY(C13,"2025-01-02","2025-01-02",0,0,1))-1,"Non-trading days")} -> Non-trading days | K84: {=IFERROR((N85/_xlfn.STOCKHISTORY(C14,"2025-01-02","2025-01-02",0,0,1))-1,"Non-trading days")} -> Non-trading days | L84: {=IFERROR((L85/_xlfn.STOCKHISTORY(C15,"2025-01-02","2025-01-02",0,0,1))-1,"Non-trading days")} -> Non-trading days | M84: {=IFERROR((M85/_xlfn.STOCKHISTORY(C16,"2025-01-02","2025-01-02",0,0,1))-1,"Non-trading days")} -> Non-trading days | N84: {=IFERROR((N85/_xlfn.STOCKHISTORY(C17,"2025-01-02","2025-01-02",0,0,1))-1,"Non-trading days")} -> Non-trading days | O84: =IFERROR(AVERAGE(D84:N84),"") -> 1.5702393
B85: Current Price | D85: {=+IFERROR(_FV(D91,"Price"),"")} -> 24.7 | E85: {=+IFERROR(_FV(E91,"Price"),"")} | F85: {=+IFERROR(_FV(F91,"Price"),"")} | G85: {=+IFERROR(_FV(G91,"Price"),"")} | H85: {=+IFERROR(_FV(H91,"Price"),"")} | I85: {=+IFERROR(_FV(I91,"Price"),"")} | J85: {=+IFERROR(_FV(J91,"Price"),"")} | K85: {=+IFERROR(_FV(K91,"Price"),"")} | ... N85: {=+IFERROR(_FV(N91,"Price"),"")} | O85: =IFERROR(AVERAGE(D85:N85),"") -> 24.7
B87: Extra
B89: % Revenues in the US | D89: 0.2437 | E89: 0.9452 | F89: 0.5863 | G89: N/A
B91: Income Statement | D91: =+DCF!R4 -> #VALUE! | E91: #VALUE! | F91: #VALUE! | G91: #VALUE! | H91: PEER 4 | I91: PEER 5 | J91: PEER 6 | K91: PEER 7 | L91: PEER 8 | M91: PEER 9 | N91: PEER 10
B93: =+Inputs!$B$6&" ("&Inputs!O$4&")" -> Revenue (Sales) (2022) | D93: =+_xlfn.XLOOKUP("Revenue (Sales)",Inputs!$B:$B,Inputs!O:O)*1000 -> 7173 | E93: 11131 | F93: 13102 | G93: 136
B94: =+Inputs!$B$6&" ("&Inputs!P$4&")" -> Revenue (Sales) (2023) | D94: =+_xlfn.XLOOKUP("Revenue (Sales)",Inputs!$B:$B,Inputs!P:P)*1000 -> 8758 | E94: 22042 | F94: 12008 | G94: 358
B95: EBITDA (2023) | D95: =+_xlfn.XLOOKUP("EBITDA",Inputs!$B:$B,Inputs!P:P)*1000 -> -75423 | E95: -147379 | F95: -61902 | G95: -25420
B96: Net Income (2023) | D96: =+_xlfn.XLOOKUP("Net Income",Inputs!$B:$B,Inputs!P:P)*1000 -> -82715 | E96: -157771 | F96: -75107 | G96: -27022
B97: =+Inputs!$B$6&" ("&Inputs!Q$4&")" -> Revenue (Sales) (2024) | D97: =+_xlfn.XLOOKUP("Revenue (Sales)",Inputs!$B:$B,Inputs!Q:Q)*1000 -> 8827 | E97: 43073 | F97: 10790 | G97: 373
B98: COGS (Cost of Goods Sold) | D98: =+_xlfn.XLOOKUP($B98,Inputs!$B:$B,Inputs!Q:Q)*1000 -> 3264 | E98: 21000 | F98: 5100 | G98: 260
B99: Gross Profit | D99: =+_xlfn.XLOOKUP($B99,Inputs!$B:$B,Inputs!Q:Q)*1000 -> 5563 | E99: =+E97-E98 -> 22073 | F99: =+F97-F98 -> 5690 | G99: =G97-G98 -> 113
B100: EBITDA | D100: =+_xlfn.XLOOKUP($B100,Inputs!$B:$B,Inputs!Q:Q)*1000 -> -69294 | E100: -213801 | F100: -190827 | G100: -62248
B101: Operating Income (EBIT) | D101: =+_xlfn.XLOOKUP($B101,Inputs!$B:$B,Inputs!Q:Q)*1000 -> -72786 | E101: -232455 | F101: -197733 | G101: -66046
B102: Net Interest Expense (Income) | D102: =+_xlfn.XLOOKUP($B102,Inputs!$B:$B,Inputs!Q:Q)*1000 -> 3897 | E102: 18 | F102: 3255 | G102: -2073
B103: Pre-Tax Income (EBT) | D103: =+_xlfn.XLOOKUP($B103,Inputs!$B:$B,Inputs!Q:Q)*1000 -> -143879 | E103: -331588 | F103: -200988 | G103: -68500
B104: Tax Expense (Benefits) | D104: =+_xlfn.XLOOKUP($B104,Inputs!$B:$B,Inputs!Q:Q)*1000 -> 0 | E104: $0,100 | F104: $0,000 | G104: $0,000
B105: Net Income | D105: =+_xlfn.XLOOKUP($B105,Inputs!$B:$B,Inputs!Q:Q)*1000 -> -143879 | E105: -331647 | F105: -200988 | G105: -68542
B106: EPS basic | D106: =+_xlfn.XLOOKUP($B106,Inputs!$B:$B,Inputs!Q:Q)*1000 -> -750 | E106: ($1.560) | F106: ($1,090) | G106: ($0,730)
B107: R&D (Research & Development) | D107: =+_xlfn.XLOOKUP($B107,Inputs!$B:$B,Inputs!Q:Q)*1000 -> 35300 | E107: 136827 | F107: 49750 | G107: 11318
B109: Balance Sheet
B111: Cash & Cash Equivalents | D111: =+_xlfn.XLOOKUP($B111,Inputs!$B:$B,Inputs!Q:Q)*1000 -> 177980 | E111: 54393 | F111: 67674 | G111: 78945
B112: Accounts Receivable | D112: =+_xlfn.XLOOKUP($B112,Inputs!$B:$B,Inputs!Q:Q)*1000 -> 1420 | E112: 6516 | F112: 2427 | G112: 27
B113: Beginning Inventory | D113: =+_xlfn.XLOOKUP("Inventory",Inputs!$B:$B,Inputs!P:P)*1000 -> 2078 | E113: 12476 | F113: 0 | G113: 73
B114: Ending Inventory | D114: =+_xlfn.XLOOKUP("Inventory",Inputs!$B:$B,Inputs!Q:Q)*1000 -> 1686 | E114: 18658 | F114: 0 | G114: 18
B115: Current Assets | D115: =+_xlfn.XLOOKUP($B115,Inputs!$B:$B,Inputs!Q:Q)*1000 -> 185040 | E115: 378802 | F115: 206758 | G115: 79151
B116: Net PP&E (Property, Plant and Equipment) | D116: =+_xlfn.XLOOKUP($B116,Inputs!$B:$B,Inputs!Q:Q)*1000 -> 11394 | E116: 62.231 | F116: 52.636 | G116: 9.734
B117: Total Assets | D117: =+_xlfn.XLOOKUP($B117,Inputs!$B:$B,Inputs!Q:Q)*1000 -> 199853 | E117: 508388 | F117: 284787 | G117: 153559
B118: Accounts Payable | D118: =+_xlfn.XLOOKUP($B118,Inputs!$B:$B,Inputs!Q:Q)*1000 -> 815 | E118: 5.23 | F118: 1.981 | G118: 1.372
B119: Current Liabilities | D119: =+_xlfn.XLOOKUP($B119,Inputs!$B:$B,Inputs!Q:Q)*1000 -> 30145 | E119: 36.085 | F119: 11.867 | G119: 4.559
B120: Long-term debt | D120: =+_xlfn.XLOOKUP($B120,Inputs!$B:$B,Inputs!Q:Q)*1000 -> 36517 | E120: 0 | F120: 0 | G120: 0
B121: Total Debt | D121: =+_xlfn.XLOOKUP($B121,Inputs!$B:$B,Inputs!Q:Q,,,-1)*1000 -> 38377 | E121: 17725 | F121: 8800 | G121: 1181
B122: Shareholder's Equity | D122: =+_xlfn.XLOOKUP($B122,Inputs!$B:$B,Inputs!Q:Q)*1000 -> 62646 | E122: 383862 | F122: 126589 | G122: 107287
B124: Cash Flow Statement
B126: Operating Cash Flow | D126: =+_xlfn.XLOOKUP($B126,Inputs!$B:$B,Inputs!Q:Q)*1000 -> -42643 | E126: -105863 | F126: -50627 | G126: -16213
B127: Net Capex | D127: =+_xlfn.XLOOKUP($B127,Inputs!$B:$B,Inputs!Q:Q)*1000 -> -2395 | E127: -18000 | F127: -11100 | G127: -6000
B128: Investing Cash Flow | D128: =+_xlfn.XLOOKUP($B128,Inputs!$B:$B,Inputs!Q:Q)*1000 -> -3141 | E128: 82730 | F128: -78362 | G128: -6360
...

Sheet ESG
B2: Environmental, Social and Governance Analysis
B4: Author: | E4: Highlights | N4: Recent News
N5: In January 2025, D-Wave partnered with Carahsoft to expand the distribution of its quantum computing solutions to the public sector. This collaboration aims to increase accessibility and adoption of D-Wave's annealing quantum computing technology among U.S. government agencies, facilitating advancements in areas such as national defense, emergency response, and infrastructure optimization.
B6: Overview | D6: . | E6: D-Wave stands out for its stable executive leadership, strong board governance, and meaningful community involvement.
B7: Last Update | D7: . | E7: However, it lacks transparency on environmental impact and has no ESG-linked compensation or clear DEI policies.
B8: Latest year with data | E8: Concerns around workplace culture and inclusion also remain, highlighting areas for improvement in social governance.
B9: GICS Sector
B10: GICS Industry Group
B11: Final Review
B13: ESG Scores
B14: LSEG ESG Score
B15: E-Score
B16: S-Score | E16: GHG Scope 1 and 2 Emissions: | N16: Water, Waste, Energy Management:
B17: G-Score
B18: S&P Global ESG Score
B19: Environmental
B20: Social
B21: Governance & Economic
B22: Sustainalytics
B23: ISS ESG Corporate Rating
B24: SDG Impact Rating
B25: Governance Quality Score
B26: MSCI ESG Ratings
B29: Industry ESG Overview:
E33: ENVIRONMENTAL
G35: Overview | H35: Targets | K35: Improvements | O35: Comments
E36: GHG (or CO2) Scope 1 Emissions
E38: Water Consumption
E40: Energy Consumption
E42: Waste Management
E44: Other
E46: SOCIAL
B48: Important Sources: | G48: Overview | H48: Targets | K48: Improvements | O48: Comments
B49: Annual Report | E49: Employee Turnover % | H49: Maintain or improve employee retention and satisfaction. | K49: Despite a 6.98% headcount reduction, D-Wave maintains its employee satisfaction score. | O49: While D-Wave reports high employee satisfaction, there remains room for improvement, particularly given signs of instability within specific departments.
B50: Sustainability Report | D50: .
B51: Proxy Statement | D51: . | E51: Salaries & Compensation | H51: Implement diversity, equity, and inclusion (DEI) metrics into compensation plans to foster a more inclusive workplace. | K51: D-Wave offers competitive salaries across various roles, indicating a commitment to fair compensation. | O51: As of 2024, there is no public evidence that D-Wave has integrated DEI or other social metrics into its compensation structures.
B52: Financial Times
B53: GlassDoor | E53: Reputation | H53: D-Wave aims to prove that its quantum optimization technology can outperform classical systems in real-word problems. | K53: Analysts gave positive ratings after strong revenue growth and product progress. | O53: Despite advancements, D-Wave faces skepticism from parts of the scientific community about the broader applicability of its quantum optimization method and the extent of its advantage.
B54: dwavequantum.com
B55: dwavefederal.com | E55: Discrimination Events | H55: Create and maintain an inclusive and ethical culture where equal opportunity is promoted. | K55: D-Wave has implemented a Code of Conduct and community guidelines that explicitly prohibit discrimination and harassment. | O55: There are anonymous reviews alleging that feedback and questions were "not well-received" especially if it came from a women.
B56: D-Wave’s SEC filings
E57: Work Safety | H57: Update the protocols as technology changes. | K57: Created clear safety rules and training programs for lab workers and staff working with cryogenic systems to keep them safe. | O57: There are no significant reports of safety concerns, however, it does not demonstrate notable innovation in occupational safety practices either.
E59: Damage to consumer health | H59: Communicate any workplace hazards publicly (even if minor), showing a strong commitment to consumer and worker safety. | K59: D-Wave's quantum computers use superconducting circuits operating at ultra-low temperatures and do not involve radiation-producing components, meaning there is no ionizing radiation risk to workers or consumers. | O59: D-Wave’s technology is especially safe from a health perspective, as it eliminates concerns typically associated with high-energy radiation exposure found in other advanced technologies.
E61: Pension Plan | H61: Implement a formal employer-supported retirement savings plan in Canada to ensure consistency across all employee regions. | K61: Established a 401(k) Plan for U.S. Employees, providing a structured, tax-advantaged retirement savings options. | O61: Expanding consistent retirement benefits across regions strengthens employee trust, enhances competitiveness, and lays the foundation for future global growth.
E63: Supply chain | H63: It aims to scale these solutions globally with partners like DP World, targeting complex logistics across industries. | K63: Improved supply chains by boosting port productivity and cargo predictability through quantum optimization. | O63: Specifically, it helped increase the number of containers moved per day and reduced the time and distance cranes needed to travel, leading to faster, smoother, and more organized port logistics.
E65: Community involvement | H65: Expand global community engagement by promoting open-source contributions, hosting hackathons, and providing accessible educational resources for diverse populations. | K65: D-Wave has built strong academic partnerships, launched the Leap™ quantum cloud platform and engaged the public through events and volunteer science projects. | O65: Strong community ties amplify D-Wave’s influence across industries and demographics, creating new opportunities for partnerships, discovery, and market expansion.
E67: Public Sector | H67: Aims to deepen government collaboration, prepare for emerging quantum tech regulations, and expand public-sector applications to support commercial growth. | K67: Established strong partnerships with public institutions like NASA and secured government funding, all while remaining a privately owned, publicly traded company. | O67: N/A
E69: Litigation | H69: Aims to complete restatements, resolve legal investigations, regain listing compliance, and rebuild investor confidence. | K69: Acknowledged past financial reporting errors and is actively restating its statements while addressing NYSE compliance concerns. | O69: N/A
E71: GOVERNANCE
G73: Overview | H73: Targets | K73: Improvements | O73: Comments
E74: Diversity (Gender, Age, Industry, Region) | H74: Raise the percentage of women on the board, as well as bring in some youger members. | K74: D-Wave has added directors from different backgrounds, broadening the board's expertise beyond pure technical quantum research. | O74: D-Wave has not publicly disclosed specific numerical diversity goals. Setting public targets would align them better with top ESG practices
E76: % Independence | H76: Increase board independence to 70-80%. | K76: Since 2022, D-Wave expanded its board with new independent memebers as part of its transition to a public company. | O76: Even though D-Wave has a relatively decent percentage of independet directors, it is not extremely high compared to "best practices" for a public company.
E78: Average time as independent directors | H78: Ensuring that independent directors play a critical role in shaping the company's strategic direction and overseeing risk management. | K78: As a newly public company, D-Wave has proritized building a strong, independent board through recent appointments. Improvements in long-term tenure will naturally develop over time as directors continue their service. | O78: The average tenure of independent directors is approximately 2 years, reflecting the company's relatively recent transition to a public entity in 2022.
E80: Departures of C-level executives | H80: Focus on retaining key executives, developing succession plans, and strengthening the leadership team's public presence. | K80: Promoted internal talent, strengthened board oversight, introduced long-term retention incentives. | O80: The fact that there have been no C-level executive departures during recent financial and board transitions shows strong internal alignment and resilience.
E82: CEO/Chairman duality | H82: Aims to continue this structure to ensure that corporate governance remains a competitive advantage as the company grows. | K82: Improved its board oversight, ensuring that management decisions are independently reviewed and challenged by the Chairman and the Board. | O82: Separating the roles limits the risk of too much power being concentrated in one individual, which promotes healthier checks and balances in leadership decisions.
E84: Transparency when reporting | H84: Begin reporting on the environmental footprint of its quantum systems, including energy consumption and sustainability measures. | K84: Increased scientific transparency by publishing more results through peer-reviewed journals, such as the 2021 hybrid solver study. | O84: While D-Wave shares more technical documents now, some limitations, like restricted problem classes or noise effects, are still not always emphasized equally.
E86: Time taken to report | H86: Provide more real-time updates between earnings - via press releases, business updates and techinal progress reports (not just quarterly) | K86: Since going public, D-Wave has filed all financial reports on time, increased the frequency of public updates, and shortened the delay between achieving milestones and annoucing them to the public. | O86: D-Wave usually reports about 1.5 months after the quarter ends and 2.5 months after the fiscal year ends.
E88: CEO or Chairman in other boards? | H88: Expand external board participation to enhance D-Wave's strategic reach and exposure to broader technology trends. | K88: Although the CEO currently does not hold external board positions, his prior board service has brought valuable governance expertise to D-Wave. | O88: Engaging external board roles is a proven way to bring fresh perspectives into a company’s leadership.
E90: Audit / Consulting | H90: Expand its audit and consulting services by building on its cost efficient practices, offering broader compliance support and enhancing transparency. | K90: Maintained audit fees below industry averages and avoided extra non-audit expenses. | O90: In 2023, D-Wave Quantum Inc. reported an audit fee of $475,000, with no additional fees for audit-related services, tax services, or other services. This total is below the average audit fee of $703,000 for non-accelerated filers in 2023.
E92: ESG-compensation related | H92: Formally integrate ESG performance metrics into employee and management bonus structures. | K92: So far, D-Wave has not yet incorporated any ESG-specific KPIs into its compensation structures, representing an area for future development. | O92: Explicitly linking a portion of bonuses to ESG outcomes would strengthen accountability, align with evolving market expectations and position the company as a forward-looking leader in responsible quantum innovation.
E94: Management compensation schemes | H94: Balance stock-based compensation with long-term technical milestones and operational KPIs to better align incentives with the company's deep-tech, long-horizon nature. | K94: Adopted performance-linked equity awards and is increasingly focusing on generating real customer revenue. | O94: Given the quantum sector’s extreme market swings and long development timelines, compensation schemes must evolve carefully to avoid rewarding short-term hype over genuine technological progress.

Sheet ESG Inputs
B2: ESG Inputs
A4: x | B4: Total GHG Scope 1 Emissions | G4: 2014 | H4: =+G4+1 -> 2015 | I4: =+H4+1 -> 2016 | J4: =+I4+1 -> 2017 | K4: =+J4+1 -> 2018 | L4: =+K4+1 -> 2019 | M4: =+L4+1 -> 2020 | N4: =+M4+1 -> 2021 | O4: =+N4+1 -> 2022 | ... Q4: =+P4+1 -> 2024 | R4: ="CAGR "&$G$4&" - "&$Q$4 -> CAGR 2014 - 2024
B6: =+Peers!B6 -> D-WAVE QUANTUM INC. | R6: =IFERROR((Q6/G6)^(1/COUNT($G$4:$Q$4))-1,"")
B7: =+Peers!B8 -> IONQ INC. | R7: =IFERROR((Q7/G7)^(1/COUNT($G$4:$Q$4))-1,"")
B8: =+Peers!B9 -> RIGETTI COMPUTING INC. | R8: =IFERROR((Q8/G8)^(1/COUNT($G$4:$Q$4))-1,"")
B9: =+Peers!B10 -> QUANTUM COMPUTING INC. | R9: =IFERROR((Q9/G9)^(1/COUNT($G$4:$Q$4))-1,"")
B10: =+Peers!B11 | R10: =IFERROR((Q10/G10)^(1/COUNT($G$4:$Q$4))-1,"")
B11: =+Peers!B12 | R11: =IFERROR((Q11/G11)^(1/COUNT($G$4:$Q$4))-1,"")
B12: =+Peers!B13 | R12: =IFERROR((Q12/G12)^(1/COUNT($G$4:$Q$4))-1,"")
B13: =+Peers!B14 | R13: =IFERROR((Q13/G13)^(1/COUNT($G$4:$Q$4))-1,"")
B14: =+Peers!B15 | R14: =IFERROR((Q14/G14)^(1/COUNT($G$4:$Q$4))-1,"")
B15: =+Peers!B16 | R15: =IFERROR((Q15/G15)^(1/COUNT($G$4:$Q$4))-1,"")
B16: =+Peers!B17 | R16: =IFERROR((Q16/G16)^(1/COUNT($G$4:$Q$4))-1,"")
A18: x | B18: Total GHG Scope 2 (Location-Based) Emissions | G18: 2014 | H18: =+G18+1 -> 2015 | I18: =+H18+1 -> 2016 | J18: =+I18+1 -> 2017 | K18: =+J18+1 -> 2018 | L18: =+K18+1 -> 2019 | M18: =+L18+1 -> 2020 | N18: =+M18+1 -> 2021 | O18: =+N18+1 -> 2022 | ... Q18: =+P18+1 -> 2024 | R18: ="CAGR "&$G$4&" - "&$Q$4 -> CAGR 2014 - 2024
B20: =+$B$6 -> D-WAVE QUANTUM INC. | R20: =IFERROR((Q20/G20)^(1/COUNT($G$4:$Q$4))-1,"")
B21: =+$B$7 -> IONQ INC. | R21: =IFERROR((Q21/G21)^(1/COUNT($G$4:$Q$4))-1,"")
B22: =+$B$8 -> RIGETTI COMPUTING INC. | R22: =IFERROR((Q22/G22)^(1/COUNT($G$4:$Q$4))-1,"")
B23: =+$B$9 -> QUANTUM COMPUTING INC. | R23: =IFERROR((Q23/G23)^(1/COUNT($G$4:$Q$4))-1,"")
B24: =+$B$10 | R24: =IFERROR((Q24/G24)^(1/COUNT($G$4:$Q$4))-1,"")
B25: =+$B$11 | R25: =IFERROR((Q25/G25)^(1/COUNT($G$4:$Q$4))-1,"")
B26: =+$B$12 | R26: =IFERROR((Q26/G26)^(1/COUNT($G$4:$Q$4))-1,"")
B27: =+$B$13 | R27: =IFERROR((Q27/G27)^(1/COUNT($G$4:$Q$4))-1,"")
B28: =+$B$14 | R28: =IFERROR((Q28/G28)^(1/COUNT($G$4:$Q$4))-1,"")
B29: =+$B$15 | R29: =IFERROR((Q29/G29)^(1/COUNT($G$4:$Q$4))-1,"")
B30: =+$B$16 | R30: =IFERROR((Q30/G30)^(1/COUNT($G$4:$Q$4))-1,"")
A32: x | B32: Total Energy Usage | G32: 2014 | H32: =+G32+1 -> 2015 | I32: =+H32+1 -> 2016 | J32: =+I32+1 -> 2017 | K32: =+J32+1 -> 2018 | L32: =+K32+1 -> 2019 | M32: =+L32+1 -> 2020 | N32: =+M32+1 -> 2021 | O32: =+N32+1 -> 2022 | ... Q32: =+P32+1 -> 2024 | R32: ="CAGR "&$G$4&" - "&$Q$4 -> CAGR 2014 - 2024
B34: =+$B$6 -> D-WAVE QUANTUM INC. | R34: =IFERROR((Q34/G34)^(1/COUNT($G$4:$Q$4))-1,"")
B35: =+$B$7 -> IONQ INC. | R35: =IFERROR((Q35/G35)^(1/COUNT($G$4:$Q$4))-1,"")
B36: =+$B$8 -> RIGETTI COMPUTING INC. | R36: =IFERROR((Q36/G36)^(1/COUNT($G$4:$Q$4))-1,"")
B37: =+$B$9 -> QUANTUM COMPUTING INC. | R37: =IFERROR((Q37/G37)^(1/COUNT($G$4:$Q$4))-1,"")
B38: =+$B$10 | R38: =IFERROR((Q38/G38)^(1/COUNT($G$4:$Q$4))-1,"")
B39: =+$B$11 | R39: =IFERROR((Q39/G39)^(1/COUNT($G$4:$Q$4))-1,"")
B40: =+$B$12 | R40: =IFERROR((Q40/G40)^(1/COUNT($G$4:$Q$4))-1,"")
B41: =+$B$13 | R41: =IFERROR((Q41/G41)^(1/COUNT($G$4:$Q$4))-1,"")
B42: =+$B$14 | R42: =IFERROR((Q42/G42)^(1/COUNT($G$4:$Q$4))-1,"")
B43: =+$B$15 | R43: =IFERROR((Q43/G43)^(1/COUNT($G$4:$Q$4))-1,"")
B44: =+$B$16 | R44: =IFERROR((Q44/G44)^(1/COUNT($G$4:$Q$4))-1,"")
A46: x | B46: Total Water Consumption | G46: 2014 | H46: =+G46+1 -> 2015 | I46: =+H46+1 -> 2016 | J46: =+I46+1 -> 2017 | K46: =+J46+1 -> 2018 | L46: =+K46+1 -> 2019 | M46: =+L46+1 -> 2020 | N46: =+M46+1 -> 2021 | O46: =+N46+1 -> 2022 | ... Q46: =+P46+1 -> 2024 | R46: ="CAGR "&$G$4&" - "&$Q$4 -> CAGR 2014 - 2024
B48: =+$B$6 -> D-WAVE QUANTUM INC. | R48: =IFERROR((Q48/G48)^(1/COUNT($G$4:$Q$4))-1,"")
B49: =+$B$7 -> IONQ INC. | R49: =IFERROR((Q49/G49)^(1/COUNT($G$4:$Q$4))-1,"")
B50: =+$B$8 -> RIGETTI COMPUTING INC. | R50: =IFERROR((Q50/G50)^(1/COUNT($G$4:$Q$4))-1,"")
B51: =+$B$9 -> QUANTUM COMPUTING INC. | R51: =IFERROR((Q51/G51)^(1/COUNT($G$4:$Q$4))-1,"")
B52: =+$B$10 | R52: =IFERROR((Q52/G52)^(1/COUNT($G$4:$Q$4))-1,"")
B53: =+$B$11 | R53: =IFERROR((Q53/G53)^(1/COUNT($G$4:$Q$4))-1,"")
B54: =+$B$12 | R54: =IFERROR((Q54/G54)^(1/COUNT($G$4:$Q$4))-1,"")
B55: =+$B$13 | R55: =IFERROR((Q55/G55)^(1/COUNT($G$4:$Q$4))-1,"")
B56: =+$B$14 | R56: =IFERROR((Q56/G56)^(1/COUNT($G$4:$Q$4))-1,"")
B57: =+$B$15 | R57: =IFERROR((Q57/G57)^(1/COUNT($G$4:$Q$4))-1,"")
B58: =+$B$16 | R58: =IFERROR((Q58/G58)^(1/COUNT($G$4:$Q$4))-1,"")
A60: x | B60: Total Waste Production | G60: 2014 | H60: =+G60+1 -> 2015 | I60: =+H60+1 -> 2016 | J60: =+I60+1 -> 2017 | K60: =+J60+1 -> 2018 | L60: =+K60+1 -> 2019 | M60: =+L60+1 -> 2020 | N60: =+M60+1 -> 2021 | O60: =+N60+1 -> 2022 | ... Q60: =+P60+1 -> 2024 | R60: ="CAGR "&$G$4&" - "&$Q$4 -> CAGR 2014 - 2024
B62: =+$B$6 -> D-WAVE QUANTUM INC. | R62: =IFERROR((Q62/G62)^(1/COUNT($G$4:$Q$4))-1,"")
B63: =+$B$7 -> IONQ INC. | R63: =IFERROR((Q63/G63)^(1/COUNT($G$4:$Q$4))-1,"")
B64: =+$B$8 -> RIGETTI COMPUTING INC. | R64: =IFERROR((Q64/G64)^(1/COUNT($G$4:$Q$4))-1,"")
B65: =+$B$9 -> QUANTUM COMPUTING INC. | R65: =IFERROR((Q65/G65)^(1/COUNT($G$4:$Q$4))-1,"")
B66: =+$B$10 | R66: =IFERROR((Q66/G66)^(1/COUNT($G$4:$Q$4))-1,"")
B67: =+$B$11 | R67: =IFERROR((Q67/G67)^(1/COUNT($G$4:$Q$4))-1,"")
B68: =+$B$12 | R68: =IFERROR((Q68/G68)^(1/COUNT($G$4:$Q$4))-1,"")
B69: =+$B$13 | R69: =IFERROR((Q69/G69)^(1/COUNT($G$4:$Q$4))-1,"")
B70: =+$B$14 | R70: =IFERROR((Q70/G70)^(1/COUNT($G$4:$Q$4))-1,"")
B71: =+$B$15 | R71: =IFERROR((Q71/G71)^(1/COUNT($G$4:$Q$4))-1,"")
B72: =+$B$16 | R72: =IFERROR((Q72/G72)^(1/COUNT($G$4:$Q$4))-1,"")
A74: x | B74: GHG Scope 1 and 2 Emissions | G74: 2014 | H74: =+G74+1 -> 2015 | I74: =+H74+1 -> 2016 | J74: =+I74+1 -> 2017 | K74: =+J74+1 -> 2018 | L74: =+K74+1 -> 2019 | M74: =+L74+1 -> 2020 | N74: =+M74+1 -> 2021 | O74: =+N74+1 -> 2022 | ... Q74: =+P74+1 -> 2024 | R74: ="CAGR "&$G$4&" - "&$Q$4 -> CAGR 2014 - 2024
B76: =+$B$6 -> D-WAVE QUANTUM INC. | G76: =+G6+G20 -> 0 | H76: =+H6+H20 -> 0 | I76: =+I6+I20 -> 0 | J76: =+J6+J20 -> 0 | K76: =+K6+K20 -> 0 | L76: =+L6+L20 -> 0 | M76: =+M6+M20 -> 0 | N76: =+N6+N20 -> 0 | ... Q76: =+Q6+Q20 -> 0 | R76: =IFERROR((Q76/G76)^(1/COUNT($G$4:$Q$4))-1,"")
B77: =+$B$7 -> IONQ INC. | G77: =+G7+G21 -> 0 | H77: =+H7+H21 -> 0 | I77: =+I7+I21 -> 0 | J77: =+J7+J21 -> 0 | K77: =+K7+K21 -> 0 | L77: =+L7+L21 -> 0 | M77: =+M7+M21 -> 0 | N77: =+N7+N21 -> 0 | ... Q77: =+Q7+Q21 -> 0 | R77: =IFERROR((Q77/G77)^(1/COUNT($G$4:$Q$4))-1,"")
B78: =+$B$8 -> RIGETTI COMPUTING INC. | G78: =+G8+G22 -> 0 | H78: =+H8+H22 -> 0 | I78: =+I8+I22 -> 0 | J78: =+J8+J22 -> 0 | K78: =+K8+K22 -> 0 | L78: =+L8+L22 -> 0 | M78: =+M8+M22 -> 0 | N78: =+N8+N22 -> 0 | ... Q78: =+Q8+Q22 -> 0 | R78: =IFERROR((Q78/G78)^(1/COUNT($G$4:$Q$4))-1,"")
B79: =+$B$9 -> QUANTUM COMPUTING INC. | G79: =+G9+G23 -> 0 | H79: =+H9+H23 -> 0 | I79: =+I9+I23 -> 0 | J79: =+J9+J23 -> 0 | K79: =+K9+K23 -> 0 | L79: =+L9+L23 -> 0 | M79: =+M9+M23 -> 0 | N79: =+N9+N23 -> 0 | ... Q79: =+Q9+Q23 -> 0 | R79: =IFERROR((Q79/G79)^(1/COUNT($G$4:$Q$4))-1,"")
B80: =+$B$10 | G80: =+G10+G24 -> 0 | H80: =+H10+H24 -> 0 | I80: =+I10+I24 -> 0 | J80: =+J10+J24 -> 0 | K80: =+K10+K24 -> 0 | L80: =+L10+L24 -> 0 | M80: =+M10+M24 -> 0 | N80: =+N10+N24 -> 0 | ... Q80: =+Q10+Q24 -> 0 | R80: =IFERROR((Q80/G80)^(1/COUNT($G$4:$Q$4))-1,"")
B81: =+$B$11 | G81: =+G11+G25 -> 0 | H81: =+H11+H25 -> 0 | I81: =+I11+I25 -> 0 | J81: =+J11+J25 -> 0 | K81: =+K11+K25 -> 0 | L81: =+L11+L25 -> 0 | M81: =+M11+M25 -> 0 | N81: =+N11+N25 -> 0 | ... Q81: =+Q11+Q25 -> 0 | R81: =IFERROR((Q81/G81)^(1/COUNT($G$4:$Q$4))-1,"")
B82: =+$B$12 | G82: =+G12+G26 -> 0 | H82: =+H12+H26 -> 0 | I82: =+I12+I26 -> 0 | J82: =+J12+J26 -> 0 | K82: =+K12+K26 -> 0 | L82: =+L12+L26 -> 0 | M82: =+M12+M26 -> 0 | N82: =+N12+N26 -> 0 | ... Q82: =+Q12+Q26 -> 0 | R82: =IFERROR((Q82/G82)^(1/COUNT($G$4:$Q$4))-1,"")
B83: =+$B$13 | G83: =+G13+G27 -> 0 | H83: =+H13+H27 -> 0 | I83: =+I13+I27 -> 0 | J83: =+J13+J27 -> 0 | K83: =+K13+K27 -> 0 | L83: =+L13+L27 -> 0 | M83: =+M13+M27 -> 0 | N83: =+N13+N27 -> 0 | ... Q83: =+Q13+Q27 -> 0 | R83: =IFERROR((Q83/G83)^(1/COUNT($G$4:$Q$4))-1,"")
B84: =+$B$14 | G84: =+G14+G28 -> 0 | H84: =+H14+H28 -> 0 | I84: =+I14+I28 -> 0 | J84: =+J14+J28 -> 0 | K84: =+K14+K28 -> 0 | L84: =+L14+L28 -> 0 | M84: =+M14+M28 -> 0 | N84: =+N14+N28 -> 0 | ... Q84: =+Q14+Q28 -> 0 | R84: =IFERROR((Q84/G84)^(1/COUNT($G$4:$Q$4))-1,"")
B85: =+$B$15 | G85: =+G15+G29 -> 0 | H85: =+H15+H29 -> 0 | I85: =+I15+I29 -> 0 | J85: =+J15+J29 -> 0 | K85: =+K15+K29 -> 0 | L85: =+L15+L29 -> 0 | M85: =+M15+M29 -> 0 | N85: =+N15+N29 -> 0 | ... Q85: =+Q15+Q29 -> 0 | R85: =IFERROR((Q85/G85)^(1/COUNT($G$4:$Q$4))-1,"")
B86: =+$B$16 | G86: =+G16+G30 -> 0 | H86: =+H16+H30 -> 0 | I86: =+I16+I30 -> 0 | J86: =+J16+J30 -> 0 | K86: =+K16+K30 -> 0 | L86: =+L16+L30 -> 0 | M86: =+M16+M30 -> 0 | N86: =+N16+N30 -> 0 | ... Q86: =+Q16+Q30 -> 0 | R86: =IFERROR((Q86/G86)^(1/COUNT($G$4:$Q$4))-1,"")

Sheet DCF
B2: DCF
A4: x | B4: Key Assumptions | R4: #VALUE!
B6: Switches | E6: Bear Case | H6: Base Case | K6: Bull Case | X6: FCFF | Y6: FCFE | Z6: Tax Shield | AA6: Total Payout | AB6: NOPAT | AC6: Debt Borrowing | AD6: Cash Balance | AE6: Total Assets | AF6: Total Liabilities | AG6: Shareholder's Equity | AH6: Current Liabilities | AI6: Current Assets
B7: Revenue | C7: 2 | E7: Revenue | F7: -0.02 | H7: Revenue | K7: Revenue | L7: 0.02 | W7: 2022 | X7: =+E191 -> 22.096 | Y7: =+E243 -> 5.064 | Z7: =+H215 -> 0 | AA7: =+E256 -> 40 | AB7: =+E181 -> 8 | AC7: =+E241 -> 44.67 | AD7: =+E86 -> 7.065 | AS7: Most Recent Fiscal Year
B8: EBIT | C8: 2 | E8: EBIT | F8: -0.01 | H8: EBIT | K8: EBIT | L8: 0.01 | W8: =+W7+1 -> 2023 | X8: =+F191 -> -56.785 | Y8: =+F243 -> -28.344 | Z8: =+I215 -> 0 | AA8: =+F256 -> 63.676 | AB8: =+F181 -> -77.268 | AC8: =+F241 -> 33.888 | AD8: =+F86 -> 41.307 | AS8: End of Fiscal Year
B9: WACC | C9: 2 | E9: WACC | F9: =IFERROR(+I9+0.5%,"") -> 0.078104697 | H9: WACC | I9: =WACC!G25 -> 0.073104697 | K9: WACC | L9: =IFERROR(I9-0.5%,"") -> 0.068104697 | W9: =+W8+1 -> 2024 | X9: =+G191 -> -36.726 | Y9: =+G243 -> -77.449 | Z9: =+J215 -> 0 | AA9: =+G256 -> 214.191 | AB9: =+G181 -> -72.786 | AC9: =+G241 -> 30.37 | AD9: =+G86 -> 177.98 | AE9: =Inputs!Q48 -> 199.853 | AF9: =+Inputs!Q60 -> 137.207 | AG9: =+AE9-AF9 -> 62.646 | AH9: =+Inputs!Q54 -> 30.145 | AI9: =+Inputs!Q38 -> 185.04 | AS9: Most Recent Quarter End Date
B10: TGR | C10: 2 | E10: TGR | F10: =+I10-0.5% -> 0.015 | H10: TGR | I10: 0.02 | K10: TGR | L10: =+I10+0.5% -> 0.025 | W10: =+W9+1 -> 2025 | X10: =+H191 -> -70.28795 | Y10: =+H243 -> -19.642917 | Z10: =+K215 -> 0 | AA10: =+H256 -> 0 | AB10: =+H181 -> -82.731013 | AC10: =+H241 -> 77.449 | AD10: =+H86 -> 190.31468 | AE10: =Inputs!Q48+DCF!H86+DCF!H88+DCF!H91+DCF!H94+DCF!H97+DCF!H103-DCF!G86-DCF!G88-DCF!G91-DCF!G94-DCF!G97-DCF!G103 -> 222.89526 | AF10: =+Inputs!Q60+(DCF!H108+DCF!H111+DCF!H114+DCF!H116*DCF!G108*DCF!G111*DCF!G114*DCF!G116) -> 9824.0894 | AG10: =+AE10-AF10 -> -9601.1941 | AH10: =+AH9+H108+H111-G108-G111 -> 30.971029 | AI10: =+H86+H88+H91+H94 -> 201.05646 | AS10: Valuation Date
W11: =+W10+1 -> 2026 | X11: =+I191 -> -83.004918 | Y11: =+I243 -> -110.63419 | Z11: =+L215 -> 0 | AA11: =+I256 -> 0 | AB11: =+I181 -> -104.75181 | AC11: =+I241 -> 19.642917 | AD11: =+I86 -> 131.11335 | AE11: =AE10+DCF!I86+DCF!I88+DCF!I91+DCF!I94+DCF!I97+DCF!I103-DCF!H86-DCF!H88-DCF!H91-DCF!H94-DCF!H97-DCF!H103 -> 174.16843 | AF11: =AF10+(DCF!I108+DCF!I111+DCF!I114+DCF!I116*DCF!H108*DCF!H111*DCF!H114*DCF!H116) -> 1462259.8 | AG11: =+AE11-AF11 -> -1462085.6 | AH11: =+AH10+I108+I111-H108-H111 -> 39.200798 | AI11: =+I86+I88+I91+I94 -> 145.72851
B12: WACC | C12: =CHOOSE(C9,F9,I9,L9) -> 0.073104697 | W12: =+W11+1 -> 2027 | X12: =+J191 -> -108.3403 | Y12: =+J243 -> -71.096395 | Z12: =+M215 -> 0 | AA12: =+J256 -> 0 | AB12: =+J181 -> -132.90496 | AC12: =+J241 -> 110.63419 | AD12: =+J86 -> 137.39
B13: WACC with Tax Rate | C13: =WACC!G26 -> 0.073104697
B14: TGR | C14: =CHOOSE(C10,F10,I10,L10) -> 0.02 | W14: =+W12+1 -> 2028 | X14: =+K191 -> -146.4819 | Y14: =+K243 -> -155.89612 | Z14: =+N215 -> 0 | AA14: =+K256 -> 0 | AB14: =+K181 -> -168.57578 | AC14: =+K241 -> 71.096395 | AD14: =+K86 -> 67.245073
W15: =+W14+1 -> 2029 | X15: =+L191 -> -171.10265 | Y15: =+L243 -> -124.54688 | Z15: =+O215 -> 0 | AA15: =+L256 -> 0 | AB15: =+L181 -> -194.76307 | AC15: =+L241 -> 155.89612 | AD15: =+L86 -> 57.128641
A16: x | B16: Operating Assumptions | E16: 2022 | F16: =+E16+1 -> 2023 | G16: =+F16+1 -> 2024 | H16: =+G16+1 -> 2025 | I16: =+H16+1 -> 2026 | J16: =+I16+1 -> 2027 | K16: =+J16+1 -> 2028 | L16: =+K16+1 -> 2029 | M16: =+L16+1 -> 2030 | ... Q16: =+P16+1 -> 2034 | R16: 2035E | S16: 2036E | T16: 2037E | U16: 2038E | V16: 2039E | W16: 2040E | X16: 2041E | Y16: 2042E | Z16: 2043E | AA16: 2044E | AB16: 2045E
B18: Market Size (Fortune Business Insights) | E18: 695400 | F18: 885400 | G18: 1160100 | H18: =G18*(1+H19) -> 1508130 | I18: =H18*(1+I19) -> 1968109.6 | J18: =I18*(1+J19) -> 2568383.1 | K18: =J18*(1+K19) -> 3351739.9 | L18: =K18*(1+L19) -> 4374020.6 | M18: =L18*(1+M19) -> 5708096.9 | N18: =M18*(1+N19) -> 7449066.5 | O18: =N18*(1+O19) -> 9721031.7 | ... AB18: =AA18*(1+AB19) -> 3.2402493e+08
B19: Growth Rate | E19: - | F19: =F18/E18-1 -> 0.27322404 | G19: =G18/F18-1 -> 0.31025525 | H19: 0.3 | I19: 0.305 | J19: 0.305 | K19: 0.305 | L19: 0.305 | M19: 0.305 | N19: 0.305 | O19: 0.305 | P19: 0.305 | Q19: 0.31 | R19: 0.31 | S19: 0.31 | T19: 0.31 | U19: 0.31 | V19: 0.31 | W19: 0.31 | X19: 0.31 | Y19: 0.31 | Z19: 0.31 | AA19: 0.31 | AB19: 0.31
B20: Market Size (Statista) | E20: 695400 | F20: 885400 | G20: 1160100 | H20: =G20*(1+H21) -> 1498849.2 | I20: =H20*(1+I21) -> 1936513.2 | J20: =I20*(1+J21) -> 2501975 | K20: =J20*(1+K21) -> 3232551.7 | L20: =K20*(1+L21) -> 4266968.3 | M20: =L20*(1+M21) -> 5632398.1 | N20: =M20*(1+N21) -> 7434765.5 | O20: =N20*(1+O21) -> 9813890.5 | ... AB20: =AA20*(1+AB21) -> 4.0885923e+08
B21: Growth Rate | E21: - | F21: =F20/E20-1 -> 0.27322404 | G21: =G20/F20-1 -> 0.31025525 | H21: 0.292 | I21: 0.292 | J21: 0.292 | K21: 0.292 | L21: 0.32 | M21: 0.32 | N21: 0.32 | O21: 0.32 | P21: 0.32 | Q21: 0.32 | R21: 0.32 | S21: 0.32 | T21: 0.33 | U21: 0.33 | V21: 0.34 | W21: 0.34 | X21: 0.34 | Y21: 0.34 | Z21: 0.34 | AA21: 0.34 | AB21: 0.34
B22: Average | E22: =(E18+E20)/2 -> 695400 | F22: =(F18+F20)/2 -> 885400 | G22: =(G18+G20)/2 -> 1160100 | H22: =(H18+H20)/2 -> 1503489.6 | I22: =(I18+I20)/2 -> 1952311.4 | J22: =(J18+J20)/2 -> 2535179.1 | K22: =(K18+K20)/2 -> 3292145.8 | L22: =(L18+L20)/2 -> 4320494.4 | ... AB22: =(AB18+AB20)/2 -> 3.6644208e+08
B23: Average (%) | E23: - | F23: =(F19+F21)/2 -> 0.27322404 | G23: =(G19+G21)/2 -> 0.31025525 | H23: =(H19+H21)/2 -> 0.296 | I23: =(I19+I21)/2 -> 0.2985 | J23: =(J19+J21)/2 -> 0.2985 | K23: =(K19+K21)/2 -> 0.2985 | L23: =(L19+L21)/2 -> 0.3125 | M23: =(M19+M21)/2 -> 0.3125 | ... AB23: =(AB19+AB21)/2 -> 0.325
B24: Market Share | E24: =E28/E22 -> 1.0314927e-05 | F24: =F28/F22 -> 9.8915744e-06 | G24: =G28/G22 -> 7.6088268e-06 | H24: =H28/H22 -> 9.3936134e-06 | I24: =I28/I22 -> 1.1574547e-05 | J24: =J28/J22 -> 1.4261475e-05 | K24: =K28/K22 -> 1.7571709e-05 | L24: =L28/L22 -> 2.1422966e-05 | ... AB24: =AB28/AB22 -> 2.9638417e-05
B25: In millions of USD
A26: x | B26: Income Statement | E26: 2022 | F26: =+E26+1 -> 2023 | G26: =+F26+1 -> 2024 | H26: =+G26+1 -> 2025 | I26: =+H26+1 -> 2026 | J26: =+I26+1 -> 2027 | K26: =+J26+1 -> 2028 | L26: =+K26+1 -> 2029 | M26: =+L26+1 -> 2030 | ... Q26: =+P26+1 -> 2034 | R26: 2035E | S26: 2036E | T26: 2037E | U26: 2038E | V26: 2039E | W26: 2040E | X26: 2041E | Y26: 2042E | Z26: 2043E | AA26: 2044E | AB26: 2045E
B28: Revenue (Sales) | D28: =+_xlfn.XLOOKUP($B28,Inputs!$B:$B,Inputs!N:N) -> 6.279 | E28: =+_xlfn.XLOOKUP($B28,Inputs!$B:$B,Inputs!O:O) -> 7.173 | F28: =+_xlfn.XLOOKUP($B28,Inputs!$B:$B,Inputs!P:P) -> 8.758 | G28: =+_xlfn.XLOOKUP($B28,Inputs!$B:$B,Inputs!Q:Q) -> 8.827 | H28: =G28*(1+H29) -> 14.1232 | I28: =H28*(1+I29) -> 22.59712 | J28: =I28*(1+J29) -> 36.155392 | K28: =J28*(1+K29) -> 57.848627 | L28: =K28*(1+L29) -> 92.557804 | M28: =L28*(1+M29) -> 138.83671 | N28: =M28*(1+N29) -> 208.25506 | O28: =N28*(1+O29) -> 312.38259 | ... AB28: =AA28*(1+AB29) -> 10860.763
B29: % of growth | E29: =IFERROR((E28-D28)/D28,"") -> 0.14237936 | F29: =IFERROR((F28-E28)/E28,"") -> 0.22096752 | G29: =IFERROR((G28-F28)/F28,"") -> 0.0078785111 | H29: 0.6 | I29: 0.6 | J29: 0.6 | K29: 0.6 | L29: 0.6 | M29: 0.5 | N29: 0.5 | O29: 0.5 | P29: 0.4 | Q29: 0.4 | R29: 0.4 | S29: 0.4 | T29: 0.3 | U29: 0.3 | V29: 0.3 | W29: 0.3 | X29: 0.3 | Y29: 0.3 | Z29: 0.25 | AA29: 0.25 | AB29: 0.2 | AC29: isso ignora todas as operating assumptions
B31: COGS (Cost of Goods Sold) | E31: =+_xlfn.XLOOKUP($B31,Inputs!$B:$B,Inputs!O:O) -> 2.923 | F31: =+_xlfn.XLOOKUP($B31,Inputs!$B:$B,Inputs!P:P) -> 4.136 | G31: =+_xlfn.XLOOKUP($B31,Inputs!$B:$B,Inputs!Q:Q) -> 3.264 | H31: =H32*H$28 -> 5.64928 | I31: =I32*I$28 -> 9.038848 | J31: =J32*J$28 -> 14.462157 | K31: =K32*K$28 -> 23.139451 | L31: =L32*L$28 -> 37.023121 | M31: =M32*M$28 -> 55.534682 | N31: =N32*N$28 -> 83.302023 | O31: =O32*O$28 -> 124.95303 | ... AB31: =AB32*AB$28 -> 4344.3053
B32: % of revenue | E32: =IFERROR(E31/E$28,"") -> 0.40750035 | F32: =IFERROR(F31/F$28,"") -> 0.47225394 | G32: =IFERROR(G31/G$28,"") -> 0.36977456 | H32: 0.4 | I32: 0.4 | J32: 0.4 | K32: 0.4 | L32: 0.4 | M32: 0.4 | N32: 0.4 | O32: 0.4 | P32: 0.4 | Q32: 0.4 | R32: 0.4 | S32: 0.4 | T32: 0.4 | U32: 0.4 | V32: 0.4 | W32: 0.4 | X32: 0.4 | Y32: 0.4 | Z32: 0.4 | AA32: 0.4 | AB32: 0.4 | AC32: isso é uma indústria de cogs alto? | AF32: é | AG32: a longo prazo? | AH32: hmmm acho que depois deve baixar, vou ajustar
B34: Gross Profit | E34: =+_xlfn.XLOOKUP($B34,Inputs!$B:$B,Inputs!O:O) -> 4.25 | F34: =+_xlfn.XLOOKUP($B34,Inputs!$B:$B,Inputs!P:P) -> 4.622 | G34: =+_xlfn.XLOOKUP($B34,Inputs!$B:$B,Inputs!Q:Q) -> 5.563 | H34: =+H28-H31 -> 8.47392 | I34: =+I28-I31 -> 13.558272 | J34: =+J28-J31 -> 21.693235 | K34: =+K28-K31 -> 34.709176 | L34: =+L28-L31 -> 55.534682 | M34: =+M28-M31 -> 83.302023 | N34: =+N28-N31 -> 124.95303 | O34: =+O28-O31 -> 187.42955 | ... AB34: =+AB28-AB31 -> 6516.4579
B35: Gross Profit Margin | E35: =IFERROR(E34/E$28,"") -> 0.59249965 | F35: =IFERROR(F34/F$28,"") -> 0.52774606 | G35: =IFERROR(G34/G$28,"") -> 0.63022544 | H35: =IFERROR(H34/H$28,"") -> 0.6 | I35: =IFERROR(I34/I$28,"") -> 0.6 | J35: =IFERROR(J34/J$28,"") -> 0.6 | K35: =IFERROR(K34/K$28,"") -> 0.6 | L35: =IFERROR(L34/L$28,"") -> 0.6 | ... AB35: =IFERROR(AB34/AB$28,"") -> 0.6
B37: SG&A (Selling, General & Administrative) | E37: =+_xlfn.XLOOKUP($B37,Inputs!$B:$B,Inputs!O:O) -> 31.607 | F37: =+_xlfn.XLOOKUP($B37,Inputs!$B:$B,Inputs!P:P) -> 47.29 | G37: =+_xlfn.XLOOKUP($B37,Inputs!$B:$B,Inputs!Q:Q) -> 47.486 | H37: =H38*H28 -> 42.3696 | I37: =I38*I28 -> 45.19424 | J37: =J38*J28 -> 43.38647 | K37: =K38*K28 -> 46.278902 | L37: =L38*L28 -> 46.278902 | M37: =M38*M28 -> 41.651012 | N37: =N38*N28 -> 41.651012 | O37: =O38*O28 -> 46.857388 | ... AB37: =AB38*AB28 -> 217.21526 | AC37: faz mais sentido growing with a % of revenue growth
B38: SG&A Margin | E38: =IFERROR(E37/E$28,"") -> 4.4063851 | F38: =IFERROR(F37/F$28,"") -> 5.3996346 | G38: =IFERROR(G37/G$28,"") -> 5.3796307 | H38: 3 | I38: 2 | J38: 1.2 | K38: 0.8 | L38: 0.5 | M38: 0.3 | N38: 0.2 | O38: 0.15 | P38: 0.1 | Q38: 0.1 | R38: 0.08 | S38: 0.07 | T38: 0.06 | U38: 0.05 | V38: 0.05 | W38: 0.04 | X38: 0.04 | Y38: 0.03 | Z38: 0.02 | AA38: 0.02 | AB38: 0.02
B40: R&D (Research & Development) | E40: =+_xlfn.XLOOKUP($B40,Inputs!$B:$B,Inputs!O:O) -> 32.101 | F40: =+_xlfn.XLOOKUP($B40,Inputs!$B:$B,Inputs!P:P) -> 37.878 | G40: =+_xlfn.XLOOKUP($B40,Inputs!$B:$B,Inputs!Q:Q) -> 35.3 | H40: =G40*(1+H41) -> 52.95 | I40: =H40*(1+I41) -> 79.425 | J40: =I40*(1+J41) -> 119.1375 | K40: =J40*(1+K41) -> 166.7925 | L40: =K40*(1+L41) -> 216.83025 | M40: =L40*(1+M41) -> 281.87932 | N40: =M40*(1+N41) -> 310.06726 | O40: =N40*(1+O41) -> 328.67129 | ... AB40: =AA40*(1+AB41) -> 496.81407 | AC40: faz mais sentido growing with a % of revenue growth
B41: Growth % | E41: =IFERROR(E40/E28,"") -> 4.4752544 | F41: =IFERROR(F40/F28,"") -> 4.32496 | G41: =IFERROR(G40/G28,"") -> 3.9990937 | H41: 0.5 | I41: 0.5 | J41: 0.5 | K41: 0.4 | L41: 0.3 | M41: 0.3 | N41: 0.1 | O41: 0.06 | P41: 0.05 | Q41: 0.04 | R41: 0.03 | S41: 0.03 | T41: 0.03 | U41: 0.03 | V41: 0.03 | W41: 0.03 | X41: 0.03 | Y41: 0.03 | Z41: 0.03 | AA41: 0.03 | AB41: 0.03
B43: Other Operating (Income) Expenses | E43: =+_xlfn.XLOOKUP($B43,Inputs!$B:$B,Inputs!O:O) -> 0 | F43: =+_xlfn.XLOOKUP($B43,Inputs!$B:$B,Inputs!P:P) -> -3.278 | G43: =+_xlfn.XLOOKUP($B43,Inputs!$B:$B,Inputs!Q:Q) -> -4.437 | H43: =IFERROR(AVERAGE(E43:G43)*(1+H29),"") -> -4.1146667 | I43: =IFERROR(AVERAGE(F43:H43)*(1+I29),"") -> -6.3091556 | J43: =IFERROR(AVERAGE(G43:I43)*(1+J29),"") -> -7.9257719 | K43: =IFERROR(AVERAGE(H43:J43)*(1+K29),"") -> -9.7864502 | L43: =IFERROR(AVERAGE(I43:K43)*(1+L29),"") -> -12.811401 | M43: =IFERROR(AVERAGE(J43:L43)*(1+M29),"") -> -15.261812 | N43: =IFERROR(AVERAGE(K43:M43)*(1+N29),"") -> -18.929832 | O43: =IFERROR(AVERAGE(L43:N43)*(1+O29),"") -> -23.501522 | ... AB43: =IFERROR(AVERAGE(Y43:AA43)*(1+AB29),"") -> -133.52507 | AC43: fica meio alto a longo prazo
B45: EBITDA | E45: =+_xlfn.XLOOKUP($B45,Inputs!$B:$B,Inputs!O:O) -> -57.125 | F45: =+_xlfn.XLOOKUP($B45,Inputs!$B:$B,Inputs!P:P) -> -75.423 | G45: =+_xlfn.XLOOKUP($B45,Inputs!$B:$B,Inputs!Q:Q) -> -69.294 | H45: =IFERROR(H34-H37-H40-H43,"") -> -82.731013 | I45: =IFERROR(I34-I37-I40-I43,"") -> -104.75181 | J45: =IFERROR(J34-J37-J40-J43,"") -> -132.90496 | K45: =IFERROR(K34-K37-K40-K43,"") -> -168.57578 | L45: =IFERROR(L34-L37-L40-L43,"") -> -194.76307 | M45: =IFERROR(M34-M37-M40-M43,"") -> -224.9665 | N45: =IFERROR(N34-N37-N40-N43,"") -> -207.8354 | O45: =IFERROR(O34-O37-O40-O43,"") -> -164.59761 | ... AB45: =IFERROR(AB34-AB37-AB40-AB43,"") -> 5935.9537
B46: EBITDA Margin | E46: =IFERROR(E45/E$28,"") -> -7.9638924 | F46: =IFERROR(F45/F$28,"") -> -8.6118977 | G46: =IFERROR(G45/G$28,"") -> -7.8502322 | H46: =IFERROR(H45/H$28,"") -> -5.8578094 | I46: =IFERROR(I45/I$28,"") -> -4.6356267 | J46: =IFERROR(J45/J$28,"") -> -3.6759376 | K46: =IFERROR(K45/K$28,"") -> -2.9140843 | L46: =IFERROR(L45/L$28,"") -> -2.1042317 | ... AB46: =IFERROR(AB45/AB$28,"") -> 0.54655033
B48: D&A (Depreciation & Amortization) | E48: =+_xlfn.XLOOKUP($B48,Inputs!$B:$B,Inputs!O:O) -> 2.333 | F48: =+_xlfn.XLOOKUP($B48,Inputs!$B:$B,Inputs!P:P) -> 1.845 | G48: =+_xlfn.XLOOKUP($B48,Inputs!$B:$B,Inputs!Q:Q) -> 1.932 | H48: =+IFERROR(H51+H54,"") -> 0 | I48: =+IFERROR(I51+I54,"") -> 0 | J48: =+IFERROR(J51+J54,"") -> 0 | K48: =+IFERROR(K51+K54,"") -> 0 | L48: =+IFERROR(L51+L54,"") -> 0 | M48: =+IFERROR(M51+M54,"") -> 0 | N48: =+IFERROR(N51+N54,"") -> 0 | O48: =+IFERROR(O51+O54,"") -> 0 | ... AB48: =+IFERROR(AB51+AB54,"") -> 0 | AC48: pode-se fazer como % capex, até estabilizar num ritmo de crecimento moderado (80% do capex)
B49: % capex | E49: =E48/E132 -> -5.5153664 | F49: =F48/F132 -> -3.1646655 | G49: =G48/G132 -> -0.80668058 | H49: =IFERROR(H48/(G97+G103),"") -> 0 | I49: =IFERROR(I48/(H97+H103),"") -> 0 | J49: =IFERROR(J48/(I97+I103),"") -> 0 | K49: =IFERROR(K48/(J97+J103),"") -> 0 | L49: =IFERROR(L48/(K97+K103),"") -> 0 | M49: =IFERROR(M48/(L97+L103),"") -> 0 | N49: =IFERROR(N48/(M97+M103),"") -> 0 | O49: =IFERROR(O48/(N97+N103),"") -> 0 | ... AB49: =IFERROR(AB48/(AA97+AA103),"") -> 0 | AC49: o problema é que nos primeiros anos talvez não seja um bom parâmetro, aí mais vale usar alguma outra referência para o crescimento | AK49: sim, problema que não sei se outra referência seria boa porque não há como comparar com os dados históricos (fico um bocado à nora)
B51: Depreciation Expense | E51: =+_xlfn.XLOOKUP($B51,Inputs!$B:$B,Inputs!O:O) -> 2.333 | F51: =+_xlfn.XLOOKUP($B51,Inputs!$B:$B,Inputs!P:P) -> 1.845 | G51: =+_xlfn.XLOOKUP($B51,Inputs!$B:$B,Inputs!Q:Q) -> 1.932 | H51: =IFERROR(-H52*H132,"") -> 0 | I51: =IFERROR(-I52*I132,"") -> 0 | J51: =IFERROR(-J52*J132,"") -> 0 | K51: =IFERROR(-K52*K132,"") -> 0 | L51: =IFERROR(-L52*L132,"") -> 0 | M51: =IFERROR(-M52*M132,"") -> 0 | N51: =IFERROR(-N52*N132,"") -> 0 | O51: =IFERROR(-O52*O132,"") -> 0 | ... AB51: =IFERROR(-AB52*AB132,"") -> 0
B52: % Capex | E52: =IFERROR(-E51/AVERAGE(Inputs!O76,Inputs!N76),"") -> 2.1238052 | F52: =IFERROR(-F51/AVERAGE(Inputs!P76,Inputs!O76),"") -> 3.667992 | G52: =IFERROR(-G51/AVERAGE(Inputs!Q76,Inputs!P76),"") -> 1.2975151 | H52: 0.01 | I52: 1 | J52: 1 | K52: 1 | L52: 0.8 | M52: 0.7 | N52: 0.6 | O52: 0.5 | P52: 0.4 | Q52: 0.3 | R52: 0.3 | S52: 0.3 | T52: 0.3 | U52: 0.3 | V52: 0.3 | W52: 0.3 | X52: 0.3 | Y52: 0.3 | Z52: 0.3 | AA52: 0.3 | AB52: 0.3
B54: Amortization Expense | E54: =+_xlfn.XLOOKUP($B54,Inputs!$B:$B,Inputs!O:O) -> 0 | F54: =+_xlfn.XLOOKUP($B54,Inputs!$B:$B,Inputs!P:P) -> 0 | G54: =+_xlfn.XLOOKUP($B54,Inputs!$B:$B,Inputs!Q:Q) -> 0 | H54: =+H55*G103 -> 0 | I54: =+I55*H103 -> 0 | J54: =+J55*I103 -> 0 | K54: =+K55*J103 -> 0 | L54: =+L55*K103 -> 0 | M54: =+M55*L103 -> 0 | N54: =+N55*M103 -> 0 | O54: =+O55*N103 -> 0 | ... AB54: =+AB55*AA103 -> 0
B55: % of Intangibles excl. Goodwill | E55: =IFERROR(E54/AVERAGE(Inputs!N45:O45),"") -> 0 | F55: =IFERROR(F54/AVERAGE(Inputs!O45:P45),"") -> 0 | G55: =IFERROR(G54/AVERAGE(Inputs!P45:Q45),"") -> 0
B57: Operating Income (EBIT) | E57: =+_xlfn.XLOOKUP($B57,Inputs!$B:$B,Inputs!O:O) -> 8 | F57: =+_xlfn.XLOOKUP($B57,Inputs!$B:$B,Inputs!P:P) -> -77.268 | G57: =+_xlfn.XLOOKUP($B57,Inputs!$B:$B,Inputs!Q:Q) -> -72.786 | H57: =+IFERROR(H45-H48,"") -> -82.731013 | I57: =+IFERROR(I45-I48,"") -> -104.75181 | J57: =+IFERROR(J45-J48,"") -> -132.90496 | K57: =+IFERROR(K45-K48,"") -> -168.57578 | L57: =+IFERROR(L45-L48,"") -> -194.76307 | M57: =+IFERROR(M45-M48,"") -> -224.9665 | N57: =+IFERROR(N45-N48,"") -> -207.8354 | O57: =+IFERROR(O45-O48,"") -> -164.59761 | ... AB57: =+IFERROR(AB45-AB48,"") -> 5935.9537
B58: Operating Margin | E58: =IFERROR(E57/E$28,"") -> 1.1152935 | F58: =IFERROR(F57/F$28,"") -> -8.8225622 | G58: =IFERROR(G57/G$28,"") -> -8.2458366 | H58: =IFERROR(H57/H28,"") -> -5.8578094 | I58: =IFERROR(I57/I28,"") -> -4.6356267 | J58: =IFERROR(J57/J28,"") -> -3.6759376 | K58: =IFERROR(K57/K28,"") -> -2.9140843 | L58: =IFERROR(L57/L28,"") -> -2.1042317 | M58: =IFERROR(M57/M28,"") -> -1.6203676 | N58: =IFERROR(N57/N28,"") -> -0.9979849 | O58: =IFERROR(O57/O28,"") -> -0.52691031 | ... AB58: =IFERROR(AB57/AB28,"") -> 0.54655033
B60: Net Interest Expense (Income) | E60: =+_xlfn.XLOOKUP($B60,Inputs!$B:$B,Inputs!O:O) -> 2.335 | F60: =+_xlfn.XLOOKUP($B60,Inputs!$B:$B,Inputs!P:P) -> 0.037 | G60: =+_xlfn.XLOOKUP($B60,Inputs!$B:$B,Inputs!Q:Q) -> 3.897 | H60: =-H63-H66 -> -4.2867 | I60: =-I63-I66 -> -4.71537 | J60: =-J63-J66 -> -5.186907 | K60: =-K63-K66 -> -5.7055977 | L60: =-L63-L66 -> -6.2761575 | M60: =-M63-M66 -> -6.9037732 | N60: =-N63-N66 -> -7.5941505 | O60: =-O63-O66 -> -8.3535656 | ... AB60: =-AB63-AB66 -> -28.838774
B61: % of Net Debt | E61: =IFERROR(E60/AVERAGE(Inputs!N116:O116),"") -> 1.4259542 | F61: =IFERROR(F60/AVERAGE(Inputs!O116:P116),"") -> -0.0027211885 | G61: =IFERROR(G60/AVERAGE(Inputs!P116:Q116),"") -> -0.045611489 | H61: =IFERROR(H60/AVERAGE(G114+G116,H114+H116),"") -> -0.037810225 | I61: =IFERROR(I60/AVERAGE(H114+H116,I114+I116),"") -> -0.028189917 | J61: =IFERROR(J60/AVERAGE(I114+I116,J114+J116),"") -> -0.022051555 | K61: =IFERROR(K60/AVERAGE(J114+J116,K114+K116),"") -> -0.017021125 | L61: =IFERROR(L60/AVERAGE(K114+K116,L114+L116),"") -> -0.013547474 | M61: =IFERROR(M60/AVERAGE(L114+L116,M114+M116),"") -> -0.011121753 | N61: =IFERROR(N60/AVERAGE(M114+M116,N114+N116),"") -> -0.0092798214 | O61: =IFERROR(O60/AVERAGE(N114+N116,O114+O116),"") -> -0.0080669724 | ... AB61: =IFERROR(AB60/AVERAGE(AA114+AA116,AB114+AB116),"") -> -0.0045789362
B63: Interest Expense | E63: =+_xlfn.XLOOKUP($B63,Inputs!$B:$B,Inputs!O:O) -> 2.335 | F63: =+_xlfn.XLOOKUP($B63,Inputs!$B:$B,Inputs!P:P) -> 0.037 | G63: =+_xlfn.XLOOKUP($B63,Inputs!$B:$B,Inputs!Q:Q) -> 3.897 | H63: =G63*(1+H64) -> 4.2867 | I63: =H63*(1+I64) -> 4.71537 | J63: =I63*(1+J64) -> 5.186907 | K63: =J63*(1+K64) -> 5.7055977 | L63: =K63*(1+L64) -> 6.2761575 | M63: =L63*(1+M64) -> 6.9037732 | N63: =M63*(1+N64) -> 7.5941505 | O63: =N63*(1+O64) -> 8.3535656 | ... AB63: =AA63*(1+AB64) -> 28.838774
B64: % of Debt | E64: =+IFERROR(E63/AVERAGE(Inputs!N113:O113),"") -> 0.23558493 | F64: =+IFERROR(F63/AVERAGE(Inputs!O113:P113),"") -> 0.0034941921 | G64: =+IFERROR(G63/AVERAGE(Inputs!P113:Q113),"") -> 0.16100312 | H64: 0.1 | I64: 0.1 | J64: 0.1 | K64: 0.1 | L64: 0.1 | M64: 0.1 | N64: 0.1 | O64: 0.1 | P64: 0.1 | Q64: 0.1 | R64: 0.1 | S64: 0.1 | T64: 0.1 | U64: 0.1 | V64: 0.1 | W64: 0.1 | X64: 0.1 | Y64: 0.1 | Z64: 0.1 | AA64: 0.1 | AB64: 0.1
B66: Interest Income | E66: =+_xlfn.XLOOKUP($B66,Inputs!$B:$B,Inputs!O:O) -> 0 | F66: =+_xlfn.XLOOKUP($B66,Inputs!$B:$B,Inputs!P:P) -> 0 | G66: =+_xlfn.XLOOKUP($B66,Inputs!$B:$B,Inputs!Q:Q) -> 0
B67: % Cash & Cash Eq. & ST Investments | E67: =IFERROR(E66/+AVERAGE(Inputs!N32:O32),"") -> 0 | F67: =IFERROR(F66/+AVERAGE(Inputs!O32:P32),"") -> 0 | G67: =IFERROR(G66/+AVERAGE(Inputs!P32:Q32),"") -> 0
B69: FX (Gain) Loss | E69: =+_xlfn.XLOOKUP($B69,Inputs!$B:$B,Inputs!O:O) -> 0 | F69: =+_xlfn.XLOOKUP($B69,Inputs!$B:$B,Inputs!P:P) -> 0 | G69: =+_xlfn.XLOOKUP($B69,Inputs!$B:$B,Inputs!Q:Q) -> 0 | H69: =+H70*H$18 -> 0 | I69: =+I70*I$18 -> 0 | J69: =+J70*J$18 -> 0 | K69: =+K70*K$18 -> 0 | L69: =+L70*L$18 -> 0 | M69: =+M70*M$18 -> 0 | N69: =+N70*N$18 -> 0 | O69: =+O70*O$18 -> 0 | ... AB69: =+AB70*AB$18 -> 0
B70: % of revenue
B72: Other Non-Operating (Income) Expenses | E72: =+_xlfn.XLOOKUP($B72,Inputs!$B:$B,Inputs!O:O) -> -8.091 | F72: =+_xlfn.XLOOKUP($B72,Inputs!$B:$B,Inputs!P:P) -> 2.132 | G72: =+_xlfn.XLOOKUP($B72,Inputs!$B:$B,Inputs!Q:Q) -> 64.254 | H72: =IFERROR(AVERAGE(E72:G72)*(1+H29),"") -> 31.090667 | I72: =IFERROR(AVERAGE(F72:H72)*(1+I29),"") -> 51.987556 | J72: =IFERROR(AVERAGE(G72:I72)*(1+J29),"") -> 78.577185 | K72: =IFERROR(AVERAGE(H72:J72)*(1+K29),"") -> 86.216217 | L72: =IFERROR(AVERAGE(I72:K72)*(1+L29),"") -> 115.61651 | M72: =IFERROR(AVERAGE(J72:L72)*(1+M29),"") -> 140.20496 | N72: =IFERROR(AVERAGE(K72:M72)*(1+N29),"") -> 171.01884 | O72: =IFERROR(AVERAGE(L72:N72)*(1+O29),"") -> 213.42016 | ... AB72: =IFERROR(AVERAGE(Y72:AA72)*(1+AB29),"") -> 1212.5384
B74: Pre-Tax Income (EBT) | E74: =+_xlfn.XLOOKUP($B74,Inputs!$B:$B,Inputs!O:O) -> -53.702 | F74: =+_xlfn.XLOOKUP($B74,Inputs!$B:$B,Inputs!P:P) -> -82.715 | G74: =+_xlfn.XLOOKUP($B74,Inputs!$B:$B,Inputs!Q:Q) -> -143.879 | H74: =IFERROR(+H57-H60-H69-H72,"") -> -109.53498 | I74: =IFERROR(+I57-I60-I69-I72,"") -> -152.024 | J74: =IFERROR(+J57-J60-J69-J72,"") -> -206.29524 | K74: =IFERROR(+K57-K60-K69-K72,"") -> -249.08639 | L74: =IFERROR(+L57-L60-L69-L72,"") -> -304.10342 | M74: =IFERROR(+M57-M60-M69-M72,"") -> -358.26769 | N74: =IFERROR(+N57-N60-N69-N72,"") -> -371.26009 | O74: =IFERROR(+O57-O60-O69-O72,"") -> -369.6642 | ... AB74: =IFERROR(+AB57-AB60-AB69-AB72,"") -> 4752.2541
B76: Tax Expense (Benefits) | E76: =+_xlfn.XLOOKUP($B76,Inputs!$B:$B,Inputs!O:O) -> 0 | F76: =+_xlfn.XLOOKUP($B76,Inputs!$B:$B,Inputs!P:P) -> 0 | G76: =+_xlfn.XLOOKUP($B76,Inputs!$B:$B,Inputs!Q:Q) -> 0 | H76: =IFERROR(H77*H$57,"") -> 0 | I76: =IFERROR(I77*I$57,"") -> 0 | J76: =IFERROR(J77*J$57,"") -> 0 | K76: =IFERROR(K77*K$57,"") -> 0 | L76: =IFERROR(L77*L$57,"") -> 0 | M76: =IFERROR(M77*M$57,"") -> 0 | N76: =IFERROR(N77*N$57,"") -> 0 | O76: =IFERROR(O77*O$57,"") -> 0 | ... AB76: =IFERROR(AB77*AB$57,"") -> 0
B77: % of EBT | E77: 0 | F77: 0 | G77: 0 | H77: =IFERROR(AVERAGE(E77:G77),"") -> 0 | I77: =IFERROR(AVERAGE(F77:H77),"") -> 0 | J77: =IFERROR(AVERAGE(G77:I77),"") -> 0 | K77: =IFERROR(AVERAGE(H77:J77),"") -> 0 | L77: =IFERROR(AVERAGE(I77:K77),"") -> 0 | M77: =IFERROR(AVERAGE(J77:L77),"") -> 0 | N77: =IFERROR(AVERAGE(K77:M77),"") -> 0 | O77: =IFERROR(AVERAGE(L77:N77),"") -> 0 | ... AB77: =IFERROR(AVERAGE(Y77:AA77),"") -> 0
B79: Net Income | E79: =+_xlfn.XLOOKUP($B79,Inputs!$B:$B,Inputs!O:O) -> -53.702 | F79: =+_xlfn.XLOOKUP($B79,Inputs!$B:$B,Inputs!P:P) -> -82.715 | G79: =+_xlfn.XLOOKUP($B79,Inputs!$B:$B,Inputs!Q:Q) -> -143.879 | H79: =IFERROR(+H74-H76,"") -> -109.53498 | I79: =IFERROR(+I74-I76,"") -> -152.024 | J79: =IFERROR(+J74-J76,"") -> -206.29524 | K79: =IFERROR(+K74-K76,"") -> -249.08639 | L79: =IFERROR(+L74-L76,"") -> -304.10342 | M79: =IFERROR(+M74-M76,"") -> -358.26769 | N79: =IFERROR(+N74-N76,"") -> -371.26009 | O79: =IFERROR(+O74-O76,"") -> -369.6642 | ... AB79: =IFERROR(+AB74-AB76,"") -> 4752.2541
B80: Net Income Margin | E80: =IFERROR(E79/E$28,"") -> -7.4866862 | F80: =IFERROR(F79/F$28,"") -> -9.4445079 | G80: =IFERROR(G79/G$28,"") -> -16.299875 | H80: =IFERROR(H79/H$28,"") -> -7.7556772 | I80: =IFERROR(I79/I$28,"") -> -6.7275829 | J80: =IFERROR(J79/J$28,"") -> -5.7057946 | K80: =IFERROR(K79/K$28,"") -> -4.3058307 | L80: =IFERROR(L79/L$28,"") -> -3.2855514 | ... AB80: =IFERROR(AB79/AB$28,"") -> 0.4375617
A82: x | B82: Balance Sheet | E82: =E26 -> 2022 | F82: =F26 -> 2023 | G82: =G26 -> 2024 | H82: =H26 -> 2025 | I82: =I26 -> 2026 | J82: =J26 -> 2027 | K82: =K26 -> 2028 | L82: =L26 -> 2029 | ... Q82: =Q26 -> 2034 | R82: 2035E | S82: 2036E | T82: 2037E | U82: 2038E | V82: 2039E | W82: 2040E | X82: 2041E | Y82: 2042E | Z82: 2043E | AA82: 2044E | AB82: 2045E
B84: Assets
B86: Cash & Cash Equivalents & ST Investments | E86: =+_xlfn.XLOOKUP($B86,Inputs!$B:$B,Inputs!O:O) -> 7.065 | F86: =+_xlfn.XLOOKUP($B86,Inputs!$B:$B,Inputs!P:P) -> 41.307 | G86: =+_xlfn.XLOOKUP($B86,Inputs!$B:$B,Inputs!Q:Q) -> 177.98 | H86: =IFERROR(G86+H164,"") -> 190.31468 | I86: =IFERROR(H86+I164,"") -> 131.11335 | J86: =IFERROR(I86+J164,"") -> 137.39 | K86: =IFERROR(J86+K164,"") -> 67.245073 | L86: =IFERROR(K86+L164,"") -> 57.128641 | M86: =IFERROR(L86+M164,"") -> -18.118465 | N86: =IFERROR(M86+N164,"") -> 14.280129 | O86: =IFERROR(N86+O164,"") -> 11.771367 | ... AB86: =IFERROR(AA86+AB164,"") -> 23806.286
B88: Accounts Receivable | E88: =+_xlfn.XLOOKUP($B88,Inputs!$B:$B,Inputs!O:O) -> 0.757 | F88: =+_xlfn.XLOOKUP($B88,Inputs!$B:$B,Inputs!P:P) -> 1.652 | G88: =+_xlfn.XLOOKUP($B88,Inputs!$B:$B,Inputs!Q:Q) -> 1.42 | H88: =IFERROR(H89*H28/365,"") -> 2.1442453 | I88: =IFERROR(I89*I28/365,"") -> 3.7794637 | J88: =IFERROR(J89*J28/365,"") -> 5.789555 | K88: =IFERROR(K89*K28/365,"") -> 9.2405147 | L88: =IFERROR(L89*L28/365,"") -> 15.028923 | M88: =IFERROR(M89*M28/365,"") -> 22.317504 | N88: =IFERROR(N89*N28/365,"") -> 33.519061 | O88: =IFERROR(O89*O28/365,"") -> 50.405196 | ... AB88: =IFERROR(AB89*AB28/365,"") -> 1749.888
B89: DSO | E89: =IFERROR(E88/E28*365,"") -> 38.520145 | F89: =IFERROR(F88/F28*365,"") -> 68.849052 | G89: =IFERROR(G88/G28*366,"") -> 58.878441 | H89: =IFERROR(AVERAGE(E89:G89),"") -> 55.415879 | I89: =IFERROR(AVERAGE(F89:H89),"") -> 61.047791 | J89: =IFERROR(AVERAGE(G89:I89),"") -> 58.447371 | K89: =IFERROR(AVERAGE(H89:J89),"") -> 58.30368 | L89: =IFERROR(AVERAGE(I89:K89),"") -> 59.266281 | M89: =IFERROR(AVERAGE(J89:L89),"") -> 58.672444 | N89: =IFERROR(AVERAGE(K89:M89),"") -> 58.747468 | O89: =IFERROR(AVERAGE(L89:N89),"") -> 58.895398 | ... AB89: =IFERROR(AVERAGE(Y89:AA89),"") -> 58.808863
B91: Inventory | E91: =+_xlfn.XLOOKUP($B91,Inputs!$B:$B,Inputs!O:O) -> 2.196 | F91: =+_xlfn.XLOOKUP($B91,Inputs!$B:$B,Inputs!P:P) -> 2.078 | G91: =+_xlfn.XLOOKUP($B91,Inputs!$B:$B,Inputs!Q:Q) -> 1.686 | H91: =+IFERROR(H92*H31/365,"") -> 3.3335363 | I91: =+IFERROR(I92*I31/365,"") -> 4.8479666 | J91: =+IFERROR(J92*J31/365,"") -> 7.9203138 | K91: =+IFERROR(K92*K31/365,"") -> 12.912487 | L91: =+IFERROR(L92*L31/365,"") -> 20.264418 | M91: =+IFERROR(M92*M31/365,"") -> 30.6002 | N91: =+IFERROR(N92*N31/365,"") -> 45.993398 | O91: =+IFERROR(O92*O31/365,"") -> 68.74432 | ... AB91: =+IFERROR(AB92*AB31/365,"") -> 2393.5347 | AC91: conforme cresce a procura, DIH deve reduzir substancialmente
B92: DIH | E92: =IFERROR(E91/E31*365,"") -> 274.21827 | F92: =IFERROR(F91/F31*365,"") -> 183.3825 | G92: =IFERROR(G91/G31*365,"") -> 188.5386 | H92: =IFERROR(AVERAGE(E92:G92),"") -> 215.37979 | I92: =IFERROR(AVERAGE(F92:H92),"") -> 195.76696 | J92: =IFERROR(AVERAGE(G92:I92),"") -> 199.89512 | K92: =IFERROR(AVERAGE(H92:J92),"") -> 203.68062 | L92: =IFERROR(AVERAGE(I92:K92),"") -> 199.7809 | M92: =IFERROR(AVERAGE(J92:L92),"") -> 201.11888 | N92: =IFERROR(AVERAGE(K92:M92),"") -> 201.5268 | O92: =IFERROR(AVERAGE(L92:N92),"") -> 200.80886 | ... AB92: =IFERROR(AVERAGE(Y92:AA92),"") -> 201.10008
B94: Prepaid expenses and Other Current Assets | E94: =+_xlfn.XLOOKUP($B94,Inputs!$B:$B,Inputs!O:O) -> 3.907 | F94: =+_xlfn.XLOOKUP($B94,Inputs!$B:$B,Inputs!P:P) -> 2.009 | G94: =+_xlfn.XLOOKUP($B94,Inputs!$B:$B,Inputs!Q:Q) -> 3.954 | H94: =IFERROR(AVERAGE(E94:G94)*(1+H29),"") -> 5.264 | I94: =IFERROR(AVERAGE(F94:H94)*(1+I29),"") -> 5.9877333 | J94: =IFERROR(AVERAGE(G94:I94)*(1+J29),"") -> 8.1097244 | K94: =IFERROR(AVERAGE(H94:J94)*(1+K29),"") -> 10.326111 | L94: =IFERROR(AVERAGE(I94:K94)*(1+L29),"") -> 13.025903 | M94: =IFERROR(AVERAGE(J94:L94)*(1+M29),"") -> 15.730869 | N94: =IFERROR(AVERAGE(K94:M94)*(1+N29),"") -> 19.541442 | O94: =IFERROR(AVERAGE(L94:N94)*(1+O29),"") -> 24.149107 | ... AB94: =IFERROR(AVERAGE(Y94:AA94)*(1+AB29),"") -> 137.46449 | AC94: a percentagem é extremamente alta hoje pq a receita é baixa, não deve manter o ratio as % of revenue
B95: % of revenue | E95: =IFERROR(E94/E$28,"") -> 0.54468144 | F95: =IFERROR(F94/F$28,"") -> 0.22939027 | G95: =IFERROR(G94/G$28,"") -> 0.44794381 | H95: =IFERROR(AVERAGE(E95:G95),"") -> 0.40733851 | I95: =IFERROR(AVERAGE(F95:H95),"") -> 0.36155753 | J95: =IFERROR(AVERAGE(G95:I95),"") -> 0.40561328 | K95: =IFERROR(AVERAGE(H95:J95),"") -> 0.39150311 | L95: =IFERROR(AVERAGE(I95:K95),"") -> 0.38622464 | M95: =IFERROR(AVERAGE(J95:L95),"") -> 0.39444701 | N95: =IFERROR(AVERAGE(K95:M95),"") -> 0.39072492 | O95: =IFERROR(AVERAGE(L95:N95),"") -> 0.39046552 | ... AB95: =IFERROR(AVERAGE(Y95:AA95),"") -> 0.39121605
B97: Net PP&E (Property, Plant and Equipment) + ROU Assets | E97: =+E98+E99-E101 -> 20.56 | F97: =+F98+F99-F101 -> 18.997 | G97: =+G98+G99-G101 -> 18.655 | H97: =IFERROR(H98+H99-H101,"") -> 25.680792 | I97: =IFERROR(I98+I99-I101,"") -> 32.281919 | J97: =IFERROR(J98+J99-J101,"") -> 44.639305 | K97: =IFERROR(K98+K99-K101,"") -> 66.45542 | L97: =IFERROR(L98+L99-L101,"") -> 97.64839 | M97: =IFERROR(M98+M99-M101,"") -> 141.12432 | N97: =IFERROR(N98+N99-N101,"") -> 207.02366 | O97: =IFERROR(O98+O99-O101,"") -> 303.54276 | ... AB97: =IFERROR(AB98+AB99-AB101,"") -> 10182.225
B98: Gross PP&E (Property, Plant and Equipment) + ROU Assets | E98: =+_xlfn.XLOOKUP("Gross PP&E (Property, Plant and Equipment)",Inputs!$B:$B,Inputs!O:O) -> 34.538 | F98: =+_xlfn.XLOOKUP("Gross PP&E (Property, Plant and Equipment)",Inputs!$B:$B,Inputs!P:P) -> 34.827 | G98: =+_xlfn.XLOOKUP("Gross PP&E (Property, Plant and Equipment)",Inputs!$B:$B,Inputs!Q:Q) -> 36.401 | H98: =+IFERROR(G98-H132,"") -> 36.401 | I98: =+IFERROR(H98-I132,"") -> 36.401 | J98: =+IFERROR(I98-J132,"") -> 36.401 | K98: =+IFERROR(J98-K132,"") -> 36.401 | L98: =+IFERROR(K98-L132,"") -> 36.401 | M98: =+IFERROR(L98-M132,"") -> 36.401 | N98: =+IFERROR(M98-N132,"") -> 36.401 | O98: =+IFERROR(N98-O132,"") -> 36.401 | ... AB98: =+IFERROR(AA98-AB132,"") -> 36.401
B99: Right-of-Use Assets | E99: =+_xlfn.XLOOKUP("Right-of-Use Assets",Inputs!$B:$B,Inputs!O:O) -> 9.133 | F99: =+_xlfn.XLOOKUP("Right-of-Use Assets",Inputs!$B:$B,Inputs!P:P) -> 8.223 | G99: =+_xlfn.XLOOKUP("Right-of-Use Assets",Inputs!$B:$B,Inputs!Q:Q) -> 7.261 | H99: =IFERROR(H100*H$28,"") -> 14.286792 | I99: =IFERROR(I100*I$28,"") -> 20.887919 | J99: =IFERROR(J100*J$28,"") -> 33.245305 | K99: =IFERROR(K100*K$28,"") -> 55.06142 | L99: =IFERROR(L100*L$28,"") -> 86.25439 | M99: =IFERROR(M100*M$28,"") -> 129.73032 | N99: =IFERROR(N100*N$28,"") -> 195.62966 | O99: =IFERROR(O100*O$28,"") -> 292.14876 | ... AB99: =IFERROR(AB100*AB$28,"") -> 10170.831
B100: % of revenue | E100: =IFERROR(E99/E$28,"") -> 1.2732469 | F100: =IFERROR(F99/F$28,"") -> 0.93891299 | G100: =IFERROR(G99/G$28,"") -> 0.82258978 | H100: =IFERROR(AVERAGE(E100:G100),"") -> 1.0115832 | I100: =IFERROR(AVERAGE(F100:H100),"") -> 0.924362 | J100: =IFERROR(AVERAGE(G100:I100),"") -> 0.91951167 | K100: =IFERROR(AVERAGE(H100:J100),"") -> 0.95181896 | L100: =IFERROR(AVERAGE(I100:K100),"") -> 0.93189754 | M100: =IFERROR(AVERAGE(J100:L100),"") -> 0.93440939 | N100: =IFERROR(AVERAGE(K100:M100),"") -> 0.9393753 | O100: =IFERROR(AVERAGE(L100:N100),"") -> 0.93522741 | ... AB100: =IFERROR(AVERAGE(Y100:AA100),"") -> 0.93647482
B101: Accumulated Depreciation | E101: =+_xlfn.XLOOKUP($B101,Inputs!$B:$B,Inputs!O:O) -> 23.111 | F101: =+_xlfn.XLOOKUP($B101,Inputs!$B:$B,Inputs!P:P) -> 24.053 | G101: =+_xlfn.XLOOKUP($B101,Inputs!$B:$B,Inputs!Q:Q) -> 25.007 | H101: =+IFERROR(G101+H51,"") -> 25.007 | I101: =+IFERROR(H101+I51,"") -> 25.007 | J101: =+IFERROR(I101+J51,"") -> 25.007 | K101: =+IFERROR(J101+K51,"") -> 25.007 | L101: =+IFERROR(K101+L51,"") -> 25.007 | M101: =+IFERROR(L101+M51,"") -> 25.007 | N101: =+IFERROR(M101+N51,"") -> 25.007 | O101: =+IFERROR(N101+O51,"") -> 25.007 | ... AB101: =+IFERROR(AA101+AB51,"") -> 25.007
B103: Intangibles excl. Goodwill | E103: =+_xlfn.XLOOKUP($B103,Inputs!$B:$B,Inputs!O:O) -> 0.244 | F103: =+_xlfn.XLOOKUP($B103,Inputs!$B:$B,Inputs!P:P) -> 0.179 | G103: =+_xlfn.XLOOKUP($B103,Inputs!$B:$B,Inputs!Q:Q) -> 0.49 | H103: =+G103+H104*H40 -> 0.49 | I103: =+H103+I104*I40 -> 0.49 | J103: =+I103+J104*J40 -> 0.49 | K103: =+J103+K104*K40 -> 0.49 | L103: =+K103+L104*L40 -> 0.49 | M103: =+L103+M104*M40 -> 0.49 | N103: =+M103+N104*N40 -> 0.49 | O103: =+N103+O104*O40 -> 0.49 | ... AB103: =+AA103+AB104*AB40 -> 0.49
B104: growing with % of R&D | E104: =IFERROR((E103-Inputs!N45)/E40,"") -> -0.00087224697 | F104: =IFERROR((F103-E103)/F40,"") -> -0.0017160357 | G104: =IFERROR((G103-F103)/G40,"") -> 0.0088101983
B106: Liabilities
B108: Accounts Payable | E108: =+_xlfn.XLOOKUP($B108,Inputs!$B:$B,Inputs!O:O) -> 3.756 | F108: =+_xlfn.XLOOKUP($B108,Inputs!$B:$B,Inputs!P:P) -> 1.465 | G108: =+_xlfn.XLOOKUP($B108,Inputs!$B:$B,Inputs!Q:Q) -> 0.815 | H108: =+IFERROR(H109*H31/365,"") -> 3.5582289 | I108: =+IFERROR(I109*I31/365,"") -> 3.7193051 | J108: =+IFERROR(J109*J31/365,"") -> 6.2269853 | K108: =+IFERROR(K109*K31/365,"") -> 11.353034 | L108: =+IFERROR(L109*L31/365,"") -> 16.446737 | M108: =+IFERROR(M109*M31/365,"") -> 25.276337 | N108: =+IFERROR(N109*N31/365,"") -> 38.596863 | O108: =+IFERROR(O109*O31/365,"") -> 56.758263 | ... AB108: =+IFERROR(AB109*AB31/365,"") -> 1987.1899 | AC108: isso assume que a empresa tem muit power over suppliers for taking that long to pay, hoje eles devem ter acordos que os beneficiam por serem praticamente pre-revenue, mas não deve manter-se assim
B109: DPO | E109: =IFERROR(E108/E$31*365,"") -> 469.01813 | F109: =IFERROR(F108/F$31*365,"") -> 129.28554 | G109: =IFERROR(G108/G$31*366,"") -> 91.387868 | H109: =IFERROR(AVERAGE(E109:G109),"") -> 229.89718 | I109: =IFERROR(AVERAGE(F109:H109),"") -> 150.1902 | J109: =IFERROR(AVERAGE(G109:I109),"") -> 157.15841 | K109: =IFERROR(AVERAGE(H109:J109),"") -> 179.08193 | L109: =IFERROR(AVERAGE(I109:K109),"") -> 162.14351 | M109: =IFERROR(AVERAGE(J109:L109),"") -> 166.12795 | N109: =IFERROR(AVERAGE(K109:M109),"") -> 169.1178 | O109: =IFERROR(AVERAGE(L109:N109),"") -> 165.79642 | ... AB109: =IFERROR(AVERAGE(Y109:AA109),"") -> 166.9598
B111: Accrued Expenses and Other Current Liabilities | E111: =+_xlfn.XLOOKUP($B111,Inputs!$B:$B,Inputs!O:O) -> 12.284 | F111: =+_xlfn.XLOOKUP($B111,Inputs!$B:$B,Inputs!P:P) -> 9.785 | G111: =+_xlfn.XLOOKUP($B111,Inputs!$B:$B,Inputs!Q:Q) -> 29.33 | H111: =IFERROR(AVERAGE(E111:G111)*(1+H29),"") -> 27.4128 | I111: =IFERROR(AVERAGE(F111:H111)*(1+I29),"") -> 35.481493 | J111: =IFERROR(AVERAGE(G111:I111)*(1+J29),"") -> 49.18629 | K111: =IFERROR(AVERAGE(H111:J111)*(1+K29),"") -> 59.776311 | L111: =IFERROR(AVERAGE(I111:K111)*(1+L29),"") -> 77.03685 | M111: =IFERROR(AVERAGE(J111:L111)*(1+M29),"") -> 92.999725 | N111: =IFERROR(AVERAGE(K111:M111)*(1+N29),"") -> 114.90644 | O111: =IFERROR(AVERAGE(L111:N111)*(1+O29),"") -> 142.47151 | ... AB111: =IFERROR(AVERAGE(Y111:AA111)*(1+AB29),"") -> 810.3761 | AC111: a percentagem é extremamente alta hoje pq a receita é baixa, não deve manter o ratio as % of revenue
B112: growing with revenue | E112: =IFERROR(E111/E$28,"") -> 1.7125331 | F112: =IFERROR(F111/F$28,"") -> 1.1172642 | G112: =IFERROR(G111/G$28,"") -> 3.3227597 | H112: =IFERROR(H111/H$28,"") -> 1.9409765 | I112: =IFERROR(I111/I$28,"") -> 1.5701777 | J112: =IFERROR(J111/J$28,"") -> 1.3604137 | K112: =IFERROR(K111/K$28,"") -> 1.0333229 | L112: =IFERROR(L111/L$28,"") -> 0.8323107 | ... AB112: =IFERROR(AB111/AB$28,"") -> 0.074615024
B114: Total Borrowings | E114: =+_xlfn.XLOOKUP($B114,Inputs!$B:$B,Inputs!O:O) -> 2.312 | F114: =+_xlfn.XLOOKUP($B114,Inputs!$B:$B,Inputs!P:P) -> 1.63 | G114: =+_xlfn.XLOOKUP($B114,Inputs!$B:$B,Inputs!Q:Q) -> 69.875 | H114: =IFERROR(G114+H155-H157,"") -> 147.324 | I114: =IFERROR(H114+I155-I157,"") -> 166.96692 | J114: =IFERROR(I114+J155-J157,"") -> 277.6011 | K114: =IFERROR(J114+K155-K157,"") -> 348.6975 | L114: =IFERROR(K114+L155-L157,"") -> 504.59362 | M114: =IFERROR(L114+M155-M157,"") -> 629.1405 | N114: =IFERROR(M114+N155-N157,"") -> 843.16495 | O114: =IFERROR(N114+O155-O157,"") -> 980.24585 | ... AB114: =IFERROR(AA114+AB155-AB157,"") -> 1585.9308
B116: Total Leases | E116: =+_xlfn.XLOOKUP($B116,Inputs!$B:$B,Inputs!O:O) -> 7.301 | F116: =+_xlfn.XLOOKUP($B116,Inputs!$B:$B,Inputs!P:P) -> 7.028 | G116: =+_xlfn.XLOOKUP($B116,Inputs!$B:$B,Inputs!Q:Q) -> 0.6389 | H116: =+IFERROR(H117*H28,"") -> 8.9102855 | I116: =+IFERROR(I117*I28,"") -> 11.341823 | J116: =+IFERROR(J117*J28,"") -> 14.524727 | K116: =+IFERROR(K117*K28,"") -> 29.590386 | L116: =+IFERROR(L117*L28,"") -> 43.661342 | M116: =+IFERROR(M117*M28,"") -> 64.094631 | N116: =+IFERROR(N117*N28,"") -> 100.30179 | O116: =+IFERROR(O117*O28,"") -> 147.34088 | ... AB116: =+IFERROR(AB117*AB28,"") -> 5140.6327
B117: % of revenues | E117: =IFERROR(E116/E$28,"") -> 1.0178447 | F117: =IFERROR(F116/F$28,"") -> 0.80246632 | G117: =IFERROR(G116/G$28,"") -> 0.072380197 | H117: =+IFERROR(AVERAGE(E117:G117),"") -> 0.63089707 | I117: =+IFERROR(AVERAGE(F117:H117),"") -> 0.50191453 | J117: =+IFERROR(AVERAGE(G117:I117),"") -> 0.4017306 | K117: =+IFERROR(AVERAGE(H117:J117),"") -> 0.51151407 | L117: =+IFERROR(AVERAGE(I117:K117),"") -> 0.47171973 | M117: =+IFERROR(AVERAGE(J117:L117),"") -> 0.4616548 | N117: =+IFERROR(AVERAGE(K117:M117),"") -> 0.48162953 | O117: =+IFERROR(AVERAGE(L117:N117),"") -> 0.47166802 | ... AB117: =+IFERROR(AVERAGE(Y117:AA117),"") -> 0.47332149
A119: x | B119: Cash Flow | E119: =E26 -> 2022 | F119: =F26 -> 2023 | G119: =G26 -> 2024 | H119: =H26 -> 2025 | I119: =I26 -> 2026 | J119: =J26 -> 2027 | K119: =K26 -> 2028 | L119: =L26 -> 2029 | ... Q119: =Q26 -> 2034 | R119: 2035E | S119: 2036E | T119: 2037E | U119: 2038E | V119: 2039E | W119: 2040E | X119: 2041E | Y119: 2042E | Z119: 2043E | AA119: 2044E | AB119: 2045E
B121: D&A (Depreciation & Amortization) | E121: =+E48 -> 2.333 | F121: =+F48 -> 1.845 | G121: =+G48 -> 1.932 | H121: =+H48 -> 0 | I121: =+I48 -> 0 | J121: =+J48 -> 0 | K121: =+K48 -> 0 | L121: =+L48 -> 0 | ... AB121: =+AB48 -> 0
B123: Stock Based Compensation | E123: =+_xlfn.XLOOKUP($B123,Inputs!$B:$B,Inputs!O:O) -> 9.164 | F123: =+_xlfn.XLOOKUP($B123,Inputs!$B:$B,Inputs!P:P) -> 21.919 | G123: =+_xlfn.XLOOKUP($B123,Inputs!$B:$B,Inputs!Q:Q) -> 15.661 | H123: =IFERROR(H124*H37,"") -> 15.298816 | I123: =IFERROR(I124*I37,"") -> 17.390507 | J123: =IFERROR(J124*J37,"") -> 15.556613 | K123: =IFERROR(K124*K37,"") -> 17.037329 | L123: =IFERROR(L124*L37,"") -> 17.146309 | M123: =IFERROR(M124*M37,"") -> 15.233208 | N123: =IFERROR(N124*N37,"") -> 15.332827 | O123: =IFERROR(O124*O37,"") -> 17.249142 | ... AB123: =IFERROR(AB124*AB37,"") -> 79.875313
B124: % of SG&A | E124: =+IFERROR(E123/E37,"") -> 0.28993577 | F124: =+IFERROR(F123/F37,"") -> 0.4635018 | G124: =+IFERROR(G123/G37,"") -> 0.32980247 | H124: =IFERROR(AVERAGE(E124:G124),"") -> 0.36108001 | I124: =IFERROR(AVERAGE(F124:H124),"") -> 0.38479476 | J124: =IFERROR(AVERAGE(G124:I124),"") -> 0.35855908 | K124: =IFERROR(AVERAGE(H124:J124),"") -> 0.36814462 | L124: =IFERROR(AVERAGE(I124:K124),"") -> 0.37049949 | M124: =IFERROR(AVERAGE(J124:L124),"") -> 0.36573439 | N124: =IFERROR(AVERAGE(K124:M124),"") -> 0.36812617 | O124: =IFERROR(AVERAGE(L124:N124),"") -> 0.36812002 | ... AB124: =IFERROR(AVERAGE(Y124:AA124),"") -> 0.36772422
B126: Changes in Net Working Capital | E126: =+_xlfn.XLOOKUP($B126,Inputs!$B:$B,Inputs!O:O) -> 3.022 | F126: =+_xlfn.XLOOKUP($B126,Inputs!$B:$B,Inputs!P:P) -> -2.698 | G126: =+_xlfn.XLOOKUP($B126,Inputs!$B:$B,Inputs!Q:Q) -> 20.862 | H126: =IFERROR(-((H88+H91+H94-H108-H111)-(G88+G91+G94-G108-G111)),"") -> -2.8557527 | I126: =IFERROR(-((I88+I91+I94-I108-I111)-(H88+H91+H94-H108-H111)),"") -> 4.3563875 | J126: =IFERROR(-((J88+J91+J94-J108-J111)-(I88+I91+I94-I108-I111)),"") -> 9.008047 | K126: =IFERROR(-((K88+K91+K94-K108-K111)-(J88+J91+J94-J108-J111)),"") -> 5.056551 | L126: =IFERROR(-((L88+L91+L94-L108-L111)-(K88+K91+K94-K108-K111)),"") -> 6.5141106 | M126: =IFERROR(-((M88+M91+M94-M108-M111)-(L88+L91+L94-L108-L111)),"") -> 4.4631462 | N126: =IFERROR(-((N88+N91+N94-N108-N111)-(M88+M91+M94-M108-M111)),"") -> 4.8219152 | O126: =IFERROR(-((O88+O91+O94-O108-O111)-(N88+N91+N94-N108-N111)),"") -> 1.4817452 | ... AB126: =IFERROR(-((AB88+AB91+AB94-AB108-AB111)-(AA88+AA91+AA94-AA108-AA111)),"") -> -310.84575
B128: Other Operating Adjustments | E128: =+_xlfn.XLOOKUP($B128,Inputs!$B:$B,Inputs!O:O) -> -6.043 | F128: =+_xlfn.XLOOKUP($B128,Inputs!$B:$B,Inputs!P:P) -> 1 | G128: =+_xlfn.XLOOKUP($B128,Inputs!$B:$B,Inputs!Q:Q) -> 62.781 | H128: =IFERROR(AVERAGE(E128:G128)*(1+H29),"") -> 30.7936 | I128: =IFERROR(AVERAGE(F128:H128)*(1+I29),"") -> 50.439787 | J128: =IFERROR(AVERAGE(G128:I128)*(1+J29),"") -> 76.807673 | K128: =IFERROR(AVERAGE(H128:J128)*(1+K29),"") -> 84.288565 | L128: =IFERROR(AVERAGE(I128:K128)*(1+L29),"") -> 112.81921 | M128: =IFERROR(AVERAGE(J128:L128)*(1+M29),"") -> 136.95773 | N128: =IFERROR(AVERAGE(K128:M128)*(1+N29),"") -> 167.03275 | O128: =IFERROR(AVERAGE(L128:N128)*(1+O29),"") -> 208.40485 | ... AB128: =IFERROR(AVERAGE(Y128:AA128)*(1+AB29),"") -> 1184.1752
B130: Operating Cash Flow | E130: =+_xlfn.XLOOKUP($B130,Inputs!$B:$B,Inputs!O:O) -> -45.226 | F130: =+_xlfn.XLOOKUP($B130,Inputs!$B:$B,Inputs!P:P) -> -60.649 | G130: =+_xlfn.XLOOKUP($B130,Inputs!$B:$B,Inputs!Q:Q) -> -42.643 | H130: =IFERROR(H79+H121+H123+H126+H128,"") -> -66.298317 | I130: =IFERROR(I79+I121+I123+I126+I128,"") -> -79.837317 | J130: =IFERROR(J79+J121+J123+J126+J128,"") -> -104.92291 | K130: =IFERROR(K79+K121+K123+K126+K128,"") -> -142.70395 | L130: =IFERROR(L79+L121+L123+L126+L128,"") -> -167.62379 | M130: =IFERROR(M79+M121+M123+M126+M128,"") -> -201.61361 | N130: =IFERROR(N79+N121+N123+N126+N128,"") -> -184.0726 | O130: =IFERROR(O79+O121+O123+O126+O128,"") -> -142.52846 | ... AB130: =IFERROR(AB79+AB121+AB123+AB126+AB128,"") -> 5705.4589
B132: Net CapEx | E132: =+_xlfn.XLOOKUP($B132,Inputs!$B:$B,Inputs!O:O) -> -0.423 | F132: =+_xlfn.XLOOKUP($B132,Inputs!$B:$B,Inputs!P:P) -> -0.583 | G132: =+_xlfn.XLOOKUP($B132,Inputs!$B:$B,Inputs!Q:Q) -> -2.395 | AC132: capex pode crescer como %crescimento da receita até estabilizar num ratio de mais ou menos 20-30% da receita, é o que se vê em hardware
B133: % of growth / revenue growth | F133: =(F132/E132-1)/F29 -> 1.7117927 | G133: =(G132/F132-1)/G29 -> 394.49862
B135: Acquisition of Fixed & Intangibles | E135: =+_xlfn.XLOOKUP($B135,Inputs!$B:$B,Inputs!O:O) -> -0.423 | F135: =+_xlfn.XLOOKUP($B135,Inputs!$B:$B,Inputs!P:P) -> -0.583 | G135: =+_xlfn.XLOOKUP($B135,Inputs!$B:$B,Inputs!Q:Q) -> -2.395 | H135: =H136*H28 -> -4.23696 | I135: =I136*I28 -> -6.779136 | J135: =J136*J28 -> -10.846618 | K135: =K136*K28 -> -14.462157 | L135: =L136*L28 -> -23.139451 | M135: =M136*M28 -> 34.709176 | N135: =N136*N28 -> -41.651012 | O135: =O136*O28 -> -62.476517 | ... AB135: =AB136*AB28 -> -1086.0763
B136: % of Revenue | E136: =E135/E28 -> -0.058971142 | F136: =F135/F28 -> -0.06656771 | G136: =G135/G28 -> -0.27132661 | H136: -0.3 | I136: -0.3 | J136: -0.3 | K136: -0.25 | L136: -0.25 | M136: 0.25 | N136: -0.2 | O136: -0.2 | P136: -0.2 | Q136: -0.15 | R136: -0.15 | S136: -0.1 | T136: -0.1 | U136: -0.1 | V136: -0.1 | W136: -0.1 | X136: -0.1 | Y136: -0.1 | Z136: -0.1 | AA136: -0.1 | AB136: -0.1
B137: Disposal of Fixed & Intangibles | E137: =+_xlfn.XLOOKUP($B137,Inputs!$B:$B,Inputs!O:O) -> 0 | F137: =+_xlfn.XLOOKUP($B137,Inputs!$B:$B,Inputs!P:P) -> 0 | G137: =+_xlfn.XLOOKUP($B137,Inputs!$B:$B,Inputs!Q:Q) -> 0 | H137: =IFERROR(H138*G98,"") -> 0 | I137: =IFERROR(I138*H98,"") -> 0 | J137: =IFERROR(J138*I98,"") -> 0 | K137: =IFERROR(K138*J98,"") -> 0 | L137: =IFERROR(L138*K98,"") -> 0 | M137: =IFERROR(M138*L98,"") -> 0 | N137: =IFERROR(N138*M98,"") -> 0 | O137: =IFERROR(O138*N98,"") -> 0 | ... AB137: =IFERROR(AB138*AA98,"") -> 0
B138: Disposal Rate (% Gross PP&E) | E138: =IFERROR(E137/E98,"") -> 0 | F138: =IFERROR(F137/F98,"") -> 0 | G138: =IFERROR(G137/G98,"") -> 0 | H138: =IFERROR(AVERAGE(E138:G138),"") -> 0 | I138: =IFERROR(AVERAGE(F138:H138),"") -> 0 | J138: =IFERROR(AVERAGE(G138:I138),"") -> 0 | K138: =IFERROR(AVERAGE(H138:J138),"") -> 0 | L138: =IFERROR(AVERAGE(I138:K138),"") -> 0 | M138: =IFERROR(AVERAGE(J138:L138),"") -> 0 | N138: =IFERROR(AVERAGE(K138:M138),"") -> 0 | O138: =IFERROR(AVERAGE(L138:N138),"") -> 0 | ... AB138: =IFERROR(AVERAGE(Y138:AA138),"") -> 0
B140: Net Cash from Investments & Acquisitions | E140: =+_xlfn.XLOOKUP($B140,Inputs!$B:$B,Inputs!O:O) -> 0 | F140: =+_xlfn.XLOOKUP($B140,Inputs!$B:$B,Inputs!P:P) -> 0 | G140: =+_xlfn.XLOOKUP($B140,Inputs!$B:$B,Inputs!Q:Q) -> -1 | H140: 0 | I140: 0 | J140: 0 | K140: 0 | L140: 0 | M140: 0 | N140: 0 | O140: 0 | P140: 0 | Q140: 0 | R140: 0 | S140: 0 | T140: 0 | U140: 0 | V140: 0 | W140: 0 | X140: 0 | Y140: 0 | Z140: 0 | AA140: 0 | AB140: 0
B142: Other Investing Inflows (Outflows) | E142: =+_xlfn.XLOOKUP($B142,Inputs!$B:$B,Inputs!O:O) -> -0.075 | F142: =+_xlfn.XLOOKUP($B142,Inputs!$B:$B,Inputs!P:P) -> -0.047 | G142: =+_xlfn.XLOOKUP($B142,Inputs!$B:$B,Inputs!Q:Q) -> 0.254 | H142: =IFERROR(AVERAGE(E142:G142)*(1+H29),"") -> 0.0704 | I142: =IFERROR(AVERAGE(F142:H142)*(1+I29),"") -> 0.14794667 | J142: =IFERROR(AVERAGE(G142:I142)*(1+J29),"") -> 0.25191822 | K142: =IFERROR(AVERAGE(H142:J142)*(1+K29),"") -> 0.25080794 | L142: =IFERROR(AVERAGE(I142:K142)*(1+L29),"") -> 0.34702551 | M142: =IFERROR(AVERAGE(J142:L142)*(1+M29),"") -> 0.42487584 | N142: =IFERROR(AVERAGE(K142:M142)*(1+N29),"") -> 0.51135464 | O142: =IFERROR(AVERAGE(L142:N142)*(1+O29),"") -> 0.64162799 | ... AB142: =IFERROR(AVERAGE(Y142:AA142)*(1+AB29),"") -> 3.6432235
B144: Investing Cash Flow | E144: =+_xlfn.XLOOKUP($B144,Inputs!$B:$B,Inputs!O:O) -> -0.498 | F144: =+_xlfn.XLOOKUP($B144,Inputs!$B:$B,Inputs!P:P) -> -0.63 | G144: =+_xlfn.XLOOKUP($B144,Inputs!$B:$B,Inputs!Q:Q) -> -3.141 | H144: =IFERROR(+H132+H140+H142,"") -> 0.0704 | I144: =IFERROR(+I132+I140+I142,"") -> 0.14794667 | J144: =IFERROR(+J132+J140+J142,"") -> 0.25191822 | K144: =IFERROR(+K132+K140+K142,"") -> 0.25080794 | L144: =IFERROR(+L132+L140+L142,"") -> 0.34702551 | M144: =IFERROR(+M132+M140+M142,"") -> 0.42487584 | N144: =IFERROR(+N132+N140+N142,"") -> 0.51135464 | O144: =IFERROR(+O132+O140+O142,"") -> 0.64162799 | ... AB144: =IFERROR(+AB132+AB140+AB142,"") -> 3.6432235
B146: Dividends | E146: =+_xlfn.XLOOKUP($B146,Inputs!$B:$B,Inputs!O:O) -> 0 | F146: =+_xlfn.XLOOKUP($B146,Inputs!$B:$B,Inputs!P:P) -> 0 | G146: =+_xlfn.XLOOKUP($B146,Inputs!$B:$B,Inputs!Q:Q) -> 0 | H146: =+IFERROR(H147*_xlfn.XLOOKUP("Net Income",$B:$B,$H:$H),"") -> 0 | I146: =+IFERROR(I147*_xlfn.XLOOKUP("Net Income",$B:$B,$H:$H),"") -> 0 | J146: =+IFERROR(J147*_xlfn.XLOOKUP("Net Income",$B:$B,$H:$H),"") -> 0 | K146: =+IFERROR(K147*_xlfn.XLOOKUP("Net Income",$B:$B,$H:$H),"") -> 0 | L146: =+IFERROR(L147*_xlfn.XLOOKUP("Net Income",$B:$B,$H:$H),"") -> 0 | M146: =+IFERROR(M147*_xlfn.XLOOKUP("Net Income",$B:$B,$H:$H),"") -> 0 | N146: =+IFERROR(N147*_xlfn.XLOOKUP("Net Income",$B:$B,$H:$H),"") -> 0 | O146: =+IFERROR(O147*_xlfn.XLOOKUP("Net Income",$B:$B,$H:$H),"") -> 0 | ... AB146: =+IFERROR(AB147*_xlfn.XLOOKUP("Net Income",$B:$B,$H:$H),"") -> 0
B147: Dividend payout | E147: =IFERROR(-E146/E$79,"") -> 0 | F147: =IFERROR(-F146/F$79,"") -> 0 | G147: =IFERROR(-G146/G$79,"") -> 0
B149: Increase (Repurchase) of Shares | E149: =+_xlfn.XLOOKUP($B149,Inputs!$B:$B,Inputs!O:O) -> 40 | F149: =+_xlfn.XLOOKUP($B149,Inputs!$B:$B,Inputs!P:P) -> 63.676 | G149: =+_xlfn.XLOOKUP($B149,Inputs!$B:$B,Inputs!Q:Q) -> 214.191 | H149: =IFERROR(-H150*_xlfn.XLOOKUP("Net Income",$B:$B,H:H),"") -> 0 | I149: =IFERROR(-I150*_xlfn.XLOOKUP("Net Income",$B:$B,I:I),"") -> 0 | J149: =IFERROR(-J150*_xlfn.XLOOKUP("Net Income",$B:$B,J:J),"") -> 0 | K149: =IFERROR(-K150*_xlfn.XLOOKUP("Net Income",$B:$B,K:K),"") -> 0 | L149: =IFERROR(-L150*_xlfn.XLOOKUP("Net Income",$B:$B,L:L),"") -> 0 | M149: =IFERROR(-M150*_xlfn.XLOOKUP("Net Income",$B:$B,M:M),"") -> 0 | N149: =IFERROR(-N150*_xlfn.XLOOKUP("Net Income",$B:$B,N:N),"") -> 0 | O149: =IFERROR(-O150*_xlfn.XLOOKUP("Net Income",$B:$B,O:O),"") -> 0 | P149: =IFERROR(-P150*_xlfn.XLOOKUP("Net Income",$B:$B,P:P),"") -> 0 | Q149: =IFERROR(-Q150*_xlfn.XLOOKUP("Net Income",$B:$B,Q:Q),"") -> 0 | R149: =IFERROR(-R150*_xlfn.XLOOKUP("Net Income",$B:$B,R:R),"") -> 0 | S149: =IFERROR(-S150*_xlfn.XLOOKUP("Net Income",$B:$B,S:S),"") -> 0 | T149: =IFERROR(-T150*_xlfn.XLOOKUP("Net Income",$B:$B,T:T),"") -> 0 | U149: =IFERROR(-U150*_xlfn.XLOOKUP("Net Income",$B:$B,U:U),"") -> 0 | V149: =IFERROR(-V150*_xlfn.XLOOKUP("Net Income",$B:$B,V:V),"") -> 0 | W149: =IFERROR(-W150*_xlfn.XLOOKUP("Net Income",$B:$B,W:W),"") -> 0 | X149: =IFERROR(-X150*_xlfn.XLOOKUP("Net Income",$B:$B,X:X),"") -> 0 | Y149: =IFERROR(-Y150*_xlfn.XLOOKUP("Net Income",$B:$B,Y:Y),"") -> 0 | Z149: =IFERROR(-Z150*_xlfn.XLOOKUP("Net Income",$B:$B,Z:Z),"") -> 0 | AA149: =IFERROR(-AA150*_xlfn.XLOOKUP("Net Income",$B:$B,AA:AA),"") -> 0 | AB149: =IFERROR(-AB150*_xlfn.XLOOKUP("Net Income",$B:$B,AB:AB),"") -> 0
...

Sheet Inputs
B2: Inputs
B3: in millions of USD
A4: x | B4: Income Statement | G4: 2014 | H4: =+G4+1 -> 2015 | I4: =+H4+1 -> 2016 | J4: =+I4+1 -> 2017 | K4: =+J4+1 -> 2018 | L4: =+K4+1 -> 2019 | M4: =+L4+1 -> 2020 | N4: =+M4+1 -> 2021 | O4: =+N4+1 -> 2022 | ... Q4: =+P4+1 -> 2024 | R4: ="CAGR "&$N$4&" - "&$Q$4 -> CAGR 2021 - 2024
B6: Revenue (Sales) | G6: N/A | H6: N/A | I6: N/A | J6: N/A | K6: N/A | L6: N/A | M6: N/A | N6: 6.279 | O6: 7.173 | P6: 8.758 | Q6: 8.827 | R6: =IFERROR((Q6/N6)^(1/COUNT($N$4:$Q$4))-1,"") -> 0.088881604
B7: COGS (Cost of Goods Sold) | G7: N/A | H7: N/A | I7: N/A | J7: N/A | K7: N/A | L7: N/A | M7: N/A | N7: 1.75 | O7: 2.923 | P7: 4.136 | Q7: 3.264 | R7: =IFERROR((Q7/N7)^(1/COUNT($N$4:$Q$4))-1,"") -> 0.16863268
B8: Gross Profit | G8: N/A | H8: N/A | I8: N/A | J8: N/A | K8: N/A | L8: N/A | M8: N/A | N8: 4.529 | O8: 4.25 | P8: 4.622 | Q8: 5.563 | R8: =IFERROR((Q8/N8)^(1/COUNT($N$4:$Q$4))-1,"") -> 0.052753478
B9: SG&A (Selling, General & Administrative) | G9: N/A | H9: N/A | I9: N/A | J9: N/A | K9: N/A | L9: N/A | M9: N/A | N9: 18.076 | O9: 31.607 | P9: 47.29 | Q9: 47.486 | R9: =IFERROR((Q9/N9)^(1/COUNT($N$4:$Q$4))-1,"") -> 0.27310966
B10: R&D (Research & Development) | G10: N/A | H10: N/A | I10: N/A | J10: N/A | K10: N/A | L10: N/A | M10: N/A | N10: 25.401 | O10: 32.101 | P10: 37.878 | Q10: 35.3 | R10: =IFERROR((Q10/N10)^(1/COUNT($N$4:$Q$4))-1,"") -> 0.085752837
B11: Other Operating (Income) Expenses | G11: N/A | H11: N/A | I11: N/A | J11: N/A | K11: N/A | L11: N/A | M11: N/A | N11: 0 | O11: 0 | P11: -3.278 | Q11: -4.437 | R11: =IFERROR((Q11/N11)^(1/COUNT($N$4:$Q$4))-1,"")
B12: EBITDA | G12: N/A | H12: N/A | I12: N/A | J12: N/A | K12: N/A | L12: N/A | M12: N/A | N12: -36.346 | O12: -57.125 | P12: -75.423 | Q12: -69.294 | R12: =IFERROR((Q12/N12)^(1/COUNT($N$4:$Q$4))-1,"") -> 0.17505921
B13: D&A (Depreciation & Amortization) | G13: N/A | H13: N/A | I13: N/A | J13: N/A | K13: N/A | L13: N/A | M13: N/A | N13: 2.602 | O13: 2.333 | P13: 1.845 | Q13: 1.932 | R13: =IFERROR((Q13/N13)^(1/COUNT($N$4:$Q$4))-1,"") -> -0.071728627
B14: Depreciation Expense | G14: N/A | H14: N/A | I14: N/A | J14: N/A | K14: N/A | L14: N/A | M14: N/A | N14: =N13 -> 2.602 | O14: =O13 -> 2.333 | P14: =P13 -> 1.845 | Q14: =Q13 -> 1.932 | R14: =IFERROR((Q14/N14)^(1/COUNT($N$4:$Q$4))-1,"") -> -0.071728627
B15: Amortization Expense | G15: N/A | H15: N/A | I15: N/A | J15: N/A | K15: N/A | L15: N/A | M15: N/A | N15: 0 | O15: 0 | P15: 0 | Q15: 0 | R15: =IFERROR((Q15/N15)^(1/COUNT($N$4:$Q$4))-1,"")
B16: Operating Income (EBIT) | G16: N/A | H16: N/A | I16: N/A | J16: N/A | K16: N/A | L16: N/A | M16: N/A | N16: -38.948 | O16: 8 | P16: -77.268 | Q16: -72.786 | R16: =IFERROR((Q16/N16)^(1/COUNT($N$4:$Q$4))-1,"") -> 0.16920502
B17: Net Interest Expense (Income) | G17: N/A | H17: N/A | I17: N/A | J17: N/A | K17: N/A | L17: N/A | M17: N/A | N17: 1.728 | O17: 2.335 | P17: 0.037 | Q17: 3.897 | R17: =IFERROR((Q17/N17)^(1/COUNT($N$4:$Q$4))-1,"") -> 0.22545302
B18: Interest Expense | G18: N/A | H18: N/A | I18: N/A | J18: N/A | K18: N/A | L18: N/A | M18: N/A | N18: 1.728 | O18: 2.335 | P18: 0.037 | Q18: 3.897 | R18: =IFERROR((Q18/N18)^(1/COUNT($N$4:$Q$4))-1,"") -> 0.22545302
B19: Interest Income | G19: N/A | H19: N/A | I19: N/A | J19: N/A | K19: N/A | L19: N/A | M19: N/A | N19: 0 | O19: 0 | P19: 0 | Q19: 0 | R19: =IFERROR((Q19/N19)^(1/COUNT($N$4:$Q$4))-1,"")
B20: FX (Gain) Loss | G20: N/A | H20: N/A | I20: N/A | J20: N/A | K20: N/A | L20: N/A | M20: N/A | N20: 0 | O20: 0 | P20: 0 | Q20: 0 | R20: =IFERROR((Q20/N20)^(1/COUNT($N$4:$Q$4))-1,"")
B21: Other Non-Operating (Income) Expenses | G21: N/A | H21: N/A | I21: N/A | J21: N/A | K21: N/A | L21: N/A | M21: N/A | N21: -9.131 | O21: -8.091 | P21: 2.132 | Q21: 64.254 | R21: =IFERROR((Q21/N21)^(1/COUNT($N$4:$Q$4))-1,"")
B22: Pre-Tax Income (EBT) | G22: N/A | H22: N/A | I22: N/A | J22: N/A | K22: N/A | L22: N/A | M22: N/A | N22: -31.545 | O22: -53.702 | P22: -82.715 | Q22: -143.879 | R22: =IFERROR((Q22/N22)^(1/COUNT($N$4:$Q$4))-1,"") -> 0.46139198
B23: Tax Expense (Benefits) | G23: N/A | H23: N/A | I23: N/A | J23: N/A | K23: N/A | L23: N/A | M23: N/A | N23: 0 | O23: 0 | P23: 0 | Q23: 0 | R23: =IFERROR((Q23/N23)^(1/COUNT($N$4:$Q$4))-1,"")
B24: Net Income | G24: N/A | H24: N/A | I24: N/A | J24: N/A | K24: N/A | L24: N/A | M24: N/A | N24: -31.545 | O24: -53.702 | P24: -82.715 | Q24: -143.879 | R24: =IFERROR((Q24/N24)^(1/COUNT($N$4:$Q$4))-1,"") -> 0.46139198
B25: EPS basic | G25: N/A | H25: N/A | I25: N/A | J25: N/A | K25: N/A | L25: N/A | M25: N/A | N25: -0.172 | O25: -0.45 | P25: -0.6 | Q25: -0.75 | R25: =IFERROR((Q25/N25)^(1/COUNT($N$4:$Q$4))-1,"") -> 0.4450511
B26: EPS diluted | G26: N/A | H26: N/A | I26: N/A | J26: N/A | K26: N/A | L26: N/A | M26: N/A | N26: -0.172 | O26: -0.45 | P26: -0.6 | Q26: -0.75 | R26: =IFERROR((Q26/N26)^(1/COUNT($N$4:$Q$4))-1,"") -> 0.4450511
... B28: Diluted Weighted Average Shares | G28: N/A | H28: N/A | I28: N/A | J28: N/A | K28: N/A | L28: N/A | M28: N/A | N28: 182.265 | O28: 119.648 | P28: 137.994 | Q28: 192.129 | R28: =IFERROR((Q28/N28)^(1/COUNT($N$4:$Q$4))-1,"") -> 0.013263528
R29: =IFERROR((Q29/N29)^(1/COUNT($N$4:$Q$4))-1,"")
A30: x | B30: Balance Sheet | G30: 2014 | H30: =+G30+1 -> 2015 | I30: =+H30+1 -> 2016 | J30: =+I30+1 -> 2017 | K30: =+J30+1 -> 2018 | L30: =+K30+1 -> 2019 | M30: =+L30+1 -> 2020 | N30: =+M30+1 -> 2021 | O30: =+N30+1 -> 2022 | ... Q30: =+P30+1 -> 2024 | R30: ="CAGR "&$N$4&" - "&$Q$4 -> CAGR 2021 - 2024
B32: Cash & Cash Equivalents & ST Investments | G32: N/A | H32: N/A | I32: N/A | J32: N/A | K32: N/A | L32: N/A | M32: 1.085 | N32: =+SUM(N33:N34) -> 9.483 | O32: =+SUM(O33:O34) -> 7.065 | P32: =+SUM(P33:P34) -> 41.307 | Q32: =+SUM(Q33:Q34) -> 177.98 | R32: =IFERROR((Q32/N32)^(1/COUNT($N$4:$Q$4))-1,"") -> 1.0814039
B33: Cash & Cash Equivalents | G33: N/A | H33: N/A | I33: N/A | J33: N/A | K33: N/A | L33: N/A | M33: 1.085 | N33: 9.483 | O33: 7.065 | P33: 41.307 | Q33: 177.98 | R33: =IFERROR((Q33/N33)^(1/COUNT($N$4:$Q$4))-1,"") -> 1.0814039
B34: Short-Term Investments | G34: N/A | H34: N/A | I34: N/A | J34: N/A | K34: N/A | L34: N/A | M34: - | N34: 0 | O34: 0 | P34: 0 | Q34: 0 | R34: =IFERROR((Q34/N34)^(1/COUNT($N$4:$Q$4))-1,"")
B35: Accounts Receivable | G35: N/A | H35: N/A | I35: N/A | J35: N/A | K35: N/A | L35: N/A | M35: 0 | N35: 0.421 | O35: 0.757 | P35: 1.652 | Q35: 1.42 | R35: =IFERROR((Q35/N35)^(1/COUNT($N$4:$Q$4))-1,"") -> 0.35519429
B36: Inventory | G36: N/A | H36: N/A | I36: N/A | J36: N/A | K36: N/A | L36: N/A | M36: 0 | N36: 2.114 | O36: 2.196 | P36: 2.078 | Q36: 1.686 | R36: =IFERROR((Q36/N36)^(1/COUNT($N$4:$Q$4))-1,"") -> -0.054986208
B37: Prepaid expenses and Other Current Assets | G37: N/A | H37: N/A | I37: N/A | J37: N/A | K37: N/A | L37: N/A | M37: 0 | N37: 3.998 | O37: 3.907 | P37: 2.009 | Q37: 3.954 | R37: =IFERROR((Q37/N37)^(1/COUNT($N$4:$Q$4))-1,"") -> -0.0027628042
B38: Current Assets | G38: N/A | H38: N/A | I38: N/A | J38: N/A | K38: N/A | L38: N/A | M38: 1.474 | N38: 19.158 | O38: 13.925 | P38: 47.046 | Q38: 185.04 | R38: =IFERROR((Q38/N38)^(1/COUNT($N$4:$Q$4))-1,"") -> 0.76290481
B39: Net PP&E (Property, Plant and Equipment) | G39: N/A | H39: N/A | I39: N/A | J39: N/A | K39: N/A | L39: N/A | M39: 0 | N39: 11.827 | O39: 11.427 | P39: 10.774 | Q39: 11.394 | R39: =IFERROR((Q39/N39)^(1/COUNT($N$4:$Q$4))-1,"") -> -0.0092811994
B40: Gross PP&E (Property, Plant and Equipment) | G40: N/A | H40: N/A | I40: N/A | J40: N/A | K40: N/A | L40: N/A | M40: - | N40: 33.628 | O40: 34.538 | P40: 34.827 | Q40: 36.401 | R40: =IFERROR((Q40/N40)^(1/COUNT($N$4:$Q$4))-1,"") -> 0.020006805
B41: Accumulated Depreciation | G41: N/A | H41: N/A | I41: N/A | J41: N/A | K41: N/A | L41: N/A | M41: - | N41: 21.801 | O41: 23.111 | P41: 24.053 | Q41: 25.007 | R41: =IFERROR((Q41/N41)^(1/COUNT($N$4:$Q$4))-1,"") -> 0.034895015
B42: Right-of-Use Assets | G42: N/A | H42: N/A | I42: N/A | J42: N/A | K42: N/A | L42: N/A | M42: - | N42: 8.578 | O42: 9.133 | P42: 8.223 | Q42: 7.261 | R42: =IFERROR((Q42/N42)^(1/COUNT($N$4:$Q$4))-1,"") -> -0.040814514
B43: Intangibles | G43: N/A | H43: N/A | I43: N/A | J43: N/A | K43: N/A | L43: N/A | M43: 0 | N43: 0.272 | O43: 0.244 | P43: 0.179 | Q43: 0.49 | R43: =IFERROR((Q43/N43)^(1/COUNT($N$4:$Q$4))-1,"") -> 0.15852869
B44: Goodwill | G44: N/A | H44: N/A | I44: N/A | J44: N/A | K44: N/A | L44: N/A | M44: 0 | N44: 0.000 | O44: 0 | P44: 0.000 | Q44: 0 | R44: =IFERROR((Q44/N44)^(1/COUNT($N$4:$Q$4))-1,"")
B45: Intangibles excl. Goodwill | G45: N/A | H45: N/A | I45: N/A | J45: N/A | K45: N/A | L45: N/A | M45: 0 | N45: 0.272 | O45: 0.244 | P45: 0.179 | Q45: 0.49
B46: Other Non-Current Assets | G46: N/A | H46: N/A | I46: N/A | J46: N/A | K46: N/A | L46: N/A | M46: 300.059 | N46: -7.225 | O46: -7.782 | P46: -6.866 | Q46: -4.332 | R46: =IFERROR((Q46/N46)^(1/COUNT($N$4:$Q$4))-1,"") -> -0.12004057
B47: Non-Current Assets | G47: N/A | H47: N/A | I47: N/A | J47: N/A | K47: N/A | L47: N/A | M47: 300.059 | N47: 13.452 | O47: 13.022 | P47: 12.31 | Q47: 14.813 | R47: =IFERROR((Q47/N47)^(1/COUNT($N$4:$Q$4))-1,"") -> 0.024386959
B48: Total Assets | G48: N/A | H48: N/A | I48: N/A | J48: N/A | K48: N/A | L48: N/A | M48: 301.532 | N48: 32.61 | O48: 26.947 | P48: 59.356 | Q48: 199.853 | R48: =IFERROR((Q48/N48)^(1/COUNT($N$4:$Q$4))-1,"") -> 0.57340298
B49: Accounts Payable | G49: N/A | H49: N/A | I49: N/A | J49: N/A | K49: N/A | L49: N/A | M49: 0 | N49: 2.109 | O49: 3.756 | P49: 1.465 | Q49: 0.815 | R49: =IFERROR((Q49/N49)^(1/COUNT($N$4:$Q$4))-1,"") -> -0.21155708
B50: Short-Term Debt | G50: N/A | H50: N/A | I50: N/A | J50: N/A | K50: N/A | L50: N/A | M50: 0 | N50: 1.687 | O50: 1.953 | P50: 1.374 | Q50: 1.86 | R50: =IFERROR((Q50/N50)^(1/COUNT($N$4:$Q$4))-1,"") -> 0.024706439
B51: Short-Term Borrowings | G51: N/A | H51: N/A | I51: N/A | J51: N/A | K51: N/A | L51: N/A | M51: 0 | N51: 0 | O51: 0.42 | P51: 0 | Q51: 0 | R51: =IFERROR((Q51/N51)^(1/COUNT($N$4:$Q$4))-1,"")
B52: Current Portion of Lease Liabilities | G52: N/A | H52: N/A | I52: N/A | J52: N/A | K52: N/A | L52: N/A | M52: 0 | N52: 1.687 | O52: 1.533 | P52: 1.374 | Q52: 1.512 | R52: =IFERROR((Q52/N52)^(1/COUNT($N$4:$Q$4))-1,"")
B53: Accrued Expenses and Other Current Liabilities | G53: N/A | H53: N/A | I53: N/A | J53: N/A | K53: N/A | L53: N/A | M53: 0 | N53: 8.339 | O53: 12.284 | P53: 9.785 | Q53: 29.33 | R53: =IFERROR((Q53/N53)^(1/COUNT($N$4:$Q$4))-1,"") -> 0.36946054
B54: Current Liabilities | G54: N/A | H54: N/A | I54: N/A | J54: N/A | K54: N/A | L54: N/A | M54: 0.27 | N54: 10.295 | O54: 16.04 | P54: 11.25 | Q54: 30.145 | R54: =IFERROR((Q54/N54)^(1/COUNT($N$4:$Q$4))-1,"") -> 0.30811894
B55: Long-Term Debt | G55: N/A | H55: N/A | I55: N/A | J55: N/A | K55: N/A | L55: N/A | M55: 0 | N55: 6.99 | O55: 9.193 | P55: 8.658 | Q55: 36.517 | R55: =IFERROR((Q55/N55)^(1/COUNT($N$4:$Q$4))-1,"") -> 0.51183529
B56: Long-Term Borrowings | G56: N/A | H56: N/A | I56: N/A | J56: N/A | K56: N/A | L56: N/A | M56: 0 | N56: 0 | O56: 1.892 | P56: 1.63 | Q56: 69.875 | R56: =IFERROR((Q56/N56)^(1/COUNT($N$4:$Q$4))-1,"")
B57: Long-Term Operating Lease Liabilities | G57: N/A | H57: N/A | I57: N/A | J57: N/A | K57: N/A | L57: N/A | M57: 0 | N57: 6.99 | O57: 7.301 | P57: 7.028 | Q57: 0.6389 | R57: =IFERROR((Q57/N57)^(1/COUNT($N$4:$Q$4))-1,"") -> -0.45015671
B58: Other Non-Current Liabilities | G58: N/A | H58: N/A | I58: N/A | J58: N/A | K58: N/A | L58: N/A | M58: 0 | N58: 12.305 | O58: 31.177 | P58: 63.929 | Q58: 30.798 | R58: =IFERROR((Q58/N58)^(1/COUNT($N$4:$Q$4))-1,"") -> 0.25779604
B59: Non-Current Liabilities | G59: N/A | H59: N/A | I59: N/A | J59: N/A | K59: N/A | L59: N/A | M59: 10.5 | N59: 19.295 | O59: 40.37 | P59: 72.587 | Q59: 107.062 | R59: =IFERROR((Q59/N59)^(1/COUNT($N$4:$Q$4))-1,"") -> 0.53478534
B60: Total Liabilities | G60: N/A | H60: N/A | I60: N/A | J60: N/A | K60: N/A | L60: N/A | M60: 10.77 | N60: 29.59 | O60: 56.41 | P60: 83.837 | Q60: 137.207 | R60: =IFERROR((Q60/N60)^(1/COUNT($N$4:$Q$4))-1,"") -> 0.46743146
B61: Shareholder's Equity | G61: N/A | H61: N/A | I61: N/A | J61: N/A | K61: N/A | L61: N/A | M61: 290.762 | N61: 3.02 | O61: -29.463 | P61: -24.481 | Q61: 62.646 | R61: =IFERROR((Q61/N61)^(1/COUNT($N$4:$Q$4))-1,"") -> 1.1341336
B62: Non-Controlling Interest | G62: N/A | H62: N/A | I62: N/A | J62: N/A | K62: N/A | L62: N/A | M62: 0 | N62: 0 | O62: 0 | P62: 0 | Q62: 0
A64: x | B64: Cash Flow | G64: 2014 | H64: =+G64+1 -> 2015 | I64: =+H64+1 -> 2016 | J64: =+I64+1 -> 2017 | K64: =+J64+1 -> 2018 | L64: =+K64+1 -> 2019 | M64: =+L64+1 -> 2020 | N64: =+M64+1 -> 2021 | O64: =+N64+1 -> 2022 | ... Q64: =+P64+1 -> 2024 | R64: ="CAGR "&$N$4&" - "&$Q$4 -> CAGR 2021 - 2024
B66: Net Income | G66: =G24 -> N/A | H66: =H24 -> N/A | I66: =I24 -> N/A | J66: =J24 -> N/A | K66: =K24 -> N/A | L66: =L24 -> N/A | M66: =M24 -> N/A | N66: =N24 -> -31.545 | ... Q66: =Q24 -> -143.879 | R66: =IFERROR((Q66/N66)^(1/COUNT($G$4:$N$4))-1,"") -> 0.20888047
B67: D&A (Depreciation and Amortization) | G67: =+G13 -> N/A | H67: =+H13 -> N/A | I67: =+I13 -> N/A | J67: =+J13 -> N/A | K67: =+K13 -> N/A | L67: =+L13 -> N/A | M67: =+M13 -> N/A | N67: =+N13 -> 2.602 | ... Q67: =+Q13 -> 1.932 | R67: =IFERROR((Q67/N67)^(1/COUNT($G$4:$N$4))-1,"") -> -0.036531592
B68: Changes in Net Working Capital | G68: N/A | H68: N/A | I68: N/A | J68: N/A | K68: N/A | L68: N/A | M68: N/A | N68: -1.185 | O68: 3.022 | P68: -2.698 | Q68: 20.862 | R68: =IFERROR((Q68/N68)^(1/COUNT($G$4:$N$4))-1,"")
B69: (Increase) Decrease in Accounts Receivable | G69: N/A | H69: N/A | I69: N/A | J69: N/A | K69: N/A | L69: N/A | M69: N/A | N69: 0.163 | O69: -0.337 | P69: -0.818 | Q69: 0.137
B70: (Increase) Decrease in Inventories | G70: N/A | H70: N/A | I70: N/A | J70: N/A | K70: N/A | L70: N/A | M70: N/A | N70: 0.182 | O70: -0.148 | P70: -0.237 | Q70: -0.215
B71: Increase (Decrease) in Accounts Payable | G71: N/A | H71: N/A | I71: N/A | J71: N/A | K71: N/A | L71: N/A | M71: N/A | N71: -0.379 | O71: 3.597 | P71: -2.614 | Q71: -0.57
B72: Increase (Decrease) in Other | G72: N/A | H72: N/A | I72: N/A | J72: N/A | K72: N/A | L72: N/A | M72: N/A | N72: -0,100 | O72: -5442 | P72: 1222 | Q72: 88793
B73: Stock Based Compensation | G73: N/A | H73: N/A | I73: N/A | J73: N/A | K73: N/A | L73: N/A | M73: N/A | N73: 1.739 | O73: 9.164 | P73: 21.919 | Q73: 15.661
B74: Other Operating Adjustments | G74: N/A | H74: N/A | I74: N/A | J74: N/A | K74: N/A | L74: N/A | M74: N/A | N74: =+N75-N66-N67-N68-N73 -> -6.411 | O74: =+O75-O66-O67-O68-O73 -> -6.043 | P74: =+P75-P66-P67-P68-P73 -> 1 | Q74: =+Q75-Q66-Q67-Q68-Q73 -> 62.781 | R74: =IFERROR((Q74/N74)^(1/COUNT($G$4:$N$4))-1,"")
B75: Operating Cash Flow | G75: N/A | H75: N/A | I75: N/A | J75: N/A | K75: N/A | L75: N/A | M75: N/A | N75: -34.8 | O75: -45.226 | P75: -60.649 | Q75: -42.643 | R75: =IFERROR((Q75/N75)^(1/COUNT($G$4:$N$4))-1,"") -> 0.025731194
B76: Net Capex | G76: N/A | H76: N/A | I76: N/A | J76: N/A | K76: N/A | L76: N/A | M76: N/A | N76: =+SUM(N77:N78) -> -1.774 | O76: =+SUM(O77:O78) -> -0.423 | P76: =+SUM(P77:P78) -> -0.583 | Q76: =+SUM(Q77:Q78) -> -2.395 | R76: =IFERROR((Q76/N76)^(1/COUNT($G$4:$N$4))-1,"") -> 0.03823099
B77: Acquisition of Fixed & Intangibles | G77: N/A | H77: N/A | I77: N/A | J77: N/A | K77: N/A | L77: N/A | M77: N/A | N77: -1.774 | O77: -0.423 | P77: -0.583 | Q77: -2.395 | R77: =IFERROR((Q77/N77)^(1/COUNT($G$4:$N$4))-1,"") -> 0.03823099
B78: Disposal of Fixed & Intangibles | G78: N/A | H78: N/A | I78: N/A | J78: N/A | K78: N/A | L78: N/A | M78: N/A | N78: 0 | O78: 0 | P78: 0 | Q78: 0 | R78: =IFERROR((Q78/N78)^(1/COUNT($G$4:$N$4))-1,"")
B79: Net Cash from Investments & Acquisitions | G79: =+SUM(G80:G83) -> 0 | H79: =+SUM(H80:H83) -> 0 | I79: =+SUM(I80:I83) -> 0 | J79: =+SUM(J80:J83) -> 0 | K79: =+SUM(K80:K83) -> 0 | L79: =+SUM(L80:L83) -> 0 | M79: =+SUM(M80:M83) -> 0 | N79: =+SUM(N80:N83) -> 0 | ... Q79: =+SUM(Q80:Q83) -> -1 | R79: =IFERROR((Q79/N79)^(1/COUNT($G$4:$N$4))-1,"")
B80: Acquisitions | G80: N/A | H80: N/A | I80: N/A | J80: N/A | K80: N/A | L80: N/A | M80: N/A | N80: 0 | O80: 0 | P80: 0 | Q80: 0 | R80: =IFERROR((Q80/N80)^(1/COUNT($G$4:$N$4))-1,"")
B81: Divestitures | G81: N/A | H81: N/A | I81: N/A | J81: N/A | K81: N/A | L81: N/A | M81: N/A | N81: 0 | O81: 0 | P81: 0 | Q81: 0 | R81: =IFERROR((Q81/N81)^(1/COUNT($G$4:$N$4))-1,"")
B82: Increase in LT Investment | G82: N/A | H82: N/A | I82: N/A | J82: N/A | K82: N/A | L82: N/A | M82: N/A | N82: 0 | O82: 0 | P82: 0 | Q82: -1 | R82: =IFERROR((Q82/N82)^(1/COUNT($G$4:$N$4))-1,"")
B83: Decrease in LT Investment | G83: N/A | H83: N/A | I83: N/A | J83: N/A | K83: N/A | L83: N/A | M83: N/A | N83: 0 | O83: 0 | P83: 0 | Q83: 0 | R83: =IFERROR((Q83/N83)^(1/COUNT($G$4:$N$4))-1,"")
B84: Other Investing Inflows (Outflows) | G84: N/A | H84: N/A | I84: N/A | J84: N/A | K84: N/A | L84: N/A | M84: N/A | N84: =+N85-N76-N79 -> -0.225 | O84: =+O85-O76-O79 -> -0.075 | P84: =+P85-P76-P79 -> -0.047 | Q84: =+Q85-Q76-Q79 -> 0.254 | R84: =IFERROR((Q84/N84)^(1/COUNT($G$4:$N$4))-1,"")
B85: Investing Cash Flow | G85: N/A | H85: N/A | I85: N/A | J85: N/A | K85: N/A | L85: N/A | M85: N/A | N85: -1.999 | O85: -0.498 | P85: -0.63 | Q85: -3.141 | R85: =IFERROR((Q85/N85)^(1/COUNT($G$4:$N$4))-1,"") -> 0.058112617
B86: Debt Borrowing | G86: N/A | H86: N/A | I86: N/A | J86: N/A | K86: N/A | L86: N/A | M86: N/A | N86: 25.258 | O86: 23.159 | P86: 32.003 | Q86: 0 | R86: =IFERROR((Q86/N86)^(1/COUNT($G$4:$N$4))-1,"") -> -1
B87: Debt Repayment | G87: N/A | H87: N/A | I87: N/A | J87: N/A | K87: N/A | L87: N/A | M87: N/A | N87: -0.031 | O87: -21.511 | P87: -1.885 | Q87: -30.37 | R87: =IFERROR((Q87/N87)^(1/COUNT($G$4:$N$4))-1,"") -> 1.3652954
B88: Lease Payments | G88: N/A | H88: N/A | I88: N/A | J88: N/A | K88: N/A | L88: N/A | M88: N/A | N88: 0 | O88: 0 | P88: 0 | Q88: 0 | R88: =IFERROR((Q88/N88)^(1/COUNT($G$4:$N$4))-1,"")
B89: Dividends | G89: N/A | H89: N/A | I89: N/A | J89: N/A | K89: N/A | L89: N/A | M89: N/A | N89: 0 | O89: 0 | P89: 0 | Q89: 0 | R89: =IFERROR((Q89/N89)^(1/COUNT($G$4:$N$4))-1,"")
B90: Increase (Repurchase) of Shares | G90: N/A | H90: N/A | I90: N/A | J90: N/A | K90: N/A | L90: N/A | M90: N/A | N90: 0 | O90: 40 | P90: 63.676 | Q90: 214.191 | R90: =IFERROR((Q90/N90)^(1/COUNT($G$4:$N$4))-1,"")
B91: Other Financing Inflows (Outflows) | G91: N/A | H91: N/A | I91: N/A | J91: N/A | K91: N/A | L91: N/A | M91: N/A | N91: =+N92-N86-N87-N88-N89-N90 -> -0.314 | O91: =+O92-O86-O87-O88-O89-O90 -> 1.617 | P91: =+P92-P86-P87-P88-P89-P90 -> 1.842 | Q91: =+Q92-Q86-Q87-Q88-Q89-Q90 -> -1.371 | R91: =IFERROR((Q91/N91)^(1/COUNT($G$4:$N$4))-1,"") -> 0.20230174
B92: Financing Cash Flow | G92: N/A | H92: N/A | I92: N/A | J92: N/A | K92: N/A | L92: N/A | M92: N/A | N92: 24.913 | O92: 43.265 | P92: 95.636 | Q92: 182.45 | R92: =IFERROR((Q92/N92)^(1/COUNT($G$4:$N$4))-1,"") -> 0.28259555
B93: Effect of Foreign Exchange | G93: N/A | H93: N/A | I93: N/A | J93: N/A | K93: N/A | L93: N/A | M93: N/A | N93: 0.034 | O93: 0.041 | P93: -0.115 | Q93: 0.007 | R93: =IFERROR((Q93/N93)^(1/COUNT($G$4:$N$4))-1,"") -> -0.17926607
B94: Net Changes in Cash | G94: N/A | H94: N/A | I94: N/A | J94: N/A | K94: N/A | L94: N/A | M94: N/A | N94: -11.852 | O94: -2.418 | P94: 34.242 | Q94: 136.673 | R94: =IFERROR((Q94/N94)^(1/COUNT($G$4:$N$4))-1,"")
B95: in billionsof USD
A96: x | B96: Capital Structure | G96: 42004 | H96: 42369 | I96: 42735 | J96: 43100 | K96: 43465 | L96: 43830 | M96: 44196 | N96: 44561 | O96: 44926 | P96: 45291 | Q96: 45657
B98: Market Capitalization | G98: N/A | H98: N/A | I98: N/A | J98: N/A | K98: N/A | L98: N/A | M98: N/A | N98: {=(IFERROR(_xlfn.STOCKHISTORY("QBTS", N96, N96, 0, 0, 1), IFERROR(_xlfn.STOCKHISTORY("QBTS", N96+1, N96+1, 0, 0, 1), _xlfn.STOCKHISTORY("QBTS", N96-2, N96-2, 0, 0, 1))))*_xlfn.XLOOKUP("Basic Weighted Average Shares",$B:$B,N:N)} -> 1789.8423 | O98: {=(IFERROR(_xlfn.STOCKHISTORY("QBTS", O96, O96, 0, 0, 1), IFERROR(_xlfn.STOCKHISTORY("QBTS", O96+1, O96+1, 0, 0, 1), _xlfn.STOCKHISTORY("QBTS", O96-2, O96-2, 0, 0, 1))))*_xlfn.XLOOKUP("Basic Weighted Average Shares",$B:$B,O:O)} -> 174.68608 | P98: {=(IFERROR(_xlfn.STOCKHISTORY("QBTS", P96, P96, 0, 0, 1), IFERROR(_xlfn.STOCKHISTORY("QBTS", P96+1, P96+1, 0, 0, 1), _xlfn.STOCKHISTORY("QBTS", P96-2, P96-2, 0, 0, 1))))*_xlfn.XLOOKUP("Basic Weighted Average Shares",$B:$B,P:P)} -> 121.44852 | Q98: {=(IFERROR(_xlfn.STOCKHISTORY("QBTS", Q96, Q96, 0, 0, 1), IFERROR(_xlfn.STOCKHISTORY("QBTS", Q96+1, Q96+1, 0, 0, 1), _xlfn.STOCKHISTORY("QBTS", Q96-2, Q96-2, 0, 0, 1))))*_xlfn.XLOOKUP("Basic Weighted Average Shares",$B:$B,Q:Q)} -> 1613.8836
B99: Cash & Cash Equivalents | G99: N/A | H99: N/A | I99: N/A | J99: N/A | K99: N/A | L99: N/A | M99: N/A | N99: =_xlfn.XLOOKUP("Cash & Cash Equivalents & ST Investments",$B$30:$B$62,N$30:N$62) -> 9.483 | O99: =_xlfn.XLOOKUP("Cash & Cash Equivalents & ST Investments",$B$30:$B$62,O$30:O$62) -> 7.065 | P99: =_xlfn.XLOOKUP("Cash & Cash Equivalents & ST Investments",$B$30:$B$62,P$30:P$62) -> 41.307 | Q99: =_xlfn.XLOOKUP("Cash & Cash Equivalents & ST Investments",$B$30:$B$62,Q$30:Q$62) -> 177.98
B100: Total Debt | G100: N/A | H100: N/A | I100: N/A | J100: N/A | K100: N/A | L100: N/A | M100: N/A | N100: =(_xlfn.XLOOKUP("Short-Term Debt",$B$30:$B$62,N$30:N$62)+_xlfn.XLOOKUP("Long-Term Debt",$B$30:$B$62,N$30:N$62)) -> 8.677 | O100: =(_xlfn.XLOOKUP("Short-Term Debt",$B$30:$B$62,O$30:O$62)+_xlfn.XLOOKUP("Long-Term Debt",$B$30:$B$62,O$30:O$62)) -> 11.146 | P100: =(_xlfn.XLOOKUP("Short-Term Debt",$B$30:$B$62,P$30:P$62)+_xlfn.XLOOKUP("Long-Term Debt",$B$30:$B$62,P$30:P$62)) -> 10.032 | Q100: =(_xlfn.XLOOKUP("Short-Term Debt",$B$30:$B$62,Q$30:Q$62)+_xlfn.XLOOKUP("Long-Term Debt",$B$30:$B$62,Q$30:Q$62)) -> 38.377
B101: Preferred Stock | G101: N/A | H101: N/A | I101: N/A | J101: N/A | K101: N/A | L101: N/A | M101: N/A
B102: Non-Controlling Interest | G102: N/A | H102: N/A | I102: N/A | J102: N/A | K102: N/A | L102: N/A | M102: N/A | N102: =_xlfn.XLOOKUP("Non-Controlling Interest",$B$30:$B$62,N$30:N$62) -> 0 | O102: =_xlfn.XLOOKUP("Non-Controlling Interest",$B$30:$B$62,O$30:O$62) -> 0 | P102: =_xlfn.XLOOKUP("Non-Controlling Interest",$B$30:$B$62,P$30:P$62) -> 0 | Q102: =_xlfn.XLOOKUP("Non-Controlling Interest",$B$30:$B$62,Q$30:Q$62) -> 0
B103: Enterprise Value | G103: N/A | H103: N/A | I103: N/A | J103: N/A | K103: N/A | L103: N/A | M103: N/A | N103: =+N98-N99+N100+N101+N102 -> 1789.0363 | O103: =+O98-O99+O100+O101+O102 -> 178.76708 | P103: =+P98-P99+P100+P101+P102 -> 90.173519 | Q103: =+Q98-Q99+Q100+Q101+Q102 -> 1474.2806
A105: x | B105: Debt Schedule | G105: Cash | H105: 2025 | I105: =+H105+1 -> 2026 | J105: =+I105+1 -> 2027 | K105: =+J105+1 -> 2028 | L105: =+K105+1 -> 2029 | M105: =+L105+1 -> 2030 | N105: =+M105+1 -> 2031 | O105: =+N105+1 -> 2032 | P105: =+O105+1 -> 2033 | Q105: =+P105+1 -> 2034
L106: v | M106: v | N106: v | O106: v | P106: v | Q106: v
B107: Cash
B108: Fixed
...

Sheet WACC
B2: WACC
B4: WACC = % of Equity x Cost of Equity + % de Debt x Cost of Debt x (1 - Tax Rate)
B5: Cost of Equity = Risk-Free Rate + Beta x Equity Risk Premium
B7: WACC | I7: Region | J7: Weight | K7: ERP | M7: Peers | N7: Beta (Unlevered)
B9: Market Cap (in millions) | G9: {=+_FV(DCF!R4,"Market cap",TRUE)/1000000} -> 8447.852 | I9: =Segments!B6 -> United States | J9: =Segments!D6 -> 0.24368415 | K9: 0.0433 | M9: =+Peers!B8 -> IONQ INC. | N9: =+Peers!E75 -> 2.4885883
B10: % of Equity | G10: =IFERROR(G9/G23,"") -> 0.99547773 | I10: =Segments!B7 -> Germany | J10: =Segments!D7 -> 0.21456894 | K10: 0.0433 | M10: =+Peers!B9 -> RIGETTI COMPUTING INC. | N10: =+Peers!F75 -> 1.4785188
B11: Cost of Equity | G11: =IFERROR(G12+G14*G15,"") -> 0.073209157 | I11: =Segments!B8 -> Japan | J11: =Segments!D8 -> 0.12835618 | K11: 0.0527 | M11: =+Peers!B10 -> QUANTUM COMPUTING INC. | N11: =+Peers!G75 -> 3.8235113
B12: Risk-Free Rate | G12: 0.0326 | I12: =Segments!B9 -> Canada | J12: =Segments!D9 -> 0.12473094 | K12: 0.0433 | M12: =+Peers!B11 | N12: =+Peers!H75
B13: Unlevered Beta | G13: =+N19 -> 2.5968728 | M13: =+Peers!B12 | N13: =+Peers!I75
B14: Beta | G14: =0.86 -> 0.86 | I14: Others | J14: =1-SUM(J9:J13) -> 0.28865979 | K14: =MAX(K9:K13) -> 0.0527 | M14: =+Peers!B13 | N14: =+Peers!J75
B15: Equity Risk Premium | G15: =SUMPRODUCT(J9:J14,K9:K14) -> 0.04721995 | M15: =+Peers!B14 | N15: =+Peers!K75
B16: Cost of Equity | G16: =IFERROR(+G12+G14*G15,"") -> 0.073209157 | M16: =+Peers!B15 | N16: =+Peers!L75
M17: =+Peers!B16 | N17: =+Peers!M75
B18: Debt (in millions) | G18: =Inputs!Q113 -> 38.377 | M18: =+Peers!B17 | N18: =+Peers!N75
B19: % of Debt | G19: =IFERROR(G18/G23,"") -> 0.0045222678 | M19: Average | N19: =IFERROR(+AVERAGEIF(N9:N18,">0"),"") -> 2.5968728
B20: Cost of debt | G20: 0.05011
B21: Tax Rate | G21: =+DCF!H77 -> 0
B23: Total | G23: =+G9+G18 -> 8486.229
B25: WACC | G25: =IFERROR(G10*G11+G19*G20,"") -> 0.073104697
B26: WACC with Tax Rate | G26: =IFERROR(G10*G11+G19*G20*(1-G21),"") -> 0.073104697

Sheet Multiples
B2: Multiples
B4: Valuation | F4: 2014 | G4: =+F4+1 -> 2015 | H4: =+G4+1 -> 2016 | I4: =+H4+1 -> 2017 | J4: =+I4+1 -> 2018 | K4: =+J4+1 -> 2019 | L4: =+K4+1 -> 2020 | M4: =+L4+1 -> 2021 | N4: 2022 | O4: =+N4+1 -> 2023 | P4: =+O4+1 -> 2024 | Q4: =+P4+1 -> 2025 | R4: =+Q4+1 -> 2026
B6: EV / Sales | F6: =IFERROR(_xlfn.XLOOKUP("Enterprise Value",Inputs!$B:$B,Inputs!G:G)/_xlfn.XLOOKUP("Revenue (Sales)",Inputs!$B:$B,Inputs!G:G),"") | G6: =IFERROR(_xlfn.XLOOKUP("Enterprise Value",Inputs!$B:$B,Inputs!H:H)/_xlfn.XLOOKUP("Revenue (Sales)",Inputs!$B:$B,Inputs!H:H),"") | H6: =IFERROR(_xlfn.XLOOKUP("Enterprise Value",Inputs!$B:$B,Inputs!I:I)/_xlfn.XLOOKUP("Revenue (Sales)",Inputs!$B:$B,Inputs!I:I),"") | I6: =IFERROR(_xlfn.XLOOKUP("Enterprise Value",Inputs!$B:$B,Inputs!J:J)/_xlfn.XLOOKUP("Revenue (Sales)",Inputs!$B:$B,Inputs!J:J),"") | J6: =IFERROR(_xlfn.XLOOKUP("Enterprise Value",Inputs!$B:$B,Inputs!K:K)/_xlfn.XLOOKUP("Revenue (Sales)",Inputs!$B:$B,Inputs!K:K),"") | K6: =IFERROR(_xlfn.XLOOKUP("Enterprise Value",Inputs!$B:$B,Inputs!L:L)/_xlfn.XLOOKUP("Revenue (Sales)",Inputs!$B:$B,Inputs!L:L),"") | L6: =IFERROR(_xlfn.XLOOKUP("Enterprise Value",Inputs!$B:$B,Inputs!M:M)/_xlfn.XLOOKUP("Revenue (Sales)",Inputs!$B:$B,Inputs!M:M),"") | M6: =IFERROR(_xlfn.XLOOKUP("Enterprise Value",Inputs!$B:$B,Inputs!N:N)/_xlfn.XLOOKUP("Revenue (Sales)",Inputs!$B:$B,Inputs!N:N),"") -> 284.92376 | N6: =IFERROR(_xlfn.XLOOKUP("Enterprise Value",Inputs!$B:$B,Inputs!O:O)/_xlfn.XLOOKUP("Revenue (Sales)",Inputs!$B:$B,Inputs!O:O),"") -> 24.922219 | O6: =IFERROR(_xlfn.XLOOKUP("Enterprise Value",Inputs!$B:$B,Inputs!P:P)/_xlfn.XLOOKUP("Revenue (Sales)",Inputs!$B:$B,Inputs!P:P),"") -> 10.296131 | P6: =IFERROR(_xlfn.XLOOKUP("Enterprise Value",Inputs!$B:$B,Inputs!Q:Q)/_xlfn.XLOOKUP("Revenue (Sales)",Inputs!$B:$B,Inputs!Q:Q),"") -> 167.01944 | Q6: =IFERROR(_xlfn.XLOOKUP("Enterprise Value",DCF!$B:$B,DCF!R:R)/_xlfn.XLOOKUP("Revenue (Sales)",DCF!$B:$B,DCF!H:H),"") -> 816.67187 | R6: =IFERROR(_xlfn.XLOOKUP("Enterprise Value",DCF!$B:$B,DCF!S:S)/_xlfn.XLOOKUP("Revenue (Sales)",DCF!$B:$B,DCF!I:I),"") -> 1811.9274
B7: Price / Sales | F7: =IFERROR(_xlfn.XLOOKUP("Market Capitalization",Inputs!$B:$B,Inputs!G:G)/_xlfn.XLOOKUP("Revenue (Sales)",Inputs!$B:$B,Inputs!G:G),"") | G7: =IFERROR(_xlfn.XLOOKUP("Market Capitalization",Inputs!$B:$B,Inputs!H:H)/_xlfn.XLOOKUP("Revenue (Sales)",Inputs!$B:$B,Inputs!H:H),"") | H7: =IFERROR(_xlfn.XLOOKUP("Market Capitalization",Inputs!$B:$B,Inputs!I:I)/_xlfn.XLOOKUP("Revenue (Sales)",Inputs!$B:$B,Inputs!I:I),"") | I7: =IFERROR(_xlfn.XLOOKUP("Market Capitalization",Inputs!$B:$B,Inputs!J:J)/_xlfn.XLOOKUP("Revenue (Sales)",Inputs!$B:$B,Inputs!J:J),"") | J7: =IFERROR(_xlfn.XLOOKUP("Market Capitalization",Inputs!$B:$B,Inputs!K:K)/_xlfn.XLOOKUP("Revenue (Sales)",Inputs!$B:$B,Inputs!K:K),"") | K7: =IFERROR(_xlfn.XLOOKUP("Market Capitalization",Inputs!$B:$B,Inputs!L:L)/_xlfn.XLOOKUP("Revenue (Sales)",Inputs!$B:$B,Inputs!L:L),"") | L7: =IFERROR(_xlfn.XLOOKUP("Market Capitalization",Inputs!$B:$B,Inputs!M:M)/_xlfn.XLOOKUP("Revenue (Sales)",Inputs!$B:$B,Inputs!M:M),"") | M7: =IFERROR(_xlfn.XLOOKUP("Market Capitalization",Inputs!$B:$B,Inputs!N:N)/_xlfn.XLOOKUP("Revenue (Sales)",Inputs!$B:$B,Inputs!N:N),"") -> 285.05213 | N7: =IFERROR(_xlfn.XLOOKUP("Market Capitalization",Inputs!$B:$B,Inputs!O:O)/_xlfn.XLOOKUP("Revenue (Sales)",Inputs!$B:$B,Inputs!O:O),"") -> 24.35328 | O7: =IFERROR(_xlfn.XLOOKUP("Market Capitalization",Inputs!$B:$B,Inputs!P:P)/_xlfn.XLOOKUP("Revenue (Sales)",Inputs!$B:$B,Inputs!P:P),"") -> 13.867152 | P7: =IFERROR(_xlfn.XLOOKUP("Market Capitalization",Inputs!$B:$B,Inputs!Q:Q)/_xlfn.XLOOKUP("Revenue (Sales)",Inputs!$B:$B,Inputs!Q:Q),"") -> 182.83489 | Q7: =IFERROR(_xlfn.XLOOKUP("Equity Value",DCF!$B:$B,DCF!R:R)/_xlfn.XLOOKUP("Revenue (Sales)",DCF!$B:$B,DCF!H:H),"") -> 0 | R7: =IFERROR(_xlfn.XLOOKUP("Equity Value",DCF!$B:$B,DCF!S:S)/_xlfn.XLOOKUP("Revenue (Sales)",DCF!$B:$B,DCF!I:I),"") -> 0
B8: EV / EBITDA | F8: =IFERROR(_xlfn.XLOOKUP("Enterprise Value",Inputs!$B:$B,Inputs!G:G)/_xlfn.XLOOKUP("EBITDA",Inputs!$B:$B,Inputs!G:G),"") | G8: =IFERROR(_xlfn.XLOOKUP("Enterprise Value",Inputs!$B:$B,Inputs!H:H)/_xlfn.XLOOKUP("EBITDA",Inputs!$B:$B,Inputs!H:H),"") | H8: =IFERROR(_xlfn.XLOOKUP("Enterprise Value",Inputs!$B:$B,Inputs!I:I)/_xlfn.XLOOKUP("EBITDA",Inputs!$B:$B,Inputs!I:I),"") | I8: =IFERROR(_xlfn.XLOOKUP("Enterprise Value",Inputs!$B:$B,Inputs!J:J)/_xlfn.XLOOKUP("EBITDA",Inputs!$B:$B,Inputs!J:J),"") | J8: =IFERROR(_xlfn.XLOOKUP("Enterprise Value",Inputs!$B:$B,Inputs!K:K)/_xlfn.XLOOKUP("EBITDA",Inputs!$B:$B,Inputs!K:K),"") | K8: =IFERROR(_xlfn.XLOOKUP("Enterprise Value",Inputs!$B:$B,Inputs!L:L)/_xlfn.XLOOKUP("EBITDA",Inputs!$B:$B,Inputs!L:L),"") | L8: =IFERROR(_xlfn.XLOOKUP("Enterprise Value",Inputs!$B:$B,Inputs!M:M)/_xlfn.XLOOKUP("EBITDA",Inputs!$B:$B,Inputs!M:M),"") | M8: =IFERROR(_xlfn.XLOOKUP("Enterprise Value",Inputs!$B:$B,Inputs!N:N)/_xlfn.XLOOKUP("EBITDA",Inputs!$B:$B,Inputs!N:N),"") -> -49.222371 | N8: =IFERROR(_xlfn.XLOOKUP("Enterprise Value",Inputs!$B:$B,Inputs!O:O)/_xlfn.XLOOKUP("EBITDA",Inputs!$B:$B,Inputs!O:O),"") -> -3.1294018 | O8: =IFERROR(_xlfn.XLOOKUP("Enterprise Value",Inputs!$B:$B,Inputs!P:P)/_xlfn.XLOOKUP("EBITDA",Inputs!$B:$B,Inputs!P:P),"") -> -1.1955706 | P8: =IFERROR(_xlfn.XLOOKUP("Enterprise Value",Inputs!$B:$B,Inputs!Q:Q)/_xlfn.XLOOKUP("EBITDA",Inputs!$B:$B,Inputs!Q:Q),"") -> -21.275732 | Q8: =IFERROR(_xlfn.XLOOKUP("Enterprise Value",DCF!$B:$B,DCF!R:R)/_xlfn.XLOOKUP("EBITDA",DCF!$B:$B,DCF!H:H),"") -> -139.41592 | R8: =IFERROR(_xlfn.XLOOKUP("Enterprise Value",DCF!$B:$B,DCF!S:S)/_xlfn.XLOOKUP("EBITDA",DCF!$B:$B,DCF!I:I),"") -> -390.87
B9: EV / EBIT | F9: =IFERROR(_xlfn.XLOOKUP("Enterprise Value",Inputs!$B:$B,Inputs!G:G)/_xlfn.XLOOKUP("Operating Income (EBIT)",Inputs!$B:$B,Inputs!G:G),"") | G9: =IFERROR(_xlfn.XLOOKUP("Enterprise Value",Inputs!$B:$B,Inputs!H:H)/_xlfn.XLOOKUP("Operating Income (EBIT)",Inputs!$B:$B,Inputs!H:H),"") | H9: =IFERROR(_xlfn.XLOOKUP("Enterprise Value",Inputs!$B:$B,Inputs!I:I)/_xlfn.XLOOKUP("Operating Income (EBIT)",Inputs!$B:$B,Inputs!I:I),"") | I9: =IFERROR(_xlfn.XLOOKUP("Enterprise Value",Inputs!$B:$B,Inputs!J:J)/_xlfn.XLOOKUP("Operating Income (EBIT)",Inputs!$B:$B,Inputs!J:J),"") | J9: =IFERROR(_xlfn.XLOOKUP("Enterprise Value",Inputs!$B:$B,Inputs!K:K)/_xlfn.XLOOKUP("Operating Income (EBIT)",Inputs!$B:$B,Inputs!K:K),"") | K9: =IFERROR(_xlfn.XLOOKUP("Enterprise Value",Inputs!$B:$B,Inputs!L:L)/_xlfn.XLOOKUP("Operating Income (EBIT)",Inputs!$B:$B,Inputs!L:L),"") | L9: =IFERROR(_xlfn.XLOOKUP("Enterprise Value",Inputs!$B:$B,Inputs!M:M)/_xlfn.XLOOKUP("Operating Income (EBIT)",Inputs!$B:$B,Inputs!M:M),"") | M9: =IFERROR(_xlfn.XLOOKUP("Enterprise Value",Inputs!$B:$B,Inputs!N:N)/_xlfn.XLOOKUP("Operating Income (EBIT)",Inputs!$B:$B,Inputs!N:N),"") -> -45.933971 | N9: =IFERROR(_xlfn.XLOOKUP("Enterprise Value",Inputs!$B:$B,Inputs!O:O)/_xlfn.XLOOKUP("Operating Income (EBIT)",Inputs!$B:$B,Inputs!O:O),"") -> 22.345885 | O9: =IFERROR(_xlfn.XLOOKUP("Enterprise Value",Inputs!$B:$B,Inputs!P:P)/_xlfn.XLOOKUP("Operating Income (EBIT)",Inputs!$B:$B,Inputs!P:P),"") -> -1.1670228 | P9: =IFERROR(_xlfn.XLOOKUP("Enterprise Value",Inputs!$B:$B,Inputs!Q:Q)/_xlfn.XLOOKUP("Operating Income (EBIT)",Inputs!$B:$B,Inputs!Q:Q),"") -> -20.255002 | Q9: =IFERROR(_xlfn.XLOOKUP("Enterprise Value",DCF!$B:$B,DCF!R:R)/_xlfn.XLOOKUP("Operating Income (EBIT)",DCF!$B:$B,DCF!H:H),"") -> -139.41592 | R9: =IFERROR(_xlfn.XLOOKUP("Enterprise Value",DCF!$B:$B,DCF!S:S)/_xlfn.XLOOKUP("Operating Income (EBIT)",DCF!$B:$B,DCF!I:I),"") -> -390.87
B10: Price / Earnings | F10: =IFERROR(_xlfn.XLOOKUP("Market Capitalization",Inputs!$B:$B,Inputs!G:G)/_xlfn.XLOOKUP("Net Income",Inputs!$B:$B,Inputs!G:G),"") | G10: =IFERROR(_xlfn.XLOOKUP("Market Capitalization",Inputs!$B:$B,Inputs!H:H)/_xlfn.XLOOKUP("Net Income",Inputs!$B:$B,Inputs!H:H),"") | H10: =IFERROR(_xlfn.XLOOKUP("Market Capitalization",Inputs!$B:$B,Inputs!I:I)/_xlfn.XLOOKUP("Net Income",Inputs!$B:$B,Inputs!I:I),"") | I10: =IFERROR(_xlfn.XLOOKUP("Market Capitalization",Inputs!$B:$B,Inputs!J:J)/_xlfn.XLOOKUP("Net Income",Inputs!$B:$B,Inputs!J:J),"") | J10: =IFERROR(_xlfn.XLOOKUP("Market Capitalization",Inputs!$B:$B,Inputs!K:K)/_xlfn.XLOOKUP("Net Income",Inputs!$B:$B,Inputs!K:K),"") | K10: =IFERROR(_xlfn.XLOOKUP("Market Capitalization",Inputs!$B:$B,Inputs!L:L)/_xlfn.XLOOKUP("Net Income",Inputs!$B:$B,Inputs!L:L),"") | L10: =IFERROR(_xlfn.XLOOKUP("Market Capitalization",Inputs!$B:$B,Inputs!M:M)/_xlfn.XLOOKUP("Net Income",Inputs!$B:$B,Inputs!M:M),"") | M10: =IFERROR(_xlfn.XLOOKUP("Market Capitalization",Inputs!$B:$B,Inputs!N:N)/_xlfn.XLOOKUP("Net Income",Inputs!$B:$B,Inputs!N:N),"") -> -56.739334 | N10: =IFERROR(_xlfn.XLOOKUP("Market Capitalization",Inputs!$B:$B,Inputs!O:O)/_xlfn.XLOOKUP("Net Income",Inputs!$B:$B,Inputs!O:O),"") -> -3.2528785 | O10: =IFERROR(_xlfn.XLOOKUP("Market Capitalization",Inputs!$B:$B,Inputs!P:P)/_xlfn.XLOOKUP("Net Income",Inputs!$B:$B,Inputs!P:P),"") -> -1.4682768 | P10: =IFERROR(_xlfn.XLOOKUP("Market Capitalization",Inputs!$B:$B,Inputs!Q:Q)/_xlfn.XLOOKUP("Net Income",Inputs!$B:$B,Inputs!Q:Q),"") -> -11.21695 | Q10: =IFERROR(_xlfn.XLOOKUP("Equity Value",DCF!$B:$B,DCF!R:R)/_xlfn.XLOOKUP("Net Income",DCF!$B:$B,DCF!H:H),"") -> 0 | R10: =IFERROR(_xlfn.XLOOKUP("Equity Value",DCF!$B:$B,DCF!S:S)/_xlfn.XLOOKUP("Net Income",DCF!$B:$B,DCF!I:I),"") -> 0
B11: Price / Book | F11: =IFERROR(_xlfn.XLOOKUP("Market Capitalization",Inputs!$B:$B,Inputs!G:G)/_xlfn.XLOOKUP("Shareholder's Equity",Inputs!$B:$B,Inputs!G:G),"") | G11: =IFERROR(_xlfn.XLOOKUP("Market Capitalization",Inputs!$B:$B,Inputs!H:H)/_xlfn.XLOOKUP("Shareholder's Equity",Inputs!$B:$B,Inputs!H:H),"") | H11: =IFERROR(_xlfn.XLOOKUP("Market Capitalization",Inputs!$B:$B,Inputs!I:I)/_xlfn.XLOOKUP("Shareholder's Equity",Inputs!$B:$B,Inputs!I:I),"") | I11: =IFERROR(_xlfn.XLOOKUP("Market Capitalization",Inputs!$B:$B,Inputs!J:J)/_xlfn.XLOOKUP("Shareholder's Equity",Inputs!$B:$B,Inputs!J:J),"") | J11: =IFERROR(_xlfn.XLOOKUP("Market Capitalization",Inputs!$B:$B,Inputs!K:K)/_xlfn.XLOOKUP("Shareholder's Equity",Inputs!$B:$B,Inputs!K:K),"") | K11: =IFERROR(_xlfn.XLOOKUP("Market Capitalization",Inputs!$B:$B,Inputs!L:L)/_xlfn.XLOOKUP("Shareholder's Equity",Inputs!$B:$B,Inputs!L:L),"") | L11: =IFERROR(_xlfn.XLOOKUP("Market Capitalization",Inputs!$B:$B,Inputs!M:M)/_xlfn.XLOOKUP("Shareholder's Equity",Inputs!$B:$B,Inputs!M:M),"") | M11: =IFERROR(_xlfn.XLOOKUP("Market Capitalization",Inputs!$B:$B,Inputs!N:N)/_xlfn.XLOOKUP("Shareholder's Equity",Inputs!$B:$B,Inputs!N:N),"") -> 592.66301 | N11: =IFERROR(_xlfn.XLOOKUP("Market Capitalization",Inputs!$B:$B,Inputs!O:O)/_xlfn.XLOOKUP("Shareholder's Equity",Inputs!$B:$B,Inputs!O:O),"") -> -5.9289984 | O11: =IFERROR(_xlfn.XLOOKUP("Market Capitalization",Inputs!$B:$B,Inputs!P:P)/_xlfn.XLOOKUP("Shareholder's Equity",Inputs!$B:$B,Inputs!P:P),"") -> -4.9609297 | P11: =IFERROR(_xlfn.XLOOKUP("Market Capitalization",Inputs!$B:$B,Inputs!Q:Q)/_xlfn.XLOOKUP("Shareholder's Equity",Inputs!$B:$B,Inputs!Q:Q),"") -> 25.761958 | Q11: =IFERROR(+_xlfn.XLOOKUP("Equity Value",DCF!$B:$B,DCF!R:R)/(_xlfn.XLOOKUP("Shareholder's Equity",Inputs!$B:$B,Inputs!$Q:$Q)+_xlfn.XLOOKUP("Net Income",DCF!$B:$B,DCF!H:H)+_xlfn.XLOOKUP("Total Payout",DCF!$B:$B,DCF!H:H)),"") -> 0 | R11: =IFERROR(+_xlfn.XLOOKUP("Equity Value",DCF!$B:$B,DCF!S:S)/(_xlfn.XLOOKUP("Shareholder's Equity",Inputs!$B:$B,Inputs!$Q:$Q)+_xlfn.XLOOKUP("Net Income",DCF!$B:$B,DCF!I:I)+_xlfn.XLOOKUP("Total Payout",DCF!$B:$B,DCF!I:I)),"") -> 0
B13: Profitability | F13: 2014 | G13: =+F13+1 -> 2015 | H13: =+G13+1 -> 2016 | I13: =+H13+1 -> 2017 | J13: =+I13+1 -> 2018 | K13: =+J13+1 -> 2019 | L13: =+K13+1 -> 2020 | M13: =+L13+1 -> 2021 | N13: 2022 | O13: =+N13+1 -> 2023 | P13: =+O13+1 -> 2024 | Q13: =+P13+1 -> 2025 | R13: =+Q13+1 -> 2026
B15: Return on Assets | F15: =+IFERROR(_xlfn.XLOOKUP("Net Income",Inputs!$B:$B,Inputs!G:G)/_xlfn.XLOOKUP("Total Assets",Inputs!$B:$B,Inputs!G:G),"") | G15: =+IFERROR(_xlfn.XLOOKUP("Net Income",Inputs!$B:$B,Inputs!H:H)/_xlfn.XLOOKUP("Total Assets",Inputs!$B:$B,Inputs!H:H),"") | H15: =+IFERROR(_xlfn.XLOOKUP("Net Income",Inputs!$B:$B,Inputs!I:I)/_xlfn.XLOOKUP("Total Assets",Inputs!$B:$B,Inputs!I:I),"") | I15: =+IFERROR(_xlfn.XLOOKUP("Net Income",Inputs!$B:$B,Inputs!J:J)/_xlfn.XLOOKUP("Total Assets",Inputs!$B:$B,Inputs!J:J),"") | J15: =+IFERROR(_xlfn.XLOOKUP("Net Income",Inputs!$B:$B,Inputs!K:K)/_xlfn.XLOOKUP("Total Assets",Inputs!$B:$B,Inputs!K:K),"") | K15: =+IFERROR(_xlfn.XLOOKUP("Net Income",Inputs!$B:$B,Inputs!L:L)/_xlfn.XLOOKUP("Total Assets",Inputs!$B:$B,Inputs!L:L),"") | L15: =+IFERROR(_xlfn.XLOOKUP("Net Income",Inputs!$B:$B,Inputs!M:M)/_xlfn.XLOOKUP("Total Assets",Inputs!$B:$B,Inputs!M:M),"") | M15: =+IFERROR(_xlfn.XLOOKUP("Net Income",Inputs!$B:$B,Inputs!N:N)/_xlfn.XLOOKUP("Total Assets",Inputs!$B:$B,Inputs!N:N),"") -> -0.96734131 | N15: =+IFERROR(_xlfn.XLOOKUP("Net Income",Inputs!$B:$B,Inputs!O:O)/_xlfn.XLOOKUP("Total Assets",Inputs!$B:$B,Inputs!O:O),"") -> -1.9928749 | O15: =+IFERROR(_xlfn.XLOOKUP("Net Income",Inputs!$B:$B,Inputs!P:P)/_xlfn.XLOOKUP("Total Assets",Inputs!$B:$B,Inputs!P:P),"") -> -1.3935407 | P15: =+IFERROR(_xlfn.XLOOKUP("Net Income",Inputs!$B:$B,Inputs!Q:Q)/_xlfn.XLOOKUP("Total Assets",Inputs!$B:$B,Inputs!Q:Q),"") -> -0.71992414 | Q15: =IFERROR(_xlfn.XLOOKUP("Net Income",DCF!$B:$B,DCF!H:H)/_xlfn.XLOOKUP("Total assets",DCF!$6:$6,DCF!10:10),"") -> -0.49141907 | R15: =IFERROR(_xlfn.XLOOKUP("Net Income",DCF!$B:$B,DCF!I:I)/_xlfn.XLOOKUP("Total assets",DCF!$6:$6,DCF!10:10),"") -> -0.68204232
B16: Return on Equity | F16: =IFERROR(_xlfn.XLOOKUP("Net Income",Inputs!$B:$B,Inputs!G:G)/_xlfn.XLOOKUP("Shareholder's Equity",Inputs!$B:$B,Inputs!G:G),"") | G16: =IFERROR(_xlfn.XLOOKUP("Net Income",Inputs!$B:$B,Inputs!H:H)/_xlfn.XLOOKUP("Shareholder's Equity",Inputs!$B:$B,Inputs!H:H),"") | H16: =IFERROR(_xlfn.XLOOKUP("Net Income",Inputs!$B:$B,Inputs!I:I)/_xlfn.XLOOKUP("Shareholder's Equity",Inputs!$B:$B,Inputs!I:I),"") | I16: =IFERROR(_xlfn.XLOOKUP("Net Income",Inputs!$B:$B,Inputs!J:J)/_xlfn.XLOOKUP("Shareholder's Equity",Inputs!$B:$B,Inputs!J:J),"") | J16: =IFERROR(_xlfn.XLOOKUP("Net Income",Inputs!$B:$B,Inputs!K:K)/_xlfn.XLOOKUP("Shareholder's Equity",Inputs!$B:$B,Inputs!K:K),"") | K16: =IFERROR(_xlfn.XLOOKUP("Net Income",Inputs!$B:$B,Inputs!L:L)/_xlfn.XLOOKUP("Shareholder's Equity",Inputs!$B:$B,Inputs!L:L),"") | L16: =IFERROR(_xlfn.XLOOKUP("Net Income",Inputs!$B:$B,Inputs!M:M)/_xlfn.XLOOKUP("Shareholder's Equity",Inputs!$B:$B,Inputs!M:M),"") | M16: =IFERROR(_xlfn.XLOOKUP("Net Income",Inputs!$B:$B,Inputs!N:N)/_xlfn.XLOOKUP("Shareholder's Equity",Inputs!$B:$B,Inputs!N:N),"") -> -10.445364 | N16: =IFERROR(_xlfn.XLOOKUP("Net Income",Inputs!$B:$B,Inputs!O:O)/_xlfn.XLOOKUP("Shareholder's Equity",Inputs!$B:$B,Inputs!O:O),"") -> 1.8226929 | O16: =IFERROR(_xlfn.XLOOKUP("Net Income",Inputs!$B:$B,Inputs!P:P)/_xlfn.XLOOKUP("Shareholder's Equity",Inputs!$B:$B,Inputs!P:P),"") -> 3.3787427 | P16: =IFERROR(_xlfn.XLOOKUP("Net Income",Inputs!$B:$B,Inputs!Q:Q)/_xlfn.XLOOKUP("Shareholder's Equity",Inputs!$B:$B,Inputs!Q:Q),"") -> -2.2966989 | Q16: =IFERROR(_xlfn.XLOOKUP("Net Income",DCF!$B:$B,DCF!H:H)/_xlfn.XLOOKUP("Shareholder's Equity",DCF!$6:$6,DCF!10:10),"") -> 0.011408475 | R16: =IFERROR(_xlfn.XLOOKUP("Net Income",DCF!$B:$B,DCF!I:I)/_xlfn.XLOOKUP("Shareholder's Equity",DCF!$6:$6,DCF!10:10),"") -> 0.015833864
B17: Return on Total Capital | F17: =IFERROR(_xlfn.XLOOKUP("NOPAT",Inputs!$B:$B,Inputs!G:G)/(_xlfn.XLOOKUP("Shareholder's Equity",Inputs!$B:$B,Inputs!G:G)+_xlfn.XLOOKUP("Total Debt",Inputs!$B:$B,Inputs!G:G,,,-1)),"") | G17: =IFERROR(_xlfn.XLOOKUP("NOPAT",Inputs!$B:$B,Inputs!H:H)/(_xlfn.XLOOKUP("Shareholder's Equity",Inputs!$B:$B,Inputs!H:H)+_xlfn.XLOOKUP("Total Debt",Inputs!$B:$B,Inputs!H:H,,,-1)),"") | H17: =IFERROR(_xlfn.XLOOKUP("NOPAT",Inputs!$B:$B,Inputs!I:I)/(_xlfn.XLOOKUP("Shareholder's Equity",Inputs!$B:$B,Inputs!I:I)+_xlfn.XLOOKUP("Total Debt",Inputs!$B:$B,Inputs!I:I,,,-1)),"") | I17: =IFERROR(_xlfn.XLOOKUP("NOPAT",Inputs!$B:$B,Inputs!J:J)/(_xlfn.XLOOKUP("Shareholder's Equity",Inputs!$B:$B,Inputs!J:J)+_xlfn.XLOOKUP("Total Debt",Inputs!$B:$B,Inputs!J:J,,,-1)),"") | J17: =IFERROR(_xlfn.XLOOKUP("NOPAT",Inputs!$B:$B,Inputs!K:K)/(_xlfn.XLOOKUP("Shareholder's Equity",Inputs!$B:$B,Inputs!K:K)+_xlfn.XLOOKUP("Total Debt",Inputs!$B:$B,Inputs!K:K,,,-1)),"") | K17: =IFERROR(_xlfn.XLOOKUP("NOPAT",Inputs!$B:$B,Inputs!L:L)/(_xlfn.XLOOKUP("Shareholder's Equity",Inputs!$B:$B,Inputs!L:L)+_xlfn.XLOOKUP("Total Debt",Inputs!$B:$B,Inputs!L:L,,,-1)),"") | L17: =IFERROR(_xlfn.XLOOKUP("NOPAT",Inputs!$B:$B,Inputs!M:M)/(_xlfn.XLOOKUP("Shareholder's Equity",Inputs!$B:$B,Inputs!M:M)+_xlfn.XLOOKUP("Total Debt",Inputs!$B:$B,Inputs!M:M,,,-1)),"") | M17: =IFERROR(_xlfn.XLOOKUP("NOPAT",Inputs!$B:$B,Inputs!N:N)/(_xlfn.XLOOKUP("Shareholder's Equity",Inputs!$B:$B,Inputs!N:N)+_xlfn.XLOOKUP("Total Debt",Inputs!$B:$B,Inputs!N:N,,,-1)),"") -> -3.3297427 | N17: =IFERROR(_xlfn.XLOOKUP("NOPAT",Inputs!$B:$B,Inputs!O:O)/(_xlfn.XLOOKUP("Shareholder's Equity",Inputs!$B:$B,Inputs!O:O)+_xlfn.XLOOKUP("Total Debt",Inputs!$B:$B,Inputs!O:O,,,-1)),"") -> -0.43675274 | O17: =IFERROR(_xlfn.XLOOKUP("NOPAT",Inputs!$B:$B,Inputs!P:P)/(_xlfn.XLOOKUP("Shareholder's Equity",Inputs!$B:$B,Inputs!P:P)+_xlfn.XLOOKUP("Total Debt",Inputs!$B:$B,Inputs!P:P,,,-1)),"") -> 5.3476365 | P17: =IFERROR(_xlfn.XLOOKUP("NOPAT",Inputs!$B:$B,Inputs!Q:Q)/(_xlfn.XLOOKUP("Shareholder's Equity",Inputs!$B:$B,Inputs!Q:Q)+_xlfn.XLOOKUP("Total Debt",Inputs!$B:$B,Inputs!Q:Q,,,-1)),"") -> -0.72048939 | Q17: =+IFERROR(_xlfn.XLOOKUP("NOPAT",DCF!$B:$B,DCF!H:H)/(_xlfn.XLOOKUP("Shareholder's Equity",DCF!$6:$6,DCF!10:10)+_xlfn.XLOOKUP("Total Borrowings",DCF!$B:$B,DCF!H:H)+_xlfn.XLOOKUP("Total Leases",DCF!$B:$B,DCF!H:H)),"") -> 0.0087592764 | R17: =+IFERROR(_xlfn.XLOOKUP("NOPAT",DCF!$B:$B,DCF!I:I)/(_xlfn.XLOOKUP("Shareholder's Equity",DCF!$6:$6,DCF!10:10)+_xlfn.XLOOKUP("Total Borrowings",DCF!$B:$B,DCF!I:I)+_xlfn.XLOOKUP("Total Leases",DCF!$B:$B,DCF!I:I)),"") -> 0.011116745
B18: EBITDA Margin | F18: =+IFERROR(_xlfn.XLOOKUP("EBITDA",Inputs!$B:$B,Inputs!G:G)/_xlfn.XLOOKUP("Revenue (Sales)",Inputs!$B:$B,Inputs!G:G),"") | G18: =+IFERROR(_xlfn.XLOOKUP("EBITDA",Inputs!$B:$B,Inputs!H:H)/_xlfn.XLOOKUP("Revenue (Sales)",Inputs!$B:$B,Inputs!H:H),"") | H18: =+IFERROR(_xlfn.XLOOKUP("EBITDA",Inputs!$B:$B,Inputs!I:I)/_xlfn.XLOOKUP("Revenue (Sales)",Inputs!$B:$B,Inputs!I:I),"") | I18: =+IFERROR(_xlfn.XLOOKUP("EBITDA",Inputs!$B:$B,Inputs!J:J)/_xlfn.XLOOKUP("Revenue (Sales)",Inputs!$B:$B,Inputs!J:J),"") | J18: =+IFERROR(_xlfn.XLOOKUP("EBITDA",Inputs!$B:$B,Inputs!K:K)/_xlfn.XLOOKUP("Revenue (Sales)",Inputs!$B:$B,Inputs!K:K),"") | K18: =+IFERROR(_xlfn.XLOOKUP("EBITDA",Inputs!$B:$B,Inputs!L:L)/_xlfn.XLOOKUP("Revenue (Sales)",Inputs!$B:$B,Inputs!L:L),"") | L18: =+IFERROR(_xlfn.XLOOKUP("EBITDA",Inputs!$B:$B,Inputs!M:M)/_xlfn.XLOOKUP("Revenue (Sales)",Inputs!$B:$B,Inputs!M:M),"") | M18: =+IFERROR(_xlfn.XLOOKUP("EBITDA",Inputs!$B:$B,Inputs!N:N)/_xlfn.XLOOKUP("Revenue (Sales)",Inputs!$B:$B,Inputs!N:N),"") -> -5.7885014 | N18: =+IFERROR(_xlfn.XLOOKUP("EBITDA",Inputs!$B:$B,Inputs!O:O)/_xlfn.XLOOKUP("Revenue (Sales)",Inputs!$B:$B,Inputs!O:O),"") -> -7.9638924 | O18: =+IFERROR(_xlfn.XLOOKUP("EBITDA",Inputs!$B:$B,Inputs!P:P)/_xlfn.XLOOKUP("Revenue (Sales)",Inputs!$B:$B,Inputs!P:P),"") -> -8.6118977 | P18: =+IFERROR(_xlfn.XLOOKUP("EBITDA",Inputs!$B:$B,Inputs!Q:Q)/_xlfn.XLOOKUP("Revenue (Sales)",Inputs!$B:$B,Inputs!Q:Q),"") -> -7.8502322 | Q18: =+_xlfn.XLOOKUP("EBITDA Margin",DCF!$B:$B,DCF!H:H) -> -5.8578094 | R18: =+_xlfn.XLOOKUP("EBITDA Margin",DCF!$B:$B,DCF!I:I) -> -4.6356267
B19: EBIT Margin | F19: =IFERROR(_xlfn.XLOOKUP("Operating Income (EBIT)",Inputs!$B:$B,Inputs!G:G)/_xlfn.XLOOKUP("Revenue (Sales)",Inputs!$B:$B,Inputs!G:G),"") | G19: =IFERROR(_xlfn.XLOOKUP("Operating Income (EBIT)",Inputs!$B:$B,Inputs!H:H)/_xlfn.XLOOKUP("Revenue (Sales)",Inputs!$B:$B,Inputs!H:H),"") | H19: =IFERROR(_xlfn.XLOOKUP("Operating Income (EBIT)",Inputs!$B:$B,Inputs!I:I)/_xlfn.XLOOKUP("Revenue (Sales)",Inputs!$B:$B,Inputs!I:I),"") | I19: =IFERROR(_xlfn.XLOOKUP("Operating Income (EBIT)",Inputs!$B:$B,Inputs!J:J)/_xlfn.XLOOKUP("Revenue (Sales)",Inputs!$B:$B,Inputs!J:J),"") | J19: =IFERROR(_xlfn.XLOOKUP("Operating Income (EBIT)",Inputs!$B:$B,Inputs!K:K)/_xlfn.XLOOKUP("Revenue (Sales)",Inputs!$B:$B,Inputs!K:K),"") | K19: =IFERROR(_xlfn.XLOOKUP("Operating Income (EBIT)",Inputs!$B:$B,Inputs!L:L)/_xlfn.XLOOKUP("Revenue (Sales)",Inputs!$B:$B,Inputs!L:L),"") | L19: =IFERROR(_xlfn.XLOOKUP("Operating Income (EBIT)",Inputs!$B:$B,Inputs!M:M)/_xlfn.XLOOKUP("Revenue (Sales)",Inputs!$B:$B,Inputs!M:M),"") | M19: =IFERROR(_xlfn.XLOOKUP("Operating Income (EBIT)",Inputs!$B:$B,Inputs!N:N)/_xlfn.XLOOKUP("Revenue (Sales)",Inputs!$B:$B,Inputs!N:N),"") -> -6.2028986 | N19: =IFERROR(_xlfn.XLOOKUP("Operating Income (EBIT)",Inputs!$B:$B,Inputs!O:O)/_xlfn.XLOOKUP("Revenue (Sales)",Inputs!$B:$B,Inputs!O:O),"") -> 1.1152935 | O19: =IFERROR(_xlfn.XLOOKUP("Operating Income (EBIT)",Inputs!$B:$B,Inputs!P:P)/_xlfn.XLOOKUP("Revenue (Sales)",Inputs!$B:$B,Inputs!P:P),"") -> -8.8225622 | P19: =IFERROR(_xlfn.XLOOKUP("Operating Income (EBIT)",Inputs!$B:$B,Inputs!Q:Q)/_xlfn.XLOOKUP("Revenue (Sales)",Inputs!$B:$B,Inputs!Q:Q),"") -> -8.2458366 | Q19: =+_xlfn.XLOOKUP("Operating Margin",DCF!$B:$B,DCF!H:H) -> -5.8578094 | R19: =+_xlfn.XLOOKUP("Operating Margin",DCF!$B:$B,DCF!I:I) -> -4.6356267
B20: EBT Margin | F20: =IFERROR(_xlfn.XLOOKUP("Pre-Tax Income (EBT)",Inputs!$B:$B,Inputs!G:G)/_xlfn.XLOOKUP("Revenue (Sales)",Inputs!$B:$B,Inputs!G:G),"") | G20: =IFERROR(_xlfn.XLOOKUP("Pre-Tax Income (EBT)",Inputs!$B:$B,Inputs!H:H)/_xlfn.XLOOKUP("Revenue (Sales)",Inputs!$B:$B,Inputs!H:H),"") | H20: =IFERROR(_xlfn.XLOOKUP("Pre-Tax Income (EBT)",Inputs!$B:$B,Inputs!I:I)/_xlfn.XLOOKUP("Revenue (Sales)",Inputs!$B:$B,Inputs!I:I),"") | I20: =IFERROR(_xlfn.XLOOKUP("Pre-Tax Income (EBT)",Inputs!$B:$B,Inputs!J:J)/_xlfn.XLOOKUP("Revenue (Sales)",Inputs!$B:$B,Inputs!J:J),"") | J20: =IFERROR(_xlfn.XLOOKUP("Pre-Tax Income (EBT)",Inputs!$B:$B,Inputs!K:K)/_xlfn.XLOOKUP("Revenue (Sales)",Inputs!$B:$B,Inputs!K:K),"") | K20: =IFERROR(_xlfn.XLOOKUP("Pre-Tax Income (EBT)",Inputs!$B:$B,Inputs!L:L)/_xlfn.XLOOKUP("Revenue (Sales)",Inputs!$B:$B,Inputs!L:L),"") | L20: =IFERROR(_xlfn.XLOOKUP("Pre-Tax Income (EBT)",Inputs!$B:$B,Inputs!M:M)/_xlfn.XLOOKUP("Revenue (Sales)",Inputs!$B:$B,Inputs!M:M),"") | M20: =IFERROR(_xlfn.XLOOKUP("Pre-Tax Income (EBT)",Inputs!$B:$B,Inputs!N:N)/_xlfn.XLOOKUP("Revenue (Sales)",Inputs!$B:$B,Inputs!N:N),"") -> -5.0238892 | N20: =IFERROR(_xlfn.XLOOKUP("Pre-Tax Income (EBT)",Inputs!$B:$B,Inputs!O:O)/_xlfn.XLOOKUP("Revenue (Sales)",Inputs!$B:$B,Inputs!O:O),"") -> -7.4866862 | O20: =IFERROR(_xlfn.XLOOKUP("Pre-Tax Income (EBT)",Inputs!$B:$B,Inputs!P:P)/_xlfn.XLOOKUP("Revenue (Sales)",Inputs!$B:$B,Inputs!P:P),"") -> -9.4445079 | P20: =IFERROR(_xlfn.XLOOKUP("Pre-Tax Income (EBT)",Inputs!$B:$B,Inputs!Q:Q)/_xlfn.XLOOKUP("Revenue (Sales)",Inputs!$B:$B,Inputs!Q:Q),"") -> -16.299875 | Q20: =IFERROR(_xlfn.XLOOKUP("Pre-Tax Income (EBT)",DCF!$B:$B,DCF!H:H)/_xlfn.XLOOKUP("Revenue (Sales)",DCF!$B:$B,DCF!H:H),"") -> -7.7556772 | R20: =IFERROR(_xlfn.XLOOKUP("Pre-Tax Income (EBT)",DCF!$B:$B,DCF!I:I)/_xlfn.XLOOKUP("Revenue (Sales)",DCF!$B:$B,DCF!I:I),"") -> -6.7275829
B21: Gross Profit Margin | F21: =IFERROR(_xlfn.XLOOKUP("Gross Profit",Inputs!$B:$B,Inputs!G:G)/_xlfn.XLOOKUP("Revenue (Sales)",Inputs!$B:$B,Inputs!G:G),"") | G21: =IFERROR(_xlfn.XLOOKUP("Gross Profit",Inputs!$B:$B,Inputs!H:H)/_xlfn.XLOOKUP("Revenue (Sales)",Inputs!$B:$B,Inputs!H:H),"") | H21: =IFERROR(_xlfn.XLOOKUP("Gross Profit",Inputs!$B:$B,Inputs!I:I)/_xlfn.XLOOKUP("Revenue (Sales)",Inputs!$B:$B,Inputs!I:I),"") | I21: =IFERROR(_xlfn.XLOOKUP("Gross Profit",Inputs!$B:$B,Inputs!J:J)/_xlfn.XLOOKUP("Revenue (Sales)",Inputs!$B:$B,Inputs!J:J),"") | J21: =IFERROR(_xlfn.XLOOKUP("Gross Profit",Inputs!$B:$B,Inputs!K:K)/_xlfn.XLOOKUP("Revenue (Sales)",Inputs!$B:$B,Inputs!K:K),"") | K21: =IFERROR(_xlfn.XLOOKUP("Gross Profit",Inputs!$B:$B,Inputs!L:L)/_xlfn.XLOOKUP("Revenue (Sales)",Inputs!$B:$B,Inputs!L:L),"") | L21: =IFERROR(_xlfn.XLOOKUP("Gross Profit",Inputs!$B:$B,Inputs!M:M)/_xlfn.XLOOKUP("Revenue (Sales)",Inputs!$B:$B,Inputs!M:M),"") | M21: =IFERROR(_xlfn.XLOOKUP("Gross Profit",Inputs!$B:$B,Inputs!N:N)/_xlfn.XLOOKUP("Revenue (Sales)",Inputs!$B:$B,Inputs!N:N),"") -> 0.7212932 | N21: =IFERROR(_xlfn.XLOOKUP("Gross Profit",Inputs!$B:$B,Inputs!O:O)/_xlfn.XLOOKUP("Revenue (Sales)",Inputs!$B:$B,Inputs!O:O),"") -> 0.59249965 | O21: =IFERROR(_xlfn.XLOOKUP("Gross Profit",Inputs!$B:$B,Inputs!P:P)/_xlfn.XLOOKUP("Revenue (Sales)",Inputs!$B:$B,Inputs!P:P),"") -> 0.52774606 | P21: =IFERROR(_xlfn.XLOOKUP("Gross Profit",Inputs!$B:$B,Inputs!Q:Q)/_xlfn.XLOOKUP("Revenue (Sales)",Inputs!$B:$B,Inputs!Q:Q),"") -> 0.63022544 | Q21: =+_xlfn.XLOOKUP("Gross Profit Margin",DCF!$B:$B,DCF!H:H) -> 0.6 | R21: =+_xlfn.XLOOKUP("Gross Profit Margin",DCF!$B:$B,DCF!I:I) -> 0.6
B22: SG&A Margin | F22: =IFERROR(+_xlfn.XLOOKUP("SG&A (Selling, General & Administrative)",Inputs!$B:$B,Inputs!G:G)/_xlfn.XLOOKUP("Revenue (Sales)",Inputs!$B:$B,Inputs!G:G),"") | G22: =IFERROR(+_xlfn.XLOOKUP("SG&A (Selling, General & Administrative)",Inputs!$B:$B,Inputs!H:H)/_xlfn.XLOOKUP("Revenue (Sales)",Inputs!$B:$B,Inputs!H:H),"") | H22: =IFERROR(+_xlfn.XLOOKUP("SG&A (Selling, General & Administrative)",Inputs!$B:$B,Inputs!I:I)/_xlfn.XLOOKUP("Revenue (Sales)",Inputs!$B:$B,Inputs!I:I),"") | I22: =IFERROR(+_xlfn.XLOOKUP("SG&A (Selling, General & Administrative)",Inputs!$B:$B,Inputs!J:J)/_xlfn.XLOOKUP("Revenue (Sales)",Inputs!$B:$B,Inputs!J:J),"") | J22: =IFERROR(+_xlfn.XLOOKUP("SG&A (Selling, General & Administrative)",Inputs!$B:$B,Inputs!K:K)/_xlfn.XLOOKUP("Revenue (Sales)",Inputs!$B:$B,Inputs!K:K),"") | K22: =IFERROR(+_xlfn.XLOOKUP("SG&A (Selling, General & Administrative)",Inputs!$B:$B,Inputs!L:L)/_xlfn.XLOOKUP("Revenue (Sales)",Inputs!$B:$B,Inputs!L:L),"") | L22: =IFERROR(+_xlfn.XLOOKUP("SG&A (Selling, General & Administrative)",Inputs!$B:$B,Inputs!M:M)/_xlfn.XLOOKUP("Revenue (Sales)",Inputs!$B:$B,Inputs!M:M),"") | M22: =IFERROR(+_xlfn.XLOOKUP("SG&A (Selling, General & Administrative)",Inputs!$B:$B,Inputs!N:N)/_xlfn.XLOOKUP("Revenue (Sales)",Inputs!$B:$B,Inputs!N:N),"") -> 2.8788024 | N22: =IFERROR(+_xlfn.XLOOKUP("SG&A (Selling, General & Administrative)",Inputs!$B:$B,Inputs!O:O)/_xlfn.XLOOKUP("Revenue (Sales)",Inputs!$B:$B,Inputs!O:O),"") -> 4.4063851 | O22: =IFERROR(+_xlfn.XLOOKUP("SG&A (Selling, General & Administrative)",Inputs!$B:$B,Inputs!P:P)/_xlfn.XLOOKUP("Revenue (Sales)",Inputs!$B:$B,Inputs!P:P),"") -> 5.3996346 | P22: =IFERROR(+_xlfn.XLOOKUP("SG&A (Selling, General & Administrative)",Inputs!$B:$B,Inputs!Q:Q)/_xlfn.XLOOKUP("Revenue (Sales)",Inputs!$B:$B,Inputs!Q:Q),"") -> 5.3796307 | Q22: =+_xlfn.XLOOKUP("SG&A Margin",DCF!$B:$B,DCF!H:H) -> 3 | R22: =+_xlfn.XLOOKUP("SG&A Margin",DCF!$B:$B,DCF!I:I) -> 2
B23: Net Income Margin | F23: =IFERROR(_xlfn.XLOOKUP("Net Income",Inputs!$B:$B,Inputs!G:G)/_xlfn.XLOOKUP("Revenue (Sales)",Inputs!$B:$B,Inputs!G:G),"") | G23: =IFERROR(_xlfn.XLOOKUP("Net Income",Inputs!$B:$B,Inputs!H:H)/_xlfn.XLOOKUP("Revenue (Sales)",Inputs!$B:$B,Inputs!H:H),"") | H23: =IFERROR(_xlfn.XLOOKUP("Net Income",Inputs!$B:$B,Inputs!I:I)/_xlfn.XLOOKUP("Revenue (Sales)",Inputs!$B:$B,Inputs!I:I),"") | I23: =IFERROR(_xlfn.XLOOKUP("Net Income",Inputs!$B:$B,Inputs!J:J)/_xlfn.XLOOKUP("Revenue (Sales)",Inputs!$B:$B,Inputs!J:J),"") | J23: =IFERROR(_xlfn.XLOOKUP("Net Income",Inputs!$B:$B,Inputs!K:K)/_xlfn.XLOOKUP("Revenue (Sales)",Inputs!$B:$B,Inputs!K:K),"") | K23: =IFERROR(_xlfn.XLOOKUP("Net Income",Inputs!$B:$B,Inputs!L:L)/_xlfn.XLOOKUP("Revenue (Sales)",Inputs!$B:$B,Inputs!L:L),"") | L23: =IFERROR(_xlfn.XLOOKUP("Net Income",Inputs!$B:$B,Inputs!M:M)/_xlfn.XLOOKUP("Revenue (Sales)",Inputs!$B:$B,Inputs!M:M),"") | M23: =IFERROR(_xlfn.XLOOKUP("Net Income",Inputs!$B:$B,Inputs!N:N)/_xlfn.XLOOKUP("Revenue (Sales)",Inputs!$B:$B,Inputs!N:N),"") -> -5.0238892 | N23: =IFERROR(_xlfn.XLOOKUP("Net Income",Inputs!$B:$B,Inputs!O:O)/_xlfn.XLOOKUP("Revenue (Sales)",Inputs!$B:$B,Inputs!O:O),"") -> -7.4866862 | O23: =IFERROR(_xlfn.XLOOKUP("Net Income",Inputs!$B:$B,Inputs!P:P)/_xlfn.XLOOKUP("Revenue (Sales)",Inputs!$B:$B,Inputs!P:P),"") -> -9.4445079 | P23: =IFERROR(_xlfn.XLOOKUP("Net Income",Inputs!$B:$B,Inputs!Q:Q)/_xlfn.XLOOKUP("Revenue (Sales)",Inputs!$B:$B,Inputs!Q:Q),"") -> -16.299875 | Q23: =+_xlfn.XLOOKUP("Net Income Margin",DCF!$B:$B,DCF!H:H) -> -7.7556772 | R23: =+_xlfn.XLOOKUP("Net Income Margin",DCF!$B:$B,DCF!I:I) -> -6.7275829
B25: Liquidity | F25: 2014 | G25: =+F25+1 -> 2015 | H25: =+G25+1 -> 2016 | I25: =+H25+1 -> 2017 | J25: =+I25+1 -> 2018 | K25: =+J25+1 -> 2019 | L25: =+K25+1 -> 2020 | M25: =+L25+1 -> 2021 | N25: 2022 | O25: =+N25+1 -> 2023 | P25: =+O25+1 -> 2024 | Q25: =+P25+1 -> 2025 | R25: =+Q25+1 -> 2026
B27: Cash Ratio | F27: =+IFERROR(_xlfn.XLOOKUP("Cash & Cash Equivalents",Inputs!$B:$B,Inputs!G:G)/_xlfn.XLOOKUP("Current Liabilities",Inputs!$B:$B,Inputs!G:G),"") | G27: =+IFERROR(_xlfn.XLOOKUP("Cash & Cash Equivalents",Inputs!$B:$B,Inputs!H:H)/_xlfn.XLOOKUP("Current Liabilities",Inputs!$B:$B,Inputs!H:H),"") | H27: =+IFERROR(_xlfn.XLOOKUP("Cash & Cash Equivalents",Inputs!$B:$B,Inputs!I:I)/_xlfn.XLOOKUP("Current Liabilities",Inputs!$B:$B,Inputs!I:I),"") | I27: =+IFERROR(_xlfn.XLOOKUP("Cash & Cash Equivalents",Inputs!$B:$B,Inputs!J:J)/_xlfn.XLOOKUP("Current Liabilities",Inputs!$B:$B,Inputs!J:J),"") | J27: =+IFERROR(_xlfn.XLOOKUP("Cash & Cash Equivalents",Inputs!$B:$B,Inputs!K:K)/_xlfn.XLOOKUP("Current Liabilities",Inputs!$B:$B,Inputs!K:K),"") | K27: =+IFERROR(_xlfn.XLOOKUP("Cash & Cash Equivalents",Inputs!$B:$B,Inputs!L:L)/_xlfn.XLOOKUP("Current Liabilities",Inputs!$B:$B,Inputs!L:L),"") | L27: =+IFERROR(_xlfn.XLOOKUP("Cash & Cash Equivalents",Inputs!$B:$B,Inputs!M:M)/_xlfn.XLOOKUP("Current Liabilities",Inputs!$B:$B,Inputs!M:M),"") -> 4.0185185 | M27: =+IFERROR(_xlfn.XLOOKUP("Cash & Cash Equivalents",Inputs!$B:$B,Inputs!N:N)/_xlfn.XLOOKUP("Current Liabilities",Inputs!$B:$B,Inputs!N:N),"") -> 0.92112676 | N27: =+IFERROR(_xlfn.XLOOKUP("Cash & Cash Equivalents",Inputs!$B:$B,Inputs!O:O)/_xlfn.XLOOKUP("Current Liabilities",Inputs!$B:$B,Inputs!O:O),"") -> 0.44046135 | O27: =+IFERROR(_xlfn.XLOOKUP("Cash & Cash Equivalents",Inputs!$B:$B,Inputs!P:P)/_xlfn.XLOOKUP("Current Liabilities",Inputs!$B:$B,Inputs!P:P),"") -> 3.6717333 | P27: =+IFERROR(_xlfn.XLOOKUP("Cash & Cash Equivalents",Inputs!$B:$B,Inputs!Q:Q)/_xlfn.XLOOKUP("Current Liabilities",Inputs!$B:$B,Inputs!Q:Q),"") -> 5.90413 | Q27: =+IFERROR((_xlfn.XLOOKUP("Cash & Cash Equivalents & ST Investments",DCF!$B:$B,DCF!H:H)-_xlfn.XLOOKUP("Short-Term Investments",Inputs!$B:$B,Inputs!$Q:$Q))/_xlfn.XLOOKUP("Current Liabilities",DCF!$6:$6,DCF!10:10),"") -> 6.1449261 | R27: =+IFERROR((_xlfn.XLOOKUP("Cash & Cash Equivalents & ST Investments",DCF!$B:$B,DCF!I:I)-_xlfn.XLOOKUP("Short-Term Investments",Inputs!$B:$B,Inputs!$Q:$Q))/_xlfn.XLOOKUP("Current Liabilities",DCF!$6:$6,DCF!10:10),"") -> 4.2334192
