Workbook
Name blablabla: _xlfn.LAMBDA(_xldudf_BOARDFLARE_EXEC("workbook-settings:coolfucntion"))
Name blablabla: _xlfn.LAMBDA(_xldudf_BOARDFLARE_EXEC("workbook-settings:coolfucntion"))
Name blablabla: _xlfn.LAMBDA(_xldudf_BOARDFLARE_EXEC("workbook-settings:coolfucntion"))
Name COOLFUCNTION: _xlfn.LAMBDA(_xldudf_BOARDFLARE_EXEC("workbook-settings:coolfucntion"))
Name COOLFUCNTION: _xlfn.LAMBDA(_xldudf_BOARDFLARE_EXEC("workbook-settings:coolfucntion"))
Name COOLFUCNTION: _xlfn.LAMBDA(_xldudf_BOARDFLARE_EXEC("workbook-settings:coolfucntion"))
Name COOLFUCNTION: _xlfn.LAMBDA(_xldudf_BOARDFLARE_EXEC("workbook-settings:coolfucntion"))
Name COOLFUCNTION: _xlfn.LAMBDA(_xldudf_BOARDFLARE_EXEC("workbook-settings:coolfucntion"))
Name COOLFUCNTION: _xlfn.LAMBDA(_xldudf_BOARDFLARE_EXEC("workbook-settings:coolfucntion"))
Name COOLFUCNTION: _xlfn.LAMBDA(_xldudf_BOARDFLARE_EXEC("workbook-settings:coolfucntion"))
Name COOLFUCNTION: _xlfn.LAMBDA(_xldudf_BOARDFLARE_EXEC("workbook-settings:coolfucntion"))
Name COOLFUCNTION: _xlfn.LAMBDA(_xldudf_BOARDFLARE_EXEC("workbook-settings:coolfucntion"))
Name COOLFUCNTION: _xlfn.LAMBDA(_xldudf_BOARDFLARE_EXEC("workbook-settings:coolfucntion"))
Name COOLFUCNTION: _xlfn.LAMBDA(_xldudf_BOARDFLARE_EXEC("workbook-settings:coolfucntion"))
Name COOLFUCNTION: _xlfn.LAMBDA(_xldudf_BOARDFLARE_EXEC("workbook-settings:coolfucntion"))
Name COOLFUCNTION: _xlfn.LAMBDA(_xldudf_BOARDFLARE_EXEC("workbook-settings:coolfucntion"))
Name DCF_2: _xlfn.LAMBDA(_xldudf_BOARDFLARE_EXEC("workbook-settings:coolfucntion"))
Name DCF_2: _xlfn.LAMBDA(_xldudf_BOARDFLARE_EXEC("workbook-settings:coolfucntion"))
Name DCF_2: _xlfn.LAMBDA(_xldudf_BOARDFLARE_EXEC("workbook-settings:coolfucntion"))
Name DCF_2: _xlfn.LAMBDA(_xldudf_BOARDFLARE_EXEC("workbook-settings:coolfucntion"))
Name Sectors: #REF!
Name Sectors: #REF!
Name Sectors: #REF!
Name Sectors: #REF!

Sheet Summary
E2: | EQUITY RESEARCH | U2: Lisbon Investment Society Equity Research
U3: April 8, 2025
D6: {=+_FV(DCF!R4,"Name")} -> E.L.F. BEAUTY, INC. | U6: Buy
D8: E.L.F. Beauty is an American cosmetics company known for its affordable, cruelty-free, and vegan makeup and skincare products. It offers a wide range of items including foundations, lipsticks, primers, and skincare treatments, all designed to deliver high quality at accessible prices. Being extremely popular on social media, it has been growing rapidely for the past years. | U8: EXCHANGE:(TICKER)
U9: {=+"Price (19 April 25): $"&_FV(DCF!$R$4,"Price")} -> Price (19 April 25): $135.91
D10: Investment Thesis | U10: ="Price Target: $" & ROUND(IF(Summary!G25="FCFF",DCF!Q226,IF(Summary!G25="FCFE",DCF!Q269,IF(Summary!G25="Tax Shield",DCF!Q242,DCF!Q285))),2) &" "&IF(Summary!G25="FCFF","(FCFF)",IF(Summary!G25="FCFE","(FCFE)",IF(Summary!G25="Tax Shield","(APV)","(DDM)"))) -> Price Target: $107.57 (FCFF)
D11: We rate E.L.F Beauty as a Buy, supported by strong growth, fundamentals, digital presence and future stategy in a fast-growing beauty sector. For the base of your DCF, we estimated E.L.F's future market share in their main market (USA) and also in the international market individualy in order to forecast their future revenues. After carefull consideration of each estimate, we reach a fair stock price of $110,06. We believe that E.L.F is well positioned to continue capturing value in a sector undergoing structural digital transformation and that it will continue to outperform the market and that although tarriffs are a big concern, the stock price has overreacted, creating an interesting opportunity to buy. At the same time, we are not confortable setting a strong buy rating due to global uncertainty. | U11: =+"Upside (Downside): "&ROUND((DCF!$Q$229*100),2)&"%" -> Upside (Downside): -20.85%
U14: =+Industry!E28&", "&ESG!C9 -> United States, Consumer Staples
U15: =+ESG!C10 -> Personal Care Products
D17: Operating Metrics | F17: 2023 | G17: =+F17+1 -> 2024 | H17: =+G17+1 -> 2025 | I17: =+H17+1 -> 2026 | K17: Valuation Multiples | N17: 2022 | O17: =+N17+1 -> 2023 | P17: =+O17+1 -> 2024 | Q17: =+P17+1 -> 2025 | R17: =+Q17+1 -> 2026 | U17: Miguel Wever
D18: Market Share (US only) | F18: =DCF!F34 -> 0.0083067616 | G18: =DCF!G34 -> 0.013151746 | H18: =DCF!H34 -> 0.016383066 | I18: =DCF!I34 -> 0.017106453 | K18: EV / Sales | N18: =IFERROR(_xlfn.XLOOKUP($K18,Multiples!$B:$B,Multiples!N:N),"") -> 3.5253621 | O18: =IFERROR(_xlfn.XLOOKUP($K18,Multiples!$B:$B,Multiples!O:O),"") -> 7.3930114 | P18: =IFERROR(_xlfn.XLOOKUP($K18,Multiples!$B:$B,Multiples!P:P),"") -> 10.335833 | Q18: =IFERROR(_xlfn.XLOOKUP($K18,Multiples!$B:$B,Multiples!Q:Q),"") -> 5.0181315 | R18: =IFERROR(_xlfn.XLOOKUP($K18,Multiples!$B:$B,Multiples!R:R),"") -> 4.5757923 | U18: l61728@aln.iseg.ulisboa.pt
D19: Market Share (non-US) | F19: =DCF!F39 -> 0.00037643627 | G19: =DCF!G39 -> 0.00081384972 | H19: =DCF!H39 -> 0.00081140927 | I19: =DCF!I39 -> 0.0010491274 | K19: Price / Sales | N19: =IFERROR(_xlfn.XLOOKUP($K19,Multiples!$B:$B,Multiples!N:N),"") -> 3.3522361 | O19: =IFERROR(_xlfn.XLOOKUP($K19,Multiples!$B:$B,Multiples!O:O),"") -> 7.4695491 | P19: =IFERROR(_xlfn.XLOOKUP($K19,Multiples!$B:$B,Multiples!P:P),"") -> 10.255649 | Q19: =IFERROR(_xlfn.XLOOKUP($K19,Multiples!$B:$B,Multiples!Q:Q),"") -> 4.9661552 | R19: =IFERROR(_xlfn.XLOOKUP($K19,Multiples!$B:$B,Multiples!R:R),"") -> 4.6350116 | U19: (+351) 935 248 695
K20: EV / EBITDA | N20: =IFERROR(_xlfn.XLOOKUP($K20,Multiples!$B:$B,Multiples!N:N),"") -> 47.02881 | O20: =IFERROR(_xlfn.XLOOKUP($K20,Multiples!$B:$B,Multiples!O:O),"") -> 62.835169 | P20: =IFERROR(_xlfn.XLOOKUP($K20,Multiples!$B:$B,Multiples!P:P),"") -> 70.693781 | Q20: =IFERROR(_xlfn.XLOOKUP($K20,Multiples!$B:$B,Multiples!Q:Q),"") -> 56.481906 | R20: =IFERROR(_xlfn.XLOOKUP($K20,Multiples!$B:$B,Multiples!R:R),"") -> 40.154923 | U20: Mariana Gomes
K21: EV / EBIT | N21: =IFERROR(_xlfn.XLOOKUP($K21,Multiples!$B:$B,Multiples!N:N),"") -> 601.15087 | O21: =IFERROR(_xlfn.XLOOKUP($K21,Multiples!$B:$B,Multiples!O:O),"") -> 93.226035 | P21: =IFERROR(_xlfn.XLOOKUP($K21,Multiples!$B:$B,Multiples!P:P),"") -> 92.995246 | Q21: =IFERROR(_xlfn.XLOOKUP($K21,Multiples!$B:$B,Multiples!Q:Q),"") -> 83.137541 | R21: =IFERROR(_xlfn.XLOOKUP($K21,Multiples!$B:$B,Multiples!R:R),"") -> 51.719216 | U21: l63852@aln.iseg.ulisboa.pt
K22: Price / Earnings | N22: =IFERROR(_xlfn.XLOOKUP($K22,Multiples!$B:$B,Multiples!N:N),"") -> 60.03411 | O22: =IFERROR(_xlfn.XLOOKUP($K22,Multiples!$B:$B,Multiples!O:O),"") -> 70.29878 | P22: =IFERROR(_xlfn.XLOOKUP($K22,Multiples!$B:$B,Multiples!P:P),"") -> 82.229906 | Q22: =IFERROR(_xlfn.XLOOKUP($K22,Multiples!$B:$B,Multiples!Q:Q),"") -> 104.73521 | R22: =IFERROR(_xlfn.XLOOKUP($K22,Multiples!$B:$B,Multiples!R:R),"") -> 63.351551 | U22: (+351) 917 778 745
K23: Price / Book | N23: =IFERROR(_xlfn.XLOOKUP($K23,Multiples!$B:$B,Multiples!N:N),"") -> 4.2085371 | O23: =IFERROR(_xlfn.XLOOKUP($K23,Multiples!$B:$B,Multiples!O:O),"") -> 10.519161 | P23: =IFERROR(_xlfn.XLOOKUP($K23,Multiples!$B:$B,Multiples!P:P),"") -> 16.34105 | Q23: =IFERROR(_xlfn.XLOOKUP($K23,Multiples!$B:$B,Multiples!Q:Q),"") -> 9.6851816 | R23: =IFERROR(_xlfn.XLOOKUP($K23,Multiples!$B:$B,Multiples!R:R),"") -> 9.7175503 | U23: Dmitriy Zaev
U24: l61121@aln.iseg.ulisboa.pt
D25: Year | E25: Net Sales | F25: EBIT Margin | G25: FCFF | H25: =+IF(Summary!$G$25="FCFF",DCF!AB6,IF(Summary!$G$25="FCFE",DCF!AC6,DCF!AD6)) -> NOPAT | I25: Net Capex | K25: Profitability Ratios | N25: 2022 | O25: =+N25+1 -> 2023 | P25: =+O25+1 -> 2024 | Q25: =+P25+1 -> 2025 | R25: =+Q25+1 -> 2026 | U25: (+7) 981 806-15-95
D26: 2022 | E26: =+DCF!E48 -> 392.2 | F26: =+DCF!E78 -> 0.0058643549 | G26: =+INDEX(DCF!X7:AA7,MATCH(Summary!$G$25,{"FCFF","FCFE","Tax Shield","Total Payout"},0)) -> 7.4733333 | H26: =+IF(Summary!$G$25="FCFF",DCF!AB7,IF(Summary!$G$25="FCFE",DCF!AC7,DCF!AD7)) -> 7.9733333 | I26: =+DCF!E152 -> -4.8 | K26: Return on Assets | N26: =IFERROR(_xlfn.XLOOKUP($K26,Multiples!$B:$B,Multiples!N:N),"") -> 0.044278205 | O26: =IFERROR(_xlfn.XLOOKUP($K26,Multiples!$B:$B,Multiples!O:O),"") -> 0.10325722 | P26: =IFERROR(_xlfn.XLOOKUP($K26,Multiples!$B:$B,Multiples!P:P),"") -> 0.1130789 | Q26: =IFERROR(_xlfn.XLOOKUP($K26,Multiples!$B:$B,Multiples!Q:Q),"") -> 0.051614206 | R26: =IFERROR(_xlfn.XLOOKUP($K26,Multiples!$B:$B,Multiples!R:R),"") -> 0.091052147 | U26: José Godinho
D27: =+D26+1 -> 2023 | E27: =+DCF!F48 -> 578.8 | F27: =+DCF!F78 -> 0.079302004 | G27: =+INDEX(DCF!X8:AA8,MATCH(Summary!$G$25,{"FCFF","FCFE","Tax Shield","Total Payout"},0)) -> 91.954785 | H27: =+IF(Summary!$G$25="FCFF",DCF!AB8,IF(Summary!$G$25="FCFE",DCF!AC8,DCF!AD8)) -> 43.154785 | I27: =+DCF!F152 -> -1.7 | K27: Return on Equity | N27: =IFERROR(_xlfn.XLOOKUP($K27,Multiples!$B:$B,Multiples!N:N),"") -> 0.070102433 | O27: =IFERROR(_xlfn.XLOOKUP($K27,Multiples!$B:$B,Multiples!O:O),"") -> 0.14963504 | P27: =IFERROR(_xlfn.XLOOKUP($K27,Multiples!$B:$B,Multiples!P:P),"") -> 0.19872393 | Q27: =IFERROR(_xlfn.XLOOKUP($K27,Multiples!$B:$B,Multiples!Q:Q),"") -> -1.6230198e-08 | R27: =IFERROR(_xlfn.XLOOKUP($K27,Multiples!$B:$B,Multiples!R:R),"") -> -2.8631544e-08 | U27: l61474@aln.iseg.ulisboa.pt
D28: =+D27+1 -> 2024 | E28: =+DCF!G48 -> 1023.9 | F28: =+DCF!G78 -> 0.11114367 | G28: =+INDEX(DCF!X9:AA9,MATCH(Summary!$G$25,{"FCFF","FCFE","Tax Shield","Total Payout"},0)) -> 49.699049 | H28: =+IF(Summary!$G$25="FCFF",DCF!AB9,IF(Summary!$G$25="FCFE",DCF!AC9,DCF!AD9)) -> 99.399049 | I28: =+DCF!G152 -> -8.7 | K28: Return on Total Capital | N28: =IFERROR(_xlfn.XLOOKUP($K28,Multiples!$B:$B,Multiples!N:N),"") -> 0.018818346 | O28: =IFERROR(_xlfn.XLOOKUP($K28,Multiples!$B:$B,Multiples!O:O),"") -> 0.088522635 | P28: =IFERROR(_xlfn.XLOOKUP($K28,Multiples!$B:$B,Multiples!P:P),"") -> 0.11934092 | Q28: =IFERROR(_xlfn.XLOOKUP($K28,Multiples!$B:$B,Multiples!Q:Q),"") -> -1.8735422e-08 | R28: =IFERROR(_xlfn.XLOOKUP($K28,Multiples!$B:$B,Multiples!R:R),"") -> -3.1274562e-08 | U28: (+351) 934 684 550
D29: =+D28+1 -> 2025 | E29: =+DCF!H48 -> 1308.9 | F29: =+DCF!H78 -> 0.060359393 | G29: =+INDEX(DCF!X10:AA10,MATCH(Summary!$G$25,{"FCFF","FCFE","Tax Shield","Total Payout"},0)) -> 8.5855595 | H29: =+IF(Summary!$G$25="FCFF",DCF!AB10,IF(Summary!$G$25="FCFE",DCF!AC10,DCF!AD10)) -> 71.642986 | I29: =+DCF!H152 -> -8.7 | K29: EBITDA Margin | N29: =IFERROR(_xlfn.XLOOKUP($K29,Multiples!$B:$B,Multiples!N:N),"") -> 0.074961754 | O29: =IFERROR(_xlfn.XLOOKUP($K29,Multiples!$B:$B,Multiples!O:O),"") -> 0.11765722 | P29: =IFERROR(_xlfn.XLOOKUP($K29,Multiples!$B:$B,Multiples!P:P),"") -> 0.14620568 | Q29: =IFERROR(_xlfn.XLOOKUP($K29,Multiples!$B:$B,Multiples!Q:Q),"") -> 0.088844939 | R29: =IFERROR(_xlfn.XLOOKUP($K29,Multiples!$B:$B,Multiples!R:R),"") -> 0.11395346
D30: =+D29+1 -> 2026 | E30: =+DCF!I48 -> 1496.4472 | F30: =+DCF!I78 -> 0.088473737 | G30: =+INDEX(DCF!X11:AA11,MATCH(Summary!$G$25,{"FCFF","FCFE","Tax Shield","Total Payout"},0)) -> 216.4966 | H30: =+IF(Summary!$G$25="FCFF",DCF!AB11,IF(Summary!$G$25="FCFE",DCF!AC11,DCF!AD11)) -> 119.59181 | I30: =+DCF!I152 -> -9.36 | K30: EBIT Margin | N30: =IFERROR(_xlfn.XLOOKUP($K30,Multiples!$B:$B,Multiples!N:N),"") -> 0.0058643549 | O30: =IFERROR(_xlfn.XLOOKUP($K30,Multiples!$B:$B,Multiples!O:O),"") -> 0.079302004 | P30: =IFERROR(_xlfn.XLOOKUP($K30,Multiples!$B:$B,Multiples!P:P),"") -> 0.11114367 | Q30: =IFERROR(_xlfn.XLOOKUP($K30,Multiples!$B:$B,Multiples!Q:Q),"") -> 0.060359393 | R30: =IFERROR(_xlfn.XLOOKUP($K30,Multiples!$B:$B,Multiples!R:R),"") -> 0.088473737 | U30: Statistics
D31: =+D30+1 -> 2027 | E31: =+DCF!J48 -> 1683.4559 | F31: =+DCF!J78 -> 0.1030754 | G31: =+INDEX(DCF!X12:AA12,MATCH(Summary!$G$25,{"FCFF","FCFE","Tax Shield","Total Payout"},0)) -> 236.39083 | H31: =+IF(Summary!$G$25="FCFF",DCF!AB12,IF(Summary!$G$25="FCFE",DCF!AC12,DCF!AD12)) -> 156.19555 | I31: =+DCF!J152 -> -9.888 | K31: Gross Profit Margin | N31: =IFERROR(_xlfn.XLOOKUP($K31,Multiples!$B:$B,Multiples!N:N),"") -> 0.64201938 | O31: =IFERROR(_xlfn.XLOOKUP($K31,Multiples!$B:$B,Multiples!O:O),"") -> 0.67449896 | P31: =IFERROR(_xlfn.XLOOKUP($K31,Multiples!$B:$B,Multiples!P:P),"") -> 0.70719797 | Q31: =IFERROR(_xlfn.XLOOKUP($K31,Multiples!$B:$B,Multiples!Q:Q),"") -> 0.65 | R31: =IFERROR(_xlfn.XLOOKUP($K31,Multiples!$B:$B,Multiples!R:R),"") -> 0.675 | U31: Beta | V31: =Peers!D68 -> 1.6084
D32: =+D31+1 -> 2028 | E32: =+DCF!K48 -> 1867.7453 | F32: =+DCF!K78 -> 0.11086001 | G32: =+INDEX(DCF!X13:AA13,MATCH(Summary!$G$25,{"FCFF","FCFE","Tax Shield","Total Payout"},0)) -> 256.05524 | H32: =+IF(Summary!$G$25="FCFF",DCF!AB13,IF(Summary!$G$25="FCFE",DCF!AC13,DCF!AD13)) -> 185.80374 | I32: =+DCF!K152 -> -10.3104 | K32: SG&A Margin | N32: =IFERROR(_xlfn.XLOOKUP($K32,Multiples!$B:$B,Multiples!N:N),"") -> 0.56578276 | O32: =IFERROR(_xlfn.XLOOKUP($K32,Multiples!$B:$B,Multiples!O:O),"") -> 0.55684174 | P32: =IFERROR(_xlfn.XLOOKUP($K32,Multiples!$B:$B,Multiples!P:P),"") -> 0.56099228 | Q32: =IFERROR(_xlfn.XLOOKUP($K32,Multiples!$B:$B,Multiples!Q:Q),"") -> 0.5612056 | R32: =IFERROR(_xlfn.XLOOKUP($K32,Multiples!$B:$B,Multiples!R:R),"") -> 0.55967987 | U32: % Float | V32: =+Peers!D67 -> 0.97925532
D33: =+D32+1 -> 2029 | E33: =+DCF!L48 -> 2051.2897 | F33: =+DCF!L78 -> 0.11529763 | G33: =+INDEX(DCF!X14:AA14,MATCH(Summary!$G$25,{"FCFF","FCFE","Tax Shield","Total Payout"},0)) -> 309.19978 | H33: =+IF(Summary!$G$25="FCFF",DCF!AB14,IF(Summary!$G$25="FCFE",DCF!AC14,DCF!AD14)) -> 211.64388 | I33: =+DCF!L152 -> -10.64832 | K33: Net Income Margin | N33: =IFERROR(_xlfn.XLOOKUP($K33,Multiples!$B:$B,Multiples!N:N),"") -> 0.055838858 | O33: =IFERROR(_xlfn.XLOOKUP($K33,Multiples!$B:$B,Multiples!O:O),"") -> 0.10625432 | P33: =IFERROR(_xlfn.XLOOKUP($K33,Multiples!$B:$B,Multiples!P:P),"") -> 0.12471921 | Q33: =IFERROR(_xlfn.XLOOKUP($K33,Multiples!$B:$B,Multiples!Q:Q),"") -> 0.047416291 | R33: =IFERROR(_xlfn.XLOOKUP($K33,Multiples!$B:$B,Multiples!R:R),"") -> 0.073163348 | U33: % Held by Insiders | V33: =Peers!D70 -> 0.0264
U34: % Held by Institutions | V34: =Peers!D71 -> 0.9616
D35: SWOT Analysis | K35: Liquidity Ratios | N35: 2022 | O35: =+N35+1 -> 2023 | P35: =+O35+1 -> 2024 | Q35: =+P35+1 -> 2025 | R35: =+Q35+1 -> 2026 | U35: Short % of Float | V35: =+Peers!D72 -> 0.1837
D36: Strengths | G36: Weaknesses | K36: Cash Ratio | N36: =IFERROR(_xlfn.XLOOKUP($K36,Multiples!$B:$B,Multiples!N:N),"") -> 0.66769231 | O36: =IFERROR(_xlfn.XLOOKUP($K36,Multiples!$B:$B,Multiples!O:O),"") -> 1.1185185 | P36: =IFERROR(_xlfn.XLOOKUP($K36,Multiples!$B:$B,Multiples!P:P),"") -> 0.36175192 | Q36: =IFERROR(_xlfn.XLOOKUP($K36,Multiples!$B:$B,Multiples!Q:Q),"") -> 0.34007724 | R36: =IFERROR(_xlfn.XLOOKUP($K36,Multiples!$B:$B,Multiples!R:R),"") -> 1.0788852 | W36: 120.87
D37: Affordable and High-Quality Products; Strong Brand Identity and Digital Presence: Huge on TikTok and has big influencer support, digital sales account for 22% of revenue; Cruelty-Free and Vegan Products; | G37: Tarriff implications: China is a big supplier; Dependence on Third-Party Retailers; Brand Perception: Some consumers may associate low price with lower quality | K37: Quick Ratio | N37: =IFERROR(_xlfn.XLOOKUP($K37,Multiples!$B:$B,Multiples!N:N),"") -> 1.3692308 | O37: =IFERROR(_xlfn.XLOOKUP($K37,Multiples!$B:$B,Multiples!O:O),"") -> 1.7472222 | P37: =IFERROR(_xlfn.XLOOKUP($K37,Multiples!$B:$B,Multiples!P:P),"") -> 0.77566031 | Q37: =IFERROR(_xlfn.XLOOKUP($K37,Multiples!$B:$B,Multiples!Q:Q),"") -> 1.004404 | R37: =IFERROR(_xlfn.XLOOKUP($K37,Multiples!$B:$B,Multiples!R:R),"") -> 1.8426952 | U37: Major Holders | W37: 113.63
K38: Current Ratio | N38: =IFERROR(_xlfn.XLOOKUP($K38,Multiples!$B:$B,Multiples!N:N),"") -> 2.9692308 | O38: =IFERROR(_xlfn.XLOOKUP($K38,Multiples!$B:$B,Multiples!O:O),"") -> 2.8083333 | P38: =IFERROR(_xlfn.XLOOKUP($K38,Multiples!$B:$B,Multiples!P:P),"") -> 1.5951187 | Q38: =IFERROR(_xlfn.XLOOKUP($K38,Multiples!$B:$B,Multiples!Q:Q),"") -> 2.2947213 | R38: =IFERROR(_xlfn.XLOOKUP($K38,Multiples!$B:$B,Multiples!R:R),"") -> 2.2947213 | U38: Baillie Gifford & Co | V38: 0.1422
U39: Vanguard Group Inc. | V39: 0.0976
D40: Opportunities | G40: Threats | K40: Cash Flow Ratios | N40: 2022 | O40: =+N40+1 -> 2023 | P40: =+O40+1 -> 2024 | Q40: =+P40+1 -> 2025 | R40: =+Q40+1 -> 2026 | U40: BlackRock Inc. | V40: 0.0948
D41: Growing E-commerce Market; Global Expansion; Product Innovation: Developing new products in response to trends | G41: Intense Competition: The beauty industry is highly competitive with huge giants; Economic Downturns; Changing Consumer Preferences: Shifts in consumer preferences towards premium or luxury brands | K41: Cash Conversion Cycle | N41: =IFERROR(_xlfn.XLOOKUP($K41,Multiples!$B:$B,Multiples!N:N),"") -> 244.24502 | O41: =IFERROR(_xlfn.XLOOKUP($K41,Multiples!$B:$B,Multiples!O:O),"") -> 180.52541 | P41: =IFERROR(_xlfn.XLOOKUP($K41,Multiples!$B:$B,Multiples!P:P),"") -> 248.3688 | Q41: =IFERROR(_xlfn.XLOOKUP($K41,Multiples!$B:$B,Multiples!Q:Q),"") -> 176.69485 | R41: =IFERROR(_xlfn.XLOOKUP($K41,Multiples!$B:$B,Multiples!R:R),"") -> 164.86016 | U41: JPMorgan Chase & Co. | V41: 0.0505
K42: Net Income / Op Cash Flow | N42: =IFERROR(_xlfn.XLOOKUP($K42,Multiples!$B:$B,Multiples!N:N),"") -> 1.1230769 | O42: =IFERROR(_xlfn.XLOOKUP($K42,Multiples!$B:$B,Multiples!O:O),"") -> 0.60353288 | P42: =IFERROR(_xlfn.XLOOKUP($K42,Multiples!$B:$B,Multiples!P:P),"") -> 1.7935393 | Q42: =IFERROR(_xlfn.XLOOKUP($K42,Multiples!$B:$B,Multiples!Q:Q),"") -> -10.245195 | R42: =IFERROR(_xlfn.XLOOKUP($K42,Multiples!$B:$B,Multiples!R:R),"") -> 0.54538404 | U42: William Blair Inv. Man LLC. | V42: 0.0409
K43: Chg in Cash / Op Cash Flow | N43: =IFERROR(_xlfn.XLOOKUP($K43,Multiples!$B:$B,Multiples!N:N),"") -> -0.73846154 | O43: =IFERROR(_xlfn.XLOOKUP($K43,Multiples!$B:$B,Multiples!O:O),"") -> 0.7595682 | P43: =IFERROR(_xlfn.XLOOKUP($K43,Multiples!$B:$B,Multiples!P:P),"") -> -0.17696629 | Q43: =IFERROR(_xlfn.XLOOKUP($K43,Multiples!$B:$B,Multiples!Q:Q),"") -> 4.7792657 | R43: =IFERROR(_xlfn.XLOOKUP($K43,Multiples!$B:$B,Multiples!R:R),"") -> 0.85761241 | U43: Wellington Management Group LLP | V43: 0.0397
U44: Champlain Investment Partners LLC | V44: 0.0395
D45: Revenue by Region | G45: Revenue by Segment | K45: Leverage Ratios | N45: 2022 | O45: =+N45+1 -> 2023 | P45: =+O45+1 -> 2024 | Q45: =+P45+1 -> 2025 | R45: =+Q45+1 -> 2026 | U45: Clearbridge Investments LLC | V45: 0.0325
K46: Total Debt / Equity | N46: =IFERROR(_xlfn.XLOOKUP($K46,Multiples!$B:$B,Multiples!N:N),"") -> 356.27401 | O46: =IFERROR(_xlfn.XLOOKUP($K46,Multiples!$B:$B,Multiples!O:O),"") -> 186.13139 | P46: =IFERROR(_xlfn.XLOOKUP($K46,Multiples!$B:$B,Multiples!P:P),"") -> 296.14068 | Q46: =IFERROR(_xlfn.XLOOKUP($K46,Multiples!$B:$B,Multiples!Q:Q),"") -> -4.9765523e-08 | R46: =IFERROR(_xlfn.XLOOKUP($K46,Multiples!$B:$B,Multiples!R:R),"") -> -5.1188147e-08 | U46: State Street Corporation | V46: 0.031
K47: Total Debt / Capital | N47: =IFERROR(_xlfn.XLOOKUP($K47,Multiples!$B:$B,Multiples!N:N),"") -> 0.99720103 | O47: =IFERROR(_xlfn.XLOOKUP($K47,Multiples!$B:$B,Multiples!O:O),"") -> 0.99465616 | P47: =IFERROR(_xlfn.XLOOKUP($K47,Multiples!$B:$B,Multiples!P:P),"") -> 0.99663459 | Q47: =IFERROR(_xlfn.XLOOKUP($K47,Multiples!$B:$B,Multiples!Q:Q),"") -> -4.9765525e-08 | R47: =IFERROR(_xlfn.XLOOKUP($K47,Multiples!$B:$B,Multiples!R:R),"") -> -5.1188149e-08 | U47: Morgan Stanley | V47: 0.0211
K48: Total Liabilities / Total Assets | N48: =IFERROR(_xlfn.XLOOKUP($K48,Multiples!$B:$B,Multiples!N:N),"") -> 0.36837849 | O48: =IFERROR(_xlfn.XLOOKUP($K48,Multiples!$B:$B,Multiples!O:O),"") -> 0.30993956 | P48: =IFERROR(_xlfn.XLOOKUP($K48,Multiples!$B:$B,Multiples!P:P),"") -> 0.43097494 | Q48: =IFERROR(_xlfn.XLOOKUP($K48,Multiples!$B:$B,Multiples!Q:Q),"") -> 3180135 | R48: =IFERROR(_xlfn.XLOOKUP($K48,Multiples!$B:$B,Multiples!R:R),"") -> 3180135
K49: Total Debt / EBITDA | N49: =IFERROR(_xlfn.XLOOKUP($K49,Multiples!$B:$B,Multiples!N:N),"") -> 3.7857143 | O49: =IFERROR(_xlfn.XLOOKUP($K49,Multiples!$B:$B,Multiples!O:O),"") -> 1.123348 | P49: =IFERROR(_xlfn.XLOOKUP($K49,Multiples!$B:$B,Multiples!P:P),"") -> 1.2712091 | Q49: =IFERROR(_xlfn.XLOOKUP($K49,Multiples!$B:$B,Multiples!Q:Q),"") -> 1.6364383 | R49: =IFERROR(_xlfn.XLOOKUP($K49,Multiples!$B:$B,Multiples!R:R),"") -> 1.1478647 | U49: Board of Directors
K50: Total Debt / (EBITDA - Capex) | N50: =IFERROR(_xlfn.XLOOKUP($K50,Multiples!$B:$B,Multiples!N:N),"") -> 4.5243902 | O50: =IFERROR(_xlfn.XLOOKUP($K50,Multiples!$B:$B,Multiples!O:O),"") -> 1.1521084 | P50: =IFERROR(_xlfn.XLOOKUP($K50,Multiples!$B:$B,Multiples!P:P),"") -> 1.3496454 | Q50: =IFERROR(_xlfn.XLOOKUP($K50,Multiples!$B:$B,Multiples!Q:Q),"") -> 1.7687659 | R50: =IFERROR(_xlfn.XLOOKUP($K50,Multiples!$B:$B,Multiples!R:R),"") -> 1.2145293 | U50: T. Amin (Chairman, CEO 2014–present) [Non-Indep.], Nom. & Gov. T. Daniele [Indep.], Audit & Risk. L. Keith [Indep.], Comp. L. Cooks Levitan [Indep.], Chair Comp.​ K. Mitchell [Indep.], Nom. & Gov. B. Pritchard [Indep.], Lead Indep. Dir., Audit & Risk. G. Tait [Indep.], Chair Audit & Risk.​ M. Watson [Indep.], Nom. & Gov. M. Ferreras [Indep.], Comp.
K51: Net Debt / EBITDA | N51: =IFERROR(_xlfn.XLOOKUP($K50,Multiples!$B:$B,Multiples!N:N),"") -> 4.5243902 | O51: =IFERROR(_xlfn.XLOOKUP($K50,Multiples!$B:$B,Multiples!O:O),"") -> 1.1521084 | P51: =IFERROR(_xlfn.XLOOKUP($K50,Multiples!$B:$B,Multiples!P:P),"") -> 1.3496454 | Q51: =IFERROR(_xlfn.XLOOKUP($K50,Multiples!$B:$B,Multiples!Q:Q),"") -> 1.7687659 | R51: =IFERROR(_xlfn.XLOOKUP($K50,Multiples!$B:$B,Multiples!R:R),"") -> 1.2145293
K53: Solvency Ratios | N53: 2022 | O53: =+N53+1 -> 2023 | P53: =+O53+1 -> 2024 | Q53: =+P53+1 -> 2025 | R53: =+Q53+1 -> 2026
K54: EBIT / Interest Expense | N54: =IFERROR(_xlfn.XLOOKUP($K54,Multiples!$B:$B,Multiples!N:N),"") -> 0.95833333 | O54: =IFERROR(_xlfn.XLOOKUP($K54,Multiples!$B:$B,Multiples!O:O),"") -> 22.95 | P54: =IFERROR(_xlfn.XLOOKUP($K54,Multiples!$B:$B,Multiples!P:P),"") -> 16.257143 | Q54: =IFERROR(_xlfn.XLOOKUP($K54,Multiples!$B:$B,Multiples!Q:Q),"") -> N/A | R54: =IFERROR(_xlfn.XLOOKUP($K54,Multiples!$B:$B,Multiples!R:R),"") -> 0
K55: EBITDA / Interest Expense | N55: =IFERROR(_xlfn.XLOOKUP($K55,Multiples!$B:$B,Multiples!N:N),"") -> 12.25 | O55: =IFERROR(_xlfn.XLOOKUP($K55,Multiples!$B:$B,Multiples!O:O),"") -> 34.05 | P55: =IFERROR(_xlfn.XLOOKUP($K55,Multiples!$B:$B,Multiples!P:P),"") -> 21.385714 | Q55: =IFERROR(_xlfn.XLOOKUP($K55,Multiples!$B:$B,Multiples!Q:Q),"") -> 15.791573 | R55: =IFERROR(_xlfn.XLOOKUP($K55,Multiples!$B:$B,Multiples!R:R),"") -> 21.822708
K56: (EBITDA - Capex) / Interest Expense | N56: =IFERROR(_xlfn.XLOOKUP($K56,Multiples!$B:$B,Multiples!N:N),"") -> 14.25 | O56: =IFERROR(_xlfn.XLOOKUP($K56,Multiples!$B:$B,Multiples!O:O),"") -> 34.9 | P56: =IFERROR(_xlfn.XLOOKUP($K56,Multiples!$B:$B,Multiples!P:P),"") -> 22.628571 | Q56: =IFERROR(_xlfn.XLOOKUP($K56,Multiples!$B:$B,Multiples!Q:Q),"") -> 16.972996 | R56: =IFERROR(_xlfn.XLOOKUP($K56,Multiples!$B:$B,Multiples!R:R),"") -> 23.020539
D58: Debt Schedule | K58: Stock Performance
U60: ESG Traffic Light
U61: LSEG ESG Score | V61: =ESG!C14 -> 45
U62: E-Score | V62: =ESG!C15 -> 49
U63: S-Score | V63: =ESG!C16 -> 50
U64: G-Score | V64: =ESG!C17 -> 39
U65: S&P Global ESG Score | V65: =ESG!C18 -> 26
U66: Environmental | V66: =ESG!C19 -> 16
U67: Social | V67: =ESG!C20 -> 28
U68: Governance & Economic | V68: =ESG!C21 -> 33
U69: Sustainalytics | V69: =ESG!C22 -> 21.5
U70: ISS ESG Corporate Rating | V70: =ESG!C23 -> C-
U71: SDG Impact Rating | V71: =ESG!C24 -> 0.2
U72: Governance Quality Score | V72: =ESG!C25 -> 7
U73: MSCI ESG Ratings | V73: =ESG!C26 -> BBB
U75: Disclaimer: This material has been prepared solely for educational and informational purposes, based on information available to the general public and from sources considered reliable. This research is part of the activities of the Lisbon Investment Society (LIS). It does not constitute, and should not be interpreted as, investment advice, financial advice, or a recommendation to buy or sell any financial instruments. The views expressed are those of the authors and do not necessarily reflect the official position of LIS. The authors assume no responsibility for the accuracy of the information provided, neither should anything contained herein be taken as an indication that any result will be achieved. Investors should conduct their own research and consult with qualified financial advisors before making any investment decisions.
D80: Extra Notes

Sheet Segments
B2: Segments
B4: Regions | D4: Weight | E4: 2020 | F4: =+E4+1 -> 2021 | G4: =+F4+1 -> 2022 | H4: =+G4+1 -> 2023 | I4: =+H4+1 -> 2024 | J4: ="CAGR "&$G$4&" - "&$I$4 -> CAGR 2022 - 2024 | K4: 2021 | L4: =+K4+1 -> 2022 | M4: =+L4+1 -> 2023 | N4: =+M4+1 -> 2024
B6: United States | D6: =IFERROR(I6/SUM($I$6:$I$12),"") -> 0.84775391 | E6: 255.3 | F6: 284.2 | G6: 347.5 | H6: 506.8 | I6: 868.1 | J6: =IFERROR((I6/G6)^(1/COUNT($G$4:$I$4))-1,"") -> 0.35687024 | K6: =IFERROR((F6-E6)/E6,"") -> 0.11320016 | L6: =IFERROR((G6-F6)/F6,"") -> 0.22273047 | M6: =IFERROR((H6-G6)/G6,"") -> 0.45841727 | N6: =IFERROR((I6-H6)/H6,"") -> 0.7129045 | AB6: United States | AC6: 0.848
B7: Other International | D7: =IFERROR(I7/SUM($I$6:$I$12),"") -> 0.15224609 | E7: 27.6 | F7: 33.9 | G7: 44.7 | H7: 72.1 | I7: 155.9 | J7: =IFERROR((I7/G7)^(1/COUNT($G$4:$I$4))-1,"") -> 0.51651321 | K7: =IFERROR((F7-E7)/E7,"") -> 0.22826087 | L7: =IFERROR((G7-F7)/F7,"") -> 0.31858407 | M7: =IFERROR((H7-G7)/G7,"") -> 0.61297539 | N7: =IFERROR((I7-H7)/H7,"") -> 1.1622746 | AB7: Canada | AC7: =15.2%/3 -> 0.050666667
D8: =IFERROR(I8/SUM($I$6:$I$12),"") -> 0 | J8: =IFERROR((I8/E8)^(1/COUNT($E$4:$I$4))-1,"") | K8: =IFERROR(F8-E8/E8,"") | L8: =IFERROR(G8-F8/F8,"") | M8: =IFERROR(H8-G8/G8,"") | N8: =IFERROR((I8-H8)/H8,"") | AB8: Australia | AC8: =15.2%/(13*3) -> 0.0038974359
D9: =IFERROR(I9/SUM($I$6:$I$12),"") -> 0 | J9: =IFERROR((I9/E9)^(1/COUNT($E$4:$I$4))-1,"") | K9: =IFERROR(F9-E9/E9,"") | L9: =IFERROR(G9-F9/F9,"") | M9: =IFERROR(H9-G9/G9,"") | N9: =IFERROR((I9-H9)/H9,"") | AB9: United Kingdom | AC9: =15.2%/3 -> 0.050666667
D10: =IFERROR(I10/SUM($I$6:$I$12),"") -> 0 | J10: =IFERROR((I10/E10)^(1/COUNT($E$4:$I$4))-1,"") | K10: =IFERROR(F10-E10/E10,"") | L10: =IFERROR(G10-F10/F10,"") | M10: =IFERROR(H10-G10/G10,"") | N10: =IFERROR((I10-H10)/H10,"") | AB10: Saudi Arabia | AC10: =15.2%/(13*3) -> 0.0038974359
D11: =IFERROR(I11/SUM($I$6:$I$12),"") -> 0 | AB11: France | AC11: =15.2%/(13*3) -> 0.0038974359
D12: =IFERROR(I12/SUM($I$6:$I$12),"") -> 0 | AB12: Colombia | AC12: =15.2%/(13*3) -> 0.0038974359
B13: Total | D13: =SUM(D6:D12) -> 1 | E13: =SUM(E6:E10) -> 282.9 | F13: =SUM(F6:F10) -> 318.1 | G13: =SUM(G6:G10) -> 392.2 | H13: =SUM(H6:H10) -> 578.9 | I13: =SUM(I6:I10) -> 1024 | J13: =IFERROR((I13/G13)^(1/COUNT($G$4:$I$4))-1,"") -> 0.37699001 | K13: =IFERROR(F13-E13/E13,"") -> 317.1 | L13: =IFERROR(G13-F13/F13,"") -> 391.2 | M13: =IFERROR((H13-G13)/G13,"") -> 0.47603264 | N13: =IFERROR((I13-H13)/H13,"") -> 0.768872 | AB13: Spain | AC13: =15.2%/(13*3) -> 0.0038974359
AB14: Germany | AC14: =15.2%/(13*3) -> 0.0038974359
B15: Segments | D15: Weight | E15: 2020 | F15: =+E15+1 -> 2021 | G15: =+F15+1 -> 2022 | H15: =+G15+1 -> 2023 | I15: =+H15+1 -> 2024 | J15: ="CAGR "&$E$4&" - "&$I$4 -> CAGR 2020 - 2024 | K15: 2021 | L15: =+K15+1 -> 2022 | M15: =+L15+1 -> 2023 | N15: =+M15+1 -> 2024 | AB15: Mexico | AC15: =15.2%/(13*3) -> 0.0038974359
AB16: Italy | AC16: =15.2%/(13*3) -> 0.0038974359
B17: Beauty and Cosmetics | D17: =IFERROR(I17/SUM($I$17:$I$21),"") -> 1 | E17: 283 | F17: 318 | G17: 392 | H17: 579 | I17: 1024 | J17: =IFERROR((I17/E17)^(1/COUNT($E$4:$I$4))-1,"") -> 0.2933102 | K17: =IFERROR((F17-E17)/E17,"") -> 0.12367491 | L17: =IFERROR((G17-F17)/F17,"") -> 0.2327044 | M17: =IFERROR((H17-G17)/G17,"") -> 0.47704082 | N17: =IFERROR((I17-H17)/H17,"") -> 0.76856649 | AB17: Netherlands | AC17: =15.2%/(13*3) -> 0.0038974359
D18: =IFERROR(I18/SUM($I$17:$I$21),"") -> 0 | J18: =IFERROR((I18/E18)^(1/COUNT($E$4:$I$4))-1,"") | K18: =IFERROR((F18-E18)/E18,"") | L18: =IFERROR((G18-F18)/F18,"") | M18: =IFERROR((H18-G18)/G18,"") | N18: =IFERROR((I18-H18)/H18,"") | AB18: Sweden | AC18: =15.2%/(13*3) -> 0.0038974359
D19: =IFERROR(I19/SUM($I$17:$I$21),"") -> 0 | J19: =IFERROR((I19/E19)^(1/COUNT($E$4:$I$4))-1,"") | K19: =IFERROR((F19-E19)/E19,"") | L19: =IFERROR((G19-F19)/F19,"") | M19: =IFERROR((H19-G19)/G19,"") | N19: =IFERROR((I19-H19)/H19,"") | AB19: Norway | AC19: =15.2%/(13*3) -> 0.0038974359
D20: =IFERROR(I20/SUM($I$17:$I$21),"") -> 0 | J20: =IFERROR((I20/E20)^(1/COUNT($E$4:$I$4))-1,"") | K20: =IFERROR((F20-E20)/E20,"") | L20: =IFERROR((G20-F20)/F20,"") | M20: =IFERROR((H20-G20)/G20,"") | N20: =IFERROR((I20-H20)/H20,"") | AB20: Denmark | AC20: =15.2%/(13*3) -> 0.0038974359
D21: =IFERROR(I21/SUM($I$17:$I$21),"") -> 0 | J21: =IFERROR((I21/E21)^(1/COUNT($E$4:$I$4))-1,"") | K21: =IFERROR((F21-E21)/E21,"") | L21: =IFERROR((G21-F21)/F21,"") | M21: =IFERROR((H21-G21)/G21,"") | N21: =IFERROR((I21-H21)/H21,"") | AB21: Finland | AC21: =15.2%/(13*3) -> 0.0038974359
B22: Total | D22: =SUM(D17:D21) -> 1 | E22: =SUM(E17:E21) -> 283 | F22: =SUM(F17:F21) -> 318 | G22: =SUM(G17:G21) -> 392 | H22: =SUM(H17:H21) -> 579 | I22: =SUM(I17:I21) -> 1024 | J22: =IFERROR((I22/E22)^(1/COUNT($E$4:$I$4))-1,"") -> 0.2933102 | K22: =IFERROR((F22-E22)/E22,"") -> 0.12367491 | L22: =IFERROR((G22-F22)/F22,"") -> 0.2327044 | M22: =IFERROR((H22-G22)/G22,"") -> 0.47704082 | N22: =IFERROR((I22-H22)/H22,"") -> 0.76856649 | AC22: 0
B24: Categories | D24: Description | J24: Graphs | AC24: =SUM(AC6:AC21) -> 1
B26: Eye, lip and face makeup | D26: Includes products designed to enhance and alter appearance, helping individuals achieve various looks. It can be divided in three subcategorys: eye makeup, lip makeup and face makeup.
B27: Skin care | D27: Promotes healthy skin, offering a range of products to various skin concerns, including acne, sensitivity and dryness. The products are designed to cleanse, treat, hydrate and protect the skin.
B28: Beauty tools and acessories | D28: Includes products designed to enhance the application, blending and maintenance of makeup and skincare. Help users achieve professional-looking results and improve the overall effectiveness of beauty routines.
B29: =IF(B20=0,"",B20)
B30: =IF(B21=0,"",B21)
B32: Products | D32: Weight | E32: 2020 | F32: =+E32+1 -> 2021 | G32: =+F32+1 -> 2022 | H32: =+G32+1 -> 2023 | I32: =+H32+1 -> 2024 | J32: =I32+1 -> 2025 | K32: =+J32+1 -> 2026 | L32: =+K32+1 -> 2027 | M32: =+L32+1 -> 2028 | N32: =+M32+1 -> 2029 | O32: =+N32+1 -> 2030 | P32: =+O32+1 -> 2031 | Q32: =+P32+1 -> 2032 | R32: =+Q32+1 -> 2033 | ... T32: =+S32+1 -> 2035
D34: =IFERROR(I34/$I$13,"") -> 0
D36: =IFERROR(I36/$I$13,"") -> 0
F37: =IFERROR((F36-E36)/E36,"") | G37: =IFERROR((G36-F36)/F36,"") | H37: =IFERROR((H36-G36)/G36,"") | I37: =IFERROR((I36-H36)/H36,"")
B38: Product 3 | D38: =IFERROR(I38/$I$13,"") -> 0 | J38: =I38*(1+J39) -> 0 | K38: =J38*(1+K39) -> 0 | L38: =K38*(1+L39) -> 0 | M38: =L38*(1+M39) -> 0 | N38: =M38*(1+N39) -> 0 | O38: =N38*(1+O39) -> 0 | P38: =O38*(1+P39) -> 0 | Q38: =P38*(1+Q39) -> 0 | ... T38: =S38*(1+T39) -> 0
F39: =IFERROR(F38-E38/E38,"") | G39: =IFERROR(G38-F38/F38,"") | H39: =IFERROR(H38-G38/G38,"") | I39: =IFERROR(I38-H38/H38,"")
B40: Product 4 | D40: =IFERROR(I40/$I$13,"") -> 0 | J40: =I40*(1+J41) -> 0 | K40: =J40*(1+K41) -> 0 | L40: =K40*(1+L41) -> 0 | M40: =L40*(1+M41) -> 0 | N40: =M40*(1+N41) -> 0 | O40: =N40*(1+O41) -> 0 | P40: =O40*(1+P41) -> 0 | Q40: =P40*(1+Q41) -> 0 | ... T40: =S40*(1+T41) -> 0
F41: =IFERROR(F40-E40/E40,"") | G41: =IFERROR(G40-F40/F40,"") | H41: =IFERROR(H40-G40/G40,"") | I41: =IFERROR(I40-H40/H40,"")
B42: Product 5 | D42: =IFERROR(I42/$I$13,"") -> 0 | J42: =I42*(1+J43) -> 0 | K42: =J42*(1+K43) -> 0 | L42: =K42*(1+L43) -> 0 | M42: =L42*(1+M43) -> 0 | N42: =M42*(1+N43) -> 0 | O42: =N42*(1+O43) -> 0 | P42: =O42*(1+P43) -> 0 | Q42: =P42*(1+Q43) -> 0 | ... T42: =S42*(1+T43) -> 0
F43: =IFERROR(F42-E42/E42,"") | G43: =IFERROR(G42-F42/F42,"") | H43: =IFERROR(H42-G42/G42,"") | I43: =IFERROR(I42-H42/H42,"")
B44: Total | D44: =SUM(D34:D42) -> 0 | E44: =SUM(E34:E42) -> 0 | F44: =SUM(F34:F42) -> 0 | G44: =SUM(G34:G42) -> 0 | H44: =SUM(H34:H42) -> 0 | I44: =SUM(I34:I42) -> 0 | J44: =SUM(J34:J42) -> 0 | K44: =SUM(K34:K42) -> 0 | ... T44: =SUM(T34:T42) -> 0
B46: Company's Strategy / Extra Notes
B48: Business strategy relies on offering affordable, innovative and high-quality products to achieve high, sustainable and profitable growth.
B49: Strategic focus areas: value proposition, digital leadership, powerhouse innovation, disruptive marketing engine.
B50: Geographic expansion is a top priority, including both retail and online international distribution, having recently expanded to Mexico and Germany.
B51: Its main focus is delivering clean, vegan and cruelty-free products, continuing to move towards sustainable packaging and ethical sourcing.
B52: While organic growth is key, the company is starting to acquire mission-aligned brands with complementary values, such as Naturium in 2024, to expand into performance skincare.
B53: It is actively introducing new products to the market and expanding beyond color cosmetics into skincare, hybrid beauty and adjacent categories, reflecting the importance to meet consumer demand.
B54: It doesn't have a dividend policiy, focusing on reinvestment and growth, not near-term shareholder payouts.
B55: It has unusually high gross margins, aproximately 71%, which is well above average, revealing excellent supply chain and pricing strategy.
B56: It operates with low leverage, also meaning a high investment capacity that gives the company flexibility to acquire and expand more.
B57: It relies on a strong social media presence and viral marketing campains, deeply investing in direct-to-consumer channels, making it a priority to lead the beauty industry in digital engagement and e-commerce.
B132: Cosmetics | C132: Skincare | D132: Others

Sheet Industry
B2: Industry Overview
B4: Sales Growth Forecast | E4: Weight | F4: 2025 | G4: =+F4+1 -> 2026 | H4: =+G4+1 -> 2027 | I4: =+H4+1 -> 2028 | J4: =+I4+1 -> 2029 | K4: =+J4+1 -> 2030 | L4: =+K4+1 -> 2031 | M4: =+L4+1 -> 2032 | N4: =+M4+1 -> 2033 | ... P4: =+O4+1 -> 2035 | Q4: ="CAGR "&$F$4&" - "&$P$4 -> CAGR 2025 - 2035 | R4: Sources
B6: Color Cosmetics | E6: 0.524 | F6: 0.148 | G6: 0.125 | H6: 0.107 | I6: 0.093 | J6: 0.082 | K6: 0.075 | L6: 0.068 | M6: 0.063 | N6: 0.058 | O6: 0.055 | P6: 0.052 | Q6: 0.072 | R6: Grand View Research
B7: Skincare | E7: 0.287 | F7: 0.189 | G7: 0.162 | H7: 0.138 | I7: 0.116 | J7: 0.102 | K7: 0.094 | L7: 0.087 | M7: 0.081 | N7: 0.076 | O7: 0.072 | P7: 0.068 | Q7: 0.0353 | R7: Statista
B8: Personal care | E8: 0.189 | F8: 0.087 | G8: 0.073 | H8: 0.065 | I8: 0.058 | J8: 0.052 | K8: 0.048 | L8: 0.045 | M8: 0.043 | N8: 0.041 | O8: 0.039 | P8: 0.038 | Q8: 0.0298 | R8: Statista
B11: Weighted Average | E11: =SUM(E6:E10) -> 1 | F11: =SUMPRODUCT(F6:F10,$E$6:$E$10) -> 0.148238 | G11: =SUMPRODUCT(G6:G10,$E$6:$E$10) -> 0.125791 | H11: =SUMPRODUCT(H6:H10,$E$6:$E$10) -> 0.107959 | I11: =SUMPRODUCT(I6:I10,$E$6:$E$10) -> 0.092986 | J11: =SUMPRODUCT(J6:J10,$E$6:$E$10) -> 0.08207 | K11: =SUMPRODUCT(K6:K10,$E$6:$E$10) -> 0.07535 | L11: =SUMPRODUCT(L6:L10,$E$6:$E$10) -> 0.069106 | M11: =SUMPRODUCT(M6:M10,$E$6:$E$10) -> 0.064386 | ... P11: =SUMPRODUCT(P6:P10,$E$6:$E$10) -> 0.053946 | Q11: =IFERROR(((1+F11)*(1+G11)*(1+H11)*(1+I11)*(1+J11)*(1+K11)*(1+L11)*(1+M11)*(1+N11)*(1+O11)*(1+P11))^(1/COUNT($F$4:$P$4))-1,"") -> 0.084760722
B13: Key Drivers | E13: Description
B15: Inclusive and Accessible Products | E15: Focuses on clean, vegan, cruelty-free products at affordable price points, disrupting industry norms.
B16: Powerhouse Innovation | E16: Recognized for rapid product development and first-to-market launches, including dermatologist-developed formulas
B17: Digital Marketing Leadership | E17: Leverages social media platforms to connect with consumers and drive engagement.
B18: Retail Partnerships | E18: Strong relationships with major retailers like Target, Walmart, and Ulta Beauty expand distribution channels domestically and internationally.
B20: Industry Trends | E20: Description
B22: Increased Premiumization | E22: Consumers trading up for high-quality, prestige-inspired products at accessible price points.
B23: Sustainability and Corporate Social Responsibility | E23: Growing consumer demand for clean ingredients, cruelty-free formulations, and environmentally friendly packaging.
B26: Market Share | E26: Headquarters | G26: Revenues | H26: (in MM of USD) | I26: Market Share
B28: {=+_FV(DCF!R4,"Name")} -> E.L.F. BEAUTY, INC. | E28: United States | G28: {=TRANSPOSE(Peers!D91:N91)} -> 1023.9 | I28: =IFERROR(G28/$G$40,"") -> 0.0053889474
B29: L'Oréal S.A. | E29: France | G29: 43486 | I29: =IFERROR(G29/$G$40,"") -> 0.22887368
B30: Estee Lauder Companies Inc. | E30: United States | G30: 15608 | I30: =IFERROR(G30/$G$40,"") -> 0.082147368
B31: Coty Inc. | E31: United States | G31: 6118 | I31: =IFERROR(G32/$G$40,"") -> 0.058984211
B32: Ultra Beauty | E32: United States | G32: 11207 | I32: =IFERROR(G32/$G$40,"") -> 0.058984211
B33: Shiseido Company | E33: Japan | G33: 6545 | I33: =IFERROR(G33/$G$40,"") -> 0.034447368
B34: Natura &Co Holding S.A. | E34: Brazil | G34: 4487 | I34: =IFERROR(G34/$G$40,"") -> 0.023615789
G35: 0 | I35: =IFERROR(G35/$G$40,"") -> 0
G36: 0 | I36: =IFERROR(G36/$G$40,"") -> 0
B37: {=+_FV(Peers!#REF!,"Name")} -> #VALUE! | G37: 0 | I37: =IFERROR(G37/$G$40,"") -> 0
B38: {=+_FV(Peers!#REF!,"Name")} -> #VALUE! | G38: 0 | I38: =IFERROR(G38/$G$40,"") -> 0
B39: Others | E39: -- | I39: =IFERROR(G39/$G$40,"") -> 0
B40: Industry Size | E40: -- | G40: 190000 | I40: 1
B42: Porter's Five Forces Analysis | E42: Rating | H42: Graph
B44: Threat of New Entrants | E44: =IFERROR(AVERAGE(E45:E50),"") -> 2.6666667
B45: Economies of scale | E45: 3
B46: Product differentiation | E46: 3
B47: Capital requirements | E47: 2
B48: Access to distribution channels | E48: 3
B49: Regulations | E49: 3
B50: Switching costs | E50: 2
B51: Bargaining Power of Suppliers | E51: =IFERROR(AVERAGE(E52:E56),"") -> 2.6
B52: Number of suppliers | E52: 4
B53: Uniqueness | E53: 3
B54: Switching Costs | E54: 2
B55: Forward Integration | E55: 1
B56: Industry Importance | E56: 3
B57: Bargaining Power of Customers | E57: =IFERROR(AVERAGE(E58:E62),"") -> 3.8
B58: Number of buyers | E58: 4
B59: Purchase size | E59: 3
B60: Switching costs | E60: 2
B61: Price sensitivity | E61: 5
B62: Informed buyers | E62: 5
B63: Competitive Rivalry | E63: =IFERROR(AVERAGE(E64:E68),"") -> 4
B64: Number of competitors | E64: 5
B65: Industry growth | E65: 3
B66: Similarities in what's offered | E66: 4
B67: Exit barriers | E67: 4
B68: Fixed costs | E68: 4
B69: Threat of Substitutes | E69: =IFERROR(AVERAGE(E70:E74),"") -> 3.75
B70: Relative price performance | E70: 4
B71: Customer willingness to go elsewhere | E71: 4
B72: The sense that products are similar | E72: 3
B73: Availability of close substitutes | E73: 4

Sheet Peers
D3: Revenue Growth | F3: EBITDA Margin | H3: Profit Margin | J3: EV / Revenue | L3: EV / EBITDA | N3: Price / Earnings
B4: Peers | C4: Ticker | D4: =+Inputs!O4&"-"&Inputs!P4 -> 2022-2023 | E4: =+Inputs!P4&"-"&Inputs!Q4 -> 2023-2024 | F4: 2023 | G4: 2024 | H4: =+Inputs!O4&"-"&Inputs!P4 -> 2022-2023 | I4: =+Inputs!P4&"-"&Inputs!Q4 -> 2023-2024 | J4: 2023 | K4: 2024 | L4: 2023 | M4: 2024 | N4: 2023 | O4: 2024
A5: =+D85 -> #VALUE! | B5: {=IFERROR(_FV(A5,"Name"),"")} -> E.L.F. BEAUTY, INC. | C5: {=IFERROR(_FV(A5,"Ticker symbol",TRUE),"")} -> ELF | D5: =IFERROR(D88/D87-1,"") -> 0.47577766 | E5: =IFERROR(D91/D88-1,"") -> 0.76900484 | F5: =IFERROR(D89/D88,"") -> 0.11765722 | G5: =IFERROR(D94/D91,"") -> 0.14620568 | H5: =IFERROR(D90/D88,"") -> 0.10625432 | I5: =IFERROR(D99/D91,"") -> 0.12471921 | J5: {=IFERROR((_FV(A5,"Market cap",TRUE)/1000000+D$115-D$105)/D$88,"")} -> 13.46396 | K5: {=IFERROR((_FV(A5,"Market cap",TRUE)/1000000+D$115-D$105)/D$91,"")} -> 7.6110365 | L5: {=+IFERROR((_FV(A5,"Market cap",TRUE)/1000000+D$115-D$105)/D$89,"")} -> 114.43378 | M5: {=IFERROR((_FV(A5,"Market cap",TRUE)/1000000+D$115-D$105)/D$94,"")} -> 52.057049 | N5: {=IFERROR((_FV(A5,"Market cap",TRUE)/1000000)/D$90,"")} -> 125.37952 | O5: {=IFERROR((_FV(A5,"Market cap",TRUE)/1000000)/D$99,"")} -> 60.382461
A6: #VALUE! | B6: L'Oreal S.A. | C6: {=IFERROR(_FV(A6,"Ticker symbol",TRUE),"")} -> OR | D6: =+IFERROR(E88/E87-1,"") -> 0.07637219 | E6: =IFERROR(E91/E88-1,"") -> 0.055946773 | F6: =IFERROR(E89/E88,"") -> 0.21781361 | G6: =+IFERROR(E94/E91,"") -> 0.22172653 | H6: =IFERROR(E90/E88,"") -> 0.15016269 | I6: =+IFERROR(D99/D93,"") -> 0.17635686 | J6: {=+IFERROR((_FV(A6,"Market cap",TRUE)/1000000+E$115-E$105)/E$88,"")} -> 4.9528508 | K6: {=IFERROR(+(_FV(A6,"Market cap",TRUE)/1000000+E$115-E$105)/E$91,"")} -> 4.690436 | L6: {=IFERROR(+(_FV(A6,"Market cap",TRUE)/1000000+E$115-E$105)/E$89,"")} -> 22.738941 | M6: {=IFERROR(+(_FV(A6,"Market cap",TRUE)/1000000+E$115-E$105)/E$94,"")} -> 21.154149 | N6: {=IFERROR(+(_FV(A6,"Market cap",TRUE)/1000000)/E$90,"")} -> 32.264764 | O6: {=IFERROR(+(_FV(A6,"Market cap",TRUE)/1000000)/E$99,"")} -> 31.136907
A7: #VALUE! | B7: Estée Lauder Companies Inc. | C7: {=IFERROR(_FV(A7,"Ticker symbol",TRUE),"")} -> EL | D7: =IFERROR(F88/F87-1,"") -> -0.10300502 | E7: =IFERROR(+F91/F88-1,"") -> -0.018981772 | F7: =IFERROR(F89/F88,"") -> 0.18925204 | G7: =IFERROR(F94/F91,"") -> 0.18394413 | H7: =IFERROR(F90/F88,"") -> 0.078441232 | I7: =+IFERROR(F99/F91,"") -> 0.059905177 | J7: {=IFERROR(+(_FV(A7,"Market cap",TRUE)/1000000+F$115-F$106)/F$88,"")} -> 2.5199183 | K7: {=IFERROR(+(_FV(A7,"Market cap",TRUE)/1000000+F$115-F$106)/F$91,"")} -> 2.5686763 | L7: {=IFERROR(+(_FV(A7,"Market cap",TRUE)/1000000+F$115-F$106)/F$89,"")} -> 13.315144 | M7: {=IFERROR(+(_FV(A7,"Market cap",TRUE)/1000000+F$115-F$106)/F$94,"")} -> 13.964437 | N7: {=IFERROR(+(_FV(A7,"Market cap",TRUE)/1000000)/F$90,"")} -> 25.632131 | O7: {=IFERROR(+(_FV(A7,"Market cap",TRUE)/1000000)/F$99,"")} -> 34.212727
A8: #VALUE! | B8: Coty Inc. | C8: {=IFERROR(_FV(A8,"Ticker symbol",TRUE),"")} -> COTY | D8: =+IFERROR(G88/G87-1,"") -> 0.047134238 | E8: =IFERROR(G91/G88-1,"") -> 0.10154843 | F8: =IFERROR(G89/G88,"") -> 0.16168527 | G8: =IFERROR(G94/G91,"") -> 0.17325924 | H8: =IFERROR(G90/G88,"") -> 0.03474973 | I8: =+IFERROR(G99/G91,"") -> 0.016018307 | J8: {=IFERROR(+(_FV(A8,"Market cap",TRUE)/1000000+G$115-G$105)/G$88,"")} -> 1.3077059 | K8: {=IFERROR(+(_FV(A8,"Market cap",TRUE)/1000000+G$115-G$105)/G$91,"")} -> 1.1871524 | L8: {=IFERROR(+(_FV(A8,"Market cap",TRUE)/1000000+G$115-G$105)/G$89,"")} -> 8.0879717 | M8: {=IFERROR(+(_FV(A8,"Market cap",TRUE)/1000000+G$115-G$105)/G$94,"")} -> 6.8518854 | N8: {=IFERROR(+(_FV(A8,"Market cap",TRUE)/1000000)/G$90,"")} -> 17.839371 | O8: {=IFERROR(+(_FV(A8,"Market cap",TRUE)/1000000)/G$99,"")} -> 35.132638
A9: #VALUE! | B9: Ulta Beauty | C9: {=IFERROR(_FV(A9,"Ticker symbol",TRUE),"")} -> ULTA | D9: =IFERROR(H88/H87-1,"") -> 0.18282934 | E9: =IFERROR(H91/H88-1,"") -> 0.097756881 | F9: =IFERROR(H89/H88,"") -> 0.2161818 | G9: =IFERROR(H94/H91,"") -> 0.20308736 | H9: =IFERROR(H90/H88,"") -> 0.12224508 | I9: =+IFERROR(H99/H91,"") -> 0.11599893 | J9: {=IFERROR((_FV(A9,"Market cap",TRUE)/1000000+H$115-H$105)/H$88,"")} -> 2.562027 | K9: {=IFERROR(+(_FV(A9,"Market cap",TRUE)/1000000+H$115-H$105)/H$91,"")} -> 2.3338747 | L9: {=IFERROR(+(_FV(A9,"Market cap",TRUE)/1000000+H$115-H$105)/H$89,"")} -> 11.851261 | M9: {=IFERROR(+(_FV(A9,"Market cap",TRUE)/1000000+H$115-H$105)/H$94,"")} -> 11.491975 | N9: {=IFERROR(+(_FV(A9,"Market cap",TRUE)/1000000)/H$90,"")} -> 20.041454 | O9: {=IFERROR(+(_FV(A9,"Market cap",TRUE)/1000000)/H$99,"")} -> 19.239795
A10: #VALUE! | B10: Shiseido Company | C10: 4911 | D10: =+IFERROR(I88/I87-1,"") -> -0.15056923 | E10: =IFERROR(I91/I88-1,"") -> -0.056780516 | F10: =IFERROR(I89/I88,"") -> 0.11601095 | G10: =IFERROR(I94/I91,"") -> 0.11138273 | H10: =IFERROR(I90/I88,"") -> 0.02896671 | I10: =+IFERROR(I99/I91,"") -> 0.0079449962 | J10: {=IFERROR((_FV(A10,"Market cap",TRUE)/1000000+I$115-I$105)/I$88,"")} -> 1.1936757 | K10: {=IFERROR(+(_FV(A10,"Market cap",TRUE)/1000000+I$115-I$105)/I$91,"")} -> 1.2655334 | L10: {=IFERROR(+(_FV(A10,"Market cap",TRUE)/1000000+I$115-I$105)/I$89,"")} -> 10.289337 | M10: {=IFERROR(+(_FV(A10,"Market cap",TRUE)/1000000+I$115-I$105)/I$94,"")} -> 11.362025 | N10: {=IFERROR(+(_FV(A10,"Market cap",TRUE)/1000000)/I$90,"")} -> 33.611522 | O10: {=IFERROR(+(_FV(A10,"Market cap",TRUE)/1000000)/I$99,"")} -> 129.92146
A11: #VALUE! | B11: {=+_FV(A11,"Name")} -> Natura &Co Holding SA | C11: {=IFERROR(_FV(A11,"Ticker symbol",TRUE),"")} -> NTCO3Q | D11: =IFERROR(J88/J87-1,"") -> -0.29924176 | E11: =IFERROR(J91/J88-1,"") -> 0.12908908 | F11: =IFERROR(J89/J88,"") -> 0.19904378 | G11: =IFERROR(J94/J91,"") -> 0.15934923 | H11: =IFERROR(J90/J88,"") -> 0.056618017 | I11: =+IFERROR(J99/J91,"") -> 0.022955204 | J11: {=IFERROR(+(_FV(A11,"Market cap",TRUE)*Q11/1000000+J$115-J$105)/J$88,"")} -> 1.0653106 | K11: {=IFERROR(+(_FV(A11,"Market cap",TRUE)*Q11/1000000+J$115-J$105)/J$91,"")} -> 0.94351329 | L11: {=IFERROR(+(_FV(A11,"Market cap",TRUE)*Q11/1000000+J$115-J$105)/J$89,"")} -> 5.3521418 | M11: {=IFERROR(+(_FV(A11,"Market cap",TRUE)*Q11/1000000+J$115-J$105)/J$94,"")} -> 5.9210408 | N11: {=IFERROR(+(_FV(A11,"Market cap",TRUE)*Q11/1000000)/J$90,"")} -> 16.39353 | O11: {=IFERROR(+(_FV(A11,"Market cap",TRUE)*Q11/1000000)/J$99,"")} -> 35.811108 | P11: #VALUE! | Q11: {=+_FV(P11,"Previous close",TRUE)} -> 0.1873
B12: Average | D12: =IFERROR(AVERAGE(D5:D11),"") -> 0.032756776 | E12: =IFERROR(AVERAGE(E5:E11),"") -> 0.15394053 | F12: =IFERROR(AVERAGE(F5:F11),"") -> 0.17394924 | G12: =IFERROR(AVERAGE(G5:G11),"") -> 0.17127927 | H12: =IFERROR(AVERAGE(H5:H11),"") -> 0.082491111 | I12: =IFERROR(AVERAGE(I5:I11),"") -> 0.074842669 | J12: =IFERROR(AVERAGE(J5:J11),"") -> 3.8664927 | K12: =IFERROR(AVERAGE(K5:K11),"") -> 2.9428889 | ... O12: =IFERROR(AVERAGE(O5:O11),"") -> 49.4053
B13: Deviation from Average | D13: =IFERROR(+D12-D5,"") -> -0.44302089 | E13: =IFERROR(E12-E5,"") -> -0.61506431 | F13: =+IFERROR(F12-F5,"") -> 0.056292018 | G13: =IFERROR(G12-G5,"") -> 0.025073588 | H13: =IFERROR(+H5-H12,"") -> 0.023763208 | I13: =+IFERROR(I5-I12,"") -> 0.049876542 | J13: =+IFERROR(J5-J12,"") -> 9.5974677 | K13: =+IFERROR(K5-K12,"") -> 4.6681475 | L13: =IFERROR(+L5-L12,"") -> 87.852553 | M13: =IFERROR(M5-M12,"") -> 34.513826 | N13: =IFERROR(+N5-N12,"") -> 86.642047 | O13: =IFERROR(+O5-O12,"") -> 10.977161
D15: Trading Multiple | G15: Net | H15: Preferred | I15: Non-Controlling | J15: Equity Value | M15: Implied Upside (Downside)
B16: Implied Share Price | D16: Revenue | E16: EBITDA | F16: P/E | G16: Debt | H16: Stock | I16: Interest | J16: Revenue | K16: EBITDA | L16: P/E | M16: Revenue | N16: EBITDA | O16: P/E | P16: Current Price
B18: Second Minimum | D18: =IFERROR(SMALL(K5:K11,2),"") -> 1.1871524 | E18: =IFERROR(SMALL(M5:M11,2),"") -> 6.8518854 | F18: =IFERROR(SMALL(O5:O11,2),"") -> 31.136907 | G18: =-Inputs!$Q$98+Inputs!$Q$99 -> 82.1 | H18: =+Inputs!$Q$100 -> 0 | I18: =+Inputs!$Q$101 -> 0 | J18: =IFERROR(+D18*$D$91+G18+H18+I18,"") -> 1297.6254 | K18: =IFERROR(E18*$D$94+G18+H18+I18,"") -> 1107.8272 | L18: =IFERROR(F18*$D$99,"") -> 3976.183 | M18: {=IFERROR(+(J18/_FV($A$5,"Shares outstanding",TRUE)*1000000)/$P$18-1,"")} -> -0.83171414 | N18: {=IFERROR((+K18/_FV($A$5,"Shares outstanding",TRUE)*1000000)/$P$18-1,"")} -> -0.8563286 | O18: {=IFERROR(+(L18/_FV($A$5,"Shares outstanding",TRUE)*1000000)/$P$18-1,"")} -> -0.48433856 | P18: {=+_FV(A5,"Price")} -> 135.91
B19: Average | D19: =+IFERROR(AVERAGE(K5:K11),"") -> 2.9428889 | E19: =IFERROR(+AVERAGE(M5:M11),"") -> 17.543223 | F19: =IFERROR(+AVERAGE(O5:O11),"") -> 49.4053 | G19: =-Inputs!$Q$98+Inputs!$Q$99 -> 82.1 | H19: =+Inputs!$Q$100 -> 0 | I19: =+Inputs!$Q$101 -> 0 | J19: =IFERROR(+D19*$D$91+G19+H19+I19,"") -> 3095.324 | K19: =IFERROR(E19*$D$94+G19+H19+I19,"") -> 2708.3205 | L19: =IFERROR(+F19*$D$99,"") -> 6309.0568 | M19: {=IFERROR(+(J19/_FV($A$5,"Shares outstanding",TRUE)*1000000)/$P$18-1,"")} -> -0.59857501 | N19: {=IFERROR((+K19/_FV($A$5,"Shares outstanding",TRUE)*1000000)/$P$18-1,"")} -> -0.64876455 | O19: {=IFERROR(+(L19/_FV($A$5,"Shares outstanding",TRUE)*1000000)/$P$18-1,"")} -> -0.18179387
B20: Median | D20: =IFERROR(MEDIAN(K5:K11),"") -> 2.3338747 | E20: =IFERROR(MEDIAN(M5:M11),"") -> 11.491975 | F20: =IFERROR(MEDIAN(O5:O11),"") -> 35.132638 | G20: =-Inputs!$Q$98+Inputs!$Q$99 -> 82.1 | H20: =+Inputs!$Q$100 -> 0 | I20: =+Inputs!$Q$101 -> 0 | J20: =IFERROR(D20*$D$91+G20+H20+I20,"") -> 2471.7543 | K20: =IFERROR(E20*$D$94+G20+H20+I20,"") -> 1802.4486 | L20: =IFERROR(+F20*$D$99,"") -> 4486.4379 | M20: {=IFERROR(+(J20/_FV($A$5,"Shares outstanding",TRUE)*1000000)/$P$18-1,"")} -> -0.67944423 | N20: {=IFERROR((+K20/_FV($A$5,"Shares outstanding",TRUE)*1000000)/$P$18-1,"")} -> -0.76624485 | O20: {=+IFERROR((L20/_FV($A$5,"Shares outstanding",TRUE)*1000000)/$P$18-1,"")} -> -0.41816485
B21: Second Maximum | D21: =IFERROR(LARGE(K5:K11,2),"") -> 4.690436 | E21: =IFERROR(LARGE(M5:M11,2),"") -> 21.154149 | F21: =IFERROR(LARGE(O5:O11,2),"") -> 60.382461 | G21: =-Inputs!$Q$98+Inputs!$Q$99 -> 82.1 | H21: =+Inputs!$Q$100 -> 0 | I21: =+Inputs!$Q$101 -> 0 | J21: =IFERROR(+D21*$D$91+G21+H21+I21,"") -> 4884.6374 | K21: =IFERROR(E21*$D$94+G21+H21+I21,"") -> 3248.876 | L21: =IFERROR(+F21*$D$99,"") -> 7710.8403 | M21: {=IFERROR(+(J21/_FV($A$5,"Shares outstanding",TRUE)*1000000)/$P$18-1,"")} -> -0.36652333 | N21: {=IFERROR((+K21/_FV($A$5,"Shares outstanding",TRUE)*1000000)/$P$18-1,"")} -> -0.57866122 | O21: {=IFERROR(+(L21/_FV($A$5,"Shares outstanding",TRUE)*1000000)/$P$18-1,"")} -> 0
B23: Profitability | D23: =+LEFT(B5, FIND(" ", B5 & " ") - 1) -> E.L.F. | E23: =+LEFT(B6, FIND(" ", B6 & " ") - 1) -> L'Oreal | F23: =+_xlfn.TEXTBEFORE(B7, " ",2) -> Estée Lauder | G23: =+LEFT(B8, FIND(" ", B8 & " ") - 1) -> Coty | H23: =B9 -> Ulta Beauty | I23: =+LEFT(B10, FIND(" ", B10 & " ") - 1) -> Shiseido | J23: =+LEFT(B11, FIND(" ", B11 & " ") - 1) -> Natura | L23: =+LEFT(#REF!, FIND(" ",#REF! & " ") - 1) -> #REF! | M23: =+LEFT(#REF!, FIND(" ",#REF! & " ") - 1) -> #REF! | N23: =+LEFT(#REF!, FIND(" ",#REF! & " ") - 1) -> #REF! | O23: Average
B25: Operating Margin | D25: =IFERROR(D95/D91,"") -> 0.11114367 | E25: =IFERROR(E95/E91,"") -> 0.19951249 | F25: =IFERROR(F95/F91,"") -> 0.1017427 | G25: =IFERROR(G95/G91,"") -> 0.094965675 | H25: =IFERROR(H95/H91,"") -> 0.15070938 | I25: =IFERROR(I95/I91,"") -> 0.034988541 | J25: =IFERROR(J95/J91,"") -> 0.11901047 | K25: =IFERROR(K95/K91,"") | ... N25: =IFERROR(N95/N91,"") | O25: =IFERROR(+AVERAGE(D25:N25),"") -> 0.11601042
B26: Net Income Margin | D26: =IFERROR(D99/D91,"") -> 0.12471921 | E26: =IFERROR(E99/E91,"") -> 0.14735777 | F26: =IFERROR(F99/F91,"") -> 0.059905177 | G26: =IFERROR(G99/G91,"") -> 0.016018307 | H26: =IFERROR(H99/H91,"") -> 0.11599893 | I26: =IFERROR(I99/I91,"") -> 0.0079449962 | J26: =IFERROR(J99/J91,"") -> 0.022955204 | K26: =IFERROR(K99/K91,"") | ... N26: =IFERROR(N99/N91,"") | O26: =IFERROR(+AVERAGE(D26:N26),"") -> 0.070699942
B27: ROA (%) | D27: =IFERROR(D99/D111,"") -> 0.1130789 | E27: =IFERROR(E99/E111,"") -> 0.11371178 | F27: =IFERROR(F99/F111,"") -> 0.043133275 | G27: =IFERROR(G99/G111,"") -> 0.0081105686 | H27: =IFERROR(H99/H111,"") -> 0.22779043 | I27: =IFERROR(I99/I111,"") -> 0.0061443932 | J27: =IFERROR(J99/J111,"") -> 0.017115321 | K27: =IFERROR(K99/K111,"") | ... N27: =IFERROR(N99/N111,"") | O27: =IFERROR(+AVERAGE(D27:N27),"") -> 0.075583524
B28: Financial Cost of Debt | D28: =IFERROR(+(D96/D115)*(1-(D98/D97)),"") -> 0.032129149 | E28: =IFERROR(+(E96/E115)*(1-(E98/E97)),"") -> 0.019618509 | F28: =IFERROR(+(F96/F115)*(1-(F98/F97)),"") -> 0.014732027 | G28: =IFERROR(+(G96/G115)*(1-(G98/G97)),"") -> 0.033718338 | H28: =IFERROR(+(H96/H115)*(1-(H98/H97)),"") -> -0.0071733439 | I28: =IFERROR(+(I96/I115)*(1-(I98/I97)),"") -> -0.0032989753 | J28: =IFERROR(+(J96/J115)*(1-(J98/J97)),"") -> 0.0092334376 | K28: =IFERROR(+(K96/K115)*(1-(K98/K97)),"") | ... N28: =IFERROR(+(N96/N115)*(1-(N98/N97)),"") | O28: =IFERROR(+AVERAGE(D28:N28),"") -> 0.01413702
B29: Return on Equity (RoE) | D29: =IFERROR(+D99/D116,"") -> 0.19872393 | E29: =IFERROR(+E99/E116,"") -> 0.193379 | F29: =IFERROR(+F99/F116,"") -> 0.17595032 | G29: =IFERROR(+G99/G116,"") -> 0.02306968 | H29: =IFERROR(+H99/H116,"") -> 0.57042563 | I29: =IFERROR(+I99/I116,"") -> 0.0125 | J29: =IFERROR(+J99/J116,"") -> 0.040551181 | K29: =IFERROR(+K99/K116,"") | ... N29: =IFERROR(+N99/N116,"") | O29: =IFERROR(+AVERAGE(D29:N29),"") -> 0.17351425
B30: Return on Invested Capital (ROIC) | D30: =IFERROR(+D99/(D115+D116),"") -> 0.15331973 | E30: =IFERROR(+E99/(E115+E117),"") -> 0.75432607 | F30: =IFERROR(+F99/(F115+F116),"") -> 0.061740623 | G30: =IFERROR(+G99/(G115+G116),"") -> 0.011709882 | H30: =IFERROR(+H99/(H115+H116),"") -> 0.31026253 | I30: =IFERROR(+I99/(I115+I116),"") -> 0.0080395795 | J30: =IFERROR(+J99/(J115+J116),"") -> 0.027055424 | K30: =IFERROR(+K99/(K115+K116),"") | L30: =IFERROR(+L99/(L115+L116),"") | M30: =IFERROR(+M99/(M115+M116),"") | N30: =IFERROR(+N99/(N115+N116),"") | O30: =IFERROR(+AVERAGE(D30:N30),"") -> 0.18949341
B32: Solvency | D32: =+D23 -> E.L.F. | E32: =+E23 -> L'Oreal | F32: =+F23 -> Estée Lauder | G32: =+G23 -> Coty | H32: =+H23 -> Ulta Beauty | I32: =+I23 -> Shiseido | J32: =+J23 -> Natura | K32: =+K23 -> 0 | ... O32: =+O23 -> Average
B34: Debt/Assets | D34: =IFERROR(D115/D111,"") -> 0.16851147 | E34: =IFERROR(E115/E111,"") -> 0.15074619 | F34: =IFERROR(F115/F111,"") -> 0.45347603 | G34: =IFERROR(G115/G111,"") -> 0.34105768 | H34: =IFERROR(H115/H111,"") -> 0.33485194 | I34: =IFERROR(I115/I111,"") -> 0.27271653 | J34: =IFERROR(J115/J111,"") -> 0.21053506 | K34: =IFERROR(K115/K111,"") | ... N34: =IFERROR(N115/N111,"") | O34: =IFERROR(+AVERAGE(D34:N34),"") -> 0.27598499
B35: Net Debt/EBITDA | D35: =IFERROR(+(D115-D105)/D94,"") -> 0.54843019 | E35: =IFERROR(+(E115-E105)/E94,"") -> 0.46079652 | F35: =IFERROR(+(F115-F106)/F94,"") -> 2.8223615 | G35: =IFERROR(+(G115-G105)/G94,"") -> 3.6037736 | H35: =IFERROR(+(H115-H105)/H94,"") -> 0.5026362 | I35: =IFERROR(+(I115-I105)/I94,"") -> 2.0946502 | J35: =IFERROR(+(J115-J105)/J94,"") -> 0.76223776 | K35: =IFERROR(+(K115-K105)/K94,"") | L35: =IFERROR(+(L115-L105)/L94,"") | M35: =IFERROR(+(M115-M105)/M94,"") | N35: =IFERROR(+(N115-N105)/N94,"") | O35: =IFERROR(+AVERAGE(D35:N35),"") -> 1.5421266
B36: Interest Coverage Ratio | D36: =IFERROR(D95/D96,"") -> 16.257143 | E36: =IFERROR(E95/E96,"") -> 39.616438 | F36: =IFERROR(F95/F96,"") -> 7.5260664 | G36: =IFERROR(G95/G96,"") -> 2.3055556 | H36: =IFERROR(H95/F75,"") -> -84.45 | I36: =IFERROR(I95/I96,"") -> -10.904762 | J36: =IFERROR(J95/J96,"") -> 11.608696 | K36: =IFERROR(K95/K96,"") | L36: =IFERROR(L95/L96,"") | M36: =IFERROR(M95/M96,"") | N36: =IFERROR(N95/N96,"") | O36: =IFERROR(+AVERAGE(D36:N36),"") -> -2.5772662
B38: Liquidity | D38: =+D23 -> E.L.F. | E38: =+E23 -> L'Oreal | F38: =+F23 -> Estée Lauder | G38: =+G23 -> Coty | H38: =+H23 -> Ulta Beauty | I38: =+I23 -> Shiseido | J38: =+J23 -> Natura | K38: =+K23 -> 0 | ... O38: =+O23 -> Average
B40: Cash Ratio | D40: =IFERROR(D105/D113,"") -> 0.36175192 | E40: =IFERROR(E105/E113,"") -> 0.2768516 | F40: =IFERROR(F106/F113,"") -> 0.30287618 | G40: =IFERROR(G105/G113,"") -> 0.11568025 | H40: =IFERROR(H105/H113,"") -> 0.46260555 | I40: =IFERROR(I105/I113,"") -> 0.30833004 | J40: =IFERROR(J105/J113,"") -> 0.46371227 | K40: =IFERROR(K105/K113,"") | L40: =IFERROR(L105/L113,"") | M40: =IFERROR(M105/M113,"") | N40: =IFERROR(N105/N113,"") | O40: =IFERROR(+AVERAGE(D40:N40),"") -> 0.32740112
B41: Quick Ratio | D41: =IFERROR(+(D105+D106)/D113,"") -> 0.77566031 | E41: =IFERROR(+(E105+E106)/E113,"") -> 0.65953813 | F41: =IFERROR(+(F105+F106)/F113,"") -> 0.8982813 | G41: =IFERROR(+(G105+G106)/G113,"") -> 0.28554958 | H41: =IFERROR(+(H105+H106)/H113,"") -> 0.5880579 | I41: =IFERROR(+(I105+I106)/I113,"") -> 0.67666798 | J41: =IFERROR(+(J105+J106)/J113,"") -> 1.0134875 | K41: =IFERROR(+(K105+K106)/K113,"") | ... N41: =IFERROR(+(N105+N106)/N113,"") | O41: =IFERROR(+AVERAGE(D41:N41),"") -> 0.6996061
B42: Current Ratio | D42: =IFERROR(D109/D113,"") -> 1.5951187 | E42: =IFERROR(E109/E113,"") -> 1.1255124 | F42: =IFERROR(F109/F113,"") -> 1.3893371 | G42: =IFERROR(G109/G113,"") -> 0.754804 | H42: =IFERROR(H109/H113,"") -> 1.7110977 | I42: =IFERROR(I109/I113,"") -> 1.1985788 | J42: =IFERROR(J109/J113,"") -> 1.5754656 | K42: =IFERROR(K109/K113,"") | ... N42: =IFERROR(N109/N113,"") | O42: =IFERROR(+AVERAGE(D42:N42),"") -> 1.335702
B44: Activity | D44: =+D23 -> E.L.F. | E44: =+E23 -> L'Oreal | F44: =+F23 -> Estée Lauder | G44: =+G23 -> Coty | H44: =+H23 -> Ulta Beauty | I44: =+I23 -> Shiseido | J44: =+J23 -> Natura | K44: =+K23 -> 0 | ... O44: =+O23 -> Average
B46: Inventory Turnover | D46: =IFERROR(D92/(AVERAGE(D107:D108)),"") -> 2.1979472 | E46: =IFERROR(E92/(AVERAGE(E107:E108)),"") -> 2.464223 | F46: =IFERROR(F92/(AVERAGE(F107:F108)),"") -> 1.7163368 | G46: =IFERROR(G92/(AVERAGE(G107:G108)),"") -> 2.6493506 | H46: =IFERROR(H92/(AVERAGE(H107:H108)),"") -> 4.0813154 | I46: =IFERROR(I92/(AVERAGE(I107:I108)),"") -> 1.5055209 | J46: =IFERROR(J92/(AVERAGE(J107:J108)),"") -> 2.6373626 | K46: =IFERROR(K92/(AVERAGE(K107:K108)),"") | ... N46: =IFERROR(N92/(AVERAGE(N107:N108)),"") | O46: =IFERROR(+AVERAGE(D46:N46),"") -> 2.4645795
B47: Acc. Receivable Turnover | D47: =IFERROR(D91/D106,"") -> 8.2705977 | E47: =IFERROR(E91/E106,"") -> 7.7639707 | F47: =IFERROR(F91/F106,"") -> 9.0376375 | G47: =IFERROR(G91/G106,"") -> 13.841629 | H47: =IFERROR(H91/H106,"") -> 53.879808 | I47: =IFERROR(I91/I106,"") -> 7.0150054 | J47: =IFERROR(J91/J106,"") -> 5.2418224 | K47: =IFERROR(K91/K106,"") | ... N47: =IFERROR(N91/N106,"") | O47: =IFERROR(+AVERAGE(D47:N47),"") -> 15.00721
B48: Payables Turnover | D48: =IFERROR(D92/D112,"") -> 3.6966708 | E48: =IFERROR(E92/E112,"") -> 1.7357761 | F48: =IFERROR(F92/F112,"") -> 0.94629867 | G48: =IFERROR(G92/G112,"") -> 0.90839695 | H48: =IFERROR(H92/H112,"") -> 7.2771855 | I48: =IFERROR(I92/I112,"") -> 1.1304975 | J48: =IFERROR(J92/J112,"") -> 1.163311 | K48: =IFERROR(K92/K112,"") | ... N48: =IFERROR(N92/N112,"") | O48: =IFERROR(+AVERAGE(D48:N48),"") -> 2.4083052
B49: Fixed Asset Turnover | D49: =IFERROR(D91/D110,"") -> 24.731884 | E49: =IFERROR(E91/E110,"") -> 7.2901928 | F49: =IFERROR(F91/F110,"") -> 3.1410747 | G49: =IFERROR(G91/G110,"") -> 6.2813142 | H49: =IFERROR(H91/H110,"") -> 4.0649256 | I49: =IFERROR(I91/I110,"") -> 2.5798187 | J49: =IFERROR(J91/J110,"") -> 6.1047619 | K49: =IFERROR(K91/K110,"") | ... N49: =IFERROR(N91/N110,"") | O49: =IFERROR(+AVERAGE(D49:N49),"") -> 7.741996
B50: Total Asset Turnover | D50: =IFERROR(D91/D111,"") -> 0.90666785 | E50: =IFERROR(E91/E111,"") -> 0.77167143 | F50: =IFERROR(F91/F111,"") -> 0.72002583 | G50: =IFERROR(G91/G111,"") -> 0.50633121 | H50: =IFERROR(H91/H111,"") -> 1.9637288 | I50: =IFERROR(I91/I111,"") -> 0.77336642 | J50: =IFERROR(J91/J111,"") -> 0.74559654 | K50: =IFERROR(K91/K111,"") | ... N50: =IFERROR(N91/N111,"") | O50: =IFERROR(+AVERAGE(D50:N50),"") -> 0.91248401
B51: Cash Cycle (days) | D51: =IFERROR(365/D46+365/D47-365/D48,"") -> 111.45879 | E51: =IFERROR(365/E46+365/E47-365/E48,"") -> -15.148835 | F51: =IFERROR(365/F46+365/F47-365/F48,"") -> -132.66444 | G51: =IFERROR(365/G46+365/G47-365/G48,"") -> -237.66739 | H51: =IFERROR(365/H46+365/H47-365/H48,"") -> 46.049535 | I51: =IFERROR(365/I46+365/I47-365/I48,"") -> -28.39438 | J51: =IFERROR(365/J46+365/J47-365/J48,"") -> -105.73151 | K51: =IFERROR(365/K46+365/K47-365/K48,"") | ... N51: =IFERROR(365/N46+365/N47-365/N48,"") | O51: =IFERROR(+AVERAGE(D51:N51),"") -> -51.728318
B53: Cash Flow | D53: =+D32 -> E.L.F. | E53: =+E32 -> L'Oreal | F53: =+F32 -> Estée Lauder | G53: =+G32 -> Coty | H53: =+H32 -> Ulta Beauty | I53: =+I32 -> Shiseido | J53: =+J32 -> Natura | K53: =+K32 -> 0 | ... O53: =+O32 -> Average
B55: Cash Flow Margin | D55: =IFERROR(D126/D91,"") -> -0.012305889 | E55: =IFERROR(E126/E91,"") -> 0.0054040381 | F55: =IFERROR(F126/F91,"") -> -0.040620195 | G55: =IFERROR(G126/G91,"") -> 0.006047728 | H55: =IFERROR(H126/H91,"") -> 0.0025876684 | I55: =IFERROR(I126/I91,"") -> -0.0062643239 | J55: =IFERROR(J126/J91,"") -> -0.046133274 | K55: =IFERROR(K126/K91,"") | ... N55: =IFERROR(N126/N91,"") | O55: =IFERROR(+AVERAGE(D55:N55),"") -> -0.013040607
B56: Cash Flow to Net Income | D56: =IFERROR(D126/D90,"") -> -0.20487805 | E56: =IFERROR(E126/E90,"") -> 0.038001294 | F56: =IFERROR(F126/F90,"") -> -0.50801282 | G56: =IFERROR(G126/G90,"") -> 0.19170984 | H56: =IFERROR(H126/H90,"") -> 0.023237179 | I56: =IFERROR(I126/I90,"") -> -0.2039801 | J56: =IFERROR(J126/J90,"") -> -0.92 | K56: =IFERROR(K126/K90,"") | ... N56: =IFERROR(N126/N90,"") | O56: =IFERROR(+AVERAGE(D56:N56),"") -> -0.22627466
B57: CFO to Net Income | D57: =+IFERROR(D120/D99,"") -> 0.55755677 | E57: =+IFERROR(E120/E99,"") -> 1.2930712 | F57: =+IFERROR(F120/F99,"") -> 2.5240642 | G57: =+IFERROR(G121/G99,"") -> -2.3061224 | H57: =+IFERROR(H120/H99,"") -> 1.1353846 | I57: =+IFERROR(I120/I99,"") -> 6.1538462 | J57: =+IFERROR(J120/J99,"") -> -4.6213592 | K57: =+IFERROR(K120/K99,"") | L57: =+IFERROR(L120/L99,"") | M57: =+IFERROR(M120/M99,"") | N57: =+IFERROR(N120/N99,"") | O57: =IFERROR(+AVERAGE(D57:N57),"") -> 0.67663446
B58: Net Capex to CFO | D58: =IFERROR(-D121/D120,"") -> 0.12219101 | E58: =IFERROR(-E121/E120,"") -> 0.1980449 | F58: =IFERROR(-F121/F120,"") -> 0.38940678 | G58: =IFERROR(-G120/G121,"") -> 2.7212389 | H58: =IFERROR(-H121/H120,"") -> 0.29471545 | I58: =IFERROR(-I121/I120,"") -> 1.015625 | J58: =IFERROR(-J121/J120,"") -> -0.20378151 | K58: =IFERROR(-K121/K120,"") | L58: =IFERROR(-L121/L120,"") | M58: =IFERROR(-M121/M120,"") | N58: =IFERROR(-N121/N120,"") | O58: =IFERROR(+AVERAGE(D58:N58),"") -> 0.64820579
B59: CFI to CFO | D59: =IFERROR(-D122/D120,"") -> 3.9985955 | E59: =IFERROR(-E122/E120,"") -> 0.44689838 | F59: =IFERROR(-F122/F120,"") -> 0.40677966 | G59: =IFERROR(-G122/G121,"") -> -1 | H59: =IFERROR(-H122/H120,"") -> 0.29878049 | I59: =IFERROR(-I122/I120,"") -> 1.728125 | J59: =IFERROR(-J122/J120,"") -> 0.8907563 | K59: =IFERROR(-K122/K120,"") | L59: =IFERROR(-L122/L120,"") | M59: =IFERROR(-M122/M120,"") | N59: =IFERROR(-N122/N120,"") | O59: =IFERROR(+AVERAGE(D59:N59),"") -> 0.96713362
B60: Net Financing to CFO | D60: =IFERROR((D123+D124)/D120,"") -> 2.761236 | E60: =IFERROR((E123+E124)/E120,"") -> -0.30207579 | F60: =IFERROR((F123+F124)/F120,"") -> 0.12118644 | G60: =IFERROR((G123+G124)/G121,"") -> -17.5 | H60: =IFERROR((H123+H124)/H120,"") -> 0.13211382 | I60: =IFERROR((I123+I124)/I120,"") -> 2.43125 | J60: =IFERROR((J123+J124)/J120,"") -> 0 | K60: =IFERROR((K123+K124)/K120,"") | L60: =IFERROR((L123+L124)/L120,"") | M60: =IFERROR((M123+M124)/M120,"") | N60: =IFERROR((N123+N124)/N120,"") | O60: =IFERROR(+AVERAGE(D60:N60),"") -> -1.7651842
B61: Debt Borrowing to Debt Repayment | D61: =+IFERROR(-D124/D123,"") -> 0.038630807 | E61: =+IFERROR(-E124/E123,"") -> -9.1747967 | F61: =+IFERROR(-F124/F123,"") -> 1.8125 | G61: =+IFERROR(-G124/G123,"") -> 0.076581835 | H61: =+IFERROR(-H124/H123,"") -> 0 | I61: =+IFERROR(-I124/I123,"") -> -0.089635854 | J61: =+IFERROR(-J124/J123,"") | K61: =+IFERROR(-K124/K123,"") | ... N61: =+IFERROR(-N124/N123,"") | O61: =IFERROR(+AVERAGE(D61:N61),"") -> -1.2227867
B62: CFF to CFO | D62: =IFERROR(-D125/D120,"") -> -2.8216292 | E62: =IFERROR(-E125/E120,"") -> 0.57748009 | F62: =IFERROR(-F125/F120,"") -> 0.86228814 | G62: =IFERROR(-G125/G121,"") -> -1.4911504 | H62: =IFERROR(-H125/H120,"") -> 0.68157182 | I62: =IFERROR(-I125/I120,"") -> -0.48125 | J62: =IFERROR(-J125/J120,"") -> -0.3802521 | K62: =IFERROR(-K125/K120,"") | L62: =IFERROR(-L125/L120,"") | M62: =IFERROR(-M125/M120,"") | N62: =IFERROR(-N125/N120,"") | O62: =IFERROR(+AVERAGE(D62:N62),"") -> -0.43613453
B63: Payout Ratio | D63: 0 | E63: 0.5523 | F63: 4.7143 | G63: 0 | H63: 0 | I63: 12.362 | J63: 0 | O63: =IFERROR(+AVERAGE(D63:N63),"") -> 2.5183714
B65: Stock Information | D65: =+D23 -> E.L.F. | E65: =+E23 -> L'Oreal | F65: =+F23 -> Estée Lauder | G65: =+G23 -> Coty | H65: =+H23 -> Ulta Beauty | I65: =+I23 -> Shiseido | J65: =+J23 -> Natura | K65: =+K23 -> 0 | ... O65: =+O23 -> Average
B67: (%) Float | D67: =55.23/56.4 -> 0.97925532 | E67: =261.73/534.32 -> 0.48983755 | F67: =232.92/359.72 -> 0.64750361 | G67: =367.14/871.99 -> 0.42103694 | H67: =45.13/45.31 -> 0.99602737 | I67: =348.16/400.99 -> 0.86825108 | J67: =812.98/1430 -> 0.56851748 | O67: =IFERROR(+AVERAGE(D67:N67),"") -> 0.71006134
B68: β (Levered) | D68: {=IFERROR(_FV(D85,"Beta"),"")} -> 1.6084 | E68: {=IFERROR(_FV(E85,"Beta"),"")} -> 0.848 | F68: {=IFERROR(_FV(F85,"Beta"),"")} -> 1.178 | G68: {=IFERROR(_FV(G85,"Beta"),"")} -> 2.017 | H68: {=IFERROR(_FV(H85,"Beta"),"")} -> 1.0561 | I68: {=IFERROR(_FV(I85,"Beta"),"")} -> 0.4524 | J68: {=IFERROR(_FV(J85,"Beta"),"")} -> 1.2257 | K68: {=IFERROR(_FV(K85,"Beta"),"")} | ... N68: {=IFERROR(_FV(N85,"Beta"),"")} | O68: =IFERROR(+AVERAGE(D68:N68),"") -> 1.1979429
B69: β (Unlevered) | D69: =IFERROR(D68/(1+(1-D98/D97)*(D115/D116)),"") -> 1.2778616 | E69: =IFERROR(E68/(1+(1-E98/E97)*(E115/E116)),"") -> 0.70956987 | F69: =IFERROR(F68/(1+(1-F98/F97)*(F115/F116)),"") -> 0.51903511 | G69: =IFERROR(G68/(1+(1-G98/G97)*(G115/G116)),"") -> 1.3140776 | H69: =IFERROR(H68/(1+(1-H98/H97)*(H115/H116)),"") -> 0.64451518 | I69: =IFERROR(I68/(1+(1-I98/I97)*(I115/I116)),"") -> 0.37663644 | J69: =IFERROR(J68/(1+(1-J98/J97)*(J115/J116)),"") -> 1.0877126 | K69: =IFERROR(K68/(1+(1-K98/K97)*(K115/K116)),"") | ... N69: =IFERROR(N68/(1+(1-N98/N97)*(N115/N116)),"") | O69: =IFERROR(+AVERAGE(D69:N69),"") -> 0.84705836
B70: % Held by Insiders | D70: 0.0264 | E70: 0.5717 | F70: 0.0043 | G70: 0.6048 | H70: 0.0028 | I70: 0 | J70: 0.359 | O70: =IFERROR(+AVERAGE(D70:N70),"") -> 0.22414286
B71: % Held by Institutions | D71: 0.9616 | E71: 0.1469 | F71: 0.9371 | G71: 0.3937 | H71: 0.9532 | I71: 0.0001 | J71: 0.5877 | O71: =IFERROR(+AVERAGE(D71:N71),"") -> 0.56861429
B72: Short % Float | D72: 0.1837 | F72: 0.0348 | G72: 0.0455 | H72: 0.0671 | O72: =IFERROR(+AVERAGE(D72:N72),"") -> 0.082775
B74: Stock Performance | D74: =+D23 -> E.L.F. | E74: =+E23 -> L'Oreal | F74: =+F23 -> Estée Lauder | G74: =+G23 -> Coty | H74: =+H23 -> Ulta Beauty | I74: =+I23 -> Shiseido | J74: =+J23 -> Natura | K74: =+K23 -> 0 | ... O74: =+O23 -> Average
F75: -20
B76: 1 day | D76: {=IFERROR((D79/_xlfn.STOCKHISTORY(C5,TODAY()-1,TODAY()-1,0,0,1))-1,"Non-trading days")} -> 0 | E76: {=IFERROR((E79/_xlfn.STOCKHISTORY(C6,TODAY()-1,TODAY()-1,0,0,1))-1,"Non-trading days")} -> 0.0020042758 | F76: {=IFERROR((F79/_xlfn.STOCKHISTORY(C7,TODAY()-1,TODAY()-1,0,0,1))-1,"Non-trading days")} -> 0 | G76: {=IFERROR((G79/_xlfn.STOCKHISTORY(C8,TODAY()-1,TODAY()-1,0,0,1))-1,"Non-trading days")} -> 0 | H76: {=IFERROR((K79/_xlfn.STOCKHISTORY(C9,TODAY()-1,TODAY()-1,0,0,1))-1,"Non-trading days")} -> Non-trading days | I76: {=IFERROR((L79/_xlfn.STOCKHISTORY(C10,TODAY()-1,TODAY()-1,0,0,1))-1,"Non-trading days")} -> Non-trading days | J76: {=IFERROR((M79/_xlfn.STOCKHISTORY(C11,TODAY()-1,TODAY()-1,0,0,1))-1,"Non-trading days")} -> Non-trading days | K76: {=IFERROR((N79/_xlfn.STOCKHISTORY(#REF!,TODAY()-1,TODAY()-1,0,0,1))-1,"Non-trading days")} -> Non-trading days | L76: {=IFERROR((L79/_xlfn.STOCKHISTORY(#REF!,TODAY()-1,TODAY()-1,0,0,1))-1,"Non-trading days")} -> Non-trading days | M76: {=IFERROR((M79/_xlfn.STOCKHISTORY(#REF!,TODAY()-1,TODAY()-1,0,0,1))-1,"Non-trading days")} -> Non-trading days | N76: {=IFERROR((N79/_xlfn.STOCKHISTORY(#REF!,TODAY()-1,TODAY()-1,0,0,1))-1,"Non-trading days")} -> Non-trading days | O76: =IFERROR(+AVERAGE(D76:N76),"") -> 0.00050106895
B77: 1 month | D77: {=IFERROR((D79/_xlfn.STOCKHISTORY(C5,TODAY()-29,TODAY()-29,0,0,1))-1,"Non-trading days")} -> 0.016377505 | E77: {=IFERROR((E79/_xlfn.STOCKHISTORY(C6,TODAY()-29,TODAY()-29,0,0,1))-1,"Non-trading days")} -> -0.072823937 | F77: {=IFERROR((F79/_xlfn.STOCKHISTORY(C7,TODAY()-29,TODAY()-29,0,0,1))-1,"Non-trading days")} -> 0.014978276 | G77: {=IFERROR((G79/_xlfn.STOCKHISTORY(C8,TODAY()-29,TODAY()-29,0,0,1))-1,"Non-trading days")} -> -0.10045662 | H77: {=IFERROR((K79/_xlfn.STOCKHISTORY(C9,TODAY()-29,TODAY()-29,0,0,1))-1,"Non-trading days")} -> Non-trading days | I77: {=IFERROR((L79/_xlfn.STOCKHISTORY(C10,TODAY()-29,TODAY()-29,0,0,1))-1,"Non-trading days")} -> Non-trading days | J77: {=IFERROR((M79/_xlfn.STOCKHISTORY(C11,TODAY()-29,TODAY()-29,0,0,1))-1,"Non-trading days")} -> Non-trading days | K77: {=IFERROR((N79/_xlfn.STOCKHISTORY(#REF!,TODAY()-29,TODAY()-29,0,0,1))-1,"Non-trading days")} -> Non-trading days | L77: {=IFERROR((L79/_xlfn.STOCKHISTORY(#REF!,TODAY()-29,TODAY()-29,0,0,1))-1,"Non-trading days")} -> Non-trading days | M77: {=IFERROR((M79/_xlfn.STOCKHISTORY(#REF!,TODAY()-29,TODAY()-29,0,0,1))-1,"Non-trading days")} -> Non-trading days | N77: {=IFERROR((N79/_xlfn.STOCKHISTORY(#REF!,TODAY()-29,TODAY()-29,0,0,1))-1,"Non-trading days")} -> Non-trading days | O77: =IFERROR(AVERAGE(D77:N77),"") -> -0.035481194
B78: YTD | D78: {=IFERROR((D79/_xlfn.STOCKHISTORY(C5,"2025-01-02","2025-01-02",0,0,1))-1,"Non-trading days")} -> 0.10504919 | E78: {=IFERROR((E79/_xlfn.STOCKHISTORY(C6,"2025-01-02","2025-01-02",0,0,1))-1,"Non-trading days")} -> 0.10899142 | F78: {=IFERROR((F79/_xlfn.STOCKHISTORY(C7,"2025-01-02","2025-01-02",0,0,1))-1,"Non-trading days")} -> 0.1999189 | G78: {=IFERROR((G79/_xlfn.STOCKHISTORY(C8,"2025-01-02","2025-01-02",0,0,1))-1,"Non-trading days")} -> -0.42565598 | H78: {=IFERROR((K79/_xlfn.STOCKHISTORY(C9,"2025-01-02","2025-01-02",0,0,1))-1,"Non-trading days")} -> Non-trading days | I78: {=IFERROR((L79/_xlfn.STOCKHISTORY(C10,"2025-01-02","2025-01-02",0,0,1))-1,"Non-trading days")} -> Non-trading days | J78: {=IFERROR((M79/_xlfn.STOCKHISTORY(C11,"2025-01-02","2025-01-02",0,0,1))-1,"Non-trading days")} -> Non-trading days | K78: {=IFERROR((N79/_xlfn.STOCKHISTORY(#REF!,"2025-01-02","2025-01-02",0,0,1))-1,"Non-trading days")} -> Non-trading days | L78: {=IFERROR((L79/_xlfn.STOCKHISTORY(#REF!,"2025-01-02","2025-01-02",0,0,1))-1,"Non-trading days")} -> Non-trading days | M78: {=IFERROR((M79/_xlfn.STOCKHISTORY(#REF!,"2025-01-02","2025-01-02",0,0,1))-1,"Non-trading days")} -> Non-trading days | N78: {=IFERROR((N79/_xlfn.STOCKHISTORY(#REF!,"2025-01-02","2025-01-02",0,0,1))-1,"Non-trading days")} -> Non-trading days | O78: =IFERROR(AVERAGE(D78:N78),"") -> -0.0029241165
B79: Current Price | D79: {=+IFERROR(_FV(D85,"Price"),"")} -> 135.91 | E79: {=+IFERROR(_FV(E85,"Price"),"")} -> 374.95 | F79: {=+IFERROR(_FV(F85,"Price"),"")} -> 88.77 | G79: {=+IFERROR(_FV(G85,"Price"),"")} -> 3.94 | H79: {=+IFERROR(_FV(H85,"Price"),"")} -> 557.82 | I79: {=+IFERROR(_FV(I85,"Price"),"")} -> 14 | J79: {=+IFERROR(_FV(J85,"Price"),"")} | K79: {=+IFERROR(_FV(K85,"Price"),"")} | ... N79: {=+IFERROR(_FV(N85,"Price"),"")} | O79: =IFERROR(AVERAGE(D79:N79),"") -> 195.89833
B81: Extra
B83: % Revenues in the US
B85: Income Statement | D85: =+DCF!R4 -> #VALUE! | E85: =A6 -> #VALUE! | F85: =A7 -> #VALUE! | G85: =A8 -> #VALUE! | H85: =A9 -> #VALUE! | I85: =A10 -> #VALUE! | J85: #VALUE! | K85: PEER 7 | L85: PEER 8 | M85: PEER 9 | N85: PEER 10
B87: =+Inputs!$B$6&" ("&Inputs!O$4&")" -> Revenue (Sales) (2022) | D87: =+_xlfn.XLOOKUP("Revenue (Sales)",Inputs!$B:$B,Inputs!O:O) -> 392.2 | E87: 38260 | F87: 17737 | G87: 5304 | H87: 8631 | I87: 8169 | J87: 5671
B88: =+Inputs!$B$6&" ("&Inputs!P$4&")" -> Revenue (Sales) (2023) | D88: =+_xlfn.XLOOKUP("Revenue (Sales)",Inputs!$B:$B,Inputs!P:P) -> 578.8 | E88: 41182 | F88: 15910 | G88: 5554 | H88: 10209 | I88: 6939 | J88: 3974
B89: EBITDA (2023) | D89: =+_xlfn.XLOOKUP("EBITDA",Inputs!$B:$B,Inputs!P:P) -> 68.1 | E89: 8970 | F89: 3011 | G89: 898 | H89: 2207 | I89: 805 | J89: 791
B90: Net Income (2023) | D90: =+_xlfn.XLOOKUP("Net Income",Inputs!$B:$B,Inputs!P:P) -> 61.5 | E90: 6184 | F90: 1248 | G90: 193 | H90: 1248 | I90: 201 | J90: 225
B91: =+Inputs!$B$6&" ("&Inputs!Q$4&")" -> Revenue (Sales) (2024) | D91: =+_xlfn.XLOOKUP("Revenue (Sales)",Inputs!$B:$B,Inputs!Q:Q) -> 1023.9 | E91: 43486 | F91: 15608 | G91: 6118 | H91: 11207 | I91: 6545 | J91: 4487
B92: COGS (Cost of Goods Sold) | D92: =+_xlfn.XLOOKUP($B92,Inputs!$B:$B,Inputs!Q:Q) -> 299.8 | E92: 11227 | F92: 4423 | G92: 2142 | H92: 6826 | I92: 1568 | J92: 1560
B93: Gross Profit | D93: =+_xlfn.XLOOKUP($B93,Inputs!$B:$B,Inputs!Q:Q) -> 724.1 | E93: =+E91-E92 -> 32259 | F93: 11185 | G93: 3976 | H93: 4381 | I93: 4976 | J93: 2928 | K93: =+K91-K92 -> 0 | L93: =+L91-L92 -> 0 | M93: =+M91-M92 -> 0 | N93: =+N91-N92 -> 0
B94: EBITDA | D94: =+_xlfn.XLOOKUP($B94,Inputs!$B:$B,Inputs!Q:Q) -> 149.7 | E94: 9642 | F94: 2871 | G94: 1060 | H94: 2276 | I94: 729 | J94: 715
B95: Operating Income (EBIT) | D95: =+_xlfn.XLOOKUP($B95,Inputs!$B:$B,Inputs!Q:Q) -> 113.8 | E95: 8676 | F95: 1588 | G95: 581 | H95: 1689 | I95: 229 | J95: 534
B96: Net Interest Expense (Income) | D96: =+_xlfn.XLOOKUP($B96,Inputs!$B:$B,Inputs!Q:Q) -> 7 | E96: 219 | F96: 211 | G96: 252 | H96: -18 | I96: -21 | J96: 46
B97: Pre-Tax Income (EBT) | D97: =+_xlfn.XLOOKUP($B97,Inputs!$B:$B,Inputs!Q:Q) -> 105.1 | E97: 8431 | F97: 1390 | G97: 214 | H97: 1707 | I97: 171 | J97: 405
B98: Tax Expense (Benefits) | D98: =+_xlfn.XLOOKUP($B98,Inputs!$B:$B,Inputs!Q:Q) -> 13.3 | E98: 2015 | F98: 436 | G98: 96 | H98: 407 | I98: 109 | J98: 302
B99: Net Income | D99: =+_xlfn.XLOOKUP($B99,Inputs!$B:$B,Inputs!Q:Q) -> 127.7 | E99: 6408 | F99: 935 | G99: 98 | H99: 1300 | I99: 52 | J99: 103
B100: EPS basic | D100: =+_xlfn.XLOOKUP($B100,Inputs!$B:$B,Inputs!Q:Q) -> 2.33 | E100: 12 | F100: 3 | G100: 0 | H100: 26 | I100: 0 | J100: 0
B101: R&D (Research & Development) | D101: =+_xlfn.XLOOKUP($B101,Inputs!$B:$B,Inputs!Q:Q) -> 0 | E101: 1354 | F101: 792 | G101: 127 | H101: 0 | I101: 180 | J101: -
B103: Balance Sheet
B105: Cash & Cash Equivalents | D105: =+_xlfn.XLOOKUP($B105,Inputs!$B:$B,Inputs!Q:Q) -> 108.2 | E105: 4052 | F105: 3395 | G105: 301 | H105: 767 | I105: 781 | J105: 722
B106: Accounts Receivable | D106: =+_xlfn.XLOOKUP($B106,Inputs!$B:$B,Inputs!Q:Q) -> 123.8 | E106: 5601 | F106: 1727 | G106: 442 | H106: 208 | I106: 933 | J106: 856
B107: Beginning Inventory | D107: =+_xlfn.XLOOKUP("Inventory",Inputs!$B:$B,Inputs!P:P) -> 81.3 | E107: 4482 | F107: 2979 | G107: 853 | H107: 1603 | I107: 1063 | J107: 636
B108: Ending Inventory | D108: =+_xlfn.XLOOKUP("Inventory",Inputs!$B:$B,Inputs!Q:Q) -> 191.5 | E108: 4630 | F108: 2175 | G108: 764 | H108: 1742 | I108: 1020 | J108: 547
B109: Current Assets | D109: =+_xlfn.XLOOKUP($B109,Inputs!$B:$B,Inputs!Q:Q) -> 477.1 | E109: 16473 | F109: 7922 | G109: 1964 | H109: 2837 | I109: 3036 | J109: 2453
B110: Net PP&E (Property, Plant and Equipment) | D110: =+_xlfn.XLOOKUP($B110,Inputs!$B:$B,Inputs!Q:Q) -> 41.4 | E110: 5965 | F110: 4969 | G110: 974 | H110: 2757 | I110: 2537 | J110: 735
B111: Total Assets | D111: =+_xlfn.XLOOKUP($B111,Inputs!$B:$B,Inputs!Q:Q) -> 1129.3 | E111: 56353 | F111: 21677 | G111: 12083 | H111: 5707 | I111: 8463 | J111: 6018
B112: Accounts Payable | D112: =+_xlfn.XLOOKUP($B112,Inputs!$B:$B,Inputs!Q:Q) -> 81.1 | E112: 6468 | F112: 4674 | G112: 2358 | H112: 938 | I112: 1387 | J112: 1341
B113: Current Liabilities | D113: =+_xlfn.XLOOKUP($B113,Inputs!$B:$B,Inputs!Q:Q) -> 299.1 | E113: 14636 | F113: 5702 | G113: 2602 | H113: 1658 | I113: 2533 | J113: 1557
B114: Long-term debt | D114: =+_xlfn.XLOOKUP($B114,Inputs!$B:$B,Inputs!Q:Q) -> 183.3 | E114: 5187 | F114: 8968 | G114: 4061 | H114: 1627 | I114: 1493 | J114: 1225
B115: Total Debt | D115: =+_xlfn.XLOOKUP($B115,Inputs!$B:$B,Inputs!Q:Q,,,-1) -> 190.3 | E115: 8495 | F115: 9830 | G115: 4121 | H115: 1911 | I115: 2308 | J115: 1267
B116: Shareholder's Equity | D116: =+_xlfn.XLOOKUP($B116,Inputs!$B:$B,Inputs!Q:Q) -> 642.6 | E116: 33137 | F116: 5314 | G116: 4248 | H116: 2279 | I116: 4160 | J116: 2540
H117: 52
B118: Cash Flow Statement
B120: Operating Cash Flow | D120: =+_xlfn.XLOOKUP($B120,Inputs!$B:$B,Inputs!Q:Q) -> 71.2 | E120: 8286 | F120: 2360 | G120: 615 | H120: 1476 | I120: 320 | J120: -476
B121: Net Capex | D121: =+_xlfn.XLOOKUP($B121,Inputs!$B:$B,Inputs!Q:Q) -> -8.7 | E121: -1641 | F121: -919 | G121: -226 | H121: -435 | I121: -325 | J121: -97
B122: Investing Cash Flow | D122: =+_xlfn.XLOOKUP($B122,Inputs!$B:$B,Inputs!Q:Q) -> -284.7 | E122: -3703 | F122: -960 | G122: -226 | H122: -441 | I122: -553 | J122: 424
B123: Debt Borrowing | D123: =+_xlfn.XLOOKUP($B123,Inputs!$B:$B,Inputs!Q:Q) -> 204.5 | E123: -246 | F123: -352 | G123: 4283 | H123: 195 | I123: 714
B124: Debt Repayment | D124: =+_xlfn.XLOOKUP($B124,Inputs!$B:$B,Inputs!Q:Q) -> -7.9 | E124: -2257 | F124: 638 | G124: -328 | H124: 0 | I124: 64
...

Sheet Peers (2)
D3: EV / Revenue | F3: EV / EBITDA | H3: Price / Earnings | P3: Revenue Growth | R3: EBITDA Margin | T3: Profit Margin
B4: Peers | C4: Ticker | D4: 2023 | E4: 2024 | F4: 2023 | G4: 2024 | H4: 2023 | I4: 2024 | P4: =+Inputs!O4&"-"&Inputs!P4 -> 2022-2023 | Q4: =+Inputs!P4&"-"&Inputs!Q4 -> 2023-2024 | R4: 2023 | S4: 2024 | T4: =+Inputs!O4&"-"&Inputs!P4 -> 2022-2023 | U4: =+Inputs!P4&"-"&Inputs!Q4 -> 2023-2024
A5: =+P85 -> #VALUE! | B5: {=IFERROR(_FV(A5,"Name"),"")} -> E.L.F. BEAUTY, INC. | C5: {=IFERROR(_FV(A5,"Ticker symbol",TRUE),"")} -> ELF | D5: {=IFERROR((_FV(A5,"Market cap",TRUE)/1000000+P$115-P$105)/P$88,"")} -> 13.46396 | E5: {=IFERROR((_FV(A5,"Market cap",TRUE)/1000000+P$115-P$105)/P$91,"")} -> 7.6110365 | F5: {=+IFERROR((_FV(A5,"Market cap",TRUE)/1000000+P$115-P$105)/P$89,"")} -> 114.43378 | G5: {=IFERROR((_FV(A5,"Market cap",TRUE)/1000000+P$115-P$105)/P$94,"")} -> 52.057049 | H5: {=IFERROR((_FV(A5,"Market cap",TRUE)/1000000)/P$90,"")} -> 125.37952 | I5: {=IFERROR((_FV(A5,"Market cap",TRUE)/1000000)/P$99,"")} -> 60.382461 | P5: =IFERROR(P88/P87-1,"") -> 0.47577766 | Q5: =IFERROR(P91/P88-1,"") -> 0.76900484 | R5: =IFERROR(P89/P88,"") -> 0.11765722 | S5: =IFERROR(P94/P91,"") -> 0.14620568 | T5: =IFERROR(P90/P88,"") -> 0.10625432 | U5: =IFERROR(P99/P91,"") -> 0.12471921
A6: #VALUE! | B6: L'Oreal S.A. | C6: {=IFERROR(_FV(A6,"Ticker symbol",TRUE),"")} -> OR | D6: {=+IFERROR((_FV(A6,"Market cap",TRUE)/1000000+Q$115-Q$105)/Q$88,"")} -> 4.9528508 | E6: {=IFERROR(+(_FV(A6,"Market cap",TRUE)/1000000+Q$115-Q$105)/Q$91,"")} -> 4.690436 | F6: {=IFERROR(+(_FV(A6,"Market cap",TRUE)/1000000+Q$115-Q$105)/Q$89,"")} -> 22.738941 | G6: {=IFERROR(+(_FV(A6,"Market cap",TRUE)/1000000+Q$115-Q$105)/Q$94,"")} -> 21.154149 | H6: {=IFERROR(+(_FV(A6,"Market cap",TRUE)/1000000)/Q$90,"")} -> 32.264764 | I6: {=IFERROR(+(_FV(A6,"Market cap",TRUE)/1000000)/Q$99,"")} -> 31.136907 | P6: =+IFERROR(Q88/Q87-1,"") -> 0.07637219 | Q6: =IFERROR(Q91/Q88-1,"") -> 0.055946773 | R6: =IFERROR(Q89/Q88,"") -> 0.21781361 | S6: =+IFERROR(Q94/Q91,"") -> 0.22172653 | T6: =IFERROR(Q90/Q88,"") -> 0.15016269 | U6: =+IFERROR(P99/P93,"") -> 0.17635686
A7: #VALUE! | B7: Estée Lauder Companies Inc. | C7: {=IFERROR(_FV(A7,"Ticker symbol",TRUE),"")} -> EL | D7: {=IFERROR(+(_FV(A7,"Market cap",TRUE)/1000000+R$115-R$106)/R$88,"")} -> 2.5199183 | E7: {=IFERROR(+(_FV(A7,"Market cap",TRUE)/1000000+R$115-R$106)/R$91,"")} -> 2.5686763 | F7: {=IFERROR(+(_FV(A7,"Market cap",TRUE)/1000000+R$115-R$106)/R$89,"")} -> 13.315144 | G7: {=IFERROR(+(_FV(A7,"Market cap",TRUE)/1000000+R$115-R$106)/R$94,"")} -> 13.964437 | H7: {=IFERROR(+(_FV(A7,"Market cap",TRUE)/1000000)/R$90,"")} -> 25.632131 | I7: {=IFERROR(+(_FV(A7,"Market cap",TRUE)/1000000)/R$99,"")} -> 34.212727 | P7: =IFERROR(R88/R87-1,"") -> -0.10300502 | Q7: =IFERROR(+R91/R88-1,"") -> -0.018981772 | R7: =IFERROR(R89/R88,"") -> 0.18925204 | S7: =IFERROR(R94/R91,"") -> 0.18394413 | T7: =IFERROR(R90/R88,"") -> 0.078441232 | U7: =+IFERROR(R99/R91,"") -> 0.059905177
A8: #VALUE! | B8: Coty Inc. | C8: {=IFERROR(_FV(A8,"Ticker symbol",TRUE),"")} -> COTY | D8: {=IFERROR(+(_FV(A8,"Market cap",TRUE)/1000000+S$115-S$105)/S$88,"")} -> 1.3077059 | E8: {=IFERROR(+(_FV(A8,"Market cap",TRUE)/1000000+S$115-S$105)/S$91,"")} -> 1.1871524 | F8: {=IFERROR(+(_FV(A8,"Market cap",TRUE)/1000000+S$115-S$105)/S$89,"")} -> 8.0879717 | G8: {=IFERROR(+(_FV(A8,"Market cap",TRUE)/1000000+S$115-S$105)/S$94,"")} -> 6.8518854 | H8: {=IFERROR(+(_FV(A8,"Market cap",TRUE)/1000000)/S$90,"")} -> 17.839371 | I8: {=IFERROR(+(_FV(A8,"Market cap",TRUE)/1000000)/S$99,"")} -> 35.132638 | P8: =+IFERROR(S88/S87-1,"") -> 0.047134238 | Q8: =IFERROR(S91/S88-1,"") -> 0.10154843 | R8: =IFERROR(S89/S88,"") -> 0.16168527 | S8: =IFERROR(S94/S91,"") -> 0.17325924 | T8: =IFERROR(S90/S88,"") -> 0.03474973 | U8: =+IFERROR(S99/S91,"") -> 0.016018307
A9: #VALUE! | B9: Ulta Beauty | C9: {=IFERROR(_FV(A9,"Ticker symbol",TRUE),"")} -> ULTA | D9: {=IFERROR((_FV(A9,"Market cap",TRUE)/1000000+T$115-T$105)/T$88,"")} -> 2.562027 | E9: {=IFERROR(+(_FV(A9,"Market cap",TRUE)/1000000+T$115-T$105)/T$91,"")} -> 2.3338747 | F9: {=IFERROR(+(_FV(A9,"Market cap",TRUE)/1000000+T$115-T$105)/T$89,"")} -> 11.851261 | G9: {=IFERROR(+(_FV(A9,"Market cap",TRUE)/1000000+T$115-T$105)/T$94,"")} -> 11.491975 | H9: {=IFERROR(+(_FV(A9,"Market cap",TRUE)/1000000)/T$90,"")} -> 20.041454 | I9: {=IFERROR(+(_FV(A9,"Market cap",TRUE)/1000000)/T$99,"")} -> 19.239795 | P9: =IFERROR(T88/T87-1,"") -> 0.18282934 | Q9: =IFERROR(T91/T88-1,"") -> 0.097756881 | R9: =IFERROR(T89/T88,"") -> 0.2161818 | S9: =IFERROR(T94/T91,"") -> 0.20308736 | T9: =IFERROR(T90/T88,"") -> 0.12224508 | U9: =+IFERROR(T99/T91,"") -> 0.11599893
A10: #VALUE! | B10: Shiseido Company | C10: {=IFERROR(_FV(A10,"Ticker symbol",TRUE),"")} -> SSDOY | D10: {=IFERROR((_FV(A10,"Market cap",TRUE)/1000000+U$115-U$105)/U$88,"")} -> 1.1936757 | E10: {=IFERROR(+(_FV(A10,"Market cap",TRUE)/1000000+U$115-U$105)/U$91,"")} -> 1.2655334 | F10: {=IFERROR(+(_FV(A10,"Market cap",TRUE)/1000000+U$115-U$105)/U$89,"")} -> 10.289337 | G10: {=IFERROR(+(_FV(A10,"Market cap",TRUE)/1000000+U$115-U$105)/U$94,"")} -> 11.362025 | H10: {=IFERROR(+(_FV(A10,"Market cap",TRUE)/1000000)/U$90,"")} -> 33.611522 | I10: {=IFERROR(+(_FV(A10,"Market cap",TRUE)/1000000)/U$99,"")} -> 129.92146 | P10: =+IFERROR(U88/U87-1,"") -> -0.15056923 | Q10: =IFERROR(U91/U88-1,"") -> -0.056780516 | R10: =IFERROR(U89/U88,"") -> 0.11601095 | S10: =IFERROR(U94/U91,"") -> 0.11138273 | T10: =IFERROR(U90/U88,"") -> 0.02896671 | U10: =+IFERROR(U99/U91,"") -> 0.0079449962
A11: #VALUE! | B11: Natura &Co Holding S.A. | C11: {=IFERROR(_FV(A11,"Ticker symbol",TRUE),"")} -> NTCO3Q | D11: {=IFERROR(+(_FV(A11,"Market cap",TRUE)/1000000+D$115-D$105)/D$88,"")} -> 5.0926627 | E11: {=IFERROR(+(_FV(A11,"Market cap",TRUE)/1000000+D$115-D$105)/D$91,"")} -> 4.5104171 | F11: {=IFERROR(+(_FV(A11,"Market cap",TRUE)/1000000+D$115-D$105)/D$89,"")} -> 25.58564 | G11: {=IFERROR(+(_FV(A11,"Market cap",TRUE)/1000000+D$115-D$105)/D$94,"")} -> 28.305233 | H11: {=IFERROR(+(_FV(A11,"Market cap",TRUE)/1000000)/D$90,"")} -> 87.525518 | I11: {=IFERROR(+(_FV(A11,"Market cap",TRUE)/1000000)/D$99,"")} -> 191.19652 | P11: =IFERROR(D88/D87-1,"") -> -0.29924176 | Q11: =IFERROR(D91/D88-1,"") -> 0.12908908 | R11: =IFERROR(D89/D88,"") -> 0.19904378 | S11: =IFERROR(D94/D91,"") -> 0.15934923 | T11: =IFERROR(D90/D88,"") -> 0.056618017 | U11: =+IFERROR(D99/D91,"") -> 0.022955204
B12: Average | D12: =IFERROR(AVERAGE(D5:D11),"") -> 4.4418287 | E12: =IFERROR(AVERAGE(E5:E11),"") -> 3.4524466 | F12: =IFERROR(AVERAGE(F5:F11),"") -> 29.471725 | G12: =IFERROR(AVERAGE(G5:G11),"") -> 20.740965 | H12: =IFERROR(AVERAGE(H5:H11),"") -> 48.899182 | I12: =IFERROR(AVERAGE(I5:I11),"") -> 71.603216 | P12: =IFERROR(AVERAGE(P5:P11),"") -> 0.032756776 | Q12: =IFERROR(AVERAGE(Q5:Q11),"") -> 0.15394053 | R12: =IFERROR(AVERAGE(R5:R11),"") -> 0.17394924 | S12: =IFERROR(AVERAGE(S5:S11),"") -> 0.17127927 | T12: =IFERROR(AVERAGE(T5:T11),"") -> 0.082491111 | U12: =IFERROR(AVERAGE(U5:U11),"") -> 0.074842669
B13: Deviation from Average | D13: =+IFERROR(D5-D12,"") -> 9.0221317 | E13: =+IFERROR(E5-E12,"") -> 4.1585899 | F13: =IFERROR(+F5-F12,"") -> 84.962053 | G13: =IFERROR(G5-G12,"") -> 31.316084 | H13: =IFERROR(+H5-H12,"") -> 76.480334 | I13: =IFERROR(+I5-I12,"") -> -11.220755 | P13: =IFERROR(+P12-P5,"") -> -0.44302089 | Q13: =IFERROR(Q12-Q5,"") -> -0.61506431 | R13: =+IFERROR(R12-R5,"") -> 0.056292018 | S13: =IFERROR(S12-S5,"") -> 0.025073588 | T13: =IFERROR(+T5-T12,"") -> 0.023763208 | U13: =+IFERROR(U5-U12,"") -> 0.049876542
D15: Equity Value | G15: Implied Upside (Downside) | P15: Trading Multiple | S15: Net | T15: Preferred | U15: Non-Controlling
B16: Implied Share Price | D16: Revenue | E16: EBITDA | F16: P/E | G16: Revenue | H16: EBITDA | I16: P/E | J16: Current Price | P16: Revenue | Q16: EBITDA | R16: P/E | S16: Debt | T16: Stock | U16: Interest
B18: Second Minimum | D18: =IFERROR(+P18*$P$91+S18+T18+U18,"") -> 1377.8796 | E18: =IFERROR(Q18*$P$94+S18+T18+U18,"") -> 1782.9951 | F18: =IFERROR(R18*$P$99,"") -> 3976.183 | G18: {=IFERROR(+(D18/_FV($A$5,"Shares outstanding",TRUE)*1000000)/$J$18-1,"")} -> -0.82130616 | H18: {=IFERROR((+E18/_FV($A$5,"Shares outstanding",TRUE)*1000000)/$J$18-1,"")} -> -0.76876773 | I18: {=IFERROR(+(F18/_FV($A$5,"Shares outstanding",TRUE)*1000000)/$J$18-1,"")} -> -0.48433856 | J18: {=+_FV(A5,"Price")} -> 135.91 | P18: =IFERROR(SMALL(E5:E11,2),"") -> 1.2655334 | Q18: =IFERROR(SMALL(G5:G11,2),"") -> 11.362025 | R18: =IFERROR(SMALL(I5:I11,2),"") -> 31.136907 | S18: =-Inputs!$Q$98+Inputs!$Q$99 -> 82.1 | T18: =+Inputs!$Q$100 -> 0 | U18: =+Inputs!$Q$101 -> 0
B19: Average | D19: =IFERROR(+P19*$P$91+S19+T19+U19,"") -> 3617.0601 | E19: =IFERROR(Q19*$P$94+S19+T19+U19,"") -> 3187.0224 | F19: =IFERROR(+R19*$P$99,"") -> 9143.7307 | G19: {=IFERROR(+(D19/_FV($A$5,"Shares outstanding",TRUE)*1000000)/$J$18-1,"")} -> -0.53091233 | H19: {=IFERROR((+E19/_FV($A$5,"Shares outstanding",TRUE)*1000000)/$J$18-1,"")} -> -0.58668286 | I19: {=IFERROR(+(F19/_FV($A$5,"Shares outstanding",TRUE)*1000000)/$J$18-1,"")} -> 0.18582805 | P19: =+IFERROR(AVERAGE(E5:E11),"") -> 3.4524466 | Q19: =IFERROR(+AVERAGE(G5:G11),"") -> 20.740965 | R19: =IFERROR(+AVERAGE(I5:I11),"") -> 71.603216 | S19: =-Inputs!$Q$98+Inputs!$Q$99 -> 82.1 | T19: =+Inputs!$Q$100 -> 0 | U19: =+Inputs!$Q$101 -> 0
B20: Median | D20: =IFERROR(P20*$P$91+S20+T20+U20,"") -> 2712.1677 | E20: =IFERROR(Q20*$P$94+S20+T20+U20,"") -> 2172.5763 | F20: =IFERROR(+R20*$P$99,"") -> 4486.4379 | G20: {=IFERROR(+(D20/_FV($A$5,"Shares outstanding",TRUE)*1000000)/$J$18-1,"")} -> -0.64826561 | H20: {=IFERROR((+E20/_FV($A$5,"Shares outstanding",TRUE)*1000000)/$J$18-1,"")} -> -0.7182439 | I20: {=+IFERROR((F20/_FV($A$5,"Shares outstanding",TRUE)*1000000)/$J$18-1,"")} -> -0.41816485 | P20: =IFERROR(MEDIAN(E5:E11),"") -> 2.5686763 | Q20: =IFERROR(MEDIAN(G5:G11),"") -> 13.964437 | R20: =IFERROR(MEDIAN(I5:I11),"") -> 35.132638 | S20: =-Inputs!$Q$98+Inputs!$Q$99 -> 82.1 | T20: =+Inputs!$Q$100 -> 0 | U20: =+Inputs!$Q$101 -> 0
B21: Second Maximum | D21: =IFERROR(+P21*$P$91+S21+T21+U21,"") -> 4884.6374 | E21: =IFERROR(Q21*$P$94+S21+T21+U21,"") -> 4319.3934 | F21: =IFERROR(+R21*$P$99,"") -> 16590.971 | G21: {=IFERROR(+(D21/_FV($A$5,"Shares outstanding",TRUE)*1000000)/$J$18-1,"")} -> -0.36652333 | H21: {=IFERROR((+E21/_FV($A$5,"Shares outstanding",TRUE)*1000000)/$J$18-1,"")} -> -0.43982844 | I21: {=IFERROR(+(F21/_FV($A$5,"Shares outstanding",TRUE)*1000000)/$J$18-1,"")} -> 1.1516424 | P21: =IFERROR(LARGE(E5:E11,2),"") -> 4.690436 | Q21: =IFERROR(LARGE(G5:G11,2),"") -> 28.305233 | R21: =IFERROR(LARGE(I5:I11,2),"") -> 129.92146 | S21: =-Inputs!$Q$98+Inputs!$Q$99 -> 82.1 | T21: =+Inputs!$Q$100 -> 0 | U21: =+Inputs!$Q$101 -> 0
B23: Profitability | D23: =+LEFT(B11, FIND(" ", B11 & " ") - 1) -> Natura | F23: =+LEFT(#REF!, FIND(" ",#REF! & " ") - 1) -> #REF! | G23: =+LEFT(#REF!, FIND(" ",#REF! & " ") - 1) -> #REF! | H23: =+LEFT(#REF!, FIND(" ",#REF! & " ") - 1) -> #REF! | I23: Average | P23: =+LEFT(B5, FIND(" ", B5 & " ") - 1) -> E.L.F. | Q23: =+LEFT(B6, FIND(" ", B6 & " ") - 1) -> L'Oreal | R23: =+_xlfn.TEXTBEFORE(B7, " ",2) -> Estée Lauder | S23: =+LEFT(B8, FIND(" ", B8 & " ") - 1) -> Coty | T23: =B9 -> Ulta Beauty | U23: =+LEFT(B10, FIND(" ", B10 & " ") - 1) -> Shiseido
B25: Operating Margin | D25: =IFERROR(D95/D91,"") -> 0.11901047 | E25: =IFERROR(E95/E91,"") | F25: =IFERROR(F95/F91,"") | G25: =IFERROR(G95/G91,"") | H25: =IFERROR(H95/H91,"") | I25: =IFERROR(+AVERAGE(D25:H25),"") -> 0.11901047 | P25: =IFERROR(P95/P91,"") -> 0.11114367 | Q25: =IFERROR(Q95/Q91,"") -> 0.19951249 | R25: =IFERROR(R95/R91,"") -> 0.1017427 | S25: =IFERROR(S95/S91,"") -> 0.094965675 | T25: =IFERROR(T95/T91,"") -> 0.15070938 | U25: =IFERROR(U95/U91,"") -> 0.034988541
B26: Net Income Margin | D26: =IFERROR(D99/D91,"") -> 0.022955204 | E26: =IFERROR(E99/E91,"") | F26: =IFERROR(F99/F91,"") | G26: =IFERROR(G99/G91,"") | H26: =IFERROR(H99/H91,"") | I26: =IFERROR(+AVERAGE(D26:H26),"") -> 0.022955204 | P26: =IFERROR(P99/P91,"") -> 0.12471921 | Q26: =IFERROR(Q99/Q91,"") -> 0.14735777 | R26: =IFERROR(R99/R91,"") -> 0.059905177 | S26: =IFERROR(S99/S91,"") -> 0.016018307 | T26: =IFERROR(T99/T91,"") -> 0.11599893 | U26: =IFERROR(U99/U91,"") -> 0.0079449962
B27: ROA (%) | D27: =IFERROR(D99/D111,"") -> 0.017115321 | E27: =IFERROR(E99/E111,"") | F27: =IFERROR(F99/F111,"") | G27: =IFERROR(G99/G111,"") | H27: =IFERROR(H99/H111,"") | I27: =IFERROR(+AVERAGE(D27:H27),"") -> 0.017115321 | P27: =IFERROR(P99/P111,"") -> 0.1130789 | Q27: =IFERROR(Q99/Q111,"") -> 0.11371178 | R27: =IFERROR(R99/R111,"") -> 0.043133275 | S27: =IFERROR(S99/S111,"") -> 0.0081105686 | T27: =IFERROR(T99/T111,"") -> 0.22779043 | U27: =IFERROR(U99/U111,"") -> 0.0061443932
B28: Financial Cost of Debt | D28: =IFERROR(+(D96/D115)*(1-(D98/D97)),"") -> 0.0092334376 | E28: =IFERROR(+(E96/E115)*(1-(E98/E97)),"") | F28: =IFERROR(+(F96/F115)*(1-(F98/F97)),"") | G28: =IFERROR(+(G96/G115)*(1-(G98/G97)),"") | H28: =IFERROR(+(H96/H115)*(1-(H98/H97)),"") | I28: =IFERROR(+AVERAGE(D28:H28),"") -> 0.0092334376 | P28: =IFERROR(+(P96/P115)*(1-(P98/P97)),"") -> 0.032129149 | Q28: =IFERROR(+(Q96/Q115)*(1-(Q98/Q97)),"") -> 0.019618509 | R28: =IFERROR(+(R96/R115)*(1-(R98/R97)),"") -> 0.014732027 | S28: =IFERROR(+(S96/S115)*(1-(S98/S97)),"") -> 0.033718338 | T28: =IFERROR(+(T96/T115)*(1-(T98/T97)),"") -> -0.0071733439 | U28: =IFERROR(+(U96/U115)*(1-(U98/U97)),"") -> -0.0032989753
B29: Return on Equity (RoE) | D29: =IFERROR(+D99/D116,"") -> 0.040551181 | E29: =IFERROR(+E99/E116,"") | F29: =IFERROR(+F99/F116,"") | G29: =IFERROR(+G99/G116,"") | H29: =IFERROR(+H99/H116,"") | I29: =IFERROR(+AVERAGE(D29:H29),"") -> 0.040551181 | P29: =IFERROR(+P99/P116,"") -> 0.19872393 | Q29: =IFERROR(+Q99/Q116,"") -> 0.193379 | R29: =IFERROR(+R99/R116,"") -> 0.17595032 | S29: =IFERROR(+S99/S116,"") -> 0.02306968 | T29: =IFERROR(+T99/T116,"") -> 0.57042563 | U29: =IFERROR(+U99/U116,"") -> 0.0125
B30: Return on Invested Capital (ROIC) | D30: =IFERROR(+D99/(D115+D116),"") -> 0.027055424 | E30: =IFERROR(+E99/(E115+E116),"") | F30: =IFERROR(+F99/(F115+F116),"") | G30: =IFERROR(+G99/(G115+G116),"") | H30: =IFERROR(+H99/(H115+H116),"") | I30: =IFERROR(+AVERAGE(D30:H30),"") -> 0.027055424 | P30: =IFERROR(+P99/(P115+P116),"") -> 0.15331973 | Q30: =IFERROR(+Q99/(Q115+Q117),"") -> 0.75432607 | R30: =IFERROR(+R99/(R115+R116),"") -> 0.061740623 | S30: =IFERROR(+S99/(S115+S116),"") -> 0.011709882 | T30: =IFERROR(+T99/(T115+T116),"") -> 0.31026253 | U30: =IFERROR(+U99/(U115+U116),"") -> 0.0080395795
B32: Solvency | D32: =+D23 -> Natura | E32: =+E23 -> 0 | F32: =+F23 -> #REF! | G32: =+G23 -> #REF! | H32: =+H23 -> #REF! | I32: =+I23 -> Average | P32: =+P23 -> E.L.F. | Q32: =+Q23 -> L'Oreal | R32: =+R23 -> Estée Lauder | S32: =+S23 -> Coty | T32: =+T23 -> Ulta Beauty | U32: =+U23 -> Shiseido
B34: Debt/Assets | D34: =IFERROR(D115/D111,"") -> 0.21053506 | E34: =IFERROR(E115/E111,"") | F34: =IFERROR(F115/F111,"") | G34: =IFERROR(G115/G111,"") | H34: =IFERROR(H115/H111,"") | I34: =IFERROR(+AVERAGE(D34:H34),"") -> 0.21053506 | P34: =IFERROR(P115/P111,"") -> 0.16851147 | Q34: =IFERROR(Q115/Q111,"") -> 0.15074619 | R34: =IFERROR(R115/R111,"") -> 0.45347603 | S34: =IFERROR(S115/S111,"") -> 0.34105768 | T34: =IFERROR(T115/T111,"") -> 0.33485194 | U34: =IFERROR(U115/U111,"") -> 0.27271653
B35: Net Debt/EBITDA | D35: =IFERROR(+(D115-D105)/D94,"") -> 0.76223776 | E35: =IFERROR(+(E115-E105)/E94,"") | F35: =IFERROR(+(F115-F105)/F94,"") | G35: =IFERROR(+(G115-G105)/G94,"") | H35: =IFERROR(+(H115-H105)/H94,"") | I35: =IFERROR(+AVERAGE(D35:H35),"") -> 0.76223776 | P35: =IFERROR(+(P115-P105)/P94,"") -> 0.54843019 | Q35: =IFERROR(+(Q115-Q105)/Q94,"") -> 0.46079652 | R35: =IFERROR(+(R115-R106)/R94,"") -> 2.8223615 | S35: =IFERROR(+(S115-S105)/S94,"") -> 3.6037736 | T35: =IFERROR(+(T115-T105)/T94,"") -> 0.5026362 | U35: =IFERROR(+(U115-U105)/U94,"") -> 2.0946502
B36: Interest Coverage Ratio | D36: =IFERROR(D95/D96,"") -> 11.608696 | E36: =IFERROR(E95/E96,"") | F36: =IFERROR(F95/F96,"") | G36: =IFERROR(G95/G96,"") | H36: =IFERROR(H95/H96,"") | I36: =IFERROR(+AVERAGE(D36:H36),"") -> 11.608696 | P36: =IFERROR(P95/P96,"") -> 16.257143 | Q36: =IFERROR(Q95/Q96,"") -> 39.616438 | R36: =IFERROR(R95/R96,"") -> 7.5260664 | S36: =IFERROR(S95/S96,"") -> 2.3055556 | T36: =IFERROR(T95/R75,"") -> -84.45 | U36: =IFERROR(U95/U96,"") -> -10.904762
B38: Liquidity | D38: =+D23 -> Natura | E38: =+E23 -> 0 | F38: =+F23 -> #REF! | G38: =+G23 -> #REF! | H38: =+H23 -> #REF! | I38: =+I23 -> Average | P38: =+P23 -> E.L.F. | Q38: =+Q23 -> L'Oreal | R38: =+R23 -> Estée Lauder | S38: =+S23 -> Coty | T38: =+T23 -> Ulta Beauty | U38: =+U23 -> Shiseido
B40: Cash Ratio | D40: =IFERROR(D105/D113,"") -> 0.46371227 | E40: =IFERROR(E105/E113,"") | F40: =IFERROR(F105/F113,"") | G40: =IFERROR(G105/G113,"") | H40: =IFERROR(H105/H113,"") | I40: =IFERROR(+AVERAGE(D40:H40),"") -> 0.46371227 | P40: =IFERROR(P105/P113,"") -> 0.36175192 | Q40: =IFERROR(Q105/Q113,"") -> 0.2768516 | R40: =IFERROR(R106/R113,"") -> 0.30287618 | S40: =IFERROR(S105/S113,"") -> 0.11568025 | T40: =IFERROR(T105/T113,"") -> 0.46260555 | U40: =IFERROR(U105/U113,"") -> 0.30833004
B41: Quick Ratio | D41: =IFERROR(+(D105+D106)/D113,"") -> 1.0134875 | E41: =IFERROR(+(E105+E106)/E113,"") | F41: =IFERROR(+(F105+F106)/F113,"") | G41: =IFERROR(+(G105+G106)/G113,"") | H41: =IFERROR(+(H105+H106)/H113,"") | I41: =IFERROR(+AVERAGE(D41:H41),"") -> 1.0134875 | P41: =IFERROR(+(P105+P106)/P113,"") -> 0.77566031 | Q41: =IFERROR(+(Q105+Q106)/Q113,"") -> 0.65953813 | R41: =IFERROR(+(R105+R106)/R113,"") -> 0.8982813 | S41: =IFERROR(+(S105+S106)/S113,"") -> 0.28554958 | T41: =IFERROR(+(T105+T106)/T113,"") -> 0.5880579 | U41: =IFERROR(+(U105+U106)/U113,"") -> 0.67666798
B42: Current Ratio | D42: =IFERROR(D109/D113,"") -> 1.5754656 | E42: =IFERROR(E109/E113,"") | F42: =IFERROR(F109/F113,"") | G42: =IFERROR(G109/G113,"") | H42: =IFERROR(H109/H113,"") | I42: =IFERROR(+AVERAGE(D42:H42),"") -> 1.5754656 | P42: =IFERROR(P109/P113,"") -> 1.5951187 | Q42: =IFERROR(Q109/Q113,"") -> 1.1255124 | R42: =IFERROR(R109/R113,"") -> 1.3893371 | S42: =IFERROR(S109/S113,"") -> 0.754804 | T42: =IFERROR(T109/T113,"") -> 1.7110977 | U42: =IFERROR(U109/U113,"") -> 1.1985788
B44: Activity | D44: =+D23 -> Natura | E44: =+E23 -> 0 | F44: =+F23 -> #REF! | G44: =+G23 -> #REF! | H44: =+H23 -> #REF! | I44: =+I23 -> Average | P44: =+P23 -> E.L.F. | Q44: =+Q23 -> L'Oreal | R44: =+R23 -> Estée Lauder | S44: =+S23 -> Coty | T44: =+T23 -> Ulta Beauty | U44: =+U23 -> Shiseido
B46: Inventory Turnover | D46: =IFERROR(D92/(AVERAGE(D107:D108)),"") -> 2.6373626 | E46: =IFERROR(E92/(AVERAGE(E107:E108)),"") | F46: =IFERROR(F92/(AVERAGE(F107:F108)),"") | G46: =IFERROR(G92/(AVERAGE(G107:G108)),"") | H46: =IFERROR(H92/(AVERAGE(H107:H108)),"") | I46: =IFERROR(+AVERAGE(D46:H46),"") -> 2.6373626 | P46: =IFERROR(P92/(AVERAGE(P107:P108)),"") -> 2.1979472 | Q46: =IFERROR(Q92/(AVERAGE(Q107:Q108)),"") -> 2.464223 | R46: =IFERROR(R92/(AVERAGE(R107:R108)),"") -> 1.7163368 | S46: =IFERROR(S92/(AVERAGE(S107:S108)),"") -> 2.6493506 | T46: =IFERROR(T92/(AVERAGE(T107:T108)),"") -> 4.0813154 | U46: =IFERROR(U92/(AVERAGE(U107:U108)),"") -> 1.5055209
B47: Acc. Receivable Turnover | D47: =IFERROR(D91/D106,"") -> 5.2418224 | E47: =IFERROR(E91/E106,"") | F47: =IFERROR(F91/F106,"") | G47: =IFERROR(G91/G106,"") | H47: =IFERROR(H91/H106,"") | I47: =IFERROR(+AVERAGE(D47:H47),"") -> 5.2418224 | P47: =IFERROR(P91/P106,"") -> 8.2705977 | Q47: =IFERROR(Q91/Q106,"") -> 7.7639707 | R47: =IFERROR(R91/R106,"") -> 9.0376375 | S47: =IFERROR(S91/S106,"") -> 13.841629 | T47: =IFERROR(T91/T106,"") -> 53.879808 | U47: =IFERROR(U91/U106,"") -> 7.0150054
B48: Payables Turnover | D48: =IFERROR(D92/D112,"") -> 1.163311 | E48: =IFERROR(E92/E112,"") | F48: =IFERROR(F92/F112,"") | G48: =IFERROR(G92/G112,"") | H48: =IFERROR(H92/H112,"") | I48: =IFERROR(+AVERAGE(D48:H48),"") -> 1.163311 | P48: =IFERROR(P92/P112,"") -> 3.6966708 | Q48: =IFERROR(Q92/Q112,"") -> 1.7357761 | R48: =IFERROR(R92/R112,"") -> 0.94629867 | S48: =IFERROR(S92/S112,"") -> 0.90839695 | T48: =IFERROR(T92/T112,"") -> 7.2771855 | U48: =IFERROR(U92/U112,"") -> 1.1304975
B49: Fixed Asset Turnover | D49: =IFERROR(D91/D110,"") -> 6.1047619 | E49: =IFERROR(E91/E110,"") | F49: =IFERROR(F91/F110,"") | G49: =IFERROR(G91/G110,"") | H49: =IFERROR(H91/H110,"") | I49: =IFERROR(+AVERAGE(D49:H49),"") -> 6.1047619 | P49: =IFERROR(P91/P110,"") -> 24.731884 | Q49: =IFERROR(Q91/Q110,"") -> 7.2901928 | R49: =IFERROR(R91/R110,"") -> 3.1410747 | S49: =IFERROR(S91/S110,"") -> 6.2813142 | T49: =IFERROR(T91/T110,"") -> 4.0649256 | U49: =IFERROR(U91/U110,"") -> 2.5798187
B50: Total Asset Turnover | D50: =IFERROR(D91/D111,"") -> 0.74559654 | E50: =IFERROR(E91/E111,"") | F50: =IFERROR(F91/F111,"") | G50: =IFERROR(G91/G111,"") | H50: =IFERROR(H91/H111,"") | I50: =IFERROR(+AVERAGE(D50:H50),"") -> 0.74559654 | P50: =IFERROR(P91/P111,"") -> 0.90666785 | Q50: =IFERROR(Q91/Q111,"") -> 0.77167143 | R50: =IFERROR(R91/R111,"") -> 0.72002583 | S50: =IFERROR(S91/S111,"") -> 0.50633121 | T50: =IFERROR(T91/T111,"") -> 1.9637288 | U50: =IFERROR(U91/U111,"") -> 0.77336642
B51: Cash Cycle (days) | D51: =IFERROR(365/D46+365/D47-365/D48,"") -> -105.73151 | E51: =IFERROR(365/E46+365/E47-365/E48,"") | F51: =IFERROR(365/F46+365/F47-365/F48,"") | G51: =IFERROR(365/G46+365/G47-365/G48,"") | H51: =IFERROR(365/H46+365/H47-365/H48,"") | I51: =IFERROR(+AVERAGE(D51:H51),"") -> -105.73151 | P51: =IFERROR(365/P46+365/P47-365/P48,"") -> 111.45879 | Q51: =IFERROR(365/Q46+365/Q47-365/Q48,"") -> -15.148835 | R51: =IFERROR(365/R46+365/R47-365/R48,"") -> -132.66444 | S51: =IFERROR(365/S46+365/S47-365/S48,"") -> -237.66739 | T51: =IFERROR(365/T46+365/T47-365/T48,"") -> 46.049535 | U51: =IFERROR(365/U46+365/U47-365/U48,"") -> -28.39438
B53: Cash Flow | D53: =+D32 -> Natura | E53: =+E32 -> 0 | F53: =+F32 -> #REF! | G53: =+G32 -> #REF! | H53: =+H32 -> #REF! | I53: =+I32 -> Average | P53: =+P32 -> E.L.F. | Q53: =+Q32 -> L'Oreal | R53: =+R32 -> Estée Lauder | S53: =+S32 -> Coty | T53: =+T32 -> Ulta Beauty | U53: =+U32 -> Shiseido
B55: Cash Flow Margin | D55: =IFERROR(D126/D91,"") -> -0.046133274 | E55: =IFERROR(E126/E91,"") | F55: =IFERROR(F126/F91,"") | G55: =IFERROR(G126/G91,"") | H55: =IFERROR(H126/H91,"") | I55: =IFERROR(+AVERAGE(D55:H55),"") -> -0.046133274 | P55: =IFERROR(P126/P91,"") -> -0.012305889 | Q55: =IFERROR(Q126/Q91,"") -> 0.0054040381 | R55: =IFERROR(R126/R91,"") -> -0.040620195 | S55: =IFERROR(S126/S91,"") -> 0.006047728 | T55: =IFERROR(T126/T91,"") -> 0.0025876684 | U55: =IFERROR(U126/U91,"") -> -0.0062643239
B56: Cash Flow to Net Income | D56: =IFERROR(D126/D90,"") -> -0.92 | E56: =IFERROR(E126/E90,"") | F56: =IFERROR(F126/F90,"") | G56: =IFERROR(G126/G90,"") | H56: =IFERROR(H126/H90,"") | I56: =IFERROR(+AVERAGE(D56:H56),"") -> -0.92 | P56: =IFERROR(P126/P90,"") -> -0.20487805 | Q56: =IFERROR(Q126/Q90,"") -> 0.038001294 | R56: =IFERROR(R126/R90,"") -> -0.50801282 | S56: =IFERROR(S126/S90,"") -> 0.19170984 | T56: =IFERROR(T126/T90,"") -> 0.023237179 | U56: =IFERROR(U126/U90,"") -> -0.2039801
B57: CFO to Net Income | D57: =+IFERROR(D120/D99,"") -> -4.6213592 | E57: =+IFERROR(E120/E99,"") | F57: =+IFERROR(F120/F99,"") | G57: =+IFERROR(G120/G99,"") | H57: =+IFERROR(H120/H99,"") | I57: =IFERROR(+AVERAGE(D57:H57),"") -> -4.6213592 | P57: =+IFERROR(P120/P99,"") -> 0.55755677 | Q57: =+IFERROR(Q120/Q99,"") -> 1.2930712 | R57: =+IFERROR(R120/R99,"") -> 2.5240642 | S57: =+IFERROR(S121/S99,"") -> -2.3061224 | T57: =+IFERROR(T120/T99,"") -> 1.1353846 | U57: =+IFERROR(U120/U99,"") -> 6.1538462
B58: Net Capex to CFO | D58: =IFERROR(-D121/D120,"") -> -0.20378151 | E58: =IFERROR(-E121/E120,"") | F58: =IFERROR(-F121/F120,"") | G58: =IFERROR(-G121/G120,"") | H58: =IFERROR(-H121/H120,"") | I58: =IFERROR(+AVERAGE(D58:H58),"") -> -0.20378151 | P58: =IFERROR(-P121/P120,"") -> 0.12219101 | Q58: =IFERROR(-Q121/Q120,"") -> 0.1980449 | R58: =IFERROR(-R121/R120,"") -> 0.38940678 | S58: =IFERROR(-S120/S121,"") -> 2.7212389 | T58: =IFERROR(-T121/T120,"") -> 0.29471545 | U58: =IFERROR(-U121/U120,"") -> 1.015625
B59: CFI to CFO | D59: =IFERROR(-D122/D120,"") -> 0.8907563 | E59: =IFERROR(-E122/E120,"") | F59: =IFERROR(-F122/F120,"") | G59: =IFERROR(-G122/G120,"") | H59: =IFERROR(-H122/H120,"") | I59: =IFERROR(+AVERAGE(D59:H59),"") -> 0.8907563 | P59: =IFERROR(-P122/P120,"") -> 3.9985955 | Q59: =IFERROR(-Q122/Q120,"") -> 0.44689838 | R59: =IFERROR(-R122/R120,"") -> 0.40677966 | S59: =IFERROR(-S122/S121,"") -> -1 | T59: =IFERROR(-T122/T120,"") -> 0.29878049 | U59: =IFERROR(-U122/U120,"") -> 1.728125
B60: Net Financing to CFO | D60: =IFERROR((D123+D124)/D120,"") -> 0 | E60: =IFERROR((E123+E124)/E120,"") | F60: =IFERROR((F123+F124)/F120,"") | G60: =IFERROR((G123+G124)/G120,"") | H60: =IFERROR((H123+H124)/H120,"") | I60: =IFERROR(+AVERAGE(D60:H60),"") -> 0 | P60: =IFERROR((P123+P124)/P120,"") -> 2.761236 | Q60: =IFERROR((Q123+Q124)/Q120,"") -> -0.30207579 | R60: =IFERROR((R123+R124)/R120,"") -> 0.12118644 | S60: =IFERROR((S123+S124)/S121,"") -> -17.5 | T60: =IFERROR((T123+T124)/T120,"") -> 0.13211382 | U60: =IFERROR((U123+U124)/U120,"") -> 2.43125
B61: Debt Borrowing to Debt Repayment | D61: =+IFERROR(-D124/D123,"") | E61: =+IFERROR(-E124/E123,"") | F61: =+IFERROR(-F124/F123,"") | G61: =+IFERROR(-G124/G123,"") | H61: =+IFERROR(-H124/H123,"") | I61: =IFERROR(+AVERAGE(D61:H61),"") | P61: =+IFERROR(-P124/P123,"") -> 0.038630807 | Q61: =+IFERROR(-Q124/Q123,"") -> -9.1747967 | R61: =+IFERROR(-R124/R123,"") -> 1.8125 | S61: =+IFERROR(-S124/S123,"") -> 0.076581835 | T61: =+IFERROR(-T124/T123,"") -> 0 | U61: =+IFERROR(-U124/U123,"") -> -0.089635854
B62: CFF to CFO | D62: =IFERROR(-D125/D120,"") -> -0.3802521 | E62: =IFERROR(-E125/E120,"") | F62: =IFERROR(-F125/F120,"") | G62: =IFERROR(-G125/G120,"") | H62: =IFERROR(-H125/H120,"") | I62: =IFERROR(+AVERAGE(D62:H62),"") -> -0.3802521 | P62: =IFERROR(-P125/P120,"") -> -2.8216292 | Q62: =IFERROR(-Q125/Q120,"") -> 0.57748009 | R62: =IFERROR(-R125/R120,"") -> 0.86228814 | S62: =IFERROR(-S125/S121,"") -> -1.4911504 | T62: =IFERROR(-T125/T120,"") -> 0.68157182 | U62: =IFERROR(-U125/U120,"") -> -0.48125
B63: Payout Ratio | D63: 0 | I63: =IFERROR(+AVERAGE(D63:H63),"") -> 0 | P63: 0 | Q63: 0.5523 | R63: 4.7143 | S63: 0 | T63: 0 | U63: 12.362
B65: Stock Information | D65: =+D23 -> Natura | E65: =+E23 -> 0 | F65: =+F23 -> #REF! | G65: =+G23 -> #REF! | H65: =+H23 -> #REF! | I65: =+I23 -> Average | P65: =+P23 -> E.L.F. | Q65: =+Q23 -> L'Oreal | R65: =+R23 -> Estée Lauder | S65: =+S23 -> Coty | T65: =+T23 -> Ulta Beauty | U65: =+U23 -> Shiseido
B67: (%) Float | D67: =812.98/1430 -> 0.56851748 | I67: =IFERROR(+AVERAGE(D67:H67),"") -> 0.56851748 | P67: =55.23/56.4 -> 0.97925532 | Q67: =261.73/534.32 -> 0.48983755 | R67: =232.92/359.72 -> 0.64750361 | S67: =367.14/871.99 -> 0.42103694 | T67: =45.13/45.31 -> 0.99602737 | U67: =348.16/400.99 -> 0.86825108
B68: β (Levered) | D68: {=IFERROR(_FV(D85,"Beta"),"")} -> 1.2257 | E68: {=IFERROR(_FV(E85,"Beta"),"")} | F68: {=IFERROR(_FV(F85,"Beta"),"")} | G68: {=IFERROR(_FV(G85,"Beta"),"")} | H68: {=IFERROR(_FV(H85,"Beta"),"")} | I68: =IFERROR(+AVERAGE(D68:H68),"") -> 1.2257 | P68: {=IFERROR(_FV(P85,"Beta"),"")} -> 1.6084 | Q68: {=IFERROR(_FV(Q85,"Beta"),"")} -> 0.848 | R68: {=IFERROR(_FV(R85,"Beta"),"")} -> 1.178 | S68: {=IFERROR(_FV(S85,"Beta"),"")} -> 2.017 | T68: {=IFERROR(_FV(T85,"Beta"),"")} -> 1.0561 | U68: {=IFERROR(_FV(U85,"Beta"),"")} -> 0.4524
B69: β (Unlevered) | D69: =IFERROR(D68/(1+(1-D98/D97)*(D115/D116)),"") -> 1.0877126 | E69: =IFERROR(E68/(1+(1-E98/E97)*(E115/E116)),"") | F69: =IFERROR(F68/(1+(1-F98/F97)*(F115/F116)),"") | G69: =IFERROR(G68/(1+(1-G98/G97)*(G115/G116)),"") | H69: =IFERROR(H68/(1+(1-H98/H97)*(H115/H116)),"") | I69: =IFERROR(+AVERAGE(D69:H69),"") -> 1.0877126 | P69: =IFERROR(P68/(1+(1-P98/P97)*(P115/P116)),"") -> 1.2778616 | Q69: =IFERROR(Q68/(1+(1-Q98/Q97)*(Q115/Q116)),"") -> 0.70956987 | R69: =IFERROR(R68/(1+(1-R98/R97)*(R115/R116)),"") -> 0.51903511 | S69: =IFERROR(S68/(1+(1-S98/S97)*(S115/S116)),"") -> 1.3140776 | T69: =IFERROR(T68/(1+(1-T98/T97)*(T115/T116)),"") -> 0.64451518 | U69: =IFERROR(U68/(1+(1-U98/U97)*(U115/U116)),"") -> 0.37663644
B70: % Held by Insiders | D70: 0.359 | I70: =IFERROR(+AVERAGE(D70:H70),"") -> 0.359 | P70: 0.0264 | Q70: 0.5717 | R70: 0.0043 | S70: 0.6048 | T70: 0.0028 | U70: 0
B71: % Held by Institutions | D71: 0.5877 | I71: =IFERROR(+AVERAGE(D71:H71),"") -> 0.5877 | P71: 0.9616 | Q71: 0.1469 | R71: 0.9371 | S71: 0.3937 | T71: 0.9532 | U71: 0.0001
B72: Short % Float | I72: =IFERROR(+AVERAGE(D72:H72),"") | P72: 0.1837 | R72: 0.0348 | S72: 0.0455 | T72: 0.0671
B74: Stock Performance | D74: =+D23 -> Natura | E74: =+E23 -> 0 | F74: =+F23 -> #REF! | G74: =+G23 -> #REF! | H74: =+H23 -> #REF! | I74: =+I23 -> Average | P74: =+P23 -> E.L.F. | Q74: =+Q23 -> L'Oreal | R74: =+R23 -> Estée Lauder | S74: =+S23 -> Coty | T74: =+T23 -> Ulta Beauty | U74: =+U23 -> Shiseido
R75: -20
B76: 1 day | D76: {=IFERROR((G79/_xlfn.STOCKHISTORY(C11,TODAY()-1,TODAY()-1,0,0,1))-1,"Non-trading days")} -> Non-trading days | E76: {=IFERROR((H79/_xlfn.STOCKHISTORY(#REF!,TODAY()-1,TODAY()-1,0,0,1))-1,"Non-trading days")} -> Non-trading days | F76: {=IFERROR((F79/_xlfn.STOCKHISTORY(#REF!,TODAY()-1,TODAY()-1,0,0,1))-1,"Non-trading days")} -> Non-trading days | G76: {=IFERROR((G79/_xlfn.STOCKHISTORY(#REF!,TODAY()-1,TODAY()-1,0,0,1))-1,"Non-trading days")} -> Non-trading days | H76: {=IFERROR((H79/_xlfn.STOCKHISTORY(#REF!,TODAY()-1,TODAY()-1,0,0,1))-1,"Non-trading days")} -> Non-trading days | I76: =IFERROR(+AVERAGE(D76:H76),"") | P76: {=IFERROR((P79/_xlfn.STOCKHISTORY(C5,TODAY()-1,TODAY()-1,0,0,1))-1,"Non-trading days")} -> 0 | Q76: {=IFERROR((Q79/_xlfn.STOCKHISTORY(C6,TODAY()-1,TODAY()-1,0,0,1))-1,"Non-trading days")} -> 0.0020042758 | R76: {=IFERROR((R79/_xlfn.STOCKHISTORY(C7,TODAY()-1,TODAY()-1,0,0,1))-1,"Non-trading days")} -> 0 | S76: {=IFERROR((S79/_xlfn.STOCKHISTORY(C8,TODAY()-1,TODAY()-1,0,0,1))-1,"Non-trading days")} -> 0 | T76: {=IFERROR((E79/_xlfn.STOCKHISTORY(C9,TODAY()-1,TODAY()-1,0,0,1))-1,"Non-trading days")} -> Non-trading days | U76: {=IFERROR((F79/_xlfn.STOCKHISTORY(C10,TODAY()-1,TODAY()-1,0,0,1))-1,"Non-trading days")} -> Non-trading days
B77: 1 month | D77: {=IFERROR((G79/_xlfn.STOCKHISTORY(C11,TODAY()-29,TODAY()-29,0,0,1))-1,"Non-trading days")} -> Non-trading days | E77: {=IFERROR((H79/_xlfn.STOCKHISTORY(#REF!,TODAY()-29,TODAY()-29,0,0,1))-1,"Non-trading days")} -> Non-trading days | F77: {=IFERROR((F79/_xlfn.STOCKHISTORY(#REF!,TODAY()-29,TODAY()-29,0,0,1))-1,"Non-trading days")} -> Non-trading days | G77: {=IFERROR((G79/_xlfn.STOCKHISTORY(#REF!,TODAY()-29,TODAY()-29,0,0,1))-1,"Non-trading days")} -> Non-trading days | H77: {=IFERROR((H79/_xlfn.STOCKHISTORY(#REF!,TODAY()-29,TODAY()-29,0,0,1))-1,"Non-trading days")} -> Non-trading days | I77: =IFERROR(AVERAGE(D77:H77),"") | P77: {=IFERROR((P79/_xlfn.STOCKHISTORY(C5,TODAY()-29,TODAY()-29,0,0,1))-1,"Non-trading days")} -> 0.016377505 | Q77: {=IFERROR((Q79/_xlfn.STOCKHISTORY(C6,TODAY()-29,TODAY()-29,0,0,1))-1,"Non-trading days")} -> -0.072823937 | R77: {=IFERROR((R79/_xlfn.STOCKHISTORY(C7,TODAY()-29,TODAY()-29,0,0,1))-1,"Non-trading days")} -> 0.014978276 | S77: {=IFERROR((S79/_xlfn.STOCKHISTORY(C8,TODAY()-29,TODAY()-29,0,0,1))-1,"Non-trading days")} -> -0.10045662 | T77: {=IFERROR((E79/_xlfn.STOCKHISTORY(C9,TODAY()-29,TODAY()-29,0,0,1))-1,"Non-trading days")} -> Non-trading days | U77: {=IFERROR((F79/_xlfn.STOCKHISTORY(C10,TODAY()-29,TODAY()-29,0,0,1))-1,"Non-trading days")} -> Non-trading days
B78: YTD | D78: {=IFERROR((G79/_xlfn.STOCKHISTORY(C11,"2025-01-02","2025-01-02",0,0,1))-1,"Non-trading days")} -> Non-trading days | E78: {=IFERROR((H79/_xlfn.STOCKHISTORY(#REF!,"2025-01-02","2025-01-02",0,0,1))-1,"Non-trading days")} -> Non-trading days | F78: {=IFERROR((F79/_xlfn.STOCKHISTORY(#REF!,"2025-01-02","2025-01-02",0,0,1))-1,"Non-trading days")} -> Non-trading days | G78: {=IFERROR((G79/_xlfn.STOCKHISTORY(#REF!,"2025-01-02","2025-01-02",0,0,1))-1,"Non-trading days")} -> Non-trading days | H78: {=IFERROR((H79/_xlfn.STOCKHISTORY(#REF!,"2025-01-02","2025-01-02",0,0,1))-1,"Non-trading days")} -> Non-trading days | I78: =IFERROR(AVERAGE(D78:H78),"") | P78: {=IFERROR((P79/_xlfn.STOCKHISTORY(C5,"2025-01-02","2025-01-02",0,0,1))-1,"Non-trading days")} -> 0.10504919 | Q78: {=IFERROR((Q79/_xlfn.STOCKHISTORY(C6,"2025-01-02","2025-01-02",0,0,1))-1,"Non-trading days")} -> 0.10899142 | R78: {=IFERROR((R79/_xlfn.STOCKHISTORY(C7,"2025-01-02","2025-01-02",0,0,1))-1,"Non-trading days")} -> 0.1999189 | S78: {=IFERROR((S79/_xlfn.STOCKHISTORY(C8,"2025-01-02","2025-01-02",0,0,1))-1,"Non-trading days")} -> -0.42565598 | T78: {=IFERROR((E79/_xlfn.STOCKHISTORY(C9,"2025-01-02","2025-01-02",0,0,1))-1,"Non-trading days")} -> Non-trading days | U78: {=IFERROR((F79/_xlfn.STOCKHISTORY(C10,"2025-01-02","2025-01-02",0,0,1))-1,"Non-trading days")} -> Non-trading days
B79: Current Price | D79: {=+IFERROR(_FV(D85,"Price"),"")} | E79: {=+IFERROR(_FV(E85,"Price"),"")} | F79: {=+IFERROR(_FV(F85,"Price"),"")} | G79: {=+IFERROR(_FV(G85,"Price"),"")} | H79: {=+IFERROR(_FV(H85,"Price"),"")} | I79: =IFERROR(AVERAGE(D79:H79),"") | P79: {=+IFERROR(_FV(P85,"Price"),"")} -> 135.91 | Q79: {=+IFERROR(_FV(Q85,"Price"),"")} -> 374.95 | R79: {=+IFERROR(_FV(R85,"Price"),"")} -> 88.77 | S79: {=+IFERROR(_FV(S85,"Price"),"")} -> 3.94 | T79: {=+IFERROR(_FV(T85,"Price"),"")} -> 557.82 | U79: {=+IFERROR(_FV(U85,"Price"),"")} -> 17.337
B81: Extra
B83: % Revenues in the US
B85: Income Statement | D85: #VALUE! | E85: PEER 7 | F85: PEER 8 | G85: PEER 9 | H85: PEER 10 | P85: =+DCF!R4 -> #VALUE! | Q85: =A6 -> #VALUE! | R85: =A7 -> #VALUE! | S85: =A8 -> #VALUE! | T85: =A9 -> #VALUE! | U85: =A10 -> #VALUE!
B87: =+Inputs!$B$6&" ("&Inputs!O$4&")" -> Revenue (Sales) (2022) | D87: 5671 | P87: =+_xlfn.XLOOKUP("Revenue (Sales)",Inputs!$B:$B,Inputs!O:O) -> 392.2 | Q87: 38260 | R87: 17737 | S87: 5304 | T87: 8631 | U87: 8169
B88: =+Inputs!$B$6&" ("&Inputs!P$4&")" -> Revenue (Sales) (2023) | D88: 3974 | P88: =+_xlfn.XLOOKUP("Revenue (Sales)",Inputs!$B:$B,Inputs!P:P) -> 578.8 | Q88: 41182 | R88: 15910 | S88: 5554 | T88: 10209 | U88: 6939
B89: EBITDA (2023) | D89: 791 | P89: =+_xlfn.XLOOKUP("EBITDA",Inputs!$B:$B,Inputs!P:P) -> 68.1 | Q89: 8970 | R89: 3011 | S89: 898 | T89: 2207 | U89: 805
B90: Net Income (2023) | D90: 225 | P90: =+_xlfn.XLOOKUP("Net Income",Inputs!$B:$B,Inputs!P:P) -> 61.5 | Q90: 6184 | R90: 1248 | S90: 193 | T90: 1248 | U90: 201
B91: =+Inputs!$B$6&" ("&Inputs!Q$4&")" -> Revenue (Sales) (2024) | D91: 4487 | P91: =+_xlfn.XLOOKUP("Revenue (Sales)",Inputs!$B:$B,Inputs!Q:Q) -> 1023.9 | Q91: 43486 | R91: 15608 | S91: 6118 | T91: 11207 | U91: 6545
B92: COGS (Cost of Goods Sold) | D92: 1560 | P92: =+_xlfn.XLOOKUP($B92,Inputs!$B:$B,Inputs!Q:Q) -> 299.8 | Q92: 11227 | R92: 4423 | S92: 2142 | T92: 6826 | U92: 1568
B93: Gross Profit | D93: 2928 | E93: =+E91-E92 -> 0 | F93: =+F91-F92 -> 0 | G93: =+G91-G92 -> 0 | H93: =+H91-H92 -> 0 | P93: =+_xlfn.XLOOKUP($B93,Inputs!$B:$B,Inputs!Q:Q) -> 724.1 | Q93: =+Q91-Q92 -> 32259 | R93: 11185 | S93: 3976 | T93: 4381 | U93: 4976
B94: EBITDA | D94: 715 | P94: =+_xlfn.XLOOKUP($B94,Inputs!$B:$B,Inputs!Q:Q) -> 149.7 | Q94: 9642 | R94: 2871 | S94: 1060 | T94: 2276 | U94: 729
B95: Operating Income (EBIT) | D95: 534 | P95: =+_xlfn.XLOOKUP($B95,Inputs!$B:$B,Inputs!Q:Q) -> 113.8 | Q95: 8676 | R95: 1588 | S95: 581 | T95: 1689 | U95: 229
B96: Net Interest Expense (Income) | D96: 46 | P96: =+_xlfn.XLOOKUP($B96,Inputs!$B:$B,Inputs!Q:Q) -> 7 | Q96: 219 | R96: 211 | S96: 252 | T96: -18 | U96: -21
B97: Pre-Tax Income (EBT) | D97: 405 | P97: =+_xlfn.XLOOKUP($B97,Inputs!$B:$B,Inputs!Q:Q) -> 105.1 | Q97: 8431 | R97: 1390 | S97: 214 | T97: 1707 | U97: 171
B98: Tax Expense (Benefits) | D98: 302 | P98: =+_xlfn.XLOOKUP($B98,Inputs!$B:$B,Inputs!Q:Q) -> 13.3 | Q98: 2015 | R98: 436 | S98: 96 | T98: 407 | U98: 109
B99: Net Income | D99: 103 | P99: =+_xlfn.XLOOKUP($B99,Inputs!$B:$B,Inputs!Q:Q) -> 127.7 | Q99: 6408 | R99: 935 | S99: 98 | T99: 1300 | U99: 52
B100: EPS basic | D100: 0 | P100: =+_xlfn.XLOOKUP($B100,Inputs!$B:$B,Inputs!Q:Q) -> 2.33 | Q100: 12 | R100: 3 | S100: 0 | T100: 26 | U100: 0
B101: R&D (Research & Development) | D101: - | P101: =+_xlfn.XLOOKUP($B101,Inputs!$B:$B,Inputs!Q:Q) -> 0 | Q101: 1354 | R101: 792 | S101: 127 | T101: 0 | U101: 180
B103: Balance Sheet
B105: Cash & Cash Equivalents | D105: 722 | P105: =+_xlfn.XLOOKUP($B105,Inputs!$B:$B,Inputs!Q:Q) -> 108.2 | Q105: 4052 | R105: 3395 | S105: 301 | T105: 767 | U105: 781
B106: Accounts Receivable | D106: 856 | P106: =+_xlfn.XLOOKUP($B106,Inputs!$B:$B,Inputs!Q:Q) -> 123.8 | Q106: 5601 | R106: 1727 | S106: 442 | T106: 208 | U106: 933
B107: Beginning Inventory | D107: 636 | P107: =+_xlfn.XLOOKUP("Inventory",Inputs!$B:$B,Inputs!P:P) -> 81.3 | Q107: 4482 | R107: 2979 | S107: 853 | T107: 1603 | U107: 1063
B108: Ending Inventory | D108: 547 | P108: =+_xlfn.XLOOKUP("Inventory",Inputs!$B:$B,Inputs!Q:Q) -> 191.5 | Q108: 4630 | R108: 2175 | S108: 764 | T108: 1742 | U108: 1020
B109: Current Assets | D109: 2453 | P109: =+_xlfn.XLOOKUP($B109,Inputs!$B:$B,Inputs!Q:Q) -> 477.1 | Q109: 16473 | R109: 7922 | S109: 1964 | T109: 2837 | U109: 3036
B110: Net PP&E (Property, Plant and Equipment) | D110: 735 | P110: =+_xlfn.XLOOKUP($B110,Inputs!$B:$B,Inputs!Q:Q) -> 41.4 | Q110: 5965 | R110: 4969 | S110: 974 | T110: 2757 | U110: 2537
B111: Total Assets | D111: 6018 | P111: =+_xlfn.XLOOKUP($B111,Inputs!$B:$B,Inputs!Q:Q) -> 1129.3 | Q111: 56353 | R111: 21677 | S111: 12083 | T111: 5707 | U111: 8463
B112: Accounts Payable | D112: 1341 | P112: =+_xlfn.XLOOKUP($B112,Inputs!$B:$B,Inputs!Q:Q) -> 81.1 | Q112: 6468 | R112: 4674 | S112: 2358 | T112: 938 | U112: 1387
B113: Current Liabilities | D113: 1557 | P113: =+_xlfn.XLOOKUP($B113,Inputs!$B:$B,Inputs!Q:Q) -> 299.1 | Q113: 14636 | R113: 5702 | S113: 2602 | T113: 1658 | U113: 2533
B114: Long-term debt | D114: 1225 | P114: =+_xlfn.XLOOKUP($B114,Inputs!$B:$B,Inputs!Q:Q) -> 183.3 | Q114: 5187 | R114: 8968 | S114: 4061 | T114: 1627 | U114: 1493
B115: Total Debt | D115: 1267 | P115: =+_xlfn.XLOOKUP($B115,Inputs!$B:$B,Inputs!Q:Q,,,-1) -> 190.3 | Q115: 8495 | R115: 9830 | S115: 4121 | T115: 1911 | U115: 2308
B116: Shareholder's Equity | D116: 2540 | P116: =+_xlfn.XLOOKUP($B116,Inputs!$B:$B,Inputs!Q:Q) -> 642.6 | Q116: 33137 | R116: 5314 | S116: 4248 | T116: 2279 | U116: 4160
T117: 52
B118: Cash Flow Statement
B120: Operating Cash Flow | D120: -476 | P120: =+_xlfn.XLOOKUP($B120,Inputs!$B:$B,Inputs!Q:Q) -> 71.2 | Q120: 8286 | R120: 2360 | S120: 615 | T120: 1476 | U120: 320
B121: Net Capex | D121: -97 | P121: =+_xlfn.XLOOKUP($B121,Inputs!$B:$B,Inputs!Q:Q) -> -8.7 | Q121: -1641 | R121: -919 | S121: -226 | T121: -435 | U121: -325
B122: Investing Cash Flow | D122: 424 | P122: =+_xlfn.XLOOKUP($B122,Inputs!$B:$B,Inputs!Q:Q) -> -284.7 | Q122: -3703 | R122: -960 | S122: -226 | T122: -441 | U122: -553
B123: Debt Borrowing | P123: =+_xlfn.XLOOKUP($B123,Inputs!$B:$B,Inputs!Q:Q) -> 204.5 | Q123: -246 | R123: -352 | S123: 4283 | T123: 195 | U123: 714
B124: Debt Repayment | P124: =+_xlfn.XLOOKUP($B124,Inputs!$B:$B,Inputs!Q:Q) -> -7.9 | Q124: -2257 | R124: 638 | S124: -328 | T124: 0 | U124: 64
...

Sheet ESG
B2: Environmental, Social and Governance Analysis
B4: Author: | E4: Highlights | N4: Recent News
E5: The company operates with 100% renewable electricity in all the offices and US retail distribution center. | N5: Deadline alert: until May 5, 2025, investors who suffered a loss on elf investments should contact Glancy Prongay and Murray LLP to recover the loss under the federal securities laws. - GlobeNewswire - 14/04/2025 | R5: e.l.f. beauty accused of inflating revenue and profit figures in financial reports. The inventory levels in Q2 FY 2024 were not equivalent to its revenue figures. The company refuted the claims. - Beauty Packaging
B6: Overview | D6: . | E6: It has a 90% overall employee engagement and 96% of employees would recommend it as a great place to work.
B7: Last Update | D7: . | E7: It is ranked as 1 of only 4 U.S. public companies with a board of directores made of at least 2/3 women and 1/3 diverse.
B8: Latest year with data | C8: 2024 | E8: The company is currently facing legal challenges related to allegations of securities fraud and financial misreporting.
B9: GICS Sector | C9: Consumer Staples | E9: It is a cruelty free and affordable brand focused on diversity, inclusivity and ethics.
B10: GICS Industry Group | C10: Personal Care Products | E10: It is significantly reducing overall waste and water usage, implementing sustainability measures.
B11: Final Review | C11: Good
B13: ESG Scores
B14: LSEG ESG Score | C14: 45
B15: E-Score | C15: 49
B16: S-Score | C16: 50 | E16: GHG Scope 1 and 2 Emissions : | N16: Water, Waste, Energy Management:
B17: G-Score | C17: 39
B18: S&P Global ESG Score | C18: 26
B19: Environmental | C19: 16
B20: Social | C20: 28
B21: Governance & Economic | C21: 33
B22: Sustainalytics | C22: 21.5
B23: ISS ESG Corporate Rating | C23: C-
B24: SDG Impact Rating | C24: 0.2
B25: Governance Quality Score | C25: 7
B26: MSCI ESG Ratings | C26: BBB
B29: Industry ESG Overview:
B30: The cosmetics industry is evolving to meet consumer demand for sustainable and accountable practices. The industry has complex supply chains and inconsistent data making it difficult to ensure traceability. ESG investments can push the industry to be cleaner and fairer, transforming the industry towards a more ethical and inclusive.
E33: ENVIRONMENTAL
G35: Overview | H35: Targets | K35: Improvements | O35: Comments
E36: GHG (or CO2) Scope 1 Emissions | H36: By 2030, reduce its scope 1 and scope 2 emissions by 42% by 2030 from FY 2022 as baseline. | K36: Transition from 6% to 100% renewable electricity in al its offices and its US retail distribution center. | O36: Achievieng 100% renewable electricity has a bigger impact in scope 2.
E38: Water Consumption | H38: Reduce water withdrawn by over 350 cubic meters per year by replacing water with compressed air in cleaning glass bottles. | K38: Making FY 2022 a baseline to identify water reduction opportunities; successful water reduction initiative saved 1400 cubic meters of water annually. | O38: The reformulation of product SKUs to incorporate clean ingredients can affect the water usage. Although the volume of products produced was not reported, assuming the net sales are proportional to units, from 2022 to 2023, i noticed net sales increased 48% but water usage only increased 30%. However, from 2023 to 2024, net sales increased 77% and water usage increased 80%.
E40: Energy Consumption | H40: Continue meeting its commitment of sourcing 100% renewable energy for all directly managed facilities. | K40: From FY 2023 to FY 2024, the solar energy representation of total supplier energy utilization went form 2% to 4%. In FY 2024, were introduced biofuels for drayage activities, reducing the reliance on fossil fuels for transportation.
E42: Waste Management | H42: By FY 2030, achieve a 20% reduction in packaging intensity and guarantee that 50% of all packaging contain recycled content or responsibly sourced bio-based content. Eliminate anually 400 tons of packaging through lightweight. | K42: Elimination of more than 2.5 million pounds of excess packaging since 2019; over 1.3 million pounds of material recycled per year achieving an 85% waste diversion rate; new shipping recycled and smaller envelopes. | O42: Sustainable packaging materials and efforts to reduce overall packaging volume; Establishment of a free mail-back recycling program with TerraCycle to dispose e.l.f. packaging.
E44: Other
E46: SOCIAL
B48: Important Sources: | G48: Overview | H48: Targets | K48: Improvements | O48: Comments
B49: Annual Report | E49: Employee Turnover % | H49: Continue having the employee engagement at least 10 pp above the industry benchmark. | K49: The employee engagement % relative to industry benchmark went from 15 pp above the industry benchmark in FY 2022 to 19 pp in FY 2023. The job satisfaction increased in FY 2022 to FY 2023 from 22pp above the benchmark to 25pp. | O49: There is a 90% overall employee engagement. However, some employees report a high workload in peak periods and a lack of intermediate managers. | Z49: https://investor.elfbeauty.com/stock-and-financial/press-releases/landing-news/2023/21-09-2023
B50: Sustainability Report | D50: .
B51: Proxy Statement | D51: . | E51: Salaries & Compensation | H51: Maintain the comprehensive compensation package. | K51: Since 2014, they have granted $180 million in equity to the team, excluding the Executive Team. | O51: "All full-time employees receive a base salary, are bonus eligible under the same bonus plan tied to our financial performance and receive an equity award in e.l.f. Beauty stock." - annual report 2024; it offers benefits such as healthcare, retirement, parental leave, from the start; Inclusion of flexible time off.
E53: Reputation | H53: Be seen as a company that operates with integrity, is transparent and acts ethically in its business dealings. Continue being recognized as a great place to work. Continue strenghtening its reputation as a welcoming and affordable brand for.a diverse consumer base. | K53: In FY 2022, 95% recommended the company as a great place to work and it increased to 96% in FY 2024.
E55: Discrimination Events | H55: Maintain a workplace and brand free from discrimination. | K55: In 2024, it was reported a sponsorship of the NACD Center for Inclusive Governance by e.l.f. beauty inc., promoting board diversity and inclusion and the creation of companies with more inclusive leadership. | O55: The company distinguishes itself in this area, as of April 2025, there are no publicly reported lawsuits or controversies related to discrimination.
E57: Work Safety | H57: Continue enhancing safety training and real-time incident reported systems. | K57: The company already declared that has implemented measures to avoid similiar issues. | O57: There are also some dangerous chemicals used to make its products.
E59: Damage to consumer health | H59: Continue formulating clean products. | K59: In FY 2024, reformulated over 100 product SKUs to exclude many ingredients above and beyond FDA and EUCR restrictions. In FY 2024, 100% of the products had a glossary of key ingredients publicly available online. | O59: The company chooses not to use over 2500 ingredients well above the 11 ingredients restricted by the FDA. e.l.f. beauty inc. regularly evaluates the list of ingredients chosen not to include in their products.
E61: Pension Plan | H61: Continue supporting long-term employee well-being. | K61: Established a 401(k) plan and an "Equity Award Retirement Policy", reserving stock options, RSUs and PSUs, for retirement-eligible employees.
E63: Supply chain | H63: By FY 2025, achieve the 100% of the % of paper boxes made with are FSC-certified paper, maintain the 100% of the % of paper cartons that are FSC-certified and increase to 100% the % of wood brush handles made with FSC-certified wood. By FY 2027, the goal is to achieve 100% of RSPO-certified palm oil-based ingredients. The FY 2027 goal is to maintain the 100% of responsibly sourced mica. | K63: From FY 2023 to FY 2024, the palm oil-related ingredients the company's suppliers bought that were from RSPO-certified sources improved from 50% to 75%. In FY 2024, 100% of their mica was responsibly sourced. Increase of the % of paper product boxes made with FSC-certified paper from 23% in FY 2022 to 75% in FY 2023. | O63: The company is highly competitive in the affordable beauty sector, having a completely different supply chain strategy from big luxury companies, that focus on vertical integrated production. There has been a commitment to cruelty-free products since the beginning.
E65: Community involvement | H65: Continue donating 2% of prior year profits. It is focusing on partnerships that help communities facing disadvanatges (racial and women injustice, underserved students). | K65: In FY 2024, the company donated 2% of prior year profits to many charities to drive positive impact in their communities ($1.2 million). | O65: It has already done many programs (such as e.l.f. Cares) , campaigns, collaborations and partnerships to promote awareness in mainly mental health and social justice . It promotes self-expression and confidence-building. The company is supporting women's empowerment through sports, with sponsorships and brand partnerships.
E67: Public Sector | H67: Always comply with state regulation. | K67: It ensured compliance with all regulatory requirements and participated in initiatives that promote ethical business practices. | O67: The company is not partly state-owned, it is a publicly traded company. This sector is highly regulated to ensure that companies operate legally and maintain consumer trust. The governmentral interference aims to ensure consumer safety.
E69: Litigation | H69: It aims to operate within the bounds of all laws and regulations. | K69: After the 2019 situation of North Korea, it implemented many measures and the problem did not happen again. | O69: In 2020, it faced a class action lawsuit alleging the declaration of oil-free products that contained oils. The company is currently facing legal challenges related to allegations of securities' fraud and financial misreporting. However, they are are only allegations, not findings. Also, there isn't a clear history of the company being found guilty, it actually won a case (dupe mascara with Benefit cosmetics). It is also facing a class acton lawsuit alleging it sells some products in oversized containers that are up to half empty.
E71: GOVERNANCE
G73: Overview | H73: Targets | K73: Improvements | O73: Comments
E74: Diversity (Gender, Age, Industry, Region) | H74: By 2027, help double the rate at which women and people of color are added to the boards of directors of U.S. based, publicly traded companies. | K74: The % of women in the board increased from 56% in FY 2022 to 67% in FY 2024. | O74: In september 2024, the employees' base was 78% women, 44% diverse and 72% millennial and Gen Z. The company is ranked as 1 of only 4 U.S. public companies with a board of directors made of at least 2/3 women and 1/3 diverse.
E76: % Independence | H76: Maintain a high % of independence in the board. | K76: It ensured that a majority of the board members are independent, contributing to stronger supervision and governance practices. | O76: In the last proxy statement, it was reported that the % of independence is 89%.
E78: Average time as independent directors | H78: Maintain a balanced board tenure, preserving institucional knowledge and strategic continuity. | K78: It has maintained a balanced tenure, combining deeper knowledge with new perspetives. | O78: The average tenure was 5.2 years in FY 2023.
E80: Departures of C-level executives | H80: Strenghtening leadership continuity to reduce unexpected c-level departures. | K80: It has demonstrated stability on the team. | O80: It was recently announced that Beth Pritchard, a Director of the board, resigned after serving this role since November 2017. It was reported that it was not due to any disagreement with the company.
E82: CEO/Chairman duality | H82: The company hasn't showed any intention to change the structure where Taran P. Amin holds both positions. | K82: Since FY 2020, there has been an independent lead director. | O82: The CEO is the same person and the Chairman since 2014, therefore it is not independent. This can lead to conflicts of interest. However, it seems to be working as the company continues improving.
E84: Transparency when reporting | H84: Expand ESG disclosures, providing regular updates on key performance indicators. | K84: The company started releasing annual impact reports since FY 2022. | O84: It isn't very transparent in some topics, such as the energy consumption and waste management. It also seems to lack some transparency regarding financial reporting.
E86: Time taken to report | H86: Take the least time possible to report so stakeholders have acess to actual and actionable information. | K86: It seems that there hasn't been any improvement in the time taken to report since the company releases its annual reports in may. | O86: It takes usually 2 months to release the annual report. However, the impact report was released only 6 to 7 months after the end of the FY.
E88: CEO or Chairman in other boards? | H88: Taran Amin could expand his board presence in tech-driven or sustainability-focused organizations that align with clean beauty and digital innovation. | K88: The CEO has expanded his strategic influence by being a part of boards in consumer goods, wellness, private equity and academic leadership companies. | O88: The CEO is on boards of other public companies and is the President and CEO of another company and Vice President of another. It accumulates shareman, president and CEO functions.
E90: Audit / Consulting | H90: The company aims to continue with Deloitte as their independent registered public accounting firm in FY 2025. | K90: The audit fees increased from FY 2023 to FY 2024. | O90: The increase of the audit fees can reveal a more detailed audit. The audit fees are ranging the same values within its peers.
E92: ESG-compensation related
E94: Management compensation schemes | H94: Incorporate long-term performance indicators to drive sustainable value creation. | K94: Over the years, the stock awards value for each manager has increased, maintaining their salary and non equity incentive plan compensation. | O94: The percentage of stock awards in the total amount received by managers is aproximately 85%. There aren't any option awards. It can become a risk to have such a high dependence on stocks, that may drive the stock price up without increasing the profitability of the company. The company has option awards.

Sheet ESG Inputs
B2: ESG Inputs
A4: x | B4: Total GHG Scope 1 Emissions | G4: 2014 | H4: =+G4+1 -> 2015 | I4: =+H4+1 -> 2016 | J4: =+I4+1 -> 2017 | K4: =+J4+1 -> 2018 | L4: =+K4+1 -> 2019 | M4: =+L4+1 -> 2020 | N4: =+M4+1 -> 2021 | O4: =+N4+1 -> 2022 | ... Q4: =+P4+1 -> 2024 | R4: ="CAGR "&$G$4&" - "&$Q$4 -> CAGR 2014 - 2024
B6: =+Peers!B5 -> E.L.F. BEAUTY, INC. | O6: 12 | P6: 13 | Q6: 67 | R6: =IFERROR((Q6/G6)^(1/COUNT($G$4:$Q$4))-1,"") | T6: https://www.elfbeauty.com/pdfs/e-l-f-beauty-climate-change-and-emissions-policy-sept-2024-vdraft.pdf
B7: =+Peers!B6 -> L'Oreal S.A. | R7: =IFERROR((Q7/G7)^(1/COUNT($G$4:$Q$4))-1,"")
B8: =+Peers!B7 -> Estée Lauder Companies Inc. | R8: =IFERROR((Q8/G8)^(1/COUNT($G$4:$Q$4))-1,"")
B9: =+Peers!B8 -> Coty Inc. | R9: =IFERROR((Q9/G9)^(1/COUNT($G$4:$Q$4))-1,"")
B10: =+Peers!B9 -> Ulta Beauty | K10: 7 | L10: 7 | M10: 8 | N10: 8 | O10: 8 | P10: 9 | R10: =IFERROR((Q10/G10)^(1/COUNT($G$4:$Q$4))-1,"")
B11: =+Peers!B10 -> Shiseido Company | L11: 27 | M11: 28 | N11: 29 | O11: 24 | P11: 21 | R11: =IFERROR((Q11/G11)^(1/COUNT($G$4:$Q$4))-1,"")
B12: =+Peers!B11 -> Natura &Co Holding SA | G12: 2 | H12: 2 | I12: 2 | J12: 2 | K12: 5 | L12: 7 | M12: 29 | N12: 25 | O12: 27 | R12: =IFERROR((Q12/G12)^(1/COUNT($G$4:$Q$4))-1,"") -> -1
B13: =+Peers!#REF! -> #REF! | R13: =IFERROR((Q13/G13)^(1/COUNT($G$4:$Q$4))-1,"")
B14: =+Peers!#REF! -> #REF! | R14: =IFERROR((Q14/G14)^(1/COUNT($G$4:$Q$4))-1,"")
B15: =+Peers!#REF! -> #REF! | R15: =IFERROR((Q15/G15)^(1/COUNT($G$4:$Q$4))-1,"")
B16: =+Peers!#REF! -> #REF! | R16: =IFERROR((Q16/G16)^(1/COUNT($G$4:$Q$4))-1,"")
A18: x | B18: Total GHG Scope 2 (Location-Based) Emissions | G18: 2014 | H18: =+G18+1 -> 2015 | I18: =+H18+1 -> 2016 | J18: =+I18+1 -> 2017 | K18: =+J18+1 -> 2018 | L18: =+K18+1 -> 2019 | M18: =+L18+1 -> 2020 | N18: =+M18+1 -> 2021 | O18: =+N18+1 -> 2022 | ... Q18: =+P18+1 -> 2024 | R18: ="CAGR "&$G$4&" - "&$Q$4 -> CAGR 2014 - 2024
B20: =+$B$6 -> E.L.F. BEAUTY, INC. | O20: 242 | P20: 219 | Q20: 355 | R20: =IFERROR((Q20/G20)^(1/COUNT($G$4:$Q$4))-1,"") | T20: https://www.elfbeauty.com/pdfs/e-l-f-beauty-climate-change-and-emissions-policy-sept-2024-vdraft.pdf
B21: =+$B$7 -> L'Oreal S.A. | R21: =IFERROR((Q21/G21)^(1/COUNT($G$4:$Q$4))-1,"")
B22: =+$B$8 -> Estée Lauder Companies Inc. | R22: =IFERROR((Q22/G22)^(1/COUNT($G$4:$Q$4))-1,"")
B23: =+$B$9 -> Coty Inc. | R23: =IFERROR((Q23/G23)^(1/COUNT($G$4:$Q$4))-1,"")
B24: =+$B$10 -> Ulta Beauty | L24: 140 | M24: 134 | N24: — | O24: 100 | P24: 80 | R24: =IFERROR((Q24/G24)^(1/COUNT($G$4:$Q$4))-1,"")
B25: =+$B$11 -> Shiseido Company | L25: 52 | M25: 46 | N25: 37 | O25: 23 | P25: 14 | R25: =IFERROR((Q25/G25)^(1/COUNT($G$4:$Q$4))-1,"")
B26: =+$B$12 -> Natura &Co Holding SA | M26: 21 | N26: 45 | O26: 33 | R26: =IFERROR((Q26/G26)^(1/COUNT($G$4:$Q$4))-1,"")
B27: =+$B$13 -> #REF! | R27: =IFERROR((Q27/G27)^(1/COUNT($G$4:$Q$4))-1,"")
B28: =+$B$14 -> #REF! | R28: =IFERROR((Q28/G28)^(1/COUNT($G$4:$Q$4))-1,"")
B29: =+$B$15 -> #REF! | R29: =IFERROR((Q29/G29)^(1/COUNT($G$4:$Q$4))-1,"")
B30: =+$B$16 -> #REF! | R30: =IFERROR((Q30/G30)^(1/COUNT($G$4:$Q$4))-1,"")
A32: x | B32: Total Energy Usage | G32: 2014 | H32: =+G32+1 -> 2015 | I32: =+H32+1 -> 2016 | J32: =+I32+1 -> 2017 | K32: =+J32+1 -> 2018 | L32: =+K32+1 -> 2019 | M32: =+L32+1 -> 2020 | N32: =+M32+1 -> 2021 | O32: =+N32+1 -> 2022 | ... Q32: =+P32+1 -> 2024 | R32: ="CAGR "&$G$4&" - "&$Q$4 -> CAGR 2014 - 2024
B34: =+$B$6 -> E.L.F. BEAUTY, INC. | P34: 15 | Q34: 27
B35: =+$B$7 -> L'Oreal S.A. | R35: =IFERROR((Q35/G35)^(1/COUNT($G$4:$Q$4))-1,"")
B36: =+$B$8 -> Estée Lauder Companies Inc. | R36: =IFERROR((Q36/G36)^(1/COUNT($G$4:$Q$4))-1,"")
B37: =+$B$9 -> Coty Inc. | R37: =IFERROR((Q37/G37)^(1/COUNT($G$4:$Q$4))-1,"")
B38: =+$B$10 -> Ulta Beauty | R38: =IFERROR((Q38/G38)^(1/COUNT($G$4:$Q$4))-1,"")
B39: =+$B$11 -> Shiseido Company | R39: =IFERROR((Q39/G39)^(1/COUNT($G$4:$Q$4))-1,"")
B40: =+$B$12 -> Natura &Co Holding SA | H40: 294 | I40: 279 | J40: 290 | K40: 336 | L40: — | M40: — | N40: — | O40: 317 | R40: =IFERROR((Q40/G40)^(1/COUNT($G$4:$Q$4))-1,"")
B41: =+$B$13 -> #REF! | R41: =IFERROR((Q41/G41)^(1/COUNT($G$4:$Q$4))-1,"")
B42: =+$B$14 -> #REF! | R42: =IFERROR((Q42/G42)^(1/COUNT($G$4:$Q$4))-1,"")
B43: =+$B$15 -> #REF! | R43: =IFERROR((Q43/G43)^(1/COUNT($G$4:$Q$4))-1,"")
B44: =+$B$16 -> #REF! | R44: =IFERROR((Q44/G44)^(1/COUNT($G$4:$Q$4))-1,"")
A46: x | B46: Total Water Consumption | G46: 2014 | H46: =+G46+1 -> 2015 | I46: =+H46+1 -> 2016 | J46: =+I46+1 -> 2017 | K46: =+J46+1 -> 2018 | L46: =+K46+1 -> 2019 | M46: =+L46+1 -> 2020 | N46: =+M46+1 -> 2021 | O46: =+N46+1 -> 2022 | ... Q46: =+P46+1 -> 2024 | R46: ="CAGR "&$G$4&" - "&$Q$4 -> CAGR 2014 - 2024
B48: =+$B$6 -> E.L.F. BEAUTY, INC. | O48: 11560 | P48: 14997 | Q48: 27002 | R48: =IFERROR((Q48/G48)^(1/COUNT($G$4:$Q$4))-1,"")
B49: =+$B$7 -> L'Oreal S.A. | R49: =IFERROR((Q49/G49)^(1/COUNT($G$4:$Q$4))-1,"")
B50: =+$B$8 -> Estée Lauder Companies Inc. | R50: =IFERROR((Q50/G50)^(1/COUNT($G$4:$Q$4))-1,"")
B51: =+$B$9 -> Coty Inc. | R51: =IFERROR((Q51/G51)^(1/COUNT($G$4:$Q$4))-1,"")
B52: =+$B$10 -> Ulta Beauty | R52: =IFERROR((Q52/G52)^(1/COUNT($G$4:$Q$4))-1,"")
B53: =+$B$11 -> Shiseido Company | R53: =IFERROR((Q53/G53)^(1/COUNT($G$4:$Q$4))-1,"")
B54: =+$B$12 -> Natura &Co Holding SA | R54: =IFERROR((Q54/G54)^(1/COUNT($G$4:$Q$4))-1,"")
B55: =+$B$13 -> #REF! | R55: =IFERROR((Q55/G55)^(1/COUNT($G$4:$Q$4))-1,"")
B56: =+$B$14 -> #REF! | R56: =IFERROR((Q56/G56)^(1/COUNT($G$4:$Q$4))-1,"")
B57: =+$B$15 -> #REF! | R57: =IFERROR((Q57/G57)^(1/COUNT($G$4:$Q$4))-1,"")
B58: =+$B$16 -> #REF! | R58: =IFERROR((Q58/G58)^(1/COUNT($G$4:$Q$4))-1,"")
A60: x | B60: Total Waste Production | G60: 2014 | H60: =+G60+1 -> 2015 | I60: =+H60+1 -> 2016 | J60: =+I60+1 -> 2017 | K60: =+J60+1 -> 2018 | L60: =+K60+1 -> 2019 | M60: =+L60+1 -> 2020 | N60: =+M60+1 -> 2021 | O60: =+N60+1 -> 2022 | ... Q60: =+P60+1 -> 2024 | R60: ="CAGR "&$G$4&" - "&$Q$4 -> CAGR 2014 - 2024
B62: =+$B$6 -> E.L.F. BEAUTY, INC. | R62: =IFERROR((Q62/G62)^(1/COUNT($G$4:$Q$4))-1,"")
B63: =+$B$7 -> L'Oreal S.A. | N63: 38 | O63: 42.3 | P63: 30 | R63: =IFERROR((Q63/G63)^(1/COUNT($G$4:$Q$4))-1,"")
B64: =+$B$8 -> Estée Lauder Companies Inc. | R64: =IFERROR((Q64/G64)^(1/COUNT($G$4:$Q$4))-1,"")
B65: =+$B$9 -> Coty Inc. | R65: =IFERROR((Q65/G65)^(1/COUNT($G$4:$Q$4))-1,"")
B66: =+$B$10 -> Ulta Beauty | R66: =IFERROR((Q66/G66)^(1/COUNT($G$4:$Q$4))-1,"")
B67: =+$B$11 -> Shiseido Company | R67: =IFERROR((Q67/G67)^(1/COUNT($G$4:$Q$4))-1,"")
B68: =+$B$12 -> Natura &Co Holding SA | R68: =IFERROR((Q68/G68)^(1/COUNT($G$4:$Q$4))-1,"")
B69: =+$B$13 -> #REF! | R69: =IFERROR((Q69/G69)^(1/COUNT($G$4:$Q$4))-1,"")
B70: =+$B$14 -> #REF! | R70: =IFERROR((Q70/G70)^(1/COUNT($G$4:$Q$4))-1,"")
B71: =+$B$15 -> #REF! | R71: =IFERROR((Q71/G71)^(1/COUNT($G$4:$Q$4))-1,"")
B72: =+$B$16 -> #REF! | R72: =IFERROR((Q72/G72)^(1/COUNT($G$4:$Q$4))-1,"")
A74: x | B74: GHG Scope 1 and 2 Emissions | G74: 2014 | H74: =+G74+1 -> 2015 | I74: =+H74+1 -> 2016 | J74: =+I74+1 -> 2017 | K74: =+J74+1 -> 2018 | L74: =+K74+1 -> 2019 | M74: =+L74+1 -> 2020 | N74: =+M74+1 -> 2021 | O74: =+N74+1 -> 2022 | ... Q74: =+P74+1 -> 2024 | R74: ="CAGR "&$G$4&" - "&$Q$4 -> CAGR 2014 - 2024
B76: =+$B$6 -> E.L.F. BEAUTY, INC. | O76: =+O6+O20 -> 254 | P76: =+P6+P20 -> 232 | Q76: =+Q6+Q20 -> 422 | R76: =IFERROR((Q76/G76)^(1/COUNT($G$4:$Q$4))-1,"")
B77: =+$B$7 -> L'Oreal S.A. | N77: =+N7+N21 -> 0 | O77: =+O7+O21 -> 0 | P77: =+P7+P21 -> 0 | R77: =IFERROR((Q77/G77)^(1/COUNT($G$4:$Q$4))-1,"")
B78: =+$B$8 -> Estée Lauder Companies Inc. | G78: =+G8+G22 -> 0 | H78: =+H8+H22 -> 0 | I78: =+I8+I22 -> 0 | J78: =+J8+J22 -> 0 | K78: =+K8+K22 -> 0 | L78: =+L8+L22 -> 0 | M78: =+M8+M22 -> 0 | N78: =+N8+N22 -> 0 | ... Q78: =+Q8+Q22 -> 0 | R78: =IFERROR((Q78/G78)^(1/COUNT($G$4:$Q$4))-1,"")
B79: =+$B$9 -> Coty Inc. | L79: =+L9+L23 -> 0 | M79: =+M9+M23 -> 0 | N79: =+N9+N23 -> 0 | O79: =+O9+O23 -> 0 | P79: =+P9+P23 -> 0 | R79: =IFERROR((Q79/G79)^(1/COUNT($G$4:$Q$4))-1,"")
B80: =+$B$10 -> Ulta Beauty | G80: =+G10+G24 -> 0 | H80: =+H10+H24 -> 0 | I80: =+I10+I24 -> 0 | J80: =+J10+J24 -> 0 | K80: =+K10+K24 -> 7 | L80: =+L10+L24 -> 147 | M80: =+M10+M24 -> 142 | N80: =+N10+N24 -> #VALUE! | ... Q80: =+Q10+Q24 -> 0 | R80: =IFERROR((Q80/G80)^(1/COUNT($G$4:$Q$4))-1,"")
B81: =+$B$11 -> Shiseido Company | G81: =+G11+G25 -> 0 | H81: =+H11+H25 -> 0 | I81: =+I11+I25 -> 0 | J81: =+J11+J25 -> 0 | K81: =+K11+K25 -> 0 | L81: =+L11+L25 -> 79 | M81: =+M11+M25 -> 74 | N81: =+N11+N25 -> 66 | ... Q81: =+Q11+Q25 -> 0 | R81: =IFERROR((Q81/G81)^(1/COUNT($G$4:$Q$4))-1,"")
B82: =+$B$12 -> Natura &Co Holding SA | G82: =+G12+G26 -> 2 | H82: =+H12+H26 -> 2 | I82: =+I12+I26 -> 2 | J82: =+J12+J26 -> 2 | K82: =+K12+K26 -> 5 | L82: =+L12+L26 -> 7 | M82: =+M12+M26 -> 50 | N82: =+N12+N26 -> 70 | ... Q82: =+Q12+Q26 -> 0 | R82: =IFERROR((Q82/G82)^(1/COUNT($G$4:$Q$4))-1,"") -> -1
B83: =+$B$13 -> #REF! | G83: =+G13+G27 -> 0 | H83: =+H13+H27 -> 0 | I83: =+I13+I27 -> 0 | J83: =+J13+J27 -> 0 | K83: =+K13+K27 -> 0 | L83: =+L13+L27 -> 0 | M83: =+M13+M27 -> 0 | N83: =+N13+N27 -> 0 | ... Q83: =+Q13+Q27 -> 0 | R83: =IFERROR((Q83/G83)^(1/COUNT($G$4:$Q$4))-1,"")
B84: =+$B$14 -> #REF! | G84: =+G14+G28 -> 0 | H84: =+H14+H28 -> 0 | I84: =+I14+I28 -> 0 | J84: =+J14+J28 -> 0 | K84: =+K14+K28 -> 0 | L84: =+L14+L28 -> 0 | M84: =+M14+M28 -> 0 | N84: =+N14+N28 -> 0 | ... Q84: =+Q14+Q28 -> 0 | R84: =IFERROR((Q84/G84)^(1/COUNT($G$4:$Q$4))-1,"")
B85: =+$B$15 -> #REF! | G85: =+G15+G29 -> 0 | H85: =+H15+H29 -> 0 | I85: =+I15+I29 -> 0 | J85: =+J15+J29 -> 0 | K85: =+K15+K29 -> 0 | L85: =+L15+L29 -> 0 | M85: =+M15+M29 -> 0 | N85: =+N15+N29 -> 0 | ... Q85: =+Q15+Q29 -> 0 | R85: =IFERROR((Q85/G85)^(1/COUNT($G$4:$Q$4))-1,"")
B86: =+$B$16 -> #REF! | G86: =+G16+G30 -> 0 | H86: =+H16+H30 -> 0 | I86: =+I16+I30 -> 0 | J86: =+J16+J30 -> 0 | K86: =+K16+K30 -> 0 | L86: =+L16+L30 -> 0 | M86: =+M16+M30 -> 0 | N86: =+N16+N30 -> 0 | ... Q86: =+Q16+Q30 -> 0 | R86: =IFERROR((Q86/G86)^(1/COUNT($G$4:$Q$4))-1,"")

Sheet IESG
B2: Inputs - ESG
B4: GHG_SCOPE_1 | D4: FY 2014 | E4: FY 2015 | F4: FY 2016 | G4: FY 2017 | H4: FY 2018 | I4: FY 2019 | J4: FY 2020 | K4: FY 2021 | L4: FY 2022 | M4: FY 2023 | N4: FY 2024
C5: ELF BEAUTY INC | D5: — | E5: — | F5: — | G5: — | H5: — | I5: — | J5: — | K5: — | L5: 0 | M5: — | N5: —
C6: OSISKO GOLD ROYALTIES LTD | D6: — | E6: — | F6: — | G6: — | H6: — | I6: — | J6: 0 | K6: 0 | L6: 0 | M6: 0 | N6: —
C7: OLAPLEX HOLDINGS INC | D7: — | E7: — | F7: — | G7: — | H7: — | I7: — | J7: — | K7: — | L7: — | M7: — | N7: —
C8: EDGEWELL PERSONAL CARE CO | D8: — | E8: 7 | F8: 5 | G8: 7 | H8: 6 | I8: 10 | J8: 9 | K8: 8 | L8: 8 | M8: 8 | N8: —
C9: ULTA BEAUTY INC | D9: — | E9: — | F9: — | G9: — | H9: 7 | I9: 7 | J9: 8 | K9: 8 | L9: 8 | M9: 9 | N9: —
C10: SHISEIDO LTD-SPONSORED ADR | D10: — | E10: — | F10: — | G10: — | H10: — | I10: 27 | J10: 28 | K10: 29 | L10: 24 | M10: 21 | N10: —
C11: NATURA &CO HOLDING-ADR | D11: 2 | E11: 2 | F11: 2 | G11: 2 | H11: 5 | I11: 7 | J11: 29 | K11: 25 | L11: 27 | M11: — | N11: —
B13: GHG_SCOPE_2_MARKET_BASED
C14: ELF BEAUTY INC | D14: — | E14: — | F14: — | G14: — | H14: — | I14: — | J14: — | K14: — | L14: — | M14: — | N14: —
C15: OSISKO GOLD ROYALTIES LTD | D15: — | E15: — | F15: — | G15: — | H15: — | I15: — | J15: — | K15: — | L15: — | M15: — | N15: —
C16: OLAPLEX HOLDINGS INC | D16: — | E16: — | F16: — | G16: — | H16: — | I16: — | J16: — | K16: — | L16: — | M16: — | N16: —
C17: EDGEWELL PERSONAL CARE CO | D17: — | E17: — | F17: — | G17: — | H17: — | I17: — | J17: — | K17: — | L17: — | M17: — | N17: —
C18: ULTA BEAUTY INC | D18: — | E18: — | F18: — | G18: — | H18: — | I18: 140 | J18: 134 | K18: — | L18: 100 | M18: 80 | N18: —
C19: SHISEIDO LTD-SPONSORED ADR | D19: — | E19: — | F19: — | G19: — | H19: — | I19: 52 | J19: 46 | K19: 37 | L19: 23 | M19: 14 | N19: —
C20: NATURA &CO HOLDING-ADR | D20: — | E20: — | F20: — | G20: — | H20: — | I20: — | J20: 21 | K20: 45 | L20: 33 | M20: — | N20: —
B22: ENERGY_CONSUMPTION
C23: ELF BEAUTY INC | D23: — | E23: — | F23: — | G23: — | H23: — | I23: — | J23: — | K23: — | L23: — | M23: 15 | N23: 27
C24: OSISKO GOLD ROYALTIES LTD | D24: — | E24: — | F24: — | G24: — | H24: — | I24: — | J24: — | K24: — | L24: — | M24: — | N24: —
C25: OLAPLEX HOLDINGS INC | D25: — | E25: — | F25: — | G25: — | H25: — | I25: — | J25: — | K25: — | L25: — | M25: — | N25: —
C26: EDGEWELL PERSONAL CARE CO | D26: — | E26: — | F26: — | G26: — | H26: — | I26: 309 | J26: 299 | K26: 294 | L26: 311 | M26: 292 | N26: —
C27: ULTA BEAUTY INC | D27: — | E27: — | F27: — | G27: — | H27: — | I27: — | J27: — | K27: — | L27: — | M27: — | N27: —
C28: SHISEIDO LTD-SPONSORED ADR | D28: — | E28: — | F28: — | G28: — | H28: — | I28: — | J28: — | K28: — | L28: — | M28: — | N28: —
C29: NATURA &CO HOLDING-ADR | D29: — | E29: 294 | F29: 279 | G29: 290 | H29: 336 | I29: — | J29: — | K29: — | L29: 317 | M29: — | N29: —
B31: WATER_CONSMPTN
C32: ELF BEAUTY INC | D32: — | E32: — | F32: — | G32: — | H32: — | I32: — | J32: — | K32: — | L32: — | M32: 15 | N32: 27
C33: OSISKO GOLD ROYALTIES LTD | D33: — | E33: — | F33: — | G33: — | H33: — | I33: — | J33: — | K33: — | L33: — | M33: — | N33: —
C34: OLAPLEX HOLDINGS INC | D34: — | E34: — | F34: — | G34: — | H34: — | I34: — | J34: — | K34: — | L34: — | M34: — | N34: —
C35: EDGEWELL PERSONAL CARE CO | D35: — | E35: — | F35: — | G35: — | H35: — | I35: 309 | J35: 299 | K35: 294 | L35: 311 | M35: 292 | N35: —
C36: ULTA BEAUTY INC | D36: — | E36: — | F36: — | G36: — | H36: — | I36: — | J36: — | K36: — | L36: — | M36: — | N36: —
C37: SHISEIDO LTD-SPONSORED ADR | D37: — | E37: — | F37: — | G37: — | H37: — | I37: — | J37: — | K37: — | L37: — | M37: — | N37: —
C38: NATURA &CO HOLDING-ADR | D38: — | E38: 294 | F38: 279 | G38: 290 | H38: 336 | I38: — | J38: — | K38: — | L38: 317 | M38: — | N38: —
B40: TOTAL_WASTE
C41: ELF BEAUTY INC | D41: — | E41: — | F41: — | G41: — | H41: — | I41: — | J41: — | K41: — | L41: — | M41: — | N41: — | P41: ELF US Equity
C42: OSISKO GOLD ROYALTIES LTD | D42: — | E42: — | F42: — | G42: — | H42: — | I42: — | J42: — | K42: — | L42: — | M42: — | N42: — | P42: OR US Equity
C43: OLAPLEX HOLDINGS INC | D43: — | E43: — | F43: — | G43: — | H43: — | I43: — | J43: — | K43: — | L43: — | M43: — | N43: — | P43: OLPX US Equity
C44: EDGEWELL PERSONAL CARE CO | D44: — | E44: 26 | F44: 22 | G44: 23 | H44: 22 | I44: 26 | J44: 28 | K44: 24 | L44: 20 | M44: 18 | N44: — | P44: EPC US Equity
C45: ULTA BEAUTY INC | D45: — | E45: — | F45: — | G45: — | H45: — | I45: — | J45: 45 | K45: 68 | L45: 74 | M45: 87 | N45: — | P45: ULTA US Equity
C46: SHISEIDO LTD-SPONSORED ADR | D46: 9 | E46: 9 | F46: 10 | G46: 10 | H46: 8 | I46: 7 | J46: 7 | K46: 13 | L46: 13 | M46: 11 | N46: — | P46: SSDOY US Equity
C47: NATURA &CO HOLDING-ADR | D47: 14 | E47: 15 | F47: 14 | G47: 12 | H47: 15 | I47: — | J47: — | K47: 19 | L47: 31 | M47: — | N47: — | P47: NTCO US Equity

Sheet DCF (2)
B2: DCF
A4: x | B4: Key Assumptions | R4: #VALUE!
B6: Switches | E6: Bear Case | H6: Base Case | K6: Bull Case | X6: FCFF | Y6: FCFE | Z6: Tax Shield | AA6: Total Payout | AB6: NOPAT | AC6: Debt Borrowing | AD6: Cash Balance | AE6: Total Assets | AF6: Total Liabilities | AG6: Shareholder's Equity | AH6: Current Liabilities | AI6: Current Assets
B7: Revenue | C7: =AM324 -> 3 | E7: Revenue | F7: -0.06 | H7: Revenue | K7: Revenue | L7: 0.04 | S7: Most Recent Fiscal Year | W7: 2022 | X7: =+E210 -> 7.4733333 | Y7: =+E262 -> 101.5 | Z7: =+H234 -> 0.68221377 | AA7: =+E275 -> 1.7 | AB7: =+E200 -> 7.9733333 | AC7: =+E260 -> 80.1 | AD7: =+E106 -> 43.4
B8: EBIT | C8: =AM325 -> 1 | E8: EBIT | F8: -0.04 | H8: EBIT | K8: EBIT | L8: 0.03 | S8: End of Fiscal Year | W8: =+W7+1 -> 2023 | X8: =+F210 -> 91.954785 | Y8: =+F262 -> 140.3 | Z8: =+I234 -> 0.71676497 | AA8: =+F275 -> 8.1 | AB8: =+F200 -> 43.154785 | AC8: =+F260 -> 30 | AD8: =+F106 -> 120.8
B9: WACC | C9: 2 | E9: WACC | F9: =IFERROR(+I9+0.5%,"") -> 0.078151355 | H9: WACC | I9: =AM322 -> 0.073151355 | K9: WACC | L9: =IFERROR(I9-0.5%,"") -> 0.068151355 | S9: Most Recent Quarter End Date | W9: =+W8+1 -> 2024 | X9: =+G210 -> 49.699049 | Y9: =+G262 -> 290.4 | Z9: =+J234 -> 0.47778107 | AA9: =+G275 -> 5.6 | AB9: =+G200 -> 99.399049 | AC9: =+G260 -> 212.4 | AD9: =+G106 -> 108.2 | AE9: =Inputs!Q48 -> 1129.3 | AF9: =+Inputs!Q60 -> 486.7 | AG9: =+AE9-AF9 -> 642.6 | AH9: =+Inputs!Q54 -> 299.1 | AI9: =+Inputs!Q38 -> 477.1
B10: TGR | C10: 2 | E10: TGR | F10: =+I10-0.5% -> 0.015 | H10: TGR | I10: =AK323 -> 0.02 | K10: TGR | L10: =+I10+0.5% -> 0.025 | S10: Valuation Date | T10: 45755 | W10: =+W9+1 -> 2025 | X10: =+H210 -> -38.135901 | Y10: =+H262 -> -15.514243 | Z10: =+K234 -> 0.27635362 | AA10: =+H275 -> -33.514119 | AB10: =+H200 -> 24.921525 | AC10: =+H260 -> -14.52 | AD10: =+H106 -> 79.24824 | AE10: =Inputs!Q48+'DCF (2)'!H106+'DCF (2)'!H108+'DCF (2)'!H111+'DCF (2)'!H114+'DCF (2)'!H117+'DCF (2)'!H123-'DCF (2)'!G106-'DCF (2)'!G108-'DCF (2)'!G111-'DCF (2)'!G114-'DCF (2)'!G117-'DCF (2)'!G123 -> 1202.4438 | AF10: =+Inputs!Q60+('DCF (2)'!H128+'DCF (2)'!H131+'DCF (2)'!H134+'DCF (2)'!H136*'DCF (2)'!G128*'DCF (2)'!G131*'DCF (2)'!G134*'DCF (2)'!G136) -> 3.8239337e+09 | AG10: =+AE10-AF10 -> -3.8239325e+09 | AH10: =+AH9+H128+H131-G128-G131 -> 233.03012 | AI10: =+H106+H108+H111+H114 -> 534.73919
W11: =+W10+1 -> 2026 | X11: =+I210 -> 166.84217 | Y11: =+I262 -> 221.90412 | Z11: =+L234 -> 0.11241256 | AA11: =+I275 -> -38.319782 | AB11: =+I200 -> 69.937384 | AC11: =+I260 -> 15.514243 | AD11: =+I106 -> 251.41274 | AE11: =AE10+'DCF (2)'!I106+'DCF (2)'!I108+'DCF (2)'!I111+'DCF (2)'!I114+'DCF (2)'!I117+'DCF (2)'!I123-'DCF (2)'!H106-'DCF (2)'!H108-'DCF (2)'!H111-'DCF (2)'!H114-'DCF (2)'!H117-'DCF (2)'!H123 -> 1422.4509 | AF11: =AF10+('DCF (2)'!I128+'DCF (2)'!I131+'DCF (2)'!I134+'DCF (2)'!I136*'DCF (2)'!H128*'DCF (2)'!H131*'DCF (2)'!H134*'DCF (2)'!H136) -> 7.8424011e+09 | AG11: =+AE11-AF11 -> -7.8423997e+09 | AH11: =+AH10+I128+I131-H128-H131 -> 269.63203 | AI11: =+I106+I108+I111+I114 -> 743.66861
B12: WACC | C12: =CHOOSE(C9,F9,I9,L9) -> 0.073151355 | W12: =+W11+1 -> 2027 | X12: =+J210 -> 185.84376 | Y12: =+J262 -> 179.95538 | Z12: =+M234 -> 0.067941166 | AA12: =+J275 -> -74.289503 | AB12: =+J200 -> 105.64848 | AC12: =+J260 -> -48.818907 | AD12: =+J106 -> 441.7623
B13: TGR | C13: =CHOOSE(C10,F10,I10,L10) -> 0.02 | W13: =+W12+1 -> 2028 | X13: =+K210 -> 206.25574 | Y13: =+K262 -> 214.41651 | Z13: =+N234 -> 0.062333339 | AA13: =+K275 -> -90.078039 | AB13: =+K200 -> 136.00424 | AC13: =+K260 -> -35.991076 | AD13: =+K106 -> 627.09341
W14: =+W13+1 -> 2029 | X14: =+L210 -> 261.60525 | Y14: =+L262 -> 262.40058 | Z14: =+O234 -> 0.057570819 | AA14: =+L275 -> -103.86399 | AB14: =+L200 -> 164.04934 | AC14: =+L260 -> -42.883301 | AD14: =+L106 -> 859.59783
A15: x | B15: Operating Assumptions | E15: 2022 | F15: =+E15+1 -> 2023 | G15: =+F15+1 -> 2024 | H15: =+G15+1 -> 2025 | I15: =+H15+1 -> 2026 | J15: =+I15+1 -> 2027 | K15: =+J15+1 -> 2028 | L15: =+K15+1 -> 2029 | M15: =+L15+1 -> 2030 | ... Q15: =+P15+1 -> 2034
B17: Global:
B18: Market Size (Fortune Business Insights) | G18: 335950 | H18: 354680 | I18: =J18-J18*I19 -> 368301.81 | J18: =K18-K18*J19 -> 394496.37 | K18: =L18-L18*K19 -> 422553.95 | L18: =M18-M18*L19 -> 452607.06 | M18: =N18-N18*M19 -> 484797.62 | N18: =O18-O18*N19 -> 519277.66 | O18: 556210 | P18: =O18+O18*P19 -> 593142.34 | Q18: =P18+P18*Q19 -> 632527
B19: Growth Rate | H19: =(H18-G18)/G18 -> 0.055752344 | I19: 0.0664 | J19: 0.0664 | K19: 0.0664 | L19: 0.0664 | M19: 0.0664 | N19: 0.0664 | O19: =(O18-N18)/N18 -> 0.071122536 | P19: 0.0664 | Q19: 0.0664
B20: Market Size (Statista) | E20: 247000 | F20: 252500 | G20: 257540 | H20: =G20*(1+H21) -> 271962.24 | I20: =H20*(1+I21) -> 287192.13 | J20: =I20*(1+J21) -> 303274.88 | K20: =J20*(1+K21) -> 320258.28 | L20: =K20*(1+L21) -> 338192.74 | M20: =L20*(1+M21) -> 357131.54 | N20: =M20*(1+N21) -> 377130.9 | O20: =N20*(1+O21) -> 398250.23 | ... Q20: =P20*(1+Q21) -> 444103.17
B21: Growth Rate | F21: =F20/E20-1 -> 0.022267206 | G21: =G20/F20-1 -> 0.019960396 | H21: 0.056 | I21: 0.056 | J21: 0.056 | K21: 0.056 | L21: 0.056 | M21: 0.056 | N21: 0.056 | O21: 0.056 | P21: 0.056 | Q21: 0.056
B22: Average | E22: =AVERAGE(E18,E20) -> 247000 | F22: =AVERAGE(F18,F20) -> 252500 | G22: =AVERAGE(G18,G20) -> 296745 | H22: =AVERAGE(H18,H20) -> 313321.12 | I22: =AVERAGE(I18,I20) -> 327746.97 | J22: =AVERAGE(J18,J20) -> 348885.63 | K22: =AVERAGE(K18,K20) -> 371406.11 | L22: =AVERAGE(L18,L20) -> 395399.9 | ... Q22: =AVERAGE(Q18,Q20) -> 538315.08
B23: Average (%) | H23: =AVERAGE(H19,H21) -> 0.055876172 | I23: =AVERAGE(I19,I21) -> 0.0612 | J23: =AVERAGE(J19,J21) -> 0.0612 | K23: =AVERAGE(K19,K21) -> 0.0612 | L23: =AVERAGE(L19,L21) -> 0.0612 | M23: =AVERAGE(M19,M21) -> 0.0612 | N23: =AVERAGE(N19,N21) -> 0.0612 | O23: =AVERAGE(O19,O21) -> 0.063561268 | ... Q23: =AVERAGE(Q19,Q21) -> 0.0612
B24: Market Share | E24: =E48/E22 -> 0.0015878543 | F24: =F48/F22 -> 0.0022922772 | G24: =G48/G22 -> 0.0034504372 | H24: =H48/H22 -> 0.0041775033 | I24: =I42/I22 -> 0.0045658615 | J24: =J42/J22 -> 0.0048252371 | K24: =K42/K22 -> 0.0050288491 | L24: =L42/L22 -> 0.0051878861 | M24: =M42/M22 -> 0.0053112885 | N24: =N42/N22 -> 0.0054062003 | O24: =O42/O22 -> 0.0054783303 | P24: =P42/P22 -> 0.0055419096 | Q24: =Q42/Q22 -> 0.0058197265
I25: Prediction of market share results
B27: US:
B28: Market Size (Fortune Business Insights) | C28: Doesn't say nominal numbers, but growth is close | H28: - | I28: - | J28: - | K28: - | L28: - | M28: - | N28: - | O28: - | P28: - | Q28: -
B29: Growth Rate | I29: 0.0601 | J29: 0.0601 | K29: 0.0601 | L29: 0.0601 | M29: 0.0601 | N29: 0.0601 | O29: 0.0601 | P29: 0.0601 | Q29: 0.0601
B30: Market Size (Statista) | E30: 56000 | F30: 61000 | G30: 66000 | H30: 67730 | I30: =H30+H30*I31 -> 71780.254 | J30: =I30+I30*J31 -> 76072.713 | K30: =J30+J30*K31 -> 80621.861 | L30: =K30+K30*L31 -> 85443.049 | M30: =L30+L30*M31 -> 90552.543 | N30: =M30+M30*N31 -> 95967.585 | O30: =N30+N30*O31 -> 101706.45 | P30: =O30+O30*P31 -> 107788.49 | Q30: =P30+P30*Q31 -> 114234.24
B31: Growth Rate | F31: =F30/E30-1 -> 0.089285714 | G31: =G30/F30-1 -> 0.081967213 | H31: =H30/G30-1 -> 0.026212121 | I31: 0.0598 | J31: 0.0598 | K31: 0.0598 | L31: 0.0598 | M31: 0.0598 | N31: 0.0598 | O31: 0.0598 | P31: 0.0598 | Q31: 0.0598
B32: Average | H32: =AVERAGE(H28,H30) -> 67730 | I32: =AVERAGE(I28,I30) -> 71780.254 | J32: =AVERAGE(J28,J30) -> 76072.713 | K32: =AVERAGE(K28,K30) -> 80621.861 | L32: =AVERAGE(L28,L30) -> 85443.049 | M32: =AVERAGE(M28,M30) -> 90552.543 | N32: =AVERAGE(N28,N30) -> 95967.585 | O32: =AVERAGE(O28,O30) -> 101706.45 | ... Q32: =AVERAGE(Q28,Q30) -> 114234.24
B33: Average (%) | I33: =AVERAGE(I29,I31) -> 0.05995 | J33: =AVERAGE(J29,J31) -> 0.05995 | K33: =AVERAGE(K29,K31) -> 0.05995 | L33: =AVERAGE(L29,L31) -> 0.05995 | M33: =AVERAGE(M29,M31) -> 0.05995 | N33: =AVERAGE(N29,N31) -> 0.05995 | O33: =AVERAGE(O29,O31) -> 0.05995 | P33: =AVERAGE(P29,P31) -> 0.05995 | Q33: =AVERAGE(Q29,Q31) -> 0.05995
B34: Market Share (US revenue only) | E34: =E48*E43/E30 -> 0.0062053571 | F34: =F48*F43/F30 -> 0.0083067616 | G34: =G48*G43/G30 -> 0.013151746 | H34: =H48*$G$43/H32 -> 0.016383066 | I34: =H34+($Q$34-H34)/5 -> 0.017106453 | J34: =I34+($Q$34-I34)/5 -> 0.017685163 | K34: =J34+($Q$34-J34)/5 -> 0.01814813 | L34: =K34+($Q$34-K34)/5 -> 0.018518504 | M34: =L34+($Q$34-L34)/5 -> 0.018814803 | N34: =M34+($Q$34-M34)/5 -> 0.019051843 | O34: =N34+($Q$34-N34)/5 -> 0.019241474 | P34: =O34+($Q$34-O34)/5 -> 0.019393179 | Q34: 0.02
I35: Prediction of market share
B36: Global "Minus" US
B37: Market Size (based on averages) | E37: =E20-E30 -> 191000 | F37: =F20-F30 -> 191500 | G37: =G20-G30 -> 191540 | H37: =H22-H32 -> 245591.12 | I37: =I22-I32 -> 255966.71 | J37: =J22-J32 -> 272812.91 | K37: =K22-K32 -> 290784.25 | L37: =L22-L32 -> 309956.85 | M37: =M22-M32 -> 330412.03 | N37: =N22-N32 -> 352236.69 | O37: =O22-O32 -> 375523.67 | ... Q37: =Q22-Q32 -> 424080.84
B38: Growth Rate | F38: =(F37-E37)/E37 -> 0.002617801 | G38: =(G37-F37)/F37 -> 0.00020887728 | H38: =(H37-G37)/G37 -> 0.28219234 | I38: =(I37-H37)/H37 -> 0.042247426 | J38: =(J37-I37)/I37 -> 0.065814025 | K38: =(K37-J37)/J37 -> 0.065874227 | L38: =(L37-K37)/K37 -> 0.065934103 | M38: =(M37-L37)/L37 -> 0.065993648 | ... Q38: =(Q37-P37)/P37 -> 0.062702631
B39: Market Share (non-US revenue only) | E39: =E48*E44/E37 -> 0.00023403141 | F39: =F48*F44/F37 -> 0.00037643627 | G39: =G48*G44/G37 -> 0.00081384972 | H39: =(H48*G44)/H37 -> 0.00081140927 | I39: =H39+($Q$39-H39)/5 -> 0.0010491274 | J39: =I39+($Q$39-I39)/5 -> 0.0012393019 | K39: =J39+($Q$39-J39)/5 -> 0.0013914415 | L39: =K39+($Q$39-K39)/5 -> 0.0015131532 | M39: =L39+($Q$39-L39)/5 -> 0.0016105226 | N39: =M39+($Q$39-M39)/5 -> 0.0016884181 | O39: =N39+($Q$39-N39)/5 -> 0.0017507345 | P39: =O39+($Q$39-O39)/5 -> 0.0018005876 | Q39: 0.002
I40: Prediction of market share
B42: Weighted Average of expected revenue: | H42: =H32*H34+H37*H39 -> 1308.9 | I42: =I32*I34+I37*I39 -> 1496.4472 | J42: =J32*J34+J37*J39 -> 1683.4559 | K42: =K32*K34+K37*K39 -> 1867.7453 | L42: =L32*L34+L37*L39 -> 2051.2897 | M42: =M32*M34+M37*M39 -> 2235.8643 | N42: =N32*N34+N37*N39 -> 2423.0821 | O42: =O32*O34+O37*O39 -> 2614.4242 | ... Q42: =Q32*Q34+Q37*Q39 -> 3132.8466 | R42: Prediction:
B43: Current Average is: | C43: US = | E43: =Segments!G6/Segments!G13 -> 0.88602754 | F43: =Segments!H6/Segments!H13 -> 0.87545345 | G43: =Segments!D6 -> 0.84775391 | H43: =H34*H32 -> 1109.6251 | I43: =I34*I32 -> 1227.9056 | J43: =J34*J32 -> 1345.3583 | K43: =K34*K32 -> 1463.136 | L43: =L34*L32 -> 1582.2774 | M43: =M34*M32 -> 1703.7283 | N43: =N34*N32 -> 1828.3593 | O43: =O34*O32 -> 1956.982 | ... Q43: =Q34*Q32 -> 2284.6849 | R43: =Q43/Q42 -> 0.72926804
C44: Rest of the World = | E44: =1-E43 -> 0.11397246 | F44: =1-F43 -> 0.12454655 | G44: =1-G43 -> 0.15224609 | H44: =H39*H37 -> 199.27491 | I44: =I39*I37 -> 268.5417 | J44: =J39*J37 -> 338.09757 | K44: =K39*K37 -> 404.60929 | L44: =L39*L37 -> 469.01221 | M44: =M39*M37 -> 532.13605 | N44: =N39*N37 -> 594.7228 | O44: =O39*O37 -> 657.44223 | ... Q44: =Q39*Q37 -> 848.16168 | R44: =Q44/Q42 -> 0.27073196
B45: In millions of USD
A46: x | B46: Income Statement | E46: 2022 | F46: =+E46+1 -> 2023 | G46: =+F46+1 -> 2024 | H46: =+G46+1 -> 2025 | I46: =+H46+1 -> 2026 | J46: =+I46+1 -> 2027 | K46: =+J46+1 -> 2028 | L46: =+K46+1 -> 2029 | M46: =+L46+1 -> 2030 | ... Q46: =+P46+1 -> 2034
B48: Revenue (Sales) | D48: =+_xlfn.XLOOKUP($B48,Inputs!$B:$B,Inputs!N:N) -> 318.1 | E48: =+_xlfn.XLOOKUP($B48,Inputs!$B:$B,Inputs!O:O) -> 392.2 | F48: =+_xlfn.XLOOKUP($B48,Inputs!$B:$B,Inputs!P:P) -> 578.8 | G48: =+_xlfn.XLOOKUP($B48,Inputs!$B:$B,Inputs!Q:Q) -> 1023.9 | H48: 1308.9 | I48: =I42 -> 1496.4472 | J48: =J42 -> 1683.4559 | K48: =K42 -> 1867.7453 | L48: =L42 -> 2051.2897 | M48: =M42 -> 2235.8643 | N48: =N42 -> 2423.0821 | O48: =O42 -> 2614.4242 | P48: =P42 -> 2808.9019 | Q48: =+Q43+Q44 -> 3132.8466
B49: % of growth | E49: =IFERROR((E48-D48)/D48,"") -> 0.23294561 | F49: =IFERROR((F48-E48)/E48,"") -> 0.47577766 | G49: =IFERROR((G48-F48)/F48,"") -> 0.76900484 | H49: =IFERROR(H48/G48-1,"") -> 0.27834749 | I49: =IFERROR(I48/H48-1,"") -> 0.14328615 | J49: =IFERROR(J48/I48-1,"") -> 0.1249684 | K49: =IFERROR(K48/J48-1,"") -> 0.10947091 | L49: =IFERROR(L48/K48-1,"") -> 0.09827054 | M49: =IFERROR(M48/L48-1,"") -> 0.089979818 | N49: =IFERROR(N48/M48-1,"") -> 0.083733971 | O49: =IFERROR(O48/N48-1,"") -> 0.078966395 | ... Q49: =IFERROR(Q48/P48-1,"") -> 0.11532788
B51: COGS (Cost of Goods Sold) | E51: =+_xlfn.XLOOKUP($B51,Inputs!$B:$B,Inputs!O:O) -> 140.4 | F51: =+_xlfn.XLOOKUP($B51,Inputs!$B:$B,Inputs!P:P) -> 188.4 | G51: =+_xlfn.XLOOKUP($B51,Inputs!$B:$B,Inputs!Q:Q) -> 299.8 | H51: =H52*H$48 -> 458.115 | I51: =I52*I$48 -> 486.34536 | J51: =J52*J$48 -> 526.07996 | K51: =K52*K$48 -> 571.997 | L51: =L52*L$48 -> 621.79718 | M51: =M52*M$48 -> 674.25283 | N51: =N52*N$48 -> 728.81767 | O51: =O52*O$48 -> 785.34851 | ... Q51: =Q52*Q$48 -> 939.85397
B52: % of revenue | E52: =IFERROR(E51/E$48,"") -> 0.35798062 | F52: =IFERROR(F51/F$48,"") -> 0.32550104 | G52: =IFERROR(G51/G$48,"") -> 0.29280203 | H52: 0.35 | I52: =(H52+($Q$52-H52)/2) -> 0.325 | J52: =(I52+($Q$52-I52)/2) -> 0.3125 | K52: =(J52+($Q$52-J52)/2) -> 0.30625 | L52: =(K52+($Q$52-K52)/2) -> 0.303125 | M52: =(L52+($Q$52-L52)/2) -> 0.3015625 | N52: =(M52+($Q$52-M52)/2) -> 0.30078125 | O52: =(N52+($Q$52-N52)/2) -> 0.30039063 | P52: =(O52+($Q$52-O52)/2) -> 0.30019531 | Q52: 0.3
B54: Gross Profit | E54: =+_xlfn.XLOOKUP($B54,Inputs!$B:$B,Inputs!O:O) -> 251.8 | F54: =+_xlfn.XLOOKUP($B54,Inputs!$B:$B,Inputs!P:P) -> 390.4 | G54: =+_xlfn.XLOOKUP($B54,Inputs!$B:$B,Inputs!Q:Q) -> 724.1 | H54: =+H48-H51 -> 850.785 | I54: =+I48-I51 -> 1010.1019 | J54: =+J48-J51 -> 1157.3759 | K54: =+K48-K51 -> 1295.7483 | L54: =+L48-L51 -> 1429.4925 | M54: =+M48-M51 -> 1561.6115 | N54: =+N48-N51 -> 1694.2645 | O54: =+O48-O51 -> 1829.0757 | ... Q54: =+Q48-Q51 -> 2192.9926
B55: Gross Profit Margin | E55: =IFERROR(E54/E$48,"") -> 0.64201938 | F55: =IFERROR(F54/F$48,"") -> 0.67449896 | G55: =IFERROR(G54/G$48,"") -> 0.70719797 | H55: =IFERROR(H54/H$48,"") -> 0.65 | I55: =IFERROR(I54/I$48,"") -> 0.675 | J55: =IFERROR(J54/J$48,"") -> 0.6875 | K55: =IFERROR(K54/K$48,"") -> 0.69375 | L55: =IFERROR(L54/L$48,"") -> 0.696875 | ... Q55: =IFERROR(Q54/Q$48,"") -> 0.7
B57: SG&A (Selling, General & Administrative) | E57: =+_xlfn.XLOOKUP($B57,Inputs!$B:$B,Inputs!O:O) -> 221.9 | F57: =+_xlfn.XLOOKUP($B57,Inputs!$B:$B,Inputs!P:P) -> 322.3 | G57: =+_xlfn.XLOOKUP($B57,Inputs!$B:$B,Inputs!Q:Q) -> 574.4 | H57: =IFERROR(G57*(1+H49),"") -> 734.2828 | I57: =IFERROR(H57*(1+I49),"") -> 839.49536 | J57: =IFERROR(I57*(1+J49),"") -> 944.40575 | K57: =IFERROR(J57*(1+K49),"") -> 1047.7907 | L57: =IFERROR(K57*(1+L49),"") -> 1150.7577 | M57: =IFERROR(L57*(1+M49),"") -> 1254.3026 | N57: =IFERROR(M57*(1+N49),"") -> 1359.3304 | O57: =IFERROR(N57*(1+O49),"") -> 1466.6718 | ... Q57: =IFERROR(P57*(1+Q49),"") -> 1757.5027
B58: SG&A Margin | E58: =IFERROR(E57/E$48,"") -> 0.56578276 | F58: =IFERROR(F57/F$48,"") -> 0.55684174 | G58: =IFERROR(G57/G$48,"") -> 0.56099228 | H58: =IFERROR(AVERAGE(E58:G58),"") -> 0.5612056 | I58: =IFERROR(AVERAGE(F58:H58),"") -> 0.55967987 | J58: =IFERROR(AVERAGE(G58:I58),"") -> 0.56062592 | K58: =IFERROR(AVERAGE(H58:J58),"") -> 0.5605038 | L58: =IFERROR(AVERAGE(I58:K58),"") -> 0.56026986 | M58: =IFERROR(AVERAGE(J58:L58),"") -> 0.56046653 | N58: =IFERROR(AVERAGE(K58:M58),"") -> 0.5604134 | O58: =IFERROR(AVERAGE(L58:N58),"") -> 0.56038326 | ... Q58: =IFERROR(AVERAGE(N58:P58),"") -> 0.56040591
B60: R&D (Research & Development) | E60: =+_xlfn.XLOOKUP($B60,Inputs!$B:$B,Inputs!O:O) -> 0 | F60: =+_xlfn.XLOOKUP($B60,Inputs!$B:$B,Inputs!P:P) -> 0 | G60: =+_xlfn.XLOOKUP($B60,Inputs!$B:$B,Inputs!Q:Q) -> 0 | H60: =H61*H$48 -> 0 | I60: =I61*I$48 -> 0 | J60: =J61*J$48 -> 0 | K60: =K61*K$48 -> 0 | L60: =L61*L$48 -> 0 | M60: =M61*M$48 -> 0 | N60: =N61*N$48 -> 0 | O60: =O61*O$48 -> 0 | ... Q60: =Q61*Q$48 -> 0
B61: % of revenue | E61: =IFERROR(E60/E48,"") -> 0 | F61: =IFERROR(F60/F48,"") -> 0 | G61: =IFERROR(G60/G48,"") -> 0 | H61: 0 | I61: 0 | J61: 0 | K61: 0 | L61: 0 | M61: 0 | N61: 0 | O61: 0 | P61: 0 | Q61: 0
B63: Other Operating (Income) Expenses | E63: =+_xlfn.XLOOKUP($B63,Inputs!$B:$B,Inputs!O:O) -> 0.5 | F63: =+_xlfn.XLOOKUP($B63,Inputs!$B:$B,Inputs!P:P) -> 0 | G63: =+_xlfn.XLOOKUP($B63,Inputs!$B:$B,Inputs!Q:Q) -> 0 | H63: =IFERROR(AVERAGE(E63:G63)*(1+H49),"") -> 0.21305792 | I63: =IFERROR(AVERAGE(F63:H63)*(1+I49),"") -> 0.081195388 | J63: =IFERROR(AVERAGE(G63:I63)*(1+J49),"") -> 0.11034189 | K63: =IFERROR(AVERAGE(H63:J63)*(1+K49),"") -> 0.14962887 | L63: =IFERROR(AVERAGE(I63:K63)*(1+L49),"") -> 0.12489758 | M63: =IFERROR(AVERAGE(J63:L63)*(1+M49),"") -> 0.1398329 | N63: =IFERROR(AVERAGE(K63:M63)*(1+N49),"") -> 0.1496851 | O63: =IFERROR(AVERAGE(L63:N63)*(1+O49),"") -> 0.14904683 | ... Q63: =IFERROR(AVERAGE(N63:P63)*(1+Q49),"") -> 0.16945349
B65: EBITDA | E65: =+_xlfn.XLOOKUP($B65,Inputs!$B:$B,Inputs!O:O) -> 29.4 | F65: =+_xlfn.XLOOKUP($B65,Inputs!$B:$B,Inputs!P:P) -> 68.1 | G65: =+_xlfn.XLOOKUP($B65,Inputs!$B:$B,Inputs!Q:Q) -> 149.7 | H65: =IFERROR(H54-H57-H60-H63,"") -> 116.28914 | I65: =IFERROR(I54-I57-I60-I63,"") -> 170.52534 | J65: =IFERROR(J54-J57-J60-J63,"") -> 212.85981 | K65: =IFERROR(K54-K57-K60-K63,"") -> 247.80797 | L65: =IFERROR(L54-L57-L60-L63,"") -> 278.60991 | M65: =IFERROR(M54-M57-M60-M63,"") -> 307.16902 | N65: =IFERROR(N54-N57-N60-N63,"") -> 334.78439 | O65: =IFERROR(O54-O57-O60-O63,"") -> 362.25483 | ... Q65: =IFERROR(Q54-Q57-Q60-Q63,"") -> 435.32039
B66: EBITDA Margin | E66: =IFERROR(E65/E$48,"") -> 0.074961754 | F66: =IFERROR(F65/F$48,"") -> 0.11765722 | G66: =IFERROR(G65/G$48,"") -> 0.14620568 | H66: =IFERROR(H65/H$48,"") -> 0.088844939 | I66: =IFERROR(I65/I$48,"") -> 0.11395346 | J66: =IFERROR(J65/J$48,"") -> 0.12644217 | K66: =IFERROR(K65/K$48,"") -> 0.1326776 | L66: =IFERROR(L65/L$48,"") -> 0.13582183 | ... Q66: =IFERROR(Q65/Q$48,"") -> 0.13895363
B68: D&A (Depreciation & Amortization) | E68: =+_xlfn.XLOOKUP($B68,Inputs!$B:$B,Inputs!O:O) -> 27.1 | F68: =+_xlfn.XLOOKUP($B68,Inputs!$B:$B,Inputs!P:P) -> 22.2 | G68: =+_xlfn.XLOOKUP($B68,Inputs!$B:$B,Inputs!Q:Q) -> 35.9 | H68: =H69*(H117+H123) -> 37.284732 | I68: =I69*(I117+I123) -> 38.129056 | J68: =J69*(J117+J123) -> 39.336933 | K68: =K69*(K117+K123) -> 40.74971 | L68: =L69*(L117+L123) -> 42.10108 | M68: =M69*(M117+M123) -> 71.817938 | N68: =N69*(N117+N123) -> 73.494069 | O68: =O69*(O117+O123) -> 75.224393 | ... Q68: =Q69*(Q117+Q123) -> 78.207964
B69: % of PP&E+ROU Assets+Intangibles excl. Goodwill | E69: =IFERROR(E68/AVERAGE(Inputs!O39+Inputs!O42+Inputs!O44,Inputs!N39+Inputs!N42+Inputs!N44),"") -> 0.12966879 | F69: =IFERROR(F68/AVERAGE(Inputs!P39+Inputs!P42+Inputs!P44,Inputs!O39+Inputs!O42+Inputs!O44),"") -> 0.11057071 | G69: =IFERROR(G68/AVERAGE(Inputs!Q39+Inputs!Q42+Inputs!Q44,Inputs!P39+Inputs!P42+Inputs!P44),"") -> 0.12301682 | H69: 0.13 | I69: =H69+($Q$69-H69)/5 -> 0.128 | J69: =I69+($Q$69-I69)/5 -> 0.1264 | K69: =J69+($Q$69-J69)/5 -> 0.12512 | L69: =K69+($Q$69-K69)/5 -> 0.124096 | M69: =L69+($Q$69-L69)/5 -> 0.1232768 | N69: =M69+($Q$69-M69)/5 -> 0.12262144 | O69: =N69+($Q$69-N69)/5 -> 0.12209715 | P69: =O69+($Q$69-O69)/5 -> 0.12167772 | Q69: 0.12
B71: Depreciation Expense | E71: =+_xlfn.XLOOKUP($B71,Inputs!$B:$B,Inputs!O:O) -> 0 | F71: =+_xlfn.XLOOKUP($B71,Inputs!$B:$B,Inputs!P:P) -> 0 | G71: =+_xlfn.XLOOKUP($B71,Inputs!$B:$B,Inputs!Q:Q) -> 0 | H71: =IFERROR(H72*(G118+G119),"") -> 0 | I71: =IFERROR(I72*(H118+H119),"") -> 0 | J71: =IFERROR(J72*(I118+I119),"") -> 0 | K71: =IFERROR(K72*(J118+J119),"") -> 0 | L71: =IFERROR(L72*(K118+K119),"") -> 0 | M71: =IFERROR(M72*(L118+L119),"") -> 0 | N71: =IFERROR(N72*(M118+M119),"") -> 0 | O71: =IFERROR(O72*(N118+N119),"") -> 0 | ... Q71: =IFERROR(Q72*(P118+P119),"") -> 0
B72: % of PP&E+ROU Assets | E72: =IFERROR(E71/AVERAGE(Inputs!O40+Inputs!O42,Inputs!N40+Inputs!N42),"") -> 0 | F72: =IFERROR(F71/AVERAGE(Inputs!P40+Inputs!P42,Inputs!O40+Inputs!O42),"") -> 0 | G72: =IFERROR(G71/AVERAGE(Inputs!Q40+Inputs!Q42,Inputs!P40+Inputs!P42),"") -> 0 | H72: =IFERROR(AVERAGE(E72:G72),"") -> 0 | I72: =IFERROR(AVERAGE(F72:H72),"") -> 0 | J72: =IFERROR(AVERAGE(G72:I72),"") -> 0 | K72: =IFERROR(AVERAGE(H72:J72),"") -> 0 | L72: =IFERROR(AVERAGE(I72:K72),"") -> 0 | M72: =IFERROR(AVERAGE(J72:L72),"") -> 0 | N72: =IFERROR(AVERAGE(K72:M72),"") -> 0 | O72: =IFERROR(AVERAGE(L72:N72),"") -> 0 | ... Q72: =IFERROR(AVERAGE(N72:P72),"") -> 0
B74: Amortization Expense | E74: =+_xlfn.XLOOKUP($B74,Inputs!$B:$B,Inputs!O:O) -> 0 | F74: =+_xlfn.XLOOKUP($B74,Inputs!$B:$B,Inputs!P:P) -> 0 | G74: =+_xlfn.XLOOKUP($B74,Inputs!$B:$B,Inputs!Q:Q) -> 0 | H74: =+H75*G123 -> 0 | I74: =+I75*H123 -> 0 | J74: =+J75*I123 -> 0 | K74: =+K75*J123 -> 0 | L74: =+L75*K123 -> 0 | M74: =+M75*L123 -> 0 | N74: =+N75*M123 -> 0 | O74: =+O75*N123 -> 0 | ... Q74: =+Q75*P123 -> 0
B75: % of Intangibles excl. Goodwill | E75: =IFERROR(E74/AVERAGE(Inputs!N45:O45),"") -> 0 | F75: =IFERROR(F74/AVERAGE(Inputs!O45:P45),"") -> 0 | G75: =IFERROR(G74/AVERAGE(Inputs!P45:Q45),"") -> 0 | H75: 0 | I75: 0 | J75: 0 | K75: 0 | L75: 0 | M75: 0 | N75: 0 | O75: 0 | P75: 0 | Q75: 0
B77: Operating Income (EBIT) | E77: =+_xlfn.XLOOKUP($B77,Inputs!$B:$B,Inputs!O:O) -> 2.3 | F77: =+_xlfn.XLOOKUP($B77,Inputs!$B:$B,Inputs!P:P) -> 45.9 | G77: =+_xlfn.XLOOKUP($B77,Inputs!$B:$B,Inputs!Q:Q) -> 113.8 | H77: =+IFERROR(H65-H68,"") -> 79.004409 | I77: =+IFERROR(I65-I68,"") -> 132.39628 | J77: =+IFERROR(J65-J68,"") -> 173.52288 | K77: =+IFERROR(K65-K68,"") -> 207.05826 | L77: =+IFERROR(L65-L68,"") -> 236.50883 | M77: =+IFERROR(M65-M68,"") -> 235.35108 | N77: =+IFERROR(N65-N68,"") -> 261.29032 | O77: =+IFERROR(O65-O68,"") -> 287.03043 | ... Q77: =+IFERROR(Q65-Q68,"") -> 357.11243
B78: Operating Margin | E78: =IFERROR(E77/E$48,"") -> 0.0058643549 | F78: =IFERROR(F77/F$48,"") -> 0.079302004 | G78: =IFERROR(G77/G$48,"") -> 0.11114367 | H78: =IFERROR(H77/H48,"") -> 0.060359393 | I78: =IFERROR(I77/I48,"") -> 0.088473737 | J78: =IFERROR(J77/J48,"") -> 0.1030754 | K78: =IFERROR(K77/K48,"") -> 0.11086001 | L78: =IFERROR(L77/L48,"") -> 0.11529763 | M78: =IFERROR(M77/M48,"") -> 0.10526179 | N78: =IFERROR(N77/N48,"") -> 0.10783387 | O78: =IFERROR(O77/O48,"") -> 0.10978725 | ... Q78: =IFERROR(Q77/Q48,"") -> 0.11398976
B80: Net Interest Expense (Income) | E80: =+_xlfn.XLOOKUP($B80,Inputs!$B:$B,Inputs!O:O) -> 2.4 | F80: =+_xlfn.XLOOKUP($B80,Inputs!$B:$B,Inputs!P:P) -> 2 | G80: =+_xlfn.XLOOKUP($B80,Inputs!$B:$B,Inputs!Q:Q) -> 7 | H80: =H83-H86 -> 7.364 | I80: =I83-I86 -> 7.8141237 | J80: =J83-J86 -> 5.2884556 | K80: =K83-K86 -> 3.1193704 | L80: =L83-L86 -> 1.2987355 | M80: =M83-M86 -> 0.80593546 | N80: =N83-N86 -> 0.76121303 | O80: =O83-O86 -> 0.72543509 | ... Q80: =Q83-Q86 -> 0.58232331
B81: % of Net Debt | E81: =IFERROR(E80/AVERAGE(Inputs!N115:O115),"") -> 0.032967033 | F81: =IFERROR(F80/AVERAGE(Inputs!O115:P115),"") -> 0.16949153 | G81: =IFERROR(G80/AVERAGE(Inputs!P115:Q115),"") -> 0.37037037 | H81: =IFERROR(H80/AVERAGE(G134+G136,H134+H136),"") -> 0.038151485 | I81: =IFERROR(I80/AVERAGE(H134+H136,I134+I136),"") -> 0.038594548 | J81: =IFERROR(J80/AVERAGE(I134+I136,J134+J136),"") -> 0.028058136 | K81: =IFERROR(K80/AVERAGE(J134+J136,K134+K136),"") -> 0.020255439 | L81: =IFERROR(L80/AVERAGE(K134+K136,L134+L136),"") -> 0.010770128 | M81: =IFERROR(M80/AVERAGE(L134+L136,M134+M136),"") -> 0.0081900038 | N81: =IFERROR(N80/AVERAGE(M134+M136,N134+N136),"") -> 0.0076803659 | O81: =IFERROR(O80/AVERAGE(N134+N136,O134+O136),"") -> 0.0068976973 | ... Q81: =IFERROR(Q80/AVERAGE(P134+P136,Q134+Q136),"") -> 0.0048588569
B83: Interest Expense | E83: =+_xlfn.XLOOKUP($B83,Inputs!$B:$B,Inputs!O:O) -> 2.4 | F83: =+_xlfn.XLOOKUP($B83,Inputs!$B:$B,Inputs!P:P) -> 2 | G83: =+_xlfn.XLOOKUP($B83,Inputs!$B:$B,Inputs!Q:Q) -> 7 | H83: =H134*H84 -> 7.364 | I83: =I134*I84 -> 7.8141237 | J83: =J134*J84 -> 5.2884556 | K83: =K134*K84 -> 3.1193704 | L83: =L134*L84 -> 1.2987355 | M83: =M134*M84 -> 0.80593546 | N83: =N134*N84 -> 0.76121303 | O83: =O134*O84 -> 0.72543509 | ... Q83: =Q134*Q84 -> 0.58232331
B84: % of Debt | E84: =+IFERROR(E83/AVERAGE(Inputs!N112:O112),"") -> 0.019448947 | F84: =+IFERROR(F83/AVERAGE(Inputs!O112:P112),"") -> 0.021299255 | G84: =+IFERROR(G83/AVERAGE(Inputs!P112:Q112),"") -> 0.052473763 | H84: 0.05 | I84: =H84+(K84-H84)/5 -> 0.048 | J84: =I84+(K84-I84)/5 -> 0.0464 | K84: 0.04 | L84: =K84+($Q$84-K84)/5 -> 0.037 | M84: =L84+($Q$84-L84)/5 -> 0.0346 | N84: =M84+($Q$84-M84)/5 -> 0.03268 | O84: =N84+($Q$84-N84)/5 -> 0.031144 | P84: =O84+($Q$84-O84)/5 -> 0.0299152 | Q84: 0.025
B86: Interest Income | E86: =+_xlfn.XLOOKUP($B86,Inputs!$B:$B,Inputs!O:O) -> 0 | F86: =+_xlfn.XLOOKUP($B86,Inputs!$B:$B,Inputs!P:P) -> 0 | G86: =+_xlfn.XLOOKUP($B86,Inputs!$B:$B,Inputs!Q:Q) -> 0 | H86: 0 | I86: 0 | J86: 0 | K86: 0 | L86: 0 | M86: 0 | N86: 0 | O86: 0 | P86: 0 | Q86: 0
B87: % Cash & Cash Eq. & ST Investments | E87: =IFERROR(E86/+AVERAGE(Inputs!N32:O32),"") -> 0 | F87: =IFERROR(F86/+AVERAGE(Inputs!O32:P32),"") -> 0 | G87: =IFERROR(G86/+AVERAGE(Inputs!P32:Q32),"") -> 0 | H87: 0 | I87: 0 | J87: 0 | K87: 0 | L87: 0 | M87: 0 | N87: 0 | O87: 0 | P87: 0 | Q87: 0
B89: FX (Gain) Loss | E89: =+_xlfn.XLOOKUP($B89,Inputs!$B:$B,Inputs!O:O) -> 0 | F89: =+_xlfn.XLOOKUP($B89,Inputs!$B:$B,Inputs!P:P) -> 0 | G89: =+_xlfn.XLOOKUP($B89,Inputs!$B:$B,Inputs!Q:Q) -> 0 | H89: =+H90*H$18 -> 0 | I89: =+I90*I$18 -> 0 | J89: =+J90*J$18 -> 0 | K89: =+K90*K$18 -> 0 | L89: =+L90*L$18 -> 0 | M89: =+M90*M$18 -> 0 | N89: =+N90*N$18 -> 0 | O89: =+O90*O$18 -> 0 | P89: =+P90*P$17 -> 0 | Q89: =+Q90*Q$17 -> 0
B90: % of revenue | H90: 0 | I90: 0 | J90: 0 | K90: 0 | L90: 0 | M90: 0 | N90: 0 | O90: 0 | P90: 0 | Q90: 0
B92: Other Non-Operating (Income) Expenses | E92: =+_xlfn.XLOOKUP($B92,Inputs!$B:$B,Inputs!O:O) -> 1.4 | F92: =+_xlfn.XLOOKUP($B92,Inputs!$B:$B,Inputs!P:P) -> 2.1 | G92: =+_xlfn.XLOOKUP($B92,Inputs!$B:$B,Inputs!Q:Q) -> 1.7 | H92: =IFERROR(AVERAGE(E92:G92)*(1+H49),"") -> 2.2158023 | I92: =IFERROR(AVERAGE(F92:H92)*(1+I49),"") -> 2.2925945 | J92: =IFERROR(AVERAGE(G92:I92)*(1+J49),"") -> 2.3280834 | K92: =IFERROR(AVERAGE(H92:J92)*(1+K49),"") -> 2.528292 | L92: =IFERROR(AVERAGE(I92:K92)*(1+L49),"") -> 2.6171677 | M92: =IFERROR(AVERAGE(J92:L92)*(1+M49),"") -> 2.715337 | N92: =IFERROR(AVERAGE(K92:M92)*(1+N49),"") -> 2.8396708 | O92: =IFERROR(AVERAGE(L92:N92)*(1+O49),"") -> 2.9391676 | ... Q92: =IFERROR(AVERAGE(N92:P92)*(1+Q49),"") -> 3.279379
B94: Pre-Tax Income (EBT) | E94: =+_xlfn.XLOOKUP($B94,Inputs!$B:$B,Inputs!O:O) -> -1.5 | F94: =+_xlfn.XLOOKUP($B94,Inputs!$B:$B,Inputs!P:P) -> 41.8 | G94: =+_xlfn.XLOOKUP($B94,Inputs!$B:$B,Inputs!Q:Q) -> 105.1 | H94: =IFERROR(+H77-H80-H89-H92,"") -> 69.424607 | I94: =IFERROR(+I77-I80-I89-I92,"") -> 122.28956 | J94: =IFERROR(+J77-J80-J89-J92,"") -> 165.90634 | K94: =IFERROR(+K77-K80-K89-K92,"") -> 201.4106 | L94: =IFERROR(+L77-L80-L89-L92,"") -> 232.59293 | M94: =IFERROR(+M77-M80-M89-M92,"") -> 231.82981 | N94: =IFERROR(+N77-N80-N89-N92,"") -> 257.68944 | O94: =IFERROR(+O77-O80-O89-O92,"") -> 283.36583 | ... Q94: =IFERROR(+Q77-Q80-Q89-Q92,"") -> 353.25072
B96: Tax Expense (Benefits) | E96: =+_xlfn.XLOOKUP($B96,Inputs!$B:$B,Inputs!O:O) -> 3.7 | F96: =+_xlfn.XLOOKUP($B96,Inputs!$B:$B,Inputs!P:P) -> 2.5 | G96: =+_xlfn.XLOOKUP($B96,Inputs!$B:$B,Inputs!Q:Q) -> 13.3 | H96: =IFERROR(H97*H$77,"") -> 7.3614238 | I96: =IFERROR(I97*I$77,"") -> 12.804471 | J96: =IFERROR(J97*J$77,"") -> 17.327336 | K96: =IFERROR(K97*K$77,"") -> 21.254522 | L96: =IFERROR(L97*L$77,"") -> 24.864953 | M96: =IFERROR(M97*M$77,"") -> 25.262751 | N96: =IFERROR(N97*N$77,"") -> 28.559777 | O96: =IFERROR(O97*O$77,"") -> 31.873862 | ... Q96: =IFERROR(Q97*Q$77,"") -> 44.639053
B97: % of EBT | E97: =IFERROR(E96/E94,"") -> -2.4666667 | F97: =IFERROR(F96/F94,"") -> 0.059808612 | G97: =IFERROR(G96/G94,"") -> 0.12654615 | H97: =IFERROR(AVERAGE(F97:G97),"") -> 0.093177379 | I97: =H97+($Q$97-H97)/9 -> 0.096713226 | J97: =I97+($Q$97-I97)/9 -> 0.099856201 | K97: =J97+($Q$97-J97)/9 -> 0.10264996 | L97: =K97+($Q$97-K97)/9 -> 0.10513329 | M97: =L97+($Q$97-L97)/9 -> 0.10734071 | N97: =M97+($Q$97-M97)/9 -> 0.10930285 | O97: =N97+($Q$97-N97)/9 -> 0.11104698 | P97: =O97+($Q$97-O97)/9 -> 0.11259731 | Q97: 0.125
B99: Net Income | E99: =+_xlfn.XLOOKUP($B99,Inputs!$B:$B,Inputs!O:O) -> 21.9 | F99: =+_xlfn.XLOOKUP($B99,Inputs!$B:$B,Inputs!P:P) -> 61.5 | G99: =+_xlfn.XLOOKUP($B99,Inputs!$B:$B,Inputs!Q:Q) -> 127.7 | H99: =IFERROR(+H94-H96,"") -> 62.063183 | I99: =IFERROR(+I94-I96,"") -> 109.48509 | J99: =IFERROR(+J94-J96,"") -> 148.57901 | K99: =IFERROR(+K94-K96,"") -> 180.15608 | L99: =IFERROR(+L94-L96,"") -> 207.72798 | M99: =IFERROR(+M94-M96,"") -> 206.56706 | N99: =IFERROR(+N94-N96,"") -> 229.12966 | O99: =IFERROR(+O94-O96,"") -> 251.49197 | ... Q99: =IFERROR(+Q94-Q96,"") -> 308.61167
B100: Net Income Margin | E100: =IFERROR(E99/E$48,"") -> 0.055838858 | F100: =IFERROR(F99/F$48,"") -> 0.10625432 | G100: =IFERROR(G99/G$48,"") -> 0.12471921 | H100: =IFERROR(H99/H$48,"") -> 0.047416291 | I100: =IFERROR(I99/I$48,"") -> 0.073163348 | J100: =IFERROR(J99/J$48,"") -> 0.088258332 | K100: =IFERROR(K99/K$48,"") -> 0.096456448 | L100: =IFERROR(L99/L$48,"") -> 0.10126701 | ... Q100: =IFERROR(Q99/Q$48,"") -> 0.09850839
A102: x | B102: Balance Sheet | E102: =E46 -> 2022 | F102: =F46 -> 2023 | G102: =G46 -> 2024 | H102: =H46 -> 2025 | I102: =I46 -> 2026 | J102: =J46 -> 2027 | K102: =K46 -> 2028 | L102: =L46 -> 2029 | ... Q102: =Q46 -> 2034
B104: Assets
B106: Cash & Cash Equivalents & ST Investments | E106: =+_xlfn.XLOOKUP($B106,Inputs!$B:$B,Inputs!O:O) -> 43.4 | F106: =+_xlfn.XLOOKUP($B106,Inputs!$B:$B,Inputs!P:P) -> 120.8 | G106: =+_xlfn.XLOOKUP($B106,Inputs!$B:$B,Inputs!Q:Q) -> 108.2 | H106: =IFERROR(G106+H183,"") -> 79.24824 | I106: =IFERROR(H106+I183,"") -> 251.41274 | J106: =IFERROR(I106+J183,"") -> 441.7623 | K106: =IFERROR(J106+K183,"") -> 627.09341 | L106: =IFERROR(K106+L183,"") -> 859.59783 | M106: =IFERROR(L106+M183,"") -> 788.80745 | N106: =IFERROR(M106+N183,"") -> 1025.8686 | O106: =IFERROR(N106+O183,"") -> 1286.5222 | ... Q106: =IFERROR(P106+Q183,"") -> 1855.4445
B108: Accounts Receivable | E108: =+_xlfn.XLOOKUP($B108,Inputs!$B:$B,Inputs!O:O) -> 45.6 | F108: =+_xlfn.XLOOKUP($B108,Inputs!$B:$B,Inputs!P:P) -> 67.9 | G108: =+_xlfn.XLOOKUP($B108,Inputs!$B:$B,Inputs!Q:Q) -> 123.8 | H108: =IFERROR(H109*H48/365,"") -> 154.80814 | I108: =IFERROR(I109*I48/365,"") -> 177.99075 | J108: =IFERROR(J109*J48/365,"") -> 201.14895 | K108: =IFERROR(K109*K48/365,"") -> 222.0758 | L108: =IFERROR(L109*L48/365,"") -> 244.32803 | M108: =IFERROR(M109*M48/365,"") -> 266.43727 | N108: =IFERROR(N109*N48/365,"") -> 288.48825 | O108: =IFERROR(O109*O48/365,"") -> 311.40675 | ... Q108: =IFERROR(Q109*Q48/365,"") -> 373.10215
B109: DSO | E109: =IFERROR(E108/E48*365,"") -> 42.437532 | F109: =IFERROR(F108/F48*365,"") -> 42.818763 | G109: =IFERROR(G108/G48*366,"") -> 44.25315 | H109: =IFERROR(AVERAGE(E109:G109),"") -> 43.169815 | I109: =IFERROR(AVERAGE(F109:H109),"") -> 43.413909 | J109: =IFERROR(AVERAGE(G109:I109),"") -> 43.612291 | K109: =IFERROR(AVERAGE(H109:J109),"") -> 43.398672 | L109: =IFERROR(AVERAGE(I109:K109),"") -> 43.474957 | M109: =IFERROR(AVERAGE(J109:L109),"") -> 43.495307 | N109: =IFERROR(AVERAGE(K109:M109),"") -> 43.456312 | O109: =IFERROR(AVERAGE(L109:N109),"") -> 43.475525 | ... Q109: =IFERROR(AVERAGE(N109:P109),"") -> 43.469184
B111: Inventory | E111: =+_xlfn.XLOOKUP($B111,Inputs!$B:$B,Inputs!O:O) -> 84.5 | F111: =+_xlfn.XLOOKUP($B111,Inputs!$B:$B,Inputs!P:P) -> 81.3 | G111: =+_xlfn.XLOOKUP($B111,Inputs!$B:$B,Inputs!Q:Q) -> 191.5 | H111: =+IFERROR(H112*H51/365,"") -> 255.34409 | I111: =+IFERROR(I112*I51/365,"") -> 263.86955 | J111: =+IFERROR(J112*J51/365,"") -> 304.89753 | K111: =+IFERROR(K112*K51/365,"") -> 320.22314 | L111: =+IFERROR(L112*L51/365,"") -> 348.61152 | M111: =+IFERROR(M112*M51/365,"") -> 382.08786 | N111: =+IFERROR(N112*N51/365,"") -> 409.8794 | O111: =+IFERROR(O112*O51/365,"") -> 442.34084 | ... Q111: =+IFERROR(Q112*Q51/365,"") -> 529.36827
B112: DIH | E112: =IFERROR(E111/E51*365,"") -> 219.67593 | F112: =IFERROR(F111/F51*365,"") -> 157.50796 | G112: =IFERROR(G111/G51*365,"") -> 233.1471 | H112: =IFERROR(AVERAGE(E112:G112),"") -> 203.44366 | I112: =IFERROR(AVERAGE(F112:H112),"") -> 198.03291 | J112: =IFERROR(AVERAGE(G112:I112),"") -> 211.54122 | K112: =IFERROR(AVERAGE(H112:J112),"") -> 204.33926 | L112: =IFERROR(AVERAGE(I112:K112),"") -> 204.6378 | M112: =IFERROR(AVERAGE(J112:L112),"") -> 206.83943 | N112: =IFERROR(AVERAGE(K112:M112),"") -> 205.27216 | O112: =IFERROR(AVERAGE(L112:N112),"") -> 205.58313 | ... Q112: =IFERROR(AVERAGE(N112:P112),"") -> 205.58451
B114: Prepaid expenses and Other Current Assets | E114: =+_xlfn.XLOOKUP($B114,Inputs!$B:$B,Inputs!O:O) -> 19.5 | F114: =+_xlfn.XLOOKUP($B114,Inputs!$B:$B,Inputs!P:P) -> 33.3 | G114: =+_xlfn.XLOOKUP($B114,Inputs!$B:$B,Inputs!Q:Q) -> 53.6 | H114: =IFERROR(AVERAGE(E114:G114)*(1+H49),"") -> 45.338724 | I114: =IFERROR(AVERAGE(F114:H114)*(1+I49),"") -> 50.395568 | J114: =IFERROR(AVERAGE(G114:I114)*(1+J49),"") -> 55.998787 | K114: =IFERROR(AVERAGE(H114:J114)*(1+K49),"") -> 56.114479 | L114: =IFERROR(AVERAGE(I114:K114)*(1+L49),"") -> 59.492888 | M114: =IFERROR(AVERAGE(J114:L114)*(1+M49),"") -> 62.349081 | N114: =IFERROR(AVERAGE(K114:M114)*(1+N49),"") -> 64.285816 | O114: =IFERROR(AVERAGE(L114:N114)*(1+O49),"") -> 66.941875 | ... Q114: =IFERROR(AVERAGE(N114:P114)*(1+Q49),"") -> 74.560825
B115: % of revenue | E115: =IFERROR(E114/E$48,"") -> 0.049719531 | F115: =IFERROR(F114/F$48,"") -> 0.057532827 | G115: =IFERROR(G114/G$48,"") -> 0.052348862 | H115: =IFERROR(AVERAGE(E115:G115),"") -> 0.053200407 | I115: =IFERROR(AVERAGE(F115:H115),"") -> 0.054360698 | J115: =IFERROR(AVERAGE(G115:I115),"") -> 0.053303322 | K115: =IFERROR(AVERAGE(H115:J115),"") -> 0.053621476 | L115: =IFERROR(AVERAGE(I115:K115),"") -> 0.053761832 | M115: =IFERROR(AVERAGE(J115:L115),"") -> 0.05356221 | N115: =IFERROR(AVERAGE(K115:M115),"") -> 0.053648506 | O115: =IFERROR(AVERAGE(L115:N115),"") -> 0.053657516 | ... Q115: =IFERROR(AVERAGE(N115:P115),"") -> 0.053642922
B117: Net PP&E (Property, Plant and Equipment) + ROU Assets | E117: =+E118+E119-E121 -> 33.094 | F117: =+F118+F119-F121 -> 25.259 | G117: =+G118+G119-G121 -> 46.201 | H117: =IFERROR(H118+H119-H121,"") -> 59.454628 | I117: =IFERROR(I118+I119-I121,"") -> 68.25874 | J117: =IFERROR(J118+J119-J121,"") -> 79.289158 | K117: =IFERROR(K118+K119-K121,"") -> 91.445056 | L117: =IFERROR(L118+L119-L121,"") -> 102.67982 | M117: =IFERROR(M118+M119-M121,"") -> 145.99228 | N117: =IFERROR(N118+N119-N121,"") -> 158.40923 | O117: =IFERROR(O118+O119-O121,"") -> 170.7451 | ... Q117: =IFERROR(Q118+Q119-Q121,"") -> 197.42368
B118: Gross PP&E (Property, Plant and Equipment) + ROU Assets | E118: =+_xlfn.XLOOKUP("Gross PP&E (Property, Plant and Equipment)",Inputs!$B:$B,Inputs!O:O) -> 53.3 | F118: =+_xlfn.XLOOKUP("Gross PP&E (Property, Plant and Equipment)",Inputs!$B:$B,Inputs!P:P) -> 45.9 | G118: =+_xlfn.XLOOKUP("Gross PP&E (Property, Plant and Equipment)",Inputs!$B:$B,Inputs!Q:Q) -> 66.3 | H118: =+IFERROR(G118-H152,"") -> 75 | I118: =+IFERROR(H118-I152,"") -> 84.36 | J118: =+IFERROR(I118-J152,"") -> 94.248 | K118: =+IFERROR(J118-K152,"") -> 104.5584 | L118: =+IFERROR(K118-L152,"") -> 115.20672 | M118: =+IFERROR(L118-M152-M163*1/10,"") -> 157.29248 | N118: =+IFERROR(M118-N152,"") -> 168.42741 | O118: =+IFERROR(N118-O152,"") -> 179.73535 | P118: =+IFERROR(O118-P152,"") -> 191.1817 | Q118: =+IFERROR(P118-Q152,"") -> 203.1817
B119: Right-of-Use Assets | E119: =+_xlfn.XLOOKUP("Right-of-Use Assets",Inputs!$B:$B,Inputs!O:O) -> 4.294 | F119: =+_xlfn.XLOOKUP("Right-of-Use Assets",Inputs!$B:$B,Inputs!P:P) -> 3.359 | G119: =+_xlfn.XLOOKUP("Right-of-Use Assets",Inputs!$B:$B,Inputs!Q:Q) -> 4.801 | H119: =IFERROR(H120*H$48,"") -> 9.3546282 | I119: =IFERROR(I120*I$48,"") -> 8.7987405 | J119: =IFERROR(J120*J$48,"") -> 9.9411584 | K119: =IFERROR(K120*K$48,"") -> 11.786656 | L119: =IFERROR(L120*L$48,"") -> 12.373103 | M119: =IFERROR(M120*M$48,"") -> 13.5998 | N119: =IFERROR(N120*N$48,"") -> 14.881818 | O119: =IFERROR(O120*O$48,"") -> 15.90975 | ... Q119: =IFERROR(Q120*Q$48,"") -> 19.14198
B120: % of revenue | E120: =IFERROR(E119/E$48,"") -> 0.010948496 | F120: =IFERROR(F119/F$48,"") -> 0.0058033863 | G120: =IFERROR(G119/G$48,"") -> 0.0046889345 | H120: =IFERROR(AVERAGE(E120:G120),"") -> 0.0071469388 | I120: =IFERROR(AVERAGE(F120:H120),"") -> 0.0058797532 | J120: =IFERROR(AVERAGE(G120:I120),"") -> 0.0059052088 | K120: =IFERROR(AVERAGE(H120:J120),"") -> 0.0063106336 | L120: =IFERROR(AVERAGE(I120:K120),"") -> 0.0060318652 | M120: =IFERROR(AVERAGE(J120:L120),"") -> 0.0060825692 | N120: =IFERROR(AVERAGE(K120:M120),"") -> 0.0061416893 | O120: =IFERROR(AVERAGE(L120:N120),"") -> 0.0060853746 | ... Q120: =IFERROR(AVERAGE(N120:P120),"") -> 0.0061100917
B121: Accumulated Depreciation | E121: =+_xlfn.XLOOKUP($B121,Inputs!$B:$B,Inputs!O:O) -> 24.5 | F121: =+_xlfn.XLOOKUP($B121,Inputs!$B:$B,Inputs!P:P) -> 24 | G121: =+_xlfn.XLOOKUP($B121,Inputs!$B:$B,Inputs!Q:Q) -> 24.9 | H121: =+IFERROR(G121+H71,"") -> 24.9 | I121: =+IFERROR(H121+I71,"") -> 24.9 | J121: =+IFERROR(I121+J71,"") -> 24.9 | K121: =+IFERROR(J121+K71,"") -> 24.9 | L121: =+IFERROR(K121+L71,"") -> 24.9 | M121: =+IFERROR(L121+M71,"") -> 24.9 | N121: =+IFERROR(M121+N71,"") -> 24.9 | O121: =+IFERROR(N121+O71,"") -> 24.9 | ... Q121: =+IFERROR(P121+Q71,"") -> 24.9
B123: Intangibles excl. Goodwill | E123: =+_xlfn.XLOOKUP($B123,Inputs!$B:$B,Inputs!O:O) -> 86.2 | F123: =+_xlfn.XLOOKUP($B123,Inputs!$B:$B,Inputs!P:P) -> 78.1 | G123: =+_xlfn.XLOOKUP($B123,Inputs!$B:$B,Inputs!Q:Q) -> 225.1 | H123: =IF(H159=0, +G123+H124*G123, G123-H159*2/3) -> 227.351 | I123: =IF(I159=0, +H123+I124*H123, H123-I159*2/3) -> 229.62451 | J123: =IF(J159=0, +I123+J124*I123, I123-J159*2/3) -> 231.92076 | K123: =IF(K159=0, +J123+K124*J123, J123-K159*2/3) -> 234.23996 | L123: =IF(L159=0, +K123+L124*K123, K123-L159*2/3) -> 236.58236 | M123: =IF(M159=0, +L123+M124*L123, L123-M159*2/3) -> 436.58236 | N123: =IF(N159=0, +M123+N124*M123, M123-N159*2/3) -> 440.94819 | O123: =IF(O159=0, +N123+O124*N123, N123-O159*2/3) -> 445.35767 | ... Q123: =IF(Q159=0, +P123+Q124*P123, P123-Q159*2/3) -> 454.30936
B124: growing rate % | E124: =IFERROR((E123-Inputs!N45)/E60,"") | F124: =IFERROR((F123-E123)/F60,"") | G124: =IFERROR((G123-F123)/G60,"") | H124: 0.01 | I124: 0.01 | J124: 0.01 | K124: 0.01 | L124: 0.01 | M124: =(M123-L123)/L123 -> 0.84537156 | N124: 0.01 | O124: 0.01 | P124: 0.01 | Q124: 0.01
B126: Liabilities
B128: Accounts Payable | E128: =+_xlfn.XLOOKUP($B128,Inputs!$B:$B,Inputs!O:O) -> 19.2 | F128: =+_xlfn.XLOOKUP($B128,Inputs!$B:$B,Inputs!P:P) -> 31.4 | G128: =+_xlfn.XLOOKUP($B128,Inputs!$B:$B,Inputs!Q:Q) -> 81.1 | H128: =+IFERROR(H129*H51/365,"") -> 87.755534 | I128: =+IFERROR(I129*I51/365,"") -> 102.04812 | J128: =+IFERROR(J129*J51/365,"") -> 117.95399 | K128: =+IFERROR(K129*K51/365,"") -> 119.27994 | L128: =+IFERROR(L129*L51/365,"") -> 133.18314 | M128: =+IFERROR(M129*M51/365,"") -> 145.39951 | N128: =+IFERROR(N129*N51/365,"") -> 155.08474 | O128: =+IFERROR(O129*O51/365,"") -> 168.22833 | ... Q128: =+IFERROR(Q129*Q51/365,"") -> 200.88203
B129: DPO | E129: =IFERROR(E128/E$51*365,"") -> 49.91453 | F129: =IFERROR(F128/F$51*365,"") -> 60.833333 | G129: =IFERROR(G128/G$51*366,"") -> 99.008005 | H129: =IFERROR(AVERAGE(E129:G129),"") -> 69.918623 | I129: =IFERROR(AVERAGE(F129:H129),"") -> 76.586654 | J129: =IFERROR(AVERAGE(G129:I129),"") -> 81.837761 | K129: =IFERROR(AVERAGE(H129:J129),"") -> 76.114346 | L129: =IFERROR(AVERAGE(I129:K129),"") -> 78.179587 | M129: =IFERROR(AVERAGE(J129:L129),"") -> 78.710564 | N129: =IFERROR(AVERAGE(K129:M129),"") -> 77.668166 | O129: =IFERROR(AVERAGE(L129:N129),"") -> 78.186106 | ... Q129: =IFERROR(AVERAGE(N129:P129),"") -> 78.014183
B131: Accrued Expenses and Other Current Liabilities | E131: =+_xlfn.XLOOKUP($B131,Inputs!$B:$B,Inputs!O:O) -> 41.4 | F131: =+_xlfn.XLOOKUP($B131,Inputs!$B:$B,Inputs!P:P) -> 72.1 | G131: =+_xlfn.XLOOKUP($B131,Inputs!$B:$B,Inputs!Q:Q) -> 211 | H131: =IFERROR(AVERAGE(E131:G131)*(1+H49),"") -> 138.27459 | I131: =IFERROR(AVERAGE(F131:H131)*(1+I49),"") -> 160.58391 | J131: =IFERROR(AVERAGE(G131:I131)*(1+J49),"") -> 191.19157 | K131: =IFERROR(AVERAGE(H131:J131)*(1+K49),"") -> 181.2321 | L131: =IFERROR(AVERAGE(I131:K131)*(1+L49),"") -> 195.12884 | M131: =IFERROR(AVERAGE(J131:L131)*(1+M49),"") -> 206.20692 | N131: =IFERROR(AVERAGE(K131:M131)*(1+N49),"") -> 210.44953 | O131: =IFERROR(AVERAGE(L131:N131)*(1+O49),"") -> 220.03192 | ... Q131: =IFERROR(AVERAGE(N131:P131)*(1+Q49),"") -> 244.81369
B132: growing with revenue | E132: =IFERROR(E131/E$48,"") -> 0.10555839 | F132: =IFERROR(F131/F$48,"") -> 0.12456807 | G132: =IFERROR(G131/G$48,"") -> 0.20607481 | H132: =IFERROR(H131/H$48,"") -> 0.10564183 | I132: =IFERROR(I131/I$48,"") -> 0.1073101 | J132: =IFERROR(J131/J$48,"") -> 0.11357088 | K132: =IFERROR(K131/K$48,"") -> 0.097032554 | L132: =IFERROR(L131/L$48,"") -> 0.095124956 | ... Q132: =IFERROR(Q131/Q$48,"") -> 0.078144168
B134: Total Borrowings | E134: =+_xlfn.XLOOKUP($B134,Inputs!$B:$B,Inputs!O:O) -> 89.7 | F134: =+_xlfn.XLOOKUP($B134,Inputs!$B:$B,Inputs!P:P) -> 60.2 | G134: =+_xlfn.XLOOKUP($B134,Inputs!$B:$B,Inputs!Q:Q) -> 161.8 | H134: =IFERROR(G134+H174-H176,"") -> 147.28 | I134: =IFERROR(H134+I174-I176,"") -> 162.79424 | J134: =IFERROR(I134+J174-J176,"") -> 113.97534 | K134: =IFERROR(J134+K174-K176,"") -> 77.98426 | L134: =IFERROR(K134+L174-L176,"") -> 35.100958 | M134: =IFERROR(L134+M174-M176,"") -> 23.292932 | N134: =IFERROR(M134+N174-N176,"") -> 23.292932 | O134: =IFERROR(N134+O174-O176,"") -> 23.292932 | ... Q134: =IFERROR(P134+Q174-Q176,"") -> 23.292932
B136: Total Leases | E136: =+_xlfn.XLOOKUP($B136,Inputs!$B:$B,Inputs!O:O) -> 21.6 | F136: =+_xlfn.XLOOKUP($B136,Inputs!$B:$B,Inputs!P:P) -> 16.3 | G136: =+_xlfn.XLOOKUP($B136,Inputs!$B:$B,Inputs!Q:Q) -> 28.5 | H136: =+IFERROR(H137*H48,"") -> 48.460018 | I136: =+IFERROR(I137*I48,"") -> 46.399807 | J136: =+IFERROR(J137*J48,"") -> 53.794755 | K136: =+IFERROR(K137*K48,"") -> 62.24888 | L136: =+IFERROR(L137*L48,"") -> 65.839528 | M136: =+IFERROR(M137*M48,"") -> 72.576126 | N136: =+IFERROR(N137*N48,"") -> 79.061126 | O136: =+IFERROR(O137*O48,"") -> 84.694244 | ... Q136: =+IFERROR(Q137*Q48,"") -> 101.83606
B137: % of revenues | E137: =IFERROR(E136/E$48,"") -> 0.055073942 | F137: =IFERROR(F136/F$48,"") -> 0.028161714 | G137: =IFERROR(G136/G$48,"") -> 0.027834749 | H137: =+IFERROR(AVERAGE(E137:G137),"") -> 0.037023468 | I137: =+IFERROR(AVERAGE(F137:H137),"") -> 0.031006644 | J137: =+IFERROR(AVERAGE(G137:I137),"") -> 0.031954954 | K137: =+IFERROR(AVERAGE(H137:J137),"") -> 0.033328355 | L137: =+IFERROR(AVERAGE(I137:K137),"") -> 0.032096651 | M137: =+IFERROR(AVERAGE(J137:L137),"") -> 0.032459987 | N137: =+IFERROR(AVERAGE(K137:M137),"") -> 0.032628331 | O137: =+IFERROR(AVERAGE(L137:N137),"") -> 0.03239499 | ... Q137: =+IFERROR(AVERAGE(N137:P137),"") -> 0.032505919
A139: x | B139: Cash Flow | E139: =E46 -> 2022 | F139: =F46 -> 2023 | G139: =G46 -> 2024 | H139: =H46 -> 2025 | I139: =I46 -> 2026 | J139: =J46 -> 2027 | K139: =K46 -> 2028 | L139: =L46 -> 2029 | ... Q139: =Q46 -> 2034
...

Sheet DCF
B2: DCF
A4: x | B4: Key Assumptions | R4: #VALUE!
B6: Switches | E6: Bear Case | H6: Base Case | K6: Bull Case | X6: FCFF | Y6: FCFE | Z6: Tax Shield | AA6: Total Payout | AB6: NOPAT | AC6: Debt Borrowing | AD6: Cash Balance | AE6: Total Assets | AF6: Total Liabilities | AG6: Shareholder's Equity | AH6: Current Liabilities | AI6: Current Assets
B7: Revenue | C7: 2 | E7: Revenue | F7: -0.06 | H7: Revenue | K7: Revenue | L7: 0.04 | S7: Most Recent Fiscal Year | W7: 2022 | X7: =+E210 -> 7.4733333 | Y7: =+E262 -> 101.5 | Z7: =+H234 -> 0.68221377 | AA7: =+E275 -> 1.7 | AB7: =+E200 -> 7.9733333 | AC7: =+E260 -> 80.1 | AD7: =+E106 -> 43.4
B8: EBIT | C8: 2 | E8: EBIT | F8: -0.04 | H8: EBIT | K8: EBIT | L8: 0.03 | S8: End of Fiscal Year | W8: =+W7+1 -> 2023 | X8: =+F210 -> 91.954785 | Y8: =+F262 -> 140.3 | Z8: =+I234 -> 0.71676497 | AA8: =+F275 -> 8.1 | AB8: =+F200 -> 43.154785 | AC8: =+F260 -> 30 | AD8: =+F106 -> 120.8
B9: WACC | C9: 2 | E9: WACC | F9: =IFERROR(+I9+0.5%,"") -> 0.082706588 | H9: WACC | I9: =WACC!G25 -> 0.077706588 | K9: WACC | L9: =IFERROR(I9-0.5%,"") -> 0.072706588 | S9: Most Recent Quarter End Date | W9: =+W8+1 -> 2024 | X9: =+G210 -> 49.699049 | Y9: =+G262 -> 290.4 | Z9: =+J234 -> 0.47778107 | AA9: =+G275 -> 5.6 | AB9: =+G200 -> 99.399049 | AC9: =+G260 -> 212.4 | AD9: =+G106 -> 108.2 | AE9: =Inputs!Q48 -> 1129.3 | AF9: =+Inputs!Q60 -> 486.7 | AG9: =+AE9-AF9 -> 642.6 | AH9: =+Inputs!Q54 -> 299.1 | AI9: =+Inputs!Q38 -> 477.1
B10: TGR | C10: 2 | E10: TGR | F10: =+I10-0.5% -> 0.015 | H10: TGR | I10: 0.02 | K10: TGR | L10: =+I10+0.5% -> 0.025 | S10: Valuation Date | T10: 45755 | W10: =+W9+1 -> 2025 | X10: =+H210 -> 8.5855595 | Y10: =+H262 -> -15.514243 | Z10: =+K234 -> 0.27635362 | AA10: =+H275 -> -33.514119 | AB10: =+H200 -> 71.642986 | AC10: =+H260 -> -14.52 | AD10: =+H106 -> 79.24824 | AE10: =Inputs!Q48+DCF!H106+DCF!H108+DCF!H111+DCF!H114+DCF!H117+DCF!H123-DCF!G106-DCF!G108-DCF!G111-DCF!G114-DCF!G117-DCF!G123 -> 1202.4438 | AF10: =+Inputs!Q60+(DCF!H128+DCF!H131+DCF!H134+DCF!H136*DCF!G128*DCF!G131*DCF!G134*DCF!G136) -> 3.8239337e+09 | AG10: =+AE10-AF10 -> -3.8239325e+09 | AH10: =+AH9+H128+H131-G128-G131 -> 233.03012 | AI10: =+H106+H108+H111+H114 -> 534.73919
W11: =+W10+1 -> 2026 | X11: =+I210 -> 216.4966 | Y11: =+I262 -> 221.90412 | Z11: =+L234 -> 0.11241256 | AA11: =+I275 -> -38.319782 | AB11: =+I200 -> 119.59181 | AC11: =+I260 -> 15.514243 | AD11: =+I106 -> 251.41274 | AE11: =AE10+DCF!I106+DCF!I108+DCF!I111+DCF!I114+DCF!I117+DCF!I123-DCF!H106-DCF!H108-DCF!H111-DCF!H114-DCF!H117-DCF!H123 -> 1422.4509 | AF11: =AF10+(DCF!I128+DCF!I131+DCF!I134+DCF!I136*DCF!H128*DCF!H131*DCF!H134*DCF!H136) -> 7.8424011e+09 | AG11: =+AE11-AF11 -> -7.8423997e+09 | AH11: =+AH10+I128+I131-H128-H131 -> 269.63203 | AI11: =+I106+I108+I111+I114 -> 743.66861
B12: WACC | C12: =CHOOSE(C9,F9,I9,L9) -> 0.077706588 | W12: =+W11+1 -> 2027 | X12: =+J210 -> 236.39083 | Y12: =+J262 -> 179.95538 | Z12: =+M234 -> 0.067941166 | AA12: =+J275 -> -74.289503 | AB12: =+J200 -> 156.19555 | AC12: =+J260 -> -48.818907 | AD12: =+J106 -> 441.7623
B13: TGR | C13: =CHOOSE(C10,F10,I10,L10) -> 0.02 | W13: =+W12+1 -> 2028 | X13: =+K210 -> 256.05524 | Y13: =+K262 -> 214.41651 | Z13: =+N234 -> 0.062333339 | AA13: =+K275 -> -90.078039 | AB13: =+K200 -> 185.80374 | AC13: =+K260 -> -35.991076 | AD13: =+K106 -> 627.09341
W14: =+W13+1 -> 2029 | X14: =+L210 -> 309.19978 | Y14: =+L262 -> 262.40058 | Z14: =+O234 -> 0.057570819 | AA14: =+L275 -> -103.86399 | AB14: =+L200 -> 211.64388 | AC14: =+L260 -> -42.883301 | AD14: =+L106 -> 859.59783
A15: x | B15: Operating Assumptions | E15: 2022 | F15: =+E15+1 -> 2023 | G15: =+F15+1 -> 2024 | H15: =+G15+1 -> 2025 | I15: =+H15+1 -> 2026 | J15: =+I15+1 -> 2027 | K15: =+J15+1 -> 2028 | L15: =+K15+1 -> 2029 | M15: =+L15+1 -> 2030 | ... Q15: =+P15+1 -> 2034
B17: Global:
B18: Market Size (Fortune Business Insights) | G18: 335950 | H18: 354680 | I18: =J18-J18*I19 -> 368301.81 | J18: =K18-K18*J19 -> 394496.37 | K18: =L18-L18*K19 -> 422553.95 | L18: =M18-M18*L19 -> 452607.06 | M18: =N18-N18*M19 -> 484797.62 | N18: =O18-O18*N19 -> 519277.66 | O18: 556210 | P18: =O18+O18*P19 -> 593142.34 | Q18: =P18+P18*Q19 -> 632527
B19: Growth Rate | H19: =(H18-G18)/G18 -> 0.055752344 | I19: 0.0664 | J19: 0.0664 | K19: 0.0664 | L19: 0.0664 | M19: 0.0664 | N19: 0.0664 | O19: =(O18-N18)/N18 -> 0.071122536 | P19: 0.0664 | Q19: 0.0664
B20: Market Size (Statista) | E20: 247000 | F20: 252500 | G20: 257540 | H20: =G20*(1+H21) -> 271962.24 | I20: =H20*(1+I21) -> 287192.13 | J20: =I20*(1+J21) -> 303274.88 | K20: =J20*(1+K21) -> 320258.28 | L20: =K20*(1+L21) -> 338192.74 | M20: =L20*(1+M21) -> 357131.54 | N20: =M20*(1+N21) -> 377130.9 | O20: =N20*(1+O21) -> 398250.23 | ... Q20: =P20*(1+Q21) -> 444103.17
B21: Growth Rate | F21: =F20/E20-1 -> 0.022267206 | G21: =G20/F20-1 -> 0.019960396 | H21: 0.056 | I21: 0.056 | J21: 0.056 | K21: 0.056 | L21: 0.056 | M21: 0.056 | N21: 0.056 | O21: 0.056 | P21: 0.056 | Q21: 0.056
B22: Average | E22: =AVERAGE(E18,E20) -> 247000 | F22: =AVERAGE(F18,F20) -> 252500 | G22: =AVERAGE(G18,G20) -> 296745 | H22: =AVERAGE(H18,H20) -> 313321.12 | I22: =AVERAGE(I18,I20) -> 327746.97 | J22: =AVERAGE(J18,J20) -> 348885.63 | K22: =AVERAGE(K18,K20) -> 371406.11 | L22: =AVERAGE(L18,L20) -> 395399.9 | ... Q22: =AVERAGE(Q18,Q20) -> 538315.08
B23: Average (%) | H23: =AVERAGE(H19,H21) -> 0.055876172 | I23: =AVERAGE(I19,I21) -> 0.0612 | J23: =AVERAGE(J19,J21) -> 0.0612 | K23: =AVERAGE(K19,K21) -> 0.0612 | L23: =AVERAGE(L19,L21) -> 0.0612 | M23: =AVERAGE(M19,M21) -> 0.0612 | N23: =AVERAGE(N19,N21) -> 0.0612 | O23: =AVERAGE(O19,O21) -> 0.063561268 | ... Q23: =AVERAGE(Q19,Q21) -> 0.0612
B24: Market Share | E24: =E48/E22 -> 0.0015878543 | F24: =F48/F22 -> 0.0022922772 | G24: =G48/G22 -> 0.0034504372 | H24: =H48/H22 -> 0.0041775033 | I24: =I42/I22 -> 0.0045658615 | J24: =J42/J22 -> 0.0048252371 | K24: =K42/K22 -> 0.0050288491 | L24: =L42/L22 -> 0.0051878861 | M24: =M42/M22 -> 0.0053112885 | N24: =N42/N22 -> 0.0054062003 | O24: =O42/O22 -> 0.0054783303 | P24: =P42/P22 -> 0.0055419096 | Q24: =Q42/Q22 -> 0.0058197265
I25: Prediction of market share results
B27: US:
B28: Market Size (Fortune Business Insights) | C28: Doesn't say nominal numbers, but growth is close | H28: - | I28: - | J28: - | K28: - | L28: - | M28: - | N28: - | O28: - | P28: - | Q28: -
B29: Growth Rate | I29: 0.0601 | J29: 0.0601 | K29: 0.0601 | L29: 0.0601 | M29: 0.0601 | N29: 0.0601 | O29: 0.0601 | P29: 0.0601 | Q29: 0.0601
B30: Market Size (Statista) | E30: 56000 | F30: 61000 | G30: 66000 | H30: 67730 | I30: =H30+H30*I31 -> 71780.254 | J30: =I30+I30*J31 -> 76072.713 | K30: =J30+J30*K31 -> 80621.861 | L30: =K30+K30*L31 -> 85443.049 | M30: =L30+L30*M31 -> 90552.543 | N30: =M30+M30*N31 -> 95967.585 | O30: =N30+N30*O31 -> 101706.45 | P30: =O30+O30*P31 -> 107788.49 | Q30: =P30+P30*Q31 -> 114234.24
B31: Growth Rate | F31: =F30/E30-1 -> 0.089285714 | G31: =G30/F30-1 -> 0.081967213 | H31: =H30/G30-1 -> 0.026212121 | I31: 0.0598 | J31: 0.0598 | K31: 0.0598 | L31: 0.0598 | M31: 0.0598 | N31: 0.0598 | O31: 0.0598 | P31: 0.0598 | Q31: 0.0598
B32: Average | H32: =AVERAGE(H28,H30) -> 67730 | I32: =AVERAGE(I28,I30) -> 71780.254 | J32: =AVERAGE(J28,J30) -> 76072.713 | K32: =AVERAGE(K28,K30) -> 80621.861 | L32: =AVERAGE(L28,L30) -> 85443.049 | M32: =AVERAGE(M28,M30) -> 90552.543 | N32: =AVERAGE(N28,N30) -> 95967.585 | O32: =AVERAGE(O28,O30) -> 101706.45 | ... Q32: =AVERAGE(Q28,Q30) -> 114234.24
B33: Average (%) | I33: =AVERAGE(I29,I31) -> 0.05995 | J33: =AVERAGE(J29,J31) -> 0.05995 | K33: =AVERAGE(K29,K31) -> 0.05995 | L33: =AVERAGE(L29,L31) -> 0.05995 | M33: =AVERAGE(M29,M31) -> 0.05995 | N33: =AVERAGE(N29,N31) -> 0.05995 | O33: =AVERAGE(O29,O31) -> 0.05995 | P33: =AVERAGE(P29,P31) -> 0.05995 | Q33: =AVERAGE(Q29,Q31) -> 0.05995
B34: Market Share (US revenue only) | E34: =E48*E43/E30 -> 0.0062053571 | F34: =F48*F43/F30 -> 0.0083067616 | G34: =G48*G43/G30 -> 0.013151746 | H34: =H48*$G$43/H32 -> 0.016383066 | I34: =H34+($Q$34-H34)/5 -> 0.017106453 | J34: =I34+($Q$34-I34)/5 -> 0.017685163 | K34: =J34+($Q$34-J34)/5 -> 0.01814813 | L34: =K34+($Q$34-K34)/5 -> 0.018518504 | M34: =L34+($Q$34-L34)/5 -> 0.018814803 | N34: =M34+($Q$34-M34)/5 -> 0.019051843 | O34: =N34+($Q$34-N34)/5 -> 0.019241474 | P34: =O34+($Q$34-O34)/5 -> 0.019393179 | Q34: 0.02
I35: Prediction of market share
B36: Global "Minus" US
B37: Market Size (based on averages) | E37: =E20-E30 -> 191000 | F37: =F20-F30 -> 191500 | G37: =G20-G30 -> 191540 | H37: =H22-H32 -> 245591.12 | I37: =I22-I32 -> 255966.71 | J37: =J22-J32 -> 272812.91 | K37: =K22-K32 -> 290784.25 | L37: =L22-L32 -> 309956.85 | M37: =M22-M32 -> 330412.03 | N37: =N22-N32 -> 352236.69 | O37: =O22-O32 -> 375523.67 | ... Q37: =Q22-Q32 -> 424080.84
B38: Growth Rate | F38: =(F37-E37)/E37 -> 0.002617801 | G38: =(G37-F37)/F37 -> 0.00020887728 | H38: =(H37-G37)/G37 -> 0.28219234 | I38: =(I37-H37)/H37 -> 0.042247426 | J38: =(J37-I37)/I37 -> 0.065814025 | K38: =(K37-J37)/J37 -> 0.065874227 | L38: =(L37-K37)/K37 -> 0.065934103 | M38: =(M37-L37)/L37 -> 0.065993648 | ... Q38: =(Q37-P37)/P37 -> 0.062702631
B39: Market Share (non-US revenue only) | E39: =E48*E44/E37 -> 0.00023403141 | F39: =F48*F44/F37 -> 0.00037643627 | G39: =G48*G44/G37 -> 0.00081384972 | H39: =(H48*G44)/H37 -> 0.00081140927 | I39: =H39+($Q$39-H39)/5 -> 0.0010491274 | J39: =I39+($Q$39-I39)/5 -> 0.0012393019 | K39: =J39+($Q$39-J39)/5 -> 0.0013914415 | L39: =K39+($Q$39-K39)/5 -> 0.0015131532 | M39: =L39+($Q$39-L39)/5 -> 0.0016105226 | N39: =M39+($Q$39-M39)/5 -> 0.0016884181 | O39: =N39+($Q$39-N39)/5 -> 0.0017507345 | P39: =O39+($Q$39-O39)/5 -> 0.0018005876 | Q39: 0.002
I40: Prediction of market share
B42: Weighted Average of expected revenue: | H42: =H32*H34+H37*H39 -> 1308.9 | I42: =I32*I34+I37*I39 -> 1496.4472 | J42: =J32*J34+J37*J39 -> 1683.4559 | K42: =K32*K34+K37*K39 -> 1867.7453 | L42: =L32*L34+L37*L39 -> 2051.2897 | M42: =M32*M34+M37*M39 -> 2235.8643 | N42: =N32*N34+N37*N39 -> 2423.0821 | O42: =O32*O34+O37*O39 -> 2614.4242 | ... Q42: =Q32*Q34+Q37*Q39 -> 3132.8466 | R42: Prediction:
B43: Current Average is: | C43: US = | E43: =Segments!G6/Segments!G13 -> 0.88602754 | F43: =Segments!H6/Segments!H13 -> 0.87545345 | G43: =Segments!D6 -> 0.84775391 | H43: =H34*H32 -> 1109.6251 | I43: =I34*I32 -> 1227.9056 | J43: =J34*J32 -> 1345.3583 | K43: =K34*K32 -> 1463.136 | L43: =L34*L32 -> 1582.2774 | M43: =M34*M32 -> 1703.7283 | N43: =N34*N32 -> 1828.3593 | O43: =O34*O32 -> 1956.982 | ... Q43: =Q34*Q32 -> 2284.6849 | R43: =Q43/Q42 -> 0.72926804
C44: Rest of the World = | E44: =1-E43 -> 0.11397246 | F44: =1-F43 -> 0.12454655 | G44: =1-G43 -> 0.15224609 | H44: =H39*H37 -> 199.27491 | I44: =I39*I37 -> 268.5417 | J44: =J39*J37 -> 338.09757 | K44: =K39*K37 -> 404.60929 | L44: =L39*L37 -> 469.01221 | M44: =M39*M37 -> 532.13605 | N44: =N39*N37 -> 594.7228 | O44: =O39*O37 -> 657.44223 | ... Q44: =Q39*Q37 -> 848.16168 | R44: =Q44/Q42 -> 0.27073196
B45: In millions of USD
A46: x | B46: Income Statement | E46: 2022 | F46: =+E46+1 -> 2023 | G46: =+F46+1 -> 2024 | H46: =+G46+1 -> 2025 | I46: =+H46+1 -> 2026 | J46: =+I46+1 -> 2027 | K46: =+J46+1 -> 2028 | L46: =+K46+1 -> 2029 | M46: =+L46+1 -> 2030 | ... Q46: =+P46+1 -> 2034
