Workbook
Name COOLFUCNTION: _xlfn.LAMBDA(_xldudf_BOARDFLARE_EXEC("workbook-settings:coolfucntion"))
Name COOLFUCNTION: _xlfn.LAMBDA(_xldudf_BOARDFLARE_EXEC("workbook-settings:coolfucntion"))
Name COOLFUCNTION: _xlfn.LAMBDA(_xldudf_BOARDFLARE_EXEC("workbook-settings:coolfucntion"))
Name COOLFUCNTION: _xlfn.LAMBDA(_xldudf_BOARDFLARE_EXEC("workbook-settings:coolfucntion"))
Name COOLFUCNTION: _xlfn.LAMBDA(_xldudf_BOARDFLARE_EXEC("workbook-settings:coolfucntion"))
Name COOLFUCNTION: _xlfn.LAMBDA(_xldudf_BOARDFLARE_EXEC("workbook-settings:coolfucntion"))
Name COOLFUCNTION: _xlfn.LAMBDA(_xldudf_BOARDFLARE_EXEC("workbook-settings:coolfucntion"))
Name COOLFUCNTION: _xlfn.LAMBDA(_xldudf_BOARDFLARE_EXEC("workbook-settings:coolfucntion"))
Name COOLFUCNTION: _xlfn.LAMBDA(_xldudf_BOARDFLARE_EXEC("workbook-settings:coolfucntion"))
Name COOLFUCNTION: _xlfn.LAMBDA(_xldudf_BOARDFLARE_EXEC("workbook-settings:coolfucntion"))
Name Sectors: #REF!
Name Sectors: #REF!
Name Sectors: #REF!

Sheet Summary
E2: | EQUITY RESEARCH | U2: Lisbon Investment Society Equity Research
U3: April 25th, 2025
D6: {=+_FV(DCF!R4,"Name")} -> INTERNATIONAL BUSINESS MACHINES CORPORATION | U6: Buy
D8: IBM is a global technology and consulting company known for its innovative enterprise solutions and legacy of technological leadership. The company provides a wide range of services, including hybrid cloud infrastructure, artificial intelligence (AI), data analytics, cybersecurity, and quantum computing. | U8: #VALUE!
U9: {=+"Price (7 Mar 25): $"&_FV(DCF!$R$4,"Price")} -> Price (7 Mar 25): $288.37
D10: Investment Thesis | U10: ="Price Target: $" & ROUND(IF(Summary!G25="FCFF",DCF!Q209,IF(Summary!G25="FCFE",DCF!Q252,IF(Summary!G25="Tax Shield",DCF!Q225,DCF!Q268))),2) &" "&IF(Summary!G25="FCFF","(FCFF)",IF(Summary!G25="FCFE","(FCFE)",IF(Summary!G25="Tax Shield","(APV)","(DDM)"))) -> Price Target: $257.51 (FCFF)
D11: IBM’s hybrid cloud and AI strategy, together with its software-driven portfolio, is expected to deliver mid-single-digit revenue growth, benefiting future free cash flow generation and providing upside potential. While the hybrid cloud market and the evolving AI industry bring competitive challenges, IBM as an enterprise solutions provider and its strong client base support its strategic positioning. As the stock is currently trading slightly below our base case scenario value of $268.83, the recommendation on IBM is BUY | U11: =+"Upside (Downside): "&ROUND((DCF!$Q$212*100),2)&"%" -> Upside (Downside): -10.7%
U14: United States, Information Technology
U15: =+ESG!C10 -> IT Services
D17: Operating Metrics | F17: 2023 | G17: =+F17+1 -> 2024 | H17: =+G17+1 -> 2025 | I17: =+H17+1 -> 2026 | K17: Valuation Multiples | N17: 2022 | O17: =+N17+1 -> 2023 | P17: =+O17+1 -> 2024 | Q17: =+P17+1 -> 2025 | R17: =+Q17+1 -> 2026 | U17: Haitao Yu
D18: Hybrid Platform & Solutions revenue | F18: =DCF!F17 -> 17396 | G18: =DCF!G17 -> 18808 | H18: =DCF!H17 -> 20594.76 | I18: =DCF!I17 -> 22654.236 | K18: EV / Sales | N18: =IFERROR(_xlfn.XLOOKUP($K18,Multiples!$B:$B,Multiples!N:N),"") -> 2.8652042 | O18: =IFERROR(_xlfn.XLOOKUP($K18,Multiples!$B:$B,Multiples!O:O),"") -> 3.1620182 | P18: =IFERROR(_xlfn.XLOOKUP($K18,Multiples!$B:$B,Multiples!P:P),"") -> 3.9284691 | Q18: =IFERROR(_xlfn.XLOOKUP($K18,Multiples!$B:$B,Multiples!Q:Q),"") -> 4.4795343 | R18: =IFERROR(_xlfn.XLOOKUP($K18,Multiples!$B:$B,Multiples!R:R),"") -> 4.4394652 | U18: haitaoyu@aln.iseg.ulisboa.pt
D19: Transaction revenue | F19: =DCF!F20 -> 7615 | G19: =DCF!G20 -> 8277 | H19: =DCF!H20 -> 8770.2562 | I19: =DCF!I20 -> 9292.9074 | K19: Price / Sales | N19: =IFERROR(_xlfn.XLOOKUP($K19,Multiples!$B:$B,Multiples!N:N),"") -> 2.1035819 | O19: =IFERROR(_xlfn.XLOOKUP($K19,Multiples!$B:$B,Multiples!O:O),"") -> 2.4091246 | P19: =IFERROR(_xlfn.XLOOKUP($K19,Multiples!$B:$B,Multiples!P:P),"") -> 3.2290444 | Q19: =IFERROR(_xlfn.XLOOKUP($K19,Multiples!$B:$B,Multiples!Q:Q),"") -> 3.8715384 | R19: =IFERROR(_xlfn.XLOOKUP($K19,Multiples!$B:$B,Multiples!R:R),"") -> 3.8841567 | U19: (+351) 938 305 543
D20: Consulting revenue | F20: =DCF!F25 -> 20884 | G20: =DCF!G25 -> 20692 | H20: =DCF!H25 -> 21105.84 | I20: =DCF!I25 -> 21739.015 | K20: EV / EBITDA | N20: =IFERROR(_xlfn.XLOOKUP($K20,Multiples!$B:$B,Multiples!N:N),"") -> 13.364476 | O20: =IFERROR(_xlfn.XLOOKUP($K20,Multiples!$B:$B,Multiples!O:O),"") -> 14.196723 | P20: =IFERROR(_xlfn.XLOOKUP($K20,Multiples!$B:$B,Multiples!P:P),"") -> 17.548635 | Q20: =IFERROR(_xlfn.XLOOKUP($K20,Multiples!$B:$B,Multiples!Q:Q),"") -> 21.831535 | R20: =IFERROR(_xlfn.XLOOKUP($K20,Multiples!$B:$B,Multiples!R:R),"") -> 21.677854 | U20: João Baiôa
D21: Infrastucture revenue | F21: =DCF!F26 -> 14593 | G21: =DCF!G26 -> 14020 | H21: =DCF!H26 -> 14648.096 | I21: =DCF!I26 -> 14500 | K21: EV / EBIT | N21: =IFERROR(_xlfn.XLOOKUP($K21,Multiples!$B:$B,Multiples!N:N),"") -> 21.214778 | O21: =IFERROR(_xlfn.XLOOKUP($K21,Multiples!$B:$B,Multiples!O:O),"") -> 20.848694 | P21: =IFERROR(_xlfn.XLOOKUP($K21,Multiples!$B:$B,Multiples!P:P),"") -> 26.278992 | Q21: =IFERROR(_xlfn.XLOOKUP($K21,Multiples!$B:$B,Multiples!Q:Q),"") -> 33.548656 | R21: =IFERROR(_xlfn.XLOOKUP($K21,Multiples!$B:$B,Multiples!R:R),"") -> 33.406955 | U21: l61773@aln.iseg.ulisboa.pt
K22: Price / Earnings | N22: =IFERROR(_xlfn.XLOOKUP($K22,Multiples!$B:$B,Multiples!N:N),"") -> 71.453317 | O22: =IFERROR(_xlfn.XLOOKUP($K22,Multiples!$B:$B,Multiples!O:O),"") -> 19.836077 | P22: =IFERROR(_xlfn.XLOOKUP($K22,Multiples!$B:$B,Multiples!P:P),"") -> 33.682218 | Q22: =IFERROR(_xlfn.XLOOKUP($K22,Multiples!$B:$B,Multiples!Q:Q),"") -> 37.601264 | R22: =IFERROR(_xlfn.XLOOKUP($K22,Multiples!$B:$B,Multiples!R:R),"") -> 32.215569 | U22: (+351) 963 849 143
K23: Price / Book | N23: =IFERROR(_xlfn.XLOOKUP($K23,Multiples!$B:$B,Multiples!N:N),"") -> 5.7819367 | O23: =IFERROR(_xlfn.XLOOKUP($K23,Multiples!$B:$B,Multiples!O:O),"") -> 6.5906796 | P23: =IFERROR(_xlfn.XLOOKUP($K23,Multiples!$B:$B,Multiples!P:P),"") -> 7.3974965 | Q23: =IFERROR(_xlfn.XLOOKUP($K23,Multiples!$B:$B,Multiples!Q:Q),"") -> 9.4071156 | R23: =IFERROR(_xlfn.XLOOKUP($K23,Multiples!$B:$B,Multiples!R:R),"") -> 9.4674731 | U23: João Garcia
U24: joaogarcia@aln.iseg.ulisboa.pt
D25: Year | E25: Net Sales | F25: EBIT Margin | G25: FCFF | H25: =+IF(Summary!$G$25="FCFF",DCF!AB6,IF(Summary!$G$25="FCFE",DCF!AC6,DCF!AD6)) -> NOPAT | I25: Net Capex | K25: Profitability Ratios | N25: 2022 | O25: =+N25+1 -> 2023 | P25: =+O25+1 -> 2024 | Q25: =+P25+1 -> 2025 | R25: =+Q25+1 -> 2026 | U25: (+351) 969 563 512
D26: 2022 | E26: =+DCF!E31 -> 60530 | F26: =+DCF!E61 -> 0.135057 | G26: =+INDEX(DCF!X7:AA7,MATCH(Summary!$G$25,{"FCFF","FCFE","Tax Shield","Total Payout"},0)) -> 11688.4 | H26: =+IF(Summary!$G$25="FCFF",DCF!AB7,IF(Summary!$G$25="FCFE",DCF!AC7,DCF!AD7)) -> 6932.4 | I26: =+DCF!E135 -> -1235 | K26: Return on Assets | N26: =IFERROR(_xlfn.XLOOKUP($K26,Multiples!$B:$B,Multiples!N:N),"") -> 0.01400459 | O26: =IFERROR(_xlfn.XLOOKUP($K26,Multiples!$B:$B,Multiples!O:O),"") -> 0.055553502 | P26: =IFERROR(_xlfn.XLOOKUP($K26,Multiples!$B:$B,Multiples!P:P),"") -> 0.043856388 | Q26: =IFERROR(_xlfn.XLOOKUP($K26,Multiples!$B:$B,Multiples!Q:Q),"") -> 0.047421906 | R26: =IFERROR(_xlfn.XLOOKUP($K26,Multiples!$B:$B,Multiples!R:R),"") -> 0.057999094 | U26: Lucas Alves
D27: =+D26+1 -> 2023 | E27: =+DCF!F31 -> 61860 | F27: =+DCF!F61 -> 0.15166505 | G27: =+INDEX(DCF!X8:AA8,MATCH(Summary!$G$25,{"FCFF","FCFE","Tax Shield","Total Payout"},0)) -> 14857.52 | H27: =+IF(Summary!$G$25="FCFF",DCF!AB8,IF(Summary!$G$25="FCFE",DCF!AC8,DCF!AD8)) -> 8068.52 | I27: =+DCF!F135 -> -924 | K27: Return on Equity | N27: =IFERROR(_xlfn.XLOOKUP($K27,Multiples!$B:$B,Multiples!N:N),"") -> 0.080919081 | O27: =IFERROR(_xlfn.XLOOKUP($K27,Multiples!$B:$B,Multiples!O:O),"") -> 0.33225721 | P27: =IFERROR(_xlfn.XLOOKUP($K27,Multiples!$B:$B,Multiples!P:P),"") -> 0.21962617 | Q27: =IFERROR(_xlfn.XLOOKUP($K27,Multiples!$B:$B,Multiples!Q:Q),"") -> 0.2256784 | R27: =IFERROR(_xlfn.XLOOKUP($K27,Multiples!$B:$B,Multiples!R:R),"") -> 0.27601469 | U27: lucas.alves@aln.iseg.ulisboa.pt
D28: =+D27+1 -> 2024 | E28: =+DCF!G31 -> 62753 | F28: =+DCF!G61 -> 0.14949086 | G28: =+INDEX(DCF!X9:AA9,MATCH(Summary!$G$25,{"FCFF","FCFE","Tax Shield","Total Payout"},0)) -> 14905.184 | H28: =+IF(Summary!$G$25="FCFF",DCF!AB9,IF(Summary!$G$25="FCFE",DCF!AC9,DCF!AD9)) -> 8105.184 | I28: =+DCF!G135 -> -491 | K28: Return on Total Capital | N28: =IFERROR(_xlfn.XLOOKUP($K28,Multiples!$B:$B,Multiples!N:N),"") -> 0.1218004 | O28: =IFERROR(_xlfn.XLOOKUP($K28,Multiples!$B:$B,Multiples!O:O),"") -> 0.075624696 | P28: =IFERROR(_xlfn.XLOOKUP($K28,Multiples!$B:$B,Multiples!P:P),"") -> 0.084372835 | Q28: =IFERROR(_xlfn.XLOOKUP($K28,Multiples!$B:$B,Multiples!Q:Q),"") -> 0.08214452 | R28: =IFERROR(_xlfn.XLOOKUP($K28,Multiples!$B:$B,Multiples!R:R),"") -> 0.083406235 | U28: (+351) 938 350 699
D29: =+D28+1 -> 2025 | E29: =+DCF!H31 -> 65932.415 | F29: =+DCF!H61 -> 0.13352351 | G29: =+INDEX(DCF!X10:AA10,MATCH(Summary!$G$25,{"FCFF","FCFE","Tax Shield","Total Payout"},0)) -> 11932.291 | H29: =+IF(Summary!$G$25="FCFF",DCF!AB10,IF(Summary!$G$25="FCFE",DCF!AC10,DCF!AD10)) -> 7547.5575 | I29: =+DCF!H135 -> -938.72157 | K29: EBITDA Margin | N29: =IFERROR(_xlfn.XLOOKUP($K29,Multiples!$B:$B,Multiples!N:N),"") -> 0.21438956 | O29: =IFERROR(_xlfn.XLOOKUP($K29,Multiples!$B:$B,Multiples!O:O),"") -> 0.22272874 | P29: =IFERROR(_xlfn.XLOOKUP($K29,Multiples!$B:$B,Multiples!P:P),"") -> 0.22386181 | Q29: =IFERROR(_xlfn.XLOOKUP($K29,Multiples!$B:$B,Multiples!Q:Q),"") -> 0.20518641 | R29: =IFERROR(_xlfn.XLOOKUP($K29,Multiples!$B:$B,Multiples!R:R),"") -> 0.20479265
D30: =+D29+1 -> 2026 | E30: =+DCF!I31 -> 68863.861 | F30: =+DCF!I61 -> 0.13289045 | G30: =+INDEX(DCF!X11:AA11,MATCH(Summary!$G$25,{"FCFF","FCFE","Tax Shield","Total Payout"},0)) -> 13978.955 | H30: =+IF(Summary!$G$25="FCFF",DCF!AB11,IF(Summary!$G$25="FCFE",DCF!AC11,DCF!AD11)) -> 7874.2278 | I30: =+DCF!I135 -> -770.11747 | K30: EBIT Margin | N30: =IFERROR(_xlfn.XLOOKUP($K30,Multiples!$B:$B,Multiples!N:N),"") -> 0.135057 | O30: =IFERROR(_xlfn.XLOOKUP($K30,Multiples!$B:$B,Multiples!O:O),"") -> 0.15166505 | P30: =IFERROR(_xlfn.XLOOKUP($K30,Multiples!$B:$B,Multiples!P:P),"") -> 0.14949086 | Q30: =IFERROR(_xlfn.XLOOKUP($K30,Multiples!$B:$B,Multiples!Q:Q),"") -> 0.13352351 | R30: =IFERROR(_xlfn.XLOOKUP($K30,Multiples!$B:$B,Multiples!R:R),"") -> 0.13289045 | U30: Statistics
D31: =+D30+1 -> 2027 | E31: =+DCF!J31 -> 72104.208 | F31: =+DCF!J61 -> 0.13351036 | G31: =+INDEX(DCF!X12:AA12,MATCH(Summary!$G$25,{"FCFF","FCFE","Tax Shield","Total Payout"},0)) -> 14199.951 | H31: =+IF(Summary!$G$25="FCFF",DCF!AB12,IF(Summary!$G$25="FCFE",DCF!AC12,DCF!AD12)) -> 8284.6312 | I31: =+DCF!J135 -> -683.21192 | K31: Gross Profit Margin | N31: =IFERROR(_xlfn.XLOOKUP($K31,Multiples!$B:$B,Multiples!N:N),"") -> 0.54002974 | O31: =IFERROR(_xlfn.XLOOKUP($K31,Multiples!$B:$B,Multiples!O:O),"") -> 0.55447785 | P31: =IFERROR(_xlfn.XLOOKUP($K31,Multiples!$B:$B,Multiples!P:P),"") -> 0.56653865 | Q31: =IFERROR(_xlfn.XLOOKUP($K31,Multiples!$B:$B,Multiples!Q:Q),"") -> 0.553881 | R31: =IFERROR(_xlfn.XLOOKUP($K31,Multiples!$B:$B,Multiples!R:R),"") -> 0.55278492 | U31: Beta | V31: =Peers!D74 -> 0.6925
D32: =+D31+1 -> 2028 | E32: =+DCF!K31 -> 77148.077 | F32: =+DCF!K61 -> 0.14306115 | G32: =+INDEX(DCF!X13:AA13,MATCH(Summary!$G$25,{"FCFF","FCFE","Tax Shield","Total Payout"},0)) -> 15830.407 | H32: =+IF(Summary!$G$25="FCFF",DCF!AB13,IF(Summary!$G$25="FCFE",DCF!AC13,DCF!AD13)) -> 9485.7321 | I32: =+DCF!K135 -> -729.75804 | K32: SG&A Margin | N32: =IFERROR(_xlfn.XLOOKUP($K32,Multiples!$B:$B,Multiples!N:N),"") -> 0.30743433 | O32: =IFERROR(_xlfn.XLOOKUP($K32,Multiples!$B:$B,Multiples!O:O),"") -> 0.30719366 | P32: =IFERROR(_xlfn.XLOOKUP($K32,Multiples!$B:$B,Multiples!P:P),"") -> 0.31373799 | Q32: =IFERROR(_xlfn.XLOOKUP($K32,Multiples!$B:$B,Multiples!Q:Q),"") -> 0.30945533 | R32: =IFERROR(_xlfn.XLOOKUP($K32,Multiples!$B:$B,Multiples!R:R),"") -> 0.31012899 | U32: % Float | V32: =+Peers!D73 -> 0.9979
D33: =+D32+1 -> 2029 | E33: =+DCF!L31 -> 81934.093 | F33: =+DCF!L61 -> 0.14060074 | G33: =+INDEX(DCF!X14:AA14,MATCH(Summary!$G$25,{"FCFF","FCFE","Tax Shield","Total Payout"},0)) -> 16724.743 | H33: =+IF(Summary!$G$25="FCFF",DCF!AB14,IF(Summary!$G$25="FCFE",DCF!AC14,DCF!AD14)) -> 9909.0909 | I33: =+DCF!L135 -> -665.94 | K33: Net Income Margin | N33: =IFERROR(_xlfn.XLOOKUP($K33,Multiples!$B:$B,Multiples!N:N),"") -> 0.029439947 | O33: =IFERROR(_xlfn.XLOOKUP($K33,Multiples!$B:$B,Multiples!O:O),"") -> 0.12145167 | P33: =IFERROR(_xlfn.XLOOKUP($K33,Multiples!$B:$B,Multiples!P:P),"") -> 0.095867927 | Q33: =IFERROR(_xlfn.XLOOKUP($K33,Multiples!$B:$B,Multiples!Q:Q),"") -> 0.10296299 | R33: =IFERROR(_xlfn.XLOOKUP($K33,Multiples!$B:$B,Multiples!R:R),"") -> 0.12056769 | U33: % Held by Insiders | V33: =+Peers!D76 -> 0.0012
U34: % Held by Institutions | V34: =+Peers!D77 -> 0.6406
D35: SWOT Analysis | K35: Liquidity Ratios | N35: 2022 | O35: =+N35+1 -> 2023 | P35: =+O35+1 -> 2024 | Q35: =+P35+1 -> 2025 | R35: =+Q35+1 -> 2026 | U35: Short % of Float | V35: =+Peers!D78 -> 0.0223
D36: Strengths | G36: Weaknesses | K36: Cash Ratio | N36: =IFERROR(_xlfn.XLOOKUP($K36,Multiples!$B:$B,Multiples!N:N),"") -> 0.25030947 | O36: =IFERROR(_xlfn.XLOOKUP($K36,Multiples!$B:$B,Multiples!O:O),"") -> 0.38297872 | P36: =IFERROR(_xlfn.XLOOKUP($K36,Multiples!$B:$B,Multiples!P:P),"") -> 0.42082554 | Q36: =IFERROR(_xlfn.XLOOKUP($K36,Multiples!$B:$B,Multiples!Q:Q),"") -> 0.51943532 | R36: =IFERROR(_xlfn.XLOOKUP($K36,Multiples!$B:$B,Multiples!R:R),"") -> 0.64176559 | W36: 120.87
D37: Leading in hybrid cloud, with strong client base. 93% of all fortune 500 companies leverage IBM’s hybrid cloud products and solutions. | G37: Growth of Consulting and Infrastructure is relatively slow, at low to mid single digit only. Further growth is limited due to high client penetration. IBM isn't perceived as a very innovative compay. | K37: Quick Ratio | N37: =IFERROR(_xlfn.XLOOKUP($K37,Multiples!$B:$B,Multiples!N:N),"") -> 0.48712903 | O37: =IFERROR(_xlfn.XLOOKUP($K37,Multiples!$B:$B,Multiples!O:O),"") -> 0.62408417 | P37: =IFERROR(_xlfn.XLOOKUP($K37,Multiples!$B:$B,Multiples!P:P),"") -> 0.6741295 | Q37: =IFERROR(_xlfn.XLOOKUP($K37,Multiples!$B:$B,Multiples!Q:Q),"") -> 0.77937201 | R37: =IFERROR(_xlfn.XLOOKUP($K37,Multiples!$B:$B,Multiples!R:R),"") -> 0.91415099 | U37: Major Holders | W37: 113.63
K38: Current Ratio | N38: =IFERROR(_xlfn.XLOOKUP($K38,Multiples!$B:$B,Multiples!N:N),"") -> 0.92423425 | O38: =IFERROR(_xlfn.XLOOKUP($K38,Multiples!$B:$B,Multiples!O:O),"") -> 0.96442178 | P38: =IFERROR(_xlfn.XLOOKUP($K38,Multiples!$B:$B,Multiples!P:P),"") -> 1.0404321 | Q38: =IFERROR(_xlfn.XLOOKUP($K38,Multiples!$B:$B,Multiples!Q:Q),"") -> 1.166993 | R38: =IFERROR(_xlfn.XLOOKUP($K38,Multiples!$B:$B,Multiples!R:R),"") -> 1.166993 | U38: The Vanguard Group, Inc. | V38: 0.1001
U39: BlackRock, Inc. | V39: 0.0851
D40: Opportunities | G40: Threats | K40: Cash Flow Ratios | N40: 2022 | O40: =+N40+1 -> 2023 | P40: =+O40+1 -> 2024 | Q40: =+P40+1 -> 2025 | R40: =+Q40+1 -> 2026 | U40: State Street Global Advisors, Inc. | V40: 0.0598
D41: A growing market. 73% of companies use hybrid cloud today. The Hybrid cloud market is expected to grow considerably in the next 10 years. | G41: The integration of GenAI into hybrid clould presents technological and operatinal challenges. IBM need to continuously innovate and enhance its offerings to address the complexity within the growing demand. Market is highly competitive with strong players like AWS and Azure. | K41: Cash Conversion Cycle | N41: =IFERROR(_xlfn.XLOOKUP($K41,Multiples!$B:$B,Multiples!N:N),"") -> 11.608122 | O41: =IFERROR(_xlfn.XLOOKUP($K41,Multiples!$B:$B,Multiples!O:O),"") -> 6.9944773 | P41: =IFERROR(_xlfn.XLOOKUP($K41,Multiples!$B:$B,Multiples!P:P),"") -> 8.2760561 | Q41: =IFERROR(_xlfn.XLOOKUP($K41,Multiples!$B:$B,Multiples!Q:Q),"") -> 8.9513139 | R41: =IFERROR(_xlfn.XLOOKUP($K41,Multiples!$B:$B,Multiples!R:R),"") -> 8.0657111 | U41: Geode Capital Management, LLC | V41: 0.0225
K42: Net Income / Op Cash Flow | N42: =IFERROR(_xlfn.XLOOKUP($K42,Multiples!$B:$B,Multiples!N:N),"") -> 0.17077144 | O42: =IFERROR(_xlfn.XLOOKUP($K42,Multiples!$B:$B,Multiples!O:O),"") -> 0.53930084 | P42: =IFERROR(_xlfn.XLOOKUP($K42,Multiples!$B:$B,Multiples!P:P),"") -> 0.44745258 | Q42: =IFERROR(_xlfn.XLOOKUP($K42,Multiples!$B:$B,Multiples!Q:Q),"") -> 0.53710929 | R42: =IFERROR(_xlfn.XLOOKUP($K42,Multiples!$B:$B,Multiples!R:R),"") -> 0.5550604 | U42: UBS Asset Management AG | V42: 0.0143
K43: Chg in Cash / Op Cash Flow | N43: =IFERROR(_xlfn.XLOOKUP($K43,Multiples!$B:$B,Multiples!N:N),"") -> 0.09889794 | O43: =IFERROR(_xlfn.XLOOKUP($K43,Multiples!$B:$B,Multiples!O:O),"") -> 0.3661618 | P43: =IFERROR(_xlfn.XLOOKUP($K43,Multiples!$B:$B,Multiples!P:P),"") -> 0.079657865 | Q43: =IFERROR(_xlfn.XLOOKUP($K43,Multiples!$B:$B,Multiples!Q:Q),"") -> 0.29226515 | R43: =IFERROR(_xlfn.XLOOKUP($K43,Multiples!$B:$B,Multiples!R:R),"") -> 0.27774298 | U43: Capital Research and Management Company | V43: 0.013
U44: Nothern Trust Global Investments | V44: 0.0117
D45: Revenue by Region | G45: Revenue by Segment | K45: Leverage Ratios | N45: 2022 | O45: =+N45+1 -> 2023 | P45: =+O45+1 -> 2024 | Q45: =+P45+1 -> 2025 | R45: =+Q45+1 -> 2026 | U45: Morgan Stanley | V45: 0.01
K46: Total Debt / Equity | N46: =IFERROR(_xlfn.XLOOKUP($K46,Multiples!$B:$B,Multiples!N:N),"") -> 2.4526837 | O46: =IFERROR(_xlfn.XLOOKUP($K46,Multiples!$B:$B,Multiples!O:O),"") -> 2.6505838 | P46: =IFERROR(_xlfn.XLOOKUP($K46,Multiples!$B:$B,Multiples!P:P),"") -> 2.1318633 | Q46: =IFERROR(_xlfn.XLOOKUP($K46,Multiples!$B:$B,Multiples!Q:Q),"") -> 1.9413015 | R46: =IFERROR(_xlfn.XLOOKUP($K46,Multiples!$B:$B,Multiples!R:R),"") -> 2.054483 | T46: . | U46: J.P. Morgan Asset Management | V46: 0.0099
K47: Total Debt / Capital | N47: =IFERROR(_xlfn.XLOOKUP($K47,Multiples!$B:$B,Multiples!N:N),"") -> 0.99959245 | O47: =IFERROR(_xlfn.XLOOKUP($K47,Multiples!$B:$B,Multiples!O:O),"") -> 0.99962287 | P47: =IFERROR(_xlfn.XLOOKUP($K47,Multiples!$B:$B,Multiples!P:P),"") -> 0.99953115 | Q47: =IFERROR(_xlfn.XLOOKUP($K47,Multiples!$B:$B,Multiples!Q:Q),"") -> 0.66001445 | R47: =IFERROR(_xlfn.XLOOKUP($K47,Multiples!$B:$B,Multiples!R:R),"") -> 0.67261236 | U47: Managed Account Advisors LLC | V47: 0.008
K48: Total Liabilities / Total Assets | N48: =IFERROR(_xlfn.XLOOKUP($K48,Multiples!$B:$B,Multiples!N:N),"") -> 0.82693094 | O48: =IFERROR(_xlfn.XLOOKUP($K48,Multiples!$B:$B,Multiples!O:O),"") -> 0.83279971 | P48: =IFERROR(_xlfn.XLOOKUP($K48,Multiples!$B:$B,Multiples!P:P),"") -> 0.80031347 | Q48: =IFERROR(_xlfn.XLOOKUP($K48,Multiples!$B:$B,Multiples!Q:Q),"") -> 0.78986954 | R48: =IFERROR(_xlfn.XLOOKUP($K48,Multiples!$B:$B,Multiples!R:R),"") -> 0.78986954
K49: Total Debt / EBITDA | N49: =IFERROR(_xlfn.XLOOKUP($K49,Multiples!$B:$B,Multiples!N:N),"") -> 6.275866 | O49: =IFERROR(_xlfn.XLOOKUP($K49,Multiples!$B:$B,Multiples!O:O),"") -> 6.1443811 | P49: =IFERROR(_xlfn.XLOOKUP($K49,Multiples!$B:$B,Multiples!P:P),"") -> 6.2623535 | Q49: =IFERROR(_xlfn.XLOOKUP($K49,Multiples!$B:$B,Multiples!Q:Q),"") -> 4.3165375 | R49: =IFERROR(_xlfn.XLOOKUP($K49,Multiples!$B:$B,Multiples!R:R),"") -> 4.3821469 | U49: Board of Directors
K50: Total Debt / (EBITDA - Capex) | N50: =IFERROR(_xlfn.XLOOKUP($K50,Multiples!$B:$B,Multiples!N:N),"") -> 6.935949 | O50: =IFERROR(_xlfn.XLOOKUP($K50,Multiples!$B:$B,Multiples!O:O),"") -> 6.5860653 | P50: =IFERROR(_xlfn.XLOOKUP($K50,Multiples!$B:$B,Multiples!P:P),"") -> 6.48916 | Q50: =IFERROR(_xlfn.XLOOKUP($K50,Multiples!$B:$B,Multiples!Q:Q),"") -> 4.6383897 | R50: =IFERROR(_xlfn.XLOOKUP($K50,Multiples!$B:$B,Multiples!R:R),"") -> 4.6352666 | U50: A. Krishna (Chairman, CEO 2020–pres.) [Non-Indep.]. M. Brown [Indep.], Audit. T. Buberl [Indep.], Exec. Comp. D. Farr [Indep.], Audit. A. Gorsky (Lead Dir. 2021–pres.) [Indep.], Exec. M. Howard [Indep.], Audit. A. Liveris [Indep.], Chair Gov. F. McNabb [Indep.], Chair Audit. M. Miebach [Indep.], Gov. M. Pollack [Indep.], Exec. Comp. P. Voser [Indep.], Audit. F. Waddell [Indep.], Chair Comp. A. Zollar [Indep.], Gov.
K51: Net Debt / EBITDA | N51: =IFERROR(_xlfn.XLOOKUP($K50,Multiples!$B:$B,Multiples!N:N),"") -> 6.935949 | O51: =IFERROR(_xlfn.XLOOKUP($K50,Multiples!$B:$B,Multiples!O:O),"") -> 6.5860653 | P51: =IFERROR(_xlfn.XLOOKUP($K50,Multiples!$B:$B,Multiples!P:P),"") -> 6.48916 | Q51: =IFERROR(_xlfn.XLOOKUP($K50,Multiples!$B:$B,Multiples!Q:Q),"") -> 4.6383897 | R51: =IFERROR(_xlfn.XLOOKUP($K50,Multiples!$B:$B,Multiples!R:R),"") -> 4.6352666
K53: Solvency Ratios | N53: 2022 | O53: =+N53+1 -> 2023 | P53: =+O53+1 -> 2024 | Q53: =+P53+1 -> 2025 | R53: =+Q53+1 -> 2026
K54: EBIT / Interest Expense | N54: =IFERROR(_xlfn.XLOOKUP($K54,Multiples!$B:$B,Multiples!N:N),"") -> 6.7228618 | O54: =IFERROR(_xlfn.XLOOKUP($K54,Multiples!$B:$B,Multiples!O:O),"") -> 5.8382078 | P54: =IFERROR(_xlfn.XLOOKUP($K54,Multiples!$B:$B,Multiples!P:P),"") -> 5.4795561 | Q54: =IFERROR(_xlfn.XLOOKUP($K54,Multiples!$B:$B,Multiples!Q:Q),"") -> N/A | R54: =IFERROR(_xlfn.XLOOKUP($K54,Multiples!$B:$B,Multiples!R:R),"") -> 0
K55: EBITDA / Interest Expense | N55: =IFERROR(_xlfn.XLOOKUP($K55,Multiples!$B:$B,Multiples!N:N),"") -> 10.671875 | O55: =IFERROR(_xlfn.XLOOKUP($K55,Multiples!$B:$B,Multiples!O:O),"") -> 8.5737399 | P55: =IFERROR(_xlfn.XLOOKUP($K55,Multiples!$B:$B,Multiples!P:P),"") -> 8.2056075 | Q55: =IFERROR(_xlfn.XLOOKUP($K55,Multiples!$B:$B,Multiples!Q:Q),"") -> 7.8788489 | R55: =IFERROR(_xlfn.XLOOKUP($K55,Multiples!$B:$B,Multiples!R:R),"") -> 7.7774448
K56: (EBITDA - Capex) / Interest Expense | N56: =IFERROR(_xlfn.XLOOKUP($K56,Multiples!$B:$B,Multiples!N:N),"") -> 11.6875 | O56: =IFERROR(_xlfn.XLOOKUP($K56,Multiples!$B:$B,Multiples!O:O),"") -> 9.1487243 | P56: =IFERROR(_xlfn.XLOOKUP($K56,Multiples!$B:$B,Multiples!P:P),"") -> 8.4924065 | Q56: =IFERROR(_xlfn.XLOOKUP($K56,Multiples!$B:$B,Multiples!Q:Q),"") -> 8.4255525 | R56: =IFERROR(_xlfn.XLOOKUP($K56,Multiples!$B:$B,Multiples!R:R),"") -> 8.2021505
D58: Debt Schedule | K58: Stock Performance
U60: ESG Traffic Light
U61: LSEG ESG Score | V61: =ESG!C14 -> 72
U62: E-Score | V62: =ESG!C15 -> 79
U63: S-Score | V63: =ESG!C16 -> 94
U64: G-Score | V64: =ESG!C17 -> 52
U65: S&P Global ESG Score | V65: =ESG!C18 -> 60
U66: Environmental | V66: =ESG!C19 -> 76
U67: Social | V67: =ESG!C20 -> 49
U68: Governance & Economic | V68: =ESG!C21 -> 60
U69: Sustainalytics | V69: =ESG!C22 -> 13,3
U70: ISS ESG Corporate Rating | V70: =ESG!C23 -> B
U71: SDG Impact Rating | V71: =ESG!C24 -> 4.2
U72: Governance Quality Score | V72: =ESG!C25 -> 7
U73: MSCI ESG Ratings | V73: =ESG!C26 -> AA
D80: Extra Notes

Sheet Segments
B2: Segments
B4: Regions | D4: Weight | E4: 2020 | F4: =+E4+1 -> 2021 | G4: =+F4+1 -> 2022 | H4: =+G4+1 -> 2023 | I4: =+H4+1 -> 2024 | J4: ="CAGR "&$G$4&" - "&$I$4 -> CAGR 2022 - 2024 | K4: 2021 | L4: =+K4+1 -> 2022 | M4: =+L4+1 -> 2023 | N4: =+M4+1 -> 2024
B6: United States of America | D6: =IFERROR(I6/SUM($I$6:$I$12),"") -> 0.41463737 | E6: 22258 | F6: 22893 | G6: 25098 | H6: 25309 | I6: 25098 | J6: =IFERROR((I6/G6)^(1/COUNT($G$4:$I$4))-1,"") -> 0 | K6: =IFERROR((F6-E6)/E6,"") -> 0.028529068 | L6: =IFERROR((G6-F6)/F6,"") -> 0.096317652 | M6: =IFERROR((H6-G6)/G6,"") -> 0.0084070444 | N6: =IFERROR((I6-H6)/H6,"") -> -0.0083369552
B7: Other countries | D7: =IFERROR(I7/SUM($I$6:$I$12),"") -> 0.58536263 | E7: =5680+27241 -> 32921 | F7: =5648+28810 -> 34458 | G7: 25432 | H7: 36551 | I7: 35432 | J7: =IFERROR((I7/G7)^(1/COUNT($G$4:$I$4))-1,"") -> 0.11687624 | K7: =IFERROR((F7-E7)/E7,"") -> 0.046687525 | L7: =IFERROR((G7-F7)/F7,"") -> -0.26194207 | M7: =IFERROR((H7-G7)/G7,"") -> 0.4372051 | N7: =IFERROR((I7-H7)/H7,"") -> -0.030614757
D8: =IFERROR(I8/SUM($I$6:$I$12),"") -> 0 | J8: =IFERROR((I8/E8)^(1/COUNT($E$4:$I$4))-1,"") | K8: =IFERROR((F8-E8)/E8,"") | L8: =IFERROR((G8-F8)/F8,"") | M8: =IFERROR(H8-G8/G8,"") | N8: =IFERROR((I8-H8)/H8,"")
D9: =IFERROR(I9/SUM($I$6:$I$12),"") -> 0 | J9: =IFERROR((I9/E9)^(1/COUNT($E$4:$I$4))-1,"") | K9: =IFERROR((F9-E9)/E9,"") | L9: =IFERROR((G9-F9)/F9,"") | M9: =IFERROR(H9-G9/G9,"") | N9: =IFERROR((I9-H9)/H9,"")
D10: =IFERROR(I10/SUM($I$6:$I$12),"") -> 0 | J10: =IFERROR((I10/E10)^(1/COUNT($E$4:$I$4))-1,"") | K10: =IFERROR((F10-E10)/E10,"") | L10: =IFERROR((G10-F10)/F10,"") | M10: =IFERROR(H10-G10/G10,"") | N10: =IFERROR((I10-H10)/H10,"")
D11: =IFERROR(I11/SUM($I$6:$I$12),"") -> 0 | K11: =IFERROR((F11-E11)/E11,"") | L11: =IFERROR((G11-F11)/F11,"")
D12: =IFERROR(I12/SUM($I$6:$I$12),"") -> 0 | K12: =IFERROR((F12-E12)/E12,"") | L12: =IFERROR((G12-F12)/F12,"")
B13: Total | D13: =SUM(D6:D12) -> 1 | E13: =SUM(E6:E10) -> 55179 | F13: =SUM(F6:F10) -> 57351 | G13: =SUM(G6:G10) -> 50530 | H13: =SUM(H6:H10) -> 61860 | I13: =SUM(I6:I10) -> 60530 | J13: =IFERROR((I13/G13)^(1/COUNT($G$4:$I$4))-1,"") -> 0.062038984 | K13: =IFERROR((F13-E13)/E13,"") -> 0.039362801 | L13: =IFERROR((G13-F13)/F13,"") -> -0.11893428 | M13: =IFERROR((H13-G13)/G13,"") -> 0.22422323 | N13: =IFERROR((I13-H13)/H13,"") -> -0.021500162
B15: Segments | D15: Weight | E15: 2020 | F15: =+E15+1 -> 2021 | G15: =+F15+1 -> 2022 | H15: =+G15+1 -> 2023 | I15: =+H15+1 -> 2024 | J15: ="CAGR "&$E$4&" - "&$I$4 -> CAGR 2020 - 2024 | K15: 2021 | L15: =+K15+1 -> 2022 | M15: =+L15+1 -> 2023 | N15: =+M15+1 -> 2024
B17: Software | D17: =IFERROR(I17/SUM($I$17:$I$21),"") -> 0.43329067 | E17: 22927 | F17: 24141 | G17: 23629 | H17: 25011 | I17: 27085 | J17: =IFERROR((I17/E17)^(1/COUNT($E$4:$I$4))-1,"") -> 0.03389473 | K17: =IFERROR((F17-E17)/E17,"") -> 0.05295067 | L17: =IFERROR((G17-F17)/F17,"") -> -0.021208732 | M17: =IFERROR((H17-G17)/G17,"") -> 0.058487452 | N17: =IFERROR((I17-H17)/H17,"") -> 0.082923514
B18: Consulting | D18: =IFERROR(I18/SUM($I$17:$I$21),"") -> 0.33101904 | E18: 16257 | F18: 17844 | G18: 20058 | H18: 20884 | I18: 20692 | J18: =IFERROR((I18/E18)^(1/COUNT($E$4:$I$4))-1,"") -> 0.049427433 | K18: =IFERROR((F18-E18)/E18,"") -> 0.097619487 | L18: =IFERROR((G18-F18)/F18,"") -> 0.12407532 | M18: =IFERROR((H18-G18)/G18,"") -> 0.041180576 | N18: =IFERROR((I18-H18)/H18,"") -> -0.0091936411
B19: Infraestructure | D19: =IFERROR(I19/SUM($I$17:$I$21),"") -> 0.22428411 | E19: 14533 | F19: 14188 | G19: 15288 | H19: 14593 | I19: 14020 | J19: =IFERROR((I19/E19)^(1/COUNT($E$4:$I$4))-1,"") -> -0.0071616412 | K19: =IFERROR((F19-E19)/E19,"") -> -0.023739077 | L19: =IFERROR((G19-F19)/F19,"") -> 0.077530307 | M19: =IFERROR((H19-G19)/G19,"") -> -0.045460492 | N19: =IFERROR((I19-H19)/H19,"") -> -0.039265401
B20: Financing | D20: =IFERROR(I20/SUM($I$17:$I$21),"") -> 0.011406175 | E20: 975 | F20: 774 | G20: 645 | H20: 741 | I20: 713 | J20: =IFERROR((I20/E20)^(1/COUNT($E$4:$I$4))-1,"") -> -0.060672617 | K20: =IFERROR((F20-E20)/E20,"") -> -0.20615385 | L20: =IFERROR((G20-F20)/F20,"") -> -0.16666667 | M20: =IFERROR((H20-G20)/G20,"") -> 0.14883721 | N20: =IFERROR((I20-H20)/H20,"") -> -0.037786775
D21: =IFERROR(I21/SUM($I$17:$I$21),"") -> 0 | J21: =IFERROR((I21/E21)^(1/COUNT($E$4:$I$4))-1,"") | K21: =IFERROR((F21-E21)/E21,"") | L21: =IFERROR((G21-F21)/F21,"") | M21: =IFERROR((H21-G21)/G21,"") | N21: =IFERROR((I21-H21)/H21,"")
B22: Total | D22: =SUM(D17:D21) -> 1 | E22: =SUM(E17:E21) -> 54692 | F22: =SUM(F17:F21) -> 56947 | G22: =SUM(G17:G21) -> 59620 | H22: =SUM(H17:H21) -> 61229 | I22: =SUM(I17:I21) -> 62510 | J22: =IFERROR((I22/E22)^(1/COUNT($E$4:$I$4))-1,"") -> 0.027082049 | K22: =IFERROR((F22-E22)/E22,"") -> 0.041230893 | L22: =IFERROR((G22-F22)/F22,"") -> 0.046938381 | M22: =IFERROR((H22-G22)/G22,"") -> 0.026987588 | N22: =IFERROR((I22-H22)/H22,"") -> 0.020921459
B24: Categories | D24: Description | J24: Graphs
B26: Software | D26: IBM Software segment englobes, the hybrid cloud, data and AI, automation, transaction processind and security.
B27: Consulting | D27: Many of the clients need expertise, not only in the software in wich are interested but also digital transformation and cloud modernization.
B28: Infraestructure | D28: IBM infrustructure revenue is based on high tech hardware capable of run all the cutting edge software.
B30: =IF(B21=0,"",B21)
B32: Products | D32: Weight | E32: 2020 | F32: =+E32+1 -> 2021 | G32: =+F32+1 -> 2022 | H32: =+G32+1 -> 2023 | I32: =+H32+1 -> 2024 | J32: =I32+1 -> 2025 | K32: =+J32+1 -> 2026 | L32: =+K32+1 -> 2027 | M32: =+L32+1 -> 2028 | N32: =+M32+1 -> 2029 | O32: =+N32+1 -> 2030 | P32: =+O32+1 -> 2031 | Q32: =+P32+1 -> 2032 | R32: =+Q32+1 -> 2033 | S32: =+R32+1 -> 2034
B34: =Sheet1!B60 -> Software | D34: =IFERROR(I34/$I$22,"") -> 0.43329067 | E34: =Sheet1!C62 -> 22124 | F34: =Sheet1!D62 -> 23426 | G34: =Sheet1!F62 -> 23629 | H34: =Sheet1!G62 -> 25011 | I34: =Sheet1!H62 -> 27085 | J34: =I34*(1+J35) -> 29362.139 | K34: =J34*(1+K35) -> 31928.673 | L34: =K34*(1+L35) -> 34846.981 | M34: =L34*(1+M35) -> 38151.446 | N34: =M34*(1+N35) -> 41900.013 | O34: =N34*(1+O35) -> 46131.77 | P34: =O34*(1+P35) -> 50474.729 | Q34: =P34*(1+Q35) -> 54880.587 | ... S34: =R34*(1+S35) -> 63657.805
B35: growth | F35: =(F34-E34)/E34 -> 0.058850118 | G35: =(G34-F34)/F34 -> 0.0086655852 | H35: =(H34-G34)/G34 -> 0.058487452 | I35: =(I34-H34)/H34 -> 0.082923514 | J35: =Sheet1!I61 -> 0.084073816 | K35: =Sheet1!J61 -> 0.087409629 | L35: =Sheet1!K61 -> 0.091400849 | M35: =Sheet1!L61 -> 0.094827881 | N35: =Sheet1!M61 -> 0.098254914 | O35: =Sheet1!N61 -> 0.10099654 | P35: =Sheet1!O61 -> 0.094142475 | Q35: =Sheet1!P61 -> 0.08728841 | ... S35: =Sheet1!R61 -> 0.07358028
B36: =" "&Sheet1!B5 -> Hybrid Platform & Solutions | D36: =IFERROR(I36/$I$34,"") -> 0.6944065 | E36: =Sheet1!R5 -> 15518 | F36: =Sheet1!O5 -> 17036 | G36: =Sheet1!I5 -> 16458 | H36: =Sheet1!F5 -> 17396 | I36: =Sheet1!C5 -> 18808 | J36: =I36*(1+J37) -> 20594.76 | K36: =J36*(1+K37) -> 22654.236 | L36: =K36*(1+L37) -> 25055.585 | M36: =L36*(1+M37) -> 27836.755 | N36: =M36*(1+N37) -> 31065.819 | O36: =N36*(1+O37) -> 34793.717 | P36: =O36*(1+P37) -> 38621.026 | Q36: =P36*(1+Q37) -> 42483.128 | ... S36: =R36*(1+S37) -> 50011.138
B37: growth | F37: =IFERROR((F36-E36)/E36,"") -> 0.097821884 | G37: =IFERROR((G36-F36)/F36,"") -> -0.033928152 | H37: =IFERROR((H36-G36)/G36,"") -> 0.056993559 | I37: =IFERROR((I36-H36)/H36,"") -> 0.081168085 | J37: =Sheet1!V4 -> 0.095 | K37: =Sheet1!W4 -> 0.1 | L37: =Sheet1!X4 -> 0.106 | M37: =Sheet1!Y4 -> 0.111 | N37: =Sheet1!Z4 -> 0.116 | O37: =Sheet1!AA4 -> 0.12 | P37: =Sheet1!AB4 -> 0.11 | Q37: =Sheet1!AC4 -> 0.1 | ... S37: =Sheet1!AE4 -> 0.08
B38: =" "&Sheet1!B6 -> Transaction Processing | D38: =IFERROR(I38/$I$34,"") -> 0.3055935 | E38: =Sheet1!R6 -> 6606 | F38: =Sheet1!O6 -> 6390 | G38: =Sheet1!I6 -> 7171 | H38: =Sheet1!F6 -> 7615 | I38: =Sheet1!C6 -> 8277 | J38: =I38*(1+J39) -> 8770.2562 | K38: =J38*(1+K39) -> 9292.9074 | L38: =K38*(1+L39) -> 9846.7052 | M38: =L38*(1+M39) -> 10433.506 | N38: =M38*(1+N39) -> 11055.276 | O38: =N38*(1+O39) -> 11714.1 | P38: =O38*(1+P39) -> 12412.185 | Q38: =P38*(1+Q39) -> 13151.872 | ... S38: =R38*(1+S39) -> 14766.114
B39: growth | F39: =IFERROR((F38-E38)/E38,"") -> -0.032697548 | G39: =IFERROR((G38-F38)/F38,"") -> 0.12222222 | H39: =IFERROR((H38-G38)/G38,"") -> 0.061916051 | I39: =IFERROR((I38-H38)/H38,"") -> 0.086933684 | J39: =Sheet1!$V$6 -> 0.059593602 | K39: =Sheet1!$V$6 -> 0.059593602 | L39: =Sheet1!$V$6 -> 0.059593602 | M39: =Sheet1!$V$6 -> 0.059593602 | N39: =Sheet1!$V$6 -> 0.059593602 | O39: =Sheet1!$V$6 -> 0.059593602 | P39: =Sheet1!$V$6 -> 0.059593602 | Q39: =Sheet1!$V$6 -> 0.059593602 | ... S39: =Sheet1!$V$6 -> 0.059593602
B40: =Sheet1!B54 -> Consulting | D40: =IFERROR(I40/$I$22,"") -> 0.33101904 | E40: =Sheet1!C56 -> 16257 | F40: =Sheet1!D56 -> 17844 | G40: =Sheet1!F56 -> 20058 | H40: =Sheet1!G56 -> 20884 | I40: =Sheet1!H56 -> 20692 | J40: =I40*(1+J41) -> 21105.84 | K40: =J40*(1+K41) -> 21739.015 | L40: =K40*(1+L41) -> 22608.576 | M40: =L40*(1+M41) -> 23739.005 | N40: =M40*(1+N41) -> 24925.955 | O40: =N40*(1+O41) -> 26172.253 | P40: =O40*(1+P41) -> 27480.865 | Q40: =P40*(1+Q41) -> 28854.908 | ... S40: =R40*(1+S41) -> 31812.537
B41: growth | F41: =IFERROR((F40-E40)/E40,"") -> 0.097619487 | G41: =IFERROR((G40-F40)/F40,"") -> 0.12407532 | H41: =IFERROR((H40-G40)/G40,"") -> 0.041180576 | I41: =IFERROR((I40-H40)/H40,"") -> -0.0091936411 | J41: =Sheet1!I55 -> 0.02 | K41: =Sheet1!J55 -> 0.03 | L41: =Sheet1!K55 -> 0.04 | M41: =Sheet1!L55 -> 0.05 | N41: =Sheet1!M55 -> 0.05 | O41: =Sheet1!N55 -> 0.05 | P41: =Sheet1!O55 -> 0.05 | Q41: =Sheet1!P55 -> 0.05 | ... S41: =Sheet1!R55 -> 0.05
B42: =Sheet1!B57 -> Infrastructure | D42: =IFERROR(I42/$I$22,"") -> 0.22428411 | E42: =Sheet1!C59 -> 14533 | F42: =Sheet1!D59 -> 14188 | G42: =Sheet1!E59 -> 15288 | H42: =Sheet1!G59 -> 14593 | I42: =Sheet1!H59 -> 14020 | J42: =I42*(1+J43) -> 14648.096 | K42: =J42*(1+K43) -> 14500 | L42: =K42*(1+L43) -> 14000 | M42: =L42*(1+M43) -> 14630 | N42: =M42*(1+N43) -> 14500 | O42: =N42*(1+O43) -> 14000 | P42: =O42*(1+P43) -> 14630 | Q42: =P42*(1+Q43) -> 14500 | ... S42: =R42*(1+S43) -> 14630
B43: growth | F43: =IFERROR((F42-E42)/E42,"") -> -0.023739077 | G43: =IFERROR((G42-F42)/F42,"") -> 0.077530307 | H43: =IFERROR((H42-G42)/G42,"") -> -0.045460492 | I43: =IFERROR((I42-H42)/H42,"") -> -0.039265401 | J43: =Sheet1!I58 -> 0.0448 | K43: =Sheet1!J58 -> -0.010110256 | L43: =Sheet1!K58 -> -0.034482759 | M43: =Sheet1!L58 -> 0.045 | N43: =Sheet1!M58 -> -0.008885851 | O43: =Sheet1!N58 -> -0.034482759 | P43: =Sheet1!O58 -> 0.045 | Q43: =Sheet1!P58 -> -0.008885851 | ... S43: =Sheet1!R58 -> 0.045
B44: =Sheet1!B63 -> Financing | D44: =IFERROR(I44/$I$22,"") -> 0.011406175 | E44: =Sheet1!C63 -> 975 | F44: =Sheet1!D63 -> 774 | G44: =Sheet1!E63 -> 645 | H44: =Sheet1!G63 -> 741 | I44: =Sheet1!H63 -> 713 | J44: =I44*(1+J45) -> 666.33948 | K44: =J44*(1+K45) -> 646.17293 | L44: =K44*(1+L45) -> 648.65152 | M44: =L44*(1+M45) -> 627.62578 | N44: =M44*(1+N45) -> 608.12451 | O44: =N44*(1+O45) -> 594.45465 | P44: =O44*(1+P45) -> 582.24916 | Q44: =P44*(1+Q45) -> 566.74722 | ... S44: =R44*(1+S45) -> 539.38303
B45: growth | J45: =Sheet1!I64 -> -0.06544252 | K45: =Sheet1!J64 -> -0.030264688 | L45: =Sheet1!K64 -> 0.0038358068 | M45: =Sheet1!L64 -> -0.032414544 | N45: =Sheet1!M64 -> -0.031071486 | O45: =Sheet1!N64 -> -0.022478728 | P45: =Sheet1!O64 -> -0.020532238 | Q45: =Sheet1!P64 -> -0.026624249 | ... S45: =Sheet1!R64 -> -0.023702972
B46: Total | D46: =SUM(D34+D40+D42+D44) -> 1 | E46: =E34+E40+E42+E44 -> 53889 | F46: =F34+F40+F42+F44 -> 56232 | G46: =G34+G40+G42+G44 -> 59620 | H46: =H34+H40+H42+H44 -> 61229 | I46: =I34+I40+I42+I44 -> 62510 | J46: =I46*(1+J47) -> 65677.103 | K46: =J46*(1+K47) -> 68597.198 | L46: =K46*(1+L47) -> 71824.997 | M46: =L46*(1+M47) -> 76849.334 | N46: =M46*(1+N47) -> 81616.817 | O46: =N46*(1+O47) -> 86561.978 | P46: =O46*(1+P47) -> 92807.067 | Q46: =P46*(1+Q47) -> 98419.649 | ... S46: =R46*(1+S47) -> 110211.29
J47: =Sheet1!I67 -> 0.050665542 | K47: =Sheet1!J67 -> 0.044461383 | L47: =Sheet1!K67 -> 0.047054391 | M47: =Sheet1!L67 -> 0.069952483 | N47: =Sheet1!M67 -> 0.062036751 | O47: =Sheet1!N67 -> 0.06058997 | P47: =Sheet1!O67 -> 0.072145869 | Q47: =Sheet1!P67 -> 0.060475803 | ... S47: =Sheet1!R67 -> 0.062362286
B48: Company's Strategy / Extra Notes
B50: Decline of revenue from Japan | D50: Eventhough the table does not show it, it must be noted that japanese clients, until 2021, represented at least 10% of the company revenue. Therefore being the second biggest country for IBM, just behind USA.
B51: Adapting AI to the clients needs | D51: IBM has, after consulting the feedback of their clients, developped AI tools "Apache 2.0" that was specially thougt to respond to their needs. By doing this they are offering cheaper specialized services that outperform the alternatives.
B52: R&D investment | D52: The company has invested highly in AI and emerging techonolgies in order to stand out in the market as a leader in inovation.

Sheet Industry
B2: Industry Overview
B4: Sales Growth Forecast | E4: Weight | F4: 2025 | G4: =+F4+1 -> 2026 | H4: =+G4+1 -> 2027 | I4: =+H4+1 -> 2028 | J4: =+I4+1 -> 2029 | K4: =+J4+1 -> 2030 | L4: =+K4+1 -> 2031 | M4: =+L4+1 -> 2032 | N4: =+M4+1 -> 2033 | ... P4: =+O4+1 -> 2035 | Q4: ="CAGR "&$F$4&" - "&$P$4 -> CAGR 2025 - 2035 | R4: Sources
B6: AI services | Q6: 0.266 | R6: Statista
B7: Hybrid Cloud | Q7: 0.174 | R7: Allied Market Research
B8: Weighted Average | E8: =SUM(E6:E7) -> 0 | F8: =SUMPRODUCT(F6:F7,$E$6:$E$7) -> 0 | G8: =SUMPRODUCT(G6:G7,$E$6:$E$7) -> 0 | H8: =SUMPRODUCT(H6:H7,$E$6:$E$7) -> 0 | I8: =SUMPRODUCT(I6:I7,$E$6:$E$7) -> 0 | J8: =SUMPRODUCT(J6:J7,$E$6:$E$7) -> 0 | K8: =SUMPRODUCT(K6:K7,$E$6:$E$7) -> 0 | L8: =SUMPRODUCT(L6:L7,$E$6:$E$7) -> 0 | M8: =SUMPRODUCT(M6:M7,$E$6:$E$7) -> 0 | ... P8: =SUMPRODUCT(P6:P7,$E$6:$E$7) -> 0 | Q8: =IFERROR(((1+F8)*(1+G8)*(1+H8)*(1+I8)*(1+J8)*(1+K8)*(1+L8)*(1+M8)*(1+N8)*(1+O8)*(1+P8))^(1/COUNT($F$4:$P$4))-1,"") -> 0
B10: Key Drivers | E10: Description
B12: Hybrid Cloud & AI Leadership | E12: IBM has articulated a clear strategy to dominate the hybrid cloud and AI market by integrating its Red Hat OpenShift platform with AI-driven services. This approach caters to enterprises seeking seamless on-premises and multicloud solutions, positioning IBM as a one-stop provider for complex, regulated industries.
B13: Leadership in Quantum & Emerging Technologies | E13: Quantum computing is the result of fisics applied to computing and allows machine learning not only cheapper but mainly faster. IBM Quantum Roadmap is the example of the company's lead in this area and plans to keep up with the high investment in R&D in order to keep this positioning.
B14: Shift to Recurring Revenue & Software Mix | E14: Switching form hardware to software provide greater revenue visibility and more stable free cash flow to fund innovation and strategic investments and increasing operating margin.
B17: Industry Trends | E17: Description
B19: Policies on AI development | E19: All around the world the Artificial intelifgence has been considered guilty of spreading misinformation and being a threat to the world. This resulted in governments applying strict regulations to the develpment of this type of technology (eg. European AI Office)
B20: Trade war threat | E20: With the applience of tariffs by USA and China on eachother products, it is not certain the outcome but the technology sector has so far been hit harshly. Therefore, the fear of the worstning of the situation might limit the short term development of companies like IBM.
B23: Market Share | E23: Headquarters | G23: Revenues | H23: (in MM of USD) | I23: Market Share
B25: {=+_FV(DCF!R4,"Name")} -> INTERNATIONAL BUSINESS MACHINES CORPORATION | E25: #VALUE! | G25: {=TRANSPOSE(Peers!D97:N97)} -> 62753 | I25: =IFERROR(G25/$G$37,"") -> 0.041835333
B26: =Peers!E$91 -> #VALUE! | E26: #VALUE! | G26: 64896.5 | I26: =IFERROR(G26/$G$37,"") -> 0.043264333
B27: =Peers!F91 -> #VALUE! | E27: #VALUE! | G27: 22096 | I27: =IFERROR(G27/$G$37,"") -> 0.014730667
B28: =Peers!G91 -> #VALUE! | E28: #VALUE! | G28: 245122 | I28: =IFERROR(G28/$G$37,"") -> 0.16341467
B29: =Peers!H91 -> #VALUE! | E29: #VALUE! | G29: 52961 | I29: =IFERROR(G29/$G$37,"") -> 0.035307333
B30: =Peers!I91 -> #VALUE! | E30: #VALUE! | G30: 30127 | I30: =IFERROR(G30/$G$37,"") -> 0.020084667
B31: =Peers!J91 -> #VALUE! | E31: #VALUE! | G31: 43073 | I31: =IFERROR(G31/$G$37,"") -> 0.028715333
B32: =Peers!K91 -> #VALUE! | E32: #VALUE! | G32: 10790 | I32: =IFERROR(G32/$G$37,"") -> 0.0071933333
B33: {=+_FV(Peers!A15,"Name")} -> #VALUE! | G33: 0 | I33: =IFERROR(G33/$G$37,"") -> 0
B34: {=+_FV(Peers!A16,"Name")} -> #VALUE! | G34: 0 | I34: =IFERROR(G34/$G$37,"") -> 0
B35: {=+_FV(Peers!A17,"Name")} -> #VALUE! | G35: 0 | I35: =IFERROR(G35/$G$37,"") -> 0
B36: Others | E36: -- | G36: =G37-SUM(G25:G35) -> 968181.5 | I36: =IFERROR(G36/$G$37,"") -> 0.64545433
B37: Industry Size | E37: -- | G37: 1500000 | I37: 1
B39: Porter's Five Forces Analysis | E39: Rating | H39: Graph
B41: Threat of New Entrants | E41: =IFERROR(AVERAGE(E42:E47),"") -> 2.8333333
B42: Economies of scale | E42: 4
B43: Product differentiation | E43: 3
B44: Capital requirements | E44: 3
B45: Access to distribution channels | E45: 2
B46: Regulations | E46: 2
B47: Switching costs | E47: 3
B48: Bargaining Power of Suppliers | E48: =IFERROR(AVERAGE(E49:E53),"") -> 4.4
B49: Number of suppliers | E49: 5
B50: Uniqueness | E50: 4
B51: Switching Costs | E51: 4
B52: Forward Integration | E52: 4
B53: Industry Importance | E53: 5
B54: Bargaining Power of Customers | E54: =IFERROR(AVERAGE(E55:E59),"") -> 4
B55: Number of buyers | E55: 5
B56: Purchase size | E56: 4
B57: Switching costs | E57: 4
B58: Price sensitivity | E58: 3
B59: Informed buyers | E59: 4
B60: Competitive Rivalry | E60: =IFERROR(AVERAGE(E61:E65),"") -> 4.2
B61: Number of competitors | E61: 4
B62: Industry growth | E62: 5
B63: Similarities in what's offered | E63: 4
B64: Exit barriers | E64: 3
B65: Fixed costs | E65: 5
B66: Threat of Substitutes | E66: =IFERROR(AVERAGE(E67:E71),"") -> 3.5
B67: Relative price performance | E67: 4
B68: Customer willingness to go elsewhere | E68: 3
B69: The sense that products are similar | E69: 3
B70: Availability of close substitutes | E70: 4

Sheet Peers
D3: Revenue Growth | F3: EBITDA Margin | H3: Profit Margin | J3: EV / Revenue | L3: EV / EBITDA | N3: Price / Earnings
B4: Peers | C4: Ticker | D4: =+Inputs!O4&"-"&Inputs!P4 -> 2022-2023 | E4: =+Inputs!P4&"-"&Inputs!Q4 -> 2023-2024 | F4: 2023 | G4: 2024 | H4: =+Inputs!O4&"-"&Inputs!P4 -> 2022-2023 | I4: =+Inputs!P4&"-"&Inputs!Q4 -> 2023-2024 | J4: 2023 | K4: 2024 | L4: 2023 | M4: 2024 | N4: 2023 | O4: 2024
A6: =+D91 -> #VALUE! | B6: {=IFERROR(_FV(A6,"Name"),"")} -> INTERNATIONAL BUSINESS MACHINES CORPORATION | C6: {=IFERROR(_FV(A6,"Ticker symbol",TRUE),"")} -> IBM | D6: =IFERROR(D94/D93-1,"") -> 0.021972576 | E6: =IFERROR(D97/D94-1,"") -> 0.014435823 | F6: =IFERROR(D95/D94,"") -> 0.22272874 | G6: =IFERROR(D100/D97,"") -> 0.22386181 | H6: =IFERROR(D96/D94,"") -> 0.12145167 | I6: =IFERROR(D105/D97,"") -> 0.095867927 | J6: {=IFERROR((_FV(A6,"Market cap",TRUE)/1000000+D$121-D$111)/D$94,"")} -> 5.5391003 | K6: {=IFERROR((_FV(A6,"Market cap",TRUE)/1000000+D$121-D$111)/D$97,"")} -> 5.4602767 | L6: {=+IFERROR((_FV(A6,"Market cap",TRUE)/1000000+D$121-D$111)/D$95,"")} -> 24.869266 | M6: {=IFERROR((_FV(A6,"Market cap",TRUE)/1000000+D$121-D$111)/D$100,"")} -> 24.391283 | N6: {=IFERROR((_FV(A6,"Market cap",TRUE)/1000000)/D$96,"")} -> 35.754319 | O6: {=IFERROR((_FV(A6,"Market cap",TRUE)/1000000)/D$105,"")} -> 44.651297
A8: =+E91 -> #VALUE! | B8: {=IFERROR(_FV(A8,"Nome"),"")} -> ACCENTURE PUBLIC LIMITED COMPANY | C8: {=+IFERROR(_FV(A8,"Símbolo do ticker",TRUE),"")} -> ACN | D8: =+IFERROR(E94/E93-1,"") -> 0.040870665 | E8: =IFERROR(E97/E94-1,"") -> 0.012241135 | F8: =IFERROR(E95/E94,"") -> 0.20285065 | G8: =+IFERROR(E100/E97,"") -> 0.19882582 | H8: =IFERROR(E96/E94,"") -> 0.10718168 | I8: =+IFERROR(D105/D99,"") -> 0.16921692 | J8: {=+IFERROR((_FV(A8,"Capitalização de mercado",TRUE)/1000000+E$121-E$111)/E$94,"")} -> 2.3695238 | K8: {=IFERROR(+(_FV(A8,"Capitalização de mercado",TRUE)/1000000+E$121-E$111)/E$97,"")} -> 2.3408689 | L8: {=IFERROR(+(_FV(A8,"Capitalização de mercado",TRUE)/1000000+E$121-E$111)/E$95,"")} -> 11.681125 | M8: {=IFERROR(+(_FV(A8,"Capitalização de mercado",TRUE)/1000000+E$121-E$111)/E$100,"")} -> 11.773465 | N8: {=IFERROR(+(_FV(A8,"Capitalização de mercado",TRUE)/1000000)/E$96,"")} -> 22.23619 | O8: {=IFERROR(+(_FV(A8,"Capitalização de mercado",TRUE)/1000000)/E$105,"")} -> 21.032678
A9: =+F91 -> #VALUE! | B9: {=IFERROR(_FV(A9,"Nome"),"")} -> Capgemini | C9: {=+IFERROR(_FV(A9,"Símbolo do ticker",TRUE),"")} -> CAPMF | D9: =IFERROR(F94/F93-1,"") -> 0.023959991 | E9: =IFERROR(+F97/F94-1,"") -> -0.018914839 | F9: =IFERROR(F95/F94,"") -> 0.14692301 | G9: =IFERROR(F100/F97,"") -> 0.14613505 | H9: =IFERROR(F96/F94,"") -> 0.073838913 | I9: =+IFERROR(F105/F97,"") -> 0.075624547 | J9: {=+IFERROR((_FV(A9,"Capitalização de mercado",TRUE)/1000000+E$121-E$111)/E$94,"")} -> 0.3198906 | K9: {=IFERROR(+(_FV(A9,"Capitalização de mercado",TRUE)/1000000+E$121-E$111)/E$97,"")} -> 0.31602213 | L9: {=IFERROR(+(_FV(A9,"Capitalização de mercado",TRUE)/1000000+E$121-E$111)/E$95,"")} -> 1.576976 | M9: {=IFERROR(+(_FV(A9,"Capitalização de mercado",TRUE)/1000000+E$121-E$111)/E$100,"")} -> 1.5894421 | N9: {=IFERROR(+(_FV(A9,"Capitalização de mercado",TRUE)/1000000)/E$96,"")} -> 3.1132094 | O9: {=IFERROR(+(_FV(A9,"Capitalização de mercado",TRUE)/1000000)/E$105,"")} -> 2.9447101
A10: =+G91 -> #VALUE! | B10: {=IFERROR(_FV(A10,"Nome"),"")} -> MICROSOFT CORPORATION | C10: {=+IFERROR(_FV(A10,"Símbolo do ticker",TRUE),"")} -> MSFT | D10: =+IFERROR(G94/G93-1,"") -> 0.068820296 | E10: =IFERROR(G97/G94-1,"") -> 0.15669962 | F10: =IFERROR(G95/G94,"") -> 0.50222967 | G10: =IFERROR(G100/G97,"") -> 0.55186805 | H10: =IFERROR(G96/G94,"") -> 0.34146238 | I10: =+IFERROR(G105/G97,"") -> 0.35955973 | J10: {=+IFERROR((_FV(A10,"Capitalização de mercado",TRUE)/1000000+E$121-E$111)/E$94,"")} -> 59.968227 | K10: {=IFERROR(+(_FV(A10,"Capitalização de mercado",TRUE)/1000000+E$121-E$111)/E$97,"")} -> 59.243025 | L10: {=IFERROR(+(_FV(A10,"Capitalização de mercado",TRUE)/1000000+E$121-E$111)/E$95,"")} -> 295.62748 | M10: {=IFERROR(+(_FV(A10,"Capitalização de mercado",TRUE)/1000000+E$121-E$111)/E$100,"")} -> 297.96444 | N10: {=IFERROR(+(_FV(A10,"Capitalização de mercado",TRUE)/1000000)/E$96,"")} -> 559.62934 | O10: {=IFERROR(+(_FV(A10,"Capitalização de mercado",TRUE)/1000000)/E$105,"")} -> 529.33997
A11: =+H91 -> #VALUE! | B11: {=IFERROR(_FV(A11,"Nome"),"")} -> ORACLE CORPORATION | C11: {=+IFERROR(_FV(A11,"Símbolo do ticker",TRUE),"")} -> ORCL | D11: =IFERROR(H94/H93-1,"") -> 0.17704995 | E11: =IFERROR(H97/H94-1,"") -> 0.06019538 | F11: =IFERROR(H95/H94,"") -> 0.41524202 | G11: =IFERROR(H100/H97,"") -> 0.44185344 | H11: =IFERROR(H96/H94,"") -> 0.1702166 | I11: =+IFERROR(H105/H102,"") -> 3.417238 | J11: {=+IFERROR((_FV(A11,"Capitalização de mercado",TRUE)/1000000+E$121-E$111)/E$94,"")} -> 12.709721 | K11: {=IFERROR(+(_FV(A11,"Capitalização de mercado",TRUE)/1000000+E$121-E$111)/E$97,"")} -> 12.556021 | L11: {=IFERROR(+(_FV(A11,"Capitalização de mercado",TRUE)/1000000+E$121-E$111)/E$95,"")} -> 62.655558 | M11: {=IFERROR(+(_FV(A11,"Capitalização de mercado",TRUE)/1000000+E$121-E$111)/E$100,"")} -> 63.150855 | N11: {=IFERROR(+(_FV(A11,"Capitalização de mercado",TRUE)/1000000)/E$96,"")} -> 118.70973 | O11: {=IFERROR(+(_FV(A11,"Capitalização de mercado",TRUE)/1000000)/E$105,"")} -> 112.28469
A12: =+I91 -> #VALUE! | B12: {=IFERROR(_FV(A12,"Nome"),"")} -> HEWLETT PACKARD ENTERPRISE COMPANY | C12: {=+IFERROR(_FV(A12,"Símbolo do ticker",TRUE),"")} -> HPE | D12: =+IFERROR(I94/I93-1,"") -> 0.0224242 | E12: =IFERROR(I97/I94-1,"") -> 0.034048395 | F12: =IFERROR(I95/I94,"") -> 0.18060752 | G12: =IFERROR(I100/I97,"") -> 0.17552362 | H12: =IFERROR(I96/I94,"") -> 0.069504033 | I12: =+IFERROR(I105/I97,"") -> 0.085604275 | J12: {=+IFERROR((_FV(A12,"Capitalização de mercado",TRUE)/1000000+E$121-E$111)/E$94,"")} -> 0.4889928 | K12: {=IFERROR(+(_FV(A12,"Capitalização de mercado",TRUE)/1000000+E$121-E$111)/E$97,"")} -> 0.48307936 | L12: {=IFERROR(+(_FV(A12,"Capitalização de mercado",TRUE)/1000000+E$121-E$111)/E$95,"")} -> 2.4106051 | M12: {=IFERROR(+(_FV(A12,"Capitalização de mercado",TRUE)/1000000+E$121-E$111)/E$100,"")} -> 2.4296611 | N12: {=IFERROR(+(_FV(A12,"Capitalização de mercado",TRUE)/1000000)/E$96,"")} -> 4.690925 | O12: {=IFERROR(+(_FV(A12,"Capitalização de mercado",TRUE)/1000000)/E$105,"")} -> 4.4370334
A13: =+J91 -> #VALUE! | B13: {=IFERROR(_FV(A13,"Nome"),"")} -> IONQ | C13: {=+IFERROR(_FV(A13,"Símbolo do ticker",TRUE),"")} -> IONQ | D13: =IFERROR(J94/J93-1,"") -> 0.98023538 | E13: =IFERROR(J97/J94-1,"") -> 0.95413302 | F13: =IFERROR(J95/J94,"") -> -6.6862807 | G13: =IFERROR(J100/J97,"") -> -4.9636896 | H13: =IFERROR(J96/J94,"") -> -7.1555688 | I13: =+IFERROR(J105/J97,"") -> -7.698281 | J13: {=+IFERROR((_FV(A13,"Capitalização de mercado",TRUE)/1000000+E$121-E$111)/E$94,"")} -> 0.3554646 | K13: {=IFERROR(+(_FV(A13,"Capitalização de mercado",TRUE)/1000000+E$121-E$111)/E$97,"")} -> 0.35116593 | L13: {=IFERROR(+(_FV(A13,"Capitalização de mercado",TRUE)/1000000+E$121-E$111)/E$95,"")} -> 1.7523464 | M13: {=IFERROR(+(_FV(A13,"Capitalização de mercado",TRUE)/1000000+E$121-E$111)/E$100,"")} -> 1.7661988 | N13: {=IFERROR(+(_FV(A13,"Capitalização de mercado",TRUE)/1000000)/E$96,"")} -> 3.4451132 | O13: {=IFERROR(+(_FV(A13,"Capitalização de mercado",TRUE)/1000000)/E$105,"")} -> 3.2586499
A14: =+K91 -> #VALUE! | B14: {=IFERROR(_FV(A14,"Nome"),"")} -> Rigetti | C14: {=+IFERROR(_FV(A14,"Símbolo do ticker",TRUE),"")} -> RGTI | D14: =IFERROR(K94/K93-1,"") -> -0.083498702 | E14: =IFERROR(K97/K94-1,"") -> -0.10143238 | F14: =+IFERROR(K95/K94,"") -> -5.1550633 | G14: =IFERROR(K100/K97,"") -> -6.3493976 | H14: =IFERROR(K96/K94,"") -> -6.2547468 | I14: =+IFERROR(K105/K97,"") -> -7.1616311 | J14: {=+IFERROR((_FV(A14,"Capitalização de mercado",TRUE)/1000000+E$121-E$111)/E$94,"")} -> 0.18876523 | K14: {=IFERROR(+(_FV(A14,"Capitalização de mercado",TRUE)/1000000+E$121-E$111)/E$97,"")} -> 0.18648248 | L14: {=IFERROR(+(_FV(A14,"Capitalização de mercado",TRUE)/1000000+E$121-E$111)/E$95,"")} -> 0.93056263 | M14: {=IFERROR(+(_FV(A14,"Capitalização de mercado",TRUE)/1000000+E$121-E$111)/E$100,"")} -> 0.93791879 | N14: {=IFERROR(+(_FV(A14,"Capitalização de mercado",TRUE)/1000000)/E$96,"")} -> 1.8898161 | O14: {=IFERROR(+(_FV(A14,"Capitalização de mercado",TRUE)/1000000)/E$105,"")} -> 1.7875317
A15: =+L91 -> PEER 8 | B15: {=IFERROR(_FV(A15,"Name"),"")} | C15: {=IFERROR(_FV(A15,"Ticker symbol",TRUE),"")} | D15: =+IFERROR(L94/L93,"") | E15: =IFERROR(L97/L94,"") | F15: =IFERROR(L95/L94,"") | G15: =IFERROR(L100/L97,"") | H15: =IFERROR(L96/L94,"") | I15: =+IFERROR(L105/L97,"") | J15: {=IFERROR(+(_FV(A15,"Market cap",TRUE)/1000000+L$121-L$111)/L$94,"")} | K15: {=IFERROR(+(_FV(A15,"Market cap",TRUE)/1000000+L$121-L$111)/L$97,"")} | L15: {=IFERROR(+(_FV(A15,"Market cap",TRUE)/1000000+L$121-L$111)/L$95,"")} | M15: {=IFERROR(+(_FV(A15,"Market cap",TRUE)/1000000+L$121-L$111)/L$100,"")} | N15: {=IFERROR(+(_FV(A15,"Market cap",TRUE)/1000000)/L$96,"")} | O15: {=IFERROR(+(_FV(A15,"Market cap",TRUE)/1000000)/L$105,"")}
A16: =+M91 -> PEER 9 | B16: {=IFERROR(_FV(A16,"Name"),"")} | C16: {=IFERROR(_FV(A16,"Ticker symbol",TRUE),"")} | D16: =IFERROR(M94/M93-1,"") | E16: =IFERROR(M97/M94-1,"") | F16: =IFERROR(M95/M94,"") | G16: =IFERROR(M100/M97,"") | H16: =IFERROR(M96/M94,"") | I16: =+IFERROR(M105/M97,"") | J16: {=IFERROR(+(_FV(A16,"Market cap",TRUE)/1000000+M$121-M$111)/M$94,"")} | K16: {=IFERROR(+(_FV(A16,"Market cap",TRUE)/1000000+M$121-M$111)/M$97,"")} | L16: {=IFERROR(+(_FV(A16,"Market cap",TRUE)/1000000+M$121-M$111)/M$95,"")} | M16: {=IFERROR(+(_FV(A16,"Market cap",TRUE)/1000000+M$121-M$111)/M$100,"")} | N16: {=IFERROR(+(_FV(A16,"Market cap",TRUE)/1000000)/M$96,"")} | O16: {=IFERROR(+(_FV(A16,"Market cap",TRUE)/1000000)/M$105,"")}
A17: =+N91 -> PEER 10 | B17: {=IFERROR(_FV(A17,"Name"),"")} | C17: {=+IFERROR(_FV(A17,"Ticker symbol",TRUE),"")} | D17: =IFERROR(N94/N93-1,"") | E17: =IFERROR(N97/N94-1,"") | F17: =IFERROR(N95/N94,"") | G17: =IFERROR(N100/N97,"") | H17: =IFERROR(N96/N94,"") | I17: =+IFERROR(N105/N97,"") | J17: {=IFERROR(+(_FV(A17,"Market cap",TRUE)/1000000+N$121-N$111)/N$94,"")} | K17: {=IFERROR(+(_FV(A17,"Market cap",TRUE)/1000000+N$121-N$111)/N$97,"")} | L17: {=IFERROR(+(_FV(A17,"Market cap",TRUE)/1000000+N$121-N$111)/N$95,"")} | M17: {=IFERROR(+(_FV(A17,"Market cap",TRUE)/1000000+N$121-N$111)/N$100,"")} | N17: {=IFERROR(+(_FV(A17,"Market cap",TRUE)/1000000)/N$96,"")} | O17: {=IFERROR(+(_FV(A17,"Market cap",TRUE)/1000000)/N$105,"")}
B18: Average | D18: =IFERROR(AVERAGE(D6:D17),"") -> 0.15647929 | E18: =IFERROR(AVERAGE(E6:E17),"") -> 0.13892577 | F18: =IFERROR(AVERAGE(F6:F17),"") -> -1.2713453 | G18: =IFERROR(AVERAGE(G6:G17),"") -> -1.1968774 | H18: =IFERROR(AVERAGE(H6:H17),"") -> -1.5658325 | I18: =IFERROR(AVERAGE(I6:I17),"") -> -1.3321001 | J18: =IFERROR(AVERAGE(J6:J17),"") -> 10.242461 | K18: =IFERROR(AVERAGE(K6:K17),"") -> 10.117118 | ... O18: =IFERROR(AVERAGE(O6:O17),"") -> 89.967069
B19: Deviation from Average | D19: =IFERROR(+D18-D6,"") -> 0.13450672 | E19: =IFERROR(E18-E6,"") -> 0.12448995 | F19: =+IFERROR(F18-F6,"") -> -1.494074 | G19: =IFERROR(G18-G6,"") -> -1.4207392 | H19: =IFERROR(+H6-H18,"") -> 1.6872842 | I19: =+IFERROR(I6-I18,"") -> 1.427968 | J19: =+IFERROR(J6-J18,"") -> -4.7033604 | K19: =+IFERROR(K6-K18,"") -> -4.656841 | L19: =IFERROR(+L6-L18,"") -> -25.318725 | M19: =IFERROR(M6-M18,"") -> -26.109125 | N19: =IFERROR(+N6-N18,"") -> -57.929262 | O19: =IFERROR(+O6-O18,"") -> -45.315773
D21: Trading Multiple | G21: Net | H21: Preferred | I21: Non-Controlling | J21: Equity Value | M21: Implied Upside (Downside)
B22: Implied Share Price | D22: Revenue | E22: EBITDA | F22: P/E | G22: Debt | H22: Stock | I22: Interest | J22: Revenue | K22: EBITDA | L22: P/E | M22: Revenue | N22: EBITDA | O22: P/E | P22: Current Price
B24: Second Minimum | D24: =IFERROR(SMALL(K6:K17,2),"") -> 0.31602213 | E24: =IFERROR(SMALL(M6:M17,2),"") -> 1.5894421 | F24: =IFERROR(SMALL(O6:O17,2),"") -> 2.9447101 | G24: =-Inputs!$Q$100+Inputs!$Q$101 -> 43805 | H24: =+Inputs!$Q$102 -> 0 | I24: =+Inputs!$Q$103 -> 86 | J24: =IFERROR(+D24*$D$97+G24+H24+I24,"") -> 63722.337 | K24: =IFERROR(E24*$D$100+G24+H24+I24,"") -> 66219.482 | L24: =IFERROR(F24*$D$105,"") -> 17715.376 | M24: {=IFERROR(+(J24/_FV($A$6,"Shares outstanding",TRUE)*1000000)/$P$24-1,"")} -> -0.76278082 | N24: {=IFERROR((+K24/_FV($A$6,"Shares outstanding",TRUE)*1000000)/$P$24-1,"")} -> -0.75348469 | O24: {=IFERROR(+(L24/_FV($A$6,"Shares outstanding",TRUE)*1000000)/$P$24-1,"")} -> -0.93405096 | P24: {=+_FV(A6,"Price")} -> 288.37
B25: Average | D25: =+IFERROR(AVERAGE(K6:K17),"") -> 10.117118 | E25: =IFERROR(+AVERAGE(M6:M17),"") -> 50.500408 | F25: =IFERROR(+AVERAGE(O6:O17),"") -> 89.967069 | G25: =-Inputs!$Q$100+Inputs!$Q$101 -> 43805 | H25: =+Inputs!$Q$102 -> 0 | I25: =+Inputs!$Q$103 -> 86 | J25: =IFERROR(+D25*$D$97+G25+H25+I25,"") -> 678770.49 | K25: =IFERROR(E25*$D$100+G25+H25+I25,"") -> 753320.74 | L25: =IFERROR(+F25*$D$105,"") -> 541241.89 | M25: {=IFERROR(+(J25/_FV($A$6,"Shares outstanding",TRUE)*1000000)/$P$24-1,"")} -> 1.5268593 | N25: {=IFERROR((+K25/_FV($A$6,"Shares outstanding",TRUE)*1000000)/$P$24-1,"")} -> 1.8043876 | O25: {=IFERROR(+(L25/_FV($A$6,"Shares outstanding",TRUE)*1000000)/$P$24-1,"")} -> 1.0148815
B26: Median | D26: =IFERROR(MEDIAN(K6:K17),"") -> 1.4119741 | E26: =IFERROR(MEDIAN(M6:M17),"") -> 7.1015632 | F26: =IFERROR(MEDIAN(O6:O17),"") -> 12.734856 | G26: =-Inputs!$Q$100+Inputs!$Q$101 -> 43805 | H26: =+Inputs!$Q$102 -> 0 | I26: =+Inputs!$Q$103 -> 86 | J26: =IFERROR(D26*$D$97+G26+H26+I26,"") -> 132496.61 | K26: =IFERROR(E26*$D$100+G26+H26+I26,"") -> 143653.76 | L26: =IFERROR(+F26*$D$105,"") -> 76612.892 | M26: {=IFERROR(+(J26/_FV($A$6,"Shares outstanding",TRUE)*1000000)/$P$24-1,"")} -> -0.50675477 | N26: {=IFERROR((+K26/_FV($A$6,"Shares outstanding",TRUE)*1000000)/$P$24-1,"")} -> -0.46522006 | O26: {=+IFERROR((L26/_FV($A$6,"Shares outstanding",TRUE)*1000000)/$P$24-1,"")} -> -0.71479314
B27: Second Maximum | D27: =IFERROR(LARGE(K6:K17,2),"") -> 12.556021 | E27: =IFERROR(LARGE(M6:M17,2),"") -> 63.150855 | F27: =IFERROR(LARGE(O6:O17,2),"") -> 112.28469 | G27: =-Inputs!$Q$100+Inputs!$Q$101 -> 43805 | H27: =+Inputs!$Q$102 -> 0 | I27: =+Inputs!$Q$103 -> 86 | J27: =IFERROR(+D27*$D$97+G27+H27+I27,"") -> 831818.97 | K27: =IFERROR(E27*$D$100+G27+H27+I27,"") -> 931034.21 | L27: =IFERROR(+F27*$D$105,"") -> 675504.68 | M27: {=IFERROR(+(J27/_FV($A$6,"Shares outstanding",TRUE)*1000000)/$P$24-1,"")} -> 2.096613 | N27: {=IFERROR((+K27/_FV($A$6,"Shares outstanding",TRUE)*1000000)/$P$24-1,"")} -> 2.4659616 | O27: {=IFERROR(+(L27/_FV($A$6,"Shares outstanding",TRUE)*1000000)/$P$24-1,"")} -> 1.5147017
B29: Profitability | D29: =+LEFT(B6, FIND(" ", B6 & " ") - 1) -> INTERNATIONAL | E29: =+LEFT(B8, FIND(" ", B8 & " ") - 1) -> ACCENTURE | F29: =+LEFT(B9, FIND(" ", B9 & " ") - 1) -> Capgemini | G29: =+LEFT(B10, FIND(" ", B10 & " ") - 1) -> MICROSOFT | H29: =+LEFT(B11, FIND(" ", B11 & " ") - 1) -> ORACLE | I29: =+LEFT(B12, FIND(" ", B12 & " ") - 1) -> HEWLETT | J29: =+LEFT(B13, FIND(" ", B13 & " ") - 1) -> IONQ | K29: =+LEFT(B14, FIND(" ", B14 & " ") - 1) -> Rigetti | L29: =+LEFT(B15, FIND(" ", B15 & " ") - 1) | M29: =+LEFT(B16, FIND(" ", B16 & " ") - 1) | N29: =+LEFT(B17, FIND(" ", B17 & " ") - 1) | O29: Average
B31: Operating Margin | D31: =IFERROR(D101/D97,"") -> 0.14949086 | E31: =IFERROR(E101/E97,"") -> 0.15462005 | F31: =IFERROR(F101/F97,"") -> 0.11522448 | G31: =IFERROR(G101/G97,"") -> 0.446443 | H31: =IFERROR(H101/H97,"") -> 0.30344971 | I31: =IFERROR(I101/I97,"") -> 0.082683307 | J31: =IFERROR(J101/J97,"") -> -5.3967683 | K31: =IFERROR(K101/K97,"") -> -6.9894347 | ... N31: =IFERROR(N101/N97,"") | O31: =IFERROR(+AVERAGE(D31:N31),"") -> -1.3917864
B32: Net Income Margin | D32: =IFERROR(D105/D97,"") -> 0.095867927 | E32: =IFERROR(E105/E97,"") -> 0.1119444 | F32: =IFERROR(F105/F97,"") -> 0.075624547 | G32: =IFERROR(G105/G97,"") -> 0.35955973 | H32: =IFERROR(H105/H97,"") -> 0.197636 | I32: =IFERROR(I105/I97,"") -> 0.085604275 | J32: =IFERROR(J105/J97,"") -> -7.698281 | K32: =IFERROR(K105/K97,"") -> -7.1616311 | ... N32: =IFERROR(N105/N97,"") | O32: =IFERROR(+AVERAGE(D32:N32),"") -> -1.7417094
B33: ROA (%) | D33: =IFERROR(D105/D117,"") -> 0.043856388 | E33: =IFERROR(E105/E117,"") -> 0.12988536 | F33: =IFERROR(F105/F117,"") -> 0.065120811 | G33: =IFERROR(G105/G117,"") -> 0.17208584 | H33: =IFERROR(H105/H117,"") -> 0.07424668 | I33: =IFERROR(I105/I117,"") -> 0.036190396 | J33: =IFERROR(J105/J117,"") -> -0.65223424 | K33: =IFERROR(K105/K117,"") -> -0.27133963 | ... N33: =IFERROR(N105/N117,"") | O33: =IFERROR(+AVERAGE(D33:N33),"") -> -0.050273549
B34: Financial Cost of Debt | D34: =IFERROR(+(D102/D121)*(1-(D104/D103)),"") -> 0.020192091 | E34: =IFERROR(+(E102/E121)*(1-(E104/E103)),"") -> -0.040122932 | F34: =IFERROR(+(F102/F121)*(1-(F104/F103)),"") -> -0.0032606173 | G34: =IFERROR(+(G102/G121)*(1-(G104/G103)),"") -> 0.024525922 | H34: =IFERROR(+(H102/H121)*(1-(H104/H103)),"") -> 0.028905123 | I34: =IFERROR(+(I102/I121)*(1-(I104/I103)),"") -> 0.0051565325 | J34: =IFERROR(+(J102/J121)*(1-(J104/J103)),"") -> -1.0295629 | K34: =IFERROR(+(K102/K121)*(1-(K104/K103)),"") -> 0.21113636 | ... N34: =IFERROR(+(N102/N121)*(1-(N104/N103)),"") | O34: =IFERROR(+AVERAGE(D34:N34),"") -> -0.097878808
B35: Return on Equity (RoE) | D35: =IFERROR(+D105/D122,"") -> 0.21962617 | E35: =IFERROR(+E105/E122,"") -> 0.24906576 | F35: =IFERROR(+F105/F122,"") -> 0.14164618 | G35: =IFERROR(+G105/G122,"") -> 0.32828138 | H35: =IFERROR(+H105/H122,"") -> 1.1329148 | I35: =IFERROR(+I105/I122,"") -> 0.10365756 | J35: =IFERROR(+J105/J122,"") -> -0.86382101 | K35: =IFERROR(+K105/K122,"") -> -0.61043219 | ... N35: =IFERROR(+N105/N122,"") | O35: =IFERROR(+AVERAGE(D35:N35),"") -> 0.087617334
B36: Return on Invested Capital (ROIC) | D36: =IFERROR(+D105/(D121+D122),"") -> 0.052147287 | E36: =IFERROR(+E105/(E121+E122),"") -> 0.21823622 | F36: =IFERROR(+F105/(F121+F122),"") -> 0.093487748 | G36: =IFERROR(+G105/(G121+G122),"") -> 0.24059247 | H36: =IFERROR(+H105/(H121+H122),"") -> 0.1009276 | I36: =IFERROR(+I105/(I121+I122),"") -> 0.057700913 | J36: =IFERROR(+J105/(J121+J122),"") -> -0.82569421 | K36: =IFERROR(+K105/(K121+K122),"") -> -0.57075538 | ... N36: =IFERROR(+N105/(N121+N122),"") | O36: =IFERROR(+AVERAGE(D36:N36),"") -> -0.079169668
B38: Solvency | D38: =+D29 -> INTERNATIONAL | E38: =+E29 -> ACCENTURE | F38: =+F29 -> Capgemini | G38: =+G29 -> MICROSOFT | H38: =+H29 -> ORACLE | I38: =+I29 -> HEWLETT | J38: =+J29 -> IONQ | K38: =+K29 -> Rigetti | ... O38: =+O29 -> Average
B40: Debt/Assets | D40: =IFERROR(D121/D117,"") -> 0.64132343 | E40: =IFERROR(E121/E117,"") -> 0.073669286 | F40: =IFERROR(F121/F117,"") -> 0.23682775 | G40: =IFERROR(G121/G117,"") -> 0.19105636 | H40: =IFERROR(H121/H117,"") -> 0.67010697 | I40: =IFERROR(I121/I117,"") -> 0.27807246 | J40: =IFERROR(J121/J117,"") -> 0.034865103 | K40: =IFERROR(K121/K117,"") -> 0.030900287 | ... N40: =IFERROR(N121/N117,"") | O40: =IFERROR(+AVERAGE(D40:N40),"") -> 0.26960271
B41: Net Debt/EBITDA | D41: =IFERROR(+(D121-D111)/D100,"") -> 5.2695431 | E41: =IFERROR(+(E121-E111)/E100,"") -> -0.068510668 | F41: =IFERROR(+(F121-F111)/F100,"") -> 1.0182719 | G41: =IFERROR(+(G121-G111)/G100,"") -> 0.58796526 | H41: =IFERROR(+(H121-H111)/H100,"") -> 3.6196744 | I41: =IFERROR(+(I121-I111)/I100,"") -> 0.93986384 | J41: =IFERROR(+(J121-J111)/J100,"") -> 0.17150528 | K41: =IFERROR(+(K121-K111)/K100,"") -> 0.859349 | ... N41: =IFERROR(+(N121-N111)/N100,"") | O41: =IFERROR(+AVERAGE(D41:N41),"") -> 1.5497078
B42: Interest Coverage Ratio | D42: =IFERROR(D101/D102,"") -> 5.4795561 | E42: =IFERROR(E101/E102,"") -> -47.043132 | F42: =IFERROR(F101/F102,"") -> -94.296296 | G42: =IFERROR(G101/G102,"") -> 37.28552 | H42: =IFERROR(H101/H102,"") -> 5.2468168 | I42: =IFERROR(I101/I102,"") -> 21.290598 | J42: =IFERROR(J101/J102,"") -> 12.737958 | K42: =IFERROR(K101/K102,"") -> -40.589882 | ... N42: =IFERROR(N101/N102,"") | O42: =IFERROR(+AVERAGE(D42:N42),"") -> -12.486108
B44: Liquidity | D44: =+D29 -> INTERNATIONAL | E44: =+E29 -> ACCENTURE | F44: =+F29 -> Capgemini | G44: =+G29 -> MICROSOFT | H44: =+H29 -> ORACLE | I44: =+I29 -> HEWLETT | J44: =+J29 -> IONQ | K44: =+K29 -> Rigetti | ... O44: =+O29 -> Average
B46: Cash Ratio | D46: =IFERROR(D111/D119,"") -> 0.42082554 | E46: =IFERROR(E111/E119,"") -> 0.26372648 | F46: =IFERROR(F111/F119,"") -> 0.36178493 | G46: =IFERROR(G111/G119,"") -> 0.14618553 | H46: =IFERROR(H111/H119,"") -> 0.30956759 | I46: =IFERROR(I111/I119,"") -> 0.57159358 | J46: =IFERROR(J111/J119,"") -> 1.5073576 | K46: =IFERROR(K111/K119,"") -> 5.702705 | ... N46: =IFERROR(N111/N119,"") | O46: =IFERROR(+AVERAGE(D46:N46),"") -> 1.1604683
B47: Quick Ratio | D47: =IFERROR(+(D111+D112)/D119,"") -> 0.65469797 | E47: =IFERROR(+(E111+E112)/E119,"") -> 0.88942933 | F47: =IFERROR(+(F111+F112)/F119,"") -> 0.78181346 | G47: =IFERROR(+(G111+G112)/G119,"") -> 0.60053797 | H47: =IFERROR(+(H111+H112)/H119,"") -> 0.52878519 | I47: =IFERROR(+(I111+I112)/I119,"") -> 0.6961845 | J47: =IFERROR(+(J111+J112)/J119,"") -> 1.6879313 | K47: =IFERROR(+(K111+K112)/K119,"") -> 5.9072217 | ... N47: =IFERROR(+(N111+N112)/N119,"") | O47: =IFERROR(+AVERAGE(D47:N47),"") -> 1.4683252
B48: Current Ratio | D48: =IFERROR(D115/D119,"") -> 1.0404321 | E48: =IFERROR(E115/E119,"") -> 1.0991616 | F48: =IFERROR(F115/F119,"") -> 1.2074199 | G48: =IFERROR(G115/G119,"") -> 1.2749549 | H48: =IFERROR(H115/H119,"") -> 0.71500127 | I48: =IFERROR(I115/I119,"") -> 1.2881454 | J48: =IFERROR(J115/J119,"") -> 10.497492 | K48: =IFERROR(K115/K119,"") -> 17.422938 | ... N48: =IFERROR(N115/N119,"") | O48: =IFERROR(+AVERAGE(D48:N48),"") -> 4.3181931
B50: Activity | D50: =+D29 -> INTERNATIONAL | E50: =+E29 -> ACCENTURE | F50: =+F29 -> Capgemini | G50: =+G29 -> MICROSOFT | H50: =+H29 -> ORACLE | I50: =+I29 -> HEWLETT | J50: =+J29 -> IONQ | K50: =+K29 -> Rigetti | ... O50: =+O29 -> Average
B52: Inventory Turnover | D52: =IFERROR(D98/(AVERAGE(D113:D114)),"") -> 22.204898 | E52: =IFERROR(E98/(AVERAGE(E113:E114)),"0") -> 0 | F52: =IFERROR(F98/(AVERAGE(F113:F114)),"0") -> 0 | G52: =IFERROR(G98/(AVERAGE(G113:G114)),"") -> 39.569674 | H52: =IFERROR(H98/(AVERAGE(H113:H114)),"") -> 47.920886 | I52: =IFERROR(I98/(AVERAGE(I113:I114)),"") -> 3.1817669 | J52: =IFERROR(J98/(AVERAGE(J113:J114)),"0") -> 0 | K52: =IFERROR(K98/(AVERAGE(K113:K114)),"0") -> 0 | L52: =IFERROR(L98/(AVERAGE(L113:L114)),"") | M52: =IFERROR(M98/(AVERAGE(M113:M114)),"") | N52: =IFERROR(N98/(AVERAGE(N113:N114)),"") | O52: =IFERROR(+AVERAGE(D52:N52),"") -> 28.219306
B53: Acc. Receivable Turnover | D53: =IFERROR(D97/D112,"") -> 8.0961166 | E53: =IFERROR(E97/E112,"") -> 5.4657049 | F53: =IFERROR(F97/F112,"") -> 6.8239654 | G53: =IFERROR(G97/G112,"") -> 4.3061275 | H53: =IFERROR(H97/H112,"") -> 7.6588576 | I53: =IFERROR(I97/I112,"") -> 9.3099506 | J53: =IFERROR(J97/J112,"") -> 6.6103438 | K53: =IFERROR(K97/K112,"") -> 4.4458179 | ... N53: =IFERROR(N97/N112,"") | O53: =IFERROR(+AVERAGE(D53:N53),"") -> 6.5896105
B54: Payables Turnover | D54: =IFERROR(D98/D118,"") -> 6.7462798 | E54: =IFERROR(E98/E118,"") -> 15.939245 | F54: =IFERROR(F98/F118,"") -> 9.771011 | G54: =IFERROR(G98/G118,"") -> 3.3694308 | H54: =IFERROR(H98/H118,"") -> 6.4246924 | I54: =IFERROR(I98/I118,"") -> 1.7854302 | J54: =IFERROR(J98/J118,"") -> 3.9382409 | K54: =IFERROR(K98/K118,"") -> 3.2031447 | ... N54: =IFERROR(N98/N118,"") | O54: =IFERROR(+AVERAGE(D54:N54),"") -> 6.3971843
B55: Fixed Asset Turnover | D55: =IFERROR(D97/D116,"") -> 10.947837 | E55: =IFERROR(E97/E116,"") -> 15.16805 | F55: =IFERROR(F97/F116,"") -> 13.664811 | G55: =IFERROR(G97/G116,"") -> 1.5860164 | H55: =IFERROR(H97/H116,"") -> 1.8366278 | I55: =IFERROR(I97/I116,"") -> 4.2600396 | J55: =IFERROR(J97/J116,"") -> 0.692147 | K55: =IFERROR(K97/K116,"") -> 0.20499278 | ... N55: =IFERROR(N97/N116,"") | O55: =IFERROR(+AVERAGE(D55:N55),"") -> 6.0450651
B56: Total Asset Turnover | D56: =IFERROR(D97/D117,"") -> 0.45746674 | E56: =IFERROR(E97/E117,"") -> 1.1602667 | F56: =IFERROR(F97/F117,"") -> 0.86110678 | G56: =IFERROR(G97/G117,"") -> 0.47860154 | H56: =IFERROR(H97/H117,"") -> 0.37567387 | I56: =IFERROR(I97/I117,"") -> 0.42276389 | J56: =IFERROR(J97/J117,"") -> 0.084724659 | K56: =IFERROR(K97/K117,"") -> 0.037887965 | ... N56: =IFERROR(N97/N117,"") | O56: =IFERROR(+AVERAGE(D56:N56),"") -> 0.48481152
B57: Cash Cycle (days) | D57: =IFERROR(365/D52+365/D53-365/D54,"") -> 7.4172642 | E57: =IFERROR(365/E52+365/E53-365/E54,"0") -> 0 | F57: =IFERROR(365/F52+365/F53-365/F54,"0") -> 0 | G57: =IFERROR(365/G52+365/G53-365/G54,"") -> -14.339732 | H57: =IFERROR(365/H52+365/H53-365/H54,"") -> -1.5380994 | I57: =IFERROR(365/I52+365/I53-365/I54,"") -> -50.511023 | J57: =IFERROR(365/J52+365/J53-365/J54,"0") -> 0 | K57: =IFERROR(365/K52+365/K53-365/K54,"0") -> 0 | L57: =IFERROR(365/L52+365/L53-365/L54,"") | M57: =IFERROR(365/M52+365/M53-365/M54,"") | N57: =IFERROR(365/N52+365/N53-365/N54,"") | O57: =IFERROR(+AVERAGE(D57:N57),"") -> -14.742897
B59: Cash Flow | D59: =+D38 -> INTERNATIONAL | E59: =+E38 -> ACCENTURE | F59: =+F38 -> Capgemini | G59: =+G38 -> MICROSOFT | H59: =+H38 -> ORACLE | I59: =+I38 -> HEWLETT | J59: =+J38 -> IONQ | K59: =+K38 -> Rigetti | ... O59: =+O38 -> Average
B61: Cash Flow Margin | D61: =IFERROR(D132/D97,"") -> 0.017066913 | E61: =IFERROR(E132/E97,"") -> -0.062262218 | F61: =IFERROR(F132/F97,"") -> -0.033037654 | G61: =IFERROR(G132/G97,"") -> -0.066860584 | H61: =IFERROR(H132/H97,"") -> 0.013009573 | I61: =IFERROR(I132/I97,"") -> 0.34932121 | J61: =IFERROR(J132/J97,"") -> 0.43551645 | K61: =IFERROR(K132/K97,"") -> 4.3067655 | ... N61: =IFERROR(N132/N97,"") | O61: =IFERROR(+AVERAGE(D61:N61),"") -> 0.6199399
B62: Cash Flow to Net Income | D62: =IFERROR(D132/D96,"") -> 0.14255291 | E62: =IFERROR(E132/E96,"") -> -0.58801444 | F62: =IFERROR(F132/F96,"") -> -0.43896572 | G62: =IFERROR(G132/G96,"") -> -0.22648941 | H62: =IFERROR(H132/H96,"") -> 0.081030225 | I62: =IFERROR(I132/I96,"") -> 5.197037 | J62: =IFERROR(J132/J96,"") -> -0.11893633 | K62: =IFERROR(K132/K96,"") -> -0.6187173 | ... N62: =IFERROR(N132/N96,"") | O62: =IFERROR(+AVERAGE(D62:N62),"") -> 0.42868712
B63: CFO to Net Income | D63: =+IFERROR(D126/D105,"") -> 2.2348737 | E63: =+IFERROR(E126/E105,"") -> 1.2568825 | F63: =+IFERROR(F126/F105,"") -> 1.4099342 | G63: =+IFERROR(G126/G105,"") -> 1.3450576 | H63: =+IFERROR(H126/H105,"") -> 1.7839878 | I63: =+IFERROR(I126/I105,"") -> 1.6832105 | J63: =+IFERROR(J126/J105,"") -> 0.31871775 | K63: =+IFERROR(K126/K105,"") -> 0.65516215 | ... N63: =+IFERROR(N126/N105,"") | O63: =IFERROR(+AVERAGE(D63:N63),"") -> 1.3359783
B64: Net Capex to CFO | D64: =IFERROR(-D127/D126,"") -> 0.036519152 | E64: =IFERROR(-E127/E126,"") -> 0.056565546 | F64: =IFERROR(-F127/F126,"") -> 0.13157895 | G64: =IFERROR(-G127/G126,"") -> 0.37518136 | H64: =IFERROR(-H127/H126,"") -> 0.36769667 | I64: =IFERROR(-I127/I126,"") -> 0.46003225 | J64: =IFERROR(-J127/J126,"") -> -0.223016 | K64: =IFERROR(-K127/K126,"") -> -0.21921109 | ... N64: =IFERROR(-N127/N126,"") | O64: =IFERROR(+AVERAGE(D64:N64),"") -> 0.12316835
B65: CFI to CFO | D65: =IFERROR(-D128/D126,"") -> 0.3671997 | E65: =IFERROR(-E128/E126,"") -> 0.77338736 | F65: =IFERROR(-F128/F126,"") -> 0.56748727 | G65: =IFERROR(-G128/G126,"") -> 0.8179809 | H65: =IFERROR(-H128/H126,"") -> 0.39415198 | I65: =IFERROR(-I128/I126,"") -> 0.012209168 | J65: =IFERROR(-J128/J126,"") -> 0.78281275 | K65: =IFERROR(-K128/K126,"") -> -1.5478302 | ... N65: =IFERROR(-N128/N126,"") | O65: =IFERROR(+AVERAGE(D65:N65),"") -> 0.27092487
B66: Net Financing to CFO | D66: =IFERROR((D129+D130)/D126,"") -> -0.065451841 | E66: =IFERROR((E129+E130)/E126,"") -> -0.075851495 | F66: =IFERROR((F129+F130)/F126,"") -> 1.4448217 | G66: =IFERROR((G129+G130)/G126,"") -> 0.17133144 | H66: =IFERROR((H129+H130)/H126,"") -> 3.8878059 | I66: =IFERROR((I129+I130)/I126,"") -> 2.0117484 | J66: =IFERROR((J129+J130)/J126,"") -> 0 | K66: =IFERROR((K129+K130)/K126,"") -> 0.4607818 | ... N66: =IFERROR((N129+N130)/N126,"") | O66: =IFERROR(+AVERAGE(D66:N66),"") -> 0.97939825
B67: Debt Borrowing to Debt Repayment | D67: =+IFERROR(-D130/D129,"") -> 1.1534438 | E67: =+IFERROR(-E130/E129,"") -> 9.8117048 | F67: =+IFERROR(-F130/F129,"") -> 0.33825816 | G67: =+IFERROR(-G130/G129,"") -> 0.58868796 | H67: =+IFERROR(-H130/H129,"") -> 0.048082975 | I67: =+IFERROR(-I130/I129,"") -> 0.38668446 | J67: =+IFERROR(-J130/J129,"0") -> 0 | K67: =+IFERROR(-K130/K129,"0") -> 0 | L67: =+IFERROR(-L130/L129,"") | M67: =+IFERROR(-M130/M129,"") | N67: =+IFERROR(-N130/N129,"") | O67: =IFERROR(+AVERAGE(D67:N67),"") -> 2.054477
B68: CFF to CFO | D68: =IFERROR(-D131/D126,"") -> 0.52651543 | E68: =IFERROR(-E131/E126,"") -> 0.66405651 | F68: =IFERROR(-F131/F126,"") -> 0.78353141 | G68: =IFERROR(-G131/G126,"") -> 0.31849546 | H68: =IFERROR(-H131/H126,"") -> 0.56520109 | I68: =IFERROR(-I131/I126,"") -> -1.4473624 | J68: =IFERROR(-J131/J126,"") -> 0.39445322 | K68: =IFERROR(-K131/K126,"") -> 3.4657199 | ... N68: =IFERROR(-N131/N126,"") | O68: =IFERROR(+AVERAGE(D68:N68),"") -> 0.65882633
B69: Payout Ratio | O69: =IFERROR(+AVERAGE(D69:N69),"")
B71: Stock Information | D71: =+D29 -> INTERNATIONAL | E71: =+E29 -> ACCENTURE | F71: =+F29 -> Capgemini | G71: =+G29 -> MICROSOFT | H71: =+H29 -> ORACLE | I71: =+I29 -> HEWLETT | J71: =+J29 -> IONQ | K71: =+K29 -> Rigetti | ... O71: =+O29 -> Average
B73: (%) Float | D73: 0.9979 | E73: 0.9982 | F73: 0.998 | G73: 0.9987 | H73: 0.5892 | I73: 1 | J73: 0.8531 | K73: 0.988 | O73: =IFERROR(+AVERAGE(D73:N73),"") -> 0.9278875
B74: β (Levered) | D74: {=IFERROR(_FV(D91,"Beta"),"")} -> 0.6925 | E74: {=IFERROR(_FV(E91,"Beta"),"")} -> 1.281 | F74: {=IFERROR(_FV(F91,"Beta"),"")} -> 1.0537 | G74: {=IFERROR(_FV(G91,"Beta"),"")} -> 1.02 | H74: {=IFERROR(_FV(H91,"Beta"),"")} -> 1.5211 | I74: {=IFERROR(_FV(I91,"Beta"),"")} -> 1.4451 | J74: {=IFERROR(_FV(J91,"Beta"),"")} -> 2.5926 | K74: {=IFERROR(_FV(K91,"Beta"),"")} -> 1.5957 | ... N74: {=IFERROR(_FV(N91,"Beta"),"")} | O74: =IFERROR(+AVERAGE(D74:N74),"") -> 1.4002125
B75: β (Unlevered) | D75: =IFERROR(D74/(1+(1-D104/D103)*(D121/D122)),"") -> 0.15984189 | E75: =IFERROR(E74/(1+(1-E104/E103)*(E121/E122)),"") -> 1.1545799 | F75: =IFERROR(F74/(1+(1-F104/F103)*(F121/F122)),"") -> 0.76463422 | G75: =IFERROR(G74/(1+(1-G104/G103)*(G121/G122)),"") -> 0.78581051 | H75: =IFERROR(H74/(1+(1-H104/H103)*(H121/H122)),"") -> 0.15037288 | I75: =IFERROR(I74/(1+(1-I104/I103)*(I121/I122)),"") -> 0.85226956 | J75: =IFERROR(J74/(1+(1-J104/J103)*(J121/J122)),"") -> 2.4781694 | K75: =IFERROR(K74/(1+(1-K104/K103)*(K121/K122)),"") -> 1.4919829 | ... N75: =IFERROR(N74/(1+(1-N104/N103)*(N121/N122)),"") | O75: =IFERROR(+AVERAGE(D75:N75),"") -> 0.97970766
B76: % Held by Insiders | D76: 0.0012 | E76: 0.0008 | F76: 0.0938 | G76: 0.0006 | H76: 0.4111 | I76: 0.0043 | J76: 0.0854 | K76: 0.0101 | O76: =IFERROR(+AVERAGE(D76:N76),"") -> 0.0759125
B77: % Held by Institutions | D77: 0.6406 | E77: 0.7909 | F77: 0.6534 | G77: 0.7441 | H77: 0.4487 | I77: 0.8596 | J77: 0.3738 | K77: 0.2411 | O77: =IFERROR(+AVERAGE(D77:N77),"") -> 0.594025
B78: Short % Float | D78: 0.0223 | E78: 0.0116 | F78: 0 | G78: 0.0068 | H78: 0.0127 | I78: 0.0617 | J78: 0.1466 | K78: 0.2606 | O78: =IFERROR(+AVERAGE(D78:N78),"") -> 0.0652875
B80: Stock Performance | D80: =+D29 -> INTERNATIONAL | E80: =+E29 -> ACCENTURE | F80: =+F29 -> Capgemini | G80: =+G29 -> MICROSOFT | H80: =+H29 -> ORACLE | I80: =+I29 -> HEWLETT | J80: =+J29 -> IONQ | K80: =+K29 -> Rigetti | ... O80: =+O29 -> Average
B82: 1 day | D82: {=IFERROR((D85/_xlfn.STOCKHISTORY(C6,TODAY()-1,TODAY()-1,0,0,1))-1,"Non-trading days")} -> 0 | E82: {=IFERROR((E85/_xlfn.STOCKHISTORY(C8,TODAY()-1,TODAY()-1,0,0,1))-1,"Non-trading days")} -> Non-trading days | F82: {=IFERROR((F85/_xlfn.STOCKHISTORY(C9,TODAY()-1,TODAY()-1,0,0,1))-1,"Non-trading days")} -> 0 | G82: {=IFERROR((G85/_xlfn.STOCKHISTORY(C10,TODAY()-1,TODAY()-1,0,0,1))-1,"Non-trading days")} -> Non-trading days | H82: {=IFERROR((K85/_xlfn.STOCKHISTORY(C11,TODAY()-1,TODAY()-1,0,0,1))-1,"Non-trading days")} -> -0.8599986 | I82: {=IFERROR((L85/_xlfn.STOCKHISTORY(C12,TODAY()-1,TODAY()-1,0,0,1))-1,"Non-trading days")} -> Non-trading days | J82: {=IFERROR((M85/_xlfn.STOCKHISTORY(C13,TODAY()-1,TODAY()-1,0,0,1))-1,"Non-trading days")} -> Non-trading days | K82: {=IFERROR((N85/_xlfn.STOCKHISTORY(C14,TODAY()-1,TODAY()-1,0,0,1))-1,"Non-trading days")} -> Non-trading days | L82: {=IFERROR((L85/_xlfn.STOCKHISTORY(C15,TODAY()-1,TODAY()-1,0,0,1))-1,"Non-trading days")} -> Non-trading days | M82: {=IFERROR((M85/_xlfn.STOCKHISTORY(C16,TODAY()-1,TODAY()-1,0,0,1))-1,"Non-trading days")} -> Non-trading days | N82: {=IFERROR((N85/_xlfn.STOCKHISTORY(C17,TODAY()-1,TODAY()-1,0,0,1))-1,"Non-trading days")} -> Non-trading days | O82: =IFERROR(+AVERAGE(D82:N82),"") -> -0.2866662
B83: 1 month | D83: {=IFERROR((D85/_xlfn.STOCKHISTORY(C6,TODAY()-29,TODAY()-29,0,0,1))-1,"Non-trading days")} -> 0.16030258 | E83: {=IFERROR((E85/_xlfn.STOCKHISTORY(C8,TODAY()-29,TODAY()-29,0,0,1))-1,"Non-trading days")} -> -0.037772112 | F83: {=IFERROR((F85/_xlfn.STOCKHISTORY(C9,TODAY()-29,TODAY()-29,0,0,1))-1,"Non-trading days")} -> Non-trading days | G83: {=IFERROR((G85/_xlfn.STOCKHISTORY(C10,TODAY()-29,TODAY()-29,0,0,1))-1,"Non-trading days")} -> Non-trading days | H83: {=IFERROR((K85/_xlfn.STOCKHISTORY(C11,TODAY()-29,TODAY()-29,0,0,1))-1,"Non-trading days")} -> -0.82792096 | I83: {=IFERROR((L85/_xlfn.STOCKHISTORY(C12,TODAY()-29,TODAY()-29,0,0,1))-1,"Non-trading days")} -> Non-trading days | J83: {=IFERROR((M85/_xlfn.STOCKHISTORY(C13,TODAY()-29,TODAY()-29,0,0,1))-1,"Non-trading days")} -> Non-trading days | K83: {=IFERROR((N85/_xlfn.STOCKHISTORY(C14,TODAY()-29,TODAY()-29,0,0,1))-1,"Non-trading days")} -> Non-trading days | L83: {=IFERROR((L85/_xlfn.STOCKHISTORY(C15,TODAY()-29,TODAY()-29,0,0,1))-1,"Non-trading days")} -> Non-trading days | M83: {=IFERROR((M85/_xlfn.STOCKHISTORY(C16,TODAY()-29,TODAY()-29,0,0,1))-1,"Non-trading days")} -> Non-trading days | N83: {=IFERROR((N85/_xlfn.STOCKHISTORY(C17,TODAY()-29,TODAY()-29,0,0,1))-1,"Non-trading days")} -> Non-trading days | O83: =IFERROR(AVERAGE(D83:N83),"") -> -0.23513017
B84: YTD | D84: {=IFERROR((D85/_xlfn.STOCKHISTORY(C6,"2025-01-02","2025-01-02",0,0,1))-1,"Non-trading days")} -> 0.31113031 | E84: {=IFERROR((E85/_xlfn.STOCKHISTORY(C8,"2025-01-02","2025-01-02",0,0,1))-1,"Non-trading days")} -> -0.29671464 | F84: {=IFERROR((F85/_xlfn.STOCKHISTORY(C9,"2025-01-02","2025-01-02",0,0,1))-1,"Non-trading days")} -> -0.080554807 | G84: {=IFERROR((G85/_xlfn.STOCKHISTORY(C10,"2025-01-02","2025-01-02",0,0,1))-1,"Non-trading days")} -> 0.23596445 | H84: {=IFERROR((K85/_xlfn.STOCKHISTORY(C11,"2025-01-02","2025-01-02",0,0,1))-1,"Non-trading days")} -> -0.7587183 | I84: {=IFERROR((L85/_xlfn.STOCKHISTORY(C12,"2025-01-02","2025-01-02",0,0,1))-1,"Non-trading days")} -> Non-trading days | J84: {=IFERROR((M85/_xlfn.STOCKHISTORY(C13,"2025-01-02","2025-01-02",0,0,1))-1,"Non-trading days")} -> Non-trading days | K84: {=IFERROR((N85/_xlfn.STOCKHISTORY(C14,"2025-01-02","2025-01-02",0,0,1))-1,"Non-trading days")} -> Non-trading days | L84: {=IFERROR((L85/_xlfn.STOCKHISTORY(C15,"2025-01-02","2025-01-02",0,0,1))-1,"Non-trading days")} -> Non-trading days | M84: {=IFERROR((M85/_xlfn.STOCKHISTORY(C16,"2025-01-02","2025-01-02",0,0,1))-1,"Non-trading days")} -> Non-trading days | N84: {=IFERROR((N85/_xlfn.STOCKHISTORY(C17,"2025-01-02","2025-01-02",0,0,1))-1,"Non-trading days")} -> Non-trading days | O84: =IFERROR(AVERAGE(D84:N84),"") -> -0.1177786
B85: Current Price | D85: {=+IFERROR(_FV(D91,"Price"),"")} -> 288.37 | E85: {=+IFERROR(_FV(E91,"Preço"),"")} -> 245.32 | F85: {=+IFERROR(_FV(F91,"Preço"),"")} -> 147.01 | G85: {=+IFERROR(_FV(G91,"Preço"),"")} -> 517.35 | H85: {=+IFERROR(_FV(H91,"Preço"),"")} -> 286.14 | I85: {=+IFERROR(_FV(I91,"Preço"),"")} -> 24.43 | J85: {=+IFERROR(_FV(J91,"Preço"),"")} -> 73.28 | K85: {=+IFERROR(_FV(K91,"Preço"),"")} -> 40.06 | L85: {=+IFERROR(_FV(L91,"Price"),"")} | M85: {=+IFERROR(_FV(M91,"Price"),"")} | N85: {=+IFERROR(_FV(N91,"Price"),"")} | O85: =IFERROR(AVERAGE(D85:N85),"") -> 202.745
B87: Extra
B89: % Revenues in the US
B91: Income Statement | D91: =+DCF!R4 -> #VALUE! | E91: #VALUE! | F91: #VALUE! | G91: #VALUE! | H91: #VALUE! | I91: #VALUE! | J91: #VALUE! | K91: #VALUE! | L91: PEER 8 | M91: PEER 9 | N91: PEER 10
B93: =+Inputs!$B$6&" ("&Inputs!O$4&")" -> Revenue (Sales) (2022) | D93: =+_xlfn.XLOOKUP("Revenue (Sales)",Inputs!$B:$B,Inputs!O:O) -> 60530 | E93: 61594.3 | F93: 21995 | G93: 198270 | H93: 42440 | I93: 28496 | J93: 11131 | K93: 13102
B94: =+Inputs!$B$6&" ("&Inputs!P$4&")" -> Revenue (Sales) (2023) | D94: =+_xlfn.XLOOKUP("Revenue (Sales)",Inputs!$B:$B,Inputs!P:P) -> 61860 | E94: 64111.7 | F94: 22522 | G94: 211915 | H94: 49954 | I94: 29135 | J94: 22042 | K94: 12008
B95: EBITDA (2023) | D95: =+_xlfn.XLOOKUP("EBITDA",Inputs!$B:$B,Inputs!P:P) -> 13778 | E95: 13005.1 | F95: 3309 | G95: 106430 | H95: 20743 | I95: 5262 | J95: -147379 | K95: -61902
B96: Net Income (2023) | D96: =+_xlfn.XLOOKUP("Net Income",Inputs!$B:$B,Inputs!P:P) -> 7513 | E96: 6871.6 | F96: 1663 | G96: 72361 | H96: 8503 | I96: 2025 | J96: -157723.05 | K96: -75107
B97: =+Inputs!$B$6&" ("&Inputs!Q$4&")" -> Revenue (Sales) (2024) | D97: =+_xlfn.XLOOKUP("Revenue (Sales)",Inputs!$B:$B,Inputs!Q:Q) -> 62753 | E97: 64896.5 | F97: 22096 | G97: 245122 | H97: 52961 | I97: 30127 | J97: 43073 | K97: 10790
B98: COGS (Cost of Goods Sold) | D98: =+_xlfn.XLOOKUP($B98,Inputs!$B:$B,Inputs!Q:Q) -> 27201 | E98: 43734.1 | F98: 16044 | G98: 74114 | H98: 15143 | I98: 19754 | J98: 20597 | K98: 5093
B99: Gross Profit | D99: =+_xlfn.XLOOKUP($B99,Inputs!$B:$B,Inputs!Q:Q) -> 35552 | E99: =+E97-E98 -> 21162.4 | F99: =+F97-F98 -> 6052 | G99: =G97-G98 -> 171008 | H99: =+H97-H98 -> 37818 | I99: =I97-I98 -> 10373 | J99: 22476 | K99: 5697 | L99: =+L97-L98 -> 0 | M99: =+M97-M98 -> 0 | N99: =+N97-N98 -> 0
B100: EBITDA | D100: =+_xlfn.XLOOKUP($B100,Inputs!$B:$B,Inputs!Q:Q) -> 14048 | E100: 12903.1 | F100: 3229 | G100: 135275 | H100: 23401 | I100: 5288 | J100: -213801 | K100: -68510
B101: Operating Income (EBIT) | D101: =+_xlfn.XLOOKUP($B101,Inputs!$B:$B,Inputs!Q:Q) -> 9381 | E101: 10034.3 | F101: 2546 | G101: 109433 | H101: 16071 | I101: 2491 | J101: -232455 | K101: -75416
B102: Net Interest Expense (Income) | D102: =+_xlfn.XLOOKUP($B102,Inputs!$B:$B,Inputs!Q:Q) -> 1712 | E102: -213.3 | F102: -27 | G102: 2935 | H102: 3063 | I102: 117 | J102: -18249 | K102: 1858
B103: Pre-Tax Income (EBT) | D103: =+_xlfn.XLOOKUP($B103,Inputs!$B:$B,Inputs!Q:Q) -> 5798 | E103: 10137.8 | F103: 2559 | G103: 107787 | H103: 11741 | I103: 2953 | J103: -331588 | K103: -77274
B104: Tax Expense (Benefits) | D104: =+_xlfn.XLOOKUP($B104,Inputs!$B:$B,Inputs!Q:Q) -> -218 | E104: 2280.1 | F104: 681 | G104: 19651 | H104: 1274 | I104: 374 | J104: 0.059 | K104: 0
B105: Net Income | D105: =+_xlfn.XLOOKUP($B105,Inputs!$B:$B,Inputs!Q:Q) -> 6016 | E105: 7264.8 | F105: 1671 | G105: 88136 | H105: 10467 | I105: 2579 | J105: -331588.06 | K105: -77274
B106: EPS basic | D106: =+_xlfn.XLOOKUP($B106,Inputs!$B:$B,Inputs!Q:Q) -> 6.53 | E106: 11.57 | F106: 9.82 | G106: 11.36 | H106: 3.82 | I106: 1.95 | J106: -1.56 | K106: -1.09
B107: R&D (Research & Development) | D107: =+_xlfn.XLOOKUP($B107,Inputs!$B:$B,Inputs!Q:Q) -> 7479 | E107: 1150.4 | F107: 0 | G107: 29510 | H107: 8915 | I107: 1640 | J107: 136827 | K107: 49750
B109: Balance Sheet
B111: Cash & Cash Equivalents | D111: =+_xlfn.XLOOKUP($B111,Inputs!$B:$B,Inputs!Q:Q) -> 13947 | E111: 5004.5 | F111: 2789 | G111: 18315 | H111: 9765 | I111: 14846 | J111: 54393 | K111: 67674
B112: Accounts Receivable | D112: =+_xlfn.XLOOKUP($B112,Inputs!$B:$B,Inputs!Q:Q) -> 7751 | E112: 11873.4 | F112: 3238 | G112: 56924 | H112: 6915 | I112: 3236 | J112: 6516 | K112: 2427
B113: Beginning Inventory | D113: =+_xlfn.XLOOKUP("Inventory",Inputs!$B:$B,Inputs!P:P) -> 1161 | E113: 0 | F113: 0 | G113: 2500 | H113: 298 | I113: 4607 | J113: 0 | K113: 0
B114: Ending Inventory | D114: =+_xlfn.XLOOKUP("Inventory",Inputs!$B:$B,Inputs!Q:Q) -> 1289 | E114: 0 | F114: 0 | G114: 1246 | H114: 334 | I114: 7810 | J114: 0 | K114: 0
B115: Current Assets | D115: =+_xlfn.XLOOKUP($B115,Inputs!$B:$B,Inputs!Q:Q) -> 34482 | E115: 20857.8 | F115: 9308 | G115: 159734 | H115: 22554 | I115: 33457 | J115: 378802 | K115: 206758
B116: Net PP&E (Property, Plant and Equipment) | D116: =+_xlfn.XLOOKUP($B116,Inputs!$B:$B,Inputs!Q:Q) -> 5732 | E116: 4278.5 | F116: 1617 | G116: 154552 | H116: 28836 | I116: 7072 | J116: 62231 | K116: 52636
B117: Total Assets | D117: =+_xlfn.XLOOKUP($B117,Inputs!$B:$B,Inputs!Q:Q) -> 137175 | E117: 55932.4 | F117: 25660 | G117: 512163 | H117: 140976 | I117: 71262 | J117: 508388 | K117: 284787
B118: Accounts Payable | D118: =+_xlfn.XLOOKUP($B118,Inputs!$B:$B,Inputs!Q:Q) -> 4032 | E118: 2743.8 | F118: 1642 | G118: 21996 | H118: 2357 | I118: 11064 | J118: 5230 | K118: 1590
B119: Current Liabilities | D119: =+_xlfn.XLOOKUP($B119,Inputs!$B:$B,Inputs!Q:Q) -> 33142 | E119: 18976.1 | F119: 7709 | G119: 125286 | H119: 31544 | I119: 25973 | J119: 36085 | K119: 11867
B120: Long-term debt | D120: =+_xlfn.XLOOKUP($B120,Inputs!$B:$B,Inputs!Q:Q) -> 52539 | E120: 2448.1 | F120: 4952 | G120: 82981 | H120: 82564 | I120: 14813 | J120: 14359 | K120: 6641
B121: Total Debt | D121: =+_xlfn.XLOOKUP($B121,Inputs!$B:$B,Inputs!Q:Q,,,-1) -> 87973.542 | E121: 4120.5 | F121: 6077 | G121: 97852 | H121: 94469 | I121: 19816 | J121: 17725 | K121: 8800
B122: Shareholder's Equity | D122: =+_xlfn.XLOOKUP($B122,Inputs!$B:$B,Inputs!Q:Q) -> 27392 | E122: 29168.2 | F122: 11797 | G122: 268477 | H122: 9239 | I122: 24880 | J122: 383862 | K122: 126589
B124: Cash Flow Statement
B126: Operating Cash Flow | D126: =+_xlfn.XLOOKUP($B126,Inputs!$B:$B,Inputs!Q:Q) -> 13445 | E126: 9131 | F126: 2356 | G126: 118548 | H126: 18673 | I126: 4341 | J126: -105683 | K126: -50627
B127: Net Capex | D127: =+_xlfn.XLOOKUP($B127,Inputs!$B:$B,Inputs!Q:Q) -> -491 | E127: -516.5 | F127: -310 | G127: -44477 | H127: -6866 | I127: -1997 | J127: -23569 | K127: -11098
B128: Investing Cash Flow | D128: =+_xlfn.XLOOKUP($B128,Inputs!$B:$B,Inputs!Q:Q) -> -4937 | E128: -7061.8 | F128: -1337 | G128: -96970 | H128: -7360 | I128: -53 | J128: 82730 | K128: -78362
...

Sheet ESG
B2: Environmental, Social and Governance Analysis
B4: Author: | C4: João Garcia | E4: Highlights | N4: Recent News
E5: AI Ethics | G5: An AI Ethics board that oversees AI workflows assuring transparency and responsability
B6: Overview | D6: .
B7: Last Update | C7: 45772 | D7: . | E7: New social paradigm | G7: IBM had a good track record in terms of DEI policies for the beginning of the decade, but a change in its approach might happen to avoid jumping to the eye of the new administration
B8: Latest year with data | C8: 2023
B9: GICS Sector | C9: Information Technology | E9: Good behavior environamentaly | G9: Given that IBM is in an highly scrutinized sector in terms of energy consumption and water use, their figures are very satisfactory
B10: GICS Industry Group | C10: IT Services
B11: Final Review | C11: Very Good | E11: Very high transperency and disclosure | G11: IBM has an overall very high disclosure ratings and is very transparent in all of its processes, which is expected for a well established company
B13: ESG Scores
B14: LSEG ESG Score | C14: 72
B15: E-Score | C15: 79
B16: S-Score | C16: 94 | E16: GHG Scope 1 and 2 Emissions: | N16: Water, Waste, Energy Management:
B17: G-Score | C17: 52
B18: S&P Global ESG Score | C18: 60
B19: Environmental | C19: 76
B20: Social | C20: 49
B21: Governance & Economic | C21: 60
B22: Sustainalytics | C22: 13,3
B23: ISS ESG Corporate Rating | C23: B
B24: SDG Impact Rating | C24: 4.2
B25: Governance Quality Score | C25: 7
B26: MSCI ESG Ratings | C26: AA
B29: Industry ESG Overview:
B30: The IT Services industry plays a critical role in driving digital transformation across sectors, placing it at the top of energy consumption, data privacy, and workforce ethics. ESG efforts in this sector focus on reducing carbon footprints from data centers, ensuring ethical AI development, promoting inclusive hiring practices, and enhancing cybersecurity. Investments in renewable energy, green cloud infrastructure, and ethical technology governance are key to advancing sustainability and stakeholder trust in IT services.
E33: ENVIRONMENTAL
G35: Overview | H35: Targets | K35: Improvements | O35: Comments
E36: GHG (or CO2) Scope 1 Emissions | H36: Reduce Scope 1 GHG emissions by 65% by 2025 (vs. 2010) and targets net-zero emissions by 2030. | K36: Achieved a 68.5% reduction by 2023, | O36: GHG Scope 1 emissions are near the median in its peers.
E38: Water Consumption | H38: Reduce year-over-year water withdrawals at its major sites located in regions experiencing high water stress | K38: - | O38: 98,6 percentile in water management among its peers (in Bloomberg).
E40: Energy Consumption | H40: 3,000 energy conservation projects by 2025 to avoid 275,000 MWh, procure 75% of its global electricity from renewable sources by 2025 (90% by 2030) | K40: Completed, since 2021, 2,130 energy conservation projects, avoiding an estimated 256,000 MWh of energy consumption. | O40: Energy consumption itself is big, but taking into account the company's size and its ranking among peers in terms of energy management (82,7 percentile), it sholdn't be ranked badly.
E42: Waste Management | H42: Divert 90% or more of its total nonhazardous waste from landfill and incineration (without energy recovery) annually | K42: - | O42: Has gotten a lot better over the years, opposing the trend of its peers that have generated more waste generally
E44: Other | H44: - | K44: - | O44: IBM expanded its Sustainability Accelerator, committing up to $75 million to support organizations aiding communities vulnerable to environmental threats.
E46: SOCIAL
B48: Important Sources: | G48: Overview | H48: Targets | K48: Improvements | O48: Comments
B49: Annual Report | C49: https://www.ibm.com/investor/services/annual-report | E49: Employee Turnover % | H49: Reduce turnover through career development and improved employee experience | K49: Implementation of talent development programs and focus on employee well-being | O49: Turnover rates are slightly below industry averages, addressing key attrition drivers such as promotion opportunities and workload balance can further enhance retention.
B50: Sustainability Report | C50: https://www.ibm.com/impact/2023-ibm-impact-report | D50: .
B51: Proxy Statement | C51: https://www.ibm.com/annualreport/assets/downloads/IBM_Proxy_2024.pdf | D51: . | E51: Salaries & Compensation | H51: Pay equity across gender/ethnicity; global compensation parity | K51: - | O51: Very good employee sentiment regarding their compensation, per reviews on Comparably
B52: Upready | C52: https://iamupready.com/turnover/company/ibm_com/
B53: Comparably | C53: https://www.comparably.com/companies/ibm | E53: Reputation | H53: - | K53: AI Ethics Board, Global Integrity Survey, high ESG transparency ratings | O53: Has a generally good reputation but is often seen as a legacy tech company that isn't as flashy as other tech companies.
E55: Discrimination Events | H55: Unclear with shift in social politics from the US government | K55: Company claims equal pay to men and women and to all ethnicities | O55: Lawsuits were filled by people claiming to have been fired because of DEI policies but the company hasn't had charges pressed.
E57: Work Safety | H57: - | K57: - | O57: Very low incident rates, employees have access to well-being and prevention programs.
E59: Damage to consumer health | H59: - | K59: - | O59: No known consumer health risks, proactively manage product safety through internal policies and supplier partnerships.
E61: Pension Plan | H61: Provide stable retirement benefits while managing financial obligations | K61: Reintroduction of a defined benefit component; immediate vesting in new plan | O61: Pension plan changes reflect a balance between offering employee benefits and managing company liabilities. Employee feedback is mixed, indicating room for improvement in communication and plan generosity.
E63: Supply chain | H63: Social/environmental compliance, ESG disclosures, Scope 3 reduction | K63: - | O63: Supply chain practices reflect a serious approach to sustainability and ethics, aligning with best practices and industry standards. The company's proactive measures in auditing, environmental management, ethical sourcing, and supplier diversity contribute to this.
E65: Community involvement | H65: 30M learners, 4M volunteer hours, $75M Accelerator Impact | K65: +543K volunteer hours, $386.9M in donations, AI and sustainability training | O65: Excellent social impact as seen before with Sustainability Accelerator.
E67: Public Sector | H67: Shape tech regulation, workforce policy, transparency | K67: Policy labs, ethical tech leadership | O67: Industry-leading practices in nonpartisan engagement, transparency, and global cooperation with public institutions. Its Policy Lab, ESG transparency, and ethical lobbying practices solidify its reputation as a responsible public sector partner.
E69: Litigation | H69: No material litigation; effective legal compliance program | K69: - | O69: No major cases are open besides the ones discussed earlier that seem unlikely to dent IBM's reputation.
E71: GOVERNANCE
G73: Overview | H73: Targets | K73: Improvements | O73: Comments
E74: Diversity (Gender, Age, Industry, Region) | H74: - | K74: - | O74: Only 3 of the 13 board members are women, lacks age diversity.
E76: % Independence | H76: - | K76: - | O76: All board membeers besides the Chairman (also CEO) are independent. Unfortunately, the duality harms the board's independence significantly.
E78: Average time as independent directors | H78: - | K78: - | O78: A lot of board members have been there for around a decade.
E80: Departures of C-level executives | H80: - | K80: - | O80: Only significant departures were due to retirements or reestructuring (Chief Marketing Officer position extinguished).
E82: CEO/Chairman duality | H82: - | K82: - | O82: -
E84: Transparency when reporting | H84: - | K84: - | O84: Very high disclosure ratings across all categories
E86: Time taken to report | H86: - | K86: - | O86: Annual Report was published on the 10th of March.
E88: CEO or Chairman in other boards? | H88: - | K88: - | O88: CEO and Chairman Arvind Krishna also serves as a board member for Northrop Grumman, an aerospace and defense company
E90: Audit / Consulting | H90: - | K90: - | O90: All audit payments were reported transparently. The Audit Committee ensures independence through regular evaluations, partner rotations, and limits on services rendered by the auditor.
E92: ESG-compensation related | H92: - | K92: - | O92: ESG considerations are present but limited. A Diversity Modifier can adjust the Annual Incentive Plan (AIP) by ±5 points based on representation of women and underrepresented minorities in leadership, but no formal linkage to environmental or governance metrics exists.
E94: Management compensation schemes | H94: - | K94: - | O94: Compensation is strongly performance-linked (77% of CEO pay is performance-based), with incentives tied to revenue, cash flow, EPS, and ESG goals. IBM's Compensation Committee ensures transparency and alignment with shareholder value.

Sheet ESG Inputs
B2: ESG Inputs
A4: x | B4: Total GHG Scope 1 Emissions | G4: 2014 | H4: =+G4+1 -> 2015 | I4: =+H4+1 -> 2016 | J4: =+I4+1 -> 2017 | K4: =+J4+1 -> 2018 | L4: =+K4+1 -> 2019 | M4: =+L4+1 -> 2020 | N4: =+M4+1 -> 2021 | O4: =+N4+1 -> 2022 | ... Q4: =+P4+1 -> 2024 | R4: ="CAGR "&$G$4&" - "&$Q$4 -> CAGR 2014 - 2024
B6: =+Peers!B6 -> INTERNATIONAL BUSINESS MACHINES CORPORATION | G6: 556.653 | H6: 354.046 | I6: 133.663 | J6: 124.901 | K6: 105 | L6: 98 | M6: 73 | N6: 78 | O6: 78 | P6: 71 | R6: =IFERROR((Q6/G6)^(1/COUNT($G$4:$Q$4))-1,"") -> -1
B7: =+Peers!A8 -> #VALUE! | H7: 26.29 | I7: 27.203 | J7: 24.095 | K7: 22.183 | L7: 19.992 | M7: 13.945 | N7: 9.25 | O7: 17.804 | P7: 22.038 | Q7: 22.395 | R7: =IFERROR((Q7/G7)^(1/COUNT($G$4:$Q$4))-1,"")
B8: =+Peers!A9 -> #VALUE! | H8: 9.621 | I8: 6.225 | J8: 6.799 | K8: 8.041 | L8: 13.08 | M8: 8.529 | N8: 10.972 | O8: 8.459 | P8: 8.83 | Q8: 7.893 | R8: =IFERROR((Q8/G8)^(1/COUNT($G$4:$Q$4))-1,"")
B9: =+Peers!A10 -> #VALUE! | G9: 85.188 | H9: 90.568 | I9: 88.486 | J9: 107.452 | K9: 99.008 | L9: 117.956 | M9: 118.1 | N9: 123.704 | O9: 139.413 | P9: 144.96 | R9: =IFERROR((Q9/G9)^(1/COUNT($G$4:$Q$4))-1,"") -> -1
B10: =+Peers!A11 -> #VALUE! | H10: 11.741 | I10: 14.953 | J10: 11.293 | K10: 14.763 | L10: 17.084 | M10: 16.52 | N10: 10.3 | O10: 9.489 | P10: 10.237 | Q10: 15.2 | R10: =IFERROR((Q10/G10)^(1/COUNT($G$4:$Q$4))-1,"")
B11: =+Peers!A12 -> #VALUE! | I11: 37.3 | J11: 79.964 | K11: 74.106 | L11: 56.577 | M11: 36.796 | N11: 29.017 | O11: 31.908 | P11: 40.495 | R11: =IFERROR((Q11/G11)^(1/COUNT($G$4:$Q$4))-1,"")
R12: =IFERROR((Q12/G12)^(1/COUNT($G$4:$Q$4))-1,"")
R13: =IFERROR((Q13/G13)^(1/COUNT($G$4:$Q$4))-1,"")
R14: =IFERROR((Q14/G14)^(1/COUNT($G$4:$Q$4))-1,"")
R15: =IFERROR((Q15/G15)^(1/COUNT($G$4:$Q$4))-1,"")
R16: =IFERROR((Q16/G16)^(1/COUNT($G$4:$Q$4))-1,"")
A18: x | B18: Total GHG Scope 2 (Location-Based) Emissions | G18: 2014 | H18: =+G18+1 -> 2015 | I18: =+H18+1 -> 2016 | J18: =+I18+1 -> 2017 | K18: =+J18+1 -> 2018 | L18: =+K18+1 -> 2019 | M18: =+L18+1 -> 2020 | N18: =+M18+1 -> 2021 | O18: =+N18+1 -> 2022 | ... Q18: =+P18+1 -> 2024 | R18: ="CAGR "&$G$4&" - "&$Q$4 -> CAGR 2014 - 2024
B20: =+$B$6 -> INTERNATIONAL BUSINESS MACHINES CORPORATION | G20: 1882.01 | H20: 1433.46 | I20: 1155.83 | J20: 1076.88 | K20: 505 | L20: 460 | M20: 262 | N20: 221 | O20: 183 | P20: 150 | R20: =IFERROR((Q20/G20)^(1/COUNT($G$4:$Q$4))-1,"") -> -1
B21: =+$B$7 -> #VALUE! | H21: 237.239 | I21: 263.05 | J21: 243.773 | K21: 218.855 | L21: 226.013 | M21: 162.983 | N21: 70.659 | O21: 8.356 | P21: 4.786 | Q21: 3.584 | R21: =IFERROR((Q21/G21)^(1/COUNT($G$4:$Q$4))-1,"")
B22: =+$B$8 -> #VALUE! | H22: 187.067 | I22: 158.282 | J22: 137.798 | K22: 127.914 | L22: 140.797 | M22: 69.804 | N22: 52.871 | O22: 10.457 | P22: 4.765 | Q22: 3.267 | R22: =IFERROR((Q22/G22)^(1/COUNT($G$4:$Q$4))-1,"")
B23: =+$B$9 -> #VALUE! | G23: 496.161 | H23: 153.773 | I23: 37.087 | J23: 139.066 | K23: 183.329 | L23: 275.42 | M23: 456.119 | N23: 429.405 | O23: 288.029 | P23: 393.134 | R23: =IFERROR((Q23/G23)^(1/COUNT($G$4:$Q$4))-1,"") -> -1
B24: =+$B$10 -> #VALUE! | H24: 374.979 | I24: 444.563 | J24: 354.428 | K24: 403.16 | L24: 362.448 | M24: 349.022 | N24: 419.277 | O24: 450.7 | P24: 262.339 | Q24: 368 | R24: =IFERROR((Q24/G24)^(1/COUNT($G$4:$Q$4))-1,"")
B25: =+$B$11 -> #VALUE! | I25: 397.48 | J25: 297.403 | K25: 231.606 | L25: 194.079 | M25: 162.075 | N25: 139.403 | O25: 132.328 | P25: 122.101 | R25: =IFERROR((Q25/G25)^(1/COUNT($G$4:$Q$4))-1,"")
R26: =IFERROR((Q26/G26)^(1/COUNT($G$4:$Q$4))-1,"")
R27: =IFERROR((Q27/G27)^(1/COUNT($G$4:$Q$4))-1,"")
R28: =IFERROR((Q28/G28)^(1/COUNT($G$4:$Q$4))-1,"")
R29: =IFERROR((Q29/G29)^(1/COUNT($G$4:$Q$4))-1,"")
R30: =IFERROR((Q30/G30)^(1/COUNT($G$4:$Q$4))-1,"")
A32: x | B32: Total Energy Usage | G32: 2014 | H32: =+G32+1 -> 2015 | I32: =+H32+1 -> 2016 | J32: =+I32+1 -> 2017 | K32: =+J32+1 -> 2018 | L32: =+K32+1 -> 2019 | M32: =+L32+1 -> 2020 | N32: =+M32+1 -> 2021 | O32: =+N32+1 -> 2022 | ... Q32: =+P32+1 -> 2024 | R32: ="CAGR "&$G$4&" - "&$Q$4 -> CAGR 2014 - 2024
B34: =+$B$6 -> INTERNATIONAL BUSINESS MACHINES CORPORATION | H34: 5375.73 | I34: 4912.71 | J34: 4845.69 | K34: 4666.51 | L34: 2837 | M34: 2529 | N34: 2486 | O34: 2248 | P34: 2287 | R34: =IFERROR((Q34/G34)^(1/COUNT($G$4:$Q$4))-1,"")
B35: =+$B$7 -> #VALUE! | H35: 469.31 | I35: 512.29 | J35: 499.05 | K35: 489.08 | L35: 492.82 | M35: 405.93 | N35: 299.42 | O35: 330.39 | P35: 360.97 | Q35: 345.86 | R35: =IFERROR((Q35/G35)^(1/COUNT($G$4:$Q$4))-1,"")
B36: =+$B$8 -> #VALUE! | H36: 481.97 | I36: 418.43 | J36: 412.31 | K36: 380.15 | L36: 337.12 | M36: 229.94 | N36: 193.39 | O36: 205.92 | P36: 201.05 | R36: =IFERROR((Q36/G36)^(1/COUNT($G$4:$Q$4))-1,"")
B37: =+$B$9 -> #VALUE! | H37: 4194.7 | I37: 5187.18 | J37: 6756.78 | K37: 7781.38 | L37: 9249.36 | M37: 11283.5 | N37: 14134 | O37: 18644.9 | P37: 24007.9 | R37: =IFERROR((Q37/G37)^(1/COUNT($G$4:$Q$4))-1,"")
B38: =+$B$10 -> #VALUE! | I38: 1067.11 | J38: 1100.43 | K38: 1224.31 | L38: 1202.31 | M38: 1471.52 | N38: 1631.25 | O38: 1907.06 | P38: 2343.76 | Q38: 3623.17 | R38: =IFERROR((Q38/G38)^(1/COUNT($G$4:$Q$4))-1,"")
B39: =+$B$11 -> #VALUE! | R39: =IFERROR((Q39/G39)^(1/COUNT($G$4:$Q$4))-1,"")
R40: =IFERROR((Q40/G40)^(1/COUNT($G$4:$Q$4))-1,"")
R41: =IFERROR((Q41/G41)^(1/COUNT($G$4:$Q$4))-1,"")
R42: =IFERROR((Q42/G42)^(1/COUNT($G$4:$Q$4))-1,"")
R43: =IFERROR((Q43/G43)^(1/COUNT($G$4:$Q$4))-1,"")
R44: =IFERROR((Q44/G44)^(1/COUNT($G$4:$Q$4))-1,"")
A46: x | B46: Total Water Consumption | G46: 2014 | H46: =+G46+1 -> 2015 | I46: =+H46+1 -> 2016 | J46: =+I46+1 -> 2017 | K46: =+J46+1 -> 2018 | L46: =+K46+1 -> 2019 | M46: =+L46+1 -> 2020 | N46: =+M46+1 -> 2021 | O46: =+N46+1 -> 2022 | ... Q46: =+P46+1 -> 2024 | R46: ="CAGR "&$G$4&" - "&$Q$4 -> CAGR 2014 - 2024
B48: =+$B$6 -> INTERNATIONAL BUSINESS MACHINES CORPORATION | H48: 1607.38 | I48: 1612.78 | J48: 1528.13 | K48: 1521.92 | L48: 1492.5 | M48: 1305.8 | N48: 1253 | O48: 494 | P48: 756 | R48: =IFERROR((Q48/G48)^(1/COUNT($G$4:$Q$4))-1,"")
B49: =+$B$7 -> #VALUE! | H49: 1934 | I49: 2191 | J49: 2179 | K49: 2518 | L49: 2639.44 | M49: 1997.04 | N49: 1019.07 | O49: 1100.71 | P49: 1442.86 | Q49: 1495.73 | R49: =IFERROR((Q49/G49)^(1/COUNT($G$4:$Q$4))-1,"")
B50: =+$B$8 -> #VALUE! | H50: 1899.6 | I50: 1236.69 | J50: 1281.14 | K50: 1407.23 | L50: 1873.05 | M50: 882.62 | N50: 622.18 | O50: 773.63 | P50: 834.39 | R50: =IFERROR((Q50/G50)^(1/COUNT($G$4:$Q$4))-1,"")
B51: =+$B$9 -> #VALUE! | H51: 4633.49 | I51: 4687.75 | J51: 5148.45 | K51: 6718.98 | L51: 7505.08 | M51: 7936 | N51: 8068 | O51: 10706 | P51: 12951 | R51: =IFERROR((Q51/G51)^(1/COUNT($G$4:$Q$4))-1,"")
B52: =+$B$10 -> #VALUE! | I52: 959.59 | J52: 929.67 | K52: 893.18 | L52: 852.12 | M52: 832.69 | N52: 741.73 | O52: 583.44 | P52: 708.36 | Q52: 866.07 | R52: =IFERROR((Q52/G52)^(1/COUNT($G$4:$Q$4))-1,"")
B53: =+$B$11 -> #VALUE! | R53: =IFERROR((Q53/G53)^(1/COUNT($G$4:$Q$4))-1,"")
R54: =IFERROR((Q54/G54)^(1/COUNT($G$4:$Q$4))-1,"")
R55: =IFERROR((Q55/G55)^(1/COUNT($G$4:$Q$4))-1,"")
R56: =IFERROR((Q56/G56)^(1/COUNT($G$4:$Q$4))-1,"")
R57: =IFERROR((Q57/G57)^(1/COUNT($G$4:$Q$4))-1,"")
R58: =IFERROR((Q58/G58)^(1/COUNT($G$4:$Q$4))-1,"")
A60: x | B60: Total Waste Production | G60: 2014 | H60: =+G60+1 -> 2015 | I60: =+H60+1 -> 2016 | J60: =+I60+1 -> 2017 | K60: =+J60+1 -> 2018 | L60: =+K60+1 -> 2019 | M60: =+L60+1 -> 2020 | N60: =+M60+1 -> 2021 | O60: =+N60+1 -> 2022 | ... Q60: =+P60+1 -> 2024 | R60: ="CAGR "&$G$4&" - "&$Q$4 -> CAGR 2014 - 2024
B62: =+$B$6 -> INTERNATIONAL BUSINESS MACHINES CORPORATION | G62: 107 | H62: 53 | I62: 44.5 | J62: 36.9 | K62: 28.3 | L62: 31.5 | M62: 22.1 | N62: 20.7 | O62: 14.8 | P62: 16.5 | R62: =IFERROR((Q62/G62)^(1/COUNT($G$4:$Q$4))-1,"") -> -1
B63: =+$B$7 -> #VALUE! | G63: 0.266 | H63: 0.18 | I63: 0.36 | J63: 0.302 | K63: 0.583 | L63: 0.423 | M63: 0.278 | N63: 0.32 | O63: 0.512 | P63: 0.429 | R63: =IFERROR((Q63/G63)^(1/COUNT($G$4:$Q$4))-1,"") -> -1
B64: =+$B$8 -> #VALUE! | H64: 6.225 | I64: 4.601 | J64: 4.68 | K64: 4.333 | L64: 6.065 | M64: 3.135 | N64: 2.614 | O64: 2.18 | P64: 2.497 | R64: =IFERROR((Q64/G64)^(1/COUNT($G$4:$Q$4))-1,"") | AB64: Resumo de argumentos Corrino
B65: =+$B$9 -> #VALUE! | H65: =2.434+21.71+0.952+5.314 -> 30.41 | I65: =2.243+22.378+0.931+5.691 -> 31.243 | J65: =2.047+17.398+0.69+5.924 -> 26.059 | K65: 48.126 | L65: =46.178 -> 46.178 | M65: 40.571 | N65: 22.518 | O65: 29.596 | P65: 36.392 | R65: =IFERROR((Q65/G65)^(1/COUNT($G$4:$Q$4))-1,"")
B66: =+$B$10 -> #VALUE! | G66: 264 | H66: 296 | I66: 281 | J66: 212 | K66: 154 | L66: 113 | N66: 36.05 | O66: 137.37 | P66: 94.71 | R66: =IFERROR((Q66/G66)^(1/COUNT($G$4:$Q$4))-1,"") -> -1
B67: =+$B$11 -> #VALUE! | I67: 43.241 | J67: 13.309 | K67: 13.321 | L67: 8.257 | M67: 6.549 | N67: 5.486 | O67: 5.142 | P67: 5.136 | R67: =IFERROR((Q67/G67)^(1/COUNT($G$4:$Q$4))-1,"")
R68: =IFERROR((Q68/G68)^(1/COUNT($G$4:$Q$4))-1,"")
R69: =IFERROR((Q69/G69)^(1/COUNT($G$4:$Q$4))-1,"")
R70: =IFERROR((Q70/G70)^(1/COUNT($G$4:$Q$4))-1,"")
R71: =IFERROR((Q71/G71)^(1/COUNT($G$4:$Q$4))-1,"")
R72: =IFERROR((Q72/G72)^(1/COUNT($G$4:$Q$4))-1,"")
A74: x | B74: GHG Scope 1 and 2 Emissions | G74: 2014 | H74: =+G74+1 -> 2015 | I74: =+H74+1 -> 2016 | J74: =+I74+1 -> 2017 | K74: =+J74+1 -> 2018 | L74: =+K74+1 -> 2019 | M74: =+L74+1 -> 2020 | N74: =+M74+1 -> 2021 | O74: =+N74+1 -> 2022 | ... Q74: =+P74+1 -> 2024 | R74: ="CAGR "&$G$4&" - "&$Q$4 -> CAGR 2014 - 2024
B76: =+$B$6 -> INTERNATIONAL BUSINESS MACHINES CORPORATION | G76: =+G6+G20 -> 2438.663 | H76: =+H6+H20 -> 1787.506 | I76: =+I6+I20 -> 1289.493 | J76: =+J6+J20 -> 1201.781 | K76: =+K6+K20 -> 610 | L76: =+L6+L20 -> 558 | M76: =+M6+M20 -> 335 | N76: =+N6+N20 -> 299 | ... Q76: =+Q6+Q20 -> 0 | R76: =IFERROR((Q76/G76)^(1/COUNT($G$4:$Q$4))-1,"") -> -1
B77: =+$B$7 -> #VALUE! | G77: =+G7+G21 -> 0 | H77: =+H7+H21 -> 263.529 | I77: =+I7+I21 -> 290.253 | J77: =+J7+J21 -> 267.868 | K77: =+K7+K21 -> 241.038 | L77: =+L7+L21 -> 246.005 | M77: =+M7+M21 -> 176.928 | N77: =+N7+N21 -> 79.909 | ... Q77: =+Q7+Q21 -> 25.979 | R77: =IFERROR((Q77/G77)^(1/COUNT($G$4:$Q$4))-1,"")
B78: =+$B$8 -> #VALUE! | G78: =+G8+G22 -> 0 | H78: =+H8+H22 -> 196.688 | I78: =+I8+I22 -> 164.507 | J78: =+J8+J22 -> 144.597 | K78: =+K8+K22 -> 135.955 | L78: =+L8+L22 -> 153.877 | M78: =+M8+M22 -> 78.333 | N78: =+N8+N22 -> 63.843 | ... Q78: =+Q8+Q22 -> 11.16 | R78: =IFERROR((Q78/G78)^(1/COUNT($G$4:$Q$4))-1,"")
B79: =+$B$9 -> #VALUE! | G79: =+G9+G23 -> 581.349 | H79: =+H9+H23 -> 244.341 | I79: =+I9+I23 -> 125.573 | J79: =+J9+J23 -> 246.518 | K79: =+K9+K23 -> 282.337 | L79: =+L9+L23 -> 393.376 | M79: =+M9+M23 -> 574.219 | N79: =+N9+N23 -> 553.109 | ... Q79: =+Q9+Q23 -> 0 | R79: =IFERROR((Q79/G79)^(1/COUNT($G$4:$Q$4))-1,"") -> -1
B80: =+$B$10 -> #VALUE! | G80: =+G10+G24 -> 0 | H80: =+H10+H24 -> 386.72 | I80: =+I10+I24 -> 459.516 | J80: =+J10+J24 -> 365.721 | K80: =+K10+K24 -> 417.923 | L80: =+L10+L24 -> 379.532 | M80: =+M10+M24 -> 365.542 | N80: =+N10+N24 -> 429.577 | ... Q80: =+Q10+Q24 -> 383.2 | R80: =IFERROR((Q80/G80)^(1/COUNT($G$4:$Q$4))-1,"")
B81: =+$B$11 -> #VALUE! | G81: =+G11+G25 -> 0 | H81: =+H11+H25 -> 0 | I81: =+I11+I25 -> 434.78 | J81: =+J11+J25 -> 377.367 | K81: =+K11+K25 -> 305.712 | L81: =+L11+L25 -> 250.656 | M81: =+M11+M25 -> 198.871 | N81: =+N11+N25 -> 168.42 | ... Q81: =+Q11+Q25 -> 0 | R81: =IFERROR((Q81/G81)^(1/COUNT($G$4:$Q$4))-1,"")
G82: =+G12+G26 -> 0 | H82: =+H12+H26 -> 0 | I82: =+I12+I26 -> 0 | J82: =+J12+J26 -> 0 | K82: =+K12+K26 -> 0 | L82: =+L12+L26 -> 0 | M82: =+M12+M26 -> 0 | N82: =+N12+N26 -> 0 | ... Q82: =+Q12+Q26 -> 0 | R82: =IFERROR((Q82/G82)^(1/COUNT($G$4:$Q$4))-1,"")
G83: =+G13+G27 -> 0 | H83: =+H13+H27 -> 0 | I83: =+I13+I27 -> 0 | J83: =+J13+J27 -> 0 | K83: =+K13+K27 -> 0 | L83: =+L13+L27 -> 0 | M83: =+M13+M27 -> 0 | N83: =+N13+N27 -> 0 | ... Q83: =+Q13+Q27 -> 0 | R83: =IFERROR((Q83/G83)^(1/COUNT($G$4:$Q$4))-1,"")
G84: =+G14+G28 -> 0 | H84: =+H14+H28 -> 0 | I84: =+I14+I28 -> 0 | J84: =+J14+J28 -> 0 | K84: =+K14+K28 -> 0 | L84: =+L14+L28 -> 0 | M84: =+M14+M28 -> 0 | N84: =+N14+N28 -> 0 | ... Q84: =+Q14+Q28 -> 0 | R84: =IFERROR((Q84/G84)^(1/COUNT($G$4:$Q$4))-1,"")
G85: =+G15+G29 -> 0 | H85: =+H15+H29 -> 0 | I85: =+I15+I29 -> 0 | J85: =+J15+J29 -> 0 | K85: =+K15+K29 -> 0 | L85: =+L15+L29 -> 0 | M85: =+M15+M29 -> 0 | N85: =+N15+N29 -> 0 | ... Q85: =+Q15+Q29 -> 0 | R85: =IFERROR((Q85/G85)^(1/COUNT($G$4:$Q$4))-1,"")
G86: =+G16+G30 -> 0 | H86: =+H16+H30 -> 0 | I86: =+I16+I30 -> 0 | J86: =+J16+J30 -> 0 | K86: =+K16+K30 -> 0 | L86: =+L16+L30 -> 0 | M86: =+M16+M30 -> 0 | N86: =+N16+N30 -> 0 | ... Q86: =+Q16+Q30 -> 0 | R86: =IFERROR((Q86/G86)^(1/COUNT($G$4:$Q$4))-1,"")

Sheet DCF
B2: DCF
A4: x | B4: Key Assumptions | R4: #VALUE!
B6: Switches | E6: Bear Case | H6: Base Case | K6: Bull Case | X6: FCFF | Y6: FCFE | Z6: Tax Shield | AA6: Total Payout | AB6: NOPAT | AC6: Debt Borrowing | AD6: Cash Balance | AE6: Total Assets | AF6: Total Liabilities | AG6: Shareholder's Equity | AH6: Current Liabilities | AI6: Current Assets
B7: Revenue | C7: 2 | E7: Revenue | F7: -0.02 | H7: Revenue | K7: Revenue | L7: 0.02 | S7: Most Recent Fiscal Year | T7: 2024 | W7: 2022 | X7: =+E193 -> 11688.4 | Y7: =+E245 -> 21359 | Z7: =+H217 -> 244.11303 | AA7: =+E258 -> -6355 | AB7: =+E183 -> 6932.4 | AC7: =+E243 -> 14821 | AD7: =+E89 -> 7989
B8: EBIT | C8: 2 | E8: EBIT | F8: -0.01 | H8: EBIT | K8: EBIT | L8: 0.01 | S8: End of Fiscal Year | T8: 12/31/2024 | W8: =+W7+1 -> 2023 | X8: =+F193 -> 14857.52 | Y8: =+F245 -> 28977 | Z8: =+I217 -> 244.99115 | AA8: =+F258 -> -6442 | AB8: =+F183 -> 8068.52 | AC8: =+F243 -> 14675 | AD8: =+F89 -> 13441
B9: WACC | C9: 2 | E9: WACC | F9: =IFERROR(+I9+0.5%,"") -> 0.09101046 | H9: WACC | I9: =WACC!G25 -> 0.08601046 | K9: WACC | L9: =IFERROR(I9-0.5%,"") -> 0.08101046 | S9: Most Recent Quarter End Date | T9: 12/31/2024 | W9: =+W8+1 -> 2024 | X9: =+G193 -> 14905.184 | Y9: =+G245 -> 25166 | Z9: =+J217 -> 245.33735 | AA9: =+G258 -> -6798 | AB9: =+G183 -> 8105.184 | AC9: =+G243 -> 12350 | AD9: =+G89 -> 14591 | AE9: =Inputs!Q48 -> 137175 | AF9: =+Inputs!Q60 -> 109783 | AG9: =+AE9-AF9 -> 27392 | AH9: =+Inputs!Q54 -> 33142 | AI9: =+Inputs!Q38 -> 34482
B10: TGR | C10: 2 | E10: TGR | F10: =+I10-0.5% -> 0.015 | H10: TGR | I10: 0.02 | K10: TGR | L10: =+I10+0.5% -> 0.025 | S10: Valuation Date | T10: 4/20/2025 | W10: =+W9+1 -> 2025 | X10: =+H193 -> 11932.291 | Y10: =+H245 -> 24579.951 | Z10: =+K217 -> 250.17903 | AA10: =+H258 -> -7045.8328 | AB10: =+H183 -> 7547.5575 | AC10: =+H243 -> 13406.619 | AD10: =+H89 -> 18284.979 | AE10: =Inputs!Q48+DCF!H89+DCF!H91+DCF!H94+DCF!H97+DCF!H100+DCF!H106-DCF!G89-DCF!G91-DCF!G94-DCF!G97-DCF!G100-DCF!G106 -> 143153.21 | AF10: =AF9+(I111+I114+I117+I119-H111-H114-H117-H119) -> 113072.36 | AG10: =+AE10-AF10 -> 30080.851 | AH10: =+AH9+H111+H114-G111-G114 -> 33961.841 | AI10: =+H89+H91+H94+H97 -> 39633.23
W11: =+W10+1 -> 2026 | X11: =+I193 -> 13978.955 | Y11: =+I245 -> 29320.096 | Z11: =+L217 -> 252.86444 | AA11: =+I258 -> -7442.4421 | AB11: =+I183 -> 7874.2278 | AC11: =+I243 -> 14912.612 | AD11: =+I89 -> 22439.541 | AE11: =AE10+DCF!I89+DCF!I91+DCF!I94+DCF!I97+DCF!I100+DCF!I106-DCF!H89-DCF!H91-DCF!H94-DCF!H97-DCF!H100-DCF!H106 -> 147710.45 | AF11: =AF10+(DCF!I111+DCF!I114+DCF!I117+DCF!I119-DCF!H111-DCF!H114-DCF!H117-DCF!H119) -> 116361.73 | AG11: =+AE11-AF11 -> 31348.724 | AH11: =+AH10+I111+I114-H111-H114 -> 34724.509 | AI11: =+I89+I91+I94+I97 -> 43966.32
B12: WACC | C12: =CHOOSE(C9,F9,I9,L9) -> 0.08601046 | W12: =+W11+1 -> 2027 | X12: =+J193 -> 14199.951 | Y12: =+J245 -> 28451.863 | Z12: =+M217 -> 255.98722 | AA12: =+J258 -> -7644.814 | AB12: =+J183 -> 8284.6312 | AC12: =+J243 -> 14458.72 | AD12: =+J89 -> 26148.262
B13: TGR | C13: =CHOOSE(C10,F10,I10,L10) -> 0.02 | W13: =+W12+1 -> 2028 | X13: =+K193 -> 15830.407 | Y13: =+K245 -> 26387.221 | Z13: =+N217 -> 258.56903 | AA13: =+K258 -> -6212.7101 | AB13: =+K183 -> 9485.7321 | AC13: =+K243 -> 10716.38 | AD13: =+K89 -> 33970.231
W14: =+W13+1 -> 2029 | X14: =+L193 -> 16724.743 | Y14: =+L245 -> 29436.033 | Z14: =+O217 -> 261.0126 | AA14: =+L258 -> -7052.3573 | AB14: =+L183 -> 9909.0909 | AC14: =+L243 -> 12636.162 | AD14: =+L89 -> 41481.601
A15: x | B15: Operating Assumptions | E15: 2022 | F15: =+E15+1 -> 2023 | G15: =+F15+1 -> 2024 | H15: =+G15+1 -> 2025 | I15: =+H15+1 -> 2026 | J15: =+I15+1 -> 2027 | K15: =+J15+1 -> 2028 | L15: =+K15+1 -> 2029 | M15: =+L15+1 -> 2030 | ... Q15: =+P15+1 -> 2034
B17: Hybrid Platforms & Solutions | E17: =Sheet1!I5 -> 16458 | F17: =Sheet1!F5 -> 17396 | G17: =Sheet1!C5 -> 18808 | H17: =G17*(1+H19) -> 20594.76 | I17: =H17*(1+I19) -> 22654.236 | J17: =I17*(1+J19) -> 25055.585 | K17: =J17*(1+K19) -> 27836.755 | L17: =K17*(1+L19) -> 31065.819 | M17: =L17*(1+M19) -> 34793.717 | N17: =M17*(1+N19) -> 38621.026 | O17: =N17*(1+O19) -> 42483.128 | ... Q17: =P17*(1+Q19) -> 50011.138
B18: weight | E18: =Sheet1!J5 -> 0.69651699 | F18: =Sheet1!H5 -> 0.69553397 | G18: =Sheet1!E5 -> 0.6944065 | H18: =Sheet1!V11 -> 0.6914065 | I18: =Sheet1!W11 -> 0.6884065 | J18: =Sheet1!X11 -> 0.6854065 | K18: =Sheet1!Y11 -> 0.6854065 | L18: =Sheet1!Z11 -> 0.6854065 | M18: =Sheet1!AA11 -> 0.6854065 | N18: =Sheet1!AB11 -> 0.6854065 | O18: =Sheet1!AC11 -> 0.6854065 | ... Q18: =Sheet1!AE11 -> 0.6854065
B19: growth | F19: =Sheet1!G5 -> 0.056993559 | G19: =Sheet1!D5 -> 0.081168085 | H19: =Sheet1!V4 -> 0.095 | I19: =Sheet1!W4 -> 0.1 | J19: =Sheet1!X4 -> 0.106 | K19: =Sheet1!Y4 -> 0.111 | L19: =Sheet1!Z4 -> 0.116 | M19: =Sheet1!AA4 -> 0.12 | N19: =Sheet1!AB4 -> 0.11 | O19: =Sheet1!AC4 -> 0.1 | ... Q19: =Sheet1!AE4 -> 0.08
B20: Transaction Processing | E20: =Sheet1!I6 -> 7171 | F20: =Sheet1!F6 -> 7615 | G20: =Sheet1!C6 -> 8277 | H20: =G20*(1+$H$22) -> 8770.2562 | I20: =H20*(1+$H$22) -> 9292.9074 | J20: =I20*(1+$H$22) -> 9846.7052 | K20: =J20*(1+$H$22) -> 10433.506 | L20: =K20*(1+$H$22) -> 11055.276 | M20: =L20*(1+$H$22) -> 11714.1 | N20: =M20*(1+$H$22) -> 12412.185 | O20: =N20*(1+$H$22) -> 13151.872 | ... Q20: =P20*(1+$H$22) -> 14766.114
B21: weight | E21: =1-E18 -> 0.30348301 | F21: =1-F18 -> 0.30446603 | G21: =1-G18 -> 0.3055935 | H21: =1-DCF!H18 -> 0.3085935 | I21: =1-DCF!I18 -> 0.3115935 | J21: =1-DCF!J18 -> 0.3145935 | K21: =1-DCF!K18 -> 0.3145935 | L21: =1-DCF!L18 -> 0.3145935 | M21: =1-DCF!M18 -> 0.3145935 | N21: =1-DCF!N18 -> 0.3145935 | O21: =1-DCF!O18 -> 0.3145935 | ... Q21: =1-DCF!Q18 -> 0.3145935
B22: growth | F22: =Sheet1!G6 -> 0.061916051 | G22: =Sheet1!D6 -> 0.086933684 | H22: =Sheet1!J2 -> 0.059593602
B23: Revenue from Software | E23: =Sheet1!I7 -> 23629 | F23: =Sheet1!F7 -> 25011 | G23: =Sheet1!C7 -> 27085 | H23: =G23*(1+H24) -> 29362.139 | I23: =H23*(1+I24) -> 31928.673 | J23: =I23*(1+J24) -> 34846.981 | K23: =J23*(1+K24) -> 38151.446 | L23: =K23*(1+L24) -> 41900.013 | M23: =L23*(1+M24) -> 46131.77 | N23: =M23*(1+N24) -> 50474.729 | O23: =N23*(1+O24) -> 54880.587 | ... Q23: =P23*(1+Q24) -> 63657.805
B24: growth | F24: =Sheet1!G7 -> 0.058487452 | G24: =Sheet1!D7 -> 0.082923514 | H24: =H18*H19+H21*$H$22 -> 0.084073816 | I24: =I18*I19+I21*$H$22 -> 0.087409629 | J24: =J18*J19+J21*$H$22 -> 0.091400849 | K24: =K18*K19+K21*$H$22 -> 0.094827881 | L24: =L18*L19+L21*$H$22 -> 0.098254914 | M24: =M18*M19+M21*$H$22 -> 0.10099654 | N24: =N18*N19+N21*$H$22 -> 0.094142475 | O24: =O18*O19+O21*$H$22 -> 0.08728841 | ... Q24: =Q18*Q19+Q21*$H$22 -> 0.07358028
B25: Revenue from Consulting | E25: =Sheet1!F56 -> 20058 | F25: =Sheet1!G56 -> 20884 | G25: =Sheet1!H56 -> 20692 | H25: =Sheet1!I56 -> 21105.84 | I25: =Sheet1!J56 -> 21739.015 | J25: =Sheet1!K56 -> 22608.576 | K25: =Sheet1!L56 -> 23739.005 | L25: =Sheet1!M56 -> 24925.955 | ... Q25: =Sheet1!R56 -> 31812.537
B26: Revenue from Infrastructure | E26: =Sheet1!E59 -> 15288 | F26: =Sheet1!G59 -> 14593 | G26: =Sheet1!H59 -> 14020 | H26: =Sheet1!I59 -> 14648.096 | I26: =Sheet1!J59 -> 14500 | J26: =Sheet1!K59 -> 14000 | K26: =Sheet1!L59 -> 14630 | L26: =Sheet1!M59 -> 14500 | M26: =Sheet1!N59 -> 14000 | ... Q26: =Sheet1!R59 -> 14630
B27: Revenue from Financing and Other | E27: =Sheet1!E63+Sheet1!F65 -> 1554 | F27: =Sheet1!G63+Sheet1!G65 -> 1373 | G27: =Sheet1!H63+Sheet1!H65 -> 956 | H27: =Sheet1!I63+Sheet1!I65 -> 816.33948 | I27: =Sheet1!J63+Sheet1!J65 -> 696.17293 | J27: =Sheet1!K63+Sheet1!K65 -> 648.65152 | K27: =Sheet1!L63+Sheet1!L65 -> 627.62578 | L27: =Sheet1!M63+Sheet1!M65 -> 608.12451 | M27: =Sheet1!N63+Sheet1!N65 -> 594.45465 | ... Q27: =Sheet1!R63+Sheet1!R65 -> 539.38303
B28: In millions of USD
A29: x | B29: Income Statement | E29: 2022 | F29: =+E29+1 -> 2023 | G29: =+F29+1 -> 2024 | H29: =+G29+1 -> 2025 | I29: =+H29+1 -> 2026 | J29: =+I29+1 -> 2027 | K29: =+J29+1 -> 2028 | L29: =+K29+1 -> 2029 | M29: =+L29+1 -> 2030 | ... Q29: =+P29+1 -> 2034
B31: Revenue (Sales) | D31: =+_xlfn.XLOOKUP($B31,Inputs!$B:$B,Inputs!N:N) -> 57350 | E31: =+_xlfn.XLOOKUP($B31,Inputs!$B:$B,Inputs!O:O) -> 60530 | F31: =+_xlfn.XLOOKUP($B31,Inputs!$B:$B,Inputs!P:P) -> 61860 | G31: =+_xlfn.XLOOKUP($B31,Inputs!$B:$B,Inputs!Q:Q) -> 62753 | H31: =+H26+H27+H25+H23 -> 65932.415 | I31: =+I26+I27+I25+I23 -> 68863.861 | J31: =+J26+J27+J25+J23 -> 72104.208 | K31: =+K26+K27+K25+K23 -> 77148.077 | L31: =+L26+L27+L25+L23 -> 81934.093 | M31: =+M26+M27+M25+M23 -> 86898.477 | N31: =+N26+N27+N25+N23 -> 93167.843 | O31: =+O26+O27+O25+O23 -> 98802.243 | ... Q31: =+Q26+Q27+Q25+Q23 -> 110639.72
B32: % of growth | E32: =IFERROR((E31-D31)/D31,"") -> 0.055448997 | F32: =IFERROR((F31-E31)/E31,"") -> 0.021972576 | G32: =IFERROR((G31-F31)/F31,"") -> 0.014435823 | H32: =IFERROR(H31/G31-1,"") -> 0.050665542 | I32: =IFERROR(I31/H31-1,"") -> 0.044461383 | J32: =IFERROR(J31/I31-1,"") -> 0.047054391 | K32: =IFERROR(K31/J31-1,"") -> 0.069952483 | L32: =IFERROR(L31/K31-1,"") -> 0.062036751 | M32: =IFERROR(M31/L31-1,"") -> 0.06058997 | N32: =IFERROR(N31/M31-1,"") -> 0.072145869 | O32: =IFERROR(O31/N31-1,"") -> 0.060475803 | ... Q32: =IFERROR(Q31/P31-1,"") -> 0.062362286
B34: COGS (Cost of Goods Sold) | E34: =+_xlfn.XLOOKUP($B34,Inputs!$B:$B,Inputs!O:O) -> 27842 | F34: =+_xlfn.XLOOKUP($B34,Inputs!$B:$B,Inputs!P:P) -> 27560 | G34: =+_xlfn.XLOOKUP($B34,Inputs!$B:$B,Inputs!Q:Q) -> 27201 | H34: =H35*H$31 -> 29413.703 | I34: =I35*I$31 -> 30796.957 | J34: =J35*J$31 -> 32191.469 | K34: =K35*K$31 -> 34234.847 | L34: =L35*L$31 -> 36329.708 | M34: =M35*M$31 -> 38703.683 | N34: =N35*N$31 -> 41482.403 | O34: =O35*O$31 -> 43952.131 | ... Q34: =Q35*Q$31 -> 49199.549
B35: % of revenue | E35: =IFERROR(E34/E$31,"") -> 0.45997026 | F35: =IFERROR(F34/F$31,"") -> 0.44552215 | G35: =IFERROR(G34/G$31,"") -> 0.43346135 | H35: =AVERAGE(G35,F35,E35,(Inputs!N7/Inputs!N6),(Inputs!M7/Inputs!M6)) -> 0.446119 | I35: =AVERAGE(H35,G35,F35,(Inputs!N7/Inputs!N6),DCF!E35) -> 0.44721508 | J35: =AVERAGE(E35:I35) -> 0.44645757 | K35: =AVERAGE(F35:J35) -> 0.44375503 | L35: =AVERAGE(G35:K35) -> 0.4434016 | M35: =AVERAGE(H35:L35) -> 0.44538966 | N35: =AVERAGE(I35:M35) -> 0.44524379 | O35: =AVERAGE(J35:N35) -> 0.44484953 | P35: =AVERAGE(K35:O35) -> 0.44452792 | Q35: =AVERAGE(L35:P35) -> 0.4446825
B37: Gross Profit | E37: =+_xlfn.XLOOKUP($B37,Inputs!$B:$B,Inputs!O:O) -> 32688 | F37: =+_xlfn.XLOOKUP($B37,Inputs!$B:$B,Inputs!P:P) -> 34300 | G37: =+_xlfn.XLOOKUP($B37,Inputs!$B:$B,Inputs!Q:Q) -> 35552 | H37: =+H31-H34 -> 36518.712 | I37: =+I31-I34 -> 38066.904 | J37: =+J31-J34 -> 39912.739 | K37: =+K31-K34 -> 42913.23 | L37: =+L31-L34 -> 45604.384 | M37: =+M31-M34 -> 48194.794 | N37: =+N31-N34 -> 51685.44 | O37: =+O31-O34 -> 54850.112 | ... Q37: =+Q31-Q34 -> 61440.175
B38: Gross Profit Margin | E38: =IFERROR(E37/E$31,"") -> 0.54002974 | F38: =IFERROR(F37/F$31,"") -> 0.55447785 | G38: =IFERROR(G37/G$31,"") -> 0.56653865 | H38: =IFERROR(H37/H$31,"") -> 0.553881 | I38: =IFERROR(I37/I$31,"") -> 0.55278492 | J38: =IFERROR(J37/J$31,"") -> 0.55354243 | K38: =IFERROR(K37/K$31,"") -> 0.55624497 | L38: =IFERROR(L37/L$31,"") -> 0.5565984 | ... Q38: =IFERROR(Q37/Q$31,"") -> 0.5553175
B40: SG&A (Selling, General & Administrative) | E40: =+_xlfn.XLOOKUP($B40,Inputs!$B:$B,Inputs!O:O) -> 18609 | F40: =+_xlfn.XLOOKUP($B40,Inputs!$B:$B,Inputs!P:P) -> 19003 | G40: =+_xlfn.XLOOKUP($B40,Inputs!$B:$B,Inputs!Q:Q) -> 19688 | H40: =IFERROR(G40*(1+H32),"") -> 20685.503 | I40: =IFERROR(H40*(1+I32),"") -> 21605.209 | J40: =IFERROR(I40*(1+J32),"") -> 22621.829 | K40: =IFERROR(J40*(1+K32),"") -> 24204.282 | L40: =IFERROR(K40*(1+L32),"") -> 25705.837 | M40: =IFERROR(L40*(1+M32),"") -> 27263.353 | N40: =IFERROR(M40*(1+N32),"") -> 29230.292 | O40: =IFERROR(N40*(1+O32),"") -> 30998.017 | ... Q40: =IFERROR(P40*(1+Q32),"") -> 34711.885
B41: SG&A Margin | E41: =IFERROR(E40/E$31,"") -> 0.30743433 | F41: =IFERROR(F40/F$31,"") -> 0.30719366 | G41: =IFERROR(G40/G$31,"") -> 0.31373799 | H41: =IFERROR(AVERAGE(E41:G41),"") -> 0.30945533 | I41: =IFERROR(AVERAGE(F41:H41),"") -> 0.31012899 | J41: =IFERROR(AVERAGE(G41:I41),"") -> 0.31110744 | K41: =IFERROR(AVERAGE(H41:J41),"") -> 0.31023059 | L41: =IFERROR(AVERAGE(I41:K41),"") -> 0.310489 | M41: =IFERROR(AVERAGE(J41:L41),"") -> 0.31060901 | N41: =IFERROR(AVERAGE(K41:M41),"") -> 0.31044287 | O41: =IFERROR(AVERAGE(L41:N41),"") -> 0.31051363 | ... Q41: =IFERROR(AVERAGE(N41:P41),"") -> 0.31049278
B43: R&D (Research & Development) | E43: =+_xlfn.XLOOKUP($B43,Inputs!$B:$B,Inputs!O:O) -> 6567 | F43: =+_xlfn.XLOOKUP($B43,Inputs!$B:$B,Inputs!P:P) -> 6775 | G43: =+_xlfn.XLOOKUP($B43,Inputs!$B:$B,Inputs!Q:Q) -> 7479 | H43: =H44*H$31 -> 7911.8898 | I43: =I44*I$31 -> 8263.6633 | J43: =J44*J$31 -> 8652.505 | K43: =K44*K$31 -> 8679.1586 | L43: =L44*L$31 -> 9422.4206 | M43: =M44*M$31 -> 9776.0786 | N43: =N44*N$31 -> 10248.463 | O43: =O44*O$31 -> 10621.241 | ... Q43: =Q44*Q$31 -> 11340.572
B44: % of revenue | E44: =IFERROR(E43/E31,"") -> 0.10849166 | F44: =IFERROR(F43/F31,"") -> 0.1095215 | G44: =IFERROR(G43/G31,"") -> 0.11918155 | H44: 0.12 | I44: 0.12 | J44: 0.12 | K44: 0.1125 | L44: 0.115 | M44: 0.1125 | N44: 0.11 | O44: 0.1075 | P44: 0.105 | Q44: 0.1025
B46: Other Operating (Income) Expenses | E46: =+_xlfn.XLOOKUP($B46,Inputs!$B:$B,Inputs!O:O) -> -663 | F46: =+_xlfn.XLOOKUP($B46,Inputs!$B:$B,Inputs!P:P) -> -860 | G46: =+_xlfn.XLOOKUP($B46,Inputs!$B:$B,Inputs!Q:Q) -> -996 | H46: =IFERROR(AVERAGE(E46:G46)*(1+H32),"") -> -882.20883 | I46: =IFERROR(AVERAGE(F46:H46)*(1+I32),"") -> -953.3178 | J46: =IFERROR(AVERAGE(G46:I46)*(1+J32),"") -> -988.25413 | K46: =IFERROR(AVERAGE(H46:J46)*(1+K32),"") -> -1007.1037 | L46: =IFERROR(AVERAGE(I46:K46)*(1+L32),"") -> -1043.8673 | M46: =IFERROR(AVERAGE(J46:L46)*(1+M32),"") -> -1074.4572 | N46: =IFERROR(AVERAGE(K46:M46)*(1+N32),"") -> -1116.9717 | O46: =IFERROR(AVERAGE(L46:N46)*(1+O32),"") -> -1143.6511 | ... Q46: =IFERROR(AVERAGE(N46:P46)*(1+Q32),"") -> -1215.4952
B48: EBITDA | E48: =+_xlfn.XLOOKUP($B48,Inputs!$B:$B,Inputs!O:O) -> 12977 | F48: =+_xlfn.XLOOKUP($B48,Inputs!$B:$B,Inputs!P:P) -> 13778 | G48: =+_xlfn.XLOOKUP($B48,Inputs!$B:$B,Inputs!Q:Q) -> 14048 | H48: =H60+H51 -> 13528.436 | I48: =I60+I51 -> 14102.813 | J48: =J60+J51 -> 14870.052 | K48: =K60+K51 -> 16564.635 | L48: =L60+L51 -> 17361.685 | M48: =M60+M51 -> 18399.866 | N48: =N60+N51 -> 19816.696 | O48: =O60+O51 -> 21002.481 | ... Q48: =Q60+Q51 -> 23648.905
B49: EBITDA Margin | E49: =IFERROR(E48/E$31,"") -> 0.21438956 | F49: =IFERROR(F48/F$31,"") -> 0.22272874 | G49: =IFERROR(G48/G$31,"") -> 0.22386181 | H49: =IFERROR(H48/H$31,"") -> 0.20518641 | I49: =IFERROR(I48/I$31,"") -> 0.20479265 | J49: =IFERROR(J48/J$31,"") -> 0.20623002 | K49: =IFERROR(K48/K$31,"") -> 0.21471222 | L49: =IFERROR(L48/L$31,"") -> 0.21189818 | ... Q49: =IFERROR(Q48/Q$31,"") -> 0.21374696
B51: D&A (Depreciation & Amortization) | E51: =+_xlfn.XLOOKUP($B51,Inputs!$B:$B,Inputs!O:O) -> 4802 | F51: =+_xlfn.XLOOKUP($B51,Inputs!$B:$B,Inputs!P:P) -> 4396 | G51: =+_xlfn.XLOOKUP($B51,Inputs!$B:$B,Inputs!Q:Q) -> 4667 | H51: =+IFERROR(H54+H57,"") -> 4724.9082 | I51: =+IFERROR(I54+I57,"") -> 4951.4634 | J51: =+IFERROR(J54+J57,"") -> 5243.3934 | K51: =+IFERROR(K54+K57,"") -> 5527.7424 | L51: =+IFERROR(L54+L57,"") -> 5841.6914 | M51: =+IFERROR(M54+M57,"") -> 6170.0469 | N51: =+IFERROR(N54+N57,"") -> 6493.0385 | O51: =+IFERROR(O54+O57,"") -> 6627.9764 | ... Q51: =+IFERROR(Q54+Q57,"") -> 7045.6911
B52: % of PP&E+ROU Assets+Intangibles excl. Goodwill | E52: =IFERROR(E51/AVERAGE(Inputs!O39+Inputs!O42+Inputs!O44,Inputs!N39+Inputs!N42+Inputs!N44),"") -> 0.07461098 | F52: =IFERROR(F51/AVERAGE(Inputs!P39+Inputs!P42+Inputs!P44,Inputs!O39+Inputs!O42+Inputs!O44),"") -> 0.066075455 | G52: =IFERROR(G51/AVERAGE(Inputs!Q39+Inputs!Q42+Inputs!Q44,Inputs!P39+Inputs!P42+Inputs!P44),"") -> 0.067376962 | H52: =IFERROR(H51/(G100+G106),"") -> 0.24120211 | I52: =IFERROR(I51/(H100+H106),"") -> 0.24252877 | J52: =IFERROR(J51/(I100+I106),"") -> 0.25403878 | K52: =IFERROR(K51/(J100+J106),"") -> 0.26482438 | L52: =IFERROR(L51/(K100+K106),"") -> 0.27599672 | M52: =IFERROR(M51/(L100+L106),"") -> 0.28667412 | N52: =IFERROR(N51/(M100+M106),"") -> 0.2951077 | O52: =IFERROR(O51/(N100+N106),"") -> 0.29767048 | ... Q52: =IFERROR(Q51/(P100+P106),"") -> 0.3014554
B54: Depreciation Expense | E54: =+_xlfn.XLOOKUP($B54,Inputs!$B:$B,Inputs!O:O) -> 2407 | F54: =+_xlfn.XLOOKUP($B54,Inputs!$B:$B,Inputs!P:P) -> 2109 | G54: =+_xlfn.XLOOKUP($B54,Inputs!$B:$B,Inputs!Q:Q) -> 2168 | H54: =IFERROR(H55*(G101+G102),"") -> 2146.0815 | I54: =IFERROR(I55*(H101+H102),"") -> 2220.9302 | J54: =IFERROR(J55*(I101+I102),"") -> 2342.4266 | K54: =IFERROR(K55*(J101+J102),"") -> 2423.1111 | L54: =IFERROR(L55*(K101+K102),"") -> 2517.5606 | M54: =IFERROR(M55*(L101+L102),"") -> 2616.5561 | N54: =IFERROR(N55*(M101+M102),"") -> 2706.3802 | O54: =IFERROR(O55*(N101+N102),"") -> 2801.7389 | ... Q54: =IFERROR(Q55*(P101+P102),"") -> 2982.6666
B55: % of PP&E+ROU Assets | E55: =IFERROR(E54/AVERAGE(Inputs!O40+Inputs!O42,Inputs!N40+Inputs!N42),"") -> 0.10726381 | F55: =IFERROR(F54/AVERAGE(Inputs!P40+Inputs!P42,Inputs!O40+Inputs!O42),"") -> 0.098287312 | G55: =IFERROR(G54/AVERAGE(Inputs!Q40+Inputs!Q42,Inputs!P40+Inputs!P42),"") -> 0.10267582 | H55: =IFERROR(AVERAGE(E55:G55),"") -> 0.10274232 | I55: =IFERROR(AVERAGE(F55:H55),"") -> 0.10123515 | J55: =IFERROR(AVERAGE(G55:I55),"") -> 0.10221776 | K55: =IFERROR(AVERAGE(H55:J55),"") -> 0.10206508 | L55: =IFERROR(AVERAGE(I55:K55),"") -> 0.10183933 | M55: =IFERROR(AVERAGE(J55:L55),"") -> 0.10204072 | N55: =IFERROR(AVERAGE(K55:M55),"") -> 0.10198171 | O55: =IFERROR(AVERAGE(L55:N55),"") -> 0.10195392 | ... Q55: =IFERROR(AVERAGE(N55:P55),"") -> 0.10197592
B57: Amortization Expense | E57: =+_xlfn.XLOOKUP($B57,Inputs!$B:$B,Inputs!O:O) -> 2395 | F57: =+_xlfn.XLOOKUP($B57,Inputs!$B:$B,Inputs!P:P) -> 2287 | G57: =+_xlfn.XLOOKUP($B57,Inputs!$B:$B,Inputs!Q:Q) -> 2499 | H57: =+H58*G106 -> 2578.8267 | I57: =+I58*H106 -> 2730.5332 | J57: =+J58*I106 -> 2900.9669 | K57: =+K58*J106 -> 3104.6313 | L57: =+L58*K106 -> 3324.1308 | M57: =+M58*L106 -> 3553.4908 | N57: =+N58*M106 -> 3786.6583 | O57: =+O58*N106 -> 3826.2375 | ... Q57: =+Q58*P106 -> 4063.0245
B58: % of Intangibles excl. Goodwill | E58: =IFERROR(E57/AVERAGE(Inputs!N45:O45),"") -> 0.20215235 | F58: =IFERROR(F57/AVERAGE(Inputs!O45:P45),"") -> 0.20585059 | G58: =IFERROR(G57/AVERAGE(Inputs!P45:Q45),"") -> 0.23036504 | H58: =Inputs!H187/G106 -> 0.2419162 | I58: =Inputs!I187/H106 -> 0.23871444 | J58: =Inputs!J187/I106 -> 0.26139555 | K58: =Inputs!K187/J106 -> 0.28404655 | L58: =Inputs!L187/K106 -> 0.30720891 | M58: =Inputs!M187/L106 -> 0.33271521 | N58: =Inputs!N187/M106 -> 0.35357256 | O58: =Inputs!O187/N106 -> 0.36525427 | ... Q58: =Inputs!Q187/P106 -> 0.38186489
B60: Operating Income (EBIT) | E60: =+_xlfn.XLOOKUP($B60,Inputs!$B:$B,Inputs!O:O) -> 8175 | F60: =+_xlfn.XLOOKUP($B60,Inputs!$B:$B,Inputs!P:P) -> 9382 | G60: =+_xlfn.XLOOKUP($B60,Inputs!$B:$B,Inputs!Q:Q) -> 9381 | H60: =H37-H40-H43-H46 -> 8803.5274 | I60: =I37-I40-I43-I46 -> 9151.3494 | J60: =J37-J40-J43-J46 -> 9626.6587 | K60: =K37-K40-K43-K46 -> 11036.892 | L60: =L37-L40-L43-L46 -> 11519.994 | M60: =M37-M40-M43-M46 -> 12229.819 | N60: =N37-N40-N43-N46 -> 13323.657 | O60: =O37-O40-O43-O46 -> 14374.505 | ... Q60: =Q37-Q40-Q43-Q46 -> 16603.214
B61: Operating Margin | E61: =IFERROR(E60/E$31,"") -> 0.135057 | F61: =IFERROR(F60/F$31,"") -> 0.15166505 | G61: =IFERROR(G60/G$31,"") -> 0.14949086 | H61: =IFERROR(H60/H31,"") -> 0.13352351 | I61: =IFERROR(I60/I31,"") -> 0.13289045 | J61: =IFERROR(J60/J31,"") -> 0.13351036 | K61: =IFERROR(K60/K31,"") -> 0.14306115 | L61: =IFERROR(L60/L31,"") -> 0.14060074 | M61: =IFERROR(M60/M31,"") -> 0.14073687 | N61: =IFERROR(N60/N31,"") -> 0.14300704 | O61: =IFERROR(O60/O31,"") -> 0.14548764 | ... Q61: =IFERROR(Q60/Q31,"") -> 0.15006558
B63: Net Interest Expense (Income) | E63: =+_xlfn.XLOOKUP($B63,Inputs!$B:$B,Inputs!O:O) -> 1216 | F63: =+_xlfn.XLOOKUP($B63,Inputs!$B:$B,Inputs!P:P) -> 1607 | G63: =+_xlfn.XLOOKUP($B63,Inputs!$B:$B,Inputs!Q:Q) -> 1712 | H63: =-H66-H69 -> -1717.0574 | I63: =-I66-I69 -> -1813.2964 | J63: =-J66-J69 -> -1871.0807 | K63: =-K66-K69 -> -1948.0717 | L63: =-L66-L69 -> -2036.9657 | M63: =-M66-M69 -> -2121.1619 | N63: =-N66-N69 -> -2202.6337 | O63: =-O66-O69 -> -2291.0371 | ... Q63: =-Q66-Q69 -> -2476.6229
B64: % of Net Debt | E64: =IFERROR(E63/AVERAGE(Inputs!N117:O117),"") -> 0.025815491 | F64: =IFERROR(F63/AVERAGE(Inputs!O117:P117),"") -> 0.034739186 | G64: =IFERROR(G63/AVERAGE(Inputs!P117:Q117),"") -> 0.037918471 | H64: =IFERROR(H63/AVERAGE(G117+G119,H117+H119),"") -> -0.028570815 | I64: =IFERROR(I63/AVERAGE(H117+H119,I117+I119),"") -> -0.028753298 | J64: =IFERROR(J63/AVERAGE(I117+I119,J117+J119),"") -> -0.028662057 | K64: =IFERROR(K63/AVERAGE(J117+J119,K117+K119),"") -> -0.028707678 | L64: =IFERROR(L63/AVERAGE(K117+K119,L117+L119),"") -> -0.028684867 | M64: =IFERROR(M63/AVERAGE(L117+L119,M117+M119),"") -> -0.028696272 | N64: =IFERROR(N63/AVERAGE(M117+M119,N117+N119),"") -> -0.02869057 | O64: =IFERROR(O63/AVERAGE(N117+N119,O117+O119),"") -> -0.028693421 | ... Q64: =IFERROR(Q63/AVERAGE(P117+P119,Q117+Q119),"") -> -0.028692708
B66: Interest Expense | E66: =+_xlfn.XLOOKUP($B66,Inputs!$B:$B,Inputs!O:O) -> 1216 | F66: =+_xlfn.XLOOKUP($B66,Inputs!$B:$B,Inputs!P:P) -> 1607 | G66: =+_xlfn.XLOOKUP($B66,Inputs!$B:$B,Inputs!Q:Q) -> 1712 | H66: =H67*AVERAGE(Inputs!H229,Inputs!Q114) -> 1717.0574 | I66: =I67*AVERAGE(Inputs!I229,Inputs!H229) -> 1813.2964 | J66: =J67*AVERAGE(Inputs!J229,Inputs!I229) -> 1871.0807 | K66: =K67*AVERAGE(Inputs!K229,Inputs!J229) -> 1948.0717 | L66: =L67*AVERAGE(Inputs!L229,Inputs!K229) -> 2036.9657 | M66: =M67*AVERAGE(Inputs!M229,Inputs!L229) -> 2121.1619 | N66: =N67*AVERAGE(Inputs!N229,Inputs!M229) -> 2202.6337 | O66: =O67*AVERAGE(Inputs!O229,Inputs!N229) -> 2291.0371 | P66: =P67*AVERAGE(Inputs!P229,Inputs!O229) -> 2382.8587 | Q66: =Q67*AVERAGE(Inputs!Q229,Inputs!P229) -> 2476.6229
B67: % of Debt | E67: =+IFERROR(E66/AVERAGE(Inputs!N114:O114),"") -> 0.022280652 | F67: =+IFERROR(F66/AVERAGE(Inputs!O114:P114),"") -> 0.028205848 | G67: =+IFERROR(G66/AVERAGE(Inputs!P114:Q114),"") -> 0.028935782 | H67: =AVERAGE(G66/AVERAGE(Inputs!Q114,Inputs!P114),DCF!F66/AVERAGE(Inputs!P114,Inputs!O114)) -> 0.028570815 | I67: =AVERAGE(DCF!H66/AVERAGE(Inputs!H229,Inputs!Q114),DCF!G66/AVERAGE(Inputs!Q114,Inputs!P114)) -> 0.028753298 | J67: =AVERAGE(DCF!I66/AVERAGE(Inputs!I229,Inputs!H229),DCF!H66/AVERAGE(Inputs!H229,Inputs!Q114)) -> 0.028662057 | K67: =AVERAGE(DCF!J66/AVERAGE(Inputs!J229,Inputs!I229),DCF!I66/AVERAGE(Inputs!I229,Inputs!H229)) -> 0.028707678 | L67: =AVERAGE(DCF!K66/AVERAGE(Inputs!K229,Inputs!J229),DCF!J66/AVERAGE(Inputs!J229,Inputs!I229)) -> 0.028684867 | M67: =AVERAGE(DCF!L66/AVERAGE(Inputs!L229,Inputs!K229),DCF!K66/AVERAGE(Inputs!K229,Inputs!J229)) -> 0.028696272 | N67: =AVERAGE(DCF!M66/AVERAGE(Inputs!M229,Inputs!L229),DCF!L66/AVERAGE(Inputs!L229,Inputs!K229)) -> 0.02869057 | O67: =AVERAGE(DCF!N66/AVERAGE(Inputs!N229,Inputs!M229),DCF!M66/AVERAGE(Inputs!M229,Inputs!L229)) -> 0.028693421 | P67: =AVERAGE(DCF!O66/AVERAGE(Inputs!O229,Inputs!N229),DCF!N66/AVERAGE(Inputs!N229,Inputs!M229)) -> 0.028691995 | Q67: =AVERAGE(DCF!P66/AVERAGE(Inputs!P229,Inputs!O229),DCF!O66/AVERAGE(Inputs!O229,Inputs!N229)) -> 0.028692708
B69: Interest Income | E69: =+_xlfn.XLOOKUP($B69,Inputs!$B:$B,Inputs!O:O) -> 0 | F69: =+_xlfn.XLOOKUP($B69,Inputs!$B:$B,Inputs!P:P) -> 0 | G69: =+_xlfn.XLOOKUP($B69,Inputs!$B:$B,Inputs!Q:Q) -> 0
B70: % Cash & Cash Eq. & ST Investments | E70: =IFERROR(E69/+AVERAGE(Inputs!N32:O32),"") -> 0 | F70: =IFERROR(F69/+AVERAGE(Inputs!O32:P32),"") -> 0 | G70: =IFERROR(G69/+AVERAGE(Inputs!P32:Q32),"") -> 0
B72: FX (Gain) Loss | E72: =+_xlfn.XLOOKUP($B72,Inputs!$B:$B,Inputs!O:O) -> -643 | F72: =+_xlfn.XLOOKUP($B72,Inputs!$B:$B,Inputs!P:P) -> 116 | G72: =+_xlfn.XLOOKUP($B72,Inputs!$B:$B,Inputs!Q:Q) -> -458 | H72: =+H73*H$17 -> -110.15509 | I72: =+I73*I$17 -> -81.343424 | J72: =+J73*J$17 -> -135.61586 | K72: =+K73*K$17 -> -133.17053 | L72: =+L73*L$17 -> -142.77054 | M72: =+M73*M$17 -> -171.56 | N72: =+N73*N$17 -> -184.22874 | O72: =+O73*O$17 -> -202.45598 | ... Q72: =+Q73*Q$17 -> -239.35159
B73: % of revenue | H73: =Inputs!H234 -> -0.0053486951 | I73: =Inputs!I234 -> -0.0035906496 | J73: =Inputs!J234 -> -0.0054126002 | K73: =Inputs!K234 -> -0.0047839817 | L73: =Inputs!L234 -> -0.0045957438 | M73: =Inputs!M234 -> -0.0049307752 | N73: =Inputs!N234 -> -0.0047701669 | O73: =Inputs!O234 -> -0.004765562 | ... Q73: =Inputs!Q234 -> -0.0047859657
B75: Other Non-Operating (Income) Expenses | E75: =+_xlfn.XLOOKUP($B75,Inputs!$B:$B,Inputs!O:O) -> 6446 | F75: =+_xlfn.XLOOKUP($B75,Inputs!$B:$B,Inputs!P:P) -> -1030 | G75: =+_xlfn.XLOOKUP($B75,Inputs!$B:$B,Inputs!Q:Q) -> 2329 | H75: =IFERROR(AVERAGE(E75:G75)*(1+H32),"") -> 2712.4682 | I75: =IFERROR(AVERAGE(F75:H75)*(1+I32),"") -> 1396.6079 | J75: =IFERROR(AVERAGE(G75:I75)*(1+J32),"") -> 2247.0053 | K75: =IFERROR(AVERAGE(H75:J75)*(1+K32),"") -> 2266.9017 | L75: =IFERROR(AVERAGE(I75:K75)*(1+L32),"") -> 2092.3947 | M75: =IFERROR(AVERAGE(J75:L75)*(1+M32),"") -> 2335.5257 | N75: =IFERROR(AVERAGE(K75:M75)*(1+N32),"") -> 2392.6086 | O75: =IFERROR(AVERAGE(L75:N75)*(1+O32),"") -> 2411.002 | ... Q75: =IFERROR(AVERAGE(N75:P75)*(1+Q32),"") -> 2589.3333
B77: Pre-Tax Income (EBT) | E77: =+_xlfn.XLOOKUP($B77,Inputs!$B:$B,Inputs!O:O) -> 1156 | F77: =+_xlfn.XLOOKUP($B77,Inputs!$B:$B,Inputs!P:P) -> 8689 | G77: =+_xlfn.XLOOKUP($B77,Inputs!$B:$B,Inputs!Q:Q) -> 5798 | H77: =IFERROR(+H60-H63-H72-H75,"") -> 7918.2717 | I77: =IFERROR(+I60-I63-I72-I75,"") -> 9649.3814 | J77: =IFERROR(+J60-J63-J72-J75,"") -> 9386.35 | K77: =IFERROR(+K60-K63-K72-K75,"") -> 10851.233 | L77: =IFERROR(+L60-L63-L72-L75,"") -> 11607.335 | M77: =IFERROR(+M60-M63-M72-M75,"") -> 12187.016 | N77: =IFERROR(+N60-N63-N72-N75,"") -> 13317.911 | O77: =IFERROR(+O60-O63-O72-O75,"") -> 14456.996 | ... Q77: =IFERROR(+Q60-Q63-Q72-Q75,"") -> 16729.855
B79: Tax Expense (Benefits) | C79: non-GAAP | E79: =E80*E77 -> 175.712 | F79: =F80*F77 -> 1216.46 | G79: =G80*G77 -> 788.528 | H79: =IFERROR(H80*H77,"") -> 1129.6734 | I79: =IFERROR(I80*I77,"") -> 1346.6248 | J79: =IFERROR(J80*J77,"") -> 1308.5267 | K79: =IFERROR(K80*K77,"") -> 1525.0671 | L79: =IFERROR(L80*L77,"") -> 1623.1163 | M79: =IFERROR(M80*M77,"") -> 1705.3129 | N79: =IFERROR(N80*N77,"") -> 1865.8716 | O79: =IFERROR(O80*O77,"") -> 2023.336 | ... Q79: =IFERROR(Q80*Q77,"") -> 2342.4778
B80: % of EBT | E80: =Inputs!O236 -> 0.152 | F80: =Inputs!P236 -> 0.14 | G80: =Inputs!Q236 -> 0.136 | H80: =IFERROR(AVERAGE(E80:G80),"") -> 0.14266667 | I80: =IFERROR(AVERAGE(F80:H80),"") -> 0.13955556 | J80: =IFERROR(AVERAGE(G80:I80),"") -> 0.13940741 | K80: =IFERROR(AVERAGE(H80:J80),"") -> 0.14054321 | L80: =IFERROR(AVERAGE(I80:K80),"") -> 0.13983539 | M80: =IFERROR(AVERAGE(J80:L80),"") -> 0.13992867 | N80: =IFERROR(AVERAGE(K80:M80),"") -> 0.14010242 | O80: =IFERROR(AVERAGE(L80:N80),"") -> 0.13995549 | ... Q80: =IFERROR(AVERAGE(N80:P80),"") -> 0.14001782
B82: Net Income | E82: =+_xlfn.XLOOKUP($B82,Inputs!$B:$B,Inputs!O:O) -> 1782 | F82: =+_xlfn.XLOOKUP($B82,Inputs!$B:$B,Inputs!P:P) -> 7513 | G82: =+_xlfn.XLOOKUP($B82,Inputs!$B:$B,Inputs!Q:Q) -> 6016 | H82: =IFERROR(+H77-H79,"") -> 6788.5982 | I82: =IFERROR(+I77-I79,"") -> 8302.7566 | J82: =IFERROR(+J77-J79,"") -> 8077.8233 | K82: =IFERROR(+K77-K79,"") -> 9326.1658 | L82: =IFERROR(+L77-L79,"") -> 9984.219 | M82: =IFERROR(+M77-M79,"") -> 10481.703 | N82: =IFERROR(+N77-N79,"") -> 11452.039 | O82: =IFERROR(+O77-O79,"") -> 12433.66 | ... Q82: =IFERROR(+Q77-Q79,"") -> 14387.378
B83: Net Income Margin | E83: =IFERROR(E82/E$31,"") -> 0.029439947 | F83: =IFERROR(F82/F$31,"") -> 0.12145167 | G83: =IFERROR(G82/G$31,"") -> 0.095867927 | H83: =IFERROR(H82/H$31,"") -> 0.10296299 | I83: =IFERROR(I82/I$31,"") -> 0.12056769 | J83: =IFERROR(J82/J$31,"") -> 0.11202985 | K83: =IFERROR(K82/K$31,"") -> 0.12088656 | L83: =IFERROR(L82/L$31,"") -> 0.12185671 | ... Q83: =IFERROR(Q82/Q$31,"") -> 0.13003808
A85: x | B85: Balance Sheet | E85: =E29 -> 2022 | F85: =F29 -> 2023 | G85: =G29 -> 2024 | H85: =H29 -> 2025 | I85: =I29 -> 2026 | J85: =J29 -> 2027 | K85: =K29 -> 2028 | L85: =L29 -> 2029 | ... Q85: =Q29 -> 2034
B87: Assets
B89: Cash & Cash Equivalents & ST Investments | E89: =+_xlfn.XLOOKUP($B89,Inputs!$B:$B,Inputs!O:O) -> 7989 | F89: =+_xlfn.XLOOKUP($B89,Inputs!$B:$B,Inputs!P:P) -> 13441 | G89: =+_xlfn.XLOOKUP($B89,Inputs!$B:$B,Inputs!Q:Q) -> 14591 | H89: =IFERROR(G89+H166,"") -> 18284.979 | I89: =IFERROR(H89+I166,"") -> 22439.541 | J89: =IFERROR(I89+J166,"") -> 26148.262 | K89: =IFERROR(J89+K166,"") -> 33970.231 | L89: =IFERROR(K89+L166,"") -> 41481.601 | M89: =IFERROR(L89+M166,"") -> 48918.654 | N89: =IFERROR(M89+N166,"") -> 57770.987 | O89: =IFERROR(N89+O166,"") -> 67373.949 | ... Q89: =IFERROR(P89+Q166,"") -> 90105.622
B91: Accounts Receivable | E91: =+_xlfn.XLOOKUP($B91,Inputs!$B:$B,Inputs!O:O) -> 7358 | F91: =+_xlfn.XLOOKUP($B91,Inputs!$B:$B,Inputs!P:P) -> 7854 | G91: =+_xlfn.XLOOKUP($B91,Inputs!$B:$B,Inputs!Q:Q) -> 7751 | H91: =IFERROR(H92*H31/365,"") -> 8183.9286 | I91: =IFERROR(I92*I31/365,"") -> 8606.7097 | J91: =IFERROR(J92*J31/365,"") -> 8964.042 | K91: =IFERROR(K92*K31/365,"") -> 9603.0889 | L91: =IFERROR(L92*L31/365,"") -> 10208.393 | M91: =IFERROR(M92*M31/365,"") -> 10815.658 | N91: =IFERROR(N92*N31/365,"") -> 11600.389 | O91: =IFERROR(O92*O31/365,"") -> 12303.071 | ... Q91: =IFERROR(Q92*Q31/365,"") -> 13775.807
B92: DSO | E92: =IFERROR(E91/E31*365,"") -> 44.369238 | F92: =IFERROR(F91/F31*365,"") -> 46.341901 | G92: =IFERROR(G91/G31*366,"") -> 45.206859 | H92: =IFERROR(AVERAGE(E92:G92),"") -> 45.305999 | I92: =IFERROR(AVERAGE(F92:H92),"") -> 45.618253 | J92: =IFERROR(AVERAGE(G92:I92),"") -> 45.377037 | K92: =IFERROR(AVERAGE(H92:J92),"") -> 45.433763 | L92: =IFERROR(AVERAGE(I92:K92),"") -> 45.476351 | M92: =IFERROR(AVERAGE(J92:L92),"") -> 45.42905 | N92: =IFERROR(AVERAGE(K92:M92),"") -> 45.446388 | O92: =IFERROR(AVERAGE(L92:N92),"") -> 45.450597 | ... Q92: =IFERROR(AVERAGE(N92:P92),"") -> 45.446332
B94: Inventory | E94: =+_xlfn.XLOOKUP($B94,Inputs!$B:$B,Inputs!O:O) -> 1552 | F94: =+_xlfn.XLOOKUP($B94,Inputs!$B:$B,Inputs!P:P) -> 1161 | G94: =+_xlfn.XLOOKUP($B94,Inputs!$B:$B,Inputs!Q:Q) -> 1289 | H94: =+IFERROR(H95*H34/365,"") -> 1424.1856 | I94: =+IFERROR(I95*I34/365,"") -> 1415.9758 | J94: =+IFERROR(J95*J34/365,"") -> 1521.4211 | K94: =+IFERROR(K95*K34/365,"") -> 1616.5526 | L94: =+IFERROR(L95*L34/365,"") -> 1700.9438 | M94: =+IFERROR(M95*M34/365,"") -> 1822.9534 | N94: =+IFERROR(N95*N34/365,"") -> 1951.6005 | O94: =+IFERROR(O95*O34/365,"") -> 2065.2573 | ... Q94: =+IFERROR(Q95*Q34/365,"") -> 2313.6978
B95: DIH | E95: =IFERROR(E94/E34*365,"") -> 20.346239 | F95: =IFERROR(F94/F34*365,"") -> 15.376089 | G95: =IFERROR(G94/G34*365,"") -> 17.296607 | H95: =IFERROR(AVERAGE(E95:G95),"") -> 17.672978 | I95: =IFERROR(AVERAGE(F95:H95),"") -> 16.781891 | J95: =IFERROR(AVERAGE(G95:I95),"") -> 17.250492 | K95: =IFERROR(AVERAGE(H95:J95),"") -> 17.23512 | L95: =IFERROR(AVERAGE(I95:K95),"") -> 17.089168 | M95: =IFERROR(AVERAGE(J95:L95),"") -> 17.191593 | N95: =IFERROR(AVERAGE(K95:M95),"") -> 17.171961 | O95: =IFERROR(AVERAGE(L95:N95),"") -> 17.150907 | ... Q95: =IFERROR(AVERAGE(N95:P95),"") -> 17.164785
B97: Prepaid expenses and Other Current Assets | E97: =+_xlfn.XLOOKUP($B97,Inputs!$B:$B,Inputs!O:O) -> 12219 | F97: =+_xlfn.XLOOKUP($B97,Inputs!$B:$B,Inputs!P:P) -> 10452 | G97: =+_xlfn.XLOOKUP($B97,Inputs!$B:$B,Inputs!Q:Q) -> 10851 | H97: =IFERROR(AVERAGE(E97:G97)*(1+H32),"") -> 11740.137 | I97: =IFERROR(AVERAGE(F97:H97)*(1+I32),"") -> 11504.093 | J97: =IFERROR(AVERAGE(G97:I97)*(1+J32),"") -> 11899.853 | K97: =IFERROR(AVERAGE(H97:J97)*(1+K32),"") -> 12534.167 | L97: =IFERROR(AVERAGE(I97:K97)*(1+L32),"") -> 12722.532 | M97: =IFERROR(AVERAGE(J97:L97)*(1+M32),"") -> 13135.956 | N97: =IFERROR(AVERAGE(K97:M97)*(1+N32),"") -> 13720.842 | O97: =IFERROR(AVERAGE(L97:N97)*(1+O32),"") -> 13990.974 | ... Q97: =IFERROR(AVERAGE(N97:P97)*(1+Q32),"") -> 14895.745
B98: % of revenue | E98: =IFERROR(E97/E$31,"") -> 0.20186684 | F98: =IFERROR(F97/F$31,"") -> 0.16896217 | G98: =IFERROR(G97/G$31,"") -> 0.17291604 | H98: =IFERROR(AVERAGE(E98:G98),"") -> 0.18124835 | I98: =IFERROR(AVERAGE(F98:H98),"") -> 0.17437552 | J98: =IFERROR(AVERAGE(G98:I98),"") -> 0.17617997 | K98: =IFERROR(AVERAGE(H98:J98),"") -> 0.17726795 | L98: =IFERROR(AVERAGE(I98:K98),"") -> 0.17594114 | M98: =IFERROR(AVERAGE(J98:L98),"") -> 0.17646302 | N98: =IFERROR(AVERAGE(K98:M98),"") -> 0.17655737 | O98: =IFERROR(AVERAGE(L98:N98),"") -> 0.17632051 | ... Q98: =IFERROR(AVERAGE(N98:P98),"") -> 0.17644162
B100: Net PP&E (Property, Plant and Equipment) + ROU Assets | E100: =+E101+E102-E104 -> 8212 | F100: =+F101+F102-F104 -> 8721 | G100: =+G101+G102-G104 -> 8929 | H100: =IFERROR(H101+H102-H104,"") -> 8977.4912 | I100: =IFERROR(I101+I102-I104,"") -> 9542.1333 | J100: =IFERROR(J101+J102-J104,"") -> 9943.2295 | K100: =IFERROR(K101+K102-K104,"") -> 10345.375 | L100: =IFERROR(L101+L102-L104,"") -> 10842.582 | M100: =IFERROR(M101+M102-M104,"") -> 11292.561 | N100: =IFERROR(N101+N102-N104,"") -> 11790.607 | O100: =IFERROR(O101+O102-O104,"") -> 12275.416 | ... Q100: =IFERROR(Q101+Q102-Q104,"") -> 13254.042
B101: Gross PP&E (Property, Plant and Equipment) | E101: =+_xlfn.XLOOKUP("Gross PP&E (Property, Plant and Equipment)",Inputs!$B:$B,Inputs!O:O) -> 18695 | F101: =+_xlfn.XLOOKUP("Gross PP&E (Property, Plant and Equipment)",Inputs!$B:$B,Inputs!P:P) -> 18122 | G101: =+_xlfn.XLOOKUP("Gross PP&E (Property, Plant and Equipment)",Inputs!$B:$B,Inputs!Q:Q) -> 17691 | H101: =+IFERROR(G101-H135,"") -> 18629.722 | I101: =+IFERROR(H101-I135,"") -> 19399.839 | J101: =+IFERROR(I101-J135,"") -> 20083.051 | K101: =+IFERROR(J101-K135,"") -> 20812.809 | L101: =+IFERROR(K101-L135,"") -> 21478.749 | M101: =+IFERROR(L101-M135,"") -> 22129.194 | N101: =+IFERROR(M101-N135,"") -> 22753.523 | O101: =+IFERROR(N101-O135,"") -> 23357.208 | ... Q101: =+IFERROR(P101-Q135,"") -> 24588.987
B102: Right-of-Use Assets | E102: =+_xlfn.XLOOKUP("Right-of-Use Assets",Inputs!$B:$B,Inputs!O:O) -> 2878 | F102: =+_xlfn.XLOOKUP("Right-of-Use Assets",Inputs!$B:$B,Inputs!P:P) -> 3220 | G102: =+_xlfn.XLOOKUP("Right-of-Use Assets",Inputs!$B:$B,Inputs!Q:Q) -> 3197 | H102: =IFERROR(H103*H$31,"") -> 3308.6087 | I102: =IFERROR(I103*I$31,"") -> 3516.2029 | J102: =IFERROR(J103*J$31,"") -> 3657.7936 | K102: =IFERROR(K103*K$31,"") -> 3908.0977 | L102: =IFERROR(L103*L$31,"") -> 4163.5238 | M102: =IFERROR(M103*M$31,"") -> 4408.7041 | N102: =IFERROR(N103*N$31,"") -> 4726.9197 | O102: =IFERROR(O103*O$31,"") -> 5015.367 | ... Q102: =IFERROR(Q103*Q$31,"") -> 5614.6311
B103: % of revenue | E103: =IFERROR(E102/E$31,"") -> 0.047546671 | F103: =IFERROR(F102/F$31,"") -> 0.052053023 | G103: =IFERROR(G102/G$31,"") -> 0.050945772 | H103: =IFERROR(AVERAGE(E103:G103),"") -> 0.050181822 | I103: =IFERROR(AVERAGE(F103:H103),"") -> 0.051060205 | J103: =IFERROR(AVERAGE(G103:I103),"") -> 0.050729266 | K103: =IFERROR(AVERAGE(H103:J103),"") -> 0.050657098 | L103: =IFERROR(AVERAGE(I103:K103),"") -> 0.050815523 | M103: =IFERROR(AVERAGE(J103:L103),"") -> 0.050733962 | N103: =IFERROR(AVERAGE(K103:M103),"") -> 0.050735528 | O103: =IFERROR(AVERAGE(L103:N103),"") -> 0.050761671 | ... Q103: =IFERROR(AVERAGE(N103:P103),"") -> 0.050746973
B104: Accumulated Depreciation | E104: =+_xlfn.XLOOKUP($B104,Inputs!$B:$B,Inputs!O:O) -> 13361 | F104: =+_xlfn.XLOOKUP($B104,Inputs!$B:$B,Inputs!P:P) -> 12621 | G104: =+_xlfn.XLOOKUP($B104,Inputs!$B:$B,Inputs!Q:Q) -> 11959 | H104: =H101*H105 -> 12960.839 | I104: =I101*I105 -> 13373.909 | J104: =J101*J105 -> 13797.615 | K104: =K101*K105 -> 14375.531 | L104: =L101*L105 -> 14799.69 | M104: =M101*M105 -> 15245.337 | N104: =N101*N105 -> 15689.835 | O104: =O101*O105 -> 16097.159 | ... Q104: =Q101*Q105 -> 16949.576
B105: % of gross PPE | E105: =E104/E101 -> 0.71468307 | F105: =F104/F101 -> 0.69644631 | G105: =G104/G101 -> 0.67599344 | H105: =AVERAGE(DCF!E105:G105) -> 0.69570761 | I105: =AVERAGE(DCF!F105:H105) -> 0.68938245 | J105: =AVERAGE(DCF!G105:I105) -> 0.68702783 | K105: =AVERAGE(DCF!H105:J105) -> 0.69070596 | L105: =AVERAGE(DCF!I105:K105) -> 0.68903875 | M105: =AVERAGE(DCF!J105:L105) -> 0.68892418 | N105: =AVERAGE(DCF!K105:M105) -> 0.6895563 | O105: =AVERAGE(DCF!L105:N105) -> 0.68917308 | ... Q105: =AVERAGE(DCF!N105:P105) -> 0.68931574
B106: Intangibles excl. Goodwill | E106: =E107*Inputs!O175-Inputs!O15+Inputs!N45 -> 11184 | F106: =F107*Inputs!P175-Inputs!P15+Inputs!O45 -> 11036 | G106: =G107*Inputs!Q175-Inputs!Q15+Inputs!P45 -> 10660 | H106: =G106+Inputs!H188 -> 11438.492 | I106: =H106+Inputs!I188 -> 11097.996 | J106: =I106+Inputs!J188 -> 10930.009 | K106: =J106+Inputs!K188 -> 10820.424 | L106: =K106+Inputs!L188 -> 10680.278 | M106: =L106+Inputs!M188 -> 10709.706 | N106: =M106+Inputs!N188 -> 10475.545 | O106: =N106+Inputs!O188 -> 10489.632 | ... Q106: =P106+Inputs!Q188 -> 10916.917
B107: growing with % of Acquisitions (before amortization) | E107: =IFERROR(((Inputs!O45+Inputs!O15)-(Inputs!N45))/Inputs!O175,"") -> 0.40301887 | F107: =IFERROR(((Inputs!P45+Inputs!P15)-(Inputs!O45))/Inputs!P175,"") -> 0.41158361 | G107: =IFERROR(((Inputs!Q45+Inputs!Q15)-(Inputs!P45))/Inputs!Q175,"") -> 0.60398293 | H107: =AVERAGE(E107:G107) -> 0.4728618 | I107: =AVERAGE(F107:H107) -> 0.49614278 | J107: =AVERAGE(G107:I107) -> 0.52432917 | K107: =AVERAGE(H107:J107) -> 0.49777792 | L107: =AVERAGE(I107:K107) -> 0.50608329 | M107: =AVERAGE(J107:L107) -> 0.50939679 | N107: =AVERAGE(K107:M107) -> 0.50441933 | O107: =AVERAGE(L107:N107) -> 0.50663314 | ... Q107: =AVERAGE(N107:P107) -> 0.5059563
B109: Liabilities
B111: Accounts Payable | E111: =+_xlfn.XLOOKUP($B111,Inputs!$B:$B,Inputs!O:O) -> 4051 | F111: =+_xlfn.XLOOKUP($B111,Inputs!$B:$B,Inputs!P:P) -> 4132 | G111: =+_xlfn.XLOOKUP($B111,Inputs!$B:$B,Inputs!Q:Q) -> 4032 | H111: =+IFERROR(H112*H34/365,"") -> 4353.8457 | I111: =+IFERROR(I112*I34/365,"") -> 4584.48 | J111: =+IFERROR(J112*J34/365,"") -> 4780.6308 | K111: =+IFERROR(K112*K34/365,"") -> 5082.6034 | L111: =+IFERROR(L112*L34/365,"") -> 5398.9635 | M111: =+IFERROR(M112*M34/365,"") -> 5748.5181 | N111: =+IFERROR(N112*N34/365,"") -> 6161.5114 | O111: =+IFERROR(O112*O34/365,"") -> 6529.3773 | ... Q111: =+IFERROR(Q112*Q34/365,"") -> 7308.2385
B112: DPO | E112: =IFERROR(E111/E$34*365,"") -> 53.107356 | F112: =IFERROR(F111/F$34*365,"") -> 54.723512 | G112: =IFERROR(G111/G$34*366,"") -> 54.252123 | H112: =IFERROR(AVERAGE(E112:G112),"") -> 54.027664 | I112: =IFERROR(AVERAGE(F112:H112),"") -> 54.334433 | J112: =IFERROR(AVERAGE(G112:I112),"") -> 54.20474 | K112: =IFERROR(AVERAGE(H112:J112),"") -> 54.188946 | L112: =IFERROR(AVERAGE(I112:K112),"") -> 54.242706 | M112: =IFERROR(AVERAGE(J112:L112),"") -> 54.212131 | N112: =IFERROR(AVERAGE(K112:M112),"") -> 54.214594 | O112: =IFERROR(AVERAGE(L112:N112),"") -> 54.223144 | ... Q112: =IFERROR(AVERAGE(N112:P112),"") -> 54.21812
B114: Accrued Expenses and Other Current Liabilities | E114: =+_xlfn.XLOOKUP($B114,Inputs!$B:$B,Inputs!O:O) -> 21820 | F114: =+_xlfn.XLOOKUP($B114,Inputs!$B:$B,Inputs!P:P) -> 22744 | G114: =+_xlfn.XLOOKUP($B114,Inputs!$B:$B,Inputs!Q:Q) -> 23253 | H114: =IFERROR(AVERAGE(E114:G114)*(1+H32),"") -> 23750.995 | I114: =IFERROR(AVERAGE(F114:H114)*(1+I32),"") -> 24283.029 | J114: =IFERROR(AVERAGE(G114:I114)*(1+J32),"") -> 24880.464 | K114: =IFERROR(AVERAGE(H114:J114)*(1+K32),"") -> 26005.013 | L114: =IFERROR(AVERAGE(I114:K114)*(1+L32),"") -> 26610.572 | M114: =IFERROR(AVERAGE(J114:L114)*(1+M32),"") -> 27397.177 | N114: =IFERROR(AVERAGE(K114:M114)*(1+N32),"") -> 28595.117 | O114: =IFERROR(AVERAGE(L114:N114)*(1+O32),"") -> 29199.447 | ... Q114: =IFERROR(AVERAGE(N114:P114)*(1+Q32),"") -> 31066.094
B115: growing with revenue | E115: =IFERROR(E114/E$31,"") -> 0.36048241 | F115: =IFERROR(F114/F$31,"") -> 0.36766893 | G115: =IFERROR(G114/G$31,"") -> 0.37054802 | H115: =IFERROR(H114/H$31,"") -> 0.36023245 | I115: =IFERROR(I114/I$31,"") -> 0.35262369 | J115: =IFERROR(J114/J$31,"") -> 0.34506258 | K115: =IFERROR(K114/K$31,"") -> 0.33707921 | L115: =IFERROR(L114/L$31,"") -> 0.32478021 | ... Q115: =IFERROR(Q114/Q$31,"") -> 0.28078608
B117: Total Borrowings | E117: =+_xlfn.XLOOKUP($B117,Inputs!$B:$B,Inputs!O:O) -> 50949 | F117: =+_xlfn.XLOOKUP($B117,Inputs!$B:$B,Inputs!P:P) -> 56547 | G117: =+_xlfn.XLOOKUP($B117,Inputs!$B:$B,Inputs!Q:Q) -> 54973 | H117: =IFERROR(G117+H157+H159,"") -> 58285.619 | I117: =IFERROR(H117+I157+I159,"") -> 60594.231 | J117: =IFERROR(I117+J157+J159,"") -> 62338.951 | K117: =IFERROR(J117+K157+K159,"") -> 65329.331 | L117: =IFERROR(K117+L157+L159,"") -> 68113.492 | M117: =IFERROR(L117+M157+M159,"") -> 70605.698 | N117: =IFERROR(M117+N157+N159,"") -> 73222.738 | O117: =IFERROR(N117+O157+O159,"") -> 76108.59 | ... Q117: =IFERROR(P117+Q157+Q159,"") -> 82003.026
B119: Total Leases | E119: =+_xlfn.XLOOKUP($B119,Inputs!$B:$B,Inputs!O:O) -> 3064 | F119: =+_xlfn.XLOOKUP($B119,Inputs!$B:$B,Inputs!P:P) -> 3388 | G119: =+_xlfn.XLOOKUP($B119,Inputs!$B:$B,Inputs!Q:Q) -> 3423 | H119: =+IFERROR(H120*H31,"") -> 3514.9791 | I119: =+IFERROR(I120*I31,"") -> 3733.0612 | J119: =+IFERROR(J120*J31,"") -> 3895.2697 | K119: =+IFERROR(K120*K31,"") -> 4154.2676 | L119: =+IFERROR(L120*L31,"") -> 4426.6271 | M119: =+IFERROR(M120*M31,"") -> 4689.5468 | N119: =+IFERROR(N120*N31,"") -> 5026.1091 | O119: =+IFERROR(O120*O31,"") -> 5333.3225 | ... Q119: =+IFERROR(Q120*Q31,"") -> 5970.5152
B120: % of revenues | E120: =IFERROR(E119/E$31,"") -> 0.050619528 | F120: =IFERROR(F119/F$31,"") -> 0.054768833 | G120: =IFERROR(G119/G$31,"") -> 0.054547193 | H120: =+IFERROR(AVERAGE(E120:G120),"") -> 0.053311851 | I120: =+IFERROR(AVERAGE(F120:H120),"") -> 0.054209292 | J120: =+IFERROR(AVERAGE(G120:I120),"") -> 0.054022779 | K120: =+IFERROR(AVERAGE(H120:J120),"") -> 0.053847974 | L120: =+IFERROR(AVERAGE(I120:K120),"") -> 0.054026682 | M120: =+IFERROR(AVERAGE(J120:L120),"") -> 0.053965812 | N120: =+IFERROR(AVERAGE(K120:M120),"") -> 0.053946822 | O120: =+IFERROR(AVERAGE(L120:N120),"") -> 0.053979772 | ... Q120: =+IFERROR(AVERAGE(N120:P120),"") -> 0.053963577
A122: x | B122: Cash Flow | E122: =E29 -> 2022 | F122: =F29 -> 2023 | G122: =G29 -> 2024 | H122: =H29 -> 2025 | I122: =I29 -> 2026 | J122: =J29 -> 2027 | K122: =K29 -> 2028 | L122: =L29 -> 2029 | ... Q122: =Q29 -> 2034
B124: D&A (Depreciation & Amortization) | E124: =+E51 -> 4802 | F124: =+F51 -> 4396 | G124: =+G51 -> 4667 | H124: =+H51 -> 4724.9082 | I124: =+I51 -> 4951.4634 | J124: =+J51 -> 5243.3934 | K124: =+K51 -> 5527.7424 | L124: =+L51 -> 5841.6914 | ... Q124: =+Q51 -> 7045.6911
B126: Stock Based Compensation | E126: =+_xlfn.XLOOKUP($B126,Inputs!$B:$B,Inputs!O:O) -> 987 | F126: =+_xlfn.XLOOKUP($B126,Inputs!$B:$B,Inputs!P:P) -> 1133 | G126: =+_xlfn.XLOOKUP($B126,Inputs!$B:$B,Inputs!Q:Q) -> 1311 | H126: =IFERROR(H127*H40,"") -> 1235.9575 | I126: =IFERROR(I127*I40,"") -> 1339.2413 | J126: =IFERROR(J127*J40,"") -> 1420.0905 | K126: =IFERROR(K127*K40,"") -> 1488.6612 | L126: =IFERROR(L127*L40,"") -> 1596.0431 | M126: =IFERROR(M127*M40,"") -> 1693.6723 | N126: =IFERROR(N127*N40,"") -> 1809.5056 | O126: =IFERROR(O127*O40,"") -> 1923.0815 | ... Q126: =IFERROR(Q127*Q40,"") -> 2151.7461
B127: % of SG&A | E127: =+IFERROR(E126/E40,"") -> 0.053038852 | F127: =+IFERROR(F126/F40,"") -> 0.059622165 | G127: =+IFERROR(G126/G40,"") -> 0.066588785 | H127: =IFERROR(AVERAGE(E127:G127),"") -> 0.059749934 | I127: =IFERROR(AVERAGE(F127:H127),"") -> 0.061986961 | J127: =IFERROR(AVERAGE(G127:I127),"") -> 0.062775227 | K127: =IFERROR(AVERAGE(H127:J127),"") -> 0.061504041 | L127: =IFERROR(AVERAGE(I127:K127),"") -> 0.062088743 | M127: =IFERROR(AVERAGE(J127:L127),"") -> 0.06212267 | N127: =IFERROR(AVERAGE(K127:M127),"") -> 0.061905151 | O127: =IFERROR(AVERAGE(L127:N127),"") -> 0.062038855 | ... Q127: =IFERROR(AVERAGE(N127:P127),"") -> 0.061988744
B129: Changes in Net Working Capital | E129: =+_xlfn.XLOOKUP($B129,Inputs!$B:$B,Inputs!O:O) -> 202 | F129: =+_xlfn.XLOOKUP($B129,Inputs!$B:$B,Inputs!P:P) -> 2184 | G129: =+_xlfn.XLOOKUP($B129,Inputs!$B:$B,Inputs!Q:Q) -> 1313 | H129: =IFERROR(-((H91+H94+H97-H111-H114)-(G91+G94+G97-G111-G114)),"") -> -637.41027 | I129: =IFERROR(-((I91+I94+I97-I111-I114)-(H91+H94+H97-H111-H114)),"") -> 584.14038 | J129: =IFERROR(-((J91+J94+J97-J111-J114)-(I91+I94+I97-I111-I114)),"") -> -64.952017 | K129: =IFERROR(-((K91+K94+K97-K111-K114)-(J91+J94+J97-J111-J114)),"") -> 58.029804 | L129: =IFERROR(-((L91+L94+L97-L111-L114)-(K91+K94+K97-K111-K114)),"") -> 43.857882 | M129: =IFERROR(-((M91+M94+M97-M111-M114)-(L91+L94+L97-L111-L114)),"") -> -6.5378624 | N129: =IFERROR(-((N91+N94+N97-N111-N114)-(M91+M94+M97-M111-M114)),"") -> 112.6692 | O129: =IFERROR(-((O91+O94+O97-O111-O114)-(N91+N94+N97-N111-N114)),"") -> -114.27506 | ... Q129: =IFERROR(-((Q91+Q94+Q97-Q111-Q114)-(P91+P94+P97-P111-P114)),"") -> 75.689558
B131: Other Operating Adjustments | E131: =+_xlfn.XLOOKUP($B131,Inputs!$B:$B,Inputs!O:O) -> 2662 | F131: =+_xlfn.XLOOKUP($B131,Inputs!$B:$B,Inputs!P:P) -> -1295 | G131: =+_xlfn.XLOOKUP($B131,Inputs!$B:$B,Inputs!Q:Q) -> 138 | H131: =IFERROR(AVERAGE(E131:G131)*(1+H32),"") -> 527.08388 | I131: =IFERROR(AVERAGE(F131:H131)*(1+I32),"") -> -219.30769 | J131: =IFERROR(AVERAGE(G131:I131)*(1+J32),"") -> 155.58397 | K131: =IFERROR(AVERAGE(H131:J131)*(1+K32),"") -> 165.25779 | L131: =IFERROR(AVERAGE(I131:K131)*(1+L32),"") -> 35.944306 | M131: =IFERROR(AVERAGE(J131:L131)*(1+M32),"") -> 126.13457 | N131: =IFERROR(AVERAGE(K131:M131)*(1+N32),"") -> 116.98422 | O131: =IFERROR(AVERAGE(L131:N131)*(1+O32),"") -> 98.646555 | ... Q131: =IFERROR(AVERAGE(N131:P131)*(1+Q32),"") -> 118.88291
B133: Operating Cash Flow | E133: =+_xlfn.XLOOKUP($B133,Inputs!$B:$B,Inputs!O:O) -> 10435 | F133: =+_xlfn.XLOOKUP($B133,Inputs!$B:$B,Inputs!P:P) -> 13931 | G133: =+_xlfn.XLOOKUP($B133,Inputs!$B:$B,Inputs!Q:Q) -> 13445 | H133: =IFERROR(H82+H124+H126+H129+H131,"") -> 12639.138 | I133: =IFERROR(I82+I124+I126+I129+I131,"") -> 14958.294 | J133: =IFERROR(J82+J124+J126+J129+J131,"") -> 14831.939 | K133: =IFERROR(K82+K124+K126+K129+K131,"") -> 16565.857 | L133: =IFERROR(L82+L124+L126+L129+L131,"") -> 17501.756 | M133: =IFERROR(M82+M124+M126+M129+M131,"") -> 18465.019 | N133: =IFERROR(N82+N124+N126+N129+N131,"") -> 19984.237 | O133: =IFERROR(O82+O124+O126+O129+O131,"") -> 20969.089 | ... Q133: =IFERROR(Q82+Q124+Q126+Q129+Q131,"") -> 23779.387
B135: Net CapEx | E135: =+_xlfn.XLOOKUP($B135,Inputs!$B:$B,Inputs!O:O) -> -1235 | F135: =+_xlfn.XLOOKUP($B135,Inputs!$B:$B,Inputs!P:P) -> -924 | G135: =+_xlfn.XLOOKUP($B135,Inputs!$B:$B,Inputs!Q:Q) -> -491 | H135: =IFERROR(H137+H139,"") -> -938.72157 | I135: =IFERROR(I137+I139,"") -> -770.11747 | J135: =IFERROR(J137+J139,"") -> -683.21192 | K135: =IFERROR(K137+K139,"") -> -729.75804 | L135: =IFERROR(L137+L139,"") -> -665.94 | M135: =IFERROR(M137+M139,"") -> -650.4452 | N135: =IFERROR(N137+N139,"") -> -624.32854 | O135: =IFERROR(O137+O139,"") -> -603.68567 | ... Q135: =IFERROR(Q137+Q139,"") -> -624.95579
B137: Acquisition of Fixed & Intangibles | E137: =+_xlfn.XLOOKUP($B137,Inputs!$B:$B,Inputs!O:O) -> -1346 | F137: =+_xlfn.XLOOKUP($B137,Inputs!$B:$B,Inputs!P:P) -> -1245 | G137: =+_xlfn.XLOOKUP($B137,Inputs!$B:$B,Inputs!Q:Q) -> -1048 | H137: =Inputs!R241 -> -1263.8564 | I137: =Inputs!S241 -> -1189.7628 | J137: =Inputs!T241 -> -1151.324 | K137: =Inputs!U241 -> -1165.1172 | L137: =Inputs!V241 -> -1140.0087 | M137: =Inputs!W241 -> -1141.4878 | N137: =Inputs!X241 -> -1120.889 | O137: =Inputs!Y241 -> -1120.0289 | ... Q137: =Inputs!AA241 -> -1166.5162
B139: Disposal of Fixed & Intangibles | E139: =+_xlfn.XLOOKUP($B139,Inputs!$B:$B,Inputs!O:O) -> 111 | F139: =+_xlfn.XLOOKUP($B139,Inputs!$B:$B,Inputs!P:P) -> 321 | G139: =+_xlfn.XLOOKUP($B139,Inputs!$B:$B,Inputs!Q:Q) -> 557 | H139: =IFERROR(H140*G101,"") -> 325.1348 | I139: =IFERROR(I140*H101,"") -> 419.64538 | J139: =IFERROR(J140*I101,"") -> 468.11206 | K139: =IFERROR(K140*J101,"") -> 435.35915 | L139: =IFERROR(L140*K101,"") -> 474.0687 | M139: =IFERROR(M140*L101,"") -> 491.04261 | N139: =IFERROR(N140*M101,"") -> 496.56041 | O139: =IFERROR(O140*N101,"") -> 516.34326 | ... Q139: =IFERROR(Q140*P101,"") -> 541.56042
B140: Disposal Rate (% Gross PP&E) | E140: =IFERROR(E139/E101,"") -> 0.0059374164 | F140: =IFERROR(F139/F101,"") -> 0.017713277 | G140: =IFERROR(G139/G101,"") -> 0.031484936 | H140: =IFERROR(AVERAGE(E140:G140),"") -> 0.018378543 | I140: =IFERROR(AVERAGE(F140:H140),"") -> 0.022525585 | J140: =IFERROR(AVERAGE(G140:I140),"") -> 0.024129688 | K140: =IFERROR(AVERAGE(H140:J140),"") -> 0.021677939 | L140: =IFERROR(AVERAGE(I140:K140),"") -> 0.022777737 | M140: =IFERROR(AVERAGE(J140:L140),"") -> 0.022861788 | N140: =IFERROR(AVERAGE(K140:M140),"") -> 0.022439155 | O140: =IFERROR(AVERAGE(L140:N140),"") -> 0.022692893 | ... Q140: =IFERROR(AVERAGE(N140:P140),"") -> 0.022598887
B142: Net Cash from Investments & Acquisitions | E142: =+_xlfn.XLOOKUP($B142,Inputs!$B:$B,Inputs!O:O) -> -2341 | F142: =+_xlfn.XLOOKUP($B142,Inputs!$B:$B,Inputs!P:P) -> -5582 | G142: =+_xlfn.XLOOKUP($B142,Inputs!$B:$B,Inputs!Q:Q) -> -3809 | H142: =AVERAGE(E142/E31,F142/F31,G142/G31)*G31 -> -3966.1851 | I142: =AVERAGE(F142/F31,G142/G31,H142/H31)*H31 -> -4639.2162 | J142: =AVERAGE(G142/G31,H142/H31,I142/I31)*I31 -> -4320.5541 | K142: =AVERAGE(H142/H31,I142/I31,J142/J31)*J31 -> -4505.1724 | L142: =AVERAGE(I142/I31,J142/J31,K142/K31)*K31 -> -4775.0889 | M142: =AVERAGE(J142/J31,K142/K31,L142/L31)*L31 -> -4823.1059 | N142: =AVERAGE(K142/K31,L142/L31,M142/M31)*M31 -> -4987.3594 | O142: =AVERAGE(L142/L31,M142/M31,N142/N31)*N31 -> -5196.0734 | ... Q142: =AVERAGE(N142/N31,O142/O31,P142/P31)*P31 -> -5458.326
B144: Other Investing Inflows (Outflows) | E144: =+_xlfn.XLOOKUP($B144,Inputs!$B:$B,Inputs!O:O) -> -626 | F144: =+_xlfn.XLOOKUP($B144,Inputs!$B:$B,Inputs!P:P) -> -564 | G144: =+_xlfn.XLOOKUP($B144,Inputs!$B:$B,Inputs!Q:Q) -> -637 | H144: =IFERROR(AVERAGE(E144:G144)*(1+H32),"") -> -639.85532 | I144: =IFERROR(AVERAGE(F144:H144)*(1+I32),"") -> -640.90076 | J144: =IFERROR(AVERAGE(G144:I144)*(1+J32),"") -> -669.33164 | K144: =IFERROR(AVERAGE(H144:J144)*(1+K32),"") -> -695.5004 | L144: =IFERROR(AVERAGE(I144:K144)*(1+L32),"") -> -710.05398 | M144: =IFERROR(AVERAGE(J144:L144)*(1+M32),"") -> -733.53443 | N144: =IFERROR(AVERAGE(K144:M144)*(1+N32),"") -> -764.47175 | O144: =IFERROR(AVERAGE(L144:N144)*(1+O32),"") -> -780.53146 | ... Q144: =IFERROR(AVERAGE(N144:P144)*(1+Q32),"") -> -830.62092
B146: Investing Cash Flow | E146: =+_xlfn.XLOOKUP($B146,Inputs!$B:$B,Inputs!O:O) -> -4202 | F146: =+_xlfn.XLOOKUP($B146,Inputs!$B:$B,Inputs!P:P) -> -7070 | G146: =+_xlfn.XLOOKUP($B146,Inputs!$B:$B,Inputs!Q:Q) -> -4937 | H146: =IFERROR(+H135+H142+H144,"") -> -5544.762 | I146: =IFERROR(+I135+I142+I144,"") -> -6050.2345 | J146: =IFERROR(+J135+J142+J144,"") -> -5673.0976 | K146: =IFERROR(+K135+K142+K144,"") -> -5930.4308 | L146: =IFERROR(+L135+L142+L144,"") -> -6151.0829 | M146: =IFERROR(+M135+M142+M144,"") -> -6207.0856 | N146: =IFERROR(+N135+N142+N144,"") -> -6376.1597 | O146: =IFERROR(+O135+O142+O144,"") -> -6580.2905 | ... Q146: =IFERROR(+Q135+Q142+Q144,"") -> -6913.9027
B148: Dividends | E148: =+_xlfn.XLOOKUP($B148,Inputs!$B:$B,Inputs!O:O) -> -5948 | F148: =+_xlfn.XLOOKUP($B148,Inputs!$B:$B,Inputs!P:P) -> -6040 | G148: =+_xlfn.XLOOKUP($B148,Inputs!$B:$B,Inputs!Q:Q) -> -6147 | H148: =-Inputs!H220*DCF!H149 -> -6525.1905 | I148: =-Inputs!I220*DCF!I149 -> -6874.3252 | J148: =-Inputs!J220*DCF!J149 -> -7009.55 | K148: =-Inputs!K220*DCF!K149 -> -5571.1991 | L148: =-Inputs!L220*DCF!L149 -> -6359.4192 | M148: =-Inputs!M220*DCF!M149 -> -7016.3332 | N148: =-Inputs!N220*DCF!N149 -> -7034.7611 | O148: =-Inputs!O220*DCF!O149 -> -7288.6953 | ... Q148: =-Inputs!Q220*DCF!Q149 -> -7346.4576
...

Sheet Sheet1
A1: DCF - Revenue | F1: 2023'
A2: Management | B2: revenue growth of 5% | F2: 18693 | G2: 26308 | H2: =F2/G2 -> 0.71054432 | I2: TP(average) | J2: =AVERAGE(D6,G6,M6,P6) -> 0.059593602
B3: $13.5 billion free cash flow | C3: 2024 | F3: 2023 | I3: 2022 | K3: segment change | L3: 2022' | O3: 2021' | R3: 2020' | T3: Method 1 | V3: 2025 | W3: 2026 | X3: 2027 | Y3: 2028 | Z3: 2029 | AA3: 2030 | AB3: 2031 | AC3: 2032 | AD3: 2033 | AE3: 2034
A4: Segments | C4: revenue | D4: growth | E4: weight | F4: revenue | G4: growth | H4: weight | I4: revenue | J4: weight | L4: revenue | M4: growth | N4: weight | O4: revenue | P4: growth | Q4: weight | R4: revenue | S4: weight | T4: hybrid cloud | U4: growth | V4: 0.095 | W4: 0.1 | X4: 0.106 | Y4: 0.111 | Z4: 0.116 | AA4: 0.12 | AB4: 0.11 | AC4: 0.1 | AD4: 0.09 | AE4: 0.08
A5: Software | B5: Hybrid Platform & Solutions | C5: 18808 | D5: =(C5-F5)/F5 -> 0.081168085 | E5: =C5/$C$7 -> 0.6944065 | F5: 17396 | G5: =(F5-I5)/I5 -> 0.056993559 | H5: =F5/$F$7 -> 0.69553397 | I5: 16458 | J5: =I5/$I$7 -> 0.69651699 | L5: 17866 | M5: =(L5-O5)/O5 -> 0.048720357 | N5: =L5/$L$7 -> 0.7135839 | O5: 17036 | P5: =(O5-R5)/R5 -> 0.097821884 | Q5: =O5/$O$7 -> 0.72722616 | R5: 15518 | S5: =R5/$R$7 -> 0.70141023 | U5: revenue | V5: =V4*C5+C5 -> 20594.76 | W5: =W4*V5+V5 -> 22654.236 | X5: =X4*W5+W5 -> 25055.585 | Y5: =Y4*X5+X5 -> 27836.755 | Z5: =Z4*Y5+Y5 -> 31065.819 | AA5: =AA4*Z5+Z5 -> 34793.717 | AB5: =AB4*AA5+AA5 -> 38621.026 | AC5: =AC4*AB5+AB5 -> 42483.128 | AD5: =AD4*AC5+AC5 -> 46306.61 | AE5: =AE4*AD5+AD5 -> 50011.138
B6: Transaction Processing | C6: 8277 | D6: =(C6-F6)/F6 -> 0.086933684 | E6: =C6/$C$7 -> 0.3055935 | F6: 7615 | G6: =(F6-I6)/I6 -> 0.061916051 | H6: =F6/$F$7 -> 0.30446603 | I6: 7171 | J6: =I6/$I$7 -> 0.30348301 | K6: = | L6: 7171 | M6: =(L6-O6)/O6 -> 0.12222222 | N6: =L6/$L$7 -> 0.2864161 | O6: 6390 | P6: =(O6-R6)/R6 -> -0.032697548 | Q6: =O6/$O$7 -> 0.27277384 | R6: 6606 | S6: =R6/$R$7 -> 0.29858977 | T6: Transaction | U6: growth | V6: =J2 -> 0.059593602
B7: Total | C7: =C5+C6 -> 27085 | D7: =(C7-F7)/F7 -> 0.082923514 | F7: =F5+F6 -> 25011 | G7: =(F7-I7)/I7 -> 0.058487452 | I7: =I5+I6 -> 23629 | L7: =L5+L6 -> 25037 | M7: =(L7-O7)/O7 -> 0.068769743 | O7: =O5+O6 -> 23426 | P7: =(O7-R7)/R7 -> 0.058850118 | R7: =R5+R6 -> 22124 | U7: revenue | V7: =C6*V6+C6 -> 8770.2562 | W7: =V7*$V$6+V7 -> 9292.9074 | X7: =W7*$V$6+W7 -> 9846.7052 | Y7: =X7*$V$6+X7 -> 10433.506 | Z7: =Y7*$V$6+Y7 -> 11055.276 | AA7: =Z7*$V$6+Z7 -> 11714.1 | AB7: =AA7*$V$6+AA7 -> 12412.185 | AC7: =AB7*$V$6+AB7 -> 13151.872 | AD7: =AC7*$V$6+AC7 -> 13935.639 | AE7: =AD7*$V$6+AD7 -> 14766.114
T8: Software | U8: revenue | V8: =V5+V7 -> 29365.016 | W8: =W5+W7 -> 31947.143 | X8: =X5+X7 -> 34902.29 | Y8: =Y5+Y7 -> 38270.261 | Z8: =Z5+Z7 -> 42121.095 | AA8: =AA5+AA7 -> 46507.817 | AB8: =AB5+AB7 -> 51033.211 | AC8: =AC5+AC7 -> 55635 | ... AE8: =AE5+AE7 -> 64777.253
U9: growth | V9: =(V8-C7)/C7 -> 0.084180035 | W9: =(W8-V8)/V8 -> 0.087932087 | X9: =(X8-W8)/W8 -> 0.092501129 | Y9: =(Y8-X8)/X8 -> 0.096497122 | Z9: =(Z8-Y8)/Y8 -> 0.10062209 | AA9: =(AA8-Z8)/Z8 -> 0.10414549 | AB9: =(AB8-AA8)/AA8 -> 0.09730395 | AC9: =(AC8-AB8)/AB8 -> 0.090172445 | AD9: =(AD8-AC8)/AC8 -> 0.08281206 | AE9: =(AE8-AD8)/AD8 -> 0.075279456
T10: Method 2
V11: =E5-0.003 -> 0.6914065 | W11: =V11-0.003 -> 0.6884065 | X11: =W11-0.003 -> 0.6854065 | Y11: =X11 -> 0.6854065 | Z11: =Y11 -> 0.6854065 | AA11: =Z11 -> 0.6854065 | AB11: =AA11 -> 0.6854065 | AC11: =AB11 -> 0.6854065 | AD11: =AC11 -> 0.6854065 | AE11: =AD11 -> 0.6854065
U12: growth rate | V12: =V11*V4+(1-V11)*$J$2 -> 0.084073816 | W12: =W11*W4+(1-W11)*$J$2 -> 0.087409629 | X12: =X11*X4+(1-X11)*$J$2 -> 0.091400849 | Y12: =Y11*Y4+(1-Y11)*$J$2 -> 0.094827881 | Z12: =Z11*Z4+(1-Z11)*$J$2 -> 0.098254914 | AA12: =AA11*AA4+(1-AA11)*$J$2 -> 0.10099654 | AB12: =AB11*AB4+(1-AB11)*$J$2 -> 0.094142475 | AC12: =AC11*AC4+(1-AC11)*$J$2 -> 0.08728841 | ... AE12: =AE11*AE4+(1-AE11)*$J$2 -> 0.07358028
N27: Market Research Future
N28: IBM's growth in hybrid clouds is much slower comparing to the market growth
N29: And market share diluted
N30: (from IBM Investor Day 2025) the market growth of hybrid cloud will be 15%
N31: Assumption: for IBM hybrid clould grow at 10% in the future 3 years
N32: (from Allied Market Research) CAGR = 17.4% from 2023 to 2033.
N33: Assumption: IBM hybrid cloud growth increases to 12% after 2027
N35: https://www.crnasia.com/news/2024/hybrid-cloud/gartner-90-of-organizations-will-adopt-hybrid-cloud-through?utm_source=chatgpt.com
N36: According to Gartner, 90% of organizaitons will adopt hybrid cloud by 2027
N37: GenAI brings challenges and demands --> room for more growth
N38: Assumption: Grow fast until 2030-2033, then mature
N40: Weight
N41: Assumption: -0.3% for 3 years, then maintain the ratio
B54: Consulting | C54: 2020' | D54: 2021' | E54: 2022' | F54: 2022 | G54: 2023 | H54: 2024 | I54: 2025 | J54: 2026 | K54: 2027 | L54: 2028 | M54: 2029 | N54: 2030 | O54: 2031 | P54: 2032 | Q54: 2033 | R54: 2034
B55: growth | D55: =(D56-C56)/C56 -> 0.097619487 | E55: =(E56-D56)/D56 -> 0.070780094 | G55: =(G56-F56)/F56 -> 0.041180576 | H55: =(H56-G56)/G56 -> -0.0091936411 | I55: 0.02 | J55: 0.03 | K55: 0.04 | L55: 0.05 | M55: 0.05 | N55: 0.05 | O55: 0.05 | P55: 0.05 | Q55: 0.05 | R55: 0.05
B56: revenue | C56: 16257 | D56: 17844 | E56: 19107 | F56: 20058 | G56: 20884 | H56: 20692 | I56: =H56*(1+I55) -> 21105.84 | J56: =I56*(1+J55) -> 21739.015 | K56: =J56*(1+K55) -> 22608.576 | L56: =K56*(1+L55) -> 23739.005 | M56: =L56*(1+M55) -> 24925.955 | N56: =M56*(1+N55) -> 26172.253 | O56: =N56*(1+O55) -> 27480.865 | P56: =O56*(1+P55) -> 28854.908 | ... R56: =Q56*(1+R55) -> 31812.537
B57: Infrastructure
B58: growth | D58: =(D59-C59)/C59 -> -0.023739077 | E58: =(E59-D59)/D59 -> 0.077530307 | G58: =(G59-E59)/E59 -> -0.045460492 | H58: =(H59-G59)/G59 -> -0.039265401 | I58: 0.0448 | J58: =(J59-I59)/I59 -> -0.010110256 | K58: =(K59-J59)/J59 -> -0.034482759 | L58: 0.045 | M58: =(M59-L59)/L59 -> -0.008885851 | N58: =(N59-M59)/M59 -> -0.034482759 | O58: 0.045 | P58: =(P59-O59)/O59 -> -0.008885851 | Q58: =(Q59-P59)/P59 -> -0.034482759 | R58: 0.045
B59: revenue | C59: 14533 | D59: 14188 | E59: 15288 | G59: 14593 | H59: 14020 | I59: =H59*(1+I58) -> 14648.096 | J59: 14500 | K59: 14000 | L59: =K59*(1+L58) -> 14630 | M59: 14500 | N59: 14000 | O59: =N59*(1+O58) -> 14630 | P59: 14500 | Q59: 14000 | R59: =Q59*(1+R58) -> 14630
B60: Software
B61: growth | D61: =(D62-C62)/C62 -> 0.058850118 | E61: =(E62-D62)/D62 -> 0.068769743 | G61: =G7 -> 0.058487452 | H61: =D7 -> 0.082923514 | I61: =V12 -> 0.084073816 | J61: =W12 -> 0.087409629 | K61: =X12 -> 0.091400849 | L61: =Y12 -> 0.094827881 | M61: =Z12 -> 0.098254914 | N61: =AA12 -> 0.10099654 | O61: =AB12 -> 0.094142475 | P61: =AC12 -> 0.08728841 | ... R61: =AE12 -> 0.07358028
B62: Revenue | C62: =R7 -> 22124 | D62: =O7 -> 23426 | E62: =L7 -> 25037 | F62: =I7 -> 23629 | G62: =F7 -> 25011 | H62: =C7 -> 27085 | I62: =H62*(1+I61) -> 29362.139 | J62: =I62*(1+J61) -> 31928.673 | K62: =J62*(1+K61) -> 34846.981 | L62: =K62*(1+L61) -> 38151.446 | M62: =L62*(1+M61) -> 41900.013 | N62: =M62*(1+N61) -> 46131.77 | O62: =N62*(1+O61) -> 50474.729 | P62: =O62*(1+P61) -> 54880.587 | ... R62: =Q62*(1+R61) -> 63657.805
B63: Financing | C63: 975 | D63: 774 | E63: 645 | G63: 741 | H63: 713 | I63: =H63*(1+I64) -> 666.33948 | J63: =I63*(1+J64) -> 646.17293 | K63: =J63*(1+K64) -> 648.65152 | L63: =K63*(1+L64) -> 627.62578 | M63: =L63*(1+M64) -> 608.12451 | N63: =M63*(1+N64) -> 594.45465 | O63: =N63*(1+O64) -> 582.24916 | P63: =O63*(1+P64) -> 566.74722 | ... R63: =Q63*(1+R64) -> 539.38303
B64: growth | D64: =(D63-C63)/C63 -> -0.20615385 | E64: =(E63-D63)/D63 -> -0.16666667 | G64: =(G63-E63)/E63 -> 0.14883721 | H64: =(H63-G63)/G63 -> -0.037786775 | I64: =AVERAGE(D64:H64) -> -0.06544252 | J64: =AVERAGE(E64:I64) -> -0.030264688 | K64: =AVERAGE(G64:J64) -> 0.0038358068 | L64: =AVERAGE(H64:K64) -> -0.032414544 | M64: =AVERAGE(I64:L64) -> -0.031071486 | N64: =AVERAGE(J64:M64) -> -0.022478728 | O64: =AVERAGE(K64:N64) -> -0.020532238 | P64: =AVERAGE(L64:O64) -> -0.026624249 | Q64: =AVERAGE(M64:P64) -> -0.025176675 | R64: =AVERAGE(N64:Q64) -> -0.023702972
B65: Other | C65: 1291 | D65: 1119 | E65: 453 | F65: 909 | G65: 632 | H65: 243 | I65: 150 | J65: 50 | K65: 0 | L65: 0 | M65: 0 | N65: 0 | O65: 0 | P65: 0 | Q65: 0 | R65: 0
B66: Total revenue | C66: =C56+C59+C62+C63+C65 -> 55180 | D66: =D56+D59+D62+D63+D65 -> 57351 | E66: =E56+E59+E62+E63+E65 -> 60530 | F66: =F56+E59+F62+E63+F65 -> 60529 | G66: =G56+G59+G62+G63+G65 -> 61861 | H66: =H56+H59+H62+H63+H65 -> 62753 | I66: =I56+I59+I62+I63+I65 -> 65932.415 | J66: =J56+J59+J62+J63+J65 -> 68863.861 | K66: =K56+K59+K62+K63+K65 -> 72104.208 | L66: =L56+L59+L62+L63+L65 -> 77148.077 | M66: =M56+M59+M62+M63+M65 -> 81934.093 | N66: =N56+N59+N62+N63+N65 -> 86898.477 | ... R66: =R56+R59+R62+R63+R65 -> 110639.72
B67: growth | D67: =(D66-C66)/C66 -> 0.039343965 | E67: =(E66-D66)/D66 -> 0.055430594 | G67: =(G66-F66)/F66 -> 0.022005981 | H67: =(H66-G66)/G66 -> 0.014419424 | I67: =(I66-H66)/H66 -> 0.050665542 | J67: =(J66-I66)/I66 -> 0.044461383 | K67: =(K66-J66)/J66 -> 0.047054391 | L67: =(L66-K66)/K66 -> 0.069952483 | M67: =(M66-L66)/L66 -> 0.062036751 | N67: =(N66-M66)/M66 -> 0.06058997 | ... R67: =(R66-Q66)/Q66 -> 0.062362286

Sheet Inputs
B2: Inputs
B3: in millions of USD | G3: =G7/G6 -> 0.49988684 | H3: =H7/H6 -> 0.5022816 | I3: =I7/I6 -> 0.52083985 | J3: =J7/J6 -> 0.53318844 | K3: =K7/K6 -> 0.53592743 | L3: =L7/L6 -> 0.52703281 | M3: =M7/M6 -> 0.44063865 | N3: =N7/N6 -> 0.45100262 | ... Q3: =Q7/Q6 -> 0.43346135
A4: x | B4: Income Statement | G4: 2014 | H4: =+G4+1 -> 2015 | I4: =+H4+1 -> 2016 | J4: =+I4+1 -> 2017 | K4: =+J4+1 -> 2018 | L4: =+K4+1 -> 2019 | M4: =+L4+1 -> 2020 | N4: =+M4+1 -> 2021 | O4: =+N4+1 -> 2022 | ... Q4: =+P4+1 -> 2024 | R4: ="CAGR "&$G$4&" - "&$Q$4 -> CAGR 2014 - 2024
B6: Revenue (Sales) | G6: 92793 | H6: 81741 | I6: 79919 | J6: 79139 | K6: 79591 | L6: 77147 | M6: 55179 | N6: 57350 | O6: 60530 | P6: 61860 | Q6: 62753 | R6: =IFERROR((Q6/G6)^(1/COUNT($G$4:$Q$4))-1,"") -> -0.034935594
B7: COGS (Cost of Goods Sold) | G7: 46386 | H7: 41057 | I7: 41625 | J7: 42196 | K7: 42655 | L7: 40659 | M7: 24314 | N7: 25865 | O7: 27842 | P7: 27560 | Q7: 27201 | R7: =IFERROR((Q7/G7)^(1/COUNT($G$4:$Q$4))-1,"") -> -0.047363788
B8: Gross Profit | G8: =G6-G7 -> 46407 | H8: =H6-H7 -> 40684 | I8: =I6-I7 -> 38294 | J8: =J6-J7 -> 36943 | K8: =K6-K7 -> 36936 | L8: =L6-L7 -> 36488 | M8: =M6-M7 -> 30865 | N8: =N6-N7 -> 31485 | ... Q8: =Q6-Q7 -> 35552 | R8: =IFERROR((Q8/G8)^(1/COUNT($G$4:$Q$4))-1,"") -> -0.023932057
B9: SG&A (Selling, General & Administrative) | G9: 23180 | H9: 20430 | I9: 21069 | J9: 19680 | K9: 19366 | L9: 20604 | M9: 20561 | N9: 18745 | O9: 18609 | P9: 19003 | Q9: 19688 | R9: =IFERROR((Q9/G9)^(1/COUNT($G$4:$Q$4))-1,"") -> -0.01473406
B10: R&D (Research & Development) | G10: 5437 | H10: 5247 | I10: 5751 | J10: 5590 | K10: 5379 | L10: 5989 | M10: 6262 | N10: 6488 | O10: 6567 | P10: 6775 | Q10: 7479 | R10: =IFERROR((Q10/G10)^(1/COUNT($G$4:$Q$4))-1,"") -> 0.029412584
B11: Other Operating (Income) Expenses | G11: =G152 -> -742 | H11: =H152 -> -682 | I11: =I152 -> -1631 | J11: =J152 -> -1466 | K11: =K152 -> -1026 | L11: =L152 -> -639 | M11: =M152 -> -620 | N11: =N152 -> -612 | ... Q11: =Q152 -> -996 | R11: =IFERROR((Q11/G11)^(1/COUNT($G$4:$Q$4))-1,"") -> 0.027124814
B12: EBITDA | G12: =G16+G13 -> 23024 | H12: =H16+H13 -> 19544 | I12: =I16+I13 -> 17486 | J12: =J16+J13 -> 17680 | K12: =K16+K13 -> 17697 | L12: =L16+L13 -> 16593 | M12: =M16+M13 -> 11357 | N12: =N16+N13 -> 13281 | ... Q12: =Q16+Q13 -> 14048 | R12: =IFERROR((Q12/G12)^(1/COUNT($G$4:$Q$4))-1,"") -> -0.043920569
B13: D&A (Depreciation & Amortization) | G13: =+SUM(G14:G15) -> 4492 | H13: =+SUM(H14:H15) -> 3855 | I13: =+SUM(I14:I15) -> 4381 | J13: =+SUM(J14:J15) -> 4541 | K13: =+SUM(K14:K15) -> 4480 | L13: =+SUM(L14:L15) -> 6059 | M13: =+SUM(M14:M15) -> 6695 | N13: =+SUM(N14:N15) -> 6417 | ... Q13: =+SUM(Q14:Q15) -> 4667 | R13: =IFERROR((Q13/G13)^(1/COUNT($G$4:$Q$4))-1,"") -> 0.0034804455
B14: Depreciation Expense | G14: 3145 | H14: 2662 | I14: 2837 | J14: 3021 | K14: 3127 | L14: 4209 | M14: 4227 | N14: 3888 | O14: 2407 | P14: 2109 | Q14: 2168 | R14: =IFERROR((Q14/G14)^(1/COUNT($G$4:$Q$4))-1,"") -> -0.033253513
B15: Amortization Expense | G15: 1347 | H15: 1193 | I15: 1544 | J15: 1520 | K15: 1353 | L15: 1850 | M15: 2468 | N15: 2529 | O15: 2395 | P15: 2287 | Q15: 2499 | R15: =IFERROR((Q15/G15)^(1/COUNT($G$4:$Q$4))-1,"") -> 0.057791026
B16: Operating Income (EBIT) | G16: =+G8-G9-G10-G11 -> 18532 | H16: =+H8-H9-H10-H11 -> 15689 | I16: =+I8-I9-I10-I11 -> 13105 | J16: =+J8-J9-J10-J11 -> 13139 | K16: =+K8-K9-K10-K11 -> 13217 | L16: =+L8-L9-L10-L11 -> 10534 | M16: =+M8-M9-M10-M11 -> 4662 | N16: =+N8-N9-N10-N11 -> 6864 | ... Q16: =+Q8-Q9-Q10-Q11 -> 9381 | R16: =IFERROR((Q16/G16)^(1/COUNT($G$4:$Q$4))-1,"") -> -0.060015652
B17: Net Interest Expense (Income) | G17: =+G18-G19 -> 484 | H17: =+H18-H19 -> 468 | I17: =+I18-I19 -> 630 | J17: =+J18-J19 -> 615 | K17: =+K18-K19 -> 723 | L17: =+L18-L19 -> 1344 | M17: =+M18-M19 -> 1288 | N17: =+N18-N19 -> 1155 | ... Q17: =+Q18-Q19 -> 1712 | R17: =IFERROR((Q17/G17)^(1/COUNT($G$4:$Q$4))-1,"") -> 0.1217034
B18: Interest Expense | G18: 484 | H18: 468 | I18: 630 | J18: 615 | K18: 723 | L18: 1344 | M18: 1288 | N18: 1155 | O18: 1216 | P18: 1607 | Q18: 1712 | R18: =IFERROR((Q18/G18)^(1/COUNT($G$4:$Q$4))-1,"") -> 0.1217034
B19: Interest Income | G19: 0 | H19: 0 | I19: 0 | J19: 0 | K19: 0 | L19: 0 | M19: 0 | N19: 0 | O19: 0 | P19: 0 | Q19: 0 | R19: =IFERROR((Q19/G19)^(1/COUNT($G$4:$Q$4))-1,"")
B20: FX (Gain) Loss | G20: =G155 -> -599 | H20: =H155 -> 414 | I20: =I155 -> -116 | J20: =J155 -> 405 | K20: =K155 -> -427 | L20: =L155 -> -279 | M20: =M155 -> 114 | N20: =N155 -> -204 | ... Q20: =Q155 -> -458 | R20: =IFERROR((Q20/G20)^(1/COUNT($G$4:$Q$4))-1,"") -> -0.024104053
B21: Other Non-Operating (Income) Expenses | G21: =G156-G155 -> -1339 | H21: =H156-H155 -> -1138 | I21: =I156-I155 -> 709 | J21: =J156-J155 -> 720 | K21: =K156-K155 -> 1579 | L21: =L156-L155 -> -689 | M21: =M156-M155 -> 747 | N21: =N156-N155 -> 1077 | ... Q21: =Q156-Q155 -> 2329 | R21: =IFERROR((Q21/G21)^(1/COUNT($G$4:$Q$4))-1,"") -> -2.0516072
B22: Pre-Tax Income (EBT) | G22: =+G16-G17-G20-G21 -> 19986 | H22: =+H16-H17-H20-H21 -> 15945 | I22: =+I16-I17-I20-I21 -> 11882 | J22: =+J16-J17-J20-J21 -> 11399 | K22: =+K16-K17-K20-K21 -> 11342 | L22: =+L16-L17-L20-L21 -> 10158 | M22: =+M16-M17-M20-M21 -> 2513 | N22: =+N16-N17-N20-N21 -> 4836 | ... Q22: =+Q16-Q17-Q20-Q21 -> 5798 | R22: =IFERROR((Q22/G22)^(1/COUNT($G$4:$Q$4))-1,"") -> -0.1064042
B23: Tax Expense (Benefits) | G23: 4234 | H23: 2581 | I23: 449 | J23: 5642 | K23: 2619 | L23: 60 | M23: -1360 | N23: 124 | O23: -626 | P23: 1176 | Q23: -218 | R23: =IFERROR((Q23/G23)^(1/COUNT($G$4:$Q$4))-1,"") -> -1.7636289
B24: Net Income | G24: =+G22-G23 -> 15752 | H24: =+H22-H23 -> 13364 | I24: =+I22-I23 -> 11433 | J24: =+J22-J23 -> 5757 | K24: =+K22-K23 -> 8723 | L24: =+L22-L23 -> 10098 | M24: =+M22-M23 -> 3873 | N24: =+N22-N23 -> 4712 | ... Q24: =+Q22-Q23 -> 6016 | R24: =IFERROR((Q24/G24)^(1/COUNT($G$4:$Q$4))-1,"") -> -0.083784856
B25: EPS basic | G25: 11.97 | H25: 13.48 | I25: 12.43 | J25: 6.17 | K25: 9.57 | L25: 10.63 | M25: 6.28 | N25: 6.41 | O25: 1.82 | P25: 8.23 | Q25: 6.53 | R25: =IFERROR((Q25/G25)^(1/COUNT($G$4:$Q$4))-1,"") -> -0.053600598
B26: EPS diluted | G26: 11.9 | H26: 13.42 | I26: 12.38 | J26: 6.14 | K26: 9.52 | L26: 10.56 | M26: 6.23 | N26: 6.35 | O26: 1.8 | P26: 8.14 | Q26: 6.43 | R26: =IFERROR((Q26/G26)^(1/COUNT($G$4:$Q$4))-1,"") -> -0.054423374
B27: Basic Weighted Average Shares | G27: 1004272584 | H27: 978744523 | I27: 955422530 | J27: 932828295 | K27: 912048072 | L27: 887235105 | M27: 890348679 | N27: 895990771 | O27: 902664190 | P27: 911210319 | Q27: 921767834
B28: Diluted Weighted Average Shares | G28: 1010000480 | H28: 982700267 | I28: 958714097 | J28: 937385625 | K28: 916315714 | L28: 892813376 | M28: 896563971 | N28: 904641001 | O28: 912269062 | P28: 922073828 | Q28: 937161224 | R28: =IFERROR((Q28/G28)^(1/COUNT($G$4:$Q$4))-1,"") -> -0.006781515
A30: x | B30: Balance Sheet | G30: 2014 | H30: =+G30+1 -> 2015 | I30: =+H30+1 -> 2016 | J30: =+I30+1 -> 2017 | K30: =+J30+1 -> 2018 | L30: =+K30+1 -> 2019 | M30: =+L30+1 -> 2020 | N30: =+M30+1 -> 2021 | O30: =+N30+1 -> 2022 | ... Q30: =+P30+1 -> 2024 | R30: ="CAGR "&$G$4&" - "&$Q$4 -> CAGR 2014 - 2024
B32: Cash & Cash Equivalents & ST Investments | G32: =+SUM(G33:G34) -> 8476 | H32: =+SUM(H33:H34) -> 8194 | I32: =+SUM(I33:I34) -> 8527 | J32: =+SUM(J33:J34) -> 12580 | K32: =+SUM(K33:K34) -> 11997 | L32: =+SUM(L33:L34) -> 8313 | M32: =+SUM(M33:M34) -> 13675 | N32: =+SUM(N33:N34) -> 6957 | ... Q32: =+SUM(Q33:Q34) -> 14591 | R32: =IFERROR((Q32/G32)^(1/COUNT($G$4:$Q$4))-1,"") -> 0.050618198
B33: Cash & Cash Equivalents | G33: 8476 | H33: 7686 | I33: 7826 | J33: 11972 | K33: 11379 | L33: 8172 | M33: 13212 | N33: 6650 | O33: 7886 | P33: 13068 | Q33: 13947 | R33: =IFERROR((Q33/G33)^(1/COUNT($G$4:$Q$4))-1,"") -> 0.046315632
B34: Short-Term Investments | G34: 0 | H34: 508 | I34: 701 | J34: 608 | K34: 618 | L34: 141 | M34: 463 | N34: 307 | O34: 103 | P34: 373 | Q34: 644 | R34: =IFERROR((Q34/G34)^(1/COUNT($G$4:$Q$4))-1,"")
B35: Accounts Receivable | G35: =G134 -> 11996 | H35: =H134 -> 9534 | I35: =I134 -> 10239 | J35: =J134 -> 9909 | K35: =K134 -> 8175 | L35: =L134 -> 9603 | M35: =M134 -> 7846 | N35: =N134 -> 7756 | ... Q35: =Q134 -> 7751 | R35: =IFERROR((Q35/G35)^(1/COUNT($G$4:$Q$4))-1,"") -> -0.038926771
B36: Inventory | G36: 2103 | H36: 1551 | I36: 1553 | J36: 1583 | K36: 1682 | L36: 1619 | M36: 1839 | N36: 1649 | O36: 1552 | P36: 1161 | Q36: 1289 | R36: =IFERROR((Q36/G36)^(1/COUNT($G$4:$Q$4))-1,"") -> -0.043524241
B37: Prepaid expenses and Other Current Assets | G37: =+G38-G32-G35-G36 -> 24802 | H37: =+H38-H32-H35-H36 -> 23225 | I37: =+I38-I32-I35-I36 -> 23569 | J37: =+J38-J32-J35-J36 -> 25663 | K37: =+K38-K32-K35-K36 -> 27292 | L37: =+L38-L32-L35-L36 -> 18885 | M37: =+M38-M32-M35-M36 -> 15805 | N37: =+N38-N32-N35-N36 -> 13177 | ... Q37: =+Q38-Q32-Q35-Q36 -> 10851 | R37: =IFERROR((Q37/G37)^(1/COUNT($G$4:$Q$4))-1,"") -> -0.072397103
B38: Current Assets | G38: 47377 | H38: 42504 | I38: 43888 | J38: 49735 | K38: 49146 | L38: 38420 | M38: 39165 | N38: 29539 | O38: 29118 | P38: 32908 | Q38: 34482 | R38: =IFERROR((Q38/G38)^(1/COUNT($G$4:$Q$4))-1,"") -> -0.028468675
B39: Net PP&E (Property, Plant and Equipment) | G39: =+G40-G41 -> 10771 | H39: =+H40-H41 -> 10727 | I39: =+I40-I41 -> 10830 | J39: =+J40-J41 -> 11116 | K39: =+K40-K41 -> 10792 | L39: =+L40-L41 -> 10010 | M39: =+M40-M41 -> 10040 | N39: =+N40-N41 -> 5695 | ... Q39: =+Q40-Q41 -> 5732 | R39: =IFERROR((Q39/G39)^(1/COUNT($G$4:$Q$4))-1,"") -> -0.055731573
B40: Gross PP&E (Property, Plant and Equipment) | G40: 39034 | H40: 29342 | I40: 30133 | J40: 32331 | K40: 32460 | L40: 32028 | M40: 33176 | N40: 20085 | O40: 18695 | P40: 18122 | Q40: 17691 | R40: =IFERROR((Q40/G40)^(1/COUNT($G$4:$Q$4))-1,"") -> -0.069416403
B41: Accumulated Depreciation | G41: 28263 | H41: 18615 | I41: 19303 | J41: 21215 | K41: 21668 | L41: 22018 | M41: 23136 | N41: 14390 | O41: 13361 | P41: 12621 | Q41: 11959 | R41: =IFERROR((Q41/G41)^(1/COUNT($G$4:$Q$4))-1,"") -> -0.075209568
B42: Right-of-Use Assets | G42: 0 | H42: 0 | I42: 0 | J42: 0 | K42: 0 | L42: 4996 | M42: 4686 | N42: 3222 | O42: 2878 | P42: 3220 | Q42: 3197 | R42: =IFERROR((Q42/G42)^(1/COUNT($G$4:$Q$4))-1,"")
B43: Intangibles | G43: =G44+G45 -> 33660 | H43: =H44+H45 -> 35508 | I43: =I44+I45 -> 40887 | J43: =J44+J45 -> 40530 | K43: =K44+K45 -> 39352 | L43: =L44+L45 -> 73457 | M43: =M44+M45 -> 73413 | N43: =N44+N45 -> 68154 | ... Q43: =Q44+Q45 -> 71366 | R43: =IFERROR((Q43/G43)^(1/COUNT($G$4:$Q$4))-1,"") -> 0.070707041
B44: Goodwill | G44: 30556 | H44: 32021 | I44: 36199 | J44: 36788 | K44: 36265 | L44: 58222 | M44: 59617 | N44: 55643 | O44: 55949 | P44: 60178 | Q44: 60706 | R44: =IFERROR((Q44/G44)^(1/COUNT($G$4:$Q$4))-1,"") -> 0.064395898
B45: Intangibles excl. Goodwill | G45: 3104 | H45: 3487 | I45: 4688 | J45: 3742 | K45: 3087 | L45: 15235 | M45: 13796 | N45: 12511 | O45: 11184 | P45: 11036 | Q45: 10660
B46: Other Non-Current Assets | G46: =+G47-G39-G42-G43 -> 25464 | H46: =+H47-H39-H42-H43 -> 21756 | I46: =+I47-I39-I42-I43 -> 21864 | J46: =+J47-J39-J42-J43 -> 23974 | K46: =+K47-K39-K42-K43 -> 24092 | L46: =+L47-L39-L42-L43 -> 25305 | M46: =+M47-M39-M42-M43 -> 28668 | N46: =+N47-N39-N42-N43 -> 25392 | ... Q46: =+Q47-Q39-Q42-Q43 -> 22398 | R46: =IFERROR((Q46/G46)^(1/COUNT($G$4:$Q$4))-1,"") -> -0.011595343
B47: Non-Current Assets | G47: =G144 -> 69895 | H47: =H144 -> 67991 | I47: =I144 -> 73581 | J47: =J144 -> 75620 | K47: =K144 -> 74236 | L47: =L144 -> 113768 | M47: =M144 -> 116807 | N47: =N144 -> 102463 | ... Q47: =Q144 -> 102693 | R47: =IFERROR((Q47/G47)^(1/COUNT($G$4:$Q$4))-1,"") -> 0.035596157
B48: Total Assets | G48: =SUM(G47,G38) -> 117272 | H48: =SUM(H47,H38) -> 110495 | I48: =SUM(I47,I38) -> 117469 | J48: =SUM(J47,J38) -> 125355 | K48: =SUM(K47,K38) -> 123382 | L48: =SUM(L47,L38) -> 152188 | M48: =SUM(M47,M38) -> 155972 | N48: =SUM(N47,N38) -> 132002 | ... Q48: =SUM(Q47,Q38) -> 137175 | R48: =IFERROR((Q48/G48)^(1/COUNT($G$4:$Q$4))-1,"") -> 0.014353072
B49: Accounts Payable | G49: 6864 | H49: 6028 | I49: 6209 | J49: 6451 | K49: 6558 | L49: 4896 | M49: 4908 | N49: 3955 | O49: 4051 | P49: 4132 | Q49: 4032 | R49: =IFERROR((Q49/G49)^(1/COUNT($G$4:$Q$4))-1,"") -> -0.047215155
B50: Short-Term Debt | G50: =+SUM(G51:G52) -> 5731 | H50: =+SUM(H51:H52) -> 6461 | I50: =+SUM(I51:I52) -> 7513 | J50: =+SUM(J51:J52) -> 6987 | K50: =+SUM(K51:K52) -> 10207 | L50: =+SUM(L51:L52) -> 10177 | M50: =+SUM(M51:M52) -> 8540 | N50: =+SUM(N51:N52) -> 7761 | ... Q50: =+SUM(Q51:Q52) -> 5857 | R50: =IFERROR((Q50/G50)^(1/COUNT($G$4:$Q$4))-1,"") -> 0.0019790003
B51: Short-Term Borrowings | G51: 5731 | H51: 6461 | I51: 7513 | J51: 6987 | K51: 10207 | L51: 8797 | M51: 7183 | N51: 6787 | O51: 4760 | P51: 6426 | Q51: 5089 | R51: =IFERROR((Q51/G51)^(1/COUNT($G$4:$Q$4))-1,"") -> -0.010742671
B52: Current Portion of Lease Liabilities | G52: 0 | H52: 0 | I52: 0 | J52: 0 | K52: 0 | L52: 1380 | M52: 1357 | N52: 974 | O52: 874 | P52: 820 | Q52: 768 | R52: =IFERROR((Q52/G52)^(1/COUNT($G$4:$Q$4))-1,"")
B53: Accrued Expenses and Other Current Liabilities | G53: =+G54-G49-G50 -> 26986 | H53: =+H54-H49-H50 -> 21780 | I53: =+I54-I49-I50 -> 22553 | J53: =+J54-J49-J50 -> 23925 | K53: =+K54-K49-K50 -> 21462 | L53: =+L54-L49-L50 -> 22628 | M53: =+M54-M49-M50 -> 26421 | N53: =+N54-N49-N50 -> 21903 | ... Q53: =+Q54-Q49-Q50 -> 23253 | R53: =IFERROR((Q53/G53)^(1/COUNT($G$4:$Q$4))-1,"") -> -0.013443729
B54: Current Liabilities | G54: 39581 | H54: 34269 | I54: 36275 | J54: 37363 | K54: 38227 | L54: 37701 | M54: 39869 | N54: 33619 | O54: 31505 | P54: 34122 | Q54: 33142 | R54: =IFERROR((Q54/G54)^(1/COUNT($G$4:$Q$4))-1,"") -> -0.01601115
B55: Long-Term Debt | G55: =+SUM(G56:G57) -> 34991 | H55: =+SUM(H56:H57) -> 33428 | I55: =+SUM(I56:I57) -> 34655 | J55: =+SUM(J56:J57) -> 39837 | K55: =+SUM(K56:K57) -> 35605 | L55: =+SUM(L56:L57) -> 58234 | M55: =+SUM(M56:M57) -> 57676 | N55: =+SUM(N56:N57) -> 47379 | ... Q55: =+SUM(Q56:Q57) -> 52539 | R55: =IFERROR((Q55/G55)^(1/COUNT($G$4:$Q$4))-1,"") -> 0.03764254
B56: Long-Term Borrowings | G56: 34991 | H56: 33428 | I56: 34655 | J56: 39837 | K56: 35605 | L56: 54355 | M56: 54102 | N56: 44917 | O56: 46189 | P56: 50121 | Q56: 49884 | R56: =IFERROR((Q56/G56)^(1/COUNT($G$4:$Q$4))-1,"") -> 0.032762469
B57: Long-Term Operating Lease Liabilities | G57: 0 | H57: 0 | I57: 0 | J57: 0 | K57: 0 | L57: 3879 | M57: 3574 | N57: 2462 | O57: 2190 | P57: 2568 | Q57: 2655 | R57: =IFERROR((Q57/G57)^(1/COUNT($G$4:$Q$4))-1,"")
B58: Other Non-Current Liabilities | G58: =+G59-G55 -> 30685 | H58: =+H59-H55 -> 28374 | I58: =+I59-I55 -> 28147 | J58: =+J59-J55 -> 30431 | K58: =+K59-K55 -> 24193 | L58: =+L59-L55 -> 35519 | M58: =+M59-M55 -> 37446 | N58: =+N59-N55 -> 32008 | ... Q58: =+Q59-Q55 -> 24102 | R58: =IFERROR((Q58/G58)^(1/COUNT($G$4:$Q$4))-1,"") -> -0.021713441
B59: Non-Current Liabilities | G59: =G150 -> 65676 | H59: =H150 -> 61802 | I59: =I150 -> 62802 | J59: =J150 -> 70268 | K59: =K150 -> 59798 | L59: =L150 -> 93753 | M59: =M150 -> 95122 | N59: =N150 -> 79387 | ... Q59: =Q150 -> 76641 | R59: =IFERROR((Q59/G59)^(1/COUNT($G$4:$Q$4))-1,"") -> 0.014135209
B60: Total Liabilities | G60: =SUM(G59,G54) -> 105257 | H60: =SUM(H59,H54) -> 96071 | I60: =SUM(I59,I54) -> 99077 | J60: =SUM(J59,J54) -> 107631 | K60: =SUM(K59,K54) -> 98025 | L60: =SUM(L59,L54) -> 131454 | M60: =SUM(M59,M54) -> 134991 | N60: =SUM(N59,N54) -> 113006 | ... Q60: =SUM(Q59,Q54) -> 109783 | R60: =IFERROR((Q60/G60)^(1/COUNT($G$4:$Q$4))-1,"") -> 0.003834671
B61: Shareholder's Equity | G61: =G48-G60 -> 12015 | H61: =H48-H60 -> 14424 | I61: =I48-I60 -> 18392 | J61: =J48-J60 -> 17724 | K61: =K48-K60 -> 25357 | L61: =L48-L60 -> 20734 | M61: =M48-M60 -> 20981 | N61: =N48-N60 -> 18996 | ... Q61: =Q48-Q60 -> 27392 | R61: =IFERROR((Q61/G61)^(1/COUNT($G$4:$Q$4))-1,"") -> 0.077795487
B62: Non-Controlling Interest | G62: 146 | H62: 162 | I62: 146 | J62: 131 | K62: 134 | L62: 144 | M62: 129 | N62: 95 | O62: 77 | P62: 80 | Q62: 86
A64: x | B64: Cash Flow | G64: 2014 | H64: =+G64+1 -> 2015 | I64: =+H64+1 -> 2016 | J64: =+I64+1 -> 2017 | K64: =+J64+1 -> 2018 | L64: =+K64+1 -> 2019 | M64: =+L64+1 -> 2020 | N64: =+M64+1 -> 2021 | O64: =+N64+1 -> 2022 | ... Q64: =+P64+1 -> 2024 | R64: ="CAGR "&$G$4&" - "&$Q$4 -> CAGR 2014 - 2024
B66: Net Income | G66: =G24 -> 15752 | H66: =H24 -> 13364 | I66: =I24 -> 11433 | J66: =J24 -> 5757 | K66: =K24 -> 8723 | L66: =L24 -> 10098 | M66: =M24 -> 3873 | N66: =N24 -> 4712 | ... Q66: =Q24 -> 6016 | R66: =IFERROR((Q66/G66)^(1/COUNT($G$4:$Q$4))-1,"") -> -0.083784856
B67: D&A (Depreciation and Amortization) | G67: =+G13 -> 4492 | H67: =+H13 -> 3855 | I67: =+I13 -> 4381 | J67: =+J13 -> 4541 | K67: =+K13 -> 4480 | L67: =+L13 -> 6059 | M67: =+M13 -> 6695 | N67: =+N13 -> 6417 | ... Q67: =+Q13 -> 4667 | R67: =IFERROR((Q67/G67)^(1/COUNT($G$4:$Q$4))-1,"") -> 0.0034804455
B68: Changes in Net Working Capital | G68: =+SUM(G69:G73) -> -1766 | H68: =+SUM(H69:H73) -> -2444 | I68: =+SUM(I69:I73) -> 1357 | J68: =+SUM(J69:J73) -> 6813 | K68: =+SUM(K69:K73) -> 554 | L68: =+SUM(L69:L73) -> 1225 | M68: =+SUM(M69:M73) -> 8249 | N68: =+SUM(N69:N73) -> 1962 | ... Q68: =+SUM(Q69:Q73) -> 1313 | R68: =IFERROR((Q68/G68)^(1/COUNT($G$4:$Q$4))-1,"") -> -1.9734141
B69: (Increase) Decrease in Accounts Receivable | G69: 1270 | H69: 812 | I69: 712 | J69: 1297 | K69: 1006 | L69: 502 | M69: 5297 | N69: 1372 | O69: -539 | P69: 725 | Q69: -374
B70: (Increase) Decrease in Inventories | G70: -39 | H70: 133 | I70: -14 | J70: 18 | K70: -127 | L70: 67 | M70: -209 | N70: 138 | O70: 71 | P70: 390 | Q70: -166
B71: Increase (Decrease) in Account Payables | G71: -456 | H71: 81 | I71: 197 | J71: 47 | K71: 126 | L71: -503 | M71: 138 | N71: 85 | O71: 213 | P71: 65 | Q71: -13
B72: Increase (Decrease) in Retirement related | G72: -655 | H72: -22 | I72: 54 | J72: 1014 | K72: 1368 | L72: 301 | M72: 936 | N72: 1038 | O72: 331 | P72: -462 | Q72: 265
B73: Increase (Decrease) in Other | G73: -1886 | H73: -3448 | I73: 408 | J73: 4437 | K73: -1819 | L73: 858 | M73: 2087 | N73: -671 | O73: 126 | P73: 1466 | Q73: 1601
B74: Stock Based Compensation | G74: 512 | H74: 468 | I74: 544 | J74: 534 | K74: 510 | L74: 679 | M74: 937 | N74: 982 | O74: 987 | P74: 1133 | Q74: 1311
B75: Other Operating Adjustments | G75: =+G76-G66-G67-G68-G74 -> -2122 | H75: =+H76-H66-H67-H68-H74 -> 1765 | I75: =+I76-I66-I67-I68-I74 -> -631 | J75: =+J76-J66-J67-J68-J74 -> -921 | K75: =+K76-K66-K67-K68-K74 -> 980 | L75: =+L76-L66-L67-L68-L74 -> -3291 | M75: =+M76-M66-M67-M68-M74 -> -1557 | N75: =+N76-N66-N67-N68-N74 -> -1277 | ... Q75: =+Q76-Q66-Q67-Q68-Q74 -> 138 | R75: =IFERROR((Q75/G75)^(1/COUNT($G$4:$Q$4))-1,"") -> -1.7800152
B76: Operating Cash Flow | G76: 16868 | H76: 17008 | I76: 17084 | J76: 16724 | K76: 15247 | L76: 14770 | M76: 18197 | N76: 12796 | O76: 10435 | P76: 13931 | Q76: 13445 | R76: =IFERROR((Q76/G76)^(1/COUNT($G$4:$Q$4))-1,"") -> -0.020408064
B77: Net Capex | G77: =+SUM(G78:G79) -> -3336 | H77: =+SUM(H78:H79) -> -3209 | I77: =+SUM(I78:I79) -> -3143 | J77: =+SUM(J78:J79) -> -2769 | K77: =+SUM(K78:K79) -> -3147 | L77: =+SUM(L78:L79) -> -1749 | M77: =+SUM(M78:M79) -> -2430 | N77: =+SUM(N78:N79) -> -1675 | ... Q77: =+SUM(Q78:Q79) -> -491 | R77: =IFERROR((Q77/G77)^(1/COUNT($G$4:$Q$4))-1,"") -> -0.15986226
B78: Acquisition of Fixed & Intangibles | G78: -3740 | H78: -3579 | I78: -3567 | J78: -3229 | K78: -3395 | L78: -2286 | M78: -2618 | N78: -2062 | O78: -1346 | P78: -1245 | Q78: -1048 | R78: =IFERROR((Q78/G78)^(1/COUNT($G$4:$Q$4))-1,"") -> -0.10921727
B79: Disposal of Fixed & Intangibles | G79: 404 | H79: 370 | I79: 424 | J79: 460 | K79: 248 | L79: 537 | M79: 188 | N79: 387 | O79: 111 | P79: 321 | Q79: 557 | R79: =IFERROR((Q79/G79)^(1/COUNT($G$4:$Q$4))-1,"") -> 0.029625854
B80: Net Cash from Investments & Acquisitions | G80: =+SUM(G81:G84) -> 1856 | H80: =+SUM(H81:H84) -> -3981 | I80: =+SUM(I81:I84) -> -6311 | J80: =+SUM(J81:J84) -> -1740 | K80: =+SUM(K81:K84) -> -693 | L80: =+SUM(L81:L84) -> -31286 | M80: =+SUM(M81:M84) -> -461 | N80: =+SUM(N81:N84) -> -3593 | ... Q80: =+SUM(Q81:Q84) -> -3809 | R80: =IFERROR((Q80/G80)^(1/COUNT($G$4:$Q$4))-1,"") -> -2.0675416
B81: Acquisitions | G81: -656 | H81: -3349 | I81: -5696 | J81: -496 | K81: -139 | L81: -32630 | M81: -336 | N81: -3293 | O81: -2348 | P81: -5082 | Q81: -3289 | R81: =IFERROR((Q81/G81)^(1/COUNT($G$4:$Q$4))-1,"") -> 0.1578463
B82: Divestitures | G82: 2357 | H82: -401 | I82: -454 | J82: -205 | K82: 0 | L82: 1076 | M82: 503 | N82: 114 | O82: 1272 | P82: -4 | Q82: 698 | R82: =IFERROR((Q82/G82)^(1/COUNT($G$4:$Q$4))-1,"") -> -0.10472972
B83: Increase in LT Investment | G83: -2338 | H83: -3073 | I83: -5853 | J83: -4949 | K83: -7041 | L83: -3693 | M83: -6246 | N83: -3561 | O83: -5930 | P83: -11143 | Q83: -7762 | R83: =IFERROR((Q83/G83)^(1/COUNT($G$4:$Q$4))-1,"") -> 0.11525807
B84: Decrease in LT Investment | G84: 2493 | H84: 2842 | I84: 5692 | J84: 3910 | K84: 6487 | L84: 3961 | M84: 5618 | N84: 3147 | O84: 4665 | P84: 10647 | Q84: 6544 | R84: =IFERROR((Q84/G84)^(1/COUNT($G$4:$Q$4))-1,"") -> 0.091696481
B85: Other Investing Inflows (Outflows) | G85: =+G86-G77-G80 -> -1521 | H85: =+H86-H77-H80 -> -969 | I85: =+I86-I77-I80 -> -1474 | J85: =+J86-J77-J80 -> -2572 | K85: =+K86-K77-K80 -> -1073 | L85: =+L86-L77-L80 -> 6099 | M85: =+M86-M77-M80 -> -137 | N85: =+N86-N77-N80 -> -707 | ... Q85: =+Q86-Q77-Q80 -> -637 | R85: =IFERROR((Q85/G85)^(1/COUNT($G$4:$Q$4))-1,"") -> -0.076073779
B86: Investing Cash Flow | G86: -3001 | H86: -8159 | I86: -10928 | J86: -7081 | K86: -4913 | L86: -26936 | M86: -3028 | N86: -5975 | O86: -4202 | P86: -7070 | Q86: -4937 | R86: =IFERROR((Q86/G86)^(1/COUNT($G$4:$Q$4))-1,"") -> 0.046295325
B87: Debt Borrowing | G87: =IF(G129>0,G127+G129,G127) -> 8180 | H87: =IF(H129>0,H127+H129,H127) -> 5641 | I87: =IF(I129>0,I127+I129,I127) -> 9158 | J87: =IF(J129>0,J127+J129,J127) -> 10263 | K87: =IF(K129>0,K127+K129,K127) -> 8232 | L87: =IF(L129>0,L127+L129,L127) -> 31825 | M87: =IF(M129>0,M127+M129,M127) -> 10504 | N87: =IF(N129>0,N127+N129,N127) -> 522 | ... Q87: =IF(Q129>0,Q127+Q129,Q127) -> 5735 | R87: =IFERROR((Q87/G87)^(1/COUNT($G$4:$Q$4))-1,"") -> -0.03176671
B88: Debt Repayment | G88: =IF(G129<0,G128+G129,G128) -> -6397 | H88: =IF(H129<0,H128+H129,H128) -> -5622 | I88: =IF(I129<0,I128+I129,I128) -> -6395 | J88: =IF(J129<0,J128+J129,J128) -> -6816 | K88: =IF(K129<0,K128+K129,K128) -> -8533 | L88: =IF(L129<0,L128+L129,L128) -> -15541 | M88: =IF(M129<0,M128+M129,M128) -> -14218 | N88: =IF(N129<0,N128+N129,N128) -> -8637 | ... Q88: =IF(Q129<0,Q128+Q129,Q128) -> -6615 | R88: =IFERROR((Q88/G88)^(1/COUNT($G$4:$Q$4))-1,"") -> 0.0030510693
B89: Lease Payments | G89: 0 | H89: 0 | I89: 0 | J89: 0 | K89: 0 | L89: -4 | M89: -25 | N89: -42 | O89: -55 | P89: -75 | Q89: -189 | R89: =IFERROR((Q89/G89)^(1/COUNT($G$4:$Q$4))-1,"")
B90: Dividends | G90: -4265 | H90: -4897 | I90: -5256 | J90: -5506 | K90: -5666 | L90: -5707 | M90: -5797 | N90: -5869 | O90: -5948 | P90: -6040 | Q90: -6147 | R90: =IFERROR((Q90/G90)^(1/COUNT($G$4:$Q$4))-1,"") -> 0.033787529
B91: Increase (Repurchase) of Shares | G91: =G130+G131 -> -12970 | H91: =H130+H131 -> -4287 | I91: =I130+I131 -> -3628 | J91: =J130+J131 -> -4533 | K91: =K130+K131 -> -4614 | L91: =L130+L131 -> -1633 | M91: =M130+M131 -> -302 | N91: =N130+N131 -> -319 | ... Q91: =Q130+Q131 -> -651 | R91: =IFERROR((Q91/G91)^(1/COUNT($G$4:$Q$4))-1,"") -> -0.23813775
B92: Other Financing Inflows (Outflows) | G92: =+G93-G87-G88-G89-G90-G91 -> 0 | H92: =+H93-H87-H88-H89-H90-H91 -> -1 | I92: =+I93-I87-I88-I89-I90-I91 -> 204 | J92: =+J93-J87-J88-J89-J90-J91 -> 174 | K92: =+K93-K87-K88-K89-K90-K91 -> 112 | L92: =+L93-L87-L88-L89-L90-L91 -> 102 | M92: =+M93-M87-M88-M89-M90-M91 -> 117 | N92: =+N93-N87-N88-N89-N90-N91 -> 991 | ... Q92: =+Q93-Q87-Q88-Q89-Q90-Q91 -> 788 | R92: =IFERROR((Q92/G92)^(1/COUNT($G$4:$Q$4))-1,"")
B93: Financing Cash Flow | G93: -15452 | H93: -9166 | I93: -5917 | J93: -6418 | K93: -10469 | L93: 9042 | M93: -9721 | N93: -13354 | O93: -4958 | P93: -1769 | Q93: -7079 | R93: =IFERROR((Q93/G93)^(1/COUNT($G$4:$Q$4))-1,"") -> -0.068504726
B94: Effect of Foreign Exchange | G94: -655 | H94: -473 | I94: -51 | J94: 937 | K94: -495 | L94: -167 | M94: -87 | N94: -185 | O94: -244 | P94: 9 | Q94: -359 | R94: =IFERROR((Q94/G94)^(1/COUNT($G$4:$Q$4))-1,"") -> -0.053197541
B95: Net Changes in Cash | G95: -2240 | H95: -790 | I95: 188 | J95: 4161 | K95: -630 | L95: -3290 | M95: 5361 | N95: -6718 | O95: 1032 | P95: 5101 | Q95: 1071 | R95: =IFERROR((Q95/G95)^(1/COUNT($G$4:$Q$4))-1,"") -> -1.9351201
B96: in millions of USD
A97: x | B97: Capital Structure | G97: 42004 | H97: 42369 | I97: 42735 | J97: 43100 | K97: 43465 | L97: 43830 | M97: 44196 | N97: 44561 | O97: 44926 | P97: 45291 | Q97: 45657
B99: Market Capitalization | G99: {=(IFERROR(_xlfn.STOCKHISTORY(DCF!$R$4, G97, G97, 0, 0, 1), IFERROR(_xlfn.STOCKHISTORY(DCF!$R$4, G97+1, G97+1, 0, 0, 1), _xlfn.STOCKHISTORY(DCF!$R$4, G97-2, G97-2, 0, 0, 1))))*_xlfn.XLOOKUP("Basic Weighted Average Shares",$B:$B,G:G)/1000000} -> 161125.49 | H99: {=(IFERROR(_xlfn.STOCKHISTORY(DCF!$R$4, H97, H97, 0, 0, 1), IFERROR(_xlfn.STOCKHISTORY(DCF!$R$4, H97+1, H97+1, 0, 0, 1), _xlfn.STOCKHISTORY(DCF!$R$4, H97-2, H97-2, 0, 0, 1))))*_xlfn.XLOOKUP("Basic Weighted Average Shares",$B:$B,H:H)/1000000} -> 134694.82 | I99: {=(IFERROR(_xlfn.STOCKHISTORY(DCF!$R$4, I97, I97, 0, 0, 1), IFERROR(_xlfn.STOCKHISTORY(DCF!$R$4, I97+1, I97+1, 0, 0, 1), _xlfn.STOCKHISTORY(DCF!$R$4, I97-2, I97-2, 0, 0, 1))))*_xlfn.XLOOKUP("Basic Weighted Average Shares",$B:$B,I:I)/1000000} -> 159173.39 | J99: {=(IFERROR(_xlfn.STOCKHISTORY(DCF!$R$4, J97, J97, 0, 0, 1), IFERROR(_xlfn.STOCKHISTORY(DCF!$R$4, J97+1, J97+1, 0, 0, 1), _xlfn.STOCKHISTORY(DCF!$R$4, J97-2, J97-2, 0, 0, 1))))*_xlfn.XLOOKUP("Basic Weighted Average Shares",$B:$B,J:J)/1000000} -> 143114.52 | K99: {=(IFERROR(_xlfn.STOCKHISTORY(DCF!$R$4, K97, K97, 0, 0, 1), IFERROR(_xlfn.STOCKHISTORY(DCF!$R$4, K97+1, K97+1, 0, 0, 1), _xlfn.STOCKHISTORY(DCF!$R$4, K97-2, K97-2, 0, 0, 1))))*_xlfn.XLOOKUP("Basic Weighted Average Shares",$B:$B,K:K)/1000000} -> 103672.5 | L99: {=(IFERROR(_xlfn.STOCKHISTORY(DCF!$R$4, L97, L97, 0, 0, 1), IFERROR(_xlfn.STOCKHISTORY(DCF!$R$4, L97+1, L97+1, 0, 0, 1), _xlfn.STOCKHISTORY(DCF!$R$4, L97-2, L97-2, 0, 0, 1))))*_xlfn.XLOOKUP("Basic Weighted Average Shares",$B:$B,L:L)/1000000} -> 118924.99 | M99: {=(IFERROR(_xlfn.STOCKHISTORY(DCF!$R$4, M97, M97, 0, 0, 1), IFERROR(_xlfn.STOCKHISTORY(DCF!$R$4, M97+1, M97+1, 0, 0, 1), _xlfn.STOCKHISTORY(DCF!$R$4, M97-2, M97-2, 0, 0, 1))))*_xlfn.XLOOKUP("Basic Weighted Average Shares",$B:$B,M:M)/1000000} -> 112077.09 | N99: {=(IFERROR(_xlfn.STOCKHISTORY(DCF!$R$4, N97, N97, 0, 0, 1), IFERROR(_xlfn.STOCKHISTORY(DCF!$R$4, N97+1, N97+1, 0, 0, 1), _xlfn.STOCKHISTORY(DCF!$R$4, N97-2, N97-2, 0, 0, 1))))*_xlfn.XLOOKUP("Basic Weighted Average Shares",$B:$B,N:N)/1000000} -> 119758.13 | O99: {=(IFERROR(_xlfn.STOCKHISTORY(DCF!$R$4, O97, O97, 0, 0, 1), IFERROR(_xlfn.STOCKHISTORY(DCF!$R$4, O97+1, O97+1, 0, 0, 1), _xlfn.STOCKHISTORY(DCF!$R$4, O97-2, O97-2, 0, 0, 1))))*_xlfn.XLOOKUP("Basic Weighted Average Shares",$B:$B,O:O)/1000000} -> 127329.81 | P99: {=(IFERROR(_xlfn.STOCKHISTORY(DCF!$R$4, P97, P97, 0, 0, 1), IFERROR(_xlfn.STOCKHISTORY(DCF!$R$4, P97+1, P97+1, 0, 0, 1), _xlfn.STOCKHISTORY(DCF!$R$4, P97-2, P97-2, 0, 0, 1))))*_xlfn.XLOOKUP("Basic Weighted Average Shares",$B:$B,P:P)/1000000} -> 149028.45 | Q99: {=(IFERROR(_xlfn.STOCKHISTORY(DCF!$R$4, Q97, Q97, 0, 0, 1), IFERROR(_xlfn.STOCKHISTORY(DCF!$R$4, Q97+1, Q97+1, 0, 0, 1), _xlfn.STOCKHISTORY(DCF!$R$4, Q97-2, Q97-2, 0, 0, 1))))*_xlfn.XLOOKUP("Basic Weighted Average Shares",$B:$B,Q:Q)/1000000} -> 202632.22
B100: Cash & Cash Equivalents | G100: =_xlfn.XLOOKUP("Cash & Cash Equivalents & ST Investments",$B$30:$B$62,G$30:G$62) -> 8476 | H100: =_xlfn.XLOOKUP("Cash & Cash Equivalents & ST Investments",$B$30:$B$62,H$30:H$62) -> 8194 | I100: =_xlfn.XLOOKUP("Cash & Cash Equivalents & ST Investments",$B$30:$B$62,I$30:I$62) -> 8527 | J100: =_xlfn.XLOOKUP("Cash & Cash Equivalents & ST Investments",$B$30:$B$62,J$30:J$62) -> 12580 | K100: =_xlfn.XLOOKUP("Cash & Cash Equivalents & ST Investments",$B$30:$B$62,K$30:K$62) -> 11997 | L100: =_xlfn.XLOOKUP("Cash & Cash Equivalents & ST Investments",$B$30:$B$62,L$30:L$62) -> 8313 | M100: =_xlfn.XLOOKUP("Cash & Cash Equivalents & ST Investments",$B$30:$B$62,M$30:M$62) -> 13675 | N100: =_xlfn.XLOOKUP("Cash & Cash Equivalents & ST Investments",$B$30:$B$62,N$30:N$62) -> 6957 | ... Q100: =_xlfn.XLOOKUP("Cash & Cash Equivalents & ST Investments",$B$30:$B$62,Q$30:Q$62) -> 14591
B101: Total Debt | G101: =(_xlfn.XLOOKUP("Short-Term Debt",$B$30:$B$62,G$30:G$62)+_xlfn.XLOOKUP("Long-Term Debt",$B$30:$B$62,G$30:G$62)) -> 40722 | H101: =(_xlfn.XLOOKUP("Short-Term Debt",$B$30:$B$62,H$30:H$62)+_xlfn.XLOOKUP("Long-Term Debt",$B$30:$B$62,H$30:H$62)) -> 39889 | I101: =(_xlfn.XLOOKUP("Short-Term Debt",$B$30:$B$62,I$30:I$62)+_xlfn.XLOOKUP("Long-Term Debt",$B$30:$B$62,I$30:I$62)) -> 42168 | J101: =(_xlfn.XLOOKUP("Short-Term Debt",$B$30:$B$62,J$30:J$62)+_xlfn.XLOOKUP("Long-Term Debt",$B$30:$B$62,J$30:J$62)) -> 46824 | K101: =(_xlfn.XLOOKUP("Short-Term Debt",$B$30:$B$62,K$30:K$62)+_xlfn.XLOOKUP("Long-Term Debt",$B$30:$B$62,K$30:K$62)) -> 45812 | L101: =(_xlfn.XLOOKUP("Short-Term Debt",$B$30:$B$62,L$30:L$62)+_xlfn.XLOOKUP("Long-Term Debt",$B$30:$B$62,L$30:L$62)) -> 68411 | M101: =(_xlfn.XLOOKUP("Short-Term Debt",$B$30:$B$62,M$30:M$62)+_xlfn.XLOOKUP("Long-Term Debt",$B$30:$B$62,M$30:M$62)) -> 66216 | N101: =(_xlfn.XLOOKUP("Short-Term Debt",$B$30:$B$62,N$30:N$62)+_xlfn.XLOOKUP("Long-Term Debt",$B$30:$B$62,N$30:N$62)) -> 55140 | ... Q101: =(_xlfn.XLOOKUP("Short-Term Debt",$B$30:$B$62,Q$30:Q$62)+_xlfn.XLOOKUP("Long-Term Debt",$B$30:$B$62,Q$30:Q$62)) -> 58396
B102: Preferred Stock | G102: 0 | H102: 0 | I102: 0 | J102: 0 | K102: 0 | L102: 0 | M102: 0 | N102: 0 | O102: 0 | P102: 0 | Q102: 0
B103: Non-Controlling Interest | G103: =_xlfn.XLOOKUP("Non-Controlling Interest",$B$30:$B$62,G$30:G$62) -> 146 | H103: =_xlfn.XLOOKUP("Non-Controlling Interest",$B$30:$B$62,H$30:H$62) -> 162 | I103: =_xlfn.XLOOKUP("Non-Controlling Interest",$B$30:$B$62,I$30:I$62) -> 146 | J103: =_xlfn.XLOOKUP("Non-Controlling Interest",$B$30:$B$62,J$30:J$62) -> 131 | K103: =_xlfn.XLOOKUP("Non-Controlling Interest",$B$30:$B$62,K$30:K$62) -> 134 | L103: =_xlfn.XLOOKUP("Non-Controlling Interest",$B$30:$B$62,L$30:L$62) -> 144 | M103: =_xlfn.XLOOKUP("Non-Controlling Interest",$B$30:$B$62,M$30:M$62) -> 129 | N103: =_xlfn.XLOOKUP("Non-Controlling Interest",$B$30:$B$62,N$30:N$62) -> 95 | ... Q103: =_xlfn.XLOOKUP("Non-Controlling Interest",$B$30:$B$62,Q$30:Q$62) -> 86
B104: Enterprise Value | G104: =+G99-G100+G101+G102+G103 -> 193517.49 | H104: =+H99-H100+H101+H102+H103 -> 166551.82 | I104: =+I99-I100+I101+I102+I103 -> 192960.39 | J104: =+J99-J100+J101+J102+J103 -> 177489.52 | K104: =+K99-K100+K101+K102+K103 -> 137621.5 | L104: =+L99-L100+L101+L102+L103 -> 179166.99 | M104: =+M99-M100+M101+M102+M103 -> 164747.09 | N104: =+N99-N100+N101+N102+N103 -> 168036.13 | ... Q104: =+Q99-Q100+Q101+Q102+Q103 -> 246523.22
A106: x | B106: Debt Schedule | G106: Cash | H106: 2025 | I106: =+H106+1 -> 2026 | J106: =+I106+1 -> 2027 | K106: =+J106+1 -> 2028 | L106: =+K106+1 -> 2029 | M106: =+L106+1 -> 2030 | N106: =+M106+1 -> 2031 | O106: =+N106+1 -> 2032 | P106: =+O106+1 -> 2033 | Q106: =+P106+1 -> 2034
L107: v | M107: v | N107: v | O107: v | P107: v | Q107: v
B108: Cash | G108: =SUM(H108:Q108) -> 55112 | H108: =H165 -> 4777.6667 | I108: =I165 -> 6140 | J108: =J165 -> 6530 | K108: =K165 -> 3445.3333 | L108: =L165 -> 4785 | M108: =M165 -> 2385 | N108: =N165 -> 3088 | O108: =O165 -> 3506 | ... Q108: =Q165 -> 19705
...

Sheet WACC
B2: WACC
B4: WACC = % of Equity x Cost of Equity + % de Debt x Cost of Debt x (1 - Tax Rate)
B5: Cost of Equity = Risk-Free Rate + Beta x Equity Risk Premium
B7: WACC | I7: Region | J7: Weight | K7: ERP | M7: Peers | N7: Beta (Unlevered)
B9: Market Cap (in millions) | G9: {=+_FV(DCF!R4,"Market cap",TRUE)/1000000} -> 268622.2 | I9: =Segments!B6 -> United States of America | J9: =Segments!D6 -> 0.41463737 | K9: 0.0433 | M9: =+Peers!B8 -> ACCENTURE PUBLIC LIMITED COMPANY | N9: =+Peers!E75 -> 1.1545799
B10: % of Equity | G10: =IFERROR(G9/G23,"") -> 0.8214289 | M10: =+Peers!B9 -> Capgemini | N10: =+Peers!F75 -> 0.76463422
B11: Cost of Equity | G11: =IFERROR(G12+G14*G15,"") -> 0.099244333 | M11: =+Peers!B10 -> MICROSOFT CORPORATION | N11: =+Peers!G75 -> 0.78581051
B12: Risk-Free Rate | G12: 0.0429 | M12: =+Peers!B11 -> ORACLE CORPORATION | N12: =+Peers!H75 -> 0.15037288
B13: Unlevered Beta | G13: =+N19 -> 1.0968313 | M13: =+Peers!B12 -> HEWLETT PACKARD ENTERPRISE COMPANY | N13: =+Peers!I75 -> 0.85226956
B14: Beta | G14: =+IFERROR(G13*(1+(1-G21)*(G18/G9)),"") -> 1.3012548 | I14: Others | J14: =1-SUM(J9:J13) -> 0.58536263 | K14: =MAX(K9:K13) -> 0.0433 | M14: =+Peers!B13 -> IONQ | N14: =+Peers!J75 -> 2.4781694
B15: Equity Risk Premium | G15: =SUMPRODUCT(J9:J14,K9:K14) -> 0.0433 | M15: =+Peers!B14 -> Rigetti | N15: =+Peers!K75 -> 1.4919829
B16: Cost of Equity | G16: =IFERROR(+G12+G13*G15,"") -> 0.090392797 | M16: =+Peers!B15 | N16: =+Peers!L75
M17: =+Peers!B16 | N17: =+Peers!M75
B18: Debt (in millions) | G18: =Inputs!Q114 -> 58396 | M18: =+Peers!B17 | N18: =+Peers!N75
B19: % of Debt | G19: =IFERROR(G18/G23,"") -> 0.1785711 | M19: Average | N19: =IFERROR(+AVERAGEIF(N9:N18,">0"),"") -> 1.0968313
B20: Cost of debt | G20: =Inputs!Q18/Inputs!Q114 -> 0.029317077
B21: Tax Rate | G21: =+DCF!H80 -> 0.14266667
B23: Total | G23: =+G9+G18 -> 327018.2
B25: WACC | G25: =IFERROR(G10*G11+G19*G20*(1-G21),"") -> 0.08601046

Sheet Multiples
B2: Multiples
