Workbook
Name COOLFUCNTION: _xlfn.LAMBDA(_xldudf_BOARDFLARE_EXEC("workbook-settings:coolfucntion"))
Name COOLFUCNTION: _xlfn.LAMBDA(_xldudf_BOARDFLARE_EXEC("workbook-settings:coolfucntion"))
Name COOLFUCNTION: _xlfn.LAMBDA(_xldudf_BOARDFLARE_EXEC("workbook-settings:coolfucntion"))
Name COOLFUCNTION: _xlfn.LAMBDA(_xldudf_BOARDFLARE_EXEC("workbook-settings:coolfucntion"))
Name COOLFUCNTION: _xlfn.LAMBDA(_xldudf_BOARDFLARE_EXEC("workbook-settings:coolfucntion"))
Name COOLFUCNTION: _xlfn.LAMBDA(_xldudf_BOARDFLARE_EXEC("workbook-settings:coolfucntion"))
Name COOLFUCNTION: _xlfn.LAMBDA(_xldudf_BOARDFLARE_EXEC("workbook-settings:coolfucntion"))
Name COOLFUCNTION: _xlfn.LAMBDA(_xldudf_BOARDFLARE_EXEC("workbook-settings:coolfucntion"))
Name COOLFUCNTION: _xlfn.LAMBDA(_xldudf_BOARDFLARE_EXEC("workbook-settings:coolfucntion"))
Name COOLFUCNTION: _xlfn.LAMBDA(_xldudf_BOARDFLARE_EXEC("workbook-settings:coolfucntion"))
Name Sectors: #REF!
Name Sectors: #REF!
Name Sectors: #REF!

Sheet Summary
E2: | EQUITY RESEARCH | U2: Lisbon Investment Society Equity Research
U3: April 18, 2025
D6: {=+_FV(DCF!R4,"Name")} -> INTEL CORPORATION | U6: Hold
D8: Intel is a leading American technology company known for designing and manufacturing semiconductor chips and processors that power computers, data centers, and AI systems. Its products include high-performance CPUs, GPUs, and system-on-chip solutions used by major tech firms, enterprises, and consumers worldwide. | U8: EXCHANGE:(TICKER)
U9: {=+"Price (7 Mar 25): $"&_FV(DCF!$R$4,"Price")} -> Price (7 Mar 25): $31,515
D10: Investment Thesis | U10: ="Price Target: $" & ROUND(IF(Summary!G25="FCFF",DCF!Q211,IF(Summary!G25="FCFE",DCF!Q254,IF(Summary!G25="Tax Shield",DCF!Q227,DCF!Q270))),2) &" "&IF(Summary!G25="FCFF","(FCFF)",IF(Summary!G25="FCFE","(FCFE)",IF(Summary!G25="Tax Shield","(APV)","(DDM)"))) -> Price Target: $6,33 (FCFF)
D11: We issue a HOLD recommendation on Intel Corporation. While our Free Cash Flow to the Firm (FCFF) valuation indicates a downside potential, we believe the company's strong market presence and ongoing strategic investments justify a neutral stance. Despite Intel’s efforts to optimize its manufacturing processes, we do not foresee a significant turnaround in performance over the next decade. Its entrenched position in the semiconductor ecosystem provides a degree of stability and long-term optionality. We acknowledge the continued uncertainty regarding Intel’s ability to achieve and sustain a gross margin of 50% or higher, which is critical to regaining investor confidence and driving valuation multiples. | U11: =+"Upside (Downside): "&ROUND((DCF!$Q$214*100),2)&"%" -> Upside (Downside): -79,9%
U14: =+Industry!E28&", "&ESG!C9 -> USA, Information Technology
U15: =+ESG!C10 -> Semiconductors & Semiconductor Equipment
D17: Operating Metrics | F17: 2023 | G17: =+F17+1 -> 2024 | H17: =+G17+1 -> 2025 | I17: =+H17+1 -> 2026 | K17: Valuation Multiples | N17: 2022 | O17: =+N17+1 -> 2023 | P17: =+O17+1 -> 2024 | Q17: =+P17+1 -> 2025 | R17: =+Q17+1 -> 2026 | U17: Mafalda Bento
D18: =DCF!B17 -> CCD | F18: =DCF!F17 -> 29258 | G18: =DCF!G17 -> 30290 | H18: =DCF!H17 -> 31804.5 | I18: =DCF!I17 -> 34030.815 | K18: EV / Sales | N18: =IFERROR(_xlfn.XLOOKUP($K18,Multiples!$B:$B,Multiples!N:N),"") -> 1.9543991 | O18: =IFERROR(_xlfn.XLOOKUP($K18,Multiples!$B:$B,Multiples!O:O),"") -> 4.375922 | P18: =IFERROR(_xlfn.XLOOKUP($K18,Multiples!$B:$B,Multiples!P:P),"") -> 2.1893373 | Q18: =IFERROR(_xlfn.XLOOKUP($K18,Multiples!$B:$B,Multiples!Q:Q),"") -> 0.030084902 | R18: =IFERROR(_xlfn.XLOOKUP($K18,Multiples!$B:$B,Multiples!R:R),"") -> 0.028802171 | U18: mafaldajbento@aln.iseg.ulisboa.pt
D19: =DCF!B20 -> DCAI | F19: =DCF!F20 -> 12635 | G19: =DCF!G20 -> 12817 | H19: =DCF!H20 -> 11535.3 | I19: =DCF!I20 -> 10958.535 | K19: Price / Sales | N19: =IFERROR(_xlfn.XLOOKUP($K19,Multiples!$B:$B,Multiples!N:N),"") -> 1.7075948 | O19: =IFERROR(_xlfn.XLOOKUP($K19,Multiples!$B:$B,Multiples!O:O),"") -> 3.8826344 | P19: =IFERROR(_xlfn.XLOOKUP($K19,Multiples!$B:$B,Multiples!P:P),"") -> 1.6160524 | Q19: =IFERROR(_xlfn.XLOOKUP($K19,Multiples!$B:$B,Multiples!Q:Q),"") -> 0 | R19: =IFERROR(_xlfn.XLOOKUP($K19,Multiples!$B:$B,Multiples!R:R),"") -> 0 | U19: (+351) 913 761 691
D20: =DCF!B23 -> NEX | F20: =DCF!F23 -> 5774 | G20: =DCF!G23 -> 5842 | H20: =DCF!H23 -> 5900.42 | I20: =DCF!I23 -> 6018.4284 | K20: EV / EBITDA | N20: =IFERROR(_xlfn.XLOOKUP($K20,Multiples!$B:$B,Multiples!N:N),"") -> 8.5524797 | O20: =IFERROR(_xlfn.XLOOKUP($K20,Multiples!$B:$B,Multiples!O:O),"") -> 25.031382 | P20: =IFERROR(_xlfn.XLOOKUP($K20,Multiples!$B:$B,Multiples!P:P),"") -> 19.522418 | Q20: =IFERROR(_xlfn.XLOOKUP($K20,Multiples!$B:$B,Multiples!Q:Q),"") -> -0.26114947 | R20: =IFERROR(_xlfn.XLOOKUP($K20,Multiples!$B:$B,Multiples!R:R),"") -> -0.90451115 | U20: Deolize Neto
D21: =DCF!B26 -> Intel Foundry | F21: =DCF!F26 -> 18910 | G21: =DCF!G26 -> 17543 | H21: =DCF!H26 -> 18069.29 | I21: =DCF!I26 -> 19334.14 | K21: EV / EBIT | N21: =IFERROR(_xlfn.XLOOKUP($K21,Multiples!$B:$B,Multiples!N:N),"") -> 89.688996 | O21: =IFERROR(_xlfn.XLOOKUP($K21,Multiples!$B:$B,Multiples!O:O),"") -> -1945.0615 | P21: =IFERROR(_xlfn.XLOOKUP($K21,Multiples!$B:$B,Multiples!P:P),"") -> -21.433628 | Q21: =IFERROR(_xlfn.XLOOKUP($K21,Multiples!$B:$B,Multiples!Q:Q),"") -> -0.26114947 | R21: =IFERROR(_xlfn.XLOOKUP($K21,Multiples!$B:$B,Multiples!R:R),"") -> -0.90451115 | U21: l62144@aln.iseg.ulisboa.pt
K22: Price / Earnings | N22: =IFERROR(_xlfn.XLOOKUP($K22,Multiples!$B:$B,Multiples!N:N),"") -> 38.412658 | O22: =IFERROR(_xlfn.XLOOKUP($K22,Multiples!$B:$B,Multiples!O:O),"") -> 110.98972 | P22: =IFERROR(_xlfn.XLOOKUP($K22,Multiples!$B:$B,Multiples!P:P),"") -> -6.6081934 | Q22: =IFERROR(_xlfn.XLOOKUP($K22,Multiples!$B:$B,Multiples!Q:Q),"") -> 0 | R22: =IFERROR(_xlfn.XLOOKUP($K22,Multiples!$B:$B,Multiples!R:R),"") -> 0 | U22: (+351) 939 196 808
K23: Price / Book | N23: =IFERROR(_xlfn.XLOOKUP($K23,Multiples!$B:$B,Multiples!N:N),"") -> 1.0424518 | O23: =IFERROR(_xlfn.XLOOKUP($K23,Multiples!$B:$B,Multiples!O:O),"") -> 1.9146774 | P23: =IFERROR(_xlfn.XLOOKUP($K23,Multiples!$B:$B,Multiples!P:P),"") -> 0.81702719 | Q23: =IFERROR(_xlfn.XLOOKUP($K23,Multiples!$B:$B,Multiples!Q:Q),"") -> 0 | R23: =IFERROR(_xlfn.XLOOKUP($K23,Multiples!$B:$B,Multiples!R:R),"") -> 0 | U23: Guilherme Tomás
U24: l63853@aln.iseg.ulisboa.pt
D25: Year | E25: Net Sales | F25: EBIT Margin | G25: FCFF | H25: =+IF(Summary!$G$25="FCFF",DCF!AB6,IF(Summary!$G$25="FCFE",DCF!AC6,DCF!AD6)) -> NOPAT | I25: Net Capex | K25: Profitability Ratios | N25: 2022 | O25: =+N25+1 -> 2023 | P25: =+O25+1 -> 2024 | Q25: =+P25+1 -> 2025 | R25: =+Q25+1 -> 2026 | U25: (+351) 911 188 108
D26: 2022 | E26: =+DCF!E32 -> 63054 | F26: =+DCF!E62 -> 0.021790846 | G26: =+INDEX(DCF!X7:AA7,MATCH(Summary!$G$25,{"FCFF","FCFE","Tax Shield","Total Payout"},0)) -> -10609.043 | H26: =+IF(Summary!$G$25="FCFF",DCF!AB7,IF(Summary!$G$25="FCFE",DCF!AC7,DCF!AD7)) -> 1507.9569 | I26: =+DCF!E136 -> -25050 | K26: Return on Assets | N26: =IFERROR(_xlfn.XLOOKUP($K26,Multiples!$B:$B,Multiples!N:N),"") -> 0.015392388 | O26: =IFERROR(_xlfn.XLOOKUP($K26,Multiples!$B:$B,Multiples!O:O),"") -> 0.0099022822 | P26: =IFERROR(_xlfn.XLOOKUP($K26,Multiples!$B:$B,Multiples!P:P),"") -> -0.066091559 | Q26: =IFERROR(_xlfn.XLOOKUP($K26,Multiples!$B:$B,Multiples!Q:Q),"") -> -0.056875013 | R26: =IFERROR(_xlfn.XLOOKUP($K26,Multiples!$B:$B,Multiples!R:R),"") -> -0.014451172 | U26: Maria Ferreira
D27: =+D26+1 -> 2023 | E27: =+DCF!F32 -> 54228 | F27: =+DCF!F62 -> -0.0022497603 | G27: =+INDEX(DCF!X8:AA8,MATCH(Summary!$G$25,{"FCFF","FCFE","Tax Shield","Total Payout"},0)) -> -15272.197 | H27: =+IF(Summary!$G$25="FCFF",DCF!AB8,IF(Summary!$G$25="FCFE",DCF!AC8,DCF!AD8)) -> -235.19715 | I27: =+DCF!F136 -> -25750 | K27: Return on Equity | N27: =IFERROR(_xlfn.XLOOKUP($K27,Multiples!$B:$B,Multiples!N:N),"") -> 0.027138238 | O27: =IFERROR(_xlfn.XLOOKUP($K27,Multiples!$B:$B,Multiples!O:O),"") -> 0.017250943 | P27: =IFERROR(_xlfn.XLOOKUP($K27,Multiples!$B:$B,Multiples!P:P),"") -> -0.12363851 | Q27: =IFERROR(_xlfn.XLOOKUP($K27,Multiples!$B:$B,Multiples!Q:Q),"") -> 3.587293e-15 | R27: =IFERROR(_xlfn.XLOOKUP($K27,Multiples!$B:$B,Multiples!R:R),"") -> 9.1148267e-16 | U27: l61624@aln.iseg.ulisboa.pt
D28: =+D27+1 -> 2024 | E28: =+DCF!G32 -> 53101 | F28: =+DCF!G62 -> -0.10214497 | G28: =+INDEX(DCF!X9:AA9,MATCH(Summary!$G$25,{"FCFF","FCFE","Tax Shield","Total Payout"},0)) -> -24467.235 | H28: =+IF(Summary!$G$25="FCFF",DCF!AB9,IF(Summary!$G$25="FCFE",DCF!AC9,DCF!AD9)) -> -14192.235 | I28: =+DCF!G136 -> -23944 | K28: Return on Total Capital | N28: =IFERROR(_xlfn.XLOOKUP($K28,Multiples!$B:$B,Multiples!N:N),"") -> 0.010376588 | O28: =IFERROR(_xlfn.XLOOKUP($K28,Multiples!$B:$B,Multiples!O:O),"") -> -0.0014945109 | P28: =IFERROR(_xlfn.XLOOKUP($K28,Multiples!$B:$B,Multiples!P:P),"") -> -0.093509002 | Q28: =IFERROR(_xlfn.XLOOKUP($K28,Multiples!$B:$B,Multiples!Q:Q),"") -> 2.1696913e-15 | R28: =IFERROR(_xlfn.XLOOKUP($K28,Multiples!$B:$B,Multiples!R:R),"") -> 6.2674025e-16 | U28: (+351) 967 081 495
D29: =+D28+1 -> 2025 | E29: =+DCF!H32 -> 67309.51 | F29: =+DCF!H62 -> -0.11520185 | G29: =+INDEX(DCF!X10:AA10,MATCH(Summary!$G$25,{"FCFF","FCFE","Tax Shield","Total Payout"},0)) -> 10069.536 | H29: =+IF(Summary!$G$25="FCFF",DCF!AB10,IF(Summary!$G$25="FCFE",DCF!AC10,DCF!AD10)) -> -7754.1799 | I29: =+DCF!H136 -> -3112.72 | K29: EBITDA Margin | N29: =IFERROR(_xlfn.XLOOKUP($K29,Multiples!$B:$B,Multiples!N:N),"") -> 0.22851841 | O29: =IFERROR(_xlfn.XLOOKUP($K29,Multiples!$B:$B,Multiples!O:O),"") -> 0.17481744 | P29: =IFERROR(_xlfn.XLOOKUP($K29,Multiples!$B:$B,Multiples!P:P),"") -> 0.11214478 | Q29: =IFERROR(_xlfn.XLOOKUP($K29,Multiples!$B:$B,Multiples!Q:Q),"") -> -0.11520185 | R29: =IFERROR(_xlfn.XLOOKUP($K29,Multiples!$B:$B,Multiples!R:R),"") -> -0.031842804
D30: =+D29+1 -> 2026 | E30: =+DCF!I32 -> 70341.919 | F30: =+DCF!I62 -> -0.031842804 | G30: =+INDEX(DCF!X11:AA11,MATCH(Summary!$G$25,{"FCFF","FCFE","Tax Shield","Total Payout"},0)) -> 6728.3739 | H30: =+IF(Summary!$G$25="FCFF",DCF!AB11,IF(Summary!$G$25="FCFE",DCF!AC11,DCF!AD11)) -> -2239.8839 | I30: =+DCF!I136 -> -3423.992 | K30: EBIT Margin | N30: =IFERROR(_xlfn.XLOOKUP($K30,Multiples!$B:$B,Multiples!N:N),"") -> 0.021790846 | O30: =IFERROR(_xlfn.XLOOKUP($K30,Multiples!$B:$B,Multiples!O:O),"") -> -0.0022497603 | P30: =IFERROR(_xlfn.XLOOKUP($K30,Multiples!$B:$B,Multiples!P:P),"") -> -0.10214497 | Q30: =IFERROR(_xlfn.XLOOKUP($K30,Multiples!$B:$B,Multiples!Q:Q),"") -> -0.11520185 | R30: =IFERROR(_xlfn.XLOOKUP($K30,Multiples!$B:$B,Multiples!R:R),"") -> -0.031842804 | U30: Statistics
D31: =+D30+1 -> 2027 | E31: =+DCF!J32 -> 73263.225 | F31: =+DCF!J62 -> -0.01347868 | G31: =+INDEX(DCF!X12:AA12,MATCH(Summary!$G$25,{"FCFF","FCFE","Tax Shield","Total Payout"},0)) -> 12111.315 | H31: =+IF(Summary!$G$25="FCFF",DCF!AB12,IF(Summary!$G$25="FCFE",DCF!AC12,DCF!AD12)) -> -2185.2784 | I31: =+DCF!J136 -> -3595.1916 | K31: Gross Profit Margin | N31: =IFERROR(_xlfn.XLOOKUP($K31,Multiples!$B:$B,Multiples!N:N),"") -> 0.42607923 | O31: =IFERROR(_xlfn.XLOOKUP($K31,Multiples!$B:$B,Multiples!O:O),"") -> 0.40036513 | P31: =IFERROR(_xlfn.XLOOKUP($K31,Multiples!$B:$B,Multiples!P:P),"") -> 0.32664168 | Q31: =IFERROR(_xlfn.XLOOKUP($K31,Multiples!$B:$B,Multiples!Q:Q),"") -> 0.35 | R31: =IFERROR(_xlfn.XLOOKUP($K31,Multiples!$B:$B,Multiples!R:R),"") -> 0.38 | U31: Beta | V31: =Peers!D74 -> 1.266
D32: =+D31+1 -> 2028 | E32: =+DCF!K32 -> 76429.421 | F32: =+DCF!K62 -> -0.053088308 | G32: =+INDEX(DCF!X13:AA13,MATCH(Summary!$G$25,{"FCFF","FCFE","Tax Shield","Total Payout"},0)) -> 6742.719 | H32: =+IF(Summary!$G$25="FCFF",DCF!AB13,IF(Summary!$G$25="FCFE",DCF!AC13,DCF!AD13)) -> -8433.2258 | I32: =+DCF!K136 -> -3774.9512 | K32: SG&A Margin | N32: =IFERROR(_xlfn.XLOOKUP($K32,Multiples!$B:$B,Multiples!N:N),"") -> 0.11104767 | O32: =IFERROR(_xlfn.XLOOKUP($K32,Multiples!$B:$B,Multiples!O:O),"") -> 0.10389467 | P32: =IFERROR(_xlfn.XLOOKUP($K32,Multiples!$B:$B,Multiples!P:P),"") -> 0.10370803 | Q32: =IFERROR(_xlfn.XLOOKUP($K32,Multiples!$B:$B,Multiples!Q:Q),"") -> 0.10621679 | R32: =IFERROR(_xlfn.XLOOKUP($K32,Multiples!$B:$B,Multiples!R:R),"") -> 0.10460649 | U32: % Float | V32: =+Peers!D73 -> 0.99082569
D33: =+D32+1 -> 2029 | E33: =+DCF!L32 -> 79853.274 | F33: =+DCF!L62 -> -0.052452368 | G33: =+INDEX(DCF!X14:AA14,MATCH(Summary!$G$25,{"FCFF","FCFE","Tax Shield","Total Payout"},0)) -> 4999.6844 | H33: =+IF(Summary!$G$25="FCFF",DCF!AB14,IF(Summary!$G$25="FCFE",DCF!AC14,DCF!AD14)) -> -8981.6159 | I33: =+DCF!L136 -> -3963.6987 | K33: Net Income Margin | N33: =IFERROR(_xlfn.XLOOKUP($K33,Multiples!$B:$B,Multiples!N:N),"") -> 0.04445396 | O33: =IFERROR(_xlfn.XLOOKUP($K33,Multiples!$B:$B,Multiples!O:O),"") -> 0.034981928 | P33: =IFERROR(_xlfn.XLOOKUP($K33,Multiples!$B:$B,Multiples!P:P),"") -> -0.24455283 | Q33: =IFERROR(_xlfn.XLOOKUP($K33,Multiples!$B:$B,Multiples!Q:Q),"") -> -0.19047077 | R33: =IFERROR(_xlfn.XLOOKUP($K33,Multiples!$B:$B,Multiples!R:R),"") -> -0.046309718 | U33: % Held by Insiders | V33: =+Peers!D76 -> 0.0008
U34: % Held by Institutions | V34: =+Peers!D77 -> 0.6606
D35: SWOT Analysis | K35: Liquidity Ratios | N35: 2022 | O35: =+N35+1 -> 2023 | P35: =+O35+1 -> 2024 | Q35: =+P35+1 -> 2025 | R35: =+Q35+1 -> 2026 | U35: Short % of Float | V35: =+Peers!D78 -> 0.0261
D36: Strengths | G36: Weaknesses | K36: Cash Ratio | N36: =IFERROR(_xlfn.XLOOKUP($K36,Multiples!$B:$B,Multiples!N:N),"") -> 0.3465713 | O36: =IFERROR(_xlfn.XLOOKUP($K36,Multiples!$B:$B,Multiples!O:O),"") -> 0.25234378 | P36: =IFERROR(_xlfn.XLOOKUP($K36,Multiples!$B:$B,Multiples!P:P),"") -> 0.2312847 | Q36: =IFERROR(_xlfn.XLOOKUP($K36,Multiples!$B:$B,Multiples!Q:Q),"") -> 1.0419216 | R36: =IFERROR(_xlfn.XLOOKUP($K36,Multiples!$B:$B,Multiples!R:R),"") -> 1.6221183 | W36: 120.87
D37: Economies of scale; Strong recognition; Government Support; Advanced Manufacturing Capabilities | G37: A bad past scenario compared to the growth of the sector; Dependence on one market (not diverse); High capital intensity needed; | K37: Quick Ratio | N37: =IFERROR(_xlfn.XLOOKUP($K37,Multiples!$B:$B,Multiples!N:N),"") -> 1.0098274 | O37: =IFERROR(_xlfn.XLOOKUP($K37,Multiples!$B:$B,Multiples!O:O),"") -> 1.0136527 | P37: =IFERROR(_xlfn.XLOOKUP($K37,Multiples!$B:$B,Multiples!P:P),"") -> 0.71608815 | Q37: =IFERROR(_xlfn.XLOOKUP($K37,Multiples!$B:$B,Multiples!Q:Q),"") -> 1.4841004 | R37: =IFERROR(_xlfn.XLOOKUP($K37,Multiples!$B:$B,Multiples!R:R),"") -> 2.0674539 | U37: Major Holders | W37: 113.63
K38: Current Ratio | N38: =IFERROR(_xlfn.XLOOKUP($K38,Multiples!$B:$B,Multiples!N:N),"") -> 1.5676256 | O38: =IFERROR(_xlfn.XLOOKUP($K38,Multiples!$B:$B,Multiples!O:O),"") -> 1.5424019 | P38: =IFERROR(_xlfn.XLOOKUP($K38,Multiples!$B:$B,Multiples!P:P),"") -> 1.3268659 | Q38: =IFERROR(_xlfn.XLOOKUP($K38,Multiples!$B:$B,Multiples!Q:Q),"") -> 2.0178625 | R38: =IFERROR(_xlfn.XLOOKUP($K38,Multiples!$B:$B,Multiples!R:R),"") -> 2.0178625 | U38: Blackrock Inc. | V38: 0.0891
U39: Vanguard Group Inc | V39: 0.0846
D40: Opportunities | G40: Threats | K40: Cash Flow Ratios | N40: 2022 | O40: =+N40+1 -> 2023 | P40: =+O40+1 -> 2024 | Q40: =+P40+1 -> 2025 | R40: =+Q40+1 -> 2026 | U40: State Street Corporation | V40: 0.0457
D41: The era of technology; Custom chips and emerging markets(drones, automatic cars...); | G41: Intensifying Competition and Chinese products; The level of the product's prices which can benefit competitors with lower prices. | K41: Cash Conversion Cycle | N41: =IFERROR(_xlfn.XLOOKUP($K41,Multiples!$B:$B,Multiples!N:N),"") -> 101.76231 | O41: =IFERROR(_xlfn.XLOOKUP($K41,Multiples!$B:$B,Multiples!O:O),"") -> 90.060609 | P41: =IFERROR(_xlfn.XLOOKUP($K41,Multiples!$B:$B,Multiples!P:P),"") -> 62.118733 | Q41: =IFERROR(_xlfn.XLOOKUP($K41,Multiples!$B:$B,Multiples!Q:Q),"") -> 19.966555 | R41: =IFERROR(_xlfn.XLOOKUP($K41,Multiples!$B:$B,Multiples!R:R),"") -> 30.481231 | U41: Morgan Stanley | V41: 0.0242
K42: Net Income / Op Cash Flow | N42: =IFERROR(_xlfn.XLOOKUP($K42,Multiples!$B:$B,Multiples!N:N),"") -> 0.18162379 | O42: =IFERROR(_xlfn.XLOOKUP($K42,Multiples!$B:$B,Multiples!O:O),"") -> 0.16537355 | P42: =IFERROR(_xlfn.XLOOKUP($K42,Multiples!$B:$B,Multiples!P:P),"") -> -1.5668436 | Q42: =IFERROR(_xlfn.XLOOKUP($K42,Multiples!$B:$B,Multiples!Q:Q),"") -> -1.1959458 | R42: =IFERROR(_xlfn.XLOOKUP($K42,Multiples!$B:$B,Multiples!R:R),"") -> -0.26496173 | U42: Geode Capital Management, LLC | V42: 0.0219
K43: Chg in Cash / Op Cash Flow | N43: =IFERROR(_xlfn.XLOOKUP($K43,Multiples!$B:$B,Multiples!N:N),"") -> 0.4093177 | O43: =IFERROR(_xlfn.XLOOKUP($K43,Multiples!$B:$B,Multiples!O:O),"") -> -0.35437189 | P43: =IFERROR(_xlfn.XLOOKUP($K43,Multiples!$B:$B,Multiples!P:P),"") -> 0.14116795 | Q43: =IFERROR(_xlfn.XLOOKUP($K43,Multiples!$B:$B,Multiples!Q:Q),"") -> 3.2384187 | R43: =IFERROR(_xlfn.XLOOKUP($K43,Multiples!$B:$B,Multiples!R:R),"") -> 1.9460278 | U43: Primecap Management Company | V43: 0.0177
U44: UBS AM | V44: 0.0145
D45: Revenue by Region | G45: Revenue by Segment | K45: Leverage Ratios | N45: 2022 | O45: =+N45+1 -> 2023 | P45: =+O45+1 -> 2024 | Q45: =+P45+1 -> 2025 | R45: =+Q45+1 -> 2026 | U45: NORGES BANK | V45: 0.0143
K46: Total Debt / Equity | N46: =IFERROR(_xlfn.XLOOKUP($K46,Multiples!$B:$B,Multiples!N:N),"") -> 406.99611 | O46: =IFERROR(_xlfn.XLOOKUP($K46,Multiples!$B:$B,Multiples!O:O),"") -> 431.12809 | P46: =IFERROR(_xlfn.XLOOKUP($K46,Multiples!$B:$B,Multiples!P:P),"") -> 445.02628 | Q46: =IFERROR(_xlfn.XLOOKUP($K46,Multiples!$B:$B,Multiples!Q:Q),"") -> -1.3078844e-14 | R46: =IFERROR(_xlfn.XLOOKUP($K46,Multiples!$B:$B,Multiples!R:R),"") -> -1.8149291e-14 | U46: Northern Trust Corporation | V46: 0.0105
K47: Total Debt / Capital | N47: =IFERROR(_xlfn.XLOOKUP($K47,Multiples!$B:$B,Multiples!N:N),"") -> 0.997549 | O47: =IFERROR(_xlfn.XLOOKUP($K47,Multiples!$B:$B,Multiples!O:O),"") -> 0.99768587 | P47: =IFERROR(_xlfn.XLOOKUP($K47,Multiples!$B:$B,Multiples!P:P),"") -> 0.99775798 | Q47: =IFERROR(_xlfn.XLOOKUP($K47,Multiples!$B:$B,Multiples!Q:Q),"") -> -1.3078844e-14 | R47: =IFERROR(_xlfn.XLOOKUP($K47,Multiples!$B:$B,Multiples!R:R),"") -> -1.8149291e-14 | U47: Invesco Ltd. | V47: 0.0099
K48: Total Liabilities / Total Assets | N48: =IFERROR(_xlfn.XLOOKUP($K48,Multiples!$B:$B,Multiples!N:N),"") -> 0.43281549 | O48: =IFERROR(_xlfn.XLOOKUP($K48,Multiples!$B:$B,Multiples!O:O),"") -> 0.42598605 | P48: =IFERROR(_xlfn.XLOOKUP($K48,Multiples!$B:$B,Multiples!P:P),"") -> 0.4654452 | Q48: =IFERROR(_xlfn.XLOOKUP($K48,Multiples!$B:$B,Multiples!Q:Q),"") -> -3.7846661e-15 | R48: =IFERROR(_xlfn.XLOOKUP($K48,Multiples!$B:$B,Multiples!R:R),"") -> -5.2519173e-15
K49: Total Debt / EBITDA | N49: =IFERROR(_xlfn.XLOOKUP($K49,Multiples!$B:$B,Multiples!N:N),"") -> 2.9174127 | O49: =IFERROR(_xlfn.XLOOKUP($K49,Multiples!$B:$B,Multiples!O:O),"") -> 5.0009494 | P49: =IFERROR(_xlfn.XLOOKUP($K49,Multiples!$B:$B,Multiples!P:P),"") -> 7.8492024 | Q49: =IFERROR(_xlfn.XLOOKUP($K49,Multiples!$B:$B,Multiples!Q:Q),"") -> -6.0279746 | R49: =IFERROR(_xlfn.XLOOKUP($K49,Multiples!$B:$B,Multiples!R:R),"") -> -28.958234 | U49: Board of Directors
K50: Total Debt / (EBITDA - Capex) | N50: =IFERROR(_xlfn.XLOOKUP($K50,Multiples!$B:$B,Multiples!N:N),"") -> -3.9504746 | O50: =IFERROR(_xlfn.XLOOKUP($K50,Multiples!$B:$B,Multiples!O:O),"") -> -2.9138906 | P50: =IFERROR(_xlfn.XLOOKUP($K50,Multiples!$B:$B,Multiples!P:P),"") -> -2.5983657 | Q50: =IFERROR(_xlfn.XLOOKUP($K50,Multiples!$B:$B,Multiples!Q:Q),"") -> -4.3013187 | R50: =IFERROR(_xlfn.XLOOKUP($K50,Multiples!$B:$B,Multiples!R:R),"") -> -11.452067 | U50: Lip-Bu Tan (CEO); Frank D. Yeary (Chair of the Board); Gregory D. Smith (Independent Director); Stacy Smith (Independent Director); Andrea Goldsmith (Independent Director); James J. Goetz (Independent Director); Alyssa Henry (Independent Director); Dr. Omar Ishrak (Independent Director); Tsu-Jae King Liu (Independent Director); Risa Lavizzo-Mourey (Independent Director); Eric Meurice (Independent Director); Steve Sanghi (Independent Director).
K51: Net Debt / EBITDA | N51: =IFERROR(_xlfn.XLOOKUP($K50,Multiples!$B:$B,Multiples!N:N),"") -> -3.9504746 | O51: =IFERROR(_xlfn.XLOOKUP($K50,Multiples!$B:$B,Multiples!O:O),"") -> -2.9138906 | P51: =IFERROR(_xlfn.XLOOKUP($K50,Multiples!$B:$B,Multiples!P:P),"") -> -2.5983657 | Q51: =IFERROR(_xlfn.XLOOKUP($K50,Multiples!$B:$B,Multiples!Q:Q),"") -> -4.3013187 | R51: =IFERROR(_xlfn.XLOOKUP($K50,Multiples!$B:$B,Multiples!R:R),"") -> -11.452067
K53: Solvency Ratios | N53: 2022 | O53: =+N53+1 -> 2023 | P53: =+O53+1 -> 2024 | Q53: =+P53+1 -> 2025 | R53: =+Q53+1 -> 2026
K54: EBIT / Interest Expense | N54: =IFERROR(_xlfn.XLOOKUP($K54,Multiples!$B:$B,Multiples!N:N),"") -> 2.7701613 | O54: =IFERROR(_xlfn.XLOOKUP($K54,Multiples!$B:$B,Multiples!O:O),"") -> -0.13895216 | P54: =IFERROR(_xlfn.XLOOKUP($K54,Multiples!$B:$B,Multiples!P:P),"") -> -5.245648 | Q54: =IFERROR(_xlfn.XLOOKUP($K54,Multiples!$B:$B,Multiples!Q:Q),"") -> N/A | R54: =IFERROR(_xlfn.XLOOKUP($K54,Multiples!$B:$B,Multiples!R:R),"") -> N/A
K55: EBITDA / Interest Expense | N55: =IFERROR(_xlfn.XLOOKUP($K55,Multiples!$B:$B,Multiples!N:N),"") -> 29.050403 | O55: =IFERROR(_xlfn.XLOOKUP($K55,Multiples!$B:$B,Multiples!O:O),"") -> 10.797267 | P55: =IFERROR(_xlfn.XLOOKUP($K55,Multiples!$B:$B,Multiples!P:P),"") -> 5.7591876 | Q55: =IFERROR(_xlfn.XLOOKUP($K55,Multiples!$B:$B,Multiples!Q:Q),"") -> N/A | R55: =IFERROR(_xlfn.XLOOKUP($K55,Multiples!$B:$B,Multiples!R:R),"") -> N/A
K56: (EBITDA - Capex) / Interest Expense | N56: =IFERROR(_xlfn.XLOOKUP($K56,Multiples!$B:$B,Multiples!N:N),"") -> 79.554435 | O56: =IFERROR(_xlfn.XLOOKUP($K56,Multiples!$B:$B,Multiples!O:O),"") -> 40.125285 | P56: =IFERROR(_xlfn.XLOOKUP($K56,Multiples!$B:$B,Multiples!P:P),"") -> 28.915861 | Q56: =IFERROR(_xlfn.XLOOKUP($K56,Multiples!$B:$B,Multiples!Q:Q),"") -> N/A | R56: =IFERROR(_xlfn.XLOOKUP($K56,Multiples!$B:$B,Multiples!R:R),"") -> N/A
D58: Debt Schedule | K58: Stock Performance
U60: ESG Traffic Light
U61: LSEG ESG Score | V61: =ESG!C14 -> 88
U62: E-Score | V62: =ESG!C15 -> 89
U63: S-Score | V63: =ESG!C16 -> 88
U64: G-Score | V64: =ESG!C17 -> 88
U65: S&P Global ESG Score | V65: =ESG!C18 -> 60
U66: Environmental | V66: =ESG!C19 -> 61
U67: Social | V67: =ESG!C20 -> 59
U68: Governance & Economic | V68: =ESG!C21 -> 60
U69: Sustainalytics | V69: =ESG!C22 -> 19.2
U70: ISS ESG Corporate Rating | V70: =ESG!C23 -> ?
U71: SDG Impact Rating | V71: =ESG!C24 -> ?
U72: Governance Quality Score | V72: =ESG!C25 -> ?
U73: MSCI ESG Ratings | V73: =ESG!C26 -> AA
U75: Disclaimer: This material has been prepared solely for educational and informational purposes, based on information available to the general public and from sources considered reliable. This research is part of the activities of the Lisbon Investment Society (LIS). It does not constitute, and should not be interpreted as, investment advice, financial advice, or a recommendation to buy or sell any financial instruments. The views expressed are those of the authors and do not necessarily reflect the official position of LIS. The authors assume no responsibility for the accuracy of the information provided, neither should anything contained herein be taken as an indication that any result will be achieved. Investors should conduct their own research and consult with qualified financial advisors before making any investment decisions.
D80: Extra Notes

Sheet Segments
B2: Segments
B4: Regions | D4: Weight | E4: 2020 | F4: =+E4+1 -> 2021 | G4: =+F4+1 -> 2022 | H4: =+G4+1 -> 2023 | I4: =+H4+1 -> 2024 | J4: ="CAGR "&$G$4&" - "&$I$4 -> CAGR 2022 - 2024 | K4: 2021 | L4: =+K4+1 -> 2022 | M4: =+L4+1 -> 2023 | N4: =+M4+1 -> 2024
B6: China | D6: =IFERROR(I6/SUM($I$6:$I$10),"") -> 0.2924992 | E6: 20257 | F6: 22961 | G6: 17125 | H6: 14854 | I6: 15532 | J6: =IFERROR((I6/G6)^(1/COUNT($G$4:$I$4))-1,"") -> -0.032021747 | K6: =IFERROR((F6-E6)/E6,"") -> 0.13348472 | L6: =IFERROR((G6-F6)/F6,"") -> -0.25417011 | M6: =IFERROR((H6-G6)/G6,"") -> -0.13261314 | N6: =IFERROR((I6-H6)/H6,"") -> 0.045644271
B7: United States | D7: =IFERROR(I7/SUM($I$6:$I$10),"") -> 0.24470349 | E7: 17845 | F7: 18096 | G7: 16529 | H7: 13958 | I7: 12994 | J7: =IFERROR((I7/G7)^(1/COUNT($G$4:$I$4))-1,"") -> -0.077077088 | K7: =IFERROR((F7-E7)/E7,"") -> 0.014065565 | L7: =IFERROR((G7-F7)/F7,"") -> -0.086593722 | M7: =IFERROR((H7-G7)/G7,"") -> -0.1555448 | N7: =IFERROR((I7-H7)/H7,"") -> -0.069064336
B8: Singapore | D8: =IFERROR(I8/SUM($I$6:$I$10),"") -> 0.19184196 | E8: 16573 | F8: 14322 | G8: 9664 | H8: 8602 | I8: 10187 | J8: =IFERROR((I8/E8)^(1/COUNT($E$4:$I$4))-1,"") -> -0.0927457 | K8: =IFERROR((F8-E8)/E8,"") -> -0.13582333 | L8: =IFERROR((G8-F8)/F8,"") -> -0.32523391 | M8: =IFERROR((H8-G8)/G8,"") -> -0.10989238 | N8: =IFERROR((I8-H8)/H8,"") -> 0.18425947
B9: Taiwan | D9: =IFERROR(I9/SUM($I$6:$I$10),"") -> 0.14696522 | E9: 11605 | F9: 11418 | G9: 8287 | H9: 6867 | I9: 7804 | J9: =IFERROR((I9/E9)^(1/COUNT($E$4:$I$4))-1,"") -> -0.076292599 | K9: =IFERROR((F9-E9)/E9,"") -> -0.016113744 | L9: =IFERROR((G9-F9)/F9,"") -> -0.27421615 | M9: =IFERROR((H9-G9)/G9,"") -> -0.17135272 | N9: =IFERROR((I9-H9)/H9,"") -> 0.13644969
B10: Other Regions | D10: =IFERROR(I10/SUM($I$6:$I$10),"") -> 0.12399013 | E10: 11587 | F10: 12227 | G10: 11449 | H10: 9947 | I10: 6584 | J10: =IFERROR((I10/E10)^(1/COUNT($E$4:$I$4))-1,"") -> -0.10689245 | K10: =IFERROR((F10-E10)/E10,"") -> 0.055234314 | L10: =IFERROR((G10-F10)/F10,"") -> -0.063629672 | M10: =IFERROR((H10-G10)/G10,"") -> -0.1311905 | N10: =IFERROR((I10-H10)/H10,"") -> -0.33809189
B11: Total | D11: =SUM(D6:D10) -> 1 | E11: =SUM(E6:E10) -> 77867 | F11: =SUM(F6:F10) -> 79024 | G11: =SUM(G6:G10) -> 63054 | H11: =SUM(H6:H10) -> 54228 | I11: =SUM(I6:I10) -> 53101 | J11: =IFERROR((I11/G11)^(1/COUNT($G$4:$I$4))-1,"") -> -0.055656448 | K11: =IFERROR(F11-E11/E11,"") -> 79023 | L11: =IFERROR(G11-F11/F11,"") -> 63053 | M11: =IFERROR((H11-G11)/G11,"") -> -0.13997526 | N11: =IFERROR((I11-H11)/H11,"") -> -0.020782622
B13: Segments | D13: Weight | E13: 2020 | F13: =+E13+1 -> 2021 | G13: =+F13+1 -> 2022 | H13: =+G13+1 -> 2023 | I13: =+H13+1 -> 2024 | J13: ="CAGR "&$E$4&" - "&$I$4 -> CAGR 2020 - 2024 | K13: 2021 | L13: =+K13+1 -> 2022 | M13: =+L13+1 -> 2023 | N13: =+M13+1 -> 2024
B15: CCG | D15: =IFERROR(I15/I22,"") -> 0.5704224 | E15: 40535 | F15: 41067 | G15: 31773 | H15: 29258 | I15: 30290 | J15: =IFERROR((I15/E15)^(1/COUNT($E$4:$I$4))-1,"") -> -0.056604459 | K15: =IFERROR((F15-E15)/E15,"") -> 0.01312446 | L15: =IFERROR((G15-F15)/F15,"") -> -0.2263131 | M15: =IFERROR((H15-G15)/G15,"") -> -0.079155258 | N15: =IFERROR((I15-H15)/H15,"") -> 0.035272404
B16: DCAI | D16: =IFERROR(I16/I22,"") -> 0.24137022 | E16: 23413 | F16: 22691 | G16: 16856 | H16: 12635 | I16: 12817 | J16: =IFERROR((I16/E16)^(1/COUNT($E$4:$I$4))-1,"") -> -0.11352628 | K16: =IFERROR((F16-E16)/E16,"") -> -0.030837569 | L16: =IFERROR((G16-F16)/F16,"") -> -0.25715041 | M16: =IFERROR((H16-G16)/G16,"") -> -0.25041528 | N16: =IFERROR((I16-H16)/H16,"") -> 0.014404432
B17: NEX | D17: =IFERROR(I17/SUM($I$15:$I$21),"") -> 0.11001676 | E17: 7132 | F17: 7976 | G17: 8409 | H17: 5774 | I17: 5842 | J17: =IFERROR((I17/E17)^(1/COUNT($E$4:$I$4))-1,"") -> -0.039118032 | K17: =IFERROR((F17-E17)/E17,"") -> 0.11833988 | L17: =IFERROR((G17-F17)/F17,"") -> 0.054287864 | M17: =IFERROR((H17-G17)/G17,"") -> -0.31335474 | N17: =IFERROR((I17-H17)/H17,"") -> 0.011776931
B18: Intel Foundry | D18: =IFERROR(I18/SUM($I$15:$I$21),"") -> 0.33037043 | E18: 715 | F18: 786 | G18: 27491 | H18: 18910 | I18: 17543 | J18: =IFERROR((I18/E18)^(1/COUNT($E$4:$I$4))-1,"") -> 0.89652933 | K18: =IFERROR((F18-E18)/E18,"") -> 0.099300699 | L18: =IFERROR((G18-F18)/F18,"") -> 33.975827 | M18: =IFERROR((H18-G18)/G18,"") -> -0.31213852 | N18: =IFERROR((I18-H18)/H18,"") -> -0.072289794
B19: All Other | D19: =IFERROR(I19/SUM($I$15:$I$21),"") -> 0.07201371 | E19: 6709 | F19: 7179 | G19: 5530 | H19: 5608 | I19: 3824 | J19: =IFERROR((I19/E19)^(1/COUNT($E$4:$I$4))-1,"") -> -0.10634062 | K19: =IFERROR((F19-E19)/E19,"") -> 0.07005515 | L19: =IFERROR((G19-F19)/F19,"") -> -0.22969773 | M19: =IFERROR((H19-G19)/G19,"") -> 0.014104882 | N19: =IFERROR((I19-H19)/H19,"") -> -0.31811698
B20: Corporate Unallocated | E20: 0 | F20: 0 | G20: 0 | H20: 0 | I20: 0 | J20: =IFERROR((I20/E20)^(1/COUNT($E$4:$I$4))-1,"") | K20: =IFERROR((F20-E20)/E20,"") | L20: =IFERROR((G20-F20)/F20,"") | M20: =IFERROR((H20-G20)/G20,"") | N20: =IFERROR((I20-H20)/H20,"")
B21: Intersegment Eliminations | D21: =IFERROR(I21/SUM($I$15:$I$21),"") -> -0.32419352 | E21: -637 | F21: -675 | G21: -27005 | H21: -17957 | I21: -17215 | J21: =IFERROR((I21/E21)^(1/COUNT($E$4:$I$4))-1,"") -> 0.93354159 | K21: =IFERROR((F21-E21)/E21,"") -> 0.059654631 | L21: =IFERROR((G21-F21)/F21,"") -> 39.007407 | M21: =IFERROR((H21-G21)/G21,"") -> -0.33504906 | N21: =IFERROR((I21-H21)/H21,"") -> -0.041320933
B22: Total | D22: =SUM(D15:D21) -> 1 | E22: =SUM(E15:E21) -> 77867 | F22: =SUM(F15:F21) -> 79024 | G22: =SUM(G15:G21) -> 63054 | H22: =SUM(H15:H21) -> 54228 | I22: =SUM(I15:I21) -> 53101 | J22: =IFERROR((I22/E22)^(1/COUNT($E$4:$I$4))-1,"") -> -0.073703866 | K22: =IFERROR((F22-E22)/E22,"") -> 0.014858669 | L22: =IFERROR((G22-F22)/F22,"") -> -0.2020905 | M22: =IFERROR((H22-G22)/G22,"") -> -0.13997526 | N22: =IFERROR((I22-H22)/H22,"") -> -0.020782622
B24: Categories | D24: Description | J24: Graphs
B26: CCG | D26: Focuses on processors, chipsets, and other components for consumer and business PCs — laptops, desktops, and tablets. Core products include Intel® Core™ processors (i3, i5, i7, i9).
B27: DCAI | D27: Serves enterprise, cloud, and government markets with high-performance computing and AI solutions. Includes Intel® Xeon® CPUs and AI accelerators (e.g., Habana® Gaudi®).
B28: NEX | D28: Provides infrastructure for 5G networks, edge computing, and IoT. Supports telco and industrial customers with networking silicon and edge hardware/software.
B29: Intel Foundry | D29: Intel's internal and external wafer fabrication business. Manufactures chips for Intel and third-party customers under the IDM 2.0 strategy. Includes Intel Foundry Services (IFS).
B30: All Other | D30: Includes smaller businesses like Mobileye (autonomous driving), Altera (FPGAs), and early-stage ventures.
B31: Corporate Unallocated | D31: Overhead costs, R&D not tied to specific segments, and restructuring charges.
B32: Intersegment Eliminations | D32: Internal sales between Intel segments (e.g., Foundry services provided to CCG or DCAI).
B33: =IF(B18=0,"",B18) -> Intel Foundry
B34: =IF(B19=0,"",B19) -> All Other
B36: Products | D36: Weight | E36: 2020 | F36: =+E36+1 -> 2021 | G36: =+F36+1 -> 2022 | H36: =+G36+1 -> 2023 | I36: =+H36+1 -> 2024 | J36: =I36+1 -> 2025 | K36: =+J36+1 -> 2026 | L36: =+K36+1 -> 2027 | M36: =+L36+1 -> 2028 | N36: =+M36+1 -> 2029 | O36: =+N36+1 -> 2030 | P36: =+O36+1 -> 2031 | Q36: =+P36+1 -> 2032 | R36: =+Q36+1 -> 2033 | S36: =+R36+1 -> 2034
B38: =B15 -> CCG | D38: =IFERROR(I38/$I$11,"") -> 0.5704224 | E38: =E15 -> 40535 | F38: =F15 -> 41067 | G38: =G15 -> 31773 | H38: =H15 -> 29258 | I38: =I15 -> 30290 | J38: =DCF!H17 -> 31804.5 | K38: =DCF!I17 -> 34030.815 | L38: =DCF!J17 -> 36412.972 | M38: =DCF!K17 -> 38961.88 | N38: =DCF!L17 -> 41689.212 | O38: =DCF!M17 -> 44607.457 | P38: =DCF!N17 -> 46391.755 | Q38: =DCF!O17 -> 48247.425 | ... S38: =DCF!Q17 -> 52184.415
B39: =B16 -> DCAI | D39: =IFERROR(I39/$I$11,"") -> 0.24137022 | E39: =E16 -> 23413 | F39: =F16 -> 22691 | G39: =G16 -> 16856 | H39: =H16 -> 12635 | I39: =I16 -> 12817 | J39: =DCF!H20 -> 11535.3 | K39: =DCF!I20 -> 10958.535 | L39: =DCF!J20 -> 10410.608 | M39: =DCF!K20 -> 9890.0778 | N39: =DCF!L20 -> 9395.5739 | O39: =DCF!M20 -> 9583.4854 | P39: =DCF!N20 -> 9775.1551 | Q39: =DCF!O20 -> 9970.6582 | ... S39: =DCF!Q20 -> 10373.473
B41: NEX | D41: =IFERROR(I41/$I$11,"") -> 0.11001676 | E41: =E17 -> 7132 | F41: =F17 -> 7976 | G41: =G17 -> 8409 | H41: =H17 -> 5774 | I41: =I17 -> 5842 | J41: =DCF!H23 -> 5900.42 | K41: =DCF!I23 -> 6018.4284 | L41: =DCF!J23 -> 6138.797 | M41: =DCF!K23 -> 6261.5729 | N41: =DCF!L23 -> 6386.8044 | O41: =DCF!M23 -> 6514.5405 | P41: =DCF!N23 -> 6644.8313 | Q41: =DCF!O23 -> 6777.7279 | ... S41: =DCF!Q23 -> 7051.5481
F45: =IFERROR((F41-E41)/E41,"") -> 0.11833988 | G45: =IFERROR((G41-F41)/F41,"") -> 0.054287864 | H45: =IFERROR((H41-G41)/G41,"") -> -0.31335474 | I45: =IFERROR((I41-H41)/H41,"") -> 0.011776931
B46: Product 3 | D46: =IFERROR(I46/$I$11,"") -> 0 | J46: =I46*(1+J47) -> 0 | K46: =J46*(1+K47) -> 0 | L46: =K46*(1+L47) -> 0 | M46: =L46*(1+M47) -> 0 | N46: =M46*(1+N47) -> 0 | O46: =N46*(1+O47) -> 0 | P46: =O46*(1+P47) -> 0 | Q46: =P46*(1+Q47) -> 0 | ... S46: =R46*(1+S47) -> 0
F47: =IFERROR(F46-E46/E46,"") | G47: =IFERROR(G46-F46/F46,"") | H47: =IFERROR(H46-G46/G46,"") | I47: =IFERROR(I46-H46/H46,"")
B48: Product 4 | D48: =IFERROR(I48/$I$11,"") -> 0 | J48: =I48*(1+J49) -> 0 | K48: =J48*(1+K49) -> 0 | L48: =K48*(1+L49) -> 0 | M48: =L48*(1+M49) -> 0 | N48: =M48*(1+N49) -> 0 | O48: =N48*(1+O49) -> 0 | P48: =O48*(1+P49) -> 0 | Q48: =P48*(1+Q49) -> 0 | ... S48: =R48*(1+S49) -> 0
F49: =IFERROR(F48-E48/E48,"") | G49: =IFERROR(G48-F48/F48,"") | H49: =IFERROR(H48-G48/G48,"") | I49: =IFERROR(I48-H48/H48,"")
B50: Product 5 | D50: =IFERROR(I50/$I$11,"") -> 0 | J50: =I50*(1+J51) -> 0 | K50: =J50*(1+K51) -> 0 | L50: =K50*(1+L51) -> 0 | M50: =L50*(1+M51) -> 0 | N50: =M50*(1+N51) -> 0 | O50: =N50*(1+O51) -> 0 | P50: =O50*(1+P51) -> 0 | Q50: =P50*(1+Q51) -> 0 | ... S50: =R50*(1+S51) -> 0
F51: =IFERROR(F50-E50/E50,"") | G51: =IFERROR(G50-F50/F50,"") | H51: =IFERROR(H50-G50/G50,"") | I51: =IFERROR(I50-H50/H50,"")
B52: Total | D52: =SUM(D38:D50) -> 0.92180938 | E52: =SUM(E38:E50) -> 71080 | F52: =SUM(F38:F50) -> 71734.118 | G52: =SUM(G38:G50) -> 57038.054 | H52: =SUM(H38:H50) -> 47666.687 | I52: =SUM(I38:I50) -> 48949.012 | J52: =SUM(J38:J50) -> 49240.22 | K52: =SUM(K38:K50) -> 51007.778 | ... S52: =SUM(S38:S50) -> 69609.436
B54: Company's Strategy / Extra Notes
B56: Intel’s strategy focuses on transforming its business through the IDM 2.0 model, which integrates in-house manufacturing, external foundry partnerships, and a growing Intel Foundry Services (IFS) business. The company is aiming to reclaim technology leadership by advancing five process nodes in four years, leveraging innovations like RibbonFET and PowerVia. It’s also focused on delivering competitive products across CPUs, AI, and networking, while investing in U.S. and European manufacturing to enhance supply chain resilience. Through its Smart Capital strategy, Intel is managing investments efficiently to drive long-term growth.

Sheet Industry
B2: Industry Overview
B4: Sales Growth Forecast | E4: Weight | F4: 2025 | G4: =+F4+1 -> 2026 | H4: =+G4+1 -> 2027 | I4: =+H4+1 -> 2028 | J4: =+I4+1 -> 2029 | K4: =+J4+1 -> 2030 | L4: =+K4+1 -> 2031 | M4: =+L4+1 -> 2032 | N4: =+M4+1 -> 2033 | ... P4: =+O4+1 -> 2035 | Q4: ="CAGR "&$F$4&" - "&$P$4 -> CAGR 2025 - 2035 | R4: Sources
B6: =Segments!B15 -> CCG | Q6: 0.045 | R6: Market Research Future | S6: https://www.marketresearchfuture.com/reports/client-computing-market-16110
B7: =Segments!B16 -> DCAI | Q7: 0.14 | R7: edge ai + vision | S7: https://www.edge-ai-vision.com/2025/04/ai-chips-for-data-centers-and-cloud-2025-2035-technologies-market-forecasts/
B8: =Segments!B17 -> NEX | Q8: 0.2363 | R8: =R6 -> Market Research Future | S8: https://www.marketresearchfuture.com/reports/us-intelligent-network-market-15455
B11: Weighted Average | E11: =SUM(E6:E10) -> 0 | F11: =SUMPRODUCT(F6:F10,$E$6:$E$10) -> 0 | G11: =SUMPRODUCT(G6:G10,$E$6:$E$10) -> 0 | H11: =SUMPRODUCT(H6:H10,$E$6:$E$10) -> 0 | I11: =SUMPRODUCT(I6:I10,$E$6:$E$10) -> 0 | J11: =SUMPRODUCT(J6:J10,$E$6:$E$10) -> 0 | K11: =SUMPRODUCT(K6:K10,$E$6:$E$10) -> 0 | L11: =SUMPRODUCT(L6:L10,$E$6:$E$10) -> 0 | M11: =SUMPRODUCT(M6:M10,$E$6:$E$10) -> 0 | ... P11: =SUMPRODUCT(P6:P10,$E$6:$E$10) -> 0 | Q11: =IFERROR(((1+F11)*(1+G11)*(1+H11)*(1+I11)*(1+J11)*(1+K11)*(1+L11)*(1+M11)*(1+N11)*(1+O11)*(1+P11))^(1/COUNT($F$4:$P$4))-1,"") -> 0
B13: Key Drivers | E13: Description
B15: Artificial Intelligence (AI) | E15: AI is rapidly reshaping the semiconductor landscape. From cloud-based training of large models to real-time inference in AI PCs and edge devices, demand is growing for chips optimized for AI workloads. This includes GPUs, NPUs, and accelerators, all driving innovation and investment across the industry.
B16: Cloud & Edge Computing | E16: As data volumes grow, processing is shifting to both large-scale cloud data centers and local edge environments. The cloud demands high-performance chips, while edge computing requires low-power, real-time processors. This dual trend is broadening the types of chips needed and driving architectural diversity.
B17: Advanced Manufacturing Technology | E17: With traditional scaling slowing, progress now depends on innovations in process nodes and packaging. Technologies like 3nm chips, chiplets, and 3D stacking are enabling better performance and power efficiency, helping the industry continue to advance despite physical limitations.
B18: Supply Chain & Geopolitical Realignment | E18: Semiconductors are now seen as strategic assets. Trade tensions and supply disruptions have led governments to invest in domestic production. Initiatives like the CHIPS Act are pushing for localized, secure, and diversified supply chains, reshaping global manufacturing dynamics.
B20: Industry Trends | E20: Description
B22: AI Integration Across Devices | E22: AI is rapidly expanding beyond cloud infrastructure into everyday hardware. This trend is evident in the rise of AI PCs, smartphones with on-device inference, and AI-enabled edge systems. Consumers and enterprises alike are expecting smarter, faster, and more context-aware devices. As a result, chipmakers are embedding AI accelerators into CPUs and SoCs, making AI a core feature rather than an add-on.
B23: Custom and Domain-Specific Chip Design | E23: There’s growing demand for chips optimized for specific tasks—like AI training, 5G networking, or autonomous driving. Major tech companies are increasingly designing custom silicon to gain performance advantages and efficiency. This trend is reshaping the competitive landscape, as traditional chipmakers now compete not only with each other but also with their largest customers.
B26: Market Share | E26: Headquarters | G26: Revenues | H26: (in MM of USD) | I26: Market Share
B28: {=+_FV(DCF!R4,"Name")} -> INTEL CORPORATION | E28: USA | G28: {=TRANSPOSE(Peers!D97:N97)} -> 53101 | I28: =IFERROR(G28/$G$40,"") -> 0.084708153
B29: {=+_FV(Peers!A8,"Name")} -> NVIDIA CORPORATION | E29: USA | G29: 130497 | I29: =IFERROR(G29/$G$40,"") -> 0.20817235
B30: {=+_FV(Peers!A9,"Name")} -> ADVANCED MICRO DEVICES, INC. | E30: USA | G30: 25785 | I30: =IFERROR(G30/$G$40,"") -> 0.04113293
B31: {=+_FV(Peers!A10,"Name")} -> BROADCOM INC. | E31: USA | G31: 51574 | I31: =IFERROR(G31/$G$40,"") -> 0.082272241
B32: {=+_FV(Peers!A11,"Name")} -> ASML Holding NV | E32: Netherlands | G32: 30574 | I32: =IFERROR(G32/$G$40,"") -> 0.048772473
G33: 0
G34: 0
G35: 0
G36: 0
G37: 0
G38: 0
B39: Others | E39: -- | G39: =G40-SUM(G28:G38) -> 335339 | I39: =IFERROR(G39/$G$40,"") -> 0.53494185
B40: Industry Size | E40: -- | G40: 626870 | H40: Source: Statista | I40: 1
B42: Porter's Five Forces Analysis | E42: Rating | H42: Graph
B44: Threat of New Entrants | E44: =IFERROR(AVERAGE(E45:E50),"") -> 2
B45: Economies of scale | E45: 1
B46: Product differentiation | E46: 2
B47: Capital requirements | E47: 1
B48: Access to distribution channels | E48: 2
B49: Regulations | E49: 4
B50: Switching costs | E50: 2
B51: Bargaining Power of Suppliers | E51: =IFERROR(AVERAGE(E52:E56),"") -> 2.8
B52: Number of suppliers | E52: 4
B53: Uniqueness | E53: 4
B54: Switching Costs | E54: 3
B55: Forward Integration | E55: 1
B56: Industry Importance | E56: 2
B57: Bargaining Power of Customers | E57: =IFERROR(AVERAGE(E58:E62),"") -> 3.4
B58: Number of buyers | E58: 3
B59: Purchase size | E59: 4
B60: Switching costs | E60: 3
B61: Price sensitivity | E61: 3
B62: Informed buyers | E62: 4
B63: Competitive Rivalry | E63: =IFERROR(AVERAGE(E64:E68),"") -> 4.2
B64: Number of competitors | E64: 5
B65: Industry growth | E65: 3
B66: Similarities in what's offered | E66: 4
B67: Exit barriers | E67: 4
B68: Fixed costs | E68: 5
B69: Threat of Substitutes | E69: =IFERROR(AVERAGE(E70:E74),"") -> 3.5
B70: Relative price performance | E70: 4
B71: Customer willingness to go elsewhere | E71: 3
B72: The sense that products are similar | E72: 3
B73: Availability of close substitutes | E73: 4

Sheet Peers
D3: Revenue Growth | F3: EBITDA Margin | H3: Profit Margin | J3: EV / Revenue | L3: EV / EBITDA | N3: Price / Earnings
B4: Peers | C4: Ticker | D4: =+Inputs!O4&"-"&Inputs!P4 -> 2022-2023 | E4: =+Inputs!P4&"-"&Inputs!Q4 -> 2023-2024 | F4: 2023 | G4: 2024 | H4: =+Inputs!O4&"-"&Inputs!P4 -> 2022-2023 | I4: =+Inputs!P4&"-"&Inputs!Q4 -> 2023-2024 | J4: 2023 | K4: 2024 | L4: 2023 | M4: 2024 | N4: 2023 | O4: 2024
A6: =+D91 -> #VALUE! | B6: {=IFERROR(_FV(A6,"Name"),"")} -> INTEL CORPORATION | C6: {=IFERROR(_FV(A6,"Ticker symbol",TRUE),"")} -> INTC | D6: =IFERROR(D94/D93-1,"") -> -0.13997526 | E6: =IFERROR(D97/D94-1,"") -> -0.020782622 | F6: =IFERROR(D95/D94,"") -> 0.17481744 | G6: =IFERROR(D100/D97,"") -> 0.11214478 | H6: =IFERROR(D96/D94,"") -> 0.034981928 | I6: =IFERROR(D105/D97,"") -> -0.24455283 | J6: {=IFERROR((_FV(A6,"Market cap",TRUE)/1000000+D$121-D$111)/D$94,"")} -> 3.4239933 | K6: {=IFERROR((_FV(A6,"Market cap",TRUE)/1000000+D$121-D$111)/D$97,"")} -> 3.4966631 | L6: {=+IFERROR((_FV(A6,"Market cap",TRUE)/1000000+D$121-D$111)/D$95,"")} -> 19.586108 | M6: {=IFERROR((_FV(A6,"Market cap",TRUE)/1000000+D$121-D$111)/D$100,"")} -> 31.1799 | N6: {=IFERROR((_FV(A6,"Market cap",TRUE)/1000000)/D$96,"")} -> 77.587405 | O6: {=IFERROR((_FV(A6,"Market cap",TRUE)/1000000)/D$105,"")} -> -11.333999
A8: =+E91 -> #VALUE! | B8: NVIDIA | C8: {=IFERROR(_FV(A8,"Ticker symbol",TRUE),"")} -> NVDA | D8: =+IFERROR(E94/E93-1,"") -> 1.2585453 | E8: =IFERROR(E97/E94-1,"") -> 1.1420341 | F8: =IFERROR(E95/E94,"") -> 0.83879387 | G8: =+IFERROR(E100/E97,"") -> 0.63846678 | H8: =IFERROR(E96/E94,"") -> 0.48849348 | I8: =+IFERROR(E105/E99,"") -> 0.7447526 | J8: {=+IFERROR((_FV(A8,"Market cap",TRUE)/1000000+E$121-E$111)/E$94,"")} -> 70.130372 | K8: {=IFERROR(+(_FV(A8,"Market cap",TRUE)/1000000+E$121-E$111)/E$97,"")} -> 32.740082 | L8: {=IFERROR(+(_FV(A8,"Market cap",TRUE)/1000000+E$121-E$111)/E$95,"")} -> 83.608589 | M8: {=IFERROR(+(_FV(A8,"Market cap",TRUE)/1000000+E$121-E$111)/E$100,"")} -> 51.279225 | N8: {=IFERROR(+(_FV(A8,"Market cap",TRUE)/1000000)/E$96,"")} -> 143.51779 | O8: {=IFERROR(+(_FV(A8,"Market cap",TRUE)/1000000)/E$105,"")} -> 58.604411
A9: =+F91 -> #VALUE! | B9: AMD | C9: {=IFERROR(_FV(A9,"Ticker symbol",TRUE),"")} -> AMD | D9: =IFERROR(F94/F93-1,"") -> -0.03902377 | E9: =IFERROR(+F97/F94-1,"") -> 0.13690476 | F9: =IFERROR(F95/F94,"") -> 0.21763668 | G9: =IFERROR(F100/F97,"") -> 0.19255381 | H9: =IFERROR(F96/F94,"") -> 0.037654321 | I9: =+IFERROR(F105/F97,"") -> 0.063641652 | J9: {=IFERROR(+(_FV(A9,"Market cap",TRUE)/1000000+F$121-F$111)/F$94,"")} -> 10.985103 | K9: {=IFERROR(+(_FV(A9,"Market cap",TRUE)/1000000+F$121-F$111)/F$97,"")} -> 9.6622896 | L9: {=IFERROR(+(_FV(A9,"Market cap",TRUE)/1000000+F$121-F$111)/F$95,"")} -> 50.474501 | M9: {=IFERROR(+(_FV(A9,"Market cap",TRUE)/1000000+F$121-F$111)/F$100,"")} -> 50.179685 | N9: {=IFERROR(+(_FV(A9,"Market cap",TRUE)/1000000)/F$96,"")} -> 294.15473 | O9: {=IFERROR(+(_FV(A9,"Market cap",TRUE)/1000000)/F$105,"")} -> 153.08235
A10: =+G91 -> #VALUE! | B10: Broadcom Inc. | C10: {=IFERROR(_FV(A10,"Ticker symbol",TRUE),"")} -> AVGO | D10: =+IFERROR(G94/G93-1,"") -> 0.078788061 | E10: =IFERROR(G97/G94-1,"") -> 0.43985036 | F10: =IFERROR(G95/G94,"") -> 0.50540216 | G10: =IFERROR(G100/G97,"") -> 0.38055997 | H10: =IFERROR(G96/G94,"") -> 0.3931433 | I10: =+IFERROR(G105/G97,"") -> 0.11430178 | J10: {=IFERROR(+(_FV(A10,"Market cap",TRUE)/1000000+G$121-G$111)/G$94,"")} -> 47.327012 | K10: {=IFERROR(+(_FV(A10,"Market cap",TRUE)/1000000+G$121-G$111)/G$97,"")} -> 32.869396 | L10: {=IFERROR(+(_FV(A10,"Market cap",TRUE)/1000000+G$121-G$111)/G$95,"")} -> 93.642283 | M10: {=IFERROR(+(_FV(A10,"Market cap",TRUE)/1000000+G$121-G$111)/G$100,"")} -> 86.371134 | N10: {=IFERROR(+(_FV(A10,"Market cap",TRUE)/1000000)/G$96,"")} -> 116.33712 | O10: {=IFERROR(+(_FV(A10,"Market cap",TRUE)/1000000)/G$105,"")} -> 277.90657
A11: =+H91 -> #VALUE! | B11: ASML | C11: {=IFERROR(_FV(A11,"Ticker symbol",TRUE),"")} -> ASML | D11: =IFERROR(H94/H93-1,"") -> 0.33648715 | E11: =IFERROR(H97/H94-1,"") -> 0.02580104 | F11: =IFERROR(H95/H94,"") -> 0.3845328 | G11: =IFERROR(H100/H97,"") -> 0.41888533 | H11: =IFERROR(H96/H94,"") -> 0.29448079 | I11: =+IFERROR(H105/H102,"") -> -430.09524 | J11: {=IFERROR((_FV(A11,"Market cap",TRUE)/1000000+H$121-H$111)/H$94,"")} -> 11.285617 | K11: {=IFERROR(+(_FV(A11,"Market cap",TRUE)/1000000+H$121-H$111)/H$97,"")} -> 11.00176 | L11: {=IFERROR(+(_FV(A11,"Market cap",TRUE)/1000000+H$121-H$111)/H$95,"")} -> 29.348905 | M11: {=IFERROR(+(_FV(A11,"Market cap",TRUE)/1000000+H$121-H$111)/H$100,"")} -> 26.264371 | N11: {=IFERROR(+(_FV(A11,"Market cap",TRUE)/1000000)/H$96,"")} -> 39.240754 | O11: {=IFERROR(+(_FV(A11,"Market cap",TRUE)/1000000)/H$105,"")} -> 38.132872
A12: =+I91 -> PEER 5 | B12: {=IFERROR(_FV(A12,"Name"),"")} | C12: {=IFERROR(_FV(A12,"Ticker symbol",TRUE),"")} | D12: =+IFERROR(I94/I93-1,"") | E12: =IFERROR(I97/I94-1,"") | F12: =IFERROR(I95/I94,"") | G12: =IFERROR(I100/I97,"") | H12: =IFERROR(I96/I94,"") | I12: =+IFERROR(I105/I97,"") | J12: {=IFERROR((_FV(A12,"Market cap",TRUE)/1000000+I$121-I$111)/I$94,"")} | K12: {=IFERROR(+(_FV(A12,"Market cap",TRUE)/1000000+I$121-I$111)/I$97,"")} | L12: {=IFERROR(+(_FV(A12,"Market cap",TRUE)/1000000+I$121-I$111)/I$95,"")} | M12: {=IFERROR(+(_FV(A12,"Market cap",TRUE)/1000000+I$121-I$111)/I$100,"")} | N12: {=IFERROR(+(_FV(A12,"Market cap",TRUE)/1000000)/I$96,"")} | O12: {=IFERROR(+(_FV(A12,"Market cap",TRUE)/1000000)/I$105,"")}
A13: =+J91 -> PEER 6 | B13: {=IFERROR(_FV(A13,"Name"),"")} | C13: {=IFERROR(_FV(A13,"Ticker symbol",TRUE),"")} | D13: =IFERROR(J94/J93-1,"") | E13: =IFERROR(J97/J94-1,"") | F13: =IFERROR(J95/J94,"") | G13: =IFERROR(J100/J97,"") | H13: =IFERROR(J96/J94,"") | I13: =+IFERROR(J105/J97,"") | J13: {=IFERROR(+(_FV(A13,"Market cap",TRUE)/1000000+J$121-J$111)/J$94,"")} | K13: {=IFERROR(+(_FV(A13,"Market cap",TRUE)/1000000+J$121-J$111)/J$97,"")} | L13: {=IFERROR(+(_FV(A13,"Market cap",TRUE)/1000000+J$121-J$111)/J$95,"")} | M13: {=IFERROR(+(_FV(A13,"Market cap",TRUE)/1000000+J$121-J$111)/J$100,"")} | N13: {=IFERROR(+(_FV(A13,"Market cap",TRUE)/1000000)/J$96,"")} | O13: {=IFERROR(+(_FV(A13,"Market cap",TRUE)/1000000)/J$105,"")}
A14: =+K91 -> PEER 7 | B14: {=IFERROR(_FV(A14,"Name"),"")} | C14: {=IFERROR(_FV(A14,"Ticker symbol",TRUE),"")} | D14: =IFERROR(K94/K93-1,"") | E14: =IFERROR(K97/K94-1,"") | F14: =+IFERROR(K95/K94,"") | G14: =IFERROR(K100/K97,"") | H14: =IFERROR(K96/K94,"") | I14: =+IFERROR(K105/K97,"") | J14: {=IFERROR((_FV(A14,"Market cap",TRUE)/1000000+D$121-K$111)/K$94,"")} | K14: {=IFERROR(+(_FV(A14,"Market cap",TRUE)/1000000+D$121-K$111)/K$97,"")} | L14: {=IFERROR(+(_FV(A14,"Market cap",TRUE)/1000000+D$121-K$111)/K$95,"")} | M14: {=IFERROR(+(_FV(A14,"Market cap",TRUE)/1000000+D$121-K$111)/K$100,"")} | N14: {=IFERROR(+(_FV(A14,"Market cap",TRUE)/1000000)/K$96,"")} | O14: {=IFERROR(+(_FV(A14,"Market cap",TRUE)/1000000)/K$105,"")}
A15: =+L91 -> PEER 8 | B15: {=IFERROR(_FV(A15,"Name"),"")} | C15: {=IFERROR(_FV(A15,"Ticker symbol",TRUE),"")} | D15: =+IFERROR(L94/L93,"") | E15: =IFERROR(L97/L94,"") | F15: =IFERROR(L95/L94,"") | G15: =IFERROR(L100/L97,"") | H15: =IFERROR(L96/L94,"") | I15: =+IFERROR(L105/L97,"") | J15: {=IFERROR(+(_FV(A15,"Market cap",TRUE)/1000000+L$121-L$111)/L$94,"")} | K15: {=IFERROR(+(_FV(A15,"Market cap",TRUE)/1000000+L$121-L$111)/L$97,"")} | L15: {=IFERROR(+(_FV(A15,"Market cap",TRUE)/1000000+L$121-L$111)/L$95,"")} | M15: {=IFERROR(+(_FV(A15,"Market cap",TRUE)/1000000+L$121-L$111)/L$100,"")} | N15: {=IFERROR(+(_FV(A15,"Market cap",TRUE)/1000000)/L$96,"")} | O15: {=IFERROR(+(_FV(A15,"Market cap",TRUE)/1000000)/L$105,"")}
A16: =+M91 -> PEER 9 | B16: {=IFERROR(_FV(A16,"Name"),"")} | C16: {=IFERROR(_FV(A16,"Ticker symbol",TRUE),"")} | D16: =IFERROR(M94/M93-1,"") | E16: =IFERROR(M97/M94-1,"") | F16: =IFERROR(M95/M94,"") | G16: =IFERROR(M100/M97,"") | H16: =IFERROR(M96/M94,"") | I16: =+IFERROR(M105/M97,"") | J16: {=IFERROR(+(_FV(A16,"Market cap",TRUE)/1000000+M$121-M$111)/M$94,"")} | K16: {=IFERROR(+(_FV(A16,"Market cap",TRUE)/1000000+M$121-M$111)/M$97,"")} | L16: {=IFERROR(+(_FV(A16,"Market cap",TRUE)/1000000+M$121-M$111)/M$95,"")} | M16: {=IFERROR(+(_FV(A16,"Market cap",TRUE)/1000000+M$121-M$111)/M$100,"")} | N16: {=IFERROR(+(_FV(A16,"Market cap",TRUE)/1000000)/M$96,"")} | O16: {=IFERROR(+(_FV(A16,"Market cap",TRUE)/1000000)/M$105,"")}
A17: =+N91 -> PEER 10 | B17: {=IFERROR(_FV(A17,"Name"),"")} | C17: {=+IFERROR(_FV(A17,"Ticker symbol",TRUE),"")} | D17: =IFERROR(N94/N93-1,"") | E17: =IFERROR(N97/N94-1,"") | F17: =IFERROR(N95/N94,"") | G17: =IFERROR(N100/N97,"") | H17: =IFERROR(N96/N94,"") | I17: =+IFERROR(N105/N97,"") | J17: {=IFERROR(+(_FV(A17,"Market cap",TRUE)/1000000+N$121-N$111)/N$94,"")} | K17: {=IFERROR(+(_FV(A17,"Market cap",TRUE)/1000000+N$121-N$111)/N$97,"")} | L17: {=IFERROR(+(_FV(A17,"Market cap",TRUE)/1000000+N$121-N$111)/N$95,"")} | M17: {=IFERROR(+(_FV(A17,"Market cap",TRUE)/1000000+N$121-N$111)/N$100,"")} | N17: {=IFERROR(+(_FV(A17,"Market cap",TRUE)/1000000)/N$96,"")} | O17: {=IFERROR(+(_FV(A17,"Market cap",TRUE)/1000000)/N$105,"")}
B18: Average | D18: =IFERROR(AVERAGE(D6:D17),"") -> 0.29896429 | E18: =IFERROR(AVERAGE(E6:E17),"") -> 0.34476152 | F18: =IFERROR(AVERAGE(F6:F17),"") -> 0.42423659 | G18: =IFERROR(AVERAGE(G6:G17),"") -> 0.34852214 | H18: =IFERROR(AVERAGE(H6:H17),"") -> 0.24975077 | I18: =IFERROR(AVERAGE(I6:I17),"") -> -85.883419 | J18: =IFERROR(AVERAGE(J6:J17),"") -> 28.630419 | K18: =IFERROR(AVERAGE(K6:K17),"") -> 17.954038 | ... O18: =IFERROR(AVERAGE(O6:O17),"") -> 103.27844
B19: Deviation from Average | D19: =IFERROR(+D18-D6,"") -> 0.43893955 | E19: =IFERROR(E18-E6,"") -> 0.36554414 | F19: =+IFERROR(F18-F6,"") -> 0.24941915 | G19: =IFERROR(G18-G6,"") -> 0.23637735 | H19: =IFERROR(+H6-H18,"") -> -0.21476884 | I19: =+IFERROR(I6-I18,"") -> 85.638866 | J19: =+IFERROR(J6-J18,"") -> -25.206426 | K19: =+IFERROR(K6-K18,"") -> -14.457375 | L19: =IFERROR(+L6-L18,"") -> -35.745969 | M19: =IFERROR(M6-M18,"") -> -17.874963 | N19: =IFERROR(+N6-N18,"") -> -56.580154 | O19: =IFERROR(+O6-O18,"") -> -114.61244
D21: Trading Multiple | G21: Net | H21: Preferred | I21: Non-Controlling | J21: Equity Value | M21: Implied Upside (Downside)
B22: Implied Share Price | D22: Revenue | E22: EBITDA | F22: P/E | G22: Debt | H22: Stock | I22: Interest | J22: Revenue | K22: EBITDA | L22: P/E | M22: Revenue | N22: EBITDA | O22: P/E | P22: Current Price
B24: Second Minimum | D24: =IFERROR(SMALL(K6:K17,2),"") -> 9.6622896 | E24: =IFERROR(SMALL(M6:M17,2),"") -> 31.1799 | F24: =IFERROR(SMALL(O6:O17,2),"") -> 38.132872 | G24: =-Inputs!$Q$99+Inputs!$Q$100 -> 24680 | H24: =+Inputs!$Q$101 -> 0 | I24: =+Inputs!$Q$102 -> 5762 | J24: =IFERROR(+D24*$D$97+G24+H24+I24,"") -> 543519.24 | K24: =IFERROR(E24*$D$100+G24+H24+I24,"") -> 216118.31 | L24: =IFERROR(F24*$D$105,"") -> -495193.48 | M24: {=IFERROR(+(J24/_FV($A$6,"Shares outstanding",TRUE)*1000000)/$P$24-1,"")} -> 2.6928049 | N24: {=IFERROR((+K24/_FV($A$6,"Shares outstanding",TRUE)*1000000)/$P$24-1,"")} -> 0.46836154 | O24: {=IFERROR(+(L24/_FV($A$6,"Shares outstanding",TRUE)*1000000)/$P$24-1,"")} -> -4.3644677 | P24: {=+_FV(A6,"Price")} -> 31.515
B25: Average | D25: =+IFERROR(AVERAGE(K6:K17),"") -> 17.954038 | E25: =IFERROR(+AVERAGE(M6:M17),"") -> 49.054863 | F25: =IFERROR(+AVERAGE(O6:O17),"") -> 103.27844 | G25: =-Inputs!$Q$99+Inputs!$Q$100 -> 24680 | H25: =+Inputs!$Q$101 -> 0 | I25: =+Inputs!$Q$102 -> 5762 | J25: =IFERROR(+D25*$D$97+G25+H25+I25,"") -> 983819.38 | K25: =IFERROR(E25*$D$100+G25+H25+I25,"") -> 322563.71 | L25: =IFERROR(+F25*$D$105,"") -> -1341173.8 | M25: {=IFERROR(+(J25/_FV($A$6,"Shares outstanding",TRUE)*1000000)/$P$24-1,"")} -> 5.6843136 | N25: {=IFERROR((+K25/_FV($A$6,"Shares outstanding",TRUE)*1000000)/$P$24-1,"")} -> 1.1915781 | O25: {=IFERROR(+(L25/_FV($A$6,"Shares outstanding",TRUE)*1000000)/$P$24-1,"")} -> -10.112269
B26: Median | D26: =IFERROR(MEDIAN(K6:K17),"") -> 11.00176 | E26: =IFERROR(MEDIAN(M6:M17),"") -> 50.179685 | F26: =IFERROR(MEDIAN(O6:O17),"") -> 58.604411 | G26: =-Inputs!$Q$99+Inputs!$Q$100 -> 24680 | H26: =+Inputs!$Q$101 -> 0 | I26: =+Inputs!$Q$102 -> 5762 | J26: =IFERROR(D26*$D$97+G26+H26+I26,"") -> 614646.44 | K26: =IFERROR(E26*$D$100+G26+H26+I26,"") -> 329262.03 | L26: =IFERROR(+F26*$D$105,"") -> -761036.89 | M26: {=IFERROR(+(J26/_FV($A$6,"Shares outstanding",TRUE)*1000000)/$P$24-1,"")} -> 3.1760608 | N26: {=IFERROR((+K26/_FV($A$6,"Shares outstanding",TRUE)*1000000)/$P$24-1,"")} -> 1.2370881 | O26: {=+IFERROR((L26/_FV($A$6,"Shares outstanding",TRUE)*1000000)/$P$24-1,"")} -> -6.1706739
B27: Second Maximum | D27: =IFERROR(LARGE(K6:K17,2),"") -> 32.740082 | E27: =IFERROR(LARGE(M6:M17,2),"") -> 51.279225 | F27: =IFERROR(LARGE(O6:O17,2),"") -> 153.08235 | G27: =-Inputs!$Q$99+Inputs!$Q$100 -> 24680 | H27: =+Inputs!$Q$101 -> 0 | I27: =+Inputs!$Q$102 -> 5762 | J27: =IFERROR(+D27*$D$97+G27+H27+I27,"") -> 1768973.1 | K27: =IFERROR(E27*$D$100+G27+H27+I27,"") -> 335809.79 | L27: =IFERROR(+F27*$D$105,"") -> -1987927.4 | M27: {=IFERROR(+(J27/_FV($A$6,"Shares outstanding",TRUE)*1000000)/$P$24-1,"")} -> 11.018843 | N27: {=IFERROR((+K27/_FV($A$6,"Shares outstanding",TRUE)*1000000)/$P$24-1,"")} -> 1.2815752 | O27: {=IFERROR(+(L27/_FV($A$6,"Shares outstanding",TRUE)*1000000)/$P$24-1,"")} -> -14.506473
B29: Profitability | D29: =+LEFT(B6, FIND(" ", B6 & " ") - 1) -> INTEL | E29: =+LEFT(B8, FIND(" ", B8 & " ") - 1) -> NVIDIA | F29: =+LEFT(B9, FIND(" ", B9 & " ") - 1) -> AMD | G29: =+LEFT(B10, FIND(" ", B10 & " ") - 1) -> Broadcom | H29: =+LEFT(B11, FIND(" ", B11 & " ") - 1) -> ASML | I29: =+LEFT(B12, FIND(" ", B12 & " ") - 1) | J29: =+LEFT(C12, FIND(" ", C12 & " ") - 1) | K29: =+LEFT(B14, FIND(" ", B14 & " ") - 1) | L29: =+LEFT(B15, FIND(" ", B15 & " ") - 1) | M29: =+LEFT(B16, FIND(" ", B16 & " ") - 1) | N29: =+LEFT(B17, FIND(" ", B17 & " ") - 1) | O29: Average
B31: Operating Margin | D31: =IFERROR(D101/D97,"") -> -0.10214497 | E31: =IFERROR(E101/E97,"") -> 0.62417527 | F31: =IFERROR(F101/F97,"") -> 0.073686252 | G31: =IFERROR(G101/G97,"") -> 0.30616202 | H31: =IFERROR(H101/H97,"") -> 0.35284883 | I31: =IFERROR(I101/I97,"") | J31: =IFERROR(J101/J97,"") | K31: =IFERROR(K101/K97,"") | ... N31: =IFERROR(N101/N97,"") | O31: =IFERROR(+AVERAGE(D31:N31),"") -> 0.25094548
B32: Net Income Margin | D32: =IFERROR(D105/D97,"") -> -0.24455283 | E32: =IFERROR(E105/E97,"") -> 0.55848027 | F32: =IFERROR(F105/F97,"") -> 0.063641652 | G32: =IFERROR(G105/G97,"") -> 0.11430178 | H32: =IFERROR(H105/H97,"") -> 0.2954144 | I32: =IFERROR(I105/I97,"") | J32: =IFERROR(J105/J97,"") | K32: =IFERROR(K105/K97,"") | ... N32: =IFERROR(N105/N97,"") | O32: =IFERROR(+AVERAGE(D32:N32),"") -> 0.15745705
B33: ROA (%) | D33: =IFERROR(D105/D117,"") -> -0.066091559 | E33: =IFERROR(E105/E117,"") -> 0.65304074 | F33: =IFERROR(F105/F117,"") -> 0.023704966 | G33: =IFERROR(G105/G117,"") -> 0.035588155 | H33: =IFERROR(H105/H117,"") -> 0.1858834 | I33: =IFERROR(I105/I117,"") | J33: =IFERROR(J105/J117,"") | K33: =IFERROR(K105/K117,"") | ... N33: =IFERROR(N105/N117,"") | O33: =IFERROR(+AVERAGE(D33:N33),"") -> 0.16642514
B34: Financial Cost of Debt | D34: =IFERROR(+(D102/D121)*(1-(D104/D103)),"") -> -0.011811534 | E34: =IFERROR(+(E102/E121)*(1-(E104/E103)),"") -> 0.22357173 | F34: =IFERROR(+(F102/F121)*(1-(F104/F103)),"") -> -0.043217358 | G34: =IFERROR(+(G102/G121)*(1-(G104/G103)),"") -> 0.037089748 | H34: =IFERROR(+(H102/H121)*(1-(H104/H103)),"") -> -0.0036622002 | I34: =IFERROR(+(I102/I121)*(1-(I104/I103)),"") | J34: =IFERROR(+(J102/J121)*(1-(J104/J103)),"") | K34: =IFERROR(+(K102/K121)*(1-(K104/K103)),"") | ... N34: =IFERROR(+(N102/N121)*(1-(N104/N103)),"") | O34: =IFERROR(+AVERAGE(D34:N34),"") -> 0.040394078
B35: Return on Equity (RoE) | D35: =IFERROR(+D105/D122,"") -> -0.12363851 | E35: =IFERROR(+E105/E122,"") -> 0.91872881 | F35: =IFERROR(+F105/F122,"") -> 0.02850542 | G35: =IFERROR(+G105/G122,"") -> 0.087103638 | H35: =IFERROR(+H105/H122,"") -> 0.1858834 | I35: =IFERROR(+I105/I122,"") | J35: =IFERROR(+J105/J122,"") | K35: =IFERROR(+K105/K122,"") | ... N35: =IFERROR(+N105/N122,"") | O35: =IFERROR(+AVERAGE(D35:N35),"") -> 0.21931655
B36: Return on Invested Capital (ROIC) | D36: =IFERROR(+D105/(D121+D122),"") -> -0.085561427 | E36: =IFERROR(+E105/(E121+E122),"") -> 0.81604318 | F36: =IFERROR(+F105/(F121+F122),"") -> 0.027677984 | G36: =IFERROR(+G105/(G121+G122),"") -> 0.044001403 | H36: =IFERROR(+H105/(H121+H122),"") -> 0.16952843 | I36: =IFERROR(+I105/(I121+I122),"") | J36: =IFERROR(+J105/(J121+J122),"") | K36: =IFERROR(+K105/(K121+K122),"") | ... N36: =IFERROR(+N105/(N121+N122),"") | O36: =IFERROR(+AVERAGE(D36:N36),"") -> 0.19433791
B38: Solvency | D38: =+D29 -> INTEL | E38: =+E29 -> NVIDIA | F38: =+F29 -> AMD | G38: =+G29 -> Broadcom | H38: =+H29 -> ASML | I38: =+I29 | J38: =+J29 | K38: =+K29 | ... O38: =+O29 -> Average
B40: Debt/Assets | D40: =IFERROR(D121/D117,"") -> 0.23789093 | E40: =IFERROR(E121/E117,"") -> 0.089443643 | F40: =IFERROR(F121/F117,"") -> 0.024860602 | G40: =IFERROR(G121/G117,"") -> 0.40022337 | H40: =IFERROR(H121/H117,"") -> 0.096473319 | I40: =IFERROR(I121/I117,"") | J40: =IFERROR(J121/J117,"") | K40: =IFERROR(K121/K117,"") | ... N40: =IFERROR(N121/N117,"") | O40: =IFERROR(+AVERAGE(D40:N40),"") -> 0.16977837
B41: Net Debt/EBITDA | D41: =IFERROR(+(D121-D111)/D100,"") -> 6.4639798 | E41: =IFERROR(+(E121-E111)/E100,"") -> 0.016719076 | F41: =IFERROR(+(F121-F111)/F100,"") -> -0.41611279 | G41: =IFERROR(+(G121-G111)/G100,"") -> 2.9014623 | H41: =IFERROR(+(H121-H111)/H100,"") -> -0.62842976 | I41: =IFERROR(+(I121-I111)/I100,"") | J41: =IFERROR(+(J121-J111)/J100,"") | K41: =IFERROR(+(K121-K111)/K100,"") | ... N41: =IFERROR(+(N121-N111)/N100,"") | O41: =IFERROR(+AVERAGE(D41:N41),"") -> 1.6675237
B42: Interest Coverage Ratio | D42: =IFERROR(D101/D102,"") -> 25.706161 | E42: =IFERROR(E101/E102,"") -> 31.656821 | F42: =IFERROR(F101/F102,"") -> -20.652174 | G42: =IFERROR(G101/G102,"") -> 3.9944346 | H42: =IFERROR(H101/H102,"") -> -513.71429 | I42: =IFERROR(I101/I102,"") | J42: =IFERROR(J101/J102,"") | K42: =IFERROR(K101/K102,"") | ... N42: =IFERROR(N101/N102,"") | O42: =IFERROR(+AVERAGE(D42:N42),"") -> -94.601809
B44: Liquidity | D44: =+D29 -> INTEL | E44: =+E29 -> NVIDIA | F44: =+F29 -> AMD | G44: =+G29 -> Broadcom | H44: =+H29 -> ASML | I44: =+I29 | J44: =+J29 | K44: =+K29 | ... O44: =+O29 -> Average
B46: Cash Ratio | D46: =IFERROR(D111/D119,"") -> 0.2312847 | E46: =IFERROR(E111/E119,"") -> 0.47592398 | F46: =IFERROR(F111/F119,"") -> 0.52012086 | G46: =IFERROR(G111/G119,"") -> 0.55986105 | H46: =IFERROR(H111/H119,"") -> 0.63516263 | I46: =IFERROR(I111/I119,"") | J46: =IFERROR(J111/J119,"") | K46: =IFERROR(K111/K119,"") | ... N46: =IFERROR(N111/N119,"") | O46: =IFERROR(+AVERAGE(D46:N46),"") -> 0.48447064
B47: Quick Ratio | D47: =IFERROR(+(D111+D112)/D119,"") -> 0.32880054 | E47: =IFERROR(+(E111+E112)/E119,"") -> 1.7539757 | F47: =IFERROR(+(F111+F112)/F119,"") -> 1.3705535 | G47: =IFERROR(+(G111+G112)/G119,"") -> 0.8243397 | H47: =IFERROR(+(H111+H112)/H119,"") -> 0.85846375 | I47: =IFERROR(+(I111+I112)/I119,"") | J47: =IFERROR(+(J111+J112)/J119,"") | K47: =IFERROR(+(K111+K112)/K119,"") | ... N47: =IFERROR(+(N111+N112)/N119,"") | O47: =IFERROR(+AVERAGE(D47:N47),"") -> 1.0272266
B48: Current Ratio | D48: =IFERROR(D115/D119,"") -> 1.3268659 | E48: =IFERROR(E115/E119,"") -> 4.4398515 | F48: =IFERROR(F115/F119,"") -> 2.6162615 | G48: =IFERROR(G115/G119,"") -> 1.1735641 | H48: =IFERROR(H115/H119,"") -> 1.5329304 | I48: =IFERROR(I115/I119,"") | J48: =IFERROR(J115/J119,"") | K48: =IFERROR(K115/K119,"") | ... N48: =IFERROR(N115/N119,"") | O48: =IFERROR(+AVERAGE(D48:N48),"") -> 2.2178947
B50: Activity | D50: =+D29 -> INTEL | E50: =+E29 -> NVIDIA | F50: =+F29 -> AMD | G50: =+G29 -> Broadcom | H50: =+H29 -> ASML | I50: =+I29 | J50: =+J29 | K50: =+K29 | ... O50: =+O29 -> Average
B52: Inventory Turnover | D52: =IFERROR(D98/(AVERAGE(D113:D114)),"") -> 3.065895 | E52: =IFERROR(E98/(AVERAGE(E113:E114)),"") -> 3.2510583 | F52: =IFERROR(F98/(AVERAGE(F113:F114)),"") -> 2.4023798 | G52: =IFERROR(G98/(AVERAGE(G113:G114)),"") -> 10.423729 | H52: =IFERROR(H98/(AVERAGE(H113:H114)),"") -> 1.5319468 | I52: =IFERROR(I98/(AVERAGE(I113:I114)),"") | J52: =IFERROR(J98/(AVERAGE(J113:J114)),"") | K52: =IFERROR(K98/(AVERAGE(K113:K114)),"") | ... N52: =IFERROR(N98/(AVERAGE(N113:N114)),"") | O52: =IFERROR(+AVERAGE(D52:N52),"") -> 4.1350017
B53: Acc. Receivable Turnover | D53: =IFERROR(D97/D112,"") -> 15.267683 | E53: =IFERROR(E97/E112,"") -> 5.6577932 | F53: =IFERROR(F97/F112,"") -> 4.1642442 | G53: =IFERROR(G97/G112,"") -> 11.678895 | H53: =IFERROR(H97/H112,"") -> 6.828364 | I53: =IFERROR(I97/I112,"") | J53: =IFERROR(J97/J112,"") | K53: =IFERROR(K97/K112,"") | ... N53: =IFERROR(N97/N112,"") | O53: =IFERROR(+AVERAGE(D53:N53),"") -> 8.7193958
B54: Payables Turnover | D54: =IFERROR(D98/D118,"") -> 2.8477222 | E54: =IFERROR(E98/E118,"") -> 5.1725832 | F54: =IFERROR(F98/F118,"") -> 6.0874372 | G54: =IFERROR(G98/G118,"") -> 11.471119 | H54: =IFERROR(H98/H118,"") -> 4.3200777 | I54: =IFERROR(I98/I118,"") | J54: =IFERROR(J98/J118,"") | K54: =IFERROR(K98/K118,"") | ... N54: =IFERROR(N98/N118,"") | O54: =IFERROR(+AVERAGE(D54:N54),"") -> 5.9797879
B55: Fixed Asset Turnover | D55: =IFERROR(D97/D116,"") -> 0.4899701 | E55: =IFERROR(E97/E116,"") -> 20.769855 | F55: =IFERROR(F97/F116,"") -> 14.309101 | G55: =IFERROR(G97/G116,"") -> 20.457755 | H55: =IFERROR(H97/H116,"") -> 4.4654437 | I55: =IFERROR(I97/I116,"") | J55: =IFERROR(J97/J116,"") | K55: =IFERROR(K97/K116,"") | ... N55: =IFERROR(N97/N116,"") | O55: =IFERROR(+AVERAGE(D55:N55),"") -> 12.098425
B56: Total Asset Turnover | D56: =IFERROR(D97/D117,"") -> 0.27025473 | E56: =IFERROR(E97/E117,"") -> 1.1693175 | F56: =IFERROR(F97/F117,"") -> 0.37247566 | G56: =IFERROR(G97/G117,"") -> 0.31135259 | H56: =IFERROR(H97/H117,"") -> 0.6292293 | I56: =IFERROR(I97/I117,"") | J56: =IFERROR(J97/J117,"") | K56: =IFERROR(K97/K117,"") | ... N56: =IFERROR(N97/N117,"") | O56: =IFERROR(+AVERAGE(D56:N56),"") -> 0.55052595
B57: Cash Cycle (days) | D57: =IFERROR(365/D52+365/D53-365/D54,"") -> 14.785789 | E57: =IFERROR(365/E52+365/E53-365/E54,"") -> 106.21956 | F57: =IFERROR(365/F52+365/F53-365/F54,"") -> 179.62409 | G57: =IFERROR(365/G52+365/G53-365/G54,"") -> 34.450177 | H57: =IFERROR(365/H52+365/H53-365/H54,"") -> 207.22321 | I57: =IFERROR(365/I52+365/I53-365/I54,"") | J57: =IFERROR(365/J52+365/J53-365/J54,"") | K57: =IFERROR(365/K52+365/K53-365/K54,"") | ... N57: =IFERROR(365/N52+365/N53-365/N54,"") | O57: =IFERROR(+AVERAGE(D57:N57),"") -> 108.46057
B59: Cash Flow | D59: =+D38 -> INTEL | E59: =+E38 -> NVIDIA | F59: =+F38 -> AMD | G59: =+G38 -> Broadcom | H59: =+H38 -> ASML | I59: =+I38 | J59: =+J38 | K59: =+K38 | ... O59: =+O38 -> Average
B61: Cash Flow Margin | D61: =IFERROR(D132/D97,"") -> 0.022033483 | E61: =IFERROR(E132/E97,"") -> 0.010030882 | F61: =IFERROR(F132/F97,"") -> -0.004731433 | G61: =IFERROR(G132/G97,"") -> -0.093865126 | H61: =IFERROR(H132/H97,"") -> 0.18745339 | I61: =IFERROR(I132/I97,"") | J61: =IFERROR(J132/J97,"") | K61: =IFERROR(K132/K97,"") | ... N61: =IFERROR(N132/N97,"") | O61: =IFERROR(+AVERAGE(D61:N61),"") -> 0.02418424
B62: Cash Flow to Net Income | D62: =IFERROR(D132/D96,"") -> 0.61676331 | E62: =IFERROR(E132/E96,"") -> 0.043985215 | F62: =IFERROR(F132/F96,"") -> -0.14285714 | G62: =IFERROR(G132/G96,"") -> -0.34377219 | H62: =IFERROR(H132/H96,"") -> 0.65297938 | I62: =IFERROR(I132/I96,"") | J62: =IFERROR(J132/J96,"") | K62: =IFERROR(K132/K96,"") | ... N62: =IFERROR(N132/N96,"") | O62: =IFERROR(+AVERAGE(D62:N62),"") -> 0.16541971
B63: CFO to Net Income | D63: =+IFERROR(D126/D105,"") -> -0.63822578 | E63: =+IFERROR(E126/E105,"") -> 0.87937706 | F63: =+IFERROR(F126/F105,"") -> 1.8531383 | G63: =+IFERROR(G126/G105,"") -> 3.3862595 | H63: =+IFERROR(H126/H105,"") -> 1.2362932 | I63: =+IFERROR(I126/I105,"") | J63: =+IFERROR(J126/J105,"") | K63: =+IFERROR(K126/K105,"") | ... N63: =+IFERROR(N126/N105,"") | O63: =IFERROR(+AVERAGE(D63:N63),"") -> 1.3433685
B64: Net Capex to CFO | D64: =IFERROR(-D127/D126,"") -> 2.8889961 | E64: =IFERROR(-E127/E126,"") -> 0.050492284 | F64: =IFERROR(-F127/F126,"") -> 0.20914173 | G64: =IFERROR(-G127/G126,"") -> 0.027452159 | H64: =IFERROR(-H127/H126,"") -> 0.18513012 | I64: =IFERROR(-I127/I126,"") | J64: =IFERROR(-J127/J126,"") | K64: =IFERROR(-K127/K126,"") | ... N64: =IFERROR(-N127/N126,"") | O64: =IFERROR(+AVERAGE(D64:N64),"") -> 0.67224249
B65: CFI to CFO | D65: =IFERROR(-D128/D126,"") -> 2.2027027 | E65: =IFERROR(-E128/E126,"") -> 0.31863502 | F65: =IFERROR(-F128/F126,"") -> 0.36205196 | G65: =IFERROR(-G128/G126,"") -> 1.1556958 | H65: =IFERROR(-H128/H126,"") -> 0.23367842 | I65: =IFERROR(-I128/I126,"") | J65: =IFERROR(-J128/J126,"") | K65: =IFERROR(-K128/K126,"") | ... N65: =IFERROR(-N128/N126,"") | O65: =IFERROR(+AVERAGE(D65:N65),"") -> 0.85455279
B66: Net Financing to CFO | D66: =IFERROR((D129+D130)/D126,"") -> 0.082890927 | E66: =IFERROR((E129+E130)/E126,"") -> -0.019504127 | F66: =IFERROR((F129+F130)/F126,"") -> -0.2466294 | G66: =IFERROR((G129+G130)/G126,"") -> 1.0192365 | H66: =IFERROR((H129+H130)/H126,"") -> -0.010298938 | I66: =IFERROR((I129+I130)/I126,"") | J66: =IFERROR((J129+J130)/J126,"") | K66: =IFERROR((K129+K130)/K126,"") | ... N66: =IFERROR((N129+N130)/N126,"") | O66: =IFERROR(+AVERAGE(D66:N66),"") -> 0.165139
B67: Debt Borrowing to Debt Repayment | D67: =+IFERROR(-D130/D129,"") -> 0.76907563 | E67: =+IFERROR(-E130/E129,"") | F67: =+IFERROR(-F130/F129,"") | G67: =+IFERROR(-G130/G129,"") -> 0.49076438 | H67: =+IFERROR(-H130/H129,"") | I67: =+IFERROR(-I130/I129,"") | J67: =+IFERROR(-J130/J129,"") | K67: =+IFERROR(-K130/K129,"") | ... N67: =+IFERROR(-N130/N129,"") | O67: =IFERROR(+AVERAGE(D67:N67),"") -> 0.62992
B68: CFF to CFO | D68: =IFERROR(-D131/D126,"") -> -1.3438707 | E68: =IFERROR(-E131/E126,"") -> 0.66094025 | F68: =IFERROR(-F131/F126,"") -> 0.67806643 | G68: =IFERROR(-G131/G126,"") -> 0.086814948 | H68: =IFERROR(-H131/H126,"") -> -0.2536315 | I68: =IFERROR(-I131/I126,"") | J68: =IFERROR(-J131/J126,"") | K68: =IFERROR(-K131/K126,"") | ... N68: =IFERROR(-N131/N126,"") | O68: =IFERROR(+AVERAGE(D68:N68),"") -> -0.034336105
B69: Payout Ratio | O69: =IFERROR(+AVERAGE(D69:N69),"")
B71: Stock Information | D71: =+D29 -> INTEL | E71: =+E29 -> NVIDIA | F71: =+F29 -> AMD | G71: =+G29 -> Broadcom | H71: =+H29 -> ASML | I71: =+I29 | J71: =+J29 | K71: =+K29 | ... O71: =+O29 -> Average
B73: (%) Float | D73: =4.32/4.36 -> 0.99082569 | E73: =23.41/24.4 -> 0.95942623 | F73: =1.61/1.62 -> 0.99382716 | G73: 0.000863 | H73: =392.08/393.2 -> 0.99715158 | O73: =IFERROR(+AVERAGE(D73:N73),"") -> 0.78841873
B74: β (Levered) | D74: {=IFERROR(_FV(D91,"Beta"),"")} -> 1.266 | E74: {=IFERROR(_FV(E91,"Beta"),"")} -> 2.1216 | F74: {=IFERROR(_FV(F91,"Beta"),"")} -> 1.9023 | G74: {=IFERROR(_FV(G91,"Beta"),"")} -> 1.2089 | H74: {=IFERROR(_FV(H91,"Beta"),"")} -> 1.8327 | I74: {=IFERROR(_FV(I91,"Beta"),"")} | J74: {=IFERROR(_FV(J91,"Beta"),"")} | K74: {=IFERROR(_FV(K91,"Beta"),"")} | ... N74: {=IFERROR(_FV(N91,"Beta"),"")} | O74: =IFERROR(+AVERAGE(D74:N74),"") -> 1.6663
B75: β (Unlevered) | D75: =IFERROR(D74/(1+(1-D104/D103)*(D121/D122)),"") -> 0.58490904 | E75: =+E74/(1+(1-E104/E103)*(E121/E122)) -> 1.9128302 | F75: =+F74/(1+(1-F104/F103)*(F121/F122)) -> 1.8574091 | G75: =+G74/(1+(1-G104/G103)*(G121/G122)) -> 0.75118967 | H75: =+H74/(1+(1-H104/H103)*(H121/H122)) -> 1.6987308 | I75: =IFERROR(I74/(1+(1-I104/I103)*(I121/I122)),"") | J75: =IFERROR(J74/(1+(1-J104/J103)*(J121/J122)),"") | K75: =IFERROR(K74/(1+(1-K104/K103)*(K121/K122)),"") | L75: =IFERROR(L74/(1+(1-L104/L103)*(L121/L122)),"") | M75: =IFERROR(M74/(1+(1-M104/M103)*(M121/M122)),"") | N75: =IFERROR(N74/(1+(1-N104/N103)*(N121/N122)),"") | O75: =IFERROR(+AVERAGE(D75:N75),"") -> 1.3610138
B76: % Held by Insiders | D76: 0.0008 | E76: 0.0432 | F76: 0.0047 | G76: 0.0202 | H76: 0.0001 | O76: =IFERROR(+AVERAGE(D76:N76),"") -> 0.0138
B77: % Held by Institutions | D77: 0.6606 | E77: 0.6761 | F77: 0.7016 | G77: 0.7894 | H77: 0.1867 | O77: =IFERROR(+AVERAGE(D77:N77),"") -> 0.60288
B78: Short % Float | D78: 0.0261 | E78: 0.01 | F78: 0.0285 | G78: 0.0133 | H78: 0.0055 | O78: =IFERROR(+AVERAGE(D78:N78),"") -> 0.01668
B80: Stock Performance | D80: =+D29 -> INTEL | E80: =+E29 -> NVIDIA | F80: =+F29 -> AMD | G80: =+G29 -> Broadcom | H80: =+H29 -> ASML | I80: =+I29 | J80: =+J29 | K80: =+K29 | ... O80: =+O29 -> Average
B82: 1 day | D82: {=IFERROR((D85/_xlfn.STOCKHISTORY(C6,TODAY()-1,TODAY()-1,0,0,1))-1,"Non-trading days")} -> 0.26566265 | E82: {=IFERROR((E85/_xlfn.STOCKHISTORY(C8,TODAY()-1,TODAY()-1,0,0,1))-1,"Non-trading days")} -> 0.032151036 | F82: {=IFERROR((F85/_xlfn.STOCKHISTORY(C9,TODAY()-1,TODAY()-1,0,0,1))-1,"Non-trading days")} -> -0.027425232 | G82: {=IFERROR((G85/_xlfn.STOCKHISTORY(C10,TODAY()-1,TODAY()-1,0,0,1))-1,"Non-trading days")} -> Non-trading days | H82: {=IFERROR((K85/_xlfn.STOCKHISTORY(C11,TODAY()-1,TODAY()-1,0,0,1))-1,"Non-trading days")} -> Non-trading days | I82: {=IFERROR((L85/_xlfn.STOCKHISTORY(C12,TODAY()-1,TODAY()-1,0,0,1))-1,"Non-trading days")} -> Non-trading days | J82: {=IFERROR((M85/_xlfn.STOCKHISTORY(C13,TODAY()-1,TODAY()-1,0,0,1))-1,"Non-trading days")} -> Non-trading days | K82: {=IFERROR((N85/_xlfn.STOCKHISTORY(C14,TODAY()-1,TODAY()-1,0,0,1))-1,"Non-trading days")} -> Non-trading days | L82: {=IFERROR((L85/_xlfn.STOCKHISTORY(C15,TODAY()-1,TODAY()-1,0,0,1))-1,"Non-trading days")} -> Non-trading days | M82: {=IFERROR((M85/_xlfn.STOCKHISTORY(C16,TODAY()-1,TODAY()-1,0,0,1))-1,"Non-trading days")} -> Non-trading days | N82: {=IFERROR((N85/_xlfn.STOCKHISTORY(C17,TODAY()-1,TODAY()-1,0,0,1))-1,"Non-trading days")} -> Non-trading days | O82: =IFERROR(+AVERAGE(D82:N82),"") -> 0.090129485
B83: 1 month | D83: {=IFERROR((D85/_xlfn.STOCKHISTORY(C6,TODAY()-29,TODAY()-29,0,0,1))-1,"Non-trading days")} -> 0.33878505 | E83: {=IFERROR((E85/_xlfn.STOCKHISTORY(C8,TODAY()-29,TODAY()-29,0,0,1))-1,"Non-trading days")} -> Non-trading days | F83: {=IFERROR((F85/_xlfn.STOCKHISTORY(C9,TODAY()-29,TODAY()-29,0,0,1))-1,"Non-trading days")} -> -0.062984262 | G83: {=IFERROR((G85/_xlfn.STOCKHISTORY(C10,TODAY()-29,TODAY()-29,0,0,1))-1,"Non-trading days")} -> 0.19145173 | H83: {=IFERROR((K85/_xlfn.STOCKHISTORY(C11,TODAY()-29,TODAY()-29,0,0,1))-1,"Non-trading days")} -> Non-trading days | I83: {=IFERROR((L85/_xlfn.STOCKHISTORY(C12,TODAY()-29,TODAY()-29,0,0,1))-1,"Non-trading days")} -> Non-trading days | J83: {=IFERROR((M85/_xlfn.STOCKHISTORY(C13,TODAY()-29,TODAY()-29,0,0,1))-1,"Non-trading days")} -> Non-trading days | K83: {=IFERROR((N85/_xlfn.STOCKHISTORY(C14,TODAY()-29,TODAY()-29,0,0,1))-1,"Non-trading days")} -> Non-trading days | L83: {=IFERROR((L85/_xlfn.STOCKHISTORY(C15,TODAY()-29,TODAY()-29,0,0,1))-1,"Non-trading days")} -> Non-trading days | M83: {=IFERROR((M85/_xlfn.STOCKHISTORY(C16,TODAY()-29,TODAY()-29,0,0,1))-1,"Non-trading days")} -> Non-trading days | N83: {=IFERROR((N85/_xlfn.STOCKHISTORY(C17,TODAY()-29,TODAY()-29,0,0,1))-1,"Non-trading days")} -> Non-trading days | O83: =IFERROR(AVERAGE(D83:N83),"") -> 0.15575084
B84: YTD | D84: {=IFERROR((D85/_xlfn.STOCKHISTORY(C6,"2025-01-02","2025-01-02",0,0,1))-1,"Non-trading days")} -> 0.55860534 | E84: {=IFERROR((E85/_xlfn.STOCKHISTORY(C8,"2025-01-02","2025-01-02",0,0,1))-1,"Non-trading days")} -> 0.27080471 | F84: {=IFERROR((F85/_xlfn.STOCKHISTORY(C9,"2025-01-02","2025-01-02",0,0,1))-1,"Non-trading days")} -> 0.28322142 | G84: {=IFERROR((G85/_xlfn.STOCKHISTORY(C10,"2025-01-02","2025-01-02",0,0,1))-1,"Non-trading days")} -> 0.49545219 | H84: {=IFERROR((K85/_xlfn.STOCKHISTORY(C11,"2025-01-02","2025-01-02",0,0,1))-1,"Non-trading days")} -> Non-trading days | I84: {=IFERROR((L85/_xlfn.STOCKHISTORY(C12,"2025-01-02","2025-01-02",0,0,1))-1,"Non-trading days")} -> Non-trading days | J84: {=IFERROR((M85/_xlfn.STOCKHISTORY(C13,"2025-01-02","2025-01-02",0,0,1))-1,"Non-trading days")} -> Non-trading days | K84: {=IFERROR((N85/_xlfn.STOCKHISTORY(C14,"2025-01-02","2025-01-02",0,0,1))-1,"Non-trading days")} -> Non-trading days | L84: {=IFERROR((L85/_xlfn.STOCKHISTORY(C15,"2025-01-02","2025-01-02",0,0,1))-1,"Non-trading days")} -> Non-trading days | M84: {=IFERROR((M85/_xlfn.STOCKHISTORY(C16,"2025-01-02","2025-01-02",0,0,1))-1,"Non-trading days")} -> Non-trading days | N84: {=IFERROR((N85/_xlfn.STOCKHISTORY(C17,"2025-01-02","2025-01-02",0,0,1))-1,"Non-trading days")} -> Non-trading days | O84: =IFERROR(AVERAGE(D84:N84),"") -> 0.40202092
B85: Current Price | D85: {=+IFERROR(_FV(D91,"Price"),"")} -> 31.515 | E85: {=+IFERROR(_FV(E91,"Price"),"")} -> 175.765 | F85: {=+IFERROR(_FV(F91,"Price"),"")} -> 154.795 | G85: {=+IFERROR(_FV(G91,"Price"),"")} -> 346.915 | H85: {=+IFERROR(_FV(H91,"Price"),"")} -> 936 | I85: {=+IFERROR(_FV(I91,"Price"),"")} | J85: {=+IFERROR(_FV(J91,"Price"),"")} | K85: {=+IFERROR(_FV(K91,"Price"),"")} | ... N85: {=+IFERROR(_FV(N91,"Price"),"")} | O85: =IFERROR(AVERAGE(D85:N85),"") -> 328.998
B87: Extra
B89: % Revenues in the US | D89: =Segments!I7/Segments!I11 -> 0.24470349
B91: Income Statement | D91: =+DCF!R4 -> #VALUE! | E91: #VALUE! | F91: #VALUE! | G91: #VALUE! | H91: #VALUE! | I91: PEER 5 | J91: PEER 6 | K91: PEER 7 | L91: PEER 8 | M91: PEER 9 | N91: PEER 10
B93: =+Inputs!$B$6&" ("&Inputs!O$4&")" -> Revenue (Sales) (2022) | D93: =+_xlfn.XLOOKUP("Revenue (Sales)",Inputs!$B:$B,Inputs!O:O) -> 63054 | E93: 26974 | F93: 23601 | G93: 33203 | H93: 22301
B94: =+Inputs!$B$6&" ("&Inputs!P$4&")" -> Revenue (Sales) (2023) | D94: =+_xlfn.XLOOKUP("Revenue (Sales)",Inputs!$B:$B,Inputs!P:P) -> 54228 | E94: 60922 | F94: 22680 | G94: 35819 | H94: 29805
B95: EBITDA (2023) | D95: =+_xlfn.XLOOKUP("EBITDA",Inputs!$B:$B,Inputs!P:P) -> 9480 | E95: =E94-11329+1508 -> 51101 | F95: =1900+1448+642+946 -> 4936 | G95: =16207+1394+502 -> 18103 | H95: 11461
B96: Net Income (2023) | D96: =+_xlfn.XLOOKUP("Net Income",Inputs!$B:$B,Inputs!P:P) -> 1897 | E96: 29760 | F96: 854 | G96: 14082 | H96: 8777
B97: =+Inputs!$B$6&" ("&Inputs!Q$4&")" -> Revenue (Sales) (2024) | D97: =+_xlfn.XLOOKUP("Revenue (Sales)",Inputs!$B:$B,Inputs!Q:Q) -> 53101 | E97: 130497 | F97: 25785 | G97: 51574 | H97: 30574
B98: COGS (Cost of Goods Sold) | D98: =+_xlfn.XLOOKUP($B98,Inputs!$B:$B,Inputs!Q:Q) -> 35756 | E98: 32639 | F98: 12114 | G98: 19065 | H98: 15122
B99: Gross Profit | D99: =+_xlfn.XLOOKUP($B99,Inputs!$B:$B,Inputs!Q:Q) -> 17345 | E99: =+E97-E98 -> 97858 | F99: =+F97-F98 -> 13671 | G99: =G97-G98 -> 32509 | H99: =+H97-H98 -> 15452
B100: EBITDA | D100: =+_xlfn.XLOOKUP($B100,Inputs!$B:$B,Inputs!Q:Q) -> 5955 | E100: =E99-16405+1865 -> 83318 | F100: =F101+1448+946+671 -> 4965 | G100: =G101+3244+593 -> 19627 | H100: 12807
B101: Operating Income (EBIT) | D101: =+_xlfn.XLOOKUP($B101,Inputs!$B:$B,Inputs!Q:Q) -> -5424 | E101: 81453 | F101: 1900 | G101: 15790 | H101: 10788
B102: Net Interest Expense (Income) | D102: =+_xlfn.XLOOKUP($B102,Inputs!$B:$B,Inputs!Q:Q) -> -211 | E102: 2573 | F102: -92 | G102: 3953 | H102: -21
B103: Pre-Tax Income (EBT) | D103: =+_xlfn.XLOOKUP($B103,Inputs!$B:$B,Inputs!Q:Q) -> -4963 | E103: =E101+E102 -> 84026 | F103: 1989 | G103: 9916 | H103: 10771
B104: Tax Expense (Benefits) | D104: =+_xlfn.XLOOKUP($B104,Inputs!$B:$B,Inputs!Q:Q) -> 8023 | E104: 11146 | F104: 381 | G104: 3748 | H104: 1966
B105: Net Income | D105: =+_xlfn.XLOOKUP($B105,Inputs!$B:$B,Inputs!Q:Q) -> -12986 | E105: =E103-E104 -> 72880 | F105: 1641 | G105: 5895 | H105: 9032
B106: EPS basic | D106: =+_xlfn.XLOOKUP($B106,Inputs!$B:$B,Inputs!Q:Q) -> -4.38 | E106: 2.97 | F106: 1.01 | G106: 1.27 | H106: 393,3
B107: R&D (Research & Development) | D107: =+_xlfn.XLOOKUP($B107,Inputs!$B:$B,Inputs!Q:Q) -> 16546 | E107: 12914 | F107: 6456 | G107: 9310 | H107: 3441
B109: Balance Sheet
B111: Cash & Cash Equivalents | D111: =+_xlfn.XLOOKUP($B111,Inputs!$B:$B,Inputs!Q:Q) -> 8249 | E111: 8589 | F111: 3787 | G111: 9348 | H111: 12735.9
B112: Accounts Receivable | D112: =+_xlfn.XLOOKUP($B112,Inputs!$B:$B,Inputs!Q:Q) -> 3478 | E112: 23065 | F112: 6192 | G112: 4416 | H112: 4477.5
B113: Beginning Inventory | D113: =+_xlfn.XLOOKUP("Inventory",Inputs!$B:$B,Inputs!P:P) -> 11127 | E113: 9999 | F113: 4351 | G113: 1898 | H113: 8850.7
B114: Ending Inventory | D114: =+_xlfn.XLOOKUP("Inventory",Inputs!$B:$B,Inputs!Q:Q) -> 12198 | E114: 10080 | F114: 5734 | G114: 1760 | H114: 10891.5
B115: Current Assets | D115: =+_xlfn.XLOOKUP($B115,Inputs!$B:$B,Inputs!Q:Q) -> 47324 | E115: 80126 | F115: 19049 | G115: 19595 | H115: 30737.4
B116: Net PP&E (Property, Plant and Equipment) | D116: =+_xlfn.XLOOKUP($B116,Inputs!$B:$B,Inputs!Q:Q) -> 108376 | E116: 6283 | F116: 1802 | G116: 2521 | H116: 6846.8
B117: Total Assets | D117: =+_xlfn.XLOOKUP($B117,Inputs!$B:$B,Inputs!Q:Q) -> 196485 | E117: 111601 | F117: 69226 | G117: 165645 | H117: 48589.6
B118: Accounts Payable | D118: =+_xlfn.XLOOKUP($B118,Inputs!$B:$B,Inputs!Q:Q) -> 12556 | E118: 6310 | F118: 1990 | G118: 1662 | H118: 3500.4
B119: Current Liabilities | D119: =+_xlfn.XLOOKUP($B119,Inputs!$B:$B,Inputs!Q:Q) -> 35666 | E119: 18047 | F119: 7281 | G119: 16697 | H119: 20051.4
B120: Long-term debt | D120: =+_xlfn.XLOOKUP($B120,Inputs!$B:$B,Inputs!Q:Q) -> 46561 | E120: =8463+1519 -> 9982 | F120: =1721 -> 1721 | G120: 66295 | H120: 3677.3
B121: Total Debt | D121: =+_xlfn.XLOOKUP($B121,Inputs!$B:$B,Inputs!Q:Q,,,-1) -> 46742 | E121: =E120+0 -> 9982 | F121: =F120+0 -> 1721 | G121: =G120 -> 66295 | H121: =H120+1010.3 -> 4687.6
B122: Shareholder's Equity | D122: =+_xlfn.XLOOKUP($B122,Inputs!$B:$B,Inputs!Q:Q) -> 105032 | E122: 79327 | F122: 57568 | G122: 67678 | H122: 48589.6
B124: Cash Flow Statement
B126: Operating Cash Flow | D126: =+_xlfn.XLOOKUP($B126,Inputs!$B:$B,Inputs!Q:Q) -> 8288 | E126: 64089 | F126: 3041 | G126: 19962 | H126: 11166.2
B127: Net Capex | D127: =+_xlfn.XLOOKUP($B127,Inputs!$B:$B,Inputs!Q:Q) -> -23944 | E127: -3236 | F127: -636 | G127: -548 | H127: -2067.2
B128: Investing Cash Flow | D128: =+_xlfn.XLOOKUP($B128,Inputs!$B:$B,Inputs!Q:Q) -> -18256 | E128: -20421 | F128: -1101 | G128: -23070 | H128: -2609.3
...

Sheet ESG
B2: Environmental, Social and Governance Analysis
B4: Author: | C4: Guilherme | E4: Highlights | N4: Recent News
B6: Overview | D6: .
B7: Last Update | C7: 45761 | D7: .
B8: Latest year with data | C8: 2024
B9: GICS Sector | C9: Information Technology
B10: GICS Industry Group | C10: Semiconductors & Semiconductor Equipment
B11: Final Review
B13: ESG Scores
B14: LSEG ESG Score | C14: 88
B15: E-Score | C15: 89
B16: S-Score | C16: 88 | E16: GHG Scope 1 and 2 Emissions: | N16: Water, Waste, Energy Management:
B17: G-Score | C17: 88
B18: S&P Global ESG Score | C18: 60
B19: Environmental | C19: 61
B20: Social | C20: 59
B21: Governance & Economic | C21: 60
B22: Sustainalytics | C22: 19.2
B23: ISS ESG Corporate Rating | C23: ?
B24: SDG Impact Rating | C24: ?
B25: Governance Quality Score | C25: ?
B26: MSCI ESG Ratings | C26: AA
B29: Industry ESG Overview:
E33: ENVIRONMENTAL
G35: Overview | H35: Targets | K35: Improvements | O35: Comments
E36: GHG (or CO2) Scope 1 Emissions | H36: Reduce Scope 1 (and 2 greenhouse) gas emissions by 10% between 2020 and 2030. Achieve net-zero emissions for these categories by 2040. | K36: In 2023, 100% renewable electricity in US, Europe, Israel, Malaysia, Vietnam, and China locations, was reached China locations | O36: N/A
E38: Water Consumption | H38: Save 60 billion gallons of water and support external projects that help restore water sources to achieve net positive water by 2030. | K38: In 2023, it was maintained the net positive water in the US and India and reached 2 additional countries (Costa Rica and México) | O38: Intel was the first semiconductor company in the US to achieve the Alliance for Water Stewardship (AWS) platinum certification (2023)
E40: Energy Consumption | H40: Transition to 100% renewable electricity and reduce electricity consumption by 4 billion kWh by 2030. | K40: In 2023 Intel had conserved a cumulative total of 1.6 billion kWh of electricity since the baseline date, which tends to raise every year (aimed at more 125 million in 2024) | O40: N/A
E42: Waste Management | H42: Achieve 0 waste to landfill. Adopt circular economy practices for at least 60% of the manufacturing waste streams by 2030 | K42: Intel continues to find ways to recover materials and regenerate resources to create circular economy solutions reducing costs and impact. | O42: 63% manufacturing waste upcycled in 2023
E44: Other
E46: SOCIAL
B48: Important Sources: | G48: Overview | H48: Targets | K48: Improvements | O48: Comments
B49: Annual Report | C49: https://d1io3yog0oux5.cloudfront.net/_7836e22efae1ffbd5e36f11a2d4b09f6/intel/db/888/9122/file/2024+ARS+Form+10-K+after+filing.pdf | E49: Employee Turnover % | H49: N/A | K49: N/A | O49: Its was 4% in 2020. In summer of 2024 due to a plan to reduce costs, Intel layed off roughly 15%.
B50: Sustainability Report | D50: .
B51: Proxy Statement | C51: https://d1io3yog0oux5.cloudfront.net/_7836e22efae1ffbd5e36f11a2d4b09f6/intel/db/888/9121/file/2025+Proxy+Statement+Final.pdf | D51: . | E51: Salaries & Compensation | H51: Intel is comitted to globay pay equity. | O51: To support employees during Covid19 more than $100 milion is being invested in employer benefits. Intel uses analysis to ensure fair pay. The median yearly total compensation reported at Intel is $174,771.
B53: Retiree Annual Enrollment Guide | C53: Retiree Benefits Enrollment Guide | E53: Reputation | H53: Commitment with lauching a new chip (Intel’s Panther Lake chipset) in the second half of 2025 | K53: (possible improvement) New CEO (18/3) strategy that consits in continuing to compound on what the company already does well can show relience and improve reputation | O53: Intel was named by Forbes as one of the 2019 World’s Most Reputable Companies. However, since then in January 2025 the company’s annual revenue presented a loss of about 33% in four years.
B55: Responsability Report | C55: https://csrreportbuilder.intel.com/pdfbuilder/pdfs/CSR-2023-24-Full-Report.pdf | E55: Discrimination Events | H55: N/A | K55: N/A | O55: (Sept. 2024) Processo por discriminação contra a Intel (“Intel failed to protect a talented Israeli employee from workplace discrimination, instead punishing him for raising concerns about his hostile anti-Israel manager.")
E57: Work Safety | H57: N/A | K57: In 2023 there was a reduction of 15% in office CTD(the most prevalent type of injury experienced at Intel in 2023) rates compared to 2022 | O57: In 2023 Intel had an OSHA(course that promotes workplace safety and improves compliance) recordable rate of 0.83 per 100 employees. (bigger than the industry average). Employees are required to complete EHS training.
E59: Damage to consumer health | H59: N/A | K59: N/A | O59: Intel's products alone won't damage consumer health. But, they boost the future of healthcare and life sciences (with AI-powered automation for example)
E61: Pension Plan | H61: N/A | K61: Annual deductible for High-Deductible Health Plans has increased +-8% in 2025 compared to 2024 | O61: For Intel employees, there is the Intel Pension Plan that plays an important role in securing financial stability during retirement.
E63: Supply chain | H63: (2030)Scale the supplier responsibility programs to ensure respect for human rights across 100% of the contracted suppliers and all high-risk-identified suppliers in the supply chain. | K63: In 2023, was reached the 25% of suppliers with respect for human rights ensured. | O63: N/A
E65: Community involvement | H65: (Intel Digital Readiness Program Portfolio(to advance inclusion and accessibility for millions of people who do not have the technology, skills, or resources)) 2030 goal: 30 countries, 30000 Institutions, 30milion people empowered. | K65: In 2023 the Intel Disability and Accessibility Network was expanded and formalized. | O65: Increase global annual spending with diverse suppliers by 100% to $2 billion. 20% Intel Capital (venture capital organization) investments in diverse start-ups. Intel employees and US retirees have donated more than 21.6 million hours of service
E67: Public Sector | H67: N/A | K67: N/A | O67: Intel has a public policy and works with governments, organizations and industries around the world.
E69: Litigation | H69: N/A | K69: N/A | O69: AMD Patent Settlement(2009); European Union Antitrust Fine(2009) won by Intel; A Jewish former employee of Intel (2025)
E71: GOVERNANCE
G73: Overview | H73: Targets | K73: Improvements | O73: Comments
E74: Diversity (Gender, Age, Industry, Region) | H74: N/A | K74: (downgrade) According to the proxy statement of 2023, 33% of the directors were women which was a higher number than the current 27% | O74: The average age is 62years, and 45% were born outside the US. Also there is a 18% racially/ethincally diverse.
E76: % Independence | H76: The board believes that a majority should be independent of management | K76: According to the proxy statement of 2023, 83% of the directores were independent | O76: 91% independentof the board directores are independent. (10 out of 11 nominees are independent)
E78: Average time as independent directors | H78: N/A | K78: (not necessarilyan improvement)According to the proxy statement of 2019 it was 5.3 years | O78: The average tenure is 4.4years
E80: Departures of C-level executives | H80: N/A | K80: N/A | O80: The previous CEO Patrick Gelsinger was forced out after the lost of confidence of the board
E82: CEO/Chairman duality | H82: N/A | K82: In the past there were exemples where the CEO was also the Chairman (for exemple in 2005) | O82: The CEO (Lip-Bu Tan) in not the same person as the Chairman (Frank D. Yeary).
E84: Transparency when reporting | H84: N/A | K84: N/A | O84: Especialy the proxy statement contains the details of the directors benefits and compensations.
E86: Time taken to report | H86: N/A | K86: N/A | P86: The 2024 annual report was released in January 31 of 2025, and the annual report to security holders on March 27, 2025.
E88: CEO or Chairman in other boards? | H88: N/A | K88: N/A | P88: Frank D. Yeary is a managing member of Darwin Capital Advisors LLC and Lip-Bu Tan is the executive chairman of Cadence Design Systems
E90: Audit / Consulting | H90: N/A | K90: N/A | O90: Intel is required by U.S. securitie laws to have annual audicts conducted by an independent registered public accounting firm. Ernst & Young LLC is Intel’s auditor since 1968.
E92: ESG-compensation related | H92: N/A | K92: Intel is recognized as a leader in ESG issues, and since 2008, it has been integrated the commitment to corporate responsibility and sustainability leadership into the compensation program. | O92: The ESG incentive bonus accounts for up to 7% of its annual cash bonus plan. (2022 proxy statement)
E94: Management compensation schemes | H94: Commitment to consult stockholders to better understand any significant views. | K94: (2023) The board voted and adopted a policy providing for an annual advisory stockholder vote to aprove the executive officers compensation | O94: N/A

Sheet ESG Inputs
B2: ESG Inputs
A4: x | B4: Total GHG Scope 1 Emissions | G4: 2014 | H4: =+G4+1 -> 2015 | I4: =+H4+1 -> 2016 | J4: =+I4+1 -> 2017 | K4: =+J4+1 -> 2018 | L4: =+K4+1 -> 2019 | M4: =+L4+1 -> 2020 | N4: =+M4+1 -> 2021 | O4: =+N4+1 -> 2022 | ... Q4: =+P4+1 -> 2024 | R4: ="CAGR "&$G$4&" - "&$Q$4 -> CAGR 2014 - 2024
B6: =+Peers!B6 -> INTEL CORPORATION | G6: 1041 | H6: 1052.6 | I6: 976 | J6: 1490 | K6: 940 | L6: 900 | M6: 1040 | N6: 1150 | O6: 1180 | P6: 845 | R6: =IFERROR((Q6/G6)^(1/COUNT($G$4:$Q$4))-1,"") -> -1
B7: =+Peers!B8 -> NVIDIA | G7: 2.7 | H7: 3.6 | I7: 2.4 | J7: 2.6 | K7: 2.4 | L7: 2.7 | M7: 2.8 | N7: 2.7 | O7: 4.6 | P7: 12.3 | Q7: 14.4 | R7: =IFERROR((Q7/G7)^(1/COUNT($G$4:$Q$4))-1,"") -> 0.16436943
B8: =+Peers!B9 -> AMD | G8: 55.1 | H8: 65.8 | I8: 2.6 | J8: 4.1 | K8: 3.2 | L8: 3.4 | M8: 6.4 | N8: 6.5 | O8: 8.1 | P8: 10 | R8: =IFERROR((Q8/G8)^(1/COUNT($G$4:$Q$4))-1,"") -> -1
B9: =+Peers!B10 -> Broadcom Inc. | N9: 127.8 | O9: 97.2 | P9: 58.8 | R9: =IFERROR((Q9/G9)^(1/COUNT($G$4:$Q$4))-1,"")
B10: =+Peers!B11 -> ASML | I10: 20.4 | J10: 19 | K10: 17.5 | L10: 16.9 | M10: 15.4 | N10: 19.3 | O10: 17.3 | P10: 19.2 | Q10: 23.5 | R10: =IFERROR((Q10/G10)^(1/COUNT($G$4:$Q$4))-1,"")
B11: =+Peers!B12 | R11: =IFERROR((Q11/G11)^(1/COUNT($G$4:$Q$4))-1,"")
B12: =+Peers!B13 | R12: =IFERROR((Q12/G12)^(1/COUNT($G$4:$Q$4))-1,"")
B13: =+Peers!B14 | R13: =IFERROR((Q13/G13)^(1/COUNT($G$4:$Q$4))-1,"")
B14: =+Peers!B15 | R14: =IFERROR((Q14/G14)^(1/COUNT($G$4:$Q$4))-1,"")
B15: =+Peers!B16 | R15: =IFERROR((Q15/G15)^(1/COUNT($G$4:$Q$4))-1,"")
B16: =+Peers!B17 | R16: =IFERROR((Q16/G16)^(1/COUNT($G$4:$Q$4))-1,"")
A18: x | B18: Total GHG Scope 2 (Location-Based) Emissions | G18: 2014 | H18: =+G18+1 -> 2015 | I18: =+H18+1 -> 2016 | J18: =+I18+1 -> 2017 | K18: =+J18+1 -> 2018 | L18: =+K18+1 -> 2019 | M18: =+L18+1 -> 2020 | N18: =+M18+1 -> 2021 | O18: =+N18+1 -> 2022 | ... Q18: =+P18+1 -> 2024 | R18: ="CAGR "&$G$4&" - "&$Q$4 -> CAGR 2014 - 2024
B20: =+$B$6 -> INTEL CORPORATION | G20: 2339 | H20: 2440.4 | I20: 2439 | J20: 2615 | K20: 1120 | L20: 3345 | M20: 3700 | N20: 3074.4 | O20: 3303.3 | P20: 3130 | R20: =IFERROR((Q20/G34)^(1/COUNT($G$4:$Q$4))-1,"") -> -1
B21: =+$B$7 -> NVIDIA | G21: 48.7 | H21: 52.3 | I21: 48.8 | J21: 51.2 | K21: 50.9 | L21: 65.1 | M21: 74.7 | N21: 105.6 | O21: 133.6 | P21: 142.9 | Q21: 178.1 | R21: =IFERROR((Q21/G21)^(1/COUNT($G$4:$Q$4))-1,"") -> 0.12510767
B22: =+$B$8 -> AMD | G22: 145.8 | H22: 137.7 | I22: 67 | J22: 51.2 | K22: 50 | L22: 50.6 | M22: 68.5 | N22: 70.7 | O22: 74.5 | P22: 80.8 | R22: =IFERROR((Q22/G22)^(1/COUNT($G$4:$Q$4))-1,"") -> -1
B23: =+$B$9 -> Broadcom Inc. | N23: 188.4 | O23: 181.2 | P23: 186.1 | R23: =IFERROR((Q23/G23)^(1/COUNT($G$4:$Q$4))-1,"")
B24: =+$B$10 -> ASML | N24: 165.1 | O24: 192.9 | P24: 168.1 | Q24: 228.2 | R24: =IFERROR((Q24/G24)^(1/COUNT($G$4:$Q$4))-1,"")
B25: =+$B$11 | R25: =IFERROR((Q25/G25)^(1/COUNT($G$4:$Q$4))-1,"")
B26: =+$B$12 | R26: =IFERROR((Q26/G26)^(1/COUNT($G$4:$Q$4))-1,"")
B27: =+$B$13 | R27: =IFERROR((Q27/G27)^(1/COUNT($G$4:$Q$4))-1,"")
B28: =+$B$14 | R28: =IFERROR((Q28/G28)^(1/COUNT($G$4:$Q$4))-1,"")
B29: =+$B$15 | R29: =IFERROR((Q29/G29)^(1/COUNT($G$4:$Q$4))-1,"")
B30: =+$B$16 | R30: =IFERROR((Q30/G30)^(1/COUNT($G$4:$Q$4))-1,"")
A32: x | B32: Total Energy Usage | G32: 2014 | H32: =+G32+1 -> 2015 | I32: =+H32+1 -> 2016 | J32: =+I32+1 -> 2017 | K32: =+J32+1 -> 2018 | L32: =+K32+1 -> 2019 | M32: =+L32+1 -> 2020 | N32: =+M32+1 -> 2021 | O32: =+N32+1 -> 2022 | ... Q32: =+P32+1 -> 2024 | R32: ="CAGR "&$G$4&" - "&$Q$4 -> CAGR 2014 - 2024
B34: =+$B$6 -> INTEL CORPORATION | G34: 5820 | H34: 6394.3 | I34: 6460.5 | J34: 7419 | K34: 8330 | L34: 9610 | M34: 10610 | N34: 11610 | O34: 10910 | P34: 10800 | R34: =IFERROR((Q34/#REF!)^(1/COUNT($G$4:$Q$4))-1,"")
B35: =+$B$7 -> NVIDIA | G35: 129 | H35: 135 | I35: 131.3 | J35: 139.8 | K35: 154.1 | L35: 197.1 | M35: 254.1 | N35: 328.4 | O35: 425 | P35: 496.9 | Q35: 612.6 | R35: =IFERROR((Q35/G35)^(1/COUNT($G$4:$Q$4))-1,"") -> 0.15214711
B36: =+$B$8 -> AMD | G36: 289 | H36: 261 | I36: 125 | J36: 129 | K36: 121 | L36: 126 | M36: 199 | N36: 181 | O36: 208 | P36: 232.7 | R36: =IFERROR((Q36/G36)^(1/COUNT($G$4:$Q$4))-1,"") -> -1
B37: =+$B$9 -> Broadcom Inc. | N37: 551.8 | O37: 541.7 | P37: 550.8 | R37: =IFERROR((Q37/G37)^(1/COUNT($G$4:$Q$4))-1,"")
B38: =+$B$10 -> ASML | G38: 282.2 | H38: 309.7 | I38: 131.9 | J38: 366.7 | K38: 376.3 | L38: 379.8 | M38: 391.2 | N38: 469.2 | O38: 453.6 | P38: 480.3 | Q38: 582.2 | R38: =IFERROR((Q38/G38)^(1/COUNT($G$4:$Q$4))-1,"") -> 0.068051736
B39: =+$B$11 | R39: =IFERROR((Q39/G39)^(1/COUNT($G$4:$Q$4))-1,"")
B40: =+$B$12 | R40: =IFERROR((Q40/G40)^(1/COUNT($G$4:$Q$4))-1,"")
B41: =+$B$13 | R41: =IFERROR((Q41/G41)^(1/COUNT($G$4:$Q$4))-1,"")
B42: =+$B$14 | R42: =IFERROR((Q42/G42)^(1/COUNT($G$4:$Q$4))-1,"")
B43: =+$B$15 | R43: =IFERROR((Q43/G43)^(1/COUNT($G$4:$Q$4))-1,"")
B44: =+$B$16 | R44: =IFERROR((Q44/G44)^(1/COUNT($G$4:$Q$4))-1,"")
A46: x | B46: Total Water Consumption | G46: 2014 | H46: =+G46+1 -> 2015 | I46: =+H46+1 -> 2016 | J46: =+I46+1 -> 2017 | K46: =+J46+1 -> 2018 | L46: =+K46+1 -> 2019 | M46: =+L46+1 -> 2020 | N46: =+M46+1 -> 2021 | O46: =+N46+1 -> 2022 | ... Q46: =+P46+1 -> 2024 | R46: ="CAGR "&$G$4&" - "&$Q$4 -> CAGR 2014 - 2024
B48: =+$B$6 -> INTEL CORPORATION | H48: 7465.2 | I48: 7083.1 | J48: 10289.2 | K48: 11541 | L48: 11028 | M48: 13020 | N48: 10791 | O48: 9971 | P48: 9890 | R48: =IFERROR((Q48/G48)^(1/COUNT($G$4:$Q$4))-1,"")
B49: =+$B$7 -> NVIDIA | G49: 80.1 | H49: 57.2 | I49: 29.1 | J49: 39.5 | K49: 61.2 | L49: 96.2 | M49: 72.4 | N49: 97.3 | O49: 239.8 | P49: 197.8 | Q49: 145.8 | R49: =IFERROR((Q49/G49)^(1/COUNT($G$4:$Q$4))-1,"") -> 0.055960634
B50: =+$B$8 -> AMD | N50: 0 | O50: 0 | P50: 0 | R50: =IFERROR((Q50/G50)^(1/COUNT($G$4:$Q$4))-1,"")
B51: =+$B$9 -> Broadcom Inc. | R51: =IFERROR((Q51/G51)^(1/COUNT($G$4:$Q$4))-1,"")
B52: =+$B$10 -> ASML | R52: =IFERROR((Q52/G52)^(1/COUNT($G$4:$Q$4))-1,"")
B53: =+$B$11 | R53: =IFERROR((Q53/G53)^(1/COUNT($G$4:$Q$4))-1,"")
B54: =+$B$12 | R54: =IFERROR((Q54/G54)^(1/COUNT($G$4:$Q$4))-1,"")
B55: =+$B$13 | R55: =IFERROR((Q55/G55)^(1/COUNT($G$4:$Q$4))-1,"")
B56: =+$B$14 | R56: =IFERROR((Q56/G56)^(1/COUNT($G$4:$Q$4))-1,"")
B57: =+$B$15 | R57: =IFERROR((Q57/G57)^(1/COUNT($G$4:$Q$4))-1,"")
B58: =+$B$16 | R58: =IFERROR((Q58/G58)^(1/COUNT($G$4:$Q$4))-1,"")
A60: x | B60: Total Waste Production | G60: 2014 | H60: =+G60+1 -> 2015 | I60: =+H60+1 -> 2016 | J60: =+I60+1 -> 2017 | K60: =+J60+1 -> 2018 | L60: =+K60+1 -> 2019 | M60: =+L60+1 -> 2020 | N60: =+M60+1 -> 2021 | O60: =+N60+1 -> 2022 | ... Q60: =+P60+1 -> 2024 | R60: ="CAGR "&$G$4&" - "&$Q$4 -> CAGR 2014 - 2024
B62: =+$B$6 -> INTEL CORPORATION | G62: 144.1 | H62: 129.2 | I62: 160.5 | J62: 183 | K62: 186 | L62: 351.1 | M62: 375.6 | N62: 312.1 | O62: 282.1 | P62: 264.9 | Q62: ND | R62: =IFERROR((Q62/G62)^(1/COUNT($G$4:$Q$4))-1,"")
B63: =+$B$7 -> NVIDIA | G63: ND | H63: 1.3 | I63: 15.6 | J63: 3 | K63: 2.7 | L63: 18.3 | M63: 5.3 | N63: 2.8 | O63: 0.9 | P63: 1.9 | Q63: 2.3 | R63: =IFERROR((Q63/G63)^(1/COUNT($G$4:$Q$4))-1,"")
B64: =+$B$8 -> AMD | G64: 2 | H64: 0.6 | I64: 0.6 | J64: 0.7 | K64: 0.6 | L64: 0.7 | M64: 0.5 | N64: 0.5 | O64: 0.8 | P64: 1.3 | Q64: ND | R64: =IFERROR((Q64/G64)^(1/COUNT($G$4:$Q$4))-1,"")
B65: =+$B$9 -> Broadcom Inc. | G65: ND | H65: ND | I65: ND | J65: ND | K65: ND | L65: ND | M65: ND | N65: 12.4 | O65: 14.7 | P65: 39.6 | Q65: ND | R65: =IFERROR((Q65/G65)^(1/COUNT($G$4:$Q$4))-1,"")
B66: =+$B$10 -> ASML | G66: 3.8 | H66: 5.3 | I66: 3.9 | J66: 3.9 | K66: 4.5 | L66: 5.5 | M66: 5.3 | N66: 5.9 | O66: 6.9 | P66: 8.9 | Q66: 13.5 | R66: =IFERROR((Q66/G66)^(1/COUNT($G$4:$Q$4))-1,"") -> 0.12214768
B67: =+$B$11 | R67: =IFERROR((Q67/G67)^(1/COUNT($G$4:$Q$4))-1,"")
B68: =+$B$12 | R68: =IFERROR((Q68/G68)^(1/COUNT($G$4:$Q$4))-1,"")
B69: =+$B$13 | R69: =IFERROR((Q69/G69)^(1/COUNT($G$4:$Q$4))-1,"")
B70: =+$B$14 | R70: =IFERROR((Q70/G70)^(1/COUNT($G$4:$Q$4))-1,"")
B71: =+$B$15 | R71: =IFERROR((Q71/G71)^(1/COUNT($G$4:$Q$4))-1,"")
B72: =+$B$16 | R72: =IFERROR((Q72/G72)^(1/COUNT($G$4:$Q$4))-1,"")
A74: x | B74: GHG Scope 1 and 2 Emissions | G74: 2014 | H74: =+G74+1 -> 2015 | I74: =+H74+1 -> 2016 | J74: =+I74+1 -> 2017 | K74: =+J74+1 -> 2018 | L74: =+K74+1 -> 2019 | M74: =+L74+1 -> 2020 | N74: =+M74+1 -> 2021 | O74: =+N74+1 -> 2022 | ... Q74: =+P74+1 -> 2024 | R74: ="CAGR "&$G$4&" - "&$Q$4 -> CAGR 2014 - 2024
B76: =+$B$6 -> INTEL CORPORATION | G76: =+G6+G34 -> 6861 | H76: =+H6+H34 -> 7446.9 | I76: =+I6+I34 -> 7436.5 | J76: =+J6+J34 -> 8909 | K76: =+K6+K34 -> 9270 | L76: =+L6+L34 -> 10510 | M76: =+M6+M34 -> 11650 | N76: =+N6+N34 -> 12760 | ... P76: =+P6+P34 -> 11645 | Q76: =+Q6+Q20 -> 0 | R76: =IFERROR((Q76/G76)^(1/COUNT($G$4:$Q$4))-1,"") -> -1
B77: =+$B$7 -> NVIDIA | G77: =+G7+G21 -> 51.4 | H77: =+H7+H21 -> 55.9 | I77: =+I7+I21 -> 51.2 | J77: =+J7+J21 -> 53.8 | K77: =+K7+K21 -> 53.3 | L77: =+L7+L21 -> 67.8 | M77: =+M7+M21 -> 77.5 | N77: =+N7+N21 -> 108.3 | ... Q77: =+Q7+Q21 -> 192.5 | R77: =IFERROR((Q77/G77)^(1/COUNT($G$4:$Q$4))-1,"") -> 0.1275438
B78: =+$B$8 -> AMD | G78: =+G8+G22 -> 200.9 | H78: =+H8+H22 -> 203.5 | I78: =+I8+I22 -> 69.6 | J78: =+J8+J22 -> 55.3 | K78: =+K8+K22 -> 53.2 | L78: =+L8+L22 -> 54 | M78: =+M8+M22 -> 74.9 | N78: =+N8+N22 -> 77.2 | ... Q78: =+Q8+Q22 -> 0 | R78: =IFERROR((Q78/G78)^(1/COUNT($G$4:$Q$4))-1,"") -> -1
B79: =+$B$9 -> Broadcom Inc. | G79: =+G9+G23 -> 0 | H79: =+H9+H23 -> 0 | I79: =+I9+I23 -> 0 | J79: =+J9+J23 -> 0 | K79: =+K9+K23 -> 0 | L79: =+L9+L23 -> 0 | M79: =+M9+M23 -> 0 | N79: =+N9+N23 -> 316.2 | ... Q79: =+Q9+Q23 -> 0 | R79: =IFERROR((Q79/G79)^(1/COUNT($G$4:$Q$4))-1,"")
B80: =+$B$10 -> ASML | G80: =+G10+G24 -> 0 | H80: =+H10+H24 -> 0 | I80: =+I10+I24 -> 20.4 | J80: =+J10+J24 -> 19 | K80: =+K10+K24 -> 17.5 | L80: =+L10+L24 -> 16.9 | M80: =+M10+M24 -> 15.4 | N80: =+N10+N24 -> 184.4 | ... Q80: =+Q10+Q24 -> 251.7 | R80: =IFERROR((Q80/G80)^(1/COUNT($G$4:$Q$4))-1,"")
B81: =+$B$11 | G81: =+G11+G25 -> 0 | H81: =+H11+H25 -> 0 | I81: =+I11+I25 -> 0 | J81: =+J11+J25 -> 0 | K81: =+K11+K25 -> 0 | L81: =+L11+L25 -> 0 | M81: =+M11+M25 -> 0 | N81: =+N11+N25 -> 0 | ... Q81: =+Q11+Q25 -> 0 | R81: =IFERROR((Q81/G81)^(1/COUNT($G$4:$Q$4))-1,"")
B82: =+$B$12 | G82: =+G12+G26 -> 0 | H82: =+H12+H26 -> 0 | I82: =+I12+I26 -> 0 | J82: =+J12+J26 -> 0 | K82: =+K12+K26 -> 0 | L82: =+L12+L26 -> 0 | M82: =+M12+M26 -> 0 | N82: =+N12+N26 -> 0 | ... Q82: =+Q12+Q26 -> 0 | R82: =IFERROR((Q82/G82)^(1/COUNT($G$4:$Q$4))-1,"")
B83: =+$B$13 | G83: =+G13+G27 -> 0 | H83: =+H13+H27 -> 0 | I83: =+I13+I27 -> 0 | J83: =+J13+J27 -> 0 | K83: =+K13+K27 -> 0 | L83: =+L13+L27 -> 0 | M83: =+M13+M27 -> 0 | N83: =+N13+N27 -> 0 | ... Q83: =+Q13+Q27 -> 0 | R83: =IFERROR((Q83/G83)^(1/COUNT($G$4:$Q$4))-1,"")
B84: =+$B$14 | G84: =+G14+G28 -> 0 | H84: =+H14+H28 -> 0 | I84: =+I14+I28 -> 0 | J84: =+J14+J28 -> 0 | K84: =+K14+K28 -> 0 | L84: =+L14+L28 -> 0 | M84: =+M14+M28 -> 0 | N84: =+N14+N28 -> 0 | ... Q84: =+Q14+Q28 -> 0 | R84: =IFERROR((Q84/G84)^(1/COUNT($G$4:$Q$4))-1,"")
B85: =+$B$15 | G85: =+G15+G29 -> 0 | H85: =+H15+H29 -> 0 | I85: =+I15+I29 -> 0 | J85: =+J15+J29 -> 0 | K85: =+K15+K29 -> 0 | L85: =+L15+L29 -> 0 | M85: =+M15+M29 -> 0 | N85: =+N15+N29 -> 0 | ... Q85: =+Q15+Q29 -> 0 | R85: =IFERROR((Q85/G85)^(1/COUNT($G$4:$Q$4))-1,"")
B86: =+$B$16 | G86: =+G16+G30 -> 0 | H86: =+H16+H30 -> 0 | I86: =+I16+I30 -> 0 | J86: =+J16+J30 -> 0 | K86: =+K16+K30 -> 0 | L86: =+L16+L30 -> 0 | M86: =+M16+M30 -> 0 | N86: =+N16+N30 -> 0 | ... Q86: =+Q16+Q30 -> 0 | R86: =IFERROR((Q86/G86)^(1/COUNT($G$4:$Q$4))-1,"")

Sheet DCF
B2: DCF
A4: x | B4: Key Assumptions | R4: #VALUE!
B6: Switches | E6: Bear Case | H6: Base Case | K6: Bull Case | X6: FCFF | Y6: FCFE | Z6: Tax Shield | AA6: Total Payout | AB6: NOPAT | AC6: Debt Borrowing | AD6: Cash Balance | AE6: Total Assets | AF6: Total Liabilities | AG6: Shareholder's Equity | AH6: Current Liabilities | AI6: Current Assets
B7: Revenue | C7: 2 | E7: Revenue | F7: -0.02 | H7: Revenue | K7: Revenue | L7: 0.02 | S7: Most Recent Fiscal Year | T7: 2024 | W7: 2022 | X7: =+E195 -> -10609.043 | Y7: =+E247 -> 2563 | Z7: =+H219 -> 0 | AA7: =+E260 -> -3988 | AB7: =+E185 -> 1507.9569 | AC7: =+E245 -> 11877 | AD7: =+E90 -> 28338
B8: EBIT | C8: 2 | E8: EBIT | F8: -0.01 | H8: EBIT | K8: EBIT | L8: 0.01 | S8: End of Fiscal Year | T8: 45657 | W8: =+W7+1 -> 2023 | X8: =+F195 -> -15272.197 | Y8: =+F247 -> -1230 | Z8: =+I219 -> 0 | AA8: =+F260 -> 913 | AB8: =+F185 -> -235.19715 | AC8: =+F245 -> 11910 | AD8: =+F90 -> 25034
B9: WACC | C9: 2 | E9: WACC | F9: =IFERROR(+I9+0.5%,"") -> 0.095345549 | H9: WACC | I9: =WACC!G25 -> 0.090345549 | K9: WACC | L9: =IFERROR(I9-0.5%,"") -> 0.085345549 | S9: Most Recent Quarter End Date | T9: 45654 | W9: =+W8+1 -> 2024 | X9: =+G195 -> -24467.235 | Y9: =+G247 -> -17998 | Z9: =+J219 -> 0 | AA9: =+G260 -> -612 | AB9: =+G185 -> -14192.235 | AC9: =+G245 -> 5263 | AD9: =+G90 -> 22062 | AE9: =Inputs!Q48 -> 196485 | AF9: =+Inputs!Q60 -> 91453 | AG9: =+AE9-AF9 -> 105032 | AH9: =+Inputs!Q54 -> 35666 | AI9: =+Inputs!Q38 -> 47324
B10: TGR | C10: 2 | E10: TGR | F10: =+I10-0.5% -> 0.015 | H10: TGR | I10: 0.02 | K10: TGR | L10: =+I10+0.5% -> 0.025 | S10: Valuation Date | T10: 45762 | W10: =+W9+1 -> 2025 | X10: =+H195 -> 10069.536 | Y10: =+H247 -> 23001.221 | Z10: =+K219 -> 0 | AA10: =+H260 -> 0 | AB10: =+H185 -> -7754.1799 | AC10: =+H245 -> 17998 | AD10: =+H90 -> 56777.728 | AE10: =Inputs!Q48+DCF!H90+DCF!H92+DCF!H95+DCF!H98+DCF!H101+DCF!H107-DCF!G90-DCF!G92-DCF!G95-DCF!G98-DCF!G101-DCF!G107 -> 225415.24 | AF10: =+Inputs!Q60+(DCF!H112+DCF!H115+DCF!H118+DCF!H120*DCF!G112*DCF!G115*DCF!G118*DCF!G120) -> 3.5738633e+18 | AG10: =+AE10-AF10 -> -3.5738633e+18 | AH10: =+AH9+H112+H115-G112-G115 -> 41236.047 | AI10: =+H90+H92+H95+H98 -> 83208.671
W11: =+W10+1 -> 2026 | X11: =+I195 -> 6728.3739 | Y11: =+I247 -> -1189.6229 | Z11: =+L219 -> 0 | AA11: =+I260 -> 0 | AB11: =+I185 -> -2239.8839 | AC11: =+I245 -> -6900.3663 | AD11: =+I90 -> 80702.745 | AE11: =AE10+DCF!I90+DCF!I92+DCF!I95+DCF!I98+DCF!I101+DCF!I107-DCF!H90-DCF!H92-DCF!H95-DCF!H98-DCF!H101-DCF!H107 -> 244277.27 | AF11: =AF10+(DCF!I112+DCF!I115+DCF!I118+DCF!I120*DCF!H112*DCF!H115*DCF!H118*DCF!H120) -> 1.2350363e+19 | AG11: =+AE11-AF11 -> -1.2350363e+19 | AH11: =+AH10+I112+I115-H112-H115 -> 37910.691 | AI11: =+I90+I92+I95+I98 -> 107911.26
B12: WACC | C12: =CHOOSE(C9,F9,I9,L9) -> 0.090345549 | W12: =+W11+1 -> 2027 | X12: =+J195 -> 12111.315 | Y12: =+J247 -> 14910.525 | Z12: =+M219 -> 0 | AA12: =+J260 -> -641.02472 | AB12: =+J185 -> -2185.2784 | AC12: =+J245 -> 1189.6229 | AD12: =+J90 -> 111291.78
B13: TGR | C13: =CHOOSE(C10,F10,I10,L10) -> 0.02 | W13: =+W12+1 -> 2028 | X13: =+K195 -> 6742.719 | Y13: =+K247 -> 4092.0776 | Z13: =+N219 -> 0 | AA13: =+K260 -> -641.02472 | AB13: =+K185 -> -8433.2258 | AC13: =+K245 -> -4473.1575 | AD13: =+K90 -> 137371.96
W14: =+W13+1 -> 2029 | X14: =+L195 -> 4999.6844 | Y14: =+L247 -> 5165.4943 | Z14: =+O219 -> 0 | AA14: =+L260 -> -641.02472 | AB14: =+L185 -> -8981.6159 | AC14: =+L245 -> -1636.8311 | AD14: =+L90 -> 159559.13
A15: x | B15: Operating Assumptions | E15: 2022 | F15: =+E15+1 -> 2023 | G15: =+F15+1 -> 2024 | H15: =+G15+1 -> 2025 | I15: =+H15+1 -> 2026 | J15: =+I15+1 -> 2027 | K15: =+J15+1 -> 2028 | L15: =+K15+1 -> 2029 | M15: =+L15+1 -> 2030 | ... Q15: =+P15+1 -> 2034
B17: CCD | E17: =Segments!G15 -> 31773 | F17: =Segments!H15 -> 29258 | G17: =Segments!I15 -> 30290 | H17: =G17*(1+H19) -> 31804.5 | I17: =H17*(1+I19) -> 34030.815 | J17: =I17*(1+J19) -> 36412.972 | K17: =J17*(1+K19) -> 38961.88 | L17: =K17*(1+L19) -> 41689.212 | M17: =L17*(1+M19) -> 44607.457 | N17: =M17*(1+N19) -> 46391.755 | O17: =N17*(1+O19) -> 48247.425 | ... Q17: =P17*(1+Q19) -> 52184.415
B18: % OF REVENUE | E18: =E17/E32 -> 0.50390142 | F18: =F17/F32 -> 0.53953677 | G18: =G17/G32 -> 0.5704224 | H18: =H17/H32 -> 0.47251124 | I18: =I17/I32 -> 0.4837914 | J18: =J17/J32 -> 0.49701569 | K18: =K17/K32 -> 0.50977595 | L18: =L17/L32 -> 0.52207267 | ... Q18: =Q17/Q32 -> 0.54903556
B19: growth rate in % | F19: =F17/E17-1 -> -0.079155258 | G19: =G17/F17-1 -> 0.035272404 | H19: 0.05 | I19: 0.07 | J19: 0.07 | K19: 0.07 | L19: 0.07 | M19: 0.07 | N19: 0.04 | O19: 0.04 | P19: 0.04 | Q19: 0.04
B20: DCAI | E20: =Segments!G16 -> 16856 | F20: =Segments!H16 -> 12635 | G20: =Segments!I16 -> 12817 | H20: =G20*(1+H22) -> 11535.3 | I20: =H20*(1+I22) -> 10958.535 | J20: =I20*(1+J22) -> 10410.608 | K20: =J20*(1+K22) -> 9890.0778 | L20: =K20*(1+L22) -> 9395.5739 | M20: =L20*(1+M22) -> 9583.4854 | N20: =M20*(1+N22) -> 9775.1551 | O20: =N20*(1+O22) -> 9970.6582 | ... Q20: =P20*(1+Q22) -> 10373.473
B21: % OF REVENUE | E21: =E20/E32 -> 0.26732642 | F21: =F20/F32 -> 0.23299771 | G21: =G20/G32 -> 0.24137022 | H21: =H20/H32 -> 0.17137697 | I21: =I20/I32 -> 0.15578954 | J21: =J20/J32 -> 0.14209869 | K21: =K20/K32 -> 0.12940145 | L21: =L20/L32 -> 0.11766047 | ... Q21: =Q20/Q32 -> 0.10913997
B22: growth rate in % | F22: =F20/E20-1 -> -0.25041528 | G22: =G20/F20-1 -> 0.014404432 | H22: -0.1 | I22: -0.05 | J22: -0.05 | K22: -0.05 | L22: -0.05 | M22: 0.02 | N22: 0.02 | O22: 0.02 | P22: 0.02 | Q22: 0.02
B23: NEX | E23: =Segments!G17 -> 8409 | F23: =Segments!H17 -> 5774 | G23: =Segments!I17 -> 5842 | H23: =G23*(1+H25) -> 5900.42 | I23: =H23*(1+I25) -> 6018.4284 | J23: =I23*(1+J25) -> 6138.797 | K23: =J23*(1+K25) -> 6261.5729 | L23: =K23*(1+L25) -> 6386.8044 | M23: =L23*(1+M25) -> 6514.5405 | N23: =M23*(1+N25) -> 6644.8313 | O23: =N23*(1+O25) -> 6777.7279 | ... Q23: =P23*(1+Q25) -> 7051.5481
B24: % OF REVENUE | E24: =E23/E32 -> 0.13336188 | F24: =F23/F32 -> 0.10647636 | G24: =G23/G32 -> 0.11001676 | H24: =H23/H32 -> 0.087661016 | I24: =I23/I32 -> 0.085559628 | J24: =J23/J32 -> 0.083790974 | K24: =K23/K32 -> 0.081926212 | L24: =L23/L32 -> 0.079981747 | ... Q24: =Q23/Q32 -> 0.074189787
B25: growth rate in % | F25: =F23/E23-1 -> -0.31335474 | G25: =G23/F23-1 -> 0.011776931 | H25: 0.01 | I25: 0.02 | J25: 0.02 | K25: 0.02 | L25: 0.02 | M25: 0.02 | N25: 0.02 | O25: 0.02 | P25: 0.02 | Q25: 0.02
B26: Intel Foundry | E26: =Segments!G18 -> 27491 | F26: =Segments!H18 -> 18910 | G26: =Segments!I18 -> 17543 | H26: =G26*(1+H28) -> 18069.29 | I26: =H26*(1+I28) -> 19334.14 | J26: =I26*(1+J28) -> 20300.847 | K26: =J26*(1+K28) -> 21315.89 | L26: =K26*(1+L28) -> 22381.684 | M26: =L26*(1+M28) -> 23500.768 | N26: =M26*(1+N28) -> 23970.784 | O26: =N26*(1+O28) -> 24450.199 | ... Q26: =P26*(1+Q28) -> 25437.987
B27: % OF REVENUE | E27: =E26/E32 -> 0.43599137 | F27: =F26/F32 -> 0.34871284 | G27: =G26/G32 -> 0.33037043 | H27: =H26/H32 -> 0.26845077 | I27: =I26/I32 -> 0.27485944 | J27: =J26/J32 -> 0.27709465 | K27: =K26/K32 -> 0.27889639 | L27: =L26/L32 -> 0.28028512 | ... Q27: =Q26/Q32 -> 0.26763469
B28: growth rate in % | F28: =F26/E26-1 -> -0.31213852 | G28: =G26/F26-1 -> -0.072289794 | H28: 0.03 | I28: 0.07 | J28: 0.05 | K28: 0.05 | L28: 0.05 | M28: 0.05 | N28: 0.02 | O28: 0.02 | P28: 0.02 | Q28: 0.02
B29: In millions of USD
B30: Income Statement | E30: 2022 | F30: =+E30+1 -> 2023 | G30: =+F30+1 -> 2024 | H30: =+G30+1 -> 2025 | I30: =+H30+1 -> 2026 | J30: =+I30+1 -> 2027 | K30: =+J30+1 -> 2028 | L30: =+K30+1 -> 2029 | M30: =+L30+1 -> 2030 | ... Q30: =+P30+1 -> 2034
A32: x | B32: Revenue (Sales) | D32: =+_xlfn.XLOOKUP($B32,Inputs!$B:$B,Inputs!N:N) -> 74718 | E32: =+_xlfn.XLOOKUP($B32,Inputs!$B:$B,Inputs!O:O) -> 63054 | F32: =+_xlfn.XLOOKUP($B32,Inputs!$B:$B,Inputs!P:P) -> 54228 | G32: =+_xlfn.XLOOKUP($B32,Inputs!$B:$B,Inputs!Q:Q) -> 53101 | H32: =H17+H20+H23+H26 -> 67309.51 | I32: =I17+I20+I23+I26 -> 70341.919 | J32: =J17+J20+J23+J26 -> 73263.225 | K32: =K17+K20+K23+K26 -> 76429.421 | L32: =L17+L20+L23+L26 -> 79853.274 | M32: =M17+M20+M23+M26 -> 84206.251 | N32: =N17+N20+N23+N26 -> 86782.525 | O32: =O17+O20+O23+O26 -> 89446.011 | ... Q32: =Q17+Q20+Q23+Q26 -> 95047.423
B33: % of growth | E33: =IFERROR((E32-D32)/D32,"") -> -0.15610696 | F33: =IFERROR((F32-E32)/E32,"") -> -0.13997526 | G33: =IFERROR((G32-F32)/F32,"") -> -0.020782622 | H33: =IFERROR(H32/G32-1,"") -> 0.26757519 | I33: =IFERROR(I32/H32-1,"") -> 0.045051713 | J33: =IFERROR(J32/I32-1,"") -> 0.041530085 | K33: =IFERROR(K32/J32-1,"") -> 0.043216716 | L33: =IFERROR(L32/K32-1,"") -> 0.044797588 | M33: =IFERROR(M32/L32-1,"") -> 0.054512187 | N33: =IFERROR(N32/M32-1,"") -> 0.030594809 | O33: =IFERROR(O32/N32-1,"") -> 0.030691497 | ... Q33: =IFERROR(Q32/P32-1,"") -> 0.030884466
B35: COGS (Cost of Goods Sold) | E35: =+_xlfn.XLOOKUP($B35,Inputs!$B:$B,Inputs!O:O) -> 36188 | F35: =+_xlfn.XLOOKUP($B35,Inputs!$B:$B,Inputs!P:P) -> 32517 | G35: =+_xlfn.XLOOKUP($B35,Inputs!$B:$B,Inputs!Q:Q) -> 35756 | H35: =H36*H$32 -> 43751.182 | I35: =I36*I$32 -> 43611.99 | J35: =J36*J$32 -> 43957.935 | K35: =K36*K$32 -> 48914.829 | L35: =L36*L$32 -> 51106.095 | M35: =M36*M$32 -> 53892 | N35: =N36*N$32 -> 55540.816 | O35: =O36*O$32 -> 57245.447 | ... Q35: =Q36*Q$32 -> 60830.351
B36: % of revenue | E36: =IFERROR(E35/E$32,"") -> 0.57392077 | F36: =IFERROR(F35/F$32,"") -> 0.59963487 | G36: =IFERROR(G35/G$32,"") -> 0.67335832 | H36: 0.65 | I36: 0.62 | J36: 0.6 | K36: 0.64 | L36: 0.64 | M36: 0.64 | N36: 0.64 | O36: 0.64 | P36: 0.64 | Q36: 0.64
B38: Gross Profit | E38: =+_xlfn.XLOOKUP($B38,Inputs!$B:$B,Inputs!O:O) -> 26866 | F38: =+_xlfn.XLOOKUP($B38,Inputs!$B:$B,Inputs!P:P) -> 21711 | G38: =+_xlfn.XLOOKUP($B38,Inputs!$B:$B,Inputs!Q:Q) -> 17345 | H38: =+H32-H35 -> 23558.329 | I38: =+I32-I35 -> 26729.929 | J38: =+J32-J35 -> 29305.29 | K38: =+K32-K35 -> 27514.591 | L38: =+L32-L35 -> 28747.179 | M38: =+M32-M35 -> 30314.25 | N38: =+N32-N35 -> 31241.709 | O38: =+O32-O35 -> 32200.564 | ... Q38: =+Q32-Q35 -> 34217.072
B39: Gross Profit Margin | E39: =IFERROR(E38/E$32,"") -> 0.42607923 | F39: =IFERROR(F38/F$32,"") -> 0.40036513 | G39: =IFERROR(G38/G$32,"") -> 0.32664168 | H39: =IFERROR(H38/H$32,"") -> 0.35 | I39: =IFERROR(I38/I$32,"") -> 0.38 | J39: =IFERROR(J38/J$32,"") -> 0.4 | K39: =IFERROR(K38/K$32,"") -> 0.36 | L39: =IFERROR(L38/L$32,"") -> 0.36 | ... Q39: =IFERROR(Q38/Q$32,"") -> 0.36
B41: SG&A (Selling, General & Administrative) | E41: =+_xlfn.XLOOKUP($B41,Inputs!$B:$B,Inputs!O:O) -> 7002 | F41: =+_xlfn.XLOOKUP($B41,Inputs!$B:$B,Inputs!P:P) -> 5634 | G41: =+_xlfn.XLOOKUP($B41,Inputs!$B:$B,Inputs!Q:Q) -> 5507 | H41: =IFERROR(G41*(1+H33),"") -> 6980.5366 | I41: =IFERROR(H41*(1+I33),"") -> 7295.0217 | J41: =IFERROR(I41*(1+J33),"") -> 7597.9846 | K41: =IFERROR(J41*(1+K33),"") -> 7926.3445 | L41: =IFERROR(K41*(1+L33),"") -> 8281.4256 | M41: =IFERROR(L41*(1+M33),"") -> 8732.8642 | N41: =IFERROR(M41*(1+N33),"") -> 9000.0445 | O41: =IFERROR(N41*(1+O33),"") -> 9276.2694 | ... Q41: =IFERROR(P41*(1+Q33),"") -> 9857.1808
B42: SG&A Margin | E42: =IFERROR(E41/E$32,"") -> 0.11104767 | F42: =IFERROR(F41/F$32,"") -> 0.10389467 | G42: =IFERROR(G41/G$32,"") -> 0.10370803 | H42: =IFERROR(AVERAGE(E42:G42),"") -> 0.10621679 | I42: =IFERROR(AVERAGE(F42:H42),"") -> 0.10460649 | J42: =IFERROR(AVERAGE(G42:I42),"") -> 0.10484377 | K42: =IFERROR(AVERAGE(H42:J42),"") -> 0.10522235 | L42: =IFERROR(AVERAGE(I42:K42),"") -> 0.10489087 | M42: =IFERROR(AVERAGE(J42:L42),"") -> 0.10498566 | N42: =IFERROR(AVERAGE(K42:M42),"") -> 0.10503296 | O42: =IFERROR(AVERAGE(L42:N42),"") -> 0.10496983 | ... Q42: =IFERROR(AVERAGE(N42:P42),"") -> 0.10499965
B44: R&D (Research & Development) | E44: =+_xlfn.XLOOKUP($B44,Inputs!$B:$B,Inputs!O:O) -> 17528 | F44: =+_xlfn.XLOOKUP($B44,Inputs!$B:$B,Inputs!P:P) -> 16046 | G44: =+_xlfn.XLOOKUP($B44,Inputs!$B:$B,Inputs!Q:Q) -> 16546 | H44: =H45*H$32 -> 23558.329 | I44: =I45*I$32 -> 21102.576 | J44: =J45*J$32 -> 21978.967 | K44: =K45*K$32 -> 22928.826 | L44: =L45*L$32 -> 23955.982 | M44: =M45*M$32 -> 25261.875 | N44: =N45*N$32 -> 26034.757 | O44: =O45*O$32 -> 26833.803 | ... Q44: =Q45*Q$32 -> 28514.227
B45: % of revenue | E45: =IFERROR(E44/E32,"") -> 0.27798395 | F45: =IFERROR(F44/F32,"") -> 0.2958988 | G45: =IFERROR(G44/G32,"") -> 0.31159489 | H45: 0.35 | I45: 0.3 | J45: 0.3 | K45: 0.3 | L45: 0.3 | M45: 0.3 | N45: 0.3 | O45: 0.3 | P45: 0.3 | Q45: 0.3
B47: Other Operating (Income) Expenses | E47: =+_xlfn.XLOOKUP($B47,Inputs!$B:$B,Inputs!O:O) -> 962 | F47: =+_xlfn.XLOOKUP($B47,Inputs!$B:$B,Inputs!P:P) -> 153 | G47: =+_xlfn.XLOOKUP($B47,Inputs!$B:$B,Inputs!Q:Q) -> 716 | H47: =IFERROR(AVERAGE(E47:G47)*(1+H33),"") -> 773.64339 | I47: =IFERROR(AVERAGE(F47:H47)*(1+I33),"") -> 572.21576 | J47: =IFERROR(AVERAGE(G47:I47)*(1+J33),"") -> 715.82945 | K47: =IFERROR(AVERAGE(H47:J47)*(1+K33),"") -> 716.92934 | L47: =IFERROR(AVERAGE(I47:K47)*(1+L33),"") -> 698.26419 | M47: =IFERROR(AVERAGE(J47:L47)*(1+M33),"") -> 749.06323 | N47: =IFERROR(AVERAGE(K47:M47)*(1+N33),"") -> 743.49059 | O47: =IFERROR(AVERAGE(L47:N47)*(1+O33),"") -> 752.68583 | ... Q47: =IFERROR(AVERAGE(N47:P47)*(1+Q33),"") -> 779.22214
B49: EBITDA | E49: =+_xlfn.XLOOKUP($B49,Inputs!$B:$B,Inputs!O:O) -> 14409 | F49: =+_xlfn.XLOOKUP($B49,Inputs!$B:$B,Inputs!P:P) -> 9480 | G49: =+_xlfn.XLOOKUP($B49,Inputs!$B:$B,Inputs!Q:Q) -> 5955 | H49: =IFERROR(H38-H41-H44-H47,"") -> -7754.1799 | I49: =IFERROR(I38-I41-I44-I47,"") -> -2239.8839 | J49: =IFERROR(J38-J41-J44-J47,"") -> -987.49154 | K49: =IFERROR(K38-K41-K44-K47,"") -> -4057.5086 | L49: =IFERROR(L38-L41-L44-L47,"") -> -4188.4933 | M49: =IFERROR(M38-M41-M44-M47,"") -> -4429.5524 | N49: =IFERROR(N38-N41-N44-N47,"") -> -4536.5836 | O49: =IFERROR(O38-O41-O44-O47,"") -> -4662.1946 | ... Q49: =IFERROR(Q38-Q41-Q44-Q47,"") -> -4933.5576
B50: EBITDA Margin | E50: =IFERROR(E49/E$32,"") -> 0.22851841 | F50: =IFERROR(F49/F$32,"") -> 0.17481744 | G50: =IFERROR(G49/G$32,"") -> 0.11214478 | H50: =IFERROR(H49/H$32,"") -> -0.11520185 | I50: =IFERROR(I49/I$32,"") -> -0.031842804 | J50: =IFERROR(J49/J$32,"") -> -0.01347868 | K50: =IFERROR(K49/K$32,"") -> -0.053088308 | L50: =IFERROR(L49/L$32,"") -> -0.052452368 | ... Q50: =IFERROR(Q49/Q$32,"") -> -0.051906274
B52: D&A (Depreciation & Amortization) | E52: =+_xlfn.XLOOKUP($B52,Inputs!$B:$B,Inputs!O:O) -> 13035 | F52: =+_xlfn.XLOOKUP($B52,Inputs!$B:$B,Inputs!P:P) -> 9602 | G52: =+_xlfn.XLOOKUP($B52,Inputs!$B:$B,Inputs!Q:Q) -> 11379 | H52: =+IFERROR(H55+H58,"") -> 12721.472 | I52: =+IFERROR(I55+I58,"") -> 12267.234 | J52: =+IFERROR(J55+J58,"") -> 13170.433 | K52: =+IFERROR(K55+K58,"") -> 13944.565 | L52: =+IFERROR(L55+L58,"") -> 14364.595 | M52: =+IFERROR(M55+M58,"") -> 14748.527 | N52: =+IFERROR(N55+N58,"") -> 13943.528 | O52: =+IFERROR(O55+O58,"") -> 13884.174 | ... Q52: =+IFERROR(Q55+Q58,"") -> 14913.532
B53: % of PP&E+ROU Assets+Intangibles excl. Goodwill | E53: =IFERROR(E52/AVERAGE(Inputs!O39+Inputs!O42+Inputs!O44,Inputs!N39+Inputs!N42+Inputs!N44),"") -> 0.13054909 | F53: =IFERROR(F52/AVERAGE(Inputs!P39+Inputs!P42+Inputs!P44,Inputs!O39+Inputs!O42+Inputs!O44),"") -> 0.082180408 | G53: =IFERROR(G52/AVERAGE(Inputs!Q39+Inputs!Q42+Inputs!Q44,Inputs!P39+Inputs!P42+Inputs!P44),"") -> 0.088273626 | H53: =IFERROR(H52/(G101+G107),"") -> 0.11351666 | I53: =IFERROR(I52/(H101+H107),"") -> 0.11670569 | J53: =IFERROR(J52/(I101+I107),"") -> 0.13267014 | K53: =IFERROR(K52/(J101+J107),"") -> 0.14985038 | L53: =IFERROR(L52/(K101+K107),"") -> 0.1654914 | M53: =IFERROR(M52/(L101+L107),"") -> 0.18253654 | N53: =IFERROR(N52/(M101+M107),"") -> 0.19452152 | O53: =IFERROR(O52/(N101+N107),"") -> 0.21842372 | ... Q53: =IFERROR(Q52/(P101+P107),"") -> 0.29363292
B55: Depreciation Expense | E55: =+_xlfn.XLOOKUP($B55,Inputs!$B:$B,Inputs!O:O) -> 11128 | F55: =+_xlfn.XLOOKUP($B55,Inputs!$B:$B,Inputs!P:P) -> 7847 | G55: =+_xlfn.XLOOKUP($B55,Inputs!$B:$B,Inputs!Q:Q) -> 9951 | H55: =IFERROR(H56*(G102+G103),"") -> 11245.072 | I55: =IFERROR(I56*(H102+H103),"") -> 10319.668 | J55: =IFERROR(J56*(I102+I103),"") -> 10909.565 | K55: =IFERROR(K56*(J102+J103),"") -> 11178.343 | L55: =IFERROR(L56*(K102+K103),"") -> 11163.474 | M55: =IFERROR(M56*(L102+L103),"") -> 11469.995 | N55: =IFERROR(N56*(M102+M103),"") -> 11675.877 | O55: =IFERROR(O56*(N102+N103),"") -> 11859.504 | ... Q55: =IFERROR(Q56*(P102+P103),"") -> 12351.259
B56: % of PP&E+ROU Assets | E56: =IFERROR(E55/AVERAGE(Inputs!O40+Inputs!O42,Inputs!N40+Inputs!N42),"") -> 0.068729329 | F56: =IFERROR(F55/AVERAGE(Inputs!P40+Inputs!P42,Inputs!O40+Inputs!O42),"") -> 0.042428257 | G56: =IFERROR(G55/AVERAGE(Inputs!Q40+Inputs!Q42,Inputs!P40+Inputs!P42),"") -> 0.049052205 | H56: =IFERROR(AVERAGE(E56:G56),"") -> 0.053403263 | I56: =IFERROR(AVERAGE(F56:H56),"") -> 0.048294575 | J56: =IFERROR(AVERAGE(G56:I56),"") -> 0.050250014 | K56: =IFERROR(AVERAGE(H56:J56),"") -> 0.050649284 | L56: =IFERROR(AVERAGE(I56:K56),"") -> 0.049731291 | M56: =IFERROR(AVERAGE(J56:L56),"") -> 0.050210196 | N56: =IFERROR(AVERAGE(K56:M56),"") -> 0.050196924 | O56: =IFERROR(AVERAGE(L56:N56),"") -> 0.050046137 | ... Q56: =IFERROR(AVERAGE(N56:P56),"") -> 0.050131382
B58: Amortization Expense | E58: =+_xlfn.XLOOKUP($B58,Inputs!$B:$B,Inputs!O:O) -> 1907 | F58: =+_xlfn.XLOOKUP($B58,Inputs!$B:$B,Inputs!P:P) -> 1755 | G58: =+_xlfn.XLOOKUP($B58,Inputs!$B:$B,Inputs!Q:Q) -> 1428 | H58: =+H59*G107 -> 1476.4 | I58: =+I59*H107 -> 1947.5666 | J58: =+J59*I107 -> 2260.8675 | K58: =+K59*J107 -> 2766.2226 | L58: =+L59*K107 -> 3201.1205 | M58: =+M59*L107 -> 3278.5319 | N58: =+N59*M107 -> 2267.6513 | O58: =+O59*N107 -> 2024.6705 | ... Q58: =+Q59*P107 -> 2562.273
B59: % of Intangibles excl. Goodwill | E59: =IFERROR(E58/AVERAGE(Inputs!N45:O45),"") -> 0.28702589 | F59: =IFERROR(F58/AVERAGE(Inputs!O45:P45),"") -> 0.33091355 | G59: =IFERROR(G58/AVERAGE(Inputs!P45:Q45),"") -> 0.34492754 | H59: 0.4 | I59: 0.4 | J59: =AVERAGE(G59:I59) -> 0.38164251 | K59: =AVERAGE(H59:J59) -> 0.39388084 | L59: =AVERAGE(I59:K59) -> 0.39184112 | M59: 0.35 | N59: 0.3 | O59: 0.3 | P59: 0.3 | Q59: 0.3
B61: Operating Income (EBIT) | E61: =+_xlfn.XLOOKUP($B61,Inputs!$B:$B,Inputs!O:O) -> 1374 | F61: =+_xlfn.XLOOKUP($B61,Inputs!$B:$B,Inputs!P:P) -> -122 | G61: =+_xlfn.XLOOKUP($B61,Inputs!$B:$B,Inputs!Q:Q) -> -5424 | H61: =H49 -> -7754.1799 | I61: =I49 -> -2239.8839 | J61: =J49 -> -987.49154 | K61: =K49 -> -4057.5086 | L61: =L49 -> -4188.4933 | M61: =M49 -> -4429.5524 | N61: =N49 -> -4536.5836 | O61: =O49 -> -4662.1946 | ... Q61: =Q49 -> -4933.5576
B62: Operating Margin | E62: =IFERROR(E61/E$32,"") -> 0.021790846 | F62: =IFERROR(F61/F$32,"") -> -0.0022497603 | G62: =IFERROR(G61/G$32,"") -> -0.10214497 | H62: =IFERROR(H61/H32,"") -> -0.11520185 | I62: =IFERROR(I61/I32,"") -> -0.031842804 | J62: =IFERROR(J61/J32,"") -> -0.01347868 | K62: =IFERROR(K61/K32,"") -> -0.053088308 | L62: =IFERROR(L61/L32,"") -> -0.052452368 | M62: =IFERROR(M61/M32,"") -> -0.052603606 | N62: =IFERROR(N61/N32,"") -> -0.052275313 | O62: =IFERROR(O61/O32,"") -> -0.052123002 | ... Q62: =IFERROR(Q61/Q32,"") -> -0.051906274
B64: Net Interest Expense (Income) | E64: =+_xlfn.XLOOKUP($B64,Inputs!$B:$B,Inputs!O:O) -> -93 | F64: =+_xlfn.XLOOKUP($B64,Inputs!$B:$B,Inputs!P:P) -> -457 | G64: =+_xlfn.XLOOKUP($B64,Inputs!$B:$B,Inputs!Q:Q) -> -211 | H64: =-H67-H70 -> -1332.15 | I64: =-I67-I70 -> -1408.9249 | J64: =-J67-J70 -> -1493.6966 | K64: =-K67-K70 -> -1587.2021 | L64: =-L67-L70 -> -1634.8181 | M64: =-M67-M70 -> -1683.8627 | N64: =-N67-N70 -> -1734.3785 | O64: =-O67-O70 -> -1786.4099 | ... Q64: =-Q67-Q70 -> -1895.2023
B65: % of Net Debt | E65: =IFERROR(E64/AVERAGE(Inputs!N116:O116),"") -> -0.0096518084 | F65: =IFERROR(F64/AVERAGE(Inputs!O116:P116),"") -> -0.025336808 | G65: =IFERROR(G64/AVERAGE(Inputs!P116:Q116),"") -> -0.0089682287 | H65: =IFERROR(H64/AVERAGE(G118+G120,H118+H120),"") -> -0.023872568 | I65: =IFERROR(I64/AVERAGE(H118+H120,I118+I120),"") -> -0.022940063 | J65: =IFERROR(J64/AVERAGE(I118+I120,J118+J120),"") -> -0.02549616 | K65: =IFERROR(K64/AVERAGE(J118+J120,K118+K120),"") -> -0.027858311 | L65: =IFERROR(L64/AVERAGE(K118+K120,L118+L120),"") -> -0.030305323 | M65: =IFERROR(M64/AVERAGE(L118+L120,M118+M120),"") -> -0.032303358 | N65: =IFERROR(N64/AVERAGE(M118+M120,N118+N120),"") -> -0.034718194 | O65: =IFERROR(O64/AVERAGE(N118+N120,O118+O120),"") -> -0.037183631 | ... Q65: =IFERROR(Q64/AVERAGE(P118+P120,Q118+Q120),"")
B67: Interest Expense | E67: =+_xlfn.XLOOKUP($B67,Inputs!$B:$B,Inputs!O:O) -> 496 | F67: =+_xlfn.XLOOKUP($B67,Inputs!$B:$B,Inputs!P:P) -> 878 | G67: =+_xlfn.XLOOKUP($B67,Inputs!$B:$B,Inputs!Q:Q) -> 1034
B68: % of Debt | E68: =+IFERROR(E67/AVERAGE(Inputs!N113:O113),"") -> 0.013048854 | F68: =+IFERROR(F67/AVERAGE(Inputs!O113:P113),"") -> 0.019631957 | G68: =+IFERROR(G67/AVERAGE(Inputs!P113:Q113),"") -> 0.021964716
B70: Interest Income | E70: =+_xlfn.XLOOKUP($B70,Inputs!$B:$B,Inputs!O:O) -> 589 | F70: =+_xlfn.XLOOKUP($B70,Inputs!$B:$B,Inputs!P:P) -> 1335 | G70: =+_xlfn.XLOOKUP($B70,Inputs!$B:$B,Inputs!Q:Q) -> 1245 | H70: =G70*(1+H71) -> 1332.15 | I70: =H70*(1+I71) -> 1408.9249 | J70: =I70*(1+J71) -> 1493.6966 | K70: =J70*(1+K71) -> 1587.2021 | L70: =K70*(1+L71) -> 1634.8181 | M70: =L70*(1+M71) -> 1683.8627 | N70: =M70*(1+N71) -> 1734.3785 | O70: =N70*(1+O71) -> 1786.4099 | ... Q70: =P70*(1+Q71) -> 1895.2023
B71: % Cash & Cash Eq. & ST Investments | E71: =IFERROR(E70/+AVERAGE(Inputs!N32:O32),"") -> 0.020757343 | F71: =IFERROR(F70/+AVERAGE(Inputs!O32:P32),"") -> 0.050026231 | G71: =IFERROR(G70/+AVERAGE(Inputs!P32:Q32),"") -> 0.052870732 | H71: 0.07 | I71: =AVERAGE(F71:H71) -> 0.057632321 | J71: =AVERAGE(G71:I71) -> 0.060167684 | K71: =AVERAGE(H71:J71) -> 0.062600002 | L71: 0.03 | M71: 0.03 | N71: 0.03 | O71: 0.03 | P71: 0.03 | Q71: 0.03
B73: FX (Gain) Loss | E73: =+_xlfn.XLOOKUP($B73,Inputs!$B:$B,Inputs!O:O) -> 0 | F73: =+_xlfn.XLOOKUP($B73,Inputs!$B:$B,Inputs!P:P) -> 0 | G73: =+_xlfn.XLOOKUP($B73,Inputs!$B:$B,Inputs!Q:Q) -> 0 | H73: =+H74*H$17 -> 0 | I73: =+I74*I$17 -> 0 | J73: =+J74*J$17 -> 0 | K73: =+K74*K$17 -> 0 | L73: =+L74*L$17 -> 0 | M73: =+M74*M$17 -> 0 | N73: =+N74*N$17 -> 0 | O73: =+O74*O$17 -> 0 | ... Q73: =+Q74*Q$17 -> 0
B74: % of revenue
B76: Other Non-Operating (Income) Expenses | E76: =+_xlfn.XLOOKUP($B76,Inputs!$B:$B,Inputs!O:O) -> -1073 | F76: =+_xlfn.XLOOKUP($B76,Inputs!$B:$B,Inputs!P:P) -> -172 | G76: =+_xlfn.XLOOKUP($B76,Inputs!$B:$B,Inputs!Q:Q) -> 227 | H76: =IFERROR(AVERAGE(E76:G76)*(1+H33),"") -> -430.13051 | I76: =IFERROR(AVERAGE(F76:H76)*(1+I33),"") -> -130.67693 | J76: =IFERROR(AVERAGE(G76:I76)*(1+J33),"") -> -115.89016 | K76: =IFERROR(AVERAGE(H76:J76)*(1+K33),"") -> -235.31408 | L76: =IFERROR(AVERAGE(I76:K76)*(1+L33),"") -> -167.82276 | M76: =IFERROR(AVERAGE(J76:L76)*(1+M33),"") -> -182.4401 | N76: =IFERROR(AVERAGE(K76:M76)*(1+N33),"") -> -201.16419 | O76: =IFERROR(AVERAGE(L76:N76)*(1+O33),"") -> -189.45039 | ... Q76: =IFERROR(AVERAGE(N76:P76)*(1+Q33),"") -> -201.88631
B78: Pre-Tax Income (EBT) | E78: =+_xlfn.XLOOKUP($B78,Inputs!$B:$B,Inputs!O:O) -> 2554 | F78: =+_xlfn.XLOOKUP($B78,Inputs!$B:$B,Inputs!P:P) -> 984 | G78: =+_xlfn.XLOOKUP($B78,Inputs!$B:$B,Inputs!Q:Q) -> -4963 | H78: =IFERROR(+H61-H64-H73-H76,"") -> -5991.8994 | I78: =IFERROR(+I61-I64-I73-I76,"") -> -700.28212 | J78: =IFERROR(+J61-J64-J73-J76,"") -> 622.09527 | K78: =IFERROR(+K61-K64-K73-K76,"") -> -2234.9925 | L78: =IFERROR(+L61-L64-L73-L76,"") -> -2385.8525 | M78: =IFERROR(+M61-M64-M73-M76,"") -> -2563.2496 | N78: =IFERROR(+N61-N64-N73-N76,"") -> -2601.0409 | O78: =IFERROR(+O61-O64-O73-O76,"") -> -2686.3343 | ... Q78: =IFERROR(+Q61-Q64-Q73-Q76,"") -> -2836.469
B80: Tax Expense (Benefits) | E80: =+_xlfn.XLOOKUP($B80,Inputs!$B:$B,Inputs!O:O) -> -249 | F80: =+_xlfn.XLOOKUP($B80,Inputs!$B:$B,Inputs!P:P) -> -913 | G80: =+_xlfn.XLOOKUP($B80,Inputs!$B:$B,Inputs!Q:Q) -> 8023 | H80: =IFERROR(H81*H$61,"") -> 6828.5951 | I80: =IFERROR(I81*I$61,"") -> 2557.2323 | J80: =IFERROR(J81*J$61,"") -> 1197.7869 | K80: =IFERROR(K81*K$61,"") -> 4375.7172 | L80: =IFERROR(L81*L$61,"") -> 4793.1226 | M80: =IFERROR(M81*M$61,"") -> 5072.928 | N80: =IFERROR(N81*N$61,"") -> 5093.11 | O80: =IFERROR(O81*O$61,"") -> 5302.8986 | ... Q80: =IFERROR(Q81*Q$61,"") -> 5583.4983
B81: % of EBT | E81: =IFERROR(E80/E78,"") -> -0.097494127 | F81: =IFERROR(F80/F78,"") -> -0.92784553 | G81: =IFERROR(G80/G78,"") -> -1.6165626 | H81: =IFERROR(AVERAGE(E81:G81),"") -> -0.88063407 | I81: =IFERROR(AVERAGE(F81:H81),"") -> -1.1416807 | J81: =IFERROR(AVERAGE(G81:I81),"") -> -1.2129591 | K81: =IFERROR(AVERAGE(H81:J81),"") -> -1.0784246 | L81: =IFERROR(AVERAGE(I81:K81),"") -> -1.1443548 | M81: =IFERROR(AVERAGE(J81:L81),"") -> -1.1452462 | N81: =IFERROR(AVERAGE(K81:M81),"") -> -1.1226752 | O81: =IFERROR(AVERAGE(L81:N81),"") -> -1.1374254 | ... Q81: =IFERROR(AVERAGE(N81:P81),"") -> -1.1317387
B83: Net Income | E83: =+_xlfn.XLOOKUP($B83,Inputs!$B:$B,Inputs!O:O) -> 2803 | F83: =+_xlfn.XLOOKUP($B83,Inputs!$B:$B,Inputs!P:P) -> 1897 | G83: =+_xlfn.XLOOKUP($B83,Inputs!$B:$B,Inputs!Q:Q) -> -12986 | H83: =IFERROR(+H78-H80,"") -> -12820.494 | I83: =IFERROR(+I78-I80,"") -> -3257.5144 | J83: =IFERROR(+J78-J80,"") -> -575.6916 | K83: =IFERROR(+K78-K80,"") -> -6610.7097 | L83: =IFERROR(+L78-L80,"") -> -7178.975 | M83: =IFERROR(+M78-M80,"") -> -7636.1777 | N83: =IFERROR(+N78-N80,"") -> -7694.1509 | O83: =IFERROR(+O78-O80,"") -> -7989.2329 | ... Q83: =IFERROR(+Q78-Q80,"") -> -8419.9673
B84: Net Income Margin | E84: =IFERROR(E83/E$32,"") -> 0.04445396 | F84: =IFERROR(F83/F$32,"") -> 0.034981928 | G84: =IFERROR(G83/G$32,"") -> -0.24455283 | H84: =IFERROR(H83/H$32,"") -> -0.19047077 | I84: =IFERROR(I83/I$32,"") -> -0.046309718 | J84: =IFERROR(J83/J$32,"") -> -0.0078578524 | K84: =IFERROR(K83/K$32,"") -> -0.086494306 | L84: =IFERROR(L83/L$32,"") -> -0.089902075 | ... Q84: =IFERROR(Q83/Q$32,"") -> -0.088587013
B86: Balance Sheet | E86: =E30 -> 2022 | F86: =F30 -> 2023 | G86: =G30 -> 2024 | H86: =H30 -> 2025 | I86: =I30 -> 2026 | J86: =J30 -> 2027 | K86: =K30 -> 2028 | L86: =L30 -> 2029 | ... Q86: =Q30 -> 2034
A88: x | B88: Assets
B90: Cash & Cash Equivalents & ST Investments | E90: =+_xlfn.XLOOKUP($B90,Inputs!$B:$B,Inputs!O:O) -> 28338 | F90: =+_xlfn.XLOOKUP($B90,Inputs!$B:$B,Inputs!P:P) -> 25034 | G90: =+_xlfn.XLOOKUP($B90,Inputs!$B:$B,Inputs!Q:Q) -> 22062 | H90: =IFERROR(G90+H168,"") -> 56777.728 | I90: =IFERROR(H90+I168,"") -> 80702.745 | J90: =IFERROR(I90+J168,"") -> 111291.78 | K90: =IFERROR(J90+K168,"") -> 137371.96 | L90: =IFERROR(K90+L168,"") -> 159559.13 | M90: =IFERROR(L90+M168,"") -> 184494.54 | N90: =IFERROR(M90+N168,"") -> 207363.24 | O90: =IFERROR(N90+O168,"") -> 229576.53 | ... Q90: =IFERROR(P90+Q168,"") -> 276357.79
B92: Accounts Receivable | E92: =+_xlfn.XLOOKUP($B92,Inputs!$B:$B,Inputs!O:O) -> 4133 | F92: =+_xlfn.XLOOKUP($B92,Inputs!$B:$B,Inputs!P:P) -> 3402 | G92: =+_xlfn.XLOOKUP($B92,Inputs!$B:$B,Inputs!Q:Q) -> 3478 | H92: =IFERROR(H93*H32/365,"") -> 4420.7049 | I92: =IFERROR(I93*I32/365,"") -> 4550.8797 | J92: =IFERROR(J93*J32/365,"") -> 4787.7785 | K92: =IFERROR(K93*K32/365,"") -> 4986.3621 | L92: =IFERROR(L93*L32/365,"") -> 5198.1371 | M92: =IFERROR(M93*M32/365,"") -> 5492.7139 | N92: =IFERROR(N93*N32/365,"") -> 5657.26 | O92: =IFERROR(O93*O32/365,"") -> 5829.3254 | ... Q92: =IFERROR(Q93*Q32/365,"") -> 6195.7273
B93: DSO | E93: =IFERROR(E92/E32*365,"") -> 23.924652 | F93: =IFERROR(F92/F32*365,"") -> 22.898318 | G93: =IFERROR(G92/G32*366,"") -> 23.972204 | H93: =G93 -> 23.972204 | I93: =IFERROR(AVERAGE(F93:H93),"") -> 23.614242 | J93: =IFERROR(AVERAGE(G93:I93),"") -> 23.852883 | K93: =IFERROR(AVERAGE(H93:J93),"") -> 23.81311 | L93: =IFERROR(AVERAGE(I93:K93),"") -> 23.760078 | M93: =IFERROR(AVERAGE(J93:L93),"") -> 23.80869 | N93: =IFERROR(AVERAGE(K93:M93),"") -> 23.79396 | O93: =IFERROR(AVERAGE(L93:N93),"") -> 23.787576 | P93: =IFERROR(AVERAGE(M93:O93),"") -> 23.796742 | Q93: =IFERROR(AVERAGE(N93:P93),"") -> 23.792759
B95: Inventory | E95: =+_xlfn.XLOOKUP($B95,Inputs!$B:$B,Inputs!O:O) -> 13224 | F95: =+_xlfn.XLOOKUP($B95,Inputs!$B:$B,Inputs!P:P) -> 11127 | G95: =+_xlfn.XLOOKUP($B95,Inputs!$B:$B,Inputs!Q:Q) -> 12198 | H95: =+IFERROR(H96*H35/365,"") -> 14925.521 | I95: =+IFERROR(I96*I35/365,"") -> 14893.223 | J95: =+IFERROR(J96*J35/365,"") -> 15001.156 | K95: =+IFERROR(K96*K35/365,"") -> 16694.646 | L95: =+IFERROR(L96*L35/365,"") -> 17445.163 | M95: =+IFERROR(M96*M35/365,"") -> 18393.588 | N95: =+IFERROR(N96*N35/365,"") -> 18957.133 | O95: =+IFERROR(O96*O35/365,"") -> 19539.311 | ... Q95: =+IFERROR(Q96*Q35/365,"") -> 20762.622
B96: DIH | E96: =IFERROR(E95/E35*365,"") -> 133.38013 | F96: =IFERROR(F95/F35*365,"") -> 124.89944 | G96: =IFERROR(G95/G35*365,"") -> 124.51812 | H96: =G96 -> 124.51812 | I96: =IFERROR(AVERAGE(F96:H96),"") -> 124.64523 | J96: =IFERROR(AVERAGE(G96:I96),"") -> 124.56049 | K96: =IFERROR(AVERAGE(H96:J96),"") -> 124.57461 | L96: =IFERROR(AVERAGE(I96:K96),"") -> 124.59344 | M96: =IFERROR(AVERAGE(J96:L96),"") -> 124.57618 | N96: =IFERROR(AVERAGE(K96:M96),"") -> 124.58141 | O96: =IFERROR(AVERAGE(L96:N96),"") -> 124.58368 | P96: =IFERROR(AVERAGE(M96:O96),"") -> 124.58043 | Q96: =IFERROR(AVERAGE(N96:P96),"") -> 124.58184
B98: Prepaid expenses and Other Current Assets | E98: =+_xlfn.XLOOKUP($B98,Inputs!$B:$B,Inputs!O:O) -> 4712 | F98: =+_xlfn.XLOOKUP($B98,Inputs!$B:$B,Inputs!P:P) -> 3706 | G98: =+_xlfn.XLOOKUP($B98,Inputs!$B:$B,Inputs!Q:Q) -> 9586 | H98: =IFERROR(AVERAGE(E98:G98)*(1+H99),"") -> 7084.7175 | I98: =IFERROR(AVERAGE(F98:H98)*(1+I99),"") -> 7764.4098 | J98: =IFERROR(AVERAGE(G98:I98)*(1+J99),"") -> 9513.8913 | K98: =IFERROR(AVERAGE(H98:J98)*(1+K99),"") -> 9452.0735 | L98: =IFERROR(AVERAGE(I98:K98)*(1+L99),"") -> 10321.171 | M98: =IFERROR(AVERAGE(J98:L98)*(1+M99),"") -> 11357.967 | N98: =IFERROR(AVERAGE(K98:M98)*(1+N99),"") -> 12057.157 | O98: =IFERROR(AVERAGE(L98:N98)*(1+O99),"") -> 13058.61 | ... Q98: =IFERROR(AVERAGE(N98:P98)*(1+Q99),"") -> 15198.238
B99: % of revenue | E99: =IFERROR(E98/E$32,"") -> 0.074729597 | F99: =IFERROR(F98/F$32,"") -> 0.068341078 | G99: =IFERROR(G98/G$32,"") -> 0.18052391 | H99: =G99 -> 0.18052391 | I99: =IFERROR(AVERAGE(F99:H99),"") -> 0.14312963 | J99: =IFERROR(AVERAGE(G99:I99),"") -> 0.16805915 | K99: =IFERROR(AVERAGE(H99:J99),"") -> 0.16390423 | L99: =IFERROR(AVERAGE(I99:K99),"") -> 0.15836434 | M99: =IFERROR(AVERAGE(J99:L99),"") -> 0.16344257 | N99: =IFERROR(AVERAGE(K99:M99),"") -> 0.16190371 | O99: =IFERROR(AVERAGE(L99:N99),"") -> 0.16123687 | P99: =IFERROR(AVERAGE(M99:O99),"") -> 0.16219439 | Q99: =IFERROR(AVERAGE(N99:P99),"") -> 0.16177832
B101: Net PP&E (Property, Plant and Equipment) + ROU Assets | E101: =+E102+E103-E105 -> 81347 | F101: =+F102+F103-F105 -> 97152 | G101: =+G102+G103-G105 -> 108376 | H101: =IFERROR(H102+H103-H105,"") -> 100243.65 | I101: =IFERROR(I102+I103-I105,"") -> 93347.972 | J101: =IFERROR(J102+J103-J105,"") -> 86033.599 | K101: =IFERROR(K102+K103-K105,"") -> 78630.207 | L101: =IFERROR(L102+L103-L105,"") -> 71430.432 | M101: =IFERROR(M102+M103-M105,"") -> 64122.321 | N101: =IFERROR(N102+N103-N105,"") -> 56816.422 | O101: =IFERROR(O102+O103-O105,"") -> 49545.395 | ... Q101: =IFERROR(Q102+Q103-Q105,"") -> 34956.341
B102: Gross PP&E (Property, Plant and Equipment) + ROU Assets | E102: =+_xlfn.XLOOKUP("Gross PP&E (Property, Plant and Equipment)",Inputs!$B:$B,Inputs!O:O) -> 174733 | F102: =+_xlfn.XLOOKUP("Gross PP&E (Property, Plant and Equipment)",Inputs!$B:$B,Inputs!P:P) -> 195162 | G102: =+_xlfn.XLOOKUP("Gross PP&E (Property, Plant and Equipment)",Inputs!$B:$B,Inputs!Q:Q) -> 210569 | H102: =+IFERROR(G102-H136,"") -> 213681.72 | I102: =+IFERROR(H102-I136,"") -> 217105.71 | J102: =+IFERROR(I102-J136,"") -> 220700.9 | K102: =+IFERROR(J102-K136,"") -> 224475.85 | L102: =+IFERROR(K102-L136,"") -> 228439.55 | M102: =+IFERROR(L102-M136,"") -> 232601.44 | N102: =+IFERROR(M102-N136,"") -> 236971.42 | O102: =+IFERROR(N102-O136,"") -> 241559.89 | ... Q102: =+IFERROR(P102-Q136,"") -> 251436.59
B103: Right-of-Use Assets | E103: =+_xlfn.XLOOKUP("Right-of-Use Assets",Inputs!$B:$B,Inputs!O:O) -> 0 | F103: =+_xlfn.XLOOKUP("Right-of-Use Assets",Inputs!$B:$B,Inputs!P:P) -> 0 | G103: =+_xlfn.XLOOKUP("Right-of-Use Assets",Inputs!$B:$B,Inputs!Q:Q) -> 0 | H103: =IFERROR(H104*H$32,"") -> 0 | I103: =IFERROR(I104*I$32,"") -> 0 | J103: =IFERROR(J104*J$32,"") -> 0 | K103: =IFERROR(K104*K$32,"") -> 0 | L103: =IFERROR(L104*L$32,"") -> 0 | M103: =IFERROR(M104*M$32,"") -> 0 | N103: =IFERROR(N104*N$32,"") -> 0 | O103: =IFERROR(O104*O$32,"") -> 0 | ... Q103: =IFERROR(Q104*Q$32,"") -> 0
B104: % of revenue | E104: =IFERROR(E103/E$32,"") -> 0 | F104: =IFERROR(F103/F$32,"") -> 0 | G104: =IFERROR(G103/G$32,"") -> 0 | H104: =IFERROR(AVERAGE(E104:G104),"") -> 0 | I104: =IFERROR(AVERAGE(F104:H104),"") -> 0 | J104: =IFERROR(AVERAGE(G104:I104),"") -> 0 | K104: =IFERROR(AVERAGE(H104:J104),"") -> 0 | L104: =IFERROR(AVERAGE(I104:K104),"") -> 0 | M104: =IFERROR(AVERAGE(J104:L104),"") -> 0 | N104: =IFERROR(AVERAGE(K104:M104),"") -> 0 | O104: =IFERROR(AVERAGE(L104:N104),"") -> 0 | ... Q104: =IFERROR(AVERAGE(N104:P104),"") -> 0
B105: Accumulated Depreciation | E105: =+_xlfn.XLOOKUP($B105,Inputs!$B:$B,Inputs!O:O) -> 93386 | F105: =+_xlfn.XLOOKUP($B105,Inputs!$B:$B,Inputs!P:P) -> 98010 | G105: =+_xlfn.XLOOKUP($B105,Inputs!$B:$B,Inputs!Q:Q) -> 102193 | H105: =+IFERROR(G105+H55,"") -> 113438.07 | I105: =+IFERROR(H105+I55,"") -> 123757.74 | J105: =+IFERROR(I105+J55,"") -> 134667.3 | K105: =+IFERROR(J105+K55,"") -> 145845.65 | L105: =+IFERROR(K105+L55,"") -> 157009.12 | M105: =+IFERROR(L105+M55,"") -> 168479.12 | N105: =+IFERROR(M105+N55,"") -> 180154.99 | O105: =+IFERROR(N105+O55,"") -> 192014.5 | ... Q105: =+IFERROR(P105+Q55,"") -> 216480.25
B107: Intangibles excl. Goodwill | E107: =+_xlfn.XLOOKUP($B107,Inputs!$B:$B,Inputs!O:O) -> 6018 | F107: =+_xlfn.XLOOKUP($B107,Inputs!$B:$B,Inputs!P:P) -> 4589 | G107: =+_xlfn.XLOOKUP($B107,Inputs!$B:$B,Inputs!Q:Q) -> 3691 | H107: =+G107+H108*H44 -> 4868.9164 | I107: =+H107+I108*I44 -> 5924.0452 | J107: =+I107+J108*J44 -> 7022.9936 | K107: =+J107+K108*K44 -> 8169.4349 | L107: =+K107+L108*L44 -> 9367.234 | M107: =+L107+M108*M44 -> 7558.8376 | N107: =+M107+N108*N44 -> 6748.9016 | O107: =+N107+O108*O44 -> 7157.9119 | ... Q107: =+P107+Q108*Q44 -> 9966.6214
B108: growing with % of R&D | E108: =IFERROR((E107-Inputs!N45)/E44,"") -> -0.071428571 | F108: =IFERROR((F107-E107)/F44,"") -> -0.089056463 | G108: =IFERROR((G107-F107)/G44,"") -> -0.054272936 | H108: 0.05 | I108: 0.05 | J108: 0.05 | K108: 0.05 | L108: 0.05 | M108: =AVERAGE(E108:G108) -> -0.07158599 | N108: =AVERAGE(F108:H108) -> -0.0311098 | O108: =AVERAGE(G108:I108) -> 0.015242355 | P108: =AVERAGE(H108:J108) -> 0.05 | Q108: =AVERAGE(I108:K108) -> 0.05
B110: Liabilities
B112: Accounts Payable | E112: =+_xlfn.XLOOKUP($B112,Inputs!$B:$B,Inputs!O:O) -> 9595 | F112: =+_xlfn.XLOOKUP($B112,Inputs!$B:$B,Inputs!P:P) -> 8578 | G112: =+_xlfn.XLOOKUP($B112,Inputs!$B:$B,Inputs!Q:Q) -> 12556 | H112: =+IFERROR(H113*H35/365,"") -> 15405.663 | I112: =+IFERROR(I113*I35/365,"") -> 14072.721 | J112: =+IFERROR(J113*J35/365,"") -> 15047.093 | K112: =+IFERROR(K113*K35/365,"") -> 16583.867 | L112: =+IFERROR(L113*L35/365,"") -> 17103.887 | M112: =+IFERROR(M113*M35/365,"") -> 18251.717 | N112: =+IFERROR(N113*N35/365,"") -> 18742.837 | O112: =+IFERROR(O113*O35/365,"") -> 19288.029 | ... Q112: =+IFERROR(Q113*Q35/365,"") -> 20521.841
B113: DPO | E113: =IFERROR(E112/E$35*365,"") -> 96.777247 | F113: =IFERROR(F112/F$35*365,"") -> 96.287173 | G113: =IFERROR(G112/G$35*366,"") -> 128.52377 | H113: =G113 -> 128.52377 | I113: =IFERROR(AVERAGE(F113:H113),"") -> 117.77824 | J113: =IFERROR(AVERAGE(G113:I113),"") -> 124.94193 | K113: =IFERROR(AVERAGE(H113:J113),"") -> 123.74798 | L113: =IFERROR(AVERAGE(I113:K113),"") -> 122.15605 | M113: =IFERROR(AVERAGE(J113:L113),"") -> 123.61532 | N113: =IFERROR(AVERAGE(K113:M113),"") -> 123.17312 | O113: =IFERROR(AVERAGE(L113:N113),"") -> 122.98149 | P113: =IFERROR(AVERAGE(M113:O113),"") -> 123.25664 | Q113: =IFERROR(AVERAGE(N113:P113),"") -> 123.13708
B115: Accrued Expenses and Other Current Liabilities | E115: =+_xlfn.XLOOKUP($B115,Inputs!$B:$B,Inputs!O:O) -> 18443 | F115: =+_xlfn.XLOOKUP($B115,Inputs!$B:$B,Inputs!P:P) -> 19333 | G115: =+_xlfn.XLOOKUP($B115,Inputs!$B:$B,Inputs!Q:Q) -> 22929 | H115: =IFERROR(AVERAGE(E115:G115)*(1+H33),"") -> 25649.384 | I115: =IFERROR(AVERAGE(F115:H115)*(1+I33),"") -> 23656.969 | J115: =IFERROR(AVERAGE(G115:I115)*(1+J33),"") -> 25078.431 | K115: =IFERROR(AVERAGE(H115:J115)*(1+K33),"") -> 25866.484 | L115: =IFERROR(AVERAGE(I115:K115)*(1+L33),"") -> 25981.29 | M115: =IFERROR(AVERAGE(J115:L115)*(1+M33),"") -> 27039.873 | N115: =IFERROR(AVERAGE(K115:M115)*(1+N33),"") -> 27100.4 | O115: =IFERROR(AVERAGE(L115:N115)*(1+O33),"") -> 27526.871 | ... Q115: =IFERROR(AVERAGE(N115:P115)*(1+Q33),"") -> 28413.848
B116: growing with revenue | E116: =IFERROR(E115/E$32,"") -> 0.29249532 | F116: =IFERROR(F115/F$32,"") -> 0.35651324 | G116: =IFERROR(G115/G$32,"") -> 0.43179978 | H116: =G116 -> 0.43179978 | I116: =IFERROR(I115/I$32,"") -> 0.33631396 | J116: =IFERROR(J115/J$32,"") -> 0.34230586 | K116: =IFERROR(K115/K$32,"") -> 0.33843621 | L116: =IFERROR(L115/L$32,"") -> 0.32536286 | M116: =IFERROR(M115/M$32,"") -> 0.3211148 | N116: =IFERROR(N115/N$32,"") -> 0.31227946 | O116: =IFERROR(O115/O$32,"") -> 0.30774845 | P116: =IFERROR(P115/P$32,"") -> 0.30434428 | Q116: =IFERROR(Q115/Q$32,"") -> 0.29894391
B118: Total Borrowings | E118: =+_xlfn.XLOOKUP($B118,Inputs!$B:$B,Inputs!O:O) -> 41628 | F118: =+_xlfn.XLOOKUP($B118,Inputs!$B:$B,Inputs!P:P) -> 46978 | G118: =+_xlfn.XLOOKUP($B118,Inputs!$B:$B,Inputs!Q:Q) -> 46282 | H118: =IFERROR(G118+H159-H161,"") -> 64280 | I118: =IFERROR(H118+I159-I161,"") -> 57379.634 | J118: =IFERROR(I118+J159-J161,"") -> 58569.257 | K118: =IFERROR(J118+K159-K161,"") -> 54096.099 | L118: =IFERROR(K118+L159-L161,"") -> 52459.268 | M118: =IFERROR(L118+M159-M161,"") -> 50393.07 | N118: =IFERROR(M118+N159-N161,"") -> 48056.955 | O118: =IFERROR(N118+O159-O161,"") -> 46523.536 | P118: =IFERROR(O118+P159-P161,"") -> 44359.425 | Q118: S
B120: Total Leases | E120: =+_xlfn.XLOOKUP($B120,Inputs!$B:$B,Inputs!O:O) -> 409 | F120: =+_xlfn.XLOOKUP($B120,Inputs!$B:$B,Inputs!P:P) -> 431 | G120: =+_xlfn.XLOOKUP($B120,Inputs!$B:$B,Inputs!Q:Q) -> 460 | H120: =+IFERROR(H121*H32,"") -> 583.08459 | I120: =+IFERROR(I121*I32,"") -> 592.59309 | J120: =+IFERROR(J121*J32,"") -> 628.84121 | K120: =+IFERROR(K121*K32,"") -> 653.99423 | L120: =+IFERROR(L121*L32,"") -> 680.47282 | M120: =+IFERROR(M121*M32,"") -> 720.29161 | N120: =+IFERROR(N121*N32,"") -> 741.47785 | O120: =+IFERROR(O121*O32,"") -> 763.85486 | ... Q120: =+IFERROR(Q121*Q32,"") -> 812.01796
B121: % of revenues | E121: =IFERROR(E120/E$32,"") -> 0.0064865036 | F121: =IFERROR(F120/F$32,"") -> 0.0079479236 | G121: =IFERROR(G120/G$32,"") -> 0.008662737 | H121: =G121 -> 0.008662737 | I121: =+IFERROR(AVERAGE(F121:H121),"") -> 0.0084244659 | J121: =+IFERROR(AVERAGE(G121:I121),"") -> 0.0085833133 | K121: =+IFERROR(AVERAGE(H121:J121),"") -> 0.0085568388 | L121: =+IFERROR(AVERAGE(I121:K121),"") -> 0.0085215393 | M121: =+IFERROR(AVERAGE(J121:L121),"") -> 0.0085538971 | N121: =+IFERROR(AVERAGE(K121:M121),"") -> 0.0085440917 | O121: =+IFERROR(AVERAGE(L121:N121),"") -> 0.0085398427 | P121: =+IFERROR(AVERAGE(M121:O121),"") -> 0.0085459439 | Q121: =+IFERROR(AVERAGE(N121:P121),"") -> 0.0085432928
B123: Cash Flow | E123: =E30 -> 2022 | F123: =F30 -> 2023 | G123: =G30 -> 2024 | H123: =H30 -> 2025 | I123: =I30 -> 2026 | J123: =J30 -> 2027 | K123: =K30 -> 2028 | L123: =L30 -> 2029 | ... Q123: =Q30 -> 2034
A125: x | B125: D&A (Depreciation & Amortization) | E125: =+E52 -> 13035 | F125: =+F52 -> 9602 | G125: =+G52 -> 11379 | H125: =+H52 -> 12721.472 | I125: =+I52 -> 12267.234 | J125: =+J52 -> 13170.433 | K125: =+K52 -> 13944.565 | L125: =+L52 -> 14364.595 | ... Q125: =+Q52 -> 14913.532
B127: Stock Based Compensation | E127: =+_xlfn.XLOOKUP($B127,Inputs!$B:$B,Inputs!O:O) -> 3128 | F127: =+_xlfn.XLOOKUP($B127,Inputs!$B:$B,Inputs!P:P) -> 3229 | G127: =+_xlfn.XLOOKUP($B127,Inputs!$B:$B,Inputs!Q:Q) -> 3410 | H127: =IFERROR(H128*H41,"") -> 3813.86 | I127: =IFERROR(I128*I41,"") -> 4227.9408 | J127: =IFERROR(J128*J41,"") -> 4419.8322 | K127: =IFERROR(K128*K41,"") -> 4511.7615 | L127: =IFERROR(L128*L41,"") -> 4776.9671 | M127: =IFERROR(M128*M41,"") -> 5029.4052 | N127: =IFERROR(N128*N41,"") -> 5165.8965 | O127: =IFERROR(O128*O41,"") -> 5339.2097 | ... Q127: =IFERROR(Q128*Q41,"") -> 5666.9685
B128: % of SG&A | E128: =+IFERROR(E127/E41,"") -> 0.44672951 | F128: =+IFERROR(F127/F41,"") -> 0.57312744 | G128: =+IFERROR(G127/G41,"") -> 0.61921191 | H128: =IFERROR(AVERAGE(E128:G128),"") -> 0.54635629 | I128: =IFERROR(AVERAGE(F128:H128),"") -> 0.57956521 | J128: =IFERROR(AVERAGE(G128:I128),"") -> 0.58171114 | K128: =IFERROR(AVERAGE(H128:J128),"") -> 0.56921088 | L128: =IFERROR(AVERAGE(I128:K128),"") -> 0.57682908 | M128: =IFERROR(AVERAGE(J128:L128),"") -> 0.57591703 | N128: =IFERROR(AVERAGE(K128:M128),"") -> 0.57398566 | O128: =IFERROR(AVERAGE(L128:N128),"") -> 0.57557726 | ... Q128: =IFERROR(AVERAGE(N128:P128),"") -> 0.57490763
B130: Changes in Net Working Capital | E130: =+_xlfn.XLOOKUP($B130,Inputs!$B:$B,Inputs!O:O) -> -3230 | F130: =+_xlfn.XLOOKUP($B130,Inputs!$B:$B,Inputs!P:P) -> -2118 | G130: =+_xlfn.XLOOKUP($B130,Inputs!$B:$B,Inputs!Q:Q) -> -1120 | H130: =IFERROR(-((H92+H95+H98-H112-H115)-(G92+G95+G98-G112-G115)),"") -> 4401.1037 | I130: =IFERROR(-((I92+I95+I98-I112-I115)-(H92+H95+H98-H112-H115)),"") -> -4102.9253 | J130: =IFERROR(-((J92+J95+J98-J112-J115)-(I92+I95+I98-I112-I115)),"") -> 301.52051 | K130: =IFERROR(-((K92+K95+K98-K112-K115)-(J92+J95+J98-J112-J115)),"") -> 494.56914 | L130: =IFERROR(-((L92+L95+L98-L112-L115)-(K92+K95+K98-K112-K115)),"") -> -1196.5626 | M130: =IFERROR(-((M92+M95+M98-M112-M115)-(L92+L95+L98-L112-L115)),"") -> -73.383786 | N130: =IFERROR(-((N92+N95+N98-N112-N115)-(M92+M95+M98-M112-M115)),"") -> -875.63457 | O130: =IFERROR(-((O92+O95+O98-O112-O115)-(N92+N95+N98-N112-N115)),"") -> -784.03291 | ... Q130: =IFERROR(-((Q92+Q95+Q98-Q112-Q115)-(P92+P95+P98-P112-P115)),"") -> -926.42295
B132: Other Operating Adjustments | E132: =+_xlfn.XLOOKUP($B132,Inputs!$B:$B,Inputs!O:O) -> -303 | F132: =+_xlfn.XLOOKUP($B132,Inputs!$B:$B,Inputs!P:P) -> -1139 | G132: =+_xlfn.XLOOKUP($B132,Inputs!$B:$B,Inputs!Q:Q) -> 7605 | H132: =IFERROR(AVERAGE(E132:G132)*(1+H33),"") -> 2604.022 | I132: =IFERROR(AVERAGE(F132:H132)*(1+I33),"") -> 3159.5473 | J132: =IFERROR(AVERAGE(G132:I132)*(1+J33),"") -> 4641.2557 | K132: =IFERROR(AVERAGE(H132:J132)*(1+K33),"") -> 3618.1625 | L132: =IFERROR(AVERAGE(I132:K132)*(1+L33),"") -> 3976.8359 | M132: =IFERROR(AVERAGE(J132:L132)*(1+M33),"") -> 4301.093 | N132: =IFERROR(AVERAGE(K132:M132)*(1+N33),"") -> 4086.6833 | O132: =IFERROR(AVERAGE(L132:N132)*(1+O33),"") -> 4248.0335 | ... Q132: =IFERROR(AVERAGE(N132:P132)*(1+Q33),"") -> 4355.9442
B134: Operating Cash Flow | E134: =+_xlfn.XLOOKUP($B134,Inputs!$B:$B,Inputs!O:O) -> 15433 | F134: =+_xlfn.XLOOKUP($B134,Inputs!$B:$B,Inputs!P:P) -> 11471 | G134: =+_xlfn.XLOOKUP($B134,Inputs!$B:$B,Inputs!Q:Q) -> 8288 | H134: =IFERROR(H83+H125+H127+H130+H132,"") -> 10719.963 | I134: =IFERROR(I83+I125+I127+I130+I132,"") -> 12294.283 | J134: =IFERROR(J83+J125+J127+J130+J132,"") -> 21957.349 | K134: =IFERROR(K83+K125+K127+K130+K132,"") -> 15958.349 | L134: =IFERROR(L83+L125+L127+L130+L132,"") -> 14742.86 | M134: =IFERROR(M83+M125+M127+M130+M132,"") -> 16369.464 | N134: =IFERROR(N83+N125+N127+N130+N132,"") -> 14626.322 | O134: =IFERROR(O83+O125+O127+O130+O132,"") -> 14698.152 | ... Q134: =IFERROR(Q83+Q125+Q127+Q130+Q132,"") -> 15590.055
B136: Net CapEx | E136: =+_xlfn.XLOOKUP($B136,Inputs!$B:$B,Inputs!O:O) -> -25050 | F136: =+_xlfn.XLOOKUP($B136,Inputs!$B:$B,Inputs!P:P) -> -25750 | G136: =+_xlfn.XLOOKUP($B136,Inputs!$B:$B,Inputs!Q:Q) -> -23944 | H136: =IFERROR(H138+H141,"") -> -3112.72 | I136: =IFERROR(I138+I141,"") -> -3423.992 | J136: =IFERROR(J138+J141,"") -> -3595.1916 | K136: =IFERROR(K138+K141,"") -> -3774.9512 | L136: =IFERROR(L138+L141,"") -> -3963.6987 | M136: =IFERROR(M138+M141,"") -> -4161.8837 | N136: =IFERROR(N138+N141,"") -> -4369.9779 | O136: =IFERROR(O138+O141,"") -> -4588.4768 | ... Q136: =IFERROR(Q138+Q141,"") -> -5058.7956
B138: Acquisition of Fixed & Intangibles | E138: =+_xlfn.XLOOKUP($B138,Inputs!$B:$B,Inputs!O:O) -> -25050 | F138: =+_xlfn.XLOOKUP($B138,Inputs!$B:$B,Inputs!P:P) -> -25750 | G138: =+_xlfn.XLOOKUP($B138,Inputs!$B:$B,Inputs!Q:Q) -> -23944 | H138: =G138*H139 -> -3112.72 | I138: =H138*(1+I139) -> -3423.992 | J138: =I138*(1+J139) -> -3595.1916 | K138: =J138*(1+K139) -> -3774.9512 | L138: =K138*(1+L139) -> -3963.6987 | M138: =L138*(1+M139) -> -4161.8837 | N138: =M138*(1+N139) -> -4369.9779 | O138: =N138*(1+O139) -> -4588.4768 | P138: =O138*(1+P139) -> -4817.9006 | Q138: =P138*(1+Q139) -> -5058.7956
B139: Growth rate % | F139: =F138/E138-1 -> 0.027944112 | G139: =G138/F138-1 -> -0.070135922 | H139: 0.13 | I139: 0.1 | J139: 0.05 | K139: 0.05 | L139: 0.05 | M139: 0.05 | N139: 0.05 | O139: 0.05 | P139: 0.05 | Q139: 0.05
B141: Disposal of Fixed & Intangibles | E141: =+_xlfn.XLOOKUP($B141,Inputs!$B:$B,Inputs!O:O) -> 0 | F141: =+_xlfn.XLOOKUP($B141,Inputs!$B:$B,Inputs!P:P) -> 0 | G141: =+_xlfn.XLOOKUP($B141,Inputs!$B:$B,Inputs!Q:Q) -> 0 | H141: =IFERROR(H142*G102,"") -> 0 | I141: =IFERROR(I142*H102,"") -> 0 | J141: =IFERROR(J142*I102,"") -> 0 | K141: =IFERROR(K142*J102,"") -> 0 | L141: =IFERROR(L142*K102,"") -> 0 | M141: =IFERROR(M142*L102,"") -> 0 | N141: =IFERROR(N142*M102,"") -> 0 | O141: =IFERROR(O142*N102,"") -> 0 | ... Q141: =IFERROR(Q142*P102,"") -> 0
B142: Disposal Rate (% Gross PP&E) | E142: =IFERROR(E141/E102,"") -> 0 | F142: =IFERROR(F141/F102,"") -> 0 | G142: =IFERROR(G141/G102,"") -> 0 | H142: =IFERROR(AVERAGE(E142:G142),"") -> 0 | I142: =IFERROR(AVERAGE(F142:H142),"") -> 0 | J142: =IFERROR(AVERAGE(G142:I142),"") -> 0 | K142: =IFERROR(AVERAGE(H142:J142),"") -> 0 | L142: =IFERROR(AVERAGE(I142:K142),"") -> 0 | M142: =IFERROR(AVERAGE(J142:L142),"") -> 0 | N142: =IFERROR(AVERAGE(K142:M142),"") -> 0 | O142: =IFERROR(AVERAGE(L142:N142),"") -> 0 | ... Q142: =IFERROR(AVERAGE(N142:P142),"") -> 0
B144: Net Cash from Investments & Acquisitions | E144: =+_xlfn.XLOOKUP($B144,Inputs!$B:$B,Inputs!O:O) -> 11030 | F144: =+_xlfn.XLOOKUP($B144,Inputs!$B:$B,Inputs!P:P) -> 73 | G144: =+_xlfn.XLOOKUP($B144,Inputs!$B:$B,Inputs!Q:Q) -> -82 | H144: 0 | I144: 0 | J144: 0 | K144: 0 | L144: 0 | M144: 0 | N144: 0 | O144: 0 | P144: 0 | Q144: 0
B146: Other Investing Inflows (Outflows) | E146: =+_xlfn.XLOOKUP($B146,Inputs!$B:$B,Inputs!O:O) -> 3789 | F146: =+_xlfn.XLOOKUP($B146,Inputs!$B:$B,Inputs!P:P) -> 1636 | G146: =+_xlfn.XLOOKUP($B146,Inputs!$B:$B,Inputs!Q:Q) -> 5770 | H146: =IFERROR(AVERAGE(E146:G146)*(1+H33),"") -> 4730.1681 | I146: =IFERROR(AVERAGE(F146:H146)*(1+I33),"") -> 4227.6411 | J146: =IFERROR(AVERAGE(G146:I146)*(1+J33),"") -> 5113.1521 | K146: =IFERROR(AVERAGE(H146:J146)*(1+K33),"") -> 4893.0207 | L146: =IFERROR(AVERAGE(I146:K146)*(1+L33),"") -> 4957.1515 | M146: =IFERROR(AVERAGE(J146:L146)*(1+M33),"") -> 5259.6692 | N146: =IFERROR(AVERAGE(K146:M146)*(1+N33),"") -> 5190.708 | O146: =IFERROR(AVERAGE(L146:N146)*(1+O33),"") -> 5293.4696 | ... Q146: =IFERROR(AVERAGE(N146:P146)*(1+Q33),"") -> 5461.5231
B148: Investing Cash Flow | E148: =+_xlfn.XLOOKUP($B148,Inputs!$B:$B,Inputs!O:O) -> -10231 | F148: =+_xlfn.XLOOKUP($B148,Inputs!$B:$B,Inputs!P:P) -> -24041 | G148: =+_xlfn.XLOOKUP($B148,Inputs!$B:$B,Inputs!Q:Q) -> -18256 | H148: =IFERROR(+H136+H144+H146,"") -> 1617.4481 | I148: =IFERROR(+I136+I144+I146,"") -> 803.64908 | J148: =IFERROR(+J136+J144+J146,"") -> 1517.9605 | K148: =IFERROR(+K136+K144+K146,"") -> 1118.0695 | L148: =IFERROR(+L136+L144+L146,"") -> 993.45272 | M148: =IFERROR(+M136+M144+M146,"") -> 1097.7856 | N148: =IFERROR(+N136+N144+N146,"") -> 820.73017 | O148: =IFERROR(+O136+O144+O146,"") -> 704.99286 | ... Q148: =IFERROR(+Q136+Q144+Q146,"") -> 402.72745
...

Sheet Inputs
B2: Inputs
B3: in millions of USD
A4: x | B4: Income Statement | G4: 2014 | H4: =+G4+1 -> 2015 | I4: =+H4+1 -> 2016 | J4: =+I4+1 -> 2017 | K4: =+J4+1 -> 2018 | L4: =+K4+1 -> 2019 | M4: =+L4+1 -> 2020 | N4: =+M4+1 -> 2021 | O4: =+N4+1 -> 2022 | ... Q4: =+P4+1 -> 2024 | R4: ="CAGR "&$G$4&" - "&$Q$4 -> CAGR 2014 - 2024
B6: Revenue (Sales) | G6: =IS!C6 -> 55870 | H6: =IS!D6 -> 55355 | I6: =IS!E6 -> 59387 | J6: =IS!F6 -> 62761 | K6: =IS!G6 -> 70848 | L6: =IS!H6 -> 67906 | M6: =IS!I6 -> 72900 | N6: =IS!J6 -> 74718 | ... Q6: =IS!M6 -> 53101 | R6: =IFERROR((Q6/G6)^(1/COUNT($G$4:$Q$4))-1,"") -> -0.0046104123
B7: COGS (Cost of Goods Sold) | G7: =IS!C8 -> 20261 | H7: =IS!D8 -> 20676 | I7: =IS!E8 -> 23154 | J7: =IS!F8 -> 23663 | K7: =IS!G8 -> 27111 | L7: =IS!H8 -> 29825 | M7: =IS!I8 -> 30812 | N7: =IS!J8 -> 32898 | ... Q7: =IS!M8 -> 35756 | R7: =IFERROR((Q7/G7)^(1/COUNT($G$4:$Q$4))-1,"") -> 0.052994703
B8: Gross Profit | G8: =G6-G7 -> 35609 | H8: =H6-H7 -> 34679 | I8: =I6-I7 -> 36233 | J8: =J6-J7 -> 39098 | K8: =K6-K7 -> 43737 | L8: =L6-L7 -> 38081 | M8: =M6-M7 -> 42088 | N8: =N6-N7 -> 41820 | ... Q8: =Q6-Q7 -> 17345 | R8: =IFERROR((Q8/G8)^(1/COUNT($G$4:$Q$4))-1,"") -> -0.063298274
B9: SG&A (Selling, General & Administrative) | G9: =IS!C13 -> 8136 | H9: =IS!D13 -> 7930 | I9: =IS!E13 -> 8377 | J9: =IS!F13 -> 7452 | K9: =IS!G13 -> 6950 | L9: =IS!H13 -> 6350 | M9: =IS!I13 -> 6180 | N9: =IS!J13 -> 6543 | ... Q9: =IS!M13 -> 5507 | R9: =IFERROR((Q9/G9)^(1/COUNT($G$4:$Q$4))-1,"") -> -0.034857845
B10: R&D (Research & Development) | G10: =IS!C14 -> 11537 | H10: =IS!D14 -> 12128 | I10: =IS!E14 -> 12685 | J10: =IS!F14 -> 13035 | K10: =IS!G14 -> 13543 | L10: =IS!H14 -> 13362 | M10: =IS!I14 -> 13556 | N10: =IS!J14 -> 15190 | ... Q10: =IS!M14 -> 16546 | R10: =IFERROR((Q10/G10)^(1/COUNT($G$4:$Q$4))-1,"") -> 0.033323664
B11: Other Operating (Income) Expenses | G11: =IS!C15 -> 294 | H11: =IS!D15 -> 253 | I11: =IS!E15 -> 194 | J11: =IS!F15 -> 451 | K11: =IS!G15 -> 0 | L11: =IS!H15 -> -4659 | M11: =IS!I15 -> -587 | N11: =IS!J15 -> -626 | ... Q11: =IS!M15 -> 716 | R11: =IFERROR((Q11/G11)^(1/COUNT($G$4:$Q$4))-1,"") -> 0.084282218
B12: EBITDA | G12: =+G8-G9-G10-G11+CS!E8 -> 24191 | H12: =+H8-H9-H10-H11+CS!F8 -> 23079 | I12: =+I8-I9-I10-I11+CS!G8 -> 22767 | J12: =+J8-J9-J10-J11+CS!H8 -> 26289 | K12: =+K8-K9-K10-K11+CS!I8 -> 32329 | L12: =+L8-L9-L10-L11+CS!J8 -> 33854 | M12: =+M8-M9-M10-M11+CS!K8 -> 35178 | N12: =+N8-N9-N10-N11+CS!L8 -> 32505 | ... Q12: =+Q8-Q9-Q10-Q11+CS!O8 -> 5955 | R12: =IFERROR((Q12/G12)^(1/COUNT($G$4:$Q$4))-1,"") -> -0.11964652
B13: D&A (Depreciation & Amortization) | G13: =+SUM(G14:G15) -> 8549 | H13: =+SUM(H14:H15) -> 8711 | I13: =+SUM(I14:I15) -> 7790 | J13: =+SUM(J14:J15) -> 8129 | K13: =+SUM(K14:K15) -> 9085 | L13: =+SUM(L14:L15) -> 10826 | M13: =+SUM(M14:M15) -> 12239 | N13: =+SUM(N14:N15) -> 11792 | ... Q13: =+SUM(Q14:Q15) -> 11379 | R13: =IFERROR((Q13/G13)^(1/COUNT($G$4:$Q$4))-1,"") -> 0.026336772
B14: Depreciation Expense | G14: =IS!C78 -> 7380 | H14: =IS!D78 -> 7821 | I14: =IS!E78 -> 6266 | J14: =IS!F78 -> 6752 | K14: =IS!G78 -> 7520 | L14: =IS!H78 -> 9204 | M14: =IS!I78 -> 10482 | N14: =IS!J78 -> 9953 | ... Q14: =IS!M78 -> 9951 | R14: =IFERROR((Q14/G14)^(1/COUNT($G$4:$Q$4))-1,"") -> 0.027545217
B15: Amortization Expense | G15: =CS!E8-IS!C78 -> 1169 | H15: =CS!F8-IS!D78 -> 890 | I15: =CS!G8-IS!E78 -> 1524 | J15: =CS!H8-IS!F78 -> 1377 | K15: =CS!I8-IS!G78 -> 1565 | L15: =CS!J8-IS!H78 -> 1622 | M15: =CS!K8-IS!I78 -> 1757 | N15: =CS!L8-IS!J78 -> 1839 | ... Q15: =CS!O8-IS!M78 -> 1428 | R15: =IFERROR((Q15/G15)^(1/COUNT($G$4:$Q$4))-1,"") -> 0.018359795
B16: Operating Income (EBIT) | G16: =+G12-G13 -> 15642 | H16: =+H12-H13 -> 14368 | I16: =+I12-I13 -> 14977 | J16: =+J12-J13 -> 18160 | K16: =+K12-K13 -> 23244 | L16: =+L12-L13 -> 23028 | M16: =+M12-M13 -> 22939 | N16: =+N12-N13 -> 20713 | ... Q16: =+Q12-Q13 -> -5424 | R16: =IFERROR((Q16/G16)^(1/COUNT($G$4:$Q$4))-1,"") -> -1.9082059
B17: Net Interest Expense (Income) | G17: =+G18-G19 -> 51 | H17: =+H18-H19 -> 213 | I17: =+I18-I19 -> 511 | J17: =+J18-J19 -> 205 | K17: =+K18-K19 -> 30 | L17: =+L18-L19 -> 6 | M17: =+M18-M19 -> 357 | N17: =+N18-N19 -> 453 | ... Q17: =+Q18-Q19 -> -211 | R17: =IFERROR((Q17/G17)^(1/COUNT($G$4:$Q$4))-1,"") -> -2.1377969
B18: Interest Expense | G18: =IS!C19 -> 192 | H18: =IS!D19 -> 337 | I18: =IS!E19 -> 733 | J18: =IS!F19 -> 646 | K18: =IS!G19 -> 468 | L18: =IS!H19 -> 489 | M18: =IS!I19 -> 629 | N18: =IS!J19 -> 597 | ... Q18: =IS!M19 -> 1034 | R18: =IFERROR((Q18/G18)^(1/COUNT($G$4:$Q$4))-1,"") -> 0.16539858
B19: Interest Income | G19: =IS!C20 -> 141 | H19: =IS!D20 -> 124 | I19: =IS!E20 -> 222 | J19: =IS!F20 -> 441 | K19: =IS!G20 -> 438 | L19: =IS!H20 -> 483 | M19: =IS!I20 -> 272 | N19: =IS!J20 -> 144 | ... Q19: =IS!M20 -> 1245 | R19: =IFERROR((Q19/G19)^(1/COUNT($G$4:$Q$4))-1,"") -> 0.2189769
B20: FX (Gain) Loss | G20: =IS!C21 -> 0 | H20: =IS!D21 -> 0 | I20: =IS!E21 -> 0 | J20: =IS!F21 -> 0 | K20: =IS!G21 -> 0 | L20: =IS!H21 -> 0 | M20: =IS!I21 -> 0 | N20: =IS!J21 -> 0 | ... Q20: =IS!M21 -> 0 | R20: =IFERROR((Q20/G20)^(1/COUNT($G$4:$Q$4))-1,"")
B21: Other Non-Operating (Income) Expenses | G21: =IS!C23 -> -985 | H21: =IS!D23 -> -203 | I21: =IS!E23 -> 698 | J21: =IS!F23 -> 144 | K21: =IS!G23 -> 338 | L21: =IS!H23 -> -319 | M21: =IS!I23 -> 147 | N21: =IS!J23 -> 29 | ... Q21: =IS!M23 -> 227 | R21: =IFERROR((Q21/G21)^(1/COUNT($G$4:$Q$4))-1,"") -> -1.8750918
B22: Pre-Tax Income (EBT) | G22: =+G16-G17-G20-G21-IS!D45 -> 16576 | H22: =+H16-H17-H20-H21-IS!E45 -> 14358 | I22: =+I16-I17-I20-I21-IS!F45 -> 13768 | J22: =+J16-J17-J20-J21-IS!G45 -> 17811 | K22: =+K16-K17-K20-K21-IS!H45 -> 22876 | L22: =+L16-L17-L20-L21-IS!I45 -> 23341 | M22: =+M16-M17-M20-M21-IS!J45 -> 22435 | N22: =+N16-N17-N20-N21-IS!K45 -> 20228 | ... Q22: =+Q16-Q17-Q20-Q21-IS!N45 -> -4963 | R22: =IFERROR((Q22/G22)^(1/COUNT($G$4:$Q$4))-1,"") -> -1.8961644
B23: Tax Expense (Benefits) | G23: =IS!C36 -> 4097 | H23: =IS!D36 -> 2792 | I23: =IS!E36 -> 2620 | J23: =IS!F36 -> 10751 | K23: =IS!G36 -> 2264 | L23: =IS!H36 -> 3010 | M23: =IS!I36 -> 4179 | N23: =IS!J36 -> 1835 | ... Q23: =IS!M36 -> 8023 | R23: =IFERROR((Q23/G23)^(1/COUNT($G$4:$Q$4))-1,"") -> 0.063001094
B24: Net Income | G24: =+G22-G23 -> 12479 | H24: =+H22-H23 -> 11566 | I24: =+I22-I23 -> 11148 | J24: =+J22-J23 -> 7060 | K24: =+K22-K23 -> 20612 | L24: =+L22-L23 -> 20331 | M24: =+M22-M23 -> 18256 | N24: =+N22-N23 -> 18393 | ... Q24: =+Q22-Q23 -> -12986 | R24: =IFERROR((Q24/G24)^(1/COUNT($G$4:$Q$4))-1,"") -> -2.003627
B25: EPS basic | G25: =IS!C56 -> 2.39 | H25: =IS!D56 -> 2.41 | I25: =IS!E56 -> 2.18 | J25: =IS!F56 -> 2.04 | K25: =IS!G56 -> 4.57 | L25: =IS!H56 -> 4.77 | M25: =IS!I56 -> 4.98 | N25: =IS!J56 -> 4.89 | ... Q25: =IS!M56 -> -4.38 | R25: =IFERROR((Q25/G25)^(1/COUNT($G$4:$Q$4))-1,"") -> -2.0566132
B26: EPS diluted | G26: =IS!C61 -> 2.31 | H26: =IS!D61 -> 2.33 | I26: =IS!E61 -> 2.12 | J26: =IS!F61 -> 1.99 | K26: =IS!G61 -> 4.48 | L26: =IS!H61 -> 4.71 | M26: =IS!I61 -> 4.94 | N26: =IS!J61 -> 4.86 | ... Q26: =IS!M61 -> -4.38 | R26: =IFERROR((Q26/G26)^(1/COUNT($G$4:$Q$4))-1,"") -> -2.0598885
B27: Basic Weighted Average Shares | G27: =IS!C55 -> 4901 | H27: =IS!D55 -> 4742 | I27: =IS!E55 -> 4730 | J27: =IS!F55 -> 4701 | K27: =IS!G55 -> 4611 | L27: =IS!H55 -> 4417 | M27: =IS!I55 -> 4199 | N27: =IS!J55 -> 4059 | ... Q27: =IS!M55 -> 4280
B28: Diluted Weighted Average Shares | G28: =IS!C60 -> 5056 | H28: =IS!D60 -> 4894 | I28: =IS!E60 -> 4875 | J28: =IS!F60 -> 4835 | K28: =IS!G60 -> 4701 | L28: =IS!H60 -> 4473 | M28: =IS!I60 -> 4232 | N28: =IS!J60 -> 4090 | ... Q28: =IS!M60 -> 4280 | R28: =IFERROR((Q28/G28)^(1/COUNT($G$4:$Q$4))-1,"") -> -0.015033367
A30: x | B30: Balance Sheet | G30: 2014 | H30: =+G30+1 -> 2015 | I30: =+H30+1 -> 2016 | J30: =+I30+1 -> 2017 | K30: =+J30+1 -> 2018 | L30: =+K30+1 -> 2019 | M30: =+L30+1 -> 2020 | N30: =+M30+1 -> 2021 | O30: =+N30+1 -> 2022 | ... Q30: =+P30+1 -> 2024 | R30: ="CAGR "&$G$4&" - "&$Q$4 -> CAGR 2014 - 2024
B32: Cash & Cash Equivalents & ST Investments | G32: =+SUM(G33:G34) -> 14054 | H32: =+SUM(H33:H34) -> 25313 | I32: =+SUM(I33:I34) -> 17099 | J32: =+SUM(J33:J34) -> 14002 | K32: =+SUM(K33:K34) -> 11650 | L32: =+SUM(L33:L34) -> 13123 | M32: =+SUM(M33:M34) -> 23895 | N32: =+SUM(N33:N34) -> 28413 | ... Q32: =+SUM(Q33:Q34) -> 22062 | R32: =IFERROR((Q32/G32)^(1/COUNT($G$4:$Q$4))-1,"") -> 0.041847334
B33: Cash & Cash Equivalents | G33: 2561 | H33: 15308 | I33: 5560 | J33: 3433 | K33: 3019 | L33: 4194 | M33: 5865 | N33: 4827 | O33: 11144 | P33: 7079 | Q33: 8249 | R33: =IFERROR((Q33/G33)^(1/COUNT($G$4:$Q$4))-1,"") -> 0.11219533
B34: Short-Term Investments | G34: 11493 | H34: 10005 | I34: 11539 | J34: 10569 | K34: 8631 | L34: 8929 | M34: 18030 | N34: 23586 | O34: 17194 | P34: 17955 | Q34: 13813 | R34: =IFERROR((Q34/G34)^(1/COUNT($G$4:$Q$4))-1,"") -> 0.016856126
B35: Accounts Receivable | G35: 4427 | H35: 4787 | I35: 4690 | J35: 5607 | K35: 6722 | L35: 7659 | M35: 6782 | N35: 9457 | O35: 4133 | P35: 3402 | Q35: 3478 | R35: =IFERROR((Q35/G35)^(1/COUNT($G$4:$Q$4))-1,"") -> -0.021694375
B36: Inventory | G36: 4273 | H36: 5167 | I36: 5553 | J36: 6983 | K36: 7253 | L36: 8744 | M36: 8427 | N36: 10776 | O36: 13224 | P36: 11127 | Q36: 12198 | R36: =IFERROR((Q36/G36)^(1/COUNT($G$4:$Q$4))-1,"") -> 0.10005439
B37: Prepaid expenses and Other Current Assets | G37: =+G38-G32-G35-G36 -> 4976 | H37: =+H38-H32-H35-H36 -> 5089 | I37: =+I38-I32-I35-I36 -> 8166 | J37: =+J38-J32-J35-J36 -> 2908 | K37: =+K38-K32-K35-K36 -> 3162 | L37: =+L38-L32-L35-L36 -> 1713 | M37: =+M38-M32-M35-M36 -> 8145 | N37: =+N38-N32-N35-N36 -> 9072 | ... Q37: =+Q38-Q32-Q35-Q36 -> 9586 | R37: =IFERROR((Q37/G37)^(1/COUNT($G$4:$Q$4))-1,"") -> 0.06141936
B38: Current Assets | G38: 27730 | H38: 40356 | I38: 35508 | J38: 29500 | K38: 28787 | L38: 31239 | M38: 47249 | N38: 57718 | O38: 50407 | P38: 43269 | Q38: 47324 | R38: =IFERROR((Q38/G38)^(1/COUNT($G$4:$Q$4))-1,"") -> 0.049791061
B39: Net PP&E (Property, Plant and Equipment) | G39: =+G40-G41 -> 33238 | H39: =+H40-H41 -> 31858 | I39: =+I40-I41 -> 36171 | J39: =+J40-J41 -> 41109 | K39: =+K40-K41 -> 48976 | L39: =+L40-L41 -> 56014 | M39: =+M40-M41 -> 57188 | N39: =+N40-N41 -> 63794 | ... Q39: =+Q40-Q41 -> 108376 | R39: =IFERROR((Q39/G39)^(1/COUNT($G$4:$Q$4))-1,"") -> 0.11343143
B40: Gross PP&E (Property, Plant and Equipment) | G40: 79709 | H40: 83396 | I40: 90105 | J40: 100395 | K40: 114318 | L40: 129335 | M40: 134833 | N40: 149088 | O40: 174733 | P40: 195162 | Q40: 210569 | R40: =IFERROR((Q40/G40)^(1/COUNT($G$4:$Q$4))-1,"") -> 0.092328765
B41: Accumulated Depreciation | G41: 46471 | H41: 51538 | I41: 53934 | J41: 59286 | K41: 65342 | L41: 73321 | M41: 77645 | N41: 85294 | O41: 93386 | P41: 98010 | Q41: 102193 | R41: =IFERROR((Q41/G41)^(1/COUNT($G$4:$Q$4))-1,"") -> 0.074268022
B42: Right-of-Use Assets | G42: 0 | H42: 0 | I42: 0 | J42: 0 | K42: 0 | L42: 0 | M42: 0 | N42: 0 | O42: 0 | P42: 0 | Q42: 0 | R42: =IFERROR((Q42/G42)^(1/COUNT($G$4:$Q$4))-1,"")
B43: Intangibles | G43: 15307 | H43: 15265 | I43: 23593 | J43: 37134 | K43: 36349 | L43: 37103 | M43: 35997 | N43: 34233 | O43: 33609 | P43: 32180 | Q43: 28384 | R43: =IFERROR((Q43/G43)^(1/COUNT($G$4:$Q$4))-1,"") -> 0.057743389
B44: Goodwill | G44: 10861 | H44: 11332 | I44: 14099 | J44: 24389 | K44: 24513 | L44: 26276 | M44: 26971 | N44: 26963 | O44: 27591 | P44: 27591 | Q44: 24693 | R44: =IFERROR((Q44/G44)^(1/COUNT($G$4:$Q$4))-1,"") -> 0.077525707
B45: Intangibles excl. Goodwill | G45: =+G43-G44 -> 4446 | H45: =+H43-H44 -> 3933 | I45: =+I43-I44 -> 9494 | J45: =+J43-J44 -> 12745 | K45: =+K43-K44 -> 11836 | L45: =+L43-L44 -> 10827 | M45: =+M43-M44 -> 9026 | N45: =+N43-N44 -> 7270 | ... Q45: =+Q43-Q44 -> 3691
B46: Other Non-Current Assets | G46: =+G47-G39-G42-G43 -> 15625 | H46: =+H47-H39-H42-H43 -> 15586 | I46: =+I47-I39-I42-I43 -> 18055 | J46: =+J47-J39-J42-J43 -> 15506 | K46: =+K47-K39-K42-K43 -> 13851 | L46: =+L47-L39-L42-L43 -> 12168 | M46: =+M47-M39-M42-M43 -> 12657 | N46: =+N47-N39-N42-N43 -> 12661 | ... Q46: =+Q47-Q39-Q42-Q43 -> 12401 | R46: =IFERROR((Q46/G46)^(1/COUNT($G$4:$Q$4))-1,"") -> -0.0207895
B47: Non-Current Assets | G47: 64170 | H47: 62709 | I47: 77819 | J47: 93749 | K47: 99176 | L47: 105285 | M47: 105842 | N47: 110688 | O47: 131696 | P47: 148303 | Q47: 149161 | R47: =IFERROR((Q47/G47)^(1/COUNT($G$4:$Q$4))-1,"") -> 0.079697544
B48: Total Assets | G48: =SUM(G47,G38) -> 91900 | H48: =SUM(H47,H38) -> 103065 | I48: =SUM(I47,I38) -> 113327 | J48: =SUM(J47,J38) -> 123249 | K48: =SUM(K47,K38) -> 127963 | L48: =SUM(L47,L38) -> 136524 | M48: =SUM(M47,M38) -> 153091 | N48: =SUM(N47,N38) -> 168406 | ... Q48: =SUM(Q47,Q38) -> 196485 | R48: =IFERROR((Q48/G48)^(1/COUNT($G$4:$Q$4))-1,"") -> 0.071522421
B49: Accounts Payable | G49: 2748 | H49: 2063 | I49: 2475 | J49: 2928 | K49: 3824 | L49: 4128 | M49: 5581 | N49: 5747 | O49: 9595 | P49: 8578 | Q49: 12556 | R49: =IFERROR((Q49/G49)^(1/COUNT($G$4:$Q$4))-1,"") -> 0.14811387
B50: Short-Term Debt | G50: =+SUM(G51:G52) -> 508 | H50: =+SUM(H51:H52) -> 32 | I50: =+SUM(I51:I52) -> 16 | J50: =+SUM(J51:J52) -> 37 | K50: =+SUM(K51:K52) -> 500 | L50: =+SUM(L51:L52) -> 175 | M50: =+SUM(M51:M52) -> 173 | N50: =+SUM(N51:N52) -> 180 | ... Q50: =+SUM(Q51:Q52) -> 181 | R50: =IFERROR((Q50/G50)^(1/COUNT($G$4:$Q$4))-1,"") -> -0.089550427
B51: Short-Term Borrowings | G51: 508 | H51: 32 | I51: 16 | J51: 37 | K51: 500 | L51: 0 | M51: 0 | N51: 0 | O51: 3944 | P51: 0 | Q51: 0 | R51: =IFERROR((Q51/G51)^(1/COUNT($G$4:$Q$4))-1,"") -> -1
B52: Current Portion of Lease Liabilities | G52: 0 | H52: 0 | I52: 0 | J52: 0 | K52: 0 | L52: 175 | M52: 173 | N52: 180 | O52: 173 | P52: 142 | Q52: 181 | R52: =IFERROR((Q52/G52)^(1/COUNT($G$4:$Q$4))-1,"")
B53: Accrued Expenses and Other Current Liabilities | G53: =+G54-G49-G50 -> 12755 | H53: =+H54-H49-H50 -> 13572 | I53: =+I54-I49-I50 -> 17811 | J53: =+J54-J49-J50 -> 14456 | K53: =+K54-K49-K50 -> 12302 | L53: =+L54-L49-L50 -> 18007 | M53: =+M54-M49-M50 -> 19000 | N53: =+N54-N49-N50 -> 21535 | ... Q53: =+Q54-Q49-Q50 -> 22929 | R53: =IFERROR((Q53/G53)^(1/COUNT($G$4:$Q$4))-1,"") -> 0.054763198
B54: Current Liabilities | G54: 16011 | H54: 15667 | I54: 20302 | J54: 17421 | K54: 16626 | L54: 22310 | M54: 24754 | N54: 27462 | O54: 32155 | P54: 28053 | Q54: 35666 | R54: =IFERROR((Q54/G54)^(1/COUNT($G$4:$Q$4))-1,"") -> 0.075527328
B55: Long-Term Debt | G55: =+SUM(G56:G57) -> 12059 | H55: =+SUM(H56:H57) -> 20036 | I55: =+SUM(I56:I57) -> 20649 | J55: =+SUM(J56:J57) -> 25037 | K55: =+SUM(K56:K57) -> 25098 | L55: =+SUM(L56:L57) -> 25683 | M55: =+SUM(M56:M57) -> 34251 | N55: =+SUM(N56:N57) -> 33805 | ... Q55: =+SUM(Q56:Q57) -> 46561 | R55: =IFERROR((Q55/G55)^(1/COUNT($G$4:$Q$4))-1,"") -> 0.13067389
B56: Long-Term Borrowings | G56: 12059 | H56: 20036 | I56: 20649 | J56: 25037 | K56: 25098 | L56: 25308 | M56: 33897 | N56: 33510 | O56: 37684 | P56: 46978 | Q56: 46282 | R56: =IFERROR((Q56/G56)^(1/COUNT($G$4:$Q$4))-1,"") -> 0.13005628
B57: Long-Term Operating Lease Liabilities | G57: 0 | H57: 0 | I57: 0 | J57: 0 | K57: 0 | L57: 375 | M57: 354 | N57: 295 | O57: 236 | P57: 289 | Q57: 279 | R57: =IFERROR((Q57/G57)^(1/COUNT($G$4:$Q$4))-1,"")
B58: Other Non-Current Liabilities | G58: =+G59-G55 -> 7053 | H58: =+H59-H55 -> 6277 | I58: =+I59-I55 -> 5268 | J58: =+J59-J55 -> 10906 | K58: =+K59-K55 -> 11257 | L58: =+L59-L55 -> 10872 | M58: =+M59-M55 -> 13048 | N58: =+N59-N55 -> 11748 | ... Q58: =+Q59-Q55 -> 9226 | R58: =IFERROR((Q58/G58)^(1/COUNT($G$4:$Q$4))-1,"") -> 0.024716188
B59: Non-Current Liabilities | G59: 19112 | H59: 26313 | I59: 25917 | J59: 35943 | K59: 36355 | L59: 36555 | M59: 47299 | N59: 45553 | O59: 46662 | P59: 53554 | Q59: 55787 | R59: =IFERROR((Q59/G59)^(1/COUNT($G$4:$Q$4))-1,"") -> 0.10228362
B60: Total Liabilities | G60: =SUM(G59,G54) -> 35123 | H60: =SUM(H59,H54) -> 41980 | I60: =SUM(I59,I54) -> 46219 | J60: =SUM(J59,J54) -> 53364 | K60: =SUM(K59,K54) -> 52981 | L60: =SUM(L59,L54) -> 58865 | M60: =SUM(M59,M54) -> 72053 | N60: =SUM(N59,N54) -> 73015 | ... Q60: =SUM(Q59,Q54) -> 91453 | R60: =IFERROR((Q60/G60)^(1/COUNT($G$4:$Q$4))-1,"") -> 0.090893605
B61: Shareholder's Equity | G61: =G48-G60 -> 56777 | H61: =H48-H60 -> 61085 | I61: =I48-I60 -> 67108 | J61: =J48-J60 -> 69885 | K61: =K48-K60 -> 74982 | L61: =L48-L60 -> 77659 | M61: =M48-M60 -> 81038 | N61: =N48-N60 -> 95391 | ... Q61: =Q48-Q60 -> 105032 | R61: =IFERROR((Q61/G61)^(1/COUNT($G$4:$Q$4))-1,"") -> 0.057514401
B62: Non-Controlling Interest | G62: 0 | H62: 0 | I62: 0 | J62: 0 | K62: 0 | L62: 0 | M62: 0 | N62: 0 | O62: 1863 | P62: 4375 | Q62: 5762
A64: x | B64: Cash Flow | G64: 2014 | H64: =+G64+1 -> 2015 | I64: =+H64+1 -> 2016 | J64: =+I64+1 -> 2017 | K64: =+J64+1 -> 2018 | L64: =+K64+1 -> 2019 | M64: =+L64+1 -> 2020 | N64: =+M64+1 -> 2021 | O64: =+N64+1 -> 2022 | ... Q64: =+P64+1 -> 2024 | R64: ="CAGR "&$G$4&" - "&$Q$4 -> CAGR 2014 - 2024
B66: Net Income | G66: =G24 -> 12479 | H66: =H24 -> 11566 | I66: =I24 -> 11148 | J66: =J24 -> 7060 | K66: =K24 -> 20612 | L66: =L24 -> 20331 | M66: =M24 -> 18256 | N66: =N24 -> 18393 | ... Q66: =Q24 -> -12986 | R66: =IFERROR((Q66/G66)^(1/COUNT($G$4:$Q$4))-1,"") -> -2.003627
B67: D&A (Depreciation and Amortization) | G67: =+G13 -> 8549 | H67: =+H13 -> 8711 | I67: =+I13 -> 7790 | J67: =+J13 -> 8129 | K67: =+K13 -> 9085 | L67: =+L13 -> 10826 | M67: =+M13 -> 12239 | N67: =+N13 -> 11792 | ... Q67: =+Q13 -> 11379 | R67: =IFERROR((Q67/G67)^(1/COUNT($G$4:$Q$4))-1,"") -> 0.026336772
B68: Changes in Net Working Capital | G68: =+SUM(G69:G72) -> -1490 | H68: =+SUM(H69:H72) -> -1756 | I68: =+SUM(I69:I72) -> 2039 | J68: =+SUM(J69:J72) -> 3651 | K68: =+SUM(K69:K72) -> -2211 | L68: =+SUM(L69:L72) -> -1877 | M68: =+SUM(M69:M72) -> 2388 | N68: =+SUM(N69:N72) -> -5332 | ... Q68: =+SUM(Q69:Q72) -> -1120 | R68: =IFERROR((Q68/G68)^(1/COUNT($G$4:$Q$4))-1,"") -> -0.025615965
B69: (Increase) Decrease in Accounts Receivable | G69: -861 | H69: -355 | I69: 65 | J69: -781 | K69: -1714 | L69: -935 | M69: 883 | N69: -2674 | O69: 5327 | P69: 731 | Q69: -75
B70: (Increase) Decrease in Inventories | G70: -98 | H70: -764 | I70: 119 | J70: -1300 | K70: -214 | L70: -1481 | M70: -687 | N70: -2339 | O70: -2436 | P70: 2097 | Q70: -1105
B71: Increase (Decrease) in Accounts Payables | G71: =CS!E16 -> -249 | H71: =CS!F16 -> -312 | I71: =CS!G16 -> 182 | J71: =CS!H16 -> 191 | K71: =CS!I16 -> 211 | L71: =CS!J16 -> 696 | M71: =CS!K16 -> 405 | N71: =CS!L16 -> 1190 | ... Q71: =CS!O16 -> 634
B72: Increase (Decrease) in Other | G72: -282 | H72: -325 | I72: 1673 | J72: 5541 | K72: -494 | L72: -157 | M72: 1787 | N72: -1509 | O72: -6092 | P72: -4145 | Q72: -574
B73: Stock Based Compensation | G73: 1026 | H73: 1146 | I73: 1444 | J73: 1358 | K73: 1546 | L73: 1705 | M73: 1854 | N73: 2036 | O73: 3128 | P73: 3229 | Q73: 3410
B74: Other Operating Adjustments | G74: =+G75-G66-G67-G68-G73 -> -146 | H74: =+H75-H66-H67-H68-H73 -> -650 | I74: =+I75-I66-I67-I68-I73 -> -613 | J74: =+J75-J66-J67-J68-J73 -> 1912 | K74: =+K75-K66-K67-K68-K73 -> 400 | L74: =+L75-L66-L67-L68-L73 -> 2160 | M74: =+M75-M66-M67-M68-M73 -> 1127 | N74: =+N75-N66-N67-N68-N73 -> 3102 | ... Q74: =+Q75-Q66-Q67-Q68-Q73 -> 7605 | R74: =IFERROR((Q74/G74)^(1/COUNT($G$4:$Q$4))-1,"") -> -2.4324117
B75: Operating Cash Flow | G75: 20418 | H75: 19017 | I75: 21808 | J75: 22110 | K75: 29432 | L75: 33145 | M75: 35864 | N75: 29991 | O75: 15433 | P75: 11471 | Q75: 8288 | R75: =IFERROR((Q75/G75)^(1/COUNT($G$4:$Q$4))-1,"") -> -0.078695225
B76: Net Capex | G76: =+SUM(G77:G78) -> -10105 | H76: =+SUM(H77:H78) -> -7446 | I76: =+SUM(I77:I78) -> -9625 | J76: =+SUM(J77:J78) -> -11778 | K76: =+SUM(K77:K78) -> -15181 | L76: =+SUM(L77:L78) -> -16213 | M76: =+SUM(M77:M78) -> -14453 | N76: =+SUM(N77:N78) -> -20329 | ... Q76: =+SUM(Q77:Q78) -> -23944 | R76: =IFERROR((Q76/G76)^(1/COUNT($G$4:$Q$4))-1,"") -> 0.081583455
B77: Acquisition of Fixed & Intangibles | G77: -10105 | H77: -7446 | I77: -9625 | J77: -11778 | K77: -15181 | L77: -16213 | M77: -14453 | N77: -20329 | O77: -25050 | P77: -25750 | Q77: -23944 | R77: =IFERROR((Q77/G77)^(1/COUNT($G$4:$Q$4))-1,"") -> 0.081583455
B78: Disposal of Fixed & Intangibles | G78: 0 | H78: 0 | I78: 0 | J78: 0 | K78: 0 | L78: 0 | M78: 0 | N78: 0 | O78: 0 | P78: 0 | Q78: 0 | R78: =IFERROR((Q78/G78)^(1/COUNT($G$4:$Q$4))-1,"")
B79: Net Cash from Investments & Acquisitions | G79: =+SUM(G80:G83) -> 6633 | H79: =+SUM(H80:H83) -> 3244 | I79: =+SUM(I80:I83) -> -9699 | J79: =+SUM(J80:J83) -> -7145 | K79: =+SUM(K80:K83) -> 2286 | L79: =+SUM(L80:L83) -> 208 | M79: =+SUM(M80:M83) -> 190 | N79: =+SUM(N80:N83) -> -2122 | ... Q79: =+SUM(Q80:Q83) -> -82 | R79: =IFERROR((Q79/G79)^(1/COUNT($G$4:$Q$4))-1,"") -> -1.6707411
B80: Acquisitions | G80: =-934+0 -> -934 | H80: =-913+0 -> -913 | I80: =-15470+0 -> -15470 | J80: =-14449+0 -> -14449 | K80: =-190+0 -> -190 | L80: =-1958+0 -> -1958 | M80: =0+0 -> 0 | N80: =-2090+0 -> -2090 | O80: =0+0 -> 0 | P80: =0+0 -> 0 | Q80: =-82+0 -> -82 | R80: =IFERROR((Q80/G80)^(1/COUNT($G$4:$Q$4))-1,"") -> -0.19841138
B81: Divestitures | G81: 0 | H81: 0 | I81: 0 | J81: 0 | K81: 548 | L81: 0 | M81: 0 | N81: 0 | O81: 6579 | P81: 0 | Q81: 0 | R81: =IFERROR((Q81/G81)^(1/COUNT($G$4:$Q$4))-1,"")
B82: Increase in LT Investment | G82: -1377 | H82: -2011 | I82: -963 | J82: -1619 | K82: -874 | L82: -522 | M82: -720 | N82: -613 | O82: -510 | P82: -399 | Q82: 0 | R82: =IFERROR((Q82/G82)^(1/COUNT($G$4:$Q$4))-1,"") -> -1
B83: Decrease in LT Investment | G83: 8944 | H83: 6168 | I83: 6734 | J83: 8923 | K83: 2802 | L83: 2688 | M83: 910 | N83: 581 | O83: 4961 | P83: 472 | Q83: 0 | R83: =IFERROR((Q83/G83)^(1/COUNT($G$4:$Q$4))-1,"") -> -1
B84: Other Investing Inflows (Outflows) | G84: =+G85-G76-G79 -> -6433 | H84: =+H85-H76-H79 -> -3981 | I84: =+I85-I76-I79 -> -6493 | J84: =+J85-J76-J79 -> 3161 | K84: =+K85-K76-K79 -> 1656 | L84: =+L85-L76-L79 -> 1600 | M84: =+M85-M76-M79 -> -7261 | N84: =+N85-N76-N79 -> -2716 | ... Q84: =+Q85-Q76-Q79 -> 5770 | R84: =IFERROR((Q84/G84)^(1/COUNT($G$4:$Q$4))-1,"") -> -1.9901606
B85: Investing Cash Flow | G85: -9905 | H85: -8183 | I85: -25817 | J85: -15762 | K85: -11239 | L85: -14405 | M85: -21524 | N85: -25167 | O85: -10231 | P85: -24041 | Q85: -18256 | R85: =IFERROR((Q85/G85)^(1/COUNT($G$4:$Q$4))-1,"") -> 0.057160709
B86: Debt Borrowing | G86: 0 | H86: 9581 | I86: 2734 | J86: 7716 | K86: 423 | L86: 3392 | M86: 10247 | N86: 4974 | O86: 6548 | P86: 11391 | Q86: 2975 | R86: =IFERROR((Q86/G86)^(1/COUNT($G$4:$Q$4))-1,"")
B87: Debt Repayment | G87: 0 | H87: 0 | I87: -1500 | J87: -8080 | K87: -3026 | L87: -2627 | M87: -4525 | N87: -2500 | O87: -5329 | P87: -519 | Q87: -2288 | R87: =IFERROR((Q87/G87)^(1/COUNT($G$4:$Q$4))-1,"")
B88: Lease Payments | G88: =BS!B52+BS!B63 -> 0 | H88: =BS!C52+BS!C63 -> 0 | I88: =BS!D52+BS!D63 -> 0 | J88: =BS!E52+BS!E63 -> 0 | K88: 0 | L88: =BS!G52+BS!G63 -> 550 | M88: =BS!H52+BS!H63 -> 527 | N88: =BS!I52+BS!I63 -> 475 | O88: =BS!J52+BS!J63 -> 409 | P88: =BS!K52+BS!K63 -> 431 | Q88: =BS!L52+BS!L63 -> 460 | R88: =IFERROR((Q88/G88)^(1/COUNT($G$4:$Q$4))-1,"")
B89: Dividends | G89: -4409 | H89: -4556 | I89: -4925 | J89: -5072 | K89: -5541 | L89: -5576 | M89: -5568 | N89: -5644 | O89: -5997 | P89: -3088 | Q89: -1599 | R89: =IFERROR((Q89/G89)^(1/COUNT($G$4:$Q$4))-1,"") -> -0.088083013
B90: Increase (Repurchase) of Shares | G90: -9335 | H90: -1651 | I90: -1479 | J90: -2845 | K90: -10175 | L90: -12826 | M90: -13332 | N90: -1395 | O90: 2009 | P90: 4001 | Q90: 987 | R90: =IFERROR((Q90/G90)^(1/COUNT($G$4:$Q$4))-1,"") -> -1.8152507
B91: Other Financing Inflows (Outflows) | G91: =+G92-G86-G87-G88-G89-G90 -> 133 | H91: =+H92-H86-H87-H88-H89-H90 -> -1462 | I91: =+I92-I86-I87-I88-I89-I90 -> -569 | J91: =+J92-J86-J87-J88-J89-J90 -> -194 | K91: =+K92-K86-K87-K88-K89-K90 -> -288 | L91: =+L92-L86-L87-L88-L89-L90 -> -478 | M91: =+M92-M86-M87-M88-M89-M90 -> -18 | N91: =+N92-N86-N87-N88-N89-N90 -> -1772 | ... Q91: =+Q92-Q86-Q87-Q88-Q89-Q90 -> 10603 | R91: =IFERROR((Q91/G91)^(1/COUNT($G$4:$Q$4))-1,"") -> 0.48891754
B92: Financing Cash Flow | G92: -13611 | H92: 1912 | I92: -5739 | J92: -8475 | K92: -18607 | L92: -17565 | M92: -12669 | N92: -5862 | O92: 1115 | P92: 8505 | Q92: 11138 | R92: =IFERROR((Q92/G92)^(1/COUNT($G$4:$Q$4))-1,"") -> -1.9819364
B93: Effect of Foreign Exchange | G93: -15 | H93: 1 | I93: 0 | J93: 0 | K93: 0 | L93: 0 | M93: 0 | N93: 0 | O93: 0 | P93: 0 | Q93: 0 | R93: =IFERROR((Q93/G93)^(1/COUNT($G$4:$Q$4))-1,"") -> -1
B94: Net Changes in Cash | G94: -3113 | H94: 12747 | I94: -9748 | J94: -2127 | K94: -414 | L94: 1175 | M94: 1671 | N94: -1038 | O94: 6317 | P94: -4065 | Q94: 1170 | R94: =IFERROR((Q94/G94)^(1/COUNT($G$4:$Q$4))-1,"") -> -1.9148802
B95: in billionsof USD
A96: x | B96: Capital Structure | G96: 42004 | H96: 42369 | I96: 42735 | J96: 43100 | K96: 43465 | L96: 43830 | M96: 44196 | N96: 44561 | O96: 44926 | P96: 45291 | Q96: 45657
B98: Market Capitalization | G98: {=(IFERROR(_xlfn.STOCKHISTORY(DCF!$R$4, G96, G96, 0, 0, 1), IFERROR(_xlfn.STOCKHISTORY(DCF!$R$4, G96+1, G96+1, 0, 0, 1), _xlfn.STOCKHISTORY(DCF!$R$4, G96-2, G96-2, 0, 0, 1))))*_xlfn.XLOOKUP("Basic Weighted Average Shares",$B:$B,G:G)} -> 177857.29 | H98: {=(IFERROR(_xlfn.STOCKHISTORY(DCF!$R$4, H96, H96, 0, 0, 1), IFERROR(_xlfn.STOCKHISTORY(DCF!$R$4, H96+1, H96+1, 0, 0, 1), _xlfn.STOCKHISTORY(DCF!$R$4, H96-2, H96-2, 0, 0, 1))))*_xlfn.XLOOKUP("Basic Weighted Average Shares",$B:$B,H:H)} -> 163361.9 | I98: {=(IFERROR(_xlfn.STOCKHISTORY(DCF!$R$4, I96, I96, 0, 0, 1), IFERROR(_xlfn.STOCKHISTORY(DCF!$R$4, I96+1, I96+1, 0, 0, 1), _xlfn.STOCKHISTORY(DCF!$R$4, I96-2, I96-2, 0, 0, 1))))*_xlfn.XLOOKUP("Basic Weighted Average Shares",$B:$B,I:I)} -> 173401.8 | J98: {=(IFERROR(_xlfn.STOCKHISTORY(DCF!$R$4, J96, J96, 0, 0, 1), IFERROR(_xlfn.STOCKHISTORY(DCF!$R$4, J96+1, J96+1, 0, 0, 1), _xlfn.STOCKHISTORY(DCF!$R$4, J96-2, J96-2, 0, 0, 1))))*_xlfn.XLOOKUP("Basic Weighted Average Shares",$B:$B,J:J)} -> 216998.16 | K98: {=(IFERROR(_xlfn.STOCKHISTORY(DCF!$R$4, K96, K96, 0, 0, 1), IFERROR(_xlfn.STOCKHISTORY(DCF!$R$4, K96+1, K96+1, 0, 0, 1), _xlfn.STOCKHISTORY(DCF!$R$4, K96-2, K96-2, 0, 0, 1))))*_xlfn.XLOOKUP("Basic Weighted Average Shares",$B:$B,K:K)} -> 216394.23 | L98: {=(IFERROR(_xlfn.STOCKHISTORY(DCF!$R$4, L96, L96, 0, 0, 1), IFERROR(_xlfn.STOCKHISTORY(DCF!$R$4, L96+1, L96+1, 0, 0, 1), _xlfn.STOCKHISTORY(DCF!$R$4, L96-2, L96-2, 0, 0, 1))))*_xlfn.XLOOKUP("Basic Weighted Average Shares",$B:$B,L:L)} -> 264357.45 | M98: {=(IFERROR(_xlfn.STOCKHISTORY(DCF!$R$4, M96, M96, 0, 0, 1), IFERROR(_xlfn.STOCKHISTORY(DCF!$R$4, M96+1, M96+1, 0, 0, 1), _xlfn.STOCKHISTORY(DCF!$R$4, M96-2, M96-2, 0, 0, 1))))*_xlfn.XLOOKUP("Basic Weighted Average Shares",$B:$B,M:M)} -> 209194.18 | N98: {=(IFERROR(_xlfn.STOCKHISTORY(DCF!$R$4, N96, N96, 0, 0, 1), IFERROR(_xlfn.STOCKHISTORY(DCF!$R$4, N96+1, N96+1, 0, 0, 1), _xlfn.STOCKHISTORY(DCF!$R$4, N96-2, N96-2, 0, 0, 1))))*_xlfn.XLOOKUP("Basic Weighted Average Shares",$B:$B,N:N)} -> 209038.5 | O98: {=(IFERROR(_xlfn.STOCKHISTORY(DCF!$R$4, O96, O96, 0, 0, 1), IFERROR(_xlfn.STOCKHISTORY(DCF!$R$4, O96+1, O96+1, 0, 0, 1), _xlfn.STOCKHISTORY(DCF!$R$4, O96-2, O96-2, 0, 0, 1))))*_xlfn.XLOOKUP("Basic Weighted Average Shares",$B:$B,O:O)} -> 107670.68 | P98: {=(IFERROR(_xlfn.STOCKHISTORY(DCF!$R$4, P96, P96, 0, 0, 1), IFERROR(_xlfn.STOCKHISTORY(DCF!$R$4, P96+1, P96+1, 0, 0, 1), _xlfn.STOCKHISTORY(DCF!$R$4, P96-2, P96-2, 0, 0, 1))))*_xlfn.XLOOKUP("Basic Weighted Average Shares",$B:$B,P:P)} -> 210547.5 | Q98: {=(IFERROR(_xlfn.STOCKHISTORY(DCF!$R$4, Q96, Q96, 0, 0, 1), IFERROR(_xlfn.STOCKHISTORY(DCF!$R$4, Q96+1, Q96+1, 0, 0, 1), _xlfn.STOCKHISTORY(DCF!$R$4, Q96-2, Q96-2, 0, 0, 1))))*_xlfn.XLOOKUP("Basic Weighted Average Shares",$B:$B,Q:Q)} -> 85814
B99: Cash & Cash Equivalents | G99: =_xlfn.XLOOKUP("Cash & Cash Equivalents & ST Investments",$B$30:$B$62,G$30:G$62) -> 14054 | H99: =_xlfn.XLOOKUP("Cash & Cash Equivalents & ST Investments",$B$30:$B$62,H$30:H$62) -> 25313 | I99: =_xlfn.XLOOKUP("Cash & Cash Equivalents & ST Investments",$B$30:$B$62,I$30:I$62) -> 17099 | J99: =_xlfn.XLOOKUP("Cash & Cash Equivalents & ST Investments",$B$30:$B$62,J$30:J$62) -> 14002 | K99: =_xlfn.XLOOKUP("Cash & Cash Equivalents & ST Investments",$B$30:$B$62,K$30:K$62) -> 11650 | L99: =_xlfn.XLOOKUP("Cash & Cash Equivalents & ST Investments",$B$30:$B$62,L$30:L$62) -> 13123 | M99: =_xlfn.XLOOKUP("Cash & Cash Equivalents & ST Investments",$B$30:$B$62,M$30:M$62) -> 23895 | N99: =_xlfn.XLOOKUP("Cash & Cash Equivalents & ST Investments",$B$30:$B$62,N$30:N$62) -> 28413 | ... Q99: =_xlfn.XLOOKUP("Cash & Cash Equivalents & ST Investments",$B$30:$B$62,Q$30:Q$62) -> 22062
B100: Total Debt | G100: =(_xlfn.XLOOKUP("Short-Term Debt",$B$30:$B$62,G$30:G$62)+_xlfn.XLOOKUP("Long-Term Debt",$B$30:$B$62,G$30:G$62)) -> 12567 | H100: =(_xlfn.XLOOKUP("Short-Term Debt",$B$30:$B$62,H$30:H$62)+_xlfn.XLOOKUP("Long-Term Debt",$B$30:$B$62,H$30:H$62)) -> 20068 | I100: =(_xlfn.XLOOKUP("Short-Term Debt",$B$30:$B$62,I$30:I$62)+_xlfn.XLOOKUP("Long-Term Debt",$B$30:$B$62,I$30:I$62)) -> 20665 | J100: =(_xlfn.XLOOKUP("Short-Term Debt",$B$30:$B$62,J$30:J$62)+_xlfn.XLOOKUP("Long-Term Debt",$B$30:$B$62,J$30:J$62)) -> 25074 | K100: =(_xlfn.XLOOKUP("Short-Term Debt",$B$30:$B$62,K$30:K$62)+_xlfn.XLOOKUP("Long-Term Debt",$B$30:$B$62,K$30:K$62)) -> 25598 | L100: =(_xlfn.XLOOKUP("Short-Term Debt",$B$30:$B$62,L$30:L$62)+_xlfn.XLOOKUP("Long-Term Debt",$B$30:$B$62,L$30:L$62)) -> 25858 | M100: =(_xlfn.XLOOKUP("Short-Term Debt",$B$30:$B$62,M$30:M$62)+_xlfn.XLOOKUP("Long-Term Debt",$B$30:$B$62,M$30:M$62)) -> 34424 | N100: =(_xlfn.XLOOKUP("Short-Term Debt",$B$30:$B$62,N$30:N$62)+_xlfn.XLOOKUP("Long-Term Debt",$B$30:$B$62,N$30:N$62)) -> 33985 | ... Q100: =(_xlfn.XLOOKUP("Short-Term Debt",$B$30:$B$62,Q$30:Q$62)+_xlfn.XLOOKUP("Long-Term Debt",$B$30:$B$62,Q$30:Q$62)) -> 46742
B101: Preferred Stock
B102: Non-Controlling Interest | G102: =_xlfn.XLOOKUP("Non-Controlling Interest",$B$30:$B$62,G$30:G$62) -> 0 | H102: =_xlfn.XLOOKUP("Non-Controlling Interest",$B$30:$B$62,H$30:H$62) -> 0 | I102: =_xlfn.XLOOKUP("Non-Controlling Interest",$B$30:$B$62,I$30:I$62) -> 0 | J102: =_xlfn.XLOOKUP("Non-Controlling Interest",$B$30:$B$62,J$30:J$62) -> 0 | K102: =_xlfn.XLOOKUP("Non-Controlling Interest",$B$30:$B$62,K$30:K$62) -> 0 | L102: =_xlfn.XLOOKUP("Non-Controlling Interest",$B$30:$B$62,L$30:L$62) -> 0 | M102: =_xlfn.XLOOKUP("Non-Controlling Interest",$B$30:$B$62,M$30:M$62) -> 0 | N102: =_xlfn.XLOOKUP("Non-Controlling Interest",$B$30:$B$62,N$30:N$62) -> 0 | ... Q102: =_xlfn.XLOOKUP("Non-Controlling Interest",$B$30:$B$62,Q$30:Q$62) -> 5762
B103: Enterprise Value | G103: =+G98-G99+G100+G101+G102 -> 176370.29 | H103: =+H98-H99+H100+H101+H102 -> 158116.9 | I103: =+I98-I99+I100+I101+I102 -> 176967.8 | J103: =+J98-J99+J100+J101+J102 -> 228070.16 | K103: =+K98-K99+K100+K101+K102 -> 230342.23 | L103: =+L98-L99+L100+L101+L102 -> 277092.45 | M103: =+M98-M99+M100+M101+M102 -> 219723.18 | N103: =+N98-N99+N100+N101+N102 -> 214610.5 | ... Q103: =+Q98-Q99+Q100+Q101+Q102 -> 116256
A105: x | B105: Debt Schedule | G105: Cash | H105: 2025 | I105: =+H105+1 -> 2026 | J105: =+I105+1 -> 2027 | K105: =+J105+1 -> 2028 | L105: =+K105+1 -> 2029 | M105: =+L105+1 -> 2030 | N105: =+M105+1 -> 2031 | O105: =+N105+1 -> 2032 | P105: =+O105+1 -> 2033 | Q105: =+P105+1 -> 2034
L106: v | M106: v | N106: v | O106: v | P106: v | Q106: v
B107: Cash
B108: Fixed | H108: =DDIS!C3/1000000 -> 2250 | I108: =DDIS!C4/1000000000 -> 2.5 | J108: =DDIS!C5/1000000000 -> 3.25 | K108: =DDIS!C6/1000000000 -> 2.75 | L108: =DDIS!C7/1000000000 -> 2.85 | M108: =DDIS!B8/1000000000 -> 2.75 | N108: =DDIS!C9/100000 -> 17500 | O108: =DDIS!C10/100000 -> 20000 | P108: =DDIS!C11/100000 -> 22500 | Q108: =DDIS!C12/100000 -> 9000
...

Sheet WACC
B2: WACC
B4: WACC = % of Equity x Cost of Equity + % de Debt x Cost of Debt x (1 - Tax Rate)
B5: Cost of Equity = Risk-Free Rate + Beta x Equity Risk Premium
B7: WACC | I7: Region | J7: Weight | K7: ERP | M7: Peers | N7: Beta (Unlevered)
B9: Market Cap (in millions) | G9: {=+_FV(DCF!R4,"Market cap",TRUE)/1000000} -> 147183.31 | I9: =Segments!B6 -> China | J9: =Segments!D6 -> 0.2924992 | K9: 0.0527 | M9: =+Peers!B8 -> NVIDIA | N9: =Peers!E75 -> 1.9128302
B10: % of Equity | G10: =IFERROR(G9/G23,"") -> 0.75896905 | I10: =Segments!B7 -> United States | J10: =Segments!D7 -> 0.24470349 | K10: 0.0433 | M10: =+Peers!B9 -> AMD | N10: =Peers!F75 -> 1.8574091
B11: Cost of Equity | G11: =IFERROR(G12+G14*G15,"") -> 0.10500265 | I11: =Segments!B8 -> Singapore | J11: =Segments!D8 -> 0.19184196 | K11: 0.0433 | M11: =+Peers!B10 -> Broadcom Inc. | N11: =Peers!G75 -> 0.75118967
B12: Risk-Free Rate | G12: 0.04374 | I12: =Segments!B9 -> Taiwan | J12: =Segments!D9 -> 0.14696522 | K12: 0.0513 | M12: =+Peers!B11 -> ASML | N12: =Peers!H75 -> 1.6987308
B13: Unlevered Beta | G13: =+N19 -> 1.5550399 | M13: =+Peers!B12 | N13: =+Peers!I75
B14: Beta | G14: =Peers!D74 -> 1.266 | I14: Other regions | J14: =1-SUM(J9:J13) -> 0.12399013 | K14: =MAX(K9:K13) -> 0.0527 | M14: =+Peers!B13 | N14: =+Peers!J75
B15: Equity Risk Premium | G15: =SUMPRODUCT(J9:J14,K9:K14) -> 0.048390721 | M15: =+Peers!B14 | N15: =+Peers!K75
B16: Unlevered Cost of Equity | G16: =IFERROR(+G12+G13*G15,"") -> 0.1189895 | M16: =+Peers!B15 | N16: =+Peers!L75
M17: =+Peers!B16 | N17: =+Peers!M75
B18: Debt (in millions) | G18: =Inputs!Q113 -> 46742 | M18: =+Peers!B17 | N18: =+Peers!N75
B19: % of Debt | G19: =IFERROR(G18/G23,"") -> 0.24103095 | M19: Average | N19: =IFERROR(+AVERAGEIF(N9:N18,">0"),"") -> 1.5550399
B20: Cost of debt | G20: =G12+0.0122 -> 0.05594
B21: Tax Rate | G21: 0.21
B23: Total | G23: =+G9+G18 -> 193925.31
B25: WACC | G25: =IFERROR(G10*G11+G19*G20*(1-G21),"") -> 0.090345549

Sheet Multiples
B2: Multiples
B4: Valuation | F4: 2014 | G4: =+F4+1 -> 2015 | H4: =+G4+1 -> 2016 | I4: =+H4+1 -> 2017 | J4: =+I4+1 -> 2018 | K4: =+J4+1 -> 2019 | L4: =+K4+1 -> 2020 | M4: =+L4+1 -> 2021 | N4: 2022 | O4: =+N4+1 -> 2023 | P4: =+O4+1 -> 2024 | Q4: =+P4+1 -> 2025 | R4: =+Q4+1 -> 2026
B6: EV / Sales | F6: =IFERROR(_xlfn.XLOOKUP("Enterprise Value",Inputs!$B:$B,Inputs!G:G)/_xlfn.XLOOKUP("Revenue (Sales)",Inputs!$B:$B,Inputs!G:G),"") -> 3.1567977 | G6: =IFERROR(_xlfn.XLOOKUP("Enterprise Value",Inputs!$B:$B,Inputs!H:H)/_xlfn.XLOOKUP("Revenue (Sales)",Inputs!$B:$B,Inputs!H:H),"") -> 2.8564159 | H6: =IFERROR(_xlfn.XLOOKUP("Enterprise Value",Inputs!$B:$B,Inputs!I:I)/_xlfn.XLOOKUP("Revenue (Sales)",Inputs!$B:$B,Inputs!I:I),"") -> 2.9799081 | I6: =IFERROR(_xlfn.XLOOKUP("Enterprise Value",Inputs!$B:$B,Inputs!J:J)/_xlfn.XLOOKUP("Revenue (Sales)",Inputs!$B:$B,Inputs!J:J),"") -> 3.6339472 | J6: =IFERROR(_xlfn.XLOOKUP("Enterprise Value",Inputs!$B:$B,Inputs!K:K)/_xlfn.XLOOKUP("Revenue (Sales)",Inputs!$B:$B,Inputs!K:K),"") -> 3.2512171 | K6: =IFERROR(_xlfn.XLOOKUP("Enterprise Value",Inputs!$B:$B,Inputs!L:L)/_xlfn.XLOOKUP("Revenue (Sales)",Inputs!$B:$B,Inputs!L:L),"") -> 4.0805297 | L6: =IFERROR(_xlfn.XLOOKUP("Enterprise Value",Inputs!$B:$B,Inputs!M:M)/_xlfn.XLOOKUP("Revenue (Sales)",Inputs!$B:$B,Inputs!M:M),"") -> 3.0140354 | M6: =IFERROR(_xlfn.XLOOKUP("Enterprise Value",Inputs!$B:$B,Inputs!N:N)/_xlfn.XLOOKUP("Revenue (Sales)",Inputs!$B:$B,Inputs!N:N),"") -> 2.8722731 | N6: =IFERROR(_xlfn.XLOOKUP("Enterprise Value",Inputs!$B:$B,Inputs!O:O)/_xlfn.XLOOKUP("Revenue (Sales)",Inputs!$B:$B,Inputs!O:O),"") -> 1.9543991 | O6: =IFERROR(_xlfn.XLOOKUP("Enterprise Value",Inputs!$B:$B,Inputs!P:P)/_xlfn.XLOOKUP("Revenue (Sales)",Inputs!$B:$B,Inputs!P:P),"") -> 4.375922 | P6: =IFERROR(_xlfn.XLOOKUP("Enterprise Value",Inputs!$B:$B,Inputs!Q:Q)/_xlfn.XLOOKUP("Revenue (Sales)",Inputs!$B:$B,Inputs!Q:Q),"") -> 2.1893373 | Q6: =IFERROR(_xlfn.XLOOKUP("Enterprise Value",DCF!$B:$B,DCF!R:R)/_xlfn.XLOOKUP("Revenue (Sales)",DCF!$B:$B,DCF!H:H),"") -> 0.030084902 | R6: =IFERROR(_xlfn.XLOOKUP("Enterprise Value",DCF!$B:$B,DCF!S:S)/_xlfn.XLOOKUP("Revenue (Sales)",DCF!$B:$B,DCF!I:I),"") -> 0.028802171
B7: Price / Sales | F7: =IFERROR(_xlfn.XLOOKUP("Market Capitalization",Inputs!$B:$B,Inputs!G:G)/_xlfn.XLOOKUP("Revenue (Sales)",Inputs!$B:$B,Inputs!G:G),"") -> 3.1834131 | G7: =IFERROR(_xlfn.XLOOKUP("Market Capitalization",Inputs!$B:$B,Inputs!H:H)/_xlfn.XLOOKUP("Revenue (Sales)",Inputs!$B:$B,Inputs!H:H),"") -> 2.9511679 | H7: =IFERROR(_xlfn.XLOOKUP("Market Capitalization",Inputs!$B:$B,Inputs!I:I)/_xlfn.XLOOKUP("Revenue (Sales)",Inputs!$B:$B,Inputs!I:I),"") -> 2.9198612 | I7: =IFERROR(_xlfn.XLOOKUP("Market Capitalization",Inputs!$B:$B,Inputs!J:J)/_xlfn.XLOOKUP("Revenue (Sales)",Inputs!$B:$B,Inputs!J:J),"") -> 3.4575319 | J7: =IFERROR(_xlfn.XLOOKUP("Market Capitalization",Inputs!$B:$B,Inputs!K:K)/_xlfn.XLOOKUP("Revenue (Sales)",Inputs!$B:$B,Inputs!K:K),"") -> 3.0543449 | K7: =IFERROR(_xlfn.XLOOKUP("Market Capitalization",Inputs!$B:$B,Inputs!L:L)/_xlfn.XLOOKUP("Revenue (Sales)",Inputs!$B:$B,Inputs!L:L),"") -> 3.892991 | L7: =IFERROR(_xlfn.XLOOKUP("Market Capitalization",Inputs!$B:$B,Inputs!M:M)/_xlfn.XLOOKUP("Revenue (Sales)",Inputs!$B:$B,Inputs!M:M),"") -> 2.8696047 | M7: =IFERROR(_xlfn.XLOOKUP("Market Capitalization",Inputs!$B:$B,Inputs!N:N)/_xlfn.XLOOKUP("Revenue (Sales)",Inputs!$B:$B,Inputs!N:N),"") -> 2.7976993 | N7: =IFERROR(_xlfn.XLOOKUP("Market Capitalization",Inputs!$B:$B,Inputs!O:O)/_xlfn.XLOOKUP("Revenue (Sales)",Inputs!$B:$B,Inputs!O:O),"") -> 1.7075948 | O7: =IFERROR(_xlfn.XLOOKUP("Market Capitalization",Inputs!$B:$B,Inputs!P:P)/_xlfn.XLOOKUP("Revenue (Sales)",Inputs!$B:$B,Inputs!P:P),"") -> 3.8826344 | P7: =IFERROR(_xlfn.XLOOKUP("Market Capitalization",Inputs!$B:$B,Inputs!Q:Q)/_xlfn.XLOOKUP("Revenue (Sales)",Inputs!$B:$B,Inputs!Q:Q),"") -> 1.6160524 | Q7: =IFERROR(_xlfn.XLOOKUP("Equity Value",DCF!$B:$B,DCF!R:R)/_xlfn.XLOOKUP("Revenue (Sales)",DCF!$B:$B,DCF!H:H),"") -> 0 | R7: =IFERROR(_xlfn.XLOOKUP("Equity Value",DCF!$B:$B,DCF!S:S)/_xlfn.XLOOKUP("Revenue (Sales)",DCF!$B:$B,DCF!I:I),"") -> 0
B8: EV / EBITDA | F8: =IFERROR(_xlfn.XLOOKUP("Enterprise Value",Inputs!$B:$B,Inputs!G:G)/_xlfn.XLOOKUP("EBITDA",Inputs!$B:$B,Inputs!G:G),"") -> 7.2907399 | G8: =IFERROR(_xlfn.XLOOKUP("Enterprise Value",Inputs!$B:$B,Inputs!H:H)/_xlfn.XLOOKUP("EBITDA",Inputs!$B:$B,Inputs!H:H),"") -> 6.8511157 | H8: =IFERROR(_xlfn.XLOOKUP("Enterprise Value",Inputs!$B:$B,Inputs!I:I)/_xlfn.XLOOKUP("EBITDA",Inputs!$B:$B,Inputs!I:I),"") -> 7.772996 | I8: =IFERROR(_xlfn.XLOOKUP("Enterprise Value",Inputs!$B:$B,Inputs!J:J)/_xlfn.XLOOKUP("EBITDA",Inputs!$B:$B,Inputs!J:J),"") -> 8.6754977 | J8: =IFERROR(_xlfn.XLOOKUP("Enterprise Value",Inputs!$B:$B,Inputs!K:K)/_xlfn.XLOOKUP("EBITDA",Inputs!$B:$B,Inputs!K:K),"") -> 7.1249414 | K8: =IFERROR(_xlfn.XLOOKUP("Enterprise Value",Inputs!$B:$B,Inputs!L:L)/_xlfn.XLOOKUP("EBITDA",Inputs!$B:$B,Inputs!L:L),"") -> 8.184925 | L8: =IFERROR(_xlfn.XLOOKUP("Enterprise Value",Inputs!$B:$B,Inputs!M:M)/_xlfn.XLOOKUP("EBITDA",Inputs!$B:$B,Inputs!M:M),"") -> 6.2460396 | M8: =IFERROR(_xlfn.XLOOKUP("Enterprise Value",Inputs!$B:$B,Inputs!N:N)/_xlfn.XLOOKUP("EBITDA",Inputs!$B:$B,Inputs!N:N),"") -> 6.6023842 | N8: =IFERROR(_xlfn.XLOOKUP("Enterprise Value",Inputs!$B:$B,Inputs!O:O)/_xlfn.XLOOKUP("EBITDA",Inputs!$B:$B,Inputs!O:O),"") -> 8.5524797 | O8: =IFERROR(_xlfn.XLOOKUP("Enterprise Value",Inputs!$B:$B,Inputs!P:P)/_xlfn.XLOOKUP("EBITDA",Inputs!$B:$B,Inputs!P:P),"") -> 25.031382 | P8: =IFERROR(_xlfn.XLOOKUP("Enterprise Value",Inputs!$B:$B,Inputs!Q:Q)/_xlfn.XLOOKUP("EBITDA",Inputs!$B:$B,Inputs!Q:Q),"") -> 19.522418 | Q8: =IFERROR(_xlfn.XLOOKUP("Enterprise Value",DCF!$B:$B,DCF!R:R)/_xlfn.XLOOKUP("EBITDA",DCF!$B:$B,DCF!H:H),"") -> -0.26114947 | R8: =IFERROR(_xlfn.XLOOKUP("Enterprise Value",DCF!$B:$B,DCF!S:S)/_xlfn.XLOOKUP("EBITDA",DCF!$B:$B,DCF!I:I),"") -> -0.90451115
B9: EV / EBIT | F9: =IFERROR(_xlfn.XLOOKUP("Enterprise Value",Inputs!$B:$B,Inputs!G:G)/_xlfn.XLOOKUP("Operating Income (EBIT)",Inputs!$B:$B,Inputs!G:G),"") -> 11.275431 | G9: =IFERROR(_xlfn.XLOOKUP("Enterprise Value",Inputs!$B:$B,Inputs!H:H)/_xlfn.XLOOKUP("Operating Income (EBIT)",Inputs!$B:$B,Inputs!H:H),"") -> 11.004795 | H9: =IFERROR(_xlfn.XLOOKUP("Enterprise Value",Inputs!$B:$B,Inputs!I:I)/_xlfn.XLOOKUP("Operating Income (EBIT)",Inputs!$B:$B,Inputs!I:I),"") -> 11.815971 | I9: =IFERROR(_xlfn.XLOOKUP("Enterprise Value",Inputs!$B:$B,Inputs!J:J)/_xlfn.XLOOKUP("Operating Income (EBIT)",Inputs!$B:$B,Inputs!J:J),"") -> 12.55893 | J9: =IFERROR(_xlfn.XLOOKUP("Enterprise Value",Inputs!$B:$B,Inputs!K:K)/_xlfn.XLOOKUP("Operating Income (EBIT)",Inputs!$B:$B,Inputs!K:K),"") -> 9.90975 | K9: =IFERROR(_xlfn.XLOOKUP("Enterprise Value",Inputs!$B:$B,Inputs!L:L)/_xlfn.XLOOKUP("Operating Income (EBIT)",Inputs!$B:$B,Inputs!L:L),"") -> 12.032849 | L9: =IFERROR(_xlfn.XLOOKUP("Enterprise Value",Inputs!$B:$B,Inputs!M:M)/_xlfn.XLOOKUP("Operating Income (EBIT)",Inputs!$B:$B,Inputs!M:M),"") -> 9.5785858 | M9: =IFERROR(_xlfn.XLOOKUP("Enterprise Value",Inputs!$B:$B,Inputs!N:N)/_xlfn.XLOOKUP("Operating Income (EBIT)",Inputs!$B:$B,Inputs!N:N),"") -> 10.36115 | N9: =IFERROR(_xlfn.XLOOKUP("Enterprise Value",Inputs!$B:$B,Inputs!O:O)/_xlfn.XLOOKUP("Operating Income (EBIT)",Inputs!$B:$B,Inputs!O:O),"") -> 89.688996 | O9: =IFERROR(_xlfn.XLOOKUP("Enterprise Value",Inputs!$B:$B,Inputs!P:P)/_xlfn.XLOOKUP("Operating Income (EBIT)",Inputs!$B:$B,Inputs!P:P),"") -> -1945.0615 | P9: =IFERROR(_xlfn.XLOOKUP("Enterprise Value",Inputs!$B:$B,Inputs!Q:Q)/_xlfn.XLOOKUP("Operating Income (EBIT)",Inputs!$B:$B,Inputs!Q:Q),"") -> -21.433628 | Q9: =IFERROR(_xlfn.XLOOKUP("Enterprise Value",DCF!$B:$B,DCF!R:R)/_xlfn.XLOOKUP("Operating Income (EBIT)",DCF!$B:$B,DCF!H:H),"") -> -0.26114947 | R9: =IFERROR(_xlfn.XLOOKUP("Enterprise Value",DCF!$B:$B,DCF!S:S)/_xlfn.XLOOKUP("Operating Income (EBIT)",DCF!$B:$B,DCF!I:I),"") -> -0.90451115
B10: Price / Earnings | F10: =IFERROR(_xlfn.XLOOKUP("Market Capitalization",Inputs!$B:$B,Inputs!G:G)/_xlfn.XLOOKUP("Net Income",Inputs!$B:$B,Inputs!G:G),"") -> 14.252527 | G10: =IFERROR(_xlfn.XLOOKUP("Market Capitalization",Inputs!$B:$B,Inputs!H:H)/_xlfn.XLOOKUP("Net Income",Inputs!$B:$B,Inputs!H:H),"") -> 14.124321 | H10: =IFERROR(_xlfn.XLOOKUP("Market Capitalization",Inputs!$B:$B,Inputs!I:I)/_xlfn.XLOOKUP("Net Income",Inputs!$B:$B,Inputs!I:I),"") -> 15.554521 | I10: =IFERROR(_xlfn.XLOOKUP("Market Capitalization",Inputs!$B:$B,Inputs!J:J)/_xlfn.XLOOKUP("Net Income",Inputs!$B:$B,Inputs!J:J),"") -> 30.736283 | J10: =IFERROR(_xlfn.XLOOKUP("Market Capitalization",Inputs!$B:$B,Inputs!K:K)/_xlfn.XLOOKUP("Net Income",Inputs!$B:$B,Inputs!K:K),"") -> 10.498459 | K10: =IFERROR(_xlfn.XLOOKUP("Market Capitalization",Inputs!$B:$B,Inputs!L:L)/_xlfn.XLOOKUP("Net Income",Inputs!$B:$B,Inputs!L:L),"") -> 13.002678 | L10: =IFERROR(_xlfn.XLOOKUP("Market Capitalization",Inputs!$B:$B,Inputs!M:M)/_xlfn.XLOOKUP("Net Income",Inputs!$B:$B,Inputs!M:M),"") -> 11.458927 | M10: =IFERROR(_xlfn.XLOOKUP("Market Capitalization",Inputs!$B:$B,Inputs!N:N)/_xlfn.XLOOKUP("Net Income",Inputs!$B:$B,Inputs!N:N),"") -> 11.365112 | N10: =IFERROR(_xlfn.XLOOKUP("Market Capitalization",Inputs!$B:$B,Inputs!O:O)/_xlfn.XLOOKUP("Net Income",Inputs!$B:$B,Inputs!O:O),"") -> 38.412658 | O10: =IFERROR(_xlfn.XLOOKUP("Market Capitalization",Inputs!$B:$B,Inputs!P:P)/_xlfn.XLOOKUP("Net Income",Inputs!$B:$B,Inputs!P:P),"") -> 110.98972 | P10: =IFERROR(_xlfn.XLOOKUP("Market Capitalization",Inputs!$B:$B,Inputs!Q:Q)/_xlfn.XLOOKUP("Net Income",Inputs!$B:$B,Inputs!Q:Q),"") -> -6.6081934 | Q10: =IFERROR(_xlfn.XLOOKUP("Equity Value",DCF!$B:$B,DCF!R:R)/_xlfn.XLOOKUP("Net Income",DCF!$B:$B,DCF!H:H),"") -> 0 | R10: =IFERROR(_xlfn.XLOOKUP("Equity Value",DCF!$B:$B,DCF!S:S)/_xlfn.XLOOKUP("Net Income",DCF!$B:$B,DCF!I:I),"") -> 0
B11: Price / Book | F11: =IFERROR(_xlfn.XLOOKUP("Market Capitalization",Inputs!$B:$B,Inputs!G:G)/_xlfn.XLOOKUP("Shareholder's Equity",Inputs!$B:$B,Inputs!G:G),"") -> 3.1325588 | G11: =IFERROR(_xlfn.XLOOKUP("Market Capitalization",Inputs!$B:$B,Inputs!H:H)/_xlfn.XLOOKUP("Shareholder's Equity",Inputs!$B:$B,Inputs!H:H),"") -> 2.6743374 | H11: =IFERROR(_xlfn.XLOOKUP("Market Capitalization",Inputs!$B:$B,Inputs!I:I)/_xlfn.XLOOKUP("Shareholder's Equity",Inputs!$B:$B,Inputs!I:I),"") -> 2.5839214 | I11: =IFERROR(_xlfn.XLOOKUP("Market Capitalization",Inputs!$B:$B,Inputs!J:J)/_xlfn.XLOOKUP("Shareholder's Equity",Inputs!$B:$B,Inputs!J:J),"") -> 3.1050749 | J11: =IFERROR(_xlfn.XLOOKUP("Market Capitalization",Inputs!$B:$B,Inputs!K:K)/_xlfn.XLOOKUP("Shareholder's Equity",Inputs!$B:$B,Inputs!K:K),"") -> 2.885949 | K11: =IFERROR(_xlfn.XLOOKUP("Market Capitalization",Inputs!$B:$B,Inputs!L:L)/_xlfn.XLOOKUP("Shareholder's Equity",Inputs!$B:$B,Inputs!L:L),"") -> 3.40408 | L11: =IFERROR(_xlfn.XLOOKUP("Market Capitalization",Inputs!$B:$B,Inputs!M:M)/_xlfn.XLOOKUP("Shareholder's Equity",Inputs!$B:$B,Inputs!M:M),"") -> 2.5814332 | M11: =IFERROR(_xlfn.XLOOKUP("Market Capitalization",Inputs!$B:$B,Inputs!N:N)/_xlfn.XLOOKUP("Shareholder's Equity",Inputs!$B:$B,Inputs!N:N),"") -> 2.191386 | N11: =IFERROR(_xlfn.XLOOKUP("Market Capitalization",Inputs!$B:$B,Inputs!O:O)/_xlfn.XLOOKUP("Shareholder's Equity",Inputs!$B:$B,Inputs!O:O),"") -> 1.0424518 | O11: =IFERROR(_xlfn.XLOOKUP("Market Capitalization",Inputs!$B:$B,Inputs!P:P)/_xlfn.XLOOKUP("Shareholder's Equity",Inputs!$B:$B,Inputs!P:P),"") -> 1.9146774 | P11: =IFERROR(_xlfn.XLOOKUP("Market Capitalization",Inputs!$B:$B,Inputs!Q:Q)/_xlfn.XLOOKUP("Shareholder's Equity",Inputs!$B:$B,Inputs!Q:Q),"") -> 0.81702719 | Q11: =IFERROR(+_xlfn.XLOOKUP("Equity Value",DCF!$B:$B,DCF!R:R)/(_xlfn.XLOOKUP("Shareholder's Equity",Inputs!$B:$B,Inputs!$Q:$Q)+_xlfn.XLOOKUP("Net Income",DCF!$B:$B,DCF!H:H)+_xlfn.XLOOKUP("Total Payout",DCF!$B:$B,DCF!H:H)),"") -> 0 | R11: =IFERROR(+_xlfn.XLOOKUP("Equity Value",DCF!$B:$B,DCF!S:S)/(_xlfn.XLOOKUP("Shareholder's Equity",Inputs!$B:$B,Inputs!$Q:$Q)+_xlfn.XLOOKUP("Net Income",DCF!$B:$B,DCF!I:I)+_xlfn.XLOOKUP("Total Payout",DCF!$B:$B,DCF!I:I)),"") -> 0
B13: Profitability | F13: 2014 | G13: =+F13+1 -> 2015 | H13: =+G13+1 -> 2016 | I13: =+H13+1 -> 2017 | J13: =+I13+1 -> 2018 | K13: =+J13+1 -> 2019 | L13: =+K13+1 -> 2020 | M13: =+L13+1 -> 2021 | N13: 2022 | O13: =+N13+1 -> 2023 | P13: =+O13+1 -> 2024 | Q13: =+P13+1 -> 2025 | R13: =+Q13+1 -> 2026
B15: Return on Assets | F15: =+IFERROR(_xlfn.XLOOKUP("Net Income",Inputs!$B:$B,Inputs!G:G)/_xlfn.XLOOKUP("Total Assets",Inputs!$B:$B,Inputs!G:G),"") -> 0.1357889 | G15: =+IFERROR(_xlfn.XLOOKUP("Net Income",Inputs!$B:$B,Inputs!H:H)/_xlfn.XLOOKUP("Total Assets",Inputs!$B:$B,Inputs!H:H),"") -> 0.11222044 | H15: =+IFERROR(_xlfn.XLOOKUP("Net Income",Inputs!$B:$B,Inputs!I:I)/_xlfn.XLOOKUP("Total Assets",Inputs!$B:$B,Inputs!I:I),"") -> 0.098370203 | I15: =+IFERROR(_xlfn.XLOOKUP("Net Income",Inputs!$B:$B,Inputs!J:J)/_xlfn.XLOOKUP("Total Assets",Inputs!$B:$B,Inputs!J:J),"") -> 0.057282412 | J15: =+IFERROR(_xlfn.XLOOKUP("Net Income",Inputs!$B:$B,Inputs!K:K)/_xlfn.XLOOKUP("Total Assets",Inputs!$B:$B,Inputs!K:K),"") -> 0.16107781 | K15: =+IFERROR(_xlfn.XLOOKUP("Net Income",Inputs!$B:$B,Inputs!L:L)/_xlfn.XLOOKUP("Total Assets",Inputs!$B:$B,Inputs!L:L),"") -> 0.14891887 | L15: =+IFERROR(_xlfn.XLOOKUP("Net Income",Inputs!$B:$B,Inputs!M:M)/_xlfn.XLOOKUP("Total Assets",Inputs!$B:$B,Inputs!M:M),"") -> 0.11924934 | M15: =+IFERROR(_xlfn.XLOOKUP("Net Income",Inputs!$B:$B,Inputs!N:N)/_xlfn.XLOOKUP("Total Assets",Inputs!$B:$B,Inputs!N:N),"") -> 0.1092182 | N15: =+IFERROR(_xlfn.XLOOKUP("Net Income",Inputs!$B:$B,Inputs!O:O)/_xlfn.XLOOKUP("Total Assets",Inputs!$B:$B,Inputs!O:O),"") -> 0.015392388 | O15: =+IFERROR(_xlfn.XLOOKUP("Net Income",Inputs!$B:$B,Inputs!P:P)/_xlfn.XLOOKUP("Total Assets",Inputs!$B:$B,Inputs!P:P),"") -> 0.0099022822 | P15: =+IFERROR(_xlfn.XLOOKUP("Net Income",Inputs!$B:$B,Inputs!Q:Q)/_xlfn.XLOOKUP("Total Assets",Inputs!$B:$B,Inputs!Q:Q),"") -> -0.066091559 | Q15: =IFERROR(_xlfn.XLOOKUP("Net Income",DCF!$B:$B,DCF!H:H)/_xlfn.XLOOKUP("Total assets",DCF!$6:$6,DCF!10:10),"") -> -0.056875013 | R15: =IFERROR(_xlfn.XLOOKUP("Net Income",DCF!$B:$B,DCF!I:I)/_xlfn.XLOOKUP("Total assets",DCF!$6:$6,DCF!10:10),"") -> -0.014451172
B16: Return on Equity | F16: =IFERROR(_xlfn.XLOOKUP("Net Income",Inputs!$B:$B,Inputs!G:G)/_xlfn.XLOOKUP("Shareholder's Equity",Inputs!$B:$B,Inputs!G:G),"") -> 0.2197897 | G16: =IFERROR(_xlfn.XLOOKUP("Net Income",Inputs!$B:$B,Inputs!H:H)/_xlfn.XLOOKUP("Shareholder's Equity",Inputs!$B:$B,Inputs!H:H),"") -> 0.18934272 | H16: =IFERROR(_xlfn.XLOOKUP("Net Income",Inputs!$B:$B,Inputs!I:I)/_xlfn.XLOOKUP("Shareholder's Equity",Inputs!$B:$B,Inputs!I:I),"") -> 0.16612028 | I16: =IFERROR(_xlfn.XLOOKUP("Net Income",Inputs!$B:$B,Inputs!J:J)/_xlfn.XLOOKUP("Shareholder's Equity",Inputs!$B:$B,Inputs!J:J),"") -> 0.10102311 | J16: =IFERROR(_xlfn.XLOOKUP("Net Income",Inputs!$B:$B,Inputs!K:K)/_xlfn.XLOOKUP("Shareholder's Equity",Inputs!$B:$B,Inputs!K:K),"") -> 0.27489264 | K16: =IFERROR(_xlfn.XLOOKUP("Net Income",Inputs!$B:$B,Inputs!L:L)/_xlfn.XLOOKUP("Shareholder's Equity",Inputs!$B:$B,Inputs!L:L),"") -> 0.26179837 | L16: =IFERROR(_xlfn.XLOOKUP("Net Income",Inputs!$B:$B,Inputs!M:M)/_xlfn.XLOOKUP("Shareholder's Equity",Inputs!$B:$B,Inputs!M:M),"") -> 0.22527703 | M16: =IFERROR(_xlfn.XLOOKUP("Net Income",Inputs!$B:$B,Inputs!N:N)/_xlfn.XLOOKUP("Shareholder's Equity",Inputs!$B:$B,Inputs!N:N),"") -> 0.19281693 | N16: =IFERROR(_xlfn.XLOOKUP("Net Income",Inputs!$B:$B,Inputs!O:O)/_xlfn.XLOOKUP("Shareholder's Equity",Inputs!$B:$B,Inputs!O:O),"") -> 0.027138238 | O16: =IFERROR(_xlfn.XLOOKUP("Net Income",Inputs!$B:$B,Inputs!P:P)/_xlfn.XLOOKUP("Shareholder's Equity",Inputs!$B:$B,Inputs!P:P),"") -> 0.017250943 | P16: =IFERROR(_xlfn.XLOOKUP("Net Income",Inputs!$B:$B,Inputs!Q:Q)/_xlfn.XLOOKUP("Shareholder's Equity",Inputs!$B:$B,Inputs!Q:Q),"") -> -0.12363851 | Q16: =IFERROR(_xlfn.XLOOKUP("Net Income",DCF!$B:$B,DCF!H:H)/_xlfn.XLOOKUP("Shareholder's Equity",DCF!$6:$6,DCF!10:10),"") -> 3.587293e-15 | R16: =IFERROR(_xlfn.XLOOKUP("Net Income",DCF!$B:$B,DCF!I:I)/_xlfn.XLOOKUP("Shareholder's Equity",DCF!$6:$6,DCF!10:10),"") -> 9.1148267e-16
B17: Return on Total Capital | F17: =IFERROR(_xlfn.XLOOKUP("NOPAT",Inputs!$B:$B,Inputs!G:G)/(_xlfn.XLOOKUP("Shareholder's Equity",Inputs!$B:$B,Inputs!G:G)+_xlfn.XLOOKUP("Total Debt",Inputs!$B:$B,Inputs!G:G,,,-1)),"") -> 0.16981789 | G17: =IFERROR(_xlfn.XLOOKUP("NOPAT",Inputs!$B:$B,Inputs!H:H)/(_xlfn.XLOOKUP("Shareholder's Equity",Inputs!$B:$B,Inputs!H:H)+_xlfn.XLOOKUP("Total Debt",Inputs!$B:$B,Inputs!H:H,,,-1)),"") -> 0.14262018 | H17: =IFERROR(_xlfn.XLOOKUP("NOPAT",Inputs!$B:$B,Inputs!I:I)/(_xlfn.XLOOKUP("Shareholder's Equity",Inputs!$B:$B,Inputs!I:I)+_xlfn.XLOOKUP("Total Debt",Inputs!$B:$B,Inputs!I:I,,,-1)),"") -> 0.13816244 | I17: =IFERROR(_xlfn.XLOOKUP("NOPAT",Inputs!$B:$B,Inputs!J:J)/(_xlfn.XLOOKUP("Shareholder's Equity",Inputs!$B:$B,Inputs!J:J)+_xlfn.XLOOKUP("Total Debt",Inputs!$B:$B,Inputs!J:J,,,-1)),"") -> 0.075804696 | J17: =IFERROR(_xlfn.XLOOKUP("NOPAT",Inputs!$B:$B,Inputs!K:K)/(_xlfn.XLOOKUP("Shareholder's Equity",Inputs!$B:$B,Inputs!K:K)+_xlfn.XLOOKUP("Total Debt",Inputs!$B:$B,Inputs!K:K,,,-1)),"") -> 0.20822807 | K17: =IFERROR(_xlfn.XLOOKUP("NOPAT",Inputs!$B:$B,Inputs!L:L)/(_xlfn.XLOOKUP("Shareholder's Equity",Inputs!$B:$B,Inputs!L:L)+_xlfn.XLOOKUP("Total Debt",Inputs!$B:$B,Inputs!L:L,,,-1)),"") -> 0.19376879 | L17: =IFERROR(_xlfn.XLOOKUP("NOPAT",Inputs!$B:$B,Inputs!M:M)/(_xlfn.XLOOKUP("Shareholder's Equity",Inputs!$B:$B,Inputs!M:M)+_xlfn.XLOOKUP("Total Debt",Inputs!$B:$B,Inputs!M:M,,,-1)),"") -> 0.16166461 | M17: =IFERROR(_xlfn.XLOOKUP("NOPAT",Inputs!$B:$B,Inputs!N:N)/(_xlfn.XLOOKUP("Shareholder's Equity",Inputs!$B:$B,Inputs!N:N)+_xlfn.XLOOKUP("Total Debt",Inputs!$B:$B,Inputs!N:N,,,-1)),"") -> 0.14557571 | N17: =IFERROR(_xlfn.XLOOKUP("NOPAT",Inputs!$B:$B,Inputs!O:O)/(_xlfn.XLOOKUP("Shareholder's Equity",Inputs!$B:$B,Inputs!O:O)+_xlfn.XLOOKUP("Total Debt",Inputs!$B:$B,Inputs!O:O,,,-1)),"") -> 0.010376588 | O17: =IFERROR(_xlfn.XLOOKUP("NOPAT",Inputs!$B:$B,Inputs!P:P)/(_xlfn.XLOOKUP("Shareholder's Equity",Inputs!$B:$B,Inputs!P:P)+_xlfn.XLOOKUP("Total Debt",Inputs!$B:$B,Inputs!P:P,,,-1)),"") -> -0.0014945109 | P17: =IFERROR(_xlfn.XLOOKUP("NOPAT",Inputs!$B:$B,Inputs!Q:Q)/(_xlfn.XLOOKUP("Shareholder's Equity",Inputs!$B:$B,Inputs!Q:Q)+_xlfn.XLOOKUP("Total Debt",Inputs!$B:$B,Inputs!Q:Q,,,-1)),"") -> -0.093509002 | Q17: =+IFERROR(_xlfn.XLOOKUP("NOPAT",DCF!$B:$B,DCF!H:H)/(_xlfn.XLOOKUP("Shareholder's Equity",DCF!$6:$6,DCF!10:10)+_xlfn.XLOOKUP("Total Borrowings",DCF!$B:$B,DCF!H:H)+_xlfn.XLOOKUP("Total Leases",DCF!$B:$B,DCF!H:H)),"") -> 2.1696913e-15 | R17: =+IFERROR(_xlfn.XLOOKUP("NOPAT",DCF!$B:$B,DCF!I:I)/(_xlfn.XLOOKUP("Shareholder's Equity",DCF!$6:$6,DCF!10:10)+_xlfn.XLOOKUP("Total Borrowings",DCF!$B:$B,DCF!I:I)+_xlfn.XLOOKUP("Total Leases",DCF!$B:$B,DCF!I:I)),"") -> 6.2674025e-16
