Workbook
Name COOLFUCNTION: _xlfn.LAMBDA(_xldudf_BOARDFLARE_EXEC("workbook-settings:coolfucntion"))
Name COOLFUCNTION: _xlfn.LAMBDA(_xldudf_BOARDFLARE_EXEC("workbook-settings:coolfucntion"))
Name COOLFUCNTION: _xlfn.LAMBDA(_xldudf_BOARDFLARE_EXEC("workbook-settings:coolfucntion"))
Name COOLFUCNTION: _xlfn.LAMBDA(_xldudf_BOARDFLARE_EXEC("workbook-settings:coolfucntion"))
Name COOLFUCNTION: _xlfn.LAMBDA(_xldudf_BOARDFLARE_EXEC("workbook-settings:coolfucntion"))
Name COOLFUCNTION: _xlfn.LAMBDA(_xldudf_BOARDFLARE_EXEC("workbook-settings:coolfucntion"))
Name COOLFUCNTION: _xlfn.LAMBDA(_xldudf_BOARDFLARE_EXEC("workbook-settings:coolfucntion"))
Name COOLFUCNTION: _xlfn.LAMBDA(_xldudf_BOARDFLARE_EXEC("workbook-settings:coolfucntion"))
Name COOLFUCNTION: _xlfn.LAMBDA(_xldudf_BOARDFLARE_EXEC("workbook-settings:coolfucntion"))
Name COOLFUCNTION: _xlfn.LAMBDA(_xldudf_BOARDFLARE_EXEC("workbook-settings:coolfucntion"))
Name Sectors: #REF!
Name Sectors: #REF!
Name Sectors: #REF!

Sheet Summary
E2: | EQUITY RESEARCH | U2: Lisbon Investment Society Equity Research
U3: April 21, 2025
D6: {=+_FV(DCF!AA4,"Name")} -> IONQ, INC. | U6: Sell
D8: IonQ is an American technology company focused on quantum computing. It is known for developing quantum computers based on trapped ions, one of the most promising approaches in the field. Its solutions allow businesses and researchers to explore quantum computing for applications like chemical simulations, optimization, and machine learning. | U8: XNYS⁩:(IONQ)
U9: {=+"Price (22 Apr 25): $"&_FV(DCF!$AA$4,"Price")} -> Price (22 Apr 25): $55.008
D10: Investment Thesis | U10: ="Price Target: $" & ROUND(IF(Summary!G25="FCFF",DCF!Z210,IF(Summary!G25="FCFE",DCF!AA253,IF(Summary!G25="Tax Shield",DCF!AA226,DCF!Q269))),2) &" "&IF(Summary!G25="FCFF","(FCFF)",IF(Summary!G25="FCFE","(FCFE)",IF(Summary!G25="Tax Shield","(APV)","(DDM)"))) -> Price Target: $13.35 (FCFF)
D11: IonQ offers compelling long-term potential driven by breakthroughs in quantum computing, with a particular focus on high-impact sectors such as healthcare—where quantum capabilities could revolutionize drug discovery, diagnostics, and genomics. Its partnerships with tech giants like Amazon and Microsoft offer distribution advantages and validation, but they also reflect the power imbalance in the ecosystem, where IonQ’s growth is partly dependent on these larger players’ platforms and roadmaps. While consumers wield influence over the broader tech landscape, IonQ remains largely insulated due to its B2B/government focus, although public perception and trust still impact long-term viability and investment flow. Despite strong growth relative to peers and a solid technology foundation, IonQ operates in a highly volatile market, with substantial risks tied to the availability of public and private funding—particularly in light of changing economic conditions. The company also faces the structural challenge of high operating costs and limited short- to mid-term monetization. Even over a 20-year horizon, stable and steady profitability remains uncertain, making the investment less appealing for those seeking near-term returns or sure long-term ones. | U11: =+"Upside (Downside): "&ROUND((DCF!$Z$213*100),2)&"%" -> Upside (Downside): -75.73%
U15: =+ESG!C10 -> 0
E17: j | K17: Valuation Multiples | N17: 2022 | O17: =+N17+1 -> 2023 | P17: =+O17+1 -> 2024 | Q17: =+P17+1 -> 2025 | R17: =+Q17+1 -> 2026 | U17: Cristina Lin
K18: EV / Sales | N18: =IFERROR(_xlfn.XLOOKUP($K18,Multiples!$B:$B,Multiples!N:N),"") -> 31.282787 | O18: =IFERROR(_xlfn.XLOOKUP($K18,Multiples!$B:$B,Multiples!O:O),"") -> 98.112097 | P18: =IFERROR(_xlfn.XLOOKUP($K18,Multiples!$B:$B,Multiples!P:P),"") -> 199.09628 | Q18: =IFERROR(_xlfn.XLOOKUP($K18,Multiples!$B:$B,Multiples!Q:Q),"") -> -27.061042 | R18: =IFERROR(_xlfn.XLOOKUP($K18,Multiples!$B:$B,Multiples!R:R),"") -> -17.209963 | U18: cristina.lin@aln.iseg.ulisboa.pt
K19: Price / Sales | N19: =IFERROR(_xlfn.XLOOKUP($K19,Multiples!$B:$B,Multiples!N:N),"") -> 62.883452 | O19: =IFERROR(_xlfn.XLOOKUP($K19,Multiples!$B:$B,Multiples!O:O),"") -> 113.87001 | P19: =IFERROR(_xlfn.XLOOKUP($K19,Multiples!$B:$B,Multiples!P:P),"") -> 206.58505 | Q19: =IFERROR(_xlfn.XLOOKUP($K19,Multiples!$B:$B,Multiples!Q:Q),"") -> -29.825629 | R19: =IFERROR(_xlfn.XLOOKUP($K19,Multiples!$B:$B,Multiples!R:R),"") -> -23.550357 | U19: (+351) 968185578
K20: EV / EBITDA | N20: =IFERROR(_xlfn.XLOOKUP($K20,Multiples!$B:$B,Multiples!N:N),"") -> -4.3448966 | O20: =IFERROR(_xlfn.XLOOKUP($K20,Multiples!$B:$B,Multiples!O:O),"") -> -14.673643 | P20: =IFERROR(_xlfn.XLOOKUP($K20,Multiples!$B:$B,Multiples!P:P),"") -> -40.110542 | Q20: =IFERROR(_xlfn.XLOOKUP($K20,Multiples!$B:$B,Multiples!Q:Q),"") -> 7.1044773 | R20: =IFERROR(_xlfn.XLOOKUP($K20,Multiples!$B:$B,Multiples!R:R),"") -> 5.984625 | U20: Madalena Oliveira da Silva
K21: EV / EBIT | N21: =IFERROR(_xlfn.XLOOKUP($K21,Multiples!$B:$B,Multiples!N:N),"") -> -4.0609323 | O21: =IFERROR(_xlfn.XLOOKUP($K21,Multiples!$B:$B,Multiples!O:O),"") -> -13.708602 | P21: =IFERROR(_xlfn.XLOOKUP($K21,Multiples!$B:$B,Multiples!P:P),"") -> -36.89176 | Q21: =IFERROR(_xlfn.XLOOKUP($K21,Multiples!$B:$B,Multiples!Q:Q),"") -> 6.5589154 | R21: =IFERROR(_xlfn.XLOOKUP($K21,Multiples!$B:$B,Multiples!R:R),"") -> 5.4442224 | U21: l.63835@aln.iseg.ulisboa.pt
K22: Price / Earnings | N22: =IFERROR(_xlfn.XLOOKUP($K22,Multiples!$B:$B,Multiples!N:N),"") -> -14.428804 | O22: =IFERROR(_xlfn.XLOOKUP($K22,Multiples!$B:$B,Multiples!O:O),"") -> -15.913482 | P22: =IFERROR(_xlfn.XLOOKUP($K22,Multiples!$B:$B,Multiples!P:P),"") -> -26.835219 | Q22: =IFERROR(_xlfn.XLOOKUP($K22,Multiples!$B:$B,Multiples!Q:Q),"") -> 7.3033356 | R22: =IFERROR(_xlfn.XLOOKUP($K22,Multiples!$B:$B,Multiples!R:R),"") -> 6.8596672 | U22: (+351) 937583978
K23: Price / Book | N23: =IFERROR(_xlfn.XLOOKUP($K23,Multiples!$B:$B,Multiples!N:N),"") -> 1.2318588 | O23: =IFERROR(_xlfn.XLOOKUP($K23,Multiples!$B:$B,Multiples!O:O),"") -> 5.1751627 | P23: =IFERROR(_xlfn.XLOOKUP($K23,Multiples!$B:$B,Multiples!P:P),"") -> 23.180825 | Q23: =IFERROR(_xlfn.XLOOKUP($K23,Multiples!$B:$B,Multiples!Q:Q),"") -> -20.069772 | R23: =IFERROR(_xlfn.XLOOKUP($K23,Multiples!$B:$B,Multiples!R:R),"") -> -490.16913 | U23: Gabriela de Almeida Rito Major
U24: l64181@aln.iseg.ulisboa.pt
D25: Year | E25: Net Sales | F25: EBIT Margin | G25: FCFF | H25: =+IF(Summary!$G$25="FCFF",DCF!AK6,IF(Summary!$G$25="FCFE",DCF!AL6,DCF!AM6)) -> NOPAT | I25: Net Capex | K25: Profitability Ratios | N25: 2022 | O25: =+N25+1 -> 2023 | P25: =+O25+1 -> 2024 | Q25: =+P25+1 -> 2025 | R25: =+Q25+1 -> 2026 | U25: (+351) 910247429
D26: 2022 | E26: =+DCF!E30 -> 11131 | F26: =+DCF!E61 -> -7.703351 | G26: =+INDEX(DCF!AG7:AJ7,MATCH(Summary!$G$25,{"FCFF","FCFE","Tax Shield","Total Payout"},0)) -> -64536 | H26: =+IF(Summary!$G$25="FCFF",DCF!AK7,IF(Summary!$G$25="FCFE",DCF!AL7,DCF!AM7)) -> -85746 | I26: =+DCF!E135 -> -12564 | K26: Return on Assets | N26: =IFERROR(_xlfn.XLOOKUP($K26,Multiples!$B:$B,Multiples!N:N),"") -> -0.081123159 | O26: =IFERROR(_xlfn.XLOOKUP($K26,Multiples!$B:$B,Multiples!O:O),"") -> -0.28491464 | P26: =IFERROR(_xlfn.XLOOKUP($K26,Multiples!$B:$B,Multiples!P:P),"") -> -0.65223424 | Q26: =IFERROR(_xlfn.XLOOKUP($K26,Multiples!$B:$B,Multiples!Q:Q),"") -> -0.95331909 | R26: =IFERROR(_xlfn.XLOOKUP($K26,Multiples!$B:$B,Multiples!R:R),"") -> -1.2822844 | U26: João de Sousa Eiró
D27: =+D26+1 -> 2023 | E27: =+DCF!F30 -> 22042 | F27: =+DCF!F61 -> -7.1569731 | G27: =+INDEX(DCF!AG8:AJ8,MATCH(Summary!$G$25,{"FCFF","FCFE","Tax Shield","Total Payout"},0)) -> -113850.05 | H27: =+IF(Summary!$G$25="FCFF",DCF!AK8,IF(Summary!$G$25="FCFE",DCF!AL8,DCF!AM8)) -> -157754.05 | I27: =+DCF!F135 -> -19549 | K27: Return on Equity | N27: =IFERROR(_xlfn.XLOOKUP($K27,Multiples!$B:$B,Multiples!N:N),"") -> -0.085374975 | O27: =IFERROR(_xlfn.XLOOKUP($K27,Multiples!$B:$B,Multiples!O:O),"") -> -0.32520618 | P27: =IFERROR(_xlfn.XLOOKUP($K27,Multiples!$B:$B,Multiples!P:P),"") -> -0.86382101 | Q27: =IFERROR(_xlfn.XLOOKUP($K27,Multiples!$B:$B,Multiples!Q:Q),"") -> 2.1736588 | R27: =IFERROR(_xlfn.XLOOKUP($K27,Multiples!$B:$B,Multiples!R:R),"") -> 2.9237313 | U27: joaodesousaeiro@aln.iseg.ulisboa.pt
D28: =+D27+1 -> 2024 | E28: =+DCF!G30 -> 43073 | F28: =+DCF!G61 -> -5.3967683 | G28: =+INDEX(DCF!AG9:AJ9,MATCH(Summary!$G$25,{"FCFF","FCFE","Tax Shield","Total Payout"},0)) -> -146246.04 | H28: =+IF(Summary!$G$25="FCFF",DCF!AK9,IF(Summary!$G$25="FCFE",DCF!AL9,DCF!AM9)) -> -232455.04 | I28: =+DCF!G135 -> -23569 | K28: Return on Total Capital | N28: =IFERROR(_xlfn.XLOOKUP($K28,Multiples!$B:$B,Multiples!N:N),"") -> -0.14983722 | O28: =IFERROR(_xlfn.XLOOKUP($K28,Multiples!$B:$B,Multiples!O:O),"") -> -0.31992368 | P28: =IFERROR(_xlfn.XLOOKUP($K28,Multiples!$B:$B,Multiples!P:P),"") -> -0.57884105 | Q28: =IFERROR(_xlfn.XLOOKUP($K28,Multiples!$B:$B,Multiples!Q:Q),"") -> -1.5801313 | R28: =IFERROR(_xlfn.XLOOKUP($K28,Multiples!$B:$B,Multiples!R:R),"") -> -1.7368601 | U28: (+351) 918446662
D29: =+D28+1 -> 2025 | E29: =+DCF!H30 -> 68916.8 | F29: =+DCF!H61 -> -4.1258411 | G29: =+INDEX(DCF!AG10:AJ10,MATCH(Summary!$G$25,{"FCFF","FCFE","Tax Shield","Total Payout"},0)) -> -112020.3 | H29: =+IF(Summary!$G$25="FCFF",DCF!AK10,IF(Summary!$G$25="FCFE",DCF!AL10,DCF!AM10)) -> -224628.41 | I29: =+DCF!H135 -> -34458.4 | K29: EBITDA Margin | N29: =IFERROR(_xlfn.XLOOKUP($K29,Multiples!$B:$B,Multiples!N:N),"") -> -7.1998922 | O29: =IFERROR(_xlfn.XLOOKUP($K29,Multiples!$B:$B,Multiples!O:O),"") -> -6.6862807 | P29: =IFERROR(_xlfn.XLOOKUP($K29,Multiples!$B:$B,Multiples!P:P),"") -> -4.9636896 | Q29: =IFERROR(_xlfn.XLOOKUP($K29,Multiples!$B:$B,Multiples!Q:Q),"") -> -3.8090125 | R29: =IFERROR(_xlfn.XLOOKUP($K29,Multiples!$B:$B,Multiples!R:R),"") -> -2.8756962
D30: =+D29+1 -> 2026 | E30: =+DCF!I30 -> 110266.88 | F30: =+DCF!I61 -> -3.1611426 | G30: =+INDEX(DCF!AG11:AJ11,MATCH(Summary!$G$25,{"FCFF","FCFE","Tax Shield","Total Payout"},0)) -> -188326.8 | H30: =+IF(Summary!$G$25="FCFF",DCF!AK11,IF(Summary!$G$25="FCFE",DCF!AL11,DCF!AM11)) -> -275369.77 | I30: =+DCF!I135 -> -55133.44 | K30: EBIT Margin | N30: =IFERROR(_xlfn.XLOOKUP($K30,Multiples!$B:$B,Multiples!N:N),"") -> -7.703351 | O30: =IFERROR(_xlfn.XLOOKUP($K30,Multiples!$B:$B,Multiples!O:O),"") -> -7.1569731 | P30: =IFERROR(_xlfn.XLOOKUP($K30,Multiples!$B:$B,Multiples!P:P),"") -> -5.3967683 | Q30: =IFERROR(_xlfn.XLOOKUP($K30,Multiples!$B:$B,Multiples!Q:Q),"") -> -4.1258411 | R30: =IFERROR(_xlfn.XLOOKUP($K30,Multiples!$B:$B,Multiples!R:R),"") -> -3.1611426 | U30: Statistics
D31: =+D30+1 -> 2027 | E31: =+DCF!J30 -> 165400.32 | F31: =+DCF!J61 -> -2.5476658 | G31: =+INDEX(DCF!AG12:AJ12,MATCH(Summary!$G$25,{"FCFF","FCFE","Tax Shield","Total Payout"},0)) -> -232576.45 | H31: =+IF(Summary!$G$25="FCFF",DCF!AK12,IF(Summary!$G$25="FCFE",DCF!AL12,DCF!AM12)) -> -332893.95 | I31: =+DCF!J135 -> -74430.144 | K31: Gross Profit Margin | N31: =IFERROR(_xlfn.XLOOKUP($K31,Multiples!$B:$B,Multiples!N:N),"") -> 0.73551343 | O31: =IFERROR(_xlfn.XLOOKUP($K31,Multiples!$B:$B,Multiples!O:O),"") -> 0.63215679 | P31: =IFERROR(_xlfn.XLOOKUP($K31,Multiples!$B:$B,Multiples!P:P),"") -> 0.52181181 | Q31: =IFERROR(_xlfn.XLOOKUP($K31,Multiples!$B:$B,Multiples!Q:Q),"") -> 0.52181181 | R31: =IFERROR(_xlfn.XLOOKUP($K31,Multiples!$B:$B,Multiples!R:R),"") -> 0.52181181 | U31: Beta | V31: =Peers!D74 -> 2.5362
D32: =+D31+1 -> 2028 | E32: =+DCF!K30 -> 248100.48 | F32: =+DCF!K61 -> -2.0417154 | G32: =+INDEX(DCF!AG13:AJ13,MATCH(Summary!$G$25,{"FCFF","FCFE","Tax Shield","Total Payout"},0)) -> -318961.71 | H32: =+IF(Summary!$G$25="FCFF",DCF!AK13,IF(Summary!$G$25="FCFE",DCF!AL13,DCF!AM13)) -> -400174.95 | I32: =+DCF!K135 -> -111645.22 | K32: SG&A Margin | N32: =IFERROR(_xlfn.XLOOKUP($K32,Multiples!$B:$B,Multiples!N:N),"") -> 3.9844578 | O32: =IFERROR(_xlfn.XLOOKUP($K32,Multiples!$B:$B,Multiples!O:O),"") -> 3.1300245 | P32: =IFERROR(_xlfn.XLOOKUP($K32,Multiples!$B:$B,Multiples!P:P),"") -> 2.308871 | Q32: =IFERROR(_xlfn.XLOOKUP($K32,Multiples!$B:$B,Multiples!Q:Q),"") | R32: =IFERROR(_xlfn.XLOOKUP($K32,Multiples!$B:$B,Multiples!R:R),"") | U32: % Float | V32: =+Peers!D73 -> 0.85310616
D33: =+D32+1 -> 2029 | E33: =+DCF!L30 -> 372150.72 | F33: =+DCF!L61 -> -1.5225164 | G33: =+INDEX(DCF!AG14:AJ14,MATCH(Summary!$G$25,{"FCFF","FCFE","Tax Shield","Total Payout"},0)) -> -376231.76 | H33: =+IF(Summary!$G$25="FCFF",DCF!AK14,IF(Summary!$G$25="FCFE",DCF!AL14,DCF!AM14)) -> -447618.39 | I33: =+DCF!L135 -> -148860.29 | K33: Net Income Margin | N33: =IFERROR(_xlfn.XLOOKUP($K33,Multiples!$B:$B,Multiples!N:N),"") -> -4.3581888 | O33: =IFERROR(_xlfn.XLOOKUP($K33,Multiples!$B:$B,Multiples!O:O),"") -> -7.1555688 | P33: =IFERROR(_xlfn.XLOOKUP($K33,Multiples!$B:$B,Multiples!P:P),"") -> -7.698281 | Q33: =IFERROR(_xlfn.XLOOKUP($K33,Multiples!$B:$B,Multiples!Q:Q),"") -> -4.0838366 | R33: =IFERROR(_xlfn.XLOOKUP($K33,Multiples!$B:$B,Multiples!R:R),"") -> -3.4331631 | U33: % Held by Insiders | V33: =+Peers!D76 -> 0.0854
U34: % Held by Institutions | V34: =+Peers!D77 -> 0.3738
D35: SWOT Analysis | K35: Liquidity Ratios | N35: 2022 | O35: =+N35+1 -> 2023 | P35: =+O35+1 -> 2024 | Q35: =+P35+1 -> 2025 | R35: =+Q35+1 -> 2026 | U35: Short % of Float | V35: =+Peers!D78 -> 0.1466
D36: Strengths | G36: Weaknesses | K36: Cash Ratio | N36: =IFERROR(_xlfn.XLOOKUP($K36,Multiples!$B:$B,Multiples!N:N),"") -> 2.200744 | O36: =IFERROR(_xlfn.XLOOKUP($K36,Multiples!$B:$B,Multiples!O:O),"") -> 0.95966527 | P36: =IFERROR(_xlfn.XLOOKUP($K36,Multiples!$B:$B,Multiples!P:P),"") -> 1.5073576 | Q36: =IFERROR(_xlfn.XLOOKUP($K36,Multiples!$B:$B,Multiples!Q:Q),"") -> -3.9720603 | R36: =IFERROR(_xlfn.XLOOKUP($K36,Multiples!$B:$B,Multiples!R:R),"") -> -12.715983 | W36: 120.87
D37: Technological Leadership: IonQ utilizes trapped-ion quantum technology, offering high fidelity and long coherence times, positioning them at the forefront of quantum computing advancements; Robust Intellectual Property Portfolio: As of February 1, 2024, IonQ holds or exclusively licenses 82 issued U.S. patents and 185 pending or allowed U.S. patent applications, along with international patents and trademarks; Strategic Partnerships: Collaborations with major cloud providers like Amazon Web Services and Microsoft Azure enhance accessibility to IonQ's quantum computing services. | G37: Financial Losses: In 2024, IonQ reported a net loss of $331.6 million and an Adjusted EBITDA loss of $107.2 million, indicating ongoing challenges in achieving profitability; High Operational Costs: Significant investments in research and development contribute to substantial operational expenses, impacting short-term financial performance. | K37: Quick Ratio | N37: =IFERROR(_xlfn.XLOOKUP($K37,Multiples!$B:$B,Multiples!N:N),"") -> 17.811954 | O37: =IFERROR(_xlfn.XLOOKUP($K37,Multiples!$B:$B,Multiples!O:O),"") -> 9.8726725 | P37: =IFERROR(_xlfn.XLOOKUP($K37,Multiples!$B:$B,Multiples!P:P),"") -> 9.6107801 | Q37: =IFERROR(_xlfn.XLOOKUP($K37,Multiples!$B:$B,Multiples!Q:Q),"") -> 1.1227435 | R37: =IFERROR(_xlfn.XLOOKUP($K37,Multiples!$B:$B,Multiples!R:R),"") -> -7.5133431 | U37: Major Holders | W37: 113.63
K38: Current Ratio | N38: =IFERROR(_xlfn.XLOOKUP($K38,Multiples!$B:$B,Multiples!N:N),"") -> 18.433929 | O38: =IFERROR(_xlfn.XLOOKUP($K38,Multiples!$B:$B,Multiples!O:O),"") -> 10.49373 | P38: =IFERROR(_xlfn.XLOOKUP($K38,Multiples!$B:$B,Multiples!P:P),"") -> 10.497492 | Q38: =IFERROR(_xlfn.XLOOKUP($K38,Multiples!$B:$B,Multiples!Q:Q),"") -> 1.7427224 | R38: =IFERROR(_xlfn.XLOOKUP($K38,Multiples!$B:$B,Multiples!R:R),"") -> 1.7427224 | U38: Vanguard Group Inc | V38: 0.0959
U39: Blackrock Inc. | V39: 0.0718
D40: Opportunities | G40: Threats | K40: Cash Flow Ratios | N40: 2022 | O40: =+N40+1 -> 2023 | P40: =+O40+1 -> 2024 | Q40: =+P40+1 -> 2025 | R40: =+Q40+1 -> 2026 | U40: Morgan Stanley | V40: 0.0281
D41: Growing Quantum Computing Market: The expanding demand for quantum computing solutions across various industries presents opportunities for IonQ to capture market share; Government and Defense Contracts: Engagements with governmental agencies, such as the U.S. Air Force Research Laboratory, open avenues for specialized applications and funding. | G41: Intense Competition: The quantum computing sector is highly competitive, with major players like IBM and Google investing heavily in similar technologies; Regulatory and Geopolitical Risks: Potential changes in regulations and international relations could affect IonQ's operations and collaborations. | K41: Cash Conversion Cycle | N41: =IFERROR(_xlfn.XLOOKUP($K41,Multiples!$B:$B,Multiples!N:N),"") -> 7.7715389 | O41: =IFERROR(_xlfn.XLOOKUP($K41,Multiples!$B:$B,Multiples!O:O),"") -> 97.169948 | P41: =IFERROR(_xlfn.XLOOKUP($K41,Multiples!$B:$B,Multiples!P:P),"") -> 10.897546 | Q41: =IFERROR(_xlfn.XLOOKUP($K41,Multiples!$B:$B,Multiples!Q:Q),"") -> -34.632229 | R41: =IFERROR(_xlfn.XLOOKUP($K41,Multiples!$B:$B,Multiples!R:R),"") -> -9.632229 | U41: State Street Corporation | V41: 0.0206
K42: Net Income / Op Cash Flow | N42: =IFERROR(_xlfn.XLOOKUP($K42,Multiples!$B:$B,Multiples!N:N),"") -> 1.0853058 | O42: =IFERROR(_xlfn.XLOOKUP($K42,Multiples!$B:$B,Multiples!O:O),"") -> 2.0012822 | P42: =IFERROR(_xlfn.XLOOKUP($K42,Multiples!$B:$B,Multiples!P:P),"") -> 3.1375724 | Q42: =IFERROR(_xlfn.XLOOKUP($K42,Multiples!$B:$B,Multiples!Q:Q),"") -> 3.5102349 | R42: =IFERROR(_xlfn.XLOOKUP($K42,Multiples!$B:$B,Multiples!R:R),"") -> 2.757168 | U42: Geode Capital Management, LLC | V42: 0.02
K43: Chg in Cash / Op Cash Flow | N43: =IFERROR(_xlfn.XLOOKUP($K43,Multiples!$B:$B,Multiples!N:N),"") -> 7.8897937 | O43: =IFERROR(_xlfn.XLOOKUP($K43,Multiples!$B:$B,Multiples!O:O),"") -> 0.10513761 | P43: =IFERROR(_xlfn.XLOOKUP($K43,Multiples!$B:$B,Multiples!P:P),"") -> -0.17750253 | Q43: =IFERROR(_xlfn.XLOOKUP($K43,Multiples!$B:$B,Multiples!Q:Q),"") -> 3.5600169 | R43: =IFERROR(_xlfn.XLOOKUP($K43,Multiples!$B:$B,Multiples!R:R),"") -> 3.7043132 | U43: UBS Group AG | V43: 0.0111
U44: JP Morgan Chase & Co | V44: 0.0111
D45: Revenue by Region | G45: Revenue by Segment | K45: Leverage Ratios | N45: 2022 | O45: =+N45+1 -> 2023 | P45: =+O45+1 -> 2024 | Q45: =+P45+1 -> 2025 | R45: =+Q45+1 -> 2026 | U45: Northern Trust Corporation | V45: 0.0087
K46: Total Debt / Equity | N46: =IFERROR(_xlfn.XLOOKUP($K46,Multiples!$B:$B,Multiples!N:N),"") -> 7.1276339 | O46: =IFERROR(_xlfn.XLOOKUP($K46,Multiples!$B:$B,Multiples!O:O),"") -> 16.711547 | P46: =IFERROR(_xlfn.XLOOKUP($K46,Multiples!$B:$B,Multiples!P:P),"") -> 46.175448 | Q46: =IFERROR(_xlfn.XLOOKUP($K46,Multiples!$B:$B,Multiples!Q:Q),"") -> -0.13689392 | R46: =IFERROR(_xlfn.XLOOKUP($K46,Multiples!$B:$B,Multiples!R:R),"") -> -2.0979168 | U46: Goldman Sachs Group Inc | V46: 0.0085
K47: Total Debt / Capital | N47: =IFERROR(_xlfn.XLOOKUP($K47,Multiples!$B:$B,Multiples!N:N),"") -> 0.87696296 | O47: =IFERROR(_xlfn.XLOOKUP($K47,Multiples!$B:$B,Multiples!O:O),"") -> 0.94353966 | P47: =IFERROR(_xlfn.XLOOKUP($K47,Multiples!$B:$B,Multiples!P:P),"") -> 0.97880253 | Q47: =IFERROR(_xlfn.XLOOKUP($K47,Multiples!$B:$B,Multiples!Q:Q),"") -> -0.15860614 | R47: =IFERROR(_xlfn.XLOOKUP($K47,Multiples!$B:$B,Multiples!R:R),"") -> 1.9108158 | U47: Charles Schwab Investment Management, Inc. | V47: 0.0074
K48: Total Liabilities / Total Assets | N48: =IFERROR(_xlfn.XLOOKUP($K48,Multiples!$B:$B,Multiples!N:N),"") -> 0.04980167 | O48: =IFERROR(_xlfn.XLOOKUP($K48,Multiples!$B:$B,Multiples!O:O),"") -> 0.12389537 | P48: =IFERROR(_xlfn.XLOOKUP($K48,Multiples!$B:$B,Multiples!P:P),"") -> 0.24494284 | Q48: =IFERROR(_xlfn.XLOOKUP($K48,Multiples!$B:$B,Multiples!Q:Q),"") -> 1.4385781 | R48: =IFERROR(_xlfn.XLOOKUP($K48,Multiples!$B:$B,Multiples!R:R),"") -> 1.4385781
K49: Total Debt / EBITDA | N49: =IFERROR(_xlfn.XLOOKUP($K49,Multiples!$B:$B,Multiples!N:N),"") -> -0.0505353 | O49: =IFERROR(_xlfn.XLOOKUP($K49,Multiples!$B:$B,Multiples!O:O),"") -> -0.054994266 | P49: =IFERROR(_xlfn.XLOOKUP($K49,Multiples!$B:$B,Multiples!P:P),"") -> -0.082904196 | Q49: =IFERROR(_xlfn.XLOOKUP($K49,Multiples!$B:$B,Multiples!Q:Q),"") -> -0.067522536 | R49: =IFERROR(_xlfn.XLOOKUP($K49,Multiples!$B:$B,Multiples!R:R),"") -> -0.85664771 | U49: Board of Directors
K50: Total Debt / (EBITDA - Capex) | N50: =IFERROR(_xlfn.XLOOKUP($K50,Multiples!$B:$B,Multiples!N:N),"") -> -0.043686493 | O50: =IFERROR(_xlfn.XLOOKUP($K50,Multiples!$B:$B,Multiples!O:O),"") -> -0.048553868 | P50: =IFERROR(_xlfn.XLOOKUP($K50,Multiples!$B:$B,Multiples!P:P),"") -> -0.074672452 | Q50: =IFERROR(_xlfn.XLOOKUP($K50,Multiples!$B:$B,Multiples!Q:Q),"") -> -0.0596875 | R50: =IFERROR(_xlfn.XLOOKUP($K50,Multiples!$B:$B,Multiples!R:R),"") -> -0.72976311 | U50: Peter Chapman (Chairman, Executive Chair) [Non-Indep.], Chair of Executive Committee; Niccolo de Masi (CEO) [Non-Indep.], Member of Executive Committee; Harry You [Indep.], Lead Independent Director, Chair of Audit Committee; Inder Singh [Indep.], Member of Audit Committee; Kathy Chou [Indep.], Member of Compensation Committee; Wendy Thomas [Indep.], Member of Compensation Committee; Robert Cardillo [Indep.], Member of Nominating & Governance Committee; William Scannell [Indep.], Member of Compensation Committee; Gabrielle Toledano [Indep.], Member of Nominating & Governance Committee
K51: Net Debt / EBITDA | N51: =IFERROR(_xlfn.XLOOKUP($K50,Multiples!$B:$B,Multiples!N:N),"") -> -0.043686493 | O51: =IFERROR(_xlfn.XLOOKUP($K50,Multiples!$B:$B,Multiples!O:O),"") -> -0.048553868 | P51: =IFERROR(_xlfn.XLOOKUP($K50,Multiples!$B:$B,Multiples!P:P),"") -> -0.074672452 | Q51: =IFERROR(_xlfn.XLOOKUP($K50,Multiples!$B:$B,Multiples!Q:Q),"") -> -0.0596875 | R51: =IFERROR(_xlfn.XLOOKUP($K50,Multiples!$B:$B,Multiples!R:R),"") -> -0.72976311
K53: Solvency Ratios | N53: 2022 | O53: =+N53+1 -> 2023 | P53: =+O53+1 -> 2024 | Q53: =+P53+1 -> 2025 | R53: =+Q53+1 -> 2026
K54: EBIT / Interest Expense | N54: =IFERROR(_xlfn.XLOOKUP($K54,Multiples!$B:$B,Multiples!N:N),"") -> N/A | O54: =IFERROR(_xlfn.XLOOKUP($K54,Multiples!$B:$B,Multiples!O:O),"") -> N/A | P54: =IFERROR(_xlfn.XLOOKUP($K54,Multiples!$B:$B,Multiples!P:P),"") -> N/A | Q54: =IFERROR(_xlfn.XLOOKUP($K54,Multiples!$B:$B,Multiples!Q:Q),"") -> N/A | R54: =IFERROR(_xlfn.XLOOKUP($K54,Multiples!$B:$B,Multiples!R:R),"") -> N/A
K55: EBITDA / Interest Expense | N55: =IFERROR(_xlfn.XLOOKUP($K55,Multiples!$B:$B,Multiples!N:N),"") -> N/A | O55: =IFERROR(_xlfn.XLOOKUP($K55,Multiples!$B:$B,Multiples!O:O),"") -> N/A | P55: =IFERROR(_xlfn.XLOOKUP($K55,Multiples!$B:$B,Multiples!P:P),"") -> N/A | Q55: =IFERROR(_xlfn.XLOOKUP($K55,Multiples!$B:$B,Multiples!Q:Q),"") -> N/A | R55: =IFERROR(_xlfn.XLOOKUP($K55,Multiples!$B:$B,Multiples!R:R),"") -> N/A
K56: (EBITDA - Capex) / Interest Expense | N56: =IFERROR(_xlfn.XLOOKUP($K56,Multiples!$B:$B,Multiples!N:N),"") -> N/A | O56: =IFERROR(_xlfn.XLOOKUP($K56,Multiples!$B:$B,Multiples!O:O),"") -> N/A | P56: =IFERROR(_xlfn.XLOOKUP($K56,Multiples!$B:$B,Multiples!P:P),"") -> N/A | Q56: =IFERROR(_xlfn.XLOOKUP($K56,Multiples!$B:$B,Multiples!Q:Q),"") -> N/A | R56: =IFERROR(_xlfn.XLOOKUP($K56,Multiples!$B:$B,Multiples!R:R),"") -> N/A
D58: Debt Schedule | K58: Stock Performance
U60: ESG Traffic Light
U61: LSEG ESG Score | V61: =ESG!C14 -> 32
U62: E-Score | V62: =ESG!C15 -> 0
U63: S-Score | V63: =ESG!C16 -> 26
U64: G-Score | V64: =ESG!C17 -> 47
U65: S&P Global ESG Score | V65: =ESG!C18 -> N/A
U66: Environmental | V66: =ESG!C19 -> N/A
U67: Social | V67: =ESG!C20 -> N/A
U68: Governance & Economic | V68: =ESG!C21 -> N/A
U69: Sustainalytics | V69: =ESG!C22 -> 20
U70: ISS ESG Corporate Rating | V70: =ESG!C23 -> D
U71: SDG Impact Rating | V71: =ESG!C24 -> -8.4
U72: Governance Quality Score | V72: =ESG!C25 -> 8
U73: MSCI ESG Ratings | V73: =ESG!C26 -> N/A
D80: Extra Notes

Sheet Industry
B2: Industry Overview
B5: Key Drivers | E5: Description
B7: Limitations of Classical Computing | E7: Classical Computing is struggling with processing power, handling complex tasks with many variables and meeting the high energy requirements for AI systems, resulting in high costs and environmental concerns.
B8: Government and Private Sector Investment | E8: Governments and private companies are investing heavily in quantum computing, recognizing its potential to revolutionize industries like finance, healthcare, and cybersecurity. Notable examples include the U.S. government's $1.2 billion investment through the National Quantum Initiative Act and Microsoft's $1 billion commitment to R&D in Quantum Computing.
B9: Healthcare Personalizing | E9: A quantum computer can perform extremely fast DNA sequencing, which opens the possibility for personalized medicine. It can enable the development of new therapies and medicines through detailed modeling.
B10: Rapid Progression in Quantum Hardware | E10: Advancements in quantum hardware, such as improved qubit stability and error correction techniques, are enhancing the power and reliability of quantum computers. These developments are crucial for scaling quantum computing to address complex, industry specific challenges.
B12: Industry Trends | E12: Description
B14: Increasing Market Accessibility | E14: Cloud providers, such as Microsoft Azure and Google Cloud, are reshaping how businesses interact with quantum computing by lowering the barriers to access it and eliminating the need for expensive infrastructure. Greater accessibility allows for greater customer reach and, in turn, accelerated industry growth.
B15: Innovation Driven by Partnerships | E15: Companies, be it tech giants or startups, are increasingly forming strategic partnerships to tackle technical challenges and accelerate quantum technology. This shift from competitive rivalry to cooperation is aimed at solving shared problems and meet evolving market demands.
B16: Quantum Solutions as a Complement | E16: Faced with the limitations of classical computing systems and the early-stage challenges of quantum, businesses are integrating both technologies into a hybrid system, unlocking new ways to solve complex issues that neither could solve alone.
B19: Market Share | E19: Headquarters | G19: Revenues | H19: (in MM of USD) | I19: Market Share
B21: {=+_FV(DCF!AA4,"Name")} -> IONQ, INC. | E21: College Park, Maryland | G21: {=TRANSPOSE(Peers!D97:N97)} -> 43073 | I21: =IFERROR(G21/$G$33,"") -> 0.037128696
B22: {=+_FV(Peers!A8,"Name")} -> RIGETTI COMPUTING, INC | E22: Berkeley, California | G22: 10790 | I22: =IFERROR(G22/$G$33,"") -> 0.0093009223
B23: {=+_FV(Peers!A9,"Name")} -> D-WAVE QUANTUM INC. | E23: Burnaby, Canada | G23: 8827 | I23: =IFERROR(G23/$G$33,"") -> 0.0076088268
B24: {=+_FV(Peers!A10,"Name")} -> QUANTUM COMPUTING INC. | E24: Leesburg, Virginia | G24: 373 | I24: =IFERROR(G24/$G$33,"") -> 0.00032152401
G25: 0
G26: 0
G27: 0
G28: 0
G29: 0
G30: 0
G31: 0
B32: Others | E32: -- | G32: =G33-SUM(G21:G31) -> 1097037 | I32: =IFERROR(G32/$G$33,"") -> 0.94564003
B33: Industry Size | E33: -- | G33: =DCF!G21 -> 1160100 | I33: 1
B35: Porter's Five Forces Analysis | E35: Rating | H35: Graph
B37: Threat of New Entrants | E37: =IFERROR(AVERAGE(E38:E43),"") -> 2.1666667
B38: Economies of scale | E38: 2
B39: Product differentiation | E39: 2
B40: Capital requirements | E40: 1
B41: Access to distribution channels | E41: 2
B42: Regulations | E42: 2
B43: Switching costs | E43: 4
B44: Bargaining Power of Suppliers | E44: =IFERROR(AVERAGE(E45:E49),"") -> 3.4
B45: Number of suppliers | E45: 4
B46: Uniqueness | E46: 4
B47: Switching Costs | E47: 4
B48: Forward Integration | E48: 2
B49: Industry Importance | E49: 3
B50: Bargaining Power of Customers | E50: =IFERROR(AVERAGE(E51:E55),"") -> 4.2
B51: Number of buyers | E51: 3
B52: Purchase size | E52: 4
B53: Switching costs | E53: 5
B54: Price sensitivity | E54: 4
B55: Informed buyers | E55: 5
B56: Competitive Rivalry | E56: =IFERROR(AVERAGE(E57:E61),"") -> 3.6
B57: Number of competitors | E57: 4
B58: Industry growth | E58: 2
B59: Similarities in what's offered | E59: 3
B60: Exit barriers | E60: 4
B61: Fixed costs | E61: 5
B62: Threat of Substitutes | E62: =IFERROR(AVERAGE(E63:E67),"") -> 1.75
B63: Relative price performance | E63: 3
B64: Customer willingness to go elsewhere | E64: 2
B65: The sense that products are similar | E65: 1
B66: Availability of close substitutes | E66: 1

Sheet Segments
B2: Segments
B4: Regions | D4: Weight | E4: 2020 | F4: =+E4+1 -> 2021 | G4: =+F4+1 -> 2022 | H4: =+G4+1 -> 2023 | I4: =+H4+1 -> 2024 | J4: ="CAGR "&$F$4&" - "&$I$4 -> CAGR 2021 - 2024 | K4: 2021 | L4: =+K4+1 -> 2022 | M4: =+L4+1 -> 2023 | N4: =+M4+1 -> 2024
B6: United States | D6: =IFERROR(I6/SUM($I$6:$I$7),"") -> 0.94523251 | E6: 0 | F6: 1889.1 | G6: 9175 | H6: 18703 | I6: 40714 | J6: =IFERROR((I6/F6)^(1/COUNT($G$4:$I$4))-1,"") -> 1.7828915 | K6: =IFERROR(F6-E6/E6,"") | L6: =IFERROR((G6-F6)/F6,"") -> 3.8568101 | M6: =IFERROR((H6-G6)/G6,"") -> 1.0384741 | N6: =IFERROR((I6-H6)/H6,"") -> 1.17687
B7: International | D7: =IFERROR(I7/SUM($I$6:$I$7),"") -> 0.054767488 | E7: 0 | F7: 209.9 | G7: 1956 | H7: 3339 | I7: 2359 | J7: =IFERROR((I7/F7)^(1/COUNT($G$4:$I$4))-1,"") -> 1.2399509 | K7: =IFERROR(F7-E7/E7,"") | L7: =IFERROR((G7-F7)/F7,"") -> 8.3187232 | M7: =IFERROR((H7-G7)/G7,"") -> 0.70705521 | N7: =IFERROR((I7-H7)/H7,"") -> -0.29350105
B8: Total | D8: =SUM(D6:D7) -> 1 | E8: =SUM(E6:E7) -> 0 | F8: =SUM(F6:F7) -> 2099 | G8: =SUM(G6:G7) -> 11131 | H8: =SUM(H6:H7) -> 22042 | I8: =SUM(I6:I7) -> 43073 | J8: =IFERROR((I8/F8)^(1/COUNT($G$4:$I$4))-1,"") -> 1.7377738 | K8: =IFERROR(F8-E8/E8,"") | L8: =IFERROR((G8-F8)/F8,"") -> 4.3030014 | M8: =IFERROR((H8-G8)/G8,"") -> 0.98023538 | N8: =IFERROR((I8-H8)/H8,"") -> 0.95413302
B10: Segments | D10: Weight | E10: 2020 | F10: =+E10+1 -> 2021 | G10: =+F10+1 -> 2022 | H10: =+G10+1 -> 2023 | I10: =+H10+1 -> 2024 | J10: ="CAGR "&$G$4&" - "&$I$4 -> CAGR 2022 - 2024 | K10: 2021 | L10: =+K10+1 -> 2022 | M10: =+L10+1 -> 2023 | N10: =+M10+1 -> 2024
B12: Specialized quantum computing hardware | D12: =IFERROR(I12/SUM($I$12:$I$13),"") -> 0.50133494 | E12: 0 | F12: 0 | G12: 239 | H12: 7083 | I12: 21594 | J12: =IFERROR((I12/G12)^(1/COUNT($H$4:$I$4))-1,"") -> 8.5053387 | K12: =IFERROR((F12-E12)/E12,"") | L12: =IFERROR((G12-F12)/F12,"") | M12: =IFERROR((H12-G12)/G12,"") -> 28.635983 | N12: =IFERROR((I12-H12)/H12,"") -> 2.0487082
B13: Platform, consulting and support services | D13: =IFERROR(I13/SUM($I$12:$I$13),"") -> 0.49866506 | E13: 0 | F13: 2099 | G13: 10892 | H13: 14959 | I13: 21479 | J13: =IFERROR((I13/G13)^(1/COUNT($H$4:$I$4))-1,"") -> 0.40427839 | K13: =IFERROR((F13-E13)/E13,"") | L13: =IFERROR((G13-F13)/F13,"") -> 4.1891377 | M13: =IFERROR((H13-G13)/G13,"") -> 0.37339332 | N13: =IFERROR((I13-H13)/H13,"") -> 0.43585801
B14: Total | D14: =SUM(D12:D13) -> 1 | E14: =SUM(E12:E13) -> 0 | F14: =SUM(F12:F13) -> 2099 | G14: =SUM(G12:G13) -> 11131 | H14: =SUM(H12:H13) -> 22042 | I14: =SUM(I12:I13) -> 43073 | J14: =IFERROR((I14/G14)^(1/COUNT($H$4:$I$4))-1,"") -> 0.9671409 | K14: =IFERROR((F14-E14)/E14,"") | L14: =IFERROR((G14-F14)/F14,"") -> 4.3030014 | M14: =IFERROR((H14-G14)/G14,"") -> 0.98023538 | N14: =IFERROR((I14-H14)/H14,"") -> 0.95413302
B16: Categories | D16: Description | J16: Graphs
B18: Specialized quantum computing hardware | D18: This segment focuses on building advanced quantum processors using trapped-ion technology. These processors deliver highly accurate and stable qubits, making them ideal for tackling complex problems. IonQ’s hardware powers its cloud services, allowing customers to access cutting-edge quantum computing for various applications.
B19: Platform, consulting and support services | D19: These services provide businesses and researchers with the tools, expertise, and support needed to effectively adopt and utilize quantum computing. They include cloud access, technical assistance, and specialized consulting.
B20: =IF(#REF!=0,"",#REF!) -> #REF!
B21: =IF(#REF!=0,"",#REF!) -> #REF!
B24: Company's Strategy / Extra Notes
B26: Tech Innovation | D26: This year marks the launch of the AQ 64 Tempo system, which is a substantial upgrade over the AQ36 Forte Enterprise. This system doubles the qubit count, improves qubit fidelity to over 99.9% and expands computational capacity by 536 million times, setting new standards in performance.
B27: Strategic Acquisitions | D27: In 2025, the company acquired Qubitekk and ID Quantique, gaining access to a more specialized team and increasing its patent portfolio to over 900 patents. These acquisitions also position the company for expansion into European and Asian markets, accelerating global growth.
B28: Major Partnerships | D28: Partnerships with major companies and entities such as AstraZeneca, Hyundai, U.S. Department of Defense and Airbus will help the company in the long-term, accelerating its growth and increasing its global credibility.
B29: Revenue Scaling | D29: Revenue has doubled in both 2023 and 2024, reflecting strong market demand and growth. Management expects this trend to continue with projections of $75-95 million in revenue for 2025.
B30: First Public Quantum Company | D30: In 2021, the company made history by becoming the first pure-play quantum computing company to go public. This was achieved through a merger with dMY Technology Group III, a special-purpose acquisition company (SPAC).

Sheet Peers
D3: Revenue Growth | F3: EBITDA Margin | H3: Profit Margin | J3: EV / Revenue | L3: EV / EBITDA | N3: Price / Earnings
B4: Peers | C4: Ticker | D4: =+Inputs!O4&"-"&Inputs!P4 -> 2022-2023 | E4: =+Inputs!P4&"-"&Inputs!Q4 -> 2023-2024 | F4: 2023 | G4: 2024 | H4: =+Inputs!O4&"-"&Inputs!P4 -> 2022-2023 | I4: =+Inputs!P4&"-"&Inputs!Q4 -> 2023-2024 | J4: 2023 | K4: 2024 | L4: 2023 | M4: 2024 | N4: 2023 | O4: 2024
A6: =+D91 -> #VALUE! | B6: {=IFERROR(_FV(A6,"Name"),"")} -> IONQ, INC. | C6: {=IFERROR(_FV(A6,"Ticker symbol",TRUE),"")} -> IONQ | D6: =IFERROR(D94/D93-1,"") -> 0.98023538 | E6: =IFERROR(D97/D94-1,"") -> 0.95413302 | F6: =IFERROR(D95/D94,"") -> -6.6862807 | G6: =IFERROR(D100/D97,"") -> -4.9636896 | H6: =IFERROR(D96/D94,"") -> -7.1555688 | I6: =IFERROR(D105/D97,"") -> -7.698281 | J6: {=IFERROR((_FV(A6,"Market cap",TRUE)/1000+D$121-D$111)/D$94,"")} -> 741.23244 | K6: {=IFERROR((_FV(A6,"Market cap",TRUE)/1000+D$121-D$111)/D$97,"")} -> 379.31524 | L6: {=+IFERROR((_FV(A6,"Market cap",TRUE)/1000+D$121-D$111)/D$95,"")} -> -110.85871 | M6: {=IFERROR((_FV(A6,"Market cap",TRUE)/1000+D$121-D$111)/D$100,"")} -> -76.418003 | N6: {=IFERROR((_FV(A6,"Market cap",TRUE)/1000)/D$96,"")} -> -103.82068 | O6: {=IFERROR((_FV(A6,"Market cap",TRUE)/1000)/D$105,"")} -> -49.383303
A8: =+E91 -> #VALUE! | B8: {=IFERROR(_FV(A8,"Name"),"")} -> RIGETTI COMPUTING, INC | C8: {=+IFERROR(_FV(A8,"Ticker symbol",TRUE),"")} -> RGTI | D8: =+IFERROR(E94/E93-1,"") -> -0.083498702 | E8: =IFERROR(E97/E94-1,"") -> -0.10143238 | F8: =IFERROR(E95/E94,"") -> -5.1550633 | G8: =+IFERROR(E100/E97,"") -> -6.3493976 | H8: =IFERROR(E96/E94,"") -> -6.2547468 | I8: =+IFERROR(E105/E99,"") -> -13.563981 | J8: {=+IFERROR((_FV(A8,"Market cap",TRUE)/1000+E$121-E$111)/E$94,"")} -> 517.0603 | K8: {=IFERROR(+(_FV(A8,"Market cap",TRUE)/1000+E$121-E$111)/E$97,"")} -> 575.42726 | L8: {=IFERROR(+(_FV(A8,"Market cap",TRUE)/1000+E$121-E$111)/E$95,"")} -> -100.30145 | M8: {=IFERROR(+(_FV(A8,"Market cap",TRUE)/1000+E$121-E$111)/E$100,"")} -> -90.627064 | N8: {=IFERROR(+(_FV(A8,"Market cap",TRUE)/1000)/E$96,"")} -> -83.450732 | O8: {=IFERROR(+(_FV(A8,"Market cap",TRUE)/1000)/E$105,"")} -> -81.110518
A9: =+F91 -> #VALUE! | B9: {=IFERROR(_FV(A9,"Name"),"")} -> D-WAVE QUANTUM INC. | C9: {=+IFERROR(_FV(A9,"Ticker symbol",TRUE),"")} -> QBTS | D9: =IFERROR(F94/F93-1,"") -> 0.22096752 | E9: =IFERROR(+F97/F94-1,"") -> 0.0078785111 | F9: =IFERROR(F95/F94,"") -> -8.6118977 | G9: =IFERROR(F100/F97,"") -> -8.7484989 | H9: =IFERROR(F96/F94,"") -> -9.4445079 | I9: =+IFERROR(F105/F97,"") -> -8.5258865 | J9: {=IFERROR(+(_FV(A9,"Market cap",TRUE)/1000+F$121-F$111)/F$94,"")} -> 679.96838 | K9: {=IFERROR(+(_FV(A9,"Market cap",TRUE)/1000+F$121-F$111)/F$97,"")} -> 674.65312 | L9: {=IFERROR(+(_FV(A9,"Market cap",TRUE)/1000+F$121-F$111)/F$95,"")} -> -78.956858 | M9: {=IFERROR(+(_FV(A9,"Market cap",TRUE)/1000+F$121-F$111)/F$100,"")} -> -77.116443 | N9: {=IFERROR(+(_FV(A9,"Market cap",TRUE)/1000)/F$96,"")} -> -73.683928 | O9: {=IFERROR(+(_FV(A9,"Market cap",TRUE)/1000)/F$105,"")} -> -80.98496
A10: =+G91 -> #VALUE! | B10: {=IFERROR(_FV(A10,"Name"),"")} -> QUANTUM COMPUTING INC. | C10: {=IFERROR(_FV(A10,"Ticker symbol",TRUE),"")} -> QUBT | D10: =+IFERROR(G94/G93-1,"") -> 1.6323529 | E10: =IFERROR(G97/G94-1,"") -> 0.041899441 | F10: =IFERROR(G95/G94,"") -> -61.768156 | G10: =IFERROR(G100/G97,"") -> -69.536193 | H10: =IFERROR(G96/G94,"") -> -75.480447 | I10: =+IFERROR(G105/G97,"") -> -74.160858 | J10: {=IFERROR(+(_FV(A10,"Market cap",TRUE)/1000+G$121-G$111)/G$94,"")} -> 7372.7681 | K10: {=IFERROR(+(_FV(A10,"Market cap",TRUE)/1000+G$121-G$111)/G$97,"")} -> 7076.2761 | L10: {=IFERROR(+(_FV(A10,"Market cap",TRUE)/1000+G$121-G$111)/G$95,"")} -> -119.36196 | M10: {=IFERROR(+(_FV(A10,"Market cap",TRUE)/1000+G$121-G$111)/G$100,"")} -> -101.76393 | N10: {=IFERROR(+(_FV(A10,"Market cap",TRUE)/1000)/G$96,"")} -> -100.55566 | O10: {=IFERROR(+(_FV(A10,"Market cap",TRUE)/1000)/G$105,"")} -> -98.229159
A11: =+H91 -> N/A | B11: {=IFERROR(_FV(A11,"Name"),"")} | C11: {=IFERROR(_FV(A11,"Ticker symbol",TRUE),"")} | D11: =IFERROR(H94/H93-1,"") | E11: =IFERROR(H97/H94-1,"") | F11: =IFERROR(H95/H94,"") | G11: =IFERROR(H100/H97,"") | H11: =IFERROR(H96/H94,"") | I11: =+IFERROR(H105/H102,"") | J11: {=IFERROR((_FV(A11,"Market cap",TRUE)/1000000+H$121-H$111)/H$94,"")} | K11: {=IFERROR(+(_FV(A11,"Market cap",TRUE)/1000000+H$121-H$111)/H$97,"")} | L11: {=IFERROR(+(_FV(A11,"Market cap",TRUE)/1000000+H$121-H$111)/H$95,"")} | M11: {=IFERROR(+(_FV(A11,"Market cap",TRUE)/1000000+H$121-H$111)/H$100,"")} | N11: {=IFERROR(+(_FV(A11,"Market cap",TRUE)/1000000)/H$96,"")} | O11: {=IFERROR(+(_FV(A11,"Market cap",TRUE)/1000000)/H$105,"")}
A12: =+I91 -> N/A | B12: {=IFERROR(_FV(A12,"Name"),"")} | C12: {=IFERROR(_FV(A12,"Ticker symbol",TRUE),"")} | D12: =+IFERROR(I94/I93-1,"") | E12: =IFERROR(I97/I94-1,"") | F12: =IFERROR(I95/I94,"") | G12: =IFERROR(I100/I97,"") | H12: =IFERROR(I96/I94,"") | I12: =+IFERROR(I105/I97,"") | J12: {=IFERROR((_FV(A12,"Market cap",TRUE)/1000000+I$121-I$111)/I$94,"")} | K12: {=IFERROR(+(_FV(A12,"Market cap",TRUE)/1000000+I$121-I$111)/I$97,"")} | L12: {=IFERROR(+(_FV(A12,"Market cap",TRUE)/1000000+I$121-I$111)/I$95,"")} | M12: {=IFERROR(+(_FV(A12,"Market cap",TRUE)/1000000+I$121-I$111)/I$100,"")} | N12: {=IFERROR(+(_FV(A12,"Market cap",TRUE)/1000000)/I$96,"")} | O12: {=IFERROR(+(_FV(A12,"Market cap",TRUE)/1000000)/I$105,"")}
A13: =+J91 -> N/A | B13: {=IFERROR(_FV(A13,"Name"),"")} | C13: {=IFERROR(_FV(A13,"Ticker symbol",TRUE),"")} | D13: =IFERROR(J94/J93-1,"") | E13: =IFERROR(J97/J94-1,"") | F13: =IFERROR(J95/J94,"") | G13: =IFERROR(J100/J97,"") | H13: =IFERROR(J96/J94,"") | I13: =+IFERROR(J105/J97,"") | J13: {=IFERROR(+(_FV(A13,"Market cap",TRUE)/1000000+J$121-J$111)/J$94,"")} | K13: {=IFERROR(+(_FV(A13,"Market cap",TRUE)/1000000+J$121-J$111)/J$97,"")} | L13: {=IFERROR(+(_FV(A13,"Market cap",TRUE)/1000000+J$121-J$111)/J$95,"")} | M13: {=IFERROR(+(_FV(A13,"Market cap",TRUE)/1000000+J$121-J$111)/J$100,"")} | N13: {=IFERROR(+(_FV(A13,"Market cap",TRUE)/1000000)/J$96,"")} | O13: {=IFERROR(+(_FV(A13,"Market cap",TRUE)/1000000)/J$105,"")}
A14: =+K91 -> N/A | B14: {=IFERROR(_FV(A14,"Name"),"")} | C14: {=IFERROR(_FV(A14,"Ticker symbol",TRUE),"")} | D14: =IFERROR(K94/K93-1,"") | E14: =IFERROR(K97/K94-1,"") | F14: =+IFERROR(K95/K94,"") | G14: =IFERROR(K100/K97,"") | H14: =IFERROR(K96/K94,"") | I14: =+IFERROR(K105/K97,"") | J14: {=IFERROR((_FV(A14,"Market cap",TRUE)/1000000+D$121-K$111)/K$94,"")} | K14: {=IFERROR(+(_FV(A14,"Market cap",TRUE)/1000000+D$121-K$111)/K$97,"")} | L14: {=IFERROR(+(_FV(A14,"Market cap",TRUE)/1000000+D$121-K$111)/K$95,"")} | M14: {=IFERROR(+(_FV(A14,"Market cap",TRUE)/1000000+D$121-K$111)/K$100,"")} | N14: {=IFERROR(+(_FV(A14,"Market cap",TRUE)/1000000)/K$96,"")} | O14: {=IFERROR(+(_FV(A14,"Market cap",TRUE)/1000000)/K$105,"")}
A15: =+L91 -> N/A | B15: {=IFERROR(_FV(A15,"Name"),"")} | C15: {=IFERROR(_FV(A15,"Ticker symbol",TRUE),"")} | D15: =+IFERROR(L94/L93,"") | E15: =IFERROR(L97/L94,"") | F15: =IFERROR(L95/L94,"") | G15: =IFERROR(L100/L97,"") | H15: =IFERROR(L96/L94,"") | I15: =+IFERROR(L105/L97,"") | J15: {=IFERROR(+(_FV(A15,"Market cap",TRUE)/1000000+L$121-L$111)/L$94,"")} | K15: {=IFERROR(+(_FV(A15,"Market cap",TRUE)/1000000+L$121-L$111)/L$97,"")} | L15: {=IFERROR(+(_FV(A15,"Market cap",TRUE)/1000000+L$121-L$111)/L$95,"")} | M15: {=IFERROR(+(_FV(A15,"Market cap",TRUE)/1000000+L$121-L$111)/L$100,"")} | N15: {=IFERROR(+(_FV(A15,"Market cap",TRUE)/1000000)/L$96,"")} | O15: {=IFERROR(+(_FV(A15,"Market cap",TRUE)/1000000)/L$105,"")}
A16: =+M91 -> N/A | B16: {=IFERROR(_FV(A16,"Name"),"")} | C16: {=IFERROR(_FV(A16,"Ticker symbol",TRUE),"")} | D16: =IFERROR(M94/M93-1,"") | E16: =IFERROR(M97/M94-1,"") | F16: =IFERROR(M95/M94,"") | G16: =IFERROR(M100/M97,"") | H16: =IFERROR(M96/M94,"") | I16: =+IFERROR(M105/M97,"") | J16: {=IFERROR(+(_FV(A16,"Market cap",TRUE)/1000000+M$121-M$111)/M$94,"")} | K16: {=IFERROR(+(_FV(A16,"Market cap",TRUE)/1000000+M$121-M$111)/M$97,"")} | L16: {=IFERROR(+(_FV(A16,"Market cap",TRUE)/1000000+M$121-M$111)/M$95,"")} | M16: {=IFERROR(+(_FV(A16,"Market cap",TRUE)/1000000+M$121-M$111)/M$100,"")} | N16: {=IFERROR(+(_FV(A16,"Market cap",TRUE)/1000000)/M$96,"")} | O16: {=IFERROR(+(_FV(A16,"Market cap",TRUE)/1000000)/M$105,"")}
A17: =+N91 -> N/A | B17: {=IFERROR(_FV(A17,"Name"),"")} | C17: {=+IFERROR(_FV(A17,"Ticker symbol",TRUE),"")} | D17: =IFERROR(N94/N93-1,"") | E17: =IFERROR(N97/N94-1,"") | F17: =IFERROR(N95/N94,"") | G17: =IFERROR(N100/N97,"") | H17: =IFERROR(N96/N94,"") | I17: =+IFERROR(N105/N97,"") | J17: {=IFERROR(+(_FV(A17,"Market cap",TRUE)/1000000+N$121-N$111)/N$94,"")} | K17: {=IFERROR(+(_FV(A17,"Market cap",TRUE)/1000000+N$121-N$111)/N$97,"")} | L17: {=IFERROR(+(_FV(A17,"Market cap",TRUE)/1000000+N$121-N$111)/N$95,"")} | M17: {=IFERROR(+(_FV(A17,"Market cap",TRUE)/1000000+N$121-N$111)/N$100,"")} | N17: {=IFERROR(+(_FV(A17,"Market cap",TRUE)/1000000)/N$96,"")} | O17: {=IFERROR(+(_FV(A17,"Market cap",TRUE)/1000000)/N$105,"")}
B18: Average | D18: =IFERROR(AVERAGE(D6:D17),"") -> 0.68751428 | E18: =IFERROR(AVERAGE(E6:E17),"") -> 0.22561965 | F18: =IFERROR(AVERAGE(F6:F17),"") -> -20.55535 | G18: =IFERROR(AVERAGE(G6:G17),"") -> -22.399445 | H18: =IFERROR(AVERAGE(H6:H17),"") -> -24.583818 | I18: =IFERROR(AVERAGE(I6:I17),"") -> -25.987252 | J18: =IFERROR(AVERAGE(J6:J17),"") -> 2327.7573 | K18: =IFERROR(AVERAGE(K6:K17),"") -> 2176.4179 | ... O18: =IFERROR(AVERAGE(O6:O17),"") -> -77.426985
B19: Deviation from Average | D19: =IFERROR(+D18-D6,"") -> -0.2927211 | E19: =IFERROR(E18-E6,"") -> -0.72851337 | F19: =+IFERROR(F18-F6,"") -> -13.869069 | G19: =IFERROR(G18-G6,"") -> -17.435755 | H19: =IFERROR(+H6-H18,"") -> 17.428249 | I19: =+IFERROR(I6-I18,"") -> 18.288971 | J19: =+IFERROR(J6-J18,"") -> -1586.5249 | K19: =+IFERROR(K6-K18,"") -> -1797.1027 | L19: =IFERROR(+L6-L18,"") -> -8.4889649 | M19: =IFERROR(M6-M18,"") -> 10.063356 | N19: =IFERROR(+N6-N18,"") -> -13.442927 | O19: =IFERROR(+O6-O18,"") -> 28.043682 | T19: {=_FV(A6,"Market cap",TRUE)} -> 16374913459
D21: Trading Multiple | G21: Net | H21: Preferred | I21: Non-Controlling | J21: Equity Value | M21: Implied Upside (Downside)
B22: Implied Share Price | D22: Revenue | E22: EBITDA | F22: P/E | G22: Debt | H22: Stock | I22: Interest | J22: Revenue | K22: EBITDA | L22: P/E | M22: Revenue | N22: EBITDA | O22: P/E | P22: Current Price
B24: Second Minimum | D24: =IFERROR(SMALL(K6:K17,2),"") -> 575.42726 | E24: =IFERROR(SMALL(M6:M17,2),"") -> -90.627064 | F24: =IFERROR(SMALL(O6:O17,2),"") -> -81.110518 | G24: =-Inputs!$Q$99+Inputs!$Q$100 -> -322564 | H24: =+Inputs!$Q$101 -> 0 | I24: =+Inputs!$Q$102 -> 0 | J24: =IFERROR(+D24*$D$97+G24+H24+I24,"") -> 24462814 | K24: =IFERROR(E24*$D$100+G24+H24+I24,"") -> 19053593 | L24: =IFERROR(F24*$D$105,"") -> 26895279 | M24: {=IFERROR(+(J24/_FV($A$6,"Shares outstanding",TRUE)*1000000)/$P$24-1,"")} -> 1492.9202 | N24: {=IFERROR((+K24/_FV($A$6,"Shares outstanding",TRUE)*1000000)/$P$24-1,"")} -> 1162.5843 | O24: {=IFERROR(+(L24/_FV($A$6,"Shares outstanding",TRUE)*1000000)/$P$24-1,"")} -> 1641.4685 | P24: {=+_FV(A6,"Price")} -> 55.008
B25: Average | D25: =+IFERROR(AVERAGE(K6:K17),"") -> 2176.4179 | E25: =IFERROR(+AVERAGE(M6:M17),"") -> -86.481359 | F25: =IFERROR(+AVERAGE(O6:O17),"") -> -77.426985 | G25: =-Inputs!$Q$99+Inputs!$Q$100 -> -322564 | H25: =+Inputs!$Q$101 -> 0 | I25: =+Inputs!$Q$102 -> 0 | J25: =IFERROR(+D25*$D$97+G25+H25+I25,"") -> 93422286 | K25: =IFERROR(E25*$D$100+G25+H25+I25,"") -> 18167237 | L25: =IFERROR(+F25*$D$105,"") -> 25673864 | M25: {=IFERROR(+(J25/_FV($A$6,"Shares outstanding",TRUE)*1000000)/$P$24-1,"")} -> 5704.2079 | N25: {=IFERROR((+K25/_FV($A$6,"Shares outstanding",TRUE)*1000000)/$P$24-1,"")} -> 1108.4555 | O25: {=IFERROR(+(L25/_FV($A$6,"Shares outstanding",TRUE)*1000000)/$P$24-1,"")} -> 1566.8778
B26: Median | D26: =IFERROR(MEDIAN(K6:K17),"") -> 625.04019 | E26: =IFERROR(MEDIAN(M6:M17),"") -> -83.871754 | F26: =IFERROR(MEDIAN(O6:O17),"") -> -81.047739 | G26: =-Inputs!$Q$99+Inputs!$Q$100 -> -322564 | H26: =+Inputs!$Q$101 -> 0 | I26: =+Inputs!$Q$102 -> 0 | J26: =IFERROR(D26*$D$97+G26+H26+I26,"") -> 26599792 | K26: =IFERROR(E26*$D$100+G26+H26+I26,"") -> 17609301 | L26: =IFERROR(+F26*$D$105,"") -> 26874462 | M26: {=IFERROR(+(J26/_FV($A$6,"Shares outstanding",TRUE)*1000000)/$P$24-1,"")} -> 1623.4234 | N26: {=IFERROR((+K26/_FV($A$6,"Shares outstanding",TRUE)*1000000)/$P$24-1,"")} -> 1074.3828 | O26: {=+IFERROR((L26/_FV($A$6,"Shares outstanding",TRUE)*1000000)/$P$24-1,"")} -> 1640.1972
B27: Second Maximum | D27: =IFERROR(LARGE(K6:K17,2),"") -> 674.65312 | E27: =IFERROR(LARGE(M6:M17,2),"") -> -77.116443 | F27: =IFERROR(LARGE(O6:O17,2),"") -> -80.98496 | G27: =-Inputs!$Q$99+Inputs!$Q$100 -> -322564 | H27: =+Inputs!$Q$101 -> 0 | I27: =+Inputs!$Q$102 -> 0 | J27: =IFERROR(+D27*$D$97+G27+H27+I27,"") -> 28736770 | K27: =IFERROR(E27*$D$100+G27+H27+I27,"") -> 16165009 | L27: =IFERROR(+F27*$D$105,"") -> 26853646 | M27: {=IFERROR(+(J27/_FV($A$6,"Shares outstanding",TRUE)*1000000)/$P$24-1,"")} -> 1753.9265 | N27: {=IFERROR((+K27/_FV($A$6,"Shares outstanding",TRUE)*1000000)/$P$24-1,"")} -> 986.18132 | O27: {=IFERROR(+(L27/_FV($A$6,"Shares outstanding",TRUE)*1000000)/$P$24-1,"")} -> 1638.926
B29: Profitability | D29: =+LEFT(B6, FIND(" ", B6 & " ") - 1) -> IONQ, | E29: =+LEFT(B8, FIND(" ", B8 & " ") - 1) -> RIGETTI | F29: =+LEFT(B9, FIND(" ", B9 & " ") - 1) -> D-WAVE | G29: =+LEFT(B10, FIND(" ", B10 & " ") - 1) -> QUANTUM | H29: =+LEFT(B11, FIND(" ", B11 & " ") - 1) | I29: =+LEFT(B12, FIND(" ", B12 & " ") - 1) | J29: =+LEFT(B13, FIND(" ", B13 & " ") - 1) | K29: =+LEFT(B14, FIND(" ", B14 & " ") - 1) | L29: =+LEFT(B15, FIND(" ", B15 & " ") - 1) | M29: =+LEFT(B16, FIND(" ", B16 & " ") - 1) | N29: =+LEFT(B17, FIND(" ", B17 & " ") - 1) | O29: Average
B31: Operating Margin | D31: =IFERROR(D101/D97,"") -> -5.3967683 | E31: =IFERROR(E101/E97,"") -> -6.9894347 | F31: =IFERROR(F101/F97,"") -> -8.9673728 | G31: =IFERROR(G101/G97,"") -> -79.718499 | H31: =IFERROR(H101/H97,"") | I31: =IFERROR(I101/I97,"") | J31: =IFERROR(J101/J97,"") | K31: =IFERROR(K101/K97,"") | ... N31: =IFERROR(N101/N97,"") | O31: =IFERROR(+AVERAGE(D31:N31),"") -> -25.268019
B32: Net Income Margin | D32: =IFERROR(D105/D97,"") -> -7.698281 | E32: =IFERROR(E105/E97,"") -> -7.1616311 | F32: =IFERROR(F105/F97,"") -> -8.5258865 | G32: =IFERROR(G105/G97,"") -> -74.160858 | H32: =IFERROR(H105/H97,"") | I32: =IFERROR(I105/I97,"") | J32: =IFERROR(J105/J97,"") | K32: =IFERROR(K105/K97,"") | ... N32: =IFERROR(N105/N97,"") | O32: =IFERROR(+AVERAGE(D32:N32),"") -> -24.386664
B33: ROA (%) | D33: =IFERROR(D105/D117,"") -> -0.65223424 | E33: =IFERROR(E105/E117,"") -> -0.27133963 | F33: =IFERROR(F105/F117,"") -> -0.37656678 | G33: =IFERROR(G105/G117,"") -> -0.18013923 | H33: =IFERROR(H105/H117,"") | I33: =IFERROR(I105/I117,"") | J33: =IFERROR(J105/J117,"") | K33: =IFERROR(K105/K117,"") | ... N33: =IFERROR(N105/N117,"") | O33: =IFERROR(+AVERAGE(D33:N33),"") -> -0.37006997
B34: Financial Cost of Debt | D34: =IFERROR(+(D102/D121)*(1-(D104/D103)),"") -> -1.0295629 | E34: =IFERROR(+(E102/E121)*(1-(E104/E103)),"") -> 0.21113636 | F34: =IFERROR(+(F102/F121)*(1-(F104/F103)),"") -> -0.1015452 | G34: =IFERROR(+(G102/G121)*(1-(G104/G103)),"") -> -1.7552921 | H34: =IFERROR(+(H102/H121)*(1-(H104/H103)),"") | I34: =IFERROR(+(I102/I121)*(1-(I104/I103)),"") | J34: =IFERROR(+(J102/J121)*(1-(J104/J103)),"") | K34: =IFERROR(+(K102/K121)*(1-(K104/K103)),"") | ... N34: =IFERROR(+(N102/N121)*(1-(N104/N103)),"") | O34: =IFERROR(+AVERAGE(D34:N34),"") -> -0.66881598
B35: Return on Equity (RoE) | D35: =IFERROR(+D105/D122,"") -> -0.86382101 | E35: =IFERROR(+E105/E122,"") -> -0.61043219 | F35: =IFERROR(+F105/F122,"") -> -1.2013217 | G35: =IFERROR(+G105/G122,"") -> -0.2578318 | H35: =IFERROR(+H105/H122,"") | I35: =IFERROR(+I105/I122,"") | J35: =IFERROR(+J105/J122,"") | K35: =IFERROR(+K105/K122,"") | ... N35: =IFERROR(+N105/N122,"") | O35: =IFERROR(+AVERAGE(D35:N35),"") -> -0.73335168
B36: Return on Invested Capital (ROIC) | D36: =IFERROR(+D105/(D121+D122),"") -> -0.82569421 | E36: =IFERROR(+E105/(E121+E122),"") -> -0.57075538 | F36: =IFERROR(+F105/(F121+F122),"") -> -0.74495907 | G36: =IFERROR(+G105/(G121+G122),"") -> -0.25502452 | H36: =IFERROR(+H105/(H121+H122),"") | I36: =IFERROR(+I105/(I121+I122),"") | J36: =IFERROR(+J105/(J121+J122),"") | K36: =IFERROR(+K105/(K121+K122),"") | ... N36: =IFERROR(+N105/(N121+N122),"") | O36: =IFERROR(+AVERAGE(D36:N36),"") -> -0.59910829
B38: Solvency | D38: =+D29 -> IONQ, | E38: =+E29 -> RIGETTI | F38: =+F29 -> D-WAVE | G38: =+G29 -> QUANTUM | H38: =+H29 | I38: =+I29 | J38: =+J29 | K38: =+K29 | ... O38: =+O29 -> Average
B40: Debt/Assets | D40: =IFERROR(D121/D117,"") -> 0.034865103 | E40: =IFERROR(E121/E117,"") -> 0.030900287 | F40: =IFERROR(F121/F117,"") -> 0.19202614 | G40: =IFERROR(G121/G117,"") -> 0.007690855 | H40: =IFERROR(H121/H117,"") | I40: =IFERROR(I121/I117,"") | J40: =IFERROR(J121/J117,"") | K40: =IFERROR(K121/K117,"") | ... N40: =IFERROR(N121/N117,"") | O40: =IFERROR(+AVERAGE(D40:N40),"") -> 0.066370596
B41: Net Debt/EBITDA | D41: =IFERROR(+(D121-D111)/D100,"") -> 0.17150528 | E41: =IFERROR(+(E121-E111)/E100,"") -> 0.859349 | F41: =IFERROR(+(F121-F111)/F100,"") -> 1.8077904 | G41: =IFERROR(+(G121-G111)/G100,"") -> 2.9981879 | H41: =IFERROR(+(H121-H111)/H100,"") | I41: =IFERROR(+(I121-I111)/I100,"") | J41: =IFERROR(+(J121-J111)/J100,"") | K41: =IFERROR(+(K121-K111)/K100,"") | ... N41: =IFERROR(+(N121-N111)/N100,"") | O41: =IFERROR(+AVERAGE(D41:N41),"") -> 1.4592082
B42: Interest Coverage Ratio | D42: =IFERROR(D101/D102,"") -> 12.737958 | E42: =IFERROR(E101/E102,"") -> -40.589882 | F42: =IFERROR(F101/F102,"") -> 20.311778 | G42: =IFERROR(G101/G102,"") -> 14.343946 | H42: =IFERROR(H101/H102,"") | I42: =IFERROR(I101/I102,"") | J42: =IFERROR(J101/J102,"") | K42: =IFERROR(K101/K102,"") | ... N42: =IFERROR(N101/N102,"") | O42: =IFERROR(+AVERAGE(D42:N42),"") -> 1.7009502
B44: Liquidity | D44: =+D29 -> IONQ, | E44: =+E29 -> RIGETTI | F44: =+F29 -> D-WAVE | G44: =+G29 -> QUANTUM | H44: =+H29 | I44: =+I29 | J44: =+J29 | K44: =+K29 | ... O44: =+O29 -> Average
B46: Cash Ratio | D46: =IFERROR(D111/D119,"") -> 1.5073576 | E46: =IFERROR(E111/E119,"") -> 5.702705 | F46: =IFERROR(F111/F119,"") -> 5.90413 | G46: =IFERROR(G111/G119,"") -> 17.316297 | H46: =IFERROR(H111/H119,"") | I46: =IFERROR(I111/I119,"") | J46: =IFERROR(J111/J119,"") | K46: =IFERROR(K111/K119,"") | ... N46: =IFERROR(N111/N119,"") | O46: =IFERROR(+AVERAGE(D46:N46),"") -> 7.6076225
B47: Quick Ratio | D47: =IFERROR(+(D111+D112)/D119,"") -> 1.6879313 | E47: =IFERROR(+(E111+E112)/E119,"") -> 5.9072217 | F47: =IFERROR(+(F111+F112)/F119,"") -> 5.9512357 | G47: =IFERROR(+(G111+G112)/G119,"") -> 17.32222 | H47: =IFERROR(+(H111+H112)/H119,"") | I47: =IFERROR(+(I111+I112)/I119,"") | J47: =IFERROR(+(J111+J112)/J119,"") | K47: =IFERROR(+(K111+K112)/K119,"") | ... N47: =IFERROR(+(N111+N112)/N119,"") | O47: =IFERROR(+AVERAGE(D47:N47),"") -> 7.7171521
B48: Current Ratio | D48: =IFERROR(D115/D119,"") -> 10.497492 | E48: =IFERROR(E115/E119,"") -> 17.422938 | F48: =IFERROR(F115/F119,"") -> 6.1383314 | G48: =IFERROR(G115/G119,"") -> 17.361483 | H48: =IFERROR(H115/H119,"") | I48: =IFERROR(I115/I119,"") | J48: =IFERROR(J115/J119,"") | K48: =IFERROR(K115/K119,"") | ... N48: =IFERROR(N115/N119,"") | O48: =IFERROR(+AVERAGE(D48:N48),"") -> 12.855061
B50: Activity | D50: =+D29 -> IONQ, | E50: =+E29 -> RIGETTI | F50: =+F29 -> D-WAVE | G50: =+G29 -> QUANTUM | H50: =+H29 | I50: =+I29 | J50: =+J29 | K50: =+K29 | ... O50: =+O29 -> Average
B52: Inventory Turnover | D52: =IFERROR(D98/(AVERAGE(D113:D114)),"") | E52: =IFERROR(E98/(AVERAGE(E113:E114)),"") | F52: =IFERROR(F98/(AVERAGE(F113:F114)),"") -> 1.7343252 | G52: =IFERROR(G98/(AVERAGE(G113:G114)),"") -> 5.7362637 | H52: =IFERROR(H98/(AVERAGE(H113:H114)),"") | I52: =IFERROR(I98/(AVERAGE(I113:I114)),"") | J52: =IFERROR(J98/(AVERAGE(J113:J114)),"") | K52: =IFERROR(K98/(AVERAGE(K113:K114)),"") | ... N52: =IFERROR(N98/(AVERAGE(N113:N114)),"") | O52: =IFERROR(+AVERAGE(D52:N52),"") -> 3.7352945
B53: Acc. Receivable Turnover | D53: =IFERROR(D97/D112,"") -> 6.6103438 | E53: =IFERROR(E97/E112,"") -> 4.4458179 | F53: =IFERROR(F97/F112,"") -> 6.2161972 | G53: =IFERROR(G97/G112,"") -> 13.814815 | H53: =IFERROR(H97/H112,"") | I53: =IFERROR(I97/I112,"") | J53: =IFERROR(J97/J112,"") | K53: =IFERROR(K97/K112,"") | ... N53: =IFERROR(N97/N112,"") | O53: =IFERROR(+AVERAGE(D53:N53),"") -> 7.7717934
B54: Payables Turnover | D54: =IFERROR(D98/D118,"") -> 3.9382409 | E54: =IFERROR(E98/E118,"") -> 3.2031447 | F54: =IFERROR(F98/F118,"") -> 4.004908 | G54: =IFERROR(G98/G118,"") -> 0.19023324 | H54: =IFERROR(H98/H118,"") | I54: =IFERROR(I98/I118,"") | J54: =IFERROR(J98/J118,"") | K54: =IFERROR(K98/K118,"") | ... N54: =IFERROR(N98/N118,"") | O54: =IFERROR(+AVERAGE(D54:N54),"") -> 2.8341317
B55: Fixed Asset Turnover | D55: =IFERROR(D97/D116,"") -> 0.692147 | E55: =IFERROR(E97/E116,"") -> 0.20499278 | F55: =IFERROR(F97/F116,"") -> 0.77470599 | G55: =IFERROR(G97/G116,"") -> 0.038319293 | H55: =IFERROR(H97/H116,"") | I55: =IFERROR(I97/I116,"") | J55: =IFERROR(J97/J116,"") | K55: =IFERROR(K97/K116,"") | ... N55: =IFERROR(N97/N116,"") | O55: =IFERROR(+AVERAGE(D55:N55),"") -> 0.42754127
B56: Total Asset Turnover | D56: =IFERROR(D97/D117,"") -> 0.084724659 | E56: =IFERROR(E97/E117,"") -> 0.037887965 | F56: =IFERROR(F97/F117,"") -> 0.044167463 | G56: =IFERROR(G97/G117,"") -> 0.0024290338 | H56: =IFERROR(H97/H117,"") | I56: =IFERROR(I97/I117,"") | J56: =IFERROR(J97/J117,"") | K56: =IFERROR(K97/K117,"") | ... N56: =IFERROR(N97/N117,"") | O56: =IFERROR(+AVERAGE(D56:N56),"") -> 0.04230228
B57: Cash Cycle (days) | D57: =IFERROR(365/D52+365/D53-365/D54,"") | E57: =IFERROR(365/E52+365/E53-365/E54,"") | F57: =IFERROR(365/F52+365/F53-365/F54,"") -> 178.03589 | G57: =IFERROR(365/G52+365/G53-365/G54,"") -> -1828.6461 | H57: =IFERROR(365/H52+365/H53-365/H54,"") | I57: =IFERROR(365/I52+365/I53-365/I54,"") | J57: =IFERROR(365/J52+365/J53-365/J54,"") | K57: =IFERROR(365/K52+365/K53-365/K54,"") | ... N57: =IFERROR(365/N52+365/N53-365/N54,"") | O57: =IFERROR(+AVERAGE(D57:N57),"") -> -825.30512
B59: Cash Flow | D59: =+D38 -> IONQ, | E59: =+E38 -> RIGETTI | F59: =+F38 -> D-WAVE | G59: =+G38 -> QUANTUM | H59: =+H38 | I59: =+I38 | J59: =+J38 | K59: =+K38 | ... O59: =+O38 -> Average
B61: Cash Flow Margin | D61: =IFERROR(D132/D97,"") -> 0.43551645 | E61: =IFERROR(E132/E97,"") -> 4.3067655 | F61: =IFERROR(F132/F97,"") -> 15.482723 | G61: =IFERROR(G132/G97,"") -> 206.12869 | H61: =IFERROR(H132/H97,"") | I61: =IFERROR(I132/I97,"") | J61: =IFERROR(J132/J97,"") | K61: =IFERROR(K132/K97,"") | ... N61: =IFERROR(N132/N97,"") | O61: =IFERROR(+AVERAGE(D61:N61),"") -> 56.588423
B62: Cash Flow to Net Income | D62: =IFERROR(D132/D96,"") -> -0.11893633 | E62: =IFERROR(E132/E96,"") -> -0.6187173 | F62: =IFERROR(F132/F96,"") -> -1.6522517 | G62: =IFERROR(G132/G96,"") -> -2.8453112 | H62: =IFERROR(H132/H96,"") | I62: =IFERROR(I132/I96,"") | J62: =IFERROR(J132/J96,"") | K62: =IFERROR(K132/K96,"") | ... N62: =IFERROR(N132/N96,"") | O62: =IFERROR(+AVERAGE(D62:N62),"") -> -1.3088041
B63: CFO to Net Income | D63: =+IFERROR(D126/D105,"") -> 0.31871775 | E63: =+IFERROR(E126/E105,"") -> 0.65516215 | F63: =+IFERROR(F126/F105,"") -> 0.56662415 | G63: =+IFERROR(G126/G105,"") -> 0.58611091 | H63: =+IFERROR(H126/H105,"") | I63: =+IFERROR(I126/I105,"") | J63: =+IFERROR(J126/J105,"") | K63: =+IFERROR(K126/K105,"") | ... N63: =+IFERROR(N126/N105,"") | O63: =IFERROR(+AVERAGE(D63:N63),"") -> 0.53165374
B64: Net Capex to CFO | D64: =IFERROR(-D127/D126,"") -> -0.223016 | E64: =IFERROR(-E127/E126,"") -> -0.21921109 | F64: =IFERROR(-F127/F126,"") -> -0.056163966 | G64: =IFERROR(-G127/G126,"") -> -0.37229384 | H64: =IFERROR(-H127/H126,"") | I64: =IFERROR(-I127/I126,"") | J64: =IFERROR(-J127/J126,"") | K64: =IFERROR(-K127/K126,"") | ... N64: =IFERROR(-N127/N126,"") | O64: =IFERROR(+AVERAGE(D64:N64),"") -> -0.21767122
B65: CFI to CFO | D65: =IFERROR(-D128/D126,"") -> 0.78281275 | E65: =IFERROR(-E128/E126,"") -> -1.5478302 | F65: =IFERROR(-F128/F126,"") -> -0.073658045 | G65: =IFERROR(-G128/G126,"") -> -0.37229384 | H65: =IFERROR(-H128/H126,"") | I65: =IFERROR(-I128/I126,"") | J65: =IFERROR(-J128/J126,"") | K65: =IFERROR(-K128/K126,"") | ... N65: =IFERROR(-N128/N126,"") | O65: =IFERROR(+AVERAGE(D65:N65),"") -> -0.30274234
B66: Net Financing to CFO | D66: =IFERROR((D129+D130)/D126,"") -> 0 | E66: =IFERROR((E129+E130)/E126,"") -> 0.4607818 | F66: =IFERROR((F129+F130)/F126,"") -> 0.71219192 | G66: =IFERROR((G129+G130)/G126,"") -> 0 | H66: =IFERROR((H129+H130)/H126,"") | I66: =IFERROR((I129+I130)/I126,"") | J66: =IFERROR((J129+J130)/J126,"") | K66: =IFERROR((K129+K130)/K126,"") | ... N66: =IFERROR((N129+N130)/N126,"") | O66: =IFERROR(+AVERAGE(D66:N66),"") -> 0.29324343
B67: Debt Borrowing to Debt Repayment | D67: =+IFERROR(-D130/D129,"") | E67: =+IFERROR(-E130/E129,"") | F67: =+IFERROR(-F130/F129,"") | G67: =+IFERROR(-G130/G129,"") | H67: =+IFERROR(-H130/H129,"") | I67: =+IFERROR(-I130/I129,"") | J67: =+IFERROR(-J130/J129,"") | K67: =+IFERROR(-K130/K129,"") | ... N67: =+IFERROR(-N130/N129,"") | O67: =IFERROR(+AVERAGE(D67:N67),"")
B68: CFF to CFO | D68: =IFERROR(-D131/D126,"") -> 0.39445322 | E68: =IFERROR(-E131/E126,"") -> 3.4657199 | F68: =IFERROR(-F131/F126,"") -> 4.2785451 | G68: =IFERROR(-G131/G126,"") -> 6.1145377 | H68: =IFERROR(-H131/H126,"") | I68: =IFERROR(-I131/I126,"") | J68: =IFERROR(-J131/J126,"") | K68: =IFERROR(-K131/K126,"") | ... N68: =IFERROR(-N131/N126,"") | O68: =IFERROR(+AVERAGE(D68:N68),"") -> 3.563314
B69: Payout Ratio | O69: =IFERROR(+AVERAGE(D69:N69),"")
B71: Stock Information | D71: =+D29 -> IONQ, | E71: =+E29 -> RIGETTI | F71: =+F29 -> D-WAVE | G71: =+G29 -> QUANTUM | H71: =+H29 | I71: =+I29 | J71: =+J29 | K71: =+K29 | ... O71: =+O29 -> Average
B73: (%) Float | D73: =(203790/238880) -> 0.85310616 | E73: =(282400/285830) -> 0.98799986 | F73: =(276080/287820) -> 0.95921062 | G73: =(112180/137240) -> 0.81740017 | O73: =IFERROR(+AVERAGE(D73:N73),"") -> 0.9044292
B74: β (Levered) | D74: {=IFERROR(_FV(D91,"Beta"),"")} -> 2.5362 | E74: {=IFERROR(_FV(E91,"Beta"),"")} -> 1.4372 | F74: {=IFERROR(_FV(F91,"Beta"),"")} -> 1.3795 | G74: {=IFERROR(_FV(G91,"Beta"),"")} -> 3.8584 | K74: {=IFERROR(_FV(K91,"Beta"),"")} | L74: {=IFERROR(_FV(L91,"Beta"),"")} | M74: {=IFERROR(_FV(M91,"Beta"),"")} | N74: {=IFERROR(_FV(N91,"Beta"),"")} | O74: =IFERROR(+AVERAGE(D74:N74),"") -> 2.302825
B75: β (Unlevered) | D75: =IFERROR(D74/(1+(1-D104/D103)*(D121/D122)),"") -> 2.4242587 | E75: =IFERROR(E74/(1+(1-E104/E103)*(E121/E122)),"") -> 1.343785 | F75: =IFERROR(F74/(1+(1-F104/F103)*(F121/F122)),"") -> 0.85545031 | G75: =IFERROR(G74/(1+(1-G104/G103)*(G121/G122)),"") -> 3.8163897 | K75: =IFERROR(K74/(1+(1-K104/K103)*(K121/K122)),"") | L75: =IFERROR(L74/(1+(1-L104/L103)*(L121/L122)),"") | M75: =IFERROR(M74/(1+(1-M104/M103)*(M121/M122)),"") | N75: =IFERROR(N74/(1+(1-N104/N103)*(N121/N122)),"") | O75: =IFERROR(+AVERAGE(D75:N75),"") -> 2.109971
B76: % Held by Insiders | D76: 0.0854 | E76: 0.0101 | F76: 0.0176 | G76: 0.1805 | O76: =IFERROR(+AVERAGE(D76:N76),"") -> 0.0734
B77: % Held by Institutions | D77: 0.3738 | E77: 0.2415 | F77: 0.195 | G77: 0.1664 | O77: =IFERROR(+AVERAGE(D77:N77),"") -> 0.244175
B78: Short % Float | D78: 0.1466 | E78: 0.2606 | F78: 0.2266 | G78: 0.2096 | O78: =IFERROR(+AVERAGE(D78:N78),"") -> 0.21085
B80: Stock Performance | D80: =+D29 -> IONQ, | E80: =+E29 -> RIGETTI | F80: =+F29 -> D-WAVE | G80: =+G29 -> QUANTUM | H80: =+H29 | I80: =+I29 | J80: =+J29 | K80: =+K29 | ... O80: =+O29 -> Average
B82: 1 day | D82: {=IFERROR((D85/_xlfn.STOCKHISTORY(C6,TODAY()-1,TODAY()-1,0,0,1))-1,"Non-trading days")} -> 0.16913921 | E82: {=IFERROR((E85/_xlfn.STOCKHISTORY(C8,TODAY()-1,TODAY()-1,0,0,1))-1,"Non-trading days")} -> Non-trading days | F82: {=IFERROR((F85/_xlfn.STOCKHISTORY(C9,TODAY()-1,TODAY()-1,0,0,1))-1,"Non-trading days")} -> Non-trading days | G82: {=IFERROR((G85/_xlfn.STOCKHISTORY(C10,TODAY()-1,TODAY()-1,0,0,1))-1,"Non-trading days")} -> Non-trading days | H82: {=IFERROR((K85/_xlfn.STOCKHISTORY(C11,TODAY()-1,TODAY()-1,0,0,1))-1,"Non-trading days")} -> Non-trading days | I82: {=IFERROR((L85/_xlfn.STOCKHISTORY(C12,TODAY()-1,TODAY()-1,0,0,1))-1,"Non-trading days")} -> Non-trading days | J82: {=IFERROR((M85/_xlfn.STOCKHISTORY(C13,TODAY()-1,TODAY()-1,0,0,1))-1,"Non-trading days")} -> Non-trading days | K82: {=IFERROR((N85/_xlfn.STOCKHISTORY(C14,TODAY()-1,TODAY()-1,0,0,1))-1,"Non-trading days")} -> Non-trading days | L82: {=IFERROR((L85/_xlfn.STOCKHISTORY(C15,TODAY()-1,TODAY()-1,0,0,1))-1,"Non-trading days")} -> Non-trading days | M82: {=IFERROR((M85/_xlfn.STOCKHISTORY(C16,TODAY()-1,TODAY()-1,0,0,1))-1,"Non-trading days")} -> Non-trading days | N82: {=IFERROR((N85/_xlfn.STOCKHISTORY(C17,TODAY()-1,TODAY()-1,0,0,1))-1,"Non-trading days")} -> Non-trading days | O82: =IFERROR(+AVERAGE(D82:N82),"") -> 0.16913921
B83: 1 month | D83: {=IFERROR((D85/_xlfn.STOCKHISTORY(C6,TODAY()-29,TODAY()-29,0,0,1))-1,"Non-trading days")} -> 0.34067755 | E83: {=IFERROR((E85/_xlfn.STOCKHISTORY(C8,TODAY()-29,TODAY()-29,0,0,1))-1,"Non-trading days")} -> 0.075361513 | F83: {=IFERROR((F85/_xlfn.STOCKHISTORY(C9,TODAY()-29,TODAY()-29,0,0,1))-1,"Non-trading days")} -> Non-trading days | G83: {=IFERROR((G85/_xlfn.STOCKHISTORY(C10,TODAY()-29,TODAY()-29,0,0,1))-1,"Non-trading days")} -> Non-trading days | H83: {=IFERROR((K85/_xlfn.STOCKHISTORY(C11,TODAY()-29,TODAY()-29,0,0,1))-1,"Non-trading days")} -> Non-trading days | I83: {=IFERROR((L85/_xlfn.STOCKHISTORY(C12,TODAY()-29,TODAY()-29,0,0,1))-1,"Non-trading days")} -> Non-trading days | J83: {=IFERROR((M85/_xlfn.STOCKHISTORY(C13,TODAY()-29,TODAY()-29,0,0,1))-1,"Non-trading days")} -> Non-trading days | K83: {=IFERROR((N85/_xlfn.STOCKHISTORY(C14,TODAY()-29,TODAY()-29,0,0,1))-1,"Non-trading days")} -> Non-trading days | L83: {=IFERROR((L85/_xlfn.STOCKHISTORY(C15,TODAY()-29,TODAY()-29,0,0,1))-1,"Non-trading days")} -> Non-trading days | M83: {=IFERROR((M85/_xlfn.STOCKHISTORY(C16,TODAY()-29,TODAY()-29,0,0,1))-1,"Non-trading days")} -> Non-trading days | N83: {=IFERROR((N85/_xlfn.STOCKHISTORY(C17,TODAY()-29,TODAY()-29,0,0,1))-1,"Non-trading days")} -> Non-trading days | O83: =IFERROR(AVERAGE(D83:N83),"") -> 0.20801953
B84: YTD | D84: {=IFERROR((D85/_xlfn.STOCKHISTORY(C6,"2025-01-02","2025-01-02",0,0,1))-1,"Non-trading days")} -> 0.2762877 | E84: {=IFERROR((E85/_xlfn.STOCKHISTORY(C8,"2025-01-02","2025-01-02",0,0,1))-1,"Non-trading days")} -> -0.03325 | F84: {=IFERROR((F85/_xlfn.STOCKHISTORY(C9,"2025-01-02","2025-01-02",0,0,1))-1,"Non-trading days")} -> 0.85431842 | G84: {=IFERROR((G85/_xlfn.STOCKHISTORY(C10,"2025-01-02","2025-01-02",0,0,1))-1,"Non-trading days")} -> -0.093841642 | H84: {=IFERROR((K85/_xlfn.STOCKHISTORY(C11,"2025-01-02","2025-01-02",0,0,1))-1,"Non-trading days")} -> Non-trading days | I84: {=IFERROR((L85/_xlfn.STOCKHISTORY(C12,"2025-01-02","2025-01-02",0,0,1))-1,"Non-trading days")} -> Non-trading days | J84: {=IFERROR((M85/_xlfn.STOCKHISTORY(C13,"2025-01-02","2025-01-02",0,0,1))-1,"Non-trading days")} -> Non-trading days | K84: {=IFERROR((N85/_xlfn.STOCKHISTORY(C14,"2025-01-02","2025-01-02",0,0,1))-1,"Non-trading days")} -> Non-trading days | L84: {=IFERROR((L85/_xlfn.STOCKHISTORY(C15,"2025-01-02","2025-01-02",0,0,1))-1,"Non-trading days")} -> Non-trading days | M84: {=IFERROR((M85/_xlfn.STOCKHISTORY(C16,"2025-01-02","2025-01-02",0,0,1))-1,"Non-trading days")} -> Non-trading days | N84: {=IFERROR((N85/_xlfn.STOCKHISTORY(C17,"2025-01-02","2025-01-02",0,0,1))-1,"Non-trading days")} -> Non-trading days | O84: =IFERROR(AVERAGE(D84:N84),"") -> 0.25087862
B85: Current Price | D85: {=+IFERROR(_FV(D91,"Price"),"")} -> 55.008 | E85: {=+IFERROR(_FV(E91,"Price"),"")} -> 19.335 | F85: {=+IFERROR(_FV(F91,"Price"),"")} -> 17.82 | G85: {=+IFERROR(_FV(G91,"Price"),"")} -> 16.995 | H85: {=+IFERROR(_FV(H91,"Price"),"")} | I85: {=+IFERROR(_FV(I91,"Price"),"")} | J85: {=+IFERROR(_FV(J91,"Price"),"")} | K85: {=+IFERROR(_FV(K91,"Price"),"")} | ... N85: {=+IFERROR(_FV(N91,"Price"),"")} | O85: =IFERROR(AVERAGE(D85:N85),"") -> 27.2895
B87: Extra
B89: % Revenues in the US | D89: 0.945
B91: Income Statement | D91: =+DCF!AA4 -> #VALUE! | E91: #VALUE! | F91: #VALUE! | G91: #VALUE! | H91: N/A | I91: N/A | J91: N/A | K91: N/A | L91: N/A | M91: N/A | N91: N/A
B93: =+Inputs!$B$6&" ("&Inputs!O$4&")" -> Revenue (Sales) (2022) | D93: =+_xlfn.XLOOKUP("Revenue (Sales)",Inputs!$B:$B,Inputs!O:O) -> 11131 | E93: 13102 | F93: 7173 | G93: 136
B94: =+Inputs!$B$6&" ("&Inputs!P$4&")" -> Revenue (Sales) (2023) | D94: =+_xlfn.XLOOKUP("Revenue (Sales)",Inputs!$B:$B,Inputs!P:P) -> 22042 | E94: 12008 | F94: 8758 | G94: 358
B95: EBITDA (2023) | D95: =+_xlfn.XLOOKUP("EBITDA",Inputs!$B:$B,Inputs!P:P) -> -147379 | E95: -61902 | F95: -75423 | G95: -22113
B96: Net Income (2023) | D96: =+_xlfn.XLOOKUP("Net Income",Inputs!$B:$B,Inputs!P:P) -> -157723.05 | E96: -75107 | F96: -82715 | G96: -27022
B97: =+Inputs!$B$6&" ("&Inputs!Q$4&")" -> Revenue (Sales) (2024) | D97: =+_xlfn.XLOOKUP("Revenue (Sales)",Inputs!$B:$B,Inputs!Q:Q) -> 43073 | E97: 10790 | F97: 8827 | G97: 373
B98: COGS (Cost of Goods Sold) | D98: =+_xlfn.XLOOKUP($B98,Inputs!$B:$B,Inputs!Q:Q) -> 20597 | E98: 5093 | F98: 3264 | G98: 261
B99: Gross Profit | D99: =+_xlfn.XLOOKUP($B99,Inputs!$B:$B,Inputs!Q:Q) -> 22476 | E99: =+E97-E98 -> 5697 | F99: =+F97-F98 -> 5563 | G99: =G97-G98 -> 112 | H99: =+H97-H98 -> 0 | I99: =+I97-I98 -> 0 | J99: =+J97-J98 -> 0 | K99: =+K97-K98 -> 0 | L99: =+L97-L98 -> 0 | M99: =+M97-M98 -> 0 | N99: =+N97-N98 -> 0
B100: EBITDA | D100: =+_xlfn.XLOOKUP($B100,Inputs!$B:$B,Inputs!Q:Q) -> -213801 | E100: -68510 | F100: -77223 | G100: -25937
B101: Operating Income (EBIT) | D101: =+_xlfn.XLOOKUP($B101,Inputs!$B:$B,Inputs!Q:Q) -> -232455 | E101: =+E100-6906 -> -75416 | F101: =+F100-1932 -> -79155 | G101: =+G100-3798 -> -29735
B102: Net Interest Expense (Income) | D102: =+_xlfn.XLOOKUP($B102,Inputs!$B:$B,Inputs!Q:Q) -> -18249 | E102: 1858 | F102: -3897 | G102: -2073
B103: Pre-Tax Income (EBT) | D103: =+_xlfn.XLOOKUP($B103,Inputs!$B:$B,Inputs!Q:Q) -> -331588 | E103: =E105 -> -77274 | F103: =F105 -> -75258 | G103: =G105 -> -27662
B104: Tax Expense (Benefits) | D104: =+_xlfn.XLOOKUP($B104,Inputs!$B:$B,Inputs!Q:Q) -> 0.059 | E104: 0 | F104: 0 | G104: 0
B105: Net Income | D105: =+_xlfn.XLOOKUP($B105,Inputs!$B:$B,Inputs!Q:Q) -> -331588.06 | E105: =+E101-E102 -> -77274 | F105: =+F101-F102 -> -75258 | G105: =+G101-G102 -> -27662
B106: EPS basic | D106: =+_xlfn.XLOOKUP($B106,Inputs!$B:$B,Inputs!Q:Q) -> -1.56 | E106: -1.09 | F106: -0.75 | G106: -0.73
B107: R&D (Research & Development) | D107: =+_xlfn.XLOOKUP($B107,Inputs!$B:$B,Inputs!Q:Q) -> 136827 | E107: 49750 | F107: 35300 | G107: 11318
B109: Balance Sheet
B111: Cash & Cash Equivalents | D111: =+_xlfn.XLOOKUP($B111,Inputs!$B:$B,Inputs!Q:Q) -> 54393 | E111: 67674 | F111: 177980 | G111: 78945
B112: Accounts Receivable | D112: =+_xlfn.XLOOKUP($B112,Inputs!$B:$B,Inputs!Q:Q) -> 6516 | E112: 2427 | F112: 1420 | G112: 27
B113: Beginning Inventory | D113: =+_xlfn.XLOOKUP("Inventory",Inputs!$B:$B,Inputs!P:P) -> 0 | E113: 0 | F113: 2078 | G113: 73
B114: Ending Inventory | D114: =+_xlfn.XLOOKUP("Inventory",Inputs!$B:$B,Inputs!Q:Q) -> 0 | E114: 0 | F114: 1686 | G114: 18
B115: Current Assets | D115: =+_xlfn.XLOOKUP($B115,Inputs!$B:$B,Inputs!Q:Q) -> 378802 | E115: 206758 | F115: 185040 | G115: 79151
B116: Net PP&E (Property, Plant and Equipment) | D116: =+_xlfn.XLOOKUP($B116,Inputs!$B:$B,Inputs!Q:Q) -> 62231 | E116: 52636 | F116: 11394 | G116: 9734
B117: Total Assets | D117: =+_xlfn.XLOOKUP($B117,Inputs!$B:$B,Inputs!Q:Q) -> 508388 | E117: 284787 | F117: 199853 | G117: 153559
B118: Accounts Payable | D118: =+_xlfn.XLOOKUP($B118,Inputs!$B:$B,Inputs!Q:Q) -> 5230 | E118: 1590 | F118: 815 | G118: 1372
B119: Current Liabilities | D119: =+_xlfn.XLOOKUP($B119,Inputs!$B:$B,Inputs!Q:Q) -> 36085 | E119: 11867 | F119: 30145 | G119: 4559
B120: Long-term debt | D120: =+_xlfn.XLOOKUP($B120,Inputs!$B:$B,Inputs!Q:Q) -> 14359 | E120: 6641 | F120: 36517 | G120: 1181
B121: Total Debt | D121: =+_xlfn.XLOOKUP($B121,Inputs!$B:$B,Inputs!Q:Q,,,-1) -> 17725 | E121: =E120+2159 -> 8800 | F121: =F120+1860 -> 38377 | G121: =G120 -> 1181
B122: Shareholder's Equity | D122: =+_xlfn.XLOOKUP($B122,Inputs!$B:$B,Inputs!Q:Q) -> 383862 | E122: 126589 | F122: 62646 | G122: 107287
B124: Cash Flow Statement
B126: Operating Cash Flow | D126: =+_xlfn.XLOOKUP($B126,Inputs!$B:$B,Inputs!Q:Q) -> -105683 | E126: -50627 | F126: -42643 | G126: -16213
B127: Net Capex | D127: =+_xlfn.XLOOKUP($B127,Inputs!$B:$B,Inputs!Q:Q) -> -23569 | E127: -11098 | F127: -2395 | G127: -6036
B128: Investing Cash Flow | D128: =+_xlfn.XLOOKUP($B128,Inputs!$B:$B,Inputs!Q:Q) -> 82730 | E128: -78362 | F128: -3141 | G128: -6036
...

Sheet ESG
B2: Environmental, Social and Governance Analysis
B4: Author: | C4: Cristina Lin | E4: Highlights
B6: Overview | E6: Educational Initiatives | G6: IonQ actively supports quantum education and workforce development. It collaborates with institutions like Sungkyunkwan University to provide quantum cloud resources for competitions and training programs
B7: Last Update | C7: 45768
B8: Latest year with data | C8: 2024 | E8: Weak environmental contribution | F8: It was not possible to assess the company's environmental commitment.
B9: GICS Sector
B10: GICS Industry Group
B11: Final Review | E11: High rotativity of directors | G11: IonQ divides its directors into three classes with overlapping three-year terms. This approach ensures that only a portion of the board is up for election each year, but at the same time, there is a high rotativity of the members of the board.
B13: ESG Scores
B14: LSEG ESG Score | C14: 32
B15: E-Score | C15: 0
B16: S-Score | C16: 26
B17: G-Score | C17: 47
B18: S&P Global ESG Score | C18: N/A
B19: Environmental | C19: N/A
B20: Social | C20: N/A
B21: Governance & Economic | C21: N/A
B22: Sustainalytics | C22: 20
B23: ISS ESG Corporate Rating | C23: D
B24: SDG Impact Rating | C24: -8.4
B25: Governance Quality Score | C25: 8
B26: MSCI ESG Ratings | C26: N/A
B29: Industry ESG Overview: | C29: Adequate
B30: Companies in the quantum computing industry often do not disclose ESG parameters due to their early-stage focus, lack of standard frameworks, and smaller market share at the moment. As the industry grows and attracts more institutional attention, ESG practices and transparency are expected to become more common and integrated into business strategies.
E33: ENVIRONMENTAL
E35: Comments
E36: The compay and its peers do not disclose any information regarding this matter as they are in early-growth stage (currently having a minimal footprint)
E46: SOCIAL
B48: Important Sources: | G48: Overview | H48: Targets | K48: Improvements | O48: Comments
B49: Annual Report | C49: https://www.sec.gov/ix?doc=/Archives/edgar/data/1824920/000095017025027722/ionq-20241231.htm | E49: Community Involvement | H49: N/A | K49: N/A | O49: IonQ actively supports quantum education and workforce development. It collaborates with Sungkyunkwan University in educational programs and with Hyundai Motors for years applying quantum computing to projects.
B50: Sustainability Report | C50: N/A
B51: Proxy Statement | C51: https://www.sec.gov/Archives/edgar/data/1824920/000119312524114115/d104516ddef14a.htm#toc | E51: Public Sector | H51: N/A | K51: N/A | O51: IonQ Announces Largest U.S. Quantum Contract Award of $54.5M with United States Air Force Research Lab in 2024.
E53: Litigation | H53: N/A | K53: N/A | O53: The company was invovled in a consolidated securities fraud class action. The plaintiffs alleged that IonQ and the special purpose acquisition company (SPAC) into which it merged, dMY Technology Group, misled investors about IonQ’s quantum computing technology, thereby inflating IonQ’s share price. On 8th April 2025, Cooley secured an appellate win on behalf of IonQ.
E55: GOVERNANCE
G57: Overview | H57: Targets | K57: Improvements | O57: Comments
E58: Diversity (Gender, Age, Industry, Region) | H58: N/A | K58: N/A | O58: 37.5% of board members are female (Gabrielle Toledano was appointed for the board in February 2025, so theproxy as of June 2024 only had 25% of female directors).
E60: % Independence | H60: N/A | K60: N/A | O60: 80% of the board members are independent (only CEO&President and Scientific Advisor Jungsang Kim were not).
E62: Average time as independent directors | H62: N/A | K62: N/A | O62: N/A
E64: Departures of C-level executives | H64: N/A | K64: N/A | O64: Harry You departed in February 2025 to lead a private AI-healthcare company. Craig Barratt chose not to stand for re-election at the June 2024 Annual Meeting, concluding his term as Chairman. Jungsang Kim also did not seek re-election in June 2024, ending his tenure as a director and co-founder.
E66: CEO/Chairman duality | H66: N/A | K66: N/A | O66: Peter Chapman is the Chairman (as of June 2024) while Niccolo de Masi is the CEO (Niccolo was the CEO of the predecessor, dMY Technology Group, Inc. III, a special purpose acquisition company). In the report for 2024, Peter was the CEO and Crag Barratt was the Chairman.
E68: Transparency when reporting | H68: N/A | K68: N/A | O68: Although some information was not available, the information on the annual report and the SEC fillings was transparent.
E70: Time taken to report | H70: N/A | K70: N/A | O70: The annual report (SEC fillings) of 2024 was released on 26th February 2025.
E72: CEO or Chairman in other boards? | H72: N/A | K72: N/A | O72: Niccolo de Masi currently serves in the boards of Rush Street Interactive (since December 2020), Planet Labs PBC ( since December 2021) and in Glu Mobile as Chairman of the Board. (Niccolo started serving as CEO of IonQ in 2025)
E74: Audit / Consulting | H74: N/A | K74: N/A | O74: All the audit fees and their purpose were transparent. ​Ernst & Young LLP (EY) has been serving as IonQ's independent registered public accounting firm since 2020. They were the auditors for legacy IonQ prior to its merger with dMY Technology Group, Inc. III in September 2021. Following the merger, EY continued in this role for the combined public entity.
E76: ESG-compensation related | H76: N/A | K76: N/A | O76: N/A
E78: Management compensation schemes | H78: N/A | K78: N/A | O78: A significant portion of compensation paid consists of performance-based annual bonuses that were only earned based on achievement of corporate goals and is a mix of performance-based and time-based equity awards (performance-based restricted stock units).

Sheet DCF
B2: DCF
A4: x | B4: Key Assumptions | AA4: #VALUE!
B6: Switches | E6: Bear Case | H6: Base Case | K6: Bull Case | AG6: FCFF | AH6: FCFE | AI6: Tax Shield | AJ6: Total Payout | AK6: NOPAT | AL6: Debt Borrowing | AM6: Cash Balance | AN6: Total Assets | AO6: Total Liabilities | AP6: Shareholder's Equity | AQ6: Current Liabilities | AR6: Current Assets
B7: Revenue | C7: 2 | E7: Revenue | F7: -0.02 | H7: Revenue | K7: Revenue | L7: 0.02 | AB7: Most Recent Fiscal Year | AC7: 2024 | AF7: 2022 | AG7: =+E194 -> -64536 | AH7: =+E246 -> -27301 | AI7: =+H218 -> 0 | AJ7: =+E259 -> -905 | AK7: =+E184 -> -85746 | AL7: =+E244 -> 0 | AM7: =+E89 -> 355797
B8: EBIT | C8: 2 | E8: EBIT | F8: -0.01 | H8: EBIT | K8: EBIT | L8: 0.01 | AB8: End of Fiscal Year | AC8: 45657 | AF8: =+AF7+1 -> 2023 | AG8: =+F194 -> -113850.05 | AH8: =+F246 -> -113819.05 | AI8: =+I218 -> 0 | AJ8: =+F259 -> 1954 | AK8: =+F184 -> -157754.05 | AL8: =+F244 -> 0 | AM8: =+F89 -> 355441
B9: WACC | C9: 2 | E9: WACC | F9: =IFERROR(+I9+0.5%,"") -> 0.13452675 | H9: WACC | I9: =WACC!G25 -> 0.12952675 | K9: WACC | L9: =IFERROR(I9-0.5%,"") -> 0.12452675 | AB9: Most Recent Quarter End Date | AC9: 45726 | AF9: =+AF8+1 -> 2024 | AG9: =+G194 -> -146246.04 | AH9: =+G246 -> -245379.06 | AI9: =+J218 -> 0 | AJ9: =+G259 -> 41449 | AK9: =+G184 -> -232455.04 | AL9: =+G244 -> 0 | AM9: =+G89 -> 340289 | AN9: =Inputs!Q48 -> 508388 | AO9: =+Inputs!Q60 -> 124526 | AP9: =+AN9-AO9 -> 383862 | AQ9: =+Inputs!Q54 -> 36085 | AR9: =+Inputs!Q38 -> 378802
B10: TGR | C10: 2 | E10: TGR | F10: =+I10-0.5% -> 0.015 | H10: TGR | I10: 0.02 | K10: TGR | L10: =+I10+0.5% -> 0.025 | AB10: Valuation Date | AC10: 45769 | AF10: =+AF9+1 -> 2025 | AG10: =+H194 -> -112020.3 | AH10: =+H246 -> 76542.223 | AI10: =+K218 -> 0 | AJ10: =+H259 -> 0 | AK10: =+H184 -> -224628.41 | AL10: =+H244 -> 245379.06 | AM10: =+H89 -> 54852.613 | AN10: =Inputs!Q48+DCF!H89+DCF!H91+DCF!H94+DCF!H97+DCF!H100+DCF!H106-DCF!G89-DCF!G91-DCF!G94-DCF!G97-DCF!G100-DCF!G106 -> 295226.38 | AO10: =+Inputs!Q60+(DCF!H111+DCF!H114+DCF!H117+DCF!H119*DCF!G111*DCF!G114*DCF!G117*DCF!G119) -> 424706.2 | AP10: =+AN10-AO10 -> -129479.82 | AQ10: =+AQ9+H111+H114-G111-G114 -> 58167.14 | AR10: =+H89+H91+H94+H97 -> 101369.18
AF11: =+AF10+1 -> 2026 | AG11: =+I194 -> -188326.8 | AH11: =+I246 -> -291521.22 | AI11: =+L218 -> 0 | AJ11: =+I259 -> 0 | AK11: =+I184 -> -275369.77 | AL11: =+I244 -> 0 | AM11: =+I89 -> -453756.34 | AN11: =AN10+DCF!I89+DCF!I91+DCF!I94+DCF!I97+DCF!I100+DCF!I106-DCF!H89-DCF!H91-DCF!H94-DCF!H97-DCF!H100-DCF!H106 -> -113659.55 | AO11: =AO10+(DCF!I111+DCF!I114+DCF!I117+DCF!I119*DCF!H111*DCF!H114*DCF!H117*DCF!H119) -> 1.0421837e+23 | AP11: =+AN11-AO11 -> -1.0421837e+23 | AQ11: =+AQ10+I111+I114-H111-H114 -> 72087.335 | AR11: =+I89+I91+I94+I97 -> -388421.46
B12: WACC | C12: =CHOOSE(C9,F9,I9,L9) -> 0.12952675 | AF12: =+AF11+1 -> 2027 | AG12: =+J194 -> -232576.45 | AH12: =+J246 -> -79751.71 | AI12: =+M218 -> 0 | AJ12: =+J259 -> 0 | AK12: =+J184 -> -332893.95 | AL12: =+J244 -> 291521.22 | AM12: =+J89 -> -703982.19
B13: TGR | C13: =CHOOSE(C10,F10,I10,L10) -> 0.02 | AF13: =+AF12+1 -> 2028 | AG13: =+K194 -> -318961.71 | AH13: =+K246 -> -388563.72 | AI13: =+N218 -> 0 | AJ13: =+K259 -> 0 | AK13: =+K184 -> -400174.95 | AL13: =+K244 -> 79751.71 | AM13: =+K89 -> -1467316.1
AF14: =+AF13+1 -> 2029 | AG14: =+L194 -> -376231.76 | AH14: =+L246 -> -183290.35 | AI14: =+O218 -> 0 | AJ14: =+L259 -> 0 | AK14: =+L184 -> -447618.39 | AL14: =+L244 -> 388563.72 | AM14: =+L89 -> -2031772.6
A15: x | B15: Market and Growth Assumptions | E15: 2022 | F15: =+E15+1 -> 2023 | G15: =+F15+1 -> 2024 | H15: =+G15+1 -> 2025 | I15: =+H15+1 -> 2026 | J15: =+I15+1 -> 2027 | K15: =+J15+1 -> 2028 | L15: =+K15+1 -> 2029 | M15: =+L15+1 -> 2030 | ... Z15: =+Y15+1 -> 2043
B17: Market Size (Fortune Business Insights) | E17: 695400 | F17: 885400 | G17: 1160100 | H17: =G17*(1+H18) -> 1508130 | I17: =H17*(1+I18) -> 1968109.6 | J17: =I17*(1+J18) -> 2568383.1 | K17: =J17*(1+K18) -> 3351739.9 | L17: =K17*(1+L18) -> 4374020.6 | M17: =L17*(1+M18) -> 5708096.9 | N17: =M17*(1+N18) -> 7449066.5 | O17: =N17*(1+O18) -> 9721031.7 | ... Z17: =Y17*(1+Z18) -> 1.8881471e+08
B18: Growth Rate | E18: - | F18: =F17/E17-1 -> 0.27322404 | G18: =G17/F17-1 -> 0.31025525 | H18: 0.3 | I18: 0.305 | J18: 0.305 | K18: 0.305 | L18: 0.305 | M18: 0.305 | N18: 0.305 | O18: 0.305 | P18: 0.305 | Q18: 0.31 | R18: 0.31 | S18: 0.31 | T18: 0.31 | U18: 0.31 | V18: 0.31 | W18: 0.31 | X18: 0.31 | Y18: 0.31 | Z18: 0.31
B19: Market Size (Statista) | E19: 695400 | F19: 885400 | G19: 1160100 | H19: =G19*(1+H20) -> 1498849.2 | I19: =H19*(1+I20) -> 1936513.2 | J19: =I19*(1+J20) -> 2501975 | K19: =J19*(1+K20) -> 3232551.7 | L19: =K19*(1+L20) -> 4266968.3 | M19: =L19*(1+M20) -> 5632398.1 | N19: =M19*(1+N20) -> 7434765.5 | O19: =N19*(1+O20) -> 9813890.5 | ... Z19: =Y19*(1+Z20) -> 2.2770062e+08
B20: Growth Rate | H20: 0.292 | I20: 0.292 | J20: 0.292 | K20: 0.292 | L20: 0.32 | M20: 0.32 | N20: 0.32 | O20: 0.32 | P20: 0.32 | Q20: 0.32 | R20: 0.32 | S20: 0.32 | T20: 0.33 | U20: 0.33 | V20: 0.34 | W20: 0.34 | X20: 0.34 | Y20: 0.34 | Z20: 0.34
B21: Average | E21: 695400 | F21: 885400 | G21: 1160100 | H21: =(H17+H19)/2 -> 1503489.6 | I21: =(I17+I19)/2 -> 1952311.4 | J21: =(J17+J19)/2 -> 2535179.1 | K21: =(K17+K19)/2 -> 3292145.8 | L21: =(L17+L19)/2 -> 4320494.4 | M21: =(M17+M19)/2 -> 5670247.5 | N21: =(N17+N19)/2 -> 7441916 | O21: =(O17+O19)/2 -> 9767461.1 | ... Z21: =(Z17+Z19)/2 -> 2.0825766e+08
B22: Average (%) | H22: =(H18+H20)/2 -> 0.296 | I22: =(I18+I20)/2 -> 0.2985 | J22: =(J18+J20)/2 -> 0.2985 | K22: =(K18+K20)/2 -> 0.2985 | L22: =(L18+L20)/2 -> 0.3125 | M22: =(M18+M20)/2 -> 0.3125 | N22: =(N18+N20)/2 -> 0.3125 | O22: =(O18+O20)/2 -> 0.3125 | ... Z22: =(Z18+Z20)/2 -> 0.325 | AX22: 0.6 | AY22: 0.6 | AZ22: 0.5 | BA22: 0.5 | BB22: 0.5 | BC22: 0.4 | BD22: 0.4 | BE22: 0.4 | BF22: 0.3 | BG22: 0.3 | BH22: 0.3 | BI22: 0.25 | BJ22: 0.25 | BK22: 0.25 | BL22: 0.25 | BM22: 0.25 | BN22: 0.2 | BO22: 0.2 | BP22: 0.2 | BQ22: =AVERAGE(AX22:BP22) -> 0.35
B23: Market Share | E23: =E30/E21 -> 0.016006615 | F23: =F30/F21 -> 0.024894963 | G23: =G30/G21 -> 0.037128696 | H23: =+G23-($G$23-$Z$23)/($Z$15-$G$15) -> 0.038858764 | I23: =+H23-($G$23-$Z$23)/($Z$15-$G$15) -> 0.040588833 | J23: =+I23-($G$23-$Z$23)/($Z$15-$G$15) -> 0.042318902 | K23: =+J23-($G$23-$Z$23)/($Z$15-$G$15) -> 0.04404897 | L23: =+K23-($G$23-$Z$23)/($Z$15-$G$15) -> 0.045779039 | M23: =+L23-($G$23-$Z$23)/($Z$15-$G$15) -> 0.047509108 | N23: =+M23-($G$23-$Z$23)/($Z$15-$G$15) -> 0.049239176 | O23: =+N23-($G$23-$Z$23)/($Z$15-$G$15) -> 0.050969245 | ... Y23: =+X23-($G$23-$Z$23)/($Z$15-$G$15) -> 0.068269931 | Z23: 0.07
B27: In thousands of USD
A28: x | B28: Income Statement | E28: 2022 | F28: =+E28+1 -> 2023 | G28: =+F28+1 -> 2024 | H28: =+G28+1 -> 2025 | I28: =+H28+1 -> 2026 | J28: =+I28+1 -> 2027 | K28: =+J28+1 -> 2028 | L28: =+K28+1 -> 2029 | M28: =+L28+1 -> 2030 | ... Z28: =+Y28+1 -> 2043
B30: Revenue (Sales) | D30: =+_xlfn.XLOOKUP($B30,Inputs!$B:$B,Inputs!N:N) -> 2099 | E30: =+_xlfn.XLOOKUP($B30,Inputs!$B:$B,Inputs!O:O) -> 11131 | F30: =+_xlfn.XLOOKUP($B30,Inputs!$B:$B,Inputs!P:P) -> 22042 | G30: =+_xlfn.XLOOKUP($B30,Inputs!$B:$B,Inputs!Q:Q) -> 43073 | H30: =+G30*(1+H31) -> 68916.8 | I30: =+H30*(1+I31) -> 110266.88 | J30: =+I30*(1+J31) -> 165400.32 | K30: =+J30*(1+K31) -> 248100.48 | L30: =+K30*(1+L31) -> 372150.72 | M30: =+L30*(1+M31) -> 521011.01 | N30: =+M30*(1+N31) -> 729415.41 | O30: =+N30*(1+O31) -> 1021181.6 | ... Z30: =+Y30*(1+Z31) -> 11831146
B31: % of growth | E31: =IFERROR((E30-D30)/D30,"") -> 4.3030014 | F31: =IFERROR(F30/E30-1,"") -> 0.98023538 | G31: =IFERROR(G30/F30-1,"") -> 0.95413302 | H31: 0.6 | I31: 0.6 | J31: 0.5 | K31: 0.5 | L31: 0.5 | M31: 0.4 | N31: 0.4 | O31: 0.4 | P31: 0.3 | Q31: 0.3 | R31: 0.3 | S31: 0.25 | T31: 0.25 | U31: 0.25 | V31: 0.25 | W31: 0.25 | X31: 0.2 | Y31: 0.2 | Z31: 0.2
B33: COGS (Cost of Goods Sold) | E33: =+_xlfn.XLOOKUP($B33,Inputs!$B:$B,Inputs!O:O) -> 2944 | F33: =+_xlfn.XLOOKUP($B33,Inputs!$B:$B,Inputs!P:P) -> 8108 | G33: =+_xlfn.XLOOKUP($B33,Inputs!$B:$B,Inputs!Q:Q) -> 20597 | H33: =H34*H$30 -> 32955.2 | I33: =I34*I$30 -> 52728.32 | J33: =J34*J$30 -> 79092.48 | K33: =K34*K$30 -> 118638.72 | L33: =L34*L$30 -> 177958.08 | M33: =M34*M$30 -> 249141.31 | N33: =N34*N$30 -> 348797.84 | O33: =O34*O$30 -> 488316.97 | ... Z33: =Z34*Z$30 -> 5657514.5
B34: % of revenue | E34: =IFERROR(E33/E$30,"") -> 0.26448657 | F34: =IFERROR(F33/F$30,"") -> 0.36784321 | G34: =IFERROR(G33/G$30,"") -> 0.47818819 | H34: =+G34 -> 0.47818819 | I34: =+H34 -> 0.47818819 | J34: =+I34 -> 0.47818819 | K34: =+J34 -> 0.47818819 | L34: =+K34 -> 0.47818819 | M34: =+L34 -> 0.47818819 | N34: =+M34 -> 0.47818819 | O34: =+N34 -> 0.47818819 | ... Z34: =+Y34 -> 0.47818819
B36: Gross Profit | E36: =+_xlfn.XLOOKUP($B36,Inputs!$B:$B,Inputs!O:O) -> 8187 | F36: =+_xlfn.XLOOKUP($B36,Inputs!$B:$B,Inputs!P:P) -> 13934 | G36: =+_xlfn.XLOOKUP($B36,Inputs!$B:$B,Inputs!Q:Q) -> 22476 | H36: =+H30-H33 -> 35961.6 | I36: =+I30-I33 -> 57538.56 | J36: =+J30-J33 -> 86307.84 | K36: =+K30-K33 -> 129461.76 | L36: =+L30-L33 -> 194192.64 | M36: =+M30-M33 -> 271869.7 | N36: =+N30-N33 -> 380617.57 | O36: =+O30-O33 -> 532864.6 | ... Z36: =+Z30-Z33 -> 6173631.9
B37: Gross Profit Margin | E37: =IFERROR((E36/D$36)-1,"") | F37: =IFERROR((F36/E$36)-1,"") -> 0.70196653 | G37: =IFERROR((G36/F$36)-1,"") -> 0.61303287 | H37: =IFERROR(H36/H$30,"") -> 0.52181181 | I37: =IFERROR(I36/I$30,"") -> 0.52181181 | J37: =IFERROR(J36/J$30,"") -> 0.52181181 | K37: =IFERROR(K36/K$30,"") -> 0.52181181 | L37: =IFERROR(L36/L$30,"") -> 0.52181181 | M37: =IFERROR(M36/M$30,"") -> 0.52181181 | N37: =IFERROR(N36/N$30,"") -> 0.52181181 | O37: =IFERROR(O36/O$30,"") -> 0.52181181 | ... Z37: =IFERROR(Z36/Z$30,"") -> 0.52181181
B39: SG&A (Selling, General & Administrative) | E39: =+_xlfn.XLOOKUP($B39,Inputs!$B:$B,Inputs!O:O) -> 44351 | F39: =+_xlfn.XLOOKUP($B39,Inputs!$B:$B,Inputs!P:P) -> 68992 | G39: =+_xlfn.XLOOKUP($B39,Inputs!$B:$B,Inputs!Q:Q) -> 99450 | H39: =+G39*(1+H31/8) -> 106908.75 | I39: =+H39*(1+I31/8) -> 114926.91 | J39: =+I39*(1+J31/8) -> 122109.84 | K39: =+J39*(1+K31/8) -> 129741.7 | L39: =+K39*(1+L31/8) -> 137850.56 | M39: =+L39*(1+M31/8) -> 144743.09 | N39: =+M39*(1+N31/8) -> 151980.24 | O39: =+N39*(1+O31/8) -> 159579.25 | ... Z39: =+Y39*(1+Z31/8) -> 223837.14
B40: growth % | E40: =IFERROR(E39/D$39,"") | F40: =IFERROR((F39/E$39)-1,"") -> 0.55559063 | G40: =IFERROR((G39/F$39)-1,"") -> 0.44147147 | H40: =+H31/H41 -> 0.23453988 | I40: =+I31/I41 -> 0.20339852 | J40: =+J31/J41 -> 0.14963126 | K40: =+K31/K41 -> 0.13393259 | L40: =+L31/L41 -> 0.12121521 | M40: =+M31/M41 -> 0.088562807 | N40: =+N31/N41 -> 0.081495568 | O40: =+O31/O41 -> 0.075472894 | ... Z40: =+Z31/Z41 -> 0.02
B41: rev growth / sg&a growth | F41: =+F31/F40 -> 1.7643123 | G41: =+G31/G40 -> 2.1612563 | H41: =+G41+(G41-F41) -> 2.5582004 | I41: =+H41+($Z$41-$H$41)/($Z$28-$G$28) -> 2.949874 | J41: =+I41+($Z$41-$H$41)/($Z$28-$G$28) -> 3.3415477 | K41: =+J41+($Z$41-$H$41)/($Z$28-$G$28) -> 3.7332214 | L41: =+K41+($Z$41-$H$41)/($Z$28-$G$28) -> 4.124895 | M41: =+L41+($Z$41-$H$41)/($Z$28-$G$28) -> 4.5165687 | N41: =+M41+($Z$41-$H$41)/($Z$28-$G$28) -> 4.9082424 | O41: =+N41+($Z$41-$H$41)/($Z$28-$G$28) -> 5.299916 | P41: =+O41+($Z$41-$H$41)/($Z$28-$G$28) -> 5.6915897 | ... Y41: =+X41+($Z$41-$H$41)/($Z$28-$G$28) -> 9.2166527 | Z41: 10
B43: R&D (Research & Development) | E43: =+_xlfn.XLOOKUP($B43,Inputs!$B:$B,Inputs!O:O) -> 43978 | F43: =+_xlfn.XLOOKUP($B43,Inputs!$B:$B,Inputs!P:P) -> 92321 | G43: =+_xlfn.XLOOKUP($B43,Inputs!$B:$B,Inputs!Q:Q) -> 136827 | H43: =(H44+1)*G43 -> 191557.8 | I43: =(I44+1)*H43 -> 258603.03 | J43: =(J44+1)*I43 -> 336183.94 | K43: =(K44+1)*J43 -> 437039.12 | L43: =(L44+1)*K43 -> 524446.94 | M43: =(M44+1)*L43 -> 603113.99 | N43: =(N44+1)*M43 -> 663425.39 | O43: =(O44+1)*N43 -> 713182.29 | ... Z43: =(Z44+1)*Y43 -> 1032588.4
B44: growth % | E44: =IFERROR((E43/D$43)-1,"") | F44: =+F31/F41 -> 0.55559063 | G44: =+G31/G41 -> 0.44147147 | H44: 0.4 | I44: 0.35 | J44: 0.3 | K44: 0.3 | L44: 0.2 | M44: 0.15 | N44: 0.1 | O44: 0.075 | P44: =+P31/P41 -> 0.052709351 | Q44: =+Q31/Q41 -> 0.049315636 | R44: =+R31/R41 -> 0.046332497 | S44: =+S31/S41 -> 0.036408064 | T44: =+T31/T41 -> 0.034443401 | U44: =+U31/U41 -> 0.032679918 | V44: =+V31/V41 -> 0.031088218 | W44: =+W31/W41 -> 0.029644367 | ... Z44: =+Z31/Z41 -> 0.02
B46: Other Operating (Income) Expenses | E46: =+_xlfn.XLOOKUP($B46,Inputs!$B:$B,Inputs!O:O) -> 0 | F46: =+_xlfn.XLOOKUP($B46,Inputs!$B:$B,Inputs!P:P) -> 0 | G46: =+_xlfn.XLOOKUP($B46,Inputs!$B:$B,Inputs!Q:Q) -> 0 | H46: =+H30*0.01 -> 689.168 | I46: =+I30*0.01 -> 1102.6688 | J46: =+J30*0.01 -> 1654.0032 | K46: =+K30*0.01 -> 2481.0048 | L46: =+L30*0.01 -> 3721.5072 | M46: =+M30*0.01 -> 5210.1101 | N46: =+N30*0.01 -> 7294.1541 | O46: =+O30*0.01 -> 10211.816 | ... Z46: =+Z30*0.01 -> 118311.46
H47: =IFERROR(AVERAGE(E46:G46)*(1+H31),"") -> 0
B48: EBITDA | E48: =+_xlfn.XLOOKUP($B48,Inputs!$B:$B,Inputs!O:O) -> -80142 | F48: =+_xlfn.XLOOKUP($B48,Inputs!$B:$B,Inputs!P:P) -> -147379 | G48: =+_xlfn.XLOOKUP($B48,Inputs!$B:$B,Inputs!Q:Q) -> -213801 | H48: =IFERROR(H36-H39-H43-H47,"") -> -262504.95 | I48: =IFERROR(I36-I39-I43-I46,"") -> -317094.05 | J48: =IFERROR(J36-J39-J43-J46,"") -> -373639.94 | K48: =IFERROR(K36-K39-K43-K46,"") -> -439800.07 | L48: =IFERROR(L36-L39-L43-L46,"") -> -471826.37 | M48: =IFERROR(M36-M39-M43-M46,"") -> -481197.49 | N48: =IFERROR(N36-N39-N43-N46,"") -> -442082.21 | O48: =IFERROR(O36-O39-O43-O46,"") -> -350108.75 | P48: =IFERROR(P36-P39-P43-P46,"") -> -236888.52 | ... Z48: =IFERROR(Z36-Z39-Z43-Z46,"") -> 4798894.9
B49: EBITDA Margin | E49: =IFERROR(E48/E$30,"") -> -7.1998922 | F49: =IFERROR(F48/F$30,"") -> -6.6862807 | G49: =IFERROR(G48/G$30,"") -> -4.9636896 | H49: =IFERROR(H48/H$30,"") -> -3.8090125 | I49: =IFERROR(I48/I$30,"") -> -2.8756962 | J49: =IFERROR(J48/J$30,"") -> -2.2590037 | K49: =IFERROR(K48/K$30,"") -> -1.7726692 | L49: =IFERROR(L48/L$30,"") -> -1.2678368 | ... Z49: =IFERROR(Z48/Z$30,"") -> 0.40561538
B51: D&A (Depreciation & Amortization) | E51: =+_xlfn.XLOOKUP($B51,Inputs!$B:$B,Inputs!O:O) -> 5604 | F51: =+_xlfn.XLOOKUP($B51,Inputs!$B:$B,Inputs!P:P) -> 10375 | G51: =+_xlfn.XLOOKUP($B51,Inputs!$B:$B,Inputs!Q:Q) -> 18654 | H51: =+IFERROR(H54+H57,"") -> 21834.814 | I51: =+IFERROR(I54+I57,"") -> 31475.283 | J51: =+IFERROR(J54+J57,"") -> 47744.803 | K51: =+IFERROR(K54+K57,"") -> 66750.503 | L51: =+IFERROR(L54+L57,"") -> 94779.189 | M51: =+IFERROR(M54+M57,"") -> 128858.64 | N51: =+IFERROR(N54+N57,"") -> 172020.47 | O51: =+IFERROR(O54+O57,"") -> 223000.08 | ... Z51: =+IFERROR(Z54+Z57,"") -> 1559352.9
B52: % of PP&E+ROU Assets+Intangibles excl. Goodwill | E52: =IFERROR(E51/AVERAGE(Inputs!O39+Inputs!O42+Inputs!O44,Inputs!N39+Inputs!N42+Inputs!N44),"") -> 0.20984441 | F52: =IFERROR(F51/AVERAGE(Inputs!P39+Inputs!P42+Inputs!P44,Inputs!O39+Inputs!O42+Inputs!O44),"") -> 0.28277845 | G52: =IFERROR(G51/AVERAGE(Inputs!Q39+Inputs!Q42+Inputs!Q44,Inputs!P39+Inputs!P42+Inputs!P44),"") -> 0.32440329 | H52: =IFERROR(H51/(G100+G106),"") -> 0.23811139 | I52: =IFERROR(I51/(H100+H106),"") -> 0.20180188 | J52: =IFERROR(J51/(I100+I106),"") -> 0.2015604 | K52: =IFERROR(K51/(J100+J106),"") -> 0.19860989 | L52: =IFERROR(L51/(K100+K106),"") -> 0.20046044 | M52: =IFERROR(M51/(L100+L106),"") -> 0.20320727 | N52: =IFERROR(N51/(M100+M106),"") -> 0.20635992 | O52: =IFERROR(O51/(N100+N106),"") -> 0.21338698 | ... Z52: =IFERROR(Z51/(Y100+Y106),"") -> 0.48945647
B54: Depreciation Expense | E54: =+_xlfn.XLOOKUP($B54,Inputs!$B:$B,Inputs!O:O) -> 4000 | F54: =+_xlfn.XLOOKUP($B54,Inputs!$B:$B,Inputs!P:P) -> 7200 | G54: =+_xlfn.XLOOKUP($B54,Inputs!$B:$B,Inputs!Q:Q) -> 13000 | H54: =IFERROR(H55*(G101+G102),"") -> 13670.814 | I54: =IFERROR(I55*(H101+H102),"") -> 20004.98 | J54: =IFERROR(J55*(I101+I102),"") -> 29337.137 | K54: =IFERROR(K55*(J101+J102),"") -> 40330.693 | L54: =IFERROR(L55*(K101+K102),"") -> 58884.112 | M54: =IFERROR(M55*(L101+L102),"") -> 82893.425 | N54: =IFERROR(N55*(M101+M102),"") -> 115914.53 | O54: =IFERROR(O55*(N101+N102),"") -> 157348.87 | ... Z54: =IFERROR(Z55*(Y101+Y102),"") -> 1447459.9
B55: % of PP&E+ROU Assets | E55: =IFERROR(E54/AVERAGE(Inputs!O40+Inputs!O42,Inputs!N40+Inputs!N42),"") -> 0.12583563 | F55: =IFERROR(F54/AVERAGE(Inputs!P40+Inputs!P42,Inputs!O40+Inputs!O42),"") -> 0.15326486 | G55: =IFERROR(G54/AVERAGE(Inputs!Q40+Inputs!Q42,Inputs!P40+Inputs!P42),"") -> 0.17738964 | H55: =IFERROR(AVERAGE(E55:G55),"") -> 0.15216338 | I55: =IFERROR(AVERAGE(F55:H55),"") -> 0.16093929 | J55: =IFERROR(AVERAGE(G55:I55),"") -> 0.16349744 | K55: =IFERROR(AVERAGE(H55:J55),"") -> 0.1588667 | L55: =IFERROR(AVERAGE(I55:K55),"") -> 0.16110114 | M55: =IFERROR(AVERAGE(J55:L55),"") -> 0.1611551 | N55: =IFERROR(AVERAGE(K55:M55),"") -> 0.16037431 | O55: =IFERROR(AVERAGE(L55:N55),"") -> 0.16087685 | ... Z55: =IFERROR(AVERAGE(W55:Y55),"") -> 0.16075546
B57: Amortization Expense | E57: =+_xlfn.XLOOKUP($B57,Inputs!$B:$B,Inputs!O:O) -> 0 | F57: =+_xlfn.XLOOKUP($B57,Inputs!$B:$B,Inputs!P:P) -> 0 | G57: =+_xlfn.XLOOKUP($B57,Inputs!$B:$B,Inputs!Q:Q) -> 0 | H57: 8164 | I57: =+I58*H106 -> 11470.304 | J57: =+J58*I106 -> 18407.666 | K57: =+K58*J106 -> 26419.81 | L57: =+L58*K106 -> 35895.078 | M57: =+M58*L106 -> 45965.211 | N57: =+N58*M106 -> 56105.942 | O57: =+O58*N106 -> 65651.211 | P57: =+P58*O106 -> 74320.57 | ... Z57: =+Z58*Y106 -> 111892.99
B58: % of Intangibles excl. Goodwill | E58: =IFERROR(E57/AVERAGE(Inputs!N45:O45),"") -> 0 | F58: =IFERROR(F57/AVERAGE(Inputs!O45:P45),"") -> 0 | G58: =IFERROR(G57/AVERAGE(Inputs!P45:Q45),"") -> 0 | H58: =+H57/AVERAGE(G106:H106) -> 0.15941947 | I58: =+H58-($H$58-$Z$58)/($Z$28-$H$28) -> 0.1572295 | J58: =+I58-($H$58-$Z$58)/($Z$28-$H$28) -> 0.15503952 | K58: =+J58-($H$58-$Z$58)/($Z$28-$H$28) -> 0.15284955 | L58: =+K58-($H$58-$Z$58)/($Z$28-$H$28) -> 0.15065958 | M58: =+L58-($H$58-$Z$58)/($Z$28-$H$28) -> 0.14846961 | N58: =+M58-($H$58-$Z$58)/($Z$28-$H$28) -> 0.14627964 | O58: =+N58-($H$58-$Z$58)/($Z$28-$H$28) -> 0.14408967 | P58: =+O58-($H$58-$Z$58)/($Z$28-$H$28) -> 0.1418997 | ... Y58: =+X58-($H$58-$Z$58)/($Z$28-$H$28) -> 0.12218997 | Z58: 0.12
B60: Operating Income (EBIT) | E60: =+_xlfn.XLOOKUP($B60,Inputs!$B:$B,Inputs!O:O) -> -85746 | F60: =+_xlfn.XLOOKUP($B60,Inputs!$B:$B,Inputs!P:P) -> -157754 | G60: =+_xlfn.XLOOKUP($B60,Inputs!$B:$B,Inputs!Q:Q) -> -232455 | H60: =+IFERROR(H48-H51,"") -> -284339.76 | I60: =+IFERROR(I48-I51,"") -> -348569.33 | J60: =+IFERROR(J48-J51,"") -> -421384.74 | K60: =+IFERROR(K48-K51,"") -> -506550.57 | L60: =+IFERROR(L48-L51,"") -> -566605.56 | M60: =+IFERROR(M48-M51,"") -> -610056.12 | N60: =+IFERROR(N48-N51,"") -> -614102.68 | O60: =+IFERROR(O48-O51,"") -> -573108.83 | ... Z60: =+IFERROR(Z48-Z51,"") -> 3239542
B61: Operating Margin | E61: =IFERROR(E60/E$30,"") -> -7.703351 | F61: =IFERROR(F60/F$30,"") -> -7.1569731 | G61: =IFERROR(G60/G$30,"") -> -5.3967683 | H61: =IFERROR(H60/H30,"") -> -4.1258411 | I61: =IFERROR(I60/I30,"") -> -3.1611426 | J61: =IFERROR(J60/J30,"") -> -2.5476658 | K61: =IFERROR(K60/K30,"") -> -2.0417154 | L61: =IFERROR(L60/L30,"") -> -1.5225164 | M61: =IFERROR(M60/M30,"") -> -1.1709083 | N61: =IFERROR(N60/N30,"") -> -0.84191075 | O61: =IFERROR(O60/O30,"") -> -0.56122128 | ... Z61: =IFERROR(Z60/Z30,"") -> 0.27381472
B63: Net Interest Expense (Income) | E63: =+_xlfn.XLOOKUP($B63,Inputs!$B:$B,Inputs!O:O) -> -7093 | F63: =+_xlfn.XLOOKUP($B63,Inputs!$B:$B,Inputs!P:P) -> -19322 | G63: =+_xlfn.XLOOKUP($B63,Inputs!$B:$B,Inputs!Q:Q) -> -18249 | H63: =-H66-H69 -> 0 | I63: =-I66-I69 -> 0 | J63: =-J66-J69 -> 0 | K63: =-K66-K69 -> 0 | L63: =-L66-L69 -> 0 | M63: =-M66-M69 -> 0 | N63: =-N66-N69 -> 0 | O63: =-O66-O69 -> 0 | ... Z63: =-Z66-Z69 -> 0
B64: % of Net Debt | E64: =IFERROR(E63/AVERAGE(Inputs!N115:O115),"") -> 0.016305672 | F64: =IFERROR(F63/AVERAGE(Inputs!O115:P115),"") -> 0.055278129 | G64: =IFERROR(G63/AVERAGE(Inputs!P115:Q115),"") -> 0.054482759 | H64: =IFERROR(H63/AVERAGE(G117+G119,H117+H119),"") -> 0 | I64: =IFERROR(I63/AVERAGE(H117+H119,I117+I119),"") -> 0 | J64: =IFERROR(J63/AVERAGE(I117+I119,J117+J119),"") -> 0 | K64: =IFERROR(K63/AVERAGE(J117+J119,K117+K119),"") -> 0 | L64: =IFERROR(L63/AVERAGE(K117+K119,L117+L119),"") -> 0 | M64: =IFERROR(M63/AVERAGE(L117+L119,M117+M119),"") -> 0 | N64: =IFERROR(N63/AVERAGE(M117+M119,N117+N119),"") -> 0 | O64: =IFERROR(O63/AVERAGE(N117+N119,O117+O119),"") -> 0 | ... Z64: =IFERROR(Z63/AVERAGE(Y117+Y119,Z117+Z119),"") -> 0
B66: Interest Expense | E66: =+_xlfn.XLOOKUP($B66,Inputs!$B:$B,Inputs!O:O) -> 0 | F66: =+_xlfn.XLOOKUP($B66,Inputs!$B:$B,Inputs!P:P) -> 0 | G66: =+_xlfn.XLOOKUP($B66,Inputs!$B:$B,Inputs!Q:Q) -> 0 | H66: 0 | I66: 0 | J66: 0 | K66: 0 | L66: 0 | M66: 0 | N66: 0 | O66: 0 | P66: 0 | Q66: 0 | R66: 0 | S66: 0 | T66: 0 | U66: 0 | V66: 0 | W66: 0 | X66: 0 | Y66: 0 | Z66: 0
B67: % of Debt | E67: =+IFERROR(E66/AVERAGE(Inputs!N112:O112),"") -> 0 | F67: =+IFERROR(F66/AVERAGE(Inputs!O112:P112),"") -> 0 | G67: =+IFERROR(G66/AVERAGE(Inputs!P112:Q112),"") -> 0 | H67: 0 | I67: 0 | J67: 0 | K67: 0 | L67: 0 | M67: 0 | N67: 0 | O67: 0 | P67: 0 | Q67: 0 | R67: 0 | S67: 0 | T67: 0 | U67: 0 | V67: 0 | W67: 0 | X67: 0 | Y67: 0 | Z67: 0
B69: Interest Income | E69: =+_xlfn.XLOOKUP($B69,Inputs!$B:$B,Inputs!O:O) -> 7093 | F69: =+_xlfn.XLOOKUP($B69,Inputs!$B:$B,Inputs!P:P) -> 19322 | G69: =+_xlfn.XLOOKUP($B69,Inputs!$B:$B,Inputs!Q:Q) -> 18249
B70: % Cash & Cash Eq. & ST Investments | E70: =IFERROR(E69/+AVERAGE(Inputs!N32:O32),"") -> 0.0161523 | F70: =IFERROR(F69/+AVERAGE(Inputs!O32:P32),"") -> 0.05433343 | G70: =IFERROR(G69/+AVERAGE(Inputs!P32:Q32),"") -> 0.052460006
B72: FX (Gain) Loss | E72: =+_xlfn.XLOOKUP($B72,Inputs!$B:$B,Inputs!O:O) -> 0 | F72: =+_xlfn.XLOOKUP($B72,Inputs!$B:$B,Inputs!P:P) -> 0 | G72: =+_xlfn.XLOOKUP($B72,Inputs!$B:$B,Inputs!Q:Q) -> 0 | H72: =+H73*H$17 -> 0 | I72: =+I73*I$17 -> 0 | J72: =+J73*J$17 -> 0 | K72: =+K73*K$17 -> 0 | L72: =+L73*L$17 -> 0 | M72: =+M73*M$17 -> 0 | N72: =+N73*N$17 -> 0 | O72: =+O73*O$17 -> 0 | ... Z72: =+Z73*Z$17 -> 0
B73: % of revenue
B75: Other Non-Operating (Income) Expenses | E75: =+_xlfn.XLOOKUP($B75,Inputs!$B:$B,Inputs!O:O) -> -30142 | F75: =+_xlfn.XLOOKUP($B75,Inputs!$B:$B,Inputs!P:P) -> 19291 | G75: =+_xlfn.XLOOKUP($B75,Inputs!$B:$B,Inputs!Q:Q) -> 117382 | H75: =IFERROR(AVERAGE(E75:G75)*(1+H31),"") -> 56816.533 | I75: =IFERROR(AVERAGE(F75:H75)*(1+I31),"") -> 103194.42 | J75: =IFERROR(AVERAGE(G75:I75)*(1+J31),"") -> 138696.48 | K75: =IFERROR(AVERAGE(H75:J75)*(1+K31),"") -> 149353.71 | L75: =IFERROR(AVERAGE(I75:K75)*(1+L31),"") -> 195622.3 | M75: =IFERROR(AVERAGE(J75:L75)*(1+M31),"") -> 225713.83 | N75: =IFERROR(AVERAGE(K75:M75)*(1+N31),"") -> 266321.93 | O75: =IFERROR(AVERAGE(L75:N75)*(1+O31),"") -> 320907.1 | ... Z75: =IFERROR(AVERAGE(W75:Y75)*(1+Z31),"") -> 1060779.1
B77: Pre-Tax Income (EBT) | E77: =+_xlfn.XLOOKUP($B77,Inputs!$B:$B,Inputs!O:O) -> -48511 | F77: =+_xlfn.XLOOKUP($B77,Inputs!$B:$B,Inputs!P:P) -> -157723 | G77: =+_xlfn.XLOOKUP($B77,Inputs!$B:$B,Inputs!Q:Q) -> -331588 | H77: =IFERROR(+H60-H63-H72-H75,"") -> -341156.3 | I77: =IFERROR(+I60-I63-I72-I75,"") -> -451763.75 | J77: =IFERROR(+J60-J63-J72-J75,"") -> -560081.22 | K77: =IFERROR(+K60-K63-K72-K75,"") -> -655904.28 | L77: =IFERROR(+L60-L63-L72-L75,"") -> -762227.86 | M77: =IFERROR(+M60-M63-M72-M75,"") -> -835769.95 | N77: =IFERROR(+N60-N63-N72-N75,"") -> -880424.6 | O77: =IFERROR(+O60-O63-O72-O75,"") -> -894015.93 | ... Z77: =IFERROR(+Z60-Z63-Z72-Z75,"") -> 2178762.9
B79: Tax Expense (Benefits) | E79: =+_xlfn.XLOOKUP($B79,Inputs!$B:$B,Inputs!O:O) -> 0 | F79: =+_xlfn.XLOOKUP($B79,Inputs!$B:$B,Inputs!P:P) -> 0.048 | G79: =+_xlfn.XLOOKUP($B79,Inputs!$B:$B,Inputs!Q:Q) -> 0.059 | H79: =IFERROR(H80*H$60,"") -> -59711.351 | I79: =IFERROR(I80*I$60,"") -> -73199.559 | J79: =IFERROR(J80*J$60,"") -> -88490.796 | K79: =IFERROR(K80*K$60,"") -> -106375.62 | L79: =IFERROR(L80*L$60,"") -> -118987.17 | M79: =IFERROR(M80*M$60,"") -> -128111.79 | N79: =IFERROR(N80*N$60,"") -> -128961.56 | O79: =IFERROR(O80*O$60,"") -> -120352.86 | ... Z79: =IFERROR(Z80*Z$60,"") -> 680303.82
B80: % of EBT | E80: =IFERROR(E79/E77,"") -> 0 | F80: =IFERROR(F79/F77,"") -> -3.0433101e-07 | G80: =IFERROR(G79/G77,"") -> -1.7793165e-07 | H80: 0.21 | I80: 0.21 | J80: 0.21 | K80: 0.21 | L80: 0.21 | M80: 0.21 | N80: 0.21 | O80: 0.21 | P80: 0.21 | Q80: 0.21 | R80: 0.21 | S80: 0.21 | T80: 0.21 | U80: 0.21 | V80: 0.21 | W80: 0.21 | X80: 0.21 | Y80: 0.21 | Z80: 0.21
B82: Net Income | E82: =+_xlfn.XLOOKUP($B82,Inputs!$B:$B,Inputs!O:O) -> -48511 | F82: =+_xlfn.XLOOKUP($B82,Inputs!$B:$B,Inputs!P:P) -> -157723.05 | G82: =+_xlfn.XLOOKUP($B82,Inputs!$B:$B,Inputs!Q:Q) -> -331588.06 | H82: =IFERROR(+H77-H79,"") -> -281444.95 | I82: =IFERROR(+I77-I79,"") -> -378564.19 | J82: =IFERROR(+J77-J79,"") -> -471590.42 | K82: =IFERROR(+K77-K79,"") -> -549528.66 | L82: =IFERROR(+L77-L79,"") -> -643240.7 | M82: =IFERROR(+M77-M79,"") -> -707658.17 | N82: =IFERROR(+N77-N79,"") -> -751463.04 | O82: =IFERROR(+O77-O79,"") -> -773663.07 | ... Z82: =IFERROR(+Z77-Z79,"") -> 1498459.1
B83: Net Income Margin | E83: =IFERROR(E82/E$30,"") -> -4.3581888 | F83: =IFERROR(F82/F$30,"") -> -7.1555688 | G83: =IFERROR(G82/G$30,"") -> -7.698281 | H83: =IFERROR(H82/H$30,"") -> -4.0838366 | I83: =IFERROR(I82/I$30,"") -> -3.4331631 | J83: =IFERROR(J82/J$30,"") -> -2.8512062 | K83: =IFERROR(K82/K$30,"") -> -2.214944 | L83: =IFERROR(L82/L$30,"") -> -1.7284414 | ... Z83: =IFERROR(Z82/Z$30,"") -> 0.12665375
A85: x | B85: Balance Sheet | E85: =E28 -> 2022 | F85: =F28 -> 2023 | G85: =G28 -> 2024 | H85: =H28 -> 2025 | I85: =I28 -> 2026 | J85: =J28 -> 2027 | K85: =K28 -> 2028 | L85: =L28 -> 2029 | ... Z85: =Z28 -> 2043
B87: Assets
B89: Cash & Cash Equivalents & ST Investments | E89: =+_xlfn.XLOOKUP($B89,Inputs!$B:$B,Inputs!O:O) -> 355797 | F89: =+_xlfn.XLOOKUP($B89,Inputs!$B:$B,Inputs!P:P) -> 355441 | G89: =+_xlfn.XLOOKUP($B89,Inputs!$B:$B,Inputs!Q:Q) -> 340289 | H89: =IFERROR(G89+H167,"") -> 54852.613 | I89: =IFERROR(H89+I167,"") -> -453756.34 | J89: =IFERROR(I89+J167,"") -> -703982.19 | K89: =IFERROR(J89+K167,"") -> -1467316.1 | L89: =IFERROR(K89+L167,"") -> -2031772.6 | M89: =IFERROR(L89+M167,"") -> -2920295 | N89: =IFERROR(M89+N167,"") -> -3709392.5 | O89: =IFERROR(N89+O167,"") -> -4876034.9 | ... Z89: =IFERROR(Y89+Z167,"") -> -17649206
B91: Accounts Receivable | E91: =+_xlfn.XLOOKUP($B91,Inputs!$B:$B,Inputs!O:O) -> 3292 | F91: =+_xlfn.XLOOKUP($B91,Inputs!$B:$B,Inputs!P:P) -> 11467 | G91: =+_xlfn.XLOOKUP($B91,Inputs!$B:$B,Inputs!Q:Q) -> 6516 | H91: =IFERROR(H92*H30/365,"") -> 10454.163 | I91: =IFERROR(I92*I30/365,"") -> 16726.661 | J91: =IFERROR(J92*J30/365,"") -> 25089.992 | K91: =IFERROR(K92*K30/365,"") -> 37634.988 | L91: =IFERROR(L92*L30/365,"") -> 56452.482 | M91: =IFERROR(M92*M30/365,"") -> 79033.474 | N91: =IFERROR(N92*N30/365,"") -> 110646.86 | O91: =IFERROR(O92*O30/365,"") -> 154905.61 | ... Z91: =IFERROR(Z92*Z30/365,"") -> 1794696.5
B92: DSO | E92: =IFERROR(E91/E30*365,"") -> 107.94897 | F92: =IFERROR(F91/F30*365,"") -> 189.88545 | G92: =IFERROR(G91/G30*366,"") -> 55.367771 | H92: =+G92 -> 55.367771 | I92: =+H92 -> 55.367771 | J92: =+I92 -> 55.367771 | K92: =+J92 -> 55.367771 | L92: =+K92 -> 55.367771 | M92: =+L92 -> 55.367771 | N92: =+M92 -> 55.367771 | O92: =+N92 -> 55.367771 | ... Z92: =+Y92 -> 55.367771
B94: Inventory | E94: =+_xlfn.XLOOKUP($B94,Inputs!$B:$B,Inputs!O:O) -> 0 | F94: =+_xlfn.XLOOKUP($B94,Inputs!$B:$B,Inputs!P:P) -> 0 | G94: =+_xlfn.XLOOKUP($B94,Inputs!$B:$B,Inputs!Q:Q) -> 0 | H94: =+IFERROR(H95*H33/365,"") -> 0 | I94: =+IFERROR(I95*I33/365,"") -> 0 | J94: =+IFERROR(J95*J33/365,"") -> 0 | K94: =+IFERROR(K95*K33/365,"") -> 0 | L94: =+IFERROR(L95*L33/365,"") -> 9751.1277 | M94: =+IFERROR(M95*M33/(365*10),"") -> 1706.4473 | N94: =+IFERROR(N95*N33/(365*10),"") -> 2866.8315 | O94: =+IFERROR(O95*O33/(365*10),"") -> 4682.4915 | P94: =+IFERROR(P95*P33/(365*10),"") -> 6435.0812 | Q94: =+IFERROR(Q95*Q33/(365*10),"") -> 9043.8979 | R94: =+IFERROR(R95*R33/(365*10),"") -> 11757.067 | S94: =+IFERROR(S95*S33/(365*10),"") -> 14696.334 | T94: =+IFERROR(T95*T33/(365*10),"") -> 18370.418 | ... Z94: =+IFERROR(Z95*Z33/(365*10),"") -> 62000.159
B95: DIH | E95: =IFERROR(E94/E33*365,"") -> 0 | F95: =IFERROR(F94/F33*365,"") -> 0 | G95: =IFERROR(G94/G33*365,"") -> 0 | H95: =IFERROR(AVERAGE(E95:G95),"") -> 0 | I95: =IFERROR(AVERAGE(F95:H95),"") -> 0 | J95: =IFERROR(AVERAGE(G95:I95),"") -> 0 | K95: =IFERROR(AVERAGE(H95:J95),"") -> 0 | L95: 20 | M95: 25 | N95: 30 | O95: 35 | P95: 37 | Q95: 40 | R95: 40 | S95: 40 | T95: 40 | U95: 40 | V95: 40 | W95: 40 | X95: 40 | Y95: 40 | Z95: 40
B97: Prepaid expenses and Other Current Assets | E97: =+_xlfn.XLOOKUP($B97,Inputs!$B:$B,Inputs!O:O) -> 12539 | F97: =+_xlfn.XLOOKUP($B97,Inputs!$B:$B,Inputs!P:P) -> 23081 | G97: =+_xlfn.XLOOKUP($B97,Inputs!$B:$B,Inputs!Q:Q) -> 31997 | H97: =IFERROR(AVERAGE(E97:G97)*(1+H31),"") -> 36062.4 | I97: =IFERROR(AVERAGE(F97:H97)*(1+I31),"") -> 48608.213 | J97: =IFERROR(AVERAGE(G97:I97)*(1+J31),"") -> 58333.807 | K97: =IFERROR(AVERAGE(H97:J97)*(1+K31),"") -> 71502.21 | L97: =IFERROR(AVERAGE(I97:K97)*(1+L31),"") -> 89222.115 | M97: =IFERROR(AVERAGE(J97:L97)*(1+M31),"") -> 102227.13 | N97: =IFERROR(AVERAGE(K97:M97)*(1+N31),"") -> 122710.68 | O97: =IFERROR(AVERAGE(L97:N97)*(1+O31),"") -> 146607.96 | ... Z97: =IFERROR(AVERAGE(W97:Y97)*(1+Z31),"") -> 485337.85
B98: growing with revenue | E98: =IFERROR(E97/E$30,"") -> 1.1264936 | F98: =IFERROR(F97/F$30,"") -> 1.0471373 | G98: =IFERROR(G97/G$30,"") -> 0.74285515 | H98: =IFERROR(H97/H$30,"") -> 0.52327444 | I98: =IFERROR(I97/I$30,"") -> 0.44082333 | J98: =IFERROR(J97/J$30,"") -> 0.35268255 | K98: =IFERROR(K97/K$30,"") -> 0.2881986 | L98: =IFERROR(L97/L$30,"") -> 0.23974726 | ... Z98: =IFERROR(Z97/Z$30,"") -> 0.041022047
B100: Net PP&E (Property, Plant and Equipment) + ROU Assets | E100: =+E101+E102-E104 -> 29767 | F100: =+F101+F102-F104 -> 42128 | G100: =+G101+G102-G104 -> 62231 | H100: =IFERROR(H101+H102-H104,"") -> 83018.586 | I100: =IFERROR(I101+I102-I104,"") -> 118147.05 | J100: =IFERROR(J101+J102-J104,"") -> 163240.05 | K100: =IFERROR(K101+K102-K104,"") -> 234554.58 | L100: =IFERROR(L101+L102-L104,"") -> 324530.75 | M100: =IFERROR(M101+M102-M104,"") -> 450041.73 | N100: =IFERROR(N101+N102-N104,"") -> 589422.6 | O100: =IFERROR(O101+O102-O104,"") -> 789487.28 | ... Z100: =IFERROR(Z101+Z102-Z104,"") -> 2580657.3
B101: Gross PP&E (Property, Plant and Equipment) + ROU Assets | E101: =+_xlfn.XLOOKUP("Gross PP&E (Property, Plant and Equipment)",Inputs!$B:$B,Inputs!O:O) -> 37228 | F101: =+_xlfn.XLOOKUP("Gross PP&E (Property, Plant and Equipment)",Inputs!$B:$B,Inputs!P:P) -> 56727 | G101: =+_xlfn.XLOOKUP("Gross PP&E (Property, Plant and Equipment)",Inputs!$B:$B,Inputs!Q:Q) -> 89843 | H101: =+IFERROR(G101-H135,"") -> 124301.4 | I101: =+IFERROR(H101-I135,"") -> 179434.84 | J101: =+IFERROR(I101-J135,"") -> 253864.98 | K101: =+IFERROR(J101-K135,"") -> 365510.2 | L101: =+IFERROR(K101-L135,"") -> 514370.49 | M101: =+IFERROR(L101-M135,"") -> 722774.89 | N101: =+IFERROR(M101-N135,"") -> 978070.29 | O101: =+IFERROR(N101-O135,"") -> 1335483.8 | ... Z101: =+IFERROR(Y101-Z135,"") -> 10778783
B102: Right-of-Use Assets | E102: =+_xlfn.XLOOKUP("Right-of-Use Assets",Inputs!$B:$B,Inputs!O:O) -> 0 | F102: =+_xlfn.XLOOKUP("Right-of-Use Assets",Inputs!$B:$B,Inputs!P:P) -> 0 | G102: =+_xlfn.XLOOKUP("Right-of-Use Assets",Inputs!$B:$B,Inputs!Q:Q) -> 0 | H102: =IFERROR(H103*H$30,"") -> 0 | I102: =IFERROR(I103*I$30,"") -> 0 | J102: =IFERROR(J103*J$30,"") -> 0 | K102: =IFERROR(K103*K$30,"") -> 0 | L102: =IFERROR(L103*L$30,"") -> 0 | M102: =IFERROR(M103*M$30,"") -> 0 | N102: =IFERROR(N103*N$30,"") -> 0 | O102: =IFERROR(O103*O$30,"") -> 0 | ... Z102: =IFERROR(Z103*Z$30,"") -> 0
B103: % of revenue | E103: =IFERROR(E102/E$30,"") -> 0 | F103: =IFERROR(F102/F$30,"") -> 0 | G103: =IFERROR(G102/G$30,"") -> 0 | H103: =IFERROR(AVERAGE(E103:G103),"") -> 0 | I103: =IFERROR(AVERAGE(F103:H103),"") -> 0 | J103: =IFERROR(AVERAGE(G103:I103),"") -> 0 | K103: =IFERROR(AVERAGE(H103:J103),"") -> 0 | L103: =IFERROR(AVERAGE(I103:K103),"") -> 0 | M103: =IFERROR(AVERAGE(J103:L103),"") -> 0 | N103: =IFERROR(AVERAGE(K103:M103),"") -> 0 | O103: =IFERROR(AVERAGE(L103:N103),"") -> 0 | ... Z103: =IFERROR(AVERAGE(W103:Y103),"") -> 0
B104: Accumulated Depreciation | E104: =+_xlfn.XLOOKUP($B104,Inputs!$B:$B,Inputs!O:O) -> 7461 | F104: =+_xlfn.XLOOKUP($B104,Inputs!$B:$B,Inputs!P:P) -> 14599 | G104: =+_xlfn.XLOOKUP($B104,Inputs!$B:$B,Inputs!Q:Q) -> 27612 | H104: =+IFERROR(G104+H54,"") -> 41282.814 | I104: =+IFERROR(H104+I54,"") -> 61287.794 | J104: =+IFERROR(I104+J54,"") -> 90624.93 | K104: =+IFERROR(J104+K54,"") -> 130955.62 | L104: =+IFERROR(K104+L54,"") -> 189839.74 | M104: =+IFERROR(L104+M54,"") -> 272733.16 | N104: =+IFERROR(M104+N54,"") -> 388647.69 | O104: =+IFERROR(N104+O54,"") -> 545996.56 | ... Z104: =+IFERROR(Y104+Z54,"") -> 8198125.2
B106: Intangibles excl. Goodwill | E106: =+_xlfn.XLOOKUP($B106,Inputs!$B:$B,Inputs!O:O) -> 8944 | F106: =+_xlfn.XLOOKUP($B106,Inputs!$B:$B,Inputs!P:P) -> 15077 | G106: =+_xlfn.XLOOKUP($B106,Inputs!$B:$B,Inputs!Q:Q) -> 29469 | H106: =+G106+H107*H43 -> 72952.621 | I106: =+H106+I107*I43-I57 -> 118728.86 | J106: =+I106+J107*J43-J57 -> 172848.46 | K106: =+J106+K107*K43-K57 -> 238252.87 | L106: =+K106+L107*L43-L57 -> 309593.39 | M106: =+L106+M107*M43-M57 -> 383552.63 | N106: =+M106+N107*N43-N57 -> 455627.46 | O106: =+N106+O107*O43-O57 -> 523754.23 | P106: =+O106+P107*P43-P57 -> 586034.95 | ... Z106: =+Y106+Z107*Z43-Z57 -> 944459.23
B107: growing with % of R&D | E107: =IFERROR((E106-Inputs!N45)/E43,"") -> 0.070558006 | F107: =IFERROR((F106-E106)/F43,"") -> 0.066431256 | G107: =IFERROR((G106-F106)/G43,"") -> 0.10518392 | H107: 0.227 | I107: =+H107-($H$107-$Z$107)/($Z$28-$G$85) -> 0.22136842 | J107: =+I107-($H$107-$Z$107)/($Z$28-$G$85) -> 0.21573684 | K107: =+J107-($H$107-$Z$107)/($Z$28-$G$85) -> 0.21010526 | L107: =+K107-($H$107-$Z$107)/($Z$28-$G$85) -> 0.20447368 | M107: =+L107-($H$107-$Z$107)/($Z$28-$G$85) -> 0.19884211 | N107: =+M107-($H$107-$Z$107)/($Z$28-$G$85) -> 0.19321053 | O107: =+N107-($H$107-$Z$107)/($Z$28-$G$85) -> 0.18757895 | P107: =+O107-($H$107-$Z$107)/($Z$28-$G$85) -> 0.18194737 | ... Y107: =+X107-($H$107-$Z$107)/($Z$28-$G$85) -> 0.13126316 | Z107: 0.12
B109: Liabilities
B111: Accounts Payable | E111: =+_xlfn.XLOOKUP($B111,Inputs!$B:$B,Inputs!O:O) -> 3055 | F111: =+_xlfn.XLOOKUP($B111,Inputs!$B:$B,Inputs!P:P) -> 5599 | G111: =+_xlfn.XLOOKUP($B111,Inputs!$B:$B,Inputs!Q:Q) -> 5230 | H111: =+IFERROR(H112*H33/365,"") -> 8125.9397 | I111: =+IFERROR(I112*I33/365,"") -> 9389.9748 | J111: =+IFERROR(J112*J33/365,"") -> 14084.962 | K111: =+IFERROR(K112*K33/365,"") -> 16251.879 | L111: =+IFERROR(L112*L33/365,"") -> 24377.819 | M111: =+IFERROR(M112*M33/365,"") -> 34128.947 | N111: =+IFERROR(N112*N33/365,"") -> 47780.526 | O111: =+IFERROR(O112*O33/365,"") -> 66892.736 | ... Z111: =+IFERROR(Z112*Z33/365,"") -> 418501.08
B112: DPO | E112: =IFERROR(E111/E$33*365,"") -> 378.76189 | F112: =IFERROR(F111/F$33*365,"") -> 252.05168 | G112: =IFERROR(G111/G$33*366,"") -> 92.934893 | H112: 90 | I112: 65 | J112: 65 | K112: 50 | L112: 50 | M112: 50 | N112: 50 | O112: 50 | P112: 45 | Q112: 45 | R112: 45 | S112: 45 | T112: 30 | U112: 30 | V112: 30 | W112: 30 | X112: 27 | Y112: 27 | Z112: 27
B114: Accrued Expenses and Other Current Liabilities | E114: =+_xlfn.XLOOKUP($B114,Inputs!$B:$B,Inputs!O:O) -> 16514 | F114: =+_xlfn.XLOOKUP($B114,Inputs!$B:$B,Inputs!P:P) -> 30855 | G114: =+_xlfn.XLOOKUP($B114,Inputs!$B:$B,Inputs!Q:Q) -> 27489 | H114: =IFERROR(AVERAGE(F114:G114)*(1+H31),"") -> 46675.2 | I114: =IFERROR(AVERAGE(G114:H114)*(1+I31),"") -> 59331.36 | J114: =IFERROR(AVERAGE(H114:I114)*(1+J31),"") -> 79504.92 | K114: =IFERROR(AVERAGE(I114:J114)*(1+K31),"") -> 104127.21 | L114: =IFERROR(AVERAGE(J114:K114)*(1+L31),"") -> 137724.1 | M114: =IFERROR(AVERAGE(K114:L114)*(1+M31),"") -> 169295.92 | N114: =IFERROR(AVERAGE(L114:M114)*(1+N31),"") -> 214914.01 | O114: =IFERROR(AVERAGE(M114:N114)*(1+O31),"") -> 268946.95 | ... Z114: =IFERROR(AVERAGE(X114:Y114)*(1+Z31),"") -> 1361355.8
B115: growing with revenue | E115: =IFERROR(E114/E$30,"") -> 1.4836043 | F115: =IFERROR(F114/F$30,"") -> 1.3998276 | G115: =IFERROR(G114/G$30,"") -> 0.63819562 | H115: =IFERROR(H114/H$30,"") -> 0.67726882 | I115: =IFERROR(I114/I$30,"") -> 0.53807054 | J115: =IFERROR(J114/J$30,"") -> 0.48068178 | K115: =IFERROR(K114/K$30,"") -> 0.41969774 | L115: =IFERROR(L114/L$30,"") -> 0.37007613 | ... Z115: =IFERROR(Z114/Z$30,"") -> 0.11506542
B117: Total Borrowings | E117: =+_xlfn.XLOOKUP($B117,Inputs!$B:$B,Inputs!O:O) -> 0 | F117: =+_xlfn.XLOOKUP($B117,Inputs!$B:$B,Inputs!P:P) -> 0 | G117: =+_xlfn.XLOOKUP($B117,Inputs!$B:$B,Inputs!Q:Q) -> 0 | H117: =IFERROR(G117+H158-H160,"") -> 245379.06 | I117: =IFERROR(H117+I158-I160,"") -> 245379.06 | J117: =IFERROR(I117+J158-J160,"") -> 536900.27 | K117: =IFERROR(J117+K158-K160,"") -> 616651.98 | L117: =IFERROR(K117+L158-L160,"") -> 1005215.7 | M117: =IFERROR(L117+M158-M160,"") -> 1188506 | N117: =IFERROR(M117+N158-N160,"") -> 1644703.6 | O117: =IFERROR(N117+O158-O160,"") -> 1879279.2 | ... Z117: =IFERROR(Y117+Z158-Z160,"") -> 3796845.2
B119: Total Leases | E119: =+_xlfn.XLOOKUP($B119,Inputs!$B:$B,Inputs!O:O) -> 4050 | F119: =+_xlfn.XLOOKUP($B119,Inputs!$B:$B,Inputs!P:P) -> 8105 | G119: =+_xlfn.XLOOKUP($B119,Inputs!$B:$B,Inputs!Q:Q) -> 17725 | H119: =+IFERROR(H120*H30,"") -> 26258.829 | I119: =+IFERROR(I120*I30,"") -> 42645.347 | J119: =+IFERROR(J120*J30,"") -> 65017.736 | K119: =+IFERROR(K120*K30,"") -> 96003.473 | L119: =+IFERROR(L120*L30,"") -> 144741.05 | M119: =+IFERROR(M120*M30,"") -> 203016.88 | N119: =+IFERROR(N120*N30,"") -> 283388.77 | O119: =+IFERROR(O120*O30,"") -> 397275.6 | ... Z119: =+IFERROR(Z120*Z30,"") -> 4601905.9
B120: % of revenues | E120: =IFERROR(E119/E$30,"") -> 0.36384871 | F120: =IFERROR(F119/F$30,"") -> 0.3677071 | G120: =IFERROR(G119/G$30,"") -> 0.41151069 | H120: =+IFERROR(AVERAGE(E120:G120),"") -> 0.38102217 | I120: =+IFERROR(AVERAGE(F120:H120),"") -> 0.38674665 | J120: =+IFERROR(AVERAGE(G120:I120),"") -> 0.39309317 | K120: =+IFERROR(AVERAGE(H120:J120),"") -> 0.386954 | L120: =+IFERROR(AVERAGE(I120:K120),"") -> 0.38893127 | M120: =+IFERROR(AVERAGE(J120:L120),"") -> 0.38965948 | N120: =+IFERROR(AVERAGE(K120:M120),"") -> 0.38851492 | O120: =+IFERROR(AVERAGE(L120:N120),"") -> 0.38903523 | ... Z120: =+IFERROR(AVERAGE(W120:Y120),"") -> 0.38896534
A122: x | B122: Cash Flow | E122: =E28 -> 2022 | F122: =F28 -> 2023 | G122: =G28 -> 2024 | H122: =H28 -> 2025 | I122: =I28 -> 2026 | J122: =J28 -> 2027 | K122: =K28 -> 2028 | L122: =L28 -> 2029 | ... Z122: =Z28 -> 2043
B124: D&A (Depreciation & Amortization) | E124: =+E51 -> 5604 | F124: =+F51 -> 10375 | G124: =+G51 -> 18654 | H124: =+H51 -> 21834.814 | I124: =+I51 -> 31475.283 | J124: =+J51 -> 47744.803 | K124: =+K51 -> 66750.503 | L124: =+L51 -> 94779.189 | ... Z124: =+Z51 -> 1559352.9
B126: Stock Based Compensation | E126: =+_xlfn.XLOOKUP($B126,Inputs!$B:$B,Inputs!O:O) -> 31456 | F126: =+_xlfn.XLOOKUP($B126,Inputs!$B:$B,Inputs!P:P) -> 69743 | G126: =+_xlfn.XLOOKUP($B126,Inputs!$B:$B,Inputs!Q:Q) -> 106878 | H126: =+G126*(1+H127) -> 111153.12 | I126: =+H126*(1+I127) -> 115599.24 | J126: =+I126*(1+J127) -> 120223.21 | K126: =+J126*(1+K127) -> 125032.14 | L126: =+K126*(1+L127) -> 130033.43 | M126: =+L126*(1+M127) -> 133934.43 | N126: =+M126*(1+N127) -> 137952.46 | O126: =+N126*(1+O127) -> 142091.04 | ... Z126: =+Y126*(1+Z127) -> 178378.79
B127: Growth | E127: =+IFERROR(E126/E39,"") -> 0.7092512 | F127: =+IFERROR(F126/F39,"") -> 1.0108853 | G127: =+IFERROR(G126/G39,"") -> 1.0746908 | H127: 0.04 | I127: 0.04 | J127: 0.04 | K127: 0.04 | L127: 0.04 | M127: 0.03 | N127: 0.03 | O127: 0.03 | P127: 0.03 | Q127: 0.03 | R127: 0.03 | S127: 0.02 | T127: 0.02 | U127: 0.02 | V127: 0.02 | W127: 0.015 | X127: 0.015 | Y127: 0.015 | Z127: 0.015
B129: Changes in Net Working Capital | E129: =+_xlfn.XLOOKUP($B129,Inputs!$B:$B,Inputs!O:O) -> -3286 | F129: =+_xlfn.XLOOKUP($B129,Inputs!$B:$B,Inputs!P:P) -> -16665 | G129: =+_xlfn.XLOOKUP($B129,Inputs!$B:$B,Inputs!Q:Q) -> -15754 | H129: =IFERROR(-((H91+H94+H97-H111-H114)-(G91+G94+G97-G111-G114)),"") -> 14078.576 | I129: =IFERROR(-((I91+I94+I97-I111-I114)-(H91+H94+H97-H111-H114)),"") -> -4898.1162 | J129: =IFERROR(-((J91+J94+J97-J111-J114)-(I91+I94+I97-I111-I114)),"") -> 6779.6234 | K129: =IFERROR(-((K91+K94+K97-K111-K114)-(J91+J94+J97-J111-J114)),"") -> 1075.808 | L129: =IFERROR(-((L91+L94+L97-L111-L114)-(K91+K94+K97-K111-K114)),"") -> -4565.6994 | M129: =IFERROR(-((M91+M94+M97-M111-M114)-(L91+L94+L97-L111-L114)),"") -> 13781.62 | N129: =IFERROR(-((N91+N94+N97-N111-N114)-(M91+M94+M97-M111-M114)),"") -> 6012.3484 | O129: =IFERROR(-((O91+O94+O97-O111-O114)-(N91+N94+N97-N111-N114)),"") -> 3173.4574 | ... Z129: =IFERROR(-((Z91+Z94+Z97-Z111-Z114)-(Y91+Y94+Y97-Y111-Y114)),"") -> -129764.15
B131: Other Operating Adjustments | E131: =+_xlfn.XLOOKUP($B131,Inputs!$B:$B,Inputs!O:O) -> -29961 | F131: =+_xlfn.XLOOKUP($B131,Inputs!$B:$B,Inputs!P:P) -> 15459.048 | G131: =+_xlfn.XLOOKUP($B131,Inputs!$B:$B,Inputs!Q:Q) -> 116127.06 | H131: =IFERROR(AVERAGE(E131:G131)*(1+H31),"") -> 54200.057 | I131: =IFERROR(AVERAGE(F131:H131)*(1+I31),"") -> 99085.954 | J131: =IFERROR(AVERAGE(G131:I131)*(1+J31),"") -> 134706.54 | K131: =IFERROR(AVERAGE(H131:J131)*(1+K31),"") -> 143996.27 | L131: =IFERROR(AVERAGE(I131:K131)*(1+L31),"") -> 188894.38 | M131: =IFERROR(AVERAGE(J131:L131)*(1+M31),"") -> 218212.02 | N131: =IFERROR(AVERAGE(K131:M131)*(1+N31),"") -> 257181.25 | O131: =IFERROR(AVERAGE(L131:N131)*(1+O31),"") -> 310000.9 | ... Z131: =IFERROR(AVERAGE(W131:Y131)*(1+Z31),"") -> 1024728.5
B133: Operating Cash Flow | E133: =+_xlfn.XLOOKUP($B133,Inputs!$B:$B,Inputs!O:O) -> -44698 | F133: =+_xlfn.XLOOKUP($B133,Inputs!$B:$B,Inputs!P:P) -> -78811 | G133: =+_xlfn.XLOOKUP($B133,Inputs!$B:$B,Inputs!Q:Q) -> -105683 | H133: =IFERROR(H82+H124+H126+H129+H131,"") -> -80178.379 | I133: =IFERROR(I82+I124+I126+I129+I131,"") -> -137301.82 | J133: =IFERROR(J82+J124+J126+J129+J131,"") -> -162136.25 | K133: =IFERROR(K82+K124+K126+K129+K131,"") -> -212673.94 | L133: =IFERROR(L82+L124+L126+L129+L131,"") -> -234099.4 | M133: =IFERROR(M82+M124+M126+M129+M131,"") -> -212871.46 | N133: =IFERROR(N82+N124+N126+N129+N131,"") -> -178296.51 | O133: =IFERROR(O82+O124+O126+O129+O131,"") -> -95397.594 | ... Z133: =IFERROR(Z82+Z124+Z126+Z129+Z131,"") -> 4131155.1
B135: Net CapEx | E135: =+_xlfn.XLOOKUP($B135,Inputs!$B:$B,Inputs!O:O) -> -12564 | F135: =+_xlfn.XLOOKUP($B135,Inputs!$B:$B,Inputs!P:P) -> -19549 | G135: =+_xlfn.XLOOKUP($B135,Inputs!$B:$B,Inputs!Q:Q) -> -23569 | H135: =IFERROR(H137+H140,"") -> -34458.4 | I135: =IFERROR(I137+I140,"") -> -55133.44 | J135: =IFERROR(J137+J140,"") -> -74430.144 | K135: =IFERROR(K137+K140,"") -> -111645.22 | L135: =IFERROR(L137+L140,"") -> -148860.29 | M135: =IFERROR(M137+M140,"") -> -208404.4 | N135: =IFERROR(N137+N140,"") -> -255295.39 | O135: =IFERROR(O137+O140,"") -> -357413.55 | ... Z135: =IFERROR(Z137+Z140,"") -> -1774672
B137: Acquisition of Fixed & Intangibles | E137: =+_xlfn.XLOOKUP($B137,Inputs!$B:$B,Inputs!O:O) -> -12564 | F137: =+_xlfn.XLOOKUP($B137,Inputs!$B:$B,Inputs!P:P) -> -19549 | G137: =+_xlfn.XLOOKUP($B137,Inputs!$B:$B,Inputs!Q:Q) -> -23569 | H137: =+H138*H30 -> -34458.4 | I137: =+I138*I30 -> -55133.44 | J137: =+J138*J30 -> -74430.144 | K137: =+K138*K30 -> -111645.22 | L137: =+L138*L30 -> -148860.29 | M137: =+M138*M30 -> -208404.4 | N137: =+N138*N30 -> -255295.39 | O137: =+O138*O30 -> -357413.55 | ... Z137: =+Z138*Z30 -> -1774672
B138: % of revenue | E138: =IFERROR(E137/E$30,"") -> -1.1287396 | F138: =IFERROR(F137/F$30,"") -> -0.88689774 | G138: =IFERROR(G137/G$30,"") -> -0.54718733 | H138: -0.5 | I138: -0.5 | J138: -0.45 | K138: -0.45 | L138: -0.4 | M138: -0.4 | N138: -0.35 | O138: -0.35 | P138: -0.3 | Q138: -0.3 | R138: -0.2 | S138: -0.2 | T138: -0.15 | U138: -0.15 | V138: -0.15 | W138: -0.15 | X138: -0.15 | Y138: -0.15 | Z138: -0.15
B140: Disposal of Fixed & Intangibles | E140: =+_xlfn.XLOOKUP($B140,Inputs!$B:$B,Inputs!O:O) -> 0 | F140: =+_xlfn.XLOOKUP($B140,Inputs!$B:$B,Inputs!P:P) -> 0 | G140: =+_xlfn.XLOOKUP($B140,Inputs!$B:$B,Inputs!Q:Q) -> 0 | H140: =IFERROR(H141*G101,"") -> 0 | I140: =IFERROR(I141*H101,"") -> 0 | J140: =IFERROR(J141*I101,"") -> 0 | K140: =IFERROR(K141*J101,"") -> 0 | L140: =IFERROR(L141*K101,"") -> 0 | M140: =IFERROR(M141*L101,"") -> 0 | N140: =IFERROR(N141*M101,"") -> 0 | O140: =IFERROR(O141*N101,"") -> 0 | ... Z140: =IFERROR(Z141*Y101,"") -> 0
B141: Disposal Rate (% Gross PP&E) | E141: =IFERROR(E140/E101,"") -> 0 | F141: =IFERROR(F140/F101,"") -> 0 | G141: =IFERROR(G140/G101,"") -> 0 | H141: =IFERROR(AVERAGE(E141:G141),"") -> 0 | I141: =IFERROR(AVERAGE(F141:H141),"") -> 0 | J141: =IFERROR(AVERAGE(G141:I141),"") -> 0 | K141: =IFERROR(AVERAGE(H141:J141),"") -> 0 | L141: =IFERROR(AVERAGE(I141:K141),"") -> 0 | M141: =IFERROR(AVERAGE(J141:L141),"") -> 0 | N141: =IFERROR(AVERAGE(K141:M141),"") -> 0 | O141: =IFERROR(AVERAGE(L141:N141),"") -> 0 | ... Z141: =IFERROR(AVERAGE(W141:Y141),"") -> 0
B143: Net Cash from Investments & Acquisitions | E143: =+_xlfn.XLOOKUP($B143,Inputs!$B:$B,Inputs!O:O) -> 309197 | F143: =+_xlfn.XLOOKUP($B143,Inputs!$B:$B,Inputs!P:P) -> 386760 | G143: =+_xlfn.XLOOKUP($B143,Inputs!$B:$B,Inputs!Q:Q) -> -15454 | H143: 0 | I143: 0 | J143: 0 | K143: 0 | L143: 0 | M143: 0 | N143: 0 | O143: 0 | P143: 0 | Q143: 0 | R143: 0 | S143: 0 | T143: 0 | U143: 0 | V143: 0 | W143: 0 | X143: 0 | Y143: 0 | Z143: 0
B145: Other Investing Inflows (Outflows) | E145: =+_xlfn.XLOOKUP($B145,Inputs!$B:$B,Inputs!O:O) -> -605689 | F145: =+_xlfn.XLOOKUP($B145,Inputs!$B:$B,Inputs!P:P) -> -298445 | G145: =+_xlfn.XLOOKUP($B145,Inputs!$B:$B,Inputs!Q:Q) -> 121753 | H145: =IFERROR(AVERAGE(E145:G145)*(1+H31),"") -> -417269.87 | I145: =IFERROR(AVERAGE(F145:H145)*(1+I31),"") -> -316779.66 | J145: =IFERROR(AVERAGE(G145:I145)*(1+J31),"") -> -306148.26 | K145: =IFERROR(AVERAGE(H145:J145)*(1+K31),"") -> -520098.9 | L145: =IFERROR(AVERAGE(I145:K145)*(1+L31),"") -> -571513.41 | M145: =IFERROR(AVERAGE(J145:L145)*(1+M31),"") -> -652288.27 | N145: =IFERROR(AVERAGE(K145:M145)*(1+N31),"") -> -813820.27 | O145: =IFERROR(AVERAGE(L145:N145)*(1+O31),"") -> -950890.24 | ... Z145: =IFERROR(AVERAGE(W145:Y145)*(1+Z31),"") -> -3163305.3
B147: Investing Cash Flow | E147: =+_xlfn.XLOOKUP($B147,Inputs!$B:$B,Inputs!O:O) -> -309056 | F147: =+_xlfn.XLOOKUP($B147,Inputs!$B:$B,Inputs!P:P) -> 68766 | G147: =+_xlfn.XLOOKUP($B147,Inputs!$B:$B,Inputs!Q:Q) -> 82730 | H147: =IFERROR(+H135+H143+H145,"") -> -451728.27 | I147: =IFERROR(+I135+I143+I145,"") -> -371913.1 | J147: =IFERROR(+J135+J143+J145,"") -> -380578.41 | K147: =IFERROR(+K135+K143+K145,"") -> -631744.11 | L147: =IFERROR(+L135+L143+L145,"") -> -720373.7 | M147: =IFERROR(+M135+M143+M145,"") -> -860692.67 | N147: =IFERROR(+N135+N143+N145,"") -> -1069115.7 | O147: =IFERROR(+O135+O143+O145,"") -> -1308303.8 | ... Z147: =IFERROR(+Z135+Z143+Z145,"") -> -4937977.2
B149: Dividends | E149: =+_xlfn.XLOOKUP($B149,Inputs!$B:$B,Inputs!O:O) -> 0 | F149: =+_xlfn.XLOOKUP($B149,Inputs!$B:$B,Inputs!P:P) -> 0 | G149: =+_xlfn.XLOOKUP($B149,Inputs!$B:$B,Inputs!Q:Q) -> 0 | H149: =+IFERROR(H150*_xlfn.XLOOKUP("Net Income",$B:$B,$H:$H),"") -> 0 | I149: =+IFERROR(I150*_xlfn.XLOOKUP("Net Income",$B:$B,$H:$H),"") -> 0 | J149: =+IFERROR(J150*_xlfn.XLOOKUP("Net Income",$B:$B,$H:$H),"") -> 0 | K149: =+IFERROR(K150*_xlfn.XLOOKUP("Net Income",$B:$B,$H:$H),"") -> 0 | L149: =+IFERROR(L150*_xlfn.XLOOKUP("Net Income",$B:$B,$H:$H),"") -> 0 | M149: =+IFERROR(M150*_xlfn.XLOOKUP("Net Income",$B:$B,$H:$H),"") -> 0 | N149: =+IFERROR(N150*_xlfn.XLOOKUP("Net Income",$B:$B,$H:$H),"") -> 0 | O149: =+IFERROR(O150*_xlfn.XLOOKUP("Net Income",$B:$B,$H:$H),"") -> 0 | ... Z149: =+IFERROR(Z150*_xlfn.XLOOKUP("Net Income",$B:$B,$H:$H),"") -> 0
B150: Dividend payout | E150: =IFERROR(-E149/E$82,"") -> 0 | F150: =IFERROR(-F149/F$82,"") -> 0 | G150: =IFERROR(-G149/G$82,"") -> 0 | H150: 0 | I150: 0 | J150: 0 | K150: 0 | L150: 0 | M150: 0 | N150: 0 | O150: 0 | P150: 0 | Q150: 0 | R150: 0 | S150: 0 | T150: 0 | U150: 0 | V150: 0 | W150: 0 | X150: 0 | Y150: 0 | Z150: 0
B152: Increase (Repurchase) of Shares | E152: =+_xlfn.XLOOKUP($B152,Inputs!$B:$B,Inputs!O:O) -> -905 | F152: =+_xlfn.XLOOKUP($B152,Inputs!$B:$B,Inputs!P:P) -> 1954 | G152: =+_xlfn.XLOOKUP($B152,Inputs!$B:$B,Inputs!Q:Q) -> 41449 | H152: =IFERROR(-H153*_xlfn.XLOOKUP("Net Income",$B:$B,H:H),"") -> 0 | I152: =IFERROR(-I153*_xlfn.XLOOKUP("Net Income",$B:$B,I:I),"") -> 0 | J152: =IFERROR(-J153*_xlfn.XLOOKUP("Net Income",$B:$B,J:J),"") -> 0 | K152: =IFERROR(-K153*_xlfn.XLOOKUP("Net Income",$B:$B,K:K),"") -> 0 | L152: =IFERROR(-L153*_xlfn.XLOOKUP("Net Income",$B:$B,L:L),"") -> 0 | M152: =IFERROR(-M153*_xlfn.XLOOKUP("Net Income",$B:$B,M:M),"") -> 0 | N152: =IFERROR(-N153*_xlfn.XLOOKUP("Net Income",$B:$B,N:N),"") -> 0 | O152: =IFERROR(-O153*_xlfn.XLOOKUP("Net Income",$B:$B,O:O),"") -> 0 | P152: =IFERROR(-P153*_xlfn.XLOOKUP("Net Income",$B:$B,P:P),"") -> 0 | Q152: =IFERROR(-Q153*_xlfn.XLOOKUP("Net Income",$B:$B,Q:Q),"") -> 0 | R152: =IFERROR(-R153*_xlfn.XLOOKUP("Net Income",$B:$B,R:R),"") -> 0 | S152: =IFERROR(-S153*_xlfn.XLOOKUP("Net Income",$B:$B,S:S),"") -> 0 | T152: =IFERROR(-T153*_xlfn.XLOOKUP("Net Income",$B:$B,T:T),"") -> 0 | U152: =IFERROR(-U153*_xlfn.XLOOKUP("Net Income",$B:$B,U:U),"") -> 0 | V152: =IFERROR(-V153*_xlfn.XLOOKUP("Net Income",$B:$B,V:V),"") -> 0 | W152: =IFERROR(-W153*_xlfn.XLOOKUP("Net Income",$B:$B,W:W),"") -> 0 | X152: =IFERROR(-X153*_xlfn.XLOOKUP("Net Income",$B:$B,X:X),"") -> 0 | Y152: =IFERROR(-Y153*_xlfn.XLOOKUP("Net Income",$B:$B,Y:Y),"") -> 0 | Z152: =IFERROR(-Z153*_xlfn.XLOOKUP("Net Income",$B:$B,Z:Z),"") -> 0
...

Sheet Inputs
B2: Inputs
B3: in thousands of USD
A4: x | B4: Income Statement | G4: 2014 | H4: =+G4+1 -> 2015 | I4: =+H4+1 -> 2016 | J4: =+I4+1 -> 2017 | K4: =+J4+1 -> 2018 | L4: =+K4+1 -> 2019 | M4: =+L4+1 -> 2020 | N4: =+M4+1 -> 2021 | O4: =+N4+1 -> 2022 | ... Q4: =+P4+1 -> 2024 | R4: ="CAGR "&$N$4&" - "&$Q$4 -> CAGR 2021 - 2024
B6: Revenue (Sales) | M6: =IS!B6 -> 0 | N6: 2099 | O6: 11131 | P6: 22042 | Q6: 43073 | R6: =IFERROR((Q6/N6)^(1/COUNT($N$4:$Q$4))-1,"") -> 1.1283751
B7: COGS (Cost of Goods Sold) | M7: =IS!B9 -> 143 | N7: 1040 | O7: 2944 | P7: 8108 | Q7: 20597 | R7: =IFERROR((Q7/N7)^(1/COUNT($N$4:$Q$4))-1,"") -> 1.1095638
B8: Gross Profit | G8: =G6-G7 -> 0 | H8: =H6-H7 -> 0 | I8: =I6-I7 -> 0 | J8: =J6-J7 -> 0 | K8: =K6-K7 -> 0 | L8: =L6-L7 -> 0 | M8: =M6-M7 -> -143 | N8: =N6-N7 -> 1059 | ... Q8: =Q6-Q7 -> 22476 | R8: =IFERROR((Q8/N8)^(1/COUNT($N$4:$Q$4))-1,"") -> 1.1463758
B9: SG&A (Selling, General & Administrative) | M9: =IS!B13 -> 4033 | N9: 16970 | O9: 44351 | P9: 68992 | Q9: 99450 | R9: =IFERROR((Q9/N9)^(1/COUNT($N$4:$Q$4))-1,"") -> 0.55589662
B10: R&D (Research & Development) | M10: =IS!B16 -> 10157 | N10: 20228 | O10: 43978 | P10: 92321 | Q10: 136827 | R10: =IFERROR((Q10/N10)^(1/COUNT($N$4:$Q$4))-1,"") -> 0.61270419
B11: Other Operating (Income) Expenses | M11: =IS!B18 -> 0 | N11: 0 | O11: 0 | P11: 0 | Q11: 0 | R11: =IFERROR((Q11/N11)^(1/COUNT($N$4:$Q$4))-1,"") | T11: Amortization
B12: EBITDA | G12: =+G8-G9-G10-G11 -> 0 | H12: =+H8-H9-H10-H11 -> 0 | I12: =+I8-I9-I10-I11 -> 0 | J12: =+J8-J9-J10-J11 -> 0 | K12: =+K8-K9-K10-K11 -> 0 | L12: =+L8-L9-L10-L11 -> 0 | M12: =+M8-M9-M10-M11 -> -14333 | N12: =+N8-N9-N10-N11 -> -36139 | ... Q12: =+Q8-Q9-Q10-Q11 -> -213801 | R12: =IFERROR((Q12/N12)^(1/COUNT($N$4:$Q$4))-1,"") -> 0.55958267 | T12: 2022 | U12: =T$12+1 -> 2023 | V12: =U$12+1 -> 2024 | W12: 2025* | X12: 2026* | Y12: 2027* | Z12: 2028* | AA12: 2029* | AB12: Thereafter
B13: D&A (Depreciation & Amortization) | G13: =+SUM(G14:G15) -> 0 | H13: =+SUM(H14:H15) -> 0 | I13: =+SUM(I14:I15) -> 0 | J13: =+SUM(J14:J15) -> 0 | K13: =+SUM(K14:K15) -> 0 | L13: =+SUM(L14:L15) -> 0 | M13: =IS!B17 -> 1400 | N13: 2548 | O13: 5604 | P13: 10375 | Q13: 18654 | R13: =IFERROR((Q13/N13)^(1/COUNT($N$4:$Q$4))-1,"") -> 0.64491377 | T13: 5600 | U13: 3200 | V13: 1600 | W13: 8164 | X13: 6495 | Y13: 3660 | Z13: 2573 | AA13: 2570 | AB13: 5630
B14: Depreciation Expense | M14: =IS!B69 -> — | N14: 0 | O14: 4000 | P14: 7200 | Q14: 13000 | R14: =IFERROR((Q14/N14)^(1/COUNT($N$4:$Q$4))-1,"") | U14: =T13/U13 -> 1.75 | V14: =U13/V13 -> 2 | W14: =V13/W13 -> 0.19598236 | X14: =W13/X13 -> 1.2569669 | Y14: =X13/Y13 -> 1.7745902 | Z14: =Y13/Z13 -> 1.422464 | AA14: =Z13/AA13 -> 1.0011673 | AB14: =AA13/AB13 -> 0.45648313
B15: Amortization Expense | R15: =IFERROR((Q15/N15)^(1/COUNT($N$4:$Q$4))-1,"") | T15: *Projected by the company
B16: Operating Income (EBIT) | G16: =+G12-G13 -> 0 | H16: =+H12-H13 -> 0 | I16: =+I12-I13 -> 0 | J16: =+J12-J13 -> 0 | K16: =+K12-K13 -> 0 | L16: =+L12-L13 -> 0 | M16: =+M12-M13 -> -15733 | N16: =+N12-N13 -> -38687 | ... Q16: =+Q12-Q13 -> -232455 | R16: =IFERROR((Q16/N16)^(1/COUNT($N$4:$Q$4))-1,"") -> 0.56564559
B17: Net Interest Expense (Income) | G17: =+G18-G19 -> 0 | H17: =+H18-H19 -> 0 | I17: =+I18-I19 -> 0 | J17: =+J18-J19 -> 0 | K17: =+K18-K19 -> 0 | L17: =+L18-L19 -> 0 | M17: =+M18-M19 -> 0 | N17: 0 | O17: -7093 | P17: -19322 | Q17: -18249 | R17: =IFERROR((Q17/N17)^(1/COUNT($N$4:$Q$4))-1,"")
B18: Interest Expense | M18: 0 | N18: 0 | O18: 0 | P18: 0 | Q18: 0 | R18: =IFERROR((Q18/N18)^(1/COUNT($N$4:$Q$4))-1,"")
B19: Interest Income | M19: 0 | N19: 0 | O19: 7093 | P19: 19322 | Q19: 18249 | R19: =IFERROR((Q19/N19)^(1/COUNT($N$4:$Q$4))-1,"") | T19: Intangables without Goodwill as % of R&D
B20: FX (Gain) Loss | M20: 0 | N20: 0 | O20: 0 | P20: 0 | Q20: 0 | R20: =IFERROR((Q20/N20)^(1/COUNT($N$4:$Q$4))-1,"") | T20: 2020 | U20: =T$20+1 -> 2021 | V20: =U$20+1 -> 2022 | W20: =V$20+1 -> 2023 | X20: =W$20+1 -> 2024 | Y20: AVERAGE
B21: Other Non-Operating (Income) Expenses | M21: =IS!B25 -> -309 | N21: 67499 | O21: -30142 | P21: 19291 | Q21: 117382 | R21: =IFERROR((Q21/N21)^(1/COUNT($N$4:$Q$4))-1,"") -> 0.14835467 | T21: =M45/M10 -> 0.26454662 | U21: =N45/N10 -> 0.28875816 | V21: =O45/O10 -> 0.20337441 | W21: =P45/P10 -> 0.16331062 | X21: =Q45/Q10 -> 0.21537416 | Y21: =AVERAGE(T21:X21) -> 0.22707279
B22: Pre-Tax Income (EBT) | G22: =+G16-G17-G20-G21 -> 0 | H22: =+H16-H17-H20-H21 -> 0 | I22: =+I16-I17-I20-I21 -> 0 | J22: =+J16-J17-J20-J21 -> 0 | K22: =+K16-K17-K20-K21 -> 0 | L22: =+L16-L17-L20-L21 -> 0 | M22: =+M16-M17-M20-M21 -> -15424 | N22: =+N16-N17-N20-N21 -> -106186 | ... Q22: =+Q16-Q17-Q20-Q21 -> -331588 | R22: =IFERROR((Q22/N22)^(1/COUNT($N$4:$Q$4))-1,"") -> 0.32933025
B23: Tax Expense (Benefits) | M23: =IS!B29 -> 0 | N23: 0 | O23: 0 | P23: 0.048 | Q23: 0.059 | R23: =IFERROR((Q23/N23)^(1/COUNT($N$4:$Q$4))-1,"")
B24: Net Income | G24: =+G22-G23 -> 0 | H24: =+H22-H23 -> 0 | I24: =+I22-I23 -> 0 | J24: =+J22-J23 -> 0 | K24: =+K22-K23 -> 0 | L24: =+L22-L23 -> 0 | M24: =+M22-M23 -> -15424 | N24: =+N22-N23 -> -106186 | ... Q24: =+Q22-Q23 -> -331588.06 | R24: =IFERROR((Q24/N24)^(1/COUNT($N$4:$Q$4))-1,"") -> 0.3293303
B25: EPS basic | M25: =IS!B48 -> -0.13 | N25: -0.77 | O25: -0.25 | P25: -0.78 | Q25: -1.56 | R25: =IFERROR((Q25/N25)^(1/COUNT($N$4:$Q$4))-1,"") -> 0.19304951
B26: EPS diluted | M26: =IS!B53 -> -0.13 | N26: -0.77 | O26: -0.25 | P26: -0.78 | Q26: -1.56 | R26: =IFERROR((Q26/N26)^(1/COUNT($N$4:$Q$4))-1,"") -> 0.19304951
B27: Basic Weighted Average Shares | M27: =IS!B47 -> 115 | N27: 137609.6 | O27: 197727.6 | P27: 202576.5 | Q27: 213029.4 | R27: =IFERROR((Q27/N27)^(1/COUNT($N$4:$Q$4))-1,"") -> 0.11544382
B28: Diluted Weighted Average Shares | M28: =IS!B52 -> 115 | N28: 137609.6 | O28: 197727.6 | P28: 202576.5 | Q28: 213029.4 | R28: =IFERROR((Q28/N28)^(1/COUNT($N$4:$Q$4))-1,"") -> 0.11544382
A30: x | B30: Balance Sheet | G30: 2014 | H30: =+G30+1 -> 2015 | I30: =+H30+1 -> 2016 | J30: =+I30+1 -> 2017 | K30: =+J30+1 -> 2018 | L30: =+K30+1 -> 2019 | M30: =+L30+1 -> 2020 | N30: =+M30+1 -> 2021 | O30: =+N30+1 -> 2022 | ... Q30: =+P30+1 -> 2024 | R30: ="CAGR "&$N$4&" - "&$Q$4 -> CAGR 2021 - 2024
B32: Cash & Cash Equivalents & ST Investments | G32: =+SUM(G33:G34) -> 0 | H32: =+SUM(H33:H34) -> 0 | I32: =+SUM(I33:I34) -> 0 | J32: =+SUM(J33:J34) -> 0 | K32: =+SUM(K33:K34) -> 0 | L32: =+SUM(L33:L34) -> 0 | M32: =+SUM(M33:M34) -> 36120 | N32: =+SUM(N33:N34) -> 522468 | ... Q32: =+SUM(Q33:Q34) -> 340289 | R32: =IFERROR((Q32/N32)^(1/COUNT($N$4:$Q$4))-1,"") -> -0.10164694
B33: Cash & Cash Equivalents | M33: 36120 | N33: 399025 | O33: 44367 | P33: 35665 | Q33: 54393 | R33: =IFERROR((Q33/N33)^(1/COUNT($N$4:$Q$4))-1,"") -> -0.39237487
B34: Short-Term Investments | M34: 0 | N34: 123443 | O34: 311430 | P34: 319776 | Q34: 285896 | R34: =IFERROR((Q34/N34)^(1/COUNT($N$4:$Q$4))-1,"") -> 0.23363137
B35: Accounts Receivable | M35: 390 | N35: 707 | O35: 3292 | P35: 11467 | Q35: 6516 | R35: =IFERROR((Q35/N35)^(1/COUNT($N$4:$Q$4))-1,"") -> 0.74237012
B36: Inventory | M36: 0 | N36: 0 | O36: 0 | P36: 0 | Q36: 0 | R36: =IFERROR((Q36/N36)^(1/COUNT($N$4:$Q$4))-1,"")
B37: Prepaid expenses and Other Current Assets | G37: =+G38-G32-G35-G36 -> 0 | H37: =+H38-H32-H35-H36 -> 0 | I37: =+I38-I32-I35-I36 -> 0 | J37: =+J38-J32-J35-J36 -> 0 | K37: =+K38-K32-K35-K36 -> 0 | L37: =+L38-L32-L35-L36 -> 0 | M37: =+M38-M32-M35-M36 -> 2069 | N37: =+N38-N32-N35-N36 -> 6442 | ... Q37: =+Q38-Q32-Q35-Q36 -> 31997 | R37: =IFERROR((Q37/N37)^(1/COUNT($N$4:$Q$4))-1,"") -> 0.4928705
B38: Current Assets | M38: 38579 | N38: 529617 | O38: 371628 | P38: 389989 | Q38: 378802 | R38: =IFERROR((Q38/N38)^(1/COUNT($G$4:$Q$4))-1,"") -> -0.030007864
B39: Net PP&E (Property, Plant and Equipment) | G39: =+G40-G41 -> 0 | H39: =+H40-H41 -> 0 | I39: =+I40-I41 -> 0 | J39: =+J40-J41 -> 0 | K39: =+K40-K41 -> 0 | L39: =+L40-L41 -> 0 | M39: =+M40-M41 -> 16284 | N39: =+N40-N41 -> 22902 | ... Q39: =+Q40-Q41 -> 62231 | R39: =IFERROR((Q39/N39)^(1/COUNT($G$4:$Q$4))-1,"") -> 0.095132506
B40: Gross PP&E (Property, Plant and Equipment) | M40: 17987 | N40: 26347 | O40: 37228 | P40: 56727 | Q40: 89843 | R40: =IFERROR((Q40/N40)^(1/COUNT($G$4:$Q$4))-1,"") -> 0.11797501
B41: Accumulated Depreciation | M41: 1703 | N41: 3445 | O41: 7461 | P41: 14599 | Q41: 27612 | R41: =IFERROR((Q41/N41)^(1/COUNT($G$4:$Q$4))-1,"") -> 0.20829649
B42: Right-of-Use Assets | R42: =IFERROR((Q42/N42)^(1/COUNT($G$4:$Q$4))-1,"")
B43: Intangibles | M43: 2687 | N43: 5841 | O43: 9686 | P43: 15819 | Q43: 39373 | R43: =IFERROR((Q43/N43)^(1/COUNT($G$4:$Q$4))-1,"") -> 0.1894259
B44: Goodwill | M44: 0 | N44: 0 | O44: 742 | P44: 742 | Q44: 9904 | R44: =IFERROR((Q44/O44)^(1/COUNT($G$4:$Q$4))-1,"") -> 0.26563857
B45: Intangibles excl. Goodwill | G45: =+G43-G44 -> 0 | H45: =+H43-H44 -> 0 | I45: =+I43-I44 -> 0 | J45: =+J43-J44 -> 0 | K45: =+K43-K44 -> 0 | L45: =+L43-L44 -> 0 | M45: =+M43-M44 -> 2687 | N45: =+N43-N44 -> 5841 | ... Q45: =+Q43-Q44 -> 29469 | R45: =IFERROR((Q45/N45)^(1/COUNT($G$4:$Q$4))-1,"") -> 0.15850528
B46: Other Non-Current Assets | G46: =+G47-G39-G42-G43 -> 0 | H46: =+H47-H39-H42-H43 -> 0 | I46: =+I47-I39-I42-I43 -> 0 | J46: =+J47-J39-J42-J43 -> 0 | K46: =+K47-K39-K42-K43 -> 0 | L46: =+L47-L39-L42-L43 -> 0 | M46: =+M47-M39-M42-M43 -> 2928 | N46: =+N47-N39-N42-N43 -> 83668 | ... Q46: =+Q47-Q39-Q42-Q43 -> 27982 | R46: =IFERROR((Q46/N46)^(1/COUNT($G$4:$Q$4))-1,"") -> -0.094775487
B47: Non-Current Assets | M47: 21899 | N47: 112411 | O47: 226364 | P47: 163591 | Q47: 129586 | R47: =IFERROR((Q47/N47)^(1/COUNT($G$4:$Q$4))-1,"") -> 0.013009622
B48: Total Assets | G48: =SUM(G47,G38) -> 0 | H48: =SUM(H47,H38) -> 0 | I48: =SUM(I47,I38) -> 0 | J48: =SUM(J47,J38) -> 0 | K48: =SUM(K47,K38) -> 0 | L48: =SUM(L47,L38) -> 0 | M48: =SUM(M47,M38) -> 60478 | N48: =SUM(N47,N38) -> 642028 | ... Q48: =SUM(Q47,Q38) -> 508388 | R48: =IFERROR((Q48/N48)^(1/COUNT($G$4:$Q$4))-1,"") -> -0.020993501
B49: Accounts Payable | M49: 538 | N49: 1882 | O49: 3055 | P49: 5599 | Q49: 5230 | R49: =IFERROR((Q49/N49)^(1/COUNT($G$4:$Q$4))-1,"") -> 0.097369576
B50: Short-Term Debt | G50: =+SUM(G51:G52) -> 0 | H50: =+SUM(H51:H52) -> 0 | I50: =+SUM(I51:I52) -> 0 | J50: =+SUM(J51:J52) -> 0 | K50: =+SUM(K51:K52) -> 0 | L50: =+SUM(L51:L52) -> 0 | M50: =+SUM(M51:M52) -> 495 | N50: =+SUM(N51:N52) -> 568 | ... Q50: =+SUM(Q51:Q52) -> 3366 | R50: =IFERROR((Q50/N50)^(1/COUNT($G$4:$Q$4))-1,"") -> 0.17557796
B51: Short-Term Borrowings | M51: 0 | N51: 0 | O51: 0 | P51: 0 | Q51: 0 | R51: =IFERROR((Q51/N51)^(1/COUNT($G$4:$Q$4))-1,"")
B52: Current Portion of Lease Liabilities | M52: 495 | N52: 568 | O52: 591 | P52: 710 | Q52: 3366 | R52: =IFERROR((Q52/N52)^(1/COUNT($G$4:$Q$4))-1,"") -> 0.17557796
B53: Accrued Expenses and Other Current Liabilities | G53: =+G54-G49-G50 -> 0 | H53: =+H54-H49-H50 -> 0 | I53: =+I54-I49-I50 -> 0 | J53: =+J54-J49-J50 -> 0 | K53: =+K54-K49-K50 -> 0 | L53: =+L54-L49-L50 -> 0 | M53: =+M54-M49-M50 -> 848 | N53: =+N54-N49-N50 -> 7241 | ... Q53: =+Q54-Q49-Q50 -> 27489 | R53: =IFERROR((Q53/N53)^(1/COUNT($G$4:$Q$4))-1,"") -> 0.12893549
B54: Current Liabilities | M54: 1881 | N54: 9691 | O54: 20160 | P54: 37164 | Q54: 36085 | R54: =IFERROR((Q54/N54)^(1/COUNT($G$4:$Q$4))-1,"") -> 0.12695165
B55: Long-Term Debt | G55: =+SUM(G56:G57) -> 0 | H55: =+SUM(H56:H57) -> 0 | I55: =+SUM(I56:I57) -> 0 | J55: =+SUM(J56:J57) -> 0 | K55: =+SUM(K56:K57) -> 0 | L55: =+SUM(L56:L57) -> 0 | M55: =+SUM(M56:M57) -> 3776 | N55: =+SUM(N56:N57) -> 3643 | ... Q55: =+SUM(Q56:Q57) -> 14359 | R55: =IFERROR((Q55/N55)^(1/COUNT($G$4:$Q$4))-1,"") -> 0.13279511
B56: Long-Term Borrowings | M56: 0 | N56: 0 | O56: 0 | P56: 0 | Q56: 0 | R56: =IFERROR((Q56/N56)^(1/COUNT($G$4:$Q$4))-1,"")
B57: Long-Term Operating Lease Liabilities | M57: 3776 | N57: 3643 | O57: 3459 | P57: 7395 | Q57: 14359 | R57: =IFERROR((Q57/N57)^(1/COUNT($G$4:$Q$4))-1,"") -> 0.13279511
B58: Other Non-Current Liabilities | G58: =+G59-G55 -> 0 | H58: =+H59-H55 -> 0 | I58: =+I59-I55 -> 0 | J58: =+J59-J55 -> 0 | K58: =+K59-K55 -> 0 | L58: =+L59-L55 -> 0 | M58: =+M59-M55 -> 1118 | N58: =+N59-N55 -> 37464 | ... Q58: =+Q59-Q55 -> 74082 | R58: =IFERROR((Q58/N58)^(1/COUNT($G$4:$Q$4))-1,"") -> 0.063942238
B59: Non-Current Liabilities | M59: 4894 | N59: 41107 | O59: 9621 | P59: 31422 | Q59: 88441 | R59: =IFERROR((Q59/N59)^(1/COUNT($G$4:$Q$4))-1,"") -> 0.072133575
B60: Total Liabilities | G60: =SUM(G59,G54) -> 0 | H60: =SUM(H59,H54) -> 0 | I60: =SUM(I59,I54) -> 0 | J60: =SUM(J59,J54) -> 0 | K60: =SUM(K59,K54) -> 0 | L60: =SUM(L59,L54) -> 0 | M60: =SUM(M59,M54) -> 6775 | N60: =SUM(N59,N54) -> 50798 | ... Q60: =SUM(Q59,Q54) -> 124526 | R60: =IFERROR((Q60/N60)^(1/COUNT($G$4:$Q$4))-1,"") -> 0.084928756
B61: Shareholder's Equity | G61: =G48-G60 -> 0 | H61: =H48-H60 -> 0 | I61: =I48-I60 -> 0 | J61: =J48-J60 -> 0 | K61: =K48-K60 -> 0 | L61: =L48-L60 -> 0 | M61: =M48-M60 -> 53703 | N61: =N48-N60 -> 591230 | ... Q61: =Q48-Q60 -> 383862 | R61: =IFERROR((Q61/N61)^(1/COUNT($G$4:$Q$4))-1,"") -> -0.038504733
B62: Non-Controlling Interest | M62: 0 | N62: 0 | O62: 0 | P62: 0 | Q62: 0
A64: x | B64: Cash Flow | G64: 2014 | H64: =+G64+1 -> 2015 | I64: =+H64+1 -> 2016 | J64: =+I64+1 -> 2017 | K64: =+J64+1 -> 2018 | L64: =+K64+1 -> 2019 | M64: =+L64+1 -> 2020 | N64: =+M64+1 -> 2021 | O64: =+N64+1 -> 2022 | ... Q64: =+P64+1 -> 2024 | R64: ="CAGR "&$N$4&" - "&$Q$4 -> CAGR 2021 - 2024
B66: Net Income | G66: =G24 -> 0 | H66: =H24 -> 0 | I66: =I24 -> 0 | J66: =J24 -> 0 | K66: =K24 -> 0 | L66: =L24 -> 0 | M66: -15424 | N66: =N24 -> -106186 | O66: =O24 -> -48511 | P66: =P24 -> -157723.05 | Q66: =Q24 -> -331588.06 | R66: =IFERROR((Q66/N66)^(1/COUNT($G$4:$Q$4))-1,"") -> 0.10906607
B67: D&A (Depreciation and Amortization) | G67: =+G13 -> 0 | H67: =+H13 -> 0 | I67: =+I13 -> 0 | J67: =+J13 -> 0 | K67: =+K13 -> 0 | L67: =+L13 -> 0 | M67: 1400 | N67: =+N13 -> 2548 | O67: =+O13 -> 5604 | P67: =+P13 -> 10375 | Q67: =+Q13 -> 18654 | R67: =IFERROR((Q67/N67)^(1/COUNT($G$4:$Q$4))-1,"") -> 0.19838815
B68: Changes in Net Working Capital | G68: =+SUM(G69:G72) -> 0 | H68: =+SUM(H69:H72) -> 0 | I68: =+SUM(I69:I72) -> 0 | J68: =+SUM(J69:J72) -> 0 | K68: =+SUM(K69:K72) -> 0 | L68: =+SUM(L69:L72) -> 0 | M68: =+SUM(M69:M72) -> 743 | N68: =+SUM(N69:N72) -> 757 | ... Q68: =+SUM(Q69:Q72) -> -15754 | R68: =IFERROR((Q68/N68)^(1/COUNT($G$4:$Q$4))-1,"") -> -2.3177863
B69: (Increase) Decrease in Accounts Receivable | M69: -290 | N69: -317 | O69: -1510 | P69: -8175 | Q69: 1609 | R69: =IFERROR((Q69/N69)^(1/COUNT($G$4:$Q$4))-1,"") -> -2.1591405
B70: (Increase) Decrease in Inventories | M70: 0 | N70: 0 | O70: 0 | P70: 0 | Q70: 0 | R70: =IFERROR((Q70/N70)^(1/COUNT($G$4:$Q$4))-1,"")
B71: Increase (Decrease) in Inventories | M71: 0 | N71: 0 | O71: 0 | P71: 0 | Q71: 0 | R71: =IFERROR((Q71/N71)^(1/COUNT($G$4:$Q$4))-1,"")
B72: Increase (Decrease) in Other | M72: 1033 | N72: 1074 | O72: -1776 | P72: -8490 | Q72: -17363 | R72: =IFERROR((Q72/N72)^(1/COUNT($G$4:$Q$4))-1,"") -> -2.2878776
B73: Stock Based Compensation | M73: 1224 | N73: 7748 | O73: 31456 | P73: 69743 | Q73: 106878 | R73: =IFERROR((Q73/N73)^(1/COUNT($G$4:$Q$4))-1,"") -> 0.26943063
B74: Other Operating Adjustments | G74: =+G75-G66-G67-G68-G73 -> 0 | H74: =+H75-H66-H67-H68-H73 -> 0 | I74: =+I75-I66-I67-I68-I73 -> 0 | J74: =+J75-J66-J67-J68-J73 -> 0 | K74: =+K75-K66-K67-K68-K73 -> 0 | L74: =+L75-L66-L67-L68-L73 -> 0 | M74: =+M75-M66-M67-M68-M73 -> 50 | N74: =+N75-N66-N67-N68-N73 -> 68596 | ... Q74: =+Q75-Q66-Q67-Q68-Q73 -> 116127.06 | R74: =IFERROR((Q74/N74)^(1/COUNT($G$4:$Q$4))-1,"") -> 0.049022895
B75: Operating Cash Flow | M75: -12007 | N75: -26537 | O75: -44698 | P75: -78811 | Q75: -105683 | R75: =IFERROR((Q75/N75)^(1/COUNT($G$4:$Q$4))-1,"") -> 0.13385989
B76: Net Capex | G76: =+SUM(G77:G78) -> 0 | H76: =+SUM(H77:H78) -> 0 | I76: =+SUM(I77:I78) -> 0 | J76: =+SUM(J77:J78) -> 0 | K76: =+SUM(K77:K78) -> 0 | L76: =+SUM(L77:L78) -> 0 | M76: =+SUM(M77:M78) -> -11676 | N76: =+SUM(N77:N78) -> -10024 | ... Q76: =+SUM(Q77:Q78) -> -23569 | R76: =IFERROR((Q76/N76)^(1/COUNT($G$4:$Q$4))-1,"") -> 0.080822941
B77: Acquisition of Fixed & Intangibles | M77: -11676 | N77: -10024 | O77: -12564 | P77: -19549 | Q77: -23569 | R77: =IFERROR((Q77/N77)^(1/COUNT($G$4:$Q$4))-1,"") -> 0.080822941
B78: Disposal of Fixed & Intangibles | M78: 0 | N78: 0 | O78: 0 | P78: 0 | Q78: 0 | R78: =IFERROR((Q78/N78)^(1/COUNT($G$4:$Q$4))-1,"")
B79: Net Cash from Investments & Acquisitions | G79: =+SUM(G80:G83) -> 0 | H79: =+SUM(H80:H83) -> 0 | I79: =+SUM(I80:I83) -> 0 | J79: =+SUM(J80:J83) -> 0 | K79: =+SUM(K80:K83) -> 0 | L79: =+SUM(L80:L83) -> 0 | M79: =+SUM(M80:M83) -> 0 | N79: =+SUM(N80:N83) -> 0 | ... Q79: =+SUM(Q80:Q83) -> -15454 | R79: =IFERROR((Q79/O79)^(1/COUNT($G$4:$Q$4))-1,"") -> -1.7615696
B80: Acquisitions | M80: 0 | N80: 0 | O80: -848 | P80: 0 | Q80: -15454 | R80: =IFERROR((Q80/N80)^(1/COUNT($G$4:$Q$4))-1,"")
B81: Divestitures | M81: 0 | N81: 0 | O81: 0 | P81: 0 | Q81: 0 | R81: =IFERROR((Q81/N81)^(1/COUNT($G$4:$Q$4))-1,"")
B82: Increase in LT Investment | M82: 0 | N82: 0 | O82: 0 | P82: 0 | Q82: 0 | R82: =IFERROR((Q82/N82)^(1/COUNT($G$4:$Q$4))-1,"")
B83: Decrease in LT Investment | M83: 0 | N83: 0 | O83: 310045 | P83: 386760 | Q83: 0 | R83: =IFERROR((Q83/N83)^(1/COUNT($G$4:$Q$4))-1,"")
B84: Other Investing Inflows (Outflows) | G84: =+G85-G76-G79 -> 0 | H84: =+H85-H76-H79 -> 0 | I84: =+I85-I76-I79 -> 0 | J84: =+J85-J76-J79 -> 0 | K84: =+K85-K76-K79 -> 0 | L84: =+L85-L76-L79 -> 0 | M84: =+M85-M76-M79 -> 0 | N84: =+N85-N76-N79 -> -203761 | ... Q84: =+Q85-Q76-Q79 -> 121753 | R84: =IFERROR((Q84/N84)^(1/COUNT($G$4:$Q$4))-1,"") -> -1.9542649
B85: Investing Cash Flow | M85: -11676 | N85: -213785 | O85: -309056 | P85: 68766 | Q85: 82730 | R85: =IFERROR((Q85/N85)^(1/COUNT($G$4:$Q$4))-1,"") -> -1.9173116
B86: Debt Borrowing | M86: 0 | N86: 0 | O86: 0 | P86: 0 | Q86: 0 | R86: =IFERROR((Q86/G86)^(1/COUNT($G$4:$Q$4))-1,"")
B87: Debt Repayment | M87: 0 | N87: 0 | O87: 0 | P87: 0 | Q87: 0 | R87: =IFERROR((Q87/G87)^(1/COUNT($G$4:$Q$4))-1,"")
B88: Lease Payments | M88: 0 | N88: 0 | O88: 0 | P88: 0 | Q88: 0 | R88: =IFERROR((Q88/G88)^(1/COUNT($G$4:$Q$4))-1,"")
B89: Dividends | M89: 0 | N89: 0 | O89: 0 | P89: 0 | Q89: 0 | R89: =IFERROR((Q89/G89)^(1/COUNT($G$4:$Q$4))-1,"")
B90: Increase (Repurchase) of Shares | M90: 276 | N90: 4489 | O90: -905 | P90: 1954 | Q90: 41449 | R90: =IFERROR((Q90/N90)^(1/COUNT($G$4:$Q$4))-1,"") -> 0.22394078
B91: Other Financing Inflows (Outflows) | G91: =+G92-G86-G87-G88-G89-G90 -> 0 | H91: =+H92-H86-H87-H88-H89-H90 -> 0 | I91: =+I92-I86-I87-I88-I89-I90 -> 0 | J91: =+J92-J86-J87-J88-J89-J90 -> 0 | K91: =+K92-K86-K87-K88-K89-K90 -> 0 | L91: =+L92-L86-L87-L88-L89-L90 -> 0 | M91: =+M92-M86-M87-M88-M89-M90 -> 0 | N91: =+N92-N86-N87-N88-N89-N90 -> 598738 | ... Q91: =+Q92-Q86-Q87-Q88-Q89-Q90 -> 238 | R91: =IFERROR((Q91/N91)^(1/COUNT($G$4:$Q$4))-1,"") -> -0.50926266
B92: Financing Cash Flow | M92: 276 | N92: 603227 | O92: 1096 | P92: 1761 | Q92: 41687 | R92: =IFERROR((Q92/N92)^(1/COUNT($G$4:$Q$4))-1,"") -> -0.21566462
B93: Effect of Foreign Exchange | M93: 0 | N93: 0 | O93: 0 | P93: -2 | Q93: 25 | R93: =IFERROR((Q93/N93)^(1/COUNT($G$4:$Q$4))-1,"")
B94: Net Changes in Cash | M94: -23407 | N94: 362905 | O94: -352658 | P94: -8286 | Q94: 18759 | R94: =IFERROR((Q94/N94)^(1/COUNT($G$4:$Q$4))-1,"") -> -0.23609758
B95: in billionsof USD
A96: x | B96: Capital Structure | G96: 42004 | H96: 42369 | I96: 42735 | J96: 43100 | K96: 43465 | L96: 43830 | M96: 44196 | N96: 44561 | O96: 44926 | P96: 45291 | Q96: 45657
B98: Market Capitalization | G98: {=(IFERROR(_xlfn.STOCKHISTORY(DCF!$AA$4, G96, G96, 0, 0, 1), IFERROR(_xlfn.STOCKHISTORY(DCF!$AA$4, G96+1, G96+1, 0, 0, 1), _xlfn.STOCKHISTORY(DCF!$AA$4, G96-2, G96-2, 0, 0, 1))))*_xlfn.XLOOKUP("Basic Weighted Average Shares",$B:$B,G:G)} -> #VALUE! | H98: {=(IFERROR(_xlfn.STOCKHISTORY(DCF!$AA$4, H96, H96, 0, 0, 1), IFERROR(_xlfn.STOCKHISTORY(DCF!$AA$4, H96+1, H96+1, 0, 0, 1), _xlfn.STOCKHISTORY(DCF!$AA$4, H96-2, H96-2, 0, 0, 1))))*_xlfn.XLOOKUP("Basic Weighted Average Shares",$B:$B,H:H)} -> #VALUE! | I98: {=(IFERROR(_xlfn.STOCKHISTORY(DCF!$AA$4, I96, I96, 0, 0, 1), IFERROR(_xlfn.STOCKHISTORY(DCF!$AA$4, I96+1, I96+1, 0, 0, 1), _xlfn.STOCKHISTORY(DCF!$AA$4, I96-2, I96-2, 0, 0, 1))))*_xlfn.XLOOKUP("Basic Weighted Average Shares",$B:$B,I:I)} -> #VALUE! | J98: {=(IFERROR(_xlfn.STOCKHISTORY(DCF!$AA$4, J96, J96, 0, 0, 1), IFERROR(_xlfn.STOCKHISTORY(DCF!$AA$4, J96+1, J96+1, 0, 0, 1), _xlfn.STOCKHISTORY(DCF!$AA$4, J96-2, J96-2, 0, 0, 1))))*_xlfn.XLOOKUP("Basic Weighted Average Shares",$B:$B,J:J)} -> #VALUE! | K98: {=(IFERROR(_xlfn.STOCKHISTORY(DCF!$AA$4, K96, K96, 0, 0, 1), IFERROR(_xlfn.STOCKHISTORY(DCF!$AA$4, K96+1, K96+1, 0, 0, 1), _xlfn.STOCKHISTORY(DCF!$AA$4, K96-2, K96-2, 0, 0, 1))))*_xlfn.XLOOKUP("Basic Weighted Average Shares",$B:$B,K:K)} -> #VALUE! | L98: {=(IFERROR(_xlfn.STOCKHISTORY(DCF!$AA$4, L96, L96, 0, 0, 1), IFERROR(_xlfn.STOCKHISTORY(DCF!$AA$4, L96+1, L96+1, 0, 0, 1), _xlfn.STOCKHISTORY(DCF!$AA$4, L96-2, L96-2, 0, 0, 1))))*_xlfn.XLOOKUP("Basic Weighted Average Shares",$B:$B,L:L)} -> #VALUE! | M98: {=(IFERROR(_xlfn.STOCKHISTORY(DCF!$AA$4, M96, M96, 0, 0, 1), IFERROR(_xlfn.STOCKHISTORY(DCF!$AA$4, M96+1, M96+1, 0, 0, 1), _xlfn.STOCKHISTORY(DCF!$AA$4, M96-2, M96-2, 0, 0, 1))))*_xlfn.XLOOKUP("Basic Weighted Average Shares",$B:$B,M:M)} -> #VALUE! | N98: {=(IFERROR(_xlfn.STOCKHISTORY(DCF!$AA$4, N96, N96, 0, 0, 1), IFERROR(_xlfn.STOCKHISTORY(DCF!$AA$4, N96+1, N96+1, 0, 0, 1), _xlfn.STOCKHISTORY(DCF!$AA$4, N96-2, N96-2, 0, 0, 1))))*_xlfn.XLOOKUP("Basic Weighted Average Shares",$B:$B,N:N)} -> 2298080.3 | O98: {=(IFERROR(_xlfn.STOCKHISTORY(DCF!$AA$4, O96, O96, 0, 0, 1), IFERROR(_xlfn.STOCKHISTORY(DCF!$AA$4, O96+1, O96+1, 0, 0, 1), _xlfn.STOCKHISTORY(DCF!$AA$4, O96-2, O96-2, 0, 0, 1))))*_xlfn.XLOOKUP("Basic Weighted Average Shares",$B:$B,O:O)} -> 699955.7 | P98: {=(IFERROR(_xlfn.STOCKHISTORY(DCF!$AA$4, P96, P96, 0, 0, 1), IFERROR(_xlfn.STOCKHISTORY(DCF!$AA$4, P96+1, P96+1, 0, 0, 1), _xlfn.STOCKHISTORY(DCF!$AA$4, P96-2, P96-2, 0, 0, 1))))*_xlfn.XLOOKUP("Basic Weighted Average Shares",$B:$B,P:P)} -> 2509922.8 | Q98: {=(IFERROR(_xlfn.STOCKHISTORY(DCF!$AA$4, Q96, Q96, 0, 0, 1), IFERROR(_xlfn.STOCKHISTORY(DCF!$AA$4, Q96+1, Q96+1, 0, 0, 1), _xlfn.STOCKHISTORY(DCF!$AA$4, Q96-2, Q96-2, 0, 0, 1))))*_xlfn.XLOOKUP("Basic Weighted Average Shares",$B:$B,Q:Q)} -> 8898238
B99: Cash & Cash Equivalents | G99: =_xlfn.XLOOKUP("Cash & Cash Equivalents & ST Investments",$B$30:$B$62,G$30:G$62) -> 0 | H99: =_xlfn.XLOOKUP("Cash & Cash Equivalents & ST Investments",$B$30:$B$62,H$30:H$62) -> 0 | I99: =_xlfn.XLOOKUP("Cash & Cash Equivalents & ST Investments",$B$30:$B$62,I$30:I$62) -> 0 | J99: =_xlfn.XLOOKUP("Cash & Cash Equivalents & ST Investments",$B$30:$B$62,J$30:J$62) -> 0 | K99: =_xlfn.XLOOKUP("Cash & Cash Equivalents & ST Investments",$B$30:$B$62,K$30:K$62) -> 0 | L99: =_xlfn.XLOOKUP("Cash & Cash Equivalents & ST Investments",$B$30:$B$62,L$30:L$62) -> 0 | M99: =_xlfn.XLOOKUP("Cash & Cash Equivalents & ST Investments",$B$30:$B$62,M$30:M$62) -> 36120 | N99: =_xlfn.XLOOKUP("Cash & Cash Equivalents & ST Investments",$B$30:$B$62,N$30:N$62) -> 522468 | ... Q99: =_xlfn.XLOOKUP("Cash & Cash Equivalents & ST Investments",$B$30:$B$62,Q$30:Q$62) -> 340289
B100: Total Debt | G100: =(_xlfn.XLOOKUP("Short-Term Debt",$B$30:$B$62,G$30:G$62)+_xlfn.XLOOKUP("Long-Term Debt",$B$30:$B$62,G$30:G$62)) -> 0 | H100: =(_xlfn.XLOOKUP("Short-Term Debt",$B$30:$B$62,H$30:H$62)+_xlfn.XLOOKUP("Long-Term Debt",$B$30:$B$62,H$30:H$62)) -> 0 | I100: =(_xlfn.XLOOKUP("Short-Term Debt",$B$30:$B$62,I$30:I$62)+_xlfn.XLOOKUP("Long-Term Debt",$B$30:$B$62,I$30:I$62)) -> 0 | J100: =(_xlfn.XLOOKUP("Short-Term Debt",$B$30:$B$62,J$30:J$62)+_xlfn.XLOOKUP("Long-Term Debt",$B$30:$B$62,J$30:J$62)) -> 0 | K100: =(_xlfn.XLOOKUP("Short-Term Debt",$B$30:$B$62,K$30:K$62)+_xlfn.XLOOKUP("Long-Term Debt",$B$30:$B$62,K$30:K$62)) -> 0 | L100: =(_xlfn.XLOOKUP("Short-Term Debt",$B$30:$B$62,L$30:L$62)+_xlfn.XLOOKUP("Long-Term Debt",$B$30:$B$62,L$30:L$62)) -> 0 | M100: =(_xlfn.XLOOKUP("Short-Term Debt",$B$30:$B$62,M$30:M$62)+_xlfn.XLOOKUP("Long-Term Debt",$B$30:$B$62,M$30:M$62)) -> 4271 | N100: =(_xlfn.XLOOKUP("Short-Term Debt",$B$30:$B$62,N$30:N$62)+_xlfn.XLOOKUP("Long-Term Debt",$B$30:$B$62,N$30:N$62)) -> 4211 | ... Q100: =(_xlfn.XLOOKUP("Short-Term Debt",$B$30:$B$62,Q$30:Q$62)+_xlfn.XLOOKUP("Long-Term Debt",$B$30:$B$62,Q$30:Q$62)) -> 17725
B101: Preferred Stock
B102: Non-Controlling Interest | G102: =_xlfn.XLOOKUP("Non-Controlling Interest",$B$30:$B$62,G$30:G$62) -> 0 | H102: =_xlfn.XLOOKUP("Non-Controlling Interest",$B$30:$B$62,H$30:H$62) -> 0 | I102: =_xlfn.XLOOKUP("Non-Controlling Interest",$B$30:$B$62,I$30:I$62) -> 0 | J102: =_xlfn.XLOOKUP("Non-Controlling Interest",$B$30:$B$62,J$30:J$62) -> 0 | K102: =_xlfn.XLOOKUP("Non-Controlling Interest",$B$30:$B$62,K$30:K$62) -> 0 | L102: =_xlfn.XLOOKUP("Non-Controlling Interest",$B$30:$B$62,L$30:L$62) -> 0 | M102: =_xlfn.XLOOKUP("Non-Controlling Interest",$B$30:$B$62,M$30:M$62) -> 0 | N102: =_xlfn.XLOOKUP("Non-Controlling Interest",$B$30:$B$62,N$30:N$62) -> 0 | ... Q102: =_xlfn.XLOOKUP("Non-Controlling Interest",$B$30:$B$62,Q$30:Q$62) -> 0
B103: Enterprise Value | G103: =+G98-G99+G100+G101+G102 -> #VALUE! | H103: =+H98-H99+H100+H101+H102 -> #VALUE! | I103: =+I98-I99+I100+I101+I102 -> #VALUE! | J103: =+J98-J99+J100+J101+J102 -> #VALUE! | K103: =+K98-K99+K100+K101+K102 -> #VALUE! | L103: =+L98-L99+L100+L101+L102 -> #VALUE! | M103: =+M98-M99+M100+M101+M102 -> #VALUE! | N103: =+N98-N99+N100+N101+N102 -> 1779823.3 | ... Q103: =+Q98-Q99+Q100+Q101+Q102 -> 8575674
A105: x | B105: Debt Schedule | G105: Cash | H105: 2025 | I105: =+H105+1 -> 2026 | J105: =+I105+1 -> 2027 | K105: =+J105+1 -> 2028 | L105: =+K105+1 -> 2029 | M105: =+L105+1 -> 2030 | N105: =+M105+1 -> 2031 | O105: =+N105+1 -> 2032 | P105: =+O105+1 -> 2033 | Q105: =+P105+1 -> 2034
B107: Fixed | H107: 0 | I107: 0 | J107: 0 | K107: 0 | L107: 0 | M107: 0 | N107: 0 | O107: 0 | P107: 0 | Q107: 0
B108: Floating | H108: 0 | I108: 0 | J108: 0 | K108: 0 | L108: 0 | M108: 0 | N108: 0 | O108: 0 | P108: 0 | Q108: 0
A110: x | B110: Additional | G110: 2014 | H110: =+G110+1 -> 2015 | I110: =+H110+1 -> 2016 | J110: =+I110+1 -> 2017 | K110: =+J110+1 -> 2018 | L110: =+K110+1 -> 2019 | M110: =+L110+1 -> 2020 | N110: =+M110+1 -> 2021 | O110: =+N110+1 -> 2022 | ... Q110: =+P110+1 -> 2024 | R110: ="CAGR "&$N$4&" - "&$Q$4 -> CAGR 2021 - 2024
...

Sheet WACC
B2: WACC
B4: WACC = % of Equity x Cost of Equity + % de Debt x Cost of Debt x (1 - Tax Rate)
B5: Cost of Equity = Risk-Free Rate + Beta x Equity Risk Premium
B7: WACC | I7: Region | J7: Weight | K7: ERP | M7: Peers | N7: Beta (Unlevered)
B9: Market Cap (in millions) | G9: {=+_FV(DCF!AA4,"Market cap",TRUE)/1000000} -> 16374.913 | I9: U.S. | J9: 0.945 | K9: 0.0433 | M9: =+Peers!B8 -> RIGETTI COMPUTING, INC | N9: =+Peers!E75 -> 1.343785
B10: % of Equity | G10: =IFERROR(G9/G23,"") -> 0.48020396 | I10: Internacional | J10: 0.055 | M10: =+Peers!B9 -> D-WAVE QUANTUM INC. | N10: =+Peers!F75 -> 0.85545031
B11: Cost of Equity | G11: =IFERROR(G12+G14*G15,"") -> 0.14539625 | M11: =+Peers!B10 -> QUANTUM COMPUTING INC. | N11: =+Peers!G75 -> 3.8163897
B12: Risk-Free Rate | G12: 0.0431 | M12: =+Peers!B11 | N12: =+Peers!H75 -> 0
B13: Unlevered Beta | G13: =+N19 -> 2.0052084 | M13: =+Peers!B12 | N13: =+Peers!I75 -> 0
B14: Beta | G14: 2.5 | I14: Others | J14: =1-SUM(J9:J13) -> 0 | K14: =MAX(K9:K13) -> 0.0433 | M14: =+Peers!B13 | N14: =+Peers!J75 -> 0
B15: Equity Risk Premium | G15: =SUMPRODUCT(J9:J14,K9:K14) -> 0.0409185 | M15: =+Peers!B14 | N15: =+Peers!K75
B16: Unlevered Cost of Equity | G16: =IFERROR(+G12+G13*G15,"") -> 0.12515012 | M16: =+Peers!B15 | N16: =+Peers!L75
M17: =+Peers!B16 | N17: =+Peers!M75
B18: Debt (in millions) | G18: 17725 | M18: =+Peers!B17 | N18: =+Peers!N75
B19: % of Debt | G19: =IFERROR(G18/G23,"") -> 0.51979604 | M19: Average | N19: =IFERROR(+AVERAGEIF(N9:N18,">0"),"") -> 2.0052084
B20: Cost of debt | G20: 0.1454
B21: Tax Rate | G21: =+DCF!H80 -> 0.21
B23: Total | G23: =+G9+G18 -> 34099.913
B25: WACC | G25: =IFERROR(G10*G11+G19*G20*(1-G21),"") -> 0.12952675

Sheet Multiples
B2: Multiples
B4: Valuation | F4: 2014 | G4: =+F4+1 -> 2015 | H4: =+G4+1 -> 2016 | I4: =+H4+1 -> 2017 | J4: =+I4+1 -> 2018 | K4: =+J4+1 -> 2019 | L4: =+K4+1 -> 2020 | M4: =+L4+1 -> 2021 | N4: 2022 | O4: =+N4+1 -> 2023 | P4: =+O4+1 -> 2024 | Q4: =+P4+1 -> 2025 | R4: =+Q4+1 -> 2026
B6: EV / Sales | F6: =IFERROR(_xlfn.XLOOKUP("Enterprise Value",Inputs!$B:$B,Inputs!G:G)/_xlfn.XLOOKUP("Revenue (Sales)",Inputs!$B:$B,Inputs!G:G),"") | G6: =IFERROR(_xlfn.XLOOKUP("Enterprise Value",Inputs!$B:$B,Inputs!H:H)/_xlfn.XLOOKUP("Revenue (Sales)",Inputs!$B:$B,Inputs!H:H),"") | H6: =IFERROR(_xlfn.XLOOKUP("Enterprise Value",Inputs!$B:$B,Inputs!I:I)/_xlfn.XLOOKUP("Revenue (Sales)",Inputs!$B:$B,Inputs!I:I),"") | I6: =IFERROR(_xlfn.XLOOKUP("Enterprise Value",Inputs!$B:$B,Inputs!J:J)/_xlfn.XLOOKUP("Revenue (Sales)",Inputs!$B:$B,Inputs!J:J),"") | J6: =IFERROR(_xlfn.XLOOKUP("Enterprise Value",Inputs!$B:$B,Inputs!K:K)/_xlfn.XLOOKUP("Revenue (Sales)",Inputs!$B:$B,Inputs!K:K),"") | K6: =IFERROR(_xlfn.XLOOKUP("Enterprise Value",Inputs!$B:$B,Inputs!L:L)/_xlfn.XLOOKUP("Revenue (Sales)",Inputs!$B:$B,Inputs!L:L),"") | L6: =IFERROR(_xlfn.XLOOKUP("Enterprise Value",Inputs!$B:$B,Inputs!M:M)/_xlfn.XLOOKUP("Revenue (Sales)",Inputs!$B:$B,Inputs!M:M),"") | M6: =IFERROR(_xlfn.XLOOKUP("Enterprise Value",Inputs!$B:$B,Inputs!N:N)/_xlfn.XLOOKUP("Revenue (Sales)",Inputs!$B:$B,Inputs!N:N),"") -> 847.93869 | N6: =IFERROR(_xlfn.XLOOKUP("Enterprise Value",Inputs!$B:$B,Inputs!O:O)/_xlfn.XLOOKUP("Revenue (Sales)",Inputs!$B:$B,Inputs!O:O),"") -> 31.282787 | O6: =IFERROR(_xlfn.XLOOKUP("Enterprise Value",Inputs!$B:$B,Inputs!P:P)/_xlfn.XLOOKUP("Revenue (Sales)",Inputs!$B:$B,Inputs!P:P),"") -> 98.112097 | P6: =IFERROR(_xlfn.XLOOKUP("Enterprise Value",Inputs!$B:$B,Inputs!Q:Q)/_xlfn.XLOOKUP("Revenue (Sales)",Inputs!$B:$B,Inputs!Q:Q),"") -> 199.09628 | Q6: =IFERROR(_xlfn.XLOOKUP("Enterprise Value",DCF!$B:$B,DCF!AA:AA)/_xlfn.XLOOKUP("Revenue (Sales)",DCF!$B:$B,DCF!H:H),"") -> -27.061042 | R6: =IFERROR(_xlfn.XLOOKUP("Enterprise Value",DCF!$B:$B,DCF!AB:AB)/_xlfn.XLOOKUP("Revenue (Sales)",DCF!$B:$B,DCF!I:I),"") -> -17.209963
B7: Price / Sales | F7: =IFERROR(_xlfn.XLOOKUP("Market Capitalization",Inputs!$B:$B,Inputs!G:G)/_xlfn.XLOOKUP("Revenue (Sales)",Inputs!$B:$B,Inputs!G:G),"") | G7: =IFERROR(_xlfn.XLOOKUP("Market Capitalization",Inputs!$B:$B,Inputs!H:H)/_xlfn.XLOOKUP("Revenue (Sales)",Inputs!$B:$B,Inputs!H:H),"") | H7: =IFERROR(_xlfn.XLOOKUP("Market Capitalization",Inputs!$B:$B,Inputs!I:I)/_xlfn.XLOOKUP("Revenue (Sales)",Inputs!$B:$B,Inputs!I:I),"") | I7: =IFERROR(_xlfn.XLOOKUP("Market Capitalization",Inputs!$B:$B,Inputs!J:J)/_xlfn.XLOOKUP("Revenue (Sales)",Inputs!$B:$B,Inputs!J:J),"") | J7: =IFERROR(_xlfn.XLOOKUP("Market Capitalization",Inputs!$B:$B,Inputs!K:K)/_xlfn.XLOOKUP("Revenue (Sales)",Inputs!$B:$B,Inputs!K:K),"") | K7: =IFERROR(_xlfn.XLOOKUP("Market Capitalization",Inputs!$B:$B,Inputs!L:L)/_xlfn.XLOOKUP("Revenue (Sales)",Inputs!$B:$B,Inputs!L:L),"") | L7: =IFERROR(_xlfn.XLOOKUP("Market Capitalization",Inputs!$B:$B,Inputs!M:M)/_xlfn.XLOOKUP("Revenue (Sales)",Inputs!$B:$B,Inputs!M:M),"") | M7: =IFERROR(_xlfn.XLOOKUP("Market Capitalization",Inputs!$B:$B,Inputs!N:N)/_xlfn.XLOOKUP("Revenue (Sales)",Inputs!$B:$B,Inputs!N:N),"") -> 1094.8453 | N7: =IFERROR(_xlfn.XLOOKUP("Market Capitalization",Inputs!$B:$B,Inputs!O:O)/_xlfn.XLOOKUP("Revenue (Sales)",Inputs!$B:$B,Inputs!O:O),"") -> 62.883452 | O7: =IFERROR(_xlfn.XLOOKUP("Market Capitalization",Inputs!$B:$B,Inputs!P:P)/_xlfn.XLOOKUP("Revenue (Sales)",Inputs!$B:$B,Inputs!P:P),"") -> 113.87001 | P7: =IFERROR(_xlfn.XLOOKUP("Market Capitalization",Inputs!$B:$B,Inputs!Q:Q)/_xlfn.XLOOKUP("Revenue (Sales)",Inputs!$B:$B,Inputs!Q:Q),"") -> 206.58505 | Q7: =IFERROR(_xlfn.XLOOKUP("Equity Value",DCF!$B:$B,DCF!AA:AA)/_xlfn.XLOOKUP("Revenue (Sales)",DCF!$B:$B,DCF!H:H),"") -> -29.825629 | R7: =IFERROR(_xlfn.XLOOKUP("Equity Value",DCF!$B:$B,DCF!AB:AB)/_xlfn.XLOOKUP("Revenue (Sales)",DCF!$B:$B,DCF!I:I),"") -> -23.550357
B8: EV / EBITDA | F8: =IFERROR(_xlfn.XLOOKUP("Enterprise Value",Inputs!$B:$B,Inputs!G:G)/_xlfn.XLOOKUP("EBITDA",Inputs!$B:$B,Inputs!G:G),"") | G8: =IFERROR(_xlfn.XLOOKUP("Enterprise Value",Inputs!$B:$B,Inputs!H:H)/_xlfn.XLOOKUP("EBITDA",Inputs!$B:$B,Inputs!H:H),"") | H8: =IFERROR(_xlfn.XLOOKUP("Enterprise Value",Inputs!$B:$B,Inputs!I:I)/_xlfn.XLOOKUP("EBITDA",Inputs!$B:$B,Inputs!I:I),"") | I8: =IFERROR(_xlfn.XLOOKUP("Enterprise Value",Inputs!$B:$B,Inputs!J:J)/_xlfn.XLOOKUP("EBITDA",Inputs!$B:$B,Inputs!J:J),"") | J8: =IFERROR(_xlfn.XLOOKUP("Enterprise Value",Inputs!$B:$B,Inputs!K:K)/_xlfn.XLOOKUP("EBITDA",Inputs!$B:$B,Inputs!K:K),"") | K8: =IFERROR(_xlfn.XLOOKUP("Enterprise Value",Inputs!$B:$B,Inputs!L:L)/_xlfn.XLOOKUP("EBITDA",Inputs!$B:$B,Inputs!L:L),"") | L8: =IFERROR(_xlfn.XLOOKUP("Enterprise Value",Inputs!$B:$B,Inputs!M:M)/_xlfn.XLOOKUP("EBITDA",Inputs!$B:$B,Inputs!M:M),"") | M8: =IFERROR(_xlfn.XLOOKUP("Enterprise Value",Inputs!$B:$B,Inputs!N:N)/_xlfn.XLOOKUP("EBITDA",Inputs!$B:$B,Inputs!N:N),"") -> -49.249379 | N8: =IFERROR(_xlfn.XLOOKUP("Enterprise Value",Inputs!$B:$B,Inputs!O:O)/_xlfn.XLOOKUP("EBITDA",Inputs!$B:$B,Inputs!O:O),"") -> -4.3448966 | O8: =IFERROR(_xlfn.XLOOKUP("Enterprise Value",Inputs!$B:$B,Inputs!P:P)/_xlfn.XLOOKUP("EBITDA",Inputs!$B:$B,Inputs!P:P),"") -> -14.673643 | P8: =IFERROR(_xlfn.XLOOKUP("Enterprise Value",Inputs!$B:$B,Inputs!Q:Q)/_xlfn.XLOOKUP("EBITDA",Inputs!$B:$B,Inputs!Q:Q),"") -> -40.110542 | Q8: =IFERROR(_xlfn.XLOOKUP("Enterprise Value",DCF!$B:$B,DCF!AA:AA)/_xlfn.XLOOKUP("EBITDA",DCF!$B:$B,DCF!H:H),"") -> 7.1044773 | R8: =IFERROR(_xlfn.XLOOKUP("Enterprise Value",DCF!$B:$B,DCF!AB:AB)/_xlfn.XLOOKUP("EBITDA",DCF!$B:$B,DCF!I:I),"") -> 5.984625
B9: EV / EBIT | F9: =IFERROR(_xlfn.XLOOKUP("Enterprise Value",Inputs!$B:$B,Inputs!G:G)/_xlfn.XLOOKUP("Operating Income (EBIT)",Inputs!$B:$B,Inputs!G:G),"") | G9: =IFERROR(_xlfn.XLOOKUP("Enterprise Value",Inputs!$B:$B,Inputs!H:H)/_xlfn.XLOOKUP("Operating Income (EBIT)",Inputs!$B:$B,Inputs!H:H),"") | H9: =IFERROR(_xlfn.XLOOKUP("Enterprise Value",Inputs!$B:$B,Inputs!I:I)/_xlfn.XLOOKUP("Operating Income (EBIT)",Inputs!$B:$B,Inputs!I:I),"") | I9: =IFERROR(_xlfn.XLOOKUP("Enterprise Value",Inputs!$B:$B,Inputs!J:J)/_xlfn.XLOOKUP("Operating Income (EBIT)",Inputs!$B:$B,Inputs!J:J),"") | J9: =IFERROR(_xlfn.XLOOKUP("Enterprise Value",Inputs!$B:$B,Inputs!K:K)/_xlfn.XLOOKUP("Operating Income (EBIT)",Inputs!$B:$B,Inputs!K:K),"") | K9: =IFERROR(_xlfn.XLOOKUP("Enterprise Value",Inputs!$B:$B,Inputs!L:L)/_xlfn.XLOOKUP("Operating Income (EBIT)",Inputs!$B:$B,Inputs!L:L),"") | L9: =IFERROR(_xlfn.XLOOKUP("Enterprise Value",Inputs!$B:$B,Inputs!M:M)/_xlfn.XLOOKUP("Operating Income (EBIT)",Inputs!$B:$B,Inputs!M:M),"") | M9: =IFERROR(_xlfn.XLOOKUP("Enterprise Value",Inputs!$B:$B,Inputs!N:N)/_xlfn.XLOOKUP("Operating Income (EBIT)",Inputs!$B:$B,Inputs!N:N),"") -> -46.005721 | N9: =IFERROR(_xlfn.XLOOKUP("Enterprise Value",Inputs!$B:$B,Inputs!O:O)/_xlfn.XLOOKUP("Operating Income (EBIT)",Inputs!$B:$B,Inputs!O:O),"") -> -4.0609323 | O9: =IFERROR(_xlfn.XLOOKUP("Enterprise Value",Inputs!$B:$B,Inputs!P:P)/_xlfn.XLOOKUP("Operating Income (EBIT)",Inputs!$B:$B,Inputs!P:P),"") -> -13.708602 | P9: =IFERROR(_xlfn.XLOOKUP("Enterprise Value",Inputs!$B:$B,Inputs!Q:Q)/_xlfn.XLOOKUP("Operating Income (EBIT)",Inputs!$B:$B,Inputs!Q:Q),"") -> -36.89176 | Q9: =IFERROR(_xlfn.XLOOKUP("Enterprise Value",DCF!$B:$B,DCF!AA:AA)/_xlfn.XLOOKUP("Operating Income (EBIT)",DCF!$B:$B,DCF!H:H),"") -> 6.5589154 | R9: =IFERROR(_xlfn.XLOOKUP("Enterprise Value",DCF!$B:$B,DCF!AB:AB)/_xlfn.XLOOKUP("Operating Income (EBIT)",DCF!$B:$B,DCF!I:I),"") -> 5.4442224
B10: Price / Earnings | F10: =IFERROR(_xlfn.XLOOKUP("Market Capitalization",Inputs!$B:$B,Inputs!G:G)/_xlfn.XLOOKUP("Net Income",Inputs!$B:$B,Inputs!G:G),"") | G10: =IFERROR(_xlfn.XLOOKUP("Market Capitalization",Inputs!$B:$B,Inputs!H:H)/_xlfn.XLOOKUP("Net Income",Inputs!$B:$B,Inputs!H:H),"") | H10: =IFERROR(_xlfn.XLOOKUP("Market Capitalization",Inputs!$B:$B,Inputs!I:I)/_xlfn.XLOOKUP("Net Income",Inputs!$B:$B,Inputs!I:I),"") | I10: =IFERROR(_xlfn.XLOOKUP("Market Capitalization",Inputs!$B:$B,Inputs!J:J)/_xlfn.XLOOKUP("Net Income",Inputs!$B:$B,Inputs!J:J),"") | J10: =IFERROR(_xlfn.XLOOKUP("Market Capitalization",Inputs!$B:$B,Inputs!K:K)/_xlfn.XLOOKUP("Net Income",Inputs!$B:$B,Inputs!K:K),"") | K10: =IFERROR(_xlfn.XLOOKUP("Market Capitalization",Inputs!$B:$B,Inputs!L:L)/_xlfn.XLOOKUP("Net Income",Inputs!$B:$B,Inputs!L:L),"") | L10: =IFERROR(_xlfn.XLOOKUP("Market Capitalization",Inputs!$B:$B,Inputs!M:M)/_xlfn.XLOOKUP("Net Income",Inputs!$B:$B,Inputs!M:M),"") | M10: =IFERROR(_xlfn.XLOOKUP("Market Capitalization",Inputs!$B:$B,Inputs!N:N)/_xlfn.XLOOKUP("Net Income",Inputs!$B:$B,Inputs!N:N),"") -> -21.642027 | N10: =IFERROR(_xlfn.XLOOKUP("Market Capitalization",Inputs!$B:$B,Inputs!O:O)/_xlfn.XLOOKUP("Net Income",Inputs!$B:$B,Inputs!O:O),"") -> -14.428804 | O10: =IFERROR(_xlfn.XLOOKUP("Market Capitalization",Inputs!$B:$B,Inputs!P:P)/_xlfn.XLOOKUP("Net Income",Inputs!$B:$B,Inputs!P:P),"") -> -15.913482 | P10: =IFERROR(_xlfn.XLOOKUP("Market Capitalization",Inputs!$B:$B,Inputs!Q:Q)/_xlfn.XLOOKUP("Net Income",Inputs!$B:$B,Inputs!Q:Q),"") -> -26.835219 | Q10: =IFERROR(_xlfn.XLOOKUP("Equity Value",DCF!$B:$B,DCF!AA:AA)/_xlfn.XLOOKUP("Net Income",DCF!$B:$B,DCF!H:H),"") -> 7.3033356 | R10: =IFERROR(_xlfn.XLOOKUP("Equity Value",DCF!$B:$B,DCF!AB:AB)/_xlfn.XLOOKUP("Net Income",DCF!$B:$B,DCF!I:I),"") -> 6.8596672
B11: Price / Book | F11: =IFERROR(_xlfn.XLOOKUP("Market Capitalization",Inputs!$B:$B,Inputs!G:G)/_xlfn.XLOOKUP("Shareholder's Equity",Inputs!$B:$B,Inputs!G:G),"") | G11: =IFERROR(_xlfn.XLOOKUP("Market Capitalization",Inputs!$B:$B,Inputs!H:H)/_xlfn.XLOOKUP("Shareholder's Equity",Inputs!$B:$B,Inputs!H:H),"") | H11: =IFERROR(_xlfn.XLOOKUP("Market Capitalization",Inputs!$B:$B,Inputs!I:I)/_xlfn.XLOOKUP("Shareholder's Equity",Inputs!$B:$B,Inputs!I:I),"") | I11: =IFERROR(_xlfn.XLOOKUP("Market Capitalization",Inputs!$B:$B,Inputs!J:J)/_xlfn.XLOOKUP("Shareholder's Equity",Inputs!$B:$B,Inputs!J:J),"") | J11: =IFERROR(_xlfn.XLOOKUP("Market Capitalization",Inputs!$B:$B,Inputs!K:K)/_xlfn.XLOOKUP("Shareholder's Equity",Inputs!$B:$B,Inputs!K:K),"") | K11: =IFERROR(_xlfn.XLOOKUP("Market Capitalization",Inputs!$B:$B,Inputs!L:L)/_xlfn.XLOOKUP("Shareholder's Equity",Inputs!$B:$B,Inputs!L:L),"") | L11: =IFERROR(_xlfn.XLOOKUP("Market Capitalization",Inputs!$B:$B,Inputs!M:M)/_xlfn.XLOOKUP("Shareholder's Equity",Inputs!$B:$B,Inputs!M:M),"") | M11: =IFERROR(_xlfn.XLOOKUP("Market Capitalization",Inputs!$B:$B,Inputs!N:N)/_xlfn.XLOOKUP("Shareholder's Equity",Inputs!$B:$B,Inputs!N:N),"") -> 3.8869481 | N11: =IFERROR(_xlfn.XLOOKUP("Market Capitalization",Inputs!$B:$B,Inputs!O:O)/_xlfn.XLOOKUP("Shareholder's Equity",Inputs!$B:$B,Inputs!O:O),"") -> 1.2318588 | O11: =IFERROR(_xlfn.XLOOKUP("Market Capitalization",Inputs!$B:$B,Inputs!P:P)/_xlfn.XLOOKUP("Shareholder's Equity",Inputs!$B:$B,Inputs!P:P),"") -> 5.1751627 | P11: =IFERROR(_xlfn.XLOOKUP("Market Capitalization",Inputs!$B:$B,Inputs!Q:Q)/_xlfn.XLOOKUP("Shareholder's Equity",Inputs!$B:$B,Inputs!Q:Q),"") -> 23.180825 | Q11: =IFERROR(+_xlfn.XLOOKUP("Equity Value",DCF!$B:$B,DCF!AA:AA)/(_xlfn.XLOOKUP("Shareholder's Equity",Inputs!$B:$B,Inputs!$Q:$Q)+_xlfn.XLOOKUP("Net Income",DCF!$B:$B,DCF!H:H)+_xlfn.XLOOKUP("Total Payout",DCF!$B:$B,DCF!H:H)),"") -> -20.069772 | R11: =IFERROR(+_xlfn.XLOOKUP("Equity Value",DCF!$B:$B,DCF!AB:AB)/(_xlfn.XLOOKUP("Shareholder's Equity",Inputs!$B:$B,Inputs!$Q:$Q)+_xlfn.XLOOKUP("Net Income",DCF!$B:$B,DCF!I:I)+_xlfn.XLOOKUP("Total Payout",DCF!$B:$B,DCF!I:I)),"") -> -490.16913
B13: Profitability | F13: 2014 | G13: =+F13+1 -> 2015 | H13: =+G13+1 -> 2016 | I13: =+H13+1 -> 2017 | J13: =+I13+1 -> 2018 | K13: =+J13+1 -> 2019 | L13: =+K13+1 -> 2020 | M13: =+L13+1 -> 2021 | N13: 2022 | O13: =+N13+1 -> 2023 | P13: =+O13+1 -> 2024 | Q13: =+P13+1 -> 2025 | R13: =+Q13+1 -> 2026
B15: Return on Assets | F15: =+IFERROR(_xlfn.XLOOKUP("Net Income",Inputs!$B:$B,Inputs!G:G)/_xlfn.XLOOKUP("Total Assets",Inputs!$B:$B,Inputs!G:G),"") | G15: =+IFERROR(_xlfn.XLOOKUP("Net Income",Inputs!$B:$B,Inputs!H:H)/_xlfn.XLOOKUP("Total Assets",Inputs!$B:$B,Inputs!H:H),"") | H15: =+IFERROR(_xlfn.XLOOKUP("Net Income",Inputs!$B:$B,Inputs!I:I)/_xlfn.XLOOKUP("Total Assets",Inputs!$B:$B,Inputs!I:I),"") | I15: =+IFERROR(_xlfn.XLOOKUP("Net Income",Inputs!$B:$B,Inputs!J:J)/_xlfn.XLOOKUP("Total Assets",Inputs!$B:$B,Inputs!J:J),"") | J15: =+IFERROR(_xlfn.XLOOKUP("Net Income",Inputs!$B:$B,Inputs!K:K)/_xlfn.XLOOKUP("Total Assets",Inputs!$B:$B,Inputs!K:K),"") | K15: =+IFERROR(_xlfn.XLOOKUP("Net Income",Inputs!$B:$B,Inputs!L:L)/_xlfn.XLOOKUP("Total Assets",Inputs!$B:$B,Inputs!L:L),"") | L15: =+IFERROR(_xlfn.XLOOKUP("Net Income",Inputs!$B:$B,Inputs!M:M)/_xlfn.XLOOKUP("Total Assets",Inputs!$B:$B,Inputs!M:M),"") -> -0.25503489 | M15: =+IFERROR(_xlfn.XLOOKUP("Net Income",Inputs!$B:$B,Inputs!N:N)/_xlfn.XLOOKUP("Total Assets",Inputs!$B:$B,Inputs!N:N),"") -> -0.16539154 | N15: =+IFERROR(_xlfn.XLOOKUP("Net Income",Inputs!$B:$B,Inputs!O:O)/_xlfn.XLOOKUP("Total Assets",Inputs!$B:$B,Inputs!O:O),"") -> -0.081123159 | O15: =+IFERROR(_xlfn.XLOOKUP("Net Income",Inputs!$B:$B,Inputs!P:P)/_xlfn.XLOOKUP("Total Assets",Inputs!$B:$B,Inputs!P:P),"") -> -0.28491464 | P15: =+IFERROR(_xlfn.XLOOKUP("Net Income",Inputs!$B:$B,Inputs!Q:Q)/_xlfn.XLOOKUP("Total Assets",Inputs!$B:$B,Inputs!Q:Q),"") -> -0.65223424 | Q15: =IFERROR(_xlfn.XLOOKUP("Net Income",DCF!$B:$B,DCF!H:H)/_xlfn.XLOOKUP("Total assets",DCF!$6:$6,DCF!10:10),"") -> -0.95331909 | R15: =IFERROR(_xlfn.XLOOKUP("Net Income",DCF!$B:$B,DCF!I:I)/_xlfn.XLOOKUP("Total assets",DCF!$6:$6,DCF!10:10),"") -> -1.2822844
B16: Return on Equity | F16: =IFERROR(_xlfn.XLOOKUP("Net Income",Inputs!$B:$B,Inputs!G:G)/_xlfn.XLOOKUP("Shareholder's Equity",Inputs!$B:$B,Inputs!G:G),"") | G16: =IFERROR(_xlfn.XLOOKUP("Net Income",Inputs!$B:$B,Inputs!H:H)/_xlfn.XLOOKUP("Shareholder's Equity",Inputs!$B:$B,Inputs!H:H),"") | H16: =IFERROR(_xlfn.XLOOKUP("Net Income",Inputs!$B:$B,Inputs!I:I)/_xlfn.XLOOKUP("Shareholder's Equity",Inputs!$B:$B,Inputs!I:I),"") | I16: =IFERROR(_xlfn.XLOOKUP("Net Income",Inputs!$B:$B,Inputs!J:J)/_xlfn.XLOOKUP("Shareholder's Equity",Inputs!$B:$B,Inputs!J:J),"") | J16: =IFERROR(_xlfn.XLOOKUP("Net Income",Inputs!$B:$B,Inputs!K:K)/_xlfn.XLOOKUP("Shareholder's Equity",Inputs!$B:$B,Inputs!K:K),"") | K16: =IFERROR(_xlfn.XLOOKUP("Net Income",Inputs!$B:$B,Inputs!L:L)/_xlfn.XLOOKUP("Shareholder's Equity",Inputs!$B:$B,Inputs!L:L),"") | L16: =IFERROR(_xlfn.XLOOKUP("Net Income",Inputs!$B:$B,Inputs!M:M)/_xlfn.XLOOKUP("Shareholder's Equity",Inputs!$B:$B,Inputs!M:M),"") -> -0.28720928 | M16: =IFERROR(_xlfn.XLOOKUP("Net Income",Inputs!$B:$B,Inputs!N:N)/_xlfn.XLOOKUP("Shareholder's Equity",Inputs!$B:$B,Inputs!N:N),"") -> -0.17960185 | N16: =IFERROR(_xlfn.XLOOKUP("Net Income",Inputs!$B:$B,Inputs!O:O)/_xlfn.XLOOKUP("Shareholder's Equity",Inputs!$B:$B,Inputs!O:O),"") -> -0.085374975 | O16: =IFERROR(_xlfn.XLOOKUP("Net Income",Inputs!$B:$B,Inputs!P:P)/_xlfn.XLOOKUP("Shareholder's Equity",Inputs!$B:$B,Inputs!P:P),"") -> -0.32520618 | P16: =IFERROR(_xlfn.XLOOKUP("Net Income",Inputs!$B:$B,Inputs!Q:Q)/_xlfn.XLOOKUP("Shareholder's Equity",Inputs!$B:$B,Inputs!Q:Q),"") -> -0.86382101 | Q16: =IFERROR(_xlfn.XLOOKUP("Net Income",DCF!$B:$B,DCF!H:H)/_xlfn.XLOOKUP("Shareholder's Equity",DCF!$6:$6,DCF!10:10),"") -> 2.1736588 | R16: =IFERROR(_xlfn.XLOOKUP("Net Income",DCF!$B:$B,DCF!I:I)/_xlfn.XLOOKUP("Shareholder's Equity",DCF!$6:$6,DCF!10:10),"") -> 2.9237313
B17: Return on Total Capital | F17: =IFERROR(_xlfn.XLOOKUP("NOPAT",Inputs!$B:$B,Inputs!G:G)/(_xlfn.XLOOKUP("Shareholder's Equity",Inputs!$B:$B,Inputs!G:G)+_xlfn.XLOOKUP("Total Debt",Inputs!$B:$B,Inputs!G:G,,,-1)),"") | G17: =IFERROR(_xlfn.XLOOKUP("NOPAT",Inputs!$B:$B,Inputs!H:H)/(_xlfn.XLOOKUP("Shareholder's Equity",Inputs!$B:$B,Inputs!H:H)+_xlfn.XLOOKUP("Total Debt",Inputs!$B:$B,Inputs!H:H,,,-1)),"") | H17: =IFERROR(_xlfn.XLOOKUP("NOPAT",Inputs!$B:$B,Inputs!I:I)/(_xlfn.XLOOKUP("Shareholder's Equity",Inputs!$B:$B,Inputs!I:I)+_xlfn.XLOOKUP("Total Debt",Inputs!$B:$B,Inputs!I:I,,,-1)),"") | I17: =IFERROR(_xlfn.XLOOKUP("NOPAT",Inputs!$B:$B,Inputs!J:J)/(_xlfn.XLOOKUP("Shareholder's Equity",Inputs!$B:$B,Inputs!J:J)+_xlfn.XLOOKUP("Total Debt",Inputs!$B:$B,Inputs!J:J,,,-1)),"") | J17: =IFERROR(_xlfn.XLOOKUP("NOPAT",Inputs!$B:$B,Inputs!K:K)/(_xlfn.XLOOKUP("Shareholder's Equity",Inputs!$B:$B,Inputs!K:K)+_xlfn.XLOOKUP("Total Debt",Inputs!$B:$B,Inputs!K:K,,,-1)),"") | K17: =IFERROR(_xlfn.XLOOKUP("NOPAT",Inputs!$B:$B,Inputs!L:L)/(_xlfn.XLOOKUP("Shareholder's Equity",Inputs!$B:$B,Inputs!L:L)+_xlfn.XLOOKUP("Total Debt",Inputs!$B:$B,Inputs!L:L,,,-1)),"") | L17: =IFERROR(_xlfn.XLOOKUP("NOPAT",Inputs!$B:$B,Inputs!M:M)/(_xlfn.XLOOKUP("Shareholder's Equity",Inputs!$B:$B,Inputs!M:M)+_xlfn.XLOOKUP("Total Debt",Inputs!$B:$B,Inputs!M:M,,,-1)),"") -> -0.27138027 | M17: =IFERROR(_xlfn.XLOOKUP("NOPAT",Inputs!$B:$B,Inputs!N:N)/(_xlfn.XLOOKUP("Shareholder's Equity",Inputs!$B:$B,Inputs!N:N)+_xlfn.XLOOKUP("Total Debt",Inputs!$B:$B,Inputs!N:N,,,-1)),"") -> -0.064972012 | N17: =IFERROR(_xlfn.XLOOKUP("NOPAT",Inputs!$B:$B,Inputs!O:O)/(_xlfn.XLOOKUP("Shareholder's Equity",Inputs!$B:$B,Inputs!O:O)+_xlfn.XLOOKUP("Total Debt",Inputs!$B:$B,Inputs!O:O,,,-1)),"") -> -0.14983722 | O17: =IFERROR(_xlfn.XLOOKUP("NOPAT",Inputs!$B:$B,Inputs!P:P)/(_xlfn.XLOOKUP("Shareholder's Equity",Inputs!$B:$B,Inputs!P:P)+_xlfn.XLOOKUP("Total Debt",Inputs!$B:$B,Inputs!P:P,,,-1)),"") -> -0.31992368 | P17: =IFERROR(_xlfn.XLOOKUP("NOPAT",Inputs!$B:$B,Inputs!Q:Q)/(_xlfn.XLOOKUP("Shareholder's Equity",Inputs!$B:$B,Inputs!Q:Q)+_xlfn.XLOOKUP("Total Debt",Inputs!$B:$B,Inputs!Q:Q,,,-1)),"") -> -0.57884105 | Q17: =+IFERROR(_xlfn.XLOOKUP("NOPAT",DCF!$B:$B,DCF!H:H)/(_xlfn.XLOOKUP("Shareholder's Equity",DCF!$6:$6,DCF!10:10)+_xlfn.XLOOKUP("Total Borrowings",DCF!$B:$B,DCF!H:H)+_xlfn.XLOOKUP("Total Leases",DCF!$B:$B,DCF!H:H)),"") -> -1.5801313 | R17: =+IFERROR(_xlfn.XLOOKUP("NOPAT",DCF!$B:$B,DCF!I:I)/(_xlfn.XLOOKUP("Shareholder's Equity",DCF!$6:$6,DCF!10:10)+_xlfn.XLOOKUP("Total Borrowings",DCF!$B:$B,DCF!I:I)+_xlfn.XLOOKUP("Total Leases",DCF!$B:$B,DCF!I:I)),"") -> -1.7368601
B18: EBITDA Margin | F18: =+IFERROR(_xlfn.XLOOKUP("EBITDA",Inputs!$B:$B,Inputs!G:G)/_xlfn.XLOOKUP("Revenue (Sales)",Inputs!$B:$B,Inputs!G:G),"") | G18: =+IFERROR(_xlfn.XLOOKUP("EBITDA",Inputs!$B:$B,Inputs!H:H)/_xlfn.XLOOKUP("Revenue (Sales)",Inputs!$B:$B,Inputs!H:H),"") | H18: =+IFERROR(_xlfn.XLOOKUP("EBITDA",Inputs!$B:$B,Inputs!I:I)/_xlfn.XLOOKUP("Revenue (Sales)",Inputs!$B:$B,Inputs!I:I),"") | I18: =+IFERROR(_xlfn.XLOOKUP("EBITDA",Inputs!$B:$B,Inputs!J:J)/_xlfn.XLOOKUP("Revenue (Sales)",Inputs!$B:$B,Inputs!J:J),"") | J18: =+IFERROR(_xlfn.XLOOKUP("EBITDA",Inputs!$B:$B,Inputs!K:K)/_xlfn.XLOOKUP("Revenue (Sales)",Inputs!$B:$B,Inputs!K:K),"") | K18: =+IFERROR(_xlfn.XLOOKUP("EBITDA",Inputs!$B:$B,Inputs!L:L)/_xlfn.XLOOKUP("Revenue (Sales)",Inputs!$B:$B,Inputs!L:L),"") | L18: =+IFERROR(_xlfn.XLOOKUP("EBITDA",Inputs!$B:$B,Inputs!M:M)/_xlfn.XLOOKUP("Revenue (Sales)",Inputs!$B:$B,Inputs!M:M),"") | M18: =+IFERROR(_xlfn.XLOOKUP("EBITDA",Inputs!$B:$B,Inputs!N:N)/_xlfn.XLOOKUP("Revenue (Sales)",Inputs!$B:$B,Inputs!N:N),"") -> -17.217246 | N18: =+IFERROR(_xlfn.XLOOKUP("EBITDA",Inputs!$B:$B,Inputs!O:O)/_xlfn.XLOOKUP("Revenue (Sales)",Inputs!$B:$B,Inputs!O:O),"") -> -7.1998922 | O18: =+IFERROR(_xlfn.XLOOKUP("EBITDA",Inputs!$B:$B,Inputs!P:P)/_xlfn.XLOOKUP("Revenue (Sales)",Inputs!$B:$B,Inputs!P:P),"") -> -6.6862807 | P18: =+IFERROR(_xlfn.XLOOKUP("EBITDA",Inputs!$B:$B,Inputs!Q:Q)/_xlfn.XLOOKUP("Revenue (Sales)",Inputs!$B:$B,Inputs!Q:Q),"") -> -4.9636896 | Q18: =+_xlfn.XLOOKUP("EBITDA Margin",DCF!$B:$B,DCF!H:H) -> -3.8090125 | R18: =+_xlfn.XLOOKUP("EBITDA Margin",DCF!$B:$B,DCF!I:I) -> -2.8756962
B19: EBIT Margin | F19: =IFERROR(_xlfn.XLOOKUP("Operating Income (EBIT)",Inputs!$B:$B,Inputs!G:G)/_xlfn.XLOOKUP("Revenue (Sales)",Inputs!$B:$B,Inputs!G:G),"") | G19: =IFERROR(_xlfn.XLOOKUP("Operating Income (EBIT)",Inputs!$B:$B,Inputs!H:H)/_xlfn.XLOOKUP("Revenue (Sales)",Inputs!$B:$B,Inputs!H:H),"") | H19: =IFERROR(_xlfn.XLOOKUP("Operating Income (EBIT)",Inputs!$B:$B,Inputs!I:I)/_xlfn.XLOOKUP("Revenue (Sales)",Inputs!$B:$B,Inputs!I:I),"") | I19: =IFERROR(_xlfn.XLOOKUP("Operating Income (EBIT)",Inputs!$B:$B,Inputs!J:J)/_xlfn.XLOOKUP("Revenue (Sales)",Inputs!$B:$B,Inputs!J:J),"") | J19: =IFERROR(_xlfn.XLOOKUP("Operating Income (EBIT)",Inputs!$B:$B,Inputs!K:K)/_xlfn.XLOOKUP("Revenue (Sales)",Inputs!$B:$B,Inputs!K:K),"") | K19: =IFERROR(_xlfn.XLOOKUP("Operating Income (EBIT)",Inputs!$B:$B,Inputs!L:L)/_xlfn.XLOOKUP("Revenue (Sales)",Inputs!$B:$B,Inputs!L:L),"") | L19: =IFERROR(_xlfn.XLOOKUP("Operating Income (EBIT)",Inputs!$B:$B,Inputs!M:M)/_xlfn.XLOOKUP("Revenue (Sales)",Inputs!$B:$B,Inputs!M:M),"") | M19: =IFERROR(_xlfn.XLOOKUP("Operating Income (EBIT)",Inputs!$B:$B,Inputs!N:N)/_xlfn.XLOOKUP("Revenue (Sales)",Inputs!$B:$B,Inputs!N:N),"") -> -18.431158 | N19: =IFERROR(_xlfn.XLOOKUP("Operating Income (EBIT)",Inputs!$B:$B,Inputs!O:O)/_xlfn.XLOOKUP("Revenue (Sales)",Inputs!$B:$B,Inputs!O:O),"") -> -7.703351 | O19: =IFERROR(_xlfn.XLOOKUP("Operating Income (EBIT)",Inputs!$B:$B,Inputs!P:P)/_xlfn.XLOOKUP("Revenue (Sales)",Inputs!$B:$B,Inputs!P:P),"") -> -7.1569731 | P19: =IFERROR(_xlfn.XLOOKUP("Operating Income (EBIT)",Inputs!$B:$B,Inputs!Q:Q)/_xlfn.XLOOKUP("Revenue (Sales)",Inputs!$B:$B,Inputs!Q:Q),"") -> -5.3967683 | Q19: =+_xlfn.XLOOKUP("Operating Margin",DCF!$B:$B,DCF!H:H) -> -4.1258411 | R19: =+_xlfn.XLOOKUP("Operating Margin",DCF!$B:$B,DCF!I:I) -> -3.1611426
B20: EBT Margin | F20: =IFERROR(_xlfn.XLOOKUP("Pre-Tax Income (EBT)",Inputs!$B:$B,Inputs!G:G)/_xlfn.XLOOKUP("Revenue (Sales)",Inputs!$B:$B,Inputs!G:G),"") | G20: =IFERROR(_xlfn.XLOOKUP("Pre-Tax Income (EBT)",Inputs!$B:$B,Inputs!H:H)/_xlfn.XLOOKUP("Revenue (Sales)",Inputs!$B:$B,Inputs!H:H),"") | H20: =IFERROR(_xlfn.XLOOKUP("Pre-Tax Income (EBT)",Inputs!$B:$B,Inputs!I:I)/_xlfn.XLOOKUP("Revenue (Sales)",Inputs!$B:$B,Inputs!I:I),"") | I20: =IFERROR(_xlfn.XLOOKUP("Pre-Tax Income (EBT)",Inputs!$B:$B,Inputs!J:J)/_xlfn.XLOOKUP("Revenue (Sales)",Inputs!$B:$B,Inputs!J:J),"") | J20: =IFERROR(_xlfn.XLOOKUP("Pre-Tax Income (EBT)",Inputs!$B:$B,Inputs!K:K)/_xlfn.XLOOKUP("Revenue (Sales)",Inputs!$B:$B,Inputs!K:K),"") | K20: =IFERROR(_xlfn.XLOOKUP("Pre-Tax Income (EBT)",Inputs!$B:$B,Inputs!L:L)/_xlfn.XLOOKUP("Revenue (Sales)",Inputs!$B:$B,Inputs!L:L),"") | L20: =IFERROR(_xlfn.XLOOKUP("Pre-Tax Income (EBT)",Inputs!$B:$B,Inputs!M:M)/_xlfn.XLOOKUP("Revenue (Sales)",Inputs!$B:$B,Inputs!M:M),"") | M20: =IFERROR(_xlfn.XLOOKUP("Pre-Tax Income (EBT)",Inputs!$B:$B,Inputs!N:N)/_xlfn.XLOOKUP("Revenue (Sales)",Inputs!$B:$B,Inputs!N:N),"") -> -50.588852 | N20: =IFERROR(_xlfn.XLOOKUP("Pre-Tax Income (EBT)",Inputs!$B:$B,Inputs!O:O)/_xlfn.XLOOKUP("Revenue (Sales)",Inputs!$B:$B,Inputs!O:O),"") -> -4.3581888 | O20: =IFERROR(_xlfn.XLOOKUP("Pre-Tax Income (EBT)",Inputs!$B:$B,Inputs!P:P)/_xlfn.XLOOKUP("Revenue (Sales)",Inputs!$B:$B,Inputs!P:P),"") -> -7.1555666 | P20: =IFERROR(_xlfn.XLOOKUP("Pre-Tax Income (EBT)",Inputs!$B:$B,Inputs!Q:Q)/_xlfn.XLOOKUP("Revenue (Sales)",Inputs!$B:$B,Inputs!Q:Q),"") -> -7.6982797 | Q20: =IFERROR(_xlfn.XLOOKUP("Pre-Tax Income (EBT)",DCF!$B:$B,DCF!H:H)/_xlfn.XLOOKUP("Revenue (Sales)",DCF!$B:$B,DCF!H:H),"") -> -4.9502632 | R20: =IFERROR(_xlfn.XLOOKUP("Pre-Tax Income (EBT)",DCF!$B:$B,DCF!I:I)/_xlfn.XLOOKUP("Revenue (Sales)",DCF!$B:$B,DCF!I:I),"") -> -4.0970031
B21: Gross Profit Margin | F21: =IFERROR(_xlfn.XLOOKUP("Gross Profit",Inputs!$B:$B,Inputs!G:G)/_xlfn.XLOOKUP("Revenue (Sales)",Inputs!$B:$B,Inputs!G:G),"") | G21: =IFERROR(_xlfn.XLOOKUP("Gross Profit",Inputs!$B:$B,Inputs!H:H)/_xlfn.XLOOKUP("Revenue (Sales)",Inputs!$B:$B,Inputs!H:H),"") | H21: =IFERROR(_xlfn.XLOOKUP("Gross Profit",Inputs!$B:$B,Inputs!I:I)/_xlfn.XLOOKUP("Revenue (Sales)",Inputs!$B:$B,Inputs!I:I),"") | I21: =IFERROR(_xlfn.XLOOKUP("Gross Profit",Inputs!$B:$B,Inputs!J:J)/_xlfn.XLOOKUP("Revenue (Sales)",Inputs!$B:$B,Inputs!J:J),"") | J21: =IFERROR(_xlfn.XLOOKUP("Gross Profit",Inputs!$B:$B,Inputs!K:K)/_xlfn.XLOOKUP("Revenue (Sales)",Inputs!$B:$B,Inputs!K:K),"") | K21: =IFERROR(_xlfn.XLOOKUP("Gross Profit",Inputs!$B:$B,Inputs!L:L)/_xlfn.XLOOKUP("Revenue (Sales)",Inputs!$B:$B,Inputs!L:L),"") | L21: =IFERROR(_xlfn.XLOOKUP("Gross Profit",Inputs!$B:$B,Inputs!M:M)/_xlfn.XLOOKUP("Revenue (Sales)",Inputs!$B:$B,Inputs!M:M),"") | M21: =IFERROR(_xlfn.XLOOKUP("Gross Profit",Inputs!$B:$B,Inputs!N:N)/_xlfn.XLOOKUP("Revenue (Sales)",Inputs!$B:$B,Inputs!N:N),"") -> 0.50452596 | N21: =IFERROR(_xlfn.XLOOKUP("Gross Profit",Inputs!$B:$B,Inputs!O:O)/_xlfn.XLOOKUP("Revenue (Sales)",Inputs!$B:$B,Inputs!O:O),"") -> 0.73551343 | O21: =IFERROR(_xlfn.XLOOKUP("Gross Profit",Inputs!$B:$B,Inputs!P:P)/_xlfn.XLOOKUP("Revenue (Sales)",Inputs!$B:$B,Inputs!P:P),"") -> 0.63215679 | P21: =IFERROR(_xlfn.XLOOKUP("Gross Profit",Inputs!$B:$B,Inputs!Q:Q)/_xlfn.XLOOKUP("Revenue (Sales)",Inputs!$B:$B,Inputs!Q:Q),"") -> 0.52181181 | Q21: =+_xlfn.XLOOKUP("Gross Profit Margin",DCF!$B:$B,DCF!H:H) -> 0.52181181 | R21: =+_xlfn.XLOOKUP("Gross Profit Margin",DCF!$B:$B,DCF!I:I) -> 0.52181181
B22: SG&A Margin | F22: =IFERROR(+_xlfn.XLOOKUP("SG&A (Selling, General & Administrative)",Inputs!$B:$B,Inputs!G:G)/_xlfn.XLOOKUP("Revenue (Sales)",Inputs!$B:$B,Inputs!G:G),"") | G22: =IFERROR(+_xlfn.XLOOKUP("SG&A (Selling, General & Administrative)",Inputs!$B:$B,Inputs!H:H)/_xlfn.XLOOKUP("Revenue (Sales)",Inputs!$B:$B,Inputs!H:H),"") | H22: =IFERROR(+_xlfn.XLOOKUP("SG&A (Selling, General & Administrative)",Inputs!$B:$B,Inputs!I:I)/_xlfn.XLOOKUP("Revenue (Sales)",Inputs!$B:$B,Inputs!I:I),"") | I22: =IFERROR(+_xlfn.XLOOKUP("SG&A (Selling, General & Administrative)",Inputs!$B:$B,Inputs!J:J)/_xlfn.XLOOKUP("Revenue (Sales)",Inputs!$B:$B,Inputs!J:J),"") | J22: =IFERROR(+_xlfn.XLOOKUP("SG&A (Selling, General & Administrative)",Inputs!$B:$B,Inputs!K:K)/_xlfn.XLOOKUP("Revenue (Sales)",Inputs!$B:$B,Inputs!K:K),"") | K22: =IFERROR(+_xlfn.XLOOKUP("SG&A (Selling, General & Administrative)",Inputs!$B:$B,Inputs!L:L)/_xlfn.XLOOKUP("Revenue (Sales)",Inputs!$B:$B,Inputs!L:L),"") | L22: =IFERROR(+_xlfn.XLOOKUP("SG&A (Selling, General & Administrative)",Inputs!$B:$B,Inputs!M:M)/_xlfn.XLOOKUP("Revenue (Sales)",Inputs!$B:$B,Inputs!M:M),"") | M22: =IFERROR(+_xlfn.XLOOKUP("SG&A (Selling, General & Administrative)",Inputs!$B:$B,Inputs!N:N)/_xlfn.XLOOKUP("Revenue (Sales)",Inputs!$B:$B,Inputs!N:N),"") -> 8.0848023 | N22: =IFERROR(+_xlfn.XLOOKUP("SG&A (Selling, General & Administrative)",Inputs!$B:$B,Inputs!O:O)/_xlfn.XLOOKUP("Revenue (Sales)",Inputs!$B:$B,Inputs!O:O),"") -> 3.9844578 | O22: =IFERROR(+_xlfn.XLOOKUP("SG&A (Selling, General & Administrative)",Inputs!$B:$B,Inputs!P:P)/_xlfn.XLOOKUP("Revenue (Sales)",Inputs!$B:$B,Inputs!P:P),"") -> 3.1300245 | P22: =IFERROR(+_xlfn.XLOOKUP("SG&A (Selling, General & Administrative)",Inputs!$B:$B,Inputs!Q:Q)/_xlfn.XLOOKUP("Revenue (Sales)",Inputs!$B:$B,Inputs!Q:Q),"") -> 2.308871 | Q22: =+_xlfn.XLOOKUP("SG&A Margin",DCF!$B:$B,DCF!H:H) -> #N/A | R22: =+_xlfn.XLOOKUP("SG&A Margin",DCF!$B:$B,DCF!I:I) -> #N/A
B23: Net Income Margin | F23: =IFERROR(_xlfn.XLOOKUP("Net Income",Inputs!$B:$B,Inputs!G:G)/_xlfn.XLOOKUP("Revenue (Sales)",Inputs!$B:$B,Inputs!G:G),"") | G23: =IFERROR(_xlfn.XLOOKUP("Net Income",Inputs!$B:$B,Inputs!H:H)/_xlfn.XLOOKUP("Revenue (Sales)",Inputs!$B:$B,Inputs!H:H),"") | H23: =IFERROR(_xlfn.XLOOKUP("Net Income",Inputs!$B:$B,Inputs!I:I)/_xlfn.XLOOKUP("Revenue (Sales)",Inputs!$B:$B,Inputs!I:I),"") | I23: =IFERROR(_xlfn.XLOOKUP("Net Income",Inputs!$B:$B,Inputs!J:J)/_xlfn.XLOOKUP("Revenue (Sales)",Inputs!$B:$B,Inputs!J:J),"") | J23: =IFERROR(_xlfn.XLOOKUP("Net Income",Inputs!$B:$B,Inputs!K:K)/_xlfn.XLOOKUP("Revenue (Sales)",Inputs!$B:$B,Inputs!K:K),"") | K23: =IFERROR(_xlfn.XLOOKUP("Net Income",Inputs!$B:$B,Inputs!L:L)/_xlfn.XLOOKUP("Revenue (Sales)",Inputs!$B:$B,Inputs!L:L),"") | L23: =IFERROR(_xlfn.XLOOKUP("Net Income",Inputs!$B:$B,Inputs!M:M)/_xlfn.XLOOKUP("Revenue (Sales)",Inputs!$B:$B,Inputs!M:M),"") | M23: =IFERROR(_xlfn.XLOOKUP("Net Income",Inputs!$B:$B,Inputs!N:N)/_xlfn.XLOOKUP("Revenue (Sales)",Inputs!$B:$B,Inputs!N:N),"") -> -50.588852 | N23: =IFERROR(_xlfn.XLOOKUP("Net Income",Inputs!$B:$B,Inputs!O:O)/_xlfn.XLOOKUP("Revenue (Sales)",Inputs!$B:$B,Inputs!O:O),"") -> -4.3581888 | O23: =IFERROR(_xlfn.XLOOKUP("Net Income",Inputs!$B:$B,Inputs!P:P)/_xlfn.XLOOKUP("Revenue (Sales)",Inputs!$B:$B,Inputs!P:P),"") -> -7.1555688 | P23: =IFERROR(_xlfn.XLOOKUP("Net Income",Inputs!$B:$B,Inputs!Q:Q)/_xlfn.XLOOKUP("Revenue (Sales)",Inputs!$B:$B,Inputs!Q:Q),"") -> -7.698281 | Q23: =+_xlfn.XLOOKUP("Net Income Margin",DCF!$B:$B,DCF!H:H) -> -4.0838366 | R23: =+_xlfn.XLOOKUP("Net Income Margin",DCF!$B:$B,DCF!I:I) -> -3.4331631
B25: Liquidity | F25: 2014 | G25: =+F25+1 -> 2015 | H25: =+G25+1 -> 2016 | I25: =+H25+1 -> 2017 | J25: =+I25+1 -> 2018 | K25: =+J25+1 -> 2019 | L25: =+K25+1 -> 2020 | M25: =+L25+1 -> 2021 | N25: 2022 | O25: =+N25+1 -> 2023 | P25: =+O25+1 -> 2024 | Q25: =+P25+1 -> 2025 | R25: =+Q25+1 -> 2026
B27: Cash Ratio | F27: =+IFERROR(_xlfn.XLOOKUP("Cash & Cash Equivalents",Inputs!$B:$B,Inputs!G:G)/_xlfn.XLOOKUP("Current Liabilities",Inputs!$B:$B,Inputs!G:G),"") | G27: =+IFERROR(_xlfn.XLOOKUP("Cash & Cash Equivalents",Inputs!$B:$B,Inputs!H:H)/_xlfn.XLOOKUP("Current Liabilities",Inputs!$B:$B,Inputs!H:H),"") | H27: =+IFERROR(_xlfn.XLOOKUP("Cash & Cash Equivalents",Inputs!$B:$B,Inputs!I:I)/_xlfn.XLOOKUP("Current Liabilities",Inputs!$B:$B,Inputs!I:I),"") | I27: =+IFERROR(_xlfn.XLOOKUP("Cash & Cash Equivalents",Inputs!$B:$B,Inputs!J:J)/_xlfn.XLOOKUP("Current Liabilities",Inputs!$B:$B,Inputs!J:J),"") | J27: =+IFERROR(_xlfn.XLOOKUP("Cash & Cash Equivalents",Inputs!$B:$B,Inputs!K:K)/_xlfn.XLOOKUP("Current Liabilities",Inputs!$B:$B,Inputs!K:K),"") | K27: =+IFERROR(_xlfn.XLOOKUP("Cash & Cash Equivalents",Inputs!$B:$B,Inputs!L:L)/_xlfn.XLOOKUP("Current Liabilities",Inputs!$B:$B,Inputs!L:L),"") | L27: =+IFERROR(_xlfn.XLOOKUP("Cash & Cash Equivalents",Inputs!$B:$B,Inputs!M:M)/_xlfn.XLOOKUP("Current Liabilities",Inputs!$B:$B,Inputs!M:M),"") -> 19.202552 | M27: =+IFERROR(_xlfn.XLOOKUP("Cash & Cash Equivalents",Inputs!$B:$B,Inputs!N:N)/_xlfn.XLOOKUP("Current Liabilities",Inputs!$B:$B,Inputs!N:N),"") -> 41.174801 | N27: =+IFERROR(_xlfn.XLOOKUP("Cash & Cash Equivalents",Inputs!$B:$B,Inputs!O:O)/_xlfn.XLOOKUP("Current Liabilities",Inputs!$B:$B,Inputs!O:O),"") -> 2.200744 | O27: =+IFERROR(_xlfn.XLOOKUP("Cash & Cash Equivalents",Inputs!$B:$B,Inputs!P:P)/_xlfn.XLOOKUP("Current Liabilities",Inputs!$B:$B,Inputs!P:P),"") -> 0.95966527 | P27: =+IFERROR(_xlfn.XLOOKUP("Cash & Cash Equivalents",Inputs!$B:$B,Inputs!Q:Q)/_xlfn.XLOOKUP("Current Liabilities",Inputs!$B:$B,Inputs!Q:Q),"") -> 1.5073576 | Q27: =+IFERROR((_xlfn.XLOOKUP("Cash & Cash Equivalents & ST Investments",DCF!$B:$B,DCF!H:H)-_xlfn.XLOOKUP("Short-Term Investments",Inputs!$B:$B,Inputs!$Q:$Q))/_xlfn.XLOOKUP("Current Liabilities",DCF!$6:$6,DCF!10:10),"") -> -3.9720603 | R27: =+IFERROR((_xlfn.XLOOKUP("Cash & Cash Equivalents & ST Investments",DCF!$B:$B,DCF!I:I)-_xlfn.XLOOKUP("Short-Term Investments",Inputs!$B:$B,Inputs!$Q:$Q))/_xlfn.XLOOKUP("Current Liabilities",DCF!$6:$6,DCF!10:10),"") -> -12.715983
B28: Quick Ratio | F28: =IFERROR((_xlfn.XLOOKUP("Cash & Cash Equivalents & ST Investments",Inputs!$B:$B,Inputs!G:G)+_xlfn.XLOOKUP("Accounts Receivable",Inputs!$B:$B,Inputs!G:G))/_xlfn.XLOOKUP("Current Liabilities",Inputs!$B:$B,Inputs!G:G),"") | G28: =IFERROR((_xlfn.XLOOKUP("Cash & Cash Equivalents & ST Investments",Inputs!$B:$B,Inputs!H:H)+_xlfn.XLOOKUP("Accounts Receivable",Inputs!$B:$B,Inputs!H:H))/_xlfn.XLOOKUP("Current Liabilities",Inputs!$B:$B,Inputs!H:H),"") | H28: =IFERROR((_xlfn.XLOOKUP("Cash & Cash Equivalents & ST Investments",Inputs!$B:$B,Inputs!I:I)+_xlfn.XLOOKUP("Accounts Receivable",Inputs!$B:$B,Inputs!I:I))/_xlfn.XLOOKUP("Current Liabilities",Inputs!$B:$B,Inputs!I:I),"") | I28: =IFERROR((_xlfn.XLOOKUP("Cash & Cash Equivalents & ST Investments",Inputs!$B:$B,Inputs!J:J)+_xlfn.XLOOKUP("Accounts Receivable",Inputs!$B:$B,Inputs!J:J))/_xlfn.XLOOKUP("Current Liabilities",Inputs!$B:$B,Inputs!J:J),"") | J28: =IFERROR((_xlfn.XLOOKUP("Cash & Cash Equivalents & ST Investments",Inputs!$B:$B,Inputs!K:K)+_xlfn.XLOOKUP("Accounts Receivable",Inputs!$B:$B,Inputs!K:K))/_xlfn.XLOOKUP("Current Liabilities",Inputs!$B:$B,Inputs!K:K),"") | K28: =IFERROR((_xlfn.XLOOKUP("Cash & Cash Equivalents & ST Investments",Inputs!$B:$B,Inputs!L:L)+_xlfn.XLOOKUP("Accounts Receivable",Inputs!$B:$B,Inputs!L:L))/_xlfn.XLOOKUP("Current Liabilities",Inputs!$B:$B,Inputs!L:L),"") | L28: =IFERROR((_xlfn.XLOOKUP("Cash & Cash Equivalents & ST Investments",Inputs!$B:$B,Inputs!M:M)+_xlfn.XLOOKUP("Accounts Receivable",Inputs!$B:$B,Inputs!M:M))/_xlfn.XLOOKUP("Current Liabilities",Inputs!$B:$B,Inputs!M:M),"") -> 19.409888 | M28: =IFERROR((_xlfn.XLOOKUP("Cash & Cash Equivalents & ST Investments",Inputs!$B:$B,Inputs!N:N)+_xlfn.XLOOKUP("Accounts Receivable",Inputs!$B:$B,Inputs!N:N))/_xlfn.XLOOKUP("Current Liabilities",Inputs!$B:$B,Inputs!N:N),"") -> 53.985657 | N28: =IFERROR((_xlfn.XLOOKUP("Cash & Cash Equivalents & ST Investments",Inputs!$B:$B,Inputs!O:O)+_xlfn.XLOOKUP("Accounts Receivable",Inputs!$B:$B,Inputs!O:O))/_xlfn.XLOOKUP("Current Liabilities",Inputs!$B:$B,Inputs!O:O),"") -> 17.811954 | O28: =IFERROR((_xlfn.XLOOKUP("Cash & Cash Equivalents & ST Investments",Inputs!$B:$B,Inputs!P:P)+_xlfn.XLOOKUP("Accounts Receivable",Inputs!$B:$B,Inputs!P:P))/_xlfn.XLOOKUP("Current Liabilities",Inputs!$B:$B,Inputs!P:P),"") -> 9.8726725 | P28: =IFERROR((_xlfn.XLOOKUP("Cash & Cash Equivalents & ST Investments",Inputs!$B:$B,Inputs!Q:Q)+_xlfn.XLOOKUP("Accounts Receivable",Inputs!$B:$B,Inputs!Q:Q))/_xlfn.XLOOKUP("Current Liabilities",Inputs!$B:$B,Inputs!Q:Q),"") -> 9.6107801 | Q28: =+IFERROR((_xlfn.XLOOKUP("Cash & Cash Equivalents & ST Investments",DCF!$B:$B,DCF!H:H)+_xlfn.XLOOKUP("Accounts Receivable",DCF!$B:$B,DCF!H:H))/_xlfn.XLOOKUP("Current Liabilities",DCF!$6:$6,DCF!10:10),"") -> 1.1227435 | R28: =+IFERROR((_xlfn.XLOOKUP("Cash & Cash Equivalents & ST Investments",DCF!$B:$B,DCF!I:I)+_xlfn.XLOOKUP("Accounts Receivable",DCF!$B:$B,DCF!I:I))/_xlfn.XLOOKUP("Current Liabilities",DCF!$6:$6,DCF!10:10),"") -> -7.5133431
B29: Current Ratio | F29: =IFERROR(_xlfn.XLOOKUP("Current Assets",Inputs!$B:$B,Inputs!G:G)/+_xlfn.XLOOKUP("Current Liabilities",Inputs!$B:$B,Inputs!G:G),"") | G29: =IFERROR(_xlfn.XLOOKUP("Current Assets",Inputs!$B:$B,Inputs!H:H)/+_xlfn.XLOOKUP("Current Liabilities",Inputs!$B:$B,Inputs!H:H),"") | H29: =IFERROR(_xlfn.XLOOKUP("Current Assets",Inputs!$B:$B,Inputs!I:I)/+_xlfn.XLOOKUP("Current Liabilities",Inputs!$B:$B,Inputs!I:I),"") | I29: =IFERROR(_xlfn.XLOOKUP("Current Assets",Inputs!$B:$B,Inputs!J:J)/+_xlfn.XLOOKUP("Current Liabilities",Inputs!$B:$B,Inputs!J:J),"") | J29: =IFERROR(_xlfn.XLOOKUP("Current Assets",Inputs!$B:$B,Inputs!K:K)/+_xlfn.XLOOKUP("Current Liabilities",Inputs!$B:$B,Inputs!K:K),"") | K29: =IFERROR(_xlfn.XLOOKUP("Current Assets",Inputs!$B:$B,Inputs!L:L)/+_xlfn.XLOOKUP("Current Liabilities",Inputs!$B:$B,Inputs!L:L),"") | L29: =IFERROR(_xlfn.XLOOKUP("Current Assets",Inputs!$B:$B,Inputs!M:M)/+_xlfn.XLOOKUP("Current Liabilities",Inputs!$B:$B,Inputs!M:M),"") -> 20.509835 | M29: =IFERROR(_xlfn.XLOOKUP("Current Assets",Inputs!$B:$B,Inputs!N:N)/+_xlfn.XLOOKUP("Current Liabilities",Inputs!$B:$B,Inputs!N:N),"") -> 54.650397 | N29: =IFERROR(_xlfn.XLOOKUP("Current Assets",Inputs!$B:$B,Inputs!O:O)/+_xlfn.XLOOKUP("Current Liabilities",Inputs!$B:$B,Inputs!O:O),"") -> 18.433929 | O29: =IFERROR(_xlfn.XLOOKUP("Current Assets",Inputs!$B:$B,Inputs!P:P)/+_xlfn.XLOOKUP("Current Liabilities",Inputs!$B:$B,Inputs!P:P),"") -> 10.49373 | P29: =IFERROR(_xlfn.XLOOKUP("Current Assets",Inputs!$B:$B,Inputs!Q:Q)/+_xlfn.XLOOKUP("Current Liabilities",Inputs!$B:$B,Inputs!Q:Q),"") -> 10.497492 | Q29: =+IFERROR(_xlfn.XLOOKUP("Current Assets",DCF!$6:$6,DCF!10:10)/_xlfn.XLOOKUP("Current Liabilities",DCF!$6:$6,DCF!10:10),"") -> 1.7427224 | R29: =+IFERROR(_xlfn.XLOOKUP("Current Assets",DCF!$6:$6,DCF!10:10)/_xlfn.XLOOKUP("Current Liabilities",DCF!$6:$6,DCF!10:10),"") -> 1.7427224
B31: Efficiency | F31: 2014 | G31: =+F31+1 -> 2015 | H31: =+G31+1 -> 2016 | I31: =+H31+1 -> 2017 | J31: =+I31+1 -> 2018 | K31: =+J31+1 -> 2019 | L31: =+K31+1 -> 2020 | M31: =+L31+1 -> 2021 | N31: 2022 | O31: =+N31+1 -> 2023 | P31: =+O31+1 -> 2024 | Q31: =+P31+1 -> 2025 | R31: =+Q31+1 -> 2026
B33: Days Sales Outstanding | F33: =+_xlfn.XLOOKUP("DSO",Inputs!$B:$B,Inputs!G:G) | G33: =+_xlfn.XLOOKUP("DSO",Inputs!$B:$B,Inputs!H:H) | H33: =+_xlfn.XLOOKUP("DSO",Inputs!$B:$B,Inputs!I:I) | I33: =+_xlfn.XLOOKUP("DSO",Inputs!$B:$B,Inputs!J:J) | J33: =+_xlfn.XLOOKUP("DSO",Inputs!$B:$B,Inputs!K:K) | K33: =+_xlfn.XLOOKUP("DSO",Inputs!$B:$B,Inputs!L:L) | L33: =+_xlfn.XLOOKUP("DSO",Inputs!$B:$B,Inputs!M:M) | M33: =+_xlfn.XLOOKUP("DSO",Inputs!$B:$B,Inputs!N:N) -> 122.94188 | N33: =+_xlfn.XLOOKUP("DSO",Inputs!$B:$B,Inputs!O:O) -> 107.94897 | O33: =+_xlfn.XLOOKUP("DSO",Inputs!$B:$B,Inputs!P:P) -> 189.88545 | P33: =+_xlfn.XLOOKUP("DSO",Inputs!$B:$B,Inputs!Q:Q) -> 55.216493 | Q33: =+_xlfn.XLOOKUP("DSO",DCF!$B:$B,DCF!H:H) -> 55.367771 | R33: =+_xlfn.XLOOKUP("DSO",DCF!$B:$B,DCF!I:I) -> 55.367771
B34: Days Payable Outstanding | F34: =+_xlfn.XLOOKUP("DPO",Inputs!$B:$B,Inputs!G:G) | G34: =+_xlfn.XLOOKUP("DPO",Inputs!$B:$B,Inputs!H:H) | H34: =+_xlfn.XLOOKUP("DPO",Inputs!$B:$B,Inputs!I:I) | I34: =+_xlfn.XLOOKUP("DPO",Inputs!$B:$B,Inputs!J:J) | J34: =+_xlfn.XLOOKUP("DPO",Inputs!$B:$B,Inputs!K:K) | K34: =+_xlfn.XLOOKUP("DPO",Inputs!$B:$B,Inputs!L:L) | L34: =+_xlfn.XLOOKUP("DPO",Inputs!$B:$B,Inputs!M:M) | M34: =+_xlfn.XLOOKUP("DPO",Inputs!$B:$B,Inputs!N:N) -> 327.26536 | N34: =+_xlfn.XLOOKUP("DPO",Inputs!$B:$B,Inputs!O:O) -> 100.17743 | O34: =+_xlfn.XLOOKUP("DPO",Inputs!$B:$B,Inputs!P:P) -> 92.715498 | P34: =+_xlfn.XLOOKUP("DPO",Inputs!$B:$B,Inputs!Q:Q) -> 44.318947 | Q34: =+_xlfn.XLOOKUP("DPO",DCF!$B:$B,DCF!H:H) -> 90 | R34: =+_xlfn.XLOOKUP("DPO",DCF!$B:$B,DCF!I:I) -> 65
B35: Days Inventory Outstanding | F35: =+_xlfn.XLOOKUP("DIH",Inputs!$B:$B,Inputs!G:G) | G35: =+_xlfn.XLOOKUP("DIH",Inputs!$B:$B,Inputs!H:H) | H35: =+_xlfn.XLOOKUP("DIH",Inputs!$B:$B,Inputs!I:I) | I35: =+_xlfn.XLOOKUP("DIH",Inputs!$B:$B,Inputs!J:J) | J35: =+_xlfn.XLOOKUP("DIH",Inputs!$B:$B,Inputs!K:K) | K35: =+_xlfn.XLOOKUP("DIH",Inputs!$B:$B,Inputs!L:L) | L35: =+_xlfn.XLOOKUP("DIH",Inputs!$B:$B,Inputs!M:M) -> 0 | M35: =+_xlfn.XLOOKUP("DIH",Inputs!$B:$B,Inputs!N:N) -> 0 | N35: =+_xlfn.XLOOKUP("DIH",Inputs!$B:$B,Inputs!O:O) -> 0 | O35: =+_xlfn.XLOOKUP("DIH",Inputs!$B:$B,Inputs!P:P) -> 0 | P35: =+_xlfn.XLOOKUP("DIH",Inputs!$B:$B,Inputs!Q:Q) -> 0 | Q35: =+_xlfn.XLOOKUP("DIH",DCF!$B:$B,DCF!H:H) -> 0 | R35: =+_xlfn.XLOOKUP("DIH",DCF!$B:$B,DCF!I:I) -> 0
B36: Cash Conversion Cycle | F36: =IFERROR(F35+F33-F34,"") | G36: =IFERROR(G35+G33-G34,"") | H36: =IFERROR(H35+H33-H34,"") | I36: =IFERROR(I35+I33-I34,"") | J36: =IFERROR(J35+J33-J34,"") | K36: =IFERROR(K35+K33-K34,"") | L36: =IFERROR(L35+L33-L34,"") | M36: =IFERROR(M35+M33-M34,"") -> -204.32349 | ... R36: =IFERROR(R35+R33-R34,"") -> -9.632229
B38: Leverage | F38: 2014 | G38: =+F38+1 -> 2015 | H38: =+G38+1 -> 2016 | I38: =+H38+1 -> 2017 | J38: =+I38+1 -> 2018 | K38: =+J38+1 -> 2019 | L38: =+K38+1 -> 2020 | M38: =+L38+1 -> 2021 | N38: 2022 | O38: =+N38+1 -> 2023 | P38: =+O38+1 -> 2024 | Q38: =+P38+1 -> 2025 | R38: =+Q38+1 -> 2026
B40: Total Debt / Equity | F40: =+IFERROR(_xlfn.XLOOKUP("Total Debt",Inputs!$B:$B,Inputs!G:G)*1000/+_xlfn.XLOOKUP("Shareholder's Equity",Inputs!$B:$B,Inputs!G:G),"") | G40: =+IFERROR(_xlfn.XLOOKUP("Total Debt",Inputs!$B:$B,Inputs!H:H)*1000/+_xlfn.XLOOKUP("Shareholder's Equity",Inputs!$B:$B,Inputs!H:H),"") | H40: =+IFERROR(_xlfn.XLOOKUP("Total Debt",Inputs!$B:$B,Inputs!I:I)*1000/+_xlfn.XLOOKUP("Shareholder's Equity",Inputs!$B:$B,Inputs!I:I),"") | I40: =+IFERROR(_xlfn.XLOOKUP("Total Debt",Inputs!$B:$B,Inputs!J:J)*1000/+_xlfn.XLOOKUP("Shareholder's Equity",Inputs!$B:$B,Inputs!J:J),"") | J40: =+IFERROR(_xlfn.XLOOKUP("Total Debt",Inputs!$B:$B,Inputs!K:K)*1000/+_xlfn.XLOOKUP("Shareholder's Equity",Inputs!$B:$B,Inputs!K:K),"") | K40: =+IFERROR(_xlfn.XLOOKUP("Total Debt",Inputs!$B:$B,Inputs!L:L)*1000/+_xlfn.XLOOKUP("Shareholder's Equity",Inputs!$B:$B,Inputs!L:L),"") | L40: =+IFERROR(_xlfn.XLOOKUP("Total Debt",Inputs!$B:$B,Inputs!M:M)*1000/+_xlfn.XLOOKUP("Shareholder's Equity",Inputs!$B:$B,Inputs!M:M),"") -> 79.530008 | M40: =+IFERROR(_xlfn.XLOOKUP("Total Debt",Inputs!$B:$B,Inputs!N:N)*1000/+_xlfn.XLOOKUP("Shareholder's Equity",Inputs!$B:$B,Inputs!N:N),"") -> 7.1224397 | N40: =+IFERROR(_xlfn.XLOOKUP("Total Debt",Inputs!$B:$B,Inputs!O:O)*1000/+_xlfn.XLOOKUP("Shareholder's Equity",Inputs!$B:$B,Inputs!O:O),"") -> 7.1276339 | O40: =+IFERROR(_xlfn.XLOOKUP("Total Debt",Inputs!$B:$B,Inputs!P:P)*1000/+_xlfn.XLOOKUP("Shareholder's Equity",Inputs!$B:$B,Inputs!P:P),"") -> 16.711547 | P40: =+IFERROR(_xlfn.XLOOKUP("Total Debt",Inputs!$B:$B,Inputs!Q:Q)*1000/+_xlfn.XLOOKUP("Shareholder's Equity",Inputs!$B:$B,Inputs!Q:Q),"") -> 46.175448 | Q40: =IFERROR((_xlfn.XLOOKUP("Total Borrowings",DCF!$B:$B,DCF!G:G)+_xlfn.XLOOKUP("Total Leases",DCF!$B:$B,DCF!G:G))/_xlfn.XLOOKUP("Shareholder's Equity",DCF!$6:$6,DCF!10:10),"") -> -0.13689392 | R40: =IFERROR((_xlfn.XLOOKUP("Total Borrowings",DCF!$B:$B,DCF!H:H)+_xlfn.XLOOKUP("Total Leases",DCF!$B:$B,DCF!H:H))/_xlfn.XLOOKUP("Shareholder's Equity",DCF!$6:$6,DCF!10:10),"") -> -2.0979168
B41: Total Debt / Capital | F41: =+IFERROR(_xlfn.XLOOKUP("Total Debt",Inputs!$B:$B,Inputs!G:G)*1000/(+_xlfn.XLOOKUP("Shareholder's Equity",Inputs!$B:$B,Inputs!G:G)+_xlfn.XLOOKUP("Total Debt",Inputs!$B:$B,Inputs!G:G)*1000),"") | G41: =+IFERROR(_xlfn.XLOOKUP("Total Debt",Inputs!$B:$B,Inputs!H:H)*1000/(+_xlfn.XLOOKUP("Shareholder's Equity",Inputs!$B:$B,Inputs!H:H)+_xlfn.XLOOKUP("Total Debt",Inputs!$B:$B,Inputs!H:H)*1000),"") | H41: =+IFERROR(_xlfn.XLOOKUP("Total Debt",Inputs!$B:$B,Inputs!I:I)*1000/(+_xlfn.XLOOKUP("Shareholder's Equity",Inputs!$B:$B,Inputs!I:I)+_xlfn.XLOOKUP("Total Debt",Inputs!$B:$B,Inputs!I:I)*1000),"") | I41: =+IFERROR(_xlfn.XLOOKUP("Total Debt",Inputs!$B:$B,Inputs!J:J)*1000/(+_xlfn.XLOOKUP("Shareholder's Equity",Inputs!$B:$B,Inputs!J:J)+_xlfn.XLOOKUP("Total Debt",Inputs!$B:$B,Inputs!J:J)*1000),"") | J41: =+IFERROR(_xlfn.XLOOKUP("Total Debt",Inputs!$B:$B,Inputs!K:K)*1000/(+_xlfn.XLOOKUP("Shareholder's Equity",Inputs!$B:$B,Inputs!K:K)+_xlfn.XLOOKUP("Total Debt",Inputs!$B:$B,Inputs!K:K)*1000),"") | K41: =+IFERROR(_xlfn.XLOOKUP("Total Debt",Inputs!$B:$B,Inputs!L:L)*1000/(+_xlfn.XLOOKUP("Shareholder's Equity",Inputs!$B:$B,Inputs!L:L)+_xlfn.XLOOKUP("Total Debt",Inputs!$B:$B,Inputs!L:L)*1000),"") | L41: =+IFERROR(_xlfn.XLOOKUP("Total Debt",Inputs!$B:$B,Inputs!M:M)*1000/(+_xlfn.XLOOKUP("Shareholder's Equity",Inputs!$B:$B,Inputs!M:M)+_xlfn.XLOOKUP("Total Debt",Inputs!$B:$B,Inputs!M:M)*1000),"") -> 0.98758227 | M41: =+IFERROR(_xlfn.XLOOKUP("Total Debt",Inputs!$B:$B,Inputs!N:N)*1000/(+_xlfn.XLOOKUP("Shareholder's Equity",Inputs!$B:$B,Inputs!N:N)+_xlfn.XLOOKUP("Total Debt",Inputs!$B:$B,Inputs!N:N)*1000),"") -> 0.87688428 | N41: =+IFERROR(_xlfn.XLOOKUP("Total Debt",Inputs!$B:$B,Inputs!O:O)*1000/(+_xlfn.XLOOKUP("Shareholder's Equity",Inputs!$B:$B,Inputs!O:O)+_xlfn.XLOOKUP("Total Debt",Inputs!$B:$B,Inputs!O:O)*1000),"") -> 0.87696296 | O41: =+IFERROR(_xlfn.XLOOKUP("Total Debt",Inputs!$B:$B,Inputs!P:P)*1000/(+_xlfn.XLOOKUP("Shareholder's Equity",Inputs!$B:$B,Inputs!P:P)+_xlfn.XLOOKUP("Total Debt",Inputs!$B:$B,Inputs!P:P)*1000),"") -> 0.94353966 | P41: =+IFERROR(_xlfn.XLOOKUP("Total Debt",Inputs!$B:$B,Inputs!Q:Q)*1000/(+_xlfn.XLOOKUP("Shareholder's Equity",Inputs!$B:$B,Inputs!Q:Q)+_xlfn.XLOOKUP("Total Debt",Inputs!$B:$B,Inputs!Q:Q)*1000),"") -> 0.97880253 | Q41: =IFERROR((_xlfn.XLOOKUP("Total Borrowings",DCF!$B:$B,DCF!G:G)+_xlfn.XLOOKUP("Total Leases",DCF!$B:$B,DCF!G:G))/(_xlfn.XLOOKUP("Shareholder's Equity",DCF!$6:$6,DCF!10:10)+_xlfn.XLOOKUP("Total Borrowings",DCF!$B:$B,DCF!G:G)+_xlfn.XLOOKUP("Total Leases",DCF!$B:$B,DCF!G:G)),"") -> -0.15860614 | R41: =IFERROR((_xlfn.XLOOKUP("Total Borrowings",DCF!$B:$B,DCF!H:H)+_xlfn.XLOOKUP("Total Leases",DCF!$B:$B,DCF!H:H))/(_xlfn.XLOOKUP("Shareholder's Equity",DCF!$6:$6,DCF!10:10)+_xlfn.XLOOKUP("Total Borrowings",DCF!$B:$B,DCF!H:H)+_xlfn.XLOOKUP("Total Leases",DCF!$B:$B,DCF!H:H)),"") -> 1.9108158
B42: Total Liabilities / Total Assets | F42: =IFERROR(_xlfn.XLOOKUP("Total Liabilities",Inputs!$B:$B,Inputs!G:G)/_xlfn.XLOOKUP("Total Assets",Inputs!$B:$B,Inputs!G:G),"") | G42: =IFERROR(_xlfn.XLOOKUP("Total Liabilities",Inputs!$B:$B,Inputs!H:H)/_xlfn.XLOOKUP("Total Assets",Inputs!$B:$B,Inputs!H:H),"") | H42: =IFERROR(_xlfn.XLOOKUP("Total Liabilities",Inputs!$B:$B,Inputs!I:I)/_xlfn.XLOOKUP("Total Assets",Inputs!$B:$B,Inputs!I:I),"") | I42: =IFERROR(_xlfn.XLOOKUP("Total Liabilities",Inputs!$B:$B,Inputs!J:J)/_xlfn.XLOOKUP("Total Assets",Inputs!$B:$B,Inputs!J:J),"") | J42: =IFERROR(_xlfn.XLOOKUP("Total Liabilities",Inputs!$B:$B,Inputs!K:K)/_xlfn.XLOOKUP("Total Assets",Inputs!$B:$B,Inputs!K:K),"") | K42: =IFERROR(_xlfn.XLOOKUP("Total Liabilities",Inputs!$B:$B,Inputs!L:L)/_xlfn.XLOOKUP("Total Assets",Inputs!$B:$B,Inputs!L:L),"") | L42: =IFERROR(_xlfn.XLOOKUP("Total Liabilities",Inputs!$B:$B,Inputs!M:M)/_xlfn.XLOOKUP("Total Assets",Inputs!$B:$B,Inputs!M:M),"") -> 0.11202421 | M42: =IFERROR(_xlfn.XLOOKUP("Total Liabilities",Inputs!$B:$B,Inputs!N:N)/_xlfn.XLOOKUP("Total Assets",Inputs!$B:$B,Inputs!N:N),"") -> 0.07912116 | N42: =IFERROR(_xlfn.XLOOKUP("Total Liabilities",Inputs!$B:$B,Inputs!O:O)/_xlfn.XLOOKUP("Total Assets",Inputs!$B:$B,Inputs!O:O),"") -> 0.04980167 | O42: =IFERROR(_xlfn.XLOOKUP("Total Liabilities",Inputs!$B:$B,Inputs!P:P)/_xlfn.XLOOKUP("Total Assets",Inputs!$B:$B,Inputs!P:P),"") -> 0.12389537 | P42: =IFERROR(_xlfn.XLOOKUP("Total Liabilities",Inputs!$B:$B,Inputs!Q:Q)/_xlfn.XLOOKUP("Total Assets",Inputs!$B:$B,Inputs!Q:Q),"") -> 0.24494284 | Q42: =IFERROR(+_xlfn.XLOOKUP("Total Liabilities",DCF!$6:$6,DCF!10:10)/_xlfn.XLOOKUP("Total Assets",DCF!$6:$6,DCF!10:10),"") -> 1.4385781 | R42: =IFERROR(+_xlfn.XLOOKUP("Total Liabilities",DCF!$6:$6,DCF!10:10)/_xlfn.XLOOKUP("Total Assets",DCF!$6:$6,DCF!10:10),"") -> 1.4385781
