Workbook
Name COOLFUCNTION: _xlfn.LAMBDA(_xldudf_BOARDFLARE_EXEC("workbook-settings:coolfucntion"))
Name COOLFUCNTION: _xlfn.LAMBDA(_xldudf_BOARDFLARE_EXEC("workbook-settings:coolfucntion"))
Name COOLFUCNTION: _xlfn.LAMBDA(_xldudf_BOARDFLARE_EXEC("workbook-settings:coolfucntion"))
Name COOLFUCNTION: _xlfn.LAMBDA(_xldudf_BOARDFLARE_EXEC("workbook-settings:coolfucntion"))
Name COOLFUCNTION: _xlfn.LAMBDA(_xldudf_BOARDFLARE_EXEC("workbook-settings:coolfucntion"))
Name COOLFUCNTION: _xlfn.LAMBDA(_xldudf_BOARDFLARE_EXEC("workbook-settings:coolfucntion"))
Name COOLFUCNTION: _xlfn.LAMBDA(_xldudf_BOARDFLARE_EXEC("workbook-settings:coolfucntion"))
Name COOLFUCNTION: _xlfn.LAMBDA(_xldudf_BOARDFLARE_EXEC("workbook-settings:coolfucntion"))
Name COOLFUCNTION: _xlfn.LAMBDA(_xldudf_BOARDFLARE_EXEC("workbook-settings:coolfucntion"))
Name COOLFUCNTION: _xlfn.LAMBDA(_xldudf_BOARDFLARE_EXEC("workbook-settings:coolfucntion"))
Name Sectors: #REF!
Name Sectors: #REF!
Name Sectors: #REF!

Sheet Summary
E2: | EQUITY RESEARCH | U2: Lisbon Investment Society Equity Research
U3: April 27th, 2025
D6: {=+_FV(#REF!,"Name")} -> #VALUE! | U6: Strong Sell
D8: Rocket Lab USA, Inc. is an end-to-end space company. The Company designs and manufactures small and medium-class rockets, spacecraft and spacecraft components, and related software and services to support the space economy. The Company delivers reliable launch services, satellite manufacture, spacecraft design services, spacecraft components, spacecraft manufacturing, and other spacecraft and on-orbit management solutions that make it easier to access space. Its Launch Services segment provides launch and launch-related services to customers on a dedicated mission or ride-share basis. Its Space Systems segment comprises the design and manufacture of spacecraft components and spacecraft program management services, space data applications, and mission operations. Its space systems solutions are the building blocks for spacecraft, which include composite structures, reaction wheels, star trackers, solar solutions, radios, separation systems, and command and control spacecraft software. | U8: #VALUE!
U9: {=+"Price (7 Mar 25): $"&_FV(#REF!,"Price")} -> #VALUE!
D10: Investment Thesis | U10: ="Price Target: $" & ROUND(IF(Summary!G25="FCFF",#REF!,IF(Summary!G25="FCFE",#REF!,IF(Summary!G25="Tax Shield",#REF!,#REF!))),2) &" "&IF(Summary!G25="FCFF","(FCFF)",IF(Summary!G25="FCFE","(FCFE)",IF(Summary!G25="Tax Shield","(APV)","(DDM)"))) -> #REF!
D11: The DCF implies a –130% downside to intrinsic value by 2034, well below current market levels, flagging deeply negative free-cash-flow projections and ongoing investment burn . Persistent sub-$100 M annual gross profit relative to over $400 M R&D and SG&A spend underscores structural unprofitability and likely dilution .With net operating losses persisting (–61% EBIT margin in 2029E) and no path to sustainable cash generation, a Strong Sell stance is warranted . | U11: =+"Upside (Downside): "&ROUND((#REF!*100),2)&"%" -> #REF!
U14: =+Industry!E28&", "&ESG!C9 -> , Industrials
U15: =+ESG!C10 -> Aerospace & Defense
D17: Operating Metrics | F17: 2023 | G17: =+F17+1 -> 2024 | H17: =+G17+1 -> 2025 | I17: =+H17+1 -> 2026 | K17: Valuation Multiples | N17: 2022 | O17: =+N17+1 -> 2023 | P17: =+O17+1 -> 2024 | Q17: =+P17+1 -> 2025 | R17: =+Q17+1 -> 2026 | U17: Jorge Daniel Vieira Freitas
K18: EV / Sales | N18: =IFERROR(_xlfn.XLOOKUP($K18,Multiples!$B:$B,Multiples!N:N),"") | O18: =IFERROR(_xlfn.XLOOKUP($K18,Multiples!$B:$B,Multiples!O:O),"") | P18: =IFERROR(_xlfn.XLOOKUP($K18,Multiples!$B:$B,Multiples!P:P),"") | Q18: =IFERROR(_xlfn.XLOOKUP($K18,Multiples!$B:$B,Multiples!Q:Q),"") | R18: =IFERROR(_xlfn.XLOOKUP($K18,Multiples!$B:$B,Multiples!R:R),"") | U18: vieirafreitasjorgedaniel@gmail.com
K19: Price / Sales | N19: =IFERROR(_xlfn.XLOOKUP($K19,Multiples!$B:$B,Multiples!N:N),"") | O19: =IFERROR(_xlfn.XLOOKUP($K19,Multiples!$B:$B,Multiples!O:O),"") | P19: =IFERROR(_xlfn.XLOOKUP($K19,Multiples!$B:$B,Multiples!P:P),"") | Q19: =IFERROR(_xlfn.XLOOKUP($K19,Multiples!$B:$B,Multiples!Q:Q),"") | R19: =IFERROR(_xlfn.XLOOKUP($K19,Multiples!$B:$B,Multiples!R:R),"") | U19: (+351) 935 907 954
K20: EV / EBITDA | N20: =IFERROR(_xlfn.XLOOKUP($K20,Multiples!$B:$B,Multiples!N:N),"") | O20: =IFERROR(_xlfn.XLOOKUP($K20,Multiples!$B:$B,Multiples!O:O),"") | P20: =IFERROR(_xlfn.XLOOKUP($K20,Multiples!$B:$B,Multiples!P:P),"") | Q20: =IFERROR(_xlfn.XLOOKUP($K20,Multiples!$B:$B,Multiples!Q:Q),"") | R20: =IFERROR(_xlfn.XLOOKUP($K20,Multiples!$B:$B,Multiples!R:R),"") | U20: Maria Pilar Fortunato
K21: EV / EBIT | N21: =IFERROR(_xlfn.XLOOKUP($K21,Multiples!$B:$B,Multiples!N:N),"") | O21: =IFERROR(_xlfn.XLOOKUP($K21,Multiples!$B:$B,Multiples!O:O),"") | P21: =IFERROR(_xlfn.XLOOKUP($K21,Multiples!$B:$B,Multiples!P:P),"") | Q21: =IFERROR(_xlfn.XLOOKUP($K21,Multiples!$B:$B,Multiples!Q:Q),"") | R21: =IFERROR(_xlfn.XLOOKUP($K21,Multiples!$B:$B,Multiples!R:R),"") | U21: pilarbarrocalfortunato@gmail.com
K22: Price / Earnings | N22: =IFERROR(_xlfn.XLOOKUP($K22,Multiples!$B:$B,Multiples!N:N),"") | O22: =IFERROR(_xlfn.XLOOKUP($K22,Multiples!$B:$B,Multiples!O:O),"") | P22: =IFERROR(_xlfn.XLOOKUP($K22,Multiples!$B:$B,Multiples!P:P),"") | Q22: =IFERROR(_xlfn.XLOOKUP($K22,Multiples!$B:$B,Multiples!Q:Q),"") | R22: =IFERROR(_xlfn.XLOOKUP($K22,Multiples!$B:$B,Multiples!R:R),"") | U22: (+351) 914 350 356
K23: Price / Book | N23: =IFERROR(_xlfn.XLOOKUP($K23,Multiples!$B:$B,Multiples!N:N),"") | O23: =IFERROR(_xlfn.XLOOKUP($K23,Multiples!$B:$B,Multiples!O:O),"") | P23: =IFERROR(_xlfn.XLOOKUP($K23,Multiples!$B:$B,Multiples!P:P),"") | Q23: =IFERROR(_xlfn.XLOOKUP($K23,Multiples!$B:$B,Multiples!Q:Q),"") | R23: =IFERROR(_xlfn.XLOOKUP($K23,Multiples!$B:$B,Multiples!R:R),"") | U23: Thor Cordeiro Alves Pinto
U24: thoropinto@gmail.com
D25: Year | E25: Net Sales | F25: EBIT Margin | G25: FCFF | H25: =+IF(Summary!$G$25="FCFF",#REF!,IF(Summary!$G$25="FCFE",#REF!,#REF!)) -> #REF! | I25: Net Capex | K25: Profitability Ratios | N25: 2022 | O25: =+N25+1 -> 2023 | P25: =+O25+1 -> 2024 | Q25: =+P25+1 -> 2025 | R25: =+Q25+1 -> 2026 | U25: (+351) 924 698 417
D26: 2022 | E26: =+#REF! -> #REF! | F26: =+#REF! -> #REF! | G26: =+INDEX(#REF!,MATCH(Summary!$G$25,{"FCFF","FCFE","Tax Shield","Total Payout"},0)) -> #REF! | H26: =+IF(Summary!$G$25="FCFF",#REF!,IF(Summary!$G$25="FCFE",#REF!,#REF!)) -> #REF! | I26: =+#REF! -> #REF! | K26: Return on Assets | N26: =IFERROR(_xlfn.XLOOKUP($K26,Multiples!$B:$B,Multiples!N:N),"") -> -0.10764331 | O26: =IFERROR(_xlfn.XLOOKUP($K26,Multiples!$B:$B,Multiples!O:O),"") -> -0.1638334 | P26: =IFERROR(_xlfn.XLOOKUP($K26,Multiples!$B:$B,Multiples!P:P),"") -> -0.12727349 | Q26: =IFERROR(_xlfn.XLOOKUP($K26,Multiples!$B:$B,Multiples!Q:Q),"") | R26: =IFERROR(_xlfn.XLOOKUP($K26,Multiples!$B:$B,Multiples!R:R),"") | U26: Maria Rita Baltazar Moura
D27: =+D26+1 -> 2023 | E27: =+#REF! -> #REF! | F27: =+#REF! -> #REF! | G27: =+INDEX(#REF!,MATCH(Summary!$G$25,{"FCFF","FCFE","Tax Shield","Total Payout"},0)) -> #REF! | H27: =+IF(Summary!$G$25="FCFF",#REF!,IF(Summary!$G$25="FCFE",#REF!,#REF!)) -> #REF! | I27: =+#REF! -> #REF! | K27: Return on Equity | N27: =IFERROR(_xlfn.XLOOKUP($K27,Multiples!$B:$B,Multiples!N:N),"") -> -0.15815508 | O27: =IFERROR(_xlfn.XLOOKUP($K27,Multiples!$B:$B,Multiples!O:O),"") -> -0.27808837 | P27: =IFERROR(_xlfn.XLOOKUP($K27,Multiples!$B:$B,Multiples!P:P),"") -> -0.39416841 | Q27: =IFERROR(_xlfn.XLOOKUP($K27,Multiples!$B:$B,Multiples!Q:Q),"") | R27: =IFERROR(_xlfn.XLOOKUP($K27,Multiples!$B:$B,Multiples!R:R),"") | U27: mariaritabaltazarmoura@gmail.com
D28: =+D27+1 -> 2024 | E28: =+#REF! -> #REF! | F28: =+#REF! -> #REF! | G28: =+INDEX(#REF!,MATCH(Summary!$G$25,{"FCFF","FCFE","Tax Shield","Total Payout"},0)) -> #REF! | H28: =+IF(Summary!$G$25="FCFF",#REF!,IF(Summary!$G$25="FCFE",#REF!,#REF!)) -> #REF! | I28: =+#REF! -> #REF! | K28: Return on Total Capital | N28: =IFERROR(_xlfn.XLOOKUP($K28,Multiples!$B:$B,Multiples!N:N),"") -> -0.13640392 | O28: =IFERROR(_xlfn.XLOOKUP($K28,Multiples!$B:$B,Multiples!O:O),"") -> -0.21705458 | P28: =IFERROR(_xlfn.XLOOKUP($K28,Multiples!$B:$B,Multiples!P:P),"") -> -0.17937245 | Q28: =IFERROR(_xlfn.XLOOKUP($K28,Multiples!$B:$B,Multiples!Q:Q),"") | R28: =IFERROR(_xlfn.XLOOKUP($K28,Multiples!$B:$B,Multiples!R:R),"") | U28: (+351) 925 922 810
D29: =+D28+1 -> 2025 | E29: =+#REF! -> #REF! | F29: =+#REF! -> #REF! | G29: =+INDEX(#REF!,MATCH(Summary!$G$25,{"FCFF","FCFE","Tax Shield","Total Payout"},0)) -> #REF! | H29: =+IF(Summary!$G$25="FCFF",#REF!,IF(Summary!$G$25="FCFE",#REF!,#REF!)) -> #REF! | I29: =+#REF! -> #REF! | K29: EBITDA Margin | N29: =IFERROR(_xlfn.XLOOKUP($K29,Multiples!$B:$B,Multiples!N:N),"") -> -0.64075829 | O29: =IFERROR(_xlfn.XLOOKUP($K29,Multiples!$B:$B,Multiples!O:O),"") -> -0.72771872 | P29: =IFERROR(_xlfn.XLOOKUP($K29,Multiples!$B:$B,Multiples!P:P),"") -> -0.41746905 | Q29: =IFERROR(_xlfn.XLOOKUP($K29,Multiples!$B:$B,Multiples!Q:Q),"") | R29: =IFERROR(_xlfn.XLOOKUP($K29,Multiples!$B:$B,Multiples!R:R),"")
D30: =+D29+1 -> 2026 | E30: =+#REF! -> #REF! | F30: =+#REF! -> #REF! | G30: =+INDEX(#REF!,MATCH(Summary!$G$25,{"FCFF","FCFE","Tax Shield","Total Payout"},0)) -> #REF! | H30: =+IF(Summary!$G$25="FCFF",#REF!,IF(Summary!$G$25="FCFE",#REF!,#REF!)) -> #REF! | I30: =+#REF! -> #REF! | K30: EBIT Margin | N30: =IFERROR(_xlfn.XLOOKUP($K30,Multiples!$B:$B,Multiples!N:N),"") -> -0.50127962 | O30: =IFERROR(_xlfn.XLOOKUP($K30,Multiples!$B:$B,Multiples!O:O),"") -> -0.61120196 | P30: =IFERROR(_xlfn.XLOOKUP($K30,Multiples!$B:$B,Multiples!P:P),"") -> -0.34440624 | Q30: =IFERROR(_xlfn.XLOOKUP($K30,Multiples!$B:$B,Multiples!Q:Q),"") | R30: =IFERROR(_xlfn.XLOOKUP($K30,Multiples!$B:$B,Multiples!R:R),"") | U30: Statistics
D31: =+D30+1 -> 2027 | E31: =+#REF! -> #REF! | F31: =+#REF! -> #REF! | G31: =+INDEX(#REF!,MATCH(Summary!$G$25,{"FCFF","FCFE","Tax Shield","Total Payout"},0)) -> #REF! | H31: =+IF(Summary!$G$25="FCFF",#REF!,IF(Summary!$G$25="FCFE",#REF!,#REF!)) -> #REF! | I31: =+#REF! -> #REF! | K31: Gross Profit Margin | N31: =IFERROR(_xlfn.XLOOKUP($K31,Multiples!$B:$B,Multiples!N:N),"") -> 0.090047393 | O31: =IFERROR(_xlfn.XLOOKUP($K31,Multiples!$B:$B,Multiples!O:O),"") -> 0.210139 | P31: =IFERROR(_xlfn.XLOOKUP($K31,Multiples!$B:$B,Multiples!P:P),"") -> 0.26616231 | Q31: =IFERROR(_xlfn.XLOOKUP($K31,Multiples!$B:$B,Multiples!Q:Q),"") | R31: =IFERROR(_xlfn.XLOOKUP($K31,Multiples!$B:$B,Multiples!R:R),"") | U31: Beta | V31: =Peers!D74
D32: =+D31+1 -> 2028 | E32: =+#REF! -> #REF! | F32: =+#REF! -> #REF! | G32: =+INDEX(#REF!,MATCH(Summary!$G$25,{"FCFF","FCFE","Tax Shield","Total Payout"},0)) -> #REF! | H32: =+IF(Summary!$G$25="FCFF",#REF!,IF(Summary!$G$25="FCFE",#REF!,#REF!)) -> #REF! | I32: =+#REF! -> #REF! | K32: SG&A Margin | N32: =IFERROR(_xlfn.XLOOKUP($K32,Multiples!$B:$B,Multiples!N:N),"") -> 0.42180095 | O32: =IFERROR(_xlfn.XLOOKUP($K32,Multiples!$B:$B,Multiples!O:O),"") -> 0.45094031 | P32: =IFERROR(_xlfn.XLOOKUP($K32,Multiples!$B:$B,Multiples!P:P),"") -> 0.28381476 | Q32: =IFERROR(_xlfn.XLOOKUP($K32,Multiples!$B:$B,Multiples!Q:Q),"") | R32: =IFERROR(_xlfn.XLOOKUP($K32,Multiples!$B:$B,Multiples!R:R),"") | U32: % Float | V32: =+Peers!D73 -> 0
D33: =+D32+1 -> 2029 | E33: =+#REF! -> #REF! | F33: =+#REF! -> #REF! | G33: =+INDEX(#REF!,MATCH(Summary!$G$25,{"FCFF","FCFE","Tax Shield","Total Payout"},0)) -> #REF! | H33: =+IF(Summary!$G$25="FCFF",#REF!,IF(Summary!$G$25="FCFE",#REF!,#REF!)) -> #REF! | I33: =+#REF! -> #REF! | K33: Net Income Margin | N33: =IFERROR(_xlfn.XLOOKUP($K33,Multiples!$B:$B,Multiples!N:N),"") -> -0.50459716 | O33: =IFERROR(_xlfn.XLOOKUP($K33,Multiples!$B:$B,Multiples!O:O),"") -> -0.63041701 | P33: =IFERROR(_xlfn.XLOOKUP($K33,Multiples!$B:$B,Multiples!P:P),"") -> -0.3455525 | Q33: =IFERROR(_xlfn.XLOOKUP($K33,Multiples!$B:$B,Multiples!Q:Q),"") | R33: =IFERROR(_xlfn.XLOOKUP($K33,Multiples!$B:$B,Multiples!R:R),"") | U33: % Held by Insiders | V33: =+Peers!D76 -> 0
U34: % Held by Institutions | V34: =+Peers!D77 -> 0
D35: SWOT Analysis | K35: Liquidity Ratios | N35: 2022 | O35: =+N35+1 -> 2023 | P35: =+O35+1 -> 2024 | Q35: =+P35+1 -> 2025 | R35: =+Q35+1 -> 2026 | U35: Short % of Float | V35: =+Peers!D78 -> 0
D36: Strengths | G36: Weaknesses | K36: Cash Ratio | N36: =IFERROR(_xlfn.XLOOKUP($K36,Multiples!$B:$B,Multiples!N:N),"") -> 1.4886433 | O36: =IFERROR(_xlfn.XLOOKUP($K36,Multiples!$B:$B,Multiples!O:O),"") -> 0.72739481 | P36: =IFERROR(_xlfn.XLOOKUP($K36,Multiples!$B:$B,Multiples!P:P),"") -> 0.7982327 | Q36: =IFERROR(_xlfn.XLOOKUP($K36,Multiples!$B:$B,Multiples!Q:Q),"") | R36: =IFERROR(_xlfn.XLOOKUP($K36,Multiples!$B:$B,Multiples!R:R),"") | W36: 120.87
D37: Global leader in dedicated small satellite launches, with a proven track record in a rapidly expanding market. Strong technological innovation and vertical integration, enabling cost reductions, faster production, and efficient mission delivery. Strategic global launch sites and key partnerships that strengthen international market reach and customer access. | G37: Reliance on Future Success of the Neutron Rocket. High capital expenditures required for developing cutting-edge technologies and expanding capabilities. Extreme operational complexity and inherent technical risks that could lead to launch delays or failures. | K37: Quick Ratio | N37: =IFERROR(_xlfn.XLOOKUP($K37,Multiples!$B:$B,Multiples!N:N),"") -> 3.1209331 | O37: =IFERROR(_xlfn.XLOOKUP($K37,Multiples!$B:$B,Multiples!O:O),"") -> 1.2533572 | P37: =IFERROR(_xlfn.XLOOKUP($K37,Multiples!$B:$B,Multiples!P:P),"") -> 1.3410898 | Q37: =IFERROR(_xlfn.XLOOKUP($K37,Multiples!$B:$B,Multiples!Q:Q),"") | R37: =IFERROR(_xlfn.XLOOKUP($K37,Multiples!$B:$B,Multiples!R:R),"") | U37: Major Holders | W37: 113.63
K38: Current Ratio | N38: =IFERROR(_xlfn.XLOOKUP($K38,Multiples!$B:$B,Multiples!N:N),"") -> 4.0656845 | O38: =IFERROR(_xlfn.XLOOKUP($K38,Multiples!$B:$B,Multiples!O:O),"") -> 2.1338406 | P38: =IFERROR(_xlfn.XLOOKUP($K38,Multiples!$B:$B,Multiples!P:P),"") -> 2.0400589 | Q38: =IFERROR(_xlfn.XLOOKUP($K38,Multiples!$B:$B,Multiples!Q:Q),"") | R38: =IFERROR(_xlfn.XLOOKUP($K38,Multiples!$B:$B,Multiples!R:R),"") | U38: Vanguard Group Inc | V38: 7.98%
U39: VK Services, LLC | V39: 7.24%
D40: Opportunities | G40: Threats | K40: Cash Flow Ratios | N40: 2022 | O40: =+N40+1 -> 2023 | P40: =+O40+1 -> 2024 | Q40: =+P40+1 -> 2025 | R40: =+Q40+1 -> 2026 | U40: Blackrock Inc. | V40: 6.95%
D41: Growing global demand for small satellites, fuelled by advancements in communication and Earth observation technologies. Potential expansion into larger payloads through the development of new vehicles like the Neutron rocket. Increasing opportunities to secure government and commercial contracts in a rapidly evolving space market. | G41: Intense competition from larger, well-established companies such as SpaceX and Blue Origin. Uncertainty in regulatory environments and geopolitical tensions that could impact international launches. Risks of technical issues, supply chain disruptions, and potential launch failures that may damage the company’s reputation. | K41: Cash Conversion Cycle | N41: =IFERROR(_xlfn.XLOOKUP($K41,Multiples!$B:$B,Multiples!N:N),"") -> 202.7979 | O41: =IFERROR(_xlfn.XLOOKUP($K41,Multiples!$B:$B,Multiples!O:O),"") -> 204.29601 | P41: =IFERROR(_xlfn.XLOOKUP($K41,Multiples!$B:$B,Multiples!P:P),"") -> 105.59852 | Q41: =IFERROR(_xlfn.XLOOKUP($K41,Multiples!$B:$B,Multiples!Q:Q),"") | R41: =IFERROR(_xlfn.XLOOKUP($K41,Multiples!$B:$B,Multiples!R:R),"") | U41: State Street Corporation | V41: 3.06%
K42: Net Income / Op Cash Flow | N42: =IFERROR(_xlfn.XLOOKUP($K42,Multiples!$B:$B,Multiples!N:N),"") -> 0.99971831 | O42: =IFERROR(_xlfn.XLOOKUP($K42,Multiples!$B:$B,Multiples!O:O),"") -> 1.5591507 | P42: =IFERROR(_xlfn.XLOOKUP($K42,Multiples!$B:$B,Multiples!P:P),"") -> 3.0824131 | Q42: =IFERROR(_xlfn.XLOOKUP($K42,Multiples!$B:$B,Multiples!Q:Q),"") | R42: =IFERROR(_xlfn.XLOOKUP($K42,Multiples!$B:$B,Multiples!R:R),"") | U42: Shaw D.E. & Co., Inc. | V42: 1.85%
K43: Chg in Cash / Op Cash Flow | N43: =IFERROR(_xlfn.XLOOKUP($K43,Multiples!$B:$B,Multiples!N:N),"") -> 4.1896714 | O43: =IFERROR(_xlfn.XLOOKUP($K43,Multiples!$B:$B,Multiples!O:O),"") -> 0.80283114 | P43: =IFERROR(_xlfn.XLOOKUP($K43,Multiples!$B:$B,Multiples!P:P),"") -> -2.2269939 | Q43: =IFERROR(_xlfn.XLOOKUP($K43,Multiples!$B:$B,Multiples!Q:Q),"") | R43: =IFERROR(_xlfn.XLOOKUP($K43,Multiples!$B:$B,Multiples!R:R),"") | U43: Geode Capital Management, LLC | V43: 1.83%
U44: Deer Management Co. LLC | V44: 1.80%
D45: Revenue by Region | G45: Revenue by Segment | K45: Leverage Ratios | N45: 2022 | O45: =+N45+1 -> 2023 | P45: =+O45+1 -> 2024 | Q45: =+P45+1 -> 2025 | R45: =+Q45+1 -> 2026 | U45: UBS Group AG | V45: 1.04%
K46: Total Debt / Equity | N46: =IFERROR(_xlfn.XLOOKUP($K46,Multiples!$B:$B,Multiples!N:N),"") -> 185.2347 | O46: =IFERROR(_xlfn.XLOOKUP($K46,Multiples!$B:$B,Multiples!O:O),"") -> 272.67809 | P46: =IFERROR(_xlfn.XLOOKUP($K46,Multiples!$B:$B,Multiples!P:P),"") -> 1201.8828 | Q46: =IFERROR(_xlfn.XLOOKUP($K46,Multiples!$B:$B,Multiples!Q:Q),"") | R46: =IFERROR(_xlfn.XLOOKUP($K46,Multiples!$B:$B,Multiples!R:R),"") | U46: Morgan Stanley | V46: 0.95%
K47: Total Debt / Capital | N47: =IFERROR(_xlfn.XLOOKUP($K47,Multiples!$B:$B,Multiples!N:N),"") -> 0.99463043 | O47: =IFERROR(_xlfn.XLOOKUP($K47,Multiples!$B:$B,Multiples!O:O),"") -> 0.99634607 | P47: =IFERROR(_xlfn.XLOOKUP($K47,Multiples!$B:$B,Multiples!P:P),"") -> 0.99916866 | Q47: =IFERROR(_xlfn.XLOOKUP($K47,Multiples!$B:$B,Multiples!Q:Q),"") | R47: =IFERROR(_xlfn.XLOOKUP($K47,Multiples!$B:$B,Multiples!R:R),"") | U47: Bank of America Corporation | V47: 0.84%
K48: Total Liabilities / Total Assets | N48: =IFERROR(_xlfn.XLOOKUP($K48,Multiples!$B:$B,Multiples!N:N),"") -> 0.31938126 | O48: =IFERROR(_xlfn.XLOOKUP($K48,Multiples!$B:$B,Multiples!O:O),"") -> 0.41085848 | P48: =IFERROR(_xlfn.XLOOKUP($K48,Multiples!$B:$B,Multiples!P:P),"") -> 0.67710884 | Q48: =IFERROR(_xlfn.XLOOKUP($K48,Multiples!$B:$B,Multiples!Q:Q),"") | R48: =IFERROR(_xlfn.XLOOKUP($K48,Multiples!$B:$B,Multiples!R:R),"")
K49: Total Debt / EBITDA | N49: =IFERROR(_xlfn.XLOOKUP($K49,Multiples!$B:$B,Multiples!N:N),"") -> -0.92233728 | O49: =IFERROR(_xlfn.XLOOKUP($K49,Multiples!$B:$B,Multiples!O:O),"") -> -0.8494382 | P49: =IFERROR(_xlfn.XLOOKUP($K49,Multiples!$B:$B,Multiples!P:P),"") -> -2.523888 | Q49: =IFERROR(_xlfn.XLOOKUP($K49,Multiples!$B:$B,Multiples!Q:Q),"") | R49: =IFERROR(_xlfn.XLOOKUP($K49,Multiples!$B:$B,Multiples!R:R),"") | U49: Board of Directors
K50: Total Debt / (EBITDA - Capex) | N50: =IFERROR(_xlfn.XLOOKUP($K50,Multiples!$B:$B,Multiples!N:N),"") -> -0.51232539 | O50: =IFERROR(_xlfn.XLOOKUP($K50,Multiples!$B:$B,Multiples!O:O),"") -> -0.60967742 | P50: =IFERROR(_xlfn.XLOOKUP($K50,Multiples!$B:$B,Multiples!P:P),"") -> -1.9416984 | Q50: =IFERROR(_xlfn.XLOOKUP($K50,Multiples!$B:$B,Multiples!Q:Q),"") | R50: =IFERROR(_xlfn.XLOOKUP($K50,Multiples!$B:$B,Multiples!R:R),"") | U50: Peter Beck (Founder, President and CEO, Chairman) [Non-Indep.], Merline Saintil (Lead Independent Director) [Indep.], Nina Armagno (Director, Retired Lieutenant General, U.S. Space Force) [Indep.], Edward Frank (Director, Technology Executive) [Indep.], Matt Ocko (Director, Representative of DCVC) [Non-Indep.], Jon A. Olson (Director) [Indep.], Kenneth R. Possenriede (Director, Former CFO of Lockheed Martin) [Indep.], Alex Slusky (Director, Representative of Vector Capital) [Non-Indep.].
K51: Net Debt / EBITDA | N51: =IFERROR(_xlfn.XLOOKUP($K50,Multiples!$B:$B,Multiples!N:N),"") -> -0.51232539 | O51: =IFERROR(_xlfn.XLOOKUP($K50,Multiples!$B:$B,Multiples!O:O),"") -> -0.60967742 | P51: =IFERROR(_xlfn.XLOOKUP($K50,Multiples!$B:$B,Multiples!P:P),"") -> -1.9416984 | Q51: =IFERROR(_xlfn.XLOOKUP($K50,Multiples!$B:$B,Multiples!Q:Q),"") | R51: =IFERROR(_xlfn.XLOOKUP($K50,Multiples!$B:$B,Multiples!R:R),"")
K53: Solvency Ratios | N53: 2022 | O53: =+N53+1 -> 2023 | P53: =+O53+1 -> 2024 | Q53: =+P53+1 -> 2025 | R53: =+Q53+1 -> 2026
K54: EBIT / Interest Expense | N54: =IFERROR(_xlfn.XLOOKUP($K54,Multiples!$B:$B,Multiples!N:N),"") -> -13.560256 | O54: =IFERROR(_xlfn.XLOOKUP($K54,Multiples!$B:$B,Multiples!O:O),"") -> -35.595238 | P54: =IFERROR(_xlfn.XLOOKUP($K54,Multiples!$B:$B,Multiples!P:P),"") -> -37.5575 | Q54: =IFERROR(_xlfn.XLOOKUP($K54,Multiples!$B:$B,Multiples!Q:Q),"") -> N/A | R54: =IFERROR(_xlfn.XLOOKUP($K54,Multiples!$B:$B,Multiples!R:R),"") -> N/A
K55: EBITDA / Interest Expense | N55: =IFERROR(_xlfn.XLOOKUP($K55,Multiples!$B:$B,Multiples!N:N),"") -> -17.333333 | O55: =IFERROR(_xlfn.XLOOKUP($K55,Multiples!$B:$B,Multiples!O:O),"") -> -42.380952 | P55: =IFERROR(_xlfn.XLOOKUP($K55,Multiples!$B:$B,Multiples!P:P),"") -> -45.525 | Q55: =IFERROR(_xlfn.XLOOKUP($K55,Multiples!$B:$B,Multiples!Q:Q),"") -> N/A | R55: =IFERROR(_xlfn.XLOOKUP($K55,Multiples!$B:$B,Multiples!R:R),"") -> N/A
K56: (EBITDA - Capex) / Interest Expense | N56: =IFERROR(_xlfn.XLOOKUP($K56,Multiples!$B:$B,Multiples!N:N),"") -> -3.4615385 | O56: =IFERROR(_xlfn.XLOOKUP($K56,Multiples!$B:$B,Multiples!O:O),"") -> -25.714286 | P56: =IFERROR(_xlfn.XLOOKUP($K56,Multiples!$B:$B,Multiples!P:P),"") -> -31.875 | Q56: =IFERROR(_xlfn.XLOOKUP($K56,Multiples!$B:$B,Multiples!Q:Q),"") -> N/A | R56: =IFERROR(_xlfn.XLOOKUP($K56,Multiples!$B:$B,Multiples!R:R),"") -> N/A
D58: Debt Schedule | K58: Stock Performance
U60: ESG Traffic Light
U61: LSEG ESG Score | V61: =ESG!C14 -> 22
U62: E-Score | V62: =ESG!C15 -> 0
U63: S-Score | V63: =ESG!C16 -> 13
U64: G-Score | V64: =ESG!C17 -> 50
U65: S&P Global ESG Score | V65: =ESG!C18 -> private
U66: Environmental | V66: =ESG!C19 -> private
U67: Social | V67: =ESG!C20 -> private
U68: Governance & Economic | V68: =ESG!C21 -> private
U69: Sustainalytics | V69: =ESG!C22 -> 39.9
U70: ISS ESG Corporate Rating | V70: =ESG!C23 -> D-
U71: SDG Impact Rating | V71: =ESG!C24 -> -7.8
U72: Governance Quality Score | V72: =ESG!C25 -> 8
U73: MSCI ESG Ratings | V73: =ESG!C26 -> N/A
D80: Extra Notes

Sheet Regions
A1: In Millions of USD | E1: 2021 A (Rep) | F1: 2022 A (Rep) | G1: 2023 A (Rep) | H1: 2024 A (Rep) | I1: 2025 A (Fwd) | J1: 2026 A (Fwd)
A2: 12 Months Ending | B2: Field Expression | C2: Calcrt Field | D2: Segment Id | E2: 44561 | F2: 44926 | G2: 45291 | H2: 45657 | I2: 46022 | J2: 46387 | M2: =2 -> 2 | N2: =M2+1 -> 3 | O2: =N2+1 -> 4 | P2: =O2+1 -> 5
A3: Revenue | B3: SALES_REV_TURN | C3: IS010 | E3: 62.237 | F3: 210.996 | G3: 244.592 | H3: 436.214 | M3: 2021 | N3: =M3+1 -> 2022 | O3: =N3+1 -> 2023 | P3: =O3+1 -> 2024
A4: United States | B4: SALES_REV_TURN | C4: IS010 | D4: SEG0001085575 Segment | E4: 45.75 | F4: 164.593 | G4: 184.748 | H4: 268.326 | L4: United States | M4: =E4 -> 45.75 | N4: =F4 -> 164.593 | O4: =G4 -> 184.748 | P4: =H4 -> 268.326
A5: % of Total | B5: SALES_REV_TURN | C5: IS010 | D5: SEG0001085575 Segment | E5: 73.509327 | F5: 78.00764 | G5: 75.533133 | H5: 61.512469 | L5: Japan | M5: =E6 -> 0.769 | N5: =F6 -> 15.306 | O5: =G6 | P5: =H6 -> 30.684
A6: Japan | B6: SALES_REV_TURN | C6: IS010 | D6: SEG0001085569 Segment | E6: 0.769 | F6: 15.306 | H6: 30.684 | L6: Germany | M6: =E8 -> 9.77 | N6: =F8 -> 5.26 | O6: =G8 -> 5.503 | P6: =H8
A7: % of Total | B7: SALES_REV_TURN | C7: IS010 | D7: SEG0001085569 Segment | E7: 1.2355994 | F7: 7.254166 | H7: 7.0341621 | L7: Canada | M7: =E12 | N7: =F12 | O7: =G12 -> 36.116 | P7: =H12 -> 104.388
A8: Germany | B8: SALES_REV_TURN | C8: IS010 | D8: SEG0001085573 Segment | E8: 9.77 | F8: 5.26 | G8: 5.503 | L8: Rest Of World | M8: =E10 -> 5.948 | N8: =F10 -> 25.837 | O8: =G10 -> 18.225 | P8: =H10 -> 32.816
A9: % of Total | B9: SALES_REV_TURN | C9: IS010 | D9: SEG0001085573 Segment | E9: 15.698057 | F9: 2.4929383 | G9: 2.2498692
A10: Rest Of World | B10: SALES_REV_TURN | C10: IS010 | D10: SEG0001085570 Segment | E10: 5.948 | F10: 25.837 | G10: 18.225 | H10: 32.816
A11: % of Total | B11: SALES_REV_TURN | C11: IS010 | D11: SEG0001085570 Segment | E11: 9.5570159 | F11: 12.245256 | G11: 7.451184 | H11: 7.5229131
A12: Canada | B12: SALES_REV_TURN | C12: IS010 | D12: SEG0001085571 Segment | G12: 36.116 | H12: 104.388
A13: % of Total | B13: SALES_REV_TURN | C13: IS010 | D13: SEG0001085571 Segment | G13: 14.765814 | H13: 23.930456
A15: Percentage of Revenue | B15: IS_PERCENTAGE_OF_REVENUE | C15: IC214
A16: United States | B16: IS_PERCENTAGE_OF_REVENUE | C16: IC214 | D16: SEG0001085575 Segment | H16: 61
A17: % of Total | B17: IS_PERCENTAGE_OF_REVENUE | C17: IC214 | D17: SEG0001085575 Segment
A18: Japan | B18: IS_PERCENTAGE_OF_REVENUE | C18: IC214 | D18: SEG0001085569 Segment | H18: 7
A19: % of Total | B19: IS_PERCENTAGE_OF_REVENUE | C19: IC214 | D19: SEG0001085569 Segment
A20: Rest Of World | B20: IS_PERCENTAGE_OF_REVENUE | C20: IC214 | D20: SEG0001085570 Segment | H20: 8
A21: % of Total | B21: IS_PERCENTAGE_OF_REVENUE | C21: IC214 | D21: SEG0001085570 Segment
A22: Canada | B22: IS_PERCENTAGE_OF_REVENUE | C22: IC214 | D22: SEG0001085571 Segment | H22: 24
A23: % of Total | B23: IS_PERCENTAGE_OF_REVENUE | C23: IC214 | D23: SEG0001085571 Segment
A25: Total Non-Current Assets | B25: BS_TOTAL_NON_CURRENT_ASSETS | C25: BM321 | E25: 206.083 | F25: 326.829 | G25: 464.489 | H25: 491.721
A26: United States | B26: BS_TOTAL_NON_CURRENT_ASSETS | C26: BM321 | D26: SEG0001085575 Segment | H26: 346.383
A27: % of Total | B27: BS_TOTAL_NON_CURRENT_ASSETS | C27: BM321 | D27: SEG0001085575 Segment | H27: 70.442995
A28: Canada | B28: BS_TOTAL_NON_CURRENT_ASSETS | C28: BM321 | D28: SEG0001085571 Segment | H28: 4.082
A29: % of Total | B29: BS_TOTAL_NON_CURRENT_ASSETS | C29: BM321 | D29: SEG0001085571 Segment | H29: 0.83014555
A30: New Zealand | B30: BS_TOTAL_NON_CURRENT_ASSETS | C30: BM321 | D30: SEG0001085568 Segment | H30: 42.09
A31: % of Total | B31: BS_TOTAL_NON_CURRENT_ASSETS | C31: BM321 | D31: SEG0001085568 Segment | H31: 8.559732
A32: Source: Bloomberg

Sheet Segments
B2: Segments
B4: Regions | D4: Weight | E4: 2020 | F4: =+E4+1 -> 2021 | G4: =+F4+1 -> 2022 | H4: =+G4+1 -> 2023 | I4: =+H4+1 -> 2024 | J4: ="CAGR "&$G$4&" - "&$I$4 -> CAGR 2022 - 2024 | K4: 2021 | L4: =+K4+1 -> 2022 | M4: =+L4+1 -> 2023 | N4: =+M4+1 -> 2024
B6: United States | D6: =IFERROR(I6/SUM($I$6:$I$12),"") -> 0.61512469 | F6: =VLOOKUP($B6,Regions!$L$3:$P$8,Regions!M2,FALSE) -> 45.75 | G6: =VLOOKUP($B6,Regions!$L$3:$P$8,Regions!N2,FALSE) -> 164.593 | H6: =VLOOKUP($B6,Regions!$L$3:$P$8,Regions!O2,FALSE) -> 184.748 | I6: =VLOOKUP($B6,Regions!$L$3:$P$8,Regions!P2,FALSE) -> 268.326 | J6: =IFERROR((I6/G6)^(1/COUNT($G$4:$I$4))-1,"") -> 0.17692954 | K6: =IFERROR(F6-E6/E6,"") | L6: =IFERROR(G6-F6/F6,"") -> 163.593 | M6: =IFERROR((H6-G6)/G6,"") -> 0.12245357 | N6: =IFERROR((I6-H6)/H6,"") -> 0.4523892
B7: Japan | D7: =IFERROR(I7/SUM($I$6:$I$12),"") -> 0.070341621 | F7: =VLOOKUP($B7,Regions!$L$3:$P$8,Regions!M$2,FALSE) -> 0.769 | G7: =VLOOKUP($B7,Regions!$L$3:$P$8,Regions!N$2,FALSE) -> 15.306 | H7: =VLOOKUP($B7,Regions!$L$3:$P$8,Regions!O$2,FALSE) | I7: =VLOOKUP($B7,Regions!$L$3:$P$8,Regions!P$2,FALSE) -> 30.684 | J7: =IFERROR((I7/G7)^(1/COUNT($G$4:$I$4))-1,"") -> 0.26090806 | K7: =IFERROR(F7-E7/E7,"") | L7: =IFERROR(G7-F7/F7,"") -> 14.306 | M7: =IFERROR((H7-G7)/G7,"") | N7: =IFERROR((I7-H7)/H7,"")
B8: Germany | D8: =IFERROR(I8/SUM($I$6:$I$12),"") | F8: =VLOOKUP($B8,Regions!$L$3:$P$8,Regions!M$2,FALSE) -> 9.77 | G8: =VLOOKUP($B8,Regions!$L$3:$P$8,Regions!N$2,FALSE) -> 5.26 | H8: =VLOOKUP($B8,Regions!$L$3:$P$8,Regions!O$2,FALSE) -> 5.503 | I8: =VLOOKUP($B8,Regions!$L$3:$P$8,Regions!P$2,FALSE) | J8: =IFERROR((I8/E8)^(1/COUNT($E$4:$I$4))-1,"") | K8: =IFERROR(F8-E8/E8,"") | L8: =IFERROR(G8-F8/F8,"") -> 4.26 | M8: =IFERROR(H8-G8/G8,"") -> 4.503 | N8: =IFERROR((I8-H8)/H8,"")
B9: Canada | D9: =IFERROR(I9/SUM($I$6:$I$12),"") -> 0.23930456 | F9: =VLOOKUP($B9,Regions!$L$3:$P$8,Regions!M$2,FALSE) | G9: =VLOOKUP($B9,Regions!$L$3:$P$8,Regions!N$2,FALSE) | H9: =VLOOKUP($B9,Regions!$L$3:$P$8,Regions!O$2,FALSE) -> 36.116 | I9: =VLOOKUP($B9,Regions!$L$3:$P$8,Regions!P$2,FALSE) -> 104.388 | J9: =IFERROR((I9/E9)^(1/COUNT($E$4:$I$4))-1,"") | K9: =IFERROR(F9-E9/E9,"") | L9: =IFERROR(G9-F9/F9,"") | M9: =IFERROR(H9-G9/G9,"") | N9: =IFERROR((I9-H9)/H9,"") -> 1.8903533
B10: Rest Of World | D10: =IFERROR(I10/SUM($I$6:$I$12),"") -> 0.075229131 | F10: =VLOOKUP($B10,Regions!$L$3:$P$8,Regions!M$2,FALSE) -> 5.948 | G10: =VLOOKUP($B10,Regions!$L$3:$P$8,Regions!N$2,FALSE) -> 25.837 | H10: =VLOOKUP($B10,Regions!$L$3:$P$8,Regions!O$2,FALSE) -> 18.225 | I10: =VLOOKUP($B10,Regions!$L$3:$P$8,Regions!P$2,FALSE) -> 32.816 | J10: =IFERROR((I10/E10)^(1/COUNT($E$4:$I$4))-1,"") | K10: =IFERROR(F10-E10/E10,"") | L10: =IFERROR(G10-F10/F10,"") -> 24.837 | M10: =IFERROR(H10-G10/G10,"") -> 17.225 | N10: =IFERROR((I10-H10)/H10,"") -> 0.80060357
D11: =IFERROR(I11/SUM($I$6:$I$12),"") -> 0
D12: =IFERROR(I12/SUM($I$6:$I$12),"") -> 0
B13: Total | D13: =SUM(D6:D12) -> 1 | E13: =SUM(E6:E10) -> 0 | F13: =SUM(F6:F10) -> 62.237 | G13: =SUM(G6:G10) -> 210.996 | H13: =SUM(H6:H10) -> 244.592 | I13: =SUM(I6:I10) -> 436.214 | J13: =IFERROR((I13/G13)^(1/COUNT($G$4:$I$4))-1,"") -> 0.27391893 | K13: =IFERROR(F13-E13/E13,"") | L13: =IFERROR(G13-F13/F13,"") -> 209.996 | M13: =IFERROR((H13-G13)/G13,"") -> 0.15922577 | N13: =IFERROR((I13-H13)/H13,"") -> 0.78343527
B15: Segments | D15: Weight | E15: 2020 | F15: =+E15+1 -> 2021 | G15: =+F15+1 -> 2022 | H15: =+G15+1 -> 2023 | I15: =+H15+1 -> 2024 | J15: ="CAGR "&$E$4&" - "&$I$4 -> CAGR 2020 - 2024 | K15: 2021 | L15: =+K15+1 -> 2022 | M15: =+L15+1 -> 2023 | N15: =+M15+1 -> 2024
B17: Launch Service | D17: =IFERROR(I17/SUM($I$17:$I$21),"") -> 0.28741856 | F17: =VLOOKUP($B17,'Segments - Inputs'!$J$3:$N$5,'Segments - Inputs'!K$2,FALSE) -> 38.971 | G17: =VLOOKUP($B17,'Segments - Inputs'!$J$3:$N$5,'Segments - Inputs'!L$2,FALSE) -> 60.686 | H17: =VLOOKUP($B17,'Segments - Inputs'!$J$3:$N$5,'Segments - Inputs'!M$2,FALSE) -> 71.894 | I17: =VLOOKUP($B17,'Segments - Inputs'!$J$3:$N$5,'Segments - Inputs'!N$2,FALSE) -> 125.376 | J17: =IFERROR((I17/E17)^(1/COUNT($E$4:$I$4))-1,"") | K17: =IFERROR((F17-E17)/E17,"") | L17: =IFERROR((G17-F17)/F17,"") -> 0.55720921 | M17: =IFERROR((H17-G17)/G17,"") -> 0.1846884 | N17: =IFERROR((I17-H17)/H17,"") -> 0.74390074
B18: Space System | D18: =IFERROR(I18/SUM($I$17:$I$21),"") -> 0.71258144 | F18: =VLOOKUP($B18,'Segments - Inputs'!$J$3:$N$5,'Segments - Inputs'!K$2,FALSE) -> 23.266 | G18: =VLOOKUP($B18,'Segments - Inputs'!$J$3:$N$5,'Segments - Inputs'!L$2,FALSE) -> 150.31 | H18: =VLOOKUP($B18,'Segments - Inputs'!$J$3:$N$5,'Segments - Inputs'!M$2,FALSE) -> 172.698 | I18: =VLOOKUP($B18,'Segments - Inputs'!$J$3:$N$5,'Segments - Inputs'!N$2,FALSE) -> 310.838 | J18: =IFERROR((I18/E18)^(1/COUNT($E$4:$I$4))-1,"") | K18: =IFERROR((F18-E18)/E18,"") | L18: =IFERROR((G18-F18)/F18,"") -> 5.4605003 | M18: =IFERROR((H18-G18)/G18,"") -> 0.14894551 | N18: =IFERROR((I18-H18)/H18,"") -> 0.79989346
D19: =IFERROR(I19/SUM($I$17:$I$21),"") -> 0 | J19: =IFERROR((I19/E19)^(1/COUNT($E$4:$I$4))-1,"") | K19: =IFERROR((F19-E19)/E19,"") | L19: =IFERROR((G19-F19)/F19,"") | M19: =IFERROR((H19-G19)/G19,"") | N19: =IFERROR((I19-H19)/H19,"")
D20: =IFERROR(I20/SUM($I$17:$I$21),"") -> 0 | J20: =IFERROR((I20/E20)^(1/COUNT($E$4:$I$4))-1,"") | K20: =IFERROR((F20-E20)/E20,"") | L20: =IFERROR((G20-F20)/F20,"") | M20: =IFERROR((H20-G20)/G20,"") | N20: =IFERROR((I20-H20)/H20,"")
D21: =IFERROR(I21/SUM($I$17:$I$21),"") -> 0 | J21: =IFERROR((I21/E21)^(1/COUNT($E$4:$I$4))-1,"") | K21: =IFERROR((F21-E21)/E21,"") | L21: =IFERROR((G21-F21)/F21,"") | M21: =IFERROR((H21-G21)/G21,"") | N21: =IFERROR((I21-H21)/H21,"")
B22: Total | D22: =SUM(D17:D21) -> 1 | E22: =SUM(E17:E21) -> 0 | F22: =SUM(F17:F21) -> 62.237 | G22: =SUM(G17:G21) -> 210.996 | H22: =SUM(H17:H21) -> 244.592 | I22: =SUM(I17:I21) -> 436.214 | J22: =IFERROR((I22/E22)^(1/COUNT($E$4:$I$4))-1,"") | K22: =IFERROR((F22-E22)/E22,"") | L22: =IFERROR((G22-F22)/F22,"") -> 2.390202 | M22: =IFERROR((H22-G22)/G22,"") -> 0.15922577 | N22: =IFERROR((I22-H22)/H22,"") -> 0.78343527
B24: Categories | D24: Description | J24: Graphs
B26: Launch Service | D26: Rocket Lab provides small satellite launch solutions using its Electron rocket for payloads up to 300 kg, with a focus on flexibility and reusability, and is developing the Neutron rocket for larger payloads.
B27: Space System | D27: Rocket Lab offers integrated satellite solutions through its Photon platform, providing end-to-end services from satellite design and build to launch and operations, catering to both commercial and government clients.
B29: =IF(B20=0,"",B20)
B30: =IF(B21=0,"",B21)
B32: Products | D32: Weight | E32: 2020 | F32: =+E32+1 -> 2021 | G32: =+F32+1 -> 2022 | H32: =+G32+1 -> 2023 | I32: =+H32+1 -> 2024 | J32: =I32+1 -> 2025 | K32: =+J32+1 -> 2026 | L32: =+K32+1 -> 2027 | M32: =+L32+1 -> 2028 | N32: =+M32+1 -> 2029 | O32: =+N32+1 -> 2030 | P32: =+O32+1 -> 2031 | Q32: =+P32+1 -> 2032 | R32: =+Q32+1 -> 2033 | ... T32: =+S32+1 -> 2035
D34: =IFERROR(I34/$I$13,"") -> 0
D36: =IFERROR(I36/$I$13,"") -> 0
F37: =IFERROR((F36-E36)/E36,"") | G37: =IFERROR((G36-F36)/F36,"") | H37: =IFERROR((H36-G36)/G36,"") | I37: =IFERROR((I36-H36)/H36,"")
B38: Product 3 | D38: =IFERROR(I38/$I$13,"") -> 0 | J38: =I38*(1+J39) -> 0 | K38: =J38*(1+K39) -> 0 | L38: =K38*(1+L39) -> 0 | M38: =L38*(1+M39) -> 0 | N38: =M38*(1+N39) -> 0 | O38: =N38*(1+O39) -> 0 | P38: =O38*(1+P39) -> 0 | Q38: =P38*(1+Q39) -> 0 | ... T38: =S38*(1+T39) -> 0
F39: =IFERROR(F38-E38/E38,"") | G39: =IFERROR(G38-F38/F38,"") | H39: =IFERROR(H38-G38/G38,"") | I39: =IFERROR(I38-H38/H38,"")
B40: Product 4 | D40: =IFERROR(I40/$I$13,"") -> 0 | J40: =I40*(1+J41) -> 0 | K40: =J40*(1+K41) -> 0 | L40: =K40*(1+L41) -> 0 | M40: =L40*(1+M41) -> 0 | N40: =M40*(1+N41) -> 0 | O40: =N40*(1+O41) -> 0 | P40: =O40*(1+P41) -> 0 | Q40: =P40*(1+Q41) -> 0 | ... T40: =S40*(1+T41) -> 0
F41: =IFERROR(F40-E40/E40,"") | G41: =IFERROR(G40-F40/F40,"") | H41: =IFERROR(H40-G40/G40,"") | I41: =IFERROR(I40-H40/H40,"")
B42: Product 5 | D42: =IFERROR(I42/$I$13,"") -> 0 | J42: =I42*(1+J43) -> 0 | K42: =J42*(1+K43) -> 0 | L42: =K42*(1+L43) -> 0 | M42: =L42*(1+M43) -> 0 | N42: =M42*(1+N43) -> 0 | O42: =N42*(1+O43) -> 0 | P42: =O42*(1+P43) -> 0 | Q42: =P42*(1+Q43) -> 0 | ... T42: =S42*(1+T43) -> 0
F43: =IFERROR(F42-E42/E42,"") | G43: =IFERROR(G42-F42/F42,"") | H43: =IFERROR(H42-G42/G42,"") | I43: =IFERROR(I42-H42/H42,"")
B44: Total | D44: =SUM(D34:D42) -> 0 | E44: =SUM(E34:E42) -> 0 | F44: =SUM(F34:F42) -> 0 | G44: =SUM(G34:G42) -> 0 | H44: =SUM(H34:H42) -> 0 | I44: =SUM(I34:I42) -> 0 | J44: =SUM(J34:J42) -> 0 | K44: =SUM(K34:K42) -> 0 | ... T44: =SUM(T34:T42) -> 0
B46: Company's Strategy / Extra Notes

Sheet Industry
B2: Industry Overview
B4: Sales Growth Forecast | E4: Weight | F4: 2025 | G4: =+F4+1 -> 2026 | H4: =+G4+1 -> 2027 | I4: =+H4+1 -> 2028 | J4: =+I4+1 -> 2029 | K4: =+J4+1 -> 2030 | L4: =+K4+1 -> 2031 | M4: =+L4+1 -> 2032 | N4: =+M4+1 -> 2033 | ... P4: =+O4+1 -> 2035 | Q4: ="CAGR "&$F$4&" - "&$P$4 -> CAGR 2025 - 2035 | R4: Sources
B11: Weighted Average | E11: =SUM(E6:E10) -> 0 | F11: =SUMPRODUCT(F6:F10,$E$6:$E$10) -> 0 | G11: =SUMPRODUCT(G6:G10,$E$6:$E$10) -> 0 | H11: =SUMPRODUCT(H6:H10,$E$6:$E$10) -> 0 | I11: =SUMPRODUCT(I6:I10,$E$6:$E$10) -> 0 | J11: =SUMPRODUCT(J6:J10,$E$6:$E$10) -> 0 | K11: =SUMPRODUCT(K6:K10,$E$6:$E$10) -> 0 | L11: =SUMPRODUCT(L6:L10,$E$6:$E$10) -> 0 | M11: =SUMPRODUCT(M6:M10,$E$6:$E$10) -> 0 | ... P11: =SUMPRODUCT(P6:P10,$E$6:$E$10) -> 0 | Q11: =IFERROR(((1+F11)*(1+G11)*(1+H11)*(1+I11)*(1+J11)*(1+K11)*(1+L11)*(1+M11)*(1+N11)*(1+O11)*(1+P11))^(1/COUNT($F$4:$P$4))-1,"") -> 0
B13: Key Drivers | E13: Description
B20: Industry Trends | E20: Description
B26: Market Share | E26: Headquarters | G26: Revenues | H26: (in MM of USD) | I26: Market Share
B28: {=+_FV(#REF!,"Name")} -> #VALUE! | G28: {=TRANSPOSE(Peers!D97:N97)} -> 436.2 | I28: =IFERROR(G28/$G$40,"")
B29: {=+_FV(Peers!A8,"Name")} -> #VALUE! | G29: 0 | I29: =IFERROR(G29/$G$40,"")
B30: {=+_FV(Peers!A9,"Name")} -> #VALUE! | G30: 0 | I30: =IFERROR(G30/$G$40,"")
B31: {=+_FV(Peers!A10,"Name")} -> #VALUE! | G31: 0 | I31: =IFERROR(G31/$G$40,"")
B32: {=+_FV(Peers!A11,"Name")} -> #VALUE! | G32: 0 | I32: =IFERROR(G32/$G$40,"")
B33: {=+_FV(Peers!A12,"Name")} -> #VALUE! | G33: 0 | I33: =IFERROR(G33/$G$40,"")
B34: {=+_FV(Peers!A13,"Name")} -> #VALUE! | G34: 0 | I34: =IFERROR(G34/$G$40,"")
B35: {=+_FV(Peers!A14,"Name")} -> #VALUE! | G35: 0 | I35: =IFERROR(G35/$G$40,"")
B36: {=+_FV(Peers!A15,"Name")} -> #VALUE! | G36: 0 | I36: =IFERROR(G36/$G$40,"")
B37: {=+_FV(Peers!A16,"Name")} -> #VALUE! | G37: 0 | I37: =IFERROR(G37/$G$40,"")
B38: {=+_FV(Peers!A17,"Name")} -> #VALUE! | G38: 0 | I38: =IFERROR(G38/$G$40,"")
B39: Others | E39: -- | G39: =G40-SUM(G28:G38) -> -436.2 | I39: =IFERROR(G39/$G$40,"")
B40: Industry Size | E40: -- | I40: 1
B42: Porter's Five Forces Analysis | E42: Rating | H42: Graph
B44: Threat of New Entrants | E44: =IFERROR(AVERAGE(E45:E50),"")
B45: Economies of scale
B46: Product differentiation
B47: Capital requirements
B48: Access to distribution channels
B49: Regulations
B50: Switching costs
B51: Bargaining Power of Suppliers | E51: =IFERROR(AVERAGE(E52:E56),"")
B52: Number of suppliers
B53: Uniqueness
B54: Switching Costs
B55: Forward Integration
B56: Industry Importance
B57: Bargaining Power of Customers | E57: =IFERROR(AVERAGE(E58:E62),"")
B58: Number of buyers
B59: Purchase size
B60: Switching costs
B61: Price sensitivity
B62: Informed buyers
B63: Competitive Rivalry | E63: =IFERROR(AVERAGE(E64:E68),"")
B64: Number of competitors
B65: Industry growth
B66: Similarities in what's offered
B67: Exit barriers
B68: Fixed costs
B69: Threat of Substitutes | E69: =IFERROR(AVERAGE(E70:E74),"")
B70: Relative price performance
B71: Customer willingness to go elsewhere
B72: The sense that products are similar
B73: Availability of close substitutes

Sheet Peers
D3: Revenue Growth | F3: EBITDA Margin | H3: Profit Margin | J3: EV / Revenue | L3: EV / EBITDA | N3: Price / Earnings
B4: Peers | C4: Ticker | D4: =+Inputs!O4&"-"&Inputs!P4 -> 2022-2023 | E4: =+Inputs!P4&"-"&Inputs!Q4 -> 2023-2024 | F4: 2023 | G4: 2024 | H4: =+Inputs!O4&"-"&Inputs!P4 -> 2022-2023 | I4: =+Inputs!P4&"-"&Inputs!Q4 -> 2023-2024 | J4: 2023 | K4: 2024 | L4: 2023 | M4: 2024 | N4: 2023 | O4: 2024
A6: =+D91 -> #REF! | B6: {=IFERROR(_FV(A6,"Name"),"")} | C6: {=IFERROR(_FV(A6,"Ticker symbol",TRUE),"")} | D6: =IFERROR(D94/D93-1,"") -> 0.15924171 | E6: =IFERROR(D97/D94-1,"") -> 0.78331971 | F6: =IFERROR(D95/D94,"") -> -0.72771872 | G6: =IFERROR(D100/D97,"") -> -0.41746905 | H6: =IFERROR(D96/D94,"") -> -0.63041701 | I6: =IFERROR(D105/D97,"") -> -0.3455525 | J6: {=IFERROR((_FV(A6,"Market cap",TRUE)/1000000+D$121-D$111)/D$94,"")} | K6: {=IFERROR((_FV(A6,"Market cap",TRUE)/1000000+D$121-D$111)/D$97,"")} | L6: {=+IFERROR((_FV(A6,"Market cap",TRUE)/1000000+D$121-D$111)/D$95,"")} | M6: {=IFERROR((_FV(A6,"Market cap",TRUE)/1000000+D$121-D$111)/D$100,"")} | N6: {=IFERROR((_FV(A6,"Market cap",TRUE)/1000000)/D$96,"")} | O6: {=IFERROR((_FV(A6,"Market cap",TRUE)/1000000)/D$105,"")}
A8: =+E91 -> PEER 1 | B8: {=IFERROR(_FV(A8,"Name"),"")} | C8: {=+IFERROR(_FV(A8,"Ticker symbol",TRUE),"")} | D8: =+IFERROR(E94/E93-1,"") | E8: =IFERROR(E97/E94-1,"") | F8: =IFERROR(E95/E94,"") | G8: =+IFERROR(E100/E97,"") | H8: =IFERROR(E96/E94,"") | I8: =+IFERROR(E105/E97,"") | J8: {=+IFERROR((_FV(A8,"Market cap",TRUE)/1000000+E$121-E$111)/E$94,"")} | K8: {=IFERROR(+(_FV(A8,"Market cap",TRUE)/1000000+E$121-E$111)/E$97,"")} | L8: {=IFERROR(+(_FV(A8,"Market cap",TRUE)/1000000+E$121-E$111)/E$95,"")} | M8: {=IFERROR(+(_FV(A8,"Market cap",TRUE)/1000000+E$121-E$111)/E$100,"")} | N8: {=IFERROR(+(_FV(A8,"Market cap",TRUE)/1000000)/E$96,"")} | O8: {=IFERROR(+(_FV(A8,"Market cap",TRUE)/1000000)/E$105,"")}
A9: =+F91 -> PEER 2 | B9: {=IFERROR(_FV(A9,"Name"),"")} | C9: {=+IFERROR(_FV(A9,"Ticker symbol",TRUE),"")} | D9: =IFERROR(F94/F93-1,"") | E9: =IFERROR(+F97/F94-1,"") | F9: =IFERROR(F95/F94,"") | G9: =IFERROR(F100/F97,"") | H9: =IFERROR(F96/F94,"") | I9: =+IFERROR(F105/F97,"") | J9: {=IFERROR(+(_FV(A9,"Market cap",TRUE)/1000000+F$121-F$111)/F$94,"")} | K9: {=IFERROR(+(_FV(A9,"Market cap",TRUE)/1000000+F$121-F$111)/F$97,"")} | L9: {=IFERROR(+(_FV(A9,"Market cap",TRUE)/1000000+F$121-F$111)/F$95,"")} | M9: {=IFERROR(+(_FV(A9,"Market cap",TRUE)/1000000+F$121-F$111)/F$100,"")} | N9: {=IFERROR(+(_FV(A9,"Market cap",TRUE)/1000000)/F$96,"")} | O9: {=IFERROR(+(_FV(A9,"Market cap",TRUE)/1000000)/F$105,"")}
A10: =+G91 -> PEER 3 | B10: {=IFERROR(_FV(A10,"Name"),"")} | C10: {=IFERROR(_FV(A10,"Ticker symbol",TRUE),"")} | D10: =+IFERROR(G94/G93-1,"") | E10: =IFERROR(G97/G94-1,"") | F10: =IFERROR(G95/G94,"") | G10: =IFERROR(G100/G97,"") | H10: =IFERROR(G96/G94,"") | I10: =+IFERROR(G105/G97,"") | J10: {=IFERROR(+(_FV(A10,"Market cap",TRUE)/1000000+G$121-G$111)/G$94,"")} | K10: {=IFERROR(+(_FV(A10,"Market cap",TRUE)/1000000+G$121-G$111)/G$97,"")} | L10: {=IFERROR(+(_FV(A10,"Market cap",TRUE)/1000000+G$121-G$111)/G$95,"")} | M10: {=IFERROR(+(_FV(A10,"Market cap",TRUE)/1000000+G$121-G$111)/G$100,"")} | N10: {=IFERROR(+(_FV(A10,"Market cap",TRUE)/1000000)/G$96,"")} | O10: {=IFERROR(+(_FV(A10,"Market cap",TRUE)/1000000)/G$105,"")}
A11: =+H91 -> PEER 4 | B11: {=IFERROR(_FV(A11,"Name"),"")} | C11: {=IFERROR(_FV(A11,"Ticker symbol",TRUE),"")} | D11: =IFERROR(H94/H93-1,"") | E11: =IFERROR(H97/H94-1,"") | F11: =IFERROR(H95/H94,"") | G11: =IFERROR(H100/H97,"") | H11: =IFERROR(H96/H94,"") | I11: =+IFERROR(H105/H102,"") | J11: {=IFERROR((_FV(A11,"Market cap",TRUE)/1000000+H$121-H$111)/H$94,"")} | K11: {=IFERROR(+(_FV(A11,"Market cap",TRUE)/1000000+H$121-H$111)/H$97,"")} | L11: {=IFERROR(+(_FV(A11,"Market cap",TRUE)/1000000+H$121-H$111)/H$95,"")} | M11: {=IFERROR(+(_FV(A11,"Market cap",TRUE)/1000000+H$121-H$111)/H$100,"")} | N11: {=IFERROR(+(_FV(A11,"Market cap",TRUE)/1000000)/H$96,"")} | O11: {=IFERROR(+(_FV(A11,"Market cap",TRUE)/1000000)/H$105,"")}
A12: =+I91 -> PEER 5 | B12: {=IFERROR(_FV(A12,"Name"),"")} | C12: {=IFERROR(_FV(A12,"Ticker symbol",TRUE),"")} | D12: =+IFERROR(I94/I93-1,"") | E12: =IFERROR(I97/I94-1,"") | F12: =IFERROR(I95/I94,"") | G12: =IFERROR(I100/I97,"") | H12: =IFERROR(I96/I94,"") | I12: =+IFERROR(I105/I97,"") | J12: {=IFERROR((_FV(A12,"Market cap",TRUE)/1000000+I$121-I$111)/I$94,"")} | K12: {=IFERROR(+(_FV(A12,"Market cap",TRUE)/1000000+I$121-I$111)/I$97,"")} | L12: {=IFERROR(+(_FV(A12,"Market cap",TRUE)/1000000+I$121-I$111)/I$95,"")} | M12: {=IFERROR(+(_FV(A12,"Market cap",TRUE)/1000000+I$121-I$111)/I$100,"")} | N12: {=IFERROR(+(_FV(A12,"Market cap",TRUE)/1000000)/I$96,"")} | O12: {=IFERROR(+(_FV(A12,"Market cap",TRUE)/1000000)/I$105,"")}
A13: =+J91 -> PEER 6 | B13: {=IFERROR(_FV(A13,"Name"),"")} | C13: {=IFERROR(_FV(A13,"Ticker symbol",TRUE),"")} | D13: =IFERROR(J94/J93-1,"") | E13: =IFERROR(J97/J94-1,"") | F13: =IFERROR(J95/J94,"") | G13: =IFERROR(J100/J97,"") | H13: =IFERROR(J96/J94,"") | I13: =+IFERROR(J105/J97,"") | J13: {=IFERROR(+(_FV(A13,"Market cap",TRUE)/1000000+J$121-J$111)/J$94,"")} | K13: {=IFERROR(+(_FV(A13,"Market cap",TRUE)/1000000+J$121-J$111)/J$97,"")} | L13: {=IFERROR(+(_FV(A13,"Market cap",TRUE)/1000000+J$121-J$111)/J$95,"")} | M13: {=IFERROR(+(_FV(A13,"Market cap",TRUE)/1000000+J$121-J$111)/J$100,"")} | N13: {=IFERROR(+(_FV(A13,"Market cap",TRUE)/1000000)/J$96,"")} | O13: {=IFERROR(+(_FV(A13,"Market cap",TRUE)/1000000)/J$105,"")}
A14: =+K91 -> PEER 7 | B14: {=IFERROR(_FV(A14,"Name"),"")} | C14: {=IFERROR(_FV(A14,"Ticker symbol",TRUE),"")} | D14: =IFERROR(K94/K93-1,"") | E14: =IFERROR(K97/K94-1,"") | F14: =+IFERROR(K95/K94,"") | G14: =IFERROR(K100/K97,"") | H14: =IFERROR(K96/K94,"") | I14: =+IFERROR(K105/K97,"") | J14: {=IFERROR((_FV(A14,"Market cap",TRUE)/1000000+D$121-K$111)/K$94,"")} | K14: {=IFERROR(+(_FV(A14,"Market cap",TRUE)/1000000+D$121-K$111)/K$97,"")} | L14: {=IFERROR(+(_FV(A14,"Market cap",TRUE)/1000000+D$121-K$111)/K$95,"")} | M14: {=IFERROR(+(_FV(A14,"Market cap",TRUE)/1000000+D$121-K$111)/K$100,"")} | N14: {=IFERROR(+(_FV(A14,"Market cap",TRUE)/1000000)/K$96,"")} | O14: {=IFERROR(+(_FV(A14,"Market cap",TRUE)/1000000)/K$105,"")}
A15: =+L91 -> PEER 8 | B15: {=IFERROR(_FV(A15,"Name"),"")} | C15: {=IFERROR(_FV(A15,"Ticker symbol",TRUE),"")} | D15: =+IFERROR(L94/L93,"") | E15: =IFERROR(L97/L94,"") | F15: =IFERROR(L95/L94,"") | G15: =IFERROR(L100/L97,"") | H15: =IFERROR(L96/L94,"") | I15: =+IFERROR(L105/L97,"") | J15: {=IFERROR(+(_FV(A15,"Market cap",TRUE)/1000000+L$121-L$111)/L$94,"")} | K15: {=IFERROR(+(_FV(A15,"Market cap",TRUE)/1000000+L$121-L$111)/L$97,"")} | L15: {=IFERROR(+(_FV(A15,"Market cap",TRUE)/1000000+L$121-L$111)/L$95,"")} | M15: {=IFERROR(+(_FV(A15,"Market cap",TRUE)/1000000+L$121-L$111)/L$100,"")} | N15: {=IFERROR(+(_FV(A15,"Market cap",TRUE)/1000000)/L$96,"")} | O15: {=IFERROR(+(_FV(A15,"Market cap",TRUE)/1000000)/L$105,"")}
A16: =+M91 -> PEER 9 | B16: {=IFERROR(_FV(A16,"Name"),"")} | C16: {=IFERROR(_FV(A16,"Ticker symbol",TRUE),"")} | D16: =IFERROR(M94/M93-1,"") | E16: =IFERROR(M97/M94-1,"") | F16: =IFERROR(M95/M94,"") | G16: =IFERROR(M100/M97,"") | H16: =IFERROR(M96/M94,"") | I16: =+IFERROR(M105/M97,"") | J16: {=IFERROR(+(_FV(A16,"Market cap",TRUE)/1000000+M$121-M$111)/M$94,"")} | K16: {=IFERROR(+(_FV(A16,"Market cap",TRUE)/1000000+M$121-M$111)/M$97,"")} | L16: {=IFERROR(+(_FV(A16,"Market cap",TRUE)/1000000+M$121-M$111)/M$95,"")} | M16: {=IFERROR(+(_FV(A16,"Market cap",TRUE)/1000000+M$121-M$111)/M$100,"")} | N16: {=IFERROR(+(_FV(A16,"Market cap",TRUE)/1000000)/M$96,"")} | O16: {=IFERROR(+(_FV(A16,"Market cap",TRUE)/1000000)/M$105,"")}
A17: =+N91 -> PEER 10 | B17: {=IFERROR(_FV(A17,"Name"),"")} | C17: {=+IFERROR(_FV(A17,"Ticker symbol",TRUE),"")} | D17: =IFERROR(N94/N93-1,"") | E17: =IFERROR(N97/N94-1,"") | F17: =IFERROR(N95/N94,"") | G17: =IFERROR(N100/N97,"") | H17: =IFERROR(N96/N94,"") | I17: =+IFERROR(N105/N97,"") | J17: {=IFERROR(+(_FV(A17,"Market cap",TRUE)/1000000+N$121-N$111)/N$94,"")} | K17: {=IFERROR(+(_FV(A17,"Market cap",TRUE)/1000000+N$121-N$111)/N$97,"")} | L17: {=IFERROR(+(_FV(A17,"Market cap",TRUE)/1000000+N$121-N$111)/N$95,"")} | M17: {=IFERROR(+(_FV(A17,"Market cap",TRUE)/1000000+N$121-N$111)/N$100,"")} | N17: {=IFERROR(+(_FV(A17,"Market cap",TRUE)/1000000)/N$96,"")} | O17: {=IFERROR(+(_FV(A17,"Market cap",TRUE)/1000000)/N$105,"")}
B18: Average | D18: =IFERROR(AVERAGE(D6:D17),"") -> 0.15924171 | E18: =IFERROR(AVERAGE(E6:E17),"") -> 0.78331971 | F18: =IFERROR(AVERAGE(F6:F17),"") -> -0.72771872 | G18: =IFERROR(AVERAGE(G6:G17),"") -> -0.41746905 | H18: =IFERROR(AVERAGE(H6:H17),"") -> -0.63041701 | I18: =IFERROR(AVERAGE(I6:I17),"") -> -0.3455525 | J18: =IFERROR(AVERAGE(J6:J17),"") | K18: =IFERROR(AVERAGE(K6:K17),"") | ... O18: =IFERROR(AVERAGE(O6:O17),"")
B19: Deviation from Average | D19: =IFERROR(+D18-D6,"") -> 0 | E19: =IFERROR(E18-E6,"") -> 0 | F19: =+IFERROR(F18-F6,"") -> 0 | G19: =IFERROR(G18-G6,"") -> 0 | H19: =IFERROR(+H6-H18,"") -> 0 | I19: =+IFERROR(I6-I18,"") -> 0 | J19: =+IFERROR(J6-J18,"") | K19: =+IFERROR(K6-K18,"") | L19: =IFERROR(+L6-L18,"") | M19: =IFERROR(M6-M18,"") | N19: =IFERROR(+N6-N18,"") | O19: =IFERROR(+O6-O18,"")
D21: Trading Multiple | G21: Net | H21: Preferred | I21: Non-Controlling | J21: Equity Value | M21: Implied Upside (Downside)
B22: Implied Share Price | D22: Revenue | E22: EBITDA | F22: P/E | G22: Debt | H22: Stock | I22: Interest | J22: Revenue | K22: EBITDA | L22: P/E | M22: Revenue | N22: EBITDA | O22: P/E | P22: Current Price
B24: Second Minimum | D24: =IFERROR(SMALL(K6:K17,2),"") | E24: =IFERROR(SMALL(M6:M17,2),"") | F24: =IFERROR(SMALL(O6:O17,2),"") | G24: =-Inputs!$Q$99+Inputs!$Q$100 -> 40.7 | H24: =+Inputs!$Q$101 -> 0 | I24: =+Inputs!$Q$102 -> 0 | J24: =IFERROR(+D24*$D$97+G24+H24+I24,"") | K24: =IFERROR(E24*$D$100+G24+H24+I24,"") | L24: =IFERROR(F24*$D$105,"") | M24: {=IFERROR(+(J24/_FV($A$6,"Shares outstanding",TRUE)*1000000)/$P$24-1,"")} | N24: {=IFERROR((+K24/_FV($A$6,"Shares outstanding",TRUE)*1000000)/$P$24-1,"")} | O24: {=IFERROR(+(L24/_FV($A$6,"Shares outstanding",TRUE)*1000000)/$P$24-1,"")} | P24: {=+_FV(A6,"Price")} -> #VALUE!
B25: Average | D25: =+IFERROR(AVERAGE(K6:K17),"") | E25: =IFERROR(+AVERAGE(M6:M17),"") | F25: =IFERROR(+AVERAGE(O6:O17),"") | G25: =-Inputs!$Q$99+Inputs!$Q$100 -> 40.7 | H25: =+Inputs!$Q$101 -> 0 | I25: =+Inputs!$Q$102 -> 0 | J25: =IFERROR(+D25*$D$97+G25+H25+I25,"") | K25: =IFERROR(E25*$D$100+G25+H25+I25,"") | L25: =IFERROR(+F25*$D$105,"") | M25: {=IFERROR(+(J25/_FV($A$6,"Shares outstanding",TRUE)*1000000)/$P$24-1,"")} | N25: {=IFERROR((+K25/_FV($A$6,"Shares outstanding",TRUE)*1000000)/$P$24-1,"")} | O25: {=IFERROR(+(L25/_FV($A$6,"Shares outstanding",TRUE)*1000000)/$P$24-1,"")}
B26: Median | D26: =IFERROR(MEDIAN(K6:K17),"") | E26: =IFERROR(MEDIAN(M6:M17),"") | F26: =IFERROR(MEDIAN(O6:O17),"") | G26: =-Inputs!$Q$99+Inputs!$Q$100 -> 40.7 | H26: =+Inputs!$Q$101 -> 0 | I26: =+Inputs!$Q$102 -> 0 | J26: =IFERROR(D26*$D$97+G26+H26+I26,"") | K26: =IFERROR(E26*$D$100+G26+H26+I26,"") | L26: =IFERROR(+F26*$D$105,"") | M26: {=IFERROR(+(J26/_FV($A$6,"Shares outstanding",TRUE)*1000000)/$P$24-1,"")} | N26: {=IFERROR((+K26/_FV($A$6,"Shares outstanding",TRUE)*1000000)/$P$24-1,"")} | O26: {=+IFERROR((L26/_FV($A$6,"Shares outstanding",TRUE)*1000000)/$P$24-1,"")}
B27: Second Maximum | D27: =IFERROR(LARGE(K6:K17,2),"") | E27: =IFERROR(LARGE(M6:M17,2),"") | F27: =IFERROR(LARGE(O6:O17,2),"") | G27: =-Inputs!$Q$99+Inputs!$Q$100 -> 40.7 | H27: =+Inputs!$Q$101 -> 0 | I27: =+Inputs!$Q$102 -> 0 | J27: =IFERROR(+D27*$D$97+G27+H27+I27,"") | K27: =IFERROR(E27*$D$100+G27+H27+I27,"") | L27: =IFERROR(+F27*$D$105,"") | M27: {=IFERROR(+(J27/_FV($A$6,"Shares outstanding",TRUE)*1000000)/$P$24-1,"")} | N27: {=IFERROR((+K27/_FV($A$6,"Shares outstanding",TRUE)*1000000)/$P$24-1,"")} | O27: {=IFERROR(+(L27/_FV($A$6,"Shares outstanding",TRUE)*1000000)/$P$24-1,"")}
B29: Profitability | D29: =+LEFT(B6, FIND(" ", B6 & " ") - 1) | E29: =+LEFT(B8, FIND(" ", B8 & " ") - 1) | F29: =+LEFT(B9, FIND(" ", B9 & " ") - 1) | G29: =+LEFT(B10, FIND(" ", B10 & " ") - 1) | H29: =+LEFT(B11, FIND(" ", B11 & " ") - 1) | I29: =+LEFT(B12, FIND(" ", B12 & " ") - 1) | J29: =+LEFT(C12, FIND(" ", C12 & " ") - 1) | K29: =+LEFT(B14, FIND(" ", B14 & " ") - 1) | L29: =+LEFT(B15, FIND(" ", B15 & " ") - 1) | M29: =+LEFT(B16, FIND(" ", B16 & " ") - 1) | N29: =+LEFT(B17, FIND(" ", B17 & " ") - 1) | O29: Average
B31: Operating Margin | D31: =IFERROR(D101/D97,"") -> -0.34440624 | E31: =IFERROR(E101/E97,"") | F31: =IFERROR(F101/F97,"") | G31: =IFERROR(G101/G97,"") | H31: =IFERROR(H101/H97,"") | I31: =IFERROR(I101/I97,"") | J31: =IFERROR(J101/J97,"") | K31: =IFERROR(K101/K97,"") | ... N31: =IFERROR(N101/N97,"") | O31: =IFERROR(+AVERAGE(D31:N31),"") -> -0.34440624
B32: Net Income Margin | D32: =IFERROR(D105/D97,"") -> -0.3455525 | E32: =IFERROR(E105/E97,"") | F32: =IFERROR(F105/F97,"") | G32: =IFERROR(G105/G97,"") | H32: =IFERROR(H105/H97,"") | I32: =IFERROR(I105/I97,"") | J32: =IFERROR(J105/J97,"") | K32: =IFERROR(K105/K97,"") | ... N32: =IFERROR(N105/N97,"") | O32: =IFERROR(+AVERAGE(D32:N32),"") -> -0.3455525
B33: ROA (%) | D33: =IFERROR(D105/D117,"") -> -0.12727349 | E33: =IFERROR(E105/E117,"") | F33: =IFERROR(F105/F117,"") | G33: =IFERROR(G105/G117,"") | H33: =IFERROR(H105/H117,"") | I33: =IFERROR(I105/I117,"") | J33: =IFERROR(J105/J117,"") | K33: =IFERROR(K105/K117,"") | ... N33: =IFERROR(N105/N117,"") | O33: =IFERROR(+AVERAGE(D33:N33),"") -> -0.12727349
B34: Financial Cost of Debt | D34: =IFERROR(+(D102/D121)*(1-(D104/D103)),"") -> 0.008749659 | E34: =IFERROR(+(E102/E121)*(1-(E104/E103)),"") | F34: =IFERROR(+(F102/F121)*(1-(F104/F103)),"") | G34: =IFERROR(+(G102/G121)*(1-(G104/G103)),"") | H34: =IFERROR(+(H102/H121)*(1-(H104/H103)),"") | I34: =IFERROR(+(I102/I121)*(1-(I104/I103)),"") | J34: =IFERROR(+(J102/J121)*(1-(J104/J103)),"") | K34: =IFERROR(+(K102/K121)*(1-(K104/K103)),"") | ... N34: =IFERROR(+(N102/N121)*(1-(N104/N103)),"") | O34: =IFERROR(+AVERAGE(D34:N34),"") -> 0.008749659
B35: Return on Equity (RoE) | D35: =IFERROR(+D105/D122,"") -> -0.39416841 | E35: =IFERROR(+E105/E122,"") | F35: =IFERROR(+F105/F122,"") | G35: =IFERROR(+G105/G122,"") | H35: =IFERROR(+H105/H122,"") | I35: =IFERROR(+I105/I122,"") | J35: =IFERROR(+J105/J122,"") | K35: =IFERROR(+K105/K122,"") | ... N35: =IFERROR(+N105/N122,"") | O35: =IFERROR(+AVERAGE(D35:N35),"") -> -0.39416841
B36: Return on Invested Capital (ROIC) | D36: =IFERROR(+D105/(D121+D122),"") -> -0.17901425 | E36: =IFERROR(+E105/(E121+E122),"") | F36: =IFERROR(+F105/(F121+F122),"") | G36: =IFERROR(+G105/(G121+G122),"") | H36: =IFERROR(+H105/(H121+H122),"") | I36: =IFERROR(+I105/(I121+I122),"") | J36: =IFERROR(+J105/(J121+J122),"") | K36: =IFERROR(+K105/(K121+K122),"") | ... N36: =IFERROR(+N105/(N121+N122),"") | O36: =IFERROR(+AVERAGE(D36:N36),"") -> -0.17901425
B38: Solvency | D38: =+D29 | E38: =+E29 | F38: =+F29 | G38: =+G29 | H38: =+H29 | I38: =+I29 | J38: =+J29 | K38: =+K29 | ... O38: =+O29 -> Average
B40: Debt/Assets | D40: =IFERROR(D121/D117,"") -> 0.38807735 | E40: =IFERROR(E121/E117,"") | F40: =IFERROR(F121/F117,"") | G40: =IFERROR(G121/G117,"") | H40: =IFERROR(H121/H117,"") | I40: =IFERROR(I121/I117,"") | J40: =IFERROR(J121/J117,"") | K40: =IFERROR(K121/K117,"") | ... N40: =IFERROR(N121/N117,"") | O40: =IFERROR(+AVERAGE(D40:N40),"") -> 0.38807735
B41: Net Debt/EBITDA | D41: =IFERROR(+(D121-D111)/D100,"") -> -1.0356947 | E41: =IFERROR(+(E121-E111)/E100,"") | F41: =IFERROR(+(F121-F111)/F100,"") | G41: =IFERROR(+(G121-G111)/G100,"") | H41: =IFERROR(+(H121-H111)/H100,"") | I41: =IFERROR(+(I121-I111)/I100,"") | J41: =IFERROR(+(J121-J111)/J100,"") | K41: =IFERROR(+(K121-K111)/K100,"") | ... N41: =IFERROR(+(N121-N111)/N100,"") | O41: =IFERROR(+AVERAGE(D41:N41),"") -> -1.0356947
B42: Interest Coverage Ratio | D42: =IFERROR(D101/D102,"") -> -37.5575 | E42: =IFERROR(E101/E102,"") | F42: =IFERROR(F101/F102,"") | G42: =IFERROR(G101/G102,"") | H42: =IFERROR(H101/H102,"") | I42: =IFERROR(I101/I102,"") | J42: =IFERROR(J101/J102,"") | K42: =IFERROR(K101/K102,"") | ... N42: =IFERROR(N101/N102,"") | O42: =IFERROR(+AVERAGE(D42:N42),"") -> -37.5575
B44: Liquidity | D44: =+D29 | E44: =+E29 | F44: =+F29 | G44: =+G29 | H44: =+H29 | I44: =+I29 | J44: =+J29 | K44: =+K29 | ... O44: =+O29 -> Average
B46: Cash Ratio | D46: =IFERROR(D111/D119,"") -> 0.7982327 | E46: =IFERROR(E111/E119,"") | F46: =IFERROR(F111/F119,"") | G46: =IFERROR(G111/G119,"") | H46: =IFERROR(H111/H119,"") | I46: =IFERROR(I111/I119,"") | J46: =IFERROR(J111/J119,"") | K46: =IFERROR(K111/K119,"") | ... N46: =IFERROR(N111/N119,"") | O46: =IFERROR(+AVERAGE(D46:N46),"") -> 0.7982327
B47: Quick Ratio | D47: =IFERROR(+(D111+D112)/D119,"") -> 0.90544919 | E47: =IFERROR(+(E111+E112)/E119,"") | F47: =IFERROR(+(F111+F112)/F119,"") | G47: =IFERROR(+(G111+G112)/G119,"") | H47: =IFERROR(+(H111+H112)/H119,"") | I47: =IFERROR(+(I111+I112)/I119,"") | J47: =IFERROR(+(J111+J112)/J119,"") | K47: =IFERROR(+(K111+K112)/K119,"") | ... N47: =IFERROR(+(N111+N112)/N119,"") | O47: =IFERROR(+AVERAGE(D47:N47),"") -> 0.90544919
B48: Current Ratio | D48: =IFERROR(D115/D119,"") -> 2.0400589 | E48: =IFERROR(E115/E119,"") | F48: =IFERROR(F115/F119,"") | G48: =IFERROR(G115/G119,"") | H48: =IFERROR(H115/H119,"") | I48: =IFERROR(I115/I119,"") | J48: =IFERROR(J115/J119,"") | K48: =IFERROR(K115/K119,"") | ... N48: =IFERROR(N115/N119,"") | O48: =IFERROR(+AVERAGE(D48:N48),"") -> 2.0400589
B50: Activity | D50: =+D29 | E50: =+E29 | F50: =+F29 | G50: =+G29 | H50: =+H29 | I50: =+I29 | J50: =+J29 | K50: =+K29 | ... O50: =+O29 -> Average
B52: Inventory Turnover | D52: =IFERROR(D98/(AVERAGE(D113:D114)),"") -> 2.8202643 | E52: =IFERROR(E98/(AVERAGE(E113:E114)),"") | F52: =IFERROR(F98/(AVERAGE(F113:F114)),"") | G52: =IFERROR(G98/(AVERAGE(G113:G114)),"") | H52: =IFERROR(H98/(AVERAGE(H113:H114)),"") | I52: =IFERROR(I98/(AVERAGE(I113:I114)),"") | J52: =IFERROR(J98/(AVERAGE(J113:J114)),"") | K52: =IFERROR(K98/(AVERAGE(K113:K114)),"") | ... N52: =IFERROR(N98/(AVERAGE(N113:N114)),"") | O52: =IFERROR(+AVERAGE(D52:N52),"") -> 2.8202643
B53: Acc. Receivable Turnover | D53: =IFERROR(D97/D112,"") -> 11.983516 | E53: =IFERROR(E97/E112,"") | F53: =IFERROR(F97/F112,"") | G53: =IFERROR(G97/G112,"") | H53: =IFERROR(H97/H112,"") | I53: =IFERROR(I97/I112,"") | J53: =IFERROR(J97/J112,"") | K53: =IFERROR(K97/K112,"") | ... N53: =IFERROR(N97/N112,"") | O53: =IFERROR(+AVERAGE(D53:N53),"") -> 11.983516
B54: Payables Turnover | D54: =IFERROR(D98/D118,"") -> 4.4151724 | E54: =IFERROR(E98/E118,"") | F54: =IFERROR(F98/F118,"") | G54: =IFERROR(G98/G118,"") | H54: =IFERROR(H98/H118,"") | I54: =IFERROR(I98/I118,"") | J54: =IFERROR(J98/J118,"") | K54: =IFERROR(K98/K118,"") | ... N54: =IFERROR(N98/N118,"") | O54: =IFERROR(+AVERAGE(D54:N54),"") -> 4.4151724
B55: Fixed Asset Turnover | D55: =IFERROR(D97/D116,"") -> 1.659186 | E55: =IFERROR(E97/E116,"") | F55: =IFERROR(F97/F116,"") | G55: =IFERROR(G97/G116,"") | H55: =IFERROR(H97/H116,"") | I55: =IFERROR(I97/I116,"") | J55: =IFERROR(J97/J116,"") | K55: =IFERROR(K97/K116,"") | ... N55: =IFERROR(N97/N116,"") | O55: =IFERROR(+AVERAGE(D55:N55),"") -> 1.659186
B56: Total Asset Turnover | D56: =IFERROR(D97/D117,"") -> 0.36831884 | E56: =IFERROR(E97/E117,"") | F56: =IFERROR(F97/F117,"") | G56: =IFERROR(G97/G117,"") | H56: =IFERROR(H97/H117,"") | I56: =IFERROR(I97/I117,"") | J56: =IFERROR(J97/J117,"") | K56: =IFERROR(K97/K117,"") | ... N56: =IFERROR(N97/N117,"") | O56: =IFERROR(+AVERAGE(D56:N56),"") -> 0.36831884
B57: Cash Cycle (days) | D57: =IFERROR(365/D52+365/D53-365/D54,"") -> 77.209521 | E57: =IFERROR(365/E52+365/E53-365/E54,"") | F57: =IFERROR(365/F52+365/F53-365/F54,"") | G57: =IFERROR(365/G52+365/G53-365/G54,"") | H57: =IFERROR(365/H52+365/H53-365/H54,"") | I57: =IFERROR(365/I52+365/I53-365/I54,"") | J57: =IFERROR(365/J52+365/J53-365/J54,"") | K57: =IFERROR(365/K52+365/K53-365/K54,"") | ... N57: =IFERROR(365/N52+365/N53-365/N54,"") | O57: =IFERROR(+AVERAGE(D57:N57),"") -> 77.209521
B59: Cash Flow | D59: =+D38 | E59: =+E38 | F59: =+F38 | G59: =+G38 | H59: =+H38 | I59: =+I38 | J59: =+J38 | K59: =+K38 | ... O59: =+O38 -> Average
B61: Cash Flow Margin | D61: =IFERROR(D132/D97,"") -> 0.24965612 | E61: =IFERROR(E132/E97,"") | F61: =IFERROR(F132/F97,"") | G61: =IFERROR(G132/G97,"") | H61: =IFERROR(H132/H97,"") | I61: =IFERROR(I132/I97,"") | J61: =IFERROR(J132/J97,"") | K61: =IFERROR(K132/K97,"") | ... N61: =IFERROR(N132/N97,"") | O61: =IFERROR(+AVERAGE(D61:N61),"") -> 0.24965612
B62: Cash Flow to Net Income | D62: =IFERROR(D132/D96,"") -> -0.70622568 | E62: =IFERROR(E132/E96,"") | F62: =IFERROR(F132/F96,"") | G62: =IFERROR(G132/G96,"") | H62: =IFERROR(H132/H96,"") | I62: =IFERROR(I132/I96,"") | J62: =IFERROR(J132/J96,"") | K62: =IFERROR(K132/K96,"") | ... N62: =IFERROR(N132/N96,"") | O62: =IFERROR(+AVERAGE(D62:N62),"") -> -0.70622568
B63: CFO to Net Income | D63: =+IFERROR(D126/D105,"") -> 0.32442115 | E63: =+IFERROR(E126/E105,"") | F63: =+IFERROR(F126/F105,"") | G63: =+IFERROR(G126/G105,"") | H63: =+IFERROR(H126/H105,"") | I63: =+IFERROR(I126/I105,"") | J63: =+IFERROR(J126/J105,"") | K63: =+IFERROR(K126/K105,"") | ... N63: =+IFERROR(N126/N105,"") | O63: =IFERROR(+AVERAGE(D63:N63),"") -> 0.32442115
B64: Net Capex to CFO | D64: =IFERROR(-D127/D126,"") -> -1.1165644 | E64: =IFERROR(-E127/E126,"") | F64: =IFERROR(-F127/F126,"") | G64: =IFERROR(-G127/G126,"") | H64: =IFERROR(-H127/H126,"") | I64: =IFERROR(-I127/I126,"") | J64: =IFERROR(-J127/J126,"") | K64: =IFERROR(-K127/K126,"") | ... N64: =IFERROR(-N127/N126,"") | O64: =IFERROR(+AVERAGE(D64:N64),"") -> -1.1165644
B65: CFI to CFO | D65: =IFERROR(-D128/D126,"") -> -2.0102249 | E65: =IFERROR(-E128/E126,"") | F65: =IFERROR(-F128/F126,"") | G65: =IFERROR(-G128/G126,"") | H65: =IFERROR(-H128/H126,"") | I65: =IFERROR(-I128/I126,"") | J65: =IFERROR(-J128/J126,"") | K65: =IFERROR(-K128/K126,"") | ... N65: =IFERROR(-N128/N126,"") | O65: =IFERROR(+AVERAGE(D65:N65),"") -> -2.0102249
B66: Net Financing to CFO | D66: =IFERROR((D129+D130)/D126,"") -> -14.398773 | E66: =IFERROR((E129+E130)/E126,"") | F66: =IFERROR((F129+F130)/F126,"") | G66: =IFERROR((G129+G130)/G126,"") | H66: =IFERROR((H129+H130)/H126,"") | I66: =IFERROR((I129+I130)/I126,"") | J66: =IFERROR((J129+J130)/J126,"") | K66: =IFERROR((K129+K130)/K126,"") | ... N66: =IFERROR((N129+N130)/N126,"") | O66: =IFERROR(+AVERAGE(D66:N66),"") -> -14.398773
B67: Debt Borrowing to Debt Repayment | D67: =+IFERROR(-D130/D129,"") -> -0.75498504 | E67: =+IFERROR(-E130/E129,"") | F67: =+IFERROR(-F130/F129,"") | G67: =+IFERROR(-G130/G129,"") | H67: =+IFERROR(-H130/H129,"") | I67: =+IFERROR(-I130/I129,"") | J67: =+IFERROR(-J130/J129,"") | K67: =+IFERROR(-K130/K129,"") | ... N67: =+IFERROR(-N130/N129,"") | O67: =IFERROR(+AVERAGE(D67:N67),"") -> -0.75498504
B68: CFF to CFO | D68: =IFERROR(-D131/D126,"") -> 0 | E68: =IFERROR(-E131/E126,"") | F68: =IFERROR(-F131/F126,"") | G68: =IFERROR(-G131/G126,"") | H68: =IFERROR(-H131/H126,"") | I68: =IFERROR(-I131/I126,"") | J68: =IFERROR(-J131/J126,"") | K68: =IFERROR(-K131/K126,"") | ... N68: =IFERROR(-N131/N126,"") | O68: =IFERROR(+AVERAGE(D68:N68),"") -> 0
B69: Payout Ratio | O69: =IFERROR(+AVERAGE(D69:N69),"")
B71: Stock Information | D71: =+D29 | E71: =+E29 | F71: =+F29 | G71: =+G29 | H71: =+H29 | I71: =+I29 | J71: =+J29 | K71: =+K29 | ... O71: =+O29 -> Average
B73: (%) Float | O73: =IFERROR(+AVERAGE(D73:N73),"")
B74: β (Levered) | D74: {=IFERROR(_FV(D91,"Beta"),"")} | E74: {=IFERROR(_FV(E91,"Beta"),"")} | F74: {=IFERROR(_FV(F91,"Beta"),"")} | G74: {=IFERROR(_FV(G91,"Beta"),"")} | H74: {=IFERROR(_FV(H91,"Beta"),"")} | I74: {=IFERROR(_FV(I91,"Beta"),"")} | J74: {=IFERROR(_FV(J91,"Beta"),"")} | K74: {=IFERROR(_FV(K91,"Beta"),"")} | ... N74: {=IFERROR(_FV(N91,"Beta"),"")} | O74: =IFERROR(+AVERAGE(D74:N74),"")
B75: β (Unlevered) | D75: =IFERROR(D74/(1+(1-D104/D103)*(D121/D122)),"") | E75: =IFERROR(E74/(1+(1-E104/E103)*(E121/E122)),"") | F75: =IFERROR(F74/(1+(1-F104/F103)*(F121/F122)),"") | G75: =IFERROR(G74/(1+(1-G104/G103)*(G121/G122)),"") | H75: =IFERROR(H74/(1+(1-H104/H103)*(H121/H122)),"") | I75: =IFERROR(I74/(1+(1-I104/I103)*(I121/I122)),"") | J75: =IFERROR(J74/(1+(1-J104/J103)*(J121/J122)),"") | K75: =IFERROR(K74/(1+(1-K104/K103)*(K121/K122)),"") | ... N75: =IFERROR(N74/(1+(1-N104/N103)*(N121/N122)),"") | O75: =IFERROR(+AVERAGE(D75:N75),"")
B76: % Held by Insiders | O76: =IFERROR(+AVERAGE(D76:N76),"")
B77: % Held by Institutions | O77: =IFERROR(+AVERAGE(D77:N77),"")
B78: Short % Float | O78: =IFERROR(+AVERAGE(D78:N78),"")
B80: Stock Performance | D80: =+D29 | E80: =+E29 | F80: =+F29 | G80: =+G29 | H80: =+H29 | I80: =+I29 | J80: =+J29 | K80: =+K29 | ... O80: =+O29 -> Average
B82: 1 day | D82: {=IFERROR((D85/_xlfn.STOCKHISTORY(C6,TODAY()-1,TODAY()-1,0,0,1))-1,"Non-trading days")} -> Non-trading days | E82: {=IFERROR((E85/_xlfn.STOCKHISTORY(C8,TODAY()-1,TODAY()-1,0,0,1))-1,"Non-trading days")} -> Non-trading days | F82: {=IFERROR((F85/_xlfn.STOCKHISTORY(C9,TODAY()-1,TODAY()-1,0,0,1))-1,"Non-trading days")} -> Non-trading days | G82: {=IFERROR((G85/_xlfn.STOCKHISTORY(C10,TODAY()-1,TODAY()-1,0,0,1))-1,"Non-trading days")} -> Non-trading days | H82: {=IFERROR((K85/_xlfn.STOCKHISTORY(C11,TODAY()-1,TODAY()-1,0,0,1))-1,"Non-trading days")} -> Non-trading days | I82: {=IFERROR((L85/_xlfn.STOCKHISTORY(C12,TODAY()-1,TODAY()-1,0,0,1))-1,"Non-trading days")} -> Non-trading days | J82: {=IFERROR((M85/_xlfn.STOCKHISTORY(C13,TODAY()-1,TODAY()-1,0,0,1))-1,"Non-trading days")} -> Non-trading days | K82: {=IFERROR((N85/_xlfn.STOCKHISTORY(C14,TODAY()-1,TODAY()-1,0,0,1))-1,"Non-trading days")} -> Non-trading days | L82: {=IFERROR((L85/_xlfn.STOCKHISTORY(C15,TODAY()-1,TODAY()-1,0,0,1))-1,"Non-trading days")} -> Non-trading days | M82: {=IFERROR((M85/_xlfn.STOCKHISTORY(C16,TODAY()-1,TODAY()-1,0,0,1))-1,"Non-trading days")} -> Non-trading days | N82: {=IFERROR((N85/_xlfn.STOCKHISTORY(C17,TODAY()-1,TODAY()-1,0,0,1))-1,"Non-trading days")} -> Non-trading days | O82: =IFERROR(+AVERAGE(D82:N82),"")
B83: 1 month | D83: {=IFERROR((D85/_xlfn.STOCKHISTORY(C6,TODAY()-29,TODAY()-29,0,0,1))-1,"Non-trading days")} -> Non-trading days | E83: {=IFERROR((E85/_xlfn.STOCKHISTORY(C8,TODAY()-29,TODAY()-29,0,0,1))-1,"Non-trading days")} -> Non-trading days | F83: {=IFERROR((F85/_xlfn.STOCKHISTORY(C9,TODAY()-29,TODAY()-29,0,0,1))-1,"Non-trading days")} -> Non-trading days | G83: {=IFERROR((G85/_xlfn.STOCKHISTORY(C10,TODAY()-29,TODAY()-29,0,0,1))-1,"Non-trading days")} -> Non-trading days | H83: {=IFERROR((K85/_xlfn.STOCKHISTORY(C11,TODAY()-29,TODAY()-29,0,0,1))-1,"Non-trading days")} -> Non-trading days | I83: {=IFERROR((L85/_xlfn.STOCKHISTORY(C12,TODAY()-29,TODAY()-29,0,0,1))-1,"Non-trading days")} -> Non-trading days | J83: {=IFERROR((M85/_xlfn.STOCKHISTORY(C13,TODAY()-29,TODAY()-29,0,0,1))-1,"Non-trading days")} -> Non-trading days | K83: {=IFERROR((N85/_xlfn.STOCKHISTORY(C14,TODAY()-29,TODAY()-29,0,0,1))-1,"Non-trading days")} -> Non-trading days | L83: {=IFERROR((L85/_xlfn.STOCKHISTORY(C15,TODAY()-29,TODAY()-29,0,0,1))-1,"Non-trading days")} -> Non-trading days | M83: {=IFERROR((M85/_xlfn.STOCKHISTORY(C16,TODAY()-29,TODAY()-29,0,0,1))-1,"Non-trading days")} -> Non-trading days | N83: {=IFERROR((N85/_xlfn.STOCKHISTORY(C17,TODAY()-29,TODAY()-29,0,0,1))-1,"Non-trading days")} -> Non-trading days | O83: =IFERROR(AVERAGE(D83:N83),"")
B84: YTD | D84: {=IFERROR((D85/_xlfn.STOCKHISTORY(C6,"2025-01-02","2025-01-02",0,0,1))-1,"Non-trading days")} -> Non-trading days | E84: {=IFERROR((E85/_xlfn.STOCKHISTORY(C8,"2025-01-02","2025-01-02",0,0,1))-1,"Non-trading days")} -> Non-trading days | F84: {=IFERROR((F85/_xlfn.STOCKHISTORY(C9,"2025-01-02","2025-01-02",0,0,1))-1,"Non-trading days")} -> Non-trading days | G84: {=IFERROR((G85/_xlfn.STOCKHISTORY(C10,"2025-01-02","2025-01-02",0,0,1))-1,"Non-trading days")} -> Non-trading days | H84: {=IFERROR((K85/_xlfn.STOCKHISTORY(C11,"2025-01-02","2025-01-02",0,0,1))-1,"Non-trading days")} -> Non-trading days | I84: {=IFERROR((L85/_xlfn.STOCKHISTORY(C12,"2025-01-02","2025-01-02",0,0,1))-1,"Non-trading days")} -> Non-trading days | J84: {=IFERROR((M85/_xlfn.STOCKHISTORY(C13,"2025-01-02","2025-01-02",0,0,1))-1,"Non-trading days")} -> Non-trading days | K84: {=IFERROR((N85/_xlfn.STOCKHISTORY(C14,"2025-01-02","2025-01-02",0,0,1))-1,"Non-trading days")} -> Non-trading days | L84: {=IFERROR((L85/_xlfn.STOCKHISTORY(C15,"2025-01-02","2025-01-02",0,0,1))-1,"Non-trading days")} -> Non-trading days | M84: {=IFERROR((M85/_xlfn.STOCKHISTORY(C16,"2025-01-02","2025-01-02",0,0,1))-1,"Non-trading days")} -> Non-trading days | N84: {=IFERROR((N85/_xlfn.STOCKHISTORY(C17,"2025-01-02","2025-01-02",0,0,1))-1,"Non-trading days")} -> Non-trading days | O84: =IFERROR(AVERAGE(D84:N84),"")
B85: Current Price | D85: {=+IFERROR(_FV(D91,"Price"),"")} | E85: {=+IFERROR(_FV(E91,"Price"),"")} | F85: {=+IFERROR(_FV(F91,"Price"),"")} | G85: {=+IFERROR(_FV(G91,"Price"),"")} | H85: {=+IFERROR(_FV(H91,"Price"),"")} | I85: {=+IFERROR(_FV(I91,"Price"),"")} | J85: {=+IFERROR(_FV(J91,"Price"),"")} | K85: {=+IFERROR(_FV(K91,"Price"),"")} | ... N85: {=+IFERROR(_FV(N91,"Price"),"")} | O85: =IFERROR(AVERAGE(D85:N85),"")
B87: Extra
B89: % Revenues in the US
B91: Income Statement | D91: =+#REF! -> #REF! | E91: PEER 1 | F91: PEER 2 | G91: PEER 3 | H91: PEER 4 | I91: PEER 5 | J91: PEER 6 | K91: PEER 7 | L91: PEER 8 | M91: PEER 9 | N91: PEER 10
B93: =+Inputs!$B$6&" ("&Inputs!O$4&")" -> Revenue (Sales) (2022) | D93: =+_xlfn.XLOOKUP("Revenue (Sales)",Inputs!$B:$B,Inputs!O:O) -> 211
B94: =+Inputs!$B$6&" ("&Inputs!P$4&")" -> Revenue (Sales) (2023) | D94: =+_xlfn.XLOOKUP("Revenue (Sales)",Inputs!$B:$B,Inputs!P:P) -> 244.6
B95: EBITDA (2023) | D95: =+_xlfn.XLOOKUP("EBITDA",Inputs!$B:$B,Inputs!P:P) -> -178
B96: Net Income (2023) | D96: =+_xlfn.XLOOKUP("Net Income",Inputs!$B:$B,Inputs!P:P) -> -154.2
B97: =+Inputs!$B$6&" ("&Inputs!Q$4&")" -> Revenue (Sales) (2024) | D97: =+_xlfn.XLOOKUP("Revenue (Sales)",Inputs!$B:$B,Inputs!Q:Q) -> 436.2
B98: COGS (Cost of Goods Sold) | D98: =+_xlfn.XLOOKUP($B98,Inputs!$B:$B,Inputs!Q:Q) -> 320.1
B99: Gross Profit | D99: =+_xlfn.XLOOKUP($B99,Inputs!$B:$B,Inputs!Q:Q) -> 116.1 | E99: =+E97-E98 -> 0 | F99: =+F97-F98 -> 0 | G99: =G97-G98 -> 0 | H99: =+H97-H98 -> 0 | I99: =I97-I98 -> 0 | J99: =+J97-J98 -> 0 | K99: =+K97-K98 -> 0 | L99: =+L97-L98 -> 0 | M99: =+M97-M98 -> 0 | N99: =+N97-N98 -> 0
B100: EBITDA | D100: =+_xlfn.XLOOKUP($B100,Inputs!$B:$B,Inputs!Q:Q) -> -182.1
B101: Operating Income (EBIT) | D101: =+_xlfn.XLOOKUP($B101,Inputs!$B:$B,Inputs!Q:Q) -> -150.23
B102: Net Interest Expense (Income) | D102: =+_xlfn.XLOOKUP($B102,Inputs!$B:$B,Inputs!Q:Q) -> 4
B103: Pre-Tax Income (EBT) | D103: =+_xlfn.XLOOKUP($B103,Inputs!$B:$B,Inputs!Q:Q) -> -149.93
B104: Tax Expense (Benefits) | D104: =+_xlfn.XLOOKUP($B104,Inputs!$B:$B,Inputs!Q:Q) -> 0.8
B105: Net Income | D105: =+_xlfn.XLOOKUP($B105,Inputs!$B:$B,Inputs!Q:Q) -> -150.73
B106: EPS basic | D106: =+_xlfn.XLOOKUP($B106,Inputs!$B:$B,Inputs!Q:Q) -> -0.38
B107: R&D (Research & Development) | D107: =+_xlfn.XLOOKUP($B107,Inputs!$B:$B,Inputs!Q:Q) -> 174.4
B109: Balance Sheet
B111: Cash & Cash Equivalents | D111: =+_xlfn.XLOOKUP($B111,Inputs!$B:$B,Inputs!Q:Q) -> 271
B112: Accounts Receivable | D112: =+_xlfn.XLOOKUP($B112,Inputs!$B:$B,Inputs!Q:Q) -> 36.4
B113: Beginning Inventory | D113: =+_xlfn.XLOOKUP("Inventory",Inputs!$B:$B,Inputs!P:P) -> 107.9
B114: Ending Inventory | D114: =+_xlfn.XLOOKUP("Inventory",Inputs!$B:$B,Inputs!Q:Q) -> 119.1
B115: Current Assets | D115: =+_xlfn.XLOOKUP($B115,Inputs!$B:$B,Inputs!Q:Q) -> 692.6
B116: Net PP&E (Property, Plant and Equipment) | D116: =+_xlfn.XLOOKUP($B116,Inputs!$B:$B,Inputs!Q:Q) -> 262.9
B117: Total Assets | D117: =+_xlfn.XLOOKUP($B117,Inputs!$B:$B,Inputs!Q:Q) -> 1184.3
B118: Accounts Payable | D118: =+_xlfn.XLOOKUP($B118,Inputs!$B:$B,Inputs!Q:Q) -> 72.5
B119: Current Liabilities | D119: =+_xlfn.XLOOKUP($B119,Inputs!$B:$B,Inputs!Q:Q) -> 339.5
B120: Long-term debt | D120: =+_xlfn.XLOOKUP($B120,Inputs!$B:$B,Inputs!Q:Q) -> 441.4
B121: Total Debt | D121: =+_xlfn.XLOOKUP($B121,Inputs!$B:$B,Inputs!Q:Q,,,-1) -> 459.6
B122: Shareholder's Equity | D122: =+_xlfn.XLOOKUP($B122,Inputs!$B:$B,Inputs!Q:Q) -> 382.4
B124: Cash Flow Statement
B126: Operating Cash Flow | D126: =+_xlfn.XLOOKUP($B126,Inputs!$B:$B,Inputs!Q:Q) -> -48.9
B127: Net Capex | D127: =+_xlfn.XLOOKUP($B127,Inputs!$B:$B,Inputs!Q:Q) -> -54.6
B128: Investing Cash Flow | D128: =+_xlfn.XLOOKUP($B128,Inputs!$B:$B,Inputs!Q:Q) -> -98.3
...

Sheet ESG
B2: Environmental, Social and Governance Analysis
B4: Author: | E4: Highlights | N4: Recent News
G5: Rocket Lab’s 2021 ESG report does not include any quantitative data on Scope 1 or Scope 2 greenhouse gas emissions. Furthermore, the report does not contain any stated commitment to monitor or disclose these emissions in future reports.
B6: Overview | D6: .
B7: Last Update | C7: 45727 | D7: . | G7: The 2021 ESG report by Rocket Lab does not provide any data or discussion related to water consumption. There is no mention of water usage, monitoring, or reduction efforts.
B8: Latest year with data
B9: GICS Sector | C9: Industrials | G9: Rocket Lab’s 2021 ESG report does not include any quantitative data on energy consumption. While the company mentions environmental considerations in general, there are no metrics, breakdowns, or targets related to energy use.
B10: GICS Industry Group | C10: Aerospace & Defense
B11: Final Review | G11: The 2021 ESG report mentions a general commitment to environmentally responsible operations and waste minimization, but does not include any quantitative data or specific strategies regarding waste management.
B13: ESG Scores
B14: LSEG ESG Score | C14: 22
B15: E-Score | C15: 0
B16: S-Score | C16: 13 | E16: GHG Scope 1 and 2 Emissions: | N16: Water, Waste, Energy Management:
B17: G-Score | C17: 50
B18: S&P Global ESG Score | C18: private
B19: Environmental | C19: private
B20: Social | C20: private
B21: Governance & Economic | C21: private
B22: Sustainalytics | C22: 39.9
B23: ISS ESG Corporate Rating | C23: D-
B24: SDG Impact Rating | C24: -7.8
B25: Governance Quality Score | C25: 8
B26: MSCI ESG Ratings | C26: N/A
B29: Industry ESG Overview:
E33: ENVIRONMENTAL
G35: Overview | H35: Targets | K35: Improvements | O35: Comments
E36: GHG (or CO2) Scope 1 Emissions
E38: Water Consumption
E40: Energy Consumption
E42: Waste Management
E44: Other
E46: SOCIAL
B48: Important Sources: | G48: Overview | H48: Targets | K48: Improvements | O48: Comments
B49: Annual Report | E49: Employee Turnover % | K49: ​Rocket Lab has initiated measures to enhance employee retention and address workplace culture concerns:Employee Relations Initiatives: Dedicated Management Role: The company has established positions such as the Employee Relations and Compliance Manager, responsible for developing and implementing employee recognition and engagement programs, aiming to improve workplace morale and retention. Policy Guidance and Support: Rocket Lab employs People & Culture Business Partners who work closely with management and staff to provide policy guidance, enhance work relationships, and boost productivity and retention. | O49: Rocket Lab does not publicly disclose official employee turnover statistics in its ESG or financial reports. However, various employee reviews and third-party platforms provide insights into the company's workforce dynamics. Short Tenure Reports: Some employees have noted a high turnover rate, with average tenures ranging from 1 to 2 years.
B50: Sustainability Report | D50: .
B51: Proxy Statement | D51: . | E51: Salaries & Compensation | K51: Rocket Lab's compensation practices have evolved positively, with noticeable increases in executive pay and competitive salaries for employees. | O51: While Rocket Lab's ESG disclosures, such as the 2021 ESG Impact Report, do not extensively cover compensation practices, the company demonstrates transparency in executive pay through its SEC filings. However, detailed information on company-wide compensation policies, pay equity initiatives, or benefits programs is limited. Rocket Lab's lower pay ratio reflects a more equitable compensation structure, aligning with its position as a growing company in the aerospace industry.​
E53: Reputation | O53: Rocket Lab is esteemed for its innovation and industry position, though it faces notable ESG risks that may impact its overall reputation.
E55: Discrimination Events | O55: Some of Rocket Lab's job postings, particularly for U.S.-based positions, specify that applicants must be U.S. citizens as defined by the International Traffic in Arms Regulations. This requirement could potentially exclude certain individuals, such as refugees or asylees, who are legally authorized to work in the U.S.
E57: Work Safety | K57: Rocket Lab has established formal health and safety policies, systems, and processes to ensure a safe working environment.
E59: Damage to consumer health | G59: N/A
E61: Pension Plan
E63: Supply chain | O63: Rocket Lab briefly mentions its supply chain in the context of logistics and operations, but there are no publicly disclosed ESG policies, ethical sourcing standards, or supplier audits.
E65: Community involvement | O65: The company supports STEM initiatives, scholarships for women and gender minorities, and community engagement in education. These efforts are mentioned but not quantified or reported in detail.
E67: Public Sector | O67: Rocket Lab has clear partnerships with public agencies like NASA, DARPA, and the NRO. It collaborates with regulatory authorities for launch operations but does not elaborate on public policy or governance strategies.
E69: Litigation | O69: There are no major public lawsuits related to ESG, environmental violations, labor disputes, or discrimination. No litigation disclosures appear in recent SEC filings.
E71: GOVERNANCE
G73: Overview | H73: Targets | K73: Improvements | O73: Comments
E74: Diversity (Gender, Age, Industry, Region) | O74: Rocket Lab’s board of directors reflects a low/moderate level of diversity, with both male and female directors, and professionals with experience across aerospace, technology, and finance sectors. However, there is room for improvement in terms of age diversity and regional representation. While the company operates in New Zealand and the United States, its board is predominantly composed of individuals with experience in the U.S. and Western regions.
E76: % Independence | O76: Rocket Lab's board of directors comprises 9 members, with 8 identified as independent directors, resulting in an independence ratio of approximately 89%.
E78: Average time as independent directors | O78: 2.4 years
E80: Departures of C-level executives | O80: Rocket Lab has experienced notable executive changes in recent years: Dr. Sven Strohband: A founding board member since 2013, Dr. Strohband did not seek re-election at the 2024 Annual Meeting after serving for over a decade
E82: CEO/Chairman duality | O82: Peter Beck holds both roles as CEO and Chairman
E84: Transparency when reporting | O84: While Rocket Lab demonstrates strong transparency in governance and social practices, it falls short in providing clear, measurable environmental disclosures.
E86: Time taken to report | O86: Rocket Lab's financial reports are on time and regular (9 days to report, on average), but their ESG reporting has significant gaps, with the latest filling being from 2021.
E88: CEO or Chairman in other boards? | O88: Peter Beck, CEO and Chairman of Rocket Lab, does not serve on any other boards
E90: Audit / Consulting | O90: Audit related fees represent 0% of total, Deloitte & Touche LLP has been serving as Rocket Lab's independent registered public accounting firm since August 30, 2021.
E92: ESG-compensation related
E94: Management compensation schemes | O94: Rocket Lab's management compensation includes elements linked to the company's stock performance ( through RSUs and stock-based compensation)

Sheet ESG Inputs
B2: ESG Inputs
A4: x | B4: Total GHG Scope 1 Emissions | G4: 2014 | H4: =+G4+1 -> 2015 | I4: =+H4+1 -> 2016 | J4: =+I4+1 -> 2017 | K4: =+J4+1 -> 2018 | L4: =+K4+1 -> 2019 | M4: =+L4+1 -> 2020 | N4: =+M4+1 -> 2021 | O4: =+N4+1 -> 2022 | ... Q4: =+P4+1 -> 2024 | R4: ="CAGR "&$G$4&" - "&$Q$4 -> CAGR 2014 - 2024
B6: =+Peers!B6 | G6: x | R6: =IFERROR((Q6/G6)^(1/COUNT($G$4:$Q$4))-1,"")
B7: =+Peers!B8 | R7: =IFERROR((Q7/G7)^(1/COUNT($G$4:$Q$4))-1,"")
B8: =+Peers!B9 | R8: =IFERROR((Q8/G8)^(1/COUNT($G$4:$Q$4))-1,"")
B9: =+Peers!B10 | R9: =IFERROR((Q9/G9)^(1/COUNT($G$4:$Q$4))-1,"")
B10: =+Peers!B11 | R10: =IFERROR((Q10/G10)^(1/COUNT($G$4:$Q$4))-1,"")
B11: =+Peers!B12 | R11: =IFERROR((Q11/G11)^(1/COUNT($G$4:$Q$4))-1,"")
B12: =+Peers!B13 | R12: =IFERROR((Q12/G12)^(1/COUNT($G$4:$Q$4))-1,"")
B13: =+Peers!B14 | R13: =IFERROR((Q13/G13)^(1/COUNT($G$4:$Q$4))-1,"")
B14: =+Peers!B15 | R14: =IFERROR((Q14/G14)^(1/COUNT($G$4:$Q$4))-1,"")
B15: =+Peers!B16 | R15: =IFERROR((Q15/G15)^(1/COUNT($G$4:$Q$4))-1,"")
B16: =+Peers!B17 | R16: =IFERROR((Q16/G16)^(1/COUNT($G$4:$Q$4))-1,"")
A18: x | B18: Total GHG Scope 2 (Location-Based) Emissions | G18: 2014 | H18: =+G18+1 -> 2015 | I18: =+H18+1 -> 2016 | J18: =+I18+1 -> 2017 | K18: =+J18+1 -> 2018 | L18: =+K18+1 -> 2019 | M18: =+L18+1 -> 2020 | N18: =+M18+1 -> 2021 | O18: =+N18+1 -> 2022 | ... Q18: =+P18+1 -> 2024 | R18: ="CAGR "&$G$4&" - "&$Q$4 -> CAGR 2014 - 2024
B20: =+$B$6 | R20: =IFERROR((Q20/G20)^(1/COUNT($G$4:$Q$4))-1,"")
B21: =+$B$7 | R21: =IFERROR((Q21/G21)^(1/COUNT($G$4:$Q$4))-1,"")
B22: =+$B$8 | R22: =IFERROR((Q22/G22)^(1/COUNT($G$4:$Q$4))-1,"")
B23: =+$B$9 | R23: =IFERROR((Q23/G23)^(1/COUNT($G$4:$Q$4))-1,"")
B24: =+$B$10 | R24: =IFERROR((Q24/G24)^(1/COUNT($G$4:$Q$4))-1,"")
B25: =+$B$11 | R25: =IFERROR((Q25/G25)^(1/COUNT($G$4:$Q$4))-1,"")
B26: =+$B$12 | R26: =IFERROR((Q26/G26)^(1/COUNT($G$4:$Q$4))-1,"")
B27: =+$B$13 | R27: =IFERROR((Q27/G27)^(1/COUNT($G$4:$Q$4))-1,"")
B28: =+$B$14 | R28: =IFERROR((Q28/G28)^(1/COUNT($G$4:$Q$4))-1,"")
B29: =+$B$15 | R29: =IFERROR((Q29/G29)^(1/COUNT($G$4:$Q$4))-1,"")
B30: =+$B$16 | R30: =IFERROR((Q30/G30)^(1/COUNT($G$4:$Q$4))-1,"")
A32: x | B32: Total Energy Usage | G32: 2014 | H32: =+G32+1 -> 2015 | I32: =+H32+1 -> 2016 | J32: =+I32+1 -> 2017 | K32: =+J32+1 -> 2018 | L32: =+K32+1 -> 2019 | M32: =+L32+1 -> 2020 | N32: =+M32+1 -> 2021 | O32: =+N32+1 -> 2022 | ... Q32: =+P32+1 -> 2024 | R32: ="CAGR "&$G$4&" - "&$Q$4 -> CAGR 2014 - 2024
B34: =+$B$6 | R34: =IFERROR((Q34/G34)^(1/COUNT($G$4:$Q$4))-1,"")
B35: =+$B$7 | R35: =IFERROR((Q35/G35)^(1/COUNT($G$4:$Q$4))-1,"")
B36: =+$B$8 | R36: =IFERROR((Q36/G36)^(1/COUNT($G$4:$Q$4))-1,"")
B37: =+$B$9 | R37: =IFERROR((Q37/G37)^(1/COUNT($G$4:$Q$4))-1,"")
B38: =+$B$10 | R38: =IFERROR((Q38/G38)^(1/COUNT($G$4:$Q$4))-1,"")
B39: =+$B$11 | R39: =IFERROR((Q39/G39)^(1/COUNT($G$4:$Q$4))-1,"")
B40: =+$B$12 | R40: =IFERROR((Q40/G40)^(1/COUNT($G$4:$Q$4))-1,"")
B41: =+$B$13 | R41: =IFERROR((Q41/G41)^(1/COUNT($G$4:$Q$4))-1,"")
B42: =+$B$14 | R42: =IFERROR((Q42/G42)^(1/COUNT($G$4:$Q$4))-1,"")
B43: =+$B$15 | R43: =IFERROR((Q43/G43)^(1/COUNT($G$4:$Q$4))-1,"")
B44: =+$B$16 | R44: =IFERROR((Q44/G44)^(1/COUNT($G$4:$Q$4))-1,"")
A46: x | B46: Total Water Consumption | G46: 2014 | H46: =+G46+1 -> 2015 | I46: =+H46+1 -> 2016 | J46: =+I46+1 -> 2017 | K46: =+J46+1 -> 2018 | L46: =+K46+1 -> 2019 | M46: =+L46+1 -> 2020 | N46: =+M46+1 -> 2021 | O46: =+N46+1 -> 2022 | ... Q46: =+P46+1 -> 2024 | R46: ="CAGR "&$G$4&" - "&$Q$4 -> CAGR 2014 - 2024
B48: =+$B$6 | R48: =IFERROR((Q48/G48)^(1/COUNT($G$4:$Q$4))-1,"")
B49: =+$B$7 | R49: =IFERROR((Q49/G49)^(1/COUNT($G$4:$Q$4))-1,"")
B50: =+$B$8 | R50: =IFERROR((Q50/G50)^(1/COUNT($G$4:$Q$4))-1,"")
B51: =+$B$9 | R51: =IFERROR((Q51/G51)^(1/COUNT($G$4:$Q$4))-1,"")
B52: =+$B$10 | R52: =IFERROR((Q52/G52)^(1/COUNT($G$4:$Q$4))-1,"")
B53: =+$B$11 | R53: =IFERROR((Q53/G53)^(1/COUNT($G$4:$Q$4))-1,"")
B54: =+$B$12 | R54: =IFERROR((Q54/G54)^(1/COUNT($G$4:$Q$4))-1,"")
B55: =+$B$13 | R55: =IFERROR((Q55/G55)^(1/COUNT($G$4:$Q$4))-1,"")
B56: =+$B$14 | R56: =IFERROR((Q56/G56)^(1/COUNT($G$4:$Q$4))-1,"")
B57: =+$B$15 | R57: =IFERROR((Q57/G57)^(1/COUNT($G$4:$Q$4))-1,"")
B58: =+$B$16 | R58: =IFERROR((Q58/G58)^(1/COUNT($G$4:$Q$4))-1,"")
A60: x | B60: Total Waste Production | G60: 2014 | H60: =+G60+1 -> 2015 | I60: =+H60+1 -> 2016 | J60: =+I60+1 -> 2017 | K60: =+J60+1 -> 2018 | L60: =+K60+1 -> 2019 | M60: =+L60+1 -> 2020 | N60: =+M60+1 -> 2021 | O60: =+N60+1 -> 2022 | ... Q60: =+P60+1 -> 2024 | R60: ="CAGR "&$G$4&" - "&$Q$4 -> CAGR 2014 - 2024
B62: =+$B$6 | R62: =IFERROR((Q62/G62)^(1/COUNT($G$4:$Q$4))-1,"")
B63: =+$B$7 | R63: =IFERROR((Q63/G63)^(1/COUNT($G$4:$Q$4))-1,"")
B64: =+$B$8 | R64: =IFERROR((Q64/G64)^(1/COUNT($G$4:$Q$4))-1,"")
B65: =+$B$9 | R65: =IFERROR((Q65/G65)^(1/COUNT($G$4:$Q$4))-1,"")
B66: =+$B$10 | R66: =IFERROR((Q66/G66)^(1/COUNT($G$4:$Q$4))-1,"")
B67: =+$B$11 | R67: =IFERROR((Q67/G67)^(1/COUNT($G$4:$Q$4))-1,"")
B68: =+$B$12 | R68: =IFERROR((Q68/G68)^(1/COUNT($G$4:$Q$4))-1,"")
B69: =+$B$13 | R69: =IFERROR((Q69/G69)^(1/COUNT($G$4:$Q$4))-1,"")
B70: =+$B$14 | R70: =IFERROR((Q70/G70)^(1/COUNT($G$4:$Q$4))-1,"")
B71: =+$B$15 | R71: =IFERROR((Q71/G71)^(1/COUNT($G$4:$Q$4))-1,"")
B72: =+$B$16 | R72: =IFERROR((Q72/G72)^(1/COUNT($G$4:$Q$4))-1,"")
A74: x | B74: GHG Scope 1 and 2 Emissions | G74: 2014 | H74: =+G74+1 -> 2015 | I74: =+H74+1 -> 2016 | J74: =+I74+1 -> 2017 | K74: =+J74+1 -> 2018 | L74: =+K74+1 -> 2019 | M74: =+L74+1 -> 2020 | N74: =+M74+1 -> 2021 | O74: =+N74+1 -> 2022 | ... Q74: =+P74+1 -> 2024 | R74: ="CAGR "&$G$4&" - "&$Q$4 -> CAGR 2014 - 2024
B76: =+$B$6 | G76: =+G6+G20 -> #VALUE! | H76: =+H6+H20 -> #VALUE! | I76: =+I6+I20 -> 0 | J76: =+J6+J20 -> 0 | K76: =+K6+K20 -> 0 | L76: =+L6+L20 -> 0 | M76: =+M6+M20 -> 0 | N76: =+N6+N20 -> 0 | ... Q76: =+Q6+Q20 -> 0 | R76: =IFERROR((Q76/G76)^(1/COUNT($G$4:$Q$4))-1,"")
B77: =+$B$7 | G77: =+G7+G21 -> 0 | H77: =+H7+H21 -> 0 | I77: =+I7+I21 -> 0 | J77: =+J7+J21 -> 0 | K77: =+K7+K21 -> 0 | L77: =+L7+L21 -> 0 | M77: =+M7+M21 -> 0 | N77: =+N7+N21 -> 0 | ... Q77: =+Q7+Q21 -> 0 | R77: =IFERROR((Q77/G77)^(1/COUNT($G$4:$Q$4))-1,"")
B78: =+$B$8 | G78: =+G8+G22 -> 0 | H78: =+H8+H22 -> 0 | I78: =+I8+I22 -> 0 | J78: =+J8+J22 -> 0 | K78: =+K8+K22 -> 0 | L78: =+L8+L22 -> 0 | M78: =+M8+M22 -> 0 | N78: =+N8+N22 -> 0 | ... Q78: =+Q8+Q22 -> 0 | R78: =IFERROR((Q78/G78)^(1/COUNT($G$4:$Q$4))-1,"")
B79: =+$B$9 | G79: =+G9+G23 -> 0 | H79: =+H9+H23 -> 0 | I79: =+I9+I23 -> 0 | J79: =+J9+J23 -> 0 | K79: =+K9+K23 -> 0 | L79: =+L9+L23 -> 0 | M79: =+M9+M23 -> 0 | N79: =+N9+N23 -> 0 | ... Q79: =+Q9+Q23 -> 0 | R79: =IFERROR((Q79/G79)^(1/COUNT($G$4:$Q$4))-1,"")
B80: =+$B$10 | G80: =+G10+G24 -> 0 | H80: =+H10+H24 -> 0 | I80: =+I10+I24 -> 0 | J80: =+J10+J24 -> 0 | K80: =+K10+K24 -> 0 | L80: =+L10+L24 -> 0 | M80: =+M10+M24 -> 0 | N80: =+N10+N24 -> 0 | ... Q80: =+Q10+Q24 -> 0 | R80: =IFERROR((Q80/G80)^(1/COUNT($G$4:$Q$4))-1,"")
B81: =+$B$11 | G81: =+G11+G25 -> 0 | H81: =+H11+H25 -> 0 | I81: =+I11+I25 -> 0 | J81: =+J11+J25 -> 0 | K81: =+K11+K25 -> 0 | L81: =+L11+L25 -> 0 | M81: =+M11+M25 -> 0 | N81: =+N11+N25 -> 0 | ... Q81: =+Q11+Q25 -> 0 | R81: =IFERROR((Q81/G81)^(1/COUNT($G$4:$Q$4))-1,"")
B82: =+$B$12 | G82: =+G12+G26 -> 0 | H82: =+H12+H26 -> 0 | I82: =+I12+I26 -> 0 | J82: =+J12+J26 -> 0 | K82: =+K12+K26 -> 0 | L82: =+L12+L26 -> 0 | M82: =+M12+M26 -> 0 | N82: =+N12+N26 -> 0 | ... Q82: =+Q12+Q26 -> 0 | R82: =IFERROR((Q82/G82)^(1/COUNT($G$4:$Q$4))-1,"")
B83: =+$B$13 | G83: =+G13+G27 -> 0 | H83: =+H13+H27 -> 0 | I83: =+I13+I27 -> 0 | J83: =+J13+J27 -> 0 | K83: =+K13+K27 -> 0 | L83: =+L13+L27 -> 0 | M83: =+M13+M27 -> 0 | N83: =+N13+N27 -> 0 | ... Q83: =+Q13+Q27 -> 0 | R83: =IFERROR((Q83/G83)^(1/COUNT($G$4:$Q$4))-1,"")
B84: =+$B$14 | G84: =+G14+G28 -> 0 | H84: =+H14+H28 -> 0 | I84: =+I14+I28 -> 0 | J84: =+J14+J28 -> 0 | K84: =+K14+K28 -> 0 | L84: =+L14+L28 -> 0 | M84: =+M14+M28 -> 0 | N84: =+N14+N28 -> 0 | ... Q84: =+Q14+Q28 -> 0 | R84: =IFERROR((Q84/G84)^(1/COUNT($G$4:$Q$4))-1,"")
B85: =+$B$15 | G85: =+G15+G29 -> 0 | H85: =+H15+H29 -> 0 | I85: =+I15+I29 -> 0 | J85: =+J15+J29 -> 0 | K85: =+K15+K29 -> 0 | L85: =+L15+L29 -> 0 | M85: =+M15+M29 -> 0 | N85: =+N15+N29 -> 0 | ... Q85: =+Q15+Q29 -> 0 | R85: =IFERROR((Q85/G85)^(1/COUNT($G$4:$Q$4))-1,"")
B86: =+$B$16 | G86: =+G16+G30 -> 0 | H86: =+H16+H30 -> 0 | I86: =+I16+I30 -> 0 | J86: =+J16+J30 -> 0 | K86: =+K16+K30 -> 0 | L86: =+L16+L30 -> 0 | M86: =+M16+M30 -> 0 | N86: =+N16+N30 -> 0 | ... Q86: =+Q16+Q30 -> 0 | R86: =IFERROR((Q86/G86)^(1/COUNT($G$4:$Q$4))-1,"")

Sheet DCF
B2: DCF
A4: x | B4: Key Assumptions | R4: #VALUE!
B6: Switches | E6: Bear Case | H6: Base Case | K6: Bull Case | AE6: FCFF | AF6: FCFE | AG6: Tax Shield | AH6: Total Payout | AI6: NOPAT | AJ6: Debt Borrowing | AK6: Cash Balance | AL6: Total Assets | AM6: Total Liabilities | AN6: Shareholder's Equity | AO6: Current Liabilities | AP6: Current Assets
B7: Revenue | C7: 2 | E7: Revenue | F7: -0.02 | H7: Revenue | K7: Revenue | L7: 0.02 | AD7: 2022 | AE7: =+E190 -> -167.50669 | AF7: =+E242 -> -77.84 | AG7: =+H214 -> 0 | AH7: =+E255 -> 3.9 | AI7: =+E180 -> -108.83669 | AJ7: =+E240 -> 87.3 | AK7: =+E85 -> 471.8
B8: EBIT | C8: 2 | E8: EBIT | F8: -0.01 | H8: EBIT | K8: EBIT | L8: 0.01 | AD8: =+AD7+1 -> 2023 | AE8: =+F190 -> -147.67542 | AF8: =+F242 -> -58.6 | AG8: =+I214 -> 0 | AH8: =+F255 -> 2.4 | AI8: =+F180 -> -153.17542 | AJ8: =+F240 -> 90.1 | AK8: =+F85 -> 244.8
B9: WACC | C9: 2 | E9: WACC | F9: =IFERROR(+I9+0.5%,"") -> 0.13501782 | H9: WACC | I9: =WACC!G26 -> 0.13001782 | K9: WACC | L9: =IFERROR(I9-0.5%,"") -> 0.12501782 | AD9: =+AD8+1 -> 2024 | AE9: =+G190 -> -78.861601 | AF9: =+G242 -> 19.74 | AG9: =+J214 -> 0 | AH9: =+G255 -> -26.1 | AI9: =+G180 -> -151.0316 | AJ9: =+G240 -> 98.3 | AK9: =+G85 -> 418.9 | AL9: =Inputs!Q48 -> 1184.3 | AM9: =+Inputs!Q60 -> 801.9 | AN9: =+AL9-AM9 -> 382.4 | AO9: =+Inputs!Q54 -> 339.5 | AP9: =+Inputs!Q38 -> 692.6
B10: EBITDAR&D | C10: 2 | E10: EBITDAR&D | F10: =+I10-1 -> 16.02 | H10: EBITDAR&D | I10: 17.02 | K10: EBITDAR&D | L10: =+I10+1 -> 18.02 | AD10: =+AD9+1 -> 2025 | AE10: =+H190 -> -306.70191 | AF10: =+H242 -> -298.6475 | AG10: =+K214 -> 0 | AH10: =+H255 -> 0 | AI10: =+H180 -> -295.67185 | AJ10: =+H240 -> 0 | AK10: =+H85 -> -348.54247 | AL10: =Inputs!Q48+DCF!H85+DCF!H87+DCF!H90+DCF!H93+DCF!H96+DCF!H102-DCF!G85-DCF!G87-DCF!G90-DCF!G93-DCF!G96-DCF!G102 -> 459.44891 | AM10: =+Inputs!Q60+(DCF!H107+DCF!H110+DCF!H113+DCF!H115*DCF!G107*DCF!G110*DCF!G113*DCF!G115) -> 1085.1991 | AN10: =+AL10-AM10 -> -625.75017 | AO10: =+AO9+H107+H110-G107-G110 -> 301.49908 | AP10: =+H85+H87+H90+H93 -> -75.875411
AD11: =+AD10+1 -> 2026 | AE11: =+I190 -> -288.01253 | AF11: =+I242 -> 16.392413 | AG11: =+L214 -> 0 | AH11: =+I255 -> 0 | AI11: =+I180 -> -318.86029 | AJ11: =+I240 -> 298.6475 | AK11: =+I85 -> -819.64739 | AL11: =AL10+DCF!I85+DCF!I87+DCF!I90+DCF!I93+DCF!I96+DCF!I102-DCF!H85-DCF!H87-DCF!H90-DCF!H93-DCF!H96-DCF!H102 -> 42.104111 | AM11: =AM10+(DCF!I107+DCF!I110+DCF!I113+DCF!I115*DCF!H107*DCF!H110*DCF!H113*DCF!H115) -> 1390.7159 | AN11: =+AL11-AM11 -> -1348.6118 | AO11: =+AO10+I107+I110-H107-H110 -> 323.71684 | AP11: =+I85+I87+I90+I93 -> -530.70873
B12: WACC | C12: =CHOOSE(C9,F9,I9,L9) -> 0.13001782 | AD12: =+AD11+1 -> 2027 | AE12: =+J190 -> -318.45398 | AF12: =+J242 -> -311.96306 | AG12: =+M214 -> 0 | AH12: =+J255 -> 0 | AI12: =+J180 -> -347.94913 | AJ12: =+J240 -> 0 | AK12: =+J85 -> -1760.1541
B13: EBITDAR&D Exit Multiple | C13: =CHOOSE(C10,F10,I10,L10) -> 17.02 | AD13: =+AD12+1 -> 2028 | AE13: =+K190 -> -371.94481 | AF13: =+K242 -> -52.745382 | AG13: =+N214 -> 0 | AH13: =+K255 -> 0 | AI13: =+K180 -> -382.34105 | AJ13: =+K240 -> 311.96306 | AK13: =+K85 -> -2377.771
AD14: =+AD13+1 -> 2029 | AE14: =+L190 -> -400.10639 | AF14: =+L242 -> -340.41599 | AG14: =+O214 -> 0 | AH14: =+L255 -> 0 | AI14: =+L180 -> -417.59041 | AJ14: =+L240 -> 52.745382 | AK14: =+L85 -> -3317.321
A15: x | B15: Operating Assumptions | E15: 2022 | F15: =+E15+1 -> 2023 | G15: =+F15+1 -> 2024 | H15: =+G15+1 -> 2025 | I15: =+H15+1 -> 2026 | J15: =+I15+1 -> 2027 | K15: =+J15+1 -> 2028 | L15: =+K15+1 -> 2029 | M15: =+L15+1 -> 2030 | ... AP15: =+AO15+1 -> 2059
B17: Space Industry | E17: 525000 | F17: 630000 | G17: =F17*1.09 -> 686700 | H17: =G17*1.09 -> 748503 | I17: =H17*1.09 -> 815868.27 | J17: =I17*1.09 -> 889296.41 | K17: =J17*1.09 -> 969333.09 | L17: =K17*1.09 -> 1056573.1 | M17: =L17*1.09 -> 1151664.6 | N17: =M17*1.09 -> 1255314.5 | ... AA17: =Z17*1.09 -> 3848548.9
B18: NASA Budget | E18: 25796 | F18: 26247 | G18: 24875 | H18: =G18*1.05 -> 26118.75 | I18: =H18*1.05 -> 27424.688 | J18: =I18*1.05 -> 28795.922 | K18: =J18*1.05 -> 30235.718 | L18: =K18*1.05 -> 31747.504 | M18: =L18*1.05 -> 33334.879 | N18: =M18*1.05 -> 35001.623 | O18: =N18*1.05 -> 36751.704 | ... AA18: =Z18*1.05 -> 66000.78
B19: Government Revenue | E19: =E27*0.51 -> 107.61 | F19: =F27*0.51 -> 124.746 | G19: =G27*0.51 -> 222.462 | H19: =G19*1.075 -> 239.14665 | I19: =H19*1.075 -> 257.08265 | J19: =I19*1.075 -> 276.36385 | K19: =J19*1.075 -> 297.09114 | L19: =K19*1.075 -> 319.37297 | M19: =L19*1.075 -> 343.32594 | N19: =M19*1.091 -> 374.5686 | O19: =N19*1.091 -> 408.65435 | P19: =O19*1.091 -> 445.84189 | Q19: =P19*1.091 -> 486.41351 | R19: =Q19*1.091 -> 530.67713 | S19: =R19*1.091 -> 578.96875 | T19: =S19*1.091 -> 631.65491 | U19: =T19*1.091 -> 689.13551 | ... AA19: =Z19*1.091 -> 1162.1258
B20: % of growth | F20: =(F19-E19)/E19 -> 0.15924171 | G20: =(G19-F19)/F19 -> 0.78331971 | H20: =(H19-G19)/G19 -> 0.075 | I20: =(I19-H19)/H19 -> 0.075 | J20: =(J19-I19)/I19 -> 0.075 | K20: =(K19-J19)/J19 -> 0.075 | L20: =(L19-K19)/K19 -> 0.075 | M20: =(M19-L19)/L19 -> 0.075 | ... AA20: =(AA19-Z19)/Z19 -> 0.091
B21: Commercial Revenue | E21: =E27*0.49 -> 103.39 | F21: =F27*0.49 -> 119.854 | G21: =G27*0.49 -> 213.738 | H21: =G21*1.0631 -> 227.22487 | I21: =H21*1.0631 -> 241.56276 | J21: =I21*1.0631 -> 256.80537 | K21: =J21*1.0631 -> 273.00979 | L21: =K21*1.0631 -> 290.2367 | M21: =L21*1.0611 -> 307.97017 | N21: =M21*1.0611 -> 326.78714 | O21: =N21*1.0611 -> 346.75384 | P21: =O21*1.0611 -> 367.9405 | Q21: =P21*1.0611 -> 390.42166 | R21: =Q21*1.0611 -> 414.27642 | S21: =R21*1.0611 -> 439.58871 | T21: =S21*1.0611 -> 466.44758 | ... AA21: =Z21*1.0611 -> 706.47541
B22: % of growth | F22: =(F21-E21)/E21 -> 0.15924171 | G22: =(G21-F21)/F21 -> 0.78331971 | H22: =(H21-G21)/G21 -> 0.0631 | I22: =(I21-H21)/H21 -> 0.0631 | J22: =(J21-I21)/I21 -> 0.0631 | K22: =(K21-J21)/J21 -> 0.0631 | L22: =(L21-K21)/K21 -> 0.0631 | M22: =(M21-L21)/L21 -> 0.0611 | ... AA22: =(AA21-Z21)/Z21 -> 0.0611
B24: In millions of USD
A25: x | B25: Income Statement | E25: 2022 | F25: =+E25+1 -> 2023 | G25: =+F25+1 -> 2024 | H25: =+G25+1 -> 2025 | I25: =+H25+1 -> 2026 | J25: =+I25+1 -> 2027 | K25: =+J25+1 -> 2028 | L25: =+K25+1 -> 2029 | M25: =+L25+1 -> 2030 | ... AA25: =+Z25+1 -> 2044
B27: Revenue (Sales) | D27: =+_xlfn.XLOOKUP($B27,Inputs!$B:$B,Inputs!N:N) -> 62.2 | E27: =+_xlfn.XLOOKUP($B27,Inputs!$B:$B,Inputs!O:O) -> 211 | F27: =+_xlfn.XLOOKUP($B27,Inputs!$B:$B,Inputs!P:P) -> 244.6 | G27: =+_xlfn.XLOOKUP($B27,Inputs!$B:$B,Inputs!Q:Q) -> 436.2 | H27: =H19+H21 -> 466.37152 | I27: =I19+I21 -> 498.64541 | J27: =J19+J21 -> 533.16921 | K27: =K19+K21 -> 570.10092 | L27: =L19+L21 -> 609.60967 | M27: =M19+M21 -> 651.29611 | N27: =N19+N21 -> 701.35575 | O27: =O19+O21 -> 755.40819 | ... AA27: =AA19+AA21 -> 1868.6012
B28: % of growth | E28: =IFERROR((E27-D27)/D27,"") -> 2.392283 | F28: =IFERROR((F27-E27)/E27,"") -> 0.15924171 | G28: =IFERROR((G27-F27)/F27,"") -> 0.78331971 | H28: =IFERROR(H27/G27-1,"") -> 0.069169 | I28: =IFERROR(I27/H27-1,"") -> 0.069202099 | J28: =IFERROR(J27/I27-1,"") -> 0.069235188 | K28: =IFERROR(K27/J27-1,"") -> 0.069268266 | L28: =IFERROR(L27/K27-1,"") -> 0.069301331 | M28: =IFERROR(M27/L27-1,"") -> 0.068382175 | N28: =IFERROR(N27/M27-1,"") -> 0.076861565 | O28: =IFERROR(O27/N27-1,"") -> 0.077068503 | ... AA28: =IFERROR(AA27/Z27-1,"") -> 0.079499473
B30: COGS (Cost of Goods Sold) | E30: =+_xlfn.XLOOKUP($B30,Inputs!$B:$B,Inputs!O:O) -> 192 | F30: =+_xlfn.XLOOKUP($B30,Inputs!$B:$B,Inputs!P:P) -> 193.2 | G30: =+_xlfn.XLOOKUP($B30,Inputs!$B:$B,Inputs!Q:Q) -> 320.1 | H30: =H31*H$27 -> 370.67208 | I30: =I31*I$27 -> 374.44946 | J30: =J31*J$27 -> 376.98618 | K30: =K31*K$27 -> 378.09093 | L30: =L31*L$27 -> 377.55159 | M30: =M31*M$27 -> 374.7992 | N30: =N31*N$27 -> 372.84072 | O30: =O31*O$27 -> 368.43775 | ... AA30: =AA31*AA$27 -> 1494.8809
B31: % of revenue | E31: =IFERROR(E30/E$27,"") -> 0.90995261 | F31: =IFERROR(F30/F$27,"") -> 0.789861 | G31: =IFERROR(G30/G$27,"") -> 0.73383769 | H31: 0.7948 | I31: =H31-($H$31-$Q$31)/9 -> 0.75093333 | J31: =I31-($H$31-$Q$31)/9 -> 0.70706667 | K31: =J31-($H$31-$Q$31)/9 -> 0.6632 | L31: =K31-($H$31-$Q$31)/9 -> 0.61933333 | M31: =L31-($H$31-$Q$31)/9 -> 0.57546667 | N31: =M31-($H$31-$Q$31)/9 -> 0.5316 | O31: =N31-($H$31-$Q$31)/9 -> 0.48773333 | P31: =O31-($H$31-$Q$31)/9 -> 0.44386667 | Q31: 0.4 | R31: =Q31-($Q$31-$AA$31)/10 -> 0.44 | S31: =R31-($Q$31-$AA$31)/10 -> 0.48 | T31: =S31-($Q$31-$AA$31)/10 -> 0.52 | U31: =T31-($Q$31-$AA$31)/10 -> 0.56 | V31: =U31-($Q$31-$AA$31)/10 -> 0.6 | W31: =V31-($Q$31-$AA$31)/10 -> 0.64 | X31: =W31-($Q$31-$AA$31)/10 -> 0.68 | Y31: =X31-($Q$31-$AA$31)/10 -> 0.72 | Z31: =Y31-($Q$31-$AA$31)/10 -> 0.76 | AA31: 0.8
B33: Gross Profit | E33: =+_xlfn.XLOOKUP($B33,Inputs!$B:$B,Inputs!O:O) -> 19 | F33: =+_xlfn.XLOOKUP($B33,Inputs!$B:$B,Inputs!P:P) -> 51.4 | G33: =+_xlfn.XLOOKUP($B33,Inputs!$B:$B,Inputs!Q:Q) -> 116.1 | H33: =+H27-H30 -> 95.699435 | I33: =+I27-I30 -> 124.19595 | J33: =+J27-J30 -> 156.18304 | K33: =+K27-K30 -> 192.00999 | L33: =+L27-L30 -> 232.05808 | M33: =+M27-M30 -> 276.49691 | N33: =+N27-N30 -> 328.51503 | O33: =+O27-O30 -> 386.97043 | ... AA33: =+AA27-AA30 -> 373.72024
B34: Gross Profit Margin | E34: =IFERROR(E33/E$27,"") -> 0.090047393 | F34: =IFERROR(F33/F$27,"") -> 0.210139 | G34: =IFERROR(G33/G$27,"") -> 0.26616231 | H34: =IFERROR(H33/H$27,"") -> 0.2052 | I34: =IFERROR(I33/I$27,"") -> 0.24906667 | J34: =IFERROR(J33/J$27,"") -> 0.29293333 | K34: =IFERROR(K33/K$27,"") -> 0.3368 | L34: =IFERROR(L33/L$27,"") -> 0.38066667 | ... AA34: =IFERROR(AA33/AA$27,"") -> 0.2
B36: SG&A (Selling, General & Administrative) | E36: =+_xlfn.XLOOKUP($B36,Inputs!$B:$B,Inputs!O:O) -> 89 | F36: =+_xlfn.XLOOKUP($B36,Inputs!$B:$B,Inputs!P:P) -> 110.3 | G36: =+_xlfn.XLOOKUP($B36,Inputs!$B:$B,Inputs!Q:Q) -> 123.8 | H36: =H37*H27 -> 132.44951 | I36: =I37*I27 -> 130.94428 | J36: =J37*J27 -> 128.60041 | K36: =K37*K27 -> 125.30818 | L36: =L37*L27 -> 120.94656 | M36: =M37*M27 -> 115.27941 | N36: =N37*N27 -> 109.13095 | O36: =O37*O27 -> 101.37578 | ... AA36: =AA37*AA27 -> 130.80208
B37: SG&A Margin | E37: =IFERROR(E36/E$27,"") -> 0.42180095 | F37: =IFERROR(F36/F$27,"") -> 0.45094031 | G37: =IFERROR(G36/G$27,"") -> 0.28381476 | H37: 0.284 | I37: =+H37-($H$37-$Q$37)/10 -> 0.2626 | J37: =+I37-($H$37-$Q$37)/10 -> 0.2412 | K37: =+J37-($H$37-$Q$37)/10 -> 0.2198 | L37: =+K37-($H$37-$Q$37)/10 -> 0.1984 | M37: =+L37-($H$37-$Q$37)/10 -> 0.177 | N37: =+M37-($H$37-$Q$37)/10 -> 0.1556 | O37: =+N37-($H$37-$Q$37)/10 -> 0.1342 | P37: =+O37-($H$37-$Q$37)/10 -> 0.1128 | Q37: 0.07 | R37: =Q37-($Q$37-$AA$37)/10 -> 0.07 | S37: =R37-($Q$37-$AA$37)/10 -> 0.07 | T37: =S37-($Q$37-$AA$37)/10 -> 0.07 | U37: =T37-($Q$37-$AA$37)/10 -> 0.07 | V37: =U37-($Q$37-$AA$37)/10 -> 0.07 | W37: =V37-($Q$37-$AA$37)/10 -> 0.07 | X37: =W37-($Q$37-$AA$37)/10 -> 0.07 | Y37: =X37-($Q$37-$AA$37)/10 -> 0.07 | Z37: =Y37-($Q$37-$AA$37)/10 -> 0.07 | AA37: 0.07
AR38: <<
B39: R&D (Research & Development) | E39: =+_xlfn.XLOOKUP($B39,Inputs!$B:$B,Inputs!O:O) -> 65.2 | F39: =+_xlfn.XLOOKUP($B39,Inputs!$B:$B,Inputs!P:P) -> 119.1 | G39: =+_xlfn.XLOOKUP($B39,Inputs!$B:$B,Inputs!Q:Q) -> 174.4 | H39: =G39*(1+H40) -> 218 | I39: =H39*(1+I40) -> 269.23 | J39: =I39*(1+J40) -> 328.4606 | K39: =J39*(1+K40) -> 395.79502 | L39: =K39*(1+L40) -> 470.99608 | M39: =L39*(1+M40) -> 553.42039 | N39: =M39*(1+N40) -> 641.96765 | O39: =N39*(1+O40) -> 735.05296 | ... AA39: =Z39*(1+AA40) -> 1613.7071
B40: % of growth | F40: =(F39/E39)-1 -> 0.82668712 | G40: =(G39/F39)-1 -> 0.4643157 | H40: 0.25 | I40: =H40-($H$40-$Q$40)/10 -> 0.235 | J40: =I40-($H$40-$Q$40)/10 -> 0.22 | K40: =J40-($H$40-$Q$40)/10 -> 0.205 | L40: =K40-($H$40-$Q$40)/10 -> 0.19 | M40: =L40-($H$40-$Q$40)/10 -> 0.175 | N40: =M40-($H$40-$Q$40)/10 -> 0.16 | O40: =N40-($H$40-$Q$40)/10 -> 0.145 | P40: =O40-($H$40-$Q$40)/10 -> 0.13 | Q40: 0.1 | R40: =+Q40-($Q$40-$AA$40)/10 -> 0.0925 | S40: =+R40-($Q$40-$AA$40)/10 -> 0.085 | T40: =+S40-($Q$40-$AA$40)/10 -> 0.0775 | U40: =+T40-($Q$40-$AA$40)/10 -> 0.07 | V40: =+U40-($Q$40-$AA$40)/10 -> 0.0625 | W40: =+V40-($Q$40-$AA$40)/10 -> 0.055 | X40: =+W40-($Q$40-$AA$40)/10 -> 0.0475 | Y40: =+X40-($Q$40-$AA$40)/10 -> 0.04 | Z40: =+Y40-($Q$40-$AA$40)/10 -> 0.0325 | AA40: 0.025
B42: Other Operating (Income) Expenses | E42: =+_xlfn.XLOOKUP($B42,Inputs!$B:$B,Inputs!O:O) -> 0 | F42: =+_xlfn.XLOOKUP($B42,Inputs!$B:$B,Inputs!P:P) -> 0 | G42: =+_xlfn.XLOOKUP($B42,Inputs!$B:$B,Inputs!Q:Q) -> 0 | H42: =IFERROR(AVERAGE(E42:G42)*(1+H28),"") -> 0 | I42: =IFERROR(AVERAGE(F42:H42)*(1+I28),"") -> 0 | J42: =IFERROR(AVERAGE(G42:I42)*(1+J28),"") -> 0 | K42: =IFERROR(AVERAGE(H42:J42)*(1+K28),"") -> 0 | L42: =IFERROR(AVERAGE(I42:K42)*(1+L28),"") -> 0 | M42: =IFERROR(AVERAGE(J42:L42)*(1+M28),"") -> 0 | N42: =IFERROR(AVERAGE(K42:M42)*(1+N28),"") -> 0 | O42: =IFERROR(AVERAGE(L42:N42)*(1+O28),"") -> 0 | ... Q42: =IFERROR(AVERAGE(N42:P42)*(1+Q28),"") -> 0 | AA42: =S42*1000000 -> 0
B44: EBITDA | E44: =+_xlfn.XLOOKUP($B44,Inputs!$B:$B,Inputs!O:O) -> -135.2 | F44: =+_xlfn.XLOOKUP($B44,Inputs!$B:$B,Inputs!P:P) -> -178 | G44: =+_xlfn.XLOOKUP($B44,Inputs!$B:$B,Inputs!Q:Q) -> -182.1 | H44: =IFERROR(H33-H36-H39-H42,"") -> -254.75008 | I44: =IFERROR(I33-I36-I39-I42,"") -> -275.97833 | J44: =IFERROR(J33-J36-J39-J42,"") -> -300.87798 | K44: =IFERROR(K33-K36-K39-K42,"") -> -329.09322 | L44: =IFERROR(L33-L36-L39-L42,"") -> -359.88455 | M44: =IFERROR(M33-M36-M39-M42,"") -> -392.20289 | N44: =IFERROR(N33-N36-N39-N42,"") -> -422.58358 | O44: =IFERROR(O33-O36-O39-O42,"") -> -449.45831 | ... AA44: =IFERROR(AA33-AA36-AA39-AA42,"") -> -1370.7889
B45: EBITDA Margin | E45: =IFERROR(E44/E$27,"") -> -0.64075829 | F45: =IFERROR(F44/F$27,"") -> -0.72771872 | G45: =IFERROR(G44/G$27,"") -> -0.41746905 | H45: =IFERROR(H44/H$27,"") -> -0.54623849 | I45: =IFERROR(I44/I$27,"") -> -0.55345609 | J45: =IFERROR(J44/J$27,"") -> -0.56431987 | K45: =IFERROR(K44/K$27,"") -> -0.57725431 | L45: =IFERROR(L44/L$27,"") -> -0.59035243 | ... AA45: =IFERROR(AA44/AA$27,"") -> -0.73359094
B47: D&A (Depreciation & Amortization) | E47: =+_xlfn.XLOOKUP($B47,Inputs!$B:$B,Inputs!O:O) -> 29.43 | F47: =+_xlfn.XLOOKUP($B47,Inputs!$B:$B,Inputs!P:P) -> 28.5 | G47: =+_xlfn.XLOOKUP($B47,Inputs!$B:$B,Inputs!Q:Q) -> 31.87 | H47: =+IFERROR(H50+H53,"") -> 35.227154 | I47: =+IFERROR(I50+I53,"") -> 37.700125 | J47: =+IFERROR(J50+J53,"") -> 42.324259 | K47: =+IFERROR(K50+K53,"") -> 46.981322 | L47: =+IFERROR(L50+L53,"") -> 51.262669 | M47: =+IFERROR(M50+M53,"") -> 56.056384 | N47: =+IFERROR(N50+N53,"") -> 60.815854 | O47: =+IFERROR(O50+O53,"") -> 65.526286 | ... AA47: =+IFERROR(AA50+AA53,"") -> 139.88357
B48: % of PP&E+ROU Assets+Intangibles excl. Goodwill | E48: =IFERROR(E47/AVERAGE(Inputs!O39+Inputs!O42+Inputs!O44,Inputs!N39+Inputs!N42+Inputs!N44),"") -> 0.16327323 | F48: =IFERROR(F47/AVERAGE(Inputs!P39+Inputs!P42+Inputs!P44,Inputs!O39+Inputs!O42+Inputs!O44),"") -> 0.11085181 | G48: =IFERROR(G47/AVERAGE(Inputs!Q39+Inputs!Q42+Inputs!Q44,Inputs!P39+Inputs!P42+Inputs!P44),"") -> 0.10203298 | H48: =IFERROR(H47/(G96+G102),"") -> 0.10953717 | I48: =IFERROR(I47/(H96+H102),"") -> 0.10322458 | J48: =IFERROR(J47/(I96+I102),"") -> 0.10509786 | K48: =IFERROR(K47/(J96+J102),"") -> 0.10721347 | L48: =IFERROR(L47/(K96+K102),"") -> 0.10814643 | M48: =IFERROR(M47/(L96+L102),"") -> 0.11089711 | N48: =IFERROR(N47/(M96+M102),"") -> 0.11403775 | O48: =IFERROR(O47/(N96+N102),"") -> 0.1176183 | ... AA48: =IFERROR(AA47/(Z96+Z102),"") -> 0.20347492
B50: Depreciation Expense | E50: =+_xlfn.XLOOKUP($B50,Inputs!$B:$B,Inputs!O:O) -> 16.2 | F50: =+_xlfn.XLOOKUP($B50,Inputs!$B:$B,Inputs!P:P) -> 15.4 | G50: =+_xlfn.XLOOKUP($B50,Inputs!$B:$B,Inputs!Q:Q) -> 19.8 | H50: =IFERROR(H51*(G97+G98),"") -> 21.681 | I50: =IFERROR(I51*(H97+H98),"") -> 25.991151 | J50: =IFERROR(J51*(I97+I98),"") -> 30.180809 | K50: =IFERROR(K51*(J97+J98),"") -> 34.51513 | L50: =IFERROR(L51*(K97+K98),"") -> 39.156464 | M50: =IFERROR(M51*(L97+L98),"") -> 43.817768 | N50: =IFERROR(N51*(M97+M98),"") -> 48.545516 | O50: =IFERROR(O51*(N97+N98),"") -> 53.321233 | ... AA50: =IFERROR(AA51*(Z97+Z98),"") -> 127.65118
B51: % of PP&E+ROU Assets | E51: =IFERROR(E50/AVERAGE(Inputs!O40+Inputs!O42,Inputs!N40+Inputs!N42),"") -> 0.10629921 | F51: =IFERROR(F50/AVERAGE(Inputs!P40+Inputs!P42,Inputs!O40+Inputs!O42),"") -> 0.067292987 | G51: =IFERROR(G50/AVERAGE(Inputs!Q40+Inputs!Q42,Inputs!P40+Inputs!P42),"") -> 0.066287245 | H51: 0.066 | I51: 0.066 | J51: 0.066 | K51: 0.066 | L51: 0.066 | M51: 0.066 | N51: 0.066 | O51: 0.066 | P51: 0.066 | Q51: 0.066 | R51: 0.066 | S51: 0.066 | T51: 0.066 | U51: 0.066 | V51: 0.066 | W51: 0.066 | X51: 0.066 | Y51: 0.066 | Z51: 0.066 | AA51: 0.066
B53: Amortization Expense | E53: =+_xlfn.XLOOKUP($B53,Inputs!$B:$B,Inputs!O:O) -> 13.23 | F53: =+_xlfn.XLOOKUP($B53,Inputs!$B:$B,Inputs!P:P) -> 13.1 | G53: =+_xlfn.XLOOKUP($B53,Inputs!$B:$B,Inputs!Q:Q) -> 12.07 | H53: =+H54*G102 -> 13.546154 | I53: =+I54*H102 -> 11.708974 | J53: =+J54*I102 -> 12.14345 | K53: =+K54*J102 -> 12.466193 | L53: =+L54*K102 -> 12.106206 | M53: =+M54*L102 -> 12.238616 | N53: =+N54*M102 -> 12.270338 | O53: =+O54*N102 -> 12.205053 | ... AA53: =+AA54*Z102 -> 12.232383
B54: % of Intangibles excl. Goodwill | E54: =IFERROR(E53/AVERAGE(Inputs!N45:O45),"") -> 0.32466258 | F54: =IFERROR(F53/AVERAGE(Inputs!O45:P45),"") -> 0.17726658 | G54: =IFERROR(G53/AVERAGE(Inputs!P45:Q45),"") -> 0.19037855 | H54: =AVERAGE(E54:G54) -> 0.23076923 | I54: =AVERAGE(F54:H54) -> 0.19947145 | J54: =AVERAGE(G54:I54) -> 0.20687308 | K54: =AVERAGE(H54:J54) -> 0.21237126 | L54: =AVERAGE(I54:K54) -> 0.2062386 | M54: =AVERAGE(J54:L54) -> 0.20849431 | N54: =AVERAGE(K54:M54) -> 0.20903472 | O54: =AVERAGE(L54:N54) -> 0.20792254 | ... AA54: =AVERAGE(X54:Z54) -> 0.20838812
B56: Operating Income (EBIT) | E56: =+_xlfn.XLOOKUP($B56,Inputs!$B:$B,Inputs!O:O) -> -105.77 | F56: =+_xlfn.XLOOKUP($B56,Inputs!$B:$B,Inputs!P:P) -> -149.5 | G56: =+_xlfn.XLOOKUP($B56,Inputs!$B:$B,Inputs!Q:Q) -> -150.23 | H56: =+IFERROR(H44-H47,"") -> -289.97723 | I56: =+IFERROR(I44-I47,"") -> -313.67846 | J56: =+IFERROR(J44-J47,"") -> -343.20224 | K56: =+IFERROR(K44-K47,"") -> -376.07454 | L56: =+IFERROR(L44-L47,"") -> -411.14722 | M56: =+IFERROR(M44-M47,"") -> -448.25928 | N56: =+IFERROR(N44-N47,"") -> -483.39943 | O56: =+IFERROR(O44-O47,"") -> -514.9846 | ... AA56: =+IFERROR(AA44-AA47,"") -> -1510.6725
B57: Operating Margin | E57: =IFERROR(E56/E$27,"") -> -0.50127962 | F57: =IFERROR(F56/F$27,"") -> -0.61120196 | G57: =IFERROR(G56/G$27,"") -> -0.34440624 | H57: =IFERROR(H56/H27,"") -> -0.62177303 | I57: =IFERROR(I56/I27,"") -> -0.62906117 | J57: =IFERROR(J56/J27,"") -> -0.64370228 | K57: =IFERROR(K56/K27,"") -> -0.65966309 | L57: =IFERROR(L56/L27,"") -> -0.6744434 | M57: =IFERROR(M56/M27,"") -> -0.68825726 | N57: =IFERROR(N56/N27,"") -> -0.68923571 | O57: =IFERROR(O56/O27,"") -> -0.68173023 | ... AA57: =IFERROR(AA56/AA27,"") -> -0.80845099
B59: Net Interest Expense (Income) | E59: =+_xlfn.XLOOKUP($B59,Inputs!$B:$B,Inputs!O:O) -> 7.8 | F59: =+_xlfn.XLOOKUP($B59,Inputs!$B:$B,Inputs!P:P) -> 4.2 | G59: =+_xlfn.XLOOKUP($B59,Inputs!$B:$B,Inputs!Q:Q) -> 4 | H59: =-H62-H65 -> 0 | I59: =-I62-I65 -> 0 | J59: =-J62-J65 -> 0 | K59: =-K62-K65 -> 0 | L59: =-L62-L65 -> 0 | M59: =-M62-M65 -> 0 | N59: =-N62-N65 -> 0 | O59: =-O62-O65 -> 0 | ... AA59: =-AA62-AA65 -> 0
B60: % of Net Debt | E60: =IFERROR(E59/AVERAGE(Inputs!N115:O115),"") -> -0.01714851 | F60: =IFERROR(F59/AVERAGE(Inputs!O115:P115),"") -> -0.019060585 | G60: =IFERROR(G59/AVERAGE(Inputs!P115:Q115),"") -> -0.15122873 | H60: =IFERROR(H59/AVERAGE(G113+G115,H113+H115),"") -> 0 | I60: =IFERROR(I59/AVERAGE(H113+H115,I113+I115),"") | J60: =IFERROR(J59/AVERAGE(I113+I115,J113+J115),"") | K60: =IFERROR(K59/AVERAGE(J113+J115,K113+K115),"") | L60: =IFERROR(L59/AVERAGE(K113+K115,L113+L115),"") | M60: =IFERROR(M59/AVERAGE(L113+L115,M113+M115),"") | N60: =IFERROR(N59/AVERAGE(M113+M115,N113+N115),"") | O60: =IFERROR(O59/AVERAGE(N113+N115,O113+O115),"") | ... Q60: =IFERROR(Q59/AVERAGE(P113+P115,Q113+Q115),"")
B62: Interest Expense | E62: =+_xlfn.XLOOKUP($B62,Inputs!$B:$B,Inputs!O:O) -> 7.8 | F62: =+_xlfn.XLOOKUP($B62,Inputs!$B:$B,Inputs!P:P) -> 4.2 | G62: =+_xlfn.XLOOKUP($B62,Inputs!$B:$B,Inputs!Q:Q) -> 4
B63: % of Debt | E63: =+IFERROR(E62/AVERAGE(Inputs!N112:O112),"") -> 0.061635717 | F63: =+IFERROR(F62/AVERAGE(Inputs!O112:P112),"") -> 0.030445814 | G63: =+IFERROR(G62/AVERAGE(Inputs!P112:Q112),"") -> 0.013097577 | I63: =+IFERROR(I62/AVERAGE(Inputs!R112:S112),"") -> 0 | J63: =+IFERROR(J62/AVERAGE(Inputs!S112:T112),"") | K63: =+IFERROR(K62/AVERAGE(Inputs!T112:U112),"") | L63: =+IFERROR(L62/AVERAGE(Inputs!U112:V112),"") | M63: =+IFERROR(M62/AVERAGE(Inputs!V112:W112),"") | N63: =+IFERROR(N62/AVERAGE(Inputs!W112:X112),"") | O63: =+IFERROR(O62/AVERAGE(Inputs!X112:Y112),"") | P63: =+IFERROR(P62/AVERAGE(Inputs!Y112:Z112),"") | ... AA63: =+IFERROR(AA62/AVERAGE(Inputs!AJ112:AK112),"")
B65: Interest Income | E65: =+_xlfn.XLOOKUP($B65,Inputs!$B:$B,Inputs!O:O) -> 0 | F65: =+_xlfn.XLOOKUP($B65,Inputs!$B:$B,Inputs!P:P) -> 0 | G65: =+_xlfn.XLOOKUP($B65,Inputs!$B:$B,Inputs!Q:Q) -> 0
B66: % Cash & Cash Eq. & ST Investments | E66: =IFERROR(E65/+AVERAGE(Inputs!N32:O32),"") -> 0 | F66: =IFERROR(F65/+AVERAGE(Inputs!O32:P32),"") -> 0 | G66: =IFERROR(G65/+AVERAGE(Inputs!P32:Q32),"") -> 0
B68: FX (Gain) Loss | E68: =+_xlfn.XLOOKUP($B68,Inputs!$B:$B,Inputs!O:O) -> 4.4 | F68: =+_xlfn.XLOOKUP($B68,Inputs!$B:$B,Inputs!P:P) -> 0.5 | G68: =+_xlfn.XLOOKUP($B68,Inputs!$B:$B,Inputs!Q:Q) -> 0.1 | H68: =+H69*H$17 -> 0 | I68: =+I69*I$17 -> 0 | J68: =+J69*J$17 -> 0 | K68: =+K69*K$17 -> 0 | L68: =+L69*L$17 -> 0 | M68: =+M69*M$17 -> 0 | N68: =+N69*N$17 -> 0 | O68: =+O69*O$17 -> 0 | ... AA68: =+AA69*AA$17 -> 0
B69: % of revenue
B71: Other Non-Operating (Income) Expenses | E71: =+_xlfn.XLOOKUP($B71,Inputs!$B:$B,Inputs!O:O) -> -14.5 | F71: =+_xlfn.XLOOKUP($B71,Inputs!$B:$B,Inputs!P:P) -> -3.7 | G71: =+_xlfn.XLOOKUP($B71,Inputs!$B:$B,Inputs!Q:Q) -> -4.4 | H71: =IFERROR(AVERAGE(E71:G71)*(1+H28),"") -> -8.0544065 | I71: =IFERROR(AVERAGE(F71:H71)*(1+I28),"") -> -5.7574418 | J71: =IFERROR(AVERAGE(G71:I71)*(1+J28),"") -> -6.4909163 | K71: =IFERROR(AVERAGE(H71:J71)*(1+K28),"") -> -7.2363673 | L71: =IFERROR(AVERAGE(I71:K71)*(1+L28),"") -> -6.9450143 | M71: =IFERROR(AVERAGE(J71:L71)*(1+M28),"") -> -7.3619715 | N71: =IFERROR(AVERAGE(K71:M71)*(1+N28),"") -> -7.7330696 | O71: =IFERROR(AVERAGE(L71:N71)*(1+O28),"") -> -7.9128832 | ... AA71: =IFERROR(AVERAGE(X71:Z71)*(1+AA28),"") -> -12.555792
B73: Pre-Tax Income (EBT) | E73: =+_xlfn.XLOOKUP($B73,Inputs!$B:$B,Inputs!O:O) -> -103.47 | F73: =+_xlfn.XLOOKUP($B73,Inputs!$B:$B,Inputs!P:P) -> -150.5 | G73: =+_xlfn.XLOOKUP($B73,Inputs!$B:$B,Inputs!Q:Q) -> -149.93 | H73: =IFERROR(+H56-H59-H68-H71,"") -> -281.92282 | I73: =IFERROR(+I56-I59-I68-I71,"") -> -307.92102 | J73: =IFERROR(+J56-J59-J68-J71,"") -> -336.71132 | K73: =IFERROR(+K56-K59-K68-K71,"") -> -368.83817 | L73: =IFERROR(+L56-L59-L68-L71,"") -> -404.20221 | M73: =IFERROR(+M56-M59-M68-M71,"") -> -440.89731 | N73: =IFERROR(+N56-N59-N68-N71,"") -> -475.66636 | O73: =IFERROR(+O56-O59-O68-O71,"") -> -507.07171 | ... AA73: =IFERROR(+AA56-AA59-AA68-AA71,"") -> -1498.1167
B75: Tax Expense (Benefits) | E75: =+_xlfn.XLOOKUP($B75,Inputs!$B:$B,Inputs!O:O) -> 3 | F75: =+_xlfn.XLOOKUP($B75,Inputs!$B:$B,Inputs!P:P) -> 3.7 | G75: =+_xlfn.XLOOKUP($B75,Inputs!$B:$B,Inputs!Q:Q) -> 0.8 | H75: =IFERROR(H76*H$56,"") -> 5.6946166 | I75: =IFERROR(I76*I$56,"") -> 5.1818314 | J75: =IFERROR(J76*J$56,"") -> 4.7468917 | K75: =IFERROR(K76*K$56,"") -> 6.2665167 | L75: =IFERROR(L76*L$56,"") -> 6.4431852 | M75: =IFERROR(M76*M$56,"") -> 6.89802 | N75: =IFERROR(N76*N$56,"") -> 7.6897023 | O75: =IFERROR(O76*O$56,"") -> 8.06247 | ... AA75: =IFERROR(AA76*AA$56,"") -> 23.709947
B76: % of EBT | E76: =IFERROR(E75/E73,"") -> -0.028993911 | F76: =IFERROR(F75/F73,"") -> -0.024584718 | G76: =IFERROR(G75/G73,"") -> -0.0053358234 | H76: =IFERROR(AVERAGE(E76:G76),"") -> -0.019638151 | I76: =IFERROR(AVERAGE(F76:H76),"") -> -0.016519564 | J76: =IFERROR(AVERAGE(G76:I76),"") -> -0.013831179 | K76: =IFERROR(AVERAGE(H76:J76),"") -> -0.016662965 | L76: =IFERROR(AVERAGE(I76:K76),"") -> -0.015671236 | M76: =IFERROR(AVERAGE(J76:L76),"") -> -0.01538846 | N76: =IFERROR(AVERAGE(K76:M76),"") -> -0.015907554 | O76: =IFERROR(AVERAGE(L76:N76),"") -> -0.01565575 | ... AA76: =IFERROR(AVERAGE(X76:Z76),"") -> -0.015694962
B78: Net Income | E78: =+_xlfn.XLOOKUP($B78,Inputs!$B:$B,Inputs!O:O) -> -106.47 | F78: =+_xlfn.XLOOKUP($B78,Inputs!$B:$B,Inputs!P:P) -> -154.2 | G78: =+_xlfn.XLOOKUP($B78,Inputs!$B:$B,Inputs!Q:Q) -> -150.73 | H78: =IFERROR(+H73-H75,"") -> -287.61744 | I78: =IFERROR(+I73-I75,"") -> -313.10285 | J78: =IFERROR(+J73-J75,"") -> -341.45821 | K78: =IFERROR(+K73-K75,"") -> -375.10469 | L78: =IFERROR(+L73-L75,"") -> -410.64539 | M78: =IFERROR(+M73-M75,"") -> -447.79533 | N78: =IFERROR(+N73-N75,"") -> -483.35606 | O78: =IFERROR(+O73-O75,"") -> -515.13418 | ... AA78: =IFERROR(+AA73-AA75,"") -> -1521.8266
B79: Net Income Margin | E79: =IFERROR(E78/E$27,"") -> -0.50459716 | F79: =IFERROR(F78/F$27,"") -> -0.63041701 | G79: =IFERROR(G78/G$27,"") -> -0.3455525 | H79: =IFERROR(H78/H$27,"") -> -0.61671313 | I79: =IFERROR(I78/I$27,"") -> -0.62790682 | J79: =IFERROR(J78/J$27,"") -> -0.64043123 | K79: =IFERROR(K78/K$27,"") -> -0.6579619 | L79: =IFERROR(L78/L$27,"") -> -0.67362021 | ... AA79: =IFERROR(AA78/AA$27,"") -> -0.81442024
A81: x | B81: Balance Sheet | E81: =E25 -> 2022 | F81: =F25 -> 2023 | G81: =G25 -> 2024 | H81: =H25 -> 2025 | I81: =I25 -> 2026 | J81: =J25 -> 2027 | K81: =K25 -> 2028 | L81: =L25 -> 2029 | ... Q81: =Q25 -> 2034 | R81: =+Q81+1 -> 2035 | S81: =+R81+1 -> 2036 | T81: =+S81+1 -> 2037 | U81: =+T81+1 -> 2038 | V81: =+U81+1 -> 2039 | W81: =+V81+1 -> 2040 | X81: =+W81+1 -> 2041 | Y81: =+X81+1 -> 2042 | ... AA81: =+Z81+1 -> 2044
B83: Assets
B85: Cash & Cash Equivalents & ST Investments | E85: =+_xlfn.XLOOKUP($B85,Inputs!$B:$B,Inputs!O:O) -> 471.8 | F85: =+_xlfn.XLOOKUP($B85,Inputs!$B:$B,Inputs!P:P) -> 244.8 | G85: =+_xlfn.XLOOKUP($B85,Inputs!$B:$B,Inputs!Q:Q) -> 418.9 | H85: =IFERROR(G85+H163,"") -> -348.54247 | I85: =IFERROR(H85+I163,"") -> -819.64739 | J85: =IFERROR(I85+J163,"") -> -1760.1541 | K85: =IFERROR(J85+K163,"") -> -2377.771 | L85: =IFERROR(K85+L163,"") -> -3317.321 | M85: =IFERROR(L85+M163,"") -> -4048.5419 | N85: =IFERROR(M85+N163,"") -> -5074.571 | O85: =IFERROR(N85+O163,"") -> -5873.8797 | ... AA85: =IFERROR(Z85+AA163,"") -> -22475.64
B87: Accounts Receivable | E87: =+_xlfn.XLOOKUP($B87,Inputs!$B:$B,Inputs!O:O) -> 36.6 | F87: =+_xlfn.XLOOKUP($B87,Inputs!$B:$B,Inputs!P:P) -> 35.2 | G87: =+_xlfn.XLOOKUP($B87,Inputs!$B:$B,Inputs!Q:Q) -> 36.4 | H87: =IFERROR(H88*H27/365,"") -> 39.024376 | I87: =IFERROR(I88*I27/365,"") -> 41.724944 | J87: =IFERROR(J88*J27/365,"") -> 44.613779 | K87: =IFERROR(K88*K27/365,"") -> 47.704098 | L87: =IFERROR(L88*L27/365,"") -> 51.010055 | M87: =IFERROR(M88*M27/365,"") -> 54.498234 | N87: =IFERROR(N88*N27/365,"") -> 58.687053 | O87: =IFERROR(O88*O27/365,"") -> 63.209977 | ... AA87: =IFERROR(AA88*AA27/365,"") -> 156.35816
B88: DSO | E88: =IFERROR(E87/E27*365,"") -> 63.312796 | F88: =IFERROR(F87/F27*365,"") -> 52.526574 | G88: =IFERROR(G87/G27*366,"") -> 30.541953 | H88: =G88 -> 30.541953 | I88: =H88 -> 30.541953 | J88: =I88 -> 30.541953 | K88: =J88 -> 30.541953 | L88: =K88 -> 30.541953 | M88: =L88 -> 30.541953 | N88: =M88 -> 30.541953 | O88: =N88 -> 30.541953 | ... AA88: =Z88 -> 30.541953
B90: Inventory | E90: =+_xlfn.XLOOKUP($B90,Inputs!$B:$B,Inputs!O:O) -> 92.3 | F90: =+_xlfn.XLOOKUP($B90,Inputs!$B:$B,Inputs!P:P) -> 107.9 | G90: =+_xlfn.XLOOKUP($B90,Inputs!$B:$B,Inputs!Q:Q) -> 119.1 | H90: =+IFERROR(H91*H30/365,"") -> 137.91642 | I90: =+IFERROR(I91*I30/365,"") -> 139.32187 | J90: =+IFERROR(J91*J30/365,"") -> 140.26571 | K90: =+IFERROR(K91*K30/365,"") -> 140.67676 | L90: =+IFERROR(L91*L30/365,"") -> 140.47608 | M90: =+IFERROR(M91*M30/365,"") -> 139.452 | N90: =+IFERROR(N91*N30/365,"") -> 138.7233 | O90: =+IFERROR(O91*O30/365,"") -> 137.08509 | ... AA90: =+IFERROR(AA91*AA30/365,"") -> 556.20219
B91: DIH | E91: =IFERROR(E90/E30*365,"") -> 175.46615 | F91: =IFERROR(F90/F30*365,"") -> 203.84834 | G91: =IFERROR(G90/G30*365,"") -> 135.806 | H91: =G91 -> 135.806 | I91: =H91 -> 135.806 | J91: =I91 -> 135.806 | K91: =J91 -> 135.806 | L91: =K91 -> 135.806 | M91: =L91 -> 135.806 | N91: =M91 -> 135.806 | O91: =N91 -> 135.806 | ... AA91: =Z91 -> 135.806
B93: Prepaid expenses and Other Current Assets | E93: =+_xlfn.XLOOKUP($B93,Inputs!$B:$B,Inputs!O:O) -> 61.6 | F93: =+_xlfn.XLOOKUP($B93,Inputs!$B:$B,Inputs!P:P) -> 88.8 | G93: =+_xlfn.XLOOKUP($B93,Inputs!$B:$B,Inputs!Q:Q) -> 118.2 | H93: =IFERROR(AVERAGE(E93:G93)*(1+H28),"") -> 95.726264 | I93: =IFERROR(AVERAGE(F93:H93)*(1+I28),"") -> 107.89185 | J93: =IFERROR(AVERAGE(G93:I93)*(1+J28),"") -> 114.69975 | K93: =IFERROR(AVERAGE(H93:J93)*(1+K28),"") -> 113.45573 | L93: =IFERROR(AVERAGE(I93:K93)*(1+L28),"") -> 119.77862 | M93: =IFERROR(AVERAGE(J93:L93)*(1+M28),"") -> 123.90887 | N93: =IFERROR(AVERAGE(K93:M93)*(1+N28),"") -> 128.19793 | O93: =IFERROR(AVERAGE(L93:N93)*(1+O28),"") -> 133.51536 | ... AA93: =IFERROR(AVERAGE(X93:Z93)*(1+AA28),"") -> 210.53211
B94: % of revenue | E94: =IFERROR(E93/E$27,"") -> 0.29194313 | F94: =IFERROR(F93/F$27,"") -> 0.3630417 | G94: =IFERROR(G93/G$27,"") -> 0.27097662 | H94: =H93/H27 -> 0.20525753 | I94: =I93/I27 -> 0.21636989 | J94: =J93/J27 -> 0.21512823 | K94: =K93/K27 -> 0.19900991 | L94: =L93/L27 -> 0.19648412 | M94: =M93/M27 -> 0.19024966 | N94: =N93/N27 -> 0.18278589 | O94: =O93/O27 -> 0.17674598 | ... AA94: =AA93/AA27 -> 0.1126683
B96: Net PP&E (Property, Plant and Equipment) + ROU Assets | E96: =+E97+E98-E100 -> 152.4 | F96: =+F97+F98-F100 -> 219.8 | G96: =+G97+G98-G100 -> 262.9 | H96: =IFERROR(H97+H98-H100,"") -> 306.52432 | I96: =IFERROR(I97+I98-I100,"") -> 344.01284 | J96: =IFERROR(J97+J98-J100,"") -> 379.50355 | K96: =IFERROR(K97+K98-K100,"") -> 415.31166 | L96: =IFERROR(L97+L98-L100,"") -> 446.78102 | M96: =IFERROR(M97+M98-M100,"") -> 474.5958 | N96: =IFERROR(N97+N98-N100,"") -> 498.40963 | O96: =IFERROR(O97+O98-O100,"") -> 516.44751 | ... AA96: =IFERROR(AA97+AA98-AA100,"") -> 637.30116
B97: Gross PP&E (Property, Plant and Equipment) + ROU Assets | E97: =+_xlfn.XLOOKUP("Gross PP&E (Property, Plant and Equipment)",Inputs!$B:$B,Inputs!O:O) -> 188.8 | F97: =+_xlfn.XLOOKUP("Gross PP&E (Property, Plant and Equipment)",Inputs!$B:$B,Inputs!P:P) -> 268.9 | G97: =+_xlfn.XLOOKUP("Gross PP&E (Property, Plant and Equipment)",Inputs!$B:$B,Inputs!Q:Q) -> 328.5 | H97: =+IFERROR(G97-H131,"") -> 393.80532 | I97: =+IFERROR(H97-I131,"") -> 457.28499 | J97: =+IFERROR(I97-J131,"") -> 522.95651 | K97: =+IFERROR(J97-K131,"") -> 593.27975 | L97: =+IFERROR(K97-L131,"") -> 663.90557 | M97: =+IFERROR(L97-M131,"") -> 735.53812 | N97: =+IFERROR(M97-N131,"") -> 807.89747 | O97: =+IFERROR(N97-O131,"") -> 879.25658 | ... AA97: =+IFERROR(Z97-AA131,"") -> 2070.2879
B98: Right-of-Use Assets | E98: =+_xlfn.XLOOKUP("Right-of-Use Assets",Inputs!$B:$B,Inputs!O:O) -> 0 | F98: =+_xlfn.XLOOKUP("Right-of-Use Assets",Inputs!$B:$B,Inputs!P:P) -> 0 | G98: =+_xlfn.XLOOKUP("Right-of-Use Assets",Inputs!$B:$B,Inputs!Q:Q) -> 0 | H98: =IFERROR(H99*H$27,"") -> 0 | I98: =IFERROR(I99*I$27,"") -> 0 | J98: =IFERROR(J99*J$27,"") -> 0 | K98: =IFERROR(K99*K$27,"") -> 0 | L98: =IFERROR(L99*L$27,"") -> 0 | M98: =IFERROR(M99*M$27,"") -> 0 | N98: =IFERROR(N99*N$27,"") -> 0 | O98: =IFERROR(O99*O$27,"") -> 0 | ... AA98: =IFERROR(AA99*AA$27,"") -> 0
B99: % of revenue | E99: =IFERROR(E98/E$27,"") -> 0 | F99: =IFERROR(F98/F$27,"") -> 0 | G99: =IFERROR(G98/G$27,"") -> 0 | H99: =IFERROR(AVERAGE(E99:G99),"") -> 0 | I99: =IFERROR(AVERAGE(F99:H99),"") -> 0 | J99: =IFERROR(AVERAGE(G99:I99),"") -> 0 | K99: =IFERROR(AVERAGE(H99:J99),"") -> 0 | L99: =IFERROR(AVERAGE(I99:K99),"") -> 0 | M99: =IFERROR(AVERAGE(J99:L99),"") -> 0 | N99: =IFERROR(AVERAGE(K99:M99),"") -> 0 | O99: =IFERROR(AVERAGE(L99:N99),"") -> 0 | ... AA99: =IFERROR(AVERAGE(X99:Z99),"") -> 0
B100: Accumulated Depreciation | E100: =+_xlfn.XLOOKUP($B100,Inputs!$B:$B,Inputs!O:O) -> 36.4 | F100: =+_xlfn.XLOOKUP($B100,Inputs!$B:$B,Inputs!P:P) -> 49.1 | G100: =+_xlfn.XLOOKUP($B100,Inputs!$B:$B,Inputs!Q:Q) -> 65.6 | H100: =+IFERROR(G100+H50,"") -> 87.281 | I100: =+IFERROR(H100+I50,"") -> 113.27215 | J100: =+IFERROR(I100+J50,"") -> 143.45296 | K100: =+IFERROR(J100+K50,"") -> 177.96809 | L100: =+IFERROR(K100+L50,"") -> 217.12455 | M100: =+IFERROR(L100+M50,"") -> 260.94232 | N100: =+IFERROR(M100+N50,"") -> 309.48784 | O100: =+IFERROR(N100+O50,"") -> 362.80907 | ... AA100: =+IFERROR(Z100+AA50,"") -> 1432.9868
B102: Intangibles excl. Goodwill | E102: =+_xlfn.XLOOKUP($B102,Inputs!$B:$B,Inputs!O:O) -> 79.7 | F102: =+_xlfn.XLOOKUP($B102,Inputs!$B:$B,Inputs!P:P) -> 68.1 | G102: =+_xlfn.XLOOKUP($B102,Inputs!$B:$B,Inputs!Q:Q) -> 58.7 | H102: =+G102+H103*H39 -> 58.7 | I102: =+H102+I103*I39 -> 58.7 | J102: =+I102+J103*J39 -> 58.7 | K102: =+J102+K103*K39 -> 58.7 | L102: =+K102+L103*L39 -> 58.7 | M102: =+L102+M103*M39 -> 58.7 | N102: =+M102+N103*N39 -> 58.7 | O102: =+N102+O103*O39 -> 58.7 | ... AA102: =+Z102+AA103*AA39 -> 58.7
B103: growing with % of R&D | E103: =IFERROR((E102-Inputs!N45)/E39,"") -> 1.1947853 | F103: =IFERROR((F102-E102)/F39,"") -> -0.097397145 | G103: =IFERROR((G102-F102)/G39,"") -> -0.053899083
B105: Liabilities
B107: Accounts Payable | E107: =+_xlfn.XLOOKUP($B107,Inputs!$B:$B,Inputs!O:O) -> 20.8 | F107: =+_xlfn.XLOOKUP($B107,Inputs!$B:$B,Inputs!P:P) -> 34.9 | G107: =+_xlfn.XLOOKUP($B107,Inputs!$B:$B,Inputs!Q:Q) -> 72.5 | H107: =+IFERROR(H108*H30/365,"") -> 84.184169 | I107: =+IFERROR(I108*I30/365,"") -> 85.042057 | J107: =+IFERROR(J108*J30/365,"") -> 85.618178 | K107: =+IFERROR(K108*K30/365,"") -> 85.869081 | L107: =+IFERROR(L108*L30/365,"") -> 85.74659 | M107: =+IFERROR(M108*M30/365,"") -> 85.121489 | N107: =+IFERROR(N108*N30/365,"") -> 84.676693 | O107: =+IFERROR(O108*O30/365,"") -> 83.676726 | ... AA107: =+IFERROR(AA108*AA30/365,"") -> 339.50577
B108: DPO | E108: =IFERROR(E107/E$30*365,"") -> 39.541667 | F108: =IFERROR(F107/F$30*365,"") -> 65.934265 | G108: =IFERROR(G107/G$30*366,"") -> 82.89597 | H108: =G108 -> 82.89597 | I108: =H108 -> 82.89597 | J108: =I108 -> 82.89597 | K108: =J108 -> 82.89597 | L108: =K108 -> 82.89597 | M108: =L108 -> 82.89597 | N108: =M108 -> 82.89597 | O108: =N108 -> 82.89597 | ... AA108: =Z108 -> 82.89597
B110: Accrued Expenses and Other Current Liabilities | E110: =+_xlfn.XLOOKUP($B110,Inputs!$B:$B,Inputs!O:O) -> 139.2 | F110: =+_xlfn.XLOOKUP($B110,Inputs!$B:$B,Inputs!P:P) -> 170.7 | G110: =+_xlfn.XLOOKUP($B110,Inputs!$B:$B,Inputs!Q:Q) -> 248.8 | H110: =IFERROR(AVERAGE(E110:G110)*(1+H28),"") -> 199.11491 | I110: =IFERROR(AVERAGE(F110:H110)*(1+I28),"") -> 220.47479 | J110: =IFERROR(AVERAGE(G110:I110)*(1+J28),"") -> 238.22193 | K110: =IFERROR(AVERAGE(H110:J110)*(1+K28),"") -> 234.45903 | L110: =IFERROR(AVERAGE(I110:K110)*(1+L28),"") -> 247.06412 | M110: =IFERROR(AVERAGE(J110:L110)*(1+M28),"") -> 256.32094 | N110: =IFERROR(AVERAGE(K110:M110)*(1+N28),"") -> 264.85198 | O110: =IFERROR(AVERAGE(L110:N110)*(1+O28),"") -> 275.81464 | ... AA110: =IFERROR(AVERAGE(X110:Z110)*(1+AA28),"") -> 435.02417
B111: growing with revenue | E111: =IFERROR(E110/E$27,"") -> 0.65971564 | F111: =IFERROR(F110/F$27,"") -> 0.69787408 | G111: =IFERROR(G110/G$27,"") -> 0.57038056 | H111: =IFERROR(H110/H$27,"") -> 0.42694483 | I111: =IFERROR(I110/I$27,"") -> 0.44214743 | J111: =IFERROR(J110/J$27,"") -> 0.4468036 | K111: =IFERROR(K110/K$27,"") -> 0.41125882 | L111: =IFERROR(L110/L$27,"") -> 0.40528248 | ... AA111: =IFERROR(AA110/AA$27,"") -> 0.2328074
B113: Total Borrowings | E113: =+_xlfn.XLOOKUP($B113,Inputs!$B:$B,Inputs!O:O) -> 87 | F113: =+_xlfn.XLOOKUP($B113,Inputs!$B:$B,Inputs!P:P) -> 89.8 | G113: =+_xlfn.XLOOKUP($B113,Inputs!$B:$B,Inputs!Q:Q) -> 401.2
B115: Total Leases | E115: =+_xlfn.XLOOKUP($B115,Inputs!$B:$B,Inputs!O:O) -> 37.7 | F115: =+_xlfn.XLOOKUP($B115,Inputs!$B:$B,Inputs!P:P) -> 61.4 | G115: =+_xlfn.XLOOKUP($B115,Inputs!$B:$B,Inputs!Q:Q) -> 58.4
B116: % of revenues | E116: =IFERROR(E115/E$27,"") -> 0.17867299 | F116: =IFERROR(F115/F$27,"") -> 0.25102208 | G116: =IFERROR(G115/G$27,"") -> 0.13388354
A118: x | B118: Cash Flow | E118: =E25 -> 2022 | F118: =F25 -> 2023 | G118: =G25 -> 2024 | H118: =H25 -> 2025 | I118: =I25 -> 2026 | J118: =J25 -> 2027 | K118: =K25 -> 2028 | L118: =L25 -> 2029 | ... Q118: =Q25 -> 2034 | R118: =+Q118+1 -> 2035 | S118: =+R118+1 -> 2036 | T118: =+S118+1 -> 2037 | U118: =+T118+1 -> 2038 | V118: =+U118+1 -> 2039 | W118: =+V118+1 -> 2040 | X118: =+W118+1 -> 2041 | Y118: =+X118+1 -> 2042 | ... AA118: =+Z118+1 -> 2044
B120: D&A (Depreciation & Amortization) | E120: =+E47 -> 29.43 | F120: =+F47 -> 28.5 | G120: =+G47 -> 31.87 | H120: =+H47 -> 35.227154 | I120: =+I47 -> 37.700125 | J120: =+J47 -> 42.324259 | K120: =+K47 -> 46.981322 | L120: =+L47 -> 51.262669 | ... AA120: =+AA47 -> 139.88357
B122: Stock Based Compensation | E122: =+_xlfn.XLOOKUP($B122,Inputs!$B:$B,Inputs!O:O) -> 55.6 | F122: =+_xlfn.XLOOKUP($B122,Inputs!$B:$B,Inputs!P:P) -> 53.5 | G122: =+_xlfn.XLOOKUP($B122,Inputs!$B:$B,Inputs!Q:Q) -> 56.8 | H122: =IFERROR(H123*H36,"") -> 56.016086 | I122: =IFERROR(I123*I36,"") -> 50.681149 | J122: =IFERROR(J123*J36,"") -> 45.159729 | K122: =IFERROR(K123*K36,"") -> 39.507504 | L122: =IFERROR(L123*L36,"") -> 33.792742 | M122: =IFERROR(M123*M36,"") -> 28.073051 | N122: =IFERROR(N123*N36,"") -> 22.660099 | O122: =IFERROR(O123*O36,"") -> 17.412395 | ... AA122: =IFERROR(AA123*AA36,"") -> 13.080208
B123: % of SG&A | E123: =+IFERROR(E122/E36,"") -> 0.6247191 | F123: =+IFERROR(F122/F36,"") -> 0.4850408 | G123: =+IFERROR(G122/G36,"") -> 0.45880452 | H123: =G123-($G$123-$Q$123)/10 -> 0.42292407 | I123: =H123-($G$123-$Q$123)/10 -> 0.38704362 | J123: =I123-($G$123-$Q$123)/10 -> 0.35116317 | K123: =J123-($G$123-$Q$123)/10 -> 0.31528271 | L123: =K123-($G$123-$Q$123)/10 -> 0.27940226 | M123: =L123-($G$123-$Q$123)/10 -> 0.24352181 | N123: =M123-($G$123-$Q$123)/10 -> 0.20764136 | O123: =N123-($G$123-$Q$123)/10 -> 0.1717609 | P123: =O123-($G$123-$Q$123)/10 -> 0.13588045 | Q123: 0.1 | R123: 0.1 | S123: 0.1 | T123: 0.1 | U123: 0.1 | V123: 0.1 | W123: 0.1 | X123: 0.1 | Y123: 0.1 | Z123: 0.1 | AA123: 0.1
B125: Changes in Net Working Capital | E125: =+_xlfn.XLOOKUP($B125,Inputs!$B:$B,Inputs!O:O) -> -35.5 | F125: =+_xlfn.XLOOKUP($B125,Inputs!$B:$B,Inputs!P:P) -> -6.5 | G125: =+_xlfn.XLOOKUP($B125,Inputs!$B:$B,Inputs!Q:Q) -> 38.1 | H125: =IFERROR(-((H87+H90+H93-H107-H110)-(G87+G90+G93-G107-G110)),"") -> -36.967981 | I125: =IFERROR(-((I87+I90+I93-I107-I110)-(H87+H90+H93-H107-H110)),"") -> 5.9461578 | J125: =IFERROR(-((J87+J90+J93-J107-J110)-(I87+I90+I93-I107-I110)),"") -> 7.6826864 | K125: =IFERROR(-((K87+K90+K93-K107-K110)-(J87+J90+J93-J107-J110)),"") -> -5.7693396 | L125: =IFERROR(-((L87+L90+L93-L107-L110)-(K87+K90+K93-K107-K110)),"") -> 3.0544246 | M125: =IFERROR(-((M87+M90+M93-M107-M110)-(L87+L90+L93-L107-L110)),"") -> 2.0373784 | N125: =IFERROR(-((N87+N90+N93-N107-N110)-(M87+M90+M93-M107-M110)),"") -> 0.33705321 | O125: =IFERROR(-((O87+O90+O93-O107-O110)-(N87+N90+N93-N107-N110)),"") -> 1.7605614 | ... AA125: =IFERROR(-((AA87+AA90+AA93-AA107-AA110)-(Z87+Z90+Z93-Z107-Z110)),"") -> -29.018858
B127: Other Operating Adjustments | E127: =+_xlfn.XLOOKUP($B127,Inputs!$B:$B,Inputs!O:O) -> -49.56 | F127: =+_xlfn.XLOOKUP($B127,Inputs!$B:$B,Inputs!P:P) -> -20.2 | G127: =+_xlfn.XLOOKUP($B127,Inputs!$B:$B,Inputs!Q:Q) -> -24.94 | H127: =IFERROR(AVERAGE(E127:G127)*(1+H28),"") -> -33.750101 | I127: =IFERROR(AVERAGE(F127:H127)*(1+I28),"") -> -28.116487 | J127: =IFERROR(AVERAGE(G127:I127)*(1+J28),"") -> -30.938886 | K127: =IFERROR(AVERAGE(H127:J127)*(1+K28),"") -> -33.077983 | L127: =IFERROR(AVERAGE(I127:K127)*(1+L28),"") -> -32.83944 | M127: =IFERROR(AVERAGE(J127:L127)*(1+M28),"") -> -34.493185 | N127: =IFERROR(AVERAGE(K127:M127)*(1+N28),"") -> -36.042775 | O127: =IFERROR(AVERAGE(L127:N127)*(1+O28),"") -> -37.114129 | ... AA127: =IFERROR(AVERAGE(X127:Z127)*(1+AA28),"") -> -58.757151
B129: Operating Cash Flow | E129: =+_xlfn.XLOOKUP($B129,Inputs!$B:$B,Inputs!O:O) -> -106.5 | F129: =+_xlfn.XLOOKUP($B129,Inputs!$B:$B,Inputs!P:P) -> -98.9 | G129: =+_xlfn.XLOOKUP($B129,Inputs!$B:$B,Inputs!Q:Q) -> -48.9 | H129: =IFERROR(H78+H120+H122+H125+H127,"") -> -267.09228 | I129: =IFERROR(I78+I120+I122+I125+I127,"") -> -246.8919 | J129: =IFERROR(J78+J120+J122+J125+J127,"") -> -277.23043 | K129: =IFERROR(K78+K120+K122+K125+K127,"") -> -327.46318 | L129: =IFERROR(L78+L120+L122+L125+L127,"") -> -355.375 | M129: =IFERROR(M78+M120+M122+M125+M127,"") -> -396.1217 | N129: =IFERROR(N78+N120+N122+N125+N127,"") -> -435.58583 | O129: =IFERROR(O78+O120+O122+O125+O127,"") -> -467.54907 | ... AA129: =IFERROR(AA78+AA120+AA122+AA125+AA127,"") -> -1456.6389
B131: Net CapEx | E131: =+_xlfn.XLOOKUP($B131,Inputs!$B:$B,Inputs!O:O) -> -108.2 | F131: =+_xlfn.XLOOKUP($B131,Inputs!$B:$B,Inputs!P:P) -> -70 | G131: =+_xlfn.XLOOKUP($B131,Inputs!$B:$B,Inputs!Q:Q) -> -54.6 | H131: =IFERROR(H133+H136,"") -> -65.30532 | I131: =IFERROR(I133+I136,"") -> -63.47967 | J131: =IFERROR(J133+J136,"") -> -65.671521 | K131: =IFERROR(K133+K136,"") -> -70.323242 | L131: =IFERROR(L133+L136,"") -> -70.625818 | M131: =IFERROR(M133+M136,"") -> -71.632551 | N131: =IFERROR(N133+N136,"") -> -72.35935 | O131: =IFERROR(O133+O136,"") -> -71.359112 | ... AA131: =IFERROR(AA133+AA136,"") -> -136.17908
B133: Acquisition of Fixed & Intangibles | E133: =+_xlfn.XLOOKUP($B133,Inputs!$B:$B,Inputs!O:O) -> -108.2 | F133: =+_xlfn.XLOOKUP($B133,Inputs!$B:$B,Inputs!P:P) -> -73.7 | G133: =+_xlfn.XLOOKUP($B133,Inputs!$B:$B,Inputs!Q:Q) -> -67.1 | H133: =H120*H134 -> -70.978681 | I133: =I120*I134 -> -72.547959 | J133: =J120*J134 -> -77.614218 | K133: =K120*K134 -> -81.900518 | L133: =L120*L134 -> -84.722539 | M133: =M120*M134 -> -87.569675 | N133: =N120*N134 -> -89.498344 | O133: =O120*O134 -> -90.497414 | ... AA133: =AA120*AA134 -> -181.84864
E134: =E133/E120 -> -3.6765206 | F134: =F133/F120 -> -2.5859649 | G134: =G133/G120 -> -2.1054283 | H134: =G134-($G$134-$Q$134)/10 -> -2.0148855 | I134: =H134-($G$134-$Q$134)/10 -> -1.9243426 | J134: =I134-($G$134-$Q$134)/10 -> -1.8337998 | K134: =J134-($G$134-$Q$134)/10 -> -1.743257 | L134: =K134-($G$134-$Q$134)/10 -> -1.6527142 | M134: =L134-($G$134-$Q$134)/10 -> -1.5621713 | N134: =M134-($G$134-$Q$134)/10 -> -1.4716285 | O134: =N134-($G$134-$Q$134)/10 -> -1.3810857 | P134: =O134-($G$134-$Q$134)/10 -> -1.2905428 | Q134: -1.2 | R134: -1.3 | S134: -1.3 | T134: -1.3 | U134: -1.3 | V134: -1.3 | W134: -1.3 | X134: -1.3 | Y134: -1.3 | Z134: -1.3 | AA134: -1.3
B136: Disposal of Fixed & Intangibles | E136: =+_xlfn.XLOOKUP($B136,Inputs!$B:$B,Inputs!O:O) -> 0 | F136: =+_xlfn.XLOOKUP($B136,Inputs!$B:$B,Inputs!P:P) -> 3.7 | G136: =+_xlfn.XLOOKUP($B136,Inputs!$B:$B,Inputs!Q:Q) -> 12.5 | H136: =IFERROR(H137*G97,"") -> 5.6733606 | I136: =IFERROR(I137*H97,"") -> 9.0682885 | J136: =IFERROR(J137*I97,"") -> 11.942698 | K136: =IFERROR(K137*J97,"") -> 11.577276 | L136: =IFERROR(L137*K97,"") -> 14.096721 | M136: =IFERROR(M137*L97,"") -> 15.937124 | N136: =IFERROR(N137*M97,"") -> 17.138994 | O136: =IFERROR(O137*N97,"") -> 19.138302 | ... AA136: =IFERROR(AA137*Z97,"") -> 45.669557
B137: Disposal Rate (% Gross PP&E) | E137: =IFERROR(E136/E97,"") -> 0 | F137: =IFERROR(F136/F97,"") -> 0.013759762 | G137: =IFERROR(G136/G97,"") -> 0.03805175 | H137: =IFERROR(AVERAGE(E137:G137),"") -> 0.017270504 | I137: =IFERROR(AVERAGE(F137:H137),"") -> 0.023027339 | J137: =IFERROR(AVERAGE(G137:I137),"") -> 0.026116531 | K137: =IFERROR(AVERAGE(H137:J137),"") -> 0.022138125 | L137: =IFERROR(AVERAGE(I137:K137),"") -> 0.023760665 | M137: =IFERROR(AVERAGE(J137:L137),"") -> 0.024005107 | N137: =IFERROR(AVERAGE(K137:M137),"") -> 0.023301299 | O137: =IFERROR(AVERAGE(L137:N137),"") -> 0.023689024 | ... AA137: =IFERROR(AVERAGE(X137:Z137),"") -> 0.023612713
B139: Net Cash from Investments & Acquisitions | E139: =+_xlfn.XLOOKUP($B139,Inputs!$B:$B,Inputs!O:O) -> 0.6 | F139: =+_xlfn.XLOOKUP($B139,Inputs!$B:$B,Inputs!P:P) -> 0.3 | G139: =+_xlfn.XLOOKUP($B139,Inputs!$B:$B,Inputs!Q:Q) -> 2.4 | H139: 0 | I139: 0 | J139: 0 | K139: 0 | L139: 0 | M139: 0 | N139: 0 | O139: 0 | P139: 0 | Q139: 0 | R139: 0 | S139: 0 | T139: 0 | U139: 0 | V139: 0 | W139: 0 | X139: 0 | Y139: 0 | Z139: 0 | AA139: 0
B141: Other Investing Inflows (Outflows) | E141: =+_xlfn.XLOOKUP($B141,Inputs!$B:$B,Inputs!O:O) -> -238.5 | F141: =+_xlfn.XLOOKUP($B141,Inputs!$B:$B,Inputs!P:P) -> 81.7 | G141: =+_xlfn.XLOOKUP($B141,Inputs!$B:$B,Inputs!Q:Q) -> -46.1 | H141: =IFERROR(AVERAGE(E141:G141)*(1+H28),"") -> -72.311463 | I141: =IFERROR(AVERAGE(F141:H141)*(1+I28),"") -> -13.083991 | J141: =IFERROR(AVERAGE(G141:I141)*(1+J28),"") -> -46.866522 | K141: =IFERROR(AVERAGE(H141:J141)*(1+K28),"") -> -47.141178 | L141: =IFERROR(AVERAGE(I141:K141)*(1+L28),"") -> -38.171096 | M141: =IFERROR(AVERAGE(J141:L141)*(1+M28),"") -> -47.07249 | N141: =IFERROR(AVERAGE(K141:M141)*(1+N28),"") -> -47.520022 | O141: =IFERROR(AVERAGE(L141:N141)*(1+O28),"") -> -47.665167 | ... AA141: =IFERROR(AVERAGE(X141:Z141)*(1+AA28),"") -> -76.895485
B143: Investing Cash Flow | E143: =+_xlfn.XLOOKUP($B143,Inputs!$B:$B,Inputs!O:O) -> -346.1 | F143: =+_xlfn.XLOOKUP($B143,Inputs!$B:$B,Inputs!P:P) -> 12 | G143: =+_xlfn.XLOOKUP($B143,Inputs!$B:$B,Inputs!Q:Q) -> -98.3 | H143: =IFERROR(+H131+H139+H141,"") -> -137.61678 | I143: =IFERROR(+I131+I139+I141,"") -> -76.563662 | J143: =IFERROR(+J131+J139+J141,"") -> -112.53804 | K143: =IFERROR(+K131+K139+K141,"") -> -117.46442 | L143: =IFERROR(+L131+L139+L141,"") -> -108.79691 | M143: =IFERROR(+M131+M139+M141,"") -> -118.70504 | N143: =IFERROR(+N131+N139+N141,"") -> -119.87937 | O143: =IFERROR(+O131+O139+O141,"") -> -119.02428 | ... AA143: =IFERROR(+AA131+AA139+AA141,"") -> -213.07456
B145: Dividends | E145: =+_xlfn.XLOOKUP($B145,Inputs!$B:$B,Inputs!O:O) -> 0 | F145: =+_xlfn.XLOOKUP($B145,Inputs!$B:$B,Inputs!P:P) -> 0 | G145: =+_xlfn.XLOOKUP($B145,Inputs!$B:$B,Inputs!Q:Q) -> 0 | H145: =+IFERROR(H146*_xlfn.XLOOKUP("Net Income",$B:$B,$H:$H),"") -> 0 | I145: =+IFERROR(I146*_xlfn.XLOOKUP("Net Income",$B:$B,$H:$H),"") -> 0 | J145: =+IFERROR(J146*_xlfn.XLOOKUP("Net Income",$B:$B,$H:$H),"") -> 0 | K145: =+IFERROR(K146*_xlfn.XLOOKUP("Net Income",$B:$B,$H:$H),"") -> 0 | L145: =+IFERROR(L146*_xlfn.XLOOKUP("Net Income",$B:$B,$H:$H),"") -> 0 | M145: =+IFERROR(M146*_xlfn.XLOOKUP("Net Income",$B:$B,$H:$H),"") -> 0 | N145: =+IFERROR(N146*_xlfn.XLOOKUP("Net Income",$B:$B,$H:$H),"") -> 0 | O145: =+IFERROR(O146*_xlfn.XLOOKUP("Net Income",$B:$B,$H:$H),"") -> 0 | ... AA145: =+IFERROR(AA146*_xlfn.XLOOKUP("Net Income",$B:$B,$H:$H),"") -> 0
B146: Dividend payout | E146: =IFERROR(-E145/E$78,"") -> 0 | F146: =IFERROR(-F145/F$78,"") -> 0 | G146: =IFERROR(-G145/G$78,"") -> 0
B148: Increase (Repurchase) of Shares | E148: =+_xlfn.XLOOKUP($B148,Inputs!$B:$B,Inputs!O:O) -> 3.9 | F148: =+_xlfn.XLOOKUP($B148,Inputs!$B:$B,Inputs!P:P) -> 2.4 | G148: =+_xlfn.XLOOKUP($B148,Inputs!$B:$B,Inputs!Q:Q) -> -26.1 | H148: =IFERROR(-H149*_xlfn.XLOOKUP("Net Income",$B:$B,H:H),"") -> 0 | I148: =IFERROR(-I149*_xlfn.XLOOKUP("Net Income",$B:$B,I:I),"") -> 0 | J148: =IFERROR(-J149*_xlfn.XLOOKUP("Net Income",$B:$B,J:J),"") -> 0 | K148: =IFERROR(-K149*_xlfn.XLOOKUP("Net Income",$B:$B,K:K),"") -> 0 | L148: =IFERROR(-L149*_xlfn.XLOOKUP("Net Income",$B:$B,L:L),"") -> 0 | M148: =IFERROR(-M149*_xlfn.XLOOKUP("Net Income",$B:$B,M:M),"") -> 0 | N148: =IFERROR(-N149*_xlfn.XLOOKUP("Net Income",$B:$B,N:N),"") -> 0 | O148: =IFERROR(-O149*_xlfn.XLOOKUP("Net Income",$B:$B,O:O),"") -> 0 | P148: =IFERROR(-P149*_xlfn.XLOOKUP("Net Income",$B:$B,P:P),"") -> 0 | Q148: =IFERROR(-Q149*_xlfn.XLOOKUP("Net Income",$B:$B,Q:Q),"") -> 0 | R148: =IFERROR(-R149*_xlfn.XLOOKUP("Net Income",$B:$B,R:R),"") -> 0 | S148: =IFERROR(-S149*_xlfn.XLOOKUP("Net Income",$B:$B,S:S),"") -> 0 | T148: =IFERROR(-T149*_xlfn.XLOOKUP("Net Income",$B:$B,T:T),"") -> 0 | U148: =IFERROR(-U149*_xlfn.XLOOKUP("Net Income",$B:$B,U:U),"") -> 0 | V148: =IFERROR(-V149*_xlfn.XLOOKUP("Net Income",$B:$B,V:V),"") -> 0 | W148: =IFERROR(-W149*_xlfn.XLOOKUP("Net Income",$B:$B,W:W),"") -> 0 | X148: =IFERROR(-X149*_xlfn.XLOOKUP("Net Income",$B:$B,X:X),"") -> 0 | Y148: =IFERROR(-Y149*_xlfn.XLOOKUP("Net Income",$B:$B,Y:Y),"") -> 0 | Z148: =IFERROR(-Z149*_xlfn.XLOOKUP("Net Income",$B:$B,Z:Z),"") -> 0 | AA148: =IFERROR(-AA149*_xlfn.XLOOKUP("Net Income",$B:$B,AA:AA),"") -> 0
B149: Repurchase payout | E149: =IFERROR(-E148/E$78,"") -> 0.036630037 | F149: =IFERROR(-F148/F$78,"") -> 0.015564202 | G149: =IFERROR(-G148/G$78,"") -> -0.1731573
B151: Lease Payments | E151: =+_xlfn.XLOOKUP($B151,Inputs!$B:$B,Inputs!O:O) -> 37.7 | F151: =+_xlfn.XLOOKUP($B151,Inputs!$B:$B,Inputs!P:P) -> 61.4 | G151: =+_xlfn.XLOOKUP($B151,Inputs!$B:$B,Inputs!Q:Q) -> 58.2 | H151: =+IFERROR(H152*H98,"") -> 0 | I151: =+IFERROR(I152*I98,"") -> 0 | J151: =+IFERROR(J152*J98,"") -> 0 | K151: =+IFERROR(K152*K98,"") -> 0 | L151: =+IFERROR(L152*L98,"") -> 0 | M151: =+IFERROR(M152*M98,"") -> 0 | N151: =+IFERROR(N152*N98,"") -> 0 | O151: =+IFERROR(O152*O98,"") -> 0 | ... AA151: =+IFERROR(AA152*AA98,"") -> 0
...

Sheet Inputs
B2: Inputs
B3: in millions of USD
A4: x | B4: Income Statement | G4: 2014 | H4: =+G4+1 -> 2015 | I4: =+H4+1 -> 2016 | J4: =+I4+1 -> 2017 | K4: =+J4+1 -> 2018 | L4: =+K4+1 -> 2019 | M4: =+L4+1 -> 2020 | N4: =+M4+1 -> 2021 | O4: =+N4+1 -> 2022 | ... Q4: =+P4+1 -> 2024 | R4: ="CAGR "&$G$4&" - "&$Q$4 -> CAGR 2014 - 2024
B6: Revenue (Sales) | N6: =VLOOKUP(Inputs!$B6,IS!$L$7:$P$20,IS!M$5,FALSE) -> 62.2 | O6: =VLOOKUP(Inputs!$B6,IS!$L$7:$P$20,IS!N$5,FALSE) -> 211 | P6: =VLOOKUP(Inputs!$B6,IS!$L$7:$P$20,IS!O$5,FALSE) -> 244.6 | Q6: =VLOOKUP(Inputs!$B6,IS!$L$7:$P$20,IS!P$5,FALSE) -> 436.2 | R6: =IFERROR((Q6/N6)^(1/COUNT($G$4:$Q$4))-1,"") -> 0.19371203
B7: COGS (Cost of Goods Sold) | N7: =VLOOKUP(Inputs!$B7,IS!$L$7:$P$20,IS!M$5,FALSE) -> 64.1 | O7: =VLOOKUP($B7,IS!$L$7:$P$8,IS!N$5,0) -> 192 | P7: =VLOOKUP($B7,IS!$L$7:$P$8,IS!O$5,0) -> 193.2 | Q7: =VLOOKUP($B7,IS!$L$7:$P$8,IS!P$5,0) -> 320.1 | R7: =IFERROR((Q7/N7)^(1/COUNT($G$4:$Q$4))-1,"") -> 0.1574265
B8: Gross Profit | G8: =G6-G7 -> 0 | H8: =H6-H7 -> 0 | I8: =I6-I7 -> 0 | J8: =J6-J7 -> 0 | K8: =K6-K7 -> 0 | L8: =L6-L7 -> 0 | M8: =M6-M7 -> 0 | N8: =N6-N7 -> -1.9 | ... Q8: =Q6-Q7 -> 116.1 | R8: =IFERROR((Q8/N8)^(1/COUNT($G$4:$Q$4))-1,"") -> -2.4533519
B9: SG&A (Selling, General & Administrative) | N9: =VLOOKUP(Inputs!$B9,IS!$L$7:$P$20,IS!M$5,FALSE) -> 58.4 | O9: =VLOOKUP(Inputs!$B9,IS!$L$7:$P$20,IS!N$5,FALSE) -> 89 | P9: =VLOOKUP(Inputs!$B9,IS!$L$7:$P$20,IS!O$5,FALSE) -> 110.3 | Q9: =VLOOKUP(Inputs!$B9,IS!$L$7:$P$20,IS!P$5,FALSE) -> 123.8 | R9: =IFERROR((Q9/N9)^(1/COUNT($G$4:$Q$4))-1,"") -> 0.070691476
B10: R&D (Research & Development) | N10: =VLOOKUP(Inputs!$B10,IS!$L$7:$P$20,IS!M$5,FALSE) -> 41.8 | O10: =VLOOKUP(Inputs!$B10,IS!$L$7:$P$20,IS!N$5,FALSE) -> 65.2 | P10: =VLOOKUP(Inputs!$B10,IS!$L$7:$P$20,IS!O$5,FALSE) -> 119.1 | Q10: =VLOOKUP(Inputs!$B10,IS!$L$7:$P$20,IS!P$5,FALSE) -> 174.4 | R10: =IFERROR((Q10/N10)^(1/COUNT($G$4:$Q$4))-1,"") -> 0.13866846
B11: Other Operating (Income) Expenses | N11: =VLOOKUP(Inputs!$B11,IS!$L$7:$P$20,IS!M$5,FALSE) -> 0 | O11: =VLOOKUP(Inputs!$B11,IS!$L$7:$P$20,IS!N$5,FALSE) -> 0 | P11: =VLOOKUP(Inputs!$B11,IS!$L$7:$P$20,IS!O$5,FALSE) -> 0 | Q11: =VLOOKUP(Inputs!$B11,IS!$L$7:$P$20,IS!P$5,FALSE) -> 0 | R11: =IFERROR((Q11/N11)^(1/COUNT($G$4:$Q$4))-1,"")
B12: EBITDA | G12: =+G8-G9-G10-G11 -> 0 | H12: =+H8-H9-H10-H11 -> 0 | I12: =+I8-I9-I10-I11 -> 0 | J12: =+J8-J9-J10-J11 -> 0 | K12: =+K8-K9-K10-K11 -> 0 | L12: =+L8-L9-L10-L11 -> 0 | M12: =+M8-M9-M10-M11 -> 0 | N12: =+N8-N9-N10-N11 -> -102.1 | ... Q12: =+Q8-Q9-Q10-Q11 -> -182.1 | R12: =IFERROR((Q12/N12)^(1/COUNT($G$4:$Q$4))-1,"") -> 0.05400827
B13: D&A (Depreciation & Amortization) | G13: =+SUM(G14:G15) -> 0 | H13: =+SUM(H14:H15) -> 0 | I13: =+SUM(I14:I15) -> 0 | J13: =+SUM(J14:J15) -> 0 | K13: =+SUM(K14:K15) -> 0 | L13: =+SUM(L14:L15) -> 0 | N13: =+SUM(N14:N15) -> 10.81 | O13: =+SUM(O14:O15) -> 29.43 | P13: =+SUM(P14:P15) -> 28.5 | Q13: =+SUM(Q14:Q15) -> 31.87 | R13: =IFERROR((Q13/N13)^(1/COUNT($G$4:$Q$4))-1,"") -> 0.10328304
B14: Depreciation Expense | N14: =VLOOKUP(Inputs!$B14,IS!$L$7:$P$20,IS!M$5,FALSE) -> 7.5 | O14: =VLOOKUP(Inputs!$B14,IS!$L$7:$P$20,IS!N$5,FALSE) -> 16.2 | P14: =VLOOKUP(Inputs!$B14,IS!$L$7:$P$20,IS!O$5,FALSE) -> 15.4 | Q14: =VLOOKUP(Inputs!$B14,IS!$L$7:$P$20,IS!P$5,FALSE) -> 19.8 | R14: =IFERROR((Q14/N14)^(1/COUNT($G$4:$Q$4))-1,"") -> 0.092264025
B15: Amortization Expense | N15: =VLOOKUP(Inputs!$B15,IS!$L$7:$P$20,IS!M$5,FALSE) -> 3.31 | O15: =VLOOKUP(Inputs!$B15,IS!$L$7:$P$20,IS!N$5,FALSE) -> 13.23 | P15: =VLOOKUP(Inputs!$B15,IS!$L$7:$P$20,IS!O$5,FALSE) -> 13.1 | Q15: =VLOOKUP(Inputs!$B15,IS!$L$7:$P$20,IS!P$5,FALSE) -> 12.07 | R15: =IFERROR((Q15/N15)^(1/COUNT($G$4:$Q$4))-1,"") -> 0.12481198
B16: Operating Income (EBIT) | G16: =+G12-G13 -> 0 | H16: =+H12-H13 -> 0 | I16: =+I12-I13 -> 0 | J16: =+J12-J13 -> 0 | K16: =+K12-K13 -> 0 | L16: =+L12-L13 -> 0 | M16: =+M12-M13 -> 0 | N16: =+N12+N13 -> -91.29 | O16: =+O12+O13 -> -105.77 | P16: =+P12+P13 -> -149.5 | Q16: =+Q12+Q13 -> -150.23 | R16: =IFERROR((Q16/N16)^(1/COUNT($G$4:$Q$4))-1,"") -> 0.046325183
B17: Net Interest Expense (Income) | G17: =+G18-G19 -> 0 | H17: =+H18-H19 -> 0 | I17: =+I18-I19 -> 0 | J17: =+J18-J19 -> 0 | K17: =+K18-K19 -> 0 | L17: =+L18-L19 -> 0 | M17: =+M18-M19 -> 0 | N17: =+N18-N19 -> 6.1 | ... Q17: =+Q18-Q19 -> 4 | R17: =IFERROR((Q17/N17)^(1/COUNT($G$4:$Q$4))-1,"") -> -0.037636584
B18: Interest Expense | N18: =VLOOKUP(Inputs!$B18,IS!$L$7:$P$20,IS!M$5,FALSE) -> 6.1 | O18: =VLOOKUP(Inputs!$B18,IS!$L$7:$P$20,IS!N$5,FALSE) -> 7.8 | P18: =VLOOKUP(Inputs!$B18,IS!$L$7:$P$20,IS!O$5,FALSE) -> 4.2 | Q18: =VLOOKUP(Inputs!$B18,IS!$L$7:$P$20,IS!P$5,FALSE) -> 4 | R18: =IFERROR((Q18/N18)^(1/COUNT($G$4:$Q$4))-1,"") -> -0.037636584
B19: Interest Income | N19: =VLOOKUP(Inputs!$B19,IS!$L$7:$P$20,IS!M$5,FALSE) -> 0 | O19: =VLOOKUP(Inputs!$B19,IS!$L$7:$P$20,IS!N$5,FALSE) -> 0 | P19: =VLOOKUP(Inputs!$B19,IS!$L$7:$P$20,IS!O$5,FALSE) -> 0 | Q19: =VLOOKUP(Inputs!$B19,IS!$L$7:$P$20,IS!P$5,FALSE) -> 0 | R19: =IFERROR((Q19/N19)^(1/COUNT($G$4:$Q$4))-1,"")
B20: FX (Gain) Loss | N20: =VLOOKUP(Inputs!$B20,IS!$L$7:$P$20,IS!M$5,FALSE) -> 0.6 | O20: =VLOOKUP(Inputs!$B20,IS!$L$7:$P$20,IS!N$5,FALSE) -> 4.4 | P20: =VLOOKUP(Inputs!$B20,IS!$L$7:$P$20,IS!O$5,FALSE) -> 0.5 | Q20: =VLOOKUP(Inputs!$B20,IS!$L$7:$P$20,IS!P$5,FALSE) -> 0.1 | R20: =IFERROR((Q20/N20)^(1/COUNT($G$4:$Q$4))-1,"") -> -0.15031299
B21: Other Non-Operating (Income) Expenses | N21: =VLOOKUP(Inputs!$B21,IS!$L$7:$P$20,IS!M$5,FALSE) -> 16.1 | O21: =VLOOKUP(Inputs!$B21,IS!$L$7:$P$20,IS!N$5,FALSE) -> -14.5 | P21: =VLOOKUP(Inputs!$B21,IS!$L$7:$P$20,IS!O$5,FALSE) -> -3.7 | Q21: =VLOOKUP(Inputs!$B21,IS!$L$7:$P$20,IS!P$5,FALSE) -> -4.4 | R21: =IFERROR((Q21/N21)^(1/COUNT($G$4:$Q$4))-1,"") -> -1.8887595
B22: Pre-Tax Income (EBT) | G22: =+G16-G17-G20-G21 -> 0 | H22: =+H16-H17-H20-H21 -> 0 | I22: =+I16-I17-I20-I21 -> 0 | J22: =+J16-J17-J20-J21 -> 0 | K22: =+K16-K17-K20-K21 -> 0 | L22: =+L16-L17-L20-L21 -> 0 | M22: =+M16-M17-M20-M21 -> 0 | N22: =+N16-N17-N20-N21 -> -114.09 | ... Q22: =+Q16-Q17-Q20-Q21 -> -149.93 | R22: =IFERROR((Q22/N22)^(1/COUNT($G$4:$Q$4))-1,"") -> 0.025145576 | S22: tax | T22: ebit | U22: interest | V22: ebt
B23: Tax Expense (Benefits) | N23: =VLOOKUP(Inputs!$B23,IS!$L$7:$P$20,IS!M$5,FALSE) -> -7.5 | O23: =VLOOKUP(Inputs!$B23,IS!$L$7:$P$20,IS!N$5,FALSE) -> 3 | P23: =VLOOKUP(Inputs!$B23,IS!$L$7:$P$20,IS!O$5,FALSE) -> 3.7 | Q23: =VLOOKUP(Inputs!$B23,IS!$L$7:$P$20,IS!P$5,FALSE) -> 0.8 | R23: =IFERROR((Q23/N23)^(1/COUNT($G$4:$Q$4))-1,"") -> -1.8159038 | S23: =+T23*T24 -> 20 | T23: 100 | U23: 10 | V23: =+T23-U23 -> 90
B24: Net Income | G24: =+G22-G23 -> 0 | H24: =+H22-H23 -> 0 | I24: =+I22-I23 -> 0 | J24: =+J22-J23 -> 0 | K24: =+K22-K23 -> 0 | L24: =+L22-L23 -> 0 | M24: =+M22-M23 -> 0 | N24: =+N22-N23 -> -106.59 | ... Q24: =+Q22-Q23 -> -150.73 | R24: =IFERROR((Q24/N24)^(1/COUNT($G$4:$Q$4))-1,"") -> 0.032001419 | S24: =+V23*T24 -> 18 | T24: 0.2
B25: EPS basic | O25: -0.29 | P25: -0.38 | Q25: -0.38 | R25: =IFERROR((Q25/N25)^(1/COUNT($G$4:$Q$4))-1,"")
B26: EPS diluted | O26: -0.29 | P26: -0.38 | Q26: -0.38 | R26: =IFERROR((Q26/N26)^(1/COUNT($G$4:$Q$4))-1,"")
B27: Basic Weighted Average Shares | N27: 209,9 | O27: 466214.1 | P27: 481768.06 | Q27: 495929.86 | R27: =IFERROR((Q27/N27)^(1/COUNT($G$4:$Q$4))-1,"")
B28: Diluted Weighted Average Shares | N28: 209,9 | O28: 466214.1 | P28: 481768.06 | Q28: 495929.86 | R28: =IFERROR((Q28/N28)^(1/COUNT($G$4:$Q$4))-1,"")
A30: x | B30: Balance Sheet | G30: 2014 | H30: =+G30+1 -> 2015 | I30: =+H30+1 -> 2016 | J30: =+I30+1 -> 2017 | K30: =+J30+1 -> 2018 | L30: =+K30+1 -> 2019 | M30: =+L30+1 -> 2020 | N30: =+M30+1 -> 2021 | O30: =+N30+1 -> 2022 | ... Q30: =+P30+1 -> 2024 | R30: ="CAGR "&$G$4&" - "&$Q$4 -> CAGR 2014 - 2024
B32: Cash & Cash Equivalents & ST Investments | G32: =+SUM(G33:G34) -> 0 | H32: =+SUM(H33:H34) -> 0 | I32: =+SUM(I33:I34) -> 0 | J32: =+SUM(J33:J34) -> 0 | K32: =+SUM(K33:K34) -> 0 | L32: =+SUM(L33:L34) -> 0 | M32: =+SUM(M33:M34) -> 0 | N32: =+SUM(N33:N34) -> 691 | ... Q32: =+SUM(Q33:Q34) -> 418.9 | R32: =IFERROR((Q32/N32)^(1/COUNT($G$4:$Q$4))-1,"") -> -0.044481057
B33: Cash & Cash Equivalents | N33: =VLOOKUP($B33,BS!$I$5:$M$31,BS!J$3,FALSE) -> 691 | O33: =VLOOKUP($B33,BS!$I$5:$M$31,BS!K$3,FALSE) -> 242.5 | P33: =VLOOKUP($B33,BS!$I$5:$M$31,BS!L$3,FALSE) -> 162.5 | Q33: =VLOOKUP($B33,BS!$I$5:$M$31,BS!M$3,FALSE) -> 271 | R33: =IFERROR((Q33/N33)^(1/COUNT($G$4:$Q$4))-1,"") -> -0.081572967
B34: Short-Term Investments | N34: =VLOOKUP($B34,BS!$I$5:$M$31,BS!J$3,FALSE) -> 0 | O34: =VLOOKUP($B34,BS!$I$5:$M$31,BS!K$3,FALSE) -> 229.3 | P34: =VLOOKUP($B34,BS!$I$5:$M$31,BS!L$3,FALSE) -> 82.3 | Q34: =VLOOKUP($B34,BS!$I$5:$M$31,BS!M$3,FALSE) -> 147.9 | R34: =IFERROR((Q34/N34)^(1/COUNT($G$4:$Q$4))-1,"")
B35: Accounts Receivable | N35: =VLOOKUP($B35,BS!$I$5:$M$31,BS!J$3,FALSE) -> 14 | O35: =VLOOKUP($B35,BS!$I$5:$M$31,BS!K$3,FALSE) -> 36.6 | P35: =VLOOKUP($B35,BS!$I$5:$M$31,BS!L$3,FALSE) -> 35.2 | Q35: =VLOOKUP($B35,BS!$I$5:$M$31,BS!M$3,FALSE) -> 36.4 | R35: =IFERROR((Q35/N35)^(1/COUNT($G$4:$Q$4))-1,"") -> 0.090749066
B36: Inventory | N36: =VLOOKUP($B36,BS!$I$5:$M$31,BS!J$3,FALSE) -> 47.9 | O36: =VLOOKUP($B36,BS!$I$5:$M$31,BS!K$3,FALSE) -> 92.3 | P36: =VLOOKUP($B36,BS!$I$5:$M$31,BS!L$3,FALSE) -> 107.9 | Q36: =VLOOKUP($B36,BS!$I$5:$M$31,BS!M$3,FALSE) -> 119.1 | R36: =IFERROR((Q36/N36)^(1/COUNT($G$4:$Q$4))-1,"") -> 0.086329259
B37: Prepaid expenses and Other Current Assets | G37: =+G38-G32-G35-G36 -> 0 | H37: =+H38-H32-H35-H36 -> 0 | I37: =+I38-I32-I35-I36 -> 0 | J37: =+J38-J32-J35-J36 -> 0 | K37: =+K38-K32-K35-K36 -> 0 | L37: =+L38-L32-L35-L36 -> 0 | M37: =+M38-M32-M35-M36 -> 0 | N37: =+N38-N32-N35-N36 -> 21.9 | ... Q37: =+Q38-Q32-Q35-Q36 -> 118.2 | R37: =IFERROR((Q37/N37)^(1/COUNT($G$4:$Q$4))-1,"") -> 0.16563134
B38: Current Assets | N38: =VLOOKUP($B38,BS!$I$5:$M$31,BS!J$3,FALSE) -> 774.8 | O38: =VLOOKUP($B38,BS!$I$5:$M$31,BS!K$3,FALSE) -> 662.3 | P38: =VLOOKUP($B38,BS!$I$5:$M$31,BS!L$3,FALSE) -> 476.7 | Q38: =VLOOKUP($B38,BS!$I$5:$M$31,BS!M$3,FALSE) -> 692.6 | R38: =IFERROR((Q38/N38)^(1/COUNT($G$4:$Q$4))-1,"") -> -0.010143864
B39: Net PP&E (Property, Plant and Equipment) | G39: =+G40-G41 -> 0 | H39: =+H40-H41 -> 0 | I39: =+I40-I41 -> 0 | J39: =+J40-J41 -> 0 | K39: =+K40-K41 -> 0 | L39: =+L40-L41 -> 0 | M39: =+M40-M41 -> 0 | N39: =+N40-N41 -> 93.8 | ... Q39: =+Q40-Q41 -> 262.9 | R39: =IFERROR((Q39/N39)^(1/COUNT($G$4:$Q$4))-1,"") -> 0.09822113
B40: Gross PP&E (Property, Plant and Equipment) | N40: =VLOOKUP($B40,BS!$I$5:$M$31,BS!J$3,FALSE) -> 116 | O40: =VLOOKUP($B40,BS!$I$5:$M$31,BS!K$3,FALSE) -> 188.8 | P40: =VLOOKUP($B40,BS!$I$5:$M$31,BS!L$3,FALSE) -> 268.9 | Q40: =VLOOKUP($B40,BS!$I$5:$M$31,BS!M$3,FALSE) -> 328.5 | R40: =IFERROR((Q40/N40)^(1/COUNT($G$4:$Q$4))-1,"") -> 0.09925372
B41: Accumulated Depreciation | N41: =VLOOKUP($B41,BS!$I$5:$M$31,BS!J$3,FALSE) -> 22.2 | O41: =VLOOKUP($B41,BS!$I$5:$M$31,BS!K$3,FALSE) -> 36.4 | P41: =VLOOKUP($B41,BS!$I$5:$M$31,BS!L$3,FALSE) -> 49.1 | Q41: =VLOOKUP($B41,BS!$I$5:$M$31,BS!M$3,FALSE) -> 65.6 | R41: =IFERROR((Q41/N41)^(1/COUNT($G$4:$Q$4))-1,"") -> 0.10351274
B42: Right-of-Use Assets | N42: 0 | O42: 0 | P42: 0 | Q42: 0 | R42: =IFERROR((Q42/N42)^(1/COUNT($G$4:$Q$4))-1,"")
B43: Intangibles | N43: =VLOOKUP($B43,BS!$I$5:$M$31,BS!J$3,FALSE) -> 45.1 | O43: =VLOOKUP($B43,BS!$I$5:$M$31,BS!K$3,FALSE) -> 150.7 | P43: =VLOOKUP($B43,BS!$I$5:$M$31,BS!L$3,FALSE) -> 139.1 | Q43: =VLOOKUP($B43,BS!$I$5:$M$31,BS!M$3,FALSE) -> 129.7 | R43: =IFERROR((Q43/N43)^(1/COUNT($G$4:$Q$4))-1,"") -> 0.10079327
B44: Goodwill | N44: =VLOOKUP($B44,BS!$I$5:$M$31,BS!J$3,FALSE) -> 43.3 | O44: =VLOOKUP($B44,BS!$I$5:$M$31,BS!K$3,FALSE) -> 71 | P44: =VLOOKUP($B44,BS!$I$5:$M$31,BS!L$3,FALSE) -> 71 | Q44: =VLOOKUP($B44,BS!$I$5:$M$31,BS!M$3,FALSE) -> 71 | R44: =IFERROR((Q44/N44)^(1/COUNT($G$4:$Q$4))-1,"") -> 0.045982905
B45: Intangibles excl. Goodwill | G45: =+G43-G44 -> 0 | H45: =+H43-H44 -> 0 | I45: =+I43-I44 -> 0 | J45: =+J43-J44 -> 0 | K45: =+K43-K44 -> 0 | L45: =+L43-L44 -> 0 | M45: =+M43-M44 -> 0 | N45: =+N43-N44 -> 1.8 | ... Q45: =+Q43-Q44 -> 58.7
B46: Other Non-Current Assets | G46: =+G47-G39-G42-G43 -> 0 | H46: =+H47-H39-H42-H43 -> 0 | I46: =+I47-I39-I42-I43 -> 0 | J46: =+J47-J39-J42-J43 -> 0 | K46: =+K47-K39-K42-K43 -> 0 | L46: =+L47-L39-L42-L43 -> 0 | M46: =+M47-M39-M42-M43 -> 0 | N46: =+N47-N39-N42-N43 -> 67.2 | ... Q46: =+Q47-Q39-Q42-Q43 -> 99.1 | R46: =IFERROR((Q46/G46)^(1/COUNT($G$4:$Q$4))-1,"")
B47: Non-Current Assets | N47: =VLOOKUP($B47,BS!$I$5:$M$31,BS!J$3,FALSE) -> 206.1 | O47: =VLOOKUP($B47,BS!$I$5:$M$31,BS!K$3,FALSE) -> 326.8 | P47: =VLOOKUP($B47,BS!$I$5:$M$31,BS!L$3,FALSE) -> 464.5 | Q47: =VLOOKUP($B47,BS!$I$5:$M$31,BS!M$3,FALSE) -> 491.7 | R47: =IFERROR((Q47/N47)^(1/COUNT($G$4:$Q$4))-1,"") -> 0.082254231
B48: Total Assets | G48: =SUM(G47,G38) -> 0 | H48: =SUM(H47,H38) -> 0 | I48: =SUM(I47,I38) -> 0 | J48: =SUM(J47,J38) -> 0 | K48: =SUM(K47,K38) -> 0 | L48: =SUM(L47,L38) -> 0 | M48: =SUM(M47,M38) -> 0 | N48: =SUM(N47,N38) -> 980.9 | ... Q48: =SUM(Q47,Q38) -> 1184.3 | R48: =IFERROR((Q48/N48)^(1/COUNT($G$4:$Q$4))-1,"") -> 0.017278174
B49: Accounts Payable | N49: =VLOOKUP($B49,BS!$I$5:$M$31,BS!J$3,FALSE) -> 14.5 | O49: =VLOOKUP($B49,BS!$I$5:$M$31,BS!K$3,FALSE) -> 20.8 | P49: =VLOOKUP($B49,BS!$I$5:$M$31,BS!L$3,FALSE) -> 34.9 | Q49: =VLOOKUP($B49,BS!$I$5:$M$31,BS!M$3,FALSE) -> 72.5 | R49: =IFERROR((Q49/N49)^(1/COUNT($G$4:$Q$4))-1,"") -> 0.15755791
B50: Short-Term Debt | G50: =+SUM(G51:G52) -> 0 | H50: =+SUM(H51:H52) -> 0 | I50: =+SUM(I51:I52) -> 0 | J50: =+SUM(J51:J52) -> 0 | K50: =+SUM(K51:K52) -> 0 | L50: =+SUM(L51:L52) -> 0 | M50: =+SUM(M51:M52) -> 0 | N50: =+SUM(N51:N52) -> 2.8 | ... Q50: =+SUM(Q51:Q52) -> 18.2 | R50: =IFERROR((Q50/N50)^(1/COUNT($G$4:$Q$4))-1,"") -> 0.18549906
B51: Short-Term Borrowings | N51: =VLOOKUP($B51,BS!$I$5:$M$31,BS!J$3,FALSE) -> 2.8 | O51: =VLOOKUP($B51,BS!$I$5:$M$31,BS!K$3,FALSE) -> 2.9 | P51: =VLOOKUP($B51,BS!$I$5:$M$31,BS!L$3,FALSE) -> 17.8 | Q51: =VLOOKUP($B51,BS!$I$5:$M$31,BS!M$3,FALSE) -> 11.8 | R51: =IFERROR((Q51/N51)^(1/COUNT($G$4:$Q$4))-1,"") -> 0.13970667
B52: Current Portion of Lease Liabilities | N52: =VLOOKUP($B52,BS!$I$5:$M$31,BS!J$3,FALSE) -> 0 | O52: =VLOOKUP($B52,BS!$I$5:$M$31,BS!K$3,FALSE) -> — | P52: =VLOOKUP($B52,BS!$I$5:$M$31,BS!L$3,FALSE) -> — | Q52: =VLOOKUP($B52,BS!$I$5:$M$31,BS!M$3,FALSE) -> 6.4 | R52: =IFERROR((Q52/N52)^(1/COUNT($G$4:$Q$4))-1,"")
B53: Accrued Expenses and Other Current Liabilities | G53: =+G54-G49-G50 -> 0 | H53: =+H54-H49-H50 -> 0 | I53: =+I54-I49-I50 -> 0 | J53: =+J54-J49-J50 -> 0 | K53: =+K54-K49-K50 -> 0 | L53: =+L54-L49-L50 -> 0 | M53: =+M54-M49-M50 -> 0 | N53: =+N54-N49-N50 -> 79 | ... Q53: =+Q54-Q49-Q50 -> 248.8 | R53: =IFERROR((Q53/N53)^(1/COUNT($G$4:$Q$4))-1,"") -> 0.10992345
B54: Current Liabilities | N54: =VLOOKUP($B54,BS!$I$5:$M$31,BS!J$3,FALSE) -> 96.3 | O54: =VLOOKUP($B54,BS!$I$5:$M$31,BS!K$3,FALSE) -> 162.9 | P54: =VLOOKUP($B54,BS!$I$5:$M$31,BS!L$3,FALSE) -> 223.4 | Q54: =VLOOKUP($B54,BS!$I$5:$M$31,BS!M$3,FALSE) -> 339.5 | R54: =IFERROR((Q54/N54)^(1/COUNT($G$4:$Q$4))-1,"") -> 0.12136418
B55: Long-Term Debt | G55: =+SUM(G56:G57) -> 0 | H55: =+SUM(H56:H57) -> 0 | I55: =+SUM(I56:I57) -> 0 | J55: =+SUM(J56:J57) -> 0 | K55: =+SUM(K56:K57) -> 0 | L55: =+SUM(L56:L57) -> 0 | M55: =+SUM(M56:M57) -> 0 | N55: =+SUM(N56:N57) -> 125.6 | ... Q55: =+SUM(Q56:Q57) -> 441.4 | R55: =IFERROR((Q55/N55)^(1/COUNT($G$4:$Q$4))-1,"") -> 0.12104246
B56: Long-Term Borrowings | N56: =VLOOKUP($B56,BS!$I$5:$M$31,BS!J$3,FALSE) -> 97.3 | O56: =VLOOKUP($B56,BS!$I$5:$M$31,BS!K$3,FALSE) -> 84.1 | P56: =VLOOKUP($B56,BS!$I$5:$M$31,BS!L$3,FALSE) -> 72 | Q56: =VLOOKUP($B56,BS!$I$5:$M$31,BS!M$3,FALSE) -> 389.4 | R56: =IFERROR((Q56/N56)^(1/COUNT($G$4:$Q$4))-1,"") -> 0.1343655
B57: Long-Term Operating Lease Liabilities | N57: =VLOOKUP($B57,BS!$I$5:$M$31,BS!J$3,FALSE) -> 28.3 | O57: =VLOOKUP($B57,BS!$I$5:$M$31,BS!K$3,FALSE) -> 37.7 | P57: =VLOOKUP($B57,BS!$I$5:$M$31,BS!L$3,FALSE) -> 61.4 | Q57: =VLOOKUP($B57,BS!$I$5:$M$31,BS!M$3,FALSE) -> 52 | R57: =IFERROR((Q57/N57)^(1/COUNT($G$4:$Q$4))-1,"") -> 0.056865495
B58: Other Non-Current Liabilities | G58: =+G59-G55 -> 0 | H58: =+H59-H55 -> 0 | I58: =+I59-I55 -> 0 | J58: =+J59-J55 -> 0 | K58: =+K59-K55 -> 0 | L58: =+L59-L55 -> 0 | M58: =+M59-M55 -> 0 | N58: =+N59-N55 -> 60.5 | ... Q58: =+Q59-Q55 -> 21 | R58: =IFERROR((Q58/N58)^(1/COUNT($G$4:$Q$4))-1,"") -> -0.091711129
B59: Non-Current Liabilities | N59: =BS!J32 -> 186.1 | O59: =BS!K32 -> 153 | P59: =BS!L32 -> 163.3 | Q59: =BS!M32 -> 462.4 | R59: =IFERROR((Q59/N59)^(1/COUNT($G$4:$Q$4))-1,"") -> 0.086259952
B60: Total Liabilities | G60: =SUM(G59,G54) -> 0 | H60: =SUM(H59,H54) -> 0 | I60: =SUM(I59,I54) -> 0 | J60: =SUM(J59,J54) -> 0 | K60: =SUM(K59,K54) -> 0 | L60: =SUM(L59,L54) -> 0 | M60: =SUM(M59,M54) -> 0 | N60: =SUM(N59,N54) -> 282.4 | ... Q60: =SUM(Q59,Q54) -> 801.9 | R60: =IFERROR((Q60/N60)^(1/COUNT($G$4:$Q$4))-1,"") -> 0.099524845
B61: Shareholder's Equity | G61: =G48-G60 -> 0 | H61: =H48-H60 -> 0 | I61: =I48-I60 -> 0 | J61: =J48-J60 -> 0 | K61: =K48-K60 -> 0 | L61: =L48-L60 -> 0 | M61: =M48-M60 -> 0 | N61: =N48-N60 -> 698.5 | ... Q61: =Q48-Q60 -> 382.4 | R61: =IFERROR((Q61/N61)^(1/COUNT($G$4:$Q$4))-1,"") -> -0.053296963
B62: Non-Controlling Interest
A64: x | B64: Cash Flow | G64: 2014 | H64: =+G64+1 -> 2015 | I64: =+H64+1 -> 2016 | J64: =+I64+1 -> 2017 | K64: =+J64+1 -> 2018 | L64: =+K64+1 -> 2019 | M64: =+L64+1 -> 2020 | N64: =+M64+1 -> 2021 | O64: =+N64+1 -> 2022 | ... Q64: =+P64+1 -> 2024 | R64: ="CAGR "&$G$4&" - "&$Q$4 -> CAGR 2014 - 2024
B66: Net Income | G66: =G24 -> 0 | H66: =H24 -> 0 | I66: =I24 -> 0 | J66: =J24 -> 0 | K66: =K24 -> 0 | L66: =L24 -> 0 | M66: =M24 -> 0 | N66: =N24 -> -106.59 | ... Q66: =Q24 -> -150.73 | R66: =IFERROR((Q66/N66)^(1/COUNT($G$4:$Q$4))-1,"") -> 0.032001419
B67: D&A (Depreciation and Amortization) | G67: =+G13 -> 0 | H67: =+H13 -> 0 | I67: =+I13 -> 0 | J67: =+J13 -> 0 | K67: =+K13 -> 0 | L67: =+L13 -> 0 | M67: =+M13 -> 0 | N67: =+N13 -> 10.81 | ... Q67: =+Q13 -> 31.87 | R67: =IFERROR((Q67/N67)^(1/COUNT($G$4:$Q$4))-1,"") -> 0.10328304
B68: Changes in Net Working Capital | G68: =+SUM(G69:G72) -> 0 | H68: =+SUM(H69:H72) -> 0 | I68: =+SUM(I69:I72) -> 0 | J68: =+SUM(J69:J72) -> 0 | K68: =+SUM(K69:K72) -> 0 | L68: =+SUM(L69:L72) -> 0 | M68: =+SUM(M69:M72) -> 0 | N68: =+SUM(N69:N72) -> 2.5 | ... Q68: =+SUM(Q69:Q72) -> 38.1 | R68: =IFERROR((Q68/N68)^(1/COUNT($G$4:$Q$4))-1,"") -> 0.28098513
B69: (Increase) Decrease in Accounts Receivable | N69: =VLOOKUP(Inputs!$B69,CF!$L$8:$P$36,CF!M$6,FALSE) -> -7.8 | O69: =VLOOKUP(Inputs!$B69,CF!$L$8:$P$36,CF!N$6,FALSE) -> -9.4 | P69: =VLOOKUP(Inputs!$B69,CF!$L$8:$P$36,CF!O$6,FALSE) -> 1.5 | Q69: =VLOOKUP(Inputs!$B69,CF!$L$8:$P$36,CF!P$6,FALSE) -> -1.4
B70: (Increase) Decrease in Inventories | N70: =VLOOKUP(Inputs!$B70,CF!$L$8:$P$36,CF!M$6,FALSE) -> -12.7 | O70: =VLOOKUP(Inputs!$B70,CF!$L$8:$P$36,CF!N$6,FALSE) -> -26 | P70: =VLOOKUP(Inputs!$B70,CF!$L$8:$P$36,CF!O$6,FALSE) -> -15.6 | Q70: =VLOOKUP(Inputs!$B70,CF!$L$8:$P$36,CF!P$6,FALSE) -> -12.4
B71: Increase (Decrease) in Inventories | N71: =VLOOKUP(Inputs!$B71,CF!$L$8:$P$36,CF!M$6,FALSE) -> 0 | O71: =VLOOKUP(Inputs!$B71,CF!$L$8:$P$36,CF!N$6,FALSE) -> 0 | P71: =VLOOKUP(Inputs!$B71,CF!$L$8:$P$36,CF!O$6,FALSE) -> 0 | Q71: =VLOOKUP(Inputs!$B71,CF!$L$8:$P$36,CF!P$6,FALSE) -> 0
B72: Increase (Decrease) in Other | N72: =VLOOKUP(Inputs!$B72,CF!$L$8:$P$36,CF!M$6,FALSE) -> 23 | O72: =VLOOKUP(Inputs!$B72,CF!$L$8:$P$36,CF!N$6,FALSE) -> -0.1 | P72: =VLOOKUP(Inputs!$B72,CF!$L$8:$P$36,CF!O$6,FALSE) -> 7.6 | Q72: =VLOOKUP(Inputs!$B72,CF!$L$8:$P$36,CF!P$6,FALSE) -> 51.9
B73: Stock Based Compensation | N73: =VLOOKUP(Inputs!$B73,CF!$L$8:$P$36,CF!M$6,FALSE) -> 32.6 | O73: =VLOOKUP(Inputs!$B73,CF!$L$8:$P$36,CF!N$6,FALSE) -> 55.6 | P73: =VLOOKUP(Inputs!$B73,CF!$L$8:$P$36,CF!O$6,FALSE) -> 53.5 | Q73: =VLOOKUP(Inputs!$B73,CF!$L$8:$P$36,CF!P$6,FALSE) -> 56.8
B74: Other Operating Adjustments | G74: =+G75-G66-G67-G68-G73 -> 0 | H74: =+H75-H66-H67-H68-H73 -> 0 | I74: =+I75-I66-I67-I68-I73 -> 0 | J74: =+J75-J66-J67-J68-J73 -> 0 | K74: =+K75-K66-K67-K68-K73 -> 0 | L74: =+L75-L66-L67-L68-L73 -> 0 | M74: =+M75-M66-M67-M68-M73 -> 0 | N74: =+N75-N66-N67-N68-N73 -> -11.12 | ... Q74: =+Q75-Q66-Q67-Q68-Q73 -> -24.94 | R74: =IFERROR((Q74/N74)^(1/COUNT($G$4:$Q$4))-1,"") -> 0.076192971
B75: Operating Cash Flow | N75: =VLOOKUP(Inputs!$B75,CF!$L$8:$P$36,CF!M$6,FALSE) -> -71.8 | O75: =VLOOKUP(Inputs!$B75,CF!$L$8:$P$36,CF!N$6,FALSE) -> -106.5 | P75: =VLOOKUP(Inputs!$B75,CF!$L$8:$P$36,CF!O$6,FALSE) -> -98.9 | Q75: =VLOOKUP(Inputs!$B75,CF!$L$8:$P$36,CF!P$6,FALSE) -> -48.9 | R75: =IFERROR((Q75/N75)^(1/COUNT($G$4:$Q$4))-1,"") -> -0.034316198
B76: Net Capex | G76: =+SUM(G77:G78) -> 0 | H76: =+SUM(H77:H78) -> 0 | I76: =+SUM(I77:I78) -> 0 | J76: =+SUM(J77:J78) -> 0 | K76: =+SUM(K77:K78) -> 0 | L76: =+SUM(L77:L78) -> 0 | M76: =+SUM(M77:M78) -> 0 | N76: =+SUM(N77:N78) -> -92.1 | ... Q76: =+SUM(Q77:Q78) -> -54.6 | R76: =IFERROR((Q76/N76)^(1/COUNT($G$4:$Q$4))-1,"") -> -0.046419094
B77: Acquisition of Fixed & Intangibles | N77: =VLOOKUP(Inputs!$B77,CF!$L$8:$P$36,CF!M$6,FALSE) -> -92.1 | O77: =VLOOKUP(Inputs!$B77,CF!$L$8:$P$36,CF!N$6,FALSE) -> -108.2 | P77: =VLOOKUP(Inputs!$B77,CF!$L$8:$P$36,CF!O$6,FALSE) -> -73.7 | Q77: =VLOOKUP(Inputs!$B77,CF!$L$8:$P$36,CF!P$6,FALSE) -> -67.1 | R77: =IFERROR((Q77/N77)^(1/COUNT($G$4:$Q$4))-1,"") -> -0.028379596
B78: Disposal of Fixed & Intangibles | N78: =VLOOKUP(Inputs!$B78,CF!$L$8:$P$36,CF!M$6,FALSE) -> 0 | O78: =VLOOKUP(Inputs!$B78,CF!$L$8:$P$36,CF!N$6,FALSE) -> 0 | P78: =VLOOKUP(Inputs!$B78,CF!$L$8:$P$36,CF!O$6,FALSE) -> 3.7 | Q78: =VLOOKUP(Inputs!$B78,CF!$L$8:$P$36,CF!P$6,FALSE) -> 12.5 | R78: =IFERROR((Q78/N78)^(1/COUNT($G$4:$Q$4))-1,"")
B79: Net Cash from Investments & Acquisitions | G79: =+SUM(G80:G83) -> 0 | H79: =+SUM(H80:H83) -> 0 | I79: =+SUM(I80:I83) -> 0 | J79: =+SUM(J80:J83) -> 0 | K79: =+SUM(K80:K83) -> 0 | L79: =+SUM(L80:L83) -> 0 | M79: =+SUM(M80:M83) -> 0 | N79: =+SUM(N80:N83) -> 2.5 | ... Q79: =+SUM(Q80:Q83) -> 2.4 | R79: =IFERROR((Q79/N79)^(1/COUNT($G$4:$Q$4))-1,"") -> -0.0037042128
B80: Acquisitions | N80: =VLOOKUP(Inputs!$B80,CF!$L$8:$P$36,CF!M$6,FALSE) -> 2.5 | O80: =VLOOKUP(Inputs!$B80,CF!$L$8:$P$36,CF!N$6,FALSE) -> 0.6 | P80: =VLOOKUP(Inputs!$B80,CF!$L$8:$P$36,CF!O$6,FALSE) -> 0.3 | Q80: =VLOOKUP(Inputs!$B80,CF!$L$8:$P$36,CF!P$6,FALSE) -> 2.4 | R80: =IFERROR((Q80/N80)^(1/COUNT($G$4:$Q$4))-1,"") -> -0.0037042128
B81: Divestitures | N81: =VLOOKUP(Inputs!$B81,CF!$L$8:$P$36,CF!M$6,FALSE) -> 0 | O81: =VLOOKUP(Inputs!$B81,CF!$L$8:$P$36,CF!N$6,FALSE) -> 0 | P81: =VLOOKUP(Inputs!$B81,CF!$L$8:$P$36,CF!O$6,FALSE) -> 0 | Q81: =VLOOKUP(Inputs!$B81,CF!$L$8:$P$36,CF!P$6,FALSE) -> 0 | R81: =IFERROR((Q81/N81)^(1/COUNT($G$4:$Q$4))-1,"")
B82: Increase in LT Investment | N82: =VLOOKUP(Inputs!$B82,CF!$L$8:$P$36,CF!M$6,FALSE) -> 0 | O82: =VLOOKUP(Inputs!$B82,CF!$L$8:$P$36,CF!N$6,FALSE) -> 0 | P82: =VLOOKUP(Inputs!$B82,CF!$L$8:$P$36,CF!O$6,FALSE) -> 0 | Q82: =VLOOKUP(Inputs!$B82,CF!$L$8:$P$36,CF!P$6,FALSE) -> 0 | R82: =IFERROR((Q82/N82)^(1/COUNT($G$4:$Q$4))-1,"")
B83: Decrease in LT Investment | N83: =VLOOKUP(Inputs!$B83,CF!$L$8:$P$36,CF!M$6,FALSE) -> 0 | O83: =VLOOKUP(Inputs!$B83,CF!$L$8:$P$36,CF!N$6,FALSE) -> 0 | P83: =VLOOKUP(Inputs!$B83,CF!$L$8:$P$36,CF!O$6,FALSE) -> 0 | Q83: =VLOOKUP(Inputs!$B83,CF!$L$8:$P$36,CF!P$6,FALSE) -> 0 | R83: =IFERROR((Q83/N83)^(1/COUNT($G$4:$Q$4))-1,"")
B84: Other Investing Inflows (Outflows) | G84: =+G85-G76-G79 -> 0 | H84: =+H85-H76-H79 -> 0 | I84: =+I85-I76-I79 -> 0 | J84: =+J85-J76-J79 -> 0 | K84: =+K85-K76-K79 -> 0 | L84: =+L85-L76-L79 -> 0 | M84: =+M85-M76-M79 -> 0 | N84: =+N85-N76-N79 -> -2.5 | ... Q84: =+Q85-Q76-Q79 -> -46.1 | R84: =IFERROR((Q84/N84)^(1/COUNT($G$4:$Q$4))-1,"") -> 0.30337436
B85: Investing Cash Flow | N85: =VLOOKUP(Inputs!$B85,CF!$L$8:$P$36,CF!M$6,FALSE) -> -92.1 | O85: =VLOOKUP(Inputs!$B85,CF!$L$8:$P$36,CF!N$6,FALSE) -> -346.1 | P85: =VLOOKUP(Inputs!$B85,CF!$L$8:$P$36,CF!O$6,FALSE) -> 12 | Q85: =VLOOKUP(Inputs!$B85,CF!$L$8:$P$36,CF!P$6,FALSE) -> -98.3 | R85: =IFERROR((Q85/N85)^(1/COUNT($G$4:$Q$4))-1,"") -> 0.0059402175
B86: Debt Borrowing | N86: =VLOOKUP(Inputs!$B86,CF!$L$8:$P$36,CF!M$6,FALSE) -> 100,1 | O86: =VLOOKUP(Inputs!$B86,CF!$L$8:$P$36,CF!N$6,FALSE) -> 87 | P86: =VLOOKUP(Inputs!$B86,CF!$L$8:$P$36,CF!O$6,FALSE) -> 89.8 | Q86: =VLOOKUP(Inputs!$B86,CF!$L$8:$P$36,CF!P$6,FALSE) -> 401.2 | R86: =IFERROR((Q86/N86)^(1/COUNT($G$4:$Q$4))-1,"")
B87: Debt Repayment | N87: =VLOOKUP(Inputs!$B87,CF!$L$8:$P$36,CF!M$6,FALSE) -> 796.8 | O87: =VLOOKUP(Inputs!$B87,CF!$L$8:$P$36,CF!N$6,FALSE) -> -0.3 | P87: =VLOOKUP(Inputs!$B87,CF!$L$8:$P$36,CF!O$6,FALSE) -> -0.3 | Q87: =VLOOKUP(Inputs!$B87,CF!$L$8:$P$36,CF!P$6,FALSE) -> 302.9 | R87: =IFERROR((Q87/N87)^(1/COUNT($G$4:$Q$4))-1,"") -> -0.084172602
B88: Lease Payments | N88: =VLOOKUP(Inputs!$B88,CF!$L$8:$P$36,CF!M$6,FALSE) -> 28.3 | O88: =VLOOKUP(Inputs!$B88,CF!$L$8:$P$36,CF!N$6,FALSE) -> 37.7 | P88: =VLOOKUP(Inputs!$B88,CF!$L$8:$P$36,CF!O$6,FALSE) -> 61.4 | Q88: =VLOOKUP(Inputs!$B88,CF!$L$8:$P$36,CF!P$6,FALSE) -> 58.2 | R88: =IFERROR((Q88/N88)^(1/COUNT($G$4:$Q$4))-1,"") -> 0.067743556
B89: Dividends | N89: =VLOOKUP(Inputs!$B89,CF!$L$8:$P$36,CF!M$6,FALSE) -> 0 | O89: =VLOOKUP(Inputs!$B89,CF!$L$8:$P$36,CF!N$6,FALSE) -> 0 | P89: =VLOOKUP(Inputs!$B89,CF!$L$8:$P$36,CF!O$6,FALSE) -> 0 | Q89: =VLOOKUP(Inputs!$B89,CF!$L$8:$P$36,CF!P$6,FALSE) -> 0 | R89: =IFERROR((Q89/N89)^(1/COUNT($G$4:$Q$4))-1,"")
B90: Increase (Repurchase) of Shares | N90: =VLOOKUP(Inputs!$B90,CF!$L$8:$P$36,CF!M$6,FALSE) -> 3.1 | O90: =VLOOKUP(Inputs!$B90,CF!$L$8:$P$36,CF!N$6,FALSE) -> 3.9 | P90: =VLOOKUP(Inputs!$B90,CF!$L$8:$P$36,CF!O$6,FALSE) -> 2.4 | Q90: =VLOOKUP(Inputs!$B90,CF!$L$8:$P$36,CF!P$6,FALSE) -> -26.1 | R90: =IFERROR((Q90/N90)^(1/COUNT($G$4:$Q$4))-1,"") -> -2.2137137
B91: Other Financing Inflows (Outflows) | G91: =+G92-G86-G87-G88-G89-G90 -> 0 | H91: =+H92-H86-H87-H88-H89-H90 -> 0 | I91: =+I92-I86-I87-I88-I89-I90 -> 0 | J91: =+J92-J86-J87-J88-J89-J90 -> 0 | K91: =+K92-K86-K87-K88-K89-K90 -> 0 | L91: =+L92-L86-L87-L88-L89-L90 -> 0 | M91: =+M92-M86-M87-M88-M89-M90 -> 0 | N91: =+N92-N86-N87-N88-N89-N90 -> #VALUE! | ... Q91: =+Q92-Q86-Q87-Q88-Q89-Q90 -> -736.2 | R91: =IFERROR((Q91/N91)^(1/COUNT($G$4:$Q$4))-1,"")
B92: Financing Cash Flow | R92: =IFERROR((Q92/N92)^(1/COUNT($G$4:$Q$4))-1,"")
B93: Effect of Foreign Exchange | N93: =VLOOKUP(Inputs!$B93,CF!$L$8:$P$36,CF!M$6,FALSE) -> 2.1 | O93: =VLOOKUP(Inputs!$B93,CF!$L$8:$P$36,CF!N$6,FALSE) -> 4.4 | P93: =VLOOKUP(Inputs!$B93,CF!$L$8:$P$36,CF!O$6,FALSE) -> 0 | Q93: =VLOOKUP(Inputs!$B93,CF!$L$8:$P$36,CF!P$6,FALSE) -> -0.6 | R93: =IFERROR((Q93/N93)^(1/COUNT($G$4:$Q$4))-1,"") -> -1.8923583
B94: Net Changes in Cash | N94: =VLOOKUP(Inputs!$B94,CF!$L$8:$P$36,CF!M$6,FALSE) -> 638.1 | O94: =VLOOKUP(Inputs!$B94,CF!$L$8:$P$36,CF!N$6,FALSE) -> -446.2 | P94: =VLOOKUP(Inputs!$B94,CF!$L$8:$P$36,CF!O$6,FALSE) -> -79.4 | Q94: =VLOOKUP(Inputs!$B94,CF!$L$8:$P$36,CF!P$6,FALSE) -> 108.9 | R94: =IFERROR((Q94/N94)^(1/COUNT($G$4:$Q$4))-1,"") -> -0.14848076
B95: in billionsof USD
A96: x | B96: Capital Structure | G96: 42004 | H96: 42369 | I96: 42735 | J96: 43100 | K96: 43465 | L96: 43830 | M96: 44196 | N96: 44561 | O96: 44926 | P96: 45291 | Q96: 45657
B98: Market Capitalization | G98: {=(IFERROR(_xlfn.STOCKHISTORY(#REF!, G96, G96, 0, 0, 1), IFERROR(_xlfn.STOCKHISTORY(#REF!, G96+1, G96+1, 0, 0, 1), _xlfn.STOCKHISTORY(#REF!, G96-2, G96-2, 0, 0, 1))))*_xlfn.XLOOKUP("Basic Weighted Average Shares",$B:$B,G:G)} -> #REF! | H98: {=(IFERROR(_xlfn.STOCKHISTORY(#REF!, H96, H96, 0, 0, 1), IFERROR(_xlfn.STOCKHISTORY(#REF!, H96+1, H96+1, 0, 0, 1), _xlfn.STOCKHISTORY(#REF!, H96-2, H96-2, 0, 0, 1))))*_xlfn.XLOOKUP("Basic Weighted Average Shares",$B:$B,H:H)} -> #REF! | I98: {=(IFERROR(_xlfn.STOCKHISTORY(#REF!, I96, I96, 0, 0, 1), IFERROR(_xlfn.STOCKHISTORY(#REF!, I96+1, I96+1, 0, 0, 1), _xlfn.STOCKHISTORY(#REF!, I96-2, I96-2, 0, 0, 1))))*_xlfn.XLOOKUP("Basic Weighted Average Shares",$B:$B,I:I)} -> #REF! | J98: {=(IFERROR(_xlfn.STOCKHISTORY(#REF!, J96, J96, 0, 0, 1), IFERROR(_xlfn.STOCKHISTORY(#REF!, J96+1, J96+1, 0, 0, 1), _xlfn.STOCKHISTORY(#REF!, J96-2, J96-2, 0, 0, 1))))*_xlfn.XLOOKUP("Basic Weighted Average Shares",$B:$B,J:J)} -> #REF! | K98: {=(IFERROR(_xlfn.STOCKHISTORY(#REF!, K96, K96, 0, 0, 1), IFERROR(_xlfn.STOCKHISTORY(#REF!, K96+1, K96+1, 0, 0, 1), _xlfn.STOCKHISTORY(#REF!, K96-2, K96-2, 0, 0, 1))))*_xlfn.XLOOKUP("Basic Weighted Average Shares",$B:$B,K:K)} -> #REF! | L98: {=(IFERROR(_xlfn.STOCKHISTORY(#REF!, L96, L96, 0, 0, 1), IFERROR(_xlfn.STOCKHISTORY(#REF!, L96+1, L96+1, 0, 0, 1), _xlfn.STOCKHISTORY(#REF!, L96-2, L96-2, 0, 0, 1))))*_xlfn.XLOOKUP("Basic Weighted Average Shares",$B:$B,L:L)} -> #REF! | M98: {=(IFERROR(_xlfn.STOCKHISTORY(#REF!, M96, M96, 0, 0, 1), IFERROR(_xlfn.STOCKHISTORY(#REF!, M96+1, M96+1, 0, 0, 1), _xlfn.STOCKHISTORY(#REF!, M96-2, M96-2, 0, 0, 1))))*_xlfn.XLOOKUP("Basic Weighted Average Shares",$B:$B,M:M)} -> #REF! | N98: {=(IFERROR(_xlfn.STOCKHISTORY(#REF!, N96, N96, 0, 0, 1), IFERROR(_xlfn.STOCKHISTORY(#REF!, N96+1, N96+1, 0, 0, 1), _xlfn.STOCKHISTORY(#REF!, N96-2, N96-2, 0, 0, 1))))*_xlfn.XLOOKUP("Basic Weighted Average Shares",$B:$B,N:N)} -> #REF! | O98: {=(IFERROR(_xlfn.STOCKHISTORY(#REF!, O96, O96, 0, 0, 1), IFERROR(_xlfn.STOCKHISTORY(#REF!, O96+1, O96+1, 0, 0, 1), _xlfn.STOCKHISTORY(#REF!, O96-2, O96-2, 0, 0, 1))))*_xlfn.XLOOKUP("Basic Weighted Average Shares",$B:$B,O:O)} -> #REF! | P98: {=(IFERROR(_xlfn.STOCKHISTORY(#REF!, P96, P96, 0, 0, 1), IFERROR(_xlfn.STOCKHISTORY(#REF!, P96+1, P96+1, 0, 0, 1), _xlfn.STOCKHISTORY(#REF!, P96-2, P96-2, 0, 0, 1))))*_xlfn.XLOOKUP("Basic Weighted Average Shares",$B:$B,P:P)} -> #REF! | Q98: {=(IFERROR(_xlfn.STOCKHISTORY(#REF!, Q96, Q96, 0, 0, 1), IFERROR(_xlfn.STOCKHISTORY(#REF!, Q96+1, Q96+1, 0, 0, 1), _xlfn.STOCKHISTORY(#REF!, Q96-2, Q96-2, 0, 0, 1))))*_xlfn.XLOOKUP("Basic Weighted Average Shares",$B:$B,Q:Q)} -> #REF!
B99: Cash & Cash Equivalents | G99: =_xlfn.XLOOKUP("Cash & Cash Equivalents & ST Investments",$B$30:$B$62,G$30:G$62) -> 0 | H99: =_xlfn.XLOOKUP("Cash & Cash Equivalents & ST Investments",$B$30:$B$62,H$30:H$62) -> 0 | I99: =_xlfn.XLOOKUP("Cash & Cash Equivalents & ST Investments",$B$30:$B$62,I$30:I$62) -> 0 | J99: =_xlfn.XLOOKUP("Cash & Cash Equivalents & ST Investments",$B$30:$B$62,J$30:J$62) -> 0 | K99: =_xlfn.XLOOKUP("Cash & Cash Equivalents & ST Investments",$B$30:$B$62,K$30:K$62) -> 0 | L99: =_xlfn.XLOOKUP("Cash & Cash Equivalents & ST Investments",$B$30:$B$62,L$30:L$62) -> 0 | M99: =_xlfn.XLOOKUP("Cash & Cash Equivalents & ST Investments",$B$30:$B$62,M$30:M$62) -> 0 | N99: =_xlfn.XLOOKUP("Cash & Cash Equivalents & ST Investments",$B$30:$B$62,N$30:N$62) -> 691 | ... Q99: =_xlfn.XLOOKUP("Cash & Cash Equivalents & ST Investments",$B$30:$B$62,Q$30:Q$62) -> 418.9
B100: Total Debt | G100: =(_xlfn.XLOOKUP("Short-Term Debt",$B$30:$B$62,G$30:G$62)+_xlfn.XLOOKUP("Long-Term Debt",$B$30:$B$62,G$30:G$62)) -> 0 | H100: =(_xlfn.XLOOKUP("Short-Term Debt",$B$30:$B$62,H$30:H$62)+_xlfn.XLOOKUP("Long-Term Debt",$B$30:$B$62,H$30:H$62)) -> 0 | I100: =(_xlfn.XLOOKUP("Short-Term Debt",$B$30:$B$62,I$30:I$62)+_xlfn.XLOOKUP("Long-Term Debt",$B$30:$B$62,I$30:I$62)) -> 0 | J100: =(_xlfn.XLOOKUP("Short-Term Debt",$B$30:$B$62,J$30:J$62)+_xlfn.XLOOKUP("Long-Term Debt",$B$30:$B$62,J$30:J$62)) -> 0 | K100: =(_xlfn.XLOOKUP("Short-Term Debt",$B$30:$B$62,K$30:K$62)+_xlfn.XLOOKUP("Long-Term Debt",$B$30:$B$62,K$30:K$62)) -> 0 | L100: =(_xlfn.XLOOKUP("Short-Term Debt",$B$30:$B$62,L$30:L$62)+_xlfn.XLOOKUP("Long-Term Debt",$B$30:$B$62,L$30:L$62)) -> 0 | M100: =(_xlfn.XLOOKUP("Short-Term Debt",$B$30:$B$62,M$30:M$62)+_xlfn.XLOOKUP("Long-Term Debt",$B$30:$B$62,M$30:M$62)) -> 0 | N100: =(_xlfn.XLOOKUP("Short-Term Debt",$B$30:$B$62,N$30:N$62)+_xlfn.XLOOKUP("Long-Term Debt",$B$30:$B$62,N$30:N$62)) -> 128.4 | ... Q100: =(_xlfn.XLOOKUP("Short-Term Debt",$B$30:$B$62,Q$30:Q$62)+_xlfn.XLOOKUP("Long-Term Debt",$B$30:$B$62,Q$30:Q$62)) -> 459.6
B101: Preferred Stock
B102: Non-Controlling Interest | G102: =_xlfn.XLOOKUP("Non-Controlling Interest",$B$30:$B$62,G$30:G$62) -> 0 | H102: =_xlfn.XLOOKUP("Non-Controlling Interest",$B$30:$B$62,H$30:H$62) -> 0 | I102: =_xlfn.XLOOKUP("Non-Controlling Interest",$B$30:$B$62,I$30:I$62) -> 0 | J102: =_xlfn.XLOOKUP("Non-Controlling Interest",$B$30:$B$62,J$30:J$62) -> 0 | K102: =_xlfn.XLOOKUP("Non-Controlling Interest",$B$30:$B$62,K$30:K$62) -> 0 | L102: =_xlfn.XLOOKUP("Non-Controlling Interest",$B$30:$B$62,L$30:L$62) -> 0 | M102: =_xlfn.XLOOKUP("Non-Controlling Interest",$B$30:$B$62,M$30:M$62) -> 0 | N102: =_xlfn.XLOOKUP("Non-Controlling Interest",$B$30:$B$62,N$30:N$62) -> 0 | ... Q102: =_xlfn.XLOOKUP("Non-Controlling Interest",$B$30:$B$62,Q$30:Q$62) -> 0
B103: Enterprise Value | G103: =+G98-G99+G100+G101+G102 -> #REF! | H103: =+H98-H99+H100+H101+H102 -> #REF! | I103: =+I98-I99+I100+I101+I102 -> #REF! | J103: =+J98-J99+J100+J101+J102 -> #REF! | K103: =+K98-K99+K100+K101+K102 -> #REF! | L103: =+L98-L99+L100+L101+L102 -> #REF! | M103: =+M98-M99+M100+M101+M102 -> #REF! | N103: =+N98-N99+N100+N101+N102 -> #REF! | ... Q103: =+Q98-Q99+Q100+Q101+Q102 -> #REF!
A105: x | B105: Debt Schedule | G105: Cash | H105: 2025 | I105: =+H105+1 -> 2026 | J105: =+I105+1 -> 2027 | K105: =+J105+1 -> 2028 | L105: =+K105+1 -> 2029 | M105: =+L105+1 -> 2030 | N105: =+M105+1 -> 2031 | O105: =+N105+1 -> 2032 | P105: =+O105+1 -> 2033 | Q105: =+P105+1 -> 2034
B107: Fixed | L107: 355
B108: Floating
A110: x | B110: Additional | G110: 2014 | H110: =+G110+1 -> 2015 | I110: =+H110+1 -> 2016 | J110: =+I110+1 -> 2017 | K110: =+J110+1 -> 2018 | L110: =+K110+1 -> 2019 | M110: =+L110+1 -> 2020 | N110: =+M110+1 -> 2021 | O110: =+N110+1 -> 2022 | ... Q110: =+P110+1 -> 2024 | R110: ="CAGR "&$G$4&" - "&$Q$4 -> CAGR 2014 - 2024
...

Sheet WACC
B2: WACC
B4: WACC = % of Equity x Cost of Equity + % de Debt x Cost of Debt x (1 - Tax Rate)
B5: Cost of Equity = Risk-Free Rate + Beta x Equity Risk Premium
B7: WACC | I7: Region | J7: Weight | K7: ERP | M7: Peers | N7: Beta (Unlevered)
B9: Market Cap (in millions) | G9: {=_FV(DCF!R4,"Market cap",TRUE)/1000000} -> 23495.324 | I9: =Segments!B6 -> United States | J9: =Segments!D6 -> 0.61512469 | K9: 0.0433 | M9: =+Peers!B8 | N9: =+Peers!E75
B10: % of Equity | G10: =IFERROR(G9/G24,"") -> 0.98081397 | I10: =Segments!B7 -> Japan | J10: =Segments!D7 -> 0.070341621 | K10: 0.0527 | M10: =+Peers!B9 | N10: =+Peers!F75
B11: Cost of Equity | G11: =IFERROR(G12+G14*G15,"") -> 0.13172978 | I11: =Segments!B9 -> Canada | J11: =Segments!D9 -> 0.23930456 | K11: 0.0433 | M11: =+Peers!B10 | N11: =+Peers!G75
B12: Risk-Free Rate | G12: 0.04418 | M12: =+Peers!B11 | N12: =+Peers!H75
B13: Unlevered Beta | G13: =+N19 | M13: =+Peers!B12 | N13: =+Peers!I75
B14: Beta | G14: {=_FV(DCF!R4,"Beta")} -> 2.1509 | I14: Others | J14: =1-SUM(J9:J13) -> 0.075229131 | K14: =MAX(K9:K13) -> 0.0527 | M14: =+Peers!B13 | N14: =+Peers!J75
B15: Equity Risk Premium | G15: =SUMPRODUCT(J9:J13,K9:K13) -> 0.04070379 | M15: =+Peers!B14 | N15: =+Peers!K75
B16: Unlevered Cost of Equity | G16: =+G14*G15+G12 -> 0.13172978 | M16: =+Peers!B15 | N16: =+Peers!L75
M17: =+Peers!B16 | N17: =+Peers!M75
B18: Debt (in millions) | G18: =+Inputs!Q55+Inputs!Q50 -> 459.6 | M18: =+Peers!B17 | N18: =+Peers!N75
B19: % of Debt | G19: =IFERROR(G18/G24,"") -> 0.019186035 | M19: Average | N19: =IFERROR(+AVERAGEIF(N9:N18,">0"),"")
B20: Cost of debt | G20: 0.0425
B21: Tax Rate | C21: 10 years | G21: 0
B22: Tax Rate | C22: after 10 years | G22: 0.24
B24: Total | G24: =+G9+G18 -> 23954.924
B26: WACC | C26: 10 years | G26: =IFERROR(G10*G11+G19*G20*(1-G21),"") -> 0.13001782
B27: WACC | C27: after 10 years | G27: =IFERROR(G10*G11+G19*G20*(1-G22),"") -> 0.12982212

Sheet Multiples
B2: Multiples
B4: Valuation | F4: 2014 | G4: =+F4+1 -> 2015 | H4: =+G4+1 -> 2016 | I4: =+H4+1 -> 2017 | J4: =+I4+1 -> 2018 | K4: =+J4+1 -> 2019 | L4: =+K4+1 -> 2020 | M4: =+L4+1 -> 2021 | N4: 2022 | O4: =+N4+1 -> 2023 | P4: =+O4+1 -> 2024 | Q4: =+P4+1 -> 2025 | R4: =+Q4+1 -> 2026
B6: EV / Sales | F6: =IFERROR(_xlfn.XLOOKUP("Enterprise Value",Inputs!$B:$B,Inputs!G:G)/_xlfn.XLOOKUP("Revenue (Sales)",Inputs!$B:$B,Inputs!G:G),"") | G6: =IFERROR(_xlfn.XLOOKUP("Enterprise Value",Inputs!$B:$B,Inputs!H:H)/_xlfn.XLOOKUP("Revenue (Sales)",Inputs!$B:$B,Inputs!H:H),"") | H6: =IFERROR(_xlfn.XLOOKUP("Enterprise Value",Inputs!$B:$B,Inputs!I:I)/_xlfn.XLOOKUP("Revenue (Sales)",Inputs!$B:$B,Inputs!I:I),"") | I6: =IFERROR(_xlfn.XLOOKUP("Enterprise Value",Inputs!$B:$B,Inputs!J:J)/_xlfn.XLOOKUP("Revenue (Sales)",Inputs!$B:$B,Inputs!J:J),"") | J6: =IFERROR(_xlfn.XLOOKUP("Enterprise Value",Inputs!$B:$B,Inputs!K:K)/_xlfn.XLOOKUP("Revenue (Sales)",Inputs!$B:$B,Inputs!K:K),"") | K6: =IFERROR(_xlfn.XLOOKUP("Enterprise Value",Inputs!$B:$B,Inputs!L:L)/_xlfn.XLOOKUP("Revenue (Sales)",Inputs!$B:$B,Inputs!L:L),"") | L6: =IFERROR(_xlfn.XLOOKUP("Enterprise Value",Inputs!$B:$B,Inputs!M:M)/_xlfn.XLOOKUP("Revenue (Sales)",Inputs!$B:$B,Inputs!M:M),"") | M6: =IFERROR(_xlfn.XLOOKUP("Enterprise Value",Inputs!$B:$B,Inputs!N:N)/_xlfn.XLOOKUP("Revenue (Sales)",Inputs!$B:$B,Inputs!N:N),"") | N6: =IFERROR(_xlfn.XLOOKUP("Enterprise Value",Inputs!$B:$B,Inputs!O:O)/_xlfn.XLOOKUP("Revenue (Sales)",Inputs!$B:$B,Inputs!O:O),"") | O6: =IFERROR(_xlfn.XLOOKUP("Enterprise Value",Inputs!$B:$B,Inputs!P:P)/_xlfn.XLOOKUP("Revenue (Sales)",Inputs!$B:$B,Inputs!P:P),"") | P6: =IFERROR(_xlfn.XLOOKUP("Enterprise Value",Inputs!$B:$B,Inputs!Q:Q)/_xlfn.XLOOKUP("Revenue (Sales)",Inputs!$B:$B,Inputs!Q:Q),"") | Q6: =IFERROR(_xlfn.XLOOKUP("Enterprise Value",#REF!,#REF!)/_xlfn.XLOOKUP("Revenue (Sales)",#REF!,#REF!),"") | R6: =IFERROR(_xlfn.XLOOKUP("Enterprise Value",#REF!,#REF!)/_xlfn.XLOOKUP("Revenue (Sales)",#REF!,#REF!),"")
B7: Price / Sales | F7: =IFERROR(_xlfn.XLOOKUP("Market Capitalization",Inputs!$B:$B,Inputs!G:G)/_xlfn.XLOOKUP("Revenue (Sales)",Inputs!$B:$B,Inputs!G:G),"") | G7: =IFERROR(_xlfn.XLOOKUP("Market Capitalization",Inputs!$B:$B,Inputs!H:H)/_xlfn.XLOOKUP("Revenue (Sales)",Inputs!$B:$B,Inputs!H:H),"") | H7: =IFERROR(_xlfn.XLOOKUP("Market Capitalization",Inputs!$B:$B,Inputs!I:I)/_xlfn.XLOOKUP("Revenue (Sales)",Inputs!$B:$B,Inputs!I:I),"") | I7: =IFERROR(_xlfn.XLOOKUP("Market Capitalization",Inputs!$B:$B,Inputs!J:J)/_xlfn.XLOOKUP("Revenue (Sales)",Inputs!$B:$B,Inputs!J:J),"") | J7: =IFERROR(_xlfn.XLOOKUP("Market Capitalization",Inputs!$B:$B,Inputs!K:K)/_xlfn.XLOOKUP("Revenue (Sales)",Inputs!$B:$B,Inputs!K:K),"") | K7: =IFERROR(_xlfn.XLOOKUP("Market Capitalization",Inputs!$B:$B,Inputs!L:L)/_xlfn.XLOOKUP("Revenue (Sales)",Inputs!$B:$B,Inputs!L:L),"") | L7: =IFERROR(_xlfn.XLOOKUP("Market Capitalization",Inputs!$B:$B,Inputs!M:M)/_xlfn.XLOOKUP("Revenue (Sales)",Inputs!$B:$B,Inputs!M:M),"") | M7: =IFERROR(_xlfn.XLOOKUP("Market Capitalization",Inputs!$B:$B,Inputs!N:N)/_xlfn.XLOOKUP("Revenue (Sales)",Inputs!$B:$B,Inputs!N:N),"") | N7: =IFERROR(_xlfn.XLOOKUP("Market Capitalization",Inputs!$B:$B,Inputs!O:O)/_xlfn.XLOOKUP("Revenue (Sales)",Inputs!$B:$B,Inputs!O:O),"") | O7: =IFERROR(_xlfn.XLOOKUP("Market Capitalization",Inputs!$B:$B,Inputs!P:P)/_xlfn.XLOOKUP("Revenue (Sales)",Inputs!$B:$B,Inputs!P:P),"") | P7: =IFERROR(_xlfn.XLOOKUP("Market Capitalization",Inputs!$B:$B,Inputs!Q:Q)/_xlfn.XLOOKUP("Revenue (Sales)",Inputs!$B:$B,Inputs!Q:Q),"") | Q7: =IFERROR(_xlfn.XLOOKUP("Equity Value",#REF!,#REF!)/_xlfn.XLOOKUP("Revenue (Sales)",#REF!,#REF!),"") | R7: =IFERROR(_xlfn.XLOOKUP("Equity Value",#REF!,#REF!)/_xlfn.XLOOKUP("Revenue (Sales)",#REF!,#REF!),"")
B8: EV / EBITDA | F8: =IFERROR(_xlfn.XLOOKUP("Enterprise Value",Inputs!$B:$B,Inputs!G:G)/_xlfn.XLOOKUP("EBITDA",Inputs!$B:$B,Inputs!G:G),"") | G8: =IFERROR(_xlfn.XLOOKUP("Enterprise Value",Inputs!$B:$B,Inputs!H:H)/_xlfn.XLOOKUP("EBITDA",Inputs!$B:$B,Inputs!H:H),"") | H8: =IFERROR(_xlfn.XLOOKUP("Enterprise Value",Inputs!$B:$B,Inputs!I:I)/_xlfn.XLOOKUP("EBITDA",Inputs!$B:$B,Inputs!I:I),"") | I8: =IFERROR(_xlfn.XLOOKUP("Enterprise Value",Inputs!$B:$B,Inputs!J:J)/_xlfn.XLOOKUP("EBITDA",Inputs!$B:$B,Inputs!J:J),"") | J8: =IFERROR(_xlfn.XLOOKUP("Enterprise Value",Inputs!$B:$B,Inputs!K:K)/_xlfn.XLOOKUP("EBITDA",Inputs!$B:$B,Inputs!K:K),"") | K8: =IFERROR(_xlfn.XLOOKUP("Enterprise Value",Inputs!$B:$B,Inputs!L:L)/_xlfn.XLOOKUP("EBITDA",Inputs!$B:$B,Inputs!L:L),"") | L8: =IFERROR(_xlfn.XLOOKUP("Enterprise Value",Inputs!$B:$B,Inputs!M:M)/_xlfn.XLOOKUP("EBITDA",Inputs!$B:$B,Inputs!M:M),"") | M8: =IFERROR(_xlfn.XLOOKUP("Enterprise Value",Inputs!$B:$B,Inputs!N:N)/_xlfn.XLOOKUP("EBITDA",Inputs!$B:$B,Inputs!N:N),"") | N8: =IFERROR(_xlfn.XLOOKUP("Enterprise Value",Inputs!$B:$B,Inputs!O:O)/_xlfn.XLOOKUP("EBITDA",Inputs!$B:$B,Inputs!O:O),"") | O8: =IFERROR(_xlfn.XLOOKUP("Enterprise Value",Inputs!$B:$B,Inputs!P:P)/_xlfn.XLOOKUP("EBITDA",Inputs!$B:$B,Inputs!P:P),"") | P8: =IFERROR(_xlfn.XLOOKUP("Enterprise Value",Inputs!$B:$B,Inputs!Q:Q)/_xlfn.XLOOKUP("EBITDA",Inputs!$B:$B,Inputs!Q:Q),"") | Q8: =IFERROR(_xlfn.XLOOKUP("Enterprise Value",#REF!,#REF!)/_xlfn.XLOOKUP("EBITDA",#REF!,#REF!),"") | R8: =IFERROR(_xlfn.XLOOKUP("Enterprise Value",#REF!,#REF!)/_xlfn.XLOOKUP("EBITDA",#REF!,#REF!),"")
B9: EV / EBIT | F9: =IFERROR(_xlfn.XLOOKUP("Enterprise Value",Inputs!$B:$B,Inputs!G:G)/_xlfn.XLOOKUP("Operating Income (EBIT)",Inputs!$B:$B,Inputs!G:G),"") | G9: =IFERROR(_xlfn.XLOOKUP("Enterprise Value",Inputs!$B:$B,Inputs!H:H)/_xlfn.XLOOKUP("Operating Income (EBIT)",Inputs!$B:$B,Inputs!H:H),"") | H9: =IFERROR(_xlfn.XLOOKUP("Enterprise Value",Inputs!$B:$B,Inputs!I:I)/_xlfn.XLOOKUP("Operating Income (EBIT)",Inputs!$B:$B,Inputs!I:I),"") | I9: =IFERROR(_xlfn.XLOOKUP("Enterprise Value",Inputs!$B:$B,Inputs!J:J)/_xlfn.XLOOKUP("Operating Income (EBIT)",Inputs!$B:$B,Inputs!J:J),"") | J9: =IFERROR(_xlfn.XLOOKUP("Enterprise Value",Inputs!$B:$B,Inputs!K:K)/_xlfn.XLOOKUP("Operating Income (EBIT)",Inputs!$B:$B,Inputs!K:K),"") | K9: =IFERROR(_xlfn.XLOOKUP("Enterprise Value",Inputs!$B:$B,Inputs!L:L)/_xlfn.XLOOKUP("Operating Income (EBIT)",Inputs!$B:$B,Inputs!L:L),"") | L9: =IFERROR(_xlfn.XLOOKUP("Enterprise Value",Inputs!$B:$B,Inputs!M:M)/_xlfn.XLOOKUP("Operating Income (EBIT)",Inputs!$B:$B,Inputs!M:M),"") | M9: =IFERROR(_xlfn.XLOOKUP("Enterprise Value",Inputs!$B:$B,Inputs!N:N)/_xlfn.XLOOKUP("Operating Income (EBIT)",Inputs!$B:$B,Inputs!N:N),"") | N9: =IFERROR(_xlfn.XLOOKUP("Enterprise Value",Inputs!$B:$B,Inputs!O:O)/_xlfn.XLOOKUP("Operating Income (EBIT)",Inputs!$B:$B,Inputs!O:O),"") | O9: =IFERROR(_xlfn.XLOOKUP("Enterprise Value",Inputs!$B:$B,Inputs!P:P)/_xlfn.XLOOKUP("Operating Income (EBIT)",Inputs!$B:$B,Inputs!P:P),"") | P9: =IFERROR(_xlfn.XLOOKUP("Enterprise Value",Inputs!$B:$B,Inputs!Q:Q)/_xlfn.XLOOKUP("Operating Income (EBIT)",Inputs!$B:$B,Inputs!Q:Q),"") | Q9: =IFERROR(_xlfn.XLOOKUP("Enterprise Value",#REF!,#REF!)/_xlfn.XLOOKUP("Operating Income (EBIT)",#REF!,#REF!),"") | R9: =IFERROR(_xlfn.XLOOKUP("Enterprise Value",#REF!,#REF!)/_xlfn.XLOOKUP("Operating Income (EBIT)",#REF!,#REF!),"")
B10: Price / Earnings | F10: =IFERROR(_xlfn.XLOOKUP("Market Capitalization",Inputs!$B:$B,Inputs!G:G)/_xlfn.XLOOKUP("Net Income",Inputs!$B:$B,Inputs!G:G),"") | G10: =IFERROR(_xlfn.XLOOKUP("Market Capitalization",Inputs!$B:$B,Inputs!H:H)/_xlfn.XLOOKUP("Net Income",Inputs!$B:$B,Inputs!H:H),"") | H10: =IFERROR(_xlfn.XLOOKUP("Market Capitalization",Inputs!$B:$B,Inputs!I:I)/_xlfn.XLOOKUP("Net Income",Inputs!$B:$B,Inputs!I:I),"") | I10: =IFERROR(_xlfn.XLOOKUP("Market Capitalization",Inputs!$B:$B,Inputs!J:J)/_xlfn.XLOOKUP("Net Income",Inputs!$B:$B,Inputs!J:J),"") | J10: =IFERROR(_xlfn.XLOOKUP("Market Capitalization",Inputs!$B:$B,Inputs!K:K)/_xlfn.XLOOKUP("Net Income",Inputs!$B:$B,Inputs!K:K),"") | K10: =IFERROR(_xlfn.XLOOKUP("Market Capitalization",Inputs!$B:$B,Inputs!L:L)/_xlfn.XLOOKUP("Net Income",Inputs!$B:$B,Inputs!L:L),"") | L10: =IFERROR(_xlfn.XLOOKUP("Market Capitalization",Inputs!$B:$B,Inputs!M:M)/_xlfn.XLOOKUP("Net Income",Inputs!$B:$B,Inputs!M:M),"") | M10: =IFERROR(_xlfn.XLOOKUP("Market Capitalization",Inputs!$B:$B,Inputs!N:N)/_xlfn.XLOOKUP("Net Income",Inputs!$B:$B,Inputs!N:N),"") | N10: =IFERROR(_xlfn.XLOOKUP("Market Capitalization",Inputs!$B:$B,Inputs!O:O)/_xlfn.XLOOKUP("Net Income",Inputs!$B:$B,Inputs!O:O),"") | O10: =IFERROR(_xlfn.XLOOKUP("Market Capitalization",Inputs!$B:$B,Inputs!P:P)/_xlfn.XLOOKUP("Net Income",Inputs!$B:$B,Inputs!P:P),"") | P10: =IFERROR(_xlfn.XLOOKUP("Market Capitalization",Inputs!$B:$B,Inputs!Q:Q)/_xlfn.XLOOKUP("Net Income",Inputs!$B:$B,Inputs!Q:Q),"") | Q10: =IFERROR(_xlfn.XLOOKUP("Equity Value",#REF!,#REF!)/_xlfn.XLOOKUP("Net Income",#REF!,#REF!),"") | R10: =IFERROR(_xlfn.XLOOKUP("Equity Value",#REF!,#REF!)/_xlfn.XLOOKUP("Net Income",#REF!,#REF!),"")
B11: Price / Book | F11: =IFERROR(_xlfn.XLOOKUP("Market Capitalization",Inputs!$B:$B,Inputs!G:G)/_xlfn.XLOOKUP("Shareholder's Equity",Inputs!$B:$B,Inputs!G:G),"") | G11: =IFERROR(_xlfn.XLOOKUP("Market Capitalization",Inputs!$B:$B,Inputs!H:H)/_xlfn.XLOOKUP("Shareholder's Equity",Inputs!$B:$B,Inputs!H:H),"") | H11: =IFERROR(_xlfn.XLOOKUP("Market Capitalization",Inputs!$B:$B,Inputs!I:I)/_xlfn.XLOOKUP("Shareholder's Equity",Inputs!$B:$B,Inputs!I:I),"") | I11: =IFERROR(_xlfn.XLOOKUP("Market Capitalization",Inputs!$B:$B,Inputs!J:J)/_xlfn.XLOOKUP("Shareholder's Equity",Inputs!$B:$B,Inputs!J:J),"") | J11: =IFERROR(_xlfn.XLOOKUP("Market Capitalization",Inputs!$B:$B,Inputs!K:K)/_xlfn.XLOOKUP("Shareholder's Equity",Inputs!$B:$B,Inputs!K:K),"") | K11: =IFERROR(_xlfn.XLOOKUP("Market Capitalization",Inputs!$B:$B,Inputs!L:L)/_xlfn.XLOOKUP("Shareholder's Equity",Inputs!$B:$B,Inputs!L:L),"") | L11: =IFERROR(_xlfn.XLOOKUP("Market Capitalization",Inputs!$B:$B,Inputs!M:M)/_xlfn.XLOOKUP("Shareholder's Equity",Inputs!$B:$B,Inputs!M:M),"") | M11: =IFERROR(_xlfn.XLOOKUP("Market Capitalization",Inputs!$B:$B,Inputs!N:N)/_xlfn.XLOOKUP("Shareholder's Equity",Inputs!$B:$B,Inputs!N:N),"") | N11: =IFERROR(_xlfn.XLOOKUP("Market Capitalization",Inputs!$B:$B,Inputs!O:O)/_xlfn.XLOOKUP("Shareholder's Equity",Inputs!$B:$B,Inputs!O:O),"") | O11: =IFERROR(_xlfn.XLOOKUP("Market Capitalization",Inputs!$B:$B,Inputs!P:P)/_xlfn.XLOOKUP("Shareholder's Equity",Inputs!$B:$B,Inputs!P:P),"") | P11: =IFERROR(_xlfn.XLOOKUP("Market Capitalization",Inputs!$B:$B,Inputs!Q:Q)/_xlfn.XLOOKUP("Shareholder's Equity",Inputs!$B:$B,Inputs!Q:Q),"") | Q11: =IFERROR(+_xlfn.XLOOKUP("Equity Value",#REF!,#REF!)/(_xlfn.XLOOKUP("Shareholder's Equity",Inputs!$B:$B,Inputs!$Q:$Q)+_xlfn.XLOOKUP("Net Income",#REF!,#REF!)+_xlfn.XLOOKUP("Total Payout",#REF!,#REF!)),"") | R11: =IFERROR(+_xlfn.XLOOKUP("Equity Value",#REF!,#REF!)/(_xlfn.XLOOKUP("Shareholder's Equity",Inputs!$B:$B,Inputs!$Q:$Q)+_xlfn.XLOOKUP("Net Income",#REF!,#REF!)+_xlfn.XLOOKUP("Total Payout",#REF!,#REF!)),"")
B13: Profitability | F13: 2014 | G13: =+F13+1 -> 2015 | H13: =+G13+1 -> 2016 | I13: =+H13+1 -> 2017 | J13: =+I13+1 -> 2018 | K13: =+J13+1 -> 2019 | L13: =+K13+1 -> 2020 | M13: =+L13+1 -> 2021 | N13: 2022 | O13: =+N13+1 -> 2023 | P13: =+O13+1 -> 2024 | Q13: =+P13+1 -> 2025 | R13: =+Q13+1 -> 2026
B15: Return on Assets | F15: =+IFERROR(_xlfn.XLOOKUP("Net Income",Inputs!$B:$B,Inputs!G:G)/_xlfn.XLOOKUP("Total Assets",Inputs!$B:$B,Inputs!G:G),"") | G15: =+IFERROR(_xlfn.XLOOKUP("Net Income",Inputs!$B:$B,Inputs!H:H)/_xlfn.XLOOKUP("Total Assets",Inputs!$B:$B,Inputs!H:H),"") | H15: =+IFERROR(_xlfn.XLOOKUP("Net Income",Inputs!$B:$B,Inputs!I:I)/_xlfn.XLOOKUP("Total Assets",Inputs!$B:$B,Inputs!I:I),"") | I15: =+IFERROR(_xlfn.XLOOKUP("Net Income",Inputs!$B:$B,Inputs!J:J)/_xlfn.XLOOKUP("Total Assets",Inputs!$B:$B,Inputs!J:J),"") | J15: =+IFERROR(_xlfn.XLOOKUP("Net Income",Inputs!$B:$B,Inputs!K:K)/_xlfn.XLOOKUP("Total Assets",Inputs!$B:$B,Inputs!K:K),"") | K15: =+IFERROR(_xlfn.XLOOKUP("Net Income",Inputs!$B:$B,Inputs!L:L)/_xlfn.XLOOKUP("Total Assets",Inputs!$B:$B,Inputs!L:L),"") | L15: =+IFERROR(_xlfn.XLOOKUP("Net Income",Inputs!$B:$B,Inputs!M:M)/_xlfn.XLOOKUP("Total Assets",Inputs!$B:$B,Inputs!M:M),"") | M15: =+IFERROR(_xlfn.XLOOKUP("Net Income",Inputs!$B:$B,Inputs!N:N)/_xlfn.XLOOKUP("Total Assets",Inputs!$B:$B,Inputs!N:N),"") -> -0.10866551 | N15: =+IFERROR(_xlfn.XLOOKUP("Net Income",Inputs!$B:$B,Inputs!O:O)/_xlfn.XLOOKUP("Total Assets",Inputs!$B:$B,Inputs!O:O),"") -> -0.10764331 | O15: =+IFERROR(_xlfn.XLOOKUP("Net Income",Inputs!$B:$B,Inputs!P:P)/_xlfn.XLOOKUP("Total Assets",Inputs!$B:$B,Inputs!P:P),"") -> -0.1638334 | P15: =+IFERROR(_xlfn.XLOOKUP("Net Income",Inputs!$B:$B,Inputs!Q:Q)/_xlfn.XLOOKUP("Total Assets",Inputs!$B:$B,Inputs!Q:Q),"") -> -0.12727349 | Q15: =IFERROR(_xlfn.XLOOKUP("Net Income",#REF!,#REF!)/_xlfn.XLOOKUP("Total assets",#REF!,#REF!),"") | R15: =IFERROR(_xlfn.XLOOKUP("Net Income",#REF!,#REF!)/_xlfn.XLOOKUP("Total assets",#REF!,#REF!),"")
B16: Return on Equity | F16: =IFERROR(_xlfn.XLOOKUP("Net Income",Inputs!$B:$B,Inputs!G:G)/_xlfn.XLOOKUP("Shareholder's Equity",Inputs!$B:$B,Inputs!G:G),"") | G16: =IFERROR(_xlfn.XLOOKUP("Net Income",Inputs!$B:$B,Inputs!H:H)/_xlfn.XLOOKUP("Shareholder's Equity",Inputs!$B:$B,Inputs!H:H),"") | H16: =IFERROR(_xlfn.XLOOKUP("Net Income",Inputs!$B:$B,Inputs!I:I)/_xlfn.XLOOKUP("Shareholder's Equity",Inputs!$B:$B,Inputs!I:I),"") | I16: =IFERROR(_xlfn.XLOOKUP("Net Income",Inputs!$B:$B,Inputs!J:J)/_xlfn.XLOOKUP("Shareholder's Equity",Inputs!$B:$B,Inputs!J:J),"") | J16: =IFERROR(_xlfn.XLOOKUP("Net Income",Inputs!$B:$B,Inputs!K:K)/_xlfn.XLOOKUP("Shareholder's Equity",Inputs!$B:$B,Inputs!K:K),"") | K16: =IFERROR(_xlfn.XLOOKUP("Net Income",Inputs!$B:$B,Inputs!L:L)/_xlfn.XLOOKUP("Shareholder's Equity",Inputs!$B:$B,Inputs!L:L),"") | L16: =IFERROR(_xlfn.XLOOKUP("Net Income",Inputs!$B:$B,Inputs!M:M)/_xlfn.XLOOKUP("Shareholder's Equity",Inputs!$B:$B,Inputs!M:M),"") | M16: =IFERROR(_xlfn.XLOOKUP("Net Income",Inputs!$B:$B,Inputs!N:N)/_xlfn.XLOOKUP("Shareholder's Equity",Inputs!$B:$B,Inputs!N:N),"") -> -0.15259843 | N16: =IFERROR(_xlfn.XLOOKUP("Net Income",Inputs!$B:$B,Inputs!O:O)/_xlfn.XLOOKUP("Shareholder's Equity",Inputs!$B:$B,Inputs!O:O),"") -> -0.15815508 | O16: =IFERROR(_xlfn.XLOOKUP("Net Income",Inputs!$B:$B,Inputs!P:P)/_xlfn.XLOOKUP("Shareholder's Equity",Inputs!$B:$B,Inputs!P:P),"") -> -0.27808837 | P16: =IFERROR(_xlfn.XLOOKUP("Net Income",Inputs!$B:$B,Inputs!Q:Q)/_xlfn.XLOOKUP("Shareholder's Equity",Inputs!$B:$B,Inputs!Q:Q),"") -> -0.39416841 | Q16: =IFERROR(_xlfn.XLOOKUP("Net Income",#REF!,#REF!)/_xlfn.XLOOKUP("Shareholder's Equity",#REF!,#REF!),"") | R16: =IFERROR(_xlfn.XLOOKUP("Net Income",#REF!,#REF!)/_xlfn.XLOOKUP("Shareholder's Equity",#REF!,#REF!),"")
B17: Return on Total Capital | F17: =IFERROR(_xlfn.XLOOKUP("NOPAT",Inputs!$B:$B,Inputs!G:G)/(_xlfn.XLOOKUP("Shareholder's Equity",Inputs!$B:$B,Inputs!G:G)+_xlfn.XLOOKUP("Total Debt",Inputs!$B:$B,Inputs!G:G,,,-1)),"") | G17: =IFERROR(_xlfn.XLOOKUP("NOPAT",Inputs!$B:$B,Inputs!H:H)/(_xlfn.XLOOKUP("Shareholder's Equity",Inputs!$B:$B,Inputs!H:H)+_xlfn.XLOOKUP("Total Debt",Inputs!$B:$B,Inputs!H:H,,,-1)),"") | H17: =IFERROR(_xlfn.XLOOKUP("NOPAT",Inputs!$B:$B,Inputs!I:I)/(_xlfn.XLOOKUP("Shareholder's Equity",Inputs!$B:$B,Inputs!I:I)+_xlfn.XLOOKUP("Total Debt",Inputs!$B:$B,Inputs!I:I,,,-1)),"") | I17: =IFERROR(_xlfn.XLOOKUP("NOPAT",Inputs!$B:$B,Inputs!J:J)/(_xlfn.XLOOKUP("Shareholder's Equity",Inputs!$B:$B,Inputs!J:J)+_xlfn.XLOOKUP("Total Debt",Inputs!$B:$B,Inputs!J:J,,,-1)),"") | J17: =IFERROR(_xlfn.XLOOKUP("NOPAT",Inputs!$B:$B,Inputs!K:K)/(_xlfn.XLOOKUP("Shareholder's Equity",Inputs!$B:$B,Inputs!K:K)+_xlfn.XLOOKUP("Total Debt",Inputs!$B:$B,Inputs!K:K,,,-1)),"") | K17: =IFERROR(_xlfn.XLOOKUP("NOPAT",Inputs!$B:$B,Inputs!L:L)/(_xlfn.XLOOKUP("Shareholder's Equity",Inputs!$B:$B,Inputs!L:L)+_xlfn.XLOOKUP("Total Debt",Inputs!$B:$B,Inputs!L:L,,,-1)),"") | L17: =IFERROR(_xlfn.XLOOKUP("NOPAT",Inputs!$B:$B,Inputs!M:M)/(_xlfn.XLOOKUP("Shareholder's Equity",Inputs!$B:$B,Inputs!M:M)+_xlfn.XLOOKUP("Total Debt",Inputs!$B:$B,Inputs!M:M,,,-1)),"") | M17: =IFERROR(_xlfn.XLOOKUP("NOPAT",Inputs!$B:$B,Inputs!N:N)/(_xlfn.XLOOKUP("Shareholder's Equity",Inputs!$B:$B,Inputs!N:N)+_xlfn.XLOOKUP("Total Debt",Inputs!$B:$B,Inputs!N:N,,,-1)),"") -> -0.10314284 | N17: =IFERROR(_xlfn.XLOOKUP("NOPAT",Inputs!$B:$B,Inputs!O:O)/(_xlfn.XLOOKUP("Shareholder's Equity",Inputs!$B:$B,Inputs!O:O)+_xlfn.XLOOKUP("Total Debt",Inputs!$B:$B,Inputs!O:O,,,-1)),"") -> -0.13640392 | O17: =IFERROR(_xlfn.XLOOKUP("NOPAT",Inputs!$B:$B,Inputs!P:P)/(_xlfn.XLOOKUP("Shareholder's Equity",Inputs!$B:$B,Inputs!P:P)+_xlfn.XLOOKUP("Total Debt",Inputs!$B:$B,Inputs!P:P,,,-1)),"") -> -0.21705458 | P17: =IFERROR(_xlfn.XLOOKUP("NOPAT",Inputs!$B:$B,Inputs!Q:Q)/(_xlfn.XLOOKUP("Shareholder's Equity",Inputs!$B:$B,Inputs!Q:Q)+_xlfn.XLOOKUP("Total Debt",Inputs!$B:$B,Inputs!Q:Q,,,-1)),"") -> -0.17937245 | Q17: =+IFERROR(_xlfn.XLOOKUP("NOPAT",#REF!,#REF!)/(_xlfn.XLOOKUP("Shareholder's Equity",#REF!,#REF!)+_xlfn.XLOOKUP("Total Borrowings",#REF!,#REF!)+_xlfn.XLOOKUP("Total Leases",#REF!,#REF!)),"") | R17: =+IFERROR(_xlfn.XLOOKUP("NOPAT",#REF!,#REF!)/(_xlfn.XLOOKUP("Shareholder's Equity",#REF!,#REF!)+_xlfn.XLOOKUP("Total Borrowings",#REF!,#REF!)+_xlfn.XLOOKUP("Total Leases",#REF!,#REF!)),"")
B18: EBITDA Margin | F18: =+IFERROR(_xlfn.XLOOKUP("EBITDA",Inputs!$B:$B,Inputs!G:G)/_xlfn.XLOOKUP("Revenue (Sales)",Inputs!$B:$B,Inputs!G:G),"") | G18: =+IFERROR(_xlfn.XLOOKUP("EBITDA",Inputs!$B:$B,Inputs!H:H)/_xlfn.XLOOKUP("Revenue (Sales)",Inputs!$B:$B,Inputs!H:H),"") | H18: =+IFERROR(_xlfn.XLOOKUP("EBITDA",Inputs!$B:$B,Inputs!I:I)/_xlfn.XLOOKUP("Revenue (Sales)",Inputs!$B:$B,Inputs!I:I),"") | I18: =+IFERROR(_xlfn.XLOOKUP("EBITDA",Inputs!$B:$B,Inputs!J:J)/_xlfn.XLOOKUP("Revenue (Sales)",Inputs!$B:$B,Inputs!J:J),"") | J18: =+IFERROR(_xlfn.XLOOKUP("EBITDA",Inputs!$B:$B,Inputs!K:K)/_xlfn.XLOOKUP("Revenue (Sales)",Inputs!$B:$B,Inputs!K:K),"") | K18: =+IFERROR(_xlfn.XLOOKUP("EBITDA",Inputs!$B:$B,Inputs!L:L)/_xlfn.XLOOKUP("Revenue (Sales)",Inputs!$B:$B,Inputs!L:L),"") | L18: =+IFERROR(_xlfn.XLOOKUP("EBITDA",Inputs!$B:$B,Inputs!M:M)/_xlfn.XLOOKUP("Revenue (Sales)",Inputs!$B:$B,Inputs!M:M),"") | M18: =+IFERROR(_xlfn.XLOOKUP("EBITDA",Inputs!$B:$B,Inputs!N:N)/_xlfn.XLOOKUP("Revenue (Sales)",Inputs!$B:$B,Inputs!N:N),"") -> -1.6414791 | N18: =+IFERROR(_xlfn.XLOOKUP("EBITDA",Inputs!$B:$B,Inputs!O:O)/_xlfn.XLOOKUP("Revenue (Sales)",Inputs!$B:$B,Inputs!O:O),"") -> -0.64075829 | O18: =+IFERROR(_xlfn.XLOOKUP("EBITDA",Inputs!$B:$B,Inputs!P:P)/_xlfn.XLOOKUP("Revenue (Sales)",Inputs!$B:$B,Inputs!P:P),"") -> -0.72771872 | P18: =+IFERROR(_xlfn.XLOOKUP("EBITDA",Inputs!$B:$B,Inputs!Q:Q)/_xlfn.XLOOKUP("Revenue (Sales)",Inputs!$B:$B,Inputs!Q:Q),"") -> -0.41746905 | Q18: =+_xlfn.XLOOKUP("EBITDA Margin",#REF!,#REF!) -> #REF! | R18: =+_xlfn.XLOOKUP("EBITDA Margin",#REF!,#REF!) -> #REF!
B19: EBIT Margin | F19: =IFERROR(_xlfn.XLOOKUP("Operating Income (EBIT)",Inputs!$B:$B,Inputs!G:G)/_xlfn.XLOOKUP("Revenue (Sales)",Inputs!$B:$B,Inputs!G:G),"") | G19: =IFERROR(_xlfn.XLOOKUP("Operating Income (EBIT)",Inputs!$B:$B,Inputs!H:H)/_xlfn.XLOOKUP("Revenue (Sales)",Inputs!$B:$B,Inputs!H:H),"") | H19: =IFERROR(_xlfn.XLOOKUP("Operating Income (EBIT)",Inputs!$B:$B,Inputs!I:I)/_xlfn.XLOOKUP("Revenue (Sales)",Inputs!$B:$B,Inputs!I:I),"") | I19: =IFERROR(_xlfn.XLOOKUP("Operating Income (EBIT)",Inputs!$B:$B,Inputs!J:J)/_xlfn.XLOOKUP("Revenue (Sales)",Inputs!$B:$B,Inputs!J:J),"") | J19: =IFERROR(_xlfn.XLOOKUP("Operating Income (EBIT)",Inputs!$B:$B,Inputs!K:K)/_xlfn.XLOOKUP("Revenue (Sales)",Inputs!$B:$B,Inputs!K:K),"") | K19: =IFERROR(_xlfn.XLOOKUP("Operating Income (EBIT)",Inputs!$B:$B,Inputs!L:L)/_xlfn.XLOOKUP("Revenue (Sales)",Inputs!$B:$B,Inputs!L:L),"") | L19: =IFERROR(_xlfn.XLOOKUP("Operating Income (EBIT)",Inputs!$B:$B,Inputs!M:M)/_xlfn.XLOOKUP("Revenue (Sales)",Inputs!$B:$B,Inputs!M:M),"") | M19: =IFERROR(_xlfn.XLOOKUP("Operating Income (EBIT)",Inputs!$B:$B,Inputs!N:N)/_xlfn.XLOOKUP("Revenue (Sales)",Inputs!$B:$B,Inputs!N:N),"") -> -1.4676849 | N19: =IFERROR(_xlfn.XLOOKUP("Operating Income (EBIT)",Inputs!$B:$B,Inputs!O:O)/_xlfn.XLOOKUP("Revenue (Sales)",Inputs!$B:$B,Inputs!O:O),"") -> -0.50127962 | O19: =IFERROR(_xlfn.XLOOKUP("Operating Income (EBIT)",Inputs!$B:$B,Inputs!P:P)/_xlfn.XLOOKUP("Revenue (Sales)",Inputs!$B:$B,Inputs!P:P),"") -> -0.61120196 | P19: =IFERROR(_xlfn.XLOOKUP("Operating Income (EBIT)",Inputs!$B:$B,Inputs!Q:Q)/_xlfn.XLOOKUP("Revenue (Sales)",Inputs!$B:$B,Inputs!Q:Q),"") -> -0.34440624 | Q19: =+_xlfn.XLOOKUP("Operating Margin",#REF!,#REF!) -> #REF! | R19: =+_xlfn.XLOOKUP("Operating Margin",#REF!,#REF!) -> #REF!
B20: EBT Margin | F20: =IFERROR(_xlfn.XLOOKUP("Pre-Tax Income (EBT)",Inputs!$B:$B,Inputs!G:G)/_xlfn.XLOOKUP("Revenue (Sales)",Inputs!$B:$B,Inputs!G:G),"") | G20: =IFERROR(_xlfn.XLOOKUP("Pre-Tax Income (EBT)",Inputs!$B:$B,Inputs!H:H)/_xlfn.XLOOKUP("Revenue (Sales)",Inputs!$B:$B,Inputs!H:H),"") | H20: =IFERROR(_xlfn.XLOOKUP("Pre-Tax Income (EBT)",Inputs!$B:$B,Inputs!I:I)/_xlfn.XLOOKUP("Revenue (Sales)",Inputs!$B:$B,Inputs!I:I),"") | I20: =IFERROR(_xlfn.XLOOKUP("Pre-Tax Income (EBT)",Inputs!$B:$B,Inputs!J:J)/_xlfn.XLOOKUP("Revenue (Sales)",Inputs!$B:$B,Inputs!J:J),"") | J20: =IFERROR(_xlfn.XLOOKUP("Pre-Tax Income (EBT)",Inputs!$B:$B,Inputs!K:K)/_xlfn.XLOOKUP("Revenue (Sales)",Inputs!$B:$B,Inputs!K:K),"") | K20: =IFERROR(_xlfn.XLOOKUP("Pre-Tax Income (EBT)",Inputs!$B:$B,Inputs!L:L)/_xlfn.XLOOKUP("Revenue (Sales)",Inputs!$B:$B,Inputs!L:L),"") | L20: =IFERROR(_xlfn.XLOOKUP("Pre-Tax Income (EBT)",Inputs!$B:$B,Inputs!M:M)/_xlfn.XLOOKUP("Revenue (Sales)",Inputs!$B:$B,Inputs!M:M),"") | M20: =IFERROR(_xlfn.XLOOKUP("Pre-Tax Income (EBT)",Inputs!$B:$B,Inputs!N:N)/_xlfn.XLOOKUP("Revenue (Sales)",Inputs!$B:$B,Inputs!N:N),"") -> -1.8342444 | N20: =IFERROR(_xlfn.XLOOKUP("Pre-Tax Income (EBT)",Inputs!$B:$B,Inputs!O:O)/_xlfn.XLOOKUP("Revenue (Sales)",Inputs!$B:$B,Inputs!O:O),"") -> -0.49037915 | O20: =IFERROR(_xlfn.XLOOKUP("Pre-Tax Income (EBT)",Inputs!$B:$B,Inputs!P:P)/_xlfn.XLOOKUP("Revenue (Sales)",Inputs!$B:$B,Inputs!P:P),"") -> -0.61529027 | P20: =IFERROR(_xlfn.XLOOKUP("Pre-Tax Income (EBT)",Inputs!$B:$B,Inputs!Q:Q)/_xlfn.XLOOKUP("Revenue (Sales)",Inputs!$B:$B,Inputs!Q:Q),"") -> -0.34371848 | Q20: =IFERROR(_xlfn.XLOOKUP("Pre-Tax Income (EBT)",#REF!,#REF!)/_xlfn.XLOOKUP("Revenue (Sales)",#REF!,#REF!),"") | R20: =IFERROR(_xlfn.XLOOKUP("Pre-Tax Income (EBT)",#REF!,#REF!)/_xlfn.XLOOKUP("Revenue (Sales)",#REF!,#REF!),"")
B21: Gross Profit Margin | F21: =IFERROR(_xlfn.XLOOKUP("Gross Profit",Inputs!$B:$B,Inputs!G:G)/_xlfn.XLOOKUP("Revenue (Sales)",Inputs!$B:$B,Inputs!G:G),"") | G21: =IFERROR(_xlfn.XLOOKUP("Gross Profit",Inputs!$B:$B,Inputs!H:H)/_xlfn.XLOOKUP("Revenue (Sales)",Inputs!$B:$B,Inputs!H:H),"") | H21: =IFERROR(_xlfn.XLOOKUP("Gross Profit",Inputs!$B:$B,Inputs!I:I)/_xlfn.XLOOKUP("Revenue (Sales)",Inputs!$B:$B,Inputs!I:I),"") | I21: =IFERROR(_xlfn.XLOOKUP("Gross Profit",Inputs!$B:$B,Inputs!J:J)/_xlfn.XLOOKUP("Revenue (Sales)",Inputs!$B:$B,Inputs!J:J),"") | J21: =IFERROR(_xlfn.XLOOKUP("Gross Profit",Inputs!$B:$B,Inputs!K:K)/_xlfn.XLOOKUP("Revenue (Sales)",Inputs!$B:$B,Inputs!K:K),"") | K21: =IFERROR(_xlfn.XLOOKUP("Gross Profit",Inputs!$B:$B,Inputs!L:L)/_xlfn.XLOOKUP("Revenue (Sales)",Inputs!$B:$B,Inputs!L:L),"") | L21: =IFERROR(_xlfn.XLOOKUP("Gross Profit",Inputs!$B:$B,Inputs!M:M)/_xlfn.XLOOKUP("Revenue (Sales)",Inputs!$B:$B,Inputs!M:M),"") | M21: =IFERROR(_xlfn.XLOOKUP("Gross Profit",Inputs!$B:$B,Inputs!N:N)/_xlfn.XLOOKUP("Revenue (Sales)",Inputs!$B:$B,Inputs!N:N),"") -> -0.030546624 | N21: =IFERROR(_xlfn.XLOOKUP("Gross Profit",Inputs!$B:$B,Inputs!O:O)/_xlfn.XLOOKUP("Revenue (Sales)",Inputs!$B:$B,Inputs!O:O),"") -> 0.090047393 | O21: =IFERROR(_xlfn.XLOOKUP("Gross Profit",Inputs!$B:$B,Inputs!P:P)/_xlfn.XLOOKUP("Revenue (Sales)",Inputs!$B:$B,Inputs!P:P),"") -> 0.210139 | P21: =IFERROR(_xlfn.XLOOKUP("Gross Profit",Inputs!$B:$B,Inputs!Q:Q)/_xlfn.XLOOKUP("Revenue (Sales)",Inputs!$B:$B,Inputs!Q:Q),"") -> 0.26616231 | Q21: =+_xlfn.XLOOKUP("Gross Profit Margin",#REF!,#REF!) -> #REF! | R21: =+_xlfn.XLOOKUP("Gross Profit Margin",#REF!,#REF!) -> #REF!
B22: SG&A Margin | F22: =IFERROR(+_xlfn.XLOOKUP("SG&A (Selling, General & Administrative)",Inputs!$B:$B,Inputs!G:G)/_xlfn.XLOOKUP("Revenue (Sales)",Inputs!$B:$B,Inputs!G:G),"") | G22: =IFERROR(+_xlfn.XLOOKUP("SG&A (Selling, General & Administrative)",Inputs!$B:$B,Inputs!H:H)/_xlfn.XLOOKUP("Revenue (Sales)",Inputs!$B:$B,Inputs!H:H),"") | H22: =IFERROR(+_xlfn.XLOOKUP("SG&A (Selling, General & Administrative)",Inputs!$B:$B,Inputs!I:I)/_xlfn.XLOOKUP("Revenue (Sales)",Inputs!$B:$B,Inputs!I:I),"") | I22: =IFERROR(+_xlfn.XLOOKUP("SG&A (Selling, General & Administrative)",Inputs!$B:$B,Inputs!J:J)/_xlfn.XLOOKUP("Revenue (Sales)",Inputs!$B:$B,Inputs!J:J),"") | J22: =IFERROR(+_xlfn.XLOOKUP("SG&A (Selling, General & Administrative)",Inputs!$B:$B,Inputs!K:K)/_xlfn.XLOOKUP("Revenue (Sales)",Inputs!$B:$B,Inputs!K:K),"") | K22: =IFERROR(+_xlfn.XLOOKUP("SG&A (Selling, General & Administrative)",Inputs!$B:$B,Inputs!L:L)/_xlfn.XLOOKUP("Revenue (Sales)",Inputs!$B:$B,Inputs!L:L),"") | L22: =IFERROR(+_xlfn.XLOOKUP("SG&A (Selling, General & Administrative)",Inputs!$B:$B,Inputs!M:M)/_xlfn.XLOOKUP("Revenue (Sales)",Inputs!$B:$B,Inputs!M:M),"") | M22: =IFERROR(+_xlfn.XLOOKUP("SG&A (Selling, General & Administrative)",Inputs!$B:$B,Inputs!N:N)/_xlfn.XLOOKUP("Revenue (Sales)",Inputs!$B:$B,Inputs!N:N),"") -> 0.93890675 | N22: =IFERROR(+_xlfn.XLOOKUP("SG&A (Selling, General & Administrative)",Inputs!$B:$B,Inputs!O:O)/_xlfn.XLOOKUP("Revenue (Sales)",Inputs!$B:$B,Inputs!O:O),"") -> 0.42180095 | O22: =IFERROR(+_xlfn.XLOOKUP("SG&A (Selling, General & Administrative)",Inputs!$B:$B,Inputs!P:P)/_xlfn.XLOOKUP("Revenue (Sales)",Inputs!$B:$B,Inputs!P:P),"") -> 0.45094031 | P22: =IFERROR(+_xlfn.XLOOKUP("SG&A (Selling, General & Administrative)",Inputs!$B:$B,Inputs!Q:Q)/_xlfn.XLOOKUP("Revenue (Sales)",Inputs!$B:$B,Inputs!Q:Q),"") -> 0.28381476 | Q22: =+_xlfn.XLOOKUP("SG&A Margin",#REF!,#REF!) -> #REF! | R22: =+_xlfn.XLOOKUP("SG&A Margin",#REF!,#REF!) -> #REF!
B23: Net Income Margin | F23: =IFERROR(_xlfn.XLOOKUP("Net Income",Inputs!$B:$B,Inputs!G:G)/_xlfn.XLOOKUP("Revenue (Sales)",Inputs!$B:$B,Inputs!G:G),"") | G23: =IFERROR(_xlfn.XLOOKUP("Net Income",Inputs!$B:$B,Inputs!H:H)/_xlfn.XLOOKUP("Revenue (Sales)",Inputs!$B:$B,Inputs!H:H),"") | H23: =IFERROR(_xlfn.XLOOKUP("Net Income",Inputs!$B:$B,Inputs!I:I)/_xlfn.XLOOKUP("Revenue (Sales)",Inputs!$B:$B,Inputs!I:I),"") | I23: =IFERROR(_xlfn.XLOOKUP("Net Income",Inputs!$B:$B,Inputs!J:J)/_xlfn.XLOOKUP("Revenue (Sales)",Inputs!$B:$B,Inputs!J:J),"") | J23: =IFERROR(_xlfn.XLOOKUP("Net Income",Inputs!$B:$B,Inputs!K:K)/_xlfn.XLOOKUP("Revenue (Sales)",Inputs!$B:$B,Inputs!K:K),"") | K23: =IFERROR(_xlfn.XLOOKUP("Net Income",Inputs!$B:$B,Inputs!L:L)/_xlfn.XLOOKUP("Revenue (Sales)",Inputs!$B:$B,Inputs!L:L),"") | L23: =IFERROR(_xlfn.XLOOKUP("Net Income",Inputs!$B:$B,Inputs!M:M)/_xlfn.XLOOKUP("Revenue (Sales)",Inputs!$B:$B,Inputs!M:M),"") | M23: =IFERROR(_xlfn.XLOOKUP("Net Income",Inputs!$B:$B,Inputs!N:N)/_xlfn.XLOOKUP("Revenue (Sales)",Inputs!$B:$B,Inputs!N:N),"") -> -1.7136656 | N23: =IFERROR(_xlfn.XLOOKUP("Net Income",Inputs!$B:$B,Inputs!O:O)/_xlfn.XLOOKUP("Revenue (Sales)",Inputs!$B:$B,Inputs!O:O),"") -> -0.50459716 | O23: =IFERROR(_xlfn.XLOOKUP("Net Income",Inputs!$B:$B,Inputs!P:P)/_xlfn.XLOOKUP("Revenue (Sales)",Inputs!$B:$B,Inputs!P:P),"") -> -0.63041701 | P23: =IFERROR(_xlfn.XLOOKUP("Net Income",Inputs!$B:$B,Inputs!Q:Q)/_xlfn.XLOOKUP("Revenue (Sales)",Inputs!$B:$B,Inputs!Q:Q),"") -> -0.3455525 | Q23: =+_xlfn.XLOOKUP("Net Income Margin",#REF!,#REF!) -> #REF! | R23: =+_xlfn.XLOOKUP("Net Income Margin",#REF!,#REF!) -> #REF!
B25: Liquidity | F25: 2014 | G25: =+F25+1 -> 2015 | H25: =+G25+1 -> 2016 | I25: =+H25+1 -> 2017 | J25: =+I25+1 -> 2018 | K25: =+J25+1 -> 2019 | L25: =+K25+1 -> 2020 | M25: =+L25+1 -> 2021 | N25: 2022 | O25: =+N25+1 -> 2023 | P25: =+O25+1 -> 2024 | Q25: =+P25+1 -> 2025 | R25: =+Q25+1 -> 2026
