Workbook
Name COOLFUCNTION: _xlfn.LAMBDA(_xldudf_BOARDFLARE_EXEC("workbook-settings:coolfucntion"))
Name COOLFUCNTION: _xlfn.LAMBDA(_xldudf_BOARDFLARE_EXEC("workbook-settings:coolfucntion"))
Name COOLFUCNTION: _xlfn.LAMBDA(_xldudf_BOARDFLARE_EXEC("workbook-settings:coolfucntion"))
Name COOLFUCNTION: _xlfn.LAMBDA(_xldudf_BOARDFLARE_EXEC("workbook-settings:coolfucntion"))
Name COOLFUCNTION: _xlfn.LAMBDA(_xldudf_BOARDFLARE_EXEC("workbook-settings:coolfucntion"))
Name COOLFUCNTION: _xlfn.LAMBDA(_xldudf_BOARDFLARE_EXEC("workbook-settings:coolfucntion"))
Name COOLFUCNTION: _xlfn.LAMBDA(_xldudf_BOARDFLARE_EXEC("workbook-settings:coolfucntion"))
Name COOLFUCNTION: _xlfn.LAMBDA(_xldudf_BOARDFLARE_EXEC("workbook-settings:coolfucntion"))
Name COOLFUCNTION: _xlfn.LAMBDA(_xldudf_BOARDFLARE_EXEC("workbook-settings:coolfucntion"))
Name COOLFUCNTION: _xlfn.LAMBDA(_xldudf_BOARDFLARE_EXEC("workbook-settings:coolfucntion"))
Name Sectors: #REF!
Name Sectors: #REF!
Name Sectors: #REF!

Sheet Summary
E2: | EQUITY RESEARCH | U2: Lisbon Investment Society Equity Research
U3: April 5, 2025
D6: {=+_FV(DCF!R4,"Name")} -> SK hynix Inc. | U6: Strong Buy
D8: {=_FV(U8,"Descrição")} -> SK Hynix Inc is a Korea-based company mainly engaged in the production and sale of semiconductor memories. The Company’s major products include dynamic random access memory (DRAM), NAND flashes, as well as multi-chip packages (MCP), among others. In addition, the Company manufactures and sells complementary metal oxide semiconductor image sensors (CISs). CISs is used in mobile phones, notebooks, tablets, medical devices, digital single lens reflex (DSLR) cameras, camcorders, automobiles, security equipments, game machines, and home appliances. The Company distributes its products within the domestic market and to overseas markets, including America, Germany, United Kingdom, Japan, Singapore, India, and China. | U8: #VALUE!
U9: {=+"Price (7 Mar 25): ₩"&_FV(DCF!$R$4,"Price")} -> Price (7 Mar 25): ₩184400
D10: Investment Thesis | U10: ="Price Target: ₩" & ROUND(IF(Summary!G25="FCFF",DCF!Q214,IF(Summary!G25="FCFE",DCF!Q257,IF(Summary!G25="Tax Shield",DCF!Q230,DCF!Q273))),2) &" "&IF(Summary!G25="FCFF","(FCFF)",IF(Summary!G25="FCFE","(FCFE)",IF(Summary!G25="Tax Shield","(APV)","(DDM)"))) -> Price Target: ₩257816.51 (FCFF)
D11: SK Hynix is uniquely positioned to benefit from the accelerating demand for advanced memory driven by the global AI boom. As the leading supplier of high-bandwidth memory (HBM) to NVIDIA, and with HBM4 production on track for late 2025, the company sits at the core of AI infrastructure buildout. Despite this strategic positioning, SK Hynix trades at a 72% TTM EV/EBITDA discount to the NASDAQ 100, far below the historical Korean average of 45%, reflecting an exaggerated valuation gap rather than fundamentals. With DRAM recovering, NAND bottoming, and HBM supply sold out for 2025, SK Hynix offers rare exposure to both cyclical recovery and structural growth, at a deeply mispriced entry point. | U11: =+"Upside (Downside): "&ROUND((DCF!$Q$217*100),2)&"%" -> Upside (Downside): 42.44%
U14: =+Industry!E29&", "&ESG!C9 -> South Korea, Informational Technology
U15: =+ESG!C10 -> Semiconductor Equipment
D17: Market Data | F17: 2023 | G17: =+F17+1 -> 2024 | H17: =+G17+1 -> 2025 | I17: =+H17+1 -> 2026 | K17: Valuation Multiples | N17: 2022 | O17: =+N17+1 -> 2023 | P17: =+O17+1 -> 2024 | Q17: =+P17+1 -> 2025 | R17: =+Q17+1 -> 2026 | U17: Raul Vasconcelos, Co-head of ER
D18: =+DCF!B17 -> DRAM Market | F18: =+DCF!F17 -> 79410.252 | G18: =+DCF!G17 -> 152948.38 | H18: =+DCF!H17 -> 183538.06 | I18: =+DCF!I17 -> 215069.9 | K18: EV / Sales | N18: =IFERROR(_xlfn.XLOOKUP($K18,Ratios!$B:$B,Ratios!N:N),"") -> 1.4951638 | O18: =IFERROR(_xlfn.XLOOKUP($K18,Ratios!$B:$B,Ratios!O:O),"") -> 3.5238512 | P18: =IFERROR(_xlfn.XLOOKUP($K18,Ratios!$B:$B,Ratios!P:P),"") -> 1.923657 | Q18: =IFERROR(_xlfn.XLOOKUP($K18,Ratios!$B:$B,Ratios!Q:Q),"") -> 2.7637354 | R18: =IFERROR(_xlfn.XLOOKUP($K18,Ratios!$B:$B,Ratios!R:R),"") -> 2.54297 | U18: raul.vasconcelos@aln.iseg.ulisboa.pt
D19: =+DCF!B18 -> Market growth | F19: =+DCF!F18 -> -0.36065483 | G19: =+DCF!G18 -> 0.92605338 | H19: =+DCF!H18 -> 0.2 | I19: =+DCF!I18 -> 0.1718 | K19: Price / Sales | N19: =IFERROR(_xlfn.XLOOKUP($K19,Ratios!$B:$B,Ratios!N:N),"") -> 1.1557183 | O19: =IFERROR(_xlfn.XLOOKUP($K19,Ratios!$B:$B,Ratios!O:O),"") -> 2.9715877 | P19: =IFERROR(_xlfn.XLOOKUP($K19,Ratios!$B:$B,Ratios!P:P),"") -> 1.8093292 | Q19: =IFERROR(_xlfn.XLOOKUP($K19,Ratios!$B:$B,Ratios!Q:Q),"") -> 2.5449301 | R19: =IFERROR(_xlfn.XLOOKUP($K19,Ratios!$B:$B,Ratios!R:R),"") -> 2.2047795 | U19: (+351) 960 242 437
D20: =+DCF!B19 -> SK Hynix Market Share | F20: =+DCF!F19 -> 0.26153628 | G20: =+DCF!G19 -> 0.29246248 | H20: =+DCF!H19 -> 0.30508108 | I20: =+DCF!I19 -> 0.31246248 | K20: EV / EBITDA | N20: =IFERROR(_xlfn.XLOOKUP($K20,Ratios!$B:$B,Ratios!N:N),"") -> 8.9088506 | O20: =IFERROR(_xlfn.XLOOKUP($K20,Ratios!$B:$B,Ratios!O:O),"") -> -16.163601 | P20: =IFERROR(_xlfn.XLOOKUP($K20,Ratios!$B:$B,Ratios!P:P),"") -> 5.2995642 | Q20: =IFERROR(_xlfn.XLOOKUP($K20,Ratios!$B:$B,Ratios!Q:Q),"") -> 11.452243 | R20: =IFERROR(_xlfn.XLOOKUP($K20,Ratios!$B:$B,Ratios!R:R),"") -> 9.9819784 | U20: Maria Ana Rocha, ER Analyst
D21: =+DCF!B24 -> Nand Market | F21: =+DCF!F24 -> 45721.938 | G21: =+DCF!G24 -> 71577.847 | H21: =+DCF!H24 -> 78735.632 | I21: =+DCF!I24 -> 85554.138 | K21: EV / EBIT | N21: =IFERROR(_xlfn.XLOOKUP($K21,Ratios!$B:$B,Ratios!N:N),"") -> 9.7977208 | O21: =IFERROR(_xlfn.XLOOKUP($K21,Ratios!$B:$B,Ratios!O:O),"") -> -14.936025 | P21: =IFERROR(_xlfn.XLOOKUP($K21,Ratios!$B:$B,Ratios!P:P),"") -> 5.4259368 | Q21: =IFERROR(_xlfn.XLOOKUP($K21,Ratios!$B:$B,Ratios!Q:Q),"") -> 11.868305 | R21: =IFERROR(_xlfn.XLOOKUP($K21,Ratios!$B:$B,Ratios!R:R),"") -> 10.324853 | U21: maria.ana.rocha@aln.iseg.ulisboa.pt
D22: =+DCF!B25 -> Market growth | F22: =+DCF!F25 -> -0.30124207 | G22: =+DCF!G25 -> 0.56550334 | H22: =+DCF!H25 -> 0.1 | I22: =+DCF!I25 -> 0.0866 | K22: Price / Earnings | N22: =IFERROR(_xlfn.XLOOKUP($K22,Ratios!$B:$B,Ratios!N:N),"") -> 23.004862 | O22: =IFERROR(_xlfn.XLOOKUP($K22,Ratios!$B:$B,Ratios!O:O),"") -> -10.65555 | P22: =IFERROR(_xlfn.XLOOKUP($K22,Ratios!$B:$B,Ratios!P:P),"") -> 6.0496199 | Q22: =IFERROR(_xlfn.XLOOKUP($K22,Ratios!$B:$B,Ratios!Q:Q),"") -> 16.665114 | R22: =IFERROR(_xlfn.XLOOKUP($K22,Ratios!$B:$B,Ratios!R:R),"") -> 12.147745 | U22: (+351) 935 474 506
D23: =+DCF!B26 -> SK Hynix Market Share | F23: =+DCF!F26 -> 0.21112534 | G23: =+DCF!G26 -> 0.26927479 | H23: =+DCF!H26 -> 0.26927479 | I23: =+DCF!I26 -> 0.26927479 | K23: Price / Book | N23: =IFERROR(_xlfn.XLOOKUP($K23,Ratios!$B:$B,Ratios!N:N),"") -> 0.81481423 | O23: =IFERROR(_xlfn.XLOOKUP($K23,Ratios!$B:$B,Ratios!O:O),"") -> 1.8197988 | P23: =IFERROR(_xlfn.XLOOKUP($K23,Ratios!$B:$B,Ratios!P:P),"") -> 1.6202908 | Q23: =IFERROR(_xlfn.XLOOKUP($K23,Ratios!$B:$B,Ratios!Q:Q),"") -> 2.3578344 | R23: =IFERROR(_xlfn.XLOOKUP($K23,Ratios!$B:$B,Ratios!R:R),"") -> 2.2618721 | U23: Rodrigo Ji, ER Analyst
U24: l63970@aln.iseg.ulisboa.pt
D25: Year | E25: Net Sales | F25: EBIT Margin | G25: FCFF | H25: =+IF(Summary!$G$25="FCFF",DCF!AB6,IF(Summary!$G$25="FCFE",DCF!AC6,DCF!AD6)) -> NOPAT | I25: Net Capex | K25: Profitability Ratios | N25: 2022 | O25: =+N25+1 -> 2023 | P25: =+O25+1 -> 2024 | Q25: =+P25+1 -> 2025 | R25: =+Q25+1 -> 2026 | U25: (+351) 963 757 458
D26: 2022 | E26: =+DCF!E36 -> 44621.6 | F26: =+DCF!E64 -> 0.15260322 | G26: {=TRANSPOSE(DCF!F198:M198)} -> -270.113 | H26: =+IF(Summary!$G$25="FCFF",DCF!AB7,IF(Summary!$G$25="FCFE",DCF!AC7,DCF!AD7)) -> 3813.4886 | I26: =+DCF!E138 -> -19424.2 | K26: Return on Assets | N26: =IFERROR(_xlfn.XLOOKUP($K26,Ratios!$B:$B,Ratios!N:N),"") -> 0.021581473 | O26: =IFERROR(_xlfn.XLOOKUP($K26,Ratios!$B:$B,Ratios!O:O),"") -> -0.091075269 | P26: =IFERROR(_xlfn.XLOOKUP($K26,Ratios!$B:$B,Ratios!P:P),"") -> 0.16517514 | Q26: =IFERROR(_xlfn.XLOOKUP($K26,Ratios!$B:$B,Ratios!Q:Q),"") -> 0.10158014 | R26: =IFERROR(_xlfn.XLOOKUP($K26,Ratios!$B:$B,Ratios!R:R),"") -> 0.14102809 | U26: Joao Branco, ER Analyst
D27: =+D26+1 -> 2023 | E27: =+DCF!F36 -> 32765.7 | F27: =+DCF!F64 -> -0.23592965 | G27: 10413.865 | H27: =+IF(Summary!$G$25="FCFF",DCF!AB8,IF(Summary!$G$25="FCFE",DCF!AC8,DCF!AD8)) -> -6059.179 | I27: =+DCF!F138 -> -7239.5 | K27: Return on Equity | N27: =IFERROR(_xlfn.XLOOKUP($K27,Ratios!$B:$B,Ratios!N:N),"") -> 0.035419218 | O27: =IFERROR(_xlfn.XLOOKUP($K27,Ratios!$B:$B,Ratios!O:O),"") -> -0.17078413 | P27: =IFERROR(_xlfn.XLOOKUP($K27,Ratios!$B:$B,Ratios!P:P),"") -> 0.26783349 | Q27: =IFERROR(_xlfn.XLOOKUP($K27,Ratios!$B:$B,Ratios!Q:Q),"") -> -1.0685163e-15 | R27: =IFERROR(_xlfn.XLOOKUP($K27,Ratios!$B:$B,Ratios!R:R),"") -> -1.4834672e-15 | U27: l61862@aln.iseg.ulisboa.pt
D28: =+D27+1 -> 2024 | E28: =+DCF!G36 -> 66193 | F28: =+DCF!G64 -> 0.35452994 | G28: -6051.9415 | H28: =+IF(Summary!$G$25="FCFF",DCF!AB9,IF(Summary!$G$25="FCFE",DCF!AC9,DCF!AD9)) -> 19450.565 | I28: =+DCF!G138 -> -16595.8 | K28: Return on Total Capital | N28: =IFERROR(_xlfn.XLOOKUP($K28,Ratios!$B:$B,Ratios!N:N),"") -> 0.045134155 | O28: =IFERROR(_xlfn.XLOOKUP($K28,Ratios!$B:$B,Ratios!O:O),"") -> -0.075465515 | P28: =IFERROR(_xlfn.XLOOKUP($K28,Ratios!$B:$B,Ratios!P:P),"") -> 0.20388625 | Q28: =IFERROR(_xlfn.XLOOKUP($K28,Ratios!$B:$B,Ratios!Q:Q),"") -> -1.1800366e-15 | R28: =IFERROR(_xlfn.XLOOKUP($K28,Ratios!$B:$B,Ratios!R:R),"") -> -1.5681202e-15 | U28: (+351) 924 355 215
D29: =+D28+1 -> 2025 | E29: =+DCF!H36 -> 79767.388 | F29: =+DCF!H64 -> 0.23286689 | G29: 4190.3822 | H29: =+IF(Summary!$G$25="FCFF",DCF!AB10,IF(Summary!$G$25="FCFE",DCF!AC10,DCF!AD10)) -> 13452.632 | I29: =+DCF!H138 -> -27178.341 | K29: EBITDA Margin | N29: =IFERROR(_xlfn.XLOOKUP($K29,Ratios!$B:$B,Ratios!N:N),"") -> 0.16782903 | O29: =IFERROR(_xlfn.XLOOKUP($K29,Ratios!$B:$B,Ratios!O:O),"") -> -0.21801152 | P29: =IFERROR(_xlfn.XLOOKUP($K29,Ratios!$B:$B,Ratios!P:P),"") -> 0.362984 | Q29: =IFERROR(_xlfn.XLOOKUP($K29,Ratios!$B:$B,Ratios!Q:Q),"") -> 0.241327 | R29: =IFERROR(_xlfn.XLOOKUP($K29,Ratios!$B:$B,Ratios!R:R),"") -> 0.25475611
D30: =+D29+1 -> 2026 | E30: =+DCF!I36 -> 93179.47 | F30: =+DCF!I64 -> 0.246296 | G30: 6770.2361 | H30: =+IF(Summary!$G$25="FCFF",DCF!AB11,IF(Summary!$G$25="FCFE",DCF!AC11,DCF!AD11)) -> 17876.856 | I30: =+DCF!I138 -> -31608.232 | K30: EBIT Margin | N30: =IFERROR(_xlfn.XLOOKUP($K30,Ratios!$B:$B,Ratios!N:N),"") -> 0.15260322 | O30: =IFERROR(_xlfn.XLOOKUP($K30,Ratios!$B:$B,Ratios!O:O),"") -> -0.23592965 | P30: =IFERROR(_xlfn.XLOOKUP($K30,Ratios!$B:$B,Ratios!P:P),"") -> 0.35452994 | Q30: =IFERROR(_xlfn.XLOOKUP($K30,Ratios!$B:$B,Ratios!Q:Q),"") -> 0.23286689 | R30: =IFERROR(_xlfn.XLOOKUP($K30,Ratios!$B:$B,Ratios!R:R),"") -> 0.246296 | U30: Statistics
D31: =+D30+1 -> 2027 | E31: =+DCF!J36 -> 106852.3 | F31: =+DCF!J64 -> 0.25310524 | G31: 6926.0222 | H31: =+IF(Summary!$G$25="FCFF",DCF!AB12,IF(Summary!$G$25="FCFE",DCF!AC12,DCF!AD12)) -> 21023.034 | I31: =+DCF!J138 -> -36638.734 | K31: Gross Profit Margin | N31: =IFERROR(_xlfn.XLOOKUP($K31,Ratios!$B:$B,Ratios!N:N),"") -> 0.35023173 | O31: =IFERROR(_xlfn.XLOOKUP($K31,Ratios!$B:$B,Ratios!O:O),"") -> -0.016282271 | P31: =IFERROR(_xlfn.XLOOKUP($K31,Ratios!$B:$B,Ratios!P:P),"") -> 0.48083936 | Q31: =IFERROR(_xlfn.XLOOKUP($K31,Ratios!$B:$B,Ratios!Q:Q),"") -> 0.35 | R31: =IFERROR(_xlfn.XLOOKUP($K31,Ratios!$B:$B,Ratios!R:R),"") -> 0.35 | U31: Beta | V31: =Peers!D74 -> 1.1446
D32: =+D31+1 -> 2028 | E32: =+DCF!K36 -> 120498.4 | F32: =+DCF!K64 -> 0.25913056 | G32: 10565.121 | H32: =+IF(Summary!$G$25="FCFF",DCF!AB13,IF(Summary!$G$25="FCFE",DCF!AC13,DCF!AD13)) -> 23736.295 | I32: =+DCF!K138 -> -41027.39 | K32: SG&A Margin | N32: =IFERROR(_xlfn.XLOOKUP($K32,Ratios!$B:$B,Ratios!N:N),"") -> 0.082123904 | O32: =IFERROR(_xlfn.XLOOKUP($K32,Ratios!$B:$B,Ratios!O:O),"") -> 0.087258932 | P32: =IFERROR(_xlfn.XLOOKUP($K32,Ratios!$B:$B,Ratios!P:P),"") -> 0.05083468 | Q32: =IFERROR(_xlfn.XLOOKUP($K32,Ratios!$B:$B,Ratios!Q:Q),"") -> 0.044911977 | R32: =IFERROR(_xlfn.XLOOKUP($K32,Ratios!$B:$B,Ratios!R:R),"") -> 0.039778236 | U32: % Float | V32: =+Peers!D73 -> 0.78296516
D33: =+D32+1 -> 2029 | E33: =+DCF!L36 -> 133714 | F33: =+DCF!L64 -> 0.26455899 | G33: 12992.71 | H33: =+IF(Summary!$G$25="FCFF",DCF!AB14,IF(Summary!$G$25="FCFE",DCF!AC14,DCF!AD14)) -> 27315.227 | I33: =+DCF!L138 -> -45482.143 | K33: Net Income Margin | N33: =IFERROR(_xlfn.XLOOKUP($K33,Ratios!$B:$B,Ratios!N:N),"") -> 0.050238001 | O33: =IFERROR(_xlfn.XLOOKUP($K33,Ratios!$B:$B,Ratios!O:O),"") -> -0.278877 | P33: =IFERROR(_xlfn.XLOOKUP($K33,Ratios!$B:$B,Ratios!P:P),"") -> 0.29908147 | Q33: =IFERROR(_xlfn.XLOOKUP($K33,Ratios!$B:$B,Ratios!Q:Q),"") -> 0.15271003 | R33: =IFERROR(_xlfn.XLOOKUP($K33,Ratios!$B:$B,Ratios!R:R),"") -> 0.18149702 | U33: % Held by Insiders | V33: =+Peers!D76 -> 0.2042
U34: % Held by Institutions | V34: =+Peers!D77 -> 0.439
D35: SWOT Analysis | K35: Liquidity Ratios | N35: 2022 | O35: =+N35+1 -> 2023 | P35: =+O35+1 -> 2024 | Q35: =+P35+1 -> 2025 | R35: =+Q35+1 -> 2026 | U35: Short % of Float | V35: =+Peers!D78 -> 0
D36: Strengths | G36: Weaknesses | K36: Cash Ratio | N36: =IFERROR(_xlfn.XLOOKUP($K36,Ratios!$B:$B,Ratios!N:N),"") -> 0.25081008 | O36: =IFERROR(_xlfn.XLOOKUP($K36,Ratios!$B:$B,Ratios!O:O),"") -> 0.36116585 | P36: =IFERROR(_xlfn.XLOOKUP($K36,Ratios!$B:$B,Ratios!P:P),"") -> 0.44882517 | Q36: =IFERROR(_xlfn.XLOOKUP($K36,Ratios!$B:$B,Ratios!Q:Q),"") -> -0.058287674 | R36: =IFERROR(_xlfn.XLOOKUP($K36,Ratios!$B:$B,Ratios!R:R),"") -> 0.22368549 | W36: 120.87
D37: HBM market leadership, supplying NVIDIA's Blackwell. Strong positioning in DRAM (36% market share). Vertical integration, reducing supplier dependency. | G37: Heavy exposure to China, with multiple manufacturing facilities located there. Volatile NAND margins. High dependence of geopolitical waivers. | K37: Quick Ratio | N37: =IFERROR(_xlfn.XLOOKUP($K37,Ratios!$B:$B,Ratios!N:N),"") -> 0.56771167 | O37: =IFERROR(_xlfn.XLOOKUP($K37,Ratios!$B:$B,Ratios!O:O),"") -> 0.72789155 | P37: =IFERROR(_xlfn.XLOOKUP($K37,Ratios!$B:$B,Ratios!P:P),"") -> 1.0793739 | Q37: =IFERROR(_xlfn.XLOOKUP($K37,Ratios!$B:$B,Ratios!Q:Q),"") -> 0.68400826 | R37: =IFERROR(_xlfn.XLOOKUP($K37,Ratios!$B:$B,Ratios!R:R),"") -> 1.0776456 | U37: Ownership Structure | W37: 113.63
K38: Current Ratio | N38: =IFERROR(_xlfn.XLOOKUP($K38,Ratios!$B:$B,Ratios!N:N),"") -> 1.447981 | O38: =IFERROR(_xlfn.XLOOKUP($K38,Ratios!$B:$B,Ratios!O:O),"") -> 1.4503232 | P38: =IFERROR(_xlfn.XLOOKUP($K38,Ratios!$B:$B,Ratios!P:P),"") -> 1.6934998 | Q38: =IFERROR(_xlfn.XLOOKUP($K38,Ratios!$B:$B,Ratios!Q:Q),"") -> 1.4587889 | R38: =IFERROR(_xlfn.XLOOKUP($K38,Ratios!$B:$B,Ratios!R:R),"") -> 1.4587889 | U38: Foreigner | V38: 0.539 | X38: The only foreign fund that owns more than 5% of stock is The Capital Group Companies, Inc. Totalling 6.7% of shares
U39: SK Square | V39: 0.201
D40: Opportunities | G40: Threats | K40: Cash Flow Ratios | N40: 2022 | O40: =+N40+1 -> 2023 | P40: =+O40+1 -> 2024 | Q40: =+P40+1 -> 2025 | R40: =+Q40+1 -> 2026 | U40: National Pension Service | V40: 0.074
D41: Mass production of HBM. Growing AI and HPC. Recovery in NAND pricing. Potential correction in Korean equities prices (current EV/EBITDA discount 72% vs usual 45%) | G41: Samsung's aggresive HBM4 roadmap and R&D. Micron's geopolitical advantage. U.S.-China trade tensions, disrupting Chinese production. KRW appreciation risk. Decreasing demand for conventional memory. | K41: Cash Conversion Cycle | N41: =IFERROR(_xlfn.XLOOKUP($K41,Ratios!$B:$B,Ratios!N:N),"") -> 221.74086 | O41: =IFERROR(_xlfn.XLOOKUP($K41,Ratios!$B:$B,Ratios!O:O),"") -> 200.73201 | P41: =IFERROR(_xlfn.XLOOKUP($K41,Ratios!$B:$B,Ratios!P:P),"") -> 200.64302 | Q41: =IFERROR(_xlfn.XLOOKUP($K41,Ratios!$B:$B,Ratios!Q:Q),"") -> 167.98406 | R41: =IFERROR(_xlfn.XLOOKUP($K41,Ratios!$B:$B,Ratios!R:R),"") -> 169.67067 | U41: Domestic Individual | V41: 0.073
K42: Net Income / Op Cash Flow | N42: =IFERROR(_xlfn.XLOOKUP($K42,Ratios!$B:$B,Ratios!N:N),"") -> 0.15166605 | O42: =IFERROR(_xlfn.XLOOKUP($K42,Ratios!$B:$B,Ratios!O:O),"") -> -2.1358515 | P42: =IFERROR(_xlfn.XLOOKUP($K42,Ratios!$B:$B,Ratios!P:P),"") -> 0.66442363 | Q42: =IFERROR(_xlfn.XLOOKUP($K42,Ratios!$B:$B,Ratios!Q:Q),"") -> 1.6033417 | R42: =IFERROR(_xlfn.XLOOKUP($K42,Ratios!$B:$B,Ratios!R:R),"") -> 1.0881717 | U42: Domestic Institutions | V42: 0.06
K43: Chg in Cash / Op Cash Flow | N43: =IFERROR(_xlfn.XLOOKUP($K43,Ratios!$B:$B,Ratios!N:N),"") -> -0.0054801935 | O43: =IFERROR(_xlfn.XLOOKUP($K43,Ratios!$B:$B,Ratios!O:O),"") -> 0.61013978 | P43: =IFERROR(_xlfn.XLOOKUP($K43,Ratios!$B:$B,Ratios!P:P),"") -> 0.12141939 | Q43: =IFERROR(_xlfn.XLOOKUP($K43,Ratios!$B:$B,Ratios!Q:Q),"") -> -1.6655929 | R43: =IFERROR(_xlfn.XLOOKUP($K43,Ratios!$B:$B,Ratios!R:R),"") -> 0.45107214 | U43: Others | V43: 0.027
U44: Treasury Stock | V44: 0.026
D45: Revenue by Region | G45: Revenue by Segment | K45: Leverage Ratios | N45: 2022 | O45: =+N45+1 -> 2023 | P45: =+O45+1 -> 2024 | Q45: =+P45+1 -> 2025 | R45: =+Q45+1 -> 2026
K46: Total Debt / Equity | N46: =IFERROR(_xlfn.XLOOKUP($K46,Ratios!$B:$B,Ratios!N:N),"") -> 0.33499182 | O46: =IFERROR(_xlfn.XLOOKUP($K46,Ratios!$B:$B,Ratios!O:O),"") -> 0.50065416 | P46: =IFERROR(_xlfn.XLOOKUP($K46,Ratios!$B:$B,Ratios!P:P),"") -> 0.29064732 | Q46: =IFERROR(_xlfn.XLOOKUP($K46,Ratios!$B:$B,Ratios!Q:Q),"") -> -1.8844787e-15 | R46: =IFERROR(_xlfn.XLOOKUP($K46,Ratios!$B:$B,Ratios!R:R),"") -> -2.0487953e-15 | U46: ESG Traffic Light
K47: Total Debt / Capital | N47: =IFERROR(_xlfn.XLOOKUP($K47,Ratios!$B:$B,Ratios!N:N),"") -> 0.25093174 | O47: =IFERROR(_xlfn.XLOOKUP($K47,Ratios!$B:$B,Ratios!O:O),"") -> 0.33362394 | P47: =IFERROR(_xlfn.XLOOKUP($K47,Ratios!$B:$B,Ratios!P:P),"") -> 0.225195 | Q47: =IFERROR(_xlfn.XLOOKUP($K47,Ratios!$B:$B,Ratios!Q:Q),"") -> -1.8844787e-15 | R47: =IFERROR(_xlfn.XLOOKUP($K47,Ratios!$B:$B,Ratios!R:R),"") -> -2.0487953e-15 | U47: LSEG ESG Score | V47: =ESG!C14 -> 70
K48: Total Liabilities / Total Assets | N48: =IFERROR(_xlfn.XLOOKUP($K48,Ratios!$B:$B,Ratios!N:N),"") -> 0.39068464 | O48: =IFERROR(_xlfn.XLOOKUP($K48,Ratios!$B:$B,Ratios!O:O),"") -> 0.46672288 | P48: =IFERROR(_xlfn.XLOOKUP($K48,Ratios!$B:$B,Ratios!P:P),"") -> 0.38329167 | Q48: =IFERROR(_xlfn.XLOOKUP($K48,Ratios!$B:$B,Ratios!Q:Q),"") -> 9.5066535e+13 | R48: =IFERROR(_xlfn.XLOOKUP($K48,Ratios!$B:$B,Ratios!R:R),"") -> 9.5066535e+13 | U48: E-Score | V48: =ESG!C15 -> 57
K49: Total Debt / EBITDA | N49: =IFERROR(_xlfn.XLOOKUP($K49,Ratios!$B:$B,Ratios!N:N),"") -> 2.8311345 | O49: =IFERROR(_xlfn.XLOOKUP($K49,Ratios!$B:$B,Ratios!O:O),"") -> -3.7499335 | P49: =IFERROR(_xlfn.XLOOKUP($K49,Ratios!$B:$B,Ratios!P:P),"") -> 0.89413576 | Q49: =IFERROR(_xlfn.XLOOKUP($K49,Ratios!$B:$B,Ratios!Q:Q),"") -> 1.1160194 | R49: =IFERROR(_xlfn.XLOOKUP($K49,Ratios!$B:$B,Ratios!R:R),"") -> 0.98393296 | U49: S-Score | V49: =ESG!C16 -> 66
K50: Total Debt / (EBITDA - Capex) | N50: =IFERROR(_xlfn.XLOOKUP($K50,Ratios!$B:$B,Ratios!N:N),"") -> -1.7763795 | O50: =IFERROR(_xlfn.XLOOKUP($K50,Ratios!$B:$B,Ratios!O:O),"") -> -1.862426 | P50: =IFERROR(_xlfn.XLOOKUP($K50,Ratios!$B:$B,Ratios!P:P),"") -> 2.8909732 | Q50: =IFERROR(_xlfn.XLOOKUP($K50,Ratios!$B:$B,Ratios!Q:Q),"") -> -2.7097053 | R50: =IFERROR(_xlfn.XLOOKUP($K50,Ratios!$B:$B,Ratios!R:R),"") -> -2.9677342 | U50: G-Score | V50: =ESG!C17 -> 94
K51: Net Debt / EBITDA | N51: =IFERROR(_xlfn.XLOOKUP($K50,Ratios!$B:$B,Ratios!N:N),"") -> -1.7763795 | O51: =IFERROR(_xlfn.XLOOKUP($K50,Ratios!$B:$B,Ratios!O:O),"") -> -1.862426 | P51: =IFERROR(_xlfn.XLOOKUP($K50,Ratios!$B:$B,Ratios!P:P),"") -> 2.8909732 | Q51: =IFERROR(_xlfn.XLOOKUP($K50,Ratios!$B:$B,Ratios!Q:Q),"") -> -2.7097053 | R51: =IFERROR(_xlfn.XLOOKUP($K50,Ratios!$B:$B,Ratios!R:R),"") -> -2.9677342 | U51: S&P Global ESG Score | V51: =ESG!C18 -> 56
U52: Environmental | V52: =ESG!C19 -> 53
K53: Solvency Ratios | N53: 2022 | O53: =+N53+1 -> 2023 | P53: =+O53+1 -> 2024 | Q53: =+P53+1 -> 2025 | R53: =+Q53+1 -> 2026 | U53: Social | V53: =ESG!C20 -> 60
K54: EBIT / Interest Expense | N54: =IFERROR(_xlfn.XLOOKUP($K54,Ratios!$B:$B,Ratios!N:N),"") -> 12.773213 | O54: =IFERROR(_xlfn.XLOOKUP($K54,Ratios!$B:$B,Ratios!O:O),"") -> -5.2648641 | P54: =IFERROR(_xlfn.XLOOKUP($K54,Ratios!$B:$B,Ratios!P:P),"") -> 17.445287 | Q54: =IFERROR(_xlfn.XLOOKUP($K54,Ratios!$B:$B,Ratios!Q:Q),"") -> N/A | R54: =IFERROR(_xlfn.XLOOKUP($K54,Ratios!$B:$B,Ratios!R:R),"") -> N/A | U54: Governance & Economic | V54: =ESG!C21 -> 56
K55: EBITDA / Interest Expense | N55: =IFERROR(_xlfn.XLOOKUP($K55,Ratios!$B:$B,Ratios!N:N),"") -> 14.047646 | O55: =IFERROR(_xlfn.XLOOKUP($K55,Ratios!$B:$B,Ratios!O:O),"") -> -4.865014 | P55: =IFERROR(_xlfn.XLOOKUP($K55,Ratios!$B:$B,Ratios!P:P),"") -> 17.861285 | Q55: =IFERROR(_xlfn.XLOOKUP($K55,Ratios!$B:$B,Ratios!Q:Q),"") -> N/A | R55: =IFERROR(_xlfn.XLOOKUP($K55,Ratios!$B:$B,Ratios!R:R),"") -> N/A | U55: Sustainalytics | V55: =ESG!C22 -> 17.3
K56: (EBITDA - Capex) / Interest Expense | N56: =IFERROR(_xlfn.XLOOKUP($K56,Ratios!$B:$B,Ratios!N:N),"") -> 50.483962 | O56: =IFERROR(_xlfn.XLOOKUP($K56,Ratios!$B:$B,Ratios!O:O),"") -> 0.065517946 | P56: =IFERROR(_xlfn.XLOOKUP($K56,Ratios!$B:$B,Ratios!P:P),"") -> 30.198335 | Q56: =IFERROR(_xlfn.XLOOKUP($K56,Ratios!$B:$B,Ratios!Q:Q),"") -> N/A | R56: =IFERROR(_xlfn.XLOOKUP($K56,Ratios!$B:$B,Ratios!R:R),"") -> N/A | U56: ISS ESG Corporate Rating | V56: =ESG!C23 -> C+
U57: SDG Impact Rating | V57: =ESG!C24 -> 3.7
D58: Debt Schedule | K58: Stock Performance | U58: Governance Quality Score | V58: =ESG!C25 -> 1
U59: MSCI ESG Ratings | V59: =ESG!C26 -> A
D80: Extra Notes

Sheet Segments
B2: Segments
B4: Regions | D4: Weight | E4: 2020 | F4: =+E4+1 -> 2021 | G4: =+F4+1 -> 2022 | H4: =+G4+1 -> 2023 | I4: =+H4+1 -> 2024 | J4: ="CAGR "&$G$4&" - "&$I$4 -> CAGR 2022 - 2024 | K4: 2021 | L4: =+K4+1 -> 2022 | M4: =+L4+1 -> 2023 | N4: =+M4+1 -> 2024
B6: South Korea | D6: =IFERROR(I6/SUM($I$6:$I$12),"") -> 0.028766054 | E6: =SEG!I19 -> 1452.01 | F6: =SEG!J19 -> 1461.98 | G6: =SEG!K19 -> 1225.77 | H6: =SEG!L19 -> 2033.86 | I6: =SEG!M19 -> 1904.11 | J6: =IFERROR((I6/G6)^(1/COUNT($G$4:$I$4))-1,"") -> 0.15813988 | K6: =IFERROR((F6-E6)/E6,"") -> 0.0068663439 | L6: =IFERROR((G6-F6)/F6,"") -> -0.16156856 | M6: =IFERROR((H6-G6)/G6,"") -> 0.65925092 | N6: =IFERROR((I6-H6)/H6,"") -> -0.063794951
B7: China | D7: =IFERROR(I7/SUM($I$6:$I$12),"") -> 0.23467091 | E7: =SEG!I21 -> 12217.63 | F7: =SEG!J21 -> 15730.22 | G7: =SEG!K21 -> 12210.47 | H7: =SEG!L21 -> 10110.08 | I7: =SEG!M21 -> 15533.56 | J7: =IFERROR((I7/G7)^(1/COUNT($G$4:$I$4))-1,"") -> 0.083543138 | K7: =IFERROR((F7-E7)/E7,"") -> 0.28750175 | L7: =IFERROR((G7-F7)/F7,"") -> -0.2237572 | M7: =IFERROR((H7-G7)/G7,"") -> -0.17201549 | N7: =IFERROR((I7-H7)/H7,"") -> 0.53644284
B8: Asia (without China) | D8: =IFERROR(I8/SUM($I$6:$I$12),"") -> 0.081299292 | E8: =SEG!I23 | F8: =SEG!J23 -> 7022.93 | G8: =SEG!K23 -> 5615.38 | H8: =SEG!L23 -> 4296.94 | I8: =SEG!M23 -> 5381.44 | J8: =IFERROR((I8/E8)^(1/COUNT($E$4:$I$4))-1,"") | K8: =IFERROR((F8-E8)/E8,"") | L8: =IFERROR((G8-F8)/F8,"") -> -0.20042205 | M8: =IFERROR((H8-G8)/G8,"") -> -0.23479088 | N8: =IFERROR((I8-H8)/H8,"") -> 0.25238891
B9: United States | D9: =IFERROR(I9/SUM($I$6:$I$12),"") -> 0.63392053 | E9: =SEG!I25 -> 12686.11 | F9: =SEG!J25 -> 17144.32 | G9: =SEG!K25 -> 23960.98 | H9: =SEG!L25 -> 15390.23 | I9: =SEG!M25 -> 41961.07 | J9: =IFERROR((I9/E9)^(1/COUNT($E$4:$I$4))-1,"") -> 0.27029216 | K9: =IFERROR((F9-E9)/E9,"") -> 0.35142451 | L9: =IFERROR((G9-F9)/F9,"") -> 0.39760457 | M9: =IFERROR((H9-G9)/G9,"") -> -0.35769614 | N9: =IFERROR((I9-H9)/H9,"") -> 1.7264745
B10: Europe | D10: =IFERROR(I10/SUM($I$6:$I$12),"") -> 0.02134321 | E10: =SEG!I27 -> 1222.7 | F10: =SEG!J27 -> 1638.34 | G10: =SEG!K27 -> 1608.97 | H10: =SEG!L27 -> 934.61 | I10: =SEG!M27 -> 1412.77 | J10: =IFERROR((I10/E10)^(1/COUNT($E$4:$I$4))-1,"") -> 0.029319761 | K10: =IFERROR((F10-E10)/E10,"") -> 0.33993621 | L10: =IFERROR((G10-F10)/F10,"") -> -0.017926682 | M10: =IFERROR((H10-G10)/G10,"") -> -0.41912528 | N10: =IFERROR((I10-H10)/H10,"") -> 0.51161447
D11: =IFERROR(I11/SUM($I$6:$I$12),"") -> 0
D12: =IFERROR(I12/SUM($I$6:$I$12),"") -> 0
B13: Total | D13: =SUM(D6:D12) -> 1 | E13: =SUM(E6:E10) -> 27578.45 | F13: =SUM(F6:F10) -> 42997.79 | G13: =SUM(G6:G10) -> 44621.57 | H13: =SUM(H6:H10) -> 32765.72 | I13: =SUM(I6:I10) -> 66192.95 | J13: =IFERROR((I13/G13)^(1/COUNT($G$4:$I$4))-1,"") -> 0.14048339 | K13: =IFERROR((F13-E13)/E13,"") -> 0.55910829 | L13: =IFERROR((G13-F13)/F13,"") -> 0.037764266 | M13: =IFERROR((H13-G13)/G13,"") -> -0.26569773 | N13: =IFERROR((I13-H13)/H13,"") -> 1.0201891
B15: Segments | D15: Weight | E15: 2020 | F15: =+E15+1 -> 2021 | G15: =+F15+1 -> 2022 | H15: =+G15+1 -> 2023 | I15: =+H15+1 -> 2024 | J15: ="CAGR "&$E$4&" - "&$I$4 -> CAGR 2020 - 2024 | K15: 2021 | L15: =+K15+1 -> 2022 | M15: =+L15+1 -> 2023 | N15: =+M15+1 -> 2024
B17: DRAM | D17: =IFERROR(I17/SUM($I$17:$I$21),"") -> 0.6757768 | E17: =+SEG!I6 -> 22536.4 | F17: =+SEG!J6 -> 30599.71 | G17: =+SEG!K6 -> 28168.8 | H17: =+SEG!L6 -> 20768.66 | I17: =+SEG!M6 -> 44731.66 | J17: =IFERROR((I17/E17)^(1/COUNT($E$4:$I$4))-1,"") -> 0.14695425 | K17: =IFERROR((F17-E17)/E17,"") -> 0.35779051 | L17: =IFERROR((G17-F17)/F17,"") -> -0.079442256 | M17: =IFERROR((H17-G17)/G17,"") -> -0.26270697 | N17: =IFERROR((I17-H17)/H17,"") -> 1.1538058
B18: Nand | D18: =IFERROR(I18/SUM($I$17:$I$21),"") -> 0.29118071 | E18: =+SEG!I8 -> 7471.24 | F18: =+SEG!J8 -> 10529.45 | G18: =+SEG!K8 -> 14183.92 | H18: =+SEG!L8 -> 9653.06 | I18: =+SEG!M8 -> 19274.11 | J18: =IFERROR((I18/E18)^(1/COUNT($E$4:$I$4))-1,"") -> 0.2086939 | K18: =IFERROR((F18-E18)/E18,"") -> 0.40933098 | L18: =IFERROR((G18-F18)/F18,"") -> 0.34707131 | M18: =IFERROR((H18-G18)/G18,"") -> -0.31943638 | N18: =IFERROR((I18-H18)/H18,"") -> 0.99668395
B19: Other | D19: =IFERROR(I19/SUM($I$17:$I$21),"") -> 0.033042492 | E19: =+SEG!I10 -> 1892.77 | F19: =+SEG!J10 -> 1868.63 | G19: =+SEG!K10 -> 2268.84 | H19: =+SEG!L10 -> 2344 | I19: =+SEG!M10 -> 2187.18 | J19: =IFERROR((I19/E19)^(1/COUNT($E$4:$I$4))-1,"") -> 0.029336413 | K19: =IFERROR((F19-E19)/E19,"") -> -0.012753795 | L19: =IFERROR((G19-F19)/F19,"") -> 0.21417295 | M19: =IFERROR((H19-G19)/G19,"") -> 0.033127061 | N19: =IFERROR((I19-H19)/H19,"") -> -0.06690273
D20: =IFERROR(I20/SUM($I$17:$I$21),"") -> 0 | J20: =IFERROR((I20/E20)^(1/COUNT($E$4:$I$4))-1,"") | K20: =IFERROR((F20-E20)/E20,"") | L20: =IFERROR((G20-F20)/F20,"") | M20: =IFERROR((H20-G20)/G20,"") | N20: =IFERROR((I20-H20)/H20,"")
D21: =IFERROR(I21/SUM($I$17:$I$21),"") -> 0 | J21: =IFERROR((I21/E21)^(1/COUNT($E$4:$I$4))-1,"") | K21: =IFERROR((F21-E21)/E21,"") | L21: =IFERROR((G21-F21)/F21,"") | M21: =IFERROR((H21-G21)/G21,"") | N21: =IFERROR((I21-H21)/H21,"")
B22: Total | D22: =SUM(D17:D21) -> 1 | E22: =SUM(E17:E21) -> 31900.41 | F22: =SUM(F17:F21) -> 42997.79 | G22: =SUM(G17:G21) -> 44621.56 | H22: =SUM(H17:H21) -> 32765.72 | I22: =SUM(I17:I21) -> 66192.95 | J22: =IFERROR((I22/E22)^(1/COUNT($E$4:$I$4))-1,"") -> 0.1571858 | K22: =IFERROR((F22-E22)/E22,"") -> 0.34787578 | L22: =IFERROR((G22-F22)/F22,"") -> 0.037764034 | M22: =IFERROR((H22-G22)/G22,"") -> -0.26569757 | N22: =IFERROR((I22-H22)/H22,"") -> 1.0201891
B24: Categories | D24: Description | J24: Graphs
B26: DRAM (Dynamic Random-Access Memory) | D26: High-speed, volatile memory used for temporary data storage in computers and devices. Unlike permanent storage, DRAM loses data when powered off. It stores bits in tiny capacitors that require constant refreshing, enabling cost-effective, dense memory for system RAM. This makes DRAM essential for multitasking and performance in PCs, smartphones, and servers.
B27: Nand | D27: Non-volatile storage technology that retains data even when powered off. Unlike DRAM, it doesn't require constant refreshing, making it ideal for long-term data storage in devices like SSDs, USB drives, and smartphones. NAND stores data in memory cells organized in blocks, enabling high density and cost efficiency. While slower than DRAM, its persistence and endurance make it the backbone of modern storage solutions.
B29: =IF(B20=0,"",B20)
B30: =IF(B21=0,"",B21)
B32: Products | D32: Weight | E32: 2020 | F32: =+E32+1 -> 2021 | G32: =+F32+1 -> 2022 | H32: =+G32+1 -> 2023 | I32: =+H32+1 -> 2024 | J32: =I32+1 -> 2025 | K32: =+J32+1 -> 2026 | L32: =+K32+1 -> 2027 | M32: =+L32+1 -> 2028 | N32: =+M32+1 -> 2029 | O32: =+N32+1 -> 2030 | P32: =+O32+1 -> 2031 | Q32: =+P32+1 -> 2032 | R32: =+Q32+1 -> 2033 | S32: =+R32+1 -> 2034 | T32: CAGR
B34: DRAM | D34: =IFERROR(I34/$I$13,"") -> 0.6757768 | E34: =+E17 -> 22536.4 | F34: =+F17 -> 30599.71 | G34: =+G17 -> 28168.8 | H34: =+H17 -> 20768.66 | I34: =+I17 -> 44731.66 | J34: =+I34*(1+J35) -> 49459.796 | K34: =+J34*(1+K35) -> 54687.697 | L34: =+K34*(1+L35) -> 60468.187 | M34: =+L34*(1+M35) -> 66859.674 | N34: =+M34*(1+N35) -> 73926.741 | O34: =+N34*(1+O35) -> 81740.798 | P34: =+O34*(1+P35) -> 90380.8 | Q34: =+P34*(1+Q35) -> 99934.051 | ... S34: =+R34*(1+S35) -> 122176.62 | T34: Stellar
B35: % growth | F35: =+F34/E34-1 -> 0.35779051 | G35: =+G34/F34-1 -> -0.079442256 | H35: =+H34/G34-1 -> -0.26270697 | I35: =+I34/H34-1 -> 1.1538058 | J35: =+$T$35 -> 0.1057 | K35: =+$T$35 -> 0.1057 | L35: =+$T$35 -> 0.1057 | M35: =+$T$35 -> 0.1057 | N35: =+$T$35 -> 0.1057 | O35: =+$T$35 -> 0.1057 | P35: =+$T$35 -> 0.1057 | Q35: =+$T$35 -> 0.1057 | ... S35: =+$T$35 -> 0.1057 | T35: 0.1057
B36: Nand | D36: =IFERROR(I36/$I$13,"") -> 0.29118071 | E36: =+E18 -> 7471.24 | F36: =+F18 -> 10529.45 | G36: =+G18 -> 14183.92 | H36: =+H18 -> 9653.06 | I36: =+I18 -> 19274.11 | J36: =+I36*(1+J37) -> 20353.46 | K36: =+J36*(1+K37) -> 21493.254 | L36: =+K36*(1+L37) -> 22696.876 | M36: =+L36*(1+M37) -> 23967.901 | N36: =+M36*(1+N37) -> 25310.104 | O36: =+N36*(1+O37) -> 26727.469 | P36: =+O36*(1+P37) -> 28224.208 | Q36: =+P36*(1+Q37) -> 29804.763 | ... S36: =+R36*(1+S37) -> 33236.365 | T36: GMI
B37: % growth | F37: =+F36/E36-1 -> 0.40933098 | G37: =+G36/F36-1 -> 0.34707131 | H37: =+H36/G36-1 -> -0.31943638 | I37: =+I36/H36-1 -> 0.99668395 | J37: =+$T$37 -> 0.056 | K37: =+$T$37 -> 0.056 | L37: =+$T$37 -> 0.056 | M37: =+$T$37 -> 0.056 | N37: =+$T$37 -> 0.056 | O37: =+$T$37 -> 0.056 | P37: =+$T$37 -> 0.056 | Q37: =+$T$37 -> 0.056 | ... S37: =+$T$37 -> 0.056 | T37: 0.056
B38: Other | D38: =IFERROR(I38/$I$13,"") -> 0.033042492 | E38: =+E19 -> 1892.77 | F38: =+F19 -> 1868.63 | G38: =+G19 -> 2268.84 | H38: =+H19 -> 2344 | I38: =+I19 -> 2187.18 | J38: =+I38*(1+J46) -> 2364.0135 | K38: =+J38*(1+K46) -> 2555.144 | L38: =+K38*(1+L46) -> 2761.7274 | M38: =+L38*(1+M46) -> 2985.013 | N38: =+M38*(1+N46) -> 3226.3514 | O38: =+N38*(1+O46) -> 3487.2019 | P38: =+O38*(1+P46) -> 3769.1421 | Q38: =+P38*(1+Q46) -> 4073.8773 | ... S38: =+R38*(1+S46) -> 4759.253
F39: =IFERROR((F38-E38)/E38,"") -> -0.012753795 | G39: =IFERROR((G38-F38)/F38,"") -> 0.21417295 | H39: =IFERROR((H38-G38)/G38,"") -> 0.033127061 | I39: =IFERROR((I38-H38)/H38,"") -> -0.06690273
B40: Product 3 | D40: =IFERROR(I40/$I$13,"") -> 0 | J40: =I40*(1+J41) -> 0 | K40: =J40*(1+K41) -> 0 | L40: =K40*(1+L41) -> 0 | M40: =L40*(1+M41) -> 0 | N40: =M40*(1+N41) -> 0 | O40: =N40*(1+O41) -> 0 | P40: =O40*(1+P41) -> 0 | Q40: =P40*(1+Q41) -> 0 | ... S40: =R40*(1+S41) -> 0
F41: =IFERROR(F40-E40/E40,"") | G41: =IFERROR(G40-F40/F40,"") | H41: =IFERROR(H40-G40/G40,"") | I41: =IFERROR(I40-H40/H40,"")
B42: Product 4 | D42: =IFERROR(I42/$I$13,"") -> 0 | J42: =I42*(1+J43) -> 0 | K42: =J42*(1+K43) -> 0 | L42: =K42*(1+L43) -> 0 | M42: =L42*(1+M43) -> 0 | N42: =M42*(1+N43) -> 0 | O42: =N42*(1+O43) -> 0 | P42: =O42*(1+P43) -> 0 | Q42: =P42*(1+Q43) -> 0 | ... S42: =R42*(1+S43) -> 0
F43: =IFERROR(F42-E42/E42,"") | G43: =IFERROR(G42-F42/F42,"") | H43: =IFERROR(H42-G42/G42,"") | I43: =IFERROR(I42-H42/H42,"")
B44: Product 5 | D44: =IFERROR(I44/$I$13,"") -> 0 | J44: =I44*(1+J45) -> 0 | K44: =J44*(1+K45) -> 0 | L44: =K44*(1+L45) -> 0 | M44: =L44*(1+M45) -> 0 | N44: =M44*(1+N45) -> 0 | O44: =N44*(1+O45) -> 0 | P44: =O44*(1+P45) -> 0 | Q44: =P44*(1+Q45) -> 0 | ... S44: =R44*(1+S45) -> 0
F45: =IFERROR(F44-E44/E44,"") | G45: =IFERROR(G44-F44/F44,"") | H45: =IFERROR(H44-G44/G44,"") | I45: =IFERROR(I44-H44/H44,"")
B46: % growth | F46: =+F38/E38-1 -> -0.012753795 | G46: =+G38/F38-1 -> 0.21417295 | H46: =+H38/G38-1 -> 0.033127061 | I46: =+I38/H38-1 -> -0.06690273 | J46: =+AVERAGE(J37,J35) -> 0.08085 | K46: =+J46 -> 0.08085 | L46: =+K46 -> 0.08085 | M46: =+L46 -> 0.08085 | N46: =+M46 -> 0.08085 | O46: =+N46 -> 0.08085 | P46: =+O46 -> 0.08085 | Q46: =+P46 -> 0.08085 | R46: =+Q46 -> 0.08085 | S46: =+R46 -> 0.08085
B47: Total | D47: =SUM(D34:D44) -> 1 | E47: =SUM(E34:E44) -> 31900.41 | F47: =SUM(F34:F44) -> 42998.544 | G47: =SUM(G34:G44) -> 44622.042 | H47: =SUM(H34:H44) -> 32765.171 | I47: =SUM(I34:I44) -> 66195.034 | J47: =SUM(J34:J44) -> 72177.432 | K47: =SUM(K34:K44) -> 78736.257 | ... S47: =SUM(S34:S44) -> 160172.4
B49: Company's Strategy / Extra Notes

Sheet Industry
B2: Industry Overview
E3: 584.17 | F3: 627.76 | G3: 676.06 | H3: 729.63 | I3: 789.13 | J3: 855.3 | K3: 929 | L3: 997.69 | M3: 1067.63 | N3: 1137.57 | O3: 1207.51
B4: Sales Growth Forecast | E4: Weight | F4: 2025 | G4: =+F4+1 -> 2026 | H4: =+G4+1 -> 2027 | I4: =+H4+1 -> 2028 | J4: =+I4+1 -> 2029 | K4: =+J4+1 -> 2030 | L4: =+K4+1 -> 2031 | M4: =+L4+1 -> 2032 | N4: =+M4+1 -> 2033 | ... P4: =+O4+1 -> 2035 | Q4: ="CAGR "&$F$4&" - "&$P$4 -> CAGR 2025 - 2035 | R4: Sources
B6: Semiconductor Market | E6: 1 | F6: =(F3-E3)/E3 -> 0.07461869 | G6: =(G3-F3)/F3 -> 0.076940232 | H6: =(H3-G3)/G3 -> 0.079238529 | I6: =(I3-H3)/H3 -> 0.081548182 | J6: =(J3-I3)/I3 -> 0.083851837 | K6: =(K3-J3)/J3 -> 0.086168596 | L6: =(L3-K3)/K3 -> 0.07393972 | M6: =(M3-L3)/L3 -> 0.070101935 | ... O6: =(O3-N3)/N3 -> 0.061481931 | Q6: 6,8% | R6: Precendence Research
B11: Weighted Average | E11: =SUM(E6:E10) -> 1 | F11: =SUMPRODUCT(F6:F10,$E$6:$E$10) -> 0.07461869 | G11: =SUMPRODUCT(G6:G10,$E$6:$E$10) -> 0.076940232 | H11: =SUMPRODUCT(H6:H10,$E$6:$E$10) -> 0.079238529 | I11: =SUMPRODUCT(I6:I10,$E$6:$E$10) -> 0.081548182 | J11: =SUMPRODUCT(J6:J10,$E$6:$E$10) -> 0.083851837 | K11: =SUMPRODUCT(K6:K10,$E$6:$E$10) -> 0.086168596 | L11: =SUMPRODUCT(L6:L10,$E$6:$E$10) -> 0.07393972 | M11: =SUMPRODUCT(M6:M10,$E$6:$E$10) -> 0.070101935 | ... P11: =SUMPRODUCT(P6:P10,$E$6:$E$10) -> 0 | Q11: =IFERROR(((1+F11)*(1+G11)*(1+H11)*(1+I11)*(1+J11)*(1+K11)*(1+L11)*(1+M11)*(1+N11)*(1+O11)*(1+P11))^(1/COUNT($F$4:$P$4))-1,"") -> 0.068238723
B13: Key Drivers | E13: Description
B15: AI/HPC boom | E15: Explosive demand for AI accelarators (Nvidia Blackwell/Feynman GPUs, AMD MI400) is driving 8x growth in High-Bandwidth Memory (HBM) through 2030. SK Hynix's HBM3E/HBM4 products command 70% market shre due to (1) TSMC Logic Die Partnership that enables 16-layer stacking (HBM4) with 30% better power efficiency vs competitors; (2) MR-MUF packaging that achieves 85% yield rates vs industry average of 65% (thermal compression).
B16: Supply constraints | E16: HBM production requires 3x more wafers than standard DRAM, creating shortages (1) capacity lag, since only SK Hynix/Samsung can mass-produce 12Hi+ stacks until 2026; (2) geopolitical risks, since US export controls limit China's CXMT to legacy nodes (<18nm).
B17: Automotive/edge AI demand | E17: Next-gen vehicles and IoT devices will consume 22% of DRAM by 2030, fueled by (1) LPDDR6 adoption - 30% power savings for autonomous driving systems (2027 rollout); (2) MRAM Pilots - SK Hynix's embedded memory for Tesla Dojo 2.0 (sampling 2026)
B18: Geopolitical reshoring | E18: US/EU subsidies ($53B CHIPS Act) are accelerating kicak production (1) SK Hynix Indiana Fab, $3.9B facility exempt form US-China trade tariffs; (2) Samsung Taylor, TX, $17B fab ensures HBM supply for Nvidia/AWS.
B20: Industry Trends | E20: Description
B22: AI is changing memory chip designs | E22: The need for faster data processing in AI systems is pushing memory chip makers to develop new solutions. High-Bandwidth Memory (HBM) is now essential for AI chips, with companies like SK Hynix leading in advanced 3D-stacked designs. Their latest HBM3E technology is already used in top AI processors, and even more advanced versions are coming soon. This shift is making HBM a major revenue driver, expected to grow much faster than traditional memory chips.
B23: Global politics affects where chips are made | E23: Trade tensions and new laws are forcing chip companies to spread their factories across different countries. While many still operate in China, new plants are being built in the U.S. and South Korea to reduce risks. Governments are offering incentives to attract these factories, as having local chip production is now seen as vital for economic and national security.
B24: New types of memory for future tech | E24: Beyond standard memory chips, new varieties are being developed for specific uses. Cars, smart devices, and AI systems at the "edge" (like phones and sensors) need specialized memory that’s faster, more efficient, or more durable. Companies investing in these new memory types now could gain an advantage as demand grows in the coming years.
B25: Chip makers focus on sustainability | E25: The industry is working to reduce its environmental impact by cutting water and energy use in manufacturing. New factories are being designed to run on cleaner energy and recycle more resources. These efforts aren’t just about being eco-friendly—they’re becoming important for winning business from big tech companies with strict sustainability goals.
B26: HBM is becoming a high-profit oligopoly | E26: The market for HBM is controlled by just a few companies, allowing them to charge premium prices while other memory chips face price drops. This divide is pushing chip makers to focus more on high-end HBM development, where profits remain strong despite broader industry challenges.
B27: Market Share - Memory | E27: Headquarters | G27: Revenues | H27: (in Billions of KRW) | I27: Market Share
B29: {=+_FV(DCF!R4,"Name")} -> SK hynix Inc. | E29: South Korea | G29: =+Peers!D99 -> 66193 | I29: =IFERROR(G29/$G$41,"") -> 0.28516593
B30: {=+_FV(Peers!A8,"Name")} -> Samsung Electronics Co., Ltd. | E30: South Korea | G30: 84500 | I30: =IFERROR(G30/$G$41,"") -> 0.36403428
B31: {=+_FV(Peers!A9,"Name")} -> MICRON TECHNOLOGY, INC. | E31: United States | G31: 33767 | I31: =IFERROR(G31/$G$41,"") -> 0.14547154
B32: {=+_FV(Peers!A10,"Name")} -> Kioxia Holdings Corporation | E32: Japan | G32: 9842 | I32: =IFERROR(G32/$G$41,"") -> 0.0424003
B33: {=+_FV(Peers!A11,"Name")} -> WESTERN DIGITAL CORPORATION | E33: United States | G33: =+Peers!H99 -> 17344.6 | I33: =IFERROR(G33/$G$41,"") -> 0.074722235
I34: =IFERROR(G34/$G$41,"") -> 0
I35: =IFERROR(G35/$G$41,"") -> 0
I36: =IFERROR(G36/$G$41,"") -> 0
I37: =IFERROR(G37/$G$41,"") -> 0
I38: =IFERROR(G38/$G$41,"") -> 0
I39: =IFERROR(G39/$G$41,"") -> 0
B40: Others | E40: -- | G40: =+G41-SUM(G29:G39) -> 20474.4 | I40: =IFERROR(G40/$G$41,"") -> 0.08820572
B41: Industry Size | E41: -- | G41: 232121 | H41: Statista | I41: 1
B43: Porter's Five Forces Analysis | E43: Rating | H43: Graph
B45: Threat of New Entrants | E45: =IFERROR(AVERAGE(E46:E51),"") -> 1.5
B46: Economies of scale | E46: 1
B47: Product differentiation | E47: 2
B48: Capital requirements | E48: 1
B49: Access to distribution channels | E49: 2
B50: Regulations | E50: 2
B51: Switching costs | E51: 1
B52: Bargaining Power of Suppliers | E52: =IFERROR(AVERAGE(E53:E57),"") -> 4.25
B53: Number of suppliers | E53: 4
B54: Uniqueness | E54: 5
B55: Switching Costs | E55: 3
B56: Forward Integration
B57: Industry Importance | E57: 5
B58: Bargaining Power of Customers | E58: =IFERROR(AVERAGE(E59:E63),"") -> 2.8
B59: Number of buyers | E59: 3
B60: Purchase size | E60: 2
B61: Switching costs | E61: 2
B62: Price sensitivity | E62: 2
B63: Informed buyers | E63: 5
B64: Competitive Rivalry | E64: =IFERROR(AVERAGE(E65:E69),"") -> 4.6
B65: Number of competitors | E65: 5
B66: Industry growth | E66: 4
B67: Similarities in what's offered | E67: 4
B68: Exit barriers | E68: 5
B69: Fixed costs | E69: 5
B70: Threat of Substitutes | E70: =IFERROR(AVERAGE(E71:E75),"") -> 1.75
B71: Relative price performance | E71: 3
B72: Customer willingness to go elsewhere | E72: 1
B73: The sense that products are similar | E73: 1
B74: Availability of close substitutes | E74: 2

Sheet Peers
D3: Revenue Growth | F3: EBITDA Margin | H3: Profit Margin | J3: EV / Revenue | L3: EV / EBITDA | N3: Price / Earnings
B4: Peers | C4: Ticker | D4: =+Inputs!O4&"-"&Inputs!P4 -> 2022-2023 | E4: =+Inputs!P4&"-"&Inputs!Q4 -> 2023-2024 | F4: 2023 | G4: 2024 | H4: =+Inputs!O4&"-"&Inputs!P4 -> 2022-2023 | I4: =+Inputs!P4&"-"&Inputs!Q4 -> 2023-2024 | J4: 2023 | K4: 2024 | L4: 2023 | M4: 2024 | N4: 2023 | O4: 2024
A6: =+D93 -> #VALUE! | B6: {=IFERROR(_FV(A6,"Name"),"")} -> SK hynix Inc. | C6: {=IFERROR(_FV(A6,"Ticker symbol",TRUE),"")} -> 000660 | D6: =IFERROR(D96/D95-1,"") -> -0.26569868 | E6: =IFERROR(D99/D96-1,"") -> 1.0201918 | F6: =IFERROR(D97/D96,"") -> -0.21801152 | G6: =IFERROR(D102/D99,"") -> 0.362984 | H6: =IFERROR(D98/D96,"") -> -0.278877 | I6: =IFERROR(D107/D99,"") -> 0.29908147 | J6: {=IFERROR((_FV(A6,"Market cap",TRUE)/1000000000+D$123-D$113)/D$96,"")} -> 4.275236 | K6: {=IFERROR((_FV(A6,"Market cap",TRUE)/1000000000+D$123-D$113)/D$99,"")} -> 2.1162525 | L6: {=+IFERROR((_FV(A6,"Market cap",TRUE)/1000000000+D$123-D$113)/D$97,"")} -> -19.610138 | M6: {=IFERROR((_FV(A6,"Market cap",TRUE)/1000000000+D$123-D$113)/D$102,"")} -> 5.8301536 | N6: {=IFERROR((_FV(A6,"Market cap",TRUE)/1000000000)/D$98,"")} -> -14.205349 | O6: {=IFERROR((_FV(A6,"Market cap",TRUE)/1000000000)/D$107,"")} -> 6.5566573
A8: =+E93 -> #VALUE! | B8: {=IFERROR(_FV(A8,"Name"),"")} -> Samsung Electronics Co., Ltd. | C8: {=+IFERROR(_FV(A8,"Ticker symbol",TRUE),"")} -> 005930 | D8: =+IFERROR(E96/E95-1,"") -> -0.14325414 | E8: =IFERROR(E99/E96-1,"") -> 0.16195307 | F8: =IFERROR(E97/E96,"") -> 0.17469022 | G8: =+IFERROR(E102/E99,"") -> 0.25046224 | H8: =IFERROR(E98/E96,"") -> 0.055895773 | I8: =+IFERROR(E107/E101,"") -> 0.29412835 | J8: {=+IFERROR((_FV(A8,"Market cap",TRUE)/1000000000+E$123-E$113)/E$96,"")} -> 1.2860566 | K8: {=IFERROR(+(_FV(A8,"Market cap",TRUE)/1000000000+E$123-E$113)/E$99,"")} -> 1.1068059 | L8: {=IFERROR(+(_FV(A8,"Market cap",TRUE)/1000000000+E$123-E$113)/E$97,"")} -> 7.3619264 | M8: {=IFERROR(+(_FV(A8,"Market cap",TRUE)/1000000000+E$123-E$113)/E$102,"")} -> 4.4190531 | N8: {=IFERROR(+(_FV(A8,"Market cap",TRUE)/1000000000)/E$98,"")} -> 25.383193 | O8: {=IFERROR(+(_FV(A8,"Market cap",TRUE)/1000000000)/E$107,"")} -> 10.927002
A9: =+F93 -> #VALUE! | B9: {=IFERROR(_FV(A9,"Name"),"")} -> MICRON TECHNOLOGY, INC. | C9: {=+IFERROR(_FV(A9,"Ticker symbol",TRUE),"")} -> MU | D9: =IFERROR(F96/F95-1,"") -> -0.4574375 | E9: =IFERROR(+F99/F96-1,"") -> 0.64442248 | F9: =IFERROR(F97/F96,"") -> 0.15868648 | G9: =IFERROR(F102/F99,"") -> 0.35777048 | H9: =IFERROR(F98/F96,"") -> -0.37535429 | I9: =+IFERROR(F107/F99,"") -> 0.030983004 | J9: {=IFERROR(+(_FV(A9,"Market cap",TRUE)*Q9/1000000000+Q9+F$123-F$113)/F$96,"")} -> 6.5140537 | K9: {=IFERROR(+(_FV(A9,"Market cap",TRUE)*Q9/1000000000+F$123-F$113)/F$99,"")} -> 3.9187347 | L9: {=IFERROR(+(_FV(A9,"Market cap",TRUE)*Q9/1000000000+F$123-F$113)/F$97,"")} -> 40.608723 | M9: {=IFERROR(+(_FV(A9,"Market cap",TRUE)*Q9/1000000000+F$123-F$113)/F$102,"")} -> 10.953209 | N9: {=IFERROR(+(_FV(A9,"Market cap",TRUE)*Q9/1000000000)/F$98,"")} -> -16.13522 | O9: {=IFERROR(+(_FV(A9,"Market cap",TRUE)*Q9/1000000000)/F$107,"")} -> 118.87194 | P9: #VALUE! | Q9: {=+_FV(P9,"Price")} -> 1437.36 | R9: Market cap is in USD, convert to KRW
A10: =+G93 -> #VALUE! | B10: {=IFERROR(_FV(A10,"Name"),"")} -> Kioxia Holdings Corporation | C10: {=IFERROR(_FV(A10,"Ticker symbol",TRUE),"")} -> KI5 | D10: =+IFERROR(G96/G95-1,"") -> -0.21842907 | E10: =IFERROR(G99/G96-1,"") -> -0.20612719 | F10: =IFERROR(G97/G96,"") -> 0.25037105 | G10: =IFERROR(G102/G99,"") -> 0.074844033 | H10: =IFERROR(G98/G96,"") -> -0.10775014 | I10: =+IFERROR(G107/G99,"") -> -0.22639151 | J10: {=IFERROR(+(_FV(A10,"Market cap",TRUE)*Q10/1000000000+G$123-G$113)/G$96,"")} -> 1.8184336 | K10: {=IFERROR(+(_FV(A10,"Market cap",TRUE)*Q10/1000000000+G$123-G$113)/G$99,"")} -> 2.2905855 | L10: {=IFERROR(+(_FV(A10,"Market cap",TRUE)*Q10/1000000000+G$123-G$113)/G$97,"")} -> 7.2629546 | M10: {=IFERROR(+(_FV(A10,"Market cap",TRUE)*Q10/1000000000+G$123-G$113)/G$102,"")} -> 30.604785 | N10: {=IFERROR(+(_FV(A10,"Market cap",TRUE)*Q10/1000000000)/G$98,"")} -> -7.3211444 | O10: {=IFERROR(+(_FV(A10,"Market cap",TRUE)*Q10/1000000000)/G$107,"")} -> -4.3892036 | P10: #VALUE! | Q10: {=+_FV(P10,"Price")} -> 10.0011 | R10: Market cap is in JPY, convert to KRW
A11: =+H93 -> #VALUE! | B11: {=IFERROR(_FV(A11,"Name"),"")} -> WESTERN DIGITAL CORPORATION | C11: {=IFERROR(_FV(A11,"Ticker symbol",TRUE),"")} -> WDC | D11: =IFERROR(H96/H95-1,"") -> -0.27908376 | E11: =IFERROR(H99/H96-1,"") -> 0.064105474 | F11: =IFERROR(H97/H96,"") -> -0.012420842 | G11: =IFERROR(H102/H99,"") -> 0.073060203 | H11: =IFERROR(H98/H96,"") -> -0.13670804 | I11: =+IFERROR(H107/H104,"") -> -2.1110252 | J11: {=IFERROR((_FV(A11,"Market cap",TRUE)*Q11/1000000000+H$123-H$113)/H$96,"")} -> 1.7503565 | K11: {=IFERROR(+(_FV(A11,"Market cap",TRUE)*Q11/1000000000+H$123-H$113)/H$99,"")} -> 1.6449088 | L11: {=IFERROR(+(_FV(A11,"Market cap",TRUE)*Q11/1000000000+H$123-H$113)/H$97,"")} -> -140.92092 | M11: {=IFERROR(+(_FV(A11,"Market cap",TRUE)*Q11/1000000000+H$123-H$113)/H$102,"")} -> 22.51443 | N11: {=IFERROR(+(_FV(A11,"Market cap",TRUE)*Q11/1000000000)/H$98,"")} -> -9.1495248 | O11: {=IFERROR(+(_FV(A11,"Market cap",TRUE)*Q11/1000000000)/H$107,"")} -> -19.154346 | P11: #VALUE! | Q11: {=+_FV(P11,"Price")} -> 1437.36 | R11: Market cap is in USD, convert to KRW
A12: =+I93 -> PEER 5 | B12: {=IFERROR(_FV(A12,"Name"),"")} | C12: {=IFERROR(_FV(A12,"Ticker symbol",TRUE),"")} | D12: =+IFERROR(I96/I95-1,"") | E12: =IFERROR(I99/I96-1,"") | F12: =IFERROR(I97/I96,"") | G12: =IFERROR(I102/I99,"") | H12: =IFERROR(I98/I96,"") | I12: =+IFERROR(I107/I99,"") | J12: {=IFERROR((_FV(A12,"Market cap",TRUE)/1000000+I$123-I$113)/I$96,"")} | K12: {=IFERROR(+(_FV(A12,"Market cap",TRUE)/1000000+I$123-I$113)/I$99,"")} | L12: {=IFERROR(+(_FV(A12,"Market cap",TRUE)/1000000+I$123-I$113)/I$97,"")} | M12: {=IFERROR(+(_FV(A12,"Market cap",TRUE)/1000000+I$123-I$113)/I$102,"")} | N12: {=IFERROR(+(_FV(A12,"Market cap",TRUE)/1000000)/I$98,"")} | O12: {=IFERROR(+(_FV(A12,"Market cap",TRUE)/1000000)/I$107,"")} | S12: SANTANDER
A13: =+J93 -> PEER 6 | B13: {=IFERROR(_FV(A13,"Name"),"")} | C13: {=IFERROR(_FV(A13,"Ticker symbol",TRUE),"")} | D13: =IFERROR(J96/J95-1,"") | E13: =IFERROR(J99/J96-1,"") | F13: =IFERROR(J97/J96,"") | G13: =IFERROR(J102/J99,"") | H13: =IFERROR(J98/J96,"") | I13: =+IFERROR(J107/J99,"") | J13: {=IFERROR(+(_FV(A13,"Market cap",TRUE)/1000000+J$123-J$113)/J$96,"")} | K13: {=IFERROR(+(_FV(A13,"Market cap",TRUE)/1000000+J$123-J$113)/J$99,"")} | L13: {=IFERROR(+(_FV(A13,"Market cap",TRUE)/1000000+J$123-J$113)/J$97,"")} | M13: {=IFERROR(+(_FV(A13,"Market cap",TRUE)/1000000+J$123-J$113)/J$102,"")} | N13: {=IFERROR(+(_FV(A13,"Market cap",TRUE)/1000000)/J$98,"")} | O13: {=IFERROR(+(_FV(A13,"Market cap",TRUE)/1000000)/J$107,"")} | S13: HAITONG
A14: =+K93 -> PEER 7 | B14: {=IFERROR(_FV(A14,"Name"),"")} | C14: {=IFERROR(_FV(A14,"Ticker symbol",TRUE),"")} | D14: =IFERROR(K96/K95-1,"") | E14: =IFERROR(K99/K96-1,"") | F14: =+IFERROR(K97/K96,"") | G14: =IFERROR(K102/K99,"") | H14: =IFERROR(K98/K96,"") | I14: =+IFERROR(K107/K99,"") | J14: {=IFERROR((_FV(A14,"Market cap",TRUE)/1000000+D$123-K$113)/K$96,"")} | K14: {=IFERROR(+(_FV(A14,"Market cap",TRUE)/1000000+D$123-K$113)/K$99,"")} | L14: {=IFERROR(+(_FV(A14,"Market cap",TRUE)/1000000+D$123-K$113)/K$97,"")} | M14: {=IFERROR(+(_FV(A14,"Market cap",TRUE)/1000000+D$123-K$113)/K$102,"")} | N14: {=IFERROR(+(_FV(A14,"Market cap",TRUE)/1000000)/K$98,"")} | O14: {=IFERROR(+(_FV(A14,"Market cap",TRUE)/1000000)/K$107,"")} | S14: BNP
A15: =+L93 -> PEER 8 | B15: {=IFERROR(_FV(A15,"Name"),"")} | C15: {=IFERROR(_FV(A15,"Ticker symbol",TRUE),"")} | D15: =+IFERROR(L96/L95,"") | E15: =IFERROR(L99/L96,"") | F15: =IFERROR(L97/L96,"") | G15: =IFERROR(L102/L99,"") | H15: =IFERROR(L98/L96,"") | I15: =+IFERROR(L107/L99,"") | J15: {=IFERROR(+(_FV(A15,"Market cap",TRUE)/1000000+L$123-L$113)/L$96,"")} | K15: {=IFERROR(+(_FV(A15,"Market cap",TRUE)/1000000+L$123-L$113)/L$99,"")} | L15: {=IFERROR(+(_FV(A15,"Market cap",TRUE)/1000000+L$123-L$113)/L$97,"")} | M15: {=IFERROR(+(_FV(A15,"Market cap",TRUE)/1000000+L$123-L$113)/L$102,"")} | N15: {=IFERROR(+(_FV(A15,"Market cap",TRUE)/1000000)/L$98,"")} | O15: {=IFERROR(+(_FV(A15,"Market cap",TRUE)/1000000)/L$107,"")}
A16: =+M93 -> PEER 9 | B16: {=IFERROR(_FV(A16,"Name"),"")} | C16: {=IFERROR(_FV(A16,"Ticker symbol",TRUE),"")} | D16: =IFERROR(M96/M95-1,"") | E16: =IFERROR(M99/M96-1,"") | F16: =IFERROR(M97/M96,"") | G16: =IFERROR(M102/M99,"") | H16: =IFERROR(M98/M96,"") | I16: =+IFERROR(M107/M99,"") | J16: {=IFERROR(+(_FV(A16,"Market cap",TRUE)/1000000+M$123-M$113)/M$96,"")} | K16: {=IFERROR(+(_FV(A16,"Market cap",TRUE)/1000000+M$123-M$113)/M$99,"")} | L16: {=IFERROR(+(_FV(A16,"Market cap",TRUE)/1000000+M$123-M$113)/M$97,"")} | M16: {=IFERROR(+(_FV(A16,"Market cap",TRUE)/1000000+M$123-M$113)/M$102,"")} | N16: {=IFERROR(+(_FV(A16,"Market cap",TRUE)/1000000)/M$98,"")} | O16: {=IFERROR(+(_FV(A16,"Market cap",TRUE)/1000000)/M$107,"")}
A17: =+N93 -> PEER 10 | B17: {=IFERROR(_FV(A17,"Name"),"")} | C17: {=+IFERROR(_FV(A17,"Ticker symbol",TRUE),"")} | D17: =IFERROR(N96/N95-1,"") | E17: =IFERROR(N99/N96-1,"") | F17: =IFERROR(N97/N96,"") | G17: =IFERROR(N102/N99,"") | H17: =IFERROR(N98/N96,"") | I17: =+IFERROR(N107/N99,"") | J17: {=IFERROR(+(_FV(A17,"Market cap",TRUE)/1000000+N$123-N$113)/N$96,"")} | K17: {=IFERROR(+(_FV(A17,"Market cap",TRUE)/1000000+N$123-N$113)/N$99,"")} | L17: {=IFERROR(+(_FV(A17,"Market cap",TRUE)/1000000+N$123-N$113)/N$97,"")} | M17: {=IFERROR(+(_FV(A17,"Market cap",TRUE)/1000000+N$123-N$113)/N$102,"")} | N17: {=IFERROR(+(_FV(A17,"Market cap",TRUE)/1000000)/N$98,"")} | O17: {=IFERROR(+(_FV(A17,"Market cap",TRUE)/1000000)/N$107,"")}
B18: Average | D18: =IFERROR(AVERAGE(D6:D17),"") -> -0.27278063 | E18: =IFERROR(AVERAGE(E6:E17),"") -> 0.33690914 | F18: =IFERROR(AVERAGE(F6:F17),"") -> 0.070663079 | G18: =IFERROR(AVERAGE(G6:G17),"") -> 0.22382419 | H18: =IFERROR(AVERAGE(H6:H17),"") -> -0.16855874 | I18: =IFERROR(AVERAGE(I6:I17),"") -> -0.34264477 | J18: =IFERROR(AVERAGE(J6:J17),"") -> 3.1288273 | K18: =IFERROR(AVERAGE(K6:K17),"") -> 2.2154575 | ... O18: =IFERROR(AVERAGE(O6:O17),"") -> 22.56241
B19: Deviation from Average | D19: =IFERROR(+D18-D6,"") -> -0.0070819537 | E19: =IFERROR(E18-E6,"") -> -0.68328271 | F19: =+IFERROR(F18-F6,"") -> 0.2886746 | G19: =IFERROR(G18-G6,"") -> -0.13915981 | H19: =IFERROR(+H6-H18,"") -> -0.11031826 | I19: =+IFERROR(I6-I18,"") -> 0.64172624 | J19: =+IFERROR(J6-J18,"") -> 1.1464087 | K19: =+IFERROR(K6-K18,"") -> -0.099205023 | L19: =IFERROR(+L6-L18,"") -> 1.449353 | M19: =IFERROR(M6-M18,"") -> -9.0341725 | N19: =IFERROR(+N6-N18,"") -> -9.9197401 | O19: =IFERROR(+O6-O18,"") -> -16.005752
D21: Trading Multiple | G21: Net | H21: Preferred | I21: Non-Controlling | J21: Equity Value | M21: Implied Upside (Downside)
B22: Implied Share Price | D22: Revenue | E22: EBITDA | F22: P/E | G22: Debt | H22: Stock | I22: Interest | J22: Revenue | K22: EBITDA | L22: P/E | M22: Revenue | N22: EBITDA | O22: P/E | P22: Current Price
B24: Second Minimum | D24: =+MIN(K6:K11) -> 1.1068059 | E24: =MIN(M6:M11) -> 4.4190531 | F24: =MIN(O6:O11) -> -19.154346 | G24: =-Inputs!$Q$99+Inputs!$Q$100 -> 7555.4 | H24: =+Inputs!$Q$101 -> 0 | I24: =+Inputs!$Q$102 -> 12.3 | J24: =IFERROR(+D24*$D$99+G24+H24+I24,"") -> 80830.506 | K24: =IFERROR(E24*$D$102+G24+H24+I24,"") -> 113744.29 | L24: =IFERROR(F24*$D$107,"") -> -379200.51 | M24: {=IFERROR(+(J24/_FV($A$6,"Shares outstanding",TRUE)*1000000000)/$P$24-1,"")} -> -0.39788206 | N24: {=IFERROR((+K24/_FV($A$6,"Shares outstanding",TRUE)*1000000000)/$P$24-1,"")} -> -0.15270261 | O24: {=IFERROR(+(L24/_FV($A$6,"Shares outstanding",TRUE)*1000000000)/$P$24-1,"")} -> -3.8247185 | P24: {=+_FV(A6,"Price")} -> 184400
B25: Average | D25: =+IFERROR(AVERAGE(K6:K17),"") -> 2.2154575 | E25: =IFERROR(+AVERAGE(M6:M17),"") -> 14.864326 | F25: =IFERROR(+AVERAGE(O6:O17),"") -> 22.56241 | G25: =-Inputs!$Q$99+Inputs!$Q$100 -> 7555.4 | H25: =+Inputs!$Q$101 -> 0 | I25: =+Inputs!$Q$102 -> 12.3 | J25: =IFERROR(+D25*$D$99+G25+H25+I25,"") -> 154215.48 | K25: =IFERROR(E25*$D$102+G25+H25+I25,"") -> 364712.86 | L25: =IFERROR(+F25*$D$107,"") -> 446670.28 | M25: {=IFERROR(+(J25/_FV($A$6,"Shares outstanding",TRUE)*1000000000)/$P$24-1,"")} -> 0.14877305 | N25: {=IFERROR((+K25/_FV($A$6,"Shares outstanding",TRUE)*1000000000)/$P$24-1,"")} -> 1.716798 | O25: {=IFERROR(+(L25/_FV($A$6,"Shares outstanding",TRUE)*1000000000)/$P$24-1,"")} -> 2.3273105
B26: Median | D26: =IFERROR(MEDIAN(K6:K17),"") -> 2.1162525 | E26: =IFERROR(MEDIAN(M6:M17),"") -> 10.953209 | F26: =IFERROR(MEDIAN(O6:O17),"") -> 6.5566573 | G26: =-Inputs!$Q$99+Inputs!$Q$100 -> 7555.4 | H26: =+Inputs!$Q$101 -> 0 | I26: =+Inputs!$Q$102 -> 12.3 | J26: =IFERROR(D26*$D$99+G26+H26+I26,"") -> 147648.8 | K26: =IFERROR(E26*$D$102+G26+H26+I26,"") -> 270740.44 | L26: =IFERROR(+F26*$D$107,"") -> 129802.8 | M26: {=IFERROR(+(J26/_FV($A$6,"Shares outstanding",TRUE)*1000000000)/$P$24-1,"")} -> 0.099856926 | N26: {=IFERROR((+K26/_FV($A$6,"Shares outstanding",TRUE)*1000000000)/$P$24-1,"")} -> 1.0167841 | O26: {=+IFERROR((L26/_FV($A$6,"Shares outstanding",TRUE)*1000000000)/$P$24-1,"")} -> -0.033080468
B27: Second Maximum | D27: =+MAX(K6:K11) -> 3.9187347 | E27: =+MAX(M6:M11) -> 30.604785 | F27: =MAX(O6:O11) -> 118.87194 | G27: =-Inputs!$Q$99+Inputs!$Q$100 -> 7555.4 | H27: =+Inputs!$Q$101 -> 0 | I27: =+Inputs!$Q$102 -> 12.3 | J27: =IFERROR(+D27*$D$99+G27+H27+I27,"") -> 266960.51 | K27: =IFERROR(E27*$D$102+G27+H27+I27,"") -> 742908.87 | L27: =IFERROR(+F27*$D$107,"") -> 2353319.7 | M27: {=IFERROR(+(J27/_FV($A$6,"Shares outstanding",TRUE)*1000000000)/$P$24-1,"")} -> 0.9886268 | N27: {=IFERROR((+K27/_FV($A$6,"Shares outstanding",TRUE)*1000000000)/$P$24-1,"")} -> 4.5340339 | O27: {=+IFERROR((L27/_FV($A$6,"Shares outstanding",TRUE)*1000000000)/$P$24-1,"")} -> 16.530213
B29: Profitability | D29: =+LEFT(B6, FIND(" ", B6 & " ") - 1) -> SK | E29: =+LEFT(B8, FIND(" ", B8 & " ") - 1) -> Samsung | F29: =+LEFT(B9, FIND(" ", B9 & " ") - 1) -> MICRON | G29: =+LEFT(B10, FIND(" ", B10 & " ") - 1) -> Kioxia | H29: =+LEFT(B11, FIND(" ", B11 & " ") - 1) -> WESTERN | I29: =+LEFT(B12, FIND(" ", B12 & " ") - 1) | J29: =+LEFT(C12, FIND(" ", C12 & " ") - 1) | K29: =+LEFT(B14, FIND(" ", B14 & " ") - 1) | L29: =+LEFT(B15, FIND(" ", B15 & " ") - 1) | M29: =+LEFT(B16, FIND(" ", B16 & " ") - 1) | N29: =+LEFT(B17, FIND(" ", B17 & " ") - 1) | O29: Average
B31: Operating Margin | D31: =IFERROR(D103/D99,"") -> 0.35452994 | E31: =IFERROR(E103/E99,"") -> 0.1087709 | F31: =IFERROR(F103/F99,"") -> 0.042372856 | G31: =IFERROR(G103/G99,"") -> -0.24660123 | H31: =IFERROR(H103/H99,"") -> 0.024455854 | I31: =IFERROR(I103/I99,"") | J31: =IFERROR(J103/J99,"") | K31: =IFERROR(K103/K99,"") | ... N31: =IFERROR(N103/N99,"") | O31: =IFERROR(+AVERAGE(D31:N31),"") -> 0.056705664
B32: Net Income Margin | D32: =IFERROR(D107/D99,"") -> 0.29908147 | E32: =IFERROR(E107/E99,"") -> 0.11174693 | F32: =IFERROR(F107/F99,"") -> 0.030983004 | G32: =IFERROR(G107/G99,"") -> -0.22639151 | H32: =IFERROR(H107/H99,"") -> -0.061367803 | I32: =IFERROR(I107/I99,"") | J32: =IFERROR(J107/J99,"") | K32: =IFERROR(K107/K99,"") | ... N32: =IFERROR(N107/N99,"") | O32: =IFERROR(+AVERAGE(D32:N32),"") -> 0.030810419
B33: ROA (%) | D33: =IFERROR(D107/D119,"") -> 0.16517514 | E33: =IFERROR(E107/E119,"") -> 0.065343665 | F33: =IFERROR(F107/F119,"") -> 0.011307862 | G33: =IFERROR(G107/G119,"") -> -0.087428585 | H33: =IFERROR(H107/H119,"") -> -0.031907814 | I33: =IFERROR(I107/I119,"") | J33: =IFERROR(J107/J119,"") | K33: =IFERROR(K107/K119,"") | ... N33: =IFERROR(N107/N119,"") | O33: =IFERROR(+AVERAGE(D33:N33),"") -> 0.024498055
B34: Financial Cost of Debt | D34: =IFERROR(+(D104/D123)*(1-(D106/D105)),"") -> 0.03859561 | E34: =IFERROR(+(E104/E123)*(1-(E106/E105)),"") -> -0.18592942 | F34: =IFERROR(+(F104/F123)*(1-(F106/F105)),"") -> 0.0015055717 | G34: =IFERROR(+(G104/G123)*(1-(G106/G105)),"") -> 0.021636559 | H34: =IFERROR(+(H104/H123)*(1-(H106/H105)),"") -> 0.056709984 | I34: =IFERROR(+(I104/I123)*(1-(I106/I105)),"") | J34: =IFERROR(+(J104/J123)*(1-(J106/J105)),"") | K34: =IFERROR(+(K104/K123)*(1-(K106/K105)),"") | ... N34: =IFERROR(+(N104/N123)*(1-(N106/N105)),"") | O34: =IFERROR(+AVERAGE(D34:N34),"") -> -0.01349634
B35: Return on Equity (RoE) | D35: =IFERROR(+D107/D124,"") -> 0.26783349 | E35: =IFERROR(+E107/E124,"") -> 0.083595376 | F35: =IFERROR(+F107/F124,"") -> 0.017392605 | G35: =IFERROR(+G107/G124,"") -> -0.55691362 | H35: =IFERROR(+H107/H124,"") -> -0.069863607 | I35: =IFERROR(+I107/I124,"") | J35: =IFERROR(+J107/J124,"") | K35: =IFERROR(+K107/K124,"") | ... N35: =IFERROR(+N107/N124,"") | O35: =IFERROR(+AVERAGE(D35:N35),"") -> -0.05159115
B36: Return on Invested Capital (ROIC) | D36: =IFERROR(+D107/(D123+D124),"") -> 0.20751873 | E36: =IFERROR(+E107/(E123+E124),"") -> 0.079761854 | F36: =IFERROR(+F107/(F123+F124),"") -> 0.013257201 | G36: =IFERROR(+G107/(G123+G124),"") -> -0.12119646 | H36: =IFERROR(+H107/(H123+H124),"") -> -0.040987015 | I36: =IFERROR(+I107/(I123+I124),"") | J36: =IFERROR(+J107/(J123+J124),"") | K36: =IFERROR(+K107/(K123+K124),"") | ... N36: =IFERROR(+N107/(N123+N124),"") | O36: =IFERROR(+AVERAGE(D36:N36),"") -> 0.027670861
B38: Solvency | D38: =+D29 -> SK | E38: =+E29 -> Samsung | F38: =+F29 -> MICRON | G38: =+G29 -> Kioxia | H38: =+H29 -> WESTERN | I38: =+I29 | J38: =+J29 | K38: =+K29 | ... O38: =+O29 -> Average
B40: Debt/Assets | D40: =IFERROR(D123/D119,"") -> 0.17924462 | E40: =IFERROR(E123/E119,"") -> 0.037568516 | F40: =IFERROR(F123/F119,"") -> 0.20280654 | G40: =IFERROR(G123/G119,"") -> 0.56439132 | H40: =IFERROR(H123/H119,"") -> 0.3217701 | I40: =IFERROR(I123/I119,"") | J40: =IFERROR(J123/J119,"") | K40: =IFERROR(K123/K119,"") | ... N40: =IFERROR(N123/N119,"") | O40: =IFERROR(+AVERAGE(D40:N40),"") -> 0.26115622
B41: Net Debt/EBITDA | D41: =IFERROR(+(D123-D113)/D102,"") -> 0.42778125 | E41: =IFERROR(+(E123-E113)/E102,"") -> -0.45616852 | F41: =IFERROR(+(F123-F113)/F102,"") -> 0.65887193 | G41: =IFERROR(+(G123-G113)/G102,"") -> 17.328129 | H41: =IFERROR(+(H123-H113)/H102,"") -> 6.4255051 | I41: =IFERROR(+(I123-I113)/I102,"") | J41: =IFERROR(+(J123-J113)/J102,"") | K41: =IFERROR(+(K123-K113)/K102,"") | ... N41: =IFERROR(+(N123-N113)/N102,"") | O41: =IFERROR(+AVERAGE(D41:N41),"") -> 4.8768238
B42: Interest Coverage Ratio | D42: =IFERROR(D103/D104,"") -> 23.458017 | E42: =IFERROR(E103/E104,"") -> -8.3587045 | F42: =IFERROR(F103/F104,"") -> 32.225225 | G42: =IFERROR(G103/G104,"") -> -5.5360401 | H42: =IFERROR(H103/H104,"") -> 0.8412705 | I42: =IFERROR(I103/I104,"") | J42: =IFERROR(J103/J104,"") | K42: =IFERROR(K103/K104,"") | ... N42: =IFERROR(N103/N104,"") | O42: =IFERROR(+AVERAGE(D42:N42),"") -> 8.5259536
B44: Liquidity | D44: =+D29 -> SK | E44: =+E29 -> Samsung | F44: =+F29 -> MICRON | G44: =+G29 -> Kioxia | H44: =+H29 -> WESTERN | I44: =+I29 | J44: =+J29 | K44: =+K29 | ... O44: =+O29 -> Average
B46: Cash Ratio | D46: =IFERROR(D113/D121,"") -> 0.44882517 | E46: =IFERROR(E113/E121,"") -> 0.57546051 | F46: =IFERROR(F113/F121,"") -> 0.87651306 | G46: =IFERROR(G113/G121,"") -> 0.097560829 | H46: =IFERROR(H113/H121,"") -> 0.30869109 | I46: =IFERROR(I113/I121,"") | J46: =IFERROR(J113/J121,"") | K46: =IFERROR(K113/K121,"") | ... N46: =IFERROR(N113/N121,"") | O46: =IFERROR(+AVERAGE(D46:N46),"") -> 0.46141013
B47: Quick Ratio | D47: =IFERROR(+(D113+D114)/D121,"") -> 0.9703069 | E47: =IFERROR(+(E113+E114)/E121,"") -> 1.0428861 | F47: =IFERROR(+(F113+F114)/F121,"") -> 1.4624777 | G47: =IFERROR(+(G113+G114)/G121,"") -> 0.16598293 | H47: =IFERROR(+(H113+H114)/H121,"") -> 0.66453042 | I47: =IFERROR(+(I113+I114)/I121,"") | J47: =IFERROR(+(J113+J114)/J121,"") | K47: =IFERROR(+(K113+K114)/K121,"") | ... N47: =IFERROR(+(N113+N114)/N121,"") | O47: =IFERROR(+AVERAGE(D47:N47),"") -> 0.86123681
B48: Current Ratio | D48: =IFERROR(D117/D121,"") -> 1.6934998 | E48: =IFERROR(E117/E121,"") -> 2.4329937 | F48: =IFERROR(F117/F121,"") -> 2.6353805 | G48: =IFERROR(G117/G121,"") -> 0.3490503 | H48: =IFERROR(H117/H121,"") -> 1.3241411 | I48: =IFERROR(I117/I121,"") | J48: =IFERROR(J117/J121,"") | K48: =IFERROR(K117/K121,"") | ... N48: =IFERROR(N117/N121,"") | O48: =IFERROR(+AVERAGE(D48:N48),"") -> 1.6870131
B50: Activity | D50: =+D29 -> SK | E50: =+E29 -> Samsung | F50: =+F29 -> MICRON | G50: =+G29 -> Kioxia | H50: =+H29 -> WESTERN | I50: =+I29 | J50: =+J29 | K50: =+K29 | ... O50: =+O29 -> Average
B52: Inventory Turnover | D52: =IFERROR(D100/(AVERAGE(D115:D116)),"") -> 2.5650542 | E52: =IFERROR(E100/(AVERAGE(E115:E116)),"") -> 3.6092253 | F52: =IFERROR(F100/(AVERAGE(F115:F116)),"") -> 2.2871373 | G52: =IFERROR(G100/(AVERAGE(G115:G116)),"") -> 3.6791483 | H52: =IFERROR(H100/(AVERAGE(H115:H116)),"") -> 2.8295564 | I52: =IFERROR(I100/(AVERAGE(I115:I116)),"") | J52: =IFERROR(J100/(AVERAGE(J115:J116)),"") | K52: =IFERROR(K100/(AVERAGE(K115:K116)),"") | ... N52: =IFERROR(N100/(AVERAGE(N115:N116)),"") | O52: =IFERROR(+AVERAGE(D52:N52),"") -> 2.9940243
B53: Acc. Receivable Turnover | D53: =IFERROR(D99/D114,"") -> 5.0843383 | E53: =IFERROR(E99/E114,"") -> 6.8970545 | F53: =IFERROR(F99/F114,"") -> 4.6751724 | G53: =IFERROR(G99/G114,"") -> 8.6650819 | H53: =IFERROR(H99/H114,"") -> 5.8063069 | I53: =IFERROR(I99/I114,"") | J53: =IFERROR(J99/J114,"") | K53: =IFERROR(K99/K114,"") | ... N53: =IFERROR(N99/N114,"") | O53: =IFERROR(+AVERAGE(D53:N53),"") -> 6.2255908
B54: Payables Turnover | D54: =IFERROR(D100/D120,"") -> 15.090151 | E54: =IFERROR(E100/E120,"") -> 15.081591 | F54: =IFERROR(F100/F120,"") -> 7.2229929 | G54: =IFERROR(G100/G120,"") -> 10.976999 | H54: =IFERROR(H100/H120,"") -> 6.8942446 | I54: =IFERROR(I100/I120,"") | J54: =IFERROR(J100/J120,"") | K54: =IFERROR(K100/K120,"") | ... N54: =IFERROR(N100/N120,"") | O54: =IFERROR(+AVERAGE(D54:N54),"") -> 11.053196
B55: Fixed Asset Turnover | D55: =IFERROR(D99/D118,"") -> 1.0566484 | E55: =IFERROR(E99/E118,"") -> 1.460927 | F55: =IFERROR(F99/F118,"") -> 0.62719105 | G55: =IFERROR(G99/G118,"") -> 0.83282279 | H55: =IFERROR(H99/H118,"") -> 3.6004816 | I55: =IFERROR(I99/I118,"") | J55: =IFERROR(J99/J118,"") | K55: =IFERROR(K99/K118,"") | ... N55: =IFERROR(N99/N118,"") | O55: =IFERROR(+AVERAGE(D55:N55),"") -> 1.5156142
B56: Total Asset Turnover | D56: =IFERROR(D99/D119,"") -> 0.55227474 | E56: =IFERROR(E99/E119,"") -> 0.58474683 | F56: =IFERROR(F99/F119,"") -> 0.36496984 | G56: =IFERROR(G99/G119,"") -> 0.38618314 | H56: =IFERROR(H99/H119,"") -> 0.51994388 | I56: =IFERROR(I99/I119,"") | J56: =IFERROR(J99/J119,"") | K56: =IFERROR(K99/K119,"") | ... N56: =IFERROR(N99/N119,"") | O56: =IFERROR(+AVERAGE(D56:N56),"") -> 0.48162369
B57: Cash Cycle (days) | D57: =IFERROR(365/D52+365/D53-365/D54,"") -> 189.89831 | E57: =IFERROR(365/E52+365/E53-365/E54,"") -> 129.84919 | F57: =IFERROR(365/F52+365/F53-365/F54,"") -> 187.12706 | G57: =IFERROR(365/G52+365/G53-365/G54,"") -> 108.07948 | H57: =IFERROR(365/H52+365/H53-365/H54,"") -> 138.91545 | I57: =IFERROR(365/I52+365/I53-365/I54,"") | J57: =IFERROR(365/J52+365/J53-365/J54,"") | K57: =IFERROR(365/K52+365/K53-365/K54,"") | ... N57: =IFERROR(365/N52+365/N53-365/N54,"") | O57: =IFERROR(+AVERAGE(D57:N57),"") -> 150.7739
B59: Cash Flow | D59: =+D38 -> SK | E59: =+E38 -> Samsung | F59: =+F38 -> MICRON | G59: =+G38 -> Kioxia | H59: =+H38 -> WESTERN | I59: =+I38 | J59: =+J38 | K59: =+K38 | ... O59: =+O38 -> Average
B61: Cash Flow Margin | D61: =IFERROR(D134/D99,"") -> 0.054655326 | E61: =IFERROR(E134/E99,"") -> -0.051102649 | F61: =IFERROR(F134/F99,"") -> -0.063876163 | G61: =IFERROR(G134/G99,"") -> -0.06851389 | H61: =IFERROR(H134/H99,"") -> -0.01107434 | I61: =IFERROR(I134/I99,"") | J61: =IFERROR(J134/J99,"") | K61: =IFERROR(K134/K99,"") | ... N61: =IFERROR(N134/N99,"") | O61: =IFERROR(+AVERAGE(D61:N61),"") -> -0.027982343
B62: Cash Flow to Net Income | D62: =IFERROR(D134/D98,"") -> -0.39592453 | E62: =IFERROR(E134/E98,"") -> -1.0623143 | F62: =IFERROR(F134/F98,"") -> 0.27984068 | G62: =IFERROR(G134/G98,"") -> 0.50479114 | H62: =IFERROR(H134/H98,"") -> 0.086200242 | I62: =IFERROR(I134/I98,"") | J62: =IFERROR(J134/J98,"") | K62: =IFERROR(K134/K98,"") | ... N62: =IFERROR(N134/N98,"") | O62: =IFERROR(+AVERAGE(D62:N62),"") -> -0.11748136
B63: CFO to Net Income | D63: =+IFERROR(D128/D107,"") -> 1.5050639 | E63: =+IFERROR(E128/E107,"") -> 2.1707186 | F63: =+IFERROR(F128/F107,"") -> 10.934238 | G63: =+IFERROR(G128/G107,"") -> -0.80050267 | H63: =+IFERROR(H128/H107,"") -> 0.36843574 | I63: =+IFERROR(I128/I107,"") | J63: =+IFERROR(J128/J107,"") | K63: =+IFERROR(K128/K107,"") | ... N63: =+IFERROR(N128/N107,"") | O63: =IFERROR(+AVERAGE(D63:N63),"") -> 2.8355908
B64: Net Capex to CFO | D64: =IFERROR(-D129/D128,"") -> 0.55698267 | E64: =IFERROR(-E129/E128,"") -> 0.73261298 | F64: =IFERROR(-F129/F128,"") -> 0.98577723 | G64: =IFERROR(-G129/G128,"") -> 1.5056066 | H64: =IFERROR(-H129/H128,"") -> -0.99319671 | I64: =IFERROR(-I129/I128,"") | J64: =IFERROR(-J129/J128,"") | K64: =IFERROR(-K129/K128,"") | ... N64: =IFERROR(-N129/N128,"") | O64: =IFERROR(+AVERAGE(D64:N64),"") -> 0.55755656
B65: CFI to CFO | D65: =IFERROR(-D130/D128,"") -> 0.60426435 | E65: =IFERROR(-E130/E128,"") -> 1.1698912 | F65: =IFERROR(-F130/F128,"") -> 0.97672081 | G65: =IFERROR(-G130/G128,"") -> 1.4087239 | H65: =IFERROR(-H130/H128,"") -> -0.091836813 | I65: =IFERROR(-I130/I128,"") | J65: =IFERROR(-J130/J128,"") | K65: =IFERROR(-K130/K128,"") | ... N65: =IFERROR(-N130/N128,"") | O65: =IFERROR(+AVERAGE(D65:N65),"") -> 0.81355269
B66: Net Financing to CFO | D66: =IFERROR((D131+D132)/D128,"") -> 0.36036837 | E66: =IFERROR((E131+E132)/E128,"") -> 0.24807831 | F66: =IFERROR((F131+F132)/F128,"") -> 1.2036908 | G66: =IFERROR((G131+G132)/G128,"") -> 3.6763848 | H66: =IFERROR((H131+H132)/H128,"") -> -21.319069 | I66: =IFERROR((I131+I132)/I128,"") | J66: =IFERROR((J131+J132)/J128,"") | K66: =IFERROR((K131+K132)/K128,"") | ... N66: =IFERROR((N131+N132)/N128,"") | O66: =IFERROR(+AVERAGE(D66:N66),"") -> -3.1661093
B67: Debt Borrowing to Debt Repayment | D67: =+IFERROR(-D132/D131,"") -> 0.42626236 | E67: =+IFERROR(-E132/E131,"") -> -0.37228656 | F67: =+IFERROR(-F132/F131,"") -> 0.080623623 | G67: =+IFERROR(-G132/G131,"") -> -0.0045345916 | H67: =+IFERROR(-H132/H131,"") -> -0.066532721 | I67: =+IFERROR(-I132/I131,"") | J67: =+IFERROR(-J132/J131,"") | K67: =+IFERROR(-K132/K131,"") | ... N67: =+IFERROR(-N132/N131,"") | O67: =IFERROR(+AVERAGE(D67:N67),"") -> 0.012706421
B68: CFF to CFO | D68: =IFERROR(-D133/D128,"") -> 0.29211737 | E68: =IFERROR(-E133/E128,"") -> 0.10683642 | F68: =IFERROR(-F133/F128,"") -> 0.21652359 | G68: =IFERROR(-G133/G128,"") -> -0.016595649 | H68: =IFERROR(-H133/H128,"") -> 0.6360544 | I68: =IFERROR(-I133/I128,"") | J68: =IFERROR(-J133/J128,"") | K68: =IFERROR(-K133/K128,"") | ... N68: =IFERROR(-N133/N128,"") | O68: =IFERROR(+AVERAGE(D68:N68),"") -> 0.24698723
B69: Payout Ratio | D69: 0.0317 | E69: 0.2921 | F69: 0.11 | O69: =IFERROR(+AVERAGE(D69:N69),"") -> 0.1446
B71: Stock Information | D71: =+D29 -> SK | E71: =+E29 -> Samsung | F71: =+F29 -> MICRON | G71: =+G29 -> Kioxia | H71: =+H29 -> WESTERN | I71: =+I29 | J71: =+J29 | K71: =+K29 | ... O71: =+O29 -> Average
B73: (%) Float | D73: =540.52/690.35 -> 0.78296516 | E73: =5.57/5.92 -> 0.94087838 | F73: =1.11/1.12 -> 0.99107143 | G73: =80.02/539.06 -> 0.14844359 | H73: =344.89/347.82 -> 0.9915761 | O73: =IFERROR(+AVERAGE(D73:N73),"") -> 0.77098693
B74: β (Levered) | D74: {=IFERROR(_FV(D93,"Beta"),"")} -> 1.1446 | E74: {=IFERROR(_FV(E93,"Beta"),"")} -> 1.0683 | F74: {=IFERROR(_FV(F93,"Beta"),"")} -> 1.2168 | G74: {=IFERROR(_FV(G93,"Beta"),"")} -> 1.698 | H74: {=IFERROR(_FV(H93,"Beta"),"")} -> 1.4378 | I74: {=IFERROR(_FV(I93,"Beta"),"")} | J74: {=IFERROR(_FV(J93,"Beta"),"")} | K74: {=IFERROR(_FV(K93,"Beta"),"")} | ... N74: {=IFERROR(_FV(N93,"Beta"),"")} | O74: =IFERROR(+AVERAGE(D74:N74),"") -> 1.3131
B75: β (Unlevered) | D75: =IFERROR(D74/(1+(1-D106/D105)*(D123/D124)),"") -> 0.92239637 | E75: =IFERROR(E74/(1+(1-E106/E105)*(E123/E124)),"") -> 1.0231585 | F75: =IFERROR(F74/(1+(1-F106/F105)*(F123/F124)),"") -> 1.0152922 | G75: =IFERROR(G74/(1+(1-G106/G105)*(G123/G124)),"") -> 0.47803005 | H75: =IFERROR(H74/(1+(1-H106/H105)*(H123/H124)),"") -> 0.77695708 | I75: =IFERROR(I74/(1+(1-I106/I105)*(I123/I124)),"") | J75: =IFERROR(J74/(1+(1-J106/J105)*(J123/J124)),"") | K75: =IFERROR(K74/(1+(1-K106/K105)*(K123/K124)),"") | ... N75: =IFERROR(N74/(1+(1-N106/N105)*(N123/N124)),"") | O75: =IFERROR(+AVERAGE(D75:N75),"") -> 0.84316684
B76: % Held by Insiders | D76: 0.2042 | E76: 0.1007 | F76: 0.0027 | G76: 0.3352 | H76: 0.0071 | O76: =IFERROR(+AVERAGE(D76:N76),"") -> 0.12998
B77: % Held by Institutions | D77: 0.439 | E77: 0.3745 | F77: 0.8296 | G77: 0.5562 | H77: 0.9862 | O77: =IFERROR(+AVERAGE(D77:N77),"") -> 0.6371
B78: Short % Float | D78: 0 | E78: 0 | F78: 0.0277 | G78: 0 | H78: 0.1086 | O78: =IFERROR(+AVERAGE(D78:N78),"") -> 0.02726
B80: Stock Performance | D80: =+D29 -> SK | E80: =+E29 -> Samsung | F80: =+F29 -> MICRON | G80: =+G29 -> Kioxia | H80: =+H29 -> WESTERN | I80: =+I29 | J80: =+J29 | K80: =+K29 | ... O80: =+O29 -> Average
B82: 1 day | D82: {=IFERROR((D85/_xlfn.STOCKHISTORY(C6,TODAY()-1,TODAY()-1,0,0,1))-1,"Non-trading days")} -> Non-trading days | E82: {=IFERROR((E85/_xlfn.STOCKHISTORY(C8,TODAY()-1,TODAY()-1,0,0,1))-1,"Non-trading days")} -> Non-trading days | F82: {=IFERROR((F85/_xlfn.STOCKHISTORY(C9,TODAY()-1,TODAY()-1,0,0,1))-1,"Non-trading days")} -> -0.51701174 | G82: {=IFERROR((G85/_xlfn.STOCKHISTORY(C10,TODAY()-1,TODAY()-1,0,0,1))-1,"Non-trading days")} -> -0.67052023 | H82: {=IFERROR((K85/_xlfn.STOCKHISTORY(C11,TODAY()-1,TODAY()-1,0,0,1))-1,"Non-trading days")} -> Non-trading days | I82: {=IFERROR((L85/_xlfn.STOCKHISTORY(C12,TODAY()-1,TODAY()-1,0,0,1))-1,"Non-trading days")} -> Non-trading days | J82: {=IFERROR((M85/_xlfn.STOCKHISTORY(C13,TODAY()-1,TODAY()-1,0,0,1))-1,"Non-trading days")} -> Non-trading days | K82: {=IFERROR((N85/_xlfn.STOCKHISTORY(C14,TODAY()-1,TODAY()-1,0,0,1))-1,"Non-trading days")} -> Non-trading days | L82: {=IFERROR((L85/_xlfn.STOCKHISTORY(C15,TODAY()-1,TODAY()-1,0,0,1))-1,"Non-trading days")} -> Non-trading days | M82: {=IFERROR((M85/_xlfn.STOCKHISTORY(C16,TODAY()-1,TODAY()-1,0,0,1))-1,"Non-trading days")} -> Non-trading days | N82: {=IFERROR((N85/_xlfn.STOCKHISTORY(C17,TODAY()-1,TODAY()-1,0,0,1))-1,"Non-trading days")} -> Non-trading days | O82: =IFERROR(+AVERAGE(D82:N82),"") -> -0.59376599
B83: 1 month | D83: {=IFERROR((D85/_xlfn.STOCKHISTORY(C6,TODAY()-29,TODAY()-29,0,0,1))-1,"Non-trading days")} -> -0.39934853 | E83: {=IFERROR((E85/_xlfn.STOCKHISTORY(C8,TODAY()-29,TODAY()-29,0,0,1))-1,"Non-trading days")} -> -0.24114441 | F83: {=IFERROR((F85/_xlfn.STOCKHISTORY(C9,TODAY()-29,TODAY()-29,0,0,1))-1,"Non-trading days")} -> -0.38030138 | G83: {=IFERROR((G85/_xlfn.STOCKHISTORY(C10,TODAY()-29,TODAY()-29,0,0,1))-1,"Non-trading days")} -> -0.51282051 | H83: {=IFERROR((K85/_xlfn.STOCKHISTORY(C11,TODAY()-29,TODAY()-29,0,0,1))-1,"Non-trading days")} -> Non-trading days | I83: {=IFERROR((L85/_xlfn.STOCKHISTORY(C12,TODAY()-29,TODAY()-29,0,0,1))-1,"Non-trading days")} -> Non-trading days | J83: {=IFERROR((M85/_xlfn.STOCKHISTORY(C13,TODAY()-29,TODAY()-29,0,0,1))-1,"Non-trading days")} -> Non-trading days | K83: {=IFERROR((N85/_xlfn.STOCKHISTORY(C14,TODAY()-29,TODAY()-29,0,0,1))-1,"Non-trading days")} -> Non-trading days | L83: {=IFERROR((L85/_xlfn.STOCKHISTORY(C15,TODAY()-29,TODAY()-29,0,0,1))-1,"Non-trading days")} -> Non-trading days | M83: {=IFERROR((M85/_xlfn.STOCKHISTORY(C16,TODAY()-29,TODAY()-29,0,0,1))-1,"Non-trading days")} -> Non-trading days | N83: {=IFERROR((N85/_xlfn.STOCKHISTORY(C17,TODAY()-29,TODAY()-29,0,0,1))-1,"Non-trading days")} -> Non-trading days | O83: =IFERROR(AVERAGE(D83:N83),"") -> -0.38340371
B84: YTD | D84: {=IFERROR((D85/_xlfn.STOCKHISTORY(C6,"2025-01-02","2025-01-02",0,0,1))-1,"Non-trading days")} -> 0.077102804 | E84: {=IFERROR((E85/_xlfn.STOCKHISTORY(C8,"2025-01-02","2025-01-02",0,0,1))-1,"Non-trading days")} -> 0.043071161 | F84: {=IFERROR((F85/_xlfn.STOCKHISTORY(C9,"2025-01-02","2025-01-02",0,0,1))-1,"Non-trading days")} -> -0.086453681 | G84: {=IFERROR((G85/_xlfn.STOCKHISTORY(C10,"2025-01-02","2025-01-02",0,0,1))-1,"Non-trading days")} -> 0.17829457 | H84: {=IFERROR((K85/_xlfn.STOCKHISTORY(C11,"2025-01-02","2025-01-02",0,0,1))-1,"Non-trading days")} -> Non-trading days | I84: {=IFERROR((L85/_xlfn.STOCKHISTORY(C12,"2025-01-02","2025-01-02",0,0,1))-1,"Non-trading days")} -> Non-trading days | J84: {=IFERROR((M85/_xlfn.STOCKHISTORY(C13,"2025-01-02","2025-01-02",0,0,1))-1,"Non-trading days")} -> Non-trading days | K84: {=IFERROR((N85/_xlfn.STOCKHISTORY(C14,"2025-01-02","2025-01-02",0,0,1))-1,"Non-trading days")} -> Non-trading days | L84: {=IFERROR((L85/_xlfn.STOCKHISTORY(C15,"2025-01-02","2025-01-02",0,0,1))-1,"Non-trading days")} -> Non-trading days | M84: {=IFERROR((M85/_xlfn.STOCKHISTORY(C16,"2025-01-02","2025-01-02",0,0,1))-1,"Non-trading days")} -> Non-trading days | N84: {=IFERROR((N85/_xlfn.STOCKHISTORY(C17,"2025-01-02","2025-01-02",0,0,1))-1,"Non-trading days")} -> Non-trading days | O84: =IFERROR(AVERAGE(D84:N84),"") -> 0.053003714
B85: Current Price | D85: {=+IFERROR(_FV(D93,"Price"),"")} -> 184400 | E85: {=+IFERROR(_FV(E93,"Price"),"")} -> 55700 | F85: {=+IFERROR(_FV(F93,"Price"),"")} -> 79.78 | G85: {=+IFERROR(_FV(G93,"Price"),"")} -> 11.4 | H85: {=+IFERROR(_FV(H93,"Price"),"")} -> 40.78 | I85: {=+IFERROR(_FV(I93,"Price"),"")} | J85: {=+IFERROR(_FV(J93,"Price"),"")} | K85: {=+IFERROR(_FV(K93,"Price"),"")} | ... N85: {=+IFERROR(_FV(N93,"Price"),"")} | O85: =IFERROR(AVERAGE(D85:N85),"") -> 48046.392
B87: Extra
B89: Exposure to the US
B90: DRAM Revenue
B91: NAND Revenue
B93: Income Statement | D93: =+DCF!R4 -> #VALUE! | E93: #VALUE! | F93: #VALUE! | G93: #VALUE! | H93: #VALUE! | I93: PEER 5 | J93: PEER 6 | K93: PEER 7 | L93: PEER 8 | M93: PEER 9 | N93: PEER 10
B95: =+Inputs!$B$6&" ("&Inputs!O$4&")" -> Revenue (Sales) (2022) | D95: =+_xlfn.XLOOKUP("Revenue (Sales)",Inputs!$B:$B,Inputs!O:O) -> 44621.6 | E95: =+'Samsung IS'!B6 -> 302231.4 | F95: =+'Micron IS'!B6 -> 37846.7 | G95: =+'Kioxia IS'!B6 -> 15861.9 | H95: =+'WDC IS'!J6 /1000 -> 22609.7
B96: =+Inputs!$B$6&" ("&Inputs!P$4&")" -> Revenue (Sales) (2023) | D96: =+_xlfn.XLOOKUP("Revenue (Sales)",Inputs!$B:$B,Inputs!P:P) -> 32765.7 | E96: =+'Samsung IS'!C6 -> 258935.5 | F96: =+'Micron IS'!C6 -> 20534.2 | G96: =+'Kioxia IS'!C6 -> 12397.2 | H96: =+'WDC IS'!K6/1000 -> 16299.7
B97: EBITDA (2023) | D97: =+_xlfn.XLOOKUP("EBITDA",Inputs!$B:$B,Inputs!P:P) -> -7143.3 | E97: =+'Samsung IS'!C67 -> 45233.5 | F97: =+'Micron IS'!C67 -> 3258.5 | G97: =+'Kioxia IS'!C66 -> 3103.9 | H97: =+'WDC IS'!K67/1000 -> -202.456
B98: Net Income (2023) | D98: =+_xlfn.XLOOKUP("Net Income",Inputs!$B:$B,Inputs!P:P) -> -9137.6 | E98: =+'Samsung IS'!C46 -> 14473.4 | F98: =+'Micron IS'!C46 -> -7707.6 | G98: =+'Kioxia IS'!C45 -> -1335.8 | H98: =+'WDC IS'!K46/1000 -> -2228.3
B99: =+Inputs!$B$6&" ("&Inputs!Q$4&")" -> Revenue (Sales) (2024) | D99: =+_xlfn.XLOOKUP("Revenue (Sales)",Inputs!$B:$B,Inputs!Q:Q) -> 66193 | E99: =+'Samsung IS'!D6 -> 300870.9 | F99: =+'Micron IS'!D6 -> 33766.9 | G99: =+'Kioxia IS'!D6 -> 9841.8 | H99: =+'WDC IS'!L6/1000 -> 17344.6
B100: COGS (Cost of Goods Sold) | D100: =+_xlfn.XLOOKUP($B100,Inputs!$B:$B,Inputs!Q:Q) -> 34364.8 | E100: =+'Samsung IS'!D8 -> 186562.3 | F100: =+'Micron IS'!D8 -> 26243.3 | G100: =+'Kioxia IS'!D8 -> 11024.2 | H100: =+'WDC IS'!L8/1000 -> 13416.2
B101: Gross Profit | D101: =+_xlfn.XLOOKUP($B101,Inputs!$B:$B,Inputs!Q:Q) -> 31828.2 | E101: =+E99-E100 -> 114308.6 | F101: =+F99-F100 -> 7523.6 | G101: =G99-G100 -> -1182.4 | H101: =+H99-H100 -> 3928.4 | I101: =I99-I100 -> 0 | J101: =+J99-J100 -> 0 | K101: =+K99-K100 -> 0 | L101: =+L99-L100 -> 0 | M101: =+M99-M100 -> 0 | N101: =+N99-N100 -> 0
B102: EBITDA | D102: =+_xlfn.XLOOKUP($B102,Inputs!$B:$B,Inputs!Q:Q) -> 24027 | E102: =+'Samsung IS'!D67 -> 75356.8 | F102: =+'Micron IS'!D67 -> 12080.8 | G102: =+'Kioxia IS'!D66 -> 736.6 | H102: =+'WDC IS'!L67/1000 -> 1267.2
B103: Operating Income (EBIT) | D103: =+_xlfn.XLOOKUP($B103,Inputs!$B:$B,Inputs!Q:Q) -> 23467.4 | E103: =+'Samsung IS'!D70 -> 32726 | F103: =+'Micron IS'!D16 -> 1430.8 | G103: =+'Kioxia IS'!D19 -> -2427 | H103: =+'WDC IS'!L16/1000 -> 424.177
B104: Net Interest Expense (Income) | D104: =+_xlfn.XLOOKUP($B104,Inputs!$B:$B,Inputs!Q:Q) -> 1000.4 | E104: =+'Samsung IS'!D22 -> -3915.2 | F104: =+'Micron IS'!D18 -> 44.4 | G104: =+'Kioxia IS'!D21 -> 438.4 | H104: =+'WDC IS'!L18/1000 -> 504.21
B105: Pre-Tax Income (EBT) | D105: =+_xlfn.XLOOKUP($B105,Inputs!$B:$B,Inputs!Q:Q) -> 23885.5 | E105: =+'Samsung IS'!D35 -> 37529.7 | F105: =+'Micron IS'!D35 -> 1667.4 | G105: =+'Kioxia IS'!D35 -> -3138.6 | H105: ='WDC IS'!L35/1000 -> -881.7
B106: Tax Expense (Benefits) | D106: =+_xlfn.XLOOKUP($B106,Inputs!$B:$B,Inputs!Q:Q) -> 4088.4 | E106: =+'Samsung IS'!D36 -> 3078.4 | F106: =+'Micron IS'!D36 -> 606.5 | G106: =+'Kioxia IS'!D36 -> -910.6 | H106: =+'WDC IS'!L36/1000 -> 182.743
B107: Net Income | D107: =+_xlfn.XLOOKUP($B107,Inputs!$B:$B,Inputs!Q:Q) -> 19797.1 | E107: =+'Samsung IS'!D46 -> 33621.4 | F107: =+'Micron IS'!D46 -> 1046.2 | G107: =+'Kioxia IS'!D45 -> -2228.1 | H107: =+'WDC IS'!L46/1000 -> -1064.4
B108: EPS basic | D108: =+_xlfn.XLOOKUP($B108,Inputs!$B:$B,Inputs!Q:Q) -> 28732 | E108: =+'Samsung IS'!D56 -> 4950 | F108: =+'Micron IS'!D56 -> 941.29 | G108: =+'Kioxia IS'!D55 -> -4305.45 | H108: =+'WDC IS'!L56/1000 -> -3.48145
B109: R&D (Research & Development) | D109: =+_xlfn.XLOOKUP($B109,Inputs!$B:$B,Inputs!Q:Q) -> 4436.3 | E109: =+'Samsung IS'!D17 -> 34998.1 | F109: =+'Micron IS'!D14 -> 4612.3 | G109: =+'Kioxia IS'!D16 -> 522.7 | H109: =+'WDC IS'!L14/1000 -> 2543.7
B111: Balance Sheet
B113: Cash & Cash Equivalents | D113: =+_xlfn.XLOOKUP($B113,Inputs!$B:$B,Inputs!Q:Q) -> 11205.1 | E113: =+'Samsung BS'!D8 -> 53705.6 | F113: =+'Micron BS'!D7 -> 10803.9 | G113: =+'Kioxia BS'!D8 -> 1619.5 | H113: =+'WDC BS'!O8/1000 -> 2591.4
B114: Accounts Receivable | D114: =+_xlfn.XLOOKUP($B114,Inputs!$B:$B,Inputs!Q:Q) -> 13019 | E114: =+'Samsung BS'!D11 -> 43623.1 | F114: =+'Micron BS'!D11 -> 7222.6 | G114: =+'Kioxia BS'!D10 -> 1135.8 | H114: =+'WDC BS'!O11/1000 -> 2987.2
B115: Beginning Inventory | D115: =+_xlfn.XLOOKUP("Inventory",Inputs!$B:$B,Inputs!P:P) -> 13480.7 | E115: =+'Samsung BS'!C13 -> 51625.9 | F115: =+'Micron BS'!C13 -> 11119.7 | G115: =+'Kioxia BS'!C11 -> 3575.2 | H115: =+'WDC BS'!N13/1000 -> 4873.8
B116: Ending Inventory | D116: =+_xlfn.XLOOKUP("Inventory",Inputs!$B:$B,Inputs!Q:Q) -> 13313.9 | E116: =+'Samsung BS'!D13 -> 51754.9 | F116: =+'Micron BS'!D13 -> 11828.9 | G116: =+'Kioxia BS'!D11 -> 2417.6 | H116: =+'WDC BS'!O13/1000 -> 4609.1
B117: Current Assets | D117: =+_xlfn.XLOOKUP($B117,Inputs!$B:$B,Inputs!Q:Q) -> 42278.9 | E117: =+'Samsung BS'!D22 -> 227062.3 | F117: =+'Micron BS'!D23 -> 32483.7 | G117: =+'Kioxia BS'!D18 -> 5794.2 | H117: =+'WDC BS'!O22/1000 -> 11115.9
B118: Net PP&E (Property, Plant and Equipment) | D118: =+_xlfn.XLOOKUP($B118,Inputs!$B:$B,Inputs!Q:Q) -> 62644.3 | E118: =+'Samsung BS'!D23 -> 205945.2 | F118: =+'Micron BS'!D24 -> 53838.3 | G118: =+'Kioxia BS'!D19 -> 11817.4 | H118: =+'WDC BS'!O23/1000 -> 4817.3
B119: Total Assets | D119: =+_xlfn.XLOOKUP($B119,Inputs!$B:$B,Inputs!Q:Q) -> 119855.2 | E119: =+'Samsung BS'!D39 -> 514531.9 | F119: =+'Micron BS'!D38 -> 92519.7 | G119: =+'Kioxia BS'!D33 -> 25484.8 | H119: =+'WDC BS'!O36/1000 -> 33358.6
B120: Accounts Payable | D120: =+_xlfn.XLOOKUP($B120,Inputs!$B:$B,Inputs!Q:Q) -> 2277.3 | E120: =+'Samsung BS'!D43 -> 12370.2 | F120: =+'Micron BS'!D42 -> 3633.3 | G120: =+'Kioxia BS'!D37 -> 1004.3 | H120: =+'WDC BS'!O40/1000 -> 1946
B121: Current Liabilities | D121: =+_xlfn.XLOOKUP($B121,Inputs!$B:$B,Inputs!Q:Q) -> 24965.4 | E121: =+'Samsung BS'!D56 -> 93326.3 | F121: =+'Micron BS'!D56 -> 12326 | G121: =+'Kioxia BS'!D49 -> 16599.9 | H121: =+'WDC BS'!O54/1000 -> 8394.8
B122: Long-term debt | D122: =+_xlfn.XLOOKUP($B122,Inputs!$B:$B,Inputs!Q:Q) -> 19611.5 | E122: =+'Samsung BS'!D57 -> 3950.4 | F122: =+'Micron BS'!D57 -> 18094.5 | G122: =+'Kioxia BS'!D50 -> 3805.2 | H122: =+'WDC BS'!O55/1000 -> 8262.4
B123: Total Debt | D123: =+_xlfn.XLOOKUP($B123,Inputs!$B:$B,Inputs!Q:Q,,,-1) -> 21483.4 | E123: =+'Samsung BS'!D57+'Samsung BS'!D46 -> 19330.2 | F123: =+'Micron BS'!D57+'Micron BS'!D46 -> 18763.6 | G123: =+'Kioxia BS'!D50+'Kioxia BS'!D41 -> 14383.4 | H123: =+('WDC BS'!O55+'WDC BS'!O44)/1000 -> 10733.8
B124: Shareholder's Equity | D124: =+_xlfn.XLOOKUP($B124,Inputs!$B:$B,Inputs!Q:Q) -> 73915.7 | E124: =+'Samsung BS'!D81 -> 402192.1 | F124: =+'Micron BS'!D82 -> 60152 | G124: =+'Kioxia BS'!D70 -> 4000.8 | H124: =+'WDC BS'!O80/1000 -> 15235.4
B126: Cash Flow Statement
B128: Operating Cash Flow | D128: =+_xlfn.XLOOKUP($B128,Inputs!$B:$B,Inputs!Q:Q) -> 29795.9 | E128: =+'Samsung CF'!D17 -> 72982.6 | F128: =+'Micron CF'!D19 -> 11439.4 | G128: =+'Kioxia CF'!D17 -> 1783.6 | H128: =+'WDC CF'!N19/1000 -> -392.163
...

Sheet ESG
B2: Environmental, Social and Governance Analysis
B4: Author: | C4: João Branco | E4: Highlights | N4: Recent News
B6: Overview | D6: .
B7: Last Update | C7: 45767 | D7: .
B8: Latest year with data | C8: 2024
B9: GICS Sector | C9: Informational Technology
B10: GICS Industry Group | C10: Semiconductor Equipment
B11: Final Review
B13: ESG Scores
B14: LSEG ESG Score | C14: 70
B15: E-Score | C15: 57
B16: S-Score | C16: 66 | E16: GHG Scope 1 and 2 Emissions: | N16: Water, Waste, Energy Management:
B17: G-Score | C17: 94
B18: S&P Global ESG Score | C18: 56
B19: Environmental | C19: 53
B20: Social | C20: 60
B21: Governance & Economic | C21: 56
B22: Sustainalytics | C22: 17.3
B23: ISS ESG Corporate Rating | C23: C+
B24: SDG Impact Rating | C24: 3.7
B25: Governance Quality Score | C25: 1
B26: MSCI ESG Ratings | C26: A
B29: Industry ESG Overview:
E33: ENVIRONMENTAL
G35: Overview | H35: Targets | K35: Improvements | O35: Comments
E36: GHG (or CO2) Scope 1 Emissions | H36: SK Hynix wants to reduce their GHG emissions by 40% until 2030 | K36: The company was able to reduce their GHG Scope 1 emissions by 25% between 2022 and 2023. | O36: The company has been able to keep reducing the GHG scope 1 emissions and keep values low when compared to their competitors.
E38: Water Consumption | H38: The company wants to conserve 600 million tons of water by 2030 | K38: The company was able to reduce their water consumption by 9% between 2022 and 2023. | O38: Although the company was able to reduce their water consumption they still maintain very high levels of consumption.
E40: Energy Consumption | H40: The company wants to create energy saving of 3000 GWh by 2030. | K40: The company increased the energy consumption by 36% | O40: The company keeps the 2nd highest energy consumption when compared to the other companies.
E42: Waste Management | K42: The company reduced their waste by 18%. | O42: Even though the company reduced their waste, they still are the 2nd company that produces more waste.
E44: Other
E46: SOCIAL
B48: Important Sources: | G48: Overview | H48: Targets | K48: Improvements | O48: Comments
B49: Annual Report | E49: Employee Turnover % | G49: Not Reported
B50: Sustainability Report | D50: .
B51: Proxy Statement | D51: . | E51: Salaries & Compensation | O51: The company has a higher salary when compared to the industry, paying 1$ extra per hour.
E53: Reputation | K53: Brand is well known for its high quality and being ahead in technology. | O53: Overall the company is well known and has a good reputation.
E55: Discrimination Events | O55: Could not find any information about discrimination events at Hynix.
E57: Work Safety | O57: There were only two accidents, one in 2015 killing 3 people and the other was in 2020 injuring 3 people.
E59: Damage to consumer health | O59: Hynix products cause no damages to consumer health.
E61: Pension Plan | O61: Could not find anything related to the Pension plan.
E63: Supply chain | O63: Could not find any information about problems with suppliers at Hynix.
E65: Community involvement | O65: The company spent 82954 euros on comunity this year in things like an "Happy Lunchbox", an Handball League for Individuals with Developmental Disabilities etc.
E67: Public Sector
E69: Litigation | O69: The company is currently facing a lawsuit over patent infringement. SK hynix sold around 1,500 semiconductor patents to Mimir IP, a non-practicing entity (NPE) which buy patents to sue companies for infrigement and extract settlements.
E71: GOVERNANCE
G73: Overview | H73: Targets | K73: Improvements | O73: Comments
E74: Diversity (Gender, Age, Industry, Region) | K74: The percentage of women has remained more or less the same. | O74: 35% of their workers are Women.
E76: % Independence | K76: There is one less independent member on the board when compared to last year. | O76: 6 out of 10 members of the board are independent.
E78: Average time as independent directors | O78: The average time as independent director is 3 years.
E80: Departures of C-level executives | O80: The CEO changed in 2022.
E82: CEO/Chairman duality | O82: The CEO and the chairman are two diferent people.
E84: Transparency when reporting | O84: Overall it was very easy to find specific information but the company lacks some crucial information.
E86: Time taken to report | O86: ESG/Corporate Governance reports took 8 months to report. Financials are released within 1 month
E88: CEO or Chairman in other boards? | O88: The CEO and the Chairman are not part of other boards.
E90: Audit / Consulting
E92: ESG-compensation related | G92: Not reported
E94: Management compensation schemes | O94: The company has performance based compensation. It is important to highlight the huge gap between the compensation that the board receive and the employees. It is also important to keep an eye on the fact that Park Sung-wook earned most of his pay from stock options, not salary
E96: BOARD
E98: moved to a separate sheet due to formatting

Sheet ESG Inputs
B2: ESG Inputs
A4: x | B4: Total GHG Scope 1 Emissions | G4: 2014 | H4: =+G4+1 -> 2015 | I4: =+H4+1 -> 2016 | J4: =+I4+1 -> 2017 | K4: =+J4+1 -> 2018 | L4: =+K4+1 -> 2019 | M4: =+L4+1 -> 2020 | N4: =+M4+1 -> 2021 | O4: =+N4+1 -> 2022 | ... Q4: =+P4+1 -> 2024 | R4: ="CAGR "&$G$4&" - "&$Q$4 -> CAGR 2014 - 2024
B6: =+Peers!B6 -> SK hynix Inc. | G6: 1645 | H6: 1726 | I6: 1691 | J6: 1710 | K6: 1959 | L6: 2126 | M6: 2711 | N6: 2629 | O6: 2943 | P6: 2338 | R6: =IFERROR((Q6/G6)^(1/COUNT($G$4:$Q$4))-1,"") -> -1
B7: =+Peers!B8 -> Samsung Electronics Co., Ltd. | G7: 2620 | H7: 2445 | I7: 2554 | J7: 3668 | K7: 4855 | L7: 5067 | M7: 5726 | N7: 7604 | O7: 5972 | P7: 3733 | R7: =IFERROR((Q7/G7)^(1/COUNT($G$4:$Q$4))-1,"") -> -1
B8: =+Peers!B9 -> MICRON TECHNOLOGY, INC. | H8: 1415 | I8: 1724 | J8: 2844 | K8: 2946 | L8: 3195 | M8: 3048 | N8: 3340 | O8: 3478 | P8: 2699 | R8: =IFERROR((Q8/G8)^(1/COUNT($G$4:$Q$4))-1,"")
B9: =+Peers!B10 -> Kioxia Holdings Corporation | R9: =IFERROR((Q9/G9)^(1/COUNT($G$4:$Q$4))-1,"")
B10: =+Peers!B11 -> WESTERN DIGITAL CORPORATION | G10: 55 | H10: 29 | I10: 45 | J10: 50 | K10: 46 | L10: 51 | M10: 45 | N10: 46 | O10: 48 | P10: 107 | R10: =IFERROR((Q10/G10)^(1/COUNT($G$4:$Q$4))-1,"") -> -1
B11: =+Peers!B12 | R11: =IFERROR((Q11/G11)^(1/COUNT($G$4:$Q$4))-1,"")
B12: =+Peers!B13 | R12: =IFERROR((Q12/G12)^(1/COUNT($G$4:$Q$4))-1,"")
B13: =+Peers!B14 | R13: =IFERROR((Q13/G13)^(1/COUNT($G$4:$Q$4))-1,"")
B14: =+Peers!B15 | R14: =IFERROR((Q14/G14)^(1/COUNT($G$4:$Q$4))-1,"")
B15: =+Peers!B16 | R15: =IFERROR((Q15/G15)^(1/COUNT($G$4:$Q$4))-1,"")
B16: =+Peers!B17 | R16: =IFERROR((Q16/G16)^(1/COUNT($G$4:$Q$4))-1,"")
A18: x | B18: Total GHG Scope 2 (Location-Based) Emissions | G18: 2014 | H18: =+G18+1 -> 2015 | I18: =+H18+1 -> 2016 | J18: =+I18+1 -> 2017 | K18: =+J18+1 -> 2018 | L18: =+K18+1 -> 2019 | M18: =+L18+1 -> 2020 | N18: =+M18+1 -> 2021 | O18: =+N18+1 -> 2022 | ... Q18: =+P18+1 -> 2024 | R18: ="CAGR "&$G$4&" - "&$Q$4 -> CAGR 2014 - 2024
B20: =+$B$6 -> SK hynix Inc. | G20: 2741 | H20: 2997 | I20: 3251 | J20: 3378 | K20: 3956 | L20: 4713 | M20: 4837 | N20: 5214 | O20: 6140 | P20: 4987 | R20: =IFERROR((Q20/G20)^(1/COUNT($G$4:$Q$4))-1,"") -> -1
B21: =+$B$7 -> Samsung Electronics Co., Ltd. | G21: 6670 | H21: 7747 | I21: 9046 | J21: 9917 | N21: 12566 | O21: 13920 | P21: 14570 | R21: =IFERROR((Q21/G21)^(1/COUNT($G$4:$Q$4))-1,"") -> -1
B22: =+$B$8 -> MICRON TECHNOLOGY, INC. | H22: 1619 | I22: 1971 | J22: 2455 | K22: 2673 | L22: 2856 | M22: 3099 | N22: 3449 | O22: 3865 | P22: 3937 | R22: =IFERROR((Q22/G22)^(1/COUNT($G$4:$Q$4))-1,"")
B23: =+$B$9 -> Kioxia Holdings Corporation | R23: =IFERROR((Q23/G23)^(1/COUNT($G$4:$Q$4))-1,"")
B24: =+$B$10 -> WESTERN DIGITAL CORPORATION | G24: 1041 | H24: 933 | I24: 1127 | J24: 1081 | K24: 1110 | L24: 970 | M24: 958 | N24: 999 | O24: 1019 | R24: =IFERROR((Q24/G24)^(1/COUNT($G$4:$Q$4))-1,"") -> -1
B25: =+$B$11 | R25: =IFERROR((Q25/G25)^(1/COUNT($G$4:$Q$4))-1,"")
B26: =+$B$12 | R26: =IFERROR((Q26/G26)^(1/COUNT($G$4:$Q$4))-1,"")
B27: =+$B$13 | R27: =IFERROR((Q27/G27)^(1/COUNT($G$4:$Q$4))-1,"")
B28: =+$B$14 | R28: =IFERROR((Q28/G28)^(1/COUNT($G$4:$Q$4))-1,"")
B29: =+$B$15 | R29: =IFERROR((Q29/G29)^(1/COUNT($G$4:$Q$4))-1,"")
B30: =+$B$16 | R30: =IFERROR((Q30/G30)^(1/COUNT($G$4:$Q$4))-1,"")
A32: x | B32: Total Energy Usage | G32: 2014 | H32: =+G32+1 -> 2015 | I32: =+H32+1 -> 2016 | J32: =+I32+1 -> 2017 | K32: =+J32+1 -> 2018 | L32: =+K32+1 -> 2019 | M32: =+L32+1 -> 2020 | N32: =+M32+1 -> 2021 | O32: =+N32+1 -> 2022 | ... Q32: =+P32+1 -> 2024 | R32: ="CAGR "&$G$4&" - "&$Q$4 -> CAGR 2014 - 2024
B34: =+$B$6 -> SK hynix Inc. | G34: 14408 | H34: 6641 | I34: 7391 | J34: 8123 | K34: 9713 | L34: 11053 | M34: 11765 | N34: 13160 | O34: 14768 | P34: 20049 | R34: =IFERROR((Q34/G34)^(1/COUNT($G$4:$Q$4))-1,"") -> -1
B35: =+$B$7 -> Samsung Electronics Co., Ltd. | G35: 16485 | H35: 19006 | I35: 21073 | J35: 23420 | K35: 26028 | L35: 27452 | M35: 29025 | N35: 32322 | O35: 35177 | P35: 36399 | R35: =IFERROR((Q35/G35)^(1/COUNT($G$4:$Q$4))-1,"") -> -1
B36: =+$B$8 -> MICRON TECHNOLOGY, INC. | I36: 6695 | J36: 7432 | K36: 7951 | L36: 8563 | M36: 9399 | N36: 10418 | O36: 11140 | P36: 11389 | R36: =IFERROR((Q36/G36)^(1/COUNT($G$4:$Q$4))-1,"")
B37: =+$B$9 -> Kioxia Holdings Corporation | R37: =IFERROR((Q37/G37)^(1/COUNT($G$4:$Q$4))-1,"")
B38: =+$B$10 -> WESTERN DIGITAL CORPORATION | I38: 2219 | J38: 2331 | K38: 2215 | L38: 2067 | M38: 2034 | N38: 2101 | O38: 2161 | P38: 1916 | R38: =IFERROR((Q38/G38)^(1/COUNT($G$4:$Q$4))-1,"")
B39: =+$B$11 | R39: =IFERROR((Q39/G39)^(1/COUNT($G$4:$Q$4))-1,"")
B40: =+$B$12 | R40: =IFERROR((Q40/G40)^(1/COUNT($G$4:$Q$4))-1,"")
B41: =+$B$13 | R41: =IFERROR((Q41/G41)^(1/COUNT($G$4:$Q$4))-1,"")
B42: =+$B$14 | R42: =IFERROR((Q42/G42)^(1/COUNT($G$4:$Q$4))-1,"")
B43: =+$B$15 | R43: =IFERROR((Q43/G43)^(1/COUNT($G$4:$Q$4))-1,"")
B44: =+$B$16 | R44: =IFERROR((Q44/G44)^(1/COUNT($G$4:$Q$4))-1,"")
A46: x | B46: Total Water Consumption | G46: 2014 | H46: =+G46+1 -> 2015 | I46: =+H46+1 -> 2016 | J46: =+I46+1 -> 2017 | K46: =+J46+1 -> 2018 | L46: =+K46+1 -> 2019 | M46: =+L46+1 -> 2020 | N46: =+M46+1 -> 2021 | O46: =+N46+1 -> 2022 | ... Q46: =+P46+1 -> 2024 | R46: ="CAGR "&$G$4&" - "&$Q$4 -> CAGR 2014 - 2024
B48: =+$B$6 -> SK hynix Inc. | K48: 13854 | L48: 14720 | M48: 13418 | N48: 17982 | O48: 20851 | P48: 19198 | R48: =IFERROR((Q48/G48)^(1/COUNT($G$4:$Q$4))-1,"")
B49: =+$B$7 -> Samsung Electronics Co., Ltd. | H49: 19831 | I49: 22537 | J49: 24700 | K49: 26531 | L49: 26020 | M49: 33093 | N49: 32706 | O49: 36691 | P49: 34356 | R49: =IFERROR((Q49/G49)^(1/COUNT($G$4:$Q$4))-1,"")
B50: =+$B$8 -> MICRON TECHNOLOGY, INC. | K50: 10343 | L50: 11185 | M50: 12196 | N50: 12811 | O50: 14590 | P50: 14319 | R50: =IFERROR((Q50/G50)^(1/COUNT($G$4:$Q$4))-1,"")
B51: =+$B$9 -> Kioxia Holdings Corporation | R51: =IFERROR((Q51/G51)^(1/COUNT($G$4:$Q$4))-1,"")
B52: =+$B$10 -> WESTERN DIGITAL CORPORATION | K52: 9856 | L52: 9106 | M52: 6482 | N52: 7231 | O52: 6939 | P52: 5480 | R52: =IFERROR((Q52/G52)^(1/COUNT($G$4:$Q$4))-1,"")
B53: =+$B$11 | R53: =IFERROR((Q53/G53)^(1/COUNT($G$4:$Q$4))-1,"")
B54: =+$B$12 | R54: =IFERROR((Q54/G54)^(1/COUNT($G$4:$Q$4))-1,"")
B55: =+$B$13 | R55: =IFERROR((Q55/G55)^(1/COUNT($G$4:$Q$4))-1,"")
B56: =+$B$14 | R56: =IFERROR((Q56/G56)^(1/COUNT($G$4:$Q$4))-1,"")
B57: =+$B$15 | R57: =IFERROR((Q57/G57)^(1/COUNT($G$4:$Q$4))-1,"")
B58: =+$B$16 | R58: =IFERROR((Q58/G58)^(1/COUNT($G$4:$Q$4))-1,"")
A60: x | B60: Total Waste Production | G60: 2014 | H60: =+G60+1 -> 2015 | I60: =+H60+1 -> 2016 | J60: =+I60+1 -> 2017 | K60: =+J60+1 -> 2018 | L60: =+K60+1 -> 2019 | M60: =+L60+1 -> 2020 | N60: =+M60+1 -> 2021 | O60: =+N60+1 -> 2022 | ... Q60: =+P60+1 -> 2024 | R60: ="CAGR "&$G$4&" - "&$Q$4 -> CAGR 2014 - 2024
B62: =+$B$6 -> SK hynix Inc. | G62: 158 | H62: 189 | I62: 192 | J62: 295 | K62: 442 | L62: 413 | M62: 468 | N62: 505 | O62: 590 | P62: 501 | R62: =IFERROR((Q62/G62)^(1/COUNT($G$4:$Q$4))-1,"") -> -1
B63: =+$B$7 -> Samsung Electronics Co., Ltd. | G63: 778 | H63: 937 | I63: 1078 | J63: 1147 | K63: 1211 | L63: 1099 | M63: 1182 | N63: 1325 | O63: 1413 | P63: 1315 | R63: =IFERROR((Q63/G63)^(1/COUNT($G$4:$Q$4))-1,"") -> -1
B64: =+$B$8 -> MICRON TECHNOLOGY, INC. | H64: 95 | I64: 131 | J64: 192 | K64: 163 | L64: 183 | M64: 198 | N64: 223 | O64: 234 | P64: 196 | R64: =IFERROR((Q64/G64)^(1/COUNT($G$4:$Q$4))-1,"")
B65: =+$B$9 -> Kioxia Holdings Corporation | R65: =IFERROR((Q65/G65)^(1/COUNT($G$4:$Q$4))-1,"")
B66: =+$B$10 -> WESTERN DIGITAL CORPORATION | O66: 24 | P66: 20 | R66: =IFERROR((Q66/G66)^(1/COUNT($G$4:$Q$4))-1,"")
B67: =+$B$11 | R67: =IFERROR((Q67/G67)^(1/COUNT($G$4:$Q$4))-1,"")
B68: =+$B$12 | R68: =IFERROR((Q68/G68)^(1/COUNT($G$4:$Q$4))-1,"")
B69: =+$B$13 | R69: =IFERROR((Q69/G69)^(1/COUNT($G$4:$Q$4))-1,"")
B70: =+$B$14 | R70: =IFERROR((Q70/G70)^(1/COUNT($G$4:$Q$4))-1,"")
B71: =+$B$15 | R71: =IFERROR((Q71/G71)^(1/COUNT($G$4:$Q$4))-1,"")
B72: =+$B$16 | R72: =IFERROR((Q72/G72)^(1/COUNT($G$4:$Q$4))-1,"")
A74: x | B74: GHG Scope 1 and 2 Emissions | G74: 2014 | H74: =+G74+1 -> 2015 | I74: =+H74+1 -> 2016 | J74: =+I74+1 -> 2017 | K74: =+J74+1 -> 2018 | L74: =+K74+1 -> 2019 | M74: =+L74+1 -> 2020 | N74: =+M74+1 -> 2021 | O74: =+N74+1 -> 2022 | ... Q74: =+P74+1 -> 2024 | R74: ="CAGR "&$G$4&" - "&$Q$4 -> CAGR 2014 - 2024
B76: =+$B$6 -> SK hynix Inc. | G76: =+G6+G20 -> 4386 | H76: =+H6+H20 -> 4723 | I76: =+I6+I20 -> 4942 | J76: =+J6+J20 -> 5088 | K76: =+K6+K20 -> 5915 | L76: =+L6+L20 -> 6839 | M76: =+M6+M20 -> 7548 | N76: =+N6+N20 -> 7843 | ... Q76: =+Q6+Q20 -> 0 | R76: =IFERROR((Q76/G76)^(1/COUNT($G$4:$Q$4))-1,"") -> -1
B77: =+$B$7 -> Samsung Electronics Co., Ltd. | G77: =+G7+G21 -> 9290 | H77: =+H7+H21 -> 10192 | I77: =+I7+I21 -> 11600 | J77: =+J7+J21 -> 13585 | K77: =+K7+K21 -> 4855 | L77: =+L7+L21 -> 5067 | M77: =+M7+M21 -> 5726 | N77: =+N7+N21 -> 20170 | ... Q77: =+Q7+Q21 -> 0 | R77: =IFERROR((Q77/G77)^(1/COUNT($G$4:$Q$4))-1,"") -> -1
B78: =+$B$8 -> MICRON TECHNOLOGY, INC. | G78: =+G8+G22 -> 0 | H78: =+H8+H22 -> 3034 | I78: =+I8+I22 -> 3695 | J78: =+J8+J22 -> 5299 | K78: =+K8+K22 -> 5619 | L78: =+L8+L22 -> 6051 | M78: =+M8+M22 -> 6147 | N78: =+N8+N22 -> 6789 | ... Q78: =+Q8+Q22 -> 0 | R78: =IFERROR((Q78/G78)^(1/COUNT($G$4:$Q$4))-1,"")
B79: =+$B$9 -> Kioxia Holdings Corporation | G79: =+G9+G23 -> 0 | H79: =+H9+H23 -> 0 | I79: =+I9+I23 -> 0 | J79: =+J9+J23 -> 0 | K79: =+K9+K23 -> 0 | L79: =+L9+L23 -> 0 | M79: =+M9+M23 -> 0 | N79: =+N9+N23 -> 0 | ... Q79: =+Q9+Q23 -> 0 | R79: =IFERROR((Q79/G79)^(1/COUNT($G$4:$Q$4))-1,"")
B80: =+$B$10 -> WESTERN DIGITAL CORPORATION | G80: =+G10+G24 -> 1096 | H80: =+H10+H24 -> 962 | I80: =+I10+I24 -> 1172 | J80: =+J10+J24 -> 1131 | K80: =+K10+K24 -> 1156 | L80: =+L10+L24 -> 1021 | M80: =+M10+M24 -> 1003 | N80: =+N10+N24 -> 1045 | ... Q80: =+Q10+Q24 -> 0 | R80: =IFERROR((Q80/G80)^(1/COUNT($G$4:$Q$4))-1,"") -> -1
B81: =+$B$11
B82: =+$B$12
B83: =+$B$13
B84: =+$B$14
B85: =+$B$15
B86: =+$B$16

Sheet DCF
B2: DCF
A4: x | B4: Key Assumptions | R4: #VALUE!
B6: Switches | E6: Bear Case | H6: Base Case | K6: Bull Case | X6: FCFF | Y6: FCFE | Z6: Tax Shield | AA6: Total Payout | AB6: NOPAT | AC6: Debt Borrowing | AD6: Cash Balance | AE6: Total Assets | AF6: Total Liabilities | AG6: Shareholder's Equity | AH6: Current Liabilities | AI6: Current Assets
B7: Revenue | C7: 2 | E7: Revenue | F7: -0.02 | H7: Revenue | K7: Revenue | L7: 0.02 | S7: Most Recent Fiscal Year | T7: 45657 | W7: 2022 | X7: =+E197 -> -18020.111 | Y7: =+E250 -> -4678.2 | Z7: =+H222 -> 0 | AA7: =+E263 -> -1669.2 | AB7: =+E187 -> 3813.4886 | AC7: =+E248 -> 14913.7 | AD7: =+E92 -> 6079.4
B8: EBIT | C8: 2 | E8: EBIT | F8: -0.01 | H8: EBIT | K8: EBIT | L8: 0.01 | S8: End of Fiscal Year | T8: 46022 | W8: =+W7+1 -> 2023 | X8: =+F197 -> -11746.579 | Y8: =+F250 -> 2424.9 | Z8: =+I222 -> 0 | AA8: =+F263 -> -801 | AB8: =+F187 -> -6059.179 | AC8: =+F248 -> 17249.9 | AD8: =+F92 -> 8691.1
B9: WACC | C9: 2 | E9: WACC | F9: =IFERROR(+I9+0.5%,"") -> 0.10043911 | H9: WACC | I9: =WACC!G27 -> 0.095439106 | K9: WACC | L9: =IFERROR(I9-0.5%,"") -> 0.090439106 | S9: Most Recent Quarter End Date | T9: 45747 | W9: =+W8+1 -> 2024 | X9: =+G197 -> -2620.2352 | Y9: =+G250 -> 24418.8 | Z9: =+J222 -> 0 | AA9: =+G263 -> -732.5 | AB9: =+G187 -> 19450.565 | AC9: =+G248 -> 26692.5 | AD9: =+G92 -> 13928 | AE9: =Inputs!Q48 -> 119855.2 | AF9: =+Inputs!Q60 -> 45939.5 | AG9: =+AE9-AF9 -> 73915.7 | AH9: =+Inputs!Q54 -> 24965.4 | AI9: =+Inputs!Q38 -> 42278.9
B10: TGR | C10: 2 | E10: TGR | F10: =+I10-0.5% -> 0.015 | H10: TGR | I10: 0.02 | K10: TGR | L10: =+I10+0.5% -> 0.025 | S10: Valuation Date | T10: 45765 | W10: =+W9+1 -> 2025 | X10: =+H197 -> -19797.861 | Y10: =+H250 -> -21069.213 | Z10: =+K222 -> 0 | AA10: =+H263 -> 0 | AB10: =+H187 -> 13452.632 | AC10: =+H248 -> 0 | AD10: =+H92 -> 1273.7703 | AE10: =Inputs!Q48+DCF!H92+DCF!H94+DCF!H97+DCF!H100+DCF!H103+DCF!H109-DCF!G92-DCF!G94-DCF!G97-DCF!G100-DCF!G103-DCF!G109 -> 119917.93 | AF10: =+Inputs!Q60+(DCF!H114+DCF!H117+DCF!H120+DCF!H122*DCF!G114*DCF!G117*DCF!G120*DCF!G122) -> 1.1400182e+19 | AG10: =+AE10-AF10 -> -1.1400182e+19 | AH10: =+AH9+H114+H117-G114-G117 -> 24861.684 | AI10: =+H92+H94+H97+H100 -> 36267.948
W11: =+W10+1 -> 2026 | X11: =+I197 -> -16549.139 | Y11: =+I250 -> 3555.0151 | Z11: =+L222 -> 0 | AA11: =+I263 -> 0 | AB11: =+I187 -> 17876.856 | AC11: =+I248 -> 21069.213 | AD11: =+I92 -> 8284.098 | AE11: =AE10+DCF!I92+DCF!I94+DCF!I97+DCF!I100+DCF!I103+DCF!I109-DCF!H92-DCF!H94-DCF!H97-DCF!H100-DCF!H103-DCF!H109 -> 139618.52 | AF11: =AF10+(DCF!I114+DCF!I117+DCF!I120+DCF!I122*DCF!H114*DCF!H117*DCF!H120*DCF!H122) -> 4.6070954e+19 | AG11: =+AE11-AF11 -> -4.6070954e+19 | AH11: =+AH10+I114+I117-H114-H117 -> 26990.835 | AI11: =+I92+I94+I97+I100 -> 49013.498
B12: WACC | C12: =CHOOSE(C9,F9,I9,L9) -> 0.095439106 | W12: =+W11+1 -> 2027 | X12: =+J197 -> -17456.426 | Y12: =+J250 -> -17871.817 | Z12: =+M222 -> 0 | AA12: =+J263 -> 0 | AB12: =+J187 -> 21023.034 | AC12: =+J248 -> 0 | AD12: =+J92 -> 198.41483
B13: TGR | C13: =CHOOSE(C10,F10,I10,L10) -> 0.02 | W13: =+W12+1 -> 2028 | X13: =+K197 -> -20855.577 | Y13: =+K250 -> -3980.5813 | Z13: =+N222 -> 0 | AA13: =+K263 -> 0 | AB13: =+K187 -> 23736.295 | AC13: =+K248 -> 17871.817 | AD13: =+K92 -> 4358.5569
G14: 1 | H14: 1 | I14: =+H14+1 -> 2 | J14: =+I14+1 -> 3 | K14: =+J14+1 -> 4 | L14: =+K14+1 -> 5 | M14: =+L14+1 -> 6 | N14: =+M14+1 -> 7 | O14: =+N14+1 -> 8 | P14: =+O14+1 -> 9 | Q14: =+P14+1 -> 10 | W14: =+W13+1 -> 2029 | X14: =+L197 -> -20764.463 | Y14: =+L250 -> -17663.214 | Z14: =+O222 -> 0 | AA14: =+L263 -> 0 | AB14: =+L187 -> 27315.227 | AC14: =+L248 -> 3980.5813 | AD14: =+L92 -> -5395.5747
A15: x | B15: DRAM | E15: 2022 | F15: =+E15+1 -> 2023 | G15: =+F15+1 -> 2024 | H15: =+G15+1 -> 2025 | I15: =+H15+1 -> 2026 | J15: =+I15+1 -> 2027 | K15: =+J15+1 -> 2028 | L15: =+K15+1 -> 2029 | M15: =+L15+1 -> 2030 | ... Q15: =+P15+1 -> 2034
B17: DRAM Market | E17: =+SUM(Peers!H169:K171)/1000 -> 124205.6 | F17: =+SUM(Peers!L169:O171)/1000 -> 79410.252 | G17: =+SUM(Peers!P169:S171)/1000 -> 152948.38 | H17: =+G17*(1+H18) -> 183538.06 | I17: =+H17*(1+I18) -> 215069.9 | J17: =+I17*(1+J18) -> 247782.03 | K17: =+J17*(1+K18) -> 280662.71 | L17: =+K17*(1+L18) -> 312545.99 | M17: =+L17*(1+M18) -> 342206.6 | N17: =+M17*(1+N18) -> 368351.19 | O17: =+N17*(1+O18) -> 389826.06 | ... Q17: =+P17*(1+Q18) -> 417782.44
B18: Market growth | F18: =+F17/E17-1 -> -0.36065483 | G18: =+G17/F17-1 -> 0.92605338 | H18: 0.2 | I18: 0.1718 | J18: 0.1521 | K18: 0.1327 | L18: 0.1136 | M18: 0.0949 | N18: 0.0764 | O18: 0.0583 | P18: 0.0405 | Q18: 0.03
B19: SK Hynix Market Share | E19: =+SUM(Peers!H169:K169)/(DCF!E17*1000) -> 0.22679172 | F19: =+SUM(Peers!L169:O169)/(DCF!F17*1000) -> 0.26153628 | G19: =+SUM(Peers!P169:S169)/(DCF!G17*1000) -> 0.29246248 | H19: =($G$19*100+(LOG(H20+1)/LOG(9))*4)/100 -> 0.30508108 | I19: =($G$19*100+(LOG(I20+1)/LOG(9))*4)/100 -> 0.31246248 | J19: =($G$19*100+(LOG(J20+1)/LOG(9))*4)/100 -> 0.31769967 | K19: =($G$19*100+(LOG(K20+1)/LOG(9))*4)/100 -> 0.32176195 | L19: =($G$19*100+(LOG(L20+1)/LOG(9))*4)/100 -> 0.32508108 | M19: =($G$19*100+(LOG(M20+1)/LOG(9))*4)/100 -> 0.32788736 | N19: =($G$19*100+(LOG(N20+1)/LOG(9))*4)/100 -> 0.33031827 | O19: =($G$19*100+(LOG(O20+1)/LOG(9))*4)/100 -> 0.33246248 | P19: =AVERAGE(N19:O19) -> 0.33139037 | Q19: =AVERAGE(O19:P19) -> 0.33192643
H20: 1 | I20: 2 | J20: 3 | K20: 4 | L20: 5 | M20: 6 | N20: 7 | O20: 8 | P20: 9 | Q20: 10
B21: SK Hynix DRAM Revenue | E21: =Segments!G17 -> 28168.8 | F21: =Segments!H17 -> 20768.66 | G21: =Segments!I17 -> 44731.66 | H21: =+H17*H19 -> 55993.989 | I21: =+I17*I19 -> 67201.275 | J21: =+J17*J19 -> 78720.27 | K21: =+K17*K19 -> 90306.581 | L21: =+L17*L19 -> 101602.79 | M21: =+M17*M19 -> 112205.22 | N21: =+N17*N19 -> 121673.13 | O21: =+O17*O19 -> 129602.54 | ... Q21: =+Q17*Q19 -> 138673.03
B22: SK Hynix DRAM Growth | F22: =+F21/E21-1 -> -0.26270697 | G22: =+G21/F21-1 -> 1.1538058 | H22: =+H21/G21-1 -> 0.25177535 | I22: =+I21/H21-1 -> 0.20015158 | J22: =+J21/I21-1 -> 0.17141037 | K22: =+K21/J21-1 -> 0.14718332 | L22: =+L21/K21-1 -> 0.1250873 | M22: =+M21/L21-1 -> 0.10435178 | ... Q22: =+Q21/P21-1 -> 0.031666118
B24: Nand Market | E24: =SUM(Peers!H176:K180)/1000 -> 65433.158 | F24: =SUM(Peers!L176:O180)/1000 -> 45721.938 | G24: =SUM(Peers!P176:S180)/1000 -> 71577.847 | H24: =+G24*(1+H25) -> 78735.632 | I24: =+H24*(1+I25) -> 85554.138 | J24: =+I24*(1+J25) -> 92193.139 | K24: =+J24*(1+K25) -> 98517.588 | L24: =+K24*(1+L25) -> 104389.24 | M24: =+L24*(1+M25) -> 109692.21 | N24: =+M24*(1+N25) -> 114299.28 | O24: =+N24*(1+O25) -> 118105.45 | ... Q24: =+P24*(1+Q25) -> 123443.11
B25: Market growth | F25: =+F24/E24-1 -> -0.30124207 | G25: =+G24/F24-1 -> 0.56550334 | H25: 0.1 | I25: 0.0866 | J25: 0.0776 | K25: 0.0686 | L25: 0.0596 | M25: 0.0508 | N25: 0.042 | O25: 0.0333 | P25: 0.0247 | Q25: 0.02
B26: SK Hynix Market Share | E26: =+E27/E24 -> 0.21676961 | F26: =+F27/F24 -> 0.21112534 | G26: =+G27/G24 -> 0.26927479 | H26: =+G26 -> 0.26927479 | I26: =+H26 -> 0.26927479 | J26: =+I26 -> 0.26927479 | K26: =+J26 -> 0.26927479 | L26: =+K26 -> 0.26927479 | M26: =+L26 -> 0.26927479 | N26: =+M26 -> 0.26927479 | O26: =+N26 -> 0.26927479 | ... Q26: =+P26 -> 0.26927479
B27: SK Hynix NAND Revenue | E27: =Segments!G18 -> 14183.92 | F27: =Segments!H18 -> 9653.06 | G27: =Segments!I18 -> 19274.11 | H27: =+H24*H26 -> 21201.521 | I27: =+I24*I26 -> 23037.573 | J27: =+J24*J26 -> 24825.288 | K27: =+K24*K26 -> 26528.303 | L27: =+L24*L26 -> 28109.39 | M27: =+M24*M26 -> 29537.347 | N27: =+N24*N26 -> 30777.916 | O27: =+O24*O26 -> 31802.82 | ... Q27: =+Q24*Q26 -> 33240.117
B28: SK Hynix NAND Growth | F28: =+F27/E27-1 -> -0.31943638 | G28: =+G27/F27-1 -> 0.99668395 | H28: =+H27/G27-1 -> 0.1 | I28: =+I27/H27-1 -> 0.0866 | J28: =+J27/I27-1 -> 0.0776 | K28: =+K27/J27-1 -> 0.0686 | L28: =+L27/K27-1 -> 0.0596 | M28: =+M27/L27-1 -> 0.0508 | ... Q28: =+Q27/P27-1 -> 0.02
B30: Others
B31: SK Hynix Others Revenue | E31: =Segments!G38 -> 2268.84 | F31: =Segments!H38 -> 2344 | G31: =Segments!I38 -> 2187.18 | H31: =+G31*(1+H32) -> 2571.878 | I31: =+H31*(1+I32) -> 2940.623 | J31: =+I31*(1+J32) -> 3306.7459 | K31: =+J31*(1+K32) -> 3663.5162 | L31: =+K31*(1+L32) -> 4001.8186 | M31: =+L31*(1+M32) -> 4312.2633 | N31: =+M31*(1+N32) -> 4584.7558 | O31: =+N31*(1+O32) -> 4810.4858 | ... Q31: =+P31*(1+Q32) -> 5087.3495
B32: Growth | E32: =Segments!G46 -> 0.21417295 | F32: =Segments!H46 -> 0.033127061 | G32: =Segments!I46 -> -0.06690273 | H32: =+AVERAGE(H28,H22) -> 0.17588767 | I32: =+AVERAGE(I28,I22) -> 0.14337579 | J32: =+AVERAGE(J28,J22) -> 0.12450519 | K32: =+AVERAGE(K28,K22) -> 0.10789166 | L32: =+AVERAGE(L28,L22) -> 0.092343652 | M32: =+AVERAGE(M28,M22) -> 0.077575892 | N32: =+AVERAGE(N28,N22) -> 0.063190138 | O32: =+AVERAGE(O28,O22) -> 0.049234903 | ... Q32: =+AVERAGE(Q28,Q22) -> 0.025833059
A34: x | B34: Income Statement | E34: 2022 | F34: =+E34+1 -> 2023 | G34: =+F34+1 -> 2024 | H34: =+G34+1 -> 2025 | I34: =+H34+1 -> 2026 | J34: =+I34+1 -> 2027 | K34: =+J34+1 -> 2028 | L34: =+K34+1 -> 2029 | M34: =+L34+1 -> 2030 | ... Q34: =+P34+1 -> 2034
B36: Revenue (Sales) | D36: =+_xlfn.XLOOKUP($B36,Inputs!$B:$B,Inputs!N:N) -> 42997.8 | E36: =+_xlfn.XLOOKUP($B36,Inputs!$B:$B,Inputs!O:O) -> 44621.6 | F36: =+_xlfn.XLOOKUP($B36,Inputs!$B:$B,Inputs!P:P) -> 32765.7 | G36: =+_xlfn.XLOOKUP($B36,Inputs!$B:$B,Inputs!Q:Q) -> 66193 | H36: =H21+H27+H31 -> 79767.388 | I36: =I21+I27+I31 -> 93179.47 | J36: =J21+J27+J31 -> 106852.3 | K36: =K21+K27+K31 -> 120498.4 | L36: =L21+L27+L31 -> 133714 | M36: =M21+M27+M31 -> 146054.83 | N36: =N21+N27+N31 -> 157035.8 | O36: =O21+O27+O31 -> 166215.85 | ... Q36: =Q21+Q27+Q31 -> 177000.5
B37: % of growth | E37: =IFERROR((E36-D36)/D36,"") -> 0.037764723 | F37: =IFERROR((F36-E36)/E36,"") -> -0.26569868 | G37: =IFERROR((G36-F36)/F36,"") -> 1.0201918 | H37: =IFERROR(H36/G36-1,"") -> 0.20507287 | I37: =IFERROR(I36/H36-1,"") -> 0.16813992 | J37: =IFERROR(J36/I36-1,"") -> 0.14673655 | K37: =IFERROR(K36/J36-1,"") -> 0.12770988 | L37: =IFERROR(L36/K36-1,"") -> 0.10967445 | M37: =IFERROR(M36/L36-1,"") -> 0.09229276 | N37: =IFERROR(N36/M36-1,"") -> 0.075183878 | O37: =IFERROR(O36/N36-1,"") -> 0.058458318 | ... Q37: =IFERROR(Q36/P36-1,"") -> 0.029287093
B39: COGS (Cost of Goods Sold) | E39: =+_xlfn.XLOOKUP($B39,Inputs!$B:$B,Inputs!O:O) -> 28993.7 | F39: =+_xlfn.XLOOKUP($B39,Inputs!$B:$B,Inputs!P:P) -> 33299.2 | G39: =+_xlfn.XLOOKUP($B39,Inputs!$B:$B,Inputs!Q:Q) -> 34364.8 | H39: =H40*H$36 -> 51848.802 | I39: =I40*I$36 -> 60566.656 | J39: =J40*J$36 -> 69453.998 | K39: =K40*K$36 -> 78323.96 | L39: =L40*L$36 -> 86914.097 | M39: =M40*M$36 -> 94935.639 | N39: =N40*N$36 -> 102073.27 | O39: =O40*O$36 -> 108040.3 | ... Q39: =Q40*Q$36 -> 115050.32
B40: % of revenue | E40: =IFERROR(E39/E$36,"") -> 0.64976827 | F40: =IFERROR(F39/F$36,"") -> 1.0162823 | G40: =IFERROR(G39/G$36,"") -> 0.51916064 | H40: 0.65 | I40: =+H40 -> 0.65 | J40: =+I40 -> 0.65 | K40: =+J40 -> 0.65 | L40: =+K40 -> 0.65 | M40: =+L40 -> 0.65 | N40: =+M40 -> 0.65 | O40: =+N40 -> 0.65 | P40: =+O40 -> 0.65 | Q40: =+P40 -> 0.65 | R40: REVER
B42: Gross Profit | E42: =+_xlfn.XLOOKUP($B42,Inputs!$B:$B,Inputs!O:O) -> 15627.9 | F42: =+_xlfn.XLOOKUP($B42,Inputs!$B:$B,Inputs!P:P) -> -533.5 | G42: =+_xlfn.XLOOKUP($B42,Inputs!$B:$B,Inputs!Q:Q) -> 31828.2 | H42: =+H36-H39 -> 27918.586 | I42: =+I36-I39 -> 32612.815 | J42: =+J36-J39 -> 37398.307 | K42: =+K36-K39 -> 42174.44 | L42: =+L36-L39 -> 46799.899 | M42: =+M36-M39 -> 51119.19 | N42: =+N36-N39 -> 54962.529 | O42: =+O36-O39 -> 58175.546 | ... Q42: =+Q36-Q39 -> 61950.175 | S42: =3362*1.03^(H34-$G$34)+0.0015*H36 -> 3582.5111
B43: Gross Profit Margin | E43: =IFERROR(E42/E$36,"") -> 0.35023173 | F43: =IFERROR(F42/F$36,"") -> -0.016282271 | G43: =IFERROR(G42/G$36,"") -> 0.48083936 | H43: =IFERROR(H42/H$36,"") -> 0.35 | I43: =IFERROR(I42/I$36,"") -> 0.35 | J43: =IFERROR(J42/J$36,"") -> 0.35 | K43: =IFERROR(K42/K$36,"") -> 0.35 | L43: =IFERROR(L42/L$36,"") -> 0.35 | ... Q43: =IFERROR(Q42/Q$36,"") -> 0.35
B45: SG&A (Selling, General & Administrative) | E45: =+_xlfn.XLOOKUP($B45,Inputs!$B:$B,Inputs!O:O) -> 3664.5 | F45: =+_xlfn.XLOOKUP($B45,Inputs!$B:$B,Inputs!P:P) -> 2859.1 | G45: =+_xlfn.XLOOKUP($B45,Inputs!$B:$B,Inputs!Q:Q) -> 3364.9 | H45: =3362*1.03^(H34-$G$34)+0.0015*H36 -> 3582.5111 | I45: =3362*1.03^(I34-$G$34)+0.0015*I36 -> 3706.515 | J45: =3362*1.03^(J34-$G$34)+0.0015*J36 -> 3834.0266 | K45: =3362*1.03^(K34-$G$34)+0.0015*K36 -> 3964.7082 | L45: =3362*1.03^(L34-$G$34)+0.0015*L36 -> 4098.0504 | M45: =3362*1.03^(M34-$G$34)+0.0015*M36 -> 4233.4861 | N45: =3362*1.03^(N34-$G$34)+0.0015*N36 -> 4370.3896 | O45: =3362*1.03^(O34-$G$34)+0.0015*O36 -> 4508.2048 | ... Q45: =3362*1.03^(Q34-$G$34)+0.0015*Q36 -> 4783.7476
B46: SG&A Margin | E46: =IFERROR(E45/E$36,"") -> 0.082123904 | F46: =IFERROR(F45/F$36,"") -> 0.087258932 | G46: =IFERROR(G45/G$36,"") -> 0.05083468 | H46: =IFERROR(H45/H$36,"") -> 0.044911977 | I46: =IFERROR(I45/I$36,"") -> 0.039778236 | J46: =IFERROR(J45/J$36,"") -> 0.035881553 | K46: =IFERROR(K45/K$36,"") -> 0.03290258 | L46: =IFERROR(L45/L$36,"") -> 0.030647879 | ... Q46: =IFERROR(Q45/Q$36,"") -> 0.027026746
B48: R&D (Research & Development) | E48: =+_xlfn.XLOOKUP($B48,Inputs!$B:$B,Inputs!O:O) -> 4474.6 | F48: =+_xlfn.XLOOKUP($B48,Inputs!$B:$B,Inputs!P:P) -> 3750.7 | G48: =+_xlfn.XLOOKUP($B48,Inputs!$B:$B,Inputs!Q:Q) -> 4436.3 | H48: =+AVERAGE(E48:G48)*(1+H37) -> 5086.0502 | I48: =+AVERAGE(F48:H48)*(1+I37) -> 5168.2599 | J48: =+AVERAGE(G48:I48)*(1+J37) -> 5615.4199 | K48: =+AVERAGE(H48:J48)*(1+K37) -> 5965.4838 | L48: =+AVERAGE(I48:K48)*(1+L37) -> 6195.373 | M48: =+AVERAGE(J48:L48)*(1+M37) -> 6472.2994 | N48: =+AVERAGE(K48:M48)*(1+N37) -> 6678.023 | O48: =+AVERAGE(L48:N48)*(1+O37) -> 6825.5374 | ... Q48: =+AVERAGE(N48:P48)*(1+Q37) -> 6996.5648
B49: % of revenue | E49: =IFERROR(E48/E36,"") -> 0.10027879 | F49: =IFERROR(F48/F36,"") -> 0.11447031 | G49: =IFERROR(G48/G36,"") -> 0.067020682
B51: Other Operating (Income) Expenses | E51: =+_xlfn.XLOOKUP($B51,Inputs!$B:$B,Inputs!O:O) -> 0 | F51: =+_xlfn.XLOOKUP($B51,Inputs!$B:$B,Inputs!P:P) -> 0 | G51: =+_xlfn.XLOOKUP($B51,Inputs!$B:$B,Inputs!Q:Q) -> 0 | H51: =IFERROR(AVERAGE(E51:G51)*(1+H37),"") -> 0 | I51: =IFERROR(AVERAGE(F51:H51)*(1+I37),"") -> 0 | J51: =IFERROR(AVERAGE(G51:I51)*(1+J37),"") -> 0 | K51: =IFERROR(AVERAGE(H51:J51)*(1+K37),"") -> 0 | L51: =IFERROR(AVERAGE(I51:K51)*(1+L37),"") -> 0 | M51: =IFERROR(AVERAGE(J51:L51)*(1+M37),"") -> 0 | N51: =IFERROR(AVERAGE(K51:M51)*(1+N37),"") -> 0 | O51: =IFERROR(AVERAGE(L51:N51)*(1+O37),"") -> 0 | ... Q51: =IFERROR(AVERAGE(N51:P51)*(1+Q37),"") -> 0
B53: EBITDA | E53: =+_xlfn.XLOOKUP($B53,Inputs!$B:$B,Inputs!O:O) -> 7488.8 | F53: =+_xlfn.XLOOKUP($B53,Inputs!$B:$B,Inputs!P:P) -> -7143.3 | G53: =+_xlfn.XLOOKUP($B53,Inputs!$B:$B,Inputs!Q:Q) -> 24027 | H53: =IFERROR(H42-H45-H48-H51,"") -> 19250.025 | I53: =IFERROR(I42-I45-I48-I51,"") -> 23738.04 | J53: =IFERROR(J42-J45-J48-J51,"") -> 27948.86 | K53: =IFERROR(K42-K45-K48-K51,"") -> 32244.248 | L53: =IFERROR(L42-L45-L48-L51,"") -> 36506.475 | M53: =IFERROR(M42-M45-M48-M51,"") -> 40413.405 | N53: =IFERROR(N42-N45-N48-N51,"") -> 43914.117 | O53: =IFERROR(O42-O45-O48-O51,"") -> 46841.804 | ... Q53: =IFERROR(Q42-Q45-Q48-Q51,"") -> 50169.862
B54: EBITDA Margin | E54: =IFERROR(E53/E$36,"") -> 0.16782903 | F54: =IFERROR(F53/F$36,"") -> -0.21801152 | G54: =IFERROR(G53/G$36,"") -> 0.362984 | H54: =IFERROR(H53/H$36,"") -> 0.241327 | I54: =IFERROR(I53/I$36,"") -> 0.25475611 | J54: =IFERROR(J53/J$36,"") -> 0.26156535 | K54: =IFERROR(K53/K$36,"") -> 0.26759067 | L54: =IFERROR(L53/L$36,"") -> 0.2730191 | ... Q54: =IFERROR(Q53/Q$36,"") -> 0.28344475
B56: D&A (Depreciation & Amortization) | E56: =+_xlfn.XLOOKUP($B56,Inputs!$B:$B,Inputs!O:O) -> 679.4 | F56: =+_xlfn.XLOOKUP($B56,Inputs!$B:$B,Inputs!P:P) -> 587.1 | G56: =+_xlfn.XLOOKUP($B56,Inputs!$B:$B,Inputs!Q:Q) -> 559.6 | H56: =+IFERROR(H59+H61,"") -> 674.84081 | I56: =+IFERROR(I59+I61,"") -> 788.30848 | J56: =+IFERROR(J59+J61,"") -> 903.98215 | K56: =+IFERROR(K59+K61,"") -> 1019.4296 | L56: =+IFERROR(L59+L61,"") -> 1131.235 | M56: =+IFERROR(M59+M61,"") -> 1235.6398 | N56: =+IFERROR(N59+N61,"") -> 1328.54 | O56: =+IFERROR(O59+O61,"") -> 1406.2042 | ... Q56: =+IFERROR(Q59+Q61,"") -> 1497.4435
B57: % of PP&E+ROU Assets+Intangibles excl. Goodwill | E57: =IFERROR(E56/AVERAGE(Inputs!O39+Inputs!O42+Inputs!O44,Inputs!N39+Inputs!N42+Inputs!N44),"") -> 0.011399118 | F57: =IFERROR(F56/AVERAGE(Inputs!P39+Inputs!P42+Inputs!P44,Inputs!O39+Inputs!O42+Inputs!O44),"") -> 0.0098663812 | G57: =IFERROR(G56/AVERAGE(Inputs!Q39+Inputs!Q42+Inputs!Q44,Inputs!P39+Inputs!P42+Inputs!P44),"") -> 0.0093503464 | H57: =IFERROR(H56/(G103+G109),"") -> 0.010253711 | I57: =IFERROR(I56/(H103+H109),"") -> 0.010965789 | J57: =IFERROR(J56/(I103+I109),"") -> 0.011465595 | K57: =IFERROR(K56/(J103+J109),"") -> 0.011689227 | L57: =IFERROR(L56/(K103+K109),"") -> 0.011740008 | M57: =IFERROR(M56/(L103+L109),"") -> 0.011606427 | N57: =IFERROR(N56/(M103+M109),"") -> 0.011304473 | O57: =IFERROR(O56/(N103+N109),"") -> 0.010881353 | ... Q57: =IFERROR(Q56/(P103+P109),"") -> 0.0097199534
B59: Depreciation Expense | E59: =+_xlfn.XLOOKUP($B59,Inputs!$B:$B,Inputs!O:O) -> 265 | F59: =+_xlfn.XLOOKUP($B59,Inputs!$B:$B,Inputs!P:P) -> 304 | G59: =+_xlfn.XLOOKUP($B59,Inputs!$B:$B,Inputs!Q:Q) -> 303 | H59: =+G59*(1+H37) -> 365.13708 | I59: =+H59*(1+I37) -> 426.5312 | J59: =+I59*(1+J37) -> 489.11891 | K59: =+J59*(1+K37) -> 551.58423 | L59: =+K59*(1+L37) -> 612.07893 | M59: =+L59*(1+M37) -> 668.56939 | N59: =+M59*(1+N37) -> 718.83502 | O59: =+N59*(1+O37) -> 760.85691 | ... Q59: =+P59*(1+Q37) -> 810.22391
B61: Amortization Expense | E61: =+_xlfn.XLOOKUP($B61,Inputs!$B:$B,Inputs!O:O) -> 414 | F61: =+_xlfn.XLOOKUP($B61,Inputs!$B:$B,Inputs!P:P) -> 283 | G61: =+_xlfn.XLOOKUP($B61,Inputs!$B:$B,Inputs!Q:Q) -> 257 | H61: =G61*(1+H37) -> 309.70373 | I61: =H61*(1+I37) -> 361.77729 | J61: =I61*(1+J37) -> 414.86324 | K61: =J61*(1+K37) -> 467.84537 | L61: =K61*(1+L37) -> 519.15606 | M61: =L61*(1+M37) -> 567.0704 | N61: =M61*(1+N37) -> 609.70496 | O61: =N61*(1+O37) -> 645.34728 | ... Q61: =P61*(1+Q37) -> 687.21962
B63: Operating Income (EBIT) | E63: =+_xlfn.XLOOKUP($B63,Inputs!$B:$B,Inputs!O:O) -> 6809.4 | F63: =+_xlfn.XLOOKUP($B63,Inputs!$B:$B,Inputs!P:P) -> -7730.4 | G63: =+_xlfn.XLOOKUP($B63,Inputs!$B:$B,Inputs!Q:Q) -> 23467.4 | H63: =+IFERROR(H53-H56,"") -> 18575.184 | I63: =+IFERROR(I53-I56,"") -> 22949.731 | J63: =+IFERROR(J53-J56,"") -> 27044.878 | K63: =+IFERROR(K53-K56,"") -> 31224.818 | L63: =+IFERROR(L53-L56,"") -> 35375.24 | M63: =+IFERROR(M53-M56,"") -> 39177.765 | N63: =+IFERROR(N53-N56,"") -> 42585.577 | O63: =+IFERROR(O53-O56,"") -> 45435.6 | ... Q63: =+IFERROR(Q53-Q56,"") -> 48672.419
B64: Operating Margin | E64: =IFERROR(E63/E$36,"") -> 0.15260322 | F64: =IFERROR(F63/F$36,"") -> -0.23592965 | G64: =IFERROR(G63/G$36,"") -> 0.35452994 | H64: =IFERROR(H63/H36,"") -> 0.23286689 | I64: =IFERROR(I63/I36,"") -> 0.246296 | J64: =IFERROR(J63/J36,"") -> 0.25310524 | K64: =IFERROR(K63/K36,"") -> 0.25913056 | L64: =IFERROR(L63/L36,"") -> 0.26455899 | M64: =IFERROR(M63/M36,"") -> 0.26824012 | N64: =IFERROR(N63/N36,"") -> 0.27118388 | O64: =IFERROR(O63/O36,"") -> 0.273353 | ... Q64: =IFERROR(Q63/Q36,"") -> 0.27498464
B66: Net Interest Expense (Income) | E66: =+_xlfn.XLOOKUP($B66,Inputs!$B:$B,Inputs!O:O) -> 443.5 | F66: =+_xlfn.XLOOKUP($B66,Inputs!$B:$B,Inputs!P:P) -> 1251.9 | G66: =+_xlfn.XLOOKUP($B66,Inputs!$B:$B,Inputs!Q:Q) -> 1000.4 | H66: =-H69-H72 -> 0 | I66: =-I69-I72 -> 0 | J66: =-J69-J72 -> 0 | K66: =-K69-K72 -> 0 | L66: =-L69-L72 -> 0 | M66: =-M69-M72 -> 0 | N66: =-N69-N72 -> 0 | O66: =-O69-O72 -> 0 | ... Q66: =-Q69-Q72 -> 0
B67: % of Net Debt | E67: =IFERROR(E66/AVERAGE(Inputs!N116:O116),"") -> 0.038113162 | F67: =IFERROR(F66/AVERAGE(Inputs!O116:P116),"") -> 0.075374343 | G67: =IFERROR(G66/AVERAGE(Inputs!P116:Q116),"") -> 0.07800025 | H67: =IFERROR(H66/AVERAGE(G120+G122,H120+H122),"") -> 0 | I67: =IFERROR(I66/AVERAGE(H120+H122,I120+I122),"") -> 0 | J67: =IFERROR(J66/AVERAGE(I120+I122,J120+J122),"") -> 0 | K67: =IFERROR(K66/AVERAGE(J120+J122,K120+K122),"") -> 0 | L67: =IFERROR(L66/AVERAGE(K120+K122,L120+L122),"") -> 0 | M67: =IFERROR(M66/AVERAGE(L120+L122,M120+M122),"") -> 0 | N67: =IFERROR(N66/AVERAGE(M120+M122,N120+N122),"") -> 0 | O67: =IFERROR(O66/AVERAGE(N120+N122,O120+O122),"") -> 0 | ... Q67: =IFERROR(Q66/AVERAGE(P120+P122,Q120+Q122),"") -> 0
B69: Interest Expense | E69: =+_xlfn.XLOOKUP($B69,Inputs!$B:$B,Inputs!O:O) -> 533.1 | F69: =+_xlfn.XLOOKUP($B69,Inputs!$B:$B,Inputs!P:P) -> 1468.3 | G69: =+_xlfn.XLOOKUP($B69,Inputs!$B:$B,Inputs!Q:Q) -> 1345.2
B70: % of Debt | E70: =+IFERROR(E69/AVERAGE(Inputs!N113:O113),"") -> 0.028278317 | F70: =+IFERROR(F69/AVERAGE(Inputs!O113:P113),"") -> 0.061193573 | G70: =+IFERROR(G69/AVERAGE(Inputs!P113:Q113),"") -> 0.055736136
B72: Interest Income | E72: =+_xlfn.XLOOKUP($B72,Inputs!$B:$B,Inputs!O:O) -> 89.6 | F72: =+_xlfn.XLOOKUP($B72,Inputs!$B:$B,Inputs!P:P) -> 216.4 | G72: =+_xlfn.XLOOKUP($B72,Inputs!$B:$B,Inputs!Q:Q) -> 344.8
B73: % Cash & Cash Eq. & ST Investments | E73: =IFERROR(E72/+AVERAGE(Inputs!N32:O32),"") -> 0.012417712 | F73: =IFERROR(F72/+AVERAGE(Inputs!O32:P32),"") -> 0.029301649 | G73: =IFERROR(G72/+AVERAGE(Inputs!P32:Q32),"") -> 0.030487508
B75: FX (Gain) Loss | E75: =+_xlfn.XLOOKUP($B75,Inputs!$B:$B,Inputs!O:O) -> 405.2 | F75: =+_xlfn.XLOOKUP($B75,Inputs!$B:$B,Inputs!P:P) -> 318.8 | G75: =+_xlfn.XLOOKUP($B75,Inputs!$B:$B,Inputs!Q:Q) -> -268.8 | H75: =+H76*H$17 -> 0 | I75: =+I76*I$17 -> 0 | J75: =+J76*J$17 -> 0 | K75: =+K76*K$17 -> 0 | L75: =+L76*L$17 -> 0 | M75: =+M76*M$17 -> 0 | N75: =+N76*N$17 -> 0 | O75: =+O76*O$17 -> 0 | ... Q75: =+Q76*Q$17 -> 0
B76: % of revenue
B78: Other Non-Operating (Income) Expenses | E78: =+_xlfn.XLOOKUP($B78,Inputs!$B:$B,Inputs!O:O) -> 1957.9 | F78: =+_xlfn.XLOOKUP($B78,Inputs!$B:$B,Inputs!P:P) -> 2356.8 | G78: =+_xlfn.XLOOKUP($B78,Inputs!$B:$B,Inputs!Q:Q) -> -1149.7 | H78: =IFERROR(AVERAGE(E78:G78)*(1+H37),"") -> 1271.3519 | I78: =IFERROR(AVERAGE(F78:H78)*(1+I37),"") -> 965.05952 | J78: =IFERROR(AVERAGE(G78:I78)*(1+J37),"") -> 415.39056 | K78: =IFERROR(AVERAGE(H78:J78)*(1+K37),"") -> 996.82109 | L78: =IFERROR(AVERAGE(I78:K78)*(1+L37),"") -> 879.33236 | M78: =IFERROR(AVERAGE(J78:L78)*(1+M37),"") -> 834.34565 | N78: =IFERROR(AVERAGE(K78:M78)*(1+N37),"") -> 971.42831 | O78: =IFERROR(AVERAGE(L78:N78)*(1+O37),"") -> 947.35771 | ... Q78: =IFERROR(AVERAGE(N78:P78)*(1+Q37),"") -> 984.07881
B80: Pre-Tax Income (EBT) | E80: =+_xlfn.XLOOKUP($B80,Inputs!$B:$B,Inputs!O:O) -> 4002.8 | F80: =+_xlfn.XLOOKUP($B80,Inputs!$B:$B,Inputs!P:P) -> -11657.9 | G80: =+_xlfn.XLOOKUP($B80,Inputs!$B:$B,Inputs!Q:Q) -> 23885.5 | H80: =IFERROR(+H63-H66-H75-H78,"") -> 17303.832 | I80: =IFERROR(+I63-I66-I75-I78,"") -> 21984.672 | J80: =IFERROR(+J63-J66-J75-J78,"") -> 26629.487 | K80: =IFERROR(+K63-K66-K75-K78,"") -> 30227.997 | L80: =IFERROR(+L63-L66-L75-L78,"") -> 34495.908 | M80: =IFERROR(+M63-M66-M75-M78,"") -> 38343.419 | N80: =IFERROR(+N63-N66-N75-N78,"") -> 41614.148 | O80: =IFERROR(+O63-O66-O75-O78,"") -> 44488.242 | ... Q80: =IFERROR(+Q63-Q66-Q75-Q78,"") -> 47688.34
B82: Tax Expense (Benefits) | E82: =+_xlfn.XLOOKUP($B82,Inputs!$B:$B,Inputs!O:O) -> 1761.1 | F82: =+_xlfn.XLOOKUP($B82,Inputs!$B:$B,Inputs!P:P) -> -2520.3 | G82: =+_xlfn.XLOOKUP($B82,Inputs!$B:$B,Inputs!Q:Q) -> 4088.4 | H82: =IFERROR(H83*H$63,"") -> 5122.5515 | I82: =IFERROR(I83*I$63,"") -> 5072.8752 | J82: =IFERROR(J83*J$63,"") -> 6021.8435 | K82: =IFERROR(K83*K$63,"") -> 7488.5231 | L82: =IFERROR(L83*L$63,"") -> 8060.0131 | M82: =IFERROR(M83*M$63,"") -> 9015.2019 | N82: =IFERROR(N83*N$63,"") -> 9905.1142 | O82: =IFERROR(O83*O$63,"") -> 10458.468 | ... Q82: =IFERROR(Q83*Q$63,"") -> 11255.29
B83: % of EBT | E83: =IFERROR(E82/E80,"") -> 0.43996702 | F83: =IFERROR(F82/F80,"") -> 0.21618816 | G83: =IFERROR(G82/G80,"") -> 0.17116661 | H83: =IFERROR(AVERAGE(E83:G83),"") -> 0.27577393 | I83: =IFERROR(AVERAGE(F83:H83),"") -> 0.2210429 | J83: =IFERROR(AVERAGE(G83:I83),"") -> 0.22266115 | K83: =IFERROR(AVERAGE(H83:J83),"") -> 0.23982599 | L83: =IFERROR(AVERAGE(I83:K83),"") -> 0.22784335 | M83: =IFERROR(AVERAGE(J83:L83),"") -> 0.23011016 | N83: =IFERROR(AVERAGE(K83:M83),"") -> 0.23259317 | O83: =IFERROR(AVERAGE(L83:N83),"") -> 0.23018223 | ... Q83: =IFERROR(AVERAGE(N83:P83),"") -> 0.23124575
B85: Net Income | E85: =+_xlfn.XLOOKUP($B85,Inputs!$B:$B,Inputs!O:O) -> 2241.7 | F85: =+_xlfn.XLOOKUP($B85,Inputs!$B:$B,Inputs!P:P) -> -9137.6 | G85: =+_xlfn.XLOOKUP($B85,Inputs!$B:$B,Inputs!Q:Q) -> 19797.1 | H85: =IFERROR(+H80-H82,"") -> 12181.28 | I85: =IFERROR(+I80-I82,"") -> 16911.797 | J85: =IFERROR(+J80-J82,"") -> 20607.644 | K85: =IFERROR(+K80-K82,"") -> 22739.474 | L85: =IFERROR(+L80-L82,"") -> 26435.895 | M85: =IFERROR(+M80-M82,"") -> 29328.218 | N85: =IFERROR(+N80-N82,"") -> 31709.034 | O85: =IFERROR(+O80-O82,"") -> 34029.775 | ... Q85: =IFERROR(+Q80-Q82,"") -> 36433.05
B86: Net Income Margin | E86: =IFERROR(E85/E$36,"") -> 0.050238001 | F86: =IFERROR(F85/F$36,"") -> -0.278877 | G86: =IFERROR(G85/G$36,"") -> 0.29908147 | H86: =IFERROR(H85/H$36,"") -> 0.15271003 | I86: =IFERROR(I85/I$36,"") -> 0.18149702 | J86: =IFERROR(J85/J$36,"") -> 0.19286101 | K86: =IFERROR(K85/K$36,"") -> 0.18871184 | L86: =IFERROR(L85/L$36,"") -> 0.19770477 | ... Q86: =IFERROR(Q85/Q$36,"") -> 0.20583586
A88: x | B88: Balance Sheet | E88: =E34 -> 2022 | F88: =F34 -> 2023 | G88: =G34 -> 2024 | H88: =H34 -> 2025 | I88: =I34 -> 2026 | J88: =J34 -> 2027 | K88: =K34 -> 2028 | L88: =L34 -> 2029 | ... Q88: =Q34 -> 2034
B90: Assets
B92: Cash & Cash Equivalents & ST Investments | E92: =+_xlfn.XLOOKUP($B92,Inputs!$B:$B,Inputs!O:O) -> 6079.4 | F92: =+_xlfn.XLOOKUP($B92,Inputs!$B:$B,Inputs!P:P) -> 8691.1 | G92: =+_xlfn.XLOOKUP($B92,Inputs!$B:$B,Inputs!Q:Q) -> 13928 | H92: =IFERROR(G92+H170,"") -> 1273.7703 | I92: =IFERROR(H92+I170,"") -> 8284.098 | J92: =IFERROR(I92+J170,"") -> 198.41483 | K92: =IFERROR(J92+K170,"") -> 4358.5569 | L92: =IFERROR(K92+L170,"") -> -5395.5747 | M92: =IFERROR(L92+M170,"") -> -932.8321 | N92: =IFERROR(M92+N170,"") -> -10550.795 | O92: =IFERROR(N92+O170,"") -> -6073.4949 | ... Q92: =IFERROR(P92+Q170,"") -> -9941.2201
B94: Accounts Receivable | E94: =+_xlfn.XLOOKUP($B94,Inputs!$B:$B,Inputs!O:O) -> 5186.1 | F94: =+_xlfn.XLOOKUP($B94,Inputs!$B:$B,Inputs!P:P) -> 6600.3 | G94: =+_xlfn.XLOOKUP($B94,Inputs!$B:$B,Inputs!Q:Q) -> 13019 | H94: =IFERROR(H95*H36/365,"") -> 15731.827 | I94: =IFERROR(I95*I36/365,"") -> 18507.986 | J94: =IFERROR(J95*J36/365,"") -> 21123.627 | K94: =IFERROR(K95*K36/365,"") -> 23840.148 | L94: =IFERROR(L95*L36/365,"") -> 26482.655 | M94: =IFERROR(M95*M36/365,"") -> 28898.925 | N94: =IFERROR(N95*N36/365,"") -> 31080.744 | O94: =IFERROR(O95*O36/365,"") -> 32901.84 | ... Q94: =IFERROR(Q95*Q36/365,"") -> 35033.02
B95: DSO | E95: =IFERROR(E94/E36*365,"") -> 42.421753 | F95: =IFERROR(F94/F36*365,"") -> 73.525348 | G95: =IFERROR(G94/G36*366,"") -> 71.985769 | H95: =+G95 -> 71.985769 | I95: =IFERROR(AVERAGE(F95:H95),"") -> 72.498962 | J95: =IFERROR(AVERAGE(G95:I95),"") -> 72.156833 | K95: =IFERROR(AVERAGE(H95:J95),"") -> 72.213855 | L95: =IFERROR(AVERAGE(I95:K95),"") -> 72.289883 | M95: =IFERROR(AVERAGE(J95:L95),"") -> 72.22019 | N95: =IFERROR(AVERAGE(K95:M95),"") -> 72.241309 | O95: =IFERROR(AVERAGE(L95:N95),"") -> 72.250461 | P95: =IFERROR(AVERAGE(M95:O95),"") -> 72.23732 | Q95: =IFERROR(AVERAGE(N95:P95),"") -> 72.24303
B97: Inventory | E97: =+_xlfn.XLOOKUP($B97,Inputs!$B:$B,Inputs!O:O) -> 15664.7 | F97: =+_xlfn.XLOOKUP($B97,Inputs!$B:$B,Inputs!P:P) -> 13480.7 | G97: =+_xlfn.XLOOKUP($B97,Inputs!$B:$B,Inputs!Q:Q) -> 13313.9 | H97: =+IFERROR(H98*H39/365,"") -> 17046.182 | I97: =+IFERROR(I98*I39/365,"") -> 19912.325 | J97: =+IFERROR(J98*J39/365,"") -> 22834.191 | K97: =+IFERROR(K98*K39/365,"") -> 25750.343 | L97: =+IFERROR(L98*L39/365,"") -> 28574.498 | M97: =+IFERROR(M98*M39/365,"") -> 31211.717 | N97: =+IFERROR(N98*N39/365,"") -> 33558.335 | O97: =+IFERROR(O98*O39/365,"") -> 35520.099 | ... Q97: =+IFERROR(Q98*Q39/365,"") -> 37824.764
B98: DIH | E98: =IFERROR(E97/E39*365,"") -> 197.202 | F98: =IFERROR(F97/F39*365,"") -> 147.76498 | G98: =IFERROR(G97/G39*365,"") -> 141.41137 | H98: 120 | I98: =+H98 -> 120 | J98: =+I98 -> 120 | K98: =+J98 -> 120 | L98: =+K98 -> 120 | M98: =+L98 -> 120 | N98: =+M98 -> 120 | O98: =+N98 -> 120 | P98: =+O98 -> 120 | Q98: =+P98 -> 120
B100: Prepaid expenses and Other Current Assets | E100: =+_xlfn.XLOOKUP($B100,Inputs!$B:$B,Inputs!O:O) -> 1803.1 | F100: =+_xlfn.XLOOKUP($B100,Inputs!$B:$B,Inputs!P:P) -> 1696 | G100: =+_xlfn.XLOOKUP($B100,Inputs!$B:$B,Inputs!Q:Q) -> 2018 | H100: =IFERROR(AVERAGE(E100:G100)*(1+H37),"") -> 2216.1692 | I100: =IFERROR(AVERAGE(F100:H100)*(1+I37),"") -> 2309.0891 | J100: =IFERROR(AVERAGE(G100:I100)*(1+J37),"") -> 2501.1311 | K100: =IFERROR(AVERAGE(H100:J100)*(1+K37),"") -> 2641.2429 | L100: =IFERROR(AVERAGE(I100:K100)*(1+L37),"") -> 2756.2328 | M100: =IFERROR(AVERAGE(J100:L100)*(1+M37),"") -> 2875.8637 | N100: =IFERROR(AVERAGE(K100:M100)*(1+N37),"") -> 2965.1204 | O100: =IFERROR(AVERAGE(L100:N100)*(1+O37),"") -> 3033.2652 | ... Q100: =IFERROR(AVERAGE(N100:P100)*(1+Q37),"") -> 3108.0248
B101: % of revenue | E101: =IFERROR(E100/E$36,"") -> 0.040408681 | F101: =IFERROR(F100/F$36,"") -> 0.051761446 | G101: =IFERROR(G100/G$36,"") -> 0.030486607 | H101: =IFERROR(AVERAGE(E101:G101),"") -> 0.040885578 | I101: =IFERROR(AVERAGE(F101:H101),"") -> 0.041044544 | J101: =IFERROR(AVERAGE(G101:I101),"") -> 0.037472243 | K101: =IFERROR(AVERAGE(H101:J101),"") -> 0.039800788 | L101: =IFERROR(AVERAGE(I101:K101),"") -> 0.039439192 | M101: =IFERROR(AVERAGE(J101:L101),"") -> 0.038904074 | N101: =IFERROR(AVERAGE(K101:M101),"") -> 0.039381351 | O101: =IFERROR(AVERAGE(L101:N101),"") -> 0.039241539 | ... Q101: =IFERROR(AVERAGE(N101:P101),"") -> 0.039266182
B103: Net PP&E (Property, Plant and Equipment) + ROU Assets | E103: =+E104+E105-E107 -> 62008.5 | F103: =+F104+F105-F107 -> 55399.7 | G103: =+G104+G105-G107 -> 62644.3 | H103: =IFERROR(H104+H105-H107,"") -> 68717.983 | I103: =IFERROR(I104+I105-I107,"") -> 75673.021 | J103: =IFERROR(J104+J105-J107,"") -> 84041.037 | K103: =IFERROR(K104+K105-K107,"") -> 93187.259 | L103: =IFERROR(L104+L105-L107,"") -> 103291.68 | M103: =IFERROR(M104+M105-M107,"") -> 114353.39 | N103: =IFERROR(N104+N105-N107,"") -> 126060.64 | O103: =IFERROR(O104+O105-O107,"") -> 138339.59 | ... Q103: =IFERROR(Q104+Q105-Q107,"") -> 163595.24
B104: Gross PP&E (Property, Plant and Equipment) + ROU Assets | E104: =+_xlfn.XLOOKUP("Gross PP&E (Property, Plant and Equipment)",Inputs!$B:$B,Inputs!O:O) -> 134442.4 | F104: =+_xlfn.XLOOKUP("Gross PP&E (Property, Plant and Equipment)",Inputs!$B:$B,Inputs!P:P) -> 139076.3 | G104: =+_xlfn.XLOOKUP("Gross PP&E (Property, Plant and Equipment)",Inputs!$B:$B,Inputs!Q:Q) -> 159664.6 | H104: =+IFERROR(G104-H138,"") -> 186842.94 | I104: =+IFERROR(H104-I138,"") -> 218451.17 | J104: =+IFERROR(I104-J138,"") -> 255089.91 | K104: =+IFERROR(J104-K138,"") -> 296117.3 | L104: =+IFERROR(K104-L138,"") -> 341599.44 | M104: =+IFERROR(L104-M138,"") -> 391303.97 | N104: =+IFERROR(M104-N138,"") -> 444559.37 | O104: =+IFERROR(N104-O138,"") -> 500815.29 | ... Q104: =+IFERROR(P104-Q138,"") -> 618399.15
B105: Right-of-Use Assets | E105: =+_xlfn.XLOOKUP("Right-of-Use Assets",Inputs!$B:$B,Inputs!O:O) -> 0 | F105: =+_xlfn.XLOOKUP("Right-of-Use Assets",Inputs!$B:$B,Inputs!P:P) -> 0 | G105: =+_xlfn.XLOOKUP("Right-of-Use Assets",Inputs!$B:$B,Inputs!Q:Q) -> 0 | H105: =IFERROR(H106*H$36,"") -> 0 | I105: =IFERROR(I106*I$36,"") -> 0 | J105: =IFERROR(J106*J$36,"") -> 0 | K105: =IFERROR(K106*K$36,"") -> 0 | L105: =IFERROR(L106*L$36,"") -> 0 | M105: =IFERROR(M106*M$36,"") -> 0 | N105: =IFERROR(N106*N$36,"") -> 0 | O105: =IFERROR(O106*O$36,"") -> 0 | ... Q105: =IFERROR(Q106*Q$36,"") -> 0
B106: % of revenue | E106: =IFERROR(E105/E$36,"") -> 0 | F106: =IFERROR(F105/F$36,"") -> 0 | G106: =IFERROR(G105/G$36,"") -> 0 | H106: =IFERROR(AVERAGE(E106:G106),"") -> 0 | I106: =IFERROR(AVERAGE(F106:H106),"") -> 0 | J106: =IFERROR(AVERAGE(G106:I106),"") -> 0 | K106: =IFERROR(AVERAGE(H106:J106),"") -> 0 | L106: =IFERROR(AVERAGE(I106:K106),"") -> 0 | M106: =IFERROR(AVERAGE(J106:L106),"") -> 0 | N106: =IFERROR(AVERAGE(K106:M106),"") -> 0 | O106: =IFERROR(AVERAGE(L106:N106),"") -> 0 | ... Q106: =IFERROR(AVERAGE(N106:P106),"") -> 0
B107: Accumulated Depreciation | E107: =+_xlfn.XLOOKUP($B107,Inputs!$B:$B,Inputs!O:O) -> 72433.9 | F107: =+_xlfn.XLOOKUP($B107,Inputs!$B:$B,Inputs!P:P) -> 83676.6 | G107: =+_xlfn.XLOOKUP($B107,Inputs!$B:$B,Inputs!Q:Q) -> 97020.3 | H107: =+IFERROR(G107+H59+0.4*H39,"") -> 118124.96 | I107: =+IFERROR(H107+I59+0.4*I39,"") -> 142778.15 | J107: =+IFERROR(I107+J59+0.4*J39,"") -> 171048.87 | K107: =+IFERROR(J107+K59+0.4*K39,"") -> 202930.04 | L107: =+IFERROR(K107+L59+0.4*L39,"") -> 238307.76 | M107: =+IFERROR(L107+M59+0.4*M39,"") -> 276950.58 | N107: =+IFERROR(M107+N59+0.4*N39,"") -> 318498.72 | O107: =+IFERROR(N107+O59+0.4*O39,"") -> 362475.7 | ... Q107: =+IFERROR(P107+Q59+0.4*Q39,"") -> 454803.91
B109: Intangibles excl. Goodwill | E109: =+_xlfn.XLOOKUP($B109,Inputs!$B:$B,Inputs!O:O) -> 2713.4 | F109: =+_xlfn.XLOOKUP($B109,Inputs!$B:$B,Inputs!P:P) -> 3031.3 | G109: =+_xlfn.XLOOKUP($B109,Inputs!$B:$B,Inputs!Q:Q) -> 3170 | H109: =+G109+H110*H48 -> 3170 | I109: =+H109+I110*I48 -> 3170 | J109: =+I109+J110*J48 -> 3170 | K109: =+J109+K110*K48 -> 3170 | L109: =+K109+L110*L48 -> 3170 | M109: =+L109+M110*M48 -> 3170 | N109: =+M109+N110*N48 -> 3170 | O109: =+N109+O110*O48 -> 3170 | ... Q109: =+P109+Q110*Q48 -> 3170
B110: growing with % of R&D | E110: =IFERROR((E109-Inputs!N45)/E48,"") -> -0.11437894 | F110: =IFERROR((F109-E109)/F48,"") -> 0.084757512 | G110: =IFERROR((G109-F109)/G48,"") -> 0.031264793
B112: Liabilities
B114: Accounts Payable | E114: =+_xlfn.XLOOKUP($B114,Inputs!$B:$B,Inputs!O:O) -> 2186.2 | F114: =+_xlfn.XLOOKUP($B114,Inputs!$B:$B,Inputs!P:P) -> 1845.5 | G114: =+_xlfn.XLOOKUP($B114,Inputs!$B:$B,Inputs!Q:Q) -> 2277.3 | H114: =+IFERROR(H115*H39/365,"") -> 3409.4785 | I114: =+IFERROR(I115*I39/365,"") -> 3788.0364 | J114: =+IFERROR(J115*J39/365,"") -> 4508.7523 | K114: =+IFERROR(K115*K39/365,"") -> 5044.5451 | L114: =+IFERROR(L115*L39/365,"") -> 5558.6352 | M114: =+IFERROR(M115*M39/365,"") -> 6116.3477 | N114: =+IFERROR(N115*N39/365,"") -> 6559.4976 | O114: =+IFERROR(O115*O39/365,"") -> 6937.7864 | ... Q114: =+IFERROR(Q115*Q39/365,"") -> 7393.0829
B115: DPO | E115: =IFERROR(E114/E$39*365,"") -> 27.521944 | F115: =IFERROR(F114/F$39*365,"") -> 20.228939 | G115: =IFERROR(G114/G$39*366,"") -> 24.254231 | H115: =IFERROR(AVERAGE(E115:G115),"") -> 24.001705 | I115: =IFERROR(AVERAGE(F115:H115),"") -> 22.828292 | J115: =IFERROR(AVERAGE(G115:I115),"") -> 23.694743 | K115: =IFERROR(AVERAGE(H115:J115),"") -> 23.508246 | L115: =IFERROR(AVERAGE(I115:K115),"") -> 23.34376 | M115: =IFERROR(AVERAGE(J115:L115),"") -> 23.515583 | N115: =IFERROR(AVERAGE(K115:M115),"") -> 23.455863 | O115: =IFERROR(AVERAGE(L115:N115),"") -> 23.438402 | ... Q115: =IFERROR(AVERAGE(N115:P115),"") -> 23.454738
B117: Accrued Expenses and Other Current Liabilities | E117: =+_xlfn.XLOOKUP($B117,Inputs!$B:$B,Inputs!O:O) -> 13543.3 | F117: =+_xlfn.XLOOKUP($B117,Inputs!$B:$B,Inputs!P:P) -> 14385.2 | G117: =+_xlfn.XLOOKUP($B117,Inputs!$B:$B,Inputs!Q:Q) -> 20816.2 | H117: =IFERROR(AVERAGE(E117:G117)*(1+H37),"") -> 19580.305 | I117: =IFERROR(AVERAGE(F117:H117)*(1+I37),"") -> 21330.899 | J117: =IFERROR(AVERAGE(G117:I117)*(1+J37),"") -> 23595.023 | K117: =IFERROR(AVERAGE(H117:J117)*(1+K37),"") -> 24248.103 | L117: =IFERROR(AVERAGE(I117:K117)*(1+L37),"") -> 25586.883 | M117: =IFERROR(AVERAGE(J117:L117)*(1+M37),"") -> 26735.689 | N117: =IFERROR(AVERAGE(K117:M117)*(1+N37),"") -> 27442.519 | O117: =IFERROR(AVERAGE(L117:N117)*(1+O37),"") -> 28142.675 | ... Q117: =IFERROR(AVERAGE(N117:P117)*(1+Q37),"") -> 28811.279
B118: growing with revenue | E118: =IFERROR(E117/E$36,"") -> 0.30351444 | F118: =IFERROR(F117/F$36,"") -> 0.43903228 | G118: =IFERROR(G117/G$36,"") -> 0.31447736 | H118: =IFERROR(H117/H$36,"") -> 0.24546755 | I118: =IFERROR(I117/I$36,"") -> 0.22892273 | J118: =IFERROR(J117/J$36,"") -> 0.22081904 | K118: =IFERROR(K117/K$36,"") -> 0.20123175 | L118: =IFERROR(L117/L$36,"") -> 0.19135531 | ... Q118: =IFERROR(Q117/Q$36,"") -> 0.16277513
B120: Total Borrowings | E120: =+_xlfn.XLOOKUP($B120,Inputs!$B:$B,Inputs!O:O) -> 19404.7 | F120: =+_xlfn.XLOOKUP($B120,Inputs!$B:$B,Inputs!P:P) -> 23757 | G120: =+_xlfn.XLOOKUP($B120,Inputs!$B:$B,Inputs!Q:Q) -> 18715 | H120: =IFERROR(G120+H161-H163,"") -> 18715 | I120: =IFERROR(H120+I161-I163,"") -> 39784.213 | J120: =IFERROR(I120+J161-J163,"") -> 39784.213 | K120: =IFERROR(J120+K161-K163,"") -> 57656.03 | L120: =IFERROR(K120+L161-L163,"") -> 61636.611 | M120: =IFERROR(L120+M161-M163,"") -> 79299.825 | N120: =IFERROR(M120+N161-N163,"") -> 84243.886 | O120: =IFERROR(N120+O161-O163,"") -> 102985.36 | ... Q120: =IFERROR(P120+Q161-Q163,"") -> 126120.02
B122: Total Leases | E122: =+_xlfn.XLOOKUP($B122,Inputs!$B:$B,Inputs!O:O) -> 1797.1 | F122: =+_xlfn.XLOOKUP($B122,Inputs!$B:$B,Inputs!P:P) -> 3029.9 | G122: =+_xlfn.XLOOKUP($B122,Inputs!$B:$B,Inputs!Q:Q) -> 2768.4 | H122: =+IFERROR(H123*H36,"") -> 4641.6396 | I122: =+IFERROR(I123*I36,"") -> 5978.536 | J122: =+IFERROR(J123*J36,"") -> 5847.4695 | K122: =+IFERROR(K123*K36,"") -> 7112.4579 | L122: =+IFERROR(L123*L36,"") -> 7929.7584 | M122: =+IFERROR(M123*M36,"") -> 8425.1239 | N122: =+IFERROR(N123*N36,"") -> 9213.493 | O122: =+IFERROR(O123*O36,"") -> 9732.4826 | ... Q122: =+IFERROR(Q123*Q36,"") -> 10356.16
B123: % of revenues | E123: =IFERROR(E122/E$36,"") -> 0.040274217 | F123: =IFERROR(F122/F$36,"") -> 0.092471701 | G123: =IFERROR(G122/G$36,"") -> 0.041823154 | H123: =+IFERROR(AVERAGE(E123:G123),"") -> 0.05818969 | I123: =+IFERROR(AVERAGE(F123:H123),"") -> 0.064161515 | J123: =+IFERROR(AVERAGE(G123:I123),"") -> 0.054724786 | K123: =+IFERROR(AVERAGE(H123:J123),"") -> 0.05902533 | L123: =+IFERROR(AVERAGE(I123:K123),"") -> 0.059303877 | M123: =+IFERROR(AVERAGE(J123:L123),"") -> 0.057684665 | N123: =+IFERROR(AVERAGE(K123:M123),"") -> 0.058671291 | O123: =+IFERROR(AVERAGE(L123:N123),"") -> 0.058553278 | ... Q123: =+IFERROR(AVERAGE(N123:P123),"") -> 0.058509215
A125: x | B125: Cash Flow | E125: =E34 -> 2022 | F125: =F34 -> 2023 | G125: =G34 -> 2024 | H125: =H34 -> 2025 | I125: =I34 -> 2026 | J125: =J34 -> 2027 | K125: =K34 -> 2028 | L125: =L34 -> 2029 | ... Q125: =Q34 -> 2034
B127: D&A (Depreciation & Amortization) | E127: =+E56 -> 679.4 | F127: =+F56 -> 587.1 | G127: =+G56 -> 559.6 | H127: =+H56 -> 674.84081 | I127: =+I56 -> 788.30848 | J127: =+J56 -> 903.98215 | K127: =+K56 -> 1019.4296 | L127: =+L56 -> 1131.235 | ... Q127: =+Q56 -> 1497.4435
B129: Stock Based Compensation | E129: =+_xlfn.XLOOKUP($B129,Inputs!$B:$B,Inputs!O:O) -> 0 | F129: =+_xlfn.XLOOKUP($B129,Inputs!$B:$B,Inputs!P:P) -> 0 | G129: =+_xlfn.XLOOKUP($B129,Inputs!$B:$B,Inputs!Q:Q) -> 0 | H129: =IFERROR(H130*H45,"") -> 0 | I129: =IFERROR(I130*I45,"") -> 0 | J129: =IFERROR(J130*J45,"") -> 0 | K129: =IFERROR(K130*K45,"") -> 0 | L129: =IFERROR(L130*L45,"") -> 0 | M129: =IFERROR(M130*M45,"") -> 0 | N129: =IFERROR(N130*N45,"") -> 0 | O129: =IFERROR(O130*O45,"") -> 0 | ... Q129: =IFERROR(Q130*Q45,"") -> 0
B130: % of SG&A | E130: =+IFERROR(E129/E45,"") -> 0 | F130: =+IFERROR(F129/F45,"") -> 0 | G130: =+IFERROR(G129/G45,"") -> 0 | H130: =IFERROR(AVERAGE(E130:G130),"") -> 0 | I130: =IFERROR(AVERAGE(F130:H130),"") -> 0 | J130: =IFERROR(AVERAGE(G130:I130),"") -> 0 | K130: =IFERROR(AVERAGE(H130:J130),"") -> 0 | L130: =IFERROR(AVERAGE(I130:K130),"") -> 0 | M130: =IFERROR(AVERAGE(J130:L130),"") -> 0 | N130: =IFERROR(AVERAGE(K130:M130),"") -> 0 | O130: =IFERROR(AVERAGE(L130:N130),"") -> 0 | ... Q130: =IFERROR(AVERAGE(N130:P130),"") -> 0
B132: Changes in Net Working Capital | E132: =+_xlfn.XLOOKUP($B132,Inputs!$B:$B,Inputs!O:O) -> -3088.8 | F132: =+_xlfn.XLOOKUP($B132,Inputs!$B:$B,Inputs!P:P) -> 965 | G132: =+_xlfn.XLOOKUP($B132,Inputs!$B:$B,Inputs!Q:Q) -> -6034.6 | H132: =IFERROR(-((H94+H97+H100-H114-H117)-(G94+G97+G100-G114-G117)),"") -> -6746.9939 | I132: =IFERROR(-((I94+I97+I100-I114-I117)-(H94+H97+H100-H114-H117)),"") -> -3606.0711 | J132: =IFERROR(-((J94+J97+J100-J114-J117)-(I94+I97+I100-I114-I117)),"") -> -2744.7086 | K132: =IFERROR(-((K94+K97+K100-K114-K117)-(J94+J97+J100-J114-J117)),"") -> -4583.9116 | L132: =IFERROR(-((L94+L97+L100-L114-L117)-(K94+K97+K100-K114-K117)),"") -> -3728.7823 | M132: =IFERROR(-((M94+M97+M100-M114-M117)-(L94+L97+L100-L114-L117)),"") -> -3466.601 | N132: =IFERROR(-((N94+N97+N100-N114-N117)-(M94+M97+M100-M114-M117)),"") -> -3467.7147 | O132: =IFERROR(-((O94+O97+O100-O114-O117)-(N94+N97+N100-N114-N117)),"") -> -2772.5595 | ... Q132: =IFERROR(-((Q94+Q97+Q100-Q114-Q117)-(P94+P97+P100-P114-P117)),"") -> -1495.7028
B134: Other Operating Adjustments | E134: =+_xlfn.XLOOKUP($B134,Inputs!$B:$B,Inputs!O:O) -> 1476.1 | F134: =+_xlfn.XLOOKUP($B134,Inputs!$B:$B,Inputs!P:P) -> -1222.9 | G134: =+_xlfn.XLOOKUP($B134,Inputs!$B:$B,Inputs!Q:Q) -> 3451.9 | H134: =IFERROR(AVERAGE(E134:G134)*(1+H37),"") -> 1488.3052 | I134: =IFERROR(AVERAGE(F134:H134)*(1+I37),"") -> 1447.4442 | J134: =IFERROR(AVERAGE(G134:I134)*(1+J37),"") -> 2441.6503 | K134: =IFERROR(AVERAGE(H134:J134)*(1+K37),"") -> 2021.3823 | L134: =IFERROR(AVERAGE(I134:K134)*(1+L37),"") -> 2186.235 | M134: =IFERROR(AVERAGE(J134:L134)*(1+M37),"") -> 2420.9823 | N134: =IFERROR(AVERAGE(K134:M134)*(1+N37),"") -> 2375.6545 | O134: =IFERROR(AVERAGE(L134:N134)*(1+O37),"") -> 2463.6929 | ... Q134: =IFERROR(AVERAGE(N134:P134)*(1+Q37),"") -> 2519.4042
B136: Operating Cash Flow | E136: =+_xlfn.XLOOKUP($B136,Inputs!$B:$B,Inputs!O:O) -> 14780.5 | F136: =+_xlfn.XLOOKUP($B136,Inputs!$B:$B,Inputs!P:P) -> 4278.2 | G136: =+_xlfn.XLOOKUP($B136,Inputs!$B:$B,Inputs!Q:Q) -> 29795.9 | H136: =IFERROR(H85+H127+H129+H132+H134,"") -> 7597.4325 | I136: =IFERROR(I85+I127+I129+I132+I134,"") -> 15541.478 | J136: =IFERROR(J85+J127+J129+J132+J134,"") -> 21208.568 | K136: =IFERROR(K85+K127+K129+K132+K134,"") -> 21196.374 | L136: =IFERROR(L85+L127+L129+L132+L134,"") -> 26024.582 | M136: =IFERROR(M85+M127+M129+M132+M134,"") -> 29518.239 | N136: =IFERROR(N85+N127+N129+N132+N134,"") -> 31945.514 | O136: =IFERROR(O85+O127+O129+O132+O134,"") -> 35127.112 | ... Q136: =IFERROR(Q85+Q127+Q129+Q132+Q134,"") -> 38954.195
B138: Net CapEx | E138: =+_xlfn.XLOOKUP($B138,Inputs!$B:$B,Inputs!O:O) -> -19424.2 | F138: =+_xlfn.XLOOKUP($B138,Inputs!$B:$B,Inputs!P:P) -> -7239.5 | G138: =+_xlfn.XLOOKUP($B138,Inputs!$B:$B,Inputs!Q:Q) -> -16595.8 | H138: =IFERROR(H140+H143,"") -> -27178.341 | I138: =IFERROR(I140+I143,"") -> -31608.232 | J138: =IFERROR(J140+J143,"") -> -36638.734 | K138: =IFERROR(K140+K143,"") -> -41027.39 | L138: =IFERROR(L140+L143,"") -> -45482.143 | M138: =IFERROR(M140+M143,"") -> -49704.531 | N138: =IFERROR(N140+N143,"") -> -53255.395 | O138: =IFERROR(O140+O143,"") -> -56255.927 | ... Q138: =IFERROR(Q140+Q143,"") -> -59536.876
B140: Acquisition of Fixed & Intangibles | E140: =+_xlfn.XLOOKUP($B140,Inputs!$B:$B,Inputs!O:O) -> -19748.9 | F140: =+_xlfn.XLOOKUP($B140,Inputs!$B:$B,Inputs!P:P) -> -8779.8 | G140: =+_xlfn.XLOOKUP($B140,Inputs!$B:$B,Inputs!Q:Q) -> -16662.6 | H140: =+H141*H36 -> -27918.586 | I140: =+I141*I36 -> -32612.815 | J140: =+J141*J36 -> -37398.307 | K140: =+K141*K36 -> -42174.44 | L140: =+L141*L36 -> -46799.899 | M140: =+M141*M36 -> -51119.19 | N140: =+N141*N36 -> -54962.529 | O140: =+O141*O36 -> -58175.546 | ... Q140: =+Q141*Q36 -> -61950.175
B141: % of revenue | E141: =+E140/E36 -> -0.4425861 | F141: =+F140/F36 -> -0.26795704 | G141: =+G140/G36 -> -0.25172752 | H141: -0.35 | I141: -0.35 | J141: -0.35 | K141: -0.35 | L141: -0.35 | M141: -0.35 | N141: -0.35 | O141: -0.35 | P141: -0.35 | Q141: -0.35
B143: Disposal of Fixed & Intangibles | E143: =+_xlfn.XLOOKUP($B143,Inputs!$B:$B,Inputs!O:O) -> 324.7 | F143: =+_xlfn.XLOOKUP($B143,Inputs!$B:$B,Inputs!P:P) -> 1540.3 | G143: =+_xlfn.XLOOKUP($B143,Inputs!$B:$B,Inputs!Q:Q) -> 66.8 | H143: =IFERROR(H144*G104,"") -> 740.24518 | I143: =IFERROR(I144*H104,"") -> 1004.5825 | J143: =IFERROR(J144*I104,"") -> 759.5724 | K143: =IFERROR(K144*J104,"") -> 1147.0497 | L143: =IFERROR(L144*K104,"") -> 1317.756 | M143: =IFERROR(M144*L104,"") -> 1414.6594 | N143: =IFERROR(N144*M104,"") -> 1707.1347 | O143: =IFERROR(O144*N104,"") -> 1919.6189 | ... Q143: =IFERROR(Q144*P104,"") -> 2413.2984
B144: Disposal Rate (% Gross PP&E) | E144: =IFERROR(E143/E104,"") -> 0.0024151607 | F144: =IFERROR(F143/F104,"") -> 0.011075216 | G144: =IFERROR(G143/G104,"") -> 0.00041837702 | H144: =IFERROR(AVERAGE(E144:G144),"") -> 0.0046362511 | I144: =IFERROR(AVERAGE(F144:H144),"") -> 0.0053766146 | J144: =IFERROR(AVERAGE(G144:I144),"") -> 0.0034770809 | K144: =IFERROR(AVERAGE(H144:J144),"") -> 0.0044966488 | L144: =IFERROR(AVERAGE(I144:K144),"") -> 0.0044501148 | M144: =IFERROR(AVERAGE(J144:L144),"") -> 0.0041412815 | N144: =IFERROR(AVERAGE(K144:M144),"") -> 0.0043626817 | O144: =IFERROR(AVERAGE(L144:N144),"") -> 0.004318026 | ... Q144: =IFERROR(AVERAGE(N144:P144),"") -> 0.0043182347
B146: Net Cash from Investments & Acquisitions | E146: =+_xlfn.XLOOKUP($B146,Inputs!$B:$B,Inputs!O:O) -> -38696.4 | F146: =+_xlfn.XLOOKUP($B146,Inputs!$B:$B,Inputs!P:P) -> -14491.2 | G146: =+_xlfn.XLOOKUP($B146,Inputs!$B:$B,Inputs!Q:Q) -> -33208.7 | H146: 0 | I146: 0 | J146: 0 | K146: 0 | L146: 0 | M146: 0 | N146: 0 | O146: 0 | P146: 0 | Q146: 0
B148: Other Investing Inflows (Outflows) | E148: =+_xlfn.XLOOKUP($B148,Inputs!$B:$B,Inputs!O:O) -> 40236.9 | F148: =+_xlfn.XLOOKUP($B148,Inputs!$B:$B,Inputs!P:P) -> 14396 | G148: =+_xlfn.XLOOKUP($B148,Inputs!$B:$B,Inputs!Q:Q) -> 31799.9 | H148: =IFERROR(AVERAGE(E148:G148)*(1+H37),"") -> 34719.274 | I148: =IFERROR(AVERAGE(F148:H148)*(1+I37),"") -> 31506.748 | J148: =IFERROR(AVERAGE(G148:I148)*(1+J37),"") -> 37469.969 | K148: =IFERROR(AVERAGE(H148:J148)*(1+K37),"") -> 38979.665 | L148: =IFERROR(AVERAGE(I148:K148)*(1+L37),"") -> 39932.147 | M148: =IFERROR(AVERAGE(J148:L148)*(1+M37),"") -> 42374.325 | N148: =IFERROR(AVERAGE(K148:M148)*(1+N37),"") -> 43468.3 | O148: =IFERROR(AVERAGE(L148:N148)*(1+O37),"") -> 44375.784 | ... Q148: =IFERROR(AVERAGE(N148:P148)*(1+Q37),"") -> 45546.419
B150: Investing Cash Flow | E150: =+_xlfn.XLOOKUP($B150,Inputs!$B:$B,Inputs!O:O) -> -17883.7 | F150: =+_xlfn.XLOOKUP($B150,Inputs!$B:$B,Inputs!P:P) -> -7334.7 | G150: =+_xlfn.XLOOKUP($B150,Inputs!$B:$B,Inputs!Q:Q) -> -18004.6 | H150: =IFERROR(+H138+H146+H148,"") -> 7540.9333 | I150: =IFERROR(+I138+I146+I148,"") -> -101.48391 | J150: =IFERROR(+J138+J146+J148,"") -> 831.23516 | K150: =IFERROR(+K138+K146+K148,"") -> -2047.7253 | L150: =IFERROR(+L138+L146+L148,"") -> -5549.9961 | M150: =IFERROR(+M138+M146+M148,"") -> -7330.2054 | N150: =IFERROR(+N138+N146+N148,"") -> -9787.095 | O150: =IFERROR(+O138+O146+O148,"") -> -11880.143 | ... Q150: =IFERROR(+Q138+Q146+Q148,"") -> -13990.457
B152: Dividends | E152: =+_xlfn.XLOOKUP($B152,Inputs!$B:$B,Inputs!O:O) -> -1680.9 | F152: =+_xlfn.XLOOKUP($B152,Inputs!$B:$B,Inputs!P:P) -> -825.6 | G152: =+_xlfn.XLOOKUP($B152,Inputs!$B:$B,Inputs!Q:Q) -> -826.3 | H152: =+IFERROR(H153*_xlfn.XLOOKUP("Net Income",$B:$B,$H:$H),"") -> 0 | I152: =+IFERROR(I153*_xlfn.XLOOKUP("Net Income",$B:$B,$H:$H),"") -> 0 | J152: =+IFERROR(J153*_xlfn.XLOOKUP("Net Income",$B:$B,$H:$H),"") -> 0 | K152: =+IFERROR(K153*_xlfn.XLOOKUP("Net Income",$B:$B,$H:$H),"") -> 0 | L152: =+IFERROR(L153*_xlfn.XLOOKUP("Net Income",$B:$B,$H:$H),"") -> 0 | M152: =+IFERROR(M153*_xlfn.XLOOKUP("Net Income",$B:$B,$H:$H),"") -> 0 | N152: =+IFERROR(N153*_xlfn.XLOOKUP("Net Income",$B:$B,$H:$H),"") -> 0 | O152: =+IFERROR(O153*_xlfn.XLOOKUP("Net Income",$B:$B,$H:$H),"") -> 0 | ... Q152: =+IFERROR(Q153*_xlfn.XLOOKUP("Net Income",$B:$B,$H:$H),"") -> 0
...

Sheet Inputs
B2: Inputs
B3: in billions of KRW
A4: x | B4: Income Statement | G4: 2014 | H4: =+G4+1 -> 2015 | I4: =+H4+1 -> 2016 | J4: =+I4+1 -> 2017 | K4: =+J4+1 -> 2018 | L4: =+K4+1 -> 2019 | M4: =+L4+1 -> 2020 | N4: =+M4+1 -> 2021 | O4: =+N4+1 -> 2022 | ... Q4: =+P4+1 -> 2024 | R4: ="CAGR "&$G$4&" - "&$Q$4 -> CAGR 2014 - 2024
B6: Revenue (Sales) | G6: =IS!B6 -> 17125.6 | H6: =IS!C6 -> 18798 | I6: =IS!D6 -> 17198 | J6: =IS!E6 -> 30109.4 | K6: =IS!F6 -> 40445.1 | L6: =IS!G6 -> 26990.7 | M6: =IS!H6 -> 31900.4 | N6: =IS!I6 -> 42997.8 | ... Q6: =IS!L6 -> 66193 | R6: =IFERROR((Q6/G6)^(1/COUNT($G$4:$Q$4))-1,"") -> 0.13078165 | S6: 11 | T6: =+S6-1 -> 10 | U6: =+T6-1 -> 9 | V6: =+U6-1 -> 8 | W6: =+V6-1 -> 7 | X6: =+W6-1 -> 6 | Y6: =+X6-1 -> 5 | Z6: =+Y6-1 -> 4 | AA6: =+Z6-1 -> 3 | AB6: =+AA6-1 -> 2
B7: COGS (Cost of Goods Sold) | G7: =IS!B9 -> 9461.7 | H7: =IS!C9 -> 10515.4 | I7: =IS!D9 -> 10787.1 | J7: =IS!E9 -> 12701.8 | K7: =IS!F9 -> 15180.8 | L7: =IS!G9 -> 18818.8 | M7: =IS!H9 -> 21089.8 | N7: =IS!I9 -> 24045.6 | ... Q7: =IS!L9 -> 34364.8 | R7: =IFERROR((Q7/G7)^(1/COUNT($G$4:$Q$4))-1,"") -> 0.12440363 | S7: =+SLOPE(G6:$Q$6,G9:$Q$9) -> 12.099544 | T7: =+SLOPE(H9:$Q$9,H6:$Q$6) -> 0.052642291 | U7: =+SLOPE(I9:$Q$9,I6:$Q$6) -> 0.050518312 | V7: =+SLOPE(J9:$Q$9,J6:$Q$6) -> 0.047846426 | W7: =+SLOPE(K9:$Q$9,K6:$Q$6) -> 0.041314076 | X7: =+SLOPE(L9:$Q$9,L6:$Q$6) -> 0.04089608 | Y7: =+SLOPE(M9:$Q$9,M6:$Q$6) -> 0.033906633 | Z7: =+SLOPE(N9:$Q$9,N6:$Q$6) -> 0.017723202 | AA7: =+SLOPE(O9:$Q$9,O6:$Q$6) -> 0.011602044 | AB7: =+SLOPE(P9:$Q$9,P6:$Q$6) -> 0.015131345 | AC7: b1
B8: Gross Profit | G8: =G6-G7 -> 7663.9 | H8: =H6-H7 -> 8282.6 | I8: =I6-I7 -> 6410.9 | J8: =J6-J7 -> 17407.6 | K8: =K6-K7 -> 25264.3 | L8: =L6-L7 -> 8171.9 | M8: =M6-M7 -> 10810.6 | N8: =N6-N7 -> 18952.2 | ... Q8: =Q6-Q7 -> 31828.2 | R8: =IFERROR((Q8/G8)^(1/COUNT($G$4:$Q$4))-1,"") -> 0.13818996 | S8: =+INTERCEPT(G9:$Q$9,G6:$Q$6) -> 119.56057 | T8: =+INTERCEPT(H9:$Q$9,H6:$Q$6) -> 179.50766 | U8: =+INTERCEPT(I9:$Q$9,I6:$Q$6) -> 278.11134 | V8: =+INTERCEPT(J9:$Q$9,J6:$Q$6) -> 400.12442 | W8: =+INTERCEPT(K9:$Q$9,K6:$Q$6) -> 753.75928 | X8: =+INTERCEPT(L9:$Q$9,L6:$Q$6) -> 920.01199 | Y8: =+INTERCEPT(M9:$Q$9,M6:$Q$6) -> 1289.5259 | Z8: =+INTERCEPT(N9:$Q$9,N6:$Q$6) -> 2206.8847 | ... AB8: =+INTERCEPT(P9:$Q$9,P6:$Q$6) -> 2363.3109 | AC8: b0
B9: SG&A (Selling, General & Administrative) | G9: =+IS!B16 -> 909.2 | H9: =+IS!C16 -> 989.4 | I9: =+IS!D16 -> 1015.2 | J9: =+IS!E16 -> 1233 | K9: =+IS!F16 -> 1529.8 | L9: =+IS!G16 -> 1703.3 | M9: =+IS!H16 -> 1721.2 | N9: =+IS!I16 -> 2245.8 | ... Q9: =+IS!L16 -> 3364.9 | R9: =IFERROR((Q9/G9)^(1/COUNT($G$4:$Q$4))-1,"") -> 0.12632778
B10: R&D (Research & Development) | G10: =+IS!B19 -> 1409.5 | H10: =+IS!C19 -> 1620.3 | I10: =+IS!D19 -> 1744.7 | J10: =+IS!E19 -> 1975.4 | K10: =+IS!F19 -> 2284 | L10: =+IS!G19 -> 2855.6 | M10: =+IS!H19 -> 3111.3 | N10: =+IS!I19 -> 3551.2 | ... Q10: =+IS!L19 -> 4436.3 | R10: =IFERROR((Q10/G10)^(1/COUNT($G$4:$Q$4))-1,"") -> 0.10986131 | S10: Y = b0 + xb1
B11: Other Operating (Income) Expenses | G11: =+IS!B21 -> 0 | H11: =+IS!C21 -> 0 | I11: =+IS!D21 -> 0 | J11: =+IS!E21 -> 0 | K11: =+IS!F21 -> 0 | L11: =+IS!G21 -> 0 | M11: =+IS!H21 -> 0 | N11: =+IS!I21 -> 0 | ... Q11: =+IS!L21 -> 0 | R11: =IFERROR((Q11/G11)^(1/COUNT($G$4:$Q$4))-1,"")
B12: EBITDA | G12: =+G8-G9-G10-G11 -> 5345.2 | H12: =+H8-H9-H10-H11 -> 5672.9 | I12: =+I8-I9-I10-I11 -> 3651 | J12: =+J8-J9-J10-J11 -> 14199.2 | K12: =+K8-K9-K10-K11 -> 21450.5 | L12: =+L8-L9-L10-L11 -> 3613 | M12: =+M8-M9-M10-M11 -> 5978.1 | N12: =+N8-N9-N10-N11 -> 13155.2 | ... Q12: =+Q8-Q9-Q10-Q11 -> 24027 | R12: =IFERROR((Q12/G12)^(1/COUNT($G$4:$Q$4))-1,"") -> 0.14640903 | S12: Costs = 2363 + 0.02*revenue
B13: D&A (Depreciation & Amortization) | G13: =+IS!B20 -> 228.5 | H13: =+IS!C20 -> 329.1 | I13: =+IS!D20 -> 364.9 | J13: =+IS!E20 -> 444.7 | K13: =+IS!F20 -> 572.6 | L13: =+IS!G20 -> 893.8 | M13: =+IS!H20 -> 965.5 | N13: =+IS!I20 -> 744.9 | ... Q13: =+IS!L20 -> 559.6 | R13: =IFERROR((Q13/G13)^(1/COUNT($G$4:$Q$4))-1,"") -> 0.08483294 | S13: =+AB8+AB7*Q6 -> 3364.9
B14: Depreciation Expense | G14: 59 | H14: 90 | I14: 82 | J14: 96 | K14: 130 | L14: 206 | M14: 246 | N14: 219 | O14: 265 | P14: 304 | Q14: 303 | R14: =IFERROR((Q14/G14)^(1/COUNT($G$4:$Q$4))-1,"") -> 0.16037709 | S14: 3365
B15: Amortization Expense | G15: 170 | H15: 239 | I15: 282 | J15: 349 | K15: 442 | L15: 687 | M15: 720 | N15: 526 | O15: 414 | P15: 283 | Q15: 257 | R15: =IFERROR((Q15/G15)^(1/COUNT($G$4:$Q$4))-1,"") -> 0.038285396
B16: Operating Income (EBIT) | G16: =+G12-G13 -> 5116.7 | H16: =+H12-H13 -> 5343.8 | I16: =+I12-I13 -> 3286.1 | J16: =+J12-J13 -> 13754.5 | K16: =+K12-K13 -> 20877.9 | L16: =+L12-L13 -> 2719.2 | M16: =+M12-M13 -> 5012.6 | N16: =+N12-N13 -> 12410.3 | ... Q16: =+Q12-Q13 -> 23467.4 | R16: =IFERROR((Q16/G16)^(1/COUNT($G$4:$Q$4))-1,"") -> 0.14850818
B17: Net Interest Expense (Income) | G17: =+G18-G19 -> 118.3 | H17: =+H18-H19 -> 77.8 | I17: =+I18-I19 -> 85.9 | J17: =+J18-J19 -> 69.6 | K17: =+K18-K19 -> 32.1 | L17: =+L18-L19 -> 215.3 | M17: =+M18-M19 -> 225.6 | N17: =+N18-N19 -> 237.6 | ... Q17: =+Q18-Q19 -> 1000.4 | R17: =IFERROR((Q17/G17)^(1/COUNT($G$4:$Q$4))-1,"") -> 0.21419909
B18: Interest Expense | G18: =+IS!B25 -> 170.4 | H18: =+IS!C25 -> 118.5 | I18: =+IS!D25 -> 120.1 | J18: =+IS!E25 -> 123.9 | K18: =+IS!F25 -> 94.6 | L18: =+IS!G25 -> 245.4 | M18: =+IS!H25 -> 253.5 | N18: =+IS!I25 -> 260 | ... Q18: =+IS!L25 -> 1345.2 | R18: =IFERROR((Q18/G18)^(1/COUNT($G$4:$Q$4))-1,"") -> 0.2066305 | T18: Revenue growth | V18: =H6/G6-1 -> 0.097654973 | W18: =I6/H6-1 -> -0.085115438 | X18: =J6/I6-1 -> 0.75075009 | Y18: =K6/J6-1 -> 0.34327154 | Z18: =L6/K6-1 -> -0.33265834 | AA18: =M6/L6-1 -> 0.1819034 | AB18: =N6/M6-1 -> 0.34787652 | AC18: =O6/N6-1 -> 0.037764723 | ... AE18: =Q6/P6-1 -> 1.0201918
B19: Interest Income | G19: =+IS!B26 -> 52.1 | H19: =+IS!C26 -> 40.7 | I19: =+IS!D26 -> 34.2 | J19: =+IS!E26 -> 54.3 | K19: =+IS!F26 -> 62.5 | L19: =+IS!G26 -> 30.1 | M19: =+IS!H26 -> 27.9 | N19: =+IS!I26 -> 22.4 | ... Q19: =+IS!L26 -> 344.8 | R19: =IFERROR((Q19/G19)^(1/COUNT($G$4:$Q$4))-1,"") -> 0.18744028 | T19: Standard deviation | V19: =_xlfn.STDEV.S(V18:AE18) -> 0.42642276
B20: FX (Gain) Loss | G20: =+IS!B28 -> -128.5 | H20: =+IS!C28 -> -57.6 | I20: =+IS!D28 -> -38.1 | J20: =+IS!E28 -> 231.6 | K20: =+IS!F28 -> -340.1 | L20: =+IS!G28 -> -99.4 | M20: =+IS!H28 -> 190.4 | N20: =+IS!I28 -> -488.6 | ... Q20: =+IS!L28 -> -268.8 | R20: =IFERROR((Q20/G20)^(1/COUNT($G$4:$Q$4))-1,"") -> 0.069396454
B21: Other Non-Operating (Income) Expenses | G21: =+IS!B30+IS!B29+IS!B27+IS!B32 -> 79.3 | H21: =+IS!C30+IS!C29+IS!C27+IS!C32 -> 54.5 | I21: =+IS!D30+IS!D29+IS!D27+IS!D32 -> 21.7 | J21: =+IS!E30+IS!E29+IS!E27+IS!E32 -> 13.7 | K21: =+IS!F30+IS!F29+IS!F27+IS!F32 -> -155.3 | L21: =+IS!G30+IS!G29+IS!G27+IS!G32 -> 170.6 | M21: =+IS!H30+IS!H29+IS!H27+IS!H32 -> -1640.4 | N21: =+IS!I30+IS!I29+IS!I27+IS!I32 -> -754.7 | ... Q21: =+IS!L30+IS!L29+IS!L27+IS!L32 -> -1149.7 | R21: =IFERROR((Q21/G21)^(1/COUNT($G$4:$Q$4))-1,"") -> -2.2751867 | T21: total d&a | U21: =+G67 -> 3444 | V21: =+H67 -> 3953.2 | W21: =+I67 -> 4456.3 | X21: =+J67 -> 5026.1 | Y21: =+K67 -> 6428.3 | Z21: =+L67 -> 8620.4 | AA21: =+M67 -> 9771.9 | AB21: =+N67 -> 10656.7 | ... AE21: =+Q67 -> 12581.5
B22: Pre-Tax Income (EBT) | G22: =+G16-G17-G20-G21 -> 5047.6 | H22: =+H16-H17-H20-H21 -> 5269.1 | I22: =+I16-I17-I20-I21 -> 3216.6 | J22: =+J16-J17-J20-J21 -> 13439.6 | K22: =+K16-K17-K20-K21 -> 21341.2 | L22: =+L16-L17-L20-L21 -> 2432.7 | M22: =+M16-M17-M20-M21 -> 6237 | N22: =+N16-N17-N20-N21 -> 13416 | ... Q22: =+Q16-Q17-Q20-Q21 -> 23885.5 | R22: =IFERROR((Q22/G22)^(1/COUNT($G$4:$Q$4))-1,"") -> 0.15177627 | T22: opex D&A | U22: =+G13 -> 228.5 | V22: =+H13 -> 329.1 | W22: =+I13 -> 364.9 | X22: =+J13 -> 444.7 | Y22: =+K13 -> 572.6 | Z22: =+L13 -> 893.8 | AA22: =+M13 -> 965.5 | AB22: =+N13 -> 744.9 | ... AE22: =+Q13 -> 559.6
B23: Tax Expense (Benefits) | G23: =+IS!B44 -> 852.5 | H23: =+IS!C44 -> 945.5 | I23: =+IS!D44 -> 256 | J23: =+IS!E44 -> 2797.3 | K23: =+IS!F44 -> 5801 | L23: =+IS!G44 -> 423.6 | M23: =+IS!H44 -> 1478.1 | N23: =+IS!I44 -> 3799.8 | ... Q23: =+IS!L44 -> 4088.4 | R23: =IFERROR((Q23/G23)^(1/COUNT($G$4:$Q$4))-1,"") -> 0.1531778 | T23: COGS d&a | U23: =+U21-U22 -> 3215.5 | V23: =+V21-V22 -> 3624.1 | W23: =+W21-W22 -> 4091.4 | X23: =+X21-X22 -> 4581.4 | Y23: =+Y21-Y22 -> 5855.7 | Z23: =+Z21-Z22 -> 7726.6 | AA23: =+AA21-AA22 -> 8806.4 | AB23: =+AB21-AB22 -> 9911.8 | ... AE23: =+AE21-AE22 -> 12021.9 | AF23: 11y avg | AG23: 6y avg | AH23: 3y avg
B24: Net Income | G24: =+G22-G23 -> 4195.1 | H24: =+H22-H23 -> 4323.6 | I24: =+I22-I23 -> 2960.6 | J24: =+J22-J23 -> 10642.3 | K24: =+K22-K23 -> 15540.2 | L24: =+L22-L23 -> 2009.1 | M24: =+M22-M23 -> 4758.9 | N24: =+N22-N23 -> 9616.2 | ... Q24: =+Q22-Q23 -> 19797.1 | R24: =IFERROR((Q24/G24)^(1/COUNT($G$4:$Q$4))-1,"") -> 0.15148937 | T24: total d&A % cogs | U24: =+U21/G7 -> 0.36399379 | V24: =+V21/H7 -> 0.37594385 | W24: =+W21/I7 -> 0.41311381 | X24: =+X21/J7 -> 0.39569982 | Y24: =+Y21/K7 -> 0.42344936 | Z24: =+Z21/L7 -> 0.45807384 | AA24: =+AA21/M7 -> 0.46334721 | AB24: =+AB21/N7 -> 0.44318711 | ... AE24: =+AE21/Q7 -> 0.36611591 | AF24: =+AVERAGE(U24:AE24) -> 0.41833136 | AG24: =+AVERAGE(Z24:AE24) -> 0.43824073 | AH24: =+AVERAGE(AC24:AE24) -> 0.42161206
B25: EPS basic | G25: =+IS!B64 -> 5842 | H25: =+IS!C64 -> 6002 | I25: =+IS!D64 -> 4184 | J25: =+IS!E64 -> 15073 | K25: =+IS!F64 -> 22255 | L25: =+IS!G64 -> 2933 | M25: =+IS!H64 -> 6952 | N25: =+IS!I64 -> 13989 | ... Q25: =+IS!L64 -> 28732 | R25: =IFERROR((Q25/G25)^(1/COUNT($G$4:$Q$4))-1,"") -> 0.15582292 | T25: COGS d&a % cogs | U25: =+U23/G7 -> 0.33984379 | V25: =+V23/H7 -> 0.3446469 | W25: =+W23/I7 -> 0.37928637 | X25: =+X23/J7 -> 0.36068904 | Y25: =+Y23/K7 -> 0.38573066 | Z25: =+Z23/L7 -> 0.41057878 | AA25: =+AA23/M7 -> 0.41756679 | AB25: =+AB23/N7 -> 0.41220847 | ... AE25: =+AE23/Q7 -> 0.3498318 | AF25: =+AVERAGE(U25:AE25) -> 0.38709447 | AG25: =+AVERAGE(AA25:AF25) -> 0.40405968 | AH25: =+AVERAGE(AC25:AE25) -> 0.40249612
B26: EPS diluted | G26: =+IS!B69 -> 5842 | H26: =+IS!C69 -> 6002 | I26: =+IS!D69 -> 4184 | J26: =+IS!E69 -> 15072 | K26: =+IS!F69 -> 22252 | L26: =+IS!G69 -> 2932 | M26: =+IS!H69 -> 6950 | N26: =+IS!I69 -> 13984 | ... Q26: =+IS!L69 -> 28419 | R26: =IFERROR((Q26/G26)^(1/COUNT($G$4:$Q$4))-1,"") -> 0.15467255
B27: Basic Weighted Average Shares | G27: =+IS!B63 -> 718.2 | H27: =+IS!C63 -> 720.1 | I27: =+IS!D63 -> 706 | J27: =+IS!E63 -> 706 | K27: =+IS!F63 -> 698.3 | L27: =+IS!G63 -> 684 | M27: =+IS!H63 -> 684 | N27: =+IS!I63 -> 686.4 | ... Q27: =+IS!L63 -> 688.7 | R27: =IFERROR((Q27/G27)^(1/COUNT($G$4:$Q$4))-1,"") -> -0.0038056781
B28: Diluted Weighted Average Shares | G28: =+IS!B68 -> 718.2 | H28: =+IS!C68 -> 720.1 | I28: =+IS!D68 -> 706 | J28: =+IS!E68 -> 706 | K28: =+IS!F68 -> 698.4 | L28: =+IS!G68 -> 684.1 | M28: =+IS!H68 -> 684.1 | N28: =+IS!I68 -> 686.7 | ... Q28: =+IS!L68 -> 709.8 | R28: =IFERROR((Q28/G28)^(1/COUNT($G$4:$Q$4))-1,"") -> -0.0010689593
A30: x | B30: Balance Sheet | G30: 2014 | H30: =+G30+1 -> 2015 | I30: =+H30+1 -> 2016 | J30: =+I30+1 -> 2017 | K30: =+J30+1 -> 2018 | L30: =+K30+1 -> 2019 | M30: =+L30+1 -> 2020 | N30: =+M30+1 -> 2021 | O30: =+N30+1 -> 2022 | ... Q30: =+P30+1 -> 2024 | R30: ="CAGR "&$G$4&" - "&$Q$4 -> CAGR 2014 - 2024
B32: Cash & Cash Equivalents & ST Investments | G32: =+SUM(G33:G34) -> 3977.2 | H32: =+SUM(H33:H34) -> 4682.9 | I32: =+SUM(I33:I34) -> 4052 | J32: =+SUM(J33:J34) -> 8320.2 | K32: =+SUM(K33:K34) -> 8135.8 | L32: =+SUM(L33:L34) -> 3760.9 | M32: =+SUM(M33:M34) -> 4627.9 | N32: =+SUM(N33:N34) -> 8351.6 | ... Q32: =+SUM(Q33:Q34) -> 13928 | R32: =IFERROR((Q32/G32)^(1/COUNT($G$4:$Q$4))-1,"") -> 0.12068316
B33: Cash & Cash Equivalents | G33: =+BS!B8 -> 436.8 | H33: =+BS!C8 -> 1175.7 | I33: =+BS!D8 -> 613.8 | J33: =+BS!E8 -> 2950 | K33: =+BS!F8 -> 2349.3 | L33: =+BS!G8 -> 2306.1 | M33: =+BS!H8 -> 2976 | N33: =+BS!I8 -> 5058 | ... Q33: =+BS!L8 -> 11205.1 | R33: =IFERROR((Q33/G33)^(1/COUNT($G$4:$Q$4))-1,"") -> 0.34308349
B34: Short-Term Investments | G34: =+BS!B9 -> 3540.4 | H34: =+BS!C9 -> 3507.2 | I34: =+BS!D9 -> 3438.2 | J34: =+BS!E9 -> 5370.2 | K34: =+BS!F9 -> 5786.5 | L34: =+BS!G9 -> 1454.8 | M34: =+BS!H9 -> 1651.9 | N34: =+BS!I9 -> 3293.6 | ... Q34: =+BS!L9 -> 2722.9 | R34: =IFERROR((Q34/G34)^(1/COUNT($G$4:$Q$4))-1,"") -> -0.0235849
B35: Accounts Receivable | G35: =+BS!B11 -> 3732.9 | H35: =+BS!C11 -> 2628.4 | I35: =+BS!D11 -> 3251.7 | J35: =+BS!E11 -> 5552.8 | K35: =+BS!F11 -> 6320 | L35: =+BS!G11 -> 4261.7 | M35: =+BS!H11 -> 4931.3 | N35: =+BS!I11 -> 8267.1 | ... Q35: =+BS!L11 -> 13019 | R35: =IFERROR((Q35/G35)^(1/COUNT($G$4:$Q$4))-1,"") -> 0.12026566
B36: Inventory | G36: =+BS!B14 -> 1497.6 | H36: =+BS!C14 -> 1923.4 | I36: =+BS!D14 -> 2026.2 | J36: =+BS!E14 -> 2640.4 | K36: =+BS!F14 -> 4422.7 | L36: =+BS!G14 -> 5295.8 | M36: =+BS!H14 -> 6136.3 | N36: =+BS!I14 -> 8950.1 | ... Q36: =+BS!L14 -> 13313.9 | R36: =IFERROR((Q36/G36)^(1/COUNT($G$4:$Q$4))-1,"") -> 0.21973222
B37: Prepaid expenses and Other Current Assets | G37: =+G38-G32-G35-G36 -> 1155.8 | H37: =+H38-H32-H35-H36 -> 525.3 | I37: =+I38-I32-I35-I36 -> 509.1 | J37: =+J38-J32-J35-J36 -> 797 | K37: =+K38-K32-K35-K36 -> 1015.6 | L37: =+L38-L32-L35-L36 -> 1139.2 | M37: =+M38-M32-M35-M36 -> 875.5 | N37: =+N38-N32-N35-N36 -> 1338.3 | ... Q37: =+Q38-Q32-Q35-Q36 -> 2018 | R37: =IFERROR((Q37/G37)^(1/COUNT($G$4:$Q$4))-1,"") -> 0.051970345
B38: Current Assets | G38: =+BS!B25 -> 10363.5 | H38: =+BS!C25 -> 9760 | I38: =+BS!D25 -> 9839 | J38: =+BS!E25 -> 17310.4 | K38: =+BS!F25 -> 19894.1 | L38: =+BS!G25 -> 14457.6 | M38: =+BS!H25 -> 16571 | N38: =+BS!I25 -> 26907.1 | ... Q38: =+BS!L25 -> 42278.9 | R38: =IFERROR((Q38/G38)^(1/COUNT($G$4:$Q$4))-1,"") -> 0.13634618
B39: Net PP&E (Property, Plant and Equipment) | G39: =+G40-G41 -> 14090.4 | H39: =+H40-H41 -> 16966.3 | I39: =+I40-I41 -> 18777.4 | J39: =+J40-J41 -> 24062.6 | K39: =+K40-K41 -> 34952.6 | L39: =+L40-L41 -> 41656.6 | M39: =+M40-M41 -> 42938.2 | N39: =+N40-N41 -> 54823 | ... Q39: =+Q40-Q41 -> 62644.3 | R39: =IFERROR((Q39/G39)^(1/COUNT($G$4:$Q$4))-1,"") -> 0.14526317
B40: Gross PP&E (Property, Plant and Equipment) | G40: =+BS!B27 -> 40213.2 | H40: =+BS!C27 -> 46037.9 | I40: =+BS!D27 -> 50547 | J40: =+BS!E27 -> 56259.4 | K40: =+BS!F27 -> 71880.7 | L40: =+BS!G27 -> 85340.8 | M40: =+BS!H27 -> 94373.2 | N40: =+BS!I27 -> 115737.7 | ... Q40: =+BS!L27 -> 159664.6 | R40: =IFERROR((Q40/G40)^(1/COUNT($G$4:$Q$4))-1,"") -> 0.13354822
B41: Accumulated Depreciation | G41: =+BS!B28 -> 26122.8 | H41: =+BS!C28 -> 29071.6 | I41: =+BS!D28 -> 31769.6 | J41: =+BS!E28 -> 32196.8 | K41: =+BS!F28 -> 36928.1 | L41: =+BS!G28 -> 43684.2 | M41: =+BS!H28 -> 51435 | N41: =+BS!I28 -> 60914.7 | ... Q41: =+BS!L28 -> 97020.3 | R41: =IFERROR((Q41/G41)^(1/COUNT($G$4:$Q$4))-1,"") -> 0.1266886
B42: Right-of-Use Assets | R42: =IFERROR((Q42/G42)^(1/COUNT($G$4:$Q$4))-1,"")
B43: Intangibles | G43: =+BS!B33 -> 1336.7 | H43: =+BS!C33 -> 1704.9 | I43: =+BS!D33 -> 1915.6 | J43: =+BS!E33 -> 2247.3 | K43: =+BS!F33 -> 2678.8 | L43: =+BS!G33 -> 2571 | M43: =+BS!H33 -> 3400.3 | N43: =+BS!I33 -> 4797.2 | ... Q43: =+BS!L33 -> 4018.8 | R43: =IFERROR((Q43/G43)^(1/COUNT($G$4:$Q$4))-1,"") -> 0.10524923
B44: Goodwill | G44: =+BS!B34 -> 704.2 | H44: =+BS!C34 -> 720.8 | I44: =+BS!D34 -> 730.2 | J44: =+BS!E34 -> 695.1 | K44: =+BS!F34 -> 709.8 | L44: =+BS!G34 -> 720.2 | M44: =+BS!H34 -> 701.6 | N44: =+BS!I34 -> 1572 | ... Q44: =+BS!L34 -> 848.8 | R44: =IFERROR((Q44/G44)^(1/COUNT($G$4:$Q$4))-1,"") -> 0.017123239
B45: Intangibles excl. Goodwill | G45: =+G43-G44 -> 632.5 | H45: =+H43-H44 -> 984.1 | I45: =+I43-I44 -> 1185.4 | J45: =+J43-J44 -> 1552.2 | K45: =+K43-K44 -> 1969 | L45: =+L43-L44 -> 1850.8 | M45: =+M43-M44 -> 2698.7 | N45: =+N43-N44 -> 3225.2 | ... Q45: =+Q43-Q44 -> 3170
B46: Other Non-Current Assets | G46: =+G47-G39-G42-G43 -> 1092.7 | H46: =+H47-H39-H42-H43 -> 1246.7 | I46: =+I47-I39-I42-I43 -> 1684 | J46: =+J47-J39-J42-J43 -> 1798.1 | K46: =+K47-K39-K42-K43 -> 6132.8 | L46: =+L47-L39-L42-L43 -> 6563.1 | M46: =+M47-M39-M42-M43 -> 8264.4 | N46: =+N47-N39-N42-N43 -> 9819.3 | ... Q46: =+Q47-Q39-Q42-Q43 -> 10913.2 | R46: =IFERROR((Q46/G46)^(1/COUNT($G$4:$Q$4))-1,"") -> 0.23270511
B47: Non-Current Assets | G47: =+BS!B42 -> 16519.8 | H47: =+BS!C42 -> 19917.9 | I47: =+BS!D42 -> 22377 | J47: =+BS!E42 -> 28108 | K47: =+BS!F42 -> 43764.2 | L47: =+BS!G42 -> 50790.7 | M47: =+BS!H42 -> 54602.9 | N47: =+BS!I42 -> 69439.5 | ... Q47: =+BS!L42 -> 77576.3 | R47: =IFERROR((Q47/G47)^(1/COUNT($G$4:$Q$4))-1,"") -> 0.15097487
B48: Total Assets | G48: =SUM(G47,G38) -> 26883.3 | H48: =SUM(H47,H38) -> 29677.9 | I48: =SUM(I47,I38) -> 32216 | J48: =SUM(J47,J38) -> 45418.4 | K48: =SUM(K47,K38) -> 63658.3 | L48: =SUM(L47,L38) -> 65248.3 | M48: =SUM(M47,M38) -> 71173.9 | N48: =SUM(N47,N38) -> 96346.6 | ... Q48: =SUM(Q47,Q38) -> 119855.2 | R48: =IFERROR((Q48/G48)^(1/COUNT($G$4:$Q$4))-1,"") -> 0.14555474
B49: Accounts Payable | G49: =+BS!B47 -> 787.8 | H49: =+BS!C47 -> 791.4 | I49: =+BS!D47 -> 696.1 | J49: =+BS!E47 -> 758.6 | K49: =+BS!F47 -> 1096.4 | L49: =+BS!G47 -> 1042.5 | M49: =+BS!H47 -> 1046.2 | N49: =+BS!I47 -> 1359.2 | ... Q49: =+BS!L47 -> 2277.3 | R49: =IFERROR((Q49/G49)^(1/COUNT($G$4:$Q$4))-1,"") -> 0.10130974
B50: Short-Term Debt | G50: =+SUM(G51:G52) -> 734.2 | H50: =+SUM(H51:H52) -> 147.9 | I50: =+SUM(I51:I52) -> 0 | J50: =+SUM(J51:J52) -> 192.7 | K50: =+SUM(K51:K52) -> 585.8 | L50: =+SUM(L51:L52) -> 1461.6 | M50: =+SUM(M51:M52) -> 527.1 | N50: =+SUM(N51:N52) -> 535.3 | ... Q50: =+SUM(Q51:Q52) -> 1871.9 | R50: =IFERROR((Q50/G50)^(1/COUNT($G$4:$Q$4))-1,"") -> 0.088808896
B51: Short-Term Borrowings | G51: =+BS!B51 -> 734.2 | H51: =+BS!C51 -> 147.9 | I51: =+BS!D51 -> 0 | J51: =+BS!E51 -> 192.7 | K51: =+BS!F51 -> 585.8 | L51: =+BS!G51 -> 1168.4 | M51: =+BS!H51 -> 179.6 | N51: =+BS!I51 -> 233.2 | ... Q51: =+BS!L51 -> 1283.5 | R51: =IFERROR((Q51/G51)^(1/COUNT($G$4:$Q$4))-1,"") -> 0.052089928
B52: Current Portion of Lease Liabilities | G52: =+BS!B52 -> — | H52: =+BS!C52 -> — | I52: =+BS!D52 -> — | J52: =+BS!E52 -> — | K52: =+BS!F52 -> — | L52: =+BS!G52 -> 293.2 | M52: =+BS!H52 -> 347.5 | N52: =+BS!I52 -> 302.1 | ... Q52: =+BS!L52 -> 588.4 | R52: =IFERROR((Q52/G52)^(1/COUNT($G$4:$Q$4))-1,"")
B53: Accrued Expenses and Other Current Liabilities | G53: =+G54-G49-G50 -> 4243.3 | H53: =+H54-H49-H50 -> 3901.4 | I53: =+I54-I49-I50 -> 3464.7 | J53: =+J54-J49-J50 -> 7164.8 | K53: =+K54-K49-K50 -> 11349.7 | L53: =+L54-L49-L50 -> 5457.9 | M53: =+M54-M49-M50 -> 7499.1 | N53: =+N54-N49-N50 -> 12840.9 | ... Q53: =+Q54-Q49-Q50 -> 20816.2 | R53: =IFERROR((Q53/G53)^(1/COUNT($G$4:$Q$4))-1,"") -> 0.15555521
B54: Current Liabilities | G54: =+BS!B58 -> 5765.3 | H54: =+BS!C58 -> 4840.7 | I54: =+BS!D58 -> 4160.8 | J54: =+BS!E58 -> 8116.1 | K54: =+BS!F58 -> 13031.9 | L54: =+BS!G58 -> 7962 | M54: =+BS!H58 -> 9072.4 | N54: =+BS!I58 -> 14735.4 | ... Q54: =+BS!L58 -> 24965.4 | R54: =IFERROR((Q54/G54)^(1/COUNT($G$4:$Q$4))-1,"") -> 0.14252351
B55: Long-Term Debt | G55: =+SUM(G56:G57) -> 2419.7 | H55: =+SUM(H56:H57) -> 2805.2 | I55: =+SUM(I56:I57) -> 3631.1 | J55: =+SUM(J56:J57) -> 3397.5 | K55: =+SUM(K56:K57) -> 3667.6 | L55: =+SUM(L56:L57) -> 9159.5 | M55: =+SUM(M56:M57) -> 9433.7 | N55: =+SUM(N56:N57) -> 15966.7 | ... Q55: =+SUM(Q56:Q57) -> 19611.5 | R55: =IFERROR((Q55/G55)^(1/COUNT($G$4:$Q$4))-1,"") -> 0.20952144
B56: Long-Term Borrowings | G56: =+BS!B60 -> 2419.7 | H56: =+BS!C60 -> 2805.2 | I56: =+BS!D60 -> 3631.1 | J56: =+BS!E60 -> 3397.5 | K56: =+BS!F60 -> 3667.6 | L56: =+BS!G60 -> 7785.7 | M56: =+BS!H60 -> 8137.4 | N56: =+BS!I60 -> 14743 | ... Q56: =+BS!L60 -> 17431.5 | R56: =IFERROR((Q56/G56)^(1/COUNT($G$4:$Q$4))-1,"") -> 0.19663363
B57: Long-Term Operating Lease Liabilities | G57: =+BS!B61 -> — | H57: =+BS!C61 -> — | I57: =+BS!D61 -> — | J57: =+BS!E61 -> — | K57: =+BS!F61 -> — | L57: =+BS!G61 -> 1373.8 | M57: =+BS!H61 -> 1296.3 | N57: =+BS!I61 -> 1223.7 | ... Q57: =+BS!L61 -> 2180 | R57: =IFERROR((Q57/G57)^(1/COUNT($G$4:$Q$4))-1,"")
B58: Other Non-Current Liabilities | G58: =+G59-G55 -> 662 | H58: =+H59-H55 -> 644.3 | I58: =+I59-I55 -> 400.5 | J58: =+J59-J55 -> 83.9 | K58: =+K59-K55 -> 106.6 | L58: =+L59-L55 -> 191 | M58: =+M59-M55 -> 758.7 | N58: =+N59-N55 -> 3453.4 | ... Q58: =+Q59-Q55 -> 1362.6 | R58: =IFERROR((Q58/G58)^(1/COUNT($G$4:$Q$4))-1,"") -> 0.067827116
B59: Non-Current Liabilities | G59: =+BS!B71 -> 3081.7 | H59: =+BS!C71 -> 3449.5 | I59: =+BS!D71 -> 4031.6 | J59: =+BS!E71 -> 3481.4 | K59: =+BS!F71 -> 3774.2 | L59: =+BS!G71 -> 9350.5 | M59: =+BS!H71 -> 10192.4 | N59: =+BS!I71 -> 19420.1 | ... Q59: =+BS!L71 -> 20974.1 | R59: =IFERROR((Q59/G59)^(1/COUNT($G$4:$Q$4))-1,"") -> 0.1904675
B60: Total Liabilities | G60: =SUM(G59,G54) -> 8847 | H60: =SUM(H59,H54) -> 8290.2 | I60: =SUM(I59,I54) -> 8192.4 | J60: =SUM(J59,J54) -> 11597.5 | K60: =SUM(K59,K54) -> 16806.1 | L60: =SUM(L59,L54) -> 17312.5 | M60: =SUM(M59,M54) -> 19264.8 | N60: =SUM(N59,N54) -> 34155.5 | ... Q60: =SUM(Q59,Q54) -> 45939.5 | R60: =IFERROR((Q60/G60)^(1/COUNT($G$4:$Q$4))-1,"") -> 0.16154349
B61: Shareholder's Equity | G61: =G48-G60 -> 18036.3 | H61: =H48-H60 -> 21387.7 | I61: =I48-I60 -> 24023.6 | J61: =J48-J60 -> 33820.9 | K61: =K48-K60 -> 46852.2 | L61: =L48-L60 -> 47935.8 | M61: =M48-M60 -> 51909.1 | N61: =N48-N60 -> 62191.1 | ... Q61: =Q48-Q60 -> 73915.7 | R61: =IFERROR((Q61/G61)^(1/COUNT($G$4:$Q$4))-1,"") -> 0.13681536
B62: Non-Controlling Interest | G62: =+BS!B82 -> -0.2 | H62: =+BS!C82 -> 0.8 | I62: =+BS!D82 -> 6.6 | J62: =+BS!E82 -> 5.6 | K62: =+BS!F82 -> 6.6 | L62: =+BS!G82 -> 14.8 | M62: =+BS!H82 -> 20.6 | N62: =+BS!I82 -> 34 | ... Q62: =+BS!L82 -> 12.3
A64: x | B64: Cash Flow | G64: 2014 | H64: =+G64+1 -> 2015 | I64: =+H64+1 -> 2016 | J64: =+I64+1 -> 2017 | K64: =+J64+1 -> 2018 | L64: =+K64+1 -> 2019 | M64: =+L64+1 -> 2020 | N64: =+M64+1 -> 2021 | O64: =+N64+1 -> 2022 | ... Q64: =+P64+1 -> 2024 | R64: ="CAGR "&$G$4&" - "&$Q$4 -> CAGR 2014 - 2024
B66: Net Income | G66: =G24 -> 4195.1 | H66: =H24 -> 4323.6 | I66: =I24 -> 2960.6 | J66: =J24 -> 10642.3 | K66: =K24 -> 15540.2 | L66: =L24 -> 2009.1 | M66: =M24 -> 4758.9 | N66: =N24 -> 9616.2 | ... Q66: =Q24 -> 19797.1 | R66: =IFERROR((Q66/G66)^(1/COUNT($G$4:$Q$4))-1,"") -> 0.15148937
B67: D&A (Depreciation and Amortization) | G67: =+CF!B8 -> 3444 | H67: =+CF!C8 -> 3953.2 | I67: =+CF!D8 -> 4456.3 | J67: =+CF!E8 -> 5026.1 | K67: =+CF!F8 -> 6428.3 | L67: =+CF!G8 -> 8620.4 | M67: =+CF!H8 -> 9771.9 | N67: =+CF!I8 -> 10656.7 | ... Q67: =+CF!L8 -> 12581.5 | R67: =IFERROR((Q67/G67)^(1/COUNT($G$4:$Q$4))-1,"") -> 0.12499801
B68: Changes in Net Working Capital | G68: =+SUM(G69:G72) -> -2006.7 | H68: =+SUM(H69:H72) -> 622.2 | I68: =+SUM(I69:I72) -> -796 | J68: =+SUM(J69:J72) -> -3045.3 | K68: =+SUM(K69:K72) -> -2312.2 | L68: =+SUM(L69:L72) -> 1025.2 | M68: =+SUM(M69:M72) -> -1551.7 | N68: =+SUM(N69:N72) -> -3046.2 | ... Q68: =+SUM(Q69:Q72) -> -6034.6 | R68: =IFERROR((Q68/G68)^(1/COUNT($G$4:$Q$4))-1,"") -> 0.1052732
B69: (Increase) Decrease in Accounts Receivable | G69: =+CF!B13 -> -1628.7 | H69: =+CF!C13 -> 1260.2 | I69: =+CF!D13 -> -470.8 | J69: =+CF!E13 -> -2964.3 | K69: =+CF!F13 -> -547.3 | L69: =+CF!G13 -> 2214.8 | M69: =+CF!H13 -> -935.3 | N69: =+CF!I13 -> -2525.7 | ... Q69: =+CF!L13 -> -5098
B70: (Increase) Decrease in Inventories | G70: =+CF!B14 -> -314.5 | H70: =+CF!C14 -> -414.8 | I70: =+CF!D14 -> -110.8 | J70: =+CF!E14 -> -634.6 | K70: =+CF!F14 -> -1782.4 | L70: =+CF!G14 -> -851.7 | M70: =+CF!H14 -> -843.8 | N70: =+CF!I14 -> -696.6 | ... Q70: =+CF!L14 -> 166.7
B71: Increase (Decrease) in Accounts Payable | G71: =+CF!B15 -> 69.3 | H71: =+CF!C15 -> -156.1 | I71: =+CF!D15 -> -208.4 | J71: =+CF!E15 -> 514.8 | K71: =+CF!F15 -> 58.8 | L71: =+CF!G15 -> -278.5 | M71: =+CF!H15 -> 222 | N71: =+CF!I15 -> -198 | ... Q71: =+CF!L15 -> 275
B72: Increase (Decrease) in Other | G72: =+CF!B16 -> -132.8 | H72: =+CF!C16 -> -67.1 | I72: =+CF!D16 -> -6 | J72: =+CF!E16 -> 38.8 | K72: =+CF!F16 -> -41.3 | L72: =+CF!G16 -> -59.4 | M72: =+CF!H16 -> 5.4 | N72: =+CF!I16 -> 374.1 | ... Q72: =+CF!L16 -> -1378.3
B73: Stock Based Compensation | J73: =+CF!E10 -> 0.8 | K73: =+CF!F10 -> 1.2 | L73: =+CF!G10 -> 1.7 | M73: =+CF!H10 -> 1.6
B74: Other Operating Adjustments | G74: =+G75-G66-G67-G68-G73 -> 234.3 | H74: =+H75-H66-H67-H68-H73 -> 420.5 | I74: =+I75-I66-I67-I68-I73 -> -1072 | J74: =+J75-J66-J67-J68-J73 -> 2066.7 | K74: =+K75-K66-K67-K68-K73 -> 2569.7 | L74: =+L75-L66-L67-L68-L73 -> -5106.7 | M74: =+M75-M66-M67-M68-M73 -> -666.1 | N74: =+N75-N66-N67-N68-N73 -> 2570.9 | ... Q74: =+Q75-Q66-Q67-Q68-Q73 -> 3451.9 | R74: =IFERROR((Q74/G74)^(1/COUNT($G$4:$Q$4))-1,"") -> 0.27704973
B75: Operating Cash Flow | G75: =+CF!B18 -> 5866.7 | H75: =+CF!C18 -> 9319.5 | I75: =+CF!D18 -> 5548.9 | J75: =+CF!E18 -> 14690.6 | K75: =+CF!F18 -> 22227.2 | L75: =+CF!G18 -> 6549.7 | M75: =+CF!H18 -> 12314.6 | N75: =+CF!I18 -> 19797.6 | ... Q75: =+CF!L18 -> 29795.9 | R75: =IFERROR((Q75/G75)^(1/COUNT($G$4:$Q$4))-1,"") -> 0.15920498
B76: Net Capex | G76: =+SUM(G77:G78) -> -4937.8 | H76: =+SUM(H77:H78) -> -7170.3 | I76: =+SUM(I77:I78) -> -6323 | J76: =+SUM(J77:J78) -> -9665.1 | K76: =+SUM(K77:K78) -> -16835 | L76: =+SUM(L77:L78) -> -14539.6 | M76: =+SUM(M77:M78) -> -10809.6 | N76: =+SUM(N77:N78) -> -13378.5 | ... Q76: =+SUM(Q77:Q78) -> -16595.8 | R76: =IFERROR((Q76/G76)^(1/COUNT($G$4:$Q$4))-1,"") -> 0.11650437 | U76: =H76/G76-1 -> 0.45212443 | V76: =I76/H76-1 -> -0.118168 | W76: =J76/I76-1 -> 0.52856239 | X76: =K76/J76-1 -> 0.74183402 | Y76: =L76/K76-1 -> -0.1363469 | Z76: =M76/L76-1 -> -0.25654076 | AA76: =N76/M76-1 -> 0.23764987 | AB76: =O76/N76-1 -> 0.4518967 | ... AD76: =Q76/P76-1 -> 1.2923959
B77: Acquisition of Fixed & Intangibles | G77: =+CF!B25 -> -5137 | H77: =+CF!C25 -> -7398.4 | I77: =+CF!D25 -> -6486.7 | J77: =+CF!E25 -> -9913.2 | K77: =+CF!F25 -> -16969.3 | L77: =+CF!G25 -> -14593.6 | M77: =+CF!H25 -> -10869.4 | N77: =+CF!I25 -> -13460.5 | ... Q77: =+CF!L25 -> -16662.6 | R77: =IFERROR((Q77/G77)^(1/COUNT($G$4:$Q$4))-1,"") -> 0.11290364
B78: Disposal of Fixed & Intangibles | G78: =+CF!B22 -> 199.2 | H78: =+CF!C22 -> 228.1 | I78: =+CF!D22 -> 163.7 | J78: =+CF!E22 -> 248.1 | K78: =+CF!F22 -> 134.3 | L78: =+CF!G22 -> 54 | M78: =+CF!H22 -> 59.8 | N78: =+CF!I22 -> 82 | ... Q78: =+CF!L22 -> 66.8 | R78: =IFERROR((Q78/G78)^(1/COUNT($G$4:$Q$4))-1,"") -> -0.094554184 | U78: =_xlfn.STDEV.P(U76:AD76) -> 0.52900475
B79: Net Cash from Investments & Acquisitions | G79: =+SUM(G80:G83) -> -9848.3 | H79: =+SUM(H80:H83) -> -14344.6 | I79: =+SUM(I80:I83) -> -12662.5 | J79: =+SUM(J80:J83) -> -19353 | K79: =+SUM(K80:K83) -> -37675.6 | L79: =+SUM(L80:L83) -> -29156.3 | M79: =+SUM(M80:M83) -> -21712.3 | N79: =+SUM(N80:N83) -> -26841.3 | ... Q79: =+SUM(Q80:Q83) -> -33208.7 | R79: =IFERROR((Q79/G79)^(1/COUNT($G$4:$Q$4))-1,"") -> 0.11683767
B80: Acquisitions | G80: =+CF!B25+CF!B26+CF!B27 -> -10274 | H80: =+CF!C25+CF!C26+CF!C27 -> -14796.7 | I80: =+CF!D25+CF!D26+CF!D27 -> -12973.5 | J80: =+CF!E25+CF!E26+CF!E27 -> -19826.4 | K80: =+CF!F25+CF!F26+CF!F27 -> -33938.5 | L80: =+CF!G25+CF!G26+CF!G27 -> -29187.2 | M80: =+CF!H25+CF!H26+CF!H27 -> -21738.8 | N80: =+CF!I25+CF!I26+CF!I27 -> -26921 | ... Q80: =+CF!L25+CF!L26+CF!L27 -> -33325.2 | R80: =IFERROR((Q80/G80)^(1/COUNT($G$4:$Q$4))-1,"") -> 0.11290364
B81: Divestitures | G81: =+CF!B22+CF!B23+CF!B24 -> 398.5 | H81: =+CF!C22+CF!C23+CF!C24 -> 456.2 | I81: =+CF!D22+CF!D23+CF!D24 -> 327.4 | J81: =+CF!E22+CF!E23+CF!E24 -> 496.2 | K81: =+CF!F22+CF!F23+CF!F24 -> 268.6 | L81: =+CF!G22+CF!G23+CF!G24 -> 108 | M81: =+CF!H22+CF!H23+CF!H24 -> 119.6 | N81: =+CF!I22+CF!I23+CF!I24 -> 164 | ... Q81: =+CF!L22+CF!L23+CF!L24 -> 133.6 | R81: =IFERROR((Q81/G81)^(1/COUNT($G$4:$Q$4))-1,"") -> -0.094574842
B82: Increase in LT Investment | G82: =+CF!B30 -> -1.4 | H82: =+CF!C30 -> -5.4 | I82: =+CF!D30 -> -19.1 | J82: =+CF!E30 -> -26.2 | K82: =+CF!F30 -> -4012.8 | L82: =+CF!G30 -> -81.4 | M82: =+CF!H30 -> -93.8 | N82: =+CF!I30 -> -130.3 | ... Q82: =+CF!L30 -> -19.5 | R82: =IFERROR((Q82/G82)^(1/COUNT($G$4:$Q$4))-1,"") -> 0.27054926
B83: Decrease in LT Investment | G83: =+CF!B29 -> 28.6 | H83: =+CF!C29 -> 1.3 | I83: =+CF!D29 -> 2.7 | J83: =+CF!E29 -> 3.4 | K83: =+CF!F29 -> 7.1 | L83: =+CF!G29 -> 4.3 | M83: =+CF!H29 -> 0.7 | N83: =+CF!I29 -> 46 | ... Q83: =+CF!L29 -> 2.4 | R83: =IFERROR((Q83/G83)^(1/COUNT($G$4:$Q$4))-1,"") -> -0.20169703
B84: Other Investing Inflows (Outflows) | G84: =+G85-G76-G79 -> 8698.3 | H84: =+H85-H76-H79 -> 14389.4 | I84: =+I85-I76-I79 -> 12755 | J84: =+J85-J76-J79 -> 17098.9 | K84: =+K85-K76-K79 -> 33081.9 | L84: =+L85-L76-L79 -> 33245 | M84: =+M85-M76-M79 -> 20681.5 | N84: =+N85-N76-N79 -> 17827.5 | ... Q84: =+Q85-Q76-Q79 -> 31799.9 | R84: =IFERROR((Q84/G84)^(1/COUNT($G$4:$Q$4))-1,"") -> 0.12507386
B85: Investing Cash Flow | G85: =+CF!B37 -> -6087.8 | H85: =+CF!C37 -> -7125.5 | I85: =+CF!D37 -> -6230.5 | J85: =+CF!E37 -> -11919.2 | K85: =+CF!F37 -> -21428.7 | L85: =+CF!G37 -> -10450.9 | M85: =+CF!H37 -> -11840.4 | N85: =+CF!I37 -> -22392.3 | ... Q85: =+CF!L37 -> -18004.6 | R85: =IFERROR((Q85/G85)^(1/COUNT($G$4:$Q$4))-1,"") -> 0.10359873
B86: Debt Borrowing | G86: =+BS!B51+BS!B60 -> 3153.9 | H86: =+BS!C51+BS!C60 -> 2953.1 | I86: =+BS!D51+BS!D60 -> 3631.1 | J86: =+BS!E51+BS!E60 -> 3590.2 | K86: =+BS!F51+BS!F60 -> 4253.4 | L86: =+BS!G51+BS!G60 -> 8954.1 | M86: =+BS!H51+BS!H60 -> 8317 | N86: =+BS!I51+BS!I60 -> 14976.2 | ... Q86: =+BS!L51+BS!L60 -> 18715 | R86: =IFERROR((Q86/G86)^(1/COUNT($G$4:$Q$4))-1,"") -> 0.17571974
B87: Debt Repayment | G87: =+CF!B41 -> 28.4 | H87: =+CF!C41 -> -472 | I87: =+CF!D41 -> 469.9 | J87: =+CF!E41 -> 71.7 | K87: =+CF!F41 -> 1047.2 | L87: =+CF!G41 -> 4858 | M87: =+CF!H41 -> 932 | N87: =+CF!I41 -> 5288.9 | ... Q87: =+CF!L41 -> -7977.5 | R87: =IFERROR((Q87/G87)^(1/COUNT($G$4:$Q$4))-1,"") -> -2.6695342
B88: Lease Payments | M88: =+BS!G52+BS!H61 -> 1589.5 | N88: =+BS!H52+BS!I61 -> 1571.2 | O88: =+BS!I52+BS!J61 -> 1818.3 | P88: =+BS!J52+BS!K61 -> 2679.3 | Q88: =+BS!K52+BS!L61 -> 2811.5 | R88: =IFERROR((Q88/G88)^(1/COUNT($G$4:$Q$4))-1,"")
B89: Dividends | G89: =+CF!B40 -> 0 | H89: =+CF!C40 -> -218.4 | I89: =+CF!D40 -> -353 | J89: =+CF!E40 -> -423.6 | K89: =+CF!F40 -> -706 | L89: =+CF!G40 -> -1026 | M89: =+CF!H40 -> -684 | N89: =+CF!I40 -> -805 | ... Q89: =+CF!L40 -> -826.3 | R89: =IFERROR((Q89/G89)^(1/COUNT($G$4:$Q$4))-1,"")
B90: Increase (Repurchase) of Shares | G90: =+CF!B45 -> 0 | H90: =+CF!C45 -> -771.9 | I90: =+CF!D45 -> 0 | J90: =+CF!E45 -> 0 | K90: =+CF!F45 -> -1736.5 | L90: =+CF!G45 -> 0 | M90: =+CF!H45 -> 0 | N90: =+CF!I45 -> 8.5 | ... Q90: =+CF!L45 -> 93.8 | R90: =IFERROR((Q90/G90)^(1/COUNT($G$4:$Q$4))-1,"")
B91: Other Financing Inflows (Outflows) | G91: =+G92-G86-G87-G88-G89-G90 -> -3154 | H91: =+H92-H86-H87-H88-H89-H90 -> -2953.1 | I91: =+I92-I86-I87-I88-I89-I90 -> -3631.1 | J91: =+J92-J86-J87-J88-J89-J90 -> -3590.2 | K91: =+K92-K86-K87-K88-K89-K90 -> -4253.4 | L91: =+L92-L86-L87-L88-L89-L90 -> -8949.4 | M91: =+M92-M86-M87-M88-M89-M90 -> -9902.4 | N91: =+N92-N86-N87-N88-N89-N90 -> -16547.5 | ... Q91: =+Q92-Q86-Q87-Q88-Q89-Q90 -> -21520.4 | R91: =IFERROR((Q91/G91)^(1/COUNT($G$4:$Q$4))-1,"") -> 0.19074057
B92: Financing Cash Flow | G92: =+CF!B50 -> 28.3 | H92: =+CF!C50 -> -1462.3 | I92: =+CF!D50 -> 116.9 | J92: =+CF!E50 -> -351.9 | K92: =+CF!F50 -> -1395.3 | L92: =+CF!G50 -> 3836.7 | M92: =+CF!H50 -> 252.1 | N92: =+CF!I50 -> 4492.3 | ... Q92: =+CF!L50 -> -8703.9 | R92: =IFERROR((Q92/G92)^(1/COUNT($G$4:$Q$4))-1,"") -> -2.6833531
B93: Effect of Foreign Exchange | G93: =+CF!B52 -> -2.3 | H93: =+CF!C52 -> 7.2 | I93: =+CF!D52 -> 2.7 | J93: =+CF!E52 -> -83.3 | K93: =+CF!F52 -> -3.8 | L93: =+CF!G52 -> 21.3 | M93: =+CF!H52 -> -56.3 | N93: =+CF!I52 -> 184.3 | ... Q93: =+CF!L52 -> 530.5 | R93: =IFERROR((Q93/G93)^(1/COUNT($G$4:$Q$4))-1,"") -> -2.6398885
B94: Net Changes in Cash | G94: =+CF!B54 -> -195.1 | H94: =+CF!C54 -> 739 | I94: =+CF!D54 -> -561.9 | J94: =+CF!E54 -> 2336.2 | K94: =+CF!F54 -> -600.7 | L94: =+CF!G54 -> -43.2 | M94: =+CF!H54 -> 669.9 | N94: =+CF!I54 -> 2082 | ... Q94: =+CF!L54 -> 3617.8 | R94: =IFERROR((Q94/G94)^(1/COUNT($G$4:$Q$4))-1,"") -> -2.3040365
B95: in billionsof USD
A96: x | B96: Capital Structure | G96: 42004 | H96: 42369 | I96: 42735 | J96: 43099 | K96: 43464 | L96: 43829 | M96: 44196 | N96: 44561 | O96: 44926 | P96: 45290 | Q96: 45656
B98: Market Capitalization | G98: {=(IFERROR(_xlfn.STOCKHISTORY(Peers!$C$6, G96, G96, 0, 0, 1), IFERROR(_xlfn.STOCKHISTORY(Peers!$C$6, G96+1, G96+1, 0, 0, 1), _xlfn.STOCKHISTORY(Peers!$C$6, G96-2, G96-2, 0, 0, 1))))*_xlfn.XLOOKUP("Basic Weighted Average Shares",$B:$B,G:G)/1000} -> 34294.05 | H98: {=(IFERROR(_xlfn.STOCKHISTORY(Peers!$C$6, H96, H96, 0, 0, 1), IFERROR(_xlfn.STOCKHISTORY(Peers!$C$6, H96+1, H96+1, 0, 0, 1), _xlfn.STOCKHISTORY(Peers!$C$6, H96-2, H96-2, 0, 0, 1))))*_xlfn.XLOOKUP("Basic Weighted Average Shares",$B:$B,H:H)/1000} -> 22467.12 | I98: {=(IFERROR(_xlfn.STOCKHISTORY(Peers!$C$6, I96, I96, 0, 0, 1), IFERROR(_xlfn.STOCKHISTORY(Peers!$C$6, I96+1, I96+1, 0, 0, 1), _xlfn.STOCKHISTORY(Peers!$C$6, I96-2, I96-2, 0, 0, 1))))*_xlfn.XLOOKUP("Basic Weighted Average Shares",$B:$B,I:I)/1000} -> 31558.2 | J98: {=(IFERROR(_xlfn.STOCKHISTORY(Peers!$C$6, J96, J96, 0, 0, 1), IFERROR(_xlfn.STOCKHISTORY(Peers!$C$6, J96+1, J96+1, 0, 0, 1), _xlfn.STOCKHISTORY(Peers!$C$6, J96-2, J96-2, 0, 0, 1))))*_xlfn.XLOOKUP("Basic Weighted Average Shares",$B:$B,J:J)/1000} -> 54009 | K98: {=(IFERROR(_xlfn.STOCKHISTORY(Peers!$C$6, K96, K96, 0, 0, 1), IFERROR(_xlfn.STOCKHISTORY(Peers!$C$6, K96+1, K96+1, 0, 0, 1), _xlfn.STOCKHISTORY(Peers!$C$6, K96-2, K96-2, 0, 0, 1))))*_xlfn.XLOOKUP("Basic Weighted Average Shares",$B:$B,K:K)/1000} -> 42247.15 | L98: {=(IFERROR(_xlfn.STOCKHISTORY(Peers!$C$6, L96, L96, 0, 0, 1), IFERROR(_xlfn.STOCKHISTORY(Peers!$C$6, L96+1, L96+1, 0, 0, 1), _xlfn.STOCKHISTORY(Peers!$C$6, L96-2, L96-2, 0, 0, 1))))*_xlfn.XLOOKUP("Basic Weighted Average Shares",$B:$B,L:L)/1000} -> 64364.4 | M98: {=(IFERROR(_xlfn.STOCKHISTORY(Peers!$C$6, M96, M96, 0, 0, 1), IFERROR(_xlfn.STOCKHISTORY(Peers!$C$6, M96+1, M96+1, 0, 0, 1), _xlfn.STOCKHISTORY(Peers!$C$6, M96-2, M96-2, 0, 0, 1))))*_xlfn.XLOOKUP("Basic Weighted Average Shares",$B:$B,M:M)/1000} -> 79344 | N98: {=(IFERROR(_xlfn.STOCKHISTORY(Peers!$C$6, N96, N96, 0, 0, 1), IFERROR(_xlfn.STOCKHISTORY(Peers!$C$6, N96+1, N96+1, 0, 0, 1), _xlfn.STOCKHISTORY(Peers!$C$6, N96-2, N96-2, 0, 0, 1))))*_xlfn.XLOOKUP("Basic Weighted Average Shares",$B:$B,N:N)/1000} -> 87172.8 | O98: {=(IFERROR(_xlfn.STOCKHISTORY(Peers!$C$6, O96, O96, 0, 0, 1), IFERROR(_xlfn.STOCKHISTORY(Peers!$C$6, O96+1, O96+1, 0, 0, 1), _xlfn.STOCKHISTORY(Peers!$C$6, O96-2, O96-2, 0, 0, 1))))*_xlfn.XLOOKUP("Basic Weighted Average Shares",$B:$B,O:O)/1000} -> 51570 | P98: {=(IFERROR(_xlfn.STOCKHISTORY(Peers!$C$6, P96, P96, 0, 0, 1), IFERROR(_xlfn.STOCKHISTORY(Peers!$C$6, P96+1, P96+1, 0, 0, 1), _xlfn.STOCKHISTORY(Peers!$C$6, P96-2, P96-2, 0, 0, 1))))*_xlfn.XLOOKUP("Basic Weighted Average Shares",$B:$B,P:P)/1000} -> 97366.15 | Q98: {=(IFERROR(_xlfn.STOCKHISTORY(Peers!$C$6, Q96, Q96, 0, 0, 1), IFERROR(_xlfn.STOCKHISTORY(Peers!$C$6, Q96+1, Q96+1, 0, 0, 1), _xlfn.STOCKHISTORY(Peers!$C$6, Q96-2, Q96-2, 0, 0, 1))))*_xlfn.XLOOKUP("Basic Weighted Average Shares",$B:$B,Q:Q)/1000} -> 119764.93
B99: Cash & Cash Equivalents | G99: =_xlfn.XLOOKUP("Cash & Cash Equivalents & ST Investments",$B$30:$B$62,G$30:G$62) -> 3977.2 | H99: =_xlfn.XLOOKUP("Cash & Cash Equivalents & ST Investments",$B$30:$B$62,H$30:H$62) -> 4682.9 | I99: =_xlfn.XLOOKUP("Cash & Cash Equivalents & ST Investments",$B$30:$B$62,I$30:I$62) -> 4052 | J99: =_xlfn.XLOOKUP("Cash & Cash Equivalents & ST Investments",$B$30:$B$62,J$30:J$62) -> 8320.2 | K99: =_xlfn.XLOOKUP("Cash & Cash Equivalents & ST Investments",$B$30:$B$62,K$30:K$62) -> 8135.8 | L99: =_xlfn.XLOOKUP("Cash & Cash Equivalents & ST Investments",$B$30:$B$62,L$30:L$62) -> 3760.9 | M99: =_xlfn.XLOOKUP("Cash & Cash Equivalents & ST Investments",$B$30:$B$62,M$30:M$62) -> 4627.9 | N99: =_xlfn.XLOOKUP("Cash & Cash Equivalents & ST Investments",$B$30:$B$62,N$30:N$62) -> 8351.6 | ... Q99: =_xlfn.XLOOKUP("Cash & Cash Equivalents & ST Investments",$B$30:$B$62,Q$30:Q$62) -> 13928
B100: Total Debt | G100: =(_xlfn.XLOOKUP("Short-Term Debt",$B$30:$B$62,G$30:G$62)+_xlfn.XLOOKUP("Long-Term Debt",$B$30:$B$62,G$30:G$62)) -> 3153.9 | H100: =(_xlfn.XLOOKUP("Short-Term Debt",$B$30:$B$62,H$30:H$62)+_xlfn.XLOOKUP("Long-Term Debt",$B$30:$B$62,H$30:H$62)) -> 2953.1 | I100: =(_xlfn.XLOOKUP("Short-Term Debt",$B$30:$B$62,I$30:I$62)+_xlfn.XLOOKUP("Long-Term Debt",$B$30:$B$62,I$30:I$62)) -> 3631.1 | J100: =(_xlfn.XLOOKUP("Short-Term Debt",$B$30:$B$62,J$30:J$62)+_xlfn.XLOOKUP("Long-Term Debt",$B$30:$B$62,J$30:J$62)) -> 3590.2 | K100: =(_xlfn.XLOOKUP("Short-Term Debt",$B$30:$B$62,K$30:K$62)+_xlfn.XLOOKUP("Long-Term Debt",$B$30:$B$62,K$30:K$62)) -> 4253.4 | L100: =(_xlfn.XLOOKUP("Short-Term Debt",$B$30:$B$62,L$30:L$62)+_xlfn.XLOOKUP("Long-Term Debt",$B$30:$B$62,L$30:L$62)) -> 10621.1 | M100: =(_xlfn.XLOOKUP("Short-Term Debt",$B$30:$B$62,M$30:M$62)+_xlfn.XLOOKUP("Long-Term Debt",$B$30:$B$62,M$30:M$62)) -> 9960.8 | N100: =(_xlfn.XLOOKUP("Short-Term Debt",$B$30:$B$62,N$30:N$62)+_xlfn.XLOOKUP("Long-Term Debt",$B$30:$B$62,N$30:N$62)) -> 16502 | ... Q100: =(_xlfn.XLOOKUP("Short-Term Debt",$B$30:$B$62,Q$30:Q$62)+_xlfn.XLOOKUP("Long-Term Debt",$B$30:$B$62,Q$30:Q$62)) -> 21483.4
B101: Preferred Stock
B102: Non-Controlling Interest | G102: =_xlfn.XLOOKUP("Non-Controlling Interest",$B$30:$B$62,G$30:G$62) -> -0.2 | H102: =_xlfn.XLOOKUP("Non-Controlling Interest",$B$30:$B$62,H$30:H$62) -> 0.8 | I102: =_xlfn.XLOOKUP("Non-Controlling Interest",$B$30:$B$62,I$30:I$62) -> 6.6 | J102: =_xlfn.XLOOKUP("Non-Controlling Interest",$B$30:$B$62,J$30:J$62) -> 5.6 | K102: =_xlfn.XLOOKUP("Non-Controlling Interest",$B$30:$B$62,K$30:K$62) -> 6.6 | L102: =_xlfn.XLOOKUP("Non-Controlling Interest",$B$30:$B$62,L$30:L$62) -> 14.8 | M102: =_xlfn.XLOOKUP("Non-Controlling Interest",$B$30:$B$62,M$30:M$62) -> 20.6 | N102: =_xlfn.XLOOKUP("Non-Controlling Interest",$B$30:$B$62,N$30:N$62) -> 34 | ... Q102: =_xlfn.XLOOKUP("Non-Controlling Interest",$B$30:$B$62,Q$30:Q$62) -> 12.3
B103: Enterprise Value | G103: =+G98-G99+G100+G101+G102 -> 33470.55 | H103: =+H98-H99+H100+H101+H102 -> 20738.12 | I103: =+I98-I99+I100+I101+I102 -> 31143.9 | J103: =+J98-J99+J100+J101+J102 -> 49284.6 | K103: =+K98-K99+K100+K101+K102 -> 38371.35 | L103: =+L98-L99+L100+L101+L102 -> 71239.4 | M103: =+M98-M99+M100+M101+M102 -> 84697.5 | N103: =+N98-N99+N100+N101+N102 -> 95357.2 | ... Q103: =+Q98-Q99+Q100+Q101+Q102 -> 127332.63
A105: x | B105: Debt Schedule | G105: Cash | H105: 2025 | I105: =+H105+1 -> 2026 | J105: =+I105+1 -> 2027 | K105: =+J105+1 -> 2028 | L105: =+K105+1 -> 2029 | M105: =+L105+1 -> 2030 | N105: =+M105+1 -> 2031 | O105: =+N105+1 -> 2032 | P105: =+O105+1 -> 2033 | Q105: =+P105+1 -> 2034
B107: Cash
B108: Corporates | H108: {=+TRANSPOSE(DDIS!B4:B12)/1000000000} -> 530.27 | I108: 3478.24 | J108: 1213.78 | K108: 2767.57 | L108: 2017.57 | M108: 3014.86 | N108: 1757.57 | O108: 70 | P108: 1180.68 | Q108: =+DDIS!B14/1000000000 -> 100
B109: Loans | H109: {=TRANSPOSE(DDIS!B19:B28)/1000000000} -> 2935.13 | I109: 293.513 | J109: 1467.57 | K109: 0 | L109: 0 | M109: 0 | N109: 0 | O109: 1467.57 | P109: 0 | Q109: 1467.57
...

Sheet WACC
B2: WACC
B4: WACC = % of Equity x Cost of Equity + % de Debt x Cost of Debt x (1 - Tax Rate)
B5: Cost of Equity = Risk-Free Rate + Beta x Equity Risk Premium
B7: WACC | I7: Region | J7: Weight | K7: ERP | M7: Peers | N7: Beta (Unlevered)
B9: Market Cap (in billions) | G9: {=+_FV(DCF!R4,"Market cap",TRUE)/1000000000} -> 129802.8 | I9: =+Segments!B6 -> South Korea | J9: =+Segments!D6 -> 0.028766054 | K9: 0.0499 | M9: =+Peers!B8 -> Samsung Electronics Co., Ltd. | N9: =+Peers!E75 -> 1.0231585
B10: % of Equity | G10: =IFERROR(G9/G23,"") -> 0.85799498 | I10: =+Segments!B7 -> China | J10: =+Segments!D7 -> 0.23467091 | K10: 0.0527 | M10: =+Peers!B9 -> MICRON TECHNOLOGY, INC. | N10: =+Peers!F75 -> 1.0152922
B11: Cost of Equity | G11: =IFERROR(G12+G14*G15,"") -> 0.081006299 | I11: =+Segments!B8 -> Asia (without China) | J11: =+Segments!D8 -> 0.081299292 | K11: 0.0595 | M11: =+Peers!B10 -> Kioxia Holdings Corporation | N11: =+Peers!G75 -> 0.47803005
B12: Risk-Free Rate | G12: 0.027 | I12: =+Segments!B9 -> United States | J12: =+Segments!D9 -> 0.63392053 | K12: 0.0433 | M12: =+Peers!B11 -> WESTERN DIGITAL CORPORATION | N12: =+Peers!H75 -> 0.77695708
B13: Unlevered Beta | G13: =+N19 -> 0.82335946 | I13: =+Segments!B10 -> Europe | J13: =+Segments!D10 -> 0.02134321 | K13: 0.0513 | M13: =+Peers!B12 | N13: =+Peers!I75
B14: Beta | G14: {=+_FV(DCF!R4,"Beta")} -> 1.1446 | I14: Others | J14: =1-SUM(J9:J13) -> 0 | K14: =MAX(K9:K13) -> 0.0595 | M14: =+Peers!B13 | N14: =+Peers!J75
B15: Equity Risk Premium | G15: =SUMPRODUCT(J9:J13,K9:K13) -> 0.047183557 | M15: =+Peers!B14 | N15: =+Peers!K75
B16: Cost of Equity | G16: =IFERROR(+G12+G14*G15,"") -> 0.081006299 | J16: %Customer Facilities | K16: ERP | M16: =+Peers!B15 | N16: =+Peers!L75
I17: Germany | J17: 6.16 | K17: 4.33 | M17: =+Peers!B16 | N17: =+Peers!M75
B18: Debt (in millions) | G18: =+Inputs!Q113 -> 21483.4 | I18: United Kingdom | J18: 4.01 | K18: 5.13 | M18: =+Peers!B17 | N18: =+Peers!N75
B19: % of Debt | G19: =IFERROR(G18/G23,"") -> 0.14200502 | I19: France | J19: 1.67 | K19: 5.13 | M19: Average | N19: =IFERROR(+AVERAGEIF(N9:N18,">0"),"") -> 0.82335946
B20: Cost of debt | G20: =(Inputs!Q18)/(0.5*Inputs!Q113+0.5*Inputs!P113) -> 0.055736136 | I20: Spain | J20: 1.51 | K20: 6.46
B21: Tax Rate | G21: 0.25 | I21: Italy | J21: 1.37 | K21: 7.27 | M21: 1) damodaran - EUA/Germany 0
I22: Europe | K22: =(K17*J17+K18*J18+K19*J19+K20*J20+K21*J21)/K23 -> 5.130822 | M22: 2) credit default spread
B23: Total | G23: =+G9+G18 -> 151286.2 | K23: =SUM(J17:J21) -> 14.72 | M23: expected earnings from indexes
I24: Taiwan | J24: 3.95 | K24: 5.13
B25: Country Risk Premium | G25: 0.02 | I25: India | J25: 3.45 | K25: 7.26
I26: Japan | J26: 4.48 | K26: 5.27
B27: WACC | G27: =IFERROR(G10*G11+G19*G20*(1-G21)+G25,"") -> 0.095439106 | I27: Malaysia | J27: 1.1 | K27: 5.93
I28: Vietnam | J28: 0.74 | K28: 8.35
I29: Asia | K29: =(K24*J24+K25*J25+K26*J26+K27*J27+K28*J28)/K30 -> 5.9491327
K30: =SUM(J24:J28) -> 13.72

Sheet Ratios
B2: Multiples
B4: Valuation | F4: 2014 | G4: =+F4+1 -> 2015 | H4: =+G4+1 -> 2016 | I4: =+H4+1 -> 2017 | J4: =+I4+1 -> 2018 | K4: =+J4+1 -> 2019 | L4: =+K4+1 -> 2020 | M4: =+L4+1 -> 2021 | N4: 2022 | O4: =+N4+1 -> 2023 | P4: =+O4+1 -> 2024 | Q4: =+P4+1 -> 2025 | R4: =+Q4+1 -> 2026
B6: EV / Sales | F6: =IFERROR(_xlfn.XLOOKUP("Enterprise Value",Inputs!$B:$B,Inputs!G:G)/_xlfn.XLOOKUP("Revenue (Sales)",Inputs!$B:$B,Inputs!G:G),"") -> 1.9544162 | G6: =IFERROR(_xlfn.XLOOKUP("Enterprise Value",Inputs!$B:$B,Inputs!H:H)/_xlfn.XLOOKUP("Revenue (Sales)",Inputs!$B:$B,Inputs!H:H),"") -> 1.1032089 | H6: =IFERROR(_xlfn.XLOOKUP("Enterprise Value",Inputs!$B:$B,Inputs!I:I)/_xlfn.XLOOKUP("Revenue (Sales)",Inputs!$B:$B,Inputs!I:I),"") -> 1.8109024 | I6: =IFERROR(_xlfn.XLOOKUP("Enterprise Value",Inputs!$B:$B,Inputs!J:J)/_xlfn.XLOOKUP("Revenue (Sales)",Inputs!$B:$B,Inputs!J:J),"") -> 1.636851 | J6: =IFERROR(_xlfn.XLOOKUP("Enterprise Value",Inputs!$B:$B,Inputs!K:K)/_xlfn.XLOOKUP("Revenue (Sales)",Inputs!$B:$B,Inputs!K:K),"") -> 0.94872679 | K6: =IFERROR(_xlfn.XLOOKUP("Enterprise Value",Inputs!$B:$B,Inputs!L:L)/_xlfn.XLOOKUP("Revenue (Sales)",Inputs!$B:$B,Inputs!L:L),"") -> 2.6394054 | L6: =IFERROR(_xlfn.XLOOKUP("Enterprise Value",Inputs!$B:$B,Inputs!M:M)/_xlfn.XLOOKUP("Revenue (Sales)",Inputs!$B:$B,Inputs!M:M),"") -> 2.6550608 | M6: =IFERROR(_xlfn.XLOOKUP("Enterprise Value",Inputs!$B:$B,Inputs!N:N)/_xlfn.XLOOKUP("Revenue (Sales)",Inputs!$B:$B,Inputs!N:N),"") -> 2.2177228 | N6: =IFERROR(_xlfn.XLOOKUP("Enterprise Value",Inputs!$B:$B,Inputs!O:O)/_xlfn.XLOOKUP("Revenue (Sales)",Inputs!$B:$B,Inputs!O:O),"") -> 1.4951638 | O6: =IFERROR(_xlfn.XLOOKUP("Enterprise Value",Inputs!$B:$B,Inputs!P:P)/_xlfn.XLOOKUP("Revenue (Sales)",Inputs!$B:$B,Inputs!P:P),"") -> 3.5238512 | P6: =IFERROR(_xlfn.XLOOKUP("Enterprise Value",Inputs!$B:$B,Inputs!Q:Q)/_xlfn.XLOOKUP("Revenue (Sales)",Inputs!$B:$B,Inputs!Q:Q),"") -> 1.923657 | Q6: =IFERROR(_xlfn.XLOOKUP("Enterprise Value",DCF!$B:$B,DCF!R:R)/_xlfn.XLOOKUP("Revenue (Sales)",DCF!$B:$B,DCF!H:H),"") -> 2.7637354 | R6: =IFERROR(_xlfn.XLOOKUP("Enterprise Value",DCF!$B:$B,DCF!S:S)/_xlfn.XLOOKUP("Revenue (Sales)",DCF!$B:$B,DCF!I:I),"") -> 2.54297
B7: Price / Sales | F7: =IFERROR(_xlfn.XLOOKUP("Market Capitalization",Inputs!$B:$B,Inputs!G:G)/_xlfn.XLOOKUP("Revenue (Sales)",Inputs!$B:$B,Inputs!G:G),"") -> 2.0025021 | G7: =IFERROR(_xlfn.XLOOKUP("Market Capitalization",Inputs!$B:$B,Inputs!H:H)/_xlfn.XLOOKUP("Revenue (Sales)",Inputs!$B:$B,Inputs!H:H),"") -> 1.1951867 | H7: =IFERROR(_xlfn.XLOOKUP("Market Capitalization",Inputs!$B:$B,Inputs!I:I)/_xlfn.XLOOKUP("Revenue (Sales)",Inputs!$B:$B,Inputs!I:I),"") -> 1.8349924 | I7: =IFERROR(_xlfn.XLOOKUP("Market Capitalization",Inputs!$B:$B,Inputs!J:J)/_xlfn.XLOOKUP("Revenue (Sales)",Inputs!$B:$B,Inputs!J:J),"") -> 1.7937588 | J7: =IFERROR(_xlfn.XLOOKUP("Market Capitalization",Inputs!$B:$B,Inputs!K:K)/_xlfn.XLOOKUP("Revenue (Sales)",Inputs!$B:$B,Inputs!K:K),"") -> 1.0445555 | K7: =IFERROR(_xlfn.XLOOKUP("Market Capitalization",Inputs!$B:$B,Inputs!L:L)/_xlfn.XLOOKUP("Revenue (Sales)",Inputs!$B:$B,Inputs!L:L),"") -> 2.3846881 | L7: =IFERROR(_xlfn.XLOOKUP("Market Capitalization",Inputs!$B:$B,Inputs!M:M)/_xlfn.XLOOKUP("Revenue (Sales)",Inputs!$B:$B,Inputs!M:M),"") -> 2.4872415 | M7: =IFERROR(_xlfn.XLOOKUP("Market Capitalization",Inputs!$B:$B,Inputs!N:N)/_xlfn.XLOOKUP("Revenue (Sales)",Inputs!$B:$B,Inputs!N:N),"") -> 2.0273781 | N7: =IFERROR(_xlfn.XLOOKUP("Market Capitalization",Inputs!$B:$B,Inputs!O:O)/_xlfn.XLOOKUP("Revenue (Sales)",Inputs!$B:$B,Inputs!O:O),"") -> 1.1557183 | O7: =IFERROR(_xlfn.XLOOKUP("Market Capitalization",Inputs!$B:$B,Inputs!P:P)/_xlfn.XLOOKUP("Revenue (Sales)",Inputs!$B:$B,Inputs!P:P),"") -> 2.9715877 | P7: =IFERROR(_xlfn.XLOOKUP("Market Capitalization",Inputs!$B:$B,Inputs!Q:Q)/_xlfn.XLOOKUP("Revenue (Sales)",Inputs!$B:$B,Inputs!Q:Q),"") -> 1.8093292 | Q7: =IFERROR(_xlfn.XLOOKUP("Equity Value",DCF!$B:$B,DCF!R:R)/_xlfn.XLOOKUP("Revenue (Sales)",DCF!$B:$B,DCF!H:H),"") -> 2.5449301 | R7: =IFERROR(_xlfn.XLOOKUP("Equity Value",DCF!$B:$B,DCF!S:S)/_xlfn.XLOOKUP("Revenue (Sales)",DCF!$B:$B,DCF!I:I),"") -> 2.2047795
B8: EV / EBITDA | F8: =IFERROR(_xlfn.XLOOKUP("Enterprise Value",Inputs!$B:$B,Inputs!G:G)/_xlfn.XLOOKUP("EBITDA",Inputs!$B:$B,Inputs!G:G),"") -> 6.2617956 | G8: =IFERROR(_xlfn.XLOOKUP("Enterprise Value",Inputs!$B:$B,Inputs!H:H)/_xlfn.XLOOKUP("EBITDA",Inputs!$B:$B,Inputs!H:H),"") -> 3.655647 | H8: =IFERROR(_xlfn.XLOOKUP("Enterprise Value",Inputs!$B:$B,Inputs!I:I)/_xlfn.XLOOKUP("EBITDA",Inputs!$B:$B,Inputs!I:I),"") -> 8.5302383 | I8: =IFERROR(_xlfn.XLOOKUP("Enterprise Value",Inputs!$B:$B,Inputs!J:J)/_xlfn.XLOOKUP("EBITDA",Inputs!$B:$B,Inputs!J:J),"") -> 3.470942 | J8: =IFERROR(_xlfn.XLOOKUP("Enterprise Value",Inputs!$B:$B,Inputs!K:K)/_xlfn.XLOOKUP("EBITDA",Inputs!$B:$B,Inputs!K:K),"") -> 1.7888324 | K8: =IFERROR(_xlfn.XLOOKUP("Enterprise Value",Inputs!$B:$B,Inputs!L:L)/_xlfn.XLOOKUP("EBITDA",Inputs!$B:$B,Inputs!L:L),"") -> 19.71752 | L8: =IFERROR(_xlfn.XLOOKUP("Enterprise Value",Inputs!$B:$B,Inputs!M:M)/_xlfn.XLOOKUP("EBITDA",Inputs!$B:$B,Inputs!M:M),"") -> 14.167963 | M8: =IFERROR(_xlfn.XLOOKUP("Enterprise Value",Inputs!$B:$B,Inputs!N:N)/_xlfn.XLOOKUP("EBITDA",Inputs!$B:$B,Inputs!N:N),"") -> 7.2486317 | N8: =IFERROR(_xlfn.XLOOKUP("Enterprise Value",Inputs!$B:$B,Inputs!O:O)/_xlfn.XLOOKUP("EBITDA",Inputs!$B:$B,Inputs!O:O),"") -> 8.9088506 | O8: =IFERROR(_xlfn.XLOOKUP("Enterprise Value",Inputs!$B:$B,Inputs!P:P)/_xlfn.XLOOKUP("EBITDA",Inputs!$B:$B,Inputs!P:P),"") -> -16.163601 | P8: =IFERROR(_xlfn.XLOOKUP("Enterprise Value",Inputs!$B:$B,Inputs!Q:Q)/_xlfn.XLOOKUP("EBITDA",Inputs!$B:$B,Inputs!Q:Q),"") -> 5.2995642 | Q8: =IFERROR(_xlfn.XLOOKUP("Enterprise Value",DCF!$B:$B,DCF!R:R)/_xlfn.XLOOKUP("EBITDA",DCF!$B:$B,DCF!H:H),"") -> 11.452243 | R8: =IFERROR(_xlfn.XLOOKUP("Enterprise Value",DCF!$B:$B,DCF!S:S)/_xlfn.XLOOKUP("EBITDA",DCF!$B:$B,DCF!I:I),"") -> 9.9819784
B9: EV / EBIT | F9: =IFERROR(_xlfn.XLOOKUP("Enterprise Value",Inputs!$B:$B,Inputs!G:G)/_xlfn.XLOOKUP("Operating Income (EBIT)",Inputs!$B:$B,Inputs!G:G),"") -> 6.541433 | G9: =IFERROR(_xlfn.XLOOKUP("Enterprise Value",Inputs!$B:$B,Inputs!H:H)/_xlfn.XLOOKUP("Operating Income (EBIT)",Inputs!$B:$B,Inputs!H:H),"") -> 3.8807815 | H9: =IFERROR(_xlfn.XLOOKUP("Enterprise Value",Inputs!$B:$B,Inputs!I:I)/_xlfn.XLOOKUP("Operating Income (EBIT)",Inputs!$B:$B,Inputs!I:I),"") -> 9.4774657 | I9: =IFERROR(_xlfn.XLOOKUP("Enterprise Value",Inputs!$B:$B,Inputs!J:J)/_xlfn.XLOOKUP("Operating Income (EBIT)",Inputs!$B:$B,Inputs!J:J),"") -> 3.5831619 | J9: =IFERROR(_xlfn.XLOOKUP("Enterprise Value",Inputs!$B:$B,Inputs!K:K)/_xlfn.XLOOKUP("Operating Income (EBIT)",Inputs!$B:$B,Inputs!K:K),"") -> 1.8378932 | K9: =IFERROR(_xlfn.XLOOKUP("Enterprise Value",Inputs!$B:$B,Inputs!L:L)/_xlfn.XLOOKUP("Operating Income (EBIT)",Inputs!$B:$B,Inputs!L:L),"") -> 26.198661 | L9: =IFERROR(_xlfn.XLOOKUP("Enterprise Value",Inputs!$B:$B,Inputs!M:M)/_xlfn.XLOOKUP("Operating Income (EBIT)",Inputs!$B:$B,Inputs!M:M),"") -> 16.89692 | M9: =IFERROR(_xlfn.XLOOKUP("Enterprise Value",Inputs!$B:$B,Inputs!N:N)/_xlfn.XLOOKUP("Operating Income (EBIT)",Inputs!$B:$B,Inputs!N:N),"") -> 7.6837143 | N9: =IFERROR(_xlfn.XLOOKUP("Enterprise Value",Inputs!$B:$B,Inputs!O:O)/_xlfn.XLOOKUP("Operating Income (EBIT)",Inputs!$B:$B,Inputs!O:O),"") -> 9.7977208 | O9: =IFERROR(_xlfn.XLOOKUP("Enterprise Value",Inputs!$B:$B,Inputs!P:P)/_xlfn.XLOOKUP("Operating Income (EBIT)",Inputs!$B:$B,Inputs!P:P),"") -> -14.936025 | P9: =IFERROR(_xlfn.XLOOKUP("Enterprise Value",Inputs!$B:$B,Inputs!Q:Q)/_xlfn.XLOOKUP("Operating Income (EBIT)",Inputs!$B:$B,Inputs!Q:Q),"") -> 5.4259368 | Q9: =IFERROR(_xlfn.XLOOKUP("Enterprise Value",DCF!$B:$B,DCF!R:R)/_xlfn.XLOOKUP("Operating Income (EBIT)",DCF!$B:$B,DCF!H:H),"") -> 11.868305 | R9: =IFERROR(_xlfn.XLOOKUP("Enterprise Value",DCF!$B:$B,DCF!S:S)/_xlfn.XLOOKUP("Operating Income (EBIT)",DCF!$B:$B,DCF!I:I),"") -> 10.324853
B10: Price / Earnings | F10: =IFERROR(_xlfn.XLOOKUP("Market Capitalization",Inputs!$B:$B,Inputs!G:G)/_xlfn.XLOOKUP("Net Income",Inputs!$B:$B,Inputs!G:G),"") -> 8.1747873 | G10: =IFERROR(_xlfn.XLOOKUP("Market Capitalization",Inputs!$B:$B,Inputs!H:H)/_xlfn.XLOOKUP("Net Income",Inputs!$B:$B,Inputs!H:H),"") -> 5.1963919 | H10: =IFERROR(_xlfn.XLOOKUP("Market Capitalization",Inputs!$B:$B,Inputs!I:I)/_xlfn.XLOOKUP("Net Income",Inputs!$B:$B,Inputs!I:I),"") -> 10.659393 | I10: =IFERROR(_xlfn.XLOOKUP("Market Capitalization",Inputs!$B:$B,Inputs!J:J)/_xlfn.XLOOKUP("Net Income",Inputs!$B:$B,Inputs!J:J),"") -> 5.0749368 | J10: =IFERROR(_xlfn.XLOOKUP("Market Capitalization",Inputs!$B:$B,Inputs!K:K)/_xlfn.XLOOKUP("Net Income",Inputs!$B:$B,Inputs!K:K),"") -> 2.7185718 | K10: =IFERROR(_xlfn.XLOOKUP("Market Capitalization",Inputs!$B:$B,Inputs!L:L)/_xlfn.XLOOKUP("Net Income",Inputs!$B:$B,Inputs!L:L),"") -> 32.036434 | L10: =IFERROR(_xlfn.XLOOKUP("Market Capitalization",Inputs!$B:$B,Inputs!M:M)/_xlfn.XLOOKUP("Net Income",Inputs!$B:$B,Inputs!M:M),"") -> 16.672761 | M10: =IFERROR(_xlfn.XLOOKUP("Market Capitalization",Inputs!$B:$B,Inputs!N:N)/_xlfn.XLOOKUP("Net Income",Inputs!$B:$B,Inputs!N:N),"") -> 9.0652025 | N10: =IFERROR(_xlfn.XLOOKUP("Market Capitalization",Inputs!$B:$B,Inputs!O:O)/_xlfn.XLOOKUP("Net Income",Inputs!$B:$B,Inputs!O:O),"") -> 23.004862 | O10: =IFERROR(_xlfn.XLOOKUP("Market Capitalization",Inputs!$B:$B,Inputs!P:P)/_xlfn.XLOOKUP("Net Income",Inputs!$B:$B,Inputs!P:P),"") -> -10.65555 | P10: =IFERROR(_xlfn.XLOOKUP("Market Capitalization",Inputs!$B:$B,Inputs!Q:Q)/_xlfn.XLOOKUP("Net Income",Inputs!$B:$B,Inputs!Q:Q),"") -> 6.0496199 | Q10: =IFERROR(_xlfn.XLOOKUP("Equity Value",DCF!$B:$B,DCF!R:R)/_xlfn.XLOOKUP("Net Income",DCF!$B:$B,DCF!H:H),"") -> 16.665114 | R10: =IFERROR(_xlfn.XLOOKUP("Equity Value",DCF!$B:$B,DCF!S:S)/_xlfn.XLOOKUP("Net Income",DCF!$B:$B,DCF!I:I),"") -> 12.147745
B11: Price / Book | F11: =IFERROR(_xlfn.XLOOKUP("Market Capitalization",Inputs!$B:$B,Inputs!G:G)/_xlfn.XLOOKUP("Shareholder's Equity",Inputs!$B:$B,Inputs!G:G),"") -> 1.9013905 | G11: =IFERROR(_xlfn.XLOOKUP("Market Capitalization",Inputs!$B:$B,Inputs!H:H)/_xlfn.XLOOKUP("Shareholder's Equity",Inputs!$B:$B,Inputs!H:H),"") -> 1.0504692 | H11: =IFERROR(_xlfn.XLOOKUP("Market Capitalization",Inputs!$B:$B,Inputs!I:I)/_xlfn.XLOOKUP("Shareholder's Equity",Inputs!$B:$B,Inputs!I:I),"") -> 1.3136333 | I11: =IFERROR(_xlfn.XLOOKUP("Market Capitalization",Inputs!$B:$B,Inputs!J:J)/_xlfn.XLOOKUP("Shareholder's Equity",Inputs!$B:$B,Inputs!J:J),"") -> 1.596912 | J11: =IFERROR(_xlfn.XLOOKUP("Market Capitalization",Inputs!$B:$B,Inputs!K:K)/_xlfn.XLOOKUP("Shareholder's Equity",Inputs!$B:$B,Inputs!K:K),"") -> 0.90171113 | K11: =IFERROR(_xlfn.XLOOKUP("Market Capitalization",Inputs!$B:$B,Inputs!L:L)/_xlfn.XLOOKUP("Shareholder's Equity",Inputs!$B:$B,Inputs!L:L),"") -> 1.3427209 | L11: =IFERROR(_xlfn.XLOOKUP("Market Capitalization",Inputs!$B:$B,Inputs!M:M)/_xlfn.XLOOKUP("Shareholder's Equity",Inputs!$B:$B,Inputs!M:M),"") -> 1.5285181 | M11: =IFERROR(_xlfn.XLOOKUP("Market Capitalization",Inputs!$B:$B,Inputs!N:N)/_xlfn.XLOOKUP("Shareholder's Equity",Inputs!$B:$B,Inputs!N:N),"") -> 1.4016925 | N11: =IFERROR(_xlfn.XLOOKUP("Market Capitalization",Inputs!$B:$B,Inputs!O:O)/_xlfn.XLOOKUP("Shareholder's Equity",Inputs!$B:$B,Inputs!O:O),"") -> 0.81481423 | O11: =IFERROR(_xlfn.XLOOKUP("Market Capitalization",Inputs!$B:$B,Inputs!P:P)/_xlfn.XLOOKUP("Shareholder's Equity",Inputs!$B:$B,Inputs!P:P),"") -> 1.8197988 | P11: =IFERROR(_xlfn.XLOOKUP("Market Capitalization",Inputs!$B:$B,Inputs!Q:Q)/_xlfn.XLOOKUP("Shareholder's Equity",Inputs!$B:$B,Inputs!Q:Q),"") -> 1.6202908 | Q11: =IFERROR(+_xlfn.XLOOKUP("Equity Value",DCF!$B:$B,DCF!R:R)/(_xlfn.XLOOKUP("Shareholder's Equity",Inputs!$B:$B,Inputs!$Q:$Q)+_xlfn.XLOOKUP("Net Income",DCF!$B:$B,DCF!H:H)+_xlfn.XLOOKUP("Total Payout",DCF!$B:$B,DCF!H:H)),"") -> 2.3578344 | R11: =IFERROR(+_xlfn.XLOOKUP("Equity Value",DCF!$B:$B,DCF!S:S)/(_xlfn.XLOOKUP("Shareholder's Equity",Inputs!$B:$B,Inputs!$Q:$Q)+_xlfn.XLOOKUP("Net Income",DCF!$B:$B,DCF!I:I)+_xlfn.XLOOKUP("Total Payout",DCF!$B:$B,DCF!I:I)),"") -> 2.2618721
B13: Profitability | F13: 2014 | G13: =+F13+1 -> 2015 | H13: =+G13+1 -> 2016 | I13: =+H13+1 -> 2017 | J13: =+I13+1 -> 2018 | K13: =+J13+1 -> 2019 | L13: =+K13+1 -> 2020 | M13: =+L13+1 -> 2021 | N13: 2022 | O13: =+N13+1 -> 2023 | P13: =+O13+1 -> 2024 | Q13: =+P13+1 -> 2025 | R13: =+Q13+1 -> 2026
