Workbook
Name COOLFUCNTION: _xlfn.LAMBDA(_xldudf_BOARDFLARE_EXEC("workbook-settings:coolfucntion"))
Name COOLFUCNTION: _xlfn.LAMBDA(_xldudf_BOARDFLARE_EXEC("workbook-settings:coolfucntion"))
Name COOLFUCNTION: _xlfn.LAMBDA(_xldudf_BOARDFLARE_EXEC("workbook-settings:coolfucntion"))
Name COOLFUCNTION: _xlfn.LAMBDA(_xldudf_BOARDFLARE_EXEC("workbook-settings:coolfucntion"))
Name COOLFUCNTION: _xlfn.LAMBDA(_xldudf_BOARDFLARE_EXEC("workbook-settings:coolfucntion"))
Name COOLFUCNTION: _xlfn.LAMBDA(_xldudf_BOARDFLARE_EXEC("workbook-settings:coolfucntion"))
Name COOLFUCNTION: _xlfn.LAMBDA(_xldudf_BOARDFLARE_EXEC("workbook-settings:coolfucntion"))
Name COOLFUCNTION: _xlfn.LAMBDA(_xldudf_BOARDFLARE_EXEC("workbook-settings:coolfucntion"))
Name COOLFUCNTION: _xlfn.LAMBDA(_xldudf_BOARDFLARE_EXEC("workbook-settings:coolfucntion"))
Name COOLFUCNTION: _xlfn.LAMBDA(_xldudf_BOARDFLARE_EXEC("workbook-settings:coolfucntion"))
Name Sectors: #REF!
Name Sectors: #REF!
Name Sectors: #REF!

Sheet Summary
E2: | EQUITY RESEARCH | U2: Lisbon Investment Society Equity Research | AB2: Iterations
U3: April 30, 2025
AA4: 1 | AB4: 95.991539
AA5: =+AA4+1 -> 2 | AB5: 100.38109
D6: {=+_FV(DCF!R4,"Name")} -> UBER TECHNOLOGIES, INC. | U6: Buy | AA6: =+AA5+1 -> 3 | AB6: 90.015784
AA7: =+AA6+1 -> 4 | AB7: 89.345851
D8: Uber is a ride-hailing company that allows passengers to find drivers through the mobile app. Beyond transportation, Uber offers food delivery services as well as freight services. Uber has a strong market position globally, among its peers, it has the best financial performance as well as the highest number of users. The company has gone through some major losses, however, it has shown significant growth in revenue, primarily driven by the mobility sector and its ability to maintain costs. | U8: UBER | AA8: =+AA7+1 -> 5 | AB8: 89.345851
U9: {=+"Price (7 Mar 25): $"&_FV(DCF!$R$4,"Price")} -> Price (7 Mar 25): $94,36 | AA9: =+AA8+1 -> 6 | AB9: 84.845899
D10: Investment Thesis | U10: ="Price Target: $" & ROUND(IF(Summary!G25="FCFF",DCF!Q204,IF(Summary!G25="FCFE",DCF!Q247,IF(Summary!G25="Tax Shield",DCF!Q220,DCF!Q263))),2) &" "&IF(Summary!G25="FCFF","(FCFF)",IF(Summary!G25="FCFE","(FCFE)",IF(Summary!G25="Tax Shield","(APV)","(DDM)"))) -> Price Target: $88.18 (FCFF) | AA10: =+AA9+1 -> 7 | AB10: 95.198437
D11: Up until 2022, Uber represented negative operting income, however, since then the company was able to generate high positive operating income and net income, primarly driven by the increase of revenue in the mobility sector and as well as its ability to mantain its cost of good solds and other expenses. This increase is both explained by the number of trips realized and montly active platform menbers. Thus despite its past losses, it is belived Uber will have an upside of 11,02% this it efforts in innovation shod by its recent partnerships such as with Nvidea and Weride and as well its effortsin expanding the autonomaus veichels in the US. Furthermore, comparing to its peers, Uber is the only one with positive profit margin , it has a signifcant leverage due to its diverse business model which offers mobility delivery and fright services. Despite that the comapany still has legal relatuon issues in the classification of itts drivers as legal employeed in some regions which could have an negative impact in its profitabiltiy. | U11: =+"Upside (Downside): "&ROUND((DCF!$Q$207*100),2)&"%" -> Upside (Downside): 11.02% | AA11: =+AA10+1 -> 8 | AB11: 101.96157
AA12: =+AA11+1 -> 9 | AB12: 90.015784
AA13: =+AA12+1 -> 10 | AB13: 84.845899
U14: =+Industry!E28&", "&ESG!C9 -> EUA, Industrials | AA14: =+AA13+1 -> 11 | AB14: 100.38109
U15: =+ESG!C10 -> Transportation | AA15: =+AA14+1 -> 12 | AB15: 100.38109
AA16: =+AA15+1 -> 13 | AB16: 95.991539
D17: Operating Metrics | F17: 2023 | G17: =+F17+1 -> 2024 | H17: =+G17+1 -> 2025 | I17: =+H17+1 -> 2026 | K17: Valuation Multiples | N17: 2022 | O17: =+N17+1 -> 2023 | P17: =+O17+1 -> 2024 | Q17: =+P17+1 -> 2025 | R17: =+Q17+1 -> 2026 | U17: Mariana Zhu | AA17: =+AA16+1 -> 14 | AB17: 89.345851
D18: =DCF!B17 -> Yearly Active Platform Consumers | F18: =DCF!F17 -> 2236 | G18: =DCF!G17 -> 2548 | H18: =DCF!H17 -> 2751.84 | I18: =DCF!I17 -> 2971.9872 | K18: EV / Sales | N18: =IFERROR(_xlfn.XLOOKUP($K18,Multiples!$B:$B,Multiples!N:N),"") -> 1.7812847 | O18: =IFERROR(_xlfn.XLOOKUP($K18,Multiples!$B:$B,Multiples!O:O),"") -> 3.5686019 | P18: =IFERROR(_xlfn.XLOOKUP($K18,Multiples!$B:$B,Multiples!P:P),"") -> 2.9318812 | Q18: =IFERROR(_xlfn.XLOOKUP($K18,Multiples!$B:$B,Multiples!Q:Q),"") -> 3.1162152 | R18: =IFERROR(_xlfn.XLOOKUP($K18,Multiples!$B:$B,Multiples!R:R),"") -> 2.8733681 | U18: l63113@aln.iseg.ulisboa.pt | AA18: =+AA17+1 -> 15 | AB18: 89.345851
D19: =DCF!B19 -> Trip | F19: =DCF!F19 -> 9448 | G19: =DCF!G19 -> 11273 | H19: =DCF!H19 -> 12373.583 | I19: =DCF!I19 -> 13023.38 | K19: Price / Sales | N19: =IFERROR(_xlfn.XLOOKUP($K19,Multiples!$B:$B,Multiples!N:N),"") -> 1.5410801 | O19: =IFERROR(_xlfn.XLOOKUP($K19,Multiples!$B:$B,Multiples!O:O),"") -> 3.3619819 | P19: =IFERROR(_xlfn.XLOOKUP($K19,Multiples!$B:$B,Multiples!P:P),"") -> 2.8729427 | Q19: =IFERROR(_xlfn.XLOOKUP($K19,Multiples!$B:$B,Multiples!Q:Q),"") -> 2.9410175 | R19: =IFERROR(_xlfn.XLOOKUP($K19,Multiples!$B:$B,Multiples!R:R),"") -> 2.7937255 | U19: (+351) 926 820 308 | AA19: =+AA18+1 -> 16 | AB19: 90.015784
D20: =DCF!B20 -> Average Revenue per Trip | F20: =DCF!F20 -> 3.9459145 | G20: =DCF!G20 -> 3.9011798 | H20: =DCF!H20 -> 4.126312 | I20: =DCF!I20 -> 4.2501014 | K20: EV / EBITDA | N20: =IFERROR(_xlfn.XLOOKUP($K20,Multiples!$B:$B,Multiples!N:N),"") -> -64.160464 | O20: =IFERROR(_xlfn.XLOOKUP($K20,Multiples!$B:$B,Multiples!O:O),"") -> 68.826202 | P20: =IFERROR(_xlfn.XLOOKUP($K20,Multiples!$B:$B,Multiples!P:P),"") -> 36.73455 | Q20: =IFERROR(_xlfn.XLOOKUP($K20,Multiples!$B:$B,Multiples!Q:Q),"") -> 44.656863 | R20: =IFERROR(_xlfn.XLOOKUP($K20,Multiples!$B:$B,Multiples!R:R),"") -> 35.445728 | U20: João Ferreira | AA20: =+AA19+1 -> 17 | AB20: 95.198437
D21: =DCF!B21 -> Average Trip per MAPC | F21: =DCF!F21 -> 4.2254025 | G21: =DCF!G21 -> 4.4242543 | H21: =DCF!H21 -> 4.4964763 | I21: =DCF!I21 -> 4.3820444 | K21: EV / EBIT | N21: =IFERROR(_xlfn.XLOOKUP($K21,Multiples!$B:$B,Multiples!N:N),"") -> -30.994547 | O21: =IFERROR(_xlfn.XLOOKUP($K21,Multiples!$B:$B,Multiples!O:O),"") -> 119.8568 | P21: =IFERROR(_xlfn.XLOOKUP($K21,Multiples!$B:$B,Multiples!P:P),"") -> 46.065835 | Q21: =IFERROR(_xlfn.XLOOKUP($K21,Multiples!$B:$B,Multiples!Q:Q),"") -> 57.428454 | R21: =IFERROR(_xlfn.XLOOKUP($K21,Multiples!$B:$B,Multiples!R:R),"") -> 43.17702 | U21: joao@aln.iseg.ulisboa.pt | AA21: =+AA20+1 -> 18 | AB21: 100.38109
D22: =DCF!B22 -> Revenue for Mobility and Delivery | F22: =DCF!F22 -> 37281 | G22: =DCF!G22 -> 43978 | H22: =DCF!H22 -> 51057.265 | I22: =DCF!I22 -> 55350.684 | K22: Price / Earnings | N22: =IFERROR(_xlfn.XLOOKUP($K22,Multiples!$B:$B,Multiples!N:N),"") -> -5.3136843 | O22: =IFERROR(_xlfn.XLOOKUP($K22,Multiples!$B:$B,Multiples!O:O),"") -> 59.458278 | P22: =IFERROR(_xlfn.XLOOKUP($K22,Multiples!$B:$B,Multiples!P:P),"") -> 12.784202 | Q22: =IFERROR(_xlfn.XLOOKUP($K22,Multiples!$B:$B,Multiples!Q:Q),"") -> 93.432868 | R22: =IFERROR(_xlfn.XLOOKUP($K22,Multiples!$B:$B,Multiples!R:R),"") -> 39.866388 | U22: (+351) 968 210 598 | AA22: =+AA21+1 -> 19 | AB22: 101.96157
D23: =DCF!B23 -> Freight Revenue | G23: =DCF!G23 -> 5141 | H23: =DCF!H23 -> 5000 | I23: =DCF!I23 -> 5750 | K23: Price / Book | N23: =IFERROR(_xlfn.XLOOKUP($K23,Multiples!$B:$B,Multiples!N:N),"") -> 5.7766946 | O23: =IFERROR(_xlfn.XLOOKUP($K23,Multiples!$B:$B,Multiples!O:O),"") -> 9.8831453 | P23: =IFERROR(_xlfn.XLOOKUP($K23,Multiples!$B:$B,Multiples!P:P),"") -> 5.621386 | Q23: =IFERROR(_xlfn.XLOOKUP($K23,Multiples!$B:$B,Multiples!Q:Q),"") -> 6.5977806 | R23: =IFERROR(_xlfn.XLOOKUP($K23,Multiples!$B:$B,Multiples!R:R),"") -> 6.5164074 | U23: José Gonçalves | AA23: =+AA22+1 -> 20 | AB23: 84.845899
U24: l64272@aln.iseg.ulisboa.pt | AA24: =+AA23+1 -> 21 | AB24: 93.845803
D25: Year | E25: Net Sales | F25: EBIT Margin | G25: FCFF | H25: =+IF(Summary!$G$25="FCFF",DCF!AB6,IF(Summary!$G$25="FCFE",DCF!AC6,DCF!AD6)) -> NOPAT | I25: Net Capex | K25: Profitability Ratios | N25: 2022 | O25: =+N25+1 -> 2023 | P25: =+O25+1 -> 2024 | Q25: =+P25+1 -> 2025 | R25: =+Q25+1 -> 2026 | U25: (+351) 927 598 576 | AA25: =+AA24+1 -> 22 | AB25: 95.991539
D26: 2022 | E26: =+DCF!E26 -> 31877 | F26: =+DCF!E56 -> -0.057470904 | G26: =+INDEX(DCF!X7:AA7,MATCH(Summary!$G$25,{"FCFF","FCFE","Tax Shield","Total Payout"},0)) -> 556.17844 | H26: =+IF(Summary!$G$25="FCFF",DCF!AB7,IF(Summary!$G$25="FCFE",DCF!AC7,DCF!AD7)) -> -1796.8216 | I26: =+DCF!E130 -> -252 | K26: Return on Assets | N26: =IFERROR(_xlfn.XLOOKUP($K26,Multiples!$B:$B,Multiples!N:N),"") -> -0.2879255 | O26: =IFERROR(_xlfn.XLOOKUP($K26,Multiples!$B:$B,Multiples!O:O),"") -> 0.054471692 | P26: =IFERROR(_xlfn.XLOOKUP($K26,Multiples!$B:$B,Multiples!P:P),"") -> 0.1928616 | Q26: =IFERROR(_xlfn.XLOOKUP($K26,Multiples!$B:$B,Multiples!Q:Q),"") -> 0.029093078 | R26: =IFERROR(_xlfn.XLOOKUP($K26,Multiples!$B:$B,Multiples!R:R),"") -> 0.083634594 | U26: Marta Ferreiro | AA26: =+AA25+1 -> 23 | AB26: 89.345851
D27: =+D26+1 -> 2023 | E27: =+DCF!F26 -> 37281 | F27: =+DCF!F56 -> 0.029773879 | G27: =+INDEX(DCF!X8:AA8,MATCH(Summary!$G$25,{"FCFF","FCFE","Tax Shield","Total Payout"},0)) -> 3402.1344 | H27: =+IF(Summary!$G$25="FCFF",DCF!AB8,IF(Summary!$G$25="FCFE",DCF!AC8,DCF!AD8)) -> 1008.1344 | I27: =+DCF!F130 -> -223 | K27: Return on Equity | N27: =IFERROR(_xlfn.XLOOKUP($K27,Multiples!$B:$B,Multiples!N:N),"") -> -1.0871355 | O27: =IFERROR(_xlfn.XLOOKUP($K27,Multiples!$B:$B,Multiples!O:O),"") -> 0.16621984 | P27: =IFERROR(_xlfn.XLOOKUP($K27,Multiples!$B:$B,Multiples!P:P),"") -> 0.43971347 | Q27: =IFERROR(_xlfn.XLOOKUP($K27,Multiples!$B:$B,Multiples!Q:Q),"") -> 0.06919639 | R27: =IFERROR(_xlfn.XLOOKUP($K27,Multiples!$B:$B,Multiples!R:R),"") -> 0.19261473 | U27: marta.remuinan@aln.iseg.ulisboa.pt | AA27: =+AA26+1 -> 24 | AB27: 89.345851
D28: =+D27+1 -> 2024 | E28: =+DCF!G26 -> 43978 | F28: =+DCF!G56 -> 0.063645459 | G28: =+INDEX(DCF!X9:AA9,MATCH(Summary!$G$25,{"FCFF","FCFE","Tax Shield","Total Payout"},0)) -> 11040.065 | H28: =+IF(Summary!$G$25="FCFF",DCF!AB9,IF(Summary!$G$25="FCFE",DCF!AC9,DCF!AD9)) -> 6706.0647 | I28: =+DCF!G130 -> -242 | K28: Return on Total Capital | N28: =IFERROR(_xlfn.XLOOKUP($K28,Multiples!$B:$B,Multiples!N:N),"") -> -0.089652807 | O28: =IFERROR(_xlfn.XLOOKUP($K28,Multiples!$B:$B,Multiples!O:O),"") -> 0.041386528 | P28: =IFERROR(_xlfn.XLOOKUP($K28,Multiples!$B:$B,Multiples!P:P),"") -> 0.21544205 | Q28: =IFERROR(_xlfn.XLOOKUP($K28,Multiples!$B:$B,Multiples!Q:Q),"") -> 0.068078497 | R28: =IFERROR(_xlfn.XLOOKUP($K28,Multiples!$B:$B,Multiples!R:R),"") -> 0.11984609 | U28: (+34) 698 138 312 | AA28: =+AA27+1 -> 25 | AB28: 95.198437
D29: =+D28+1 -> 2025 | E29: =+DCF!H26 -> 56057.265 | F29: =+DCF!H56 -> 0.055215463 | G29: =+INDEX(DCF!X10:AA10,MATCH(Summary!$G$25,{"FCFF","FCFE","Tax Shield","Total Payout"},0)) -> 4175.9664 | H29: =+IF(Summary!$G$25="FCFF",DCF!AB10,IF(Summary!$G$25="FCFE",DCF!AC10,DCF!AD10)) -> 2204.012 | I29: =+DCF!H130 -> -300 | K29: EBITDA Margin | N29: =IFERROR(_xlfn.XLOOKUP($K29,Multiples!$B:$B,Multiples!N:N),"") -> -0.027762964 | O29: =IFERROR(_xlfn.XLOOKUP($K29,Multiples!$B:$B,Multiples!O:O),"") -> 0.051849468 | P29: =IFERROR(_xlfn.XLOOKUP($K29,Multiples!$B:$B,Multiples!P:P),"") -> 0.079812634 | Q29: =IFERROR(_xlfn.XLOOKUP($K29,Multiples!$B:$B,Multiples!Q:Q),"") -> 0.070234737 | R29: =IFERROR(_xlfn.XLOOKUP($K29,Multiples!$B:$B,Multiples!R:R),"") -> 0.083041581 | AA29: =+AA28+1 -> 26 | AB29: 100.38109
D30: =+D29+1 -> 2026 | E30: =+DCF!I26 -> 61100.684 | F30: =+DCF!I56 -> 0.068219208 | G30: =+INDEX(DCF!X11:AA11,MATCH(Summary!$G$25,{"FCFF","FCFE","Tax Shield","Total Payout"},0)) -> 6797.9969 | H30: =+IF(Summary!$G$25="FCFF",DCF!AB11,IF(Summary!$G$25="FCFE",DCF!AC11,DCF!AD11)) -> 4009.5308 | I30: =+DCF!I130 -> -330 | K30: EBIT Margin | N30: =IFERROR(_xlfn.XLOOKUP($K30,Multiples!$B:$B,Multiples!N:N),"") -> -0.057470904 | O30: =IFERROR(_xlfn.XLOOKUP($K30,Multiples!$B:$B,Multiples!O:O),"") -> 0.029773879 | P30: =IFERROR(_xlfn.XLOOKUP($K30,Multiples!$B:$B,Multiples!P:P),"") -> 0.063645459 | Q30: =IFERROR(_xlfn.XLOOKUP($K30,Multiples!$B:$B,Multiples!Q:Q),"") -> 0.055215463 | R30: =IFERROR(_xlfn.XLOOKUP($K30,Multiples!$B:$B,Multiples!R:R),"") -> 0.068219208 | U30: Statistics | AA30: =+AA29+1 -> 27 | AB30: 84.845899
D31: =+D30+1 -> 2027 | E31: =+DCF!J26 -> 68918.259 | F31: =+DCF!J56 -> 0.071762543 | G31: =+INDEX(DCF!X12:AA12,MATCH(Summary!$G$25,{"FCFF","FCFE","Tax Shield","Total Payout"},0)) -> 9152.6815 | H31: =+IF(Summary!$G$25="FCFF",DCF!AB12,IF(Summary!$G$25="FCFE",DCF!AC12,DCF!AD12)) -> 4729.4643 | I31: =+DCF!J130 -> -363 | K31: Gross Profit Margin | N31: =IFERROR(_xlfn.XLOOKUP($K31,Multiples!$B:$B,Multiples!N:N),"") -> 0.38328575 | O31: =IFERROR(_xlfn.XLOOKUP($K31,Multiples!$B:$B,Multiples!O:O),"") -> 0.39762882 | P31: =IFERROR(_xlfn.XLOOKUP($K31,Multiples!$B:$B,Multiples!P:P),"") -> 0.39399245 | Q31: =IFERROR(_xlfn.XLOOKUP($K31,Multiples!$B:$B,Multiples!Q:Q),"") -> 0.39163567 | R31: =IFERROR(_xlfn.XLOOKUP($K31,Multiples!$B:$B,Multiples!R:R),"") -> 0.39441898 | U31: Beta | V31: =Peers!D74 -> 1.482 | AA31: =+AA30+1 -> 28 | AB31: 95.991539
D32: =+D31+1 -> 2028 | E32: =+DCF!K26 -> 76965.424 | F32: =+DCF!K56 -> 0.072003797 | G32: =+INDEX(DCF!X13:AA13,MATCH(Summary!$G$25,{"FCFF","FCFE","Tax Shield","Total Payout"},0)) -> 8099.7704 | H32: =+IF(Summary!$G$25="FCFF",DCF!AB13,IF(Summary!$G$25="FCFE",DCF!AC13,DCF!AD13)) -> 4360.534 | I32: =+DCF!K130 -> -399.3 | K32: SG&A Margin | N32: =IFERROR(_xlfn.XLOOKUP($K32,Multiples!$B:$B,Multiples!N:N),"") -> 0.24757662 | O32: =IFERROR(_xlfn.XLOOKUP($K32,Multiples!$B:$B,Multiples!O:O),"") -> 0.18878249 | P32: =IFERROR(_xlfn.XLOOKUP($K32,Multiples!$B:$B,Multiples!P:P),"") -> 0.18136341 | Q32: =IFERROR(_xlfn.XLOOKUP($K32,Multiples!$B:$B,Multiples!Q:Q),"") -> 0.18091 | R32: =IFERROR(_xlfn.XLOOKUP($K32,Multiples!$B:$B,Multiples!R:R),"") -> 0.18045773 | U32: % Float | V32: =+Peers!D73 -> 0.9634 | AA32: =+AA31+1 -> 29 | AB32: 100.38109
D33: =+D32+1 -> 2029 | E33: =+DCF!L26 -> 85560.99 | F33: =+DCF!L56 -> 0.077418287 | G33: =+INDEX(DCF!X14:AA14,MATCH(Summary!$G$25,{"FCFF","FCFE","Tax Shield","Total Payout"},0)) -> 9622.6828 | H33: =+IF(Summary!$G$25="FCFF",DCF!AB14,IF(Summary!$G$25="FCFE",DCF!AC14,DCF!AD14)) -> 5232.9484 | I33: =+DCF!L130 -> -439.23 | K33: Net Income Margin | N33: =IFERROR(_xlfn.XLOOKUP($K33,Multiples!$B:$B,Multiples!N:N),"") -> -0.29002102 | O33: =IFERROR(_xlfn.XLOOKUP($K33,Multiples!$B:$B,Multiples!O:O),"") -> 0.056543548 | P33: =IFERROR(_xlfn.XLOOKUP($K33,Multiples!$B:$B,Multiples!P:P),"") -> 0.224726 | Q33: =IFERROR(_xlfn.XLOOKUP($K33,Multiples!$B:$B,Multiples!Q:Q),"") -> 0.027044967 | R33: =IFERROR(_xlfn.XLOOKUP($K33,Multiples!$B:$B,Multiples!R:R),"") -> 0.072384671 | U33: % Held by Insiders | V33: =+Peers!D76 -> 0.0167 | AA33: =+AA32+1 -> 30 | AB33: 89.345851
U34: % Held by Institutions | V34: =+Peers!D77 -> 0.8116 | AA34: =+AA33+1 -> 31 | AB34: 89.345851
D35: SWOT Analysis | K35: Liquidity Ratios | N35: 2022 | O35: =+N35+1 -> 2023 | P35: =+O35+1 -> 2024 | Q35: =+P35+1 -> 2025 | R35: =+Q35+1 -> 2026 | U35: Short % of Float | V35: =+Peers!D78 -> 0.031 | AA35: =+AA34+1 -> 32 | AB35: 93.845803
D36: Strengths | G36: Weaknesses | K36: Cash Ratio | N36: =IFERROR(_xlfn.XLOOKUP($K36,Multiples!$B:$B,Multiples!N:N),"") -> 0.4753191 | O36: =IFERROR(_xlfn.XLOOKUP($K36,Multiples!$B:$B,Multiples!O:O),"") -> 0.49502856 | P36: =IFERROR(_xlfn.XLOOKUP($K36,Multiples!$B:$B,Multiples!P:P),"") -> 0.51350645 | Q36: =IFERROR(_xlfn.XLOOKUP($K36,Multiples!$B:$B,Multiples!Q:Q),"") -> 0.28314325 | R36: =IFERROR(_xlfn.XLOOKUP($K36,Multiples!$B:$B,Multiples!R:R),"") -> 0.3377768 | W36: 120.87 | AA36: =+AA35+1 -> 33 | AB36: 107.93161
D37: Brand Recognition Variety of Services | G37: Driver classification lawsuits Reputation Concerns | K37: Quick Ratio | N37: =IFERROR(_xlfn.XLOOKUP($K37,Multiples!$B:$B,Multiples!N:N),"") -> 0.80085847 | O37: =IFERROR(_xlfn.XLOOKUP($K37,Multiples!$B:$B,Multiples!O:O),"") -> 0.93198646 | P37: =IFERROR(_xlfn.XLOOKUP($K37,Multiples!$B:$B,Multiples!P:P),"") -> 0.89839665 | Q37: =IFERROR(_xlfn.XLOOKUP($K37,Multiples!$B:$B,Multiples!Q:Q),"") -> 0.74182436 | R37: =IFERROR(_xlfn.XLOOKUP($K37,Multiples!$B:$B,Multiples!R:R),"") -> 0.82630139 | U37: Major Holders | W37: 113.63 | AA37: =+AA36+1 -> 34 | AB37: 95.198437
K38: Current Ratio | N38: =IFERROR(_xlfn.XLOOKUP($K38,Multiples!$B:$B,Multiples!N:N),"") -> 1.0447306 | O38: =IFERROR(_xlfn.XLOOKUP($K38,Multiples!$B:$B,Multiples!O:O),"") -> 1.1949439 | P38: =IFERROR(_xlfn.XLOOKUP($K38,Multiples!$B:$B,Multiples!P:P),"") -> 1.0670094 | Q38: =IFERROR(_xlfn.XLOOKUP($K38,Multiples!$B:$B,Multiples!Q:Q),"") -> 0.96143881 | R38: =IFERROR(_xlfn.XLOOKUP($K38,Multiples!$B:$B,Multiples!R:R),"") -> 0.96143881 | U38: Vanguard Group Inc. | V38: 0.0864 | AA38: =+AA37+1 -> 35 | AB38: 100.38109
U39: BlackRock Inc. | V39: 0.0741 | AA39: =+AA38+1 -> 36 | AB39: 93.845803
D40: Opportunities | G40: Threats | K40: Cash Flow Ratios | N40: 2022 | O40: =+N40+1 -> 2023 | P40: =+O40+1 -> 2024 | Q40: =+P40+1 -> 2025 | R40: =+Q40+1 -> 2026 | U40: Capital Research Global Investors | V40: 0.0565 | AA40: =+AA39+1 -> 37 | AB40: 89.345851
D41: Expansion to AVs Strategic Partnerships | G41: Intensive Competition Regulatory Issues | K41: Cash Conversion Cycle | N41: =IFERROR(_xlfn.XLOOKUP($K41,Multiples!$B:$B,Multiples!N:N),"") -> 23.484487 | O41: =IFERROR(_xlfn.XLOOKUP($K41,Multiples!$B:$B,Multiples!O:O),"") -> 25.592393 | P41: =IFERROR(_xlfn.XLOOKUP($K41,Multiples!$B:$B,Multiples!P:P),"") -> 20.541521 | Q41: =IFERROR(_xlfn.XLOOKUP($K41,Multiples!$B:$B,Multiples!Q:Q),"") -> 18.248673 | R41: =IFERROR(_xlfn.XLOOKUP($K41,Multiples!$B:$B,Multiples!R:R),"") -> 18.23029 | U41: State Street Corporation | V41: 0.0408 | AA41: =+AA40+1 -> 38 | AB41: 95.198437
K42: Net Income / Op Cash Flow | N42: =IFERROR(_xlfn.XLOOKUP($K42,Multiples!$B:$B,Multiples!N:N),"") -> -14.400312 | O42: =IFERROR(_xlfn.XLOOKUP($K42,Multiples!$B:$B,Multiples!O:O),"") -> 0.58800558 | P42: =IFERROR(_xlfn.XLOOKUP($K42,Multiples!$B:$B,Multiples!P:P),"") -> 1.3847555 | Q42: =IFERROR(_xlfn.XLOOKUP($K42,Multiples!$B:$B,Multiples!Q:Q),"") -> 0.46127993 | R42: =IFERROR(_xlfn.XLOOKUP($K42,Multiples!$B:$B,Multiples!R:R),"") -> 1.032239 | U42: Morgan Stanley | V42: 0.0387 | AA42: =+AA41+1 -> 39 | AB42: 93.845803
K43: Chg in Cash / Op Cash Flow | N43: =IFERROR(_xlfn.XLOOKUP($K43,Multiples!$B:$B,Multiples!N:N),"") -> -1.7570093 | O43: =IFERROR(_xlfn.XLOOKUP($K43,Multiples!$B:$B,Multiples!O:O),"") -> 0.091213389 | P43: =IFERROR(_xlfn.XLOOKUP($K43,Multiples!$B:$B,Multiples!P:P),"") -> 0.22502452 | Q43: =IFERROR(_xlfn.XLOOKUP($K43,Multiples!$B:$B,Multiples!Q:Q),"") -> -0.69629775 | R43: =IFERROR(_xlfn.XLOOKUP($K43,Multiples!$B:$B,Multiples!R:R),"") -> 0.16232565 | U43: Public Investment Fund | V43: 0.0348 | AA43: =+AA42+1 -> 40 | AB43: 84.845899
U44: JPMORGAN CHASE & CO | V44: 0.0214 | AA44: =+AA43+1 -> 41 | AB44: 89.345851
D45: Revenue by Region | G45: Revenue by Segment | K45: Leverage Ratios | N45: 2022 | O45: =+N45+1 -> 2023 | P45: =+O45+1 -> 2024 | Q45: =+P45+1 -> 2025 | R45: =+Q45+1 -> 2026 | U45: Geode Capital Management, LLC | V45: 0.0208 | AA45: =+AA44+1 -> 42 | AB45: 95.991539
K46: Total Debt / Equity | N46: =IFERROR(_xlfn.XLOOKUP($K46,Multiples!$B:$B,Multiples!N:N),"") -> 1356.7733 | O46: =IFERROR(_xlfn.XLOOKUP($K46,Multiples!$B:$B,Multiples!O:O),"") -> 920.75382 | P46: =IFERROR(_xlfn.XLOOKUP($K46,Multiples!$B:$B,Multiples!P:P),"") -> 384.89945 | Q46: =IFERROR(_xlfn.XLOOKUP($K46,Multiples!$B:$B,Multiples!Q:Q),"") -> 477.6415 | R46: =IFERROR(_xlfn.XLOOKUP($K46,Multiples!$B:$B,Multiples!R:R),"") -> 457.0233 | U46: FMR, LLC | V46: 0.0201 | AA46: =+AA45+1 -> 43 | AB46: 95.991539
K47: Total Debt / Capital | N47: =IFERROR(_xlfn.XLOOKUP($K47,Multiples!$B:$B,Multiples!N:N),"") -> 0.9992635 | O47: =IFERROR(_xlfn.XLOOKUP($K47,Multiples!$B:$B,Multiples!O:O),"") -> 0.99891511 | P47: =IFERROR(_xlfn.XLOOKUP($K47,Multiples!$B:$B,Multiples!P:P),"") -> 0.99740865 | Q47: =IFERROR(_xlfn.XLOOKUP($K47,Multiples!$B:$B,Multiples!Q:Q),"") -> 0.99791075 | R47: =IFERROR(_xlfn.XLOOKUP($K47,Multiples!$B:$B,Multiples!R:R),"") -> 1 | U47: Wellington Management Group, LLP | V47: 0.0181 | AA47: =+AA46+1 -> 44 | AB47: 95.198437
K48: Total Liabilities / Total Assets | N48: =IFERROR(_xlfn.XLOOKUP($K48,Multiples!$B:$B,Multiples!N:N),"") -> 0.73515214 | O48: =IFERROR(_xlfn.XLOOKUP($K48,Multiples!$B:$B,Multiples!O:O),"") -> 0.67229127 | P48: =IFERROR(_xlfn.XLOOKUP($K48,Multiples!$B:$B,Multiples!P:P),"") -> 0.56139255 | Q48: =IFERROR(_xlfn.XLOOKUP($K48,Multiples!$B:$B,Multiples!Q:Q),"") -> 0.57955787 | R48: =IFERROR(_xlfn.XLOOKUP($K48,Multiples!$B:$B,Multiples!R:R),"") -> 0.56579337 | AA48: =+AA47+1 -> 45 | AB48: 101.96157
K49: Total Debt / EBITDA | N49: =IFERROR(_xlfn.XLOOKUP($K49,Multiples!$B:$B,Multiples!N:N),"") -> -13.037288 | O49: =IFERROR(_xlfn.XLOOKUP($K49,Multiples!$B:$B,Multiples!O:O),"") -> 6.0408691 | P49: =IFERROR(_xlfn.XLOOKUP($K49,Multiples!$B:$B,Multiples!P:P),"") -> 2.4646724 | Q49: =IFERROR(_xlfn.XLOOKUP($K49,Multiples!$B:$B,Multiples!Q:Q),"") -> 2.6579885 | R49: =IFERROR(_xlfn.XLOOKUP($K49,Multiples!$B:$B,Multiples!R:R),"") -> 2.0682348 | U49: Board of Directors | AA49: =+AA48+1 -> 46 | AB49: 100.38109
K50: Total Debt / (EBITDA - Capex) | N50: =IFERROR(_xlfn.XLOOKUP($K50,Multiples!$B:$B,Multiples!N:N),"") -> -10.147757 | O50: =IFERROR(_xlfn.XLOOKUP($K50,Multiples!$B:$B,Multiples!O:O),"") -> 6.828655 | P50: =IFERROR(_xlfn.XLOOKUP($K50,Multiples!$B:$B,Multiples!P:P),"") -> 2.6471848 | Q50: =IFERROR(_xlfn.XLOOKUP($K50,Multiples!$B:$B,Multiples!Q:Q),"") -> 2.828025 | R50: =IFERROR(_xlfn.XLOOKUP($K50,Multiples!$B:$B,Multiples!R:R),"") -> 2.2059806 | U50: R. Sugar(Chairman, Lead Indep.) [Indep.], Audit Committee. Chair Nom & Gov., Comp U. Burns(Chairman, Lead[Indep.], Audit Committee, Nom & Gov. D.Khosrowshahi. W.Martello[Indep.], Nom & Gov., Comp. J.Thain [Indep.] D.Trujillo. [Indep.], Nom & Gov., Comp. A. Ginsberg. [Indep.], Comp R.Eckert[Indep.], Chair Comp., Nom & Gov. R.Advaithi [Indep.], Audit Committee A.Wynaendts [Indep.], Audit Committee T.Alnowaiser[Indep.], Audit Committee | AA50: =+AA49+1 -> 47 | AB50: 95.198437
K51: Net Debt / EBITDA | N51: =IFERROR(_xlfn.XLOOKUP($K50,Multiples!$B:$B,Multiples!N:N),"") -> -10.147757 | O51: =IFERROR(_xlfn.XLOOKUP($K50,Multiples!$B:$B,Multiples!O:O),"") -> 6.828655 | P51: =IFERROR(_xlfn.XLOOKUP($K50,Multiples!$B:$B,Multiples!P:P),"") -> 2.6471848 | Q51: =IFERROR(_xlfn.XLOOKUP($K50,Multiples!$B:$B,Multiples!Q:Q),"") -> 2.828025 | R51: =IFERROR(_xlfn.XLOOKUP($K50,Multiples!$B:$B,Multiples!R:R),"") -> 2.2059806 | AA51: =+AA50+1 -> 48 | AB51: 84.845899
AA52: =+AA51+1 -> 49 | AB52: 95.198437
K53: Solvency Ratios | N53: 2022 | O53: =+N53+1 -> 2023 | P53: =+O53+1 -> 2024 | Q53: =+P53+1 -> 2025 | R53: =+Q53+1 -> 2026 | AA53: =+AA52+1 -> 50 | AB53: 100.38109
K54: EBIT / Interest Expense | N54: =IFERROR(_xlfn.XLOOKUP($K54,Multiples!$B:$B,Multiples!N:N),"") -> -3.2424779 | O54: =IFERROR(_xlfn.XLOOKUP($K54,Multiples!$B:$B,Multiples!O:O),"") -> 1.7535545 | P54: =IFERROR(_xlfn.XLOOKUP($K54,Multiples!$B:$B,Multiples!P:P),"") -> 5.3518164 | Q54: =IFERROR(_xlfn.XLOOKUP($K54,Multiples!$B:$B,Multiples!Q:Q),"") -> 6.3205957 | R54: =IFERROR(_xlfn.XLOOKUP($K54,Multiples!$B:$B,Multiples!R:R),"") -> 8.648319 | AA54: =+AA53+1 -> 51 | AB54: 100.38109
K55: EBITDA / Interest Expense | N55: =IFERROR(_xlfn.XLOOKUP($K55,Multiples!$B:$B,Multiples!N:N),"") -> -1.5663717 | O55: =IFERROR(_xlfn.XLOOKUP($K55,Multiples!$B:$B,Multiples!O:O),"") -> 3.0537125 | P55: =IFERROR(_xlfn.XLOOKUP($K55,Multiples!$B:$B,Multiples!P:P),"") -> 6.7112811 | Q55: =IFERROR(_xlfn.XLOOKUP($K55,Multiples!$B:$B,Multiples!Q:Q),"") -> 8.0398742 | R55: =IFERROR(_xlfn.XLOOKUP($K55,Multiples!$B:$B,Multiples!R:R),"") -> 10.527388 | AA55: =+AA54+1 -> 52 | AB55: 89.345851
K56: (EBITDA - Capex) / Interest Expense | N56: =IFERROR(_xlfn.XLOOKUP($K56,Multiples!$B:$B,Multiples!N:N),"") -> -1.120354 | O56: =IFERROR(_xlfn.XLOOKUP($K56,Multiples!$B:$B,Multiples!O:O),"") -> 3.4060032 | P56: =IFERROR(_xlfn.XLOOKUP($K56,Multiples!$B:$B,Multiples!P:P),"") -> 7.1739962 | Q56: =IFERROR(_xlfn.XLOOKUP($K56,Multiples!$B:$B,Multiples!Q:Q),"") -> 8.6524878 | R56: =IFERROR(_xlfn.XLOOKUP($K56,Multiples!$B:$B,Multiples!R:R),"") -> 11.212076 | AA56: =+AA55+1 -> 53 | AB56: 100.38109
AA59: =+AA56+1 -> 54 | AB59: 95.991539
D60: Debt Schedule | K60: Stock Performance | AA60: =+AA59+1 -> 55 | AB60: 101.96157
AA61: =+AA60+1 -> 56 | AB61: 89.345851
U62: ESG Traffic Light | AA62: =+AA61+1 -> 57 | AB62: 100.38109
U63: LSEG ESG Score | V63: =ESG!C14 -> 78 | AA63: =+AA62+1 -> 58 | AB63: 95.198437
U64: E-Score | V64: =ESG!C15 -> 67 | AA64: =+AA63+1 -> 59 | AB64: 100.38109
U65: S-Score | V65: =ESG!C16 -> 67 | AA65: =+AA64+1 -> 60 | AB65: 84.845899
U66: G-Score | V66: =ESG!C17 -> 90 | AA66: =+AA65+1 -> 61 | AB66: 95.198437
U67: S&P Global ESG Score | V67: =ESG!C18 -> 39 | AA67: =+AA66+1 -> 62 | AB67: 107.93161
U68: Environmental | V68: =ESG!C19 -> 55 | AA68: =+AA67+1 -> 63 | AB68: 84.845899
U69: Social | V69: =ESG!C20 -> 27 | AA69: =+AA68+1 -> 64 | AB69: 89.345851
U70: Governance & Economic | V70: =ESG!C21 -> 42 | AA70: =+AA69+1 -> 65 | AB70: 95.198437
U71: Sustainalytics | V71: =ESG!C22 -> 21.8 | AA71: =+AA70+1 -> 66 | AB71: 107.93161
U72: ISS ESG Corporate Rating | V72: =ESG!C23 -> C+ | AA72: =+AA71+1 -> 67 | AB72: 101.96157
U73: SDG Impact Rating | V73: =ESG!C24 -> -5.5 | AA73: =+AA72+1 -> 68 | AB73: 100.38109
U74: Governance Quality Score | V74: =ESG!C25 -> 9 | AA74: =+AA73+1 -> 69 | AB74: 90.015784
U75: MSCI ESG Ratings | V75: =ESG!C26 -> A | AA75: =+AA74+1 -> 70 | AB75: 93.845803
AA76: =+AA75+1 -> 71 | AB76: 95.198437
U77: Disclaimer: This material has been prepared solely for educational and informational purposes, based on information available to the general public and from sources considered reliable. This research is part of the activities of the Lisbon Investment Society (LIS). It does not constitute, and should not be interpreted as, investment advice, financial advice, or a recommendation to buy or sell any financial instruments. The views expressed are those of the authors and do not necessarily reflect the official position of LIS. The authors assume no responsibility for the accuracy of the information provided, neither should anything contained herein be taken as an indication that any result will be achieved. Investors should conduct their own research and consult with qualified financial advisors before making any investment decisions. | AA77: =+AA76+1 -> 72 | AB77: 84.845899
AA78: =+AA77+1 -> 73 | AB78: 95.991539
AA79: =+AA78+1 -> 74 | AB79: 101.96157
AA80: =+AA79+1 -> 75 | AB80: 89.345851
AA81: =+AA80+1 -> 76 | AB81: 90.015784
D82: Extra Notes | AA82: =+AA81+1 -> 77 | AB82: 84.845899
AA83: =+AA82+1 -> 78 | AB83: 100.38109
AA84: =+AA83+1 -> 79 | AB84: 93.845803
AA85: =+AA84+1 -> 80 | AB85: 95.198437
AA86: =+AA85+1 -> 81 | AB86: 84.845899
AA87: =+AA86+1 -> 82 | AB87: 101.96157
AA88: =+AA87+1 -> 83 | AB88: 101.96157
AA89: =+AA88+1 -> 84 | AB89: 90.015784
AA90: =+AA89+1 -> 85 | AB90: 93.845803
AA91: =+AA90+1 -> 86 | AB91: 95.198437
AA92: =+AA91+1 -> 87 | AB92: 107.93161
AA93: =+AA92+1 -> 88 | AB93: 107.93161
AA94: =+AA93+1 -> 89 | AB94: 107.93161
... AA4999: =+AA4998+1 -> 4994 | AB4999: 89.345851

Sheet Segments
B2: Segments
B4: Regions | D4: Weight | E4: 2020 | F4: =+E4+1 -> 2021 | G4: =+F4+1 -> 2022 | H4: =+G4+1 -> 2023 | I4: =+H4+1 -> 2024 | J4: ="CAGR "&$G$4&" - "&$I$4 -> CAGR 2022 - 2024 | K4: 2021 | L4: =+K4+1 -> 2022 | M4: =+L4+1 -> 2023 | N4: =+M4+1 -> 2024
B6: United States and Canada | D6: =IFERROR(I6/SUM($I$6:$I$12),"") -> 0.50274597 | E6: 6611 | F6: 10094 | G6: 19474 | H6: 20436 | I6: 23618 | J6: =IFERROR((I6/G6)^(1/COUNT($G$4:$I$4))-1,"") -> 0.066422544 | K6: =IFERROR((F6-E6)/E6,"") -> 0.52684919 | L6: =IFERROR((G6-F6)/F6,"") -> 0.92926491 | M6: =IFERROR((H6-G6)/G6,"") -> 0.049399199 | N6: =IFERROR((I6-H6)/H6,"") -> 0.15570562
B7: Europe, Middle East & Africa | D7: =IFERROR(I7/SUM($I$6:$I$12),"") -> 0.26669931 | E7: 2086 | F7: 3213 | G7: 6944 | H7: 9904 | I7: 12529 | J7: =IFERROR((I7/E7)^(1/COUNT($E$4:$I$4))-1,"") -> 0.43126622 | K7: =IFERROR((F7-E7)/E7,"") -> 0.54026846 | L7: =IFERROR((G7-F7)/F7,"") -> 1.16122 | M7: =IFERROR((H7-G7)/G7,"") -> 0.42626728 | N7: =IFERROR((I7-H7)/H7,"") -> 0.26504443
B8: Asia Pacific | D8: =IFERROR(I8/SUM($I$6:$I$12),"") -> 0.17105879 | E8: 1147 | F8: 2731 | G8: 3481 | H8: 4429 | I8: 8036 | J8: =IFERROR((I8/E8)^(1/COUNT($E$4:$I$4))-1,"") -> 0.4760304 | K8: =IFERROR((F8-E8)/E8,"") -> 1.3809939 | L8: =IFERROR((G8-F8)/F8,"") -> 0.27462468 | M8: =IFERROR((H8-G8)/G8,"") -> 0.27233554 | N8: =IFERROR((I8-H8)/H8,"") -> 0.81440506
B9: Latin America | D9: =IFERROR(I9/SUM($I$6:$I$12),"") -> 0.059495934 | E9: 1295 | F9: 1417 | G9: 1978 | H9: 2512 | I9: 2795 | J9: =IFERROR((I9/G9)^(1/COUNT($G$4:$I$4))-1,"") -> 0.1221524 | K9: =IFERROR((F9-E9)/E9,"") -> 0.094208494 | L9: =IFERROR((G9-F9)/F9,"") -> 0.39590685 | M9: =IFERROR((H9-G9)/G9,"") -> 0.26996967 | N9: =IFERROR((I9-H9)/H9,"") -> 0.11265924
D10: =IFERROR(I10/SUM($I$6:$I$12),"") -> 0 | J10: =IFERROR((I10/E10)^(1/COUNT($E$4:$I$4))-1,"") | K10: =IFERROR(F10-E10/E10,"") | L10: =IFERROR(G10-F10/F10,"") | M10: =IFERROR(H10-G10/G10,"") | N10: =IFERROR((I10-H10)/H10,"")
D11: =IFERROR(I11/SUM($I$6:$I$12),"") -> 0
D12: =IFERROR(I12/SUM($I$6:$I$12),"") -> 0
B13: Total | D13: =SUM(D6:D12) -> 1 | E13: =SUM(E6:E10) -> 11139 | F13: =SUM(F6:F10) -> 17455 | G13: =SUM(G6:G10) -> 31877 | H13: =SUM(H6:H10) -> 37281 | I13: =SUM(I6:I10) -> 46978 | J13: =IFERROR((I13/G13)^(1/COUNT($G$4:$I$4))-1,"") -> 0.13799152 | K13: =IFERROR((F13-E13)/E13,"") -> 0.56701679 | L13: =IFERROR((G13-F13)/F13,"") -> 0.8262389 | M13: =IFERROR((H13-G13)/G13,"") -> 0.16952662 | N13: =IFERROR((I13-H13)/H13,"") -> 0.26010568
B15: Segments | D15: Weight | E15: 2020 | F15: =+E15+1 -> 2021 | G15: =+F15+1 -> 2022 | H15: =+G15+1 -> 2023 | I15: =+H15+1 -> 2024 | J15: ="CAGR "&$E$4&" - "&$I$4 -> CAGR 2020 - 2024 | K15: 2021 | L15: =+K15+1 -> 2022 | M15: =+L15+1 -> 2023 | N15: =+M15+1 -> 2024
B17: Mobility | D17: =IFERROR(I17/SUM($I$17:$I$21),"") -> 0.57044431 | E17: 6089 | F17: 6953 | G17: 14029 | H17: 19832 | I17: 25087 | J17: =IFERROR((I17/E17)^(1/COUNT($E$4:$I$4))-1,"") -> 0.32733501 | K17: =IFERROR((F17-E17)/E17,"") -> 0.14189522 | L17: =IFERROR((G17-F17)/F17,"") -> 1.0176902 | M17: =IFERROR((H17-G17)/G17,"") -> 0.41364317 | N17: =IFERROR((I17-H17)/H17,"") -> 0.2649758
B18: Delivery | D18: =IFERROR(I18/SUM($I$17:$I$21),"") -> 0.31265633 | E18: 3904 | F18: 8362 | G18: 10901 | H18: 12204 | I18: 13750 | J18: =IFERROR((I18/E18)^(1/COUNT($E$4:$I$4))-1,"") -> 0.2863483 | K18: =IFERROR((F18-E18)/E18,"") -> 1.1419057 | L18: =IFERROR((G18-F18)/F18,"") -> 0.30363549 | M18: =IFERROR((H18-G18)/G18,"") -> 0.11953032 | N18: =IFERROR((I18-H18)/H18,"") -> 0.12667978
B19: Freight | D19: =IFERROR(I19/SUM($I$17:$I$21),"") -> 0.11689936 | E19: 1011 | F19: 2132 | G19: 6947 | H19: 5245 | I19: 5141 | J19: =IFERROR((I19/E19)^(1/COUNT($E$4:$I$4))-1,"") -> 0.38439267 | K19: =IFERROR((F19-E19)/E19,"") -> 1.1088032 | L19: =IFERROR((G19-F19)/F19,"") -> 2.2584428 | M19: =IFERROR((H19-G19)/G19,"") -> -0.24499784 | N19: =IFERROR((I19-H19)/H19,"") -> -0.019828408
B20: All Other | D20: =IFERROR(I20/SUM($I$17:$I$21),"") -> 0 | E20: 135 | F20: 8 | J20: =IFERROR((I20/E20)^(1/COUNT($E$4:$I$4))-1,"") -> -1 | K20: =IFERROR((F20-E20)/E20,"") -> -0.94074074 | L20: =IFERROR((G20-F20)/F20,"") -> -1 | M20: =IFERROR((H20-G20)/G20,"") | N20: =IFERROR((I20-H20)/H20,"")
D21: =IFERROR(I21/SUM($I$17:$I$21),"") -> 0 | J21: =IFERROR((I21/E21)^(1/COUNT($E$4:$I$4))-1,"") | K21: =IFERROR((F21-E21)/E21,"") | L21: =IFERROR((G21-F21)/F21,"") | M21: =IFERROR((H21-G21)/G21,"") | N21: =IFERROR((I21-H21)/H21,"")
B22: Total | D22: =SUM(D17:D21) -> 1 | E22: =SUM(E17:E21) -> 11139 | F22: =SUM(F17:F21) -> 17455 | G22: =SUM(G17:G21) -> 31877 | H22: =SUM(H17:H21) -> 37281 | I22: =SUM(I17:I21) -> 43978 | J22: =IFERROR((I22/E22)^(1/COUNT($E$4:$I$4))-1,"") -> 0.31606656 | K22: =IFERROR((F22-E22)/E22,"") -> 0.56701679 | L22: =IFERROR((G22-F22)/F22,"") -> 0.8262389 | M22: =IFERROR((H22-G22)/G22,"") -> 0.16952662 | N22: =IFERROR((I22-H22)/H22,"") -> 0.17963574
B24: Categories | D24: Description | J24: Graphs
B26: Mobility | D26: The Mobility segment's offering connects consumers with a wide range of transportation modalities, such as ridesharing, carsharing, micromobility, rentals, public transit, taxis, and more
B27: Delivery | D27: The Delivery segment's offering allows consumers to search for and discover local restaurants, order a meal, and either pick-up at the restaurant or have the meal delivered
B28: Freight | D28: The Freight segment leverages its proprietary technology, brand awareness, and experience revolutionizing industries to connect carriers with shippers on its platform, and gives carriers upfront, transparent pricing and the ability to book a shipment
B29: All Other | C29: All Other
B30: =IF(B21=0,"",B21)
B32: Products | D32: Weight | E32: 2020 | F32: =+E32+1 -> 2021 | G32: =+F32+1 -> 2022 | H32: =+G32+1 -> 2023 | I32: =+H32+1 -> 2024 | J32: =I32+1 -> 2025 | K32: =+J32+1 -> 2026 | L32: =+K32+1 -> 2027 | M32: =+L32+1 -> 2028 | N32: =+M32+1 -> 2029 | O32: =+N32+1 -> 2030 | P32: =+O32+1 -> 2031 | Q32: =+P32+1 -> 2032 | R32: =+Q32+1 -> 2033 | ... T32: =+S32+1 -> 2035
B34: UBER ONE | D34: =IFERROR(I34/$I$13,"") -> 0.056036797 | F34: 0 | G34: =+W52 -> 1052.9987 | H34: =+X52 -> 1667.2479 | I34: =+Y52 -> 2632.4966 | J34: =+I34*(1+DCF!H18) -> 2843.0964 | K34: =+J34*(1+DCF!I18) -> 3070.5441 | L34: =+K34*(1+DCF!J18) -> 3316.1876 | M34: =+L34*(1+DCF!K18) -> 3581.4826 | N34: =+M34*(1+DCF!L18) -> 3868.0012 | O34: =+N34*(1+DCF!M18) -> 4177.4413 | P34: =+O34*(1+DCF!N18) -> 4511.6366 | Q34: =+P34*(1+DCF!O18) -> 4872.5675 | ... S34: =+R34*(1+DCF!Q18) -> 5683.3628 | T34: =+S34*(1+0.08) -> 6138.0318
D36: =IFERROR(I36/$I$13,"") -> 0 | J36: =+J34/I34-1 -> 0.08 | K36: =+K34/J34-1 -> 0.08 | L36: =+L34/K34-1 -> 0.08 | M36: =+M34/L34-1 -> 0.08 | N36: =+N34/M34-1 -> 0.08 | O36: =+O34/N34-1 -> 0.08 | P36: =+P34/O34-1 -> 0.08 | Q36: =+Q34/P34-1 -> 0.08 | ... T36: =+T34/S34-1 -> 0.08
F37: =IFERROR((F36-E36)/E36,"") | G37: =IFERROR((G36-F36)/F36,"") | H37: =IFERROR((H36-G36)/G36,"") | I37: =IFERROR((I36-H36)/H36,"")
B38: Product 3 | D38: =IFERROR(I38/$I$13,"") -> 0 | J38: =I38*(1+J39) -> 0 | K38: =J38*(1+K39) -> 0 | L38: =K38*(1+L39) -> 0 | M38: =L38*(1+M39) -> 0 | N38: =M38*(1+N39) -> 0 | O38: =N38*(1+O39) -> 0 | P38: =O38*(1+P39) -> 0 | Q38: =P38*(1+Q39) -> 0 | ... T38: =S38*(1+T39) -> 0
F39: =IFERROR(F38-E38/E38,"") | G39: =IFERROR(G38-F38/F38,"") | H39: =IFERROR(H38-G38/G38,"") | I39: =IFERROR(I38-H38/H38,"")
B40: Product 4 | D40: =IFERROR(I40/$I$13,"") -> 0 | J40: =I40*(1+J41) -> 0 | K40: =J40*(1+K41) -> 0 | L40: =K40*(1+L41) -> 0 | M40: =L40*(1+M41) -> 0 | N40: =M40*(1+N41) -> 0 | O40: =N40*(1+O41) -> 0 | P40: =O40*(1+P41) -> 0 | Q40: =P40*(1+Q41) -> 0 | ... T40: =S40*(1+T41) -> 0
F41: =IFERROR(F40-E40/E40,"") | G41: =IFERROR(G40-F40/F40,"") | H41: =IFERROR(H40-G40/G40,"") | I41: =IFERROR(I40-H40/H40,"")
B42: Product 5 | D42: =IFERROR(I42/$I$13,"") -> 0 | J42: =I42*(1+J43) -> 0 | K42: =J42*(1+K43) -> 0 | L42: =K42*(1+L43) -> 0 | M42: =L42*(1+M43) -> 0 | N42: =M42*(1+N43) -> 0 | O42: =N42*(1+O43) -> 0 | P42: =O42*(1+P43) -> 0 | Q42: =P42*(1+Q43) -> 0 | ... T42: =S42*(1+T43) -> 0
F43: =IFERROR(F42-E42/E42,"") | G43: =IFERROR(G42-F42/F42,"") | H43: =IFERROR(H42-G42/G42,"") | I43: =IFERROR(I42-H42/H42,"")
B44: Total | D44: =SUM(D34:D42) -> 0.056036797 | E44: =SUM(E34:E42) -> 0 | F44: =SUM(F34:F42) -> 0 | G44: =SUM(G34:G42) -> 1052.9987 | H44: =SUM(H34:H42) -> 1667.2479 | I44: =SUM(I34:I42) -> 2632.4966 | J44: =SUM(J34:J42) -> 2843.1764 | K44: =SUM(K34:K42) -> 3070.6241 | ... T44: =SUM(T34:T42) -> 6138.1118
B46: Company's Strategy / Extra Notes
D49: Suppliers | F49: % Quantity of Supplies Origin | G49: Tarrif (19/4/25) | I49: Ride Option | J49: Description | K49: Price Category / Description | M49: Region | N49: Country | O49: Local Price (Monthly) | P49: Approx USD Price | Q49: Total GDP 2024 (USD Trillions) | R49: GDP % of Total | S49: Weighted Price (USD) | U49: UBER ONE | V49: 2021 | W49: =+V49+1 -> 2022 | X49: =+W49+1 -> 2023 | Y49: =+X49+1 -> 2024
D50: US | F50: 0.4759 | G50: 0 | I50: UberX Share | J50: Share the ride (and cost) with another passenger. | K50: Economy (Cheapest option) | M50: North America | N50: USA | O50: USD 9,99 | P50: 9.99 | Q50: 28.78 | R50: =+Q50/$Q$69 -> 0.46383445 | S50: =+R50*P50 -> 4.6337062 | U50: Users (millions) | V50: 0 | W50: 12 | X50: 19 | Y50: 30
D51: China | F51: 0.1074 | G51: 145% (245%) | I51: UberX Saver | J51: Lower-cost option if you're willing to wait longer. | K51: Economy (Cheaper than UberX) | M51: North America | N51: Canada | O51: CAD 9,99 | P51: 7.21 | Q51: 2.24 | R51: =+Q51/$Q$69 -> 0.036101083 | S51: =+R51*P51 -> 0.26028881 | U51: Growth % | V51: - | W51: - | X51: =+X50/W50-1 -> 0.58333333 | Y51: =+Y50/X50-1 -> 0.57894737
D52: Brazil | F52: 0.062 | G52: 0.1 | I52: UberX | J52: Standard, affordable ride for up to 4 passengers. | K52: Economy (Base price) | M52: North America | N52: Mexico | O52: MXN 70,00 | P52: 3.57 | Q52: 1.99 | R52: =+Q52/$Q$69 -> 0.032071944 | S52: =+R52*P52 -> 0.11449684 | U52: Expected Revenue | V52: 0 | W52: =+W50*$S$69*12 -> 1052.9987 | X52: =+X50*$S$69*12 -> 1667.2479 | Y52: =+Y50*$S$69*12 -> 2632.4966
D53: Canada | F53: 0.0481 | G53: 0.1 | I53: Uber Green | J53: Ride in an electric or hybrid vehicle (up to 4 passengers). | K53: Economy (Often similar to UberX) | M53: Europe | N53: Portugal | O53: EUR 4,99 | P53: 5.69 | Q53: 0.309 | R53: =+Q53/$Q$69 -> 0.0049800155 | S53: =+R53*P53 -> 0.028336288
D54: Mexico | F54: 0.038 | G54: 0.1 | I54: Uber Comfort | J54: Newer car with extra legroom & top-rated driver. | K54: Mid-Tier (More expensive than UberX) | M54: Europe | N54: UK | O54: GBP 4,99 | P54: 6.69 | Q54: 3.58 | R54: =+Q54/$Q$69 -> 0.057697267 | S54: =+R54*P54 -> 0.38599471
D55: France | F55: 0.0269 | G55: 0.1 | I55: UberXL | J55: Larger vehicle (SUV/minivan) for groups up to 6. | K55: Mid-Tier (More expensive than UberX) | M55: Europe | N55: Luxembourg | O55: EUR 9,99 | P55: 11.39 | Q55: 0.094 | R55: =+Q55/$Q$69 -> 0.0015149562 | S55: =+R55*P55 -> 0.017255351
D56: United Kingdom | F56: 0.0241 | G56: 0.1 | I56: Uber Access/WAV | J56: Wheelchair-accessible vehicle with trained driver. | K56: Economy/Mid-Tier (Pricing similar to UberX/XL, availability varies) | M56: Europe | N56: Belgium | O56: EUR 6,99 | P56: 7.97 | Q56: 0.665 | R56: =+Q56/$Q$69 -> 0.010717509 | S56: =+R56*P56 -> 0.085418547
D57: Sweden | F57: 0.0213 | G57: 0.1 | I57: Uber Black | J57: Premium ride in a high-end luxury vehicle. | K57: Premium (Significantly more than UberX) | M57: Europe | N57: France | O57: EUR 5,99 | P57: 6.83 | Q57: 3.16 | R57: =+Q57/$Q$69 -> 0.050928314 | S57: =+R57*P57 -> 0.34784038
D58: India | F58: 0.0176 | G58: 0.1 | I58: Uber Reserve | J58: Pre-book a ride for a specific time (various car types). | K58: Varies (Often includes a reservation fee) | M58: Europe | N58: Germany | O58: EUR 4,99 | P58: 5.69 | Q58: 4.59 | R58: =+Q58/$Q$69 -> 0.073974987 | S58: =+R58*P58 -> 0.42091768
D59: Russia | F59: 0.0028 | G59: 0 | I59: Uber Taxi | J59: Request a ride from a licensed local taxi via the app. | K59: Metered Taxi Fare (May vary) | M59: Europe | N59: Ireland | O59: EUR 5,99 | P59: 6.83 | Q59: 0.56 | R59: =+Q59/$Q$69 -> 0.0090252708 | S59: =+R59*P59 -> 0.061642599
D60: Other | F60: =1-SUM(F50:F58) -> 0.1787 | G60: 0.1 | M60: Europe | N60: Sweden | O60: SEK 49,99 | P60: 5 | Q60: 0.6 | R60: =+Q60/$Q$69 -> 0.009669933 | S60: =+R60*P60 -> 0.048349665
D61: *Disclaimers | M61: Europe | N61: Spain | O61: EUR 4,99 | P61: 5.69 | Q61: 1.7 | R61: =+Q61/$Q$69 -> 0.027398143 | S61: =+R61*P61 -> 0.15589544
D62: Isn't accurate, as the destination of supplies isn't implied, not necessearly to the USA | M62: Asia-Pacific | N62: Japan | O62: JPY 498,00 | P62: 3.49 | Q62: 4.2 | R62: =+Q62/$Q$69 -> 0.067689531 | S62: =+R62*P62 -> 0.23623646
D63: Uber isn't affected the same as others by tarifs since its business model doesn't relly heavilly on external inventories and/or supplies | M63: Asia-Pacific | N63: Australia | O63: AUD 9,99 | P63: 6.41 | Q63: 1.75 | R63: =+Q63/$Q$69 -> 0.028203971 | S63: =+R63*P63 -> 0.18078745
D64: Mostly only third parties involved will be affected | M64: Asia-Pacific | N64: Taiwan | O64: TWD 120,00 | P64: 3.72 | Q64: 0.8 | R64: =+Q64/$Q$69 -> 0.012893244 | S64: =+R64*P64 -> 0.047962867
M65: Asia-Pacific | N65: India | O65: INR 149,00 | P65: 1.74 | Q65: 3.94 | R65: =+Q65/$Q$69 -> 0.063499226 | S65: =+R65*P65 -> 0.11048865
M66: Latin America | N66: Brazil | O66: BRL 19,90 | P66: 3.5 | Q66: 2.33 | R66: =+Q66/$Q$69 -> 0.037551573 | S66: =+R66*P66 -> 0.13143051
M67: Latin America | N67: Colombia | O67: COP 19900,00 | P67: 4.72 | Q67: 0.38 | R67: =+Q67/$Q$69 -> 0.0061242909 | S67: =+R67*P67 -> 0.028906653
M68: Africa | N68: South Africa | O68: ZAR 50,00 | P68: 2.7 | Q68: 0.38 | R68: =+Q68/$Q$69 -> 0.0061242909 | S68: =+R68*P68 -> 0.016535585
M69: Total | P69: =+AVERAGE(P50:P68) -> 5.7278947 | Q69: =+SUM(Q50:Q68) -> 62.048 | S69: =+SUM(S50:S68) -> 7.3124907
D71: 2024 UBER Earnigs Call Highlights
D72: Topic: Autonomous Veichles
D73: Brian Nowak -- Morgan Stanley -- Analyst
D75: As you think about the portfolio of assets you have at the company, how do you think philosophically about investing more in autonomous assets, be it first-party car fleet or other fleet management tools?
D76: Or where are you on sort of the portfolio of the current assets from an autonomous perspective?
D78: Dara Khosrowshahi -- Chief Executive Officer
D79: I think on autonomous, we think we are very, very well-positioned. We're investing aggressively across all parts of the portfolio.
D80: And I think the way that you can think about it is that every new product that we build, we first build by going out and investing in supply and building out kind of liquidity on the supply side.
D83: Michael Morton -- Analyst
D84: When you talk about securing supply from OEMs (Original Equipment Manufacturer), are you speaking about Uber buying cars directly?
D85: And then when you're thinking over the long term about potential business models with AVs, could you talk about an agency model versus a merchant model of renting AVs for the day?
D86: And then a question we get from investors is, how much of your global mobility business do you see being addressable by autonomous vehicles due to different driver costs in certain markets compared to the AV costs?
... D132: “I think the same economic laws apply to them. Ultimately, if Tesla puts their cars on our network, we already have 150,000 drivers who are driving Teslas, and if they get FSD, they’d love to plug it into Uber as well"

Sheet Industry
B2: Industry Overview
B4: Sales Growth Forecast | E4: Weight | F4: 2025 | G4: =+F4+1 -> 2026 | H4: =+G4+1 -> 2027 | I4: =+H4+1 -> 2028 | J4: =+I4+1 -> 2029 | K4: =+J4+1 -> 2030 | L4: =+K4+1 -> 2031 | M4: =+L4+1 -> 2032 | N4: =+M4+1 -> 2033 | ... P4: =+O4+1 -> 2035 | Q4: ="CAGR "&$F$4&" - "&$P$4 -> CAGR 2025 - 2035 | R4: Sources
B6: Mobility | E6: 0.57 | F6: =25087*(1+0.171) -> 29376.877 | G6: =F6*(1+0.171) -> 34400.323 | H6: =G6*(1+0.171) -> 40282.778 | I6: =H6*(1+0.171) -> 47171.133 | J6: =I6*(1+0.171) -> 55237.397 | K6: =J6*(1+0.171) -> 64682.992 | L6: =K6*(1+0.171) -> 75743.784 | M6: =L6*(1+0.171) -> 88695.971 | N6: =M6*(1+0.171) -> 103862.98 | O6: =N6*(1+0.171) -> 121623.55 | Q6: 0.39 | R6: Precedence Research
B7: Delivery | E7: 31.3% | F7: =13750*(1+0.09) -> 14987.5 | G7: =F7*(1+0.09) -> 16336.375 | H7: =G7*(1+0.09) -> 17806.649 | I7: =H7*(1+0.09) -> 19409.247 | J7: =I7*(1+0.09) -> 21156.079 | K7: =J7*(1+0.09) -> 23060.127 | Q7: 0.09 | R7: Grand Review Research
B8: Freight | E8: 17.1% | F8: =5141*(1+0.1131) -> 5722.4471 | G8: =F8*(1+0.1131) -> 6369.6559 | H8: =G8*(1+0.1131) -> 7090.0639 | I8: =H8*(1+0.1131) -> 7891.9502 | J8: =I8*(1+0.1131) -> 8784.5297 | K8: =J8*(1+0.1131) -> 9778.0601 | Q8: 4,99% | R8: Precedence Research
B11: Weighted Average | E11: =SUM(E6:E10) -> 0.57 | F11: =SUMPRODUCT(F6:F10,$E$6:$E$10) -> 16744.82 | G11: =SUMPRODUCT(G6:G10,$E$6:$E$10) -> 19608.184 | H11: =SUMPRODUCT(H6:H10,$E$6:$E$10) -> 22961.184 | I11: =SUMPRODUCT(I6:I10,$E$6:$E$10) -> 26887.546 | J11: =SUMPRODUCT(J6:J10,$E$6:$E$10) -> 31485.316 | K11: =SUMPRODUCT(K6:K10,$E$6:$E$10) -> 36869.305 | L11: =SUMPRODUCT(L6:L10,$E$6:$E$10) -> 43173.957 | M11: =SUMPRODUCT(M6:M10,$E$6:$E$10) -> 50556.703 | ... O11: =SUMPRODUCT(O6:O10,$E$6:$E$10) -> 69325.424
B13: Key Drivers | E13: Description
B15: Platform Expansion and User Growth | E15: Uber's ability to acquire and retain both drivers and riders directly increases the number of transactions on the platform.
B16: Diversification of Services | E16: Investing in other forms of mobility (bikes, scooters), delivery (Uber Eats) and freight services, creates more income streams and reduces dependence on single segments.
B17: Geographic Expansion | E17: The growth in internacional markets and the expansion to different geographic locations increases Uber's total adressable market allowing long-term scalability.
B18: Technology and Operational Efficiency | E18: Investment in arificial intelligence, automation and possible future technologies like autonomous vehicles can lead to changes that could help improving user experience, reduce costs and provide competitive advantages.
B20: Industry Trends | E20: Description
B22: Increasing Customer Demand for Sustainability | E22: Consumers and governments are prioritizing lower carbon emissions and other and eco-friendly practices, calling for corporate responsability. Uber has commited to becoming a zero-emissions platform in key markets by 2040.
B23: Integration of AI in the Industry | E23: Companies from all industries are using artificial intelligence to personalize user experience and improve operational efficiency. Uber relies on AI in many aspects such as route optimization, pricing and matching riders to drivers. As this technology evolves, Uber can make the platform smarter and more efficient.
B26: Market Share | E26: Headquarters | G26: Revenues | H26: (in MM of USD) | I26: Global Market Share | K26: US Market Share
B28: {=+_FV(DCF!R4,"Name")} -> UBER TECHNOLOGIES, INC. | E28: EUA | G28: 43978 | I28: =G28/$G$40 -> 0.26581643
B29: =Peers!B8 -> LYFT INC. | E29: EUA | G29: 5786 | I29: =G29/$G$40 -> 0.034972347
B30: =Peers!B9 -> DOORDASH INC. | E30: EUA | G30: 10722 | I30: =G30/$G$40 -> 0.064807036
B31: =Peers!B10 -> GRAB HOLDINGS LIMITED | E31: SG | G31: 2797 | I31: =G31/$G$40 -> 0.01690592
B32: =Peers!B11 -> DELIVERY HERO SE | E32: GER | G32: 12082 | I32: =G32/$G$40 -> 0.07302729
B33: =Peers!B12 -> DiDi GLOBAL INC. | E33: CN | G33: 28379 | I33: =G33/$G$40 -> 0.17153132
B34: =Peers!B13 -> MEITUAN | E34: CN | G34: 46328 | I34: =G34/$G$40 -> 0.28002055
B35: =Peers!B14 -> DELIVEROO PLC | E35: UK | G35: 2760 | I35: =G35/$G$40 -> 0.016682281
B36: =Peers!B15 -> JUST EAT TAKEAWAY | E36: NLD | G36: 3564 | I36: =G36/$G$40 -> 0.021541902
B37: =Peers!B16 -> HERTZ GLOBAL HOLDINGS INC. | E37: EUA | G37: 9049 | I37: =G37/$G$40 -> 0.054694914
B38: Others | I38: =G38/$G$40 -> 0
E39: -- | G39: =G40-SUM(G28:G38) -> 0 | I39: =G39/$G$40 -> 0
B40: Industry Size | E40: -- | G40: =SUM(G28:G37) -> 165445 | I40: 1
B42: Porter's Five Forces Analysis | E42: Rating | H42: Graph
B44: Threat of New Entrants | E44: =IFERROR(AVERAGE(E45:E50),"") -> 4.1666667
B45: Economies of scale | E45: 5
B46: Product differentiation | E46: 3
B47: Capital requirements | E47: 5
B48: Access to distribution channels | E48: 5
B49: Regulations | E49: 5
B50: Switching costs | E50: 2
B51: Bargaining Power of Suppliers | E51: =IFERROR(AVERAGE(E52:E56),"") -> 3.2
B52: Number of suppliers | E52: 4
B53: Uniqueness | E53: 3
B54: Switching Costs | E54: 2
B55: Forward Integration | E55: 3
B56: Industry Importance | E56: 4
B57: Bargaining Power of Customers | E57: =IFERROR(AVERAGE(E58:E62),"") -> 3.2
B58: Number of buyers | E58: 5
B59: Purchase size | E59: 1
B60: Switching costs | E60: 1
B61: Price sensitivity | E61: 4
B62: Informed buyers | E62: 5
B63: Competitive Rivalry | E63: =IFERROR(AVERAGE(E64:E68),"") -> 3.8
B64: Number of competitors | E64: 5
B65: Industry growth | E65: 3
B66: Similarities in what's offered | E66: 5
B67: Exit barriers | E67: 3
B68: Fixed costs | E68: 3
B69: Threat of Substitutes | E69: =IFERROR(AVERAGE(E70:E74),"") -> 4.75
B70: Relative price performance | E70: 4
B71: Customer willingness to go elsewhere | E71: 5
B72: The sense that products are similar | E72: 5
B73: Availability of close substitutes | E73: 5

Sheet Peers
D3: Revenue Growth | F3: EBITDA Margin | H3: Profit Margin | J3: EV / Revenue | L3: EV / EBITDA | N3: Price / Earnings
B4: Peers | C4: Ticker | D4: =+Inputs!O4&"-"&Inputs!P4 -> 2022-2023 | E4: =+Inputs!P4&"-"&Inputs!Q4 -> 2023-2024 | F4: 2023 | G4: 2024 | H4: =+Inputs!O4&"-"&Inputs!P4 -> 2022-2023 | I4: =+Inputs!P4&"-"&Inputs!Q4 -> 2023-2024 | J4: 2023 | K4: 2024 | L4: 2023 | M4: 2024 | N4: 2023 | O4: 2024
A6: =+D91 -> #VALUE! | B6: {=IFERROR(_FV(A6,"Name"),"")} -> UBER TECHNOLOGIES, INC. | C6: {=IFERROR(_FV(A6,"Ticker symbol",TRUE),"")} -> UBER | D6: =IFERROR(D94/D93-1,"") -> 0.16952662 | E6: =IFERROR(D97/D94-1,"") -> 0.17963574 | F6: =IFERROR(D95/D94,"") -> 0.051849468 | G6: =IFERROR(D100/D97,"") -> 0.079812634 | H6: =IFERROR(D96/D94,"") -> 0.056543548 | I6: =IFERROR(D105/D97,"") -> 0.224726 | J6: {=IFERROR((_FV(A6,"Market cap",TRUE)/1000000+D$121-D$111)/D$94,"")} -> 5.3522743 | K6: {=IFERROR((_FV(A6,"Market cap",TRUE)/1000000+D$121-D$111)/D$97,"")} -> 4.5372263 | L6: {=+IFERROR((_FV(A6,"Market cap",TRUE)/1000000+D$121-D$111)/D$95,"")} -> 103.22718 | M6: {=IFERROR((_FV(A6,"Market cap",TRUE)/1000000+D$121-D$111)/D$100,"")} -> 56.848472 | N6: {=IFERROR((_FV(A6,"Market cap",TRUE)/1000000)/D$96,"")} -> 93.349211 | O6: {=IFERROR((_FV(A6,"Market cap",TRUE)/1000000)/D$105,"")} -> 19.910972
A8: =+E91 -> #VALUE! | B8: {=IFERROR(_FV(A8,"Name"),"LYFT INC.")} -> LYFT INC. | C8: {=+IFERROR(_FV(A8,"Ticker symbol",TRUE),"LYFT")} -> LYFT | D8: =+IFERROR(E94/E93-1,"") -> 0.075457875 | E8: =IFERROR(E97/E94-1,"") -> 0.31380563 | F8: =IFERROR(E95/E94,"") -> -0.057674841 | G8: =+IFERROR(E100/E97,"") -> 0.012616661 | H8: =IFERROR(E96/E94,"") -> -0.077202543 | I8: =+IFERROR(E105/E97,"") -> 0.0039751123 | J8: {=(_FV(A8,"Capitalização de mercado",TRUE)/1000000+$E$121-$E$111)/$E$94} -> 1.7266301 | K8: {=(_FV(A8,"Capitalização de mercado",TRUE)/1000000+$E$121-$E$111)/$E$97} -> 1.3142204 | L8: {=(_FV(A8,"Capitalização de mercado",TRUE)/1000000+$E$121-E$111)/E$95} -> -29.937319 | M8: {=(_FV(A8,"Capitalização de mercado",TRUE)/1000000+E$121-E$111)/E$100} -> 104.16547 | N8: {=(_FV(A8,"Capitalização de mercado",TRUE)/1000000)/E$96} -> -21.17082 | O8: {=(_FV(A8,"Capitalização de mercado",TRUE)/1000000)/E$105} -> 312.95995
A9: =+F91 -> #VALUE! | B9: {=IFERROR(_FV(A9,"Name"),"DOORDASH INC.")} -> DOORDASH INC. | C9: {=+IFERROR(_FV(A9,"Ticker symbol",TRUE),"DASH")} -> DASH | D9: =IFERROR(F94/F93-1,"") -> 0.31171199 | E9: =IFERROR(+F97/F94-1,"") -> 0.24169079 | F9: =IFERROR(F95/F94,"") -> 0.02327736 | G9: =IFERROR(F100/F97,"") -> 0.083379966 | H9: =IFERROR(F96/F94,"") -> -0.06462073 | I9: =+IFERROR(F105/F97,"") -> 0.01147174 | J9: {=(_FV($A$9,"Capitalização de mercado",TRUE)/1000000+$F$121-$F$111)/$F$94} -> 11.994443 | K9: {=(_FV($A$9,"Capitalização de mercado",TRUE)/1000000+$F$121-$F$111)/$F$94} -> 11.994443 | L9: {=(_FV(A9,"Capitalização de mercado",TRUE)/1000000+F$121-F$111)/F$95} -> 515.28367 | M9: {=(_FV(A9,"Capitalização de mercado",TRUE)/1000000+F$121-F$111)/F$100} -> 115.85237 | N9: {=(_FV(A9,"Capitalização de mercado",TRUE)/1000000)/F$96} -> -191.85487 | O9: {=(_FV(A9,"Capitalização de mercado",TRUE)/1000000)/F$105} -> 870.36599
A10: =+G91 -> #VALUE! | B10: {=IFERROR(_FV(A10,"Name"),"GRAB HOLDINGS LIMITED")} -> GRAB HOLDINGS LIMITED | C10: {=IFERROR(_FV(A10,"Ticker symbol",TRUE),"GRAB")} -> GRAB | D10: =+IFERROR(G94/G93-1,"") -> 0.64619679 | E10: =IFERROR(G97/G94-1,"") -> 0.18567189 | F10: =IFERROR(G95/G94,"") -> -0.14963968 | G10: =IFERROR(G100/G97,"") -> -0.030747229 | H10: =IFERROR(G96/G94,"") -> -0.18397626 | I10: =+IFERROR(G105/G97,"") -> -0.037540222 | J10: {=(_FV(A10,"Capitalização de mercado",TRUE)/1000000+$G$121-$G$111)/$G$94} -> 7.8653836 | K10: {=(_FV(A10,"Capitalização de mercado",TRUE)/1000000+$G$121-$G$111)/$G$97} -> 6.6336932 | L10: {=(_FV(A10,"Capitalização de mercado",TRUE)/1000000+G$121-G$111)/G$95} -> -52.562153 | M10: {=(_FV(A10,"Capitalização de mercado",TRUE)/1000000+G$121-G$111)/G$100} -> -215.7493 | N10: {=(_FV(A10,"Capitalização de mercado",TRUE)/1000000)/G$96} -> -48.742949 | O10: {=(_FV(A10,"Capitalização de mercado",TRUE)/1000000)/G$105} -> -201.47086
A11: =+H91 -> #VALUE! | B11: {=IFERROR(_FV(A11,"Name"),"DELIVERY HERO SE")} -> DELIVERY HERO SE | C11: DHER | D11: =IFERROR(H94/H93-1,"") -> 0.15914655 | E11: =IFERROR(H97/H94-1,"") -> 0.21524844 | F11: =IFERROR(H95/H94,"") -> -0.015590424 | G11: =IFERROR(H100/H97,"") -> 0.060503228 | H11: =IFERROR(H96/H94,"") -> -0.23114062 | I11: =+IFERROR(H105/H97,"") -> -0.069442145 | J11: {=(_FV(A11,"Capitalização de mercado",TRUE)/1000000+$H$121-$H$111)/$H$94} -> 1.1943149 | K11: {=(_FV(A11,"Capitalização de mercado",TRUE)/1000000+$H$121-$H$111)/$H$97} -> 0.98277429 | L11: {=(_FV(A11,"Capitalização de mercado",TRUE)/1000000+H$121-H$111)/H$95} -> -76.605671 | M11: {=(_FV(A11,"Capitalização de mercado",TRUE)/1000000+H$121-H$111)/H$100} -> 16.243337 | N11: {=(_FV(A11,"Capitalização de mercado",TRUE)/1000000)/H$96} -> -3.4681806 | O11: {=(_FV(A11,"Capitalização de mercado",TRUE)/1000000)/H$105} -> -9.4992598
A12: =+I91 -> #VALUE! | B12: {=IFERROR(_FV(A12,"Name"),"DiDi GLOBAL INC.")} -> DiDi GLOBAL INC. | C12: {=IFERROR(_FV(A12,"Ticker symbol",TRUE),"DIDIY")} -> DIDIY | D12: =+IFERROR(I94/I93-1,"") -> 0.29763565 | E12: =IFERROR(I97/I94-1,"") -> 0.0572821 | F12: =IFERROR(I95/I94,"") -> 0.024050973 | G12: =IFERROR(I100/I97,"") -> 0.0045955402 | H12: =IFERROR(I96/I94,"") -> -0.024915984 | I12: =+IFERROR(I105/I97,"") -> 0.0060856093 | J12: {=(_FV(A12,"Capitalização de mercado",TRUE)/1000000+$I$121-$I$111)/$I$94} -> 0.86837312 | K12: {=(_FV(A12,"Capitalização de mercado",TRUE)/1000000+$I$121-$I$111)/$I$97} -> 0.82132585 | L12: {=(_FV(A12,"Capitalização de mercado",TRUE)/1000000+I$121-I$111)/I$95} -> 36.10553 | M12: {=(_FV(A12,"Capitalização de mercado",TRUE)/1000000+I$121-I$111)/I$100} -> 178.72237 | N12: {=(_FV(A12,"Capitalização de mercado",TRUE)/1000000)/I$96} -> -44.713182 | O12: {=(_FV(A12,"Capitalização de mercado",TRUE)/1000000)/I$105} -> 173.14847
A13: =+J91 -> #VALUE! | B13: {=IFERROR(_FV(A13,"Name"),"MEITUAN")} -> MEITUAN | C13: {=IFERROR(_FV(A13,"Ticker symbol",TRUE),"3690")} -> 3690 | D13: =IFERROR(J94/J93-1,"") -> 0.19481607 | E13: =IFERROR(J97/J94-1,"") -> 0.19981833 | F13: =IFERROR(J95/J94,"") -> 0.080993322 | G13: =IFERROR(J100/J97,"") -> 0.14769216 | H13: =IFERROR(J96/J94,"") -> 0.050067808 | I13: =+IFERROR(J105/J97,"") -> 0.10606717 | J13: {=(_FV(A13,"Capitalização de mercado",TRUE)/1000000+$J$121-$J$111)/$J$94} -> 15.575584 | K13: {=(_FV(A13,"Capitalização de mercado",TRUE)/1000000+$J$121-$J$111)/$J$97} -> 12.981619 | L13: {=(_FV(A13,"Capitalização de mercado",TRUE)/1000000+J$121-J$111)/J$95} -> 192.30702 | M13: {=(_FV(A13,"Capitalização de mercado",TRUE)/1000000+J$121-J$111)/J$100} -> 87.896467 | N13: {=(_FV(A13,"Capitalização de mercado",TRUE)/1000000)/J$96} -> 318.56268 | O13: {=(_FV(A13,"Capitalização de mercado",TRUE)/1000000)/J$105} -> 125.33057
A14: =+K91 -> #VALUE! | B14: {=IFERROR(_FV(A14,"Name"),"DELIVEROO PLC")} -> DELIVEROO PLC | C14: ROO | D14: =IFERROR(K94/K93-1,"") -> 0.027848101 | E14: =IFERROR(K97/K94-1,"") -> 0.020689655 | F14: =+IFERROR(K95/K94,"") -> 0.0098522167 | G14: =IFERROR(K100/K97,"") -> 0.042471042 | H14: =IFERROR(K96/K94,"") -> 0.0014778325 | I14: =+IFERROR(K105/K97,"") -> 0.0014478764 | J14: {=(_FV(A14,"Capitalização de mercado",TRUE)/1000000+$K$121-$K$111)/$K$94} -> 1.1179236 | K14: {=(_FV(A14,"Capitalização de mercado",TRUE)/1000000+$K$121-$K$111)/$K$97} -> 1.095263 | L14: {=(_FV(A14,"Capitalização de mercado",TRUE)/1000000+D$121-K$111)/K$95} -> 543.51925 | M14: {=(_FV(A14,"Capitalização de mercado",TRUE)/1000000+D$121-K$111)/K$100} -> 123.5271 | N14: {=(_FV(A14,"Capitalização de mercado",TRUE)/1000000)/K$96} -> 893.46167 | O14: {=(_FV(A14,"Capitalização de mercado",TRUE)/1000000)/K$105} -> 893.46167
A15: =+L91 -> #VALUE! | B15: {=IFERROR(_FV(A15,"Name"),"JUST EAT TAKEAWAY")} -> JUST EAT TAKEAWAY | C15: {=IFERROR(_FV(A15,"Ticker symbol",TRUE),"TKWY")} -> TKWY | D15: =+IFERROR(L94/L93-1,"") -> -0.36450279 | E15: =IFERROR(L97/L94-1,"") -> 0.0084889643 | F15: =IFERROR(L95/L94,"") -> 0.11544992 | G15: =IFERROR(L100/L97,"") -> 0.10549944 | H15: =IFERROR(L96/L94,"") -> -0.52235427 | I15: =+IFERROR(L105/L97,"") -> -0.46156004 | J15: {=(_FV(A15,"Capitalização de mercado",TRUE)/1000000+$L$121-$L$111)/$L$94} -> 1.3060291 | K15: {=(_FV(A15,"Capitalização de mercado",TRUE)/1000000+$L$121-$L$111)/$L$97} -> 1.2950356 | L15: {=(_FV(A15,"Capitalização de mercado",TRUE)/1000000+L$121-L$111)/L$95} -> 11.312517 | M15: {=(_FV(A15,"Capitalização de mercado",TRUE)/1000000+L$121-L$111)/L$100} -> 12.275285 | N15: {=(_FV(A15,"Capitalização de mercado",TRUE)/1000000)/L$96} -> -2.2911739 | O15: {=(_FV(A15,"Capitalização de mercado",TRUE)/1000000)/L$105} -> -2.5711289
A16: =+M91 -> #VALUE! | B16: {=IFERROR(_FV(A16,"Name"),"HERTZ GLOBAL HOLDINGS INC.")} -> HERTZ GLOBAL HOLDINGS INC. | C16: {=IFERROR(_FV(A16,"Ticker symbol",TRUE),"HTZ")} -> HTZ | D16: =IFERROR(M94/M93-1,"") -> 0.078986759 | E16: =IFERROR(M97/M94-1,"") -> -0.034361327 | F16: =IFERROR(M95/M94,"") -> 0.42044606 | G16: =IFERROR(M100/M97,"") -> 0.40137032 | H16: =IFERROR(M96/M94,"") -> 0.065734713 | I16: =+IFERROR(M105/M97,"") -> -0.31627804 | J16: {=(_FV(A16,"Capitalização de mercado",TRUE)/1000000+$M$121-$M$111)/$M$94} -> 2.0995093 | K16: {=(_FV(A16,"Capitalização de mercado",TRUE)/1000000+$M$121-$M$111)/$M$97} -> 2.1742183 | L16: {=(_FV(A16,"Capitalização de mercado",TRUE)/1000000+M$121-M$111)/M$95} -> 4.9935283 | M16: {=(_FV(A16,"Capitalização de mercado",TRUE)/1000000+M$121-M$111)/M$100} -> 5.4169883 | N16: {=(_FV(A16,"Capitalização de mercado",TRUE)/1000000)/M$96} -> 3.0170479 | O16: {=(_FV(A16,"Capitalização de mercado",TRUE)/1000000)/M$105} -> -0.64937158
A17: =+N91 -> 0 | C17: {=+IFERROR(_FV(A17,"Ticker symbol",TRUE),"")} | D17: =IFERROR(N94/N93-1,"") | E17: =IFERROR(N97/N94-1,"") | F17: =IFERROR(N95/N94,"") | G17: =IFERROR(N100/N97,"") | H17: =IFERROR(N96/N94,"") | I17: =+IFERROR(N105/N97,"") | J17: {=IFERROR(+(_FV(A17,"Market cap",TRUE)/1000000+N$121-N$111)/N$94,"")} | K17: {=IFERROR(+(_FV(A17,"Market cap",TRUE)/1000000+N$121-N$111)/N$97,"")} | L17: {=IFERROR(+(_FV(A17,"Market cap",TRUE)/1000000+N$121-N$111)/N$95,"")} | M17: {=IFERROR(+(_FV(A17,"Market cap",TRUE)/1000000+N$121-N$111)/N$100,"")} | N17: {=IFERROR(+(_FV(A17,"Market cap",TRUE)/1000000)/N$96,"")} | O17: {=IFERROR(+(_FV(A17,"Market cap",TRUE)/1000000)/N$105,"")}
B18: Average | D18: =IFERROR(AVERAGE(D6:D17),"") -> 0.15968236 | E18: =IFERROR(AVERAGE(E6:E17),"") -> 0.13879702 | F18: =IFERROR(AVERAGE(F6:F17),"") -> 0.050301437 | G18: =IFERROR(AVERAGE(G6:G17),"") -> 0.090719376 | H18: =IFERROR(AVERAGE(H6:H17),"") -> -0.09303865 | I18: =IFERROR(AVERAGE(I6:I17),"") -> -0.053104695 | J18: =IFERROR(AVERAGE(J6:J17),"") -> 4.9100465 | K18: =IFERROR(AVERAGE(K6:K17),"") -> 4.3829819 | ... O18: =IFERROR(AVERAGE(O6:O17),"") -> 218.0987
B19: Deviation from Average | D19: =IFERROR(+D18-D6,"") -> -0.0098442558 | E19: =IFERROR(E18-E6,"") -> -0.040838718 | F19: =+IFERROR(F18-F6,"") -> -0.0015480308 | G19: =IFERROR(G18-G6,"") -> 0.010906742 | H19: =IFERROR(+H6-H18,"") -> 0.1495822 | I19: =+IFERROR(I6-I18,"") -> 0.27783069 | J19: =+IFERROR(J6-J18,"") -> 0.44222773 | K19: =+IFERROR(K6-K18,"") -> 0.15424438 | L19: =IFERROR(+L6-L18,"") -> -21.537175 | M19: =IFERROR(M6-M18,"") -> 8.3286168 | N19: =IFERROR(+N6-N18,"") -> -6.2657322 | O19: =IFERROR(+O6-O18,"") -> -198.18773
D21: Trading Multiple | G21: Net | H21: Preferred | I21: Non-Controlling | J21: Equity Value | M21: Implied Upside (Downside)
B22: Implied Share Price | D22: Revenue | E22: EBITDA | F22: P/E | G22: Debt | H22: Stock | I22: Interest | J22: Revenue | K22: EBITDA | L22: P/E | M22: Revenue | N22: EBITDA | O22: P/E | P22: Current Price
B24: Second Minimum | D24: =IFERROR(SMALL(K6:K17,2),"") -> 0.98277429 | E24: =IFERROR(SMALL(M6:M17,2),"") -> 5.4169883 | F24: =IFERROR(SMALL(O6:O17,2),"") -> -9.4992598 | G24: =-Inputs!$Q$100+Inputs!$Q$101 -> 1674 | H24: =+Inputs!$Q$102 -> 0 | I24: =+Inputs!$Q$103 -> 918 | J24: =IFERROR(+D24*$D$97+G24+H24+I24,"") -> 45812.448 | K24: =IFERROR(E24*$D$100+G24+H24+I24,"") -> 21605.629 | L24: =IFERROR(F24*$D$105,"") -> -93881.185 | M24: {=IFERROR(+(J24/_FV($A$6,"Shares outstanding",TRUE)*1000000)/$P$24-1,"")} -> -0.76718967 | N24: {=IFERROR((+K24/_FV($A$6,"Shares outstanding",TRUE)*1000000)/$P$24-1,"")} -> -0.89020422 | O24: {=IFERROR(+(L24/_FV($A$6,"Shares outstanding",TRUE)*1000000)/$P$24-1,"")} -> -1.4770867 | P24: {=+_FV(A6,"Price")} -> 94.36
B25: Average | D25: =+IFERROR(AVERAGE(K6:K17),"") -> 4.3829819 | E25: =IFERROR(+AVERAGE(M6:M17),"") -> 48.519855 | F25: =IFERROR(+AVERAGE(O6:O17),"") -> 218.0987 | G25: =-Inputs!$Q$100+Inputs!$Q$101 -> 1674 | H25: =+Inputs!$Q$102 -> 0 | I25: =+Inputs!$Q$103 -> 918 | J25: =IFERROR(+D25*$D$97+G25+H25+I25,"") -> 195346.78 | K25: =IFERROR(E25*$D$100+G25+H25+I25,"") -> 172896.69 | L25: =IFERROR(+F25*$D$105,"") -> 2155469.5 | M25: {=IFERROR(+(J25/_FV($A$6,"Shares outstanding",TRUE)*1000000)/$P$24-1,"")} -> -0.0072840653 | N25: {=IFERROR((+K25/_FV($A$6,"Shares outstanding",TRUE)*1000000)/$P$24-1,"")} -> -0.12137122 | O25: {=IFERROR(+(L25/_FV($A$6,"Shares outstanding",TRUE)*1000000)/$P$24-1,"")} -> 9.9536943
B26: Median | D26: =IFERROR(MEDIAN(K6:K17),"") -> 1.7442193 | E26: =IFERROR(MEDIAN(M6:M17),"") -> 72.372469 | F26: =IFERROR(MEDIAN(O6:O17),"") -> 72.620772 | G26: =-Inputs!$Q$100+Inputs!$Q$101 -> 1674 | H26: =+Inputs!$Q$102 -> 0 | I26: =+Inputs!$Q$103 -> 918 | J26: =IFERROR(D26*$D$97+G26+H26+I26,"") -> 79299.278 | K26: =IFERROR(E26*$D$100+G26+H26+I26,"") -> 256619.37 | L26: =IFERROR(+F26*$D$105,"") -> 717711.09 | M26: {=IFERROR(+(J26/_FV($A$6,"Shares outstanding",TRUE)*1000000)/$P$24-1,"")} -> -0.59701584 | N26: {=IFERROR((+K26/_FV($A$6,"Shares outstanding",TRUE)*1000000)/$P$24-1,"")} -> 0.30409182 | O26: {=+IFERROR((L26/_FV($A$6,"Shares outstanding",TRUE)*1000000)/$P$24-1,"")} -> 2.6472741
B27: Second Maximum | D27: =IFERROR(LARGE(K6:K17,2),"") -> 11.994443 | E27: =IFERROR(LARGE(M6:M17,2),"") -> 123.5271 | F27: =IFERROR(LARGE(O6:O17,2),"") -> 870.36599 | G27: =-Inputs!$Q$100+Inputs!$Q$101 -> 1674 | H27: =+Inputs!$Q$102 -> 0 | I27: =+Inputs!$Q$103 -> 918 | J27: =IFERROR(+D27*$D$97+G27+H27+I27,"") -> 530083.62 | K27: =IFERROR(E27*$D$100+G27+H27+I27,"") -> 436172.13 | L27: =IFERROR(+F27*$D$105,"") -> 8601827.1 | M27: {=IFERROR(+(J27/_FV($A$6,"Shares outstanding",TRUE)*1000000)/$P$24-1,"")} -> 1.6937862 | N27: {=IFERROR((+K27/_FV($A$6,"Shares outstanding",TRUE)*1000000)/$P$24-1,"")} -> 1.2165455 | O27: {=IFERROR(+(L27/_FV($A$6,"Shares outstanding",TRUE)*1000000)/$P$24-1,"")} -> 42.712883
B29: Profitability | D29: =+LEFT(B6, FIND(" ", B6 & " ") - 1) -> UBER | E29: =+LEFT(B8, FIND(" ", B8 & " ") - 1) -> LYFT | F29: =+LEFT(B9, FIND(" ", B9 & " ") - 1) -> DOORDASH | G29: =+LEFT(B10, FIND(" ", B10 & " ") - 1) -> GRAB | H29: DELIVERY HERO | I29: =+LEFT(B12, FIND(" ", B12 & " ") - 1) -> DiDi | J29: =+LEFT(C12, FIND(" ", C12 & " ") - 1) -> DIDIY | K29: =+LEFT(B14, FIND(" ", B14 & " ") - 1) -> DELIVEROO | L29: JUST EAT TAKEAWAY | M29: =+LEFT(B16, FIND(" ", B16 & " ") - 1) -> HERTZ | N29: =+LEFT(B17, FIND(" ", B17 & " ") - 1) | O29: Average
B31: Operating Margin | D31: =IFERROR(D101/D97,"") -> 0.063645459 | E31: =IFERROR(E101/E97,"") -> -0.019702731 | F31: =IFERROR(F101/F97,"") -> 0.021637754 | G31: =IFERROR(G101/G97,"") -> -0.08330354 | H31: =IFERROR(H101/H97,"") -> 0.015808641 | I31: =IFERROR(I101/I97,"") -> -0.010642853 | J31: =IFERROR(J101/J97,"") -> 0.12274659 | K31: =IFERROR(K101/K97,"") -> 0.0014478764 | ... N31: =IFERROR(N101/N97,"") | O31: =IFERROR(+AVERAGE(D31:N31),"") -> -0.0054630033
B32: Net Income Margin | D32: =IFERROR(D105/D97,"") -> 0.224726 | E32: =IFERROR(E105/E97,"") -> 0.0039751123 | F32: =IFERROR(F105/F97,"") -> 0.01147174 | G32: =IFERROR(G105/G97,"") -> -0.037540222 | H32: =IFERROR(H105/H97,"") -> -0.069442145 | I32: =IFERROR(I105/I97,"") -> 0.0060856093 | J32: =IFERROR(J105/J97,"") -> 0.10606717 | K32: =IFERROR(K105/K97,"") -> 0.0014478764 | ... N32: =IFERROR(N105/N97,"") | O32: =IFERROR(+AVERAGE(D32:N32),"") -> -0.053104695
B33: ROA (%) | D33: =IFERROR(D105/D117,"") -> 0.1928616 | E33: =IFERROR(E105/E117,"") -> 0.0042318307 | F33: =IFERROR(F105/F117,"") -> 0.0095757104 | G33: =IFERROR(G105/G117,"") -> -0.011296396 | H33: =IFERROR(H105/H117,"") -> -0.079996186 | I33: =IFERROR(I105/I117,"") -> 0.008867245 | J33: =IFERROR(J105/J117,"") -> 0.11192552 | K33: =IFERROR(K105/K117,"") -> 0.0031678986 | ... N33: =IFERROR(N105/N117,"") | O33: =IFERROR(+AVERAGE(D33:N33),"") -> -0.0094321946
B34: Financial Cost of Debt | D34: =IFERROR(+(D102/D121)*(1-(D104/D103)),"") -> -0.054835742 | E34: =IFERROR(+(E102/E121)*(1-(E104/E103)),"") -> -0.10348498 | F34: =IFERROR(+(F102/F121)*(1-(F104/F103)),"") -> -0.27845149 | G34: =IFERROR(+(G102/G121)*(1-(G104/G103)),"") -> -0.3335454 | H34: =IFERROR(+(H102/H121)*(1-(H104/H103)),"") | I34: =IFERROR(+(I102/I121)*(1-(I104/I103)),"") -> -3.2136468 | J34: =IFERROR(+(J102/J121)*(1-(J104/J103)),"") -> 0.00070477272 | K34: =IFERROR(+(K102/K121)*(1-(K104/K103)),"") -> 0 | ... N34: =IFERROR(+(N102/N121)*(1-(N104/N103)),"") | O34: =IFERROR(+AVERAGE(D34:N34),"") -> -0.45077974
B35: Return on Equity (RoE) | D35: =IFERROR(+D105/D122,"") -> 0.43971347 | E35: =IFERROR(+E105/E122,"") -> 0.029986962 | F35: =IFERROR(+F105/F122,"") -> 0.01574904 | G35: =IFERROR(+G105/G122,"") -> -0.016532829 | H35: =IFERROR(+H105/H122,"") -> -0.50879321 | I35: =IFERROR(+I105/I122,"") -> 0.012927082 | J35: =IFERROR(+J105/J122,"") -> 0.21032889 | K35: =IFERROR(+K105/K122,"") -> 0.006833713 | ... N35: =IFERROR(+N105/N122,"") | O35: =IFERROR(+AVERAGE(D35:N35),"") -> -1.8885998
B36: Return on Invested Capital (ROIC) | D36: =IFERROR(+D105/(D121+D122),"") -> 0.3175057 | E36: =IFERROR(+E105/(E121+E122),"") -> 0.011904762 | F36: =IFERROR(+F105/(F121+F122),"") -> 0.014737599 | G36: =IFERROR(+G105/(G121+G122),"") -> -0.015636634 | H36: =IFERROR(+H105/(H121+H122),"") -> -0.11633389 | I36: =IFERROR(+I105/(I121+I122),"") -> 0.012742475 | J36: =IFERROR(+J105/(J121+J122),"") -> 0.15506813 | K36: =IFERROR(+K105/(K121+K122),"") -> 0.0061349693 | ... N36: =IFERROR(+N105/(N121+N122),"") | O36: =IFERROR(+AVERAGE(D36:N36),"") -> -0.0042009552
B38: Solvency | D38: =+D29 -> UBER | E38: =+E29 -> LYFT | F38: =+F29 -> DOORDASH | G38: =+G29 -> GRAB | H38: =+H29 -> DELIVERY HERO | I38: =+I29 -> DiDi | J38: =+J29 -> DIDIY | K38: =+K29 -> DELIVEROO | ... O38: =+O29 -> Average
B40: Debt/Assets | D40: =IFERROR(D121/D117,"") -> 0.16881976 | E40: =IFERROR(E121/E117,"") -> 0.21435143 | F40: =IFERROR(F121/F117,"") -> 0.041728299 | G40: =IFERROR(G121/G117,"") -> 0.039160839 | H40: =IFERROR(H121/H117,"") -> 0.53041571 | I40: =IFERROR(I121/I117,"") -> 0.0099376046 | J40: =IFERROR(J121/J117,"") -> 0.18963763 | K40: =IFERROR(K121/K117,"") -> 0.05279831 | ... N40: =IFERROR(N121/N117,"") | O40: =IFERROR(+AVERAGE(D40:N40),"") -> 0.2283474
B41: Net Debt/EBITDA | D41: =IFERROR(+(D121-D111)/D100,"") -> 0.78575499 | E41: =IFERROR(+(E121-E111)/E100,"") -> 5.5616438 | F41: =IFERROR(+(F121-F111)/F100,"") -> -3.8959732 | G41: =IFERROR(+(G121-G111)/G100,"") -> 30.232558 | H41: =IFERROR(+(H121-H111)/H100,"") -> 5.3406293 | I41: =IFERROR(+(I121-I111)/I100,"") -> -50.568182 | J41: =IFERROR(+(J121-J111)/J100,"") -> -2.1114176 | K41: =IFERROR(+(K121-K111)/K100,"") -> -4.6704545 | ... N41: =IFERROR(+(N121-N111)/N100,"") | O41: =IFERROR(+AVERAGE(D41:N41),"") -> -1.3393559
B42: Interest Coverage Ratio | D42: =IFERROR(D101/D102,"") -> -14.136364 | E42: =IFERROR(E101/E102,"") -> 0.83211679 | F42: =IFERROR(F101/F102,"") -> -1.1658291 | G42: =IFERROR(G101/G102,"") -> 3.1917808 | H42: =IFERROR(H101/H102,"") | I42: =IFERROR(I101/I102,"") -> 0.49338283 | J42: =IFERROR(J101/J102,"") -> 913.5873 | K42: =IFERROR(K101/K102,"") -> -0.12 | ... N42: =IFERROR(N101/N102,"") | O42: =IFERROR(+AVERAGE(D42:N42),"") -> 100.8201
B44: Liquidity | D44: =+D29 -> UBER | E44: =+E29 -> LYFT | F44: =+F29 -> DOORDASH | G44: =+G29 -> GRAB | H44: =+H29 -> DELIVERY HERO | I44: =+I29 -> DiDi | J44: =+J29 -> DIDIY | K44: =+K29 -> DELIVEROO | ... O44: =+O29 -> Average
B46: Cash Ratio | D46: =IFERROR(D111/D119,"") -> 0.51350645 | E46: =IFERROR(E111/E119,"") -> 0.19556815 | F46: =IFERROR(F111/F119,"") -> 0.9055881 | G46: =IFERROR(G111/G119,"") -> 1.1435185 | H46: =IFERROR(H111/H119,"") -> 0.56351902 | I46: =IFERROR(I111/I119,"") -> 1.1545791 | J46: =IFERROR(J111/J119,"") -> 1.5587378 | K46: =IFERROR(K111/K119,"") -> 0.9978355 | ... N46: =IFERROR(N111/N119,"") | O46: =IFERROR(+AVERAGE(D46:N46),"") -> 0.78336024
B47: Quick Ratio | D47: =IFERROR(+(D111+D112)/D119,"") -> 0.80393865 | E47: =IFERROR(+(E111+E112)/E119,"") -> 0.19556815 | F47: =IFERROR(+(F111+F112)/F119,"") -> 1.0705273 | G47: =IFERROR(+(G111+G112)/G119,"") -> 1.2229938 | H47: =IFERROR(+(H111+H112)/H119,"") -> 0.77309783 | I47: =IFERROR(+(I111+I112)/I119,"") -> 1.2349857 | J47: =IFERROR(+(J111+J112)/J119,"") -> 1.5833204 | K47: =IFERROR(+(K111+K112)/K119,"") -> 1.1298701 | ... N47: =IFERROR(+(N111+N112)/N119,"") | O47: =IFERROR(+AVERAGE(D47:N47),"") -> 0.94978278
B48: Current Ratio | D48: =IFERROR(D115/D119,"") -> 1.0670094 | E48: =IFERROR(E115/E119,"") -> 0.76037104 | F48: =IFERROR(F115/F119,"") -> 1.6642632 | G48: =IFERROR(G115/G119,"") -> 2.533179 | H48: =IFERROR(H115/H119,"") -> 0.96297554 | I48: =IFERROR(I115/I119,"") -> 11.747437 | J48: =IFERROR(J115/J119,"") -> 1.9431524 | K48: =IFERROR(K115/K119,"") -> 1.7121212 | ... N48: =IFERROR(N115/N119,"") | O48: =IFERROR(+AVERAGE(D48:N48),"") -> 2.5135879
B50: Activity | D50: =+D29 -> UBER | E50: =+E29 -> LYFT | F50: =+F29 -> DOORDASH | G50: =+G29 -> GRAB | H50: =+H29 -> DELIVERY HERO | I50: =+I29 -> DiDi | J50: =+J29 -> DIDIY | K50: =+K29 -> DELIVEROO | ... O50: =+O29 -> Average
B52: Inventory Turnover | D52: =IFERROR(D98/(AVERAGE(D113:D114)),"") | E52: =IFERROR(E98/(AVERAGE(E113:E114)),"") | F52: =IFERROR(F98/(AVERAGE(F113:F114)),"") | G52: =IFERROR(G98/(AVERAGE(G113:G114)),"") -> 30.055556 | H52: =IFERROR(H98/(AVERAGE(H113:H114)),"") -> 58.385965 | I52: =IFERROR(I98/(AVERAGE(I113:I114)),"") | J52: =IFERROR(J98/(AVERAGE(J113:J114)),"") -> 274.10826 | K52: =IFERROR(K98/(AVERAGE(K113:K114)),"") -> 93.214286 | ... N52: =IFERROR(N98/(AVERAGE(N113:N114)),"") | O52: =IFERROR(+AVERAGE(D52:N52),"") -> 118.17504
B53: Acc. Receivable Turnover | D53: =IFERROR(D97/D112,"") -> 13.194719 | E53: =IFERROR(E97/E112,"") | F53: =IFERROR(F97/F112,"") -> 14.647541 | G53: =IFERROR(G97/G112,"") -> 13.57767 | H53: =IFERROR(H97/H112,"") -> 19.581848 | I53: =IFERROR(I97/I112,"") -> 60.028213 | J53: =IFERROR(J97/J112,"") -> 128.99615 | K53: =IFERROR(K97/K112,"") -> 33.967213 | ... N53: =IFERROR(N97/N112,"") | O53: =IFERROR(+AVERAGE(D53:N53),"") -> 34.718622
B54: Payables Turnover | D54: =IFERROR(D98/D118,"") -> 31.061772 | E54: =IFERROR(E98/E118,"") -> 34.061224 | F54: =IFERROR(F98/F118,"") -> 17.155763 | G54: =IFERROR(G98/G118,"") -> 1.3883661 | H54: =IFERROR(H98/H118,"") -> 28.29932 | I54: =IFERROR(I98/I118,"") -> 5.318944 | J54: =IFERROR(J98/J118,"") -> 4.5054321 | K54: =IFERROR(K98/K118,"") -> 37.285714 | ... N54: =IFERROR(N98/N118,"") | O54: =IFERROR(+AVERAGE(D54:N54),"") -> 21.035651
B55: Fixed Asset Turnover | D55: =IFERROR(D97/D116,"") -> 14.140836 | E55: =IFERROR(E97/E116,"") -> 9.7571669 | F55: =IFERROR(F97/F116,"") -> 9.1876607 | G55: =IFERROR(G97/G116,"") -> 4.9329806 | H55: =IFERROR(H97/H116,"") -> 8.4253835 | I55: =IFERROR(I97/I116,"") -> 32.966257 | J55: =IFERROR(J97/J116,"") -> 11.319003 | K55: =IFERROR(K97/K116,"") -> 10.36 | ... N55: =IFERROR(N97/N116,"") | O55: =IFERROR(+AVERAGE(D55:N55),"") -> 10.777307
B56: Total Asset Turnover | D56: =IFERROR(D97/D117,"") -> 0.85820779 | E56: =IFERROR(E97/E117,"") -> 1.0645814 | F56: =IFERROR(F97/F117,"") -> 0.83472168 | G56: =IFERROR(G97/G117,"") -> 0.30091447 | H56: =IFERROR(H97/H117,"") -> 1.1519832 | I56: =IFERROR(I97/I117,"") -> 1.4570842 | J56: =IFERROR(J97/J117,"") -> 1.0552325 | K56: =IFERROR(K97/K117,"") -> 2.187962 | ... N56: =IFERROR(N97/N117,"") | O56: =IFERROR(+AVERAGE(D56:N56),"") -> 0.97642251
B57: Cash Cycle (days) | D57: =IFERROR(365/D52+365/D53-365/D54,"") | E57: =IFERROR(365/E52+365/E53-365/E54,"") | F57: =IFERROR(365/F52+365/F53-365/F54,"") | G57: =IFERROR(365/G52+365/G53-365/G54,"") -> -223.8724 | H57: =IFERROR(365/H52+365/H53-365/H54,"") -> 11.993378 | I57: =IFERROR(365/I52+365/I53-365/I54,"") | J57: =IFERROR(365/J52+365/J53-365/J54,"") -> -76.852185 | K57: =IFERROR(365/K52+365/K53-365/K54,"") -> 4.8720932 | ... N57: =IFERROR(365/N52+365/N53-365/N54,"") | O57: =IFERROR(+AVERAGE(D57:N57),"") -> -54.470427
B59: Cash Flow | D59: =+D38 -> UBER | E59: =+E38 -> LYFT | F59: =+F38 -> DOORDASH | G59: =+G38 -> GRAB | H59: =+H38 -> DELIVERY HERO | I59: =+I38 -> DiDi | J59: =+J38 -> DIDIY | K59: =+K38 -> DELIVEROO | ... O59: =+O38 -> Average
B61: Cash Flow Margin | D61: =IFERROR(D132/D97,"") -> 0.036518259 | E61: =IFERROR(E132/E97,"") -> 0.030072589 | F61: =IFERROR(F132/F97,"") -> 0.1351427 | G61: =IFERROR(G132/G97,"") -> -0.053628888 | H61: =IFERROR(H132/H97,"") -> -0.062737957 | I61: =IFERROR(I132/I97,"") -> -0.51362125 | J61: =IFERROR(J132/J97,"") -> 0.11106396 | K61: =IFERROR(K132/K97,"") -> -0.068532819 | ... N61: =IFERROR(N132/N97,"") | O61: =IFERROR(+AVERAGE(D61:N61),"") -> -0.051219689
B62: Cash Flow to Net Income | D62: =IFERROR(D132/D96,"") -> 0.76185958 | E62: =IFERROR(E132/E96,"") -> -0.51176471 | F62: =IFERROR(F132/F96,"") -> -2.5967742 | G62: =IFERROR(G132/G96,"") -> 0.34562212 | H62: =IFERROR(H132/H96,"") -> 0.32985205 | I62: =IFERROR(I132/I96,"") -> 21.794948 | J62: =IFERROR(J132/J96,"") -> 2.661522 | K62: =IFERROR(K132/K96,"") -> -47.333333 | ... N62: =IFERROR(N132/N96,"") | O62: =IFERROR(+AVERAGE(D62:N62),"") -> -2.4437973
B63: CFO to Net Income | D63: =+IFERROR(D126/D105,"") -> 0.72214914 | E63: =+IFERROR(E126/E105,"") -> 36.956522 | F63: =+IFERROR(F126/F105,"") -> 17.333333 | G63: =+IFERROR(G126/G105,"") -> -9.6095238 | H63: =+IFERROR(H126/H105,"") -> 0.170441 | I63: =+IFERROR(I126/I105,"") -> 36.925629 | J63: =+IFERROR(J126/J105,"") -> 1.7057203 | K63: =+IFERROR(K126/K105,"") -> 58.666667 | ... N63: =+IFERROR(N126/N105,"") | O63: =IFERROR(+AVERAGE(D63:N63),"") -> 14.192425
B64: Net Capex to CFO | D64: =IFERROR(-D127/D126,"") -> 0.033907804 | E64: =IFERROR(-E127/E126,"") -> 0.098823529 | F64: =IFERROR(-F127/F126,"") -> 0.15478424 | G64: =IFERROR(-G127/G126,"") -> 0.14667988 | H64: =IFERROR(-H127/H126,"") | I64: =IFERROR(-I127/I126,"") -> 0.55891922 | J64: =IFERROR(-J127/J126,"") -> 0.18009289 | K64: =IFERROR(-K127/K126,"") | ... N64: =IFERROR(-N127/N126,"") | O64: =IFERROR(+AVERAGE(D64:N64),"") -> 0.37884583
B65: CFI to CFO | D65: =IFERROR(-D128/D126,"") -> 0.44514502 | E65: =IFERROR(-E128/E126,"") -> 0.60941176 | F65: =IFERROR(-F128/F126,"") -> 0.20825516 | G65: =IFERROR(-G128/G126,"") -> 0.51337958 | H65: =IFERROR(-H128/H126,"") -> -1.5314685 | I65: =IFERROR(-I128/I126,"") -> 2.1909181 | J65: =IFERROR(-J128/J126,"") -> -0.095739916 | K65: =IFERROR(-K128/K126,"") -> 1.0056818 | ... N65: =IFERROR(-N128/N126,"") | O65: =IFERROR(+AVERAGE(D65:N65),"") -> 0.53077407
B66: Net Financing to CFO | D66: =IFERROR((D129+D130)/D126,"") -> -0.02606137 | E66: =IFERROR((E129+E130)/E126,"") -> 0.51647059 | F66: =IFERROR((F129+F130)/F126,"") -> 0 | G66: =IFERROR((G129+G130)/G126,"") -> -0.55599604 | H66: =IFERROR((H129+H130)/H126,"") | I66: =IFERROR((I129+I130)/I126,"") -> 0.45595389 | J66: =IFERROR((J129+J130)/J126,"") -> 1.6812834 | K66: =IFERROR((K129+K130)/K126,"") -> -3.4153409 | ... N66: =IFERROR((N129+N130)/N126,"") | O66: =IFERROR(+AVERAGE(D66:N66),"") -> 0.80860482
B67: Debt Borrowing to Debt Repayment | D67: =+IFERROR(-D130/D129,"") -> 1.0468278 | E67: =+IFERROR(-E130/E129,"") -> 0.045652174 | F67: =+IFERROR(-F130/F129,"") | G67: =+IFERROR(-G130/G129,"") -> 5.675 | H67: =+IFERROR(-H130/H129,"") | I67: =+IFERROR(-I130/I129,"") -> -3.037037 | J67: =+IFERROR(-J130/J129,"") -> 0.13917557 | K67: =+IFERROR(-K130/K129,"") | ... N67: =+IFERROR(-N130/N129,"") | O67: =IFERROR(+AVERAGE(D67:N67),"") -> 0.6252545
B68: CFF to CFO | D68: =IFERROR(-D131/D126,"") -> 0.29241978 | E68: =IFERROR(-E131/E126,"") -> 0.18352941 | F68: =IFERROR(-F131/F126,"") -> 0.095684803 | G68: =IFERROR(-G131/G126,"") -> 0.73042616 | H68: =IFERROR(-H131/H126,"") -> -2.048951 | I68: =IFERROR(-I131/I126,"") -> 1.0228364 | J68: =IFERROR(-J131/J126,"") -> 0.49098239 | K68: =IFERROR(-K131/K126,"") -> 0.78409091 | ... N68: =IFERROR(-N131/N126,"") | O68: =IFERROR(+AVERAGE(D68:N68),"") -> 0.31978079
B69: Payout Ratio | O69: =IFERROR(+AVERAGE(D69:N69),"")
B71: Stock Information | D71: =+D29 -> UBER | E71: =+E29 -> LYFT | F71: =+F29 -> DOORDASH | G71: =+G29 -> GRAB | H71: =+H29 -> DELIVERY HERO | I71: =+I29 -> DiDi | J71: =+J29 -> DIDIY | K71: =+K29 -> DELIVEROO | ... O71: =+O29 -> Average
B73: (%) Float | D73: 0.9634 | E73: 0.866 | F73: 0.845 | G73: 0.6947 | H73: 0.661 | I73: 0.125 | J73: 0.125 | K73: 0.7396 | L73: 0.168 | M73: 0.392 | O73: =IFERROR(+AVERAGE(D73:N73),"") -> 0.55797
B74: β (Levered) | D74: {=IFERROR(_FV(D91,"Beta"),"")} -> 1.482 | E74: {=IFERROR(_FV(E91,"Beta"),"")} -> 2.3464 | F74: {=IFERROR(_FV(F91,"Beta"),"")} -> 1.6959 | G74: {=IFERROR(_FV(G91,"Beta"),"")} -> 0.8431 | H74: {=IFERROR(_FV(H91,"Beta"),"")} -> 1.1181 | I74: {=IFERROR(_FV(I91,"Beta"),"")} -> 0.5674 | J74: {=IFERROR(_FV(J91,"Beta"),"")} -> 1.5295 | K74: {=IFERROR(_FV(K91,"Beta"),"")} -> 0.2181 | ... N74: {=IFERROR(_FV(N91,"Beta"),"")} | O74: =IFERROR(+AVERAGE(D74:N74),"") -> 1.32975
B75: β (Unlevered) | D75: =IFERROR(D74/(1+(1-D104/D103)*(D121/D122)),"") -> 0.77100263 | E75: =IFERROR(E74/(1+(1-E104/E103)*(E121/E122)),"") -> 1.0041786 | F75: =IFERROR(F74/(1+(1-F104/F103)*(F121/F122)),"") -> 1.612881 | G75: =IFERROR(G74/(1+(1-G104/G103)*(G121/G122)),"") -> 0.76972805 | H75: =IFERROR(H74/(1+(1-H104/H103)*(H121/H122)),"") | I75: =IFERROR(I74/(1+(1-I104/I103)*(I121/I122)),"") -> 0.5591689 | J75: =IFERROR(J74/(1+(1-J104/J103)*(J121/J122)),"") -> 1.1448876 | K75: =IFERROR(K74/(1+(1-K104/K103)*(K121/K122)),"") -> 0.2181 | ... N75: =IFERROR(N74/(1+(1-N104/N103)*(N121/N122)),"") | O75: =IFERROR(+AVERAGE(D75:N75),"") -> 0.79186067
B76: % Held by Insiders | D76: 0.0167 | E76: 0.0909 | F76: 0.0056 | G76: 0 | H76: 0.2603 | I76: 0.0031 | J76: 0.0031 | K76: 0.0658 | L76: 0.0756 | M76: 0.0165 | O76: =IFERROR(+AVERAGE(D76:N76),"") -> 0.05376
B77: % Held by Institutions | D77: 0.8116 | E77: 0.8012 | F77: 0.857 | G77: 0.4909 | H77: 0.5916 | I77: 0.0175 | J77: 0.0175 | K77: 0.6684 | L77: 0.603 | M77: 0.3195 | O77: =IFERROR(+AVERAGE(D77:N77),"") -> 0.51782
B78: Short % Float | D78: 0.031 | E78: 0.1371 | F78: 0.038 | G78: 0.0244 | H78: 0.01 | I78: 0.061 | J78: 0.061 | K78: 0.0017 | L78: 0.0009 | M78: 0.3715 | O78: =IFERROR(+AVERAGE(D78:N78),"") -> 0.07366
B80: Stock Performance | D80: =+D29 -> UBER | E80: =+E29 -> LYFT | F80: =+F29 -> DOORDASH | G80: =+G29 -> GRAB | H80: =+H29 -> DELIVERY HERO | I80: =+I29 -> DiDi | J80: =+J29 -> DIDIY | K80: =+K29 -> DELIVEROO | ... O80: =+O29 -> Average
B82: 1 day | D82: {=IFERROR((D85/_xlfn.STOCKHISTORY(C6,TODAY()-1,TODAY()-1,0,0,1))-1,"Non-trading days")} -> 0 | E82: {=IFERROR((E85/_xlfn.STOCKHISTORY(C8,TODAY()-1,TODAY()-1,0,0,1))-1,"Non-trading days")} -> Non-trading days | F82: {=IFERROR((F85/_xlfn.STOCKHISTORY(C9,TODAY()-1,TODAY()-1,0,0,1))-1,"Non-trading days")} -> Non-trading days | G82: {=IFERROR((G85/_xlfn.STOCKHISTORY(C10,TODAY()-1,TODAY()-1,0,0,1))-1,"Non-trading days")} -> Non-trading days | H82: {=IFERROR((K85/_xlfn.STOCKHISTORY(C11,TODAY()-1,TODAY()-1,0,0,1))-1,"Non-trading days")} -> Non-trading days | I82: {=IFERROR((L85/_xlfn.STOCKHISTORY(C12,TODAY()-1,TODAY()-1,0,0,1))-1,"Non-trading days")} -> Non-trading days | J82: {=IFERROR((M85/_xlfn.STOCKHISTORY(C13,TODAY()-1,TODAY()-1,0,0,1))-1,"Non-trading days")} -> Non-trading days | K82: {=IFERROR((N85/_xlfn.STOCKHISTORY(C14,TODAY()-1,TODAY()-1,0,0,1))-1,"Non-trading days")} -> Non-trading days | L82: {=IFERROR((L85/_xlfn.STOCKHISTORY(C15,TODAY()-1,TODAY()-1,0,0,1))-1,"Non-trading days")} -> Non-trading days | M82: {=IFERROR((M85/_xlfn.STOCKHISTORY(C16,TODAY()-1,TODAY()-1,0,0,1))-1,"Non-trading days")} -> Non-trading days | N82: {=IFERROR((N85/_xlfn.STOCKHISTORY(C17,TODAY()-1,TODAY()-1,0,0,1))-1,"Non-trading days")} -> Non-trading days | O82: =IFERROR(+AVERAGE(D82:N82),"") -> 0
B83: 1 month | D83: {=IFERROR((D85/_xlfn.STOCKHISTORY(C6,TODAY()-29,TODAY()-29,0,0,1))-1,"Non-trading days")} -> 0.041731066 | E83: {=IFERROR((E85/_xlfn.STOCKHISTORY(C8,TODAY()-29,TODAY()-29,0,0,1))-1,"Non-trading days")} -> Non-trading days | F83: {=IFERROR((F85/_xlfn.STOCKHISTORY(C9,TODAY()-29,TODAY()-29,0,0,1))-1,"Non-trading days")} -> Non-trading days | G83: {=IFERROR((G85/_xlfn.STOCKHISTORY(C10,TODAY()-29,TODAY()-29,0,0,1))-1,"Non-trading days")} -> Non-trading days | H83: {=IFERROR((K85/_xlfn.STOCKHISTORY(C11,TODAY()-29,TODAY()-29,0,0,1))-1,"Non-trading days")} -> Non-trading days | I83: {=IFERROR((L85/_xlfn.STOCKHISTORY(C12,TODAY()-29,TODAY()-29,0,0,1))-1,"Non-trading days")} -> Non-trading days | J83: {=IFERROR((M85/_xlfn.STOCKHISTORY(C13,TODAY()-29,TODAY()-29,0,0,1))-1,"Non-trading days")} -> Non-trading days | K83: {=IFERROR((N85/_xlfn.STOCKHISTORY(C14,TODAY()-29,TODAY()-29,0,0,1))-1,"Non-trading days")} -> Non-trading days | L83: {=IFERROR((L85/_xlfn.STOCKHISTORY(C15,TODAY()-29,TODAY()-29,0,0,1))-1,"Non-trading days")} -> Non-trading days | M83: {=IFERROR((M85/_xlfn.STOCKHISTORY(C16,TODAY()-29,TODAY()-29,0,0,1))-1,"Non-trading days")} -> Non-trading days | N83: {=IFERROR((N85/_xlfn.STOCKHISTORY(C17,TODAY()-29,TODAY()-29,0,0,1))-1,"Non-trading days")} -> Non-trading days | O83: =IFERROR(AVERAGE(D83:N83),"") -> 0.041731066
B84: YTD | D84: {=IFERROR((D85/_xlfn.STOCKHISTORY(C6,"2025-01-02","2025-01-02",0,0,1))-1,"Non-trading days")} -> 0.49374703 | E84: {=IFERROR((E85/_xlfn.STOCKHISTORY(C8,"2025-01-02","2025-01-02",0,0,1))-1,"Non-trading days")} -> Non-trading days | F84: {=IFERROR((F85/_xlfn.STOCKHISTORY(C9,"2025-01-02","2025-01-02",0,0,1))-1,"Non-trading days")} -> Non-trading days | G84: {=IFERROR((G85/_xlfn.STOCKHISTORY(C10,"2025-01-02","2025-01-02",0,0,1))-1,"Non-trading days")} -> Non-trading days | H84: {=IFERROR((K85/_xlfn.STOCKHISTORY(C11,"2025-01-02","2025-01-02",0,0,1))-1,"Non-trading days")} -> Non-trading days | I84: {=IFERROR((L85/_xlfn.STOCKHISTORY(C12,"2025-01-02","2025-01-02",0,0,1))-1,"Non-trading days")} -> Non-trading days | J84: {=IFERROR((M85/_xlfn.STOCKHISTORY(C13,"2025-01-02","2025-01-02",0,0,1))-1,"Non-trading days")} -> Non-trading days | K84: {=IFERROR((N85/_xlfn.STOCKHISTORY(C14,"2025-01-02","2025-01-02",0,0,1))-1,"Non-trading days")} -> Non-trading days | L84: {=IFERROR((L85/_xlfn.STOCKHISTORY(C15,"2025-01-02","2025-01-02",0,0,1))-1,"Non-trading days")} -> Non-trading days | M84: {=IFERROR((M85/_xlfn.STOCKHISTORY(C16,"2025-01-02","2025-01-02",0,0,1))-1,"Non-trading days")} -> Non-trading days | N84: {=IFERROR((N85/_xlfn.STOCKHISTORY(C17,"2025-01-02","2025-01-02",0,0,1))-1,"Non-trading days")} -> Non-trading days | O84: =IFERROR(AVERAGE(D84:N84),"") -> 0.49374703
B85: Current Price | D85: {=+IFERROR(_FV(D91,"Price"),"")} -> 94.36 | E85: {=+IFERROR(_FV(E91,"Price"),"")} | F85: {=+IFERROR(_FV(F91,"Price"),"")} | G85: {=+IFERROR(_FV(G91,"Price"),"")} | H85: {=+IFERROR(_FV(H91,"Price"),"")} | I85: {=+IFERROR(_FV(I91,"Price"),"")} | J85: {=+IFERROR(_FV(J91,"Price"),"")} | K85: {=+IFERROR(_FV(K91,"Price"),"")} | ... N85: {=+IFERROR(_FV(N91,"Price"),"")} | O85: =IFERROR(AVERAGE(D85:N85),"") -> 94.36
B87: Extra
B89: % Revenues in the US | D89: 0.75 | E89: 1 | F89: 0.736 | G89: 0 | H89: 0.062 | I89: 0.041 | J89: 0 | K89: 0 | L89: 0.38 | M89: 0.82
B91: Income Statement | D91: =+DCF!R4 -> #VALUE! | E91: #VALUE! | F91: #VALUE! | G91: #VALUE! | H91: #VALUE! | I91: #VALUE! | J91: #VALUE! | K91: #VALUE! | L91: #VALUE! | M91: #VALUE!
B93: =+Inputs!$B$6&" ("&Inputs!O$4&")" -> Revenue (Sales) (2022) | D93: =+_xlfn.XLOOKUP("Revenue (Sales)",Inputs!$B:$B,Inputs!O:O) -> 31877 | E93: 4095 | F93: 6583 | G93: 1433 | H93: 8577 | I93: 20936 | J93: 32708.8 | K93: 1975 | L93: 5561 | M93: 8685
B94: =+Inputs!$B$6&" ("&Inputs!P$4&")" -> Revenue (Sales) (2023) | D94: =+_xlfn.XLOOKUP("Revenue (Sales)",Inputs!$B:$B,Inputs!P:P) -> 37281 | E94: 4404 | F94: 8635 | G94: 2359 | H94: 9942 | I94: 27167.3 | J94: 39081 | K94: 2030 | L94: 3534 | M94: 9371
B95: EBITDA (2023) | D95: =+_xlfn.XLOOKUP("EBITDA",Inputs!$B:$B,Inputs!P:P) -> 1933 | E95: -254 | F95: 201 | G95: -353 | H95: -155 | I95: 653.4 | J95: 3165.3 | K95: 20 | L95: 408 | M95: 3940
B96: Net Income (2023) | D96: =+_xlfn.XLOOKUP("Net Income",Inputs!$B:$B,Inputs!P:P) -> 2108 | E96: -340 | F96: -558 | G96: -434 | H96: -2298 | I96: -676.9 | J96: 1956.7 | K96: 3 | L96: -1846 | M96: 616
B97: =+Inputs!$B$6&" ("&Inputs!Q$4&")" -> Revenue (Sales) (2024) | D97: =+_xlfn.XLOOKUP("Revenue (Sales)",Inputs!$B:$B,Inputs!Q:Q) -> 43978 | E97: 5786 | F97: 10722 | G97: 2797 | H97: 12082 | I97: 28723.5 | J97: 46890.1 | K97: 2072 | L97: 3564 | M97: 9049
B98: COGS (Cost of Goods Sold) | D98: =+_xlfn.XLOOKUP($B98,Inputs!$B:$B,Inputs!Q:Q) -> 26651 | E98: 3338 | F98: 5507 | G98: 1623 | H98: 8320 | I98: 23472.5 | J98: 28863.6 | K98: 1305 | L98: 1824 | M98: 5689
B99: Gross Profit | D99: =+_xlfn.XLOOKUP($B99,Inputs!$B:$B,Inputs!Q:Q) -> 17327 | E99: =+E97-E98 -> 2448 | F99: =+F97-F98 -> 5215 | G99: =G97-G98 -> 1174 | H99: =+H97-H98 -> 3762 | I99: 4251 | J99: 18026.6 | K99: =+K97-K98 -> 767 | L99: =+L97-L98 -> 1740 | M99: =+M97-M98 -> 3360 | N99: =+N97-N98 -> 0
B100: EBITDA | D100: =+_xlfn.XLOOKUP($B100,Inputs!$B:$B,Inputs!Q:Q) -> 3510 | E100: 73 | F100: 894 | G100: -86 | H100: 731 | I100: 132 | J100: 6925.3 | K100: 88 | L100: 376 | M100: 3632
B101: Operating Income (EBIT) | D101: =+_xlfn.XLOOKUP($B101,Inputs!$B:$B,Inputs!Q:Q) -> 2799 | E101: -114 | F101: 232 | G101: -233 | H101: 191 | I101: -305.7 | J101: 5755.6 | K101: 3 | L101: -168 | M101: -1078
B102: Net Interest Expense (Income) | D102: =+_xlfn.XLOOKUP($B102,Inputs!$B:$B,Inputs!Q:Q) -> -198 | E102: -137 | F102: -199 | G102: -73 | H102: - | I102: -619.6 | J102: 6.3 | K102: -25 | L102: -47 | M102: -959
B103: Pre-Tax Income (EBT) | D103: =+_xlfn.XLOOKUP($B103,Inputs!$B:$B,Inputs!Q:Q) -> 4125 | E103: 25 | F103: 156 | G103: -95 | H103: -472 | I103: 174.3 | J103: 5276 | K103: 12 | L103: -532 | M103: -3237
B104: Tax Expense (Benefits) | D104: =+_xlfn.XLOOKUP($B104,Inputs!$B:$B,Inputs!Q:Q) -> -5758 | E104: 3 | F104: 39 | G104: 63 | H104: - | I104: -2.8 | J104: 302.4 | K104: 12 | L104: -42 | M104: -375
B105: Net Income | D105: =+_xlfn.XLOOKUP($B105,Inputs!$B:$B,Inputs!Q:Q) -> 9883 | E105: 23 | F105: 123 | G105: -105 | H105: -839 | I105: 174.8 | J105: 4973.5 | K105: 3 | L105: -1645 | M105: -2862
B106: EPS basic | D106: =+_xlfn.XLOOKUP($B106,Inputs!$B:$B,Inputs!Q:Q) -> 4.71 | E106: 0.06 | F106: 0.3 | G106: -0.03 | H106: -3.39 | I106: 0.04 | J106: 0.81 | K106: 0 | L106: -8.09 | M106: -9.33
B107: R&D (Research & Development) | D107: =+_xlfn.XLOOKUP($B107,Inputs!$B:$B,Inputs!Q:Q) -> 3109 | E107: 396 | F107: 1145 | G107: 410 | H107: - | I107: 1675.1 | J107: 2924.3 | K107: 0 | L107: 0 | M107: 0
B109: Balance Sheet
B111: Cash & Cash Equivalents | D111: =+_xlfn.XLOOKUP($B111,Inputs!$B:$B,Inputs!Q:Q) -> 5893 | E111: 759 | F111: 4019 | G111: 2964 | H111: 1659 | I111: 6870.9 | J111: 23048.9 | K111: 461 | L111: 1177 | M111: 592
B112: Accounts Receivable | D112: =+_xlfn.XLOOKUP($B112,Inputs!$B:$B,Inputs!Q:Q) -> 3333 | E112: 0 | F112: 732 | G112: 206 | H112: 617 | I112: 478.5 | J112: 363.5 | K112: 61 | L112: 170 | M112: 1205
B113: Beginning Inventory | D113: =+_xlfn.XLOOKUP("Inventory",Inputs!$B:$B,Inputs!P:P) -> 0 | E113: 0 | F113: 0 | G113: 49 | H113: 141 | I113: 0 | J113: 7.6 | K113: 15 | L113: 19 | M113: 0
B114: Ending Inventory | D114: =+_xlfn.XLOOKUP("Inventory",Inputs!$B:$B,Inputs!Q:Q) -> 0 | E114: 0 | F114: 0 | G114: 59 | H114: 144 | I114: 0 | J114: 203 | K114: 13 | L114: 8 | M114: 0
B115: Current Assets | D115: =+_xlfn.XLOOKUP($B115,Inputs!$B:$B,Inputs!Q:Q) -> 12245 | E115: 2951 | F115: 7386 | G115: 6566 | H115: 2835 | I115: 69909 | J115: 28733.2 | K115: 791 | L115: 2604 | M115: 3232
B116: Net PP&E (Property, Plant and Equipment) | D116: =+_xlfn.XLOOKUP($B116,Inputs!$B:$B,Inputs!Q:Q) -> 3110 | E116: 593 | F116: 1167 | G116: 567 | H116: 1434 | I116: 871.3 | J116: 4142.6 | K116: 200 | L116: 582 | M116: 16157
B117: Total Assets | D117: =+_xlfn.XLOOKUP($B117,Inputs!$B:$B,Inputs!Q:Q) -> 51244 | E117: 5435 | F117: 12845 | G117: 9295 | H117: 10488 | I117: 19713 | J117: 44435.8 | K117: 947 | L117: 8128 | M117: 21802
B118: Accounts Payable | D118: =+_xlfn.XLOOKUP($B118,Inputs!$B:$B,Inputs!Q:Q) -> 858 | E118: 98 | F118: 321 | G118: 1169 | H118: 294 | I118: 4413 | J118: 6406.4 | K118: 35 | L118: 43 | M118: 642
B119: Current Liabilities | D119: =+_xlfn.XLOOKUP($B119,Inputs!$B:$B,Inputs!Q:Q) -> 11476 | E119: 3881 | F119: 4438 | G119: 2592 | H119: 2944 | I119: 5951 | J119: 14786.9 | K119: 462 | L119: 2350 | M119: 1974
B120: Long-term debt | D120: =+_xlfn.XLOOKUP($B120,Inputs!$B:$B,Inputs!Q:Q) -> 8340 | E120: 718 | F120: 468 | G120: 241 | H120: 5157 | I120: 195.9 | J120: 5797.6 | K120: 33 | L120: 919 | M120: 18408
B121: Total Debt | D121: =+_xlfn.XLOOKUP($B121,Inputs!$B:$B,Inputs!Q:Q,,,-1) -> 8651 | E121: 1165 | F121: 536 | G121: 364 | H121: 5563 | I121: 195.9 | J121: =+J120+2629.1 -> 8426.7 | K121: 50 | L121: 1563 | M121: 18408
B122: Shareholder's Equity | D122: =+_xlfn.XLOOKUP($B122,Inputs!$B:$B,Inputs!Q:Q) -> 22476 | E122: 767 | F122: 7810 | G122: 6351 | H122: 1649 | I122: =+I117-6191 -> 13522 | J122: =+J117-20789.5 -> 23646.3 | K122: 439 | L122: 4442 | M122: 153
B124: Cash Flow Statement
B126: Operating Cash Flow | D126: =+_xlfn.XLOOKUP($B126,Inputs!$B:$B,Inputs!Q:Q) -> 7137 | E126: 850 | F126: 2132 | G126: 1009 | H126: -143 | I126: 6454.6 | J126: 8483.4 | K126: 176 | L126: 279 | M126: 2224
B127: Net Capex | D127: =+_xlfn.XLOOKUP($B127,Inputs!$B:$B,Inputs!Q:Q) -> -242 | E127: -84 | F127: -330 | G127: -148 | H127: - | I127: -3607.6 | J127: -1527.8 | K127: - | L127: -167 | M127: -2800
B128: Investing Cash Flow | D128: =+_xlfn.XLOOKUP($B128,Inputs!$B:$B,Inputs!Q:Q) -> -3177 | E128: -518 | F128: -444 | G128: -518 | H128: -219 | I128: -14141.5 | J128: 812.2 | K128: -177 | L128: -180 | M128: -2929
...

Sheet ESG
B2: Environmental, Social and Governance Analysis
B4: Author: | C4: Bloomberg | E4: Highlights | N4: Recent News
G5: EV Integration: Uber has expanded its electric vehicle offerings, now with over 182,000 EVs available globally. The "Uber Green" option is accessible in over 200 cities, allowing users to choose electric or hybrid vehicles easily and promoting deliveries by bike, foot, or EVs. | N5: Climate-Focused Initiatives: At its "Go-Get Zero" event in October 2024, Uber unveiled several climate-focused features, including the ability for users to choose electric vehicles at the same price as standard rides and to track emissions savings. These initiatives align with Uber's goal to become an emissions-free mobility platform by 2040. | R5: Investor Call for Transparency: In December 2024, a group of Uber investors proposed a resolution demanding more detailed disclosures on driver compensation. They argue that the current lack of transparency hinders the assessment of the company's financial health and its commitment to fair labor practices.
B6: Overview | D6: . | E6: Leadership in Sustainability: In August 2024, Uber appointed former Tesla executive Rebecca Tinucci as its Global Head of Sustainability, underscoring its commitment to accelerating the transition to electric vehicles and enhancing sustainability efforts.
B7: Last Update | C7: 45748 | D7: . | G7: Uber aims to have net-zero emissions across its platform by 2040, including Uber Eats deliveries.
B8: Latest year with data | C8: 2024 | E8: The platform now enables users to track emissions savings when opting for sustainable transport options. Uber also introduced a sustainable packaging marketplace for restaurants and provided financial incentives to encourage eco-friendly packaging .​
B9: GICS Sector | C9: Industrials
B10: GICS Industry Group | C10: Transportation
B11: Final Review
B13: ESG Scores
B14: LSEG ESG Score | C14: 78
B15: E-Score | C15: 67 | O15: https://www.esgdive.com/news/uber-rolls-out-climate-focused-features-updates-drives-sustainability-goals/729509/? | S15: https://www.bloomberg.com/news/articles/2024-12-20/uber-investors-are-calling-for-more-transparency-into-driver-pay
B16: S-Score | C16: 67 | E16: GHG Scope 1 and 2 Emissions: | N16: Water, Waste, Energy Management:
B17: G-Score | C17: 90
B18: S&P Global ESG Score | C18: 39
B19: Environmental | C19: 55
B20: Social | C20: 27
B21: Governance & Economic | C21: 42
B22: Sustainalytics | C22: 21.8
B23: ISS ESG Corporate Rating | C23: C+
B24: SDG Impact Rating | C24: -5.5
B25: Governance Quality Score | C25: 9
B26: MSCI ESG Ratings | C26: A
B29: Industry ESG Overview:
B30: Concerning environmental impact, particularly carbon emissions and waste management, companies in the mobility and delivery sector like Uber are pivotal in transitioning to sustainable practices. This includes adopting electric vehicles (EVs), reducing packaging waste, and enhancing supply chain sustainability. Socially, there's a growing emphasis on worker rights, diversity, and community engagement. Governance-wise, transparency in operations and aligning executive compensation with ESG goals are becoming industry standards.
E33: ENVIRONMENTAL
G35: Overview | H35: Targets | K35: Improvements | O35: Comments
E36: GHG (or CO2) Scope 1 Emissions | H36: Uber aims to reduce absolute Scope 1 and 2 GHG emissions by 42% by 2030 and 90% by 2040, using 2021 as the base year. | K36: Transition to renewable energy sources by increasing the use of renewable energy. Enhance energy efficiency, implementing energy-saving measures across all facilities. | O36: In 2023, Uber reported Scope 1 emissions of approximately 1.7 million kg CO₂e.
E38: Water Consumption | H38: Implement water-saving initiatives across all operations.​ | K38: Monitor water usage, that is, regularly track and report water consumption to identify areas for improvement.​ | O38: Uber uses over 250,000 m³ of water annually, with 15% sourced from high and extremely high water-stressed areas.
E40: Energy Consumption | H40: Achieve 100% renewable electricity across U.S. corporate offices by 2025. | K40: They signed Power Purchase Agreements (PPAs) with renewable providers like Enel Green Power and invested $10 million in renewable energy development in India. | O40: Uber is pursuing LEED and WELL certifications for its largest U.S. offices, including San Francisco, Dallas, New York, and Chicago, to improve energy and water consumption and support employee well-being. The energy consumption was 367 639 268 kWh in 2023.
E42: Waste Management | H42: Remove all unnecessary plastic from deliveries globally by 2030, with an earlier target of 80% elimination by 2025 in Europe and Asia-Pacific regions. | K42: Expand sustainable packaging initiatives and increase consumer awareness by enhancing features in the Uber Eats app to help consumers identify and choose merchants that use environmentally friendly packaging. | O42: Uber is working with the World Wildlife Fund (WWF) and Closed Loop Partners to establish sustainable packaging guidelines. It has also partnered with sustainable packaging providers such as Green Paper Products, Bunzl, Enviropack, and Dinovia across U.S. and European markets
E44: Other | H44: Become a net-zero emissions platform across all rides and services by 2040. | K44: Work with policymakers, climate experts, and industry leaders to reduce the environmental impact of trips taken on the app. | O44: Uber has committed $800 million through 2025 to support driver transitions to zero-emission vehicles (ZEVs) via discounts, subsidies, and education.
E46: SOCIAL
B48: Important Sources: | G48: Overview | H48: Targets | K48: Improvements | O48: Comments
B49: Annual Report | C49: https://www.sec.gov/Archives/edgar/data/1543151/000154315124000012/uber-20231231.htm? | E49: Employee Turnover % | H49: Reduce burnout and improve long-term engagement. | K49: Encourage more transparent and stable communication from upper management. | O49: Uber shows relatively high retention, about 58% of employees wouldn’t leave even for higher pay and 82% report excitement about coming to work. However, concerns exist around inconsistent leadership and fast-paced, high-pressure work culture.
B50: Sustainability Report | C50: https://sustainabilityreports.com/reports/uber-technologies-inc-2023-esg-report-pdf/? | D50: .
B51: Proxy Statement | C51: https://www.sec.gov/Archives/edgar/data/1543151/000155278124000177/e24048_uber-def14a.htm | D51: . | E51: Salaries & Compensation | H51: Offer salaries at or above market averages, ensure fair compensation across job levels and strengthen benefits aligned with modern employee needs. | K51: Improve transparency in how salaries and bonuses are structured and communicated. | O51: Salaries range widely (from aprox $2,000/month for drivers to over $100,000/year for corporate roles) and the employee rating of compensation is about 3.5/5 stars. Nevertheless, the executive pay is significant: CEO received $136M in stock awards tied to performance.
E53: Reputation | H53: Eliminate discrimination and harassment in the workplace. | K53: Continue investing in D&I (Diversity & Inclusion) initiatives. | O53: Strong culture scores: 4.2/5 rating on AmbitionBox for work-life balance, compensation, and values. However, past scandals such as gender discrimination lawsuits still affect.
E55: Discrimination Events | H55: Eliminate all forms of discrimination, including gender, racial, and ethnic biases; besides ensure equal pay and promotion opportunities across all employee demographics. | K55: Implement comprehensive anti-discrimination training programs for all employees and stablish clear and accessible reporting mechanisms for discrimination and harassment. | O55: Uber has faced multiple lawsuits alleging discrimination: former employees have publicly shared experiences of harassment and discrimination, highlighting systemic issues within the company; in 2017, a class-action lawsuit claimed the company discriminated against women and minorities, leading to a $10 million settlement. But in 2019, Uber agreed to pay $4.4 million to settle sexual harassment and retaliation claims, acknowledging a culture that tolerated such behaviors.
E57: Work Safety | H57: Ensure the safety and well-being of all employees, particularly drivers and couriers. | K57: Implement real-time safety monitoring and support systems for drivers. | O57: They need to focus on their targets, specially providing adequate training and resources to handle potential safety risks and establish clear protocols for reporting and addressing safety incidents. In April 2025, a 77-year-old Uber driver was fatally shot during a pickup in Philadelphia, raising concerns about driver safety. Previous incidents, such as the fatal self-driving car crash in 2018, have also highlighted safety issues within Uber's operations.​
E59: Damage to consumer health | H59: Ensure that all products and services meet health and safety standards. Provide clear and accurate information to consumers regarding health-related aspects of services. | K59: Provide consumers with clear information about health and safety measures in place. | O59: There have been instances where consumers reported health-related issues, such as food safety concerns with Uber Eats deliveries, though these are relatively rare.​ Moreover, in 2023, Uber Eats faced criticism over the use of facial recognition technology to verify delivery personnel, leading to concerns about potential health risks and privacy issues.
E61: Pension Plan | H61: Extend pension schemes to all markets where Uber operates. | K61: Standardize contribution rates to ensure consistency across regions. | O61: In the UK, for employees, Uber offers a pension scheme with a 1:1 matching contribution, ranging from 4.5% to 5.5% of employee earnings. ​For drivers, Uber introduced a pension scheme, contributing 3% of earnings, having the option to contribute a minimum of 5%. ​
E63: Supply chain | H63: Achieve zero-emission deliveries by 2040. Eliminate unnecessary plastic waste from deliveries by 2030. | K63: Accelerate the transition to electric vehicles and e-bikes for deliveries. | O63: The company is working with partners to provide discounts on sustainable packaging for merchants and is promoting the use of eco-friendly materials. Their aim is to achieve their targets.
E65: Community involvement | H65: Increase the number of community-focused initiatives globally. | K65: Enhance collaboration with local organizations to address community needs. | O65: Uber has expanded its services to include fresh produce from farmers' markets in New York City and Los Angeles, aiming to make sustainable living more accessible for customers. The company is also launching a campaign to promote sustainable packaging by partnering with companies that offer eco-friendly packaging solutions, making them more accessible and affordable for merchants.
E67: Public Sector | H67: Expand public transport partnerships, enhance accessibility and promote sustainability. | K67: Collaborate with local and regional governments to integrate Uber's platform, develop services tailored for individuals with disabilities or mobility challenges. | O67: In 2020, Uber signed a contract to manage parts of California's public transport system using their software. This partnership allows residents to book minibus rides through Uber's app, with proceeds supporting the local transit authority. It is been involved in discussions with various cities worldwide to explore this kind of opportunities, but for the moment they need to broaden geographic reach.
E69: Litigation | H69: Ensure legal compliance and promote fair labor practices. | O69: Uber has faced multiple lawsuits related to driver classification, including a $20 million settlement in 2019 over similar issues. In 2021, Uber was ordered to pay $1.1 million after a blind customer was denied rides multiple times, highlighting issues related to service accessibility. In 2024, the U.S. Supreme Court declined Uber's request to dismiss lawsuits filed by California on behalf of drivers who were allegedly misclassified as independent contractors.
E71: GOVERNANCE
G73: Overview | H73: Targets | K73: Improvements | O73: Comments
E74: Diversity (Gender, Age, Industry, Region) | H74: Achieve 40% female representation on the board and increase ethnic minority representation to 30%. | K74: Expand the board's expertise by including members from additional industries and regions.​ | O74: The composition of Uber's board includes 36% women and 27% ethnic minorities, with an average age of 58 years. Uber has a total of 30,400 employees globally (aproximatelly 10 000 women). In the Executive Committee, 4 are women and 8 are men.
E76: % Independence | H76: Maintain at least 80-90%. | K76: Continue to uphold and potentially increase the percentage of independent board members. | O76: 10 independent out of 11 in the board, so a 91% independence rate.
E78: Average time as independent directors | H78: Average tenure of independent directors not exceeding 7 years. | K78: Maintain current rotation strategy. | O78: The average tenure of independent directors on Uber's board is approximately 5.8 years.
E80: Departures of C-level executives | H80: Reduce turnover among C-level executives and ensure smooth transitions while maintaining stability in the leadership team. | K80: Continue investing in executive development and company culture. | O80: Dismissal of Ryan Graves as CEO in 2010, besides Travis Kalanick, cofounder and ex CEO. Nelson Chai, who served as Uber's CFO, announced his resignation in August 2023, with a transition period until January 2024, and his sucessor is Prashanth Mahendra-Rajah, previously the CFO at Analog Devices.
E82: CEO/Chairman duality | H82: Maintain separate CEO and Chairman roles to avoid concentration of power. | K82: N/A | O82: Separate CEO and Chairman structure, with Ronald Sugar serving as Chairman and Dara Khosrowshahi as CEO.
E84: Transparency when reporting | H84: Publishing clear, detailed reports annually on progress toward goals | K84: N/A | O84: Transparent, in fact it was the first ride-sharing company to publish an independent Civil Rights Assessment. Uber publishes detailed annual reports on ESG, governance, and financial performance and complies fully with SEC disclosure requirements.
E86: Time taken to report | H86: Reduce the time taken to prepare and publish ESG and financial reports. | K86: Streamline internal ESG reporting processes to reduce delays. | O86: The reports are typically released within the first quarter of the following year.
E88: CEO or Chairman in other boards? | G88: No | H88: Limit CEO and Chairman roles in other boards to avoid conflicts of interest. | K88: N/A | O88: Ronald D. Sugar, also holds board positions at Apple Inc. (since 2010) and Chevron Corporation (since 2005), but Dara Khosrowshahi does not serve on the board of any other company.
E90: Audit / Consulting | H90: Ensure the independence of audits and compliance with regulatory standards. | K90: N/A | O90: Uber has worked with recognized audit and consulting firms to ensure the integrity of its financial and operational reports. Moreover, it engages PricewaterhouseCoopers LLP (PwC) as its independent registered public accounting firm for annual audits.
E92: ESG-compensation related | H92: Keep the integration of ESG metrics (such as diversity and inclusion, safety, and sustainability) into executive compensation. | K92: Focus on binding ESG metrics that are directly tied to performance outcomes. | O92: Uber incorporates ESG metrics into its executive compensation plans, including Diversity, Equity, and Inclusion (DEI) and safety goals, as part of its Performance Restricted Stock Units (PRSUs) and annual cash bonus plans.
E94: Management compensation schemes | H94: Maintain the mix of base salary, performance-based bonuses, and equity awards. | K94: Enhance transparency in compensation disclosures to provide shareholders with a clearer understanding of executive pay structures. | O94: Uber's executive compensation comprises three primary elements: base salary, annual cash bonus and equity awards. Uber also offers competitive compensation packages to its executive team. For example, the CEO, Dara Khosrowshahi, received a total compensation of $24,248,208 in fiscal year 2023. Despite these efforts, concerns have been raised about the transparency of compensation structures and their alignment with long-term performance.

Sheet ESG Inputs
B2: ESG Inputs
A4: x | B4: Total GHG Scope 1 Emissions | G4: 2014 | H4: =+G4+1 -> 2015 | I4: =+H4+1 -> 2016 | J4: =+I4+1 -> 2017 | K4: =+J4+1 -> 2018 | L4: =+K4+1 -> 2019 | M4: =+L4+1 -> 2020 | N4: =+M4+1 -> 2021 | O4: =+N4+1 -> 2022 | ... Q4: =+P4+1 -> 2024 | R4: ="CAGR "&$G$4&" - "&$Q$4 -> CAGR 2014 - 2024
B6: =+Peers!B6 -> UBER TECHNOLOGIES, INC. | L6: 3 | M6: 1 | N6: 1 | O6: 1 | P6: 2 | R6: =IFERROR((Q6/G6)^(1/COUNT($G$4:$Q$4))-1,"")
B7: =+Peers!B8 -> LYFT INC. | K7: 0 | L7: 2 | M7: 1 | N7: 1 | O7: 2 | R7: =IFERROR((Q7/G7)^(1/COUNT($G$4:$Q$4))-1,"")
B8: =+Peers!B9 -> DOORDASH INC. | N8: 1 | O8: 4 | R8: =IFERROR((Q8/G8)^(1/COUNT($G$4:$Q$4))-1,"")
B9: =+Peers!B10 -> GRAB HOLDINGS LIMITED | O9: 15 | P9: 36 | R9: =IFERROR((Q9/G9)^(1/COUNT($G$4:$Q$4))-1,"")
B10: =+Peers!B11 -> DELIVERY HERO SE | M10: 1 | N10: 4 | O10: 35 | P10: 39 | R10: =IFERROR((Q10/G10)^(1/COUNT($G$4:$Q$4))-1,"")
B11: =+Peers!B12 -> DiDi GLOBAL INC. | R11: =IFERROR((Q11/G11)^(1/COUNT($G$4:$Q$4))-1,"")
B12: =+Peers!B13 -> MEITUAN | K12: 9 | R12: =IFERROR((Q12/G12)^(1/COUNT($G$4:$Q$4))-1,"")
B13: =+Peers!B14 -> DELIVEROO PLC | N13: 2 | O13: 4 | P13: 5 | Q13: 4 | R13: =IFERROR((Q13/G13)^(1/COUNT($G$4:$Q$4))-1,"")
B14: =+Peers!B15 -> JUST EAT TAKEAWAY | M14: 4 | N14: 7 | O14: 9 | P14: 5 | Q14: 5 | R14: =IFERROR((Q14/G14)^(1/COUNT($G$4:$Q$4))-1,"")
B15: =+Peers!B16 -> HERTZ GLOBAL HOLDINGS INC. | L15: 6528 | O15: 4064 | P15: 3411 | R15: =IFERROR((Q15/G15)^(1/COUNT($G$4:$Q$4))-1,"")
B16: =+Peers!B17 -> 0 | L16: 11 | M16: 10 | N16: 9 | O16: 20 | P16: 21 | R16: =IFERROR((Q16/G16)^(1/COUNT($G$4:$Q$4))-1,"")
A18: x | B18: Total GHG Scope 2 (Location-Based) Emissions | G18: 2014 | H18: =+G18+1 -> 2015 | I18: =+H18+1 -> 2016 | J18: =+I18+1 -> 2017 | K18: =+J18+1 -> 2018 | L18: =+K18+1 -> 2019 | M18: =+L18+1 -> 2020 | N18: =+M18+1 -> 2021 | O18: =+N18+1 -> 2022 | ... Q18: =+P18+1 -> 2024 | R18: ="CAGR "&$G$4&" - "&$Q$4 -> CAGR 2014 - 2024
B20: =+$B$6 -> UBER TECHNOLOGIES, INC. | N20: 61 | O20: 59 | P20: 82 | R20: =IFERROR((Q20/G20)^(1/COUNT($G$4:$Q$4))-1,"")
B21: =+$B$7 -> LYFT INC. | K21: 2 | L21: 1 | M21: 2 | N21: 1 | O21: 1 | R21: =IFERROR((Q21/G21)^(1/COUNT($G$4:$Q$4))-1,"")
B22: =+$B$8 -> DOORDASH INC. | R22: =IFERROR((Q22/G22)^(1/COUNT($G$4:$Q$4))-1,"")
B23: =+$B$9 -> GRAB HOLDINGS LIMITED | L23: 9 | M23: 6 | N23: 9 | O23: 46 | P23: 54 | R23: =IFERROR((Q23/G23)^(1/COUNT($G$4:$Q$4))-1,"")
B24: =+$B$10 -> DELIVERY HERO SE | M24: 2 | N24: 56 | O24: 83 | R24: =IFERROR((Q24/G24)^(1/COUNT($G$4:$Q$4))-1,"")
B25: =+$B$11 -> DiDi GLOBAL INC. | R25: =IFERROR((Q25/G25)^(1/COUNT($G$4:$Q$4))-1,"")
B26: =+$B$12 -> MEITUAN | R26: =IFERROR((Q26/G26)^(1/COUNT($G$4:$Q$4))-1,"")
B27: =+$B$13 -> DELIVEROO PLC | O27: 8 | P27: 6 | Q27: 6 | R27: =IFERROR((Q27/G27)^(1/COUNT($G$4:$Q$4))-1,"")
B28: =+$B$14 -> JUST EAT TAKEAWAY | M28: 2 | N28: 4 | Q28: 4 | R28: =IFERROR((Q28/G28)^(1/COUNT($G$4:$Q$4))-1,"")
B29: =+$B$15 -> HERTZ GLOBAL HOLDINGS INC. | M29: 112 | O29: 74 | P29: 150 | R29: =IFERROR((Q29/G29)^(1/COUNT($G$4:$Q$4))-1,"")
B30: =+$B$16 -> 0 | R30: =IFERROR((Q30/G30)^(1/COUNT($G$4:$Q$4))-1,"")
A32: x | B32: Total Energy Usage | G32: 2014 | H32: =+G32+1 -> 2015 | I32: =+H32+1 -> 2016 | J32: =+I32+1 -> 2017 | K32: =+J32+1 -> 2018 | L32: =+K32+1 -> 2019 | M32: =+L32+1 -> 2020 | N32: =+M32+1 -> 2021 | O32: =+N32+1 -> 2022 | ... Q32: =+P32+1 -> 2024 | R32: ="CAGR "&$G$4&" - "&$Q$4 -> CAGR 2014 - 2024
B34: =+$B$6 -> UBER TECHNOLOGIES, INC. | R34: =IFERROR((Q34/G34)^(1/COUNT($G$4:$Q$4))-1,"")
B35: =+$B$7 -> LYFT INC. | R35: =IFERROR((Q35/G35)^(1/COUNT($G$4:$Q$4))-1,"")
B36: =+$B$8 -> DOORDASH INC. | R36: =IFERROR((Q36/G36)^(1/COUNT($G$4:$Q$4))-1,"")
B37: =+$B$9 -> GRAB HOLDINGS LIMITED | R37: =IFERROR((Q37/G37)^(1/COUNT($G$4:$Q$4))-1,"")
B38: =+$B$10 -> DELIVERY HERO SE | R38: =IFERROR((Q38/G38)^(1/COUNT($G$4:$Q$4))-1,"")
B39: =+$B$11 -> DiDi GLOBAL INC. | R39: =IFERROR((Q39/G39)^(1/COUNT($G$4:$Q$4))-1,"")
B40: =+$B$12 -> MEITUAN | R40: =IFERROR((Q40/G40)^(1/COUNT($G$4:$Q$4))-1,"")
B41: =+$B$13 -> DELIVEROO PLC | R41: =IFERROR((Q41/G41)^(1/COUNT($G$4:$Q$4))-1,"")
B42: =+$B$14 -> JUST EAT TAKEAWAY | R42: =IFERROR((Q42/G42)^(1/COUNT($G$4:$Q$4))-1,"")
B43: =+$B$15 -> HERTZ GLOBAL HOLDINGS INC. | R43: =IFERROR((Q43/G43)^(1/COUNT($G$4:$Q$4))-1,"")
B44: =+$B$16 -> 0 | R44: =IFERROR((Q44/G44)^(1/COUNT($G$4:$Q$4))-1,"")
A46: x | B46: Total Water Consumption | G46: 2014 | H46: =+G46+1 -> 2015 | I46: =+H46+1 -> 2016 | J46: =+I46+1 -> 2017 | K46: =+J46+1 -> 2018 | L46: =+K46+1 -> 2019 | M46: =+L46+1 -> 2020 | N46: =+M46+1 -> 2021 | O46: =+N46+1 -> 2022 | ... Q46: =+P46+1 -> 2024 | R46: ="CAGR "&$G$4&" - "&$Q$4 -> CAGR 2014 - 2024
B48: =+$B$6 -> UBER TECHNOLOGIES, INC. | R48: =IFERROR((Q48/G48)^(1/COUNT($G$4:$Q$4))-1,"")
B49: =+$B$7 -> LYFT INC. | R49: =IFERROR((Q49/G49)^(1/COUNT($G$4:$Q$4))-1,"")
B50: =+$B$8 -> DOORDASH INC. | R50: =IFERROR((Q50/G50)^(1/COUNT($G$4:$Q$4))-1,"")
B51: =+$B$9 -> GRAB HOLDINGS LIMITED | R51: =IFERROR((Q51/G51)^(1/COUNT($G$4:$Q$4))-1,"")
B52: =+$B$10 -> DELIVERY HERO SE | R52: =IFERROR((Q52/G52)^(1/COUNT($G$4:$Q$4))-1,"")
B53: =+$B$11 -> DiDi GLOBAL INC. | R53: =IFERROR((Q53/G53)^(1/COUNT($G$4:$Q$4))-1,"")
B54: =+$B$12 -> MEITUAN | R54: =IFERROR((Q54/G54)^(1/COUNT($G$4:$Q$4))-1,"")
B55: =+$B$13 -> DELIVEROO PLC | R55: =IFERROR((Q55/G55)^(1/COUNT($G$4:$Q$4))-1,"")
B56: =+$B$14 -> JUST EAT TAKEAWAY | R56: =IFERROR((Q56/G56)^(1/COUNT($G$4:$Q$4))-1,"")
B57: =+$B$15 -> HERTZ GLOBAL HOLDINGS INC. | R57: =IFERROR((Q57/G57)^(1/COUNT($G$4:$Q$4))-1,"")
B58: =+$B$16 -> 0 | R58: =IFERROR((Q58/G58)^(1/COUNT($G$4:$Q$4))-1,"")
A60: x | B60: Total Waste Production | G60: 2014 | H60: =+G60+1 -> 2015 | I60: =+H60+1 -> 2016 | J60: =+I60+1 -> 2017 | K60: =+J60+1 -> 2018 | L60: =+K60+1 -> 2019 | M60: =+L60+1 -> 2020 | N60: =+M60+1 -> 2021 | O60: =+N60+1 -> 2022 | ... Q60: =+P60+1 -> 2024 | R60: ="CAGR "&$G$4&" - "&$Q$4 -> CAGR 2014 - 2024
B62: =+$B$6 -> UBER TECHNOLOGIES, INC. | R62: =IFERROR((Q62/G62)^(1/COUNT($G$4:$Q$4))-1,"")
B63: =+$B$7 -> LYFT INC. | R63: =IFERROR((Q63/G63)^(1/COUNT($G$4:$Q$4))-1,"")
B64: =+$B$8 -> DOORDASH INC. | R64: =IFERROR((Q64/G64)^(1/COUNT($G$4:$Q$4))-1,"")
B65: =+$B$9 -> GRAB HOLDINGS LIMITED | R65: =IFERROR((Q65/G65)^(1/COUNT($G$4:$Q$4))-1,"")
B66: =+$B$10 -> DELIVERY HERO SE | R66: =IFERROR((Q66/G66)^(1/COUNT($G$4:$Q$4))-1,"")
B67: =+$B$11 -> DiDi GLOBAL INC. | R67: =IFERROR((Q67/G67)^(1/COUNT($G$4:$Q$4))-1,"")
B68: =+$B$12 -> MEITUAN | K68: 2 | L68: 5 | M68: 4 | N68: 7 | O68: 8 | P68: 9 | R68: =IFERROR((Q68/G68)^(1/COUNT($G$4:$Q$4))-1,"")
B69: =+$B$13 -> DELIVEROO PLC | R69: =IFERROR((Q69/G69)^(1/COUNT($G$4:$Q$4))-1,"")
B70: =+$B$14 -> JUST EAT TAKEAWAY | R70: =IFERROR((Q70/G70)^(1/COUNT($G$4:$Q$4))-1,"")
B71: =+$B$15 -> HERTZ GLOBAL HOLDINGS INC. | R71: =IFERROR((Q71/G71)^(1/COUNT($G$4:$Q$4))-1,"")
B72: =+$B$16 -> 0 | R72: =IFERROR((Q72/G72)^(1/COUNT($G$4:$Q$4))-1,"")
A74: x | B74: GHG Scope 1 and 2 Emissions | G74: 2014 | H74: =+G74+1 -> 2015 | I74: =+H74+1 -> 2016 | J74: =+I74+1 -> 2017 | K74: =+J74+1 -> 2018 | L74: =+K74+1 -> 2019 | M74: =+L74+1 -> 2020 | N74: =+M74+1 -> 2021 | O74: =+N74+1 -> 2022 | ... Q74: =+P74+1 -> 2024 | R74: ="CAGR "&$G$4&" - "&$Q$4 -> CAGR 2014 - 2024
B76: =+$B$6 -> UBER TECHNOLOGIES, INC. | G76: =+G6+G20 -> 0 | H76: =+H6+H20 -> 0 | I76: =+I6+I20 -> 0 | J76: =+J6+J20 -> 0 | K76: =+K6+K20 -> 0 | L76: =+L6+L20 -> 3 | M76: =+M6+M20 -> 1 | N76: =+N6+N20 -> 62 | ... Q76: =+Q6+Q20 -> 0 | R76: =IFERROR((Q76/G76)^(1/COUNT($G$4:$Q$4))-1,"")
B77: =+$B$7 -> LYFT INC. | G77: =+G7+G21 -> 0 | H77: =+H7+H21 -> 0 | I77: =+I7+I21 -> 0 | J77: =+J7+J21 -> 0 | K77: =+K7+K21 -> 2 | L77: =+L7+L21 -> 3 | M77: =+M7+M21 -> 3 | N77: =+N7+N21 -> 2 | ... Q77: =+Q7+Q21 -> 0 | R77: =IFERROR((Q77/G77)^(1/COUNT($G$4:$Q$4))-1,"")
B78: =+$B$8 -> DOORDASH INC. | G78: =+G8+G22 -> 0 | H78: =+H8+H22 -> 0 | I78: =+I8+I22 -> 0 | J78: =+J8+J22 -> 0 | K78: =+K8+K22 -> 0 | L78: =+L8+L22 -> 0 | M78: =+M8+M22 -> 0 | N78: =+N8+N22 -> 1 | ... Q78: =+Q8+Q22 -> 0 | R78: =IFERROR((Q78/G78)^(1/COUNT($G$4:$Q$4))-1,"")
B79: =+$B$9 -> GRAB HOLDINGS LIMITED | G79: =+G9+G23 -> 0 | H79: =+H9+H23 -> 0 | I79: =+I9+I23 -> 0 | J79: =+J9+J23 -> 0 | K79: =+K9+K23 -> 0 | L79: =+L9+L23 -> 9 | M79: =+M9+M23 -> 6 | N79: =+N9+N23 -> 9 | ... Q79: =+Q9+Q23 -> 0 | R79: =IFERROR((Q79/G79)^(1/COUNT($G$4:$Q$4))-1,"")
B80: =+$B$10 -> DELIVERY HERO SE | G80: =+G10+G24 -> 0 | H80: =+H10+H24 -> 0 | I80: =+I10+I24 -> 0 | J80: =+J10+J24 -> 0 | K80: =+K10+K24 -> 0 | L80: =+L10+L24 -> 0 | M80: =+M10+M24 -> 3 | N80: =+N10+N24 -> 60 | ... Q80: =+Q10+Q24 -> 0 | R80: =IFERROR((Q80/G80)^(1/COUNT($G$4:$Q$4))-1,"")
B81: =+$B$11 -> DiDi GLOBAL INC. | G81: =+G11+G25 -> 0 | H81: =+H11+H25 -> 0 | I81: =+I11+I25 -> 0 | J81: =+J11+J25 -> 0 | K81: =+K11+K25 -> 0 | L81: =+L11+L25 -> 0 | M81: =+M11+M25 -> 0 | N81: =+N11+N25 -> 0 | ... Q81: =+Q11+Q25 -> 0 | R81: =IFERROR((Q81/G81)^(1/COUNT($G$4:$Q$4))-1,"")
B82: =+$B$12 -> MEITUAN | G82: =+G12+G26 -> 0 | H82: =+H12+H26 -> 0 | I82: =+I12+I26 -> 0 | J82: =+J12+J26 -> 0 | K82: =+K12+K26 -> 9 | L82: =+L12+L26 -> 0 | M82: =+M12+M26 -> 0 | N82: =+N12+N26 -> 0 | ... Q82: =+Q12+Q26 -> 0 | R82: =IFERROR((Q82/G82)^(1/COUNT($G$4:$Q$4))-1,"")
B83: =+$B$13 -> DELIVEROO PLC | G83: =+G13+G27 -> 0 | H83: =+H13+H27 -> 0 | I83: =+I13+I27 -> 0 | J83: =+J13+J27 -> 0 | K83: =+K13+K27 -> 0 | L83: =+L13+L27 -> 0 | M83: =+M13+M27 -> 0 | N83: =+N13+N27 -> 2 | ... Q83: =+Q13+Q27 -> 10 | R83: =IFERROR((Q83/G83)^(1/COUNT($G$4:$Q$4))-1,"")
B84: =+$B$14 -> JUST EAT TAKEAWAY | G84: =+G14+G28 -> 0 | H84: =+H14+H28 -> 0 | I84: =+I14+I28 -> 0 | J84: =+J14+J28 -> 0 | K84: =+K14+K28 -> 0 | L84: =+L14+L28 -> 0 | M84: =+M14+M28 -> 6 | N84: =+N14+N28 -> 11 | ... Q84: =+Q14+Q28 -> 9 | R84: =IFERROR((Q84/G84)^(1/COUNT($G$4:$Q$4))-1,"")
B85: =+$B$15 -> HERTZ GLOBAL HOLDINGS INC. | G85: =+G15+G29 -> 0 | H85: =+H15+H29 -> 0 | I85: =+I15+I29 -> 0 | J85: =+J15+J29 -> 0 | K85: =+K15+K29 -> 0 | L85: =+L15+L29 -> 6528 | M85: =+M15+M29 -> 112 | N85: =+N15+N29 -> 0 | ... Q85: =+Q15+Q29 -> 0 | R85: =IFERROR((Q85/G85)^(1/COUNT($G$4:$Q$4))-1,"")
B86: =+$B$16 -> 0 | G86: =+G16+G30 -> 0 | H86: =+H16+H30 -> 0 | I86: =+I16+I30 -> 0 | J86: =+J16+J30 -> 0 | K86: =+K16+K30 -> 0 | L86: =+L16+L30 -> 11 | M86: =+M16+M30 -> 10 | N86: =+N16+N30 -> 9 | ... Q86: =+Q16+Q30 -> 0 | R86: =IFERROR((Q86/G86)^(1/COUNT($G$4:$Q$4))-1,"")

Sheet DCF
B2: DCF
A4: x | B4: Key Assumptions | R4: #VALUE!
B6: Switches | E6: Bear Case | H6: Base Case | K6: Bull Case | X6: FCFF | Y6: FCFE | Z6: Tax Shield | AA6: Total Payout | AB6: NOPAT | AC6: Debt Borrowing | AD6: Cash Balance | AE6: Total Assets | AF6: Total Liabilities | AG6: Shareholder's Equity | AH6: Current Liabilities | AI6: Current Assets
B7: Revenue | C7: 2 | E7: Revenue | F7: -0.02 | H7: Revenue | K7: Revenue | L7: 0.02 | S7: Most Recent Fiscal Year | T7: 2024 | W7: 2022 | X7: =+E188 -> 556.17844 | Y7: =+E240 -> -6628 | Z7: =+H212 -> 139.97729 | AA7: =+E253 -> 347 | AB7: =+E178 -> -1796.8216 | AC7: =+E238 -> 264 | AD7: =+E84 -> 4311
B8: EBIT | C8: 2 | E8: EBIT | F8: -0.01 | H8: EBIT | K8: EBIT | L8: 0.01 | S8: End of Fiscal Year | T8: 31/12/2024 | W8: =+W7+1 -> 2023 | X8: =+F188 -> 3402.1344 | Y8: =+F240 -> 10197 | Z8: =+I212 -> 17.383716 | AA8: =+F253 -> 130 | AB8: =+F178 -> 1008.1344 | AC8: =+F238 -> 5695 | AD8: =+F84 -> 5407
B9: WACC | C9: 2 | E9: WACC | F9: =IFERROR(+I9+0.5%,"") -> 0.11774652 | H9: WACC | I9: =WACC!G25 -> 0.11274652 | K9: WACC | L9: =IFERROR(I9-0.5%,"") -> 0.10774652 | S9: Most Recent Quarter End Date | T9: 31/03/2025 | W9: =+W8+1 -> 2024 | X9: =+G188 -> 11040.065 | Y9: =+G240 -> 22347 | Z9: =+J212 -> 17.17166 | AA9: =+G253 -> -1096 | AB9: =+G178 -> 6706.0647 | AC9: =+G238 -> 8130 | AD9: =+G84 -> 6977 | AE9: =Inputs!Q48 -> 51244 | AF9: =+Inputs!Q60 -> 28768 | AG9: =+AE9-AF9 -> 22476 | AH9: =+Inputs!Q54 -> 11476 | AI9: =+Inputs!Q38 -> 12245
B10: TGR | C10: 2 | E10: TGR | F10: =+I10-0.5% -> 0.025 | H10: TGR | I10: 0.03 | K10: TGR | L10: =+I10+0.5% -> 0.035 | S10: Valuation Date | T10: 23/04/2025 | W10: =+W9+1 -> 2025 | X10: =+H188 -> 4175.9664 | Y10: =+H240 -> 4638.0212 | Z10: =+K212 -> 62.832835 | AA10: =+H253 -> 0 | AB10: =+H178 -> 2204.012 | AC10: =+H238 -> 1150 | AD10: =+H84 -> 4688.5112 | AE10: =Inputs!Q48+DCF!H84+DCF!H86+DCF!H89+DCF!H92+DCF!H95+DCF!H101-DCF!G84-DCF!G86-DCF!G89-DCF!G92-DCF!G95-DCF!G101 -> 52110.914 | AF10: =+Inputs!Q60+(DCF!H106+DCF!H109+DCF!H112+DCF!H114*DCF!G106*DCF!G109*DCF!G112*DCF!G114) -> 4.6773794e+17 | AG10: =+AE10-AF10 -> -4.6773794e+17 | AH10: =+AH9+H106+H109-G106-G109 -> 12730.345 | AI10: =+H84+H86+H89+H92 -> 12239.447
W11: =+W10+1 -> 2026 | X11: =+I188 -> 6797.9969 | Y11: =+I240 -> 7211.219 | Z11: =+L212 -> 24.746989 | AA11: =+I253 -> 0 | AB11: =+I178 -> 4009.5308 | AC11: =+I238 -> 0 | AD11: =+I84 -> 5384.0151 | AE11: =AE10+DCF!I84+DCF!I86+DCF!I89+DCF!I92+DCF!I95+DCF!I101-DCF!H84-DCF!H86-DCF!H89-DCF!H92-DCF!H95-DCF!H101 -> 52881.86 | AF11: =AF10+(DCF!I106+DCF!I109+DCF!I112+DCF!I114*DCF!H106*DCF!H109*DCF!H112*DCF!H114) -> 1.5022643e+18 | AG11: =+AE11-AF11 -> -1.5022643e+18 | AH11: =+AH10+I106+I109-H106-H109 -> 12420.195 | AI11: =+I84+I86+I89+I92 -> 13141.119
B12: WACC | C12: =CHOOSE(C9,F9,I9,L9) -> 0.11274652 | W12: =+W11+1 -> 2027 | X12: =+J188 -> 9152.6815 | Y12: =+J240 -> 9665.4186 | Z12: =+M212 -> 17.80973 | AA12: =+J253 -> 0 | AB12: =+J178 -> 4729.4643 | AC12: =+J238 -> 700 | AD12: =+J84 -> 7470.6572
B13: TGR | C13: =CHOOSE(C10,F10,I10,L10) -> 0.03 | W13: =+W12+1 -> 2028 | X13: =+K188 -> 8099.7704 | Y13: =+K240 -> 9555.7048 | Z13: =+N212 -> 18.95831 | AA13: =+K253 -> 0 | AB13: =+K178 -> 4360.534 | AC13: =+K238 -> 2225 | AD13: =+K84 -> 10519.134
W14: =+W13+1 -> 2029 | X14: =+L188 -> 9622.6828 | Y14: =+L240 -> 14043.19 | Z14: =+O212 -> 19.633741 | AA14: =+L253 -> 0 | AB14: =+L178 -> 5232.9484 | AC14: =+L238 -> 5100 | AD14: =+L84 -> 17142.806
A15: x | B15: Operating Assumptions | E15: 2022 | F15: =+E15+1 -> 2023 | G15: =+F15+1 -> 2024 | H15: =+G15+1 -> 2025 | I15: =+H15+1 -> 2026 | J15: =+I15+1 -> 2027 | K15: =+J15+1 -> 2028 | L15: =+K15+1 -> 2029 | M15: =+L15+1 -> 2030 | ... Q15: =+P15+1 -> 2034
B17: Yearly Active Platform Consumers | E17: =115*4+122*4+124*4+131+4 -> 1579 | F17: =130*4+137*4+142*4+150*4 -> 2236 | G17: =(149*4)+(156*4)+(161*4)+(171*4) -> 2548 | H17: =G17*(1+H18) -> 2751.84 | I17: =H17*(1+I18) -> 2971.9872 | J17: =I17*(1+J18) -> 3209.7462 | K17: =J17*(1+K18) -> 3466.5259 | L17: =K17*(1+L18) -> 3743.8479 | M17: =L17*(1+M18) -> 4043.3558 | N17: =M17*(1+N18) -> 4366.8242 | O17: =N17*(1+O18) -> 4716.1702 | ... Q17: =P17*(1+Q18) -> 5500.9409
B18: % growth | F18: =+F17/E17-1 -> 0.41608613 | G18: =+G17/F17-1 -> 0.13953488 | H18: 0.08 | I18: 0.08 | J18: 0.08 | K18: 0.08 | L18: 0.08 | M18: 0.08 | N18: 0.08 | O18: 0.08 | P18: 0.08 | Q18: 0.08 | AF18: =+Inputs!Q60+(DCF!H106+DCF!H109+DCF!H112+DCF!H114+DCF!G106+DCF!G109+DCF!G112+DCF!G114) -> 73103.29
B19: Trip | E19: 7642 | F19: 9448 | G19: 11273 | H19: =H17*H21 -> 12373.583 | I19: =I17*I21 -> 13023.38 | J19: =J17*J21 -> 14232.844 | K19: =K17*K21 -> 15383.031 | L19: =L17*L21 -> 16540.19 | M19: =M17*M21 -> 17911.819 | N19: =N17*N21 -> 19338.477 | O19: =O17*O21 -> 20871.259 | ... Q19: =Q17*Q21 -> 24354.38
B20: Average Revenue per Trip | E20: =E26/E19 -> 4.1712902 | F20: =F26/F19 -> 3.9459145 | G20: =G26/G19 -> 3.9011798 | H20: =(SUM(E20:G20)/3)*(1+0.03) -> 4.126312 | I20: =H20*(1+0.03) -> 4.2501014 | J20: =I20*(1+0.03) -> 4.3776044 | K20: =J20*(1+0.03) -> 4.5089326 | L20: =K20*(1+0.03) -> 4.6442005 | M20: =L20*(1+0.03) -> 4.7835265 | N20: =M20*(1+0.03) -> 4.9270323 | O20: =N20*(1+0.03) -> 5.0748433 | P20: =O20*(1+0.03) -> 5.2270886 | Q20: =P20*(1+0.03) -> 5.3839013
B21: Average Trip per MAPC | E21: =E19/E17 -> 4.839772 | F21: =F19/F17 -> 4.2254025 | G21: =G19/G17 -> 4.4242543 | H21: =(G21+F21+E21)/3 -> 4.4964763 | I21: =(H21+G21+F21)/3 -> 4.3820444 | J21: =(I21+H21+G21)/3 -> 4.4342583 | K21: =(J21+I21+H21)/3 -> 4.437593 | L21: =(K21+J21+I21)/3 -> 4.4179652 | M21: =(L21+K21+J21)/3 -> 4.4299388 | N21: =(M21+L21+K21)/3 -> 4.428499 | O21: =(N21+M21+L21)/3 -> 4.4254677 | ... Q21: =(P21+O21+N21)/3 -> 4.4273117
B22: Revenue for Mobility and Delivery | E22: =E19*E20 -> 31877 | F22: =F19*F20 -> 37281 | G22: =G19*G20 -> 43978 | H22: =H19*H20 -> 51057.265 | I22: =I19*I20 -> 55350.684 | J22: =J19*J20 -> 62305.759 | K22: =K19*K20 -> 69361.049 | L22: =L19*L20 -> 76815.959 | ... Q22: =Q19*Q20 -> 131121.58
B23: Freight Revenue | E23: 6947 | F23: 5245 | G23: 5141 | H23: 5000 | I23: =H23*(1+0.15) -> 5750 | J23: =I23*(1+0.15) -> 6612.5 | K23: =J23*(1+0.15) -> 7604.375 | L23: =K23*(1+0.15) -> 8745.0312 | M23: =L23*(1+0.15) -> 10056.786 | N23: =M23*(1+0.15) -> 11565.304 | O23: =N23*(1+0.15) -> 13300.099 | P23: =O23*(1+0.15) -> 15295.114 | Q23: =P23*(1+0.15) -> 17589.381
A24: x | B24: Income Statement | E24: 2022 | F24: =+E24+1 -> 2023 | G24: =+F24+1 -> 2024 | H24: =+G24+1 -> 2025 | I24: =+H24+1 -> 2026 | J24: =+I24+1 -> 2027 | K24: =+J24+1 -> 2028 | L24: =+K24+1 -> 2029 | M24: =+L24+1 -> 2030 | ... Q24: =+P24+1 -> 2034
B26: Revenue (Sales) | D26: =+_xlfn.XLOOKUP($B26,Inputs!$B:$B,Inputs!N:N) -> 17455 | E26: =+_xlfn.XLOOKUP($B26,Inputs!$B:$B,Inputs!O:O) -> 31877 | F26: =+_xlfn.XLOOKUP($B26,Inputs!$B:$B,Inputs!P:P) -> 37281 | G26: =+_xlfn.XLOOKUP($B26,Inputs!$B:$B,Inputs!Q:Q) -> 43978 | H26: =H22+H23 -> 56057.265 | I26: =I22+I23 -> 61100.684 | J26: =J22+J23 -> 68918.259 | K26: =K22+K23 -> 76965.424 | L26: =L22+L23 -> 85560.99 | M26: =M22+M23 -> 95738.447 | N26: =N22+N23 -> 106846.6 | O26: =O22+O23 -> 119218.47 | ... Q26: =Q22+Q23 -> 148710.96
B27: % of growth | E27: =IFERROR((E26-D26)/D26,"") -> 0.8262389 | F27: =IFERROR((F26-E26)/E26,"") -> 0.16952662 | G27: =IFERROR((G26-F26)/F26,"") -> 0.17963574 | H27: =IFERROR(H26/G26-1,"") -> 0.27466609 | I27: =IFERROR(I26/H26-1,"") -> 0.08996905 | J27: =IFERROR(J26/I26-1,"") -> 0.12794579 | K27: =IFERROR(K26/J26-1,"") -> 0.11676389 | L27: =IFERROR(L26/K26-1,"") -> 0.11168089 | M27: =IFERROR(M26/L26-1,"") -> 0.11894972 | N27: =IFERROR(N26/M26-1,"") -> 0.11602609 | O27: =IFERROR(O26/N26-1,"") -> 0.11579088 | ... Q27: =IFERROR(Q26/P26-1,"") -> 0.11657197
B29: COGS (Cost of Goods Sold) | E29: =+_xlfn.XLOOKUP($B29,Inputs!$B:$B,Inputs!O:O) -> 19659 | F29: =+_xlfn.XLOOKUP($B29,Inputs!$B:$B,Inputs!P:P) -> 22457 | G29: =+_xlfn.XLOOKUP($B29,Inputs!$B:$B,Inputs!Q:Q) -> 26651 | H29: =H30*H$26 -> 34103.24 | I29: =I30*I$26 -> 37001.415 | J29: =J30*J$26 -> 41809.329 | K29: =K30*K$26 -> 46707.655 | L29: =L30*L$26 -> 51881.259 | M29: =M30*M$26 -> 58077.565 | N29: =N30*N$26 -> 64815.239 | O29: =O30*O$26 -> 72310.481 | ... Q29: =Q30*Q$26 -> 90205.688
B30: % of revenue | E30: =IFERROR(E29/E$26,"") -> 0.61671425 | F30: =IFERROR(F29/F$26,"") -> 0.60237118 | G30: =IFERROR(G29/G$26,"") -> 0.60600755 | H30: =SUM(E30:G30)/3 -> 0.60836433 | I30: =SUM(F30:H30)/3 -> 0.60558102 | J30: =SUM(G30:I30)/3 -> 0.60665096 | K30: =SUM(H30:J30)/3 -> 0.60686544 | L30: =SUM(I30:K30)/3 -> 0.60636581 | M30: =SUM(J30:L30)/3 -> 0.6066274 | N30: =SUM(K30:M30)/3 -> 0.60661955 | O30: =SUM(L30:N30)/3 -> 0.60653759 | ... Q30: =SUM(N30:P30)/3 -> 0.60658399
B32: Gross Profit | E32: =+_xlfn.XLOOKUP($B32,Inputs!$B:$B,Inputs!O:O) -> 12218 | F32: =+_xlfn.XLOOKUP($B32,Inputs!$B:$B,Inputs!P:P) -> 14824 | G32: =+_xlfn.XLOOKUP($B32,Inputs!$B:$B,Inputs!Q:Q) -> 17327 | H32: =+H26-H29 -> 21954.025 | I32: =+I26-I29 -> 24099.27 | J32: =+J26-J29 -> 27108.931 | K32: =+K26-K29 -> 30257.768 | L32: =+L26-L29 -> 33679.731 | M32: =+M26-M29 -> 37660.882 | N32: =+N26-N29 -> 42031.366 | O32: =+O26-O29 -> 46907.986 | ... Q32: =+Q26-Q29 -> 58505.272
B33: Gross Profit Margin | E33: =IFERROR(E32/E$26,"") -> 0.38328575 | F33: =IFERROR(F32/F$26,"") -> 0.39762882 | G33: =IFERROR(G32/G$26,"") -> 0.39399245 | H33: =IFERROR(H32/H$26,"") -> 0.39163567 | I33: =IFERROR(I32/I$26,"") -> 0.39441898 | J33: =IFERROR(J32/J$26,"") -> 0.39334904 | K33: =IFERROR(K32/K$26,"") -> 0.39313456 | L33: =IFERROR(L32/L$26,"") -> 0.39363419 | ... Q33: =IFERROR(Q32/Q$26,"") -> 0.39341601
B35: SG&A (Selling, General & Administrative) | E35: =+_xlfn.XLOOKUP($B35,Inputs!$B:$B,Inputs!O:O) -> 7892 | F35: =+_xlfn.XLOOKUP($B35,Inputs!$B:$B,Inputs!P:P) -> 7038 | G35: =+_xlfn.XLOOKUP($B35,Inputs!$B:$B,Inputs!Q:Q) -> 7976 | H35: =H36*H26 -> 10141.32 | I35: =I36*I26 -> 11026.091 | J35: =J36*J26 -> 12405.74 | K35: =K36*K26 -> 13819.647 | L35: =L36*L26 -> 15324.63 | M35: =M36*M26 -> 17104.622 | N35: =N36*N26 -> 19041.481 | O35: =O36*O26 -> 21193.195 | ... Q35: =Q36*Q26 -> 26303.994
B36: SG&A Margin | E36: =IFERROR(E35/E$26,"") -> 0.24757662 | F36: =IFERROR(F35/F$26,"") -> 0.18878249 | G36: =IFERROR(G35/G$26,"") -> 0.18136341 | H36: =G36*(1-0.0025) -> 0.18091 | I36: =H36*(1-0.0025) -> 0.18045773 | J36: =I36*(1-0.0025) -> 0.18000658 | K36: =J36*(1-0.0025) -> 0.17955656 | L36: =K36*(1-0.0025) -> 0.17910767 | M36: =L36*(1-0.0025) -> 0.1786599 | N36: =M36*(1-0.0025) -> 0.17821325 | O36: =N36*(1-0.0025) -> 0.17776772 | ... Q36: =P36*(1-0.0025) -> 0.17687999
B38: R&D (Research & Development) | E38: =+_xlfn.XLOOKUP($B38,Inputs!$B:$B,Inputs!O:O) -> 2798 | F38: =+_xlfn.XLOOKUP($B38,Inputs!$B:$B,Inputs!P:P) -> 3164 | G38: =+_xlfn.XLOOKUP($B38,Inputs!$B:$B,Inputs!Q:Q) -> 3109 | H38: =H39*H$26 -> 4546.9597 | I38: =I39*I$26 -> 4820.3586 | J38: =J39*J$26 -> 5299.7971 | K38: =K39*K$26 -> 6077.8203 | L38: =L39*L$26 -> 6695.4327 | M38: =M39*M$26 -> 7471.4691 | N38: =N39*N$26 -> 8378.9802 | O38: =O39*O$26 -> 9327.4307 | ... Q38: =Q39*Q$26 -> 11643.665
B39: % of revenue | E39: =IFERROR(E38/E26,"") -> 0.087774885 | F39: =IFERROR(F38/F26,"") -> 0.084868968 | G39: =IFERROR(G38/G26,"") -> 0.070694438 | H39: =AVERAGE(E39:G39) -> 0.081112764 | I39: =AVERAGE(F39:H39) -> 0.078892057 | J39: =AVERAGE(G39:I39) -> 0.076899753 | K39: =AVERAGE(H39:J39) -> 0.078968191 | L39: =AVERAGE(I39:K39) -> 0.078253333 | M39: =AVERAGE(J39:L39) -> 0.078040426 | N39: =AVERAGE(K39:M39) -> 0.07842065 | O39: =AVERAGE(L39:N39) -> 0.078238136 | ... Q39: =AVERAGE(N39:P39) -> 0.078297286
B41: Other Operating (Income) Expenses | E41: =+_xlfn.XLOOKUP($B41,Inputs!$B:$B,Inputs!O:O) -> 2413 | F41: =+_xlfn.XLOOKUP($B41,Inputs!$B:$B,Inputs!P:P) -> 2689 | G41: =+_xlfn.XLOOKUP($B41,Inputs!$B:$B,Inputs!Q:Q) -> 2732 | H41: =IFERROR(AVERAGE(E41:G41)*(1+H27),"") -> 3328.5781 | I41: =IFERROR(AVERAGE(F41:H41)*(1+I27),"") -> 3178.9231 | J41: =IFERROR(AVERAGE(G41:I41)*(1+J27),"") -> 3473.8855 | K41: =IFERROR(AVERAGE(H41:J41)*(1+K27),"") -> 3715.6174 | L41: =IFERROR(AVERAGE(I41:K41)*(1+L27),"") -> 3842.127 | M41: =IFERROR(AVERAGE(J41:L41)*(1+M27),"") -> 4114.6131 | N41: =IFERROR(AVERAGE(K41:M41)*(1+N27),"") -> 4342.2185 | O41: =IFERROR(AVERAGE(L41:N41)*(1+O27),"") -> 4574.3553 | ... Q41: =IFERROR(AVERAGE(N41:P41)*(1+Q27),"") -> 5124.7617
B43: EBITDA | E43: =+_xlfn.XLOOKUP($B43,Inputs!$B:$B,Inputs!O:O) -> -885 | F43: =+_xlfn.XLOOKUP($B43,Inputs!$B:$B,Inputs!P:P) -> 1933 | G43: =+_xlfn.XLOOKUP($B43,Inputs!$B:$B,Inputs!Q:Q) -> 3510 | H43: =IFERROR(H32-H35-H38-H41,"") -> 3937.1673 | I43: =IFERROR(I32-I35-I38-I41,"") -> 5073.8974 | J43: =IFERROR(J32-J35-J38-J41,"") -> 5929.5081 | K43: =IFERROR(K32-K35-K38-K41,"") -> 6644.6835 | L43: =IFERROR(L32-L35-L38-L41,"") -> 7817.5419 | M43: =IFERROR(M32-M35-M38-M41,"") -> 8970.1776 | N43: =IFERROR(N32-N35-N38-N41,"") -> 10268.686 | O43: =IFERROR(O32-O35-O38-O41,"") -> 11813.005 | ... Q43: =IFERROR(Q32-Q35-Q38-Q41,"") -> 15432.852
B44: EBITDA Margin | E44: =IFERROR(E43/E$26,"") -> -0.027762964 | F44: =IFERROR(F43/F$26,"") -> 0.051849468 | G44: =IFERROR(G43/G$26,"") -> 0.079812634 | H44: =IFERROR(H43/H$26,"") -> 0.070234737 | I44: =IFERROR(I43/I$26,"") -> 0.083041581 | J44: =IFERROR(J43/J$26,"") -> 0.086036822 | K44: =IFERROR(K43/K$26,"") -> 0.086333359 | L44: =IFERROR(L43/L$26,"") -> 0.091368062 | ... Q44: =IFERROR(Q43/Q$26,"") -> 0.1037775
B46: D&A (Depreciation & Amortization) | E46: =+_xlfn.XLOOKUP($B46,Inputs!$B:$B,Inputs!O:O) -> 947 | F46: =+_xlfn.XLOOKUP($B46,Inputs!$B:$B,Inputs!P:P) -> 823 | G46: =+_xlfn.XLOOKUP($B46,Inputs!$B:$B,Inputs!Q:Q) -> 711 | H46: =+IFERROR(H49+H52,"") -> 841.93942 | I46: =+IFERROR(I49+I52,"") -> 905.65713 | J46: =+IFERROR(J49+J52,"") -> 983.7585 | K46: =+IFERROR(K49+K52,"") -> 1102.8808 | L46: =+IFERROR(L49+L52,"") -> 1193.5565 | M46: =+IFERROR(M49+M52,"") -> 1311.135 | N46: =+IFERROR(N49+N52,"") -> 1446.1972 | O46: =+IFERROR(O49+O52,"") -> 1586.8336 | ... Q46: =+IFERROR(Q49+Q52,"") -> 1928.1158
B47: % of PP&E+ROU Assets+Intangibles excl. Goodwill | E47: =IFERROR(E46/AVERAGE(Inputs!O39+Inputs!O42+Inputs!O45,Inputs!N39+Inputs!N42+Inputs!N45),"") -> 0.13630802 | F47: =IFERROR(F46/AVERAGE(Inputs!P39+Inputs!P42+Inputs!P45,Inputs!O39+Inputs!O42+Inputs!O45),"") -> 0.12825308 | G47: =IFERROR(G46/AVERAGE(Inputs!Q39+Inputs!Q42+Inputs!Q45,Inputs!P39+Inputs!P42+Inputs!P45),"") -> 0.12503297 | H47: =IFERROR(H46/(G95+G101),"") -> 0.15611708 | I47: =IFERROR(I46/(H95+H101),"") -> 0.14454743 | J47: =IFERROR(J46/(I95+I101),"") -> 0.1603586 | K47: =IFERROR(K46/(J95+J101),"") -> 0.17457981 | L47: =IFERROR(L46/(K95+K101),"") -> 0.18000134 | M47: =IFERROR(M46/(L95+L101),"") -> 0.19290629 | N47: =IFERROR(N46/(M95+M101),"") -> 0.2034975 | O47: =IFERROR(O46/(N95+N101),"") -> 0.21241935 | ... Q47: =IFERROR(Q46/(P95+P101),"") -> 0.23195667
B49: Depreciation Expense | E49: =+_xlfn.XLOOKUP($B49,Inputs!$B:$B,Inputs!O:O) -> 792 | F49: =+_xlfn.XLOOKUP($B49,Inputs!$B:$B,Inputs!P:P) -> 461 | G49: =+_xlfn.XLOOKUP($B49,Inputs!$B:$B,Inputs!Q:Q) -> 417 | H49: =IFERROR(H50*(G96+G97),"") -> 541.93942 | I49: =IFERROR(I50*(H96+H97),"") -> 553.94073 | J49: =IFERROR(J50*(I96+I97),"") -> 587.04147 | K49: =IFERROR(K50*(J96+J97),"") -> 659.84152 | L49: =IFERROR(L50*(K96+K97),"") -> 701.03825 | M49: =IFERROR(M50*(L96+L97),"") -> 760.03181 | N49: =IFERROR(N50*(M96+M97),"") -> 831.1517 | O49: =IFERROR(O50*(N96+N97),"") -> 900.57139 | ... Q49: =IFERROR(Q50*(P96+P97),"") -> 1072.0847
B50: % of PP&E+ROU Assets | E50: =IFERROR(E49/AVERAGE(Inputs!O40+Inputs!O42,Inputs!N40+Inputs!N42),"") -> 0.13116926 | F50: =IFERROR(F49/AVERAGE(Inputs!P40+Inputs!P42,Inputs!O40+Inputs!O42),"") -> 0.075443908 | G50: =IFERROR(G49/AVERAGE(Inputs!Q40+Inputs!Q42,Inputs!P40+Inputs!P42),"") -> 0.070546439 | H50: =IFERROR(AVERAGE(E50:G50),"") -> 0.092386536 | I50: =IFERROR(AVERAGE(F50:H50),"") -> 0.079458961 | J50: =IFERROR(AVERAGE(G50:I50),"") -> 0.080797312 | K50: =IFERROR(AVERAGE(H50:J50),"") -> 0.08421427 | L50: =IFERROR(AVERAGE(I50:K50),"") -> 0.081490181 | M50: =IFERROR(AVERAGE(J50:L50),"") -> 0.082167254 | N50: =IFERROR(AVERAGE(K50:M50),"") -> 0.082623902 | O50: =IFERROR(AVERAGE(L50:N50),"") -> 0.082093779 | ... Q50: =IFERROR(AVERAGE(N50:P50),"") -> 0.082337553
B52: Amortization Expense | E52: =+_xlfn.XLOOKUP($B52,Inputs!$B:$B,Inputs!O:O) -> 155 | F52: =+_xlfn.XLOOKUP($B52,Inputs!$B:$B,Inputs!P:P) -> 362 | G52: =+_xlfn.XLOOKUP($B52,Inputs!$B:$B,Inputs!Q:Q) -> 294 | H52: 300 | I52: =H53*I101 -> 351.7164 | J52: =I53*J101 -> 396.71703 | K52: =J53*K101 -> 443.03925 | L52: =K53*L101 -> 492.51827 | M52: =L53*M101 -> 551.10318 | N52: =M53*N101 -> 615.04553 | O52: =N53*O101 -> 686.2622 | P52: =O53*P101 -> 766.65999 | Q52: =P53*Q101 -> 856.03105
B53: % of Intangibles excl. Goodwill | E53: =IFERROR(E52/AVERAGE(Inputs!N45:O45),"") -> 0.072328511 | F53: =IFERROR(F52/AVERAGE(Inputs!O45:P45),"") -> 0.21946044 | G53: =IFERROR(G52/AVERAGE(Inputs!P45:Q45),"") -> 0.23058824 | H53: =AVERAGE(F53:G53) -> 0.22502434 | I53: =I52/I101 -> 0.22502434 | J53: =J52/J101 -> 0.22502434 | K53: =K52/K101 -> 0.22502434 | L53: =L52/L101 -> 0.22502434 | M53: =M52/M101 -> 0.22502434 | N53: =N52/N101 -> 0.22502434 | O53: =O52/O101 -> 0.22502434 | P53: =P52/P101 -> 0.22502434 | Q53: =Q52/Q101 -> 0.22502434
B55: Operating Income (EBIT) | E55: =+_xlfn.XLOOKUP($B55,Inputs!$B:$B,Inputs!O:O) -> -1832 | F55: =+_xlfn.XLOOKUP($B55,Inputs!$B:$B,Inputs!P:P) -> 1110 | G55: =+_xlfn.XLOOKUP($B55,Inputs!$B:$B,Inputs!Q:Q) -> 2799 | H55: =+IFERROR(H43-H46,"") -> 3095.2279 | I55: =+IFERROR(I43-I46,"") -> 4168.2403 | J55: =+IFERROR(J43-J46,"") -> 4945.7496 | K55: =+IFERROR(K43-K46,"") -> 5541.8028 | L55: =+IFERROR(L43-L46,"") -> 6623.9853 | M55: =+IFERROR(M43-M46,"") -> 7659.0426 | N55: =+IFERROR(N43-N46,"") -> 8822.4886 | O55: =+IFERROR(O43-O46,"") -> 10226.171 | ... Q55: =+IFERROR(Q43-Q46,"") -> 13504.736
B56: Operating Margin | E56: =IFERROR(E55/E$26,"") -> -0.057470904 | F56: =IFERROR(F55/F$26,"") -> 0.029773879 | G56: =IFERROR(G55/G$26,"") -> 0.063645459 | H56: =IFERROR(H55/H26,"") -> 0.055215463 | I56: =IFERROR(I55/I26,"") -> 0.068219208 | J56: =IFERROR(J55/J26,"") -> 0.071762543 | K56: =IFERROR(K55/K26,"") -> 0.072003797 | L56: =IFERROR(L55/L26,"") -> 0.077418287 | M56: =IFERROR(M55/M26,"") -> 0.079999654 | N56: =IFERROR(N55/N26,"") -> 0.082571539 | O56: =IFERROR(O55/O26,"") -> 0.085776738 | ... Q56: =IFERROR(Q55/Q26,"") -> 0.090811978
B58: Net Interest Expense (Income) | E58: =+_xlfn.XLOOKUP($B58,Inputs!$B:$B,Inputs!O:O) -> 426 | F58: =+_xlfn.XLOOKUP($B58,Inputs!$B:$B,Inputs!P:P) -> 149 | G58: =+_xlfn.XLOOKUP($B58,Inputs!$B:$B,Inputs!Q:Q) -> -198 | H58: =-H61-H64 -> -1326.9451 | I58: =-I61-I64 -> -716.39671 | J58: =-J61-J64 -> -703.61825 | K58: =-K61-K64 -> -715.30776 | L58: =-L61-L64 -> -669.14762 | M58: =-M61-M64 -> -965.13734 | N58: =-N61-N64 -> -1165.813 | O58: =-O61-O64 -> -1336.8846 | ... Q58: =-Q61-Q64 -> -1780.3892
B59: % of Net Debt | E59: =IFERROR(E58/AVERAGE(Inputs!N117:O117),"") -> 0.059701493 | F59: =IFERROR(F58/AVERAGE(Inputs!O117:P117),"") -> 0.022078981 | G59: =IFERROR(G58/AVERAGE(Inputs!P117:Q117),"") -> -0.049848943 | H59: =IFERROR(H58/AVERAGE(G112+G114,H112+H114),"") -> -0.12789249 | I59: =IFERROR(I58/AVERAGE(H112+H114,I112+I114),"") -> -0.068361868 | J59: =IFERROR(J58/AVERAGE(I112+I114,J112+J114),"") -> -0.068369756 | K59: =IFERROR(K58/AVERAGE(J112+J114,K112+K114),"") -> -0.077007039 | L59: =IFERROR(L58/AVERAGE(K112+K114,L112+L114),"") -> -0.10925772 | M59: =IFERROR(M58/AVERAGE(L112+L114,M112+M114),"") -> -0.28365943 | N59: =IFERROR(N58/AVERAGE(M112+M114,N112+N114),"") -> -0.34625239 | O59: =IFERROR(O58/AVERAGE(N112+N114,O112+O114),"") -> -0.33366892 | ... Q59: =IFERROR(Q58/AVERAGE(P112+P114,Q112+Q114),"") -> -0.4315699
B61: Interest Expense | E61: =+_xlfn.XLOOKUP($B61,Inputs!$B:$B,Inputs!O:O) -> 565 | F61: =+_xlfn.XLOOKUP($B61,Inputs!$B:$B,Inputs!P:P) -> 633 | G61: =+_xlfn.XLOOKUP($B61,Inputs!$B:$B,Inputs!Q:Q) -> 523 | H61: =H62*(H112+H114) -> 489.70508 | I61: =I62*(I112+I114) -> 481.97115 | J61: =J62*(J112+J114) -> 434.4175 | K61: =K62*(K112+K114) -> 341.7749 | L61: =L62*(L112+L114) -> 143.19093 | M61: =M62*(M112+M114) -> 107.99702 | N61: =N62*(N112+N114) -> 121.50431 | O61: =O62*(O112+O114) -> 131.87315 | ... Q61: =Q62*(Q112+Q114) -> 80.803325
B62: % of Debt | E62: =+IFERROR(E61/AVERAGE(Inputs!N114:O114),"") -> 0.049394588 | F62: =+IFERROR(F61/AVERAGE(Inputs!O114:P114),"") -> 0.054533707 | G62: =+IFERROR(G61/AVERAGE(Inputs!P114:Q114),"") -> 0.05145612 | H62: =AVERAGE(E62:G62)-0.005 -> 0.046794805 | I62: =AVERAGE(F62:H62)-0.005 -> 0.04592821 | J62: =AVERAGE(G62:I62)-0.005 -> 0.043059712 | K62: =AVERAGE(H62:J62)-0.005 -> 0.040260909 | L62: =AVERAGE(I62:K62)-0.005 -> 0.038082944 | M62: =AVERAGE(J62:L62)-0.005 -> 0.035467855 | N62: =AVERAGE(K62:M62)-0.005 -> 0.032937236 | O62: =AVERAGE(L62:N62)-0.005 -> 0.030496011 | ... Q62: =AVERAGE(N62:P62)-0.005 -> 0.02546676
B64: Interest Income | E64: =+_xlfn.XLOOKUP($B64,Inputs!$B:$B,Inputs!O:O) -> 139 | F64: =+_xlfn.XLOOKUP($B64,Inputs!$B:$B,Inputs!P:P) -> 484 | G64: =+_xlfn.XLOOKUP($B64,Inputs!$B:$B,Inputs!Q:Q) -> 721 | H64: =+H65*G84 -> 837.24 | I64: =+I65*H84 -> 234.42556 | J64: =+J65*I84 -> 269.20075 | K64: =+K65*J84 -> 373.53286 | L64: =+L65*K84 -> 525.95669 | M64: =+M65*L84 -> 857.14032 | N64: =+N65*M84 -> 1044.3087 | O64: =+O65*N84 -> 1205.0115 | ... Q64: =+Q65*P84 -> 1699.5859
B65: % Cash & Cash Eq. & ST Investments | E65: =IFERROR(E64/+AVERAGE(Inputs!N32:O32),"") -> 0.032303044 | F65: =IFERROR(F64/+AVERAGE(Inputs!O32:P32),"") -> 0.099608973 | G65: =IFERROR(G64/+AVERAGE(Inputs!P32:Q32),"") -> 0.11644057 | H65: 0.12 | I65: 0.05 | J65: 0.05 | K65: 0.05 | L65: 0.05 | M65: 0.05 | N65: 0.05 | O65: 0.05 | P65: 0.05 | Q65: 0.05
B67: FX (Gain) Loss | E67: =+_xlfn.XLOOKUP($B67,Inputs!$B:$B,Inputs!O:O) -> 147 | F67: =+_xlfn.XLOOKUP($B67,Inputs!$B:$B,Inputs!P:P) -> 182 | G67: =+_xlfn.XLOOKUP($B67,Inputs!$B:$B,Inputs!Q:Q) -> 391 | H67: =+H68*H26 -> 610.50897 | I67: =+I68*I26 -> 787.63725 | J67: =+J68*J26 -> 1026.2486 | K67: =+K68*K26 -> 1300.0083 | L67: =+L68*L26 -> 1616.3163 | M67: =+M68*M26 -> 2000.0536 | N67: =+N68*N26 -> 2445.8052 | O67: =+O68*O26 -> 2967.4441 | ... Q67: =+Q68*Q26 -> 4296.38
B68: % of revenue | E68: =E67/E26 -> 0.0046114754 | F68: =F67/F26 -> 0.0048818433 | G68: =G67/G26 -> 0.008890809 | H68: =G68+0.002 -> 0.010890809 | I68: =H68+0.002 -> 0.012890809 | J68: =I68+0.002 -> 0.014890809 | K68: =J68+0.002 -> 0.016890809 | L68: =K68+0.002 -> 0.018890809 | M68: =L68+0.002 -> 0.020890809 | N68: =M68+0.002 -> 0.022890809 | O68: =N68+0.002 -> 0.024890809 | ... Q68: =P68+0.002 -> 0.028890809
B70: Other Non-Operating (Income) Expenses | E70: =+_xlfn.XLOOKUP($B70,Inputs!$B:$B,Inputs!O:O) -> 7021 | F70: =+_xlfn.XLOOKUP($B70,Inputs!$B:$B,Inputs!P:P) -> -1542 | G70: =+_xlfn.XLOOKUP($B70,Inputs!$B:$B,Inputs!Q:Q) -> -1519 | H70: =IFERROR(AVERAGE(E70:G70)*(1+H27),"") -> 1682.5592 | I70: =IFERROR(AVERAGE(F70:H70)*(1+I27),"") -> -500.81925 | J70: =IFERROR(AVERAGE(G70:I70)*(1+J27),"") -> -126.80367 | K70: =IFERROR(AVERAGE(H70:J70)*(1+K27),"") -> 392.70493 | L70: =IFERROR(AVERAGE(I70:K70)*(1+L27),"") -> -87.051281 | M70: =IFERROR(AVERAGE(J70:L70)*(1+M27),"") -> 66.708045 | N70: =IFERROR(AVERAGE(K70:M70)*(1+N27),"") -> 138.52179 | O70: =IFERROR(AVERAGE(L70:N70)*(1+O27),"") -> 43.954184 | ... Q70: =IFERROR(AVERAGE(N70:P70)*(1+Q27),"") -> 102.45226
B72: Pre-Tax Income (EBT) | E72: =+_xlfn.XLOOKUP($B72,Inputs!$B:$B,Inputs!O:O) -> -9426 | F72: =+_xlfn.XLOOKUP($B72,Inputs!$B:$B,Inputs!P:P) -> 2321 | G72: =+_xlfn.XLOOKUP($B72,Inputs!$B:$B,Inputs!Q:Q) -> 4125 | H72: =H55-H58-H67-H70 -> 2129.1047 | I72: =IFERROR(+I55-I58-I67-I70,"") -> 4597.819 | J72: =IFERROR(+J55-J58-J67-J70,"") -> 4749.9228 | K72: =IFERROR(+K55-K58-K67-K70,"") -> 4564.3973 | L72: =IFERROR(+L55-L58-L67-L70,"") -> 5763.8679 | M72: =IFERROR(+M55-M58-M67-M70,"") -> 6557.4183 | N72: =IFERROR(+N55-N58-N67-N70,"") -> 7403.9746 | O72: =IFERROR(+O55-O58-O67-O70,"") -> 8551.6575 | P72: =IFERROR(+P55-P58-P67-P70,"") -> 9649.1361 | Q72: =IFERROR(+Q55-Q58-Q67-Q70,"") -> 10886.293
B74: Tax Expense (Benefits) | E74: =+_xlfn.XLOOKUP($B74,Inputs!$B:$B,Inputs!O:O) -> -181 | F74: =+_xlfn.XLOOKUP($B74,Inputs!$B:$B,Inputs!P:P) -> 213 | G74: =+_xlfn.XLOOKUP($B74,Inputs!$B:$B,Inputs!Q:Q) -> -5758 | H74: =H296 -> 613.03785 | I74: =I296 -> 175.06609 | J74: =J296 -> 207.72148 | K74: =K296 -> 972.92888 | L74: =L296 -> 1210.4123 | M74: =M296 -> 1377.0578 | N74: =N296 -> 1554.8347 | O74: =O296 -> 1795.8481 | ... Q74: =Q296 -> 2286.1216
B75: % of EBT | E75: =IFERROR(E74/E72,"") -> 0.019202207 | F75: =IFERROR(F74/F72,"") -> 0.091770788 | G75: =IFERROR(G74/G72,"") -> -1.3958788 | H75: =H74/H72 -> 0.28793222 | I75: =I74/I72 -> 0.038075899 | J75: =J74/J72 -> 0.043731549 | K75: =K74/K72 -> 0.21315604 | L75: =L74/L72 -> 0.21 | M75: =M74/M72 -> 0.21 | N75: =N74/N72 -> 0.21 | O75: =O74/O72 -> 0.21 | ... Q75: =Q74/Q72 -> 0.21
B77: Net Income | E77: =+_xlfn.XLOOKUP($B77,Inputs!$B:$B,Inputs!O:O) -> -9245 | F77: =+_xlfn.XLOOKUP($B77,Inputs!$B:$B,Inputs!P:P) -> 2108 | G77: =+_xlfn.XLOOKUP($B77,Inputs!$B:$B,Inputs!Q:Q) -> 9883 | H77: =IFERROR(+H72-H74,"") -> 1516.0669 | I77: =IFERROR(+I72-I74,"") -> 4422.7529 | J77: =IFERROR(+J72-J74,"") -> 4542.2014 | K77: =IFERROR(+K72-K74,"") -> 3591.4684 | L77: =IFERROR(+L72-L74,"") -> 4553.4557 | M77: =IFERROR(+M72-M74,"") -> 5180.3604 | N77: =IFERROR(+N72-N74,"") -> 5849.1399 | O77: =IFERROR(+O72-O74,"") -> 6755.8095 | ... Q77: =IFERROR(+Q72-Q74,"") -> 8600.1718
B78: Net Income Margin | E78: =IFERROR(E77/E$26,"") -> -0.29002102 | F78: =IFERROR(F77/F$26,"") -> 0.056543548 | G78: =IFERROR(G77/G$26,"") -> 0.224726 | H78: =IFERROR(H77/H$26,"") -> 0.027044967 | I78: =IFERROR(I77/I$26,"") -> 0.072384671 | J78: =IFERROR(J77/J$26,"") -> 0.065907082 | K78: =IFERROR(K77/K$26,"") -> 0.046663401 | L78: =IFERROR(L77/L$26,"") -> 0.053218828 | ... Q78: =IFERROR(Q77/Q$26,"") -> 0.057831459
A80: x | B80: Balance Sheet | E80: =E24 -> 2022 | F80: =F24 -> 2023 | G80: =G24 -> 2024 | H80: =H24 -> 2025 | I80: =I24 -> 2026 | J80: =J24 -> 2027 | K80: =K24 -> 2028 | L80: =L24 -> 2029 | ... Q80: =Q24 -> 2034
B82: Assets | H82: =+SUM(H84:H92,H95:H97,H99:H101) -> 27647.222 | I82: =+SUM(I84:I92,I95:I97,I99:I101) -> 29266.023
B84: Cash & Cash Equivalents & ST Investments | E84: =+_xlfn.XLOOKUP($B84,Inputs!$B:$B,Inputs!O:O) -> 4311 | F84: =+_xlfn.XLOOKUP($B84,Inputs!$B:$B,Inputs!P:P) -> 5407 | G84: =+_xlfn.XLOOKUP($B84,Inputs!$B:$B,Inputs!Q:Q) -> 6977 | H84: =IFERROR(G84+H161,"") -> 4688.5112 | I84: =IFERROR(H84+I161,"") -> 5384.0151 | J84: =IFERROR(I84+J161,"") -> 7470.6572 | K84: =IFERROR(J84+K161,"") -> 10519.134 | L84: =IFERROR(K84+L161,"") -> 17142.806 | M84: =IFERROR(L84+M161,"") -> 20886.175 | N84: =IFERROR(M84+N161,"") -> 24100.23 | O84: =IFERROR(N84+O161,"") -> 28457.55 | P84: =IFERROR(O84+P161,"") -> 33991.718 | Q84: =P84+Q161 -> 43524.779
B86: Accounts Receivable | E86: =+_xlfn.XLOOKUP($B86,Inputs!$B:$B,Inputs!O:O) -> 2779 | F86: =+_xlfn.XLOOKUP($B86,Inputs!$B:$B,Inputs!P:P) -> 3404 | G86: =+_xlfn.XLOOKUP($B86,Inputs!$B:$B,Inputs!Q:Q) -> 3333 | H86: =IFERROR(H87*H26/365,"") -> 4755.1685 | I86: =IFERROR(I87*I26/365,"") -> 5135.0864 | J86: =IFERROR(J87*J26/365,"") -> 5625.2355 | K86: =IFERROR(K87*K26/365,"") -> 6426.4038 | L86: =IFERROR(L87*L26/365,"") -> 7106.1869 | M86: =IFERROR(M87*M26/365,"") -> 7919.9049 | N86: =IFERROR(N87*N26/365,"") -> 8878.0884 | O86: =IFERROR(O87*O26/365,"") -> 9889.9807 | ... Q86: =IFERROR(Q87*Q26/365,"") -> 12341.674 | T86: 2025 | Z86: 2026
B87: DSO | E87: =IFERROR(E86/E26*365,"") -> 31.820278 | F87: =IFERROR(F86/F26*365,"") -> 33.326896 | G87: =IFERROR(G86/G26*366,"") -> 27.738369 | H87: =IFERROR(AVERAGE(E87:G87),"") -> 30.961848 | I87: =IFERROR(AVERAGE(F87:H87),"") -> 30.675704 | J87: =IFERROR(AVERAGE(G87:I87),"") -> 29.791974 | K87: =IFERROR(AVERAGE(H87:J87),"") -> 30.476508 | L87: =IFERROR(AVERAGE(I87:K87),"") -> 30.314729 | M87: =IFERROR(AVERAGE(J87:L87),"") -> 30.194404 | N87: =IFERROR(AVERAGE(K87:M87),"") -> 30.328547 | O87: =IFERROR(AVERAGE(L87:N87),"") -> 30.279226 | ... Q87: =IFERROR(AVERAGE(N87:P87),"") -> 30.291722 | S87: liab | T87: =+Inputs!Q60+SUM(H106:H109,H112:H114)-SUM(G106,G109,G112:G114)-H107 -> 30201.29 | Z87: =+DCF!T87+SUM(I106,I108:I109,I112,I114)-SUM(H106,H109,H112:H114) -> 29920.206
B89: Inventory | E89: =+_xlfn.XLOOKUP($B89,Inputs!$B:$B,Inputs!O:O) -> 0 | F89: =+_xlfn.XLOOKUP($B89,Inputs!$B:$B,Inputs!P:P) -> 0 | G89: =+_xlfn.XLOOKUP($B89,Inputs!$B:$B,Inputs!Q:Q) -> 0 | H89: =+IFERROR(H90*H29/365,"") -> 0 | I89: =+IFERROR(I90*I29/365,"") -> 0 | J89: =+IFERROR(J90*J29/365,"") -> 0 | K89: =+IFERROR(K90*K29/365,"") -> 0 | L89: =+IFERROR(L90*L29/365,"") -> 0 | M89: =+IFERROR(M90*M29/365,"") -> 0 | N89: =+IFERROR(N90*N29/365,"") -> 0 | O89: =+IFERROR(O90*O29/365,"") -> 0 | ... Q89: =+IFERROR(Q90*Q29/365,"") -> 0 | S89: ass | T89: =+AE10 -> 52110.914 | Z89: =+AE11 -> 52881.86
B90: DIH | E90: =IFERROR(E89/E29*365,"") -> 0 | F90: =IFERROR(F89/F29*365,"") -> 0 | G90: =IFERROR(G89/G29*365,"") -> 0 | H90: =IFERROR(AVERAGE(E90:G90),"") -> 0 | I90: =IFERROR(AVERAGE(F90:H90),"") -> 0 | J90: =IFERROR(AVERAGE(G90:I90),"") -> 0 | K90: =IFERROR(AVERAGE(H90:J90),"") -> 0 | L90: =IFERROR(AVERAGE(I90:K90),"") -> 0 | M90: =IFERROR(AVERAGE(J90:L90),"") -> 0 | N90: =IFERROR(AVERAGE(K90:M90),"") -> 0 | O90: =IFERROR(AVERAGE(L90:N90),"") -> 0 | ... Q90: =IFERROR(AVERAGE(N90:P90),"") -> 0 | S90: se | T90: =+T89-T87 -> 21909.624 | Z90: =+Z89-Z87 -> 22961.655
B92: Prepaid expenses and Other Current Assets | E92: =+_xlfn.XLOOKUP($B92,Inputs!$B:$B,Inputs!O:O) -> 2159 | F92: =+_xlfn.XLOOKUP($B92,Inputs!$B:$B,Inputs!P:P) -> 2486 | G92: =+_xlfn.XLOOKUP($B92,Inputs!$B:$B,Inputs!Q:Q) -> 1935 | H92: =IFERROR(AVERAGE(E92:G92)*(1+H27),"") -> 2795.7676 | I92: =IFERROR(AVERAGE(F92:H92)*(1+I27),"") -> 2622.0178 | J92: =IFERROR(AVERAGE(G92:I92)*(1+J27),"") -> 2764.5144 | K92: =IFERROR(AVERAGE(H92:J92)*(1+K27),"") -> 3045.899 | L92: =IFERROR(AVERAGE(I92:K92)*(1+L27),"") -> 3124.7242 | M92: =IFERROR(AVERAGE(J92:L92)*(1+M27),"") -> 3332.6566 | N92: =IFERROR(AVERAGE(K92:M92)*(1+N27),"") -> 3535.3028 | O92: =IFERROR(AVERAGE(L92:N92)*(1+O27),"") -> 3716.5817 | ... Q92: =IFERROR(AVERAGE(N92:P92)*(1+Q27),"") -> 4166.0798
B93: % of revenue | E93: =IFERROR(E92/E$26,"") -> 0.067729084 | F93: =IFERROR(F92/F$26,"") -> 0.066682761 | G93: =IFERROR(G92/G$26,"") -> 0.043999272 | H93: =IFERROR(AVERAGE(E93:G93),"") -> 0.059470372 | I93: =IFERROR(AVERAGE(F93:H93),"") -> 0.056717468 | J93: =IFERROR(AVERAGE(G93:I93),"") -> 0.053395704 | K93: =IFERROR(AVERAGE(H93:J93),"") -> 0.056527848 | L93: =IFERROR(AVERAGE(I93:K93),"") -> 0.055547007 | M93: =IFERROR(AVERAGE(J93:L93),"") -> 0.055156853 | N93: =IFERROR(AVERAGE(K93:M93),"") -> 0.055743903 | O93: =IFERROR(AVERAGE(L93:N93),"") -> 0.055482588 | ... Q93: =IFERROR(AVERAGE(N93:P93),"") -> 0.055562535
B95: Net PP&E (Property, Plant and Equipment) + ROU Assets | E95: =+E96+E97-E99 -> 4980 | F95: =+F96+F97-F99 -> 4555 | G95: =+G96+G97-G99 -> 4268 | H95: =IFERROR(H96+H97-H99,"") -> 4831.4673 | I95: =IFERROR(I96+I97-I99,"") -> 4571.7262 | J95: =IFERROR(J96+J97-J99,"") -> 4554.3482 | K95: =IFERROR(K96+K97-K99,"") -> 4661.9697 | L95: =IFERROR(L96+L97-L99,"") -> 4608.0125 | M95: =IFERROR(M96+M97-M99,"") -> 4657.6252 | N95: =IFERROR(N96+N97-N99,"") -> 4737.0472 | O95: =IFERROR(O96+O97-O99,"") -> 4795.0094 | ... Q95: =IFERROR(Q96+Q97-Q99,"") -> 5040.0891
B96: Gross PP&E (Property, Plant and Equipment) + ROU Assets | E96: =+_xlfn.XLOOKUP("Gross PP&E (Property, Plant and Equipment)",Inputs!$B:$B,Inputs!O:O) -> 4816 | F96: =+_xlfn.XLOOKUP("Gross PP&E (Property, Plant and Equipment)",Inputs!$B:$B,Inputs!P:P) -> 4715 | G96: =+_xlfn.XLOOKUP("Gross PP&E (Property, Plant and Equipment)",Inputs!$B:$B,Inputs!Q:Q) -> 4708 | H96: =+IFERROR(G96-H130,"") -> 5008 | I96: =+IFERROR(H96-I130,"") -> 5338 | J96: =+IFERROR(I96-J130,"") -> 5701 | K96: =+IFERROR(J96-K130,"") -> 6100.3 | L96: =+IFERROR(K96-L130,"") -> 6539.53 | M96: =+IFERROR(L96-M130,"") -> 7022.683 | N96: =+IFERROR(M96-N130,"") -> 7554.1513 | O96: =+IFERROR(N96-O130,"") -> 8138.7664 | ... Q96: =+IFERROR(P96-Q130,"") -> 9489.2274
B97: Right-of-Use Assets | E97: =+_xlfn.XLOOKUP("Right-of-Use Assets",Inputs!$B:$B,Inputs!O:O) -> 1449 | F97: =+_xlfn.XLOOKUP("Right-of-Use Assets",Inputs!$B:$B,Inputs!P:P) -> 1241 | G97: =+_xlfn.XLOOKUP("Right-of-Use Assets",Inputs!$B:$B,Inputs!Q:Q) -> 1158 | H97: =IFERROR(H98*H$26,"") -> 1963.4067 | I97: =IFERROR(I98*I$26,"") -> 1927.6064 | J97: =IFERROR(J98*J$26,"") -> 2134.2698 | K97: =IFERROR(K98*K$26,"") -> 2502.4328 | L97: =IFERROR(L98*L$26,"") -> 2710.2839 | M97: =IFERROR(M98*M$26,"") -> 3036.7754 | N97: =IFERROR(N98*N$26,"") -> 3415.8808 | O97: =IFERROR(O98*O$26,"") -> 3789.7993 | ... Q97: =IFERROR(Q98*Q$26,"") -> 4738.1638
B98: % of revenue | E98: =IFERROR(E97/E$26,"") -> 0.045455971 | F98: =IFERROR(F97/F$26,"") -> 0.033287734 | G98: =IFERROR(G97/G$26,"") -> 0.026331347 | H98: =IFERROR(AVERAGE(E98:G98),"") -> 0.035025018 | I98: =IFERROR(AVERAGE(F98:H98),"") -> 0.031548033 | J98: =IFERROR(AVERAGE(G98:I98),"") -> 0.030968133 | K98: =IFERROR(AVERAGE(H98:J98),"") -> 0.032513728 | L98: =IFERROR(AVERAGE(I98:K98),"") -> 0.031676631 | M98: =IFERROR(AVERAGE(J98:L98),"") -> 0.031719497 | N98: =IFERROR(AVERAGE(K98:M98),"") -> 0.031969952 | O98: =IFERROR(AVERAGE(L98:N98),"") -> 0.031788693 | ... Q98: =IFERROR(AVERAGE(N98:P98),"") -> 0.031861564
B99: Accumulated Depreciation | E99: =+_xlfn.XLOOKUP($B99,Inputs!$B:$B,Inputs!O:O) -> 1285 | F99: =+_xlfn.XLOOKUP($B99,Inputs!$B:$B,Inputs!P:P) -> 1401 | G99: =+_xlfn.XLOOKUP($B99,Inputs!$B:$B,Inputs!Q:Q) -> 1598 | H99: =+IFERROR(G99+H49,"") -> 2139.9394 | I99: =+IFERROR(H99+I49,"") -> 2693.8802 | J99: =+IFERROR(I99+J49,"") -> 3280.9216 | K99: =+IFERROR(J99+K49,"") -> 3940.7631 | L99: =+IFERROR(K99+L49,"") -> 4641.8014 | M99: =+IFERROR(L99+M49,"") -> 5401.8332 | N99: =+IFERROR(M99+N49,"") -> 6232.9849 | O99: =+IFERROR(N99+O49,"") -> 7133.5563 | ... Q99: =+IFERROR(P99+Q49,"") -> 9187.3021
B101: Intangibles excl. Goodwill | E101: =+_xlfn.XLOOKUP($B101,Inputs!$B:$B,Inputs!O:O) -> 1874 | F101: =+_xlfn.XLOOKUP($B101,Inputs!$B:$B,Inputs!P:P) -> 1425 | G101: =+_xlfn.XLOOKUP($B101,Inputs!$B:$B,Inputs!Q:Q) -> 1125 | H101: =G101*(1+H27) -> 1433.9994 | I101: =H101*(1+I27) -> 1563.0149 | J101: =I101*(1+J27) -> 1762.9961 | K101: =J101*(1+K27) -> 1968.8504 | L101: =K101*(1+L27) -> 2188.7333 | M101: =L101*(1+M27) -> 2449.0826 | N101: =M101*(1+N27) -> 2733.24 | O101: =N101*(1+O27) -> 3049.7243 | ... Q101: =P101*(1+Q27) -> 3804.171
B102: growing with % Revenue | F102: =IFERROR((F101-E101)/F26,"") -> -0.012043668 | G102: =IFERROR((G101-F101)/G26,"") -> -0.0068215926 | H102: =IFERROR((H101-G101)/H26,"") -> 0.0055122088 | I102: =IFERROR((I101-H101)/I26,"") -> 0.002111524 | J102: =IFERROR((J101-I101)/J26,"") -> 0.0029017154 | K102: =IFERROR((K101-J101)/K26,"") -> 0.0026746333 | L102: =IFERROR((L101-K101)/L26,"") -> 0.0025698972 | M102: =IFERROR((M101-L101)/M26,"") -> 0.0027193801 | ... Q102: =IFERROR((Q101-P101)/Q26,"") -> 0.002670696
B104: Liabilities | H104: =+SUM(H106:H109,H112:H114) -> 22897.003 | I104: =+SUM(I106:I109,I112:I114) -> 22615.651
B106: Accounts Payable | E106: =+_xlfn.XLOOKUP($B106,Inputs!$B:$B,Inputs!O:O) -> 728 | F106: =+_xlfn.XLOOKUP($B106,Inputs!$B:$B,Inputs!P:P) -> 790 | G106: =+_xlfn.XLOOKUP($B106,Inputs!$B:$B,Inputs!Q:Q) -> 858 | H106: =+IFERROR(H107*H29/365,"") -> 1187.8368 | I106: =+IFERROR(I107*I29/365,"") -> 1261.6381 | J106: =+IFERROR(J107*J29/365,"") -> 1410.504 | K106: =+IFERROR(K107*K29/365,"") -> 1598.4017 | L106: =+IFERROR(L107*L29/365,"") -> 1764.9142 | M106: =+IFERROR(M107*M29/365,"") -> 1974.179 | N106: =+IFERROR(N107*N29/365,"") -> 2208.7274 | O106: =+IFERROR(O107*O29/365,"") -> 2460.6711 | ... Q106: =+IFERROR(Q107*Q29/365,"") -> 3071.1853
B107: DPO | E107: =IFERROR(E106/E$29*365,"") -> 13.516456 | F107: =IFERROR(F106/F$29*365,"") -> 12.840094 | G107: =IFERROR(G106/G$29*366,"") -> 11.782972 | H107: =IFERROR(AVERAGE(E107:G107),"") -> 12.713174 | I107: =IFERROR(AVERAGE(F107:H107),"") -> 12.445414 | J107: =IFERROR(AVERAGE(G107:I107),"") -> 12.313853 | K107: =IFERROR(AVERAGE(H107:J107),"") -> 12.490814 | L107: =IFERROR(AVERAGE(I107:K107),"") -> 12.416694 | M107: =IFERROR(AVERAGE(J107:L107),"") -> 12.40712 | N107: =IFERROR(AVERAGE(K107:M107),"") -> 12.438209 | O107: =IFERROR(AVERAGE(L107:N107),"") -> 12.420674 | ... Q107: =IFERROR(AVERAGE(N107:P107),"") -> 12.426962
B109: Accrued Expenses and Other Current Liabilities | E109: =+_xlfn.XLOOKUP($B109,Inputs!$B:$B,Inputs!O:O) -> 7809 | F109: =+_xlfn.XLOOKUP($B109,Inputs!$B:$B,Inputs!P:P) -> 8318 | G109: =+_xlfn.XLOOKUP($B109,Inputs!$B:$B,Inputs!Q:Q) -> 10307 | H109: =IFERROR(AVERAGE(E109:G109)*(1+H27),"") -> 11231.508 | I109: =IFERROR(AVERAGE(F109:H109)*(1+I27),"") -> 10847.556 | J109: =IFERROR(AVERAGE(G109:I109)*(1+J27),"") -> 12176.575 | K109: =IFERROR(AVERAGE(H109:J109)*(1+K27),"") -> 12751.82 | L109: =IFERROR(AVERAGE(I109:K109)*(1+L27),"") -> 13257.147 | M109: =IFERROR(AVERAGE(J109:L109)*(1+M27),"") -> 14242.567 | N109: =IFERROR(AVERAGE(K109:M109)*(1+N27),"") -> 14973.921 | O109: =IFERROR(AVERAGE(L109:N109)*(1+O27),"") -> 15797.232 | ... Q109: =IFERROR(AVERAGE(N109:P109)*(1+Q27),"") -> 17691.547
B110: growing with revenue | E110: =IFERROR(E109/E$26,"") -> 0.24497286 | F110: =IFERROR(F109/F$26,"") -> 0.22311633 | G110: =IFERROR(G109/G$26,"") -> 0.23436718 | H110: =IFERROR(H109/H$26,"") -> 0.20035775 | I110: =IFERROR(I109/I$26,"") -> 0.17753576 | J110: =IFERROR(J109/J$26,"") -> 0.17668141 | K110: =IFERROR(K109/K$26,"") -> 0.16568245 | L110: =IFERROR(L109/L$26,"") -> 0.15494383 | ... Q110: =IFERROR(Q109/Q$26,"") -> 0.11896599
B112: Total Borrowings | E112: =+_xlfn.XLOOKUP($B112,Inputs!$B:$B,Inputs!O:O) -> 9265 | F112: =+_xlfn.XLOOKUP($B112,Inputs!$B:$B,Inputs!P:P) -> 9459 | G112: =+_xlfn.XLOOKUP($B112,Inputs!$B:$B,Inputs!Q:Q) -> 8347 | H112: =IFERROR(G112+H152-H154,"") -> 7197 | I112: =IFERROR(H112+I152-I154,"") -> 7197 | J112: =IFERROR(I112+J152-J154,"") -> 6497 | K112: =IFERROR(J112+K152-K154,"") -> 4272 | L112: =IFERROR(K112+L152-L154,"") -> -828 | M112: =IFERROR(L112+M152-M154,"") -> -2078 | N112: =IFERROR(M112+N152-N154,"") -> -2078 | O112: =IFERROR(N112+O152-O154,"") -> -2078 | ... Q112: =IFERROR(P112+Q152-Q154,"") -> -4828
B114: Total Leases | E114: =+_xlfn.XLOOKUP($B114,Inputs!$B:$B,Inputs!O:O) -> 2273 | F114: =+_xlfn.XLOOKUP($B114,Inputs!$B:$B,Inputs!P:P) -> 2218 | G114: =+_xlfn.XLOOKUP($B114,Inputs!$B:$B,Inputs!Q:Q) -> 1939 | H114: =+IFERROR(H115*H26,"") -> 3267.9455 | I114: =+IFERROR(I115*I26,"") -> 3297.0112 | J114: =+IFERROR(J115*J26,"") -> 3591.7229 | K114: =+IFERROR(K115*K26,"") -> 4217.001 | L114: =+IFERROR(L115*L26,"") -> 4587.9754 | M114: =+IFERROR(M115*M26,"") -> 5122.9268 | N114: =+IFERROR(N115*N26,"") -> 5766.9649 | O114: =+IFERROR(O115*O26,"") -> 6402.2755 | ... Q114: =+IFERROR(Q115*Q26,"") -> 8000.8937
B115: % of revenues | E115: =IFERROR(E114/E$26,"") -> 0.07130533 | F115: =IFERROR(F114/F$26,"") -> 0.059494112 | G115: =IFERROR(G114/G$26,"") -> 0.044090227 | H115: =+IFERROR(AVERAGE(E115:G115),"") -> 0.058296556 | I115: =+IFERROR(AVERAGE(F115:H115),"") -> 0.053960299 | J115: =+IFERROR(AVERAGE(G115:I115),"") -> 0.052115694 | K115: =+IFERROR(AVERAGE(H115:J115),"") -> 0.05479085 | L115: =+IFERROR(AVERAGE(I115:K115),"") -> 0.053622281 | M115: =+IFERROR(AVERAGE(J115:L115),"") -> 0.053509608 | N115: =+IFERROR(AVERAGE(K115:M115),"") -> 0.053974246 | O115: =+IFERROR(AVERAGE(L115:N115),"") -> 0.053702045 | ... Q115: =+IFERROR(AVERAGE(N115:P115),"") -> 0.053801641
A117: x | B117: Cash Flow | E117: =E24 -> 2022 | F117: =F24 -> 2023 | G117: =G24 -> 2024 | H117: =H24 -> 2025 | I117: =I24 -> 2026 | J117: =J24 -> 2027 | K117: =K24 -> 2028 | L117: =L24 -> 2029 | ... Q117: =Q24 -> 2034
B119: D&A (Depreciation & Amortization) | E119: =+E46 -> 947 | F119: =+F46 -> 823 | G119: =+G46 -> 711 | H119: =+H46 -> 841.93942 | I119: =+I46 -> 905.65713 | J119: =+J46 -> 983.7585 | K119: =+K46 -> 1102.8808 | L119: =+L46 -> 1193.5565 | ... Q119: =+Q46 -> 1928.1158
B121: Stock Based Compensation | E121: =+_xlfn.XLOOKUP($B121,Inputs!$B:$B,Inputs!O:O) -> 1793 | F121: =+_xlfn.XLOOKUP($B121,Inputs!$B:$B,Inputs!P:P) -> 1935 | G121: =+_xlfn.XLOOKUP($B121,Inputs!$B:$B,Inputs!Q:Q) -> 1796 | H121: =IFERROR(H122*H35,"") -> 2458.6064 | I121: =IFERROR(I122*I35,"") -> 2729.127 | J121: =IFERROR(J122*J35,"") -> 2957.2203 | K121: =IFERROR(K122*K35,"") -> 3355.0653 | L121: =IFERROR(L122*L35,"") -> 3722.1767 | M121: =IFERROR(M122*M35,"") -> 4128.1361 | N121: =IFERROR(N122*N35,"") -> 4614.4478 | O121: =IFERROR(O122*O35,"") -> 5132.7896 | ... Q121: =IFERROR(Q122*Q35,"") -> 6369.8173
B122: % of SG&A | E122: =+IFERROR(E121/E35,"") -> 0.22719209 | F122: =+IFERROR(F121/F35,"") -> 0.27493606 | G122: =+IFERROR(G121/G35,"") -> 0.22517553 | H122: =IFERROR(AVERAGE(E122:G122),"") -> 0.24243456 | I122: =IFERROR(AVERAGE(F122:H122),"") -> 0.24751538 | J122: =IFERROR(AVERAGE(G122:I122),"") -> 0.23837516 | K122: =IFERROR(AVERAGE(H122:J122),"") -> 0.24277503 | L122: =IFERROR(AVERAGE(I122:K122),"") -> 0.24288852 | M122: =IFERROR(AVERAGE(J122:L122),"") -> 0.24134624 | N122: =IFERROR(AVERAGE(K122:M122),"") -> 0.2423366 | O122: =IFERROR(AVERAGE(L122:N122),"") -> 0.24219045 | ... Q122: =IFERROR(AVERAGE(N122:P122),"") -> 0.24216161
B124: Changes in Net Working Capital | E124: =+_xlfn.XLOOKUP($B124,Inputs!$B:$B,Inputs!O:O) -> -135 | F124: =+_xlfn.XLOOKUP($B124,Inputs!$B:$B,Inputs!P:P) -> -141 | G124: =+_xlfn.XLOOKUP($B124,Inputs!$B:$B,Inputs!Q:Q) -> 2069 | H124: =IFERROR(-((H86+H89+H92-H106-H109)-(G86+G89+G92-G106-G109)),"") -> -1028.5915 | I124: =IFERROR(-((I86+I89+I92-I106-I109)-(H86+H89+H92-H106-H109)),"") -> -516.31802 | J124: =IFERROR(-((J86+J89+J92-J106-J109)-(I86+I89+I92-I106-I109)),"") -> 845.23844 | K124: =IFERROR(-((K86+K89+K92-K106-K109)-(J86+J89+J92-J106-J109)),"") -> -319.40967 | L124: =IFERROR(-((L86+L89+L92-L106-L109)-(K86+K89+K92-K106-K109)),"") -> -86.768866 | M124: =IFERROR(-((M86+M89+M92-M106-M109)-(L86+L89+L92-L106-L109)),"") -> 173.03451 | N124: =IFERROR(-((N86+N89+N92-N106-N109)-(M86+M89+M92-M106-M109)),"") -> -194.9275 | O124: =IFERROR(-((O86+O89+O92-O106-O109)-(N86+N89+N92-N106-N109)),"") -> -117.91693 | ... Q124: =IFERROR(-((Q86+Q89+Q92-Q106-Q109)-(P86+P89+P92-P106-P109)),"") -> -271.10526
B126: Other Operating Adjustments | E126: =+_xlfn.XLOOKUP($B126,Inputs!$B:$B,Inputs!O:O) -> 7282 | F126: =+_xlfn.XLOOKUP($B126,Inputs!$B:$B,Inputs!P:P) -> -1140 | G126: =+_xlfn.XLOOKUP($B126,Inputs!$B:$B,Inputs!Q:Q) -> -7322 | H126: =IFERROR(AVERAGE(E126:G126)*(1+H27),"") -> -501.36866 | I126: =IFERROR(AVERAGE(F126:H126)*(1+I27),"") -> -3256.5981 | J126: =IFERROR(AVERAGE(G126:I126)*(1+J27),"") -> -4165.8673 | K126: =IFERROR(AVERAGE(H126:J126)*(1+K27),"") -> -2949.6839 | L126: =IFERROR(AVERAGE(I126:K126)*(1+L27),"") -> -3843.5067 | M126: =IFERROR(AVERAGE(J126:L126)*(1+M27),"") -> -4087.545 | N126: =IFERROR(AVERAGE(K126:M126)*(1+N27),"") -> -4047.7283 | O126: =IFERROR(AVERAGE(L126:N126)*(1+O27),"") -> -4455.2712 | ... Q126: =IFERROR(AVERAGE(N126:P126)*(1+Q27),"") -> -4909.7611
B128: Operating Cash Flow | E128: =+_xlfn.XLOOKUP($B128,Inputs!$B:$B,Inputs!O:O) -> 642 | F128: =+_xlfn.XLOOKUP($B128,Inputs!$B:$B,Inputs!P:P) -> 3585 | G128: =+_xlfn.XLOOKUP($B128,Inputs!$B:$B,Inputs!Q:Q) -> 7137 | H128: =IFERROR(H77+H119+H121+H124+H126,"") -> 3286.6526 | I128: =IFERROR(I77+I119+I121+I124+I126,"") -> 4284.6209 | J128: =IFERROR(J77+J119+J121+J124+J126,"") -> 5162.5513 | K128: =IFERROR(K77+K119+K121+K124+K126,"") -> 4780.3209 | L128: =IFERROR(L77+L119+L121+L124+L126,"") -> 5538.9133 | M128: =IFERROR(M77+M119+M121+M124+M126,"") -> 6705.1211 | N128: =IFERROR(N77+N119+N121+N124+N126,"") -> 7667.1291 | O128: =IFERROR(O77+O119+O121+O124+O126,"") -> 8902.2445 | ... Q128: =IFERROR(Q77+Q119+Q121+Q124+Q126,"") -> 11717.239
B130: Net CapEx | E130: =+_xlfn.XLOOKUP($B130,Inputs!$B:$B,Inputs!O:O) -> -252 | F130: =+_xlfn.XLOOKUP($B130,Inputs!$B:$B,Inputs!P:P) -> -223 | G130: =+_xlfn.XLOOKUP($B130,Inputs!$B:$B,Inputs!Q:Q) -> -242 | H130: =G275 -> -300 | I130: =H275 -> -330 | J130: =I275 -> -363 | K130: =J275 -> -399.3 | L130: =K275 -> -439.23 | M130: =L275 -> -483.153 | N130: =M275 -> -531.4683 | O130: =N275 -> -584.61513 | ... Q130: =P275 -> -707.38431
B132: Acquisition of Fixed & Intangibles | E132: =+_xlfn.XLOOKUP($B132,Inputs!$B:$B,Inputs!O:O) -> -252 | F132: =+_xlfn.XLOOKUP($B132,Inputs!$B:$B,Inputs!P:P) -> -223 | G132: =+_xlfn.XLOOKUP($B132,Inputs!$B:$B,Inputs!Q:Q) -> -242 | H132: =G275 -> -300 | I132: =H275 -> -330 | J132: =I275 -> -363 | K132: =J275 -> -399.3 | L132: =K275 -> -439.23 | M132: =L275 -> -483.153 | N132: =M275 -> -531.4683 | O132: =N275 -> -584.61513 | ... Q132: =P275 -> -707.38431
B134: Disposal of Fixed & Intangibles | E134: =+_xlfn.XLOOKUP($B134,Inputs!$B:$B,Inputs!O:O) -> 0 | F134: =+_xlfn.XLOOKUP($B134,Inputs!$B:$B,Inputs!P:P) -> 0 | G134: =+_xlfn.XLOOKUP($B134,Inputs!$B:$B,Inputs!Q:Q) -> 0 | I134: =IFERROR(I135*H96,"") -> 0 | J134: =IFERROR(J135*I96,"") -> 0 | K134: =IFERROR(K135*J96,"") -> 0 | L134: =IFERROR(L135*K96,"") -> 0 | M134: =IFERROR(M135*L96,"") -> 0 | N134: =IFERROR(N135*M96,"") -> 0 | O134: =IFERROR(O135*N96,"") -> 0 | P134: =IFERROR(P135*O96,"") -> 0 | Q134: =IFERROR(Q135*P96,"") -> 0
B135: Disposal Rate (% Gross PP&E) | E135: =IFERROR(E134/E96,"") -> 0 | F135: =IFERROR(F134/F96,"") -> 0 | G135: =IFERROR(G134/G96,"") -> 0 | H135: =IFERROR(AVERAGE(E135:G135),"") -> 0 | I135: =IFERROR(AVERAGE(F135:H135),"") -> 0 | J135: =IFERROR(AVERAGE(G135:I135),"") -> 0 | K135: =IFERROR(AVERAGE(H135:J135),"") -> 0 | L135: =IFERROR(AVERAGE(I135:K135),"") -> 0 | M135: =IFERROR(AVERAGE(J135:L135),"") -> 0 | N135: =IFERROR(AVERAGE(K135:M135),"") -> 0 | O135: =IFERROR(AVERAGE(L135:N135),"") -> 0 | ... Q135: =IFERROR(AVERAGE(N135:P135),"") -> 0
B137: Net Cash from Investments & Acquisitions | E137: =+_xlfn.XLOOKUP($B137,Inputs!$B:$B,Inputs!O:O) -> -1405 | F137: =+_xlfn.XLOOKUP($B137,Inputs!$B:$B,Inputs!P:P) -> -3036 | G137: =+_xlfn.XLOOKUP($B137,Inputs!$B:$B,Inputs!Q:Q) -> -2833 | H137: =G281 -> -6068.5833 | I137: =H281 -> -2829.7257 | J137: =I281 -> -2837.0642 | K137: =J281 -> -3040.1013 | L137: =K281 -> -3001.7151 | M137: =L281 -> -3095.9136 | N137: =M281 -> -3269.6623 | O137: =N281 -> -3258.4972 | ... Q137: =P281 -> -3433.2051
B139: Other Investing Inflows (Outflows) | E139: =+_xlfn.XLOOKUP($B139,Inputs!$B:$B,Inputs!O:O) -> 20 | F139: =+_xlfn.XLOOKUP($B139,Inputs!$B:$B,Inputs!P:P) -> 33 | G139: =+_xlfn.XLOOKUP($B139,Inputs!$B:$B,Inputs!Q:Q) -> -102 | H139: 90 | I139: 90 | J139: 90 | K139: 90 | L139: 90 | M139: 90 | N139: 90 | O139: 90 | P139: 90 | Q139: 90
B141: Investing Cash Flow | E141: =+_xlfn.XLOOKUP($B141,Inputs!$B:$B,Inputs!O:O) -> -1637 | F141: =+_xlfn.XLOOKUP($B141,Inputs!$B:$B,Inputs!P:P) -> -3226 | G141: =+_xlfn.XLOOKUP($B141,Inputs!$B:$B,Inputs!Q:Q) -> -3177 | H141: =IFERROR(+H130+H137+H139,"") -> -6278.5833 | I141: =IFERROR(+I130+I137+I139,"") -> -3069.7257 | J141: =IFERROR(+J130+J137+J139,"") -> -3110.0642 | K141: =IFERROR(+K130+K137+K139,"") -> -3349.4013 | L141: =IFERROR(+L130+L137+L139,"") -> -3350.9451 | M141: =IFERROR(+M130+M137+M139,"") -> -3489.0666 | N141: =IFERROR(+N130+N137+N139,"") -> -3711.1306 | O141: =IFERROR(+O130+O137+O139,"") -> -3753.1124 | ... Q141: =IFERROR(+Q130+Q137+Q139,"") -> -4050.5894
B143: Dividends | E143: =+_xlfn.XLOOKUP($B143,Inputs!$B:$B,Inputs!O:O) -> 0 | F143: =+_xlfn.XLOOKUP($B143,Inputs!$B:$B,Inputs!P:P) -> 0 | G143: =+_xlfn.XLOOKUP($B143,Inputs!$B:$B,Inputs!Q:Q) -> 0 | H143: =+IFERROR(H144*_xlfn.XLOOKUP("Net Income",$B:$B,$H:$H),"") -> 0 | I143: =+IFERROR(I144*_xlfn.XLOOKUP("Net Income",$B:$B,$H:$H),"") -> 0 | J143: =+IFERROR(J144*_xlfn.XLOOKUP("Net Income",$B:$B,$H:$H),"") -> 0 | K143: =+IFERROR(K144*_xlfn.XLOOKUP("Net Income",$B:$B,$H:$H),"") -> 0 | L143: =+IFERROR(L144*_xlfn.XLOOKUP("Net Income",$B:$B,$H:$H),"") -> 0 | M143: =+IFERROR(M144*_xlfn.XLOOKUP("Net Income",$B:$B,$H:$H),"") -> 0 | N143: =+IFERROR(N144*_xlfn.XLOOKUP("Net Income",$B:$B,$H:$H),"") -> 0 | O143: =+IFERROR(O144*_xlfn.XLOOKUP("Net Income",$B:$B,$H:$H),"") -> 0 | ... Q143: =+IFERROR(Q144*_xlfn.XLOOKUP("Net Income",$B:$B,$H:$H),"") -> 0
B144: Dividend payout | E144: =IFERROR(-E143/E$77,"") -> 0 | F144: =IFERROR(-F143/F$77,"") -> 0 | G144: =IFERROR(-G143/G$77,"") -> 0
B146: Increase (Repurchase) of Shares | E146: =+_xlfn.XLOOKUP($B146,Inputs!$B:$B,Inputs!O:O) -> 347 | F146: =+_xlfn.XLOOKUP($B146,Inputs!$B:$B,Inputs!P:P) -> 130 | G146: =+_xlfn.XLOOKUP($B146,Inputs!$B:$B,Inputs!Q:Q) -> -1096 | I146: =IFERROR(-I147*_xlfn.XLOOKUP("Net Income",$B:$B,I:I),"") -> 0 | J146: =IFERROR(-J147*_xlfn.XLOOKUP("Net Income",$B:$B,J:J),"") -> 0 | K146: =IFERROR(-K147*_xlfn.XLOOKUP("Net Income",$B:$B,K:K),"") -> 0 | L146: =IFERROR(-L147*_xlfn.XLOOKUP("Net Income",$B:$B,L:L),"") -> 0 | M146: =IFERROR(-M147*_xlfn.XLOOKUP("Net Income",$B:$B,M:M),"") -> 0 | N146: =IFERROR(-N147*_xlfn.XLOOKUP("Net Income",$B:$B,N:N),"") -> 0 | O146: =IFERROR(-O147*_xlfn.XLOOKUP("Net Income",$B:$B,O:O),"") -> 0 | P146: =IFERROR(-P147*_xlfn.XLOOKUP("Net Income",$B:$B,P:P),"") -> 0 | Q146: =IFERROR(-Q147*_xlfn.XLOOKUP("Net Income",$B:$B,Q:Q),"") -> 0
B147: Repurchase payout | E147: =IFERROR(-E146/E$77,"") -> 0.037533802 | F147: =IFERROR(-F146/F$77,"") -> -0.061669829 | G147: =IFERROR(-G146/G$77,"") -> 0.1108975
B149: Lease Payments | E149: =+_xlfn.XLOOKUP($B149,Inputs!$B:$B,Inputs!O:O) -> 0 | F149: =+_xlfn.XLOOKUP($B149,Inputs!$B:$B,Inputs!P:P) -> 0 | G149: =+_xlfn.XLOOKUP($B149,Inputs!$B:$B,Inputs!Q:Q) -> 0 | H149: =+IFERROR(H150*H97,"") -> 0 | I149: =+IFERROR(I150*I97,"") -> 0 | J149: =+IFERROR(J150*J97,"") -> 0 | K149: =+IFERROR(K150*K97,"") -> 0 | L149: =+IFERROR(L150*L97,"") -> 0 | M149: =+IFERROR(M150*M97,"") -> 0 | N149: =+IFERROR(N150*N97,"") -> 0 | O149: =+IFERROR(O150*O97,"") -> 0 | ... Q149: =+IFERROR(Q150*Q97,"") -> 0
B150: % of Right-of-Use Assets | E150: =IFERROR(E149/E97,"") -> 0 | F150: =IFERROR(F149/F97,"") -> 0 | G150: =IFERROR(G149/G97,"") -> 0
B152: Debt Borrowing | E152: =+_xlfn.XLOOKUP($B152,Inputs!$B:$B,Inputs!O:O) -> 0 | F152: =+_xlfn.XLOOKUP($B152,Inputs!$B:$B,Inputs!P:P) -> 2824 | G152: =+_xlfn.XLOOKUP($B152,Inputs!$B:$B,Inputs!Q:Q) -> 3972 | H152: =IFERROR(MAX(0,-G240),"") -> 0 | I152: =IFERROR(MAX(0,-H240),"") -> 0 | J152: =IFERROR(MAX(0,-I240),"") -> 0 | K152: =IFERROR(MAX(0,-J240),"") -> 0 | L152: =IFERROR(MAX(0,-K240),"") -> 0 | M152: =IFERROR(MAX(0,-L240),"") -> 0 | N152: =IFERROR(MAX(0,-M240),"") -> 0 | O152: =IFERROR(MAX(0,-N240),"") -> 0 | ... Q152: =IFERROR(MAX(0,-P240),"") -> 0
...

Sheet WACC
B2: WACC
B4: WACC = % of Equity x Cost of Equity + % de Debt x Cost of Debt x (1 - Tax Rate)
B5: Cost of Equity = Risk-Free Rate + Beta x Equity Risk Premium
B7: WACC | I7: Region | J7: Weight | K7: ERP | M7: Peers | N7: Beta (Unlevered)
B9: Market Cap (in millions) | G9: {=+_FV(DCF!R4,"Market cap",TRUE)/1000000} -> 196780.14 | I9: US & Canada | J9: =23.618/43.978 -> 0.53704125 | K9: 0.0433 | M9: =+Peers!B8 -> LYFT INC. | N9: =+Peers!E75 -> 1.0041786
B10: % of Equity | G10: =IFERROR(G9/G23,"") -> 0.95359941 | I10: LatAm | J10: =2.795/43.978 -> 0.063554505 | K10: 0.1229 | M10: =+Peers!B9 -> DOORDASH INC. | N10: =+Peers!F75 -> 1.612881
B11: Cost of Equity | G11: =IFERROR(G12+G14*G15,"") -> 0.11596705 | I11: EMEA | J11: =12.529/43.978 -> 0.28489245 | K11: 0.0676 | M11: =+Peers!B10 -> GRAB HOLDINGS LIMITED | N11: =+Peers!G75 -> 0.76972805
B12: Risk-Free Rate | G12: 0.042 | I12: APAC | J12: =5.036/43.978 -> 0.1145118 | K12: 0.074 | M12: =+Peers!B11 -> DELIVERY HERO SE | N12: =+Peers!H75
B13: Unlevered Beta | G13: =+N19 -> 0.79446793 | I13: Others | K13: 0 | M13: =+Peers!B12 -> DiDi GLOBAL INC. | N13: =+Peers!I75 -> 0.5591689
B14: Beta | G14: 1.258 | M14: =+Peers!B13 -> MEITUAN | N14: =+Peers!J75 -> 1.1448876
B15: Equity Risk Premium | G15: =SUMPRODUCT(J9:J12,K9:K12) -> 0.058797337 | M15: =+Peers!B14 -> DELIVEROO PLC | N15: =+Peers!K75 -> 0.2181
B16: Cost of Equity | G16: =IFERROR(+G12+G14*G15,"") -> 0.11596705 | M16: =+Peers!B15 -> JUST EAT TAKEAWAY | N16: =+Peers!L75 -> 1.0268944
G17: =G13*G15+G12 -> 0.088712599 | M17: =+Peers!B16 -> HERTZ GLOBAL HOLDINGS INC. | N17: =+Peers!M75 -> 0.019904891
B18: Debt (in millions) | G18: 9575 | M18: =+Peers!B17 -> 0 | N18: =+Peers!N75
B19: % of Debt | G19: =IFERROR(G18/G23,"") -> 0.04640059 | M19: Average | N19: =IFERROR(+AVERAGEIF(N9:N18,">0"),"") -> 0.79446793
B20: Cost of debt | G20: =4.8% -> 0.048
B21: Tax Rate | G21: =3% -> 0.03
B23: Total | G23: =+G9+G18 -> 206355.14
B25: WACC | G25: =IFERROR(G10*G11+G19*G20*(1-G21),"") -> 0.11274652

Sheet Multiples
B2: Multiples
B4: Valuation | F4: 2014 | G4: =+F4+1 -> 2015 | H4: =+G4+1 -> 2016 | I4: =+H4+1 -> 2017 | J4: =+I4+1 -> 2018 | K4: =+J4+1 -> 2019 | L4: =+K4+1 -> 2020 | M4: =+L4+1 -> 2021 | N4: 2022 | O4: =+N4+1 -> 2023 | P4: =+O4+1 -> 2024 | Q4: =+P4+1 -> 2025 | R4: =+Q4+1 -> 2026
B6: EV / Sales | F6: =IFERROR(_xlfn.XLOOKUP("Enterprise Value",Inputs!$B:$B,Inputs!G:G)/_xlfn.XLOOKUP("Revenue (Sales)",Inputs!$B:$B,Inputs!G:G),"") | G6: =IFERROR(_xlfn.XLOOKUP("Enterprise Value",Inputs!$B:$B,Inputs!H:H)/_xlfn.XLOOKUP("Revenue (Sales)",Inputs!$B:$B,Inputs!H:H),"") | H6: =IFERROR(_xlfn.XLOOKUP("Enterprise Value",Inputs!$B:$B,Inputs!I:I)/_xlfn.XLOOKUP("Revenue (Sales)",Inputs!$B:$B,Inputs!I:I),"") | I6: =IFERROR(_xlfn.XLOOKUP("Enterprise Value",Inputs!$B:$B,Inputs!J:J)/_xlfn.XLOOKUP("Revenue (Sales)",Inputs!$B:$B,Inputs!J:J),"") | J6: =IFERROR(_xlfn.XLOOKUP("Enterprise Value",Inputs!$B:$B,Inputs!K:K)/_xlfn.XLOOKUP("Revenue (Sales)",Inputs!$B:$B,Inputs!K:K),"") | K6: =IFERROR(_xlfn.XLOOKUP("Enterprise Value",Inputs!$B:$B,Inputs!L:L)/_xlfn.XLOOKUP("Revenue (Sales)",Inputs!$B:$B,Inputs!L:L),"") -> 2.6045705 | L6: =IFERROR(_xlfn.XLOOKUP("Enterprise Value",Inputs!$B:$B,Inputs!M:M)/_xlfn.XLOOKUP("Revenue (Sales)",Inputs!$B:$B,Inputs!M:M),"") -> 8.3435676 | M6: =IFERROR(_xlfn.XLOOKUP("Enterprise Value",Inputs!$B:$B,Inputs!N:N)/_xlfn.XLOOKUP("Revenue (Sales)",Inputs!$B:$B,Inputs!N:N),"") -> 4.9613592 | N6: =IFERROR(_xlfn.XLOOKUP("Enterprise Value",Inputs!$B:$B,Inputs!O:O)/_xlfn.XLOOKUP("Revenue (Sales)",Inputs!$B:$B,Inputs!O:O),"") -> 1.7812847 | O6: =IFERROR(_xlfn.XLOOKUP("Enterprise Value",Inputs!$B:$B,Inputs!P:P)/_xlfn.XLOOKUP("Revenue (Sales)",Inputs!$B:$B,Inputs!P:P),"") -> 3.5686019 | P6: =IFERROR(_xlfn.XLOOKUP("Enterprise Value",Inputs!$B:$B,Inputs!Q:Q)/_xlfn.XLOOKUP("Revenue (Sales)",Inputs!$B:$B,Inputs!Q:Q),"") -> 2.9318812 | Q6: =IFERROR(_xlfn.XLOOKUP("Enterprise Value",[1]DCF!$B:$B,[1]DCF!R:R)/_xlfn.XLOOKUP("Revenue (Sales)",[1]DCF!$B:$B,[1]DCF!H:H),"") -> 3.1162152 | R6: =IFERROR(_xlfn.XLOOKUP("Enterprise Value",[1]DCF!$B:$B,[1]DCF!S:S)/_xlfn.XLOOKUP("Revenue (Sales)",[1]DCF!$B:$B,[1]DCF!I:I),"") -> 2.8733681
B7: Price / Sales | F7: =IFERROR(_xlfn.XLOOKUP("Market Capitalization",Inputs!$B:$B,Inputs!G:G)/_xlfn.XLOOKUP("Revenue (Sales)",Inputs!$B:$B,Inputs!G:G),"") | G7: =IFERROR(_xlfn.XLOOKUP("Market Capitalization",Inputs!$B:$B,Inputs!H:H)/_xlfn.XLOOKUP("Revenue (Sales)",Inputs!$B:$B,Inputs!H:H),"") | H7: =IFERROR(_xlfn.XLOOKUP("Market Capitalization",Inputs!$B:$B,Inputs!I:I)/_xlfn.XLOOKUP("Revenue (Sales)",Inputs!$B:$B,Inputs!I:I),"") | I7: =IFERROR(_xlfn.XLOOKUP("Market Capitalization",Inputs!$B:$B,Inputs!J:J)/_xlfn.XLOOKUP("Revenue (Sales)",Inputs!$B:$B,Inputs!J:J),"") | J7: =IFERROR(_xlfn.XLOOKUP("Market Capitalization",Inputs!$B:$B,Inputs!K:K)/_xlfn.XLOOKUP("Revenue (Sales)",Inputs!$B:$B,Inputs!K:K),"") | K7: =IFERROR(_xlfn.XLOOKUP("Market Capitalization",Inputs!$B:$B,Inputs!L:L)/_xlfn.XLOOKUP("Revenue (Sales)",Inputs!$B:$B,Inputs!L:L),"") -> 2.8559551 | L7: =IFERROR(_xlfn.XLOOKUP("Market Capitalization",Inputs!$B:$B,Inputs!M:M)/_xlfn.XLOOKUP("Revenue (Sales)",Inputs!$B:$B,Inputs!M:M),"") -> 8.0261244 | M7: =IFERROR(_xlfn.XLOOKUP("Market Capitalization",Inputs!$B:$B,Inputs!N:N)/_xlfn.XLOOKUP("Revenue (Sales)",Inputs!$B:$B,Inputs!N:N),"") -> 4.54612 | N7: =IFERROR(_xlfn.XLOOKUP("Market Capitalization",Inputs!$B:$B,Inputs!O:O)/_xlfn.XLOOKUP("Revenue (Sales)",Inputs!$B:$B,Inputs!O:O),"") -> 1.5410801 | O7: =IFERROR(_xlfn.XLOOKUP("Market Capitalization",Inputs!$B:$B,Inputs!P:P)/_xlfn.XLOOKUP("Revenue (Sales)",Inputs!$B:$B,Inputs!P:P),"") -> 3.3619819 | P7: =IFERROR(_xlfn.XLOOKUP("Market Capitalization",Inputs!$B:$B,Inputs!Q:Q)/_xlfn.XLOOKUP("Revenue (Sales)",Inputs!$B:$B,Inputs!Q:Q),"") -> 2.8729427 | Q7: =IFERROR(_xlfn.XLOOKUP("Equity Value",[1]DCF!$B:$B,[1]DCF!R:R)/_xlfn.XLOOKUP("Revenue (Sales)",[1]DCF!$B:$B,[1]DCF!H:H),"") -> 2.9410175 | R7: =IFERROR(_xlfn.XLOOKUP("Equity Value",[1]DCF!$B:$B,[1]DCF!S:S)/_xlfn.XLOOKUP("Revenue (Sales)",[1]DCF!$B:$B,[1]DCF!I:I),"") -> 2.7937255
B8: EV / EBITDA | F8: =IFERROR(_xlfn.XLOOKUP("Enterprise Value",Inputs!$B:$B,Inputs!G:G)/_xlfn.XLOOKUP("EBITDA",Inputs!$B:$B,Inputs!G:G),"") | G8: =IFERROR(_xlfn.XLOOKUP("Enterprise Value",Inputs!$B:$B,Inputs!H:H)/_xlfn.XLOOKUP("EBITDA",Inputs!$B:$B,Inputs!H:H),"") | H8: =IFERROR(_xlfn.XLOOKUP("Enterprise Value",Inputs!$B:$B,Inputs!I:I)/_xlfn.XLOOKUP("EBITDA",Inputs!$B:$B,Inputs!I:I),"") | I8: =IFERROR(_xlfn.XLOOKUP("Enterprise Value",Inputs!$B:$B,Inputs!J:J)/_xlfn.XLOOKUP("EBITDA",Inputs!$B:$B,Inputs!J:J),"") | J8: =IFERROR(_xlfn.XLOOKUP("Enterprise Value",Inputs!$B:$B,Inputs!K:K)/_xlfn.XLOOKUP("EBITDA",Inputs!$B:$B,Inputs!K:K),"") | K8: =IFERROR(_xlfn.XLOOKUP("Enterprise Value",Inputs!$B:$B,Inputs!L:L)/_xlfn.XLOOKUP("EBITDA",Inputs!$B:$B,Inputs!L:L),"") -> -4.1678257 | L8: =IFERROR(_xlfn.XLOOKUP("Enterprise Value",Inputs!$B:$B,Inputs!M:M)/_xlfn.XLOOKUP("EBITDA",Inputs!$B:$B,Inputs!M:M),"") -> -21.674207 | M8: =IFERROR(_xlfn.XLOOKUP("Enterprise Value",Inputs!$B:$B,Inputs!N:N)/_xlfn.XLOOKUP("EBITDA",Inputs!$B:$B,Inputs!N:N),"") -> -29.536332 | N8: =IFERROR(_xlfn.XLOOKUP("Enterprise Value",Inputs!$B:$B,Inputs!O:O)/_xlfn.XLOOKUP("EBITDA",Inputs!$B:$B,Inputs!O:O),"") -> -64.160464 | O8: =IFERROR(_xlfn.XLOOKUP("Enterprise Value",Inputs!$B:$B,Inputs!P:P)/_xlfn.XLOOKUP("EBITDA",Inputs!$B:$B,Inputs!P:P),"") -> 68.826202 | P8: =IFERROR(_xlfn.XLOOKUP("Enterprise Value",Inputs!$B:$B,Inputs!Q:Q)/_xlfn.XLOOKUP("EBITDA",Inputs!$B:$B,Inputs!Q:Q),"") -> 36.73455 | Q8: =IFERROR(_xlfn.XLOOKUP("Enterprise Value",[1]DCF!$B:$B,[1]DCF!R:R)/_xlfn.XLOOKUP("EBITDA",[1]DCF!$B:$B,[1]DCF!H:H),"") -> 44.656863 | R8: =IFERROR(_xlfn.XLOOKUP("Enterprise Value",[1]DCF!$B:$B,[1]DCF!S:S)/_xlfn.XLOOKUP("EBITDA",[1]DCF!$B:$B,[1]DCF!I:I),"") -> 35.445728
B9: EV / EBIT | F9: =IFERROR(_xlfn.XLOOKUP("Enterprise Value",Inputs!$B:$B,Inputs!G:G)/_xlfn.XLOOKUP("Operating Income (EBIT)",Inputs!$B:$B,Inputs!G:G),"") | G9: =IFERROR(_xlfn.XLOOKUP("Enterprise Value",Inputs!$B:$B,Inputs!H:H)/_xlfn.XLOOKUP("Operating Income (EBIT)",Inputs!$B:$B,Inputs!H:H),"") | H9: =IFERROR(_xlfn.XLOOKUP("Enterprise Value",Inputs!$B:$B,Inputs!I:I)/_xlfn.XLOOKUP("Operating Income (EBIT)",Inputs!$B:$B,Inputs!I:I),"") | I9: =IFERROR(_xlfn.XLOOKUP("Enterprise Value",Inputs!$B:$B,Inputs!J:J)/_xlfn.XLOOKUP("Operating Income (EBIT)",Inputs!$B:$B,Inputs!J:J),"") | J9: =IFERROR(_xlfn.XLOOKUP("Enterprise Value",Inputs!$B:$B,Inputs!K:K)/_xlfn.XLOOKUP("Operating Income (EBIT)",Inputs!$B:$B,Inputs!K:K),"") | K9: =IFERROR(_xlfn.XLOOKUP("Enterprise Value",Inputs!$B:$B,Inputs!L:L)/_xlfn.XLOOKUP("Operating Income (EBIT)",Inputs!$B:$B,Inputs!L:L),"") -> -3.9389735 | L9: =IFERROR(_xlfn.XLOOKUP("Enterprise Value",Inputs!$B:$B,Inputs!M:M)/_xlfn.XLOOKUP("Operating Income (EBIT)",Inputs!$B:$B,Inputs!M:M),"") -> -19.111454 | M9: =IFERROR(_xlfn.XLOOKUP("Enterprise Value",Inputs!$B:$B,Inputs!N:N)/_xlfn.XLOOKUP("Operating Income (EBIT)",Inputs!$B:$B,Inputs!N:N),"") -> -22.587513 | N9: =IFERROR(_xlfn.XLOOKUP("Enterprise Value",Inputs!$B:$B,Inputs!O:O)/_xlfn.XLOOKUP("Operating Income (EBIT)",Inputs!$B:$B,Inputs!O:O),"") -> -30.994547 | O9: =IFERROR(_xlfn.XLOOKUP("Enterprise Value",Inputs!$B:$B,Inputs!P:P)/_xlfn.XLOOKUP("Operating Income (EBIT)",Inputs!$B:$B,Inputs!P:P),"") -> 119.8568 | P9: =IFERROR(_xlfn.XLOOKUP("Enterprise Value",Inputs!$B:$B,Inputs!Q:Q)/_xlfn.XLOOKUP("Operating Income (EBIT)",Inputs!$B:$B,Inputs!Q:Q),"") -> 46.065835 | Q9: =IFERROR(_xlfn.XLOOKUP("Enterprise Value",[1]DCF!$B:$B,[1]DCF!R:R)/_xlfn.XLOOKUP("Operating Income (EBIT)",[1]DCF!$B:$B,[1]DCF!H:H),"") -> 57.428454 | R9: =IFERROR(_xlfn.XLOOKUP("Enterprise Value",[1]DCF!$B:$B,[1]DCF!S:S)/_xlfn.XLOOKUP("Operating Income (EBIT)",[1]DCF!$B:$B,[1]DCF!I:I),"") -> 43.17702
B10: Price / Earnings | F10: =IFERROR(_xlfn.XLOOKUP("Market Capitalization",Inputs!$B:$B,Inputs!G:G)/_xlfn.XLOOKUP("Net Income",Inputs!$B:$B,Inputs!G:G),"") | G10: =IFERROR(_xlfn.XLOOKUP("Market Capitalization",Inputs!$B:$B,Inputs!H:H)/_xlfn.XLOOKUP("Net Income",Inputs!$B:$B,Inputs!H:H),"") | H10: =IFERROR(_xlfn.XLOOKUP("Market Capitalization",Inputs!$B:$B,Inputs!I:I)/_xlfn.XLOOKUP("Net Income",Inputs!$B:$B,Inputs!I:I),"") | I10: =IFERROR(_xlfn.XLOOKUP("Market Capitalization",Inputs!$B:$B,Inputs!J:J)/_xlfn.XLOOKUP("Net Income",Inputs!$B:$B,Inputs!J:J),"") | J10: =IFERROR(_xlfn.XLOOKUP("Market Capitalization",Inputs!$B:$B,Inputs!K:K)/_xlfn.XLOOKUP("Net Income",Inputs!$B:$B,Inputs!K:K),"") | K10: =IFERROR(_xlfn.XLOOKUP("Market Capitalization",Inputs!$B:$B,Inputs!L:L)/_xlfn.XLOOKUP("Net Income",Inputs!$B:$B,Inputs!L:L),"") -> -4.3792659 | L10: =IFERROR(_xlfn.XLOOKUP("Market Capitalization",Inputs!$B:$B,Inputs!M:M)/_xlfn.XLOOKUP("Net Income",Inputs!$B:$B,Inputs!M:M),"") -> -24.493973 | M10: =IFERROR(_xlfn.XLOOKUP("Market Capitalization",Inputs!$B:$B,Inputs!N:N)/_xlfn.XLOOKUP("Net Income",Inputs!$B:$B,Inputs!N:N),"") -> -148.87903 | N10: =IFERROR(_xlfn.XLOOKUP("Market Capitalization",Inputs!$B:$B,Inputs!O:O)/_xlfn.XLOOKUP("Net Income",Inputs!$B:$B,Inputs!O:O),"") -> -5.3136843 | O10: =IFERROR(_xlfn.XLOOKUP("Market Capitalization",Inputs!$B:$B,Inputs!P:P)/_xlfn.XLOOKUP("Net Income",Inputs!$B:$B,Inputs!P:P),"") -> 59.458278 | P10: =IFERROR(_xlfn.XLOOKUP("Market Capitalization",Inputs!$B:$B,Inputs!Q:Q)/_xlfn.XLOOKUP("Net Income",Inputs!$B:$B,Inputs!Q:Q),"") -> 12.784202 | Q10: =IFERROR(_xlfn.XLOOKUP("Equity Value",[1]DCF!$B:$B,[1]DCF!R:R)/_xlfn.XLOOKUP("Net Income",[1]DCF!$B:$B,[1]DCF!H:H),"") -> 93.432868 | R10: =IFERROR(_xlfn.XLOOKUP("Equity Value",[1]DCF!$B:$B,[1]DCF!S:S)/_xlfn.XLOOKUP("Net Income",[1]DCF!$B:$B,[1]DCF!I:I),"") -> 39.866388
B11: Price / Book | F11: =IFERROR(_xlfn.XLOOKUP("Market Capitalization",Inputs!$B:$B,Inputs!G:G)/_xlfn.XLOOKUP("Shareholder's Equity",Inputs!$B:$B,Inputs!G:G),"") | G11: =IFERROR(_xlfn.XLOOKUP("Market Capitalization",Inputs!$B:$B,Inputs!H:H)/_xlfn.XLOOKUP("Shareholder's Equity",Inputs!$B:$B,Inputs!H:H),"") | H11: =IFERROR(_xlfn.XLOOKUP("Market Capitalization",Inputs!$B:$B,Inputs!I:I)/_xlfn.XLOOKUP("Shareholder's Equity",Inputs!$B:$B,Inputs!I:I),"") | I11: =IFERROR(_xlfn.XLOOKUP("Market Capitalization",Inputs!$B:$B,Inputs!J:J)/_xlfn.XLOOKUP("Shareholder's Equity",Inputs!$B:$B,Inputs!J:J),"") | J11: =IFERROR(_xlfn.XLOOKUP("Market Capitalization",Inputs!$B:$B,Inputs!K:K)/_xlfn.XLOOKUP("Shareholder's Equity",Inputs!$B:$B,Inputs!K:K),"") | K11: =IFERROR(_xlfn.XLOOKUP("Market Capitalization",Inputs!$B:$B,Inputs!L:L)/_xlfn.XLOOKUP("Shareholder's Equity",Inputs!$B:$B,Inputs!L:L),"") -> 2.4453281 | L11: =IFERROR(_xlfn.XLOOKUP("Market Capitalization",Inputs!$B:$B,Inputs!M:M)/_xlfn.XLOOKUP("Shareholder's Equity",Inputs!$B:$B,Inputs!M:M),"") -> 6.5001454 | M11: =IFERROR(_xlfn.XLOOKUP("Market Capitalization",Inputs!$B:$B,Inputs!N:N)/_xlfn.XLOOKUP("Shareholder's Equity",Inputs!$B:$B,Inputs!N:N),"") -> 5.1698824 | N11: =IFERROR(_xlfn.XLOOKUP("Market Capitalization",Inputs!$B:$B,Inputs!O:O)/_xlfn.XLOOKUP("Shareholder's Equity",Inputs!$B:$B,Inputs!O:O),"") -> 5.7766946 | O11: =IFERROR(_xlfn.XLOOKUP("Market Capitalization",Inputs!$B:$B,Inputs!P:P)/_xlfn.XLOOKUP("Shareholder's Equity",Inputs!$B:$B,Inputs!P:P),"") -> 9.8831453 | P11: =IFERROR(_xlfn.XLOOKUP("Market Capitalization",Inputs!$B:$B,Inputs!Q:Q)/_xlfn.XLOOKUP("Shareholder's Equity",Inputs!$B:$B,Inputs!Q:Q),"") -> 5.621386 | Q11: =IFERROR(+_xlfn.XLOOKUP("Equity Value",[1]DCF!$B:$B,[1]DCF!R:R)/(_xlfn.XLOOKUP("Shareholder's Equity",[1]Inputs!$B:$B,[1]Inputs!$Q:$Q)+_xlfn.XLOOKUP("Net Income",[1]DCF!$B:$B,[1]DCF!H:H)+_xlfn.XLOOKUP("Total Payout",[1]DCF!$B:$B,[1]DCF!H:H)),"") -> 6.5977806 | R11: =IFERROR(+_xlfn.XLOOKUP("Equity Value",[1]DCF!$B:$B,[1]DCF!S:S)/(_xlfn.XLOOKUP("Shareholder's Equity",[1]Inputs!$B:$B,[1]Inputs!$Q:$Q)+_xlfn.XLOOKUP("Net Income",[1]DCF!$B:$B,[1]DCF!I:I)+_xlfn.XLOOKUP("Total Payout",[1]DCF!$B:$B,[1]DCF!I:I)),"") -> 6.5164074
B13: Profitability | F13: 2014 | G13: =+F13+1 -> 2015 | H13: =+G13+1 -> 2016 | I13: =+H13+1 -> 2017 | J13: =+I13+1 -> 2018 | K13: =+J13+1 -> 2019 | L13: =+K13+1 -> 2020 | M13: =+L13+1 -> 2021 | N13: 2022 | O13: =+N13+1 -> 2023 | P13: =+O13+1 -> 2024 | Q13: =+P13+1 -> 2025 | R13: =+Q13+1 -> 2026
B15: Return on Assets | F15: =+IFERROR(_xlfn.XLOOKUP("Net Income",Inputs!$B:$B,Inputs!G:G)/_xlfn.XLOOKUP("Total Assets",Inputs!$B:$B,Inputs!G:G),"") | G15: =+IFERROR(_xlfn.XLOOKUP("Net Income",Inputs!$B:$B,Inputs!H:H)/_xlfn.XLOOKUP("Total Assets",Inputs!$B:$B,Inputs!H:H),"") | H15: =+IFERROR(_xlfn.XLOOKUP("Net Income",Inputs!$B:$B,Inputs!I:I)/_xlfn.XLOOKUP("Total Assets",Inputs!$B:$B,Inputs!I:I),"") | I15: =+IFERROR(_xlfn.XLOOKUP("Net Income",Inputs!$B:$B,Inputs!J:J)/_xlfn.XLOOKUP("Total Assets",Inputs!$B:$B,Inputs!J:J),"") -> -0.26144172 | J15: =+IFERROR(_xlfn.XLOOKUP("Net Income",Inputs!$B:$B,Inputs!K:K)/_xlfn.XLOOKUP("Total Assets",Inputs!$B:$B,Inputs!K:K),"") -> 0.042896448 | K15: =+IFERROR(_xlfn.XLOOKUP("Net Income",Inputs!$B:$B,Inputs!L:L)/_xlfn.XLOOKUP("Total Assets",Inputs!$B:$B,Inputs!L:L),"") -> -0.26693114 | L15: =+IFERROR(_xlfn.XLOOKUP("Net Income",Inputs!$B:$B,Inputs!M:M)/_xlfn.XLOOKUP("Total Assets",Inputs!$B:$B,Inputs!M:M),"") -> -0.10976783 | M15: =+IFERROR(_xlfn.XLOOKUP("Net Income",Inputs!$B:$B,Inputs!N:N)/_xlfn.XLOOKUP("Total Assets",Inputs!$B:$B,Inputs!N:N),"") -> -0.013746325 | N15: =+IFERROR(_xlfn.XLOOKUP("Net Income",Inputs!$B:$B,Inputs!O:O)/_xlfn.XLOOKUP("Total Assets",Inputs!$B:$B,Inputs!O:O),"") -> -0.2879255 | O15: =+IFERROR(_xlfn.XLOOKUP("Net Income",Inputs!$B:$B,Inputs!P:P)/_xlfn.XLOOKUP("Total Assets",Inputs!$B:$B,Inputs!P:P),"") -> 0.054471692 | P15: =+IFERROR(_xlfn.XLOOKUP("Net Income",Inputs!$B:$B,Inputs!Q:Q)/_xlfn.XLOOKUP("Total Assets",Inputs!$B:$B,Inputs!Q:Q),"") -> 0.1928616 | Q15: =+DCF!H77/DCF!T89 -> 0.029093078 | R15: =+DCF!I77/DCF!Z89 -> 0.083634594
B16: Return on Equity | F16: =IFERROR(_xlfn.XLOOKUP("Net Income",Inputs!$B:$B,Inputs!G:G)/_xlfn.XLOOKUP("Shareholder's Equity",Inputs!$B:$B,Inputs!G:G),"") | G16: =IFERROR(_xlfn.XLOOKUP("Net Income",Inputs!$B:$B,Inputs!H:H)/_xlfn.XLOOKUP("Shareholder's Equity",Inputs!$B:$B,Inputs!H:H),"") | H16: =IFERROR(_xlfn.XLOOKUP("Net Income",Inputs!$B:$B,Inputs!I:I)/_xlfn.XLOOKUP("Shareholder's Equity",Inputs!$B:$B,Inputs!I:I),"") | I16: =IFERROR(_xlfn.XLOOKUP("Net Income",Inputs!$B:$B,Inputs!J:J)/_xlfn.XLOOKUP("Shareholder's Equity",Inputs!$B:$B,Inputs!J:J),"") -> -1.1040241 | J16: =IFERROR(_xlfn.XLOOKUP("Net Income",Inputs!$B:$B,Inputs!K:K)/_xlfn.XLOOKUP("Shareholder's Equity",Inputs!$B:$B,Inputs!K:K),"") -> 0.15150177 | K16: =IFERROR(_xlfn.XLOOKUP("Net Income",Inputs!$B:$B,Inputs!L:L)/_xlfn.XLOOKUP("Shareholder's Equity",Inputs!$B:$B,Inputs!L:L),"") -> -0.55838767 | L16: =IFERROR(_xlfn.XLOOKUP("Net Income",Inputs!$B:$B,Inputs!M:M)/_xlfn.XLOOKUP("Shareholder's Equity",Inputs!$B:$B,Inputs!M:M),"") -> -0.26537734 | M16: =IFERROR(_xlfn.XLOOKUP("Net Income",Inputs!$B:$B,Inputs!N:N)/_xlfn.XLOOKUP("Shareholder's Equity",Inputs!$B:$B,Inputs!N:N),"") -> -0.034725389 | N16: =IFERROR(_xlfn.XLOOKUP("Net Income",Inputs!$B:$B,Inputs!O:O)/_xlfn.XLOOKUP("Shareholder's Equity",Inputs!$B:$B,Inputs!O:O),"") -> -1.0871355 | O16: =IFERROR(_xlfn.XLOOKUP("Net Income",Inputs!$B:$B,Inputs!P:P)/_xlfn.XLOOKUP("Shareholder's Equity",Inputs!$B:$B,Inputs!P:P),"") -> 0.16621984 | P16: =IFERROR(_xlfn.XLOOKUP("Net Income",Inputs!$B:$B,Inputs!Q:Q)/_xlfn.XLOOKUP("Shareholder's Equity",Inputs!$B:$B,Inputs!Q:Q),"") -> 0.43971347 | Q16: =+DCF!H77/DCF!T90 -> 0.06919639 | R16: =+DCF!I77/DCF!Z90 -> 0.19261473
B17: Return on Total Capital | F17: =IFERROR(_xlfn.XLOOKUP("NOPAT",Inputs!$B:$B,Inputs!G:G)/(_xlfn.XLOOKUP("Shareholder's Equity",Inputs!$B:$B,Inputs!G:G)+_xlfn.XLOOKUP("Total Debt",Inputs!$B:$B,Inputs!G:G,,,-1)),"") | G17: =IFERROR(_xlfn.XLOOKUP("NOPAT",Inputs!$B:$B,Inputs!H:H)/(_xlfn.XLOOKUP("Shareholder's Equity",Inputs!$B:$B,Inputs!H:H)+_xlfn.XLOOKUP("Total Debt",Inputs!$B:$B,Inputs!H:H,,,-1)),"") -> -0.93644086 | H17: =IFERROR(_xlfn.XLOOKUP("NOPAT",Inputs!$B:$B,Inputs!I:I)/(_xlfn.XLOOKUP("Shareholder's Equity",Inputs!$B:$B,Inputs!I:I)+_xlfn.XLOOKUP("Total Debt",Inputs!$B:$B,Inputs!I:I,,,-1)),"") -> -1.0594419 | I17: =IFERROR(_xlfn.XLOOKUP("NOPAT",Inputs!$B:$B,Inputs!J:J)/(_xlfn.XLOOKUP("Shareholder's Equity",Inputs!$B:$B,Inputs!J:J)+_xlfn.XLOOKUP("Total Debt",Inputs!$B:$B,Inputs!J:J,,,-1)),"") -> -0.53673222 | J17: =IFERROR(_xlfn.XLOOKUP("NOPAT",Inputs!$B:$B,Inputs!K:K)/(_xlfn.XLOOKUP("Shareholder's Equity",Inputs!$B:$B,Inputs!K:K)+_xlfn.XLOOKUP("Total Debt",Inputs!$B:$B,Inputs!K:K,,,-1)),"") -> -0.17412914 | K17: =IFERROR(_xlfn.XLOOKUP("NOPAT",Inputs!$B:$B,Inputs!L:L)/(_xlfn.XLOOKUP("Shareholder's Equity",Inputs!$B:$B,Inputs!L:L)+_xlfn.XLOOKUP("Total Debt",Inputs!$B:$B,Inputs!L:L,,,-1)),"") -> -0.37709429 | L17: =IFERROR(_xlfn.XLOOKUP("NOPAT",Inputs!$B:$B,Inputs!M:M)/(_xlfn.XLOOKUP("Shareholder's Equity",Inputs!$B:$B,Inputs!M:M)+_xlfn.XLOOKUP("Total Debt",Inputs!$B:$B,Inputs!M:M,,,-1)),"") -> -0.19802729 | M17: =IFERROR(_xlfn.XLOOKUP("NOPAT",Inputs!$B:$B,Inputs!N:N)/(_xlfn.XLOOKUP("Shareholder's Equity",Inputs!$B:$B,Inputs!N:N)+_xlfn.XLOOKUP("Total Debt",Inputs!$B:$B,Inputs!N:N,,,-1)),"") -> -0.074703237 | N17: =IFERROR(_xlfn.XLOOKUP("NOPAT",Inputs!$B:$B,Inputs!O:O)/(_xlfn.XLOOKUP("Shareholder's Equity",Inputs!$B:$B,Inputs!O:O)+_xlfn.XLOOKUP("Total Debt",Inputs!$B:$B,Inputs!O:O,,,-1)),"") -> -0.089652807 | O17: =IFERROR(_xlfn.XLOOKUP("NOPAT",Inputs!$B:$B,Inputs!P:P)/(_xlfn.XLOOKUP("Shareholder's Equity",Inputs!$B:$B,Inputs!P:P)+_xlfn.XLOOKUP("Total Debt",Inputs!$B:$B,Inputs!P:P,,,-1)),"") -> 0.041386528 | P17: =IFERROR(_xlfn.XLOOKUP("NOPAT",Inputs!$B:$B,Inputs!Q:Q)/(_xlfn.XLOOKUP("Shareholder's Equity",Inputs!$B:$B,Inputs!Q:Q)+_xlfn.XLOOKUP("Total Debt",Inputs!$B:$B,Inputs!Q:Q,,,-1)),"") -> 0.21544205 | Q17: =+DCF!H178/(DCF!T90+SUM(DCF!H112:H114)) -> 0.068078497 | R17: =+DCF!I178/(DCF!Z90+SUM(DCF!I112:I114)) -> 0.11984609
B18: EBITDA Margin | F18: =+IFERROR(_xlfn.XLOOKUP("EBITDA",Inputs!$B:$B,Inputs!G:G)/_xlfn.XLOOKUP("Revenue (Sales)",Inputs!$B:$B,Inputs!G:G),"") -> -1.2787879 | G18: =+IFERROR(_xlfn.XLOOKUP("EBITDA",Inputs!$B:$B,Inputs!H:H)/_xlfn.XLOOKUP("Revenue (Sales)",Inputs!$B:$B,Inputs!H:H),"") -> -0.63258145 | H18: =+IFERROR(_xlfn.XLOOKUP("EBITDA",Inputs!$B:$B,Inputs!I:I)/_xlfn.XLOOKUP("Revenue (Sales)",Inputs!$B:$B,Inputs!I:I),"") -> -0.7029909 | I18: =+IFERROR(_xlfn.XLOOKUP("EBITDA",Inputs!$B:$B,Inputs!J:J)/_xlfn.XLOOKUP("Revenue (Sales)",Inputs!$B:$B,Inputs!J:J),"") -> -0.45007564 | J18: =+IFERROR(_xlfn.XLOOKUP("EBITDA",Inputs!$B:$B,Inputs!K:K)/_xlfn.XLOOKUP("Revenue (Sales)",Inputs!$B:$B,Inputs!K:K),"") -> -0.24988019 | K18: =+IFERROR(_xlfn.XLOOKUP("EBITDA",Inputs!$B:$B,Inputs!L:L)/_xlfn.XLOOKUP("Revenue (Sales)",Inputs!$B:$B,Inputs!L:L),"") -> -0.62492308 | L18: =+IFERROR(_xlfn.XLOOKUP("EBITDA",Inputs!$B:$B,Inputs!M:M)/_xlfn.XLOOKUP("Revenue (Sales)",Inputs!$B:$B,Inputs!M:M),"") -> -0.38495377 | M18: =+IFERROR(_xlfn.XLOOKUP("EBITDA",Inputs!$B:$B,Inputs!N:N)/_xlfn.XLOOKUP("Revenue (Sales)",Inputs!$B:$B,Inputs!N:N),"") -> -0.16797479 | N18: =+IFERROR(_xlfn.XLOOKUP("EBITDA",Inputs!$B:$B,Inputs!O:O)/_xlfn.XLOOKUP("Revenue (Sales)",Inputs!$B:$B,Inputs!O:O),"") -> -0.027762964 | O18: =+IFERROR(_xlfn.XLOOKUP("EBITDA",Inputs!$B:$B,Inputs!P:P)/_xlfn.XLOOKUP("Revenue (Sales)",Inputs!$B:$B,Inputs!P:P),"") -> 0.051849468 | P18: =+IFERROR(_xlfn.XLOOKUP("EBITDA",Inputs!$B:$B,Inputs!Q:Q)/_xlfn.XLOOKUP("Revenue (Sales)",Inputs!$B:$B,Inputs!Q:Q),"") -> 0.079812634 | Q18: =+_xlfn.XLOOKUP("EBITDA Margin",DCF!$B:$B,DCF!H:H) -> 0.070234737 | R18: =+_xlfn.XLOOKUP("EBITDA Margin",DCF!$B:$B,DCF!I:I) -> 0.083041581
B19: EBIT Margin | F19: =IFERROR(_xlfn.XLOOKUP("Operating Income (EBIT)",Inputs!$B:$B,Inputs!G:G)/_xlfn.XLOOKUP("Revenue (Sales)",Inputs!$B:$B,Inputs!G:G),"") -> -1.3010101 | G19: =IFERROR(_xlfn.XLOOKUP("Operating Income (EBIT)",Inputs!$B:$B,Inputs!H:H)/_xlfn.XLOOKUP("Revenue (Sales)",Inputs!$B:$B,Inputs!H:H),"") -> -0.67117794 | H19: =IFERROR(_xlfn.XLOOKUP("Operating Income (EBIT)",Inputs!$B:$B,Inputs!I:I)/_xlfn.XLOOKUP("Revenue (Sales)",Inputs!$B:$B,Inputs!I:I),"") -> -0.78621586 | I19: =IFERROR(_xlfn.XLOOKUP("Operating Income (EBIT)",Inputs!$B:$B,Inputs!J:J)/_xlfn.XLOOKUP("Revenue (Sales)",Inputs!$B:$B,Inputs!J:J),"") -> -0.51437216 | J19: =IFERROR(_xlfn.XLOOKUP("Operating Income (EBIT)",Inputs!$B:$B,Inputs!K:K)/_xlfn.XLOOKUP("Revenue (Sales)",Inputs!$B:$B,Inputs!K:K),"") -> -0.29071216 | K19: =IFERROR(_xlfn.XLOOKUP("Operating Income (EBIT)",Inputs!$B:$B,Inputs!L:L)/_xlfn.XLOOKUP("Revenue (Sales)",Inputs!$B:$B,Inputs!L:L),"") -> -0.66123077 | L19: =IFERROR(_xlfn.XLOOKUP("Operating Income (EBIT)",Inputs!$B:$B,Inputs!M:M)/_xlfn.XLOOKUP("Revenue (Sales)",Inputs!$B:$B,Inputs!M:M),"") -> -0.4365742 | M19: =IFERROR(_xlfn.XLOOKUP("Operating Income (EBIT)",Inputs!$B:$B,Inputs!N:N)/_xlfn.XLOOKUP("Revenue (Sales)",Inputs!$B:$B,Inputs!N:N),"") -> -0.21965053 | N19: =IFERROR(_xlfn.XLOOKUP("Operating Income (EBIT)",Inputs!$B:$B,Inputs!O:O)/_xlfn.XLOOKUP("Revenue (Sales)",Inputs!$B:$B,Inputs!O:O),"") -> -0.057470904 | O19: =IFERROR(_xlfn.XLOOKUP("Operating Income (EBIT)",Inputs!$B:$B,Inputs!P:P)/_xlfn.XLOOKUP("Revenue (Sales)",Inputs!$B:$B,Inputs!P:P),"") -> 0.029773879 | P19: =IFERROR(_xlfn.XLOOKUP("Operating Income (EBIT)",Inputs!$B:$B,Inputs!Q:Q)/_xlfn.XLOOKUP("Revenue (Sales)",Inputs!$B:$B,Inputs!Q:Q),"") -> 0.063645459 | Q19: =+_xlfn.XLOOKUP("Operating Margin",DCF!$B:$B,DCF!H:H) -> 0.055215463 | R19: =+_xlfn.XLOOKUP("Operating Margin",DCF!$B:$B,DCF!I:I) -> 0.068219208
B20: EBT Margin | F20: =IFERROR(_xlfn.XLOOKUP("Pre-Tax Income (EBT)",Inputs!$B:$B,Inputs!G:G)/_xlfn.XLOOKUP("Revenue (Sales)",Inputs!$B:$B,Inputs!G:G),"") -> -1.3494949 | G20: =IFERROR(_xlfn.XLOOKUP("Pre-Tax Income (EBT)",Inputs!$B:$B,Inputs!H:H)/_xlfn.XLOOKUP("Revenue (Sales)",Inputs!$B:$B,Inputs!H:H),"") -> -1.3538847 | H20: =IFERROR(_xlfn.XLOOKUP("Pre-Tax Income (EBT)",Inputs!$B:$B,Inputs!I:I)/_xlfn.XLOOKUP("Revenue (Sales)",Inputs!$B:$B,Inputs!I:I),"") -> -0.088946684 | I20: =IFERROR(_xlfn.XLOOKUP("Pre-Tax Income (EBT)",Inputs!$B:$B,Inputs!J:J)/_xlfn.XLOOKUP("Revenue (Sales)",Inputs!$B:$B,Inputs!J:J),"") -> -0.57677761 | J20: =IFERROR(_xlfn.XLOOKUP("Pre-Tax Income (EBT)",Inputs!$B:$B,Inputs!K:K)/_xlfn.XLOOKUP("Revenue (Sales)",Inputs!$B:$B,Inputs!K:K),"") -> 0.12575482 | K20: =IFERROR(_xlfn.XLOOKUP("Pre-Tax Income (EBT)",Inputs!$B:$B,Inputs!L:L)/_xlfn.XLOOKUP("Revenue (Sales)",Inputs!$B:$B,Inputs!L:L),"") -> -0.64869231 | L20: =IFERROR(_xlfn.XLOOKUP("Pre-Tax Income (EBT)",Inputs!$B:$B,Inputs!M:M)/_xlfn.XLOOKUP("Revenue (Sales)",Inputs!$B:$B,Inputs!M:M),"") -> -0.34491427 | M20: =IFERROR(_xlfn.XLOOKUP("Pre-Tax Income (EBT)",Inputs!$B:$B,Inputs!N:N)/_xlfn.XLOOKUP("Revenue (Sales)",Inputs!$B:$B,Inputs!N:N),"") -> -0.058722429 | N20: =IFERROR(_xlfn.XLOOKUP("Pre-Tax Income (EBT)",Inputs!$B:$B,Inputs!O:O)/_xlfn.XLOOKUP("Revenue (Sales)",Inputs!$B:$B,Inputs!O:O),"") -> -0.29569909 | O20: =IFERROR(_xlfn.XLOOKUP("Pre-Tax Income (EBT)",Inputs!$B:$B,Inputs!P:P)/_xlfn.XLOOKUP("Revenue (Sales)",Inputs!$B:$B,Inputs!P:P),"") -> 0.062256914 | P20: =IFERROR(_xlfn.XLOOKUP("Pre-Tax Income (EBT)",Inputs!$B:$B,Inputs!Q:Q)/_xlfn.XLOOKUP("Revenue (Sales)",Inputs!$B:$B,Inputs!Q:Q),"") -> 0.093796898 | Q20: =IFERROR(_xlfn.XLOOKUP("Pre-Tax Income (EBT)",DCF!$B:$B,DCF!H:H)/_xlfn.XLOOKUP("Revenue (Sales)",DCF!$B:$B,DCF!H:H),"") -> 0.037980888 | R20: =IFERROR(_xlfn.XLOOKUP("Pre-Tax Income (EBT)",DCF!$B:$B,DCF!I:I)/_xlfn.XLOOKUP("Revenue (Sales)",DCF!$B:$B,DCF!I:I),"") -> 0.075249877
B21: Gross Profit Margin | F21: =IFERROR(_xlfn.XLOOKUP("Gross Profit",Inputs!$B:$B,Inputs!G:G)/_xlfn.XLOOKUP("Revenue (Sales)",Inputs!$B:$B,Inputs!G:G),"") -> 0.21616162 | G21: =IFERROR(_xlfn.XLOOKUP("Gross Profit",Inputs!$B:$B,Inputs!H:H)/_xlfn.XLOOKUP("Revenue (Sales)",Inputs!$B:$B,Inputs!H:H),"") -> 0.46015038 | H21: =IFERROR(_xlfn.XLOOKUP("Gross Profit",Inputs!$B:$B,Inputs!I:I)/_xlfn.XLOOKUP("Revenue (Sales)",Inputs!$B:$B,Inputs!I:I),"") -> 0.42054616 | I21: =IFERROR(_xlfn.XLOOKUP("Gross Profit",Inputs!$B:$B,Inputs!J:J)/_xlfn.XLOOKUP("Revenue (Sales)",Inputs!$B:$B,Inputs!J:J),"") -> 0.47554211 | J21: =IFERROR(_xlfn.XLOOKUP("Gross Profit",Inputs!$B:$B,Inputs!K:K)/_xlfn.XLOOKUP("Revenue (Sales)",Inputs!$B:$B,Inputs!K:K),"") -> 0.5412633 | K21: =IFERROR(_xlfn.XLOOKUP("Gross Profit",Inputs!$B:$B,Inputs!L:L)/_xlfn.XLOOKUP("Revenue (Sales)",Inputs!$B:$B,Inputs!L:L),"") -> 0.53376923 | L21: =IFERROR(_xlfn.XLOOKUP("Gross Profit",Inputs!$B:$B,Inputs!M:M)/_xlfn.XLOOKUP("Revenue (Sales)",Inputs!$B:$B,Inputs!M:M),"") -> 0.53730137 | M21: =IFERROR(_xlfn.XLOOKUP("Gross Profit",Inputs!$B:$B,Inputs!N:N)/_xlfn.XLOOKUP("Revenue (Sales)",Inputs!$B:$B,Inputs!N:N),"") -> 0.46427958 | N21: =IFERROR(_xlfn.XLOOKUP("Gross Profit",Inputs!$B:$B,Inputs!O:O)/_xlfn.XLOOKUP("Revenue (Sales)",Inputs!$B:$B,Inputs!O:O),"") -> 0.38328575 | O21: =IFERROR(_xlfn.XLOOKUP("Gross Profit",Inputs!$B:$B,Inputs!P:P)/_xlfn.XLOOKUP("Revenue (Sales)",Inputs!$B:$B,Inputs!P:P),"") -> 0.39762882 | P21: =IFERROR(_xlfn.XLOOKUP("Gross Profit",Inputs!$B:$B,Inputs!Q:Q)/_xlfn.XLOOKUP("Revenue (Sales)",Inputs!$B:$B,Inputs!Q:Q),"") -> 0.39399245 | Q21: =+_xlfn.XLOOKUP("Gross Profit Margin",DCF!$B:$B,DCF!H:H) -> 0.39163567 | R21: =+_xlfn.XLOOKUP("Gross Profit Margin",DCF!$B:$B,DCF!I:I) -> 0.39441898
B22: SG&A Margin | F22: =IFERROR(+_xlfn.XLOOKUP("SG&A (Selling, General & Administrative)",Inputs!$B:$B,Inputs!G:G)/_xlfn.XLOOKUP("Revenue (Sales)",Inputs!$B:$B,Inputs!G:G),"") -> 0.9979798 | G22: =IFERROR(+_xlfn.XLOOKUP("SG&A (Selling, General & Administrative)",Inputs!$B:$B,Inputs!H:H)/_xlfn.XLOOKUP("Revenue (Sales)",Inputs!$B:$B,Inputs!H:H),"") -> 0.68471178 | H22: =IFERROR(+_xlfn.XLOOKUP("SG&A (Selling, General & Administrative)",Inputs!$B:$B,Inputs!I:I)/_xlfn.XLOOKUP("Revenue (Sales)",Inputs!$B:$B,Inputs!I:I),"") -> 0.66970091 | I22: =IFERROR(+_xlfn.XLOOKUP("SG&A (Selling, General & Administrative)",Inputs!$B:$B,Inputs!J:J)/_xlfn.XLOOKUP("Revenue (Sales)",Inputs!$B:$B,Inputs!J:J),"") -> 0.60350479 | J22: =IFERROR(+_xlfn.XLOOKUP("SG&A (Selling, General & Administrative)",Inputs!$B:$B,Inputs!K:K)/_xlfn.XLOOKUP("Revenue (Sales)",Inputs!$B:$B,Inputs!K:K),"") -> 0.50158152 | K22: =IFERROR(+_xlfn.XLOOKUP("SG&A (Selling, General & Administrative)",Inputs!$B:$B,Inputs!L:L)/_xlfn.XLOOKUP("Revenue (Sales)",Inputs!$B:$B,Inputs!L:L),"") -> 0.60961538 | L22: =IFERROR(+_xlfn.XLOOKUP("SG&A (Selling, General & Administrative)",Inputs!$B:$B,Inputs!M:M)/_xlfn.XLOOKUP("Revenue (Sales)",Inputs!$B:$B,Inputs!M:M),"") -> 0.56100189 | M22: =IFERROR(+_xlfn.XLOOKUP("SG&A (Selling, General & Administrative)",Inputs!$B:$B,Inputs!N:N)/_xlfn.XLOOKUP("Revenue (Sales)",Inputs!$B:$B,Inputs!N:N),"") -> 0.40704669 | N22: =IFERROR(+_xlfn.XLOOKUP("SG&A (Selling, General & Administrative)",Inputs!$B:$B,Inputs!O:O)/_xlfn.XLOOKUP("Revenue (Sales)",Inputs!$B:$B,Inputs!O:O),"") -> 0.24757662 | O22: =IFERROR(+_xlfn.XLOOKUP("SG&A (Selling, General & Administrative)",Inputs!$B:$B,Inputs!P:P)/_xlfn.XLOOKUP("Revenue (Sales)",Inputs!$B:$B,Inputs!P:P),"") -> 0.18878249 | P22: =IFERROR(+_xlfn.XLOOKUP("SG&A (Selling, General & Administrative)",Inputs!$B:$B,Inputs!Q:Q)/_xlfn.XLOOKUP("Revenue (Sales)",Inputs!$B:$B,Inputs!Q:Q),"") -> 0.18136341 | Q22: =+_xlfn.XLOOKUP("SG&A Margin",DCF!$B:$B,DCF!H:H) -> 0.18091 | R22: =+_xlfn.XLOOKUP("SG&A Margin",DCF!$B:$B,DCF!I:I) -> 0.18045773
B23: Net Income Margin | F23: =IFERROR(_xlfn.XLOOKUP("Net Income",Inputs!$B:$B,Inputs!G:G)/_xlfn.XLOOKUP("Revenue (Sales)",Inputs!$B:$B,Inputs!G:G),"") -> -1.3535354 | G23: =IFERROR(_xlfn.XLOOKUP("Net Income",Inputs!$B:$B,Inputs!H:H)/_xlfn.XLOOKUP("Revenue (Sales)",Inputs!$B:$B,Inputs!H:H),"") -> -1.3473684 | H23: =IFERROR(_xlfn.XLOOKUP("Net Income",Inputs!$B:$B,Inputs!I:I)/_xlfn.XLOOKUP("Revenue (Sales)",Inputs!$B:$B,Inputs!I:I),"") -> -0.096228869 | I23: =IFERROR(_xlfn.XLOOKUP("Net Income",Inputs!$B:$B,Inputs!J:J)/_xlfn.XLOOKUP("Revenue (Sales)",Inputs!$B:$B,Inputs!J:J),"") -> -0.5084468 | J23: =IFERROR(_xlfn.XLOOKUP("Net Income",Inputs!$B:$B,Inputs!K:K)/_xlfn.XLOOKUP("Revenue (Sales)",Inputs!$B:$B,Inputs!K:K),"") -> 0.098629349 | K23: =IFERROR(_xlfn.XLOOKUP("Net Income",Inputs!$B:$B,Inputs!L:L)/_xlfn.XLOOKUP("Revenue (Sales)",Inputs!$B:$B,Inputs!L:L),"") -> -0.65215385 | L23: =IFERROR(_xlfn.XLOOKUP("Net Income",Inputs!$B:$B,Inputs!M:M)/_xlfn.XLOOKUP("Revenue (Sales)",Inputs!$B:$B,Inputs!M:M),"") -> -0.32767753 | M23: =IFERROR(_xlfn.XLOOKUP("Net Income",Inputs!$B:$B,Inputs!N:N)/_xlfn.XLOOKUP("Revenue (Sales)",Inputs!$B:$B,Inputs!N:N),"") -> -0.030535663 | N23: =IFERROR(_xlfn.XLOOKUP("Net Income",Inputs!$B:$B,Inputs!O:O)/_xlfn.XLOOKUP("Revenue (Sales)",Inputs!$B:$B,Inputs!O:O),"") -> -0.29002102 | O23: =IFERROR(_xlfn.XLOOKUP("Net Income",Inputs!$B:$B,Inputs!P:P)/_xlfn.XLOOKUP("Revenue (Sales)",Inputs!$B:$B,Inputs!P:P),"") -> 0.056543548 | P23: =IFERROR(_xlfn.XLOOKUP("Net Income",Inputs!$B:$B,Inputs!Q:Q)/_xlfn.XLOOKUP("Revenue (Sales)",Inputs!$B:$B,Inputs!Q:Q),"") -> 0.224726 | Q23: =+_xlfn.XLOOKUP("Net Income Margin",DCF!$B:$B,DCF!H:H) -> 0.027044967 | R23: =+_xlfn.XLOOKUP("Net Income Margin",DCF!$B:$B,DCF!I:I) -> 0.072384671
