Workbook
Name COOLFUCNTION: _xlfn.LAMBDA(_xldudf_BOARDFLARE_EXEC("workbook-settings:coolfucntion"))
Name COOLFUCNTION: _xlfn.LAMBDA(_xldudf_BOARDFLARE_EXEC("workbook-settings:coolfucntion"))
Name COOLFUCNTION: _xlfn.LAMBDA(_xldudf_BOARDFLARE_EXEC("workbook-settings:coolfucntion"))
Name COOLFUCNTION: _xlfn.LAMBDA(_xldudf_BOARDFLARE_EXEC("workbook-settings:coolfucntion"))
Name COOLFUCNTION: _xlfn.LAMBDA(_xldudf_BOARDFLARE_EXEC("workbook-settings:coolfucntion"))
Name COOLFUCNTION: _xlfn.LAMBDA(_xldudf_BOARDFLARE_EXEC("workbook-settings:coolfucntion"))
Name COOLFUCNTION: _xlfn.LAMBDA(_xldudf_BOARDFLARE_EXEC("workbook-settings:coolfucntion"))
Name COOLFUCNTION: _xlfn.LAMBDA(_xldudf_BOARDFLARE_EXEC("workbook-settings:coolfucntion"))
Name COOLFUCNTION: _xlfn.LAMBDA(_xldudf_BOARDFLARE_EXEC("workbook-settings:coolfucntion"))
Name COOLFUCNTION: _xlfn.LAMBDA(_xldudf_BOARDFLARE_EXEC("workbook-settings:coolfucntion"))
Name COOLFUCNTION: _xlfn.LAMBDA(_xldudf_BOARDFLARE_EXEC("workbook-settings:coolfucntion"))
Name Sectors: #REF!
Name Sectors: #REF!
Name Sectors: #REF!
Name Sectors: #REF!
Name Sectors: #REF!
Name Sectors: #REF!
Name Sectors: #REF!
Name Sectors: #REF!

Sheet Dashboard
C154: =+C155+1 -> 45984
C155: =+C156+1 -> 45983
C156: =+C157+1 -> 45982
C157: =+C158+1 -> 45981
C158: =+C159+1 -> 45980
C159: =+C160+1 -> 45979
C160: =+C161+1 -> 45978 | L160: =IF(FCFF!$R$157="Revenue Exit",FCFF!$AF$169,IF(FCFF!$R$157="EBITDA Exit",FCFF!Z169,FCFF!AL169)) -> 46.167588
C161: =+C162+1 -> 45977
C162: =+C163+1 -> 45976 | E162: =IF(FCFF!$R$157="Revenue Exit",FCFF!$AF$169,IF(FCFF!$R$157="EBITDA Exit",FCFF!Z169,FCFF!AL169)) -> 46.167588
C163: =+C164+1 -> 45975 | E163: =E164+($E$162-$E$193)/COUNTA($C$162:$C$192) -> 48.762827
C164: =+C165+1 -> 45974 | E164: =E165+($E$162-$E$193)/COUNTA($C$162:$C$192) -> 51.358066
C165: =+C166+1 -> 45973 | E165: =E166+($E$162-$E$193)/COUNTA($C$162:$C$192) -> 53.953306
C166: =+C167+1 -> 45972 | E166: =E167+($E$162-$E$193)/COUNTA($C$162:$C$192) -> 56.548545
C167: =+C168+1 -> 45971 | E167: =E168+($E$162-$E$193)/COUNTA($C$162:$C$192) -> 59.143784
C168: =+C169+1 -> 45970 | E168: =E169+($E$162-$E$193)/COUNTA($C$162:$C$192) -> 61.739023
C169: =+C170+1 -> 45969 | E169: =E170+($E$162-$E$193)/COUNTA($C$162:$C$192) -> 64.334262
C170: =+C171+1 -> 45968 | E170: =E171+($E$162-$E$193)/COUNTA($C$162:$C$192) -> 66.929501
C171: =+C172+1 -> 45967 | E171: =E172+($E$162-$E$193)/COUNTA($C$162:$C$192) -> 69.52474
C172: =+C173+1 -> 45966 | E172: =E173+($E$162-$E$193)/COUNTA($C$162:$C$192) -> 72.119979
C173: =+C174+1 -> 45965 | E173: =E174+($E$162-$E$193)/COUNTA($C$162:$C$192) -> 74.715218
C174: =+C175+1 -> 45964 | E174: =E175+($E$162-$E$193)/COUNTA($C$162:$C$192) -> 77.310457
... C192: =+C193+1 -> 45946 | E192: =E193+($E$162-$E$193)/COUNTA($C$162:$C$192) -> 124.02476
B193: TODAY | C193: =+'Stock Data'!AM4 -> 45945 | D193: =_xlfn.XLOOKUP(C193,'Stock Data'!$AM$4:$AM$1051,'Stock Data'!$AN$4:$AN$1051) -> 126.62 | E193: =D193 -> 126.62
C194: =+'Stock Data'!AM5 -> 45944 | D194: =_xlfn.XLOOKUP(C194,'Stock Data'!$AM$4:$AM$1051,'Stock Data'!$AN$4:$AN$1051) -> 126.62
C195: =+'Stock Data'!AM6 -> 45943 | D195: =_xlfn.XLOOKUP(C195,'Stock Data'!$AM$4:$AM$1051,'Stock Data'!$AN$4:$AN$1051) -> 126.62
C196: =+'Stock Data'!AM7 -> 45942 | D196: =_xlfn.XLOOKUP(C196,'Stock Data'!$AM$4:$AM$1051,'Stock Data'!$AN$4:$AN$1051) -> 126.62
C197: =+'Stock Data'!AM8 -> 45941 | D197: =_xlfn.XLOOKUP(C197,'Stock Data'!$AM$4:$AM$1051,'Stock Data'!$AN$4:$AN$1051) -> 125.94
C198: =+'Stock Data'!AM9 -> 45940 | D198: =_xlfn.XLOOKUP(C198,'Stock Data'!$AM$4:$AM$1051,'Stock Data'!$AN$4:$AN$1051) -> 124.08
C199: =+'Stock Data'!AM10 -> 45939 | D199: =_xlfn.XLOOKUP(C199,'Stock Data'!$AM$4:$AM$1051,'Stock Data'!$AN$4:$AN$1051) -> 124.94
C200: =+'Stock Data'!AM11 -> 45938 | D200: =_xlfn.XLOOKUP(C200,'Stock Data'!$AM$4:$AM$1051,'Stock Data'!$AN$4:$AN$1051) -> 124.89
C201: =+'Stock Data'!AM12 -> 45937 | D201: =_xlfn.XLOOKUP(C201,'Stock Data'!$AM$4:$AM$1051,'Stock Data'!$AN$4:$AN$1051) -> 124.89
C202: =+'Stock Data'!AM13 -> 45936 | D202: =_xlfn.XLOOKUP(C202,'Stock Data'!$AM$4:$AM$1051,'Stock Data'!$AN$4:$AN$1051) -> 124.89
C203: =+'Stock Data'!AM14 -> 45935 | D203: =_xlfn.XLOOKUP(C203,'Stock Data'!$AM$4:$AM$1051,'Stock Data'!$AN$4:$AN$1051) -> 124.89
C204: =+'Stock Data'!AM15 -> 45934 | D204: =_xlfn.XLOOKUP(C204,'Stock Data'!$AM$4:$AM$1051,'Stock Data'!$AN$4:$AN$1051) -> 125.74
C205: =+'Stock Data'!AM16 -> 45933 | D205: =_xlfn.XLOOKUP(C205,'Stock Data'!$AM$4:$AM$1051,'Stock Data'!$AN$4:$AN$1051) -> 125.64
... C558: =+'Stock Data'!AM369 -> 45580 | D558: =_xlfn.XLOOKUP(C558,'Stock Data'!$AM$4:$AM$1051,'Stock Data'!$AN$4:$AN$1051) -> 94.05

Sheet Key Info
B7: Analysts | F7: LIS – Equity Research | J7: Stock Performance
B12: Mariana Zhu, Co-Head of Equity Research | F12: Recommendation: | H12: Strong Buy
B13: MSc in Mathematical Finance, ISEG – Ulisboa | E13: #VALUE! | F13: Target Price (FCFF):
B14: l63113@aln.iseg.ulisboa.pt | F14: Upside:
B15: Maria Ana Rocha, Analyst
B16: BSc in Applied Mathematics, ISEG – Ulisboa | F16: Ticker | H16: {=_FV(E13,"Nome")} -> ACM Rsrch
B17: maria.ana.rocha@aln.iseg.ulisboa.pt | F17: Stock Exchange | H17: {=_FV(E13,"Bolsa")} -> Nasdaq Stock Market
B18: Rodrigo Ji, Analyst
B19: BSc in Economics, ISEG – Ulisboa | F19: Current Price | H19: 38.12
B20: l63970@aln.iseg.ulisboa.pt | F20: ="Market Cap (in "&IF(Inputs!$D$14="BLN","billions",IF(Inputs!$D$14="MLN","millions","thousands"))&")" -> Market Cap (in millions) | H20: 2443.7
B21: Maria Gonçalves, Analyst | F21: Beta | H21: 1.52
B22: BSc in Applied Mathematics, ISEG – Ulisboa | F22: % of 52-Week High | H22: 0.4512
B23: l63847@aln.iseg.ulisboa.pt | F23: 100-Day Moving Average | H23: 29.42
B25: Reviewed by: | F25: Avg Vol (1 month) | H25: 156927
B26: José Lima, Vice President | F26: Shares Outstanding (millions) | H26: 59.2
B27: BSc in Management, ISEG – Ulisboa | F27: % Float | H27: =50.2/59.2 -> 0.84797297
B28: l60456@aln.iseg.ulisboa.pt | F28: Short % of Float | H28: 0.0959
B30: LISBON INVESTMENT SOCIETY | F30: % Held by Insiders | H30: 0.1526
B31: ISEG – Rua do Quelhas, 6 | F31: % Held by Institutions | H31: 0.7036
B32: lis@iseg.ulisboa.pt
B34: Disclaimer: This report was prepared by members of the Lisbon Investment Society (LIS), an independent, student-led, non-profit organization based at ISEG – Lisbon School of Economics & Management, and is intended solely for academic and educational purposes. All analyses, forecasts, and opinions expressed in this report reflect the independent judgment of the authors as of the date of publication and are subject to change without notice. The views presented herein do not represent those of ISEG, its faculty, or any affiliated entity. This document does not constitute, and should not be interpreted as, investment advice, an offer, or a solicitation to buy or sell any security or financial instrument. Nothing in this report should be construed as a recommendation to make or refrain from making any investment decision. The content is intended for informational purposes only, and readers are strongly encouraged to conduct their own research and seek advice from a qualified financial professional before making any financial decisions. The information contained in this report has been obtained from publicly available sources believed to be reliable; however, no representation or warranty is made regarding the accuracy, completeness, or timeliness of such information. LIS and its members accept no liability whatsoever for any direct or indirect loss arising from the use of this report or its contents. This report incorporates terminology, financial metrics, and methodologies commonly used in professional equity research, including but not limited to Discounted Cash Flow (DCF), trading multiples, Monte Carlo simulations, and strategic analysis tools such as Porter’s Five Forces. Definitions and assumptions used in these models are disclosed within the report and reflect a hypothetical investment thesis designed solely for academic discussion. All valuations, projections, and target prices presented herein are based on publicly available data and subject to the limitations of modeling assumptions. These are not guarantees of future performance and should not be relied upon as such, as past performance is not indicative of future results. Any company names, logos, trademarks, or brand references mentioned in this report are the property of their respective owners and are used strictly for identification and academic purposes. This document may not be reproduced, redistributed, or quoted in whole or in part without the prior written consent of the Lisbon Investment Society. About LIS – Lisbon Investment Society: The Lisbon Investment Society (LIS) is a non-profit academic association headquartered at ISEG – Lisbon School of Economics & Management. Founded in 2016, LIS is committed to fostering student interest in finance and investment through applied research, skill development, and institutional engagement. The Society operates independently and autonomously from any political, religious, or commercial affiliation, and is composed of selected students and collaborators who are invited through a rigorous recruitment process and share a commitment to excellence, analytical rigor, and ethical standards. Its activities include equity research, portfolio management, macroeconomic analysis, and investment education. This report was prepared by the Equity Research team at the Lisbon Investment Society, whose analysts combine rigorous financial modeling, critical thinking, and collaborative research to deliver high-quality, student-led investment analysis. We welcome your feedback, discussion, and questions regarding this report or our research process, and invite you to reach out to our team as we are always open to engagement.

Sheet Industry
D6: 584.17 | E6: 627.76 | F6: 676.06 | G6: 729.63 | H6: 789.13 | I6: 855.3 | J6: 929 | K6: 997.69 | L6: 1067.63 | M6: 1137.57
A7: x | B7: Industry Growth Forecast | O7: Industry Index
D9: 2022 | E9: =+D9+1 -> 2023 | F9: =+E9+1 -> 2024 | G9: =+F9+1 -> 2025 | H9: =+G9+1 -> 2026 | I9: =+H9+1 -> 2027 | J9: =+I9+1 -> 2028 | K9: =+J9+1 -> 2029 | M9: ="CAGR "&$G$9&" - "&$K$9 -> CAGR 2025 - 2029
B12: Market Size | D12: 608180 | E12: 549420 | F12: 659100 | G12: 789270 | H12: 891000 | I12: 969010 | J12: 1036450 | K12: 1148020 | M12: =(K12/G12)^(1/5)-1 -> 0.077816361
B13: Market Share | D13: =+IS!T18/D12 -> 0.00063933704 | E13: =+IS!Z18/Industry!E12 -> 0.0010151123 | F13: =IS!AF18/Industry!F12 -> 0.0011866454 | G13: =+IS!AK18/Industry!G12 -> 0.00038624451 | H13: =+IS!AR18/Industry!H12 -> 0.0012748995 | I13: =IS!AT18/Industry!I12 -> 0.001387179 | J13: =+IS!AV18/Industry!J12 -> 0.0015130706 | K13: =+IS!AX18/Industry!K12 -> 0.0015709267 | M13: =((K13*K12)/(G13*G12))^(1/5)-1 -> 0.42693271
A23: x
B25: Industry Driver | D25: Description | O25: Porter's Five Forces
B27: Subsidies | D27: Governments encouraging domestic semiconductor fabs with subsidies
B28: Growth tied to China | D28: China is the largest consumer of semiconductors. Adittionally, the Chinese government could intervene in ACM Shanghai’s operations, impose restrictions on foreign listings, or change audit and access requirements
B29: Market Expansion | D29: The semiconductor industry is currently in a massive expansion phase, due to the rising demand in chips fueled by AI, data centres, and high-performance computing.
B30: Rising Complexity of chips | D30: As chips move toward smaller nodes, manufacturing steps become more complex, requiring more advanced cleaning.
B31: Sustainability & ESG Pressures | D31: Push for greener manufacturing processes in semiconductors (reducing water, energy, and chemical usage) and increases demand for advanced, efficient equipment.
O32: Rivalry Among Existing Competitors | R32: 3.5
O33: Threat of New Entrants | R33: 2
O34: Threat of Substitutes | R34: 3
O35: Bargaining Power of Customers | R35: 4
O36: Bargaining Power of Suppliers | R36: 5

Sheet ESG
A7: x | B7: ESG Analysis
B12: ESG Scores | G12: GHG Scope 1 Emissions, Water Consumption, Energy Consumption and Waste Production per Sales
B15: LSEG ESG Score | D15: 52
B16: E-Score | D16: 34
B17: S-Score | D17: 46
B18: G-Score | D18: 85
B19: S&P Global ESG Score | D19: 32
B20: Environmental | D20: -
B21: Social | D21: -
B22: Governance & Economic | D22: -
B23: Sustainalytics | D23: 20.5
B24: ISS ESG Corporate Rating | D24: D
B25: SDG Impact Rating | D25: -7
B26: Governance Quality Score | D26: 9
B27: MSCI ESG Ratings | D27: -
B30: Key Info | G30: Environmental
H32: Overview | I32: Targets | J32: Improvements | K32: Comments
B33: GICS Sector | C33: Information Technology | G33: GHG Scope 1 Emissions | I33: Annual greenhouse gas emissions accounting is conducted across all facilities, with full coverage to be achieved in 2025. | J33: In 2024, ACM Research iniciated measures to reduce potencial climate risks associated with GHG emissions by procuring energy-efficient equipment and promoting energy conservation awareness among employess. | K33: Annual emissions surveys ensure timely compliance with regulatory requirements.
B34: GICS Industry Group | C34: Semiconductors & Semiconductor Equipment
B35: GICS Industry | C35: Semiconductor Equipment & Materials | G35: Water Consumption | I35: Long-term water resource management goals include achieving a 75% purification rate of the water system by 2030. | J35: In 2024, water management practices were enhanced through conservation signage and strengthened maintenance of water-related equipment, improving utilization efficiency. | K35: Improper water management or shortages have been identified as potencial operation risks, ongoing assessments are conducted to evaluate likelihood and impact.
B36: GICS Sub-Industry | C36: Semiconductor Equipment & Materials
G37: Energy Consumption | I37: Annual upgrades to production processes and equipment are implemented to reduce energy consmption and environmental pollution. | J37: In 2024, energy-saving measures such as awareness signage and optimized office air conditioning were introduced, contributing to reductions in consumption. | K37: Energy management strategies are in place to anticipate and address risks, impacts and opportunities associated with energy use.
B38: Headquarters | C38: Fremont, CA 94539 United States
B39: Numer of Employees | C39: 2023 | G39: Waste Management | I39: Strict compliance with hazardous and non-hazardous waste seperation requirements in maintained, with a zero-tolerance target to non-compliance incidents. | J39: A dedicated hazardous waste storage facility has been constructed in compliance with all appicable regulations and standards. | K39: N/A
B41: Annual Report | C41: 2024 | G41: Other
B42: Sustainability Report | C42: 2024
B44: Recent Headlines | G44: Social
H46: Overview | I46: Targets | J46: Improvements | K46: Comments
G47: Employee Turnover % | I47: Maintain a fair and supportive work environment by upholding employee rights and benefits, with the goal of improving employee retention and attractiong top talent. | J47: Extensive training programmes covering about 91.9% of employees, along with share-ownership incentives involving 4.4% of the workforce, serve as key retention mechanisms and provide a baseline for monitoring future improvements. | K47: The ESG Report highlights workplace practices and notes that over 75% of employees report being "Satisfeid" or "Very Satisfied". However, it doesn't look into the reasons behind staff turnover or set any goals for reducing it.
B48: ACM Research, Inc. (ACMR) Suffers a Larger Drop Than the General Market: Key Insights --Yahoo Finance -- 7/10/2025
G49: Salaries & Compensation | I49: Ensure competitive and fair salaries with comprehensive compensation benefits to attract and retain top talent. | J49: A performance-driven culture is promoted through ongoing feedback and quaterly assessments, culminating in an annual review that guides salary adjustments, position changes and year-end bonuses for all employees. | K49: Year-on-year salary increases and target salary levels are not included in the ESG or Annual Report.
B50: ACM Research (NASDAQ:ACMR) Receives Hold (C+) Rating from Weiss Ratings -- MarketBeat.com -- 8/10/25
G51: Reputation | I51: Maintain and communicate an externally verified reputation score. | J51: The report documents multiple awards and customer recognitions and outlines active stakeholder communication channels. | K51: N/A
B52: ACM Research’s Operating Subsidiary ACM Research (Shanghai) Provides Backlog Data -- Yahoo Finance -- 29/09/2025
G53: Discrimination Events | I53: Maintain a zero-tolerance policy toward any form of discrimination, ensuring an inclusive and equitable work environment for all employees. | J53: Discrimination or biased actions based on race, color, religion, gender, nationality or any other characteristic protected by local laws and regulations are strictly prohibited. | K53: The report provides gender breakdowns (total workforce: male 1,706; female 296) and indicates female representation in senior management (40%).
B54: ACM Research (NASDAQ:ACMR) Trading Down 3.8% - What's Next? -- MarketBeat.com -- 3/10/2025
G55: Work Safety | I55: Clear occupational health and safety targets are set, including maintaining ISO 45001 certification and achieving certification for newer facilities within 2 years. | J55: In 2024, safety management systems were further enhanced, with strengthened safety drills and awareness training to achieve occupational health and safety targets. | K55: N/A
G57: Damage to consumer health | I57: Maintain 100% third-party safety assessment before shipment for all product models. | J57: The report records zero major liability incidents related to product safety in 2024. | K57: N/A
G59: Pension Plan | I59: N/A | J59: Insurance coverage is detailed, showing 100% coverage for work injury and work safety liability insurance, along with the amounts invested. | K59: The company offers statutory and contribution-based pension plans only. No defined benefit or formal enhancement targets reported.
G61: Supply chain | I61: Implement regular audits to ensure compliance and foster long-term partnerships that align with ACM Research's sustainability goals. | J61: In 2024, the supllier base expanded to 1.154 in total (1.069 in Mainland China; 85 overseas), including 451 new suppliers. Supply-chain governance was stregthened by introducing transparent procurement, regular conferences and dedicated due-diligence channels. | K61: Supllier management and supply-chain security are highlighted, but the report lacks dislosure of supplier ESG KPIs or identification of major suppliers.
G63: Community involvement | I63: Strengthen community impact through charitable programs, volunteer initiatives, and partnerships that align with social responsibility goals. | J63: Charitable donations are disclosed (for example the participation in the "SMIC Liver Transplant Program") along with awards for social contribution | K63: Community involvement highlights contributions, but quantitative KPI's (total beneficiaries or hours volunteered) are not provided.
G65: Public Sector | I65: Maintain full compliance with all governmental and regulatory disclosure requirements, while expanding constructive engagement with public authorities. | J65: The 10-K confirms U.S. public listing status, majority owership of ACM Shanghai (~81.5%), and includes expanded disclosure on regulatory risks and interactions with government and regulatory bodies. | K65: N/A
G67: Litigation | I67: N/A | J67: No material litigation disclosed in the 2024 annual report. | K67: ACM faced a securities class action lawsuit in 2020 over allegedly misleading financial statements. The case was dismissed in January 2022.
B70: Board of Directors | G70: Governance
B72: Name | C72: Position | E72: M/F – Age | H72: Overview | I72: Targets | J72: Improvements | K72: Comments
B73: David H. Wang | C73: Chairman, CEO and President | E73: M 63 | G73: Diversity (Gender, Age, Industry, Region) | I73: Enhance board-level diversity in age, gender, nationality and expertise | J73: In 2025, a new independent director nominee was added, enhancing the board´s industry expertise diversity. | K73: Gender diversity is limited, only 1 woman in the board, and there is concentration in older age groups.
B74: Haiping Dun | C74: Lead Independent Director | E74: M 75
B75: Tracy Liu | C75: Independent Director | E75: F 60 | G75: % Independence | I75: Maintain a majority of independent directors on the Board, in line with Nasdaq listing standards, board and committee guidelines, applicable laws and regulation | J75: As of 2025, 80% of the board is independent, with the Founder being the only non-independent director. | K75: The company annually reviews independence and has categorical standards posted.
B76: Charles Pappis | C76: Independent Director | E76: M 64
B77: Chenming C. Hu | C77: Independent Director | E77: M 76 | G77: Average time as independent directors | I77: N/A | J77: Board refreshment in 2025 with the addition of a new independent director (Charles Pappis, 1 month tenure), balancing the long service of existing members. | K77: The company does not disclose a formal refreshment or rotation schedule.
G79: Departures of C-level executives | I79: N/A | J79: No departures of C-level executives were reported in 2024. | K79: A director, Chenming Hu, is not standing for re-election and Xiao Xing resigned from the board effective 15 November 2024.
G81: CEO/Chairman duality | I81: N/A | J81: To mitigate risks associated with the concentrated leadership, the board maintains an Independent Lead Director. | K81: David H. Wang serves as the Chair of the Board, Chief Executive Officer and President.
G83: Transparency when reporting | I83: Maintain a 100% response rate to investor inquiries via the Shanghai Stock Exchange (SSE) e-interactive platform. | J83: ACM Shanghai improved transparency by achieving an A rating in the SSE 2023-2024 Information Disclosure Assessment. | K83: Transparency procedures include management review and approval by the Board of Directors before external disclosure.
G85: Time taken to report | I85: Maintain financial and ESG disclosures within 1.5-2 months after the fiscal year-end. | J85: Reporting timeline meets international standards. | K85: The Annual Report was released around two months after the fiscal year end. This timeframe is within industry norms (1.5-2 months)
G87: CEO or Chairman in other boards? | I87: Maintain compliance with governance guidelines to ensure directors are not classified as having excessive commitments. | J87: The CEO/Chairman holds no other public directorships listed in the provided director nominee table. | K87: No overboarding concerns identified; director's other commitments are disclosed and comply with governance guidelines.
G89: Audit / Consulting | I89: Achieve and maintain compliance with PCAOB inspection access requirement to avoid being placed on the SEC's Conclusive List. | J89: Audit Committee oversight improved with clearer disclosure of audit vs non-audit fees and confirmation of auditor independence despite higher total fees. | K89: N/A
G91: ESG-compensation related | I91: N/A | J91: N/A | K91: No ESG-specific incentive metrics currently disclosed; compensation remains primarily based on financial and idividual performance.
G93: Management compensation schemes | I93: Maintain a balanced pay structure that links compensation to both company performance and long-term shareholder valuewhile ensuring governance compliance. | J93: Adoption of a clawback policy, aligning with a new SEC requirements and enhancing accountability. | K93: Compensation includes salary, discretionary bonuses, and stock options.

Sheet Segments
A7: x | B7: Segments | D7: =F7 -> 2020 | E7: =F7 -> 2020 | F7: 2020 | G7: =F7 -> 2020 | H7: =F7 -> 2020 | J7: =L7 -> 2021 | K7: =L7 -> 2021 | L7: 2021 | M7: =L7 -> 2021 | N7: =L7 -> 2021 | P7: =R7 -> 2022 | Q7: =R7 -> 2022 | R7: 2022 | S7: =R7 -> 2022 | T7: =R7 -> 2022 | V7: =X7 -> 2023 | W7: =X7 -> 2023 | X7: 2023 | Y7: =X7 -> 2023 | Z7: =X7 -> 2023 | AB7: =AD7 -> 2024 | AC7: =AD7 -> 2024 | AD7: 2024 | AE7: =AD7 -> 2024 | AF7: =AD7 -> 2024 | AH7: =AJ7 -> 2025 | AI7: =AJ7 -> 2025 | AJ7: 2025 | AK7: =AJ7 -> 2025 | AL7: =AJ7 -> 2025 | AN7: =AP7 -> 2025 | AO7: =AP7 -> 2025 | AP7: 2025 | AQ7: =AP7 -> 2025 | AR7: =AP7 -> 2025 | AZ7: Products
D8: 2020 | J8: =D8+1 -> 2021 | P8: =J8+1 -> 2022 | V8: =P8+1 -> 2023 | AB8: =V8+1 -> 2024 | AH8: =AB8+1 -> 2025 | AN8: =AH8+1 -> 2026 | AT8: =AN8+1 -> 2027 | AV8: =+AT8+1 -> 2028 | AX8: =+AV8+1 -> 2029
D9: Q1 | E9: Q2 | F9: Q3 | G9: Q4 | H9: FY | J9: Q1 | K9: Q2 | L9: Q3 | M9: Q4 | N9: FY | P9: Q1 | Q9: Q2 | R9: Q3 | S9: Q4 | T9: FY | V9: Q1 | W9: Q2 | X9: Q3 | Y9: Q4 | Z9: FY | AB9: Q1 | AC9: Q2 | AD9: Q3 | AE9: Q4 | AF9: FY | AH9: Q1 | AI9: Q2 | AJ9: Q3 | AK9: Q4 | AL9: FY | AN9: Q1 | AO9: Q2 | AP9: Q3 | AQ9: Q4 | AR9: FY | AT9: FY | AV9: FY | AX9: FY
B12: Revenue by segment:
B13: Single Wafer Cleaning,Tahoe and Semi- Critical Cleaning Equipment | H13: 131.248 | N13: 189.208 | T13: 272.939 | Z13: 403.851 | AF13: 578.887 | AL13: =FCFF!Z10 -> 681.09169 | AR13: =FCFF!AF10 -> 817.31002 | AT13: =FCFF!AH10 -> 967.15019 | AV13: =FCFF!AJ10 -> 1128.3419 | AX13: =FCFF!AL10 -> 1297.5932
B14: Electro-chemical plating (ECP) (front-end and packaging), Furnace and Other Technologies | H14: 13.343 | N14: 33.21 | T14: 77.482 | Z14: 103.356 | AF14: 151.057 | AL14: =FCFF!Z11 -> 211.00001 | AR14: =FCFF!AF11 -> 253.20001 | AT14: =FCFF!AH11 -> 299.62002 | AV14: =FCFF!AJ11 -> 349.55668 | AX14: =FCFF!AL11 -> 401.99019
B15: Advanced Packaging, Services & Spares | H15: 12.033 | N15: 37.333 | T15: 38.411 | Z15: 50.516 | AF15: 52.174 | AL15: =FCFF!Z12 -> 54.524902 | AR15: =FCFF!AF12 -> 65.429882 | AT15: =FCFF!AH12 -> 77.425361 | AV15: =FCFF!AJ12 -> 90.329587 | AX15: =FCFF!AL12 -> 103.87903
B18: Total revenue | D18: =IS!D18 -> 24.348 | E18: =IS!E18 -> 39.049 | F18: =IS!F18 -> 47.665 | G18: =IS!G18 -> 45.562 | H18: =IS!H18 -> 156.624 | J18: =IS!J18 -> 43.732 | K18: =IS!K18 -> 53.864 | L18: =IS!L18 -> 67.013 | M18: =IS!M18 -> 95.142 | N18: =IS!N18 -> 259.751 | P18: =IS!P18 -> 42.186 | Q18: =IS!Q18 -> 104.395 | R18: =IS!R18 -> 133.709 | S18: =IS!S18 -> 108.542 | T18: =IS!T18 -> 388.832 | V18: =IS!V18 -> 74.256 | W18: =IS!W18 -> 144.577 | X18: =IS!X18 -> 168.569 | Y18: =IS!Y18 -> 170.321 | Z18: =IS!Z18 -> 557.723 | AB18: =IS!AB18 -> 152.191 | AC18: =IS!AC18 -> 202.48 | AD18: =IS!AD18 -> 203.976 | AE18: =IS!AE18 -> 223.471 | AF18: =IS!AF18 -> 782.118 | AH18: =IS!AH18 -> 172.347 | AI18: =IS!AI18 -> 215.372 | AJ18: =IS!AJ18 -> 254.04267 | AK18: =IS!AK18 -> 304.85121 | AL18: =FCFF!Z31 -> 946.61288 | AN18: =IS!AN18 -> 206.8164 | AO18: =IS!AO18 -> 258.4464 | AP18: =IS!AP18 -> 304.85121 | AQ18: =IS!AQ18 -> 365.82145 | AR18: =FCFF!AF31 -> 1135.9355 | AT18: =FCFF!AH31 -> 1344.1903 | AV18: =FCFF!AJ31 -> 1568.222 | AX18: =FCFF!AL31 -> 1803.4553
B20: Revenue by region:
B21: Mainland China | H21: 154.359 | N21: 258.615 | T21: 377.752 | Z21: 540.969 | AF21: 775.752 | AL21: =AL26*98% -> 927.68062 | AN21: =AN26*98% -> 202.68007 | AO21: =AO26*98% -> 253.27747 | AP21: =AP26*98% -> 298.75418 | AQ21: =AQ26*98% -> 358.50502 | AR21: =AR26*98% -> 1113.2167 | AT21: =AT26*98% -> 1317.3065 | AV21: =AV26*98% -> 1536.8576 | AX21: =AX26*98% -> 1767.3862
B22: Other Regions | H22: 2.265 | N22: 1.136 | T22: 11.08 | Z22: 16.754 | AF22: 6.366 | AL22: =2%*AL26 -> 18.932258 | AN22: =2%*AN26 -> 4.136328 | AO22: =2%*AO26 -> 5.168928 | AP22: =2%*AP26 -> 6.0970241 | AQ22: =2%*AQ26 -> 7.316429 | AR22: =2%*AR26 -> 22.718709 | AT22: =2%*AT26 -> 26.883806 | AV22: =2%*AV26 -> 31.36444 | AX22: =2%*AX26 -> 36.069106
B26: Total revenue | D26: =IS!D18 -> 24.348 | E26: =IS!E18 -> 39.049 | F26: =IS!F18 -> 47.665 | G26: =IS!G18 -> 45.562 | H26: =IS!H18 -> 156.624 | J26: =IS!J18 -> 43.732 | K26: =IS!K18 -> 53.864 | L26: =IS!L18 -> 67.013 | M26: =IS!M18 -> 95.142 | N26: =IS!N18 -> 259.751 | P26: =IS!P18 -> 42.186 | Q26: =IS!Q18 -> 104.395 | R26: =IS!R18 -> 133.709 | S26: =IS!S18 -> 108.542 | T26: =IS!T18 -> 388.832 | V26: =IS!V18 -> 74.256 | W26: =IS!W18 -> 144.577 | X26: =IS!X18 -> 168.569 | Y26: =IS!Y18 -> 170.321 | Z26: =IS!Z18 -> 557.723 | AB26: =IS!AB18 -> 152.191 | AC26: =IS!AC18 -> 202.48 | AD26: =IS!AD18 -> 203.976 | AE26: =IS!AE18 -> 223.471 | AF26: =IS!AF18 -> 782.118 | AH26: =IS!AH18 -> 172.347 | AI26: =IS!AI18 -> 215.372 | AJ26: =IS!AJ18 -> 254.04267 | AK26: =IS!AK18 -> 304.85121 | AL26: =FCFF!Z31 -> 946.61288 | AN26: =IS!AN18 -> 206.8164 | AO26: =IS!AO18 -> 258.4464 | AP26: =IS!AP18 -> 304.85121 | AQ26: =IS!AQ18 -> 365.82145 | AR26: =FCFF!AF31 -> 1135.9355 | AT26: =FCFF!AH31 -> 1344.1903 | AV26: =FCFF!AJ31 -> 1568.222 | AX26: =FCFF!AL31 -> 1803.4553
B28: Products:
B29: Product 1
B30: Product 2
B31: Product 3
B32: Product 4
B33: Product 5
A35: x | B35: Notes & Forecasts
B40: Shift toward advanced wafer cleaning | H40: Growing microchip complexity and shrinking node sizes are increasing the need for advanced single-wafer cleaning systems. New processes like plasma and cryogenic cleaning are gaining traction as they reduce chemical waste and improve precision. This trend supports long-term growth in high-end cleaning equipment demand.
B41: China's expanding semiconductor self-sufficiency | H41: Mainland China remains one of the biggest investors in semiconductor manufacturing equipment, helped by strong government support and expanding local factories. Despite export restrictions from other countries, China continues to invest heavily in older but reliable chip technologies.
B42: Diversification beyond cleaning tools | H42: ACM Research is gradually expanding beyond its core cleaning business into electro-chemical planting (ECP), furnace, and advanced packaging equipment. These new segments are gaining traction, supported by growing demand for advanced interconnect and packaging technologies. The shift should help reduce dependence on traditional cleaning tools and provide higher-margin growth opportunities over the next few years.
B43: Expansion into other regions | H43: Although currently small, ACM's non-China revenue is expected to increase gradually as the company qualifies tools with international customers and builds service capabilities abroad. Successful expansion into overseas markets would help mitigate geographic concentration risk and improve long-term valuation potencial.

Sheet Peers
N6: on
B7: Peers
D11: TIER I | I11: TIER II | N11: TIER III
A12: x | B12: Growth | C12: ACM RESEARCH-A | D12: NAURA TECH GR -A | E12: LAM RESEARCH | F12: TOKYO ELECTRON | G12: APPLIED MATERIAL | H12: KINGSEMI CO LT-A | I12: SCREEN HOLDINGS | J12: SAMSUNG ELECTRON | K12: HIMAX TECHNO-ADR | L12: ENTEGRIS INC | M12: ONTO INNOVATION | N12: SK HYNIX INC | O12: TAIWAN SEMIC-ADR | P12: NVIDIA CORP | Q12: QUALCOMM INC | R12: ADV MICRO DEVICE
B14: Revenue (LTM) | C14: 0.17533425 | D14: 0.28825718 | E14: 0.2368409 | F14: 0.21678189 | G14: 0.065502346 | H14: 0.031571713 | I14: 0.16200785 | J14: 0.097540541 | K14: -0.02606187 | L14: -0.02606187 | M14: -0.018596879 | N14: 0.56855116 | O14: 0.39483946 | P14: 0.7155347 | Q14: 0.7155347 | R14: 0.15821463
B15: Revenue (3-yr CAGR) | C15: 0.38214284 | D15: 0.42944736 | E15: 0.022858305 | F15: 0.062015613 | G15: 0.043814535 | H15: 0.21677968 | I15: 0.13313386 | J15: 0.0033317187 | K15: -0.17742233 | L15: 0.080252437 | M15: 0.039031412 | N15: 0.15471249 | O15: 0.21891361 | P15: 0.77112223 | Q15: 0.0087507094 | R15: 0.11115231
B16: Gross profit (LTM) | C16: 0.17224414 | D16: 0.25586403 | E16: 0.25323779 | F16: 0.21916612 | G16: 0.088848808 | H16: 0.066816319 | I16: 0.16116396 | J16: 0.14164459 | K16: -0.034606507 | L16: -0.034606507 | M16: 0.020992182 | N16: 1.8546024 | O16: 0.53145785 | P16: 0.57690056 | Q16: 0.57690056 | R16: 0.15376509
B17: EBIT (LTM) | C17: 0.22008511 | D17: 0.20877056 | E17: 0.34093105 | F17: 0.25338468 | G17: 0.09764181 | H17: -0.22141708 | I17: 0.21920674 | J17: 0.2119973 | K17: -0.045584729 | L17: -0.045584729 | M17: 0.019486393 | N17: 3.5980277 | O17: 0.61840034 | P17: 0.60461058 | Q17: 0.60461058 | R17: 0.26977937
B18: EBITDA (LTM) | C18: 0.22068057 | D18: 0.22022173 | E18: 0.32088681 | F18: 0.24893117 | G18: 0.082874251 | H18: -0.084102483 | I18: 0.21153302 | J18: 0.17073199 | K18: -0.031391968 | L18: -0.031391968 | M18: 0.01832896 | N18: 1.2593119 | O18: 0.43307613 | P18: 0.59879178 | Q18: 0.59879178 | R18: 0.22398466
B19: FCF (LTM) | E19: 0.27222466 | F19: 0.3338495 | G19: -0.014090071 | I19: -0.14964746 | K19: -0.10535829 | L19: 0.83026952 | M19: 0.43087684 | O19: 1.7873594 | P19: 1.2520632 | Q19: 0.13321149 | R19: 1.1454059
A21: x | B21: Margins | C21: =C12 -> ACM RESEARCH-A | D21: =D12 -> NAURA TECH GR -A | E21: =E12 -> LAM RESEARCH | F21: =F12 -> TOKYO ELECTRON | G21: =G12 -> APPLIED MATERIAL | H21: =H12 -> KINGSEMI CO LT-A | I21: =I12 -> SCREEN HOLDINGS | J21: =J12 -> SAMSUNG ELECTRON | ... R21: =R12 -> ADV MICRO DEVICE
B23: Gross margin | C23: 0.5006329 | D23: 0.42854289 | E23: 0.48705024 | F23: 0.47141927 | G23: 0.47457315 | H23: 0.37674125 | I23: 0.37631483 | J23: 0.37992585 | K23: 0.30458799 | L23: 0.45869287 | M23: 0.52192549 | N23: 0.48083884 | O23: 0.56122352 | P23: 0.74988697 | Q23: 0.56213747 | R23: 0.49350398
B24: EBIT margin | C24: 0.19306294 | D24: 0.22063906 | E24: 0.32008564 | F24: 0.2867775 | G24: 0.28948337 | H24: 0.12628751 | I24: 0.2169994 | J24: 0.10877077 | K24: 0.07523252 | L24: 0.16472932 | M24: 0.18950574 | N24: 0.35452893 | O24: 0.4567667 | P24: 0.62417527 | Q24: 0.25848262 | R24: 0.073686252
B25: EBITDA margin | C25: 0.19772046 | D25: =1052.9/4114.4 -> 0.25590609 | E25: 0.34103843 | F25: 0.30608269 | G25: 0.31642959 | H25: =39.8/243.6 -> 0.16338259 | I25: 0.23210659 | J25: 0.23484276 | K25: 0.099470413 | L25: 0.27791021 | M25: 0.24012475 | N25: 0.58050798 | O25: 0.69350797 | P25: 0.59728964 | Q25: 0.31643433 | R25: 0.17827703
B26: Net margin | C26: 0.13249535 | D26: 0.18838984 | E26: 0.29064525 | F26: 0.22377865 | G26: 0.26409332 | H26: 0.11565426 | I26: 0.15907873 | J26: 0.09821447 | K26: 0.087951945 | L26: 0.090332678 | M26: 0.20425981 | N26: 0.29895336 | O26: 0.40537076 | P26: 0.55848027 | Q26: 0.26030491 | R26: 0.063641652
B27: SG&A margin | C27: 0.17271435 | D27: 0.099535053 | E27: 0.053250476 | F27: 0.081819632 | G27: 0.066124522 | H27: 0.1814637 | I27: 0.10860606 | J27: 0.14683642 | K27: 0.052548406 | L27: 0.13777795 | M27: 0.16408139 | N27: 0.050834077 | O27: 0.033475533 | P27: 0.026751573 | Q27: 0.070812587 | R27: 0.10793097
B28: R&D margin | C28: 0.14341496 | E28: 0.11371412 | F28: 0.10664186 | G28: 0.12270646 | H28: 0.17619823 | I28: 0.052763318 | J28: 0.12059922 | K28: 0.17648368 | L28: 0.10283479 | M28: 0.12205397 | N28: 0.073727014 | O28: 0.066988849 | P28: 0.093113341 | Q28: 0.20745775 | R28: 0.23547297
A30: x | B30: Returns | C30: =+C21 -> ACM RESEARCH-A | D30: =D21 -> NAURA TECH GR -A | E30: =E21 -> LAM RESEARCH | F30: =F21 -> TOKYO ELECTRON | G30: =G21 -> APPLIED MATERIAL | H30: =H21 -> KINGSEMI CO LT-A | I30: =I21 -> SCREEN HOLDINGS | J30: =J21 -> SAMSUNG ELECTRON | K30: =K21 -> HIMAX TECHNO-ADR | ... R30: =R21 -> ADV MICRO DEVICE
B32: ROIC | C32: 0.093969143 | D32: 0.13661976 | E32: 0.36742097 | G32: 0.25026919 | H32: 0.037240064 | I32: 0.23305939 | J32: 0.063682368 | K32: 0.04677638 | L32: 0.059044886 | M32: 0.090878512 | N32: 0.2672146 | O32: 0.25841889 | P32: 1.0268123 | Q32: 0.28951275 | R32: 0.04324939
B33: CROIC | C33: 0.053793367 | D33: -0.014716985 | E33: 0.35698561 | F33: 0.22111462 | G33: 0.31050929 | H33: 0.044838495 | I33: 0.11130795 | J33: 0.052296567 | K33: 0.08096272 | L33: 0.04001478 | M33: 0.11246363 | N33: 0.13869852 | O33: 0.17068653 | P33: 0.75701934 | Q33: 0.29568696 | R33: 0.040362507
B34: ROCE | C34: 0.11770327 | D34: 0.16396785 | E34: 0.55333883 | F34: 0.45359657 | G34: 0.47742444 | H34: 0.062094108 | I34: 0.39663998 | J34: 0.098340047 | K34: 0.12317328 | L34: 0.18223216 | M34: 0.12608359 | N34: 0.27066855 | O34: 0.24860964 | P34: 0.91328333 | Q34: 0.46605581 | R34: 0.11306832
B35: RONA | C35: 0.13778372 | D35: 0.20429491 | E35: 0.5983772 | F35: 0.37587086 | G35: 0.41403084 | H35: 0.07853762 | I35: 0.32252183 | J35: 0.081368986 | K35: 0.076111732 | L35: 0.14463536 | M35: 0.09715185 | N35: 0.31748759 | O35: 0.30577083 | P35: 1.0268005 | Q35: 0.38330669 | R35: 0.033004447
B36: ROE | C36: 0.12323899 | D36: 0.19888032 | E36: 0.58238093 | F36: 0.29389652 | G36: 0.35635301 | H36: 0.055096325 | I36: 0.24658314 | J36: 0.069935052 | K36: 0.086130426 | L36: 0.080838516 | M36: 0.10533705 | N36: 0.39267559 | O36: 0.34870793 | P36: 1.0941701 | Q36: 0.44634631 | R36: 0.04877671
B37: ROA | C37: 0.060488389 | D37: 0.08379492 | E37: 0.26730948 | F37: 0.21408956 | G37: 0.20136167 | H37: 0.027273066 | I37: 0.15409814 | J37: 0.061213637 | K37: 0.043843926 | L37: 0.03521071 | M37: 0.096425148 | N37: 0.24586254 | O37: 0.22477584 | P37: 0.76645705 | Q37: 0.21519846 | R37: 0.039718022
A39: x | B39: Efficiency | C39: ACM RESEARCH-A | D39: =D30 -> NAURA TECH GR -A | E39: =E30 -> LAM RESEARCH | F39: =F30 -> TOKYO ELECTRON | G39: =G30 -> APPLIED MATERIAL | H39: =H30 -> KINGSEMI CO LT-A | I39: =I30 -> SCREEN HOLDINGS | J39: =J30 -> SAMSUNG ELECTRON | K39: =K30 -> HIMAX TECHNO-ADR | ... R39: =R30 -> ADV MICRO DEVICE
B41: Asset turnover | C41: 0.43976382 | D41: 0.46610335 | E41: 0.91971048 | F41: 0.96948931 | G41: 0.84331987 | H41: 0.33836023 | I41: 0.98627122 | J41: 0.62302357 | K41: 0.52590068 | L41: 0.38402413 | M41: 0.49996744 | N41: 0.65792251 | O41: 0.52371605 | P41: 1.4623197 | Q41: 0.80401104 | R41: 0.4148389
B42: Net operating asset turnover | C42: 0.63958987 | D42: 0.66141513 | E42: 1.8077572 | F42: 1.1533071 | G42: 1.4823542 | H42: 0.70870011 | I42: 1.3408352 | J42: 0.78648784 | K42: 1.0376817 | L42: 0.81063639 | M42: 0.79010711 | N42: 0.82252709 | O42: 0.89799023 | P42: 2.2452642 | Q42: 1.4750511 | R42: 0.41765201
B43: Fixed asset turnover | C43: 2.9565154 | D43: 4.3901527 | E43: 7.5707084 | F43: 5.8148561 | G43: 7.0666831 | H43: 1.5648719 | I43: 5.7420797 | J43: 1.5449951 | K43: 7.1986097 | L43: 1.9414066 | M43: 7.4820449 | N43: 1.2599335 | O43: 1.0345164 | P43: 18.70463 | Q43: 9.362987 | R43: 13.366448
B44: Revenue per employee thsnd of USD | C44: 402.94909 | D44: 285.04789 | E44: 970.29426 | F44: 829.20078 | G44: 801.48459 | H44: 179.44499 | I44: 653.68633 | J44: #VALUE! | K44: 408.61782 | L44: 393.06476 | M44: 668.18375 | N44: #VALUE! | O44: 1266.3073 | P44: 4589.3889 | Q44: 882.79592 | R44: 1057.1429
B45: EBIT per employee thsnd of USD | C45: 71.994068 | D45: 57.307325 | E45: 312.82016 | F45: 231.14292 | G45: 241.20448 | H45: 17.231958 | I45: 137.96785 | J45: #VALUE! | K45: 29.237023 | L45: 63.087683 | M45: 159.55706 | N45: #VALUE! | O45: 616.90416 | P45: 2681.75 | Q45: 252.53061 | R45: 95.25
A47: x | B47: Working Capital | C47: ACM RESEARCH-A | D47: =D39 -> NAURA TECH GR -A | E47: =E39 -> LAM RESEARCH | F47: =F39 -> TOKYO ELECTRON | G47: =G39 -> APPLIED MATERIAL | H47: =H39 -> KINGSEMI CO LT-A | I47: =I39 -> SCREEN HOLDINGS | J47: =J39 -> SAMSUNG ELECTRON | K47: =K39 -> HIMAX TECHNO-ADR | ... R47: =R39 -> ADV MICRO DEVICE
B49: DSO | C49: 162.79737 | D49: 82.436898 | E49: 58.219583 | F49: 56.541621 | G49: 68.327124 | H49: 100.79116 | I49: 50.221513 | J49: 51.576144 | K49: 94.66187 | L49: 53.711647 | M49: 91.875006 | N49: 55.188518 | O49: 23.925655 | P49: 46.200051 | Q49: 27.265159 | R49: 66.798919
B50: DIO | C50: 553.55537 | D50: 485.1318 | E50: 164.08939 | F50: 215.34159 | G50: 140.49881 | H50: 636.6938 | I50: 167.01704 | J50: 99.037351 | K50: 99.870869 | L50: 137.6333 | M50: 213.78951 | N50: 137.24236 | O50: 74.710076 | P50: 79.046409 | Q50: 119.57691 | R50: 136.96956
B51: DPO | C51: 131.15285 | D51: 143.06845 | E51: 27.989828 | F51: 25.434942 | G51: 39.368105 | H51: 96.771231 | I51: 48.820485 | J51: 24.524046 | K51: 96.948928 | L51: 29.882593 | M51: 35.874324 | N51: 20.254174 | O51: 18.842625 | P51: 39.917529 | Q51: 46.858048 | R51: 50.597906
B52: CCC | C52: 565.09836 | D52: 387.87773 | E52: 194.31914 | F52: 251.72768 | G52: 172.01492 | H52: 595.8599 | I52: 154.91905 | J52: 127.00841 | K52: 133.95945 | L52: 150.07985 | M52: 290.80926 | N52: 174.86502 | O52: 89.204707 | P52: 87.976881 | Q52: 124.64536 | R52: 171.22044
B53: Working capital intensity | C53: 1.0621352 | D53: 0.77161558 | E53: 0.44732366 | F53: 0.428873 | G53: 0.44172229 | H53: 1.26046 | I53: 0.3499921 | J53: 0.42330918 | K53: 0.49321857 | L53: 0.36070951 | M53: 1.2425385 | N53: 0.20857268 | O53: 0.50428477 | P53: 0.37412994 | Q53: 0.35483274 | R53: 0.43827703
B54: Cash conversion ratio | C54: 1.009616 | D54: 0.22101468 | E54: 1.0461443 | F54: 0.83487471 | G54: 1.1029617 | H54: 1.9169258 | I54: 0.52500313 | J54: 2.2301139 | K54: 1.7000044 | L54: 1.183171 | M54: 1.3130522 | N54: 1.2696757 | O54: 1.427635 | P54: 0.78682185 | Q54: 1.2115977 | R54: 1.6005263
B55: CFO margin | C55: 0.19491944 | D55: 0.04876447 | E55: 0.33485577 | F55: 0.23942329 | G55: 0.31928908 | H55: 0.24208379 | I55: 0.11392537 | J55: 0.24257122 | K55: 0.12789562 | L55: 0.19490295 | M55: 0.24883093 | N55: 0.45013677 | O55: 0.65209615 | P55: 0.49111474 | Q55: 0.31317694 | R55: 0.11793678
A57: x | B57: Leverage & Coverage | C57: ACM RESEARCH-A | D57: =D47 -> NAURA TECH GR -A | E57: =E47 -> LAM RESEARCH | F57: =F47 -> TOKYO ELECTRON | G57: =G47 -> APPLIED MATERIAL | H57: =H47 -> KINGSEMI CO LT-A | I57: =I47 -> SCREEN HOLDINGS | J57: =J47 -> SAMSUNG ELECTRON | K57: =K47 -> HIMAX TECHNO-ADR | ... R57: =R47 -> ADV MICRO DEVICE
B59: Net debt / EBITDA | C59: -1.2833814 | D59: ='Trading Comps'!T15 -> -0.53024979 | E59: -0.2599078 | F59: ='Trading Comps'!T17 -> -0.86142492 | G59: -0.027833002 | H59: ='Trading Comps'!T19 -> 0.33248082 | I59: -1.1344257 | J59: -1.1963192 | K59: 2.3392665 | L59: 4.1076606 | M59: -3.5423461 | N59: 0.16525226 | O59: -0.6882496 | P59: -0.46809481 | Q59: 0.34899182 | R59: -0.37540269
B60: Net debt / FCF | C60: -3.6479918 | D60: 6.8946122 | E60: -0.30182498 | F60: -1.1204318 | G60: -0.38279685 | H60: 0.47214077 | I60: -3.9604231 | J60: -4.3251972 | K60: 2.8066274 | L60: 11.824317 | M60: -3.9161587 | N60: 0.81555666 | O60: -1.4760762 | P60: -0.54130445 | Q60: 0.19173909 | R60: -1.2162162
B61: Interest coverage | C61: 36.376295 | D61: 37.905028 | E61: 33.113741 | G61: 31.850202 | H61: 8.3201208 | I61: 1005.0593 | J61: 36.204568 | K61: 16.995765 | L61: 2.4808542 | N61: 17.444721 | O61: 125.96313 | P61: 329.76923 | Q61: 14.449067 | R61: 20.652174
B62: Debt / capital | C62: 0.14694841 | D62: 0.20403397 | E62: 0.3253864 | F62: 0.011403021 | G62: 0.25794736 | H62: 0.36323441 | I62: 0.010727656 | J62: 0.045858039 | K62: 0.37827906 | L62: 0.52420249 | M62: 0.0078097268 | N62: 0.25614038 | O62: 0.19495747 | P62: 0.11462437 | Q62: 0.37013952 | R62: 0.039316468
B63: Short term debt / total debt | C63: 0.42068407 | D63: 0.50260587 | E63: 0.17513053 | F63: 0.17360624 | G63: 0.1341408 | H63: 0.34494415 | I63: 0.43467777 | J63: 0.79563619 | K63: 0.94141118 | L63: 0.0033913958 | M63: 0.3572795 | N63: 0.22947383 | O63: 0.05716855 | P63: 0.028042843 | Q63: 0.094689119 | R63: 0.061120543
A65: x | B65: Liquidity | C65: ACM RESEARCH-A | D65: =D57 -> NAURA TECH GR -A | E65: =E57 -> LAM RESEARCH | F65: =F57 -> TOKYO ELECTRON | G65: =G57 -> APPLIED MATERIAL | H65: =H57 -> KINGSEMI CO LT-A | I65: =I57 -> SCREEN HOLDINGS | J65: =J57 -> SAMSUNG ELECTRON | K65: =K57 -> HIMAX TECHNO-ADR | ... R65: =R57 -> ADV MICRO DEVICE
B67: Current ratio | C67: 2.3133229 | D67: 1.9679205 | E67: 2.2101181 | F67: 2.6562761 | G67: 2.5059046 | H67: 2.7011155 | I67: 2.0025029 | J67: 2.4329934 | K67: 1.6529674 | L67: 3.0776308 | M67: 8.6867581 | N67: 1.6934963 | O67: 2.4423022 | P67: 4.4398515 | Q67: 2.4020373 | R67: 2.6162615
B68: Quick ratio | C68: 1.2961591 | D68: 0.83827814 | E68: 1.4872256 | F68: 1.4481012 | G68: 1.7365376 | H68: 1.3257343 | I68: 1.2346583 | J68: 1.6744997 | K68: 0.64687094 | L68: 1.5699915 | M68: 6.8227222 | N68: 1.0793717 | O68: 2.1303563 | P68: 3.6723555 | Q68: 1.6402323 | R68: 1.5552809
B69: Cash ratio | C69: 0.69256417 | D69: 0.52533532 | E69: 0.97293628 | F69: 0.73199543 | G69: 1.1184459 | H69: 0.95897898 | I69: 0.83595233 | J69: 1.2070744 | K69: 0.31174271 | L69: 0.62685985 | M69: 5.0110707 | N69: 0.55789066 | O69: 1.9151864 | P69: 2.3943038 | Q69: 1.2661843 | R69: 0.70484824
A71: x | B71: Cash Deployment | C71: ACM RESEARCH-A | D71: =D65 -> NAURA TECH GR -A | E71: =E65 -> LAM RESEARCH | F71: =F65 -> TOKYO ELECTRON | G71: =G65 -> APPLIED MATERIAL | H71: =H65 -> KINGSEMI CO LT-A | I71: =I65 -> SCREEN HOLDINGS | J71: =J65 -> SAMSUNG ELECTRON | K71: =K65 -> HIMAX TECHNO-ADR | ... R71: =R65 -> ADV MICRO DEVICE
B73: Capex intensity | C73: 0.10989135 | D73: 0.06857529 | E73: 0.041180454 | F73: 0.069107259 | G73: 0.043788637 | H73: 0.1279076 | I73: 0.040889601 | J73: 0.17862026 | K73: 0.083983053 | L73: 0.097372955 | M73: 0.032312693 | N73: 0.25172828 | O73: 0.33337236 | P73: 0.024797505 | Q73: 0.026718341 | R73: 0.024665503
B74: Capex / depreciation | C74: 8.6232567 | D74: 2.0296 | E74: 1.9653927 | F74: 2.6987714 | G74: 3.0357143 | H74: 3.5676871 | I74: 1.9925961 | J74: 1.2606287 | K74: 3.4068176 | L74: 0.83440893 | M74: 0.51201271 | N74: 1.3243737 | O74: 1.4557741 | P74: 1.7360515 | Q74: 0.6101993 | R74: 0.2075718
B75: R&D capitalization rate | C75: #VALUE! | D75: 0.42476519 | E75: #VALUE! | F75: #VALUE! | G75: #VALUE! | H75: 0 | I75: #VALUE! | J75: #VALUE! | K75: #VALUE! | L75: #VALUE! | M75: #VALUE! | N75: 0.084312941 | O75: #VALUE! | P75: #VALUE! | Q75: #VALUE! | R75: #VALUE!
B76: R&D capitalization test | C76: #VALUE! | D76: #VALUE! | E76: #VALUE! | F76: #VALUE! | G76: #VALUE! | H76: #VALUE! | I76: #VALUE! | J76: #VALUE! | K76: #VALUE! | L76: #VALUE! | M76: #VALUE! | N76: 2.4163117 | O76: #VALUE! | P76: #VALUE! | Q76: #VALUE! | R76: #VALUE!
B77: Dividend payout | C77: 0 | D77: 0.10073061 | E77: 0.22082214 | F77: 0.50127818 | G77: 0.16608611 | H77: 0.10903677 | I77: 0.29891321 | J77: 0.29176183 | K77: 0.63558197 | L77: 0.20621954 | M77: 0 | N77: 0.07681642 | O77: 0.37574599 | P77: 0.011443469 | Q77: 0.36468843 | R77: 0
B78: FCF payout | C78: -0.15858659 | D78: 1.2071042 | E78: 0.76206175 | F78: 0.99756961 | G78: 0.63737144 | H78: -0.96511558 | I78: 0.98424608 | J78: #VALUE! | K78: 0.4370448 | L78: 0.14656818 | M78: 0.16359848 | N78: 0.10297652 | O78: 0.47334056 | P78: 0.56437645 | Q78: 0.65702086 | R78: 0.13703347
B79: Buybacks as % CFO | C79: 0 | D79: 0 | E79: 0.55437788 | F79: 0.25766867 | G79: 0.44059007 | H79: 0 | I79: 0.26584215 | J79: 0.024824746 | K79: 0.025867421 | L79: 0 | M79: 0.1795617 | N79: 0 | O79: 0.0016367655 | P79: 0.52592489 | Q79: 0.33773152 | R79: 0.52285432
A81: x | B81: Earnings Quality | C81: ACM RESEARCH-A | D81: =D71 -> NAURA TECH GR -A | E81: =E71 -> LAM RESEARCH | F81: =F71 -> TOKYO ELECTRON | G81: =G71 -> APPLIED MATERIAL | H81: =H71 -> KINGSEMI CO LT-A | I81: =I71 -> SCREEN HOLDINGS | J81: =J71 -> SAMSUNG ELECTRON | K81: =K71 -> HIMAX TECHNO-ADR | ... R81: =R71 -> ADV MICRO DEVICE
B83: Cash/earnings conversion | C83: 4.1471708 | D83: 0.70547279 | E83: 3.9952083 | F83: 4.8234811 | G83: 5.1321695 | H83: #VALUE! | I83: 2.7983874 | J83: 8.5041047 | K83: 164.50496 | L83: 5.7691416 | M83: 5.7356711 | N83: 3.5360126 | O83: 4.6694433 | P83: 2.103539 | Q83: 3.9394522 | R83: 1.606601
B84: FCF / net income | C84: 1.9038901 | D84: -0.286602 | E84: 3.5038789 | F84: 3.5113064 | G84: 4.4283223 | H84: #VALUE! | I84: 1.9425367 | J84: 2.5141167 | K84: 164.28794 | L84: 2.886895 | M84: 4.9908482 | N84: 1.6436839 | O84: 2.3042337 | P84: 1.9973265 | Q84: 3.6033622 | R84: 1.2705937
A86: x | B86: Per Share & Dilution | C86: ACM RESEARCH-A | D86: =D81 -> NAURA TECH GR -A | E86: =E81 -> LAM RESEARCH | F86: =F81 -> TOKYO ELECTRON | G86: =G81 -> APPLIED MATERIAL | H86: =H81 -> KINGSEMI CO LT-A | I86: =I81 -> SCREEN HOLDINGS | J86: =J81 -> SAMSUNG ELECTRON | K86: =K81 -> HIMAX TECHNO-ADR | ... R86: =R81 -> ADV MICRO DEVICE
B88: Diluted share count YoY | C88: 0.064695207 | D88: 0.00075725306 | E88: 0.0031420549 | F88: 0.0028183833 | G88: 0.0084643289 | H88: 0 | I88: 0.0011833714 | J88: 0 | K88: 0.0012471681 | L88: 0.0059226478 | M88: 0.0064244168 | N88: 0.030641934 | O88: #VALUE! | P88: 0.010140501 | Q88: 0.012544803 | R88: 0.010493827
B89: SBC / revenue | C89: 0.063386855 | D89: {=_xll.BDP(Inputs!$E$21,"CF_STOCK_BASED_COMPENSATION")/_xll.BDP(Inputs!$E$21,"sales_rev_turn")} -> #NAME? | E89: 0.01862544 | F89: #VALUE! | G89: 0.021231969 | H89: #VALUE! | I89: #VALUE! | J89: #VALUE! | K89: 0.0013751624 | L89: 0.020319276 | M89: 0.028943981 | N89: #VALUE! | O89: 0.00042936658 | P89: 0.036299685 | Q89: 0.067963657 | R89: 0.054566608
B90: SBC / CFO | C90: 0.32519515 | D90: {=_xll.BDP(Inputs!$E$21,"CF_STOCK_BASED_COMPENSATION")/_xll.BDP(Inputs!$E$21,"cf_cash_from_oper")} -> #NAME? | E90: 0.055622277 | F90: #VALUE! | G90: 0.066497637 | H90: #VALUE! | I90: #VALUE! | J90: #VALUE! | K90: 0.010752225 | L90: 0.1042533 | M90: 0.11631987 | N90: #VALUE! | O90: 0.0006584406 | P90: 0.07391284 | Q90: 0.2170136 | R90: 0.46267675
B91: EPS in USD | C91: 1.713291 | D91: 1.1653285 | E91: 4.133232 | F91: 7.8213258 | G91: 9.511659 | H91: 0.084260282 | I91: 6.7495978 | J91: 3.2041373 | K91: 0.402583 | L91: 1.987539 | M91: 4.72027 | N91: 27.325777 | O91: #N/A | P91: 3.446677 | Q91: 9.934211 | R91: 1.841934

Sheet Trading Comps
D7: Current | E7: % of | I7: Enterprise Value / | S7: LTM | T7: Net | V7: Price / | Z7: LT
D8: Share | E8: 52-week | F8: Equity | G8: Enterprise | I8: LTM | J8: 2025 | K8: 2026 | L8: LTM | M8: 2025E | N8: 2026E | O8: LTM | P8: 2025E | Q8: 2026E | S8: EBITDA | T8: Debt / | V8: LTM | W8: 2025E | X8: 2026E | Z8: EPS
B9: Company | C9: Ticker | D9: Price | E9: High | F9: Value | G9: Value | I9: Sales | J9: Sales | K9: Sales | L9: EBITDA | M9: EBITDA | N9: EBITDA | O9: EBIT | P9: EBIT | Q9: EBIT | S9: Margin | T9: EBITDA | V9: EPS | W9: EPS | X9: EPS | Z9: Growth
B11: ACM RESEARCH-A | C11: ACMR US | D11: USD 41,07 | E11: 0.91023936 | F11: 2411.3302 | G11: 1659.0665 | I11: 2.0352498 | J11: 1.8196506 | K11: 1.5585406 | L11: 10.293572 | M11: 9.4695574 | N11: 7.3605433 | O11: 11.391245 | P11: 9.986856 | Q11: 7.9906873 | S11: 0.19772046 | T11: 1.7829874 | V11: 22.304965 | W11: 18.033452 | X11: 15.237474 | Z11: 0.12620777
B12: Tier I: Wafer Cleaning, Electroplanting and PECVD equipment and Track system
B15: NAURA TECH GR -A | C15: 002371 CH | D15: CNY 458,05 | E15: 0.96704387 | F15: 317078.43 | G15: 246241.31 | I15: 7.318872 | J15: 6.3666721 | K15: 5.028357 | L15: 31.177 | M15: 26.536197 | N15: 20.194639 | O15: 36.404229 | P15: 30.166943 | Q15: 22.686216 | S15: 0.23475229 | T15: =+-558.3/1052.9 -> -0.53024979 | V15: 52.353312 | W15: 42.88882 | X15: 32.903184 | Z15: 0.23977321
B16: LAM RESEARCH | C16: LRCX US | D16: USD 141 | E16: 0.91740135 | F16: 169243.14 | G16: 121687.42 | I16: 6.6006793 | J16: 6.6634109 | K16: 6.0554512 | L16: 19.224347 | M16: 19.499719 | N16: 17.452231 | O16: 20.473749 | P16: 20.771272 | Q16: 18.76951 | S16: 0.34334999 | T16: 0.75654042 | V16: 31.838035 | W16: 32.665485 | X16: 29.848879 | Z16: 0.11251985
B17: TOKYO ELECTRON | C17: 8035 JT | D17: JPY 29700 | E17: 0.94225888 | F17: 13809406 | G17: 17860479 | I17: 7.361858 | J17: 7.3885397 | K17: 7.4411087 | L17: 24.05186 | M17: 23.573634 | N17: 25.557035 | O17: 26.409887 | P17: 25.834296 | Q17: 29.047342 | S17: 0.30608269 | T17: =+-3034.8/3523 -> -0.86142492 | V17: 25.718894 | W17: 25.948484 | X17: 28.886836 | Z17: 0.051737427
B18: APPLIED MATERIAL | C18: AMAT US | D18: USD 220,3 | E18: 0.97266988 | F18: 170075.19 | G18: 147742.93 | I18: 5.1634897 | J18: 5.2298901 | K18: 5.0800179 | L18: 16.33963 | M18: 16.502926 | N18: 16.277124 | O18: 17.157465 | P18: 17.325197 | Q18: 17.22501 | S18: 0.31601021 | T18: 0.74685222 | V18: 22.058298 | W18: 22.470919 | X18: 22.584847 | Z18: 0.040295709
B19: KINGSEMI CO LT-A | C19: 688037 CH | D19: CNY 150,1 | E19: 0.94473817 | F19: 29945.686 | G19: 22227.609 | I19: 12.564227 | J19: 10.670494 | K19: 8.1705498 | L19: 90.537005 | M19: 112.54486 | N19: 79.384319 | O19: 130.83757 | P19: 82.446622 | Q19: 51.860965 | S19: 0.13877449 | T19: =13/39.1 -> 0.33248082 | V19: 245.2583 | W19: 118.83209 | X19: 75.735169 | Z19: -0.6931
B21: Mean | I21: =AVERAGE(I15:I19) -> 7.8018252 | K21: =AVERAGE(K15:K19) -> 6.3550969 | L21: =AVERAGE(L15:L19) -> 36.265968 | M21: =AVERAGE(M15:M19) -> 39.731467 | N21: =AVERAGE(N15:N19) -> 31.77307 | O21: =AVERAGE(O15:O19) -> 46.25658 | P21: =AVERAGE(P15:P19) -> 35.308866 | Q21: =AVERAGE(Q15:Q19) -> 27.917808 | S21: =AVERAGE(S15:S19) -> 0.26779393 | T21: =AVERAGE(T15:T19) -> 0.088839751 | V21: =AVERAGE(V15:V19) -> 75.445369 | W21: =AVERAGE(W15:W19) -> 48.561159 | X21: =AVERAGE(X15:X19) -> 37.991783 | Z21: =AVERAGE(Z15:Z19) -> -0.049754761
B22: Median | I22: =MEDIAN(I15:I19) -> 7.318872 | J22: =MEDIAN(J15:J19) -> 6.6634109 | K22: =MEDIAN(K15:K19) -> 6.0554512 | L22: =MEDIAN(L15:L19) -> 24.05186 | M22: =MEDIAN(M15:M19) -> 23.573634 | N22: =MEDIAN(N15:N19) -> 20.194639 | O22: =MEDIAN(O15:O19) -> 26.409887 | P22: =MEDIAN(P15:P19) -> 25.834296 | Q22: =MEDIAN(Q15:Q19) -> 22.686216 | S22: =MEDIAN(S15:S19) -> 0.30608269 | T22: =MEDIAN(T15:T19) -> 0.33248082 | V22: =MEDIAN(V15:V19) -> 31.838035 | W22: =MEDIAN(W15:W19) -> 32.665485 | X22: =MEDIAN(X15:X19) -> 29.848879 | Z22: =MEDIAN(Z15:Z19) -> 0.051737427
B24: Tier II: Related to Wafer
B27: SCREEN HOLDINGS | C27: 7735 JT | D27: JPY 14295 | E27: 0.92106959 | F27: 1318628.3 | G27: 945983.95 | I27: 1.5091387 | J27: 1.5312018 | K27: 1.5030303 | L27: 6.5019207 | M27: 6.7231961 | N27: 6.8134051 | O27: 7.1502403 | P27: 7.3664877 | Q27: 7.6722613 | S27: 0.23210659 | T27: 0.030943069 | V27: 13.510964 | W27: 14.289076 | X27: 14.51873 | Z27: 0.052579814
B28: SAMSUNG ELECTRON | C28: 005930 KS | D28: KRW 89000 | E28: 0.94179894 | F28: 5.5881382e+08 | G28: 2.7571821e+08 | I28: 0.89346641 | J28: 0.89346641 | K28: 0.78169168 | L28: 3.8045303 | M28: 3.5398446 | N28: 2.7590312 | O28: 10.197659 | P28: 8.7103889 | Q28: 5.1807098 | S28: 0.23484276 | T28: 0.1935901 | V28: 20.964264 | W28: 17.61825 | X28: 12.133603 | Z28: 0.20293984
B29: HIMAX TECHNO-ADR | C29: HIMX US | D29: USD 8,94 | E29: 0.64270309 | F29: 1471.0218 | G29: 1775.5605 | I29: 1.9959964 | J29: 2.1580802 | K29: 1.905619 | L29: 20.819386 | M29: 23.099226 | N29: 16.734783 | O29: 27.896126 | P29: 32.489671 | Q29: 18.939312 | S29: 0.095872009 | T29: 6.0600554 | V29: 20.905307 | W29: 29.34219 | X29: 15.649168 | Z29: 0.3989
B30: ENTEGRIS INC | C30: ENTG US | D30: USD 94,23 | E30: 0.83864365 | F30: 13363.54 | G30: 16151.732 | I30: 5.0111932 | J30: 5.0433448 | K30: 4.654566 | L30: 17.97761 | M30: 18.061304 | N30: 15.887423 | O30: 31.221996 | P30: 23.374431 | Q30: 19.811446 | S30: 0.27874635 | T30: 4.5283179 | V30: 44.427918 | W30: 31.423459 | X30: 24.94467 | Z30: 0.19185015
B31: ONTO INNOVATION | C31: ONTO US | D31: USD 136,6 | E31: 0.59802119 | F31: 6244.5252 | G31: 3957.3636 | I31: 3.8185479 | J31: 3.9682763 | K31: 3.5849743 | L31: 12.957374 | M31: 13.369471 | N31: 11.27454 | O31: 15.991092 | P31: 15.748462 | Q31: 13.337287 | S31: 0.29470074 | T31: 0.053883 | V31: 26.874971 | W31: 25.821607 | X31: 22.026544 | Z31: 0.24970818
B33: Mean | I33: =AVERAGE(I27:I31) -> 2.6456685 | J33: =AVERAGE(J27:J31) -> 2.7188739 | K33: =AVERAGE(K27:K31) -> 2.4859763 | L33: =AVERAGE(L27:L31) -> 12.412164 | M33: =AVERAGE(M27:M31) -> 12.958609 | N33: =AVERAGE(N27:N31) -> 10.693837 | O33: =AVERAGE(O27:O31) -> 18.491423 | P33: =AVERAGE(P27:P31) -> 17.537888 | Q33: =AVERAGE(Q27:Q31) -> 12.988203 | S33: =AVERAGE(S27:S31) -> 0.22725369 | T33: =AVERAGE(T27:T31) -> 2.1733579 | V33: =AVERAGE(V27:V31) -> 25.336685 | W33: =AVERAGE(W27:W31) -> 23.698916 | X33: =AVERAGE(X27:X31) -> 17.854543 | Z33: =AVERAGE(Z27:Z31) -> 0.2191956
B34: Median | I34: =MEDIAN(I27:I31) -> 1.9959964 | J34: =MEDIAN(J27:J31) -> 2.1580802 | K34: =MEDIAN(K27:K31) -> 1.905619 | L34: =MEDIAN(L27:L31) -> 12.957374 | M34: =MEDIAN(M27:M31) -> 13.369471 | N34: =MEDIAN(N27:N31) -> 11.27454 | O34: =MEDIAN(O27:O31) -> 15.991092 | P34: =MEDIAN(P27:P31) -> 15.748462 | Q34: =MEDIAN(Q27:Q31) -> 13.337287 | S34: =MEDIAN(S27:S31) -> 0.23484276 | T34: =MEDIAN(T27:T31) -> 0.1935901 | V34: =MEDIAN(V27:V31) -> 20.964264 | W34: =MEDIAN(W27:W31) -> 25.821607 | X34: =MEDIAN(X27:X31) -> 15.649168 | Z34: =MEDIAN(Z27:Z31) -> 0.20293984
B36: Tier III: Semiconductors Industry
B39: SK HYNIX INC | C39: 000660 KS | D39: KRW 395500 | E39: 0.97775031 | F39: 2.8792494e+14 | G39: 2.0902255e+08 | I39: 2.7071534 | J39: 2.3402536 | K39: 1.8978659 | L39: 4.6634215 | M39: 3.9082272 | N39: 3.0506407 | O39: 6.580049 | P39: 5.3375498 | Q39: 4.0600281 | S39: 0.58050798 | T39: 0.54369117 | V39: 11.811781 | W39: 9.6664487 | X39: 7.6743818 | Z39: 0.40193663
B40: TAIWAN SEMIC-ADR | C40: TSM US | D40: USD 292,19 | E40: 0.95082981 | F40: 1.5793553e+12 | G40: 25900715 | I40: 7.6151723 | J40: 6.9958919 | K40: 5.9399039 | L40: 10.980656 | M40: 10.252473 | N40: 8.8403122 | O40: 15.631517 | P40: 14.549916 | Q40: 12.491881 | S40: 0.69350797 | T40: 0.42787285 | V40: 1.0614112 | W40: 0.99627027 | X40: 0.85305053 | Z40: 0.1545171
B41: NVIDIA CORP | C41: NVDA US | D41: USD 187,62 | E41: 0.98204658 | F41: 4513239000000 | G41: 4178011.5 | I41: 25.287871 | J41: 32.235625 | K41: 20.243348 | L41: 42.097955 | M41: 47.634476 | N41: 32.215379 | O41: 43.276172 | P41: 48.649495 | Q41: 32.18802 | S41: 0.60069121 | T41: 0.10739438 | V41: 55.520693 | W41: 63.940457 | X41: 42.379469 | Z41: 0.35454655
B42: QUALCOMM INC | C42: QCOM US | D42: USD 169,18 | E42: 0.92904997 | F42: 182761020000 | G42: 176634.36 | I42: 4.0833706 | J42: 4.0456996 | K42: 3.9613941 | L42: 12.577212 | M42: 10.4571 | N42: 11.112651 | O42: 14.274637 | P42: 11.596364 | Q42: 11.897032 | S42: 0.32466422 | T42: 1.0803624 | V42: 16.275368 | W42: 13.578253 | X42: 13.677148 | Z42: 0.024015069
B43: ADV MICRO DEVICE | C43: AMD US | D43: USD 164,67 | E43: 0.72634964 | F43: 3.372756e+11 | G43: 231278.82 | I43: 7.8134736 | J43: 7.0102586 | K43: 5.5877151 | L43: 40.73962 | M43: 31.849628 | N43: 20.377826 | O43: 86.718718 | P43: 32.337077 | Q43: 20.95217 | S43: 0.19179054 | T43: 0.73640326 | V43: 126.54692 | W43: 59.018161 | X43: 37.26666 | Z43: 0.35890074
B45: Mean | I45: =AVERAGE(I39:I43) -> 9.5014082 | J45: =AVERAGE(J39:J43) -> 10.525546 | K45: =AVERAGE(K39:K43) -> 7.5260455 | L45: =AVERAGE(L39:L43) -> 22.211773 | M45: =AVERAGE(M39:M43) -> 20.820381 | N45: =AVERAGE(N39:N43) -> 15.119362 | O45: =AVERAGE(O39:O43) -> 33.296219 | P45: =AVERAGE(P39:P43) -> 22.49408 | Q45: =AVERAGE(Q39:Q43) -> 16.317826 | S45: =AVERAGE(S39:S43) -> 0.47823238 | T45: =AVERAGE(T39:T43) -> 0.5791448 | V45: =AVERAGE(V39:V43) -> 42.243234 | W45: =AVERAGE(W39:W43) -> 29.439918 | X45: =AVERAGE(X39:X43) -> 20.370142 | Z45: =AVERAGE(Z39:Z43) -> 0.25878322
B46: Median | I46: =MEDIAN(I39:I43) -> 7.6151723 | J46: =MEDIAN(J39:J43) -> 6.9958919 | K46: =MEDIAN(K39:K43) -> 5.5877151 | L46: =MEDIAN(L39:L43) -> 12.577212 | M46: =MEDIAN(M39:M43) -> 10.4571 | N46: =MEDIAN(N39:N43) -> 11.112651 | O46: =MEDIAN(O39:O43) -> 15.631517 | P46: =MEDIAN(P39:P43) -> 14.549916 | Q46: =MEDIAN(Q39:Q43) -> 12.491881 | S46: =MEDIAN(S39:S43) -> 0.58050798 | T46: =MEDIAN(T39:T43) -> 0.54369117 | V46: =MEDIAN(V39:V43) -> 16.275368 | W46: =MEDIAN(W39:W43) -> 13.578253 | X46: =MEDIAN(X39:X43) -> 13.677148 | Z46: =MEDIAN(Z39:Z43) -> 0.35454655
B48: Overall
B51: Mean | I51: =AVERAGE(I39:I43,I27:I32,I15:I19) -> 6.649634 | J51: =AVERAGE(J39:J43,J27:J32,J15:J19) -> 6.8360737 | K51: =AVERAGE(K39:K43,K27:K32,K15:K19) -> 5.4557062 | L51: =AVERAGE(L39:L43,L27:L32,L15:L19) -> 23.629968 | M51: =AVERAGE(M39:M43,M27:M32,M15:M19) -> 24.503485 | N51: =AVERAGE(N39:N43,N27:N32,N15:N19) -> 19.195423 | O51: =AVERAGE(O39:O43,O27:O32,O15:O19) -> 32.681407 | P51: =AVERAGE(P39:P43,P27:P32,P15:P19) -> 25.113612 | Q51: =AVERAGE(Q39:Q43,Q27:Q32,Q15:Q19) -> 19.074613 | S51: =AVERAGE(S39:S43,S27:S32,S15:S19) -> 0.32442667 | T51: =AVERAGE(T39:T43,T27:T32,T15:T19) -> 0.94711415 | V51: =AVERAGE(V39:V43,V27:V32,V15:V19) -> 47.675096 | W51: =AVERAGE(W39:W43,W27:W32,W15:W19) -> 33.899998 | X51: =AVERAGE(X39:X43,X27:X32,X15:X19) -> 25.405489 | Z51: =AVERAGE(Z39:Z43,Z27:Z32,Z15:Z19) -> 0.14274135
B52: Median | I52: =MEDIAN(I39:I43,I27:I31,I15:I19) -> 5.1634897 | J52: =MEDIAN(J39:J43,J27:J31,J15:J19) -> 5.2298901 | K52: =MEDIAN(K39:K43,K27:K31,K15:K19) -> 5.028357 | L52: =MEDIAN(L39:L43,L27:L31,L15:L19) -> 17.97761 | M52: =MEDIAN(M39:M43,M27:M31,M15:M19) -> 18.061304 | N52: =MEDIAN(N39:N43,N27:N31,N15:N19) -> 16.277124 | O52: =MEDIAN(O39:O43,O27:O31,O15:O19) -> 20.473749 | P52: =MEDIAN(P39:P43,P27:P31,P15:P19) -> 20.771272 | Q52: =MEDIAN(Q39:Q43,Q27:Q31,Q15:Q19) -> 18.76951 | S52: =MEDIAN(S39:S43,S27:S31,S15:S19) -> 0.29470074 | T52: =MEDIAN(T39:T43,T27:T31,T15:T19) -> 0.42787285 | V52: =MEDIAN(V39:V43,V27:V31,V15:V19) -> 25.718894 | W52: =MEDIAN(W39:W43,W27:W31,W15:W19) -> 25.948484 | X52: =MEDIAN(X39:X43,X27:X31,X15:X19) -> 22.584847 | Z52: =MEDIAN(Z39:Z43,Z27:Z31,Z15:Z19) -> 0.19185015
B54: High | I54: =MAX(I39:I43,I27:I31,I15:I19) -> 25.287871 | J54: =MAX(J39:J43,J27:J31,J15:J19) -> 32.235625 | K54: =MAX(K39:K43,K27:K31,K15:K19) -> 20.243348 | L54: =MAX(L39:L43,L27:L31,L15:L19) -> 90.537005 | M54: =MAX(M39:M43,M27:M31,M15:M19) -> 112.54486 | N54: =MAX(N39:N43,N27:N31,N15:N19) -> 79.384319 | O54: =MAX(O39:O43,O27:O31,O15:O19) -> 130.83757 | P54: =MAX(P39:P43,P27:P31,P15:P19) -> 82.446622 | ... T54: =MAX(T39:T43,T27:T31,T15:T19) -> 6.0600554 | V54: =MAX(V39:V43,V27:V31,V15:V19) -> 245.2583 | W54: =MAX(W39:W43,W27:W31,W15:W19) -> 118.83209 | X54: =MAX(X39:X43,X27:X31,X15:X19) -> 75.735169 | Z54: =MAX(Z39:Z43,Z27:Z31,Z15:Z19) -> 0.40193663
B55: Low | I55: =MIN(I39:I43,I27:I31,I15:I19) -> 0.89346641 | J55: =MIN(J39:J43,J27:J31,J15:J19) -> 0.89346641 | K55: =MIN(K39:K43,K27:K31,K15:K19) -> 0.78169168 | L55: =MIN(L39:L43,L27:L31,L15:L19) -> 3.8045303 | M55: =MIN(M39:M43,M27:M31,M15:M19) -> 3.5398446 | N55: =MIN(N39:N43,N27:N31,N15:N19) -> 2.7590312 | O55: =MIN(O39:O43,O27:O31,O15:O19) -> 6.580049 | P55: =MIN(P39:P43,P27:P31,P15:P19) -> 5.3375498 | ... T55: =MIN(T39:T43,T27:T31,T15:T19) -> -0.86142492 | V55: =MIN(V39:V43,V27:V31,V15:V19) -> 1.0614112 | W55: =MIN(W39:W43,W27:W31,W15:W19) -> 0.99627027 | X55: =MIN(X39:X43,X27:X31,X15:X19) -> 0.85305053 | Z55: =MIN(Z39:Z43,Z27:Z31,Z15:Z19) -> -0.6931

Sheet WACC
A7: x | B7: Rolling WACC | K7: Equity Risk Premium
P8: Weights
D9: 2025 | E9: =+D9+1 -> 2026 | F9: =+E9+1 -> 2027 | G9: =+F9+1 -> 2028 | H9: =+G9+1 -> 2029 | M9: ERP | N9: 2025 | O9: =+N9+1 -> 2026 | P9: =+O9+1 -> 2027 | Q9: =+P9+1 -> 2028 | R9: =+Q9+1 -> 2029
B12: Equity: | K12: =+Segments!B21 -> Mainland China | M12: 0.0527 | N12: =+Segments!AL21/Segments!AL$26 -> 0.98 | O12: =+Segments!AN21/Segments!AN$26 -> 0.98 | P12: =+Segments!AP21/Segments!AP$26 -> 0.98 | Q12: =+Segments!AR21/Segments!AR$26 -> 0.98 | R12: =+Segments!AT21/Segments!AT$26 -> 0.98
B13: Market Cap (in billions) | D13: =+Inputs!J13 -> 16770.325 | E13: =+FCFF!AF99*FCFF!AF31 -> 4543.7418 | F13: =+FCFF!AH99*FCFF!AH31 -> 4704.666 | G13: =+FCFF!AJ99*FCFF!AJ31 -> 5488.777 | H13: =+FCFF!AL99*FCFF!AL31 -> 6312.0936 | K13: Korea and United States | M13: =(0.0433+0.0499)/2 -> 0.0466 | N13: =+Segments!AL22/Segments!AL$26 -> 0.02 | O13: =+Segments!AN22/Segments!AN$26 -> 0.02 | P13: =+Segments!AP22/Segments!AP$26 -> 0.02 | Q13: =+Segments!AR22/Segments!AR$26 -> 0.02 | R13: =+Segments!AT22/Segments!AT$26 -> 0.02
B14: % of Equity | D14: =IFERROR(D13/D35,"") -> 0.98315289 | E14: =IFERROR(E13/E35,"") -> 0.94051621 | F14: =IFERROR(E13/F35,"") -> 0.91019758 | G14: =IFERROR(F13/G35,"") -> 0.81449858 | H14: =IFERROR(G13/H35,"") -> 0.8317001 | N14: =+Segments!AL23/Segments!AL$26 -> 0 | O14: =+Segments!AN23/Segments!AN$26 -> 0 | P14: =+Segments!AP23/Segments!AP$26 -> 0 | Q14: =+Segments!AR23/Segments!AR$26 -> 0 | R14: =+Segments!AT23/Segments!AT$26 -> 0
B15: Risk-Free Rate | D15: 0.0159 | E15: 0.0159 | F15: 0.0159 | G15: 0.0159 | H15: 0.0159
B16: Beta | D16: =+Inputs!M18 -> 1.42 | E16: =+D17*(1+(E28/E13)*(1-E32)) -> 1.4753542 | F16: =+E17*(1+(F28/F13)*(1-F32)) -> 1.4727797 | G16: =+F17*(1+(G28/G13)*(1-G32)) -> 1.462395 | H16: =+G17*(1+(H28/H13)*(1-H32)) -> 1.4542679
B17: Unlevered Beta | D17: =+D16/(1+(D28/D13)*(1-D32)) -> 1.400087 | E17: =+E16/(1+(E28/E13)*(1-E32)) -> 1.400087 | F17: =+F16/(1+(F28/F13)*(1-F32)) -> 1.400087 | G17: =+G16/(1+(G28/G13)*(1-G32)) -> 1.400087 | H17: =+H16/(1+(H28/H13)*(1-H32)) -> 1.400087
B18: Equity Risk Premium | D18: =+N18 -> 0.052578 | E18: =+O18 -> 0.052578 | F18: =+P18 -> 0.052578 | G18: =+Q18 -> 0.052578 | H18: =+R18 -> 0.052578 | K18: ERP | N18: =+SUMPRODUCT($M12:$M16,N12:N16) -> 0.052578 | O18: =+SUMPRODUCT($M12:$M16,O12:O16) -> 0.052578 | P18: =+SUMPRODUCT($M12:$M16,P12:P16) -> 0.052578 | Q18: =+SUMPRODUCT($M12:$M16,Q12:Q16) -> 0.052578 | R18: =+SUMPRODUCT($M12:$M16,R12:R16) -> 0.052578
B19: Ke (Cost of Equity) | D19: =IFERROR(+D15+D16*D18,"") -> 0.09056076 | E19: =IFERROR(+E15+E16*E18,"") -> 0.093471175 | F19: =IFERROR(+F15+F16*F18,"") -> 0.093335812 | G19: =IFERROR(+G15+G16*G18,"") -> 0.092789806 | H19: =IFERROR(+H15+H16*H18,"") -> 0.092362497
B21: Preferred Equity: | K21: ROIC vs WACC
B22: Market Capitalization | D22: =IFERROR(Inputs!J14,0) -> 0 | E22: =+D22*(E13/D13) -> 0 | F22: =+E22*(F13/E13) -> 0 | G22: =+F22*(G13/F13) -> 0 | H22: =+G22*(H13/G13) -> 0
B23: % of Preferred Equity | D23: =+D22/D35 -> 0 | E23: =+E22/E35 -> 0 | F23: =+F22/F35 -> 0 | G23: =+G22/G35 -> 0 | H23: =+H22/H35 -> 0
B24: Preferred Dividends | D24: =+IS!AF50 -> 0 | E24: =D24 -> 0 | F24: =E24 -> 0 | G24: =F24 -> 0 | H24: =G24 -> 0
B25: Kp (Cost of Preferred Equity) | D25: =IFERROR(D24/D22,0) -> 0 | E25: =IFERROR(E24/E22,0) -> 0 | F25: =IFERROR(F24/F22,0) -> 0 | G25: =IFERROR(G24/G22,0) -> 0 | H25: =IFERROR(H24/H22,0) -> 0
B27: Debt:
B28: Debt (in millions) | C28: =+BS!AF38+BS!AF39+BS!AF44+BS!AF45 -> 188.783 | D28: =+BS!AI38+BS!AI39+BS!AI44+BS!AI45 -> 287.373 | E28: 287.373 | F28: 287.373 | G28: 287.373 | H28: 287.373
B29: % of Debt | D29: =IFERROR(D28/D35,"") -> 0.016847115 | E29: =IFERROR(E28/E35,"") -> 0.059483786 | F29: =IFERROR(F28/F35,"") -> 0.057566257 | G29: =IFERROR(G28/G35,"") -> 0.049751651 | H29: =IFERROR(H28/H35,"") -> 0.043544883
B30: Debt Spread | D30: =+D31-D15 -> -0.0159 | E30: =E31-E15 -> 0.0111 | F30: =F31-F15 -> 0.0111 | G30: =G31-G15 -> 0.0111 | H30: =H31-H15 -> 0.0111
B31: Cost of Debt | D31: =+IS!AI39/WACC!D28 -> 0 | E31: 0.027 | F31: 0.027 | G31: 0.027 | H31: 0.027
B32: Tax Rate | D32: =+FCFF!Z124 -> 0.17 | E32: =+FCFF!AF124 -> 0.15 | F32: =+FCFF!AH124 -> 0.15 | G32: =+FCFF!AJ124 -> 0.15 | H32: =+FCFF!AL124 -> 0.15
B33: Kd (After-Tax Cost of Debt) | D33: =+D31*(1-D32) -> 0 | E33: =+E31*(1-E32) -> 0.02295 | F33: =+F31*(1-F32) -> 0.02295 | G33: =+G31*(1-G32) -> 0.02295 | H33: =+H31*(1-H32) -> 0.02295
B35: Total | D35: =+D13+D24+D28 -> 17057.698 | E35: =+E13+E24+E28 -> 4831.1148 | F35: =+F13+F24+F28 -> 4992.039 | G35: =+G13+G24+G28 -> 5776.15 | H35: =+H13+H24+H28 -> 6599.4666
B37: Country/Conglomerate/... Risk Premium
A39: x | B39: WACC | D39: =+D19*D14+D25*D23+D33*D29+D37 -> 0.089035072 | E39: =+E19*E14+E25*E23+E33*E29+E37 -> 0.089276309 | F39: =+F19*F14+F25*F23+F33*F29+F37 -> 0.086275175 | G39: =+G19*G14+G25*G23+G33*G29+G37 -> 0.076718966 | H39: =+H19*H14+H25*H23+H33*H29+H37 -> 0.077817253
B41: NOPAT | D41: =+FCFF!Z126 -> 139.29388 | E41: =+FCFF!AF126 -> 164.14267 | F41: =+FCFF!AH126 -> 194.2355 | G41: =+FCFF!AJ126 -> 226.60808 | H41: =+FCFF!AL126 -> 260.59929
B42: Total Payout | D42: =+FCFF!Z112+FCFF!Z115 -> 20.757556 | E42: =+FCFF!AF112+FCFF!AF115 -> 14.202622 | F42: =+FCFF!AH112+FCFF!AH115 -> 0.93317134 | G42: =+FCFF!AJ112+FCFF!AJ115 -> -3.487198 | H42: =+FCFF!AL112+FCFF!AL115 -> 2.096516
B43: Book Value of Equity | C43: =+BS!AF54 -> 1095.906 | D43: =+C43+D41+D42 -> 1255.9574 | E43: =+D43+E41+E42 -> 1434.3027 | F43: =+E43+F41+F42 -> 1629.4714 | G43: =+F43+G41+G42 -> 1852.5923 | H43: =+G43+H41+H42 -> 2115.2881
B44: Invested Capital | C44: =+C43+C28 -> 1284.689 | D44: =+D43+D28 -> 1543.3304 | E44: =+E43+E28 -> 1721.6757 | F44: =+F43+F28 -> 1916.8444 | G44: =+G43+G28 -> 2139.9653 | H44: =+H43+H28 -> 2402.6611
A45: x | B45: ROIC | D45: =+D41/((D44+C44)/2) -> 0.098509846 | E45: =+E41/((E44+D44)/2) -> 0.10054662 | F45: =+F41/((F44+E44)/2) -> 0.10676621 | G45: =+G41/((G44+F44)/2) -> 0.11171738 | H45: =+H41/((H44+G44)/2) -> 0.11473508
W49: ,

Sheet FCFF
A7: x | B7: Market Assumptions
D8: 2022 | J8: =D8+1 -> 2023 | P8: =J8+1 -> 2024 | V8: =P8+1 -> 2025 | AB8: =V8+1 -> 2026 | AH8: =AB8+1 -> 2027 | AJ8: =+AH8+1 -> 2028 | AL8: =+AJ8+1 -> 2029
D9: Q1 | E9: Q2 | F9: Q3 | G9: Q4 | H9: FY | J9: Q1 | K9: Q2 | L9: Q3 | M9: Q4 | N9: FY | P9: Q1 | Q9: Q2 | R9: Q3 | S9: Q4 | T9: FY | V9: Q1 | W9: Q2 | X9: Q3 | Y9: Q4 | Z9: FY | AB9: Q1 | AC9: Q2 | AD9: Q3 | AE9: Q4 | AF9: FY | AH9: FY | AJ9: FY | AL9: FY
B10: Single Wafer Cleaning,Tahoe and Semi- Critical Cleaning Equipment | D10: 26.033 | E10: 72.583 | F10: 99.72 | G10: 74.603 | H10: =Segments!T13 -> 272.939 | J10: 36.614 | K10: 112.528 | L10: 132.417 | M10: 122.292 | N10: =Segments!Z13 -> 403.851 | P10: 109.47 | Q10: 153.221 | R10: 160.985 | S10: 155.211 | T10: =Segments!AF13 -> 578.887 | V10: 129.569 | W10: 154.961 | Z10: =Z31*W13 -> 681.09169 | AF10: =AF$31*W13 -> 817.31002 | AH10: =AH$31*W13 -> 967.15019 | AJ10: =AJ$31*W13 -> 1128.3419 | AL10: =AL$31*W13 -> 1297.5932
B11: ECP, Furnace & Other Technologies | D11: 12.248 | E11: 20.5 | F11: 24.521 | G11: 20.213 | H11: =Segments!T14 -> 77.482 | J11: 26.598 | K11: 19.117 | L11: 25.508 | M11: 32.133 | N11: =Segments!Z14 -> 103.356 | P11: 25.8 | Q11: 38.962 | R11: 34.6 | S11: 51.695 | T11: =Segments!AF14 -> 151.057 | V11: 27.63 | W11: 48.016 | Z11: =Z$31*W14 -> 211.00001 | AF11: =AF$31*W14 -> 253.20001 | AH11: =AH$31*W14 -> 299.62002 | AJ11: =AJ$31*W14 -> 349.55668 | AL11: =AL$31*W14 -> 401.99019
B12: Advanced Packaging, Services & Spares | D12: 3.905 | E12: 11.312 | F12: 9.468 | G12: 13.726 | H12: =Segments!T15 -> 38.411 | J12: 11.044 | K12: 12.932 | L12: 10.644 | M12: 15.896 | N12: =Segments!Z15 -> 50.516 | P12: 16.921 | Q12: 10.297 | R12: 8.391 | S12: 16.565 | T12: =Segments!AF15 -> 52.174 | V12: 15.148 | W12: 12.395 | Z12: =Z$31*W15 -> 54.524902 | AF12: =AF$31*W15 -> 65.429882 | AH12: =AH$31*W15 -> 77.425361 | AJ12: =AJ$31*W15 -> 90.329587 | AL12: =AL$31*W15 -> 103.87903
W13: =W10/W31 -> 0.71950393
B14: Single Wafer Cleaning,Tahoe and Semi- Critical Cleaning Equipment % | W14: 0.2229
B15: ECP, Furnace & Other Technologies % | W15: 0.0576 | AS15: 2022 | AT15: =+AS15+1 -> 2023 | AU15: =+AT15+1 -> 2024 | AV15: =+AU15+1 -> 2025 | AW15: =+AV15+1 -> 2026 | AX15: =+AW15+1 -> 2027 | AY15: =+AX15+1 -> 2028 | AZ15: =+AY15+1 -> 2029
B16: Advanced Packaging, Services & Spares % | AR16: EBITDA | AS16: =H61+H128 -> 64.389 | AT16: =N61+N128 -> 103.929 | AU16: =T61+T128 -> 160.02 | AV16: =Z61+Z128 -> 165.56257 | AW16: =AF61+AF128 -> 206.44413 | AX16: =AH61+AH128 -> 241.01171 | AY16: =AJ61+AJ128 -> 279.74863 | AZ16: =AL61+AL128 -> 319.85059
AR17: FCFF | AS17: =H136 -> -171.72758 | AT17: =N136 -> -137.49706 | AU17: =T136 -> 16.513302 | AV17: =Z136 -> -112.51087 | AW17: =AF136 -> 99.49381 | AX17: =AH136 -> 142.71882 | AY17: =AJ136 -> 157.47185 | AZ17: =AL136 -> 194.58486
AR18: Revenue Growth | AS18: =H32 -> 0.4969413 | AT18: =N32 -> 0.43435468 | AU18: =T32 -> 0.40234131 | AV18: =Z32 -> 0.21031977 | AW18: =AF32 -> 0.2 | AX18: =AH32 -> 0.18333333 | AY18: =+AJ32 -> 0.16666667 | AZ18: =+AL32 -> 0.15
Z21: =SUM(Z10:Z12) -> 946.6166 | AF21: =SUM(AF10:AF12) -> 1135.9399 | AH21: =SUM(AH10:AH12) -> 1344.1956 | AJ21: =SUM(AJ10:AJ12) -> 1568.2282 | AL21: =SUM(AL10:AL12) -> 1803.4624
A23: x
D24: =D$8 -> 2022 | E24: =F24 -> 0 | F24: =F$8 -> 0 | G24: =F24 -> 0 | H24: =F24 -> 0 | J24: =J$8 -> 2023 | K24: =L24 -> 0 | L24: =L$8 -> 0 | M24: =L24 -> 0 | N24: =L24 -> 0 | P24: =P$8 -> 2024 | Q24: =R24 -> 0 | R24: =R$8 -> 0 | S24: =R24 -> 0 | T24: =R24 -> 0 | V24: =V$8 -> 2025 | W24: =X24 -> 0 | X24: =X$8 -> 0 | Y24: =X24 -> 0 | Z24: =X24 -> 0 | AB24: =AB$8 -> 2026 | AC24: =AD24 -> 0 | AD24: =AD$8 -> 0 | AE24: =AD24 -> 0 | AF24: =AD24 -> 0 | AH24: =AH$8 -> 2027 | AJ24: =AJ$8 -> 2028 | AL24: =AL$8 -> 2029
D25: Q1 | E25: Q2 | F25: Q3 | G25: Q4 | H25: FY | J25: Q1 | K25: Q2 | L25: Q3 | M25: Q4 | N25: FY | P25: Q1 | Q25: Q2 | R25: Q3 | S25: Q4 | T25: FY | V25: Q1 | W25: Q2 | X25: Q3 | Y25: Q4 | Z25: FY | AB25: Q1 | AC25: Q2 | AD25: Q3 | AE25: Q4 | AF25: FY | AH25: FY | AJ25: FY | AL25: FY
B28: Income Statement
B31: Revenue | D31: =IS!P18 -> 42.186 | E31: =IS!Q18 -> 104.395 | F31: =IS!R18 -> 133.709 | G31: =IS!S18 -> 108.542 | H31: =IS!T18 -> 388.832 | J31: =IS!V18 -> 74.256 | K31: =IS!W18 -> 144.577 | L31: =IS!X18 -> 168.569 | M31: =IS!Y18 -> 170.321 | N31: =IS!Z18 -> 557.723 | P31: =IS!AB18 -> 152.191 | Q31: =IS!AC18 -> 202.48 | R31: =IS!AD18 -> 203.976 | S31: =IS!AE18 -> 223.471 | T31: =IS!AF18 -> 782.118 | V31: =IS!AH18 -> 172.347 | W31: =IS!AI18 -> 215.372 | X31: =W31*(1+X32) -> 254.04267 | Y31: =X31*(1+Y32) -> 304.85121 | Z31: =SUM(V31:Y31) -> 946.61288 | AB31: =V31*(1+AB32) -> 206.8164 | AC31: =W31*(1+AC32) -> 258.4464 | AD31: =X31*(1+AD32) -> 304.85121 | AE31: =Y31*(1+AE32) -> 365.82145 | AF31: =SUM(AB31:AE31) -> 1135.9355 | AH31: =AF31*(1+AH32) -> 1344.1903 | AJ31: =AH31*(1+AJ32) -> 1568.222 | AL31: =AJ31*(1+AL32) -> 1803.4553
B32: % of growth | D32: =D31/IS!J18-1 -> -0.035351688 | E32: =E31/IS!K18-1 -> 0.93812194 | F32: =F31/IS!L18-1 -> 0.99526957 | G32: =G31/IS!M18-1 -> 0.14084211 | H32: =H31/IS!N18-1 -> 0.4969413 | J32: =J31/IS!P18-1 -> 0.76020481 | K32: =K31/IS!Q18-1 -> 0.38490349 | L32: =L31/IS!R18-1 -> 0.26071543 | M32: =M31/IS!S18-1 -> 0.56917138 | N32: =N31/H31-1 -> 0.43435468 | P32: =P31/IS!V18-1 -> 1.0495448 | Q32: =Q31/IS!W18-1 -> 0.40049939 | R32: =R31/IS!X18-1 -> 0.21004455 | S32: =S31/IS!Y18-1 -> 0.31205782 | T32: =T31/N31-1 -> 0.40234131 | V32: =V31/IS!AB18-1 -> 0.13243884 | W32: =W31/IS!AC18-1 -> 0.063670486 | X32: =AVERAGE(V32:W32,R32:S32) -> 0.17955293 | Y32: 0.2 | Z32: =Z31/T31-1 -> 0.21031977 | AB32: 0.2 | AC32: 0.2 | AD32: 0.2 | AE32: 0.2 | AF32: =AF31/Z31-1 -> 0.2 | AH32: =AF32-((0.2-0.15)/3) -> 0.18333333 | AJ32: =AH32-((0.2-0.15)/3) -> 0.16666667 | AL32: =AJ32-((0.2-0.15)/3) -> 0.15
B34: Cost of Goods & Services | D34: =IS!P21 -> 22.5 | E34: =IS!Q21 -> 60.238 | F34: =IS!R21 -> 67.742 | G34: =IS!S21 -> 54.737 | H34: =IS!T21 -> 205.217 | J34: =IS!V21 -> 34.27 | K34: =IS!W21 -> 75.938 | L34: =IS!X21 -> 80.055 | M34: =IS!Y21 -> 91.245 | N34: =IS!Z21 -> 281.508 | P34: =IS!AB21 -> 73.07 | Q34: =IS!AC21 -> 105.696 | R34: =IS!AD21 -> 99.142 | S34: =IS!AE21 -> 112.656 | T34: =IS!AF21 -> 390.564 | V34: =IS!AH21 -> 89.797 | W34: =IS!AI21 -> 110.911 | X34: =(X35+Sensitivity!$U$39)*X$31 -> 128.68309 | Y34: =(Y35+Sensitivity!$U$39)*Y$31 -> 155.98161 | Z34: =SUM(V34:Y34) -> 485.3727 | AB34: =(AB35+Sensitivity!$U$39)*AB$31 -> 106.2108 | AC34: =(AC35+Sensitivity!$U$39)*AC$31 -> 132.24258 | AD34: =(AD35+Sensitivity!$U$39)*AD$31 -> 155.73628 | AE34: =(AE35+Sensitivity!$U$39)*AE$31 -> 187.27851 | AF34: =SUM(AB34:AE34) -> 581.46816 | AH34: =(AH35+Sensitivity!$U$39)*AH$31 -> 653.66712 | AJ34: =(AJ35+Sensitivity!$U$39)*AJ$31 -> 724.48106 | AL34: =(AL35+Sensitivity!$U$39)*AL$31 -> 791.49556
B35: % of sales | D35: =D34/D31 -> 0.5333523 | E35: =E34/E31 -> 0.57701997 | F35: =F34/F31 -> 0.50663755 | G35: =G34/G31 -> 0.50429327 | H35: =H34/H31 -> 0.52777806 | J35: =J34/J31 -> 0.46151153 | K35: =K34/K31 -> 0.5252426 | L35: =L34/L31 -> 0.47490938 | M35: =M34/M31 -> 0.53572372 | N35: =N34/N31 -> 0.50474519 | P35: =P34/P31 -> 0.48012038 | Q35: =Q34/Q31 -> 0.52200711 | R35: =R34/R31 -> 0.48604738 | S35: =S34/S31 -> 0.5041191 | T35: =T34/T31 -> 0.4993671 | V35: =V34/V31 -> 0.52102444 | W35: =W34/W31 -> 0.51497409 | X35: =AVERAGE(V35:W35,R35:S35) -> 0.50654125 | Y35: =AVERAGE(V35:X35,S35) -> 0.51166472 | Z35: =Z34/Z31 -> 0.51274678 | AB35: =AVERAGE(V35:Y35) -> 0.51355113 | AC35: =AVERAGE(AB35,W35:Y35) -> 0.5116828 | AD35: =AVERAGE(AB35:AC35,X35:Y35) -> 0.51085998 | AE35: =AVERAGE(AB35:AD35,Y35) -> 0.51193966 | AF35: =AF34/AF31 -> 0.51188486 | AH35: =AF35*0.95 -> 0.48629062 | AJ35: =AH35*0.95 -> 0.46197609 | AL35: =AJ35*0.95 -> 0.43887728
AH36: 0
B37: COGS Depreciation & Amortization | D37: =IS!P22 -> 0 | E37: =IS!Q22 -> 0 | F37: =IS!R22 -> 0 | G37: =IS!S22 -> 0 | H37: =IS!T22 -> 0 | J37: =IS!V22 -> 0 | K37: =IS!W22 -> 0 | L37: =IS!X22 -> 0 | M37: =IS!Y22 -> 0 | N37: =IS!Z22 -> 0 | P37: =IS!AB22 -> 0 | Q37: =IS!AC22 -> 0 | R37: =IS!AD22 -> 0 | S37: =IS!AE22 -> 0 | T37: =IS!AF22 -> 0 | V37: =IS!AH22 -> 0 | W37: =IS!AI22 -> 0 | X37: =X38*X34 -> 0 | Y37: =Y38*Y34 -> 0 | Z37: =SUM(V37:Y37) -> 0 | AB37: =AB38*AB34 -> 0 | AC37: =AC38*AC34 -> 0 | AD37: =AD38*AD34 -> 0 | AE37: =AE38*AE34 -> 0 | AF37: =SUM(AB37:AE37) -> 0 | AH37: =AH38*AH34 -> 0 | AJ37: =AJ38*AJ34 -> 0 | AL37: =AL38*AL34 -> 0
B38: % of cost of goods & services | D38: =D37/D34 -> 0 | E38: =E37/E34 -> 0 | F38: =F37/F34 -> 0 | G38: =G37/G34 -> 0 | H38: =H37/H34 -> 0 | J38: =J37/J34 -> 0 | K38: =K37/K34 -> 0 | L38: =L37/L34 -> 0 | M38: =M37/M34 -> 0 | N38: =N37/N34 -> 0 | P38: =P37/P34 -> 0 | Q38: =Q37/Q34 -> 0 | R38: =R37/R34 -> 0 | S38: =S37/S34 -> 0 | T38: =T37/T34 -> 0 | V38: =V37/V34 -> 0 | W38: =W37/W34 -> 0
B40: Gross Profit | D40: =IS!P24 -> 19.686 | E40: =IS!Q24 -> 44.157 | F40: =IS!R24 -> 65.967 | G40: =IS!S24 -> 53.805 | H40: =IS!T24 -> 183.615 | J40: =IS!V24 -> 39.986 | K40: =IS!W24 -> 68.639 | L40: =IS!X24 -> 88.514 | M40: =IS!Y24 -> 79.076 | N40: =IS!Z24 -> 276.215 | P40: =IS!AB24 -> 79.121 | Q40: =IS!AC24 -> 96.784 | R40: =IS!AD24 -> 104.834 | S40: =IS!AE24 -> 110.815 | T40: =IS!AF24 -> 391.554 | V40: =IS!AH24 -> 82.55 | W40: =IS!AI24 -> 104.461 | X40: =X31-X34-X37 -> 125.35958 | Y40: =Y31-Y34-Y37 -> 148.8696 | Z40: =SUM(V40:Y40) -> 461.24018 | AB40: =AB31-AB34-AB37 -> 100.6056 | AC40: =AC31-AC34-AC37 -> 126.20382 | AD40: =AD31-AD34-AD37 -> 149.11493 | AE40: =AE31-AE34-AE37 -> 178.54294 | AF40: =SUM(AB40:AE40) -> 554.4673 | AH40: =AH31-AH34-AH37 -> 690.52317 | AJ40: =AJ31-AJ34-AJ37 -> 843.74094 | AL40: =AL31-AL34-AL37 -> 1011.9597
B41: % of sales | D41: =D40/D31 -> 0.4666477 | E41: =E40/E31 -> 0.42298003 | F41: =F40/F31 -> 0.49336245 | G41: =G40/G31 -> 0.49570673 | H41: =H40/H31 -> 0.47222194 | J41: =J40/J31 -> 0.53848847 | K41: =K40/K31 -> 0.4747574 | L41: =L40/L31 -> 0.52509062 | M41: =M40/M31 -> 0.46427628 | N41: =N40/N31 -> 0.49525481 | P41: =P40/P31 -> 0.51987962 | Q41: =Q40/Q31 -> 0.47799289 | R41: =R40/R31 -> 0.51395262 | S41: =S40/S31 -> 0.4958809 | T41: =T40/T31 -> 0.5006329 | V41: =V40/V31 -> 0.47897556 | W41: The | X41: =X40/X31 -> 0.49345875 | Y41: =Y40/Y31 -> 0.48833528 | Z41: =Z40/Z$31 -> 0.48725322 | AB41: =AB40/AB31 -> 0.48644887 | AC41: =AC40/AC31 -> 0.4883172 | AD41: =AD40/AD31 -> 0.48914002 | AE41: =AE40/AE31 -> 0.48806034 | AF41: =AF40/AF$31 -> 0.48811514 | AH41: =AH40/AH31 -> 0.51370938 | AJ41: =AJ40/AJ31 -> 0.53802391 | AL41: =AL40/AL31 -> 0.56112272
B43: SG&A (Selling, General & Administrative) | D43: =IS!P27 -> 11.646 | E43: =IS!Q27 -> 12.755 | F43: =IS!R27 -> 18.653 | G43: =IS!S27 -> 19.3 | H43: =IS!T27 -> 62.354 | J43: =IS!V27 -> 17.095 | K43: =IS!W27 -> 18.145 | L43: =IS!X27 -> 29.19 | M43: =IS!Y27 -> 23.237 | N43: =IS!Z27 -> 87.667 | P43: =IS!AB27 -> 29.971 | Q43: =IS!AC27 -> 33.223 | R43: =IS!AD27 -> 32.813 | S43: =IS!AE27 -> 39.076 | T43: =IS!AF27 -> 135.083 | V43: =IS!AH27 -> 29.27 | W43: =IS!AI27 -> 38.95 | X43: =(X44+Sensitivity!$U$40)*X$31 -> 43.594232 | Y43: =(Y44+Sensitivity!$U$40)*Y$31 -> 53.131225 | Z43: =SUM(V43:Y43) -> 164.94546 | AB43: =(AB44+Sensitivity!$U$40)*AB$31 -> 36.015496 | AC43: =(AC44+Sensitivity!$U$40)*AC$31 -> 45.006466 | AD43: =(AD44+Sensitivity!$U$40)*AD$31 -> 53.087508 | AE43: =(AE44+Sensitivity!$U$40)*AE$31 -> 63.718125 | AF43: =SUM(AB43:AE43) -> 197.8276 | AH43: =(AH44+Sensitivity!$U$40)*AH$31 -> 233.49316 | AJ43: =(AJ44+Sensitivity!$U$40)*AJ$31 -> 272.92677 | AL43: =(AL44+Sensitivity!$U$40)*AL$31 -> 313.73819
B44: % of sales | D44: =D43/D31 -> 0.27606315 | E44: =E43/E31 -> 0.12218018 | F44: =F43/F31 -> 0.13950445 | G44: =G43/G31 -> 0.17781135 | H44: =H43/H31 -> 0.16036232 | J44: =J43/J31 -> 0.23021709 | K44: =K43/K31 -> 0.12550406 | L44: =L43/L31 -> 0.17316351 | M44: =M43/M31 -> 0.13643062 | N44: =N43/N31 -> 0.15718735 | P44: =P43/P31 -> 0.19693017 | Q44: =Q43/Q31 -> 0.1640804 | R44: =R43/R31 -> 0.16086696 | S44: =S43/S31 -> 0.17485938 | T44: =T43/T31 -> 0.17271435 | V44: =V43/V31 -> 0.16983179 | W44: =W43/W31 -> 0.18084988 | X44: =AVERAGE(V44:W44,R44:S44) -> 0.171602 | Y44: =AVERAGE(V44:X44,S44) -> 0.17428576 | Z44: =Z43/Z31 -> 0.17424806 | AB44: =AVERAGE(V44:Y44) -> 0.17414236 | AC44: =AVERAGE(AB44) -> 0.17414236 | AD44: =AVERAGE(AB44) -> 0.17414236 | AE44: =AVERAGE(AB44:AD44,Y44) -> 0.17417821 | AF44: =AF43/AF31 -> 0.17415391 | AH44: =AVERAGE(AF44,Z44,T44) -> 0.17370544 | AJ44: =AVERAGE(AF44:AH44,Z44) -> 0.1740358 | AL44: =AVERAGE(AF44:AJ44) -> 0.17396505
B46: R&D (Research & Development) | D46: =IS!P29 -> 17.346 | E46: =IS!Q29 -> 11.367 | F46: =IS!R29 -> 15.678 | G46: =IS!S29 -> 17.835 | H46: =IS!T29 -> 62.226 | J46: =IS!V29 -> 14.029 | K46: =IS!W29 -> 20.064 | L46: =IS!X29 -> 26.151 | M46: =IS!Y29 -> 32.465 | N46: =IS!Z29 -> 92.709 | P46: =IS!AB29 -> 23.918 | Q46: =IS!AC29 -> 25.968 | R46: =IS!AD29 -> 27.837 | S46: =IS!AE29 -> 27.75 | T46: =IS!AF29 -> 105.473 | V46: =IS!AH29 -> 27.503 | W46: =IS!AI29 -> 33.817 | X46: =X47*X40 -> 42.611588 | Y46: =Y47*Y40 -> 53.133144 | Z46: =SUM(V46:Y46) -> 157.06473 | AB46: =AB47*AB40 -> 34.048 | AC46: =AC47*AC40 -> 42.877258 | AD46: =AD47*AD40 -> 51.258334 | AE46: =AE47*AE40 -> 61.545436 | AF46: =SUM(AB46:AE46) -> 189.72903 | AH46: =AH47*AH40 -> 219.14438 | AJ46: =AJ47*AJ40 -> 281.26652 | AL46: =AL47*AL40 -> 334.92459
B47: % of gross profit | D47: =D46/D40 -> 0.8811338 | E47: =E46/E40 -> 0.25742238 | F47: =F46/F40 -> 0.23766429 | G47: =G46/G40 -> 0.33147477 | H47: =H46/H40 -> 0.33889388 | J47: =J46/J40 -> 0.3508478 | K47: =K46/K40 -> 0.29231195 | L47: =L46/L40 -> 0.29544479 | M47: =M46/M40 -> 0.4105544 | N47: =N46/N40 -> 0.33564071 | P47: =P46/P40 -> 0.30229648 | Q47: =Q46/Q40 -> 0.26830881 | R47: =R46/R40 -> 0.26553408 | S47: =S46/S40 -> 0.25041736 | T47: =T46/T40 -> 0.26937025 | V47: =V46/V40 -> 0.33316778 | W47: =W46/W40 -> 0.32372847 | X47: =W47*1.05 -> 0.3399149 | Y47: =X47*1.05 -> 0.35691064 | Z47: =Z46/Z40 -> 0.340527 | AB47: =AVERAGE(V47:Y47) -> 0.33843045 | AC47: =AVERAGE(AB47,W47:Y47) -> 0.33974611 | AD47: =AVERAGE(AB47:AC47,X47:Y47) -> 0.34375052 | AE47: =AVERAGE(AB47:AD47,Y47) -> 0.34470943 | AF47: =AF46/AF40 -> 0.34218254 | AH47: =AVERAGE(AF47,Z47,T47) -> 0.31735993 | AJ47: =AVERAGE(AH47,AF47,Z47) -> 0.33335649 | AL47: =AVERAGE(AF47:AJ47) -> 0.33096632
B49: D&A (Depreciation & Amortization) | D49: =D94 -> 1.213 | E49: =E94 -> 1.342 | F49: =F94 -> 1.549 | G49: =G94 -> 1.262 | H49: =H94 -> 5.366 | J49: =J94 -> 1.714 | K49: =K94 -> 2.241 | L49: =L94 -> 2.066 | M49: =M94 -> 2.071 | N49: =N94 -> 8.092 | P49: =P94 -> 2.518 | Q49: =Q94 -> 2.166 | R49: =R94 -> 2.389 | S49: =S94 -> 2.894 | T49: =T94 -> 9.967 | V49: =V94 -> 3.017 | W49: =W94 -> 3.339 | X49: =X50*(X79+X82) -> 3.3570789 | Y49: =Y50*(Y79+Y82) -> 3.3665353 | Z49: =SUM(V49:Y49) -> 13.079614 | AB49: =AB50*(AB79+AB82) -> 3.2981235 | AC49: =AC50*(AC79+AC82) -> 3.3418524 | AD49: =AD50*(AD79+AD82) -> 3.349621 | AE49: =AE50*(AE79+AE82) -> 3.3455094 | AF49: =SUM(AB49:AE49) -> 13.335106 | AH49: =AH50*(AH79+AH82) -> 12.499356 | AJ49: =AJ50*(AJ79+AJ82) -> 13.150888 | AL49: =AL50*(AL79+AL82) -> 13.263186
B50: % of net pp&e and intangibles excl. Goodwill | D50: =D49/(D79+D82) -> 0.01681989 | E50: =E49/(E79+E82) -> 0.019036271 | F50: =F49/(F79+F82) -> 0.019723188 | G50: =G49/(G79+G82) -> 0.013240864 | H50: =H49/(H79+H82) -> 0.056273334 | J50: =J49/(J79+J82) -> 0.010244701 | K50: =K49/(K79+K82) -> 0.012645371 | L50: =L49/(L79+L82) -> 0.0099075424 | M50: =M49/(M79+M82) -> 0.0094231023 | N50: =N49/(N79+N82) -> 0.036741569 | P50: =P49/(P79+P82) -> 0.01064869 | Q50: =Q49/(Q79+Q82) -> 0.0088032319 | R50: =R49/(R79+R82) -> 0.0089288384 | S50: =S49/(S79+S82) -> 0.010108031 | T50: =T49/(T79+T82) -> 0.034751229 | V50: =V49/(V79+V82) -> 0.010130654 | W50: =W49/(W79+W82) -> 0.010733642 | X50: =W49/(W79+W82) -> 0.010733642 | Y50: =X49/(X79+X82) -> 0.010733642 | Z50: =Z49/( Z79+Z82) -> 0.041702192 | AB50: =AVERAGE(V50:Y50) -> 0.010582895 | AC50: =AVERAGE(AB50,W50:Y50) -> 0.010695956 | AD50: =AVERAGE(AB50:AC50,X50:Y50) -> 0.010686534 | AE50: =AVERAGE(AB50:AD50,Y50) -> 0.010674757 | AF50: =AF49/( AF79+AF82) -> 0.04254928 | AH50: =AVERAGE(AF50,Z50,T50) -> 0.039667567 | AJ50: =AVERAGE(AH50,AF50,Z50) -> 0.041306346 | AL50: =AVERAGE(AF50:AJ50) -> 0.041174398
B52: Depreciation | D52: =IS!P64 -> 0 | E52: =IS!Q64 -> 0 | F52: =IS!R64 -> 0 | G52: =IS!S64 -> 0 | H52: =IS!T64 -> 0 | J52: =IS!V64 -> 0 | K52: =IS!W64 -> 0 | L52: =IS!X64 -> 0 | M52: =IS!Y64 -> 0 | N52: =IS!Z64 -> 0 | P52: =IS!AB64 -> 0 | Q52: =IS!AC64 -> 0 | R52: =IS!AD64 -> 0 | S52: =IS!AE64 -> 0 | T52: =IS!AF64 -> 0 | V52: =IS!AH64 -> 0 | W52: =IS!AI64 -> 0 | X52: =X53*W79 -> 0 | Y52: =Y53*X79 -> 0 | Z52: =SUM(V52:Y52) -> 0 | AB52: =AB53*Y79 -> 0 | AC52: =AC53*AB79 -> 0 | AD52: =AD53*AC79 -> 0 | AE52: =AE53*AD79 -> 0 | AF52: =SUM(AB52:AE52) -> 0 | AH52: =AH53*AF79 -> 0 | AJ52: =AJ53*AH79 -> 0 | AL52: =AL53*AJ79 -> 0
B53: % of net pp&e | D53: =D52/D79 -> 0 | E53: =E52/E79 -> 0 | F53: =F52/F79 -> 0 | G53: =G52/G79 -> 0 | H53: =H52/H79 -> 0 | J53: =J52/J79 -> 0 | K53: =K52/K79 -> 0 | L53: =L52/L79 -> 0 | M53: =M52/M79 -> 0 | N53: =N52/N79 -> 0 | P53: =P52/P79 -> 0 | Q53: =Q52/Q79 -> 0 | R53: =R52/R79 -> 0 | S53: =S52/S79 -> 0 | T53: =T52/T79 -> 0 | V53: =V52/V79 -> 0 | W53: =W52/W79 -> 0
B55: Amortization | D55: =IS!P65 -> 0 | E55: =IS!Q65 -> 0 | F55: =IS!R65 -> 0 | G55: =IS!S65 -> 0 | H55: =IS!T65 -> 0 | J55: =IS!V65 -> 0 | K55: =IS!W65 -> 0 | L55: =IS!X65 -> 0 | M55: =IS!Y65 -> 0 | N55: =IS!Z65 -> 0 | P55: =IS!AB65 -> 0 | Q55: =IS!AC65 -> 0 | R55: =IS!AD65 -> 0 | S55: =IS!AE65 -> 0 | T55: =IS!AF65 -> 0 | V55: =IS!AH65 -> 0 | W55: =IS!AI65 -> 0 | X55: =X56*W82 -> 0 | Y55: =Y56*X82 -> 0 | Z55: =SUM(V55:Y55) -> 0 | AB55: =AB56*Y82 -> 0 | AC55: =AC56*AB82 -> 0 | AD55: =AD56*AC82 -> 0 | AE55: =AE56*AD82 -> 0 | AF55: =SUM(AB55:AE55) -> 0 | AH55: =AH56*AF82 -> 0 | AJ55: =AJ56*AH82 -> 0 | AL55: =AL56*AJ82 -> 0
B56: % of intangibles excl. goodwill | D56: =D55/D82 -> 0 | E56: =E55/E82 -> 0 | F56: =F55/F82 -> 0 | G56: =G55/G82 -> 0 | H56: =H55/H82 -> 0 | J56: =J55/J82 -> 0 | K56: =K55/K82 -> 0 | L56: =L55/L82 -> 0 | M56: =M55/M82 -> 0 | N56: =N55/N82 -> 0 | P56: =P55/P82 -> 0 | Q56: =Q55/Q82 -> 0 | R56: =R55/R82 -> 0 | S56: =S55/S82 -> 0 | T56: =T55/T82 -> 0 | V56: =V55/V82 -> 0 | W56: =W55/W82 -> 0
B58: Other Operating (Income) Expenses | D58: =IS!P30+IS!P32 -> -10.854 | E58: =IS!Q30+IS!Q32 -> -47.483 | F58: =IS!R30+IS!R32 -> -49.089 | G58: =IS!S30+IS!S32 -> -35.437 | H58: =IS!T30+IS!T32 -> 0.012 | J58: =IS!V30+IS!V32 -> -17.175 | K58: =IS!W30+IS!W32 -> -57.793 | L58: =IS!X30+IS!X32 -> -50.865 | M58: =IS!Y30+IS!Y32 -> -68.008 | N58: =IS!Z30+IS!Z32 -> 0.002 | P58: =IS!AB30+IS!AB32 -> -43.099 | Q58: =IS!AC30+IS!AC32 -> -72.473 | R58: =IS!AD30+IS!AD32 -> -66.329 | S58: =IS!AE30+IS!AE32 -> -73.58 | T58: =IS!AF30+IS!AF32 -> 0.945 | V58: =IS!AH30+IS!AH32 -> -60.527 | W58: =IS!AI30+IS!AI32 -> -71.961 | X58: =X59*X$31 -> -85.088862 | Y58: =Y59*Y$31 -> -102.85038 | Z58: =SUM(V58:Y58) -> -320.42725 | AB58: =AB59*AB$31 -> -70.1953 | AC58: =AC59*AC$31 -> -86.957599 | AD58: =AD59*AD$31 -> -102.74932 | AE58: =AE59*AE$31 -> -123.49199 | AF58: =SUM(AB58:AE58) -> -383.39421 | AH58: =AH59*AH$31 -> -302.35524 | AJ58: =AJ59*AJ$31 -> -470.96197 | AL58: =AL59*AL$31 -> -518.65259
B59: % of sales | D59: =D58/D31 -> -0.25728915 | E59: =E58/E31 -> -0.45483979 | F59: =F58/F31 -> -0.3671331 | G59: =G58/G31 -> -0.32648191 | H59: =H58/H31 -> 3.0861657e-05 | J59: =J58/J31 -> -0.23129444 | K59: =K58/K31 -> -0.39973855 | L59: =L58/L31 -> -0.30174587 | M59: =M58/M31 -> -0.3992931 | N59: =N58/N31 -> 3.5860095e-06 | P59: =P58/P31 -> -0.2831902 | Q59: =Q58/Q31 -> -0.35792671 | R59: =R58/R31 -> -0.32518041 | S59: =S58/S31 -> -0.32925972 | T59: =T58/T31 -> 0.0012082576 | V59: =V58/V31 -> -0.35119265 | W59: =W58/W31 -> -0.33412421 | X59: =AVERAGE(V59:W59,R59:S59) -> -0.33493925 | Y59: =AVERAGE(V59:X59,S59) -> -0.33737896 | Z59: =Z58/Z31 -> -0.33849872 | AB59: =AVERAGE(V59:Y59) -> -0.33940877 | AC59: =AVERAGE(AB59,W59:Y59) -> -0.3364628 | AD59: =AVERAGE(AB59:AC59,X59:Y59) -> -0.33704744 | AE59: =AVERAGE(AB59:AD59,Y59) -> -0.33757449 | AF59: =AF58/AF31 -> -0.33751408 | AH59: =AVERAGE(AF59,Z59,T59) -> -0.22493485 | AJ59: =AVERAGE(AF59:AH59,Z59) -> -0.30031588 | AL59: =AVERAGE(AF59:AJ59) -> -0.28758827
B61: EBIT (Operating Income) | D61: =IS!P33 -> -9.306 | E61: =IS!Q33 -> 20.035 | F61: =IS!R33 -> 31.636 | G61: =IS!S33 -> 16.67 | H61: =IS!T33 -> 59.023 | J61: =IS!V33 -> 8.862 | K61: =IS!W33 -> 30.43 | L61: =IS!X33 -> 33.173 | M61: =IS!Y33 -> 23.374 | N61: =IS!Z33 -> 95.837 | P61: =IS!AB33 -> 25.232 | Q61: =IS!AC33 -> 37.593 | R61: =IS!AD33 -> 44.184 | S61: =IS!AE33 -> 43.989 | T61: =IS!AF33 -> 150.053 | V61: =IS!AH33 -> 25.777 | W61: =IS!AI33 -> 31.694 | X61: =X62*X31 -> 43.187254 | Y61: =Y62*Y31 -> 51.824705 | Z61: =SUM(V61:Y61) -> 152.48296 | AB61: =AB62*AB31 -> 35.158788 | AC61: =AC62*AC31 -> 43.935888 | AD61: =AD62*AD31 -> 51.824705 | AE61: =AE62*AE31 -> 62.189646 | AF61: =SUM(AB61:AE61) -> 193.10903 | AH61: =AH62*AH31 -> 228.51235 | AJ61: =AJ62*AJ31 -> 266.59774 | AL61: =AL62*AL31 -> 306.5874
B62: % of sales | D62: =D61/D31 -> -0.22059451 | E62: =E61/E31 -> 0.19191532 | F62: =F61/F31 -> 0.23660337 | G62: =G61/G31 -> 0.1535811 | H62: =H61/H31 -> 0.15179563 | J62: =J61/J31 -> 0.11934389 | K62: =K61/K31 -> 0.21047608 | L62: =L61/L31 -> 0.19679182 | M62: =M61/M31 -> 0.13723499 | N62: =N61/N31 -> 0.1718362 | P62: =P61/P31 -> 0.16579167 | Q62: =Q61/Q31 -> 0.18566278 | R62: =R61/R31 -> 0.21661372 | S62: =S61/S31 -> 0.19684433 | T62: =T61/T31 -> 0.19185468 | V62: =V61/V31 -> 0.14956454 | W62: =W61/W31 -> 0.14715933 | X62: 0.17 | Y62: 0.17 | Z62: =Z61/Z31 -> 0.1610827 | AA62: 0.15 | AB62: 0.17 | AC62: 0.17 | AD62: 0.17 | AE62: 0.17 | AF62: =AF61/AF31 -> 0.17 | AG62: 0.15 | AH62: 0.17 | AI62: 0.15 | AJ62: 0.17 | AK62: 0.15 | AL62: 0.17
B64: Basic Weighted Average Shares | D64: =IS!P59 -> 58.8274 | E64: =IS!Q59 -> 59.1776 | F64: =IS!R59 -> 59.3608 | G64: =IS!S59 -> 59.2686 | H64: =IS!T59 -> 59.236 | J64: =IS!V59 -> 59.7368 | K64: =IS!W59 -> 59.8981 | L64: =IS!X59 -> 60.2192 | M64: =IS!Y59 -> 60.7923 | N64: =IS!Z59 -> 60.1647 | P64: =IS!AB59 -> 61.3672 | Q64: =IS!AC59 -> 62.1784 | R64: =IS!AD59 -> 62.5009 | S64: =IS!AE59 -> 62.7943 | T64: =IS!AF59 -> 62.2126 | V64: =IS!AH59 -> 63.2678 | W64: =IS!AI59 -> 63.9688 | X64: =W64+X101 -> 64.235816 | Y64: =X64+Y101 -> 64.52504 | Z64: =AVERAGE(V64:Y64) -> 63.999364 | AB64: =Y64+AB101 -> 64.697287 | AC64: =AB64+AC101 -> 64.89612 | AD64: =AC64+AD101 -> 65.126045 | AE64: =AD64+AE101 -> 65.386684 | AF64: =AVERAGE(AB64:AE64) -> 65.026534 | AH64: =AE64+AH101 -> 66.40378 | AJ64: =AF64+AJ101 -> 66.002439 | AL64: =AH64+AL101 -> 67.381951
B65: Diluted Weighted Average Shares | D65: =IS!P60 -> 65.9509 | E65: =IS!Q60 -> 65.4787 | F65: =IS!R60 -> 65.6127 | G65: =IS!S60 -> 64.1983 | H65: =IS!T60 -> 65.3418 | J65: =IS!V60 -> 65.0588 | K65: =IS!W60 -> 64.9296 | L65: =IS!X60 -> 65.4509 | M65: =IS!Y60 -> 65.9119 | N65: =IS!Z60 -> 64.8705 | P65: =IS!AB60 -> 66.2423 | Q65: =IS!AC60 -> 67.0578 | R65: =IS!AD60 -> 66.6715 | S65: =IS!AE60 -> 66.5187 | T65: =IS!AF60 -> 66.2374 | V65: =IS!AH60 -> 66.9528 | W65: =IS!AI60 -> 67.4649 | X65: =W65 -> 67.4649 | Y65: =X65 -> 67.4649 | Z65: =AVERAGE(V65:Y65) -> 67.336875 | AB65: =Y65 -> 67.4649 | AC65: =AB65 -> 67.4649 | AD65: =AC65 -> 67.4649 | AE65: =AD65 -> 67.4649 | AF65: =AVERAGE(AB65:AE65) -> 67.4649 | AH65: =AF65 -> 67.4649 | AJ65: =AH65 -> 67.4649 | AL65: =AJ65 -> 67.4649
B67: Balance Sheet | D67: Q1 22 | E67: Q2 22 | F67: Q3 22 | G67: Q4 22 | H67: FY 22 | J67: Q1 23 | K67: Q2 23 | L67: Q3 23 | M67: Q4 23 | N67: FY 23 | P67: Q1 24 | Q67: Q2 24 | R67: Q3 24 | S67: Q4 24 | T67: FY 24 | V67: Q1 25 | W67: Q2 25 | X67: Q3 25 | Y67: Q4 25 | Z67: FY 25 | AB67: Q1 26 | AC67: Q2 26 | AD67: Q3 26 | AE67: Q4 26 | AF67: FY 26 | AH67: FY 27 | AJ67: FY 28 | AL67: FY 29
B70: Accounts Receivable | D70: =BS!P18 -> 106.351 | E70: =BS!Q18 -> 154.627 | F70: =BS!R18 -> 188.341 | G70: =BS!S18 -> 182.936 | H70: =BS!T18 -> 182.936 | J70: =BS!V18 -> 186.13 | K70: =BS!W18 -> 200.745 | L70: =BS!X18 -> 248.477 | M70: =BS!Y18 -> 283.186 | N70: =BS!Z18 -> 283.186 | P70: =BS!AB18 -> 296.371 | Q70: =BS!AC18 -> 293.499 | R70: =BS!AD18 -> 370.589 | S70: =BS!AE18 -> 387.045 | T70: =BS!AF18 -> 387.045 | V70: =BS!AH18 -> 387.849 | W70: =BS!AI18 -> 433.662 | X70: =X31*X71/92 -> 491.69532 | Y70: =Y31*Y71/92 -> 599.07755 | Z70: =Y70 -> 599.07755 | AB70: =AB31*AB71/90 -> 427.78052 | AC70: =AC31*AC71/91 -> 517.06859 | AD70: =AD31*AD71/92 -> 602.31023 | AE70: =AE31*AE71/92 -> 726.45503 | AF70: =AE70 -> 726.45503 | AH70: =AH31*AH71/365 -> 791.84168 | AJ70: =AJ31*AJ71/366 -> 970.40756 | AL70: =AL31*AL71/365 -> 1111.5873
B71: days sales outstanding | D71: =D70/D31*90 -> 226.8902 | E71: =E70/E31*91 -> 134.78669 | F71: =F70/F31*92 -> 129.59017 | G71: =G70/G31*92 -> 155.05622 | H71: =H70/H31*365 -> 171.72362 | J71: =J70/J31*90 -> 225.59389 | K71: =K70/K31*91 -> 126.3534 | L71: =L70/L31*92 -> 135.61144 | M71: =M70/M31*92 -> 152.96477 | N71: =N70/N31*365 -> 185.33015 | P71: =P70/P31*90 -> 175.2626 | Q71: =Q70/Q31*91 -> 131.90641 | R71: =R70/R31*92 -> 167.14804 | S71: =S70/S31*92 -> 159.34121 | T71: =T70/T31*365 -> 180.62674 | V71: =V70/V31*90 -> 202.53564 | W71: =W70/W31*91 -> 183.23293 | X71: =AVERAGE(V71:W71,R71:S71) -> 178.06445 | Y71: =AVERAGE(V71:X71,S71) -> 180.79356 | Z71: =Z70/Z31*365 -> 230.99549 | AB71: =AVERAGE(V71:Y71) -> 186.15665 | AC71: =AVERAGE(AB71,W71:Y71) -> 182.0619 | AD71: =AVERAGE(AB71:AC71,X71:Y71) -> 181.76914 | AE71: =AVERAGE(AB71:AD71,Y71) -> 182.69531 | AF71: =AF70/AF31*365 -> 233.42531 | AH71: =AVERAGE(AF71,Z71,T71) -> 215.01585 | AJ71: =AVERAGE(AF71,AH71,Z71) -> 226.47888 | AL71: =AVERAGE(AH71,AJ71,AF71) -> 224.97335
B73: Inventory | D73: =BS!P19 -> 271.538 | E73: =BS!Q19 -> 288.08 | F73: =BS!R19 -> 327.792 | G73: =BS!S19 -> 393.172 | H73: =BS!T19 -> 393.172 | J73: =BS!V19 -> 473.299 | K73: =BS!W19 -> 471.094 | L73: =BS!X19 -> 507.431 | M73: =BS!Y19 -> 545.395 | N73: =BS!Z19 -> 545.395 | P73: =BS!AB19 -> 581.14 | Q73: =BS!AC19 -> 602.927 | R73: =BS!AD19 -> 628.72 | S73: =BS!AE19 -> 597.984 | T73: =BS!AF19 -> 597.984 | V73: =BS!AH19 -> 609.567 | W73: =BS!AI19 -> 648.278 | X73: =X74*X34/92 -> 774.41057 | Y73: =Y74*Y34/92 -> 926.07147 | Z73: =Y73 -> 926.07147 | AB73: =AB74*AB34/92 -> 647.28111 | AC73: =AC74*AC34/92 -> 787.86241 | AD73: =AD74*AD34/92 -> 934.69157 | AE73: =AE74*AE34/92 -> 1123.2415 | AF73: =AE73 -> 1123.2415 | AH73: =AH74*AH34/365 -> 1170.2322 | AJ73: =AJ74*AJ34/366 -> 1355.8827 | AL73: =AL74*AL34/365 -> 1477.0997
B74: days inventory held | D74: =D73/D34*90 -> 1086.152 | E74: =E73/E34*91 -> 435.19506 | F74: =F73/F34*92 -> 445.17233 | G74: =G73/G34*92 -> 660.82949 | H74: =H73/H34*365 -> 699.29772 | J74: =J73/J34*90 -> 1242.9796 | K74: =K73/K34*91 -> 564.53362 | L74: =L73/L34*92 -> 583.14474 | M74: =M73/M34*92 -> 549.90783 | N74: =N73/N34*365 -> 707.15282 | P74: =P73/P34*90 -> 715.7876 | Q74: =Q73/Q34*91 -> 519.09587 | R74: =R73/R34*92 -> 583.42821 | S74: =S73/S34*92 -> 488.34086 | T74: =T73/T34*365 -> 558.84352 | V74: =V73/V34*90 -> 610.94502 | W74: =W73/W34*91 -> 531.89763 | X74: =AVERAGE(V74:W74,R74:S74) -> 553.65293 | Y74: =AVERAGE(V74:X74,S74) -> 546.20911 | Z74: =Z73/Z34*365 -> 696.40523 | AB74: =AVERAGE(V74:Y74) -> 560.67617 | AC74: =AVERAGE(AB74,W74:Y74) -> 548.10896 | AD74: =AVERAGE(AB74:AC74,X74:Y74) -> 552.16179 | AE74: =AVERAGE(AB74:AD74,Y74) -> 551.78901 | AF74: =AF73/AF34*365 -> 705.08274 | AH74: =AVERAGE(AF74,Z74,T74) -> 653.44383 | AJ74: =AVERAGE(AF74,AH74,Z74) -> 684.97727 | AL74: =AVERAGE(AH74,AJ74,AF74) -> 681.16794
B76: Prepaid expenses and Other Current Assets | D76: =BS!P20 -> 21.771 | E76: =BS!Q20 -> 18.851 | F76: =BS!R20 -> 17.771 | G76: =BS!S20 -> 15.607 | H76: =BS!T20 -> 15.607 | J76: =BS!V20 -> 19.319 | K76: =BS!W20 -> 18.97 | L76: =BS!X20 -> 17.54 | M76: =BS!Y20 -> 20.023 | N76: =BS!Z20 -> 20.023 | P76: =BS!AB20 -> 20.066 | Q76: =BS!AC20 -> 18.594 | R76: =BS!AD20 -> 10.794 | S76: =BS!AE20 -> 7.507 | T76: =BS!AF20 -> 7.507 | V76: =BS!AH20 -> 10.677 | W76: =BS!AI20 -> 14.303 | X76: =X77*X$31 -> 13.646664 | Y76: =Y77*Y$31 -> 16.436967 | Z76: =Y76 -> 16.436967 | AB76: =AB77*AB$31 -> 12.202027 | AC76: =AC77*AC$31 -> 15.057474 | AD76: =AD77*AD$31 -> 17.140016 | AE76: =AE77*AE$31 -> 20.797225 | AF76: =AE76 -> 20.797225 | AH76: =AH77*AH$31 -> 20.28416 | AJ76: =AJ77*AJ$31 -> 26.535718 | AL76: =AL77*AL$31 -> 30.249714
B77: % of sales | D77: =D76/D31 -> 0.51607168 | E77: =E76/E31 -> 0.18057378 | F77: =F76/F31 -> 0.13290803 | G77: =G76/G31 -> 0.14378766 | H77: =H76/H31 -> 0.040138157 | J77: =J76/J31 -> 0.26016753 | K77: =K76/K31 -> 0.13121036 | L77: =L76/L31 -> 0.10405235 | M77: =M76/M31 -> 0.11756037 | N77: =N76/N31 -> 0.035901335 | P77: =P76/P31 -> 0.13184748 | Q77: =Q76/Q31 -> 0.091831292 | R77: =R76/R31 -> 0.05291799 | S77: =S76/S31 -> 0.033592726 | T77: =T76/T31 -> 0.0095982959 | V77: =V76/V31 -> 0.0619506 | W77: =W76/W31 -> 0.066410675 | X77: =AVERAGE(V77:W77,R77:S77) -> 0.053717998 | Y77: =AVERAGE(V77:X77,S77) -> 0.053918 | Z77: =Z76/Z31 -> 0.01736398 | AB77: =AVERAGE(V77:Y77) -> 0.058999318 | AC77: =AVERAGE(AB77,W77:Y77) -> 0.058261498 | AD77: =AVERAGE(AB77:AC77,X77:Y77) -> 0.056224203 | AE77: =AVERAGE(AB77:AD77,Y77) -> 0.056850755 | AF77: =AF76/AF31 -> 0.018308457 | AH77: =AVERAGE(AF77,Z77,T77) -> 0.015090244 | AJ77: =AVERAGE(AF77,AH77,Z77) -> 0.016920894 | AL77: =AVERAGE(AH77,AJ77,AF77) -> 0.016773198
B79: Net PP&E (Property, Plant and Equipment) | D79: =BS!P24 -> 71.369 | E79: =BS!Q24 -> 69.836 | F79: =BS!R24 -> 77.664 | G79: =BS!S24 -> 94.056 | H79: =BS!T24 -> 94.056 | J79: =BS!V24 -> 166.073 | K79: =BS!W24 -> 175.112 | L79: =BS!X24 -> 206.365 | M79: =BS!Y24 -> 217.241 | N79: =BS!Z24 -> 217.241 | P79: =BS!AB24 -> 233.625 | Q79: =BS!AC24 -> 243.208 | R79: =BS!AD24 -> 264.099 | S79: =BS!AE24 -> 283.31 | T79: =BS!AF24 -> 283.31 | V79: =BS!AH24 -> 294.812 | W79: =BS!AI24 -> 308.229 | X79: =W79-X80*X106-X109-X52-X37 -> 308.229 | Y79: =X79-Y80*Y106-Y109-Y52-Y37 -> 308.229 | Z79: =Y79 -> 308.229 | AB79: =Y79-AB80*AB106-AB109-AB52-AB37 -> 308.229 | AC79: =AB79-AC80*AC106-AC109-AC52-AC37 -> 308.229 | AD79: =AC79-AD80*AD106-AD109-AD52-AD37 -> 308.229 | AE79: =AD79-AE80*AE106-AE109-AE52-AE37 -> 308.229 | AF79: =AE79 -> 308.229 | AH79: =AF79-AH80*AH106-AH109-AH52-AH37 -> 308.229 | AJ79: =AH79-AJ80*AJ106-AJ109-AJ52-AJ37 -> 308.229 | AL79: =AJ79-AL80*AL106-AL109-AL52-AL37 -> 308.229
B80: capex allocation rate
B82: Intangibles | D82: =IF($B$82="Intangibles excl. Goodwill",BS!P29,BS!P27) -> 0.748 | E82: =IF($B$82="Intangibles excl. Goodwill",BS!Q29,BS!Q27) -> 0.661 | F82: =IF($B$82="Intangibles excl. Goodwill",BS!R29,BS!R27) -> 0.873 | G82: =IF($B$82="Intangibles excl. Goodwill",BS!S29,BS!S27) -> 1.255 | H82: =IF($B$82="Intangibles excl. Goodwill",BS!T29,BS!T27) -> 1.3 | J82: =IF($B$82="Intangibles excl. Goodwill",BS!V29,BS!V27) -> 1.233 | K82: =IF($B$82="Intangibles excl. Goodwill",BS!W29,BS!W27) -> 2.107 | L82: =IF($B$82="Intangibles excl. Goodwill",BS!X29,BS!X27) -> 2.163 | M82: =IF($B$82="Intangibles excl. Goodwill",BS!Y29,BS!Y27) -> 2.538 | N82: =IF($B$82="Intangibles excl. Goodwill",BS!Z29,BS!Z27) -> 3 | P82: =IF($B$82="Intangibles excl. Goodwill",BS!AB29,BS!AB27) -> 2.836 | Q82: =IF($B$82="Intangibles excl. Goodwill",BS!AC29,BS!AC27) -> 2.838 | R82: =IF($B$82="Intangibles excl. Goodwill",BS!AD29,BS!AD27) -> 3.461 | S82: =IF($B$82="Intangibles excl. Goodwill",BS!AE29,BS!AE27) -> 2.997 | T82: =IF($B$82="Intangibles excl. Goodwill",BS!AF29,BS!AF27) -> 3.5 | V82: =IF($B$82="Intangibles excl. Goodwill",BS!AH29,BS!AH27) -> 2.997 | W82: =IF($B$82="Intangibles excl. Goodwill",BS!AI29,BS!AI27) -> 2.849 | X82: =X83*X46 -> 4.5333236 | Y82: =Y83*Y46 -> 5.4143285 | Z82: =Y82 -> 5.4143285 | AB82: =AB83*AB46 -> 3.417617 | AC82: =AC83*AC46 -> 4.2117502 | AD82: =AD83*AD46 -> 5.2141613 | AE82: =AE83*AE46 -> 5.1748074 | AF82: =AE82 -> 5.1748074 | AH82: =AH83*AH46 -> 6.8736687 | AJ82: =AJ83*AJ46 -> 10.145516 | AL82: =AL83*AL46 -> 13.893158
B83: r&d capitalization rate | D83: =D82/D46 -> 0.043122334 | E83: =E82/E46 -> 0.058150787 | F83: =F82/F46 -> 0.055683123 | G83: =G82/G46 -> 0.070367255 | H83: =H82/H46 -> 0.020891589 | I83: =I82/I46 -> #DIV/0! | J83: =J82/J46 -> 0.087889372 | K83: =K82/K46 -> 0.10501396 | ... T83: =T82/T46 -> 0.033183848 | V83: =V82/V46 -> 0.10896993 | W83: =W82/W46 -> 0.084247568 | X83: =AVERAGE(V83:W83,R83:S83) -> 0.10638711 | Y83: =AVERAGE(V83:X83,S83) -> 0.10190115 | Z83: =Z82/Z46 -> 0.034471956 | AB83: =AVERAGE(V83:Y83) -> 0.10037644 | AC83: =AVERAGE(AB83,W83:Y83) -> 0.098228066 | AD83: =AVERAGE(AB83:AC83,X83:Y83) -> 0.10172319 | AE83: =AVERAGE(AC83:AD83,Y83:Z83) -> 0.084081091 | AF83: =AF82/AF46 -> 0.027274727 | AH83: =AF83*1.15 -> 0.031365936 | AJ83: =AH83*1.15 -> 0.036070826 | AL83: =AJ83*1.15 -> 0.04148145
B85: Accounts Payable | D85: =BS!P37 -> 145.597 | E85: =BS!Q37 -> 144.191 | F85: =BS!R37 -> 147.759 | G85: =BS!S37 -> 171.873 | H85: =BS!T37 -> 171.873 | J85: =BS!V37 -> 196.457 | K85: =BS!W37 -> 189.061 | L85: =BS!X37 -> 235.82 | M85: =BS!Y37 -> 262.573 | N85: =BS!Z37 -> 262.573 | P85: =BS!AB37 -> 270.243 | Q85: =BS!AC37 -> 286.506 | R85: =BS!AD37 -> 308.386 | S85: =BS!AE37 -> 289.863 | T85: =BS!AF37 -> 289.863 | V85: =BS!AH37 -> 260.708 | W85: =BS!AI37 -> 295.647 | X85: =X86*X34/92 -> 359.03803 | Y85: =Y86*Y34/92 -> 422.70725 | Z85: =Y85 -> 422.70725 | AB85: =AB86*AB34/90 -> 297.94374 | AC85: =AC86*AC34/91 -> 363.68445 | AD85: =AD86*AD34/92 -> 426.8943 | AE85: =AE86*AE34/92 -> 511.06359 | AF85: =AE85 -> 511.06359 | AH85: =AH86*AH34/365 -> 529.82481 | AJ85: =AJ86*AJ34/366 -> 616.61987 | AL85: =AL86*AL34/365 -> 670.90138
B86: days payable outstanding | D86: =D85/D34*90 -> 582.388 | E86: =E85/E34*91 -> 217.82564 | F86: =F85/F34*92 -> 200.6706 | G86: =G85/G34*92 -> 288.87802 | H86: =H85/H34*365 -> 305.69419 | J86: =J85/J34*90 -> 515.9361 | K86: =K85/K34*91 -> 226.5605 | L86: =L85/L34*92 -> 271.00668 | M86: =M85/M34*92 -> 264.74564 | N86: =N85/N34*365 -> 340.4491 | P86: =P85/P34*90 -> 332.85712 | Q86: =Q85/Q34*91 -> 246.67013 | R86: =R85/R34*92 -> 286.17046 | S86: =S85/S34*92 -> 236.71527 | T86: =T85/T34*365 -> 270.89029 | V86: =V85/V34*90 -> 261.29737 | W86: =W85/W34*91 -> 242.57176 | X86: =AVERAGE(V86:W86,R86:S86) -> 256.68872 | Y86: =AVERAGE(V86:X86,S86) -> 249.31828 | Z86: =Z85/Z34*365 -> 317.87561 | AB86: =AVERAGE(V86:Y86) -> 252.46903 | AC86: =AVERAGE(AB86,W86:Y86) -> 250.26195 | AD86: =AVERAGE(AB86:AC86,X86:Y86) -> 252.1845 | AE86: =AVERAGE(AB86:AD86,Y86) -> 251.05844 | AF86: =AF85/AF34*365 -> 320.80554 | AH86: =AVERAGE(AF86,T86) -> 295.84792 | AJ86: =AVERAGE(AF86:AH86,Z86) -> 311.50969 | AL86: =AVERAGE(AF86:AJ86) -> 309.38772
B88: Accrued Expenses and Other Current Liabilities | D88: =BS!P40 -> 84.735 | E88: =BS!Q40 -> 99.542 | F88: =BS!R40 -> 143.575 | G88: =BS!S40 -> 164.633 | H88: =BS!T40 -> 164.633 | J88: =BS!V40 -> 191.627 | K88: =BS!W40 -> 206.981 | L88: =BS!X40 -> 202.627 | M88: =BS!Y40 -> 197.204 | N88: =BS!Z40 -> 197.204 | P88: =BS!AB40 -> 199.083 | Q88: =BS!AC40 -> 222.981 | R88: =BS!AD40 -> 234.807 | S88: =BS!AE40 -> 271.952 | T88: =BS!AF40 -> 271.952 | V88: =BS!AH40 -> 271.72 | W88: =BS!AI40 -> 256.479 | X88: =X89*X43 -> 326.77726 | Y88: =Y89*Y43 -> 306.21514 | Z88: =Y88 -> 306.21514 | AB88: =AB89*AB43 -> 262.25862 | AC88: =AC89*AC43 -> 305.21035 | AD88: =AD89*AD43 -> 362.62169 | AE88: =AE89*AE43 -> 424.63861 | AF88: =AE88 -> 424.63861 | AH88: =AH89*AH43 -> 468.24664 | AJ88: =AJ89*AJ43 -> 546.61493 | AL88: =AL89*AL43 -> 643.65437
B89: % of sg&a | D89: =D88/D43 -> 7.2758887 | E89: =E88/E43 -> 7.8041552 | F89: =F88/F43 -> 7.6971533 | G89: =G88/G43 -> 8.5302073 | H89: =H88/H43 -> 2.6402957 | J89: =J88/J43 -> 11.209535 | K89: =K88/K43 -> 11.407054 | L89: =L88/L43 -> 6.9416581 | M89: =M88/M43 -> 8.4866377 | N89: =N88/N43 -> 2.2494667 | P89: =P88/P43 -> 6.6425211 | Q89: =Q88/Q43 -> 6.7116455 | R89: =R88/R43 -> 7.1559138 | S89: =S88/S43 -> 6.959566 | T89: =T88/T43 -> 2.0132215 | V89: =V88/V43 -> 9.2832251 | W89: =W88/W43 -> 6.5848267 | X89: =AVERAGE(V89:W89,R89:S89) -> 7.4958829 | Y89: =AVERAGE(W89:X89,S89:T89) -> 5.7633743 | Z89: =Z88/Z43 -> 1.856463 | AB89: =AVERAGE(V89:Y89) -> 7.2818273 | AC89: =AVERAGE(AB89,W89:Y89) -> 6.7814778 | AD89: =AVERAGE(AB89:AC89,X89:Y89) -> 6.8306406 | AE89: =AVERAGE(AB89:AD89,Y89) -> 6.66433 | AF89: =AF88/AF43 -> 2.1465085 | AH89: =AVERAGE(AF89,Z89,T89) -> 2.0053977 | AJ89: =AVERAGE(AF89,AH89,Z89) -> 2.0027897 | AL89: =AVERAGE(AH89,AJ89,AF89) -> 2.0515653
B91: Cash Flow Statement | D91: Q1 22 | E91: Q2 22 | F91: Q3 22 | G91: Q4 22 | H91: FY 22 | J91: Q1 23 | K91: Q2 23 | L91: Q3 23 | M91: Q4 23 | N91: FY 23 | P91: Q1 24 | Q91: Q2 24 | R91: Q3 24 | S91: Q4 24 | T91: FY 24 | V91: Q1 25 | W91: Q2 25 | X91: Q3 25 | Y91: Q4 25 | Z91: FY 25 | AB91: Q1 26 | AC91: Q2 26 | AD91: Q3 26 | AE91: Q4 26 | AF91: FY 26 | AH91: FY 27 | AJ91: FY 28 | AL91: FY 29
B94: D&A (Depreciation & Amortization) | D94: =CF!P17 -> 1.213 | E94: =CF!Q17 -> 1.342 | F94: =CF!R17 -> 1.549 | G94: =CF!S17 -> 1.262 | H94: =CF!T17 -> 5.366 | J94: =CF!V17 -> 1.714 | K94: =CF!W17 -> 2.241 | L94: =CF!X17 -> 2.066 | M94: =CF!Y17 -> 2.071 | N94: =CF!Z17 -> 8.092 | P94: =CF!AB17 -> 2.518 | Q94: =CF!AC17 -> 2.166 | R94: =CF!AD17 -> 2.389 | S94: =CF!AE17 -> 2.894 | T94: =CF!AF17 -> 9.967 | V94: =CF!AH17 -> 3.017 | W94: =CF!AI17 -> 3.339 | X94: =X37+X49 -> 3.3570789 | Y94: =Y37+Y49 -> 3.3665353 | Z94: =SUM(V94:Y94) -> 13.079614 | AB94: =AB37+AB49 -> 3.2981235 | AC94: =AC37+AC49 -> 3.3418524 | AD94: =AD37+AD49 -> 3.349621 | AE94: =AE37+AE49 -> 3.3455094 | AF94: =SUM(AB94:AE94) -> 13.335106 | AH94: =AH37+AH49 -> 12.499356 | AJ94: =AJ37+AJ49 -> 13.150888 | AL94: =AL37+AL49 -> 13.263186
B95: % of net pp&e and intangibles excl. Goodwill | D95: =D94/(D82+D79) -> 0.01681989 | E95: =E94/(E82+E79) -> 0.019036271 | F95: =F94/(F82+F79) -> 0.019723188 | G95: =G94/(G82+G79) -> 0.013240864 | H95: =H94/(H82+H79) -> 0.056273334 | J95: =J94/(J82+J79) -> 0.010244701 | K95: =K94/(K82+K79) -> 0.012645371 | L95: =L94/(L82+L79) -> 0.0099075424 | M95: =M94/(M82+M79) -> 0.0094231023 | N95: =N94/(N82+N79) -> 0.036741569 | P95: =P94/(P82+P79) -> 0.01064869 | Q95: =Q94/(Q82+Q79) -> 0.0088032319 | R95: =R94/(R82+R79) -> 0.0089288384 | S95: =S94/(S82+S79) -> 0.010108031 | T95: =T94/(T82+T79) -> 0.034751229 | V95: =V94/(V82+V79) -> 0.010130654 | W95: =W94/(W82+W79) -> 0.010733642 | X95: =X94/(X79+X82) -> 0.010733642 | Y95: =Y94/(Y79+Y82) -> 0.010733642 | Z95: =Z94/(Z79+Z82) -> 0.041702192 | AB95: =AB94/(AB79+AB82) -> 0.010582895 | AC95: =AC94/(AC79+AC82) -> 0.010695956 | AD95: =AD94/(AD79+AD82) -> 0.010686534 | AE95: =AE94/(AE79+AE82) -> 0.010674757 | AF95: =AF94/(AF79+AF82) -> 0.04254928 | AH95: =AH94/(AH79+AH82) -> 0.039667567 | AJ95: =AJ94/(AJ79+AJ82) -> 0.041306346 | AL95: =AL94/(AL79+AL82) -> 0.041174398
B97: Stock-Based Compensation Expense | D97: =CF!P18 -> 1.374 | E97: =CF!Q18 -> 1.969 | F97: =CF!R18 -> 1.893 | G97: =CF!S18 -> 2.494 | H97: =CF!T18 -> 7.73 | J97: =CF!V18 -> 2.068 | K97: =CF!W18 -> 2.017 | L97: =CF!X18 -> 10.581 | M97: =CF!Y18 -> 12.672 | N97: =CF!Z18 -> 27.338 | P97: =CF!AB18 -> 14.569 | Q97: =CF!AC18 -> 14.342 | R97: =CF!AD18 -> 11.881 | S97: =CF!AE18 -> 8.784 | T97: =CF!AF18 -> 49.576 | V97: =CF!AH18 -> 9.817 | W97: =CF!AI18 -> 9.77 | X97: =X98*X43 -> 12.78514 | Y97: =Y98*Y43 -> 15.088033 | Z97: =SUM(V97:Y97) -> 47.460173 | AB97: =AB98*AB43 -> 10.475843 | AC97: =AC98*AC43 -> 12.590081 | AD97: =AD98*AD43 -> 15.234291 | AE97: =AE98*AE43 -> 18.184392 | AF97: =SUM(AB97:AE97) -> 56.484606 | AH97: =AH98*AH43 -> 73.181499 | AJ97: =AJ98*AJ43 -> 80.665986 | AL97: =AL98*AL43 -> 93.546666
B98: % of sg&a | D98: =D97/D43 -> 0.11798042 | E98: =E97/E43 -> 0.15437083 | F98: =F97/F43 -> 0.10148502 | G98: =G97/G43 -> 0.1292228 | H98: =H97/H43 -> 0.12396959 | J98: =J97/J43 -> 0.12097104 | K98: =K97/K43 -> 0.1111601 | L98: =L97/L43 -> 0.36248715 | M98: =M97/M43 -> 0.54533718 | N98: =N97/N43 -> 0.31183912 | P98: =P97/P43 -> 0.48610323 | Q98: =Q97/Q43 -> 0.43168889 | R98: =R97/R43 -> 0.3620821 | S98: =S97/S43 -> 0.22479271 | T98: =T97/T43 -> 0.36700399 | V98: =V97/V43 -> 0.3353946 | W98: =W97/W43 -> 0.2508344 | X98: =AVERAGE(V98:W98,R98:S98) -> 0.29327595 | Y98: =AVERAGE(W98:X98,S98:T98) -> 0.28397676 | Z98: =Z97/Z43 -> 0.28773253 | AB98: =AVERAGE(V98:Y98) -> 0.29087043 | AC98: =AVERAGE(AB98,W98:Y98) -> 0.27973939 | AD98: =AVERAGE(AB98:AC98,X98:Y98) -> 0.28696563 | AE98: =AVERAGE(AB98:AD98,Y98) -> 0.28538805 | AF98: =AF97/AF43 -> 0.2855244 | AH98: =AVERAGE(AF98,Z98,T98) -> 0.31342031 | AJ98: =AVERAGE(AF98,AH98,Z98) -> 0.29555908 | AL98: =AVERAGE(AH98,AJ98,AF98) -> 0.29816793
B99: implied equity value (p/s multiple) | X99: 3.54 | Y99: 3.54 | Z99: =AVERAGE(V99:Y99) -> 3.54 | AB99: 4 | AC99: 4 | AD99: 4 | AE99: 4 | AF99: =AVERAGE(AB99:AE99) -> 4 | AH99: 3.5 | AJ99: 3.5 | AL99: 3.5
B100: implied share price (for dilution) | X100: =X99*(X31+W31+V31+S31)/W64 -> 47.881524 | Y100: =Y99*(Y31+X31+W31+V31)/X64 -> 52.167308 | Z100: =AVERAGE(V100:Y100) -> 50.024416 | AB100: =AB99*(AB31+Y31+X31+W31)/Y64 -> 60.818701 | AC100: =AC99*(AC31+AB31+Y31+X31)/AB64 -> 63.319915 | AD100: =AD99*(AD31+AC31+AB31+Y31)/AC64 -> 66.257595 | AE100: =AE99*(AE31+AD31+AC31+AB31)/AD64 -> 69.768428 | AF100: =AVERAGE(AB100:AE100) -> 65.04116 | AH100: =AH99*AH31/AE64 -> 71.951439 | AJ100: =AJ99*AJ31/AH64 -> 82.657599 | AL100: =AL99*AL31/AJ64 -> 95.634247
B101: sbc dilution (shares issued) | X101: =X97/X100 -> 0.26701614 | Y101: =Y97/Y100 -> 0.28922392 | Z101: =AVERAGE(V101:Y101) -> 0.27812003 | AB101: =AB97/AB100 -> 0.17224707 | AC101: =AC97/AC100 -> 0.19883288 | AD101: =AD97/AD100 -> 0.2299252 | AE101: =AE97/AE100 -> 0.26063926 | AF101: =AVERAGE(AB101:AE101) -> 0.2154111 | AH101: =AH97/AH100 -> 1.0170957 | AJ101: =AJ97/AJ100 -> 0.97590526 | AL101: =AL97/AL100 -> 0.97817121
B103: Changes in Net Working Capital | D103: =SUM(CF!P21:P24) -> -27.456 | E103: =SUM(CF!Q21:Q24) -> -55.363 | F103: =SUM(CF!R21:R24) -> -33.306 | G103: =SUM(CF!S21:S24) -> -21.9 | H103: =SUM(CF!T21:T24) -> -138.025 | J103: =SUM(CF!V21:V24) -> -39.072 | K103: =SUM(CF!W21:W24) -> -26.92 | L103: =SUM(CF!X21:X24) -> -61.785 | M103: =SUM(CF!Y21:Y24) -> -60.647 | N103: =SUM(CF!Z21:Z24) -> -188.424 | P103: =SUM(CF!AB21:AB24) -> -57.225 | Q103: =SUM(CF!AC21:AC24) -> 13.833 | R103: =SUM(CF!AD21:AD24) -> -59.046 | S103: =SUM(CF!AE21:AE24) -> 25.968 | T103: =SUM(CF!AF21:AF24) -> -76.47 | V103: =SUM(CF!AH21:AH24) -> -38.494 | W103: =SUM(CF!AI21:AI24) -> -89.16 | X103: =X104*(X70-W70) -> -38.282551 | Y103: =Y104*(Y70-X70) -> -63.752664 | Z103: =SUM(V103:Y103) -> -229.68922 | AB103: =AB104*(AB70-Z70) -> 91.528905 | AC103: =AC104*(AC70-AB70) -> -42.938253 | AD103: =AD104*(AD70-AC70) -> -36.89311 | AE103: =AE104*(AE70-AD70) -> -48.357574 | AF103: =SUM(AB103:AE103) -> -36.660032 | AH103: =AH104*(AH70-AF70) -> -10.255682 | AJ103: =AJ104*(AJ70-AH70) -> -22.686053 | AL103: =AL104*(AL70-AJ70) -> -14.528406
B104: % of change in sales | D104: =D103/(D31-IS!M18) -> 0.51846816 | E104: =E103/(E31-D31) -> -0.88995161 | F104: =F103/(F31-E31) -> -1.1361807 | G104: =G103/(G31-F31) -> 0.87018715 | H104: =H103/IS!N18 -> -0.53137428 | J104: =J103/(J31-IS!S18) -> 1.1395905 | K104: =K103/(K31-J31) -> -0.38281594 | L104: =L103/(L31-K31) -> -2.5752334 | M104: =M103/(M31-L31) -> -34.615868 | N104: =N103/IS!T18 -> -0.48458975 | P104: =P103/(P31-IS!Y18) -> 3.1563707 | Q104: =Q103/(Q31-P31) -> 0.27507009 | R104: =R103/(R31-Q31) -> -39.469251 | S104: =S103/(S31-R31) -> 1.3320339 | T104: =T103/IS!Z18 -> -0.13711107 | V104: =V103/(V31-IS!AE18) -> 0.7529536 | W104: =W103/(W31-V31) -> -2.0722836 | X104: =AVERAGE(V104:W104) -> -0.65966498 | Y104: =X104*0.9 -> -0.59369848 | Z104: =Z103/(Z31-T31) -> -1.3963305 | AB104: =Y104*0.9 -> -0.53432863 | AC104: =AB104*0.9 -> -0.48089577 | AD104: =AC104*0.9 -> -0.43280619 | AE104: =AD104*0.9 -> -0.38952557 | AF104: =AF103/(AF31-Z31) -> -0.19363793 | AG104: =AF104*0.9 -> -0.17427414 | AH104: =AG104*0.9 -> -0.15684672 | AI104: =AH104*0.9 -> -0.14116205 | AJ104: =AI104*0.9 -> -0.12704585 | AK104: =AJ104*0.9 -> -0.11434126 | AL104: =AK104*0.9 -> -0.10290714
B106: Capital Expenditures | D106: =CF!P28 -> -3.584 | E106: =CF!Q28 -> -2.125 | F106: =CF!R28 -> -13.787 | G106: =CF!S28 -> -73.024 | H106: =CF!T28 -> -92.52 | J106: =CF!V28 -> -15.05 | K106: =CF!W28 -> -7.868 | L106: =CF!X28 -> -28.228 | M106: =CF!Y28 -> -13.192 | N106: =CF!Z28 -> -64.338 | P106: =CF!AB28 -> -26.087 | Q106: =CF!AC28 -> -13.577 | R106: =CF!AD28 -> -33.367 | S106: =CF!AE28 -> -12.917 | T106: =CF!AF28 -> -85.948 | V106: =CF!AH28 -> -17.101 | W106: =CF!AI28 -> -15.141 | X106: =-X$31*(X107+Sensitivity!$U$38) -> -24.826988 | Y106: =-Y$31*(Y107+Sensitivity!$U$38) -> -25.586335 | Z106: =SUM(V106:Y106) -> -82.655323 | AB106: =-AB$31*(AB107+Sensitivity!$U$38) -> -17.706433 | AC106: =-AC$31*(AC107+Sensitivity!$U$38) -> -21.851084 | AD106: =-AD$31*(AD107+Sensitivity!$U$38) -> -26.81321 | AE106: =-AE$31*(AE107+Sensitivity!$U$38) -> -31.437817 | AF106: =SUM(AB106:AE106) -> -97.808544 | AH106: =-AH$31*(AH107+Sensitivity!$U$38) -> -126.94185 | AJ106: =-AJ$31*(AJ107+Sensitivity!$U$38) -> -140.26705 | AL106: =-AL$31*(AL107+Sensitivity!$U$38) -> -158.29588
B107: % of sales | D107: =-D106/D31 -> 0.084957095 | E107: =-E106/E31 -> 0.020355381 | F107: =-F106/F31 -> 0.10311198 | G107: =-G106/G31 -> 0.67277183 | H107: =-H106/H31 -> 0.23794338 | J107: =-J106/J31 -> 0.20267722 | K107: =-K106/K31 -> 0.054420828 | L107: =-L106/L31 -> 0.16745665 | M107: =-M106/M31 -> 0.077453749 | N107: =-N106/N31 -> 0.11535834 | P107: =-P106/P31 -> 0.17140961 | Q107: =-Q106/Q31 -> 0.067053536 | R107: =-R106/R31 -> 0.16358297 | S107: =-S106/S31 -> 0.057801683 | T107: =-T106/T31 -> 0.10989135 | V107: =-V106/V31 -> 0.099224239 | W107: =-W106/W31 -> 0.070301618 | X107: =AVERAGE(V107:W107,R107:S107) -> 0.097727628 | Y107: =AVERAGE(W107:X107,S107:T107) -> 0.083930569 | Z107: =-Z106/Z31 -> 0.087316922 | AB107: =AVERAGE(Z107:AA107,V107:W107) -> 0.08561426 | AC107: =AVERAGE(AA107:AB107,W107:X107) -> 0.084547835 | AD107: =AVERAGE(AB107:AC107,X107:Y107) -> 0.087955073 | AE107: =AVERAGE(AC107:AD107,Y107:Z107) -> 0.0859376 | AF107: =-AF106/AF31 -> 0.086103963 | AH107: =AVERAGE(AF107,Z107,T107) -> 0.09443741 | AJ107: =AVERAGE(AH107:AI107,AD107:AE107) -> 0.089443361 | AL107: =AVERAGE(AJ107:AK107,AF107:AG107) -> 0.087773662
B109: Proceeds from Asset Disposals | D109: =CF!P29 -> 0 | E109: =CF!Q29 -> 0 | F109: =CF!R29 -> 0 | G109: =CF!S29 -> 0 | H109: =CF!T29 -> -0.12 | J109: =CF!V29 -> 0 | K109: =CF!W29 -> 0 | L109: =CF!X29 -> 0 | M109: =CF!Y29 -> 0 | N109: =CF!Z29 -> 0.062 | P109: =CF!AB29 -> 0 | Q109: =CF!AC29 -> 0 | R109: =CF!AD29 -> 0 | S109: =CF!AE29 -> 0 | T109: =CF!AF29 -> 0.945 | V109: =CF!AH29 -> 0 | W109: =CF!AI29 -> 0 | X109: =X110*X$106 -> 0 | Y109: =Y110*Y$106 -> 0 | Z109: =SUM(V109:Y109) -> 0 | AB109: =AB110*AB$106 -> 0 | AC109: =AC110*AC$106 -> 0 | AD109: =AD110*AD$106 -> 0 | AE109: =AE110*AE$106 -> 0 | AF109: =SUM(AB109:AE109) -> 0 | AH109: =AH110*AH$106 -> 0 | AJ109: =AJ110*AJ$106 -> 0 | AL109: =AL110*AL$106 -> 0
B110: % of capex | D110: =-D109/D106 -> 0 | E110: =-E109/E106 -> 0 | F110: =-F109/F106 -> 0 | G110: =-G109/G106 -> 0 | H110: =-H109/H106 -> -0.0012970169 | J110: =-J109/J106 -> 0 | K110: =-K109/K106 -> 0 | L110: =-L109/L106 -> 0 | M110: =-M109/M106 -> 0 | N110: =-N109/N106 -> 0.00096366067 | P110: =-P109/P106 -> 0 | Q110: =-Q109/Q106 -> 0 | R110: =-R109/R106 -> 0 | S110: =-S109/S106 -> 0 | T110: =-T109/T106 -> 0.01099502 | V110: =-V109/V106 -> 0 | W110: =-W109/W106 -> 0
B112: Dividends | D112: =CF!P39 -> 0 | E112: =CF!Q39 -> 0 | F112: =CF!R39 -> 0 | G112: =CF!S39 -> 0 | H112: =CF!T39 -> 0 | J112: =CF!V39 -> 0 | K112: =CF!W39 -> 0 | L112: =CF!X39 -> -3.951 | M112: =CF!Y39 -> 0 | N112: =CF!Z39 -> -3.951 | P112: =CF!AB39 -> 0 | Q112: =CF!AC39 -> 0 | R112: =CF!AD39 -> -6.9 | S112: =CF!AE39 -> 0 | T112: =CF!AF39 -> -6.9 | V112: =CF!AH39 -> 0 | W112: =CF!AI39 -> 0 | X112: =-X113*X126 -> -4.0596019 | Y112: =-Y113*Y126 -> 0 | Z112: =-Z113*Z126 -> -6.964694 | AB112: =-AB113*AB126 -> 0 | AC112: =-AC113*AC126 -> 0 | AD112: =-AD113*AD126 -> -7.9291799 | AE112: =-AE113*AE126 -> 0 | AF112: =-AF113*AF126 -> -8.2071337 | AH112: =-AH113*AH126 -> -9.7117748 | AJ112: =-AJ113*AJ126 -> -11.330404 | AL112: =-AL113*AL126 -> -13.029965
B113: % of NOPAT | D113: =-D112/D126 -> 0 | E113: =-E112/E126 -> 0 | F113: =-F112/F126 -> 0 | G113: =-G112/G126 -> 0 | H113: =-H112/H126 -> 0 | J113: =-J112/J126 -> 0 | K113: =-K112/K126 -> 0 | L113: =-L112/L126 -> 0.12234217 | M113: =-M112/M126 -> 0 | N113: =-N112/N126 -> 0.049528075 | P113: =-P112/P126 -> 0 | Q113: =-Q112/Q126 -> 0 | R113: =-R112/R126 -> 0.17243176 | S113: =-S112/S126 -> 0 | T113: =-T112/T126 -> 0.058255721 | V113: =-V112/V126 -> 0 | W113: =-W112/W126 -> 0 | X113: 0.1 | Y113: 0 | Z113: 0.05 | AB113: 0 | AC113: 0 | AD113: 0.18 | AE113: 0 | AF113: 0.05 | AH113: 0.05 | AJ113: 0.05 | AL113: 0.05
B115: Repurchase of Stock | D115: =CF!P40 -> 0.724 | E115: =CF!Q40 -> 0.026 | F115: =CF!R40 -> 0.4 | G115: =CF!S40 -> 0.164 | H115: =CF!T40 -> 1.314 | J115: =CF!V40 -> 0.241 | K115: =CF!W40 -> 4.284 | L115: =CF!X40 -> 0.765 | M115: =CF!Y40 -> 0.848 | N115: =CF!Z40 -> 6.138 | P115: =CF!AB40 -> 4.799 | Q115: =CF!AC40 -> 1.638 | R115: =CF!AD40 -> 0.053 | S115: =CF!AE40 -> 4.609 | T115: =CF!AF40 -> 11.099 | V115: =CF!AH40 -> 22.729 | W115: =CF!AI40 -> 0.853 | X115: 0 | Y115: =AVERAGE(W115:X115,S115:T115) -> 4.14025 | Z115: =SUM(V115:Y115) -> 27.72225 | AB115: =AVERAGE(V115:Y115) -> 6.9305625 | AC115: =AVERAGE(AA115:AB115,W115:X115) -> 2.5945208 | AD115: =AVERAGE(AB115:AC115,X115:Y115) -> 3.4163333 | AE115: =AVERAGE(AC115:AD115,Y115:Z115) -> 9.4683385 | AF115: =SUM(AB115:AE115) -> 22.409755 | AH115: =AVERAGE(AF115:AG115,AB115:AC115) -> 10.644946 | AJ115: =AVERAGE(AH115:AI115,AD115:AE115) -> 7.843206 | AL115: =AVERAGE(AJ115:AK115,AF115:AG115) -> 15.126481
A117: x | B117: Free Cash Flow to Firm
D118: =D$8 -> 2022 | E118: =F118 -> 0 | F118: =F$8 -> 0 | G118: =F118 -> 0 | H118: =F118 -> 0 | J118: =J$8 -> 2023 | K118: =L118 -> 0 | L118: =L$8 -> 0 | M118: =L118 -> 0 | N118: =L118 -> 0 | P118: =P$8 -> 2024 | Q118: =R118 -> 0 | R118: =R$8 -> 0 | S118: =R118 -> 0 | T118: =R118 -> 0 | V118: =V$8 -> 2025 | W118: =X118 -> 0 | X118: =X$8 -> 0 | Y118: =X118 -> 0 | Z118: =X118 -> 0 | AB118: =AB$8 -> 2026 | AC118: =AD118 -> 0 | AD118: =AD$8 -> 0 | AE118: =AD118 -> 0 | AF118: =AD118 -> 0 | AH118: =AH$8 -> 2027 | AJ118: =AJ$8 -> 2028 | AL118: =AL$8 -> 2029
D119: Q1 | E119: Q2 | F119: Q3 | G119: Q4 | H119: FY | J119: Q1 | K119: Q2 | L119: Q3 | M119: Q4 | N119: FY | P119: Q1 | Q119: Q2 | R119: Q3 | S119: Q4 | T119: FY | V119: Q1 | W119: Q2 | X119: Q3 | Y119: Q4 | Z119: FY | AB119: Q1 | AC119: Q2 | AD119: Q3 | AE119: Q4 | AF119: FY | AH119: FY | AJ119: FY | AL119: FY
B122: EBIT (Operating Income) | D122: =D61 -> -9.306 | E122: =E61 -> 20.035 | F122: =F61 -> 31.636 | G122: =G61 -> 16.67 | H122: =H61 -> 59.023 | J122: =J61 -> 8.862 | K122: =K61 -> 30.43 | L122: =L61 -> 33.173 | M122: =M61 -> 23.374 | N122: =N61 -> 95.837 | P122: =P61 -> 25.232 | Q122: =Q61 -> 37.593 | R122: =R61 -> 44.184 | S122: =S61 -> 43.989 | T122: =T61 -> 150.053 | V122: =V61 -> 25.777 | W122: =W61 -> 31.694 | X122: =X61 -> 43.187254 | Y122: =Y61 -> 51.824705 | Z122: =Z61 -> 152.48296 | AB122: =AB61 -> 35.158788 | AC122: =AC61 -> 43.935888 | AD122: =AD61 -> 51.824705 | AE122: =AE61 -> 62.189646 | AF122: =AF61 -> 193.10903 | AH122: =AH61 -> 228.51235 | AJ122: =AJ61 -> 266.59774 | AL122: =AL61 -> 306.5874
B124: Tax Rate | D124: =IS!P45/IS!P42 -> 0.52804107 | E124: =IS!Q45/IS!Q42 -> 0.30901408 | F124: =IS!R45/IS!R42 -> 0.24068762 | G124: =IS!S45/IS!S42 -> 0.17573996 | H124: =IS!T45/IS!T42 -> 0.22332957 | J124: =IS!V45/IS!V42 -> 0.25612797 | K124: =IS!W45/IS!W42 -> 0.17135601 | L124: =IS!X45/IS!X42 -> 0.02647722 | M124: =IS!Y45/IS!Y42 -> 0.26143059 | N124: =IS!Z45/IS!Z42 -> 0.1676186 | P124: =IS!AB45/IS!AB42 -> 0.16873154 | Q124: =IS!AC45/IS!AC42 -> 0.22968719 | R124: =IS!AD45/IS!AD42 -> 0.09433662 | S124: =IS!AE45/IS!AE42 -> 0.3189444 | T124: =IS!AF45/IS!AF42 -> 0.21065688 | V124: =IS!AH45/IS!AH42 -> 0.084260833 | W124: =IS!AI45/IS!AI42 -> 0.036927948 | X124: 0.06 | Y124: 0.14 | Z124: 0.17 | AB124: 0.15 | AC124: 0.15 | AD124: 0.15 | AE124: 0.15 | AF124: 0.15 | AH124: 0.15 | AJ124: 0.15 | AL124: 0.15
B126: NOPAT (Net Operating Profit After Taxes) | D126: =D122*(1-D124) -> -4.3920498 | E126: =E122*(1-E124) -> 13.843903 | F126: =F122*(1-F124) -> 24.021606 | G126: =G122*(1-G124) -> 13.740415 | H126: =H122*(1-H124) -> 45.841419 | J126: =J122*(1-J124) -> 6.5921939 | K126: =K122*(1-K124) -> 25.215637 | L126: =L122*(1-L124) -> 32.294671 | M126: =M122*(1-M124) -> 17.263321 | N126: =N122*(1-N124) -> 79.772936 | P126: =P122*(1-P124) -> 20.974566 | Q126: =Q122*(1-Q124) -> 28.95837 | R126: =R122*(1-R124) -> 40.015831 | S126: =S122*(1-S124) -> 29.958955 | T126: =T122*(1-T124) -> 118.4433 | V126: =V122*(1-V124) -> 23.605009 | W126: =W122*(1-W124) -> 30.523606 | X126: =X122*(1-X124) -> 40.596019 | Y126: =Y122*(1-Y124) -> 44.569246 | Z126: =SUM(V126:Y126) -> 139.29388 | AB126: =AB122*(1-AB124) -> 29.88497 | AC126: =AC122*(1-AC124) -> 37.345505 | AD126: =AD122*(1-AD124) -> 44.050999 | AE126: =AE122*(1-AE124) -> 52.861199 | AF126: =SUM(AB126:AE126) -> 164.14267 | AH126: =AH122*(1-AH124) -> 194.2355 | AJ126: =AJ122*(1-AJ124) -> 226.60808 | AL126: =AL122*(1-AL124) -> 260.59929
B128: D&A (Depreciation & Amortization) | D128: =D94 -> 1.213 | E128: =E94 -> 1.342 | F128: =F94 -> 1.549 | G128: =G94 -> 1.262 | H128: =H94 -> 5.366 | J128: =J94 -> 1.714 | K128: =K94 -> 2.241 | L128: =L94 -> 2.066 | M128: =M94 -> 2.071 | N128: =N94 -> 8.092 | P128: =P94 -> 2.518 | Q128: =Q94 -> 2.166 | R128: =R94 -> 2.389 | S128: =S94 -> 2.894 | T128: =T94 -> 9.967 | V128: =V94 -> 3.017 | W128: =W94 -> 3.339 | X128: =X94 -> 3.3570789 | Y128: =Y94 -> 3.3665353 | Z128: =Z94 -> 13.079614 | AB128: =AB94 -> 3.2981235 | AC128: =AC94 -> 3.3418524 | AD128: =AD94 -> 3.349621 | AE128: =AE94 -> 3.3455094 | AF128: =AF94 -> 13.335106 | AH128: =AH94 -> 12.499356 | AJ128: =AJ94 -> 13.150888 | AL128: =AL94 -> 13.263186
B130: Stock-Based Compensation | D130: =D97 -> 1.374 | E130: =E97 -> 1.969 | F130: =F97 -> 1.893 | G130: =G97 -> 2.494 | H130: =H97 -> 7.73 | J130: =J97 -> 2.068 | K130: =K97 -> 2.017 | L130: =L97 -> 10.581 | M130: =M97 -> 12.672 | N130: =N97 -> 27.338 | P130: =P97 -> 14.569 | Q130: =Q97 -> 14.342 | R130: =R97 -> 11.881 | S130: =S97 -> 8.784 | T130: =T97 -> 49.576 | V130: =V97 -> 9.817 | W130: =W97 -> 9.77 | X130: =X97 -> 12.78514 | Y130: =Y97 -> 15.088033 | Z130: =Z97 -> 47.460173 | AB130: =AB97 -> 10.475843 | AC130: =AC97 -> 12.590081 | AD130: =AD97 -> 15.234291 | AE130: =AE97 -> 18.184392 | AF130: =AF97 -> 56.484606 | AH130: =AH97 -> 73.181499 | AJ130: =AJ97 -> 80.665986 | AL130: =AL97 -> 93.546666
B132: Changes in Net Working Capital | D132: =D103 -> -27.456 | E132: =E103 -> -55.363 | F132: =F103 -> -33.306 | G132: =G103 -> -21.9 | H132: =H103 -> -138.025 | J132: =J103 -> -39.072 | K132: =K103 -> -26.92 | L132: =L103 -> -61.785 | M132: =M103 -> -60.647 | N132: =N103 -> -188.424 | P132: =P103 -> -57.225 | Q132: =Q103 -> 13.833 | R132: =R103 -> -59.046 | S132: =S103 -> 25.968 | T132: =T103 -> -76.47 | V132: =V103 -> -38.494 | W132: =W103 -> -89.16 | X132: =X103 -> -38.282551 | Y132: =Y103 -> -63.752664 | Z132: =Z103 -> -229.68922 | AB132: =AB103 -> 91.528905 | AC132: =AC103 -> -42.938253 | AD132: =AD103 -> -36.89311 | AE132: =AE103 -> -48.357574 | AF132: =AF103 -> -36.660032 | AH132: =AH103 -> -10.255682 | AJ132: =AJ103 -> -22.686053 | AL132: =AL103 -> -14.528406
B134: Net CapEx | D134: =D106+D109 -> -3.584 | E134: =E106+E109 -> -2.125 | F134: =F106+F109 -> -13.787 | G134: =G106+G109 -> -73.024 | H134: =H106+H109 -> -92.64 | J134: =J106+J109 -> -15.05 | K134: =K106+K109 -> -7.868 | L134: =L106+L109 -> -28.228 | M134: =M106+M109 -> -13.192 | N134: =N106+N109 -> -64.276 | P134: =P106+P109 -> -26.087 | Q134: =Q106+Q109 -> -13.577 | R134: =R106+R109 -> -33.367 | S134: =S106+S109 -> -12.917 | T134: =T106+T109 -> -85.003 | V134: =V106+V109 -> -17.101 | W134: =W106+W109 -> -15.141 | X134: =X106+X109 -> -24.826988 | Y134: =Y106+Y109 -> -25.586335 | Z134: =Z106+Z109 -> -82.655323 | AB134: =AB106+AB109 -> -17.706433 | AC134: =AC106+AC109 -> -21.851084 | AD134: =AD106+AD109 -> -26.81321 | AE134: =AE106+AE109 -> -31.437817 | AF134: =AF106+AF109 -> -97.808544 | AH134: =AH106+AH109 -> -126.94185 | AJ134: =AJ106+AJ109 -> -140.26705 | AL134: =AL106+AL109 -> -158.29588
B136: FCFF (Free Cash Flow to Firm) | D136: =D126+D94+D97+D103+D134 -> -32.84505 | E136: =E126+E94+E97+E103+E134 -> -40.333097 | F136: =F126+F94+F97+F103+F134 -> -19.629394 | G136: =G126+G94+G97+G103+G134 -> -77.427585 | H136: =H126+H94+H97+H103+H134 -> -171.72758 | J136: =J126+J94+J97+J103+J134 -> -43.747806 | K136: =K126+K94+K97+K103+K134 -> -5.3143635 | L136: =L126+L94+L97+L103+L134 -> -45.071329 | M136: =M126+M94+M97+M103+M134 -> -41.832679 | N136: =N126+N94+N97+N103+N134 -> -137.49706 | P136: =P126+P94+P97+P103+P134 -> -45.250434 | Q136: =Q126+Q94+Q97+Q103+Q134 -> 45.72237 | R136: =R126+R94+R97+R103+R134 -> -38.127169 | S136: =S126+S94+S97+S103+S134 -> 54.687955 | T136: =T126+T94+T97+T103+T134 -> 16.513302 | V136: =V126+V94+V97+V103+V134 -> -19.155991 | W136: =W126+W94+W97+W103+W134 -> -60.668394 | X136: =X126+X128+X130+X132+X134 -> -6.3713013 | Y136: =Y126+Y128+Y130+Y132+Y134 -> -26.315184 | Z136: =Z126+Z128+Z130+Z132+Z134 -> -112.51087 | AB136: =AB126+AB128+AB130+AB132+AB134 -> 117.48141 | AC136: =AC126+AC128+AC130+AC132+AC134 -> -11.511898 | AD136: =AD126+AD128+AD130+AD132+AD134 -> -1.0714094 | AE136: =AE126+AE128+AE130+AE132+AE134 -> -5.4042905 | AF136: =AF126+AF128+AF130+AF132+AF134 -> 99.49381 | AH136: =AH126+AH128+AH130+AH132+AH134 -> 142.71882 | AJ136: =AJ126+AJ128+AJ130+AJ132+AJ134 -> 157.47185 | AL136: =AL126+AL128+AL130+AL132+AL134 -> 194.58486
A138: x | B138: Valuation Summary
V139: =V$8 -> 2025 | W139: =X139 -> 0 | X139: =X$8 -> 0 | Y139: =X139 -> 0 | Z139: =X139 -> 0 | AB139: =AB$8 -> 2026 | AC139: =AD139 -> 0 | AD139: =AD$8 -> 0 | AE139: =AD139 -> 0 | AF139: =AD139 -> 0 | AH139: =AH$8 -> 2027 | AJ139: =AJ$8 -> 2028 | AL139: =AL$8 -> 2029
V140: Q1 | W140: Q2 | X140: Q3 | Y140: Q4 | Z140: FY | AB140: Q1 | AC140: Q2 | AD140: Q3 | AE140: Q4 | AF140: FY | AH140: FY | AJ140: FY | AL140: FY
B143: Discounted Cash Flows (DCF)
B146: Discount Period | X146: 0.044444444 | Y146: 0.20833333 | AB146: 0.38888889 | AC146: 0.63888889 | AD146: 0.88888889 | AE146: 1.1111111 | AH146: 2.1388889 | AJ146: 3.1388889 | AL146: 4.1388889
B147: Mid-Quarter/Year Convention Discount Period | X147: 0.022222222 | Y147: 0.12638889 | AB147: 0.29861111 | AC147: 0.51388889 | AD147: 0.76388889 | AE147: 1 | AH147: 1.625 | AJ147: 2.6388889 | AL147: 3.6388889
B149: Rolling WACC (Weighted Average Cost of Capital) | X149: =WACC!$D$39+Sensitivity!U41 -> 0.089035072 | Y149: =WACC!$D$39+Sensitivity!U41 -> 0.089035072 | AB149: =WACC!$E$39+Sensitivity!U41 -> 0.089276309 | AC149: =WACC!$E$39+Sensitivity!U41 -> 0.089276309 | AD149: =WACC!$E$39+Sensitivity!U41 -> 0.089276309 | AE149: =WACC!$E$39+Sensitivity!U41 -> 0.089276309 | AH149: =WACC!$F$39+Sensitivity!U41 -> 0.086275175 | AJ149: =WACC!$G$39+Sensitivity!U41 -> 0.076718966 | AL149: =WACC!$H$39+Sensitivity!U41 -> 0.077817253
B150: Cumulative Discount Factor | X150: =(1+X149)^X147 -> 1.0018972 | Y150: =((1+X149)^X147)*((1+Y149)^Y147) -> 1.012756 | AB150: =((1+X149)^X147)*((1+Y149)^Y147)*((1+AB149)^AB147) -> 1.0389501 | AC150: =((1+X149)^X147)*((1+Y149)^Y147)*((1+AB149)^AB147)*((1+AC149)^AC147) -> 1.0856242 | AD150: =((1+X149)^X147)*((1+Y149)^Y147)*((1+AB149)^AB147)*((1+AC149)^AC147)*((1+AD149)^AD147) -> 1.1589077 | AE150: =((1+X149)^X147)*((1+Y149)^Y147)*((1+AB149)^AB147)*((1+AC149)^AC147)*((1+AD149)^AD147)*((1+AE149)^AE147) -> 1.2623707 | AH150: =((1+X149)^X147)*((1+Y149)^Y147)*((1+AB149)^AB147)*((1+AC149)^AC147)*((1+AD149)^AD147)*((1+AE149)^AE147)*((1+AH149)^AH147) -> 1.4440731 | AJ150: =((1+X149)^X147)*((1+Y149)^Y147)*((1+AB149)^AB147)*((1+AC149)^AC147)*((1+AD149)^AD147)*((1+AE149)^AE147)*((1+AH149)^AH147)*((1+AJ149)^AJ147) -> 1.7551076 | AL150: =((1+X149)^X147)*((1+Y149)^Y147)*((1+AB149)^AB147)*((1+AC149)^AC147)*((1+AD149)^AD147)*((1+AE149)^AE147)*((1+AH149)^AH147)*((1+AJ149)^AJ147)*((1+AL149)^AL147) -> 2.3053234
B152: Present Value of FCFF | X152: =X136/X150*(Inputs!$D$17-92-TODAY())/92 -> 26.957634 | Y152: =Y136/Y150 -> -25.983735 | AB152: =AB136/AB150 -> 113.07705 | AC152: =AC136/AC150 -> -10.603944 | AD152: =AD136/AD150 -> -0.92449934 | AE152: =AE136/AE150 -> -4.2810645 | AH152: =AH136/AH150 -> 98.830745 | AJ152: =AJ136/AJ150 -> 89.722051 | AL152: =AL136/AL150 -> 84.406752
B154: Terminal Value
Q157: Preferred Method: | R157: Revenue Exit | V157: EBITDA Exit Multiple | AB157: Revenue Exit Multiple | AH157: Gordon's Growth Model
V159: Current EV/EBITDA | Z159: =Inputs!M14 -> 14.15 | AB159: Current EV/Sales | AF159: =Inputs!M13 -> 3.16 | AH159: Current Growth Rate | AL159: =AL136/AJ136-1 -> 0.23568027
V160: Exit EV/EBITDA | Z160: =14.15*(1.25) -> 17.6875 | AB160: Exit EV/Sales | AF160: =3.5 -> 3.5 | AH160: Terminal Growth Rate | AL160: 0.04
R161: =R157 -> Revenue Exit | V161: Terminal Value | Z161: =(Z160+Sensitivity!U43)*(AL122+AL128) -> 5657.3573 | AB161: Terminal Value | AF161: =(AF160+Sensitivity!U44)*(AL31) -> 6312.0936 | AH161: Terminal Value | AL161: =AL136*(1+AL160+Sensitivity!U42)/(AL149-AL160-Sensitivity!U42) -> 5351.2151
R162: =IF($R$161="Revenue Exit",$AF$171,IF($R$161="EBITDA Exit",$Z$171,$AL$171)) -> 0.26175426 | V162: PV of Terminal Value | Z162: =Z161/AL150 -> 2454.0406 | AB162: PV of Terminal Value | AF162: =AF161/AL150 -> 2738.0512 | AH162: PV of Terminal Value | AL162: =AL161/AL150 -> 2321.2427
...

Sheet LBO
A7: x | B7: Key Assumptions
B10: Entry | G10: Capital Structure | J10: Interest | K10: Weight | L10: Amount
B11: LTM EBITDA | E11: =(G86+G77) -> 160.02 | G11: Revolver | L11: =K11*$E$13 -> 0
B12: Entry Multiple | G12: Bank Loan | L12: =K12*$E$13 -> 0
B13: Enterprise Value | E13: =E11*E12 -> 0 | G13: Senior Notes | L13: =K13*$E$13 -> 0
B14: Existing Net Debt | E14: =BS!AJ38+BS!AJ39+BS!AJ44+BS!AJ45-BS!AJ15 -> #NAME?
B15: Equity Value | E15: =E13-E14 -> #NAME? | G15: IRR (For reference)
G16: MOIC | L16: =L180 -> #NAME?
B17: Fees & Expenses | E17: =0.03*E13 -> 0 | G17: IRR | L17: =L181 -> #NAME?
B19: Exit
B20: Exit Multiple
A22: x | B22: Sources & Uses
B25: Sources | G25: Uses
C26: Amount | D26: xEBITDA | E26: % Capital | J26: Amount | K26: xEBITDA | L26: % Capital
B27: Revolver | C27: =L11 -> 0 | D27: =C27/$E$11 -> 0 | E27: =C27/$C$34 -> #NAME? | G27: Debt Refinancing | J27: =E14 -> #NAME? | K27: =J27/$E$11 -> #NAME? | L27: =J27/$J$34 -> #NAME?
B28: Bank Loan | C28: =L12 -> 0 | D28: =C28/$E$11 -> 0 | E28: =C28/$C$34 -> #NAME? | G28: Equity Payments | J28: =E15 -> #NAME? | K28: =J28/$E$11 -> #NAME? | L28: =J28/$J$34 -> #NAME?
B29: Senior Notes | C29: =L13 -> 0 | D29: =C29/$E$11 -> 0 | E29: =C29/$C$34 -> #NAME?
B30: Total | C30: =SUM(C27:C29) -> 0 | D30: =C30/$E$11 -> 0 | E30: =C30/$C$34 -> #NAME? | G30: Fees & Expenses | J30: =E17 -> 0 | K30: =J30/$E$11 -> 0 | L30: =J30/$J$34 -> #NAME?
B32: Sponsor Equity | C32: =C34-C30 -> #NAME? | D32: =C32/$E$11 -> #NAME? | E32: =C32/$C$34 -> #NAME?
B34: Total Sources | C34: =J34 -> #NAME? | D34: =C34/$E$11 -> #NAME? | E34: =C34/$C$34 -> #NAME? | G34: Total Uses | J34: =J27+J28+J30 -> #NAME? | K34: =J34/$E$11 -> #NAME? | L34: =J34/$J$34 -> #NAME?
B36: Market Assumptions
A38: x | E38: 2022 | F38: =+E38+1 -> 2023 | G38: =+F38+1 -> 2024 | H38: =+G38+1 -> 2025 | I38: =+H38+1 -> 2026 | J38: =+I38+1 -> 2027 | K38: =+J38+1 -> 2028 | L38: =+K38+1 -> 2029
B50: Sales | H50: 350000 | I50: 352000 | J50: 350000 | K50: 352000 | L50: 350000
B52: Operating Assumptions
A57: x | B57: Income Statement | E57: 2022 | F57: =+E57+1 -> 2023 | G57: =+F57+1 -> 2024 | H57: =+G57+1 -> 2025 | I57: =+H57+1 -> 2026 | J57: =+I57+1 -> 2027 | K57: =+J57+1 -> 2028 | L57: =+K57+1 -> 2029
B59: Revenue | D59: =+_xlfn.XLOOKUP($B59,#REF!,#REF!) -> #REF! | E59: =FCFF!H31 -> 388.832 | F59: =FCFF!N31 -> 557.723 | G59: =FCFF!T31 -> 782.118 | H59: =+H50 -> 350000 | I59: =+I50 -> 352000 | J59: =+J50 -> 350000 | K59: =+K50 -> 352000 | L59: =+L50 -> 350000
B60: % of growth | E60: =E59/IS!N18-1 -> 0.4969413 | F60: =F59/E59-1 -> 0.43435468 | G60: =G59/F59-1 -> 0.40234131 | H60: =H59/G59-1 -> 446.50281 | I60: =I59/H59-1 -> 0.0057142857 | J60: =J59/I59-1 -> -0.0056818182 | K60: =K59/J59-1 -> 0.0057142857 | L60: =L59/K59-1 -> -0.0056818182
B62: Cost of Goods & Services | E62: =FCFF!H34 -> 205.217 | F62: =FCFF!N34 -> 281.508 | G62: =FCFF!T34 -> 390.564 | H62: =H63*H$59 -> 0 | I62: =I63*I$59 -> 0 | J62: =J63*J$59 -> 0 | K62: =K63*K$59 -> 0 | L62: =L63*L$59 -> 0
B63: % of sales | E63: =E62/E59 -> 0.52777806 | F63: =F62/F59 -> 0.50474519 | G63: =G62/G59 -> 0.4993671
B65: COGS Depreciation & Amortization | E65: =FCFF!H37 -> 0 | F65: =FCFF!N37 -> 0 | G65: =FCFF!T37 -> 0 | H65: =+H66*H62 -> 0 | I65: =+I66*I62 -> 0 | J65: =+J66*J62 -> 0 | K65: =+K66*K62 -> 0 | L65: =+L66*L62 -> 0
B66: % of cost of goods & services | E66: =E65/E62 -> 0 | F66: =F65/F62 -> 0 | G66: =G65/G62 -> 0
B68: Gross Profit | E68: =FCFF!H40 -> 183.615 | F68: =FCFF!N40 -> 276.215 | G68: =FCFF!T40 -> 391.554 | H68: =+H59-H62-H65 -> 350000 | I68: =+I59-I62-I65 -> 352000 | J68: =+J59-J62-J65 -> 350000 | K68: =+K59-K62-K65 -> 352000 | L68: =+L59-L62-L65 -> 350000
B69: % of sales | E69: =E68/E59 -> 0.47222194 | F69: =F68/F59 -> 0.49525481 | G69: =G68/G59 -> 0.5006329 | H69: =IFERROR(H68/H$59,"") -> 1 | I69: =IFERROR(I68/I$59,"") -> 1 | J69: =IFERROR(J68/J$59,"") -> 1 | K69: =IFERROR(K68/K$59,"") -> 1 | L69: =IFERROR(L68/L$59,"") -> 1
B71: SG&A (Selling, General & Administrative) | E71: =FCFF!H43 -> 62.354 | F71: =FCFF!N43 -> 87.667 | G71: =FCFF!T43 -> 135.083 | H71: =+H72*H59 -> 0 | I71: =+I72*I59 -> 0 | J71: =+J72*J59 -> 0 | K71: =+K72*K59 -> 0 | L71: =+L72*L59 -> 0
B72: % of sales | E72: =E71/E59 -> 0.16036232 | F72: =F71/F59 -> 0.15718735 | G72: =G71/G59 -> 0.17271435
B74: R&D (Research & Development) | E74: =FCFF!H46 -> 62.226 | F74: =FCFF!N46 -> 92.709 | G74: =FCFF!T46 -> 105.473 | H74: =+H75*H68 -> 0 | I74: =+I75*I68 -> 0 | J74: =+J75*J68 -> 0 | K74: =+K75*K68 -> 0 | L74: =+L75*L68 -> 0
B75: % of gross profit | E75: =E74/E68 -> 0.33889388 | F75: =F74/F68 -> 0.33564071 | G75: =G74/G68 -> 0.26937025
B77: D&A (Depreciation & Amortization) | E77: =FCFF!H49 -> 5.366 | F77: =FCFF!N49 -> 8.092 | G77: =FCFF!T49 -> 9.967 | H77: =+H80+H83 -> 0 | I77: =+I80+I83 -> 0 | J77: =+J80+J83 -> 0 | K77: =+K80+K83 -> 0 | L77: =+L80+L83 -> 0
B78: % of net pp&e and intangibles excl. Goodwill | E78: =E77/(E111+E114) -> 0.056273334 | F78: =F77/(F111+F114) -> 0.036741569 | G78: =G77/(G111+G114) -> 0.034751229 | H78: =H77/(H111+H114) -> 0 | I78: =I77/(I111+I114) -> 0 | J78: =J77/(J111+J114) -> 0 | K78: =K77/(K111+K114) -> 0 | L78: =L77/(L111+L114) -> 0
B80: Depreciation | E80: =FCFF!H52 -> 0 | F80: =FCFF!N52 -> 0 | G80: =FCFF!T52 -> 0 | H80: =H81*G111 -> 0 | I80: =I81*H111 -> 0 | J80: =J81*I111 -> 0 | K80: =K81*J111 -> 0 | L80: =L81*K111 -> 0
B81: % of net pp&e | E81: =E80/E111 -> 0 | F81: =FCFF!N53 -> 0 | G81: =FCFF!T53 -> 0
B83: Amortization | E83: =FCFF!H55 -> 0 | F83: =FCFF!N55 -> 0 | G83: =FCFF!T55 -> 0 | H83: =H84*G114 -> 0 | I83: =I84*H114 -> 0 | J83: =J84*I114 -> 0 | K83: =K84*J114 -> 0 | L83: =L84*K114 -> 0
B84: % of intangibles excl. goodwill | E84: =E83/E114 -> 0 | F84: =F83/F114 -> 0 | G84: =G83/G114 -> 0
B86: EBIT (Operating Income) | E86: =FCFF!H61 -> 59.023 | F86: =FCFF!N61 -> 95.837 | G86: =FCFF!T61 -> 150.053 | H86: =H68-H71-H74-H77 -> 350000 | I86: =I68-I71-I74-I77 -> 352000 | J86: =J68-J71-J74-J77 -> 350000 | K86: =K68-K71-K74-K77 -> 352000 | L86: =L68-L71-L74-L77 -> 350000
B87: % of sales | E87: =E86/E59 -> 0.15179563 | F87: =F86/F59 -> 0.1718362 | G87: =G86/G59 -> 0.19185468 | H87: =H86/H59 -> 1 | I87: =I86/I59 -> 1 | J87: =J86/J59 -> 1 | K87: =K86/K59 -> 1 | L87: =L86/L59 -> 1
B89: Net Interest (Income) Expense | E89: =IS!T38 -> -7.085 | F89: =IS!Z38 -> -5.673 | G89: =IS!AF38 -> -5.784 | H89: =+H164 -> 0 | I89: =+I164 -> 0 | J89: =+J164 -> 0 | K89: =+K164 -> 0 | L89: =+L164 -> 0
B91: Pre-tax income | E91: =IS!T42 -> 75.205 | F91: =IS!Z42 -> 118.951 | G91: =IS!AF42 -> 164.382 | H91: =+H86-H89 -> 350000 | I91: =+I86-I89 -> 352000 | J91: =+J86-J89 -> 350000 | K91: =+K86-K89 -> 352000 | L91: =+L86-L89 -> 350000
B92: % of sales | E92: =E91/E59 -> 0.19341258 | F92: =F91/F59 -> 0.21327971 | G92: =G91/G59 -> 0.21017545 | H92: =H91/H59 -> 1 | I92: =I91/I59 -> 1 | J92: =J91/J59 -> 1 | K92: =K91/K59 -> 1 | L92: =L91/L59 -> 1
B94: Income tax expenses (benefits) | E94: =IS!T45 -> 16.7955 | F94: =IS!Z45 -> 19.9384 | G94: =IS!AF45 -> 34.6282 | H94: =H95*H91 -> 0 | I94: =I95*I91 -> 0 | J94: =J95*J91 -> 0 | K94: =K95*K91 -> 0 | L94: =L95*L91 -> 0
B95: % tax rate | E95: =E94/E91 -> 0.22332957 | F95: =F94/F91 -> 0.1676186 | G95: =G94/G91 -> 0.21065688
B97: Net income | E97: =IS!T47 -> 58.4095 | F97: =IS!Z47 -> 99.0126 | G97: =IS!AF47 -> 129.7538 | H97: =H91-H94 -> 350000 | I97: =I91-I94 -> 352000 | J97: =J91-J94 -> 350000 | K97: =K91-K94 -> 352000 | L97: =L91-L94 -> 350000
B98: % of sales | E98: =E97/E59 -> 0.15021783 | F98: =F97/F59 -> 0.17753006 | G98: =G97/G59 -> 0.16590054 | H98: =H97/H59 -> 1 | I98: =I97/I59 -> 1 | J98: =J97/J59 -> 1 | K98: =K97/K59 -> 1 | L98: =L97/L59 -> 1
A100: x | B100: Balance Sheet | E100: =E57 -> 2022 | F100: =F57 -> 2023 | G100: =G57 -> 2024 | H100: =H57 -> 2025 | I100: =I57 -> 2026 | J100: =J57 -> 2027 | K100: =K57 -> 2028 | L100: =L57 -> 2029
B102: Accounts Receivable | E102: =FCFF!H70 -> 182.936 | F102: =FCFF!N70 -> 283.186 | G102: =FCFF!T70 -> 387.045 | H102: =+H103*H59/365 -> 0 | I102: =+I103*I59/365 -> 0 | J102: =+J103*J59/365 -> 0 | K102: =+K103*K59/366 -> 0 | L102: =+L103*L59/365 -> 0
B103: days sales outstanding | E103: =FCFF!H71 -> 171.72362 | F103: =FCFF!N71 -> 185.33015 | G103: =FCFF!T71 -> 180.62674
B105: Inventory | E105: =FCFF!H73 -> 393.172 | F105: =FCFF!N73 -> 545.395 | G105: =FCFF!T73 -> 597.984 | H105: =+H106*H62/365 -> 0 | I105: =+I106*I62/365 -> 0 | J105: =+J106*J62/365 -> 0 | K105: =+K106*K62/366 -> 0 | L105: =+L106*L62/365 -> 0
B106: days inventory held | E106: =FCFF!H74 -> 699.29772 | F106: =FCFF!N74 -> 707.15282 | G106: =FCFF!T74 -> 558.84352
B108: Prepaid expenses and Other Current Assets | E108: =FCFF!H76 -> 15.607 | F108: =FCFF!N76 -> 20.023 | G108: =FCFF!T76 -> 7.507 | H108: =+H109*H59 -> 0 | I108: =+I109*I59 -> 0 | J108: =+J109*J59 -> 0 | K108: =+K109*K59 -> 0 | L108: =+L109*L59 -> 0
B109: % of sales | E109: =FCFF!H77 -> 0.040138157 | F109: =FCFF!N77 -> 0.035901335 | G109: =FCFF!T77 -> 0.0095982959
B111: Net PP&E (Property, Plant and Equipment) | E111: =FCFF!H79 -> 94.056 | F111: =FCFF!N79 -> 217.241 | G111: =FCFF!T79 -> 283.31 | H111: =+G111-H112*H131-H80-H65 -> 283.31 | I111: =+H111-I112*I131-I80-I65 -> 283.31 | J111: =+I111-J112*J131-J80-J65 -> 283.31 | K111: =+J111-K112*K131-K80-K65 -> 283.31 | L111: =+K111-L112*L131-L80-L65 -> 283.31
B112: capex allocation rate | E112: =FCFF!H80 -> 0 | F112: =FCFF!N80 -> 0 | G112: =FCFF!T80 -> 0
B114: Intangibles excl. Goodwill | E114: =FCFF!H82 -> 1.3 | F114: =FCFF!N82 -> 3 | G114: =FCFF!T82 -> 3.5 | H114: =+G114+H115*H74-(1-H112)*H131-H83 -> 3.5 | I114: =+H114+I115*I74-(1-I112)*I131-I83 -> 3.5 | J114: =+I114+J115*J74-(1-J112)*J131-J83 -> 3.5 | K114: =+J114+K115*K74-(1-K112)*K131-K83 -> 3.5 | L114: =+K114+L115*L74-(1-L112)*L131-L83 -> 3.5
B115: r&d conversion rate | E115: =FCFF!H83 -> 0.020891589 | F115: =FCFF!N83 -> 0.032359318 | G115: =FCFF!T83 -> 0.033183848
B117: Accounts Payable | E117: =FCFF!H85 -> 171.873 | F117: =FCFF!N85 -> 262.573 | G117: =FCFF!T85 -> 289.863 | H117: =+H118*H62/365 -> 0 | I117: =+I118*I62/365 -> 0 | J117: =+J118*J62/365 -> 0 | K117: =+K118*K62/366 -> 0 | L117: =+L118*L62/365 -> 0
B118: days payable outstanding | E118: =FCFF!H86 -> 305.69419 | F118: =FCFF!N86 -> 340.4491 | G118: =FCFF!T86 -> 270.89029
B120: Accrued Expenses and Other Current Liabilities | E120: =FCFF!H88 -> 164.633 | F120: =FCFF!N88 -> 197.204 | G120: =FCFF!T88 -> 271.952 | H120: =+H121*H71 -> 0 | I120: =+I121*I71 -> 0 | J120: =+J121*J71 -> 0 | K120: =+K121*K71 -> 0 | L120: =+L121*L71 -> 0
B121: % of sg&a | E121: =FCFF!H89 -> 2.6402957 | F121: =FCFF!N89 -> 2.2494667 | G121: =FCFF!T89 -> 2.0132215
A123: x | B123: Cash Flow | E123: =E57 -> 2022 | F123: =F57 -> 2023 | G123: =G57 -> 2024 | H123: =H57 -> 2025 | I123: =I57 -> 2026 | J123: =J57 -> 2027 | K123: =K57 -> 2028 | L123: =L57 -> 2029
B125: D&A (Depreciation & Amortization) | E125: =FCFF!H94 -> 5.366 | F125: =FCFF!N94 -> 8.092 | G125: =FCFF!T94 -> 9.967 | H125: =+H77+H65 -> 0 | I125: =+I77+I65 -> 0 | J125: =+J77+J65 -> 0 | K125: =+K77+K65 -> 0 | L125: =+L77+L65 -> 0
B126: % of net pp&e and intangibles excl. Goodwill | E126: =FCFF!H95 -> 0.056273334 | F126: =FCFF!N95 -> 0.036741569 | G126: =FCFF!T95 -> 0.034751229 | H126: =+H125/(H111+H114) -> 0 | I126: =+I125/(I111+I114) -> 0 | J126: =+J125/(J111+J114) -> 0 | K126: =+K125/(K111+K114) -> 0 | L126: =+L125/(L111+L114) -> 0
B128: Changes in Net Working Capital | E128: =FCFF!H103 -> -138.025 | F128: =FCFF!N103 -> -188.424 | G128: =FCFF!T103 -> -76.47 | H128: =-((H102+H105+H108-H117-H120)-(G102+G105+G108-G117-G120)) -> 430.721 | I128: =-((I102+I105+I108-I117-I120)-(H102+H105+H108-H117-H120)) -> 0 | J128: =-((J102+J105+J108-J117-J120)-(I102+I105+I108-I117-I120)) -> 0 | K128: =-((K102+K105+K108-K117-K120)-(J102+J105+J108-J117-J120)) -> 0 | L128: =-((L102+L105+L108-L117-L120)-(K102+K105+K108-K117-K120)) -> 0
B129: % of change in sales | E129: =FCFF!H104 -> -0.53137428 | F129: =FCFF!N104 -> -0.48458975 | G129: =FCFF!T104 -> -0.13711107 | H129: =H128/(H59-G59) -> 0.0012333876 | I129: =I128/(I59-H59) -> 0 | J129: =J128/(J59-I59) -> 0 | K129: =K128/(K59-J59) -> 0 | L129: =L128/(L59-K59) -> 0
B131: Net CapEx | E131: =FCFF!H106+FCFF!H109 -> -92.64 | F131: =FCFF!N106+FCFF!N109 -> -64.276 | G131: =FCFF!T106+FCFF!T109 -> -85.003 | H131: =-H132*H59 -> 0 | I131: =-I132*I59 -> 0 | J131: =-J132*J59 -> 0 | K131: =-K132*K59 -> 0 | L131: =-L132*L59 -> 0
B132: % of sales | E132: =FCFF!H107 -> 0.23794338 | F132: =FCFF!N107 -> 0.11535834 | G132: =FCFF!T107 -> 0.10989135
A134: x | B134: Levered Free Cash Flow | H134: =H57 -> 2025 | I134: =I57 -> 2026 | J134: =J57 -> 2027 | K134: =K57 -> 2028 | L134: =L57 -> 2029
B136: Net Income | H136: =H97 -> 350000 | I136: =I97 -> 352000 | J136: =J97 -> 350000 | K136: =K97 -> 352000 | L136: =L97 -> 350000
B137: Changes in NWC | H137: =+H125 -> 0 | I137: =+I125 -> 0 | J137: =+J125 -> 0 | K137: =+K125 -> 0 | L137: =+L125 -> 0
B138: D&A (Depreciation & Amortization) | H138: =+H128 -> 430.721 | I138: =+I128 -> 0 | J138: =+J128 -> 0 | K138: =+K128 -> 0 | L138: =+L128 -> 0
B139: Net CapEx | H139: =+H131 -> 0 | I139: =+I131 -> 0 | J139: =+J131 -> 0 | K139: =+K131 -> 0 | L139: =+L131 -> 0
B140: Leveraged Free Cash Flow | H140: =H136+H137+H138+H139 -> 350430.72 | I140: =I136+I137+I138+I139 -> 352000 | J140: =J136+J137+J138+J139 -> 350000 | K140: =K136+K137+K138+K139 -> 352000 | L140: =L136+L137+L138+L139 -> 350000
A142: x | B142: Debt Schedule | H142: =H134 -> 2025 | I142: =I134 -> 2026 | J142: =J134 -> 2027 | K142: =K134 -> 2028 | L142: =L134 -> 2029
B144: Revolver
B145: Beginning Balance | H145: =G148 -> 0 | I145: =H148 -> 0 | J145: =I148 -> 0 | K145: =J148 -> 0 | L145: =K148 -> 0
B146: Interest | H146: =H145*$J$11 -> 0 | I146: =I145*$J$11 -> 0 | J146: =J145*$J$11 -> 0 | K146: =K145*$J$11 -> 0 | L146: =L145*$J$11 -> 0
B147: Paydown | H147: =MIN(H140,H145) -> 0 | I147: =MIN(I140,I145) -> 0 | J147: =MIN(J140,J145) -> 0 | K147: =MIN(K140,K145) -> 0 | L147: =MIN(L140,L145) -> 0
B148: Ending Balance | G148: =L11 -> 0 | H148: =H145-H147 -> 0 | I148: =I145-I147 -> 0 | J148: =J145-J147 -> 0 | K148: =K145-K147 -> 0 | L148: =L145-L147 -> 0
B150: Bank Loan
B151: Beginning Balance | H151: =G154 -> 0 | I151: =H154 -> 0 | J151: =I154 -> 0 | K151: =J154 -> 0 | L151: =K154 -> 0
B152: Interest | H152: =H151*$J$12 -> 0 | I152: =I151*$J$12 -> 0 | J152: =J151*$J$12 -> 0 | K152: =K151*$J$12 -> 0 | L152: =L151*$J$12 -> 0
B153: Paydown | H153: =MIN(H151,H140-H147) -> 0 | I153: =MIN(I151,I140-I147) -> 0 | J153: =MIN(J151,J140-J147) -> 0 | K153: =MIN(K151,K140-K147) -> 0 | L153: =MIN(L151,L140-L147) -> 0
B154: Ending Balance | G154: =L12 -> 0 | H154: =H151-H153 -> 0 | I154: =I151-I153 -> 0 | J154: =J151-J153 -> 0 | K154: =K151-K153 -> 0 | L154: =L151-L153 -> 0
B156: Senior Note
B157: Beginning Balance | H157: =G160 -> 0 | I157: =H160 -> 0 | J157: =I160 -> 0 | K157: =J160 -> 0 | L157: =K160 -> 0
B158: Interest | H158: =H157*$J$13 -> 0 | I158: =I157*$J$13 -> 0 | J158: =J157*$J$13 -> 0 | K158: =K157*$J$13 -> 0 | L158: =L157*$J$13 -> 0
B159: Paydown | H159: =MIN(H157,H140-H147-H153) -> 0 | I159: =MIN(I157,I140-I147-I153) -> 0 | J159: =MIN(J157,J140-J147-J153) -> 0 | K159: =MIN(K157,K140-K147-K153) -> 0 | L159: =MIN(L157,L140-L147-L153) -> 0
B160: Ending Balance | G160: =L13 -> 0 | H160: =H157-H159 -> 0 | I160: =I157-I159 -> 0 | J160: =J157-J159 -> 0 | K160: =K157-K159 -> 0 | L160: =L157-L159 -> 0
B162: Total Debt
B163: Beginning Balance | H163: =H145+H151+H157 -> 0 | I163: =I145+I151+I157 -> 0 | J163: =J145+J151+J157 -> 0 | K163: =K145+K151+K157 -> 0 | L163: =L145+L151+L157 -> 0
B164: Interest | H164: =H146+H152+H158 -> 0 | I164: =I146+I152+I158 -> 0 | J164: =J146+J152+J158 -> 0 | K164: =K146+K152+K158 -> 0 | L164: =L146+L152+L158 -> 0
B165: Paydown | H165: =H147+H153+H159 -> 0 | I165: =I147+I153+I159 -> 0 | J165: =J147+J153+J159 -> 0 | K165: =K147+K153+K159 -> 0 | L165: =L147+L153+L159 -> 0
...

Sheet Sensitivity
B7: Monte-Carlo Simulations | R7: Tornado Chart – Effect on Price Target
AD28: {=_xlfn.SORTBY(R38:Z44,Z38:Z44,1)} -> COGS Margin | AE28: 0 | AF28: 0.05 | AG28: 0 | AH28: 41.931285 | AI28: 41.955616 | AJ28: -0.012135362 | AK28: 0.012195723 | AL28: 0.012195723
AD29: SG&A Margin | AE29: 0 | AF29: 0.1 | AG29: 0 | AH29: 41.583579 | AI29: 42.227819 | AJ29: -0.35984057 | AK29: 0.28439904 | AL29: 0.35984057
AD30: Capex Intensity | AE30: 0 | AF30: 0.02 | AG30: 0 | AH30: 40.668414 | AI30: 43.218426 | AJ30: -1.275006 | AK30: 1.275006 | AL30: 1.275006
AD31: WACC | AE31: 0 | AF31: 0.005 | AG31: 0 | AH31: 40.068865 | AI31: 43.919771 | AJ31: -1.8745552 | AK31: 1.9763509 | AL31: 1.9763509
R32: Reference Price Target | V32: Base Price Target | Z32: Reference | AD32: EBITDA Exit | AE32: 0 | AF32: 1 | AG32: 0 | AH32: 39.884347 | AI32: 44.002493 | AJ32: -2.0590728 | AK32: 2.0590728 | AL32: 2.0590728
R33: Gordon PT | T33: =+FCFF!AL169 -> 39.981829 | V33: Base Gordon PT | X33: 40.003571 | Z33: EBITDA | AD33: Terminal g | AE33: 0 | AF33: 0.005 | AG33: 0 | AH33: 35.803519 | AI33: 45.412066 | AJ33: -6.1399008 | AK33: 3.4686457 | AL33: 6.1399008
R34: EBITDA PT | T34: =+FCFF!Z169 -> 41.952652 | V34: Base EBITDA PT | X34: 41.94342 | AD34: Revenue Exit | AE34: 0 | AF34: 1 | AG34: 0 | AH34: 34.548417 | AI34: 57.768295 | AJ34: -7.3950031 | AK34: 15.824875 | AL34: 15.824875
R35: Revenue PT | T35: =FCFF!AF169 -> 46.167588 | V35: Base Revenue PT | X35: 46.158356
T37: Δ | U37: Δ Applied | V37: PT Low | W37: PT High | X37: Δ Low | Y37: Δ High | Z37: Max
R38: Capex Intensity | T38: 0.02 | V38: 40.668414 | W38: 43.218426 | X38: {=+V38-_xlfn.IFS($Z$33="EBITDA",$X$34,$Z$33="Revenue",$X$35,$Z$33="Gordon",$X$33)} -> -1.275006 | Y38: {=+W38-_xlfn.IFS($Z$33="EBITDA",$X$34,$Z$33="Revenue",$X$35,$Z$33="Gordon",$X$33)} -> 1.275006 | Z38: =MAX(ABS(X38),ABS(Y38)) -> 1.275006
R39: COGS Margin | T39: 0.05 | V39: 41.931285 | W39: 41.955616 | X39: {=+V39-_xlfn.IFS($Z$33="EBITDA",$X$34,$Z$33="Revenue",$X$35,$Z$33="Gordon",$X$33)} -> -0.012135362 | Y39: {=+W39-_xlfn.IFS($Z$33="EBITDA",$X$34,$Z$33="Revenue",$X$35,$Z$33="Gordon",$X$33)} -> 0.012195723 | Z39: =MAX(ABS(X39),ABS(Y39)) -> 0.012195723
R40: SG&A Margin | T40: 0.1 | V40: 41.583579 | W40: 42.227819 | X40: {=+V40-_xlfn.IFS($Z$33="EBITDA",$X$34,$Z$33="Revenue",$X$35,$Z$33="Gordon",$X$33)} -> -0.35984057 | Y40: {=+W40-_xlfn.IFS($Z$33="EBITDA",$X$34,$Z$33="Revenue",$X$35,$Z$33="Gordon",$X$33)} -> 0.28439904 | Z40: =MAX(ABS(X40),ABS(Y40)) -> 0.35984057
F41: Historical VaR | H41: Parametric VaR | J41: Monte Carlos VaR -Yearly | R41: WACC | T41: 0.005 | V41: 40.068865 | W41: 43.919771 | X41: {=+V41-_xlfn.IFS($Z$33="EBITDA",$X$34,$Z$33="Revenue",$X$35,$Z$33="Gordon",$X$33)} -> -1.8745552 | Y41: {=+W41-_xlfn.IFS($Z$33="EBITDA",$X$34,$Z$33="Revenue",$X$35,$Z$33="Gordon",$X$33)} -> 1.9763509 | Z41: =MAX(ABS(X41),ABS(Y41)) -> 1.9763509
C42: Confidence Level 95.0% | F42: 0.0624 | H42: 0.0734 | J42: 0.62891 | R42: Terminal g | T42: 0.005 | V42: 35.803519 | W42: 45.412066 | X42: {=+V42-_xlfn.IFS($Z$33="EBITDA",$X$34,$Z$33="Revenue",$X$35,$Z$33="Gordon",$X$33)} -> -6.1399008 | Y42: {=+W42-_xlfn.IFS($Z$33="EBITDA",$X$34,$Z$33="Revenue",$X$35,$Z$33="Gordon",$X$33)} -> 3.4686457 | Z42: =MAX(ABS(X42),ABS(Y42)) -> 6.1399008
C43: Confidence Level 99.0% | F43: 0.1094 | H43: 0.1048 | J43: 0.7608 | R43: EBITDA Exit | T43: 1 | V43: 39.884347 | W43: 44.002493 | X43: {=+V43-_xlfn.IFS($Z$33="EBITDA",$X$34,$Z$33="Revenue",$X$35,$Z$33="Gordon",$X$33)} -> -2.0590728 | Y43: {=+W43-_xlfn.IFS($Z$33="EBITDA",$X$34,$Z$33="Revenue",$X$35,$Z$33="Gordon",$X$33)} -> 2.0590728 | Z43: =MAX(ABS(X43),ABS(Y43)) -> 2.0590728
R44: Revenue Exit | T44: 1 | V44: 34.548417 | W44: 57.768295 | X44: {=+V44-_xlfn.IFS($Z$33="EBITDA",$X$34,$Z$33="Revenue",$X$35,$Z$33="Gordon",$X$33)} -> -7.3950031 | Y44: {=+W44-_xlfn.IFS($Z$33="EBITDA",$X$34,$Z$33="Revenue",$X$35,$Z$33="Gordon",$X$33)} -> 15.824875 | Z44: =MAX(ABS(X44),ABS(Y44)) -> 15.824875

Sheet IS
B7: Income Statement | D7: 2020 | E7: 2020 | F7: 2020 | G7: 2020 | H7: 2020 | J7: 2021 | K7: 2021 | L7: 2021 | M7: 2021 | N7: 2021 | P7: 2022 | Q7: 2022 | R7: 2022 | S7: 2022 | T7: 2022 | V7: 2023 | W7: 2023 | X7: 2023 | Y7: 2023 | Z7: 2023 | AB7: 2024 | AC7: 2024 | AD7: 2024 | AE7: 2024 | AF7: 2024 | AH7: 2025 | AI7: 2025 | AJ7: 2025 | AK7: 2025 | AL7: 2025 | AN7: 2025 | AO7: 2025 | AP7: 2025 | AQ7: 2025 | AR7: 2025
D8: 2020 | J8: 2021 | P8: 2022 | V8: 2023 | AB8: 2024 | AH8: 2025 | AN8: 2026 | AT8: 2027 | AV8: 2028 | AX8: 2029
D9: Q1 | E9: Q2 | F9: Q3 | G9: Q4 | H9: FY | J9: Q1 | K9: Q2 | L9: Q3 | M9: Q4 | N9: FY | P9: Q1 | Q9: Q2 | R9: Q3 | S9: Q4 | T9: FY | V9: Q1 | W9: Q2 | X9: Q3 | Y9: Q4 | Z9: FY | AB9: Q1 | AC9: Q2 | AD9: Q3 | AE9: Q4 | AF9: FY | AH9: Q1 | AI9: Q2 | AJ9: Q3 | AK9: Q4 | AL9: FY | AN9: Q1 | AO9: Q2 | AP9: Q3 | AQ9: Q4 | AR9: FY | AT9: FY | AV9: FY | AX9: FY
B12: Revenue:
B13: Segment 1 | D13: 0 | E13: 0 | F13: 0 | G13: 0 | H13: 0 | J13: 0 | K13: 0 | L13: 0 | M13: 0 | N13: 0 | P13: 0 | Q13: 0 | R13: 0 | S13: 0 | T13: 0 | V13: 0 | W13: 0 | X13: 0 | Y13: 0 | Z13: 0 | AB13: 0 | AC13: 0 | AD13: 0 | AE13: 0 | AF13: 0 | AH13: 0 | AI13: 0 | AJ13: 0 | AK13: 0 | AL13: 0 | AN13: 0 | AO13: 0 | AP13: 0 | AQ13: 0 | AR13: 0 | AT13: 0 | AV13: 0 | AX13: 0
B14: Segment 2 | D14: 0 | E14: 0 | F14: 0 | G14: 0 | H14: 0 | J14: 0 | K14: 0 | L14: 0 | M14: 0 | N14: 0 | P14: 0 | Q14: 0 | R14: 0 | S14: 0 | T14: 0 | V14: 0 | W14: 0 | X14: 0 | Y14: 0 | Z14: 0 | AB14: 0 | AC14: 0 | AD14: 0 | AE14: 0 | AF14: 0 | AH14: 0 | AI14: 0 | AJ14: 0 | AK14: 0 | AL14: 0 | AN14: 0 | AO14: 0 | AP14: 0 | AQ14: 0 | AR14: 0 | AT14: 0 | AV14: 0 | AX14: 0
B15: Segment 3 | D15: 0 | E15: 0 | F15: 0 | G15: 0 | H15: 0 | J15: 0 | K15: 0 | L15: 0 | M15: 0 | N15: 0 | P15: 0 | Q15: 0 | R15: 0 | S15: 0 | T15: 0 | V15: 0 | W15: 0 | X15: 0 | Y15: 0 | Z15: 0 | AB15: 0 | AC15: 0 | AD15: 0 | AE15: 0 | AF15: 0 | AH15: 0 | AI15: 0 | AJ15: 0 | AK15: 0 | AL15: 0 | AN15: 0 | AO15: 0 | AP15: 0 | AQ15: 0 | AR15: 0 | AT15: 0 | AV15: 0 | AX15: 0
B16: Segment 4 | D16: 0 | E16: 0 | F16: 0 | G16: 0 | H16: 0 | J16: 0 | K16: 0 | L16: 0 | M16: 0 | N16: 0 | P16: 0 | Q16: 0 | R16: 0 | S16: 0 | T16: 0 | V16: 0 | W16: 0 | X16: 0 | Y16: 0 | Z16: 0 | AB16: 0 | AC16: 0 | AD16: 0 | AE16: 0 | AF16: 0 | AH16: 0 | AI16: 0 | AJ16: 0 | AK16: 0 | AL16: 0 | AN16: 0 | AO16: 0 | AP16: 0 | AQ16: 0 | AR16: 0 | AT16: 0 | AV16: 0 | AX16: 0
B17: Segment 5 | D17: 0 | E17: 0 | F17: 0 | G17: 0 | H17: 0 | J17: 0 | K17: 0 | L17: 0 | M17: 0 | N17: 0 | P17: 0 | Q17: 0 | R17: 0 | S17: 0 | T17: 0 | V17: 0 | W17: 0 | X17: 0 | Y17: 0 | Z17: 0 | AB17: 0 | AC17: 0 | AD17: 0 | AE17: 0 | AF17: 0 | AH17: 0 | AI17: 0 | AJ17: 0 | AK17: 0 | AL17: 0 | AN17: 0 | AO17: 0 | AP17: 0 | AQ17: 0 | AR17: 0 | AT17: 0 | AV17: 0 | AX17: 0
B18: Total revenue | D18: 24.348 | E18: 39.049 | F18: 47.665 | G18: 45.562 | H18: 156.624 | I18: #N/A Start Date | J18: 43.732 | K18: 53.864 | L18: 67.013 | M18: 95.142 | N18: 259.751 | O18: #N/A Start Date | P18: 42.186 | Q18: 104.395 | R18: 133.709 | S18: 108.542 | T18: 388.832 | U18: #N/A Start Date | V18: 74.256 | W18: 144.577 | X18: 168.569 | Y18: 170.321 | Z18: 557.723 | AA18: #N/A Start Date | AB18: 152.191 | AC18: 202.48 | AD18: 203.976 | AE18: 223.471 | AF18: 782.118 | AG18: #N/A Start Date | AH18: 172.347 | AI18: 215.372 | AJ18: =FCFF!X31 -> 254.04267 | AK18: =FCFF!Y31 -> 304.85121 | AL18: =FCFF!Z31 -> 946.61288 | AM18: =FCFF!AA31 -> 0 | AN18: =FCFF!AB31 -> 206.8164 | AO18: =FCFF!AC31 -> 258.4464 | AP18: =FCFF!AD31 -> 304.85121 | AQ18: =FCFF!AE31 -> 365.82145 | ... AX18: =FCFF!AL31 -> 1803.4553
A20: x | B20: Cost of revenue:
B21: Cost of goods and services | D21: 0 | E21: 19.693 | F21: 27.324 | G21: 25.888 | H21: 87.025 | I21: #N/A Start Date | J21: 25.687 | K21: 32.184 | L21: 37.328 | M21: 49.696 | N21: 144.895 | O21: #N/A Start Date | P21: 22.5 | Q21: 60.238 | R21: 67.742 | S21: 54.737 | T21: 205.217 | U21: #N/A Start Date | V21: 34.27 | W21: 75.938 | X21: 80.055 | Y21: 91.245 | Z21: 281.508 | AA21: #N/A Start Date | AB21: 73.07 | AC21: 105.696 | AD21: 99.142 | AE21: 112.656 | AF21: 390.564 | AG21: #N/A Start Date | AH21: 89.797 | AI21: 110.911 | AJ21: 8750 | AK21: 9500 | AL21: 25476.6 | AN21: 7260 | AO21: 7920 | AP21: 7480 | AQ21: 6160 | AR21: 28820 | AT21: 32400 | AV21: 26100 | AX21: 33600
B22: Depreciation & amortization | D22: 0 | E22: 0 | F22: 0 | G22: 0 | H22: 0 | J22: 0 | K22: 0 | L22: 0 | M22: 0 | N22: 0 | P22: 0 | Q22: 0 | R22: 0 | S22: 0 | T22: 0 | V22: 0 | W22: 0 | X22: 0 | Y22: 0 | Z22: 0 | AB22: 0 | AC22: 0 | AD22: 0 | AE22: 0 | AF22: 0 | AH22: 0 | AI22: 0 | AJ22: 3267 | AK22: 3801.6 | AL22: 3366 | AN22: 13391.4 | AO22: 0 | AP22: 15552 | AQ22: 0 | AR22: 12528 | AT22: 16128 | AV22: 0 | AX22: 0
B23: Total cost of revenue | D23: 14.12 | E23: 19.693 | F23: 27.324 | G23: 25.888 | H23: 87.025 | J23: 25.687 | K23: 32.184 | L23: 37.328 | M23: 49.696 | N23: 144.895 | P23: 22.5 | Q23: 60.238 | R23: 67.742 | S23: 54.737 | T23: 205.217 | U23: #N/A Start Date | V23: 34.27 | W23: 75.938 | X23: 80.055 | Y23: 91.245 | Z23: 281.508 | AA23: #N/A Start Date | AB23: 73.07 | AC23: 105.696 | AD23: 99.142 | AE23: 112.656 | AF23: 390.564 | AG23: #N/A Start Date | AH23: 89.797 | AI23: 110.911 | AJ23: 11875 | AK23: 10750 | AL23: 23184.165 | AN23: 11473 | AO23: 10278.4 | AP23: 11154 | AQ23: 12883.2 | AR23: 45788.6 | AT23: 42048 | AV23: 48372 | AX23: 55272
B24: Gross margin | D24: 10.228 | E24: 19.356 | F24: 20.341 | G24: 19.674 | H24: 69.599 | I24: #N/A Start Date | J24: 18.045 | K24: 21.68 | L24: 29.685 | M24: 45.446 | N24: 114.856 | O24: #N/A Start Date | P24: 19.686 | Q24: 44.157 | R24: 65.967 | S24: 53.805 | T24: 183.615 | U24: #N/A Start Date | V24: 39.986 | W24: 68.639 | X24: 88.514 | Y24: 79.076 | Z24: 276.215 | AA24: #N/A Start Date | AB24: 79.121 | AC24: 96.784 | AD24: 104.834 | AE24: 110.815 | AF24: 391.554 | AG24: #N/A Start Date | AH24: 82.55 | AI24: 104.461 | AJ24: 11875 | AK24: 10750 | AL24: 23184.165 | AN24: 11473 | AO24: 10278.4 | AP24: 11154 | AQ24: 12883.2 | AR24: 45788.6 | AT24: 42048 | AV24: 48372 | AX24: 55272
A26: x | B26: Operating expenses:
B27: Selling, general and administrative | D27: 5.333 | E27: 6.799 | F27: 8.492 | G27: 8.364 | H27: 28.988 | I27: 188.535 | J27: 25.687 | K27: 32.184 | L27: 37.328 | M27: 49.696 | N27: 41.947 | O27: #N/A Start Date | P27: 11.646 | Q27: 12.755 | R27: 18.653 | S27: 19.3 | T27: 62.354 | U27: 17.095 | V27: 17.095 | W27: 18.145 | X27: 29.19 | Y27: 23.237 | Z27: 87.667 | AA27: 33.223 | AB27: 29.971 | AC27: 33.223 | AD27: 32.813 | AE27: 39.076 | AF27: 135.083 | AG27: #N/A Start Date | AH27: 29.27 | AI27: 38.95 | AJ27: 1375 | AK27: 1250 | AL27: 2705.513 | AN27: 1210 | AO27: 1100 | AP27: 1210 | AQ27: 1100 | AR27: 4620 | AT27: 4500 | AV27: 4350 | AX27: 5250
B28: Depreciation and amortization | O28: =FCFF!C49 -> 0 | P28: 1.213 | Q28: 1.342 | R28: 1.549 | S28: 1.262 | T28: 5.366 | U28: 0 | V28: 1.714 | W28: 2.241 | X28: 2.066 | Y28: 2.071 | Z28: 8.092 | AA28: 0 | AB28: 2.518 | AC28: 2.166 | AD28: 2.389 | AE28: 2.894 | AF28: 9.967 | AG28: 0 | AH28: 3.017 | AI28: 3.339 | AJ28: 3.3570789 | AK28: 3.3665353 | AL28: 13.079614 | AN28: 3.2981235 | AO28: 3.3418524 | AP28: 3.349621 | AQ28: 3.3455094 | AR28: 13.335106 | AT28: 12.499356 | AV28: 13.150888 | AX28: 13.263186
B29: Research and development | D29: 3.677 | E29: 5.221 | F29: 4.343 | G29: 5.878 | H29: 19.119 | J29: 5.504 | K29: 7.933 | L29: 7.856 | M29: 12.914 | N29: 34.207 | O29: #N/A Start Date | P29: 17.346 | Q29: 11.367 | R29: 15.678 | S29: 17.835 | T29: 62.226 | U29: #N/A Start Date | V29: 14.029 | W29: 20.064 | X29: 26.151 | Y29: 32.465 | Z29: 92.709 | AA29: #N/A Start Date | AB29: 23.918 | AC29: 25.968 | AD29: 27.837 | AE29: 27.75 | AF29: 105.473 | AG29: #N/A Start Date | AH29: 27.503 | AI29: 33.817 | AJ29: =FCFF!X49 -> 3.3570789 | AK29: 1935 | AL29: 4072.5 | AN29: 1835.68 | AO29: 1850.112 | AP29: 1896.18 | AQ29: 2447.808 | AR29: 8029.78 | AT29: 8409.6 | AV29: 8706.96 | AX29: 8843.52
B30: Other operating expenses | D30: 0 | E30: -0.001 | F30: 0 | G30: 0 | H30: 0 | I30: #VALUE! | J30: -16.596 | K30: -22.768 | L30: -27.294 | M30: -36.29 | N30: 0 | O30: #VALUE! | P30: -10.854 | Q30: -47.483 | R30: -49.089 | S30: -35.437 | T30: 0.012 | U30: #VALUE! | V30: -17.175 | W30: -57.793 | X30: -50.865 | Y30: -68.008 | Z30: 0.002 | AA30: #VALUE! | AB30: -43.099 | AC30: -72.473 | AD30: -66.329 | AE30: -73.58 | AF30: 0.945 | AG30: #VALUE! | AH30: -60.527 | AI30: -71.961 | AJ30: 25 | AK30: 25 | AL30: 27.883 | AN30: 22 | AO30: 22 | AP30: 22 | AQ30: 22 | AR30: 88 | AT30: 90 | AV30: 87 | AX30: 105
B31: Total operating expenses | D31: 9.01 | E31: 12.019 | F31: 12.835 | G31: 14.242 | H31: 48.107 | I31: #N/A Start Date | J31: 14.595 | K31: 17.349 | L31: 17.89 | M31: 26.32 | N31: 76.154 | O31: #N/A Start Date | P31: 28.992 | Q31: 24.122 | R31: 34.331 | S31: 37.135 | T31: 124.592 | U31: #N/A Start Date | V31: 31.124 | W31: 38.209 | X31: 55.341 | Y31: 55.702 | Z31: 180.378 | AA31: #N/A Start Date | AB31: 53.889 | AC31: 59.191 | AD31: 60.65 | AE31: 66.826 | AF31: 241.501 | AG31: #N/A Start Date | AH31: 56.773 | AI31: 72.767 | AJ31: 3921.9902 | AK31: 3794.5301 | AL31: 7774.9163 | AN31: 3822.726 | AO31: 3827.4713 | AP31: 4075.4215 | AQ31: 4603.1332 | AR31: 16328.752 | AT31: 14101.237 | AV31: 14609.735 | AX31: 16117.012
B32: Other operating income | D32: 0 | E32: 0 | F32: 0 | G32: 0 | H32: 0 | I32: #N/A Start Date | J32: 0 | K32: 0 | L32: 0 | M32: 0 | N32: 0 | O32: #N/A Start Date | P32: 0 | Q32: 0 | R32: 0 | S32: 0 | T32: 0 | U32: #N/A Start Date | V32: 0 | W32: 0 | X32: 0 | Y32: 0 | Z32: 0 | AA32: #N/A Start Date | AB32: 0 | AC32: 0 | AD32: 0 | AE32: 0 | AF32: 0 | AG32: #N/A Start Date | AH32: 0 | AI32: 0
B33: Operating income | D33: 1.218 | E33: 7.337 | F33: 7.506 | G33: 5.432 | H33: 21.492 | I33: #N/A Start Date | J33: 3.45 | K33: 4.331 | L33: 11.795 | M33: 19.126 | N33: 38.702 | O33: #N/A Start Date | P33: -9.306 | Q33: 20.035 | R33: 31.636 | S33: 16.67 | T33: 59.023 | U33: #N/A Start Date | V33: 8.862 | W33: 30.43 | X33: 33.173 | Y33: 23.374 | Z33: 95.837 | AA33: #N/A Start Date | AB33: 25.232 | AC33: 37.593 | AD33: 44.184 | AE33: 43.989 | AF33: 150.053 | AG33: #N/A Start Date | AH33: 25.777 | AI33: 31.694 | AJ33: =FCFF!X61 -> 43.187254 | AK33: =FCFF!Y61 -> 51.824705 | AL33: =FCFF!Z61 -> 152.48296 | AM33: =FCFF!AA61 -> 0 | AN33: =FCFF!AB61 -> 35.158788 | AO33: =FCFF!AC61 -> 43.935888 | AP33: =FCFF!AD61 -> 51.824705 | AQ33: =FCFF!AE61 -> 62.189646 | ... AX33: =FCFF!AL61 -> 306.5874
A35: x | B35: Non-operating (income) loss:
B36: Interest expense | D36: 0.111 | E36: 0.228 | F36: 0.272 | G36: 0.371 | H36: 0 | I36: #N/A Start Date | J36: 0.189 | K36: 0.194 | L36: 0.191 | M36: 0.191 | N36: 0.765 | O36: #N/A Start Date | P36: 0.261 | Q36: 0.306 | R36: 0.419 | S36: 0.669 | T36: 1.655 | U36: #N/A Start Date | V36: 0.695 | W36: 0.649 | X36: 0.64 | Y36: 0.697 | Z36: 180.378 | AA36: #N/A Start Date | AB36: 0.783 | AC36: 0.932 | AD36: 1.208 | AE36: 1.228 | AF36: 241.501 | AG36: #N/A Start Date | AH36: 1.558 | AI36: 1.757
B37: Interest income | D37: 0.335 | E37: 0.32 | F37: 0.179 | G37: 0.063 | H37: 0.897 | I37: #N/A Start Date | J37: 0.049 | K37: 0.031 | L37: 0.033 | M37: 0.392 | N37: 0.505 | O37: #N/A Start Date | P37: 1.805 | Q37: 2.144 | R37: 2.016 | S37: 2.775 | T37: 8.74 | U37: #N/A Start Date | V37: 1.785 | W37: 2.346 | X37: 2.152 | Y37: 2.071 | Z37: 8.354 | AA37: #N/A Start Date | AB37: 1.774 | AC37: 2.381 | AD37: 2.967 | AE37: 2.813 | AF37: 9.935 | AG37: #N/A Start Date | AH37: 3.339 | AI37: 4.013
A38: x | B38: Net interest (income) expense | D38: -0.224 | E38: -0.092 | F38: 0.093 | G38: 0.308 | H38: 0.085 | I38: #N/A Start Date | J38: 0.14 | K38: 0.163 | L38: 0.158 | M38: -0.201 | N38: 0.26 | O38: #N/A Start Date | P38: -1.544 | Q38: -1.838 | R38: -1.597 | S38: -2.106 | T38: -7.085 | U38: #N/A Start Date | V38: -1.09 | W38: -1.697 | X38: -1.512 | Y38: -1.374 | Z38: -5.673 | AA38: #N/A Start Date | AB38: -0.991 | AC38: -1.449 | AD38: -1.759 | AE38: -1.585 | AF38: -5.784 | AG38: #N/A Start Date | AH38: -1.781 | AI38: -2.256
B39: Foreign exchange (gains) losses | D39: 0 | E39: 0 | F39: 0 | G39: 0 | H39: 0 | I39: #N/A Start Date | J39: 0 | K39: 0 | L39: 0 | M39: 0 | N39: 0 | O39: #N/A Start Date | P39: 0 | Q39: 0 | R39: 0 | S39: 0 | T39: 0 | U39: #N/A Start Date | V39: 0 | W39: 0 | X39: 0 | Y39: 0 | Z39: 0 | AA39: #N/A Start Date | AB39: 0 | AC39: 0 | AD39: 0 | AE39: 0 | AF39: 0 | AG39: #N/A Start Date | AH39: 0 | AI39: 0
B40: Other non-operating (income) expenses | D40: -0.825 | E40: 5.073 | F40: 8.11 | G40: 2.328 | H40: 14.686 | I40: #VALUE! | J40: 0.258 | K40: -3.181 | L40: -0.166 | M40: -3.653 | N40: -4.006 | O40: #VALUE! | P40: -0.166 | Q40: -2.977 | R40: -14.875 | S40: 3.64 | T40: -9.097 | U40: #VALUE! | V40: 1.45 | W40: -7.644 | X40: 2.31 | Y40: -4.988 | Z40: -17.441 | AA40: #VALUE! | AB40: -2.56 | AC40: -0.662 | AD40: 3.848 | AE40: -8.727 | AF40: -8.545 | AG40: #VALUE! | AH40: -0.69 | AI40: -1.427
B41: Total non-operating expenses | D41: -1.049 | E41: 4.981 | F41: 8.203 | G41: 2.636 | H41: 14.771 | I41: #N/A Start Date | J41: 0.398 | K41: -3.018 | L41: -0.008 | M41: -3.854 | N41: -3.746 | O41: #N/A Start Date | P41: -1.71 | Q41: -4.815 | R41: -16.472 | S41: 1.534 | T41: -16.182 | U41: #N/A Start Date | V41: 0.36 | W41: -9.341 | X41: 0.798 | Y41: -6.362 | Z41: -23.114 | AA41: #N/A Start Date | AB41: -3.551 | AC41: -2.111 | AD41: 2.089 | AE41: -10.312 | AF41: -14.329 | AG41: #N/A Start Date | AH41: -2.471 | AI41: -3.683
B42: Pre-tax income | D42: 2.267 | E42: 2.356 | F42: -0.697 | G42: 2.796 | H42: 6.721 | I42: #N/A Start Date | J42: 3.052 | K42: 7.349 | L42: 11.803 | M42: 22.98 | N42: 42.448 | O42: #N/A Start Date | P42: -7.596 | Q42: 24.85 | R42: 48.108 | S42: 15.136 | T42: 75.205 | U42: #N/A Start Date | V42: 8.502 | W42: 39.771 | X42: 32.375 | Y42: 29.736 | Z42: 118.951 | AA42: #N/A Start Date | AB42: 28.783 | AC42: 39.704 | AD42: 42.095 | AE42: 54.301 | AF42: 164.382 | AG42: #N/A Start Date | AH42: 28.248 | AI42: 35.377
A44: x | B44: Tax & net income:
B45: Income tax expenses (benefits) | D45: 0.304 | E45: 1.8592 | F45: -3.6307 | G45: -3.5548 | H45: -5.0225 | I45: #N/A Start Date | J45: -2.77 | K45: 0.015 | L45: -0.073 | M45: 3.4091 | N45: 0.0065 | O45: #N/A Start Date | P45: -4.011 | Q45: 7.679 | R45: 11.579 | S45: 2.66 | T45: 16.7955 | U45: #N/A Start Date | V45: 2.1776 | W45: 6.815 | X45: 0.8572 | Y45: 7.7739 | Z45: 19.9384 | AA45: #N/A Start Date | AB45: 4.8566 | AC45: 9.1195 | AD45: 3.9711 | AE45: 17.319 | AF45: 34.6282 | AG45: #N/A Start Date | AH45: 2.3802 | AI45: 1.3064
B46: Net extraordinary losses (gains) | D46: 0 | E46: 0 | F46: 0 | G46: 0 | H46: 0 | I46: #VALUE! | J46: 0 | K46: 0 | L46: 0 | M46: 0 | N46: 0 | O46: #VALUE! | P46: 0 | Q46: 0 | R46: 0 | S46: 0 | T46: 0 | U46: #VALUE! | V46: 0 | W46: 0 | X46: 0 | Y46: 0 | Z46: 0 | AA46: #VALUE! | AB46: 0 | AC46: 0 | AD46: 0 | AE46: 0 | AF46: 0 | AG46: #VALUE! | AH46: 0 | AI46: 0
B47: Net income including minority interest | D47: 1.963 | E47: 0.4968 | F47: 2.9337 | G47: 6.3508 | H47: 11.7435 | I47: #N/A Start Date | J47: 5.822 | K47: 7.334 | L47: 11.876 | M47: 19.5709 | N47: 42.4415 | O47: #N/A Start Date | P47: -3.585 | Q47: 17.171 | R47: 36.529 | S47: 12.476 | T47: 58.4095 | U47: #N/A Start Date | V47: 6.3244 | W47: 32.956 | X47: 31.5178 | Y47: 21.9621 | Z47: 99.0126 | AA47: #N/A Start Date | AB47: 23.9264 | AC47: 30.5845 | AD47: 38.1239 | AE47: 36.982 | AF47: 129.7538 | AG47: #N/A Start Date | AH47: 25.8678 | AI47: 34.0706
A49: x | B49: Attribution:
B50: Preferred dividends | D50: 0 | E50: 0 | F50: 0 | G50: 0 | H50: 0 | I50: #N/A Start Date | J50: 0 | K50: 0 | L50: 0 | M50: 0 | N50: 0 | O50: #N/A Start Date | P50: 0 | Q50: 0 | R50: 0 | S50: 0 | T50: 0 | U50: #N/A Start Date | V50: 0 | W50: 0 | X50: 0 | Y50: 0 | Z50: 0 | AA50: #N/A Start Date | AB50: 0 | AC50: 0 | AD50: 0 | AE50: 0 | AF50: 0 | AG50: #N/A Start Date | AH50: 0 | AI50: 0
B51: Income attributable to non-controlling interests | D51: 0.258 | E51: 0.577 | F51: 1.393 | G51: 0.669 | H51: 2.897 | I51: #N/A Start Date | J51: 0.352 | K51: 0.767 | L51: 0.995 | M51: 3.05 | N51: 5.164 | O51: #N/A Start Date | P51: -1.657 | Q51: 4.512 | R51: 6.072 | S51: 2.374 | T51: 11.301 | U51: #N/A Start Date | V51: 1.818 | W51: 6.772 | X51: 5.315 | Y51: 5.598 | Z51: 19.503 | AA51: #N/A Start Date | AB51: 4.659 | AC51: 7.189 | AD51: 7.768 | AE51: 8.026 | AF51: 27.642 | AG51: #N/A Start Date | AH51: 4.633 | AI51: 6.51
B52: Net income attributable to common shareholders | D52: 1.705 | E52: -0.0802 | F52: 1.5407 | G52: 5.6818 | H52: 8.8465 | I52: #N/A Start Date | J52: 5.47 | K52: 6.567 | L52: 10.881 | M52: 16.5209 | N52: 37.2775 | O52: #N/A Start Date | P52: -1.928 | Q52: 12.659 | R52: 30.457 | S52: 10.102 | T52: 47.1085 | U52: #N/A Start Date | V52: 4.5064 | W52: 26.184 | X52: 26.2028 | Y52: 16.3641 | Z52: 79.5096 | AA52: #N/A Start Date | AB52: 19.2674 | AC52: 23.3955 | AD52: 30.3559 | AE52: 28.956 | AF52: 102.1118 | AG52: #N/A Start Date | AH52: 21.2348 | AI52: 27.5606
A54: x | B54: Earnings per share:
B55: EPS basic | D55: 0.03 | E55: -0.0015 | F55: 0.0282 | G55: 0.1021 | H55: 0.1617 | I55: #N/A Start Date | J55: 0.0967 | K55: 0.1133 | L55: 0.1867 | M55: 0.282 | N55: 0.6466 | O55: #N/A Start Date | P55: -0.0328 | Q55: 0.2139 | R55: 0.5131 | S55: 0.1704 | T55: 1.3215 | U55: #N/A Start Date | V55: 0.0754 | W55: 0.4371 | X55: 0.4351 | Y55: 0.2692 | Z55: 1.3215 | AA55: #N/A Start Date | AB55: 0.314 | AC55: 0.3763 | AD55: 0.4857 | AE55: 0.4611 | AF55: 1.6413 | AG55: #N/A Start Date | AH55: 0.3356 | AI55: 0.4308
B56: EPS diluted | D56: 0.0267 | E56: -0.0015 | F56: 0.0237 | G56: 0.0865 | H56: 0.1404 | I56: #N/A Start Date | J56: 0.0833 | K56: 0.1 | L56: 0.1643 | M56: 0.2477 | N56: 0.5693 | O56: #N/A Start Date | P56: -0.0415 | Q56: 0.1865 | R56: 0.4641 | S56: 0.1534 | T56: 0.7101 | U56: #N/A Start Date | V56: 0.0694 | W56: 0.4001 | X56: 0.398 | Y56: 0.2397 | Z56: 1.1933 | AA56: #N/A Start Date | AB56: 0.2877 | AC56: 0.3379 | AD56: 0.4418 | AE56: 0.4281 | AF56: 1.5071 | AG56: #N/A Start Date | AH56: 0.3128 | AI56: 0.4074
A58: x | B58: Shares used in computing earnings per share:
B59: Basic weighted average shares | D59: 54.3611 | E59: 54.1525 | F59: 54.6058 | G59: 55.6713 | H59: 54.7001 | I59: #N/A Start Date | J59: 56.3606 | K59: 57.371 | L59: 58.2676 | M59: 58.5884 | N59: 57.6547 | O59: #N/A Start Date | P59: 58.8274 | Q59: 59.1776 | R59: 59.3608 | S59: 59.2686 | T59: 59.236 | U59: #N/A Start Date | V59: 59.7368 | W59: 59.8981 | X59: 60.2192 | Y59: 60.7923 | Z59: 60.1647 | AA59: #N/A Start Date | AB59: 61.3672 | AC59: 62.1784 | AD59: 62.5009 | AE59: 62.7943 | AF59: 62.2126 | AG59: #N/A Start Date | AH59: 63.2678 | AI59: 63.9688 | AJ59: 132.45346 | AK59: 132.46592 | AL59: 132.46284 | AN59: 132.47511 | AO59: 132.48185 | AP59: 132.48951 | AQ59: 132.49671 | AR59: 132.4858 | AT59: 132.52552 | AV59: 132.51461 | AX59: 132.55432
B60: Diluted weighted average shares | D60: 63.1999 | E60: 64.5485 | F60: 64.6659 | G60: 65.3826 | H60: 63.5504 | I60: #N/A Start Date | J60: 65.6048 | K60: 65.4232 | L60: 66.1275 | M60: 66.3258 | N60: 65.3567 | O60: #N/A Start Date | P60: 65.9509 | Q60: 65.4787 | R60: 65.6127 | S60: 64.1983 | T60: 65.3418 | U60: #N/A Start Date | V60: 65.0588 | W60: 64.9296 | X60: 65.4509 | Y60: 65.9119 | Z60: 64.8705 | AA60: #N/A Start Date | AB60: 66.2423 | AC60: 67.0578 | AD60: 66.6715 | AE60: 66.5187 | AF60: 66.2374 | AG60: #N/A Start Date | AH60: 66.9528 | AI60: 67.4649 | AJ60: 133.139 | AK60: 133.139 | AL60: 133.2605 | AN60: 133.139 | AO60: 133.139 | AP60: 133.139 | AQ60: 133.139 | AR60: 133.139 | AT60: 133.139 | AV60: 133.139 | AX60: 133.139
B62: Additional Items
B64: Depreciation (from opex)
B65: Amortization (form opex)

Sheet BS
AH1: 0
B7: Balance Sheet | D7: 2020 | E7: 2020 | F7: 2020 | G7: 2020 | H7: 2020 | J7: 2021 | K7: 2021 | L7: 2021 | M7: 2021 | N7: 2021 | P7: 2022 | Q7: 2022 | R7: 2022 | S7: 2022 | T7: 2022 | V7: 2023 | W7: 2023 | X7: 2023 | Y7: 2023 | Z7: 2023 | AB7: 2024 | AC7: 2024 | AD7: 2024 | AE7: 2024 | AF7: 2024 | AH7: 2025 | AI7: 2025 | AJ7: 2025 | AK7: 2025 | AL7: 2025 | AN7: 2025 | AO7: 2025 | AP7: 2025 | AQ7: 2025 | AR7: 2025
D8: 2020 | J8: 2021 | P8: 2022 | V8: 2023 | AB8: 2024 | AH8: 2025 | AN8: 2026 | AT8: 2027 | AV8: 2028 | AX8: 2029
D9: Q1 | E9: Q2 | F9: Q3 | G9: Q4 | H9: FY | J9: Q1 | K9: Q2 | L9: Q3 | M9: Q4 | N9: FY | P9: Q1 | Q9: Q2 | R9: Q3 | S9: Q4 | T9: FY | V9: Q1 | W9: Q2 | X9: Q3 | Y9: Q4 | Z9: FY | AB9: Q1 | AC9: Q2 | AD9: Q3 | AE9: Q4 | AF9: FY | AH9: Q1 | AI9: Q2 | AJ9: Q3 | AK9: Q4 | AL9: FY | AN9: Q1 | AO9: Q2 | AP9: Q3 | AQ9: Q4 | AR9: FY | AT9: FY | AV9: FY | AX9: FY
B12: Assets
A14: x | B14: Current assets:
B15: Cash & cash equivalents & short-term investments | D15: 52.283 | E15: 86.397 | F15: 116.091 | G15: 100.005 | H15: 100.005 | J15: 105.799 | K15: 101.466 | L15: 95.255 | M15: 592.565 | N15: 592.565 | P15: 480.108 | Q15: 417.64 | R15: 416.615 | S15: 338.652 | T15: 338.652 | V15: 276.119 | W15: 269.795 | X15: 304.596 | Y15: 283.926 | Z15: 283.926 | AB15: 278.317 | AC15: 370.811 | AD15: 374.127 | AE15: 444.095 | AF15: 444.095 | AH15: 492.761 | AI15: 494.222
B16: Cash & cash equivalents | D16: 0 | E16: 0 | F16: 23.888 | G16: 28.239 | H16: 28.239 | J16: 27.003 | K16: 31.257 | L16: 30.219 | M16: 29.498 | N16: 29.498 | P16: 99.797 | Q16: 93.924 | R16: 80.34 | S16: 90.701 | T16: 90.701 | V16: 15.732 | W16: 12.375 | X16: 97.495 | Y16: 101.836 | Z16: 101.836 | AB16: 67.012 | AC16: 46.78 | AD16: 40.655 | AE16: 36.65 | AF16: 36.65 | AH16: 35.521 | AI16: 52.134 | AJ16: =_xll.BDH(Inputs!$D$15,"BS_MKT_SEC_OTHER_ST_INVEST","F"&AJ$9&AJ$7,"F"&AJ$9&AJ$7,"Currency="&Inputs!$D$13,"Period=FQ","BEST_FPERIOD_OVERRIDE=FQ","FILING_STATUS=MR","SCALING_FORMAT="&Inputs!$D$14,"FA_ADJUSTED=Adjusted","Sort=A","Dates=H","DateFormat=P","Fill=0","Direction=H","UseDPDF=Y") -> #NAME?
B17: Short-term investments | D17: 52.283 | E17: 86.397 | F17: 92.203 | G17: 71.766 | H17: 71.766 | J17: 78.796 | K17: 70.209 | L17: 65.036 | M17: 563.067 | N17: 563.067 | P17: 380.311 | Q17: 323.716 | R17: 336.275 | S17: 247.951 | T17: 247.951 | V17: 260.387 | W17: 257.42 | X17: 207.101 | Y17: 182.09 | Z17: 182.09 | AB17: 211.305 | AC17: 324.031 | AD17: 333.472 | AE17: 407.445 | AF17: 407.445 | AH17: 457.24 | AI17: 442.088 | AJ17: =_xll.BDH(Inputs!$D$15,"BS_CASH_NEAR_CASH_ITEM","F"&AJ$9&AJ$7,"F"&AJ$9&AJ$7,"Currency="&Inputs!$D$13,"Period=FQ","BEST_FPERIOD_OVERRIDE=FQ","FILING_STATUS=MR","SCALING_FORMAT="&Inputs!$D$14,"FA_ADJUSTED=Adjusted","Sort=A","Dates=H","DateFormat=P","Fill=0","Direction=H","UseDPDF=Y") -> #NAME?
B18: Accounts receivable | D18: 37.26 | E18: 58.903 | F18: 59.796 | G18: 56.441 | H18: 56.441 | J18: 60.394 | K18: 71.357 | L18: 84.787 | M18: 105.553 | N18: 105.553 | P18: 106.351 | Q18: 154.627 | R18: 188.341 | S18: 182.936 | T18: 182.936 | V18: 186.13 | W18: 200.745 | X18: 248.477 | Y18: 283.186 | Z18: 283.186 | AB18: 296.371 | AC18: 293.499 | AD18: 370.589 | AE18: 387.045 | AF18: 387.045 | AH18: 387.849 | AI18: 433.662 | AJ18: =_xll.BDH(Inputs!$D$15,"BS_ACCT_NOTE_RCV","F"&AJ$9&AJ$7,"F"&AJ$9&AJ$7,"Currency="&Inputs!$D$13,"Period=FQ","BEST_FPERIOD_OVERRIDE=FQ","FILING_STATUS=MR","SCALING_FORMAT="&Inputs!$D$14,"FA_ADJUSTED=Adjusted","Sort=A","Dates=H","DateFormat=P","Fill=0","Direction=H","UseDPDF=Y") -> #NAME? | AK18: 13586.957 | AL18: 13586.957 | AN18: 12222.222 | AO18: 12087.912 | AP18: 11956.522 | AQ18: 11956.522 | AR18: 11956.522 | AT18: 12328.767 | AV18: 11885.246
B19: Inventory | D19: 44.987 | E19: 49.772 | F19: 64.182 | G19: 88.639 | H19: 88.639 | J19: 103.226 | K19: 136.852 | L19: 176.609 | M19: 218.116 | N19: 218.116 | P19: 271.538 | Q19: 288.08 | R19: 327.792 | S19: 393.172 | T19: 393.172 | V19: 473.299 | W19: 471.094 | X19: 507.431 | Y19: 545.395 | Z19: 545.395 | AB19: 581.14 | AC19: 602.927 | AD19: 628.72 | AE19: 597.984 | AF19: 597.984 | AH19: 609.567 | AI19: 648.278 | AJ19: =_xll.BDH(Inputs!$D$15,"BS_INVENTORIES","F"&AJ$9&AJ$7,"F"&AJ$9&AJ$7,"Currency="&Inputs!$D$13,"Period=FQ","BEST_FPERIOD_OVERRIDE=FQ","FILING_STATUS=MR","SCALING_FORMAT="&Inputs!$D$14,"FA_ADJUSTED=Adjusted","Sort=A","Dates=H","DateFormat=P","Fill=0","Direction=H","UseDPDF=Y") -> #NAME? | AK19: 15489.13 | AL19: 15489.13 | AN19: 11836.957 | AO19: 12913.043 | AP19: 12195.652 | AQ19: 10043.478 | AR19: 10043.478 | AT19: 13315.068 | AV19: 10696.721
B20: Prepaid expenses and other current assets | D20: 1.985 | E20: 3.157 | F20: 5.531 | G20: 5.892 | H20: =G20 -> 5.892 | J20: 5.917 | K20: 8.953 | L20: 7.531 | M20: 16.639 | N20: =M20 -> 16.639 | P20: 21.771 | Q20: 18.851 | R20: 17.771 | S20: 15.607 | T20: =S20 -> 15.607 | V20: 19.319 | W20: 18.97 | X20: 17.54 | Y20: 20.023 | Z20: =Y20 -> 20.023 | AB20: 20.066 | AC20: 18.594 | AD20: 10.794 | AE20: 7.507 | AF20: =AE20 -> 7.507 | AH20: 10.677 | AI20: 14.303 | AJ20: =AJ21-AJ15-AJ18-AJ19 -> #NAME? | AK20: 1250 | AL20: 1250 | AN20: 1100 | AO20: 1100 | AP20: 1100 | AQ20: 1100 | AR20: 1100 | AT20: 4500 | AV20: 4350
B21: Total current assets | D21: 198.477 | E21: 205.88 | F21: 251.777 | G21: 260.656 | H21: 260.656 | J21: 286.552 | K21: 329.361 | L21: 377.347 | M21: 952.934 | N21: 952.934 | P21: 904.977 | Q21: 900.628 | R21: 971.242 | S21: 963.806 | T21: 963.806 | V21: 993.811 | W21: 996.832 | X21: 1115.894 | Y21: 1176.11 | Z21: 1176.11 | AB21: 1229.356 | AC21: 1343.162 | AD21: 1445.314 | AE21: 1483.379 | AF21: 1483.379 | AH21: 1547.874 | AI21: 1645.653 | AJ21: =_xll.BDH(Inputs!$D$15,"BS_CUR_ASSET_REPORT","F"&AJ$9&AJ$7,"F"&AJ$9&AJ$7,"Currency="&Inputs!$D$13,"Period=FQ","BEST_FPERIOD_OVERRIDE=FQ","FILING_STATUS=MR","SCALING_FORMAT="&Inputs!$D$14,"FA_ADJUSTED=Adjusted","Sort=A","Dates=H","DateFormat=P","Fill=0","Direction=H","UseDPDF=Y") -> #NAME?
A23: x | B23: Non-current assets:
B24: Net PP&E (Property, Plant and Equipment) | D24: 7.042 | E24: 8.604 | F24: 19.826 | G24: 22.135 | H24: 22.135 | J24: 23.65 | K24: 23.836 | L24: 24.16 | M24: 27.891 | N24: 27.891 | P24: 71.369 | Q24: 69.836 | R24: 77.664 | S24: 94.056 | T24: 94.056 | V24: 166.073 | W24: 175.112 | X24: 206.365 | Y24: 217.241 | Z24: 217.241 | AB24: 233.625 | AC24: 243.208 | AD24: 264.099 | AE24: 283.31 | AF24: 283.31 | AH24: 294.812 | AI24: 308.229 | AJ24: =_xll.BDH(Inputs!$D$15,"BS_NET_FIX_ASSET ","F"&AJ$9&AJ$7,"F"&AJ$9&AJ$7,"Currency="&Inputs!$D$13,"Period=FQ","BEST_FPERIOD_OVERRIDE=FQ","FILING_STATUS=MR","SCALING_FORMAT="&Inputs!$D$14,"FA_ADJUSTED=Adjusted","Sort=A","Dates=H","DateFormat=P","Fill=0","Direction=H","UseDPDF=Y") -> #NAME? | AK24: 7772.8753 | AL24: 7772.8753 | AN24: 9859.2315 | AO24: 11724.67 | AP24: 13514.436 | AQ24: 14996.915 | AR24: 14996.915 | AT24: 20475.069 | AV24: 27977.315
B25: Gross PP&E (Property, Plant and Equipment) | D25: 10.308 | E25: 12.051 | F25: 23.577 | G25: 25.88 | H25: 25.88 | J25: 27.699 | K25: 28.517 | L25: 29.28 | M25: 33.791 | N25: 33.791 | P25: 78.206 | Q25: 77.45 | R25: 86.175 | S25: 104.103 | T25: 104.103 | V25: 177.77 | W25: 188.212 | X25: 221.488 | Y25: 234.744 | Z25: 234.744 | AB25: 253.156 | AC25: 264.402 | AD25: 287.73 | AE25: 308.192 | AF25: 308.192 | AH25: 322.214 | AI25: 339.015 | AJ25: =_xll.BDH(Inputs!$D$15,"BS_GROSS_FIX_ASSET ","F"&AJ$9&AJ$7,"F"&AJ$9&AJ$7,"Currency="&Inputs!$D$13,"Period=FQ","BEST_FPERIOD_OVERRIDE=FQ","FILING_STATUS=MR","SCALING_FORMAT="&Inputs!$D$14,"FA_ADJUSTED=Adjusted","Sort=A","Dates=H","DateFormat=P","Fill=0","Direction=H","UseDPDF=Y") -> #NAME?
B26: Accumulated Depreciation | D26: 3.266 | E26: 3.447 | F26: 3.751 | G26: 3.745 | H26: 3.745 | J26: 4.049 | K26: 4.681 | L26: 5.12 | M26: 5.9 | N26: 5.9 | P26: 6.837 | Q26: 7.614 | R26: 8.511 | S26: 10.047 | T26: 10.047 | V26: 11.697 | W26: 13.1 | X26: 15.123 | Y26: 17.503 | Z26: 17.503 | AB26: 19.531 | AC26: 21.194 | AD26: 23.631 | AE26: 24.882 | AF26: 24.882 | AH26: 27.402 | AI26: 30.786 | AJ26: =_xll.BDH(Inputs!$D$15,"BS_ACCUM_DEPR ","F"&AJ$9&AJ$7,"F"&AJ$9&AJ$7,"Currency="&Inputs!$D$13,"Period=FQ","BEST_FPERIOD_OVERRIDE=FQ","FILING_STATUS=MR","SCALING_FORMAT="&Inputs!$D$14,"FA_ADJUSTED=Adjusted","Sort=A","Dates=H","DateFormat=P","Fill=0","Direction=H","UseDPDF=Y") -> #NAME?
B27: Intangibles | D27: 0 | E27: 0 | F27: 0 | G27: 0 | H27: 0 | J27: 0 | K27: 0 | L27: 0 | M27: 0 | N27: 0 | P27: 0.748 | Q27: 0.661 | R27: 0.873 | S27: 1.255 | T27: 1.3 | V27: 1.233 | W27: 2.107 | X27: 2.163 | Y27: 2.538 | Z27: 3 | AB27: 2.836 | AC27: 2.838 | AD27: 3.461 | AE27: 2.997 | AF27: 3.5 | AH27: 2.997 | AI27: 2.849 | AJ27: =_xll.BDH(Inputs!$D$15,"OTHER_INTANGIBLE_ASSETS_DETAILED ","F"&AJ$9&AJ$7,"F"&AJ$9&AJ$7,"Currency="&Inputs!$D$13,"Period=FQ","BEST_FPERIOD_OVERRIDE=FQ","FILING_STATUS=MR","SCALING_FORMAT="&$D$9,"FA_ADJUSTED=Adjusted","Sort=A","Dates=H","DateFormat=P","Fill=0","Direction=H","UseDPDF=Y") -> #NAME?
B28: Goodwill | D28: 0 | E28: 0 | F28: 0 | G28: 0 | H28: 0 | J28: 0 | K28: 0 | L28: 0 | M28: 0 | N28: 0 | P28: 0 | Q28: 0 | R28: 0 | S28: 0 | V28: 0 | W28: 0 | X28: 0 | Y28: 0 | Z28: 0 | AB28: 0 | AC28: 0 | AD28: 0 | AE28: 0 | AF28: 0 | AH28: 0 | AI28: 0 | AJ28: =_xll.BDH(Inputs!$D$15,"BS_GOODWILL ","F"&AJ$9&AJ$7,"F"&AJ$9&AJ$7,"Currency="&Inputs!$D$13,"Period=FQ","BEST_FPERIOD_OVERRIDE=FQ","FILING_STATUS=MR","SCALING_FORMAT="&Inputs!$D$14,"FA_ADJUSTED=Adjusted","Sort=A","Dates=H","DateFormat=P","Fill=0","Direction=H","UseDPDF=Y") -> #NAME?
B29: Intangibles excl. Goodwill | D29: 0 | E29: 0 | F29: 0 | G29: 0 | H29: 0 | J29: 0 | K29: 0 | L29: 0 | M29: 0 | N29: 0 | P29: =_xll.BDH("ACMR US Equity","OTHER_INTANGIBLE_ASSETS_DETAILED","FQ1 2022","FQ1 2022","Currency=USD","Period=FQ","BEST_FPERIOD_OVERRIDE=FQ","FILING_STATUS=MR","SCALING_FORMAT=MLN","Sort=A","Dates=H","DateFormat=P","Fill=—","Direction=H","UseDPDF=Y") -> #NAME? | Q29: =_xll.BDH("ACMR US Equity","OTHER_INTANGIBLE_ASSETS_DETAILED","FQ2 2022","FQ2 2022","Currency=USD","Period=FQ","BEST_FPERIOD_OVERRIDE=FQ","FILING_STATUS=MR","SCALING_FORMAT=MLN","Sort=A","Dates=H","DateFormat=P","Fill=—","Direction=H","UseDPDF=Y") -> #NAME? | R29: =_xll.BDH("ACMR US Equity","OTHER_INTANGIBLE_ASSETS_DETAILED","FQ3 2022","FQ3 2022","Currency=USD","Period=FQ","BEST_FPERIOD_OVERRIDE=FQ","FILING_STATUS=MR","SCALING_FORMAT=MLN","Sort=A","Dates=H","DateFormat=P","Fill=—","Direction=H","UseDPDF=Y") -> #NAME? | S29: =_xll.BDH("ACMR US Equity","OTHER_INTANGIBLE_ASSETS_DETAILED","FQ4 2022","FQ4 2022","Currency=USD","Period=FQ","BEST_FPERIOD_OVERRIDE=FQ","FILING_STATUS=MR","SCALING_FORMAT=MLN","Sort=A","Dates=H","DateFormat=P","Fill=—","Direction=H","UseDPDF=Y") -> #NAME? | T29: 0 | V29: 1.233 | W29: 2.107 | X29: 2.163 | Y29: 2.538 | Z29: 0 | AB29: 2.803 | AC29: 2.836 | AD29: 2.838 | AE29: 3.461 | AF29: 0 | AH29: 2.997 | AI29: 2.849 | AJ29: =_xll.BDH(Inputs!$D$15,"OTHER_INTANGIBLE_ASSETS_DETAILED ","F"&AJ$9&AJ$7,"F"&AJ$9&AJ$7,"Currency="&Inputs!$D$13,"Period=FQ","BEST_FPERIOD_OVERRIDE=FQ","FILING_STATUS=MR","SCALING_FORMAT="&$D$9,"FA_ADJUSTED=Adjusted","Sort=A","Dates=H","DateFormat=P","Fill=0","Direction=H","UseDPDF=Y") -> #NAME? | AK29: 3664.0224 | AL29: 3664.0224 | AN29: 3623.977 | AO29: 3610.0804 | AP29: 3576.0342 | AQ29: 3517.9088 | AR29: 3517.9088 | AT29: 4420.2139 | AV29: 5196.2621
B30: Other Non-Current Assets | D30: 11.689 | E30: 42.918 | F30: 25.016 | G30: 58.466 | H30: 58.466 | J30: 61.617 | K30: 65.761 | L30: 68.002 | M30: 71.354 | N30: 71.354 | P30: 111.026 | Q30: 101.06 | R30: 98.76 | S30: 177.638 | T30: 177.638 | V30: 152.867 | W30: 144.97 | X30: 87.989 | Y30: 97.557 | Z30: 97.557 | AB30: 93.768 | AC30: 81.205 | AD30: 84.762 | AE30: 89.032 | AF30: 89.032 | AH30: 91.082 | AI30: 85.833 | AJ30: =AJ31-AJ24-AJ27 -> #NAME?
B31: Total Non-Current Assets | D31: 18.731 | E31: 51.522 | F31: 44.842 | G31: 80.601 | H31: 80.601 | J31: 85.267 | K31: 89.597 | L31: 92.162 | M31: 99.245 | N31: 99.245 | P31: 182.395 | Q31: 170.896 | R31: 176.424 | S31: 271.694 | T31: 271.694 | V31: 318.94 | W31: 320.082 | X31: 294.354 | Y31: 314.798 | Z31: 314.798 | AB31: 327.393 | AC31: 324.413 | AD31: 348.861 | AE31: 372.342 | AF31: 372.342 | AH31: 385.894 | AI31: 394.062 | AJ31: =_xll.BDH(Inputs!$D$15,"BS_TOT_NON_CUR_ASSET ","F"&AJ$9&AJ$7,"F"&AJ$9&AJ$7,"Currency="&Inputs!$D$13,"Period=FQ","BEST_FPERIOD_OVERRIDE=FQ","FILING_STATUS=MR","SCALING_FORMAT="&Inputs!$D$14,"FA_ADJUSTED=Adjusted","Sort=A","Dates=H","DateFormat=P","Fill=0","Direction=H","UseDPDF=Y") -> #NAME?
B32: Total Assets | D32: 217.208 | E32: 257.402 | F32: 296.619 | G32: 341.257 | H32: 341.257 | J32: 371.819 | K32: 418.958 | L32: 469.509 | M32: 1052.179 | N32: 1052.179 | P32: 1087.372 | Q32: 1071.524 | R32: 1147.666 | S32: 1235.5 | T32: 1235.5 | V32: 1312.751 | W32: 1316.914 | X32: 1410.248 | Y32: 1490.908 | Z32: 1490.908 | AA32: #N/A Start Date | AB32: 1556.749 | AC32: 1667.575 | AD32: 1794.175 | AE32: 1855.721 | AF32: 1855.721 | AH32: 1933.768 | AI32: 2039.715 | AJ32: =_xll.BDH(Inputs!$D$15,"BS_TOT_NON_CUR_ASSET ","F"&AJ$9&AJ$7,"F"&AJ$9&AJ$7,"Currency="&Inputs!$D$13,"Period=FQ","BEST_FPERIOD_OVERRIDE=FQ","FILING_STATUS=MR","SCALING_FORMAT="&Inputs!$D$14,"FA_ADJUSTED=Adjusted","Sort=A","Dates=H","DateFormat=P","Fill=0","Direction=H","UseDPDF=Y") -> #NAME?
B34: Liabilities & shareholders' equity
A36: x | B36: Current Liabilities:
B37: Accounts payable | D37: 36.294 | E37: 45.012 | F37: 57.722 | G37: 54.439 | H37: 54.439 | J37: 66.711 | K37: 89.384 | L37: 120.008 | M37: 133.339 | N37: 133.339 | P37: 145.597 | Q37: 144.191 | R37: 147.759 | S37: 171.873 | T37: 171.873 | V37: 196.457 | W37: 189.061 | X37: 235.82 | Y37: 262.573 | Z37: 262.573 | AB37: 270.243 | AC37: 286.506 | AD37: 308.386 | AE37: 289.863 | AF37: 289.863 | AH37: 260.708 | AI37: 295.647 | AK37: 9293.4783 | AL37: 9293.4783 | AN37: 7260 | AO37: 7832.967 | AP37: 7317.3913 | AQ37: 6026.087 | AR37: 6026.087 | AT37: 7989.0411 | AV37: 6418.0328
B38: Short-term borrowings | D38: 3.892 | E38: 25.772 | F38: 28.327 | G38: 27.738 | H38: 27.738 | I38: #VALUE! | J38: 25.088 | K38: 23.961 | L38: 17.552 | M38: 12.001 | N38: 12.001 | P38: 12.041 | Q38: 7.226 | R38: 52.948 | S38: 58.326 | T38: 58.326 | V38: 59.114 | W38: 57.215 | X38: 40.628 | Y38: 38.118 | Z38: 38.118 | AA38: #VALUE! | AB38: 61.255 | AC38: 74.11 | AD38: 64.465 | AE38: 77.286 | AF38: 77.286 | AH38: 92.886 | AI38: 115.108 | AJ38: =_xll.BDH(Inputs!$D$15,"BS_CURR_PORTION_LT_DEBT ","F"&AJ$9&AJ$7,"F"&AJ$9&AJ$7,"Currency="&Inputs!$D$13,"Period=FQ","BEST_FPERIOD_OVERRIDE=FQ","FILING_STATUS=MR","SCALING_FORMAT="&Inputs!$D$14,"FA_ADJUSTED=Adjusted","Sort=A","Dates=H","DateFormat=P","Fill=0","Direction=H","UseDPDF=Y")+_xll.BDH(Inputs!$D$15,"SHORT_TERM_DEBT_DETAILED ","F"&AJ$9&AJ$7,"F"&AJ$9&AJ$7,"Currency="&Inputs!$D$13,"Period=FQ","BEST_FPERIOD_OVERRIDE=FQ","FILING_STATUS=MR","SCALING_FORMAT="&Inputs!$D$14,"FA_ADJUSTED=Adjusted","Sort=A","Dates=H","DateFormat=P","Fill=0","Direction=H","UseDPDF=Y") -> #NAME?
B39: Current portion of lease liabilities | D39: 1.345 | E39: 1.331 | F39: 1.388 | G39: 1.417 | H39: 1.417 | J39: 2.171 | K39: 2.437 | L39: 2.48 | M39: 2.313 | N39: 2.313 | P39: 2.076 | Q39: 1.774 | R39: 1.32 | S39: 1.382 | T39: 1.382 | V39: 3.013 | W39: 3.042 | X39: 2.876 | Y39: 2.764 | Z39: 2.764 | AB39: 2.668 | AC39: 2.573 | AD39: 2.377 | AE39: 2.132 | AF39: 2.132 | AH39: 3.564 | AI39: 3.778 | AJ39: =_xll.BDH([1]Inputs!$D$15,"ST_CAPITALIZED_LEASE_LIABILITIES ","F"&AJ$9&AJ$7,"F"&AJ$9&AJ$7,"Currency="&[1]Inputs!$D$13,"Period=FQ","BEST_FPERIOD_OVERRIDE=FQ","FILING_STATUS=MR","SCALING_FORMAT="&[1]Inputs!$D$14,"FA_ADJUSTED=Adjusted","Sort=A","Dates=H","DateFormat=P","Fill=0","Direction=H","UseDPDF=Y") -> #NAME?
B40: Accrued expenses and other current liabilities | D40: 9.236 | E40: 24.401 | F40: 8.83 | G40: 19.314 | H40: 19.314 | J40: 34.065 | K40: 46.276 | L40: 55.167 | M40: 58.286 | N40: 58.286 | P40: 84.735 | Q40: 99.542 | R40: 143.575 | S40: 164.633 | T40: 164.633 | V40: 191.627 | W40: 206.981 | X40: 202.627 | Y40: 197.204 | Z40: 197.204 | AB40: 199.083 | AC40: 222.981 | AD40: 234.807 | AE40: 271.952 | AF40: 271.952 | AH40: 271.72 | AI40: 256.479 | AJ40: =AJ41-AJ37-AJ38-AJ39 -> #NAME? | AK40: 1000 | AL40: 1000 | AN40: 968 | AO40: 880 | AP40: 968 | AQ40: 880 | AR40: 880 | AT40: 900 | AV40: 870
B41: Total current liabilities | D41: 50.767 | E41: 96.516 | F41: 96.267 | G41: 102.908 | H41: 102.908 | J41: 128.035 | K41: 162.058 | L41: 195.207 | M41: 205.939 | N41: 205.939 | P41: 244.449 | Q41: 252.733 | R41: 345.602 | S41: 396.214 | T41: 396.214 | V41: 450.211 | W41: 456.299 | X41: 481.951 | Y41: 500.659 | Z41: 500.659 | AB41: 533.249 | AC41: 586.17 | AD41: 610.035 | AE41: 641.233 | AF41: 641.233 | AH41: 628.878 | AI41: 671.012 | AJ41: =_xll.BDH(Inputs!$D$15,"BS_CUR_LIAB ","F"&AJ$9&AJ$7,"F"&AJ$9&AJ$7,"Currency="&Inputs!$D$13,"Period=FQ","BEST_FPERIOD_OVERRIDE=FQ","FILING_STATUS=MR","SCALING_FORMAT="&Inputs!$D$14,"FA_ADJUSTED=Adjusted","Sort=A","Dates=H","DateFormat=P","Fill=0","Direction=H","UseDPDF=Y") -> #NAME?
H42: 0 | N42: 0 | T42: 0 | Z42: 0 | AF42: 0
A43: x | B43: Non-current liabilities: | H43: 0 | N43: 0 | T43: 0 | Z43: 0 | AF43: 0
B44: Long-term borrowings | D44: 0 | E44: 0 | F44: 0 | G44: 17.979 | H44: 17.979 | J44: 17.444 | K44: 18.717 | L44: 23.08 | M44: 22.957 | N44: 22.957 | P44: 22.344 | Q44: 20.642 | R44: 18.81 | S44: 18.687 | T44: 18.687 | V44: 18.245 | W44: 15.899 | X44: 39.753 | Y44: 53.952 | Z44: 53.952 | AB44: 53.408 | AC44: 70.833 | AD44: 106.069 | AE44: 105.525 | AF44: 105.525 | AH44: 134.54 | AI44: 162.991 | AJ44: =_xll.BDH([1]Inputs!$D$15,"LONG_TERM_BORROWINGS_DETAILED ","F"&AJ$9&AJ$7,"F"&AJ$9&AJ$7,"Currency="&[1]Inputs!$D$13,"Period=FQ","BEST_FPERIOD_OVERRIDE=FQ","FILING_STATUS=MR","SCALING_FORMAT="&[1]Inputs!$D$14,"FA_ADJUSTED=Adjusted","Sort=A","Dates=H","DateFormat=P","Fill=0","Direction=H","UseDPDF=Y") -> #NAME?
B45: Long-term operating lease liabilities | D45: 2.202 | E45: 3.317 | F45: 3.18 | G45: 2.88 | H45: 2.88 | J45: 3.178 | K45: 2.772 | L45: 2.119 | M45: 1.869 | N45: 1.869 | P45: 1.952 | Q45: 1.704 | R45: 1.327 | S45: 1.107 | T45: 1.107 | V45: 4.395 | W45: 4.767 | X45: 4.308 | Y45: 4.262 | Z45: 4.262 | AB45: 3.83 | AC45: 3.679 | AD45: 3.303 | AE45: 3.84 | AF45: 3.84 | AH45: 6.149 | AI45: 5.496 | AJ45: =_xll.BDH([1]Inputs!$D$15,"LT_CAPITALIZED_LEASE_LIABILITIES ","F"&AJ$9&AJ$7,"F"&AJ$9&AJ$7,"Currency="&[1]Inputs!$D$13,"Period=FQ","BEST_FPERIOD_OVERRIDE=FQ","FILING_STATUS=MR","SCALING_FORMAT="&[1]Inputs!$D$14,"FA_ADJUSTED=Adjusted","Sort=A","Dates=H","DateFormat=P","Fill=0","Direction=H","UseDPDF=Y") -> #NAME?
B46: Other non-current liabilities | D46: 5.83 | E46: 6.584 | F46: 6.454 | G46: 9.32 | H46: 9.32 | J46: 7.915 | K46: 5.855 | L46: 6.596 | M46: 9.749 | N46: 9.749 | P46: 9.853 | Q46: 9.3 | R46: 7.829 | S46: 7.321 | T46: 7.321 | V46: 7.195 | W46: 6.566 | X46: 6.106 | Y46: 5.873 | Z46: 5.873 | AB46: 5.469 | AC46: 5.505 | AD46: 5.685 | AE46: 9.217 | AF46: 9.217 | AH46: 8.848 | AI46: 8.527 | AJ46: =+AJ47-AJ44-AJ45 -> #NAME?
B47: Total non-current liabilities | D47: 8.032 | E47: 9.901 | F47: 9.634 | G47: 30.179 | H47: 30.179 | J47: 28.537 | K47: 27.344 | L47: 31.795 | M47: 34.575 | N47: 34.575 | P47: 34.149 | Q47: 31.646 | R47: 27.966 | S47: 27.115 | T47: 27.115 | V47: 29.835 | W47: 27.232 | X47: 50.167 | Y47: 64.087 | Z47: 64.087 | AB47: 62.707 | AC47: 80.017 | AD47: 115.057 | AE47: 118.582 | AF47: 118.582 | AH47: 149.537 | AI47: 177.014 | AJ47: =_xll.BDH(Inputs!$D$15,"NON_CUR_LIAB ","F"&AJ$9&AJ$7,"F"&AJ$9&AJ$7,"Currency="&Inputs!$D$13,"Period=FQ","BEST_FPERIOD_OVERRIDE=FQ","FILING_STATUS=MR","SCALING_FORMAT="&Inputs!$D$14,"FA_ADJUSTED=Adjusted","Sort=A","Dates=H","DateFormat=P","Fill=0","Direction=H","UseDPDF=Y") -> #NAME?
B48: Total liabilities | D48: 58.799 | E48: 106.417 | F48: 105.901 | G48: 133.087 | H48: 133.087 | J48: 156.572 | K48: 189.402 | L48: 227.002 | M48: 240.514 | N48: 240.514 | P48: 278.598 | Q48: 284.379 | R48: 373.568 | S48: 423.329 | T48: 423.329 | V48: 480.046 | W48: 483.531 | X48: 532.118 | Y48: 564.746 | Z48: 564.746 | AB48: 595.956 | AC48: 666.187 | AD48: 725.092 | AE48: 759.815 | AF48: 759.815 | AH48: 778.415 | AI48: 848.026 | AJ48: =_xll.BDH([1]Inputs!$D$15,"BS_TOT_LIAB2 ","F"&AJ$9&AJ$7,"F"&AJ$9&AJ$7,"Currency="&[1]Inputs!$D$13,"Period=FQ","BEST_FPERIOD_OVERRIDE=FQ","FILING_STATUS=MR","SCALING_FORMAT="&[1]Inputs!$D$14,"FA_ADJUSTED=Adjusted","Sort=A","Dates=H","DateFormat=P","Fill=0","Direction=H","UseDPDF=Y") -> #NAME?
A50: x | B50: Shareholders' equity:
B51: Common equity | D51: 98.942 | E51: 89.907 | F51: 126.942 | G51: 141.15 | H51: 141.15 | J51: 148.311 | K51: 160.823 | L51: 173.016 | M51: 676.204 | N51: 676.204 | P51: 674.386 | Q51: 655.005 | R51: 643.015 | S51: 674.856 | T51: 674.856 | V51: 691.927 | W51: 691.954 | X51: 729.05 | Y51: 767.39 | Z51: 767.39 | AB51: 796.202 | AC51: 833.169 | AD51: 888.166 | AE51: 904.625 | AF51: 904.625 | AH51: 949.146 | AI51: 986.45 | AJ51: =AJ54-AJ52-AJ53 -> #NAME?
B52: Preferred equity | D52: 0 | E52: 0 | F52: 0 | G52: 0 | H52: 0 | J52: 0 | K52: 0 | L52: 0 | M52: 0 | N52: 0 | P52: 0 | Q52: 0 | R52: 0 | S52: 0 | T52: 0 | V52: 0 | W52: 0 | X52: 0 | Y52: 0 | Z52: 0 | AB52: 0 | AC52: 0 | AD52: 0 | AE52: 0 | AF52: 0 | AH52: 0 | AI52: 0 | AJ52: =_xll.BDH(Inputs!$D$15,"PFD_EQTY_HYBRID_CAPITAL ","F"&AJ$9&AJ$7,"F"&AJ$9&AJ$7,"Currency="&Inputs!$D$13,"Period=FQ","BEST_FPERIOD_OVERRIDE=FQ","FILING_STATUS=MR","SCALING_FORMAT="&Inputs!$D$14,"FA_ADJUSTED=Adjusted","Sort=A","Dates=H","DateFormat=P","Fill=0","Direction=H","UseDPDF=Y") -> #NAME?
B53: Non-controlling interest | D53: 59.467 | E53: 61.078 | F53: 63.776 | G53: 67.02 | H53: 67.02 | J53: 66.936 | K53: 68.733 | L53: 69.491 | M53: 135.461 | N53: 135.461 | P53: 134.388 | Q53: 132.14 | R53: 131.083 | S53: 137.315 | T53: 137.315 | V53: 140.778 | W53: 141.429 | X53: 149.08 | Y53: 158.772 | Z53: 158.772 | AB53: 164.591 | AC53: 168.219 | AD53: 180.917 | AE53: 191.281 | AF53: 191.281 | AH53: 206.207 | AI53: 205.239 | AJ53: =_xll.BDH(Inputs!$D$15,"MINORITY_NONCONTROLLING_INTEREST ","F"&AJ$9&AJ$7,"F"&AJ$9&AJ$7,"Currency="&Inputs!$D$13,"Period=FQ","BEST_FPERIOD_OVERRIDE=FQ","FILING_STATUS=MR","SCALING_FORMAT="&Inputs!$D$14,"FA_ADJUSTED=Adjusted","Sort=A","Dates=H","DateFormat=P","Fill=0","Direction=H","UseDPDF=Y") -> #NAME?
B54: Total equity | D54: 158.409 | E54: 150.985 | F54: 190.718 | G54: 208.17 | H54: 208.17 | J54: 215.247 | K54: 229.556 | L54: 242.507 | M54: 811.665 | N54: 811.665 | P54: 808.774 | Q54: 787.145 | R54: 774.098 | S54: 812.171 | T54: 812.171 | V54: 832.705 | W54: 833.383 | X54: 878.13 | Y54: 926.162 | Z54: 926.162 | AB54: 960.793 | AC54: 1001.388 | AD54: 1069.083 | AE54: 1095.906 | AF54: 1095.906 | AH54: 1155.353 | AI54: 1191.689 | AJ54: =_xll.BDH(Inputs!$D$15,"TOTAL_EQUITY ","F"&AJ$9&AJ$7,"F"&AJ$9&AJ$7,"Currency="&Inputs!$D$13,"Period=FQ","BEST_FPERIOD_OVERRIDE=FQ","FILING_STATUS=MR","SCALING_FORMAT="&Inputs!$D$14,"FA_ADJUSTED=Adjusted","Sort=A","Dates=H","DateFormat=P","Fill=0","Direction=H","UseDPDF=Y") -> #NAME?
B55: Total liabilities and shareholders' equity | D55: 217.208 | E55: 257.402 | F55: 296.619 | G55: 341.257 | H55: 341.257 | J55: 371.819 | K55: 418.958 | L55: 469.509 | M55: 1052.179 | N55: 1052.179 | P55: 1087.372 | Q55: 1071.524 | R55: 1147.666 | S55: 1235.5 | T55: 1235.5 | V55: 1312.751 | W55: 1316.914 | X55: 1410.248 | Y55: 1490.908 | Z55: 1490.908 | AB55: 1556.749 | AC55: 1667.575 | AD55: 1794.175 | AE55: 1855.721 | AF55: 1855.721 | AH55: 1933.768 | AI55: 2039.715 | AJ55: =_xll.BDH([1]Inputs!$D$15,"TOT_LIAB_AND_EQY ","F"&AJ$9&AJ$7,"F"&AJ$9&AJ$7,"Currency="&[1]Inputs!$D$13,"Period=FQ","BEST_FPERIOD_OVERRIDE=FQ","FILING_STATUS=MR","SCALING_FORMAT="&[1]Inputs!$D$14,"FA_ADJUSTED=Adjusted","Sort=A","Dates=H","DateFormat=P","Fill=0","Direction=H","UseDPDF=Y") -> #NAME?
B57: Capitalized R&D | D57: 0 | E57: 0 | F57: 0 | G57: 0 | H57: 0 | J57: 0 | K57: 0 | L57: 0 | M57: 0 | N57: 0 | P57: 0 | Q57: 0 | R57: 0 | S57: 0 | T57: 0 | V57: 0 | W57: 0 | X57: 0 | Y57: 0 | Z57: 0 | AB57: 0 | AC57: 0 | AD57: 0 | AE57: 0 | AF57: 0 | AH57: 0 | AI57: 0 | AJ57: =_xll.BDH([1]Inputs!$D$15,"EXPND_INCUR_ON_R&D_CAPITALZD ","F"&AJ$9&AJ$7,"F"&AJ$9&AJ$7,"Currency="&[1]Inputs!$D$13,"Period=FQ","BEST_FPERIOD_OVERRIDE=FQ","FILING_STATUS=MR","SCALING_FORMAT="&[1]Inputs!$D$14,"FA_ADJUSTED=Adjusted","Sort=A","Dates=H","DateFormat=P","Fill=0","Direction=H","UseDPDF=Y") -> #NAME?

Sheet CF
A7: x | B7: Cash Flow Statement | D7: 2020 | E7: 2020 | F7: 2020 | G7: 2020 | H7: 2020 | J7: 2021 | K7: 2021 | L7: 2021 | M7: 2021 | N7: 2021 | P7: 2022 | Q7: 2022 | R7: 2022 | S7: 2022 | T7: 2022 | V7: 2023 | W7: 2023 | X7: 2023 | Y7: 2023 | Z7: 2023 | AB7: 2024 | AC7: 2024 | AD7: 2024 | AE7: 2024 | AF7: 2024 | AH7: 2025 | AI7: 2025 | AJ7: 2025 | AK7: 2025 | AL7: 2025 | AN7: 2025 | AO7: 2025 | AP7: 2025 | AQ7: 2025 | AR7: 2025
D8: 2020 | J8: 2021 | P8: 2022 | V8: 2023 | AB8: 2024 | AH8: 2025 | AN8: 2026 | AT8: 2027 | AV8: 2028 | AX8: 2029
D9: Q1 | E9: Q2 | F9: Q3 | G9: Q4 | H9: FY | J9: Q1 | K9: Q2 | L9: Q3 | M9: Q4 | N9: FY | P9: Q1 | Q9: Q2 | R9: Q3 | S9: Q4 | T9: FY | V9: Q1 | W9: Q2 | X9: Q3 | Y9: Q4 | Z9: FY | AB9: Q1 | AC9: Q2 | AD9: Q3 | AE9: Q4 | AF9: FY | AH9: Q1 | AI9: Q2 | AJ9: Q3 | AK9: Q4 | AL9: FY | AN9: Q1 | AO9: Q2 | AP9: Q3 | AQ9: Q4 | AR9: FY | AT9: FY | AV9: FY | AX9: FY
B12: Cash and cash equivalents, beginning balances | D12: 52.283 | E12: 86.397 | F12: 92.203 | G12: 71.766 | H12: 71.766 | I12: #N/A Start Date | J12: 78.796 | K12: 70.209 | L12: 65.036 | M12: 563.067 | N12: 563.067 | P12: 380.311 | Q12: 323.716 | R12: 336.275 | S12: 247.951 | T12: 247.951 | U12: #N/A Start Date | V12: 260.387 | W12: 257.42 | X12: 207.101 | Y12: 182.09 | Z12: 182.09 | AA12: #N/A Start Date | AB12: 211.305 | AC12: 324.031 | AD12: 333.472 | AE12: 407.445 | AF12: 407.445 | AG12: #N/A Start Date | AH12: 457.24 | AI12: 442.088
A14: x | B14: Operating activities:
B15: Net income | D15: 1.705 | E15: -0.081 | F15: 8.627 | G15: 8.529 | H15: 18.78 | I15: #N/A Start Date | J15: 5.47 | K15: 6.567 | L15: 10.155 | M15: 15.565 | N15: 37.757 | O15: #N/A Start Date | P15: -5.786 | Q15: 12.236 | R15: 21.004 | S15: 11.809 | T15: 39.263 | U15: #N/A Start Date | V15: 7.145 | W15: 26.825 | X15: 25.679 | Y15: 17.7 | Z15: 77.349 | AA15: #N/A Start Date | AB15: 17.433 | AC15: 24.21 | AD15: 30.904 | AE15: 31.08 | AF15: 103.627 | AG15: #N/A Start Date | AH15: 20.38 | AI15: 29.76
B16: Adjustments to reconcile to cash from operations:
B17: Depreciation and amortization | D17: 0.212 | E17: 0.229 | F17: 0.333 | G17: 0.281 | H17: 1.055 | I17: #N/A Start Date | J17: 0.546 | K17: 0.485 | L17: 0.566 | M17: 0.756 | N17: 2.353 | O17: #N/A Start Date | P17: 1.213 | Q17: 1.342 | R17: 1.549 | S17: 1.262 | T17: 5.366 | U17: #N/A Start Date | V17: 1.714 | W17: 2.241 | X17: 2.066 | Y17: 2.071 | Z17: 8.092 | AA17: #N/A Start Date | AB17: 2.518 | AC17: 2.166 | AD17: 2.389 | AE17: 2.894 | AF17: 9.967 | AG17: #N/A Start Date | AH17: 3.017 | AI17: 3.339 | AJ17: 4759.4902 | AK17: 5334.5301 | AL17: 10177.847 | AN17: 4022.046 | AO17: 4656.9593 | AP17: 4313.2415 | AQ17: 3990.1252 | AR17: 16982.372
B18: Stock-based compensation expense | D18: 0.689 | E18: 0.855 | F18: 2.779 | G18: 1.305 | H18: 5.628 | I18: #N/A Start Date | J18: 1.21 | K18: 1.335 | L18: 1.278 | M18: 1.294 | N18: 5.117 | O18: #N/A Start Date | P18: 1.374 | Q18: 1.969 | R18: 1.893 | S18: 2.494 | T18: 7.73 | U18: #N/A Start Date | V18: 2.068 | W18: 2.017 | X18: 10.581 | Y18: 12.672 | Z18: 27.338 | AA18: #N/A Start Date | AB18: 14.569 | AC18: 14.342 | AD18: 11.881 | AE18: 8.784 | AF18: 49.576 | AG18: #N/A Start Date | AH18: 9.817 | AI18: 9.77 | AJ18: 13.75 | AK18: 12.5 | AL18: 57.007 | AN18: 12.1 | AO18: 11 | AP18: 12.1 | AQ18: 11 | AR18: 46.2
B19: Other | D19: 2.585 | E19: 7.297 | F19: -2.516 | G19: 0.652 | H19: 8.018 | I19: #N/A Start Date | J19: -1.143 | K19: -3.257 | L19: 1.823 | M19: 32.574 | N19: 7.805 | O19: #N/A Start Date | P19: 4.3 | Q19: 8.217 | R19: 8.52 | S19: 10.165 | T19: 31.202 | U19: #N/A Start Date | V19: -0.281 | W19: 4.108 | X19: 21.31 | Y19: 7.67 | Z19: 27.66 | AA19: #N/A Start Date | AB19: 27.625 | AC19: 21.382 | AD19: 37.666 | AE19: 28.653 | AF19: 115.326 | AG19: #N/A Start Date | AH19: 20.379 | AI19: 11.16
B20: Changes in working capital:
B21: Accounts receivable | D21: -6.902 | E21: -24.843 | F21: 0.899 | G21: 1.879 | H21: -28.967 | I21: #N/A Start Date | J21: -4.602 | K21: -10.287 | L21: -13.246 | M21: -27.909 | N21: -56.044 | O21: #N/A Start Date | P21: -0.284 | Q21: -56.311 | R21: -40.245 | S21: 0.854 | T21: -95.986 | U21: #N/A Start Date | V21: -2.452 | W21: -34.43 | X21: -40.924 | Y21: -35.156 | Z21: -112.962 | AA21: #N/A Start Date | AB21: -15.286 | AC21: -11.242 | AD21: -79.392 | AE21: -21.169 | AF21: -127.089 | AG21: #N/A Start Date | AH21: 0.19 | AI21: -44.698 | AJ21: -11069.02 | AK21: 0 | AL21: -10857.871 | AN21: 1364.7343 | AO21: 134.31013 | AP21: 131.39035 | AQ21: 0 | AR21: 1630.4348
B22: Inventories | D22: -0.931 | E22: -4.699 | F22: -12.732 | G22: -22.406 | H22: -40.768 | I22: #N/A Start Date | J22: -15.276 | K22: -32.156 | L22: -40.181 | M22: -40.043 | N22: -127.656 | O22: #N/A Start Date | P22: -52.503 | Q22: -28.359 | R22: -51.175 | S22: -61.277 | T22: -193.314 | U22: #N/A Start Date | V22: -79.942 | W22: -16.797 | X22: -39.149 | Y22: -28.139 | Z22: -164.027 | AA22: #N/A Start Date | AB22: -38.574 | AC22: -26.315 | AD22: -17.312 | AE22: 18.066 | AF22: -64.135 | AG22: #N/A Start Date | AH22: -15.108 | AI22: -37.838 | AJ22: -14266.304 | AK22: -1222.8261 | AL22: -15489.13 | AN22: 3652.1739 | AO22: -1076.087 | AP22: 717.3913 | AQ22: 2152.1739 | AR22: 5445.6522
B23: Accounts payable | D23: 5.617 | E23: 9.337 | F23: 7.069 | G23: -0.748 | H23: 21.275 | I23: #N/A Start Date | J23: 9.492 | K23: 21.708 | L23: 26.083 | M23: 7.928 | N23: 65.211 | O23: #N/A Start Date | P23: 6.681 | Q23: -5.518 | R23: 7.682 | S23: 15.225 | T23: 24.07 | U23: #N/A Start Date | V23: 17.136 | W23: -19.725 | X23: 34.886 | Y23: 6.985 | Z23: 39.282 | AA23: #N/A Start Date | AB23: -0.717 | AC23: 7.322 | AD23: 24.442 | AE23: -24.881 | AF23: 6.166 | AG23: #N/A Start Date | AH23: -20.22 | AI23: 31.657 | AJ23: 4005.6936 | AK23: 733.69565 | AL23: 4486.3773 | AN23: -2033.4783 | AO23: 572.96703 | AP23: -515.57573 | AQ23: -1291.3043 | AR23: -3267.3913
