Workbook
Name COOLFUCNTION: _xlfn.LAMBDA(_xldudf_BOARDFLARE_EXEC("workbook-settings:coolfucntion"))
Name COOLFUCNTION: _xlfn.LAMBDA(_xldudf_BOARDFLARE_EXEC("workbook-settings:coolfucntion"))
Name COOLFUCNTION: _xlfn.LAMBDA(_xldudf_BOARDFLARE_EXEC("workbook-settings:coolfucntion"))
Name COOLFUCNTION: _xlfn.LAMBDA(_xldudf_BOARDFLARE_EXEC("workbook-settings:coolfucntion"))
Name COOLFUCNTION: _xlfn.LAMBDA(_xldudf_BOARDFLARE_EXEC("workbook-settings:coolfucntion"))
Name COOLFUCNTION: _xlfn.LAMBDA(_xldudf_BOARDFLARE_EXEC("workbook-settings:coolfucntion"))
Name COOLFUCNTION: _xlfn.LAMBDA(_xldudf_BOARDFLARE_EXEC("workbook-settings:coolfucntion"))
Name COOLFUCNTION: _xlfn.LAMBDA(_xldudf_BOARDFLARE_EXEC("workbook-settings:coolfucntion"))
Name COOLFUCNTION: _xlfn.LAMBDA(_xldudf_BOARDFLARE_EXEC("workbook-settings:coolfucntion"))
Name COOLFUCNTION: _xlfn.LAMBDA(_xldudf_BOARDFLARE_EXEC("workbook-settings:coolfucntion"))
Name COOLFUCNTION: _xlfn.LAMBDA(_xldudf_BOARDFLARE_EXEC("workbook-settings:coolfucntion"))
Name Sectors: #REF!
Name Sectors: #REF!
Name Sectors: #REF!
Name Sectors: #REF!
Name Sectors: #REF!
Name Sectors: #REF!
Name Sectors: #REF!
Name Sectors: #REF!

Sheet Dashboard
C154: =+C155+1 -> 45993
C155: =+C156+1 -> 45992
C156: =+C157+1 -> 45991
C157: =+C158+1 -> 45990
C158: =+C159+1 -> 45989
C159: =+C160+1 -> 45988
C160: =+C161+1 -> 45987 | L160: =IF(FCFF!$R$155="Revenue Exit",FCFF!$AF$167,IF(FCFF!$R$155="EBITDA Exit",FCFF!Z167,FCFF!AL167)) -> 24.343911
C161: =+C162+1 -> 45986
C162: =+C163+1 -> 45985 | E162: =IF(FCFF!$R$155="Revenue Exit",FCFF!$AF$167,IF(FCFF!$R$155="EBITDA Exit",FCFF!Z167,FCFF!AL167)) -> 24.343911
C163: =+C164+1 -> 45984 | E163: =E164+($E$162-$E$193)/COUNTA($C$162:$C$192) -> 24.598301
C164: =+C165+1 -> 45983 | E164: =E165+($E$162-$E$193)/COUNTA($C$162:$C$192) -> 24.852691
C165: =+C166+1 -> 45982 | E165: =E166+($E$162-$E$193)/COUNTA($C$162:$C$192) -> 25.107081
C166: =+C167+1 -> 45981 | E166: =E167+($E$162-$E$193)/COUNTA($C$162:$C$192) -> 25.361471
C167: =+C168+1 -> 45980 | E167: =E168+($E$162-$E$193)/COUNTA($C$162:$C$192) -> 25.615861
C168: =+C169+1 -> 45979 | E168: =E169+($E$162-$E$193)/COUNTA($C$162:$C$192) -> 25.870251
C169: =+C170+1 -> 45978 | E169: =E170+($E$162-$E$193)/COUNTA($C$162:$C$192) -> 26.124641
C170: =+C171+1 -> 45977 | E170: =E171+($E$162-$E$193)/COUNTA($C$162:$C$192) -> 26.379031
C171: =+C172+1 -> 45976 | E171: =E172+($E$162-$E$193)/COUNTA($C$162:$C$192) -> 26.633421
C172: =+C173+1 -> 45975 | E172: =E173+($E$162-$E$193)/COUNTA($C$162:$C$192) -> 26.887811
C173: =+C174+1 -> 45974 | E173: =E174+($E$162-$E$193)/COUNTA($C$162:$C$192) -> 27.142201
C174: =+C175+1 -> 45973 | E174: =E175+($E$162-$E$193)/COUNTA($C$162:$C$192) -> 27.396591
... C192: =+C193+1 -> 45955 | E192: =E193+($E$162-$E$193)/COUNTA($C$162:$C$192) -> 31.97561
B193: TODAY | C193: =+'Stock Data'!AM4 -> 45954 | D193: =_xlfn.XLOOKUP(C193,'Stock Data'!$AM$4:$AM$1051,'Stock Data'!$AN$4:$AN$1051) -> 32.23 | E193: =D193 -> 32.23
C194: =+'Stock Data'!AM5 -> 45953 | D194: =_xlfn.XLOOKUP(C194,'Stock Data'!$AM$4:$AM$1051,'Stock Data'!$AN$4:$AN$1051) -> 32.23
C195: =+'Stock Data'!AM6 -> 45952 | D195: =_xlfn.XLOOKUP(C195,'Stock Data'!$AM$4:$AM$1051,'Stock Data'!$AN$4:$AN$1051) -> 32.87
C196: =+'Stock Data'!AM7 -> 45951 | D196: =_xlfn.XLOOKUP(C196,'Stock Data'!$AM$4:$AM$1051,'Stock Data'!$AN$4:$AN$1051) -> 32.87
C197: =+'Stock Data'!AM8 -> 45950 | D197: =_xlfn.XLOOKUP(C197,'Stock Data'!$AM$4:$AM$1051,'Stock Data'!$AN$4:$AN$1051) -> 32.87
C198: =+'Stock Data'!AM9 -> 45949 | D198: =_xlfn.XLOOKUP(C198,'Stock Data'!$AM$4:$AM$1051,'Stock Data'!$AN$4:$AN$1051) -> 33.24
C199: =+'Stock Data'!AM10 -> 45948 | D199: =_xlfn.XLOOKUP(C199,'Stock Data'!$AM$4:$AM$1051,'Stock Data'!$AN$4:$AN$1051) -> 33.53
C200: =+'Stock Data'!AM11 -> 45947 | D200: =_xlfn.XLOOKUP(C200,'Stock Data'!$AM$4:$AM$1051,'Stock Data'!$AN$4:$AN$1051) -> 33.775
C201: =+'Stock Data'!AM12 -> 45946 | D201: =_xlfn.XLOOKUP(C201,'Stock Data'!$AM$4:$AM$1051,'Stock Data'!$AN$4:$AN$1051) -> 34.695
C202: =+'Stock Data'!AM13 -> 45945 | D202: =_xlfn.XLOOKUP(C202,'Stock Data'!$AM$4:$AM$1051,'Stock Data'!$AN$4:$AN$1051) -> 34.905
C203: =+'Stock Data'!AM14 -> 45944 | D203: =_xlfn.XLOOKUP(C203,'Stock Data'!$AM$4:$AM$1051,'Stock Data'!$AN$4:$AN$1051) -> 34.905
C204: =+'Stock Data'!AM15 -> 45943 | D204: =_xlfn.XLOOKUP(C204,'Stock Data'!$AM$4:$AM$1051,'Stock Data'!$AN$4:$AN$1051) -> 34.905
C205: =+'Stock Data'!AM16 -> 45942 | D205: =_xlfn.XLOOKUP(C205,'Stock Data'!$AM$4:$AM$1051,'Stock Data'!$AN$4:$AN$1051) -> 34.905
... C558: =+'Stock Data'!AM369 -> 45589 | D558: =_xlfn.XLOOKUP(C558,'Stock Data'!$AM$4:$AM$1051,'Stock Data'!$AN$4:$AN$1051) -> 46.505

Sheet Key Info
B7: Analysts | F7: LIS – Equity Research | J7: Stock Performance
B12: Thor Pinto, Analyst | F12: Recommendation: | H12: Buy
B13: Bsc in Economics, ISEG – Ulisboa | F13: Target Price (FCFF):
B14: l62767@aln.iseg.ulisboa.pt | F14: Upside:
B15: Patrícia Franco, Analyst
B16: Bsc in Mathematics Applied to Economics and Management, ISEG – Ulisboa | F16: Ticker | H16: =Inputs!D15 -> AZZA3 BZ Equity
B17: l61831@aln.iseg.ulisboa.pt | F17: Stock Exchange
B18: Arnaud Hees, Analyst
B19: Bsc in XXX, ISEG – Ulisboa | F19: Current Price | H19: ='Stock Data'!AN4 -> 32.23
B20: email@aln.iseg.ulisboa.pt | F20: ="Market Cap (in "&IF(Inputs!$D$14="BLN","billions",IF(Inputs!$D$14="MLN","millions","thousands"))&")" -> Market Cap (in millions) | H20: ='Stock Data'!AQ4 -> 6655.1666
F21: Beta | H21: 0.41
F22: % of 52-Week High | H22: ='Stock Data'!E165 -> 0.1642097
F23: 100-Day Moving Average | H23: ='Stock Data'!E166 -> 36.1415
B25: Reviewed by: | F25: Avg Vol (1 month) | H25: ='Stock Data'!E168 -> 2277173
B26: Madalena Silva, Co-Head of Equity Research | F26: Shares Outstanding (millions) | H26: ='Stock Data'!E169 -> 206.4898
B27: Bsc in Applied Mathematics in Economics and Managment, ISEG – Ulisboa | F27: % Float | H27: ='Stock Data'!E170 -> 0.6086
B28: l63835@aln.iseg.ulisboa.pt | F28: Short % of Float | H28: =IFERROR('Stock Data'!E171,0) -> 0
B30: LISBON INVESTMENT SOCIETY | F30: % Held by Insiders | H30: ='Stock Data'!E173 -> 0.15760001
B31: ISEG – Rua do Quelhas, 6 | F31: % Held by Institutions | H31: ='Stock Data'!E174 -> 0.7931779
B32: lis@iseg.ulisboa.pt
B34: Disclaimer: This report was prepared by members of the Lisbon Investment Society (LIS), an independent, student-led, non-profit organization based at ISEG – Lisbon School of Economics & Management, and is intended solely for academic and educational purposes. All analyses, forecasts, and opinions expressed in this report reflect the independent judgment of the authors as of the date of publication and are subject to change without notice. The views presented herein do not represent those of ISEG, its faculty, or any affiliated entity. This document does not constitute, and should not be interpreted as, investment advice, an offer, or a solicitation to buy or sell any security or financial instrument. Nothing in this report should be construed as a recommendation to make or refrain from making any investment decision. The content is intended for informational purposes only, and readers are strongly encouraged to conduct their own research and seek advice from a qualified financial professional before making any financial decisions. The information contained in this report has been obtained from publicly available sources believed to be reliable; however, no representation or warranty is made regarding the accuracy, completeness, or timeliness of such information. LIS and its members accept no liability whatsoever for any direct or indirect loss arising from the use of this report or its contents. This report incorporates terminology, financial metrics, and methodologies commonly used in professional equity research, including but not limited to Discounted Cash Flow (DCF), trading multiples, Monte Carlo simulations, and strategic analysis tools such as Porter’s Five Forces. Definitions and assumptions used in these models are disclosed within the report and reflect a hypothetical investment thesis designed solely for academic discussion. All valuations, projections, and target prices presented herein are based on publicly available data and subject to the limitations of modeling assumptions. These are not guarantees of future performance and should not be relied upon as such, as past performance is not indicative of future results. Any company names, logos, trademarks, or brand references mentioned in this report are the property of their respective owners and are used strictly for identification and academic purposes. This document may not be reproduced, redistributed, or quoted in whole or in part without the prior written consent of the Lisbon Investment Society. About LIS – Lisbon Investment Society: The Lisbon Investment Society (LIS) is a non-profit academic association headquartered at ISEG – Lisbon School of Economics & Management. Founded in 2016, LIS is committed to fostering student interest in finance and investment through applied research, skill development, and institutional engagement. The Society operates independently and autonomously from any political, religious, or commercial affiliation, and is composed of selected students and collaborators who are invited through a rigorous recruitment process and share a commitment to excellence, analytical rigor, and ethical standards. Its activities include equity research, portfolio management, macroeconomic analysis, and investment education. This report was prepared by the Equity Research team at the Lisbon Investment Society, whose analysts combine rigorous financial modeling, critical thinking, and collaborative research to deliver high-quality, student-led investment analysis. We welcome your feedback, discussion, and questions regarding this report or our research process, and invite you to reach out to our team as we are always open to engagement.

Sheet Industry
D6: 584.17 | E6: 627.76 | F6: 676.06 | G6: 729.63 | H6: 789.13 | I6: 855.3 | J6: 929 | K6: 997.69 | L6: 1067.63 | M6: 1137.57
A7: x | B7: Industry Growth Forecast | O7: Industry Index
B9: in Billion | D9: 2022 | E9: =+D9+1 -> 2023 | F9: =+E9+1 -> 2024 | G9: =+F9+1 -> 2025 | H9: =+G9+1 -> 2026 | I9: =+H9+1 -> 2027 | J9: =+I9+1 -> 2028 | K9: =+J9+1 -> 2029 | M9: ="CAGR "&$G$9&" - "&$K$9 -> CAGR 2025 - 2029
B12: Market Size (Footwear) | D12: 578.74 | E12: 616.09 | F12: 649.06 | G12: 679.65 | H12: 710.18 | I12: 739.15 | J12: 773.72 | K12: 789.71 | M12: =(K12/G12)^(1/5)-1 -> 0.030472635
B13: Market Share | D13: 0.0019145039 | E13: 0.0019721145 | F13: 0.001945891 | G13: 0.002 | H13: 0.002 | I13: 0.0022 | J13: 0.0024 | K13: 0.0025 | M13: =((K13*K12)/(G13*G12))^(1/5)-1 -> 0.077502945
B14: Market Size (Bags) | D14: 1570 | E14: 1730 | F14: 1790 | G14: 1840 | H14: 1890 | I14: 1940 | J14: 2000 | K14: 2060 | M14: =(K14/G14)^(1/5)-1 -> 0.022845125
B15: Market Share | D15: 0.0013471338 | E15: 0.0013520231 | F15: 0.0015804469 | G15: 0.0017 | H15: 0.0018 | I15: 0.002 | J15: 0.0022 | K15: 0.0024 | M15: =((K15*K14)/(G15*G14))^(1/5)-1 -> 0.095878341
B16: Market Size (Apparel) | M16: =(K16/G16)^(1/5)-1 -> #DIV/0!
B17: Market Share | M17: =((K17*K16)/(G15*G14))^(1/5)-1 -> -1
B18: Market Size | M18: =(K18/G18)^(1/5)-1 -> #DIV/0!
B19: Market Share | M19: =((K19*K18)/(G19*G18))^(1/5)-1 -> #DIV/0!
B20: Market Size | M20: =(K20/G20)^(1/5)-1 -> #DIV/0!
B21: Market Share | M21: =((K21*K20)/(G21*G20))^(1/5)-1 -> #DIV/0!
A23: x
B25: Industry Driver | D25: Description | O25: Porter's Five Forces
B27: Digitalization & E-Commerce | D27: Online sales are growing rapidly, especially in emerging markets
B28: Sustainability & Circular Economy | D28: Consumers demand eco-friendly materials and recycling models
B29: Artificial Intelligence & Personalization | D29: AI supports product recommendations, inventory optimization, and design
B30: Demographic Shift & “Silver Generation” | D30: Older consumers with high purchasing power influence design and marketing
B31: Resale & Second-Hand Trend | D31: Resale platforms are booming, especially among younger demographics
O32: Rivalry Among Existing Competitors | R32: 5
O33: Threat of New Entrants | R33: 3
O34: Threat of Substitutes | R34: 4
O35: Bargaining Power of Customers | R35: 4
O36: Bargaining Power of Suppliers | R36: 2

Sheet ESG
A7: x | B7: ESG Analysis
B12: ESG Scores | G12: GHG Scope 1 Emissions, Water Consumption, Energy Consumption and Waste Production per Sales
B15: LSEG ESG Score
B16: E-Score
B17: S-Score
B18: G-Score
B19: S&P Global ESG Score | D19: 50
B20: Environmental
B21: Social
B22: Governance & Economic
B23: Sustainalytics
B24: ISS ESG Corporate Rating
B25: SDG Impact Rating
B26: Governance Quality Score
B27: MSCI ESG Ratings
B30: Key Info | G30: Environmental
H32: Overview | I32: Targets | J32: Improvements | K32: Comments
B33: GICS Sector | C33: Consumer Discrecionary | G33: GHG Scope 1 Emissions | I33: Carbon neutrality by 2040 | J33: SBTi-validated climate targets | K33: Exact emission values not disclosed
B34: GICS Industry Group | C34: Consumer Durables & Apparel
B35: GICS Industry | C35: Textiles, Apparel & Luxury Goods | G35: Water Consumption | I35: Eco-efficiency in processes | J35: Circular production model | K35: No specific consumption data available
B36: GICS Sub-Industry | C36: Apparel, Accessories & Luxury Goods
G37: Energy Consumption | I37: Reduce energy intensity | J37: LED lighting, solar integration | K37: No quantitative data disclosed
B38: Headquarters | C38: Belo Horizonte, Minas Gerais, Brazil
B39: Numer of Employees | C39: 6000 | G39: Waste Management | I39: Circular economy | J39: Leather traceability | K39: Prioritizes sustainable materials
B41: Annual Report | C41: https://ri.azzas2154.com.br/ | G41: Other
B42: Sustainability Report | C42: https://ri.azzas2154.com.br/en/sustaintability-report/
B44: Recent Headlines | G44: Social
H46: Overview | I46: Targets | J46: Improvements | K46: Comments
G47: Employee Turnover %
G49: Salaries & Compensation
G51: Reputation | I51: Brand strengthening | J51: B Corp, ISE B3
G53: Discrimination Events | I53: DEI policy | J53: Racial Equity Pact
G55: Work Safety
G57: Damage to consumer health | I57: Sustainable materials | J57: No harmful substances
G59: Pension Plan
G61: Supply chain | I61: Transparency & compliance | J61: Supplier code of conduct | K61: ESG-aligned supplier policy
G63: Community involvement | I63: Social programs | J63: 1P=5P, Fundação Hering | K63: High social impact
G65: Public Sector
G67: Litigation
B70: Board of Directors | G70: Governance
B72: Name | C72: Position | E72: M/F – Age | H72: Overview | I72: Targets | J72: Improvements | K72: Comments
B73: Nicola Calicchio | C73: Chairman of the Board | E73: M / 52 | G73: Diversity (Gender, Age, Industry, Region) | I73: DEI promotion | J73: Gender & age diversity | K73: International and diverse profiles
B74: Alexandre Birman | C74: CEO & Board Member | E74: M / 48
B75: Roberto Jatahy | C75: Board Member | E75: M / 53 | G75: % Independence | I75: 0.2 | J75: 2 out of 7 are independent
B76: Cristiane Correa | C76: Independent Board Member | E76: F / 50
B77: Carlos Jereissati Filho | C77: Board Member | E77: M / 55 | G77: Average time as independent directors | I77: 2 years | J77: Rotation possible | K77: Uniform tenure
B78: Pedro Parente | C78: Independent Board Member | E78: M / 71
B79: Renata Moraes Vichi | C79: Independent Board Member | E79: F / 46 | G79: Departures of C-level executives | I79: Stability | J79: CEO vs Soma founder conflict | K79: Leadership instability
G81: CEO/Chairman duality | I81: Separation | J81: CEO is not Chairman | K81: Nicola Calicchio is Chairman
G83: Transparency when reporting | I83: Full disclosure | J83: All reports available online | K83: Strong investor relations
G85: Time taken to report | I85: 2 months | J85: Quarterly updates | K85: No delays observed
G87: CEO or Chairman in other boards? | I87: Oversight | J87: CEO on multiple boards | K87: Birman & Calicchio hold other mandates
G89: Audit / Consulting | I89: Oversight | J89: No irregularities
G91: ESG-compensation related | I91: ESG goals | J91: ESG-based bonuses
G93: Management compensation schemes | I93: Long-term goals | J93: Stock-based incentives

Sheet Segments
A7: x | B7: Segments | D7: =F7 -> 2020 | E7: =F7 -> 2020 | F7: 2020 | G7: =F7 -> 2020 | H7: =F7 -> 2020 | J7: =L7 -> 2021 | K7: =L7 -> 2021 | L7: 2021 | M7: =L7 -> 2021 | N7: =L7 -> 2021 | P7: =R7 -> 2022 | Q7: =R7 -> 2022 | R7: 2022 | S7: =R7 -> 2022 | T7: =R7 -> 2022 | V7: =X7 -> 2023 | W7: =X7 -> 2023 | X7: 2023 | Y7: =X7 -> 2023 | Z7: =X7 -> 2023 | AB7: =AD7 -> 2024 | AC7: =AD7 -> 2024 | AD7: 2024 | AE7: =AD7 -> 2024 | AF7: =AD7 -> 2024 | AH7: =AJ7 -> 2025 | AI7: =AJ7 -> 2025 | AJ7: 2025 | AK7: =AJ7 -> 2025 | AL7: =AJ7 -> 2025 | AN7: =AP7 -> 2025 | AO7: =AP7 -> 2025 | AP7: 2025 | AQ7: =AP7 -> 2025 | AR7: =AP7 -> 2025 | AZ7: Products
D8: 2020 | J8: =D8+1 -> 2021 | P8: =J8+1 -> 2022 | V8: =P8+1 -> 2023 | AB8: =V8+1 -> 2024 | AH8: =AB8+1 -> 2025 | AN8: =AH8+1 -> 2026 | AT8: =AN8+1 -> 2027 | AV8: =+AT8+1 -> 2028 | AX8: =+AV8+1 -> 2029
D9: Q1 | E9: Q2 | F9: Q3 | G9: Q4 | H9: FY | J9: Q1 | K9: Q2 | L9: Q3 | M9: Q4 | N9: FY | P9: Q1 | Q9: Q2 | R9: Q3 | S9: Q4 | T9: FY | V9: Q1 | W9: Q2 | X9: Q3 | Y9: Q4 | Z9: FY | AB9: Q1 | AC9: Q2 | AD9: Q3 | AE9: Q4 | AF9: FY | AH9: Q1 | AI9: Q2 | AJ9: Q3 | AK9: Q4 | AL9: FY | AN9: Q1 | AO9: Q2 | AP9: Q3 | AQ9: Q4 | AR9: FY | AT9: FY | AV9: FY | AX9: FY
B12: Revenue by segment:
B13: Shoes & Bags | H13: =295.969+152.38+83.8+78.4+24.5+76.78 -> 711.829 | N13: =6.7+1065+607+292+391+520 -> 2881.7 | T13: =1381+804.7+368.964+275 -> 2829.664 | Z13: =SUM(Z14:Z24) -> 4565.8 | AF13: =SUM(AF14:AF24) -> 4785.2 | AL13: =AL14+AL16+AL20+AL22+AL24 -> 4258.697 | AR13: =AR14+AR16+AR20+AR22+AR24 -> 4575.1898 | AT13: =AT14+AT16+AT20+AT22+AT24 -> 4859.887 | AV13: =AV14+AV16+AV20+AV22+AV24 -> 5107.1826 | AX13: =AX14+AX16+AX20+AX22+AX24 -> 5308.4232
B14: Franchises | Z14: 1193 | AF14: 1199.8 | AL14: =AF14*(1+AL15) -> 1343.776 | AR14: =AL14*(1+AR15) -> 1478.1536 | AT14: =AR14*(1+AT15) -> 1596.4059 | AV14: =AT14*(1+AV15) -> 1692.1902 | AX14: =AV14*(1+AX15) -> 1759.8779
B15: % of growth | AL15: 0.12 | AR15: =AL15-($AL$15-$AX$15)/4 -> 0.1 | AT15: =AR15-($AL$15-$AX$15)/4 -> 0.08 | AV15: =AT15-($AL$15-$AX$15)/4 -> 0.06 | AX15: 0.04
B16: Multi-brand | Z16: 1278.9 | AF16: 1255.4 | AL16: =AF16*(1+AL17) -> 1318.17 | AR16: =AL16*(1+AR17) -> 1410.4419 | AT16: =AR16*(1+AT17) -> 1490.3669 | AV16: =AT16*(1+AV17) -> 1554.9495 | AX16: =AV16*(1+AX17) -> 1601.598
B17: % of growth | AL17: 0.05 | AR17: 0.07 | AT17: =AR17-($AR$17-$AX$17)/3 -> 0.056666667 | AV17: =AT17-($AR$17-$AX$17)/3 -> 0.043333333 | AX17: 0.03
B18: Owned Stores | Z18: 716.5 | AF18: 821.4 | AL18: =AF18*(1+AL19) -> 878.898 | AR18: =AL18*(1+AR19) -> 936.02637 | AT18: =AR18*(1+AT19) -> 992.18795 | AV18: =AT18*(1+AV19) -> 1046.7583 | AX18: =AV18*(1+AX19) -> 1099.0962
B19: % of growth | AL19: 0.07 | AR19: =AL19-($AL$19-$AX$19)/4 -> 0.065 | AT19: =AR19-($AL$19-$AX$19)/4 -> 0.06 | AV19: =AT19-($AL$19-$AX$19)/4 -> 0.055 | AX19: 0.05
B20: Web Commerce | Z20: 902.4 | AF20: 1028.5 | AL20: =AF20*(1+AL21) -> 1110.78 | AR20: =AL20*(1+AR21) -> 1177.4268 | AT20: =AR20*(1+AT21) -> 1244.1477 | AV20: =AT20*(1+AV21) -> 1310.5022 | AX20: =AV20*(1+AX21) -> 1376.0273
B21: % of growth | AL21: 0.08 | AR21: 0.06 | AT21: =AR21-($AR$21-$AX$21)/3 -> 0.056666667 | AV21: =AT21-($AR$21-$AX$21)/3 -> 0.053333333 | AX21: 0.05
B22: International | Z22: 430.4 | AF22: 426.6 | AL22: =AF22*(1+AL23) -> 430.866 | AR22: =AL22*(1+AR23) -> 452.4093 | AT22: =AR22*(1+AT23) -> 470.50567 | AV22: =AT22*(1+AV23) -> 489.3259 | AX22: =AV22*(1+AX23) -> 508.89893
B23: % of growth | AL23: 0.01 | AR23: 0.05 | AT23: 0.04 | AV23: 0.04 | AX23: 0.04
B24: Others | Z24: 44.6 | AF24: 53.5 | AL24: =AF24*(1+AL25) -> 55.105 | AR24: =AL24*(1+AR25) -> 56.75815 | AT24: =AR24*(1+AT25) -> 58.460895 | AV24: =AT24*(1+AV25) -> 60.214721 | AX24: =AV24*(1+AX25) -> 62.021163
B25: % of growth | AL25: 0.03 | AR25: 0.03 | AT25: 0.03 | AV25: 0.03 | AX25: 0.03
B27: Fashion & Lifestyle Women | H27: =26.3+398+75+46.9+614.4+95.2+90.7+75.1 -> 1421.6 | N27: =540.6+87.4+72.6+898.4+271.7+173.5+243.8+72.8 -> 2360.8 | T27: =463+275+670.1+1191.7+490.9+193.4+381.4+120.4+62.1+104.6+463 -> 4415.6 | Z27: =SUM(Z28:Z38) -> 4103.9 | AF27: =SUM(AF28:AF38) -> 4782.1 | AL27: =AL28+AL30+AL32+AL34+AL36+AL38 -> 5634.651 | AR27: =AR28+AR30+AR32+AR34+AR36+AR38 -> 6530.2666 | AT27: =AT28+AT30+AT32+AT34+AT36+AT38 -> 7437.1189 | AV27: =AV28+AV30+AV32+AV34+AV36+AV38 -> 8316.3496 | AX27: =AX28+AX30+AX32+AX34+AX36+AX38 -> 9124.7281
B28: Franchises | Z28: 15.2 | AF28: 9.9 | AL28: =AF28*(1+AL29) -> 10.098 | AR28: =AL28*(1+AR29) -> 10.29996 | AT28: =AR28*(1+AT29) -> 10.505959 | AV28: =AT28*(1+AV29) -> 10.716078 | AX28: =AV28*(1+AX29) -> 10.9304
B29: % of growth | AL29: 0.02 | AR29: 0.02 | AT29: 0.02 | AV29: 0.02 | AX29: 0.02
B30: Multi-brand | Z30: 810.6 | AF30: 856.6 | AL30: =AF30*(1+AL31) -> 1070.75 | AR30: =AL30*(1+AR31) -> 1298.2844 | AT30: =AR30*(1+AT31) -> 1525.4841 | AV30: =AT30*(1+AV31) -> 1735.2382 | AX30: =AV30*(1+AX31) -> 1908.762
B31: % of growth | AL31: 0.25 | AR31: =AL31-($AL$31-$AX$31)/4 -> 0.2125 | AT31: =AR31-($AL$31-$AX$31)/4 -> 0.175 | AV31: =AT31-($AL$31-$AX$31)/4 -> 0.1375 | AX31: 0.1
B32: Owned Stores | Z32: 1765.3 | AF32: 2090.8 | AL32: =AF32*(1+AL33) -> 2404.42 | AR32: =AL32*(1+AR33) -> 2716.9946 | AT32: =AR32*(1+AT33) -> 3015.864 | AV32: =AT32*(1+AV33) -> 3287.2918 | AX32: =AV32*(1+AX33) -> 3517.4022
B33: % of growth | AL33: 0.15 | AR33: =AL33-($AL$33-$AX$33)/4 -> 0.13 | AT33: =AR33-($AL$33-$AX$33)/4 -> 0.11 | AV33: =AT33-($AL$33-$AX$33)/4 -> 0.09 | AX33: 0.07
B34: Web Commerce | Z34: 719.2 | AF34: 789.9 | AL34: =AF34*(1+AL35) -> 884.688 | AR34: =AL34*(1+AR35) -> 982.00368 | AT34: =AR34*(1+AT35) -> 1080.204 | AV34: =AT34*(1+AV35) -> 1177.4224 | AX34: =AV34*(1+AX35) -> 1271.6162
B35: % of growth | AL35: 0.12 | AR35: =AL35-($AL$35-$AX$35)/4 -> 0.11 | AT35: =AR35-($AL$35-$AX$35)/4 -> 0.1 | AV35: =AT35-($AL$35-$AX$35)/4 -> 0.09 | AX35: 0.08
B36: International | Z36: 775.3 | AF36: 995.7 | AL36: =AF36*(1+AL37) -> 1224.711 | AR36: =AL36*(1+AR37) -> 1481.9003 | AT36: =AR36*(1+AT37) -> 1763.4614 | AV36: =AT36*(1+AV37) -> 2063.2498 | AX36: =AV36*(1+AX37) -> 2372.7373
B37: % of growth | AL37: 0.23 | AR37: =AL37-($AL$37-$AX$37)/4 -> 0.21 | AT37: =AR37-($AL$37-$AX$37)/4 -> 0.19 | AV37: =AT37-($AL$37-$AX$37)/4 -> 0.17 | AX37: 0.15
B38: Others | Z38: 18.3 | AF38: 39.2 | AL38: =AF38*(1+AL39) -> 39.984 | AR38: =AL38*(1+AR39) -> 40.78368 | AT38: =AR38*(1+AT39) -> 41.599354 | AV38: =AT38*(1+AV39) -> 42.431341 | AX38: =AV38*(1+AX39) -> 43.279967
B39: % of growth | AL39: 0.02 | AR39: 0.02 | AT39: 0.02 | AV39: 0.02 | AX39: 0.02
B41: Basic | H41: 8.5 | N41: 1849.4 | T41: 2330.4 | Z41: =SUM(Z42:Z52) -> 2587.7 | AF41: =SUM(AF42:AF52) -> 2794 | AL41: =AL42+AL44+AL46+AL48+AL50+AL52 -> 3047.724 | AR41: =AR42+AR44+AR46+AR48+AR50+AR52 -> 3335.3089 | AT41: =AT42+AT44+AT46+AT48+AT50+AT52 -> 3623.619 | AV41: =AV42+AV44+AV46+AV48+AV50+AV52 -> 3906.7965 | AX41: =AX42+AX44+AX46+AX48+AX50+AX52 -> 4178.4062
B42: Franchises | Z42: 787.5 | AF42: 823.5 | AL42: =AF42*(1+AL43) -> 856.44 | AR42: =AL42*(1+AR43) -> 916.3908 | AT42: =AR42*(1+AT43) -> 974.42888 | AV42: =AT42*(1+AV43) -> 1029.6465 | AX42: =AV42*(1+AX43) -> 1081.1288
AL43: 0.04 | AR43: 0.07 | AT43: =AR43-($AR$43-$AX$43)/3 -> 0.063333333 | AV43: =AT43-($AR$43-$AX$43)/3 -> 0.056666667 | AX43: 0.05
B44: Multi-brand | Z44: 881.8 | AF44: 856.4 | AL44: =AF44*(1+AL45) -> 924.912 | AR44: =AL44*(1+AR45) -> 994.2804 | AT44: =AR44*(1+AT45) -> 1063.88 | AV44: =AT44*(1+AV45) -> 1133.0322 | AX44: =AV44*(1+AX45) -> 1201.0142
AL45: 0.08 | AR45: =AL45-($AL$45-$AX$45)/4 -> 0.075 | AT45: =AR45-($AL$45-$AX$45)/4 -> 0.07 | AV45: =AT45-($AL$45-$AX$45)/4 -> 0.065 | AX45: 0.06
B46: Owned Stores | Z46: 566.3 | AF46: 610.6 | AL46: =AF46*(1+AL47) -> 714.402 | AR46: =AL46*(1+AR47) -> 823.3483 | AT46: =AR46*(1+AT47) -> 934.50033 | AV46: =AT46*(1+AV47) -> 1044.3041 | AX46: =AV46*(1+AX47) -> 1148.7345
AL47: 0.17 | AR47: =AL47-($AL$47-$AX$47)/4 -> 0.1525 | AT47: =AR47-($AL$47-$AX$47)/4 -> 0.135 | AV47: =AT47-($AL$47-$AX$47)/4 -> 0.1175 | AX47: 0.1
B48: Web Commerce | Z48: 332.3 | AF48: 480 | AL48: =AF48*(1+AL49) -> 528 | AR48: =AL48*(1+AR49) -> 576.84 | AT48: =AR48*(1+AT49) -> 625.8714 | AV48: =AT48*(1+AV49) -> 674.37643 | AX48: =AV48*(1+AX49) -> 721.58278
AL49: 0.1 | AR49: =AL49-($AL$49-$AX$49)/4 -> 0.0925 | AT49: =AR49-($AL$49-$AX$49)/4 -> 0.085 | AV49: =AT49-($AL$49-$AX$49)/4 -> 0.0775 | AX49: 0.07
B50: International | AL50: =AF50*(1+AL51) -> 0 | AR50: =AL50*(1+AR51) -> 0 | AT50: =AR50*(1+AT51) -> 0 | AV50: =AT50*(1+AV51) -> 0 | AX50: =AV50*(1+AX51) -> 0
AL51: 0 | AM51: 0 | AN51: 0 | AO51: 0 | AP51: 0 | AQ51: 0 | AR51: 0 | AS51: 0 | AT51: 0 | AU51: 0 | AV51: 0 | AW51: 0 | AX51: 0
B52: Others | Z52: 19.8 | AF52: 23.5 | AL52: =AF52*(1+AL53) -> 23.97 | AR52: =AL52*(1+AR53) -> 24.4494 | AT52: =AR52*(1+AT53) -> 24.938388 | AV52: =AT52*(1+AV53) -> 25.437156 | AX52: =AV52*(1+AX53) -> 25.945899
AL53: 0.02 | AR53: 0.02 | AT53: 0.02 | AV53: 0.02 | AX53: 0.02
B55: Fashion & Lifestyle Men | H55: =90.3+36.4 -> 126.7 | N55: =73.9+770.6 -> 844.5 | T55: =1200+104.6 -> 1304.6 | Z55: =SUM(Z56:Z66) -> 1516.2 | AF55: =SUM(AF56:AF66) -> 1794.9 | AL55: =AL56+AL58+AL60+AL62+AL64+AL66 -> 1990.696 | AR55: =AR56+AR58+AR60+AR62+AR64+AR66 -> 2142.1538 | AT55: =AT56+AT58+AT60+AT62+AT64+AT66 -> 2290.7106 | AV55: =AV56+AV58+AV60+AV62+AV64+AV66 -> 2432.3082 | AX55: =AX56+AX58+AX60+AX62+AX64+AX66 -> 2562.8377
B56: Franchises | Z56: 116.2 | AF56: 154.7 | AL56: =AF56*(1+AL57) -> 185.64 | AR56: =AL56*(1+AR57) -> 216.7347 | AT56: =AR56*(1+AT57) -> 245.99388 | AV56: =AT56*(1+AV57) -> 271.20826 | AX56: =AV56*(1+AX57) -> 290.19284
AL57: 0.2 | AR57: =AL57-($AL$57-$AX$57)/4 -> 0.1675 | AT57: =AR57-($AL$57-$AX$57)/4 -> 0.135 | AV57: =AT57-($AL$57-$AX$57)/4 -> 0.1025 | AX57: 0.07
B58: Multi-brand | Z58: 276.4 | AF58: 289.5 | AL58: =AF58*(1+AL59) -> 364.77 | AR58: =AL58*(1+AR59) -> 393.9516 | AT58: =AR58*(1+AT59) -> 421.52821 | AV58: =AT58*(1+AV59) -> 446.8199 | AX58: =AV58*(1+AX59) -> 469.1609
AL59: 0.26 | AR59: 0.08 | AT59: =AR59-($AR$59-$AX$59)/3 -> 0.07 | AV59: =AT59-($AR$59-$AX$59)/3 -> 0.06 | AX59: 0.05
B60: Owned Stores | Z60: 643.4 | AF60: 784.8 | AL60: =AF60*(1+AL61) -> 863.28 | AR60: =AL60*(1+AR61) -> 943.1334 | AT60: =AR60*(1+AT61) -> 1023.2997 | AV60: =AT60*(1+AV61) -> 1102.6055 | AX60: =AV60*(1+AX61) -> 1179.7879
AL61: 0.1 | AR61: =AL61-($AL$61-$AX$61)/4 -> 0.0925 | AT61: =AR61-($AL$61-$AX$61)/4 -> 0.085 | AV61: =AT61-($AL$61-$AX$61)/4 -> 0.0775 | AX61: 0.07
B62: Web Commerce | Z62: 478.9 | AF62: 555.3 | AL62: =AF62*(1+AL63) -> 566.406 | AR62: =AL62*(1+AR63) -> 577.73412 | AT62: =AR62*(1+AT63) -> 589.2888 | AV62: =AT62*(1+AV63) -> 601.07458 | AX62: =AV62*(1+AX63) -> 613.09607
AL63: 0.02 | AR63: 0.02 | AT63: 0.02 | AV63: 0.02 | AX63: 0.02
B64: International | AL64: =AF64*(1+AL65) -> 0 | AR64: =AL64*(1+AR65) -> 0 | AT64: =AR64*(1+AT65) -> 0 | AV64: =AT64*(1+AV65) -> 0 | AX64: =AV64*(1+AX65) -> 0
AL65: 0 | AM65: 0 | AN65: 0 | AO65: 0 | AP65: 0 | AQ65: 0 | AR65: 0 | AS65: 0 | AT65: 0 | AU65: 0 | AV65: 0 | AW65: 0 | AX65: 0
B66: Others | Z66: 1.3 | AF66: 10.6 | AL66: =AF66*(1+AL67) -> 10.6 | AR66: =AL66*(1+AR67) -> 10.6 | AT66: =AR66*(1+AT67) -> 10.6 | AV66: =AT66*(1+AV67) -> 10.6 | AX66: =AV66*(1+AX67) -> 10.6
AL67: 0 | AR67: 0 | AT67: 0 | AV67: 0 | AX67: 0
B69: Total revenue | D69: =IS!D18 -> 375.471 | E69: =IS!E18 -> 154.443 | F69: =IS!F18 -> 416.463 | G69: =IS!G18 -> 644.615 | H69: =IS!H18 -> 1590.992 | J69: =IS!J18 -> 499.952 | K69: =IS!K18 -> 552.976 | L69: =IS!L18 -> 777.949 | M69: =IS!M18 -> 1092.95 | N69: =IS!N18 -> 2923.827 | P69: =IS!P18 -> 839.576 | Q69: =IS!Q18 -> 944.752 | R69: =IS!R18 -> 1137.985 | S69: =IS!S18 -> 1311.413 | T69: =IS!T18 -> 4233.726 | V69: =IS!V18 -> 1025.291 | W69: =IS!W18 -> 1131.023 | X69: =IS!X18 -> 1265.824 | Y69: =IS!Y18 -> 1424.631 | Z69: =IS!Z18 -> 4846.768 | AB69: =IS!AB18 -> 1072.182 | AC69: =IS!AC18 -> 1357.108 | AD69: =IS!AD18 -> 2546.621 | AE69: =IS!AE18 -> 3403.842 | AF69: =IS!AF18 -> 8379.753 | AH69: =IS!AH18 -> 2696.538 | AI69: =IS!AI18 -> 2901.385 | AJ69: =IS!AJ18 -> 0 | AK69: =IS!AK18 -> 0 | AL69: =AL55+AL41+AL27+AL13 -> 14931.768 | AN69: =IS!AN18 -> 0 | AO69: =IS!AO18 -> 0 | AP69: =IS!AP18 -> 0 | AQ69: =IS!AQ18 -> 0 | AR69: =AR55+AR41+AR27+AR13 -> 16582.919 | AT69: =AT55+AT41+AT27+AT13 -> 18211.336 | AV69: =AV55+AV41+AV27+AV13 -> 19762.637 | AX69: =AX55+AX41+AX27+AX13 -> 21174.395
H70: =H55+H41+H27+H13 -> 2268.629 | N70: =N55+N41+N27+N13 -> 7936.4 | T70: =T55+T41+T27+T13 -> 10880.264 | Z70: =Z55+Z41+Z27+Z13 -> 12773.6 | AF70: =AF55+AF41+AF27+AF13 -> 14156.2 | AL70: =AL69/AF70-1 -> 0.054786454 | AR70: =AR69/AL69-1 -> 0.11057974 | AT70: =AT69/AR69-1 -> 0.098198423 | AV70: =AV69/AT69-1 -> 0.085183277 | AX70: =+AX69/AV69-1 -> 0.071435728
B72: Revenue by region: | BI72: 2021 | BJ72: =BI72+1 -> 2022 | BK72: =BJ72+1 -> 2023 | BL72: =BK72+1 -> 2024 | BM72: Average
B73: Brazil | H73: 1591 | N73: 2923.8 | T73: 4233.7 | Z73: 4846.8 | AF73: 8379.8 | AL73: =AL78*$BM$73 -> 13466.914 | AR73: =AR78*$BM$73 -> 14956.081 | AT73: =AT78*$BM$73 -> 16424.745 | AV73: =AV78*$BM$73 -> 17823.859 | AX73: =AX78*$BM$73 -> 19097.119 | BI73: =N73/(N73+N74) -> 0.88196434 | BJ73: =T73/(T73+T74) -> 0.88506324 | BK73: =Z73/(Z73+Z74) -> 0.89566471 | BL73: =AF73/(AF73+AF74) -> 0.94489485 | BM73: =AVERAGE(BI73,BJ73,BK73,BL73) -> 0.90189679
B74: Rest of the World | N74: 391.3 | T74: 549.8 | Z74: 564.6 | AF74: 488.7 | AL74: =AL78*$BM$74 -> 1464.8544 | AR74: =AR78*$BM$74 -> 1626.8377 | AT74: =AT78*$BM$74 -> 1786.5906 | AV74: =AV78*$BM$74 -> 1938.7782 | AX74: =AX78*$BM$74 -> 2077.2762 | BI74: =1-BI73 -> 0.11803566 | BJ74: =1-BJ73 -> 0.11493676 | BK74: =1-BK73 -> 0.10433529 | BL74: =1-BL73 -> 0.055105147 | BM74: =AVERAGE(BI74,BJ74,BK74,BL74) -> 0.098103214
B78: Total revenue | D78: =IS!D18 -> 375.471 | E78: =IS!E18 -> 154.443 | F78: =IS!F18 -> 416.463 | G78: =IS!G18 -> 644.615 | H78: =IS!H18 -> 1590.992 | J78: =IS!J18 -> 499.952 | K78: =IS!K18 -> 552.976 | L78: =IS!L18 -> 777.949 | M78: =IS!M18 -> 1092.95 | N78: =IS!N18 -> 2923.827 | P78: =IS!P18 -> 839.576 | Q78: =IS!Q18 -> 944.752 | R78: =IS!R18 -> 1137.985 | S78: =IS!S18 -> 1311.413 | T78: =IS!T18 -> 4233.726 | V78: =IS!V18 -> 1025.291 | W78: =IS!W18 -> 1131.023 | X78: =IS!X18 -> 1265.824 | Y78: =IS!Y18 -> 1424.631 | Z78: =IS!Z18 -> 4846.768 | AB78: =IS!AB18 -> 1072.182 | AC78: =IS!AC18 -> 1357.108 | AD78: =IS!AD18 -> 2546.621 | AE78: =IS!AE18 -> 3403.842 | AF78: =IS!AF18 -> 8379.753 | AH78: =IS!AH18 -> 2696.538 | AI78: =IS!AI18 -> 2901.385 | AJ78: =IS!AJ18 -> 0 | AK78: =IS!AK18 -> 0 | AL78: =AL69 -> 14931.768 | AN78: =IS!AN18 -> 0 | AO78: =IS!AO18 -> 0 | AP78: =IS!AP18 -> 0 | AQ78: =IS!AQ18 -> 0 | AR78: =AR69 -> 16582.919 | AT78: =AT69 -> 18211.336 | AV78: =AV69 -> 19762.637 | AX78: =AX69 -> 21174.395
B80: Products:
A87: x | B87: Notes & Forecasts
B92: Shoes & Bags | H92: The franchise segment should recover as confidence returns, supported by the rollout of over 120 new points in 2Q25 under a more agile structure. Meanwhile, the multi-brand channel faces short-term contraction but may regain traction from 2026 with planned investments in growth levers and active management. Owned stores continue to show solid momentum, with SSS up 5% in 2Q25, particularly in São Paulo and Rio de Janeiro. Although web commerce has received limited attention, it is likely to accelerate in 2025–2026, driven by lower interest rates and new taxes on foreign fast-fashion players. The international segment saw a temporary decline in 2Q25, yet still delivered double-digit growth in 1H25, with potential recovery in 2026 depending on political outcomes. The others segment should remain stable, contributing modestly to total revenue.
B93: Fashion & Lifestyle Women | H93: In 2025, the Fashion & Lifestyle Women unit is expected to maintain strong momentum, driven primarily by its owned store strategy, which remains the core focus, leaving limited room for franchise expansion. The channel has already accumulated 31.4% growth in 1H25, but we project a convergence toward 10% in the following quarters as performance stabilizes. The company plans to open 12 new FARM stores throughout the year, supported by robust Same Store Sales — +22% for FARM and +16% for Animale — reflecting successful strategic adjustments and indicating the potential for strong returns on new openings. The multi-brand channel was a highlight in 2Q25, expanding 14.5% due to solid performances from FARM, Animale, and NV, coupled with improved inventory availability. Despite a challenging macroeconomic backdrop, web commerce delivered +35.2% growth in 2Q25, showcasing the channel’s resilience and scalability; we expect around 10% growth for the full year, with possible upside to 15% in 2026, depending on the political environment following Brazil’s elections. The international and others segments remain secondary within this business unit, with limited contribution to consolidated results.
B94: Basic | H94: In 2025, the Basic segment is expected to deliver moderate yet consistent growth, supported by the continued rollout of its megastore project and strategic improvements in distribution and marketing. Although the company initially envisioned 2025 as a year to consolidate the franchise megastore model, 2Q25 showed a temporary 7.8% contraction due to lower inventory levels, which created short-term gaps in product availability. Despite this, the franchise expansion plan remains intact, with further rollout expected in the coming years. The multi-brand channel grew 8.4%, driven by the new go-to-market project, which added 132 new clients and boosted sales by 37%. The megastore initiative, launched in 2024 across both franchise and owned stores, continues to deliver solid results, with 24.5% growth in 2Q25, reinforcing management’s intention to maintain the model. Meanwhile, web commerce followed a strong growth trajectory of 15.9%, fueled by the adoption of programmatic media (ad cost), logistics optimization, and a supportive macroeconomic environment.
B95: Fashion & Lifestyle Men | H95: e

Sheet Peers
B7: Peers
A12: x | B12: Growth | C12: AZZAS 2154 SA | D12: GUARARAPES | E12: LOJAS RENNER SA | F12: C&A MODAS LTDA | G12: MARISA LOJAS SA | H12: VESTE SA ESTILO | I12: VULCABRAS SA | J12: GRENDENE SA | K12: ALPARGATAS-PREF | L12: GRUPO SBF SA | M12: TRACK & FIELD CO | N12: REDTAPE LTD/INDI | O12: LI NING CO LTD | P12: TOPSPORTS INTERN | Q12: CHINA LILANG LTD | R12: DAZZLE FASHION-A
B14: Revenue (LTM) | C14: 1.2556565 | D14: 0.11258158 | E14: 0.11855769 | F14: 0.12668832 | G14: 0.15093568 | H14: 0.05878629 | I14: 0.14072007 | J14: 0.10465911 | K14: 0.12981686 | L14: 0.12981686 | M14: 0.025524777 | N14: 0.025524777 | O14: 0.025524777 | P14: 0.025524777 | Q14: 0.025524777 | R14: 0.025524777
B15: Revenue (3-yr CAGR) | C15: 0.46735652 | D15: 0.074483354 | E15: 0.065973345 | F15: 0.099914554 | G15: -0.1879159 | H15: 0.045729191 | I15: 0.1278818 | J15: 0.030018488 | K15: 0.024792939 | L15: 0.069313482 | M15: 0.21460678 | N15: 0 | O15: 0.055534968 | P15: -0.053689788 | Q15: 0.033368996 | R15: -0.065916061
B16: Gross profit (LTM) | C16: 1.3232691 | D16: 0.14565826 | E16: 0.13090249 | F16: 0.15852495 | G16: 0.32239037 | H16: 0.035551934 | I16: 0.12152993 | J16: 0.15297977 | K16: 0.24266392 | L16: 0.24266392 | M16: 0.056092437 | N16: 0.056092437 | O16: 0.056092437 | P16: 0.056092437 | Q16: 0.056092437 | R16: 0.056092437
B17: EBIT (LTM) | C17: 0.74828656 | D17: 0.45272413 | E17: 0.4363497 | F17: -0.456377 | G17: -1.5516545 | H17: 0.40695062 | I17: 0.26944998 | J17: -0.0072534124 | K17: -1.2785196 | L17: -1.2785196 | M17: -0.13783918 | N17: -0.13783918 | O17: -0.13783918 | P17: -0.13783918 | Q17: -0.13783918 | R17: -0.13783918
B18: EBITDA (LTM) | C18: 1.0020522 | D18: 0.25926503 | E18: 0.26076944 | F18: -0.26252502 | G18: -3.2686743 | H18: 0.053443644 | I18: 0.23964658 | J18: 0.1005505 | K18: -1.6211 | L18: -1.6211 | M18: -0.059208487 | N18: -0.059208487 | O18: -0.059208487 | P18: -0.059208487 | Q18: -0.059208487 | R18: -0.059208487
B19: FCF (LTM) | C19: =-(55/177.4)-1 -> -1.3100338 | D19: 0.12284517 | E19: 0.021083572 | F19: 0.63279099 | G19: =(-88.2/279.4)-1 -> -1.3156764 | H19: 0.80945236 | I19: -0.045196394 | J19: -0.16044988 | K19: 16.335793 | L19: 0.86648428 | M19: 0.24876016 | N19: -2.8232662 | O19: 0.45966728 | P19: -0.029005954 | Q19: -0.56520088 | R19: -0.45922865
A21: x | B21: Margins | C21: AZZAS 2154 SA | D21: GUARARAPES | E21: LOJAS RENNER SA | F21: C&A MODAS LTDA | G21: MARISA LOJAS SA | H21: VESTE SA ESTILO | I21: VULCABRAS SA | J21: GRENDENE SA | K21: ALPARGATAS-PREF | L21: GRUPO SBF SA | M21: TRACK & FIELD CO | N21: REDTAPE LTD/INDI | O21: LI NING CO LTD | P21: TOPSPORTS INTERN | Q21: CHINA LILANG LTD | R21: DAZZLE FASHION-A
B23: Gross margin | C23: 0.53283921 | D23: 0.58975139 | E23: 0.60555052 | F23: 0.5469191 | G23: 0.49099499 | H23: 0.63268754 | I23: 0.4193401 | J23: 0.47214618 | K23: 0.43149022 | L23: 0.4912284 | M23: 0.56584059 | N23: =2508.1/20209.1 -> 0.12410746 | O23: 0.49366297 | P23: 0.38438672 | Q23: 0.4765214 | R23: 0.74840407
B24: EBIT margin | C24: 0.04578166 | D24: 0.079076046 | E24: 0.087234073 | F24: 0.10597013 | G24: -0.031269192 | H24: 0.039080387 | I24: 0.18839931 | J24: 0.19444034 | K24: 0.0072864493 | L24: 0.085515025 | M24: 0.19742017 | N24: 0.12461713 | O24: 0.12826935 | P24: 0.058960719 | Q24: 0.15136701 | R24: 0.16262923
B25: EBITDA margin | C25: 0.12207758 | D25: 0.15388595 | E25: 0.19028459 | F25: 0.2109477 | G25: 0.23217044 | H25: 0.19796399 | I25: 0.25010125 | J25: 0.20331435 | K25: 0.11284125 | L25: 0.1400035 | M25: 0.24680886 | N25: 0.16590051 | O25: 0.182683 | P25: 0.11302378 | Q25: 0.18864833 | R25: 0.217
B26: Net margin | C26: 0.04078008 | D26: 0.024406575 | E26: 0.082892606 | F26: 0.05925158 | G26: -0.22682878 | H26: 0.00059826099 | I26: 0.18693076 | J26: 0.27970844 | K26: 0.026283064 | L26: 0.074982864 | M26: 0.14157106 | N26: 0.08412052 | O26: 0.10506889 | P26: 0.047606884 | Q26: 0.12633429 | R26: 0.13678793
B27: SG&A margin | C27: =(5548.7/11548.4) -> 0.48047349 | D27: 0.43787537 | E27: 0.35119912 | F27: 0.33611784 | G27: 0.44772007 | H27: 0.5950034 | I27: 0.23384148 | J27: 0.27222911 | K27: 0.37046635 | L27: 0.35267042 | M27: 0.37291451 | O27: 0.37058677 | P27: 0.33092708 | Q27: 0.34168077 | R27: 0.47491698
B28: R&D margin | O28: 0.024136005 | Q28: 0.037294207 | R28: 0.035670317
A30: x | B30: Returns | C30: AZZAS 2154 SA | D30: GUARARAPES | E30: LOJAS RENNER SA | F30: C&A MODAS LTDA | G30: MARISA LOJAS SA | H30: VESTE SA ESTILO | I30: VULCABRAS SA | J30: GRENDENE SA | K30: ALPARGATAS-PREF | L30: GRUPO SBF SA | M30: TRACK & FIELD CO | N30: REDTAPE LTD/INDI | O30: LI NING CO LTD | P30: TOPSPORTS INTERN | Q30: CHINA LILANG LTD | R30: DAZZLE FASHION-A
B32: ROIC | C32: 0.16918018 | D32: 0.069005171 | E32: 0.097664511 | F32: 0.14464212 | G32: 0.11062665 | H32: 0.041986884 | I32: 0.24773206 | J32: 0.099680305 | K32: 0.049972688 | L32: 0.10286241 | M32: 0.24942472 | N32: 0.13886843 | O32: 0.086845471 | P32: 0.10023206 | Q32: 0.06732947 | R32: 0.055541628
B33: CROIC | C33: -0.0051281769 | D33: 0.15597084 | E33: 0.12040782 | F33: 0.18381891 | G33: -0.085671997 | H33: 0.17803777 | I33: 0.14329723 | J33: 0.12380824 | K33: 0.12433083 | L33: 0.15469667 | M33: 0.084197026 | N33: -0.12402523 | O33: 0.15398744 | P33: 0.25743589 | Q33: 0.075427382 | R33: 0.092778969
B34: ROCE | C34: 0.080544041 | D34: 0.14595231 | E34: 0.13188882 | F34: 0.22077174 | G34: -0.53597636 | H34: 0.092869726 | I34: 0.27617269 | J34: 0.16736201 | K34: 0.0092236426 | L34: 0.20200546 | M34: 0.27095314 | N34: 0.22679298 | O34: 0.17848211 | P34: 0.17996203 | Q34: 0.15399648 | R34: 0.10169918
B35: RONA | C35: 0.049684421 | D35: 0.14098604 | E35: 0.11689861 | F35: 0.24459663 | G35: -0.15295424 | H35: 0.041637752 | I35: 0.27216007 | J35: 0.12648078 | K35: 0.0074163006 | L35: 0.20302429 | M35: 0.3472988 | N35: 0.31925359 | O35: 0.14090752 | P35: 0.17581411 | Q35: 0.13624141 | R35: 0.09829913
B36: ROE | C36: 0.139305 | D36: 0.077408803 | E36: 0.13269836 | F36: 0.15221259 | G36: -2.2154 | H36: 0.00050451406 | I36: 0.36040769 | J36: 0.21160091 | K36: 0.06471241 | L36: 0.13232501 | M36: 0.27925058 | N36: 0.23655959 | O36: 0.10544833 | P36: 0.13602924 | Q36: 0.10359023 | R36: 0.070283704
B37: ROA | C37: 0.073857084 | D37: 0.030591115 | E37: 0.072035651 | F37: 0.057445468 | G37: -0.029876775 | H37: 0.00031506099 | I37: 0.25766966 | J37: 0.19165889 | K37: 0.040760494 | L37: 0.045710792 | M37: 0.1751245 | N37: 0.089178457 | O37: 0.077390538 | P37: 0.087344846 | Q37: 0.064491798 | R37: 0.05479408
A39: x | B39: Efficiency | C39: AZZAS 2154 SA | D39: GUARARAPES | E39: LOJAS RENNER SA | F39: C&A MODAS LTDA | G39: MARISA LOJAS SA | H39: VESTE SA ESTILO | I39: VULCABRAS SA | J39: GRENDENE SA | K39: ALPARGATAS-PREF | L39: GRUPO SBF SA | M39: TRACK & FIELD CO | N39: REDTAPE LTD/INDI | O39: LI NING CO LTD | P39: TOPSPORTS INTERN | Q39: CHINA LILANG LTD | R39: DAZZLE FASHION-A
B41: Asset turnover | C41: 1.0732879 | D41: 0.75544775 | E41: 0.81268039 | F41: 0.91776054 | G41: 0.74016266 | H41: 0.69291238 | I41: 1.0574968 | J41: 0.64482474 | K41: 0.68295093 | L41: 0.8726369 | M41: 1.2196158 | N41: 1.0601273 | O41: 0.80609823 | P41: 1.8347104 | Q41: 0.57519467 | R41: 0.47045338
B42: Net operating asset turnover | C42: 0.76537203 | D42: 1.0571958 | E42: 1.0299645 | F42: 1.4809611 | G42: 1.186773 | H42: 0.88661466 | I42: 1.3148879 | J42: 0.80942694 | K42: 1.0990872 | L42: 1.4212626 | M42: 1.2787007 | N42: 1.3592346 | O42: 1.0928419 | P42: 3.2742115 | Q42: 0.77533427 | R42: 1.7637767
B43: Fixed asset turnover | C43: 7.6145874 | D43: 4.1347389 | E43: 3.0796469 | F43: 3.6836739 | G43: 2.9318356 | H43: 3.6846039 | I43: 6.2570456 | J43: 5.027273 | K43: 2.7867584 | L43: 3.6671263 | M43: 4.7902592 | N43: 2.8675559 | O43: 4.6145698 | P43: 11.208672 | Q43: 2.7054077 | R43: 3.2506133
B44: Revenue per employee thsnd of USD | D44: 59.252105 | E44: 107.49758 | J44: 27.460398 | N44: 291.92391 | O44: 804.16277 | P44: 137.22917 | Q44: 105.15313 | R44: 431.72673
B45: EBIT per employee thsnd of USD | D45: 5.2598321 | E45: 12.531122 | J45: 4.5698511 | N45: 36.229934 | O45: 117.78982 | P45: 8.708367 | Q45: 14.012604 | R45: 49.015191
A47: x | B47: Working Capital | C47: AZZAS 2154 SA | D47: GUARARAPES | E47: LOJAS RENNER SA | F47: C&A MODAS LTDA | G47: MARISA LOJAS SA | H47: VESTE SA ESTILO | I47: VULCABRAS SA | J47: GRENDENE SA | K47: ALPARGATAS-PREF | L47: GRUPO SBF SA | M47: TRACK & FIELD CO | N47: REDTAPE LTD/INDI | O47: LI NING CO LTD | P47: TOPSPORTS INTERN | Q47: CHINA LILANG LTD | R47: DAZZLE FASHION-A
B49: DSO | C49: 56.262752 | D49: 167.0841 | E49: 147.53405 | F49: 66.590651 | G49: 14.804321 | H49: 55.977601 | I49: 101.73184 | J49: 106.48929 | K49: 75.7619 | L49: 68.88003 | M49: 64.498913 | N49: 18.346537 | O49: 16.046924 | P49: 14.062679 | Q49: 36.482074 | R49: 11.852138
B50: DIO | C50: 120.16759 | D50: 142.5043 | E50: 116.87241 | F50: 113.89348 | G50: 128.22888 | H50: 237.63833 | I50: 138.42486 | J50: 118.45076 | K50: 142.66171 | L50: 181.96172 | M50: 275.4845 | N50: 236.03189 | O50: 58.416455 | P50: 134.85213 | Q50: 177.3857 | R50: 289.71089
B51: DPO | C51: 61.492327 | D51: 96.515938 | E51: 81.425603 | F51: 137.71892 | G51: 135.37904 | H51: 112.05468 | I51: 22.233345 | J51: 17.631387 | K51: 76.188175 | L51: 102.96857 | M51: 55.496537 | N51: 71.681798 | O51: 43.74594 | P51: 8.1540487 | Q51: 76.218277 | R51: 39.798343
B52: CCC | C52: 137.04225 | D52: 213.08118 | E52: 178.16437 | F52: -7.40285 | G52: -64.488004 | H52: 189.8718 | I52: 218.721 | J52: 261.38094 | K52: 141.51727 | L52: 134.35789 | M52: 299.48737 | N52: 182.69663 | O52: 35.543633 | P52: 140.76076 | Q52: 133.67995 | R52: 233.72701
B53: Working capital intensity | C53: 0.14941759 | D53: 0.28904962 | E53: 0.29533558 | F53: 0.15100754 | G53: -0.39784517 | H53: 0.1551868 | I53: 0.45772679 | J53: 0.87837737 | K53: 0.44408789 | L53: 0.20022791 | M53: 0.3922293 | N53: 0.16145202 | O53: 0.41972076 | P53: 0.25363623 | Q53: 0.46271307 | R53: 1.336881
B54: Cash conversion ratio | C54: 0.94869135 | D54: 1.9766761 | E54: 1.9748448 | F54: 1.8351019 | G54: 1.8544749 | H54: 5.4776703 | I54: 0.98286063 | J54: 1.3749467 | K54: 28.228863 | L54: 1.7494633 | M54: 0.61132967 | N54: -0.067701715 | O54: 1.5946657 | P54: 2.3947385 | Q54: 0.97288081 | R54: 1.1237422
B55: CFO margin | C55: 0.043432664 | D55: 0.15630773 | E55: 0.17227376 | F55: 0.19446597 | G55: -0.057987931 | H55: 0.21406948 | I55: 0.18517027 | J55: 0.26734511 | K55: 0.20568818 | L55: 0.1496054 | M55: 0.12068881 | N55: -0.0084367933 | O55: 0.20454673 | P55: 0.1411955 | Q55: 0.14726206 | R55: 0.18275334
A57: x | B57: Leverage & Coverage | C57: AZZAS 2154 SA | D57: GUARARAPES | E57: LOJAS RENNER SA | F57: C&A MODAS LTDA | G57: MARISA LOJAS SA | H57: VESTE SA ESTILO | I57: VULCABRAS SA | J57: GRENDENE SA | K57: ALPARGATAS-PREF | L57: GRUPO SBF SA | M57: TRACK & FIELD CO | N57: REDTAPE LTD/INDI | O57: LI NING CO LTD | P57: TOPSPORTS INTERN | Q57: CHINA LILANG LTD | R57: DAZZLE FASHION-A
B59: Net debt / EBITDA | C59: 2.1403824 | D59: 1.2498803 | E59: 0.44633096 | F59: 1.1909165 | G59: 1.8877603 | H59: 1.3590474 | I59: 0.22024404 | J59: -3.1855785 | K59: -0.033263111 | L59: 2.1254795 | M59: 0.53290463 | N59: 2.1177857 | O59: -1.8691265 | P59: 0.48393436 | Q59: -1.0014637 | R59: -5.3
B60: Net debt / FCF | C60: -50.081462 | D60: 1.1756966 | E60: 0.44562525 | F60: 1.4686036 | G60: -6.1895206 | H60: 1.4633759 | I60: 0.14351818 | J60: -2.9384931 | K60: 0.1626787 | L60: 2.0623351 | M60: 2.3189105 | N60: -3.7769562 | O60: -1.2361179 | P60: 0.42934356 | Q60: 1.1585352 | R60: -7.8585605
B61: Interest coverage | C61: 1.6132164 | D61: 1.6112239 | E61: 3.9661848 | F61: 1.8003907 | G61: -0.31242464 | H61: 0.77774197 | I61: 11.96762 | J61: 51.279422 | K61: 0.16796562 | L61: 3.8319246 | M61: 13.396916 | N61: 5.2488537 | O61: 23.498109 | P61: 8.1012208 | Q61: 17.731217 | R61: 44.534924
B62: Debt / capital | C62: 0.31375999 | D62: 0.36064606 | E62: 0.24926449 | F62: 0.50123625 | G62: 0.69189699 | H62: 0.25007152 | I62: 0.14819096 | J62: 0.02150822 | K62: 0.28555402 | L62: 0.49198655 | M62: 0.24240618 | N62: 0.47847358 | O62: 0.070951944 | P62: 0.30973263 | Q62: 0.24543413 | R62: 0.046116257
B63: Short term debt / total debt | C63: 0.47860682 | D63: 0.33664964 | E63: 0.47963452 | F63: 0.2433991 | G63: 0.35412237 | H63: 0.30988175 | I63: 0.56671569 | J63: 0.73727821 | K63: 0.17941106 | L63: 0.24112899 | M63: 0.10503424 | N63: 0.53207041 | O63: 0.29722144 | P63: 0.72412605 | Q63: 0.45194607 | R63: 0.55651903
A65: x | B65: Liquidity | C65: AZZAS 2154 SA | D65: GUARARAPES | E65: LOJAS RENNER SA | F65: C&A MODAS LTDA | G65: MARISA LOJAS SA | H65: VESTE SA ESTILO | I65: VULCABRAS SA | J65: GRENDENE SA | K65: ALPARGATAS-PREF | L65: GRUPO SBF SA | M65: TRACK & FIELD CO | N65: REDTAPE LTD/INDI | O65: LI NING CO LTD | P65: TOPSPORTS INTERN | Q65: CHINA LILANG LTD | R65: DAZZLE FASHION-A
B67: Current ratio | C67: 1.5123939 | D67: 1.478199 | E67: 1.6105351 | F67: 1.2968936 | G67: 0.65150303 | H67: 1.5172466 | I67: 3.1810758 | J67: 7.0969224 | K67: 2.563074 | L67: 1.5127885 | M67: 2.6763627 | N67: 1.3265441 | O67: 2.7060886 | P67: 2.44354 | Q67: 1.8716078 | R67: 5.6686924
B68: Quick ratio | C68: 0.79493736 | D68: 1.1083243 | E68: 1.2650105 | F68: 0.89223722 | G68: 0.13769664 | H68: 0.71005025 | I68: 1.9375224 | J68: 5.5188969 | K68: 1.8423051 | L68: 0.80757277 | M68: 1.2478592 | N68: 0.11547549 | O68: 1.1178469 | P68: 0.74271035 | Q68: 0.6084047 | R68: 4.7660261
B69: Cash ratio | C69: 0.17146787 | D69: 0.24782912 | E69: 0.36237808 | F69: 0.40842179 | G69: 0.10402766 | H69: 0.17071662 | I69: 0.45996292 | J69: 2.7150326 | K69: 1.1029226 | L69: 0.30932388 | M69: 0.11020464 | N69: 0.012537549 | O69: 0.98541896 | P69: 0.57547652 | Q69: 0.40326541 | R69: 4.6635252
A71: x | B71: Cash Deployment | C71: AZZAS 2154 SA | D71: GUARARAPES | E71: LOJAS RENNER SA | F71: C&A MODAS LTDA | G71: MARISA LOJAS SA | H71: VESTE SA ESTILO | I71: VULCABRAS SA | J71: GRENDENE SA | K71: ALPARGATAS-PREF | L71: GRUPO SBF SA | M71: TRACK & FIELD CO | N71: REDTAPE LTD/INDI | O71: LI NING CO LTD | P71: TOPSPORTS INTERN | Q71: CHINA LILANG LTD | R71: DAZZLE FASHION-A
B73: Capex intensity | C73: 0.049996939 | D73: 0.043491488 | E73: 0.047047921 | F73: 0.038215741 | G73: 0.0061759743 | H73: 0.11683362 | I73: 0.066580878 | J73: 0.071286018 | K73: 0.038694003 | L73: 0.036370023 | M73: 0.054390755 | N73: 0.084585657 | O73: 0.05241518 | P73: 0.013800814 | Q73: 0.031514393 | R73: 0.023075216
B74: Capex / depreciation | C74: 1.0098998 | D74: 0.60532942 | E74: 0.54587006 | F74: 0.4123783 | G74: 0.05161453 | H74: 0.74807318 | I74: 1.9098864 | J74: 1.3604655 | K74: 0.63633889 | L74: 0.60772897 | M74: 1.323736 | N74: 2.0489033 | O74: 0.84856476 | P74: 0.25527253 | Q74: 0.45281764 | R74: 0.32294584
B75: R&D capitalization rate | R75: 0
B76: R&D capitalization test | R76: 0
B77: Dividend payout | C77: 0.62208729 | D77: 0 | E77: 0.56739798 | F77: 0.025085626 | H77: 8.1353383 | I77: 1.3740904 | J77: 0.58404518 | K77: 0.59185324 | L77: 0.23750037 | M77: 1.5604435 | N77: 0 | O77: 0.5 | P77: 1.3501883 | Q77: 0.73061776 | R77: 0.77541426
B78: FCF payout | C78: -3.8646722 | D78: 0 | E78: 0.37558621 | F78: 0.009512709 | G78: 7.0007714 | H78: -0.023172291 | I78: 1.2424075 | J78: 0.82939407 | K78: 0.093151253 | L78: 0.13519881 | M78: 3.3321286 | N78: 0 | O78: 0.33881671 | P78: 0.50455995 | Q78: 0.79325511 | R78: 0.664257
B79: Buybacks as % CFO | C79: 0 | D79: 0 | E79: 0 | F79: 0.02179325 | G79: 0 | H79: 0 | I79: 0.038249372 | J79: 0.0043202445 | K79: 0 | L79: 0.025315557 | M79: 0.29079335 | N79: 0 | O79: 0 | P79: 0 | Q79: 0 | R79: 0
A81: x | B81: Earnings Quality | C81: AZZAS 2154 SA | D81: GUARARAPES | E81: LOJAS RENNER SA | F81: C&A MODAS LTDA | G81: MARISA LOJAS SA | H81: VESTE SA ESTILO | I81: VULCABRAS SA | J81: GRENDENE SA | K81: ALPARGATAS-PREF | L81: GRUPO SBF SA | M81: TRACK & FIELD CO | N81: REDTAPE LTD/INDI | O81: LI NING CO LTD | P81: TOPSPORTS INTERN | Q81: CHINA LILANG LTD | R81: DAZZLE FASHION-A
B83: Cash/earnings conversion | C83: 2.0696077 | D83: 19.998685 | E83: 9.2154034 | F83: 30.630262 | K83: 8.7786308 | L83: 10.093726 | M83: 0.72296723 | N83: #VALUE! | O83: 6.6310205 | P83: 6.1716828 | Q83: 2.0833488 | R83: 1.2872904
B84: FCF / net income | C84: -0.31279392 | D84: 17.800212 | E84: 6.698679 | F84: 24.610915 | K84: 7.1271972 | L84: 8.7855943 | M84: 0.397148 | N84: #VALUE! | O84: 5.0134474 | P84: 5.5684466 | Q84: 1.6461512 | R84: 1.1247516
A86: x | B86: Per Share & Dilution | C86: AZZAS 2154 SA | D86: GUARARAPES | E86: LOJAS RENNER SA | F86: C&A MODAS LTDA | G86: MARISA LOJAS SA | H86: VESTE SA ESTILO | I86: VULCABRAS SA | J86: GRENDENE SA | K86: ALPARGATAS-PREF | L86: GRUPO SBF SA | M86: TRACK & FIELD CO | N86: REDTAPE LTD/INDI | O86: LI NING CO LTD | P86: TOPSPORTS INTERN | Q86: CHINA LILANG LTD | R86: DAZZLE FASHION-A
B88: Diluted share count YoY | C88: 0.020060595 | D88: 0 | E88: 0.0040441893 | F88: 0.010674741 | H88: 0 | I88: 0.002826505 | J88: 0 | K88: 0.015370094 | L88: 0.030286249 | M88: 0 | N88: 0 | O88: 0.0039265217 | P88: 0 | Q88: 0 | R88: 0
B89: SBC / revenue | C89: 0.0021380105 | F89: 0.0017492217 | G89: -0.012369906 | I89: 0.00072000782 | J89: 0.0010480944 | L89: 0.0016415645 | O89: 0.0027096167 | Q89: 0.00011917864
B90: SBC / CFO | C90: 0.049225866 | F90: 0.0089950015 | G90: 0.21331863 | I90: 0.0038883555 | J90: 0.00392038 | L90: 0.010972629 | O90: 0.013246932 | Q90: 0.0008092963
B91: EPS in USD | C91: 0.91658194 | D91: 0.15389725 | E91: 0.22581039 | F91: 0.092297823 | G91: -0.02900464 | H91: 0.0022908569 | I91: 0.52041285 | J91: 0.1663973 | K91: 0.11575174 | L91: 0.2668822 | M91: 0.064763304 | N91: 0.03622727 | O91: 0.17317105 | P91: 0.031005973 | Q91: 0.049325627 | R91: 0.068170893

Sheet Trading Comps
B7: in millions of BRL | D7: Current | E7: % of | I7: Enterprise Value / | S7: LTM | T7: Net | V7: Price / | Z7: LT
D8: Share | E8: 52-week | F8: Equity | G8: Enterprise | I8: LTM | J8: 2025 | K8: 2026 | L8: LTM | M8: 2025E | N8: 2026E | O8: LTM | P8: 2025E | Q8: 2026E | S8: EBITDA | T8: Debt / | V8: LTM | W8: 2025E | X8: 2026E | Z8: EPS
B9: Company | C9: Ticker | D9: Price | E9: High | F9: Value | G9: Value | I9: Sales | J9: Sales | K9: Sales | L9: EBITDA | M9: EBITDA | N9: EBITDA | O9: EBIT | P9: EBIT | Q9: EBIT | S9: Margin | T9: EBITDA | V9: EPS | W9: EPS | X9: EPS | Z9: Growth
B12: Tier I: DRAM and NAND
B15: GUARARAPES | C15: GUAR3 BZ | D15: BRL 9,53 | E15: 0.9172281 | F15: 4592.64 | G15: 6223.5221 | I15: 0.61216933 | J15: 0.58551496 | K15: 0.5466697 | L15: 3.8709538 | M15: 3.7199774 | N15: 3.3519008 | O15: 6.8960986 | P15: 6.5797696 | Q15: 5.7579507 | S15: 0.15814431 | T15: 2.0169797 | V15: 10.452433 | W15: 10.547402 | X15: 8.2453142 | Z15: 0.16472618
B16: LOJAS RENNER SA | C16: LREN3 BZ | D16: BRL 15,15 | E16: 0.76245596 | F16: 15611.398 | G16: 21000.847 | I16: 1.3607871 | J16: 1.2925478 | K16: 1.2058897 | L16: 6.8265623 | M16: 6.8668196 | N16: 6.3695351 | O16: 11.673441 | P16: 10.718504 | Q16: 9.5699318 | S16: 0.19933709 | T16: 1.0561394 | V16: 10.691501 | W16: 10.461066 | X16: 9.2632332 | Z16: 0.11225041
B17: C&A MODAS LTDA | C17: CEAB3 BZ | D17: BRL 16,3 | E17: 0.76525822 | F17: 4864.1072 | G17: 7970.7108 | I17: 0.99354859 | J17: 0.95887097 | K17: 0.87920656 | L17: 6.7791815 | M17: 4.7395337 | N17: 4.3434157 | O17: 16.983784 | P17: 7.5587585 | Q17: 7.4571028 | S17: 0.14655878 | T17: 1.7841119 | V17: 30.17011 | W17: 9.7109504 | X17: 8.7501428 | Z17: 0.1270052
B18: MARISA LOJAS SA | C18: AMAR3 BZ | D18: BRL 1,21 | E18: 0.69142857 | F18: 1248.5127 | G18: 1370.5621 | I18: 0.90734995 | J18: #VALUE! | K18: #VALUE! | L18: 3.9192734 | M18: #VALUE! | N18: #VALUE! | O18: 7.5028991 | P18: #VALUE! | Q18: #VALUE! | S18: 0.23150973 | T18: 1.918656 | V18: -29.764279 | W18: #VALUE! | X18: #VALUE! | Z18: #VALUE!
B19: VESTE SA ESTILO | C19: VSTE3 BZ | D19: BRL 5,24 | E19: 0.4192 | F19: 597.36267 | G19: 1003.5478 | I19: 0.86585215 | J19: 0.83489829 | K19: 0.78771409 | L19: 4.3447952 | M19: 3.9665919 | N19: 3.3340457 | O19: 17.419982 | P19: #VALUE! | Q19: #VALUE! | S19: 0.19928492 | T19: 1.505121 | V19: 388.53868 | W19: 12.709844 | X19: 5.5828287 | Z19: #VALUE!
B21: Mean | I21: =AVERAGE(I15:I19) -> 0.94794142 | J21: =AVERAGE(J15:J19) -> #VALUE! | K21: =AVERAGE(K15:K19) -> #VALUE! | L21: =AVERAGE(L15:L19) -> 5.1481532 | M21: =AVERAGE(M15:M19) -> #VALUE! | N21: =AVERAGE(N15:N19) -> #VALUE! | O21: =AVERAGE(O15:O19) -> 12.095241 | P21: =AVERAGE(P15:P19) -> #VALUE! | Q21: =AVERAGE(Q15:Q19) -> #VALUE! | S21: =AVERAGE(S15:S19) -> 0.18696697 | T21: =AVERAGE(T15:T19) -> 1.6562016 | V21: =AVERAGE(V15:V19) -> 82.017688 | W21: =AVERAGE(W15:W19) -> #VALUE! | X21: =AVERAGE(X15:X19) -> #VALUE! | Z21: =AVERAGE(Z15:Z19) -> #VALUE!
B22: Median | I22: =MEDIAN(I15:I19) -> 0.90734995 | J22: =MEDIAN(J15:J19) -> #VALUE! | K22: =MEDIAN(K15:K19) -> #VALUE! | L22: =MEDIAN(L15:L19) -> 4.3447952 | M22: =MEDIAN(M15:M19) -> #VALUE! | N22: =MEDIAN(N15:N19) -> #VALUE! | O22: =MEDIAN(O15:O19) -> 11.673441 | P22: =MEDIAN(P15:P19) -> #VALUE! | Q22: =MEDIAN(Q15:Q19) -> #VALUE! | S22: =MEDIAN(S15:S19) -> 0.19928492 | T22: =MEDIAN(T15:T19) -> 1.7841119 | V22: =MEDIAN(V15:V19) -> 10.691501 | W22: =MEDIAN(W15:W19) -> #VALUE! | X22: =MEDIAN(X15:X19) -> #VALUE! | Z22: =MEDIAN(Z15:Z19) -> #VALUE!
B24: Tier II: Chips
B27: VULCABRAS SA | C27: VULC3 BZ | D27: BRL 19,93 | E27: 0.88577778 | F27: 5366.783 | G27: 5910.787 | I27: 1.7986074 | J27: 1.6645415 | K27: 1.5192222 | L27: 7.1128005 | M27: 7.6137231 | N27: 7.0646857 | O27: 8.2957483 | P27: 9.0563642 | Q27: 8.4560616 | S27: 0.2528691 | T27: 0.48247073 | V27: 6.6523796 | W27: 9.237148 | X27: 8.4872689 | Z27: #VALUE!
B28: GRENDENE SA | C28: GRND3 BZ | D28: BRL 5,19 | E28: 0.86789298 | F28: 4619.0592 | G28: 3195.018 | I28: 1.1711891 | J28: 1.1711891 | K28: #VALUE! | L28: 5.3147813 | M28: #VALUE! | N28: #VALUE! | O28: 7.0377171 | P28: #VALUE! | Q28: #VALUE! | S28: 0.2203645 | T28: 0.15578822 | V28: 5.3805186 | W28: #VALUE! | X28: #VALUE! | Z28: #VALUE!
B29: ALPARGATAS-PREF | C29: ALPA4 BZ | D29: BRL 9,57 | E29: 0.90625 | F29: 6509.3405 | G29: 6253.2617 | I29: 1.436257 | J29: 1.3926643 | K29: 1.2875498 | L29: 10.576198 | M29: 8.8698747 | N29: 7.3654437 | O29: 18.913457 | P29: 13.927086 | Q29: 10.301914 | S29: 0.13580088 | T29: 1.7550067 | V29: 19.97793 | W29: 15.647453 | X29: 11.674451 | Z29: 0.17178978
B30: GRUPO SBF SA | C30: SBFG3 BZ | D30: BRL 13,23 | E30: 0.80474453 | F30: 3056.9416 | G30: 5010.0952 | I30: 0.68494293 | J30: 0.65948337 | K30: 0.59755778 | L30: 5.0015725 | M30: 4.8681087 | N30: 4.4398869 | O30: 8.9738406 | P30: 7.7475699 | Q30: 6.9419371 | S30: 0.13694552 | T30: 2.5444266 | V30: 8.304191 | W30: 7.7028767 | X30: 6.288155 | Z30: 0.13873099
B31: TRACK & FIELD CO | C31: TFCO4 BZ | D31: BRL 17,13 | E31: 0.97718197 | F31: 2560.2728 | G31: 14182.693 | I31: 15.209273 | J31: 13.659095 | K31: 11.480863 | L31: 58.93249 | M31: 59.926873 | N31: 48.962117 | O31: 69.552327 | P31: 64.761156 | Q31: 52.078433 | S31: 0.2580796 | T31: 0.63576798 | V31: 18.179288 | W31: 15.330975 | X31: 12.865692 | Z31: 0.19781149
B33: Mean | I33: =AVERAGE(I27:I31) -> 4.060054 | J33: =AVERAGE(J27:J31) -> 3.7093946 | K33: =AVERAGE(K27:K31) -> #VALUE! | L33: =AVERAGE(L27:L31) -> 17.387569 | M33: =AVERAGE(M27:M31) -> #VALUE! | N33: =AVERAGE(N27:N31) -> #VALUE! | O33: =AVERAGE(O27:O31) -> 22.554618 | P33: =AVERAGE(P27:P31) -> #VALUE! | Q33: =AVERAGE(Q27:Q31) -> #VALUE! | S33: =AVERAGE(S27:S31) -> 0.20081192 | T33: =AVERAGE(T27:T31) -> 1.114692 | V33: =AVERAGE(V27:V31) -> 11.698861 | W33: =AVERAGE(W27:W31) -> #VALUE! | X33: =AVERAGE(X27:X31) -> #VALUE! | Z33: =AVERAGE(Z27:Z31) -> #VALUE!
B34: Median | I34: =MEDIAN(I27:I31) -> 1.436257 | J34: =MEDIAN(J27:J31) -> 1.3926643 | K34: =MEDIAN(K27:K31) -> #VALUE! | L34: =MEDIAN(L27:L31) -> 7.1128005 | M34: =MEDIAN(M27:M31) -> #VALUE! | N34: =MEDIAN(N27:N31) -> #VALUE! | O34: =MEDIAN(O27:O31) -> 8.9738406 | P34: =MEDIAN(P27:P31) -> #VALUE! | Q34: =MEDIAN(Q27:Q31) -> #VALUE! | S34: =MEDIAN(S27:S31) -> 0.2203645 | T34: =MEDIAN(T27:T31) -> 0.63576798 | V34: =MEDIAN(V27:V31) -> 8.304191 | W34: =MEDIAN(W27:W31) -> #VALUE! | X34: =MEDIAN(X27:X31) -> #VALUE! | Z34: =MEDIAN(Z27:Z31) -> #VALUE!
B36: Tier III: Semiconductors
B39: REDTAPE LTD/INDI | C39: REDTAPE IN | D39: INR 146,2 | E39: 0.59564066 | F39: 80820.471 | G39: 87788.097 | I39: 4.3439885 | J39: #VALUE! | K39: #VALUE! | L39: 26.264988 | M39: #VALUE! | N39: #VALUE! | O39: 35.001833 | P39: #VALUE! | Q39: #VALUE! | S39: 0.16539084 | T39: 2.1586184 | V39: 47.743944 | W39: #VALUE! | X39: #VALUE! | Z39: #VALUE!
B40: LI NING CO LTD | C40: 2331 HK | D40: HKD 17,64 | E40: 0.84 | F40: 45337.585 | G40: 29959.457 | I40: 1.0278703 | J40: 1.0300053 | K40: 0.98325924 | L40: 5.095827 | M40: 5.9159212 | N40: 5.455026 | O40: 7.0173724 | P40: 9.2830378 | Q40: 8.4683203 | S40: 0.20170824 | T40: 0.34660035 | V40: 14.079602 | W40: 17.531757 | X40: 15.566047 | Z40: 0.15737721
B41: TOPSPORTS INTERN | C41: 6110 HK | D41: HKD 3,16 | E41: 0.79777834 | F41: 19719.886 | G41: 21028.02 | I41: 0.77844363 | J41: 0.78705569 | K41: 0.8028853 | L41: 6.6238329 | M41: 6.8461728 | N41: 6.9388836 | O41: 12.266958 | P41: 11.857809 | Q41: 12.630334 | S41: 0.11752163 | T41: 1.3314009 | V41: 14.213017 | W41: 14.075965 | X41: 14.905432 | Z41: 0.071019808
B42: CHINA LILANG LTD | C42: 1234 HK | D42: HKD 3,56 | E42: 0.75648109 | F42: 4131.323 | G42: 3498.5362 | I42: 0.92623582 | J42: 0.86661785 | K42: 0.79530263 | L42: 4.8785517 | M42: #VALUE! | N42: #VALUE! | O42: 6.9506422 | P42: 5.8601947 | Q42: 5.1223078 | S42: 0.18985877 | T42: 1.6165385 | V42: 9.6766867 | W42: 8.2958293 | X42: 7.3120761 | Z42: 0.09898232
B43: DAZZLE FASHION-A | C43: 603587 CH | D43: CNY 12,35 | E43: 0.78562341 | F43: 5855.0459 | G43: 3316.4703 | I43: 1.5381055 | J43: 1.485541 | K43: 1.3789897 | L43: 9.1793236 | M43: 6.2990889 | N43: 5.8183689 | O43: 13.547663 | P43: 8.4388557 | Q43: 7.2018899 | S43: 0.16756197 | T43: #N/A N/A | V43: 25.009604 | W43: 19.419721 | X43: 16.946587 | Z43: 0.26270081
B45: Mean | I45: 1.7229287 | J45: #VALUE! | K45: #VALUE! | L45: 10.408505 | M45: #VALUE! | N45: #VALUE! | O45: 14.956894 | P45: #VALUE! | Q45: #VALUE! | S45: 0.16840829 | T45: 1.3632895 | V45: 22.144571 | W45: #VALUE! | X45: #VALUE! | Z45: #VALUE!
B46: Median | I46: 1.0278703 | J46: #VALUE! | K46: #VALUE! | L46: 6.6238329 | M46: #VALUE! | N46: #VALUE! | O46: 12.266958 | P46: #VALUE! | Q46: #VALUE! | S46: 0.16756197 | T46: 1.4739697 | V46: 14.213017 | W46: #VALUE! | X46: #VALUE! | Z46: #VALUE!
B48: Overall
B51: Mean | I51: 2.2436414 | J51: #VALUE! | K51: #VALUE! | L51: 10.981409 | M51: #VALUE! | N51: #VALUE! | O51: 16.535584 | P51: #VALUE! | Q51: #VALUE! | S51: 0.18539572 | T51: 1.3791162 | V51: 38.620373 | W51: #VALUE! | X51: #VALUE! | Z51: #VALUE!
B52: Median | I52: 1.0278703 | J52: #VALUE! | K52: #VALUE! | L52: 6.6238329 | M52: #VALUE! | N52: #VALUE! | O52: 11.673441 | P52: #VALUE! | Q52: #VALUE! | S52: 0.18985877 | T52: 1.5608298 | V52: 14.079602 | W52: #VALUE! | X52: #VALUE! | Z52: #VALUE!
B54: High | I54: 15.209273 | J54: #VALUE! | K54: #VALUE! | L54: 58.93249 | M54: #VALUE! | N54: #VALUE! | O54: 69.552327 | P54: #VALUE! | Q54: #VALUE! | R54: 0 | S54: 0.2580796 | T54: 2.5444266 | V54: 388.53868 | W54: #VALUE! | X54: #VALUE! | Z54: #VALUE!
B55: Low | I55: 0.61216933 | J55: #VALUE! | K55: #VALUE! | L55: 3.8709538 | M55: #VALUE! | N55: #VALUE! | O55: 6.8960986 | P55: #VALUE! | Q55: #VALUE! | R55: 0 | S55: 0.11752163 | T55: 0.15578822 | V55: -29.764279 | W55: #VALUE! | X55: #VALUE! | Z55: #VALUE!

Sheet WACC
A7: x | B7: Rolling WACC | K7: Equity Risk Premium
P8: Weights
D9: 2025 | E9: =+D9+1 -> 2026 | F9: =+E9+1 -> 2027 | G9: =+F9+1 -> 2028 | H9: =+G9+1 -> 2029 | M9: ERP | N9: 2025 | O9: =+N9+1 -> 2026 | P9: =+O9+1 -> 2027 | Q9: =+P9+1 -> 2028 | R9: =+Q9+1 -> 2029
B12: Equity: | K12: =+Segments!B73 -> Brazil | M12: 0.0767 | N12: =+Segments!AL73/Segments!AL$78 -> 0.90189679 | O12: =+Segments!AR73/Segments!AR$78 -> 0.90189679 | P12: =+Segments!AT73/Segments!AT$78 -> 0.90189679 | Q12: =+Segments!AR73/Segments!AR$78 -> 0.90189679 | R12: =+Segments!AT73/Segments!AT$78 -> 0.90189679
B13: Market Cap (in billions) | D13: =+Inputs!J13 -> 6655.1666 | E13: =+FCFF!AF96*FCFF!AF26 -> 9949.7514 | F13: =+FCFF!AH96*FCFF!AH26 -> 12747.935 | G13: =+FCFF!AJ96*FCFF!AJ26 -> 15810.109 | H13: =+FCFF!AL96*FCFF!AL26 -> 14822.077 | K13: =+Segments!B74 -> Rest of the World | M13: 0.05 | N13: =+Segments!AL74/Segments!AL$78 -> 0.098103214 | O13: =+Segments!AR74/Segments!AR$78 -> 0.098103214 | P13: =+Segments!AT74/Segments!AT$78 -> 0.098103214 | Q13: =+Segments!AR74/Segments!AR$78 -> 0.098103214 | R13: =+Segments!AT74/Segments!AT$78 -> 0.098103214
B14: % of Equity | D14: =IFERROR(D13/D35,"") -> 0.63400982 | E14: =IFERROR(E13/E35,"") -> 0.73977214 | F14: =IFERROR(E13/F35,"") -> 0.62388964 | G14: =IFERROR(F13/G35,"") -> 0.67771721 | H14: =IFERROR(G13/H35,"") -> 0.8971763 | K14: =+Segments!B75 -> 0 | N14: =+Segments!AL75/Segments!AL$78 -> 0 | O14: =+Segments!AR75/Segments!AR$78 -> 0 | P14: =+Segments!AT75/Segments!AT$78 -> 0 | Q14: =+Segments!AR75/Segments!AR$78 -> 0 | R14: =+Segments!AT75/Segments!AT$78 -> 0
B15: Risk-Free Rate | D15: 0.1351 | E15: 0.1351 | F15: 0.1351 | G15: 0.1351 | H15: 0.1351 | K15: =+Segments!B76 -> 0 | N15: =+Segments!AL76/Segments!AL$78 -> 0 | O15: =+Segments!AR76/Segments!AR$78 -> 0 | P15: =+Segments!AT76/Segments!AT$78 -> 0 | Q15: =+Segments!AR76/Segments!AR$78 -> 0 | R15: =+Segments!AT76/Segments!AT$78 -> 0
B16: Beta | D16: =+Inputs!M18 -> 1.166738 | E16: =+D17*(1+(E28/E13)*(1-E32)) -> 0.85634402 | F16: =+E17*(1+(F28/F13)*(1-F32)) -> 0.80650589 | G16: =+F17*(1+(G28/G13)*(1-G32)) -> 0.77619681 | H16: =+G17*(1+(H28/H13)*(1-H32)) -> 0.77577899 | K16: =+Segments!B77 -> 0 | N16: =+Segments!AL77/Segments!AL$78 -> 0 | O16: =+Segments!AR77/Segments!AR$78 -> 0 | P16: =+Segments!AT77/Segments!AT$78 -> 0 | Q16: =+Segments!AR77/Segments!AR$78 -> 0 | R16: =+Segments!AT77/Segments!AT$78 -> 0
B17: Unlevered Beta | D17: =+D16/(1+(D28/D13)*(1-D32)) -> 0.68232871 | E17: =+E16/(1+(E28/E13)*(1-E32)) -> 0.68232871 | F17: =+F16/(1+(F28/F13)*(1-F32)) -> 0.68232871 | G17: =+G16/(1+(G28/G13)*(1-G32)) -> 0.68232871 | H17: =+H16/(1+(H28/H13)*(1-H32)) -> 0.68232871
B18: Equity Risk Premium | D18: =+N18 -> 0.074080644 | E18: =+O18 -> 0.074080644 | F18: =+P18 -> 0.074080644 | G18: =+Q18 -> 0.074080644 | H18: =+R18 -> 0.074080644 | K18: ERP | N18: =+SUMPRODUCT($M12:$M16,N12:N16) -> 0.074080644 | O18: =+SUMPRODUCT($M12:$M16,O12:O16) -> 0.074080644 | P18: =+SUMPRODUCT($M12:$M16,P12:P16) -> 0.074080644 | Q18: =+SUMPRODUCT($M12:$M16,Q12:Q16) -> 0.074080644 | R18: =+SUMPRODUCT($M12:$M16,R12:R16) -> 0.074080644
B19: Ke (Cost of Equity) | D19: =IFERROR(+D15+D16*D18,"") -> 0.2215327 | E19: =IFERROR(+E15+E16*E18,"") -> 0.19853852 | F19: =IFERROR(+F15+F16*F18,"") -> 0.19484648 | G19: =IFERROR(+G15+G16*G18,"") -> 0.19260116 | H19: =IFERROR(+H15+H16*H18,"") -> 0.19257021
B21: Preferred Equity: | K21: ROIC vs WACC
B22: Market Capitalization | D22: =IFERROR(Inputs!J14,0) -> 0 | E22: =+D22*(E13/D13) -> 0 | F22: =+E22*(F13/E13) -> 0 | G22: =+F22*(G13/F13) -> 0 | H22: =+G22*(H13/G13) -> 0
B23: % of Preferred Equity | D23: =+D22/D35 -> 0 | E23: =+E22/E35 -> 0 | F23: =+F22/F35 -> 0 | G23: =+G22/G35 -> 0 | H23: =+H22/H35 -> 0
B24: Preferred Dividends | D24: =+IS!AF50 -> 0 | E24: =D24 -> 0 | F24: =E24 -> 0 | G24: =F24 -> 0 | H24: =G24 -> 0
B25: Kp (Cost of Preferred Equity) | D25: =IFERROR(D24/D22,0) -> 0 | E25: =IFERROR(E24/E22,0) -> 0 | F25: =IFERROR(F24/F22,0) -> 0 | G25: =IFERROR(G24/G22,0) -> 0 | H25: =IFERROR(H24/H22,0) -> 0
B27: Debt:
B28: Debt (in millions) | C28: =+BS!AF38+BS!AF39+BS!AF44+BS!AF45 -> 3530.401 | D28: =+BS!AI38+BS!AI39+BS!AI44+BS!AI45 -> 3841.779 | E28: 3500 | F28: 3200 | G28: 3000 | H28: 2800
B29: % of Debt | D29: =IFERROR(D28/D35,"") -> 0.36599018 | E29: =IFERROR(E28/E35,"") -> 0.26022786 | F29: =IFERROR(F28/F35,"") -> 0.20065294 | G29: =IFERROR(G28/G35,"") -> 0.1594887 | H29: =IFERROR(H28/H35,"") -> 0.1588916
B30: Debt Spread | D30: =+D31-D15 -> -0.07319899 | E30: 0.1 | F30: 0.1 | G30: 0.1 | H30: 0.1
B31: Cost of Debt | D31: =+IS!AF36/WACC!D28 -> 0.06190101 | E31: =+E30+E15 -> 0.2351 | F31: =+F30+F15 -> 0.2351 | G31: =+G30+G15 -> 0.2351 | H31: =+H30+H15 -> 0.2351
B32: Tax Rate | D32: =+FCFF!Z121 -> -0.22983083 | E32: =+FCFF!AF121 -> 0.275 | F32: =+FCFF!AH121 -> 0.275 | G32: =+FCFF!AJ121 -> 0.275 | H32: =+FCFF!AL121 -> 0.275
B33: Kd (After-Tax Cost of Debt) | D33: =+D31*(1-D32) -> 0.07612777 | E33: =+E31*(1-E32) -> 0.1704475 | F33: =+F31*(1-F32) -> 0.1704475 | G33: =+G31*(1-G32) -> 0.1704475 | H33: =+H31*(1-H32) -> 0.1704475
B35: Total | D35: =+D13+D24+D28 -> 10496.946 | E35: =+E13+E24+E28 -> 13449.751 | F35: =+F13+F24+F28 -> 15947.935 | G35: =+G13+G24+G28 -> 18810.109 | H35: =+H13+H24+H28 -> 17622.077
B37: Country/Conglomerate/... Risk Premium | D37: 0.0075 | E37: 0.0075 | F37: 0.0075 | G37: 0.0075 | H37: 0.0075
A39: x | B39: WACC | D39: =+D19*D14+D25*D23+D33*D29+D37+Sensitivity!$U$41 -> 0.17581593 | E39: =+E19*E14+E25*E23+E33*E29+E37+Sensitivity!$U$41 -> 0.19872845 | F39: =+F19*F14+F25*F23+F33*F29+F37+Sensitivity!$U$41 -> 0.16326349 | G39: =+G19*G14+G25*G23+G33*G29+G37+Sensitivity!$U$41 -> 0.16521357 | H39: =+H19*H14+H25*H23+H33*H29+H37+Sensitivity!$U$41 -> 0.2073521
B41: NOPAT | D41: =+FCFF!Z123 -> 2435.8221 | E41: =+FCFF!AF123 -> 1679.0775 | F41: =+FCFF!AH123 -> 2370.2417 | G41: =+FCFF!AJ123 -> 2948.6842 | H41: =+FCFF!AL123 -> 3371.1755
B42: Total Payout | D42: =+FCFF!Z109+FCFF!Z112 -> 793.01717 | E42: =+FCFF!AF109+FCFF!AF112 -> -18 | F42: =+FCFF!AH109+FCFF!AH112 -> -610.56044 | G42: =+FCFF!AJ110+FCFF!AJ112 -> -17.7 | H42: =+FCFF!AL110+FCFF!AL112 -> -17.7
B43: Book Value of Equity | C43: =+BS!AF54 -> 7721.515 | D43: =+C43+D41+D42 -> 10950.354 | E43: =+D43+E41+E42 -> 12611.432 | F43: =+E43+F41+F42 -> 14371.113 | G43: =+F43+G41+G42 -> 17302.097 | H43: =+G43+H41+H42 -> 20655.573
B44: Invested Capital | C44: =+C43+C28 -> 11251.916 | D44: =+D43+D28 -> 14792.133 | E44: =+E43+E28 -> 16111.432 | F44: =+F43+F28 -> 17571.113 | G44: =+G43+G28 -> 20302.097 | H44: =+H43+H28 -> 23455.573
A45: x | B45: ROIC | D45: =+D41/((D44+C44)/2) -> 0.18705402 | E45: =+E41/((E44+D44)/2) -> 0.10866562 | F45: =+F41/((F44+E44)/2) -> 0.14074006 | G45: =+G41/((G44+F44)/2) -> 0.15571346 | H45: =+H41/((H44+G44)/2) -> 0.15408387
W49: ,

Sheet FCFF
A7: x | B7: Market Assumptions
D8: 2022 | J8: =D8+1 -> 2023 | P8: =J8+1 -> 2024 | V8: =P8+1 -> 2025 | AB8: =V8+1 -> 2026 | AH8: =AB8+1 -> 2027 | AJ8: =+AH8+1 -> 2028 | AL8: =+AJ8+1 -> 2029
D9: Q1 | E9: Q2 | F9: Q3 | G9: Q4 | H9: FY | J9: Q1 | K9: Q2 | L9: Q3 | M9: Q4 | N9: FY | P9: Q1 | Q9: Q2 | R9: Q3 | S9: Q4 | T9: FY | V9: Q1 | W9: Q2 | X9: Q3 | Y9: Q4 | Z9: FY | AB9: Q1 | AC9: Q2 | AD9: Q3 | AE9: Q4 | AF9: FY | AH9: FY | AJ9: FY | AL9: FY
B11: Shoes & Bags | D11: =$H$11*0.25 -> 707.416 | E11: =$H$11*0.25 -> 707.416 | F11: =$H$11*0.25 -> 707.416 | G11: =$H$11*0.25 -> 707.416 | H11: =Segments!T13 -> 2829.664 | J11: =$N$11*0.25 -> 1141.45 | K11: =$N$11*0.25 -> 1141.45 | L11: =$N$11*0.25 -> 1141.45 | M11: =$N$11*0.25 -> 1141.45 | N11: =Segments!Z13 -> 4565.8 | P11: =$T$11*0.25 -> 1196.3 | Q11: =$T$11*0.25 -> 1196.3 | R11: =$T$11*0.25 -> 1196.3 | S11: =$T$11*0.25 -> 1196.3 | T11: =Segments!AF13 -> 4785.2 | V11: =$Z$11*0.25 -> 1064.6742 | W11: =$Z$11*0.25 -> 1064.6742 | X11: =$Z$11*0.25 -> 1064.6742 | Y11: =$Z$11*0.25 -> 1064.6742 | Z11: =Segments!AL13 -> 4258.697 | AB11: =$AF$11*0.25 -> 1143.7974 | AC11: =$AF$11*0.25 -> 1143.7974 | AD11: =$AF$11*0.25 -> 1143.7974 | AE11: =$AF$11*0.25 -> 1143.7974 | AF11: =Segments!AR13 -> 4575.1898 | AH11: =Segments!AT13 -> 4859.887 | AJ11: =Segments!AV13 -> 5107.1826 | AL11: =Segments!AX13 -> 5308.4232 | AS11: 2022 | AT11: =+AS11+1 -> 2023 | AU11: =+AT11+1 -> 2024 | AV11: =+AU11+1 -> 2025 | AW11: =+AV11+1 -> 2026 | AX11: =+AW11+1 -> 2027 | AY11: =+AX11+1 -> 2028 | AZ11: =+AY11+1 -> 2029
B12: Fashion & Lifestyle Women | D12: =$H$12*0.227 -> 1002.3412 | E12: =$H$12*0.227 -> 1002.3412 | F12: =H12*0.26 -> 1148.056 | G12: =H12*0.286 -> 1262.8616 | H12: =Segments!T27 -> 4415.6 | J12: =$N$12*0.227 -> 931.5853 | K12: =$N$12*0.227 -> 931.5853 | L12: =N12*0.26 -> 1067.014 | M12: =N12*0.286 -> 1173.7154 | N12: =Segments!Z27 -> 4103.9 | P12: =T12*0.228 -> 1090.3188 | Q12: =T12*0.228 -> 1090.3188 | R12: 1241.6 | S12: 1362.9 | T12: =Segments!AF27 -> 4782.1 | V12: =$Z$12*0.227 -> 1279.0658 | W12: =$Z$12*0.227 -> 1279.0658 | X12: =Z12*0.26 -> 1465.0093 | Y12: =Z12*0.286 -> 1611.5102 | Z12: =Segments!AL27 -> 5634.651 | AB12: =AF12*0.227 -> 1482.3705 | AC12: =AF12*0.227 -> 1482.3705 | AD12: =AF12*0.26 -> 1697.8693 | AE12: =AF12*0.286 -> 1867.6562 | AF12: =Segments!AR27 -> 6530.2666 | AH12: =Segments!AT27 -> 7437.1189 | AJ12: =Segments!AV27 -> 8316.3496 | AL12: =Segments!AX27 -> 9124.7281 | AR12: EBITDA | AS12: =H58+H125 -> 735.73 | AT12: =N58+N125 -> 810.844 | AU12: =T58+T125 -> 1045.455 | AV12: =Z58+Z125 -> 2439.1925 | AW12: =AF58+AF125 -> 2870.0478 | AX12: =AH58+AH125 -> 3949.6079 | AY12: =AJ58+AJ125 -> 4776.7937 | AZ12: =AL58+AL125 -> 5387.0327
B13: Basic | D13: =H13*0.24 -> 559.296 | E13: =H13*0.24 -> 559.296 | F13: =H13*0.26 -> 605.904 | G13: =H13*0.27 -> 629.208 | H13: =Segments!T41 -> 2330.4 | J13: =$N$13*0.24 -> 621.048 | K13: =$N$13*0.24 -> 621.048 | L13: =N13*0.26 -> 672.802 | M13: =N13*0.27 -> 698.679 | N13: =Segments!Z41 -> 2587.7 | P13: =T13*0.24 -> 670.56 | Q13: =T13*0.24 -> 670.56 | R13: 713 | S13: 757 | T13: =Segments!AF41 -> 2794 | V13: =$Z$13*0.24 -> 731.45376 | W13: =$Z$13*0.24 -> 731.45376 | X13: =Z13*0.26 -> 792.40824 | Y13: =Z13*0.27 -> 822.88548 | Z13: =Segments!AL41 -> 3047.724 | AB13: =AF13*0.24 -> 800.47414 | AC13: =AF13*0.24 -> 800.47414 | AD13: =AF13*0.26 -> 867.18032 | AE13: =AF13*0.27 -> 900.5334 | AF13: =Segments!AR41 -> 3335.3089 | AH13: =Segments!AT41 -> 3623.619 | AJ13: =Segments!AV41 -> 3906.7965 | AL13: =Segments!AX41 -> 4178.4062 | AR13: FCFF | AS13: =H133 -> 122.33043 | AT13: =N133 -> 516.80594 | AU13: =T133 -> 842.61658 | AV13: =Z133 -> 228.89892 | AW13: =AF133 -> 1780.1075 | AX13: =AH133 -> 2450.9435 | AY13: =AJ133 -> 3604.217 | AZ13: =AL133 -> 3584.1406
B14: Fashion & Lifestyle Men | D14: =$H$14*0.223 -> 290.9258 | E14: =$H$14*0.223 -> 290.9258 | F14: =H14*0.26 -> 339.196 | G14: =H14*0.3 -> 391.38 | H14: =Segments!T55 -> 1304.6 | J14: =$N$14*0.223 -> 338.1126 | K14: =$N$14*0.223 -> 338.1126 | L14: =N14*0.26 -> 394.212 | M14: =N14*0.3 -> 454.86 | N14: =Segments!Z55 -> 1516.2 | P14: =$T$14*0.223 -> 400.2627 | Q14: =$T$14*0.223 -> 400.2627 | R14: 467.9 | S14: 525.3 | T14: =Segments!AF55 -> 1794.9 | V14: =Z14*0.223 -> 443.92521 | W14: =Z14*0.223 -> 443.92521 | X14: =Z14*0.26 -> 517.58096 | Y14: =Z14*0.3 -> 597.2088 | Z14: =Segments!AL55 -> 1990.696 | AB14: =AF14*0.223 -> 477.7003 | AC14: =AF14*0.223 -> 477.7003 | AD14: =AF14*0.26 -> 556.95999 | AE14: =AF14*0.3 -> 642.64615 | AF14: =Segments!AR55 -> 2142.1538 | AH14: =Segments!AT55 -> 2290.7106 | AJ14: =Segments!AV55 -> 2432.3082 | AL14: =Segments!AX55 -> 2562.8377 | AR14: Revenue Growth | AS14: =H27 -> 0.37093191 | AT14: =N27 -> 0.17401563 | AU14: =T27 -> 0.10823887 | AV14: =Z27 -> 0.054786454 | AW14: =AF27 -> 0.11057974 | AX14: =AH27 -> 0.098198423 | AY14: =+AJ27 -> 0.085183277 | AZ14: =+AL27 -> 0.071435728
B16: Revenue | D16: =SUM(D11:D15) -> 2559.979 | E16: =SUM(E11:E15) -> 2559.979 | F16: =SUM(F11:F15) -> 2800.572 | G16: =SUM(G11:G15) -> 2990.8656 | H16: =SUM(H11:H15) -> 10880.264 | I16: =SUM(I11:I15) -> 0 | J16: =SUM(J11:J15) -> 3032.1959 | K16: =SUM(K11:K15) -> 3032.1959 | ... AL16: =SUM(AL11:AL15) -> 21174.395
A18: x | B18: Operating Assumptions
D19: =D$8 -> 2022 | E19: =F19 -> 0 | F19: =F$8 -> 0 | G19: =F19 -> 0 | H19: =F19 -> 0 | J19: =J$8 -> 2023 | K19: =L19 -> 0 | L19: =L$8 -> 0 | M19: =L19 -> 0 | N19: =L19 -> 0 | P19: =P$8 -> 2024 | Q19: =R19 -> 0 | R19: =R$8 -> 0 | S19: =R19 -> 0 | T19: =R19 -> 0 | V19: =V$8 -> 2025 | W19: =X19 -> 0 | X19: =X$8 -> 0 | Y19: =X19 -> 0 | Z19: =X19 -> 0 | AB19: =AB$8 -> 2026 | AC19: =AD19 -> 0 | AD19: =AD$8 -> 0 | AE19: =AD19 -> 0 | AF19: =AD19 -> 0 | AH19: =AH$8 -> 2027 | AJ19: =AJ$8 -> 2028 | AL19: =AL$8 -> 2029 | AM19: =AN19 -> 0
D20: Q1 | E20: Q2 | F20: Q3 | G20: Q4 | H20: FY | J20: Q1 | K20: Q2 | L20: Q3 | M20: Q4 | N20: FY | P20: Q1 | Q20: Q2 | R20: Q3 | S20: Q4 | T20: FY | V20: Q1 | W20: Q2 | X20: Q3 | Y20: Q4 | Z20: FY | AB20: Q1 | AC20: Q2 | AD20: Q3 | AE20: Q4 | AF20: FY | AH20: FY | AJ20: FY | AL20: FY
B23: Income Statement
B26: Gross Sales | D26: =D16 -> 2559.979 | E26: =E16 -> 2559.979 | F26: =F16 -> 2800.572 | G26: =G16 -> 2990.8656 | H26: =H16 -> 10880.264 | J26: =J16 -> 3032.1959 | K26: =K16 -> 3032.1959 | L26: =L16 -> 3275.478 | M26: =M16 -> 3468.7044 | N26: =N16 -> 12773.6 | P26: =P16 -> 3357.4415 | Q26: =Q16 -> 3357.4415 | R26: =R16 -> 3618.8 | S26: =S16 -> 3841.5 | T26: =T16 -> 14156.2 | V26: =V16 -> 3519.119 | W26: =W16 -> 3519.119 | X26: =X16 -> 3839.6727 | Y26: =Y16 -> 4096.2787 | Z26: =Z16 -> 14931.768 | AA26: =AA16 -> 0 | AB26: =AB16 -> 3904.3424 | AC26: =AC16 -> 3904.3424 | ... AL26: =AL16 -> 21174.395
B27: % of growth | H27: =H26/Segments!N70-1 -> 0.37093191 | J27: =J26/D26-1 -> 0.18446124 | K27: =K26/E26-1 -> 0.18446124 | L27: =L26/F26-1 -> 0.16957464 | M27: =M26/G26-1 -> 0.15976606 | N27: =N26/H26-1 -> 0.17401563 | P27: =P26/J26-1 -> 0.10726405 | Q27: =Q26/K26-1 -> 0.10726405 | R27: =R26/L26-1 -> 0.10481585 | S27: =S26/M26-1 -> 0.10747402 | T27: =T26/N26-1 -> 0.10823887 | V27: =V26/P26-1 -> 0.04815497 | W27: =W26/Q26-1 -> 0.04815497 | X27: =X26/R26-1 -> 0.061034793 | Y27: =Y26/S26-1 -> 0.066322717 | Z27: =Z26/T26-1 -> 0.054786454 | AB27: =AB26/V26-1 -> 0.10946586 | AC27: =AC26/W26-1 -> 0.10946586 | AD27: =AD26/X26-1 -> 0.11098195 | AE27: =AE26/Y26-1 -> 0.11189535 | AF27: =AF26/Z26-1 -> 0.11057974 | AH27: =AH26/AF26-1 -> 0.098198423 | AJ27: =AJ26/AH26-1 -> 0.085183277 | AL27: =AL26/AJ26-1 -> 0.071435728
B28: Net Sales | H28: 4233.7 | N28: 4846.8 | T28: 8379.8 | Z28: =Z26*Z29 -> 9556.3315 | AF28: =AF26*AF29 -> 10944.727 | AH28: =AH26*AH29 -> 12383.708 | AJ28: =AJ26*AJ29 -> 13833.846 | AL28: =AL26*AL29 -> 15245.565
B29: % of gross sales | H29: =H28/H26 -> 0.3891174 | N29: =N28/N26 -> 0.37943884 | T29: =T28/T26 -> 0.59195264 | Z29: 0.64 | AF29: 0.66 | AH29: 0.68 | AJ29: 0.7 | AL29: 0.72
B31: Cost of Goods & Services | D31: =390.8+(1173.8-562.5) -> 1002.1 | E31: =416.145+(1376.3-714.7) -> 1077.745 | F31: 536.6 | H31: 1950 | N31: 2217.7 | T31: 3914.7 | V31: =IS!AH21 -> 1219.737 | W31: =IS!AI21 -> 1280.918 | X31: =(X32+Sensitivity!$U$39)*X$26 -> 1612.6625 | Y31: =(Y32+Sensitivity!$U$39)*Y$26 -> 1720.4371 | Z31: =Z28*(Z32+Sensitivity!$U$39) -> 3704.4909 | AB31: =(AB32+Sensitivity!$U$39)*AB$26 -> 0 | AC31: =(AC32+Sensitivity!$U$39)*AC$26 -> 0 | AD31: =(AD32+Sensitivity!$U$39)*AD$26 -> 0 | AE31: =(AE32+Sensitivity!$U$39)*AE$26 -> 0 | AF31: =AF28*(AF32+Sensitivity!$U$39) -> 4377.8906 | AH31: =AH28*(AH32+Sensitivity!$U$39) -> 4705.8091 | AJ31: =AJ28*(AJ32+Sensitivity!$U$39) -> 5118.5229 | AL31: =AL28*(AL32+Sensitivity!$U$39) -> 5488.4032
B32: % of net sales | D32: =D31/D26 -> 0.39144852 | E32: =E31/E26 -> 0.42099759 | F32: =F31/F26 -> 0.19160372 | G32: =G31/G26 -> 0 | H32: =H31/H28 -> 0.46059003 | J32: =J31/J26 -> 0 | K32: =K31/K26 -> 0 | L32: =L31/L26 -> 0 | M32: =M31/M26 -> 0 | N32: =N31/N28 -> 0.45755963 | P32: =P31/P26 -> 0 | Q32: =Q31/Q26 -> 0 | R32: =R31/R26 -> 0 | S32: =S31/S26 -> 0 | T32: =T31/T28 -> 0.46715912 | V32: =V31/V26 -> 0.34660294 | W32: =W31/W26 -> 0.36398826 | X32: 0.42 | Y32: 0.42 | Z32: =AVERAGE(V32:Y32) -> 0.3876478 | AF32: 0.4 | AH32: 0.38 | AJ32: 0.37 | AL32: 0.36
B34: COGS Depreciation & Amortization | D34: 1 | F34: 1 | H34: 0 | N34: 0 | T34: 0 | V34: =[1]IS!AH19 -> 0 | W34: =[1]IS!AI19 -> 0 | X34: =X35*X31 -> 0 | Y34: =Y35*Y31 -> 0 | Z34: =SUM(V34:Y34) -> 0 | AB34: =AB35*AB31 -> 0 | AC34: =AC35*AC31 -> 0 | AD34: =AD35*AD31 -> 0 | AE34: =AE35*AE31 -> 0 | AF34: =SUM(AB34:AE34) -> 0 | AH34: =AH35*AH31 -> 0 | AJ34: =AJ35*AJ31 -> 0 | AL34: =AL35*AL31 -> 0
B35: % of cost of goods & services | D35: =D34/D31 -> 0.0009979044 | E35: =E34/E31 -> 0 | F35: =F34/F31 -> 0.0018635855 | G35: =G34/G31 -> #DIV/0! | H35: 0 | N35: 0 | T35: 0 | V35: =V34/V31 -> 0 | W35: =W34/W31 -> 0 | X35: 0 | Y35: 0 | AH35: 0 | AJ35: 0 | AL35: 0
B37: Gross Profit | D37: =D26-D31-D34 -> 1556.879 | E37: =E26-E31-E34 -> 1482.234 | F37: =F26-F31-F34 -> 2262.972 | G37: =G26-G31-G34 -> 2990.8656 | H37: =H28-H31 -> 2283.7 | J37: =J28-J31-J34 -> 0 | K37: =K28-K31-K34 -> 0 | L37: =L28-L31-L34 -> 0 | M37: =M28-M31-M34 -> 0 | N37: =N28-N31 -> 2629.1 | O37: =O28-O31-O34 -> 0 | P37: =P28-P31-P34 -> 0 | Q37: =Q28-Q31-Q34 -> 0 | R37: =R28-R31-R34 -> 0 | S37: =S28-S31-S34 -> 0 | T37: =T28-T31 -> 4465.1 | V37: =V28-V31-V34 -> -1219.737 | W37: =W28-W31-W34 -> -1280.918 | X37: =X28-X31-X34 -> -1612.6625 | Y37: =Y28-Y31-Y34 -> -1720.4371 | Z37: =Z28-Z31 -> 5851.8406 | AA37: =AA28-AA31-AA34 -> 0 | AB37: =AB28-AB31-AB34 -> 0 | AC37: =AC28-AC31-AC34 -> 0 | AD37: =AD28-AD31-AD34 -> 0 | AE37: =AE28-AE31-AE34 -> 0 | AF37: =AF28-AF31 -> 6566.836 | AG37: =AG28-AG31-AG34 -> 0 | AH37: =AH28-AH31 -> 7677.8991 | AI37: =AI28-AI31-AI34 -> 0 | AJ37: =AJ28-AJ31 -> 8715.3228 | AK37: =AK28-AK31-AK34 -> 0 | AL37: =AL28-AL31 -> 9757.1613
B38: % of net sales | D38: =D37/D26 -> 0.60816085 | E38: =E37/E26 -> 0.57900241 | F38: =F37/F26 -> 0.80803921 | G38: =G37/G26 -> 1 | H38: =H37/H28 -> 0.53940997 | J38: =J37/J26 -> 0 | K38: =K37/K26 -> 0 | L38: =L37/L26 -> 0 | M38: =M37/M26 -> 0 | N38: =N37/N28 -> 0.54244037 | P38: =P37/P26 -> 0 | Q38: =Q37/Q26 -> 0 | R38: =R37/R26 -> 0 | S38: =S37/S26 -> 0 | T38: =T37/T28 -> 0.53284088 | V38: =V37/V26 -> -0.34660294 | W38: =W37/W26 -> -0.36398826 | X38: =X37/X26 -> -0.42 | Y38: =Y37/Y26 -> -0.42 | Z38: =Z37/Z28 -> 0.6123522 | AB38: =AB37/AB26 -> 0 | AC38: =AC37/AC26 -> 0 | AD38: =AD37/AD26 -> 0 | AE38: =AE37/AE26 -> 0 | AF38: =AF37/AF28 -> 0.6 | AH38: =AH37/AH28 -> 0.62 | AJ38: =AJ37/AJ28 -> 0.63 | AL38: =AL37/AL28 -> 0.64
B40: SG&A (Selling, General & Administrative) | D40: 287.588 | H40: 1819 | N40: 2109.2 | T40: 3883.8 | V40: =IS!AH27 -> 1236.688 | W40: =IS!AI27 -> 1268.066 | X40: =(X41+Sensitivity!$U$40)*X$26 -> 1459.0756 | Y40: =(Y41+Sensitivity!$U$40)*Y$26 -> 1556.5859 | Z40: =Z28*(Z41+Sensitivity!$U$40) -> 4013.6592 | AB40: =(AB41+Sensitivity!$U$40)*AB$26 -> 0 | AC40: =(AC41+Sensitivity!$U$40)*AC$26 -> 0 | AD40: =(AD41+Sensitivity!$U$40)*AD$26 -> 0 | AE40: =(AE41+Sensitivity!$U$40)*AE$26 -> 0 | AF40: =AF28*(AF41+Sensitivity!$U$40) -> 4377.8906 | AH40: =AH28*(AH41+Sensitivity!$U$40) -> 4581.972 | AJ40: =AJ28*(AJ41+Sensitivity!$U$40) -> 4841.846 | AL40: =AL28*(AL41+Sensitivity!$U$40) -> 5335.9476
B41: % of net sales | D41: =D40/D26 -> 0.11233998 | E41: =E40/E26 -> 0 | F41: =F40/F26 -> 0 | G41: =G40/G26 -> 0 | H41: =H40/H28 -> 0.42964783 | J41: =J40/J26 -> 0 | K41: =K40/K26 -> 0 | L41: =L40/L26 -> 0 | M41: =M40/M26 -> 0 | N41: =N40/N28 -> 0.43517372 | P41: =P40/P26 -> 0 | Q41: =Q40/Q26 -> 0 | R41: =R40/R26 -> 0 | S41: =S40/S26 -> 0 | T41: =T40/T28 -> 0.46347168 | V41: =V40/V26 -> 0.35141977 | W41: =W40/W26 -> 0.36033621 | X41: 0.38 | Y41: 0.38 | Z41: 0.42 | AF41: 0.4 | AH41: 0.37 | AJ41: 0.35 | AL41: 0.35
B43: R&D (Research & Development) | H43: =IS!T29 -> 0 | J43: =IS!V29 -> 0 | K43: =IS!W29 -> 0 | L43: =IS!X29 -> 0 | M43: =IS!Y29 -> 0 | N43: =IS!Z29 -> 0 | P43: =IS!AB29 -> 0 | Q43: =IS!AC29 -> 0 | R43: =IS!AD29 -> 0 | S43: =IS!AE29 -> 0 | T43: =IS!AF29 -> 0 | V43: =IS!AH29 -> 0 | W43: =IS!AI29 -> 0 | X43: =X44*X37 -> 0 | Y43: =Y44*Y37 -> 0 | Z43: =SUM(V43:Y43) -> 0 | AB43: =AB44*AB37 -> 0 | AC43: =AC44*AC37 -> 0 | AD43: =AD44*AD37 -> 0 | AE43: =AE44*AE37 -> 0 | AF43: =SUM(AB43:AE43) -> 0 | AH43: =AH44*AH37 -> 0 | AJ43: =AJ44*AJ37 -> 0 | AL43: =AL44*AL37 -> 0
B44: % of gross profit | D44: =D43/D37 -> 0 | E44: =E43/E37 -> 0 | F44: =F43/F37 -> 0 | G44: =G43/G37 -> 0 | H44: =H43/H37 -> 0 | J44: =J43/J37 -> #DIV/0! | K44: =K43/K37 -> #DIV/0! | L44: =L43/L37 -> #DIV/0! | M44: =M43/M37 -> #DIV/0! | N44: =N43/N37 -> 0 | P44: =P43/P37 -> #DIV/0! | Q44: =Q43/Q37 -> #DIV/0! | R44: =R43/R37 -> #DIV/0! | S44: =S43/S37 -> #DIV/0! | T44: =T43/T37 -> 0 | V44: =V43/V37 -> 0 | W44: =W43/W37 -> 0 | X44: 0 | Y44: 0 | Z44: =Z43/Z$37 -> 0 | AF44: =AF43/AF$37 -> 0 | AH44: 0 | AJ44: 0 | AL44: 0
B46: D&A (Depreciation & Amortization) | D46: 31 | E46: =IS!Q28 -> 0 | F46: =IS!R28 -> 0 | G46: =IS!S28 -> 0 | H46: =H49+H52 -> 166 | J46: =IS!V28 -> 0 | K46: =IS!W28 -> 0 | L46: =IS!X28 -> 0 | M46: =IS!Y28 -> 0 | N46: =N49+N52 -> 223 | P46: =IS!AB28 -> 0 | Q46: =IS!AC28 -> 0 | R46: =IS!AD28 -> 0 | S46: =IS!AE28 -> 0 | T46: =T49+T52 -> 414.8 | V46: =IS!AH28 -> 0 | W46: =IS!AI28 -> 0 | X46: =X49+X52 -> 433.04625 | Y46: =Y49+Y52 -> 380.999 | Z46: =Z49+Z52 -> 458.57694 | AB46: =AB49+AB52 -> 0 | AC46: =AC49+AC52 -> 0 | AD46: =AD49+AD52 -> 0 | AE46: =AE49+AE52 -> 0 | AF46: =AF49+AF52 -> 554.07884 | AH46: =AH49+AH52 -> 680.30889 | AJ46: =AJ49+AJ52 -> 709.64302 | AL46: =AL49+AL52 -> 737.13556
B47: % of net pp&e and intangibles excl. Goodwill | D47: =D46/(D76+D79) -> 0.019417719 | E47: =E46/(E76+E79) -> 0 | F47: =F46/(F76+F79) -> 0 | G47: =G46/(G76+G79) -> 0 | H47: =H46/(H76+H79) -> 0.084910747 | J47: =J46/(J76+J79) -> 0 | K47: =K46/(K76+K79) -> 0 | L47: =L46/(L76+L79) -> 0 | M47: =M46/(M76+M79) -> 0 | N47: =N46/(N76+N79) -> 0.090915206 | P47: =P46/(P76+P79) -> 0 | Q47: =Q46/(Q76+Q79) -> 0 | R47: =R46/(R76+R79) -> 0 | S47: =S46/(S76+S79) -> 0 | T47: =T46/(T76+T79) -> 0.068559014 | V47: =V46/(V76+V79) -> 0 | W47: =W46/(W76+W79) -> 0 | X47: =X46/( X76+X79) -> 0.081357635 | Y47: =Y46/( Y76+Y79) -> 0.077097996 | Z47: =Z46/(Z76+Z79) -> 0.077218243 | AB47: =AB46/( AB76+AB79) -> 0 | AC47: =AC46/( AC76+AC79) -> 0 | AD47: =AD46/( AD76+AD79) -> 0 | AE47: =AE46/( AE76+AE79) -> 0 | AF47: =AF46/(AF76+AF79) -> 0.090196882 | AH47: =AH46/( AH76+AH79) -> 0.10962633 | AJ47: =AJ46/( AJ76+AJ79) -> 0.11341721 | AL47: =AL46/( AL76+AL79) -> 0.11733963
B49: Depreciation | D49: =IS!P64 -> 0 | E49: =IS!Q64 -> 0 | F49: =IS!R64 -> 0 | G49: =IS!S64 -> 0 | H49: 135.7 | J49: =IS!V64 -> 0 | K49: =IS!W64 -> 0 | L49: =IS!X64 -> 0 | M49: =IS!Y64 -> 0 | N49: 176.3 | P49: =IS!AB64 -> 0 | Q49: =IS!AC64 -> 0 | R49: =IS!AD64 -> 0 | S49: =IS!AE64 -> 0 | T49: 288.3 | V49: =IS!AH64 -> 0 | W49: =IS!AI64 -> 0 | X49: =X50*W76 -> 325.4655 | Y49: =Y50*X76 -> 276.64567 | Z49: =Z50*T76 -> 346.33635 | AB49: =AB50*Y76 -> 0 | AC49: =AC50*AB76 -> 0 | AD49: =AD50*AC76 -> 0 | AE49: =AE50*AD76 -> 0 | AF49: =AF50*Z76 -> 435.98566 | AH49: =AH50*AF76 -> 553.78048 | AJ49: =AJ50*AH76 -> 576.76843 | AL49: =AL50*AJ76 -> 598.36982
B50: % of net pp&e | D50: =D49/D76 -> 0 | E50: =E49/E76 -> 0 | F50: =F49/F76 -> 0 | G50: =G49/G76 -> 0 | H50: =H49/H76 -> 0.19621679 | J50: =J49/J76 -> 0 | K50: =K49/K76 -> 0 | L50: =L49/L76 -> 0 | M50: =M49/M76 -> 0 | N50: =N49/N76 -> 0.19788333 | P50: =P49/P76 -> 0 | Q50: =Q49/Q76 -> 0 | R50: =R49/R76 -> 0 | S50: =S49/S76 -> 0 | T50: =T49/T76 -> 0.12486417 | V50: =V49/V76 -> 0 | W50: =W49/W76 -> 0 | X50: 0.15 | Y50: 0.15 | Z50: 0.15 | AF50: 0.17 | AH50: 0.2 | AJ50: 0.2 | AL50: 0.2
B52: Amortization | D52: =IS!P65 -> 0 | E52: =IS!Q65 -> 0 | F52: =IS!R65 -> 0 | G52: =IS!S65 -> 0 | H52: 30.3 | J52: =IS!V65 -> 0 | K52: =IS!W65 -> 0 | L52: =IS!X65 -> 0 | M52: =IS!Y65 -> 0 | N52: 46.7 | P52: =IS!AB65 -> 0 | Q52: =IS!AC65 -> 0 | R52: =IS!AD65 -> 0 | S52: =IS!AE65 -> 0 | T52: 126.5 | V52: =IS!AH65 -> 0 | W52: =IS!AI65 -> 0 | X52: =X53*W79 -> 107.58075 | Y52: =Y53*X79 -> 104.35333 | Z52: =Z53*T79 -> 112.24059 | AB52: =AB53*Y79 -> 0 | AC52: =AC53*AB79 -> 0 | AD52: =AD53*AC79 -> 0 | AE52: =AE53*AD79 -> 0 | AF52: =AF53*Z79 -> 118.09318 | AH52: =AH53*AF79 -> 126.52841 | AJ52: =AJ53*AH79 -> 132.87459 | AL52: =AL53*AJ79 -> 138.76574
B53: % of intangibles excl. goodwill | D53: =D52/D79 -> 0 | E53: =E52/E79 -> 0 | F53: =F52/F79 -> 0 | G53: =G52/G79 -> 0 | H53: =H52/H79 -> 0.023982675 | J53: =J52/J79 -> 0 | K53: =K52/K79 -> 0 | L53: =L52/L79 -> 0 | M53: =M52/M79 -> 0 | N53: =N52/N79 -> 0.029899367 | P53: =P52/P79 -> 0 | Q53: =Q52/Q79 -> 0 | R53: =R52/R79 -> 0 | S53: =S52/S79 -> 0 | T53: =T52/T79 -> 0.033811298 | V53: =V52/V79 -> 0 | W53: =W52/W79 -> 0 | X53: 0.03 | Y53: 0.03 | Z53: 0.03 | AF53: 0.035 | AH53: 0.0375 | AJ53: 0.04 | AL53: 0.0425
B55: Other Operating (Income) Expenses | D55: =IS!P30+IS!P32 -> 82.386 | E55: =IS!Q30+IS!Q32 -> 73.995 | F55: =IS!R30+IS!R32 -> 12.499 | G55: =IS!S30+IS!S32 -> -61.553 | H55: 105 | N55: 68 | T55: 49.3 | V55: =IS!AH30+IS!AH32 -> 69.356 | W55: =IS!AI30+IS!AI32 -> 31.441 | X55: =X56*X$26 -> 38.396727 | Y55: =Y56*Y$26 -> 40.962787 | Z55: =Z28*Z56 -> 142.43417 | AB55: =AB56*AB$26 -> 0 | AC55: =AC56*AC$26 -> 0 | AD55: =AD56*AD$26 -> 0 | AE55: =AE56*AE$26 -> 0 | AF55: =AF28*AF56 -> 127.02363 | AH55: =AH28*AH56 -> 173.37191 | AJ55: =AJ28*AJ56 -> 193.67384 | AL55: =AL28*AL56 -> 228.68347
B56: % of net sales | D56: =D55/D26 -> 0.032182295 | E56: =E55/E26 -> 0.028904534 | F56: =F55/F26 -> 0.0044630168 | G56: =G55/G26 -> -0.02058033 | H56: =H55/H28 -> 0.024801001 | J56: =J55/J28 -> #DIV/0! | K56: =K55/K28 -> #DIV/0! | L56: =L55/L28 -> #DIV/0! | M56: =M55/M28 -> #DIV/0! | N56: =N55/N28 -> 0.014029875 | P56: =P55/P28 -> #DIV/0! | Q56: =Q55/Q28 -> #DIV/0! | R56: =R55/R28 -> #DIV/0! | S56: =S55/S28 -> #DIV/0! | T56: =T55/T28 -> 0.0058831953 | V56: =V55/V26 -> 0.019708342 | W56: =W55/W26 -> 0.0089343384 | X56: 0.01 | Y56: 0.01 | Z56: =AVERAGE(T56,N56,H56) -> 0.014904691 | AF56: =AVERAGE(Z56,T56,N56) -> 0.01160592 | AH56: 0.014 | AJ56: 0.014 | AL56: 0.015
B58: EBIT (Operating Income) | H58: =H37-H40+H55 -> 569.7 | J58: =IS!V33 -> 116.98 | K58: =IS!W33 -> 130.92 | L58: =IS!X33 -> 179.298 | M58: =IS!Y33 -> 155.295 | N58: =N37-N40+N55 -> 587.9 | P58: =IS!AB33 -> 110.844 | Q58: =IS!AC33 -> 143.729 | R58: =IS!AD33 -> 187.465 | S58: =IS!AE33 -> 195.125 | T58: =T37-T40+T55 -> 630.6 | V58: =IS!AH33 -> 280.337 | W58: =IS!AI33 -> 367.104 | X58: =X37-X40-X43-X46-X55 -> -3543.1811 | Y58: =Y37-Y40-Y43-Y46-Y55 -> -3698.9848 | Z58: =Z37-Z40+Z55 -> 1980.6156 | AB58: =AB37-AB40-AB43-AB46-AB55 -> 0 | AC58: =AC37-AC40-AC43-AC46-AC55 -> 0 | AD58: =AD37-AD40-AD43-AD46-AD55 -> 0 | AE58: =AE37-AE40-AE43-AE46-AE55 -> 0 | AF58: =AF37-AF40+AF55 -> 2315.9689 | AH58: =AH37-AH40+AH55 -> 3269.299 | AJ58: =AJ37-AJ40+AJ55 -> 4067.1507 | AL58: =AL37-AL40+AL55 -> 4649.8972
B59: % of net sales | D59: =D58/D26 -> 0 | E59: =E58/E26 -> 0 | F59: =F58/F26 -> 0 | G59: =G58/G26 -> 0 | H59: =H58/H28 -> 0.13456315 | J59: =J58/J26 -> 0.038579302 | K59: =K58/K26 -> 0.04317663 | L59: =L58/L26 -> 0.054739491 | M59: =M58/M26 -> 0.044770318 | N59: =N58/N28 -> 0.12129653 | P59: =P58/P26 -> 0.033014425 | Q59: =Q58/Q26 -> 0.042809085 | R59: =R58/R26 -> 0.051803084 | S59: =S58/S26 -> 0.050793961 | T59: =T58/T28 -> 0.075252393 | V59: =V58/V26 -> 0.079661131 | W59: =W58/W26 -> 0.10431702 | X59: =X58/X$26 -> -0.92278207 | Y59: =Y58/Y$26 -> -0.90301101 | Z59: =Z58/Z$26 -> 0.13264441 | AB59: =AB58/AB$26 -> 0 | AC59: =AC58/AC$26 -> 0 | AD59: =AD58/AD$26 -> 0 | AE59: =AE58/AE$26 -> 0 | AF59: =AF58/AF$26 -> 0.13965991 | AH59: =AH58/AH$26 -> 0.17952 | AJ59: =AJ58/AJ$26 -> 0.2058 | AL59: =AL58/AL$26 -> 0.2196
B61: Basic Weighted Average Shares | D61: =IS!P59 -> 106.828 | E61: =IS!Q59 -> 109.772 | F61: =IS!R59 -> 110.019 | G61: =IS!S59 -> 110.197 | H61: =IS!T59 -> 109.204 | J61: =IS!V59 -> 110.095 | K61: =IS!W59 -> 110.281 | L61: =IS!X59 -> 110.914 | M61: =IS!Y59 -> 111.974 | N61: =IS!Z59 -> 110.816 | P61: =IS!AB59 -> 110.882 | Q61: =IS!AC59 -> 110.801 | R61: =IS!AD59 -> 119.792 | S61: =IS!AE59 -> 163.202 | T61: =IS!AF59 -> 130.704 | V61: =IS!AH59 -> 206.468 | W61: =IS!AI59 -> 205.998 | X61: =W61+X98 -> #DIV/0! | Y61: =X61+Y98 -> #DIV/0! | Z61: 206 | AB61: =Y61+AB98 -> #DIV/0! | AC61: =AB61+AC98 -> #DIV/0! | AD61: =AC61+AD98 -> #DIV/0! | AE61: =AD61+AE98 -> #DIV/0! | AF61: =Z61+Z98 -> 206.4216 | AH61: =AF61+AF98 -> 206.99076 | AJ61: =AH61+AH98 -> 207.40852 | AL61: =AJ61+AJ98 -> 207.78697
B62: Diluted Weighted Average Shares | D62: =IS!P60 -> 108.847 | E62: =IS!Q60 -> 111.713 | F62: =IS!R60 -> 115.014 | G62: =IS!S60 -> 116.078 | H62: =IS!T60 -> 112.913 | J62: =IS!V60 -> 113.035 | K62: =IS!W60 -> 113.211 | L62: =IS!X60 -> 113.681 | M62: =IS!Y60 -> 114.893 | N62: =IS!Z60 -> 113.705 | P62: =IS!AB60 -> 113.639 | Q62: =IS!AC60 -> 113.484 | R62: =IS!AD60 -> 123.334 | S62: =IS!AE60 -> 163.302 | T62: =IS!AF60 -> 133.326 | V62: =IS!AH60 -> 208.37 | W62: =IS!AI60 -> 209.206 | X62: =W62 -> 209.206 | Y62: =X62 -> 209.206 | Z62: =AVERAGE(V62:Y62) -> 208.997 | AB62: =Y62 -> 209.206 | AC62: =AB62 -> 209.206 | AD62: =AC62 -> 209.206 | AE62: =AD62 -> 209.206 | AF62: =AVERAGE(AB62:AE62) -> 209.206 | AH62: =AF62 -> 209.206 | AJ62: =AH62 -> 209.206 | AL62: =AJ62 -> 209.206
B64: Balance Sheet | D64: Q1 22 | E64: Q2 22 | F64: Q3 22 | G64: Q4 22 | H64: FY 22 | J64: Q1 23 | K64: Q2 23 | L64: Q3 23 | M64: Q4 23 | N64: FY 23 | P64: Q1 24 | Q64: Q2 24 | R64: Q3 24 | S64: Q4 24 | T64: FY 24 | V64: Q1 25 | W64: Q2 25 | X64: Q3 25 | Y64: Q4 25 | Z64: FY 25 | AB64: Q1 26 | AC64: Q2 26 | AD64: Q3 26 | AE64: Q4 26 | AF64: FY 26 | AH64: FY 27 | AJ64: FY 28 | AL64: FY 29
B67: Accounts Receivable | D67: =BS!P18 -> 631.278 | E67: =BS!Q18 -> 613.69 | F67: =BS!R18 -> 722.016 | G67: =BS!S18 -> 867.582 | H67: =BS!T18 -> 867.582 | J67: =BS!V18 -> 743.011 | K67: =BS!W18 -> 781.486 | L67: =BS!X18 -> 921.776 | M67: =BS!Y18 -> 1125.449 | N67: =BS!Z18 -> 1125.449 | P67: =BS!AB18 -> 902.621 | Q67: =BS!AC18 -> 963.304 | R67: =BS!AD18 -> 2512.451 | S67: =BS!AE18 -> 2816.294 | T67: =BS!AF18 -> 2816.294 | V67: =BS!AH18 -> 2448.811 | W67: =BS!AI18 -> 2596.937 | X67: =X26*X68/92 -> 2712.8122 | Y67: =Y26*Y68/92 -> 2894.11 | Z67: =Z26*Z68/365 -> 2659.082 | AB67: =AB26*AB68/90 -> 0 | AC67: =AC26*AC68/91 -> 0 | AD67: =AD26*AD68/92 -> 0 | AE67: =AE26*AE68/92 -> 0 | AF67: =AF26*AF68/365 -> 2725.9593 | AH67: =AH26*AH68/365 -> 2993.6442 | AJ67: =AJ26*AJ68/366 -> 2969.7952 | AL67: =AL26*AL68/365 -> 2900.6021
B68: days sales outstanding | D68: =D67/D26*90 -> 22.193549 | E68: =E67/E26*91 -> 21.814941 | F68: =F67/F26*92 -> 23.718537 | G68: =G67/G26*92 -> 26.687105 | H68: =H67/H26*365 -> 29.104756 | J68: =J67/J26*90 -> 22.053651 | K68: =K67/K26*91 -> 23.453374 | L68: =L67/L26*92 -> 25.890387 | M68: =M67/M26*92 -> 29.850139 | N68: =N67/N26*365 -> 32.15921 | P68: =P67/P26*90 -> 24.195772 | Q68: =Q67/Q26*91 -> 26.109365 | R68: =R67/R26*92 -> 63.873519 | S68: =S67/S26*92 -> 67.447364 | T68: =T67/T26*365 -> 72.614636 | V68: =V67/V26*90 -> 62.62732 | W68: =W67/W26*91 -> 67.153531 | X68: 65 | Y68: 65 | Z68: 65 | AF68: 60 | AH68: 60 | AJ68: 55 | AL68: 50
B70: Inventory | D70: =BS!P19 -> 556.685 | E70: =BS!Q19 -> 651.73 | F70: =BS!R19 -> 755.06 | G70: =BS!S19 -> 772.06 | H70: =BS!T19 -> 772.06 | J70: =BS!V19 -> 842.526 | K70: =BS!W19 -> 864.459 | L70: =BS!X19 -> 866.759 | M70: =BS!Y19 -> 828.557 | N70: =BS!Z19 -> 828.557 | P70: =BS!AB19 -> 920.2 | Q70: =BS!AC19 -> 968.239 | R70: =BS!AD19 -> 2313.143 | S70: =BS!AE19 -> 2218.815 | T70: =BS!AF19 -> 2218.815 | V70: =BS!AH19 -> 2456.987 | W70: =BS!AI19 -> 2474.521 | X70: =X71*X31/92 -> 3155.2093 | Y70: =Y71*Y31/92 -> 3328.6717 | Z70: =Z71*Z31/365 -> 1928.3651 | AB70: =AB71*AB31/92 -> 0 | AC70: =AC71*AC31/92 -> 0 | AD70: =AD71*AD31/92 -> 0 | AE70: =AE71*AE31/92 -> 0 | AF70: =AF71*AF31/365 -> 2158.9598 | AH70: =AH71*AH31/365 -> 2191.7467 | AJ70: =AJ71*AJ31/366 -> 2097.7553 | AL70: =AL71*AL31/365 -> 2105.141
B71: days inventory held | D71: =D70/D31*90 -> 49.996657 | E71: =E70/E31*91 -> 55.029186 | F71: =F70/F31*92 -> 129.45494 | G71: =G70/G31*92 -> #DIV/0! | H71: =H70/H31*365 -> 144.51379 | J71: =J70/J31*90 -> #DIV/0! | K71: =K70/K31*91 -> #DIV/0! | L71: =L70/L31*92 -> #DIV/0! | M71: =M70/M31*92 -> #DIV/0! | N71: =N70/N31*365 -> 136.368 | P71: =P70/P31*90 -> #DIV/0! | Q71: =Q70/Q31*91 -> #DIV/0! | R71: =R70/R31*92 -> #DIV/0! | S71: =S70/S31*92 -> #DIV/0! | T71: =T70/T31*365 -> 206.87855 | V71: =V70/V31*90 -> 181.29222 | W71: =W70/W31*91 -> 175.7969 | X71: 180 | Y71: 178 | Z71: 190 | AF71: 180 | AH71: 170 | AJ71: 150 | AL71: 140
B73: Prepaid expenses and Other Current Assets | D73: =BS!P20 -> 211.131 | E73: =BS!Q20 -> 212.246 | F73: =BS!R20 -> 268.658 | G73: =BS!S20 -> 267.369 | H73: =BS!T20 -> 267.369 | J73: =BS!V20 -> 322.411 | K73: =BS!W20 -> 443.156 | L73: =BS!X20 -> 251.663 | M73: =BS!Y20 -> 211.334 | N73: =BS!Z20 -> 211.334 | P73: =BS!AB20 -> 259.961 | Q73: =BS!AC20 -> 349.693 | R73: =BS!AD20 -> 1015.92 | S73: =BS!AE20 -> 1022.031 | T73: =BS!AF20 -> 1022.031 | V73: =BS!AH20 -> 1042.452 | W73: =BS!AI20 -> 971.353 | X73: =X74*X$26 -> 268.77709 | Y73: =Y74*Y$26 -> 245.77672 | Z73: =Z74*Z$26 -> 2621.447 | AB73: =AB74*AB$26 -> 0 | AC73: =AC74*AC$26 -> 0 | AD73: =AD74*AD$26 -> 0 | AE73: =AE74*AE$26 -> 0 | AF73: =AF74*AF$26 -> 2487.4379 | AH73: =AH74*AH$26 -> 2367.4736 | AJ73: =AJ74*AJ$26 -> 1976.2637 | AL73: =AL74*AL$26 -> 2117.4395
B74: % of sales | D74: =D73/D26 -> 0.082473723 | E74: =E73/E26 -> 0.082909274 | F74: =F73/F26 -> 0.095929689 | G74: =G73/G26 -> 0.08939519 | H74: =H73/H26 -> 0.02457376 | J74: =J73/J26 -> 0.10632921 | K74: =K73/K26 -> 0.14615019 | L74: =L73/L26 -> 0.07683245 | M74: =M73/M26 -> 0.060925918 | N74: =N73/N26 -> 0.016544592 | P74: =P73/P26 -> 0.077428304 | Q74: =Q73/Q26 -> 0.10415461 | R74: =R73/R26 -> 0.28073394 | S74: =S73/S26 -> 0.26604998 | T74: =T73/T26 -> 0.072196705 | V74: =V73/V26 -> 0.29622528 | W74: =W73/W26 -> 0.27602164 | X74: 0.07 | Y74: 0.06 | Z74: =AVERAGE(V74:Y74) -> 0.17556173 | AF74: 0.15 | AH74: 0.13 | AJ74: 0.1 | AL74: 0.1
B76: Net PP&E (Property, Plant and Equipment) | D76: =BS!P24 -> 446.326 | E76: =BS!Q24 -> 492.475 | F76: =BS!R24 -> 586.25 | G76: =BS!S24 -> 691.582 | H76: =BS!T24 -> 691.582 | J76: =BS!V24 -> 769.765 | K76: =BS!W24 -> 850.095 | L76: =BS!X24 -> 835.209 | M76: =BS!Y24 -> 890.929 | N76: =BS!Z24 -> 890.929 | P76: =BS!AB24 -> 845.792 | Q76: =BS!AC24 -> 863.457 | R76: =BS!AD24 -> 2168.252 | S76: =BS!AE24 -> 2308.909 | T76: =BS!AF24 -> 2308.909 | V76: =BS!AH24 -> 2230.121 | W76: =BS!AI24 -> 2169.77 | X76: =W76-X77*X103-X106-X49-X34 -> 1844.3045 | Y76: =X76-Y77*Y103-Y106-Y49-Y34 -> 1567.6588 | Z76: =T76-Z77*Z103-Z106-Z49-Z34 -> 2564.6215 | AB76: =Y76-AB77*AB103-AB106-AB49-AB34 -> 1567.6588 | AC76: =AB76-AC77*AC103-AC106-AC49-AC34 -> 1567.6588 | AD76: =AC76-AD77*AD103-AD106-AD49-AD34 -> 1567.6588 | AE76: =AD76-AE77*AE103-AE106-AE49-AE34 -> 1567.6588 | AF76: =Z76-AF77*AF103-AF106-AF49-AF34 -> 2768.9024 | AH76: =AF76-AH77*AH103-AH106-AH49-AH34 -> 2883.8421 | AJ76: =AH76-AJ77*AJ103-AJ106-AJ49-AJ34 -> 2991.8491 | AL76: =AJ76-AL77*AL103-AL106-AL49-AL34 -> 3079.5297
B77: capex allocation rate | Z77: 0.9 | AF77: 0.9 | AH77: 0.9 | AJ77: 0.9 | AL77: 0.9 | AN77: =T76-0.9*Z103 -> 2910.9579 | AO77: =AN77-Z49 -> 2564.6215
B79: Intangibles | D79: =IF($B$79="Intangibles excl. Goodwill",BS!P29,BS!P27) -> 1150.154 | E79: =IF($B$79="Intangibles excl. Goodwill",BS!Q29,BS!Q27) -> 1186.6 | F79: =IF($B$79="Intangibles excl. Goodwill",BS!R29,BS!R27) -> 1247.969 | G79: =IF($B$79="Intangibles excl. Goodwill",BS!S29,BS!S27) -> 1263.412 | H79: =IF($B$79="Intangibles excl. Goodwill",BS!T29,BS!T27) -> 1263.412 | J79: =IF($B$79="Intangibles excl. Goodwill",BS!V29,BS!V27) -> 1370.027 | K79: =IF($B$79="Intangibles excl. Goodwill",BS!W29,BS!W27) -> 1523.662 | L79: =IF($B$79="Intangibles excl. Goodwill",BS!X29,BS!X27) -> 1569.898 | M79: =IF($B$79="Intangibles excl. Goodwill",BS!Y29,BS!Y27) -> 1561.906 | N79: =IF($B$79="Intangibles excl. Goodwill",BS!Z29,BS!Z27) -> 1561.906 | P79: =IF($B$79="Intangibles excl. Goodwill",BS!AB29,BS!AB27) -> 1565.2 | Q79: =IF($B$79="Intangibles excl. Goodwill",BS!AC29,BS!AC27) -> 1587.92 | R79: =IF($B$79="Intangibles excl. Goodwill",BS!AD29,BS!AD27) -> 3908.228 | S79: =IF($B$79="Intangibles excl. Goodwill",BS!AE29,BS!AE27) -> 3741.353 | T79: =IF($B$79="Intangibles excl. Goodwill",BS!AF29,BS!AF27) -> 3741.353 | V79: =IF($B$79="Intangibles excl. Goodwill",BS!AH29,BS!AH27) -> 3508.455 | W79: =IF($B$79="Intangibles excl. Goodwill",BS!AI29,BS!AI27) -> 3586.025 | X79: =W79-(1-X77)*X103-X52+X80*X43 -> 3478.4443 | Y79: =X79-(1-Y77)*Y103-Y52+Y80*Y43 -> 3374.0909 | Z79: =Y79 -> 3374.0909 | AB79: =Y79-(1-AB77)*AB103-AB52+AB80*AB43 -> 3374.0909 | AC79: =AB79-(1-AC77)*AC103-AC52+AC80*AC43 -> 3374.0909 | AD79: =AC79-(1-AD77)*AD103-AD52+AD80*AD43 -> 3374.0909 | AE79: =AD79-(1-AE77)*AE103-AE52+AE80*AE43 -> 3374.0909 | AF79: =AE79 -> 3374.0909 | AH79: =AF79-(1-AH77)*AH103-AH52+AH80*AH43 -> 3321.8648 | AJ79: =AH79-(1-AJ77)*AJ103-AJ52+AJ80*AJ43 -> 3265.0763 | AL79: =AJ79-(1-AL77)*AL103-AL52+AL80*AL43 -> 3202.5384
B80: r&d capitalization rate | D80: =IFERROR(BS!P57/FCFF!D79,"") -> 0 | E80: =IFERROR(BS!Q57/FCFF!E79,"") -> 0 | F80: =IFERROR(BS!R57/FCFF!F79,"") -> 0 | G80: =IFERROR(BS!S57/FCFF!G79,"") -> 0 | H80: =IFERROR(BS!T57/FCFF!H79,"") -> 0 | J80: =IFERROR(BS!V57/FCFF!J79,"") -> 0 | K80: =IFERROR(BS!W57/FCFF!K79,"") -> 0 | L80: =IFERROR(BS!X57/FCFF!L79,"") -> 0 | M80: =IFERROR(BS!Y57/FCFF!M79,"") -> 0 | N80: =IFERROR(BS!Z57/FCFF!N79,"") -> 0 | P80: =IFERROR(BS!AB57/FCFF!P79,"") -> 0 | Q80: =IFERROR(BS!AC57/FCFF!Q79,"") -> 0 | R80: =IFERROR(BS!AD57/FCFF!R79,"") -> 0 | S80: =IFERROR(BS!AE57/FCFF!S79,"") -> 0 | T80: =IFERROR(BS!AF57/FCFF!T79,"") -> 0 | V80: =IFERROR(BS!AH57/FCFF!V79,"") -> 0 | W80: =IFERROR(BS!AI57/FCFF!W79,"") -> 0 | X80: 0.1 | Y80: 0.1 | Z80: 0.1 | AF80: 0.1 | AH80: 0.1 | AJ80: 0.1 | AL80: 0.1
B82: Accounts Payable | D82: =BS!P37 -> 744.399 | E82: =BS!Q37 -> 836.041 | F82: =BS!R37 -> 855.213 | G82: =BS!S37 -> 1064.289 | H82: =BS!T37 -> 1064.289 | J82: =BS!V37 -> 694.254 | K82: =BS!W37 -> 720.843 | L82: =BS!X37 -> 758.126 | M82: =BS!Y37 -> 1041.509 | N82: =BS!Z37 -> 1041.509 | P82: =BS!AB37 -> 827.768 | Q82: =BS!AC37 -> 934.674 | R82: =BS!AD37 -> 2339.209 | S82: =BS!AE37 -> 2794.703 | T82: =BS!AF37 -> 2794.703 | V82: =BS!AH37 -> 2213.791 | W82: =BS!AI37 -> 2086.516 | X82: =X83*X31/92 -> 0 | Y82: =Y83*Y31/92 -> 0 | Z82: =Z83*Z31/365 -> 2135.4212 | AB82: =AB83*AB31/90 -> 0 | AC82: =AC83*AC31/91 -> 0 | AD82: =AD83*AD31/92 -> 0 | AE82: =AE83*AE31/92 -> 0 | AF82: =AF83*AF31/365 -> 2568.3269 | AH82: =AH83*AH31/365 -> 2944.267 | AJ82: =AJ83*AJ31/366 -> 3043.6083 | AL82: =AL83*AL31/365 -> 3308.7396
B83: days payable outstanding | D83: =D82/D31*90 -> 66.855513 | E83: =E82/E31*91 -> 70.591588 | F83: =F82/F31*92 -> 146.62616 | G83: =G82/G31*92 -> #DIV/0! | H83: =H82/H31*365 -> 199.21307 | J83: =J82/J31*90 -> #DIV/0! | K83: =K82/K31*91 -> #DIV/0! | L83: =L82/L31*92 -> #DIV/0! | M83: =M82/M31*92 -> #DIV/0! | N83: =N82/N31*365 -> 171.41669 | P83: =P82/P31*90 -> #DIV/0! | Q83: =Q82/Q31*91 -> #DIV/0! | R83: =R82/R31*92 -> #DIV/0! | S83: =S82/S31*92 -> #DIV/0! | T83: =T82/T31*365 -> 260.57338 | V83: =V82/V31*90 -> 163.34766 | W83: =W82/W31*91 -> 148.23194 | Z83: =AVERAGE(T83,N83,H83) -> 210.40104 | AF83: =AVERAGE(Z83,T83,N83) -> 214.13037 | AH83: =AVERAGE(AF83,Z83,T83) -> 228.36826 | AJ83: =AVERAGE(AH83,AF83,Z83) -> 217.63323 | AL83: =AVERAGE(AJ83,AH83,AF83) -> 220.04395
B85: Accrued Expenses and Other Current Liabilities | D85: =BS!P40 -> 198.251 | E85: =BS!Q40 -> 189.875 | F85: =BS!R40 -> 573.546 | G85: =BS!S40 -> 89.169 | H85: =BS!T40 -> 89.169 | J85: =BS!V40 -> 138.524 | K85: =BS!W40 -> 242.344 | L85: =BS!X40 -> 226.011 | M85: =BS!Y40 -> 260.898 | N85: =BS!Z40 -> 260.898 | P85: =BS!AB40 -> 202.389 | Q85: =BS!AC40 -> 131.632 | R85: =BS!AD40 -> 262.238 | S85: =BS!AE40 -> 32.755 | T85: =BS!AF40 -> 32.755 | V85: =BS!AH40 -> 234.183 | W85: =BS!AI40 -> 236.094 | X85: =X86*X40 -> 0 | Y85: =Y86*Y40 -> 0 | Z85: =Z86*Z40 -> 242.35796 | AB85: =AB86*AB40 -> 0 | AC85: =AC86*AC40 -> 0 | AD85: =AD86*AD40 -> 0 | AE85: =AE86*AE40 -> 0 | AF85: =AF86*AF40 -> 280.93258 | AH85: =AH86*AH40 -> 203.11547 | AJ85: =AJ86*AJ40 -> 272.56902 | AL85: =AL86*AL40 -> 293.11155
B86: % of sg&a | D86: =D85/D40 -> 0.68935769 | E86: =E85/E40 -> #DIV/0! | F86: =F85/F40 -> #DIV/0! | G86: =G85/G40 -> #DIV/0! | H86: =H85/H40 -> 0.049020891 | J86: =J85/J40 -> #DIV/0! | K86: =K85/K40 -> #DIV/0! | L86: =L85/L40 -> #DIV/0! | M86: =M85/M40 -> #DIV/0! | N86: =N85/N40 -> 0.12369524 | P86: =P85/P40 -> #DIV/0! | Q86: =Q85/Q40 -> #DIV/0! | R86: =R85/R40 -> #DIV/0! | S86: =S85/S40 -> #DIV/0! | T86: =T85/T40 -> 0.0084337505 | V86: =V85/V40 -> 0.18936304 | W86: =W85/W40 -> 0.18618432 | Z86: =AVERAGE(T86,N86,H86) -> 0.060383294 | AF86: =AVERAGE(Z86,T86,N86) -> 0.064170761 | AH86: =AVERAGE(AF86,Z86,T86) -> 0.044329268 | AJ86: =AVERAGE(AH86,AF86,Z86) -> 0.056294441 | AL86: =AVERAGE(AJ86,AH86,AF86) -> 0.05493149
B88: Cash Flow Statement | D88: Q1 22 | E88: Q2 22 | F88: Q3 22 | G88: Q4 22 | H88: FY 22 | J88: Q1 23 | K88: Q2 23 | L88: Q3 23 | M88: Q4 23 | N88: FY 23 | P88: Q1 24 | Q88: Q2 24 | R88: Q3 24 | S88: Q4 24 | T88: FY 24 | V88: Q1 25 | W88: Q2 25 | X88: Q3 25 | Y88: Q4 25 | Z88: FY 25 | AB88: Q1 26 | AC88: Q2 26 | AD88: Q3 26 | AE88: Q4 26 | AF88: FY 26 | AH88: FY 27 | AJ88: FY 28 | AL88: FY 29
B91: D&A (Depreciation & Amortization) | D91: =CF!P17 -> 33.433 | E91: =CF!Q17 -> 34.813 | F91: =CF!R17 -> 38.019 | G91: =CF!S17 -> 59.765 | H91: =CF!T17 -> 166.03 | J91: =CF!V17 -> 49.396 | K91: =CF!W17 -> 54.48 | L91: =CF!X17 -> 55.587 | M91: =CF!Y17 -> 63.481 | N91: =CF!Z17 -> 222.944 | P91: =CF!AB17 -> 59.355 | Q91: =CF!AC17 -> 60.791 | R91: =CF!AD17 -> 122.918 | S91: =CF!AE17 -> 171.791 | T91: =CF!AF17 -> 414.855 | V91: =CF!AH17 -> 166.581 | W91: =CF!AI17 -> 167.139 | X91: =X34+X46 -> 433.04625 | Y91: =Y34+Y46 -> 380.999 | Z91: =Z46 -> 458.57694 | AB91: =AB34+AB46 -> 0 | AC91: =AC34+AC46 -> 0 | AD91: =AD34+AD46 -> 0 | AE91: =AE34+AE46 -> 0 | AF91: =AF46 -> 554.07884 | AH91: =AH46 -> 680.30889 | AJ91: =AJ46 -> 709.64302 | AL91: =AL46 -> 737.13556
B92: % of net pp&e and intangibles excl. Goodwill | D92: =D91/(D79+D76) -> 0.020941697 | E92: =E91/(E79+E76) -> 0.02073344 | F92: =F91/(F79+F76) -> 0.020727623 | G92: =G91/(G79+G76) -> 0.030570426 | H92: =H91/(H79+H76) -> 0.084926092 | J92: =J91/(J79+J76) -> 0.023084487 | K92: =K91/(K79+K76) -> 0.022950959 | L92: =L91/(L79+L76) -> 0.023112069 | M92: =M91/(M79+M76) -> 0.025880665 | N92: =N91/(N79+N76) -> 0.090892376 | P92: =P91/(P79+P76) -> 0.024618497 | Q92: =Q91/(Q79+Q76) -> 0.024798715 | R92: =R91/(R79+R76) -> 0.020228488 | S92: =S91/(S79+S76) -> 0.028393977 | T92: =T91/(T79+T76) -> 0.068568105 | V92: =V91/(V79+V76) -> 0.029028282 | W92: =W91/(W79+W76) -> 0.029038387 | X92: =X91/(X76+X79) -> 0.081357635 | Y92: =Y91/(Y76+Y79) -> 0.077097996 | Z92: =Z91/(Z76+Z79) -> 0.077218243 | AB92: =AB91/(AB76+AB79) -> 0 | AC92: =AC91/(AC76+AC79) -> 0 | AD92: =AD91/(AD76+AD79) -> 0 | AE92: =AE91/(AE76+AE79) -> 0 | AF92: =AF91/(AF76+AF79) -> 0.090196882 | AH92: =AH91/(AH76+AH79) -> 0.10962633 | AJ92: =AJ91/(AJ76+AJ79) -> 0.11341721 | AL92: =AL91/(AL76+AL79) -> 0.11733963
B94: Stock-Based Compensation Expense | D94: =CF!P18 -> 3.436 | E94: =CF!Q18 -> 3.436 | F94: =CF!R18 -> 4.653 | G94: =CF!S18 -> 5.018 | H94: =CF!T18 -> 16.543 | J94: =CF!V18 -> 4.39 | K94: =CF!W18 -> 4.382 | L94: =CF!X18 -> 4.858 | M94: =CF!Y18 -> 3.718 | N94: =CF!Z18 -> 17.348 | P94: =CF!AB18 -> 3.197 | Q94: =CF!AC18 -> 3.197 | R94: =CF!AD18 -> 5.365 | S94: =CF!AE18 -> 6.157 | T94: =CF!AF18 -> 17.916 | V94: =CF!AH18 -> 5.381 | W94: =CF!AI18 -> 5.815 | X94: =X95*X40 -> 0 | Y94: =Y95*Y40 -> 0 | Z94: =Z40*Z95 -> 24.081955 | AB94: =AB95*AB40 -> 0 | AC94: =AC95*AC40 -> 0 | AD94: =AD95*AD40 -> 0 | AE94: =AE95*AE40 -> 0 | AF94: =AF40*AF95 -> 27.490128 | AH94: =AH95*AH40 -> 25.800041 | AJ94: =AJ95*AJ40 -> 28.905952 | AL94: =AL95*AL40 -> 31.802441
B95: % of sg&a | D95: =D94/D40 -> 0.011947647 | E95: =E94/E40 -> #DIV/0! | F95: =F94/F40 -> #DIV/0! | G95: =G94/G40 -> #DIV/0! | H95: =H94/H40 -> 0.0090945574 | J95: =J94/J40 -> #DIV/0! | K95: =K94/K40 -> #DIV/0! | L95: =L94/L40 -> #DIV/0! | M95: =M94/M40 -> #DIV/0! | N95: =N94/N40 -> 0.0082249194 | P95: =P94/P40 -> #DIV/0! | Q95: =Q94/Q40 -> #DIV/0! | R95: =R94/R40 -> #DIV/0! | S95: =S94/S40 -> #DIV/0! | T95: =T94/T40 -> 0.0046130079 | V95: =V94/V40 -> 0.0043511379 | W95: =W94/W40 -> 0.0045857235 | Z95: 0.006 | AF95: =AVERAGE(Z95,T95,N95) -> 0.0062793091 | AH95: =AVERAGE(AF95,Z95,T95) -> 0.0056307723 | AJ95: =AVERAGE(AH95,AF95,Z95) -> 0.0059700271 | AL95: =AVERAGE(AJ95,AH95,AF95) -> 0.0059600362
B96: implied equity value (p/s multiple) | Z96: 0.5 | AF96: 0.6 | AH96: 0.7 | AJ96: 0.8 | AL96: 0.7
B97: implied share price (for dilution) | X97: =X96*(X26+W26+V26+S26)/W61 -> 0 | Y97: =Y96*(Y26+X26+W26+V26)/X61 -> #DIV/0! | Z97: =Z96*Z26/T61 -> 57.120547 | AB97: =AB96*(AB26+Y26+X26+W26)/Y61 -> #DIV/0! | AC97: =AC96*(AC26+AB26+Y26+X26)/AB61 -> #DIV/0! | AD97: =AD96*(AD26+AC26+AB26+Y26)/AC61 -> #DIV/0! | AE97: =AE96*(AE26+AD26+AC26+AB26)/AD61 -> #DIV/0! | AF97: =AF96*AF26/Z61 -> 48.299764 | AH97: =AH96*AH26/AF61 -> 61.756788 | AJ97: =AJ96*AJ26/AH61 -> 76.380752 | AL97: =AL96*AL26/AJ61 -> 71.463199
B98: sbc dilution (shares issued) | X98: =X94/X97 -> #DIV/0! | Y98: =Y94/Y97 -> #DIV/0! | Z98: =Z94/Z97 -> 0.42159882 | AB98: =AB94/AB97 -> #DIV/0! | AC98: =AC94/AC97 -> #DIV/0! | AD98: =AD94/AD97 -> #DIV/0! | AE98: =AE94/AE97 -> #DIV/0! | AF98: =AF94/AF97 -> 0.56915658 | AH98: =AH94/AH97 -> 0.41776851 | AJ98: =AJ94/AJ97 -> 0.37844551 | AL98: =AL94/AL97 -> 0.44501843
B100: Changes in Net Working Capital | D100: =SUM(CF!P21:P24) -> -50.892 | E100: =SUM(CF!Q21:Q24) -> -37.59 | F100: =SUM(CF!R21:R24) -> -188.676 | G100: =SUM(CF!S21:S24) -> -54.508 | H100: =SUM(CF!T21:T24) -> -331.666 | J100: =SUM(CF!V21:V24) -> -95.668 | K100: =SUM(CF!W21:W24) -> -76.958 | L100: =SUM(CF!X21:X24) -> -56.404 | M100: =SUM(CF!Y21:Y24) -> 131.264 | N100: =SUM(CF!Z21:Z24) -> -97.766 | P100: =SUM(CF!AB21:AB24) -> -105.854 | Q100: =SUM(CF!AC21:AC24) -> -123.229 | R100: =SUM(CF!AD21:AD24) -> -160.61 | S100: =SUM(CF!AE21:AE24) -> -146.907 | T100: =SUM(CF!AF21:AF24) -> -536.6 | V100: =SUM(CF!AH21:AH24) -> -136.44 | W100: =SUM(CF!AI21:AI24) -> -453.134 | X100: =-((X67+X70+X73-X82-X85)-(W67+W70+W73-W82-W85)) -> -2416.5976 | Y100: =-((Y67+Y70+Y73-Y82-Y85)-(X67+X70+X73-X82-X85)) -> -331.75975 | Z100: =-((Z67+Z70+Z73-Z82+Z85)-(T67+T70+T73-T82+T85)) -> -2020.6388 | AB100: =-((AB67+AB70+AB73-AB82-AB85)-(Y67+Y70+Y73-Y82-Y85)) -> 6468.5584 | AC100: =-((AC67+AC70+AC73-AC82-AC85)-(AB67+AB70+AB73-AB82-AB85)) -> 0 | AD100: =-((AD67+AD70+AD73-AD82-AD85)-(AC67+AC70+AC73-AC82-AC85)) -> 0 | AE100: =-((AE67+AE70+AE73-AE82-AE85)-(AD67+AD70+AD73-AD82-AD85)) -> 0 | AF100: =-((AF67+AF70+AF73-AF82+AF85)-(Z67+Z70+Z73-Z82+Z85)) -> 230.86828 | AH100: =-((AH67+AH70+AH73-AH82-AH85)-(AF67+AF70+AF73-AF82-AF85)) -> 117.61532 | AJ100: =-((AJ67+AJ70+AJ73-AJ82-AJ85)-(AH67+AH70+AH73-AH82-AH85)) -> 677.8453 | AL100: =-((AL67+AL70+AL73-AL82-AL85)-(AJ67+AJ70+AJ73-AJ82-AJ85)) -> 206.30532
B101: % of change in sales | D101: =D100/(D26-IS!M18) -> -0.034690521 | E101: =E100/(E26-D26) -> #DIV/0! | F101: =F100/(F26-E26) -> -0.78421234 | G101: =G100/(G26-F26) -> -0.28644158 | H101: =H100/IS!N18 -> -0.11343558 | J101: =J100/(J26-IS!S18) -> -0.055595625 | K101: =K100/(K26-J26) -> #DIV/0! | L101: =L100/(L26-K26) -> -0.23184607 | M101: =M100/(M26-L26) -> 0.67932746 | N101: =N100/IS!T18 -> -0.023092189 | P101: =P100/(P26-IS!Y18) -> -0.05476688 | Q101: =Q100/(Q26-P26) -> #DIV/0! | R101: =R100/(R26-Q26) -> -0.6145199 | S101: =S100/(S26-R26) -> -0.65966322 | T101: =T100/IS!Z18 -> -0.11071295 | V101: =V100/(V26-IS!AE18) -> -1.1835839 | W101: =W100/(W26-V26) -> #DIV/0! | X101: =X100/(X26-W26) -> -7.5388228 | Y101: =Y100/(Y26-X26) -> -1.292876 | Z101: =Z100/(Z26-T26) -> -2.6053664 | AB101: =AB100/(AB26-IS!AK18) -> 1.65676 | AC101: =AC100/(AC26-AB26) -> #DIV/0! | AD101: =AD100/(AD26-AC26) -> 0 | AE101: =AE100/(AE26-AD26) -> 0 | AF101: =AF100/(AF26-Z26) -> 0.13982263 | AH101: =AH100/(AH26-AF26) -> 0.072226807 | AJ101: =AJ100/(AJ26-AH26) -> 0.43695272 | AL101: =AL100/(AL26-AJ26) -> 0.14613359
B103: Capital Expenditures | D103: =CF!P28 -> -40.835 | E103: =CF!Q28 -> -56.004 | F103: =CF!R28 -> -63.697 | G103: =CF!S28 -> -72.607 | H103: =CF!T28 -> -233.143 | J103: =CF!V28 -> -50.998 | K103: =CF!W28 -> -74.524 | L103: =CF!X28 -> -47.712 | M103: =CF!Y28 -> -61.967 | N103: =CF!Z28 -> -235.201 | P103: =CF!AB28 -> -41.514 | Q103: =CF!AC28 -> -66.795 | R103: =CF!AD28 -> -115.464 | S103: =CF!AE28 -> -195.189 | T103: =CF!AF28 -> -418.962 | V103: =CF!AH28 -> -84.39 | W103: =CF!AI28 -> -94.177 | X103: =-X$26*(X104+Sensitivity!$U$38) -> 0 | Y103: =-Y$26*(Y104+Sensitivity!$U$38) -> 0 | Z103: =-(Z28*Z104) -> -668.94321 | AB103: =-AB$26*(AB104+Sensitivity!$U$38) -> 0 | AC103: =-AC$26*(AC104+Sensitivity!$U$38) -> 0 | AD103: =-AD$26*(AD104+Sensitivity!$U$38) -> 0 | AE103: =-AE$26*(AE104+Sensitivity!$U$38) -> 0 | AF103: =-(AF28*AF104) -> -711.40723 | AH103: =-(AH28*AH104) -> -743.02249 | AJ103: =-(AJ28*AJ104) -> -760.86152 | AL103: =-(AL28*AL104) -> -762.27823
B104: % of sales | D104: =-D103/D26 -> 0.015951303 | E104: =-E103/E26 -> 0.021876742 | F104: =-F103/F26 -> 0.022744282 | G104: =-G103/G26 -> 0.02427625 | H104: =-H103/H28 -> 0.05506838 | J104: =-J103/J26 -> 0.016818834 | K104: =-K103/K26 -> 0.024577568 | L104: =-L103/L26 -> 0.014566424 | M104: =-M103/M26 -> 0.017864595 | N104: =-N103/N28 -> 0.048527069 | P104: =-P103/P26 -> 0.012364772 | Q104: =-Q103/Q26 -> 0.019894613 | R104: =-R103/R26 -> 0.031906709 | S104: =-S103/S26 -> 0.050810621 | T104: =-T103/T28 -> 0.049996659 | V104: =-V103/V26 -> 0.023980434 | W104: =-W103/W26 -> 0.026761528 | Z104: 0.07 | AF104: 0.065 | AH104: 0.06 | AJ104: 0.055 | AL104: 0.05
B106: Proceeds from Asset Disposals | D106: =CF!P29 -> 0 | E106: =CF!Q29 -> 0 | F106: =CF!R29 -> 0 | G106: =CF!S29 -> 0 | H106: =CF!T29 -> 0 | J106: =CF!V29 -> 0 | K106: =CF!W29 -> 0 | L106: =CF!X29 -> 0 | M106: =CF!Y29 -> 0 | N106: =CF!Z29 -> 0 | P106: =CF!AB29 -> 0 | Q106: =CF!AC29 -> 0 | R106: =CF!AD29 -> 0 | S106: =CF!AE29 -> 0 | T106: =CF!AF29 -> 0 | V106: =CF!AH29 -> 0 | W106: =CF!AI29 -> 0 | X106: =X107*X$103 -> 0 | Y106: =Y107*Y$103 -> 0 | Z106: =SUM(V106:Y106) -> 0 | AB106: =AB107*AB$103 -> 0 | AC106: =AC107*AC$103 -> 0 | AD106: =AD107*AD$103 -> 0 | AE106: =AE107*AE$103 -> 0 | AF106: =SUM(AB106:AE106) -> 0 | AH106: =AH107*AH$103 -> 0 | AJ106: =AJ107*AJ$103 -> 0 | AL106: =AL107*AL$103 -> 0
B107: % of capex | D107: =-D106/D103 -> 0 | E107: =-E106/E103 -> 0 | F107: =-F106/F103 -> 0 | G107: =-G106/G103 -> 0 | H107: =-H106/H103 -> 0 | J107: =-J106/J103 -> 0 | K107: =-K106/K103 -> 0 | L107: =-L106/L103 -> 0 | M107: =-M106/M103 -> 0 | N107: =-N106/N103 -> 0 | P107: =-P106/P103 -> 0 | Q107: =-Q106/Q103 -> 0 | R107: =-R106/R103 -> 0 | S107: =-S106/S103 -> 0 | T107: =-T106/T103 -> 0 | V107: =-V106/V103 -> 0 | W107: =-W106/W103 -> 0 | X107: 0 | Y107: 0 | Z107: =-Z106/Z$26 -> 0 | AB107: 0 | AC107: 0 | AD107: 0 | AE107: 0 | AF107: =-AF106/AF$26 -> 0 | AH107: 0 | AJ107: 0 | AL107: 0
B109: Dividends | D109: =CF!P39 -> -60 | E109: =CF!Q39 -> 0 | F109: =CF!R39 -> -69.683 | G109: =CF!S39 -> -50 | H109: =CF!T39 -> -179.683 | J109: =CF!V39 -> -82.107 | K109: =CF!W39 -> 0 | L109: =CF!X39 -> -102.148 | M109: =CF!Y39 -> -112.047 | N109: =CF!Z39 -> -296.302 | P109: =CF!AB39 -> 0 | Q109: =CF!AC39 -> 0 | R109: =CF!AD39 -> -60 | S109: =CF!AE39 -> -118.749 | T109: =CF!AF39 -> -178.749 | V109: =CF!AH39 -> 0 | W109: =CF!AI39 -> 0 | X109: =-X110*X123 -> 387.97834 | Y109: =-Y110*Y123 -> 405.03883 | Z109: =SUM(V109:Y109) -> 793.01717 | AB109: =-AB110*AB123 -> 0 | AC109: =-AC110*AC123 -> 0 | AD109: =-AD110*AD123 -> 0 | AE109: =-AE110*AE123 -> 0 | AF109: =SUM(AB109:AE109) -> 0 | AH109: =-AH110*AH123 -> -592.56044 | AJ109: =-AJ110*AJ123 -> -884.60527 | AL109: =-AL110*AL123 -> -1011.3526
B110: % of NOPAT | D110: =-D109/D123 -> #DIV/0! | E110: =-E109/E123 -> #DIV/0! | F110: =-F109/F123 -> #DIV/0! | G110: =-G109/G123 -> #DIV/0! | H110: =-H109/H123 -> 0.35611366 | J110: =-J109/J123 -> 0.76067813 | K110: =-K109/K123 -> 0 | L110: =-L109/L123 -> 0.64229883 | M110: =-M109/M123 -> 0.61158001 | N110: =-N109/N123 -> 0.48615466 | P110: =-P109/P123 -> 0 | Q110: =-Q109/Q123 -> 0 | R110: =-R109/R123 -> 0.14218823 | S110: =-S109/S123 -> 0.11546873 | T110: =-T109/T123 -> 0.13091256 | V110: =-V109/V123 -> 0 | W110: =-W109/W123 -> 0 | X110: 0.15 | Y110: 0.15 | Z110: 0.15 | AB110: 0 | AC110: 0 | AD110: 0.2 | AE110: 0.2 | AF110: 0.2 | AH110: 0.25 | AJ110: 0.3 | AL110: 0.3
B112: Repurchase of Stock | D112: =CF!P40 -> -36.776 | E112: =CF!Q40 -> 36.776 | F112: =CF!R40 -> -24.377 | G112: =CF!S40 -> -1.68 | H112: =CF!T40 -> -26.057 | J112: =CF!V40 -> -6.191 | K112: =CF!W40 -> -3.024 | L112: =CF!X40 -> 0 | M112: =CF!Y40 -> -2.033 | N112: =CF!Z40 -> -11.248 | P112: =CF!AB40 -> 0 | Q112: =CF!AC40 -> 0 | R112: =CF!AD40 -> 0 | S112: =CF!AE40 -> 0 | T112: =CF!AF40 -> 0 | V112: =CF!AH40 -> 0 | W112: =CF!AI40 -> 0 | X112: 0 | Y112: 0 | Z112: =SUM(V112:Y112) -> 0 | AF112: -18 | AH112: -18 | AJ112: -18 | AL112: -18
A114: x | B114: Free Cash Flow to Firm
D115: =D$8 -> 2022 | E115: =F115 -> 0 | F115: =F$8 -> 0 | G115: =F115 -> 0 | H115: =F115 -> 0 | J115: =J$8 -> 2023 | K115: =L115 -> 0 | L115: =L$8 -> 0 | M115: =L115 -> 0 | N115: =L115 -> 0 | P115: =P$8 -> 2024 | Q115: =R115 -> 0 | R115: =R$8 -> 0 | S115: =R115 -> 0 | T115: =R115 -> 0 | V115: =V$8 -> 2025 | W115: =X115 -> 0 | X115: =X$8 -> 0 | Y115: =X115 -> 0 | Z115: =X115 -> 0 | AB115: =AB$8 -> 2026 | AC115: =AD115 -> 0 | AD115: =AD$8 -> 0 | AE115: =AD115 -> 0 | AF115: =AD115 -> 0 | AH115: =AH$8 -> 2027 | AJ115: =AJ$8 -> 2028 | AL115: =AL$8 -> 2029
D116: Q1 | E116: Q2 | F116: Q3 | G116: Q4 | H116: FY | J116: Q1 | K116: Q2 | L116: Q3 | M116: Q4 | N116: FY | P116: Q1 | Q116: Q2 | R116: Q3 | S116: Q4 | T116: FY | V116: Q1 | W116: Q2 | X116: Q3 | Y116: Q4 | Z116: FY | AB116: Q1 | AC116: Q2 | AD116: Q3 | AE116: Q4 | AF116: FY | AH116: FY | AJ116: FY | AL116: FY
B119: EBIT (Operating Income) | D119: =D58 -> 0 | E119: =E58 -> 0 | F119: =F58 -> 0 | G119: =G58 -> 0 | H119: =H58 -> 569.7 | J119: =J58 -> 116.98 | K119: =K58 -> 130.92 | L119: =L58 -> 179.298 | M119: =M58 -> 155.295 | N119: =N58 -> 587.9 | P119: =P58 -> 110.844 | Q119: =Q58 -> 143.729 | R119: =R58 -> 187.465 | S119: =S58 -> 195.125 | T119: =T58 -> 630.6 | V119: =V58 -> 280.337 | W119: =W58 -> 367.104 | X119: =X58 -> -3543.1811 | Y119: =Y58 -> -3698.9848 | Z119: =Z58 -> 1980.6156 | AB119: =AB58 -> 0 | AC119: =AC58 -> 0 | AD119: =AD58 -> 0 | AE119: =AE58 -> 0 | AF119: =AF58 -> 2315.9689 | AH119: =AH58 -> 3269.299 | AJ119: =AJ58 -> 4067.1507 | AL119: =AL58 -> 4649.8972
B121: Tax Rate | D121: =IS!P45/IS!P42 -> 0.30879537 | E121: =IS!Q45/IS!Q42 -> -0.5067251 | F121: =IS!R45/IS!R42 -> 0.13492157 | G121: =IS!S45/IS!S42 -> 0.12241993 | H121: =IS!T45/IS!T42 -> 0.11432959 | J121: =IS!V45/IS!V42 -> 0.077284885 | K121: =IS!W45/IS!W42 -> -0.19272288 | L121: =IS!X45/IS!X42 -> 0.11301292 | M121: =IS!Y45/IS!Y42 -> -0.17974863 | N121: =IS!Z45/IS!Z42 -> -0.036708528 | P121: =IS!AB45/IS!AB42 -> -0.1702624 | Q121: =IS!AC45/IS!AC42 -> -0.35326184 | R121: =IS!AD45/IS!AD42 -> -1.250958 | S121: =IS!AE45/IS!AE42 -> -4.27051 | T121: =IS!AF45/IS!AF42 -> -1.1652515 | V121: =IS!AH45/IS!AH42 -> 0.011781692 | W121: =IS!AI45/IS!AI42 -> -2.2476801 | X121: 0.27 | Y121: 0.27 | Z121: =-(Z123/Z119-1) -> -0.22983083 | AF121: 0.275 | AH121: 0.275 | AJ121: 0.275 | AL121: 0.275
B123: NOPAT (Net Operating Profit After Taxes) | D123: =D119*(1-D121) -> 0 | E123: =E119*(1-E121) -> 0 | F123: =F119*(1-F121) -> 0 | G123: =G119*(1-G121) -> 0 | H123: =H119*(1-H121) -> 504.56643 | J123: =J119*(1-J121) -> 107.93921 | K123: =K119*(1-K121) -> 156.15128 | L123: =L119*(1-L121) -> 159.03501 | M123: =M119*(1-M121) -> 183.20906 | N123: =N119*(1-N121) -> 609.48094 | P123: =P119*(1-P121) -> 129.71657 | Q123: =Q119*(1-Q121) -> 194.50297 | R123: =R119*(1-R121) -> 421.97585 | S123: =S119*(1-S121) -> 1028.4083 | T123: =T119*(1-T121) -> 1365.4076 | V123: =V119*(1-V121) -> 277.03416 | W123: =W119*(1-W121) -> 1192.2364 | X123: =X119*(1-X121) -> -2586.5222 | Y123: =Y119*(1-Y121) -> -2700.2589 | Z123: =+(Z119-W119-V119)*(1-0.275)+V123+W123 -> 2435.8221 | AB123: =AB119*(1-AB121) -> 0 | AC123: =AC119*(1-AC121) -> 0 | AD123: =AD119*(1-AD121) -> 0 | AE123: =AE119*(1-AE121) -> 0 | AF123: =AF119*(1-AF121) -> 1679.0775 | AH123: =AH119*(1-AH121) -> 2370.2417 | AJ123: =AJ119*(1-AJ121) -> 2948.6842 | AL123: =AL119*(1-AL121) -> 3371.1755
B125: D&A (Depreciation & Amortization) | D125: =D91 -> 33.433 | E125: =E91 -> 34.813 | F125: =F91 -> 38.019 | G125: =G91 -> 59.765 | H125: =H91 -> 166.03 | J125: =J91 -> 49.396 | K125: =K91 -> 54.48 | L125: =L91 -> 55.587 | M125: =M91 -> 63.481 | N125: =N91 -> 222.944 | P125: =P91 -> 59.355 | Q125: =Q91 -> 60.791 | R125: =R91 -> 122.918 | S125: =S91 -> 171.791 | T125: =T91 -> 414.855 | V125: =V91 -> 166.581 | W125: =W91 -> 167.139 | X125: =X91 -> 433.04625 | Y125: =Y91 -> 380.999 | Z125: =Z91 -> 458.57694 | AB125: =AB91 -> 0 | AC125: =AC91 -> 0 | AD125: =AD91 -> 0 | AE125: =AE91 -> 0 | AF125: =AF91 -> 554.07884 | AH125: =AH91 -> 680.30889 | AJ125: =AJ91 -> 709.64302 | AL125: =AL91 -> 737.13556
B127: Stock-Based Compensation | D127: =D94 -> 3.436 | E127: =E94 -> 3.436 | F127: =F94 -> 4.653 | G127: =G94 -> 5.018 | H127: =H94 -> 16.543 | J127: =J94 -> 4.39 | K127: =K94 -> 4.382 | L127: =L94 -> 4.858 | M127: =M94 -> 3.718 | N127: =N94 -> 17.348 | P127: =P94 -> 3.197 | Q127: =Q94 -> 3.197 | R127: =R94 -> 5.365 | S127: =S94 -> 6.157 | T127: =T94 -> 17.916 | V127: =V94 -> 5.381 | W127: =W94 -> 5.815 | X127: =X94 -> 0 | Y127: =Y94 -> 0 | Z127: =Z94 -> 24.081955 | AB127: =AB94 -> 0 | AC127: =AC94 -> 0 | AD127: =AD94 -> 0 | AE127: =AE94 -> 0 | AF127: =AF94 -> 27.490128 | AH127: =AH94 -> 25.800041 | AJ127: =AJ94 -> 28.905952 | AL127: =AL94 -> 31.802441
B129: Changes in Net Working Capital | D129: =D100 -> -50.892 | E129: =E100 -> -37.59 | F129: =F100 -> -188.676 | G129: =G100 -> -54.508 | H129: =H100 -> -331.666 | J129: =J100 -> -95.668 | K129: =K100 -> -76.958 | L129: =L100 -> -56.404 | M129: =M100 -> 131.264 | N129: =N100 -> -97.766 | P129: =P100 -> -105.854 | Q129: =Q100 -> -123.229 | R129: =R100 -> -160.61 | S129: =S100 -> -146.907 | T129: =T100 -> -536.6 | V129: =V100 -> -136.44 | W129: =W100 -> -453.134 | X129: =X100 -> -2416.5976 | Y129: =Y100 -> -331.75975 | Z129: =Z100 -> -2020.6388 | AB129: =AB100 -> 6468.5584 | AC129: =AC100 -> 0 | AD129: =AD100 -> 0 | AE129: =AE100 -> 0 | AF129: =AF100 -> 230.86828 | AH129: =AH100 -> 117.61532 | AJ129: =AJ100 -> 677.8453 | AL129: =AL100 -> 206.30532
B131: Net CapEx | D131: =D103+D106 -> -40.835 | E131: =E103+E106 -> -56.004 | F131: =F103+F106 -> -63.697 | G131: =G103+G106 -> -72.607 | H131: =H103+H106 -> -233.143 | J131: =J103+J106 -> -50.998 | K131: =K103+K106 -> -74.524 | L131: =L103+L106 -> -47.712 | M131: =M103+M106 -> -61.967 | N131: =N103+N106 -> -235.201 | P131: =P103+P106 -> -41.514 | Q131: =Q103+Q106 -> -66.795 | R131: =R103+R106 -> -115.464 | S131: =S103+S106 -> -195.189 | T131: =T103+T106 -> -418.962 | V131: =V103+V106 -> -84.39 | W131: =W103+W106 -> -94.177 | X131: =X103+X106 -> 0 | Y131: =Y103+Y106 -> 0 | Z131: =Z103+Z106 -> -668.94321 | AB131: =AB103+AB106 -> 0 | AC131: =AC103+AC106 -> 0 | AD131: =AD103+AD106 -> 0 | AE131: =AE103+AE106 -> 0 | AF131: =AF103+AF106 -> -711.40723 | AH131: =AH103+AH106 -> -743.02249 | AJ131: =AJ103+AJ106 -> -760.86152 | AL131: =AL103+AL106 -> -762.27823
B133: FCFF (Free Cash Flow to Firm) | D133: =D123+D91+D94+D100+D131 -> -54.858 | E133: =E123+E91+E94+E100+E131 -> -55.345 | F133: =F123+F91+F94+F100+F131 -> -209.701 | G133: =G123+G91+G94+G100+G131 -> -62.332 | H133: =H123+H91+H94+H100+H131 -> 122.33043 | J133: =J123+J91+J94+J100+J131 -> 15.059214 | K133: =K123+K91+K94+K100+K131 -> 63.531279 | L133: =L123+L91+L94+L100+L131 -> 115.36401 | M133: =M123+M91+M94+M100+M131 -> 319.70506 | N133: =N123+N91+N94+N100+N131 -> 516.80594 | P133: =P123+P91+P94+P100+P131 -> 44.900566 | Q133: =Q123+Q91+Q94+Q100+Q131 -> 68.466971 | R133: =R123+R91+R94+R100+R131 -> 274.18485 | S133: =S123+S91+S94+S100+S131 -> 864.26027 | T133: =T123+T91+T94+T100+T131 -> 842.61658 | V133: =V123+V91+V94+V100+V131 -> 228.16616 | W133: =W123+W91+W94+W100+W131 -> 817.87936 | X133: =X123+X125+X127+X129+X131 -> -4570.0736 | Y133: =Y123+Y125+Y127+Y129+Y131 -> -2651.0196 | Z133: =Z123+Z125+Z127+Z129+Z131 -> 228.89892 | AB133: =AB123+AB125+AB127+AB129+AB131 -> 6468.5584 | AC133: =AC123+AC125+AC127+AC129+AC131 -> 0 | AD133: =AD123+AD125+AD127+AD129+AD131 -> 0 | AE133: =AE123+AE125+AE127+AE129+AE131 -> 0 | AF133: =AF123+AF125+AF127+AF129+AF131 -> 1780.1075 | AH133: =AH123+AH125+AH127+AH129+AH131 -> 2450.9435 | AJ133: =AJ123+AJ125+AJ127+AJ129+AJ131 -> 3604.217 | AL133: =AL123+AL125+AL127+AL129+AL131 -> 3584.1406
B134: FCFF for the remainder of the year | Z134: =(Z133-W133-V133)*(1-0.2) -> -653.71728 | AF134: =AF133 -> 1780.1075 | AH134: =AH133 -> 2450.9435 | AJ134: =AJ133 -> 3604.217 | AL134: =AL133 -> 3584.1406
A136: x | B136: Valuation Summary
V137: =V$8 -> 2025 | W137: =X137 -> 0 | X137: =X$8 -> 0 | Y137: =X137 -> 0 | Z137: =X137 -> 0 | AB137: =AB$8 -> 2026 | AC137: =AD137 -> 0 | AD137: =AD$8 -> 0 | AE137: =AD137 -> 0 | AF137: =AD137 -> 0 | AH137: =AH$8 -> 2027 | AJ137: =AJ$8 -> 2028 | AL137: =AL$8 -> 2029
V138: Q1 | W138: Q2 | X138: Q3 | Y138: Q4 | Z138: FY | AB138: Q1 | AC138: Q2 | AD138: Q3 | AE138: Q4 | AF138: FY | AH138: FY | AJ138: FY | AL138: FY
B141: Discounted Cash Flows (DCF)
B144: Discount Period | X144: =YEARFRAC(TODAY(),Inputs!$D$18+92) -> 0.080555556 | Z144: =YEARFRAC(TODAY(),"2025-12-31") -> 0.18611111
B145: Mid-Quarter/Year Convention Discount Period | X145: 0.13 | Z145: =0.26/2 -> 0.13 | AF145: =Z145+1 -> 1.13 | AH145: 2.13 | AJ145: 3.13 | AL145: 4.13
B147: Rolling WACC (Weighted Average Cost of Capital) | X147: =WACC!$D$39+Sensitivity!U41 -> 0.17581593 | Z147: =WACC!D39 -> 0.17581593 | AF147: =WACC!E39 -> 0.19872845 | AH147: =WACC!F39 -> 0.16326349 | AJ147: =WACC!G39 -> 0.16521357 | AL147: =WACC!H39 -> 0.2073521
B148: Cumulative Discount Factor | Z148: =(1+WACC!D39)^Z145 -> 1.0212783 | AF148: =Z148*((1+AF147)^AF145) -> 1.2534258 | AH148: =AF148*(1+AH147)^AH145 -> 1.7297884 | AJ148: =AH148*(1+AJ147)^AJ145 -> 2.79153 | AL148: =AJ148*(1+AL147)^AL145 -> 6.0787808
B150: Present Value of FCFF | X150: =X133/X148*(Inputs!$D$17-92-TODAY())/92 -> #DIV/0! | Y150: =Y133/Y148 -> #DIV/0! | Z150: =Z133/Z148 -> 224.12981 | AB150: =AB133/AB148 -> #DIV/0! | AC150: =AC133/AC148 -> #DIV/0! | AD150: =AD133/AD148 -> #DIV/0! | AE150: =AE133/AE148 -> #DIV/0! | AF150: =AF133/AF148 -> 1420.1938 | AH150: =AH133/AH148 -> 1416.9037 | AJ150: =AJ133/AJ148 -> 1291.126 | AL150: =AL133/AL148 -> 589.61503
B152: Terminal Value
Q155: Preferred Method: | R155: Revenue Exit | V155: EBITDA Exit Multiple | AB155: Revenue Exit Multiple | AH155: Gordon's Growth Model
V157: Current EV/EBITDA | Z157: =Inputs!M14 -> 9.3917402 | AB157: Current EV/Sales | AF157: =Inputs!M13 -> 0.83767408 | AH157: Current Growth Rate | AL157: =AL133/AJ133-1 -> -0.0055702622
V158: Exit EV/EBITDA | Z158: 3.2 | AB158: Exit EV/Sales | AF158: 0.9 | AH158: Terminal Growth Rate | AL158: 0.02
R159: =R155 -> Revenue Exit | V159: Terminal Value | Z159: =(Z158+Sensitivity!U43)*(AL119+AL125) -> 17238.505 | AB159: Terminal Value | AF159: =(AF158+Sensitivity!U44)*(AL26) -> 19056.956 | AH159: Terminal Value | AL159: =AL133*(1+AL158+Sensitivity!U42)/(AL147-AL158-Sensitivity!U42) -> 19513.116
R160: =IF($R$159="Revenue Exit",$AF$169,IF($R$159="EBITDA Exit",$Z$169,$AL$169)) -> -0.24468162 | V160: PV of Terminal Value | Z160: =Z159/AL148 -> 2835.849 | AB160: PV of Terminal Value | AF160: =AF159/AL148 -> 3134.9963 | AH160: PV of Terminal Value | AL160: =AL159/AL148 -> 3210.0378
R161: =1-R160 -> 1.2446816 | V161: Implied Enterprise Value | Z161: =Z160+Z150+AF150+AH150+AJ150+AL150 -> 7777.8173 | AB161: Implied Enterprise Value | AF161: =AF160+AF150+AH150+AJ150+Z150+AL150 -> 8076.9646 | AH161: Implied Enterprise Value | AL161: =AL160+AL150+AJ150+AH150+AF150+Z150 -> 8152.0061
R162: =IF(R160>0,"Upside","Downside") -> Downside | V162: (-) Net Debt | Z162: =BS!AI45+BS!AI44+BS!AI39+BS!AI38-BS!AI15 -> 3018.617 | AB162: (-) Net Debt | AF162: =BS!AI45+BS!AI44+BS!AI39+BS!AI38-BS!AI15 -> 3018.617 | AH162: (-) Net Debt | AL162: =BS!AI45+BS!AI44+BS!AI39+BS!AI38-BS!AI15 -> 3018.617
V163: (-) Preferred Stock Market Cap | Z163: =Inputs!U63 -> 0 | AB163: (-) Preferred Stock Market Cap | AF163: =Inputs!U63 -> 0 | AH163: (-) Preferred Stock Market Cap | AL163: =Inputs!U63 -> 0
...

Sheet LBO
A7: x | B7: Key Assumptions
B10: Entry | G10: Capital Structure | J10: Interest | K10: Weight | L10: Amount
B11: LTM EBITDA | E11: =(G86+G77) -> 1045.4 | G11: Revolver | L11: =K11*$E$13 -> 0
B12: Entry Multiple | G12: Bank Loan | L12: =K12*$E$13 -> 0
B13: Enterprise Value | E13: =E11*E12 -> 0 | G13: Senior Notes | L13: =K13*$E$13 -> 0
B14: Existing Net Debt | E14: =BS!AJ38+BS!AJ39+BS!AJ44+BS!AJ45-BS!AJ15 -> 0
B15: Equity Value | E15: =E13-E14 -> 0 | G15: IRR (For reference)
G16: MOIC | L16: =L180 -> #DIV/0!
B17: Fees & Expenses | E17: =0.03*E13 -> 0 | G17: IRR | L17: =L181 -> #DIV/0!
B19: Exit
B20: Exit Multiple
A22: x | B22: Sources & Uses
B25: Sources | G25: Uses
C26: Amount | D26: xEBITDA | E26: % Capital | J26: Amount | K26: xEBITDA | L26: % Capital
B27: Revolver | C27: =L11 -> 0 | D27: =C27/$E$11 -> 0 | E27: =C27/$C$34 -> #DIV/0! | G27: Debt Refinancing | J27: =E14 -> 0 | K27: =J27/$E$11 -> 0 | L27: =J27/$J$34 -> #DIV/0!
B28: Bank Loan | C28: =L12 -> 0 | D28: =C28/$E$11 -> 0 | E28: =C28/$C$34 -> #DIV/0! | G28: Equity Payments | J28: =E15 -> 0 | K28: =J28/$E$11 -> 0 | L28: =J28/$J$34 -> #DIV/0!
B29: Senior Notes | C29: =L13 -> 0 | D29: =C29/$E$11 -> 0 | E29: =C29/$C$34 -> #DIV/0!
B30: Total | C30: =SUM(C27:C29) -> 0 | D30: =C30/$E$11 -> 0 | E30: =C30/$C$34 -> #DIV/0! | G30: Fees & Expenses | J30: =E17 -> 0 | K30: =J30/$E$11 -> 0 | L30: =J30/$J$34 -> #DIV/0!
B32: Sponsor Equity | C32: =C34-C30 -> 0 | D32: =C32/$E$11 -> 0 | E32: =C32/$C$34 -> #DIV/0!
B34: Total Sources | C34: =J34 -> 0 | D34: =C34/$E$11 -> 0 | E34: =C34/$C$34 -> #DIV/0! | G34: Total Uses | J34: =J27+J28+J30 -> 0 | K34: =J34/$E$11 -> 0 | L34: =J34/$J$34 -> #DIV/0!
B36: Market Assumptions
A38: x | E38: 2022 | F38: =+E38+1 -> 2023 | G38: =+F38+1 -> 2024 | H38: =+G38+1 -> 2025 | I38: =+H38+1 -> 2026 | J38: =+I38+1 -> 2027 | K38: =+J38+1 -> 2028 | L38: =+K38+1 -> 2029
B50: Sales | H50: 350000 | I50: 352000 | J50: 350000 | K50: 352000 | L50: 350000
B52: Operating Assumptions
A57: x | B57: Income Statement | E57: 2022 | F57: =+E57+1 -> 2023 | G57: =+F57+1 -> 2024 | H57: =+G57+1 -> 2025 | I57: =+H57+1 -> 2026 | J57: =+I57+1 -> 2027 | K57: =+J57+1 -> 2028 | L57: =+K57+1 -> 2029
B59: Revenue | D59: =+_xlfn.XLOOKUP($B59,#REF!,#REF!) -> #REF! | E59: =FCFF!H26 -> 10880.264 | F59: =FCFF!N26 -> 12773.6 | G59: =FCFF!T26 -> 14156.2 | H59: =+H50 -> 350000 | I59: =+I50 -> 352000 | J59: =+J50 -> 350000 | K59: =+K50 -> 352000 | L59: =+L50 -> 350000
B60: % of growth | E60: =E59/IS!N18-1 -> 2.7212407 | F60: =F59/E59-1 -> 0.17401563 | G60: =G59/F59-1 -> 0.10823887 | H60: =H59/G59-1 -> 23.724149 | I60: =I59/H59-1 -> 0.0057142857 | J60: =J59/I59-1 -> -0.0056818182 | K60: =K59/J59-1 -> 0.0057142857 | L60: =L59/K59-1 -> -0.0056818182
B62: Cost of Goods & Services | E62: =FCFF!H31 -> 1950 | F62: =FCFF!N31 -> 2217.7 | G62: =FCFF!T31 -> 3914.7 | H62: =H63*H$59 -> 0 | I62: =I63*I$59 -> 0 | J62: =J63*J$59 -> 0 | K62: =K63*K$59 -> 0 | L62: =L63*L$59 -> 0
B63: % of sales | E63: =E62/E59 -> 0.17922359 | F63: =F62/F59 -> 0.1736159 | G63: =G62/G59 -> 0.27653608
B65: COGS Depreciation & Amortization | E65: =FCFF!H34 -> 0 | F65: =FCFF!N34 -> 0 | G65: =FCFF!T34 -> 0 | H65: =+H66*H62 -> 0 | I65: =+I66*I62 -> 0 | J65: =+J66*J62 -> 0 | K65: =+K66*K62 -> 0 | L65: =+L66*L62 -> 0
B66: % of cost of goods & services | E66: =E65/E62 -> 0 | F66: =F65/F62 -> 0 | G66: =G65/G62 -> 0
B68: Gross Profit | E68: =FCFF!H37 -> 2283.7 | F68: =FCFF!N37 -> 2629.1 | G68: =FCFF!T37 -> 4465.1 | H68: =+H59-H62-H65 -> 350000 | I68: =+I59-I62-I65 -> 352000 | J68: =+J59-J62-J65 -> 350000 | K68: =+K59-K62-K65 -> 352000 | L68: =+L59-L62-L65 -> 350000
B69: % of sales | E69: =E68/E59 -> 0.2098938 | F69: =F68/F59 -> 0.20582295 | G69: =G68/G59 -> 0.31541657 | H69: =IFERROR(H68/H$59,"") -> 1 | I69: =IFERROR(I68/I$59,"") -> 1 | J69: =IFERROR(J68/J$59,"") -> 1 | K69: =IFERROR(K68/K$59,"") -> 1 | L69: =IFERROR(L68/L$59,"") -> 1
B71: SG&A (Selling, General & Administrative) | E71: =FCFF!H40 -> 1819 | F71: =FCFF!N40 -> 2109.2 | G71: =FCFF!T40 -> 3883.8 | H71: =+H72*H59 -> 0 | I71: =+I72*I59 -> 0 | J71: =+J72*J59 -> 0 | K71: =+K72*K59 -> 0 | L71: =+L72*L59 -> 0
B72: % of sales | E72: =E71/E59 -> 0.16718344 | F72: =F71/F59 -> 0.16512181 | G72: =G71/G59 -> 0.27435329
B74: R&D (Research & Development) | E74: =FCFF!H43 -> 0 | F74: =FCFF!N43 -> 0 | G74: =FCFF!T43 -> 0 | H74: =+H75*H68 -> 0 | I74: =+I75*I68 -> 0 | J74: =+J75*J68 -> 0 | K74: =+K75*K68 -> 0 | L74: =+L75*L68 -> 0
B75: % of gross profit | E75: =E74/E68 -> 0 | F75: =F74/F68 -> 0 | G75: =G74/G68 -> 0
B77: D&A (Depreciation & Amortization) | E77: =FCFF!H46 -> 166 | F77: =FCFF!N46 -> 223 | G77: =FCFF!T46 -> 414.8 | H77: =+H80+H83 -> 0 | I77: =+I80+I83 -> 0 | J77: =+J80+J83 -> 0 | K77: =+K80+K83 -> 0 | L77: =+L80+L83 -> 0
B78: % of net pp&e and intangibles excl. Goodwill | E78: =E77/(E111+E114) -> 0.084910747 | F78: =F77/(F111+F114) -> 0.090915206 | G78: =G77/(G111+G114) -> 0.068559014 | H78: =H77/(H111+H114) -> 0 | I78: =I77/(I111+I114) -> 0 | J78: =J77/(J111+J114) -> 0 | K78: =K77/(K111+K114) -> 0 | L78: =L77/(L111+L114) -> 0
B80: Depreciation | E80: =FCFF!H49 -> 135.7 | F80: =FCFF!N49 -> 176.3 | G80: =FCFF!T49 -> 288.3 | H80: =H81*G111 -> 0 | I80: =I81*H111 -> 0 | J80: =J81*I111 -> 0 | K80: =K81*J111 -> 0 | L80: =L81*K111 -> 0
B81: % of net pp&e | E81: =E80/E111 -> 0.19621679 | F81: =FCFF!N50 -> 0.19788333 | G81: =FCFF!T50 -> 0.12486417
B83: Amortization | E83: =FCFF!H52 -> 30.3 | F83: =FCFF!N52 -> 46.7 | G83: =FCFF!T52 -> 126.5 | H83: =H84*G114 -> 0 | I83: =I84*H114 -> 0 | J83: =J84*I114 -> 0 | K83: =K84*J114 -> 0 | L83: =L84*K114 -> 0
B84: % of intangibles excl. goodwill | E84: =E83/E114 -> 0.023982675 | F84: =F83/F114 -> 0.029899367 | G84: =G83/G114 -> 0.033811298
B86: EBIT (Operating Income) | E86: =FCFF!H58 -> 569.7 | F86: =FCFF!N58 -> 587.9 | G86: =FCFF!T58 -> 630.6 | H86: =H68-H71-H74-H77 -> 350000 | I86: =I68-I71-I74-I77 -> 352000 | J86: =J68-J71-J74-J77 -> 350000 | K86: =K68-K71-K74-K77 -> 352000 | L86: =L68-L71-L74-L77 -> 350000
B87: % of sales | E87: =E86/E59 -> 0.052360862 | F87: =F86/F59 -> 0.046024613 | G87: =G86/G59 -> 0.044545853 | H87: =H86/H59 -> 1 | I87: =I86/I59 -> 1 | J87: =J86/J59 -> 1 | K87: =K86/K59 -> 1 | L87: =L86/L59 -> 1
B89: Net Interest (Income) Expense | E89: =IS!T38 -> -2.709 | F89: =IS!Z38 -> 77.554 | G89: =IS!AF38 -> 151.218 | H89: =+H164 -> 0 | I89: =+I164 -> 0 | J89: =+J164 -> 0 | K89: =+K164 -> 0 | L89: =+L164 -> 0
B91: Pre-tax income | E91: =IS!T42 -> 489.4 | F91: =IS!Z42 -> 399.651 | G91: =IS!AF42 -> 229.322 | H91: =+H86-H89 -> 350000 | I91: =+I86-I89 -> 352000 | J91: =+J86-J89 -> 350000 | K91: =+K86-K89 -> 352000 | L91: =+L86-L89 -> 350000
B92: % of sales | E92: =E91/E59 -> 0.044980526 | F92: =F91/F59 -> 0.031287264 | G92: =G91/G59 -> 0.016199404 | H92: =H91/H59 -> 1 | I92: =I91/I59 -> 1 | J92: =J91/J59 -> 1 | K92: =K91/K59 -> 1 | L92: =L91/L59 -> 1
B94: Income tax expenses (benefits) | E94: =IS!T45 -> 55.9529 | F94: =IS!Z45 -> -14.6706 | G94: =IS!AF45 -> -267.2178 | H94: =H95*H91 -> 0 | I94: =I95*I91 -> 0 | J94: =J95*J91 -> 0 | K94: =K95*K91 -> 0 | L94: =L95*L91 -> 0
B95: % tax rate | E95: =E94/E91 -> 0.11432959 | F95: =F94/F91 -> -0.036708528 | G95: =G94/G91 -> -1.1652515
B97: Net income | E97: =IS!T47 -> 433.4471 | F97: =IS!Z47 -> 414.3216 | G97: =IS!AF47 -> 496.5398 | H97: =H91-H94 -> 350000 | I97: =I91-I94 -> 352000 | J97: =J91-J94 -> 350000 | K97: =K91-K94 -> 352000 | L97: =L91-L94 -> 350000
B98: % of sales | E98: =E97/E59 -> 0.039837921 | F98: =F97/F59 -> 0.032435774 | G98: =G97/G59 -> 0.035075783 | H98: =H97/H59 -> 1 | I98: =I97/I59 -> 1 | J98: =J97/J59 -> 1 | K98: =K97/K59 -> 1 | L98: =L97/L59 -> 1
A100: x | B100: Balance Sheet | E100: =E57 -> 2022 | F100: =F57 -> 2023 | G100: =G57 -> 2024 | H100: =H57 -> 2025 | I100: =I57 -> 2026 | J100: =J57 -> 2027 | K100: =K57 -> 2028 | L100: =L57 -> 2029
B102: Accounts Receivable | E102: =FCFF!H67 -> 867.582 | F102: =FCFF!N67 -> 1125.449 | G102: =FCFF!T67 -> 2816.294 | H102: =+H103*H59/365 -> 0 | I102: =+I103*I59/365 -> 0 | J102: =+J103*J59/365 -> 0 | K102: =+K103*K59/366 -> 0 | L102: =+L103*L59/365 -> 0
B103: days sales outstanding | E103: =FCFF!H68 -> 29.104756 | F103: =FCFF!N68 -> 32.15921 | G103: =FCFF!T68 -> 72.614636
B105: Inventory | E105: =FCFF!H70 -> 772.06 | F105: =FCFF!N70 -> 828.557 | G105: =FCFF!T70 -> 2218.815 | H105: =+H106*H62/365 -> 0 | I105: =+I106*I62/365 -> 0 | J105: =+J106*J62/365 -> 0 | K105: =+K106*K62/366 -> 0 | L105: =+L106*L62/365 -> 0
B106: days inventory held | E106: =FCFF!H71 -> 144.51379 | F106: =FCFF!N71 -> 136.368 | G106: =FCFF!T71 -> 206.87855
B108: Prepaid expenses and Other Current Assets | E108: =FCFF!H73 -> 267.369 | F108: =FCFF!N73 -> 211.334 | G108: =FCFF!T73 -> 1022.031 | H108: =+H109*H59 -> 0 | I108: =+I109*I59 -> 0 | J108: =+J109*J59 -> 0 | K108: =+K109*K59 -> 0 | L108: =+L109*L59 -> 0
B109: % of sales | E109: =FCFF!H74 -> 0.02457376 | F109: =FCFF!N74 -> 0.016544592 | G109: =FCFF!T74 -> 0.072196705
B111: Net PP&E (Property, Plant and Equipment) | E111: =FCFF!H76 -> 691.582 | F111: =FCFF!N76 -> 890.929 | G111: =FCFF!T76 -> 2308.909 | H111: =+G111-H112*H131-H80-H65 -> 2308.909 | I111: =+H111-I112*I131-I80-I65 -> 2308.909 | J111: =+I111-J112*J131-J80-J65 -> 2308.909 | K111: =+J111-K112*K131-K80-K65 -> 2308.909 | L111: =+K111-L112*L131-L80-L65 -> 2308.909
B112: capex allocation rate | E112: =FCFF!H77 -> 0 | F112: =FCFF!N77 -> 0 | G112: =FCFF!T77 -> 0
B114: Intangibles excl. Goodwill | E114: =FCFF!H79 -> 1263.412 | F114: =FCFF!N79 -> 1561.906 | G114: =FCFF!T79 -> 3741.353 | H114: =+G114+H115*H74-(1-H112)*H131-H83 -> 3741.353 | I114: =+H114+I115*I74-(1-I112)*I131-I83 -> 3741.353 | J114: =+I114+J115*J74-(1-J112)*J131-J83 -> 3741.353 | K114: =+J114+K115*K74-(1-K112)*K131-K83 -> 3741.353 | L114: =+K114+L115*L74-(1-L112)*L131-L83 -> 3741.353
B115: r&d conversion rate | E115: =FCFF!H80 -> 0 | F115: =FCFF!N80 -> 0 | G115: =FCFF!T80 -> 0
B117: Accounts Payable | E117: =FCFF!H82 -> 1064.289 | F117: =FCFF!N82 -> 1041.509 | G117: =FCFF!T82 -> 2794.703 | H117: =+H118*H62/365 -> 0 | I117: =+I118*I62/365 -> 0 | J117: =+J118*J62/365 -> 0 | K117: =+K118*K62/366 -> 0 | L117: =+L118*L62/365 -> 0
B118: days payable outstanding | E118: =FCFF!H83 -> 199.21307 | F118: =FCFF!N83 -> 171.41669 | G118: =FCFF!T83 -> 260.57338
B120: Accrued Expenses and Other Current Liabilities | E120: =FCFF!H85 -> 89.169 | F120: =FCFF!N85 -> 260.898 | G120: =FCFF!T85 -> 32.755 | H120: =+H121*H71 -> 0 | I120: =+I121*I71 -> 0 | J120: =+J121*J71 -> 0 | K120: =+K121*K71 -> 0 | L120: =+L121*L71 -> 0
B121: % of sg&a | E121: =FCFF!H86 -> 0.049020891 | F121: =FCFF!N86 -> 0.12369524 | G121: =FCFF!T86 -> 0.0084337505
A123: x | B123: Cash Flow | E123: =E57 -> 2022 | F123: =F57 -> 2023 | G123: =G57 -> 2024 | H123: =H57 -> 2025 | I123: =I57 -> 2026 | J123: =J57 -> 2027 | K123: =K57 -> 2028 | L123: =L57 -> 2029
B125: D&A (Depreciation & Amortization) | E125: =FCFF!H91 -> 166.03 | F125: =FCFF!N91 -> 222.944 | G125: =FCFF!T91 -> 414.855 | H125: =+H77+H65 -> 0 | I125: =+I77+I65 -> 0 | J125: =+J77+J65 -> 0 | K125: =+K77+K65 -> 0 | L125: =+L77+L65 -> 0
B126: % of net pp&e and intangibles excl. Goodwill | E126: =FCFF!H92 -> 0.084926092 | F126: =FCFF!N92 -> 0.090892376 | G126: =FCFF!T92 -> 0.068568105 | H126: =+H125/(H111+H114) -> 0 | I126: =+I125/(I111+I114) -> 0 | J126: =+J125/(J111+J114) -> 0 | K126: =+K125/(K111+K114) -> 0 | L126: =+L125/(L111+L114) -> 0
B128: Changes in Net Working Capital | E128: =FCFF!H100 -> -331.666 | F128: =FCFF!N100 -> -97.766 | G128: =FCFF!T100 -> -536.6 | H128: =-((H102+H105+H108-H117-H120)-(G102+G105+G108-G117-G120)) -> 3229.682 | I128: =-((I102+I105+I108-I117-I120)-(H102+H105+H108-H117-H120)) -> 0 | J128: =-((J102+J105+J108-J117-J120)-(I102+I105+I108-I117-I120)) -> 0 | K128: =-((K102+K105+K108-K117-K120)-(J102+J105+J108-J117-J120)) -> 0 | L128: =-((L102+L105+L108-L117-L120)-(K102+K105+K108-K117-K120)) -> 0
B129: % of change in sales | E129: =FCFF!H101 -> -0.11343558 | F129: =FCFF!N101 -> -0.023092189 | G129: =FCFF!T101 -> -0.11071295 | H129: =H128/(H59-G59) -> 0.0096166194 | I129: =I128/(I59-H59) -> 0 | J129: =J128/(J59-I59) -> 0 | K129: =K128/(K59-J59) -> 0 | L129: =L128/(L59-K59) -> 0
B131: Net CapEx | E131: =FCFF!H103+FCFF!H106 -> -233.143 | F131: =FCFF!N103+FCFF!N106 -> -235.201 | G131: =FCFF!T103+FCFF!T106 -> -418.962 | H131: =-H132*H59 -> 0 | I131: =-I132*I59 -> 0 | J131: =-J132*J59 -> 0 | K131: =-K132*K59 -> 0 | L131: =-L132*L59 -> 0
B132: % of sales | E132: =FCFF!H104 -> 0.05506838 | F132: =FCFF!N104 -> 0.048527069 | G132: =FCFF!T104 -> 0.049996659
A134: x | B134: Levered Free Cash Flow | H134: =H57 -> 2025 | I134: =I57 -> 2026 | J134: =J57 -> 2027 | K134: =K57 -> 2028 | L134: =L57 -> 2029
B136: Net Income | H136: =H97 -> 350000 | I136: =I97 -> 352000 | J136: =J97 -> 350000 | K136: =K97 -> 352000 | L136: =L97 -> 350000
B137: Changes in NWC | H137: =+H125 -> 0 | I137: =+I125 -> 0 | J137: =+J125 -> 0 | K137: =+K125 -> 0 | L137: =+L125 -> 0
B138: D&A (Depreciation & Amortization) | H138: =+H128 -> 3229.682 | I138: =+I128 -> 0 | J138: =+J128 -> 0 | K138: =+K128 -> 0 | L138: =+L128 -> 0
B139: Net CapEx | H139: =+H131 -> 0 | I139: =+I131 -> 0 | J139: =+J131 -> 0 | K139: =+K131 -> 0 | L139: =+L131 -> 0
B140: Leveraged Free Cash Flow | H140: =H136+H137+H138+H139 -> 353229.68 | I140: =I136+I137+I138+I139 -> 352000 | J140: =J136+J137+J138+J139 -> 350000 | K140: =K136+K137+K138+K139 -> 352000 | L140: =L136+L137+L138+L139 -> 350000
A142: x | B142: Debt Schedule | H142: =H134 -> 2025 | I142: =I134 -> 2026 | J142: =J134 -> 2027 | K142: =K134 -> 2028 | L142: =L134 -> 2029
B144: Revolver
B145: Beginning Balance | H145: =G148 -> 0 | I145: =H148 -> 0 | J145: =I148 -> 0 | K145: =J148 -> 0 | L145: =K148 -> 0
B146: Interest | H146: =H145*$J$11 -> 0 | I146: =I145*$J$11 -> 0 | J146: =J145*$J$11 -> 0 | K146: =K145*$J$11 -> 0 | L146: =L145*$J$11 -> 0
B147: Paydown | H147: =MIN(H140,H145) -> 0 | I147: =MIN(I140,I145) -> 0 | J147: =MIN(J140,J145) -> 0 | K147: =MIN(K140,K145) -> 0 | L147: =MIN(L140,L145) -> 0
B148: Ending Balance | G148: =L11 -> 0 | H148: =H145-H147 -> 0 | I148: =I145-I147 -> 0 | J148: =J145-J147 -> 0 | K148: =K145-K147 -> 0 | L148: =L145-L147 -> 0
B150: Bank Loan
B151: Beginning Balance | H151: =G154 -> 0 | I151: =H154 -> 0 | J151: =I154 -> 0 | K151: =J154 -> 0 | L151: =K154 -> 0
B152: Interest | H152: =H151*$J$12 -> 0 | I152: =I151*$J$12 -> 0 | J152: =J151*$J$12 -> 0 | K152: =K151*$J$12 -> 0 | L152: =L151*$J$12 -> 0
B153: Paydown | H153: =MIN(H151,H140-H147) -> 0 | I153: =MIN(I151,I140-I147) -> 0 | J153: =MIN(J151,J140-J147) -> 0 | K153: =MIN(K151,K140-K147) -> 0 | L153: =MIN(L151,L140-L147) -> 0
B154: Ending Balance | G154: =L12 -> 0 | H154: =H151-H153 -> 0 | I154: =I151-I153 -> 0 | J154: =J151-J153 -> 0 | K154: =K151-K153 -> 0 | L154: =L151-L153 -> 0
B156: Senior Note
B157: Beginning Balance | H157: =G160 -> 0 | I157: =H160 -> 0 | J157: =I160 -> 0 | K157: =J160 -> 0 | L157: =K160 -> 0
B158: Interest | H158: =H157*$J$13 -> 0 | I158: =I157*$J$13 -> 0 | J158: =J157*$J$13 -> 0 | K158: =K157*$J$13 -> 0 | L158: =L157*$J$13 -> 0
B159: Paydown | H159: =MIN(H157,H140-H147-H153) -> 0 | I159: =MIN(I157,I140-I147-I153) -> 0 | J159: =MIN(J157,J140-J147-J153) -> 0 | K159: =MIN(K157,K140-K147-K153) -> 0 | L159: =MIN(L157,L140-L147-L153) -> 0
B160: Ending Balance | G160: =L13 -> 0 | H160: =H157-H159 -> 0 | I160: =I157-I159 -> 0 | J160: =J157-J159 -> 0 | K160: =K157-K159 -> 0 | L160: =L157-L159 -> 0
B162: Total Debt
B163: Beginning Balance | H163: =H145+H151+H157 -> 0 | I163: =I145+I151+I157 -> 0 | J163: =J145+J151+J157 -> 0 | K163: =K145+K151+K157 -> 0 | L163: =L145+L151+L157 -> 0
B164: Interest | H164: =H146+H152+H158 -> 0 | I164: =I146+I152+I158 -> 0 | J164: =J146+J152+J158 -> 0 | K164: =K146+K152+K158 -> 0 | L164: =L146+L152+L158 -> 0
B165: Paydown | H165: =H147+H153+H159 -> 0 | I165: =I147+I153+I159 -> 0 | J165: =J147+J153+J159 -> 0 | K165: =K147+K153+K159 -> 0 | L165: =L147+L153+L159 -> 0
...

Sheet Sensitivity
B7: Monte-Carlo Simulations | R7: Tornado Chart – Effect on Price Target
AD28: {=_xlfn.SORTBY(R38:Z44,Z38:Z44,1)} -> Capex Intensity | AE28: 0 | AF28: 0.01 | AG28: 0 | AH28: 24.28 | AI28: 24.4 | AJ28: -0.06 | AK28: 0.06 | AL28: 0.06
AD29: Terminal g | AE29: 0 | AF29: 0.005 | AG29: 0 | AH29: 24 | AI29: 25 | AJ29: -0.34 | AK29: 0.66 | AL29: 0.66
AD30: SG&A Margin | AE30: 0 | AF30: 0.01 | AG30: 0 | AH30: 23.25 | AI30: 25.44 | AJ30: -1.09 | AK30: 1.1 | AL30: 1.1
AD31: WACC | AE31: 0 | AF31: 0.005 | AG31: 0 | AH31: 23.25 | AI31: 25.48 | AJ31: -1.09 | AK31: 1.14 | AL31: 1.14
R32: Reference Price Target | V32: Base Price Target | Z32: Reference | AD32: COGS Margin | AE32: 0 | AF32: 0.02 | AG32: 0 | AH32: 22.4 | AI32: 26.31 | AJ32: -1.94 | AK32: 1.97 | AL32: 1.97
R33: Gordon PT | T33: =+FCFF!AL167 -> 24.705058 | V33: Base Gordon PT | X33: 25 | Z33: Revenue | AD33: EBITDA Exit | AE33: 0 | AF33: 1.5 | AG33: 0 | AH33: 16.51 | AI33: 29.3 | AJ33: -7.83 | AK33: 4.96 | AL33: 7.83
E34: Historical VaR | G34: Parametric VaR | I34: Monte Carlos VaR | R34: EBITDA PT | T34: =+FCFF!Z167 -> 22.904229 | V34: Base EBITDA PT | X34: 22.9 | AD34: Revenue Exit | AE34: 0 | AF34: 1 | AG34: 0 | AH34: 7.58 | AI34: 41.11 | AJ34: -16.76 | AK34: 16.77 | AL34: 16.77
B35: Confidence Level 95.0% | R35: Revenue PT | T35: =FCFF!AF167 -> 24.343911 | V35: Base Revenue PT | X35: 24.34
B36: Confidence Level 99.0%
T37: Δ | U37: Δ Applied | V37: PT Low | W37: PT High | X37: Δ Low | Y37: Δ High | Z37: Max
R38: Capex Intensity | T38: 0.01 | V38: 24.28 | W38: 24.4 | X38: {=+V38-_xlfn.IFS($Z$33="EBITDA",$X$34,$Z$33="Revenue",$X$35,$Z$33="Gordon",$X$33)} -> -0.06 | Y38: {=+W38-_xlfn.IFS($Z$33="EBITDA",$X$34,$Z$33="Revenue",$X$35,$Z$33="Gordon",$X$33)} -> 0.06 | Z38: =MAX(ABS(X38),ABS(Y38)) -> 0.06
R39: COGS Margin | T39: 0.02 | V39: 22.4 | W39: 26.31 | X39: {=+V39-_xlfn.IFS($Z$33="EBITDA",$X$34,$Z$33="Revenue",$X$35,$Z$33="Gordon",$X$33)} -> -1.94 | Y39: {=+W39-_xlfn.IFS($Z$33="EBITDA",$X$34,$Z$33="Revenue",$X$35,$Z$33="Gordon",$X$33)} -> 1.97 | Z39: =MAX(ABS(X39),ABS(Y39)) -> 1.97
R40: SG&A Margin | T40: 0.01 | V40: 23.25 | W40: 25.44 | X40: {=+V40-_xlfn.IFS($Z$33="EBITDA",$X$34,$Z$33="Revenue",$X$35,$Z$33="Gordon",$X$33)} -> -1.09 | Y40: {=+W40-_xlfn.IFS($Z$33="EBITDA",$X$34,$Z$33="Revenue",$X$35,$Z$33="Gordon",$X$33)} -> 1.1 | Z40: =MAX(ABS(X40),ABS(Y40)) -> 1.1
R41: WACC | T41: 0.005 | V41: 23.25 | W41: 25.48 | X41: {=+V41-_xlfn.IFS($Z$33="EBITDA",$X$34,$Z$33="Revenue",$X$35,$Z$33="Gordon",$X$33)} -> -1.09 | Y41: {=+W41-_xlfn.IFS($Z$33="EBITDA",$X$34,$Z$33="Revenue",$X$35,$Z$33="Gordon",$X$33)} -> 1.14 | Z41: =MAX(ABS(X41),ABS(Y41)) -> 1.14
R42: Terminal g | T42: 0.005 | V42: 24 | W42: 25 | X42: {=+V42-_xlfn.IFS($Z$33="EBITDA",$X$34,$Z$33="Revenue",$X$35,$Z$33="Gordon",$X$33)} -> -0.34 | Y42: {=+W42-_xlfn.IFS($Z$33="EBITDA",$X$34,$Z$33="Revenue",$X$35,$Z$33="Gordon",$X$33)} -> 0.66 | Z42: =MAX(ABS(X42),ABS(Y42)) -> 0.66
R43: EBITDA Exit | T43: 1.5 | V43: 16.51 | W43: 29.3 | X43: {=+V43-_xlfn.IFS($Z$33="EBITDA",$X$34,$Z$33="Revenue",$X$35,$Z$33="Gordon",$X$33)} -> -7.83 | Y43: {=+W43-_xlfn.IFS($Z$33="EBITDA",$X$34,$Z$33="Revenue",$X$35,$Z$33="Gordon",$X$33)} -> 4.96 | Z43: =MAX(ABS(X43),ABS(Y43)) -> 7.83
R44: Revenue Exit | T44: 1 | V44: 7.58 | W44: 41.11 | X44: {=+V44-_xlfn.IFS($Z$33="EBITDA",$X$34,$Z$33="Revenue",$X$35,$Z$33="Gordon",$X$33)} -> -16.76 | Y44: {=+W44-_xlfn.IFS($Z$33="EBITDA",$X$34,$Z$33="Revenue",$X$35,$Z$33="Gordon",$X$33)} -> 16.77 | Z44: =MAX(ABS(X44),ABS(Y44)) -> 16.77

Sheet IS
B7: Income Statement | D7: 2020 | E7: 2020 | F7: 2020 | G7: 2020 | H7: 2020 | J7: 2021 | K7: 2021 | L7: 2021 | M7: 2021 | N7: 2021 | P7: 2022 | Q7: 2022 | R7: 2022 | S7: 2022 | T7: 2022 | V7: 2023 | W7: 2023 | X7: 2023 | Y7: 2023 | Z7: 2023 | AB7: 2024 | AC7: 2024 | AD7: 2024 | AE7: 2024 | AF7: 2024 | AH7: 2025 | AI7: 2025 | AJ7: 2025 | AK7: 2025 | AL7: 2025 | AN7: 2025 | AO7: 2025 | AP7: 2025 | AQ7: 2025 | AR7: 2025
D8: 2020 | J8: 2021 | P8: 2022 | V8: 2023 | AB8: 2024 | AH8: 2025 | AN8: 2026 | AT8: 2027 | AV8: 2028 | AX8: 2029
D9: Q1 | E9: Q2 | F9: Q3 | G9: Q4 | H9: FY | J9: Q1 | K9: Q2 | L9: Q3 | M9: Q4 | N9: FY | P9: Q1 | Q9: Q2 | R9: Q3 | S9: Q4 | T9: FY | V9: Q1 | W9: Q2 | X9: Q3 | Y9: Q4 | Z9: FY | AB9: Q1 | AC9: Q2 | AD9: Q3 | AE9: Q4 | AF9: FY | AH9: Q1 | AI9: Q2 | AJ9: Q3 | AK9: Q4 | AL9: FY | AN9: Q1 | AO9: Q2 | AP9: Q3 | AQ9: Q4 | AR9: FY | AT9: FY | AV9: FY | AX9: FY
B12: Revenue:
B13: Segment 1
B14: Segment 2
B15: Segment 3
B16: Segment 4
B17: Segment 5
B18: Total revenue | D18: 375.471 | E18: 154.443 | F18: 416.463 | G18: 644.615 | H18: 1590.992 | J18: 499.952 | K18: 552.976 | L18: 777.949 | M18: 1092.95 | N18: 2923.827 | P18: 839.576 | Q18: 944.752 | R18: 1137.985 | S18: 1311.413 | T18: 4233.726 | V18: 1025.291 | W18: 1131.023 | X18: 1265.824 | Y18: 1424.631 | Z18: 4846.768 | AB18: 1072.182 | AC18: 1357.108 | AD18: 2546.621 | AE18: 3403.842 | AF18: 8379.753 | AH18: 2696.538 | AI18: 2901.385
A20: x | B20: Cost of revenue:
B21: Cost of goods and services | D21: 203.099 | E21: 74.283 | F21: 229.976 | G21: 328.421 | H21: 835.779 | J21: 250.027 | K21: 260.004 | L21: 372.864 | M21: 502.252 | N21: 1385.147 | P21: 390.836 | Q21: 416.145 | R21: 536.683 | S21: 606.428 | T21: 1950.092 | V21: 488.467 | W21: 516.509 | X21: 585.097 | Y21: 627.634 | Z21: 2217.707 | AB21: 505.325 | AC21: 681.46 | AD21: 1152.465 | AE21: 1575.442 | AF21: 3914.692 | AH21: 1219.737 | AI21: 1280.918
B22: Depreciation & amortization | D22: 0 | E22: 0 | F22: 0 | G22: 0 | H22: 0 | J22: 0 | K22: 0 | L22: 0 | M22: 0 | N22: 0 | P22: 0 | Q22: 0 | R22: 0 | S22: 0 | T22: 0 | V22: 0 | W22: 0 | X22: 0 | Y22: 0 | Z22: 0 | AB22: 0 | AC22: 0 | AD22: 0 | AE22: 0 | AF22: 0 | AH22: 0 | AI22: 0
B23: Total cost of revenue | D23: 203.099 | E23: 74.283 | F23: 229.976 | G23: 328.421 | H23: 835.779 | J23: 250.027 | K23: 260.004 | L23: 372.864 | M23: 502.252 | N23: 1385.147 | P23: 390.836 | Q23: 416.145 | R23: 536.683 | S23: 606.428 | T23: 1950.092 | V23: 488.467 | W23: 516.509 | X23: 585.097 | Y23: 627.634 | Z23: 2217.707 | AB23: 505.325 | AC23: 681.46 | AD23: 1152.465 | AE23: 1575.442 | AF23: 3914.692 | AH23: 1219.737 | AI23: 1280.918
B24: Gross margin | D24: 172.372 | E24: 80.16 | F24: 186.487 | G24: 316.194 | H24: 755.213 | J24: 249.925 | K24: 292.972 | L24: 405.085 | M24: 590.698 | N24: 1538.68 | P24: 448.74 | Q24: 528.607 | R24: 601.302 | S24: 704.985 | T24: 2283.634 | V24: 536.824 | W24: 614.514 | X24: 680.727 | Y24: 796.997 | Z24: 2629.061 | AB24: 566.857 | AC24: 675.648 | AD24: 1394.156 | AE24: 1828.4 | AF24: 4465.061 | AH24: 1476.801 | AI24: 1620.467
A26: x | B26: Operating expenses:
B27: Selling, general and administrative | D27: 156.481 | E27: 170.814 | F27: 142.031 | G27: 224.166 | H27: 692.187 | J27: 209.062 | K27: 244.535 | L27: 304.512 | M27: 442.519 | N27: 1200.628 | P27: 362.897 | Q27: 407.017 | R27: 473.028 | S27: 576.669 | T27: 1819.611 | V27: 430.274 | W27: 489.857 | X27: 535.335 | Y27: 653.739 | Z27: 2109.204 | AB27: 461.481 | AC27: 545.871 | AD27: 1201.009 | AE27: 1675.429 | AF27: 3883.79 | AH27: 1236.688 | AI27: 1268.066
B28: Depreciation and amortization | D28: 0 | E28: 0 | F28: 0 | G28: 0 | H28: 0 | J28: 0 | K28: 0 | L28: 0 | M28: 0 | N28: 0 | P28: 0 | Q28: 0 | R28: 0 | S28: 0 | T28: 0 | V28: 0 | W28: 0 | X28: 0 | Y28: 0 | Z28: 0 | AB28: 0 | AC28: 0 | AD28: 0 | AE28: 0 | AF28: 0 | AH28: 0 | AI28: 0
B29: Research and development | D29: 5.954 | E29: 7.323 | F29: 4.89 | G29: 0 | H29: 0 | J29: 6.646 | K29: 1.655 | L29: 62.738 | M29: 0 | N29: 0 | P29: 0 | Q29: 0 | R29: 0 | S29: 0 | T29: 0 | V29: 0 | W29: 0 | X29: 0 | Y29: 0 | Z29: 0 | AB29: 0 | AC29: 0 | AD29: 0 | AE29: 0 | AF29: 0 | AH29: 0 | AI29: 0
B30: Other operating expenses | D30: -7.713 | E30: -25.467 | F30: -5.257 | G30: 27.19 | H30: 6.406 | J30: -6.55 | K30: -1.518 | L30: -54.757 | M30: 24.437 | N30: 161.17 | P30: 3.516 | Q30: 69.023 | R30: 6.778 | S30: -76.971 | T30: 2.346 | V30: -1.685 | W30: -0.027 | X30: 1.02 | Y30: 6.081 | Z30: 5.388 | AB30: -2.036 | AC30: -6.232 | AD30: 186.774 | AE30: -42.154 | AF30: 7.547 | AH30: 14.566 | AI30: 8.369
B31: Total operating expenses | D31: 154.722 | E31: 152.67 | F31: 141.664 | G31: 251.356 | H31: 698.593 | J31: 209.158 | K31: 244.672 | L31: 312.493 | M31: 466.956 | N31: 1361.798 | P31: 366.413 | Q31: 476.04 | R31: 479.806 | S31: 499.698 | T31: 1821.957 | V31: 428.589 | W31: 489.83 | X31: 536.355 | Y31: 659.82 | Z31: 2114.592 | AB31: 459.445 | AC31: 539.639 | AD31: 1387.783 | AE31: 1633.275 | AF31: 3891.337 | AH31: 1251.254 | AI31: 1276.435
B32: Other operating income | D32: 28.127 | E32: 0 | F32: 0 | G32: 29.893 | H32: 56.201 | J32: 0.238 | K32: 140.535 | L32: 0 | M32: 3.005 | N32: 146.163 | P32: 78.87 | Q32: 4.972 | R32: 5.721 | S32: 15.418 | T32: 104.981 | V32: 8.745 | W32: 6.236 | X32: 34.926 | Y32: 18.118 | Z32: 68.025 | AB32: 3.432 | AC32: 7.72 | AD32: 181.092 | AE32: 0 | AF32: 49.295 | AH32: 54.79 | AI32: 23.072
B33: Operating income | D33: 45.777 | E33: -72.51 | F33: 44.823 | G33: 94.731 | H33: 112.821 | J33: 41.005 | K33: 188.835 | L33: 92.592 | M33: 126.747 | N33: 323.045 | P33: 161.197 | Q33: 57.539 | R33: 127.217 | S33: 220.705 | T33: 566.658 | V33: 116.98 | W33: 130.92 | X33: 179.298 | Y33: 155.295 | Z33: 582.494 | AB33: 110.844 | AC33: 143.729 | AD33: 187.465 | AE33: 195.125 | AF33: 623.019 | AH33: 280.337 | AI33: 367.104
A35: x | B35: Non-operating (income) loss:
B36: Interest expense | D36: 5.388 | E36: 8.821 | F36: 7.536 | G36: 1.745 | H36: 23.49 | J36: 8.36 | K36: 9.031 | L36: 9.81 | M36: 13.399 | N36: 40.6 | P36: 8.636 | Q36: 11.612 | R36: 11.903 | S36: 30.221 | T36: 62.372 | V36: 31.955 | W36: 33.417 | X36: 39.577 | Y36: 37.796 | Z36: 142.745 | AB36: 37.736 | AC36: 35.853 | AD36: 81.147 | AE36: 83.074 | AF36: 237.81 | AH36: 93.738 | AI36: 108.178
B37: Interest income | D37: 3.131 | E37: 4.498 | F37: 2.347 | G37: 3.185 | H37: 13.161 | J37: 3.844 | K37: 3.19 | L37: 4.571 | M37: 5.7 | N37: 17.305 | P37: 11.896 | Q37: 18.454 | R37: 18.268 | S37: 16.463 | T37: 65.081 | V37: 13.095 | W37: 18.729 | X37: 17.353 | Y37: 16.014 | Z37: 65.191 | AB37: 15.427 | AC37: 13.531 | AD37: 29.04 | AE37: 28.594 | AF37: 86.592 | AH37: 20.563 | AI37: 31.167
A38: x | B38: Net interest (income) expense | D38: 2.257 | E38: 4.323 | F38: 5.189 | G38: -1.44 | H38: 10.329 | J38: 4.516 | K38: 5.841 | L38: 5.239 | M38: 7.699 | N38: 23.295 | P38: -3.26 | Q38: -6.842 | R38: -6.365 | S38: 13.758 | T38: -2.709 | V38: 18.86 | W38: 14.688 | X38: 22.224 | Y38: 21.782 | Z38: 77.554 | AB38: 22.309 | AC38: 22.322 | AD38: 52.107 | AE38: 54.48 | AF38: 151.218 | AH38: 73.175 | AI38: 77.011
B39: Foreign exchange (gains) losses | D39: -3.584 | E39: -2.015 | F39: -1.888 | G39: 9.897 | H39: 2.41 | J39: -3.07 | K39: 5.537 | L39: -1.982 | M39: 1.992 | N39: 2.477 | P39: 13.363 | Q39: 2.401 | R39: 4.098 | S39: 5.104 | T39: 27.781 | V39: 3.797 | W39: 14.021 | X39: 12.964 | Y39: 14.034 | Z39: 44.816 | AB39: 8.892 | AC39: 3.539 | AD39: 0.104 | AE39: 27.664 | AF39: 40.199 | AH39: 1.026 | AI39: 36.43
B40: Other non-operating (income) expenses | D40: 2.099 | E40: 6.767 | F40: 3.533 | G40: 0.368 | H40: 12.767 | J40: 7.17 | K40: 7.41 | L40: 9.497 | M40: 12.979 | N40: 37.056 | P40: 10.304 | Q40: 11.096 | R40: 11.932 | S40: 18.854 | T40: 52.186 | V40: 16.934 | W40: 14.965 | X40: 12.925 | Y40: 15.649 | Z40: 60.473 | AB40: 16.42 | AC40: 18.277 | AD40: 92.876 | AE40: 74.707 | AF40: 202.28 | AH40: 85.279 | AI40: 86.736
B41: Total non-operating expenses | D41: 0.772 | E41: 9.075 | F41: 6.834 | G41: 8.825 | H41: 25.506 | J41: 8.616 | K41: 18.788 | L41: 12.754 | M41: 22.67 | N41: 62.828 | P41: 20.407 | Q41: 6.655 | R41: 9.665 | S41: 37.716 | T41: 77.258 | V41: 39.591 | W41: 43.674 | X41: 48.113 | Y41: 51.465 | Z41: 182.843 | AB41: 47.621 | AC41: 44.138 | AD41: 145.087 | AE41: 156.851 | AF41: 393.697 | AH41: 159.48 | AI41: 200.177
B42: Pre-tax income | D42: 45.005 | E42: -81.585 | F42: 37.989 | G42: 85.906 | H42: 87.315 | J42: 32.389 | K42: 170.047 | L42: 79.838 | M42: 104.077 | N42: 260.217 | P42: 140.79 | Q42: 50.884 | R42: 117.552 | S42: 182.989 | T42: 489.4 | V42: 77.389 | W42: 87.246 | X42: 131.185 | Y42: 103.83 | Z42: 399.651 | AB42: 63.223 | AC42: 99.591 | AD42: 42.378 | AE42: 38.274 | AF42: 229.322 | AH42: 120.857 | AI42: 166.927
A44: x | B44: Tax & net income:
B45: Income tax expenses (benefits) | D45: 17.9561 | E45: -11.6003 | F45: 9.7998 | G45: 0.9558 | H45: 17.1114 | J45: 2.6764 | K45: 37.6414 | L45: 2.8419 | M45: 11.0233 | N45: 11.2974 | P45: 43.4753 | Q45: -25.7842 | R45: 15.8603 | S45: 22.4015 | T45: 55.9529 | V45: 5.981 | W45: -16.8143 | X45: 14.8256 | Y45: -18.6633 | Z45: -14.6706 | AB45: -10.7645 | AC45: -35.1817 | AD45: -53.0131 | AE45: -163.4495 | AF45: -267.2178 | AH45: 1.4239 | AI45: -375.1985
B46: Net extraordinary losses (gains) | D46: 0 | E46: 0 | F46: 0 | G46: 0 | H46: 0 | J46: 0 | K46: 0 | L46: 0 | M46: 0 | N46: 0 | P46: 0 | Q46: 0 | R46: 0 | S46: 0 | T46: 0 | V46: 0 | W46: 0 | X46: 0 | Y46: 0 | Z46: 0 | AB46: 0 | AC46: 0 | AD46: 0 | AE46: 0 | AF46: 0 | AH46: 0 | AI46: 0
B47: Net income including minority interest | D47: 27.0489 | E47: -69.9847 | F47: 28.1892 | G47: 84.9502 | H47: 70.2036 | J47: 29.7126 | K47: 132.4056 | L47: 76.9961 | M47: 93.0537 | N47: 248.9196 | P47: 97.3147 | Q47: 76.6682 | R47: 101.6917 | S47: 160.5875 | T47: 433.4471 | V47: 71.408 | W47: 104.0603 | X47: 116.3594 | Y47: 122.4933 | Z47: 414.3216 | AB47: 73.9875 | AC47: 134.7727 | AD47: 95.3911 | AE47: 201.7235 | AF47: 496.5398 | AH47: 119.4331 | AI47: 542.1255
A49: x | B49: Attribution:
B50: Preferred dividends | D50: 0 | E50: 0 | F50: 0 | G50: 0 | H50: 0 | J50: 0 | K50: 0 | L50: 0 | M50: 0 | N50: 0 | P50: 0 | Q50: 0 | R50: 0 | S50: 0 | T50: 0 | V50: 0 | W50: 0 | X50: 0 | Y50: 0 | Z50: 0 | AB50: 0 | AC50: 0 | AD50: 0 | AE50: 0 | AF50: 0 | AH50: 0 | AI50: 0
B51: Income attributable to non-controlling interests | D51: 0 | E51: 0 | F51: 0 | G51: 0 | H51: 0 | J51: 0 | K51: 0 | L51: -0.514 | M51: -0.215 | N51: -1.514 | P51: -0.768 | Q51: -0.629 | R51: 2.815 | S51: -0.429 | T51: -2.171 | V51: 0.244 | W51: -0.164 | X51: -0.205 | Y51: -0.602 | Z51: -0.727 | AB51: -1.538 | AC51: -1.508 | AD51: 0.515 | AE51: -0.647 | AF51: -3.178 | AH51: 0 | AI51: 0
B52: Net income attributable to common shareholders | D52: 27.0489 | E52: -69.9847 | F52: 28.1892 | G52: 84.9502 | H52: 70.2036 | J52: 29.7126 | K52: 132.4056 | L52: 77.5101 | M52: 93.2687 | N52: 250.4336 | P52: 98.0827 | Q52: 77.2972 | R52: 98.8767 | S52: 161.0165 | T52: 435.6181 | V52: 71.164 | W52: 104.2243 | X52: 116.5644 | Y52: 123.0953 | Z52: 415.0486 | AB52: 75.5255 | AC52: 136.2807 | AD52: 94.8761 | AE52: 202.3705 | AF52: 499.7178 | AH52: 119.4331 | AI52: 542.1255
A54: x | B54: Earnings per share:
B55: EPS basic | D55: 0.2976 | E55: -0.77 | F55: 0.3095 | G55: 0.9065 | H55: 0.7661 | J55: 0.2982 | K55: 1.3364 | L55: 0.7694 | M55: 0.1007 | N55: 2.5146 | P55: 0.9181 | Q55: 0.7042 | R55: 0.8987 | S55: 1.4612 | T55: 3.989 | V55: 0.6464 | W55: 0.9451 | X55: 1.0509 | Y55: 1.0993 | Z55: 3.7454 | AB55: 0.6811 | AC55: 1.23 | AD55: 0.792 | AE55: 1.24 | AF55: 3.8233 | AH55: 0.5785 | AI55: 2.6317
B56: EPS diluted | D56: 0.2976 | E56: -0.77 | F56: 0.3095 | G56: 0.8924 | H56: 0.763 | J56: 0.2975 | K56: 1.3331 | L56: 0.7693 | M56: 0.0935 | N56: 2.4636 | P56: 0.9011 | Q56: 0.6919 | R56: 0.8597 | S56: 1.3871 | T56: 3.858 | V56: 0.6296 | W56: 0.9206 | X56: 1.0254 | Y56: 1.0714 | Z56: 3.6502 | AB56: 0.6646 | AC56: 1.2009 | AD56: 0.7693 | AE56: 1.239 | AF56: 3.7481 | AH56: 0.5732 | AI56: 2.5965
A58: x | B58: Shares used in computing earnings per share:
B59: Basic weighted average shares | D59: 90.889 | E59: 90.889 | F59: 91.072 | G59: 93.714 | H59: 91.641 | J59: 99.627 | K59: 99.077 | L59: 100.736 | M59: 99.47 | N59: 99.59 | P59: 106.828 | Q59: 109.772 | R59: 110.019 | S59: 110.197 | T59: 109.204 | V59: 110.095 | W59: 110.281 | X59: 110.914 | Y59: 111.974 | Z59: 110.816 | AB59: 110.882 | AC59: 110.801 | AD59: 119.792 | AE59: 163.202 | AF59: 130.704 | AH59: 206.468 | AI59: 205.998
B60: Diluted weighted average shares | D60: 90.889 | E60: 90.889 | F60: 91.072 | G60: 95.198 | H60: 92.012 | J60: 99.875 | K60: 99.325 | L60: 100.75 | M60: 107.216 | N60: 101.654 | P60: 108.847 | Q60: 111.713 | R60: 115.014 | S60: 116.078 | T60: 112.913 | V60: 113.035 | W60: 113.211 | X60: 113.681 | Y60: 114.893 | Z60: 113.705 | AB60: 113.639 | AC60: 113.484 | AD60: 123.334 | AE60: 163.302 | AF60: 133.326 | AH60: 208.37 | AI60: 209.206
B62: Additional Items
B64: Depreciation (from opex)
B65: Amortization (form opex)

Sheet BS
AH1: 0
B7: Balance Sheet | D7: 2020 | E7: 2020 | F7: 2020 | G7: 2020 | H7: 2020 | J7: 2021 | K7: 2021 | L7: 2021 | M7: 2021 | N7: 2021 | P7: 2022 | Q7: 2022 | R7: 2022 | S7: 2022 | T7: 2022 | V7: 2023 | W7: 2023 | X7: 2023 | Y7: 2023 | Z7: 2023 | AB7: 2024 | AC7: 2024 | AD7: 2024 | AE7: 2024 | AF7: 2024 | AH7: 2025 | AI7: 2025 | AJ7: 2025 | AK7: 2025 | AL7: 2025 | AN7: 2025 | AO7: 2025 | AP7: 2025 | AQ7: 2025 | AR7: 2025
D8: 2020 | J8: 2021 | P8: 2022 | V8: 2023 | AB8: 2024 | AH8: 2025 | AN8: 2026 | AT8: 2027 | AV8: 2028 | AX8: 2029
D9: Q1 | E9: Q2 | F9: Q3 | G9: Q4 | H9: FY | J9: Q1 | K9: Q2 | L9: Q3 | M9: Q4 | N9: FY | P9: Q1 | Q9: Q2 | R9: Q3 | S9: Q4 | T9: FY | V9: Q1 | W9: Q2 | X9: Q3 | Y9: Q4 | Z9: FY | AB9: Q1 | AC9: Q2 | AD9: Q3 | AE9: Q4 | AF9: FY | AH9: Q1 | AI9: Q2 | AJ9: Q3 | AK9: Q4 | AL9: FY | AN9: Q1 | AO9: Q2 | AP9: Q3 | AQ9: Q4 | AR9: FY | AT9: FY | AV9: FY | AX9: FY
B12: Assets
A14: x | B14: Current assets:
B15: Cash & cash equivalents & short-term investments | D15: 619.181 | E15: 565.619 | F15: 566.245 | G15: 561.165 | H15: 561.165 | J15: 570.746 | K15: 385.921 | L15: 297.205 | M15: 262.559 | N15: 262.559 | P15: 710.309 | Q15: 715.247 | R15: 546.122 | S15: 476.434 | T15: 476.434 | V15: 783.068 | W15: 682.038 | X15: 643.566 | Y15: 749.714 | Z15: 749.714 | AB15: 593.85 | AC15: 562.698 | AD15: 766.397 | AE15: 774.543 | AF15: 774.543 | AH15: 1103.372 | AI15: 823.162
B16: Cash & cash equivalents | D16: 611.584 | E16: 552.654 | F16: 552.743 | G16: 522.868 | H16: 522.868 | J16: 348.148 | K16: 316.296 | L16: 248.158 | M16: 228.809 | N16: 228.809 | P16: 603.562 | Q16: 633.565 | R16: 471.189 | S16: 447.608 | T16: 447.608 | V16: 699.465 | W16: 608.572 | X16: 582.867 | Y16: 676.398 | Z16: 676.398 | AB16: 540.815 | AC16: 508.813 | AD16: 603.959 | AE16: 593.383 | AF16: 593.383 | AH16: 967.411 | AI16: 645.797
B17: Short-term investments | D17: 7.597 | E17: 12.965 | F17: 13.502 | G17: 38.297 | H17: 38.297 | J17: 222.598 | K17: 69.625 | L17: 49.047 | M17: 33.75 | N17: 33.75 | P17: 106.747 | Q17: 81.682 | R17: 74.933 | S17: 28.826 | T17: 28.826 | V17: 83.603 | W17: 73.466 | X17: 60.699 | Y17: 73.316 | Z17: 73.316 | AB17: 53.035 | AC17: 53.885 | AD17: 162.438 | AE17: 181.16 | AF17: 181.16 | AH17: 135.961 | AI17: 177.365
B18: Accounts receivable | D18: 400.136 | E18: 283.071 | F18: 406.902 | G18: 598.824 | H18: 598.824 | J18: 477.929 | K18: 455.695 | L18: 605.881 | M18: 790.302 | N18: 790.302 | P18: 631.278 | Q18: 613.69 | R18: 722.016 | S18: 867.582 | T18: 867.582 | V18: 743.011 | W18: 781.486 | X18: 921.776 | Y18: 1125.449 | Z18: 1125.449 | AB18: 902.621 | AC18: 963.304 | AD18: 2512.451 | AE18: 2816.294 | AF18: 2816.294 | AH18: 2448.811 | AI18: 2596.937
B19: Inventory | D19: 253.412 | E19: 271.321 | F19: 241.895 | G19: 290.896 | H19: 290.896 | J19: 348.041 | K19: 362.063 | L19: 448.212 | M19: 450.487 | N19: 450.487 | P19: 556.685 | Q19: 651.73 | R19: 755.06 | S19: 772.06 | T19: 772.06 | V19: 842.526 | W19: 864.459 | X19: 866.759 | Y19: 828.557 | Z19: 828.557 | AB19: 920.2 | AC19: 968.239 | AD19: 2313.143 | AE19: 2218.815 | AF19: 2218.815 | AH19: 2456.987 | AI19: 2474.521
B20: Prepaid expenses and other current assets | D20: 144.018 | E20: 156.79 | F20: 129.06 | G20: 113.983 | H20: 113.983 | J20: 126.441 | K20: 137.114 | L20: 144.175 | M20: 143.438 | N20: 143.438 | P20: 211.131 | Q20: 212.246 | R20: 268.658 | S20: 267.369 | T20: 267.369 | V20: 322.411 | W20: 443.156 | X20: 251.663 | Y20: 211.334 | Z20: 211.334 | AB20: 259.961 | AC20: 349.693 | AD20: 1015.92 | AE20: 1022.031 | AF20: 1022.031 | AH20: 1042.452 | AI20: 971.353
B21: Total current assets | D21: 1416.747 | E21: 1276.801 | F21: 1344.102 | G21: 1564.868 | H21: 1564.868 | J21: 1523.157 | K21: 1340.793 | L21: 1495.473 | M21: 1646.786 | N21: 1646.786 | P21: 2109.403 | Q21: 2192.913 | R21: 2291.856 | S21: 2383.445 | T21: 2383.445 | V21: 2691.016 | W21: 2771.139 | X21: 2683.764 | Y21: 2915.054 | Z21: 2915.054 | AB21: 2676.632 | AC21: 2843.934 | AD21: 6607.911 | AE21: 6831.683 | AF21: 6831.683 | AH21: 7051.622 | AI21: 6865.973
A23: x | B23: Non-current assets:
B24: Net PP&E (Property, Plant and Equipment) | D24: 354.778 | E24: 293.326 | F24: 277.017 | G24: 316.3 | H24: 316.3 | J24: 313.409 | K24: 287.324 | L24: 348.244 | M24: 403.868 | N24: 403.868 | P24: 446.326 | Q24: 492.475 | R24: 586.25 | S24: 691.582 | T24: 691.582 | V24: 769.765 | W24: 850.095 | X24: 835.209 | Y24: 890.929 | Z24: 890.929 | AB24: 845.792 | AC24: 863.457 | AD24: 2168.252 | AE24: 2308.909 | AF24: 2308.909 | AH24: 2230.121 | AI24: 2169.77
B25: Gross PP&E (Property, Plant and Equipment) | D25: 374.17 | E25: 387.021 | F25: 332.326 | G25: 561.496 | H25: 561.496 | J25: 335.664 | K25: 331.717 | L25: 414.753 | M25: 0 | N25: 0 | P25: 475.282 | Q25: 547.092 | R25: 668.562 | S25: 1143.717 | T25: 1143.717 | V25: 0 | W25: 933.554 | X25: 962.302 | Y25: 1519.343 | Z25: 1519.343 | AB25: 890.588 | AC25: 952.27 | AD25: 2336.356 | AE25: 3225.642 | AF25: 3225.642 | AH25: 0 | AI25: 0
B26: Accumulated Depreciation | D26: 19.392 | E26: 93.695 | F26: 55.309 | G26: 245.196 | H26: 245.196 | J26: 22.255 | K26: 44.393 | L26: 66.509 | M26: 0 | N26: 0 | P26: 28.956 | Q26: 54.617 | R26: 82.312 | S26: 452.135 | T26: 452.135 | V26: 0 | W26: 83.459 | X26: 127.093 | Y26: 628.414 | Z26: 628.414 | AB26: 44.796 | AC26: 88.813 | AD26: 168.104 | AE26: 916.733 | AF26: 916.733 | AH26: 0 | AI26: 0
B27: Intangibles | D27: 75.578 | E27: 77.425 | F27: 84.199 | G27: 829.867 | H27: 829.867 | J27: 864.238 | K27: 868.869 | L27: 990.517 | M27: 1014.918 | N27: 1014.918 | P27: 1150.154 | Q27: 1186.6 | R27: 1247.969 | S27: 1263.412 | T27: 1263.412 | V27: 1370.027 | W27: 1523.662 | X27: 1569.898 | Y27: 1561.906 | Z27: 1561.906 | AB27: 1565.2 | AC27: 1587.92 | AD27: 3908.228 | AE27: 3741.353 | AF27: 3741.353 | AH27: 3508.455 | AI27: 3586.025
B28: Goodwill | D28: 0 | E28: 0 | F28: 0 | G28: 466.128 | H28: 466.128 | J28: 494.906 | K28: 474.677 | L28: 586.343 | M28: 560.896 | N28: 560.896 | P28: 356.434 | Q28: 690.454 | R28: 729.944 | S28: 737.656 | T28: 737.656 | V28: 831.417 | W28: 898.909 | X28: 843.948 | Y28: 919.29 | Z28: 919.29 | AB28: 850.469 | AC28: 853.761 | AD28: 1505.95 | AE28: 1335.723 | AF28: 1335.723 | AH28: 1128.283 | AI28: 1123.55
B29: Intangibles excl. Goodwill | D29: 0 | E29: 0 | F29: 0 | G29: 0 | H29: 0 | J29: 0 | K29: 0 | L29: 0 | M29: 0 | N29: 0 | P29: 0 | Q29: 0 | R29: 0 | S29: 0 | T29: 0 | V29: 0 | W29: 0 | X29: 0 | Y29: 0 | Z29: 0 | AB29: 0 | AC29: 0 | AD29: 0 | AE29: 0 | AF29: 0 | AH29: 0 | AI29: 0
B30: Other Non-Current Assets | D30: 58.077 | E30: 83.14 | F30: 82.95 | G30: 121.51 | H30: 121.51 | J30: 134.827 | K30: -610.45 | L30: 291.01 | M30: 300.754 | N30: 300.754 | P30: 318.33 | Q30: 322.419 | R30: 310.346 | S30: 320.825 | T30: 320.825 | V30: 301.114 | W30: 290.167 | X30: 545.547 | Y30: 608.015 | Z30: 608.015 | AB30: 635.923 | AC30: 707.499 | AD30: 2221.88 | AE30: 2371.6 | AF30: 2371.6 | AH30: 2552.883 | AI30: 2895.064
B31: Total Non-Current Assets | D31: 488.433 | E31: 453.891 | F31: 444.166 | G31: 1267.677 | H31: 1267.677 | J31: 1312.474 | K31: 545.743 | L31: 1629.771 | M31: 1719.54 | N31: 1719.54 | P31: 1914.81 | Q31: 2001.494 | R31: 2144.565 | S31: 2275.819 | T31: 2275.819 | V31: 2440.906 | W31: 2663.924 | X31: 2950.654 | Y31: 3060.85 | Z31: 3060.85 | AB31: 3046.915 | AC31: 3158.876 | AD31: 8298.36 | AE31: 8421.862 | AF31: 8421.862 | AH31: 8291.459 | AI31: 8650.859
B32: Total Assets | D32: 1905.18 | E32: 1730.692 | F32: 1788.268 | G32: 2832.545 | H32: 2832.545 | J32: 2835.631 | K32: 2755.405 | L32: 3125.244 | M32: 3366.326 | N32: 3366.326 | P32: 4024.213 | Q32: 4194.407 | R32: 4436.421 | S32: 4659.264 | T32: 4659.264 | V32: 5131.922 | W32: 5435.063 | X32: 5634.418 | Y32: 5975.904 | Z32: 5975.904 | AB32: 5723.547 | AC32: 6002.81 | AD32: 14906.271 | AE32: 15253.545 | AF32: 15253.545 | AH32: 15343.081 | AI32: 15516.832
B34: Liabilities & shareholders' equity
A36: x | B36: Current Liabilities:
B37: Accounts payable | D37: 239.677 | E37: 183.06 | F37: 290.9 | G37: 498.939 | H37: 498.939 | J37: 455.53 | K37: 463.201 | L37: 586.107 | M37: 820.66 | N37: 820.66 | P37: 744.399 | Q37: 836.041 | R37: 855.213 | S37: 1064.289 | T37: 1064.289 | V37: 694.254 | W37: 720.843 | X37: 758.126 | Y37: 1041.509 | Z37: 1041.509 | AB37: 827.768 | AC37: 934.674 | AD37: 2339.209 | AE37: 2794.703 | AF37: 2794.703 | AH37: 2213.791 | AI37: 2086.516
B38: Short-term borrowings | D38: 307.081 | E38: 292.424 | F38: 440.509 | G38: 239.483 | H38: 239.483 | J38: 364.786 | K38: 216.587 | L38: 271.04 | M38: 496.861 | N38: 496.861 | P38: 268.463 | Q38: 345.024 | R38: 0 | S38: 392.254 | T38: 392.254 | V38: 663.004 | W38: 642.492 | X38: 1087.4 | Y38: 882.205 | Z38: 882.205 | AB38: 747.452 | AC38: 823.049 | AD38: 903.18 | AE38: 1476.529 | AF38: 1476.529 | AH38: 1904.108 | AI38: 1741.35
B39: Current portion of lease liabilities | D39: 47.995 | E39: 44.836 | F39: 42.569 | G39: 52.89 | H39: 52.89 | J39: 50.749 | K39: 44.375 | L39: 52.351 | M39: 57.017 | N39: 57.017 | P39: 58.229 | Q39: 62.079 | R39: 72.314 | S39: 89.648 | T39: 89.648 | V39: 93.79 | W39: 97.48 | X39: 101.619 | Y39: 107.671 | Z39: 107.671 | AB39: 94.482 | AC39: 96.841 | AD39: 201.569 | AE39: 213.145 | AF39: 213.145 | AH39: 210.067 | AI39: 208.687
B40: Accrued expenses and other current liabilities | D40: 33.282 | E40: 56.507 | F40: 44.384 | G40: 120.106 | H40: 120.106 | J40: 112.381 | K40: 140.627 | L40: 161.434 | M40: 144.462 | N40: 144.462 | P40: 198.251 | Q40: 189.875 | R40: 573.546 | S40: 89.169 | T40: 89.169 | V40: 138.524 | W40: 242.344 | X40: 226.011 | Y40: 260.898 | Z40: 260.898 | AB40: 202.389 | AC40: 131.632 | AD40: 262.238 | AE40: 32.755 | AF40: 32.755 | AH40: 234.183 | AI40: 236.094
B41: Total current liabilities | D41: 628.035 | E41: 576.827 | F41: 818.362 | G41: 911.418 | H41: 911.418 | J41: 983.446 | K41: 864.79 | L41: 1070.932 | M41: 1519 | N41: 1519 | P41: 1269.342 | Q41: 1433.019 | R41: 1501.073 | S41: 1635.36 | T41: 1635.36 | V41: 1589.572 | W41: 1703.159 | X41: 2173.156 | Y41: 2292.283 | Z41: 2292.283 | AB41: 1872.091 | AC41: 1986.196 | AD41: 3706.196 | AE41: 4517.132 | AF41: 4517.132 | AH41: 4562.149 | AI41: 4272.647
A43: x | B43: Non-current liabilities:
B44: Long-term borrowings | D44: 308.878 | E44: 308.923 | F44: 106.736 | G44: 394.786 | H44: 394.786 | J44: 299.106 | K44: 292.909 | L44: 297.218 | M44: 37.733 | N44: 37.733 | P44: 15.576 | Q44: 10.263 | R44: 10.053 | S44: 9.619 | T44: 9.619 | V44: 397.089 | W44: 385.533 | X44: 5.101 | Y44: 198.919 | Z44: 198.919 | AB44: 351.296 | AC44: 389.46 | AD44: 1555.759 | AE44: 1178.202 | AF44: 1178.202 | AH44: 1335.83 | AI44: 1292.011
B45: Long-term operating lease liabilities | D45: 201.228 | E45: 163.435 | F45: 154.647 | G45: 160.47 | H45: 160.47 | J45: 161.669 | K45: 142.844 | L45: 155.314 | M45: 174.879 | N45: 174.879 | P45: 168.765 | Q45: 180.107 | R45: 236.822 | S45: 284.889 | T45: 284.889 | V45: 339.922 | W45: 394.957 | X45: 401.929 | Y45: 407.514 | Z45: 407.514 | AB45: 370.469 | AC45: 368.69 | AD45: 626.196 | AE45: 662.525 | AF45: 662.525 | AH45: 623.27 | AI45: 599.731
B46: Other non-current liabilities | D46: 11.544 | E46: 12.04 | F46: 11.264 | G46: 17.274 | H46: 17.274 | J46: 19.997 | K46: 23.61 | L46: 53.605 | M46: 42.708 | N46: 42.708 | P46: 72.28 | Q46: 78.557 | R46: 73.592 | S46: 74.803 | T46: 74.803 | V46: 63.378 | W46: 145.728 | X46: 144.914 | Y46: 148.089 | Z46: 148.089 | AB46: 172.23 | AC46: 171.079 | AD46: 1134.365 | AE46: 1174.171 | AF46: 1174.171 | AH46: 1017.475 | AI46: 1012.895
B47: Total non-current liabilities | D47: 521.65 | E47: 484.398 | F47: 272.647 | G47: 572.53 | H47: 572.53 | J47: 480.772 | K47: 459.363 | L47: 506.137 | M47: 255.32 | N47: 255.32 | P47: 256.621 | Q47: 268.927 | R47: 320.467 | S47: 369.311 | T47: 369.311 | V47: 800.389 | W47: 926.218 | X47: 551.944 | Y47: 754.522 | Z47: 754.522 | AB47: 893.995 | AC47: 929.229 | AD47: 3316.32 | AE47: 3014.898 | AF47: 3014.898 | AH47: 2976.575 | AI47: 2904.637
B48: Total liabilities | D48: 1149.685 | E48: 1061.225 | F48: 1091.009 | G48: 1483.948 | H48: 1483.948 | J48: 1464.218 | K48: 1324.153 | L48: 1577.069 | M48: 1774.32 | N48: 1774.32 | P48: 1525.963 | Q48: 1701.946 | R48: 1821.54 | S48: 2004.671 | T48: 2004.671 | V48: 2389.961 | W48: 2629.377 | X48: 2725.1 | Y48: 3046.805 | Z48: 3046.805 | AB48: 2766.086 | AC48: 2915.425 | AD48: 7022.516 | AE48: 7532.03 | AF48: 7532.03 | AH48: 7538.724 | AI48: 7177.284
A50: x | B50: Shareholders' equity:
B51: Common equity | D51: 755.495 | E51: 669.467 | F51: 697.259 | G51: 1348.597 | H51: 1348.597 | J51: 1371.413 | K51: 1430.98 | L51: 1546.535 | M51: 1590.58 | N51: 1590.58 | P51: 2497.592 | Q51: 2492.432 | R51: 2614.13 | S51: 2653.792 | T51: 2653.792 | V51: 2716.661 | W51: 2783.1 | X51: 2891.405 | Y51: 2909.553 | Z51: 2909.553 | AB51: 2940.189 | AC51: 3069.791 | AD51: 7865.406 | AE51: 7702.653 | AF51: 7702.653 | AH51: 7804.357 | AI51: 8339.548
B52: Preferred equity | D52: 0 | E52: 0 | F52: 0 | G52: 0 | H52: 0 | J52: 0 | K52: 0 | L52: 0 | M52: 0 | N52: 0 | P52: 0 | Q52: 0 | R52: 0 | S52: 0 | T52: 0 | V52: 0 | W52: 0 | X52: 0 | Y52: 0 | Z52: 0 | AB52: 0 | AC52: 0 | AD52: 0 | AE52: 0 | AF52: 0 | AH52: 0 | AI52: 0
B53: Non-controlling interest | D53: 0 | E53: 0 | F53: 0 | G53: 0 | H53: 0 | J53: 0 | K53: 0.272 | L53: 1.64 | M53: 1.426 | N53: 1.426 | P53: 0.658 | Q53: 0.029 | R53: 0.751 | S53: 0.801 | T53: 0.801 | V53: 25.3 | W53: 22.586 | X53: 17.913 | Y53: 19.546 | Z53: 19.546 | AB53: 17.272 | AC53: 17.594 | AD53: 18.349 | AE53: 18.862 | AF53: 18.862 | AH53: 0 | AI53: 0
B54: Total equity | D54: 755.495 | E54: 669.467 | F54: 697.259 | G54: 1348.597 | H54: 1348.597 | J54: 1371.413 | K54: 1431.252 | L54: 1548.175 | M54: 1592.006 | N54: 1592.006 | P54: 2498.25 | Q54: 2492.461 | R54: 2614.881 | S54: 2654.593 | T54: 2654.593 | V54: 2741.961 | W54: 2805.686 | X54: 2909.318 | Y54: 2929.099 | Z54: 2929.099 | AB54: 2957.461 | AC54: 3087.385 | AD54: 7883.755 | AE54: 7721.515 | AF54: 7721.515 | AH54: 7804.357 | AI54: 8339.548
B55: Total liabilities and shareholders' equity | D55: 1905.18 | E55: 1730.692 | F55: 1788.268 | G55: 2832.545 | H55: 2832.545 | J55: 2835.631 | K55: 2755.405 | L55: 3125.244 | M55: 3366.326 | N55: 3366.326 | P55: 4024.213 | Q55: 4194.407 | R55: 4436.421 | S55: 4659.264 | T55: 4659.264 | V55: 5131.922 | W55: 5435.063 | X55: 5634.418 | Y55: 5975.904 | Z55: 5975.904 | AB55: 5723.547 | AC55: 6002.81 | AD55: 14906.271 | AE55: 15253.545 | AF55: 15253.545 | AH55: 15343.081 | AI55: 15516.832
B57: Capitalized R&D | D57: 0 | E57: 0 | F57: 0 | G57: 0 | H57: 0 | J57: 0 | K57: 0 | L57: 0 | M57: 0 | N57: 0 | P57: 0 | Q57: 0 | R57: 0 | S57: 0 | T57: 0 | V57: 0 | W57: 0 | X57: 0 | Y57: 0 | Z57: 0 | AB57: 0 | AC57: 0 | AD57: 0 | AE57: 0 | AF57: 0 | AH57: 0 | AI57: 0

Sheet CF
A7: x | B7: Cash Flow Statement | D7: 2020 | E7: 2020 | F7: 2020 | G7: 2020 | H7: 2020 | J7: 2021 | K7: 2021 | L7: 2021 | M7: 2021 | N7: 2021 | P7: 2022 | Q7: 2022 | R7: 2022 | S7: 2022 | T7: 2022 | V7: 2023 | W7: 2023 | X7: 2023 | Y7: 2023 | Z7: 2023 | AB7: 2024 | AC7: 2024 | AD7: 2024 | AE7: 2024 | AF7: 2024 | AH7: 2025 | AI7: 2025 | AJ7: 2025 | AK7: 2025 | AL7: 2025 | AN7: 2025 | AO7: 2025 | AP7: 2025 | AQ7: 2025 | AR7: 2025
D8: 2020 | J8: 2021 | P8: 2022 | V8: 2023 | AB8: 2024 | AH8: 2025 | AN8: 2026 | AT8: 2027 | AV8: 2028 | AX8: 2029
D9: Q1 | E9: Q2 | F9: Q3 | G9: Q4 | H9: FY | J9: Q1 | K9: Q2 | L9: Q3 | M9: Q4 | N9: FY | P9: Q1 | Q9: Q2 | R9: Q3 | S9: Q4 | T9: FY | V9: Q1 | W9: Q2 | X9: Q3 | Y9: Q4 | Z9: FY | AB9: Q1 | AC9: Q2 | AD9: Q3 | AE9: Q4 | AF9: FY | AH9: Q1 | AI9: Q2 | AJ9: Q3 | AK9: Q4 | AL9: FY | AN9: Q1 | AO9: Q2 | AP9: Q3 | AQ9: Q4 | AR9: FY | AT9: FY | AV9: FY | AX9: FY
B12: Cash and cash equivalents, beginning balances | D12: 13.808 | E12: 7.597 | F12: 12.965 | G12: 13.502 | H12: 38.297 | J12: 38.297 | K12: 222.598 | L12: 69.625 | M12: 49.047 | N12: 33.75 | P12: 33.75 | Q12: 106.747 | R12: 81.682 | S12: 74.933 | T12: 28.826 | V12: 28.826 | W12: 83.603 | X12: 73.466 | Y12: 60.699 | Z12: 73.316 | AB12: 73.316 | AC12: 53.035 | AD12: 53.885 | AE12: 162.438 | AF12: 181.16 | AH12: 181.16 | AI12: 135.961
A14: x | B14: Operating activities:
B15: Net income | D15: 25.888 | E15: -82.299 | F15: 27.947 | G15: 77.048 | H15: 48.584 | J15: 29.776 | K15: 132.496 | L15: 78.044 | M15: 104.133 | N15: 345.234 | P15: 98.053 | Q15: 120.45 | R15: 98.849 | S15: 107.012 | T15: 424.709 | V15: 63.141 | W15: 100.626 | X15: 113.863 | Y15: 121.77 | Z15: 399.4 | AB15: 73.1 | AC15: 129.418 | AD15: 206.463 | AE15: -67.254 | AF15: 341.727 | AH15: 117.826 | AI15: 537.654
B16: Adjustments to reconcile to cash from operations:
B17: Depreciation and amortization | D17: 20.279 | E17: 20.316 | F17: 19.201 | G17: 21.307 | H17: 81.103 | J17: 24.865 | K17: 25.142 | L17: 24.872 | M17: 30.869 | N17: 105.748 | P17: 33.433 | Q17: 34.813 | R17: 38.019 | S17: 59.765 | T17: 166.03 | V17: 49.396 | W17: 54.48 | X17: 55.587 | Y17: 63.481 | Z17: 222.944 | AB17: 59.355 | AC17: 60.791 | AD17: 122.918 | AE17: 171.791 | AF17: 414.855 | AH17: 166.581 | AI17: 167.139
B18: Stock-based compensation expense | D18: 0.727 | E18: 0.696 | F18: 0.512 | G18: 0.428 | H18: 2.363 | J18: 0.428 | K18: 0.429 | L18: 0.361 | M18: 1.443 | N18: 2.661 | P18: 3.436 | Q18: 3.436 | R18: 4.653 | S18: 5.018 | T18: 16.543 | V18: 4.39 | W18: 4.382 | X18: 4.858 | Y18: 3.718 | Z18: 17.348 | AB18: 3.197 | AC18: 3.197 | AD18: 5.365 | AE18: 6.157 | AF18: 17.916 | AH18: 5.381 | AI18: 5.815
B19: Other | D19: -22.45 | E19: 7.207 | F19: 7.896 | G19: 34.657 | H19: 27.31 | J19: -29.528 | K19: 28.084 | L19: 28.252 | M19: 50.963 | N19: 76.986 | P19: -85.109 | Q19: -62.001 | R19: 56.099 | S19: -29.467 | T19: -120.823 | V19: -93.509 | W19: -0.718 | X19: 1.567 | Y19: -19.326 | Z19: -111.986 | AB19: -82.336 | AC19: 23.084 | AD19: -203.698 | AE19: 406.923 | AF19: 143.973 | AH19: -252.113 | AI19: -164.412
B20: Changes in working capital:
B21: Accounts receivable | D21: 12.802 | E21: 106.749 | F21: -121.063 | G21: -107.285 | H21: -108.797 | J21: 117.398 | K21: 17.762 | L21: -149.555 | M21: -182.762 | N21: -197.157 | P21: 157.533 | Q21: 29.331 | R21: -103.35 | S21: -142.213 | T21: -58.699 | V21: 142.656 | W21: -35.528 | X21: -139.021 | Y21: -203.964 | Z21: -235.857 | AB21: 216.266 | AC21: -63.763 | AD21: -158.915 | AE21: -280.924 | AF21: -287.336 | AH21: 361.855 | AI21: -158.16
B22: Inventories | D22: -77.295 | E22: -19.578 | F22: 27.104 | G22: 31.114 | H22: -38.655 | J22: -64.383 | K22: -9.858 | L22: -88.914 | M22: -3.528 | N22: -166.683 | P22: -106.509 | Q22: -92.358 | R22: -98.459 | S22: -13.275 | T22: -310.601 | V22: -66.533 | W22: 13.389 | X22: -4.633 | Y22: 28.633 | Z22: -29.144 | AB22: -91.507 | AC22: -51.386 | AD22: -104.31 | AE22: -26.149 | AF22: -273.352 | AH22: -231.855 | AI22: 0.788
B23: Accounts payable | D23: 46.591 | E23: -49.496 | F23: 94.882 | G23: 142.598 | H23: 234.575 | J23: -17.206 | K23: -32.393 | L23: 114.105 | M23: 118.587 | N23: 183.093 | P23: 13.993 | Q23: -23.765 | R23: 65.916 | S23: 34.152 | T23: 90.296 | V23: -119.461 | W23: -95.7 | X23: 85.706 | Y23: 265.369 | Z23: 135.914 | AB23: -186.929 | AC23: 97.446 | AD23: 248.891 | AE23: 46.098 | AF23: 205.506 | AH23: -155.239 | AI23: -117.645
B24: Other | D24: 0 | E24: 0 | F24: 0 | G24: -23.75 | H24: -23.75 | J24: -22.771 | K24: -127.473 | L24: 26.35 | M24: 18.611 | N24: -105.283 | P24: -115.909 | Q24: 49.202 | R24: -52.783 | S24: 66.828 | T24: -52.662 | V24: -52.33 | W24: 40.881 | X24: 1.544 | Y24: 41.226 | Z24: 31.321 | AB24: -43.684 | AC24: -105.526 | AD24: -146.276 | AE24: 114.068 | AF24: -181.418 | AH24: -111.201 | AI24: -178.117
B25: Cash provided by operating activities | D25: 5.815 | E25: -17.101 | F25: 55.967 | G25: 175.689 | H25: 220.37 | J25: 38.151 | K25: 33.76 | L25: 33.154 | M25: 136.873 | N25: 241.938 | P25: -4.515 | Q25: 55.672 | R25: 4.291 | S25: 82.802 | T25: 138.25 | V25: -76.64 | W25: 77.43 | X25: 114.613 | Y25: 297.189 | Z25: 412.592 | AB25: -55.735 | AC25: 90.064 | AD25: -34.927 | AE25: 364.553 | AF25: 363.955 | AH25: -104.146 | AI25: 87.247
A27: x | B27: Investing activities:
B28: Purchase of fixed assets and intangibles | D28: -14.393 | E28: -7.043 | F28: -9.359 | G28: -15.39 | H28: -46.185 | J28: -12.545 | K28: -29.554 | L28: -62.738 | M28: -64.044 | N28: -168.881 | P28: -40.835 | Q28: -56.004 | R28: -63.697 | S28: -72.607 | T28: -233.143 | V28: -50.998 | W28: -74.524 | X28: -47.712 | Y28: -61.967 | Z28: -235.201 | AB28: -41.514 | AC28: -66.795 | AD28: -115.464 | AE28: -195.189 | AF28: -418.962 | AH28: -84.39 | AI28: -94.177
B29: Disposal of fixed assets and intangibles | D29: 0 | E29: 0 | F29: 0.345 | G29: 0.932 | H29: 1.277 | J29: 0.175 | K29: 0.213 | L29: 0.047 | M29: 1.037 | N29: 1.472 | P29: 0 | Q29: 0 | R29: 0 | S29: 0 | T29: 0 | V29: 0 | W29: 0 | X29: 0 | Y29: 0 | Z29: 0 | AB29: 0 | AC29: 0 | AD29: 0 | AE29: 0 | AF29: 0 | AH29: 0 | AI29: 0
B30: Acquisitions | D30: 0 | E30: 0 | F30: 0 | G30: -63.404 | H30: -63.404 | J30: -11.328 | K30: 0.017 | L30: -85.01 | M30: -50 | N30: -146.321 | P30: -49.983 | Q30: -6.8 | R30: -32.352 | S30: -0.6 | T30: -89.735 | V30: -130.311 | W30: -64.068 | X30: -0.243 | Y30: -0.244 | Z30: -194.866 | AB30: 0 | AC30: -8.8 | AD30: 7.821 | AE30: 0 | AF30: -0.979 | AH30: 0 | AI30: 0
B31: Divestitures | D31: 0 | E31: 0 | F31: 0 | G31: 0 | H31: 0 | J31: 0 | K31: 0 | L31: 0 | M31: 0 | N31: 0 | P31: 0 | Q31: 0 | R31: 0 | S31: 0 | T31: 0 | V31: 0 | W31: 0 | X31: 0 | Y31: 0 | Z31: 0 | AB31: 0 | AC31: 0 | AD31: 0 | AE31: 0 | AF31: 0 | AH31: 0 | AI31: 0
B32: Joint Ventures | D32: 0 | E32: 0 | F32: 0 | G32: 0 | H32: 0 | J32: 0 | K32: 0 | L32: 0 | M32: 0 | N32: 0 | P32: 0 | Q32: 0 | R32: 0 | S32: 0 | T32: 0 | V32: 0 | W32: 0 | X32: 0 | Y32: 0 | Z32: 0 | AB32: 0 | AC32: 0 | AD32: 0 | AE32: 0 | AF32: 0 | AH32: 0 | AI32: 0
B33: Increase in long-term investments | D33: 0 | E33: 0 | F33: 0 | G33: 0 | H33: 0 | J33: 0 | K33: 0 | L33: 0 | M33: 0 | N33: 0 | P33: 0 | Q33: 0 | R33: 0 | S33: 0 | T33: 0 | V33: 0 | W33: 0 | X33: 0 | Y33: 0 | Z33: 0 | AB33: 0 | AC33: -1845.822 | AD33: -2072.116 | AE33: 0 | AF33: 0 | AH33: 0 | AI33: 0
B34: Decrease in long-term investments | D34: 0 | E34: 0 | F34: 0 | G34: 0 | H34: 0 | J34: 0 | K34: 0 | L34: 0 | M34: 0 | N34: 0 | P34: 0 | Q34: 0 | R34: 0 | S34: 0 | T34: 0 | V34: 0 | W34: 0 | X34: 0 | Y34: 0 | Z34: 0 | AB34: 0 | AC34: 2031.76 | AD34: 2340.538 | AE34: 0 | AF34: 0 | AH34: 0 | AI34: 0
B35: Other investing inflows/(outflows) | D35: -345.505 | E35: 62.704 | F35: 1.598 | G35: 92.179 | H35: -189.024 | J35: 176.63 | K35: 34.083 | L35: 71.089 | M35: 21.156 | N35: 302.958 | P35: -355.406 | Q35: -27.914 | R35: 166.217 | S35: 32.733 | T35: -184.37 | V35: -243.191 | W35: 104.424 | X35: 38.156 | Y35: -83.311 | Z35: -183.922 | AB35: 138.635 | AC35: -138.635 | AD35: 467.861 | AE35: 22.788 | AF35: 945.009 | AH35: -403.399 | AI35: 340.577
B36: Cash provided by/(used in) investing activities | D36: -359.898 | E36: 55.661 | F36: -7.416 | G36: 14.317 | H36: -297.336 | J36: 152.932 | K36: 4.759 | L36: -76.612 | M36: -91.851 | N36: -10.772 | P36: -446.224 | Q36: -90.718 | R36: 70.168 | S36: -40.474 | T36: -507.248 | V36: -424.5 | W36: -34.168 | X36: -9.799 | Y36: -145.522 | Z36: -613.989 | AB36: 97.121 | AC36: -28.292 | AD36: 628.64 | AE36: -172.401 | AF36: 525.068 | AH36: -487.789 | AI36: 246.4
A38: x | B38: Financing activities:
B39: Payment of dividends | D39: -22.675 | E39: 0 | F39: 0 | G39: -148.317 | H39: -170.992 | J39: 0 | K39: 0 | L39: -32.172 | M39: 0 | N39: -32.172 | P39: -60 | Q39: 0 | R39: -69.683 | S39: -50 | T39: -179.683 | V39: -82.107 | W39: 0 | X39: -102.148 | Y39: -112.047 | Z39: -296.302 | AB39: 0 | AC39: 0 | AD39: -60 | AE39: -118.749 | AF39: -178.749 | AH39: 0 | AI39: 0
B40: Issuance (repurchase) of common shares | D40: -2.632 | E40: 0 | F40: -1.04 | G40: 0 | H40: -3.672 | J40: 0 | K40: -50.356 | L40: 39.19 | M40: -3.009 | N40: -14.175 | P40: -36.776 | Q40: 36.776 | R40: -24.377 | S40: -1.68 | T40: -26.057 | V40: -6.191 | W40: -3.024 | X40: 0 | Y40: -2.033 | Z40: -11.248 | AB40: 0 | AC40: 0 | AD40: 0 | AE40: 0 | AF40: 0 | AH40: 0 | AI40: 0
B41: Cash from (repayment) of short-term debt | D41: 0 | E41: 0 | F41: 0 | G41: 0 | H41: 0 | J41: 0 | K41: 0 | L41: 0 | M41: 0 | N41: 0 | P41: 0 | Q41: 0 | R41: 0 | S41: 0 | T41: 0 | V41: 0 | W41: 0 | X41: 0 | Y41: 0 | Z41: 0 | AB41: 0 | AC41: 0 | AD41: 0 | AE41: 0 | AF41: 0 | AH41: 0 | AI41: 0
B42: Proceeds from issuance of long-term debt | D42: 0 | E42: 0 | F42: 0 | G42: 0 | H42: 0 | J42: 0 | K42: 0 | L42: 0 | M42: 0 | N42: 0 | P42: 0 | Q42: 0 | R42: 0 | S42: 0 | T42: 0 | V42: 0 | W42: 0 | X42: 0 | Y42: 0 | Z42: 0 | AB42: 0 | AC42: 0 | AD42: 0 | AE42: 0 | AF42: 0 | AH42: 0 | AI42: 0
B43: Repayments of long-term debt | D43: 0 | E43: 0 | F43: 0 | G43: 0 | H43: 0 | J43: 0 | K43: 0 | L43: 0 | M43: 0 | N43: 0 | P43: 0 | Q43: 0 | R43: 0 | S43: 0 | T43: 0 | V43: 0 | W43: 0 | X43: 0 | Y43: 0 | Z43: 0 | AB43: 0 | AC43: 0 | AD43: 0 | AE43: 0 | AF43: 0 | AH43: 0 | AI43: 0
B44: Other financing inflows/(outflows) | D44: 373.178 | E44: -33.191 | F44: -46.974 | G44: -16.898 | H44: 276.115 | J44: -6.782 | K44: -141.136 | L44: 17.074 | M44: -56.322 | N44: -187.166 | P44: 612.396 | Q44: -22.633 | R44: 15.914 | S44: -37.511 | T44: 568.166 | V44: 642.414 | W44: -52.234 | X44: -14.284 | Y44: -25.416 | Z44: 550.48 | AB44: -61.04 | AC44: -67.385 | AD44: -425.838 | AE44: -58.759 | AF44: -613.022 | AH44: 547.612 | AI44: -289.805
B45: Cash provided by/(used in) financing activities | D45: 347.871 | E45: -33.191 | F45: -48.014 | G45: -165.215 | H45: 101.451 | J45: -6.782 | K45: -191.492 | L45: 24.092 | M45: -59.331 | N45: -233.513 | P45: 515.62 | Q45: 14.143 | R45: -78.146 | S45: -89.191 | T45: 362.426 | V45: 554.116 | W45: -55.258 | X45: -116.432 | Y45: -139.496 | Z45: 242.93 | AB45: -61.04 | AC45: -67.385 | AD45: -485.838 | AE45: -177.508 | AF45: -791.771 | AH45: 547.612 | AI45: -289.805
A47: x | B47: Effects of foreign exchange | D47: 0 | E47: 0 | F47: 0 | G47: 0.004 | H47: 0.004 | J47: 0 | K47: 0 | L47: -1.212 | M47: -0.988 | N47: -2.2 | P47: 8.116 | Q47: -4.162 | R47: -3.062 | S47: 0.756 | T47: 1.648 | V47: 1.801 | W47: 1.859 | X47: -1.149 | Y47: 0.446 | Z47: 2.957 | AB47: -0.627 | AC47: 6.463 | AD47: 0.678 | AE47: 4.078 | AF47: 10.592 | AH47: -0.876 | AI47: -2.438
A49: x | B49: Increase/(Decrease) in cash and cash equivalents | D49: -6.212 | E49: 5.369 | F49: 0.537 | G49: 24.795 | H49: 24.489 | J49: 184.301 | K49: -152.973 | L49: -20.578 | M49: -15.297 | N49: -4.547 | P49: 72.997 | Q49: -25.065 | R49: -6.749 | S49: -46.107 | T49: -4.924 | V49: 54.777 | W49: -10.137 | X49: -12.767 | Y49: 12.617 | Z49: 44.49 | AB49: -20.281 | AC49: 0.85 | AD49: 108.553 | AE49: 18.722 | AF49: 107.844 | AH49: -45.199 | AI49: 41.404
B50: Cash and cash equivalents, ending balances | D50: 7.597 | E50: 12.965 | F50: 13.502 | G50: 38.297 | H50: 38.297 | J50: 222.598 | K50: 69.625 | L50: 49.047 | M50: 33.75 | N50: 33.75 | P50: 106.747 | Q50: 81.682 | R50: 74.933 | S50: 28.826 | T50: 28.826 | V50: 83.603 | W50: 73.466 | X50: 60.699 | Y50: 73.316 | Z50: 73.316 | AB50: 53.035 | AC50: 53.885 | AD50: 162.438 | AE50: 181.16 | AF50: 181.16 | AH50: 135.961 | AI50: 177.365

Sheet Error Check
B7: Income Statement – Sum of the Quarters = FY | D7: =F7 -> 2020 | E7: =F7 -> 2020 | F7: 2020 | G7: =F7 -> 2020 | H7: =F7 -> 2020 | J7: =L7 -> 2021 | K7: =L7 -> 2021 | L7: 2021 | M7: =L7 -> 2021 | N7: =L7 -> 2021 | P7: =R7 -> 2022 | Q7: =R7 -> 2022 | R7: 2022 | S7: =R7 -> 2022 | T7: =R7 -> 2022 | V7: =X7 -> 2023 | W7: =X7 -> 2023 | X7: 2023 | Y7: =X7 -> 2023 | Z7: =X7 -> 2023 | AB7: =AD7 -> 2024 | AC7: =AD7 -> 2024 | AD7: 2024 | AE7: =AD7 -> 2024 | AF7: =AD7 -> 2024 | AH7: =AJ7 -> 2025 | AI7: =AJ7 -> 2025 | AJ7: 2025 | AK7: =AJ7 -> 2025 | AL7: =AJ7 -> 2025 | AN7: =AP7 -> 2025 | AO7: =AP7 -> 2025 | AP7: 2025 | AQ7: =AP7 -> 2025 | AR7: =AP7 -> 2025
D8: 2020 | J8: =D8+1 -> 2021 | P8: =J8+1 -> 2022 | V8: =P8+1 -> 2023 | AB8: =V8+1 -> 2024 | AH8: =AB8+1 -> 2025 | AN8: =AH8+1 -> 2026 | AT8: =AN8+1 -> 2027 | AV8: =+AT8+1 -> 2028 | AX8: =+AV8+1 -> 2029
D9: Q1 | E9: Q2 | F9: Q3 | G9: Q4 | H9: FY | J9: Q1 | K9: Q2 | L9: Q3 | M9: Q4 | N9: FY | P9: Q1 | Q9: Q2 | R9: Q3 | S9: Q4 | T9: FY | V9: Q1 | W9: Q2 | X9: Q3 | Y9: Q4 | Z9: FY | AB9: Q1 | AC9: Q2 | AD9: Q3 | AE9: Q4 | AF9: FY | AH9: Q1 | AI9: Q2 | AJ9: Q3 | AK9: Q4 | AL9: FY | AN9: Q1 | AO9: Q2 | AP9: Q3 | AQ9: Q4 | AR9: FY | AT9: FY | AV9: FY | AX9: FY
A12: x | B12: Revenue:
B13: Segment 1 | H13: =IF(ROUND(SUM(IS!D13:G13),1)=ROUND(IS!H13,1),"OK","ERROR") -> OK | N13: =IF(ROUND(SUM(IS!J13:M13),1)=ROUND(IS!N13,1),"OK","ERROR") -> OK | T13: =IF(ROUND(SUM(IS!P13:S13),1)=ROUND(IS!T13,1),"OK","ERROR") -> OK | Z13: =IF(ROUND(SUM(IS!V13:Y13),1)=ROUND(IS!Z13,1),"OK","ERROR") -> OK | AF13: =IF(ROUND(SUM(IS!AB13:AE13),1)=ROUND(IS!AF13,1),"OK","ERROR") -> OK | AL13: =IF(ROUND(SUM(IS!AH13:AK13),1)=ROUND(IS!AL13,1),"OK","ERROR") -> OK | AR13: =IF(ROUND(SUM(IS!AN13:AQ13),1)=ROUND(IS!AR13,1),"OK","ERROR") -> OK
B14: Segment 2 | H14: =IF(ROUND(SUM(IS!D14:G14),1)=ROUND(IS!H14,1),"OK","ERROR") -> OK | N14: =IF(ROUND(SUM(IS!J14:M14),1)=ROUND(IS!N14,1),"OK","ERROR") -> OK | T14: =IF(ROUND(SUM(IS!P14:S14),1)=ROUND(IS!T14,1),"OK","ERROR") -> OK | Z14: =IF(ROUND(SUM(IS!V14:Y14),1)=ROUND(IS!Z14,1),"OK","ERROR") -> OK | AF14: =IF(ROUND(SUM(IS!AB14:AE14),1)=ROUND(IS!AF14,1),"OK","ERROR") -> OK | AL14: =IF(ROUND(SUM(IS!AH14:AK14),1)=ROUND(IS!AL14,1),"OK","ERROR") -> OK | AR14: =IF(ROUND(SUM(IS!AN14:AQ14),1)=ROUND(IS!AR14,1),"OK","ERROR") -> OK
B15: Segment 3 | H15: =IF(ROUND(SUM(IS!D15:G15),1)=ROUND(IS!H15,1),"OK","ERROR") -> OK | N15: =IF(ROUND(SUM(IS!J15:M15),1)=ROUND(IS!N15,1),"OK","ERROR") -> OK | T15: =IF(ROUND(SUM(IS!P15:S15),1)=ROUND(IS!T15,1),"OK","ERROR") -> OK | Z15: =IF(ROUND(SUM(IS!V15:Y15),1)=ROUND(IS!Z15,1),"OK","ERROR") -> OK | AF15: =IF(ROUND(SUM(IS!AB15:AE15),1)=ROUND(IS!AF15,1),"OK","ERROR") -> OK | AL15: =IF(ROUND(SUM(IS!AH15:AK15),1)=ROUND(IS!AL15,1),"OK","ERROR") -> OK | AR15: =IF(ROUND(SUM(IS!AN15:AQ15),1)=ROUND(IS!AR15,1),"OK","ERROR") -> OK
B16: Segment 4 | H16: =IF(ROUND(SUM(IS!D16:G16),1)=ROUND(IS!H16,1),"OK","ERROR") -> OK | N16: =IF(ROUND(SUM(IS!J16:M16),1)=ROUND(IS!N16,1),"OK","ERROR") -> OK | T16: =IF(ROUND(SUM(IS!P16:S16),1)=ROUND(IS!T16,1),"OK","ERROR") -> OK | Z16: =IF(ROUND(SUM(IS!V16:Y16),1)=ROUND(IS!Z16,1),"OK","ERROR") -> OK | AF16: =IF(ROUND(SUM(IS!AB16:AE16),1)=ROUND(IS!AF16,1),"OK","ERROR") -> OK | AL16: =IF(ROUND(SUM(IS!AH16:AK16),1)=ROUND(IS!AL16,1),"OK","ERROR") -> OK | AR16: =IF(ROUND(SUM(IS!AN16:AQ16),1)=ROUND(IS!AR16,1),"OK","ERROR") -> OK
B17: Segment 5 | H17: =IF(ROUND(SUM(IS!D17:G17),1)=ROUND(IS!H17,1),"OK","ERROR") -> OK | N17: =IF(ROUND(SUM(IS!J17:M17),1)=ROUND(IS!N17,1),"OK","ERROR") -> OK | T17: =IF(ROUND(SUM(IS!P17:S17),1)=ROUND(IS!T17,1),"OK","ERROR") -> OK | Z17: =IF(ROUND(SUM(IS!V17:Y17),1)=ROUND(IS!Z17,1),"OK","ERROR") -> OK | AF17: =IF(ROUND(SUM(IS!AB17:AE17),1)=ROUND(IS!AF17,1),"OK","ERROR") -> OK | AL17: =IF(ROUND(SUM(IS!AH17:AK17),1)=ROUND(IS!AL17,1),"OK","ERROR") -> OK | AR17: =IF(ROUND(SUM(IS!AN17:AQ17),1)=ROUND(IS!AR17,1),"OK","ERROR") -> OK
B18: Total revenue | H18: =IF(ROUND(SUM(IS!D18:G18),1)=ROUND(IS!H18,1),"OK","ERROR") -> OK | N18: =IF(ROUND(SUM(IS!J18:M18),1)=ROUND(IS!N18,1),"OK","ERROR") -> OK | T18: =IF(ROUND(SUM(IS!P18:S18),1)=ROUND(IS!T18,1),"OK","ERROR") -> OK | Z18: =IF(ROUND(SUM(IS!V18:Y18),1)=ROUND(IS!Z18,1),"OK","ERROR") -> OK | AF18: =IF(ROUND(SUM(IS!AB18:AE18),1)=ROUND(IS!AF18,1),"OK","ERROR") -> OK | AL18: =IF(ROUND(SUM(IS!AH18:AK18),1)=ROUND(IS!AL18,1),"OK","ERROR") -> ERROR | AR18: =IF(ROUND(SUM(IS!AN18:AQ18),1)=ROUND(IS!AR18,1),"OK","ERROR") -> OK
A20: x | B20: Cost of revenue:
B21: Cost of goods and services | H21: =IF(ROUND(SUM(IS!D21:G21),1)=ROUND(IS!H21,1),"OK","ERROR") -> OK | N21: =IF(ROUND(SUM(IS!J21:M21),1)=ROUND(IS!N21,1),"OK","ERROR") -> OK | T21: =IF(ROUND(SUM(IS!P21:S21),1)=ROUND(IS!T21,1),"OK","ERROR") -> OK | Z21: =IF(ROUND(SUM(IS!V21:Y21),1)=ROUND(IS!Z21,1),"OK","ERROR") -> OK | AF21: =IF(ROUND(SUM(IS!AB21:AE21),1)=ROUND(IS!AF21,1),"OK","ERROR") -> OK | AL21: =IF(ROUND(SUM(IS!AH21:AK21),1)=ROUND(IS!AL21,1),"OK","ERROR") -> ERROR | AR21: =IF(ROUND(SUM(IS!AN21:AQ21),1)=ROUND(IS!AR21,1),"OK","ERROR") -> OK
B22: Depreciation & amortization | H22: =IF(ROUND(SUM(IS!D22:G22),1)=ROUND(IS!H22,1),"OK","ERROR") -> OK | N22: =IF(ROUND(SUM(IS!J22:M22),1)=ROUND(IS!N22,1),"OK","ERROR") -> OK | T22: =IF(ROUND(SUM(IS!P22:S22),1)=ROUND(IS!T22,1),"OK","ERROR") -> OK | Z22: =IF(ROUND(SUM(IS!V22:Y22),1)=ROUND(IS!Z22,1),"OK","ERROR") -> OK | AF22: =IF(ROUND(SUM(IS!AB22:AE22),1)=ROUND(IS!AF22,1),"OK","ERROR") -> OK | AL22: =IF(ROUND(SUM(IS!AH22:AK22),1)=ROUND(IS!AL22,1),"OK","ERROR") -> OK | AR22: =IF(ROUND(SUM(IS!AN22:AQ22),1)=ROUND(IS!AR22,1),"OK","ERROR") -> OK
B23: Total cost of revenue | H23: =IF(ROUND(SUM(IS!D23:G23),1)=ROUND(IS!H23,1),"OK","ERROR") -> OK | N23: =IF(ROUND(SUM(IS!J23:M23),1)=ROUND(IS!N23,1),"OK","ERROR") -> OK | T23: =IF(ROUND(SUM(IS!P23:S23),1)=ROUND(IS!T23,1),"OK","ERROR") -> OK | Z23: =IF(ROUND(SUM(IS!V23:Y23),1)=ROUND(IS!Z23,1),"OK","ERROR") -> OK | AF23: =IF(ROUND(SUM(IS!AB23:AE23),1)=ROUND(IS!AF23,1),"OK","ERROR") -> OK | AL23: =IF(ROUND(SUM(IS!AH23:AK23),1)=ROUND(IS!AL23,1),"OK","ERROR") -> ERROR | AR23: =IF(ROUND(SUM(IS!AN23:AQ23),1)=ROUND(IS!AR23,1),"OK","ERROR") -> OK
B24: Gross margin | H24: =IF(ROUND(SUM(IS!D24:G24),1)=ROUND(IS!H24,1),"OK","ERROR") -> OK | N24: =IF(ROUND(SUM(IS!J24:M24),1)=ROUND(IS!N24,1),"OK","ERROR") -> OK | T24: =IF(ROUND(SUM(IS!P24:S24),1)=ROUND(IS!T24,1),"OK","ERROR") -> OK | Z24: =IF(ROUND(SUM(IS!V24:Y24),1)=ROUND(IS!Z24,1),"OK","ERROR") -> OK | AF24: =IF(ROUND(SUM(IS!AB24:AE24),1)=ROUND(IS!AF24,1),"OK","ERROR") -> OK | AL24: =IF(ROUND(SUM(IS!AH24:AK24),1)=ROUND(IS!AL24,1),"OK","ERROR") -> ERROR | AR24: =IF(ROUND(SUM(IS!AN24:AQ24),1)=ROUND(IS!AR24,1),"OK","ERROR") -> OK
A26: x | B26: Operating expenses:
B27: Selling, general and administrative | H27: =IF(ROUND(SUM(IS!D27:G27),1)=ROUND(IS!H27,1),"OK","ERROR") -> ERROR | N27: =IF(ROUND(SUM(IS!J27:M27),1)=ROUND(IS!N27,1),"OK","ERROR") -> OK | T27: =IF(ROUND(SUM(IS!P27:S27),1)=ROUND(IS!T27,1),"OK","ERROR") -> OK | Z27: =IF(ROUND(SUM(IS!V27:Y27),1)=ROUND(IS!Z27,1),"OK","ERROR") -> OK | AF27: =IF(ROUND(SUM(IS!AB27:AE27),1)=ROUND(IS!AF27,1),"OK","ERROR") -> OK | AL27: =IF(ROUND(SUM(IS!AH27:AK27),1)=ROUND(IS!AL27,1),"OK","ERROR") -> ERROR | AR27: =IF(ROUND(SUM(IS!AN27:AQ27),1)=ROUND(IS!AR27,1),"OK","ERROR") -> OK
B28: Depreciation and amortization | H28: =IF(ROUND(SUM(IS!D28:G28),1)=ROUND(IS!H28,1),"OK","ERROR") -> OK | N28: =IF(ROUND(SUM(IS!J28:M28),1)=ROUND(IS!N28,1),"OK","ERROR") -> OK | T28: =IF(ROUND(SUM(IS!P28:S28),1)=ROUND(IS!T28,1),"OK","ERROR") -> OK | Z28: =IF(ROUND(SUM(IS!V28:Y28),1)=ROUND(IS!Z28,1),"OK","ERROR") -> OK | AF28: =IF(ROUND(SUM(IS!AB28:AE28),1)=ROUND(IS!AF28,1),"OK","ERROR") -> OK | AL28: =IF(ROUND(SUM(IS!AH28:AK28),1)=ROUND(IS!AL28,1),"OK","ERROR") -> OK | AR28: =IF(ROUND(SUM(IS!AN28:AQ28),1)=ROUND(IS!AR28,1),"OK","ERROR") -> OK
B29: Research and development | H29: =IF(ROUND(SUM(IS!D29:G29),1)=ROUND(IS!H29,1),"OK","ERROR") -> ERROR | N29: =IF(ROUND(SUM(IS!J29:M29),1)=ROUND(IS!N29,1),"OK","ERROR") -> ERROR | T29: =IF(ROUND(SUM(IS!P29:S29),1)=ROUND(IS!T29,1),"OK","ERROR") -> OK | Z29: =IF(ROUND(SUM(IS!V29:Y29),1)=ROUND(IS!Z29,1),"OK","ERROR") -> OK | AF29: =IF(ROUND(SUM(IS!AB29:AE29),1)=ROUND(IS!AF29,1),"OK","ERROR") -> OK | AL29: =IF(ROUND(SUM(IS!AH29:AK29),1)=ROUND(IS!AL29,1),"OK","ERROR") -> OK | AR29: =IF(ROUND(SUM(IS!AN29:AQ29),1)=ROUND(IS!AR29,1),"OK","ERROR") -> OK
B30: Other operating expenses | H30: =IF(ROUND(SUM(IS!D30:G30),1)=ROUND(IS!H30,1),"OK","ERROR") -> ERROR | N30: =IF(ROUND(SUM(IS!J30:M30),1)=ROUND(IS!N30,1),"OK","ERROR") -> ERROR | T30: =IF(ROUND(SUM(IS!P30:S30),1)=ROUND(IS!T30,1),"OK","ERROR") -> OK | Z30: =IF(ROUND(SUM(IS!V30:Y30),1)=ROUND(IS!Z30,1),"OK","ERROR") -> OK | AF30: =IF(ROUND(SUM(IS!AB30:AE30),1)=ROUND(IS!AF30,1),"OK","ERROR") -> ERROR | AL30: =IF(ROUND(SUM(IS!AH30:AK30),1)=ROUND(IS!AL30,1),"OK","ERROR") -> ERROR | AR30: =IF(ROUND(SUM(IS!AN30:AQ30),1)=ROUND(IS!AR30,1),"OK","ERROR") -> OK
B31: Total operating expenses | H31: =IF(ROUND(SUM(IS!D31:G31),1)=ROUND(IS!H31,1),"OK","ERROR") -> ERROR | N31: =IF(ROUND(SUM(IS!J31:M31),1)=ROUND(IS!N31,1),"OK","ERROR") -> ERROR | T31: =IF(ROUND(SUM(IS!P31:S31),1)=ROUND(IS!T31,1),"OK","ERROR") -> OK | Z31: =IF(ROUND(SUM(IS!V31:Y31),1)=ROUND(IS!Z31,1),"OK","ERROR") -> OK | AF31: =IF(ROUND(SUM(IS!AB31:AE31),1)=ROUND(IS!AF31,1),"OK","ERROR") -> ERROR | AL31: =IF(ROUND(SUM(IS!AH31:AK31),1)=ROUND(IS!AL31,1),"OK","ERROR") -> ERROR | AR31: =IF(ROUND(SUM(IS!AN31:AQ31),1)=ROUND(IS!AR31,1),"OK","ERROR") -> OK
B32: Other operating income | H32: =IF(ROUND(SUM(IS!D32:G32),1)=ROUND(IS!H32,1),"OK","ERROR") -> ERROR | N32: =IF(ROUND(SUM(IS!J32:M32),1)=ROUND(IS!N32,1),"OK","ERROR") -> ERROR | T32: =IF(ROUND(SUM(IS!P32:S32),1)=ROUND(IS!T32,1),"OK","ERROR") -> OK | Z32: =IF(ROUND(SUM(IS!V32:Y32),1)=ROUND(IS!Z32,1),"OK","ERROR") -> OK | AF32: =IF(ROUND(SUM(IS!AB32:AE32),1)=ROUND(IS!AF32,1),"OK","ERROR") -> ERROR | AL32: =IF(ROUND(SUM(IS!AH32:AK32),1)=ROUND(IS!AL32,1),"OK","ERROR") -> ERROR | AR32: =IF(ROUND(SUM(IS!AN32:AQ32),1)=ROUND(IS!AR32,1),"OK","ERROR") -> OK
B33: Operating income | H33: =IF(ROUND(SUM(IS!D33:G33),1)=ROUND(IS!H33,1),"OK","ERROR") -> OK | N33: =IF(ROUND(SUM(IS!J33:M33),1)=ROUND(IS!N33,1),"OK","ERROR") -> ERROR | T33: =IF(ROUND(SUM(IS!P33:S33),1)=ROUND(IS!T33,1),"OK","ERROR") -> OK | Z33: =IF(ROUND(SUM(IS!V33:Y33),1)=ROUND(IS!Z33,1),"OK","ERROR") -> OK | AF33: =IF(ROUND(SUM(IS!AB33:AE33),1)=ROUND(IS!AF33,1),"OK","ERROR") -> ERROR | AL33: =IF(ROUND(SUM(IS!AH33:AK33),1)=ROUND(IS!AL33,1),"OK","ERROR") -> ERROR | AR33: =IF(ROUND(SUM(IS!AN33:AQ33),1)=ROUND(IS!AR33,1),"OK","ERROR") -> OK
A35: x | B35: Non-operating (income) loss:
B36: Interest expense | H36: =IF(ROUND(SUM(IS!D36:G36),1)=ROUND(IS!H36,1),"OK","ERROR") -> OK | N36: =IF(ROUND(SUM(IS!J36:M36),1)=ROUND(IS!N36,1),"OK","ERROR") -> OK | T36: =IF(ROUND(SUM(IS!P36:S36),1)=ROUND(IS!T36,1),"OK","ERROR") -> OK | Z36: =IF(ROUND(SUM(IS!V36:Y36),1)=ROUND(IS!Z36,1),"OK","ERROR") -> OK | AF36: =IF(ROUND(SUM(IS!AB36:AE36),1)=ROUND(IS!AF36,1),"OK","ERROR") -> OK | AL36: =IF(ROUND(SUM(IS!AH36:AK36),1)=ROUND(IS!AL36,1),"OK","ERROR") -> ERROR | AR36: =IF(ROUND(SUM(IS!AN36:AQ36),1)=ROUND(IS!AR36,1),"OK","ERROR") -> OK
B37: Interest income | H37: =IF(ROUND(SUM(IS!D37:G37),1)=ROUND(IS!H37,1),"OK","ERROR") -> OK | N37: =IF(ROUND(SUM(IS!J37:M37),1)=ROUND(IS!N37,1),"OK","ERROR") -> OK | T37: =IF(ROUND(SUM(IS!P37:S37),1)=ROUND(IS!T37,1),"OK","ERROR") -> OK | Z37: =IF(ROUND(SUM(IS!V37:Y37),1)=ROUND(IS!Z37,1),"OK","ERROR") -> OK | AF37: =IF(ROUND(SUM(IS!AB37:AE37),1)=ROUND(IS!AF37,1),"OK","ERROR") -> OK | AL37: =IF(ROUND(SUM(IS!AH37:AK37),1)=ROUND(IS!AL37,1),"OK","ERROR") -> ERROR | AR37: =IF(ROUND(SUM(IS!AN37:AQ37),1)=ROUND(IS!AR37,1),"OK","ERROR") -> OK
A38: x | B38: Net interest (income) expense | H38: =IF(ROUND(SUM(IS!D38:G38),1)=ROUND(IS!H38,1),"OK","ERROR") -> OK | N38: =IF(ROUND(SUM(IS!J38:M38),1)=ROUND(IS!N38,1),"OK","ERROR") -> OK | T38: =IF(ROUND(SUM(IS!P38:S38),1)=ROUND(IS!T38,1),"OK","ERROR") -> OK | Z38: =IF(ROUND(SUM(IS!V38:Y38),1)=ROUND(IS!Z38,1),"OK","ERROR") -> OK | AF38: =IF(ROUND(SUM(IS!AB38:AE38),1)=ROUND(IS!AF38,1),"OK","ERROR") -> OK | AL38: =IF(ROUND(SUM(IS!AH38:AK38),1)=ROUND(IS!AL38,1),"OK","ERROR") -> ERROR | AR38: =IF(ROUND(SUM(IS!AN38:AQ38),1)=ROUND(IS!AR38,1),"OK","ERROR") -> OK
B39: Foreign exchange (gains) losses | H39: =IF(ROUND(SUM(IS!D39:G39),1)=ROUND(IS!H39,1),"OK","ERROR") -> OK | N39: =IF(ROUND(SUM(IS!J39:M39),1)=ROUND(IS!N39,1),"OK","ERROR") -> OK | T39: =IF(ROUND(SUM(IS!P39:S39),1)=ROUND(IS!T39,1),"OK","ERROR") -> ERROR | Z39: =IF(ROUND(SUM(IS!V39:Y39),1)=ROUND(IS!Z39,1),"OK","ERROR") -> OK | AF39: =IF(ROUND(SUM(IS!AB39:AE39),1)=ROUND(IS!AF39,1),"OK","ERROR") -> OK | AL39: =IF(ROUND(SUM(IS!AH39:AK39),1)=ROUND(IS!AL39,1),"OK","ERROR") -> ERROR | AR39: =IF(ROUND(SUM(IS!AN39:AQ39),1)=ROUND(IS!AR39,1),"OK","ERROR") -> OK
B40: Other non-operating (income) expenses | H40: =IF(ROUND(SUM(IS!D40:G40),1)=ROUND(IS!H40,1),"OK","ERROR") -> OK | N40: =IF(ROUND(SUM(IS!J40:M40),1)=ROUND(IS!N40,1),"OK","ERROR") -> OK | T40: =IF(ROUND(SUM(IS!P40:S40),1)=ROUND(IS!T40,1),"OK","ERROR") -> OK | Z40: =IF(ROUND(SUM(IS!V40:Y40),1)=ROUND(IS!Z40,1),"OK","ERROR") -> OK | AF40: =IF(ROUND(SUM(IS!AB40:AE40),1)=ROUND(IS!AF40,1),"OK","ERROR") -> OK | AL40: =IF(ROUND(SUM(IS!AH40:AK40),1)=ROUND(IS!AL40,1),"OK","ERROR") -> ERROR | AR40: =IF(ROUND(SUM(IS!AN40:AQ40),1)=ROUND(IS!AR40,1),"OK","ERROR") -> OK
B41: Total non-operating expenses | H41: =IF(ROUND(SUM(IS!D41:G41),1)=ROUND(IS!H41,1),"OK","ERROR") -> OK | N41: =IF(ROUND(SUM(IS!J41:M41),1)=ROUND(IS!N41,1),"OK","ERROR") -> OK | T41: =IF(ROUND(SUM(IS!P41:S41),1)=ROUND(IS!T41,1),"OK","ERROR") -> ERROR | Z41: =IF(ROUND(SUM(IS!V41:Y41),1)=ROUND(IS!Z41,1),"OK","ERROR") -> OK | AF41: =IF(ROUND(SUM(IS!AB41:AE41),1)=ROUND(IS!AF41,1),"OK","ERROR") -> OK | AL41: =IF(ROUND(SUM(IS!AH41:AK41),1)=ROUND(IS!AL41,1),"OK","ERROR") -> ERROR | AR41: =IF(ROUND(SUM(IS!AN41:AQ41),1)=ROUND(IS!AR41,1),"OK","ERROR") -> OK
