Workbook
Name COOLFUCNTION: _xlfn.LAMBDA(_xldudf_BOARDFLARE_EXEC("workbook-settings:coolfucntion"))
Name COOLFUCNTION: _xlfn.LAMBDA(_xldudf_BOARDFLARE_EXEC("workbook-settings:coolfucntion"))
Name COOLFUCNTION: _xlfn.LAMBDA(_xldudf_BOARDFLARE_EXEC("workbook-settings:coolfucntion"))
Name COOLFUCNTION: _xlfn.LAMBDA(_xldudf_BOARDFLARE_EXEC("workbook-settings:coolfucntion"))
Name COOLFUCNTION: _xlfn.LAMBDA(_xldudf_BOARDFLARE_EXEC("workbook-settings:coolfucntion"))
Name COOLFUCNTION: _xlfn.LAMBDA(_xldudf_BOARDFLARE_EXEC("workbook-settings:coolfucntion"))
Name COOLFUCNTION: _xlfn.LAMBDA(_xldudf_BOARDFLARE_EXEC("workbook-settings:coolfucntion"))
Name COOLFUCNTION: _xlfn.LAMBDA(_xldudf_BOARDFLARE_EXEC("workbook-settings:coolfucntion"))
Name COOLFUCNTION: _xlfn.LAMBDA(_xldudf_BOARDFLARE_EXEC("workbook-settings:coolfucntion"))
Name COOLFUCNTION: _xlfn.LAMBDA(_xldudf_BOARDFLARE_EXEC("workbook-settings:coolfucntion"))
Name COOLFUCNTION: _xlfn.LAMBDA(_xldudf_BOARDFLARE_EXEC("workbook-settings:coolfucntion"))
Name Sectors: #REF!
Name Sectors: #REF!
Name Sectors: #REF!
Name Sectors: #REF!
Name Sectors: #REF!
Name Sectors: #REF!
Name Sectors: #REF!
Name Sectors: #REF!

Sheet Dashboard
C154: =+C155+1 -> 45979
C155: =+C156+1 -> 45978
C156: =+C157+1 -> 45977
C157: =+C158+1 -> 45976
C158: =+C159+1 -> 45975
C159: =+C160+1 -> 45974
C160: =+C161+1 -> 45973 | L160: =IF(FCFF!$R$157="Revenue Exit",FCFF!$AF$169,IF(FCFF!$R$157="EBITDA Exit",FCFF!Z169,FCFF!AL169)) -> #VALUE!
C161: =+C162+1 -> 45972
C162: =+C163+1 -> 45971 | E162: =IF(FCFF!$R$157="Revenue Exit",FCFF!$AF$169,IF(FCFF!$R$157="EBITDA Exit",FCFF!Z169,FCFF!AL169)) -> #VALUE!
C163: =+C164+1 -> 45970 | E163: =E164+($E$162-$E$193)/COUNTA($C$162:$C$192) -> #VALUE!
C164: =+C165+1 -> 45969 | E164: =E165+($E$162-$E$193)/COUNTA($C$162:$C$192) -> #VALUE!
C165: =+C166+1 -> 45968 | E165: =E166+($E$162-$E$193)/COUNTA($C$162:$C$192) -> #VALUE!
C166: =+C167+1 -> 45967 | E166: =E167+($E$162-$E$193)/COUNTA($C$162:$C$192) -> #VALUE!
C167: =+C168+1 -> 45966 | E167: =E168+($E$162-$E$193)/COUNTA($C$162:$C$192) -> #VALUE!
C168: =+C169+1 -> 45965 | E168: =E169+($E$162-$E$193)/COUNTA($C$162:$C$192) -> #VALUE!
C169: =+C170+1 -> 45964 | E169: =E170+($E$162-$E$193)/COUNTA($C$162:$C$192) -> #VALUE!
C170: =+C171+1 -> 45963 | E170: =E171+($E$162-$E$193)/COUNTA($C$162:$C$192) -> #VALUE!
C171: =+C172+1 -> 45962 | E171: =E172+($E$162-$E$193)/COUNTA($C$162:$C$192) -> #VALUE!
C172: =+C173+1 -> 45961 | E172: =E173+($E$162-$E$193)/COUNTA($C$162:$C$192) -> #VALUE!
C173: =+C174+1 -> 45960 | E173: =E174+($E$162-$E$193)/COUNTA($C$162:$C$192) -> #VALUE!
C174: =+C175+1 -> 45959 | E174: =E175+($E$162-$E$193)/COUNTA($C$162:$C$192) -> #VALUE!
... C192: =+C193+1 -> 45941 | E192: =E193+($E$162-$E$193)/COUNTA($C$162:$C$192) -> #VALUE!
B193: TODAY | C193: =+'Stock Data'!AM4 -> 45940 | D193: =_xlfn.XLOOKUP(C193,'Stock Data'!$AM$4:$AM$1051,'Stock Data'!$AN$4:$AN$1051) -> 111.54 | E193: =D193 -> 111.54
C194: =+'Stock Data'!AM5 -> 45939 | D194: =_xlfn.XLOOKUP(C194,'Stock Data'!$AM$4:$AM$1051,'Stock Data'!$AN$4:$AN$1051) -> 111.54
C195: =+'Stock Data'!AM6 -> 45938 | D195: =_xlfn.XLOOKUP(C195,'Stock Data'!$AM$4:$AM$1051,'Stock Data'!$AN$4:$AN$1051) -> 113.83
C196: =+'Stock Data'!AM7 -> 45937 | D196: =_xlfn.XLOOKUP(C196,'Stock Data'!$AM$4:$AM$1051,'Stock Data'!$AN$4:$AN$1051) -> 113.83
C197: =+'Stock Data'!AM8 -> 45936 | D197: =_xlfn.XLOOKUP(C197,'Stock Data'!$AM$4:$AM$1051,'Stock Data'!$AN$4:$AN$1051) -> 113.83
C198: =+'Stock Data'!AM9 -> 45935 | D198: =_xlfn.XLOOKUP(C198,'Stock Data'!$AM$4:$AM$1051,'Stock Data'!$AN$4:$AN$1051) -> 113.07
C199: =+'Stock Data'!AM10 -> 45934 | D199: =_xlfn.XLOOKUP(C199,'Stock Data'!$AM$4:$AM$1051,'Stock Data'!$AN$4:$AN$1051) -> 110.6
C200: =+'Stock Data'!AM11 -> 45933 | D200: =_xlfn.XLOOKUP(C200,'Stock Data'!$AM$4:$AM$1051,'Stock Data'!$AN$4:$AN$1051) -> 116.01
C201: =+'Stock Data'!AM12 -> 45932 | D201: =_xlfn.XLOOKUP(C201,'Stock Data'!$AM$4:$AM$1051,'Stock Data'!$AN$4:$AN$1051) -> 115.64
C202: =+'Stock Data'!AM13 -> 45931 | D202: =_xlfn.XLOOKUP(C202,'Stock Data'!$AM$4:$AM$1051,'Stock Data'!$AN$4:$AN$1051) -> 115.64
C203: =+'Stock Data'!AM14 -> 45930 | D203: =_xlfn.XLOOKUP(C203,'Stock Data'!$AM$4:$AM$1051,'Stock Data'!$AN$4:$AN$1051) -> 115.64
C204: =+'Stock Data'!AM15 -> 45929 | D204: =_xlfn.XLOOKUP(C204,'Stock Data'!$AM$4:$AM$1051,'Stock Data'!$AN$4:$AN$1051) -> 115.64
C205: =+'Stock Data'!AM16 -> 45928 | D205: =_xlfn.XLOOKUP(C205,'Stock Data'!$AM$4:$AM$1051,'Stock Data'!$AN$4:$AN$1051) -> 115.4
... C558: =+'Stock Data'!AM369 -> 45575 | D558: =_xlfn.XLOOKUP(C558,'Stock Data'!$AM$4:$AM$1051,'Stock Data'!$AN$4:$AN$1051) -> 68.45

Sheet Key Info
B7: Analysts | F7: LIS – Equity Research | J7: Stock Performance
B12: NAME, Co-Head of Equity Research | F12: Recommendation: | H12: Hold
B13: Bsc in XXX, ISEG – Ulisboa | F13: Target Price (FCFF):
B14: email@aln.iseg.ulisboa.pt | F14: Upside:
B15: Martim de Sousa Patinho, Analyst
B16: Bsc in Economics, ISEG – Ulisboa | F16: Ticker
B17: l61952@aln.iseg.ulisboa.pt | F17: Stock Exchange
B18: NAME, Analyst
B19: Bsc in XXX, ISEG – Ulisboa | F19: Current Price | H19: ='Stock Data'!AN4 -> 111.54
B20: email@aln.iseg.ulisboa.pt | F20: ="Market Cap (in "&IF(Inputs!$D$14="BLN","billions",IF(Inputs!$D$14="MLN","millions","thousands"))&")" -> Market Cap (in thousands) | H20: ='Stock Data'!AQ4 -> 5409408.6
B21: NAME, Analyst | F21: Beta | H21: ='Stock Data'!E164 -> 0.70151639
B22: Bsc in XXX, ISEG – Ulisboa | F22: % of 52-Week High | H22: ='Stock Data'!E165 -> 0.73278931
B23: email@aln.iseg.ulisboa.pt | F23: 100-Day Moving Average | H23: ='Stock Data'!E166 -> 102.31285
B25: Reviewed by: | F25: Avg Vol (1 month) | H25: ='Stock Data'!E168 -> 724438.06
B26: NAME, Analyst | F26: Shares Outstanding (millions) | H26: ='Stock Data'!E169 -> 48.49748
B27: Bsc in XXX, ISEG – Ulisboa | F27: % Float | H27: ='Stock Data'!E170 -> 0.868456
B28: email@aln.iseg.ulisboa.pt | F28: Short % of Float | H28: =IFERROR('Stock Data'!E171,0) -> 0.1161959
B30: LISBON INVESTMENT SOCIETY | F30: % Held by Insiders | H30: ='Stock Data'!E173 -> 0.035214593
B31: ISEG – Rua do Quelhas, 6 | F31: % Held by Institutions | H31: ='Stock Data'!E174 -> 1.1210906
B32: lis@iseg.ulisboa.pt
B34: Disclaimer: This report was prepared by members of the Lisbon Investment Society (LIS), an independent, student-led, non-profit organization based at ISEG – Lisbon School of Economics & Management, and is intended solely for academic and educational purposes. All analyses, forecasts, and opinions expressed in this report reflect the independent judgment of the authors as of the date of publication and are subject to change without notice. The views presented herein do not represent those of ISEG, its faculty, or any affiliated entity. This document does not constitute, and should not be interpreted as, investment advice, an offer, or a solicitation to buy or sell any security or financial instrument. Nothing in this report should be construed as a recommendation to make or refrain from making any investment decision. The content is intended for informational purposes only, and readers are strongly encouraged to conduct their own research and seek advice from a qualified financial professional before making any financial decisions. The information contained in this report has been obtained from publicly available sources believed to be reliable; however, no representation or warranty is made regarding the accuracy, completeness, or timeliness of such information. LIS and its members accept no liability whatsoever for any direct or indirect loss arising from the use of this report or its contents. This report incorporates terminology, financial metrics, and methodologies commonly used in professional equity research, including but not limited to Discounted Cash Flow (DCF), trading multiples, Monte Carlo simulations, and strategic analysis tools such as Porter’s Five Forces. Definitions and assumptions used in these models are disclosed within the report and reflect a hypothetical investment thesis designed solely for academic discussion. All valuations, projections, and target prices presented herein are based on publicly available data and subject to the limitations of modeling assumptions. These are not guarantees of future performance and should not be relied upon as such, as past performance is not indicative of future results. Any company names, logos, trademarks, or brand references mentioned in this report are the property of their respective owners and are used strictly for identification and academic purposes. This document may not be reproduced, redistributed, or quoted in whole or in part without the prior written consent of the Lisbon Investment Society. About LIS – Lisbon Investment Society: The Lisbon Investment Society (LIS) is a non-profit academic association headquartered at ISEG – Lisbon School of Economics & Management. Founded in 2016, LIS is committed to fostering student interest in finance and investment through applied research, skill development, and institutional engagement. The Society operates independently and autonomously from any political, religious, or commercial affiliation, and is composed of selected students and collaborators who are invited through a rigorous recruitment process and share a commitment to excellence, analytical rigor, and ethical standards. Its activities include equity research, portfolio management, macroeconomic analysis, and investment education. This report was prepared by the Equity Research team at the Lisbon Investment Society, whose analysts combine rigorous financial modeling, critical thinking, and collaborative research to deliver high-quality, student-led investment analysis. We welcome your feedback, discussion, and questions regarding this report or our research process, and invite you to reach out to our team as we are always open to engagement.

Sheet Industry
D6: 584.17 | E6: 627.76 | F6: 676.06 | G6: 729.63 | H6: 789.13 | I6: 855.3 | J6: 929 | K6: 997.69 | L6: 1067.63 | M6: 1137.57
A7: x | B7: Industry Growth Forecast | O7: Industry Index
D9: 2022 | E9: =+D9+1 -> 2023 | F9: =+E9+1 -> 2024 | G9: =+F9+1 -> 2025 | H9: =+G9+1 -> 2026 | I9: =+H9+1 -> 2027 | J9: =+I9+1 -> 2028 | K9: =+J9+1 -> 2029 | M9: ="CAGR "&$G$9&" - "&$K$9 -> CAGR 2025 - 2029
B12: Market Size | M12: =(K12/G12)^(1/5)-1 -> #DIV/0!
B13: Market Share | M13: =((K13*K12)/(G13*G12))^(1/5)-1 -> #DIV/0!
B14: Market Size | M14: =(K14/G14)^(1/5)-1 -> #DIV/0!
B15: Market Share | M15: =((K15*K14)/(G15*G14))^(1/5)-1 -> #DIV/0!
B16: Market Size | M16: =(K16/G16)^(1/5)-1 -> #DIV/0!
B17: Market Share | M17: =((K17*K16)/(G17*G16))^(1/5)-1 -> #DIV/0!
B18: Market Size | M18: =(K18/G18)^(1/5)-1 -> #DIV/0!
B19: Market Share | M19: =((K19*K18)/(G19*G18))^(1/5)-1 -> #DIV/0!
B20: Market Size | M20: =(K20/G20)^(1/5)-1 -> #DIV/0!
B21: Market Share | M21: =((K21*K20)/(G21*G20))^(1/5)-1 -> #DIV/0!
A23: x
B25: Industry Driver | D25: Description | O25: Porter's Five Forces
O32: Rivalry Among Existing Competitors | R32: 2
O33: Threat of New Entrants | R33: 4
O34: Threat of Substitutes | R34: 3
O35: Bargaining Power of Customers | R35: 5
O36: Bargaining Power of Suppliers | R36: 5

Sheet ESG
A7: x | B7: ESG Analysis
B12: ESG Scores | G12: GHG Scope 1 Emissions, Water Consumption, Energy Consumption and Waste Production per Sales
B15: LSEG ESG Score | D15: 55
B16: E-Score | D16: 23
B17: S-Score | D17: 67
B18: G-Score | D18: 68
B19: S&P Global ESG Score | D19: 33
B20: Environmental | D20: 48
B21: Social | D21: 67
B22: Governance & Economic | D22: 67
B23: Sustainalytics | D23: 37.2
B24: ISS ESG Corporate Rating | D24: D-
B25: SDG Impact Rating | D25: -6.5
B26: Governance Quality Score | D26: 70
B27: MSCI ESG Ratings | D27: BBB
B30: Key Info | G30: Environmental
H32: Overview | I32: Targets | J32: Improvements | K32: Comments
B33: GICS Sector | C33: Consumer Staples | G33: GHG Scope 1 Emissions | I33: Reduce by 10% from 2023 baseline by 2030 | J33: Implemented methane capture pilots at farms; 5% reduction in FY2024 | K33: Strong start, but Scope 1 data not fully disclosed; aligns with UN SDG 13 (Climate Action).
B34: GICS Industry Group | C34: Food, Beverage & Staples Retailing
B35: GICS Industry | C35: Packaged Foods & Meats | G35: Water Consumption | I35: Achieve 95% water recycling in operations by 2027 | J35: Upgraded recycling systems at 80% of facilities; saved 15% water in FY2024 | K35: N/A
B36: GICS Sub-Industry | C36: Packaged Foods & Meats
G37: Energy Consumption | I37: Shift 20% to renewables (solar/wind) by 2028 | J37: Installed solar panels at 3 farms; 8% renewable mix in FY2024 | K37: N/A
B38: Headquarters | C38: Ridgeland, Mississippi
B39: Numer of Employees | C39: 3,067 | G39: Waste Management | I39: 90% waste diversion from landfills by 2026 | J39: Expanded composting for manure; 75% diversion rate in FY2024 | K39: N/A
B41: Annual Report | C41: https://www.calmainefoods.com/annual-reports | G41: Other | I41: N/A | J41: Converted 40% of flocks to cage-free; enhanced biosecurity | K41: Includes animal welfare (key for sector); FY2024 progress ties to consumer demand.
B42: Sustainability Report | C42: https://www.calmainefoods.com/reports
B44: Recent Headlines | G44: Social
B46: US Egg Giant Cal-Maine Under DOJ Probe for Price-Fixing Amid Soaring Profits (CNN Business, April 9, 2025) | H46: Overview | I46: Targets | J46: Improvements | K46: Comments
B47: Background: The DOJ launched an antitrust probe in March 2025 into Cal-Maine Foods for potential price-fixing during the HPAI outbreak, which reduced supply and drove egg prices to $5.90/dozen by February 2025. Critics allege collusion, echoing a 2023 $53 million damages case. Key Developments: Cal-Maine received a subpoena on April 8, 2025, requesting pricing data and is cooperating. Q3 FY2025 sales hit $1.42 billion (up 82%), with profits soaring 245%, though shares dropped 5% post-news. Implications: Scrutiny highlights food industry consolidation (top four firms control 60% of U.S. egg market), risking fines or lawsuits if collusion is proven, amid election-year inflation debates. | G47: Employee Turnover % | I47: Reduce to <15% by 2026 | J47: Implement retention incentives | K47: No specific turnover rate reported in 2024/2025 filings or sustainability report; employee count stable at 3,067. Reviews on Indeed and Glassdoor (205+ reviews) indicate moderate satisfaction with job security but some stress from operations, aligning with industry averages for agriculture (20-30% turnover).
G49: Salaries & Compensation | I49: Maintain competitive wages | J49: Annual wage review and benefit enhancements | K49: Average salary ~$74,361 (2025 data), competitive for sector per Salary.com; Glassdoor rates compensation 3/5 stars, with positive notes on benefits but gaps in executive pay ratios (2024 proxy). No major complaints in recent reviews.
G51: Reputation | I51: Improve to neutral by 2025 | J51: N/A | K51: Mixed perception: Strong operational performance praised in earnings (e.g., Q2 FY2025 sales up 82%), but scrutiny over HPAI profiteering and antitrust probes (Reuters, 2025) harms public view; Wikipedia notes 2025 watchdog complaints on collusion.
G53: Discrimination Events | I53: N/A | J53: N/A | K53: No reported discrimination incidents or lawsuits in 2024/2025; sustainability report emphasizes ethical practices, but general employee reviews on Fairygodboss rate equality low (1/5 for women). Proactive training implied but unverified.
B55: Cal-Maine Accused of Profiteering from Bird Flu: $1 Billion Windfall (Food & Water Watch Report, April 28, 2025) | G55: Work Safety | I55: Maintain OSHA compliance | J55: N/A | K55: No OSHA citations or incidents found in 2024/2025 releases; sustainability report highlights OSHA compliance and safety audits. Employee reviews note good safety records, aligning with "zero lost-time incidents" targets.
G57: Damage to consumer health | I57: Reduce incidents to 0 by 2027 | J57: N/A | K57: No salmonella outbreaks linked to Cal-Maine in 2024/2025 (CDC/FDA reports focus on other sources like raw milk); rigorous food safety processes noted in reports, but past concerns (pre-2024) and HPAI depopulation raise minor risks.
B58: Background: Food & Water Watch’s April 28 report claims Cal-Maine earned $1 billion in excess profits in FY2025’s first three quarters, hiking prices beyond cost increases (e.g., $1.14 profit/dozen vs. $0.15 pre-outbreak) during HPAI. Key Developments: The report cites SEC filings showing tripled margins despite minimal cost rises, plus $44.8 million in USDA indemnity payments, prompting watchdog complaints for antitrust action. Implications: Highlights risks of factory farming density and consumer cost burdens ($5.90/dozen), fueling calls for monopoly breakup and stricter regulations as profits tripled since 2022.
G59: Pension Plan | I59: N/A | J59: N/A | K59: Benefits include standard retirement plans per 2024 proxy, but no specific pension metrics; Glassdoor/Indeed reviews rate overall benefits 3/5, moderate compared to peers. No controversies noted.
G61: Supply chain | I61: 90% sustainable suppliers by 2026 | J61: N/A | K61: 2024 Sustainability Report details audits for ethical labor and 90% sustainable suppliers target; progress on transparency via SASB framework, with no major violations reported.
G63: Community involvement | I63: Increase donations by 10% by 2026 | J63: N/A | K63: Strong 60+ years of initiatives per sustainability report (e.g., donations, partnerships); 2024/2025 expansions (e.g., Dexter facility creating 96 jobs) boost local support.
G65: Public Sector | I65: N/A | J65: Engage with regulators | K65: Tense relations: DOJ antitrust probe on egg prices (2025 filing) and regulatory scrutiny over HPAI indemnity ($44.8M USDA payments); cooperating but ongoing concerns per Reuters.
G67: Litigation | I67: Reduce cases to 0 by 2026 | J67: Legal risk mitigation strategies | K67: Multiple 2024/2025 cases: Class-action antitrust suit with Tyson (Missouri farmers, June 2024); DOJ price-fixing probe (April 2025); ongoing egg price-fixing liability from 2023 verdict ($17.7M damages, potentially tripled).
B70: Board of Directors | G70: Governance
B72: Name | C72: Position | E72: M/F – Age | H72: Overview | I72: Targets | J72: Improvements | K72: Comments
B73: Adolphus B. Baker | C73: Chairman of the Board of Directors | E73: M-49 | G73: Diversity (Gender, Age, Industry, Region) | I73: Increase the diversity inside the board and also on the workers side. | J73: Appointed Melanie Boulden as independent director (female, August 2025), raising female representation to 29% and independence to 89% | K73: 2025 Proxy shows 8 of 9 directors independent (89%), with gender diversity at 22% (2 women); age and regional diversity moderate. Industry peers average 30% female directors, suggesting room for improvement.
B74: Sherman Miller | C74: President, CEO | E74: M-51
B75: Max Bowman | C75: VP, CFO, Treasury | E75: M-52 | G75: % Independence | I75: Increase to 100% independent by 2027 | J75: N/A | K75: The 2025 Proxy Statement indicates 8 of 9 directors are independent (89%), aligning with or exceeding NYSE requirements (majority independent) and industry averages for food/agriculture firms (80-85%). Excluding gender, the focus on age (average ~62 years, diverse range), industry experience (e.g., agriculture, finance), and regional representation (e.g., Mississippi, Texas) supports a strong independence profile. This is above the median for S&P 500 companies (84%) but not at the top tier (e.g., 100% independence in some firms).
B76: Melanie Boulden | C76: Independent Director | E76: F-52
B77: Letitia C. Hughes | C77: Independent Director | E77: F-70 | G77: Average time as independent directors | I77: Reduce average tenure to <6 years by 2028 | J77: N/A | K77: Proxy data indicates average tenure ~8 years; while experienced, this exceeds some benchmarks (e.g., 6 years for fresh perspective), hinting at potential stagnation.
B78: James E. Poole | C78: Independent Director | E78: M-73
B79: Steve W. Sanders | C79: Independent Director | E79: M-78 | G79: Departures of C-level executives | I79: Maintain stability with <1 departure per year | J79: N/A | K79: No significant C-level departures noted in 2024/2025 filings; stability is average, with occasional transitions (e.g., CFO changes in prior years) per Reuters archives.
B80: Camille S. Young | C80: Independent Director | E80: F-52
G81: CEO/Chairman duality | I81: N/A | J81: N/A | K81: No duality; separate CEO (Max Bowman) and Chairman (Michael Castleberry) per 2025 Proxy, aligning with best governance practices.
G83: Transparency when reporting | I83: N/A | J83: Enhanced sustainability reporting format in FY2024 (6th annual report, July 2025) with more data-focused disclosures | K83: Detailed reports with qualitative ESG data, but limited quantitative metrics (e.g., no carbon intensity), typical for the sector.
G85: Time taken to report | I85: Reduce to <6 months by 2027 | J85: Introduced first quarterly earnings call/webcast (October 1, 2025) for faster investor updates | K85: Reports released within fiscal year-end +6 months, timely but not leading-edge compared to real-time reporting trends.
G87: CEO or Chairman in other boards? | I87: N/A | J87: N/A | K87: No excessive external roles; audit firm is independent with no consulting conflicts, meeting regulatory standards.
G89: Audit / Consulting | I89: Ensure <10% of audit firm revenue | J89: N/A | K89: External audit firm (e.g., BKD or successor) provides independent services with no reported consulting conflicts; third-party evaluations confirm effective design and operational testing of internal controls.
G91: ESG-compensation related | I91: N/A | J91: N/A | K91: 45% of executive pay tied to ESG goals (e.g., safety, community), a moderate integration, but lacks aggressive climate targets per peer comparisons.
G93: Management compensation schemes | I93: Align pay ratio to <50:1 by 2026 | J93: Dissolved Long-Term Incentive Plan Committee (March 2025); responsibilities shifted to Compensation Committee | K93: Competitive pay (e.g., CEO $2.8M, 2025 Proxy), but pay ratio (94:1) exceeds median (48:1) for S&P 500 food companies; balanced but not standout.

Sheet Segments
A7: x | B7: Segments | D7: =F7 -> 2020 | E7: =F7 -> 2020 | F7: 2020 | G7: =F7 -> 2020 | H7: =F7 -> 2020 | J7: =L7 -> 2021 | K7: =L7 -> 2021 | L7: 2021 | M7: =L7 -> 2021 | N7: =L7 -> 2021 | P7: =R7 -> 2022 | Q7: =R7 -> 2022 | R7: 2022 | S7: =R7 -> 2022 | T7: =R7 -> 2022 | V7: =X7 -> 2023 | W7: =X7 -> 2023 | X7: 2023 | Y7: =X7 -> 2023 | Z7: =X7 -> 2023 | AB7: =AD7 -> 2024 | AC7: =AD7 -> 2024 | AD7: 2024 | AE7: =AD7 -> 2024 | AF7: =AD7 -> 2024 | AH7: =AJ7 -> 2025 | AI7: =AJ7 -> 2025 | AJ7: 2025 | AK7: =AJ7 -> 2025 | AL7: =AJ7 -> 2025 | AN7: =AP7 -> 2025 | AO7: =AP7 -> 2025 | AP7: 2025 | AQ7: =AP7 -> 2025 | AR7: =AP7 -> 2025 | AZ7: Products
D8: 2020 | J8: =D8+1 -> 2021 | P8: =J8+1 -> 2022 | V8: =P8+1 -> 2023 | AB8: =V8+1 -> 2024 | AH8: =AB8+1 -> 2025 | AN8: =AH8+1 -> 2026 | AT8: =AN8+1 -> 2027 | AV8: =+AT8+1 -> 2028 | AX8: =+AV8+1 -> 2029
D9: Q1 | E9: Q2 | F9: Q3 | G9: Q4 | H9: FY | J9: Q1 | K9: Q2 | L9: Q3 | M9: Q4 | N9: FY | P9: Q1 | Q9: Q2 | R9: Q3 | S9: Q4 | T9: FY | V9: Q1 | W9: Q2 | X9: Q3 | Y9: Q4 | Z9: FY | AB9: Q1 | AC9: Q2 | AD9: Q3 | AE9: Q4 | AF9: FY | AH9: Q1 | AI9: Q2 | AJ9: Q3 | AK9: Q4 | AL9: FY | AN9: Q1 | AO9: Q2 | AP9: Q3 | AQ9: Q4 | AR9: FY | AT9: FY | AV9: FY | AX9: FY
B12: Revenue by segment:
B13: Conventional shell egg sales | H13: 827727 | N13: 766284 | T13: 1061995 | Z13: 2051961 | AF13: 1291743 | AL13: 2835423
B14: Specialty shell egg sales | H14: 483881 | N14: 539780 | T14: 648838 | Z14: 956993 | AF14: 925665 | AL14: 1184487
B15: Egg products and prepared foods | H15: 48655 | N15: 36733 | T15: 60004 | Z15: 122270 | AF15: 89009 | AL15: 198833
B16: Other | H16: 6145 | N16: 6190 | T16: 6322 | Z16: 14993 | AF16: 20026 | AL16: 43142
B17: Total revenue | D17: =IS!D18 -> 241166 | E17: =IS!E18 -> 311522 | F17: =IS!F18 -> 345588 | G17: =IS!G18 -> 453333 | H17: =H13+H14+H15+H16 -> 1366408 | J17: =IS!J18 -> 292782 | K17: =IS!K18 -> 347328 | L17: =IS!L18 -> 359080 | M17: =IS!M18 -> 349798 | N17: =IS!N18 -> 1348987 | P17: =IS!P18 -> 331704 | Q17: =IS!Q18 -> 381723 | R17: =IS!R18 -> 477485 | S17: =IS!S18 -> 592964 | T17: =IS!T18 -> 1777159 | V17: =IS!V18 -> 658344 | W17: =IS!W18 -> 801700 | X17: =IS!X18 -> 997493 | Y17: =IS!Y18 -> 688680 | Z17: =IS!Z18 -> 3146217 | AB17: =IS!AB18 -> 459344 | AC17: =IS!AC18 -> 523234 | AD17: =IS!AD18 -> 703076 | AE17: =IS!AE18 -> 640789 | AF17: 2326443 | AH17: =IS!AH18 -> 785871 | AI17: =IS!AI18 -> 954671 | AJ17: =IS!AJ18 -> 25000 | AK17: =IS!AK18 -> 25000 | AL17: 4261885 | AN17: =IS!AN18 -> 22000 | AO17: =IS!AO18 -> 22000 | AP17: =IS!AP18 -> 22000 | AQ17: =IS!AQ18 -> 22000 | AR17: =IS!AR18 -> 88000 | AT17: =IS!AT18 -> 90000 | AV17: =IS!AV18 -> 87000 | AX17: =IS!AX18 -> 105000
B19: Revenue by region:
B20: USA | H20: =H21 -> 1351609 | J20: =J21 -> 292782 | K20: =K21 -> 347328 | L20: =L21 -> 359080 | M20: =M21 -> 349798 | N20: =N21 -> 1348987 | P20: =P21 -> 331704 | Q20: =Q21 -> 381723 | R20: =R21 -> 477485 | S20: =S21 -> 592964 | T20: =T21 -> 1777159 | V20: =V21 -> 658344 | W20: =W21 -> 801700 | X20: =X21 -> 997493 | Y20: =Y21 -> 688680 | Z20: =Z21 -> 3146217 | AB20: =AB21 -> 459344 | AC20: =AC21 -> 523234 | AD20: =AD21 -> 703076 | AE20: =AE21 -> 640789 | AF20: =AF21 -> 2326443
B21: Total revenue | D21: =IS!D18 -> 241166 | E21: =IS!E18 -> 311522 | F21: =IS!F18 -> 345588 | G21: =IS!G18 -> 453333 | H21: =IS!H18 -> 1351609 | J21: =IS!J18 -> 292782 | K21: =IS!K18 -> 347328 | L21: =IS!L18 -> 359080 | M21: =IS!M18 -> 349798 | N21: =IS!N18 -> 1348987 | P21: =IS!P18 -> 331704 | Q21: =IS!Q18 -> 381723 | R21: =IS!R18 -> 477485 | S21: =IS!S18 -> 592964 | T21: =IS!T18 -> 1777159 | V21: =IS!V18 -> 658344 | W21: =IS!W18 -> 801700 | X21: =IS!X18 -> 997493 | Y21: =IS!Y18 -> 688680 | Z21: =IS!Z18 -> 3146217 | AB21: =IS!AB18 -> 459344 | AC21: =IS!AC18 -> 523234 | AD21: =IS!AD18 -> 703076 | AE21: =IS!AE18 -> 640789 | AF21: =IS!AF18 -> 2326443 | AH21: =IS!AH18 -> 785871 | AI21: =IS!AI18 -> 954671 | AJ21: =IS!AJ18 -> 25000 | AK21: =IS!AK18 -> 25000 | AL21: =IS!AL18 -> 1790542 | AN21: =IS!AN18 -> 22000 | AO21: =IS!AO18 -> 22000 | AP21: =IS!AP18 -> 22000 | AQ21: =IS!AQ18 -> 22000 | AR21: =IS!AR18 -> 88000 | AT21: =IS!AT18 -> 90000 | AV21: =IS!AV18 -> 87000 | AX21: =IS!AX18 -> 105000
B23: Products:
B24: Product 1
B25: Product 2
B26: Product 3
B27: Product 4
B28: Product 5
A30: x | B30: Notes & Forecasts

Sheet Peers
B7: Peers
A12: x | B12: Growth | C12: =Inputs!S7 -> CAL-MAINE FOODS | D12: {=TRANSPOSE(Inputs!B21:B25)} -> VITAL FARMS INC | E12: POST HOLDINGS IN | F12: TYSON FOODS-A | G12: LAMB WESTON | H12: HORMEL FOODS CRP | I12: {=TRANSPOSE(Inputs!H21:H25)} -> GENERAL MILLS IN | J12: CONAGRA BRANDS I | K12: PILGRIM'S PRIDE | L12: NESTLE SA-REG | M12: UNILEVER PLC | N12: {=TRANSPOSE(Inputs!N21:N25)} -> PEPSICO INC | O12: PROCTER & GAMBLE | P12: COCA-COLA CO/THE | Q12: KIMBERLY-CLARK | R12: COLGATE-PALMOLIV
B14: Revenue (LTM) | C14: 0.83193184 | D14: =_xll.BQL( Inputs!$E$21, "(sales_rev_turn(fpt=ltm,fa_adjusted=y) / sales_rev_turn(fpt=ltm,fa_adjusted=y,fa_period_offset=-1)) - 1" ) -> 0.21491736 | E14: =_xll.BQL( Inputs!$E$22, "(sales_rev_turn(fpt=ltm,fa_adjusted=y) / sales_rev_turn(fpt=ltm,fa_adjusted=y,fa_period_offset=-1)) - 1" ) -> 0.008042759 | F14: =_xll.BQL( Inputs!$E$23, "(sales_rev_turn(fpt=ltm,fa_adjusted=y) / sales_rev_turn(fpt=ltm,fa_adjusted=y,fa_period_offset=-1)) - 1" ) -> 0.019852332 | G14: =_xll.BQL( Inputs!$E$24, "(sales_rev_turn(fpt=ltm,fa_adjusted=y) / sales_rev_turn(fpt=ltm,fa_adjusted=y,fa_period_offset=-1)) - 1" ) -> 1.5488508e-05 | H14: =_xll.BQL( Inputs!$E$25, "(sales_rev_turn(fpt=ltm,fa_adjusted=y) / sales_rev_turn(fpt=ltm,fa_adjusted=y,fa_period_offset=-1)) - 1" ) -> 0.0064941488 | I14: =_xll.BQL( Inputs!$K$21, "(sales_rev_turn(fpt=ltm,fa_adjusted=y) / sales_rev_turn(fpt=ltm,fa_adjusted=y,fa_period_offset=-1)) - 1" ) -> -0.032554569 | J14: =_xll.BQL( Inputs!$K$22, "(sales_rev_turn(fpt=ltm,fa_adjusted=y) / sales_rev_turn(fpt=ltm,fa_adjusted=y,fa_period_offset=-1)) - 1" ) -> -0.041141201 | K14: =_xll.BQL( Inputs!$K$23, "(sales_rev_turn(fpt=ltm,fa_adjusted=y) / sales_rev_turn(fpt=ltm,fa_adjusted=y,fa_period_offset=-1)) - 1" ) -> 0.020644371 | L14: =_xll.BQL( Inputs!$K$23, "(sales_rev_turn(fpt=ltm,fa_adjusted=y) / sales_rev_turn(fpt=ltm,fa_adjusted=y,fa_period_offset=-1)) - 1" ) -> 0.020644371 | M14: =_xll.BQL( Inputs!$K$24, "(sales_rev_turn(fpt=ltm,fa_adjusted=y) / sales_rev_turn(fpt=ltm,fa_adjusted=y,fa_period_offset=-1)) - 1" ) -> -0.013104467 | N14: =_xll.BQL( Inputs!$K$24, "(sales_rev_turn(fpt=ltm,fa_adjusted=y) / sales_rev_turn(fpt=ltm,fa_adjusted=y,fa_period_offset=-1)) - 1" ) -> -0.013104467 | O14: =_xll.BQL( Inputs!$K$24, "(sales_rev_turn(fpt=ltm,fa_adjusted=y) / sales_rev_turn(fpt=ltm,fa_adjusted=y,fa_period_offset=-1)) - 1" ) -> -0.013104467 | P14: =_xll.BQL( Inputs!$K$24, "(sales_rev_turn(fpt=ltm,fa_adjusted=y) / sales_rev_turn(fpt=ltm,fa_adjusted=y,fa_period_offset=-1)) - 1" ) -> -0.013104467 | Q14: =_xll.BQL( Inputs!$K$24, "(sales_rev_turn(fpt=ltm,fa_adjusted=y) / sales_rev_turn(fpt=ltm,fa_adjusted=y,fa_period_offset=-1)) - 1" ) -> -0.013104467 | R14: =_xll.BQL( Inputs!$K$24, "(sales_rev_turn(fpt=ltm,fa_adjusted=y) / sales_rev_turn(fpt=ltm,fa_adjusted=y,fa_period_offset=-1)) - 1" ) -> -0.013104467
B15: Revenue (3-yr CAGR) | C15: 0.33852087 | D15: =_xll.BQL( Inputs!$E$21, "(sales_rev_turn(fpt=ltm,fa_adjusted=y) / sales_rev_turn(fpt=ltm,fa_adjusted=y,fa_period_offset=-3))^(1/3) - 1" ) -> 0.29642431 | E15: =_xll.BQL( Inputs!$E$22, "(sales_rev_turn(fpt=ltm,fa_adjusted=y) / sales_rev_turn(fpt=ltm,fa_adjusted=y,fa_period_offset=-3))^(1/3) - 1" ) -> 0.080814416 | F15: =_xll.BQL( Inputs!$E$23, "(sales_rev_turn(fpt=ltm,fa_adjusted=y) / sales_rev_turn(fpt=ltm,fa_adjusted=y,fa_period_offset=-3))^(1/3) - 1" ) -> 0.011268873 | G15: =_xll.BQL( Inputs!$E$24, "(sales_rev_turn(fpt=ltm,fa_adjusted=y) / sales_rev_turn(fpt=ltm,fa_adjusted=y,fa_period_offset=-3))^(1/3) - 1" ) -> 0.15044764 | H15: =_xll.BQL( Inputs!$E$25, "(sales_rev_turn(fpt=ltm,fa_adjusted=y) / sales_rev_turn(fpt=ltm,fa_adjusted=y,fa_period_offset=-3))^(1/3) - 1" ) -> -0.015316215 | I15: =_xll.BQL( Inputs!$K$21, "(sales_rev_turn(fpt=ltm,fa_adjusted=y) / sales_rev_turn(fpt=ltm,fa_adjusted=y,fa_period_offset=-3))^(1/3) - 1" ) -> -0.00025218708 | J15: =_xll.BQL( Inputs!$K$22, "(sales_rev_turn(fpt=ltm,fa_adjusted=y) / sales_rev_turn(fpt=ltm,fa_adjusted=y,fa_period_offset=-3))^(1/3) - 1" ) -> -0.0096053537 | K15: =_xll.BQL( Inputs!$K$23, "(sales_rev_turn(fpt=ltm,fa_adjusted=y) / sales_rev_turn(fpt=ltm,fa_adjusted=y,fa_period_offset=-3))^(1/3) - 1" ) -> 0.027873335 | L15: =_xll.BQL( Inputs!$K$24, "(sales_rev_turn(fpt=ltm,fa_adjusted=y) / sales_rev_turn(fpt=ltm,fa_adjusted=y,fa_period_offset=-3))^(1/3) - 1" ) -> -0.0014734777 | M15: =_xll.BQL( Inputs!$K$25, "(sales_rev_turn(fpt=ltm,fa_adjusted=y) / sales_rev_turn(fpt=ltm,fa_adjusted=y,fa_period_offset=-3))^(1/3) - 1" ) -> 0.021282953 | N15: =_xll.BQL( Inputs!$Q$21, "(sales_rev_turn(fpt=ltm,fa_adjusted=y) / sales_rev_turn(fpt=ltm,fa_adjusted=y,fa_period_offset=-3))^(1/3) - 1" ) -> 0.038734967 | O15: =_xll.BQL( Inputs!$Q$22, "(sales_rev_turn(fpt=ltm,fa_adjusted=y) / sales_rev_turn(fpt=ltm,fa_adjusted=y,fa_period_offset=-3))^(1/3) - 1" ) -> 0.01674893 | P15: =_xll.BQL( Inputs!$Q$23, "(sales_rev_turn(fpt=ltm,fa_adjusted=y) / sales_rev_turn(fpt=ltm,fa_adjusted=y,fa_period_offset=-3))^(1/3) - 1" ) -> 0.045260705 | Q15: =_xll.BQL( Inputs!$Q$24, "(sales_rev_turn(fpt=ltm,fa_adjusted=y) / sales_rev_turn(fpt=ltm,fa_adjusted=y,fa_period_offset=-3))^(1/3) - 1" ) -> -0.021139434 | R15: =_xll.BQL( Inputs!$Q$25, "(sales_rev_turn(fpt=ltm,fa_adjusted=y) / sales_rev_turn(fpt=ltm,fa_adjusted=y,fa_period_offset=-3))^(1/3) - 1" ) -> 0.041528358
B16: Gross profit (LTM) | C16: 2.4176221 | D16: =_xll.BQL( Inputs!$E$21, "(gross_profit(fpt=ltm,fa_adjusted=y) / gross_profit(fpt=ltm,fa_adjusted=y,fa_period_offset=-1)) - 1" ) -> 0.24800689 | E16: =_xll.BQL( Inputs!$E$22, "(gross_profit(fpt=ltm,fa_adjusted=y) / gross_profit(fpt=ltm,fa_adjusted=y,fa_period_offset=-1)) - 1" ) -> 0.013941865 | F16: =_xll.BQL( Inputs!$E$23, "(gross_profit(fpt=ltm,fa_adjusted=y) / gross_profit(fpt=ltm,fa_adjusted=y,fa_period_offset=-1)) - 1" ) -> 0.22858056 | G16: =_xll.BQL( Inputs!$E$24, "(gross_profit(fpt=ltm,fa_adjusted=y) / gross_profit(fpt=ltm,fa_adjusted=y,fa_period_offset=-1)) - 1" ) -> -0.16225065 | H16: =_xll.BQL( Inputs!$E$25, "(gross_profit(fpt=ltm,fa_adjusted=y) / gross_profit(fpt=ltm,fa_adjusted=y,fa_period_offset=-1)) - 1" ) -> -0.0099699837 | I16: =_xll.BQL( Inputs!$K$21, "(gross_profit(fpt=ltm,fa_adjusted=y) / gross_profit(fpt=ltm,fa_adjusted=y,fa_period_offset=-1)) - 1" ) -> -0.045457185 | J16: =_xll.BQL( Inputs!$K$22, "(gross_profit(fpt=ltm,fa_adjusted=y) / gross_profit(fpt=ltm,fa_adjusted=y,fa_period_offset=-1)) - 1" ) -> -0.10840158 | K16: =_xll.BQL( Inputs!$K$23, "(gross_profit(fpt=ltm,fa_adjusted=y) / gross_profit(fpt=ltm,fa_adjusted=y,fa_period_offset=-1)) - 1" ) -> 0.43899673 | L16: =_xll.BQL( Inputs!$K$23, "(gross_profit(fpt=ltm,fa_adjusted=y) / gross_profit(fpt=ltm,fa_adjusted=y,fa_period_offset=-1)) - 1" ) -> 0.43899673 | M16: =_xll.BQL( Inputs!$K$24, "(gross_profit(fpt=ltm,fa_adjusted=y) / gross_profit(fpt=ltm,fa_adjusted=y,fa_period_offset=-1)) - 1" ) -> -0.017377201 | N16: =_xll.BQL( Inputs!$K$24, "(gross_profit(fpt=ltm,fa_adjusted=y) / gross_profit(fpt=ltm,fa_adjusted=y,fa_period_offset=-1)) - 1" ) -> -0.017377201 | O16: =_xll.BQL( Inputs!$K$24, "(gross_profit(fpt=ltm,fa_adjusted=y) / gross_profit(fpt=ltm,fa_adjusted=y,fa_period_offset=-1)) - 1" ) -> -0.017377201 | P16: =_xll.BQL( Inputs!$K$24, "(gross_profit(fpt=ltm,fa_adjusted=y) / gross_profit(fpt=ltm,fa_adjusted=y,fa_period_offset=-1)) - 1" ) -> -0.017377201 | Q16: =_xll.BQL( Inputs!$K$24, "(gross_profit(fpt=ltm,fa_adjusted=y) / gross_profit(fpt=ltm,fa_adjusted=y,fa_period_offset=-1)) - 1" ) -> -0.017377201 | R16: =_xll.BQL( Inputs!$K$24, "(gross_profit(fpt=ltm,fa_adjusted=y) / gross_profit(fpt=ltm,fa_adjusted=y,fa_period_offset=-1)) - 1" ) -> -0.017377201
B17: EBIT (LTM) | C17: 4.3173811 | D17: =_xll.BQL( Inputs!$E$21, "(is_oper_inc(fpt=ltm,fa_adjusted=y) / is_oper_inc(fpt=ltm,fa_adjusted=y,fa_period_offset=-1)) - 1" ) -> 0.22001286 | E17: =_xll.BQL( Inputs!$E$22, "(is_oper_inc(fpt=ltm,fa_adjusted=y) / is_oper_inc(fpt=ltm,fa_adjusted=y,fa_period_offset=-1)) - 1" ) -> 0.017761159 | F17: =_xll.BQL( Inputs!$E$23, "(is_oper_inc(fpt=ltm,fa_adjusted=y) / is_oper_inc(fpt=ltm,fa_adjusted=y,fa_period_offset=-1)) - 1" ) -> 0.46462585 | G17: =_xll.BQL( Inputs!$E$24, "(is_oper_inc(fpt=ltm,fa_adjusted=y) / is_oper_inc(fpt=ltm,fa_adjusted=y,fa_period_offset=-1)) - 1" ) -> -0.23688275 | H17: =_xll.BQL( Inputs!$E$25, "(is_oper_inc(fpt=ltm,fa_adjusted=y) / is_oper_inc(fpt=ltm,fa_adjusted=y,fa_period_offset=-1)) - 1" ) -> 0.0013903233 | I17: =_xll.BQL( Inputs!$K$21, "(is_oper_inc(fpt=ltm,fa_adjusted=y) / is_oper_inc(fpt=ltm,fa_adjusted=y,fa_period_offset=-1)) - 1" ) -> -0.091486029 | J17: =_xll.BQL( Inputs!$K$22, "(is_oper_inc(fpt=ltm,fa_adjusted=y) / is_oper_inc(fpt=ltm,fa_adjusted=y,fa_period_offset=-1)) - 1" ) -> -0.029727941 | K17: =_xll.BQL( Inputs!$K$23, "(is_oper_inc(fpt=ltm,fa_adjusted=y) / is_oper_inc(fpt=ltm,fa_adjusted=y,fa_period_offset=-1)) - 1" ) -> 0.59581 | L17: =_xll.BQL( Inputs!$K$23, "(is_oper_inc(fpt=ltm,fa_adjusted=y) / is_oper_inc(fpt=ltm,fa_adjusted=y,fa_period_offset=-1)) - 1" ) -> 0.59581 | M17: =_xll.BQL( Inputs!$K$24, "(is_oper_inc(fpt=ltm,fa_adjusted=y) / is_oper_inc(fpt=ltm,fa_adjusted=y,fa_period_offset=-1)) - 1" ) -> -0.047780074 | N17: =_xll.BQL( Inputs!$K$24, "(is_oper_inc(fpt=ltm,fa_adjusted=y) / is_oper_inc(fpt=ltm,fa_adjusted=y,fa_period_offset=-1)) - 1" ) -> -0.047780074 | O17: =_xll.BQL( Inputs!$K$24, "(is_oper_inc(fpt=ltm,fa_adjusted=y) / is_oper_inc(fpt=ltm,fa_adjusted=y,fa_period_offset=-1)) - 1" ) -> -0.047780074 | P17: =_xll.BQL( Inputs!$K$24, "(is_oper_inc(fpt=ltm,fa_adjusted=y) / is_oper_inc(fpt=ltm,fa_adjusted=y,fa_period_offset=-1)) - 1" ) -> -0.047780074 | Q17: =_xll.BQL( Inputs!$K$24, "(is_oper_inc(fpt=ltm,fa_adjusted=y) / is_oper_inc(fpt=ltm,fa_adjusted=y,fa_period_offset=-1)) - 1" ) -> -0.047780074 | R17: =_xll.BQL( Inputs!$K$24, "(is_oper_inc(fpt=ltm,fa_adjusted=y) / is_oper_inc(fpt=ltm,fa_adjusted=y,fa_period_offset=-1)) - 1" ) -> -0.047780074
B18: EBITDA (LTM) | C18: 3.4163446 | D18: =_xll.BQL( Inputs!$E$21, "(ebitda(fpt=ltm,fa_adjusted=y) / ebitda(fpt=ltm,fa_adjusted=y,fa_period_offset=-1)) - 1" ) -> 0.31492032 | E18: =_xll.BQL( Inputs!$E$22, "(ebitda(fpt=ltm,fa_adjusted=y) / ebitda(fpt=ltm,fa_adjusted=y,fa_period_offset=-1)) - 1" ) -> 0.03856916 | F18: =_xll.BQL( Inputs!$E$23, "(ebitda(fpt=ltm,fa_adjusted=y) / ebitda(fpt=ltm,fa_adjusted=y,fa_period_offset=-1)) - 1" ) -> 0.18724559 | G18: =_xll.BQL( Inputs!$E$24, "(ebitda(fpt=ltm,fa_adjusted=y) / ebitda(fpt=ltm,fa_adjusted=y,fa_period_offset=-1)) - 1" ) -> -0.11100528 | H18: =_xll.BQL( Inputs!$E$25, "(ebitda(fpt=ltm,fa_adjusted=y) / ebitda(fpt=ltm,fa_adjusted=y,fa_period_offset=-1)) - 1" ) -> 0.026147734 | I18: =_xll.BQL( Inputs!$K$21, "(ebitda(fpt=ltm,fa_adjusted=y) / ebitda(fpt=ltm,fa_adjusted=y,fa_period_offset=-1)) - 1" ) -> -0.083294405 | J18: =_xll.BQL( Inputs!$K$22, "(ebitda(fpt=ltm,fa_adjusted=y) / ebitda(fpt=ltm,fa_adjusted=y,fa_period_offset=-1)) - 1" ) -> -0.032209482 | K18: =_xll.BQL( Inputs!$K$23, "(ebitda(fpt=ltm,fa_adjusted=y) / ebitda(fpt=ltm,fa_adjusted=y,fa_period_offset=-1)) - 1" ) -> 0.45113872 | L18: =_xll.BQL( Inputs!$K$23, "(ebitda(fpt=ltm,fa_adjusted=y) / ebitda(fpt=ltm,fa_adjusted=y,fa_period_offset=-1)) - 1" ) -> 0.45113872 | M18: =_xll.BQL( Inputs!$K$24, "(ebitda(fpt=ltm,fa_adjusted=y) / ebitda(fpt=ltm,fa_adjusted=y,fa_period_offset=-1)) - 1" ) -> -0.033281972 | N18: =_xll.BQL( Inputs!$K$24, "(ebitda(fpt=ltm,fa_adjusted=y) / ebitda(fpt=ltm,fa_adjusted=y,fa_period_offset=-1)) - 1" ) -> -0.033281972 | O18: =_xll.BQL( Inputs!$K$24, "(ebitda(fpt=ltm,fa_adjusted=y) / ebitda(fpt=ltm,fa_adjusted=y,fa_period_offset=-1)) - 1" ) -> -0.033281972 | P18: =_xll.BQL( Inputs!$K$24, "(ebitda(fpt=ltm,fa_adjusted=y) / ebitda(fpt=ltm,fa_adjusted=y,fa_period_offset=-1)) - 1" ) -> -0.033281972 | Q18: =_xll.BQL( Inputs!$K$24, "(ebitda(fpt=ltm,fa_adjusted=y) / ebitda(fpt=ltm,fa_adjusted=y,fa_period_offset=-1)) - 1" ) -> -0.033281972 | R18: =_xll.BQL( Inputs!$K$24, "(ebitda(fpt=ltm,fa_adjusted=y) / ebitda(fpt=ltm,fa_adjusted=y,fa_period_offset=-1)) - 1" ) -> -0.033281972
B19: FCF (LTM) | C19: 2.4950441 | D19: {=_xll.BDP(Inputs!$E$21,"FREE_CASH_FLOW_1_YEAR_GROWTH")/100} -> -0.081030278 | E19: {=_xll.BDP(Inputs!$E$22,"FREE_CASH_FLOW_1_YEAR_GROWTH")/100} -> 0.12273642 | F19: {=_xll.BDP(Inputs!$E$23,"FREE_CASH_FLOW_1_YEAR_GROWTH")/100} -> #VALUE! | G19: {=_xll.BDP(Inputs!$E$24,"FREE_CASH_FLOW_1_YEAR_GROWTH")/100} -> #VALUE! | H19: {=_xll.BDP(Inputs!$E$25,"FREE_CASH_FLOW_1_YEAR_GROWTH")/100} -> 0.29919011 | I19: {=_xll.BDP(Inputs!$K$21,"FREE_CASH_FLOW_1_YEAR_GROWTH")/100} -> -0.093177773 | J19: {=_xll.BDP(Inputs!$K$22,"FREE_CASH_FLOW_1_YEAR_GROWTH")/100} -> -0.19963134 | K19: {=_xll.BDP(Inputs!$K$23,"FREE_CASH_FLOW_1_YEAR_GROWTH")/100} -> 10.293173 | L19: {=_xll.BDP(Inputs!$K$24,"FREE_CASH_FLOW_1_YEAR_GROWTH")/100} -> 0.079202112 | M19: {=_xll.BDP(Inputs!$K$25,"FREE_CASH_FLOW_1_YEAR_GROWTH")/100} -> -0.018855398 | N19: {=_xll.BDP(Inputs!$Q$21,"FREE_CASH_FLOW_1_YEAR_GROWTH")/100} -> -0.092756184 | O19: {=_xll.BDP(Inputs!$Q$22,"FREE_CASH_FLOW_1_YEAR_GROWTH")/100} -> -0.15003329 | P19: {=_xll.BDP(Inputs!$Q$23,"FREE_CASH_FLOW_1_YEAR_GROWTH")/100} -> -0.51359393 | Q19: {=_xll.BDP(Inputs!$Q$24,"FREE_CASH_FLOW_1_YEAR_GROWTH")/100} -> -0.094740634 | R19: {=_xll.BDP(Inputs!$Q$25,"FREE_CASH_FLOW_1_YEAR_GROWTH")/100} -> 0.16644737
A21: x | B21: Margins | C21: CAL-MAINE FOODS | D21: =D12 -> VITAL FARMS INC | E21: =E12 -> POST HOLDINGS IN | F21: =F12 -> TYSON FOODS-A | G21: =G12 -> LAMB WESTON | H21: =H12 -> HORMEL FOODS CRP | I21: =I12 -> GENERAL MILLS IN | J21: =J12 -> CONAGRA BRANDS I | K21: =K12 -> PILGRIM'S PRIDE | ... R21: =R12 -> COLGATE-PALMOLIV
B23: Gross margin | C23: 0.43428788 | D23: {=_xll.BDP(Inputs!$E$21,"GROSS_MARGIN")/100} -> 0.37922373 | E23: {=_xll.BDP(Inputs!$E$22,"GROSS_MARGIN")/100} -> 0.29092355 | F23: {=_xll.BDP(Inputs!$E$23,"GROSS_MARGIN")/100} -> 0.068037292 | G23: {=_xll.BDP(Inputs!$E$24,"GROSS_MARGIN")/100} -> 0.21679351 | H23: {=_xll.BDP(Inputs!$E$25,"GROSS_MARGIN")/100} -> 0.16963111 | I23: {=_xll.BDP(Inputs!$K$21,"GROSS_MARGIN")/100} -> 0.34551949 | J23: {=_xll.BDP(Inputs!$K$22,"GROSS_MARGIN")/100} -> 0.25863702 | K23: {=_xll.BDP(Inputs!$K$23,"GROSS_MARGIN")/100} -> 0.12936175 | L23: {=_xll.BDP(Inputs!$K$24,"GROSS_MARGIN")/100} -> 0.46936328 | M23: {=_xll.BDP(Inputs!$K$25,"GROSS_MARGIN")/100} -> 0.45045342 | N23: {=_xll.BDP(Inputs!$Q$21,"GROSS_MARGIN")/100} -> 0.54553966 | O23: {=_xll.BDP(Inputs!$Q$22,"GROSS_MARGIN")/100} -> 0.51160363 | P23: {=_xll.BDP(Inputs!$Q$23,"GROSS_MARGIN")/100} -> 0.61063301 | Q23: {=_xll.BDP(Inputs!$Q$24,"GROSS_MARGIN")/100} -> 0.35796191 | R23: {=_xll.BDP(Inputs!$Q$25,"GROSS_MARGIN")/100} -> 0.60499478
B24: EBIT margin | C24: 0.36053038 | D24: {=_xll.BDP(Inputs!$E$21,"OPER_MARGIN")/100} -> 0.10481819 | E24: {=_xll.BDP(Inputs!$E$22,"OPER_MARGIN")/100} -> 0.10015525 | F24: {=_xll.BDP(Inputs!$E$23,"OPER_MARGIN")/100} -> 0.026430809 | G24: {=_xll.BDP(Inputs!$E$24,"OPER_MARGIN")/100} -> 0.1030955 | H24: {=_xll.BDP(Inputs!$E$25,"OPER_MARGIN")/100} -> 0.089585621 | I24: {=_xll.BDP(Inputs!$K$21,"OPER_MARGIN")/100} -> 0.16959346 | J24: {=_xll.BDP(Inputs!$K$22,"OPER_MARGIN")/100} -> 0.11750827 | K24: {=_xll.BDP(Inputs!$K$23,"OPER_MARGIN")/100} -> 0.084240099 | L24: {=_xll.BDP(Inputs!$K$24,"OPER_MARGIN")/100} -> 0.16053205 | M24: {=_xll.BDP(Inputs!$K$25,"OPER_MARGIN")/100} -> 0.1547045 | N24: {=_xll.BDP(Inputs!$Q$21,"OPER_MARGIN")/100} -> 0.14029873 | O24: {=_xll.BDP(Inputs!$Q$22,"OPER_MARGIN")/100} -> 0.24264392 | P24: {=_xll.BDP(Inputs!$Q$23,"OPER_MARGIN")/100} -> 0.21232018 | Q24: {=_xll.BDP(Inputs!$Q$24,"OPER_MARGIN")/100} -> 0.1600359 | R24: {=_xll.BDP(Inputs!$Q$25,"OPER_MARGIN")/100} -> 0.21232774
B25: EBITDA margin | C25: 0.38259127 | D25: {=_xll.BDP(Inputs!$E$21,"EBITDA_MARGIN")/100} -> 0.13396672 | E25: {=_xll.BDP(Inputs!$E$22,"EBITDA_MARGIN")/100} -> 0.16715902 | F25: {=_xll.BDP(Inputs!$E$23,"EBITDA_MARGIN")/100} -> 0.051933661 | G25: {=_xll.BDP(Inputs!$E$24,"EBITDA_MARGIN")/100} -> 0.15825912 | H25: {=_xll.BDP(Inputs!$E$25,"EBITDA_MARGIN")/100} -> 0.1054717 | I25: {=_xll.BDP(Inputs!$K$21,"EBITDA_MARGIN")/100} -> 0.24729589 | J25: {=_xll.BDP(Inputs!$K$22,"EBITDA_MARGIN")/100} -> 0.14818567 | K25: {=_xll.BDP(Inputs!$K$23,"EBITDA_MARGIN")/100} -> 0.11949839 | L25: {=_xll.BDP(Inputs!$K$24,"EBITDA_MARGIN")/100} -> 0.19486463 | M25: {=_xll.BDP(Inputs!$K$25,"EBITDA_MARGIN")/100} -> #VALUE! | N25: {=_xll.BDP(Inputs!$Q$21,"EBITDA_MARGIN")/100} -> 0.15004142 | O25: {=_xll.BDP(Inputs!$Q$22,"EBITDA_MARGIN")/100} -> 0.27642257 | P25: {=_xll.BDP(Inputs!$Q$23,"EBITDA_MARGIN")/100} -> 0.30274956 | Q25: {=_xll.BDP(Inputs!$Q$24,"EBITDA_MARGIN")/100} -> 0.20711751 | R25: {=_xll.BDP(Inputs!$Q$25,"EBITDA_MARGIN")/100} -> 0.24412441
B26: Net margin | C26: 0.28626957 | D26: {=_xll.BDP(Inputs!$E$21,"NET_INCOME_TO_COMMON_MARGIN")/100} -> 0.088054401 | E26: {=_xll.BDP(Inputs!$E$22,"NET_INCOME_TO_COMMON_MARGIN")/100} -> 0.046284726 | F26: {=_xll.BDP(Inputs!$E$23,"NET_INCOME_TO_COMMON_MARGIN")/100} -> 0.015006847 | G26: {=_xll.BDP(Inputs!$E$24,"NET_INCOME_TO_COMMON_MARGIN")/100} -> 0.055368685 | H26: {=_xll.BDP(Inputs!$E$25,"NET_INCOME_TO_COMMON_MARGIN")/100} -> 0.06753223 | I26: {=_xll.BDP(Inputs!$K$21,"NET_INCOME_TO_COMMON_MARGIN")/100} -> 0.1177835 | J26: {=_xll.BDP(Inputs!$K$22,"NET_INCOME_TO_COMMON_MARGIN")/100} -> 0.099235327 | K26: {=_xll.BDP(Inputs!$K$23,"NET_INCOME_TO_COMMON_MARGIN")/100} -> 0.06076856 | L26: {=_xll.BDP(Inputs!$K$24,"NET_INCOME_TO_COMMON_MARGIN")/100} -> 0.1186655 | M26: {=_xll.BDP(Inputs!$K$25,"NET_INCOME_TO_COMMON_MARGIN")/100} -> 0.094534323 | N26: {=_xll.BDP(Inputs!$Q$21,"NET_INCOME_TO_COMMON_MARGIN")/100} -> 0.10427417 | O26: {=_xll.BDP(Inputs!$Q$22,"NET_INCOME_TO_COMMON_MARGIN")/100} -> 0.18607328 | P26: {=_xll.BDP(Inputs!$Q$23,"NET_INCOME_TO_COMMON_MARGIN")/100} -> 0.2258983 | Q26: {=_xll.BDP(Inputs!$Q$24,"NET_INCOME_TO_COMMON_MARGIN")/100} -> 0.12688204 | R26: {=_xll.BDP(Inputs!$Q$25,"NET_INCOME_TO_COMMON_MARGIN")/100} -> 0.14372419
B27: SG&A margin | C27: #VALUE! | D27: {=_xll.BDP(Inputs!$E$21,"SG&A_AS_%_TOTAL_SALES")/100} -> 0.27440554 | E27: {=_xll.BDP(Inputs!$E$22,"SG&A_AS_%_TOTAL_SALES")/100} -> 0.16792255 | F27: {=_xll.BDP(Inputs!$E$23,"SG&A_AS_%_TOTAL_SALES")/100} -> 0.039618076 | G27: {=_xll.BDP(Inputs!$E$24,"SG&A_AS_%_TOTAL_SALES")/100} -> 0.087594748 | H27: {=_xll.BDP(Inputs!$E$25,"SG&A_AS_%_TOTAL_SALES")/100} -> 0.084331106 | I27: {=_xll.BDP(Inputs!$K$21,"SG&A_AS_%_TOTAL_SALES")/100} -> 0.17682921 | J27: {=_xll.BDP(Inputs!$K$22,"SG&A_AS_%_TOTAL_SALES")/100} -> 0.13237979 | K27: {=_xll.BDP(Inputs!$K$23,"SG&A_AS_%_TOTAL_SALES")/100} -> 0.039898109 | L27: {=_xll.BDP(Inputs!$K$24,"SG&A_AS_%_TOTAL_SALES")/100} -> 0.27997165 | M27: {=_xll.BDP(Inputs!$K$25,"SG&A_AS_%_TOTAL_SALES")/100} -> 0.61705699 | N27: {=_xll.BDP(Inputs!$Q$21,"SG&A_AS_%_TOTAL_SALES")/100} -> 0.39603066 | O27: {=_xll.BDP(Inputs!$Q$22,"SG&A_AS_%_TOTAL_SALES")/100} -> 0.24404395 | P27: {=_xll.BDP(Inputs!$Q$23,"SG&A_AS_%_TOTAL_SALES")/100} -> 0.30985317 | Q27: {=_xll.BDP(Inputs!$Q$24,"SG&A_AS_%_TOTAL_SALES")/100} -> 0.21492671 | R27: {=_xll.BDP(Inputs!$Q$25,"SG&A_AS_%_TOTAL_SALES")/100} -> 0.36684742
B28: R&D margin | C28: #VALUE! | D28: {=_xll.BDP(Inputs!$E$21,"TRAILING_12M_R&D_%_SALES")/100} -> #VALUE! | E28: {=_xll.BDP(Inputs!$E$22,"TRAILING_12M_R&D_%_SALES")/100} -> #VALUE! | F28: {=_xll.BDP(Inputs!$E$23,"TRAILING_12M_R&D_%_SALES")/100} -> #VALUE! | G28: {=_xll.BDP(Inputs!$E$24,"TRAILING_12M_R&D_%_SALES")/100} -> #VALUE! | H28: {=_xll.BDP(Inputs!$E$25,"TRAILING_12M_R&D_%_SALES")/100} -> #VALUE! | I28: {=_xll.BDP(Inputs!$K$21,"TRAILING_12M_R&D_%_SALES")/100} -> #VALUE! | J28: {=_xll.BDP(Inputs!$K$22,"TRAILING_12M_R&D_%_SALES")/100} -> #VALUE! | K28: {=_xll.BDP(Inputs!$K$23,"TRAILING_12M_R&D_%_SALES")/100} -> #VALUE! | L28: {=_xll.BDP(Inputs!$K$24,"TRAILING_12M_R&D_%_SALES")/100} -> 0.017854982 | M28: {=_xll.BDP(Inputs!$K$25,"TRAILING_12M_R&D_%_SALES")/100} -> #VALUE! | N28: {=_xll.BDP(Inputs!$Q$21,"TRAILING_12M_R&D_%_SALES")/100} -> #VALUE! | O28: {=_xll.BDP(Inputs!$Q$22,"TRAILING_12M_R&D_%_SALES")/100} -> #VALUE! | P28: {=_xll.BDP(Inputs!$Q$23,"TRAILING_12M_R&D_%_SALES")/100} -> #VALUE! | Q28: {=_xll.BDP(Inputs!$Q$24,"TRAILING_12M_R&D_%_SALES")/100} -> #VALUE! | R28: {=_xll.BDP(Inputs!$Q$25,"TRAILING_12M_R&D_%_SALES")/100} -> #VALUE!
A30: x | B30: Returns | C30: CAL-MAINE FOODS | D30: =D21 -> VITAL FARMS INC | E30: =E21 -> POST HOLDINGS IN | F30: =F21 -> TYSON FOODS-A | G30: =G21 -> LAMB WESTON | H30: =H21 -> HORMEL FOODS CRP | I30: =I21 -> GENERAL MILLS IN | J30: =J21 -> CONAGRA BRANDS I | K30: =K21 -> PILGRIM'S PRIDE | ... R30: =R21 -> COLGATE-PALMOLIV
B32: ROIC | C32: 0.49631534 | D32: {=_xll.BDP(Inputs!$E$21,"RETURN_ON_INV_CAPITAL")/100} -> 0.16569803 | E32: {=_xll.BDP(Inputs!$E$22,"RETURN_ON_INV_CAPITAL")/100} -> 0.058291058 | F32: {=_xll.BDP(Inputs!$E$23,"RETURN_ON_INV_CAPITAL")/100} -> 0.03344423 | G32: {=_xll.BDP(Inputs!$E$24,"RETURN_ON_INV_CAPITAL")/100} -> 0.071946428 | H32: {=_xll.BDP(Inputs!$E$25,"RETURN_ON_INV_CAPITAL")/100} -> 0.072628488 | I32: {=_xll.BDP(Inputs!$K$21,"RETURN_ON_INV_CAPITAL")/100} -> 0.14140226 | J32: {=_xll.BDP(Inputs!$K$22,"RETURN_ON_INV_CAPITAL")/100} -> 0.056191781 | K32: {=_xll.BDP(Inputs!$K$23,"RETURN_ON_INV_CAPITAL")/100} -> 0.17544146 | L32: {=_xll.BDP(Inputs!$K$24,"RETURN_ON_INV_CAPITAL")/100} -> 0.11479441 | M32: {=_xll.BDP(Inputs!$K$25,"RETURN_ON_INV_CAPITAL")/100} -> #VALUE! | N32: {=_xll.BDP(Inputs!$Q$21,"RETURN_ON_INV_CAPITAL")/100} -> 0.1270013 | O32: {=_xll.BDP(Inputs!$Q$22,"RETURN_ON_INV_CAPITAL")/100} -> 0.18861607 | P32: {=_xll.BDP(Inputs!$Q$23,"RETURN_ON_INV_CAPITAL")/100} -> 0.13661659 | Q32: {=_xll.BDP(Inputs!$Q$24,"RETURN_ON_INV_CAPITAL")/100} -> 0.29099642 | R32: {=_xll.BDP(Inputs!$Q$25,"RETURN_ON_INV_CAPITAL")/100} -> 0.33781178
B33: CROIC | C33: 0.39078221 | D33: {=_xll.BDP(Inputs!$E$21,"CF_FREE_CASH_FLOW")/_xll.BDP(Inputs!$E$21,"TOTAL_INVESTED_CAPITAL")} -> 0.1252484 | E33: {=_xll.BDP(Inputs!$E$22,"CF_FREE_CASH_FLOW")/_xll.BDP(Inputs!$E$22,"TOTAL_INVESTED_CAPITAL")} -> 0.042492702 | F33: {=_xll.BDP(Inputs!$E$23,"CF_FREE_CASH_FLOW")/_xll.BDP(Inputs!$E$23,"TOTAL_INVESTED_CAPITAL")} -> 0.050218717 | G33: {=_xll.BDP(Inputs!$E$24,"CF_FREE_CASH_FLOW")/_xll.BDP(Inputs!$E$24,"TOTAL_INVESTED_CAPITAL")} -> 0.038396075 | H33: {=_xll.BDP(Inputs!$E$25,"CF_FREE_CASH_FLOW")/_xll.BDP(Inputs!$E$25,"TOTAL_INVESTED_CAPITAL")} -> 0.086889315 | I33: {=_xll.BDP(Inputs!$K$21,"CF_FREE_CASH_FLOW")/_xll.BDP(Inputs!$K$21,"TOTAL_INVESTED_CAPITAL")} -> 0.086669086 | J33: {=_xll.BDP(Inputs!$K$22,"CF_FREE_CASH_FLOW")/_xll.BDP(Inputs!$K$22,"TOTAL_INVESTED_CAPITAL")} -> 0.075526616 | K33: {=_xll.BDP(Inputs!$K$23,"CF_FREE_CASH_FLOW")/_xll.BDP(Inputs!$K$23,"TOTAL_INVESTED_CAPITAL")} -> 0.1817282 | L33: {=_xll.BDP(Inputs!$K$24,"CF_FREE_CASH_FLOW")/_xll.BDP(Inputs!$K$24,"TOTAL_INVESTED_CAPITAL")} -> 0.10351522 | M33: {=_xll.BDP(Inputs!$K$25,"CF_FREE_CASH_FLOW")/_xll.BDP(Inputs!$K$25,"TOTAL_INVESTED_CAPITAL")} -> 0.12538605 | N33: {=_xll.BDP(Inputs!$Q$21,"CF_FREE_CASH_FLOW")/_xll.BDP(Inputs!$Q$21,"TOTAL_INVESTED_CAPITAL")} -> 0.10992355 | O33: {=_xll.BDP(Inputs!$Q$22,"CF_FREE_CASH_FLOW")/_xll.BDP(Inputs!$Q$22,"TOTAL_INVESTED_CAPITAL")} -> 0.15792906 | P33: {=_xll.BDP(Inputs!$Q$23,"CF_FREE_CASH_FLOW")/_xll.BDP(Inputs!$Q$23,"TOTAL_INVESTED_CAPITAL")} -> 0.063087159 | Q33: {=_xll.BDP(Inputs!$Q$24,"CF_FREE_CASH_FLOW")/_xll.BDP(Inputs!$Q$24,"TOTAL_INVESTED_CAPITAL")} -> 0.28369835 | R33: {=_xll.BDP(Inputs!$Q$25,"CF_FREE_CASH_FLOW")/_xll.BDP(Inputs!$Q$25,"TOTAL_INVESTED_CAPITAL")} -> 0.36586876
B34: ROCE | C34: 0.57196465 | D34: {=_xll.BDP(Inputs!$E$21,"IS_OPER_INC")/_xll.BDP(Inputs!$E$21,"CAPITAL_EMPLOYED")} -> 0.2072055 | E34: {=_xll.BDP(Inputs!$E$22,"IS_OPER_INC")/_xll.BDP(Inputs!$E$22,"CAPITAL_EMPLOYED")} -> 0.19516454 | F34: {=_xll.BDP(Inputs!$E$23,"IS_OPER_INC")/_xll.BDP(Inputs!$E$23,"CAPITAL_EMPLOYED")} -> 0.10633962 | G34: {=_xll.BDP(Inputs!$E$24,"IS_OPER_INC")/_xll.BDP(Inputs!$E$24,"CAPITAL_EMPLOYED")} -> 0.15048533 | H34: {=_xll.BDP(Inputs!$E$25,"IS_OPER_INC")/_xll.BDP(Inputs!$E$25,"CAPITAL_EMPLOYED")} -> 0.25489657 | I34: {=_xll.BDP(Inputs!$K$21,"IS_OPER_INC")/_xll.BDP(Inputs!$K$21,"CAPITAL_EMPLOYED")} -> 3.8276581 | J34: {=_xll.BDP(Inputs!$K$22,"IS_OPER_INC")/_xll.BDP(Inputs!$K$22,"CAPITAL_EMPLOYED")} -> 0.45091366 | K34: {=_xll.BDP(Inputs!$K$23,"IS_OPER_INC")/_xll.BDP(Inputs!$K$23,"CAPITAL_EMPLOYED")} -> 0.29082136 | L34: {=_xll.BDP(Inputs!$K$24,"IS_OPER_INC")/_xll.BDP(Inputs!$K$24,"CAPITAL_EMPLOYED")} -> 0.79895816 | M34: {=_xll.BDP(Inputs!$K$25,"IS_OPER_INC")/_xll.BDP(Inputs!$K$25,"CAPITAL_EMPLOYED")} -> 1.8684158 | N34: {=_xll.BDP(Inputs!$Q$21,"IS_OPER_INC")/_xll.BDP(Inputs!$Q$21,"CAPITAL_EMPLOYED")} -> 0.62524865 | O34: {=_xll.BDP(Inputs!$Q$22,"IS_OPER_INC")/_xll.BDP(Inputs!$Q$22,"CAPITAL_EMPLOYED")} -> 1.4446878 | P34: {=_xll.BDP(Inputs!$Q$23,"IS_OPER_INC")/_xll.BDP(Inputs!$Q$23,"CAPITAL_EMPLOYED")} -> 0.64677325 | Q34: {=_xll.BDP(Inputs!$Q$24,"IS_OPER_INC")/_xll.BDP(Inputs!$Q$24,"CAPITAL_EMPLOYED")} -> 0.68254306 | R34: {=_xll.BDP(Inputs!$Q$25,"IS_OPER_INC")/_xll.BDP(Inputs!$Q$25,"CAPITAL_EMPLOYED")} -> 1.1381333
B35: RONA | C35: 0.59880359 | D35: {=_xll.BDP(Inputs!$E$21,"IS_OPER_INC")/_xll.BDP(Inputs!$E$21,"NET_ASSETS")} -> 0.23598785 | E35: {=_xll.BDP(Inputs!$E$22,"IS_OPER_INC")/_xll.BDP(Inputs!$E$22,"NET_ASSETS")} -> 0.19347524 | F35: {=_xll.BDP(Inputs!$E$23,"IS_OPER_INC")/_xll.BDP(Inputs!$E$23,"NET_ASSETS")} -> 0.07610457 | G35: {=_xll.BDP(Inputs!$E$24,"IS_OPER_INC")/_xll.BDP(Inputs!$E$24,"NET_ASSETS")} -> 0.38274731 | H35: {=_xll.BDP(Inputs!$E$25,"IS_OPER_INC")/_xll.BDP(Inputs!$E$25,"NET_ASSETS")} -> 0.13342462 | I35: {=_xll.BDP(Inputs!$K$21,"IS_OPER_INC")/_xll.BDP(Inputs!$K$21,"NET_ASSETS")} -> 0.35878061 | J35: {=_xll.BDP(Inputs!$K$22,"IS_OPER_INC")/_xll.BDP(Inputs!$K$22,"NET_ASSETS")} -> 0.15276456 | K35: {=_xll.BDP(Inputs!$K$23,"IS_OPER_INC")/_xll.BDP(Inputs!$K$23,"NET_ASSETS")} -> 0.35408624 | L35: {=_xll.BDP(Inputs!$K$24,"IS_OPER_INC")/_xll.BDP(Inputs!$K$24,"NET_ASSETS")} -> 0.40127545 | M35: {=_xll.BDP(Inputs!$K$25,"IS_OPER_INC")/_xll.BDP(Inputs!$K$25,"NET_ASSETS")} -> 0.41675903 | N35: {=_xll.BDP(Inputs!$Q$21,"IS_OPER_INC")/_xll.BDP(Inputs!$Q$21,"NET_ASSETS")} -> 0.70920698 | O35: {=_xll.BDP(Inputs!$Q$22,"IS_OPER_INC")/_xll.BDP(Inputs!$Q$22,"NET_ASSETS")} -> 0.39114469 | P35: {=_xll.BDP(Inputs!$Q$23,"IS_OPER_INC")/_xll.BDP(Inputs!$Q$23,"NET_ASSETS")} -> 0.3788867 | Q35: {=_xll.BDP(Inputs!$Q$24,"IS_OPER_INC")/_xll.BDP(Inputs!$Q$24,"NET_ASSETS")} -> 3.1719368 | R35: {=_xll.BDP(Inputs!$Q$25,"IS_OPER_INC")/_xll.BDP(Inputs!$Q$25,"NET_ASSETS")} -> 7.8455882
B36: ROE | C36: 0.5595561 | D36: {=_xll.BDP(Inputs!$E$21,"RETURN_COM_EQY")/100} -> 0.18813241 | E36: {=_xll.BDP(Inputs!$E$22,"RETURN_COM_EQY")/100} -> 0.092251898 | F36: {=_xll.BDP(Inputs!$E$23,"RETURN_COM_EQY")/100} -> 0.043060361 | G36: {=_xll.BDP(Inputs!$E$24,"RETURN_COM_EQY")/100} -> 0.16219495 | H36: {=_xll.BDP(Inputs!$E$25,"RETURN_COM_EQY")/100} -> 0.094609617 | I36: {=_xll.BDP(Inputs!$K$21,"RETURN_COM_EQY")/100} -> 0.31087945 | J36: {=_xll.BDP(Inputs!$K$22,"RETURN_COM_EQY")/100} -> 0.096539741 | K36: {=_xll.BDP(Inputs!$K$23,"RETURN_COM_EQY")/100} -> 0.33129458 | L36: {=_xll.BDP(Inputs!$K$24,"RETURN_COM_EQY")/100} -> 0.33413313 | M36: {=_xll.BDP(Inputs!$K$25,"RETURN_COM_EQY")/100} -> #VALUE! | N36: {=_xll.BDP(Inputs!$Q$21,"RETURN_COM_EQY")/100} -> 0.39879569 | O36: {=_xll.BDP(Inputs!$Q$22,"RETURN_COM_EQY")/100} -> 0.31220751 | P36: {=_xll.BDP(Inputs!$Q$23,"RETURN_COM_EQY")/100} -> 0.44759176 | Q36: {=_xll.BDP(Inputs!$Q$24,"RETURN_COM_EQY")/100} -> 1.9676113 | R36: {=_xll.BDP(Inputs!$Q$25,"RETURN_COM_EQY")/100} -> 7.0521212
B37: ROA | C37: 0.4630708 | D37: {=_xll.BDP(Inputs!$E$21,"RETURN_ON_ASSET")/100} -> 0.13728484 | E37: {=_xll.BDP(Inputs!$E$22,"RETURN_ON_ASSET")/100} -> 0.028731553 | F37: {=_xll.BDP(Inputs!$E$23,"RETURN_ON_ASSET")/100} -> 0.021133215 | G37: {=_xll.BDP(Inputs!$E$24,"RETURN_ON_ASSET")/100} -> 0.039880129 | H37: {=_xll.BDP(Inputs!$E$25,"RETURN_ON_ASSET")/100} -> 0.056709179 | I37: {=_xll.BDP(Inputs!$K$21,"RETURN_ON_ASSET")/100} -> 0.090129166 | J37: {=_xll.BDP(Inputs!$K$22,"RETURN_ON_ASSET")/100} -> 0.040079584 | K37: {=_xll.BDP(Inputs!$K$23,"RETURN_ON_ASSET")/100} -> 0.12251913 | L37: {=_xll.BDP(Inputs!$K$24,"RETURN_ON_ASSET")/100} -> 0.077560805 | M37: {=_xll.BDP(Inputs!$K$25,"RETURN_ON_ASSET")/100} -> #VALUE! | N37: {=_xll.BDP(Inputs!$Q$21,"RETURN_ON_ASSET")/100} -> 0.073702399 | O37: {=_xll.BDP(Inputs!$Q$22,"RETURN_ON_ASSET")/100} -> 0.1290221 | P37: {=_xll.BDP(Inputs!$Q$23,"RETURN_ON_ASSET")/100} -> 0.11854915 | Q37: {=_xll.BDP(Inputs!$Q$24,"RETURN_ON_ASSET")/100} -> 0.14272709 | R37: {=_xll.BDP(Inputs!$Q$25,"RETURN_ON_ASSET")/100} -> 0.17136966
A39: x | B39: Efficiency | C39: CAL-MAINE FOODS | D39: =D30 -> VITAL FARMS INC | E39: =E30 -> POST HOLDINGS IN | F39: =F30 -> TYSON FOODS-A | G39: =G30 -> LAMB WESTON | H39: =H30 -> HORMEL FOODS CRP | I39: =I30 -> GENERAL MILLS IN | J39: =J30 -> CONAGRA BRANDS I | K39: =K30 -> PILGRIM'S PRIDE | ... R39: =R30 -> COLGATE-PALMOLIV
B41: Asset turnover | C41: 1.617604 | D41: {=_xll.BDP(Inputs!$E$21,"ASSET_TURNOVER")} -> 1.751627 | E41: {=_xll.BDP(Inputs!$E$22,"ASSET_TURNOVER")} -> 0.62131688 | F41: {=_xll.BDP(Inputs!$E$23,"ASSET_TURNOVER")} -> 1.4595396 | G41: {=_xll.BDP(Inputs!$E$24,"ASSET_TURNOVER")} -> 0.87550511 | H41: {=_xll.BDP(Inputs!$E$25,"ASSET_TURNOVER")} -> 0.90630291 | I41: {=_xll.BDP(Inputs!$K$21,"ASSET_TURNOVER")} -> 0.59137329 | J41: {=_xll.BDP(Inputs!$K$22,"ASSET_TURNOVER")} -> 0.53985564 | K41: {=_xll.BDP(Inputs!$K$23,"ASSET_TURNOVER")} -> 1.8000006 | L41: {=_xll.BDP(Inputs!$K$24,"ASSET_TURNOVER")} -> 0.68415329 | M41: {=_xll.BDP(Inputs!$K$25,"ASSET_TURNOVER")} -> 0.76787032 | N41: {=_xll.BDP(Inputs!$Q$21,"ASSET_TURNOVER")} -> 0.89563545 | O41: {=_xll.BDP(Inputs!$Q$22,"ASSET_TURNOVER")} -> 0.680805 | P41: {=_xll.BDP(Inputs!$Q$23,"ASSET_TURNOVER")} -> 0.45794634 | Q41: {=_xll.BDP(Inputs!$Q$24,"ASSET_TURNOVER")} -> 1.1091011 | R41: {=_xll.BDP(Inputs!$Q$25,"ASSET_TURNOVER")} -> 1.1780854
B42: Net operating asset turnover | C42: 2.5180722 | D42: {=_xll.BDP(Inputs!$E$21,"SALES_REV_TURN")/(_xll.BDP(Inputs!$E$21,"BS_TOT_ASSET")-_xll.BDP(Inputs!$E$21,"BS_CASH_CASH_EQUIVALENTS_AND_STI")-_xll.BDP(Inputs!$E$21,"SHORT_AND_LONG_TERM_DEBT"))} -> 3.3622268 | E42: {=_xll.BDP(Inputs!$E$22,"SALES_REV_TURN")/(_xll.BDP(Inputs!$E$22,"BS_TOT_ASSET")-_xll.BDP(Inputs!$E$22,"BS_CASH_CASH_EQUIVALENTS_AND_STI")-_xll.BDP(Inputs!$E$22,"SHORT_AND_LONG_TERM_DEBT"))} -> 1.5827673 | F42: {=_xll.BDP(Inputs!$E$23,"SALES_REV_TURN")/(_xll.BDP(Inputs!$E$23,"BS_TOT_ASSET")-_xll.BDP(Inputs!$E$23,"BS_CASH_CASH_EQUIVALENTS_AND_STI")-_xll.BDP(Inputs!$E$23,"SHORT_AND_LONG_TERM_DEBT"))} -> 2.1407517 | G42: {=_xll.BDP(Inputs!$E$24,"SALES_REV_TURN")/(_xll.BDP(Inputs!$E$24,"BS_TOT_ASSET")-_xll.BDP(Inputs!$E$24,"BS_CASH_CASH_EQUIVALENTS_AND_STI")-_xll.BDP(Inputs!$E$24,"SHORT_AND_LONG_TERM_DEBT"))} -> 2.1029762 | H42: {=_xll.BDP(Inputs!$E$25,"SALES_REV_TURN")/(_xll.BDP(Inputs!$E$25,"BS_TOT_ASSET")-_xll.BDP(Inputs!$E$25,"BS_CASH_CASH_EQUIVALENTS_AND_STI")-_xll.BDP(Inputs!$E$25,"SHORT_AND_LONG_TERM_DEBT"))} -> 1.2345488 | I42: {=_xll.BDP(Inputs!$K$21,"SALES_REV_TURN")/(_xll.BDP(Inputs!$K$21,"BS_TOT_ASSET")-_xll.BDP(Inputs!$K$21,"BS_CASH_CASH_EQUIVALENTS_AND_STI")-_xll.BDP(Inputs!$K$21,"SHORT_AND_LONG_TERM_DEBT"))} -> 1.1192441 | J42: {=_xll.BDP(Inputs!$K$22,"SALES_REV_TURN")/(_xll.BDP(Inputs!$K$22,"BS_TOT_ASSET")-_xll.BDP(Inputs!$K$22,"BS_CASH_CASH_EQUIVALENTS_AND_STI")-_xll.BDP(Inputs!$K$22,"SHORT_AND_LONG_TERM_DEBT"))} -> 0.9249321 | K42: {=_xll.BDP(Inputs!$K$23,"SALES_REV_TURN")/(_xll.BDP(Inputs!$K$23,"BS_TOT_ASSET")-_xll.BDP(Inputs!$K$23,"BS_CASH_CASH_EQUIVALENTS_AND_STI")-_xll.BDP(Inputs!$K$23,"SHORT_AND_LONG_TERM_DEBT"))} -> 3.5542361 | L42: {=_xll.BDP(Inputs!$K$24,"SALES_REV_TURN")/(_xll.BDP(Inputs!$K$24,"BS_TOT_ASSET")-_xll.BDP(Inputs!$K$24,"BS_CASH_CASH_EQUIVALENTS_AND_STI")-_xll.BDP(Inputs!$K$24,"SHORT_AND_LONG_TERM_DEBT"))} -> 1.3360135 | M42: {=_xll.BDP(Inputs!$K$25,"SALES_REV_TURN")/(_xll.BDP(Inputs!$K$25,"BS_TOT_ASSET")-_xll.BDP(Inputs!$K$25,"BS_CASH_CASH_EQUIVALENTS_AND_STI")-_xll.BDP(Inputs!$K$25,"SHORT_AND_LONG_TERM_DEBT"))} -> 1.4990871 | N42: {=_xll.BDP(Inputs!$Q$21,"SALES_REV_TURN")/(_xll.BDP(Inputs!$Q$21,"BS_TOT_ASSET")-_xll.BDP(Inputs!$Q$21,"BS_CASH_CASH_EQUIVALENTS_AND_STI")-_xll.BDP(Inputs!$Q$21,"SHORT_AND_LONG_TERM_DEBT"))} -> 2.1638163 | O42: {=_xll.BDP(Inputs!$Q$22,"SALES_REV_TURN")/(_xll.BDP(Inputs!$Q$22,"BS_TOT_ASSET")-_xll.BDP(Inputs!$Q$22,"BS_CASH_CASH_EQUIVALENTS_AND_STI")-_xll.BDP(Inputs!$Q$22,"SHORT_AND_LONG_TERM_DEBT"))} -> 1.0507786 | P42: {=_xll.BDP(Inputs!$Q$23,"SALES_REV_TURN")/(_xll.BDP(Inputs!$Q$23,"BS_TOT_ASSET")-_xll.BDP(Inputs!$Q$23,"BS_CASH_CASH_EQUIVALENTS_AND_STI")-_xll.BDP(Inputs!$Q$23,"SHORT_AND_LONG_TERM_DEBT"))} -> 1.1694208 | Q42: {=_xll.BDP(Inputs!$Q$24,"SALES_REV_TURN")/(_xll.BDP(Inputs!$Q$24,"BS_TOT_ASSET")-_xll.BDP(Inputs!$Q$24,"BS_CASH_CASH_EQUIVALENTS_AND_STI")-_xll.BDP(Inputs!$Q$24,"SHORT_AND_LONG_TERM_DEBT"))} -> 2.6233325 | R42: {=_xll.BDP(Inputs!$Q$25,"SALES_REV_TURN")/(_xll.BDP(Inputs!$Q$25,"BS_TOT_ASSET")-_xll.BDP(Inputs!$Q$25,"BS_CASH_CASH_EQUIVALENTS_AND_STI")-_xll.BDP(Inputs!$Q$25,"SHORT_AND_LONG_TERM_DEBT"))} -> 3.2018159
B43: Fixed asset turnover | C43: 4.524491 | D43: {=_xll.BDP(Inputs!$E$21,"NET_FIX_ASSET_TURN")} -> 5.8967449 | E43: {=_xll.BDP(Inputs!$E$22,"NET_FIX_ASSET_TURN")} -> 3.4224978 | F43: {=_xll.BDP(Inputs!$E$23,"NET_FIX_ASSET_TURN")} -> 5.8698032 | G43: {=_xll.BDP(Inputs!$E$24,"NET_FIX_ASSET_TURN")} -> 1.6938414 | H43: {=_xll.BDP(Inputs!$E$25,"NET_FIX_ASSET_TURN")} -> 5.5046471 | I43: {=_xll.BDP(Inputs!$K$21,"NET_FIX_ASSET_TURN")} -> 5.2057884 | J43: {=_xll.BDP(Inputs!$K$22,"NET_FIX_ASSET_TURN")} -> 4.0228007 | K43: {=_xll.BDP(Inputs!$K$23,"NET_FIX_ASSET_TURN")} -> 5.2424206 | L43: {=_xll.BDP(Inputs!$K$24,"NET_FIX_ASSET_TURN")} -> 2.8380661 | M43: {=_xll.BDP(Inputs!$K$25,"NET_FIX_ASSET_TURN")} -> 5.4296216 | N43: {=_xll.BDP(Inputs!$Q$21,"NET_FIX_ASSET_TURN")} -> 3.286162 | O43: {=_xll.BDP(Inputs!$Q$22,"NET_FIX_ASSET_TURN")} -> 3.5229158 | P43: {=_xll.BDP(Inputs!$Q$23,"NET_FIX_ASSET_TURN")} -> 4.6384782 | Q43: {=_xll.BDP(Inputs!$Q$24,"NET_FIX_ASSET_TURN")} -> 2.7097654 | R43: {=_xll.BDP(Inputs!$Q$25,"NET_FIX_ASSET_TURN")} -> 4.4833539
B44: Revenue per employee thsnd of USD | C44: 1113.3451 | D44: =_xll.BQL( Inputs!$E$21, "sales_rev_turn(fpt=ltm,fa_adjusted=y,fs=mr)/1k", "currency=USD" )/IFERROR(VALUE(_xll.BDP(Inputs!$E$21,"NUM_OF_EMPLOYEES")),_xll.BDP(Inputs!$E$21,"NUM_OF_EMPLOYEES_CSR")) -> 1100.2458 | E44: =_xll.BQL( Inputs!$E$22, "sales_rev_turn(fpt=ltm,fa_adjusted=y,fs=mr)/1k", "currency=USD" )/IFERROR(VALUE(_xll.BDP(Inputs!$E$22,"NUM_OF_EMPLOYEES")),_xll.BDP(Inputs!$E$22,"NUM_OF_EMPLOYEES_CSR")) -> 690 | F44: =_xll.BQL( Inputs!$E$23, "sales_rev_turn(fpt=ltm,fa_adjusted=y,fs=mr)/1k", "currency=USD" )/IFERROR(VALUE(_xll.BDP(Inputs!$E$23,"NUM_OF_EMPLOYEES")),_xll.BDP(Inputs!$E$23,"NUM_OF_EMPLOYEES_CSR")) -> 392.36232 | G44: =_xll.BQL( Inputs!$E$24, "sales_rev_turn(fpt=ltm,fa_adjusted=y,fs=mr)/1k", "currency=USD" )/IFERROR(VALUE(_xll.BDP(Inputs!$E$24,"NUM_OF_EMPLOYEES")),_xll.BDP(Inputs!$E$24,"NUM_OF_EMPLOYEES_CSR")) -> 639.25743 | H44: =_xll.BQL( Inputs!$E$25, "sales_rev_turn(fpt=ltm,fa_adjusted=y,fs=mr)/1k", "currency=USD" )/IFERROR(VALUE(_xll.BDP(Inputs!$E$25,"NUM_OF_EMPLOYEES")),_xll.BDP(Inputs!$E$25,"NUM_OF_EMPLOYEES_CSR")) -> 602.9295 | I44: =_xll.BQL( Inputs!$K$21, "sales_rev_turn(fpt=ltm,fa_adjusted=y,fs=mr)/1k", "currency=USD" )/IFERROR(VALUE(_xll.BDP(Inputs!$K$21,"NUM_OF_EMPLOYEES")),_xll.BDP(Inputs!$K$21,"NUM_OF_EMPLOYEES_CSR")) -> 580.48485 | J44: =_xll.BQL( Inputs!$K$22, "sales_rev_turn(fpt=ltm,fa_adjusted=y,fs=mr)/1k", "currency=USD" )/IFERROR(VALUE(_xll.BDP(Inputs!$K$22,"NUM_OF_EMPLOYEES")),_xll.BDP(Inputs!$K$22,"NUM_OF_EMPLOYEES_CSR")) -> 625.71038 | K44: =_xll.BQL( Inputs!$K$23, "sales_rev_turn(fpt=ltm,fa_adjusted=y,fs=mr)/1k", "currency=USD" )/IFERROR(VALUE(_xll.BDP(Inputs!$K$23,"NUM_OF_EMPLOYEES")),_xll.BDP(Inputs!$K$23,"NUM_OF_EMPLOYEES_CSR")) -> 297.99044 | L44: =_xll.BQL( Inputs!$K$24, "sales_rev_turn(fpt=ltm,fa_adjusted=y,fs=mr)/1k", "currency=USD" )/IFERROR(VALUE(_xll.BDP(Inputs!$K$24,"NUM_OF_EMPLOYEES")),_xll.BDP(Inputs!$K$24,"NUM_OF_EMPLOYEES_CSR")) -> 378.89973 | M44: =_xll.BQL( Inputs!$K$25, "sales_rev_turn(fpt=ltm,fa_adjusted=y,fs=mr)/1k", "currency=USD" )/IFERROR(VALUE(_xll.BDP(Inputs!$K$25,"NUM_OF_EMPLOYEES")),_xll.BDP(Inputs!$K$25,"NUM_OF_EMPLOYEES_CSR")) -> 520.7694 | N44: =_xll.BQL( Inputs!$Q$21, "sales_rev_turn(fpt=ltm,fa_adjusted=y,fs=mr)/1k", "currency=USD" )/IFERROR(VALUE(_xll.BDP(Inputs!$Q$21,"NUM_OF_EMPLOYEES")),_xll.BDP(Inputs!$Q$21,"NUM_OF_EMPLOYEES_CSR")) -> 287.61129 | O44: =_xll.BQL( Inputs!$Q$22, "sales_rev_turn(fpt=ltm,fa_adjusted=y,fs=mr)/1k", "currency=USD" )/IFERROR(VALUE(_xll.BDP(Inputs!$Q$22,"NUM_OF_EMPLOYEES")),_xll.BDP(Inputs!$Q$22,"NUM_OF_EMPLOYEES_CSR")) -> 773.24771 | P44: =_xll.BQL( Inputs!$Q$23, "sales_rev_turn(fpt=ltm,fa_adjusted=y,fs=mr)/1k", "currency=USD" )/IFERROR(VALUE(_xll.BDP(Inputs!$Q$23,"NUM_OF_EMPLOYEES")),_xll.BDP(Inputs!$Q$23,"NUM_OF_EMPLOYEES_CSR")) -> 676.98709 | Q44: =_xll.BQL( Inputs!$Q$24, "sales_rev_turn(fpt=ltm,fa_adjusted=y,fs=mr)/1k", "currency=USD" )/IFERROR(VALUE(_xll.BDP(Inputs!$Q$24,"NUM_OF_EMPLOYEES")),_xll.BDP(Inputs!$Q$24,"NUM_OF_EMPLOYEES_CSR")) -> 496.92105 | R44: =_xll.BQL( Inputs!$Q$25, "sales_rev_turn(fpt=ltm,fa_adjusted=y,fs=mr)/1k", "currency=USD" )/IFERROR(VALUE(_xll.BDP(Inputs!$Q$25,"NUM_OF_EMPLOYEES")),_xll.BDP(Inputs!$Q$25,"NUM_OF_EMPLOYEES_CSR")) -> 588.17647
B45: EBIT per employee thsnd of USD | C45: 401.36782 | D45: =_xll.BQL( Inputs!$E$21, "is_oper_inc(fpt=ltm,fa_adjusted=y,fs=mr)/1k", "currency=USD" )/IFERROR(VALUE(_xll.BDP(Inputs!$E$21,"NUM_OF_EMPLOYEES")),_xll.BDP(Inputs!$E$21,"NUM_OF_EMPLOYEES_CSR")) -> 114.19565 | E45: =_xll.BQL( Inputs!$E$22, "is_oper_inc(fpt=ltm,fa_adjusted=y,fs=mr)/1k", "currency=USD" )/IFERROR(VALUE(_xll.BDP(Inputs!$E$22,"NUM_OF_EMPLOYEES")),_xll.BDP(Inputs!$E$22,"NUM_OF_EMPLOYEES_CSR")) -> 75.87108 | F45: =_xll.BQL( Inputs!$E$23, "is_oper_inc(fpt=ltm,fa_adjusted=y,fs=mr)/1k", "currency=USD" )/IFERROR(VALUE(_xll.BDP(Inputs!$E$23,"NUM_OF_EMPLOYEES")),_xll.BDP(Inputs!$E$23,"NUM_OF_EMPLOYEES_CSR")) -> 15.601449 | G45: =_xll.BQL( Inputs!$E$24, "is_oper_inc(fpt=ltm,fa_adjusted=y,fs=mr)/1k", "currency=USD" )/IFERROR(VALUE(_xll.BDP(Inputs!$E$24,"NUM_OF_EMPLOYEES")),_xll.BDP(Inputs!$E$24,"NUM_OF_EMPLOYEES_CSR")) -> 72.881188 | H45: =_xll.BQL( Inputs!$E$25, "is_oper_inc(fpt=ltm,fa_adjusted=y,fs=mr)/1k", "currency=USD" )/IFERROR(VALUE(_xll.BDP(Inputs!$E$25,"NUM_OF_EMPLOYEES")),_xll.BDP(Inputs!$E$25,"NUM_OF_EMPLOYEES_CSR")) -> 54.0553 | I45: =_xll.BQL( Inputs!$K$21, "is_oper_inc(fpt=ltm,fa_adjusted=y,fs=mr)/1k", "currency=USD" )/IFERROR(VALUE(_xll.BDP(Inputs!$K$21,"NUM_OF_EMPLOYEES")),_xll.BDP(Inputs!$K$21,"NUM_OF_EMPLOYEES_CSR")) -> 98.259916 | J45: =_xll.BQL( Inputs!$K$22, "is_oper_inc(fpt=ltm,fa_adjusted=y,fs=mr)/1k", "currency=USD" )/IFERROR(VALUE(_xll.BDP(Inputs!$K$22,"NUM_OF_EMPLOYEES")),_xll.BDP(Inputs!$K$22,"NUM_OF_EMPLOYEES_CSR")) -> 85.606627 | K45: =_xll.BQL( Inputs!$K$23, "is_oper_inc(fpt=ltm,fa_adjusted=y,fs=mr)/1k", "currency=USD" )/IFERROR(VALUE(_xll.BDP(Inputs!$K$23,"NUM_OF_EMPLOYEES")),_xll.BDP(Inputs!$K$23,"NUM_OF_EMPLOYEES_CSR")) -> 32.705393 | L45: =_xll.BQL( Inputs!$K$24, "is_oper_inc(fpt=ltm,fa_adjusted=y,fs=mr)/1k", "currency=USD" )/IFERROR(VALUE(_xll.BDP(Inputs!$K$24,"NUM_OF_EMPLOYEES")),_xll.BDP(Inputs!$K$24,"NUM_OF_EMPLOYEES_CSR")) -> 63.384077 | M45: =_xll.BQL( Inputs!$K$25, "is_oper_inc(fpt=ltm,fa_adjusted=y,fs=mr)/1k", "currency=USD" )/IFERROR(VALUE(_xll.BDP(Inputs!$K$25,"NUM_OF_EMPLOYEES")),_xll.BDP(Inputs!$K$25,"NUM_OF_EMPLOYEES_CSR")) -> 94.746276 | N45: =_xll.BQL( Inputs!$Q$21, "is_oper_inc(fpt=ltm,fa_adjusted=y,fs=mr)/1k", "currency=USD" )/IFERROR(VALUE(_xll.BDP(Inputs!$Q$21,"NUM_OF_EMPLOYEES")),_xll.BDP(Inputs!$Q$21,"NUM_OF_EMPLOYEES_CSR")) -> 44.322884 | O45: =_xll.BQL( Inputs!$Q$22, "is_oper_inc(fpt=ltm,fa_adjusted=y,fs=mr)/1k", "currency=USD" )/IFERROR(VALUE(_xll.BDP(Inputs!$Q$22,"NUM_OF_EMPLOYEES")),_xll.BDP(Inputs!$Q$22,"NUM_OF_EMPLOYEES_CSR")) -> 201.83486 | P45: =_xll.BQL( Inputs!$Q$23, "is_oper_inc(fpt=ltm,fa_adjusted=y,fs=mr)/1k", "currency=USD" )/IFERROR(VALUE(_xll.BDP(Inputs!$Q$23,"NUM_OF_EMPLOYEES")),_xll.BDP(Inputs!$Q$23,"NUM_OF_EMPLOYEES_CSR")) -> 209.62189 | Q45: =_xll.BQL( Inputs!$Q$24, "is_oper_inc(fpt=ltm,fa_adjusted=y,fs=mr)/1k", "currency=USD" )/IFERROR(VALUE(_xll.BDP(Inputs!$Q$24,"NUM_OF_EMPLOYEES")),_xll.BDP(Inputs!$Q$24,"NUM_OF_EMPLOYEES_CSR")) -> 105.44737 | R45: =_xll.BQL( Inputs!$Q$25, "is_oper_inc(fpt=ltm,fa_adjusted=y,fs=mr)/1k", "currency=USD" )/IFERROR(VALUE(_xll.BDP(Inputs!$Q$25,"NUM_OF_EMPLOYEES")),_xll.BDP(Inputs!$Q$25,"NUM_OF_EMPLOYEES_CSR")) -> 128.55882
A47: x | B47: Working Capital | C47: CAL-MAINE FOODS | D47: =D39 -> VITAL FARMS INC | E47: =E39 -> POST HOLDINGS IN | F47: =F39 -> TYSON FOODS-A | G47: =G39 -> LAMB WESTON | H47: =H39 -> HORMEL FOODS CRP | I47: =I39 -> GENERAL MILLS IN | J47: =J39 -> CONAGRA BRANDS I | K47: =K39 -> PILGRIM'S PRIDE | ... R47: =R39 -> COLGATE-PALMOLIV
B49: DSO | C49: 16.33983 | D49: {=_xll.BDP(Inputs!$E$21,"ACCT_RCV_DAYS")} -> 30.778734 | E49: {=_xll.BDP(Inputs!$E$22,"ACCT_RCV_DAYS")} -> 28.350029 | F49: {=_xll.BDP(Inputs!$E$23,"ACCT_RCV_DAYS")} -> 16.278691 | G49: {=_xll.BDP(Inputs!$E$24,"ACCT_RCV_DAYS")} -> 42.102563 | H49: {=_xll.BDP(Inputs!$E$25,"ACCT_RCV_DAYS")} -> 22.509542 | I49: {=_xll.BDP(Inputs!$K$21,"ACCT_RCV_DAYS")} -> 34.660378 | J49: {=_xll.BDP(Inputs!$K$22,"ACCT_RCV_DAYS")} -> 26.86012 | K49: {=_xll.BDP(Inputs!$K$23,"ACCT_RCV_DAYS")} -> 21.425185 | L49: {=_xll.BDP(Inputs!$K$24,"ACCT_RCV_DAYS")} -> #N/A N/A | M49: {=_xll.BDP(Inputs!$K$25,"ACCT_RCV_DAYS")} -> #N/A N/A | N49: {=_xll.BDP(Inputs!$Q$21,"ACCT_RCV_DAYS")} -> 48.267254 | O49: {=_xll.BDP(Inputs!$Q$22,"ACCT_RCV_DAYS")} -> 26.639665 | P49: {=_xll.BDP(Inputs!$Q$23,"ACCT_RCV_DAYS")} -> 33.695253 | Q49: {=_xll.BDP(Inputs!$Q$24,"ACCT_RCV_DAYS")} -> 41.684187 | R49: {=_xll.BDP(Inputs!$Q$25,"ACCT_RCV_DAYS")} -> 32.835034
B50: DIO | C50: 42.080574 | D50: {=_xll.BDP(Inputs!$E$21,"INVENT_DAYS")} -> 32.894848 | E50: {=_xll.BDP(Inputs!$E$22,"INVENT_DAYS")} -> 50.999777 | F50: {=_xll.BDP(Inputs!$E$23,"INVENT_DAYS")} -> 37.917572 | G50: {=_xll.BDP(Inputs!$E$24,"INVENT_DAYS")} -> 73.298827 | H50: {=_xll.BDP(Inputs!$E$25,"INVENT_DAYS")} -> 62.615507 | I50: {=_xll.BDP(Inputs!$K$21,"INVENT_DAYS")} -> 58.567279 | J50: {=_xll.BDP(Inputs!$K$22,"INVENT_DAYS")} -> 95.386171 | K50: {=_xll.BDP(Inputs!$K$23,"INVENT_DAYS")} -> 43.517895 | L50: {=_xll.BDP(Inputs!$K$24,"INVENT_DAYS")} -> 103.80396 | M50: {=_xll.BDP(Inputs!$K$25,"INVENT_DAYS")} -> #N/A N/A | N50: {=_xll.BDP(Inputs!$Q$21,"INVENT_DAYS")} -> 53.868204 | O50: {=_xll.BDP(Inputs!$Q$22,"INVENT_DAYS")} -> 64.582584 | P50: {=_xll.BDP(Inputs!$Q$23,"INVENT_DAYS")} -> 98.69946 | Q50: {=_xll.BDP(Inputs!$Q$24,"INVENT_DAYS")} -> 51.804046 | R50: {=_xll.BDP(Inputs!$Q$25,"INVENT_DAYS")} -> 93.541085
B51: DPO | C51: 13.168247 | D51: {=_xll.BDP(Inputs!$E$21,"ACCOUNTS_PAYABLE_TURNOVER_DAYS")} -> 43.047571 | E51: {=_xll.BDP(Inputs!$E$22,"ACCOUNTS_PAYABLE_TURNOVER_DAYS")} -> 30.110638 | F51: {=_xll.BDP(Inputs!$E$23,"ACCOUNTS_PAYABLE_TURNOVER_DAYS")} -> 16.758099 | G51: {=_xll.BDP(Inputs!$E$24,"ACCOUNTS_PAYABLE_TURNOVER_DAYS")} -> 46.362533 | H51: {=_xll.BDP(Inputs!$E$25,"ACCOUNTS_PAYABLE_TURNOVER_DAYS")} -> 24.451329 | I51: {=_xll.BDP(Inputs!$K$21,"ACCOUNTS_PAYABLE_TURNOVER_DAYS")} -> 108.95424 | J51: {=_xll.BDP(Inputs!$K$22,"ACCOUNTS_PAYABLE_TURNOVER_DAYS")} -> 65.100416 | K51: {=_xll.BDP(Inputs!$K$23,"ACCOUNTS_PAYABLE_TURNOVER_DAYS")} -> 32.517147 | L51: {=_xll.BDP(Inputs!$K$24,"ACCOUNTS_PAYABLE_TURNOVER_DAYS")} -> #N/A N/A | M51: {=_xll.BDP(Inputs!$K$25,"ACCOUNTS_PAYABLE_TURNOVER_DAYS")} -> #N/A N/A | N51: {=_xll.BDP(Inputs!$Q$21,"ACCOUNTS_PAYABLE_TURNOVER_DAYS")} -> #N/A N/A | O51: {=_xll.BDP(Inputs!$Q$22,"ACCOUNTS_PAYABLE_TURNOVER_DAYS")} -> 133.88469 | P51: {=_xll.BDP(Inputs!$Q$23,"ACCOUNTS_PAYABLE_TURNOVER_DAYS")} -> #N/A N/A | Q51: {=_xll.BDP(Inputs!$Q$24,"ACCOUNTS_PAYABLE_TURNOVER_DAYS")} -> 105.49293 | R51: {=_xll.BDP(Inputs!$Q$25,"ACCOUNTS_PAYABLE_TURNOVER_DAYS")} -> 75.560057
B52: CCC | C52: 45.252157 | D52: {=_xll.BDP(Inputs!$E$21,"CASH_CONVERSION_CYCLE")} -> 19.8551 | E52: {=_xll.BDP(Inputs!$E$22,"CASH_CONVERSION_CYCLE")} -> 47.647453 | F52: {=_xll.BDP(Inputs!$E$23,"CASH_CONVERSION_CYCLE")} -> 36.865355 | G52: {=_xll.BDP(Inputs!$E$24,"CASH_CONVERSION_CYCLE")} -> 68.010339 | H52: {=_xll.BDP(Inputs!$E$25,"CASH_CONVERSION_CYCLE")} -> 56.988178 | I52: {=_xll.BDP(Inputs!$K$21,"CASH_CONVERSION_CYCLE")} -> -27.041068 | J52: {=_xll.BDP(Inputs!$K$22,"CASH_CONVERSION_CYCLE")} -> 47.611141 | K52: {=_xll.BDP(Inputs!$K$23,"CASH_CONVERSION_CYCLE")} -> 31.626477 | L52: {=_xll.BDP(Inputs!$K$24,"CASH_CONVERSION_CYCLE")} -> 18.366678 | M52: {=_xll.BDP(Inputs!$K$25,"CASH_CONVERSION_CYCLE")} -> -31.499271 | N52: {=_xll.BDP(Inputs!$Q$21,"CASH_CONVERSION_CYCLE")} -> -18.34537 | O52: {=_xll.BDP(Inputs!$Q$22,"CASH_CONVERSION_CYCLE")} -> -42.662436 | P52: {=_xll.BDP(Inputs!$Q$23,"CASH_CONVERSION_CYCLE")} -> 9.9055439 | Q52: {=_xll.BDP(Inputs!$Q$24,"CASH_CONVERSION_CYCLE")} -> -14.31377 | R52: {=_xll.BDP(Inputs!$Q$25,"CASH_CONVERSION_CYCLE")} -> 38.455558
B53: Working capital intensity | C53: 0.31369159 | D53: {=_xll.BDP(Inputs!$E$21,"WORKING_CAPITAL_TO_SALES")} -> 0.25197926 | E53: {=_xll.BDP(Inputs!$E$22,"WORKING_CAPITAL_TO_SALES")} -> 0.15929405 | F53: {=_xll.BDP(Inputs!$E$23,"WORKING_CAPITAL_TO_SALES")} -> 0.082471466 | G53: {=_xll.BDP(Inputs!$E$24,"WORKING_CAPITAL_TO_SALES")} -> 0.073460853 | H53: {=_xll.BDP(Inputs!$E$25,"WORKING_CAPITAL_TO_SALES")} -> 0.15195222 | I53: {=_xll.BDP(Inputs!$K$21,"WORKING_CAPITAL_TO_SALES")} -> -0.13561286 | J53: {=_xll.BDP(Inputs!$K$22,"WORKING_CAPITAL_TO_SALES")} -> -0.00087769093 | K53: {=_xll.BDP(Inputs!$K$23,"WORKING_CAPITAL_TO_SALES")} -> 0.10082953 | L53: {=_xll.BDP(Inputs!$K$24,"WORKING_CAPITAL_TO_SALES")} -> -0.10545771 | M53: {=_xll.BDP(Inputs!$K$25,"WORKING_CAPITAL_TO_SALES")} -> -0.098764813 | N53: {=_xll.BDP(Inputs!$Q$21,"WORKING_CAPITAL_TO_SALES")} -> -0.074284998 | O53: {=_xll.BDP(Inputs!$Q$22,"WORKING_CAPITAL_TO_SALES")} -> -0.11618457 | P53: {=_xll.BDP(Inputs!$Q$23,"WORKING_CAPITAL_TO_SALES")} -> 0.074380604 | Q53: {=_xll.BDP(Inputs!$Q$24,"WORKING_CAPITAL_TO_SALES")} -> -0.070857385 | R53: {=_xll.BDP(Inputs!$Q$25,"WORKING_CAPITAL_TO_SALES")} -> -0.012076208
B54: Cash conversion ratio | C54: 0.79707316 | D54: {=_xll.BDP(Inputs!$E$21,"CF_CASH_FROM_OPER")/_xll.BDP(Inputs!$E$21,"IS_OPER_INC")} -> 1.0200151 | E54: {=_xll.BDP(Inputs!$E$22,"CF_CASH_FROM_OPER")/_xll.BDP(Inputs!$E$22,"IS_OPER_INC")} -> 1.1741651 | F54: {=_xll.BDP(Inputs!$E$23,"CF_CASH_FROM_OPER")/_xll.BDP(Inputs!$E$23,"IS_OPER_INC")} -> 1.8381831 | G54: {=_xll.BDP(Inputs!$E$24,"CF_CASH_FROM_OPER")/_xll.BDP(Inputs!$E$24,"IS_OPER_INC")} -> 1.305518 | H54: {=_xll.BDP(Inputs!$E$25,"CF_CASH_FROM_OPER")/_xll.BDP(Inputs!$E$25,"IS_OPER_INC")} -> 1.1861598 | I54: {=_xll.BDP(Inputs!$K$21,"CF_CASH_FROM_OPER")/_xll.BDP(Inputs!$K$21,"IS_OPER_INC")} -> 0.88301864 | J54: {=_xll.BDP(Inputs!$K$22,"CF_CASH_FROM_OPER")/_xll.BDP(Inputs!$K$22,"IS_OPER_INC")} -> 1.2398505 | K54: {=_xll.BDP(Inputs!$K$23,"CF_CASH_FROM_OPER")/_xll.BDP(Inputs!$K$23,"IS_OPER_INC")} -> 1.3214049 | L54: {=_xll.BDP(Inputs!$K$24,"CF_CASH_FROM_OPER")/_xll.BDP(Inputs!$K$24,"IS_OPER_INC")} -> 1.1325048 | M54: {=_xll.BDP(Inputs!$K$25,"CF_CASH_FROM_OPER")/_xll.BDP(Inputs!$K$25,"IS_OPER_INC")} -> 0.97095745 | N54: {=_xll.BDP(Inputs!$Q$21,"CF_CASH_FROM_OPER")/_xll.BDP(Inputs!$Q$21,"IS_OPER_INC")} -> 0.97051292 | O54: {=_xll.BDP(Inputs!$Q$22,"CF_CASH_FROM_OPER")/_xll.BDP(Inputs!$Q$22,"IS_OPER_INC")} -> 0.87120434 | P54: {=_xll.BDP(Inputs!$Q$23,"CF_CASH_FROM_OPER")/_xll.BDP(Inputs!$Q$23,"IS_OPER_INC")} -> 0.68104484 | Q54: {=_xll.BDP(Inputs!$Q$24,"CF_CASH_FROM_OPER")/_xll.BDP(Inputs!$Q$24,"IS_OPER_INC")} -> 1.0074766 | R54: {=_xll.BDP(Inputs!$Q$25,"CF_CASH_FROM_OPER")/_xll.BDP(Inputs!$Q$25,"IS_OPER_INC")} -> 0.96227741
B55: CFO margin | C55: 0.28736909 | D55: {=_xll.BDP(Inputs!$E$21,"CF_CASH_FROM_OPER")/_xll.BDP(Inputs!$E$21,"SALES_REV_TURN")} -> 0.10691613 | E55: {=_xll.BDP(Inputs!$E$22,"CF_CASH_FROM_OPER")/_xll.BDP(Inputs!$E$22,"SALES_REV_TURN")} -> 0.1175988 | F55: {=_xll.BDP(Inputs!$E$23,"CF_CASH_FROM_OPER")/_xll.BDP(Inputs!$E$23,"SALES_REV_TURN")} -> 0.048584667 | G55: {=_xll.BDP(Inputs!$E$24,"CF_CASH_FROM_OPER")/_xll.BDP(Inputs!$E$24,"SALES_REV_TURN")} -> 0.13459303 | H55: {=_xll.BDP(Inputs!$E$25,"CF_CASH_FROM_OPER")/_xll.BDP(Inputs!$E$25,"SALES_REV_TURN")} -> 0.10626286 | I55: {=_xll.BDP(Inputs!$K$21,"CF_CASH_FROM_OPER")/_xll.BDP(Inputs!$K$21,"SALES_REV_TURN")} -> 0.14975419 | J55: {=_xll.BDP(Inputs!$K$22,"CF_CASH_FROM_OPER")/_xll.BDP(Inputs!$K$22,"SALES_REV_TURN")} -> 0.14569268 | K55: {=_xll.BDP(Inputs!$K$23,"CF_CASH_FROM_OPER")/_xll.BDP(Inputs!$K$23,"SALES_REV_TURN")} -> 0.11131528 | L55: {=_xll.BDP(Inputs!$K$24,"CF_CASH_FROM_OPER")/_xll.BDP(Inputs!$K$24,"SALES_REV_TURN")} -> 0.18180331 | M55: {=_xll.BDP(Inputs!$K$25,"CF_CASH_FROM_OPER")/_xll.BDP(Inputs!$K$25,"SALES_REV_TURN")} -> 0.15021148 | N55: {=_xll.BDP(Inputs!$Q$21,"CF_CASH_FROM_OPER")/_xll.BDP(Inputs!$Q$21,"SALES_REV_TURN")} -> 0.13616173 | O55: {=_xll.BDP(Inputs!$Q$22,"CF_CASH_FROM_OPER")/_xll.BDP(Inputs!$Q$22,"SALES_REV_TURN")} -> 0.21139244 | P55: {=_xll.BDP(Inputs!$Q$23,"CF_CASH_FROM_OPER")/_xll.BDP(Inputs!$Q$23,"SALES_REV_TURN")} -> 0.14459956 | Q55: {=_xll.BDP(Inputs!$Q$24,"CF_CASH_FROM_OPER")/_xll.BDP(Inputs!$Q$24,"SALES_REV_TURN")} -> 0.16123243 | R55: {=_xll.BDP(Inputs!$Q$25,"CF_CASH_FROM_OPER")/_xll.BDP(Inputs!$Q$25,"SALES_REV_TURN")} -> 0.20431819
A57: x | B57: Leverage & Coverage | C57: CAL-MAINE FOODS | D57: =D47 -> VITAL FARMS INC | E57: =E47 -> POST HOLDINGS IN | F57: =F47 -> TYSON FOODS-A | G57: =G47 -> LAMB WESTON | H57: =H47 -> HORMEL FOODS CRP | I57: =I47 -> GENERAL MILLS IN | J57: =J47 -> CONAGRA BRANDS I | K57: =K47 -> PILGRIM'S PRIDE | ... R57: =R47 -> COLGATE-PALMOLIV
B59: Net debt / EBITDA | C59: -0.85375576 | D59: {=_xll.BDP(Inputs!$E$21,"NET_DEBT_TO_EBITDA")} -> -1.5589326 | E59: {=_xll.BDP(Inputs!$E$22,"NET_DEBT_TO_EBITDA")} -> 4.7510762 | F59: {=_xll.BDP(Inputs!$E$23,"NET_DEBT_TO_EBITDA")} -> 3.0049787 | G59: {=_xll.BDP(Inputs!$E$24,"NET_DEBT_TO_EBITDA")} -> 3.8099432 | H59: {=_xll.BDP(Inputs!$E$25,"NET_DEBT_TO_EBITDA")} -> 1.7504057 | I59: {=_xll.BDP(Inputs!$K$21,"NET_DEBT_TO_EBITDA")} -> 2.8400954 | J59: {=_xll.BDP(Inputs!$K$22,"NET_DEBT_TO_EBITDA")} -> 4.4682343 | K59: {=_xll.BDP(Inputs!$K$23,"NET_DEBT_TO_EBITDA")} -> 1.1795194 | L59: {=_xll.BDP(Inputs!$K$24,"NET_DEBT_TO_EBITDA")} -> 3.3923672 | M59: {=_xll.BDP(Inputs!$K$25,"NET_DEBT_TO_EBITDA")} -> #N/A N/A | N59: {=_xll.BDP(Inputs!$Q$21,"NET_DEBT_TO_EBITDA")} -> 3.1534941 | O59: {=_xll.BDP(Inputs!$Q$22,"NET_DEBT_TO_EBITDA")} -> 1.1120268 | P59: {=_xll.BDP(Inputs!$Q$23,"NET_DEBT_TO_EBITDA")} -> 2.4669427 | Q59: {=_xll.BDP(Inputs!$Q$24,"NET_DEBT_TO_EBITDA")} -> 1.6893378 | R59: {=_xll.BDP(Inputs!$Q$25,"NET_DEBT_TO_EBITDA")} -> 1.5047112
B60: Net debt / FCF | C60: -1.3090056 | D60: {=_xll.BDP(Inputs!$E$21,"NET_DEBT")/_xll.BDP(Inputs!$E$21,"CF_FREE_CASH_FLOW")} -> -3.913511 | E60: {=_xll.BDP(Inputs!$E$22,"NET_DEBT")/_xll.BDP(Inputs!$E$22,"CF_FREE_CASH_FLOW")} -> 12.492632 | F60: {=_xll.BDP(Inputs!$E$23,"NET_DEBT")/_xll.BDP(Inputs!$E$23,"CF_FREE_CASH_FLOW")} -> 6.0109739 | G60: {=_xll.BDP(Inputs!$E$24,"NET_DEBT")/_xll.BDP(Inputs!$E$24,"CF_FREE_CASH_FLOW")} -> 18.181226 | H60: {=_xll.BDP(Inputs!$E$25,"NET_DEBT")/_xll.BDP(Inputs!$E$25,"CF_FREE_CASH_FLOW")} -> 2.2226019 | I60: {=_xll.BDP(Inputs!$K$21,"NET_DEBT")/_xll.BDP(Inputs!$K$21,"CF_FREE_CASH_FLOW")} -> 6.5126259 | J60: {=_xll.BDP(Inputs!$K$22,"NET_DEBT")/_xll.BDP(Inputs!$K$22,"CF_FREE_CASH_FLOW")} -> 6.3278059 | K60: {=_xll.BDP(Inputs!$K$23,"NET_DEBT")/_xll.BDP(Inputs!$K$23,"CF_FREE_CASH_FLOW")} -> 1.0163794 | L60: {=_xll.BDP(Inputs!$K$24,"NET_DEBT")/_xll.BDP(Inputs!$K$24,"CF_FREE_CASH_FLOW")} -> 4.9714596 | M60: {=_xll.BDP(Inputs!$K$25,"NET_DEBT")/_xll.BDP(Inputs!$K$25,"CF_FREE_CASH_FLOW")} -> 3.3271079 | N60: {=_xll.BDP(Inputs!$Q$21,"NET_DEBT")/_xll.BDP(Inputs!$Q$21,"CF_FREE_CASH_FLOW")} -> 5.3533176 | O60: {=_xll.BDP(Inputs!$Q$22,"NET_DEBT")/_xll.BDP(Inputs!$Q$22,"CF_FREE_CASH_FLOW")} -> 1.8447736 | P60: {=_xll.BDP(Inputs!$Q$23,"NET_DEBT")/_xll.BDP(Inputs!$Q$23,"CF_FREE_CASH_FLOW")} -> 6.5732968 | Q60: {=_xll.BDP(Inputs!$Q$24,"NET_DEBT")/_xll.BDP(Inputs!$Q$24,"CF_FREE_CASH_FLOW")} -> 2.7290092 | R60: {=_xll.BDP(Inputs!$Q$25,"NET_DEBT")/_xll.BDP(Inputs!$Q$25,"CF_FREE_CASH_FLOW")} -> 2.0462493
B61: Interest coverage | C61: 2510.6846 | D61: {=_xll.BDP(Inputs!$E$21,"IS_OPER_INC")/_xll.BDP(Inputs!$E$21,"IS_INT_EXPENSE")} -> 62.922772 | E61: {=_xll.BDP(Inputs!$E$22,"IS_OPER_INC")/_xll.BDP(Inputs!$E$22,"IS_INT_EXPENSE")} -> 2.507109 | F61: {=_xll.BDP(Inputs!$E$23,"IS_OPER_INC")/_xll.BDP(Inputs!$E$23,"IS_INT_EXPENSE")} -> 2.9293139 | G61: {=_xll.BDP(Inputs!$E$24,"IS_OPER_INC")/_xll.BDP(Inputs!$E$24,"IS_INT_EXPENSE")} -> #VALUE! | H61: {=_xll.BDP(Inputs!$E$25,"IS_OPER_INC")/_xll.BDP(Inputs!$E$25,"IS_INT_EXPENSE")} -> 13.201622 | I61: {=_xll.BDP(Inputs!$K$21,"IS_OPER_INC")/_xll.BDP(Inputs!$K$21,"IS_INT_EXPENSE")} -> 6.0218659 | J61: {=_xll.BDP(Inputs!$K$22,"IS_OPER_INC")/_xll.BDP(Inputs!$K$22,"IS_INT_EXPENSE")} -> 3.1920468 | K61: {=_xll.BDP(Inputs!$K$23,"IS_OPER_INC")/_xll.BDP(Inputs!$K$23,"IS_INT_EXPENSE")} -> 9.344309 | L61: {=_xll.BDP(Inputs!$K$24,"IS_OPER_INC")/_xll.BDP(Inputs!$K$24,"IS_INT_EXPENSE")} -> 8.6611765 | M61: {=_xll.BDP(Inputs!$K$25,"IS_OPER_INC")/_xll.BDP(Inputs!$K$25,"IS_INT_EXPENSE")} -> 7.781457 | N61: {=_xll.BDP(Inputs!$Q$21,"IS_OPER_INC")/_xll.BDP(Inputs!$Q$21,"IS_INT_EXPENSE")} -> 14.022851 | O61: {=_xll.BDP(Inputs!$Q$22,"IS_OPER_INC")/_xll.BDP(Inputs!$Q$22,"IS_INT_EXPENSE")} -> 22.54796 | P61: {=_xll.BDP(Inputs!$Q$23,"IS_OPER_INC")/_xll.BDP(Inputs!$Q$23,"IS_INT_EXPENSE")} -> 6.0338164 | Q61: {=_xll.BDP(Inputs!$Q$24,"IS_OPER_INC")/_xll.BDP(Inputs!$Q$24,"IS_INT_EXPENSE")} -> 11.888889 | R61: {=_xll.BDP(Inputs!$Q$25,"IS_OPER_INC")/_xll.BDP(Inputs!$Q$25,"IS_INT_EXPENSE")} -> 14.616438
B62: Debt / capital | C62: 0 | D62: {=_xll.BDP(Inputs!$E$21,"TOT_DEBT_TO_TOT_CAP")/100} -> 0.064962571 | E62: {=_xll.BDP(Inputs!$E$22,"TOT_DEBT_TO_TOT_CAP")/100} -> 0.63258231 | F62: {=_xll.BDP(Inputs!$E$23,"TOT_DEBT_TO_TOT_CAP")/100} -> 0.36147612 | G62: {=_xll.BDP(Inputs!$E$24,"TOT_DEBT_TO_TOT_CAP")/100} -> 0.70999182 | H62: {=_xll.BDP(Inputs!$E$25,"TOT_DEBT_TO_TOT_CAP")/100} -> 0.27342755 | I62: {=_xll.BDP(Inputs!$K$21,"TOT_DEBT_TO_TOT_CAP")/100} -> 0.62415384 | J62: {=_xll.BDP(Inputs!$K$22,"TOT_DEBT_TO_TOT_CAP")/100} -> 0.48196111 | K62: {=_xll.BDP(Inputs!$K$23,"TOT_DEBT_TO_TOT_CAP")/100} -> 0.45699031 | L62: {=_xll.BDP(Inputs!$K$24,"TOT_DEBT_TO_TOT_CAP")/100} -> 0.63098135 | M62: {=_xll.BDP(Inputs!$K$25,"TOT_DEBT_TO_TOT_CAP")/100} -> 0.5858124 | N62: {=_xll.BDP(Inputs!$Q$21,"TOT_DEBT_TO_TOT_CAP")/100} -> 0.72435606 | O62: {=_xll.BDP(Inputs!$Q$22,"TOT_DEBT_TO_TOT_CAP")/100} -> 0.40415275 | P62: {=_xll.BDP(Inputs!$Q$23,"TOT_DEBT_TO_TOT_CAP")/100} -> 0.63426574 | Q62: {=_xll.BDP(Inputs!$Q$24,"TOT_DEBT_TO_TOT_CAP")/100} -> 0.88617703 | R62: {=_xll.BDP(Inputs!$Q$25,"TOT_DEBT_TO_TOT_CAP")/100} -> 0.93992933
B63: Short term debt / total debt | C63: #DIV/0! | D63: {=_xll.BDP(Inputs!$E$21,"BS_ST_BORROW")/_xll.BDP(Inputs!$E$21,"SHORT_AND_LONG_TERM_DEBT")} -> 0.41587386 | E63: {=_xll.BDP(Inputs!$E$22,"BS_ST_BORROW")/_xll.BDP(Inputs!$E$22,"SHORT_AND_LONG_TERM_DEBT")} -> 0.0059763213 | F63: {=_xll.BDP(Inputs!$E$23,"BS_ST_BORROW")/_xll.BDP(Inputs!$E$23,"SHORT_AND_LONG_TERM_DEBT")} -> 0.023566454 | G63: {=_xll.BDP(Inputs!$E$24,"BS_ST_BORROW")/_xll.BDP(Inputs!$E$24,"SHORT_AND_LONG_TERM_DEBT")} -> 0.11106671 | H63: {=_xll.BDP(Inputs!$E$25,"BS_ST_BORROW")/_xll.BDP(Inputs!$E$25,"SHORT_AND_LONG_TERM_DEBT")} -> 0.013240216 | I63: {=_xll.BDP(Inputs!$K$21,"BS_ST_BORROW")/_xll.BDP(Inputs!$K$21,"SHORT_AND_LONG_TERM_DEBT")} -> 0.15171246 | J63: {=_xll.BDP(Inputs!$K$22,"BS_ST_BORROW")/_xll.BDP(Inputs!$K$22,"SHORT_AND_LONG_TERM_DEBT")} -> 0.22539889 | K63: {=_xll.BDP(Inputs!$K$23,"BS_ST_BORROW")/_xll.BDP(Inputs!$K$23,"SHORT_AND_LONG_TERM_DEBT")} -> 0.049600152 | L63: {=_xll.BDP(Inputs!$K$24,"BS_ST_BORROW")/_xll.BDP(Inputs!$K$24,"SHORT_AND_LONG_TERM_DEBT")} -> 0.18907891 | M63: {=_xll.BDP(Inputs!$K$25,"BS_ST_BORROW")/_xll.BDP(Inputs!$K$25,"SHORT_AND_LONG_TERM_DEBT")} -> 0.21425661 | N63: {=_xll.BDP(Inputs!$Q$21,"BS_ST_BORROW")/_xll.BDP(Inputs!$Q$21,"SHORT_AND_LONG_TERM_DEBT")} -> 0.16175577 | O63: {=_xll.BDP(Inputs!$Q$22,"BS_ST_BORROW")/_xll.BDP(Inputs!$Q$22,"SHORT_AND_LONG_TERM_DEBT")} -> 0.27543424 | P63: {=_xll.BDP(Inputs!$Q$23,"BS_ST_BORROW")/_xll.BDP(Inputs!$Q$23,"SHORT_AND_LONG_TERM_DEBT")} -> 0.05328523 | Q63: {=_xll.BDP(Inputs!$Q$24,"BS_ST_BORROW")/_xll.BDP(Inputs!$Q$24,"SHORT_AND_LONG_TERM_DEBT")} -> 0.088716842 | R63: {=_xll.BDP(Inputs!$Q$25,"BS_ST_BORROW")/_xll.BDP(Inputs!$Q$25,"SHORT_AND_LONG_TERM_DEBT")} -> 0.090108083
A65: x | B65: Liquidity | C65: CAL-MAINE FOODS | D65: =D57 -> VITAL FARMS INC | E65: =E57 -> POST HOLDINGS IN | F65: =F57 -> TYSON FOODS-A | G65: =G57 -> LAMB WESTON | H65: =H57 -> HORMEL FOODS CRP | I65: =I57 -> GENERAL MILLS IN | J65: =J57 -> CONAGRA BRANDS I | K65: =K57 -> PILGRIM'S PRIDE | ... R65: =R57 -> COLGATE-PALMOLIV
B67: Current ratio | C67: 6.3822798 | D67: {=_xll.BDP(Inputs!$E$21,"CUR_RATIO")} -> 3.1331228 | E67: {=_xll.BDP(Inputs!$E$22,"CUR_RATIO")} -> 2.3617314 | F67: {=_xll.BDP(Inputs!$E$23,"CUR_RATIO")} -> 2.0369751 | G67: {=_xll.BDP(Inputs!$E$24,"CUR_RATIO")} -> 1.377168 | H67: {=_xll.BDP(Inputs!$E$25,"CUR_RATIO")} -> 2.3200731 | I67: {=_xll.BDP(Inputs!$K$21,"CUR_RATIO")} -> 0.6714393 | J67: {=_xll.BDP(Inputs!$K$22,"CUR_RATIO")} -> 0.71137364 | K67: {=_xll.BDP(Inputs!$K$23,"CUR_RATIO")} -> 2.0062289 | L67: {=_xll.BDP(Inputs!$K$24,"CUR_RATIO")} -> 0.82094114 | M67: {=_xll.BDP(Inputs!$K$25,"CUR_RATIO")} -> 0.76064041 | N67: {=_xll.BDP(Inputs!$Q$21,"CUR_RATIO")} -> 0.81893709 | O67: {=_xll.BDP(Inputs!$Q$22,"CUR_RATIO")} -> 0.70419879 | P67: {=_xll.BDP(Inputs!$Q$23,"CUR_RATIO")} -> 1.0296249 | Q67: {=_xll.BDP(Inputs!$Q$24,"CUR_RATIO")} -> 0.79668761 | R67: {=_xll.BDP(Inputs!$Q$25,"CUR_RATIO")} -> 0.92325056
B68: Quick ratio | C68: 5.3058783 | D68: {=_xll.BDP(Inputs!$E$21,"QUICK_RATIO")} -> 2.7331941 | E68: {=_xll.BDP(Inputs!$E$22,"QUICK_RATIO")} -> 1.4502064 | F68: {=_xll.BDP(Inputs!$E$23,"QUICK_RATIO")} -> 0.861291 | G68: {=_xll.BDP(Inputs!$E$24,"QUICK_RATIO")} -> 0.57743902 | H68: {=_xll.BDP(Inputs!$E$25,"QUICK_RATIO")} -> 1.1323749 | I68: {=_xll.BDP(Inputs!$K$21,"QUICK_RATIO")} -> 0.27487814 | J68: {=_xll.BDP(Inputs!$K$22,"QUICK_RATIO")} -> 0.19411628 | K68: {=_xll.BDP(Inputs!$K$23,"QUICK_RATIO")} -> 1.1847439 | L68: {=_xll.BDP(Inputs!$K$24,"QUICK_RATIO")} -> 0.40326155 | M68: {=_xll.BDP(Inputs!$K$25,"QUICK_RATIO")} -> 0.45747801 | N68: {=_xll.BDP(Inputs!$Q$21,"QUICK_RATIO")} -> 0.56294394 | O68: {=_xll.BDP(Inputs!$Q$22,"QUICK_RATIO")} -> 0.43654667 | P68: {=_xll.BDP(Inputs!$Q$23,"QUICK_RATIO")} -> 0.71844429 | Q68: {=_xll.BDP(Inputs!$Q$24,"QUICK_RATIO")} -> 0.43260994 | R68: {=_xll.BDP(Inputs!$Q$25,"QUICK_RATIO")} -> 0.48220177
B69: Cash ratio | C69: 4.5143674 | D69: {=_xll.BDP(Inputs!$E$21,"CASH_RATIO")} -> 2.041195 | E69: {=_xll.BDP(Inputs!$E$22,"CASH_RATIO")} -> 0.83331569 | F69: {=_xll.BDP(Inputs!$E$23,"CASH_RATIO")} -> 0.35867976 | G69: {=_xll.BDP(Inputs!$E$24,"CASH_RATIO")} -> 0.047899729 | H69: {=_xll.BDP(Inputs!$E$25,"CASH_RATIO")} -> 0.54786218 | I69: {=_xll.BDP(Inputs!$K$21,"CASH_RATIO")} -> 0.046313619 | J69: {=_xll.BDP(Inputs!$K$22,"CASH_RATIO")} -> 0.015751679 | K69: {=_xll.BDP(Inputs!$K$23,"CASH_RATIO")} -> 0.79965817 | L69: {=_xll.BDP(Inputs!$K$24,"CASH_RATIO")} -> 0.18363157 | M69: {=_xll.BDP(Inputs!$K$25,"CASH_RATIO")} -> 0.28996592 | N69: {=_xll.BDP(Inputs!$Q$21,"CASH_RATIO")} -> 0.29382293 | O69: {=_xll.BDP(Inputs!$Q$22,"CASH_RATIO")} -> 0.26501747 | P69: {=_xll.BDP(Inputs!$Q$23,"CASH_RATIO")} -> 0.57709216 | Q69: {=_xll.BDP(Inputs!$Q$24,"CASH_RATIO")} -> 0.14577384 | R69: {=_xll.BDP(Inputs!$Q$25,"CASH_RATIO")} -> 0.21809342
A71: x | B71: Cash Deployment | C71: CAL-MAINE FOODS | D71: =D65 -> VITAL FARMS INC | E71: =E65 -> POST HOLDINGS IN | F71: =F65 -> TYSON FOODS-A | G71: =G65 -> LAMB WESTON | H71: =H65 -> HORMEL FOODS CRP | I71: =I65 -> GENERAL MILLS IN | J71: =J65 -> CONAGRA BRANDS I | K71: =K65 -> PILGRIM'S PRIDE | ... R71: =R65 -> COLGATE-PALMOLIV
B73: Capex intensity | C73: 0.037836544 | D73: {=-_xll.BDP(Inputs!$E$21,"ACQUIS_OF_FIXED_INTANG")/_xll.BDP(Inputs!$E$21,"SALES_REV_TURN")} -> 0.047246692 | E73: {=-_xll.BDP(Inputs!$E$22,"ACQUIS_OF_FIXED_INTANG")/_xll.BDP(Inputs!$E$22,"SALES_REV_TURN")} -> 0.054211317 | F73: {=-_xll.BDP(Inputs!$E$23,"ACQUIS_OF_FIXED_INTANG")/_xll.BDP(Inputs!$E$23,"SALES_REV_TURN")} -> 0.021234688 | G73: {=-_xll.BDP(Inputs!$E$24,"ACQUIS_OF_FIXED_INTANG")/_xll.BDP(Inputs!$E$24,"SALES_REV_TURN")} -> 0.098925798 | H73: {=-_xll.BDP(Inputs!$E$25,"ACQUIS_OF_FIXED_INTANG")/_xll.BDP(Inputs!$E$25,"SALES_REV_TURN")} -> 0.021512068 | I73: {=-_xll.BDP(Inputs!$K$21,"ACQUIS_OF_FIXED_INTANG")/_xll.BDP(Inputs!$K$21,"SALES_REV_TURN")} -> 0.032088717 | J73: {=-_xll.BDP(Inputs!$K$22,"ACQUIS_OF_FIXED_INTANG")/_xll.BDP(Inputs!$K$22,"SALES_REV_TURN")} -> 0.033523354 | K73: {=-_xll.BDP(Inputs!$K$23,"ACQUIS_OF_FIXED_INTANG")/_xll.BDP(Inputs!$K$23,"SALES_REV_TURN")} -> 0.026633027 | L73: {=-_xll.BDP(Inputs!$K$24,"ACQUIS_OF_FIXED_INTANG")/_xll.BDP(Inputs!$K$24,"SALES_REV_TURN")} -> 0.065013083 | M73: {=-_xll.BDP(Inputs!$K$25,"ACQUIS_OF_FIXED_INTANG")/_xll.BDP(Inputs!$K$25,"SALES_REV_TURN")} -> 0.028603874 | N73: {=-_xll.BDP(Inputs!$Q$21,"ACQUIS_OF_FIXED_INTANG")/_xll.BDP(Inputs!$Q$21,"SALES_REV_TURN")} -> 0.057896227 | O73: {=-_xll.BDP(Inputs!$Q$22,"ACQUIS_OF_FIXED_INTANG")/_xll.BDP(Inputs!$Q$22,"SALES_REV_TURN")} -> 0.044765317 | P73: {=-_xll.BDP(Inputs!$Q$23,"ACQUIS_OF_FIXED_INTANG")/_xll.BDP(Inputs!$Q$23,"SALES_REV_TURN")} -> 0.043857972 | Q73: {=-_xll.BDP(Inputs!$Q$24,"ACQUIS_OF_FIXED_INTANG")/_xll.BDP(Inputs!$Q$24,"SALES_REV_TURN")} -> 0.035945757 | R73: {=-_xll.BDP(Inputs!$Q$25,"ACQUIS_OF_FIXED_INTANG")/_xll.BDP(Inputs!$Q$25,"SALES_REV_TURN")} -> 0.027909059
B74: Capex / depreciation | C74: 1.7150956 | D74: {=-_xll.BDP(Inputs!$E$21,"ACQUIS_OF_FIXED_INTANG")/_xll.BDP(Inputs!$E$21,"CF_DEPR_AMORT")} -> 2.1878867 | E74: {=-_xll.BDP(Inputs!$E$22,"ACQUIS_OF_FIXED_INTANG")/_xll.BDP(Inputs!$E$22,"CF_DEPR_AMORT")} -> 0.90060809 | F74: {=-_xll.BDP(Inputs!$E$23,"ACQUIS_OF_FIXED_INTANG")/_xll.BDP(Inputs!$E$23,"CF_DEPR_AMORT")} -> 0.80857143 | G74: {=-_xll.BDP(Inputs!$E$24,"ACQUIS_OF_FIXED_INTANG")/_xll.BDP(Inputs!$E$24,"CF_DEPR_AMORT")} -> 1.566135 | H74: {=-_xll.BDP(Inputs!$E$25,"ACQUIS_OF_FIXED_INTANG")/_xll.BDP(Inputs!$E$25,"CF_DEPR_AMORT")} -> 0.99489828 | I74: {=-_xll.BDP(Inputs!$K$21,"ACQUIS_OF_FIXED_INTANG")/_xll.BDP(Inputs!$K$21,"CF_DEPR_AMORT")} -> 1.1601113 | J74: {=-_xll.BDP(Inputs!$K$22,"ACQUIS_OF_FIXED_INTANG")/_xll.BDP(Inputs!$K$22,"CF_DEPR_AMORT")} -> 0.99769349 | K74: {=-_xll.BDP(Inputs!$K$23,"ACQUIS_OF_FIXED_INTANG")/_xll.BDP(Inputs!$K$23,"CF_DEPR_AMORT")} -> 1.0980831 | L74: {=-_xll.BDP(Inputs!$K$24,"ACQUIS_OF_FIXED_INTANG")/_xll.BDP(Inputs!$K$24,"CF_DEPR_AMORT")} -> 1.6647125 | M74: {=-_xll.BDP(Inputs!$K$25,"ACQUIS_OF_FIXED_INTANG")/_xll.BDP(Inputs!$K$25,"CF_DEPR_AMORT")} -> 0.98918611 | N74: {=-_xll.BDP(Inputs!$Q$21,"ACQUIS_OF_FIXED_INTANG")/_xll.BDP(Inputs!$Q$21,"CF_DEPR_AMORT")} -> 1.6829114 | O74: {=-_xll.BDP(Inputs!$Q$22,"ACQUIS_OF_FIXED_INTANG")/_xll.BDP(Inputs!$Q$22,"CF_DEPR_AMORT")} -> 1.3252547 | P74: {=-_xll.BDP(Inputs!$Q$23,"ACQUIS_OF_FIXED_INTANG")/_xll.BDP(Inputs!$Q$23,"CF_DEPR_AMORT")} -> 1.92 | Q74: {=-_xll.BDP(Inputs!$Q$24,"ACQUIS_OF_FIXED_INTANG")/_xll.BDP(Inputs!$Q$24,"CF_DEPR_AMORT")} -> 0.92317542 | R74: {=-_xll.BDP(Inputs!$Q$25,"ACQUIS_OF_FIXED_INTANG")/_xll.BDP(Inputs!$Q$25,"CF_DEPR_AMORT")} -> 0.92727273
B75: R&D capitalization rate | C75: #VALUE! | D75: {=_xll.BDP(Inputs!$E$21,"EXPND_INCUR_ON_R&D_CAPITALZD")/_xll.BDP(Inputs!$E$21,"IS_RD_EXPEND")} -> #VALUE! | E75: {=_xll.BDP(Inputs!$E$22,"EXPND_INCUR_ON_R&D_CAPITALZD")/_xll.BDP(Inputs!$E$22,"IS_RD_EXPEND")} -> #VALUE! | F75: {=_xll.BDP(Inputs!$E$23,"EXPND_INCUR_ON_R&D_CAPITALZD")/_xll.BDP(Inputs!$E$23,"IS_RD_EXPEND")} -> #VALUE! | G75: {=_xll.BDP(Inputs!$E$24,"EXPND_INCUR_ON_R&D_CAPITALZD")/_xll.BDP(Inputs!$E$24,"IS_RD_EXPEND")} -> #VALUE! | H75: {=_xll.BDP(Inputs!$E$25,"EXPND_INCUR_ON_R&D_CAPITALZD")/_xll.BDP(Inputs!$E$25,"IS_RD_EXPEND")} -> #VALUE! | I75: {=_xll.BDP(Inputs!$K$21,"EXPND_INCUR_ON_R&D_CAPITALZD")/_xll.BDP(Inputs!$K$21,"IS_RD_EXPEND")} -> #VALUE! | J75: {=_xll.BDP(Inputs!$K$22,"EXPND_INCUR_ON_R&D_CAPITALZD")/_xll.BDP(Inputs!$K$22,"IS_RD_EXPEND")} -> #VALUE! | K75: {=_xll.BDP(Inputs!$K$23,"EXPND_INCUR_ON_R&D_CAPITALZD")/_xll.BDP(Inputs!$K$23,"IS_RD_EXPEND")} -> #VALUE! | L75: {=_xll.BDP(Inputs!$K$24,"EXPND_INCUR_ON_R&D_CAPITALZD")/_xll.BDP(Inputs!$K$24,"IS_RD_EXPEND")} -> #VALUE! | M75: {=_xll.BDP(Inputs!$K$25,"EXPND_INCUR_ON_R&D_CAPITALZD")/_xll.BDP(Inputs!$K$25,"IS_RD_EXPEND")} -> #VALUE! | N75: {=_xll.BDP(Inputs!$Q$21,"EXPND_INCUR_ON_R&D_CAPITALZD")/_xll.BDP(Inputs!$Q$21,"IS_RD_EXPEND")} -> #VALUE! | O75: {=_xll.BDP(Inputs!$Q$22,"EXPND_INCUR_ON_R&D_CAPITALZD")/_xll.BDP(Inputs!$Q$22,"IS_RD_EXPEND")} -> #VALUE! | P75: {=_xll.BDP(Inputs!$Q$23,"EXPND_INCUR_ON_R&D_CAPITALZD")/_xll.BDP(Inputs!$Q$23,"IS_RD_EXPEND")} -> #VALUE! | Q75: {=_xll.BDP(Inputs!$Q$24,"EXPND_INCUR_ON_R&D_CAPITALZD")/_xll.BDP(Inputs!$Q$24,"IS_RD_EXPEND")} -> #VALUE! | R75: {=_xll.BDP(Inputs!$Q$25,"EXPND_INCUR_ON_R&D_CAPITALZD")/_xll.BDP(Inputs!$Q$25,"IS_RD_EXPEND")} -> #VALUE!
B76: R&D capitalization test | C76: #VALUE! | D76: {=_xll.BDP(Inputs!$E$21,"EXPND_INCUR_ON_R&D_CAPITALZD")/IFERROR(VALUE(_xll.BDP(Inputs!$E$21,"AMORTIZATION_OF_R&D")),_xll.BDP(Inputs!$E$21,"BEST_AMORTIZATION"))} -> #VALUE! | E76: {=_xll.BDP(Inputs!$E$22,"EXPND_INCUR_ON_R&D_CAPITALZD")/IFERROR(VALUE(_xll.BDP(Inputs!$E$22,"AMORTIZATION_OF_R&D")),_xll.BDP(Inputs!$E$22,"BEST_AMORTIZATION"))} -> #VALUE! | F76: {=_xll.BDP(Inputs!$E$23,"EXPND_INCUR_ON_R&D_CAPITALZD")/IFERROR(VALUE(_xll.BDP(Inputs!$E$23,"AMORTIZATION_OF_R&D")),_xll.BDP(Inputs!$E$23,"BEST_AMORTIZATION"))} -> #VALUE! | G76: {=_xll.BDP(Inputs!$E$24,"EXPND_INCUR_ON_R&D_CAPITALZD")/IFERROR(VALUE(_xll.BDP(Inputs!$E$24,"AMORTIZATION_OF_R&D")),_xll.BDP(Inputs!$E$24,"BEST_AMORTIZATION"))} -> #VALUE! | H76: {=_xll.BDP(Inputs!$E$25,"EXPND_INCUR_ON_R&D_CAPITALZD")/IFERROR(VALUE(_xll.BDP(Inputs!$E$25,"AMORTIZATION_OF_R&D")),_xll.BDP(Inputs!$E$25,"BEST_AMORTIZATION"))} -> #VALUE! | I76: {=_xll.BDP(Inputs!$K$21,"EXPND_INCUR_ON_R&D_CAPITALZD")/IFERROR(VALUE(_xll.BDP(Inputs!$K$21,"AMORTIZATION_OF_R&D")),_xll.BDP(Inputs!$K$21,"BEST_AMORTIZATION"))} -> #VALUE! | J76: {=_xll.BDP(Inputs!$K$22,"EXPND_INCUR_ON_R&D_CAPITALZD")/IFERROR(VALUE(_xll.BDP(Inputs!$K$22,"AMORTIZATION_OF_R&D")),_xll.BDP(Inputs!$K$22,"BEST_AMORTIZATION"))} -> #VALUE! | K76: {=_xll.BDP(Inputs!$K$23,"EXPND_INCUR_ON_R&D_CAPITALZD")/IFERROR(VALUE(_xll.BDP(Inputs!$K$23,"AMORTIZATION_OF_R&D")),_xll.BDP(Inputs!$K$23,"BEST_AMORTIZATION"))} -> #VALUE! | L76: {=_xll.BDP(Inputs!$K$24,"EXPND_INCUR_ON_R&D_CAPITALZD")/IFERROR(VALUE(_xll.BDP(Inputs!$K$24,"AMORTIZATION_OF_R&D")),_xll.BDP(Inputs!$K$24,"BEST_AMORTIZATION"))} -> #VALUE! | M76: {=_xll.BDP(Inputs!$K$25,"EXPND_INCUR_ON_R&D_CAPITALZD")/IFERROR(VALUE(_xll.BDP(Inputs!$K$25,"AMORTIZATION_OF_R&D")),_xll.BDP(Inputs!$K$25,"BEST_AMORTIZATION"))} -> #VALUE! | N76: {=_xll.BDP(Inputs!$Q$21,"EXPND_INCUR_ON_R&D_CAPITALZD")/IFERROR(VALUE(_xll.BDP(Inputs!$Q$21,"AMORTIZATION_OF_R&D")),_xll.BDP(Inputs!$Q$21,"BEST_AMORTIZATION"))} -> #VALUE! | O76: {=_xll.BDP(Inputs!$Q$22,"EXPND_INCUR_ON_R&D_CAPITALZD")/IFERROR(VALUE(_xll.BDP(Inputs!$Q$22,"AMORTIZATION_OF_R&D")),_xll.BDP(Inputs!$Q$22,"BEST_AMORTIZATION"))} -> #VALUE! | P76: {=_xll.BDP(Inputs!$Q$23,"EXPND_INCUR_ON_R&D_CAPITALZD")/IFERROR(VALUE(_xll.BDP(Inputs!$Q$23,"AMORTIZATION_OF_R&D")),_xll.BDP(Inputs!$Q$23,"BEST_AMORTIZATION"))} -> #VALUE! | Q76: {=_xll.BDP(Inputs!$Q$24,"EXPND_INCUR_ON_R&D_CAPITALZD")/IFERROR(VALUE(_xll.BDP(Inputs!$Q$24,"AMORTIZATION_OF_R&D")),_xll.BDP(Inputs!$Q$24,"BEST_AMORTIZATION"))} -> #VALUE! | R76: {=_xll.BDP(Inputs!$Q$25,"EXPND_INCUR_ON_R&D_CAPITALZD")/IFERROR(VALUE(_xll.BDP(Inputs!$Q$25,"AMORTIZATION_OF_R&D")),_xll.BDP(Inputs!$Q$25,"BEST_AMORTIZATION"))} -> #VALUE!
B77: Dividend payout | C77: 0.27049961 | D77: {=_xll.BDP(Inputs!$E$21,"DVD_PAYOUT_RATIO")/100} -> 0 | E77: {=_xll.BDP(Inputs!$E$22,"DVD_PAYOUT_RATIO")/100} -> 0 | F77: {=_xll.BDP(Inputs!$E$23,"DVD_PAYOUT_RATIO")/100} -> 0.85350718 | G77: {=_xll.BDP(Inputs!$E$24,"DVD_PAYOUT_RATIO")/100} -> 0.57922732 | H77: {=_xll.BDP(Inputs!$E$25,"DVD_PAYOUT_RATIO")/100} -> 0.76936741 | I77: {=_xll.BDP(Inputs!$K$21,"DVD_PAYOUT_RATIO")/100} -> 0.57981875 | J77: {=_xll.BDP(Inputs!$K$22,"DVD_PAYOUT_RATIO")/100} -> 0.5810656 | K77: {=_xll.BDP(Inputs!$K$23,"DVD_PAYOUT_RATIO")/100} -> 0 | L77: {=_xll.BDP(Inputs!$K$24,"DVD_PAYOUT_RATIO")/100} -> 0.71811834 | M77: {=_xll.BDP(Inputs!$K$25,"DVD_PAYOUT_RATIO")/100} -> 0.6382083 | N77: {=_xll.BDP(Inputs!$Q$21,"DVD_PAYOUT_RATIO")/100} -> 0.76405199 | O77: {=_xll.BDP(Inputs!$Q$22,"DVD_PAYOUT_RATIO")/100} -> 0.61083419 | P77: {=_xll.BDP(Inputs!$Q$23,"DVD_PAYOUT_RATIO")/100} -> 0.78632866 | Q77: {=_xll.BDP(Inputs!$Q$24,"DVD_PAYOUT_RATIO")/100} -> 0.64350806 | R77: {=_xll.BDP(Inputs!$Q$25,"DVD_PAYOUT_RATIO")/100} -> 0.56137695
B78: FCF payout | C78: 0.31032348 | D78: {=_xll.BDP(Inputs!$E$21,"TOTAL_PAYOUT")/_xll.BDP(Inputs!$E$21,"CF_FREE_CASH_FLOW")} -> -0.38971198 | E78: {=_xll.BDP(Inputs!$E$22,"TOTAL_PAYOUT")/_xll.BDP(Inputs!$E$22,"CF_FREE_CASH_FLOW")} -> 0.6035444 | F78: {=_xll.BDP(Inputs!$E$23,"TOTAL_PAYOUT")/_xll.BDP(Inputs!$E$23,"CF_FREE_CASH_FLOW")} -> 0.48960767 | G78: {=_xll.BDP(Inputs!$E$24,"TOTAL_PAYOUT")/_xll.BDP(Inputs!$E$24,"CF_FREE_CASH_FLOW")} -> 2.1247284 | H78: {=_xll.BDP(Inputs!$E$25,"TOTAL_PAYOUT")/_xll.BDP(Inputs!$E$25,"CF_FREE_CASH_FLOW")} -> 0.5727593 | I78: {=_xll.BDP(Inputs!$K$21,"TOTAL_PAYOUT")/_xll.BDP(Inputs!$K$21,"CF_FREE_CASH_FLOW")} -> 1.0908786 | J78: {=_xll.BDP(Inputs!$K$22,"TOTAL_PAYOUT")/_xll.BDP(Inputs!$K$22,"CF_FREE_CASH_FLOW")} -> 0.51406418 | K78: {=_xll.BDP(Inputs!$K$23,"TOTAL_PAYOUT")/_xll.BDP(Inputs!$K$23,"CF_FREE_CASH_FLOW")} -> 0 | L78: {=_xll.BDP(Inputs!$K$24,"TOTAL_PAYOUT")/_xll.BDP(Inputs!$K$24,"CF_FREE_CASH_FLOW")} -> 1.0289934 | M78: {=_xll.BDP(Inputs!$K$25,"TOTAL_PAYOUT")/_xll.BDP(Inputs!$K$25,"CF_FREE_CASH_FLOW")} -> 0.70021227 | N78: {=_xll.BDP(Inputs!$Q$21,"TOTAL_PAYOUT")/_xll.BDP(Inputs!$Q$21,"CF_FREE_CASH_FLOW")} -> 1.1345728 | O78: {=_xll.BDP(Inputs!$Q$22,"TOTAL_PAYOUT")/_xll.BDP(Inputs!$Q$22,"CF_FREE_CASH_FLOW")} -> 0.91659873 | P78: {=_xll.BDP(Inputs!$Q$23,"TOTAL_PAYOUT")/_xll.BDP(Inputs!$Q$23,"CF_FREE_CASH_FLOW")} -> 1.9955988 | Q78: {=_xll.BDP(Inputs!$Q$24,"TOTAL_PAYOUT")/_xll.BDP(Inputs!$Q$24,"CF_FREE_CASH_FLOW")} -> 0.99551452 | R78: {=_xll.BDP(Inputs!$Q$25,"TOTAL_PAYOUT")/_xll.BDP(Inputs!$Q$25,"CF_FREE_CASH_FLOW")} -> 0.76737516
B79: Buybacks as % CFO | C79: 0.044052831 | D79: {=-_xll.BDP(Inputs!$E$21,"CF_DECR_CAP_STOCK")/_xll.BDP(Inputs!$E$21,"CF_CASH_FROM_OPER")} -> 0 | E79: {=-_xll.BDP(Inputs!$E$22,"CF_DECR_CAP_STOCK")/_xll.BDP(Inputs!$E$22,"CF_CASH_FROM_OPER")} -> 0.32274337 | F79: {=-_xll.BDP(Inputs!$E$23,"CF_DECR_CAP_STOCK")/_xll.BDP(Inputs!$E$23,"CF_CASH_FROM_OPER")} -> 0.018918919 | G79: {=-_xll.BDP(Inputs!$E$24,"CF_DECR_CAP_STOCK")/_xll.BDP(Inputs!$E$24,"CF_CASH_FROM_OPER")} -> 0.33905332 | H79: {=-_xll.BDP(Inputs!$E$25,"CF_DECR_CAP_STOCK")/_xll.BDP(Inputs!$E$25,"CF_CASH_FROM_OPER")} -> 0 | I79: {=-_xll.BDP(Inputs!$K$21,"CF_DECR_CAP_STOCK")/_xll.BDP(Inputs!$K$21,"CF_CASH_FROM_OPER")} -> 0.41220615 | J79: {=-_xll.BDP(Inputs!$K$22,"CF_DECR_CAP_STOCK")/_xll.BDP(Inputs!$K$22,"CF_CASH_FROM_OPER")} -> 0.050002955 | K79: {=-_xll.BDP(Inputs!$K$23,"CF_DECR_CAP_STOCK")/_xll.BDP(Inputs!$K$23,"CF_CASH_FROM_OPER")} -> 0 | L79: {=-_xll.BDP(Inputs!$K$24,"CF_DECR_CAP_STOCK")/_xll.BDP(Inputs!$K$24,"CF_CASH_FROM_OPER")} -> 0.28053973 | M79: {=-_xll.BDP(Inputs!$K$25,"CF_DECR_CAP_STOCK")/_xll.BDP(Inputs!$K$25,"CF_CASH_FROM_OPER")} -> 0.16522406 | N79: {=-_xll.BDP(Inputs!$Q$21,"CF_DECR_CAP_STOCK")/_xll.BDP(Inputs!$Q$21,"CF_CASH_FROM_OPER")} -> 0.079955225 | O79: {=-_xll.BDP(Inputs!$Q$22,"CF_DECR_CAP_STOCK")/_xll.BDP(Inputs!$Q$22,"CF_CASH_FROM_OPER")} -> 0.36482012 | P79: {=-_xll.BDP(Inputs!$Q$23,"CF_DECR_CAP_STOCK")/_xll.BDP(Inputs!$Q$23,"CF_CASH_FROM_OPER")} -> 0.26377663 | Q79: {=-_xll.BDP(Inputs!$Q$24,"CF_DECR_CAP_STOCK")/_xll.BDP(Inputs!$Q$24,"CF_CASH_FROM_OPER")} -> 0.30921459 | R79: {=-_xll.BDP(Inputs!$Q$25,"CF_DECR_CAP_STOCK")/_xll.BDP(Inputs!$Q$25,"CF_CASH_FROM_OPER")} -> 0.42342342
A81: x | B81: Earnings Quality | C81: CAL-MAINE FOODS | D81: =D71 -> VITAL FARMS INC | E81: =E71 -> POST HOLDINGS IN | F81: =F71 -> TYSON FOODS-A | G81: =G71 -> LAMB WESTON | H81: =H71 -> HORMEL FOODS CRP | I81: =I71 -> GENERAL MILLS IN | J81: =J71 -> CONAGRA BRANDS I | K81: =K71 -> PILGRIM'S PRIDE | ... R81: =R71 -> COLGATE-PALMOLIV
B83: Cash/earnings conversion | C83: 5.4032303 | D83: {=_xll.BDP(Inputs!$E$21,"cf_cash_from_oper")/_xll.BDP(Inputs!$E$21,"BEST_NET_INCOME")} -> 4.8593703 | E83: {=_xll.BDP(Inputs!$E$22,"cf_cash_from_oper")/_xll.BDP(Inputs!$E$22,"BEST_NET_INCOME")} -> 8.19978 | F83: {=_xll.BDP(Inputs!$E$23,"cf_cash_from_oper")/_xll.BDP(Inputs!$E$23,"BEST_NET_INCOME")} -> 8.3401761 | G83: {=_xll.BDP(Inputs!$E$24,"cf_cash_from_oper")/_xll.BDP(Inputs!$E$24,"BEST_NET_INCOME")} -> 9.7234043 | H83: {=_xll.BDP(Inputs!$E$25,"cf_cash_from_oper")/_xll.BDP(Inputs!$E$25,"BEST_NET_INCOME")} -> 5.9704761 | I83: {=_xll.BDP(Inputs!$K$21,"cf_cash_from_oper")/_xll.BDP(Inputs!$K$21,"BEST_NET_INCOME")} -> 5.2731058 | J83: {=_xll.BDP(Inputs!$K$22,"cf_cash_from_oper")/_xll.BDP(Inputs!$K$22,"BEST_NET_INCOME")} -> 7.9405456 | K83: {=_xll.BDP(Inputs!$K$23,"cf_cash_from_oper")/_xll.BDP(Inputs!$K$23,"BEST_NET_INCOME")} -> 5.7451703 | L83: {=_xll.BDP(Inputs!$K$24,"cf_cash_from_oper")/_xll.BDP(Inputs!$K$24,"BEST_NET_INCOME")} -> #VALUE! | M83: {=_xll.BDP(Inputs!$K$25,"cf_cash_from_oper")/_xll.BDP(Inputs!$K$25,"BEST_NET_INCOME")} -> #VALUE! | N83: {=_xll.BDP(Inputs!$Q$21,"cf_cash_from_oper")/_xll.BDP(Inputs!$Q$21,"BEST_NET_INCOME")} -> 4.0248591 | O83: {=_xll.BDP(Inputs!$Q$22,"cf_cash_from_oper")/_xll.BDP(Inputs!$Q$22,"BEST_NET_INCOME")} -> 3.8578713 | P83: {=_xll.BDP(Inputs!$Q$23,"cf_cash_from_oper")/_xll.BDP(Inputs!$Q$23,"BEST_NET_INCOME")} -> 2.0273938 | Q83: {=_xll.BDP(Inputs!$Q$24,"cf_cash_from_oper")/_xll.BDP(Inputs!$Q$24,"BEST_NET_INCOME")} -> 5.6123326 | R83: {=_xll.BDP(Inputs!$Q$25,"cf_cash_from_oper")/_xll.BDP(Inputs!$Q$25,"BEST_NET_INCOME")} -> 5.601091
B84: FCF / net income | C84: 4.6918122 | D84: {=_xll.BDP(Inputs!$E$21,"cf_free_cash_flow")/_xll.BDP(Inputs!$E$21,"BEST_NET_INCOME")} -> 2.711994 | E84: {=_xll.BDP(Inputs!$E$22,"cf_free_cash_flow")/_xll.BDP(Inputs!$E$22,"BEST_NET_INCOME")} -> 4.419802 | F84: {=_xll.BDP(Inputs!$E$23,"cf_free_cash_flow")/_xll.BDP(Inputs!$E$23,"BEST_NET_INCOME")} -> 4.6949717 | G84: {=_xll.BDP(Inputs!$E$24,"cf_free_cash_flow")/_xll.BDP(Inputs!$E$24,"BEST_NET_INCOME")} -> 2.5767077 | H84: {=_xll.BDP(Inputs!$E$25,"cf_free_cash_flow")/_xll.BDP(Inputs!$E$25,"BEST_NET_INCOME")} -> 4.7618008 | I84: {=_xll.BDP(Inputs!$K$21,"cf_free_cash_flow")/_xll.BDP(Inputs!$K$21,"BEST_NET_INCOME")} -> 4.1432061 | J84: {=_xll.BDP(Inputs!$K$22,"cf_free_cash_flow")/_xll.BDP(Inputs!$K$22,"BEST_NET_INCOME")} -> 6.1134551 | K84: {=_xll.BDP(Inputs!$K$23,"cf_free_cash_flow")/_xll.BDP(Inputs!$K$23,"BEST_NET_INCOME")} -> 4.3705947 | L84: {=_xll.BDP(Inputs!$K$24,"cf_free_cash_flow")/_xll.BDP(Inputs!$K$24,"BEST_NET_INCOME")} -> #VALUE! | M84: {=_xll.BDP(Inputs!$K$25,"cf_free_cash_flow")/_xll.BDP(Inputs!$K$25,"BEST_NET_INCOME")} -> #VALUE! | N84: {=_xll.BDP(Inputs!$Q$21,"cf_free_cash_flow")/_xll.BDP(Inputs!$Q$21,"BEST_NET_INCOME")} -> 2.3134814 | O84: {=_xll.BDP(Inputs!$Q$22,"cf_free_cash_flow")/_xll.BDP(Inputs!$Q$22,"BEST_NET_INCOME")} -> 3.0409129 | P84: {=_xll.BDP(Inputs!$Q$23,"cf_free_cash_flow")/_xll.BDP(Inputs!$Q$23,"BEST_NET_INCOME")} -> 1.4124723 | Q84: {=_xll.BDP(Inputs!$Q$24,"cf_free_cash_flow")/_xll.BDP(Inputs!$Q$24,"BEST_NET_INCOME")} -> 4.3610982 | R84: {=_xll.BDP(Inputs!$Q$25,"cf_free_cash_flow")/_xll.BDP(Inputs!$Q$25,"BEST_NET_INCOME")} -> 4.8360041
A86: x | B86: Per Share & Dilution | C86: CAL-MAINE FOODS | D86: =D81 -> VITAL FARMS INC | E86: =E81 -> POST HOLDINGS IN | F86: =F81 -> TYSON FOODS-A | G86: =G81 -> LAMB WESTON | H86: =H81 -> HORMEL FOODS CRP | I86: =I81 -> GENERAL MILLS IN | J86: =J81 -> CONAGRA BRANDS I | K86: =K81 -> PILGRIM'S PRIDE | ... R86: =R81 -> COLGATE-PALMOLIV
B88: Diluted share count YoY | C88: 0.0035304501 | D88: {=_xll.BDP(Inputs!$E$21,"PERIODIC_SHARE_DILUTION_FACTOR")-1} -> 0.0531502 | E88: {=_xll.BDP(Inputs!$E$22,"PERIODIC_SHARE_DILUTION_FACTOR")-1} -> 0.11686144 | F88: {=_xll.BDP(Inputs!$E$23,"PERIODIC_SHARE_DILUTION_FACTOR")-1} -> 0 | G88: {=_xll.BDP(Inputs!$E$24,"PERIODIC_SHARE_DILUTION_FACTOR")-1} -> 0.0035161744 | H88: {=_xll.BDP(Inputs!$E$25,"PERIODIC_SHARE_DILUTION_FACTOR")-1} -> 0.0012825448 | I88: {=_xll.BDP(Inputs!$K$21,"PERIODIC_SHARE_DILUTION_FACTOR")-1} -> 0.0054102795 | J88: {=_xll.BDP(Inputs!$K$22,"PERIODIC_SHARE_DILUTION_FACTOR")-1} -> 0.0029270332 | K88: {=_xll.BDP(Inputs!$K$23,"PERIODIC_SHARE_DILUTION_FACTOR")-1} -> 0.0033416594 | L88: {=_xll.BDP(Inputs!$K$24,"PERIODIC_SHARE_DILUTION_FACTOR")-1} -> 0.001155624 | M88: {=_xll.BDP(Inputs!$K$25,"PERIODIC_SHARE_DILUTION_FACTOR")-1} -> 0.005817219 | N88: {=_xll.BDP(Inputs!$Q$21,"PERIODIC_SHARE_DILUTION_FACTOR")-1} -> 0.0036416606 | O88: {=_xll.BDP(Inputs!$Q$22,"PERIODIC_SHARE_DILUTION_FACTOR")-1} -> 0.04438109 | P88: {=_xll.BDP(Inputs!$Q$23,"PERIODIC_SHARE_DILUTION_FACTOR")-1} -> 0.0025527965 | Q88: {=_xll.BDP(Inputs!$Q$24,"PERIODIC_SHARE_DILUTION_FACTOR")-1} -> 0.0041716329 | R88: {=_xll.BDP(Inputs!$Q$25,"PERIODIC_SHARE_DILUTION_FACTOR")-1} -> 0.0050054938
B89: SBC / revenue | C89: 0.001062206 | D89: {=_xll.BDP(Inputs!$E$21,"CF_STOCK_BASED_COMPENSATION")/_xll.BDP(Inputs!$E$21,"sales_rev_turn")} -> 0.016935315 | E89: {=_xll.BDP(Inputs!$E$22,"CF_STOCK_BASED_COMPENSATION")/_xll.BDP(Inputs!$E$22,"sales_rev_turn")} -> 0.010652934 | F89: {=_xll.BDP(Inputs!$E$23,"CF_STOCK_BASED_COMPENSATION")/_xll.BDP(Inputs!$E$23,"sales_rev_turn")} -> 0.0018946144 | G89: {=_xll.BDP(Inputs!$E$24,"CF_STOCK_BASED_COMPENSATION")/_xll.BDP(Inputs!$E$24,"sales_rev_turn")} -> 0.006122797 | H89: {=_xll.BDP(Inputs!$E$25,"CF_STOCK_BASED_COMPENSATION")/_xll.BDP(Inputs!$E$25,"sales_rev_turn")} -> 0.0019489469 | I89: {=_xll.BDP(Inputs!$K$21,"CF_STOCK_BASED_COMPENSATION")/_xll.BDP(Inputs!$K$21,"sales_rev_turn")} -> 0.0047057978 | J89: {=_xll.BDP(Inputs!$K$22,"CF_STOCK_BASED_COMPENSATION")/_xll.BDP(Inputs!$K$22,"sales_rev_turn")} -> 0.0035736429 | K89: {=_xll.BDP(Inputs!$K$23,"CF_STOCK_BASED_COMPENSATION")/_xll.BDP(Inputs!$K$23,"sales_rev_turn")} -> 0.00083190278 | L89: {=_xll.BDP(Inputs!$K$24,"CF_STOCK_BASED_COMPENSATION")/_xll.BDP(Inputs!$K$24,"sales_rev_turn")} -> 0.0012647187 | M89: {=_xll.BDP(Inputs!$K$25,"CF_STOCK_BASED_COMPENSATION")/_xll.BDP(Inputs!$K$25,"sales_rev_turn")} -> 0.0053323678 | N89: {=_xll.BDP(Inputs!$Q$21,"CF_STOCK_BASED_COMPENSATION")/_xll.BDP(Inputs!$Q$21,"sales_rev_turn")} -> 0.0039410369 | O89: {=_xll.BDP(Inputs!$Q$22,"CF_STOCK_BASED_COMPENSATION")/_xll.BDP(Inputs!$Q$22,"sales_rev_turn")} -> 0.0056475725 | P89: {=_xll.BDP(Inputs!$Q$23,"CF_STOCK_BASED_COMPENSATION")/_xll.BDP(Inputs!$Q$23,"sales_rev_turn")} -> 0.0060772189 | Q89: {=_xll.BDP(Inputs!$Q$24,"CF_STOCK_BASED_COMPENSATION")/_xll.BDP(Inputs!$Q$24,"sales_rev_turn")} -> 0.0065310599 | R89: {=_xll.BDP(Inputs!$Q$25,"CF_STOCK_BASED_COMPENSATION")/_xll.BDP(Inputs!$Q$25,"sales_rev_turn")} -> 0.0067160838
B90: SBC / CFO | C90: 0.0036963128 | D90: {=_xll.BDP(Inputs!$E$21,"CF_STOCK_BASED_COMPENSATION")/_xll.BDP(Inputs!$E$21,"cf_cash_from_oper")} -> 0.15839812 | E90: {=_xll.BDP(Inputs!$E$22,"CF_STOCK_BASED_COMPENSATION")/_xll.BDP(Inputs!$E$22,"cf_cash_from_oper")} -> 0.090587099 | F90: {=_xll.BDP(Inputs!$E$23,"CF_STOCK_BASED_COMPENSATION")/_xll.BDP(Inputs!$E$23,"cf_cash_from_oper")} -> 0.038996139 | G90: {=_xll.BDP(Inputs!$E$24,"CF_STOCK_BASED_COMPENSATION")/_xll.BDP(Inputs!$E$24,"cf_cash_from_oper")} -> 0.04549119 | H90: {=_xll.BDP(Inputs!$E$25,"CF_STOCK_BASED_COMPENSATION")/_xll.BDP(Inputs!$E$25,"cf_cash_from_oper")} -> 0.018340809 | I90: {=_xll.BDP(Inputs!$K$21,"CF_STOCK_BASED_COMPENSATION")/_xll.BDP(Inputs!$K$21,"cf_cash_from_oper")} -> 0.03142348 | J90: {=_xll.BDP(Inputs!$K$22,"CF_STOCK_BASED_COMPENSATION")/_xll.BDP(Inputs!$K$22,"cf_cash_from_oper")} -> 0.024528636 | K90: {=_xll.BDP(Inputs!$K$23,"CF_STOCK_BASED_COMPENSATION")/_xll.BDP(Inputs!$K$23,"cf_cash_from_oper")} -> 0.0074733924 | L90: {=_xll.BDP(Inputs!$K$24,"CF_STOCK_BASED_COMPENSATION")/_xll.BDP(Inputs!$K$24,"cf_cash_from_oper")} -> 0.0069565217 | M90: {=_xll.BDP(Inputs!$K$25,"CF_STOCK_BASED_COMPENSATION")/_xll.BDP(Inputs!$K$25,"cf_cash_from_oper")} -> 0.035499069 | N90: {=_xll.BDP(Inputs!$Q$21,"CF_STOCK_BASED_COMPENSATION")/_xll.BDP(Inputs!$Q$21,"cf_cash_from_oper")} -> 0.028943791 | O90: {=_xll.BDP(Inputs!$Q$22,"CF_STOCK_BASED_COMPENSATION")/_xll.BDP(Inputs!$Q$22,"cf_cash_from_oper")} -> 0.026716058 | P90: {=_xll.BDP(Inputs!$Q$23,"CF_STOCK_BASED_COMPENSATION")/_xll.BDP(Inputs!$Q$23,"cf_cash_from_oper")} -> 0.042027921 | Q90: {=_xll.BDP(Inputs!$Q$24,"CF_STOCK_BASED_COMPENSATION")/_xll.BDP(Inputs!$Q$24,"cf_cash_from_oper")} -> 0.040507112 | R90: {=_xll.BDP(Inputs!$Q$25,"CF_STOCK_BASED_COMPENSATION")/_xll.BDP(Inputs!$Q$25,"cf_cash_from_oper")} -> 0.032870709
B91: EPS in USD | C91: 25.04088 | D91: =_xll.BQL( Inputs!$E$21, "is_eps(fpt=ltm,fa_adjusted=y,fs=mr)", "currency=USD" ) -> 1.172692 | E91: =_xll.BQL( Inputs!$E$22, "is_eps(fpt=ltm,fa_adjusted=y,fs=mr)", "currency=USD" ) -> 7.447295 | F91: =_xll.BQL( Inputs!$E$23, "is_eps(fpt=ltm,fa_adjusted=y,fs=mr)", "currency=USD" ) -> 3.932315 | G91: =_xll.BQL( Inputs!$E$24, "is_eps(fpt=ltm,fa_adjusted=y,fs=mr)", "currency=USD" ) -> 2.775662 | H91: =_xll.BQL( Inputs!$E$25, "is_eps(fpt=ltm,fa_adjusted=y,fs=mr)", "currency=USD" ) -> 1.472268 | I91: =_xll.BQL( Inputs!$K$21, "is_eps(fpt=ltm,fa_adjusted=y,fs=mr)", "currency=USD" ) -> 4.008983 | J91: =_xll.BQL( Inputs!$K$22, "is_eps(fpt=ltm,fa_adjusted=y,fs=mr)", "currency=USD" ) -> 2.338119 | K91: =_xll.BQL( Inputs!$K$23, "is_eps(fpt=ltm,fa_adjusted=y,fs=mr)", "currency=USD" ) -> 6.041685 | L91: =_xll.BQL( Inputs!$K$24, "is_eps(fpt=ltm,fa_adjusted=y,fs=mr)", "currency=USD" ) -> 5.0136866 | M91: =_xll.BQL( Inputs!$K$25, "is_eps(fpt=ltm,fa_adjusted=y,fs=mr)", "currency=USD" ) -> 3.2320775 | N91: =_xll.BQL( Inputs!$Q$21, "is_eps(fpt=ltm,fa_adjusted=y,fs=mr)", "currency=USD" ) -> 7.899147 | O91: =_xll.BQL( Inputs!$Q$22, "is_eps(fpt=ltm,fa_adjusted=y,fs=mr)", "currency=USD" ) -> 7.267967 | P91: =_xll.BQL( Inputs!$Q$23, "is_eps(fpt=ltm,fa_adjusted=y,fs=mr)", "currency=USD" ) -> 2.921453 | Q91: =_xll.BQL( Inputs!$Q$24, "is_eps(fpt=ltm,fa_adjusted=y,fs=mr)", "currency=USD" ) -> 10.627931 | R91: =_xll.BQL( Inputs!$Q$25, "is_eps(fpt=ltm,fa_adjusted=y,fs=mr)", "currency=USD" ) -> 3.663596

Sheet Trading Comps
B7: ="in "&IF(Inputs!$R$18="k","thousands",IF(Inputs!$R$18="MLN","millions","billions")&" of "&Inputs!$R$17) -> in thousands | D7: Current | E7: % of | I7: Enterprise Value / | S7: LTM | T7: Net | V7: Price / | Z7: LT
D8: Share | E8: 52-week | F8: Equity | G8: Enterprise | I8: LTM | J8: 2025 | K8: 2026 | L8: LTM | M8: 2025E | N8: 2026E | O8: LTM | P8: 2025E | Q8: 2026E | S8: EBITDA | T8: Debt / | V8: LTM | W8: 2025E | X8: 2026E | Z8: EPS
B9: Company | C9: Ticker | D9: Price | E9: High | F9: Value | G9: Value | I9: Sales | J9: Sales | K9: Sales | L9: EBITDA | M9: EBITDA | N9: EBITDA | O9: EBIT | P9: EBIT | Q9: EBIT | S9: Margin | T9: EBITDA | V9: EPS | W9: EPS | X9: EPS | Z9: Growth
B12: Tier I: DRAM and NAND
B15: =+Inputs!B21 -> VITAL FARMS INC | C15: =+_xll.BDP(Inputs!E21,"TICKER_AND_EXCH_CODE") -> VITL US | D15: =CONCATENATE(_xll.BDP(Inputs!E21,"CRNCY")," ",_xll.BDP(Inputs!E21,"PX_YEST_CLOSE")) -> USD 40,66 | E15: =_xll.BDP(Inputs!E21,"PX_YEST_CLOSE")/_xll.BDP(Inputs!E21,"HIGH_52WEEK") -> 0.76536471 | F15: =_xll.BDP(Inputs!$E21, "CUR_MKT_CAP", "SCALING_FORMAT=" & Inputs!$R$18) -> 1839051.5 | G15: =_xll.BDP(Inputs!$E21, "ENTERPRISE_VALUE", "SCALING_FORMAT=" & Inputs!$R$18) -> 1596801.2 | I15: =G15/_xll.BQL(Inputs!$E21, "sales_rev_turn(fpt = ltm, fa_adjusted = y, fs = mr)/1"&IF(Inputs!$R$18="BLN","b",IF(Inputs!$R$18="MLN","m","k"))) -> 2.4269451 | J15: =G15/_xll.BQL(Inputs!$E21, "sales_rev_turn(fpr = 2025, fpt = a, ae = e, fa_adjusted = y, fs = mr)/1"&IF(Inputs!$R$18="BLN","b",IF(Inputs!$R$18="MLN","m","k"))) -> 2.0666918 | K15: =G15/_xll.BQL(Inputs!$E21, "sales_rev_turn(fpr = 2026, fpt = a, ae = e, fa_adjusted = y, fs = mr)/1"&IF(Inputs!$R$18="BLN","b",IF(Inputs!$R$18="MLN","m","k"))) -> 1.7220406 | L15: =G15/_xll.BQL(Inputs!$E21, "ebitda(fpt = ltm, fa_adjusted = y, fs = mr)/1"&IF(Inputs!$R$18="BLN","b",IF(Inputs!$R$18="MLN","m","k"))) -> 18.01791 | M15: =G15/_xll.BQL(Inputs!$E21, "ebitda(fpr = 2025, fpt = a, ae = e, fa_adjusted = y, fs = mr)/1"&IF(Inputs!$R$18="BLN","b",IF(Inputs!$R$18="MLN","m","k"))) -> 14.397388 | N15: =G15/_xll.BQL(Inputs!$E21, "ebitda(fpr = 2026, fpt = a, ae = e, fa_adjusted = y, fs = mr)/1"&IF(Inputs!$R$18="BLN","b",IF(Inputs!$R$18="MLN","m","k"))) -> 12.257372 | O15: =G15/_xll.BQL(Inputs!$E21, "is_oper_inc(fpt = ltm, fa_adjusted = y, fs = mr)/1"&IF(Inputs!$R$18="BLN","b",IF(Inputs!$R$18="MLN","m","k"))) -> 23.382993 | P15: =G15/_xll.BQL(Inputs!$E21, "is_oper_inc(fpr = 2025, fpt = a, ae = e, fa_adjusted = y, fs = mr)/1"&IF(Inputs!$R$18="BLN","b",IF(Inputs!$R$18="MLN","m","k"))) -> 18.850412 | Q15: =G15/_xll.BQL(Inputs!$E21, "is_oper_inc(fpr = 2026, fpt = a, ae = e, fa_adjusted = y, fs = mr)/1"&IF(Inputs!$R$18="BLN","b",IF(Inputs!$R$18="MLN","m","k"))) -> 16.43107 | S15: =_xll.BQL(Inputs!$E21, "ebitda(fpt = ltm, fa_adjusted = y, fs = mr)/1"&IF(Inputs!$R$18="BLN","b",IF(Inputs!$R$18="MLN","m","k")))/_xll.BQL(Inputs!$E21, "sales_rev_turn(fpt = ltm, fa_adjusted = y, fs = mr)/1"&IF(Inputs!$R$18="BLN","b",IF(Inputs!$R$18="MLN","m","k"))) -> 0.13469626 | T15: =_xll.BDP(Inputs!$E21,"TOT_DEBT_TO_EBITDA") -> 0.19953938 | V15: =F15/_xll.BQL(Inputs!$E21, "earn_for_common(fpt = ltm, fa_adjusted = y, fs = mr)/1"&IF(Inputs!$R$18="BLN","b",IF(Inputs!$R$18="MLN","m","k"))) -> 35.403004 | W15: =F15/_xll.BQL(Inputs!$E21, "EARN_FOR_COMMON(fpr = 2025, fpt = a, ae = e, fa_adjusted = y, fs = mr)/1"&IF(Inputs!$R$18="BLN","b",IF(Inputs!$R$18="MLN","m","k"))) -> 28.721716 | X15: =F15/_xll.BQL(Inputs!$E21, "EARN_FOR_COMMON(fpr = 2026, fpt = a, ae = e, fa_adjusted = y, fs = mr)/1"&IF(Inputs!$R$18="BLN","b",IF(Inputs!$R$18="MLN","m","k"))) -> 24.538533 | Z15: =(_xll.BQL(Inputs!$E21, "EARN_FOR_COMMON(fpr = 2028, fpt = a, ae = e, fa_adjusted = y, fs = mr)")/_xll.BQL(Inputs!$E21, "EARN_FOR_COMMON(fpr = 2025, fpt = a, ae = e, fa_adjusted = y, fs = mr)"))^(1/3)-1 -> 0.19402751
B16: =+Inputs!B22 -> POST HOLDINGS IN | C16: =+_xll.BDP(Inputs!E22,"TICKER_AND_EXCH_CODE") -> POST US | D16: =CONCATENATE(_xll.BDP(Inputs!E22,"CRNCY")," ",_xll.BDP(Inputs!E22,"PX_YEST_CLOSE")) -> USD 108,06 | E16: =_xll.BDP(Inputs!E22,"PX_YEST_CLOSE")/_xll.BDP(Inputs!E22,"HIGH_52WEEK") -> 0.85870947 | F16: =_xll.BDP(Inputs!$E22, "CUR_MKT_CAP", "SCALING_FORMAT=" & Inputs!$R$18) -> 5808255.3 | G16: =_xll.BDP(Inputs!$E22, "ENTERPRISE_VALUE", "SCALING_FORMAT=" & Inputs!$R$18) -> 12224123 | I16: {=G16/_xll.BQL(Inputs!$E22, "sales_rev_turn(fpt = ltm, fa_adjusted = y, fs = mr)/1"&IF(Inputs!$R$18="BLN","b",IF(Inputs!$R$18="MLN","m","k")))} -> 1.5432161 | J16: =G16/_xll.BQL(Inputs!$E22, "sales_rev_turn(fpr = 2025, fpt = a, ae = e, fa_adjusted = y, fs = mr)/1"&IF(Inputs!$R$18="BLN","b",IF(Inputs!$R$18="MLN","m","k"))) -> 1.4970147 | K16: =G16/_xll.BQL(Inputs!$E22, "sales_rev_turn(fpr = 2026, fpt = a, ae = e, fa_adjusted = y, fs = mr)/1"&IF(Inputs!$R$18="BLN","b",IF(Inputs!$R$18="MLN","m","k"))) -> 1.4017775 | L16: =G16/_xll.BQL(Inputs!$E22, "ebitda(fpt = ltm, fa_adjusted = y, fs = mr)/1"&IF(Inputs!$R$18="BLN","b",IF(Inputs!$R$18="MLN","m","k"))) -> 8.9012766 | M16: =G16/_xll.BQL(Inputs!$E22, "ebitda(fpr = 2025, fpt = a, ae = e, fa_adjusted = y, fs = mr)/1"&IF(Inputs!$R$18="BLN","b",IF(Inputs!$R$18="MLN","m","k"))) -> 8.0620763 | N16: =G16/_xll.BQL(Inputs!$E22, "ebitda(fpr = 2026, fpt = a, ae = e, fa_adjusted = y, fs = mr)/1"&IF(Inputs!$R$18="BLN","b",IF(Inputs!$R$18="MLN","m","k"))) -> 7.7755415 | O16: =G16/_xll.BQL(Inputs!$E22, "is_oper_inc(fpt = ltm, fa_adjusted = y, fs = mr)/1"&IF(Inputs!$R$18="BLN","b",IF(Inputs!$R$18="MLN","m","k"))) -> 14.034585 | P16: =G16/_xll.BQL(Inputs!$E22, "is_oper_inc(fpr = 2025, fpt = a, ae = e, fa_adjusted = y, fs = mr)/1"&IF(Inputs!$R$18="BLN","b",IF(Inputs!$R$18="MLN","m","k"))) -> 13.362131 | Q16: =G16/_xll.BQL(Inputs!$E22, "is_oper_inc(fpr = 2026, fpt = a, ae = e, fa_adjusted = y, fs = mr)/1"&IF(Inputs!$R$18="BLN","b",IF(Inputs!$R$18="MLN","m","k"))) -> 12.776716 | S16: =_xll.BQL(Inputs!$E22, "ebitda(fpt = ltm, fa_adjusted = y, fs = mr)/1"&IF(Inputs!$R$18="BLN","b",IF(Inputs!$R$18="MLN","m","k")))/_xll.BQL(Inputs!$E22, "sales_rev_turn(fpt = ltm, fa_adjusted = y, fs = mr)/1"&IF(Inputs!$R$18="BLN","b",IF(Inputs!$R$18="MLN","m","k"))) -> 0.1733702 | T16: =_xll.BDP(Inputs!$E22,"TOT_DEBT_TO_EBITDA") -> 5.5488256 | V16: =F16/_xll.BQL(Inputs!$E22, "earn_for_common(fpt = ltm, fa_adjusted = y, fs = mr)/1"&IF(Inputs!$R$18="BLN","b",IF(Inputs!$R$18="MLN","m","k"))) -> 13.643958 | W16: =F16/_xll.BQL(Inputs!$E22, "EARN_FOR_COMMON(fpr = 2025, fpt = a, ae = e, fa_adjusted = y, fs = mr)/1"&IF(Inputs!$R$18="BLN","b",IF(Inputs!$R$18="MLN","m","k"))) -> 13.170647 | X16: =F16/_xll.BQL(Inputs!$E22, "EARN_FOR_COMMON(fpr = 2026, fpt = a, ae = e, fa_adjusted = y, fs = mr)/1"&IF(Inputs!$R$18="BLN","b",IF(Inputs!$R$18="MLN","m","k"))) -> 12.843019 | Z16: =(_xll.BQL(Inputs!$E22, "EARN_FOR_COMMON(fpr = 2028, fpt = a, ae = e, fa_adjusted = y, fs = mr)")/_xll.BQL(Inputs!$E22, "EARN_FOR_COMMON(fpr = 2025, fpt = a, ae = e, fa_adjusted = y, fs = mr)"))^(1/3)-1 -> 0.035509253
B17: =+Inputs!B23 -> TYSON FOODS-A | C17: =+_xll.BDP(Inputs!E23,"TICKER_AND_EXCH_CODE") -> TSN US | D17: =CONCATENATE(_xll.BDP(Inputs!E23,"CRNCY")," ",_xll.BDP(Inputs!E23,"PX_YEST_CLOSE")) -> USD 54,47 | E17: =_xll.BDP(Inputs!E23,"PX_YEST_CLOSE")/_xll.BDP(Inputs!E23,"HIGH_52WEEK") -> 0.82592873 | F17: =_xll.BDP(Inputs!$E23, "CUR_MKT_CAP", "SCALING_FORMAT=" & Inputs!$R$18) -> 19435682 | G17: =_xll.BDP(Inputs!$E23, "ENTERPRISE_VALUE", "SCALING_FORMAT=" & Inputs!$R$18) -> 28245440 | I17: =G17/_xll.BQL(Inputs!$E23, "sales_rev_turn(fpt = ltm, fa_adjusted = y, fs = mr)/1"&IF(Inputs!$R$18="BLN","b",IF(Inputs!$R$18="MLN","m","k"))) -> 0.52165331 | J17: =G17/_xll.BQL(Inputs!$E23, "sales_rev_turn(fpr = 2025, fpt = a, ae = e, fa_adjusted = y, fs = mr)/1"&IF(Inputs!$R$18="BLN","b",IF(Inputs!$R$18="MLN","m","k"))) -> 0.51578395 | K17: =G17/_xll.BQL(Inputs!$E23, "sales_rev_turn(fpr = 2026, fpt = a, ae = e, fa_adjusted = y, fs = mr)/1"&IF(Inputs!$R$18="BLN","b",IF(Inputs!$R$18="MLN","m","k"))) -> 0.50695244 | L17: =G17/_xll.BQL(Inputs!$E23, "ebitda(fpt = ltm, fa_adjusted = y, fs = mr)/1"&IF(Inputs!$R$18="BLN","b",IF(Inputs!$R$18="MLN","m","k"))) -> 8.0701257 | M17: =G17/_xll.BQL(Inputs!$E23, "ebitda(fpr = 2025, fpt = a, ae = e, fa_adjusted = y, fs = mr)/1"&IF(Inputs!$R$18="BLN","b",IF(Inputs!$R$18="MLN","m","k"))) -> 7.8695642 | N17: =G17/_xll.BQL(Inputs!$E23, "ebitda(fpr = 2026, fpt = a, ae = e, fa_adjusted = y, fs = mr)/1"&IF(Inputs!$R$18="BLN","b",IF(Inputs!$R$18="MLN","m","k"))) -> 7.9205777 | O17: =G17/_xll.BQL(Inputs!$E23, "is_oper_inc(fpt = ltm, fa_adjusted = y, fs = mr)/1"&IF(Inputs!$R$18="BLN","b",IF(Inputs!$R$18="MLN","m","k"))) -> 13.119108 | P17: =G17/_xll.BQL(Inputs!$E23, "is_oper_inc(fpr = 2025, fpt = a, ae = e, fa_adjusted = y, fs = mr)/1"&IF(Inputs!$R$18="BLN","b",IF(Inputs!$R$18="MLN","m","k"))) -> 12.862222 | Q17: =G17/_xll.BQL(Inputs!$E23, "is_oper_inc(fpr = 2026, fpt = a, ae = e, fa_adjusted = y, fs = mr)/1"&IF(Inputs!$R$18="BLN","b",IF(Inputs!$R$18="MLN","m","k"))) -> 12.679675 | S17: =_xll.BQL(Inputs!$E23, "ebitda(fpt = ltm, fa_adjusted = y, fs = mr)/1"&IF(Inputs!$R$18="BLN","b",IF(Inputs!$R$18="MLN","m","k")))/_xll.BQL(Inputs!$E23, "sales_rev_turn(fpt = ltm, fa_adjusted = y, fs = mr)/1"&IF(Inputs!$R$18="BLN","b",IF(Inputs!$R$18="MLN","m","k"))) -> 0.064640047 | T17: =_xll.BDP(Inputs!$E23,"TOT_DEBT_TO_EBITDA") -> 3.5551209 | V17: =F17/_xll.BQL(Inputs!$E23, "earn_for_common(fpt = ltm, fa_adjusted = y, fs = mr)/1"&IF(Inputs!$R$18="BLN","b",IF(Inputs!$R$18="MLN","m","k"))) -> 14.002652 | W17: =F17/_xll.BQL(Inputs!$E23, "EARN_FOR_COMMON(fpr = 2025, fpt = a, ae = e, fa_adjusted = y, fs = mr)/1"&IF(Inputs!$R$18="BLN","b",IF(Inputs!$R$18="MLN","m","k"))) -> 14.239754 | X17: =F17/_xll.BQL(Inputs!$E23, "EARN_FOR_COMMON(fpr = 2026, fpt = a, ae = e, fa_adjusted = y, fs = mr)/1"&IF(Inputs!$R$18="BLN","b",IF(Inputs!$R$18="MLN","m","k"))) -> 13.643064 | Z17: =(_xll.BQL(Inputs!$E23, "EARN_FOR_COMMON(fpr = 2028, fpt = a, ae = e, fa_adjusted = y, fs = mr)")/_xll.BQL(Inputs!$E23, "EARN_FOR_COMMON(fpr = 2025, fpt = a, ae = e, fa_adjusted = y, fs = mr)"))^(1/3)-1 -> 0.19595369
B18: =+Inputs!B24 -> LAMB WESTON | C18: =+_xll.BDP(Inputs!E24,"TICKER_AND_EXCH_CODE") -> LW US | D18: =CONCATENATE(_xll.BDP(Inputs!E24,"CRNCY")," ",_xll.BDP(Inputs!E24,"PX_YEST_CLOSE")) -> USD 62,01 | E18: =_xll.BDP(Inputs!E24,"PX_YEST_CLOSE")/_xll.BDP(Inputs!E24,"HIGH_52WEEK") -> 0.73837778 | F18: =_xll.BDP(Inputs!$E24, "CUR_MKT_CAP", "SCALING_FORMAT=" & Inputs!$R$18) -> 8680266 | G18: =_xll.BDP(Inputs!$E24, "ENTERPRISE_VALUE", "SCALING_FORMAT=" & Inputs!$R$18) -> 11833725 | I18: =G18/_xll.BQL(Inputs!$E24, "sales_rev_turn(fpt = ltm, fa_adjusted = y, fs = mr)/1"&IF(Inputs!$R$18="BLN","b",IF(Inputs!$R$18="MLN","m","k"))) -> 1.832839 | J18: =G18/_xll.BQL(Inputs!$E24, "sales_rev_turn(fpr = 2025, fpt = a, ae = e, fa_adjusted = y, fs = mr)/1"&IF(Inputs!$R$18="BLN","b",IF(Inputs!$R$18="MLN","m","k"))) -> 1.8596739 | K18: =G18/_xll.BQL(Inputs!$E24, "sales_rev_turn(fpr = 2026, fpt = a, ae = e, fa_adjusted = y, fs = mr)/1"&IF(Inputs!$R$18="BLN","b",IF(Inputs!$R$18="MLN","m","k"))) -> 1.8159401 | L18: =G18/_xll.BQL(Inputs!$E24, "ebitda(fpt = ltm, fa_adjusted = y, fs = mr)/1"&IF(Inputs!$R$18="BLN","b",IF(Inputs!$R$18="MLN","m","k"))) -> 10.304532 | M18: =G18/_xll.BQL(Inputs!$E24, "ebitda(fpr = 2025, fpt = a, ae = e, fa_adjusted = y, fs = mr)/1"&IF(Inputs!$R$18="BLN","b",IF(Inputs!$R$18="MLN","m","k"))) -> 10.009657 | N18: =G18/_xll.BQL(Inputs!$E24, "ebitda(fpr = 2026, fpt = a, ae = e, fa_adjusted = y, fs = mr)/1"&IF(Inputs!$R$18="BLN","b",IF(Inputs!$R$18="MLN","m","k"))) -> 10.180278 | O18: =G18/_xll.BQL(Inputs!$E24, "is_oper_inc(fpt = ltm, fa_adjusted = y, fs = mr)/1"&IF(Inputs!$R$18="BLN","b",IF(Inputs!$R$18="MLN","m","k"))) -> 16.076247 | P18: =G18/_xll.BQL(Inputs!$E24, "is_oper_inc(fpr = 2025, fpt = a, ae = e, fa_adjusted = y, fs = mr)/1"&IF(Inputs!$R$18="BLN","b",IF(Inputs!$R$18="MLN","m","k"))) -> 15.169674 | Q18: =G18/_xll.BQL(Inputs!$E24, "is_oper_inc(fpr = 2026, fpt = a, ae = e, fa_adjusted = y, fs = mr)/1"&IF(Inputs!$R$18="BLN","b",IF(Inputs!$R$18="MLN","m","k"))) -> 15.567277 | S18: =_xll.BQL(Inputs!$E24, "ebitda(fpt = ltm, fa_adjusted = y, fs = mr)/1"&IF(Inputs!$R$18="BLN","b",IF(Inputs!$R$18="MLN","m","k")))/_xll.BQL(Inputs!$E24, "sales_rev_turn(fpt = ltm, fa_adjusted = y, fs = mr)/1"&IF(Inputs!$R$18="BLN","b",IF(Inputs!$R$18="MLN","m","k"))) -> 0.17786727 | T18: =_xll.BDP(Inputs!$E24,"TOT_DEBT_TO_EBITDA") -> 3.9064396 | V18: =F18/_xll.BQL(Inputs!$E24, "earn_for_common(fpt = ltm, fa_adjusted = y, fs = mr)/1"&IF(Inputs!$R$18="BLN","b",IF(Inputs!$R$18="MLN","m","k"))) -> 22.10778 | W18: =F18/_xll.BQL(Inputs!$E24, "EARN_FOR_COMMON(fpr = 2025, fpt = a, ae = e, fa_adjusted = y, fs = mr)/1"&IF(Inputs!$R$18="BLN","b",IF(Inputs!$R$18="MLN","m","k"))) -> 19.47558 | X18: =F18/_xll.BQL(Inputs!$E24, "EARN_FOR_COMMON(fpr = 2026, fpt = a, ae = e, fa_adjusted = y, fs = mr)/1"&IF(Inputs!$R$18="BLN","b",IF(Inputs!$R$18="MLN","m","k"))) -> 22.157667 | Z18: =(_xll.BQL(Inputs!$E24, "EARN_FOR_COMMON(fpr = 2028, fpt = a, ae = e, fa_adjusted = y, fs = mr)")/_xll.BQL(Inputs!$E24, "EARN_FOR_COMMON(fpr = 2025, fpt = a, ae = e, fa_adjusted = y, fs = mr)"))^(1/3)-1 -> 0.070869184
B19: =+Inputs!B25 -> HORMEL FOODS CRP | C19: =+_xll.BDP(Inputs!E25,"TICKER_AND_EXCH_CODE") -> HRL US | D19: =CONCATENATE(_xll.BDP(Inputs!E25,"CRNCY")," ",_xll.BDP(Inputs!E25,"PX_YEST_CLOSE")) -> USD 24,8 | E19: =_xll.BDP(Inputs!E25,"PX_YEST_CLOSE")/_xll.BDP(Inputs!E25,"HIGH_52WEEK") -> 0.73372781 | F19: =_xll.BDP(Inputs!$E25, "CUR_MKT_CAP", "SCALING_FORMAT=" & Inputs!$R$18) -> 13653711 | G19: =_xll.BDP(Inputs!$E25, "ENTERPRISE_VALUE", "SCALING_FORMAT=" & Inputs!$R$18) -> 18318013 | I19: =G19/_xll.BQL(Inputs!$E25, "sales_rev_turn(fpt = ltm, fa_adjusted = y, fs = mr)/1"&IF(Inputs!$R$18="BLN","b",IF(Inputs!$R$18="MLN","m","k"))) -> 1.5190842 | J19: =G19/_xll.BQL(Inputs!$E25, "sales_rev_turn(fpr = 2025, fpt = a, ae = e, fa_adjusted = y, fs = mr)/1"&IF(Inputs!$R$18="BLN","b",IF(Inputs!$R$18="MLN","m","k"))) -> 1.5080553 | K19: =G19/_xll.BQL(Inputs!$E25, "sales_rev_turn(fpr = 2026, fpt = a, ae = e, fa_adjusted = y, fs = mr)/1"&IF(Inputs!$R$18="BLN","b",IF(Inputs!$R$18="MLN","m","k"))) -> 1.4683647 | L19: =G19/_xll.BQL(Inputs!$E25, "ebitda(fpt = ltm, fa_adjusted = y, fs = mr)/1"&IF(Inputs!$R$18="BLN","b",IF(Inputs!$R$18="MLN","m","k"))) -> 13.64943 | M19: =G19/_xll.BQL(Inputs!$E25, "ebitda(fpr = 2025, fpt = a, ae = e, fa_adjusted = y, fs = mr)/1"&IF(Inputs!$R$18="BLN","b",IF(Inputs!$R$18="MLN","m","k"))) -> 13.893656 | N19: =G19/_xll.BQL(Inputs!$E25, "ebitda(fpr = 2026, fpt = a, ae = e, fa_adjusted = y, fs = mr)/1"&IF(Inputs!$R$18="BLN","b",IF(Inputs!$R$18="MLN","m","k"))) -> 13.032579 | O19: =G19/_xll.BQL(Inputs!$E25, "is_oper_inc(fpt = ltm, fa_adjusted = y, fs = mr)/1"&IF(Inputs!$R$18="BLN","b",IF(Inputs!$R$18="MLN","m","k"))) -> 16.943772 | P19: =G19/_xll.BQL(Inputs!$E25, "is_oper_inc(fpr = 2025, fpt = a, ae = e, fa_adjusted = y, fs = mr)/1"&IF(Inputs!$R$18="BLN","b",IF(Inputs!$R$18="MLN","m","k"))) -> 17.255563 | Q19: =G19/_xll.BQL(Inputs!$E25, "is_oper_inc(fpr = 2026, fpt = a, ae = e, fa_adjusted = y, fs = mr)/1"&IF(Inputs!$R$18="BLN","b",IF(Inputs!$R$18="MLN","m","k"))) -> 16.293541 | S19: =_xll.BQL(Inputs!$E25, "ebitda(fpt = ltm, fa_adjusted = y, fs = mr)/1"&IF(Inputs!$R$18="BLN","b",IF(Inputs!$R$18="MLN","m","k")))/_xll.BQL(Inputs!$E25, "sales_rev_turn(fpt = ltm, fa_adjusted = y, fs = mr)/1"&IF(Inputs!$R$18="BLN","b",IF(Inputs!$R$18="MLN","m","k"))) -> 0.11129286 | T19: =_xll.BDP(Inputs!$E25,"TOT_DEBT_TO_EBITDA") -> 2.246277 | V19: =F19/_xll.BQL(Inputs!$E25, "earn_for_common(fpt = ltm, fa_adjusted = y, fs = mr)/1"&IF(Inputs!$R$18="BLN","b",IF(Inputs!$R$18="MLN","m","k"))) -> 16.869825 | W19: =F19/_xll.BQL(Inputs!$E25, "EARN_FOR_COMMON(fpr = 2025, fpt = a, ae = e, fa_adjusted = y, fs = mr)/1"&IF(Inputs!$R$18="BLN","b",IF(Inputs!$R$18="MLN","m","k"))) -> 17.227105 | X19: =F19/_xll.BQL(Inputs!$E25, "EARN_FOR_COMMON(fpr = 2026, fpt = a, ae = e, fa_adjusted = y, fs = mr)/1"&IF(Inputs!$R$18="BLN","b",IF(Inputs!$R$18="MLN","m","k"))) -> 16.183775 | Z19: =(_xll.BQL(Inputs!$E25, "EARN_FOR_COMMON(fpr = 2028, fpt = a, ae = e, fa_adjusted = y, fs = mr)")/_xll.BQL(Inputs!$E25, "EARN_FOR_COMMON(fpr = 2025, fpt = a, ae = e, fa_adjusted = y, fs = mr)"))^(1/3)-1 -> 0.086186154
B21: Mean | I21: =AVERAGE(I15:I19) -> 1.5687475 | J21: =AVERAGE(J15:J19) -> 1.4894439 | K21: =AVERAGE(K15:K19) -> 1.3830151 | L21: =AVERAGE(L15:L19) -> 11.788655 | M21: =AVERAGE(M15:M19) -> 10.846468 | N21: =AVERAGE(N15:N19) -> 10.23327 | O21: =AVERAGE(O15:O19) -> 16.711341 | P21: =AVERAGE(P15:P19) -> 15.500001 | Q21: =AVERAGE(Q15:Q19) -> 14.749656 | S21: =AVERAGE(S15:S19) -> 0.13237333 | T21: =AVERAGE(T15:T19) -> 3.0912405 | V21: =AVERAGE(V15:V19) -> 20.405444 | W21: =AVERAGE(W15:W19) -> 18.56696 | X21: =AVERAGE(X15:X19) -> 17.873211 | Z21: =AVERAGE(Z15:Z19) -> 0.11650916
B22: Median | I22: =MEDIAN(I15:I19) -> 1.5432161 | J22: =MEDIAN(J15:J19) -> 1.5080553 | K22: =MEDIAN(K15:K19) -> 1.4683647 | L22: =MEDIAN(L15:L19) -> 10.304532 | M22: =MEDIAN(M15:M19) -> 10.009657 | N22: =MEDIAN(N15:N19) -> 10.180278 | O22: =MEDIAN(O15:O19) -> 16.076247 | P22: =MEDIAN(P15:P19) -> 15.169674 | Q22: =MEDIAN(Q15:Q19) -> 15.567277 | S22: =MEDIAN(S15:S19) -> 0.13469626 | T22: =MEDIAN(T15:T19) -> 3.5551209 | V22: =MEDIAN(V15:V19) -> 16.869825 | W22: =MEDIAN(W15:W19) -> 17.227105 | X22: =MEDIAN(X15:X19) -> 16.183775 | Z22: =MEDIAN(Z15:Z19) -> 0.086186154
B24: Tier II: Chips
B27: =+Inputs!H21 -> GENERAL MILLS IN | C27: =+_xll.BDP(Inputs!K21,"TICKER_AND_EXCH_CODE") -> GIS US | D27: =CONCATENATE(_xll.BDP(Inputs!K21,"CRNCY")," ",_xll.BDP(Inputs!K21,"PX_YEST_CLOSE")) -> USD 50,7 | E27: =_xll.BDP(Inputs!K21,"PX_YEST_CLOSE")/_xll.BDP(Inputs!K21,"HIGH_52WEEK") -> 0.68117694 | F27: =_xll.BDP(Inputs!$K21, "CUR_MKT_CAP", "SCALING_FORMAT=" & Inputs!$R$18) -> 26854850 | G27: =_xll.BDP(Inputs!$K21, "ENTERPRISE_VALUE", "SCALING_FORMAT=" & Inputs!$R$18) -> 40297646 | I27: =G27/_xll.BQL(Inputs!$K21, "sales_rev_turn(fpt = ltm, fa_adjusted = y, fs = mr)/1"&IF(Inputs!$R$18="BLN","b",IF(Inputs!$R$18="MLN","m","k"))) -> 2.1036566 | J27: =G27/_xll.BQL(Inputs!$K21, "sales_rev_turn(fpr = 2025, fpt = a, ae = e, fa_adjusted = y, fs = mr)/1"&IF(Inputs!$R$18="BLN","b",IF(Inputs!$R$18="MLN","m","k"))) -> 2.0657461 | K27: =G27/_xll.BQL(Inputs!$K21, "sales_rev_turn(fpr = 2026, fpt = a, ae = e, fa_adjusted = y, fs = mr)/1"&IF(Inputs!$R$18="BLN","b",IF(Inputs!$R$18="MLN","m","k"))) -> 2.1677389 | L27: =G27/_xll.BQL(Inputs!$K21, "ebitda(fpt = ltm, fa_adjusted = y, fs = mr)/1"&IF(Inputs!$R$18="BLN","b",IF(Inputs!$R$18="MLN","m","k"))) -> 10.658843 | M27: =G27/_xll.BQL(Inputs!$K21, "ebitda(fpr = 2025, fpt = a, ae = e, fa_adjusted = y, fs = mr)/1"&IF(Inputs!$R$18="BLN","b",IF(Inputs!$R$18="MLN","m","k"))) -> 10.362583 | N27: =G27/_xll.BQL(Inputs!$K21, "ebitda(fpr = 2026, fpt = a, ae = e, fa_adjusted = y, fs = mr)/1"&IF(Inputs!$R$18="BLN","b",IF(Inputs!$R$18="MLN","m","k"))) -> 11.603958 | O27: =G27/_xll.BQL(Inputs!$K21, "is_oper_inc(fpt = ltm, fa_adjusted = y, fs = mr)/1"&IF(Inputs!$R$18="BLN","b",IF(Inputs!$R$18="MLN","m","k"))) -> 12.42766 | P27: =G27/_xll.BQL(Inputs!$K21, "is_oper_inc(fpr = 2025, fpt = a, ae = e, fa_adjusted = y, fs = mr)/1"&IF(Inputs!$R$18="BLN","b",IF(Inputs!$R$18="MLN","m","k"))) -> 12.095169 | Q27: =G27/_xll.BQL(Inputs!$K21, "is_oper_inc(fpr = 2026, fpt = a, ae = e, fa_adjusted = y, fs = mr)/1"&IF(Inputs!$R$18="BLN","b",IF(Inputs!$R$18="MLN","m","k"))) -> 13.809275 | S27: =_xll.BQL(Inputs!$K21, "ebitda(fpt = ltm, fa_adjusted = y, fs = mr)/1"&IF(Inputs!$R$18="BLN","b",IF(Inputs!$R$18="MLN","m","k")))/_xll.BQL(Inputs!$K21, "sales_rev_turn(fpt = ltm, fa_adjusted = y, fs = mr)/1"&IF(Inputs!$R$18="BLN","b",IF(Inputs!$R$18="MLN","m","k"))) -> 0.19736256 | T27: =_xll.BDP(Inputs!$K21,"TOT_DEBT_TO_EBITDA") -> 3.041248 | V27: =F27/_xll.BQL(Inputs!$K21, "earn_for_common(fpt = ltm, fa_adjusted = y, fs = mr)/1"&IF(Inputs!$R$18="BLN","b",IF(Inputs!$R$18="MLN","m","k"))) -> 12.16032 | W27: =F27/_xll.BQL(Inputs!$K21, "EARN_FOR_COMMON(fpr = 2025, fpt = a, ae = e, fa_adjusted = y, fs = mr)/1"&IF(Inputs!$R$18="BLN","b",IF(Inputs!$R$18="MLN","m","k"))) -> 11.469324 | X27: =F27/_xll.BQL(Inputs!$K21, "EARN_FOR_COMMON(fpr = 2026, fpt = a, ae = e, fa_adjusted = y, fs = mr)/1"&IF(Inputs!$R$18="BLN","b",IF(Inputs!$R$18="MLN","m","k"))) -> 13.655252 | Z27: =(_xll.BQL(Inputs!$K21, "EARN_FOR_COMMON(fpr = 2028, fpt = a, ae = e, fa_adjusted = y, fs = mr)")/_xll.BQL(Inputs!$K21, "EARN_FOR_COMMON(fpr = 2025, fpt = a, ae = e, fa_adjusted = y, fs = mr)"))^(1/3)-1 -> -0.03798042
B28: =+Inputs!H22 -> CONAGRA BRANDS I | C28: =+_xll.BDP(Inputs!K22,"TICKER_AND_EXCH_CODE") -> CAG US | D28: =CONCATENATE(_xll.BDP(Inputs!K22,"CRNCY")," ",_xll.BDP(Inputs!K22,"PX_YEST_CLOSE")) -> USD 19,3 | E28: =_xll.BDP(Inputs!K22,"PX_YEST_CLOSE")/_xll.BDP(Inputs!K22,"HIGH_52WEEK") -> 0.6305129 | F28: =_xll.BDP(Inputs!$K22, "CUR_MKT_CAP", "SCALING_FORMAT=" & Inputs!$R$18) -> 9186743.3 | G28: =_xll.BDP(Inputs!$K22, "ENTERPRISE_VALUE", "SCALING_FORMAT=" & Inputs!$R$18) -> 16986093 | I28: =G28/_xll.BQL(Inputs!$K22, "sales_rev_turn(fpt = ltm, fa_adjusted = y, fs = mr)/1"&IF(Inputs!$R$18="BLN","b",IF(Inputs!$R$18="MLN","m","k"))) -> 1.4834368 | J28: =G28/_xll.BQL(Inputs!$K22, "sales_rev_turn(fpt = ltm, fa_adjusted = y, fs = mr)/1"&IF(Inputs!$R$18="BLN","b",IF(Inputs!$R$18="MLN","m","k"))) -> 1.4834368 | K28: =G28/_xll.BQL(Inputs!$K22, "sales_rev_turn(fpr = 2026, fpt = a, ae = e, fa_adjusted = y, fs = mr)/1"&IF(Inputs!$R$18="BLN","b",IF(Inputs!$R$18="MLN","m","k"))) -> 1.5097109 | L28: =G28/_xll.BQL(Inputs!$K22, "ebitda(fpt = ltm, fa_adjusted = y, fs = mr)/1"&IF(Inputs!$R$18="BLN","b",IF(Inputs!$R$18="MLN","m","k"))) -> 8.6974307 | M28: =G28/_xll.BQL(Inputs!$K22, "ebitda(fpr = 2025, fpt = a, ae = e, fa_adjusted = y, fs = mr)/1"&IF(Inputs!$R$18="BLN","b",IF(Inputs!$R$18="MLN","m","k"))) -> 7.9475779 | N28: =G28/_xll.BQL(Inputs!$K22, "ebitda(fpr = 2026, fpt = a, ae = e, fa_adjusted = y, fs = mr)/1"&IF(Inputs!$R$18="BLN","b",IF(Inputs!$R$18="MLN","m","k"))) -> 9.7303173 | O28: =G28/_xll.BQL(Inputs!$K22, "is_oper_inc(fpt = ltm, fa_adjusted = y, fs = mr)/1"&IF(Inputs!$R$18="BLN","b",IF(Inputs!$R$18="MLN","m","k"))) -> 10.84264 | P28: =G28/_xll.BQL(Inputs!$K22, "is_oper_inc(fpr = 2025, fpt = a, ae = e, fa_adjusted = y, fs = mr)/1"&IF(Inputs!$R$18="BLN","b",IF(Inputs!$R$18="MLN","m","k"))) -> 10.18122 | Q28: =G28/_xll.BQL(Inputs!$K22, "is_oper_inc(fpr = 2026, fpt = a, ae = e, fa_adjusted = y, fs = mr)/1"&IF(Inputs!$R$18="BLN","b",IF(Inputs!$R$18="MLN","m","k"))) -> 13.353191 | S28: =_xll.BQL(Inputs!$K22, "ebitda(fpt = ltm, fa_adjusted = y, fs = mr)/1"&IF(Inputs!$R$18="BLN","b",IF(Inputs!$R$18="MLN","m","k")))/_xll.BQL(Inputs!$K22, "sales_rev_turn(fpt = ltm, fa_adjusted = y, fs = mr)/1"&IF(Inputs!$R$18="BLN","b",IF(Inputs!$R$18="MLN","m","k"))) -> 0.17056035 | T28: =_xll.BDP(Inputs!$K22,"TOT_DEBT_TO_EBITDA") -> 4.8796558 | V28: =F28/_xll.BQL(Inputs!$K22, "earn_for_common(fpt = ltm, fa_adjusted = y, fs = mr)/1"&IF(Inputs!$R$18="BLN","b",IF(Inputs!$R$18="MLN","m","k"))) -> 8.2160645 | W28: =F28/_xll.BQL(Inputs!$K22, "EARN_FOR_COMMON(fpr = 2025, fpt = a, ae = e, fa_adjusted = y, fs = mr)/1"&IF(Inputs!$R$18="BLN","b",IF(Inputs!$R$18="MLN","m","k"))) -> 8.2759067 | X28: =F28/_xll.BQL(Inputs!$K22, "EARN_FOR_COMMON(fpr = 2026, fpt = a, ae = e, fa_adjusted = y, fs = mr)/1"&IF(Inputs!$R$18="BLN","b",IF(Inputs!$R$18="MLN","m","k"))) -> 10.913671 | Z28: =(_xll.BQL(Inputs!$K22, "EARN_FOR_COMMON(fpr = 2028, fpt = a, ae = e, fa_adjusted = y, fs = mr)")/_xll.BQL(Inputs!$K22, "EARN_FOR_COMMON(fpr = 2025, fpt = a, ae = e, fa_adjusted = y, fs = mr)"))^(1/3)-1 -> -0.045911712
B29: =+Inputs!H23 -> PILGRIM'S PRIDE | C29: =+_xll.BDP(Inputs!K23,"TICKER_AND_EXCH_CODE") -> PPC US | D29: =CONCATENATE(_xll.BDP(Inputs!K23,"CRNCY")," ",_xll.BDP(Inputs!K23,"PX_YEST_CLOSE")) -> USD 41,24 | E29: =_xll.BDP(Inputs!K23,"PX_YEST_CLOSE")/_xll.BDP(Inputs!K23,"HIGH_52WEEK") -> 0.78174315 | F29: =_xll.BDP(Inputs!$K23, "CUR_MKT_CAP", "SCALING_FORMAT=" & Inputs!$R$18) -> 9673454.6 | G29: =_xll.BDP(Inputs!$K23, "ENTERPRISE_VALUE", "SCALING_FORMAT=" & Inputs!$R$18) -> 14274844 | I29: =G29/_xll.BQL(Inputs!$K23, "sales_rev_turn(fpt = ltm, fa_adjusted = y, fs = mr)/1"&IF(Inputs!$R$18="BLN","b",IF(Inputs!$R$18="MLN","m","k"))) -> 0.7853065 | J29: =G29/_xll.BQL(Inputs!$K23, "sales_rev_turn(fpr = 2025, fpt = a, ae = e, fa_adjusted = y, fs = mr)/1"&IF(Inputs!$R$18="BLN","b",IF(Inputs!$R$18="MLN","m","k"))) -> 0.77730113 | K29: =G29/_xll.BQL(Inputs!$K23, "sales_rev_turn(fpr = 2026, fpt = a, ae = e, fa_adjusted = y, fs = mr)/1"&IF(Inputs!$R$18="BLN","b",IF(Inputs!$R$18="MLN","m","k"))) -> 0.77330085 | L29: =G29/_xll.BQL(Inputs!$K23, "ebitda(fpt = ltm, fa_adjusted = y, fs = mr)/1"&IF(Inputs!$R$18="BLN","b",IF(Inputs!$R$18="MLN","m","k"))) -> 5.8614561 | M29: =G29/_xll.BQL(Inputs!$K23, "ebitda(fpr = 2025, fpt = a, ae = e, fa_adjusted = y, fs = mr)/1"&IF(Inputs!$R$18="BLN","b",IF(Inputs!$R$18="MLN","m","k"))) -> 6.246513 | N29: =G29/_xll.BQL(Inputs!$K23, "ebitda(fpr = 2026, fpt = a, ae = e, fa_adjusted = y, fs = mr)/1"&IF(Inputs!$R$18="BLN","b",IF(Inputs!$R$18="MLN","m","k"))) -> 7.2004256 | O29: =G29/_xll.BQL(Inputs!$K23, "is_oper_inc(fpt = ltm, fa_adjusted = y, fs = mr)/1"&IF(Inputs!$R$18="BLN","b",IF(Inputs!$R$18="MLN","m","k"))) -> 7.1552061 | P29: =G29/_xll.BQL(Inputs!$K23, "is_oper_inc(fpr = 2025, fpt = a, ae = e, fa_adjusted = y, fs = mr)/1"&IF(Inputs!$R$18="BLN","b",IF(Inputs!$R$18="MLN","m","k"))) -> 7.8773281 | Q29: =G29/_xll.BQL(Inputs!$K23, "is_oper_inc(fpr = 2026, fpt = a, ae = e, fa_adjusted = y, fs = mr)/1"&IF(Inputs!$R$18="BLN","b",IF(Inputs!$R$18="MLN","m","k"))) -> 9.427006 | S29: =_xll.BQL(Inputs!$K23, "ebitda(fpt = ltm, fa_adjusted = y, fs = mr)/1"&IF(Inputs!$R$18="BLN","b",IF(Inputs!$R$18="MLN","m","k")))/_xll.BQL(Inputs!$K23, "sales_rev_turn(fpt = ltm, fa_adjusted = y, fs = mr)/1"&IF(Inputs!$R$18="BLN","b",IF(Inputs!$R$18="MLN","m","k"))) -> 0.13397806 | T29: =_xll.BDP(Inputs!$K23,"TOT_DEBT_TO_EBITDA") -> 1.570389 | V29: =F29/_xll.BQL(Inputs!$K23, "earn_for_common(fpt = ltm, fa_adjusted = y, fs = mr)/1"&IF(Inputs!$R$18="BLN","b",IF(Inputs!$R$18="MLN","m","k"))) -> 6.7494944 | W29: =F29/_xll.BQL(Inputs!$K23, "EARN_FOR_COMMON(fpr = 2025, fpt = a, ae = e, fa_adjusted = y, fs = mr)/1"&IF(Inputs!$R$18="BLN","b",IF(Inputs!$R$18="MLN","m","k"))) -> 7.4746591 | X29: =F29/_xll.BQL(Inputs!$K23, "EARN_FOR_COMMON(fpr = 2026, fpt = a, ae = e, fa_adjusted = y, fs = mr)/1"&IF(Inputs!$R$18="BLN","b",IF(Inputs!$R$18="MLN","m","k"))) -> 8.9169961 | Z29: =(_xll.BQL(Inputs!$K23, "EARN_FOR_COMMON(fpr = 2028, fpt = a, ae = e, fa_adjusted = y, fs = mr)")/_xll.BQL(Inputs!$K23, "EARN_FOR_COMMON(fpr = 2025, fpt = a, ae = e, fa_adjusted = y, fs = mr)"))^(1/3)-1 -> -0.13383241
B30: =+Inputs!H24 -> NESTLE SA-REG | C30: =+_xll.BDP(Inputs!K24,"TICKER_AND_EXCH_CODE") -> NESN SW | D30: =CONCATENATE(_xll.BDP(Inputs!K24,"CRNCY")," ",_xll.BDP(Inputs!K24,"PX_YEST_CLOSE")) -> CHF 73,88 | E30: =_xll.BDP(Inputs!K24,"PX_YEST_CLOSE")/_xll.BDP(Inputs!K24,"HIGH_52WEEK") -> 0.80549498 | F30: =_xll.BDP(Inputs!$K24, "CUR_MKT_CAP", "SCALING_FORMAT=" & Inputs!$R$18) -> 1.9228569e+08 | G30: =_xll.BDP(Inputs!$K24, "ENTERPRISE_VALUE", "SCALING_FORMAT=" & Inputs!$R$18) -> 2.6341707e+08 | I30: =G30/_xll.BQL(Inputs!$K24, "sales_rev_turn(fpt = ltm, fa_adjusted = y, fs = mr)/1"&IF(Inputs!$R$18="BLN","b",IF(Inputs!$R$18="MLN","m","k"))) -> 2.8979095 | J30: =G30/_xll.BQL(Inputs!$K24, "sales_rev_turn(fpr = 2025, fpt = a, ae = e, fa_adjusted = y, fs = mr)/1"&IF(Inputs!$R$18="BLN","b",IF(Inputs!$R$18="MLN","m","k"))) -> 2.9376918 | K30: =G30/_xll.BQL(Inputs!$K24, "sales_rev_turn(fpr = 2026, fpt = a, ae = e, fa_adjusted = y, fs = mr)/1"&IF(Inputs!$R$18="BLN","b",IF(Inputs!$R$18="MLN","m","k"))) -> 2.8805751 | L30: =G30/_xll.BQL(Inputs!$K24, "ebitda(fpt = ltm, fa_adjusted = y, fs = mr)/1"&IF(Inputs!$R$18="BLN","b",IF(Inputs!$R$18="MLN","m","k"))) -> 13.995169 | M30: =G30/_xll.BQL(Inputs!$K24, "ebitda(fpr = 2025, fpt = a, ae = e, fa_adjusted = y, fs = mr)/1"&IF(Inputs!$R$18="BLN","b",IF(Inputs!$R$18="MLN","m","k"))) -> 14.780799 | N30: =G30/_xll.BQL(Inputs!$K24, "ebitda(fpr = 2026, fpt = a, ae = e, fa_adjusted = y, fs = mr)/1"&IF(Inputs!$R$18="BLN","b",IF(Inputs!$R$18="MLN","m","k"))) -> 14.193204 | O30: =G30/_xll.BQL(Inputs!$K24, "is_oper_inc(fpt = ltm, fa_adjusted = y, fs = mr)/1"&IF(Inputs!$R$18="BLN","b",IF(Inputs!$R$18="MLN","m","k"))) -> 17.323232 | P30: =G30/_xll.BQL(Inputs!$K24, "is_oper_inc(fpr = 2025, fpt = a, ae = e, fa_adjusted = y, fs = mr)/1"&IF(Inputs!$R$18="BLN","b",IF(Inputs!$R$18="MLN","m","k"))) -> 18.609472 | Q30: =G30/_xll.BQL(Inputs!$K24, "is_oper_inc(fpr = 2026, fpt = a, ae = e, fa_adjusted = y, fs = mr)/1"&IF(Inputs!$R$18="BLN","b",IF(Inputs!$R$18="MLN","m","k"))) -> 17.78234 | S30: =_xll.BQL(Inputs!$K24, "ebitda(fpt = ltm, fa_adjusted = y, fs = mr)/1"&IF(Inputs!$R$18="BLN","b",IF(Inputs!$R$18="MLN","m","k")))/_xll.BQL(Inputs!$K24, "sales_rev_turn(fpt = ltm, fa_adjusted = y, fs = mr)/1"&IF(Inputs!$R$18="BLN","b",IF(Inputs!$R$18="MLN","m","k"))) -> 0.20706498 | T30: =_xll.BDP(Inputs!$K24,"TOT_DEBT_TO_EBITDA") -> 3.7037204 | V30: =F30/_xll.BQL(Inputs!$K24, "earn_for_common(fpt = ltm, fa_adjusted = y, fs = mr)/1"&IF(Inputs!$R$18="BLN","b",IF(Inputs!$R$18="MLN","m","k"))) -> 17.181764 | W30: =F30/_xll.BQL(Inputs!$K24, "EARN_FOR_COMMON(fpr = 2025, fpt = a, ae = e, fa_adjusted = y, fs = mr)/1"&IF(Inputs!$R$18="BLN","b",IF(Inputs!$R$18="MLN","m","k"))) -> 17.421615 | X30: =F30/_xll.BQL(Inputs!$K24, "EARN_FOR_COMMON(fpr = 2026, fpt = a, ae = e, fa_adjusted = y, fs = mr)/1"&IF(Inputs!$R$18="BLN","b",IF(Inputs!$R$18="MLN","m","k"))) -> 16.544635 | Z30: =(_xll.BQL(Inputs!$K24, "EARN_FOR_COMMON(fpr = 2028, fpt = a, ae = e, fa_adjusted = y, fs = mr)")/_xll.BQL(Inputs!$K24, "EARN_FOR_COMMON(fpr = 2025, fpt = a, ae = e, fa_adjusted = y, fs = mr)"))^(1/3)-1 -> 0.059915672
B31: =+Inputs!H25 -> UNILEVER PLC | C31: =+_xll.BDP(Inputs!K25,"TICKER_AND_EXCH_CODE") -> ULVR LN | D31: =CONCATENATE(_xll.BDP(Inputs!K25,"CRNCY")," ",_xll.BDP(Inputs!K25,"PX_YEST_CLOSE")) -> GBp 4372 | E31: =_xll.BDP(Inputs!K25,"PX_YEST_CLOSE")/_xll.BDP(Inputs!K25,"HIGH_52WEEK") -> 0.8904277 | F31: =_xll.BDP(Inputs!$K25, "CUR_MKT_CAP", "SCALING_FORMAT=" & Inputs!$R$18) -> 1.0749065e+08 | G31: =_xll.BDP(Inputs!$K25, "ENTERPRISE_VALUE", "SCALING_FORMAT=" & Inputs!$R$18) -> 1.5518155e+08 | I31: =G31/_xll.BQL(Inputs!$K25, "sales_rev_turn(fpt = ltm, fa_adjusted = y, fs = mr)/1"&IF(Inputs!$R$18="BLN","b",IF(Inputs!$R$18="MLN","m","k"))) -> 2.5937513 | J31: =G31/_xll.BQL(Inputs!$K25, "sales_rev_turn(fpr = 2025, fpt = a, ae = e, fa_adjusted = y, fs = mr)/1"&IF(Inputs!$R$18="BLN","b",IF(Inputs!$R$18="MLN","m","k"))) -> 2.6265731 | K31: =G31/_xll.BQL(Inputs!$K25, "sales_rev_turn(fpr = 2026, fpt = a, ae = e, fa_adjusted = y, fs = mr)/1"&IF(Inputs!$R$18="BLN","b",IF(Inputs!$R$18="MLN","m","k"))) -> 2.5947555 | L31: =G31/_xll.BQL(Inputs!$K25, "ebitda(fpt = ltm, fa_adjusted = y, fs = mr)/1"&IF(Inputs!$R$18="BLN","b",IF(Inputs!$R$18="MLN","m","k"))) -> 12.224795 | M31: =G31/_xll.BQL(Inputs!$K25, "ebitda(fpr = 2025, fpt = a, ae = e, fa_adjusted = y, fs = mr)/1"&IF(Inputs!$R$18="BLN","b",IF(Inputs!$R$18="MLN","m","k"))) -> 12.177093 | N31: =G31/_xll.BQL(Inputs!$K25, "ebitda(fpr = 2026, fpt = a, ae = e, fa_adjusted = y, fs = mr)/1"&IF(Inputs!$R$18="BLN","b",IF(Inputs!$R$18="MLN","m","k"))) -> 11.798411 | O31: =G31/_xll.BQL(Inputs!$K25, "is_oper_inc(fpt = ltm, fa_adjusted = y, fs = mr)/1"&IF(Inputs!$R$18="BLN","b",IF(Inputs!$R$18="MLN","m","k"))) -> 14.256458 | P31: =G31/_xll.BQL(Inputs!$K25, "is_oper_inc(fpr = 2025, fpt = a, ae = e, fa_adjusted = y, fs = mr)/1"&IF(Inputs!$R$18="BLN","b",IF(Inputs!$R$18="MLN","m","k"))) -> 14.104499 | Q31: =G31/_xll.BQL(Inputs!$K25, "is_oper_inc(fpr = 2026, fpt = a, ae = e, fa_adjusted = y, fs = mr)/1"&IF(Inputs!$R$18="BLN","b",IF(Inputs!$R$18="MLN","m","k"))) -> 13.523545 | S31: =_xll.BQL(Inputs!$K25, "ebitda(fpt = ltm, fa_adjusted = y, fs = mr)/1"&IF(Inputs!$R$18="BLN","b",IF(Inputs!$R$18="MLN","m","k")))/_xll.BQL(Inputs!$K25, "sales_rev_turn(fpt = ltm, fa_adjusted = y, fs = mr)/1"&IF(Inputs!$R$18="BLN","b",IF(Inputs!$R$18="MLN","m","k"))) -> 0.21217136 | T31: =_xll.BDP(Inputs!$K25,"TOT_DEBT_TO_EBITDA") -> #N/A N/A | V31: =F31/_xll.BQL(Inputs!$K25, "earn_for_common(fpt = ltm, fa_adjusted = y, fs = mr)/1"&IF(Inputs!$R$18="BLN","b",IF(Inputs!$R$18="MLN","m","k"))) -> 14.650645 | W31: =F31/_xll.BQL(Inputs!$K25, "EARN_FOR_COMMON(fpr = 2025, fpt = a, ae = e, fa_adjusted = y, fs = mr)/1"&IF(Inputs!$R$18="BLN","b",IF(Inputs!$R$18="MLN","m","k"))) -> 14.555432 | X31: =F31/_xll.BQL(Inputs!$K25, "EARN_FOR_COMMON(fpr = 2026, fpt = a, ae = e, fa_adjusted = y, fs = mr)/1"&IF(Inputs!$R$18="BLN","b",IF(Inputs!$R$18="MLN","m","k"))) -> 13.94511 | Z31: =(_xll.BQL(Inputs!$K25, "EARN_FOR_COMMON(fpr = 2028, fpt = a, ae = e, fa_adjusted = y, fs = mr)")/_xll.BQL(Inputs!$K25, "EARN_FOR_COMMON(fpr = 2025, fpt = a, ae = e, fa_adjusted = y, fs = mr)"))^(1/3)-1 -> 0.049528864
B33: Mean | I33: =AVERAGE(I27:I31) -> 1.9728121 | J33: =AVERAGE(J27:J31) -> 1.9781498 | K33: =AVERAGE(K27:K31) -> 1.9852163 | L33: =AVERAGE(L27:L31) -> 10.287539 | M33: =AVERAGE(M27:M31) -> 10.302913 | N33: =AVERAGE(N27:N31) -> 10.905263 | O33: =AVERAGE(O27:O31) -> 12.401039 | P33: =AVERAGE(P27:P31) -> 12.573538 | Q33: =AVERAGE(Q27:Q31) -> 13.579071 | S33: =AVERAGE(S27:S31) -> 0.18422746 | T33: =AVERAGE(T27:T31) -> 3.2987533 | V33: =AVERAGE(V27:V31) -> 11.791658 | W33: =AVERAGE(W27:W31) -> 11.839387 | X33: =AVERAGE(X27:X31) -> 12.795133 | Z33: =AVERAGE(Z27:Z31) -> -0.021656002
B34: Median | I34: =MEDIAN(I27:I31) -> 2.1036566 | J34: =MEDIAN(J27:J31) -> 2.0657461 | K34: =MEDIAN(K27:K31) -> 2.1677389 | L34: =MEDIAN(L27:L31) -> 10.658843 | M34: =MEDIAN(M27:M31) -> 10.362583 | N34: =MEDIAN(N27:N31) -> 11.603958 | O34: =MEDIAN(O27:O31) -> 12.42766 | P34: =MEDIAN(P27:P31) -> 12.095169 | Q34: =MEDIAN(Q27:Q31) -> 13.523545 | S34: =MEDIAN(S27:S31) -> 0.19736256 | T34: =MEDIAN(T27:T31) -> 3.3724842 | V34: =MEDIAN(V27:V31) -> 12.16032 | W34: =MEDIAN(W27:W31) -> 11.469324 | X34: =MEDIAN(X27:X31) -> 13.655252 | Z34: =MEDIAN(Z27:Z31) -> -0.03798042
B36: Tier III: Semiconductors
B39: =+Inputs!N21 -> PEPSICO INC | C39: =+_xll.BDP(Inputs!Q21,"TICKER_AND_EXCH_CODE") -> PEP US | D39: =CONCATENATE(_xll.BDP(Inputs!Q21,"CRNCY")," ",_xll.BDP(Inputs!Q21,"PX_YEST_CLOSE")) -> USD 143,14 | E39: =_xll.BDP(Inputs!Q21,"PX_YEST_CLOSE")/_xll.BDP(Inputs!Q21,"HIGH_52WEEK") -> 0.80642254 | F39: =_xll.BDP(Inputs!$Q21, "CUR_MKT_CAP", "SCALING_FORMAT=" & Inputs!$R$18) -> 1.9440896e+08 | G39: =_xll.BDP(Inputs!$Q21, "ENTERPRISE_VALUE", "SCALING_FORMAT=" & Inputs!$R$18) -> 222816500 | I39: =G39/_xll.BQL(Inputs!$Q21, "sales_rev_turn(fpt = ltm, fa_adjusted = y, fs = mr)/1"&IF(Inputs!$R$18="BLN","b",IF(Inputs!$R$18="MLN","m","k"))) -> 2.4285707 | J39: =G39/_xll.BQL(Inputs!$Q21, "sales_rev_turn(fpr = 2025, fpt = a, ae = e, fa_adjusted = y, fs = mr)/1"&IF(Inputs!$R$18="BLN","b",IF(Inputs!$R$18="MLN","m","k"))) -> 2.3944223 | K39: =G39/_xll.BQL(Inputs!$Q21, "sales_rev_turn(fpr = 2026, fpt = a, ae = e, fa_adjusted = y, fs = mr)/1"&IF(Inputs!$R$18="BLN","b",IF(Inputs!$R$18="MLN","m","k"))) -> 2.3204964 | L39: =G39/_xll.BQL(Inputs!$Q21, "ebitda(fpt = ltm, fa_adjusted = y, fs = mr)/1"&IF(Inputs!$R$18="BLN","b",IF(Inputs!$R$18="MLN","m","k"))) -> 12.797456 | M39: =G39/_xll.BQL(Inputs!$Q21, "ebitda(fpr = 2025, fpt = a, ae = e, fa_adjusted = y, fs = mr)/1"&IF(Inputs!$R$18="BLN","b",IF(Inputs!$R$18="MLN","m","k"))) -> 12.388636 | N39: =G39/_xll.BQL(Inputs!$Q21, "ebitda(fpr = 2026, fpt = a, ae = e, fa_adjusted = y, fs = mr)/1"&IF(Inputs!$R$18="BLN","b",IF(Inputs!$R$18="MLN","m","k"))) -> 11.798071 | O39: =G39/_xll.BQL(Inputs!$Q21, "is_oper_inc(fpt = ltm, fa_adjusted = y, fs = mr)/1"&IF(Inputs!$R$18="BLN","b",IF(Inputs!$R$18="MLN","m","k"))) -> 15.759 | P39: =G39/_xll.BQL(Inputs!$Q21, "is_oper_inc(fpr = 2025, fpt = a, ae = e, fa_adjusted = y, fs = mr)/1"&IF(Inputs!$R$18="BLN","b",IF(Inputs!$R$18="MLN","m","k"))) -> 15.113646 | Q39: =G39/_xll.BQL(Inputs!$Q21, "is_oper_inc(fpr = 2026, fpt = a, ae = e, fa_adjusted = y, fs = mr)/1"&IF(Inputs!$R$18="BLN","b",IF(Inputs!$R$18="MLN","m","k"))) -> 14.318035 | S39: =_xll.BQL(Inputs!$Q21, "ebitda(fpt = ltm, fa_adjusted = y, fs = mr)/1"&IF(Inputs!$R$18="BLN","b",IF(Inputs!$R$18="MLN","m","k")))/_xll.BQL(Inputs!$Q21, "sales_rev_turn(fpt = ltm, fa_adjusted = y, fs = mr)/1"&IF(Inputs!$R$18="BLN","b",IF(Inputs!$R$18="MLN","m","k"))) -> 0.1897698 | T39: =_xll.BDP(Inputs!$Q21,"TOT_DEBT_TO_EBITDA") -> 3.7326747 | V39: =F39/_xll.BQL(Inputs!$Q21, "earn_for_common(fpt = ltm, fa_adjusted = y, fs = mr)/1"&IF(Inputs!$R$18="BLN","b",IF(Inputs!$R$18="MLN","m","k"))) -> 17.921821 | W39: =F39/_xll.BQL(Inputs!$Q21, "EARN_FOR_COMMON(fpr = 2025, fpt = a, ae = e, fa_adjusted = y, fs = mr)/1"&IF(Inputs!$R$18="BLN","b",IF(Inputs!$R$18="MLN","m","k"))) -> 17.64531 | X39: =F39/_xll.BQL(Inputs!$Q21, "EARN_FOR_COMMON(fpr = 2026, fpt = a, ae = e, fa_adjusted = y, fs = mr)/1"&IF(Inputs!$R$18="BLN","b",IF(Inputs!$R$18="MLN","m","k"))) -> 16.715946 | Z39: =(_xll.BQL(Inputs!$Q21, "EARN_FOR_COMMON(fpr = 2028, fpt = a, ae = e, fa_adjusted = y, fs = mr)")/_xll.BQL(Inputs!$Q21, "EARN_FOR_COMMON(fpr = 2025, fpt = a, ae = e, fa_adjusted = y, fs = mr)"))^(1/3)-1 -> 0.046915196
B40: =+Inputs!N22 -> PROCTER & GAMBLE | C40: =+_xll.BDP(Inputs!Q22,"TICKER_AND_EXCH_CODE") -> PG US | D40: =CONCATENATE(_xll.BDP(Inputs!Q22,"CRNCY")," ",_xll.BDP(Inputs!Q22,"PX_YEST_CLOSE")) -> USD 153,18 | E40: =_xll.BDP(Inputs!Q22,"PX_YEST_CLOSE")/_xll.BDP(Inputs!Q22,"HIGH_52WEEK") -> 0.8489719 | F40: =_xll.BDP(Inputs!$Q22, "CUR_MKT_CAP", "SCALING_FORMAT=" & Inputs!$R$18) -> 3.5575376e+08 | G40: =_xll.BDP(Inputs!$Q22, "ENTERPRISE_VALUE", "SCALING_FORMAT=" & Inputs!$R$18) -> 4.0019553e+08 | I40: =G40/_xll.BQL(Inputs!$Q22, "sales_rev_turn(fpt = ltm, fa_adjusted = y, fs = mr)/1"&IF(Inputs!$R$18="BLN","b",IF(Inputs!$R$18="MLN","m","k"))) -> 4.7481792 | J40: =G40/_xll.BQL(Inputs!$Q22, "sales_rev_turn(fpr = 2025, fpt = a, ae = e, fa_adjusted = y, fs = mr)/1"&IF(Inputs!$R$18="BLN","b",IF(Inputs!$R$18="MLN","m","k"))) -> 4.7499591 | K40: =G40/_xll.BQL(Inputs!$Q22, "sales_rev_turn(fpr = 2026, fpt = a, ae = e, fa_adjusted = y, fs = mr)/1"&IF(Inputs!$R$18="BLN","b",IF(Inputs!$R$18="MLN","m","k"))) -> 4.6068918 | L40: =G40/_xll.BQL(Inputs!$Q22, "ebitda(fpt = ltm, fa_adjusted = y, fs = mr)/1"&IF(Inputs!$R$18="BLN","b",IF(Inputs!$R$18="MLN","m","k"))) -> 15.929448 | M40: =G40/_xll.BQL(Inputs!$Q22, "ebitda(fpr = 2025, fpt = a, ae = e, fa_adjusted = y, fs = mr)/1"&IF(Inputs!$R$18="BLN","b",IF(Inputs!$R$18="MLN","m","k"))) -> 17.06962 | N40: =G40/_xll.BQL(Inputs!$Q22, "ebitda(fpr = 2026, fpt = a, ae = e, fa_adjusted = y, fs = mr)/1"&IF(Inputs!$R$18="BLN","b",IF(Inputs!$R$18="MLN","m","k"))) -> 16.542385 | O40: =G40/_xll.BQL(Inputs!$Q22, "is_oper_inc(fpt = ltm, fa_adjusted = y, fs = mr)/1"&IF(Inputs!$R$18="BLN","b",IF(Inputs!$R$18="MLN","m","k"))) -> 18.190706 | P40: =G40/_xll.BQL(Inputs!$Q22, "is_oper_inc(fpr = 2025, fpt = a, ae = e, fa_adjusted = y, fs = mr)/1"&IF(Inputs!$R$18="BLN","b",IF(Inputs!$R$18="MLN","m","k"))) -> 19.589671 | Q40: =G40/_xll.BQL(Inputs!$Q22, "is_oper_inc(fpr = 2026, fpt = a, ae = e, fa_adjusted = y, fs = mr)/1"&IF(Inputs!$R$18="BLN","b",IF(Inputs!$R$18="MLN","m","k"))) -> 18.895159 | S40: =_xll.BQL(Inputs!$Q22, "ebitda(fpt = ltm, fa_adjusted = y, fs = mr)/1"&IF(Inputs!$R$18="BLN","b",IF(Inputs!$R$18="MLN","m","k")))/_xll.BQL(Inputs!$Q22, "sales_rev_turn(fpt = ltm, fa_adjusted = y, fs = mr)/1"&IF(Inputs!$R$18="BLN","b",IF(Inputs!$R$18="MLN","m","k"))) -> 0.29807555 | T40: =_xll.BDP(Inputs!$Q22,"TOT_DEBT_TO_EBITDA") -> 1.5221907 | V40: =F40/_xll.BQL(Inputs!$Q22, "earn_for_common(fpt = ltm, fa_adjusted = y, fs = mr)/1"&IF(Inputs!$R$18="BLN","b",IF(Inputs!$R$18="MLN","m","k"))) -> 20.828126 | W40: =F40/_xll.BQL(Inputs!$Q22, "EARN_FOR_COMMON(fpr = 2025, fpt = a, ae = e, fa_adjusted = y, fs = mr)/1"&IF(Inputs!$R$18="BLN","b",IF(Inputs!$R$18="MLN","m","k"))) -> 21.547514 | X40: =F40/_xll.BQL(Inputs!$Q22, "EARN_FOR_COMMON(fpr = 2026, fpt = a, ae = e, fa_adjusted = y, fs = mr)/1"&IF(Inputs!$R$18="BLN","b",IF(Inputs!$R$18="MLN","m","k"))) -> 21.021081 | Z40: =(_xll.BQL(Inputs!$Q22, "EARN_FOR_COMMON(fpr = 2028, fpt = a, ae = e, fa_adjusted = y, fs = mr)")/_xll.BQL(Inputs!$Q22, "EARN_FOR_COMMON(fpr = 2025, fpt = a, ae = e, fa_adjusted = y, fs = mr)"))^(1/3)-1 -> 0.040501797
B41: =+Inputs!N23 -> COCA-COLA CO/THE | C41: =+_xll.BDP(Inputs!Q23,"TICKER_AND_EXCH_CODE") -> KO US | D41: =CONCATENATE(_xll.BDP(Inputs!Q23,"CRNCY")," ",_xll.BDP(Inputs!Q23,"PX_YEST_CLOSE")) -> USD 66,78 | E41: =_xll.BDP(Inputs!Q23,"PX_YEST_CLOSE")/_xll.BDP(Inputs!Q23,"HIGH_52WEEK") -> 0.897822 | F41: =_xll.BDP(Inputs!$Q23, "CUR_MKT_CAP", "SCALING_FORMAT=" & Inputs!$R$18) -> 2.8410659e+08 | G41: =_xll.BDP(Inputs!$Q23, "ENTERPRISE_VALUE", "SCALING_FORMAT=" & Inputs!$R$18) -> 339446320 | I41: =G41/_xll.BQL(Inputs!$Q23, "sales_rev_turn(fpt = ltm, fa_adjusted = y, fs = mr)/1"&IF(Inputs!$R$18="BLN","b",IF(Inputs!$R$18="MLN","m","k"))) -> 7.1937931 | J41: =G41/_xll.BQL(Inputs!$Q23, "sales_rev_turn(fpr = 2025, fpt = a, ae = e, fa_adjusted = y, fs = mr)/1"&IF(Inputs!$R$18="BLN","b",IF(Inputs!$R$18="MLN","m","k"))) -> 7.0164315 | K41: =G41/_xll.BQL(Inputs!$Q23, "sales_rev_turn(fpr = 2026, fpt = a, ae = e, fa_adjusted = y, fs = mr)/1"&IF(Inputs!$R$18="BLN","b",IF(Inputs!$R$18="MLN","m","k"))) -> 6.6436302 | L41: =G41/_xll.BQL(Inputs!$Q23, "ebitda(fpt = ltm, fa_adjusted = y, fs = mr)/1"&IF(Inputs!$R$18="BLN","b",IF(Inputs!$R$18="MLN","m","k"))) -> 21.619896 | M41: =G41/_xll.BQL(Inputs!$Q23, "ebitda(fpr = 2025, fpt = a, ae = e, fa_adjusted = y, fs = mr)/1"&IF(Inputs!$R$18="BLN","b",IF(Inputs!$R$18="MLN","m","k"))) -> 20.887229 | N41: =G41/_xll.BQL(Inputs!$Q23, "ebitda(fpr = 2026, fpt = a, ae = e, fa_adjusted = y, fs = mr)/1"&IF(Inputs!$R$18="BLN","b",IF(Inputs!$R$18="MLN","m","k"))) -> 19.5671 | O41: =G41/_xll.BQL(Inputs!$Q23, "is_oper_inc(fpt = ltm, fa_adjusted = y, fs = mr)/1"&IF(Inputs!$R$18="BLN","b",IF(Inputs!$R$18="MLN","m","k"))) -> 23.232808 | P41: =G41/_xll.BQL(Inputs!$Q23, "is_oper_inc(fpr = 2025, fpt = a, ae = e, fa_adjusted = y, fs = mr)/1"&IF(Inputs!$R$18="BLN","b",IF(Inputs!$R$18="MLN","m","k"))) -> 22.439171 | Q41: =G41/_xll.BQL(Inputs!$Q23, "is_oper_inc(fpr = 2026, fpt = a, ae = e, fa_adjusted = y, fs = mr)/1"&IF(Inputs!$R$18="BLN","b",IF(Inputs!$R$18="MLN","m","k"))) -> 20.906342 | S41: =_xll.BQL(Inputs!$Q23, "ebitda(fpt = ltm, fa_adjusted = y, fs = mr)/1"&IF(Inputs!$R$18="BLN","b",IF(Inputs!$R$18="MLN","m","k")))/_xll.BQL(Inputs!$Q23, "sales_rev_turn(fpt = ltm, fa_adjusted = y, fs = mr)/1"&IF(Inputs!$R$18="BLN","b",IF(Inputs!$R$18="MLN","m","k"))) -> 0.33273949 | T41: =_xll.BDP(Inputs!$Q23,"TOT_DEBT_TO_EBITDA") -> 3.4703818 | V41: =F41/_xll.BQL(Inputs!$Q23, "earn_for_common(fpt = ltm, fa_adjusted = y, fs = mr)/1"&IF(Inputs!$R$18="BLN","b",IF(Inputs!$R$18="MLN","m","k"))) -> 22.585785 | W41: =F41/_xll.BQL(Inputs!$Q23, "EARN_FOR_COMMON(fpr = 2025, fpt = a, ae = e, fa_adjusted = y, fs = mr)/1"&IF(Inputs!$R$18="BLN","b",IF(Inputs!$R$18="MLN","m","k"))) -> 22.12406 | X41: =F41/_xll.BQL(Inputs!$Q23, "EARN_FOR_COMMON(fpr = 2026, fpt = a, ae = e, fa_adjusted = y, fs = mr)/1"&IF(Inputs!$R$18="BLN","b",IF(Inputs!$R$18="MLN","m","k"))) -> 20.688137 | Z41: =(_xll.BQL(Inputs!$Q23, "EARN_FOR_COMMON(fpr = 2028, fpt = a, ae = e, fa_adjusted = y, fs = mr)")/_xll.BQL(Inputs!$Q23, "EARN_FOR_COMMON(fpr = 2025, fpt = a, ae = e, fa_adjusted = y, fs = mr)"))^(1/3)-1 -> 0.068733019
B42: =+Inputs!N24 -> KIMBERLY-CLARK | C42: =+_xll.BDP(Inputs!Q24,"TICKER_AND_EXCH_CODE") -> KMB US | D42: =CONCATENATE(_xll.BDP(Inputs!Q24,"CRNCY")," ",_xll.BDP(Inputs!Q24,"PX_YEST_CLOSE")) -> USD 123,23 | E42: =_xll.BDP(Inputs!Q24,"PX_YEST_CLOSE")/_xll.BDP(Inputs!Q24,"HIGH_52WEEK") -> 0.81907611 | F42: =_xll.BDP(Inputs!$Q24, "CUR_MKT_CAP", "SCALING_FORMAT=" & Inputs!$R$18) -> 40696127 | G42: =_xll.BDP(Inputs!$Q24, "ENTERPRISE_VALUE", "SCALING_FORMAT=" & Inputs!$R$18) -> 49527548 | I42: =G42/_xll.BQL(Inputs!$Q24, "sales_rev_turn(fpt = ltm, fa_adjusted = y, fs = mr)/1"&IF(Inputs!$R$18="BLN","b",IF(Inputs!$R$18="MLN","m","k"))) -> 2.6228644 | J42: =G42/_xll.BQL(Inputs!$Q24, "sales_rev_turn(fpr = 2025, fpt = a, ae = e, fa_adjusted = y, fs = mr)/1"&IF(Inputs!$R$18="BLN","b",IF(Inputs!$R$18="MLN","m","k"))) -> 2.994688 | K42: =G42/_xll.BQL(Inputs!$Q24, "sales_rev_turn(fpr = 2026, fpt = a, ae = e, fa_adjusted = y, fs = mr)/1"&IF(Inputs!$R$18="BLN","b",IF(Inputs!$R$18="MLN","m","k"))) -> 2.8799167 | L42: =G42/_xll.BQL(Inputs!$Q24, "ebitda(fpt = ltm, fa_adjusted = y, fs = mr)/1"&IF(Inputs!$R$18="BLN","b",IF(Inputs!$R$18="MLN","m","k"))) -> 10.201349 | M42: =G42/_xll.BQL(Inputs!$Q24, "ebitda(fpr = 2025, fpt = a, ae = e, fa_adjusted = y, fs = mr)/1"&IF(Inputs!$R$18="BLN","b",IF(Inputs!$R$18="MLN","m","k"))) -> 13.87715 | N42: =G42/_xll.BQL(Inputs!$Q24, "ebitda(fpr = 2026, fpt = a, ae = e, fa_adjusted = y, fs = mr)/1"&IF(Inputs!$R$18="BLN","b",IF(Inputs!$R$18="MLN","m","k"))) -> 13.442243 | O42: =G42/_xll.BQL(Inputs!$Q24, "is_oper_inc(fpt = ltm, fa_adjusted = y, fs = mr)/1"&IF(Inputs!$R$18="BLN","b",IF(Inputs!$R$18="MLN","m","k"))) -> 12.360257 | P42: =G42/_xll.BQL(Inputs!$Q24, "is_oper_inc(fpr = 2025, fpt = a, ae = e, fa_adjusted = y, fs = mr)/1"&IF(Inputs!$R$18="BLN","b",IF(Inputs!$R$18="MLN","m","k"))) -> 17.820596 | Q42: =G42/_xll.BQL(Inputs!$Q24, "is_oper_inc(fpr = 2026, fpt = a, ae = e, fa_adjusted = y, fs = mr)/1"&IF(Inputs!$R$18="BLN","b",IF(Inputs!$R$18="MLN","m","k"))) -> 16.820191 | S42: =_xll.BQL(Inputs!$Q24, "ebitda(fpt = ltm, fa_adjusted = y, fs = mr)/1"&IF(Inputs!$R$18="BLN","b",IF(Inputs!$R$18="MLN","m","k")))/_xll.BQL(Inputs!$Q24, "sales_rev_turn(fpt = ltm, fa_adjusted = y, fs = mr)/1"&IF(Inputs!$R$18="BLN","b",IF(Inputs!$R$18="MLN","m","k"))) -> 0.25710957 | T42: =_xll.BDP(Inputs!$Q24,"TOT_DEBT_TO_EBITDA") -> 1.8514446 | V42: =F42/_xll.BQL(Inputs!$Q24, "earn_for_common(fpt = ltm, fa_adjusted = y, fs = mr)/1"&IF(Inputs!$R$18="BLN","b",IF(Inputs!$R$18="MLN","m","k"))) -> 11.454889 | W42: =F42/_xll.BQL(Inputs!$Q24, "EARN_FOR_COMMON(fpr = 2025, fpt = a, ae = e, fa_adjusted = y, fs = mr)/1"&IF(Inputs!$R$18="BLN","b",IF(Inputs!$R$18="MLN","m","k"))) -> 17.288533 | X42: =F42/_xll.BQL(Inputs!$Q24, "EARN_FOR_COMMON(fpr = 2026, fpt = a, ae = e, fa_adjusted = y, fs = mr)/1"&IF(Inputs!$R$18="BLN","b",IF(Inputs!$R$18="MLN","m","k"))) -> 16.528123 | Z42: =(_xll.BQL(Inputs!$Q24, "EARN_FOR_COMMON(fpr = 2028, fpt = a, ae = e, fa_adjusted = y, fs = mr)")/_xll.BQL(Inputs!$Q24, "EARN_FOR_COMMON(fpr = 2025, fpt = a, ae = e, fa_adjusted = y, fs = mr)"))^(1/3)-1 -> 0.050721743
B43: =+Inputs!N25 -> COLGATE-PALMOLIV | C43: =+_xll.BDP(Inputs!Q25,"TICKER_AND_EXCH_CODE") -> CL US | D43: =CONCATENATE(_xll.BDP(Inputs!Q25,"CRNCY")," ",_xll.BDP(Inputs!Q25,"PX_YEST_CLOSE")) -> USD 79,01 | E43: =_xll.BDP(Inputs!Q25,"PX_YEST_CLOSE")/_xll.BDP(Inputs!Q25,"HIGH_52WEEK") -> 0.77000292 | F43: =_xll.BDP(Inputs!$Q25, "CUR_MKT_CAP", "SCALING_FORMAT=" & Inputs!$R$18) -> 63461498 | G43: =_xll.BDP(Inputs!$Q25, "ENTERPRISE_VALUE", "SCALING_FORMAT=" & Inputs!$R$18) -> 81163272 | I43: =G43/_xll.BQL(Inputs!$Q25, "sales_rev_turn(fpt = ltm, fa_adjusted = y, fs = mr)/1"&IF(Inputs!$R$18="BLN","b",IF(Inputs!$R$18="MLN","m","k"))) -> 4.0585695 | J43: =G43/_xll.BQL(Inputs!$Q25, "sales_rev_turn(fpr = 2025, fpt = a, ae = e, fa_adjusted = y, fs = mr)/1"&IF(Inputs!$R$18="BLN","b",IF(Inputs!$R$18="MLN","m","k"))) -> 3.9890827 | K43: =G43/_xll.BQL(Inputs!$Q25, "sales_rev_turn(fpr = 2026, fpt = a, ae = e, fa_adjusted = y, fs = mr)/1"&IF(Inputs!$R$18="BLN","b",IF(Inputs!$R$18="MLN","m","k"))) -> 3.844395 | L43: =G43/_xll.BQL(Inputs!$Q25, "ebitda(fpt = ltm, fa_adjusted = y, fs = mr)/1"&IF(Inputs!$R$18="BLN","b",IF(Inputs!$R$18="MLN","m","k"))) -> 16.337213 | M43: =G43/_xll.BQL(Inputs!$Q25, "ebitda(fpr = 2025, fpt = a, ae = e, fa_adjusted = y, fs = mr)/1"&IF(Inputs!$R$18="BLN","b",IF(Inputs!$R$18="MLN","m","k"))) -> 16.274037 | N43: =G43/_xll.BQL(Inputs!$Q25, "ebitda(fpr = 2026, fpt = a, ae = e, fa_adjusted = y, fs = mr)/1"&IF(Inputs!$R$18="BLN","b",IF(Inputs!$R$18="MLN","m","k"))) -> 15.558149 | O43: =G43/_xll.BQL(Inputs!$Q25, "is_oper_inc(fpt = ltm, fa_adjusted = y, fs = mr)/1"&IF(Inputs!$R$18="BLN","b",IF(Inputs!$R$18="MLN","m","k"))) -> 18.568582 | P43: =G43/_xll.BQL(Inputs!$Q25, "is_oper_inc(fpr = 2025, fpt = a, ae = e, fa_adjusted = y, fs = mr)/1"&IF(Inputs!$R$18="BLN","b",IF(Inputs!$R$18="MLN","m","k"))) -> 18.520727 | Q43: =G43/_xll.BQL(Inputs!$Q25, "is_oper_inc(fpr = 2026, fpt = a, ae = e, fa_adjusted = y, fs = mr)/1"&IF(Inputs!$R$18="BLN","b",IF(Inputs!$R$18="MLN","m","k"))) -> 17.63562 | S43: =_xll.BQL(Inputs!$Q25, "ebitda(fpt = ltm, fa_adjusted = y, fs = mr)/1"&IF(Inputs!$R$18="BLN","b",IF(Inputs!$R$18="MLN","m","k")))/_xll.BQL(Inputs!$Q25, "sales_rev_turn(fpt = ltm, fa_adjusted = y, fs = mr)/1"&IF(Inputs!$R$18="BLN","b",IF(Inputs!$R$18="MLN","m","k"))) -> 0.24842484 | T43: =_xll.BDP(Inputs!$Q25,"TOT_DEBT_TO_EBITDA") -> 1.7939369 | V43: =F43/_xll.BQL(Inputs!$Q25, "earn_for_common(fpt = ltm, fa_adjusted = y, fs = mr)/1"&IF(Inputs!$R$18="BLN","b",IF(Inputs!$R$18="MLN","m","k"))) -> 21.280808 | W43: =F43/_xll.BQL(Inputs!$Q25, "EARN_FOR_COMMON(fpr = 2025, fpt = a, ae = e, fa_adjusted = y, fs = mr)/1"&IF(Inputs!$R$18="BLN","b",IF(Inputs!$R$18="MLN","m","k"))) -> 21.289413 | X43: =F43/_xll.BQL(Inputs!$Q25, "EARN_FOR_COMMON(fpr = 2026, fpt = a, ae = e, fa_adjusted = y, fs = mr)/1"&IF(Inputs!$R$18="BLN","b",IF(Inputs!$R$18="MLN","m","k"))) -> 20.214602 | Z43: =(_xll.BQL(Inputs!$Q25, "EARN_FOR_COMMON(fpr = 2028, fpt = a, ae = e, fa_adjusted = y, fs = mr)")/_xll.BQL(Inputs!$Q25, "EARN_FOR_COMMON(fpr = 2025, fpt = a, ae = e, fa_adjusted = y, fs = mr)"))^(1/3)-1 -> 0.059547645
B45: Mean | I45: =AVERAGE(I39:I43) -> 4.2103953 | J45: =AVERAGE(J39:J43) -> 4.2289167 | K45: =AVERAGE(K39:K43) -> 4.059066 | L45: =AVERAGE(L39:L43) -> 15.377072 | M45: =AVERAGE(M39:M43) -> 16.099334 | N45: =AVERAGE(N39:N43) -> 15.381589 | O45: =AVERAGE(O39:O43) -> 17.62227 | P45: =AVERAGE(P39:P43) -> 18.696762 | Q45: =AVERAGE(Q39:Q43) -> 17.715069 | S45: =AVERAGE(S39:S43) -> 0.26522385 | T45: =AVERAGE(T39:T43) -> 2.4741258 | V45: =AVERAGE(V39:V43) -> 18.814286 | W45: =AVERAGE(W39:W43) -> 19.978966 | X45: =AVERAGE(X39:X43) -> 19.033578 | Z45: =AVERAGE(Z39:Z43) -> 0.05328388
B46: Median | I46: =MEDIAN(I39:I43) -> 4.0585695 | J46: =MEDIAN(J39:J43) -> 3.9890827 | K46: =MEDIAN(K39:K43) -> 3.844395 | L46: =MEDIAN(L39:L43) -> 15.929448 | M46: =MEDIAN(M39:M43) -> 16.274037 | N46: =MEDIAN(N39:N43) -> 15.558149 | O46: =MEDIAN(O39:O43) -> 18.190706 | P46: =MEDIAN(P39:P43) -> 18.520727 | Q46: =MEDIAN(Q39:Q43) -> 17.63562 | S46: =MEDIAN(S39:S43) -> 0.25710957 | T46: =MEDIAN(T39:T43) -> 1.8514446 | V46: =MEDIAN(V39:V43) -> 20.828126 | W46: =MEDIAN(W39:W43) -> 21.289413 | X46: =MEDIAN(X39:X43) -> 20.214602 | Z46: =MEDIAN(Z39:Z43) -> 0.050721743
B48: Overall
B51: Mean | I51: =AVERAGE(I39:I43,I27:I32,I15:I19) -> 2.583985 | J51: =AVERAGE(J39:J43,J27:J32,J15:J19) -> 2.5655035 | K51: =AVERAGE(K39:K43,K27:K32,K15:K19) -> 2.4757658 | L51: =AVERAGE(L39:L43,L27:L32,L15:L19) -> 12.484422 | M51: =AVERAGE(M39:M43,M27:M32,M15:M19) -> 12.416239 | N51: =AVERAGE(N39:N43,N27:N32,N15:N19) -> 12.173374 | O51: =AVERAGE(O39:O43,O27:O32,O15:O19) -> 15.578217 | P51: =AVERAGE(P39:P43,P27:P32,P15:P19) -> 15.5901 | Q51: =AVERAGE(Q39:Q43,Q27:Q32,Q15:Q19) -> 15.347932 | S51: =AVERAGE(S39:S43,S27:S32,S15:S19) -> 0.19394155 | T51: =AVERAGE(T39:T43,T27:T32,T15:T19) -> 2.9301318 | V51: =AVERAGE(V39:V43,V27:V32,V15:V19) -> 17.003796 | W51: =AVERAGE(W39:W43,W27:W32,W15:W19) -> 16.795105 | X51: =AVERAGE(X39:X43,X27:X32,X15:X19) -> 16.567307 | Z51: =AVERAGE(Z39:Z43,Z27:Z32,Z15:Z19) -> 0.049379012
B52: Median | I52: =MEDIAN(I39:I43,I27:I31,I15:I19) -> 2.4269451 | J52: =MEDIAN(J39:J43,J27:J31,J15:J19) -> 2.0666918 | K52: =MEDIAN(K39:K43,K27:K31,K15:K19) -> 2.1677389 | L52: =MEDIAN(L39:L43,L27:L31,L15:L19) -> 12.224795 | M52: =MEDIAN(M39:M43,M27:M31,M15:M19) -> 12.388636 | N52: =MEDIAN(N39:N43,N27:N31,N15:N19) -> 11.798411 | O52: =MEDIAN(O39:O43,O27:O31,O15:O19) -> 15.759 | P52: =MEDIAN(P39:P43,P27:P31,P15:P19) -> 15.169674 | Q52: =MEDIAN(Q39:Q43,Q27:Q31,Q15:Q19) -> 15.567277 | S52: =MEDIAN(S39:S43,S27:S31,S15:S19) -> 0.1897698 | T52: =MEDIAN(T39:T43,T27:T31,T15:T19) -> 3.2558149 | V52: =MEDIAN(V39:V43,V27:V31,V15:V19) -> 16.869825 | W52: =MEDIAN(W39:W43,W27:W31,W15:W19) -> 17.288533 | X52: =MEDIAN(X39:X43,X27:X31,X15:X19) -> 16.528123 | Z52: =MEDIAN(Z39:Z43,Z27:Z31,Z15:Z19) -> 0.050721743
B54: High | I54: =MAX(I39:I43,I27:I31,I15:I19) -> 7.1937931 | J54: =MAX(J39:J43,J27:J31,J15:J19) -> 7.0164315 | K54: =MAX(K39:K43,K27:K31,K15:K19) -> 6.6436302 | L54: =MAX(L39:L43,L27:L31,L15:L19) -> 21.619896 | M54: =MAX(M39:M43,M27:M31,M15:M19) -> 20.887229 | N54: =MAX(N39:N43,N27:N31,N15:N19) -> 19.5671 | O54: =MAX(O39:O43,O27:O31,O15:O19) -> 23.382993 | P54: =MAX(P39:P43,P27:P31,P15:P19) -> 22.439171 | ... T54: =MAX(T39:T43,T27:T31,T15:T19) -> 5.5488256 | V54: =MAX(V39:V43,V27:V31,V15:V19) -> 35.403004 | W54: =MAX(W39:W43,W27:W31,W15:W19) -> 28.721716 | X54: =MAX(X39:X43,X27:X31,X15:X19) -> 24.538533 | Z54: =MAX(Z39:Z43,Z27:Z31,Z15:Z19) -> 0.19595369
B55: Low | I55: =MIN(I39:I43,I27:I31,I15:I19) -> 0.52165331 | J55: =MIN(J39:J43,J27:J31,J15:J19) -> 0.51578395 | K55: =MIN(K39:K43,K27:K31,K15:K19) -> 0.50695244 | L55: =MIN(L39:L43,L27:L31,L15:L19) -> 5.8614561 | M55: =MIN(M39:M43,M27:M31,M15:M19) -> 6.246513 | N55: =MIN(N39:N43,N27:N31,N15:N19) -> 7.2004256 | O55: =MIN(O39:O43,O27:O31,O15:O19) -> 7.1552061 | P55: =MIN(P39:P43,P27:P31,P15:P19) -> 7.8773281 | ... T55: =MIN(T39:T43,T27:T31,T15:T19) -> 0.19953938 | V55: =MIN(V39:V43,V27:V31,V15:V19) -> 6.7494944 | W55: =MIN(W39:W43,W27:W31,W15:W19) -> 7.4746591 | X55: =MIN(X39:X43,X27:X31,X15:X19) -> 8.9169961 | Z55: =MIN(Z39:Z43,Z27:Z31,Z15:Z19) -> -0.13383241

Sheet WACC
A7: x | B7: Rolling WACC | K7: Equity Risk Premium
P8: Weights
D9: 2025 | E9: =+D9+1 -> 2026 | F9: =+E9+1 -> 2027 | G9: =+F9+1 -> 2028 | H9: =+G9+1 -> 2029 | M9: ERP | N9: 2025 | O9: =+N9+1 -> 2026 | P9: =+O9+1 -> 2027 | Q9: =+P9+1 -> 2028 | R9: =+Q9+1 -> 2029
B12: Equity: | K12: =+Segments!B20 -> USA | N12: =+Segments!AL20/Segments!AL$21 -> 0 | O12: =+Segments!AN20/Segments!AN$21 -> 0 | P12: =+Segments!AP20/Segments!AP$21 -> 0 | Q12: =+Segments!AR20/Segments!AR$21 -> 0 | R12: =+Segments!AT20/Segments!AT$21 -> 0
B13: Market Cap (in billions) | D13: =+Inputs!J13 -> 5409408.6 | E13: =+FCFF!AF99*FCFF!AF31 -> 29313730 | F13: =+FCFF!AH99*FCFF!AH31 -> 12819408 | G13: =+FCFF!AJ99*FCFF!AJ31 -> 19345373 | H13: =+FCFF!AL99*FCFF!AL31 -> 29193509 | K13: =+Segments!#REF! -> #REF! | N13: =+Segments!#REF!/Segments!AL$21 -> #REF! | O13: =+Segments!#REF!/Segments!AN$21 -> #REF! | P13: =+Segments!#REF!/Segments!AP$21 -> #REF! | Q13: =+Segments!#REF!/Segments!AR$21 -> #REF! | R13: =+Segments!#REF!/Segments!AT$21 -> #REF!
B14: % of Equity | D14: =IFERROR(D13/D35,"") -> 1 | E14: =IFERROR(E13/E35,"") -> 1 | F14: =IFERROR(E13/F35,"") -> 2.286668 | G14: =IFERROR(F13/G35,"") -> 0.66266017 | H14: =IFERROR(G13/H35,"") -> 0.66266008 | K14: =+Segments!#REF! -> #REF! | N14: =+Segments!#REF!/Segments!AL$21 -> #REF! | O14: =+Segments!#REF!/Segments!AN$21 -> #REF! | P14: =+Segments!#REF!/Segments!AP$21 -> #REF! | Q14: =+Segments!#REF!/Segments!AR$21 -> #REF! | R14: =+Segments!#REF!/Segments!AT$21 -> #REF!
B15: Risk-Free Rate | K15: =+Segments!#REF! -> #REF! | N15: =+Segments!#REF!/Segments!AL$21 -> #REF! | O15: =+Segments!#REF!/Segments!AN$21 -> #REF! | P15: =+Segments!#REF!/Segments!AP$21 -> #REF! | Q15: =+Segments!#REF!/Segments!AR$21 -> #REF! | R15: =+Segments!#REF!/Segments!AT$21 -> #REF!
B16: Beta | D16: =+Inputs!M18 -> 0.70151639 | E16: =+D17*(1+(E28/E13)*(1-E32)) -> 0.70151639 | F16: =+E17*(1+(F28/F13)*(1-F32)) -> 0.70151639 | G16: =+F17*(1+(G28/G13)*(1-G32)) -> 0.70151639 | H16: =+G17*(1+(H28/H13)*(1-H32)) -> 0.70151639 | K16: =+Segments!#REF! -> #REF! | N16: =+Segments!#REF!/Segments!AL$21 -> #REF! | O16: =+Segments!#REF!/Segments!AN$21 -> #REF! | P16: =+Segments!#REF!/Segments!AP$21 -> #REF! | Q16: =+Segments!#REF!/Segments!AR$21 -> #REF! | R16: =+Segments!#REF!/Segments!AT$21 -> #REF!
B17: Unlevered Beta | D17: =+D16/(1+(D28/D13)*(1-D32)) -> 0.70151639 | E17: =+E16/(1+(E28/E13)*(1-E32)) -> 0.70151639 | F17: =+F16/(1+(F28/F13)*(1-F32)) -> 0.70151639 | G17: =+G16/(1+(G28/G13)*(1-G32)) -> 0.70151639 | H17: =+H16/(1+(H28/H13)*(1-H32)) -> 0.70151639
B18: Equity Risk Premium | D18: =+N18 -> #REF! | E18: =+O18 -> #REF! | F18: =+P18 -> #REF! | G18: =+Q18 -> #REF! | H18: =+R18 -> #REF! | K18: ERP | N18: =+SUMPRODUCT($M12:$M16,N12:N16) -> #REF! | O18: =+SUMPRODUCT($M12:$M16,O12:O16) -> #REF! | P18: =+SUMPRODUCT($M12:$M16,P12:P16) -> #REF! | Q18: =+SUMPRODUCT($M12:$M16,Q12:Q16) -> #REF! | R18: =+SUMPRODUCT($M12:$M16,R12:R16) -> #REF!
B19: Ke (Cost of Equity) | D19: =IFERROR(+D15+D16*D18,"") | E19: =IFERROR(+E15+E16*E18,"") | F19: =IFERROR(+F15+F16*F18,"") | G19: =IFERROR(+G15+G16*G18,"") | H19: =IFERROR(+H15+H16*H18,"")
B21: Preferred Equity: | K21: ROIC vs WACC
B22: Market Capitalization | D22: =IFERROR(Inputs!J14,0) -> 0 | E22: =+D22*(E13/D13) -> 0 | F22: =+E22*(F13/E13) -> 0 | G22: =+F22*(G13/F13) -> 0 | H22: =+G22*(H13/G13) -> 0
B23: % of Preferred Equity | D23: =+D22/D35 -> 0 | E23: =+E22/E35 -> 0 | F23: =+F22/F35 -> 0 | G23: =+G22/G35 -> 0 | H23: =+H22/H35 -> 0
B24: Preferred Dividends | D24: =+IS!AF50 -> 0 | E24: =D24 -> 0 | F24: =E24 -> 0 | G24: =F24 -> 0 | H24: =G24 -> 0
B25: Kp (Cost of Preferred Equity) | D25: =IFERROR(D24/D22,0) -> 0 | E25: =IFERROR(E24/E22,0) -> 0 | F25: =IFERROR(F24/F22,0) -> 0 | G25: =IFERROR(G24/G22,0) -> 0 | H25: =IFERROR(H24/H22,0) -> 0
B27: Debt:
B28: Debt (in millions) | C28: =+BS!AF38+BS!AF39+BS!AF44+BS!AF45 -> 0 | D28: =+BS!AI38+BS!AI39+BS!AI44+BS!AI45 -> 0
B29: % of Debt | D29: =IFERROR(D28/D35,"") -> 0 | E29: =IFERROR(E28/E35,"") -> 0 | F29: =IFERROR(F28/F35,"") -> 0 | G29: =IFERROR(G28/G35,"") -> 0 | H29: =IFERROR(H28/H35,"") -> 0
B30: Debt Spread | D30: =+D31-D15 -> #DIV/0!
B31: Cost of Debt | D31: =+IS!AI39/WACC!D28 -> #DIV/0! | E31: =+E30+E15 -> 0 | F31: =+F30+F15 -> 0 | G31: =+G30+G15 -> 0 | H31: =+H30+H15 -> 0
B32: Tax Rate | D32: =+FCFF!Z124 -> 0.27263068 | E32: =+FCFF!AF124 -> 0.26425 | F32: =+FCFF!AH124 -> 0.264 | G32: =+FCFF!AJ124 -> 0.264 | H32: =+FCFF!AL124 -> 0.264
B33: Kd (After-Tax Cost of Debt) | D33: =+D31*(1-D32) -> #DIV/0! | E33: =+E31*(1-E32) -> 0 | F33: =+F31*(1-F32) -> 0 | G33: =+G31*(1-G32) -> 0 | H33: =+H31*(1-H32) -> 0
B35: Total | D35: =+D13+D24+D28 -> 5409408.6 | E35: =+E13+E24+E28 -> 29313730 | F35: =+F13+F24+F28 -> 12819408 | G35: =+G13+G24+G28 -> 19345373 | H35: =+H13+H24+H28 -> 29193509
B37: Country/Conglomerate/... Risk Premium | D37: 0.01 | E37: 0 | F37: 0 | G37: 0 | H37: 0
A39: x | B39: WACC | D39: =+D19*D14+D25*D23+D33*D29+D37 -> #VALUE! | E39: =+E19*E14+E25*E23+E33*E29+E37 -> #VALUE! | F39: =+F19*F14+F25*F23+F33*F29+F37 -> #VALUE! | G39: =+G19*G14+G25*G23+G33*G29+G37 -> #VALUE! | H39: =+H19*H14+H25*H23+H33*H29+H37 -> #VALUE!
B41: NOPAT | D41: =+FCFF!Z126 -> 756542.78 | E41: =+FCFF!AF126 -> 1320223.6 | F41: =+FCFF!AH126 -> 664583.75 | G41: =+FCFF!AJ126 -> 1124520.7 | H41: =+FCFF!AL126 -> 1880062
B42: Total Payout | D42: =+FCFF!Z112+FCFF!Z115 -> -225405.13 | E42: =+FCFF!AF112+FCFF!AF115 -> -475782.99 | F42: =+FCFF!AH112+FCFF!AH115 -> -280541.34 | G42: =+FCFF!AJ112+FCFF!AJ115 -> -540943.47 | H42: =+FCFF!AL112+FCFF!AL115 -> -1017132.5
B43: Book Value of Equity | C43: =+BS!AF54 -> 1797043 | D43: =+C43+D41+D42 -> 2328180.6 | E43: =+D43+E41+E42 -> 3172621.2 | F43: =+E43+F41+F42 -> 3556663.6 | G43: =+F43+G41+G42 -> 4140240.9 | H43: =+G43+H41+H42 -> 5003170.3
B44: Invested Capital | C44: =+C43+C28 -> 1797043 | D44: =+D43+D28 -> 2328180.6 | E44: =+E43+E28 -> 3172621.2 | F44: =+F43+F28 -> 3556663.6 | G44: =+G43+G28 -> 4140240.9 | H44: =+H43+H28 -> 5003170.3
A45: x | B45: ROIC | D45: =+D41/((D44+C44)/2) -> 0.36678873 | E45: =+E41/((E44+D44)/2) -> 0.48001131 | F45: =+F41/((F44+E44)/2) -> 0.19751988 | G45: =+G41/((G44+F44)/2) -> 0.29220077 | H45: =+H41/((H44+G44)/2) -> 0.41123863
W49: ,

Sheet FCFF
A7: x | B7: Market Assumptions
D8: 2022 | J8: =D8+1 -> 2023 | P8: =J8+1 -> 2024 | V8: =P8+1 -> 2025 | AB8: =V8+1 -> 2026 | AH8: =AB8+1 -> 2027 | AJ8: =+AH8+1 -> 2028 | AL8: =+AJ8+1 -> 2029
D9: Q1 | E9: Q2 | F9: Q3 | G9: Q4 | H9: FY | J9: Q1 | K9: Q2 | L9: Q3 | M9: Q4 | N9: FY | P9: Q1 | Q9: Q2 | R9: Q3 | S9: Q4 | T9: FY | V9: Q1 | W9: Q2 | X9: Q3 | Y9: Q4 | Z9: FY | AB9: Q1 | AC9: Q2 | AD9: Q3 | AE9: Q4 | AF9: FY | AH9: FY | AJ9: FY | AL9: FY
B10: Segments Assumptions
B11: Shell Eggs Revenue ($M) | D11: =0.8*D21 -> 265363.2 | E11: =0.8*E21 -> 305378.4 | F11: =0.8*F21 -> 381988 | G11: =0.8*G21 -> 474371.2 | H11: =SUM(D11:G11) -> 1427100.8 | J11: =J21*0.8 -> 526675.2 | K11: =K21*0.8 -> 641360 | L11: =L21*0.8 -> 797994.4 | M11: =M21*0.8 -> 550944 | N11: =SUM(J11:M11) -> 2516973.6 | P11: =P21*0.8 -> 367475.2 | Q11: =Q21*0.8 -> 418587.2 | R11: =R21*0.8 -> 562460.8 | S11: =S21*0.8 -> 512631.2 | T11: =SUM(P11:S11) -> 1861154.4 | V11: =0.8*V21 -> 628696.8 | W11: =0.8*W21 -> 763736.8 | X11: =0.8*X21 -> 864088.8 | Y11: =0.8*Y21 -> 938206.4 | Z11: =SUM(V11:Y11) -> 3194728.8 | AB11: =0.8*AB31 -> 1039861.6 | AC11: =0.8*AC31 -> 1152532 | AD11: =0.8*AD31 -> 1277409.6 | AE11: =0.8*AE31 -> 1415818.4 | AF11: =SUM(AB11:AE11) -> 4885621.6 | AH11: =0.8*AH21 -> 2136568 | AJ11: =0.8*AJ21 -> 3224228.8 | AL11: =0.8*AL21 -> 4865584.8
B12: Processed Eggs Revenue ($M) | D12: =0.1*D21 -> 33170.4 | E12: =0.1*E21 -> 38172.3 | F12: =0.1*F21 -> 47748.5 | G12: =0.1*G21 -> 59296.4 | H12: =SUM(D12:G12) -> 178387.6 | J12: =J21*0.1 -> 65834.4 | K12: =K21*0.1 -> 80170 | L12: =L21*0.1 -> 99749.3 | M12: =M21*0.1 -> 68868 | N12: =SUM(J12:M12) -> 314621.7 | P12: =P21*0.1 -> 45934.4 | Q12: =Q21*0.1 -> 52323.4 | R12: =R21*0.1 -> 70307.6 | S12: =S21*0.1 -> 64078.9 | T12: =SUM(P12:S12) -> 232644.3 | V12: =0.1*V21 -> 78587.1 | W12: =0.1*W21 -> 95467.1 | X12: =0.1*X21 -> 108011.1 | Y12: =0.1*Y21 -> 117275.8 | Z12: =SUM(V12:Y12) -> 399341.1 | AB12: =0.1*AB31 -> 129982.7 | AC12: =0.1*AC31 -> 144066.5 | AD12: =0.1*AD31 -> 159676.2 | AE12: =0.1*AE31 -> 176977.3 | AF12: =SUM(AB12:AE12) -> 610702.7 | AH12: =0.1*AH21 -> 267071 | AJ12: =0.1*AJ21 -> 403028.6 | AL12: =0.1*AL21 -> 608198.1
B13: Retail Revenue ($M) | D13: =0.07*D21 -> 23219.28 | E13: =0.07*E21 -> 26720.61 | F13: =0.07*F21 -> 33423.95 | G13: =0.07*G21 -> 41507.48 | H13: =SUM(D13:G13) -> 124871.32 | J13: =0.07*J21 -> 46084.08 | K13: =0.07*K21 -> 56119 | L13: =0.07*L21 -> 69824.51 | M13: =0.07*M21 -> 48207.6 | N13: =SUM(J13:M13) -> 220235.19 | P13: =P21*0.07 -> 32154.08 | Q13: =Q21*0.07 -> 36626.38 | R13: =R21*0.07 -> 49215.32 | S13: =S21*0.07 -> 44855.23 | T13: =SUM(P13:S13) -> 162851.01 | V13: =0.07*V21 -> 55010.97 | W13: =0.07*W21 -> 66826.97 | X13: =0.07*X21 -> 75607.77 | Y13: =0.07*Y21 -> 82093.06 | Z13: =SUM(V13:Y13) -> 279538.77 | AB13: =0.07*AB31 -> 90987.89 | AC13: =0.07*AC31 -> 100846.55 | AD13: =0.07*AD31 -> 111773.34 | AE13: =0.07*AE31 -> 123884.11 | AF13: =SUM(AB13:AE13) -> 427491.89 | AH13: =0.07*AH31 -> 186949.7 | AJ13: =0.07*AJ31 -> 282120.02 | AL13: =0.07*AL31 -> 425738.67
B14: Foodservice ($M) | D14: =0.03*D21 -> 9951.12 | E14: =0.03*E21 -> 11451.69 | F14: =0.03*F21 -> 14324.55 | G14: =0.03*G21 -> 17788.92 | H14: =SUM(D14:G14) -> 53516.28 | J14: =0.03*J21 -> 19750.32 | K14: =0.03*K21 -> 24051 | L14: =0.03*L21 -> 29924.79 | M14: =0.03*M21 -> 20660.4 | N14: =SUM(J14:M14) -> 94386.51 | P14: =P21*0.03 -> 13780.32 | Q14: =Q21*0.03 -> 15697.02 | R14: =R21*0.03 -> 21092.28 | S14: =S21*0.03 -> 19223.67 | T14: =SUM(P14:S14) -> 69793.29 | V14: =0.03*V21 -> 23576.13 | W14: =0.03*W21 -> 28640.13 | X14: =0.03*X21 -> 32403.33 | Y14: =0.03*Y21 -> 35182.74 | Z14: =SUM(V14:Y14) -> 119802.33 | AB14: =0.03*AB31 -> 38994.81 | AC14: =0.03*AC31 -> 43219.95 | AD14: =0.03*AD31 -> 47902.86 | AE14: =0.03*AE31 -> 53093.19 | AF14: =SUM(AB14:AE14) -> 183210.81 | AH14: =0.03*AH31 -> 80121.3 | AJ14: =0.03*AJ31 -> 120908.58 | AL14: =0.03*AL31 -> 182459.43
B15: Average Price per Dozen ($) | D15: 3.31 | E15: =D15+0.01 -> 3.32 | F15: =E15+0.01 -> 3.33 | G15: =F15+0.01 -> 3.34 | H15: =AVERAGE(D15:G15) -> 3.325 | J15: 3 | K15: 3 | L15: 3 | M15: 3 | N15: 3 | P15: 1.241 | Q15: =1.73 -> 1.73 | R15: =Q15+0.01 -> 1.74 | S15: =2.13 -> 2.13 | T15: =AVERAGE(P15:S15) -> 1.71025 | V15: 2.5 | W15: 2.74 | X15: =W15+0.01 -> 2.75 | Y15: =X15+0.01 -> 2.76 | Z15: =AVERAGE(V15:Y15) -> 2.6875 | AB15: 3.47 | AC15: =AB15+0.01 -> 3.48 | AD15: =AC15+0.01 -> 3.49 | AE15: =AD15+0.01 -> 3.5 | AF15: =AVERAGE(AB15:AE15) -> 3.485 | AH15: 3.5 | AJ15: 3.52 | AL15: 3.53 | AS15: 2022 | AT15: =+AS15+1 -> 2023 | AU15: =+AT15+1 -> 2024 | AV15: =+AU15+1 -> 2025 | AW15: =+AV15+1 -> 2026 | AX15: =+AW15+1 -> 2027 | AY15: =+AX15+1 -> 2028 | AZ15: =+AY15+1 -> 2029
B16: Volumen Sold (million dozen) | D16: =D21/D15 -> 100212.69 | E16: =E21/E15 -> 114976.81 | F16: =F21/F15 -> 143388.89 | G16: =G21/G15 -> 177534.13 | H16: =SUM(D16:G16) -> 536112.52 | J16: =J21/J15 -> 219448 | K16: =K21/K15 -> 267233.33 | L16: =L21/L15 -> 332497.67 | M16: =M21/M15 -> 229560 | N16: =SUM(J16:M16) -> 1048739 | P16: =P21/P15 -> 370140.21 | Q16: =Q21/Q15 -> 302447.4 | R16: =R21/R15 -> 404066.67 | S16: =S21/S15 -> 300839.91 | T16: =SUM(P16:S16) -> 1377494.2 | V16: =V21/V15 -> 314348.4 | W16: =W21/W15 -> 348420.07 | X16: =X21/X15 -> 392767.64 | Y16: =Y21/Y15 -> 424912.32 | Z16: =Z21/Z15 -> 1485920.4 | AB16: =AB21/AB15 -> 374589.91 | AC16: =AC21/AC15 -> 413984.2 | AD16: =AD21/AD15 -> 457524.93 | AE16: =AE21/AE15 -> 505649.43 | AF16: =SUM(AB16:AE16) -> 1751748.5 | AH16: =AH21/AH15 -> 763060 | AJ16: =AJ21/AJ15 -> 1144967.6 | AL16: =AL21/AL15 -> 1722940.8 | AR16: EBITDA | AS16: =H61+H128 -> 206823 | AT16: =N61+N128 -> 1036484 | AU16: =T61+T128 -> 369187 | AV16: =Z61+Z128 -> 1092074.3 | AW16: =AF61+AF128 -> 1806517.1 | AX16: =AH61+AH128 -> 902967.05 | AY16: =AJ61+AJ128 -> 1527881.4 | AZ16: =AL61+AL128 -> 2554432
AR17: FCFF | AS17: =H136 -> 39775.18 | AT17: =N136 -> 678007.88 | AU17: =T136 -> 261220.52 | AV17: =Z136 -> 603404.83 | AW17: =AF136 -> 852341.64 | AX17: =AH136 -> 720299.52 | AY17: =AJ136 -> 805391.58 | AZ17: =AL136 -> 1406181.6
AR18: Revenue Growth | AS18: =H32 -> 0.31740261 | AT18: =N32 -> 0.77036326 | AU18: =T32 -> -0.26055863 | AV18: =Z32 -> 0.71653077 | AW18: =AF32 -> 0.52927585 | AX18: =AH32 -> -0.56268246 | AY18: =+AJ32 -> 0.50906912 | AZ18: =+AL32 -> 0.50906933
B21: Revenue | D21: =D31 -> 331704 | E21: =E31 -> 381723 | F21: =F31 -> 477485 | G21: =G31 -> 592964 | H21: =H31 -> 1777159 | J21: =J31 -> 658344 | K21: =K31 -> 801700 | L21: =L31 -> 997493 | M21: =M31 -> 688680 | N21: =N31 -> 3146217 | P21: =P31 -> 459344 | Q21: =Q31 -> 523234 | R21: =R31 -> 703076 | S21: =S31 -> 640789 | T21: =T31 -> 2326443 | V21: 785871 | W21: =W31 -> 954671 | X21: =1080111 -> 1080111 | Y21: 1172758 | Z21: =Z31 -> 3993411 | AB21: 1299827 | AC21: 1440665 | AD21: 1596762 | AE21: =1769773 -> 1769773 | AF21: =AF31 -> 6107027 | AH21: 2670710 | AJ21: 4030286 | AL21: 6081981
A23: x | B23: Operating Assumptions
D24: =D$8 -> 2022 | E24: =F24 -> 0 | F24: =F$8 -> 0 | G24: =F24 -> 0 | H24: =F24 -> 0 | J24: =J$8 -> 2023 | K24: =L24 -> 0 | L24: =L$8 -> 0 | M24: =L24 -> 0 | N24: =L24 -> 0 | P24: =P$8 -> 2024 | Q24: =R24 -> 0 | R24: =R$8 -> 0 | S24: =R24 -> 0 | T24: =R24 -> 0 | V24: =V$8 -> 2025 | W24: =X24 -> 0 | X24: =X$8 -> 0 | Y24: =X24 -> 0 | Z24: =X24 -> 0 | AB24: =AB$8 -> 2026 | AC24: =AD24 -> 0 | AD24: =AD$8 -> 0 | AE24: =AD24 -> 0 | AF24: =AD24 -> 0 | AH24: =AH$8 -> 2027 | AJ24: =AJ$8 -> 2028 | AL24: =AL$8 -> 2029 | AM24: =AN24 -> 0
D25: Q1 | E25: Q2 | F25: Q3 | G25: Q4 | H25: FY | J25: Q1 | K25: Q2 | L25: Q3 | M25: Q4 | N25: FY | P25: Q1 | Q25: Q2 | R25: Q3 | S25: Q4 | T25: FY | V25: Q1 | W25: Q2 | X25: Q3 | Y25: Q4 | Z25: FY | AB25: Q1 | AC25: Q2 | AD25: Q3 | AE25: Q4 | AF25: FY | AH25: FY | AJ25: FY | AL25: FY
B28: Income Statement
B31: Revenue | D31: =IS!P18 -> 331704 | E31: =IS!Q18 -> 381723 | F31: =IS!R18 -> 477485 | G31: =IS!S18 -> 592964 | H31: =IS!T18 -> 1777159 | J31: =IS!V18 -> 658344 | K31: =IS!W18 -> 801700 | L31: =IS!X18 -> 997493 | M31: =IS!Y18 -> 688680 | N31: =IS!Z18 -> 3146217 | P31: =IS!AB18 -> 459344 | Q31: =IS!AC18 -> 523234 | R31: =IS!AD18 -> 703076 | S31: =IS!AE18 -> 640789 | T31: =IS!AF18 -> 2326443 | V31: =IS!AH18 -> 785871 | W31: =IS!AI18 -> 954671 | X31: =X21 -> 1080111 | Y31: =Y21 -> 1172758 | Z31: =SUM(V31:Y31) -> 3993411 | AB31: =AB21 -> 1299827 | AC31: =AC21 -> 1440665 | AD31: =AD21 -> 1596762 | AE31: =AE21 -> 1769773 | AF31: =SUM(AB31:AE31) -> 6107027 | AH31: =AH21 -> 2670710 | AJ31: =AJ21 -> 4030286 | AL31: =AL21 -> 6081981
B32: % of growth | D32: =D31/IS!J18-1 -> 0.1329385 | E32: =E31/IS!K18-1 -> 0.099027432 | F32: =F31/IS!L18-1 -> 0.32974546 | G32: =G31/IS!M18-1 -> 0.69516121 | H32: =H31/IS!N18-1 -> 0.31740261 | J32: =J31/IS!P18-1 -> 0.98473338 | K32: =K31/IS!Q18-1 -> 1.100214 | L32: =L31/IS!R18-1 -> 1.0890562 | M32: =M31/IS!S18-1 -> 0.16141958 | N32: =N31/H31-1 -> 0.77036326 | P32: =P31/IS!V18-1 -> -0.30227358 | Q32: =Q31/IS!W18-1 -> -0.34734439 | R32: =R31/IS!X18-1 -> -0.29515696 | S32: =S31/IS!Y18-1 -> -0.06954028 | T32: =T31/N31-1 -> -0.26055863 | V32: =V31/IS!AB18-1 -> 0.71085505 | W32: =W31/IS!AC18-1 -> 0.82455842 | X32: =X31/IS!AD18-1 -> 0.53626493 | Y32: =Y31/IS!AE18-1 -> 0.83017811 | Z32: =Z31/T31-1 -> 0.71653077 | AB32: =AB31/IS!AH18-1 -> 0.65399538 | AC32: =AC31/IS!AI18-1 -> 0.50906962 | AD32: =AD31/IS!AJ18-1 -> 62.87048 | AE32: =AE31/IS!AK18-1 -> 69.79092 | AF32: =AF31/Z31-1 -> 0.52927585 | AH32: =AH31/AF31-1 -> -0.56268246 | AJ32: =AJ31/AH31-1 -> 0.50906912 | AL32: =AL31/AJ31-1 -> 0.50906933
B34: Cost of Goods & Services | D34: =IS!P21 -> 325059 | E34: =IS!Q21 -> 337976 | F34: =IS!R21 -> 385903 | G34: =IS!S21 -> 397879 | H34: =IS!T21 -> 1440100 | J34: =IS!V21 -> 440854 | K34: =IS!W21 -> 483851 | L34: =IS!X21 -> 534467 | M34: =IS!Y21 -> 490588 | N34: =IS!Z21 -> 1949760 | P34: =IS!AB21 -> 413911 | Q34: =IS!AC21 -> 432104 | R34: =IS!AD21 -> 484504 | S34: =IS!AE21 -> 454353 | T34: =IS!AF21 -> 1784872 | V34: =IS!AH21 -> 538653 | W34: =IS!AI21 -> 598629 | X34: =(X35+Sensitivity!$U$39)*X$31 -> 682954.19 | Y34: =(Y35+Sensitivity!$U$39)*Y$31 -> 799586.4 | Z34: =SUM(V34:Y34) -> 2619822.6 | AB34: =(AB35+Sensitivity!$U$39)*AB$31 -> 767937.79 | AC34: =(AC35+Sensitivity!$U$39)*AC$31 -> 946805.04 | AD34: =(AD35+Sensitivity!$U$39)*AD$31 -> 953107.24 | AE34: =(AE35+Sensitivity!$U$39)*AE$31 -> 1143096.4 | AF34: =SUM(AB34:AE34) -> 3810946.4 | AH34: =(AH35+Sensitivity!$U$39)*AH$31 -> 1568240.9 | AJ34: =(AJ35+Sensitivity!$U$39)*AJ$31 -> 2223508.8 | AL34: =(AL35+Sensitivity!$U$39)*AL$31 -> 3140126.8
B35: % of sales | D35: =D34/D31 -> 0.97996708 | E35: =E34/E31 -> 0.88539595 | F35: =F34/F31 -> 0.80819921 | G35: =G34/G31 -> 0.67100026 | H35: =H34/H31 -> 0.8103383 | J35: =J34/J31 -> 0.6696408 | K35: =K34/K31 -> 0.60353125 | L35: =L34/L31 -> 0.53581028 | M35: =M34/M31 -> 0.71235988 | N35: =N34/N31 -> 0.61971568 | P35: =P34/P31 -> 0.90109156 | Q35: =Q34/Q31 -> 0.82583318 | R35: =R34/R31 -> 0.68912038 | S35: =S34/S31 -> 0.70905243 | T35: =T34/T31 -> 0.76721072 | V35: =V34/V31 -> 0.68542165 | W35: =W34/W31 -> 0.62705267 | X35: 0.6323 | Y35: 0.6818 | Z35: =Z34/Z31 -> 0.6560363 | AB35: 0.5908 | AC35: 0.6572 | AD35: 0.5969 | AE35: 0.6459 | AF35: =AF34/AF31 -> 0.62402646 | AH35: 0.5872 | AJ35: 0.5517 | AL35: 0.5163
B37: COGS Depreciation & Amortization | D37: =IS!P22 -> 19340 | E37: =IS!Q22 -> 20054 | F37: =IS!R22 -> 19757 | G37: =IS!S22 -> 21090 | H37: =IS!T22 -> 80241 | J37: =IS!V22 -> 22048 | K37: =IS!W22 -> 23770 | L37: =IS!X22 -> 0 | M37: =IS!Y22 -> 0 | N37: =IS!Z22 -> 45818 | P37: =IS!AB22 -> 0 | Q37: =IS!AC22 -> 0 | R37: =IS!AD22 -> 0 | S37: =IS!AE22 -> 0 | T37: =IS!AF22 -> 0 | V37: =IS!AH22 -> 0 | W37: =IS!AI22 -> 0 | X37: =X38*X34 -> 0 | Y37: =Y38*Y34 -> 0 | Z37: =SUM(V37:Y37) -> 0 | AB37: =AB38*AB34 -> 0 | AC37: =AC38*AC34 -> 0 | AD37: =AD38*AD34 -> 0 | AE37: =AE38*AE34 -> 0 | AF37: =SUM(AB37:AE37) -> 0 | AH37: =AH38*AH34 -> 0 | AJ37: =AJ38*AJ34 -> 0 | AL37: =AL38*AL34 -> 0
B38: % of cost of goods & services | D38: =D37/D34 -> 0.059496891 | E38: =E37/E34 -> 0.059335574 | F38: =F37/F34 -> 0.051196803 | G38: =G37/G34 -> 0.053006065 | H38: =H37/H34 -> 0.055719047 | J38: =J37/J34 -> 0.050012022 | K38: =K37/K34 -> 0.049126694 | L38: =L37/L34 -> 0 | M38: =M37/M34 -> 0 | N38: =N37/N34 -> 0.023499302 | P38: =P37/P34 -> 0 | Q38: =Q37/Q34 -> 0 | R38: =R37/R34 -> 0 | S38: =S37/S34 -> 0 | T38: =T37/T34 -> 0 | V38: =V37/V34 -> 0 | W38: =W37/W34 -> 0
B40: Gross Profit | D40: =IS!P24 -> 6645 | E40: =IS!Q24 -> 43747 | F40: =IS!R24 -> 91582 | G40: =IS!S24 -> 195085 | H40: =IS!T24 -> 337059 | J40: =IS!V24 -> 217490 | K40: =IS!W24 -> 317849 | L40: =IS!X24 -> 463026 | M40: =IS!Y24 -> 198092 | N40: =IS!Z24 -> 1196457 | P40: =IS!AB24 -> 45433 | Q40: =IS!AC24 -> 91130 | R40: =IS!AD24 -> 218572 | S40: =IS!AE24 -> 186436 | T40: =IS!AF24 -> 541571 | V40: =IS!AH24 -> 247218 | W40: =IS!AI24 -> 356042 | X40: =X31-X34-X37 -> 397156.81 | Y40: =Y31-Y34-Y37 -> 373171.6 | Z40: =SUM(V40:Y40) -> 1373588.4 | AB40: =AB31-AB34-AB37 -> 531889.21 | AC40: =AC31-AC34-AC37 -> 493859.96 | AD40: =AD31-AD34-AD37 -> 643654.76 | AE40: =AE31-AE34-AE37 -> 626676.62 | AF40: =SUM(AB40:AE40) -> 2296080.6 | AH40: =AH31-AH34-AH37 -> 1102469.1 | AJ40: =AJ31-AJ34-AJ37 -> 1806777.2 | AL40: =AL31-AL34-AL37 -> 2941854.2
B41: % of sales | D41: =D40/D31 -> 0.020032921 | E41: =E40/E31 -> 0.11460405 | F41: =F40/F31 -> 0.19180079 | G41: =G40/G31 -> 0.32899974 | H41: =H40/H31 -> 0.1896617 | J41: =J40/J31 -> 0.3303592 | K41: =K40/K31 -> 0.39646875 | L41: =L40/L31 -> 0.46418972 | M41: =M40/M31 -> 0.28764012 | N41: =N40/N31 -> 0.38028432 | P41: =P40/P31 -> 0.098908443 | Q41: =Q40/Q31 -> 0.17416682 | R41: =R40/R31 -> 0.31087962 | S41: =S40/S31 -> 0.29094757 | T41: =T40/T31 -> 0.23278928 | V41: =V40/V31 -> 0.31457835 | W41: =W40/W31 -> 0.37294733 | X41: =X40/X31 -> 0.3677 | Y41: =Y40/Y31 -> 0.3182 | Z41: =Z40/Z$31 -> 0.3439637 | AB41: =AB40/AB31 -> 0.4092 | AC41: =AC40/AC31 -> 0.3428 | AD41: =AD40/AD31 -> 0.4031 | AE41: =AE40/AE31 -> 0.3541 | AF41: =AF40/AF$31 -> 0.37597354 | AH41: =AH40/AH31 -> 0.4128 | AJ41: =AJ40/AJ31 -> 0.4483 | AL41: =AL40/AL31 -> 0.4837
B43: SG&A (Selling, General & Administrative) | D43: =IS!P27 -> 46525 | E43: =IS!Q27 -> 47780 | F43: =IS!R27 -> 52686 | G43: =IS!S27 -> 51640 | H43: =IS!T27 -> 198631 | J43: =IS!V27 -> 53607 | K43: =IS!W27 -> 57952 | L43: =IS!X27 -> 58489 | M43: =IS!Y27 -> 62159 | N43: =IS!Z27 -> 232207 | P43: =IS!AB27 -> 52246 | Q43: =IS!AC27 -> 76578 | R43: =IS!AD27 -> 66020 | S43: =IS!AE27 -> 57781 | T43: =IS!AF27 -> 252625 | V43: =IS!AH27 -> 61932 | W43: =IS!AI27 -> 77633 | X43: =(X44+Sensitivity!$U$40)*X$31 -> 85004.736 | Y43: =(Y44+Sensitivity!$U$40)*Y$31 -> 102616.32 | Z43: =SUM(V43:Y43) -> 327186.06 | AB43: =(AB44+Sensitivity!$U$40)*AB$31 -> 102686.33 | AC43: =(AC44+Sensitivity!$U$40)*AC$31 -> 125049.72 | AD43: =(AD44+Sensitivity!$U$40)*AD$31 -> 116882.98 | AE43: =(AE44+Sensitivity!$U$40)*AE$31 -> 144944.41 | AF43: =SUM(AB43:AE43) -> 489563.44 | AH43: =(AH44+Sensitivity!$U$40)*AH$31 -> 199502.04 | AJ43: =(AJ44+Sensitivity!$U$40)*AJ$31 -> 278895.79 | AL43: =(AL44+Sensitivity!$U$40)*AL$31 -> 387422.19
B44: % of sales | D44: =D43/D31 -> 0.14026059 | E44: =E43/E31 -> 0.1251693 | F44: =F43/F31 -> 0.11034064 | G44: =G43/G31 -> 0.087087918 | H44: =H43/H31 -> 0.11176884 | J44: =J43/J31 -> 0.081427035 | K44: =K43/K31 -> 0.072286391 | L44: =L43/L31 -> 0.058636 | M44: =M43/M31 -> 0.090258175 | N44: =N43/N31 -> 0.073805144 | P44: =P43/P31 -> 0.11374046 | Q44: =Q43/Q31 -> 0.14635517 | R44: =R43/R31 -> 0.093901655 | S44: =S43/S31 -> 0.090171648 | T44: =T43/T31 -> 0.10858852 | V44: =V43/V31 -> 0.078806827 | W44: =W43/W31 -> 0.081319114 | X44: 0.0787 | Y44: 0.0875 | AB44: 0.079 | AC44: 0.0868 | AD44: 0.0732 | AE44: 0.0819 | AH44: 0.0747 | AJ44: 0.0692 | AL44: 0.0637
B46: R&D (Research & Development) | D46: =IS!P29 -> 0 | E46: =IS!Q29 -> 0 | F46: =IS!R29 -> 0 | G46: =IS!S29 -> 0 | H46: =IS!T29 -> 0 | J46: =IS!V29 -> 0 | K46: =IS!W29 -> 0 | L46: =IS!X29 -> 0 | M46: =IS!Y29 -> 0 | N46: =IS!Z29 -> 0 | P46: =IS!AB29 -> 0 | Q46: =IS!AC29 -> 0 | R46: =IS!AD29 -> 0 | S46: =IS!AE29 -> 0 | T46: =IS!AF29 -> 0 | V46: =IS!AH29 -> 0 | W46: =IS!AI29 -> 0 | X46: =X47*X40 -> 0 | Y46: =Y47*Y40 -> 0 | Z46: =SUM(V46:Y46) -> 0 | AB46: =AB47*AB40 -> 0 | AC46: =AC47*AC40 -> 0 | AD46: =AD47*AD40 -> 0 | AE46: =AE47*AE40 -> 0 | AF46: =SUM(AB46:AE46) -> 0 | AH46: =AH47*AH40 -> 0 | AJ46: =AJ47*AJ40 -> 0 | AL46: =AL47*AL40 -> 0
B47: % of gross profit | D47: =D46/D40 -> 0 | E47: =E46/E40 -> 0 | F47: =F46/F40 -> 0 | G47: =G46/G40 -> 0 | H47: =H46/H40 -> 0 | J47: =J46/J40 -> 0 | K47: =K46/K40 -> 0 | L47: =L46/L40 -> 0 | M47: =M46/M40 -> 0 | N47: =N46/N40 -> 0 | P47: =P46/P40 -> 0 | Q47: =Q46/Q40 -> 0 | R47: =R46/R40 -> 0 | S47: =S46/S40 -> 0 | T47: =T46/T40 -> 0 | V47: =V46/V40 -> 0 | W47: =W46/W40 -> 0 | Z47: =Z46/Z$40 -> 0 | AF47: =AF46/AF$40 -> 0
B49: D&A (Depreciation & Amortization) | D49: =IS!P28 -> 19340 | E49: =IS!Q28 -> 20054 | F49: =IS!R28 -> 19757 | G49: =IS!S28 -> 21090 | H49: =IS!T28 -> 80241 | J49: =IS!V28 -> 22048 | K49: =IS!W28 -> 23770 | L49: =IS!X28 -> 0 | M49: =IS!Y28 -> 0 | N49: =IS!Z28 -> 45818 | P49: =IS!AB28 -> 0 | Q49: =IS!AC28 -> 0 | R49: =IS!AD28 -> 0 | S49: =IS!AE28 -> 0 | T49: =IS!AF28 -> 0 | V49: =IS!AH28 -> 0 | W49: =IS!AI28 -> 0 | X49: =X52+X55 -> 0 | Y49: =Y52+Y55 -> 0 | Z49: =SUM(V49:Y49) -> 0 | AB49: =AB52+AB55 -> 0 | AC49: =AC52+AC55 -> 0 | AD49: =AD52+AD55 -> 0 | AE49: =AE52+AE55 -> 0 | AF49: =SUM(AB49:AE49) -> 0 | AH49: =AH52+AH55 -> 0 | AJ49: =AJ52+AJ55 -> 0 | AL49: =AL52+AL55 -> 0
B50: % of net pp&e and intangibles excl. Goodwill | D50: =D49/(D79+D82) -> 0.026356458 | E50: =E49/(E79+E82) -> 0.027385251 | F50: =F49/(F79+F82) -> 0.026856814 | G50: =G49/(G79+G82) -> 0.028449675 | H50: =H49/(H79+H82) -> 0.10824231 | J50: =J49/(J79+J82) -> 0.029387381 | K50: =K49/(K79+K82) -> 0.031074942 | L50: =L49/(L79+L82) -> 0 | M50: =M49/(M79+M82) -> 0 | N50: =N49/(N79+N82) -> 0.05695618 | P50: =P49/(P79+P82) -> 0 | Q50: =Q49/(Q79+Q82) -> 0 | R50: =R49/(R79+R82) -> 0 | S50: =S49/(S79+S82) -> 0 | T50: =T49/(T79+T82) -> 0 | V50: =V49/(V79+V82) -> 0 | W50: =W49/(W79+W82) -> 0 | X50: =X49/( X79+X82) -> 0 | Y50: =Y49/( Y79+Y82) -> 0 | Z50: =Z49/( Z79+Z82) -> 0 | AB50: =AB49/( AB79+AB82) -> 0 | AC50: =AC49/( AC79+AC82) -> 0 | AD50: =AD49/( AD79+AD82) -> 0 | AE50: =AE49/( AE79+AE82) -> 0 | AF50: =AF49/( AF79+AF82) -> 0 | AH50: =AH49/( AH79+AH82) -> 0 | AJ50: =AJ49/( AJ79+AJ82) -> 0 | AL50: =AL49/( AL79+AL82) -> 0
B52: Depreciation | D52: =IS!P64 -> 9670 | E52: =IS!Q64 -> 10027 | F52: =IS!R64 -> 9878.5 | G52: =IS!S64 -> 10545 | H52: =IS!T64 -> 40120.5 | J52: =IS!V64 -> 11024 | K52: =IS!W64 -> 11885 | L52: =IS!X64 -> 0 | M52: =IS!Y64 -> 0 | N52: =IS!Z64 -> 22909 | P52: =IS!AB64 -> 0 | Q52: =IS!AC64 -> 0 | R52: =IS!AD64 -> 0 | S52: =IS!AE64 -> 0 | T52: =IS!AF64 -> 0 | V52: =IS!AH64 -> 0 | W52: =IS!AI64 -> 0 | X52: =X53*W79 -> 0 | Y52: =Y53*X79 -> 0 | Z52: =SUM(V52:Y52) -> 0 | AB52: =AB53*Y79 -> 0 | AC52: =AC53*AB79 -> 0 | AD52: =AD53*AC79 -> 0 | AE52: =AE53*AD79 -> 0 | AF52: =SUM(AB52:AE52) -> 0 | AH52: =AH53*AF79 -> 0 | AJ52: =AJ53*AH79 -> 0 | AL52: =AL53*AJ79 -> 0
B53: % of net pp&e | D53: =D52/D79 -> 0.014433224 | E53: =E52/E79 -> 0.014987034 | F53: =F52/F79 -> 0.014679397 | G53: =G52/G79 -> 0.015526258 | H53: =H52/H79 -> 0.059072665 | J53: =J52/J79 -> 0.016007992 | K53: =K52/K79 -> 0.016884932 | L53: =L52/L79 -> 0 | M53: =M52/M79 -> 0 | N53: =N52/N79 -> 0.030769334 | P53: =P52/P79 -> 0 | Q53: =Q52/Q79 -> 0 | R53: =R52/R79 -> 0 | S53: =S52/S79 -> 0 | T53: =T52/T79 -> 0 | V53: =V52/V79 -> 0 | W53: =W52/W79 -> 0 | Z53: =Z52/Z79 -> 0 | AF53: =AF52/AF79 -> 0
B55: Amortization | D55: =IS!P65 -> 9670 | E55: =IS!Q65 -> 10027 | F55: =IS!R65 -> 9878.5 | G55: =IS!S65 -> 10545 | H55: =IS!T65 -> 40120.5 | J55: =IS!V65 -> 11024 | K55: =IS!W65 -> 11885 | L55: =IS!X65 -> 0 | M55: =IS!Y65 -> 0 | N55: =IS!Z65 -> 22909 | P55: =IS!AB65 -> 0 | Q55: =IS!AC65 -> 0 | R55: =IS!AD65 -> 0 | S55: =IS!AE65 -> 0 | T55: =IS!AF65 -> 0 | V55: =IS!AH65 -> 0 | W55: =IS!AI65 -> 0 | X55: =X56*W82 -> 0 | Y55: =Y56*X82 -> 0 | Z55: =SUM(V55:Y55) -> 0 | AB55: =AB56*Y82 -> 0 | AC55: =AC56*AB82 -> 0 | AD55: =AD56*AC82 -> 0 | AE55: =AE56*AD82 -> 0 | AF55: =SUM(AB55:AE55) -> 0 | AH55: =AH56*AF82 -> 0 | AJ55: =AJ56*AH82 -> 0 | AL55: =AL56*AJ82 -> 0
B56: % of intangibles excl. goodwill | D56: =D55/D82 -> 0.1515579 | E56: =E55/E82 -> 0.15853716 | F56: =F55/F82 -> 0.15757194 | G56: =G55/G82 -> 0.16970565 | H56: =H55/H82 -> 0.6456781 | J56: =J55/J82 -> 0.17896685 | K56: =K55/K82 -> 0.19469882 | L56: =L55/L82 -> 0 | M56: =M55/M82 -> 0 | N56: =N55/N82 -> 0.38243494 | P56: =P55/P82 -> 0 | Q56: =Q55/Q82 -> 0 | R56: =R55/R82 -> 0 | S56: =S55/S82 -> 0 | T56: =T55/T82 -> 0 | V56: =V55/V82 -> 0 | W56: =W55/W82 -> 0 | Z56: =Z55/Z82 -> 0 | AF56: =AF55/AF82 -> 0
B58: Other Operating (Income) Expenses | D58: =IS!P30+IS!P32 -> 0 | E58: =IS!Q30+IS!Q32 -> 0 | F58: =IS!R30+IS!R32 -> 0 | G58: =IS!S30+IS!S32 -> 0 | H58: =IS!T30+IS!T32 -> 0 | J58: =IS!V30+IS!V32 -> 0 | K58: =IS!W30+IS!W32 -> 0 | L58: =IS!X30+IS!X32 -> 0 | M58: =IS!Y30+IS!Y32 -> 0 | N58: =IS!Z30+IS!Z32 -> 0 | P58: =IS!AB30+IS!AB32 -> 0 | Q58: =IS!AC30+IS!AC32 -> 0 | R58: =IS!AD30+IS!AD32 -> 0 | S58: =IS!AE30+IS!AE32 -> 0 | T58: =IS!AF30+IS!AF32 -> 0 | V58: =IS!AH30+IS!AH32 -> 146 | W58: =IS!AI30+IS!AI32 -> 0 | X58: =X59*X$31 -> 0 | Y58: =Y59*Y$31 -> 0 | Z58: =SUM(V58:Y58) -> 146 | AB58: =AB59*AB$31 -> 0 | AC58: =AC59*AC$31 -> 0 | AD58: =AD59*AD$31 -> 0 | AE58: =AE59*AE$31 -> 0 | AF58: =SUM(AB58:AE58) -> 0 | AH58: =AH59*AH$31 -> 0 | AJ58: =AJ59*AJ$31 -> 0 | AL58: =AL59*AL$31 -> 0
B59: % of sales | D59: =D58/D31 -> 0 | E59: =E58/E31 -> 0 | F59: =F58/F31 -> 0 | G59: =G58/G31 -> 0 | H59: =H58/H31 -> 0 | J59: =J58/J31 -> 0 | K59: =K58/K31 -> 0 | L59: =L58/L31 -> 0 | M59: =M58/M31 -> 0 | N59: =N58/N31 -> 0 | P59: =P58/P31 -> 0 | Q59: =Q58/Q31 -> 0 | R59: =R58/R31 -> 0 | S59: =S58/S31 -> 0 | T59: =T58/T31 -> 0 | V59: =V58/V31 -> 0.00018578113 | W59: =W58/W31 -> 0 | Z59: =Z58/Z$31 -> 3.6560224e-05 | AF59: =AF58/AF$31 -> 0
B61: EBIT (Operating Income) | D61: =IS!P33 -> -39880 | E61: =IS!Q33 -> -4033 | F61: =IS!R33 -> 38896 | G61: =IS!S33 -> 143445 | H61: =IS!T33 -> 138428 | J61: =IS!V33 -> 163883 | K61: =IS!W33 -> 259897 | L61: =IS!X33 -> 404537 | M61: =IS!Y33 -> 135933 | N61: =IS!Z33 -> 964250 | P61: =IS!AB33 -> -6813 | Q61: =IS!AC33 -> 14552 | R61: =IS!AD33 -> 152552 | S61: =IS!AE33 -> 128655 | T61: =IS!AF33 -> 288946 | V61: =IS!AH33 -> 185140 | W61: =IS!AI33 -> 278409 | X61: =X40-X43-X46-X49-X58 -> 312152.08 | Y61: =Y40-Y43-Y46-Y49-Y58 -> 270555.27 | Z61: =SUM(V61:Y61) -> 1046256.3 | AB61: =AB40-AB43-AB46-AB49-AB58 -> 429202.88 | AC61: =AC40-AC43-AC46-AC49-AC58 -> 368810.24 | AD61: =AD40-AD43-AD46-AD49-AD58 -> 526771.78 | AE61: =AE40-AE43-AE46-AE49-AE58 -> 481732.21 | AF61: =SUM(AB61:AE61) -> 1806517.1 | AH61: =AH40-AH43-AH46-AH49-AH58 -> 902967.05 | AJ61: =AJ40-AJ43-AJ46-AJ49-AJ58 -> 1527881.4 | AL61: =AL40-AL43-AL46-AL49-AL58 -> 2554432
B62: % of sales | D62: =D61/D31 -> -0.12022767 | E62: =E61/E31 -> -0.010565253 | F62: =F61/F31 -> 0.081460151 | G62: =G61/G31 -> 0.24191182 | H62: =H61/H31 -> 0.077892862 | J62: =J61/J31 -> 0.24893217 | K62: =K61/K31 -> 0.32418236 | L62: =L61/L31 -> 0.40555372 | M62: =M61/M31 -> 0.19738195 | N62: =N61/N31 -> 0.30647918 | P62: =P61/P31 -> -0.014832021 | Q62: =Q61/Q31 -> 0.027811648 | R62: =R61/R31 -> 0.21697797 | S62: =S61/S31 -> 0.20077592 | T62: =T61/T31 -> 0.12420076 | V62: =V61/V31 -> 0.23558574 | W62: =W61/W31 -> 0.29162822 | X62: =X61/X$31 -> 0.289 | Y62: =Y61/Y$31 -> 0.2307 | Z62: =Z61/Z$31 -> 0.26199566 | AB62: =AB61/AB$31 -> 0.3302 | AC62: =AC61/AC$31 -> 0.256 | AD62: =AD61/AD$31 -> 0.3299 | AE62: =AE61/AE$31 -> 0.2722 | AF62: =AF61/AF$31 -> 0.29580958 | AH62: =AH61/AH$31 -> 0.3381 | AJ62: =AJ61/AJ$31 -> 0.3791 | AL62: =AL61/AL$31 -> 0.42
B64: Basic Weighted Average Shares | D64: =IS!P59 -> 48858 | E64: =IS!Q59 -> 48857 | F64: =IS!R59 -> 48886 | G64: =IS!S59 -> 48622 | H64: =IS!T59 -> 48581 | J64: =IS!V59 -> 48623 | K64: =IS!W59 -> 48624 | L64: =IS!X59 -> 48653 | M64: =IS!Y59 -> 48689 | N64: =IS!Z59 -> 48648 | P64: =IS!AB59 -> 48690 | Q64: =IS!AC59 -> 48690 | R64: =IS!AD59 -> 48727 | S64: =IS!AE59 -> 48761 | T64: =IS!AF59 -> 48717 | V64: =IS!AH59 -> 48761 | W64: =IS!AI59 -> 48765 | X64: =W64+X101 -> 48766.083 | Y64: =X64+Y101 -> 48767.127 | Z64: =AVERAGE(V64:Y64) -> 48764.803 | AB64: =Y64+AB101 -> 48768.053 | AC64: =AB64+AC101 -> 48769.071 | AD64: =AC64+AD101 -> 48769.933 | AE64: =AD64+AE101 -> 48770.897 | AF64: =AVERAGE(AB64:AE64) -> 48769.489 | AH64: =AE64+AH101 -> 48773.933 | AJ64: =AF64+AJ101 -> 48772.301 | AL64: =AH64+AL101 -> 48776.522
B65: Diluted Weighted Average Shares | D65: =IS!P60 -> 48858 | E65: =IS!Q60 -> 49016 | F65: =IS!R60 -> 49036 | G65: =IS!S60 -> 48791 | H65: =IS!T60 -> 48734 | J65: =IS!V60 -> 48811 | K65: =IS!W60 -> 48840 | L65: =IS!X60 -> 48842 | M65: =IS!Y60 -> 48838 | N65: =IS!Z60 -> 48834 | P65: =IS!AB60 -> 48840 | Q65: =IS!AC60 -> 48866 | R65: =IS!AD60 -> 48884 | S65: =IS!AE60 -> 48902 | T65: =IS!AF60 -> 48873 | V65: =IS!AH60 -> 48932 | W65: =IS!AI60 -> 48970 | X65: =W65 -> 48970 | Y65: =X65 -> 48970 | Z65: =AVERAGE(V65:Y65) -> 48960.5 | AB65: =Y65 -> 48970 | AC65: =AB65 -> 48970 | AD65: =AC65 -> 48970 | AE65: =AD65 -> 48970 | AF65: =AVERAGE(AB65:AE65) -> 48970 | AH65: =AF65 -> 48970 | AJ65: =AH65 -> 48970 | AL65: =AJ65 -> 48970
B67: Balance Sheet | D67: Q1 22 | E67: Q2 22 | F67: Q3 22 | G67: Q4 22 | H67: FY 22 | J67: Q1 23 | K67: Q2 23 | L67: Q3 23 | M67: Q4 23 | N67: FY 23 | P67: Q1 24 | Q67: Q2 24 | R67: Q3 24 | S67: Q4 24 | T67: FY 24 | V67: Q1 25 | W67: Q2 25 | X67: Q3 25 | Y67: Q4 25 | Z67: FY 25 | AB67: Q1 26 | AC67: Q2 26 | AD67: Q3 26 | AE67: Q4 26 | AF67: FY 26 | AH67: FY 27 | AJ67: FY 28 | AL67: FY 29
B70: Accounts Receivable | D70: =BS!P18 -> 134400 | E70: =BS!Q18 -> 152958 | F70: =BS!R18 -> 138654 | G70: =BS!S18 -> 169109 | H70: =BS!T18 -> 169109 | J70: =BS!V18 -> 178217 | K70: =BS!W18 -> 262964 | L70: =BS!X18 -> 206920 | M70: =BS!Y18 -> 110980 | N70: =BS!Z18 -> 110980 | P70: =BS!AB18 -> 125363 | Q70: =BS!AC18 -> 165391 | R70: =BS!AD18 -> 212851 | S70: =BS!AE18 -> 138550 | T70: =BS!AF18 -> 138550 | V70: =BS!AH18 -> 272092 | W70: =BS!AI18 -> 307292 | X70: =X31*X71/92 -> 220718.33 | Y70: =Y31*Y71/92 -> 275343.18 | Z70: =Y70 -> 275343.18 | AB70: =AB31*AB71/90 -> 314846.98 | AC70: =AC31*AC71/91 -> 368873.57 | AD70: =AD31*AD71/92 -> 296789.46 | AE70: =AE31*AE71/92 -> 380885.93 | AF70: =AE70 -> 380885.93 | AH70: =AH31*AH71/365 -> 136828.16 | AJ70: =AJ31*AJ71/366 -> 187199.08 | AL70: =AL31*AL71/365 -> 253277.02
B71: days sales outstanding | D71: =D70/D31*90 -> 36.466247 | E71: =E70/E31*91 -> 36.46408 | F71: =F70/F31*92 -> 26.715327 | G71: =G70/G31*92 -> 26.237728 | H71: =H70/H31*365 -> 34.732281 | J71: =J70/J31*90 -> 24.363448 | K71: =K70/K31*91 -> 29.848726 | L71: =L70/L31*92 -> 19.084485 | M71: =M70/M31*92 -> 14.825696 | N71: =N70/N31*365 -> 12.87505 | P71: =P70/P31*90 -> 24.562572 | Q71: =Q70/Q31*91 -> 28.764532 | R71: =R70/R31*92 -> 27.852312 | S71: =S70/S31*92 -> 19.892039 | T71: =T70/T31*365 -> 21.737369 | V71: =V70/V31*90 -> 31.160687 | W71: =W70/W31*91 -> 29.291318 | X71: 18.8 | Y71: 21.6 | Z71: =Z70/Z31*365 -> 25.166521 | AB71: 21.8 | AC71: 23.3 | AD71: 17.1 | AE71: 19.8 | AF71: =AF70/AF31*365 -> 22.764491 | AH71: 18.7 | AJ71: 17 | AL71: 15.2
B73: Inventory | D73: =BS!P19 -> 226470 | E73: =BS!Q19 -> 236201 | F73: =BS!R19 -> 240087 | G73: =BS!S19 -> 263316 | H73: =BS!T19 -> 263316 | J73: =BS!V19 -> 265754 | K73: =BS!W19 -> 280582 | L73: =BS!X19 -> 290869 | M73: =BS!Y19 -> 284418 | N73: =BS!Z19 -> 284418 | P73: =BS!AB19 -> 280801 | Q73: =BS!AC19 -> 287270 | R73: =BS!AD19 -> 269244 | S73: =BS!AE19 -> 261782 | T73: =BS!AF19 -> 261782 | V73: =BS!AH19 -> 293182 | W73: =BS!AI19 -> 299365 | X73: =X74*X34/92 -> 356323.92 | Y73: =Y74*Y34/92 -> 417175.52 | Z73: =Y73 -> 417175.52 | AB73: =AB74*AB34/92 -> 392316.05 | AC73: =AC74*AC34/92 -> 473402.52 | AD73: =AD74*AD34/92 -> 466193.76 | AE73: =AE74*AE34/92 -> 559123.23 | AF73: =AE73 -> 559123.23 | AH73: =AH74*AH34/365 -> 184751.67 | AJ73: =AJ74*AJ34/366 -> 243006.42 | AL73: =AL74*AL34/365 -> 309711.14
B74: days inventory held | D74: =D73/D34*90 -> 62.703386 | E74: =E73/E34*91 -> 63.597093 | F74: =F73/F34*92 -> 57.237192 | G74: =G73/G34*92 -> 60.885525 | H74: =H73/H34*365 -> 66.738657 | J74: =J73/J34*90 -> 54.253472 | K74: =K73/K34*91 -> 52.770299 | L74: =L73/L34*92 -> 50.068476 | M74: =M73/M34*92 -> 53.336926 | N74: =N73/N34*365 -> 53.243768 | P74: =P73/P34*90 -> 61.056821 | Q74: =Q73/Q34*91 -> 60.498329 | R74: =R73/R34*92 -> 51.125374 | S74: =S73/S34*92 -> 53.00712 | T74: =T73/T34*365 -> 53.533491 | V74: =V73/V34*90 -> 48.985859 | W74: =W73/W34*91 -> 45.507677 | X74: 48 | Y74: 48 | Z74: =Z73/Z34*365 -> 58.121899 | AB74: 47 | AC74: 46 | AD74: 45 | AE74: 45 | AF74: =AF73/AF34*365 -> 53.550996 | AH74: 43 | AJ74: 40 | AL74: 36
B76: Prepaid expenses and Other Current Assets | D76: =BS!P20 -> 9249 | E76: =BS!Q20 -> 6814 | F76: =BS!R20 -> 47255 | G76: =BS!S20 -> 54581 | H76: =BS!T20 -> 54581 | J76: =BS!V20 -> 53112 | K76: =BS!W20 -> 51115 | L76: =BS!X20 -> 50546 | M76: =BS!Y20 -> 81613 | N76: =BS!Z20 -> 81613 | P76: =BS!AB20 -> 47932 | Q76: =BS!AC20 -> 43444 | R76: =BS!AD20 -> 40654 | S76: =BS!AE20 -> 29130 | T76: =BS!AF20 -> 29130 | V76: =BS!AH20 -> 24615 | W76: =BS!AI20 -> 20755 | X76: =X77*X$31 -> 31323.219 | Y76: =Y77*Y$31 -> 66847.206 | Z76: =Y76 -> 66847.206 | AB76: =AB77*AB$31 -> 66291.177 | AC76: =AC77*AC$31 -> 51863.94 | AD76: =AD77*AD$31 -> 38322.288 | AE76: =AE77*AE$31 -> 92028.196 | AF76: =AE76 -> 92028.196 | AH76: =AH77*AH$31 -> 93474.85 | AJ76: =AJ77*AJ$31 -> 120908.58 | AL76: =AL77*AL$31 -> 152049.52
