Workbook
Name COOLFUCNTION: _xlfn.LAMBDA(_xldudf_BOARDFLARE_EXEC("workbook-settings:coolfucntion"))
Name COOLFUCNTION: _xlfn.LAMBDA(_xldudf_BOARDFLARE_EXEC("workbook-settings:coolfucntion"))
Name COOLFUCNTION: _xlfn.LAMBDA(_xldudf_BOARDFLARE_EXEC("workbook-settings:coolfucntion"))
Name COOLFUCNTION: _xlfn.LAMBDA(_xldudf_BOARDFLARE_EXEC("workbook-settings:coolfucntion"))
Name COOLFUCNTION: _xlfn.LAMBDA(_xldudf_BOARDFLARE_EXEC("workbook-settings:coolfucntion"))
Name COOLFUCNTION: _xlfn.LAMBDA(_xldudf_BOARDFLARE_EXEC("workbook-settings:coolfucntion"))
Name COOLFUCNTION: _xlfn.LAMBDA(_xldudf_BOARDFLARE_EXEC("workbook-settings:coolfucntion"))
Name COOLFUCNTION: _xlfn.LAMBDA(_xldudf_BOARDFLARE_EXEC("workbook-settings:coolfucntion"))
Name COOLFUCNTION: _xlfn.LAMBDA(_xldudf_BOARDFLARE_EXEC("workbook-settings:coolfucntion"))
Name COOLFUCNTION: _xlfn.LAMBDA(_xldudf_BOARDFLARE_EXEC("workbook-settings:coolfucntion"))
Name COOLFUCNTION: _xlfn.LAMBDA(_xldudf_BOARDFLARE_EXEC("workbook-settings:coolfucntion"))
Name Sectors: #REF!
Name Sectors: #REF!
Name Sectors: #REF!
Name Sectors: #REF!
Name Sectors: #REF!
Name Sectors: #REF!
Name Sectors: #REF!
Name Sectors: #REF!

Sheet Dashboard
C154: =+C155+1 -> 45957
C155: =+C156+1 -> 45956
C156: =+C157+1 -> 45955
C157: =+C158+1 -> 45954
C158: =+C159+1 -> 45953
C159: =+C160+1 -> 45952
C160: =+C161+1 -> 45951 | L160: =IF(FCFF!$R$157="Revenue Exit",FCFF!$AF$169,IF(FCFF!$R$157="EBITDA Exit",FCFF!Z169,FCFF!AL169)) -> 393.57378
C161: =+C162+1 -> 45950
C162: =+C163+1 -> 45949 | E162: =IF(FCFF!$R$157="Revenue Exit",FCFF!$AF$169,IF(FCFF!$R$157="EBITDA Exit",FCFF!Z169,FCFF!AL169)) -> 393.57378
C163: =+C164+1 -> 45948 | E163: =E164+($E$162-$E$193)/COUNTA($C$162:$C$192) -> 396.41043
C164: =+C165+1 -> 45947 | E164: =E165+($E$162-$E$193)/COUNTA($C$162:$C$192) -> 399.24708
C165: =+C166+1 -> 45946 | E165: =E166+($E$162-$E$193)/COUNTA($C$162:$C$192) -> 402.08373
C166: =+C167+1 -> 45945 | E166: =E167+($E$162-$E$193)/COUNTA($C$162:$C$192) -> 404.92039
C167: =+C168+1 -> 45944 | E167: =E168+($E$162-$E$193)/COUNTA($C$162:$C$192) -> 407.75704
C168: =+C169+1 -> 45943 | E168: =E169+($E$162-$E$193)/COUNTA($C$162:$C$192) -> 410.59369
C169: =+C170+1 -> 45942 | E169: =E170+($E$162-$E$193)/COUNTA($C$162:$C$192) -> 413.43034
C170: =+C171+1 -> 45941 | E170: =E171+($E$162-$E$193)/COUNTA($C$162:$C$192) -> 416.26699
C171: =+C172+1 -> 45940 | E171: =E172+($E$162-$E$193)/COUNTA($C$162:$C$192) -> 419.10365
C172: =+C173+1 -> 45939 | E172: =E173+($E$162-$E$193)/COUNTA($C$162:$C$192) -> 421.9403
C173: =+C174+1 -> 45938 | E173: =E174+($E$162-$E$193)/COUNTA($C$162:$C$192) -> 424.77695
C174: =+C175+1 -> 45937 | E174: =E175+($E$162-$E$193)/COUNTA($C$162:$C$192) -> 427.6136
... C192: =+C193+1 -> 45919 | E192: =E193+($E$162-$E$193)/COUNTA($C$162:$C$192) -> 478.67335
B193: TODAY | C193: =+'Stock Data'!AM4 -> 45918 | D193: =_xlfn.XLOOKUP(C193,'Stock Data'!$AM$4:$AM$1051,'Stock Data'!$AN$4:$AN$1051) -> 481.51 | E193: =D193 -> 481.51
C194: =+'Stock Data'!AM5 -> 45917 | D194: =_xlfn.XLOOKUP(C194,'Stock Data'!$AM$4:$AM$1051,'Stock Data'!$AN$4:$AN$1051) -> 481.51
C195: =+'Stock Data'!AM6 -> 45916 | D195: =_xlfn.XLOOKUP(C195,'Stock Data'!$AM$4:$AM$1051,'Stock Data'!$AN$4:$AN$1051) -> 473.26
C196: =+'Stock Data'!AM7 -> 45915 | D196: =_xlfn.XLOOKUP(C196,'Stock Data'!$AM$4:$AM$1051,'Stock Data'!$AN$4:$AN$1051) -> 473.26
C197: =+'Stock Data'!AM8 -> 45914 | D197: =_xlfn.XLOOKUP(C197,'Stock Data'!$AM$4:$AM$1051,'Stock Data'!$AN$4:$AN$1051) -> 473.26
C198: =+'Stock Data'!AM9 -> 45913 | D198: =_xlfn.XLOOKUP(C198,'Stock Data'!$AM$4:$AM$1051,'Stock Data'!$AN$4:$AN$1051) -> 474.9
C199: =+'Stock Data'!AM10 -> 45912 | D199: =_xlfn.XLOOKUP(C199,'Stock Data'!$AM$4:$AM$1051,'Stock Data'!$AN$4:$AN$1051) -> 469.52
C200: =+'Stock Data'!AM11 -> 45911 | D200: =_xlfn.XLOOKUP(C200,'Stock Data'!$AM$4:$AM$1051,'Stock Data'!$AN$4:$AN$1051) -> 476.78
C201: =+'Stock Data'!AM12 -> 45910 | D201: =_xlfn.XLOOKUP(C201,'Stock Data'!$AM$4:$AM$1051,'Stock Data'!$AN$4:$AN$1051) -> 478.64
C202: =+'Stock Data'!AM13 -> 45909 | D202: =_xlfn.XLOOKUP(C202,'Stock Data'!$AM$4:$AM$1051,'Stock Data'!$AN$4:$AN$1051) -> 478.64
C203: =+'Stock Data'!AM14 -> 45908 | D203: =_xlfn.XLOOKUP(C203,'Stock Data'!$AM$4:$AM$1051,'Stock Data'!$AN$4:$AN$1051) -> 478.64
C204: =+'Stock Data'!AM15 -> 45907 | D204: =_xlfn.XLOOKUP(C204,'Stock Data'!$AM$4:$AM$1051,'Stock Data'!$AN$4:$AN$1051) -> 478.64
C205: =+'Stock Data'!AM16 -> 45906 | D205: =_xlfn.XLOOKUP(C205,'Stock Data'!$AM$4:$AM$1051,'Stock Data'!$AN$4:$AN$1051) -> 491.44
... C558: =+'Stock Data'!AM369 -> 45553 | D558: =_xlfn.XLOOKUP(C558,'Stock Data'!$AM$4:$AM$1051,'Stock Data'!$AN$4:$AN$1051) -> 387.23

Sheet Key Info
B7: Analysts | F7: LIS – Equity Research | J7: Stock Performance
B12: Daniel Cruz, Team Leader and Analyst | F12: Recommendation: | H12: Hold
B13: Bsc in Applied Mathematics, ISEG – Ulisboa | F13: Target Price (FCFF): | H13: =FCFF!AF169 -> 393.57378
B14: danielfccruz@aln.iseg.ulisboa.pt | F14: Upside: | H14: =FCFF!AF171 -> -0.18262596
B15: Daan Bootsma, Analyst
B16: Bsc in Management, ISEG – Ulisboa | F16: Ticker | H16: =Inputs!D15 -> DE US Equity
B17: d.bootsma@aln.iseg.ulisboa.pt | F17: Stock Exchange | H17: NYSE
B18: Nicole Sequeira, Analyst
B19: Bsc in Applied Mathematics, ISEG – Ulisboa | F19: Current Price | H19: ='Stock Data'!AN4 -> 481.51
B20: l63823@aln.iseg.ulisboa.pt | F20: ="Market Cap (in "&IF(Inputs!$D$14="BLN","billions",IF(Inputs!$D$14="MLN","millions","thousands"))&")" -> Market Cap (in millions) | H20: ='Stock Data'!AQ4 -> 130166.3
F21: Beta | H21: ='Stock Data'!E164 -> 0.89700514
F22: % of 52-Week High | H22: ='Stock Data'!E165 -> 0.55938667
F23: 100-Day Moving Average | H23: ='Stock Data'!E166 -> 500.28311
B25: Reviewed by: | F25: Avg Vol (1 month) | H25: ='Stock Data'!E168 -> 1490618.5
B26: Tomás Reis, Analyst | F26: Shares Outstanding (millions) | H26: ='Stock Data'!E169 -> 270.3294
B27: Bsc in XXX, ISEG – Ulisboa | F27: % Float | H27: ='Stock Data'!E170 -> 0.9248926
B28: email@aln.iseg.ulisboa.pt | F28: Short % of Float | H28: =IFERROR('Stock Data'!E171,0) -> 0.017152
B30: LISBON INVESTMENT SOCIETY | F30: % Held by Insiders | H30: ='Stock Data'!E173 -> 0.0019671067
B31: ISEG – Rua do Quelhas, 6 | F31: % Held by Institutions | H31: ='Stock Data'!E174 -> 0.8491587
B32: lis@iseg.ulisboa.pt
B34: Disclaimer: This report was prepared by members of the Lisbon Investment Society (LIS), an independent, student-led, non-profit organization based at ISEG – Lisbon School of Economics & Management, and is intended solely for academic and educational purposes. All analyses, forecasts, and opinions expressed in this report reflect the independent judgment of the authors as of the date of publication and are subject to change without notice. The views presented herein do not represent those of ISEG, its faculty, or any affiliated entity. This document does not constitute, and should not be interpreted as, investment advice, an offer, or a solicitation to buy or sell any security or financial instrument. Nothing in this report should be construed as a recommendation to make or refrain from making any investment decision. The content is intended for informational purposes only, and readers are strongly encouraged to conduct their own research and seek advice from a qualified financial professional before making any financial decisions. The information contained in this report has been obtained from publicly available sources believed to be reliable; however, no representation or warranty is made regarding the accuracy, completeness, or timeliness of such information. LIS and its members accept no liability whatsoever for any direct or indirect loss arising from the use of this report or its contents. This report incorporates terminology, financial metrics, and methodologies commonly used in professional equity research, including but not limited to Discounted Cash Flow (DCF), trading multiples, Monte Carlo simulations, and strategic analysis tools such as Porter’s Five Forces. Definitions and assumptions used in these models are disclosed within the report and reflect a hypothetical investment thesis designed solely for academic discussion. All valuations, projections, and target prices presented herein are based on publicly available data and subject to the limitations of modeling assumptions. These are not guarantees of future performance and should not be relied upon as such, as past performance is not indicative of future results. Any company names, logos, trademarks, or brand references mentioned in this report are the property of their respective owners and are used strictly for identification and academic purposes. This document may not be reproduced, redistributed, or quoted in whole or in part without the prior written consent of the Lisbon Investment Society. About LIS – Lisbon Investment Society: The Lisbon Investment Society (LIS) is a non-profit academic association headquartered at ISEG – Lisbon School of Economics & Management. Founded in 2016, LIS is committed to fostering student interest in finance and investment through applied research, skill development, and institutional engagement. The Society operates independently and autonomously from any political, religious, or commercial affiliation, and is composed of selected students and collaborators who are invited through a rigorous recruitment process and share a commitment to excellence, analytical rigor, and ethical standards. Its activities include equity research, portfolio management, macroeconomic analysis, and investment education. This report was prepared by the Equity Research team at the Lisbon Investment Society, whose analysts combine rigorous financial modeling, critical thinking, and collaborative research to deliver high-quality, student-led investment analysis. We welcome your feedback, discussion, and questions regarding this report or our research process, and invite you to reach out to our team as we are always open to engagement.

Sheet Industry
D6: 584.17 | E6: 627.76 | F6: 676.06 | G6: 729.63 | H6: 789.13 | I6: 855.3 | J6: 929 | K6: 997.69 | L6: 1067.63 | M6: 1137.57
A7: x | B7: Industry Growth Forecast | O7: Industry Index
D9: 2022 | E9: =+D9+1 -> 2023 | F9: =+E9+1 -> 2024 | G9: =+F9+1 -> 2025 | H9: =+G9+1 -> 2026 | I9: =+H9+1 -> 2027 | J9: =+I9+1 -> 2028 | K9: =+J9+1 -> 2029 | M9: ="CAGR "&$G$9&" - "&$K$9 -> CAGR 2025 - 2029
B12: Market Size Agricultural Machinery Manufacturing | D12: =D44 -> 97000 | E12: =E44 -> 98240 | F12: =F44 -> 100150 | G12: =G44 -> 142623.33 | H12: =H44 -> 149425.68 | I12: =I44 -> 156862.05 | J12: =J44 -> 164388.05 | K12: =K44 -> 172600.88 | M12: =(K12/G12)^(1/5)-1 -> 0.038892203
B13: Market Share | D13: =SUM(Segments!T12:T13)/D12 -> 0.3647732 | E13: =SUM(Segments!N12:N13)/E12 -> 0.28877239 | F13: =SUM(Segments!AF12:AF13)/F12 -> 0.31755367 | G13: =SUM(Segments!AL12:AL13)/G12 -> 0.19011637 | H13: =SUM(Segments!AR12:AR13)/H12 -> 0.1925837 | I13: =SUM(Segments!AT12:AT13)/I12 -> 0.20662448 | J13: =SUM(Segments!AV12:AV13)/J12 -> 0.22792253 | K13: =SUM(Segments!AX12:AX13)/K12 -> 0.22554335 | M13: =((K13*K12)/(G13*G12))^(1/5)-1 -> 0.075010215
B14: Market Size Construction Equipment | D14: 198500 | E14: 208425 | F14: 196478.75 | G14: 201113.39 | H14: 212109.52 | I14: 223721.77 | J14: 235985.5 | K14: 248938.15 | M14: =(K14/G14)^(1/5)-1 -> 0.043590444
B15: Market Share | D15: =SUM(Segments!T32:T34)/D14 -> 0.055274559 | E15: =SUM(Segments!Z32:Z34)/E14 -> 0.062789972 | F15: =SUM(Segments!AF32:AF34)/F14 -> 0.059156525 | G15: =SUM(Segments!AL32:AL34)/G14 -> 0.04968117 | H15: =SUM(Segments!AR32:AR34)/H14 -> 0.050826992 | I15: =SUM(Segments!AT32:AT34)/I14 -> 0.052647065 | J15: =SUM(Segments!AV32:AV34)/J14 -> 0.055960787 | K15: =SUM(Segments!AX32:AX34)/K14 -> 0.05527712 | M15: =((K15*K14)/(G15*G14))^(1/5)-1 -> 0.066107044
B16: Market Size Forestry Machinery | G16: 12000 | H16: =G16*1.046 -> 12552 | I16: =H16*1.046 -> 13129.392 | J16: =I16*1.046 -> 13733.344 | K16: =J16*1.046 -> 14365.078 | M16: =(K16/G16)^(1/5)-1 -> 0.036633758
B17: Market Share | G17: =Segments!AL35/G16 -> 0.098943465 | H17: =Segments!AR35/H16 -> 0.10206509 | I17: =Segments!AT35/I16 -> 0.10660397 | J17: =Segments!AV35/J16 -> 0.11426899 | K17: =Segments!AX35/K16 -> 0.11383202 | M17: =((K17*K16)/(G17*G16))^(1/5)-1 -> 0.066107044
B18: Market Size | M18: =(K18/G18)^(1/5)-1 -> #DIV/0!
B19: Market Share | M19: =((K19*K18)/(G19*G18))^(1/5)-1 -> #DIV/0!
B20: Market Size | M20: =(K20/G20)^(1/5)-1 -> #DIV/0!
B21: Market Share | M21: =((K21*K20)/(G21*G20))^(1/5)-1 -> #DIV/0!
A23: x
B25: Industry Driver | D25: Description | O25: Porter's Five Forces
B27: AGRICULTURAL MACHINERY
B28: Labor Shortage Crisis & Automation Demand | D28: Agricultural labor shortages are intensifying globally, with the US immigration restrictions are reducing farm labor availability, creating urgent demand for autonomous tractors, precision agriculture technology, and smart machinery to compensate for workforce gaps.
B29: Precision Agriculture & Technology Integration | D29: The industry is experiencing a rush toward autonomous field operations, with connected machinery using IoT, AI, and data analytics to optimize crop yields and resource management. Farmers need GPS-guided equipment, variable rate technology, and data-driven decision systems to maximize productivity while reducing input costs amid challenging farm economics.
B30: Government Support & Infrastructure Investment | D30: Government farm mechanization subsidies and climate-linked incentives are reinforcing equipment demand Industry. Farm aid resuming in 2026 will improve purchasing power. Additionally, sustainability regulations are pushing adoption of low-emission, electric, and precision equipment that reduces environmental impact.
B31: CONSTRUCTION EQUIPMENT
B32: Massive Infrastructure Spending & Urbanization | D32: Government infrastructure investments are driving sustained demand, with the US Infrastructure Investment and Jobs Act providing multi-year disbursements for roads, bridges, and broadband, while data center construction creates additional specialized equipment needs. Rapid urbanization with over 80% of the US population in urban areas is fueling residential and commercial construction projects requiring earthmoving and material handling equipment. | O32: Rivalry Among Existing Competitors | R32: =R58 -> 3.8
O33: Threat of New Entrants | R33: =R39 -> 2.5
B34: FORESTRY EQUIPMENT | O34: Threat of Substitutes | R34: =R64 -> 3
B35: Sustainable Forest Management & Bioenergy Demand | D35: Growing emphasis on sustainable forestry practices and renewable energy is driving adoption of advanced, eco-friendly machinery, with wood and biomass increasingly used for bioenergy production. Electric and hybrid forestry equipment featuring telematics, GPS systems, and autonomous capabilities is gaining market share as operators seek to minimize ecological impact while improving operational efficiency and meeting stricter environmental regulations | O35: Bargaining Power of Customers | R35: =R52 -> 3.2
O36: Bargaining Power of Suppliers | R36: =R46 -> 2.6
O39: Threat of New Entrants | R39: =AVERAGE(R40:R45) -> 2.5
B40: Market Size Agricultural Machinery Manufacturing | D40: 2022 | E40: 2023 | F40: 2024 | G40: 2025 | H40: 2026 | I40: 2027 | J40: 2028 | K40: 2029 | O40: Economies of scale | R40: 2 | T40: Are relevant for this industry
B41: Statista | D41: 97000 | E41: 98240 | F41: 100150 | G41: 100300 | H41: 100730 | I41: 101830 | J41: 101890 | K41: 102620 | O41: Product differentiation | R41: 3 | T41: Research by Farm Equipment find that 63% farmers were brand loyal in 2024
B42: Grand View Research | G42: =176.02*1000 -> 176020 | H42: =G42*1.067 -> 187813.34 | I42: =H42*1.067 -> 200396.83 | J42: =I42*1.067 -> 213823.42 | K42: =J42*1.067 -> 228149.59 | O42: Capital requirements | R42: 2 | T42: Complicated, highly fractured supply, and large numbers required
B43: Mordor Intelligence | G43: =151.55*1000 -> 151550 | H43: =G43*1.054 -> 159733.7 | I43: =H43*1.054 -> 168359.32 | J43: =I43*1.054 -> 177450.72 | K43: =J43*1.054 -> 187033.06 | O43: Access to distribution channels | R43: 2 | T43: DE has a vast expansioning dealer network
B44: Average | D44: =AVERAGE(D41:D43) -> 97000 | E44: =AVERAGE(E41:E43) -> 98240 | F44: =AVERAGE(F41:F43) -> 100150 | G44: =AVERAGE(G41:G43) -> 142623.33 | H44: =AVERAGE(H41:H43) -> 149425.68 | I44: =AVERAGE(I41:I43) -> 156862.05 | J44: =AVERAGE(J41:J43) -> 164388.05 | K44: =AVERAGE(K41:K43) -> 172600.88 | M44: =(K44/G44)^(1/5)-1 -> 0.038892203 | O44: Regulations | R44: 3 | T44: Depending on region, various safety and now environmental regulations exist
O45: Switching costs | R45: 3 | T45: Ecosystems are getting more and more integrated in developed countries
O46: Bargaining Power of Suppliers | R46: =AVERAGE(R47:R51) -> 2.6 | T46: ALAMO GROUP | U46: TEREX CORP | V46: AGCO CORP | W46: KOMATSU LTD-ADR | X46: KUBOTA CORP-ADR | Y46: CNH INDUSTRIAL N | Z46: DEERE & CO | AA46: CATTERPILLAR INC
O47: Number of suppliers | R47: 3 | T47: 16 | U47: 52 | V47: 101 | W47: 132 | X47: 150 | Y47: 164 | Z47: 245 | AA47: 372
O48: Uniqueness | R48: 3 | T48: Suppliers per firm differ vastly
O49: Switching Costs | R49: 3 | T49: Honestly not sure
O50: Forward Integration | R50: 2 | T50: Suppliers deliver specific parts, not whole sale products
B51: Construction Equipment Market (in Millions) | D51: 2022 | E51: 2023 | F51: 2024 | G51: 2025 | H51: 2026 | I51: 2027 | J51: 2028 | K51: 2029 | L51: 2030 | M51: CAGR | O51: Industry Importance | R51: 2 | T51: Suppliers are mostly not restricted to this industry
B52: Mordor Intelligence | G52: =192.59*1000 -> 192590 | H52: =G52*1.0673 -> 205551.31 | I52: =H52*1.0673 -> 219384.91 | J52: =I52*1.0673 -> 234149.51 | K52: =J52*1.0673 -> 249907.78 | L52: =K52*1.0673 -> 266726.57 | O52: Bargaining Power of Customers | R52: =AVERAGE(R53:R57) -> 3.2
B53: Econ Market Research | D53: =198.5*1000 -> 198500 | E53: =D53*1.05 -> 208425 | F53: =E53*1.05 -> 218846.25 | G53: =F53*1.05 -> 229788.56 | H53: =G53*1.05 -> 241277.99 | I53: =H53*1.05 -> 253341.89 | J53: =I53*1.05 -> 266008.98 | K53: =J53*1.05 -> 279309.43 | L53: =K53*1.05 -> 293274.91 | O53: Number of buyers | R53: 3 | T53: I expect the number of buyers to decrease over time
B54: Global Market Insights | F54: =167.8*1000 -> 167800 | G54: =170.2*1000 -> 170200 | H54: =G54*1.059 -> 180241.8 | I54: =H54*1.059 -> 190876.07 | J54: =I54*1.059 -> 202137.75 | K54: =J54*1.059 -> 214063.88 | L54: =K54*1.059 -> 226693.65 | O54: Purchase size | R54: 3 | T54: Again, larger and larger customers
B55: MMR | F55: =202.79*1000 -> 202790 | G55: =F55*1.0448 -> 211874.99 | H55: =G55*1.0448 -> 221366.99 | I55: =H55*1.0448 -> 231284.23 | J55: =I55*1.0448 -> 241645.77 | K55: =J55*1.0448 -> 252471.5 | L55: =K55*1.0448 -> 263782.22 | O55: Switching costs | R55: 2 | T55: Ecosystems are in place, with larger farmers it becomes more expensive to switch
B56: Average | D56: =AVERAGE(D52:D55) -> 198500 | E56: =AVERAGE(E52:E55) -> 208425 | F56: =AVERAGE(F52:F55) -> 196478.75 | G56: =AVERAGE(G52:G55) -> 201113.39 | H56: =AVERAGE(H52:H55) -> 212109.52 | I56: =AVERAGE(I52:I55) -> 223721.77 | J56: =AVERAGE(J52:J55) -> 235985.5 | K56: =AVERAGE(K52:K55) -> 248938.15 | L56: =AVERAGE(L52:L55) -> 262619.34 | M56: =(K56/G56)^(1/5)-1 -> 0.043590444 | O56: Price sensitivity | R56: 4 | T56: Farmers operate on fine margins, they have the need for good prices
O57: Informed buyers | R57: 4 | T57: They need to, and will become better as more consolidated
O58: Competitive Rivalry | R58: =AVERAGE(R59:R63) -> 3.8
O59: Number of competitors | R59: 3 | T59: Picking medium, don´t know how to evaluate yet
O60: Industry growth | R60: 4 | T60: A CAGR around 4% for well established industries seem relatively high
O61: Similarities in what's offered | R61: 4 | T61: Competiton offer relatively similar equipment
O62: Exit barriers | R62: 4 | T62: Large factories and wide networks make this harder to exit
B63: Notes | O63: Fixed costs | R63: 4 | T63: Probably getting higher, exposed to steel prices
B64: Recent Industry Developments | O64: Threat of Substitutes | R64: =AVERAGE(R65:R68) -> 3
O65: Relative price performance | T65: Not including, doesn´t seem helpful for whole industry
B66: January 2025: John Deere unveiled its next-generation autonomous tillage system featuring 16 cameras and advanced AI processing capabilities, enabling fully autonomous field operations without human oversight. The system represents a significant advancement in agricultural automation and positions Deere at the forefront of autonomous farming technology development. | O66: Customer willingness to go elsewhere | R66: 1 | T66: Products are increasingly part of larger ecosystem, making it more costly to switch
O67: The sense that products are similar | R67: 4 | T67: Competiton offer relatively similar equipment
O68: Availability of close substitutes | R68: 4 | T68: Competiton offer relatively similar equipment
B69: Source: https://www.mordorintelligence.com/industry-reports/agricultural-machinery-market
B73: Underlying Farming Issues | D73: Currently, US farmers ( DE biggest customer), are struggling with the effect of Tariffs and a hold on Government Aid. China´s soybeans import has transitioned to Brazil. In 2026 Government Aid should be coming back to farming. In the next period a portion of small farms will be most likely be consolidated by bigger farms, as right now small farms have less capital to winter the storm. On top of that, the Trump admin is cracking down on immigration, and `surprisingly` there is less labour available for farms.
B74: Innovation | D74: Less labourers and governmental restrictions due to climate issues create the need for smarter and autonomous vehicles.

Sheet Segments
B7: Segments | D7: 2020 | J7: =D7+1 -> 2021 | P7: =J7+1 -> 2022 | V7: =P7+1 -> 2023 | AB7: =V7+1 -> 2024 | AH7: =AB7+1 -> 2025 | AN7: =AH7+1 -> 2026 | AT7: =AN7+1 -> 2027 | AV7: =+AT7+1 -> 2028 | AX7: =+AV7+1 -> 2029
D8: Q1 | E8: Q2 | F8: Q3 | G8: Q4 | H8: FY | I8: % | J8: Q1 | K8: Q2 | L8: Q3 | M8: Q4 | N8: FY | P8: Q1 | Q8: Q2 | R8: Q3 | S8: Q4 | T8: FY | V8: Q1 | W8: Q2 | X8: Q3 | Y8: Q4 | Z8: FY | AB8: Q1 | AC8: Q2 | AD8: Q3 | AE8: Q4 | AF8: FY | AH8: Q1 | AI8: Q2 | AJ8: Q3 | AK8: Q4 | AL8: FY | AM8: DE | AN8: Q1 | AO8: Q2 | AP8: Q3 | AQ8: DE | AR8: FY | AS8: DE | AT8: FY | AV8: FY | AX8: FY
B11: Revenue by segment: | AZ11: Production agriculture
B12: Production and Precision Agriculture (PPA) | H12: 12962 | I12: =H12/H$17 -> 0.36471581 | N12: 16509 | O12: =N12/N$17 -> 0.375 | T12: 22002 | U12: =T12/T$17 -> 0.41847196 | Z12: 26790 | AA12: =Z12/Z$17 -> 0.43738061 | AF12: 20834 | AG12: =AF12/AF$17 -> 0.40285405 | AL12: 17210.74 | AM12: =AL12/AL$17 -> 0.38132623 | AR12: 18108 | AS12: =AR12/AR$17 -> 0.37793871 | AT12: 20688.61 | AU12: =AT12/AT$17 -> 0.38970224 | AV12: 24245.9 | AW12: =AV12/AV$17 -> 0.40260079 | AX12: =AV12*1.039 -> 25191.49 | AY12: =AX12/AX$17 -> 0.39939592 | AZ12: Small agriculture
B13: Small Agriculture and Turf (SAT) | H13: 9363 | I13: =H13/H$17 -> 0.26344963 | N13: 11860 | O13: =N13/N$17 -> 0.26939851 | T13: 13381 | U13: =T13/T$17 -> 0.25450292 | Z13: 13980 | AA13: =Z13/Z$17 -> 0.22824117 | AF13: 10969 | AG13: =AF13/AF$17 -> 0.2121007 | AL13: 9904.29 | AM13: =AL13/AL$17 -> 0.21944237 | AR13: 10668.95 | AS13: =AR13/AR$17 -> 0.22267557 | AT13: 11722.93 | AU13: =AT13/AT$17 -> 0.22081967 | AV13: 13221.84 | AW13: =AV13/AV$17 -> 0.21954736 | AX13: =AV13*1.039 -> 13737.492 | AY13: =AX13/AX$17 -> 0.21779967 | AZ13: Turf
B14: Construction and Forestry (CF) | H14: 9181 | I14: =H14/H$17 -> 0.25832864 | N14: 11613 | O14: =N14/N$17 -> 0.26378793 | T14: 13065 | U14: =T14/T$17 -> 0.24849269 | Z14: 15020 | AA14: =Z14/Z$17 -> 0.24522049 | AF14: 13254 | AG14: =AF14/AF$17 -> 0.25628432 | AL14: 11178.87 | AM14: =AL14/AL$17 -> 0.24768234 | AR14: 12062.01 | AS14: =AR14/AR$17 -> 0.25175064 | AT14: 13177.94 | AU14: =AT14/AT$17 -> 0.24822706 | AV14: 14775.23 | AW14: =AV14/AV$17 -> 0.24534125 | AX14: =AV14*1.042 -> 15395.79 | AY14: =AX14/AX$17 -> 0.24409098 | AZ14: Construction
B15: Financial Services (FS) | H15: 3589 | I15: =H15/H$17 -> 0.10098481 | N15: 3548 | O15: =N15/N$17 -> 0.080592404 | T15: 3625 | U15: =T15/T$17 -> 0.068946498 | Z15: 4721 | AA15: =Z15/Z$17 -> 0.077076293 | AF15: 5782 | AG15: =AF15/AF$17 -> 0.11180292 | AL15: 5833.24 | AM15: =AL15/AL$17 -> 0.12924299 | AR15: 6018.81 | AS15: =AR15/AR$17 -> 0.12562079 | AT15: 6364.38 | AU15: =AT15/AT$17 -> 0.11988302 | AV15: 6794.07 | AW15: =AV15/AV$17 -> 0.11281487 | AX15: =(AT15/AL15)*AV15 -> 7412.6974 | AY15: =AX15/AX$17 -> 0.11752386 | AZ15: Compact Construction
B16: Other | H16: 679 | I16: =H16/H$17 -> 0.019105234 | N16: 739 | O16: =N16/N$17 -> 0.016786298 | T16: 1035 | U16: =T16/T$17 -> 0.019685414 | Z16: 965 | AA16: =Z16/Z$17 -> 0.015754845 | AF16: 1175 | AG16: =AF16/AF$17 -> 0.022720241 | AL16: 1006.76 | AM16: =AL16/AL$17 -> 0.022306071 | AR16: 1054.76 | AS16: =AR16/AR$17 -> 0.022014283 | AT16: 1134.39 | AU16: =AT16/AT$17 -> 0.021368005 | AV16: 1186.14 | AW16: =AV16/AV$17 -> 0.019695738 | AX16: =(AT16/AL16)*AV16 -> 1336.5105 | AY16: =AX16/AX$17 -> 0.021189571 | AZ16: Roadbuilding
B17: Total revenue | D17: =IS!D18 -> 7631 | E17: =IS!E18 -> 9253 | F17: =IS!F18 -> 8925 | G17: =IS!G18 -> 9731 | H17: =IS!H18 -> 35540 | J17: =IS!J18 -> 9112 | K17: =IS!K18 -> 12058 | L17: =IS!L18 -> 11527 | M17: =IS!M18 -> 11327 | N17: =IS!N18 -> 44024 | P17: =IS!P18 -> 9569 | Q17: =IS!Q18 -> 13370 | R17: =IS!R18 -> 14102 | S17: =IS!S18 -> 15536 | T17: =IS!T18 -> 52577 | V17: =IS!V18 -> 12652 | W17: =IS!W18 -> 17387 | X17: =IS!X18 -> 15801 | Y17: =IS!Y18 -> 15412 | Z17: =IS!Z18 -> 61251 | AB17: =IS!AB18 -> 12185 | AC17: =IS!AC18 -> 15235 | AD17: =IS!AD18 -> 13152 | AE17: =IS!AE18 -> 11143 | AF17: =IS!AF18 -> 51716 | AH17: =IS!AH18 -> 8508 | AI17: =IS!AI18 -> 12763 | AJ17: =IS!AJ18 -> 0 | AK17: =IS!AK18 -> 0 | AL17: =SUM(AL12:AL16) -> 45133.9 | AN17: =SUM(AN12:AN16) -> 0 | AO17: =SUM(AO12:AO16) -> 0 | AP17: =SUM(AP12:AP16) -> 0 | AQ17: =SUM(AQ12:AQ16) -> 0 | AR17: =SUM(AR12:AR16) -> 47912.53 | AT17: =SUM(AT12:AT16) -> 53088.25 | AV17: =SUM(AV12:AV16) -> 60223.18 | AX17: =SUM(AX12:AX16) -> 63073.98 | AZ17: Forestry
AZ18: Financial products
B19: Revenue by region: | AZ19: Other
B20: United States (US) | H20: 18996 | I20: =H20/H$26 -> 0.53449634 | N20: 22814 | O20: =N20/N$26 -> 0.51821734 | T20: 28238 | U20: =T20/T$26 -> 0.53707895 | Z20: 34105 | AA20: =Z20/Z$26 -> 0.55680724 | AF20: 30242 | AG20: =AF20/AF$26 -> 0.58477067 | AL20: =AM20*$AL$17 -> 26392.981 | AM20: 0.58477067 | AR20: =AS20*AR$17 -> 28747.518 | AS20: 0.6 | AT20: =AU20*AT$17 -> 31852.95 | AU20: 0.6 | AV20: =AW20*AV$17 -> 36133.908 | AW20: 0.6 | AX20: =AY20*AX$17 -> 37213.648 | AY20: 0.59
B21: Canada (CAN) | H21: 2390 | I21: =H21/H$26 -> 0.067248171 | N21: 3015 | O21: =N21/N$26 -> 0.068485372 | T21: 3902 | U21: =T21/T$26 -> 0.074214961 | Z21: 4287 | AA21: =Z21/Z$26 -> 0.069990694 | AF21: 3900 | AG21: =AF21/AF$26 -> 0.075411865 | AL21: =AM21*$AL$17 -> 3403.6316 | AM21: 0.075411865 | AR21: =AS21*AR$17 -> 3353.8771 | AS21: 0.07 | AT21: =AU21*AT$17 -> 3716.1775 | AU21: 0.07 | AV21: =AW21*AV$17 -> 4215.6226 | AW21: 0.07 | AX21: =AY21*AX$17 -> 4415.1786 | AY21: 0.07
B22: Western Europe (WE) | H22: 5333 | I22: =H22/H$26 -> 0.15005627 | N22: 6429 | O22: =N22/N$26 -> 0.14603398 | T22: 6344 | U22: =T22/T$26 -> 0.12066113 | Z22: 7321 | AA22: =Z22/Z$26 -> 0.11952458 | AF22: 6189 | AG22: =AF22/AF$26 -> 0.11967283 | AL22: =AM22*$AL$17 -> 5401.3015 | AM22: 0.11967283 | AR22: =AS22*AR$17 -> 4312.1277 | AS22: 0.09 | AT22: =AU22*AT$17 -> 4777.9425 | AU22: 0.09 | AV22: =AW22*AV$17 -> 5420.0862 | AW22: 0.09 | AX22: =AY22*AX$17 -> 5676.6582 | AY22: 0.09
B23: Central Europe and CIS (CECIS) | H23: 2072 | I23: =H23/H$26 -> 0.058300506 | N23: 2664 | O23: =N23/N$26 -> 0.060512448 | T23: 2289 | U23: =T23/T$26 -> 0.043536147 | Z23: 2137 | AA23: =Z23/Z$26 -> 0.034889226 | AF23: 1488 | AG23: =AF23/AF$26 -> 0.028772527 | AL23: =AM23*$AL$17 -> 1298.6164 | AM23: 0.028772527 | AR23: =AS23*AR$17 -> 958.2506 | AS23: 0.02 | AT23: =AU23*AT$17 -> 1061.765 | AU23: 0.02 | AV23: =AW23*AV$17 -> 1204.4636 | AW23: 0.02 | AX23: =AY23*AX$17 -> 1261.4796 | AY23: 0.02
B24: Latin America (LA) | H24: 3023 | I24: =H24/H$26 -> 0.085059088 | N24: 4522 | O24: =N24/N$26 -> 0.1027167 | T24: 7339 | U24: =T24/T$26 -> 0.13958575 | Z24: 8197 | AA24: =Z24/Z$26 -> 0.13382639 | AF24: 5538 | AG24: =AF24/AF$26 -> 0.10708485 | AL24: =AM24*$AL$17 -> 4833.1568 | AM24: 0.10708485 | AR24: =AS24*AR$17 -> 6707.7542 | AS24: 0.14 | AT24: =AU24*AT$17 -> 8494.12 | AU24: 0.16 | AV24: =AW24*AV$17 -> 9635.7088 | AW24: 0.16 | AX24: =AY24*AX$17 -> 10091.837 | AY24: 0.16
B25: Asia, Africa, Australia, New Zealand, and Middle East (AAANM) | H25: 3726 | I25: =H25/H$26 -> 0.10483962 | N25: 4580 | O25: =N25/N$26 -> 0.10403416 | T25: 4465 | U25: =T25/T$26 -> 0.084923065 | Z25: 5204 | AA25: =Z25/Z$26 -> 0.084961878 | AF25: 4359 | AG25: =AF25/AF$26 -> 0.084287261 | AL25: =AM25*$AL$17 -> 3804.2128 | AM25: 0.084287261 | AR25: =AS25*AR$17 -> 4038.4159 | AS25: 0.084287261 | AT25: =AU25*AT$17 -> 3185.295 | AU25: 0.06 | AV25: =AW25*AV$17 -> 3613.3908 | AW25: 0.06 | AX25: =AY25*AX$17 -> 4415.1786 | AY25: 0.07
B26: Total revenue | D26: =IS!D18 -> 7631 | E26: =IS!E18 -> 9253 | F26: =IS!F18 -> 8925 | G26: =IS!G18 -> 9731 | H26: =IS!H18 -> 35540 | J26: =IS!J18 -> 9112 | K26: =IS!K18 -> 12058 | L26: =IS!L18 -> 11527 | M26: =IS!M18 -> 11327 | N26: =IS!N18 -> 44024 | P26: =IS!P18 -> 9569 | Q26: =IS!Q18 -> 13370 | R26: =IS!R18 -> 14102 | S26: =IS!S18 -> 15536 | T26: =IS!T18 -> 52577 | V26: =IS!V18 -> 12652 | W26: =IS!W18 -> 17387 | X26: =IS!X18 -> 15801 | Y26: =IS!Y18 -> 15412 | Z26: =IS!Z18 -> 61251 | AB26: =IS!AB18 -> 12185 | AC26: =IS!AC18 -> 15235 | AD26: =IS!AD18 -> 13152 | AE26: =IS!AE18 -> 11143 | AF26: =IS!AF18 -> 51716 | AH26: =IS!AH18 -> 8508 | AI26: =IS!AI18 -> 12763 | AJ26: =IS!AJ18 -> 0 | AK26: =IS!AK18 -> 0 | AL26: =SUM(AL20:AL25) -> 45133.9 | AM26: =SUM(AM20:AM25) -> 1 | AN26: =SUM(AN20:AN25) -> 0 | AO26: =SUM(AO20:AO25) -> 0 | AP26: =SUM(AP20:AP25) -> 0 | AQ26: =SUM(AQ20:AQ25) -> 0 | AR26: =SUM(AR20:AR25) -> 48117.944 | AS26: =SUM(AS20:AS25) -> 1.0042873 | ... AY26: =SUM(AY20:AY25) -> 1
B28: Products:
B29: Production agriculture | H29: 12662 | I29: =H29/H12 -> 0.97685542 | J29: 3726 | K29: 3726 | L29: 3726 | M29: 3726 | N29: 16248 | O29: =N29/N12 -> 0.98419044 | T29: 21685 | U29: =T29/T12 -> 0.98559222 | Z29: 26450 | AA29: =Z29/Z12 -> 0.9873087 | AF29: 20574 | AG29: =AF29/AF12 -> 0.9875204 | AL29: =$AG$29*AL12 -> 16995.957 | AR29: =$AG$29*AR12 -> 17882.019 | AT29: =$AG$29*AT12 -> 20430.424 | AV29: =$AG$29*AV12 -> 23943.321 | AX29: =$AG$29*AX12 -> 24877.11
B30: Small agriculture | H30: 6827 | I30: =H30/H13 -> 0.72914664 | N30: 8619 | O30: =N30/N13 -> 0.7267285 | T30: 10027 | U30: =T30/T13 -> 0.74934609 | Z30: 10122 | AA30: =Z30/Z13 -> 0.72403433 | AF30: 7693 | AG30: =AF30/AF13 -> 0.70134014 | AL30: =$AG$30*AL13 -> 6946.2761 | AR30: =$AG$30*AR13 -> 7482.5629 | AT30: =$AG$30*AT13 -> 8221.7614 | AV30: =$AG$30*AV13 -> 9273.0071 | AX30: =$AG$30*AX13 -> 9634.6544
B31: Turf | H31: 2390 | I31: =H31/H13 -> 0.25526007 | N31: 2853 | O31: =N31/N13 -> 0.24055649 | T31: 3027 | U31: =T31/T13 -> 0.22621628 | Z31: 3505 | AA31: =Z31/Z13 -> 0.25071531 | AF31: 3023 | AG31: =AF31/AF13 -> 0.27559486 | AL31: =$AG$31*AL13 -> 2729.5714 | AR31: =$AG$31*AR13 -> 2940.3078 | AT31: =$AG$31*AT13 -> 3230.7792 | AV31: =$AG$31*AV13 -> 3643.8711 | AX31: =$AG$31*AX13 -> 3785.9821
B32: Construction | C32: =AVERAGE(I32,O32,U32,AA32,AG32) -> 0.44006141 | H32: 3521 | I32: =H32/SUM(H$32:H$35) -> 0.3994781 | N32: 4684 | O32: =N32/SUM(N$32:N$35) -> 0.41813962 | T32: 5864 | U32: =T32/SUM(T$32:T$35) -> 0.47752443 | Z32: 6842 | AA32: =Z32/SUM(Z$32:Z$35) -> 0.47134197 | AF32: 5523 | AG32: =AF32/SUM(AF$32:AF$35) -> 0.43382295 | AL32: =AL$14*$C32 -> 4919.3893 | AR32: =AR$14*$C32 -> 5308.0252 | AT32: =AT$14*$C32 -> 5799.1029 | AV32: =AV$14*$C32 -> 6502.0086 | AX32: =AX$14*$C32 -> 6775.093
B33: Compact Construction | C33: =AVERAGE(I33,O33,U33,AA33,AG33) -> 0.15492922 | H33: 1269 | I33: =H33/SUM(H$32:H$35) -> 0.14397549 | N33: 1489 | O33: =N33/SUM(N$32:N$35) -> 0.13292269 | T33: 1667 | U33: =T33/SUM(T$32:T$35) -> 0.13574919 | Z33: 2451 | AA33: =Z33/SUM(Z$32:Z$35) -> 0.16884817 | AF33: 2459 | AG33: =AF33/SUM(AF$32:AF$35) -> 0.19315058 | AL33: =AL$14*$C33 -> 1731.9336 | AR33: =AR$14*$C33 -> 1868.7578 | AT33: =AT$14*$C33 -> 2041.648 | AV33: =AV$14*$C33 -> 2289.1149 | AX33: =AX$14*$C33 -> 2385.2577
B34: Roadbuilding | C34: =AVERAGE(I34,O34,U34,AA34,AG34) -> 0.29879813 | H34: 2924 | I34: =H34/SUM(H$32:H$35) -> 0.33174495 | N34: 3749 | O34: =N34/SUM(N$32:N$35) -> 0.33467238 | T34: 3441 | U34: =T34/SUM(T$32:T$35) -> 0.28021173 | Z34: 3794 | AA34: =Z34/SUM(Z$32:Z$35) -> 0.26136677 | AF34: 3641 | AG34: =AF34/SUM(AF$32:AF$35) -> 0.28599482 | AL34: =AL$14*$C34 -> 3340.2254 | AR34: =AR$14*$C34 -> 3604.106 | AT34: =AT$14*$C34 -> 3937.5438 | AV34: =AV$14*$C34 -> 4414.8111 | AX34: =AX$14*$C34 -> 4600.2331 | BA34: https://www.mordorintelligence.com/industry-reports/global-precision-farming-market-industry
B35: Forestry | C35: =AVERAGE(I35,O35,U35,AA35,AG35) -> 0.10621123 | H35: 1100 | I35: =H35/SUM(H$32:H$35) -> 0.12480145 | N35: 1280 | O35: =N35/SUM(N$32:N$35) -> 0.11426531 | T35: 1308 | U35: =T35/SUM(T$32:T$35) -> 0.10651466 | Z35: 1429 | AA35: =Z35/SUM(Z$32:Z$35) -> 0.098443097 | AF35: 1108 | AG35: =AF35/SUM(AF$32:AF$35) -> 0.087031655 | AL35: =AL$14*$C35 -> 1187.3216 | AR35: =AR$14*$C35 -> 1281.121 | AT35: =AT$14*$C35 -> 1399.6453 | AV35: =AV$14*$C35 -> 1569.2954 | AX35: =AX$14*$C35 -> 1635.2058 | BA35: https://www.grandviewresearch.com/industry-analysis/precision-farming-market
B36: Financial products | H36: 3720 | N36: 3669 | T36: 3769 | Z36: 5094 | AF36: 6220 | AL36: =SUM(AL12:AL14)-SUM(AL29:AL35)+AL15 -> 6276.4656 | AR36: =SUM(AR12:AR14)-SUM(AR29:AR35)+AR15 -> 6490.87 | AT36: =SUM(AT12:AT14)-SUM(AT29:AT35)+AT15 -> 6892.955 | AV36: =SUM(AV12:AV14)-SUM(AV29:AV35)+AV15 -> 7401.6109 | AX36: =SUM(AX12:AX14)-SUM(AX29:AX35)+AX15 -> 8043.9324 | BA36: https://www.alliedmarketresearch.com/precision-agriculture-market
B37: Other | H37: 1127 | N37: 1433 | T37: 1789 | Z37: 1564 | AF37: 1475 | AL37: =AL16 -> 1006.76 | AR37: =AR16 -> 1054.76 | AT37: =AT16 -> 1134.39 | AV37: =AV16 -> 1186.14 | AX37: =AX16 -> 1336.5105 | BA37: https://investor.deere.com/home/
A39: x | B39: Notes & Forecasts
B44: PPA\
B45: Regional Forecast | H45: Over the next years I expect US and Latin America´s share of total Rev to grow, mainly due to the second effect of tarrifs. The Brazillian and Argentine market are positioned to capatalize, with US trading partners opting to shift their business to these countries. In terms of precision farming and advanced agricultural machinery, developed countries seem more likely to invest, and Deere invests into these technologies. I´m expecting US and WE markets to continue to grow a bit in share due to these technologies, however I expect WE to decrease in share due to trade agreements
B46: PPA & SAT | H46: Expect a drop this year and potentially next year due to the trade wars as well as less gov aid, however when that will settle down, larger farms will be needing better equipment to deal witht the ramifications, thus in the years after I expect sales to go back up and having to catch up with demand
B51: 2025/2026/2027 PPA/SAT/CF Forecast | H51: Mean consensus from following firms: Oppenheimer,Truist Securities,Melius Research LLC,JP Morgan,Evercore ISI,Raymond James,D.A. Davidson,Baird,Bernstein,HSBC,Morningstar,Barclays,BMO Capital Markets,Daiwa Securities,Wolfe Research
B52: 2025/2026/2027 FS/Other Forecast | H52: Mean consensus from following firms: Oppenheimer,JP Morgan,D.A. Davidson,BMO Capital Markets,Daiwa Securities,Wolfe Research
B53: 2028 PPA/SAT/CF Forecast | H53: Mean consensus from following firms: Melius Research LLC,Bernstein,HSBC,Morningstar,BMO Capital Markets, D.A. Davidson
B54: 2028 FS/Other Forecast | H54: Mean consensus: BMA Capital Markets, D.A. Davidson
B55: 2029 Forecast
B71: Notes from Grand Review | N71: Key factors that are driving the agriculture equipment market growth include rising mechanization in farm practices and government support in form of subsidies, especially in developing economies.
B72: Agricultural Machinery Manufacturing | N72: Investing in precision agriculture systems
B73: US Segment | N73: Held biggest share in global revenue - 37~%
B74: Asia-Pacific agriculture equipment industry | N74: China also transitioning to precision farming
N75: India - shift to | T75: Help from government
I76: As farmers shift from traditional staple crops like wheat and rice to fruits, vegetables, pulses, and cash crops, there is a growing need for specialized machinery to suit different soil conditions and crop requirements. Equipment such as transplanters, sprayers, and drip irrigation systems is becoming more prevalent in areas where farmers are intensifying cultivation and adopting modern practices. | N76: high-end machinery via subscription or rental, reducing the financial burden on smaller farms
B77: EU | N77: Digital agriculture and data integration are driving the UK market growth.
N78: As global demand for sustainably produced, high-quality food continues to rise, German farmers’ reliance on cutting-edge agricultural equipment
B82: Notes from Mordor Intelligence
B83: Agricultural Machinery Manufacturing
B84: Shrinking agricultural labor pool in developed and emerging economies | N84: making mechanization not merely an efficiency play but an operational necessity
B85: Rapid integration of precision-agriculture and IoT platforms | N85: Adoption spreads fastest in regions with high broadband penetration, but recent satellite connectivity pilots bridge gaps in rural coverage. Interoperability standards still lag, generating vendor lock-in that favors incumbents with end-to-end ecosystems.
N86: These switching costs anchor market position, allowing Original Equipment Manufacturers (OEMs) to extract higher lifetime value across equipment generations
B87: Escalating government subsidies and tax incentives for farm mechanization | N87: India’s Sub-Mission on Agricultural Mechanization underwrites up to 50% of the purchase cost
N88: US -USD 1.5 billion in 2024 specifically for climate-smart equipment.
N89: The agricultural machinery market thus experiences policy-driven segmentation in which compliance-ready models command premium pricing
B90: Expansion of contract-farming and equipment-as-a-service models | N90: Equipment-as-a-service platforms translate prohibitively high capital costs into manageable per-hour fees, unlocking advanced capabilities for smallholders.
N91: The agricultural machinery market thus expands its customer base to include service entrepreneurs
B92: Rising capital expenditure for high-end smart machines | N92: corporate farms modernize quickly while resource-limited growers postpone upgrades, widening yield differentials across farm sizes.
B93: Cyber-security and data-ownership concerns in connected equipment | N93: These risks create adoption hesitancy that tempers near-term growth in the agricultural machinery market for connected solutions.
B95: Geography Analysis | N95: Asia-Pacific retained a 35.40% agricultural machinery market share in 2024
N96: North America posts the fastest CAGR at 7.8% through 2030 | AA96: Africa and Asia show highest CAGR next
N97: United States skews toward high-horsepower segments
B99: Competitive Landscape | N99: Incumbents underscore differentiation through bundled digital agronomy services that lock customers into proprietary ecosystems. Dealer networks evolve into data hubs, providing firmware updates and predictive maintenance that extend equipment life and recurring revenue.
B109: Notes from Bloomberg Intelligence - Global Agriculture Report | BD109: Check this
B110: Ag Machinery Sales Declining: Large tractor and combine sales for Deere, CNH and AGCO are poised to drop 25% or more in North America, but Latin America could provide some offset if Brazil and Argentina grab export share from the US | BD110: DE holding investor
B111: s Brazil to seize a bigger share of agricultural exports | BD111: If true, what is DE strategy?
B112: 4Q25: North American crop input sales decline year over year, portending weakness persisting into the first half of 2026
B113: Q26: North American large ag-equipment sales data will likely confirm weakness through 2026
B115: Brazil, Argentina, Paraguay, Uruguay, Canada and Russia, which account for 70% of global soybean exports, could hypothetically supplant the 22.1 million metric tons of soybeans the US shipped to China.
B116: A more contentious trade environment and further decoupling with China run the risk of a lower_x0002_for-longer agricultural-equipment cycle at Deere, CNH and AGCO if
B117: In North America, where large ag-machinery retail sales fell 16% last year, demand could drop 25- 30% in 2025 and remain relatively subdued in 2026.
B118: Deere and CNH are most exposed to North America, while AGCO generates 58% of revenue from Europe and the Middle East.
B119: Brazil will likely benefit from the Trump administration's trade policy, as China could increasingly rely on South American crops to displace US agricultural imports.
B120: CNH has the greatest exposure to South America vs. peers, at about 17% of consolidated 2024 revenue, down from 20% in 2022. South America represented more than 11% of AGCO revenue, followed by Deere’s 11%, as seen in Figure 12.

Sheet Trading Comps
B7: ="in "&IF(Inputs!$R$18="k","thousands",IF(Inputs!$R$18="MLN","millions","billions")&" of "&Inputs!$R$17) -> in millions of USD | D7: Current | E7: % of | I7: Enterprise Value / | S7: LTM | T7: Net | V7: Price / | Z7: LTM
D8: Share | E8: 52-week | F8: Equity | G8: Enterprise | I8: LTM | J8: 2025 | K8: 2026 | L8: LTM | M8: 2025E | N8: 2026E | O8: LTM | P8: 2025E | Q8: 2026E | S8: EBITDA | T8: Debt / | V8: LTM | W8: 2025E | X8: 2026E | Z8: EPS
B9: Company | C9: Ticker | D9: Price (USD) | E9: High | F9: Value | G9: Value | I9: Sales | J9: Sales | K9: Sales | L9: EBITDA | M9: EBITDA | N9: EBITDA | O9: EBIT | P9: EBIT | Q9: EBIT | S9: Margin | T9: EBITDA | V9: EPS | W9: EPS | X9: EPS | Z9: Growth
B15: =+Inputs!B21 -> AGCO CORP | C15: AGCO US | D15: 109.3 | E15: 0.90211291 | F15: 8.1559908e+09 | G15: 10295.065 | I15: 1.0120885 | J15: 1.0447979 | K15: 1.0004437 | L15: 9.8297452 | M15: 10.243846 | N15: 8.5935437 | O15: 14.032896 | P15: 14.63123 | Q15: 11.990311 | S15: 0.10296182 | T15: 8.3017958 | V15: 0.34780008 | W15: 0.30563562 | X15: 0.23289625 | Z15: =(_xll.BQL(Inputs!$E21, "EARN_FOR_COMMON(fpr = 2028, fpt = a, ae = e, fa_adjusted = y, fs = mr)")/_xll.BQL(Inputs!$E21, "EARN_FOR_COMMON(fpr = 2025, fpt = a, ae = e, fa_adjusted = y, fs = mr)"))^(1/3)-1 -> 0.19927279
B16: =+Inputs!B22 -> CATTERPILLAR INC | C16: CAT US | D16: 450.66 | E16: 0.99628598 | F16: 2.1112471e+11 | G16: 188322.2 | I16: 2.9826605 | J16: 3.0582475 | K16: 2.8637984 | L16: 13.55031 | M16: 14.65853 | N16: 12.953988 | O16: 16.087665 | P16: 17.428865 | Q16: 15.076511 | S16: 0.22011752 | T16: 2.9738724 | V16: 0.048693679 | W16: 0.052890642 | X16: 0.046017595 | Z16: =(_xll.BQL(Inputs!$E22, "EARN_FOR_COMMON(fpr = 2028, fpt = a, ae = e, fa_adjusted = y, fs = mr)")/_xll.BQL(Inputs!$E22, "EARN_FOR_COMMON(fpr = 2025, fpt = a, ae = e, fa_adjusted = y, fs = mr)"))^(1/3)-1 -> 0.15486087
B17: =+Inputs!B23 -> CNH INDUSTRIAL N | C17: CNH US | D17: 10.85 | E17: 0.76033637 | F17: 1.3571398e+10 | G17: 19214.628 | I17: 1.0634029 | J17: 1.2771895 | K17: 1.2025504 | L17: 4.8181113 | M17: 15.285425 | N17: 11.840984 | O17: 5.8922502 | P17: 21.320323 | Q17: 15.608213 | S17: 0.2207095 | T17: 6.9758186 | V17: 0.01289211 | W17: 0.014203636 | X17: 0.010833465 | Z17: =(_xll.BQL(Inputs!$E23, "EARN_FOR_COMMON(fpr = 2028, fpt = a, ae = e, fa_adjusted = y, fs = mr)")/_xll.BQL(Inputs!$E23, "EARN_FOR_COMMON(fpr = 2025, fpt = a, ae = e, fa_adjusted = y, fs = mr)"))^(1/3)-1 -> 0.31805284
B18: =+Inputs!B24 -> TEREX CORP | C18: TEX US | D18: 52.6 | E18: 0.89669281 | F18: 3450560000 | G18: 5249.181 | I18: 1.0155119 | J18: 0.96305609 | K18: 0.92277805 | L18: 8.3056661 | M18: 7.7650607 | N18: 7.1886894 | O18: 10.477407 | P18: 9.5145568 | Q18: 8.4732542 | S18: 0.12226736 | T18: 5.1448413 | V18: 0.17872588 | W18: 0.1648433 | X18: 0.14454159 | Z18: =(_xll.BQL(Inputs!$E24, "EARN_FOR_COMMON(fpr = 2028, fpt = a, ae = e, fa_adjusted = y, fs = mr)")/_xll.BQL(Inputs!$E24, "EARN_FOR_COMMON(fpr = 2025, fpt = a, ae = e, fa_adjusted = y, fs = mr)"))^(1/3)-1 -> #VALUE!
B19: =+Inputs!B25 -> ALAMO GROUP | C19: ALG US | D19: 201.74 | E19: 0.8647606 | F19: 2.443255e+09 | G19: 2645.0214 | I19: 1.65661 | J19: 1.6262044 | K19: 1.5329014 | L19: 11.479081 | M19: 11.148668 | N19: 10.114805 | O19: 16.016358 | P19: 14.355611 | Q19: 12.777881 | S19: 0.14431556 | T19: 0.98141017 | V19: 1.7144681 | W19: 1.563876 | X19: 1.3330837 | Z19: =(_xll.BQL(Inputs!$E25, "EARN_FOR_COMMON(fpr = 2028, fpt = a, ae = e, fa_adjusted = y, fs = mr)")/_xll.BQL(Inputs!$E25, "EARN_FOR_COMMON(fpr = 2025, fpt = a, ae = e, fa_adjusted = y, fs = mr)"))^(1/3)-1 -> #VALUE!
B20: =+Inputs!H21 -> KUBOTA CORP-ADR | C20: KUBTY US | D20: 62.415 | E20: 0.83275517 | F20: 1.4366645e+10 | G20: 3979719.1 | I20: 1.3762963 | J20: 1.3434723 | K20: 1.2848063 | L20: 10.298947 | M20: 10.89237 | N20: 10.001498 | O20: 15.206367 | P20: 16.349267 | Q20: 14.730084 | S20: 0.13363466 | T20: 5.5416301 | V20: 0.00034805382 | W20: 0.00036982861 | X20: 0.00032669536 | Z20: =(_xll.BQL(Inputs!$K21, "EARN_FOR_COMMON(fpr = 2028, fpt = a, ae = e, fa_adjusted = y, fs = mr)")/_xll.BQL(Inputs!$K21, "EARN_FOR_COMMON(fpr = 2025, fpt = a, ae = e, fa_adjusted = y, fs = mr)"))^(1/3)-1 -> 0.10901522
B21: =+Inputs!H22 -> KOMATSU LTD-ADR | C21: KMTUY US | D21: 35.59 | E21: 0.95492353 | F21: 3.3844422e+10 | G21: 5483123.8 | I21: 1.3524945 | J21: 1.3524945 | K21: 1.3864023 | L21: 6.7888758 | M21: 7.0411057 | N21: 7.4923966 | O21: 8.4835003 | P21: 8.9817617 | Q21: 9.8017535 | S21: 0.19922217 | T21: 1.7801182 | V21: 8.3667242e-05 | W21: 8.9560783e-05 | X21: 9.6090087e-05 | Z21: =(_xll.BQL(Inputs!$K22, "EARN_FOR_COMMON(fpr = 2028, fpt = a, ae = e, fa_adjusted = y, fs = mr)")/_xll.BQL(Inputs!$K22, "EARN_FOR_COMMON(fpr = 2025, fpt = a, ae = e, fa_adjusted = y, fs = mr)"))^(1/3)-1 -> 0.032789428
B23: Mean | I23: =AVERAGE(I15:I21) -> 1.4941521 | J23: =AVERAGE(J15:J21) -> 1.5236375 | K23: =AVERAGE(K15:K21) -> 1.4562401 | L23: =AVERAGE(L15:L21) -> 9.2958195 | M23: =AVERAGE(M15:M21) -> 11.005001 | N23: =AVERAGE(N15:N21) -> 9.7408435 | O23: =AVERAGE(O15:O21) -> 12.313778 | P23: =AVERAGE(P15:P21) -> 14.654516 | ... Y23: =AVERAGE(Y15:Y21) -> #DIV/0! | Z23: =AVERAGE(Z15:Z17,Z20:Z21) -> 0.16279823
B24: Median | I24: =MEDIAN(I15:I21) -> 1.3524945 | J24: =MEDIAN(J15:J21) -> 1.3434723 | K24: =MEDIAN(K15:K21) -> 1.2848063 | L24: =MEDIAN(L15:L21) -> 9.8297452 | M24: =MEDIAN(M15:M21) -> 10.89237 | N24: =MEDIAN(N15:N21) -> 10.001498 | O24: =MEDIAN(O15:O21) -> 14.032896 | P24: =MEDIAN(P15:P21) -> 14.63123 | ... Y24: =MEDIAN(Y15:Y21) -> #NUM! | Z24: =MEDIAN(Z15:Z17,Z20:Z21) -> 0.15486087
B35: Mean
B36: Median
B47: Mean
B48: Median
B50: Overall
B53: Mean | I53: =AVERAGE(I41:I45,I20:I34,I15:I19) -> 1.4784124 | J53: =AVERAGE(J41:J45,J20:J34,J15:J19) -> 1.5036191 | K53: =AVERAGE(K41:K45,K20:K34,K15:K19) -> 1.4371919 | L53: =AVERAGE(L41:L45,L20:L34,L15:L19) -> 9.3551446 | M53: =AVERAGE(M41:M45,M20:M34,M15:M19) -> 10.992486 | N53: =AVERAGE(N41:N45,N20:N34,N15:N19) -> 9.7698052 | O53: =AVERAGE(O41:O45,O20:O34,O15:O19) -> 12.504791 | P53: =AVERAGE(P41:P45,P20:P34,P15:P19) -> 14.651929 | Q53: =AVERAGE(Q41:Q45,Q20:Q34,Q15:Q19) -> 12.652527 | S53: =AVERAGE(S41:S45,S20:S34,S15:S19) -> 0.16120695 | T53: =AVERAGE(T41:T45,T20:T34,T15:T19) -> 4.5969807 | V53: =AVERAGE(V41:V45,V20:V34,V15:V19) -> 0.29785632 | W53: =AVERAGE(W41:W45,W20:W34,W15:W19) -> 0.27278576 | X53: =AVERAGE(X41:X45,X20:X34,X15:X19) -> 0.22959502 | Z53: =AVERAGE(Z41:Z45,Z27:Z34,Z15:Z17) -> 0.22406217
B54: Median | I54: =MEDIAN(I41:I45,I20:I33,I15:I19) -> 1.3524945 | J54: =MEDIAN(J41:J45,J20:J33,J15:J19) -> 1.3434723 | K54: =MEDIAN(K41:K45,K20:K33,K15:K19) -> 1.2848063 | L54: =MEDIAN(L41:L45,L20:L33,L15:L19) -> 9.8297452 | M54: =MEDIAN(M41:M45,M20:M33,M15:M19) -> 10.89237 | N54: =MEDIAN(N41:N45,N20:N33,N15:N19) -> 10.001498 | O54: =MEDIAN(O41:O45,O20:O33,O15:O19) -> 14.032896 | P54: =MEDIAN(P41:P45,P20:P33,P15:P19) -> 14.63123 | Q54: =MEDIAN(Q41:Q45,Q20:Q33,Q15:Q19) -> 12.777881 | S54: =MEDIAN(S41:S45,S20:S33,S15:S19) -> 0.14431556 | T54: =MEDIAN(T41:T45,T20:T33,T15:T19) -> 5.1448413 | V54: =MEDIAN(V41:V45,V20:V33,V15:V19) -> 0.048693679 | W54: =MEDIAN(W41:W45,W20:W33,W15:W19) -> 0.052890642 | X54: =MEDIAN(X41:X45,X20:X33,X15:X19) -> 0.046017595 | Z54: =MEDIAN(Z41:Z45,Z27:Z33,Z15:Z17) -> 0.19927279
B56: High | I56: =MAX(I41:I45,I20:I33,I15:I19) -> 2.9826605 | J56: =MAX(J41:J45,J20:J33,J15:J19) -> 3.0582475 | K56: =MAX(K41:K45,K20:K33,K15:K19) -> 2.8637984 | L56: =MAX(L41:L45,L20:L33,L15:L19) -> 13.55031 | M56: =MAX(M41:M45,M20:M33,M15:M19) -> 15.285425 | N56: =MAX(N41:N45,N20:N33,N15:N19) -> 12.953988 | O56: =MAX(O41:O45,O20:O33,O15:O19) -> 16.087665 | P56: =MAX(P41:P45,P20:P33,P15:P19) -> 21.320323 | ... T56: =MAX(T41:T45,T20:T33,T15:T19) -> 8.3017958 | V56: =MAX(V41:V45,V20:V33,V15:V19) -> 1.7144681 | W56: =MAX(W41:W45,W20:W33,W15:W19) -> 1.563876 | X56: =MAX(X41:X45,X20:X33,X15:X19) -> 1.3330837 | Z56: =MAX(Z41:Z45,Z27:Z33,Z15:Z17) -> 0.31805284
B57: Low | I57: =MIN(I41:I45,I20:I33,I15:I19) -> 1.0120885 | J57: =MIN(J41:J45,J20:J33,J15:J19) -> 0.96305609 | K57: =MIN(K41:K45,K20:K33,K15:K19) -> 0.92277805 | L57: =MIN(L41:L45,L20:L33,L15:L19) -> 4.8181113 | M57: =MIN(M41:M45,M20:M33,M15:M19) -> 7.0411057 | N57: =MIN(N41:N45,N20:N33,N15:N19) -> 7.1886894 | O57: =MIN(O41:O45,O20:O33,O15:O19) -> 5.8922502 | P57: =MIN(P41:P45,P20:P33,P15:P19) -> 8.9817617 | ... T57: =MIN(T41:T45,T20:T33,T15:T19) -> 0.98141017 | V57: =MIN(V41:V45,V20:V33,V15:V19) -> 8.3667242e-05 | W57: =MIN(W41:W45,W20:W33,W15:W19) -> 8.9560783e-05 | X57: =MIN(X41:X45,X20:X33,X15:X19) -> 9.6090087e-05 | Z57: =MIN(Z41:Z45,Z27:Z33,Z15:Z17) -> 0.15486087

Sheet Peers
B7: Peers
A12: x | B12: Growth | C12: =C21 -> DEERE & CO | D12: {=TRANSPOSE(Inputs!B21:B25)} -> AGCO CORP | E12: CATTERPILLAR INC | F12: CNH INDUSTRIAL N | G12: TEREX CORP | H12: ALAMO GROUP | I12: {=TRANSPOSE(Inputs!H21:H22)} -> KUBOTA CORP-ADR | J12: KOMATSU LTD-ADR
B14: Revenue (LTM) | C14: -0.2097 | D14: -0.2427 | E14: -0.0487 | F14: -0.2172 | G14: -0.0035 | H14: -0.049 | I14: -0.0612 | J14: X
B15: Revenue (3-yr CAGR) | C15: =(51716/52577)^(1/3)-1 -> -0.0054887317 | D15: =(11661900/12651400)^(1/3)-1 -> -0.026781755 | E15: =(64809/59427)^(1/3)-1 -> 0.029320221 | F15: =(19836000/23551000)^(1/3)-1 -> -0.055616808 | G15: =(5127/4418)^(1/3)-1 -> 0.050862437 | H15: =(1628513/1513616)^(1/3)-1 -> 0.024688448 | I15: =(20291160/18008610)^(1/3)-1 -> 0.040580207 | J15: X
B16: Gross profit (LTM) | C16: -0.184 | D16: -0.2988 | E16: -0.0786 | F16: -0.2112 | G16: -0.1846 | H16: -0.0881 | I16: -0.0475 | J16: X
B17: EBIT (LTM) | C17: -0.2743 | D17: -0.93 | E17: -0.1527 | F17: -0.2727 | G17: -0.4079 | H17: -0.1018 | I17: -0.2852 | J17: X
B18: EBITDA (LTM) | C18: -0.2574 | D18: -0.6991 | E18: -0.1277 | F18: -0.2539 | G18: -0.2707 | H18: -0.0637 | I18: -0.1284 | J18: X
B19: FCF (LTM) | C19: 0.074739141 | D19: -0.49299145 | E19: -0.099356683 | F19: #VALUE! | G19: -0.43089431 | H19: 0.9782355 | I19: #VALUE! | J19: 0.34284026
A21: x | B21: Margins | C21: DEERE & CO | D21: =D12 -> AGCO CORP | E21: =E12 -> CATTERPILLAR INC | F21: =F12 -> CNH INDUSTRIAL N | G21: =G12 -> TEREX CORP | H21: =H12 -> ALAMO GROUP | I21: =I12 -> KUBOTA CORP-ADR | J21: =J12 -> KOMATSU LTD-ADR
B23: Gross margin | C23: 0.40492304 | D23: 0.24859585 | E23: 0.35988829 | F23: 0.32698125 | G23: 0.20830895 | H23: 0.25329119 | I23: 0.30765701 | J23: 0.32218707
B24: EBIT margin | C24: 0.24274886 | D24: -0.010469992 | E24: 0.20170038 | F24: 0.18814277 | G24: 0.10259411 | H24: 0.10120153 | I24: 0.1046441 | J24: 0.16010277
B25: EBITDA margin | C25: 0.26591196 | D25: 0.036678759 | E25: 0.21701326 | F25: 0.21971332 | G25: 0.097504353 | H25: 0.14488863 | I25: 0.13004013 | J25: 0.19779028
B26: Net margin | C26: 0.13728827 | D26: -0.036426311 | E26: 0.16652008 | F26: 0.062815084 | G26: 0.065340355 | H26: 0.071187642 | I26: 0.076397723 | J26: 0.10702089
B27: SG&A margin | C27: #VALUE! | D27: 0.11985183 | E27: 0.10287151 | F27: 0.086307723 | G27: 0.10571484 | H27: 0.14212536 | I27: 0.16086266 | J27: 0.13360897
B28: R&D margin | C28: 0.050796723 | D28: 0.045034949 | E28: 0.032990703 | F28: 0.047650672 | G28: #VALUE! | H28: #VALUE! | I28: #VALUE! | J28: #VALUE!
A30: x | B30: Returns | C30: DEERE & CO | D30: =D21 -> AGCO CORP | E30: =E21 -> CATTERPILLAR INC | F30: =F21 -> CNH INDUSTRIAL N | G30: =G21 -> TEREX CORP | H30: =H21 -> ALAMO GROUP | I30: =I21 -> KUBOTA CORP-ADR | J30: =J21 -> KOMATSU LTD-ADR
B32: ROIC | C32: 0.0838383 | D32: 0.037641709 | E32: 0.15931688 | F32: 0.06848172 | G32: 0.088644543 | H32: 0.096869642 | I32: 0.040713577 | J32: 0.10192899
B33: CROIC | C33: 0.050127327 | D33: 0.044171085 | E33: 0.15075635 | F33: 0.022368421 | G33: 0.04145646 | H33: 0.14434625 | I33: 0.019935633 | J33: 0.068127943
B34: ROCE | C34: 2.0733278 | D34: -0.030751794 | E34: 0.5083019 | F34: 0.11082405 | G34: 0.24660103 | H34: 0.18039286 | I34: 0.158497 | J34: 0.24881909
B35: RONA | C35: 0.54761178 | D35: -0.030201093 | E35: 0.6705653 | F35: 0.48043254 | G35: 0.2871179 | H35: 0.16185353 | I35: 0.11520546 | J35: 0.19645856
B36: ROE | C36: 0.21589236 | D36: 0.024226798 | E36: 0.52733928 | F36: 0.10792735 | G36: 0.094486526 | H36: 0.11301735 | I36: 0.069996936 | J36: 0.13444477
B37: ROA | C37: 0.048289421 | D37: 0.0076838215 | E37: 0.10868301 | F37: 0.018780093 | G37: 0.036046921 | H37: 0.077288984 | I37: 0.029304755 | J37: 0.070862918
A39: x | B39: Efficiency | C39: DEERE & CO | D39: =D30 -> AGCO CORP | E39: =E30 -> CATTERPILLAR INC | F39: =F30 -> CNH INDUSTRIAL N | G39: =G30 -> TEREX CORP | H39: =H30 -> ALAMO GROUP | I39: =I30 -> KUBOTA CORP-ADR | J39: =J30 -> KOMATSU LTD-ADR
B41: Asset turnover | C41: 0.41205984 | D41: 0.78474499 | E41: 0.72715233 | F41: 0.41231773 | G41: 1.0409304 | H41: 1.0423274 | I41: 0.4923426 | J41: 0.68226992
B42: Net operating asset turnover | C42: 1.5493574 | D42: 1.5045089 | E42: 1.5480843 | F42: 1.5770393 | G42: 1.9538872 | H42: 1.6056375 | I42: 0.89219734 | J42: 0.98491644
B43: Fixed asset turnover | C43: 3.018991 | D43: 4.9424712 | E43: 4.7691669 | F43: 4.7947459 | G43: 7.8526396 | H43: 8.937691 | I43: 3.4911776 | J43: 4.0704799
B44: Revenue per employee thsnd of USD | C44: =51716000/75800 -> 682.26913 | D44: =11661900/24000 -> 485.9125 | E44: =64800000/112900 -> 573.95926 | F44: =19836000/35850 -> 553.30544 | G44: =5127000/11400 -> 449.73684 | H44: =1628513/3750 -> 434.27013 | I44: =20291160/52094 -> 389.5105 | J44: =27611130/65738 -> 420.0178
B45: EBIT per employee thsnd of USD | C45: =9039000/75800 -> 119.24802 | D45: =122100/24000 -> 5.0875 | E45: =13072000/112900 -> 115.78388 | F45: =3068000/35850 -> 85.578801 | G45: =526000/11400 -> 46.140351 | H45: =164808/3750 -> 43.9488 | I45: =2255610/52094 -> 43.298844 | J45: =4420620/65738 -> 67.246037
A47: x | B47: Working Capital | C47: DEERE & CO | D47: =D39 -> AGCO CORP | E47: =E39 -> CATTERPILLAR INC | F47: =F39 -> CNH INDUSTRIAL N | G47: =G39 -> TEREX CORP | H47: =H39 -> ALAMO GROUP | I47: =I39 -> KUBOTA CORP-ADR | J47: =J39 -> KOMATSU LTD-ADR
B49: DSO | C49: 55.592906 | D49: 47.931794 | E49: 112.1147 | F49: 481.79838 | G49: 57.316792 | H49: 85.126211 | I49: 207.55354 | J49: 112.17662
B50: DIO | C50: 104.69399 | D50: 156.3067 | E50: 156.91174 | F50: 166.85586 | G50: 107.94662 | H50: 115.85036 | I50: 126.42069 | J50: 205.55986
B51: DPO | C51: 38.608118 | D51: 53.4064 | E51: 68.479934 | F51: 84.707727 | G51: 63.436037 | H51: 33.222361 | I51: 52.350077 | J51: 43.855528
B52: CCC | C52: 96.227493 | D52: 128.06526 | E52: 185.35945 | F52: 494.6825 | G52: 89.299968 | H52: 154.97829 | I52: 259.05175 | J52: 256.01051
B53: Working capital intensity | C53: -0.22493923 | D53: 0.20153164 | E53: 0.16909517 | F53: 1.6497593 | G53: 0.26162701 | H53: 0.44956963 | I53: 0.41403627 | J53: 0.42374316
B54: Cash conversion ratio | C54: 0.73530349 | D54: -5.6502867 | E54: 0.92067013 | F54: 0.52733119 | G54: 0.61977186 | H54: 1.272863 | I54: 0.89370034 | J54: 0.78701465
B55: CFO margin | C55: 0.17849408 | D55: 0.059158456 | E55: 0.18569952 | F55: 0.099213551 | G55: 0.063584942 | H55: 0.12881567 | I55: 0.093520464 | J55: 0.12600322
A57: x | B57: Leverage & Coverage | C57: DEERE & CO | D57: =D47 -> AGCO CORP | E57: =E47 -> CATTERPILLAR INC | F57: =F47 -> CNH INDUSTRIAL N | G57: =G47 -> TEREX CORP | H57: =H47 -> ALAMO GROUP | I57: =I47 -> KUBOTA CORP-ADR | J57: =J47 -> KOMATSU LTD-ADR
B59: Net debt / EBITDA | C59: 0.20050783 | D59: 6.2007505 | E59: 0.47088016 | F59: 0.72619647 | G59: 4.4027778 | H59: 0.12266563 | I59: 5.0074676 | J59: 1.2203046
B60: Net debt / FCF | C60: 0.40099345 | D60: 7.4642616 | E60: 0.27721088 | F60: 2.1879795 | G60: 12.328042 | H60: 0.22449874 | I60: 20.291459 | J60: 2.6826239
B61: Interest coverage | C61: 3.7497013 | D61: -0.76647834 | E61: 25.53125 | F61: 2.3165736 | G61: 5.9101124 | H61: 8.0206346 | I61: 55.815385 | J61: 11.409609
B62: Debt / capital | C62: 0.74063221 | D62: 0.41147099 | E62: 0.66679771 | F62: 0.7776251 | G62: 0.59736264 | H62: 0.18994091 | I62: 0.46094848 | J62: 0.26737209
B63: Short term debt / total debt | C63: 0.33964224 | D63: 0.16298733 | E63: 0.28712414 | F63: 0 | G63: 0.012877116 | H63: 0.08986924 | I63: 0.3955187 | J63: 0.55197747
A65: x | B65: Liquidity | C65: DEERE & CO | D65: =D57 -> AGCO CORP | E65: =E57 -> CATTERPILLAR INC | F65: =F57 -> CNH INDUSTRIAL N | G65: =G57 -> TEREX CORP | H65: =H57 -> ALAMO GROUP | I65: =I57 -> KUBOTA CORP-ADR | J65: =J57 -> KOMATSU LTD-ADR
B67: Current ratio | C67: 0.7227655 | D67: 1.3429169 | E67: 1.4155305 | F67: 13.442485 | G67: 2.1621622 | H67: 4.5058037 | I67: 1.6151435 | J67: 1.9997472
B68: Quick ratio | C68: 0.37811926 | D68: 0.49140094 | E68: 0.79747149 | F68: 11.083543 | G68: 0.96085741 | H68: 2.6422029 | I68: 1.0837899 | J68: 1.0063164
B69: Cash ratio | C69: 0.23222944 | D69: 0.16014114 | E69: 0.21346678 | F69: 1.3396306 | G69: 0.36160298 | H69: 1.0365984 | I69: 0.16623689 | J69: 0.23376886
A71: x | B71: Cash Deployment | C71: DEERE & CO | D71: =D65 -> AGCO CORP | E71: =E65 -> CATTERPILLAR INC | F71: =F65 -> CNH INDUSTRIAL N | G71: =G65 -> TEREX CORP | H71: =H65 -> ALAMO GROUP | I71: =I65 -> KUBOTA CORP-ADR | J71: =J65 -> KOMATSU LTD-ADR
B73: Capex intensity | C73: 0.092853276 | D73: 0.033725208 | E73: 0.049607308 | F73: 0.05979028 | G73: 0.02672128 | H73: 0.015490205 | I73: 0.070947302 | J73: 0.050154773
B74: Capex / depreciation | C74: 2.2672332 | D74: 1.1839253 | E74: 1.4932652 | F74: 1.9603306 | G74: 1.6707317 | H74: 0.4752091 | I74: 1.7764837 | J74: 1.2628831
B75: R&D capitalization rate | C75: #VALUE! | D75: #VALUE! | E75: #VALUE! | F75: #VALUE! | G75: #VALUE! | H75: #VALUE! | I75: #VALUE! | J75: #VALUE!
B76: R&D capitalization test | C76: #VALUE! | D76: #VALUE! | E76: #VALUE! | F76: #VALUE! | G76: #VALUE! | H76: #VALUE! | I76: #VALUE! | J76: #VALUE!
B77: Dividend payout | C77: 0.22857465 | D77: #VALUE! | E77: 0.24939316 | F77: 0.47301766 | G77: 0.136 | H77: 0.10732338 | I77: 0.25251153 | J77: 0.39949141
B78: FCF payout | C78: 1.2827313 | D78: 0.99472468 | E78: 1.2153401 | F78: 1.6472807 | G78: 0.55152481 | H78: 0.056985145 | I78: 1.0675532 | J78: 0.88900524
B79: Buybacks as % CFO | C79: 0.43408081 | D79: 0.03188868 | E79: 0.64287495 | F79: 0.35670732 | G79: 0.15030675 | H79: 0.0094004138 | I79: 0.17726635 | J79: 0.19577622
A81: x | B81: Earnings Quality | C81: DEERE & CO | D81: =D71 -> AGCO CORP | E81: =E71 -> CATTERPILLAR INC | F81: =F71 -> CNH INDUSTRIAL N | G81: =G71 -> TEREX CORP | H81: =H71 -> ALAMO GROUP | I81: =I71 -> KUBOTA CORP-ADR | J81: =J71 -> KOMATSU LTD-ADR
B83: Cash/earnings conversion | C83: 8.5248603 | D83: 7.5771554 | E83: 5.5624242 | F83: 10.837004 | G83: 4.1396825 | H83: 6.5864364 | I83: 7.1032434 | J83: 6.0593673
B84: FCF / net income | C84: 4.0901967 | D84: 3.2575508 | E84: 4.076492 | F84: 4.3061674 | G84: 2.4 | H84: 5.8017268 | I84: 2.5411211 | J84: 3.6474751
A86: x | B86: Per Share & Dilution | C86: DEERE & CO | D86: =D81 -> AGCO CORP | E86: =E81 -> CATTERPILLAR INC | F86: =F81 -> CNH INDUSTRIAL N | G86: =G81 -> TEREX CORP | H86: =H81 -> ALAMO GROUP | I86: =I81 -> KUBOTA CORP-ADR | J86: =J81 -> KOMATSU LTD-ADR
B88: Diluted share count YoY | C88: 0.0039855072 | D88: 0.0013404826 | E88: 0.0055475652 | F88: 0.004784689 | G88: 0.0089552239 | H88: 0.0057653743 | I88: 0 | J88: 3.028009e-05
B89: SBC / revenue | C89: 0.0040219661 | D89: 0.0015777875 | E89: #VALUE! | F89: #VALUE! | G89: 0.0058513751 | H89: 0.0056130961 | I89: #VALUE! | J89: #VALUE!
B90: SBC / CFO | C90: 0.02253277 | D90: 0.026670532 | E90: #VALUE! | F90: #VALUE! | G90: 0.09202454 | H90: 0.043574636 | I90: #VALUE! | J90: #VALUE!
B91: EPS in USD | C91: 25.73 | D91: 5.69 | E91: 22.17 | F91: 0.99 | G91: 9.69 | H91: 5 | I91: 1.33 | J91: 3.18

Sheet ESG
A7: x | B7: ESG Analysis
B12: ESG Scores | G12: GHG Scope 1 Emissions, Water Consumption, Energy Consumption and Waste Production per Sales
B15: LSEG ESG Score | D15: 71
B16: E-Score | D16: 84
B17: S-Score | D17: 72
B18: G-Score | D18: 54
B19: S&P Global ESG Score | D19: 47
B20: Environmental
B21: Social
B22: Governance & Economic
B23: Sustainalytics | D23: 16.1
B24: ISS ESG Corporate Rating | D24: B-
B25: SDG Impact Rating | D25: 1.9
B26: Governance Quality Score | D26: 7
B27: MSCI ESG Ratings | D27: AA
B30: Key Info | G30: Environmental
H32: Overview | I32: Targets | J32: Improvements | K32: Comments
B33: GICS Sector | C33: Industrials | G33: GHG Scope 1 Emissions | I33: Reduce 50% operational CO2 emissions (Scope 1 & 2) by 2030 | J33: A 29% reduction in Scope 1and 2 emissions by 2024 | K33: Progress is ahead of schedule towards an ambitious, SBTi-validated goal. A portion of the reduction is attributed to lower production volumes.
B34: GICS Industry Group | C34: Machinery
B35: GICS Industry | C35: Industrial Machinery & Equipment | G35: Water Consumption | I35: Reduce 10% of freshwater consumption intensity at water stressed manufacturing locations by 2030 | J35: N/A | K35: Performance is consistently moving in the opposite direction of the time-bound goal, indicating a significant operational challenge.
B36: GICS Sub-Industry | C36: Construction & Farm Machinery
G37: Energy Consumption | I37: Implicit in GHG reduction goals, not a standalone target | J37: Renewable electricity accounts for 65% of total eletctricity in 2024, up from 59% in 2022 | K37: Demonstrates strong, consistent progress in transitioning to renewable sources. Strategic investments and acquisitions underpin this progress.
B38: Headquarters | C38: Moline, Illinois, United States
B39: Number of Employees | C39: 75800 | G39: Waste Management | I39: Reduce 15% waste intensity by 2030 | J39: A 6% increase in waste intensity by 2024. But, it's showing a consistent year-over-year decrease | K39: While not yet vellow the 2021 baseline, the company is on a postive trajectory. Execution has not yet matched the stated ambition.
B41: Annual Report | C41: January 10 2025 | G41: Other | I41: Reduce 30% Scope 3 emissions; Reduce 15% customer CO2 emissons; Grow remanufacturing revenuy by 50%; Achieve 95% recycable content | J41: A 19% reduction in Scope 3 emissions; A 5% reduction in costumer emissons; A 2% growth in remanufacturing revenue; A 92% recycable product content | K41: The strategy adresses the most significant part of the footprint. Progress is strong but inconsistent, with remanufacturing lagging significantly.
B42: Sustainability Report | C42: January 16 2025
B44: Recent Headlines | G44: Social
H46: Overview | I46: Targets | J46: Improvements | K46: Comments
B47: Product Safety Recall and Lawsuit in September and October 2024 | G47: Employee Turnover % | I47: N/A | J47: Increased to 14.2% in 2024, up from 13.2% in 2023. | K47: This rate, while increasing, remains significantly lower than the manufacturing industry average of 28.6%. The company saw a reduction of 7,200 employees in 2024.
B48: Racial and Age Discrimination Claims in June and July 2024
B49: John Deere Employees Raise Over $200K for Flood Relief | G49: Salaries & Compensation | I49: The Compensation Committee aims to align compensation with the company's strategic priorities and performance. | J49: Executive compensation increased in 2024 . | K49: The CEO's total compensation was $27.80M in 2024, up 4.04% from 2023. This contrasts with ongoing layoffs and a lawsuit alleging that older, more expensive employees were targeted for job cuts.
B50: Brock Purdy and "Tractor Kid" Team Up with Deere to Fight Hunger
B51: Federal Judge Rules Deere Must Face "Right to Repair" Antitrust Lawsuit | G51: Reputation | I51: N/A | J51: N/A | K51: The company's reputation is under pressure from layoffs product recalls and high-profile lawsuits, including an antitrust case over its "Right to Repair" policies. Customer loyalty, as measured by NPS, ranks below key competitors.
B52: Shareholder Vote down on DEI and Sustainability, February 2025
B53: Layoffs and Declining Sales | G53: Discrimination Events | I53: N/A | J53: N/A | K53: The company settled for $1.1M with the Department of Labor over allegations of racial discrimination against 277 Black and Hispanic job applicants.
B54: John Deere Launches Enhanced Digital Self-Repair Tool
B55: John Deere Reman Announces $13.5M Expansion | G55: Work Safety | I55: Reduce the Total Recordable Incident Rate (TRIR) by 20% by 2026 | J55: Improved to 1.69 in 2024 from 2.08 in 2023. Representing a 15% decrease from the 2021 baseline. | K55: This rate is better than the national average for the goods-producing sector of 2.7, indicating an effective internal safety management system. The company's fatality rate was 0.000 in 2024.
B56: John Deere Launches Enhanced Digital Self-Repair Tool
G57: Damage to consumer health | I57: N/A | J57: N/A | K57: A class-action lawsuit was filed in October 2024 over a brake system defect in certain tractors that caused a recall and led to injuries, including a hospitalization. The suit alleges the recall is "repeatedly ineffective."
G59: Pension Plan | I59: N/A | J59: N/A | K59: Deere offers both a defined contribution (401k) and a two-tiered pension plan for wage employees. The two-tiered system was a key point of contention during the 2021 UAW strike.
G61: Supply chain | I61: N/A | J61: Increased the number of supplier compliance audits to 1,902 in 2024, up from 1,468 in 2023. | K61: The company uses a multi-layered risk management process, including financial and human rights assessments, and requires suppliers to engage in third-party sustainability assessments.
G63: Community involvement | I63: N/A | J63: The company contributed a record $61.7M in 2024, and employees volunteered a record 342,015 hours, a 31% increase. | K63: The John Deere Foundation has a long-term commitment of $200M over a decade to support communities. The company has been recognized as one of the top community-minded companies in the U.S.
G65: Public Sector | I65: N/A | J65: N/A | K65: The company openly discloses its political contributions and engages in policy discussions related to its business interests, such as renewable fuels and precision agriculture.
G67: Litigation | I67: N/A | J67: N/A | K67: The company is involved in a major antitrust lawsuit challenging its "Right to Repair" policies and a class-action lawsuit over a product safety recall, in addition to a racial discrimination settlement.
B70: Board of Directors | G70: Governance
B72: Name | C72: Position | E72: M/F – Age | H72: Overview | I72: Targets | J72: Improvements | K72: Comments
B73: John C. May | C73: Chairman and CEO | E73: M - 55 | G73: Diversity (Gender, Age, Industry, Region) | I73: N/A | J73: The percentage of women in senior management increased from 25% in 2023 to 28.8% in 2024, while Black or African American representation in senior management increased from 13.9% to 18.8% in the same period. | K73: N/A
B74: Leane G. Caret | C74: Director | E74: F - 58
B75: Tami/Tamra A. Erwin | C75: Director | E75: F - 60 | G75: % Independence | I75: N/A | J75: The Board of Directors has 9 independent directors out of 10 total members, representing approximately 90% independence. | K75: This exceeds the NYSE requirement that a majority of the board be independent.
B76: R. Preston Feight | C76: Director | E76: M - 57
B77: Alan C. Heuberger | C77: Director | E77: M - 51 | G77: Average time as independent directors | I77: N/A | J77: The average tenure for the Board of Directors is 7.4 years. | K77: Individual tenures range from less than one year to over 12 years. This metric is not available in the company’s own reports and is sourced from third-party data.
B78: L. Neil Hunn | C78: Director | E78: M - 53
B79: Michael O. Johanns | C79: Director | E79: M - 75 | G79: Departures of C-level executives | I79: N/A | J79: In September 2025, there were key leadership changes, including reassignments for three presidents: Deanna Kovar, Justin Rose, and Cory Reed. | K79: There were reassignments to new roles rather than departures from the company, intended to advance the "Smart Industrial Strategy."
B80: Dmiti L. Stockton | C80: Director | E80: M - 61
B81: Gregory R. Page | C81: Director | E81: M - 73 | G81: CEO/Chairman duality | I81: N/A | J81: N/A | K81: John C. May serves as both Chairman of the Board and CEO. The company's policy states that a separate Chairman is "unnecessary in normal circumstances."
B82: Sheila G. Talton | C82: Director | E82: F - 72
G83: Transparency when reporting | I83: N/A | J83: The company publishes its sustainability report, annual reports, and proxy statements online. | K83: This level of reporting is timely and aligns with best practices. The company also aligns its disclosures with major frameworks like TCFD, SASB, and GRI.
G85: Time taken to report | I85: N/A | J85: N/A | K85: The 2024 Annual Report and 2025 Proxy Statement were published in January 2025, approximately 2.5 months after the fiscal year end of October 27, 2024.
G87: CEO or Chairman in other boards? | I87: N/A | J87: N/A | K87: CEO John C. May is a member of the board of Ford Motor Company, the Business Roundtable, and the Council on Competitiveness. Several other independent directors also hold CEO or C-level positions at other companies.
G89: Audit / Consulting | I89: N/A | J89: Tax fees paid to the independent auditor decreased by 81.6% from $250,000 in 2023 to $46,000 in 2024. | K89: Total fees paid to Deloitte & Touche LLP were $24.004M in 2024, with non-audit services making up a small percentage. The significant reduction in tax-related fees strengthens auditor independence.
G91: ESG-compensation related | I91: N/A | J91: N/A | K91: While the company states it considers sustainability, the metrics for this are not explicitly tied to quantitative ESG targets like emissions reductions, but rather to a qualitative assessment.
G93: Management compensation schemes | I93: N/A | J93: N/A | K93: A significant portion of executive compensation is tied to stock awards, aligning pay with shareholder value. This is a potential risk to be monitored.

Sheet WACC
A7: x | B7: Rolling WACC | K7: Equity Risk Premium
P8: Weights
D9: 2025 | E9: =+D9+1 -> 2026 | F9: =+E9+1 -> 2027 | G9: =+F9+1 -> 2028 | H9: =+G9+1 -> 2029 | M9: ERP | N9: 2025 | O9: =+N9+1 -> 2026 | P9: =+O9+1 -> 2027 | Q9: =+P9+1 -> 2028 | R9: =+Q9+1 -> 2029
B12: Equity: | K12: =+Segments!B20 -> United States (US) | M12: 0.0433 | N12: =+Segments!AL20/Segments!AL$26 -> 0.58477067 | O12: =Segments!$AR$20/Segments!$AR$26 -> 0.59743862 | P12: =Segments!AT20/Segments!AT26 -> 0.6 | Q12: =Segments!AV20/Segments!$AV$26 -> 0.6 | R12: =Segments!AX20/Segments!$AX$26 -> 0.59
B13: Market Cap (in billions) | D13: =+Inputs!J13 -> 130166.3 | E13: =+FCFF!AF99*FCFF!AF31 -> 119781.32 | F13: =+FCFF!AH99*FCFF!AH31 -> 132720.62 | G13: =+FCFF!AJ99*FCFF!AJ31 -> 150557.95 | H13: =+FCFF!AL99*FCFF!AL31 -> 157684.95 | K13: =+Segments!B21 -> Canada (CAN) | M13: 0.0433 | N13: =+Segments!AL21/Segments!AL$26 -> 0.075411865 | O13: =Segments!AR21/Segments!AR26 -> 0.069701173 | P13: =Segments!AT21/Segments!AT26 -> 0.07 | Q13: =Segments!AV21/Segments!$AV$26 -> 0.07 | R13: =Segments!AX21/Segments!$AX$26 -> 0.07
B14: % of Equity | D14: =IFERROR(D13/D35,"") -> 0.66246674 | E14: =IFERROR(E13/E35,"") -> 0.64129176 | F14: =IFERROR(E13/F35,"") -> 0.5952736 | G14: =IFERROR(F13/G35,"") -> 0.60174945 | H14: =IFERROR(G13/H35,"") -> 0.65265615 | K14: =+Segments!B22 -> Western Europe (WE) | M14: 0.0457 | N14: =+Segments!AL22/Segments!AL$26 -> 0.11967283 | O14: =Segments!AR22/Segments!AR26 -> 0.089615794 | P14: =Segments!AT22/Segments!AT26 -> 0.09 | Q14: =Segments!AV22/Segments!$AV$26 -> 0.09 | R14: =Segments!AX22/Segments!$AX$26 -> 0.09
B15: Risk-Free Rate | D15: 0.0417 | E15: 0.041 | F15: 0.041 | G15: 0.041 | H15: 0.041 | K15: =+Segments!B23 -> Central Europe and CIS (CECIS) | M15: 0.0927 | N15: =+Segments!AL23/Segments!AL$26 -> 0.028772527 | O15: =Segments!AR23/Segments!AR26 -> 0.019914621 | P15: =Segments!AT23/Segments!AT26 -> 0.02 | Q15: =Segments!AV23/Segments!$AV$26 -> 0.02 | R15: =Segments!AX23/Segments!$AX$26 -> 0.02
B16: Beta | D16: =+Inputs!M18 -> 0.89700514 | E16: =+D17*(1+(E28/E13)*(1-E32)) -> 0.91480089 | F16: =+E17*(1+(F28/F13)*(1-F32)) -> 0.89332398 | G16: =+F17*(1+(G28/G13)*(1-G32)) -> 0.86789577 | H16: =+G17*(1+(H28/H13)*(1-H32)) -> 0.86690773 | K16: =+Segments!B24 -> Latin America (LA) | M16: 0.1154 | N16: =+Segments!AL25/Segments!AL$26 -> 0.084287261 | O16: =Segments!AR24/Segments!AR26 -> 0.13940235 | P16: =Segments!AT24/Segments!AT26 -> 0.16 | Q16: =Segments!AV24/Segments!$AV$26 -> 0.16 | R16: =Segments!AX24/Segments!$AX$26 -> 0.16
B17: Unlevered Beta | D17: =+D16/(1+(D28/D13)*(1-D32)) -> 0.63691711 | E17: =+E16/(1+(E28/E13)*(1-E32)) -> 0.63691711 | F17: =+F16/(1+(F28/F13)*(1-F32)) -> 0.63691711 | G17: =+G16/(1+(G28/G13)*(1-G32)) -> 0.63691711 | H17: =+H16/(1+(H28/H13)*(1-H32)) -> 0.63691711 | K17: =+Segments!B25 -> Asia, Africa, Australia, New Zealand, and Middle East (AAANM) | M17: 0.1071 | N17: =Segments!AL25/Segments!AL26 -> 0.084287261 | O17: =Segments!AR25/Segments!AR26 -> 0.083927442 | P17: =Segments!AT25/Segments!AT26 -> 0.06 | Q17: =Segments!AV25/Segments!$AV$26 -> 0.06 | R17: =Segments!AX25/Segments!$AX$26 -> 0.07
B18: Equity Risk Premium | D18: =+N18 -> 0.055476081 | E18: =+O18 -> 0.05990434 | F18: =+P18 -> 0.059868 | G18: =+Q18 -> 0.059868 | H18: =+R18 -> 0.060506 | K18: ERP | N18: =+SUMPRODUCT($M12:$M17,N12:N17) -> 0.055476081 | O18: =+SUMPRODUCT($M12:$M17,O12:O17) -> 0.05990434 | P18: =+SUMPRODUCT($M12:$M17,P12:P17) -> 0.059868 | Q18: =+SUMPRODUCT($M12:$M17,Q12:Q17) -> 0.059868 | R18: =+SUMPRODUCT($M12:$M17,R12:R17) -> 0.060506
B19: Ke (Cost of Equity) | D19: =IFERROR(+D15+D16*D18,"") -> 0.09146233 | E19: =IFERROR(+E15+E16*E18,"") -> 0.095800544 | F19: =IFERROR(+F15+F16*F18,"") -> 0.09448152 | G19: =IFERROR(+G15+G16*G18,"") -> 0.092959184 | H19: =IFERROR(+H15+H16*H18,"") -> 0.093453119
B21: Preferred Equity: | K21: ROIC vs WACC
B22: Market Capitalization | D22: =IFERROR(Inputs!J14,0) -> 126816.92 | E22: =+D22*(E13/D13) -> 116699.17 | F22: =+E22*(F13/E13) -> 129305.52 | G22: =+F22*(G13/F13) -> 146683.86 | H22: =+G22*(H13/G13) -> 153627.47
B23: % of Preferred Equity | D23: =+D22/D35 -> 0.64542044 | E23: =+E22/E35 -> 0.62479033 | F23: =+F22/F35 -> 0.64260568 | G23: =+G22/G35 -> 0.66505814 | H23: =+H22/H35 -> 0.66596226
B24: Preferred Dividends | D24: =+IS!AF50 -> 0 | E24: =D24 -> 0 | F24: =E24 -> 0 | G24: =F24 -> 0 | H24: =G24 -> 0
B25: Kp (Cost of Preferred Equity) | D25: =IFERROR(D24/D22,0) -> 0 | E25: =IFERROR(E24/E22,0) -> 0 | F25: =IFERROR(F24/F22,0) -> 0 | G25: =IFERROR(G24/G22,0) -> 0 | H25: =IFERROR(H24/H22,0) -> 0
B27: Debt:
B28: Debt (in millions) | C28: =+BS!AF38+BS!AF39+BS!AF44+BS!AF45 -> 65463 | D28: =+BS!AI38+BS!AI39+BS!AI44+BS!AI45 -> 66321 | E28: 67000 | F28: 68500 | G28: 70000 | H28: 73000
B29: % of Debt | D29: =IFERROR(D28/D35,"") -> 0.33753326 | E29: =IFERROR(E28/E35,"") -> 0.35870824 | F29: =IFERROR(F28/F35,"") -> 0.34042236 | G29: =IFERROR(G28/G35,"") -> 0.31737691 | H29: =IFERROR(H28/H35,"") -> 0.31644891
B30: Debt Spread | D30: =+D31-D15 -> 0.0084047934 | E30: 0.007 | F30: 0.007 | G30: 0.008 | H30: 0.008
B31: Cost of Debt | D31: =+(IS!AI36+IS!AH36+IS!AE36+IS!AD36)/WACC!D28 -> 0.050104793 | E31: =+E30+E15 -> 0.048 | F31: =+F30+F15 -> 0.048 | G31: =+G30+G15 -> 0.049 | H31: =+H30+H15 -> 0.049
B32: Tax Rate | D32: =+FCFF!Z124 -> 0.19853425 | E32: =+FCFF!AF124 -> 0.22 | F32: =+FCFF!AH124 -> 0.22 | G32: =+FCFF!AJ124 -> 0.22 | H32: =+FCFF!AL124 -> 0.22
B33: Kd (After-Tax Cost of Debt) | D33: =+D31*(1-D32) -> 0.040157276 | E33: =+E31*(1-E32) -> 0.03744 | F33: =+F31*(1-F32) -> 0.03744 | G33: =+G31*(1-G32) -> 0.03822 | H33: =+H31*(1-H32) -> 0.03822
B35: Total | D35: =+D13+D24+D28 -> 196487.3 | E35: =+E13+E24+E28 -> 186781.33 | F35: =+F13+F24+F28 -> 201220.62 | G35: =+G13+G24+G28 -> 220557.95 | H35: =+H13+H24+H28 -> 230684.95
B37: Country/Conglomerate/... Risk Premium | D37: 0 | E37: 0 | F37: 0 | G37: 0 | H37: 0
A39: x | B39: WACC | D39: =+D19*D14+D25*D23+D33*D29+D37 -> 0.074145168 | E39: =+E19*E14+E25*E23+E33*E29+E37 -> 0.074866136 | F39: =+F19*F14+F25*F23+F33*F29+F37 -> 0.068987767 | G39: =+G19*G14+G25*G23+G33*G29+G37 -> 0.068068283 | H39: =+H19*H14+H25*H23+H33*H29+H37 -> 0.07308743
B41: NOPAT | D41: =+FCFF!Z126 -> 7829.1407 | E41: =+FCFF!AF126 -> 7850.218 | F41: =+FCFF!AH126 -> 8488.8112 | G41: =+FCFF!AJ126 -> 10475.22 | H41: =+FCFF!AL126 -> 12299.426
B42: Total Payout | D42: =+FCFF!Z112+FCFF!Z115 -> -3983.956 | E42: =+FCFF!AF112+FCFF!AF115 -> -3753.0265 | F42: =+FCFF!AH112+FCFF!AH115 -> -4945.7475 | G42: =+FCFF!AJ112+FCFF!AJ115 -> -5596.3091 | H42: =+FCFF!AL112+FCFF!AL115 -> -6760.0526
B43: Book Value of Equity | C43: =+BS!AF54 -> 22925 | D43: =+C43+D41+D42 -> 26770.185 | E43: =+D43+E41+E42 -> 30867.376 | F43: =+E43+F41+F42 -> 34410.44 | G43: =+F43+G41+G42 -> 39289.351 | H43: =+G43+H41+H42 -> 44828.724
B44: Invested Capital | C44: =+C43+C28 -> 88388 | D44: =+D43+D28 -> 93091.185 | E44: =+E43+E28 -> 97867.376 | F44: =+F43+F28 -> 102910.44 | G44: =+G43+G28 -> 109289.35 | H44: =+H43+H28 -> 117828.72
A45: x | B45: ROIC | D45: =+D41/((D44+C44)/2) -> 0.086281418 | E45: =+E41/((E44+D44)/2) -> 0.082219073 | F45: =+F41/((F44+E44)/2) -> 0.084559254 | G45: =+G41/((G44+F44)/2) -> 0.098729786 | H45: =+H41/((H44+G44)/2) -> 0.10830865
W49: ,

Sheet FCFF
A7: x | B7: Market Assumptions
D8: 2022 | J8: =D8+1 -> 2023 | P8: =J8+1 -> 2024 | V8: =P8+1 -> 2025 | AB8: =V8+1 -> 2026 | AH8: =AB8+1 -> 2027 | AJ8: =+AH8+1 -> 2028 | AL8: =+AJ8+1 -> 2029
D9: Q1 | E9: Q2 | F9: Q3 | G9: Q4 | H9: FY | J9: Q1 | K9: Q2 | L9: Q3 | M9: Q4 | N9: FY | P9: Q1 | Q9: Q2 | R9: Q3 | S9: Q4 | T9: FY | V9: Q1 | W9: Q2 | X9: Q3 | Y9: Q4 | Z9: FY | AB9: Q1 | AC9: Q2 | AD9: Q3 | AE9: Q4 | AF9: FY | AH9: FY | AJ9: FY | AL9: FY
AS15: 2022 | AT15: =+AS15+1 -> 2023 | AU15: =+AT15+1 -> 2024 | AV15: =+AU15+1 -> 2025 | AW15: =+AV15+1 -> 2026 | AX15: =+AW15+1 -> 2027 | AY15: =+AX15+1 -> 2028 | AZ15: =+AY15+1 -> 2029
AR16: EBITDA | AS16: =H61+H128 -> 11931 | AT16: =N61+N128 -> 17667 | AU16: =T61+T128 -> 14920 | AV16: =Z61+Z128 -> 11796.964 | AW16: =AF61+AF128 -> 11486.574 | AX16: =AH61+AH128 -> 11238.639 | AY16: =AJ61+AJ128 -> 13785.317 | AZ16: =AL61+AL128 -> 16124.043
AR17: FCFF | AS17: =H136 -> 7784.4202 | AT17: =N136 -> 11659.318 | AU17: =T136 -> 12551.191 | AV17: =Z136 -> 7263.9046 | AW17: =AF136 -> 8748.3363 | AX17: =AH136 -> 9563.061 | AY17: =AJ136 -> 10219.693 | AZ17: =AL136 -> 12287.847
AR18: Revenue Growth | AS18: =H32 -> 0.19428039 | AT18: =N32 -> 0.16497708 | AU18: =T32 -> -0.15567093 | AV18: =Z32 -> -0.12727396 | AW18: =AF32 -> 0.061564146 | AX18: =AH32 -> 0.10802435 | AY18: =+AJ32 -> 0.13439754 | AZ18: =+AL32 -> 0.047337246
B21: Revenue | H21: =Segments!T17 -> 52577 | N21: =Segments!Z17 -> 61251 | T21: =Segments!AF17 -> 51716 | Z21: =Segments!AL17 -> 45133.9 | AF21: =Segments!AR17 -> 47912.53 | AH21: =Segments!AT17 -> 53088.25 | AJ21: =Segments!AV17 -> 60223.18 | AL21: =Segments!AX17 -> 63073.98
A23: x | B23: Operating Assumptions
D24: =D$8 -> 2022 | E24: =F24 -> 0 | F24: =F$8 -> 0 | G24: =F24 -> 0 | H24: =F24 -> 0 | J24: =J$8 -> 2023 | K24: =L24 -> 0 | L24: =L$8 -> 0 | M24: =L24 -> 0 | N24: =L24 -> 0 | P24: =P$8 -> 2024 | Q24: =R24 -> 0 | R24: =R$8 -> 0 | S24: =R24 -> 0 | T24: =R24 -> 0 | V24: =V$8 -> 2025 | W24: =X24 -> 0 | X24: =X$8 -> 0 | Y24: =X24 -> 0 | Z24: =X24 -> 0 | AB24: =AB$8 -> 2026 | AC24: =AD24 -> 0 | AD24: =AD$8 -> 0 | AE24: =AD24 -> 0 | AF24: =AD24 -> 0 | AH24: =AH$8 -> 2027 | AJ24: =AJ$8 -> 2028 | AL24: =AL$8 -> 2029 | AM24: =AN24 -> 0
D25: Q1 | E25: Q2 | F25: Q3 | G25: Q4 | H25: FY | J25: Q1 | K25: Q2 | L25: Q3 | M25: Q4 | N25: FY | P25: Q1 | Q25: Q2 | R25: Q3 | S25: Q4 | T25: FY | V25: Q1 | W25: Q2 | X25: Q3 | Y25: Q4 | Z25: FY | AB25: Q1 | AC25: Q2 | AD25: Q3 | AE25: Q4 | AF25: FY | AH25: FY | AJ25: FY | AL25: FY
B28: Income Statement
B31: Revenue | D31: =IS!P18 -> 9569 | E31: =IS!Q18 -> 13370 | F31: =IS!R18 -> 14102 | G31: =IS!S18 -> 15536 | H31: =IS!T18 -> 52577 | J31: =IS!V18 -> 12652 | K31: =IS!W18 -> 17387 | L31: =IS!X18 -> 15801 | M31: =IS!Y18 -> 15412 | N31: =IS!Z18 -> 61251 | P31: =IS!AB18 -> 12185 | Q31: =IS!AC18 -> 15235 | R31: =IS!AD18 -> 13152 | S31: =IS!AE18 -> 11143 | T31: =IS!AF18 -> 51716 | V31: =IS!AH18 -> 8508 | W31: =IS!AI18 -> 12763 | X31: =12018 -> 12018 | Y31: =(Z31-V31-W31-X31) -> 11844.9 | Z31: =Z21 -> 45133.9 | AB31: 9000 | AC31: 12000 | AD31: 13000 | AE31: 13913 | AF31: =AF21 -> 47912.53 | AH31: =AH21 -> 53088.25 | AI31: =AI21 -> 0 | AJ31: =AJ21 -> 60223.18 | AK31: =AK21 -> 0 | AL31: =AL21 -> 63073.98
B32: % of growth | D32: =D31/IS!J18-1 -> 0.050153644 | E32: =E31/IS!K18-1 -> 0.10880743 | F32: =F31/IS!L18-1 -> 0.22338857 | G32: =G31/IS!M18-1 -> 0.37159001 | H32: =H31/IS!N18-1 -> 0.19428039 | J32: =J31/IS!P18-1 -> 0.32218623 | K32: =K31/IS!Q18-1 -> 0.30044877 | L32: =L31/IS!R18-1 -> 0.12047936 | M32: =M31/IS!S18-1 -> -0.0079814624 | N32: =N31/H31-1 -> 0.16497708 | P32: =P31/IS!V18-1 -> -0.03691116 | Q32: =Q31/IS!W18-1 -> -0.12377063 | R32: =R31/IS!X18-1 -> -0.16764762 | S32: =S31/IS!Y18-1 -> -0.27699195 | T32: =T31/N31-1 -> -0.15567093 | V32: =V31/IS!AB18-1 -> -0.30176446 | W32: =W31/IS!AC18-1 -> -0.16225796 | X32: =X31/IS!AD18-1 -> -0.086222628 | Y32: =Y31/IS!AE18-1 -> 0.062990218 | Z32: =Z31/T31-1 -> -0.12727396 | AB32: =AB31/IS!AH18-1 -> 0.057827927 | AC32: =AC31/IS!AI18-1 -> -0.059782183 | AD32: =AD31/X31-1 -> 0.081710767 | AE32: =AE31/Y31-1 -> 0.17459835 | AF32: =AF31/Z31-1 -> 0.061564146 | AH32: =AH31/AF31-1 -> 0.10802435 | AJ32: =AJ31/AH31-1 -> 0.13439754 | AL32: =AL31/AJ31-1 -> 0.047337246
B34: Cost of Goods & Services | D34: =IS!P21 -> 6695 | E34: =IS!Q21 -> 8918 | F34: =IS!R21 -> 9511 | G34: =IS!S21 -> 10214 | H34: =IS!T21 -> 35338 | J34: =IS!V21 -> 7934 | K34: =IS!W21 -> 10730 | L34: =IS!X21 -> 9624 | M34: =IS!Y21 -> 9427 | N34: =IS!Z21 -> 37715 | P34: =IS!AB21 -> 7200 | Q34: =IS!AC21 -> 9157 | R34: =IS!AD21 -> 7848 | S34: =IS!AE21 -> 6571 | T34: =IS!AF21 -> 30775 | V34: =IS!AH21 -> 5037 | W34: =IS!AI21 -> 7609 | X34: 7570 | Y34: =(Y35+Sensitivity!$U$39)*Y$31 -> 7462.287 | Z34: =SUM(V34:Y34) -> 27678.287 | AB34: =(AB35+Sensitivity!$U$39)*AB$31 -> 5850 | AC34: =(AC35+Sensitivity!$U$39)*AC$31 -> 7800 | AD34: =(AD35+Sensitivity!$U$39)*AD$31 -> 8320 | AE34: =(AE35+Sensitivity!$U$39)*AE$31 -> 8904.32 | AF34: =SUM(AB34:AE34) -> 30874.32 | AH34: =(AH35+Sensitivity!$U$39)*AH$31 -> 34507.363 | AJ34: =(AJ35+Sensitivity!$U$39)*AJ$31 -> 37940.603 | AL34: =(AL35+Sensitivity!$U$39)*AL$31 -> 37844.388
B35: % of sales | D35: =D34/D31 -> 0.69965514 | E35: =E34/E31 -> 0.66701571 | F35: =F34/F31 -> 0.67444334 | G35: =G34/G31 -> 0.65744078 | H35: =H34/H31 -> 0.67211899 | J35: =J34/J31 -> 0.62709453 | K35: =K34/K31 -> 0.61712774 | L35: =L34/L31 -> 0.60907537 | M35: =M34/M31 -> 0.61166623 | N35: =N34/N31 -> 0.61574505 | P35: =P34/P31 -> 0.59089044 | Q35: =Q34/Q31 -> 0.60105021 | R35: =R34/R31 -> 0.59671533 | S35: =S34/S31 -> 0.58969757 | T35: =T34/T31 -> 0.59507696 | V35: =V34/V31 -> 0.59203103 | W35: =W34/W31 -> 0.59617645 | X35: =X34/X31 -> 0.6298885 | Y35: 0.63 | Z35: =Z34/Z31 -> 0.61324829 | AB35: 0.65 | AC35: 0.65 | AD35: 0.64 | AE35: 0.64 | AF35: =AF34/AF31 -> 0.64438927 | AH35: 0.65 | AJ35: 0.63 | AL35: 0.6
B37: COGS Depreciation & Amortization | D37: =IS!P22 -> 0 | E37: =IS!Q22 -> 0 | F37: =IS!R22 -> 0 | G37: =IS!S22 -> 0 | H37: =IS!T22 -> 0 | J37: =IS!V22 -> 0 | K37: =IS!W22 -> 0 | L37: =IS!X22 -> 0 | M37: =IS!Y22 -> 0 | N37: =IS!Z22 -> 0 | P37: =IS!AB22 -> 0 | Q37: =IS!AC22 -> 0 | R37: =IS!AD22 -> 0 | S37: =IS!AE22 -> 0 | T37: =IS!AF22 -> 0 | V37: =IS!AH22 -> 0 | W37: =IS!AI22 -> 0 | X37: =X38*X34 -> 0 | Y37: =Y38*Y34 -> 0 | Z37: =SUM(V37:Y37) -> 0 | AB37: =AB38*AB34 -> 0 | AC37: =AC38*AC34 -> 0 | AD37: =AD38*AD34 -> 0 | AE37: =AE38*AE34 -> 0 | AF37: =SUM(AB37:AE37) -> 0 | AH37: =AH38*AH34 -> 0 | AJ37: =AJ38*AJ34 -> 0 | AL37: =AL38*AL34 -> 0
B38: % of cost of goods & services | D38: =D37/D34 -> 0 | E38: =E37/E34 -> 0 | F38: =F37/F34 -> 0 | G38: =G37/G34 -> 0 | H38: =H37/H34 -> 0 | J38: =J37/J34 -> 0 | K38: =K37/K34 -> 0 | L38: =L37/L34 -> 0 | M38: =M37/M34 -> 0 | N38: =N37/N34 -> 0 | P38: =P37/P34 -> 0 | Q38: =Q37/Q34 -> 0 | R38: =R37/R34 -> 0 | S38: =S37/S34 -> 0 | T38: =T37/T34 -> 0 | V38: =V37/V34 -> 0 | W38: =W37/W34 -> 0 | X38: 0 | Y38: 0 | Z38: =Z37/Z34 -> 0 | AB38: 0 | AC38: 0 | AD38: 0 | AE38: 0 | AF38: =AF37/AF34 -> 0 | AH38: 0 | AJ38: 0 | AL38: 0
B40: Gross Profit | D40: =IS!P24 -> 2874 | E40: =IS!Q24 -> 4452 | F40: =IS!R24 -> 4591 | G40: =IS!S24 -> 5322 | H40: =IS!T24 -> 17239 | J40: =IS!V24 -> 4718 | K40: =IS!W24 -> 6657 | L40: =IS!X24 -> 6177 | M40: =IS!Y24 -> 5985 | N40: =IS!Z24 -> 23536 | P40: =IS!AB24 -> 4985 | Q40: =IS!AC24 -> 6078 | R40: =IS!AD24 -> 5304 | S40: =IS!AE24 -> 4572 | T40: =IS!AF24 -> 20941 | V40: =IS!AH24 -> 3471 | W40: =IS!AI24 -> 5154 | X40: =X31-X34-X37 -> 4448 | Y40: =Y31-Y34-Y37 -> 4382.613 | Z40: =SUM(V40:Y40) -> 17455.613 | AB40: =AB31-AB34-AB37 -> 3150 | AC40: =AC31-AC34-AC37 -> 4200 | AD40: =AD31-AD34-AD37 -> 4680 | AE40: =AE31-AE34-AE37 -> 5008.68 | AF40: =SUM(AB40:AE40) -> 17038.68 | AH40: =AH31-AH34-AH37 -> 18580.887 | AJ40: =AJ31-AJ34-AJ37 -> 22282.577 | AL40: =AL31-AL34-AL37 -> 25229.592
B41: % of sales | D41: =D40/D31 -> 0.30034486 | E41: =E40/E31 -> 0.33298429 | F41: =F40/F31 -> 0.32555666 | G41: =G40/G31 -> 0.34255922 | H41: =H40/H31 -> 0.32788101 | J41: =J40/J31 -> 0.37290547 | K41: =K40/K31 -> 0.38287226 | L41: =L40/L31 -> 0.39092463 | M41: =M40/M31 -> 0.38833377 | N41: =N40/N31 -> 0.38425495 | P41: =P40/P31 -> 0.40910956 | Q41: =Q40/Q31 -> 0.39894979 | R41: =R40/R31 -> 0.40328467 | S41: =S40/S31 -> 0.41030243 | T41: =T40/T31 -> 0.40492304 | V41: =V40/V31 -> 0.40796897 | W41: =W40/W31 -> 0.40382355 | X41: =X40/X31 -> 0.3701115 | Y41: =Y40/Y31 -> 0.37 | Z41: =Z40/Z$31 -> 0.38675171 | AB41: =AB40/AB31 -> 0.35 | AC41: =AC40/AC31 -> 0.35 | AD41: =AD40/AD31 -> 0.36 | AE41: =AE40/AE31 -> 0.36 | AF41: =AF40/AF$31 -> 0.35562054 | AH41: =AH40/AH31 -> 0.35 | AJ41: =AJ40/AJ31 -> 0.37 | AL41: =AL40/AL31 -> 0.4
B43: SG&A (Selling, General & Administrative) | D43: =IS!P27 -> 781 | E43: =IS!Q27 -> 932 | F43: =IS!R27 -> 959 | G43: =IS!S27 -> 1191 | H43: =IS!T27 -> 3863 | J43: =IS!V27 -> 952 | K43: =IS!W27 -> 1330 | L43: =IS!X27 -> 1110 | M43: =IS!Y27 -> 1203 | N43: =IS!Z27 -> 4595 | P43: =IS!AB27 -> 1066 | Q43: =IS!AC27 -> 1265 | R43: =IS!AD27 -> 1278 | S43: =IS!AE27 -> 1232 | T43: =IS!AF27 -> 4840 | V43: =IS!AH27 -> 972 | W43: =IS!AI27 -> 1197 | X43: 1217 | Y43: =(Y44+Sensitivity!$U$40)*Y$31 -> 1066.041 | Z43: =SUM(V43:Y43) -> 4452.041 | AB43: =(AB44+Sensitivity!$U$40)*AB$31 -> 810 | AC43: =(AC44+Sensitivity!$U$40)*AC$31 -> 1080 | AD43: =(AD44+Sensitivity!$U$40)*AD$31 -> 1170 | AE43: =(AE44+Sensitivity!$U$40)*AE$31 -> 1252.17 | AF43: =SUM(AB43:AE43) -> 4312.17 | AH43: =(AH44+Sensitivity!$U$40)*AH$31 -> 4777.9425 | AJ43: =(AJ44+Sensitivity!$U$40)*AJ$31 -> 5420.0862 | AL43: =(AL44+Sensitivity!$U$40)*AL$31 -> 5676.6582
B44: % of sales | D44: =D43/D31 -> 0.081617724 | E44: =E43/E31 -> 0.069708302 | F44: =F43/F31 -> 0.068004538 | G44: =G43/G31 -> 0.076660659 | H44: =H43/H31 -> 0.073473192 | J44: =J43/J31 -> 0.075245021 | K44: =K43/K31 -> 0.076493932 | L44: =L43/L31 -> 0.070248718 | M44: =M43/M31 -> 0.07805606 | N44: =N43/N31 -> 0.075019183 | P44: =P43/P31 -> 0.087484612 | Q44: =Q43/Q31 -> 0.083032491 | R44: =R43/R31 -> 0.097171533 | S44: =S43/S31 -> 0.11056269 | T44: =T43/T31 -> 0.093588058 | V44: =V43/V31 -> 0.11424542 | W44: =W43/W31 -> 0.093786727 | X44: =X43/X31 -> 0.10126477 | Y44: 0.09 | Z44: =Z43/Z31 -> 0.098640733 | AB44: 0.09 | AC44: 0.09 | AD44: 0.09 | AE44: 0.09 | AH44: 0.09 | AJ44: 0.09 | AL44: 0.09
B46: R&D (Research & Development) | D46: =IS!P29 -> 402 | E46: =IS!Q29 -> 453 | F46: =IS!R29 -> 481 | G46: =IS!S29 -> 576 | H46: =IS!T29 -> 1912 | J46: =IS!V29 -> 495 | K46: =IS!W29 -> 547 | L46: =IS!X29 -> 528 | M46: =IS!Y29 -> 606 | N46: =IS!Z29 -> 2177 | P46: =IS!AB29 -> 533 | Q46: =IS!AC29 -> 565 | R46: =IS!AD29 -> 567 | S46: =IS!AE29 -> 626 | T46: =IS!AF29 -> 2290 | V46: =IS!AH29 -> 526 | W46: =IS!AI29 -> 549 | X46: =556 -> 556 | Y46: =Y47*Y40 -> 372.52211 | Z46: =SUM(V46:Y46) -> 2003.5221 | AB46: =AB47*AB40 -> 315 | AC46: =AC47*AC40 -> 420 | AD46: =AD47*AD40 -> 468 | AE46: =AE47*AE40 -> 500.868 | AF46: =SUM(AB46:AE46) -> 1703.868 | AH46: =AH47*AH40 -> 1858.0887 | AJ46: =AJ47*AJ40 -> 2228.2577 | AL46: =AL47*AL40 -> 2522.9592
B47: % of gross profit | D47: =D46/D40 -> 0.13987474 | E47: =E46/E40 -> 0.10175202 | F47: =F46/F40 -> 0.1047702 | G47: =G46/G40 -> 0.10822999 | H47: =H46/H40 -> 0.11091131 | J47: =J46/J40 -> 0.10491734 | K47: =K46/K40 -> 0.082169145 | L47: =L46/L40 -> 0.085478388 | M47: =M46/M40 -> 0.10125313 | N47: =N46/N40 -> 0.092496601 | P47: =P46/P40 -> 0.10692076 | Q47: =Q46/Q40 -> 0.09295821 | R47: =R46/R40 -> 0.10690045 | S47: =S46/S40 -> 0.13692038 | T47: =T46/T40 -> 0.10935485 | V47: =V46/V40 -> 0.15154134 | W47: =W46/W40 -> 0.10651921 | X47: =X46/X40 -> 0.125 | Y47: 0.085 | Z47: =Z46/Z$40 -> 0.1147781 | AB47: 0.1 | AC47: 0.1 | AD47: 0.1 | AE47: 0.1 | AF47: =AF46/AF$40 -> 0.1 | AH47: 0.1 | AJ47: 0.1 | AL47: 0.1
B49: D&A (Depreciation & Amortization) | D49: =IS!P28 -> 0 | E49: =IS!Q28 -> 0 | F49: =IS!R28 -> 0 | G49: =IS!S28 -> 0 | H49: =IS!T28 -> 0 | J49: =IS!V28 -> 0 | K49: =IS!W28 -> 0 | L49: =IS!X28 -> 0 | M49: =IS!Y28 -> 0 | N49: =IS!Z28 -> 0 | P49: =IS!AB28 -> 0 | Q49: =IS!AC28 -> 0 | R49: =IS!AD28 -> 0 | S49: =IS!AE28 -> 0 | T49: =IS!AF28 -> 0 | V49: =IS!AH28 -> 0 | W49: =IS!AI28 -> 0 | X49: =X52+X55 -> 0 | Y49: =Y52+Y55 -> 0 | Z49: =SUM(V49:Y49) -> 0 | AB49: =AB52+AB55 -> 0 | AC49: =AC52+AC55 -> 0 | AD49: =AD52+AD55 -> 0 | AE49: =AE52+AE55 -> 0 | AF49: =SUM(AB49:AE49) -> 0 | AH49: =AH52+AH55 -> 0 | AJ49: =AJ52+AJ55 -> 0 | AL49: =AL52+AL55 -> 0
B50: % of net pp&e and intangibles excl. Goodwill | D50: =D49/(D79+D82) -> 0 | E50: =E49/(E79+E82) -> 0 | F50: =F49/(F79+F82) -> 0 | G50: =G49/(G79+G82) -> 0 | H50: =H49/(H79+H82) -> 0 | J50: =J49/(J79+J82) -> 0 | K50: =K49/(K79+K82) -> 0 | L50: =L49/(L79+L82) -> 0 | M50: =M49/(M79+M82) -> 0 | N50: =N49/(N79+N82) -> 0 | P50: =P49/(P79+P82) -> 0 | Q50: =Q49/(Q79+Q82) -> 0 | R50: =R49/(R79+R82) -> 0 | S50: =S49/(S79+S82) -> 0 | T50: =T49/(T79+T82) -> 0 | V50: =V49/(V79+V82) -> 0 | W50: =W49/(W79+W82) -> 0 | X50: =X49/( X79+X82) -> 0 | Y50: =Y49/( Y79+Y82) -> 0 | Z50: =Z49/( Z79+Z82) -> 0 | AB50: =AB49/( AB79+AB82) -> 0 | AC50: =AC49/( AC79+AC82) -> 0 | AD50: =AD49/( AD79+AD82) -> 0 | AE50: =AE49/( AE79+AE82) -> 0 | AF50: =AF49/( AF79+AF82) -> 0 | AH50: =AH49/( AH79+AH82) -> 0 | AJ50: =AJ49/( AJ79+AJ82) -> 0 | AL50: =AL49/( AL79+AL82) -> 0
B52: Depreciation | D52: =IS!P64 -> 0 | E52: =IS!Q64 -> 0 | F52: =IS!R64 -> 0 | G52: =IS!S64 -> 0 | H52: =IS!T64 -> 0 | J52: =IS!V64 -> 0 | K52: =IS!W64 -> 0 | L52: =IS!X64 -> 0 | M52: =IS!Y64 -> 0 | N52: =IS!Z64 -> 0 | P52: =IS!AB64 -> 0 | Q52: =IS!AC64 -> 0 | R52: =IS!AD64 -> 0 | S52: =IS!AE64 -> 0 | T52: =IS!AF64 -> 0 | V52: =IS!AH64 -> 0 | W52: =IS!AI64 -> 0 | X52: =X53*W79 -> 0 | Y52: =Y53*X79 -> 0 | Z52: =SUM(V52:Y52) -> 0 | AB52: =AB53*Y79 -> 0 | AC52: =AC53*AB79 -> 0 | AD52: =AD53*AC79 -> 0 | AE52: =AE53*AD79 -> 0 | AF52: =SUM(AB52:AE52) -> 0 | AH52: =AH53*AF79 -> 0 | AJ52: =AJ53*AH79 -> 0 | AL52: =AL53*AJ79 -> 0
B53: % of net pp&e | D53: =D52/D79 -> 0 | E53: =E52/E79 -> 0 | F53: =F52/F79 -> 0 | G53: =G52/G79 -> 0 | H53: =H52/H79 -> 0 | J53: =J52/J79 -> 0 | K53: =K52/K79 -> 0 | L53: =L52/L79 -> 0 | M53: =M52/M79 -> 0 | N53: =N52/N79 -> 0 | P53: =P52/P79 -> 0 | Q53: =Q52/Q79 -> 0 | R53: =R52/R79 -> 0 | S53: =S52/S79 -> 0 | T53: =T52/T79 -> 0 | V53: =V52/V79 -> 0 | W53: =W52/W79 -> 0 | X53: 0 | Y53: 0 | Z53: =Z52/Z79 -> 0 | AB53: 0 | AC53: 0 | AD53: 0 | AE53: 0 | AF53: =AF52/AF79 -> 0 | AH53: 0 | AJ53: 0 | AL53: 0
B55: Amortization | D55: =IS!P65 -> 0 | E55: =IS!Q65 -> 0 | F55: =IS!R65 -> 0 | G55: =IS!S65 -> 0 | H55: =IS!T65 -> 0 | J55: =IS!V65 -> 0 | K55: =IS!W65 -> 0 | L55: =IS!X65 -> 0 | M55: =IS!Y65 -> 0 | N55: =IS!Z65 -> 0 | P55: =IS!AB65 -> 0 | Q55: =IS!AC65 -> 0 | R55: =IS!AD65 -> 0 | S55: =IS!AE65 -> 0 | T55: =IS!AF65 -> 0 | V55: =IS!AH65 -> 0 | W55: =IS!AI65 -> 0 | X55: =X56*W82 -> 0 | Y55: =Y56*X82 -> 0 | Z55: =SUM(V55:Y55) -> 0 | AB55: =AB56*Y82 -> 0 | AC55: =AC56*AB82 -> 0 | AD55: =AD56*AC82 -> 0 | AE55: =AE56*AD82 -> 0 | AF55: =SUM(AB55:AE55) -> 0 | AH55: =AH56*AF82 -> 0 | AJ55: =AJ56*AH82 -> 0 | AL55: =AL56*AJ82 -> 0
B56: % of intangibles excl. goodwill | D56: =D55/D82 -> 0 | E56: =E55/E82 -> 0 | F56: =F55/F82 -> 0 | G56: =G55/G82 -> 0 | H56: =H55/H82 -> 0 | J56: =J55/J82 -> 0 | K56: =K55/K82 -> 0 | L56: =L55/L82 -> 0 | M56: =M55/M82 -> 0 | N56: =N55/N82 -> 0 | P56: =P55/P82 -> 0 | Q56: =Q55/Q82 -> 0 | R56: =R55/R82 -> 0 | S56: =S55/S82 -> 0 | T56: =T55/T82 -> 0 | V56: =V55/V82 -> 0 | W56: =W55/W82 -> 0 | X56: 0 | Y56: 0 | Z56: =Z55/Z82 -> 0 | AB56: 0 | AC56: 0 | AD56: 0 | AE56: 0 | AF56: =AF55/AF82 -> 0 | AH56: 0 | AJ56: 0 | AL56: 0
B58: Other Operating (Income) Expenses | D58: =IS!P30+IS!P32 -> 221 | E58: =IS!Q30+IS!Q32 -> 259 | F58: =IS!R30+IS!R32 -> 276 | G58: =IS!S30+IS!S32 -> 555 | H58: =IS!T30+IS!T32 -> 1428 | J58: =IS!V30+IS!V32 -> 299 | K58: =IS!W30+IS!W32 -> 190 | L58: =IS!X30+IS!X32 -> 310 | M58: =IS!Y30+IS!Y32 -> 304 | N58: =IS!Z30+IS!Z32 -> 1101 | P58: =IS!AB30+IS!AB32 -> 369 | Q58: =IS!AC30+IS!AC32 -> 295 | R58: =IS!AD30+IS!AD32 -> 264 | S58: =IS!AE30+IS!AE32 -> 279 | T58: =IS!AF30+IS!AF32 -> 1009 | V58: =IS!AH30+IS!AH32 -> 281 | W58: =IS!AI30+IS!AI32 -> 287 | X58: =281 -> 281 | Y58: =Y59*Y$31 -> 165.8286 | Z58: =SUM(V58:Y58) -> 1014.8286 | AB58: =AB59*AB$31 -> 180 | AC58: =AC59*AC$31 -> 240 | AD58: =AD59*AD$31 -> 260 | AE58: =AE59*AE$31 -> 278.26 | AF58: =SUM(AB58:AE58) -> 958.26 | AH58: =AH59*AH$31 -> 1061.765 | AJ58: =AJ59*AJ$31 -> 1204.4636 | AL58: =AL59*AL$31 -> 1261.4796
B59: % of sales | D59: =D58/D31 -> 0.023095412 | E59: =E58/E31 -> 0.019371728 | F59: =F58/F31 -> 0.019571692 | G59: =G58/G31 -> 0.035723481 | H59: =H58/H31 -> 0.027160165 | J59: =J58/J31 -> 0.023632627 | K59: =K58/K31 -> 0.010927705 | L59: =L58/L31 -> 0.019619011 | M59: =M58/M31 -> 0.01972489 | N59: =N58/N31 -> 0.017975217 | P59: =P58/P31 -> 0.030283135 | Q59: =Q58/Q31 -> 0.019363308 | R59: =R58/R31 -> 0.020072993 | S59: =S58/S31 -> 0.025038141 | T59: =T58/T31 -> 0.019510403 | V59: =V58/V31 -> 0.033027739 | W59: =W58/W31 -> 0.022486876 | X59: =X58/X31 -> 0.023381594 | Y59: 0.014 | Z59: =Z58/Z$31 -> 0.022484842 | AB59: 0.02 | AC59: 0.02 | AD59: 0.02 | AE59: 0.02 | AF59: =AF58/AF$31 -> 0.020000196 | AH59: 0.02 | AJ59: 0.02 | AL59: 0.02
B61: EBIT (Operating Income) | D61: =IS!P33 -> 1470 | E61: =IS!Q33 -> 2808 | F61: =IS!R33 -> 2875 | G61: =IS!S33 -> 3000 | H61: =IS!T33 -> 10036 | J61: =IS!V33 -> 2972 | K61: =IS!W33 -> 4590 | L61: =IS!X33 -> 4229 | M61: =IS!Y33 -> 3872 | N61: =IS!Z33 -> 15663 | P61: =IS!AB33 -> 3017 | Q61: =IS!AC33 -> 3953 | R61: =IS!AD33 -> 3195 | S61: =IS!AE33 -> 2435 | T61: =IS!AF33 -> 12802 | V61: =IS!AH33 -> 1692 | W61: =IS!AI33 -> 3121 | X61: =X40-X43-X46-X49-X58 -> 2394 | Y61: =Y40-Y43-Y46-Y49-Y58 -> 2778.2213 | Z61: =SUM(V61:Y61) -> 9985.2213 | AB61: =AB40-AB43-AB46-AB49-AB58 -> 1845 | AC61: =AC40-AC43-AC46-AC49-AC58 -> 2460 | AD61: =AD40-AD43-AD46-AD49-AD58 -> 2782 | AE61: =AE40-AE43-AE46-AE49-AE58 -> 2977.382 | AF61: =SUM(AB61:AE61) -> 10064.382 | AH61: =AH40-AH43-AH46-AH49-AH58 -> 10883.091 | AJ61: =AJ40-AJ43-AJ46-AJ49-AJ58 -> 13429.769 | AL61: =AL40-AL43-AL46-AL49-AL58 -> 15768.495
B62: % of sales | D62: =D61/D31 -> 0.15362107 | E62: =E61/E31 -> 0.21002244 | F62: =F61/F31 -> 0.20387179 | G62: =G61/G31 -> 0.1930999 | H62: =H61/H31 -> 0.19088194 | J62: =J61/J31 -> 0.23490357 | K62: =K61/K31 -> 0.26399034 | L62: =L61/L31 -> 0.26764129 | M62: =M61/M31 -> 0.25123281 | N62: =N61/N31 -> 0.25571827 | P62: =P61/P31 -> 0.24759951 | Q62: =Q61/Q31 -> 0.25946833 | R62: =R61/R31 -> 0.24292883 | S62: =S61/S31 -> 0.21852284 | T62: =T61/T31 -> 0.24754428 | V62: =V61/V31 -> 0.19887165 | W62: =W61/W31 -> 0.24453498 | X62: =X61/X$31 -> 0.1992012 | Y62: =Y61/Y$31 -> 0.23455 | Z62: =Z61/Z$31 -> 0.22123551 | AB62: =AB61/AB$31 -> 0.205 | AC62: =AC61/AC$31 -> 0.205 | AD62: =AD61/AD$31 -> 0.214 | AE62: =AE61/AE$31 -> 0.214 | AF62: =AF61/AF$31 -> 0.21005741 | AH62: =AH61/AH$31 -> 0.205 | AJ62: =AJ61/AJ$31 -> 0.223 | AL62: =AL61/AL$31 -> 0.25
B64: Basic Weighted Average Shares | D64: =IS!P59 -> 307.4 | E64: =IS!Q59 -> 306.2 | F64: =IS!R59 -> 304.1 | G64: =IS!S59 -> 300.6 | H64: =IS!T59 -> 304.5 | J64: =IS!V59 -> 297.6 | K64: =IS!W59 -> 295.1 | L64: =IS!X59 -> 290.8 | M64: =IS!Y59 -> 285.5 | N64: =IS!Z59 -> 292.2 | P64: =IS!AB59 -> 279.9 | Q64: =IS!AC59 -> 276.8 | R64: =IS!AD59 -> 274.5 | S64: =IS!AE59 -> 272.6 | T64: =IS!AF59 -> 276 | V64: =IS!AH59 -> 271.6 | W64: =IS!AI59 -> 271.1 | X64: =W64+X101 -> 271.12611 | Y64: =X64+Y101 -> 271.14853 | Z64: =AVERAGE(V64:Y64) -> 271.24366 | AB64: =Y64+AB101 -> 271.16537 | AC64: =AB64+AC101 -> 271.18822 | AD64: =AC64+AD101 -> 271.21244 | AE64: =AD64+AE101 -> 271.23725 | AF64: =AVERAGE(AB64:AE64) -> 271.20082 | AH64: =AE64+AH101 -> 271.57901 | AJ64: =AF64+AJ101 -> 271.54301 | AL64: =AH64+AL101 -> 271.92116
B65: Diluted Weighted Average Shares | D65: =IS!P60 -> 309.4 | E65: =IS!Q60 -> 308.1 | F65: =IS!R60 -> 305.7 | G65: =IS!S60 -> 302.1 | H65: =IS!T60 -> 306.3 | J65: =IS!V60 -> 299.1 | K65: =IS!W60 -> 296.5 | L65: =IS!X60 -> 292.1 | M65: =IS!Y60 -> 286.9 | N65: =IS!Z60 -> 293.6 | P65: =IS!AB60 -> 281.1 | Q65: =IS!AC60 -> 277.9 | R65: =IS!AD60 -> 275.6 | S65: =IS!AE60 -> 273.6 | T65: =IS!AF60 -> 277.1 | V65: =IS!AH60 -> 272.3 | W65: =IS!AI60 -> 271.8 | X65: =W65 -> 271.8 | Y65: =X65 -> 271.8 | Z65: =AVERAGE(V65:Y65) -> 271.925 | AB65: =Y65 -> 271.8 | AC65: =AB65 -> 271.8 | AD65: =AC65 -> 271.8 | AE65: =AD65 -> 271.8 | AF65: =AVERAGE(AB65:AE65) -> 271.8 | AH65: =AF65 -> 271.8 | AJ65: =AH65 -> 271.8 | AL65: =AJ65 -> 271.8
B67: Balance Sheet | D67: Q1 22 | E67: Q2 22 | F67: Q3 22 | G67: Q4 22 | H67: FY 22 | J67: Q1 23 | K67: Q2 23 | L67: Q3 23 | M67: Q4 23 | N67: FY 23 | P67: Q1 24 | Q67: Q2 24 | R67: Q3 24 | S67: Q4 24 | T67: FY 24 | V67: Q1 25 | W67: Q2 25 | X67: Q3 25 | Y67: Q4 25 | Z67: FY 25 | AB67: Q1 26 | AC67: Q2 26 | AD67: Q3 26 | AE67: Q4 26 | AF67: FY 26 | AH67: FY 27 | AJ67: FY 28 | AL67: FY 29
B70: Accounts Receivable | D70: =BS!P18 -> 4855 | E70: =BS!Q18 -> 6258 | F70: =BS!R18 -> 6696 | G70: =BS!S18 -> 6410 | H70: =BS!T18 -> 6410 | J70: =BS!V18 -> 7609 | K70: =BS!W18 -> 9971 | L70: =BS!X18 -> 9297 | M70: =BS!Y18 -> 7739 | N70: =BS!Z18 -> 7739 | P70: =BS!AB18 -> 7795 | Q70: =BS!AC18 -> 8880 | R70: =BS!AD18 -> 7469 | S70: =BS!AE18 -> 5326 | T70: =BS!AF18 -> 5326 | V70: =BS!AH18 -> 4931 | W70: =BS!AI18 -> 6748 | X70: 6103 | Y70: =Y31*Y71/92 -> 5793.7011 | Z70: =Y70 -> 5793.7011 | AB70: =AB31*AB71/90 -> 4500 | AC70: =AC31*AC71/91 -> 5934.0659 | AD70: =AD31*AD71/92 -> 6358.6957 | AE70: =AE31*AE71/92 -> 6805.2717 | AF70: =AE70 -> 6805.2717 | AH70: =AH31*AH71/365 -> 6545.1267 | AJ70: =AJ31*AJ71/366 -> 7404.4893 | AL70: =AL31*AL71/365 -> 7776.244
B71: days sales outstanding | D71: =D70/D31*90 -> 45.663079 | E71: =E70/E31*91 -> 42.593717 | F71: =F70/F31*92 -> 43.684016 | G71: =G70/G31*92 -> 37.95829 | H71: =H70/H31*365 -> 44.499496 | J71: =J70/J31*90 -> 54.12662 | K71: =K70/K31*91 -> 52.186174 | L71: =L70/L31*92 -> 54.131004 | M71: =M70/M31*92 -> 46.196989 | N71: =N70/N31*365 -> 46.11737 | P71: =P70/P31*90 -> 57.574887 | Q71: =Q70/Q31*91 -> 53.041024 | R71: =R70/R31*92 -> 52.246655 | S71: =S70/S31*92 -> 43.973077 | T71: =T70/T31*365 -> 37.589721 | V71: =V70/V31*90 -> 52.161495 | W71: =W70/W31*91 -> 48.11314 | X71: =X70/X31*92 -> 46.719587 | Y71: 45 | Z71: =Z70/Z31*365 -> 46.853937 | AB71: 45 | AC71: 45 | AD71: 45 | AE71: 45 | AF71: =AF70/AF31*365 -> 51.842893 | AH71: 45 | AJ71: 45 | AL71: 45
B73: Inventory | D73: =BS!P19 -> 7935 | E73: =BS!Q19 -> 9030 | F73: =BS!R19 -> 9121 | G73: =BS!S19 -> 8495 | H73: =BS!T19 -> 8495 | J73: =BS!V19 -> 10056 | K73: =BS!W19 -> 9713 | L73: =BS!X19 -> 9350 | M73: =BS!Y19 -> 8160 | N73: =BS!Z19 -> 8160 | P73: =BS!AB19 -> 8937 | Q73: =BS!AC19 -> 8443 | R73: =BS!AD19 -> 7696 | S73: =BS!AE19 -> 7093 | T73: =BS!AF19 -> 7093 | V73: =BS!AH19 -> 7744 | W73: =BS!AI19 -> 7870 | X73: 7713 | Y73: =Y74*Y34/92 -> 6488.9452 | Z73: =Y73 -> 6488.9452 | AB73: =AB74*AB34/92 -> 5086.9565 | AC73: =AC74*AC34/92 -> 6782.6087 | AD73: =AD74*AD34/92 -> 7234.7826 | AE73: =AE74*AE34/92 -> 7742.887 | AF73: =AE73 -> 7742.887 | AH73: =AH74*AH34/365 -> 7563.2575 | AJ73: =AJ74*AJ34/366 -> 8293.0281 | AL73: =AL74*AL34/365 -> 8294.6603
B74: days inventory held | D74: =D73/D34*90 -> 106.66916 | E74: =E73/E34*91 -> 92.142857 | F74: =F73/F34*92 -> 88.227526 | G74: =G73/G34*92 -> 76.516546 | H74: =H73/H34*365 -> 87.743364 | J74: =J73/J34*90 -> 114.07109 | K74: =K73/K34*91 -> 82.37493 | L74: =L73/L34*92 -> 89.380715 | M74: =M73/M34*92 -> 79.635091 | N74: =N73/N34*365 -> 78.971232 | P74: =P73/P34*90 -> 111.7125 | Q74: =Q73/Q34*91 -> 83.904445 | R74: =R73/R34*92 -> 90.218145 | S74: =S73/S34*92 -> 99.308477 | T74: =T73/T34*365 -> 84.124939 | V74: =V73/V34*90 -> 138.36808 | W74: =W73/W34*91 -> 94.121435 | X74: =X73/X34*92 -> 93.737913 | Y74: 80 | Z74: =Z73/Z34*365 -> 85.571228 | AB74: 80 | AC74: 80 | AD74: 80 | AE74: 80 | AF74: =AF73/AF34*365 -> 91.53736 | AH74: 80 | AJ74: 80 | AL74: 80
B76: Prepaid expenses and Other Current Assets | D76: =BS!P20 -> 1936 | E76: =BS!Q20 -> 2306 | F76: =BS!R20 -> 1999 | G76: =BS!S20 -> 2492 | H76: =BS!T20 -> 2492 | J76: =BS!V20 -> 1992 | K76: =BS!W20 -> 2593 | L76: =BS!X20 -> 3118 | M76: =BS!Y20 -> 2623 | N76: =BS!Z20 -> 2623 | P76: =BS!AB20 -> 2017 | Q76: =BS!AC20 -> 2535 | R76: =BS!AD20 -> 5235 | S76: =BS!AE20 -> 5489 | T76: =BS!AF20 -> 5489 | V76: =BS!AH20 -> 5908 | W76: =BS!AI20 -> 2975 | X76: =X77*X$31 -> 4807.2 | Y76: =Y77*Y$31 -> 4737.96 | Z76: =Y76 -> 4737.96 | AB76: =AB77*AB$31 -> 3600 | AC76: =AC77*AC$31 -> 4800 | AD76: =AD77*AD$31 -> 5200 | AE76: =AE77*AE$31 -> 5565.2 | AF76: =AE76 -> 5565.2 | AH76: =AH77*AH$31 -> 5308.825 | AJ76: =AJ77*AJ$31 -> 6022.318 | AL76: =AL77*AL$31 -> 6307.398
B77: % of sales | D77: =D76/D31 -> 0.20231999 | E77: =E76/E31 -> 0.17247569 | F77: =F76/F31 -> 0.14175294 | G77: =G76/G31 -> 0.16040165 | H77: =H76/H31 -> 0.047397151 | J77: =J76/J31 -> 0.15744546 | K77: =K76/K31 -> 0.14913441 | L77: =L76/L31 -> 0.19732928 | M77: =M76/M31 -> 0.17019206 | N77: =N76/N31 -> 0.042823791 | P77: =P76/P31 -> 0.16553139 | Q77: =Q76/Q31 -> 0.16639317 | R77: =R76/R31 -> 0.39803832 | S77: =S76/S31 -> 0.49259625 | T77: =T76/T31 -> 0.10613737 | V77: =V76/V31 -> 0.69440527 | W77: =W76/W31 -> 0.23309567 | X77: 0.4 | Y77: 0.4 | Z77: =Z76/Z$31 -> 0.10497564 | AB77: 0.4 | AC77: 0.4 | AD77: 0.4 | AE77: 0.4 | AF77: =AF76/AF$31 -> 0.11615333 | AH77: 0.1 | AJ77: 0.1 | AL77: 0.1
B79: Net PP&E (Property, Plant and Equipment) | D79: =BS!P24 -> 12289 | E79: =BS!Q24 -> 12180 | F79: =BS!R24 -> 12220 | G79: =BS!S24 -> 12679 | H79: =BS!T24 -> 12679 | J79: =BS!V24 -> 12714 | K79: =BS!W24 -> 12812 | L79: =BS!X24 -> 13127 | M79: =BS!Y24 -> 13796 | N79: =BS!Z24 -> 13796 | P79: =BS!AB24 -> 13665 | Q79: =BS!AC24 -> 13999 | R79: =BS!AD24 -> 14210 | S79: =BS!AE24 -> 15031 | T79: =BS!AF24 -> 15031 | V79: =BS!AH24 -> 14582 | W79: =BS!AI24 -> 14891 | X79: 7713 | Y79: =X79-Y80*Y106-Y109-Y52-Y37 -> 7287.044 | Z79: =Y79 -> 7287.044 | AB79: =Y79-AB80*AB106-AB109-AB52-AB37 -> 6955.844 | AC79: =AB79-AC80*AC106-AC109-AC52-AC37 -> 6514.244 | AD79: =AC79-AD80*AD106-AD109-AD52-AD37 -> 6035.844 | AE79: =AD79-AE80*AE106-AE109-AE52-AE37 -> 5523.8456 | AF79: =AE79 -> 5523.8456 | AH79: =AF79-AH80*AH106-AH109-AH52-AH37 -> 3570.198 | AJ79: =AH79-AJ80*AJ106-AJ109-AJ52-AJ37 -> 1353.985 | AL79: =AJ79-AL80*AL106-AL109-AL52-AL37 -> -967.13747
B80: capex allocation rate | D80: =-D106/D31 -> 0.028320619 | E80: =-E106/E31 -> 0.012640239 | F80: =-F106/F31 -> 0.010707701 | G80: =-G106/G31 -> 0.014482492 | H80: =-H106/H31 -> 0.015520094 | J80: =-J106/J31 -> 0.024897249 | K80: =-K106/K31 -> 0.015471329 | L80: =-L106/L31 -> 0.019176002 | M80: =-M106/M31 -> 0.039774202 | N80: =-N106/N31 -> 0.024489396 | O80: =-O106/O31 -> #DIV/0! | P80: =-P106/P31 -> 0.029708658 | Q80: =-Q106/Q31 -> 0.023432885 | ... W80: =-W106/W31 -> 0.015905351 | X80: 0.08 | Y80: 0.08 | Z80: =AVERAGE(V80:Y80) -> 0.054319544 | AB80: 0.08 | AC80: 0.08 | AD80: 0.08 | AE80: 0.08 | AF80: =AVERAGE(AB80:AE80) -> 0.08 | AH80: 0.08 | AJ80: 0.08 | AL80: 0.08
B82: Intangibles | D82: =IF($B$82="Intangibles excl. Goodwill",BS!P29,BS!P27) -> 4401 | E82: =IF($B$82="Intangibles excl. Goodwill",BS!Q29,BS!Q27) -> 5164 | F82: =IF($B$82="Intangibles excl. Goodwill",BS!R29,BS!R27) -> 5035 | G82: =IF($B$82="Intangibles excl. Goodwill",BS!S29,BS!S27) -> 4905 | H82: =IF($B$82="Intangibles excl. Goodwill",BS!T29,BS!T27) -> 4905 | J82: =IF($B$82="Intangibles excl. Goodwill",BS!V29,BS!V27) -> 5146 | K82: =IF($B$82="Intangibles excl. Goodwill",BS!W29,BS!W27) -> 5185 | L82: =IF($B$82="Intangibles excl. Goodwill",BS!X29,BS!X27) -> 5193 | M82: =IF($B$82="Intangibles excl. Goodwill",BS!Y29,BS!Y27) -> 5033 | N82: =IF($B$82="Intangibles excl. Goodwill",BS!Z29,BS!Z27) -> 5033 | P82: =IF($B$82="Intangibles excl. Goodwill",BS!AB29,BS!AB27) -> 5078 | Q82: =IF($B$82="Intangibles excl. Goodwill",BS!AC29,BS!AC27) -> 5000 | R82: =IF($B$82="Intangibles excl. Goodwill",BS!AD29,BS!AD27) -> 4990 | S82: =IF($B$82="Intangibles excl. Goodwill",BS!AE29,BS!AE27) -> 4958 | T82: =IF($B$82="Intangibles excl. Goodwill",BS!AF29,BS!AF27) -> 4958 | V82: =IF($B$82="Intangibles excl. Goodwill",BS!AH29,BS!AH27) -> 4809 | W82: =IF($B$82="Intangibles excl. Goodwill",BS!AI29,BS!AI27) -> 5058 | X82: =W82-(1-X80)*X106-X55+X83*X46 -> 5331.24 | Y82: =X82-(1-Y80)*Y106-Y55+Y83*Y46 -> 5881.4 | Z82: =Y82 -> 5881.4 | AB82: =Y82-(1-AB80)*AB106-AB55+AB83*AB46 -> 6212.6 | AC82: =AB82-(1-AC80)*AC106-AC55+AC83*AC46 -> 6654.2 | AD82: =AC82-(1-AD80)*AD106-AD55+AD83*AD46 -> 7132.6 | AE82: =AD82-(1-AE80)*AE106-AE55+AE83*AE46 -> 7644.5984 | AF82: =AE82 -> 7644.5984 | AH82: =AF82-(1-AH80)*AH106-AH55+AH83*AH46 -> 9598.246 | AJ82: =AH82-(1-AJ80)*AJ106-AJ55+AJ83*AJ46 -> 11814.459 | AL82: =AJ82-(1-AL80)*AL106-AL55+AL83*AL46 -> 14135.581
B83: r&d capitalization rate | D83: =IFERROR(BS!P57/FCFF!D82,"") -> 0 | E83: =IFERROR(BS!Q57/FCFF!E82,"") -> 0 | F83: =IFERROR(BS!R57/FCFF!F82,"") -> 0 | G83: =IFERROR(BS!S57/FCFF!G82,"") -> 0 | H83: =IFERROR(BS!T57/FCFF!H82,"") -> 0 | J83: =IFERROR(BS!V57/FCFF!J82,"") -> 0 | K83: =IFERROR(BS!W57/FCFF!K82,"") -> 0 | L83: =IFERROR(BS!X57/FCFF!L82,"") -> 0 | M83: =IFERROR(BS!Y57/FCFF!M82,"") -> 0 | N83: =IFERROR(BS!Z57/FCFF!N82,"") -> 0 | P83: =IFERROR(BS!AB57/FCFF!P82,"") -> 0 | Q83: =IFERROR(BS!AC57/FCFF!Q82,"") -> 0 | R83: =IFERROR(BS!AD57/FCFF!R82,"") -> 0 | S83: =IFERROR(BS!AE57/FCFF!S82,"") -> 0 | T83: =IFERROR(BS!AF57/FCFF!T82,"") -> 0 | V83: =IFERROR(BS!AH57/FCFF!V82,"") -> 0 | W83: =IFERROR(BS!AI57/FCFF!W82,"") -> 0 | X83: 0 | Y83: 0 | Z83: =AVERAGE(V83:Y83) -> 0 | AB83: 0 | AC83: 0 | AD83: 0 | AE83: 0 | AF83: =AVERAGE(AB83:AE83) -> 0 | AH83: 0 | AJ83: 0 | AL83: 0
B85: Accounts Payable | D85: =BS!P37 -> 10108 | E85: =BS!Q37 -> 11899 | F85: =BS!R37 -> 12319 | G85: =BS!S37 -> 12333 | H85: =BS!T37 -> 12333 | J85: =BS!V37 -> 12217 | K85: =BS!W37 -> 12844 | L85: =BS!X37 -> 13210 | M85: =BS!Y37 -> 13592 | N85: =BS!Z37 -> 13592 | P85: =BS!AB37 -> 12621 | Q85: =BS!AC37 -> 12320 | R85: =BS!AD37 -> 12569 | S85: =BS!AE37 -> 12452 | T85: =BS!AF37 -> 12452 | V85: =BS!AH37 -> 11946 | W85: =BS!AI37 -> 11312 | X85: 11182 | Y85: =Y86*Y34/92 -> 11355.654 | Z85: =Y85 -> 11355.654 | AB85: =AB86*AB34/90 -> 9100 | AC85: =AC86*AC34/91 -> 12000 | AD85: =AD86*AD34/92 -> 12660.87 | AE85: =AE86*AE34/92 -> 13550.052 | AF85: =AE85 -> 13550.052 | AH85: =AH86*AH34/365 -> 13235.701 | AJ85: =AJ86*AJ34/366 -> 14512.799 | AL85: =AL86*AL34/365 -> 14515.656
B86: days payable outstanding | D86: =D85/D34*90 -> 135.88051 | E86: =E85/E34*91 -> 121.41837 | F86: =F85/F34*92 -> 119.16181 | G86: =G85/G34*92 -> 111.08635 | H86: =H85/H34*365 -> 127.38539 | J86: =J85/J34*90 -> 138.58457 | K86: =K85/K34*91 -> 108.92861 | L86: =L85/L34*92 -> 126.28013 | M86: =M85/M34*92 -> 132.64708 | N86: =N85/N34*365 -> 131.5413 | P86: =P85/P34*90 -> 157.7625 | Q86: =Q85/Q34*91 -> 122.43311 | R86: =R85/R34*92 -> 147.34302 | S86: =S85/S34*92 -> 174.33937 | T86: =T85/T34*365 -> 147.68416 | V86: =V85/V34*90 -> 213.44848 | W86: =W85/W34*91 -> 135.28611 | X86: =X85/X34*92 -> 135.89749 | Y86: 140 | Z86: =Z85/Z34*365 -> 149.74965 | AB86: 140 | AC86: 140 | AD86: 140 | AE86: 140 | AF86: =AF85/AF34*365 -> 160.19038 | AH86: 140 | AJ86: 140 | AL86: 140
B88: Accrued Expenses and Other Current Liabilities | D88: =BS!P40 -> 276 | E88: =BS!Q40 -> 780 | F88: =BS!R40 -> 667 | G88: =BS!S40 -> 2187 | H88: =BS!T40 -> 2187 | J88: =BS!V40 -> 891 | K88: =BS!W40 -> 1872 | L88: =BS!X40 -> 2130 | M88: =BS!Y40 -> 2257 | N88: =BS!Z40 -> 2257 | P88: =BS!AB40 -> 740 | Q88: =BS!AC40 -> 2289 | R88: =BS!AD40 -> 3631 | S88: =BS!AE40 -> 1821 | T88: =BS!AF40 -> 1821 | V88: =BS!AH40 -> 216 | W88: =BS!AI40 -> 2033 | X88: 2000 | Y88: =Y89*Y43 -> 1279.2492 | Z88: =Y88 -> 1279.2492 | AB88: =AB89*AB43 -> 972 | AC88: =AC89*AC43 -> 1296 | AD88: =AD89*AD43 -> 1404 | AE88: =AE89*AE43 -> 1502.604 | AF88: =AE88 -> 1502.604 | AH88: =AH89*AH43 -> 1672.2799 | AJ88: =AJ89*AJ43 -> 1897.0302 | AL88: =AL89*AL43 -> 1986.8304
B89: % of sg&a | D89: =D88/D43 -> 0.35339309 | E89: =E88/E43 -> 0.83690987 | F89: =F88/F43 -> 0.69551616 | G89: =G88/G43 -> 1.836272 | H89: =H88/H43 -> 0.56614031 | J89: =J88/J43 -> 0.93592437 | K89: =K88/K43 -> 1.4075188 | L89: =L88/L43 -> 1.9189189 | M89: =M88/M43 -> 1.876143 | N89: =N88/N43 -> 0.49118607 | P89: =P88/P43 -> 0.69418386 | Q89: =Q88/Q43 -> 1.8094862 | R89: =R88/R43 -> 2.8411581 | S89: =S88/S43 -> 1.4780844 | T89: =T88/T43 -> 0.37623967 | V89: =V88/V43 -> 0.22222222 | W89: =W88/W43 -> 1.6984127 | X89: =X88/X43 -> 1.6433854 | Y89: 1.2 | Z89: =Z88/Z43 -> 0.28733994 | AB89: 1.2 | AC89: 1.2 | AD89: 1.2 | AE89: 1.2 | AF89: =AF88/AF43 -> 0.34845658 | AH89: 0.35 | AJ89: 0.35 | AL89: 0.35
B91: Cash Flow Statement | D91: Q1 22 | E91: Q2 22 | F91: Q3 22 | G91: Q4 22 | H91: FY 22 | J91: Q1 23 | K91: Q2 23 | L91: Q3 23 | M91: Q4 23 | N91: FY 23 | P91: Q1 24 | Q91: Q2 24 | R91: Q3 24 | S91: Q4 24 | T91: FY 24 | V91: Q1 25 | W91: Q2 25 | X91: Q3 25 | Y91: Q4 25 | Z91: FY 25 | AB91: Q1 26 | AC91: Q2 26 | AD91: Q3 26 | AE91: Q4 26 | AF91: FY 26 | AH91: FY 27 | AJ91: FY 28 | AL91: FY 29
B94: D&A (Depreciation & Amortization) | D94: =CF!P17 -> 486 | E94: =CF!Q17 -> 447 | F94: =CF!R17 -> 510 | G94: =CF!S17 -> 452 | H94: =CF!T17 -> 1895 | J94: =CF!V17 -> 494 | K94: =CF!W17 -> 501 | L94: =CF!X17 -> 532 | M94: =CF!Y17 -> 477 | N94: =CF!Z17 -> 2004 | P94: =CF!AB17 -> 520 | Q94: =CF!AC17 -> 525 | R94: =CF!AD17 -> 553 | S94: =CF!AE17 -> 520 | T94: =CF!AF17 -> 2118 | V94: =CF!AH17 -> 549 | W94: =CF!AI17 -> 555 | X94: =X95*(X79+X82) -> 352.19448 | Y94: =Y95*(Y79+Y82) -> 355.54799 | Z94: =SUM(V94:Y94) -> 1811.7425 | AB94: =AB95*(AB79+AB82) -> 355.54799 | AC94: =AC95*(AC79+AC82) -> 355.54799 | AD94: =AD95*(AD79+AD82) -> 355.54799 | AE94: =AE95*(AE79+AE82) -> 355.54799 | AF94: =SUM(AB94:AE94) -> 1422.192 | AH94: =AH95*(AH79+AH82) -> 355.54799 | AJ94: =AJ95*(AJ79+AJ82) -> 355.54799 | AL94: =AL95*(AL79+AL82) -> 355.54799
B95: % of net pp&e and intangibles excl. Goodwill | D95: =D94/(D82+D79) -> 0.029119233 | E95: =E94/(E82+E79) -> 0.025772601 | F95: =F94/(F82+F79) -> 0.02955665 | G95: =G94/(G82+G79) -> 0.025705187 | H95: =H94/(H82+H79) -> 0.10776843 | J95: =J94/(J82+J79) -> 0.027659574 | K95: =K94/(K82+K79) -> 0.027837973 | L95: =L94/(L82+L79) -> 0.029039301 | M95: =M94/(M82+M79) -> 0.025333263 | N95: =N94/(N82+N79) -> 0.10643157 | P95: =P94/(P82+P79) -> 0.027743691 | Q95: =Q94/(Q82+Q79) -> 0.027633033 | R95: =R94/(R82+R79) -> 0.028802083 | S95: =S94/(S82+S79) -> 0.026014308 | T95: =T94/(T82+T79) -> 0.10595828 | V95: =V94/(V82+V79) -> 0.028312104 | W95: =W94/(W82+W79) -> 0.027820943 | X95: 0.027 | Y95: 0.027 | Z95: =Z94/(Z79+Z82) -> 0.13758212 | AB95: 0.027 | AC95: 0.027 | AD95: 0.027 | AE95: 0.027 | AF95: =AF94/(AF79+AF82) -> 0.108 | AH95: 0.027 | AJ95: 0.027 | AL95: 0.027
B97: Stock-Based Compensation Expense | D97: =CF!P18 -> 18 | E97: =CF!Q18 -> 26 | F97: =CF!R18 -> 20 | G97: =CF!S18 -> 21 | H97: =CF!T18 -> 85 | J97: =CF!V18 -> 23 | K97: =CF!W18 -> 31 | L97: =CF!X18 -> 58 | M97: =CF!Y18 -> 18 | N97: =CF!Z18 -> 130 | P97: =CF!AB18 -> 46 | Q97: =CF!AC18 -> 58 | R97: =CF!AD18 -> 55 | S97: =CF!AE18 -> 49 | T97: =CF!AF18 -> 208 | V97: =CF!AH18 -> 28 | W97: =CF!AI18 -> 26 | X97: =X98*X43 -> 49.897 | Y97: =Y98*Y43 -> 37.311435 | Z97: =SUM(V97:Y97) -> 141.20844 | AB97: =AB98*AB43 -> 28.35 | AC97: =AC98*AC43 -> 37.8 | AD97: =AD98*AD43 -> 40.95 | AE97: =AE98*AE43 -> 43.82595 | AF97: =SUM(AB97:AE97) -> 150.92595 | AH97: =AH98*AH43 -> 167.22799 | AJ97: =AJ98*AJ43 -> 189.70302 | AL97: =AL98*AL43 -> 198.68304
B98: % of sg&a | D98: =D97/D43 -> 0.023047375 | E98: =E97/E43 -> 0.027896996 | F98: =F97/F43 -> 0.020855057 | G98: =G97/G43 -> 0.017632242 | H98: =H97/H43 -> 0.022003624 | J98: =J97/J43 -> 0.024159664 | K98: =K97/K43 -> 0.023308271 | L98: =L97/L43 -> 0.052252252 | M98: =M97/M43 -> 0.014962594 | N98: =N97/N43 -> 0.028291621 | P98: =P97/P43 -> 0.04315197 | Q98: =Q97/Q43 -> 0.045849802 | R98: =R97/R43 -> 0.043035994 | S98: =S97/S43 -> 0.039772727 | T98: =T97/T43 -> 0.042975207 | V98: =V97/V43 -> 0.028806584 | W98: =W97/W43 -> 0.021720969 | X98: 0.041 | Y98: 0.035 | Z98: =Z97/Z43 -> 0.031717685 | AB98: 0.035 | AC98: 0.035 | AD98: 0.035 | AE98: 0.035 | AF98: =AF97/AF43 -> 0.035 | AH98: 0.035 | AJ98: 0.035 | AL98: 0.035
B99: implied equity value (p/s multiple) | D99: =116.01/(D31/1000) -> 12.123524 | E99: =115.83/(E31/1000) -> 8.6634256 | F99: =106.79/(F31/1000) -> 7.5726847 | G99: =127.87/(G31/1000) -> 8.2305613 | H99: =127.87/(H31/1000) -> 2.432052 | J99: =124.27/(J31/1000) -> 9.8221625 | K99: =112.02/(K31/1000) -> 6.4427446 | L99: =125.23/(L31/1000) -> 7.9254478 | M99: =112.06/(M31/1000) -> 7.2709577 | N99: =112.06/(N31/1000) -> 1.8295212 | P99: =110.21/(P31/1000) -> 9.0447271 | Q99: =109.49/(Q31/1000) -> 7.1867411 | R99: =106.52/(R31/1000) -> 8.0991484 | S99: =111.61/(S31/1000) -> 10.016154 | T99: =116.61/(T31/1000) -> 2.2548148 | V99: =130.39/(V31/1000) -> 15.325576 | W99: =124.66/(W31/1000) -> 9.7672961 | X99: =140.12/(X31/1000) -> 11.659178 | Y99: 10 | Z99: =2.5 -> 2.5 | AB99: 10 | AC99: 10 | AD99: 10 | AE99: 10 | AF99: 2.5 | AH99: 2.5 | AJ99: 2.5 | AL99: 2.5
B100: implied share price (for dilution) | D100: =D99*(D31+IS!M18+IS!L18+IS!K18)/IS!M59 -> 1744.0701 | E100: =E99*(E31+D31+IS!M18+IS!L18)/D64 -> 1290.5799 | F100: =F99*(F31+E31+D31+IS!M18)/E64 -> 1196.1973 | G100: =G99*(G31+F31+E31+D31)/F64 -> 1423.0129 | H100: =AVERAGE(D100:G100) -> 1413.465 | I100: =I99*(I31+H31+G31+F31)/H64 -> 0 | J100: =J99*(J31+G31+F31+E31)/G64 -> 1818.7011 | K100: =K99*(K31+J31+G31+F31)/J64 -> 1291.9478 | L100: =L99*(L31+K31+J31+G31)/K64 -> 1648.3642 | M100: =M99*(M31+L31+K31+J31)/L64 -> 1531.5017 | N100: =AVERAGE(J100:M100) -> 1572.6287 | O100: =O99*(O31+N31+M31+L31)/N64 -> 0 | P100: =P99*(P31+L31+K31+M31)/M64 -> 1925.6873 | Q100: =Q99*(Q31+P31+M31+L31)/P64 -> 1505.4669 | R100: =R99*(R31+Q31+P31+M31)/Q64 -> 1638.0879 | S100: =S99*(S31+R31+Q31+P31)/R64 -> 1887.0142 | T100: =AVERAGE(P100:S100) -> 1739.0641 | V100: =V99*(V31+S31+R31+Q31)/S64 -> 2700.6971 | W100: =W99*(W31+V31+S31+R31)/V64 -> 1638.6473 | X100: =X99*(X31+W31+V31+S31)/W64 -> 1910.8838 | Y100: =Y99*(Y31+X31+W31+V31)/X64 -> 1664.6829 | Z100: =AVERAGE(V100:Y100) -> 1978.7278 | AB100: =AB99*(AB31+Y31+X31+W31)/Y64 -> 1682.6903 | AC100: =AC99*(AC31+AB31+Y31+X31)/AB64 -> 1654.448 | AD100: =AD99*(AD31+AC31+AB31+Y31)/AC64 -> 1690.5196 | AE100: =AE99*(AE31+AD31+AC31+AB31)/AD64 -> 1766.6225 | AF100: =AVERAGE(AB100:AE100) -> 1698.5701 | AH100: =AH99*AH31/AE64 -> 489.31562 | AJ100: =AJ99*AJ31/AH64 -> 554.37992 | AL100: =AL99*AL31/AJ64 -> 580.69971
B101: sbc dilution (shares issued) | D101: =D97/D100 -> 0.010320686 | E101: =E97/E100 -> 0.020145983 | F101: =F97/F100 -> 0.01671965 | G101: =G97/G100 -> 0.014757421 | H101: =AVERAGE(D101:G101) -> 0.015485935 | J101: =J97/J100 -> 0.012646388 | K101: =K97/K100 -> 0.023994777 | L101: =L97/L100 -> 0.035186398 | M101: =M97/M100 -> 0.01175317 | N101: =AVERAGE(J101:M101) -> 0.020895183 | P101: =P97/P100 -> 0.023887574 | Q101: =Q97/Q100 -> 0.038526254 | R101: =R97/R100 -> 0.033575732 | S101: =S97/S100 -> 0.025966949 | T101: =AVERAGE(P101:S101) -> 0.030489127 | V101: =V97/V100 -> 0.010367694 | W101: =W97/W100 -> 0.015866745 | X101: =X97/X100 -> 0.026112001 | Y101: =Y97/Y100 -> 0.022413539 | Z101: =AVERAGE(V101:Y101) -> 0.018689995 | AB101: =AB97/AB100 -> 0.01684802 | AC101: =AC97/AC100 -> 0.0228475 | AD101: =AD97/AD100 -> 0.024223322 | AE101: =AE97/AE100 -> 0.024807762 | AF101: =AVERAGE(AB101:AE101) -> 0.022181651 | AH101: =AH97/AH100 -> 0.34175894 | AJ101: =AJ97/AJ100 -> 0.34218955 | AL101: =AL97/AL100 -> 0.3421442
B103: Changes in Net Working Capital | D103: =SUM(CF!P21:P24) -> -3141 | E103: =SUM(CF!Q21:Q24) -> -1241 | F103: =SUM(CF!R21:R24) -> -434 | G103: =SUM(CF!S21:S24) -> 1516 | H103: =SUM(CF!T21:T24) -> -3300 | J103: =SUM(CF!V21:V24) -> -3672 | K103: =SUM(CF!W21:W24) -> -2126 | L103: =SUM(CF!X21:X24) -> -472 | M103: =SUM(CF!Y21:Y24) -> 3103 | N103: =SUM(CF!Z21:Z24) -> -3167 | P103: =SUM(CF!AB21:AB24) -> -3144 | Q103: =SUM(CF!AC21:AC24) -> -1063 | R103: =SUM(CF!AD21:AD24) -> 1011 | S103: =SUM(CF!AE21:AE24) -> 3242 | T103: =SUM(CF!AF21:AF24) -> 46 | V103: =SUM(CF!AH21:AH24) -> -2117 | W103: =SUM(CF!AI21:AI24) -> -769 | X103: =-((X70+X73+X76-X85-X88)-(W70+W73+W76-W85-W88)) -> -1193.2 | Y103: =-((Y70+Y73+Y76-Y85-Y88)-(X70+X73+X76-X85-X88)) -> 1055.497 | Z103: =SUM(V103:Y103) -> -3023.703 | AB103: =-((AB70+AB73+AB76-AB85-AB88)-(Y70+Y73+Y76-Y85-Y88)) -> 1270.7465 | AC103: =-((AC70+AC73+AC76-AC85-AC88)-(AB70+AB73+AB76-AB85-AB88)) -> -1105.7181 | AD103: =-((AD70+AD73+AD76-AD85-AD88)-(AC70+AC73+AC76-AC85-AC88)) -> -507.93407 | AE103: =-((AE70+AE73+AE76-AE85-AE88)-(AD70+AD73+AD76-AD85-AD88)) -> -332.09383 | AF103: =SUM(AB103:AE103) -> -674.99955 | AH103: =-((AH70+AH73+AH76-AH85-AH88)-(AF70+AF73+AF76-AF85-AF88)) -> 551.47384 | AJ103: =-((AJ70+AJ73+AJ76-AJ85-AJ88)-(AH70+AH73+AH76-AH85-AH88)) -> -800.77744 | AL103: =-((AL70+AL73+AL76-AL85-AL88)-(AJ70+AJ73+AJ76-AJ85-AJ88)) -> -565.81028
B104: % of change in sales | D104: =D103/(D31-IS!M18) -> 1.7866894 | E104: =E103/(E31-D31) -> -0.32649303 | F104: =F103/(F31-E31) -> -0.59289617 | G104: =G103/(G31-F31) -> 1.0571827 | H104: =H103/IS!N18 -> -0.074959113 | J104: =J103/(J31-IS!S18) -> 1.2732316 | K104: =K103/(K31-J31) -> -0.44899683 | L104: =L103/(L31-K31) -> 0.29760404 | M104: =M103/(M31-L31) -> -7.9768638 | N104: =N103/IS!T18 -> -0.060235464 | P104: =P103/(P31-IS!Y18) -> 0.97427952 | Q104: =Q103/(Q31-P31) -> -0.34852459 | R104: =R103/(R31-Q31) -> -0.48535766 | S104: =S103/(S31-R31) -> -1.6137382 | T104: =T103/IS!Z18 -> 0.00075100815 | V104: =V103/(V31-IS!AE18) -> 0.80341556 | W104: =W103/(W31-V31) -> -0.18072855 | X104: =X103/(X31-W31) -> 1.6016107 | Y104: =Y103/(Y31-X31) -> -6.0976142 | Z104: =Z103/(Z31-T31) -> 0.45938272 | AB104: =AB103/(AB31-IS!AK18) -> 0.14119405 | AC104: =AC103/(AC31-AB31) -> -0.3685727 | AD104: =AD103/(AD31-AC31) -> -0.50793407 | AE104: =AE103/(AE31-AD31) -> -0.36373913 | AF104: =AF103/(AF31-Z31) -> -0.24292531 | AH104: =AH103/(AH31-AF31) -> 0.10655017 | AJ104: =AJ103/(AJ31-AH31) -> -0.1122334 | AL104: =AL103/(AL31-AJ31) -> -0.19847425
B106: Capital Expenditures | D106: =CF!D28 -> -271 | E106: =CF!E28 -> -169 | F106: =CF!F28 -> -151 | G106: =CF!G28 -> -225 | H106: =CF!H28 -> -816 | J106: =CF!V28 -> -315 | K106: =CF!W28 -> -269 | L106: =CF!X28 -> -303 | M106: =CF!Y28 -> -613 | N106: =CF!Z28 -> -1500 | P106: -362 | Q106: =-357 -> -357 | R106: =-324 -> -324 | S106: =-557 -> -557 | T106: =SUM(P106:S106) -> -1600 | V106: =-352 -> -352 | W106: -203 | X106: -297 | Y106: =-598 -> -598 | Z106: =SUM(V106:Y106) -> -1450 | AB106: =-AB$31*(AB107+Sensitivity!$U$38) -> -360 | AC106: =-AC$31*(AC107+Sensitivity!$U$38) -> -480 | AD106: =-AD$31*(AD107+Sensitivity!$U$38) -> -520 | AE106: =-AE$31*(AE107+Sensitivity!$U$38) -> -556.52 | AF106: =SUM(AB106:AE106) -> -1916.52 | AH106: =-AH$31*(AH107+Sensitivity!$U$38) -> -2123.53 | AJ106: =-AJ$31*(AJ107+Sensitivity!$U$38) -> -2408.9272 | AL106: =-AL$31*(AL107+Sensitivity!$U$38) -> -2522.9592
B107: % of sales | D107: =-D106/D31 -> 0.028320619 | E107: =-E106/E31 -> 0.012640239 | F107: =-F106/F31 -> 0.010707701 | G107: =-G106/G31 -> 0.014482492 | H107: =-H106/H31 -> 0.015520094 | J107: =-J106/J31 -> 0.024897249 | K107: =-K106/K31 -> 0.015471329 | L107: =-L106/L31 -> 0.019176002 | M107: =-M106/M31 -> 0.039774202 | N107: =-N106/N31 -> 0.024489396 | P107: =-P106/P31 -> 0.029708658 | Q107: =-Q106/Q31 -> 0.023432885 | R107: =-R106/R31 -> 0.024635036 | S107: =-S106/S31 -> 0.049986539 | T107: =-T106/T31 -> 0.030938201 | V107: =-V106/V31 -> 0.041372826 | W107: =-W106/W31 -> 0.015905351 | X107: =-X106/X31 -> 0.024712931 | Y107: =-Y106/Y31 -> 0.050485863 | Z107: =-Z106/Z$31 -> 0.032126628 | AB107: 0.04 | AC107: 0.04 | AD107: 0.04 | AE107: 0.04 | AF107: =-AF106/AF$31 -> 0.040000392 | AH107: 0.04 | AJ107: 0.04 | AL107: 0.04
B109: Proceeds from Asset Disposals | D109: =CF!P29 -> 479 | E109: =CF!Q29 -> 556 | F109: =CF!R29 -> 466 | G109: =CF!S29 -> 592 | H109: =CF!T29 -> 2093 | J109: =CF!V29 -> 497 | K109: =CF!W29 -> 496 | L109: =CF!X29 -> 452 | M109: =CF!Y29 -> 536 | N109: =CF!Z29 -> 1981 | P109: =CF!AB29 -> 506 | Q109: =CF!AC29 -> 505 | R109: =CF!AD29 -> 440 | S109: =CF!AE29 -> 478 | T109: =CF!AF29 -> 1929 | V109: =CF!AH29 -> 433 | W109: =CF!AI29 -> 568 | X109: =X110*X31 -> 480.72 | Y109: =Y110*Y31 -> 473.796 | Z109: =SUM(V109:Y109) -> 1955.516 | AB109: =AB110*AB31 -> 360 | AC109: =AC110*AC31 -> 480 | AD109: =AD110*AD31 -> 520 | AE109: =AE110*AE31 -> 556.52 | AF109: =SUM(AB109:AE109) -> 1916.52 | AH109: =AH110*AH31 -> 2123.53 | AJ109: =AJ110*AJ31 -> 2408.9272 | AL109: =AL110*AL31 -> 2522.9592
B110: % of revenue | D110: =D109/D31 -> 0.050057477 | E110: =E109/E31 -> 0.041585639 | F110: =F109/F31 -> 0.033044958 | G110: =G109/G31 -> 0.038105046 | H110: =H109/H31 -> 0.039808281 | I110: =I109/I31 -> #DIV/0! | J110: =J109/J31 -> 0.039282327 | K110: =K109/K31 -> 0.02852706 | ... W110: =W109/W31 -> 0.044503643 | X110: 0.04 | Y110: 0.04 | Z110: =Z109/Z31 -> 0.043326989 | AB110: 0.04 | AC110: 0.04 | AD110: 0.04 | AE110: 0.04 | AF110: =AF109/AF31 -> 0.040000392 | AH110: 0.04 | AJ110: 0.04 | AL110: 0.04
B112: Dividends | D112: =CF!P39 -> -327 | E112: =CF!Q39 -> -322 | F112: =CF!R39 -> -322 | G112: =CF!S39 -> -342 | H112: =CF!T39 -> -1313 | J112: =CF!V39 -> -341 | K112: =CF!W39 -> -356 | L112: =CF!X39 -> -368 | M112: =CF!Y39 -> -362 | N112: =CF!Z39 -> -1427 | P112: =CF!AB39 -> -386 | Q112: =CF!AC39 -> -410 | R112: =CF!AD39 -> -406 | S112: =CF!AE39 -> -403 | T112: =CF!AF39 -> -1605 | V112: =CF!AH39 -> -403 | W112: =CF!AI39 -> -440 | X112: -438.534 | Y112: =-Y113*Y126 -> -365.05828 | Z112: =SUM(V112:Y112) -> -1646.5923 | AB112: =-AB113*AB126 -> -259.038 | AC112: =-AC113*AC126 -> -364.572 | AD112: =-AD113*AD126 -> -433.992 | AE112: =-AE113*AE126 -> -487.69517 | AF112: =SUM(AB112:AE112) -> -1545.2972 | AH112: =-AH113*AH126 -> -1867.5385 | AJ112: =-AJ113*AJ126 -> -2514.0528 | AL112: =-AL113*AL126 -> -3074.8565
B113: % of NOPAT | D113: =-D112/D126 -> 0.28398229 | E113: =-E112/E126 -> 0.14008616 | F113: =-F112/F126 -> 0.15070855 | G113: =-G112/G126 -> 0.14690979 | H113: =-H112/H126 -> 0.16774365 | J113: =-J112/J126 -> 0.14623758 | K113: =-K112/K126 -> 0.10417595 | L113: =-L112/L126 -> 0.11506698 | M113: =-M112/M126 -> 0.12141019 | N113: =-N112/N126 -> 0.1168588 | P113: =-P112/P126 -> 0.16230858 | Q113: =-Q112/Q126 -> 0.13664039 | R113: =-R112/R126 -> 0.17298163 | S113: =-S112/S126 -> 0.19589124 | T113: =-T112/T126 -> 0.162941 | V113: =-V112/V126 -> 0.24391145 | W113: =-W112/W126 -> 0.18324323 | X113: =-X112/X126 -> 0.25093212 | Y113: 0.18 | Z113: =-Z112/Z126 -> 0.21031584 | AB113: 0.18 | AC113: 0.19 | AD113: 0.2 | AE113: 0.21 | AF113: =-AF112/AF126 -> 0.19684768 | AH113: 0.22 | AJ113: 0.24 | AL113: 0.25
B115: Repurchase of Stock | D115: =CF!P40 -> -612 | E115: =CF!Q40 -> -564 | F115: =CF!R40 -> -1246 | G115: =CF!S40 -> -1112 | H115: =CF!T40 -> -3534 | J115: =CF!V40 -> -1236 | K115: =CF!W40 -> -1280 | L115: =CF!X40 -> -2147 | M115: =CF!Y40 -> -2553 | N115: =CF!Z40 -> -7216 | P115: =CF!AB40 -> -1328 | Q115: =CF!AC40 -> -1094 | R115: =CF!AD40 -> -805 | S115: =CF!AE40 -> -780 | T115: =CF!AF40 -> -4007 | V115: =CF!AH40 -> -441 | W115: =CF!AI40 -> -397 | X115: =-0.4*(X136+X134+X112) -> -354.16699 | Y115: =-0.4*(Y136+Y134+Y112) -> -1145.1967 | Z115: =SUM(V115:Y115) -> -2337.3637 | AB115: =-0.4*(AB136+AB134+AB112) -> -1133.8826 | AC115: =0.4*(AC136+AC134+AC112) -> 336.74315 | AD115: =-0.4*(AD136+AD134+AD112) -> -649.81277 | AE115: =-0.4*(AE136+AE134+AE112) -> -760.77716 | AF115: =SUM(AB115:AE115) -> -2207.7294 | AH115: =-0.4*(AH136+AH112+AH134) -> -3078.209 | AJ115: =-0.4*(AJ136+AJ112+AJ134) -> -3082.2563 | AL115: =-0.4*(AL136+AL112+AL134) -> -3685.1961 | AN115: Repurchase since 3Q25 | AO115: =SUM(X115:Y115,AF115:AL115) -> -13552.754
A117: x | B117: Free Cash Flow to Firm
D118: =D$8 -> 2022 | E118: =F118 -> 0 | F118: =F$8 -> 0 | G118: =F118 -> 0 | H118: =F118 -> 0 | J118: =J$8 -> 2023 | K118: =L118 -> 0 | L118: =L$8 -> 0 | M118: =L118 -> 0 | N118: =L118 -> 0 | P118: =P$8 -> 2024 | Q118: =R118 -> 0 | R118: =R$8 -> 0 | S118: =R118 -> 0 | T118: =R118 -> 0 | V118: =V$8 -> 2025 | W118: =X118 -> 0 | X118: =X$8 -> 0 | Y118: =X118 -> 0 | Z118: =X118 -> 0 | AB118: =AB$8 -> 2026 | AC118: =AD118 -> 0 | AD118: =AD$8 -> 0 | AE118: =AD118 -> 0 | AF118: =AD118 -> 0 | AH118: =AH$8 -> 2027 | AJ118: =AJ$8 -> 2028 | AL118: =AL$8 -> 2029
D119: Q1 | E119: Q2 | F119: Q3 | G119: Q4 | H119: FY | J119: Q1 | K119: Q2 | L119: Q3 | M119: Q4 | N119: FY | P119: Q1 | Q119: Q2 | R119: Q3 | S119: Q4 | T119: FY | V119: Q1 | W119: Q2 | X119: Q3 | Y119: Q4 | Z119: FY | AB119: Q1 | AC119: Q2 | AD119: Q3 | AE119: Q4 | AF119: FY | AH119: FY | AJ119: FY | AL119: FY
B122: EBIT (Operating Income) | D122: =D61 -> 1470 | E122: =E61 -> 2808 | F122: =F61 -> 2875 | G122: =G61 -> 3000 | H122: =H61 -> 10036 | J122: =J61 -> 2972 | K122: =K61 -> 4590 | L122: =L61 -> 4229 | M122: =M61 -> 3872 | N122: =N61 -> 15663 | P122: =P61 -> 3017 | Q122: =Q61 -> 3953 | R122: =R61 -> 3195 | S122: =S61 -> 2435 | T122: =T61 -> 12802 | V122: =V61 -> 1692 | W122: =W61 -> 3121 | X122: =X61 -> 2394 | Y122: =Y61 -> 2778.2213 | Z122: =Z61 -> 9985.2213 | AB122: =AB61 -> 1845 | AC122: =AC61 -> 2460 | AD122: =AD61 -> 2782 | AE122: =AE61 -> 2977.382 | AF122: =AF61 -> 10064.382 | AH122: =AH61 -> 10883.091 | AJ122: =AJ61 -> 13429.769 | AL122: =AL61 -> 15768.495
B124: Tax Rate | D124: =IS!P45/IS!P42 -> 0.2166801 | E124: =IS!Q45/IS!Q42 -> 0.18141549 | F124: =IS!R45/IS!R42 -> 0.25684374 | G124: =IS!S45/IS!S42 -> 0.22401358 | H124: =IS!T45/IS!T42 -> 0.22006575 | J124: =IS!V45/IS!V42 -> 0.21540313 | K124: =IS!W45/IS!W42 -> 0.25549117 | L124: =IS!X45/IS!X42 -> 0.2437604 | M124: =IS!Y45/IS!Y42 -> 0.22995147 | N124: =IS!Z45/IS!Z42 -> 0.22037169 | P124: =IS!AB45/IS!AB42 -> 0.21173815 | Q124: =IS!AC45/IS!AC42 -> 0.2409368 | R124: =IS!AD45/IS!AD42 -> 0.26539278 | S124: =IS!AE45/IS!AE42 -> 0.15512771 | T124: =IS!AF45/IS!AF42 -> 0.23057406 | V124: =IS!AH45/IS!AH42 -> 0.023499421 | W124: =IS!AI45/IS!AI42 -> 0.23063757 | X124: 0.27 | Y124: 0.27 | Z124: =AVERAGE(V124:Y124) -> 0.19853425 | AB124: 0.22 | AC124: 0.22 | AD124: 0.22 | AE124: 0.22 | AF124: =AVERAGE(AB124:AE124) -> 0.22 | AH124: 0.22 | AJ124: 0.22 | AL124: 0.22
B126: NOPAT (Net Operating Profit After Taxes) | D126: =D122*(1-D124) -> 1151.4803 | E126: =E122*(1-E124) -> 2298.5853 | F126: =F122*(1-F124) -> 2136.5743 | G126: =G122*(1-G124) -> 2327.9593 | H126: =H122*(1-H124) -> 7827.4202 | J126: =J122*(1-J124) -> 2331.8219 | K126: =K122*(1-K124) -> 3417.2955 | L126: =L122*(1-L124) -> 3198.1373 | M126: =M122*(1-M124) -> 2981.6279 | N126: =N122*(1-N124) -> 12211.318 | P126: =P122*(1-P124) -> 2378.186 | Q126: =Q122*(1-Q124) -> 3000.5768 | R126: =R122*(1-R124) -> 2347.0701 | S126: =S122*(1-S124) -> 2057.264 | T126: =T122*(1-T124) -> 9850.1909 | V126: =V122*(1-V124) -> 1652.239 | W126: =W122*(1-W124) -> 2401.1801 | X126: =X122*(1-X124) -> 1747.62 | Y126: =Y122*(1-Y124) -> 2028.1015 | Z126: =SUM(V126:Y126) -> 7829.1407 | AB126: =AB122*(1-AB124) -> 1439.1 | AC126: =AC122*(1-AC124) -> 1918.8 | AD126: =AD122*(1-AD124) -> 2169.96 | AE126: =AE122*(1-AE124) -> 2322.358 | AF126: =SUM(AB126:AE126) -> 7850.218 | AH126: =AH122*(1-AH124) -> 8488.8112 | AJ126: =AJ122*(1-AJ124) -> 10475.22 | AL126: =AL122*(1-AL124) -> 12299.426
B128: D&A (Depreciation & Amortization) | D128: =D94 -> 486 | E128: =E94 -> 447 | F128: =F94 -> 510 | G128: =G94 -> 452 | H128: =H94 -> 1895 | J128: =J94 -> 494 | K128: =K94 -> 501 | L128: =L94 -> 532 | M128: =M94 -> 477 | N128: =N94 -> 2004 | P128: =P94 -> 520 | Q128: =Q94 -> 525 | R128: =R94 -> 553 | S128: =S94 -> 520 | T128: =T94 -> 2118 | V128: =V94 -> 549 | W128: =W94 -> 555 | X128: =X94 -> 352.19448 | Y128: =Y94 -> 355.54799 | Z128: =Z94 -> 1811.7425 | AB128: =AB94 -> 355.54799 | AC128: =AC94 -> 355.54799 | AD128: =AD94 -> 355.54799 | AE128: =AE94 -> 355.54799 | AF128: =AF94 -> 1422.192 | AH128: =AH94 -> 355.54799 | AJ128: =AJ94 -> 355.54799 | AL128: =AL94 -> 355.54799
B130: Stock-Based Compensation | D130: =D97 -> 18 | E130: =E97 -> 26 | F130: =F97 -> 20 | G130: =G97 -> 21 | H130: =H97 -> 85 | J130: =J97 -> 23 | K130: =K97 -> 31 | L130: =L97 -> 58 | M130: =M97 -> 18 | N130: =N97 -> 130 | P130: =P97 -> 46 | Q130: =Q97 -> 58 | R130: =R97 -> 55 | S130: =S97 -> 49 | T130: =T97 -> 208 | V130: =V97 -> 28 | W130: =W97 -> 26 | X130: =X97 -> 49.897 | Y130: =Y97 -> 37.311435 | Z130: =Z97 -> 141.20844 | AB130: =AB97 -> 28.35 | AC130: =AC97 -> 37.8 | AD130: =AD97 -> 40.95 | AE130: =AE97 -> 43.82595 | AF130: =AF97 -> 150.92595 | AH130: =AH97 -> 167.22799 | AJ130: =AJ97 -> 189.70302 | AL130: =AL97 -> 198.68304
B132: Changes in Net Working Capital | D132: =D103 -> -3141 | E132: =E103 -> -1241 | F132: =F103 -> -434 | G132: =G103 -> 1516 | H132: =H103 -> -3300 | J132: =J103 -> -3672 | K132: =K103 -> -2126 | L132: =L103 -> -472 | M132: =M103 -> 3103 | N132: =N103 -> -3167 | P132: =P103 -> -3144 | Q132: =Q103 -> -1063 | R132: =R103 -> 1011 | S132: =S103 -> 3242 | T132: =T103 -> 46 | V132: =V103 -> -2117 | W132: =W103 -> -769 | X132: =X103 -> -1193.2 | Y132: =Y103 -> 1055.497 | Z132: =Z103 -> -3023.703 | AB132: =AB103 -> 1270.7465 | AC132: =AC103 -> -1105.7181 | AD132: =AD103 -> -507.93407 | AE132: =AE103 -> -332.09383 | AF132: =AF103 -> -674.99955 | AH132: =AH103 -> 551.47384 | AJ132: =AJ103 -> -800.77744 | AL132: =AL103 -> -565.81028
B134: Net CapEx | D134: =D106+D109 -> 208 | E134: =E106+E109 -> 387 | F134: =F106+F109 -> 315 | G134: =G106+G109 -> 367 | H134: =H106+H109 -> 1277 | J134: =J106+J109 -> 182 | K134: =K106+K109 -> 227 | L134: =L106+L109 -> 149 | M134: =M106+M109 -> -77 | N134: =N106+N109 -> 481 | P134: =P106+P109 -> 144 | Q134: =Q106+Q109 -> 148 | R134: =R106+R109 -> 116 | S134: =S106+S109 -> -79 | T134: =T106+T109 -> 329 | V134: =V106+V109 -> 81 | W134: =W106+W109 -> 365 | X134: =X106+X109 -> 183.72 | Y134: =Y106+Y109 -> -124.204 | Z134: =Z106+Z109 -> 505.516 | AB134: =AB106+AB109 -> 0 | AC134: =AC106+AC109 -> 0 | AD134: =AD106+AD109 -> 0 | AE134: =AE106+AE109 -> 0 | AF134: =AF106+AF109 -> 0 | AH134: =AH106+AH109 -> 0 | AJ134: =AJ106+AJ109 -> 0 | AL134: =AL106+AL109 -> 0
B136: FCFF (Free Cash Flow to Firm) | D136: =D126+D94+D97+D103+D134 -> -1277.5197 | E136: =E126+E94+E97+E103+E134 -> 1917.5853 | F136: =F126+F94+F97+F103+F134 -> 2547.5743 | G136: =G126+G94+G97+G103+G134 -> 4683.9593 | H136: =H126+H94+H97+H103+H134 -> 7784.4202 | J136: =J126+J94+J97+J103+J134 -> -641.1781 | K136: =K126+K94+K97+K103+K134 -> 2050.2955 | L136: =L126+L94+L97+L103+L134 -> 3465.1373 | M136: =M126+M94+M97+M103+M134 -> 6502.6279 | N136: =N126+N94+N97+N103+N134 -> 11659.318 | P136: =P126+P94+P97+P103+P134 -> -55.813995 | Q136: =Q126+Q94+Q97+Q103+Q134 -> 2668.5768 | R136: =R126+R94+R97+R103+R134 -> 4082.0701 | S136: =S126+S94+S97+S103+S134 -> 5789.264 | T136: =T126+T94+T97+T103+T134 -> 12551.191 | V136: =V126+V94+V97+V103+V134 -> 193.23898 | W136: =W126+W94+W97+W103+W134 -> 2578.1801 | X136: =X126+X128+X130+X132+X134 -> 1140.2315 | Y136: =Y126+Y128+Y130+Y132+Y134 -> 3352.254 | Z136: =Z126+Z128+Z130+Z132+Z134 -> 7263.9046 | AB136: =AB126+AB128+AB130+AB132+AB134 -> 3093.7444 | AC136: =AC126+AC128+AC130+AC132+AC134 -> 1206.4299 | AD136: =AD126+AD128+AD130+AD132+AD134 -> 2058.5239 | AE136: =AE126+AE128+AE130+AE132+AE134 -> 2389.6381 | AF136: =AF126+AF128+AF130+AF132+AF134 -> 8748.3363 | AH136: =AH126+AH128+AH130+AH132+AH134 -> 9563.061 | AJ136: =AJ126+AJ128+AJ130+AJ132+AJ134 -> 10219.693 | AL136: =AL126+AL128+AL130+AL132+AL134 -> 12287.847
A138: x | B138: Valuation Summary
V139: =V$8 -> 2025 | W139: =X139 -> 0 | X139: =X$8 -> 0 | Y139: =X139 -> 0 | Z139: =X139 -> 0 | AB139: =AB$8 -> 2026 | AC139: =AD139 -> 0 | AD139: =AD$8 -> 0 | AE139: =AD139 -> 0 | AF139: =AD139 -> 0 | AH139: =AH$8 -> 2027 | AJ139: =AJ$8 -> 2028 | AL139: =AL$8 -> 2029
V140: Q1 | W140: Q2 | X140: Q3 | Y140: Q4 | Z140: FY | AB140: Q1 | AC140: Q2 | AD140: Q3 | AE140: Q4 | AF140: FY | AH140: FY | AJ140: FY | AL140: FY
B143: Discounted Cash Flows (DCF)
B146: Discount Period | X146: =YEARFRAC(TODAY(),Inputs!$D$18+92) -> 0.047222222 | Y146: =YEARFRAC(TODAY(),Inputs!$D$18+184) -> 0.20277778 | Z146: =YEARFRAC(TODAY(),"2025-12-31") -> 0.20277778 | AB146: =YEARFRAC(TODAY(),Inputs!$D$17+365+90) -> 0.2 | AC146: =YEARFRAC(TODAY(),Inputs!$D$17+365+90+91) -> 0.45277778 | AD146: =YEARFRAC(TODAY(),Inputs!$D$17+365+90+91+92) -> 0.70277778 | AE146: =YEARFRAC(TODAY(),Inputs!$D$17+720) -> 0.925 | AF146: =Z146+1 -> 1.2027778 | AH146: =YEARFRAC(TODAY(),Inputs!$D$17+730+365) -> 1.9527778 | AJ146: =YEARFRAC(TODAY(),Inputs!$D$17+730+731) -> 2.9527778 | AL146: =YEARFRAC(TODAY(),Inputs!$D$17+730+731+365) -> 3.9527778
B147: Mid-Quarter/Year Convention Discount Period | X147: =X146/2 -> 0.023611111 | Y147: =X146+(Y146-X146)/2 -> 0.125 | Z147: =W146+(Z146-W146)/2 -> 0.10138889 | AB147: =Y146+(AB146-Y146)/2 -> 0.20138889 | AC147: =AB146+(AC146-AB146)/2 -> 0.32638889 | AD147: =AC146+(AD146-AC146)/2 -> 0.57777778 | AE147: =AD146+(AE146-AD146)/2 -> 0.81388889 | AF147: =+Z147+1 -> 1.1013889 | AH147: =AE146+(AH146-AE146)/2 -> 1.4388889 | AJ147: =AH146+(AJ146-AH146)/2 -> 2.4527778 | AL147: =AJ146+(AL146-AJ146)/2 -> 3.4527778
B149: Rolling WACC (Weighted Average Cost of Capital) | X149: =WACC!$D$39+Sensitivity!U41 -> 0.074145168 | Y149: =WACC!$D$39+Sensitivity!U41 -> 0.074145168 | Z149: =WACC!D39 -> 0.074145168 | AB149: =WACC!$E$39+Sensitivity!U41 -> 0.074866136 | AC149: =WACC!$E$39+Sensitivity!U41 -> 0.074866136 | AD149: =WACC!$E$39+Sensitivity!U41 -> 0.074866136 | AE149: =WACC!$E$39+Sensitivity!U41 -> 0.074866136 | AF149: =WACC!E39 -> 0.074866136 | AH149: =WACC!$F$39+Sensitivity!U41 -> 0.068987767 | AJ149: =WACC!$G$39+Sensitivity!U41 -> 0.068068283 | AL149: =WACC!$H$39+Sensitivity!U41 -> 0.07308743
B150: Cumulative Discount Factor | X150: =(1+X149)^X147 -> 1.0016902 | Y150: =((1+X149)^X147)*((1+Y149)^Y147) -> 1.0106861 | Z150: =+(1+Z149)^Z147 -> 1.0072782 | AB150: =((1+X149)^X147)*((1+Y149)^Y147)*((1+AB149)^AB147) -> 1.0254883 | AC150: =((1+X149)^X147)*((1+Y149)^Y147)*((1+AB149)^AB147)*((1+AC149)^AC147) -> 1.0499399 | AD150: =((1+X149)^X147)*((1+Y149)^Y147)*((1+AB149)^AB147)*((1+AC149)^AC147)*((1+AD149)^AD147) -> 1.0946627 | AE150: =((1+X149)^X147)*((1+Y149)^Y147)*((1+AB149)^AB147)*((1+AC149)^AC147)*((1+AD149)^AD147)*((1+AE149)^AE147) -> 1.160912 | AF150: =1.01*(1+AF149)^AF147 -> 1.0935905 | AH150: =((1+X149)^X147)*((1+Y149)^Y147)*((1+AB149)^AB147)*((1+AC149)^AC147)*((1+AD149)^AD147)*((1+AE149)^AE147)*((1+AH149)^AH147) -> 1.2778734 | AJ150: =((1+X149)^X147)*((1+Y149)^Y147)*((1+AB149)^AB147)*((1+AC149)^AC147)*((1+AD149)^AD147)*((1+AE149)^AE147)*((1+AH149)^AH147)*((1+AJ149)^AJ147) -> 1.5018788 | AL150: =((1+X149)^X147)*((1+Y149)^Y147)*((1+AB149)^AB147)*((1+AC149)^AC147)*((1+AD149)^AD147)*((1+AE149)^AE147)*((1+AH149)^AH147)*((1+AJ149)^AJ147)*((1+AL149)^AL147) -> 1.9160688
B152: Present Value of FCFF | X152: =X136/X150 -> 1138.3075 | Y152: =Y136/Y150 -> 3316.8101 | Z152: =Z136/Z150 -> 7211.4184 | AB152: =AB136/AB150 -> 3016.8499 | AC152: =AC136/AC150 -> 1149.0466 | AD152: =AD136/AD150 -> 1880.5098 | AE152: =AE136/AE150 -> 2058.4145 | AF152: =AF136/AF150 -> 7999.6453 | AH152: =AH136/AH150 -> 7483.5744 | AJ152: =AJ136/AJ150 -> 6804.6061 | AL152: =AL136/AL150 -> 6413.0509
B154: Terminal Value
Q157: Preferred Method: | R157: Revenue Exit | V157: EBITDA Exit Multiple | AB157: Revenue Exit Multiple | AH157: Gordon's Growth Model
V159: Current EV/EBITDA | Z159: =Inputs!M14 -> 30.08065 | AB159: Current EV/Sales | AF159: =Inputs!M13 -> 6.8940049 | AH159: Current Growth Rate | AL159: =AL136/AJ136-1 -> 0.2023694
V160: Exit EV/EBITDA | Z160: =(WACC!H13+WACC!H28-9000)/(FCFF!AL61+FCFF!AL94) -> 13.74872 | AB160: Exit EV/Sales | AF160: =(WACC!H13+WACC!H28-9000)/FCFF!AL31 -> 3.5146815 | AH160: Terminal Growth Rate | AL160: 0.02
R161: =R157 -> Revenue Exit | V161: Terminal Value | Z161: =(Z160+Sensitivity!U43)*(AL122+AL128) -> 221684.95 | AB161: Terminal Value | AF161: =(AF160+Sensitivity!U44)*(AL31) -> 221684.95 | AH161: Terminal Value | AL161: =AL136*(1+AL160+Sensitivity!U42)/(AL149-AL160-Sensitivity!U42) -> 236093.62
R162: =IF($R$161="Revenue Exit",$AF$171,IF($R$161="EBITDA Exit",$Z$171,$AL$171)) -> -0.18262596 | V162: PV of Terminal Value | Z162: =Z161/AL150 -> 115697.8 | AB162: PV of Terminal Value | AF162: =AF161/AL150 -> 115697.8 | AH162: PV of Terminal Value | AL162: =AL161/AL150 -> 123217.72
R163: =1-R162 -> 1.182626 | V163: Implied Enterprise Value | Z163: =Z162+SUM(V152:AL152) -> 164170.04 | AB163: Implied Enterprise Value | AF163: =AF162+SUM(V152:AL152) -> 164170.04 | AH163: Implied Enterprise Value | AL163: =AL162+SUM(V152:AL152) -> 171689.95
R164: =IF(R162>0,"Upside","Downside") -> Downside | V164: (-) Net Debt | Z164: =BS!AI45+BS!AI44+BS!AI39+BS!AI38-BS!AI15 -> 57058 | AB164: (-) Net Debt | AF164: =BS!AI45+BS!AI44+BS!AI39+BS!AI38-BS!AI15 -> 57058 | AH164: (-) Net Debt | AL164: =BS!AI45+BS!AI44+BS!AI39+BS!AI38-BS!AI15 -> 57058
V165: (-) Preferred Stock Market Cap | Z165: 0 | AB165: (-) Preferred Stock Market Cap | AF165: 0 | AH165: (-) Preferred Stock Market Cap | AL165: 0
V166: (-) Non-controlling Interest | Z166: =BS!AI53 -> 91 | AB166: (-) Non-controlling Interest | AF166: =BS!AI53 -> 91 | AH166: (-) Non-controlling Interest | AL166: =BS!AI53 -> 91
V167: Implied Equity Value | Z167: =Z163-Z164-Z165-Z166 -> 107021.04 | AB167: Implied Equity Value | AF167: =AF163-AF164-AF165-AF166 -> 107021.04 | AH167: Implied Equity Value | AL167: =AL163-AL164-AL165-AL166 -> 114540.95
V168: Shares Outstanding | Z168: =AL64 -> 271.92116 | AB168: Shares Outstanding | AF168: =AL64 -> 271.92116 | AH168: Shares Outstanding | AL168: =AL64 -> 271.92116
...

Sheet LBO
A7: x | B7: Key Assumptions
B10: Entry | G10: Capital Structure | J10: Interest | K10: Weight | L10: Amount
B11: LTM EBITDA | E11: =(G86+G77) -> 12802 | G11: Revolver | L11: =K11*$E$13 -> 0
B12: Entry Multiple | G12: Bank Loan | L12: =K12*$E$13 -> 0
B13: Enterprise Value | E13: =E11*E12 -> 0 | G13: Senior Notes | L13: =K13*$E$13 -> 0
B14: Existing Net Debt | E14: =BS!AJ38+BS!AJ39+BS!AJ44+BS!AJ45-BS!AJ15 -> 0
B15: Equity Value | E15: =E13-E14 -> 0 | G15: IRR (For reference)
G16: MOIC | L16: =L180 -> #DIV/0!
B17: Fees & Expenses | E17: =0.03*E13 -> 0 | G17: IRR | L17: =L181 -> #DIV/0!
B19: Exit
B20: Exit Multiple
A22: x | B22: Sources & Uses
B25: Sources | G25: Uses
C26: Amount | D26: xEBITDA | E26: % Capital | J26: Amount | K26: xEBITDA | L26: % Capital
B27: Revolver | C27: =L11 -> 0 | D27: =C27/$E$11 -> 0 | E27: =C27/$C$34 -> #DIV/0! | G27: Debt Refinancing | J27: =E14 -> 0 | K27: =J27/$E$11 -> 0 | L27: =J27/$J$34 -> #DIV/0!
B28: Bank Loan | C28: =L12 -> 0 | D28: =C28/$E$11 -> 0 | E28: =C28/$C$34 -> #DIV/0! | G28: Equity Payments | J28: =E15 -> 0 | K28: =J28/$E$11 -> 0 | L28: =J28/$J$34 -> #DIV/0!
B29: Senior Notes | C29: =L13 -> 0 | D29: =C29/$E$11 -> 0 | E29: =C29/$C$34 -> #DIV/0!
B30: Total | C30: =SUM(C27:C29) -> 0 | D30: =C30/$E$11 -> 0 | E30: =C30/$C$34 -> #DIV/0! | G30: Fees & Expenses | J30: =E17 -> 0 | K30: =J30/$E$11 -> 0 | L30: =J30/$J$34 -> #DIV/0!
B32: Sponsor Equity | C32: =C34-C30 -> 0 | D32: =C32/$E$11 -> 0 | E32: =C32/$C$34 -> #DIV/0!
B34: Total Sources | C34: =J34 -> 0 | D34: =C34/$E$11 -> 0 | E34: =C34/$C$34 -> #DIV/0! | G34: Total Uses | J34: =J27+J28+J30 -> 0 | K34: =J34/$E$11 -> 0 | L34: =J34/$J$34 -> #DIV/0!
B36: Market Assumptions
A38: x | E38: 2022 | F38: =+E38+1 -> 2023 | G38: =+F38+1 -> 2024 | H38: =+G38+1 -> 2025 | I38: =+H38+1 -> 2026 | J38: =+I38+1 -> 2027 | K38: =+J38+1 -> 2028 | L38: =+K38+1 -> 2029
B50: Sales | H50: 350000 | I50: 352000 | J50: 350000 | K50: 352000 | L50: 350000
B52: Operating Assumptions
A57: x | B57: Income Statement | E57: 2022 | F57: =+E57+1 -> 2023 | G57: =+F57+1 -> 2024 | H57: =+G57+1 -> 2025 | I57: =+H57+1 -> 2026 | J57: =+I57+1 -> 2027 | K57: =+J57+1 -> 2028 | L57: =+K57+1 -> 2029
B59: Revenue | D59: =+_xlfn.XLOOKUP($B59,#REF!,#REF!) -> #REF! | E59: =FCFF!H31 -> 52577 | F59: =FCFF!N31 -> 61251 | G59: =FCFF!T31 -> 51716 | H59: =+H50 -> 350000 | I59: =+I50 -> 352000 | J59: =+J50 -> 350000 | K59: =+K50 -> 352000 | L59: =+L50 -> 350000
B60: % of growth | E60: =E59/IS!N18-1 -> 0.19428039 | F60: =F59/E59-1 -> 0.16497708 | G60: =G59/F59-1 -> -0.15567093 | H60: =H59/G59-1 -> 5.7677315 | I60: =I59/H59-1 -> 0.0057142857 | J60: =J59/I59-1 -> -0.0056818182 | K60: =K59/J59-1 -> 0.0057142857 | L60: =L59/K59-1 -> -0.0056818182
B62: Cost of Goods & Services | E62: =FCFF!H34 -> 35338 | F62: =FCFF!N34 -> 37715 | G62: =FCFF!T34 -> 30775 | H62: =H63*H$59 -> 0 | I62: =I63*I$59 -> 0 | J62: =J63*J$59 -> 0 | K62: =K63*K$59 -> 0 | L62: =L63*L$59 -> 0
B63: % of sales | E63: =E62/E59 -> 0.67211899 | F63: =F62/F59 -> 0.61574505 | G63: =G62/G59 -> 0.59507696
B65: COGS Depreciation & Amortization | E65: =FCFF!H37 -> 0 | F65: =FCFF!N37 -> 0 | G65: =FCFF!T37 -> 0 | H65: =+H66*H62 -> 0 | I65: =+I66*I62 -> 0 | J65: =+J66*J62 -> 0 | K65: =+K66*K62 -> 0 | L65: =+L66*L62 -> 0
B66: % of cost of goods & services | E66: =E65/E62 -> 0 | F66: =F65/F62 -> 0 | G66: =G65/G62 -> 0
B68: Gross Profit | E68: =FCFF!H40 -> 17239 | F68: =FCFF!N40 -> 23536 | G68: =FCFF!T40 -> 20941 | H68: =+H59-H62-H65 -> 350000 | I68: =+I59-I62-I65 -> 352000 | J68: =+J59-J62-J65 -> 350000 | K68: =+K59-K62-K65 -> 352000 | L68: =+L59-L62-L65 -> 350000
B69: % of sales | E69: =E68/E59 -> 0.32788101 | F69: =F68/F59 -> 0.38425495 | G69: =G68/G59 -> 0.40492304 | H69: =IFERROR(H68/H$59,"") -> 1 | I69: =IFERROR(I68/I$59,"") -> 1 | J69: =IFERROR(J68/J$59,"") -> 1 | K69: =IFERROR(K68/K$59,"") -> 1 | L69: =IFERROR(L68/L$59,"") -> 1
B71: SG&A (Selling, General & Administrative) | E71: =FCFF!H43 -> 3863 | F71: =FCFF!N43 -> 4595 | G71: =FCFF!T43 -> 4840 | H71: =+H72*H59 -> 0 | I71: =+I72*I59 -> 0 | J71: =+J72*J59 -> 0 | K71: =+K72*K59 -> 0 | L71: =+L72*L59 -> 0
B72: % of sales | E72: =E71/E59 -> 0.073473192 | F72: =F71/F59 -> 0.075019183 | G72: =G71/G59 -> 0.093588058
B74: R&D (Research & Development) | E74: =FCFF!H46 -> 1912 | F74: =FCFF!N46 -> 2177 | G74: =FCFF!T46 -> 2290 | H74: =+H75*H68 -> 0 | I74: =+I75*I68 -> 0 | J74: =+J75*J68 -> 0 | K74: =+K75*K68 -> 0 | L74: =+L75*L68 -> 0
B75: % of gross profit | E75: =E74/E68 -> 0.11091131 | F75: =F74/F68 -> 0.092496601 | G75: =G74/G68 -> 0.10935485
B77: D&A (Depreciation & Amortization) | E77: =FCFF!H49 -> 0 | F77: =FCFF!N49 -> 0 | G77: =FCFF!T49 -> 0 | H77: =+H80+H83 -> 0 | I77: =+I80+I83 -> 0 | J77: =+J80+J83 -> 0 | K77: =+K80+K83 -> 0 | L77: =+L80+L83 -> 0
B78: % of net pp&e and intangibles excl. Goodwill | E78: =E77/(E111+E114) -> 0 | F78: =F77/(F111+F114) -> 0 | G78: =G77/(G111+G114) -> 0 | H78: =H77/(H111+H114) -> 0 | I78: =I77/(I111+I114) -> 0 | J78: =J77/(J111+J114) -> 0 | K78: =K77/(K111+K114) -> 0 | L78: =L77/(L111+L114) -> 0
B80: Depreciation | E80: =FCFF!H52 -> 0 | F80: =FCFF!N52 -> 0 | G80: =FCFF!T52 -> 0 | H80: =H81*G111 -> 0 | I80: =I81*H111 -> 0 | J80: =J81*I111 -> 0 | K80: =K81*J111 -> 0 | L80: =L81*K111 -> 0
B81: % of net pp&e | E81: =E80/E111 -> 0 | F81: =FCFF!N53 -> 0 | G81: =FCFF!T53 -> 0
B83: Amortization | E83: =FCFF!H55 -> 0 | F83: =FCFF!N55 -> 0 | G83: =FCFF!T55 -> 0 | H83: =H84*G114 -> 0 | I83: =I84*H114 -> 0 | J83: =J84*I114 -> 0 | K83: =K84*J114 -> 0 | L83: =L84*K114 -> 0
B84: % of intangibles excl. goodwill | E84: =E83/E114 -> 0 | F84: =F83/F114 -> 0 | G84: =G83/G114 -> 0
B86: EBIT (Operating Income) | E86: =FCFF!H61 -> 10036 | F86: =FCFF!N61 -> 15663 | G86: =FCFF!T61 -> 12802 | H86: =H68-H71-H74-H77 -> 350000 | I86: =I68-I71-I74-I77 -> 352000 | J86: =J68-J71-J74-J77 -> 350000 | K86: =K68-K71-K74-K77 -> 352000 | L86: =L68-L71-L74-L77 -> 350000
B87: % of sales | E87: =E86/E59 -> 0.19088194 | F87: =F86/F59 -> 0.25571827 | G87: =G86/G59 -> 0.24754428 | H87: =H86/H59 -> 1 | I87: =I86/I59 -> 1 | J87: =J86/J59 -> 1 | K87: =K86/K59 -> 1 | L87: =L86/L59 -> 1
B89: Net Interest (Income) Expense | E89: =IS!T38 -> 1062 | F89: =IS!Z38 -> 2453 | G89: =IS!AF38 -> 3348 | H89: =+H164 -> 0 | I89: =+I164 -> 0 | J89: =+J164 -> 0 | K89: =+K164 -> 0 | L89: =+L164 -> 0
B91: Pre-tax income | E91: =IS!T42 -> 8974 | F91: =IS!Z42 -> 13210 | G91: =IS!AF42 -> 9459 | H91: =+H86-H89 -> 350000 | I91: =+I86-I89 -> 352000 | J91: =+J86-J89 -> 350000 | K91: =+K86-K89 -> 352000 | L91: =+L86-L89 -> 350000
B92: % of sales | E92: =E91/E59 -> 0.170683 | F92: =F91/F59 -> 0.21566995 | G92: =G91/G59 -> 0.18290278 | H92: =H91/H59 -> 1 | I92: =I91/I59 -> 1 | J92: =J91/J59 -> 1 | K92: =K91/K59 -> 1 | L92: =L91/L59 -> 1
B94: Income tax expenses (benefits) | E94: =IS!T45 -> 1974.87 | F94: =IS!Z45 -> 2911.11 | G94: =IS!AF45 -> 2181 | H94: =H95*H91 -> 0 | I94: =I95*I91 -> 0 | J94: =J95*J91 -> 0 | K94: =K95*K91 -> 0 | L94: =L95*L91 -> 0
B95: % tax rate | E95: =E94/E91 -> 0.22006575 | F95: =F94/F91 -> 0.22037169 | G95: =G94/G91 -> 0.23057406
B97: Net income | E97: =IS!T47 -> 7009.13 | F97: =IS!Z47 -> 10305.89 | G97: =IS!AF47 -> 7254 | H97: =H91-H94 -> 350000 | I97: =I91-I94 -> 352000 | J97: =J91-J94 -> 350000 | K97: =K91-K94 -> 352000 | L97: =L91-L94 -> 350000
B98: % of sales | E98: =E97/E59 -> 0.13331171 | F98: =F97/F59 -> 0.16825668 | G98: =G97/G59 -> 0.14026607 | H98: =H97/H59 -> 1 | I98: =I97/I59 -> 1 | J98: =J97/J59 -> 1 | K98: =K97/K59 -> 1 | L98: =L97/L59 -> 1
A100: x | B100: Balance Sheet | E100: =E57 -> 2022 | F100: =F57 -> 2023 | G100: =G57 -> 2024 | H100: =H57 -> 2025 | I100: =I57 -> 2026 | J100: =J57 -> 2027 | K100: =K57 -> 2028 | L100: =L57 -> 2029
B102: Accounts Receivable | E102: =FCFF!H70 -> 6410 | F102: =FCFF!N70 -> 7739 | G102: =FCFF!T70 -> 5326 | H102: =+H103*H59/365 -> 0 | I102: =+I103*I59/365 -> 0 | J102: =+J103*J59/365 -> 0 | K102: =+K103*K59/366 -> 0 | L102: =+L103*L59/365 -> 0
B103: days sales outstanding | E103: =FCFF!H71 -> 44.499496 | F103: =FCFF!N71 -> 46.11737 | G103: =FCFF!T71 -> 37.589721
B105: Inventory | E105: =FCFF!H73 -> 8495 | F105: =FCFF!N73 -> 8160 | G105: =FCFF!T73 -> 7093 | H105: =+H106*H62/365 -> 0 | I105: =+I106*I62/365 -> 0 | J105: =+J106*J62/365 -> 0 | K105: =+K106*K62/366 -> 0 | L105: =+L106*L62/365 -> 0
B106: days inventory held | E106: =FCFF!H74 -> 87.743364 | F106: =FCFF!N74 -> 78.971232 | G106: =FCFF!T74 -> 84.124939
B108: Prepaid expenses and Other Current Assets | E108: =FCFF!H76 -> 2492 | F108: =FCFF!N76 -> 2623 | G108: =FCFF!T76 -> 5489 | H108: =+H109*H59 -> 0 | I108: =+I109*I59 -> 0 | J108: =+J109*J59 -> 0 | K108: =+K109*K59 -> 0 | L108: =+L109*L59 -> 0
B109: % of sales | E109: =FCFF!H77 -> 0.047397151 | F109: =FCFF!N77 -> 0.042823791 | G109: =FCFF!T77 -> 0.10613737
B111: Net PP&E (Property, Plant and Equipment) | E111: =FCFF!H79 -> 12679 | F111: =FCFF!N79 -> 13796 | G111: =FCFF!T79 -> 15031 | H111: =+G111-H112*H131-H80-H65 -> 15031 | I111: =+H111-I112*I131-I80-I65 -> 15031 | J111: =+I111-J112*J131-J80-J65 -> 15031 | K111: =+J111-K112*K131-K80-K65 -> 15031 | L111: =+K111-L112*L131-L80-L65 -> 15031
B112: capex allocation rate | E112: =FCFF!H80 -> 0.015520094 | F112: =FCFF!N80 -> 0.024489396 | G112: =FCFF!T80 -> 0.030938201
B114: Intangibles excl. Goodwill | E114: =FCFF!H82 -> 4905 | F114: =FCFF!N82 -> 5033 | G114: =FCFF!T82 -> 4958 | H114: =+G114+H115*H74-(1-H112)*H131-H83 -> 4958 | I114: =+H114+I115*I74-(1-I112)*I131-I83 -> 4958 | J114: =+I114+J115*J74-(1-J112)*J131-J83 -> 4958 | K114: =+J114+K115*K74-(1-K112)*K131-K83 -> 4958 | L114: =+K114+L115*L74-(1-L112)*L131-L83 -> 4958
B115: r&d conversion rate | E115: =FCFF!H83 -> 0 | F115: =FCFF!N83 -> 0 | G115: =FCFF!T83 -> 0
B117: Accounts Payable | E117: =FCFF!H85 -> 12333 | F117: =FCFF!N85 -> 13592 | G117: =FCFF!T85 -> 12452 | H117: =+H118*H62/365 -> 0 | I117: =+I118*I62/365 -> 0 | J117: =+J118*J62/365 -> 0 | K117: =+K118*K62/366 -> 0 | L117: =+L118*L62/365 -> 0
B118: days payable outstanding | E118: =FCFF!H86 -> 127.38539 | F118: =FCFF!N86 -> 131.5413 | G118: =FCFF!T86 -> 147.68416
B120: Accrued Expenses and Other Current Liabilities | E120: =FCFF!H88 -> 2187 | F120: =FCFF!N88 -> 2257 | G120: =FCFF!T88 -> 1821 | H120: =+H121*H71 -> 0 | I120: =+I121*I71 -> 0 | J120: =+J121*J71 -> 0 | K120: =+K121*K71 -> 0 | L120: =+L121*L71 -> 0
B121: % of sg&a | E121: =FCFF!H89 -> 0.56614031 | F121: =FCFF!N89 -> 0.49118607 | G121: =FCFF!T89 -> 0.37623967
A123: x | B123: Cash Flow | E123: =E57 -> 2022 | F123: =F57 -> 2023 | G123: =G57 -> 2024 | H123: =H57 -> 2025 | I123: =I57 -> 2026 | J123: =J57 -> 2027 | K123: =K57 -> 2028 | L123: =L57 -> 2029
B125: D&A (Depreciation & Amortization) | E125: =FCFF!H94 -> 1895 | F125: =FCFF!N94 -> 2004 | G125: =FCFF!T94 -> 2118 | H125: =+H77+H65 -> 0 | I125: =+I77+I65 -> 0 | J125: =+J77+J65 -> 0 | K125: =+K77+K65 -> 0 | L125: =+L77+L65 -> 0
B126: % of net pp&e and intangibles excl. Goodwill | E126: =FCFF!H95 -> 0.10776843 | F126: =FCFF!N95 -> 0.10643157 | G126: =FCFF!T95 -> 0.10595828 | H126: =+H125/(H111+H114) -> 0 | I126: =+I125/(I111+I114) -> 0 | J126: =+J125/(J111+J114) -> 0 | K126: =+K125/(K111+K114) -> 0 | L126: =+L125/(L111+L114) -> 0
B128: Changes in Net Working Capital | E128: =FCFF!H103 -> -3300 | F128: =FCFF!N103 -> -3167 | G128: =FCFF!T103 -> 46 | H128: =-((H102+H105+H108-H117-H120)-(G102+G105+G108-G117-G120)) -> 3635 | I128: =-((I102+I105+I108-I117-I120)-(H102+H105+H108-H117-H120)) -> 0 | J128: =-((J102+J105+J108-J117-J120)-(I102+I105+I108-I117-I120)) -> 0 | K128: =-((K102+K105+K108-K117-K120)-(J102+J105+J108-J117-J120)) -> 0 | L128: =-((L102+L105+L108-L117-L120)-(K102+K105+K108-K117-K120)) -> 0
B129: % of change in sales | E129: =FCFF!H104 -> -0.074959113 | F129: =FCFF!N104 -> -0.060235464 | G129: =FCFF!T104 -> 0.00075100815 | H129: =H128/(H59-G59) -> 0.012186373 | I129: =I128/(I59-H59) -> 0 | J129: =J128/(J59-I59) -> 0 | K129: =K128/(K59-J59) -> 0 | L129: =L128/(L59-K59) -> 0
B131: Net CapEx | E131: =FCFF!H106+FCFF!H109 -> 1277 | F131: =FCFF!N106+FCFF!N109 -> 481 | G131: =FCFF!T106+FCFF!T109 -> 329 | H131: =-H132*H59 -> 0 | I131: =-I132*I59 -> 0 | J131: =-J132*J59 -> 0 | K131: =-K132*K59 -> 0 | L131: =-L132*L59 -> 0
B132: % of sales | E132: =FCFF!H107 -> 0.015520094 | F132: =FCFF!N107 -> 0.024489396 | G132: =FCFF!T107 -> 0.030938201
A134: x | B134: Levered Free Cash Flow | H134: =H57 -> 2025 | I134: =I57 -> 2026 | J134: =J57 -> 2027 | K134: =K57 -> 2028 | L134: =L57 -> 2029
B136: Net Income | H136: =H97 -> 350000 | I136: =I97 -> 352000 | J136: =J97 -> 350000 | K136: =K97 -> 352000 | L136: =L97 -> 350000
B137: Changes in NWC | H137: =+H125 -> 0 | I137: =+I125 -> 0 | J137: =+J125 -> 0 | K137: =+K125 -> 0 | L137: =+L125 -> 0
B138: D&A (Depreciation & Amortization) | H138: =+H128 -> 3635 | I138: =+I128 -> 0 | J138: =+J128 -> 0 | K138: =+K128 -> 0 | L138: =+L128 -> 0
B139: Net CapEx | H139: =+H131 -> 0 | I139: =+I131 -> 0 | J139: =+J131 -> 0 | K139: =+K131 -> 0 | L139: =+L131 -> 0
B140: Leveraged Free Cash Flow | H140: =H136+H137+H138+H139 -> 353635 | I140: =I136+I137+I138+I139 -> 352000 | J140: =J136+J137+J138+J139 -> 350000 | K140: =K136+K137+K138+K139 -> 352000 | L140: =L136+L137+L138+L139 -> 350000
A142: x | B142: Debt Schedule | H142: =H134 -> 2025 | I142: =I134 -> 2026 | J142: =J134 -> 2027 | K142: =K134 -> 2028 | L142: =L134 -> 2029
B144: Revolver
B145: Beginning Balance | H145: =G148 -> 0 | I145: =H148 -> 0 | J145: =I148 -> 0 | K145: =J148 -> 0 | L145: =K148 -> 0
B146: Interest | H146: =H145*$J$11 -> 0 | I146: =I145*$J$11 -> 0 | J146: =J145*$J$11 -> 0 | K146: =K145*$J$11 -> 0 | L146: =L145*$J$11 -> 0
B147: Paydown | H147: =MIN(H140,H145) -> 0 | I147: =MIN(I140,I145) -> 0 | J147: =MIN(J140,J145) -> 0 | K147: =MIN(K140,K145) -> 0 | L147: =MIN(L140,L145) -> 0
B148: Ending Balance | G148: =L11 -> 0 | H148: =H145-H147 -> 0 | I148: =I145-I147 -> 0 | J148: =J145-J147 -> 0 | K148: =K145-K147 -> 0 | L148: =L145-L147 -> 0
B150: Bank Loan
B151: Beginning Balance | H151: =G154 -> 0 | I151: =H154 -> 0 | J151: =I154 -> 0 | K151: =J154 -> 0 | L151: =K154 -> 0
B152: Interest | H152: =H151*$J$12 -> 0 | I152: =I151*$J$12 -> 0 | J152: =J151*$J$12 -> 0 | K152: =K151*$J$12 -> 0 | L152: =L151*$J$12 -> 0
B153: Paydown | H153: =MIN(H151,H140-H147) -> 0 | I153: =MIN(I151,I140-I147) -> 0 | J153: =MIN(J151,J140-J147) -> 0 | K153: =MIN(K151,K140-K147) -> 0 | L153: =MIN(L151,L140-L147) -> 0
B154: Ending Balance | G154: =L12 -> 0 | H154: =H151-H153 -> 0 | I154: =I151-I153 -> 0 | J154: =J151-J153 -> 0 | K154: =K151-K153 -> 0 | L154: =L151-L153 -> 0
B156: Senior Note
B157: Beginning Balance | H157: =G160 -> 0 | I157: =H160 -> 0 | J157: =I160 -> 0 | K157: =J160 -> 0 | L157: =K160 -> 0
B158: Interest | H158: =H157*$J$13 -> 0 | I158: =I157*$J$13 -> 0 | J158: =J157*$J$13 -> 0 | K158: =K157*$J$13 -> 0 | L158: =L157*$J$13 -> 0
B159: Paydown | H159: =MIN(H157,H140-H147-H153) -> 0 | I159: =MIN(I157,I140-I147-I153) -> 0 | J159: =MIN(J157,J140-J147-J153) -> 0 | K159: =MIN(K157,K140-K147-K153) -> 0 | L159: =MIN(L157,L140-L147-L153) -> 0
B160: Ending Balance | G160: =L13 -> 0 | H160: =H157-H159 -> 0 | I160: =I157-I159 -> 0 | J160: =J157-J159 -> 0 | K160: =K157-K159 -> 0 | L160: =L157-L159 -> 0
B162: Total Debt
B163: Beginning Balance | H163: =H145+H151+H157 -> 0 | I163: =I145+I151+I157 -> 0 | J163: =J145+J151+J157 -> 0 | K163: =K145+K151+K157 -> 0 | L163: =L145+L151+L157 -> 0
B164: Interest | H164: =H146+H152+H158 -> 0 | I164: =I146+I152+I158 -> 0 | J164: =J146+J152+J158 -> 0 | K164: =K146+K152+K158 -> 0 | L164: =L146+L152+L158 -> 0
B165: Paydown | H165: =H147+H153+H159 -> 0 | I165: =I147+I153+I159 -> 0 | J165: =J147+J153+J159 -> 0 | K165: =K147+K153+K159 -> 0 | L165: =L147+L153+L159 -> 0
...

Sheet Sensitivity
B7: Monte-Carlo Simulations | R7: Tornado Chart – Effect on Price Target
AD28: {=_xlfn.SORTBY(R38:Z44,Z38:Z44,1)} -> Capex Intensity | AE28: 0 | AF28: 0.01 | AG28: 0 | AH28: 0 | AI28: 0 | AJ28: 0 | AK28: 0 | AL28: 0
AD29: COGS Margin | AE29: 0 | AF29: 0.02 | AG29: 0 | AH29: 0 | AI29: 0 | AJ29: 0 | AK29: 0 | AL29: 0
AD30: SG&A Margin | AE30: 0 | AF30: 0.01 | AG30: 0 | AH30: 0 | AI30: 0 | AJ30: 0 | AK30: 0 | AL30: 0
AD31: WACC | AE31: 0 | AF31: 0.005 | AG31: 0 | AH31: 0 | AI31: 0 | AJ31: 0 | AK31: 0 | AL31: 0
R32: Reference Price Target | V32: Base Price Target | Z32: Reference | AD32: Terminal g | AE32: 0 | AF32: 0.005 | AG32: 0 | AH32: 0 | AI32: 0 | AJ32: 0 | AK32: 0 | AL32: 0
R33: Gordon PT | T33: =+FCFF!AL169 -> 421.22854 | V33: Base Gordon PT | Z33: EBITDA | AD33: EBITDA Exit | AE33: 0 | AF33: 1.5 | AG33: 0 | AH33: 0 | AI33: 0 | AJ33: 0 | AK33: 0 | AL33: 0
R34: EBITDA PT | T34: =+FCFF!Z169 -> 393.57378 | V34: Base EBITDA PT | AD34: Revenue Exit | AE34: 0 | AF34: 1 | AG34: 0 | AH34: 0 | AI34: 0 | AJ34: 0 | AK34: 0 | AL34: 0
R35: Revenue PT | T35: =FCFF!AF169 -> 393.57378 | V35: Base Revenue PT
T37: Δ | U37: Δ Applied | V37: PT Low | W37: PT High | X37: Δ Low | Y37: Δ High | Z37: Max
R38: Capex Intensity | T38: 0.01 | X38: {=+V38-_xlfn.IFS($Z$33="EBITDA",$X$34,$Z$33="Revenue",$X$35,$Z$33="Gordon",$X$33)} -> 0 | Y38: {=+W38-_xlfn.IFS($Z$33="EBITDA",$X$34,$Z$33="Revenue",$X$35,$Z$33="Gordon",$X$33)} -> 0 | Z38: =MAX(ABS(X38),ABS(Y38)) -> 0
R39: COGS Margin | T39: 0.02 | X39: {=+V39-_xlfn.IFS($Z$33="EBITDA",$X$34,$Z$33="Revenue",$X$35,$Z$33="Gordon",$X$33)} -> 0 | Y39: {=+W39-_xlfn.IFS($Z$33="EBITDA",$X$34,$Z$33="Revenue",$X$35,$Z$33="Gordon",$X$33)} -> 0 | Z39: =MAX(ABS(X39),ABS(Y39)) -> 0
R40: SG&A Margin | T40: 0.01 | X40: {=+V40-_xlfn.IFS($Z$33="EBITDA",$X$34,$Z$33="Revenue",$X$35,$Z$33="Gordon",$X$33)} -> 0 | Y40: {=+W40-_xlfn.IFS($Z$33="EBITDA",$X$34,$Z$33="Revenue",$X$35,$Z$33="Gordon",$X$33)} -> 0 | Z40: =MAX(ABS(X40),ABS(Y40)) -> 0
R41: WACC | T41: 0.005 | X41: {=+V41-_xlfn.IFS($Z$33="EBITDA",$X$34,$Z$33="Revenue",$X$35,$Z$33="Gordon",$X$33)} -> 0 | Y41: {=+W41-_xlfn.IFS($Z$33="EBITDA",$X$34,$Z$33="Revenue",$X$35,$Z$33="Gordon",$X$33)} -> 0 | Z41: =MAX(ABS(X41),ABS(Y41)) -> 0
R42: Terminal g | T42: 0.005 | X42: {=+V42-_xlfn.IFS($Z$33="EBITDA",$X$34,$Z$33="Revenue",$X$35,$Z$33="Gordon",$X$33)} -> 0 | Y42: {=+W42-_xlfn.IFS($Z$33="EBITDA",$X$34,$Z$33="Revenue",$X$35,$Z$33="Gordon",$X$33)} -> 0 | Z42: =MAX(ABS(X42),ABS(Y42)) -> 0
R43: EBITDA Exit | T43: 1.5 | X43: {=+V43-_xlfn.IFS($Z$33="EBITDA",$X$34,$Z$33="Revenue",$X$35,$Z$33="Gordon",$X$33)} -> 0 | Y43: {=+W43-_xlfn.IFS($Z$33="EBITDA",$X$34,$Z$33="Revenue",$X$35,$Z$33="Gordon",$X$33)} -> 0 | Z43: =MAX(ABS(X43),ABS(Y43)) -> 0
R44: Revenue Exit | T44: 1 | X44: {=+V44-_xlfn.IFS($Z$33="EBITDA",$X$34,$Z$33="Revenue",$X$35,$Z$33="Gordon",$X$33)} -> 0 | Y44: {=+W44-_xlfn.IFS($Z$33="EBITDA",$X$34,$Z$33="Revenue",$X$35,$Z$33="Gordon",$X$33)} -> 0 | Z44: =MAX(ABS(X44),ABS(Y44)) -> 0

Sheet IS
B7: Income Statement | D7: 2020 | E7: 2020 | F7: 2020 | G7: 2020 | H7: 2020 | J7: 2021 | K7: 2021 | L7: 2021 | M7: 2021 | N7: 2021 | P7: 2022 | Q7: 2022 | R7: 2022 | S7: 2022 | T7: 2022 | V7: 2023 | W7: 2023 | X7: 2023 | Y7: 2023 | Z7: 2023 | AB7: 2024 | AC7: 2024 | AD7: 2024 | AE7: 2024 | AF7: 2024 | AH7: 2025 | AI7: 2025 | AJ7: 2025 | AK7: 2025 | AL7: 2025 | AN7: 2025 | AO7: 2025 | AP7: 2025 | AQ7: 2025 | AR7: 2025
D8: 2020 | J8: 2021 | P8: 2022 | V8: 2023 | AB8: 2024 | AH8: 2025 | AN8: 2026 | AT8: 2027 | AV8: 2028 | AX8: 2029
D9: Q1 | E9: Q2 | F9: Q3 | G9: Q4 | H9: FY | J9: Q1 | K9: Q2 | L9: Q3 | M9: Q4 | N9: FY | P9: Q1 | Q9: Q2 | R9: Q3 | S9: Q4 | T9: FY | V9: Q1 | W9: Q2 | X9: Q3 | Y9: Q4 | Z9: FY | AB9: Q1 | AC9: Q2 | AD9: Q3 | AE9: Q4 | AF9: FY | AH9: Q1 | AI9: Q2 | AJ9: Q3 | AK9: Q4 | AL9: FY | AN9: Q1 | AO9: Q2 | AP9: Q3 | AQ9: Q4 | AR9: FY | AT9: FY | AV9: FY | AX9: FY
B12: Revenue:
B13: Segment 1
B14: Segment 2
B15: Segment 3
B16: Segment 4
B17: Segment 5
B18: Total revenue | D18: 7631 | E18: 9253 | F18: 8925 | G18: 9731 | H18: 35540 | J18: 9112 | K18: 12058 | L18: 11527 | M18: 11327 | N18: 44024 | P18: 9569 | Q18: 13370 | R18: 14102 | S18: 15536 | T18: 52577 | V18: 12652 | W18: 17387 | X18: 15801 | Y18: 15412 | Z18: 61251 | AB18: 12185 | AC18: 15235 | AD18: 13152 | AE18: 11143 | AF18: 51716 | AH18: 8508 | AI18: 12763
A20: x | B20: Cost of revenue:
B21: Cost of goods and services | D21: 5038 | E21: 6294 | F21: 5831 | G21: 6432 | H21: 23677 | J21: 5813 | K21: 7928 | L21: 7574 | M21: 7801 | N21: 29116 | P21: 6695 | Q21: 8918 | R21: 9511 | S21: 10214 | T21: 35338 | V21: 7934 | W21: 10730 | X21: 9624 | Y21: 9427 | Z21: 37715 | AB21: 7200 | AC21: 9157 | AD21: 7848 | AE21: 6571 | AF21: 30775 | AH21: 5037 | AI21: 7609
B22: Depreciation & amortization | D22: 0 | E22: 0 | F22: 0 | G22: 0 | H22: 0 | J22: 0 | K22: 0 | L22: 0 | M22: 0 | N22: 0 | P22: 0 | Q22: 0 | R22: 0 | S22: 0 | T22: 0 | V22: 0 | W22: 0 | X22: 0 | Y22: 0 | Z22: 0 | AB22: 0 | AC22: 0 | AD22: 0 | AE22: 0 | AF22: 0 | AH22: 0 | AI22: 0
B23: Total cost of revenue | D23: 5038 | E23: 6294 | F23: 5831 | G23: 6432 | H23: 23677 | J23: 5813 | K23: 7928 | L23: 7574 | M23: 7801 | N23: 29116 | P23: 6695 | Q23: 8918 | R23: 9511 | S23: 10214 | T23: 35338 | V23: 7934 | W23: 10730 | X23: 9624 | Y23: 9427 | Z23: 37715 | AB23: 7200 | AC23: 9157 | AD23: 7848 | AE23: 6571 | AF23: 30775 | AH23: 5037 | AI23: 7609
B24: Gross margin | D24: 2593 | E24: 2959 | F24: 3094 | G24: 3299 | H24: 11863 | J24: 3299 | K24: 4130 | L24: 3953 | M24: 3526 | N24: 14908 | P24: 2874 | Q24: 4452 | R24: 4591 | S24: 5322 | T24: 17239 | V24: 4718 | W24: 6657 | X24: 6177 | Y24: 5985 | Z24: 23536 | AB24: 4985 | AC24: 6078 | AD24: 5304 | AE24: 4572 | AF24: 20941 | AH24: 3471 | AI24: 5154
A26: x | B26: Operating expenses:
B27: Selling, general and administrative | D27: 759 | E27: 906 | F27: 752 | G27: 1007 | H27: 3477 | J27: 769 | K27: 838 | L27: 841 | M27: 935 | N27: 3383 | P27: 781 | Q27: 932 | R27: 959 | S27: 1191 | T27: 3863 | V27: 952 | W27: 1330 | X27: 1110 | Y27: 1203 | Z27: 4595 | AB27: 1066 | AC27: 1265 | AD27: 1278 | AE27: 1232 | AF27: 4840 | AH27: 972 | AI27: 1197
B28: Depreciation and amortization | D28: 0 | E28: 0 | F28: 0 | G28: 0 | H28: 0 | J28: 0 | K28: 0 | L28: 0 | M28: 0 | N28: 0 | P28: 0 | Q28: 0 | R28: 0 | S28: 0 | T28: 0 | V28: 0 | W28: 0 | X28: 0 | Y28: 0 | Z28: 0 | AB28: 0 | AC28: 0 | AD28: 0 | AE28: 0 | AF28: 0 | AH28: 0 | AI28: 0
B29: Research and development | D29: 409 | E29: 406 | F29: 370 | G29: 443 | H29: 1644 | J29: 366 | K29: 377 | L29: 394 | M29: 450 | N29: 1587 | P29: 402 | Q29: 453 | R29: 481 | S29: 576 | T29: 1912 | V29: 495 | W29: 547 | X29: 528 | Y29: 606 | Z29: 2177 | AB29: 533 | AC29: 565 | AD29: 567 | AE29: 626 | AF29: 2290 | AH29: 526 | AI29: 549
B30: Other operating expenses | D30: 393 | E30: 171 | F30: 399 | G30: 108.519 | H30: 1059 | J30: 373 | K30: 335 | L30: 351 | M30: 318 | N30: 1378 | P30: 221 | Q30: 259 | R30: 276 | S30: 555 | T30: 1428 | V30: 299 | W30: 190 | X30: 310 | Y30: 304 | Z30: 1101 | AB30: 369 | AC30: 295 | AD30: 264 | AE30: 279 | AF30: 1009 | AH30: 281 | AI30: 287
B31: Total operating expenses | D31: 1561 | E31: 1483 | F31: 1521 | G31: 1558.519 | H31: 6180 | J31: 1508 | K31: 1550 | L31: 1586 | M31: 1703 | N31: 6348 | P31: 1404 | Q31: 1644 | R31: 1716 | S31: 2322 | T31: 7203 | V31: 1746 | W31: 2067 | X31: 1948 | Y31: 2113 | Z31: 7873 | AB31: 1968 | AC31: 2125 | AD31: 2109 | AE31: 2137 | AF31: 8139 | AH31: 1779 | AI31: 2033
B32: Other operating income | D32: 0 | E32: 0 | F32: 0 | G32: 0 | H32: 0 | J32: 0 | K32: 0 | L32: 0 | M32: 0 | N32: 0 | P32: 0 | Q32: 0 | R32: 0 | S32: 0 | T32: 0 | V32: 0 | W32: 0 | X32: 0 | Y32: 0 | Z32: 0 | AB32: 0 | AC32: 0 | AD32: 0 | AE32: 0 | AF32: 0 | AH32: 0 | AI32: 0
B33: Operating income | D33: 1032 | E33: 1476 | F33: 1573 | G33: 1740.481 | H33: 5683 | J33: 1791 | K33: 2580 | L33: 2367 | M33: 1823 | N33: 8560 | P33: 1470 | Q33: 2808 | R33: 2875 | S33: 3000 | T33: 10036 | V33: 2972 | W33: 4590 | X33: 4229 | Y33: 3872 | Z33: 15663 | AB33: 3017 | AC33: 3953 | AD33: 3195 | AE33: 2435 | AF33: 12802 | AH33: 1692 | AI33: 3121
A35: x | B35: Non-operating (income) loss:
B36: Interest expense | D36: 336 | E36: 342 | F36: 290 | G36: 278 | H36: 1247 | J36: 271 | K36: 268 | L36: 244 | M36: 210 | N36: 993 | P36: 229 | Q36: 187 | R36: 296 | S36: 349 | T36: 1062 | V36: 479 | W36: 569 | X36: 623 | Y36: 781 | Z36: 2453 | AB36: 802 | AC36: 836 | AD36: 840 | AE36: 870 | AF36: 3348 | AH36: 829 | AI36: 784
B37: Interest income | D37: 0 | E37: 0 | F37: 0 | G37: 0 | H37: 0 | J37: 0 | K37: 0 | L37: 0 | M37: 0 | N37: 0 | P37: 0 | Q37: 0 | R37: 0 | S37: 0 | T37: 0 | V37: 0 | W37: 0 | X37: 0 | Y37: 0 | Z37: 0 | AB37: 0 | AC37: 0 | AD37: 0 | AE37: 0 | AF37: 0 | AH37: 0 | AI37: 0
A38: x | B38: Net interest (income) expense | D38: 336 | E38: 342 | F38: 290 | G38: 278 | H38: 1247 | J38: 271 | K38: 268 | L38: 244 | M38: 210 | N38: 993 | P38: 229 | Q38: 187 | R38: 296 | S38: 349 | T38: 1062 | V38: 479 | W38: 569 | X38: 623 | Y38: 781 | Z38: 2453 | AB38: 802 | AC38: 836 | AD38: 840 | AE38: 870 | AF38: 3348 | AH38: 829 | AI38: 784
B39: Foreign exchange (gains) losses | D39: 0 | E39: 0 | F39: 0 | G39: 0 | H39: 0 | J39: 0 | K39: 0 | L39: 0 | M39: 0 | N39: 0 | P39: 0 | Q39: 0 | R39: 0 | S39: 0 | T39: 0 | V39: 0 | W39: 0 | X39: 0 | Y39: 0 | Z39: 0 | AB39: 0 | AC39: 0 | AD39: 0 | AE39: 0 | AF39: 0 | AH39: 0 | AI39: 0
B40: Other non-operating (income) expenses | D40: 0 | E40: 0 | F40: 0 | G40: 0 | H40: 0 | J40: 0 | K40: 0 | L40: 0 | M40: 0 | N40: 0 | P40: 0 | Q40: 0 | R40: 0 | S40: 0 | T40: 0 | V40: 0 | W40: 0 | X40: 0 | Y40: 0 | Z40: 0 | AB40: 0 | AC40: 0 | AD40: 0 | AE40: -1 | AF40: -5 | AH40: 0 | AI40: 0
B41: Total non-operating expenses | D41: 336 | E41: 342 | F41: 290 | G41: 278 | H41: 1247 | J41: 271 | K41: 268 | L41: 244 | M41: 210 | N41: 993 | P41: 229 | Q41: 187 | R41: 296 | S41: 349 | T41: 1062 | V41: 479 | W41: 569 | X41: 623 | Y41: 781 | Z41: 2453 | AB41: 802 | AC41: 836 | AD41: 840 | AE41: 869 | AF41: 3343 | AH41: 829 | AI41: 784
B42: Pre-tax income | D42: 696 | E42: 1134 | F42: 1283 | G42: 1462.481 | H42: 4436 | J42: 1520 | K42: 2312 | L42: 2123 | M42: 1613 | N42: 7567 | P42: 1241 | Q42: 2621 | R42: 2579 | S42: 2651 | T42: 8974 | V42: 2493 | W42: 4021 | X42: 3606 | Y42: 3091 | Z42: 13210 | AB42: 2215 | AC42: 3117 | AD42: 2355 | AE42: 1566 | AF42: 9459 | AH42: 863 | AI42: 2337
A44: x | B44: Tax & net income:
B45: Income tax expenses (benefits) | D45: 76.67 | E45: 260.3 | F45: 459.73 | G45: 408.601 | H45: 1198.13 | J45: 298.34 | K45: 530 | L45: 485.33 | M45: 330 | N45: 1650.65 | P45: 268.9 | Q45: 475.49 | R45: 662.4 | S45: 593.86 | T45: 1974.87 | V45: 537 | W45: 1027.33 | X45: 879 | Y45: 710.78 | Z45: 2911.11 | AB45: 469 | AC45: 751 | AD45: 625 | AE45: 242.93 | AF45: 2181 | AH45: 20.28 | AI45: 539
B46: Net extraordinary losses (gains) | D46: 1 | E46: 17 | F46: 2 | G46: 28 | H46: 48 | J46: -4 | K46: -8 | L46: -8 | M46: 0 | N46: -21 | P46: -3 | Q46: -6 | R46: 0 | S46: -2 | T46: -10 | V46: -1 | W46: -2 | X46: -2 | Y46: -2 | Z46: -7 | AB46: -2 | AC46: -2 | AD46: -1 | AE46: 28 | AF46: 24 | AH46: 1 | AI46: -3
B47: Net income including minority interest | D47: 618.33 | E47: 856.7 | F47: 821.27 | G47: 1025.88 | H47: 3189.87 | J47: 1225.66 | K47: 1790 | L47: 1645.67 | M47: 1283 | N47: 5937.35 | P47: 975.1 | Q47: 2151.51 | R47: 1916.6 | S47: 2059.14 | T47: 7009.13 | V47: 1957 | W47: 2995.67 | X47: 2729 | Y47: 2382.22 | Z47: 10305.89 | AB47: 1748 | AC47: 2368 | AD47: 1731 | AE47: 1295.07 | AF47: 7254 | AH47: 841.72 | AI47: 1801
A49: x | B49: Attribution:
B50: Preferred dividends | D50: 0 | E50: 0 | F50: 0 | G50: 0 | H50: 0 | J50: 0 | K50: 0 | L50: 0 | M50: 0 | N50: 0 | P50: 0 | Q50: 0 | R50: 0 | S50: 0 | T50: 0 | V50: 0 | W50: 0 | X50: 0 | Y50: 0 | Z50: 0 | AB50: 0 | AC50: 0 | AD50: 0 | AE50: 0 | AF50: 0 | AH50: 0 | AI50: 0
B51: Income attributable to non-controlling interests | D51: 1 | E51: 0 | F51: 0 | G51: 1 | H51: 2 | J51: 0 | K51: 0 | L51: 0 | M51: 0 | N51: 2 | P51: 1 | Q51: -1 | R51: 1 | S51: -2 | T51: -1 | V51: -2 | W51: -1 | X51: -6 | Y51: -1 | Z51: -11 | AB51: -3 | AC51: -2 | AD51: -3 | AE51: -3 | AF51: -12 | AH51: -2 | AI51: -3
B52: Net income attributable to common shareholders | D52: 617.33 | E52: 856.7 | F52: 821.27 | G52: 1024.88 | H52: 3187.87 | J52: 1225.66 | K52: 1790 | L52: 1645.67 | M52: 1283 | N52: 5935.35 | P52: 974.1 | Q52: 2152.51 | R52: 1915.6 | S52: 2061.14 | T52: 7010.13 | V52: 1959 | W52: 2996.67 | X52: 2735 | Y52: 2383.22 | Z52: 10316.89 | AB52: 1751 | AC52: 2370 | AD52: 1734 | AE52: 1298.07 | AF52: 7266 | AH52: 843.72 | AI52: 1804
A54: x | B54: Earnings per share:
B55: EPS basic | D55: 1.9692 | E55: 2.7353 | F55: 2.6239 | G55: 3.2629 | H55: 10.1686 | J55: 3.9096 | K55: 5.72 | L55: 5.2915 | M55: 4.1494 | N55: 19.048 | P55: 3.1688 | Q55: 7.0298 | R55: 6.2992 | S55: 6.8568 | T55: 23.0218 | V55: 6.58 | W55: 10.1548 | X55: 9.4051 | Y55: 8.3475 | Z55: 35.3076 | AB55: 6.25 | AC55: 8.56 | AD55: 6.32 | AE55: 4.7618 | AF55: 26.3261 | AH55: 3.1065 | AI55: 6.65
B56: EPS diluted | D56: 1.9463 | E56: 2.7131 | F56: 2.6025 | G56: 3.2348 | H56: 10.0699 | J56: 3.8753 | K56: 5.68 | L56: 5.2519 | M56: 4.1214 | N56: 18.9019 | P56: 3.1498 | Q56: 6.9869 | R56: 6.2634 | S56: 6.8227 | T56: 22.8854 | V56: 6.55 | W56: 10.1109 | X56: 9.3681 | Y56: 8.3096 | Z56: 35.1439 | AB56: 6.23 | AC56: 8.53 | AD56: 6.29 | AE56: 4.744 | AF56: 26.2191 | AH56: 3.0972 | AI56: 6.64
A58: x | B58: Shares used in computing earnings per share:
B59: Basic weighted average shares | D59: 313.5 | E59: 313.2 | F59: 313 | G59: 314.1 | H59: 313.5 | J59: 313.5 | K59: 312.8 | L59: 311 | M59: 309.2 | N59: 311.6 | P59: 307.4 | Q59: 306.2 | R59: 304.1 | S59: 300.6 | T59: 304.5 | V59: 297.6 | W59: 295.1 | X59: 290.8 | Y59: 285.5 | Z59: 292.2 | AB59: 279.9 | AC59: 276.8 | AD59: 274.5 | AE59: 272.6 | AF59: 276 | AH59: 271.6 | AI59: 271.1
B60: Diluted weighted average shares | D60: 317.2 | E60: 316.2 | F60: 315.8 | G60: 317.1 | H60: 316.6 | J60: 316.1 | K60: 315.2 | L60: 313.4 | M60: 311.3 | N60: 314 | P60: 309.4 | Q60: 308.1 | R60: 305.7 | S60: 302.1 | T60: 306.3 | V60: 299.1 | W60: 296.5 | X60: 292.1 | Y60: 286.9 | Z60: 293.6 | AB60: 281.1 | AC60: 277.9 | AD60: 275.6 | AE60: 273.6 | AF60: 277.1 | AH60: 272.3 | AI60: 271.8
B62: Additional Items
B64: Depreciation (from opex)
B65: Amortization (form opex)

Sheet BS
AH1: 0
B7: Balance Sheet | D7: 2020 | E7: 2020 | F7: 2020 | G7: 2020 | H7: 2020 | J7: 2021 | K7: 2021 | L7: 2021 | M7: 2021 | N7: 2021 | P7: 2022 | Q7: 2022 | R7: 2022 | S7: 2022 | T7: 2022 | V7: 2023 | W7: 2023 | X7: 2023 | Y7: 2023 | Z7: 2023 | AB7: 2024 | AC7: 2024 | AD7: 2024 | AE7: 2024 | AF7: 2024 | AH7: 2025 | AI7: 2025 | AJ7: 2025 | AK7: 2025 | AL7: 2025 | AN7: 2025 | AO7: 2025 | AP7: 2025 | AQ7: 2025 | AR7: 2025
D8: 2020 | J8: 2021 | P8: 2022 | V8: 2023 | AB8: 2024 | AH8: 2025 | AN8: 2026 | AT8: 2027 | AV8: 2028 | AX8: 2029
D9: Q1 | E9: Q2 | F9: Q3 | G9: Q4 | H9: FY | J9: Q1 | K9: Q2 | L9: Q3 | M9: Q4 | N9: FY | P9: Q1 | Q9: Q2 | R9: Q3 | S9: Q4 | T9: FY | V9: Q1 | W9: Q2 | X9: Q3 | Y9: Q4 | Z9: FY | AB9: Q1 | AC9: Q2 | AD9: Q3 | AE9: Q4 | AF9: FY | AH9: Q1 | AI9: Q2 | AJ9: Q3 | AK9: Q4 | AL9: FY | AN9: Q1 | AO9: Q2 | AP9: Q3 | AQ9: Q4 | AR9: FY | AT9: FY | AV9: FY | AX9: FY
B12: Assets
A14: x | B14: Current assets:
B15: Cash & cash equivalents & short-term investments | D15: 4211 | E15: 9526 | F15: 8830 | G15: 7707 | H15: 7707 | J15: 7629 | K15: 7850 | L15: 8207 | M15: 8745 | N15: 8745 | P15: 5207 | Q15: 4560 | R15: 5078 | S15: 5508 | T15: 5508 | V15: 4828 | W15: 6123 | X15: 7417 | Y15: 8404 | Z15: 8404 | AB15: 6273 | AC15: 6647 | AD15: 8144 | AE15: 8478 | AF15: 8478 | AH15: 7815 | AI15: 9263
B16: Cash & cash equivalents | D16: 609 | E16: 626 | F16: 640 | G16: 641 | H16: 641 | J16: 667 | K16: 668 | L16: 688 | M16: 728 | N16: 728 | P16: 735 | Q16: 682 | R16: 719 | S16: 734 | T16: 734 | V16: 852 | W16: 856 | X16: 841 | Y16: 946 | Z16: 946 | AB16: 1136 | AC16: 1094 | AD16: 1140 | AE16: 1154 | AF16: 1154 | AH16: 1214 | AI16: 1272
B17: Short-term investments | D17: 3602 | E17: 8900 | F17: 8190 | G17: 7066 | H17: 7066 | J17: 6962 | K17: 7182 | L17: 7519 | M17: 8017 | N17: 8017 | P17: 4472 | Q17: 3878 | R17: 4359 | S17: 4774 | T17: 4774 | V17: 3976 | W17: 5267 | X17: 6576 | Y17: 7458 | Z17: 7458 | AB17: 5137 | AC17: 5553 | AD17: 7004 | AE17: 7324 | AF17: 7324 | AH17: 6601 | AI17: 7991
B18: Accounts receivable | D18: 5360 | E18: 5986 | F18: 5473 | G18: 4171 | H18: 4171 | J18: 5037 | K18: 6158 | L18: 5268 | M18: 4208 | N18: 4208 | P18: 4855 | Q18: 6258 | R18: 6696 | S18: 6410 | T18: 6410 | V18: 7609 | W18: 9971 | X18: 9297 | Y18: 7739 | Z18: 7739 | AB18: 7795 | AC18: 8880 | AD18: 7469 | AE18: 5326 | AF18: 5326 | AH18: 4931 | AI18: 6748
B19: Inventory | D19: 6482 | E19: 6171 | F19: 5650 | G19: 4999 | H19: 4999 | J19: 5956 | K19: 6042 | L19: 6410 | M19: 6781 | N19: 6781 | P19: 7935 | Q19: 9030 | R19: 9121 | S19: 8495 | T19: 8495 | V19: 10056 | W19: 9713 | X19: 9350 | Y19: 8160 | Z19: 8160 | AB19: 8937 | AC19: 8443 | AD19: 7696 | AE19: 7093 | AF19: 7093 | AH19: 7744 | AI19: 7870
B20: Prepaid expenses and other current assets | D20: 1405 | E20: 1244 | F20: 1243 | G20: 1251 | H20: 1251 | J20: 1169 | K20: 1504 | L20: 1702 | M20: 1765 | N20: 1765 | P20: 1936 | Q20: 2306 | R20: 1999 | S20: 2492 | T20: 2492 | V20: 1992 | W20: 2593 | X20: 3118 | Y20: 2623 | Z20: 2623 | AB20: 2017 | AC20: 2535 | AD20: 5235 | AE20: 5489 | AF20: 5489 | AH20: 5908 | AI20: 2975
B21: Total current assets | D21: 17458 | E21: 22927 | F21: 21196 | G21: 18128 | H21: 18128 | J21: 19791 | K21: 21554 | L21: 21587 | M21: 21499 | N21: 21499 | P21: 19933 | Q21: 22154 | R21: 22894 | S21: 22905 | T21: 22905 | V21: 24485 | W21: 28400 | X21: 29182 | Y21: 26926 | Z21: 26926 | AB21: 25022 | AC21: 26505 | AD21: 28544 | AE21: 26386 | AF21: 26386 | AH21: 26398 | AI21: 26856
A23: x | B23: Non-current assets:
B24: Net PP&E (Property, Plant and Equipment) | D24: 13404 | E24: 12930 | F24: 12912 | G24: 13115 | H24: 13115 | J24: 12771 | K24: 12812 | L24: 12631 | M24: 12808 | N24: 12808 | P24: 12289 | Q24: 12180 | R24: 12220 | S24: 12679 | T24: 12679 | V24: 12714 | W24: 12812 | X24: 13127 | Y24: 13796 | Z24: 13796 | AB24: 13665 | AC24: 13999 | AD24: 14210 | AE24: 15031 | AF24: 15031 | AH24: 14582 | AI24: 14891
B25: Gross PP&E (Property, Plant and Equipment) | D25: 0 | E25: 0 | F25: 0 | G25: 22939 | H25: 22939 | J25: 0 | K25: 0 | L25: 0 | M25: 23108 | N25: 23108 | P25: 0 | Q25: 0 | R25: 0 | S25: 22703 | T25: 22703 | V25: 0 | W25: 0 | X25: 0 | Y25: 22850 | Z25: 22850 | AB25: 0 | AC25: 0 | AD25: 0 | AE25: 24626 | AF25: 24626 | AH25: 0 | AI25: 0
B26: Accumulated Depreciation | D26: 0 | E26: 0 | F26: 0 | G26: 9824 | H26: 9824 | J26: 0 | K26: 0 | L26: 0 | M26: 10300 | N26: 10300 | P26: 0 | Q26: 0 | R26: 0 | S26: 10024 | T26: 10024 | V26: 0 | W26: 0 | X26: 0 | Y26: 9054 | Z26: 9054 | AB26: 0 | AC26: 0 | AD26: 0 | AE26: 9595 | AF26: 9595 | AH26: 0 | AI26: 0
B27: Intangibles | D27: 4294 | E27: 4228 | F27: 4285 | G27: 4408 | H27: 4408 | J27: 4536 | K27: 4500 | L27: 4415 | M27: 4566 | N27: 4566 | P27: 4401 | Q27: 5164 | R27: 5035 | S27: 4905 | T27: 4905 | V27: 5146 | W27: 5185 | X27: 5193 | Y27: 5033 | Z27: 5033 | AB27: 5078 | AC27: 5000 | AD27: 4990 | AE27: 4958 | AF27: 4958 | AH27: 4809 | AI27: 5058
B28: Goodwill | D28: 2945 | E28: 2917 | F28: 2984 | G28: 3081 | H28: 3081 | J28: 3194 | K28: 3190 | L28: 3148 | M28: 3291 | N28: 3291 | P28: 3192 | Q28: 3812 | R28: 3754 | S28: 3687 | T28: 3687 | V28: 3891 | W28: 3963 | X28: 3994 | Y28: 3900 | Z28: 3900 | AB28: 3966 | AC28: 3936 | AD28: 3960 | AE28: 3959 | AF28: 3959 | AH28: 3872 | AI28: 4094
B29: Intangibles excl. Goodwill | D29: 0 | E29: 0 | F29: 0 | G29: 0 | H29: 0 | J29: 0 | K29: 0 | L29: 0 | M29: 0 | N29: 0 | P29: 0 | Q29: 0 | R29: 0 | S29: 0 | T29: 0 | V29: 0 | W29: 0 | X29: 0 | Y29: 0 | Z29: 0 | AB29: 0 | AC29: 0 | AD29: 0 | AE29: 0 | AF29: 0 | AH29: 0 | AI29: 0
B30: Other Non-Current Assets | D30: 36665 | E30: 37241 | F30: 38871 | G30: 39440 | H30: 39440 | J30: 38382 | K30: 40113 | L30: 42055 | M30: 45241 | N30: 45241 | P30: 42991 | Q30: 44601 | R30: 46668 | S30: 49541 | T30: 49541 | V30: 49275 | W30: 51950 | X30: 55895 | Y30: 58332 | Z30: 58332 | AB30: 57606 | AC30: 60124 | AD30: 60097 | AE30: 60945 | AF30: 60945 | AH30: 57330 | AI30: 59498
B31: Total Non-Current Assets | D31: 54363 | E31: 54399 | F31: 56068 | G31: 56963 | H31: 56963 | J31: 55689 | K31: 57425 | L31: 59101 | M31: 62615 | N31: 62615 | P31: 59681 | Q31: 61945 | R31: 63923 | S31: 67125 | T31: 67125 | V31: 67135 | W31: 69947 | X31: 74215 | Y31: 77161 | Z31: 77161 | AB31: 76349 | AC31: 79123 | AD31: 79297 | AE31: 80934 | AF31: 80934 | AH31: 76721 | AI31: 79447
B32: Total Assets | D32: 71821 | E32: 77326 | F32: 77264 | G32: 75091 | H32: 75091 | J32: 75480 | K32: 78979 | L32: 80688 | M32: 84114 | N32: 84114 | P32: 79614 | Q32: 84099 | R32: 86817 | S32: 90030 | T32: 90030 | V32: 91620 | W32: 98347 | X32: 103397 | Y32: 104087 | Z32: 104087 | AB32: 101371 | AC32: 105628 | AD32: 107841 | AE32: 107320 | AF32: 107320 | AH32: 103119 | AI32: 106303
B34: Liabilities & shareholders' equity
A36: x | B36: Current Liabilities:
B37: Accounts payable | D37: 8172 | E37: 8554 | F37: 9077 | G37: 8053 | H37: 8053 | J37: 8916 | K37: 10131 | L37: 11055 | M37: 10823 | N37: 10823 | P37: 10108 | Q37: 11899 | R37: 12319 | S37: 12333 | T37: 12333 | V37: 12217 | W37: 12844 | X37: 13210 | Y37: 13592 | Z37: 13592 | AB37: 12621 | AC37: 12320 | AD37: 12569 | AE37: 12452 | AF37: 12452 | AH37: 11946 | AI37: 11312
B38: Short-term borrowings | D38: 14412 | E38: 15806 | F38: 14418 | G38: 13243 | H38: 13243 | J38: 13173 | K38: 13993 | L38: 15658 | M38: 15501 | N38: 15501 | P38: 14449 | Q38: 16419 | R38: 19096 | S38: 18282 | T38: 18282 | V38: 18970 | W38: 22488 | X38: 23751 | Y38: 24909 | Z38: 24909 | AB38: 23206 | AC38: 23611 | AD38: 23163 | AE38: 21931 | AF38: 21931 | AH38: 20791 | AI38: 23471
B39: Current portion of lease liabilities | D39: 373 | E39: 332 | F39: 336 | G39: 318 | H39: 318 | J39: 335 | K39: 352 | L39: 23 | M39: 302 | N39: 302 | P39: 290 | Q39: 0 | R39: 0 | S39: 323 | T39: 323 | V39: 23 | W39: 0 | X39: 0 | Y39: 306 | Z39: 306 | AB39: 27 | AC39: 1064 | AD39: 0 | AE39: 303 | AF39: 303 | AH39: 34 | AI39: 39
B40: Accrued expenses and other current liabilities | D40: 244 | E40: 290 | F40: 250 | G40: 1867 | H40: 1867 | J40: 292 | K40: 223 | L40: 152 | M40: 1246 | N40: 1246 | P40: 276 | Q40: 780 | R40: 667 | S40: 2187 | T40: 2187 | V40: 891 | W40: 1872 | X40: 2130 | Y40: 2257 | Z40: 2257 | AB40: 740 | AC40: 2289 | AD40: 3631 | AE40: 1821 | AF40: 1821 | AH40: 216 | AI40: 2033
B41: Total current liabilities | D41: 23201 | E41: 24982 | F41: 24081 | G41: 23481 | H41: 23481 | J41: 22716 | K41: 24699 | L41: 26888 | M41: 27872 | N41: 27872 | P41: 25123 | Q41: 29098 | R41: 32082 | S41: 33125 | T41: 33125 | V41: 32101 | W41: 37204 | X41: 39091 | Y41: 41064 | Z41: 41064 | AB41: 36594 | AC41: 39284 | AD41: 39363 | AE41: 36507 | AF41: 36507 | AH41: 32987 | AI41: 36855
A43: x | B43: Non-current liabilities:
B44: Long-term borrowings | D44: 30452 | E44: 34298 | F44: 34004 | G44: 32695 | H44: 32695 | J44: 32736 | K44: 33301 | L44: 32238 | M44: 32850 | N44: 32850 | P44: 32806 | Q44: 32447 | R44: 32132 | S44: 33566 | T44: 33566 | V44: 35071 | W44: 35611 | X44: 38112 | Y44: 38428 | Z44: 38428 | AB44: 39933 | AC44: 40962 | AD44: 42692 | AE44: 43157 | AF44: 43157 | AH44: 43556 | AI44: 42811
B45: Long-term operating lease liabilities | D45: 23 | E45: 26 | F45: 33 | G45: 100 | H45: 100 | J45: 36 | K45: 45 | L45: 42 | M45: 38 | N45: 38 | P45: 32 | Q45: 0 | R45: 0 | S45: 30 | T45: 30 | V45: 0 | W45: 0 | X45: 0 | Y45: 49 | Z45: 49 | AB45: 0 | AC45: 0 | AD45: 0 | AE45: 72 | AF45: 72 | AH45: 0 | AI45: 0
B46: Other non-current liabilities | D46: 6201 | E46: 6155 | F46: 6255 | G46: 5871 | H46: 5871 | J46: 5906 | K46: 5838 | L46: 5787 | M46: 4920 | N46: 4920 | P46: 3845 | Q46: 3548 | R46: 3472 | S46: 2952 | T46: 2952 | V46: 3012 | W46: 3031 | X46: 3042 | Y46: 2660 | Z46: 2660 | AB46: 2665 | AC46: 2596 | AD46: 2637 | AE46: 4659 | AF46: 4659 | AH46: 4012 | AI46: 2259
B47: Total non-current liabilities | D47: 36676 | E47: 40479 | F47: 40292 | G47: 38666 | H47: 38666 | J47: 38678 | K47: 39184 | L47: 38067 | M47: 37808 | N47: 37808 | P47: 36683 | Q47: 35995 | R47: 35604 | S47: 36548 | T47: 36548 | V47: 38083 | W47: 38642 | X47: 41154 | Y47: 41137 | Z47: 41137 | AB47: 42598 | AC47: 43558 | AD47: 45329 | AE47: 47888 | AF47: 47888 | AH47: 47568 | AI47: 45070
B48: Total liabilities | D48: 59877 | E48: 65461 | F48: 64373 | G48: 62147 | H48: 62147 | J48: 61394 | K48: 63883 | L48: 64955 | M48: 65680 | N48: 65680 | P48: 61806 | Q48: 65093 | R48: 67686 | S48: 69673 | T48: 69673 | V48: 70184 | W48: 75846 | X48: 80245 | Y48: 82201 | Z48: 82201 | AB48: 79192 | AC48: 82842 | AD48: 84692 | AE48: 84395 | AF48: 84395 | AH48: 80555 | AI48: 81925
A50: x | B50: Shareholders' equity:
B51: Common equity | D51: 11926 | E51: 11864 | F51: 12888 | G51: 12937 | H51: 12937 | J51: 14083 | K51: 15092 | L51: 15731 | M51: 18431 | N51: 18431 | P51: 17804 | Q51: 18904 | R51: 19033 | S51: 20262 | T51: 20262 | V51: 21332 | W51: 22395 | X51: 23048 | Y51: 21785 | Z51: 21785 | AB51: 22075 | AC51: 22684 | AD51: 23062 | AE51: 22836 | AF51: 22836 | AH51: 22479 | AI51: 24287
B52: Preferred equity | D52: 0 | E52: 0 | F52: 0 | G52: 0 | H52: 0 | J52: 0 | K52: 0 | L52: 0 | M52: 0 | N52: 0 | P52: 0 | Q52: 0 | R52: 0 | S52: 0 | T52: 0 | V52: 0 | W52: 0 | X52: 0 | Y52: 0 | Z52: 0 | AB52: 0 | AC52: 0 | AD52: 0 | AE52: 0 | AF52: 0 | AH52: 0 | AI52: 0
B53: Non-controlling interest | D53: 18 | E53: 1 | F53: 3 | G53: 7 | H53: 7 | J53: 3 | K53: 4 | L53: 2 | M53: 3 | N53: 3 | P53: 4 | Q53: 102 | R53: 98 | S53: 95 | T53: 95 | V53: 104 | W53: 106 | X53: 104 | Y53: 101 | Z53: 101 | AB53: 104 | AC53: 102 | AD53: 87 | AE53: 89 | AF53: 89 | AH53: 85 | AI53: 91
B54: Total equity | D54: 11944 | E54: 11865 | F54: 12891 | G54: 12944 | H54: 12944 | J54: 14086 | K54: 15096 | L54: 15733 | M54: 18434 | N54: 18434 | P54: 17808 | Q54: 19006 | R54: 19131 | S54: 20357 | T54: 20357 | V54: 21436 | W54: 22501 | X54: 23152 | Y54: 21886 | Z54: 21886 | AB54: 22179 | AC54: 22786 | AD54: 23149 | AE54: 22925 | AF54: 22925 | AH54: 22564 | AI54: 24378
B55: Total liabilities and shareholders' equity | D55: 71821 | E55: 77326 | F55: 77264 | G55: 75091 | H55: 75091 | J55: 75480 | K55: 78979 | L55: 80688 | M55: 84114 | N55: 84114 | P55: 79614 | Q55: 84099 | R55: 86817 | S55: 90030 | T55: 90030 | V55: 91620 | W55: 98347 | X55: 103397 | Y55: 104087 | Z55: 104087 | AB55: 101371 | AC55: 105628 | AD55: 107841 | AE55: 107320 | AF55: 107320 | AH55: 103119 | AI55: 106303
B57: Capitalized R&D | D57: 0 | E57: 0 | F57: 0 | G57: 0 | H57: 0 | J57: 0 | K57: 0 | L57: 0 | M57: 0 | N57: 0 | P57: 0 | Q57: 0 | R57: 0 | S57: 0 | T57: 0 | V57: 0 | W57: 0 | X57: 0 | Y57: 0 | Z57: 0 | AB57: 0 | AC57: 0 | AD57: 0 | AE57: 0 | AF57: 0 | AH57: 0 | AI57: 0
B61: Debt | D61: =D38+D39+D44+D45 -> 45260 | E61: =E38+E39+E44+E45 -> 50462 | F61: =F38+F39+F44+F45 -> 48791 | G61: =G38+G39+G44+G45 -> 46356 | H61: =H38+H39+H44+H45 -> 46356 | I61: =I38+I39+I44+I45 -> 0 | J61: =J38+J39+J44+J45 -> 46280 | K61: =K38+K39+K44+K45 -> 47691 | ... AI61: =AI38+AI39+AI44+AI45 -> 66321
B62: Total | T62: ='Stock Data'!AQ1047+T61 -> 169521.31 | Z62: ='Stock Data'!AQ694+Z61 -> 171735.42 | AF62: ='Stock Data'!AQ330+BS!AF61 -> 177291.45
B63: % of debt | D63: =D61/D62 -> #DIV/0! | E63: =E61/E62 -> #DIV/0! | F63: =F61/F62 -> #DIV/0! | G63: =G61/G62 -> #DIV/0! | H63: =H61/H62 -> #DIV/0! | I63: =I61/I62 -> #DIV/0! | J63: =J61/J62 -> #DIV/0! | K63: =K61/K62 -> #DIV/0! | ... AI63: =AI61/AI62 -> #DIV/0!
B64: EBITDA | D64: =IS!D33+CF!D17 -> 1570 | E64: =IS!E33+CF!E17 -> 2005 | F64: =IS!F33+CF!F17 -> 2120 | G64: =IS!G33+CF!G17 -> 2244.481 | H64: =IS!H33+CF!H17 -> 7801 | I64: =IS!I33+CF!I17 -> 0 | J64: =IS!J33+CF!J17 -> 2329 | K64: =IS!K33+CF!K17 -> 3096 | ... AI64: =IS!AI33+CF!AI17 -> 3676
B65: Debt/EBITDA | D65: =D61/D64 -> 28.828025 | E65: =E61/E64 -> 25.16808 | F65: =F61/F64 -> 23.014623 | G65: =G61/G64 -> 20.653327 | H65: =H61/H64 -> 5.9423151 | I65: =I61/I64 -> #DIV/0! | J65: =J61/J64 -> 19.871189 | K65: =K61/K64 -> 15.40407 | ... AI65: =AI61/AI64 -> 18.041621

Sheet CF
A7: x | B7: Cash Flow Statement | D7: 2020 | E7: 2020 | F7: 2020 | G7: 2020 | H7: 2020 | J7: 2021 | K7: 2021 | L7: 2021 | M7: 2021 | N7: 2021 | P7: 2022 | Q7: 2022 | R7: 2022 | S7: 2022 | T7: 2022 | V7: 2023 | W7: 2023 | X7: 2023 | Y7: 2023 | Z7: 2023 | AB7: 2024 | AC7: 2024 | AD7: 2024 | AE7: 2024 | AF7: 2024 | AH7: 2025 | AI7: 2025 | AJ7: 2025 | AK7: 2025 | AL7: 2025 | AN7: 2025 | AO7: 2025 | AP7: 2025 | AQ7: 2025 | AR7: 2025
D8: 2020 | J8: 2021 | P8: 2022 | V8: 2023 | AB8: 2024 | AH8: 2025 | AN8: 2026 | AT8: 2027 | AV8: 2028 | AX8: 2029
D9: Q1 | E9: Q2 | F9: Q3 | G9: Q4 | H9: FY | J9: Q1 | K9: Q2 | L9: Q3 | M9: Q4 | N9: FY | P9: Q1 | Q9: Q2 | R9: Q3 | S9: Q4 | T9: FY | V9: Q1 | W9: Q2 | X9: Q3 | Y9: Q4 | Z9: FY | AB9: Q1 | AC9: Q2 | AD9: Q3 | AE9: Q4 | AF9: FY | AH9: Q1 | AI9: Q2 | AJ9: Q3 | AK9: Q4 | AL9: FY | AN9: Q1 | AO9: Q2 | AP9: Q3 | AQ9: Q4 | AR9: FY | AT9: FY | AV9: FY | AX9: FY
B12: Cash and cash equivalents, beginning balances | D12: 3857 | E12: 3602 | F12: 8900 | G12: 8190 | H12: 7066 | J12: 7066 | K12: 6962 | L12: 7182 | M12: 7519 | N12: 8017 | P12: 8017 | Q12: 4472 | R12: 3878 | S12: 4359 | T12: 4774 | V12: 4774 | W12: 3976 | X12: 5267 | Y12: 6576 | Z12: 7458 | AB12: 7458 | AC12: 5137 | AD12: 5553 | AE12: 7004 | AF12: 7324 | AH12: 7324 | AI12: 6601
A14: x | B14: Operating activities:
B15: Net income | D15: 517 | E15: 666 | F15: 811 | G15: 757 | H15: 2751 | J15: 1224 | K15: 1790 | L15: 1667 | M15: 1283 | N15: 5963 | P15: 903 | Q15: 2098 | R15: 1884 | S15: 2246 | T15: 7131 | V15: 1959 | W15: 2860 | X15: 2978 | Y15: 2369 | Z15: 10166 | AB15: 1751 | AC15: 2370 | AD15: 1734 | AE15: 1245 | AF15: 7100 | AH15: 869 | AI15: 1804
B16: Adjustments to reconcile to cash from operations:
B17: Depreciation and amortization | D17: 538 | E17: 529 | F17: 547 | G17: 504 | H17: 2118 | J17: 538 | K17: 516 | L17: 515 | M17: 481 | N17: 2050 | P17: 486 | Q17: 447 | R17: 510 | S17: 452 | T17: 1895 | V17: 494 | W17: 501 | X17: 532 | Y17: 477 | Z17: 2004 | AB17: 520 | AC17: 525 | AD17: 553 | AE17: 520 | AF17: 2118 | AH17: 549 | AI17: 555
B18: Stock-based compensation expense | D18: 19 | E18: 29 | F18: 15 | G18: 18 | H18: 81 | J18: 15 | K18: 30 | L18: 19 | M18: 18 | N18: 82 | P18: 18 | Q18: 26 | R18: 20 | S18: 21 | T18: 85 | V18: 23 | W18: 31 | X18: 58 | Y18: 18 | Z18: 130 | AB18: 46 | AC18: 58 | AD18: 55 | AE18: 49 | AF18: 208 | AH18: 28 | AI18: 26
B19: Other | D19: 196 | E19: 197 | F19: 0 | G19: -185 | H19: 207 | J19: -21 | K19: -316 | L19: -114 | M19: -204 | N19: -654 | P19: -801 | Q19: -513 | R19: 220 | S19: 67 | T19: -1027 | V19: -27 | W19: -136 | X19: 5 | Y19: -256 | Z19: -414 | AB19: -35 | AC19: 20 | AD19: -103 | AE19: 85 | AF19: -33 | AH19: -433 | AI19: 110
B20: Changes in working capital:
B21: Accounts receivable | D21: 70 | E21: -561 | F21: 1117 | G21: 1383 | H21: 2009 | J21: -97 | K21: -1027 | L21: 680 | M21: 1413 | N21: 969 | P21: -106 | Q21: -1429 | R21: -822 | S21: -126 | T21: -2483 | V21: -1015 | W21: -3392 | X21: -652 | Y21: 806 | Z21: -4253 | AB21: -277 | AC21: -2192 | AD21: 23 | AE21: 2867 | AF21: 421 | AH21: 1063 | AI21: -2132
B22: Inventories | D22: -642 | E22: 146 | F22: 495 | G22: 398 | H22: 397 | J22: -926 | K22: -267 | L22: -624 | M22: -680 | N22: -2497 | P22: -1297 | Q22: -968 | R22: -261 | S22: 435 | T22: -2091 | V22: -1279 | W22: 297 | X22: 319 | Y22: 942 | Z22: 279 | AB22: -723 | AC22: 314 | AD22: 643 | AE22: 554 | AF22: 788 | AH22: -795 | AI22: 23
B23: Accounts payable | D23: 0 | E23: 0 | F23: 0 | G23: 0 | H23: 0 | J23: 0 | K23: 0 | L23: 0 | M23: 0 | N23: 0 | P23: 0 | Q23: 0 | R23: 0 | S23: 0 | T23: 0 | V23: 0 | W23: 0 | X23: 0 | Y23: 0 | Z23: 0 | AB23: 0 | AC23: 0 | AD23: 0 | AE23: 0 | AF23: 0 | AH23: 0 | AI23: 0
B24: Other | D24: -1187 | E24: 307 | F24: 312 | G24: 569 | H24: 1 | J24: -575 | K24: 947 | L24: 404 | M24: 1119 | N24: 1895 | P24: -1738 | Q24: 1156 | R24: 649 | S24: 1207 | T24: 1274 | V24: -1378 | W24: 969 | X24: -139 | Y24: 1355 | Z24: 807 | AB24: -2144 | AC24: 815 | AD24: 345 | AE24: -179 | AF24: -1163 | AH24: -2385 | AI24: 1340
B25: Cash provided by operating activities | D25: -508 | E25: 1284 | F25: 3281 | G25: 3426 | H25: 7483 | J25: 143 | K25: 1643 | L25: 2528 | M25: 3412 | N25: 7726 | P25: -2553 | Q25: 791 | R25: 2180 | S25: 4281 | T25: 4699 | V25: -1246 | W25: 1099 | X25: 3043 | Y25: 5693 | Z25: 8589 | AB25: -908 | AC25: 1852 | AD25: 3195 | AE25: 5092 | AF25: 9231 | AH25: -1132 | AI25: 1700
A27: x | B27: Investing activities:
B28: Purchase of fixed assets and intangibles | D28: -271 | E28: -169 | F28: -151 | G28: -225 | H28: -816 | J28: -154 | K28: -165 | L28: -172 | M28: -354 | N28: -845 | P28: -193 | Q28: -152 | R28: -251 | S28: -580 | T28: -1176 | V28: -315 | W28: -269 | X28: -303 | Y28: -613 | Z28: -1500 | AB28: -362 | AC28: -357 | AD28: -324 | AE28: -557 | AF28: -1600 | AH28: -352 | AI28: -203
B29: Disposal of fixed assets and intangibles | D29: 426 | E29: 472 | F29: 412 | G29: 473 | H29: 1783 | J29: 460 | K29: 551 | L29: 499 | M29: 584 | N29: 2094 | P29: 479 | Q29: 556 | R29: 466 | S29: 592 | T29: 2093 | V29: 497 | W29: 496 | X29: 452 | Y29: 536 | Z29: 1981 | AB29: 506 | AC29: 505 | AD29: 440 | AE29: 478 | AF29: 1929 | AH29: 433 | AI29: 568
B30: Acquisitions | D30: 0 | E30: 0 | F30: 0 | G30: -66 | H30: -66 | J30: -19 | K30: 0 | L30: 0 | M30: -225 | N30: -244 | P30: -24 | Q30: -449 | R30: -15 | S30: -10 | T30: -498 | V30: 0 | W30: -41 | X30: -41 | Y30: 0 | Z30: -82 | AB30: 0 | AC30: 0 | AD30: 0 | AE30: 0 | AF30: 0 | AH30: 0 | AI30: 0
B31: Divestitures | D31: 0 | E31: 0 | F31: 0 | G31: 0 | H31: 0 | J31: 0 | K31: 0 | L31: 0 | M31: 0 | N31: 0 | P31: 0 | Q31: 0 | R31: 0 | S31: 0 | T31: 0 | V31: 0 | W31: 0 | X31: 0 | Y31: 0 | Z31: 0 | AB31: 0 | AC31: 0 | AD31: 0 | AE31: 0 | AF31: 0 | AH31: 0 | AI31: 0
B32: Joint Ventures | D32: 0 | E32: 0 | F32: 0 | G32: 0 | H32: 0 | J32: 0 | K32: 0 | L32: 0 | M32: 0 | N32: 0 | P32: 0 | Q32: 0 | R32: 0 | S32: 0 | T32: 0 | V32: 0 | W32: 0 | X32: 0 | Y32: 0 | Z32: 0 | AB32: 0 | AC32: 0 | AD32: 0 | AE32: 0 | AF32: 0 | AH32: 0 | AI32: 0
B33: Increase in long-term investments | D33: -4303 | E33: -5064 | F33: -5082 | G33: -5516 | H33: -19965 | J33: -5300 | K33: -6059 | L33: -5802 | M33: -6492 | N33: -23653 | P33: -5603 | Q33: -6368 | R33: -6607 | S33: -7722 | T33: -26300 | V33: -6322 | W33: -7129 | X33: -7263 | Y33: -8058 | Z33: -28772 | AB33: -6447 | AC33: -7644 | AD33: -7022 | AE33: -7703 | AF33: -28816 | AH33: -6045 | AI33: -6699
B34: Decrease in long-term investments | D34: 5664 | E34: 3960 | F34: 3613 | G34: 4144 | H34: 17381 | J34: 5999 | K34: 4368 | L34: 4113 | M34: 4479 | N34: 18959 | P34: 6435 | Q34: 4755 | R34: 4584 | S34: 5133 | T34: 20907 | V34: 7198 | W34: 5395 | X34: 4999 | Y34: 5459 | Z34: 23051 | AB34: 7752 | AC34: 5951 | AD34: 5440 | AE34: 6019 | AF34: 25162 | AH34: 8137 | AI34: 6211
B35: Other investing inflows/(outflows) | D35: 27 | E35: 249 | F35: 15 | G35: -87 | H35: 204 | J35: -113 | K35: -190 | L35: 93 | M35: -116 | N35: -326 | P35: -55 | Q35: -264 | R35: -7 | S35: -573 | T35: -899 | V35: 199 | W35: 26 | X35: -174 | Y35: -510 | Z35: -459 | AB35: 222 | AC35: -427 | AD35: 261 | AE35: 7 | AF35: 63 | AH35: -318 | AI35: 301
B36: Cash provided by/(used in) investing activities | D36: 1026 | E36: -996 | F36: -1547 | G36: -1802 | H36: -3319 | J36: 579 | K36: -1966 | L36: -1715 | M36: -2648 | N36: -5750 | P36: 648 | Q36: -2536 | R36: -2542 | S36: -4055 | T36: -8485 | V36: 760 | W36: -2254 | X36: -3069 | Y36: -4186 | Z36: -8749 | AB36: 1217 | AC36: -2887 | AD36: -2001 | AE36: -2793 | AF36: -6464 | AH36: 1416 | AI36: -637
A38: x | B38: Financing activities:
B39: Payment of dividends | D39: -242 | E39: -239 | F39: -237 | G39: -238 | H39: -956 | J39: -242 | K39: -238 | L39: -281 | M39: -279 | N39: -1040 | P39: -327 | Q39: -322 | R39: -322 | S39: -342 | T39: -1313 | V39: -341 | W39: -356 | X39: -368 | Y39: -362 | Z39: -1427 | AB39: -386 | AC39: -410 | AD39: -406 | AE39: -403 | AF39: -1605 | AH39: -403 | AI39: -440
B40: Issuance (repurchase) of common shares | D40: -61 | E40: -132 | F40: 41 | G40: -267 | H40: -419 | J40: -281 | K40: -647 | L40: -716 | M40: -746 | N40: -2390 | P40: -612 | Q40: -564 | R40: -1246 | S40: -1112 | T40: -3534 | V40: -1236 | W40: -1280 | X40: -2147 | Y40: -2553 | Z40: -7216 | AB40: -1328 | AC40: -1094 | AD40: -805 | AE40: -780 | AF40: -4007 | AH40: -441 | AI40: -397
B41: Cash from (repayment) of short-term debt | D41: -473 | E41: 1611 | F41: -968 | G41: -1530 | H41: -1360 | J41: -695 | K41: 907 | L41: 717 | M41: -111 | N41: 818 | P41: -1018 | Q41: 1830 | R41: 3455 | S41: -415 | T41: 3852 | V41: 697 | W41: 3295 | X41: 1048 | Y41: -1032 | Z41: 4008 | AB41: -2951 | AC41: 3009 | AD41: -1050 | AE41: -864 | AF41: -1856 | AH41: -1484 | AI41: 2035
B42: Proceeds from issuance of long-term debt | D42: 1702 | E42: 5573 | F42: 1056 | G42: 940 | H42: 9271 | J42: 1757 | K42: 2210 | L42: 1910 | M42: 2845 | N42: 8722 | P42: 2353 | Q42: 1945 | R42: 1983 | S42: 4077 | T42: 10358 | V42: 2505 | W42: 2363 | X42: 5104 | Y42: 5457 | Z42: 15429 | AB42: 5287 | AC42: 4902 | AD42: 5323 | AE42: 2584 | AF42: 18096 | AH42: 3168 | AI42: 1988
B43: Repayments of long-term debt | D43: -1651 | E43: -1664 | F43: -2482 | G43: -1586 | H43: -7383 | J43: -1441 | K43: -1716 | L43: -2015 | M43: -1918 | N43: -7090 | P43: -1940 | Q43: -1685 | R43: -2953 | S43: -1867 | T43: -8445 | V43: -1925 | W43: -1642 | X43: -2295 | Y43: -2051 | Z43: -7913 | AB43: -3237 | AC43: -4902 | AD43: -2653 | AE43: -2440 | AF43: -13232 | AH43: -1753 | AI43: -3084
B44: Other financing inflows/(outflows) | D44: -38 | E44: -43 | F44: -29 | G44: -23 | H44: -133 | J44: -31 | K44: -24 | L44: -25 | M44: -18 | N44: -98 | P44: -33 | Q44: -13 | R44: -16 | S44: -30 | T44: -92 | V44: -39 | W44: -24 | X44: 20 | Y44: -30 | Z44: -73 | AB44: -30 | AC44: -22 | AD44: -36 | AE44: -25 | AF44: -113 | AH44: -10 | AI44: 0
B45: Cash provided by/(used in) financing activities | D45: -763 | E45: 5106 | F45: -2619 | G45: -2704 | H45: -980 | J45: -933 | K45: 492 | L45: -410 | M45: -227 | N45: -1078 | P45: -1577 | Q45: 1191 | R45: 901 | S45: 311 | T45: 826 | V45: -339 | W45: 2356 | X45: 1362 | Y45: -571 | Z45: 2808 | AB45: -2645 | AC45: 1483 | AD45: 373 | AE45: -1928 | AF45: -2717 | AH45: -923 | AI45: 102
A47: x | B47: Effects of foreign exchange | D47: -1 | E47: -101 | F47: 182 | G47: -48 | H47: 32 | J47: 103 | K47: 48 | L47: -45 | M47: -51 | N47: 55 | P47: -74 | Q47: -36 | R47: -33 | S47: -81 | T47: -224 | V47: 62 | W47: 8 | X47: 55 | Y47: -94 | Z47: 31 | AB47: 16 | AC47: -21 | AD47: -1 | AE47: -31 | AF47: -37 | AH47: -87 | AI47: 107
A49: x | B49: Increase/(Decrease) in cash and cash equivalents | D49: -246 | E49: 5293 | F49: -703 | G49: -1128 | H49: 3216 | J49: -108 | K49: 217 | L49: 358 | M49: 486 | N49: 953 | P49: -3556 | Q49: -590 | R49: 506 | S49: 456 | T49: -3184 | V49: -763 | W49: 1209 | X49: 1391 | Y49: 842 | Z49: 2679 | AB49: -2320 | AC49: 427 | AD49: 1566 | AE49: 340 | AF49: 13 | AH49: -726 | AI49: 1272
B50: Cash and cash equivalents, ending balances | D50: 3602 | E50: 8900 | F50: 8190 | G50: 7066 | H50: 7066 | J50: 6962 | K50: 7182 | L50: 7519 | M50: 8017 | N50: 8017 | P50: 4472 | Q50: 3878 | R50: 4359 | S50: 4774 | T50: 4774 | V50: 3976 | W50: 5267 | X50: 6576 | Y50: 7458 | Z50: 7458 | AB50: 5137 | AC50: 5553 | AD50: 7004 | AE50: 7324 | AF50: 7324 | AH50: 6601 | AI50: 7991

Sheet Error Check
B7: Income Statement – Sum of the Quarters = FY | D7: =F7 -> 2020 | E7: =F7 -> 2020 | F7: 2020 | G7: =F7 -> 2020 | H7: =F7 -> 2020 | J7: =L7 -> 2021 | K7: =L7 -> 2021 | L7: 2021 | M7: =L7 -> 2021 | N7: =L7 -> 2021 | P7: =R7 -> 2022 | Q7: =R7 -> 2022 | R7: 2022 | S7: =R7 -> 2022 | T7: =R7 -> 2022 | V7: =X7 -> 2023 | W7: =X7 -> 2023 | X7: 2023 | Y7: =X7 -> 2023 | Z7: =X7 -> 2023 | AB7: =AD7 -> 2024 | AC7: =AD7 -> 2024 | AD7: 2024 | AE7: =AD7 -> 2024 | AF7: =AD7 -> 2024 | AH7: =AJ7 -> 2025 | AI7: =AJ7 -> 2025 | AJ7: 2025 | AK7: =AJ7 -> 2025 | AL7: =AJ7 -> 2025 | AN7: =AP7 -> 2025 | AO7: =AP7 -> 2025 | AP7: 2025 | AQ7: =AP7 -> 2025 | AR7: =AP7 -> 2025
D8: 2020 | J8: =D8+1 -> 2021 | P8: =J8+1 -> 2022 | V8: =P8+1 -> 2023 | AB8: =V8+1 -> 2024 | AH8: =AB8+1 -> 2025 | AN8: =AH8+1 -> 2026 | AT8: =AN8+1 -> 2027 | AV8: =+AT8+1 -> 2028 | AX8: =+AV8+1 -> 2029
D9: Q1 | E9: Q2 | F9: Q3 | G9: Q4 | H9: FY | J9: Q1 | K9: Q2 | L9: Q3 | M9: Q4 | N9: FY | P9: Q1 | Q9: Q2 | R9: Q3 | S9: Q4 | T9: FY | V9: Q1 | W9: Q2 | X9: Q3 | Y9: Q4 | Z9: FY | AB9: Q1 | AC9: Q2 | AD9: Q3 | AE9: Q4 | AF9: FY | AH9: Q1 | AI9: Q2 | AJ9: Q3 | AK9: Q4 | AL9: FY | AN9: Q1 | AO9: Q2 | AP9: Q3 | AQ9: Q4 | AR9: FY | AT9: FY | AV9: FY | AX9: FY
A12: x | B12: Revenue:
B13: Segment 1 | H13: =IF(ROUND(SUM(IS!D13:G13),1)=ROUND(IS!H13,1),"OK","ERROR") -> OK | N13: =IF(ROUND(SUM(IS!J13:M13),1)=ROUND(IS!N13,1),"OK","ERROR") -> OK | T13: =IF(ROUND(SUM(IS!P13:S13),1)=ROUND(IS!T13,1),"OK","ERROR") -> OK | Z13: =IF(ROUND(SUM(IS!V13:Y13),1)=ROUND(IS!Z13,1),"OK","ERROR") -> OK | AF13: =IF(ROUND(SUM(IS!AB13:AE13),1)=ROUND(IS!AF13,1),"OK","ERROR") -> OK | AL13: =IF(ROUND(SUM(IS!AH13:AK13),1)=ROUND(IS!AL13,1),"OK","ERROR") -> OK | AR13: =IF(ROUND(SUM(IS!AN13:AQ13),1)=ROUND(IS!AR13,1),"OK","ERROR") -> OK
B14: Segment 2 | H14: =IF(ROUND(SUM(IS!D14:G14),1)=ROUND(IS!H14,1),"OK","ERROR") -> OK | N14: =IF(ROUND(SUM(IS!J14:M14),1)=ROUND(IS!N14,1),"OK","ERROR") -> OK | T14: =IF(ROUND(SUM(IS!P14:S14),1)=ROUND(IS!T14,1),"OK","ERROR") -> OK | Z14: =IF(ROUND(SUM(IS!V14:Y14),1)=ROUND(IS!Z14,1),"OK","ERROR") -> OK | AF14: =IF(ROUND(SUM(IS!AB14:AE14),1)=ROUND(IS!AF14,1),"OK","ERROR") -> OK | AL14: =IF(ROUND(SUM(IS!AH14:AK14),1)=ROUND(IS!AL14,1),"OK","ERROR") -> OK | AR14: =IF(ROUND(SUM(IS!AN14:AQ14),1)=ROUND(IS!AR14,1),"OK","ERROR") -> OK
B15: Segment 3 | H15: =IF(ROUND(SUM(IS!D15:G15),1)=ROUND(IS!H15,1),"OK","ERROR") -> OK | N15: =IF(ROUND(SUM(IS!J15:M15),1)=ROUND(IS!N15,1),"OK","ERROR") -> OK | T15: =IF(ROUND(SUM(IS!P15:S15),1)=ROUND(IS!T15,1),"OK","ERROR") -> OK | Z15: =IF(ROUND(SUM(IS!V15:Y15),1)=ROUND(IS!Z15,1),"OK","ERROR") -> OK | AF15: =IF(ROUND(SUM(IS!AB15:AE15),1)=ROUND(IS!AF15,1),"OK","ERROR") -> OK | AL15: =IF(ROUND(SUM(IS!AH15:AK15),1)=ROUND(IS!AL15,1),"OK","ERROR") -> OK | AR15: =IF(ROUND(SUM(IS!AN15:AQ15),1)=ROUND(IS!AR15,1),"OK","ERROR") -> OK
B16: Segment 4 | H16: =IF(ROUND(SUM(IS!D16:G16),1)=ROUND(IS!H16,1),"OK","ERROR") -> OK | N16: =IF(ROUND(SUM(IS!J16:M16),1)=ROUND(IS!N16,1),"OK","ERROR") -> OK | T16: =IF(ROUND(SUM(IS!P16:S16),1)=ROUND(IS!T16,1),"OK","ERROR") -> OK | Z16: =IF(ROUND(SUM(IS!V16:Y16),1)=ROUND(IS!Z16,1),"OK","ERROR") -> OK | AF16: =IF(ROUND(SUM(IS!AB16:AE16),1)=ROUND(IS!AF16,1),"OK","ERROR") -> OK | AL16: =IF(ROUND(SUM(IS!AH16:AK16),1)=ROUND(IS!AL16,1),"OK","ERROR") -> OK | AR16: =IF(ROUND(SUM(IS!AN16:AQ16),1)=ROUND(IS!AR16,1),"OK","ERROR") -> OK
B17: Segment 5 | H17: =IF(ROUND(SUM(IS!D17:G17),1)=ROUND(IS!H17,1),"OK","ERROR") -> OK | N17: =IF(ROUND(SUM(IS!J17:M17),1)=ROUND(IS!N17,1),"OK","ERROR") -> OK | T17: =IF(ROUND(SUM(IS!P17:S17),1)=ROUND(IS!T17,1),"OK","ERROR") -> OK | Z17: =IF(ROUND(SUM(IS!V17:Y17),1)=ROUND(IS!Z17,1),"OK","ERROR") -> OK | AF17: =IF(ROUND(SUM(IS!AB17:AE17),1)=ROUND(IS!AF17,1),"OK","ERROR") -> OK | AL17: =IF(ROUND(SUM(IS!AH17:AK17),1)=ROUND(IS!AL17,1),"OK","ERROR") -> OK | AR17: =IF(ROUND(SUM(IS!AN17:AQ17),1)=ROUND(IS!AR17,1),"OK","ERROR") -> OK
