Workbook
Name COOLFUCNTION: _xlfn.LAMBDA(_xldudf_BOARDFLARE_EXEC("workbook-settings:coolfucntion"))
Name COOLFUCNTION: _xlfn.LAMBDA(_xldudf_BOARDFLARE_EXEC("workbook-settings:coolfucntion"))
Name COOLFUCNTION: _xlfn.LAMBDA(_xldudf_BOARDFLARE_EXEC("workbook-settings:coolfucntion"))
Name COOLFUCNTION: _xlfn.LAMBDA(_xldudf_BOARDFLARE_EXEC("workbook-settings:coolfucntion"))
Name COOLFUCNTION: _xlfn.LAMBDA(_xldudf_BOARDFLARE_EXEC("workbook-settings:coolfucntion"))
Name COOLFUCNTION: _xlfn.LAMBDA(_xldudf_BOARDFLARE_EXEC("workbook-settings:coolfucntion"))
Name COOLFUCNTION: _xlfn.LAMBDA(_xldudf_BOARDFLARE_EXEC("workbook-settings:coolfucntion"))
Name COOLFUCNTION: _xlfn.LAMBDA(_xldudf_BOARDFLARE_EXEC("workbook-settings:coolfucntion"))
Name COOLFUCNTION: _xlfn.LAMBDA(_xldudf_BOARDFLARE_EXEC("workbook-settings:coolfucntion"))
Name COOLFUCNTION: _xlfn.LAMBDA(_xldudf_BOARDFLARE_EXEC("workbook-settings:coolfucntion"))
Name Sectors: #REF!
Name Sectors: #REF!
Name Sectors: #REF!
Name Sectors: #REF!
Name Sectors: #REF!
Name Sectors: #REF!
Name Sectors: #REF!
Name Sectors: #REF!

Sheet Dashboard
C154: =+C155+1 -> 45977
C155: =+C156+1 -> 45976
C156: =+C157+1 -> 45975
C157: =+C158+1 -> 45974
C158: =+C159+1 -> 45973
C159: =+C160+1 -> 45972
C160: =+C161+1 -> 45971 | L160: =IF(FCFF!$R$199="Revenue Exit",FCFF!$AF$211,IF(FCFF!$R$199="EBITDA Exit",FCFF!Z211,FCFF!AL211)) -> 271.50078
C161: =+C162+1 -> 45970
C162: =+C163+1 -> 45969 | E162: =IF(FCFF!$R$199="Revenue Exit",FCFF!$AF$211,IF(FCFF!$R$199="EBITDA Exit",FCFF!Z211,FCFF!AL211)) -> 271.50078
C163: =+C164+1 -> 45968 | E163: =E164+($E$162-$E$193)/COUNTA($C$162:$C$192) -> 270.00076
C164: =+C165+1 -> 45967 | E164: =E165+($E$162-$E$193)/COUNTA($C$162:$C$192) -> 268.50073
C165: =+C166+1 -> 45966 | E165: =E166+($E$162-$E$193)/COUNTA($C$162:$C$192) -> 267.00071
C166: =+C167+1 -> 45965 | E166: =E167+($E$162-$E$193)/COUNTA($C$162:$C$192) -> 265.50068
C167: =+C168+1 -> 45964 | E167: =E168+($E$162-$E$193)/COUNTA($C$162:$C$192) -> 264.00066
C168: =+C169+1 -> 45963 | E168: =E169+($E$162-$E$193)/COUNTA($C$162:$C$192) -> 262.50063
C169: =+C170+1 -> 45962 | E169: =E170+($E$162-$E$193)/COUNTA($C$162:$C$192) -> 261.00061
C170: =+C171+1 -> 45961 | E170: =E171+($E$162-$E$193)/COUNTA($C$162:$C$192) -> 259.50058
C171: =+C172+1 -> 45960 | E171: =E172+($E$162-$E$193)/COUNTA($C$162:$C$192) -> 258.00056
C172: =+C173+1 -> 45959 | E172: =E173+($E$162-$E$193)/COUNTA($C$162:$C$192) -> 256.50053
C173: =+C174+1 -> 45958 | E173: =E174+($E$162-$E$193)/COUNTA($C$162:$C$192) -> 255.0005
C174: =+C175+1 -> 45957 | E174: =E175+($E$162-$E$193)/COUNTA($C$162:$C$192) -> 253.50048
... C192: =+C193+1 -> 45939 | E192: =E193+($E$162-$E$193)/COUNTA($C$162:$C$192) -> 226.50003
B193: TODAY | C193: =+'Stock Data'!AM4 -> 45938 | D193: =_xlfn.XLOOKUP(C193,'Stock Data'!$AM$4:$AM$1051,'Stock Data'!$AN$4:$AN$1051) -> 225 | E193: =D193 -> 225
C194: =+'Stock Data'!AM5 -> 45937 | D194: =_xlfn.XLOOKUP(C194,'Stock Data'!$AM$4:$AM$1051,'Stock Data'!$AN$4:$AN$1051) -> 225
C195: =+'Stock Data'!AM6 -> 45936 | D195: =_xlfn.XLOOKUP(C195,'Stock Data'!$AM$4:$AM$1051,'Stock Data'!$AN$4:$AN$1051) -> 227.72
C196: =+'Stock Data'!AM7 -> 45935 | D196: =_xlfn.XLOOKUP(C196,'Stock Data'!$AM$4:$AM$1051,'Stock Data'!$AN$4:$AN$1051) -> 227.72
C197: =+'Stock Data'!AM8 -> 45934 | D197: =_xlfn.XLOOKUP(C197,'Stock Data'!$AM$4:$AM$1051,'Stock Data'!$AN$4:$AN$1051) -> 227.72
C198: =+'Stock Data'!AM9 -> 45933 | D198: =_xlfn.XLOOKUP(C198,'Stock Data'!$AM$4:$AM$1051,'Stock Data'!$AN$4:$AN$1051) -> 225.28
C199: =+'Stock Data'!AM10 -> 45932 | D199: =_xlfn.XLOOKUP(C199,'Stock Data'!$AM$4:$AM$1051,'Stock Data'!$AN$4:$AN$1051) -> 225.34
C200: =+'Stock Data'!AM11 -> 45931 | D200: =_xlfn.XLOOKUP(C200,'Stock Data'!$AM$4:$AM$1051,'Stock Data'!$AN$4:$AN$1051) -> 224.18
C201: =+'Stock Data'!AM12 -> 45930 | D201: =_xlfn.XLOOKUP(C201,'Stock Data'!$AM$4:$AM$1051,'Stock Data'!$AN$4:$AN$1051) -> 231.07
C202: =+'Stock Data'!AM13 -> 45929 | D202: =_xlfn.XLOOKUP(C202,'Stock Data'!$AM$4:$AM$1051,'Stock Data'!$AN$4:$AN$1051) -> 231.07
C203: =+'Stock Data'!AM14 -> 45928 | D203: =_xlfn.XLOOKUP(C203,'Stock Data'!$AM$4:$AM$1051,'Stock Data'!$AN$4:$AN$1051) -> 231.07
C204: =+'Stock Data'!AM15 -> 45927 | D204: =_xlfn.XLOOKUP(C204,'Stock Data'!$AM$4:$AM$1051,'Stock Data'!$AN$4:$AN$1051) -> 231.07
C205: =+'Stock Data'!AM16 -> 45926 | D205: =_xlfn.XLOOKUP(C205,'Stock Data'!$AM$4:$AM$1051,'Stock Data'!$AN$4:$AN$1051) -> 231.27
... C558: =+'Stock Data'!AM369 -> 45573 | D558: =_xlfn.XLOOKUP(C558,'Stock Data'!$AM$4:$AM$1051,'Stock Data'!$AN$4:$AN$1051) -> 283.3

Sheet Key Info
B7: Analysts | F7: LIS – Equity Research | J7: Stock Performance
B12: José Ricardo Godinho, Team Leader | F12: Recommendation: | H12: Hold
B13: Bsc in Economia, ISEG – Ulisboa | F13: Target Price (FCFF): | H13: =FCFF!AL211 -> 354.9833
B14: ze.ricardo.godinho@aln.iseg.ulisboa.pt | F14: Upside: | H14: =FCFF!AL213 -> 0.57770354
B15: Lucas Alves, Analyst
B16: Bsc in Gestão, ISEG – Ulisboa | F16: Ticker | H16: =Inputs!D15 -> FDX US Equity
B17: lucas.alves@aln.iseg.ulisboa.pt | F17: Stock Exchange | H17: NYSE
B18: Mariana Gomes, Analyst
B19: Bsc in MAEG, ISEG – Ulisboa | F19: Current Price | H19: ='Stock Data'!AN4 -> 225
B20: l63852@aln.iseg.ulisboa.pt | F20: ="Market Cap (in "&IF(Inputs!$D$14="BLN","billions",IF(Inputs!$D$14="MLN","millions","thousands"))&")" -> Market Cap (in millions) | H20: ='Stock Data'!AQ4 -> 53088.327
F21: Beta | H21: ='Stock Data'!E164 -> 0.96032262
F22: % of 52-Week High | H22: ='Stock Data'!E165 -> 0.42049286
F23: 100-Day Moving Average | H23: ='Stock Data'!E166 -> 228.79581
B25: Reviewed by: | F25: Avg Vol (1 month) | H25: ='Stock Data'!E168 -> 2225232.2
B26: Damião, Analyst | F26: Shares Outstanding (millions) | H26: ='Stock Data'!E169 -> 235.9555
B27: Bsc in Economia, ISEG – Ulisboa | F27: % Float | H27: ='Stock Data'!E170 -> 0.914445
B28: email@aln.iseg.ulisboa.pt | F28: Short % of Float | H28: =IFERROR('Stock Data'!E171,0) -> 0.02028042
B30: LISBON INVESTMENT SOCIETY | F30: % Held by Insiders | H30: ='Stock Data'!E173 -> 0.085517532
B31: ISEG – Rua do Quelhas, 6 | F31: % Held by Institutions | H31: ='Stock Data'!E174 -> 0.8870004
B32: lis@iseg.ulisboa.pt
B34: Disclaimer: This report was prepared by members of the Lisbon Investment Society (LIS), an independent, student-led, non-profit organization based at ISEG – Lisbon School of Economics & Management, and is intended solely for academic and educational purposes. All analyses, forecasts, and opinions expressed in this report reflect the independent judgment of the authors as of the date of publication and are subject to change without notice. The views presented herein do not represent those of ISEG, its faculty, or any affiliated entity. This document does not constitute, and should not be interpreted as, investment advice, an offer, or a solicitation to buy or sell any security or financial instrument. Nothing in this report should be construed as a recommendation to make or refrain from making any investment decision. The content is intended for informational purposes only, and readers are strongly encouraged to conduct their own research and seek advice from a qualified financial professional before making any financial decisions. The information contained in this report has been obtained from publicly available sources believed to be reliable; however, no representation or warranty is made regarding the accuracy, completeness, or timeliness of such information. LIS and its members accept no liability whatsoever for any direct or indirect loss arising from the use of this report or its contents. This report incorporates terminology, financial metrics, and methodologies commonly used in professional equity research, including but not limited to Discounted Cash Flow (DCF), trading multiples, Monte Carlo simulations, and strategic analysis tools such as Porter’s Five Forces. Definitions and assumptions used in these models are disclosed within the report and reflect a hypothetical investment thesis designed solely for academic discussion. All valuations, projections, and target prices presented herein are based on publicly available data and subject to the limitations of modeling assumptions. These are not guarantees of future performance and should not be relied upon as such, as past performance is not indicative of future results. Any company names, logos, trademarks, or brand references mentioned in this report are the property of their respective owners and are used strictly for identification and academic purposes. This document may not be reproduced, redistributed, or quoted in whole or in part without the prior written consent of the Lisbon Investment Society. About LIS – Lisbon Investment Society: The Lisbon Investment Society (LIS) is a non-profit academic association headquartered at ISEG – Lisbon School of Economics & Management. Founded in 2016, LIS is committed to fostering student interest in finance and investment through applied research, skill development, and institutional engagement. The Society operates independently and autonomously from any political, religious, or commercial affiliation, and is composed of selected students and collaborators who are invited through a rigorous recruitment process and share a commitment to excellence, analytical rigor, and ethical standards. Its activities include equity research, portfolio management, macroeconomic analysis, and investment education. This report was prepared by the Equity Research team at the Lisbon Investment Society, whose analysts combine rigorous financial modeling, critical thinking, and collaborative research to deliver high-quality, student-led investment analysis. We welcome your feedback, discussion, and questions regarding this report or our research process, and invite you to reach out to our team as we are always open to engagement.

Sheet Industry
D6: 584.17 | E6: 627.76 | F6: 676.06 | G6: 729.63 | H6: 789.13 | I6: 855.3 | J6: 929 | K6: 997.69 | L6: 1067.63 | M6: 1137.57
A7: x | B7: Industry Growth Forecast | O7: Industry Index
D9: 2022 | E9: =+D9+1 -> 2023 | F9: =+E9+1 -> 2024 | G9: =+F9+1 -> 2025 | H9: =+G9+1 -> 2026 | I9: =+H9+1 -> 2027 | J9: =+I9+1 -> 2028 | K9: =+J9+1 -> 2029 | M9: ="CAGR "&$G$9&" - "&$K$9 -> CAGR 2025 - 2029
B12: Global transportation and Logistics Market Size | D12: =C44 -> 1272945.2 | E12: =D44 -> 1337992.7 | F12: =E44 -> 1406364.1 | G12: =F44 -> 1478229.3 | H12: =G44 -> 1553766.8 | I12: =H44 -> 1633164.3 | J12: =I44 -> 1716619 | K12: =J44 -> 1804338.2 | M12: =(K12/G12)^(1/5)-1 -> 0.040675257
B13: FedEx Market Share | D13: =FCFF!D13 -> 0.069585087 | E13: =FCFF!E13 -> 0.064187198 | F13: =FCFF!F13 -> 0.059867143 | G13: =FCFF!G13 -> 0.057974468 | H13: =FCFF!H13 -> 0.056684884 | I13: =FCFF!J13 -> 0.055640595 | J13: =FCFF!K13 -> 0.054732614 | K13: =FCFF!L13 -> 0.05174646 | M13: =((K13*K12)/(G13*G12))^(1/5)-1 -> 0.017288193
B14: E-commerce Market Size | D14: 30830770 | E14: =D14*(1+0.189) -> 36657786 | F14: =E14*(1+0.189) -> 43586107 | G14: =F14*(1+0.189) -> 51823881 | H14: =G14*(1+0.189) -> 61618595 | I14: =H14*(1+0.189) -> 73264509 | J14: =I14*(1+0.189) -> 87111501 | K14: 83260000 | M14: =(K14/G14)^(1/5)-1 -> 0.09946471
B15: FedEx Market Share | D15: =FCFF!D15 -> 0.0025638672 | E15: =FCFF!E15 -> 0.0020800493 | F15: =FCFF!F15 -> 0.0017233244 | G15: =FCFF!G15 -> 0.0014801945 | H15: =FCFF!H15 -> 0.001282501 | I15: =FCFF!J15 -> 0.0011152217 | J15: =FCFF!K15 -> 0.00097147653 | K15: =FCFF!L15 -> 0.0010158129 | M15: =((K15*K14)/(G15*G14))^(1/5)-1 -> 0.019718461
B16: E-commerce in the U.S. Market Size | D16: =E16/(1+0.1071) -> 921190.52 | E16: =F16/(1+0.1071) -> 1019850 | F16: =G16/(1+0.1071) -> 1129076 | G16: 1250000 | H16: =G16*(1+0.1071) -> 1383875 | I16: =H16*(1.1071) -> 1532088 | J16: =I16*(1.1071) -> 1696174.6 | K16: 2080000 | M16: =(K16/G16)^(1/5)-1 -> 0.10721169
B17: FedEx Market Share | D17: =FCFF!D17 -> 0.057127162 | E17: =FCFF!E17 -> 0.05128205 | F17: =FCFF!F17 -> 0.046035875 | G17: =FCFF!G17 -> 0.042099852 | H17: =FCFF!H17 -> 0.038920613 | I17: =FCFF!J17 -> 0.036122108 | J17: =FCFF!K17 -> 0.033572922 | K17: =FCFF!L17 -> 0.027083178 | M17: =((K17*K16)/(G17*G16))^(1/5)-1 -> 0.013711737
B18: Global Express Delivery Service | D18: =E18/1.06 -> 227260.59 | E18: =F18/1.06 -> 240896.23 | F18: 255350 | G18: =F18*1.06 -> 270671 | H18: =G18*1.06 -> 286911.26 | I18: =H18*1.06 -> 304125.94 | J18: =I18*1.06 -> 322373.49 | K18: =J18*1.06 -> 341715.9 | M18: =(K18/G18)^(1/5)-1 -> 0.047718692
B19: FedEx Market Share | D19: =FCFF!D19 -> 0.20159236 | E19: =FCFF!E19 -> 0.17743325 | F19: =FCFF!F19 -> 0.16000392 | G19: =FCFF!G19 -> 0.15690974 | H19: =FCFF!H19 -> 0.154321 | I19: =FCFF!J19 -> 0.15213618 | J19: =FCFF!K19 -> 0.14995716 | K19: =FCFF!L19 -> 0.14477194 | M19: =((K19*K18)/(G19*G18))^(1/5)-1 -> 0.030983204
B20: US Express Delivery Service | D20: =E20/1.0501 -> 87330.304 | E20: =F20/1.0501 -> 91705.552 | F20: 96300 | G20: =F20*1.0501 -> 101124.63 | H20: =G20*1.0501 -> 106190.97 | I20: =H20*1.0501 -> 111511.14 | J20: =I20*1.0501 -> 117097.85 | K20: =J20*1.0501 -> 122964.45 | M20: =(K20/G20)^(1/5)-1 -> 0.039883116
B21: FedEx Market Share | D21: =FCFF!D21 -> 0.23187827 | E21: =FCFF!E21 -> 0.21430545 | F21: =FCFF!F21 -> 0.19279335 | G21: =FCFF!G21 -> 0.19023468 | H21: =FCFF!H21 -> 0.18818775 | I21: =FCFF!J21 -> 0.1865502 | J21: =FCFF!K21 -> 0.1843668 | K21: =FCFF!L21 -> 0.18 | M21: =((K21*K20)/(G21*G20))^(1/5)-1 -> 0.02844504
B22: US freight and logistics market | F22: 1405500 | G22: 1450500 | H22: =G22*1.042 -> 1511421 | I22: =H22*1.042 -> 1574900.7 | J22: =I22*1.042 -> 1641046.5 | K22: =J22*1.042 -> 1709970.5 | M22: =(K22/G22)^(1/5)-1 -> 0.033461197
B23: FedEx Market Share | F23: =FCFF!F23 -> 0.030834578 | G23: =FCFF!G23 -> 0.029802579 | H23: =FCFF!H23 -> 0.028978465 | I23: =FCFF!J23 -> 0.02832031 | J23: =FCFF!K23 -> 0.027794966 | K23: =FCFF!L23 -> 0.025671346 | M23: =((K23*K22)/(G23*G22))^(1/5)-1 -> 0.0030743649
B24: Rest of World freight and logistics market | D24: =E24/1.0415 -> 4363400.2 | E24: =F24/1.0415 -> 4544481.3 | F24: =G24/1.0415 -> 4733077.3 | G24: =6380000-G22 -> 4929500 | H24: =(G24+G22)*1.0499-H22 -> 5186941 | I24: =(H24+H22)*1.0499-I22 -> 5457709.6 | J24: =(I24+I22)*1.0499-J22 -> 5742491 | K24: =(J24+J22)*1.0499-K22 -> 6042005.6 | M24: =(K24/G24)^(1/5)-1 -> 0.041539272
B25: FedEx Market Share | D25: =FCFF!D25 -> 0.00025026354 | E25: =FCFF!E25 -> 0.00024733296 | F25: =FCFF!F25 -> 0.00023325205 | G25: =FCFF!G25 -> 0.00022460164 | H25: =FCFF!H25 -> 0.00021768131 | I25: =FCFF!J25 -> 0.00021214505 | J25: =FCFF!K25 -> 0.00020771604 | K25: =FCFF!L25 -> 0.00019 | M25: =((K25*K24)/(G25*G24))^(1/5)-1 -> 0.0072650949
A27: x
B29: Industry Driver | D29: Description | O29: Porter's Five Forces
B31: E-commerce expansion is transforming logistics | D31: As online shopping continues to grow, costumers changed their buying behavior: they demand faster deliveries and more flexible services. This shift means the companies in the industry need to expand its operations and integrate with retail networks. They can then benefit from increased parcel volume and faster and innovative services. Companies can also gain from partnerships in the last-mile delivery.
B32: Sustainability regulations are reshaping fleet strategies | D32: In a world where sustainability is a highly discussed issue, growing pressure from governments and stakeholders is leading to a cut in logistics firms' emissions. Efforts such as transitioning to electric vehicles and sustainable aviation fuel and investing in renewable energy will not only meet regulatory targets but also enhance the company's appeal to clients with ESG goals.
B33: Automation and AI are boosting supply chain efficiency | D33: Adopting automation and AI to simplify package sorting, routing and delivery can help managing labor shortages, improve operational efficiency and reduce costs. Companies such as FedEx Corporation are implementing technologies like robotic package sorting and autonomous delivery vehicles.
B34: Rising fuel and labor costs affect profitability | D34: Transport firm's margins are considerably affected by volatile fuel prices and rising labor costs, impacting operating costs. This represents a structural pressure in the industry, compelling companies to invest in fleet efficiency and route optimization to protect their profit margins.
B35: Geopolitical shifts are disrupting trade routes | D35: Big conflitcs such as wars and difficult relationships between countries are affecting global freight flows. As this means tensions, tariffs and supply chain disruptions, companies are exposed to higher risks, meaning they have to constantly adjust routes and strategies to stregthen service reliability.
O36: Rivalry Among Existing Competitors | R36: 5
O37: Threat of New Entrants | R37: 2
O38: Threat of Substitutes | R38: 3
O39: Bargaining Power of Customers | R39: 4
O40: Bargaining Power of Suppliers | R40: 3
B43: Global transportation and Logistics Market Size - 2021 | C43: 22 | D43: 2023
B44: 1211060 | C44: =B44*1.0511 -> 1272945.2 | D44: =C44*1.0511 -> 1337992.7 | E44: =D44*1.0511 -> 1406364.1 | F44: =E44*1.0511 -> 1478229.3 | G44: =F44*1.0511 -> 1553766.8 | H44: =G44*1.0511 -> 1633164.3 | I44: =H44*1.0511 -> 1716619 | J44: =I44*1.0511 -> 1804338.2 | K44: =J44*1.0511 -> 1896539.9
B47: US Express Delivery Service | C47: 22 | D47: 2023 | E47: 2024
B48: FedEx Express Segment - Total U.S. Domestic package revenue | C48: 16385 | D48: 16024 | E48: 15471

Sheet ESG
A7: x | B7: ESG Analysis
B12: ESG Scores | G12: GHG Scope 1 Emissions, Water Consumption, Energy Consumption and Waste Production per Sales
B15: LSEG ESG Score | D15: 70
B16: E-Score | D16: 71
B17: S-Score | D17: 64
B18: G-Score | D18: 78
B19: S&P Global ESG Score | D19: 31
B20: Environmental
B21: Social
B22: Governance & Economic
B23: Sustainalytics | D23: 19.4
B24: ISS ESG Corporate Rating | D24: D+
B25: SDG Impact Rating | D25: -0.7
B26: Governance Quality Score | D26: 5
B27: MSCI ESG Ratings
B30: Key Info | G30: Environmental
H32: Overview | I32: Targets | J32: Improvements | K32: Comments
B33: GICS Sector | C33: Industrials | G33: GHG Scope 1 Emissions | I33: FedEx Corporation set a goal of becoming carbon-neutral across their operations by 2040. Reducing in 40% aviation emissions intensity by 2034, considering the same 2005 baseline. By 2040, transform the entire PUD fleet to all electric vehichles. | J33: In 2006, the company launched the Fuel Sense program, resulting in over 9.6 million metric tons of avoided CO2 emissions. In 2011, met the goal of 20% reduction in aircraft CO2 emissions. Reduction of aviation emissions intensity by 30% from 2005 baseline. From FY23 to FY24, there was a 6.1% reduction in scope 1 emissions, being 4.9% of those just from jet fuel consiumption. From FY24 to FY25 scope 1 emissions reduced 4.9%. In 2024, the company prevented over 1.2 milion metric tons of CO2 emission through aircraft modernization initiatives. In FY24, the company continued adding EVs across international markets, also adding e-cargo bicycles and tricycles in Canada, Taiwan and UK. | K33: In 2022, FedEx launched FedEx Sustainability Insights for costumers and suppliers to calculate their estimated Co2 transportation emissions. In 2025, the company began using SAF (sustainable aviation fuel). However, in 2024, less than 1% of all jet fuel produced was SAF. FedEx is first focusing on decarbonizing their operations by using proven technologies that reduce emissions. The future change of new equipment will reduce their emissions per package-mile. Costumers can also forecast future emissions trough predictive modeling capabilities.
B34: GICS Industry Group | C34: Transportation
B35: GICS Industry | C35: Air Freight & Logistics | G35: Water Consumption
B36: GICS Sub-Industry | C36: Air Freight & Logistics
G37: Energy Consumption | I37: By 2040, the company aim to source 100% of their facility industry from renewable sources. By 2028, FedEx aims to source 500 gigawatt-hours (GWh) of energy from renewable sources and 1,300 GWh by 2033. In 2025, the company still plans to install an additional natural gas generator at their Lehigh Valley, Pennsylvania facility in 2025. | J37: In 2010, the company completed their first non-US on-site solar energy installation in Cologne, Germany. In 2011, FedEx opened one of the most energy efficient data centers in the US. Since FY17, the company reduced the energy consumption at participating FedEx Office stores by 47% through the implementation of energy management systems and LED lighting. In FY24, the company completed contracts to produce aproximately 8 additional Ws of renewable energy across the U.S. They also generated over 31 GWh of on- and off-site solar energy at 34 locations around the world. | K37: As part of the Fuel Sense program, the company is flying their fleet at higher altitudes where low air density requires aircraft to expend less energy to propel forward. With the transition to one FedEx and to accomodate the increasing volume of packages transported, PUD EVs will need to be larger, which means larger capacity batteries and higher energy usage to charge. FedEx manages energy usage and waste globally through ISO standards, energy systems, and employee-driven innovations to improve performance and savings.
B38: Headquarters | C38: Memphis, Tennessee, United States
B39: Numer of Employees | C39: 510.000 | G39: Waste Management | I39: The company aims to minimize their operational waste footprint. | J39: In 2021, the company introduced FedEx Reusable Pak, allowing customers to return items or prepare their own shipments without additional packaging. In FY23, FedEx Freight recycled over 1,700 tons of metal, 2,700 tons of paper, and 2,100 tons of wood-related waste. Meanwhile, FedEx Express recycled 42.5 million pounds of cardboard, wood pallets, paper, and metal waste, FedEx Office maintained its toner recycling program, preventing over 62,000 cartridges from being disposed of in landfills. Lastly, FedEx Ground facilities achieved a waste diversion rate of nearly 80% from recycling. In FY24, FedEx piloted a project that introduced mesh reusable bags into the small package sort systems, preventing 50 million plastic bags from entering landfills. | K39: FedEx earned the ISO 9001 global certification for 30 consecutive years, for their effective quality management system, by streamlining processes to improve resource management and reduce waste. Through the Supply Exchange Program, FedEx freight reduces waste via office and operations supplies reuse and sharing excess supplies across various locations and departments.
B41: Annual Report | C41: 2024 | G41: Other
B42: Sustainability Report | C42: 2024
B44: Recent Headlines | G44: Social
H46: Overview | I46: Targets | J46: Improvements | K46: Comments
B47: Concern over jobs as FedEx confirms closure plan - BBC News - 14/05/2025 | G47: Employee Turnover % | I47: The company is committed to compensating our employees fairly and respect the rights of team members to unionize. | J47: In FY24, they implemented a cohesive listening platform to analyze employee feedback across the enterprise. | K47: In FY24, the global turnover rate for all employees was 95%. Turnover for part-time team members, primarily package handlers at our sorting locations, was 195%, while full-time team member turnover was 26%. This number is so high due to many reasons: FedEx relies heavily on seasonal and part-time staff at hubs, the reoles are physically intense and low paid and hiring highly increases in peak season meaning inflating annual turnover stats when workers leave afterward.
B49: FedEx announces leadership for company split - 19/05/2025 | G49: Salaries & Compensation | I49: Maintain the comprehensive compensation package. | J49: As in January 2024, in the U.S., the company covered approximately 70% of the total eligible health, wellness and disability costs at the plan level for 215,000 participating team members. In 2024, they also launched a new plan option ("Your Choice"), designed for flexibility, simplicity, cost transparency, and increased access to quality providers. | K49: In FedEx's compensation plan, each executive officer has individual performance objectives established at the beginning of each fiscal year. "Our comprehensive benefits include health care coverage, well-being programs, basic and supplemental life and accidental death and dismemberment insurance, paid sick leave, paid time off, and parental leave for all eligible full- and part-time employees.(...)These health benefits include flexible medical, behavioral, dental, vision, and pharmacy coverage, in addition to mental health services. " - 2025 corporate responsability report. To help ensure the benefits and compensation packages remain competitive, they routinely conduct peer benchmarking and internal pay equity analyses. Workers often report burnout, feeling undervalued and unpredictable scheduling.
B50: FedEx closes 100 stations through Network 2.0 overhaul - Supply Chain Dive - 25/06/2025
B51: FedEx to implement single pricing structure for express, standard pickups. - Freight Waves - 03/07/2025 | G51: Reputation | I51: FedEx aims to be seen as a trusted, innovative and responsible global logistics leader, developing mutually rewarding relationships, valuing its people and communities and comitting to a sustainable, technology-drivn future. | J51: FedEx has been ranked among "World's Most Admired Companies" for 25 consecutive years. It remains the highest-ranked delivery company in that ranking. | K51: In 2024, FedEx was named among the World's Most Ethical Companies by Ethisphere. However, workers continue expressing frustration around workload and lack of recognition.
B52: FedEx executive Sriram Krishnasamy stepping down, company anounces - Action News 5 - 17/07/2025.
G53: Discrimination Events | I53: Fedex plans to align policies more closely with ADA (Americans with disabilities) standards. The company also suggests an ongoing focus in workforce diversity and inclusion in their goals. | J53: After the 2007's class action, FedEx eliminated the BST. After the sex discrimination case in 2012, FedEx comitted to provide anti-discrimination training, revice their policies and issue regret letters. The company also agreed to invest in ASL interpreters, acessible orientation and captioned training | K53: In 2007,there was a class action by African American and Latino employees alledging discrimination in promotions, pay, evaluations and discipline. They also revealed that the "Basic Skills Test" contruibuted to minorities being stuck in lower-paying roles, screening them out from promotions. In 2012, FedEx Freight allegedly hired a man over more qualified women for an HR position. The company faced accusations regarding failure in providing accommodations to deaf and hard-on-hearing workers. In 2024, EEOC accused FedEx of placing disabled transport workers on unpaid leave or firing them if they were not "100% healed". In 2025, EEOC also sued FedEx for disability discrimination, meaning it violated federal law by failing to accomodate several dispatchers' requests to continue working from home and demanded their immediate return to the office. It also forced one dispatcher into retirement.
G55: Work Safety | I55: FedEx Corporations plans to pilot AI capabilities within vehicles that can alert and validate operational safety in FY25. | J55: In 2020, FedEx Express launched an interactive program that encourages employee safety engagement and recognizes team members for working safely.From 2021 to 2024, FedEx reported a 74% improvement in distracted driving events since the implementation of the VEDR (video event data recorder) program. From 2023 to 2024, there was a 2.7% improvement in PUD preventable vehicle accident rate. | K55: Employees and managers use safety observations to reinforce proper lifting techniques to reduce injuries. FedEx also provides mandatory safety trainings for all new hires during onboarding. They aim to equip employees with the tools necessary to address their work- and responsibility-specific safety hazards. The Leading with Safety program teaches managers proper safety procedure execution, hazard recognition and reporting. We also provide a program to reduce risk of injury and discomfort as well as trainings to improve workplace efficiencies, reduce injury, and enhance employee morale.
G57: Damage to consumer health | I57: Continue to ensure timely delivery of medical products. | J57: In the past years, FedEx added additional facilities to their network in Asia to help supporting cold chain logistics in the region. Throughout the pandemic, the company came up with a monitoring and intervention solution to monitor vaccine transportation. | K57: Although there's no direct damage to consumer health, when it comes to delivering critical medical supplies and healthcare products, some incidents, such as late deliveris when the medicine expired and the costumer was charged can happen, which may lead to impacts on the costumer's health.
G59: Pension Plan | I59: In FY26, the company anticipates making up to 400 million dollars in voluntary contributions to its U.S. pension plan. FedEx is also commiting to ensure that healthcare and pension plans remain adequately funded and sustainable despite any volatility in the market. | J59: The Company sponsors defined benefit pension plans that provide retirement benefits to certain U.S. employees.
G61: Supply chain | I61: FedEx Corporation is in the process of making supply chains smarter and more efficient through AI and robotics technologies. | J61: In FY24, 74% of packaging materials were from third-party certified sources. With Pyxera Global, the company launched the Circular Supply Chain Coalition to transform supply chains and upcycle rare earth minerals from consumer electronic waste. Branded packaging is now 100% recyclable and 40% made from recycled content. | K61: "FedEx is consistently recognized as one of the most ethical companies in the world" - 2025 corporate responsability report. The company currently relies in 100000 direct suppliers to maintain their global operations. In 2025, FedEx established a partnership with Amazon for residential deliveries of select large packages, which means the companies renewed their relationship.
G63: Community involvement | I63: Continue ecouraging members to participate in community service programs (such as "Purple Toats" and "Community Engagement Fund") to maintain a high community involvement. | J63: FedEx has the FedEx Alert Line call center and web portal for reporting concerns accessible for team members and community members as well in which they received more than 18700 reports in FY2024. From FY2024 to FY2025, employee participation in community programs increased 20% in the Asia Pacific region. | K63: FedEx is involved with the community also through FedEx Cares, a global community engagement program that aims to connect people and possibilities. It includes volunteerism, charitable giving and strategic investments. Although the company shows a big community involvement, this varies by region.
G65: Public Sector | I65: Continue expand logistics for federal, state and local agencies and protect operational flexibility and costumer interests. | J65: The comapny provides shipping and logistics to multiple federal and state agencies. During the pandemic, it partnered with the U.S. Department of Health and Human Services to ship medical supplies. | K65: FedEx Corporation is a fully private company, publicly traded on the NYSE. There is no government ownership.
G67: Litigation | I67: FedEx Corporation aims to develop a better relationship with employees to prevent any problem related to employment classification. It also revealed a desire to stregthen its legal and compliance frameworks. | J67: FedEx successfully defended itself against a securities fraud claim related to a cyberattack. | K67: In 2016, FedEx faced a lawsuit that alleged that the company misclassified thousands of workers, denying them overtime pay, benefits and legal protections. In 2025, the company also faced a tax fraud investigation involving ilicit labor supply .
B70: Board of Directors | G70: Governance
B72: Name | C72: Position | E72: M/F – Age | H72: Overview | I72: Targets | J72: Improvements | K72: Comments
B73: Silvia Davila | C73: Director | E73: F - 54 | G73: Diversity (Gender, Age, Industry, Region) | I73: Continue creating a board with a diverse range of experiences and perspectives to effectively oversee the company's global operations. | J73: From FY24 to FY25, the percentage of female board nominees increased from 36% to 38% and the % of racially and ethnically diverse members increased form 29 to 31. | K73: 38% of board memebers are female and 31% of board membersare racially or ethnically diverse. The youngest member on the board is 50 years old and the average age is 62, meaning the board is not that diverse in terms of age. The directors also have experience in various industries.
B74: Marvin R. Ellison | C74: Director | E74: M - 60
B75: Stephen E. Gorman | C75: Director | E75: M - 70 | G75: % Independence | I75: FedEx aims for a board with a majority of independent directors who meet the applicable independence regulation laws. | J75: In the past 5 years, 5 new independent directors have joined the board. | K75: 11 out of the 12 board members are independent.
B76: Susan Patricia Griffith | C76: Director | E76: F - 60
B77: Amy B. Lane | C77: Director | E77: F - 72 | G77: Average time as independent directors | I77: The company aims to continue seeking directors with various backgrounds to provide oversight and strategic guidance. | J77: The board now includes directors with various lenghts of service, meaning a balanced institutional knowledge as well as new ideas. | K77: The average tenure within the 12 members is 6.6 years. Among these, the independent ones have na average tenure of 9 years.FedEx has actively refreshed its board.
B78: R. Brad Martin | C78: Chairman of the Board | E78: M - 73
B79: Nancy A. Norton | C79: Director | E79: F - 60 | G79: Departures of C-level executives | I79: Along with the plan to separate FedEx Freight from FedEx Corporation, the Chief Operating officer for U.S. and Canada, John A. Smith, has been selected to serve as President and CEO of the new company. | J79: Among the three recent departures, one of them was a strategic transition related to the new changes being made regarding the technology strategies. | K79: In June 2025, FedEx elected a new chairman of the board due to the passing of the last one. The company has also managed transitions smoothly with minimal disruption to operations.
B80: Frederick P. Perpall | C80: Director | E80: M - 50
B81: Joshua Cooper Ramo | C81: Director | E81: M - 56 | G81: CEO/Chairman duality | I81: While the Chairman of the board role is becoming more executive (the Chairman is being reelected also as Executive chairman), FedEx ensures that the CEO will continue to be focusing more on executing strategy while the chairman will focus on governance and public policy. | J81: In june 2022, Frederick W. Smith who had been both CEO and Chairman stepped down as CEO effective. After his passing, R. Brad Martin was elected the new Chairman to avoid a long period with both roles ambiguous. | K81: The combination of Chairman of the board and executive Chairman in the same person will mean he is no longer going to be independent, reducing the number of independent board memebers. This also means it is essential to clarify the role definition to avoid conflict with the CEO's duties.
B82: Susan C. Schwab | C82: Director | E82: F - 70
B83: Rajesh Subramaniam | C83: President and Chief Executive Officer | E83: M - 59 | G83: Transparency when reporting | I83: The company remains committed to delivering transparent and timely updates on their management of ESG matters that are aligned with the company’s strategic focus. | J83: In 2022, the company launched the FedEx Sustainability Insights, enabling tranparency for costumers to inform their emissions reporting. | K83: The company does not disclose information aboout water consumption. It also lacks governance transparency and employee-related financial transparency.
B84: Paul S. Walsh | C84: Director | E84: M - 70
G85: Time taken to report | I85: After the next fiscal year ends, FedEx Corporation aims to have the annual and esg reports published earlier to reduce information lag, despite the change in FY ending. | J85: The change of FY is na improvement in alignment as many companies in the industry use calendar year-end. The company also releases quarterly earnings reports on schedule. | K85: In January 2025, FedEx Board approved the change in the company's fiscal year end from may 31 to december 31. FedEx doesn't give a cliear timeline or goal for how quickly it will public their annual and ESG reports, introducing some uncertainty compared to its peers.
G87: CEO or Chairman in other boards? | I87: FedEx aims to continue positioning the CEO and Chairman in other boards to stregthen influence in logistics and sustainability, bring best practices to FedEx's board and exe cutive management and support its international expansion. | J87: The CEO's roles in other companies internationally reflect its active involvement in various sectors, including business, trade and technology. The Chairman roles also reveal his extensive experience in leadership and governance across the industries. Both can provide innovation and transfer of the best practices to FedEx. | K87: The CEO is part of the board in Procter & Gamble and FIRST. The Chairman of the board is also part of the board of WestRock Coffee Company. While overextension in other boards can be a concern, FedEx appears to maintain a good balance.
G89: Audit / Consulting | I89: FedEx plans to continue with the same auditor for the forseable future. | J89: FedEx Corporation has srengthened audit oversight and governance. | K89: FedEx maintains its external auditor, Ernst & Young, since 2002. Such a long time may require an assessement of auditor's independence.
G91: ESG-compensation related | I91: N/A | J91: N/A | K91: "The Compensation and Human Resources Committee reviews and discusses with our management team key human resource management strategies and programs." - 2025 corporate responsability report
G93: Management compensation schemes | I93: As vesting period is usually four years, FedEx aims to keep employees for longer periods. | J93: With the savings from their DRIVE initiatives, they were able to afford part of the rising expenses with labor, increasing salaries, compensations and pension plans. | K93: The stock-based compensation expense has been declining in the last 3 years. FedEx uses the Black-Scholes option pricing model to calculate the fair value of stock options.

Sheet Segments
A7: x | B7: Segments | D7: =F7 -> 2020 | E7: =F7 -> 2020 | F7: 2020 | G7: =F7 -> 2020 | H7: =F7 -> 2020 | J7: =L7 -> 2021 | K7: =L7 -> 2021 | L7: 2021 | M7: =L7 -> 2021 | N7: =L7 -> 2021 | P7: =R7 -> 2022 | Q7: =R7 -> 2022 | R7: 2022 | S7: =R7 -> 2022 | T7: =R7 -> 2022 | V7: =X7 -> 2023 | W7: =X7 -> 2023 | X7: 2023 | Y7: =X7 -> 2023 | Z7: =X7 -> 2023 | AB7: =AD7 -> 2024 | AC7: =AD7 -> 2024 | AD7: 2024 | AE7: =AD7 -> 2024 | AF7: =AD7 -> 2024 | AH7: =AJ7 -> 2025 | AI7: =AJ7 -> 2025 | AJ7: 2025 | AK7: =AJ7 -> 2025 | AL7: =AJ7 -> 2025 | AN7: =AP7 -> 2025 | AO7: =AP7 -> 2025 | AP7: 2025 | AQ7: =AP7 -> 2025 | AR7: =AP7 -> 2025 | AZ7: Products
D8: 2020 | J8: =D8+1 -> 2021 | P8: =J8+1 -> 2022 | V8: =P8+1 -> 2023 | AB8: =V8+1 -> 2024 | AH8: =AB8+1 -> 2025 | AN8: =AH8+1 -> 2026 | AT8: =AN8+1 -> 2027 | AV8: =+AT8+1 -> 2028 | AX8: =+AV8+1 -> 2029
D9: Q1 | E9: Q2 | F9: Q3 | G9: Q4 | H9: FY | J9: Q1 | K9: Q2 | L9: Q3 | M9: Q4 | N9: FY | P9: Q1 | Q9: Q2 | R9: Q3 | S9: Q4 | T9: FY | V9: Q1 | W9: Q2 | X9: Q3 | Y9: Q4 | Z9: FY | AB9: Q1 | AC9: Q2 | AD9: Q3 | AE9: Q4 | AF9: FY | AH9: Q1 | AI9: Q2 | AJ9: Q3 | AK9: Q4 | AL9: FY | AN9: Q1 | AO9: Q2 | AP9: Q3 | AQ9: Q4 | AR9: FY | AT9: FY | AV9: FY | AX9: FY
B12: Revenue by segment:
B13: FedEx Express | D13: =soma( | H13: 35513 | N13: 42078 | T13: 45814 | Z13: 42743 | AF13: 40857 | AL13: =FCFF!G29 -> 42470.916 | AR13: =FCFF!H29 -> 44276.432 | AT13: =FCFF!J29 -> 46268.558 | AV13: =FCFF!K29 -> 48342.212 | AX13: =FCFF!L29 -> 49470.874
B14: FedEx Ground | H14: 22733 | N14: 30496 | T14: 33232 | Z14: 33507 | AF14: 34256 | AL14: =FCFF!G30 -> 34238.509 | AR14: =FCFF!H30 -> 34749.475 | AT14: =FCFF!J30 -> 35437.614 | AV14: =FCFF!K30 -> 36284.567 | AX14: =FCFF!L30 -> 35105.71
B15: FedEx Freight | H15: 7102 | N15: 7833 | T15: 9532 | Z15: 9632 | AF15: 9082 | AL15: =FCFF!G31 -> 8990.1317 | AR15: =FCFF!H31 -> 9049.1849 | AT15: =FCFF!J31 -> 9164.0608 | AV15: =FCFF!K31 -> 9328.2652 | AX15: =FCFF!L31 -> 8791.5325
B16: FedEx Services | H16: 22 | N16: 32 | T16: 253 | Z16: 301 | AF16: 260 | AL16: =FCFF!G32 -> 267.8 | AR16: =FCFF!H32 -> 275.834 | AT16: =FCFF!J32 -> 284.10902 | AV16: =FCFF!K32 -> 292.63229 | AX16: =FCFF!L32 -> 301.41126
B17: Corporate, other and eliminations | H17: 3847 | N17: 3520 | T17: 4681 | Z17: 3972 | AF17: 3238 | AL17: =FCFF!G33 -> 3909.3207 | AR17: =FCFF!H33 -> 3823.6974 | AT17: =FCFF!J33 -> 3860.4761 | AV17: =FCFF!K33 -> 4122.2675 | AX17: =FCFF!L33 -> 4039.5437
B18: Total revenue | D18: =IS!D18 -> 17048 | E18: =IS!E18 -> 17324 | F18: =IS!F18 -> 17487 | G18: =IS!G18 -> 17358 | H18: =IS!H18 -> 69217 | J18: =IS!J18 -> 19321 | K18: =IS!K18 -> 20563 | L18: =IS!L18 -> 21510 | M18: =IS!M18 -> 22565 | N18: =IS!N18 -> 83959 | P18: =IS!P18 -> 22003 | Q18: =IS!Q18 -> 23474 | R18: =IS!R18 -> 23641 | S18: =IS!S18 -> 24394 | T18: =IS!T18 -> 93512 | V18: =IS!V18 -> 23242 | W18: =IS!W18 -> 22814 | X18: =IS!X18 -> 22169 | Y18: =IS!Y18 -> 21930 | Z18: =IS!Z18 -> 90155 | AB18: =IS!AB18 -> 21681 | AC18: =IS!AC18 -> 22165 | AD18: =IS!AD18 -> 21738 | AE18: =IS!AE18 -> 22109 | AF18: =IS!AF18 -> 87693 | AH18: =IS!AH18 -> 21579 | AI18: =IS!AI18 -> 21967 | AJ18: =IS!AJ18 -> 0 | AK18: =IS!AK18 -> 0 | AL18: =SUM(AL13:AL17) -> 89876.678 | AN18: =IS!AN18 -> 0 | AO18: =IS!AO18 -> 0 | AP18: =IS!AP18 -> 0 | AQ18: =IS!AQ18 -> 0 | AR18: =SUM(AR13:AR17) -> 92174.623 | AT18: =SUM(AT13:AT17) -> 95014.818 | AV18: =SUM(AV13:AV17) -> 98369.944 | AX18: =SUM(AX13:AX17) -> 97709.071
B20: Revenue by region:
B21: U.S. | H21: 48404 | N21: 58792 | T21: 64941 | Z21: 64890 | AF21: 63531 | AL21: =FCFF!G48 -> 64274.068 | AR21: =FCFF!H48 -> 65667.985 | AT21: =FCFF!J48 -> 67261.051 | AV21: =FCFF!K48 -> 69148.065 | AX21: =FCFF!L48 -> 67982.179
B22: International | H22: 20813 | N22: 25167 | T22: 28571 | Z22: 25265 | AF22: 24162 | AL22: =FCFF!G59 -> 24340.678 | AR22: =FCFF!H59 -> 25421.692 | AT22: =FCFF!J59 -> 26623.959 | AV22: =FCFF!K59 -> 27946.064 | AX22: =FCFF!L59 -> 28485.253
B26: Total revenue | D26: =IS!D18 -> 17048 | E26: =IS!E18 -> 17324 | F26: =IS!F18 -> 17487 | G26: =IS!G18 -> 17358 | H26: =IS!H18 -> 69217 | J26: =IS!J18 -> 19321 | K26: =IS!K18 -> 20563 | L26: =IS!L18 -> 21510 | M26: =IS!M18 -> 22565 | N26: =IS!N18 -> 83959 | P26: =IS!P18 -> 22003 | Q26: =IS!Q18 -> 23474 | R26: =IS!R18 -> 23641 | S26: =IS!S18 -> 24394 | T26: =IS!T18 -> 93512 | V26: =IS!V18 -> 23242 | W26: =IS!W18 -> 22814 | X26: =IS!X18 -> 22169 | Y26: =IS!Y18 -> 21930 | Z26: =IS!Z18 -> 90155 | AB26: =IS!AB18 -> 21681 | AC26: =IS!AC18 -> 22165 | AD26: =IS!AD18 -> 21738 | AE26: =IS!AE18 -> 22109 | AF26: =IS!AF18 -> 87693 | AH26: =IS!AH18 -> 21579 | AI26: =IS!AI18 -> 21967 | AJ26: =IS!AJ18 -> 0 | AK26: =IS!AK18 -> 0 | AL26: =SUM(AL21:AL22) -> 88614.746 | AN26: =IS!AN18 -> 0 | AO26: =IS!AO18 -> 0 | AP26: =IS!AP18 -> 0 | AQ26: =IS!AQ18 -> 0 | AR26: =SUM(AR21:AR22) -> 91089.677 | AT26: =SUM(AT21:AT22) -> 93885.01 | AV26: =SUM(AV21:AV22) -> 97094.129 | AX26: =SUM(AX21:AX22) -> 96467.432
B28: Products:
B29: Product 1
B30: Product 2
B31: Product 3
B32: Product 4
B33: Product 5
A35: x | B35: Notes & Forecasts
B40: Separating FedEx Freight from FedEx Corporation | H40: The dynamics, cost structures and investment needs within LTL market are different from parcel delivery. To compete more effectively in the market, FedEx believes to be crucial separating FedEx Freight, creating two independent industry-leading companies. This is intended to be tax-efficient for share-holders and allows better capital allocation as well as more operational agility and accountability. Although cooperation between the two is ensured, this change can lead to a range of different investor bases.
B41: Remotion of de minimis exemption | H41: The recent end of the de minimis exemption means parcels now face tariffs, increasing costs for costumers. As FedEx focused heavily on direct shippments from China to U.S. by air, the air freight demand fell sharply and is expected to continue weak, meaning an incertain future for global logistics providers. Although all this resulted in a reduction of demand for these shipments, product mix is possibly shifting from low-value cheap parcels toward high-value shipment, more lucrative than the first ones.
B42: Introduction of the "Easy Returns" program | H42: The continuous rapid growth of online shopping also came with an increase in returns. However, handling these is expensive and complex. To improve costumer experience and reduce costs to better compete in the industry, FedEx Corporation introduced a new "Easy Returns" program, with boxless returns for items under 10 pounds, QR-code based tracking and an expansion of the drop-off network. This ended up stretching FedEx's domestic retail logistics footprint and positions it to capture higher-margin services.
B43: Transforming FedEx's operating companies into a unified structure (One FedEx) | H43: FedEx always operated multiple entities, meaning redundancies in operation, overlapping networks and inefficiencies in some management and logistics. As peers operate more integrated, to remain competitive in the industry, FedEx rannounced, in 2023, the One FedEx consolidation plan, integrating all operating companies into a single organization. This will have a positive impact in financial gains, costumer experience and workforce structure.

Sheet Trading Comps
B7: in millions of USD | D7: Current | E7: % of | I7: Enterprise Value / | S7: LTM | T7: Net | V7: Price / | Z7: LT
D8: Share | E8: 52-week | F8: Equity | G8: Enterprise | I8: LTM | J8: 2025 | K8: 2026 | L8: LTM | M8: 2025E | N8: 2026E | O8: LTM | P8: 2025E | Q8: 2026E | S8: EBITDA | T8: Debt / | V8: LTM | W8: 2025E | X8: 2026E | Z8: EPS
B9: Company | C9: Ticker | D9: Price | E9: High | F9: Value | G9: Value | I9: Sales | J9: Sales | K9: Sales | L9: EBITDA | M9: EBITDA | N9: EBITDA | O9: EBIT | P9: EBIT | Q9: EBIT | S9: Margin | T9: EBITDA | V9: EPS | W9: EPS | X9: EPS | Z9: Growth
B12: Tier I: US Distribution Sector
B15: UNITED PARCEL-B | C15: UPS US | D15: USD 82,58 | E15: 0.56947797 | F15: 69992.301 | G15: 108237.03 | I15: 1.1984656 | J15: 1.2360011 | K15: 1.2331078 | L15: 7.6611711 | M15: 9.4897375 | N15: 8.9021693 | O15: 11.342034 | P15: 13.921531 | Q15: 12.673715 | S15: 0.15643374 | T15: 2.2265096 | V15: 10.593658 | W15: 12.795748 | X15: 11.741773 | Z15: 0.083500503
B16: DHL GROUP | C16: DHL GR | D16: EUR 37,85 | E16: 0.85440181 | F16: 45648 | G16: 69272 | I16: 0.82534463 | J16: 0.82475082 | K16: 0.80447903 | L16: 6.2177542 | M16: 6.4065946 | N16: 6.1294025 | O16: 10.941715 | P16: 11.553119 | Q16: 10.853427 | S16: 0.13273999 | T16: 2.3182551 | V16: 13.297212 | W16: 13.231479 | X16: 12.348581 | Z16: 0.083904073
B17: OLD DOMINION FRT | C17: ODFL UW | D17: USD 140,6 | E17: 0.6028384 | F17: 30157.026 | G17: 34325.628 | I17: 6.0875916 | J17: 6.1681776 | K17: 5.8103826 | L17: 19.200109 | M17: 19.957288 | N17: 18.144253 | O17: 23.96196 | P17: 25.291842 | Q17: 22.578599 | S17: 0.31706027 | T17: 0.095121227 | V17: 27.527026 | W17: 29.527552 | X17: 26.4314 | Z17: 0.13447901
B18: XPO INC | C18: XPO US | D18: USD 126,84 | E18: 0.78782609 | F18: 15316.725 | G18: 18844.22 | I18: 2.3531743 | J18: 2.332446 | K18: 2.2411806 | L18: 15.799631 | M18: 14.853385 | N18: 13.331174 | O18: 27.401803 | P18: 23.899986 | Q18: 21.015258 | S18: 0.14893856 | T18: 3.5373514 | V18: 42.251059 | W18: 35.914434 | X18: 28.930334 | Z18: 0.21415028
B19: HUNT (JB) TRANS | C19: JBHT US | D19: USD 134,2 | E19: 0.66966068 | F19: 13427.028 | G19: 15568.836 | I19: 1.2905104 | J19: 1.2990692 | K19: 1.2391452 | L19: 9.8336031 | M19: 10.158834 | N19: 9.2032527 | O19: 18.683664 | P19: 19.367235 | Q19: 16.6571 | S19: 0.13123474 | T19: 1.104247 | V19: 23.368823 | W19: 24.739918 | X19: 20.92771 | Z19: 0.17269073
F20: =SUM(F15:F19) -> 174541.08
B21: Mean | I21: 3.2437588 | J21: 3.2665643 | K21: 3.0969028 | L21: 14.944448 | M21: 14.989836 | N21: 13.55956 | O21: 23.349142 | P21: 22.853021 | Q21: 20.083652 | R21: #DIV/0! | S21: 0.19907786 | T21: 1.5789065 | U21: #DIV/0! | V21: 31.048969 | W21: 30.060635 | X21: 25.429815 | Y21: #DIV/0! | Z21: 0.17377334
B22: Median | I22: 1.2905104 | J22: 1.2990692 | K22: 1.2391452 | L22: 9.8336031 | M22: 10.158834 | N22: 9.2032527 | O22: 18.683664 | P22: 19.367235 | Q22: 16.6571 | S22: 0.14893856 | T22: 2.2265096 | V22: 23.368823 | W22: 24.739918 | X22: 20.92771 | Z22: 0.13447901
B24: Tier II: E-commerce
B27: AMAZON.COM INC | C27: AMZN US | D27: USD 218,15 | E27: 0.89951344 | F27: 2326550.6 | G27: 2397434.4 | I27: 3.5780574 | J27: 3.382659 | K27: 3.0640144 | L27: 16.23959 | M27: 14.407115 | N27: 12.172073 | O27: 31.466523 | P27: 29.960901 | Q27: 24.53865 | S27: 0.22032929 | T27: 1.0290458 | V27: 32.89614 | W27: 26.243134 | X27: 22.666832 | Z27: 0.18305782
B28: FSN E-COMMERCE V | C28: NYKAA IN | D28: INR 239,81 | E28: 0.96154771 | F28: 686163.34 | G28: #N/A N/A | S28: 0.062027959 | T28: #N/A N/A | V28: 860.28502 | W28: 809.15488 | X28: 298.78939 | Z28: 1.0278293
B29: SHOPIFY INC - A | C29: SHOP US | D29: USD 151,3 | E29: 0.93887682 | F29: 209195.07 | G29: 145090.54 | I29: 14.48877 | J29: 12.870042 | K29: 10.487759 | L29: 111.01036 | M29: 76.221855 | N29: 57.728971 | O29: 113.7965 | P29: 77.726775 | Q29: 58.619867 | S29: 0.13051728 | T29: 0.89403454 | V29: 144.43786 | W29: 109.16336 | X29: 85.482302 | Z29: 0.26643244
B30: ALIBABA GRP-ADR | C30: BABA US | D30: USD 189,34 | E30: 0.98271656 | F30: 451330.22 | G30: 1467142.5 | I30: 1.4660239 | J30: 1.4672228 | K30: 1.4104008 | L30: 8.9965692 | M30: 7.1966846 | N30: 8.5241546 | O30: 12.126748 | P30: 10.721424 | Q30: 12.372651 | S30: 0.16295367 | T30: 1.2752778 | V30: 3.9466945 | W30: 2.8871075 | X30: 3.5768905 | Z30: 0.077852734
B31: JD.COM INC-ADR | C31: JD US | D31: USD 35,98 | E31: 0.75240485 | F31: 51894.675 | G31: 227251.84 | I31: 0.17962939 | J31: 0.17157703 | K31: 0.16139142 | L31: 5.0577961 | M31: 8.8068453 | N31: 5.2489523 | O31: 6.339317 | P31: 23.065164 | Q31: 8.4645988 | S31: 0.035515348 | T31: 2.5652041 | V31: 1.2626419 | W31: 1.8579805 | X31: 1.337682 | Z31: 0.25958147
B33: Mean | I33: 4.9281202 | J33: 4.4728752 | K33: 3.7808915 | L33: 35.326079 | M33: 26.658125 | N33: 20.918538 | O33: 40.932273 | P33: 35.368566 | Q33: 25.998942 | S33: 0.12226871 | T33: 1.4408905 | V33: 208.56567 | W33: 189.86129 | X33: 82.370619 | Z33: 0.36295076
B34: Median | I34: 2.5220406 | J34: 2.4249409 | K34: 2.2372076 | L34: 12.618079 | M34: 11.60698 | N34: 10.348114 | O34: 21.796636 | P34: 26.513033 | Q34: 18.45565 | S34: 0.13051728 | T34: 1.1521618 | V34: 32.89614 | W34: 26.243134 | X34: 22.666832 | Z34: 0.25958147
B36: Tier III: Logistics International Sector
B39: AP MOLLER-B | C39: MAERSKB DC | D39: DKK 12610 | E39: 0.85260311 | F39: 201179.37 | G39: 27199.015 | I39: 0.47879689 | J39: 0.52026157 | K39: 0.55220043 | L39: 2.006863 | M39: 3.0128881 | N39: 4.5997519 | O39: 3.8346278 | P39: 9.5032335 | Q39: -72.882095 | S39: 0.23857975 | T39: 1.3079482 | V39: 29.140214 | W39: 77.979524 | X39: -247.77311 | Z39: -1.5484448
B40: KUEHNE & NAGEL-R | C40: KNIN SW | D40: CHF 152,6 | E40: 0.67283951 | F40: 18596.083 | G40: 23224.963 | I40: 0.90274665 | J40: 0.92618847 | K40: 0.91627693 | L40: 9.3535896 | M40: 10.023505 | N40: 9.7915062 | O40: 14.362995 | P40: 16.018321 | Q40: 15.54393 | S40: 0.096513391 | T40: 1.3700724 | V40: 16.148358 | W40: 18.053418 | X40: 17.797298 | Z40: 0.051829791
B41: DB SCHENKER | C41: 3001735Z GR | D41: EUR #N/A N/A | E41: #VALUE! | F41: #N/A N/A | G41: #N/A Field Not Applicable
B42: NIPPON EXPRESS H | C42: 9147 JT | D42: JPY 3290 | E42: 0.93732194 | F42: 855297 | G42: 1414876.5 | I42: 0.54423789 | J42: 0.54166504 | K42: 0.52807791 | L42: 5.5340814 | M42: 5.8111895 | N42: 5.1401502 | O42: 21.063486 | P42: 23.243393 | Q42: 15.829514 | S42: 0.098342949 | T42: 3.5195988 | V42: 24.278412 | W42: 24.771961 | X42: 15.034344 | Z42: 0.25512163
B43: EXPEDITORS INTL | C43: EXPD US | D43: USD 123,06 | E43: 0.95284553 | F43: 16953.958 | G43: 14871.376 | I43: 1.3191867 | J43: 1.3877502 | K43: 1.3848492 | L43: 12.649784 | M43: 14.20719 | N43: 14.446996 | O43: 13.322956 | P43: 15.050208 | Q43: 15.426739 | S43: 0.10428532 | T43: 0.49892695 | V43: 19.879855 | W43: 22.566339 | X43: 22.955346 | Z43: 0.024269636
B45: Mean | I45: 0.81124203 | J45: 0.84396633 | K45: 0.84535113 | L45: 7.3860794 | M45: 8.2636933 | N45: 8.4946011 | O45: 13.146016 | P45: 15.953789 | Q45: -6.520478 | S45: 0.13443035 | T45: 1.6741366 | V45: 22.36171 | W45: 35.842811 | X45: -47.99653 | Z45: -0.30430593
B46: Median | I46: 0.72349227 | J46: 0.73392675 | K46: 0.73423868 | L46: 7.4438355 | M46: 7.9173474 | N46: 7.4658282 | O46: 13.842976 | P46: 15.534265 | Q46: 15.485335 | S46: 0.10131413 | T46: 1.3390103 | V46: 22.079133 | W46: 23.66915 | X46: 16.415821 | Z46: 0.038049714
W47: 4
B48: Overall
B51: Mean | I51: 2.670195 | J51: 2.5482931 | K51: 2.2948666 | L51: 17.658531 | M51: 15.427163 | N51: 13.335601 | O51: 23.741872 | P51: 23.024856 | Q51: 12.437843 | S51: 0.14539088 | T51: 1.6724302 | V51: 89.236641 | W51: 86.349059 | X51: 22.874769 | Z51: 0.091875332
B52: Median | I52: 1.2905104 | J52: 1.2990692 | K52: 1.2391452 | L52: 9.3535896 | M52: 10.023505 | N52: 9.2032527 | O52: 14.362995 | P52: 19.367235 | Q52: 15.54393 | S52: 0.13198737 | T52: 1.3079482 | V52: 23.823617 | W52: 24.75594 | X52: 19.362504 | Z52: 0.15358487
B54: High | I54: 14.48877 | J54: 12.870042 | K54: 10.487759 | L54: 111.01036 | M54: 76.221855 | N54: 57.728971 | O54: 113.7965 | P54: 77.726775 | Q54: 58.619867 | R54: 0 | S54: 0.31706027 | T54: 3.5373514 | V54: 860.28502 | W54: 809.15488 | X54: 298.78939 | Z54: 1.0278293
B55: Low | I55: 0.17962939 | J55: 0.17157703 | K55: 0.16139142 | L55: 2.006863 | M55: 3.0128881 | N55: 4.5997519 | O55: 3.8346278 | P55: 9.5032335 | Q55: -72.882095 | R55: 0 | S55: 0.035515348 | T55: 0.095121227 | V55: 1.2626419 | W55: 1.8579805 | X55: -247.77311 | Z55: -1.5484448

Sheet Peers
B7: Peers
A12: x | B12: Growth | C12: FEDEX CORP | D12: UNITED PARCEL-B | E12: DHL GROUP | F12: OLD DOMINION FRT | G12: XPO INC | H12: HUNT (JB) TRANS | I12: AMAZON.COM INC | J12: FSN E-COMMERCE V | K12: SHOPIFY INC - A | L12: ALIBABA GRP-ADR | M12: JD.COM INC-ADR | N12: AP MOLLER-B | O12: KUEHNE & NAGEL-R | P12: DB SCHENKER | Q12: NIPPON EXPRESS H | R12: EXPEDITORS INTL
B14: Revenue (LTM) | C14: 0.0026569966 | D14: 0.00906125 | E14: 0.028112597 | F14: -0.055443441 | G14: -0.0011226144 | H14: -0.022369924 | I14: 0.10872134 | J14: 0.24571678 | K14: 0.28979907 | L14: 0.28979907 | M14: 0.053159807 | N14: 0.053159807 | O14: 0.053159807 | P14: 0.053159807 | Q14: 0.053159807 | R14: 0.053159807
B15: Revenue (3-yr CAGR) | C15: -0.020322072 | D15: -0.033711428 | E15: -0.023133083 | F15: -0.019136684 | G15: 0.020140491 | H15: -0.047669245 | I15: 0.11305575 | J15: 0.26744208 | K15: 0.26030292 | L15: 0.054746952 | M15: 0.080868358 | N15: -0.092705013 | O15: -0.13794412 | P15: #N/A | Q15: 0.024461922 | R15: -0.15946
B16: Gross profit (LTM) | C16: 0.0022688898 | D16: 0.064459035 | E16: 0.03322679 | F16: -0.10359638 | G16: 0.16045304 | H16: -0.022302274 | I16: 0.14480215 | J16: #N/A | K16: 0.24615385 | L16: 0.24615385 | M16: 0.14434733 | N16: 0.14434733 | O16: 0.14434733 | P16: 0.14434733 | Q16: 0.14434733 | R16: 0.14434733
B17: EBIT (LTM) | C17: -0.019387919 | D17: 0.16109016 | E17: 0.11480895 | F17: -0.13609541 | G17: 0.015805022 | H17: -0.048546306 | I17: 0.38822586 | J17: 0.72972616 | K17: 0.56826568 | L17: 0.56826568 | M17: -0.18767793 | N17: -0.18767793 | O17: -0.18767793 | P17: -0.18767793 | Q17: -0.18767793 | R17: -0.18767793
B18: EBITDA (LTM) | C18: -0.0035368847 | D18: 0.074536051 | E18: 0.082912131 | F18: -0.10431085 | G18: 0.04622807 | H18: -0.026082228 | I18: 0.27556681 | J18: 0.40581066 | K18: 0.52508751 | L18: 0.52508751 | M18: -0.10278883 | N18: -0.10278883 | O18: -0.10278883 | P18: -0.10278883 | Q18: -0.10278883 | R18: -0.10278883
B19: FCF (LTM) | C19: -0.04942602 | D19: 0.2230315 | E19: -0.055166052 | F19: 0.093787339 | G19: #VALUE! | H19: #VALUE! | I19: 0.020517118 | J19: #VALUE! | K19: 0.76464088 | L19: -0.48482453 | M19: 0.12074115 | N19: 0.16142558 | O19: -0.17241379 | P19: #VALUE! | Q19: 0.27967096 | R19: -0.32645183
A21: x | B21: Margins | C21: FEDEX CORP | D21: UNITED PARCEL-B | E21: DHL GROUP | F21: OLD DOMINION FRT | G21: XPO INC | H21: HUNT (JB) TRANS | I21: AMAZON.COM INC | J21: FSN E-COMMERCE V | K21: SHOPIFY INC - A | L21: ALIBABA GRP-ADR | M21: JD.COM INC-ADR | N21: AP MOLLER-B | O21: KUEHNE & NAGEL-R | P21: DB SCHENKER | Q21: NIPPON EXPRESS H | R21: EXPEDITORS INTL
B23: Gross margin | C23: 0.21603394 | D23: 0.20284397 | E23: 0.4920058 | F23: 0.34786915 | G23: 0.31020813 | H23: 0.12970601 | I23: 0.48854393 | J23: #VALUE! | K23: 0.5036036 | L23: 0.39952145 | M23: 0.15866844 | N23: #VALUE! | O23: 0.34956858 | P23: #VALUE! | Q23: 0.086005704 | R23: 0.32204067
B24: EBIT margin | C24: 0.059333985 | D24: 0.092983419 | E24: 0.073990925 | F24: 0.26552854 | G24: 0.081764123 | H24: 0.068769006 | I24: 0.10751945 | J24: 0.026102478 | K24: 0.12105856 | L24: 0.14142161 | M24: 0.033427136 | N24: 0.11171191 | O24: 0.06668817 | P24: #VALUE! | Q24: 0.018226729 | R24: 0.098233246
B25: EBITDA margin | C25: 0.10782931 | D25: 0.14376668 | E25: 0.13301402 | F25: 0.31694073 | G25: 0.1471029 | H25: 0.12906425 | I25: 0.22032929 | J25: 0.062027959 | K25: 0.12722189 | L25: 0.18185924 | M25: 0.031058046 | N25: 0.23808686 | O25: 0.09663 | P25: #VALUE! | Q25: 0.094991843 | R25: 0.10428532
B26: Net margin | C26: 0.046539135 | D26: 0.063489623 | E26: 0.039579027 | F26: 0.20397451 | G26: 0.047943508 | H26: 0.047230609 | I26: 0.092871172 | J26: 0.0083121379 | K26: 0.22736486 | L26: 0.12994469 | M26: 0.035690647 | N26: 0.11010778 | O26: 0.047617128 | P26: #VALUE! | Q26: 0.012310859 | R26: 0.076418268
B27: SG&A margin | C27: #VALUE! | D27: #VALUE! | E27: #VALUE! | F27: 0.036294565 | G27: #VALUE! | H27: 0.025345398 | I27: 0.086629392 | J27: #VALUE! | K27: 0.2018018 | L27: 0.18895024 | M27: 0.049050801 | N27: #VALUE! | O27: 0.054148859 | P27: #VALUE! | Q27: 0.054003211 | R27: 0.0031442812
B28: R&D margin | C28: #VALUE! | D28: 0 | E28: #VALUE! | F28: #VALUE! | G28: #VALUE! | H28: 0 | I28: 0.14323964 | J28: #VALUE! | K28: 0.14519672 | L28: 0.058734186 | M28: 0.014781265 | N28: #VALUE! | O28: 0 | P28: #VALUE! | Q28: 0 | R28: #VALUE!
A30: x | B30: Returns | C30: FEDEX CORP | D30: UNITED PARCEL-B | E30: DHL GROUP | F30: OLD DOMINION FRT | G30: XPO INC | H30: HUNT (JB) TRANS | I30: AMAZON.COM INC | J30: FSN E-COMMERCE V | K30: SHOPIFY INC - A | L30: ALIBABA GRP-ADR | M30: JD.COM INC-ADR | N30: AP MOLLER-B | O30: KUEHNE & NAGEL-R | P30: DB SCHENKER | Q30: NIPPON EXPRESS H | R30: EXPEDITORS INTL
B32: ROIC | C32: 0.054291712 | D32: 0.14724174 | E32: 0.09356161 | F32: 0.25371291 | G32: 0.086361161 | H32: 0.096352609 | I32: 0.14833321 | J32: #VALUE! | K32: 0.099553003 | L32: 0.088374937 | M32: 0.067412897 | N32: 0.090772011 | O32: 0.22803951 | P32: #VALUE! | Q32: 0.018477262 | R32: 0.29457345
B33: CROIC | C33: 0.04298362 | D33: 0.13502412 | E33: 0.10374797 | F33: 0.18483571 | G33: 0.0032934651 | H33: 0.087234765 | I33: 0.072775487 | J33: 0.10059969 | K33: 0.12555031 | L33: 0.055977452 | M33: 0.10500503 | N33: 0.10966099 | O33: 0.17655007 | P33: #VALUE! | Q33: 0.10055517 | R33: 0.24741963
B34: ROCE | C34: 0.08542656 | D34: 0.18289417 | E34: 0.21490426 | F34: 0.32289622 | G34: 0.14911884 | H34: 0.15101762 | I34: 0.17851603 | J34: 0.18507188 | K34: 0.17721728 | L34: 0.32520616 | M34: 0.20824127 | N34: 0.10794336 | O34: 0.72195548 | P34: #VALUE! | Q34: 0.040445484 | R34: 0.40512367
B35: RONA | C35: 0.18583031 | D35: 0.5057636 | E35: 0.25729038 | F35: 0.36375686 | G35: 0.41198502 | H35: 0.20705542 | I35: 0.23986082 | J35: 0.15455141 | K35: 0.093009171 | L35: 0.12925807 | M35: 0.12363987 | N35: 0.10695981 | O35: 0.50658499 | P35: #VALUE! | Q35: 0.053813765 | R35: 0.46784549
B36: ROE | C36: 0.14704614 | D36: 0.34960342 | E36: 0.16151163 | F36: 0.26251269 | G36: 0.21097561 | H36: 0.14328305 | I36: 0.24770353 | J36: #VALUE! | K36: 0.22022915 | L36: 0.15198773 | M36: 0.17258731 | N36: 0.12737132 | O36: 0.51315203 | P36: #VALUE! | Q36: 0.035152489 | R36: 0.39014862
B37: ROA | C37: 0.046863726 | D37: 0.081658247 | E37: 0.051111062 | F37: 0.20102638 | G37: 0.043626277 | H37: 0.066504597 | I37: 0.11418542 | J37: #VALUE! | K37: 0.18103215 | L37: 0.080596034 | M37: 0.056902269 | N37: 0.08163459 | O37: 0.10055915 | P37: #VALUE! | Q37: 0.012835159 | R37: 0.17813825
A39: x | B39: Efficiency | C39: FEDEX CORP | D39: UNITED PARCEL-B | E39: DHL GROUP | F39: OLD DOMINION FRT | G39: XPO INC | H39: HUNT (JB) TRANS | I39: AMAZON.COM INC | J39: FSN E-COMMERCE V | K39: SHOPIFY INC - A | L39: ALIBABA GRP-ADR | M39: JD.COM INC-ADR | N39: AP MOLLER-B | O39: KUEHNE & NAGEL-R | P39: DB SCHENKER | Q39: NIPPON EXPRESS H | R39: EXPEDITORS INTL
B41: Asset turnover | C41: 1.0069746 | D41: 1.2870508 | E41: 1.2437815 | F41: 1.0351611 | G41: 1.0097087 | H41: 1.44853 | I41: 1.0833379 | J41: #N/A N/A | K41: 0.77307291 | L41: 0.55105986 | M41: 1.8624147 | N41: 0.67384716 | O41: 2.2476848 | P41: #N/A Field Not Applicable | Q41: 1.1546841 | R41: 2.3547466
B42: Net operating asset turnover | C42: 1.9666286 | D42: 2.3902887 | E42: 2.0364296 | F42: 1.1151378 | G42: 2.4102717 | H42: 1.9793086 | I42: 1.6973585 | J42: 3.2557345 | K42: 1.2132805 | L42: 0.88326755 | M42: 3.0945494 | N42: 0.87975898 | O42: 3.0147077 | P42: #VALUE! | Q42: 2.0623124 | R42: 3.490225
B43: Fixed asset turnover | C43: 1.5068594 | D43: 2.178658 | E43: 2.7734783 | F43: 1.2716417 | G43: 1.8956089 | H43: 2.0828845 | I43: 1.9852007 | J43: #N/A N/A | K43: 69.783972 | L43: 4.8222919 | M43: 11.726025 | N43: 1.444809 | O43: 8.4907591 | P43: #N/A Field Not Applicable | Q43: 2.7234204 | R43: 11.086395
B44: Revenue per employee thsnd of USD | C44: 370.99578 | D44: 287.62102 | E44: 163.34833 | F44: 257.53012 | G44: 145.6 | H44: 358.55947 | I44: 430.61568 | J44: 495.79457 | K44: 1236.2963 | L44: 1115.3606 | M44: 307.04273 | N44: 315.31417 | O44: 394.80218 | P44: #VALUE! | Q44: 227.67239 | R44: 612.67065
B45: EBIT per employee thsnd of USD | C45: 25.822785 | D45: 30.39172 | E45: 12.321529 | F45: 65.426125 | G45: 12.503636 | H45: 24.766272 | I45: 48.965296 | J45: 13.997782 | K45: 157.40741 | L45: 134.8379 | M45: 8.7002903 | N45: 39.37056 | O45: 24.814208 | P45: #VALUE! | Q45: 5.8825943 | R45: 60.664239
A47: x | B47: Working Capital | C47: FEDEX CORP | D47: UNITED PARCEL-B | E47: DHL GROUP | F47: OLD DOMINION FRT | G47: XPO INC | H47: HUNT (JB) TRANS | I47: AMAZON.COM INC | J47: FSN E-COMMERCE V | K47: SHOPIFY INC - A | L47: ALIBABA GRP-ADR | M47: JD.COM INC-ADR | N47: AP MOLLER-B | O47: KUEHNE & NAGEL-R | P47: DB SCHENKER | Q47: NIPPON EXPRESS H | R47: EXPEDITORS INTL
B49: DSO | C49: 44.532192 | D49: 39.36017 | E49: 46.673607 | F49: 35.87995 | G49: 50.593157 | H49: 36.818005 | I49: 29.285776 | J49: #N/A N/A | K49: 47.966846 | L49: #N/A N/A | M49: 9.1784107 | N49: #N/A N/A | O49: 59.076457 | P49: #N/A Field Not Applicable | Q49: 68.722009 | R49: 62.310972
B50: DIO | C50: 3.2194513 | D50: #N/A N/A | E50: 9.3300538 | F50: #N/A N/A | G50: #N/A N/A | H50: #N/A N/A | I50: 40.501266 | J50: #N/A N/A | K50: #N/A N/A | L50: #N/A N/A | M50: 29.919077 | N50: #N/A N/A | O50: 2.9254407 | P50: #N/A Field Not Applicable | Q50: 1.876783 | R50: #N/A N/A
B51: DPO | C51: 18.221136 | D51: 28.873955 | E51: 67.002928 | F51: 9.6934484 | G51: 32.066589 | H51: #N/A N/A | I51: 95.445363 | J51: #N/A N/A | K51: #N/A N/A | L51: #N/A N/A | M51: 65.638087 | N51: #N/A N/A | O51: 45.803276 | P51: #N/A Field Not Applicable | Q51: 36.25702 | R51: 52.327678
B52: CCC | C52: 29.530507 | D52: #N/A N/A | E52: -16.396649 | F52: #N/A N/A | G52: #N/A N/A | H52: 16.137597 | I52: -31.539636 | J52: 74.810317 | K52: #N/A N/A | L52: #N/A N/A | M52: -29.161868 | N52: -890.84324 | O52: #N/A N/A | P52: #N/A Field Not Applicable | Q52: 34.446161 | R52: #N/A N/A
B53: Working capital intensity | C53: 0.044509019 | D53: 0.046217045 | E53: -0.019373056 | F53: 0.039516659 | G53: 0.0019355644 | H53: 0.0035592401 | I53: 0.014651408 | J53: #N/A N/A | K53: 0.57174955 | L53: 0.20146828 | M53: 0.044808179 | N53: 0.28927773 | O53: -0.035682357 | P53: #N/A Field Not Applicable | Q53: 0.067613133 | R53: 0.13621484
B54: Cash conversion ratio | C54: 1.3486678 | D54: 1.1953236 | E54: 1.293466 | F54: 1.0746665 | G54: 1.2242424 | H54: 1.7843015 | I54: 1.6893415 | J54: 1.7860826 | K54: 1.5032558 | L54: 1.1604201 | M54: 1.4997677 | N54: 2.0185544 | O54: 0.8923821 | P54: #VALUE! | Q54: 4.850049 | R54: 0.69465574
B55: CFO margin | C55: 0.080021837 | D55: 0.11114527 | E55: 0.095704749 | F55: 0.28535464 | G55: 0.10009911 | H55: 0.12270464 | I55: 0.18163706 | J55: 0.046621181 | K55: 0.18198198 | L55: 0.16410849 | M55: 0.050132937 | N55: 0.22549656 | O55: 0.05951133 | P55: #VALUE! | Q55: 0.088400527 | R55: 0.068238288
A57: x | B57: Leverage & Coverage | C57: FEDEX CORP | D57: UNITED PARCEL-B | E57: DHL GROUP | F57: OLD DOMINION FRT | G57: XPO INC | H57: HUNT (JB) TRANS | I57: AMAZON.COM INC | J57: FSN E-COMMERCE V | K57: SHOPIFY INC - A | L57: ALIBABA GRP-ADR | M57: JD.COM INC-ADR | N57: AP MOLLER-B | O57: KUEHNE & NAGEL-R | P57: DB SCHENKER | Q57: NIPPON EXPRESS H | R57: EXPEDITORS INTL
B59: Net debt / EBITDA | C59: 3.3661006 | D59: 1.7423752 | E59: 1.958617 | F59: 0.08165982 | G59: 3.3463497 | H59: 1.0715561 | I59: 0.39786898 | J59: #N/A N/A | K59: -3.6742543 | L59: -3.0196376 | M59: -4.4396569 | N59: -0.15977819 | O59: 1.1363636 | P59: #N/A Field Not Applicable | Q59: 2.7351572 | R59: -0.48451927
B60: Net debt / FCF | C60: 10.705803 | D60: 3.1118622 | E60: 3.8599883 | F60: 0.06713215 | G60: 203.73684 | H60: 3.417904 | I60: 1.4184561 | J60: 4.5332566 | K60: -2.7257358 | L60: -6.9231593 | M60: -4.5983603 | N60: 0.95824308 | O60: 1.0153061 | P60: #VALUE! | Q60: 3.1999577 | R60: -0.84842179
B61: Interest coverage | C61: 6.6121673 | D61: 9.778291 | E61: 7.0384181 | F61: 7283.0094 | G61: 2.9596413 | H61: 10.519172 | I61: 28.509144 | J61: 1.9734665 | K61: #DIV/0! | L61: 14.683722 | M61: 13.375691 | N61: 6.4227979 | O61: 44.702703 | P61: #VALUE! | Q61: 5.1919549 | R61: #DIV/0!
B62: Debt / capital | C62: 0.57132387 | D62: 0.60507135 | E62: 0.49939 | F62: 0.038135456 | G62: 0.7198811 | H62: 0.34966826 | I62: 0.34079132 | J62: 0.49585657 | K62: 0.088773258 | L62: 0.18540355 | M62: 0.22271346 | N62: 0.22139364 | O62: 0.41810729 | P62: #VALUE! | Q62: 0.4768957 | R62: 0.2035756
B63: Short term debt / total debt | C63: 0.10671905 | D63: 0.1002261 | E63: 0.22305495 | F63: 0.2121376 | G63: 0.045907214 | H63: 0.2770898 | I63: 0.11457136 | J63: 0.75635133 | K63: 0.8312611 | L63: 0.11058805 | M63: 0.16918055 | N63: 0.19481702 | O63: 0.32821824 | P63: #VALUE! | Q63: 0.32282734 | R63: 0.18760601
A65: x | B65: Liquidity | C65: FEDEX CORP | D65: UNITED PARCEL-B | E65: DHL GROUP | F65: OLD DOMINION FRT | G65: XPO INC | H65: HUNT (JB) TRANS | I65: AMAZON.COM INC | J65: FSN E-COMMERCE V | K65: SHOPIFY INC - A | L65: ALIBABA GRP-ADR | M65: JD.COM INC-ADR | N65: AP MOLLER-B | O65: KUEHNE & NAGEL-R | P65: DB SCHENKER | Q65: NIPPON EXPRESS H | R65: EXPEDITORS INTL
B67: Current ratio | C67: 1.1930439 | D67: 1.1745028 | E67: 0.95163195 | F67: 1.333292 | G67: 1.0605634 | H67: 1.0553878 | I67: 1.0637348 | J67: 1.2390504 | K67: 3.708589 | L67: 1.5483064 | M67: 1.2910547 | N67: 2.4471737 | O67: 0.9659356 | P67: #N/A Field Not Applicable | Q67: 1.2335661 | R67: 1.7710248
B68: Quick ratio | C68: 1.0946726 | D68: 1.045496 | E68: 0.7360068 | F68: 1.1289496 | G68: 0.86126761 | H68: 0.75752008 | I68: 0.87305427 | J68: 0.21464507 | K68: 3.4662577 | L68: 1.0549425 | M68: 0.86668714 | N68: 1.0058177 | O68: 0.8498989 | P68: #N/A Field Not Applicable | Q68: 0.98912983 | R68: 1.5224782
B69: Cash ratio | C69: 0.35701771 | D69: 0.38428319 | E69: 0.20707572 | F69: 0.20105489 | G69: 0.17323944 | H69: 0.027998737 | I69: 0.56401625 | J69: 0.10050495 | K69: 2.8011247 | L69: 0.98333969 | M69: 0.7812307 | N69: 0.58572147 | O69: 0.17918805 | P69: #N/A Field Not Applicable | Q69: 0.33164567 | R69: 0.55569078
A71: x | B71: Cash Deployment | C71: FEDEX CORP | D71: UNITED PARCEL-B | E71: DHL GROUP | F71: OLD DOMINION FRT | G71: XPO INC | H71: HUNT (JB) TRANS | I71: AMAZON.COM INC | J71: FSN E-COMMERCE V | K71: SHOPIFY INC - A | L71: ALIBABA GRP-ADR | M71: JD.COM INC-ADR | N71: AP MOLLER-B | O71: KUEHNE & NAGEL-R | P71: DB SCHENKER | Q71: NIPPON EXPRESS H | R71: EXPEDITORS INTL
B73: Capex intensity | C73: 0.046118327 | D73: 0.042923026 | E73: 0.034875157 | F73: 0.13264715 | G73: 0.097745292 | H73: 0.071594142 | I73: 0.13010084 | J73: 0.016002878 | K73: 0.0021396396 | L73: 0.086287207 | M73: 0.011925072 | N73: 0.075718251 | O73: 0.012257076 | P73: #VALUE! | Q73: 0.028318506 | R73: 0.0038173617
B74: Capex / depreciation | C74: 0.95098499 | D74: 1.0831255 | E74: 0.6220339 | F74: 2.2384424 | G74: 1.6102041 | H74: 1.1369418 | I74: 1.5720996 | J74: 0.47755255 | K74: 0.52777778 | L74: 2.0248239 | M74: 1.5519991 | N74: 0.67889463 | O74: 0.36893204 | P74: #VALUE! | Q74: 0.39792737 | R74: 0.66239974
B75: R&D capitalization rate | C75: #VALUE! | D75: #VALUE! | E75: #VALUE! | F75: #VALUE! | G75: #VALUE! | H75: #VALUE! | I75: #VALUE! | J75: #VALUE! | K75: #VALUE! | L75: #VALUE! | M75: #VALUE! | N75: #VALUE! | O75: #VALUE! | P75: #VALUE! | Q75: #VALUE! | R75: #VALUE!
B76: R&D capitalization test | C76: #VALUE! | D76: #VALUE! | E76: #VALUE! | F76: #VALUE! | G76: #VALUE! | H76: #VALUE! | I76: #VALUE! | J76: #VALUE! | K76: #VALUE! | L76: #VALUE! | M76: #VALUE! | N76: #VALUE! | O76: #VALUE! | P76: #VALUE! | Q76: #VALUE! | R76: #VALUE!
B77: Dividend payout | C77: 0.32722385 | D77: 0.9674853 | E77: 0.63985594 | F77: 0.18880713 | G77: 0 | H77: 0.30749221 | I77: 0 | J77: 0 | K77: 0 | L77: 0.13824383 | M77: 0.26167752 | N77: 0.39891963 | O77: 0.8277027 | P77: #VALUE! | Q77: 0.81990357 | R77: 0.25193655
B78: FCF payout | C78: 1.2797719 | D78: 0.94313826 | E78: 1.026362 | F78: 1.3532321 | G78: 0 | H78: 1.1161573 | I78: 0 | J78: -0.074195801 | K78: -0.038196619 | L78: 0.38418341 | M78: 0.24382782 | N78: #VALUE! | O78: 0.87670068 | P78: #VALUE! | Q78: 0.21481203 | R78: 1.4320436
B79: Buybacks as % CFO | C79: 0.42879477 | D79: 0.049397352 | E79: 0.15315874 | F79: 0.58295903 | G79: 0 | H79: 0.37102098 | I79: 0 | J79: 0 | K79: 0 | L79: 0.53001364 | M79: 0.44602806 | N79: 0.044440892 | O79: 0.034552846 | P79: #VALUE! | Q79: 0.047041011 | R79: 1.1820668
A81: x | B81: Earnings Quality | C81: FEDEX CORP | D81: UNITED PARCEL-B | E81: DHL GROUP | F81: OLD DOMINION FRT | G81: XPO INC | H81: HUNT (JB) TRANS | I81: AMAZON.COM INC | J81: FSN E-COMMERCE V | K81: SHOPIFY INC - A | L81: ALIBABA GRP-ADR | M81: JD.COM INC-ADR | N81: AP MOLLER-B | O81: KUEHNE & NAGEL-R | P81: DB SCHENKER | Q81: NIPPON EXPRESS H | R81: EXPEDITORS INTL
B83: Cash/earnings conversion | C83: 8.1291983 | D83: 8.9508684 | E83: 11.291509 | F83: 6.4117215 | G83: 6.6987788 | H83: 10.433739 | I83: 5.3351678 | J83: 7.264876 | K83: 3.6323422 | L83: 7.972563 | M83: 15.849298 | N83: 14.479034 | O83: 6.3166814 | P83: #VALUE! | Q83: 23.275281 | R83: 3.8746224
B84: FCF / net income | C84: 3.4441643 | D84: 5.4941459 | E84: 7.1768424 | F84: 3.4312316 | G84: 0.15752079 | H84: 4.3459937 | I84: 1.5137572 | J84: 4.7711828 | K84: 3.5896352 | L84: 3.7806397 | M84: 12.079241 | N84: 9.6171985 | O84: 5.0328031 | P84: #VALUE! | Q84: 17.383657 | R84: 3.6578696
A86: x | B86: Per Share & Dilution | C86: FEDEX CORP | D86: UNITED PARCEL-B | E86: DHL GROUP | F86: OLD DOMINION FRT | G86: XPO INC | H86: HUNT (JB) TRANS | I86: AMAZON.COM INC | J86: FSN E-COMMERCE V | K86: SHOPIFY INC - A | L86: ALIBABA GRP-ADR | M86: JD.COM INC-ADR | N86: AP MOLLER-B | O86: KUEHNE & NAGEL-R | P86: DB SCHENKER | Q86: NIPPON EXPRESS H | R86: EXPEDITORS INTL
B88: Diluted share count YoY | C88: 0.0082987552 | D88: 0.0011695906 | E88: 0.018598947 | F88: 0.0053825362 | G88: 0.034482759 | H88: 0.0079158779 | I88: 0.023679939 | J88: 0.0016124269 | K88: 0.0090694263 | L88: 0.028033723 | M88: 0.028885744 | N88: 0 | O88: 0.0022215065 | P88: #VALUE! | Q88: 0 | R88: 0.0051775987
B89: SBC / revenue | C89: 0.0017514728 | D89: 0.00026353355 | E89: #VALUE! | F89: 0.0019517405 | G89: 0.010777998 | H89: 0.005434342 | I89: 0.034502217 | J89: 0.0021258343 | K89: 0.048423423 | L89: 0.01402122 | M89: 0.0025879797 | N89: #VALUE! | O89: 0.00088702524 | P89: #VALUE! | Q89: #VALUE! | R89: 0.0060717805
B90: SBC / CFO | C90: 0.021887436 | D90: 0.0023710729 | E90: #VALUE! | F90: 0.0068397012 | G90: 0.10767327 | H90: 0.044287991 | I90: 0.18995141 | J90: 0.045598036 | K90: 0.26608911 | L90: 0.085438722 | M90: 0.051622343 | N90: #VALUE! | O90: 0.014905149 | P90: #VALUE! | Q90: #VALUE! | R90: 0.088979085
B91: EPS in USD | C91: 18.377593 | D91: 7.754017 | E91: 3.2411419 | F91: 5.149262 | G91: 3.103421 | H91: 5.734035 | I91: 6.687692 | J91: 0.0032917535 | K91: 1.11972 | L91: 6.8117313 | M91: 3.9314524 | N91: 458.67889 | O91: 11.225941 | P91: #N/A | Q91: 0.91519435 | R91: 6.15

Sheet WACC
A7: x | B7: Rolling WACC | K7: Equity Risk Premium
P8: Weights
D9: 2025 | E9: =+D9+1 -> 2026 | F9: =+E9+1 -> 2027 | G9: =+F9+1 -> 2028 | H9: =+G9+1 -> 2029 | M9: ERP | N9: 2025 | O9: =+N9+1 -> 2026 | P9: =+O9+1 -> 2027 | Q9: =+P9+1 -> 2028 | R9: =+Q9+1 -> 2029
B12: Equity: | K12: =+Segments!B21 -> U.S. | M12: =7.5%-D15 -> 0.035 | N12: =+Segments!AL21/Segments!AL$26 -> 0.72532023 | O12: =+Segments!AR21/Segments!AR$26 -> 0.72091578 | P12: =+Segments!AT21/Segments!AT$26 -> 0.71641949 | Q12: =+Segments!AV21/Segments!AV$26 -> 0.71217555 | R12: =+Segments!AX21/Segments!AX$26 -> 0.70471637
B13: Market Cap (in billions) | D13: =+Inputs!J13 -> 53088.327 | E13: =+FCFF!AF140*FCFF!AF71 -> 36869.849 | F13: =+FCFF!AH140*FCFF!AH71 -> 38005.927 | G13: =+FCFF!AJ140*FCFF!AJ71 -> 39347.978 | H13: =+FCFF!AL140*FCFF!AL71 -> 39083.628 | K13: =+Segments!B22 -> International | M13: =6.6%-2.5% -> 0.041 | N13: =+Segments!AL22/Segments!AL$26 -> 0.27467977 | O13: =+Segments!AR22/Segments!AR$26 -> 0.27908422 | P13: =+Segments!AT22/Segments!AT$26 -> 0.28358051 | Q13: =+Segments!AV22/Segments!AV$26 -> 0.28782445 | R13: =+Segments!AX22/Segments!AX$26 -> 0.29528363
B14: % of Equity | D14: =IFERROR(D13/D35,"") -> 0.58750509 | E14: =IFERROR(E13/E35,"") -> 0.50881363 | F14: =IFERROR(E13/F35,"") -> 0.49544805 | G14: =IFERROR(F13/G35,"") -> 0.4999806 | H14: =IFERROR(G13/H35,"") -> 0.51595956 | K14: =+Segments!B23 -> 0 | N14: =+Segments!AL23/Segments!AL$26 -> 0 | O14: =+Segments!AR23/Segments!AR$26 -> 0 | P14: =+Segments!AT23/Segments!AT$26 -> 0 | Q14: =+Segments!AV23/Segments!AV$26 -> 0 | R14: =+Segments!AX23/Segments!AX$26 -> 0
B15: Risk-Free Rate | D15: 0.04 | E15: 0.035 | F15: 0.0325 | G15: 0.0325 | H15: 0.0325 | K15: =+Segments!B24 -> 0 | N15: =+Segments!AL24/Segments!AL$26 -> 0 | O15: =+Segments!AR24/Segments!AR$26 -> 0 | P15: =+Segments!AT24/Segments!AT$26 -> 0 | Q15: =+Segments!AV24/Segments!AV$26 -> 0 | R15: =+Segments!AX24/Segments!AX$26 -> 0
B16: Beta | D16: =+Inputs!M18 -> 1.29 | E16: =+D17*(1+(E28/E13)*(1-E32)) -> 1.4551681 | F16: =+E17*(1+(F28/F13)*(1-F32)) -> 1.4497259 | G16: =+F17*(1+(G28/G13)*(1-G32)) -> 1.4363059 | H16: =+G17*(1+(H28/H13)*(1-H32)) -> 1.4518457 | K16: =+Segments!B25 -> 0 | N16: =+Segments!AL25/Segments!AL$26 -> 0 | O16: =+Segments!AR25/Segments!AR$26 -> 0 | P16: =+Segments!AT25/Segments!AT$26 -> 0 | Q16: =+Segments!AV25/Segments!AV$26 -> 0 | R16: =+Segments!AX25/Segments!AX$26 -> 0
B17: Unlevered Beta | D17: =+D16/(1+(D28/D13)*(1-D32)) -> 0.84358429 | E17: =+E16/(1+(E28/E13)*(1-E32)) -> 0.84358429 | F17: =+F16/(1+(F28/F13)*(1-F32)) -> 0.84358429 | G17: =+G16/(1+(G28/G13)*(1-G32)) -> 0.84358429 | H17: =+H16/(1+(H28/H13)*(1-H32)) -> 0.84358429
B18: Equity Risk Premium | D18: =+N18 -> 0.036648079 | E18: =+O18 -> 0.036674505 | F18: =+P18 -> 0.036701483 | G18: =+Q18 -> 0.036726947 | H18: =+R18 -> 0.036771702 | K18: ERP | N18: =+SUMPRODUCT($M12:$M16,N12:N16) -> 0.036648079 | O18: =+SUMPRODUCT($M12:$M16,O12:O16) -> 0.036674505 | P18: =+SUMPRODUCT($M12:$M16,P12:P16) -> 0.036701483 | Q18: =+SUMPRODUCT($M12:$M16,Q12:Q16) -> 0.036726947 | R18: =+SUMPRODUCT($M12:$M16,R12:R16) -> 0.036771702
B19: Ke (Cost of Equity) | D19: =IFERROR(+D15+D16*D18,"") -> 0.087276021 | E19: =IFERROR(+E15+E16*E18,"") -> 0.088367571 | F19: =IFERROR(+F15+F16*F18,"") -> 0.085707091 | G19: =IFERROR(+G15+G16*G18,"") -> 0.085251129 | H19: =IFERROR(+H15+H16*H18,"") -> 0.085886836
B21: Preferred Equity: | K21: ROIC vs WACC
B22: Market Capitalization | D22: =IFERROR(Inputs!J14,0) -> 58288.077 | E22: =+D22*(E13/D13) -> 40481.077 | F22: =+E22*(F13/E13) -> 41728.428 | G22: =+F22*(G13/F13) -> 43201.926 | H22: =+G22*(H13/G13) -> 42911.685
B23: % of Preferred Equity | D23: =+D22/D35 -> 0.64504843 | E23: =+E22/E35 -> 0.55864951 | F23: =+F22/F35 -> 0.56073644 | G23: =+G22/G35 -> 0.56833569 | H23: =+H22/H35 -> 0.5626895
B24: Preferred Dividends | D24: =+IS!AF50 -> 0 | E24: =D24 -> 0 | F24: =E24 -> 0 | G24: =F24 -> 0 | H24: =G24 -> 0
B25: Kp (Cost of Preferred Equity) | D25: =IFERROR(D24/D22,0) -> 0 | E25: =IFERROR(E24/E22,0) -> 0 | F25: =IFERROR(F24/F22,0) -> 0 | G25: =IFERROR(G24/G22,0) -> 0 | H25: =IFERROR(H24/H22,0) -> 0
B27: Debt:
B28: Debt (in millions) | C28: =+BS!AF38+BS!AF39+BS!AF44+BS!AF45 -> 37719 | D28: =+BS!AI38+BS!AI39+BS!AI44+BS!AI45 -> 37274 | E28: =Debt!AJ21 -> 35592.536 | F28: =Debt!AR21 -> 36411.259 | G28: =Debt!AT21 -> 36666.826 | H28: =Debt!AV21 -> 37178.119
B29: % of Debt | D29: =IFERROR(D28/D35,"") -> 0.41249491 | E29: =IFERROR(E28/E35,"") -> 0.49118637 | F29: =IFERROR(F28/F35,"") -> 0.48928562 | G29: =IFERROR(G28/G35,"") -> 0.48236428 | H29: =IFERROR(H28/H35,"") -> 0.48750678
B30: Debt Spread | D30: =+D31-D15 -> -0.020066534 | E30: =Debt!AP13-E15 -> 0.0012251298 | F30: =Debt!AR13-F15 -> 0.0040439668 | G30: =Debt!AT13-G15 -> 0.0043517898 | H30: =Debt!AV13-H15 -> 0.0041123418
B31: Cost of Debt | D31: =SUM(IS!AD36:AE36,IS!AH36:AI36)/WACC!D28 -> 0.019933466 | E31: =+E30+E15 -> 0.03622513 | F31: =+F30+F15 -> 0.036543967 | G31: =+G30+G15 -> 0.03685179 | H31: =+H30+H15 -> 0.036612342
B32: Tax Rate | D32: =+FCFF!Z166 -> 0.24629045 | E32: =+FCFF!AF166 -> 0.249 | F32: =+FCFF!AH166 -> 0.25 | G32: =+FCFF!AJ166 -> 0.246 | H32: =+FCFF!AL166 -> 0.242
B33: Kd (After-Tax Cost of Debt) | D33: =+D31*(1-D32) -> 0.015024044 | E33: =+E31*(1-E32) -> 0.027205073 | F33: =+F31*(1-F32) -> 0.027407975 | G33: =+G31*(1-G32) -> 0.02778625 | H33: =+H31*(1-H32) -> 0.027752155
B35: Total | D35: =+D13+D24+D28 -> 90362.327 | E35: =+E13+E24+E28 -> 72462.386 | F35: =+F13+F24+F28 -> 74417.186 | G35: =+G13+G24+G28 -> 76014.804 | H35: =+H13+H24+H28 -> 76261.748
B37: Country/Conglomerate/... Risk Premium | D37: 0.005 | E37: 0.005 | F37: 0.0025 | G37: 0.0025 | H37: 0.0025
A39: x | B39: WACC | D39: =+D19*D14+D25*D23+D33*D29+D37 -> 0.062472448 | E39: =+E19*E14+E25*E23+E33*E29+E37 -> 0.063325385 | F39: =+F19*F14+F25*F23+F33*F29+F37 -> 0.058373739 | G39: =+G19*G14+G25*G23+G33*G29+G37 -> 0.058527005 | H39: =+H19*H14+H25*H23+H33*H29+H37 -> 0.060343498
B41: NOPAT | D41: =+FCFF!Z168 -> 2971.514 | E41: =+FCFF!AF168 -> 2057.1601 | F41: =+FCFF!AH168 -> 2454.1302 | G41: =+FCFF!AJ168 -> 3228.6793 | H41: =+FCFF!AL168 -> 4039.7971
B42: Total Payout | D42: =+FCFF!Z153+FCFF!Z156 -> -3252.8088 | E42: =+FCFF!AF153+FCFF!AF156 -> -2375.5894 | F42: =+FCFF!AH153+FCFF!AH156 -> -2820.1737 | G42: =+FCFF!AJ153+FCFF!AJ156 -> -2822.0848 | H42: =+FCFF!AL153+FCFF!AL156 -> -3109.5382
B43: Book Value of Equity | C43: =+BS!AF54 -> 27582 | D43: =+C43+D41+D42 -> 27300.705 | E43: =+D43+E41+E42 -> 26982.276 | F43: =+E43+F41+F42 -> 26616.232 | G43: =+F43+G41+G42 -> 27022.827 | H43: =+G43+H41+H42 -> 27953.086
B44: Invested Capital | C44: =+C43+C28 -> 65301 | D44: =+D43+D28 -> 64574.705 | E44: =+E43+E28 -> 62574.812 | F44: =+F43+F28 -> 63027.491 | G44: =+G43+G28 -> 63689.653 | H44: =+H43+H28 -> 65131.205
A45: x | B45: ROIC | D45: =+D41/((D44+C44)/2) -> 0.045759351 | E45: =+E41/((E44+D44)/2) -> 0.032358127 | F45: =+F41/((F44+E44)/2) -> 0.03907779 | G45: =+G41/((G44+F44)/2) -> 0.05095884 | H45: =+H41/((H44+G44)/2) -> 0.062719611
W49: ,

Sheet Debt
B7: DATA | AH7: Prediction
B8: =IS!D8 -> 2020 | H8: =IS!J8 -> 2021 | N8: =IS!P8 -> 2022 | T8: =IS!V8 -> 2023 | Z8: =IS!AB8 -> 2024 | AF8: =IS!AH8 -> 2025 | AL8: 2026 | AR8: 2027 | AT8: 2028 | AV8: 2029
B9: =IS!D9 -> Q1 | C9: =IS!E9 -> Q2 | D9: =IS!F9 -> Q3 | E9: =IS!G9 -> Q4 | F9: =IS!H9 -> FY | H9: =IS!J9 -> Q1 | I9: =IS!K9 -> Q2 | J9: =IS!L9 -> Q3 | K9: =IS!M9 -> Q4 | L9: =IS!N9 -> FY | N9: =IS!P9 -> Q1 | O9: =IS!Q9 -> Q2 | P9: =IS!R9 -> Q3 | Q9: =IS!S9 -> Q4 | R9: =IS!T9 -> FY | T9: =IS!V9 -> Q1 | U9: =IS!W9 -> Q2 | V9: =IS!X9 -> Q3 | W9: =IS!Y9 -> Q4 | X9: =IS!Z9 -> FY | Z9: =IS!AB9 -> Q1 | AA9: =IS!AC9 -> Q2 | AB9: =IS!AD9 -> Q3 | AC9: =IS!AE9 -> Q4 | AD9: =IS!AF9 -> FY | AF9: =IS!AH9 -> Q1 | AG9: =IS!AI9 -> Q2 | AH9: Q3 | AI9: Q4 | AJ9: FY | AL9: =IS!AN9 -> Q1 | AM9: Q2 | AN9: Q3 | AO9: Q4 | AP9: FY | AR9: FY | AT9: FY | AV9: FY
A10: =BS!B44 -> Long-term borrowings | B10: =BS!D44 -> 18726 | C10: =BS!E44 -> 18599 | D10: =BS!F44 -> 18536 | E10: =BS!G44 -> 21467 | F10: =BS!H44 -> 21467 | G10: =L10/F10-1 -> -0.058648158 | H10: =BS!J44 -> 22731 | I10: =BS!K44 -> 22741 | J10: =BS!L44 -> 22281 | K10: =BS!M44 -> 20208 | L10: =BS!N44 -> 20208 | M10: =R10/L10-1 -> -0.024445764 | N10: =BS!P44 -> 20050 | O10: =BS!Q44 -> 19876 | P10: =BS!R44 -> 19892 | Q10: =BS!S44 -> 19714 | R10: =BS!T44 -> 19714 | S10: =X10/R10-1 -> -0.0030942477 | T10: =BS!V44 -> 19374 | U10: =BS!W44 -> 19496 | V10: =BS!X44 -> 19583 | W10: =BS!Y44 -> 19653 | X10: =BS!Z44 -> 19653 | Y10: =AD10/X10-1 -> 0.0025950237 | Z10: =BS!AB44 -> 19415 | AA10: =BS!AC44 -> 19487 | AB10: =BS!AD44 -> 19690 | AC10: =BS!AE44 -> 19704 | AD10: =BS!AF44 -> 19704 | AE10: =AJ10/AD10-1 -> -0.020898286 | AF10: =BS!AH44 -> 19240 | AG10: =BS!AI44 -> 19013 | AJ10: =(1+AVERAGE(G10,M10,S10,Y10))*AD10 -> 19292.22 | AK10: =AP10/AJ10-1 -> -0.011460819 | AP10: =(1+AVERAGE(M10,S10,Y10,AE10))*AJ10 -> 19071.116 | AQ10: =AR10/AP10-1 -> -0.0082145823 | AR10: =(1+AVERAGE(Y10,AE10,S10,AK10))*AP10 -> 18914.454 | AS10: =AT10/AR10-1 -> -0.0094946659 | AT10: =(1+AVERAGE(AE10,AK10,AQ10,Y10))*AR10 -> 18734.868 | AU10: =AV10/AT10-1 -> -0.012517088 | AV10: =(1+AVERAGE(AE10,AK10,AQ10,AS10))*AT10 -> 18500.362
A12: =IS!B36 -> Interest expense | B12: =IS!D36 -> 137 | C12: =IS!E36 -> 151 | D12: =IS!F36 -> 155 | E12: =IS!G36 -> 174 | F12: =IS!H36 -> 672 | H12: =IS!J36 -> 184 | I12: =IS!K36 -> 184 | J12: =IS!L36 -> 187 | K12: =IS!M36 -> 186 | L12: =IS!N36 -> 793 | N12: =IS!P36 -> 160 | O12: =IS!Q36 -> 155 | P12: =IS!R36 -> 163 | Q12: =IS!S36 -> 158 | R12: =IS!T36 -> 689 | T12: =IS!V36 -> 142 | U12: =IS!W36 -> 127 | V12: =IS!X36 -> 122 | W12: =IS!Y36 -> 303 | X12: =IS!Z36 -> 694 | Z12: =IS!AB36 -> 91 | AA12: =IS!AC36 -> 97 | AB12: =IS!AD36 -> 91 | AC12: =IS!AE36 -> 466 | AD12: =IS!AF36 -> 745 | AF12: =IS!AH36 -> 84 | AG12: =IS!AI36 -> 102 | AJ12: =AJ10*AJ13 -> 710.50316 | AP12: =AP10*AP13 -> 690.85364 | AR12: =AR10*AR13 -> 691.20919 | AT12: =AT10*AT13 -> 690.41341 | AV12: =AV10*AV13 -> 677.34157
A13: % of LT borrowings | B13: =B12/B10 -> 0.0073160312 | C13: =C12/C10 -> 0.0081187161 | D13: =D12/D10 -> 0.0083621062 | E13: =E12/E10 -> 0.0081054642 | F13: =F12/F10 -> 0.031303862 | H13: =H12/H10 -> 0.0080946725 | I13: =I12/I10 -> 0.008091113 | J13: =J12/J10 -> 0.008392801 | K13: =K12/K10 -> 0.0092042755 | L13: =L12/L10 -> 0.039241884 | N13: =N12/N10 -> 0.0079800499 | O13: =O12/O10 -> 0.0077983498 | P13: =P12/P10 -> 0.0081942489 | Q13: =Q12/Q10 -> 0.0080146089 | R13: =R12/R10 -> 0.034949782 | T13: =T12/T10 -> 0.0073294106 | U13: =U12/U10 -> 0.0065141568 | V13: =V12/V10 -> 0.0062298933 | W13: =W12/W10 -> 0.015417494 | X13: =X12/X10 -> 0.035312675 | Z13: =Z12/Z10 -> 0.0046870976 | AA13: =AA12/AA10 -> 0.0049776774 | AB13: =AB12/AB10 -> 0.0046216353 | AC13: =AC12/AC10 -> 0.02365002 | AD13: =AD12/AD10 -> 0.037809582 | AF13: =AF12/AF10 -> 0.0043659044 | AG13: =AG12/AG10 -> 0.0053647504 | AJ13: =AVERAGE(L13,R13,X13,AD13) -> 0.036828481 | AP13: =AVERAGE(R13,X13,AD13,AJ13) -> 0.03622513 | AR13: =AVERAGE(X13,AD13,AJ13,AP13) -> 0.036543967 | AT13: =AVERAGE(AD13,AJ13,AP13,AR13) -> 0.03685179 | AV13: =AVERAGE(AJ13,AP13,AR13,AT13) -> 0.036612342
A14: 5 year average: | G14: =AVERAGE(F13,L13,R13,X13,AD13) -> 0.035723557
A19: =BS!B45 -> Long-term operating lease liabilities | B19: =BS!D45 -> 12137 | C19: =BS!E45 -> 12524 | D19: =BS!F45 -> 12669 | E19: =BS!G45 -> 12680 | F19: =BS!H45 -> 12680 | G19: =L19/F19-1 -> 0.096214511 | H19: =BS!J45 -> 13187 | I19: =BS!K45 -> 13489 | J19: =BS!L45 -> 13506 | K19: =BS!M45 -> 13900 | L19: =BS!N45 -> 13900 | M19: =R19/L19-1 -> 0.075899281 | N19: =BS!P45 -> 13886 | O19: =BS!Q45 -> 14465 | P19: =BS!R45 -> 14951 | Q19: =BS!S45 -> 14955 | R19: =BS!T45 -> 14955 | S19: =X19/R19-1 -> 0.08077566 | T19: =BS!V45 -> 15662 | U19: =BS!W45 -> 15870 | V19: =BS!X45 -> 15912 | W19: =BS!Y45 -> 16163 | X19: =BS!Z45 -> 16163 | Y19: =AD19/X19-1 -> -0.042009528 | Z19: =BS!AB45 -> 16068 | AA19: =BS!AC45 -> 15928 | AB19: =BS!AD45 -> 15310 | AC19: =BS!AE45 -> 15484 | AD19: =BS!AF45 -> 15484 | AE19: =AJ19/AD19-1 -> 0.052719981 | AF19: =BS!AH45 -> 15393 | AG19: =BS!AI45 -> 15133 | AJ19: =(1+AVERAGE(G19,M19,S19,Y19))*AD19 -> 16300.316 | AK19: =AJ19/AD19-1 -> 0.052719981 | AP19: =(1+AVERAGE(AK19,S19,Y19,AE19))*AJ19 -> 16887.967 | AQ19: =AR19/AP19-1 -> 0.036051524 | AR19: =(1+AVERAGE(Y19,AE19,S19,AK19))*AP19 -> 17496.804 | AS19: =AT19/AR19-1 -> 0.024870489 | AT19: =(1+AVERAGE(AE19,AK19,AQ19,Y19))*AR19 -> 17931.958 | AU19: =AV19/AT19-1 -> 0.041590494 | AV19: =(1+AVERAGE(AE19,AK19,AQ19,AS19))*AT19 -> 18677.757
A21: Total is equal to | F21: =F19+F10 -> 34147 | L21: =L19+L10 -> 34108 | R21: =R19+R10 -> 34669 | X21: =X19+X10 -> 35816 | AD21: =AD19+AD10 -> 35188 | AJ21: =AJ19+AJ10 -> 35592.536 | AP21: =AP19+AP10 -> 35959.083 | AR21: =AR19+AR10 -> 36411.259 | AT21: =AT19+AT10 -> 36666.826 | AV21: =AV19+AV10 -> 37178.119

Sheet FCFF
A7: x | B7: Market Assumptions
D8: 2022 | E8: =D8+1 -> 2023 | F8: =E8+1 -> 2024 | G8: =F8+1 -> 2025 | H8: =G8+1 -> 2026 | J8: =H8+1 -> 2027 | K8: =+J8+1 -> 2028 | L8: =+K8+1 -> 2029 | AB8: 2026
D9: FY | E9: FY | F9: FY | G9: FY | H9: FY | J9: FY | K9: FY | L9: FY
B11: Industry | D11: data | G11: assumptions
B12: {=Industry!B12:B25} -> Global transportation and Logistics Market Size | D12: =Industry!D12 -> 1272945.2 | E12: =Industry!E12 -> 1337992.7 | F12: =Industry!F12 -> 1406364.1 | G12: =Industry!G12 -> 1478229.3 | H12: =Industry!H12 -> 1553766.8 | J12: =Industry!I12 -> 1633164.3 | K12: =Industry!J12 -> 1716619 | L12: =Industry!K12 -> 1804338.2 | M12: control
B13: FedEx Market Share | D13: =SUM(D29:D31)/D12 -> 0.069585087 | E13: =SUM(E29:E31)/E12 -> 0.064187198 | F13: =SUM(F29:F31)/F12 -> 0.059867143 | G13: =SUM(G29:G31)/G12 -> 0.057974468 | H13: =SUM(H29:H31)/H12 -> 0.056684884 | J13: =SUM(J29:J31)/J12 -> 0.055640595 | K13: =SUM(K29:K31)/K12 -> 0.054732614 | L13: =SUM(L29:L31)/L12 -> 0.05174646
B14: E-commerce Market Size | D14: =Industry!D14 -> 30830770 | E14: =Industry!E14 -> 36657786 | F14: =Industry!F14 -> 43586107 | G14: =Industry!G14 -> 51823881 | H14: =Industry!H14 -> 61618595 | J14: =Industry!I14 -> 73264509 | K14: =Industry!J14 -> 87111501 | L14: =Industry!K14 -> 83260000
B15: FedEx Market Share | D15: =SUM(D29:D30)/FCFF!D14 -> 0.0025638672 | E15: =SUM(E29:E30)/FCFF!E14 -> 0.0020800493 | F15: =SUM(F29:F30)/FCFF!F14 -> 0.0017233244 | G15: =SUM(G29:G30)/FCFF!G14 -> 0.0014801945 | H15: =SUM(H29:H30)/FCFF!H14 -> 0.001282501 | J15: =SUM(J29:J30)/FCFF!J14 -> 0.0011152217 | K15: =SUM(K29:K30)/FCFF!K14 -> 0.00097147653 | L15: =SUM(L29:L30)/FCFF!L14 -> 0.0010158129
B16: E-commerce in the U.S. Market Size | D16: =Industry!D16 -> 921190.52 | E16: =Industry!E16 -> 1019850 | F16: =Industry!F16 -> 1129076 | G16: =Industry!G16 -> 1250000 | H16: =Industry!H16 -> 1383875 | J16: =Industry!I16 -> 1532088 | K16: =Industry!J16 -> 1696174.6 | L16: =Industry!K16 -> 2080000
B17: FedEx Market Share | D17: =SUM(D38,D40)/D16 -> 0.057127162 | E17: =SUM(E38,E40)/E16 -> 0.05128205 | F17: =SUM(F38,F40)/F16 -> 0.046035875 | G17: =SUM(G38,G40)/G16 -> 0.042099852 | H17: =SUM(H38,H40)/H16 -> 0.038920613 | J17: =SUM(J38,J40)/J16 -> 0.036122108 | K17: =SUM(K38,K40)/K16 -> 0.033572922 | L17: =SUM(L38,L40)/L16 -> 0.027083178
B18: Global Express Delivery Service | D18: =Industry!D18 -> 227260.59 | E18: =Industry!E18 -> 240896.23 | F18: =Industry!F18 -> 255350 | G18: =Industry!G18 -> 270671 | H18: =Industry!H18 -> 286911.26 | J18: =Industry!I18 -> 304125.94 | K18: =Industry!J18 -> 322373.49 | L18: =Industry!K18 -> 341715.9
B19: FedEx Market Share | D19: =D29/D18 -> 0.20159236 | E19: =E29/E18 -> 0.17743325 | F19: =F29/F18 -> 0.16000392 | G19: =G29/G18 -> 0.15690974 | H19: =H29/H18 -> 0.154321 | J19: =J29/J18 -> 0.15213618 | K19: =K29/K18 -> 0.14995716 | L19: =L29/L18 -> 0.14477194
B20: US Express Delivery Service | D20: =Industry!D20 -> 87330.304 | E20: =Industry!E20 -> 91705.552 | F20: =Industry!F20 -> 96300 | G20: =Industry!G20 -> 101124.63 | H20: =Industry!H20 -> 106190.97 | J20: =Industry!I20 -> 111511.14 | K20: =Industry!J20 -> 117097.85 | L20: =Industry!K20 -> 122964.45
B21: FedEx Market Share | D21: =D38/D20 -> 0.23187827 | E21: =E38/E20 -> 0.21430545 | F21: =F38/F20 -> 0.19279335 | G21: =G38/G20 -> 0.19023468 | H21: =H38/H20 -> 0.18818775 | J21: =J38/J20 -> 0.1865502 | K21: =K38/K20 -> 0.1843668 | L21: =L38/L20 -> 0.18
B22: US freight and logistics market | D22: =Industry!D22 -> 0 | E22: =Industry!E22 -> 0 | F22: =Industry!F22 -> 1405500 | G22: =Industry!G22 -> 1450500 | H22: =Industry!H22 -> 1511421 | J22: =Industry!I22 -> 1574900.7 | K22: =Industry!J22 -> 1641046.5 | L22: =Industry!K22 -> 1709970.5
B23: FedEx Market Share | F23: =SUM(F30:F31)/F22 -> 0.030834578 | G23: =SUM(G30:G31)/G22 -> 0.029802579 | H23: =SUM(H30:H31)/H22 -> 0.028978465 | J23: =SUM(J30:J31)/J22 -> 0.02832031 | K23: =SUM(K30:K31)/K22 -> 0.027794966 | L23: =SUM(L30:L31)/L22 -> 0.025671346
B24: Rest of World freight and logistics market | D24: =Industry!D24 -> 4363400.2 | E24: =Industry!E24 -> 4544481.3 | F24: =Industry!F24 -> 4733077.3 | G24: =Industry!G24 -> 4929500 | H24: =Industry!H24 -> 5186941 | J24: =Industry!I24 -> 5457709.6 | K24: =Industry!J24 -> 5742491 | L24: =Industry!K24 -> 6042005.6
B25: FedEx Market Share | D25: =SUM(D53,D55)/D24 -> 0.00025026354 | E25: =SUM(E53,E55)/E24 -> 0.00024733296 | F25: =SUM(F53,F55)/F24 -> 0.00023325205 | G25: =SUM(G53,G55)/G24 -> 0.00022460164 | H25: =SUM(H53,H55)/H24 -> 0.00021768131 | J25: =SUM(J53,J55)/J24 -> 0.00021214505 | K25: =SUM(K53,K55)/K24 -> 0.00020771604 | L25: =SUM(L53,L55)/L24 -> 0.00019
B27: Total Segments
B28: {=Segments!B12:B18} -> Revenue by segment:
B29: FedEx Express | D29: {=Segments!T13:T18} -> 45814 | E29: {=Segments!Z13:Z18} -> 42743 | F29: {=Segments!AF13:AF18} -> 40857 | G29: =SUM(G38+G51) -> 42470.916 | H29: =SUM(H38+H51) -> 44276.432 | J29: =SUM(J38+J51) -> 46268.558 | K29: =SUM(K38+K51) -> 48342.212 | L29: =SUM(L38+L51) -> 49470.874
B30: FedEx Ground | D30: 33232 | E30: 33507 | F30: 34256 | G30: =G40+G53 -> 34238.509 | H30: =H40+H53 -> 34749.475 | J30: =J40+J53 -> 35437.614 | K30: =K40+K53 -> 36284.567 | L30: =L40+L53 -> 35105.71
B31: FedEx Freight | D31: 9532 | E31: 9632 | F31: 9082 | G31: =G42+G55 -> 8990.1317 | H31: =H42+H55 -> 9049.1849 | J31: =J42+J55 -> 9164.0608 | K31: =K42+K55 -> 9328.2652 | L31: =L42+L55 -> 8791.5325
B32: FedEx Services | D32: 253 | E32: 301 | F32: 260 | G32: =G44 -> 267.8 | H32: =H44 -> 275.834 | J32: =J44 -> 284.10902 | K32: =K44 -> 292.63229 | L32: =L44 -> 301.41126
B33: Corporate, other and eliminations | D33: 4681 | E33: 3972 | F33: 3238 | G33: =G46+G57 -> 3909.3207 | H33: =H46+H57 -> 3823.6974 | J33: =J46+J57 -> 3860.4761 | K33: =K46+K57 -> 4122.2675 | L33: =L46+L57 -> 4039.5437
B34: Total revenue | D34: 93512 | E34: 90155 | F34: 87693 | G34: =SUM(G29:G33) -> 89876.678 | H34: =SUM(H29:H33) -> 92174.623 | J34: =SUM(J29:J33) -> 95014.818 | K34: =SUM(K29:K33) -> 98369.944 | L34: =SUM(L29:L33) -> 97709.071
F35: =F34/D34-1 -> -0.062227308
B37: US
B38: FedEx Express Segment | D38: =D29-D51 -> 20250 | E38: =E29-E51 -> 19653 | F38: =F29-F51 -> 18566 | G38: =G20*G39 -> 19237.412 | H38: =H20*H39 -> 19983.84 | J38: =J20*J39 -> 20802.425 | K38: =K20*K39 -> 21588.956 | L38: =L20*L39 -> 22133.601
B39: Market Share | D39: =D38/D20 -> 0.23187827 | E39: =E38/E20 -> 0.21430545 | F39: =F38/F20 -> 0.19279335 | G39: =F39+($L$39-F39)/5 -> 0.19023468 | H39: =G39+($L$39-G39)/5 -> 0.18818775 | J39: =H39+($L$39-H39)/5 -> 0.1865502 | K39: =J39+($L$39-J39)/3 -> 0.1843668 | L39: 0.18
B40: FedEx Ground Segment | D40: =D30-D53 -> 32375 | E40: =E30-E53 -> 32647 | F40: =F30-F53 -> 33412 | G40: =G22*G41 -> 33387.404 | H40: =H22*H41 -> 33877.424 | J40: =J22*J41 -> 34539.823 | K40: =K22*K41 -> 35356.583 | L40: =L22*L41 -> 34199.409
B41: Market Share | F41: =F40/F22 -> 0.023772323 | G41: =F41+($L$41-F41)/5 -> 0.023017858 | H41: =G41+($L$41-G41)/5 -> 0.022414287 | J41: =H41+($L$41-H41)/5 -> 0.021931429 | K41: =J41+($L$41-J41)/5 -> 0.021545144 | L41: 0.02
B42: FedEx Freight Segment | D42: =D31-D55 -> 9297 | E42: =E31-E55 -> 9368 | F42: =F31-F55 -> 8822 | G42: =G22*G43 -> 8734.0637 | H42: =H22*H43 -> 8792.1365 | J42: =J22*J43 -> 8904.0257 | K42: =K22*K43 -> 9063.4423 | L42: =L22*L43 -> 8549.8523
B43: Market Share | F43: =F42/F22 -> 0.0062767698 | G43: =F43+($L$43-F43)/5 -> 0.0060214159 | H43: =G43+($L$43-G43)/5 -> 0.0058171327 | J43: =H43+($L$43-H43)/5 -> 0.0056537062 | K43: =J43+($L$43-J43)/5 -> 0.0055229649 | L43: 0.005
B44: FedEx Services Segment | D44: 253 | E44: 301 | F44: 260 | G44: =F44*(1+$N$47) -> 267.8 | H44: =G44*(1+$N$47) -> 275.834 | J44: =H44*(1+$N$47) -> 284.10902 | K44: =J44*(1+$N$47) -> 292.63229 | L44: =K44*(1+$N$47) -> 301.41126 | AS44: 2022 | AT44: =+AS44+1 -> 2023 | AU44: =+AT44+1 -> 2024 | AV44: =+AU44+1 -> 2025 | AW44: =+AV44+1 -> 2026 | AX44: =+AW44+1 -> 2027 | AY44: =+AX44+1 -> 2028 | AZ44: =+AY44+1 -> 2029
B45: Growth rate based on inflation | G45: =G44/F44-1 -> 0.03 | H45: =H44/G44-1 -> 0.03 | J45: =J44/H44-1 -> 0.03 | K45: =K44/J44-1 -> 0.03 | L45: =L44/K44-1 -> 0.03
B46: Corporate, other and eliminations | D46: =64741- SUM(D38,D40,D42,D44) -> 2566 | E46: =64890- SUM(E38,E40,E42,E44) -> 2921 | F46: =63531- SUM(F38,F40,F42,F44) -> 2471 | G46: =(G38+G40+G42+G44)*G47 -> 2647.3891 | H46: =(H38+H40+H42+H44)*H47 -> 2738.7506 | J46: =(J38+J40+J42+J44)*J47 -> 2730.6677 | K46: =(K38+K40+K42+K44)*K47 -> 2846.4522 | L46: =(L38+L40+L42+L44)*L47 -> 2797.9043 | N46: Inflation assumption:
B47: % of revenue shown here | used for average | D47: =D46/SUM(D38,D40,D42,D44) -> 0.041270607 | E47: =E46/SUM(E38,E40,E42,E44) -> 0.047136471 | F47: =F46/SUM(F38,F40,F42,F44) -> 0.040468392 | G47: =AVERAGE(D47:F47) -> 0.04295849 | H47: =AVERAGE(E47:G47) -> 0.043521118 | J47: =AVERAGE(F47:H47) -> 0.042316 | K47: =AVERAGE(G47:H47,J47) -> 0.042931869 | L47: =AVERAGE(J47:K47,H47) -> 0.042922996 | N47: 0.03
B48: Total | D48: =SUM(D38,D40,D42,D44,D46) -> 64741 | E48: =SUM(E38,E40,E42,E44,E46) -> 64890 | F48: =SUM(F38,F40,F42,F44,F46) -> 63531 | G48: =SUM(G38,G40,G42,G44,G46) -> 64274.068 | H48: =SUM(H38,H40,H42,H44,H46) -> 65667.985 | J48: =SUM(J38,J40,J42,J44,J46) -> 67261.051 | K48: =SUM(K38,K40,K42,K44,K46) -> 69148.065 | L48: =SUM(L38,L40,L42,L44,L46) -> 67982.179
B50: International
B51: FedEx Express Segment | D51: 25564 | E51: 23090 | F51: 22291 | G51: =G18*G52 -> 23233.504 | H51: =H18*H52 -> 24292.592 | J51: =J18*J52 -> 25466.133 | K51: =K18*K52 -> 26753.256 | L51: =L18*L52 -> 27337.272
B52: Market Share | D52: =D51/D18 -> 0.11248761 | E52: =E51/E18 -> 0.095850401 | F52: =F51/F18 -> 0.087295868 | G52: =F52+($L$52-F52)/5 -> 0.085836695 | H52: =G52+($L$52-G52)/5 -> 0.084669356 | J52: =H52+($L$52-H52)/5 -> 0.083735485 | K52: =J52+($L$52-J52)/5 -> 0.082988388 | L52: 0.08
B53: FedEx Ground Segment | D53: 857 | E53: 860 | F53: 844 | G53: =G54*G24 -> 851.1058 | H53: =H54*H24 -> 872.05178 | J53: =J54*J24 -> 897.79097 | K53: =K54*K24 -> 927.98465 | L53: =L54*L24 -> 906.30084
B54: Market Share | D54: =D53/D24 -> 0.00019640646 | E54: =E53/E24 -> 0.00018924052 | F54: =F53/F24 -> 0.00017831951 | G54: =F54+($L$54-F54)/5 -> 0.0001726556 | H54: =G54+($L$54-G54)/5 -> 0.00016812448 | J54: =H54+($L$54-H54)/5 -> 0.00016449959 | K54: =J54+($L$54-J54)/5 -> 0.00016159967 | L54: 0.00015
B55: FedEx Freight Segment | D55: 235 | E55: 264 | F55: 260 | G55: =G56*G24 -> 256.068 | H55: =H56*H24 -> 257.04836 | J55: =J56*J24 -> 260.03511 | K55: =K56*K24 -> 264.82285 | L55: =L56*L24 -> 241.68022
B56: Market Share | D56: =D55/D24 -> 5.3857081e-05 | E56: =E55/E24 -> 5.8092438e-05 | F56: =F55/F24 -> 5.4932549e-05 | G56: =F56+($L$56-F56)/5 -> 5.1946039e-05 | H56: =G56+($L$56-G56)/5 -> 4.9556831e-05 | J56: =H56+($L$56-H56)/5 -> 4.7645465e-05 | K56: =J56+($L$56-J56)/5 -> 4.6116372e-05 | L56: 4e-05
B57: Corporate, other and eliminations | D57: =D33-D46 -> 2115 | E57: =E33-E46 -> 1051 | F57: =F33-F46 -> 767 | G57: =(G51+G53+G55)*G58 -> 1261.9316 | H57: =(H51+H53+H55)*H58 -> 1084.9468 | J57: =(J51+J53+J55)*J58 -> 1129.8084 | K57: =(K51+K53+K55)*K58 -> 1275.8154 | L57: =(L51+L53+L55)*L58 -> 1241.6394
B58: % of revenue shown here | used for average | D58: =D57/SUM(D49,D51,D53,D55) -> 0.079344238 | E58: =E57/SUM(E49,E51,E53,E55) -> 0.043404642 | F58: =F57/SUM(F49,F51,F53,F55) -> 0.032784783 | G58: =AVERAGE(D58:F58) -> 0.051844554 | H58: =AVERAGE(E58:G58) -> 0.042677993 | J58: =AVERAGE(F58:H58) -> 0.042435777 | K58: =AVERAGE(G58:H58,J58) -> 0.045652775 | L58: =AVERAGE(J58:K58,H58) -> 0.043588848
B59: Total | D59: =SUM(D51,D53,D55) -> 26656 | E59: =SUM(E51,E53,E55) -> 24214 | F59: =SUM(F51,F53,F55) -> 23395 | G59: =SUM(G51,G53,G55) -> 24340.678 | H59: =SUM(H51,H53,H55) -> 25421.692 | J59: =SUM(J51,J53,J55) -> 26623.959 | K59: =SUM(K51,K53,K55) -> 27946.064 | L59: =SUM(L51,L53,L55) -> 28485.253 | N59: Base assumption/trend
V60: 0.24 | W60: 0.245 | X60: 0.255 | Y60: 0.26 | AB60: 0.24 | AC60: 0.245 | AD60: 0.255 | AE60: 0.26
V61: =$Z$61*V60 -> 21570.403 | W61: =$Z$61*W60 -> 22019.786 | X61: =$Z$61*X60 -> 22918.553 | Y61: =$Z$61*Y60 -> 23367.936 | Z61: =G34 -> 89876.678 | AB61: =$AF$61*AB60 -> 22121.91 | AC61: =$AF$61*AC60 -> 22582.783 | AD61: =$AF$61*AD60 -> 23504.529 | AE61: =$AF$61*AE60 -> 23965.402 | AF61: =H34 -> 92174.623 | AH61: =J34 -> 95014.818 | AJ61: =K34 -> 98369.944 | AL61: =L34 -> 97709.071
A63: x | B63: Operating Assumptions | D63: =D71/$H$71 -> 0.235296 | E63: =E71/$H$71 -> 0.25102661 | F63: =F71/$H$71 -> 0.25281247 | G63: =G71/$H$71 -> 0.26086492 | J63: =J71/$N$71 -> 0.25780045 | K63: =K71/$N$71 -> 0.25305308 | L63: =L71/$N$71 -> 0.24589873 | M63: =M71/$N$71 -> 0.24324774 | P63: =P71/$T$71 -> 0.24723752 | Q63: =Q71/$T$71 -> 0.25275678 | R63: =R71/$T$71 -> 0.24788752 | S63: =S71/$T$71 -> 0.25211819
D64: =D$8 -> 2022 | E64: =F64 -> #REF! | F64: =#REF! -> #REF! | G64: =F64 -> #REF! | H64: =F64 -> #REF! | J64: =E$8 -> 2023 | K64: =L64 -> #REF! | L64: =#REF! -> #REF! | M64: =L64 -> #REF! | N64: =L64 -> #REF! | P64: =F$8 -> 2024 | Q64: =R64 -> 0 | R64: =R$8 -> 0 | S64: =R64 -> 0 | T64: =R64 -> 0 | V64: =G$8 -> 2025 | W64: =X64 -> 0 | X64: =X$8 -> 0 | Y64: =X64 -> 0 | Z64: =X64 -> 0 | AB64: =H$8 -> 2026 | AC64: =AD64 -> 0 | AD64: =AD$8 -> 0 | AE64: =AD64 -> 0 | AF64: =AD64 -> 0 | AH64: =J$8 -> 2027 | AJ64: =K$8 -> 2028 | AL64: =L$8 -> 2029 | AM64: =AN64 -> 0
D65: Q1 | E65: Q2 | F65: Q3 | G65: Q4 | H65: FY | J65: Q1 | K65: Q2 | L65: Q3 | M65: Q4 | N65: FY | P65: Q1 | Q65: Q2 | R65: Q3 | S65: Q4 | T65: FY | V65: Q1 | W65: Q2 | X65: Q3 | Y65: Q4 | Z65: FY | AB65: Q1 | AC65: Q2 | AD65: Q3 | AE65: Q4 | AF65: FY | AH65: FY | AJ65: FY | AL65: FY
B68: Income Statement
B71: Revenue | D71: =IS!P18 -> 22003 | E71: =IS!Q18 -> 23474 | F71: =IS!R18 -> 23641 | G71: =IS!S18 -> 24394 | H71: =IS!T18 -> 93512 | J71: =IS!V18 -> 23242 | K71: =IS!W18 -> 22814 | L71: =IS!X18 -> 22169 | M71: =IS!Y18 -> 21930 | N71: =IS!Z18 -> 90155 | P71: =IS!AB18 -> 21681 | Q71: =IS!AC18 -> 22165 | R71: =IS!AD18 -> 21738 | S71: =IS!AE18 -> 22109 | T71: =IS!AF18 -> 87693 | V71: =IS!AH18 -> 21579 | W71: =IS!AI18 -> 21967 | X71: =X61 -> 22918.553 | Y71: =Y61 -> 23367.936 | Z71: =SUM(V71:Y71) -> 89832.489 | AB71: =AB61 -> 22121.91 | AC71: =AC61 -> 22582.783 | AD71: =AD61 -> 23504.529 | AE71: =AE61 -> 23965.402 | AF71: =SUM(AB71:AE71) -> 92174.623 | AH71: =AH61 -> 95014.818 | AJ71: =AJ61 -> 98369.944 | AL71: =AL61 -> 97709.071
B72: % of growth | D72: =D71/IS!J18-1 -> 0.13881269 | E72: =E71/IS!K18-1 -> 0.14156495 | F72: =F71/IS!L18-1 -> 0.0990702 | G72: =G71/IS!M18-1 -> 0.081054731 | H72: =H71/IS!N18-1 -> 0.11378173 | J72: =J71/IS!P18-1 -> 0.056310503 | K72: =K71/IS!Q18-1 -> -0.028116214 | L72: =L71/IS!R18-1 -> -0.06226471 | M72: =M71/IS!S18-1 -> -0.10100844 | N72: =N71/H71-1 -> -0.035899136 | P72: =P71/IS!V18-1 -> -0.067162895 | Q72: =Q71/IS!W18-1 -> -0.028447445 | R72: =R71/IS!X18-1 -> -0.019441563 | S72: =S71/IS!Y18-1 -> 0.0081623347 | T72: =T71/N71-1 -> -0.027308524 | V72: =V71/IS!AB18-1 -> -0.00470458 | W72: =W71/IS!AC18-1 -> -0.0089330025 | X72: =X71/IS!AD18-1 -> 0.054308254 | Y72: =Y71/IS!AE18-1 -> 0.056942251 | Z72: =Z71/T71-1 -> 0.02439749 | AB72: =AB71/IS!AH18-1 -> 0.025159164 | AC72: =AC71/IS!AI18-1 -> 0.028032172 | AD72: =AD71/X71-1 -> 0.025567763 | AE72: =AE71/Y71-1 -> 0.025567763 | AF72: =AF71/Z71-1 -> 0.026072241 | AH72: =AH71/AF71-1 -> 0.030813195 | AJ72: =AJ71/AH71-1 -> 0.03531161 | AL72: =AL71/AJ71-1 -> -0.0067182419
B74: Cost of Goods & Services | D74: =IS!P21 -> 16446 | E74: =IS!Q21 -> 17537 | F74: =IS!R21 -> 17764 | G74: =IS!S21 -> 17628 | H74: =IS!T21 -> 69375 | J74: =IS!V21 -> 17511 | K74: =IS!W21 -> 17127 | L74: =IS!X21 -> 16563 | M74: =IS!Y21 -> 15612 | N74: =IS!Z21 -> 66813 | P74: =IS!AB21 -> 15897 | Q74: =IS!AC21 -> 16548 | R74: =IS!AD21 -> 16127 | S74: =IS!AE21 -> 15882 | T74: =IS!AF21 -> 64454 | V74: =IS!AH21 -> 16125 | W74: =IS!AI21 -> 16325 | X74: =(X75+Sensitivity!$U$39)*X$71 -> 16730.544 | Y74: =(Y75+Sensitivity!$U$39)*Y$71 -> 17058.593 | Z74: =SUM(V74:Y74) -> 66239.137 | AB74: =(AB75+Sensitivity!$U$39)*AB$71 -> 16148.994 | AC74: =(AC75+Sensitivity!$U$39)*AC$71 -> 16485.431 | AD74: =(AD75+Sensitivity!$U$39)*AD$71 -> 17158.306 | AE74: =(AE75+Sensitivity!$U$39)*AE$71 -> 17494.744 | AF74: =SUM(AB74:AE74) -> 67287.475 | AH74: =(AH75+Sensitivity!$U$39)*AH$71 -> 69360.817 | AJ74: =(AJ75+Sensitivity!$U$39)*AJ$71 -> 70826.36 | AL74: =(AL75+Sensitivity!$U$39)*AL$71 -> 69373.44
B75: % of sales | D75: =D74/D71 -> 0.74744353 | E75: =E74/E71 -> 0.74708188 | F75: =F74/F71 -> 0.75140645 | G75: =G74/G71 -> 0.72263671 | H75: =H74/H71 -> 0.74188339 | J75: =J74/J71 -> 0.75342053 | K75: =K74/K71 -> 0.75072324 | L75: =L74/L71 -> 0.74712436 | M75: =M74/M71 -> 0.7119015 | N75: =N74/N71 -> 0.74109034 | P75: =P74/P71 -> 0.73322264 | Q75: =Q74/Q71 -> 0.74658245 | R75: =R74/R71 -> 0.74188058 | S75: =S74/S71 -> 0.71834999 | T75: =T74/T71 -> 0.73499595 | V75: =V74/V71 -> 0.74725427 | W75: =W74/W71 -> 0.74316019 | X75: 0.73 | Y75: 0.73 | Z75: =AVERAGE(V75:Y75) -> 0.73760362 | AB75: 0.73 | AC75: 0.73 | AD75: 0.73 | AE75: 0.73 | AF75: =AVERAGE(AB75:AE75) -> 0.73 | AH75: 0.73 | AJ75: 0.72 | AL75: 0.71
B77: COGS Depreciation & Amortization | D77: =IS!P22 -> 971 | E77: =IS!Q22 -> 995 | F77: =IS!R22 -> 986 | G77: =IS!S22 -> 1018 | H77: =IS!T22 -> 3970 | J77: =IS!V22 -> 1024 | K77: =IS!W22 -> 1046 | L77: =IS!X22 -> 1031 | M77: =IS!Y22 -> 1075 | N77: =IS!Z22 -> 4176 | P77: =IS!AB22 -> 1071 | Q77: =IS!AC22 -> 1040 | R77: =IS!AD22 -> 1072 | S77: =IS!AE22 -> 1104 | T77: =IS!AF22 -> 4287 | V77: =IS!AH22 -> 1078 | W77: =IS!AI22 -> 1063 | X77: =X78*X74 -> 1087.4853 | Y77: =Y78*Y74 -> 1108.8086 | Z77: =SUM(V77:Y77) -> 4337.2939 | AB77: =AB78*AB74 -> 1081.9826 | AC77: =AC78*AC74 -> 1104.5239 | AD77: =AD78*AD74 -> 1149.6065 | AE77: =AE78*AE74 -> 1172.1478 | AF77: =SUM(AB77:AE77) -> 4508.2608 | AH77: =AH78*AH74 -> 4647.1748 | AJ77: =AJ78*AJ74 -> 4816.1925 | AL77: =AL78*AL74 -> 4717.394
B78: % of cost of goods & services | D78: =D77/D74 -> 0.059041712 | E78: =E77/E74 -> 0.056737184 | F78: =F77/F74 -> 0.055505517 | G78: =G77/G74 -> 0.057749036 | H78: =H77/H74 -> 0.057225225 | J78: =J77/J74 -> 0.058477528 | K78: =K77/K74 -> 0.061073159 | L78: =L77/L74 -> 0.062247177 | M78: =M77/M74 -> 0.068857289 | N78: =N77/N74 -> 0.062502806 | P78: =P77/P74 -> 0.067371202 | Q78: =Q77/Q74 -> 0.062847474 | R78: =R77/R74 -> 0.066472376 | S78: =S77/S74 -> 0.069512656 | T78: =T77/T74 -> 0.066512552 | V78: =V77/V74 -> 0.066852713 | W78: =W77/W74 -> 0.065114855 | X78: 0.065 | Y78: 0.065 | Z78: =AVERAGE(V78:Y78) -> 0.065491892 | AB78: 0.067 | AC78: 0.067 | AD78: 0.067 | AE78: 0.067 | AF78: =AVERAGE(AB78:AE78) -> 0.067 | AH78: 0.067 | AJ78: 0.068 | AL78: 0.068
B80: Gross Profit | D80: =IS!P24 -> 4586 | E80: =IS!Q24 -> 4942 | F80: =IS!R24 -> 4891 | G80: =IS!S24 -> 5748 | H80: =IS!T24 -> 20167 | J80: =IS!V24 -> 4707 | K80: =IS!W24 -> 4641 | L80: =IS!X24 -> 4575 | M80: =IS!Y24 -> 5243 | N80: =IS!Z24 -> 19166 | P80: =IS!AB24 -> 4713 | Q80: =IS!AC24 -> 4577 | R80: =IS!AD24 -> 4539 | S80: =IS!AE24 -> 5123 | T80: =IS!AF24 -> 18952 | V80: =IS!AH24 -> 4376 | W80: =IS!AI24 -> 4579 | X80: =X71-X74-X77 -> 5100.5239 | Y80: =Y71-Y74-Y77 -> 5200.5342 | Z80: =SUM(V80:Y80) -> 19256.058 | AB80: =AB71-AB74-AB77 -> 4890.933 | AC80: =AC71-AC74-AC77 -> 4992.8274 | AD80: =AD71-AD74-AD77 -> 5196.6163 | AE80: =AE71-AE74-AE77 -> 5298.5107 | AF80: =SUM(AB80:AE80) -> 20378.887 | AH80: =AH71-AH74-AH77 -> 21006.826 | AJ80: =AJ71-AJ74-AJ77 -> 22727.392 | AL80: =AL71-AL74-AL77 -> 23618.237
B81: % of sales | D81: =D80/D71 -> 0.20842612 | E81: =E80/E71 -> 0.2105308 | F81: =F80/F71 -> 0.20688634 | G81: =G80/G71 -> 0.23563171 | H81: =H80/H71 -> 0.21566216 | J81: =J80/J71 -> 0.2025213 | K81: =K80/K71 -> 0.20342772 | L81: =L80/L71 -> 0.20636925 | M81: =M80/M71 -> 0.23907889 | N81: =N80/N71 -> 0.21258943 | P81: =P80/P71 -> 0.21737927 | Q81: =Q80/Q71 -> 0.20649673 | R81: =R80/R71 -> 0.20880486 | S81: =S80/S71 -> 0.23171559 | T81: =T80/T71 -> 0.21611759 | V81: =V80/V71 -> 0.20278975 | W81: =W80/W71 -> 0.20844904 | X81: =X80/X71 -> 0.22255 | Y81: =Y80/Y71 -> 0.22255 | Z81: =Z80/Z$71 -> 0.21435517 | AB81: =AB80/AB71 -> 0.22109 | AC81: =AC80/AC71 -> 0.22109 | AD81: =AD80/AD71 -> 0.22109 | AE81: =AE80/AE71 -> 0.22109 | AF81: =AF80/AF$71 -> 0.22109 | AH81: =AH80/AH71 -> 0.22109 | AJ81: =AJ80/AJ71 -> 0.23104 | AL81: =AL80/AL71 -> 0.24172
B83: SG&A (Selling, General & Administrative) | D83: =IS!P27 -> 0 | E83: =IS!Q27 -> 0 | F83: =IS!R27 -> 0 | G83: =IS!S27 -> 0 | H83: =IS!T27 -> 0 | J83: =IS!V27 -> 0 | K83: =IS!W27 -> 0 | L83: =IS!X27 -> 0 | M83: =IS!Y27 -> 0 | N83: =IS!Z27 -> 0 | P83: =IS!AB27 -> 0 | Q83: =IS!AC27 -> 0 | R83: =IS!AD27 -> 0 | S83: =IS!AE27 -> 0 | T83: =IS!AF27 -> 0 | V83: =IS!AH27 -> 0 | W83: =IS!AI27 -> 0 | X83: =(X84+Sensitivity!$U$40)*X$71 -> 0 | Y83: =(Y84+Sensitivity!$U$40)*Y$71 -> 0 | Z83: =SUM(V83:Y83) -> 0 | AB83: =(AB84+Sensitivity!$U$40)*AB$71 -> 0 | AC83: =(AC84+Sensitivity!$U$40)*AC$71 -> 0 | AD83: =(AD84+Sensitivity!$U$40)*AD$71 -> 0 | AE83: =(AE84+Sensitivity!$U$40)*AE$71 -> 0 | AF83: =SUM(AB83:AE83) -> 0 | AH83: =(AH84+Sensitivity!$U$40)*AH$71 -> 0 | AJ83: =(AJ84+Sensitivity!$U$40)*AJ$71 -> 0 | AL83: =(AL84+Sensitivity!$U$40)*AL$71 -> 0
B84: % of sales | D84: =D83/D71 -> 0 | E84: =E83/E71 -> 0 | F84: =F83/F71 -> 0 | G84: =G83/G71 -> 0 | H84: =H83/H71 -> 0 | J84: =J83/J71 -> 0 | K84: =K83/K71 -> 0 | L84: =L83/L71 -> 0 | M84: =M83/M71 -> 0 | N84: =N83/N71 -> 0 | P84: =P83/P71 -> 0 | Q84: =Q83/Q71 -> 0 | R84: =R83/R71 -> 0 | S84: =S83/S71 -> 0 | T84: =T83/T71 -> 0 | V84: =V83/V71 -> 0 | W84: =W83/W71 -> 0 | X84: 0 | Y84: 0 | AB84: 0 | AC84: 0 | AD84: 0 | AE84: 0 | AH84: 0 | AJ84: 0 | AL84: 0
B86: R&D (Research & Development) | D86: =IS!P29 -> 0 | E86: =IS!Q29 -> 0 | F86: =IS!R29 -> 0 | G86: =IS!S29 -> 0 | H86: =IS!T29 -> 0 | J86: =IS!V29 -> 0 | K86: =IS!W29 -> 0 | L86: =IS!X29 -> 0 | M86: =IS!Y29 -> 0 | N86: =IS!Z29 -> 0 | P86: =IS!AB29 -> 0 | Q86: =IS!AC29 -> 0 | R86: =IS!AD29 -> 0 | S86: =IS!AE29 -> 0 | T86: =IS!AF29 -> 0 | V86: =IS!AH29 -> 0 | W86: =IS!AI29 -> 0 | X86: =X87*X80 -> 0 | Y86: =Y87*Y80 -> 0 | Z86: =SUM(V86:Y86) -> 0 | AB86: =AB87*AB80 -> 0 | AC86: =AC87*AC80 -> 0 | AD86: =AD87*AD80 -> 0 | AE86: =AE87*AE80 -> 0 | AF86: =SUM(AB86:AE86) -> 0 | AH86: =AH87*AH80 -> 0 | AJ86: =AJ87*AJ80 -> 0 | AL86: =AL87*AL80 -> 0
B87: % of gross profit | D87: =D86/D80 -> 0 | E87: =E86/E80 -> 0 | F87: =F86/F80 -> 0 | G87: =G86/G80 -> 0 | H87: =H86/H80 -> 0 | J87: =J86/J80 -> 0 | K87: =K86/K80 -> 0 | L87: =L86/L80 -> 0 | M87: =M86/M80 -> 0 | N87: =N86/N80 -> 0 | P87: =P86/P80 -> 0 | Q87: =Q86/Q80 -> 0 | R87: =R86/R80 -> 0 | S87: =S86/S80 -> 0 | T87: =T86/T80 -> 0 | V87: =V86/V80 -> 0 | W87: =W86/W80 -> 0 | X87: 0 | Y87: 0 | Z87: =Z86/Z$80 -> 0 | AB87: 0 | AC87: 0 | AD87: 0 | AE87: 0 | AF87: =AF86/AF$80 -> 0 | AH87: 0 | AJ87: 0 | AL87: 0
B89: D&A (Depreciation & Amortization) | D89: =IS!P28 -> 971 | E89: =IS!Q28 -> 995 | F89: =IS!R28 -> 986 | G89: =IS!S28 -> 1018 | H89: =IS!T28 -> 3970 | J89: =IS!V28 -> 1024 | K89: =IS!W28 -> 1046 | L89: =IS!X28 -> 1031 | M89: =IS!Y28 -> 1075 | N89: =IS!Z28 -> 4176 | P89: =IS!AB28 -> 1071 | Q89: =IS!AC28 -> 1040 | R89: =IS!AD28 -> 1072 | S89: =IS!AE28 -> 1104 | T89: =IS!AF28 -> 4287 | V89: =IS!AH28 -> 1078 | W89: =IS!AI28 -> 1063 | X89: =(X119+X122)*X90 -> 1023.8775 | Y89: =(Y119+Y122)*Y90 -> 1026.7393 | Z89: =SUM(V89:Y89) -> 4191.6168 | AB89: =(AB119+AB122)*AB90 -> 959.45219 | AC89: =(AC119+AC122)*AC90 -> 1018.1873 | AD89: =(AD119+AD122)*AD90 -> 1014.9042 | AE89: =(AE119+AE122)*AE90 -> 1043.6882 | AF89: =SUM(AB89:AE89) -> 4036.2319 | AH89: =(AH119+AH122)*AH90 -> 4052.5187 | AJ89: =(AJ119+AJ122)*AJ90 -> 4083.312 | AL89: =(AL119+AL122)*AL90 -> 4120.8738
B90: % of net pp&e and intangibles excl. Goodwill | D90: =D89/(D119+D122) -> 0.016531036 | E90: =E89/(E119+E122) -> 0.016618509 | F90: =F89/(F119+F122) -> 0.016234194 | G90: =G89/(G119+G122) -> 0.016539668 | H90: =H89/(H119+H122) -> 0.064501454 | J90: =J89/(J119+J122) -> 0.016425787 | K90: =K89/(K119+K122) -> 0.016479967 | L90: =L89/(L119+L122) -> 0.016181687 | M90: =M89/(M119+M122) -> 0.016611552 | N90: =N89/(N119+N122) -> 0.064530086 | P90: =P89/(P119+P122) -> 0.016496465 | Q90: =Q89/(Q119+Q122) -> 0.015940407 | R90: =R89/(R119+R122) -> 0.01652052 | S90: =S89/(S119+S122) -> 0.016929919 | T90: =T89/(T119+T122) -> 0.065741451 | V90: =V89/(V119+V122) -> 0.016620157 | W90: =W89/(W119+W122) -> 0.016579066 | X90: 0.016 | Y90: 0.016 | Z90: =Z89/( Z119+Z122) -> 0.065319279 | AB90: 0.015 | AC90: 0.016 | AD90: 0.016 | AE90: 0.0165 | AF90: =AF89/( AF119+AF122) -> 0.063810077 | AH90: 0.065 | AJ90: 0.066 | AL90: 0.0665
B92: Depreciation | D92: =IS!P64 -> 0 | E92: =IS!Q64 -> 0 | F92: =IS!R64 -> 0 | G92: =IS!S64 -> 0 | H92: =IS!T64 -> 0 | J92: =IS!V64 -> 0 | K92: =IS!W64 -> 0 | L92: =IS!X64 -> 0 | M92: =IS!Y64 -> 0 | N92: =IS!Z64 -> 0 | P92: =IS!AB64 -> 0 | Q92: =IS!AC64 -> 0 | R92: =IS!AD64 -> 0 | S92: =IS!AE64 -> 0 | T92: =IS!AF64 -> 0 | V92: =IS!AH64 -> 0 | W92: =IS!AI64 -> 0 | X92: =X93*W119 -> 0 | Y92: =Y93*X119 -> 0 | Z92: =SUM(V92:Y92) -> 0 | AB92: =AB93*Y119 -> 0 | AC92: =AC93*AB119 -> 0 | AD92: =AD93*AC119 -> 0 | AE92: =AE93*AD119 -> 0 | AF92: =SUM(AB92:AE92) -> 0 | AH92: =AH93*AF119 -> 0 | AJ92: =AJ93*AH119 -> 0 | AL92: =AL93*AJ119 -> 0
B93: % of net pp&e | D93: =D92/D119 -> 0 | E93: =E92/E119 -> 0 | F93: =F92/F119 -> 0 | G93: =G92/G119 -> 0 | H93: =H92/H119 -> 0 | J93: =J92/J119 -> 0 | K93: =K92/K119 -> 0 | L93: =L92/L119 -> 0 | M93: =M92/M119 -> 0 | N93: =N92/N119 -> 0 | P93: =P92/P119 -> 0 | Q93: =Q92/Q119 -> 0 | R93: =R92/R119 -> 0 | S93: =S92/S119 -> 0 | T93: =T92/T119 -> 0 | V93: =V92/V119 -> 0 | W93: =W92/W119 -> 0 | X93: 0 | Y93: 0 | Z93: =Z92/Z119 -> 0 | AB93: 0 | AC93: 0 | AD93: 0 | AE93: 0 | AF93: =AF92/AF119 -> 0 | AH93: 0 | AJ93: 0 | AL93: 0
B95: Amortization | D95: =IS!P65 -> 0 | E95: =IS!Q65 -> 0 | F95: =IS!R65 -> 0 | G95: =IS!S65 -> 0 | H95: =IS!T65 -> 0 | J95: =IS!V65 -> 0 | K95: =IS!W65 -> 0 | L95: =IS!X65 -> 0 | M95: =IS!Y65 -> 0 | N95: =IS!Z65 -> 0 | P95: =IS!AB65 -> 0 | Q95: =IS!AC65 -> 0 | R95: =IS!AD65 -> 0 | S95: =IS!AE65 -> 0 | T95: =IS!AF65 -> 0 | V95: =IS!AH65 -> 0 | W95: =IS!AI65 -> 0 | X95: =X96*W122 -> 0 | Y95: =Y96*X122 -> 0 | Z95: =SUM(V95:Y95) -> 0 | AB95: =AB96*Y122 -> 0 | AC95: =AC96*AB122 -> 0 | AD95: =AD96*AC122 -> 0 | AE95: =AE96*AD122 -> 0 | AF95: =SUM(AB95:AE95) -> 0 | AH95: =AH96*AF122 -> 0 | AJ95: =AJ96*AH122 -> 0 | AL95: =AL96*AJ122 -> 0
B96: % of intangibles excl. goodwill | D96: =D95/D122 -> 0 | E96: =E95/E122 -> 0 | F96: =F95/F122 -> 0 | G96: =G95/G122 -> 0 | H96: =H95/H122 -> 0 | J96: =J95/J122 -> 0 | K96: =K95/K122 -> 0 | L96: =L95/L122 -> 0 | M96: =M95/M122 -> 0 | N96: =N95/N122 -> 0 | P96: =P95/P122 -> 0 | Q96: =Q95/Q122 -> 0 | R96: =R95/R122 -> 0 | S96: =S95/S122 -> 0 | T96: =T95/T122 -> 0 | V96: =V95/V122 -> 0 | W96: =W95/W122 -> 0 | X96: 0 | Y96: 0 | Z96: =Z95/Z122 -> 0 | AB96: 0 | AC96: 0 | AD96: 0 | AE96: 0 | AF96: =AF95/AF122 -> 0 | AH96: 0 | AJ96: 0 | AL96: 0
B98: Other Operating (Income) Expenses | D98: =IS!P30+IS!P32 -> 3092 | E98: =IS!Q30+IS!Q32 -> 3020.1646 | F98: =IS!R30+IS!R32 -> 3429 | G98: =IS!S30+IS!S32 -> 3514 | H98: =IS!T30+IS!T32 -> 13302 | J98: =IS!V30+IS!V32 -> 3473 | K98: =IS!W30+IS!W32 -> 3394.8228 | L98: =IS!X30+IS!X32 -> 3410 | M98: =IS!Y30+IS!Y32 -> 3476 | N98: =IS!Z30+IS!Z32 -> 13793 | P98: =IS!AB30+IS!AB32 -> 3123 | Q98: =IS!AC30+IS!AC32 -> 3156 | R98: =IS!AD30+IS!AD32 -> 3182 | S98: =IS!AE30+IS!AE32 -> 3250 | T98: =IS!AF30+IS!AF32 -> 12711 | V98: =IS!AH30+IS!AH32 -> 3168 | W98: =IS!AI30+IS!AI32 -> 3201 | X98: =X99*X$71 -> 3391.9458 | Y98: =Y99*Y$71 -> 3505.1904 | Z98: =SUM(V98:Y98) -> 13266.136 | AB98: =AB99*AB$71 -> 3141.3112 | AC98: =AC99*AC$71 -> 3342.2518 | AD98: =AD99*AD$71 -> 3525.6793 | AE98: =AE99*AE$71 -> 3594.8103 | AF98: =SUM(AB98:AE98) -> 13604.053 | AH98: =AH99*AH$71 -> 13682.134 | AJ98: =AJ99*AJ$71 -> 14362.012 | AL98: =AL99*AL$71 -> 14167.815
B99: % of sales | D99: =D98/D71 -> 0.14052629 | E99: =E98/E71 -> 0.12865999 | F99: =F98/F71 -> 0.14504463 | G99: =G98/G71 -> 0.14405182 | H99: =H98/H71 -> 0.14224912 | J99: =J98/J71 -> 0.14942776 | K99: =K98/K71 -> 0.14880437 | L99: =L98/L71 -> 0.1538184 | M99: =M98/M71 -> 0.15850433 | N99: =N98/N71 -> 0.15299207 | P99: =P98/P71 -> 0.14404317 | Q99: =Q98/Q71 -> 0.14238665 | R99: =R98/R71 -> 0.14637961 | S99: =S98/S71 -> 0.14699896 | T99: =T98/T71 -> 0.14494886 | V99: =V98/V71 -> 0.1468094 | W99: =W98/W71 -> 0.14571858 | X99: 0.148 | Y99: 0.15 | Z99: =Z98/Z$71 -> 0.14767637 | AB99: 0.142 | AC99: 0.148 | AD99: 0.15 | AE99: 0.15 | AF99: =AF98/AF$71 -> 0.14759 | AH99: 0.144 | AJ99: 0.146 | AL99: 0.145
B101: EBIT (Operating Income) | D101: =IS!P33 -> 1494 | E101: =IS!Q33 -> 1921.8354 | F101: =IS!R33 -> 1462 | G101: =IS!S33 -> 2234 | H101: =IS!T33 -> 6865 | J101: =IS!V33 -> 1234 | K101: =IS!W33 -> 1246.1772 | L101: =IS!X33 -> 1165 | M101: =IS!Y33 -> 1767 | N101: =IS!Z33 -> 5373 | P101: =IS!AB33 -> 1590 | Q101: =IS!AC33 -> 1421 | R101: =IS!AD33 -> 1357 | S101: =IS!AE33 -> 1873 | T101: =IS!AF33 -> 6241 | V101: =IS!AH33 -> 1208 | W101: =IS!AI33 -> 1378 | X101: =X80-X83-X86-X89-X98 -> 684.70058 | Y101: =Y80-Y83-Y86-Y89-Y98 -> 668.60451 | Z101: =SUM(V101:Y101) -> 3939.3051 | AB101: =AB80-AB83-AB86-AB89-AB98 -> 790.16964 | AC101: =AC80-AC83-AC86-AC89-AC98 -> 632.38828 | AD101: =AD80-AD83-AD86-AD89-AD98 -> 656.03277 | AE101: =AE80-AE83-AE86-AE89-AE98 -> 660.0122 | AF101: =SUM(AB101:AE101) -> 2738.6029 | AH101: =AH80-AH83-AH86-AH89-AH98 -> 3272.1737 | AJ101: =AJ80-AJ83-AJ86-AJ89-AJ98 -> 4282.0681 | AL101: =AL80-AL83-AL86-AL89-AL98 -> 5329.5476
B102: % of sales | D102: =D101/D71 -> 0.067899832 | E102: =E101/E71 -> 0.08187081 | F102: =F101/F71 -> 0.061841716 | G102: =G101/G71 -> 0.091579897 | H102: =H101/H71 -> 0.073413038 | J102: =J101/J71 -> 0.053093538 | K102: =K101/K71 -> 0.054623354 | L102: =L101/L71 -> 0.052550859 | M102: =M101/M71 -> 0.080574555 | N102: =N101/N71 -> 0.05959736 | P102: =P101/P71 -> 0.073336101 | Q102: =Q101/Q71 -> 0.064110083 | R102: =R101/R71 -> 0.062425246 | S102: =S101/S71 -> 0.084716631 | T102: =T101/T71 -> 0.071168736 | V102: =V101/V71 -> 0.055980351 | W102: =W101/W71 -> 0.062730459 | X102: =X101/X$71 -> 0.029875384 | Y102: =Y101/Y$71 -> 0.028612048 | Z102: =Z101/Z$71 -> 0.043851675 | AB102: =AB101/AB$71 -> 0.035718871 | AC102: =AC101/AC$71 -> 0.028003116 | AD102: =AD101/AD$71 -> 0.027910909 | AE102: =AE101/AE$71 -> 0.02754021 | AF102: =AF101/AF$71 -> 0.029711029 | AH102: =AH101/AH$71 -> 0.034438562 | AJ102: =AJ101/AJ$71 -> 0.043530248 | AL102: =AL101/AL$71 -> 0.054545065
B104: Basic Weighted Average Shares | D104: =IS!P59 -> 266 | E104: =IS!Q59 -> 265 | F104: =IS!R59 -> 261 | G104: =IS!S59 -> 261 | H104: =IS!T59 -> 263 | J104: =IS!V59 -> 259 | K104: =IS!W59 -> 255 | L104: =IS!X59 -> 251 | M104: =IS!Y59 -> 251 | N104: =IS!Z59 -> 254 | P104: =IS!AB59 -> 251 | Q104: =IS!AC59 -> 250 | R104: =IS!AD59 -> 247 | S104: =IS!AE59 -> 248 | T104: =IS!AF59 -> 251 | V104: =IS!AH59 -> 244 | W104: =IS!AI59 -> 242 | X104: =W104+X142 -> 242.33415 | Y104: =X104+Y142 -> 242.50234 | Z104: =AVERAGE(V104:Y104) -> 242.70912 | AB104: =Y104+AB142 -> 242.94754 | AC104: =AB104+AC142 -> 243.24902 | AD104: =AC104+AD142 -> 243.56119 | AE104: =AD104+AE142 -> 243.7195 | AF104: =AVERAGE(AB104:AE104) -> 243.36931 | AH104: =AE104+AH142 -> 244.9381 | AJ104: =AF104+AJ142 -> 244.594 | AL104: =AH104+AL142 -> 246.16107
B105: Diluted Weighted Average Shares | D105: =IS!P60 -> 271 | E105: =IS!Q60 -> 268 | F105: =IS!R60 -> 265 | G105: =IS!S60 -> 261 | H105: =IS!T60 -> 266 | J105: =IS!V60 -> 262 | K105: =IS!W60 -> 256 | L105: =IS!X60 -> 253 | M105: =IS!Y60 -> 253 | N105: =IS!Z60 -> 256 | P105: =IS!AB60 -> 254 | Q105: =IS!AC60 -> 253 | R105: =IS!AD60 -> 250 | S105: =IS!AE60 -> 248 | T105: =IS!AF60 -> 251 | V105: =IS!AH60 -> 247 | W105: =IS!AI60 -> 244 | X105: =W105 -> 244 | Y105: =X105 -> 244 | Z105: =AVERAGE(V105:Y105) -> 244.75 | AB105: =Y105 -> 244 | AC105: =AB105 -> 244 | AD105: =AC105 -> 244 | AE105: =AD105 -> 244 | AF105: =AVERAGE(AB105:AE105) -> 244 | AH105: =AF105 -> 244 | AJ105: =AH105 -> 244 | AL105: =AJ105 -> 244
B107: Balance Sheet | D107: Q1 22 | E107: Q2 22 | F107: Q3 22 | G107: Q4 22 | H107: FY 22 | J107: Q1 23 | K107: Q2 23 | L107: Q3 23 | M107: Q4 23 | N107: FY 23 | P107: Q1 24 | Q107: Q2 24 | R107: Q3 24 | S107: Q4 24 | T107: FY 24 | V107: Q1 25 | W107: Q2 25 | X107: Q3 25 | Y107: Q4 25 | Z107: FY 25 | AB107: Q1 26 | AC107: Q2 26 | AD107: Q3 26 | AE107: Q4 26 | AF107: FY 26 | AH107: FY 27 | AJ107: FY 28 | AL107: FY 29
B110: Accounts Receivable | D110: =BS!P18 -> 11125 | E110: =BS!Q18 -> 12197 | F110: =BS!R18 -> 11668 | G110: =BS!S18 -> 11863 | H110: =BS!T18 -> 11863 | J110: =BS!V18 -> 11055 | K110: =BS!W18 -> 11644 | L110: =BS!X18 -> 10721 | M110: =BS!Y18 -> 10188 | N110: =BS!Z18 -> 10188 | P110: =BS!AB18 -> 10207 | Q110: =BS!AC18 -> 10665 | R110: =BS!AD18 -> 9904 | S110: =BS!AE18 -> 10087 | T110: =BS!AF18 -> 10087 | V110: =BS!AH18 -> 10312 | W110: =BS!AI18 -> 10737 | X110: =X71*X111/92 -> 10961.047 | Y110: =Y71*Y111/92 -> 10921.97 | Z110: =Y110 -> 10921.97 | AB110: =AB71*AB111/90 -> 10323.558 | AC110: =AC71*AC111/91 -> 10670.985 | AD110: =AD71*AD111/92 -> 10985.812 | AE110: =AE71*AE111/92 -> 10940.727 | AF110: =AE110 -> 10940.727 | AH110: =AH71*AH111/365 -> 11193.527 | AJ110: =AJ71*AJ111/366 -> 11825.895 | AL110: =AL71*AL111/365 -> 11510.932
B111: days sales outstanding | D111: =D110/D71*90 -> 45.505158 | E111: =E110/E71*91 -> 47.28325 | F111: =F110/F71*92 -> 45.406539 | G111: =G110/G71*92 -> 44.740346 | H111: =H110/H71*365 -> 46.304164 | J111: =J110/J71*90 -> 42.808278 | K111: =K110/K71*91 -> 46.445341 | L111: =L110/L71*92 -> 44.491497 | M111: =M110/M71*92 -> 42.740356 | N111: =N110/N71*365 -> 41.246964 | P111: =P110/P71*90 -> 42.370278 | Q111: =Q110/Q71*91 -> 43.785924 | R111: =R110/R71*92 -> 41.915908 | S111: =S110/S71*92 -> 41.974038 | T111: =T110/T71*365 -> 41.984594 | V111: =V110/V71*90 -> 43.00848 | W111: =W110/W71*91 -> 44.478855 | X111: 44 | Y111: 43 | Z111: =Z110/Z71*365 -> 44.377253 | AB111: 42 | AC111: 43 | AD111: 43 | AE111: 42 | AF111: =AF110/AF71*365 -> 43.323913 | AH111: 43 | AJ111: 44 | AL111: 43
B113: Inventory | D113: =BS!P19 -> 577 | E113: =BS!Q19 -> 594 | F113: =BS!R19 -> 611 | G113: =BS!S19 -> 637 | H113: =BS!T19 -> 637 | J113: =BS!V19 -> 647 | K113: =BS!W19 -> 655 | L113: =BS!X19 -> 631 | M113: =BS!Y19 -> 604 | N113: =BS!Z19 -> 604 | P113: =BS!AB19 -> 631 | Q113: =BS!AC19 -> 632 | R113: =BS!AD19 -> 640 | S113: =BS!AE19 -> 614 | T113: =BS!AF19 -> 614 | V113: =BS!AH19 -> 611 | W113: =BS!AI19 -> 620 | X113: =X114*X74/92 -> 727.41494 | Y113: =Y114*Y74/92 -> 556.25848 | Z113: =Y113 -> 556.25848 | AB113: =AB114*AB74/92 -> 702.13017 | AC113: =AC114*AC74/92 -> 716.75789 | AD113: =AD114*AD74/92 -> 746.01331 | AE113: =AE114*AE74/92 -> 570.48077 | AF113: =AE113 -> 570.48077 | AH113: =AH114*AH74/365 -> 570.08891 | AJ113: =AJ114*AJ74/366 -> 580.54393 | AL113: =AL114*AL74/365 -> 570.19266
B114: days inventory held | D114: =D113/D74*90 -> 3.1576067 | E114: =E113/E74*91 -> 3.0822832 | F114: =F113/F74*92 -> 3.1643774 | G114: =G113/G74*92 -> 3.3244838 | H114: =H113/H74*365 -> 3.3514234 | J114: =J113/J74*90 -> 3.3253384 | K114: =K113/K74*91 -> 3.4801775 | L114: =L113/L74*92 -> 3.5049206 | M114: =M113/M74*92 -> 3.5593133 | N114: =N113/N74*365 -> 3.2996573 | P114: =P113/P74*90 -> 3.5723721 | Q114: =Q113/Q74*91 -> 3.4754653 | R114: =R113/R74*92 -> 3.65102 | S114: =S113/S74*92 -> 3.5567309 | T114: =T113/T74*365 -> 3.4770534 | V114: =V113/V74*90 -> 3.4102326 | W114: =W113/W74*91 -> 3.456049 | X114: 4 | Y114: 3 | Z114: =Z113/Z74*365 -> 3.065172 | AB114: 4 | AC114: 4 | AD114: 4 | AE114: 3 | AF114: =AF113/AF74*365 -> 3.0945652 | AH114: 3 | AJ114: 3 | AL114: 3
B116: Prepaid expenses and Other Current Assets | D116: =BS!P20 -> 991 | E116: =BS!Q20 -> 1123 | F116: =BS!R20 -> 1122 | G116: =BS!S20 -> 968 | H116: =BS!T20 -> 968 | J116: =BS!V20 -> 1054 | K116: =BS!W20 -> 1272 | L116: =BS!X20 -> 1219 | M116: =BS!Y20 -> 962 | N116: =BS!Z20 -> 962 | P116: =BS!AB20 -> 994 | Q116: =BS!AC20 -> 1091 | R116: =BS!AD20 -> 1236 | S116: =BS!AE20 -> 1005 | T116: =BS!AF20 -> 1005 | V116: =BS!AH20 -> 1228 | W116: =BS!AI20 -> 1335 | X116: =X117*X$71 -> 1347.6109 | Y116: =Y117*Y$71 -> 1051.5571 | Z116: =Y116 -> 1051.5571 | AB116: =AB117*AB$71 -> 1150.3393 | AC116: =AC117*AC$71 -> 1174.3047 | AD116: =AD117*AD$71 -> 1269.2446 | AE116: =AE117*AE$71 -> 1150.3393 | AF116: =AE116 -> 1150.3393 | AH116: =AH117*AH$71 -> 1045.163 | AJ116: =AJ117*AJ$71 -> 1082.0694 | AL116: =AL117*AL$71 -> 1172.5089
B117: % of sales | D117: =D116/D71 -> 0.045039313 | E117: =E116/E71 -> 0.047840164 | F117: =F116/F71 -> 0.047459921 | G117: =G116/G71 -> 0.039681889 | H117: =H116/H71 -> 0.010351613 | J117: =J116/J71 -> 0.045348937 | K117: =K116/K71 -> 0.055755238 | L117: =L116/L71 -> 0.054986693 | M117: =M116/M71 -> 0.043866849 | N117: =N116/N71 -> 0.010670512 | P117: =P116/P71 -> 0.045846594 | Q117: =Q116/Q71 -> 0.049221746 | R117: =R116/R71 -> 0.056858957 | S117: =S116/S71 -> 0.045456601 | T117: =T116/T71 -> 0.011460436 | V117: =V116/V71 -> 0.056907178 | W117: =W116/W71 -> 0.060772978 | X117: 0.0588 | Y117: 0.045 | Z117: =Z116/Z$71 -> 0.011705755 | AB117: 0.052 | AC117: 0.052 | AD117: 0.054 | AE117: 0.048 | AF117: =AF116/AF$71 -> 0.01248 | AH117: 0.011 | AJ117: 0.011 | AL117: 0.012
B119: Net PP&E (Property, Plant and Equipment) | D119: =BS!P24 -> 51895 | E119: =BS!Q24 -> 53171 | F119: =BS!R24 -> 53981 | G119: =BS!S24 -> 54704 | H119: =BS!T24 -> 54704 | J119: =BS!V24 -> 56025 | K119: =BS!W24 -> 57094 | L119: =BS!X24 -> 57259 | M119: =BS!Y24 -> 58045 | N119: =BS!Z24 -> 58045 | P119: =BS!AB24 -> 58501 | Q119: =BS!AC24 -> 58775 | R119: =BS!AD24 -> 58464 | S119: =BS!AE24 -> 58606 | T119: =BS!AF24 -> 58606 | V119: =BS!AH24 -> 58349 | W119: =BS!AI24 -> 57827 | X119: =W119-X120*X147-X150-X92-X77 -> 56761.196 | Y119: =X119-Y120*Y147-Y150-Y92-Y77 -> 55691.645 | Z119: =Y119 -> 55691.645 | AB119: =Y119-AB120*AB147-AB150-AB92-AB77 -> 54638.863 | AC119: =AB119-AC120*AC147-AC150-AC92-AC77 -> 53560.423 | AD119: =AC119-AD120*AD147-AD150-AD92-AD77 -> 52432.981 | AE119: =AD119-AE120*AE147-AE150-AE92-AE77 -> 51294.049 | AF119: =AE119 -> 51294.049 | AH119: =AF119-AH120*AH147-AH150-AH92-AH77 -> 46772.294 | AJ119: =AH119-AJ120*AJ147-AJ150-AJ92-AJ77 -> 42097.754 | AL119: =AJ119-AL120*AL147-AL150-AL92-AL77 -> 37570.893
B120: capex allocation rate | H120: =H119/H71 -> 0.58499444 | N120: =N119/N71 -> 0.64383562 | T120: =T119/T71 -> 0.66830876 | X120: 0.045 | Y120: 0.046 | Z120: =AVERAGE(V120:Y120) -> 0.0455 | AB120: 0.045 | AC120: 0.049 | AD120: 0.043 | AE120: 0.045 | AF120: =AVERAGE(AB120:AE120) -> 0.0455 | AH120: 0.049 | AJ120: 0.052 | AL120: 0.053
B122: Intangibles | D122: =IF($B$122="Intangibles excl. Goodwill",BS!P29,BS!P27) -> 6843 | E122: =IF($B$122="Intangibles excl. Goodwill",BS!Q29,BS!Q27) -> 6702 | F122: =IF($B$122="Intangibles excl. Goodwill",BS!R29,BS!R27) -> 6755 | G122: =IF($B$122="Intangibles excl. Goodwill",BS!S29,BS!S27) -> 6845 | H122: =IF($B$122="Intangibles excl. Goodwill",BS!T29,BS!T27) -> 6845 | J122: =IF($B$122="Intangibles excl. Goodwill",BS!V29,BS!V27) -> 6316 | K122: =IF($B$122="Intangibles excl. Goodwill",BS!W29,BS!W27) -> 6377 | L122: =IF($B$122="Intangibles excl. Goodwill",BS!X29,BS!X27) -> 6455 | M122: =IF($B$122="Intangibles excl. Goodwill",BS!Y29,BS!Y27) -> 6669 | N122: =IF($B$122="Intangibles excl. Goodwill",BS!Z29,BS!Z27) -> 6669 | P122: =IF($B$122="Intangibles excl. Goodwill",BS!AB29,BS!AB27) -> 6422 | Q122: =IF($B$122="Intangibles excl. Goodwill",BS!AC29,BS!AC27) -> 6468 | R122: =IF($B$122="Intangibles excl. Goodwill",BS!AD29,BS!AD27) -> 6425 | S122: =IF($B$122="Intangibles excl. Goodwill",BS!AE29,BS!AE27) -> 6604 | T122: =IF($B$122="Intangibles excl. Goodwill",BS!AF29,BS!AF27) -> 6604 | V122: =IF($B$122="Intangibles excl. Goodwill",BS!AH29,BS!AH27) -> 6512 | W122: =IF($B$122="Intangibles excl. Goodwill",BS!AI29,BS!AI27) -> 6290 | X122: =W122-(1-X120)*X147-X95+X123*X86 -> 7231.1504 | Y122: =X122-(1-Y120)*Y147-Y95+Y123*Y86 -> 8479.559 | Z122: =Y122 -> 8479.559 | AB122: =Y122-(1-AB120)*AB147-AB95+AB123*AB86 -> 9324.6159 | AC122: =AB122-(1-AC120)*AC147-AC95+AC123*AC86 -> 10076.284 | AD122: =AC122-(1-AD120)*AD147-AD95+AD123*AD86 -> 10998.531 | AE122: =AD122-(1-AE120)*AE147-AE95+AE123*AE86 -> 11959.783 | AF122: =AE122 -> 11959.783 | AH122: =AF122-(1-AH120)*AH147-AH95+AH123*AH86 -> 15574.147 | AJ122: =AH122-(1-AJ120)*AJ147-AJ95+AJ123*AJ86 -> 19770.609 | AL122: =AJ122-(1-AL120)*AL147-AL95+AL123*AL86 -> 24397.133
B123: r&d capitalization rate | D123: =IFERROR(BS!P57/FCFF!D122,"") -> 0 | E123: =IFERROR(BS!Q57/FCFF!E122,"") -> 0 | F123: =IFERROR(BS!R57/FCFF!F122,"") -> 0 | G123: =IFERROR(BS!S57/FCFF!G122,"") -> 0 | H123: =IFERROR(BS!T57/FCFF!H122,"") -> 0 | J123: =IFERROR(BS!V57/FCFF!J122,"") -> 0 | K123: =IFERROR(BS!W57/FCFF!K122,"") -> 0 | L123: =IFERROR(BS!X57/FCFF!L122,"") -> 0 | M123: =IFERROR(BS!Y57/FCFF!M122,"") -> 0 | N123: =IFERROR(BS!Z57/FCFF!N122,"") -> 0 | P123: =IFERROR(BS!AB57/FCFF!P122,"") -> 0 | Q123: =IFERROR(BS!AC57/FCFF!Q122,"") -> 0 | R123: =IFERROR(BS!AD57/FCFF!R122,"") -> 0 | S123: =IFERROR(BS!AE57/FCFF!S122,"") -> 0 | T123: =IFERROR(BS!AF57/FCFF!T122,"") -> 0 | V123: =IFERROR(BS!AH57/FCFF!V122,"") -> 0 | W123: =IFERROR(BS!AI57/FCFF!W122,"") -> 0 | X123: 0 | Y123: 0 | Z123: =AVERAGE(V123:Y123) -> 0 | AB123: 0 | AC123: 0 | AD123: 0 | AE123: 0 | AF123: =AVERAGE(AB123:AE123) -> 0 | AH123: 0 | AJ123: 0 | AL123: 0
B125: Accounts Payable | D125: =BS!P37 -> 10522 | E125: =BS!Q37 -> 11396 | F125: =BS!R37 -> 11479 | G125: =BS!S37 -> 11749 | H125: =BS!T37 -> 11749 | J125: =BS!V37 -> 11156 | K125: =BS!W37 -> 11369 | L125: =BS!X37 -> 10987 | M125: =BS!Y37 -> 11070 | N125: =BS!Z37 -> 11070 | P125: =BS!AB37 -> 11078 | Q125: =BS!AC37 -> 11481 | R125: =BS!AD37 -> 10794 | S125: =BS!AE37 -> 10824 | T125: =BS!AF37 -> 10824 | V125: =BS!AH37 -> 10979 | W125: =BS!AI37 -> 11264 | X125: =X126*X74/92 -> 11456.785 | Y125: =Y126*Y74/92 -> 11310.589 | Z125: =Y125 -> 11310.589 | AB125: =AB126*AB74/90 -> 11124.863 | AC125: =AC126*AC74/91 -> 11412.991 | AD125: =AD126*AD74/92 -> 11376.703 | AE125: =AE126*AE74/92 -> 11789.936 | AF125: =AE125 -> 11789.936 | AH125: =AH126*AH74/365 -> 11591.808 | AJ125: =AJ126*AJ74/366 -> 11997.908 | AL125: =AL126*AL74/365 -> 12164.11
B126: days payable outstanding | D126: =D125/D74*90 -> 57.581175 | E126: =E125/E74*91 -> 59.134173 | F126: =F125/F74*92 -> 59.449899 | G126: =G125/G74*92 -> 61.317676 | H126: =H125/H74*365 -> 61.814559 | J126: =J125/J74*90 -> 57.337673 | K126: =K125/K74*91 -> 60.406318 | L126: =L125/L74*92 -> 61.027833 | M126: =M125/M74*92 -> 65.234435 | N126: =N125/N74*365 -> 60.475506 | P126: =P125/P74*90 -> 62.717494 | Q126: =Q125/Q74*91 -> 63.135787 | R126: =R125/R74*92 -> 61.576735 | S126: =S125/S74*92 -> 62.700416 | T126: =T125/T74*365 -> 61.295808 | V126: =V125/V74*90 -> 61.27814 | W126: =W125/W74*91 -> 62.788606 | X126: 63 | Y126: 61 | Z126: =Z125/Z74*365 -> 62.325163 | AB126: 62 | AC126: 63 | AD126: 61 | AE126: 62 | AF126: =AF125/AF74*365 -> 63.954348 | AH126: 61 | AJ126: 62 | AL126: 64
B128: Accrued Expenses and Other Current Liabilities | D128: =BS!P40 -> 0 | E128: =BS!Q40 -> 0 | F128: =BS!R40 -> 0 | G128: =BS!S40 -> 0 | H128: =BS!T40 -> 0 | J128: =BS!V40 -> 0 | K128: =BS!W40 -> 0 | L128: =BS!X40 -> 0 | M128: =BS!Y40 -> 0 | N128: =BS!Z40 -> 0 | P128: =BS!AB40 -> 0 | Q128: =BS!AC40 -> 0 | R128: =BS!AD40 -> 0 | S128: =BS!AE40 -> 0 | T128: =BS!AF40 -> 0 | V128: =BS!AH40 -> 0 | W128: =BS!AI40 -> 0 | X128: =X129*X83 -> 0 | Y128: =Y129*Y83 -> 0 | Z128: =Y128 -> 0 | AB128: =AB129*AB83 -> 0 | AC128: =AC129*AC83 -> 0 | AD128: =AD129*AD83 -> 0 | AE128: =AE129*AE83 -> 0 | AF128: =AE128 -> 0 | AH128: =AH129*AH83 -> 0 | AJ128: =AJ129*AJ83 -> 0 | AL128: =AL129*AL83 -> 0
B129: % of sg&a | D129: =D128/D83 -> #DIV/0! | E129: =E128/E83 -> #DIV/0! | F129: =F128/F83 -> #DIV/0! | G129: =G128/G83 -> #DIV/0! | H129: 0 | J129: =J128/J83 -> #DIV/0! | K129: =K128/K83 -> #DIV/0! | L129: =L128/L83 -> #DIV/0! | M129: =M128/M83 -> #DIV/0! | N129: 0 | P129: 0 | Q129: 0 | R129: 0 | S129: 0 | T129: 0 | V129: 0 | W129: 0 | X129: 0 | Y129: 0 | Z129: =Z128/Z83 -> #DIV/0! | AB129: 0 | AC129: 0 | AD129: 0 | AE129: 0 | AF129: 0 | AH129: 0 | AJ129: 0 | AL129: 0
B131: Cash Flow Statement | D131: Q1 22 | E131: Q2 22 | F131: Q3 22 | G131: Q4 22 | H131: FY 22 | J131: Q1 23 | K131: Q2 23 | L131: Q3 23 | M131: Q4 23 | N131: FY 23 | P131: Q1 24 | Q131: Q2 24 | R131: Q3 24 | S131: Q4 24 | T131: FY 24 | V131: Q1 25 | W131: Q2 25 | X131: Q3 25 | Y131: Q4 25 | Z131: FY 25 | AB131: Q1 26 | AC131: Q2 26 | AD131: Q3 26 | AE131: Q4 26 | AF131: FY 26 | AH131: FY 27 | AJ131: FY 28 | AL131: FY 29
B134: D&A (Depreciation & Amortization) | D134: =CF!P17 -> 971 | E134: =CF!Q17 -> 995 | F134: =CF!R17 -> 986 | G134: =CF!S17 -> 1018 | H134: =CF!T17 -> 3970 | J134: =CF!V17 -> 1024 | K134: =CF!W17 -> 1046 | L134: =CF!X17 -> 1031 | M134: =CF!Y17 -> 1075 | N134: =CF!Z17 -> 4176 | P134: =CF!AB17 -> 1071 | Q134: =CF!AC17 -> 1040 | R134: =CF!AD17 -> 1072 | S134: =CF!AE17 -> 1104 | T134: =CF!AF17 -> 4287 | V134: =CF!AH17 -> 1078 | W134: =CF!AI17 -> 1063 | X134: =X77+X89 -> 2111.3629 | Y134: =Y77+Y89 -> 2135.5478 | Z134: =SUM(V134:Y134) -> 6387.9107 | AB134: =AB77+AB89 -> 2041.4348 | AC134: =AC77+AC89 -> 2122.7112 | AD134: =AD77+AD89 -> 2164.5107 | AE134: =AE77+AE89 -> 2215.8361 | AF134: =SUM(AB134:AE134) -> 8544.4928 | AH134: =AH77+AH89 -> 8699.6934 | AJ134: =AJ77+AJ89 -> 8899.5044 | AL134: =AL77+AL89 -> 8838.2677
B135: % of net pp&e and intangibles excl. Goodwill | D135: =D134/(D122+D119) -> 0.016531036 | E135: =E134/(E122+E119) -> 0.016618509 | F135: =F134/(F122+F119) -> 0.016234194 | G135: =G134/(G122+G119) -> 0.016539668 | H135: =H134/(H122+H119) -> 0.064501454 | J135: =J134/(J122+J119) -> 0.016425787 | K135: =K134/(K122+K119) -> 0.016479967 | L135: =L134/(L122+L119) -> 0.016181687 | M135: =M134/(M122+M119) -> 0.016611552 | N135: =N134/(N122+N119) -> 0.064530086 | P135: =P134/(P122+P119) -> 0.016496465 | Q135: =Q134/(Q122+Q119) -> 0.015940407 | R135: =R134/(R122+R119) -> 0.01652052 | S135: =S134/(S122+S119) -> 0.016929919 | T135: =T134/(T122+T119) -> 0.065741451 | V135: =V134/(V122+V119) -> 0.016620157 | W135: =W134/(W122+W119) -> 0.016579066 | X135: =X134/(X119+X122) -> 0.032993991 | Y135: =Y134/(Y119+Y122) -> 0.033278912 | Z135: =Z134/(Z119+Z122) -> 0.099544816 | AB135: =AB134/(AB119+AB122) -> 0.031915631 | AC135: =AC134/(AC119+AC122) -> 0.033356711 | AD135: =AD134/(AD119+AD122) -> 0.034123587 | AE135: =AE134/(AE119+AE122) -> 0.035030858 | AF135: =AF134/(AF119+AF122) -> 0.13508261 | AH135: =AH134/(AH119+AH122) -> 0.13953793 | AJ135: =AJ134/(AJ119+AJ122) -> 0.1438458 | AL135: =AL134/(AL119+AL122) -> 0.14262626
B137: Stock-Based Compensation Expense | D137: =CF!P18 -> 69 | E137: =CF!Q18 -> 43 | F137: =CF!R18 -> 39 | G137: =CF!S18 -> 39 | H137: =CF!T18 -> 190 | J137: =CF!V18 -> 68 | K137: =CF!W18 -> 40 | L137: =CF!X18 -> 34 | M137: =CF!Y18 -> 40 | N137: =CF!Z18 -> 182 | P137: =CF!AB18 -> 56 | Q137: =CF!AC18 -> 40 | R137: =CF!AD18 -> 34 | S137: =CF!AE18 -> 33 | T137: =CF!AF18 -> 163 | V137: =CF!AH18 -> 48 | W137: =CF!AI18 -> 36 | X137: =X139*X71 -> 45.837106 | Y137: =Y139*Y71 -> 23.367936 | Z137: =SUM(V137:Y137) -> 153.20504 | AB137: =AB139*AB71 -> 66.365729 | AC137: =AC139*AC71 -> 45.165565 | AD137: =AD139*AD71 -> 47.009058 | AE137: =AE139*AE71 -> 23.965402 | AF137: =SUM(AB137:AE137) -> 182.50575 | AH137: =AH139*AH71 -> 190.02964 | AJ137: =AJ139*AJ71 -> 196.73989 | AL137: =AL139*AL71 -> 195.41814
B138: % of sg&a | D138: =D137/D83 -> #DIV/0! | E138: =E137/E83 -> #DIV/0! | F138: =F137/F83 -> #DIV/0! | G138: =G137/G83 -> #DIV/0! | H138: 0 | J138: =J137/J83 -> #DIV/0! | K138: =K137/K83 -> #DIV/0! | L138: =L137/L83 -> #DIV/0! | M138: =M137/M83 -> #DIV/0! | N138: 0 | P138: 0 | Q138: 0 | R138: 0 | S138: 0 | T138: 0 | V138: 0 | W138: 0 | X138: 0 | Y138: 0 | Z138: =Z137/Z83 -> #DIV/0! | AB138: 0 | AC138: 0 | AD138: 0 | AE138: 0 | AF138: =AF137/AF83 -> #DIV/0! | AH138: 0 | AJ138: 0 | AL138: 0
B139: Based of Revenue | D139: =D137/D71 -> 0.003135936 | E139: =E137/E71 -> 0.0018318139 | F139: =F137/F71 -> 0.0016496764 | G139: =G137/G71 -> 0.0015987538 | J139: =J137/J71 -> 0.0029257379 | K139: =K137/K71 -> 0.0017533094 | L139: =L137/L71 -> 0.0015336731 | M139: =M137/M71 -> 0.0018239854 | P139: =P137/P71 -> 0.0025829067 | Q139: =Q137/Q71 -> 0.001804647 | R139: =R137/R71 -> 0.0015640813 | S139: =S137/S71 -> 0.0014926048 | V139: =V137/V71 -> 0.0022243848 | W139: =W137/W71 -> 0.0016388219 | X139: 0.002 | Y139: 0.001 | AB139: 0.003 | AC139: 0.002 | AD139: 0.002 | AE139: 0.001 | AH139: 0.002 | AJ139: 0.002 | AL139: 0.002
...

Sheet Sensitivity
B7: Monte-Carlo Simulations | R7: Tornado Chart – Effect on Price Target
AD28: {=_xlfn.SORTBY(R38:Z44,Z38:Z44,1)} -> SG&A Margin | AE28: 0 | AF28: 0.01 | AG28: 0 | AH28: 248.5 | AI28: 320.05 | AJ28: -35.78 | AK28: 35.77 | AL28: 35.78
AD29: Terminal g | AE29: 0 | AF29: 0.005 | AG29: 0 | AH29: 250.32 | AI29: 326.78 | AJ29: -33.96 | AK29: 42.5 | AL29: 42.5
AD30: Capex Intensity | AE30: 0 | AF30: 0.01 | AG30: 0 | AH30: 240.59 | AI30: 327.96 | AJ30: -43.69 | AK30: 43.68 | AL30: 43.69
AD31: WACC | AE31: 0 | AF31: 0.005 | AG31: 0 | AH31: 230.36 | AI31: 352.95 | AJ31: -53.92 | AK31: 68.67 | AL31: 68.67
R32: Reference Price Target | V32: Base Price Target | Z32: Reference | AD32: COGS Margin | AE32: 0 | AF32: 0.02 | AG32: 0 | AH32: 215.51 | AI32: 353.04 | AJ32: -68.77 | AK32: 68.76 | AL32: 68.77
R33: Gordon PT | T33: =+FCFF!AL211 -> 354.9833 | V33: Base Gordon PT | X33: 284.28 | Z33: Gordon | AD33: EBITDA Exit | AE33: 0 | AF33: 5 | AG33: 0 | AH33: 167.83 | AI33: 398.19 | AJ33: -116.45 | AK33: 113.91 | AL33: 116.45
R34: EBITDA PT | T34: =+FCFF!Z211 -> 271.50078 | V34: Base EBITDA PT | X34: 283.01 | AD34: Revenue Exit | AE34: 0 | AF34: 1 | AG34: 0 | AH34: 121.26 | AI34: 439.01 | AJ34: -163.02 | AK34: 154.73 | AL34: 163.02
R35: Revenue PT | T35: =FCFF!AF211 -> 203.73625 | V35: Base Revenue PT | X35: 278.24
T37: Δ | U37: Δ Applied | V37: PT Low | W37: PT High | X37: Δ Low | Y37: Δ High | Z37: Max
R38: Capex Intensity | T38: 0.01 | V38: 240.59 | W38: 327.96 | X38: {=+V38-_xlfn.IFS($Z$33="EBITDA",$X$34,$Z$33="Revenue",$X$35,$Z$33="Gordon",$X$33)} -> -43.69 | Y38: {=+W38-_xlfn.IFS($Z$33="EBITDA",$X$34,$Z$33="Revenue",$X$35,$Z$33="Gordon",$X$33)} -> 43.68 | Z38: =MAX(ABS(X38),ABS(Y38)) -> 43.69
R39: COGS Margin | T39: 0.02 | V39: 215.51 | W39: 353.04 | X39: {=+V39-_xlfn.IFS($Z$33="EBITDA",$X$34,$Z$33="Revenue",$X$35,$Z$33="Gordon",$X$33)} -> -68.77 | Y39: {=+W39-_xlfn.IFS($Z$33="EBITDA",$X$34,$Z$33="Revenue",$X$35,$Z$33="Gordon",$X$33)} -> 68.76 | Z39: =MAX(ABS(X39),ABS(Y39)) -> 68.77
R40: SG&A Margin | T40: 0.01 | V40: 248.5 | W40: 320.05 | X40: {=+V40-_xlfn.IFS($Z$33="EBITDA",$X$34,$Z$33="Revenue",$X$35,$Z$33="Gordon",$X$33)} -> -35.78 | Y40: {=+W40-_xlfn.IFS($Z$33="EBITDA",$X$34,$Z$33="Revenue",$X$35,$Z$33="Gordon",$X$33)} -> 35.77 | Z40: =MAX(ABS(X40),ABS(Y40)) -> 35.78
R41: WACC | T41: 0.005 | V41: 230.36 | W41: 352.95 | X41: {=+V41-_xlfn.IFS($Z$33="EBITDA",$X$34,$Z$33="Revenue",$X$35,$Z$33="Gordon",$X$33)} -> -53.92 | Y41: {=+W41-_xlfn.IFS($Z$33="EBITDA",$X$34,$Z$33="Revenue",$X$35,$Z$33="Gordon",$X$33)} -> 68.67 | Z41: =MAX(ABS(X41),ABS(Y41)) -> 68.67
R42: Terminal g | T42: 0.005 | V42: 250.32 | W42: 326.78 | X42: {=+V42-_xlfn.IFS($Z$33="EBITDA",$X$34,$Z$33="Revenue",$X$35,$Z$33="Gordon",$X$33)} -> -33.96 | Y42: {=+W42-_xlfn.IFS($Z$33="EBITDA",$X$34,$Z$33="Revenue",$X$35,$Z$33="Gordon",$X$33)} -> 42.5 | Z42: =MAX(ABS(X42),ABS(Y42)) -> 42.5
R43: EBITDA Exit | T43: 5 | V43: 167.83 | W43: 398.19 | X43: {=+V43-_xlfn.IFS($Z$33="EBITDA",$X$34,$Z$33="Revenue",$X$35,$Z$33="Gordon",$X$33)} -> -116.45 | Y43: {=+W43-_xlfn.IFS($Z$33="EBITDA",$X$34,$Z$33="Revenue",$X$35,$Z$33="Gordon",$X$33)} -> 113.91 | Z43: =MAX(ABS(X43),ABS(Y43)) -> 116.45
R44: Revenue Exit | T44: 1 | V44: 121.26 | W44: 439.01 | X44: {=+V44-_xlfn.IFS($Z$33="EBITDA",$X$34,$Z$33="Revenue",$X$35,$Z$33="Gordon",$X$33)} -> -163.02 | Y44: {=+W44-_xlfn.IFS($Z$33="EBITDA",$X$34,$Z$33="Revenue",$X$35,$Z$33="Gordon",$X$33)} -> 154.73 | Z44: =MAX(ABS(X44),ABS(Y44)) -> 163.02

Sheet IS
B7: Income Statement | D7: 2020 | E7: 2020 | F7: 2020 | G7: 2020 | H7: 2020 | J7: 2021 | K7: 2021 | L7: 2021 | M7: 2021 | N7: 2021 | P7: 2022 | Q7: 2022 | R7: 2022 | S7: 2022 | T7: 2022 | V7: 2023 | W7: 2023 | X7: 2023 | Y7: 2023 | Z7: 2023 | AB7: 2024 | AC7: 2024 | AD7: 2024 | AE7: 2024 | AF7: 2024 | AH7: 2025 | AI7: 2025 | AJ7: 2025 | AK7: 2025 | AL7: 2025 | AN7: 2025 | AO7: 2025 | AP7: 2025 | AQ7: 2025 | AR7: 2025
D8: 2020 | J8: 2021 | P8: 2022 | V8: 2023 | AB8: 2024 | AH8: 2025 | AN8: 2026 | AT8: 2027 | AV8: 2028 | AX8: 2029
D9: Q1 | E9: Q2 | F9: Q3 | G9: Q4 | H9: FY | J9: Q1 | K9: Q2 | L9: Q3 | M9: Q4 | N9: FY | P9: Q1 | Q9: Q2 | R9: Q3 | S9: Q4 | T9: FY | V9: Q1 | W9: Q2 | X9: Q3 | Y9: Q4 | Z9: FY | AB9: Q1 | AC9: Q2 | AD9: Q3 | AE9: Q4 | AF9: FY | AH9: Q1 | AI9: Q2 | AJ9: Q3 | AK9: Q4 | AL9: FY | AN9: Q1 | AO9: Q2 | AP9: Q3 | AQ9: Q4 | AR9: FY | AT9: FY | AV9: FY | AX9: FY
B12: Revenue:
B13: Segment 1
B14: Segment 2
B15: Segment 3
B16: Segment 4
B17: Segment 5
B18: Total revenue | D18: 17048 | E18: 17324 | F18: 17487 | G18: 17358 | H18: 69217 | J18: 19321 | K18: 20563 | L18: 21510 | M18: 22565 | N18: 83959 | P18: 22003 | Q18: 23474 | R18: 23641 | S18: 24394 | T18: 93512 | V18: 23242 | W18: 22814 | X18: 22169 | Y18: 21930 | Z18: 90155 | AB18: 21681 | AC18: 22165 | AD18: 21738 | AE18: 22109 | AF18: 87693 | AH18: 21579 | AI18: 21967
A20: x | B20: Cost of revenue:
B21: Cost of goods and services | D21: 12673 | E21: 13151 | F21: 13467 | G21: 12967 | H21: 52258 | J21: 14136 | K21: 15296 | L21: 16379 | M21: 16401 | N21: 62212 | P21: 16446 | Q21: 17537 | R21: 17764 | S21: 17628 | T21: 69375 | V21: 17511 | W21: 17127 | X21: 16563 | Y21: 15612 | Z21: 66813 | AB21: 15897 | AC21: 16548 | AD21: 16127 | AE21: 15882 | AF21: 64454 | AH21: 16125 | AI21: 16325
B22: Depreciation & amortization | D22: 879 | E22: 901 | F22: 908 | G22: 927 | H22: 3615 | J22: 926 | K22: 936 | L22: 956 | M22: 975 | N22: 3793 | P22: 971 | Q22: 995 | R22: 986 | S22: 1018 | T22: 3970 | V22: 1024 | W22: 1046 | X22: 1031 | Y22: 1075 | Z22: 4176 | AB22: 1071 | AC22: 1040 | AD22: 1072 | AE22: 1104 | AF22: 4287 | AH22: 1078 | AI22: 1063
B23: Total cost of revenue | D23: 13552 | E23: 14052 | F23: 14375 | G23: 13894 | H23: 55873 | J23: 15062 | K23: 16232 | L23: 17335 | M23: 17376 | N23: 66005 | P23: 17417 | Q23: 18532 | R23: 18750 | S23: 18646 | T23: 73345 | V23: 18535 | W23: 18173 | X23: 17594 | Y23: 16687 | Z23: 70989 | AB23: 16968 | AC23: 17588 | AD23: 17199 | AE23: 16986 | AF23: 68741 | AH23: 17203 | AI23: 17388
B24: Gross margin | D24: 3496 | E24: 3272 | F24: 3112 | G24: 3464 | H24: 13344 | J24: 4259 | K24: 4331 | L24: 4175 | M24: 5189 | N24: 17954 | P24: 4586 | Q24: 4942 | R24: 4891 | S24: 5748 | T24: 20167 | V24: 4707 | W24: 4641 | X24: 4575 | Y24: 5243 | Z24: 19166 | AB24: 4713 | AC24: 4577 | AD24: 4539 | AE24: 5123 | AF24: 18952 | AH24: 4376 | AI24: 4579
A26: x | B26: Operating expenses:
B27: Selling, general and administrative | D27: 0 | E27: 0 | F27: 0 | G27: 0 | H27: 0 | J27: 0 | K27: 0 | L27: 0 | M27: 0 | N27: 0 | P27: 0 | Q27: 0 | R27: 0 | S27: 0 | T27: 0 | V27: 0 | W27: 0 | X27: 0 | Y27: 0 | Z27: 0 | AB27: 0 | AC27: 0 | AD27: 0 | AE27: 0 | AF27: 0 | AH27: 0 | AI27: 0
B28: Depreciation and amortization | D28: 0 | E28: 0 | F28: 0 | G28: 0 | H28: 0 | J28: 0 | K28: 0 | L28: 0 | M28: 0 | N28: 0 | P28: 971 | Q28: 995 | R28: 986 | S28: 1018 | T28: =SUM(P28:S28) -> 3970 | V28: 1024 | W28: 1046 | X28: 1031 | Y28: 1075 | Z28: =SUM(V28:Y28) -> 4176 | AB28: 1071 | AC28: 1040 | AD28: 1072 | AE28: 1104 | AF28: =SUM(AB28:AE28) -> 4287 | AH28: 1078 | AI28: 1063 | AJ28: 1066 | AL28: =SUM(AH28:AK28) -> 3207
B29: Research and development | D29: 0 | E29: 0 | F29: 0 | G29: 0 | H29: 0 | J29: 0 | K29: 0 | L29: 0 | M29: 0 | N29: 0 | P29: 0 | Q29: 0 | R29: 0 | S29: 0 | T29: 0 | V29: 0 | W29: 0 | X29: 0 | Y29: 0 | Z29: 0 | AB29: 0 | AC29: 0 | AD29: 0 | AE29: 0 | AF29: 0 | AH29: 0 | AI29: 0
B30: Other operating expenses | D30: 2448 | E30: 2588 | F30: 2629 | G30: 1819.0253 | H30: 9428 | J30: 2620 | K30: 2766.1013 | L30: 3111 | M30: 4406.8101 | N30: 12903.911 | P30: 3092 | Q30: 3020.1646 | R30: 3429 | S30: 3514 | T30: 13302 | V30: 3473 | W30: 3394.8228 | X30: 3410 | Y30: 3476 | Z30: 13793 | AB30: 3123 | AC30: 3156 | AD30: 3182 | AE30: 3250 | AF30: 12711 | AH30: 3168 | AI30: 3201
B31: Total operating expenses | D31: 2448 | E31: 2588 | F31: 2629 | G31: 1819.0253 | H31: 9428 | J31: 2620 | K31: 2766.1013 | L31: 3111 | M31: 4406.8101 | N31: 12903.911 | P31: 3092 | Q31: 3020.1646 | R31: 3429 | S31: 3514 | T31: 13302 | V31: 3473 | W31: 3394.8228 | X31: 3410 | Y31: 3476 | Z31: 13793 | AB31: 3123 | AC31: 3156 | AD31: 3182 | AE31: 3250 | AF31: 12711 | AH31: 3168 | AI31: 3201
B32: Other operating income | D32: 0 | E32: 0 | F32: 0 | G32: 0 | H32: 0 | J32: 0 | K32: 0 | L32: 0 | M32: 0 | N32: 0 | P32: 0 | Q32: 0 | R32: 0 | S32: 0 | T32: 0 | V32: 0 | W32: 0 | X32: 0 | Y32: 0 | Z32: 0 | AB32: 0 | AC32: 0 | AD32: 0 | AE32: 0 | AF32: 0 | AH32: 0 | AI32: 0
B33: Operating income | D33: 1048 | E33: 684 | F33: 483 | G33: 1644.9747 | H33: 3916 | J33: 1639 | K33: 1564.8987 | L33: 1064 | M33: 782.1899 | N33: 5050.0886 | P33: 1494 | Q33: 1921.8354 | R33: 1462 | S33: 2234 | T33: 6865 | V33: 1234 | W33: 1246.1772 | X33: 1165 | Y33: 1767 | Z33: 5373 | AB33: 1590 | AC33: 1421 | AD33: 1357 | AE33: 1873 | AF33: 6241 | AH33: 1208 | AI33: 1378
A35: x | B35: Non-operating (income) loss:
B36: Interest expense | D36: 137 | E36: 151 | F36: 155 | G36: 174 | H36: 672 | J36: 184 | K36: 184 | L36: 187 | M36: 186 | N36: 793 | P36: 160 | Q36: 155 | R36: 163 | S36: 158 | T36: 689 | V36: 142 | W36: 127 | X36: 122 | Y36: 303 | Z36: 694 | AB36: 91 | AC36: 97 | AD36: 91 | AE36: 466 | AF36: 745 | AH36: 84 | AI36: 102
B37: Interest income | D37: 0 | E37: 0 | F37: 0 | G37: 0 | H37: 55 | J37: 0 | K37: 0 | L37: 0 | M37: 0 | N37: 52 | P37: 0 | Q37: 0 | R37: 0 | S37: 0 | T37: 53 | V37: 0 | W37: 0 | X37: 0 | Y37: 198 | Z37: 198 | AB37: 0 | AC37: 0 | AD37: 0 | AE37: 370 | AF37: 370 | AH37: 0 | AI37: 0
A38: x | B38: Net interest (income) expense | D38: 137 | E38: 151 | F38: 155 | G38: 174 | H38: 617 | J38: 184 | K38: 184 | L38: 187 | M38: 186 | N38: 741 | P38: 160 | Q38: 155 | R38: 163 | S38: 158 | T38: 636 | V38: 142 | W38: 127 | X38: 122 | Y38: 105 | Z38: 496 | AB38: 91 | AC38: 97 | AD38: 91 | AE38: 96 | AF38: 375 | AH38: 84 | AI38: 102
B39: Foreign exchange (gains) losses | D39: 0 | E39: 0 | F39: 0 | G39: 0 | H39: 0 | J39: 0 | K39: 0 | L39: 0 | M39: 0 | N39: 0 | P39: 0 | Q39: 0 | R39: 0 | S39: 0 | T39: 0 | V39: 0 | W39: 0 | X39: 0 | Y39: 0 | Z39: 0 | AB39: 0 | AC39: 0 | AD39: 0 | AE39: 0 | AF39: 0 | AH39: 0 | AI39: 0
B40: Other non-operating (income) expenses | D40: -156 | E40: -169 | F40: -164 | G40: 620 | H40: 131 | J40: -200 | K40: -125 | L40: -231 | M40: -1395 | N40: -1951 | P40: -219 | Q40: 62 | R40: -212 | S40: -236 | T40: -865 | V40: -105 | W40: -10 | X40: -102 | Y40: -80 | Z40: -297 | AB40: -29 | AC40: -23 | AD40: -31 | AE40: -569 | AF40: -652 | AH40: -60 | AI40: -31
B41: Total non-operating expenses | D41: -19 | E41: -18 | F41: -9 | G41: 794 | H41: 748 | J41: -16 | K41: 59 | L41: -44 | M41: -1209 | N41: -1210 | P41: -59 | Q41: 217 | R41: -49 | S41: -78 | T41: -229 | V41: 37 | W41: 117 | X41: 20 | Y41: 25 | Z41: 199 | AB41: 62 | AC41: 74 | AD41: 60 | AE41: -473 | AF41: -277 | AH41: 24 | AI41: 71
B42: Pre-tax income | D42: 1067 | E42: 702 | F42: 492 | G42: 850.9747 | H42: 3168 | J42: 1655 | K42: 1505.8987 | L42: 1108 | M42: 1991.1899 | N42: 6260.0886 | P42: 1553 | Q42: 1704.8354 | R42: 1511 | S42: 2312 | T42: 7094 | V42: 1197 | W42: 1129.1772 | X42: 1145 | Y42: 1742 | Z42: 5174 | AB42: 1528 | AC42: 1347 | AD42: 1297 | AE42: 2346 | AF42: 6518 | AH42: 1184 | AI42: 1307
A44: x | B44: Tax & net income:
B45: Income tax expenses (benefits) | D45: 267 | E45: 42 | F45: 121 | G45: 187.9747 | H45: 674 | J45: 372 | K45: 202.8987 | L45: 169 | M45: 631.1899 | N45: 1375.0886 | P45: 366 | Q45: 405.8354 | R45: 294 | S45: 513 | T45: 1592 | V45: 292 | W45: 285.7372 | X45: 280 | Y45: 488 | Z45: 1335 | AB45: 369 | AC45: 337 | AD45: 331 | AE45: 639.56 | AF45: 1667 | AH45: 292 | AI45: 317
B46: Net extraordinary losses (gains) | D46: 0 | E46: 0 | F46: 0 | G46: 0 | H46: 0 | J46: 0 | K46: 0 | L46: 0 | M46: 0 | N46: 0 | P46: 0 | Q46: 0 | R46: 0 | S46: 0 | T46: 0 | V46: 0 | W46: 0 | X46: 0 | Y46: 0 | Z46: 0 | AB46: 0 | AC46: 0 | AD46: 0 | AE46: 0 | AF46: 0 | AH46: 0 | AI46: 0
B47: Net income including minority interest | D47: 800 | E47: 660 | F47: 371 | G47: 663 | H47: 2494 | J47: 1283 | K47: 1303 | L47: 939 | M47: 1360 | N47: 4885 | P47: 1187 | Q47: 1299 | R47: 1217 | S47: 1799 | T47: 5502 | V47: 905 | W47: 843.44 | X47: 865 | Y47: 1254 | Z47: 3839 | AB47: 1159 | AC47: 1010 | AD47: 966 | AE47: 1706.44 | AF47: 4851 | AH47: 892 | AI47: 990
A49: x | B49: Attribution:
B50: Preferred dividends | D50: 0 | E50: 0 | F50: 0 | G50: 0 | H50: 0 | J50: 0 | K50: 0 | L50: 0 | M50: 0 | N50: 0 | P50: 0 | Q50: 0 | R50: 0 | S50: 0 | T50: 0 | V50: 0 | W50: 0 | X50: 0 | Y50: 0 | Z50: 0 | AB50: 0 | AC50: 0 | AD50: 0 | AE50: 0 | AF50: 0 | AH50: 0 | AI50: 0
B51: Income attributable to non-controlling interests | D51: 0 | E51: 0 | F51: 0 | G51: 0 | H51: 0 | J51: 0 | K51: 0 | L51: 0 | M51: 0 | N51: 0 | P51: 0 | Q51: 0 | R51: 0 | S51: 0 | T51: 0 | V51: 0 | W51: 0 | X51: 0 | Y51: 0 | Z51: 0 | AB51: 0 | AC51: 0 | AD51: 0 | AE51: 0 | AF51: 0 | AH51: 0 | AI51: 0
B52: Net income attributable to common shareholders | D52: 800 | E52: 660 | F52: 371 | G52: 663 | H52: 2494 | J52: 1283 | K52: 1303 | L52: 939 | M52: 1360 | N52: 4885 | P52: 1187 | Q52: 1299 | R52: 1217 | S52: 1799 | T52: 5502 | V52: 905 | W52: 843.44 | X52: 865 | Y52: 1254 | Z52: 3839 | AB52: 1159 | AC52: 1010 | AD52: 966 | AE52: 1706.44 | AF52: 4851 | AH52: 892 | AI52: 990
A54: x | B54: Earnings per share:
B55: EPS basic | D55: 3.0769 | E55: 2.5287 | F55: 1.4215 | G55: 2.5402 | H55: 9.5556 | J55: 4.8969 | K55: 4.9356 | L55: 3.5703 | M55: 5.0184 | N55: 18.5038 | P55: 4.4624 | Q55: 4.9019 | R55: 4.6628 | S55: 6.8927 | T55: 20.9202 | V55: 3.4942 | W55: 3.3076 | X55: 3.4462 | Y55: 4.996 | Z55: 15.1142 | AB55: 4.6175 | AC55: 4.04 | AD55: 3.9109 | AE55: 6.8808 | AF55: 19.3267 | AH55: 3.6557 | AI55: 4.0909
B56: EPS diluted | D56: 3.0499 | E56: 2.5117 | F56: 1.4137 | G56: 2.5399 | H56: 9.5107 | J56: 4.8645 | K56: 4.8439 | L56: 3.4907 | M56: 5.0055 | N56: 18.159 | P56: 4.3668 | Q56: 4.8315 | R56: 4.5962 | S56: 6.8848 | T56: 20.6308 | V56: 3.4445 | W56: 3.2866 | X56: 3.4215 | Y56: 4.9565 | Z56: 14.9605 | AB56: 4.5489 | AC56: 3.9848 | AD56: 3.858 | AE56: 6.8808 | AF56: 19.3267 | AH56: 3.6068 | AI56: 4.0505
A58: x | B58: Shares used in computing earnings per share:
B59: Basic weighted average shares | D59: 260 | E59: 261 | F59: 261 | G59: 261 | H59: 261 | J59: 262 | K59: 264 | L59: 263 | M59: 271 | N59: 264 | P59: 266 | Q59: 265 | R59: 261 | S59: 261 | T59: 263 | V59: 259 | W59: 255 | X59: 251 | Y59: 251 | Z59: 254 | AB59: 251 | AC59: 250 | AD59: 247 | AE59: 248 | AF59: 251 | AH59: 244 | AI59: 242
B60: Diluted weighted average shares | D60: 262 | E60: 262 | F60: 262 | G60: 261 | H60: 262 | J60: 263 | K60: 269 | L60: 269 | M60: 271 | N60: 268 | P60: 271 | Q60: 268 | R60: 265 | S60: 261 | T60: 266 | V60: 262 | W60: 256 | X60: 253 | Y60: 253 | Z60: 256 | AB60: 254 | AC60: 253 | AD60: 250 | AE60: 248 | AF60: 251 | AH60: 247 | AI60: 244
B62: Additional Items
B64: Depreciation (from opex)
B65: Amortization (form opex)

Sheet BS
AH1: 0
B7: Balance Sheet | D7: 2020 | E7: 2020 | F7: 2020 | G7: 2020 | H7: 2020 | J7: 2021 | K7: 2021 | L7: 2021 | M7: 2021 | N7: 2021 | P7: 2022 | Q7: 2022 | R7: 2022 | S7: 2022 | T7: 2022 | V7: 2023 | W7: 2023 | X7: 2023 | Y7: 2023 | Z7: 2023 | AB7: 2024 | AC7: 2024 | AD7: 2024 | AE7: 2024 | AF7: 2024 | AH7: 2025 | AI7: 2025 | AJ7: 2025 | AK7: 2025 | AL7: 2025 | AN7: 2025 | AO7: 2025 | AP7: 2025 | AQ7: 2025 | AR7: 2025
D8: 2020 | J8: 2021 | P8: 2022 | V8: 2023 | AB8: 2024 | AH8: 2025 | AN8: 2026 | AT8: 2027 | AV8: 2028 | AX8: 2029
D9: Q1 | E9: Q2 | F9: Q3 | G9: Q4 | H9: FY | J9: Q1 | K9: Q2 | L9: Q3 | M9: Q4 | N9: FY | P9: Q1 | Q9: Q2 | R9: Q3 | S9: Q4 | T9: FY | V9: Q1 | W9: Q2 | X9: Q3 | Y9: Q4 | Z9: FY | AB9: Q1 | AC9: Q2 | AD9: Q3 | AE9: Q4 | AF9: FY | AH9: Q1 | AI9: Q2 | AJ9: Q3 | AK9: Q4 | AL9: FY | AN9: Q1 | AO9: Q2 | AP9: Q3 | AQ9: Q4 | AR9: FY | AT9: FY | AV9: FY | AX9: FY
B12: Assets
A14: x | B14: Current assets:
B15: Cash & cash equivalents & short-term investments | D15: 2389 | E15: 2031 | F15: 1766 | G15: 4881 | H15: 4881 | J15: 6954 | K15: 8339 | L15: 8856 | M15: 7087 | N15: 7087 | P15: 6853 | Q15: 6833 | R15: 6065 | S15: 6897 | T15: 6897 | V15: 6850 | W15: 4646 | X15: 5373 | Y15: 6856 | Z15: 6856 | AB15: 7055 | AC15: 6729 | AD15: 5644 | AE15: 6501 | AF15: 6501 | AH15: 5943 | AI15: 5029
B16: Cash & cash equivalents | D16: 0 | E16: 0 | F16: 0 | G16: 0 | H16: 0 | J16: 0 | K16: 0 | L16: 0 | M16: 0 | N16: 0 | P16: 0 | Q16: 0 | R16: 0 | S16: 0 | T16: 0 | V16: 0 | W16: 0 | X16: 0 | Y16: 0 | Z16: 0 | AB16: 0 | AC16: 0 | AD16: 0 | AE16: 0 | AF16: 0 | AH16: 0 | AI16: 0
B17: Short-term investments | D17: 2389 | E17: 2031 | F17: 1766 | G17: 4881 | H17: 4881 | J17: 6954 | K17: 8339 | L17: 8856 | M17: 7087 | N17: 7087 | P17: 6853 | Q17: 6833 | R17: 6065 | S17: 6897 | T17: 6897 | V17: 6850 | W17: 4646 | X17: 5373 | Y17: 6856 | Z17: 6856 | AB17: 7055 | AC17: 6729 | AD17: 5644 | AE17: 6501 | AF17: 6501 | AH17: 5943 | AI17: 5029
B18: Accounts receivable | D18: 9312 | E18: 9709 | F18: 9323 | G18: 10102 | H18: 10102 | J18: 10508 | K18: 11417 | L18: 11481 | M18: 12069 | N18: 12069 | P18: 11125 | Q18: 12197 | R18: 11668 | S18: 11863 | T18: 11863 | V18: 11055 | W18: 11644 | X18: 10721 | Y18: 10188 | Z18: 10188 | AB18: 10207 | AC18: 10665 | AD18: 9904 | AE18: 10087 | AF18: 10087 | AH18: 10312 | AI18: 10737
B19: Inventory | D19: 574 | E19: 576 | F19: 568 | G19: 572 | H19: 572 | J19: 593 | K19: 587 | L19: 583 | M19: 587 | N19: 587 | P19: 577 | Q19: 594 | R19: 611 | S19: 637 | T19: 637 | V19: 647 | W19: 655 | X19: 631 | Y19: 604 | Z19: 604 | AB19: 631 | AC19: 632 | AD19: 640 | AE19: 614 | AF19: 614 | AH19: 611 | AI19: 620
B20: Prepaid expenses and other current assets | D20: 742 | E20: 882 | F20: 884 | G20: 828 | H20: 828 | J20: 848 | K20: 922 | L20: 790 | M20: 837 | N20: 837 | P20: 991 | Q20: 1123 | R20: 1122 | S20: 968 | T20: 968 | V20: 1054 | W20: 1272 | X20: 1219 | Y20: 962 | Z20: 962 | AB20: 994 | AC20: 1091 | AD20: 1236 | AE20: 1005 | AF20: 1005 | AH20: 1228 | AI20: 1335
B21: Total current assets | D21: 13017 | E21: 13198 | F21: 12541 | G21: 16383 | H21: 16383 | J21: 18903 | K21: 21265 | L21: 21710 | M21: 20580 | N21: 20580 | P21: 19546 | Q21: 20747 | R21: 19466 | S21: 20365 | T21: 20365 | V21: 19606 | W21: 18217 | X21: 17944 | Y21: 18610 | Z21: 18610 | AB21: 18887 | AC21: 19117 | AD21: 17424 | AE21: 18207 | AF21: 18207 | AH21: 18094 | AI21: 17721
A23: x | B23: Non-current assets:
B24: Net PP&E (Property, Plant and Equipment) | D24: 45429 | E24: 46505 | F24: 47287 | G24: 47525 | H24: 47525 | J24: 48758 | K24: 49455 | L24: 49954 | M24: 51135 | N24: 51135 | P24: 51895 | Q24: 53171 | R24: 53981 | S24: 54704 | T24: 54704 | V24: 56025 | W24: 57094 | X24: 57259 | Y24: 58045 | Z24: 58045 | AB24: 58501 | AC24: 58775 | AD24: 58464 | AE24: 58606 | AF24: 58606 | AH24: 58349 | AI24: 57827
B25: Gross PP&E (Property, Plant and Equipment) | D25: 75255 | E25: 76812 | F25: 78286 | G25: 78941 | H25: 78941 | J25: 80942 | K25: 82359 | L25: 83667 | M25: 85460 | N25: 85460 | P25: 86956 | Q25: 88992 | R25: 90751 | S25: 91888 | T25: 91888 | V25: 93931 | W25: 95905 | X25: 96745 | Y25: 97971 | Z25: 97971 | AB25: 99319 | AC25: 100524 | AD25: 101080 | AE25: 101506 | AF25: 101506 | AH25: 102252 | AI25: 102479
B26: Accumulated Depreciation | D26: 29826 | E26: 30307 | F26: 30999 | G26: 31416 | H26: 31416 | J26: 32184 | K26: 32904 | L26: 33713 | M26: 34325 | N26: 34325 | P26: 35061 | Q26: 35821 | R26: 36770 | S26: 37184 | T26: 37184 | V26: 37906 | W26: 38811 | X26: 39486 | Y26: 39926 | Z26: 39926 | AB26: 40818 | AC26: 41749 | AD26: 42616 | AE26: 42900 | AF26: 42900 | AH26: 43903 | AI26: 44652
B27: Intangibles | D27: 6821 | E27: 6861 | F27: 6814 | G27: 6694 | H27: 6694 | J27: 6633 | K27: 6702 | L27: 6977 | M27: 7314 | N27: 7314 | P27: 6843 | Q27: 6702 | R27: 6755 | S27: 6845 | T27: 6845 | V27: 6316 | W27: 6377 | X27: 6455 | Y27: 6669 | Z27: 6669 | AB27: 6422 | AC27: 6468 | AD27: 6425 | AE27: 6604 | AF27: 6604 | AH27: 6512 | AI27: 6290
B28: Goodwill | D28: 6821 | E28: 6861 | F28: 6814 | G28: 6372 | H28: 6372 | J28: 6633 | K28: 6702 | L28: 6977 | M28: 6992 | N28: 6992 | P28: 6843 | Q28: 6702 | R28: 6755 | S28: 6544 | T28: 6544 | V28: 6316 | W28: 6377 | X28: 6455 | Y28: 6435 | Z28: 6435 | AB28: 6422 | AC28: 6468 | AD28: 6425 | AE28: 6423 | AF28: 6423 | AH28: 6512 | AI28: 6290
B29: Intangibles excl. Goodwill | D29: 0 | E29: 0 | F29: 0 | G29: 0 | H29: 0 | J29: 0 | K29: 0 | L29: 0 | M29: 0 | N29: 0 | P29: 0 | Q29: 0 | R29: 0 | S29: 0 | T29: 0 | V29: 0 | W29: 0 | X29: 0 | Y29: 0 | Z29: 0 | AB29: 0 | AC29: 0 | AD29: 0 | AE29: 0 | AF29: 0 | AH29: 0 | AI29: 0
B30: Other Non-Current Assets | D30: 3185 | E30: 3390 | F30: 3372 | G30: 2935 | H30: 2935 | J30: 3354 | K30: 3734 | L30: 4152 | M30: 3748 | N30: 3748 | P30: 3764 | Q30: 3627 | R30: 3906 | S30: 4080 | T30: 4080 | V30: 3879 | W30: 3903 | X30: 4117 | Y30: 3819 | Z30: 3819 | AB30: 3766 | AC30: 3691 | AD30: 3801 | AE30: 3590 | AF30: 3590 | AH30: 3756 | AI30: 3643
B31: Total Non-Current Assets | D31: 55435 | E31: 56756 | F31: 57473 | G31: 57154 | H31: 57154 | J31: 58745 | K31: 59891 | L31: 61083 | M31: 62197 | N31: 62197 | P31: 62502 | Q31: 63500 | R31: 64642 | S31: 65629 | T31: 65629 | V31: 66220 | W31: 67374 | X31: 67831 | Y31: 68533 | Z31: 68533 | AB31: 68689 | AC31: 68934 | AD31: 68690 | AE31: 68800 | AF31: 68800 | AH31: 68617 | AI31: 67760
B32: Total Assets | D32: 68452 | E32: 69954 | F32: 70014 | G32: 73537 | H32: 73537 | J32: 77648 | K32: 81156 | L32: 82793 | M32: 82777 | N32: 82777 | P32: 82048 | Q32: 84247 | R32: 84108 | S32: 85994 | T32: 85994 | V32: 85826 | W32: 85591 | X32: 85775 | Y32: 87143 | Z32: 87143 | AB32: 87576 | AC32: 88051 | AD32: 86114 | AE32: 87007 | AF32: 87007 | AH32: 86711 | AI32: 85481
B34: Liabilities & shareholders' equity
A36: x | B36: Current Liabilities:
B37: Accounts payable | D37: 8004 | E37: 8453 | F37: 8088 | G37: 8370 | H37: 8370 | J37: 9084 | K37: 9895 | L37: 10787 | M37: 11306 | N37: 11306 | P37: 10522 | Q37: 11396 | R37: 11479 | S37: 11749 | T37: 11749 | V37: 11156 | W37: 11369 | X37: 10987 | Y37: 11070 | Z37: 11070 | AB37: 11078 | AC37: 11481 | AD37: 10794 | AE37: 10824 | AF37: 10824 | AH37: 10979 | AI37: 11264
B38: Short-term borrowings | D38: 35 | E38: 150 | F38: 300 | G38: 51 | H38: 51 | J38: 87 | K38: 97 | L38: 636 | M38: 146 | N38: 146 | P38: 125 | Q38: 117 | R38: 116 | S38: 82 | T38: 82 | V38: 139 | W38: 172 | X38: 147 | Y38: 126 | Z38: 126 | AB38: 351 | AC38: 334 | AD38: 67 | AE38: 68 | AF38: 68 | AH38: 622 | AI38: 592
B39: Current portion of lease liabilities | D39: 1896 | E39: 1944 | F39: 1937 | G39: 1923 | H39: 1923 | J39: 2024 | K39: 2123 | L39: 2143 | M39: 2208 | N39: 2208 | P39: 2263 | Q39: 2371 | R39: 2395 | S39: 2443 | T39: 2443 | V39: 2470 | W39: 2498 | X39: 2446 | Y39: 2390 | Z39: 2390 | AB39: 2382 | AC39: 2433 | AD39: 2447 | AE39: 2463 | AF39: 2463 | AH39: 2510 | AI39: 2536
B40: Accrued expenses and other current liabilities | D40: 0 | E40: 0 | F40: 0 | G40: 0 | H40: 0 | J40: 0 | K40: 0 | L40: 0 | M40: 0 | N40: 0 | P40: 0 | Q40: 0 | R40: 0 | S40: 0 | T40: 0 | V40: 0 | W40: 0 | X40: 0 | Y40: 0 | Z40: 0 | AB40: 0 | AC40: 0 | AD40: 0 | AE40: 0 | AF40: 0 | AH40: 0 | AI40: 0
B41: Total current liabilities | D41: 9935 | E41: 10547 | F41: 10325 | G41: 10344 | H41: 10344 | J41: 11195 | K41: 12115 | L41: 13566 | M41: 13660 | N41: 13660 | P41: 12910 | Q41: 13884 | R41: 13990 | S41: 14274 | T41: 14274 | V41: 13765 | W41: 14039 | X41: 13580 | Y41: 13586 | Z41: 13586 | AB41: 13811 | AC41: 14248 | AD41: 13308 | AE41: 13355 | AF41: 13355 | AH41: 14111 | AI41: 14392
A43: x | B43: Non-current liabilities:
B44: Long-term borrowings | D44: 18726 | E44: 18599 | F44: 18536 | G44: 21467 | H44: 21467 | J44: 22731 | K44: 22741 | L44: 22281 | M44: 20208 | N44: 20208 | P44: 20050 | Q44: 19876 | R44: 19892 | S44: 19714 | T44: 19714 | V44: 19374 | W44: 19496 | X44: 19583 | Y44: 19653 | Z44: 19653 | AB44: 19415 | AC44: 19487 | AD44: 19690 | AE44: 19704 | AF44: 19704 | AH44: 19240 | AI44: 19013
B45: Long-term operating lease liabilities | D45: 12137 | E45: 12524 | F45: 12669 | G45: 12680 | H45: 12680 | J45: 13187 | K45: 13489 | L45: 13506 | M45: 13900 | N45: 13900 | P45: 13886 | Q45: 14465 | R45: 14951 | S45: 14955 | T45: 14955 | V45: 15662 | W45: 15870 | X45: 15912 | Y45: 16163 | Z45: 16163 | AB45: 16068 | AC45: 15928 | AD45: 15310 | AE45: 15484 | AF45: 15484 | AH45: 15393 | AI45: 15133
B46: Other non-current liabilities | D46: 9488 | E46: 9625 | F46: 9653 | G46: 10751 | H46: 10751 | J46: 11073 | K46: 11772 | L46: 11459 | M46: 10841 | N46: 10841 | P46: 10881 | Q46: 11082 | R46: 10749 | S46: 12112 | T46: 12112 | V46: 11885 | W46: 12071 | X46: 11967 | Y46: 11653 | Z46: 11653 | AB46: 11748 | AC46: 11622 | AD46: 11431 | AE46: 10882 | AF46: 10882 | AH46: 10791 | AI46: 10483
B47: Total non-current liabilities | D47: 40351 | E47: 40748 | F47: 40858 | G47: 44898 | H47: 44898 | J47: 46991 | K47: 48002 | L47: 47246 | M47: 44949 | N47: 44949 | P47: 44817 | Q47: 45423 | R47: 45592 | S47: 46781 | T47: 46781 | V47: 46921 | W47: 47437 | X47: 47462 | Y47: 47469 | Z47: 47469 | AB47: 47231 | AC47: 47037 | AD47: 46431 | AE47: 46070 | AF47: 46070 | AH47: 45424 | AI47: 44629
B48: Total liabilities | D48: 50286 | E48: 51295 | F48: 51183 | G48: 55242 | H48: 55242 | J48: 58186 | K48: 60117 | L48: 60812 | M48: 58609 | N48: 58609 | P48: 57727 | Q48: 59307 | R48: 59582 | S48: 61055 | T48: 61055 | V48: 60686 | W48: 61476 | X48: 61042 | Y48: 61055 | Z48: 61055 | AB48: 61042 | AC48: 61285 | AD48: 59739 | AE48: 59425 | AF48: 59425 | AH48: 59535 | AI48: 59021
A50: x | B50: Shareholders' equity:
B51: Common equity | D51: 18166 | E51: 18659 | F51: 18831 | G51: 18295 | H51: 18295 | J51: 19462 | K51: 21039 | L51: 21981 | M51: 24168 | N51: 24168 | P51: 24321 | Q51: 24940 | R51: 24526 | S51: 24939 | T51: 24939 | V51: 25140 | W51: 24115 | X51: 24733 | Y51: 26088 | Z51: 26088 | AB51: 26534 | AC51: 26766 | AD51: 26375 | AE51: 27582 | AF51: 27582 | AH51: 27176 | AI51: 26460
B52: Preferred equity | D52: 0 | E52: 0 | F52: 0 | G52: 0 | H52: 0 | J52: 0 | K52: 0 | L52: 0 | M52: 0 | N52: 0 | P52: 0 | Q52: 0 | R52: 0 | S52: 0 | T52: 0 | V52: 0 | W52: 0 | X52: 0 | Y52: 0 | Z52: 0 | AB52: 0 | AC52: 0 | AD52: 0 | AE52: 0 | AF52: 0 | AH52: 0 | AI52: 0
B53: Non-controlling interest | D53: 0 | E53: 0 | F53: 0 | G53: 0 | H53: 0 | J53: 0 | K53: 0 | L53: 0 | M53: 0 | N53: 0 | P53: 0 | Q53: 0 | R53: 0 | S53: 0 | T53: 0 | V53: 0 | W53: 0 | X53: 0 | Y53: 0 | Z53: 0 | AB53: 0 | AC53: 0 | AD53: 0 | AE53: 0 | AF53: 0 | AH53: 0 | AI53: 0
B54: Total equity | D54: 18166 | E54: 18659 | F54: 18831 | G54: 18295 | H54: 18295 | J54: 19462 | K54: 21039 | L54: 21981 | M54: 24168 | N54: 24168 | P54: 24321 | Q54: 24940 | R54: 24526 | S54: 24939 | T54: 24939 | V54: 25140 | W54: 24115 | X54: 24733 | Y54: 26088 | Z54: 26088 | AB54: 26534 | AC54: 26766 | AD54: 26375 | AE54: 27582 | AF54: 27582 | AH54: 27176 | AI54: 26460
B55: Total liabilities and shareholders' equity | D55: 68452 | E55: 69954 | F55: 70014 | G55: 73537 | H55: 73537 | J55: 77648 | K55: 81156 | L55: 82793 | M55: 82777 | N55: 82777 | P55: 82048 | Q55: 84247 | R55: 84108 | S55: 85994 | T55: 85994 | V55: 85826 | W55: 85591 | X55: 85775 | Y55: 87143 | Z55: 87143 | AB55: 87576 | AC55: 88051 | AD55: 86114 | AE55: 87007 | AF55: 87007 | AH55: 86711 | AI55: 85481
B57: Capitalized R&D | D57: 0 | E57: 0 | F57: 0 | G57: 0 | H57: 0 | J57: 0 | K57: 0 | L57: 0 | M57: 0 | N57: 0 | P57: 0 | Q57: 0 | R57: 0 | S57: 0 | T57: 0 | V57: 0 | W57: 0 | X57: 0 | Y57: 0 | Z57: 0 | AB57: 0 | AC57: 0 | AD57: 0 | AE57: 0 | AF57: 0 | AH57: 0 | AI57: 0

Sheet CF
A7: x | B7: Cash Flow Statement | D7: 2020 | E7: 2020 | F7: 2020 | G7: 2020 | H7: 2020 | J7: 2021 | K7: 2021 | L7: 2021 | M7: 2021 | N7: 2021 | P7: 2022 | Q7: 2022 | R7: 2022 | S7: 2022 | T7: 2022 | V7: 2023 | W7: 2023 | X7: 2023 | Y7: 2023 | Z7: 2023 | AB7: 2024 | AC7: 2024 | AD7: 2024 | AE7: 2024 | AF7: 2024 | AH7: 2025 | AI7: 2025 | AJ7: 2025 | AK7: 2025 | AL7: 2025 | AN7: 2025 | AO7: 2025 | AP7: 2025 | AQ7: 2025 | AR7: 2025
D8: 2020 | J8: 2021 | P8: 2022 | V8: 2023 | AB8: 2024 | AH8: 2025 | AN8: 2026 | AT8: 2027 | AV8: 2028 | AX8: 2029
D9: Q1 | E9: Q2 | F9: Q3 | G9: Q4 | H9: FY | J9: Q1 | K9: Q2 | L9: Q3 | M9: Q4 | N9: FY | P9: Q1 | Q9: Q2 | R9: Q3 | S9: Q4 | T9: FY | V9: Q1 | W9: Q2 | X9: Q3 | Y9: Q4 | Z9: FY | AB9: Q1 | AC9: Q2 | AD9: Q3 | AE9: Q4 | AF9: FY | AH9: Q1 | AI9: Q2 | AJ9: Q3 | AK9: Q4 | AL9: FY | AN9: Q1 | AO9: Q2 | AP9: Q3 | AQ9: Q4 | AR9: FY | AT9: FY | AV9: FY | AX9: FY
B12: Cash and cash equivalents, beginning balances | D12: 2319 | E12: 2389 | F12: 2031 | G12: 1766 | H12: 4881 | J12: 4881 | K12: 6954 | L12: 8339 | M12: 8856 | N12: 7087 | P12: 7087 | Q12: 6853 | R12: 6833 | S12: 6065 | T12: 6897 | V12: 6897 | W12: 6850 | X12: 4646 | Y12: 5373 | Z12: 6856 | AB12: 6856 | AC12: 7055 | AD12: 6729 | AE12: 5644 | AF12: 6501 | AH12: 6501 | AI12: 5943
A14: x | B14: Operating activities:
B15: Net income | D15: 745 | E15: 560 | F15: 315 | G15: -334 | H15: 1286 | J15: 1245 | K15: 1226 | L15: 892 | M15: 1868 | N15: 5231 | P15: 1112 | Q15: 1044 | R15: 1112 | S15: 558 | T15: 3826 | V15: 875 | W15: 788 | X15: 771 | Y15: 1538 | Z15: 3972 | AB15: 1078 | AC15: 900 | AD15: 879 | AE15: 1474 | AF15: 4331 | AH15: 794 | AI15: 741
B16: Adjustments to reconcile to cash from operations:
B17: Depreciation and amortization | D17: 879 | E17: 901 | F17: 908 | G17: 927 | H17: 3615 | J17: 926 | K17: 936 | L17: 956 | M17: 975 | N17: 3793 | P17: 971 | Q17: 995 | R17: 986 | S17: 1018 | T17: 3970 | V17: 1024 | W17: 1046 | X17: 1031 | Y17: 1075 | Z17: 4176 | AB17: 1071 | AC17: 1040 | AD17: 1072 | AE17: 1104 | AF17: 4287 | AH17: 1078 | AI17: 1063
B18: Stock-based compensation expense | D18: 67 | E18: 37 | F18: 33 | G18: 31 | H18: 168 | J18: 75 | K18: 46 | L18: 40 | M18: 39 | N18: 200 | P18: 69 | Q18: 43 | R18: 39 | S18: 39 | T18: 190 | V18: 68 | W18: 40 | X18: 34 | Y18: 40 | Z18: 182 | AB18: 56 | AC18: 40 | AD18: 34 | AE18: 33 | AF18: 163 | AH18: 48 | AI18: 36
B19: Other | D19: 863 | E19: 663 | F19: 709 | G19: 1287 | H19: 3373 | J19: 699 | K19: 1057 | L19: 744 | M19: -31 | N19: 2469 | P19: 1062 | Q19: 999 | R19: 1242 | S19: 1062 | T19: 4365 | V19: 922 | W19: 976 | X19: 1025 | Y19: 64 | Z19: 3201 | AB19: 808 | AC19: 879 | AD19: 827 | AE19: 46 | AF19: 2560 | AH19: 725 | AI19: 1158
B20: Changes in working capital:
B21: Accounts receivable | D21: -267 | E21: -417 | F21: 180 | G21: -827 | H21: -1331 | J21: -387 | K21: -713 | L21: -87 | M21: -202 | N21: -1389 | P21: 726 | Q21: -1245 | R21: 453 | S21: -244 | T21: -310 | V21: 259 | W21: -771 | X21: 885 | Y21: 409 | Z21: 782 | AB21: -126 | AC21: -561 | AD21: 577 | AE21: -160 | AF21: -270 | AH21: -305 | AI21: -774
B22: Inventories | D22: 0 | E22: 0 | F22: 0 | G22: 0 | H22: 0 | J22: 0 | K22: 0 | L22: 0 | M22: 0 | N22: 0 | P22: 0 | Q22: 0 | R22: 0 | S22: 0 | T22: 0 | V22: 0 | W22: 0 | X22: 0 | Y22: 0 | Z22: 0 | AB22: 0 | AC22: 0 | AD22: 0 | AE22: 0 | AF22: 0 | AH22: 0 | AI22: 0
B23: Accounts payable | D23: 0 | E23: 0 | F23: 0 | G23: 0 | H23: 0 | J23: 0 | K23: 0 | L23: 0 | M23: 0 | N23: 0 | P23: 0 | Q23: 0 | R23: 0 | S23: 0 | T23: 0 | V23: 0 | W23: 0 | X23: 0 | Y23: 0 | Z23: 0 | AB23: 0 | AC23: 0 | AD23: 0 | AE23: 0 | AF23: 0 | AH23: 0 | AI23: 0
B24: Other | D24: -1655 | E24: -198 | F24: -908 | G24: 766 | H24: -1846 | J24: 168 | K24: 73 | L24: -343 | M24: 133 | N24: 31 | P24: -1787 | Q24: -31 | R24: -1309 | S24: 1108 | T24: -2019 | V24: -1473 | W24: -521 | X24: -1606 | Y24: 361 | Z24: -3283 | AB24: -601 | AC24: -484 | AD24: -1745 | AE24: 234 | AF24: -2596 | AH24: -1105 | AI24: -870
B25: Cash provided by operating activities | D25: 565 | E25: 1509 | F25: 1204 | G25: 1819 | H25: 5097 | J25: 2651 | K25: 2579 | L25: 2162 | M25: 2743 | N25: 10135 | P25: 2084 | Q25: 1762 | R25: 2484 | S25: 3502 | T25: 9832 | V25: 1607 | W25: 1518 | X25: 2106 | Y25: 3447 | Z25: 8848 | AB25: 2230 | AC25: 1774 | AD25: 1610 | AE25: 2698 | AF25: 8312 | AH25: 1187 | AI25: 1318
A27: x | B27: Investing activities:
B28: Purchase of fixed assets and intangibles | D28: -1419 | E28: -1847 | F28: -1439 | G28: -1163 | H28: -5868 | J28: -1424 | K28: -1402 | L28: -1376 | M28: -1682 | N28: -5884 | P28: -1570 | Q28: -1573 | R28: -1236 | S28: -2384 | T28: -6763 | V28: -1284 | W28: -1858 | X28: -1278 | Y28: -1754 | Z28: -6174 | AB28: -1290 | AC28: -1305 | AD28: -1379 | AE28: -1202 | AF28: -5176 | AH28: -767 | AI28: -818
B29: Disposal of fixed assets and intangibles | D29: 0 | E29: 4 | F29: 11 | G29: 7 | H29: 22 | J29: 6 | K29: 8 | L29: 74 | M29: 14 | N29: 102 | P29: 20 | Q29: 11 | R29: 40 | S29: 23 | T29: 94 | V29: 10 | W29: 10 | X29: 52 | Y29: 12 | Z29: 84 | AB29: 12 | AC29: 50 | AD29: 32 | AE29: 20 | AF29: 114 | AH29: 13 | AI29: 21
B30: Acquisitions | D30: 0 | E30: 0 | F30: 0 | G30: 0 | H30: 0 | J30: 0 | K30: 0 | L30: -225 | M30: -3 | N30: -228 | P30: 0 | Q30: 0 | R30: -145 | S30: -2 | T30: -147 | V30: 0 | W30: 0 | X30: 0 | Y30: 0 | Z30: 0 | AB30: -2 | AC30: -73 | AD30: -35 | AE30: -28 | AF30: -138 | AH30: 0 | AI30: -46
B31: Divestitures | D31: 0 | E31: 0 | F31: 0 | G31: 0 | H31: 0 | J31: 0 | K31: 0 | L31: 0 | M31: 0 | N31: 0 | P31: 0 | Q31: 0 | R31: 0 | S31: 0 | T31: 0 | V31: 0 | W31: 0 | X31: 0 | Y31: 0 | Z31: 0 | AB31: 0 | AC31: 0 | AD31: 0 | AE31: 0 | AF31: 0 | AH31: 0 | AI31: 0
B32: Joint Ventures | D32: 0 | E32: 0 | F32: 0 | G32: 0 | H32: 0 | J32: 0 | K32: 0 | L32: 0 | M32: 0 | N32: 0 | P32: 0 | Q32: 0 | R32: 0 | S32: 0 | T32: 0 | V32: 0 | W32: 0 | X32: 0 | Y32: 0 | Z32: 0 | AB32: 0 | AC32: 0 | AD32: 0 | AE32: 0 | AF32: 0 | AH32: 0 | AI32: 0
B33: Increase in long-term investments | D33: 0 | E33: 0 | F33: 0 | G33: 0 | H33: 0 | J33: 0 | K33: 0 | L33: 0 | M33: 0 | N33: 0 | P33: 0 | Q33: 0 | R33: 0 | S33: 0 | T33: 0 | V33: 0 | W33: 0 | X33: 0 | Y33: 0 | Z33: 0 | AB33: 0 | AC33: 0 | AD33: 0 | AE33: 0 | AF33: 0 | AH33: 0 | AI33: 0
B34: Decrease in long-term investments | D34: 0 | E34: 0 | F34: 0 | G34: 0 | H34: 0 | J34: 0 | K34: 0 | L34: 0 | M34: 0 | N34: 0 | P34: 0 | Q34: 0 | R34: 0 | S34: 0 | T34: 0 | V34: 0 | W34: 0 | X34: 0 | Y34: 0 | Z34: 0 | AB34: 0 | AC34: 0 | AD34: 0 | AE34: 0 | AF34: 0 | AH34: 0 | AI34: 0
B35: Other investing inflows/(outflows) | D35: 0 | E35: 0 | F35: 0 | G35: 0 | H35: 0 | J35: 0 | K35: 0 | L35: 0 | M35: 0 | N35: 0 | P35: 0 | Q35: 0 | R35: 0 | S35: 0 | T35: 0 | V35: -35 | W35: -43 | X35: -4 | Y35: -2 | Z35: -84 | AB35: 0 | AC35: 0 | AD35: 24 | AE35: -24 | AF35: 0 | AH35: -48 | AI35: 39
B36: Cash provided by/(used in) investing activities | D36: -1419 | E36: -1843 | F36: -1428 | G36: -1156 | H36: -5846 | J36: -1418 | K36: -1394 | L36: -1527 | M36: -1671 | N36: -6010 | P36: -1550 | Q36: -1562 | R36: -1341 | S36: -2363 | T36: -6816 | V36: -1309 | W36: -1891 | X36: -1230 | Y36: -1744 | Z36: -6174 | AB36: -1280 | AC36: -1328 | AD36: -1358 | AE36: -1234 | AF36: -5200 | AH36: -802 | AI36: -804
A38: x | B38: Financing activities:
B39: Payment of dividends | D39: -170 | E39: -169 | F39: -170 | G39: -170 | H39: -679 | J39: -170 | K39: -171 | L39: -172 | M39: -173 | N39: -686 | P39: -200 | Q39: -200 | R39: -198 | S39: -195 | T39: -793 | V39: -299 | W39: -299 | X39: -290 | Y39: -289 | Z39: -1177 | AB39: -318 | AC39: -317 | AD39: -314 | AE39: -310 | AF39: -1259 | AH39: -339 | AI39: -337
B40: Issuance (repurchase) of common shares | D40: 9 | E40: 14 | F40: 12 | G40: 26 | H40: 61 | J40: 82 | K40: 349 | L40: 51 | M40: 258 | N40: 740 | P40: -465 | Q40: -172 | R40: -1460 | S40: 33 | T40: -2064 | V40: 81 | W40: -1492 | X40: 25 | Y40: 117 | Z40: -1269 | AB40: -343 | AC40: -446 | AD40: -946 | AE40: -274 | AF40: -2009 | AH40: -596 | AI40: -984
B41: Cash from (repayment) of short-term debt | D41: 0 | E41: 150 | F41: 148 | G41: 0 | H41: 0 | J41: 0 | K41: 0 | L41: 0 | M41: 0 | N41: 0 | P41: 0 | Q41: 0 | R41: 0 | S41: 0 | T41: 0 | V41: 0 | W41: 0 | X41: 0 | Y41: 0 | Z41: 0 | AB41: 0 | AC41: 0 | AD41: 0 | AE41: 0 | AF41: 0 | AH41: 0 | AI41: 0
B42: Proceeds from issuance of long-term debt | D42: 0 | E42: 0 | F42: 0 | G42: 0 | H42: 6556 | J42: 0 | K42: 0 | L42: 0 | M42: 4212 | N42: 4212 | P42: 0 | Q42: 0 | R42: 0 | S42: 0 | T42: 0 | V42: 0 | W42: 0 | X42: 0 | Y42: 0 | Z42: 0 | AB42: 0 | AC42: 0 | AD42: 0 | AE42: 0 | AF42: 0 | AH42: 0 | AI42: 0
B43: Repayments of long-term debt | D43: 0 | E43: -36 | F43: -24 | G43: 0 | H43: -2548 | J43: -45 | K43: -30 | L43: -30 | M43: -6213 | N43: -6318 | P43: -64 | Q43: -8 | R43: -41 | S43: -48 | T43: -161 | V43: -29 | W43: -3 | X43: -91 | Y43: -29 | Z43: -152 | AB43: -66 | AC43: -28 | AD43: -49 | AE43: -4 | AF43: -147 | AH43: -34 | AI43: -13
B44: Other financing inflows/(outflows) | D44: 1103 | E44: 0 | F44: 0 | G44: 2658 | H44: -9 | J44: 958 | K44: 0 | L44: -1 | M44: -995 | N44: -38 | P44: -1 | Q44: 1 | R44: 0 | S44: -1 | T44: -1 | V44: 0 | W44: 1 | X44: 0 | Y44: 0 | Z44: 1 | AB44: 0 | AC44: 0 | AD44: -7 | AE44: -4 | AF44: -11 | AH44: 0 | AI44: -6
B45: Cash provided by/(used in) financing activities | D45: 942 | E45: -41 | F45: -34 | G45: 2514 | H45: 3381 | J45: 825 | K45: 148 | L45: -152 | M45: -2911 | N45: -2090 | P45: -730 | Q45: -379 | R45: -1699 | S45: -211 | T45: -3019 | V45: -247 | W45: -1793 | X45: -356 | Y45: -201 | Z45: -2597 | AB45: -727 | AC45: -791 | AD45: -1316 | AE45: -592 | AF45: -3426 | AH45: -969 | AI45: -1340
A47: x | B47: Effects of foreign exchange | D47: -18 | E47: 17 | F47: -7 | G47: -62 | H47: -70 | J47: 15 | K47: 52 | L47: 34 | M47: 70 | N47: 171 | P47: -38 | Q47: -77 | R47: 24 | S47: -96 | T47: -187 | V47: -98 | W47: -38 | X47: 37 | Y47: -19 | Z47: -118 | AB47: -24 | AC47: 19 | AD47: -21 | AE47: -15 | AF47: -41 | AH47: 26 | AI47: -88
A49: x | B49: Increase/(Decrease) in cash and cash equivalents | D49: 70 | E49: -358 | F49: -265 | G49: 3115 | H49: 2562 | J49: 2073 | K49: 1385 | L49: 517 | M49: -1769 | N49: 2206 | P49: -234 | Q49: -256 | R49: -532 | S49: 832 | T49: -190 | V49: -47 | W49: -2204 | X49: 557 | Y49: 1483 | Z49: -41 | AB49: 199 | AC49: -326 | AD49: -1085 | AE49: 857 | AF49: -355 | AH49: -558 | AI49: -914
B50: Cash and cash equivalents, ending balances | D50: 2389 | E50: 2031 | F50: 1766 | G50: 4881 | H50: 4881 | J50: 6954 | K50: 8339 | L50: 8856 | M50: 7087 | N50: 7087 | P50: 6853 | Q50: 6833 | R50: 6065 | S50: 6897 | T50: 6897 | V50: 6850 | W50: 4646 | X50: 5373 | Y50: 6856 | Z50: 6856 | AB50: 7055 | AC50: 6729 | AD50: 5644 | AE50: 6501 | AF50: 6501 | AH50: 5943 | AI50: 5029

Sheet Error Check
B7: Income Statement – Sum of the Quarters = FY | D7: =F7 -> 2020 | E7: =F7 -> 2020 | F7: 2020 | G7: =F7 -> 2020 | H7: =F7 -> 2020 | J7: =L7 -> 2021 | K7: =L7 -> 2021 | L7: 2021 | M7: =L7 -> 2021 | N7: =L7 -> 2021 | P7: =R7 -> 2022 | Q7: =R7 -> 2022 | R7: 2022 | S7: =R7 -> 2022 | T7: =R7 -> 2022 | V7: =X7 -> 2023 | W7: =X7 -> 2023 | X7: 2023 | Y7: =X7 -> 2023 | Z7: =X7 -> 2023 | AB7: =AD7 -> 2024 | AC7: =AD7 -> 2024 | AD7: 2024 | AE7: =AD7 -> 2024 | AF7: =AD7 -> 2024 | AH7: =AJ7 -> 2025 | AI7: =AJ7 -> 2025 | AJ7: 2025 | AK7: =AJ7 -> 2025 | AL7: =AJ7 -> 2025 | AN7: =AP7 -> 2025 | AO7: =AP7 -> 2025 | AP7: 2025 | AQ7: =AP7 -> 2025 | AR7: =AP7 -> 2025
D8: 2020 | J8: =D8+1 -> 2021 | P8: =J8+1 -> 2022 | V8: =P8+1 -> 2023 | AB8: =V8+1 -> 2024 | AH8: =AB8+1 -> 2025 | AN8: =AH8+1 -> 2026 | AT8: =AN8+1 -> 2027 | AV8: =+AT8+1 -> 2028 | AX8: =+AV8+1 -> 2029
D9: Q1 | E9: Q2 | F9: Q3 | G9: Q4 | H9: FY | J9: Q1 | K9: Q2 | L9: Q3 | M9: Q4 | N9: FY | P9: Q1 | Q9: Q2 | R9: Q3 | S9: Q4 | T9: FY | V9: Q1 | W9: Q2 | X9: Q3 | Y9: Q4 | Z9: FY | AB9: Q1 | AC9: Q2 | AD9: Q3 | AE9: Q4 | AF9: FY | AH9: Q1 | AI9: Q2 | AJ9: Q3 | AK9: Q4 | AL9: FY | AN9: Q1 | AO9: Q2 | AP9: Q3 | AQ9: Q4 | AR9: FY | AT9: FY | AV9: FY | AX9: FY
A12: x | B12: Revenue:
B13: Segment 1 | H13: =IF(ROUND(SUM(IS!D13:G13),1)=ROUND(IS!H13,1),"OK","ERROR") -> OK | N13: =IF(ROUND(SUM(IS!J13:M13),1)=ROUND(IS!N13,1),"OK","ERROR") -> OK | T13: =IF(ROUND(SUM(IS!P13:S13),1)=ROUND(IS!T13,1),"OK","ERROR") -> OK | Z13: =IF(ROUND(SUM(IS!V13:Y13),1)=ROUND(IS!Z13,1),"OK","ERROR") -> OK | AF13: =IF(ROUND(SUM(IS!AB13:AE13),1)=ROUND(IS!AF13,1),"OK","ERROR") -> OK | AL13: =IF(ROUND(SUM(IS!AH13:AK13),1)=ROUND(IS!AL13,1),"OK","ERROR") -> OK | AR13: =IF(ROUND(SUM(IS!AN13:AQ13),1)=ROUND(IS!AR13,1),"OK","ERROR") -> OK
B14: Segment 2 | H14: =IF(ROUND(SUM(IS!D14:G14),1)=ROUND(IS!H14,1),"OK","ERROR") -> OK | N14: =IF(ROUND(SUM(IS!J14:M14),1)=ROUND(IS!N14,1),"OK","ERROR") -> OK | T14: =IF(ROUND(SUM(IS!P14:S14),1)=ROUND(IS!T14,1),"OK","ERROR") -> OK | Z14: =IF(ROUND(SUM(IS!V14:Y14),1)=ROUND(IS!Z14,1),"OK","ERROR") -> OK | AF14: =IF(ROUND(SUM(IS!AB14:AE14),1)=ROUND(IS!AF14,1),"OK","ERROR") -> OK | AL14: =IF(ROUND(SUM(IS!AH14:AK14),1)=ROUND(IS!AL14,1),"OK","ERROR") -> OK | AR14: =IF(ROUND(SUM(IS!AN14:AQ14),1)=ROUND(IS!AR14,1),"OK","ERROR") -> OK
B15: Segment 3 | H15: =IF(ROUND(SUM(IS!D15:G15),1)=ROUND(IS!H15,1),"OK","ERROR") -> OK | N15: =IF(ROUND(SUM(IS!J15:M15),1)=ROUND(IS!N15,1),"OK","ERROR") -> OK | T15: =IF(ROUND(SUM(IS!P15:S15),1)=ROUND(IS!T15,1),"OK","ERROR") -> OK | Z15: =IF(ROUND(SUM(IS!V15:Y15),1)=ROUND(IS!Z15,1),"OK","ERROR") -> OK | AF15: =IF(ROUND(SUM(IS!AB15:AE15),1)=ROUND(IS!AF15,1),"OK","ERROR") -> OK | AL15: =IF(ROUND(SUM(IS!AH15:AK15),1)=ROUND(IS!AL15,1),"OK","ERROR") -> OK | AR15: =IF(ROUND(SUM(IS!AN15:AQ15),1)=ROUND(IS!AR15,1),"OK","ERROR") -> OK
B16: Segment 4 | H16: =IF(ROUND(SUM(IS!D16:G16),1)=ROUND(IS!H16,1),"OK","ERROR") -> OK | N16: =IF(ROUND(SUM(IS!J16:M16),1)=ROUND(IS!N16,1),"OK","ERROR") -> OK | T16: =IF(ROUND(SUM(IS!P16:S16),1)=ROUND(IS!T16,1),"OK","ERROR") -> OK | Z16: =IF(ROUND(SUM(IS!V16:Y16),1)=ROUND(IS!Z16,1),"OK","ERROR") -> OK | AF16: =IF(ROUND(SUM(IS!AB16:AE16),1)=ROUND(IS!AF16,1),"OK","ERROR") -> OK | AL16: =IF(ROUND(SUM(IS!AH16:AK16),1)=ROUND(IS!AL16,1),"OK","ERROR") -> OK | AR16: =IF(ROUND(SUM(IS!AN16:AQ16),1)=ROUND(IS!AR16,1),"OK","ERROR") -> OK
B17: Segment 5 | H17: =IF(ROUND(SUM(IS!D17:G17),1)=ROUND(IS!H17,1),"OK","ERROR") -> OK | N17: =IF(ROUND(SUM(IS!J17:M17),1)=ROUND(IS!N17,1),"OK","ERROR") -> OK | T17: =IF(ROUND(SUM(IS!P17:S17),1)=ROUND(IS!T17,1),"OK","ERROR") -> OK | Z17: =IF(ROUND(SUM(IS!V17:Y17),1)=ROUND(IS!Z17,1),"OK","ERROR") -> OK | AF17: =IF(ROUND(SUM(IS!AB17:AE17),1)=ROUND(IS!AF17,1),"OK","ERROR") -> OK | AL17: =IF(ROUND(SUM(IS!AH17:AK17),1)=ROUND(IS!AL17,1),"OK","ERROR") -> OK | AR17: =IF(ROUND(SUM(IS!AN17:AQ17),1)=ROUND(IS!AR17,1),"OK","ERROR") -> OK
B18: Total revenue | H18: =IF(ROUND(SUM(IS!D18:G18),1)=ROUND(IS!H18,1),"OK","ERROR") -> OK | N18: =IF(ROUND(SUM(IS!J18:M18),1)=ROUND(IS!N18,1),"OK","ERROR") -> OK | T18: =IF(ROUND(SUM(IS!P18:S18),1)=ROUND(IS!T18,1),"OK","ERROR") -> OK | Z18: =IF(ROUND(SUM(IS!V18:Y18),1)=ROUND(IS!Z18,1),"OK","ERROR") -> OK | AF18: =IF(ROUND(SUM(IS!AB18:AE18),1)=ROUND(IS!AF18,1),"OK","ERROR") -> OK | AL18: =IF(ROUND(SUM(IS!AH18:AK18),1)=ROUND(IS!AL18,1),"OK","ERROR") -> ERROR | AR18: =IF(ROUND(SUM(IS!AN18:AQ18),1)=ROUND(IS!AR18,1),"OK","ERROR") -> OK
A20: x | B20: Cost of revenue:
B21: Cost of goods and services | H21: =IF(ROUND(SUM(IS!D21:G21),1)=ROUND(IS!H21,1),"OK","ERROR") -> OK | N21: =IF(ROUND(SUM(IS!J21:M21),1)=ROUND(IS!N21,1),"OK","ERROR") -> OK | T21: =IF(ROUND(SUM(IS!P21:S21),1)=ROUND(IS!T21,1),"OK","ERROR") -> OK | Z21: =IF(ROUND(SUM(IS!V21:Y21),1)=ROUND(IS!Z21,1),"OK","ERROR") -> OK | AF21: =IF(ROUND(SUM(IS!AB21:AE21),1)=ROUND(IS!AF21,1),"OK","ERROR") -> OK | AL21: =IF(ROUND(SUM(IS!AH21:AK21),1)=ROUND(IS!AL21,1),"OK","ERROR") -> ERROR | AR21: =IF(ROUND(SUM(IS!AN21:AQ21),1)=ROUND(IS!AR21,1),"OK","ERROR") -> OK
B22: Depreciation & amortization | H22: =IF(ROUND(SUM(IS!D22:G22),1)=ROUND(IS!H22,1),"OK","ERROR") -> OK | N22: =IF(ROUND(SUM(IS!J22:M22),1)=ROUND(IS!N22,1),"OK","ERROR") -> OK | T22: =IF(ROUND(SUM(IS!P22:S22),1)=ROUND(IS!T22,1),"OK","ERROR") -> OK | Z22: =IF(ROUND(SUM(IS!V22:Y22),1)=ROUND(IS!Z22,1),"OK","ERROR") -> OK | AF22: =IF(ROUND(SUM(IS!AB22:AE22),1)=ROUND(IS!AF22,1),"OK","ERROR") -> OK | AL22: =IF(ROUND(SUM(IS!AH22:AK22),1)=ROUND(IS!AL22,1),"OK","ERROR") -> ERROR | AR22: =IF(ROUND(SUM(IS!AN22:AQ22),1)=ROUND(IS!AR22,1),"OK","ERROR") -> OK
B23: Total cost of revenue | H23: =IF(ROUND(SUM(IS!D23:G23),1)=ROUND(IS!H23,1),"OK","ERROR") -> OK | N23: =IF(ROUND(SUM(IS!J23:M23),1)=ROUND(IS!N23,1),"OK","ERROR") -> OK | T23: =IF(ROUND(SUM(IS!P23:S23),1)=ROUND(IS!T23,1),"OK","ERROR") -> OK | Z23: =IF(ROUND(SUM(IS!V23:Y23),1)=ROUND(IS!Z23,1),"OK","ERROR") -> OK | AF23: =IF(ROUND(SUM(IS!AB23:AE23),1)=ROUND(IS!AF23,1),"OK","ERROR") -> OK | AL23: =IF(ROUND(SUM(IS!AH23:AK23),1)=ROUND(IS!AL23,1),"OK","ERROR") -> ERROR | AR23: =IF(ROUND(SUM(IS!AN23:AQ23),1)=ROUND(IS!AR23,1),"OK","ERROR") -> OK
B24: Gross margin | H24: =IF(ROUND(SUM(IS!D24:G24),1)=ROUND(IS!H24,1),"OK","ERROR") -> OK | N24: =IF(ROUND(SUM(IS!J24:M24),1)=ROUND(IS!N24,1),"OK","ERROR") -> OK | T24: =IF(ROUND(SUM(IS!P24:S24),1)=ROUND(IS!T24,1),"OK","ERROR") -> OK | Z24: =IF(ROUND(SUM(IS!V24:Y24),1)=ROUND(IS!Z24,1),"OK","ERROR") -> OK | AF24: =IF(ROUND(SUM(IS!AB24:AE24),1)=ROUND(IS!AF24,1),"OK","ERROR") -> OK | AL24: =IF(ROUND(SUM(IS!AH24:AK24),1)=ROUND(IS!AL24,1),"OK","ERROR") -> ERROR | AR24: =IF(ROUND(SUM(IS!AN24:AQ24),1)=ROUND(IS!AR24,1),"OK","ERROR") -> OK
A26: x | B26: Operating expenses:
B27: Selling, general and administrative | H27: =IF(ROUND(SUM(IS!D27:G27),1)=ROUND(IS!H27,1),"OK","ERROR") -> OK | N27: =IF(ROUND(SUM(IS!J27:M27),1)=ROUND(IS!N27,1),"OK","ERROR") -> OK | T27: =IF(ROUND(SUM(IS!P27:S27),1)=ROUND(IS!T27,1),"OK","ERROR") -> OK | Z27: =IF(ROUND(SUM(IS!V27:Y27),1)=ROUND(IS!Z27,1),"OK","ERROR") -> OK | AF27: =IF(ROUND(SUM(IS!AB27:AE27),1)=ROUND(IS!AF27,1),"OK","ERROR") -> OK | AL27: =IF(ROUND(SUM(IS!AH27:AK27),1)=ROUND(IS!AL27,1),"OK","ERROR") -> OK | AR27: =IF(ROUND(SUM(IS!AN27:AQ27),1)=ROUND(IS!AR27,1),"OK","ERROR") -> OK
B28: Depreciation and amortization | H28: =IF(ROUND(SUM(IS!D28:G28),1)=ROUND(IS!H28,1),"OK","ERROR") -> OK | N28: =IF(ROUND(SUM(IS!J28:M28),1)=ROUND(IS!N28,1),"OK","ERROR") -> OK | T28: =IF(ROUND(SUM(IS!P28:S28),1)=ROUND(IS!T28,1),"OK","ERROR") -> OK | Z28: =IF(ROUND(SUM(IS!V28:Y28),1)=ROUND(IS!Z28,1),"OK","ERROR") -> OK | AF28: =IF(ROUND(SUM(IS!AB28:AE28),1)=ROUND(IS!AF28,1),"OK","ERROR") -> OK | AL28: =IF(ROUND(SUM(IS!AH28:AK28),1)=ROUND(IS!AL28,1),"OK","ERROR") -> OK | AR28: =IF(ROUND(SUM(IS!AN28:AQ28),1)=ROUND(IS!AR28,1),"OK","ERROR") -> OK
B29: Research and development | H29: =IF(ROUND(SUM(IS!D29:G29),1)=ROUND(IS!H29,1),"OK","ERROR") -> OK | N29: =IF(ROUND(SUM(IS!J29:M29),1)=ROUND(IS!N29,1),"OK","ERROR") -> OK | T29: =IF(ROUND(SUM(IS!P29:S29),1)=ROUND(IS!T29,1),"OK","ERROR") -> OK | Z29: =IF(ROUND(SUM(IS!V29:Y29),1)=ROUND(IS!Z29,1),"OK","ERROR") -> OK | AF29: =IF(ROUND(SUM(IS!AB29:AE29),1)=ROUND(IS!AF29,1),"OK","ERROR") -> OK | AL29: =IF(ROUND(SUM(IS!AH29:AK29),1)=ROUND(IS!AL29,1),"OK","ERROR") -> OK | AR29: =IF(ROUND(SUM(IS!AN29:AQ29),1)=ROUND(IS!AR29,1),"OK","ERROR") -> OK
B30: Other operating expenses | H30: =IF(ROUND(SUM(IS!D30:G30),1)=ROUND(IS!H30,1),"OK","ERROR") -> ERROR | N30: =IF(ROUND(SUM(IS!J30:M30),1)=ROUND(IS!N30,1),"OK","ERROR") -> OK | T30: =IF(ROUND(SUM(IS!P30:S30),1)=ROUND(IS!T30,1),"OK","ERROR") -> ERROR | Z30: =IF(ROUND(SUM(IS!V30:Y30),1)=ROUND(IS!Z30,1),"OK","ERROR") -> ERROR | AF30: =IF(ROUND(SUM(IS!AB30:AE30),1)=ROUND(IS!AF30,1),"OK","ERROR") -> OK | AL30: =IF(ROUND(SUM(IS!AH30:AK30),1)=ROUND(IS!AL30,1),"OK","ERROR") -> ERROR | AR30: =IF(ROUND(SUM(IS!AN30:AQ30),1)=ROUND(IS!AR30,1),"OK","ERROR") -> OK
B31: Total operating expenses | H31: =IF(ROUND(SUM(IS!D31:G31),1)=ROUND(IS!H31,1),"OK","ERROR") -> ERROR | N31: =IF(ROUND(SUM(IS!J31:M31),1)=ROUND(IS!N31,1),"OK","ERROR") -> OK | T31: =IF(ROUND(SUM(IS!P31:S31),1)=ROUND(IS!T31,1),"OK","ERROR") -> ERROR | Z31: =IF(ROUND(SUM(IS!V31:Y31),1)=ROUND(IS!Z31,1),"OK","ERROR") -> ERROR | AF31: =IF(ROUND(SUM(IS!AB31:AE31),1)=ROUND(IS!AF31,1),"OK","ERROR") -> OK | AL31: =IF(ROUND(SUM(IS!AH31:AK31),1)=ROUND(IS!AL31,1),"OK","ERROR") -> ERROR | AR31: =IF(ROUND(SUM(IS!AN31:AQ31),1)=ROUND(IS!AR31,1),"OK","ERROR") -> OK
B32: Other operating income | H32: =IF(ROUND(SUM(IS!D32:G32),1)=ROUND(IS!H32,1),"OK","ERROR") -> OK | N32: =IF(ROUND(SUM(IS!J32:M32),1)=ROUND(IS!N32,1),"OK","ERROR") -> OK | T32: =IF(ROUND(SUM(IS!P32:S32),1)=ROUND(IS!T32,1),"OK","ERROR") -> OK | Z32: =IF(ROUND(SUM(IS!V32:Y32),1)=ROUND(IS!Z32,1),"OK","ERROR") -> OK | AF32: =IF(ROUND(SUM(IS!AB32:AE32),1)=ROUND(IS!AF32,1),"OK","ERROR") -> OK | AL32: =IF(ROUND(SUM(IS!AH32:AK32),1)=ROUND(IS!AL32,1),"OK","ERROR") -> OK | AR32: =IF(ROUND(SUM(IS!AN32:AQ32),1)=ROUND(IS!AR32,1),"OK","ERROR") -> OK
B33: Operating income | H33: =IF(ROUND(SUM(IS!D33:G33),1)=ROUND(IS!H33,1),"OK","ERROR") -> ERROR | N33: =IF(ROUND(SUM(IS!J33:M33),1)=ROUND(IS!N33,1),"OK","ERROR") -> OK | T33: =IF(ROUND(SUM(IS!P33:S33),1)=ROUND(IS!T33,1),"OK","ERROR") -> ERROR | Z33: =IF(ROUND(SUM(IS!V33:Y33),1)=ROUND(IS!Z33,1),"OK","ERROR") -> ERROR | AF33: =IF(ROUND(SUM(IS!AB33:AE33),1)=ROUND(IS!AF33,1),"OK","ERROR") -> OK | AL33: =IF(ROUND(SUM(IS!AH33:AK33),1)=ROUND(IS!AL33,1),"OK","ERROR") -> ERROR | AR33: =IF(ROUND(SUM(IS!AN33:AQ33),1)=ROUND(IS!AR33,1),"OK","ERROR") -> OK
A35: x | B35: Non-operating (income) loss:
B36: Interest expense | H36: =IF(ROUND(SUM(IS!D36:G36),1)=ROUND(IS!H36,1),"OK","ERROR") -> ERROR | N36: =IF(ROUND(SUM(IS!J36:M36),1)=ROUND(IS!N36,1),"OK","ERROR") -> ERROR | T36: =IF(ROUND(SUM(IS!P36:S36),1)=ROUND(IS!T36,1),"OK","ERROR") -> ERROR | Z36: =IF(ROUND(SUM(IS!V36:Y36),1)=ROUND(IS!Z36,1),"OK","ERROR") -> OK | AF36: =IF(ROUND(SUM(IS!AB36:AE36),1)=ROUND(IS!AF36,1),"OK","ERROR") -> OK | AL36: =IF(ROUND(SUM(IS!AH36:AK36),1)=ROUND(IS!AL36,1),"OK","ERROR") -> ERROR | AR36: =IF(ROUND(SUM(IS!AN36:AQ36),1)=ROUND(IS!AR36,1),"OK","ERROR") -> OK
B37: Interest income | H37: =IF(ROUND(SUM(IS!D37:G37),1)=ROUND(IS!H37,1),"OK","ERROR") -> ERROR | N37: =IF(ROUND(SUM(IS!J37:M37),1)=ROUND(IS!N37,1),"OK","ERROR") -> ERROR | T37: =IF(ROUND(SUM(IS!P37:S37),1)=ROUND(IS!T37,1),"OK","ERROR") -> ERROR | Z37: =IF(ROUND(SUM(IS!V37:Y37),1)=ROUND(IS!Z37,1),"OK","ERROR") -> OK | AF37: =IF(ROUND(SUM(IS!AB37:AE37),1)=ROUND(IS!AF37,1),"OK","ERROR") -> OK | AL37: =IF(ROUND(SUM(IS!AH37:AK37),1)=ROUND(IS!AL37,1),"OK","ERROR") -> OK | AR37: =IF(ROUND(SUM(IS!AN37:AQ37),1)=ROUND(IS!AR37,1),"OK","ERROR") -> OK
A38: x | B38: Net interest (income) expense | H38: =IF(ROUND(SUM(IS!D38:G38),1)=ROUND(IS!H38,1),"OK","ERROR") -> OK | N38: =IF(ROUND(SUM(IS!J38:M38),1)=ROUND(IS!N38,1),"OK","ERROR") -> OK | T38: =IF(ROUND(SUM(IS!P38:S38),1)=ROUND(IS!T38,1),"OK","ERROR") -> OK | Z38: =IF(ROUND(SUM(IS!V38:Y38),1)=ROUND(IS!Z38,1),"OK","ERROR") -> OK | AF38: =IF(ROUND(SUM(IS!AB38:AE38),1)=ROUND(IS!AF38,1),"OK","ERROR") -> OK | AL38: =IF(ROUND(SUM(IS!AH38:AK38),1)=ROUND(IS!AL38,1),"OK","ERROR") -> ERROR | AR38: =IF(ROUND(SUM(IS!AN38:AQ38),1)=ROUND(IS!AR38,1),"OK","ERROR") -> OK
B39: Foreign exchange (gains) losses | H39: =IF(ROUND(SUM(IS!D39:G39),1)=ROUND(IS!H39,1),"OK","ERROR") -> OK | N39: =IF(ROUND(SUM(IS!J39:M39),1)=ROUND(IS!N39,1),"OK","ERROR") -> OK | T39: =IF(ROUND(SUM(IS!P39:S39),1)=ROUND(IS!T39,1),"OK","ERROR") -> OK | Z39: =IF(ROUND(SUM(IS!V39:Y39),1)=ROUND(IS!Z39,1),"OK","ERROR") -> OK | AF39: =IF(ROUND(SUM(IS!AB39:AE39),1)=ROUND(IS!AF39,1),"OK","ERROR") -> OK | AL39: =IF(ROUND(SUM(IS!AH39:AK39),1)=ROUND(IS!AL39,1),"OK","ERROR") -> OK | AR39: =IF(ROUND(SUM(IS!AN39:AQ39),1)=ROUND(IS!AR39,1),"OK","ERROR") -> OK
B40: Other non-operating (income) expenses | H40: =IF(ROUND(SUM(IS!D40:G40),1)=ROUND(IS!H40,1),"OK","ERROR") -> OK | N40: =IF(ROUND(SUM(IS!J40:M40),1)=ROUND(IS!N40,1),"OK","ERROR") -> OK | T40: =IF(ROUND(SUM(IS!P40:S40),1)=ROUND(IS!T40,1),"OK","ERROR") -> ERROR | Z40: =IF(ROUND(SUM(IS!V40:Y40),1)=ROUND(IS!Z40,1),"OK","ERROR") -> OK | AF40: =IF(ROUND(SUM(IS!AB40:AE40),1)=ROUND(IS!AF40,1),"OK","ERROR") -> OK | AL40: =IF(ROUND(SUM(IS!AH40:AK40),1)=ROUND(IS!AL40,1),"OK","ERROR") -> ERROR | AR40: =IF(ROUND(SUM(IS!AN40:AQ40),1)=ROUND(IS!AR40,1),"OK","ERROR") -> OK
B41: Total non-operating expenses | H41: =IF(ROUND(SUM(IS!D41:G41),1)=ROUND(IS!H41,1),"OK","ERROR") -> OK | N41: =IF(ROUND(SUM(IS!J41:M41),1)=ROUND(IS!N41,1),"OK","ERROR") -> OK | T41: =IF(ROUND(SUM(IS!P41:S41),1)=ROUND(IS!T41,1),"OK","ERROR") -> ERROR | Z41: =IF(ROUND(SUM(IS!V41:Y41),1)=ROUND(IS!Z41,1),"OK","ERROR") -> OK | AF41: =IF(ROUND(SUM(IS!AB41:AE41),1)=ROUND(IS!AF41,1),"OK","ERROR") -> OK | AL41: =IF(ROUND(SUM(IS!AH41:AK41),1)=ROUND(IS!AL41,1),"OK","ERROR") -> ERROR | AR41: =IF(ROUND(SUM(IS!AN41:AQ41),1)=ROUND(IS!AR41,1),"OK","ERROR") -> OK
B42: Pre-tax income | H42: =IF(ROUND(SUM(IS!D42:G42),1)=ROUND(IS!H42,1),"OK","ERROR") -> ERROR | N42: =IF(ROUND(SUM(IS!J42:M42),1)=ROUND(IS!N42,1),"OK","ERROR") -> OK | T42: =IF(ROUND(SUM(IS!P42:S42),1)=ROUND(IS!T42,1),"OK","ERROR") -> ERROR | Z42: =IF(ROUND(SUM(IS!V42:Y42),1)=ROUND(IS!Z42,1),"OK","ERROR") -> ERROR | AF42: =IF(ROUND(SUM(IS!AB42:AE42),1)=ROUND(IS!AF42,1),"OK","ERROR") -> OK | AL42: =IF(ROUND(SUM(IS!AH42:AK42),1)=ROUND(IS!AL42,1),"OK","ERROR") -> ERROR | AR42: =IF(ROUND(SUM(IS!AN42:AQ42),1)=ROUND(IS!AR42,1),"OK","ERROR") -> OK
A44: x | B44: Tax & net income:
B45: Income tax expenses (benefits) | H45: =IF(ROUND(SUM(IS!D45:G45),1)=ROUND(IS!H45,1),"OK","ERROR") -> ERROR | N45: =IF(ROUND(SUM(IS!J45:M45),1)=ROUND(IS!N45,1),"OK","ERROR") -> OK | T45: =IF(ROUND(SUM(IS!P45:S45),1)=ROUND(IS!T45,1),"OK","ERROR") -> ERROR | Z45: =IF(ROUND(SUM(IS!V45:Y45),1)=ROUND(IS!Z45,1),"OK","ERROR") -> ERROR | AF45: =IF(ROUND(SUM(IS!AB45:AE45),1)=ROUND(IS!AF45,1),"OK","ERROR") -> ERROR | AL45: =IF(ROUND(SUM(IS!AH45:AK45),1)=ROUND(IS!AL45,1),"OK","ERROR") -> ERROR | AR45: =IF(ROUND(SUM(IS!AN45:AQ45),1)=ROUND(IS!AR45,1),"OK","ERROR") -> OK
B46: Net extraordinary losses (gains) | H46: =IF(ROUND(SUM(IS!D46:G46),1)=ROUND(IS!H46,1),"OK","ERROR") -> OK | N46: =IF(ROUND(SUM(IS!J46:M46),1)=ROUND(IS!N46,1),"OK","ERROR") -> OK | T46: =IF(ROUND(SUM(IS!P46:S46),1)=ROUND(IS!T46,1),"OK","ERROR") -> OK | Z46: =IF(ROUND(SUM(IS!V46:Y46),1)=ROUND(IS!Z46,1),"OK","ERROR") -> OK | AF46: =IF(ROUND(SUM(IS!AB46:AE46),1)=ROUND(IS!AF46,1),"OK","ERROR") -> OK | AL46: =IF(ROUND(SUM(IS!AH46:AK46),1)=ROUND(IS!AL46,1),"OK","ERROR") -> OK | AR46: =IF(ROUND(SUM(IS!AN46:AQ46),1)=ROUND(IS!AR46,1),"OK","ERROR") -> OK
B47: Net income including minority interest | H47: =IF(ROUND(SUM(IS!D47:G47),1)=ROUND(IS!H47,1),"OK","ERROR") -> OK | N47: =IF(ROUND(SUM(IS!J47:M47),1)=ROUND(IS!N47,1),"OK","ERROR") -> OK | T47: =IF(ROUND(SUM(IS!P47:S47),1)=ROUND(IS!T47,1),"OK","ERROR") -> OK | Z47: =IF(ROUND(SUM(IS!V47:Y47),1)=ROUND(IS!Z47,1),"OK","ERROR") -> ERROR | AF47: =IF(ROUND(SUM(IS!AB47:AE47),1)=ROUND(IS!AF47,1),"OK","ERROR") -> ERROR | AL47: =IF(ROUND(SUM(IS!AH47:AK47),1)=ROUND(IS!AL47,1),"OK","ERROR") -> ERROR | AR47: =IF(ROUND(SUM(IS!AN47:AQ47),1)=ROUND(IS!AR47,1),"OK","ERROR") -> OK
A49: x | B49: Attribution:
B50: Preferred dividends | H50: =IF(ROUND(SUM(IS!D50:G50),1)=ROUND(IS!H50,1),"OK","ERROR") -> OK | N50: =IF(ROUND(SUM(IS!J50:M50),1)=ROUND(IS!N50,1),"OK","ERROR") -> OK | T50: =IF(ROUND(SUM(IS!P50:S50),1)=ROUND(IS!T50,1),"OK","ERROR") -> OK | Z50: =IF(ROUND(SUM(IS!V50:Y50),1)=ROUND(IS!Z50,1),"OK","ERROR") -> OK | AF50: =IF(ROUND(SUM(IS!AB50:AE50),1)=ROUND(IS!AF50,1),"OK","ERROR") -> OK | AL50: =IF(ROUND(SUM(IS!AH50:AK50),1)=ROUND(IS!AL50,1),"OK","ERROR") -> OK | AR50: =IF(ROUND(SUM(IS!AN50:AQ50),1)=ROUND(IS!AR50,1),"OK","ERROR") -> OK
B51: Income attributable to non-controlling interests | H51: =IF(ROUND(SUM(IS!D51:G51),1)=ROUND(IS!H51,1),"OK","ERROR") -> OK | N51: =IF(ROUND(SUM(IS!J51:M51),1)=ROUND(IS!N51,1),"OK","ERROR") -> OK | T51: =IF(ROUND(SUM(IS!P51:S51),1)=ROUND(IS!T51,1),"OK","ERROR") -> OK | Z51: =IF(ROUND(SUM(IS!V51:Y51),1)=ROUND(IS!Z51,1),"OK","ERROR") -> OK | AF51: =IF(ROUND(SUM(IS!AB51:AE51),1)=ROUND(IS!AF51,1),"OK","ERROR") -> OK | AL51: =IF(ROUND(SUM(IS!AH51:AK51),1)=ROUND(IS!AL51,1),"OK","ERROR") -> OK | AR51: =IF(ROUND(SUM(IS!AN51:AQ51),1)=ROUND(IS!AR51,1),"OK","ERROR") -> OK
B52: Net income attributable to common shareholders | H52: =IF(ROUND(SUM(IS!D52:G52),1)=ROUND(IS!H52,1),"OK","ERROR") -> OK | N52: =IF(ROUND(SUM(IS!J52:M52),1)=ROUND(IS!N52,1),"OK","ERROR") -> OK | T52: =IF(ROUND(SUM(IS!P52:S52),1)=ROUND(IS!T52,1),"OK","ERROR") -> OK | Z52: =IF(ROUND(SUM(IS!V52:Y52),1)=ROUND(IS!Z52,1),"OK","ERROR") -> ERROR | AF52: =IF(ROUND(SUM(IS!AB52:AE52),1)=ROUND(IS!AF52,1),"OK","ERROR") -> ERROR | AL52: =IF(ROUND(SUM(IS!AH52:AK52),1)=ROUND(IS!AL52,1),"OK","ERROR") -> ERROR | AR52: =IF(ROUND(SUM(IS!AN52:AQ52),1)=ROUND(IS!AR52,1),"OK","ERROR") -> OK
A54: x | B54: Earnings per share:
B55: EPS basic | H55: =IF(ROUND(AVERAGE(IS!D55:G55),0)-ROUND(IS!H55,0)<0.01*ROUND(IS!H55,0),"OK","ERROR") -> OK | N55: =IF(ROUND(AVERAGE(IS!J55:M55),0)-ROUND(IS!N55,0)<0.01*ROUND(IS!N55,0),"OK","ERROR") -> OK | T55: =IF(ROUND(AVERAGE(IS!P55:S55),0)-ROUND(IS!T55,0)<0.01*ROUND(IS!T55,0),"OK","ERROR") -> OK | Z55: =IF(ROUND(AVERAGE(IS!V55:Y55),0)-ROUND(IS!Z55,0)<0.01*ROUND(IS!Z55,0),"OK","ERROR") -> OK | AF55: =IF(ROUND(AVERAGE(IS!AB55:AE55),0)-ROUND(IS!AF55,0)<0.01*ROUND(IS!AF55,0),"OK","ERROR") -> OK | AL55: =IF(ROUND(AVERAGE(IS!AH55:AK55),0)-ROUND(IS!AL55,0)<0.01*ROUND(IS!AL55,0),"OK","ERROR") -> ERROR | AR55: =IF(ROUND(AVERAGE(IS!AN55:AQ55),0)-ROUND(IS!AR55,0)<0.01*ROUND(IS!AR55,0),"OK","ERROR") -> #DIV/0!
B56: EPS diluted | H56: =IF(ROUND(AVERAGE(IS!D56:G56),0)-ROUND(IS!H56,0)<0.01*ROUND(IS!H56,0),"OK","ERROR") -> OK | N56: =IF(ROUND(AVERAGE(IS!J56:M56),0)-ROUND(IS!N56,0)<0.01*ROUND(IS!N56,0),"OK","ERROR") -> OK | T56: =IF(ROUND(AVERAGE(IS!P56:S56),0)-ROUND(IS!T56,0)<0.01*ROUND(IS!T56,0),"OK","ERROR") -> OK | Z56: =IF(ROUND(AVERAGE(IS!V56:Y56),0)-ROUND(IS!Z56,0)<0.01*ROUND(IS!Z56,0),"OK","ERROR") -> OK | AF56: =IF(ROUND(AVERAGE(IS!AB56:AE56),0)-ROUND(IS!AF56,0)<0.01*ROUND(IS!AF56,0),"OK","ERROR") -> OK | AL56: =IF(ROUND(AVERAGE(IS!AH56:AK56),0)-ROUND(IS!AL56,0)<0.01*ROUND(IS!AL56,0),"OK","ERROR") -> ERROR | AR56: =IF(ROUND(AVERAGE(IS!AN56:AQ56),0)-ROUND(IS!AR56,0)<0.01*ROUND(IS!AR56,0),"OK","ERROR") -> #DIV/0!
A58: x | B58: Shares used in computing earnings per share:
B59: Basic weighted average shares | H59: =IF(ROUND(AVERAGE(IS!D59:G59),0)-ROUND(IS!H59,0)<0.01*ROUND(IS!H59,0),"OK","ERROR") -> OK | N59: =IF(ROUND(AVERAGE(IS!J59:M59),0)-ROUND(IS!N59,0)<0.01*ROUND(IS!N59,0),"OK","ERROR") -> OK | T59: =IF(ROUND(AVERAGE(IS!P59:S59),0)-ROUND(IS!T59,0)<0.01*ROUND(IS!T59,0),"OK","ERROR") -> OK | Z59: =IF(ROUND(AVERAGE(IS!V59:Y59),0)-ROUND(IS!Z59,0)<0.01*ROUND(IS!Z59,0),"OK","ERROR") -> OK | AF59: =IF(ROUND(AVERAGE(IS!AB59:AE59),0)-ROUND(IS!AF59,0)<0.01*ROUND(IS!AF59,0),"OK","ERROR") -> OK | AL59: =IF(ROUND(AVERAGE(IS!AH59:AK59),0)-ROUND(IS!AL59,0)<0.01*ROUND(IS!AL59,0),"OK","ERROR") -> ERROR | AR59: =IF(ROUND(AVERAGE(IS!AN59:AQ59),0)-ROUND(IS!AR59,0)<0.01*ROUND(IS!AR59,0),"OK","ERROR") -> #DIV/0!
B60: Diluted weighted average shares | H60: =IF(ROUND(AVERAGE(IS!D60:G60),0)-ROUND(IS!H60,0)<0.01*ROUND(IS!H60,0),"OK","ERROR") -> OK | N60: =IF(ROUND(AVERAGE(IS!J60:M60),0)-ROUND(IS!N60,0)<0.01*ROUND(IS!N60,0),"OK","ERROR") -> OK | T60: =IF(ROUND(AVERAGE(IS!P60:S60),0)-ROUND(IS!T60,0)<0.01*ROUND(IS!T60,0),"OK","ERROR") -> OK | Z60: =IF(ROUND(AVERAGE(IS!V60:Y60),0)-ROUND(IS!Z60,0)<0.01*ROUND(IS!Z60,0),"OK","ERROR") -> OK | AF60: =IF(ROUND(AVERAGE(IS!AB60:AE60),0)-ROUND(IS!AF60,0)<0.01*ROUND(IS!AF60,0),"OK","ERROR") -> OK | AL60: =IF(ROUND(AVERAGE(IS!AH60:AK60),0)-ROUND(IS!AL60,0)<0.01*ROUND(IS!AL60,0),"OK","ERROR") -> ERROR | AR60: =IF(ROUND(AVERAGE(IS!AN60:AQ60),0)-ROUND(IS!AR60,0)<0.01*ROUND(IS!AR60,0),"OK","ERROR") -> #DIV/0!
B62: Income Statement - Metrics | D62: =F62 -> 2020 | E62: =F62 -> 2020 | F62: 2020 | G62: =F62 -> 2020 | H62: =F62 -> 2020 | J62: =L62 -> 2021 | K62: =L62 -> 2021 | L62: 2021 | M62: =L62 -> 2021 | N62: =L62 -> 2021 | P62: =R62 -> 2022 | Q62: =R62 -> 2022 | R62: 2022 | S62: =R62 -> 2022 | T62: =R62 -> 2022 | V62: =X62 -> 2023 | W62: =X62 -> 2023 | X62: 2023 | Y62: =X62 -> 2023 | Z62: =X62 -> 2023 | AB62: =AD62 -> 2024 | AC62: =AD62 -> 2024 | AD62: 2024 | AE62: =AD62 -> 2024 | AF62: =AD62 -> 2024 | AH62: =AJ62 -> 2025 | AI62: =AJ62 -> 2025 | AJ62: 2025 | AK62: =AJ62 -> 2025 | AL62: =AJ62 -> 2025 | AN62: =AP62 -> 2025 | AO62: =AP62 -> 2025 | AP62: 2025 | AQ62: =AP62 -> 2025 | AR62: =AP62 -> 2025
D63: 2020 | J63: =D63+1 -> 2021 | P63: =J63+1 -> 2022 | V63: =P63+1 -> 2023 | AB63: =V63+1 -> 2024 | AH63: =AB63+1 -> 2025 | AN63: =AH63+1 -> 2026 | AT63: =AN63+1 -> 2027 | AV63: =+AT63+1 -> 2028 | AX63: =+AV63+1 -> 2029
D64: Q1 | E64: Q2 | F64: Q3 | G64: Q4 | H64: FY | J64: Q1 | K64: Q2 | L64: Q3 | M64: Q4 | N64: FY | P64: Q1 | Q64: Q2 | R64: Q3 | S64: Q4 | T64: FY | V64: Q1 | W64: Q2 | X64: Q3 | Y64: Q4 | Z64: FY | AB64: Q1 | AC64: Q2 | AD64: Q3 | AE64: Q4 | AF64: FY | AH64: Q1 | AI64: Q2 | AJ64: Q3 | AK64: Q4 | AL64: FY | AN64: Q1 | AO64: Q2 | AP64: Q3 | AQ64: Q4 | AR64: FY | AT64: FY | AV64: FY | AX64: FY
A67: x | B67: Revenue:
B68: Total revenue | D68: =IF(ROUND(SUM(IS!D13:D17),0)=IS!D18,"OK","ERROR") -> ERROR | E68: =IF(ROUND(SUM(IS!E13:E17),0)=IS!E18,"OK","ERROR") -> ERROR | F68: =IF(ROUND(SUM(IS!F13:F17),0)=IS!F18,"OK","ERROR") -> ERROR | G68: =IF(ROUND(SUM(IS!G13:G17),0)=IS!G18,"OK","ERROR") -> ERROR | H68: =IF(ROUND(SUM(IS!H13:H17),0)=IS!H18,"OK","ERROR") -> ERROR | J68: =IF(ROUND(SUM(IS!J13:J17),0)=IS!J18,"OK","ERROR") -> ERROR | K68: =IF(ROUND(SUM(IS!K13:K17),0)=IS!K18,"OK","ERROR") -> ERROR | L68: =IF(ROUND(SUM(IS!L13:L17),0)=IS!L18,"OK","ERROR") -> ERROR | M68: =IF(ROUND(SUM(IS!M13:M17),0)=IS!M18,"OK","ERROR") -> ERROR | N68: =IF(ROUND(SUM(IS!N13:N17),0)=IS!N18,"OK","ERROR") -> ERROR | P68: =IF(ROUND(SUM(IS!P13:P17),0)=IS!P18,"OK","ERROR") -> ERROR | Q68: =IF(ROUND(SUM(IS!Q13:Q17),0)=IS!Q18,"OK","ERROR") -> ERROR | R68: =IF(ROUND(SUM(IS!R13:R17),0)=IS!R18,"OK","ERROR") -> ERROR | S68: =IF(ROUND(SUM(IS!S13:S17),0)=IS!S18,"OK","ERROR") -> ERROR | T68: =IF(ROUND(SUM(IS!T13:T17),0)=IS!T18,"OK","ERROR") -> ERROR | V68: =IF(ROUND(SUM(IS!V13:V17),0)=IS!V18,"OK","ERROR") -> ERROR | W68: =IF(ROUND(SUM(IS!W13:W17),0)=IS!W18,"OK","ERROR") -> ERROR | X68: =IF(ROUND(SUM(IS!X13:X17),0)=IS!X18,"OK","ERROR") -> ERROR | Y68: =IF(ROUND(SUM(IS!Y13:Y17),0)=IS!Y18,"OK","ERROR") -> ERROR | Z68: =IF(ROUND(SUM(IS!Z13:Z17),0)=IS!Z18,"OK","ERROR") -> ERROR | AB68: =IF(ROUND(SUM(IS!AB13:AB17),0)=IS!AB18,"OK","ERROR") -> ERROR | AC68: =IF(ROUND(SUM(IS!AC13:AC17),0)=IS!AC18,"OK","ERROR") -> ERROR | AD68: =IF(ROUND(SUM(IS!AD13:AD17),0)=IS!AD18,"OK","ERROR") -> ERROR | AE68: =IF(ROUND(SUM(IS!AE13:AE17),0)=IS!AE18,"OK","ERROR") -> ERROR | AF68: =IF(ROUND(SUM(IS!AF13:AF17),0)=IS!AF18,"OK","ERROR") -> ERROR | AH68: =IF(ROUND(SUM(IS!AH13:AH17),0)=IS!AH18,"OK","ERROR") -> ERROR | AI68: =IF(ROUND(SUM(IS!AI13:AI17),0)=IS!AI18,"OK","ERROR") -> ERROR | AJ68: =IF(ROUND(SUM(IS!AJ13:AJ17),0)=IS!AJ18,"OK","ERROR") -> OK | AK68: =IF(ROUND(SUM(IS!AK13:AK17),0)=IS!AK18,"OK","ERROR") -> OK | AL68: =IF(ROUND(SUM(IS!AL13:AL17),0)=IS!AL18,"OK","ERROR") -> OK | AN68: =IF(ROUND(SUM(IS!AN13:AN17),0)=IS!AN18,"OK","ERROR") -> OK | AO68: =IF(ROUND(SUM(IS!AO13:AO17),0)=IS!AO18,"OK","ERROR") -> OK | AP68: =IF(ROUND(SUM(IS!AP13:AP17),0)=IS!AP18,"OK","ERROR") -> OK | AQ68: =IF(ROUND(SUM(IS!AQ13:AQ17),0)=IS!AQ18,"OK","ERROR") -> OK | AR68: =IF(ROUND(SUM(IS!AR13:AR17),0)=IS!AR18,"OK","ERROR") -> OK | AT68: =IF(ROUND(SUM(IS!AT13:AT17),0)=IS!AT18,"OK","ERROR") -> OK | AV68: =IF(ROUND(SUM(IS!AV13:AV17),0)=IS!AV18,"OK","ERROR") -> OK | AX68: =IF(ROUND(SUM(IS!AX13:AX17),0)=IS!AX18,"OK","ERROR") -> OK
A70: x | B70: Cost of revenue:
