Workbook
Name COOLFUCNTION: _xlfn.LAMBDA(_xldudf_BOARDFLARE_EXEC("workbook-settings:coolfucntion"))
Name COOLFUCNTION: _xlfn.LAMBDA(_xldudf_BOARDFLARE_EXEC("workbook-settings:coolfucntion"))
Name COOLFUCNTION: _xlfn.LAMBDA(_xldudf_BOARDFLARE_EXEC("workbook-settings:coolfucntion"))
Name COOLFUCNTION: _xlfn.LAMBDA(_xldudf_BOARDFLARE_EXEC("workbook-settings:coolfucntion"))
Name COOLFUCNTION: _xlfn.LAMBDA(_xldudf_BOARDFLARE_EXEC("workbook-settings:coolfucntion"))
Name COOLFUCNTION: _xlfn.LAMBDA(_xldudf_BOARDFLARE_EXEC("workbook-settings:coolfucntion"))
Name COOLFUCNTION: _xlfn.LAMBDA(_xldudf_BOARDFLARE_EXEC("workbook-settings:coolfucntion"))
Name COOLFUCNTION: _xlfn.LAMBDA(_xldudf_BOARDFLARE_EXEC("workbook-settings:coolfucntion"))
Name COOLFUCNTION: _xlfn.LAMBDA(_xldudf_BOARDFLARE_EXEC("workbook-settings:coolfucntion"))
Name COOLFUCNTION: _xlfn.LAMBDA(_xldudf_BOARDFLARE_EXEC("workbook-settings:coolfucntion"))
Name COOLFUCNTION: _xlfn.LAMBDA(_xldudf_BOARDFLARE_EXEC("workbook-settings:coolfucntion"))
Name Sectors: #REF!
Name Sectors: #REF!
Name Sectors: #REF!
Name Sectors: #REF!
Name Sectors: #REF!
Name Sectors: #REF!
Name Sectors: #REF!
Name Sectors: #REF!

Sheet Dashboard
C154: =+C155+1 -> 45972
C155: =+C156+1 -> 45971
C156: =+C157+1 -> 45970
C157: =+C158+1 -> 45969
C158: =+C159+1 -> 45968
C159: =+C160+1 -> 45967
C160: =+C161+1 -> 45966 | L160: =IF(FCFF!$R$157="Revenue Exit",FCFF!$AF$169,IF(FCFF!$R$157="EBITDA Exit",FCFF!Z169,FCFF!AL169)) -> 2.9943439
C161: =+C162+1 -> 45965
C162: =+C163+1 -> 45964 | E162: =IF(FCFF!$R$157="Revenue Exit",FCFF!$AF$169,IF(FCFF!$R$157="EBITDA Exit",FCFF!Z169,FCFF!AL169)) -> 2.9943439
C163: =+C164+1 -> 45963 | E163: =E164+($E$162-$E$193)/COUNTA($C$162:$C$192) -> 3.0367844
C164: =+C165+1 -> 45962 | E164: =E165+($E$162-$E$193)/COUNTA($C$162:$C$192) -> 3.079225
C165: =+C166+1 -> 45961 | E165: =E166+($E$162-$E$193)/COUNTA($C$162:$C$192) -> 3.1216655
C166: =+C167+1 -> 45960 | E166: =E167+($E$162-$E$193)/COUNTA($C$162:$C$192) -> 3.164106
C167: =+C168+1 -> 45959 | E167: =E168+($E$162-$E$193)/COUNTA($C$162:$C$192) -> 3.2065465
C168: =+C169+1 -> 45958 | E168: =E169+($E$162-$E$193)/COUNTA($C$162:$C$192) -> 3.248987
C169: =+C170+1 -> 45957 | E169: =E170+($E$162-$E$193)/COUNTA($C$162:$C$192) -> 3.2914276
C170: =+C171+1 -> 45956 | E170: =E171+($E$162-$E$193)/COUNTA($C$162:$C$192) -> 3.3338681
C171: =+C172+1 -> 45955 | E171: =E172+($E$162-$E$193)/COUNTA($C$162:$C$192) -> 3.3763086
C172: =+C173+1 -> 45954 | E172: =E173+($E$162-$E$193)/COUNTA($C$162:$C$192) -> 3.4187491
C173: =+C174+1 -> 45953 | E173: =E174+($E$162-$E$193)/COUNTA($C$162:$C$192) -> 3.4611896
C174: =+C175+1 -> 45952 | E174: =E175+($E$162-$E$193)/COUNTA($C$162:$C$192) -> 3.5036301
... C192: =+C193+1 -> 45934 | E192: =E193+($E$162-$E$193)/COUNTA($C$162:$C$192) -> 4.2675595
B193: TODAY | C193: =+'Stock Data'!AM4 -> 45933 | D193: =_xlfn.XLOOKUP(C193,'Stock Data'!$AM$4:$AM$1051,'Stock Data'!$AN$4:$AN$1051) -> 4.31 | E193: =D193 -> 4.31
C194: =+'Stock Data'!AM5 -> 45932 | D194: =_xlfn.XLOOKUP(C194,'Stock Data'!$AM$4:$AM$1051,'Stock Data'!$AN$4:$AN$1051) -> 4.31
C195: =+'Stock Data'!AM6 -> 45931 | D195: =_xlfn.XLOOKUP(C195,'Stock Data'!$AM$4:$AM$1051,'Stock Data'!$AN$4:$AN$1051) -> 4.4
C196: =+'Stock Data'!AM7 -> 45930 | D196: =_xlfn.XLOOKUP(C196,'Stock Data'!$AM$4:$AM$1051,'Stock Data'!$AN$4:$AN$1051) -> 4.4
C197: =+'Stock Data'!AM8 -> 45929 | D197: =_xlfn.XLOOKUP(C197,'Stock Data'!$AM$4:$AM$1051,'Stock Data'!$AN$4:$AN$1051) -> 4.4
C198: =+'Stock Data'!AM9 -> 45928 | D198: =_xlfn.XLOOKUP(C198,'Stock Data'!$AM$4:$AM$1051,'Stock Data'!$AN$4:$AN$1051) -> 4.45
C199: =+'Stock Data'!AM10 -> 45927 | D199: =_xlfn.XLOOKUP(C199,'Stock Data'!$AM$4:$AM$1051,'Stock Data'!$AN$4:$AN$1051) -> 4.38
C200: =+'Stock Data'!AM11 -> 45926 | D200: =_xlfn.XLOOKUP(C200,'Stock Data'!$AM$4:$AM$1051,'Stock Data'!$AN$4:$AN$1051) -> 4.375
C201: =+'Stock Data'!AM12 -> 45925 | D201: =_xlfn.XLOOKUP(C201,'Stock Data'!$AM$4:$AM$1051,'Stock Data'!$AN$4:$AN$1051) -> 4.405
C202: =+'Stock Data'!AM13 -> 45924 | D202: =_xlfn.XLOOKUP(C202,'Stock Data'!$AM$4:$AM$1051,'Stock Data'!$AN$4:$AN$1051) -> 4.51
C203: =+'Stock Data'!AM14 -> 45923 | D203: =_xlfn.XLOOKUP(C203,'Stock Data'!$AM$4:$AM$1051,'Stock Data'!$AN$4:$AN$1051) -> 4.51
C204: =+'Stock Data'!AM15 -> 45922 | D204: =_xlfn.XLOOKUP(C204,'Stock Data'!$AM$4:$AM$1051,'Stock Data'!$AN$4:$AN$1051) -> 4.51
C205: =+'Stock Data'!AM16 -> 45921 | D205: =_xlfn.XLOOKUP(C205,'Stock Data'!$AM$4:$AM$1051,'Stock Data'!$AN$4:$AN$1051) -> 4.585
... C558: =+'Stock Data'!AM369 -> 45568 | D558: =_xlfn.XLOOKUP(C558,'Stock Data'!$AM$4:$AM$1051,'Stock Data'!$AN$4:$AN$1051) -> 5.055

Sheet Key Info
B7: Analysts | F7: LIS – Equity Research | J7: Stock Performance
B12: João Pedro Ferreira, Quantitative Research Head | F12: Recommendation: | H12: Strong Sell
B13: Bsc in Finance, ISEG – Ulisboa | F13: Target Price (FCFF): | H13: =+FCFF!AL169 -> -15.041035
B14: joao@aln.iseg.ulisboa.pt | F14: Downside: | H14: =+FCFF!$AL$171 -> -4.4897992
B15: José Gonçalves, Analyst
B16: Bsc in Management, ISEG – Ulisboa | F16: Ticker | H16: HBRE3
B17: l64272@aln.iseg.ulisboa.pt | F17: Stock Exchange | H17: BRL
B18: João Baiôa, Analyst
B19: Bsc in MAEG, ISEG – Ulisboa | F19: Current Price | H19: ='Stock Data'!AN4 -> 4.31
B20: l61773@aln.iseg.ulisboa.pt | F20: ="Market Cap (in "&IF(Inputs!$D$14="BLN","billions",IF(Inputs!$D$14="MLN","millions","thousands"))&")" -> Market Cap (in thousands) | H20: ='Stock Data'!AQ4 -> 444.7445
F21: Beta | H21: ='Stock Data'!E164 -> 1.475767
F22: % of 52-Week High | H22: ='Stock Data'!E165 -> 0.717687
F23: 100-Day Moving Average | H23: 3.79
B25: Reviewed by: | F25: Avg Vol (1 month) | H25: ='Stock Data'!E168 -> 576723.3
B26: Madalena Silva, Co-Head of Equity Research | F26: Shares Outstanding (millions) | H26: ='Stock Data'!E169 -> 103.189
B27: Bsc in Applied Mathematics in Economic and Management, ISEG – Ulisboa | F27: % Float | H27: ='Stock Data'!E170 -> 0.473
B28: l63835@aln.iseg.ulisboa.pt | F28: Short % of Float | H28: =IFERROR('Stock Data'!E171,0) -> 0
B30: LISBON INVESTMENT SOCIETY | F30: % Held by Insiders | H30: ='Stock Data'!E173 -> 0.034599994
B31: ISEG – Rua do Quelhas, 6 | F31: % Held by Institutions | H31: ='Stock Data'!E174 -> 0.4350661
B32: lis@iseg.ulisboa.pt
B34: Disclaimer: This report was prepared by members of the Lisbon Investment Society (LIS), an independent, student-led, non-profit organization based at ISEG – Lisbon School of Economics & Management, and is intended solely for academic and educational purposes. All analyses, forecasts, and opinions expressed in this report reflect the independent judgment of the authors as of the date of publication and are subject to change without notice. The views presented herein do not represent those of ISEG, its faculty, or any affiliated entity. This document does not constitute, and should not be interpreted as, investment advice, an offer, or a solicitation to buy or sell any security or financial instrument. Nothing in this report should be construed as a recommendation to make or refrain from making any investment decision. The content is intended for informational purposes only, and readers are strongly encouraged to conduct their own research and seek advice from a qualified financial professional before making any financial decisions. The information contained in this report has been obtained from publicly available sources believed to be reliable; however, no representation or warranty is made regarding the accuracy, completeness, or timeliness of such information. LIS and its members accept no liability whatsoever for any direct or indirect loss arising from the use of this report or its contents. This report incorporates terminology, financial metrics, and methodologies commonly used in professional equity research, including but not limited to Discounted Cash Flow (DCF), trading multiples, Monte Carlo simulations, and strategic analysis tools such as Porter’s Five Forces. Definitions and assumptions used in these models are disclosed within the report and reflect a hypothetical investment thesis designed solely for academic discussion. All valuations, projections, and target prices presented herein are based on publicly available data and subject to the limitations of modeling assumptions. These are not guarantees of future performance and should not be relied upon as such, as past performance is not indicative of future results. Any company names, logos, trademarks, or brand references mentioned in this report are the property of their respective owners and are used strictly for identification and academic purposes. This document may not be reproduced, redistributed, or quoted in whole or in part without the prior written consent of the Lisbon Investment Society. About LIS – Lisbon Investment Society: The Lisbon Investment Society (LIS) is a non-profit academic association headquartered at ISEG – Lisbon School of Economics & Management. Founded in 2016, LIS is committed to fostering student interest in finance and investment through applied research, skill development, and institutional engagement. The Society operates independently and autonomously from any political, religious, or commercial affiliation, and is composed of selected students and collaborators who are invited through a rigorous recruitment process and share a commitment to excellence, analytical rigor, and ethical standards. Its activities include equity research, portfolio management, macroeconomic analysis, and investment education. This report was prepared by the Equity Research team at the Lisbon Investment Society, whose analysts combine rigorous financial modeling, critical thinking, and collaborative research to deliver high-quality, student-led investment analysis. We welcome your feedback, discussion, and questions regarding this report or our research process, and invite you to reach out to our team as we are always open to engagement.

Sheet Industry
D6: 584.17 | E6: 627.76 | F6: 676.06 | G6: 729.63 | H6: 789.13 | I6: 855.3 | J6: 929 | K6: 997.69 | L6: 1067.63 | M6: 1137.57
A7: x | B7: Industry Growth Forecast | O7: Industry Index
B9: Brazilian Commercial Real Estate | D9: 2022 | E9: =+D9+1 -> 2023 | F9: =+E9+1 -> 2024 | G9: =+F9+1 -> 2025 | H9: =+G9+1 -> 2026 | I9: =+H9+1 -> 2027 | J9: =+I9+1 -> 2028 | K9: =+J9+1 -> 2029 | M9: ="CAGR "&$G$9&" - "&$K$9 -> CAGR 2025 - 2029
B12: Market Size - Mordor Intelligence | D12: 227.2 | E12: 292.6 | F12: 343.4 | G12: 380.7 | H12: 413.8 | I12: 449.8 | J12: 488.9 | K12: 531.4 | M12: =(K12/G12)^(1/5)-1 -> 0.068975458
B13: Market Share | D13: =+D21/(D12*1000) -> 0.0020484155 | E13: =+E21/(E12*1000) -> 0.0021408066 | F13: =+F21/(F12*1000) -> 0.00089545719 | G13: =+G21/(G12*1000) -> 0.0011688994 | H13: =+H21/(H12*1000) -> 0.00073350787 | I13: =+I21/(I12*1000) -> 0.00075568267 | J13: =+J21/(J12*1000) -> 0.00070464846 | K13: =+K21/(K12*1000) -> 0.00063907476 | M13: =((K13*K12)/(G13*G12))^(1/5)-1 -> -0.052623426
B14: Market Size - Growth Market Reports | D14: 194.7 | E14: 195.9 | F14: 220 | G14: 233.3 | H14: 242.7 | I14: 252.4 | J14: 262.4 | K14: 272.9 | M14: =(K14/G14)^(1/5)-1 -> 0.031852829
B15: Market Share | D15: =+D21/(D16*1000) -> 0.00037065945 | E15: =+E21/(E16*1000) -> 0.00050164171 | F15: =+F21/(F16*1000) -> 0.00022182946 | G15: =+G21/(G16*1000) -> 0.00030624183 | H15: =+H21/(H16*1000) -> 0.00020319022 | I15: =+I21/(I16*1000) -> 0.00022132183 | J15: =+J21/(J16*1000) -> 0.00021700953 | K15: =+K21/(K16*1000) -> 0.00020930929 | M15: =((K15*K14)/(G15*G14))^(1/5)-1 -> -0.043769569
B16: Market Size - IMARC Group | D16: 1255.6 | E16: 1248.7 | F16: 1386.2 | G16: 1453.1 | H16: 1493.8 | I16: 1535.8 | J16: 1587.5 | K16: 1622.5 | M16: =(K16/G16)^(1/5)-1 -> 0.022298775
B17: Market Share | D17: =+D21/(D16*1000) -> 0.00037065945 | E17: =+E21/(E16*1000) -> 0.00050164171 | F17: =+F21/(F16*1000) -> 0.00022182946 | G17: =+G21/(G16*1000) -> 0.00030624183 | H17: =+H21/(H16*1000) -> 0.00020319022 | I17: =+I21/(I16*1000) -> 0.00022132183 | J17: =+J21/(J16*1000) -> 0.00021700953 | K17: =+K21/(K16*1000) -> 0.00020930929 | M17: =((K17*K16)/(G17*G16))^(1/5)-1 -> -0.052623426
B19: Average | D19: =+AVERAGE(D13,D15,D17) -> 0.00092991146 | E19: =+AVERAGE(E13,E15,E17) -> 0.00104803 | F19: =+AVERAGE(F13,F15,F17) -> 0.00044637204 | G19: =+AVERAGE(G13,G15,G17) -> 0.00059379435 | H19: =+AVERAGE(H13,H15,H17) -> 0.00037996277 | I19: =+AVERAGE(I13,I15,I17) -> 0.00039944211 | J19: =+AVERAGE(J13,J15,J17) -> 0.00037955584 | K19: =+AVERAGE(K13,K15,K17) -> 0.00035256445
B20: Median | D20: =+MEDIAN(D17,D15,D13) -> 0.00037065945 | E20: =+MEDIAN(E17,E15,E13) -> 0.00050164171 | F20: =+MEDIAN(F17,F15,F13) -> 0.00022182946 | G20: =+MEDIAN(G17,G15,G13) -> 0.00030624183 | H20: =+MEDIAN(H17,H15,H13) -> 0.00020319022 | I20: =+MEDIAN(I17,I15,I13) -> 0.00022132183 | J20: =+MEDIAN(J17,J15,J13) -> 0.00021700953 | K20: =+MEDIAN(K17,K15,K13) -> 0.00020930929
D21: 465.4 | E21: 626.4 | F21: 307.5 | G21: 445 | H21: 303.52556 | I21: 339.90607 | J21: 344.50263 | K21: 339.60433
A23: x
B25: Industry Driver | D25: Description | O25: Porter's Five Forces
B27: Interest Rate Sensitivity | D27: Its business depends heavily on financing, mortgage credit and investment in construction; Interest rates are a key input for discounting future cash flows; Demand depends on buyers or tenants obtaining loans or financing; High interest rates make fixed-income investments relatively more attractive; If interest rates rise, their capital structure becomes heavier, increasing financial (solvency) risk and limiting their ability to expand.
B28: Economic growth and consumer purchasing power in Brazil | D28: It is forecasted a slower growth in GDP of 1.5-2% (worst in 6 years). Inflation is 5-5.5% (above target), so interest rates are high. This affects mostly low-middle class individuals which make up the biggest proportion of its business (convenience stores and shopping malls). The unemployment rate is the lowest of the last 12 years. The 'trade war' between Brazil and the United States remains intense and aggressive. As a consequence, it's expected to rise inflation, and delay the decrease of interest rates.
B29: Labour and Construction Material Cost | D29: Rising labour and construction-material costs materially worsen project economics for commercial real-estate developers: they raise CAPEX, compress margins, reducing returns and making marginal projects infeasible or likely to be delayed. For highly leveraged firms, coverage ratios deteriorate, and delays mean increase interest costs.
O32: Rivalry Among Existing Competitors | R32: 4.5
O33: Threat of New Entrants | R33: 2
O34: Threat of Substitutes | R34: 3
O35: Bargaining Power of Customers | R35: 2
O36: Bargaining Power of Suppliers | R36: 3.8

Sheet ESG
A7: x | B7: ESG Analysis
B12: ESG Scores | G12: GHG Scope 1 Emissions, Water Consumption, Energy Consumption and Waste Production per Sales
B15: ESG Score
B16: E-Score
B17: S-Score
B18: G-Score
B20: S&P Global ESG Score | D20: 29
B30: Key Info | G30: Environmental
H32: Overview | I32: Targets | J32: Improvements | K32: Comments
B33: GICS Sector | C33: Real Estate | G33: GHG Scope 1 Emissions | I33: Reduce Ethanol Emissions | J33: None | K33: The company released its first GHG inventory in 2024 but set no target for the future, only for ethanol veichles which represent .1% of their total emissions
B34: GICS Industry Group | C34: Real Estate Management and Development
B35: GICS Industry | C35: Real Estate Management and Development | G35: Water Consumption | I35: Transition from Artesian well to municipal | J35: 6% YoY reduction | K35: The 6% decrease is shown but not contextualized
B36: GICS Sub-Industry | C36: Real Estate Operating Companies
G37: Energy Consumption | I37: 100% Renewable sources across all operations by 2026 | J37: Solar initiative launched at ConVem Santana 2024. Ethanol over Gasoline | K37: Clear 2026 Target but massive increase in recent years, no clear efficiency targets,14.5% consumption increase in Suzano Shopping with no clear explanation
B38: Headquarters | C38: Mogi das Cruzes, São Paulo, Brazil
B39: Numer of Employees | G39: Waste Management | I39: 100% Waste diversion goal | J39: Composting and CDRU for non Recyclables introduced | K39: Still 63% to landfill despite the 0% goal with a 22% YoY increase, only 4/48 projects are reported in the data. The recycling rate as been stagnant (13%) from 2023-2024
B41: Annual Report
B42: Sustainability Report
B44: Recent Headlines | G44: Social
B46: since june | H46: Overview | I46: Targets | J46: Improvements | K46: Comments
B47: 30/9 / Sold Building in Sao Paulo for 319.5M | G47: Employee Turnover % | I47: None | J47: First GPTW Climate Survey, 87% participation, 69% favorability | K47: 40% Turnover in for an 80 person company is problematic, under 30 employees have 58% turnover and women have 45% to mens 32%
B48: 23/9 - Asset Recycling May reduce Net Debt by 40% says CEO
B49: 11/9 - HBR Realty announced the sale of 91% of the HBR Corporate Tower for R$477.2mn As HBR Realty holds 66.6% of the asset, the expected proceeds should total ~R$318mn. This sale represents 67.0% of the company's market cap and 16.7% of its EV | G49: Salaries & Compensation | I49: No Clear Target | J49: CEO comp increased 7.5% to average employee 10% increase | K49: Highest paid employee earns 21x average salary
G51: Reputation | I51: No Target | J51: Master Imobiliario and Abrasce 2024 awards | K51: Aqards given for honors in real estate but externally judged, but still strong presence as familly has been involved in real estate for 61 years
G53: Discrimination Events | I53: To maintain | J53: No discrimination cases in 2024 | K53: 0 cases don’t mean 0 occurences, 100% white male board, management 92% white and 58% male
G55: Work Safety | I55: No Target | J55: 0 workplace accidents, zero disceases, 100% covered by health insurance | K55: Doesn-t compare to industry performance, no data on previous year. Construction partners are not covered, likely for mall operations staff among other third parties
G57: Damage to consumer health | I57: No Target | J57: None | K57: No occurances related to consumer health were reported but HBR doesn’t report Indoor air quality, fire safety, food safety among other safety protocols. With 30 million mall visitiors 0 incidents are unlikely
G59: Pension Plan | I59: No Target | J59: None | K59: No private pension plan, or not disclosed, only Governament pension. HBR offers annual life insurance, PPR (profit sharing), gym membership, 95-100% meal vouchers, 40%-80% of scholarships
G61: Supply chain | I61: To have suppliers which provide livable conditions to employees | J61: None | K61: Clauses prohibiting child labor, forced labor, slavery-like conditions, 100% of suppliers going through renewal. Very general approach for supply chain analysis. No environmental data on supply chain partners
G63: Community involvement | I63: Expansion of charitable spaces within its properties and others | J63: Charitable donations to food banks, clothing and hygiene item, creation of autism support spaces | K63: The company is really involved in eachs mall community using its own spaces for the better of the community which demonstrate real activity and not just PR stunts
G65: Public Sector | I65: No Target | J65: None | K65: No comment
G67: Litigation | I67: To maintain no litigation issues | J67: None | K67: The company was involved in 0 corruption-related legal proceedings, but doesn’t mention third parties (construction) related incidents despite having joint liability risk
B70: Board of Directors | G70: Governance
B72: Name | C72: Position | E72: M/F – Age | H72: Overview | I72: Targets | J72: Improvements | K72: Comments
B73: Henrique Borenstein | C73: Chairman / Founder | E73: M - 89 | G73: Diversity (Gender, Age, Industry, Region) | I73: No Target | J73: Get more diversity in all aspects, age, gender and race | K73: All members of the board are middle aged to older white males. In management 92% white and 58% male, workforce 52% males
B74: Henry Borenstein | C74: Vice Chair | E74: M - 52
B75: Mario Mello Freire Neto | C75: Director | E75: M - 59 | G75: % Independence | I75: To move to a more independent board | J75: None | K75: 60% of all board members are independent, besides chair and vice-chair
B76: Jose Luis Acar Pedro | C76: Director | E76: M - 72
B77: Rodolpho Amboss | C77: Director | E77: M - 62 | G77: Average time as independent directors | I77: - | J77: - | K77: =+AVERAGE(5.2, 1.5, 5.2, 5.2, 5.2) -> 4.46
B79: Major Holders | G79: Departures of C-level executives | I79: None | J79: None | K79: CFO and CEO left after 2 and 12 years, respectively
B80: Name | E80: % Owned
B81: Hélio Borenstein S.A. Administração Partic. e Comércio | E81: 0.49 | G81: CEO/Chairman duality | I81: To maintain dynamic | J81: None | K81: CEO and Chair are separate persons
B82: Free float | E82: 0.473
B83: Henry Borenstein | E83: 0.0346 | G83: Transparency when reporting | K83: HBR tens to ommit key facts especially in serious matters, along with not showing previous years data, HBR shows critical data that may seem hard to believe without context (that they don’t give)
B84: Tresury | E84: 0.0024
G85: Time taken to report | I85: None | J85: None | K85: Nothing unusual with HBRs time to report
G87: CEO or Chairman in other boards? | I87: None | J87: None | K87: Henrique is Helbors Chairman, both companies are owned by the same holding comoany, Helio Borenstein S.A
G89: Audit / Consulting | I89: To improve | J89: None | K89: Audit board composed of 3 independent members
G91: ESG-compensation related | I91: None | J91: None | K91: The Company does not mention any plans or previous experience with ESG related compensation
G93: Management compensation schemes | I93: None | J93: None | K93: Fixed monthly Compensation, chair and bice receive higher compensations, Annual General Meetings determine the compensation

Sheet Segments
A7: x | B7: Segments | D7: =F7 -> 2020 | E7: =F7 -> 2020 | F7: 2020 | G7: =F7 -> 2020 | H7: =F7 -> 2020 | J7: =L7 -> 2021 | K7: =L7 -> 2021 | L7: 2021 | M7: =L7 -> 2021 | N7: =L7 -> 2021 | P7: =R7 -> 2022 | Q7: =R7 -> 2022 | R7: 2022 | S7: =R7 -> 2022 | T7: =R7 -> 2022 | V7: =X7 -> 2023 | W7: =X7 -> 2023 | X7: 2023 | Y7: =X7 -> 2023 | Z7: =X7 -> 2023 | AB7: =AD7 -> 2024 | AC7: =AD7 -> 2024 | AD7: 2024 | AE7: =AD7 -> 2024 | AF7: =AD7 -> 2024 | AH7: =AJ7 -> 2025 | AI7: =AJ7 -> 2025 | AJ7: 2025 | AK7: =AJ7 -> 2025 | AL7: =AJ7 -> 2025 | AN7: =AP7 -> 2025 | AO7: =AP7 -> 2025 | AP7: 2025 | AQ7: =AP7 -> 2025 | AR7: =AP7 -> 2025
D8: 2020 | J8: =D8+1 -> 2021 | P8: =J8+1 -> 2022 | V8: =P8+1 -> 2023 | AB8: =V8+1 -> 2024 | AH8: =AB8+1 -> 2025 | AN8: =AH8+1 -> 2026 | AT8: =AN8+1 -> 2027 | AV8: =+AT8+1 -> 2028 | AX8: =+AV8+1 -> 2029 | AZ8: CAGR
D9: Q1 | E9: Q2 | F9: Q3 | G9: Q4 | H9: FY | J9: Q1 | K9: Q2 | L9: Q3 | M9: Q4 | N9: FY | P9: Q1 | Q9: Q2 | R9: Q3 | S9: Q4 | T9: FY | V9: Q1 | W9: Q2 | X9: Q3 | Y9: Q4 | Z9: FY | AB9: Q1 | AC9: Q2 | AD9: Q3 | AE9: Q4 | AF9: FY | AH9: Q1 | AI9: Q2 | AJ9: Q3 | AK9: Q4 | AL9: FY | AN9: Q1 | AO9: Q2 | AP9: Q3 | AQ9: Q4 | AR9: FY | AT9: FY | AV9: FY | AX9: FY | AZ9: 2025-2029
B12: Revenue by segment:
B13: ComVem | H13: =IS!H13 -> 12513 | J13: =IS!J13 -> 0 | K13: =IS!K13 -> 0 | L13: =IS!L13 -> 0 | M13: =IS!M13 -> 0 | N13: =IS!N13 -> 11799 | P13: =IS!P13 -> 3799 | Q13: =IS!Q13 -> 4345 | R13: =IS!R13 -> 4263 | S13: =IS!S13 -> 4845 | T13: =IS!T13 -> 17252 | V13: =IS!V13 -> 5383 | W13: =IS!W13 -> 6445 | X13: =IS!X13 -> 4847 | Y13: =IS!Y13 -> 5228 | Z13: =IS!Z13 -> 21903 | AB13: =IS!AB13 -> 5301 | AC13: =IS!AC13 -> 5429 | AD13: =IS!AD13 -> 6314 | AE13: =IS!AE13 -> 6552 | AF13: =IS!AF13 -> 23596 | AL13: =IS!AL13 -> 34497.742 | AR13: =IS!AR13 -> 43401.727 | AT13: =IS!AT13 -> 53812.75 | AV13: =IS!AV13 -> 62636.8 | AX13: =IS!AX13 -> 71316.84 | AZ13: =+_xlfn.RRI(5, AL13,AX13) -> 0.15632598
B14: HBR 3A | H14: =IS!H14 -> 24451 | J14: =IS!J14 -> 0 | K14: =IS!K14 -> 0 | L14: =IS!L14 -> 0 | M14: =IS!M14 -> 0 | N14: =IS!N14 -> 8417 | P14: =IS!P14 -> 7737 | Q14: =IS!Q14 -> 7647 | R14: =IS!R14 -> 7466 | S14: =IS!S14 -> 7646 | T14: =IS!T14 -> 30496 | V14: =IS!V14 -> 7690 | W14: =IS!W14 -> 7832 | X14: =IS!X14 -> 7788 | Y14: =IS!Y14 -> 7804 | Z14: =IS!Z14 -> 31114 | AB14: =IS!AB14 -> 7785 | AC14: =IS!AC14 -> 7733 | AD14: =IS!AD14 -> 8071 | AE14: =IS!AE14 -> 8466 | AF14: =IS!AF14 -> 32055 | AL14: =IS!AL14 -> 48450.166 | AR14: =IS!AR14 -> 57549.104 | AT14: =IS!AT14 -> 69390.125 | AV14: =IS!AV14 -> 78296 | AX14: =IS!AX14 -> 86599.02 | AZ14: =+_xlfn.RRI(5, AL14,AX14) -> 0.12316495
B15: HBR Malls | H15: =IS!H15 -> 31749 | J15: =IS!J15 -> 0 | K15: =IS!K15 -> 0 | L15: =IS!L15 -> 0 | M15: =IS!M15 -> 0 | N15: =IS!N15 -> 37328 | P15: =IS!P15 -> 15286 | Q15: =IS!Q15 -> 12965 | R15: =IS!R15 -> 13301 | S15: =IS!S15 -> 14842 | T15: =IS!T15 -> 56394 | V15: =IS!V15 -> 12871 | W15: =IS!W15 -> 12671 | X15: =IS!X15 -> 14359 | Y15: =IS!Y15 -> 15805 | Z15: =IS!Z15 -> 55706 | AB15: =IS!AB15 -> 14831 | AC15: =IS!AC15 -> 14262 | AD15: =IS!AD15 -> 14908 | AE15: =IS!AE15 -> 17113 | AF15: =IS!AF15 -> 61114 | AL15: =IS!AL15 -> 88525.716 | AR15: =IS!AR15 -> 86818.453 | AT15: =IS!AT15 -> 92048.125 | AV15: =IS!AV15 -> 100218.88 | AX15: =IS!AX15 -> 106975.26 | AZ15: =+_xlfn.RRI(5, AL15,AX15) -> 0.038586757
B16: HBR Opportunities | H16: =IS!H16 -> 8620 | J16: =IS!J16 -> 0 | K16: =IS!K16 -> 0 | L16: =IS!L16 -> 0 | M16: =IS!M16 -> 0 | N16: =IS!N16 -> 30358 | P16: =IS!P16 -> 9452 | Q16: =IS!Q16 -> 10696 | R16: =IS!R16 -> 10820 | S16: =IS!S16 -> 11947 | T16: =IS!T16 -> 42915 | V16: =IS!V16 -> 11741 | W16: =IS!W16 -> 12755 | X16: =IS!X16 -> 13022 | Y16: =IS!Y16 -> 12095 | Z16: =IS!Z16 -> 49613 | AB16: =IS!AB16 -> 11281 | AC16: =IS!AC16 -> 13239 | AD16: =IS!AD16 -> 13432 | AE16: =IS!AE16 -> 13363 | AF16: =IS!AF16 -> 51315 | AL16: =IS!AL16 -> 71918.279 | AR16: =IS!AR16 -> 65918.918 | AT16: =IS!AT16 -> 65141.75 | AV16: =IS!AV16 -> 68900.48 | AX16: =IS!AX16 -> 71316.84 | AZ16: =+_xlfn.RRI(5, AL16,AX16) -> -0.0016781863
B17: Other & Holding | H17: =IS!H17 -> 0 | J17: =IS!J17 -> 0 | K17: =IS!K17 -> 0 | L17: =IS!L17 -> 0 | M17: =IS!M17 -> 0 | N17: =IS!N17 -> 0 | P17: =IS!P17 -> 1139 | Q17: =IS!Q17 -> 1164 | R17: =IS!R17 -> 1034 | S17: =IS!S17 -> 1046 | T17: =IS!T17 -> 4383 | V17: =IS!V17 -> 1037 | W17: =IS!W17 -> 980 | X17: =IS!X17 -> 995 | Y17: =IS!Y17 -> 997 | Z17: =IS!Z17 -> 4009 | AB17: =IS!AB17 -> 809 | AC17: =IS!AC17 -> 1187 | AD17: =IS!AD17 -> 1001 | AE17: =IS!AE17 -> 1099 | AF17: =IS!AF17 -> 4096 | AL17: =IS!AL17 -> 5113.5516 | AR17: =IS!AR17 -> 5144.5009 | AT17: =IS!AT17 -> 5381.275 | AV17: =IS!AV17 -> 5950.496 | AX17: =IS!AX17 -> 6452.476 | AZ17: =+_xlfn.RRI(5, AL17,AX17) -> 0.047612691
B18: Total revenue | D18: =IS!D18 -> 19810 | E18: =IS!E18 -> 18309 | F18: =IS!F18 -> 20789 | G18: =IS!G18 -> 21861 | H18: =IS!H18 -> 77333 | J18: =IS!J18 -> 19127 | K18: =IS!K18 -> 17498 | L18: =IS!L18 -> 22105 | M18: =IS!M18 -> 47678 | N18: =IS!N18 -> 87902 | P18: =IS!P18 -> 34134 | Q18: =IS!Q18 -> 34302 | R18: =IS!R18 -> 34378 | S18: =IS!S18 -> 38052 | T18: =IS!T18 -> 140866 | V18: =IS!V18 -> 52729 | W18: =IS!W18 -> 39112 | X18: =IS!X18 -> 38430 | Y18: =IS!Y18 -> 23111 | Z18: =IS!Z18 -> 153382 | AB18: =IS!AB18 -> 37691 | AC18: =IS!AC18 -> 39774 | AD18: =IS!AD18 -> 41539 | AE18: =IS!AE18 -> 43978 | AF18: =IS!AF18 -> 162982 | AH18: =IS!AH18 -> 45846 | AI18: =IS!AI18 -> 63997 | AJ18: =IS!AJ18 -> 58154.6 | AK18: =IS!AK18 -> 81089.4 | AL18: =IS!AL18 -> 249087 | AN18: =IS!AN18 -> 64306.262 | AO18: =IS!AO18 -> 64306.262 | AP18: =IS!AP18 -> 65306.262 | AQ18: =IS!AQ18 -> 63306.262 | AR18: =IS!AR18 -> 257225 | AT18: =IS!AT18 -> 283225 | AV18: =IS!AV18 -> 313184 | AX18: =IS!AX18 -> 339604
B20: Notes & Forecasts
C25: Considerable growth, with minimal impact from the partial sale of the Faria Lima "trophy" asset.
B26: HBR 3A | C26: Occupancy rate of 100% in operating projects.
C27: The second segment with the most assets under development with a total of 40.
C30: Slight reduction in share over time, even with occupancy improvements, as other segments grow faster.
B31: HBR Malls | C31: Global shopping center market is expected to grow at a CAGR of 7% until 2029. (Source: Research and Markets- Shopping Centers Market Report 2025)
C32: The two malls Mogi and Patteo Olinda are increasing their occupancy rates to the segment average of 92%.
C35: Consistent growth quarter by quarter, reflecting the expansion of essential projects and revenue increase.
B36: ComVem | C36: The segment includes resilient assets as they are positioned within the essential retail dynamics.
C37: The assets under development are located in prime areas of São Paulo, and revenue is expected to improve.
C38: One of the company’s main future focuses, with 54 assets under development.
C41: Gradual decline, despite strong seasonality in Q3 and Q4:
B42: HBR Opportunities | C42: In the hospitality segment, the 3rd and 4th quarters are typically stronger. Revenue from the W Hotel, the segment’s most notable asset, is expected to increase.
C43: No new project deliveries expected until 2030.

Sheet Peers
B7: Peers
A12: x | B12: Growth | C12: HBR REALTY EMPRE | D12: ALLOS SA | E12: JHSF PART | F12: MULTIPLAN | G12: IGUATEMI SA - UN | H12: WERELDHAVE NV | I12: CTO REALTY GROWT | J12: FOUR CORNERS PRO | K12: SUNWAY REAL ESTA | L12: TERA YATIRIM TEK
B14: Revenue (LTM) | C14: 0.3487 | D14: 0.0444 | E14: 0.164 | F14: 0.0685 | G14: 0.077 | H14: 0.043 | I14: 0.141 | J14: 0.07 | K14: 0.072 | L14: 0.604
B15: Revenue (3-yr CAGR) | C15: 0.2285 | D15: 0.716 | E15: 0.235 | F15: 0.083 | G15: 0.164 | H15: 0.0103 | I15: 0.21 | J15: N/A | K15: N/A | L15: 0.39
B16: Gross profit (LTM) | C16: 0.0745 | D16: 0.0447 | E16: 0.15 | F16: 0.0714 | G16: N/A | H16: 0.095 | I16: N/A | J16: 0.081 | K16: 0.081 | L16: 0.841
B17: EBIT (LTM) | C17: =((IS!AI33+IS!AH33+IS!AE33+IS!AD33)/(IS!AI18+IS!AH18+IS!AE18+IS!AD18))/((IS!AC33+IS!AB33-IS!Y33+IS!X33)/(IS!AC18+IS!AB18+IS!Y18+IS!X18))-1 -> 0.051218417 | D17: 0.0721 | E17: 0.201 | F17: 0.0902 | G17: N/A | H17: 0.422 | I17: 0.1271 | J17: 0.089 | K17: N/A | L17: 0.045
B18: EBITDA (LTM) | C18: 13,55% | D18: 0.082 | E18: 0.187 | F18: 0.0967 | G18: 0.154 | H18: 0.416 | I18: 0.169 | J18: 0.085 | K18: N/A | L18: 0.046
B19: FCF (LTM) | C19: 0.02909853 | D19: 0.125 | E19: 0.35 | F19: 0.0523 | G19: 0.232 | H19: 3.397 | I19: 0.179 | J19: 0.094 | K19: N/A | L19: N/A
A21: x | B21: Margins | C21: HBR REALTY EMPRE | D21: ALLOS SA | E21: JHSF PART | F21: MULTIPLAN | G21: IGUATEMI SA - UN | H21: WERELDHAVE NV | I21: CTO REALTY GROWT | J21: FOUR CORNERS PRO | K21: SUNWAY REAL ESTA | L21: TERA YATIRIM TEK
B23: Gross margin | C23: 68,54% | D23: 0.744 | E23: 0.589 | F23: 0.8335 | G23: N/A | H23: 0.7205 | I23: N/A | J23: 0.8485 | K23: 0.7427 | L23: 0.2886
B24: EBIT margin | C24: 48,2% | D24: 0.72 | E24: 0.72502018 | F24: 0.67180855 | G24: N/A | H24: 0.92166395 | I24: 0.14143223 | J24: 0.55645664 | K24: 0.67485981 | L24: N/A
B25: EBITDA margin | C25: =IS!AF34/IS!AF18 -> 0.58648808 | D25: 0.748 | E25: 0.77848615 | F25: 0.71390297 | G25: 0.775 | H25: 0.72239559 | I25: 0.46156629 | J25: 0.7598 | K25: N/A | L25: 0.28653702
B26: Net margin | C26: 0.2692949 | D26: 0.378 | E26: 0.51233745 | F26: 0.52688612 | G26: 0.376 | H26: 0.7276 | I26: -0.070503297 | J26: 0.37479716 | K26: 0.68403146 | L26: N/A
B27: SG&A margin | C27: =IS!AF27/IS!AF18 -> 0.29067627 | D27: 0.03 | E27: 0.08 | F27: 0.0995 | G27: N/A | H27: 0.0738 | I27: N/A | J27: 0.0887 | K27: N/A | L27: N/A
B29: Returns | C29: HBR REALTY EMPRE | D29: ALLOS SA | E29: JHSF PART | F29: MULTIPLAN | G29: IGUATEMI SA - UN | H29: WERELDHAVE NV | I29: CTO REALTY GROWT | J29: FOUR CORNERS PRO | K29: SUNWAY REAL ESTA | L29: TERA YATIRIM TEK
A30: x
B31: ROIC | C31: 0.055446469 | D31: 0.118 | E31: 0.039 | F31: 0.14442572 | G31: N/A | H31: N/A | I31: N/A | J31: N/A | K31: 0.056177833 | L31: N/A
B32: CROIC | C32: -0,46% | D32: 0.136 | E32: 0.032 | F32: N/A | G32: N/A | H32: N/A | I32: N/A | J32: N/A | K32: N/A | L32: N/A
B33: ROCE | C33: 4,1% | D33: 0.145 | E33: 0.145 | F33: N/A | G33: N/A | H33: 0.08 | I33: N/A | J33: N/A | K33: N/A | L33: 0.3745
B34: RONA | C34: 0.095972888 | D34: 0.092 | E34: 0.092 | F34: N/A | G34: N/A | H34: N/A | I34: N/A | J34: N/A | K34: N/A | L34: N/A
B35: ROE | C35: 0.04 | D35: 0.094 | E35: 0.19 | F35: 0.19747396 | G35: 0.2 | H35: 0.1166 | I35: -0.0164 | J35: 0.0742 | K35: 0.0977 | L35: 0.2381
B36: ROA | C36: 2,3% | D36: 0.057 | E36: 0.074 | F36: 0.10749069 | G36: N/A | H36: 0.0603 | I36: -0.0018 | J36: 0.0394 | K36: 0.0486 | L36: 0.1838
B38: Efficiency | C38: HBR REALTY EMPRE | D38: ALLOS SA | E38: JHSF PART | F38: MULTIPLAN | G38: IGUATEMI SA - UN | H38: WERELDHAVE NV | I38: CTO REALTY GROWT | J38: FOUR CORNERS PRO | K38: SUNWAY REAL ESTA | L38: TERA YATIRIM TEK
A39: x
B40: Asset turnover | C40: 0,077 | D40: 0.14 | E40: 0.12 | F40: 0.22500014 | G40: N/A | H40: 0.08336662 | I40: 0.11 | J40: 0.10642623 | K40: 0.079963514 | L40: 0.0145
B41: Net operating asset turnover | C41: 0,079 | D41: 0.16 | E41: 0.13 | F41: N/A | G41: N/A | H41: N/A | I41: N/A | J41: N/A | K41: N/A | L41: N/A
B42: Fixed asset turnover | C42: 0,087 | D42: 0.16 | E42: 0.1 | F42: 0.29 | G42: N/A | H42: 0.09 | I42: 0.15 | J42: 0.11 | K42: N/A | L42: 0.018
B44: Working Capital | C44: HBR REALTY EMPRE | D44: ALLOS SA | E44: JHSF PART | F44: MULTIPLAN | G44: IGUATEMI SA - UN | H44: WERELDHAVE NV | I44: CTO REALTY GROWT | J44: FOUR CORNERS PRO | K44: SUNWAY REAL ESTA | L44: TERA YATIRIM TEK
B46: DSO | C46: 25 | D46: 23 | E46: 25 | F46: 107 | G46: N/A | H46: N/A | I46: N/A | J46: N/A | K46: N/A | L46: 235
A47: x | B47: DIO | C47: 0 | D47: 0 | E47: 0 | F47: N/A | G47: N/A | H47: N/A | I47: N/A | J47: N/A | K47: N/A | L47: N/A
B48: DPO | C48: 45 | D48: 47 | E48: 50 | F48: N/A | G48: N/A | H48: N/A | I48: N/A | J48: N/A | K48: N/A | L48: 1672
B49: CCC | C49: 20 | D49: N/A | E49: N/A | F49: N/A | G49: N/A | H49: N/A | I49: N/A | J49: N/A | K49: N/A | L49: -1104.5403
B50: Working capital intensity | C50: 0.068 | D50: 0.075 | E50: N/A | F50: N/A | G50: N/A | H50: N/A | I50: N/A | J50: N/A | K50: N/A | L50: -1.63
B51: Cash conversion ratio | C51: 0.927 | D51: 0.923 | E51: 0.27292975 | F51: N/A | G51: N/A | H51: N/A | I51: N/A | J51: N/A | K51: N/A | L51: 0.26
B52: CFO margin | C52: 0.447 | D52: 0.66 | E52: 0.19787958 | F52: 0.538447 | G52: 0.525 | H52: 0.48071268 | I52: N/A | J52: N/A | K52: N/A | L52: 5.86
B54: Leverage & Coverage | C54: HBR REALTY EMPRE | D54: ALLOS SA | E54: JHSF PART | F54: MULTIPLAN | G54: IGUATEMI SA - UN | H54: WERELDHAVE NV | I54: CTO REALTY GROWT | J54: FOUR CORNERS PRO | K54: SUNWAY REAL ESTA | L54: TERA YATIRIM TEK
B56: Net debt / EBITDA | C56: 5.467815 | D56: 3.45 | E56: 1.86 | F56: 2.31 | G56: 1.84 | H56: 5.25 | I56: 6.07 | J56: 5.2620324 | K56: 8.09 | L56: 0.29
A57: x | B57: Net debt / FCF | C57: 9.1 | D57: 5.17 | E57: 7.6 | F57: 6.25 | G57: 2.71 | H57: 17.597718 | I57: 9.87 | J57: 7.01 | K57: N/A | L57: 8.26
B58: Interest coverage | C58: 0.5 | D58: 3 | E58: 3 | F58: 4.6 | G58: N/A | H58: 4.1 | I58: 2.8 | J58: 4.5 | K58: 3.1071847 | L58: 11.2
B59: Debt / capital | C59: 0.57 | D59: 0.394 | E59: 0.39 | F59: 0.49191878 | G59: N/A | H59: 0.42980635 | I59: 0.0046 | J59: 0.33 | K59: 0.43203985 | L59: 0.11030314
B60: Short term debt / total debt | C60: 0.25 | D60: 0.142 | E60: 0.25 | F60: N/A | G60: N/A | H60: N/A | I60: N/A | J60: 0.004 | K60: N/A | L60: 0.0015
B62: Liquidity | C62: HBR REALTY EMPRE | D62: ALLOS SA | E62: JHSF PART | F62: MULTIPLAN | G62: IGUATEMI SA - UN | H62: WERELDHAVE NV | I62: CTO REALTY GROWT | J62: FOUR CORNERS PRO | K62: SUNWAY REAL ESTA | L62: TERA YATIRIM TEK
B64: Current ratio | C64: 0.83 | D64: 1.2 | E64: 2.48 | F64: N/A | G64: N/A | H64: N/A | I64: N/A | J64: 0.56 | K64: N/A | L64: 0.58761889
A65: x | B65: Quick ratio | C65: 0.76 | D65: 1.1 | E65: 2.44 | F65: N/A | G65: N/A | H65: N/A | I65: N/A | J65: 0.5 | K65: N/A | L65: 0.12452454
B66: Cash ratio | C66: 0.16 | D66: 0.05 | E66: 0.08 | F66: N/A | G66: N/A | H66: N/A | I66: N/A | J66: 0.06 | K66: N/A | L66: 0.0086404304
B68: Cash Deployment | C68: HBR REALTY EMPRE | D68: ALLOS SA | E68: JHSF PART | F68: MULTIPLAN | G68: IGUATEMI SA - UN | H68: WERELDHAVE NV | I68: CTO REALTY GROWT | J68: FOUR CORNERS PRO | K68: SUNWAY REAL ESTA | L68: TERA YATIRIM TEK
B70: Capex intensity | C70: 0.501 | D70: 0.177 | E70: 0.126 | F70: N/A | G70: 0.181 | H70: 0.2052 | I70: N/A | J70: N/A | K70: N/A | L70: 5.07
A71: x | B71: Capex / depreciation | C71: N/A | D71: 6.82 | E71: 2.9 | F71: N/A | G71: N/A | H71: 33.45 | I71: N/A | J71: N/A | K71: N/A | L71: N/A
B72: Dividend payout | C72: 0 | D72: 0.49 | E72: 0.2 | F72: 0.4302 | G72: 0.501 | H72: 0.471 | I72: 0.809 | J72: 0.802 | K72: 0.655 | L72: N/A
B73: FCF payout | C73: 0 | D73: 0.51 | E73: 0.44 | F73: N/A | G73: 0.289 | H73: 1.224 | I73: 0.76 | J73: 0.802 | K73: N/A | L73: N/A
B74: Buybacks as % CFO | C74: 0 | D74: 0.556 | E74: 0 | F74: N/A | G74: N/A | H74: 0.035 | I74: N/A | J74: 0 | K74: N/A | L74: N/A
B76: Earnings Quality | C76: HBR REALTY EMPRE | D76: ALLOS SA | E76: JHSF PART | F76: MULTIPLAN | G76: IGUATEMI SA - UN | H76: WERELDHAVE NV | I76: CTO REALTY GROWT | J76: FOUR CORNERS PRO | K76: SUNWAY REAL ESTA | L76: TERA YATIRIM TEK
B78: Cash/earnings conversion | C78: 1.516 | D78: 1.76 | E78: 1.8 | F78: 1.11 | G78: 1.74 | H78: 0.66 | I78: N/A | J78: N/A | K78: N/A | L78: 0.46
B79: FCF / net income | C79: -0.184 | D79: 1.324 | E79: 1.24 | F79: 0.51 | G79: 1.74 | H79: 0.38 | I79: N/A | J79: 1.62 | K79: N/A | L79: 0.06
A81: x | B81: Per Share & Dilution | C81: HBR REALTY EMPRE | D81: ALLOS SA | E81: JHSF PART | F81: MULTIPLAN | G81: IGUATEMI SA - UN | H81: WERELDHAVE NV | I81: CTO REALTY GROWT | J81: FOUR CORNERS PRO | K81: SUNWAY REAL ESTA | L81: TERA YATIRIM TEK
B83: Diluted share count YoY | C83: 0 | D83: -0.117 | E83: -0.003 | F83: N/A | G83: N/A | H83: N/A | I83: N/A | J83: 0.055 | K83: N/A | L83: N/A
B84: SBC / revenue | C84: 0 | D84: 0 | E84: 0 | F84: N/A | G84: N/A | H84: N/A | I84: N/A | J84: 0.026063796 | K84: N/A | L84: N/A
B85: SBC / CFO | C85: 0 | D85: 0 | E85: 0 | F85: N/A | G85: N/A | H85: N/A | I85: N/A | J85: 0.048485479 | K85: N/A | L85: N/A
A86: x | B86: EPS in USD | C86: 0.09 | D86: 0.26 | E86: 0.1 | F86: 0.51 | G86: N/A | H86: 1.7687763 | I86: 0.35 | J86: 1.08 | K86: 0.04 | L86: 0.02

Sheet Trading Comps
B7: ="in "&IF(Inputs!$R$18="k","thousands",IF(Inputs!$R$18="MLN","millions","billions")&" of "&Inputs!$R$17) -> in thousands | D7: Current | E7: % of | I7: Enterprise Value / | S7: LTM | T7: Net | V7: Price / | Z7: LT
D8: Share | E8: 52-week | F8: Equity | G8: Enterprise | I8: LTM | J8: 2025 | K8: 2026 | L8: LTM | M8: 2025E | N8: 2026E | O8: LTM | P8: 2025E | Q8: 2026E | S8: EBITDA | T8: Debt / | V8: LTM | W8: 2025E | X8: 2026E | Z8: EPS
B9: Company | C9: Ticker | D9: Price | E9: High | F9: Value | G9: Value | I9: Sales | J9: Sales | K9: Sales | L9: EBITDA | M9: EBITDA | N9: EBITDA | O9: EBIT | P9: EBIT | Q9: EBIT | S9: Margin | T9: EBITDA | V9: EPS | W9: EPS | X9: EPS | Z9: Growth
B14: HBR REALTY EMPRE | C14: HBRE3 BZ | D14: BRL 4.78 | E14: 0.87067395 | F14: 4.9014766e+08 | G14: 3.04 B | I14: 14.42 | J14: 5.9 | K14: 7.35 | L14: 30.2 | M14: 12.31 | N14: 15.48 | O14: =+Inputs!J18/SUM(IS!AH34:AI34,IS!AD34:AE34) -> 30.19932 | P14: =+Inputs!J18/FCFF!Z61 -> 28.560331 | Q14: =+Inputs!J18/FCFF!AF61 -> 26.88288 | S14: 0.49275452 | T14: =+FCFF!Z164/(FCFF!Z128+FCFF!Z122) -> 14.857587 | V14: =4.64/0.21 -> 22.095238 | W14: -32 | X14: -15 | Z14: =+AVERAGE(W15:X15) -> -1.4897629
W15: =+W14/V14-1 -> -2.4482759 | X15: =+X14/W14-1 -> -0.53125
B16: Tier I: Real Estate Operating Companies
B19: =+Inputs!B21 -> ALLOS SA | C19: ALOS3 BZ | D19: BRL 24.4 | E19: 0.98307816 | F19: 13247661 | G19: 17958489 | I19: 6.1609046 | J19: 6.3937654 | K19: 6.0977863 | L19: 9.2889904 | M19: 8.6004343 | N19: 8.2636844 | O19: 13.577432 | P19: 11.861617 | Q19: 11.511852 | S19: 0.66324804 | T19: 2.9370158 | V19: 22.777528 | W19: 16.909291 | X19: 16.195844 | Z19: 0.14099033
B20: =+Inputs!B22 -> JHSF PART | C20: JHSF3 BZ | D20: BRL 5.51 | E20: 0.95826087 | F20: 3754088.4 | G20: 7874342.7 | I20: 3.5189841 | J20: 3.7134368 | K20: 3.3365859 | L20: 8.738405 | M20: 9.0770522 | N20: 8.076249 | O20: 9.4580678 | P20: 10.669841 | Q20: 9.7094238 | S20: 0.40270325 | T20: 3.2069134 | V20: 12.430592 | W20: 6.7337908 | X20: 7.5081768
B21: =+Inputs!B23 -> LOG COMMERCIAL P | C21: LOGG3 BZ | D21: BRL 21.77 | E21: 0.91701769 | F21: 1912693.8 | G21: 3850355.1 | I21: 16.792292 | J21: 15.667772 | K21: 13.052051 | L21: -11.140912 | M21: 14.584678 | N21: 16.961917 | O21: -10.937173 | P21: 13.353833 | Q21: 17.448739 | S21: -1.5072636 | T21: 4.7939948 | V21: -3.752985 | W21: 7.3096578 | X21: 8.9896308 | Z21: -0.16929348
B22: =+Inputs!B24 -> MULTIPLAN | C22: MULT3 BZ | D22: BRL 28.4 | E22: 0.98611111 | F22: 14573849 | G22: 18280671 | I22: 6.7676311 | J22: 7.5756484 | K22: 7.2420207 | L22: 9.4797631 | M22: 10.12032 | N22: 9.3714991 | O22: 10.23563 | P22: 11.071874 | Q22: 10.25642 | S22: 0.71390297 | T22: 2.6573663 | V22: 11.293557 | W22: 14.510968 | X22: 13.179065 | Z22: 0.13662818
B23: =+Inputs!B25 -> IGUATEMI SA - UN | C23: IGTI11 BZ | D23: BRL 23.75 | E23: 0.98547718 | F23: 6772056.6 | G23: 5795567.8 | I23: 4.2476794 | J23: 3.7592872 | K23: 3.5032648 | L23: 6.2618096 | M23: 5.2306568 | N23: 4.8451173 | O23: 7.5130903 | P23: 5.6377118 | Q23: 5.632233 | S23: 0.67834695 | T23: 3.4942432 | V23: 17.070442 | W23: 12.64033 | X23: 11.870388 | Z23: 0.091667043
B25: Mean | I25: =AVERAGE(I19:I23) -> 7.4974983 | J25: =AVERAGE(J19:J23) -> 7.421982 | K25: =AVERAGE(K19:K23) -> 6.6463418 | L25: =AVERAGE(L19:L23) -> 4.5256111 | M25: =AVERAGE(M19:M23) -> 9.5226282 | N25: =AVERAGE(N19:N23) -> 9.5036932 | O25: =AVERAGE(O19:O23) -> 5.9694094 | P25: =AVERAGE(P19:P23) -> 10.518975 | Q25: =AVERAGE(Q19:Q23) -> 10.911734 | S25: =AVERAGE(S19:S23) -> 0.19018752 | T25: =AVERAGE(T19:T23) -> 3.4179067 | V25: =AVERAGE(V19:V23) -> 11.963826 | W25: =AVERAGE(W19:W23) -> 11.620807 | X25: =AVERAGE(X19:X23) -> 11.548621 | Z25: =AVERAGE(Z19:Z23) -> 0.049998017
B26: Median | I26: =MEDIAN(I19:I23) -> 6.1609046 | J26: =MEDIAN(J19:J23) -> 6.3937654 | K26: =MEDIAN(K19:K23) -> 6.0977863 | L26: =MEDIAN(L19:L23) -> 8.738405 | M26: =MEDIAN(M19:M23) -> 9.0770522 | N26: =MEDIAN(N19:N23) -> 8.2636844 | O26: =MEDIAN(O19:O23) -> 9.4580678 | P26: =MEDIAN(P19:P23) -> 11.071874 | Q26: =MEDIAN(Q19:Q23) -> 10.25642 | S26: =MEDIAN(S19:S23) -> 0.66324804 | T26: =MEDIAN(T19:T23) -> 3.2069134 | V26: =MEDIAN(V19:V23) -> 12.430592 | W26: =MEDIAN(W19:W23) -> 12.64033 | X26: =MEDIAN(X19:X23) -> 11.870388 | Z26: =MEDIAN(Z19:Z23) -> 0.11414761
B28: Tier II: Real Estate Management and Development
B31: =+Inputs!H21 -> PTA LOG IMO RESP | C31: No Data Avaliable
B32: =+Inputs!H22 -> KINEA-RENDA IMOB
B33: =+Inputs!H23 -> XP LOG FII
B34: =+Inputs!H24 -> FII REC REND
B35: =+Inputs!H25 -> FII BTG PACTUAL
B37: Mean
B38: Median
B40: Tier III: Real Estate
B41: dddddd
B43: WERELDHAVE NV | C43: WHA NA | D43: EUR 18.84 | E43: 0.98022893 | F43: 877824.94 | G43: 2078457.4 | I43: 10.214001 | J43: 11.33704 | K43: 11.016558 | L43: 15.629614 | M43: 11.775962 | N43: 11.676727 | O43: 15.775887 | P43: 11.775962 | Q43: 11.676727 | S43: 0.6535031 | T43: 7.3687662 | V43: 12.088082 | W43: 12.277272 | X43: 11.975784 | Z43: #N/A
B44: CTO REALTY GROWT | C44: CTO US | D44: USD 16.53 | E44: 0.79166667 | F44: 544491.75 | G44: 1283363.9 | I44: 9.10213 | J44: 8.5700429 | K44: 7.9097931 | L44: 14.92301 | M44: 15.027681 | N44: 12.340038 | O44: 93.18646 | P44: 69.296108 | Q44: 34.437315 | S44: 0.60993929 | T44: 9.306151 | V44: -36.450111 | W44: -21.18645 | X44: 128.19413 | Z44: #N/A
B45: FOUR CORNERS PRO | C45: FCPT US | D45: USD 25.45 | E45: 0.82282574 | F45: 2658616.7 | G45: 3955699.4 | I45: 14.155556 | J45: 14.48311 | K45: 13.324461 | L45: 17.309398 | M45: 17.580886 | N45: 15.835466 | O45: 25.407537 | P45: 23.973936 | Q45: 21.576542 | S45: 0.81779599 | T45: 5.2882041 | V45: 25.119918 | W45: 23.398167 | X45: 20.954615 | Z45: 0.063048107
B46: SUNWAY REAL ESTA | C46: SREIT MK | D46: MYR 2.06 | E46: 0.88793103 | F46: 7055103.9 | G46: 11327202 | I46: 13.432776 | J46: 13.323508 | K46: 13.243424 | L46: #N/A | M46: 19.690921 | N46: 19.001388 | O46: 19.963697 | P46: 19.358012 | Q46: 18.856222 | S46: #N/A | T46: #N/A N/A | V46: 16.831208 | W46: 17.716853 | X46: 17.091444 | Z46: 0.030941096
B47: TERA YATIRIM TEK | C47: TEHOL TI | D47: TRY 33.2 | E47: 0.97704532 | F47: 33669821 | G47: #N/A N/A | I47: #VALUE! | J47: #VALUE! | K47: #VALUE! | L47: #VALUE! | M47: #VALUE! | N47: #VALUE! | O47: #VALUE! | P47: #VALUE! | Q47: #VALUE! | S47: -26.401705 | T47: #N/A N/A | V47: -121.76453 | W47: #N/A | X47: #N/A | Z47: #N/A
B49: Mean | I49: =+AVERAGE(I43:I46) -> 11.726116 | J49: =+AVERAGE(J43:J46) -> 11.928425 | K49: =+AVERAGE(K43:K46) -> 11.373559 | L49: =+AVERAGE(L43:L45) -> 15.954007 | M49: =+AVERAGE(M43:M46) -> 16.018862 | N49: =+AVERAGE(N43:N46) -> 14.713405 | O49: =+AVERAGE(O43:O46) -> 38.583395 | P49: =+AVERAGE(P43:P46) -> 31.101004 | Q49: =+AVERAGE(Q43:Q46) -> 21.636701 | S49: =+AVERAGE(S43:S45) -> 0.69374613 | T49: =+AVERAGE(T43:T45) -> 7.3210404 | V49: =AVERAGE(V43:V47) -> -20.835086 | W49: =+AVERAGE(W43:W46) -> 8.0514606 | X49: =+AVERAGE(X43:X46) -> 44.553993 | Z49: =AVERAGE(Z43:Z47) -> #N/A
B50: Median | I50: =+MEDIAN(I43:I46) -> 11.823389 | J50: =+MEDIAN(J43:J46) -> 12.330274 | K50: =+MEDIAN(K43:K46) -> 12.129991 | L50: =+MEDIAN(L43:L45) -> 15.629614 | M50: =+MEDIAN(M43:M46) -> 16.304283 | N50: =+MEDIAN(N43:N46) -> 14.087752 | O50: =+MEDIAN(O43:O46) -> 22.685617 | P50: =+MEDIAN(P43:P46) -> 21.665974 | Q50: =+MEDIAN(Q43:Q46) -> 20.216382 | S50: =+MEDIAN(S43:S45) -> 0.6535031 | T50: =MEDIAN(T43:T47) -> 7.3687662 | V50: =MEDIAN(V43:V47) -> 12.088082 | W50: =+MEDIAN(W43:W46) -> 14.997062 | X50: =+MEDIAN(X43:X46) -> 19.023029 | Z50: =MEDIAN(Z43:Z47) -> #N/A
B52: Overall
B55: Mean | I55: =+AVERAGE(I43:I46,I19:I23) -> 9.3768839 | J55: =+AVERAGE(J43:J46,J19:J23) -> 9.4248457 | K55: =+AVERAGE(K43:K46,K19:K23) -> 8.7473272 | L55: =+AVERAGE(L43:L45,L19:L23) -> 8.8112597 | M55: =+AVERAGE(M43:M46,M19:M23) -> 12.409843 | N55: =+AVERAGE(N43:N46,N19:N23) -> 11.81912 | O55: =+AVERAGE(O43:O46,O19:O23) -> 20.464514 | P55: =+AVERAGE(P43:P46,P19:P23) -> 19.666544 | Q55: =+AVERAGE(Q43:Q46,Q19:Q23) -> 15.678386 | S55: =+AVERAGE(S43:S45,S19:S23) -> 0.37902199 | T55: =+AVERAGE(T19:T23,T43:T45) -> 4.8815819 | V55: =+AVERAGE(V43:V47,V35,V19:V23) -> -4.4356297 | W55: =+AVERAGE(W43:W46,W19:W23) -> 10.034431 | X55: =+AVERAGE(X43:X46,X19:X23) -> 26.217675 | Z55: =+AVERAGE(Z19,Z21,Z22,Z45,Z46) -> 0.040462845
B56: Median | I56: =+MEDIAN(I43:I46,I19:I23) -> 9.10213 | J56: =+MEDIAN(J43:J46,J19:J23) -> 8.5700429 | K56: =+MEDIAN(K43:K46,K19:K23) -> 7.9097931 | L56: =+MEDIAN(L43:L45,L19:L23) -> 9.3843767 | M56: =+MEDIAN(M43:M46,M19:M23) -> 11.775962 | N56: =+MEDIAN(N43:N46,N19:N23) -> 11.676727 | O56: =+MEDIAN(O43:O46,O19:O23) -> 13.577432 | P56: =+MEDIAN(P43:P46,P19:P23) -> 11.861617 | Q56: =+MEDIAN(Q43:Q46,Q19:Q23) -> 11.676727 | R56: =+MEDIAN(R43:R46,R19:R23) -> #NUM! | S56: =+MEDIAN(S43:S45,S19:S23) -> 0.65837557 | T56: =+MEDIAN(T43:T45,T19:T23) -> 4.144119 | V56: =+MEDIAN(V43:V47,V19:V23) -> 12.259337 | W56: =+MEDIAN(W43:W46,W19:W23) -> 12.64033 | X56: =+MEDIAN(X43:X46,X19:X23) -> 13.179065 | Z56: =+MEDIAN(Z46,Z45,Z23,Z22,Z21,Z19) -> 0.077357575
B58: High | I58: =+MAX(I19:I23,I43:I46) -> 16.792292 | J58: =+MAX(J19:J23,J43:J46) -> 15.667772 | K58: =+MAX(K19:K23,K43:K46) -> 13.324461 | L58: =+MAX(L19:L23,L43:L45) -> 17.309398 | M58: =+MAX(M19:M23,M43:M46) -> 19.690921 | N58: =+MAX(N19:N23,N43:N46) -> 19.001388 | O58: =+MAX(O19:O23,O43:O46) -> 93.18646 | P58: =+MAX(P19:P23,P43:P46) -> 69.296108 | Q58: =+MAX(Q19:Q23,Q43:Q46) -> 34.437315 | S58: =+MAX(S43:S45,S19:S23) -> 0.81779599 | T58: =MAX(T43:T47,T31:T35,T19:T23) -> 9.306151 | V58: =+MAX(V43:V47,V35,V19:V23) -> 25.119918 | W58: =+MAX(W43:W46,W19:W23) -> 23.398167 | X58: =+MAX(X43:X46,X19:X23) -> 128.19413 | Z58: =MAX(Z43:Z47,Z31:Z35,Z19:Z23) -> #N/A
B59: Low | I59: =+MIN(I43:I46,I19:I23) -> 3.5189841 | J59: =+MIN(J43:J46,J19:J23) -> 3.7134368 | K59: =+MIN(K43:K46,K19:K23) -> 3.3365859 | L59: =+MIN(L43:L45,L19:L23) -> -11.140912 | M59: =+MIN(M43:M46,M19:M23) -> 5.2306568 | N59: =+MIN(N43:N46,N19:N23) -> 4.8451173 | O59: =+MIN(O43:O46,O19:O23) -> -10.937173 | P59: =+MIN(P43:P46,P19:P23) -> 5.6377118 | Q59: =+MIN(Q43:Q46,Q19:Q23) -> 5.632233 | S59: =+MIN(S43:S45,S19:S23) -> -1.5072636 | T59: =+MIN(T43:T45,T19:T23) -> 2.6573663 | V59: =+MIN(V43:V47,V19:V23,V35) -> -121.76453 | W59: =+MIN(W43:W46,W19:W23) -> -21.18645 | X59: =+MIN(X43:X46,X19:X23) -> 7.5081768 | Z59: =MIN(Z43:Z47,Z31:Z35,Z19:Z23) -> #N/A
C61: Price/Book | F61: NAV
B62: HBR REALTY EMPRE | C62: 0.24 | F62: =3397-1433-76.519-(705/2)+(319.5*0.7) -> 1758.631
B63: ALLOS | C63: 0.94
B64: JHSF | C64: 0.71
B65: LOG COM | C65: 0.53 | D65: jscs
B66: multiplan | C66: 2.35
B67: Iguatemi | C67: 0.76
B68: Mean | C68: =SUM(C63:C67)/5 -> 1.058
B69: Median | C69: =C67 -> 0.76

Sheet Assumptions
B3: Revenue
B6: Main Driver
B7: Gross Leasable Area (GLA)
J8: Forecast
C9: 2020 | D9: =+C9+1 -> 2021 | E9: 2022 | F9: =+E9+1 -> 2023 | G9: =+F9+1 -> 2024 | H9: 2025 | I9: Average | J9: 2026 | K9: =+J9+1 -> 2027 | L9: =+K9+1 -> 2028 | M9: =+L9+1 -> 2029 | N9: CAGR
B10: Total Revenue | C10: 77333 | D10: 105657 | E10: 140866 | F10: 153382 | G10: 176925 | H10: =+FCFF!Z31 -> 249087 | J10: =+J12*($I$22*(1+$I$23))/1000 -> 306468.31 | K10: =+K12*($I$22*(1+$I$23))/1000 -> 347931.27 | L10: =+L12*($I$22*(1+$I$23))/1000 -> 384532.92 | M10: =+M12*($I$22*(1+$I$23))/1000 -> 416843.22 | N10: =+_xlfn.RRI(COUNT(J9:M9), J10,M10) -> 0.079932954
B11: growth % | D11: =+D10/C10-1 -> 0.3662602 | E11: =+E10/D10-1 -> 0.33323869 | F11: =+F10/E10-1 -> 0.088850397 | G11: =+G10/F10-1 -> 0.15349259 | H11: =+H10/G10-1 -> 0.40786774
B12: Total GLA | C12: 209822 | D12: 225228 | E12: 224479 | F12: 227138 | G12: 240674 | H12: 265268 | J12: =+H12+H20*B35 -> 313282.25 | K12: =+J12+J20*$B$35 -> 355667.09 | L12: =+K12+K20*$B$35 -> 393082.53 | M12: =+L12+L20*$B$35 -> 426111.22
B13: GLA Owned | C13: 138511 | D13: 147176 | E13: 148983 | F13: 152367 | G13: 161435 | H13: 176620
B14: % Total GLA | C14: 0.61 | D14: 0.66 | E14: 0.67 | F14: 0.66 | G14: 0.67 | H14: 0.68 | I14: =+AVERAGE(C14:H14) -> 0.65833333
B15: growth % | D15: =+D12/C12-1 -> 0.07342414 | E15: =+E12/D12-1 -> -0.003325519 | F15: =+F12/E12-1 -> 0.011845206 | G15: =+G12/F12-1 -> 0.059593727 | H15: =+H12/G12-1 -> 0.10218802
B17: Revenue Lease | C17: =+C14*C10 -> 47173.13 | D17: =+D14*D10 -> 69733.62 | E17: =+E14*E10 -> 94380.22 | F17: =+F14*F10 -> 101232.12 | G17: =+G14*G10 -> 118539.75 | H17: =+H14*H10 -> 169379.16
B18: Revenue Sale | C18: =+C10-C17 -> 30159.87 | D18: =+D10-D17 -> 35923.38 | E18: =+E10-E17 -> 46485.78 | F18: =+F10-F17 -> 52149.88 | G18: =+G10-G17 -> 58385.25 | H18: =+H10-H17 -> 79707.84
B20: Asset under Development | C20: 274376 | D20: 295187 | E20: 223124 | F20: 198440 | G20: 172116 | H20: 142054 | J20: =+H20*(1+I21) -> 125398.93 | K20: =+J20*(1+$I$21) -> 110696.58 | L20: =+K20*(1+$I$21) -> 97717.998 | M20: =+L20*(1+$I$21) -> 86261.087
D21: =+D20/C20-1 -> 0.075848471 | E21: =+E20/D20-1 -> -0.2441266 | F21: =+F20/E20-1 -> -0.11062907 | G21: =+G20/F20-1 -> -0.13265471 | H21: =+H20/G20-1 -> -0.17466127 | I21: =+AVERAGE(C21:H21) -> -0.11724464
B22: Revenue Per Square Meter (RSM) | C22: =+C10*1000/C12 -> 368.56478 | D22: =+D10*1000/D12 -> 469.1113 | E22: =+E10*1000/E12 -> 627.52418 | F22: =+F10*1000/F12 -> 675.28111 | G22: =+G10*1000/G12 -> 735.12303 | H22: =+H10*1000/H12 -> 939.00131 | I22: =+AVERAGE(G22:H22) -> 837.06217
B23: growth % | D23: =+D22/C22-1 -> 0.27280555 | E23: =+E22/D22-1 -> 0.33768719 | F23: =+F22/E22-1 -> 0.076103727 | G23: =+G22/F22-1 -> 0.088617795 | H23: =+H22/G22-1 -> 0.277339 | I23: =+_xlfn.RRI(COUNT(C22:H22), C22,H22) -> 0.16867044
B26: R*2 Between Revenue & GLA | C26: =+CORREL(C10:H10,C12:H12) -> 0.96834789
B27: Year 1 | C27: Projected GLA * RSM
B28: Year 2 | C28: (Projected GLA + Development) * RSM*(1+RSM Growth Rate)
B29: Year n | C29: Etc
B33: On Average HBR finished 5.5% of Under Development Assets
B34: =6.5%*4 -> 0.26 | C34: multiply by 4 quarters
B35: =+B34*(1+30%) -> 0.338 | C35: Apply 30% expected growth construction sector
B36: 34% Expected Under Development Assets Build Rate
C39: 2026 | D39: =+C39+1 -> 2027 | E39: =+D39+1 -> 2028 | F39: =+E39+1 -> 2029
B40: Revenue | C40: =+J10 -> 306468.31 | D40: =+K10 -> 347931.27 | E40: =+L10 -> 384532.92 | F40: =+M10 -> 416843.22
B41: Revenue Applied | C41: =+C40*0.99 -> 303403.62 | D41: =+FCFF!AH31 -> 349576.11 | E41: =+E40*0.96 -> 369151.6 | F41: =+F40*0.96 -> 400169.49
B43: Revenue will decrease x%, by the sensitivity analysis with a selic rate y% and -4% spread
B44: First graphshown, others arent relevant
B46: Other Calculations
B48: Debt
C50: 2022 | D50: =+C50+1 -> 2023 | E50: =+D50+1 -> 2024 | F50: 2025 | G50: =+F50+1 -> 2026 | H50: =+G50+1 -> 2027 | I50: =+H50+1 -> 2028 | J50: =+I50+1 -> 2029
B51: EBIT | C51: 84728 | D51: 19586 | E51: 93922 | F51: =+FCFF!Z61 -> 106547.59 | G51: =+FCFF!AF61 -> 113196 | H51: =+FCFF!AH61 -> 147035.96 | I51: =+FCFF!AJ61 -> 155870.63 | J51: =+FCFF!AL122 -> 169854.3
B52: DA | C52: 915 | D52: 1977 | E52: 1119 | F52: =+FCFF!Z49 -> 6918.4059 | G52: =+FCFF!AF49 -> 8165.4487 | H52: =+FCFF!AH49 -> 10273.293 | I52: 9495 | J52: 10231
B53: EBITDA | D53: =+D52+D51 -> 21563 | E53: =+E52+E51 -> 95041 | F53: =+F52+F51 -> 113466 | G53: =+G52+G51 -> 121361.45 | H53: =+H52+H51 -> 157309.25 | I53: =+I52+I51 -> 165365.63 | J53: =+J52+J51 -> 180085.3
B54: DEBT | C54: =+BS!T38+BS!V44 -> 1269184 | D54: =+BS!Z38+BS!Z44 -> 1339215 | E54: =+BS!AF38+BS!AF44 -> 1568184 | F54: =+BS!AI38+BS!AI44 -> 1709387 | G54: =+$F$55*G53 -> 1828333.5 | H54: =+$F$55*H53 -> 2369894 | I54: =+$F$55*I53 -> 2491264.8 | J54: =+$F$55*J53 -> 2713019.5
B55: ratio | C55: =+C54/C53 -> #DIV/0! | D55: =+D54/D53 -> 62.107082 | E55: =+E54/E53 -> 16.500079 | F55: =+F54/F53 -> 15.065191
B56: Predicted Debt | G56: =+G54/1000 -> 1828.3335 | H56: =+H54/1000 -> 2369.894 | I56: =+I54/1000 -> 2491.2648 | J56: =+J54/1000 -> 2713.0195
B59: ESG
B62: Job Category | C62: Male | D62: Female
B63: Board | C63: 3 | D63: 0
B64: Management | C64: 7 | D64: 5
B65: Coordination | C65: 7 | D65: 7
B66: Non-leadership | C66: 14 | D66: 44
B81: Job Category | C81: Under 30 | D81: 30-50 | E81: Over 50 | F81: Total
B82: Board | C82: 0 | D82: 1 | E82: 2 | F82: 3
B83: Management | C83: 0 | D83: 11 | E83: 1 | F83: 12
B84: Coordination | C84: 1 | D84: 12 | E84: 1 | F84: 14
B85: Non-leadership | C85: 32 | D85: 26 | E85: 0 | F85: 58

Sheet WACC
A7: x | B7: Rolling WACC | K7: Equity Risk Premium
P8: Weights
D9: 2025 | E9: =+D9+1 -> 2026 | F9: =+E9+1 -> 2027 | G9: =+F9+1 -> 2028 | H9: =+G9+1 -> 2029 | M9: ERP | N9: 2025 | O9: =+N9+1 -> 2026 | P9: =+O9+1 -> 2027 | Q9: =+P9+1 -> 2028 | R9: =+Q9+1 -> 2029
B12: Equity: | K12: Brazil | M12: 0.0767 | N12: 1 | O12: 1 | P12: 1 | Q12: 1 | R12: 1
B13: Market Cap (in billions) | D13: =+Inputs!J13/1000 -> 444.7445 | E13: =+FCFF!AF99*FCFF!AF31/1000 -> 358.01628 | F13: =+FCFF!AH99*FCFF!AH31/1000 -> 454.44894 | G13: =+FCFF!AJ99*FCFF!AJ31/1000 -> 516.81224 | H13: =+FCFF!AL99*FCFF!AL31/1000 -> 600.25424
B14: % of Equity | D14: =IFERROR(D13/D35,"") -> 0.20646117 | E14: =IFERROR(E13/E35,"") -> 0.16375069 | F14: =IFERROR(E13/F35,"") -> 0.12676091 | G14: =IFERROR(F13/G35,"") -> 0.15107623 | H14: =IFERROR(G13/H35,"") -> 0.15598236
B15: Risk-Free Rate | D15: 0.0425 | E15: 0.0425 | F15: 0.0425 | G15: 0.0425 | H15: 0.0425
B16: Beta | D16: =+Inputs!M18 -> 1.535918 | E16: 1.535918 | F16: 1.535918 | G16: 1.535918 | H16: 1.535918
B17: Unlevered Beta | D17: =+D16/(1+(D28/D13)*(1-D32)) -> 0.31710742 | E17: =+E16/(1+(E28/E13)*(1-E32)) -> 0.25150763 | F17: =+F16/(1+(F28/F13)*(1-F32)) -> 0.24713583 | G17: =+G16/(1+(G28/G13)*(1-G32)) -> 0.26388328 | H17: =+H16/(1+(H28/H13)*(1-H32)) -> 0.2782569
B18: Equity Risk Premium | D18: =+N18 -> 0.0767 | E18: =+D18*0.98 -> 0.075166 | F18: =+E18*0.98 -> 0.07366268 | G18: =+F18*0.98 -> 0.072189426 | H18: =+G18*0.98 -> 0.070745638 | K18: ERP | N18: 0.0767 | O18: 0.075166 | P18: 0.07366268 | Q18: 0.072189426 | R18: 0.070745638
B19: Ke (Cost of Equity) | D19: =IFERROR(+D15+D16*D18,"") -> 0.16030491 | E19: =IFERROR(+E15+E16*E18,"") -> 0.15794881 | F19: =IFERROR(+F15+F16*F18,"") -> 0.15563984 | G19: =IFERROR(+G15+G16*G18,"") -> 0.15337704 | H19: =IFERROR(+H15+H16*H18,"") -> 0.1511595
B21: Preferred Equity: | K21: ROIC vs WACC
B22: Market Capitalization | D22: =IFERROR(Inputs!J14,0) -> 0 | E22: 0 | F22: 0 | G22: 0 | H22: 0
B23: % of Preferred Equity | D23: =+D22/D35 -> 0 | E23: 0 | F23: 0 | G23: 0 | H23: 0
B24: Preferred Dividends | D24: =+IS!AF50 -> 0 | E24: =D24 -> 0 | F24: =E24 -> 0 | G24: =F24 -> 0 | H24: =G24 -> 0
B25: Kp (Cost of Preferred Equity) | D25: =IFERROR(D24/D22,0) -> 0 | E25: =IFERROR(E24/E22,0) -> 0 | F25: =IFERROR(F24/F22,0) -> 0 | G25: =IFERROR(G24/G22,0) -> 0 | H25: =IFERROR(H24/H22,0) -> 0
B27: Debt:
B28: Debt (in millions) | C28: =+BS!AF38+BS!AF39+BS!AF44+BS!AF45 -> 1568184 | D28: =(+BS!AI38+BS!AI39+BS!AI44+BS!AI45)/1000 -> 1709.387 | E28: =+Assumptions!G56 -> 1828.3335 | F28: =+Assumptions!H56 -> 2369.894 | G28: =+Assumptions!I56 -> 2491.2648 | H28: =+Assumptions!J56 -> 2713.0195
B29: % of Debt | D29: =IFERROR(D28/D35,"") -> 0.79353883 | E29: =IFERROR(E28/E35,"") -> 0.83624931 | F29: =IFERROR(F28/F35,"") -> 0.83909569 | G29: =IFERROR(G28/G35,"") -> 0.82819182 | H29: =IFERROR(H28/H35,"") -> 0.81883349
B30: Debt Spread | D30: =+D31-D15 -> 0.056477002 | E30: =+D30 -> 0.056477002 | F30: =+E30 -> 0.056477002 | G30: =+F30 -> 0.056477002 | H30: =+G30 -> 0.056477002
B31: Cost of Debt | D31: =+(IS!AI36+IS!AH36+IS!AE36+IS!AD36)/(WACC!D28*1000) -> 0.098977002 | E31: =+E15+E30 -> 0.098977002 | F31: =+F15+F30 -> 0.098977002 | G31: =+G15+G30 -> 0.098977002 | H31: =+H15+H30 -> 0.098977002
B32: Tax Rate | D32: 0 | E32: 0 | F32: 0 | G32: 0 | H32: 0
B33: Kd (After-Tax Cost of Debt) | D33: =+D31*(1-D32) -> 0.098977002 | E33: =+E31*(1-E32) -> 0.098977002 | F33: =+F31*(1-F32) -> 0.098977002 | G33: =+G31*(1-G32) -> 0.098977002 | H33: =+H31*(1-H32) -> 0.098977002
B35: Total | D35: =+D13+D24+D28 -> 2154.1315 | E35: =+E13+E24+E28 -> 2186.3497 | F35: =+F13+F24+F28 -> 2824.3429 | G35: =+G13+G24+G28 -> 3008.077 | H35: =+H13+H24+H28 -> 3313.2737
B37: Country/Conglomerate/... Risk Premium
A39: x | B39: WACC | D39: =+D19*D14+D25*D23+D33*D29+D37 -> 0.11163883 | E39: =+D39*0.9 -> 0.10047495 | F39: =+F19*F14+F25*F23+F33*F29+F37 -> 0.10278022 | G39: =+G19*G14+G25*G23+G33*G29+G37 -> 0.10514357 | H39: =+H19*H14+H25*H23+H33*H29+H37 -> 0.1046239
D40: =+AVERAGE(D39:H39) -> 0.10493229
B41: NOPAT | D41: =+FCFF!Z126 -> 115418.67 | E41: =+FCFF!AF126 -> 121119.72 | F41: =+FCFF!AH126 -> 154387.76 | G41: =+FCFF!AJ126 -> 162105.45 | H41: =+FCFF!AL126 -> 174949.93
B42: Total Payout | C42: 0 | D42: =+FCFF!Z112+FCFF!Z115 -> 0 | E42: =+FCFF!AF112+FCFF!AF115 -> 0 | F42: =+FCFF!AH112+FCFF!AH115 -> 0 | G42: =+FCFF!AJ112+FCFF!AJ115 -> 0 | H42: =+FCFF!AL112+FCFF!AL115 -> 0
B43: Book Value of Equity | C43: =+BS!AF54 -> 2949583 | D43: =+C43+D41+D42 -> 3065001.7 | E43: =+D43+E41+E42 -> 3186121.4 | F43: =+E43+F41+F42 -> 3340509.1 | G43: =+F43+G41+G42 -> 3502614.6 | H43: =+G43+H41+H42 -> 3677564.5
B44: Invested Capital | C44: =+C43+C28 -> 4517767 | D44: =+D43+D28 -> 3066711.1 | E44: =+E43+E28 -> 3187949.7 | F44: =+F43+F28 -> 3342879 | G44: =+G43+G28 -> 3505105.9 | H44: =+H43+H28 -> 3680277.5
A45: x | B45: ROIC | D45: =+D41/((D44+C44)/2) -> 0.030435494 | E45: =+E41/((E44+D44)/2) -> 0.038729429 | F45: =+F41/((F44+E44)/2) -> 0.047279683 | G45: =+G41/((G44+F44)/2) -> 0.047343986 | H45: =+H41/((H44+G44)/2) -> 0.048696059
B48: Bloomberg Metrics>
B49: WACC 17% | W49: ,
B50: ROIC 2.04%

Sheet FCFF
A7: x | B7: Market Assumptions
D8: 2022 | J8: =D8+1 -> 2023 | P8: =J8+1 -> 2024 | V8: =P8+1 -> 2025 | AB8: =V8+1 -> 2026 | AH8: =AB8+1 -> 2027 | AJ8: =+AH8+1 -> 2028 | AL8: =+AJ8+1 -> 2029
D9: Q1 | E9: Q2 | F9: Q3 | G9: Q4 | H9: FY | J9: Q1 | K9: Q2 | L9: Q3 | M9: Q4 | N9: FY | P9: Q1 | Q9: Q2 | R9: Q3 | S9: Q4 | T9: FY | V9: Q1 | W9: Q2 | X9: Q3 | Y9: Q4 | Z9: FY | AB9: Q1 | AC9: Q2 | AD9: Q3 | AE9: Q4 | AF9: FY | AH9: FY | AJ9: FY | AL9: FY
B21: Revenue
A23: x | B23: Operating Assumptions
D24: =D$8 -> 2022 | E24: =F24 -> 0 | F24: =F$8 -> 0 | G24: =F24 -> 0 | H24: =F24 -> 0 | J24: =J$8 -> 2023 | K24: =L24 -> 0 | L24: =L$8 -> 0 | M24: =L24 -> 0 | N24: =L24 -> 0 | P24: =P$8 -> 2024 | Q24: =R24 -> 0 | R24: =R$8 -> 0 | S24: =R24 -> 0 | T24: =R24 -> 0 | V24: =V$8 -> 2025 | W24: =X24 -> 0 | X24: =X$8 -> 0 | Y24: =X24 -> 0 | Z24: =X24 -> 0 | AB24: =AB$8 -> 2026 | AC24: =AD24 -> 0 | AD24: =AD$8 -> 0 | AE24: =AD24 -> 0 | AF24: =AD24 -> 0 | AH24: =AH$8 -> 2027 | AJ24: =AJ$8 -> 2028 | AL24: =AL$8 -> 2029
D25: Q1 | E25: Q2 | F25: Q3 | G25: Q4 | H25: FY | J25: Q1 | K25: Q2 | L25: Q3 | M25: Q4 | N25: FY | P25: Q1 | Q25: Q2 | R25: Q3 | S25: Q4 | T25: FY | V25: Q1 | W25: Q2 | X25: Q3 | Y25: Q4 | Z25: FY | AB25: Q1 | AC25: Q2 | AD25: Q3 | AE25: Q4 | AF25: FY | AH25: FY | AJ25: FY | AL25: FY
B28: Income Statement
B31: Revenue | D31: =IS!P18 -> 34134 | E31: =IS!Q18 -> 34302 | F31: =IS!R18 -> 34378 | G31: =IS!S18 -> 38052 | H31: =IS!T18 -> 140866 | J31: 52729 | K31: 39112 | L31: 38430 | M31: 23111 | N31: =+SUM(J31:M31) -> 153382 | P31: 37950 | Q31: 39774 | R31: 41539 | S31: 57921 | T31: =+SUM(P31:S31) -> 177184 | V31: =IS!AH18 -> 45846 | W31: =IS!AI18 -> 63997 | X31: =+R31*1.4 -> 58154.6 | Y31: =+S31*1.4 -> 81089.4 | Z31: 249087 | AB31: =+$AF$31/4 -> 75850.906 | AC31: =+$AF$31/4 -> 75850.906 | AD31: =+$AF$31/4 -> 75850.906 | AE31: =+$AF$31/4 -> 75850.906 | AF31: =+Assumptions!C41 -> 303403.62 | AH31: 349576.11 | AJ31: =+Assumptions!E41 -> 369151.6 | AL31: =+Assumptions!F41 -> 400169.49
B32: % of growth | D32: =D31/IS!J18-1 -> 0.78459769 | E32: =E31/IS!K18-1 -> 0.96033832 | F32: =F31/IS!L18-1 -> 0.55521375 | G32: =G31/IS!M18-1 -> -0.20189605 | H32: =H31/IS!N18-1 -> 0.60253464 | J32: =J31/IS!P18-1 -> 0.54476475 | K32: =K31/IS!Q18-1 -> 0.14022506 | L32: =L31/IS!R18-1 -> 0.11786608 | M32: =M31/IS!S18-1 -> -0.3926469 | N32: =N31/H31-1 -> 0.088850397 | P32: =P31/IS!V18-1 -> -0.2802822 | Q32: =Q31/IS!W18-1 -> 0.016925752 | R32: =R31/IS!X18-1 -> 0.080900338 | S32: =S31/IS!Y18-1 -> 1.5062092 | T32: =T31/N31-1 -> 0.15518118 | V32: =V31/IS!AB18-1 -> 0.21636465 | W32: =W31/IS!AC18-1 -> 0.60901594 | X32: =X31/IS!AD18-1 -> 0.4 | Y32: 0.4 | Z32: =Z31/T31-1 -> 0.40580978 | AB32: =AB31/IS!AH18-1 -> 0.65447162 | AC32: =AC31/IS!AI18-1 -> 0.18522596 | AD32: =AD31/IS!AJ18-1 -> 0.30429761 | AE32: =AE31/IS!AK18-1 -> -0.064601468 | AF32: =AF31/Z31-1 -> 0.21806286 | AH32: =AH31/AF31-1 -> 0.15218173 | AJ32: =AJ31/AH31-1 -> 0.055997789 | AL32: =AL31/AJ31-1 -> 0.084024805 | AR32: 2022 | AS32: =+AR32+1 -> 2023 | AT32: =+AS32+1 -> 2024 | AU32: =+AT32+1 -> 2025 | AV32: =+AU32+1 -> 2026 | AW32: =+AV32+1 -> 2027 | AX32: =+AW32+1 -> 2028 | AY32: =+AX32+1 -> 2029
AQ33: EBITDA | AR33: =H61+H128 -> 85643 | AS33: =N61+N128 -> 65966 | AT33: =T61+T128 -> 97957 | AU33: =Z61+Z128 -> 113466 | AV33: =AF61+AF128 -> 121361.45 | AW33: =AH61+AH128 -> 157309.25 | AX33: =AJ61+AJ128 -> 166118.22 | AY33: =AL61+AL128 -> 180076.27
B34: Cost of Goods & Services | D34: =IS!P21 -> 7004 | E34: =IS!Q21 -> 4944 | F34: =IS!R21 -> 4459 | G34: =IS!S21 -> 5892 | H34: =IS!T21 -> 22299 | J34: =IS!V21 -> 5907 | K34: =IS!W21 -> 6864 | L34: =IS!X21 -> 8319 | M34: =IS!Y21 -> 8013 | N34: =IS!Z21 -> 29103 | P34: =IS!AB21 -> 7197 | Q34: =IS!AC21 -> 8176 | R34: =IS!AD21 -> 8130 | S34: =IS!AE21 -> 9500 | T34: =IS!AF21 -> 33003 | V34: =IS!AH21 -> 15902 | W34: =IS!AI21 -> 27846 | X34: =(X35+Sensitivity!$U$39)*X$31 -> 5815.46 | Y34: =(Y35+Sensitivity!$U$39)*Y$31 -> 8108.94 | Z34: =SUM(V34:Y34) -> 57672.4 | AB34: =(AB35+Sensitivity!$U$39)*AB$31 -> 15170.181 | AC34: =(AC35+Sensitivity!$U$39)*AC$31 -> 15170.181 | AD34: =(AD35+Sensitivity!$U$39)*AD$31 -> 15170.181 | AE34: =(AE35+Sensitivity!$U$39)*AE$31 -> 15170.181 | AF34: =SUM(AB34:AE34) -> 60680.725 | AH34: =(AH35+Sensitivity!$U$39)*AH$31 -> 52436.417 | AJ34: =(AJ35+Sensitivity!$U$39)*AJ$31 -> 55372.74 | AL34: =(AL35+Sensitivity!$U$39)*AL$31 -> 60025.424 | AQ34: FCFF | AR34: =H136 -> 340577.16 | AS34: =N136 -> -61634.368 | AT34: =T136 -> 175059.24 | AU34: =Z136 -> 47148.377 | AV34: =AF136 -> 161535.98 | AW34: =AH136 -> 111726.85 | AX34: =AJ136 -> 186503.01 | AY34: =AL136 -> 172823.37
B35: % of sales | D35: =D34/D31 -> 0.2051913 | E35: =E34/E31 -> 0.14413154 | F35: =F34/F31 -> 0.12970504 | G35: =G34/G31 -> 0.15484074 | H35: =H34/H31 -> 0.15829938 | J35: =J34/J31 -> 0.11202564 | K35: =K34/K31 -> 0.17549601 | L35: =L34/L31 -> 0.21647151 | M35: =M34/M31 -> 0.34671801 | N35: =N34/N31 -> 0.18974195 | P35: =P34/P31 -> 0.18964427 | Q35: =Q34/Q31 -> 0.20556142 | R35: =R34/R31 -> 0.19571969 | S35: =S34/S31 -> 0.16401651 | T35: =T34/T31 -> 0.186264 | V35: =V34/V31 -> 0.34685687 | W35: =W34/W31 -> 0.43511415 | X35: 0.1 | Y35: 0.1 | Z35: =Z34/Z31 -> 0.23153517 | AB35: 0.2 | AC35: 0.2 | AD35: 0.2 | AE35: 0.2 | AF35: =AF34/AF31 -> 0.2 | AH35: 0.15 | AJ35: 0.15 | AL35: 0.15 | AQ35: Revenue Growth | AR35: =H32 -> 0.60253464 | AS35: =N32 -> 0.088850397 | AT35: =T32 -> 0.15518118 | AU35: =Z32 -> 0.40580978 | AV35: =AF32 -> 0.21806286 | AW35: =AH32 -> 0.15218173 | AX35: =+AJ32 -> 0.055997789 | AY35: =+AL32 -> 0.084024805
V36: =+AVERAGE(V35:W35,P35:S35, J35:M35) -> 0.23876241
B37: COGS Depreciation & Amortization | D37: =IS!P22 -> 0 | E37: =IS!Q22 -> 0 | F37: =IS!R22 -> 0 | G37: =IS!S22 -> 0 | H37: 0 | J37: =IS!V22 -> 0 | K37: =IS!W22 -> 0 | L37: =IS!X22 -> 0 | M37: =IS!Y22 -> 0 | N37: 0 | P37: =IS!AB22 -> 0 | Q37: =IS!AC22 -> 0 | R37: =IS!AD22 -> 0 | S37: =IS!AE22 -> 0 | T37: 0 | V37: 0 | W37: 0 | X37: 0 | Y37: 0 | Z37: =SUM(V37:Y37) -> 0 | AB37: 0 | AC37: 0 | AD37: 0 | AE37: 0 | AF37: =SUM(AB37:AE37) -> 0 | AH37: 0 | AJ37: 0 | AL37: 0
B38: % of cost of goods & services | D38: =+D37/D34 -> 0 | E38: =+E37/E34 -> 0 | F38: =+F37/F34 -> 0 | G38: =+G37/G34 -> 0 | H38: =+H37/H34 -> 0 | J38: =+J37/J34 -> 0 | K38: =+K37/K34 -> 0 | L38: =+L37/L34 -> 0 | M38: =+M37/M34 -> 0 | N38: =+N37/N34 -> 0 | P38: =+P37/P34 -> 0 | Q38: =+Q37/Q34 -> 0 | R38: =+R37/R34 -> 0 | S38: =+S37/S34 -> 0 | T38: =+T37/T34 -> 0 | V38: =+V37/V34 -> 0 | W38: =+W37/W34 -> 0 | X38: =+X37/X34 -> 0 | Y38: =+Y37/Y34 -> 0 | AB38: =+AB37/AB34 -> 0 | AC38: =+AC37/AC34 -> 0 | AD38: =+AD37/AD34 -> 0 | AE38: =+AE37/AE34 -> 0 | AH38: =+AH37/AH34 -> 0 | AJ38: =+AJ37/AJ34 -> 0 | AL38: =+AL37/AL34 -> 0
B40: Gross Profit | D40: =D31-D34-D37 -> 27130 | E40: =E31-E34-E37 -> 29358 | F40: =F31-F34-F37 -> 29919 | G40: =G31-G34-G37 -> 32160 | H40: =H31-H34-H37 -> 118567 | J40: =J31-J34-J37 -> 46822 | K40: =K31-K34-K37 -> 32248 | L40: =L31-L34-L37 -> 30111 | M40: =M31-M34-M37 -> 15098 | N40: =N31-N34-N37 -> 124279 | P40: =P31-P34-P37 -> 30753 | Q40: =Q31-Q34-Q37 -> 31598 | R40: =R31-R34-R37 -> 33409 | S40: =S31-S34-S37 -> 48421 | T40: =T31-T34-T37 -> 144181 | V40: =V31-V34-V37 -> 29944 | W40: =W31-W34-W37 -> 36151 | X40: =X31-X34-X37 -> 52339.14 | Y40: =Y31-Y34-Y37 -> 72980.46 | Z40: =SUM(V40:Y40) -> 191414.6 | AB40: =AB31-AB34-AB37 -> 60680.725 | AC40: =AC31-AC34-AC37 -> 60680.725 | AD40: =AD31-AD34-AD37 -> 60680.725 | AE40: =AE31-AE34-AE37 -> 60680.725 | AF40: =SUM(AB40:AE40) -> 242722.9 | AH40: =AH31-AH34-AH37 -> 297139.69 | AJ40: =AJ31-AJ34-AJ37 -> 313778.86 | AL40: =AL31-AL34-AL37 -> 340144.07
B41: % of sales | D41: =D40/D31 -> 0.7948087 | E41: =E40/E31 -> 0.85586846 | F41: =F40/F31 -> 0.87029496 | G41: =G40/G31 -> 0.84515926 | H41: =H40/H31 -> 0.84170062 | J41: =J40/J31 -> 0.88797436 | K41: =K40/K31 -> 0.82450399 | L41: =L40/L31 -> 0.78352849 | M41: =M40/M31 -> 0.65328199 | N41: =N40/N31 -> 0.81025805 | P41: =P40/P31 -> 0.81035573 | Q41: =Q40/Q31 -> 0.79443858 | R41: =R40/R31 -> 0.80428031 | S41: =S40/S31 -> 0.83598349 | T41: =T40/T31 -> 0.813736 | V41: =V40/V31 -> 0.65314313 | W41: =W40/W31 -> 0.56488585 | X41: =X40/X31 -> 0.9 | Y41: =Y40/Y31 -> 0.9 | Z41: =Z40/Z$31 -> 0.76846483 | AB41: =AB40/AB31 -> 0.8 | AC41: =AC40/AC31 -> 0.8 | AD41: =AD40/AD31 -> 0.8 | AE41: =AE40/AE31 -> 0.8 | AF41: =AF40/AF$31 -> 0.8 | AH41: =AH40/AH31 -> 0.85 | AJ41: =AJ40/AJ31 -> 0.85 | AL41: =AL40/AL31 -> 0.85
B43: SG&A (Selling, General & Administrative) | D43: =IS!P27 -> 9379 | E43: =IS!Q27 -> 8273 | F43: =IS!R27 -> 8676 | G43: =IS!S27 -> 7663 | H43: =IS!T27 -> 33991 | J43: =IS!V27 -> 10277 | K43: =IS!W27 -> 11727 | L43: =IS!X27 -> 10777 | M43: =IS!Y27 -> 12577 | N43: =IS!Z27 -> 45358 | P43: =IS!AB27 -> 12424 | Q43: =IS!AC27 -> 10799 | R43: =IS!AD27 -> 11389 | S43: =IS!AE27 -> 12763 | T43: =IS!AF27 -> 47375 | V43: =IS!AH27 -> 6958 | W43: =IS!AI27 -> 12627 | X43: =(X44+Sensitivity!$U$40)*X$31 -> 11630.92 | Y43: =(Y44+Sensitivity!$U$40)*Y$31 -> 16217.88 | Z43: =SUM(V43:Y43) -> 47433.8 | AB43: =(AB44+Sensitivity!$U$40)*AB$31 -> 15170.181 | AC43: =(AC44+Sensitivity!$U$40)*AC$31 -> 15170.181 | AD43: =(AD44+Sensitivity!$U$40)*AD$31 -> 15170.181 | AE43: =(AE44+Sensitivity!$U$40)*AE$31 -> 15170.181 | AF43: =SUM(AB43:AE43) -> 60680.725 | AH43: =(AH44+Sensitivity!$U$40)*AH$31 -> 69915.222 | AJ43: =(AJ44+Sensitivity!$U$40)*AJ$31 -> 73830.32 | AL43: =(AL44+Sensitivity!$U$40)*AL$31 -> 80033.898
B44: % of sales | D44: =D43/D31 -> 0.27477002 | E44: =E43/E31 -> 0.24118127 | F44: =F43/F31 -> 0.2523707 | G44: =G43/G31 -> 0.20138232 | H44: =H43/H31 -> 0.24130024 | J44: =J43/J31 -> 0.19490224 | K44: =K43/K31 -> 0.29983125 | L44: =L43/L31 -> 0.28043195 | M44: =M43/M31 -> 0.54419973 | N44: =N43/N31 -> 0.29571918 | P44: =P43/P31 -> 0.32737813 | Q44: =Q43/Q31 -> 0.27150903 | R44: =R43/R31 -> 0.27417608 | S44: =S43/S31 -> 0.22035186 | T44: =T43/T31 -> 0.26737742 | V44: =V43/V31 -> 0.15176897 | W44: =W43/W31 -> 0.19730612 | X44: 0.2 | Y44: 0.2 | Z44: =Z43/Z31 -> 0.19043065 | AB44: 0.2 | AC44: 0.2 | AD44: 0.2 | AE44: 0.2 | AF44: =AF43/AF31 -> 0.2 | AH44: 0.2 | AJ44: 0.2 | AL44: 0.2
W45: =+AVERAGE(V44:W44) -> 0.17453754
B46: R&D (Research & Development) | D46: =IS!P29 -> 0 | E46: =IS!Q29 -> 0 | F46: =IS!R29 -> 0 | G46: =IS!S29 -> 0 | H46: =IS!T29 -> 0 | J46: =IS!V29 -> 0 | K46: =IS!W29 -> 0 | L46: =IS!X29 -> 0 | M46: =IS!Y29 -> 0 | N46: =IS!Z29 -> 0 | P46: =IS!AB29 -> 0 | Q46: =IS!AC29 -> 0 | R46: =IS!AD29 -> 0 | S46: =IS!AE29 -> 0 | T46: =IS!AF29 -> 0 | V46: =IS!AH29 -> 0 | W46: =IS!AI29 -> 0 | X46: =X47*X40 -> 0 | Y46: =Y47*Y40 -> 0 | Z46: =SUM(V46:Y46) -> 0 | AB46: =AB47*AB40 -> 0 | AC46: =AC47*AC40 -> 0 | AD46: =AD47*AD40 -> 0 | AE46: =AE47*AE40 -> 0 | AF46: =SUM(AB46:AE46) -> 0 | AH46: =AH47*AH40 -> 0 | AJ46: =AJ47*AJ40 -> 0 | AL46: =AL47*AL40 -> 0
B47: % of gross profit | D47: =D46/D40 -> 0 | E47: =E46/E40 -> 0 | F47: =F46/F40 -> 0 | G47: =G46/G40 -> 0 | H47: =H46/H40 -> 0 | J47: =J46/J40 -> 0 | K47: =K46/K40 -> 0 | L47: =L46/L40 -> 0 | M47: =M46/M40 -> 0 | N47: =N46/N40 -> 0 | P47: =P46/P40 -> 0 | Q47: =Q46/Q40 -> 0 | R47: =R46/R40 -> 0 | S47: =S46/S40 -> 0 | T47: =T46/T40 -> 0 | V47: =V46/V40 -> 0 | W47: =W46/W40 -> 0 | X47: 0 | Y47: 0 | Z47: =Z46/Z$40 -> 0 | AB47: 0 | AC47: 0 | AD47: 0 | AE47: 0 | AF47: =AF46/AF$40 -> 0 | AH47: 0 | AJ47: 0 | AL47: 0
AQ48: =+Z171 -> -0.36486967 | AR48: =+AF171 -> -0.30525663 | AS48: =+AL171 -> -4.4897992
B49: D&A (Depreciation & Amortization) | D49: =IS!P28 -> 173 | E49: =IS!Q28 -> 194 | F49: =IS!R28 -> 243 | G49: =IS!S28 -> 305 | H49: =IS!T28 -> 915 | J49: =IS!V28 -> 480 | K49: =IS!W28 -> 562 | L49: =IS!X28 -> 476 | M49: =IS!Y28 -> 459 | N49: =IS!Z28 -> 1977 | P49: =IS!AB28 -> 1055 | Q49: =IS!AC28 -> 1119 | R49: =IS!AD28 -> 0 | S49: =IS!AE28 -> 0 | T49: =+SUM(Q49:S49) -> 1119 | V49: =IS!AH28 -> 1621 | W49: =IS!AI28 -> 1818 | X49: =X52+X55 -> 1722.8441 | Y49: =Y52+Y55 -> 1756.5617 | Z49: =SUM(V49:Y49) -> 6918.4059 | AB49: =AB52+AB55 -> 2042.8899 | AC49: =AC52+AC55 -> 2041.8711 | AD49: =AD52+AD55 -> 2040.8528 | AE49: =AE52+AE55 -> 2039.835 | AF49: =SUM(AB49:AE49) -> 8165.4487 | AH49: =AH52+AH55 -> 10273.293 | AJ49: =AJ52+AJ55 -> 10247.595 | AL49: =AL52+AL55 -> 10221.972
B50: % of net pp&e and intangibles excl. Goodwill | D50: =D49/(D79+D82) -> 6.1748533e-05 | E50: =E49/(E79+E82) -> 6.7880301e-05 | F50: =F49/(F79+F82) -> 7.7591632e-05 | G50: =G49/(G79+G82) -> 8.8468263e-05 | H50: =H49/(H79+H82) -> 0.00026540479 | J50: =J49/(J79+J82) -> 0.00013855341 | K50: =K49/(K79+K82) -> 0.00016027958 | L50: =L49/(L79+L82) -> 0.00013334678 | M50: =M49/(M79+M82) -> 0.00012072387 | N50: =N49/(N79+N82) -> 0.00051998059 | P50: =P49/(P79+P82) -> 0.00027420909 | Q50: =Q49/(Q79+Q82) -> 0.00029080034 | R50: =R49/(R79+R82) -> 0 | S50: =S49/(S79+S82) -> 0 | T50: =T49/(T79+T82) -> 0.00027391533 | V50: =V49/(V79+V82) -> 0.0003940027 | W50: =W49/(W79+W82) -> 0.00043983811 | X50: =X49/( X79+X82) -> 0.00041698668 | Y50: =Y49/( Y79+Y82) -> 0.00042532307 | Z50: =Z49/( Z79+Z82) -> 0.0016751803 | AB50: =AB49/( AB79+AB82) -> 0.00049488851 | AC50: =AC49/( AC79+AC82) -> 0.00049487741 | AD50: =AD49/( AD79+AD82) -> 0.00049486629 | AE50: =AE49/( AE79+AE82) -> 0.00049485516 | AF50: =AF49/( AF79+AF82) -> 0.0019809026 | AH50: =AH49/( AH79+AH82) -> 0.0024978462 | AJ50: =AJ49/( AJ79+AJ82) -> 0.0024971475 | AL50: =AL49/( AL79+AL82) -> 0.0024963917
B52: Depreciation | D52: =+IS!P28 -> 173 | E52: =+IS!Q28 -> 194 | F52: =+IS!R28 -> 243 | G52: =+IS!S28 -> 305 | H52: =+IS!T28 -> 915 | J52: =+IS!V28 -> 480 | K52: =+IS!W28 -> 562 | L52: =+IS!X28 -> 476 | M52: =+IS!Y28 -> 459 | N52: =+IS!Z28 -> 1977 | P52: =+IS!AB28 -> 1055 | Q52: =+IS!AC28 -> 1119 | R52: =+IS!AD28 -> 0 | S52: =+IS!AE28 -> 0 | T52: =+IS!AF28 -> 2174 | V52: =+IS!AH28 -> 1621 | W52: =+IS!AI28 -> 1818 | X52: =+X53*W79 -> 1722.8441 | Y52: =+Y53*X79 -> 1756.5617 | Z52: =+SUM(V52:Y52) -> 6918.4059 | AB52: =+AB53*Y79 -> 2042.8899 | AC52: =+AC53*AB79 -> 2041.8711 | AD52: =+AD53*AC79 -> 2040.8528 | AE52: =+AE53*AD79 -> 2039.835 | AF52: =+SUM(AB52:AE52) -> 8165.4487 | AH52: =+AH53*AF79*4 -> 10273.293 | AJ52: =+AJ53*AH79*4 -> 10247.595 | AL52: =+AL53*AJ79*4 -> 10221.972
B53: % of net pp&e | D53: =D52/D79 -> 6.1870233e-05 | E53: =E52/E79 -> 6.8011852e-05 | F53: =F52/F79 -> 7.7805189e-05 | G53: =G52/G79 -> 8.8784456e-05 | H53: =H52/H79 -> 0.00026635337 | J53: =J52/J79 -> 0.00013897189 | K53: =K52/K79 -> 0.00016074692 | L53: =L52/L79 -> 0.0001337117 | M53: =M52/M79 -> 0.00012102027 | N53: =N52/N79 -> 0.00052125725 | P53: =P52/P79 -> 0.00027655143 | Q53: =Q52/Q79 -> 0.00029336469 | R53: =R52/R79 -> 0 | S53: =S52/S79 -> 0 | T53: =T52/T79 -> 0.00053759452 | V53: =V52/V79 -> 0.00039804049 | W53: =W52/W79 -> 0.00044457998 | X53: =+AVERAGE(V53:W53) -> 0.00042131023 | Y53: =+X53*1.02 -> 0.00042973644 | AB53: 0.0005 | AC53: 0.0005 | AD53: 0.0005 | AE53: 0.0005 | AH53: =0.05832%*1.08 -> 0.000629856 | AJ53: =0.05832%*1.08 -> 0.000629856 | AL53: =0.05832%*1.08 -> 0.000629856
B55: Amortization | D55: =IS!P65 -> 0 | E55: =IS!Q65 -> 0 | F55: =IS!R65 -> 0 | G55: =IS!S65 -> 0 | H55: =IS!T65 -> 0 | J55: =IS!V65 -> 0 | K55: =IS!W65 -> 0 | L55: =IS!X65 -> 0 | M55: =IS!Y65 -> 0 | N55: =IS!Z65 -> 0 | P55: =IS!AB65 -> 0 | Q55: =IS!AC65 -> 0 | R55: =IS!AD65 -> 0 | S55: =IS!AE65 -> 0 | T55: =IS!AF65 -> 0 | V55: =IS!AH65 -> 0 | W55: =IS!AI65 -> 0 | X55: =X56*W82 -> 0 | Y55: =Y56*X82 -> 0 | Z55: =SUM(V55:Y55) -> 0 | AB55: =AB56*Y82 -> 0 | AC55: =AC56*AB82 -> 0 | AD55: =AD56*AC82 -> 0 | AE55: =AE56*AD82 -> 0 | AF55: =SUM(AB55:AE55) -> 0 | AH55: =AH56*AF82 -> 0 | AJ55: =AJ56*AH82 -> 0 | AL55: =AL56*AJ82 -> 0
B56: % of intangibles excl. goodwill | D56: =D55/D82 -> 0 | E56: =E55/E82 -> 0 | F56: =F55/F82 -> 0 | G56: =G55/G82 -> 0 | H56: =H55/H82 -> 0 | J56: =J55/J82 -> 0 | K56: =K55/K82 -> 0 | L56: =L55/L82 -> 0 | M56: =M55/M82 -> 0 | N56: =N55/N82 -> 0 | P56: =P55/P82 -> 0 | Q56: =Q55/Q82 -> 0 | R56: =R55/R82 -> 0 | S56: =S55/S82 -> 0 | T56: =T55/T82 -> 0 | V56: =V55/V82 -> 0 | W56: =W55/W82 -> 0 | X56: 0 | Y56: 0 | Z56: =Z55/Z82 -> 0 | AB56: 0 | AC56: 0 | AD56: 0 | AE56: 0 | AF56: =AF55/AF82 -> 0 | AH56: 0 | AJ56: 0 | AL56: 0
B58: Other Operating (Income) Expenses | D58: =IS!P30+IS!P32 -> -400 | E58: =IS!Q30+IS!Q32 -> -636 | F58: =IS!R30+IS!R32 -> -2884 | G58: =IS!S30+IS!S32 -> 8244 | H58: =IS!T30+IS!T32 -> 4324 | J58: =IS!V30+IS!V32 -> 11382 | K58: =IS!W30+IS!W32 -> 1921 | L58: =IS!X30+IS!X32 -> -2216 | M58: =IS!Y30+IS!Y32 -> 18132 | N58: =IS!Z30+IS!Z32 -> 29219 | P58: =IS!AB30+IS!AB32 -> -4859 | Q58: =IS!AC30+IS!AC32 -> 9027 | R58: =IS!AD30+IS!AD32 -> 6229 | S58: =IS!AE30+IS!AE32 -> -4256 | T58: =IS!AF30+IS!AF32 -> 6141 | V58: =IS!AH30+IS!AH32 -> 11610 | W58: =IS!AI30+IS!AI32 -> 38306 | X58: =X59*X$31 -> 11630.92 | Y58: =Y59*Y$31 -> 16217.88 | Z58: =SUM(V58:Y58) -> 77764.8 | AB58: =AB59*AB$31 -> 15170.181 | AC58: =AC59*AC$31 -> 15170.181 | AD58: =AD59*AD$31 -> 15170.181 | AE58: =AE59*AE$31 -> 15170.181 | AF58: =SUM(AB58:AE58) -> 60680.725 | AH58: =AH59*AH$31 -> 69915.222 | AJ58: =AJ59*AJ$31 -> 73830.32 | AL58: =AL59*AL$31 -> 80033.898
B59: % of sales | D59: =D58/D31 -> -0.011718521 | E59: =E58/E31 -> -0.018541193 | F59: =F58/F31 -> -0.08389086 | G59: =G58/G31 -> 0.2166509 | H59: =H58/H31 -> 0.030695839 | J59: =J58/J31 -> 0.21585845 | K59: =K58/K31 -> 0.049115361 | L59: =L58/L31 -> -0.057663284 | M59: =M58/M31 -> 0.78456146 | N59: =N58/N31 -> 0.19049823 | P59: =P58/P31 -> -0.12803689 | Q59: =Q58/Q31 -> 0.22695731 | R59: =R58/R31 -> 0.14995546 | S59: =S58/S31 -> -0.073479394 | T59: =T58/T31 -> 0.034658886 | V59: =V58/V31 -> 0.2532391 | W59: =W58/W31 -> 0.59855931 | X59: 0.2 | Y59: 0.2 | Z59: =Z58/Z$31 -> 0.31219935 | AB59: 0.2 | AC59: 0.2 | AD59: 0.2 | AE59: 0.2 | AF59: =+AVERAGE(AB59:AE59) -> 0.2 | AH59: 0.2 | AJ59: 0.2 | AL59: 0.2
S60: =+AVERAGE(V59:W59,P59:R59,J59:L59,D59:F59) -> 0.10853039
B61: EBIT (Operating Income) | D61: =IS!P33 -> 17288 | E61: =IS!Q33 -> 21112 | F61: =IS!R33 -> 20961 | G61: =IS!S33 -> 25367 | H61: =IS!T33 -> 84728 | J61: =IS!V33 -> 36065 | K61: =IS!W33 -> 19959 | L61: =IS!X33 -> 18675 | M61: =IS!Y33 -> -10710 | N61: =IS!Z33 -> 63989 | P61: =IS!AB33 -> 16906 | Q61: =IS!AC33 -> 19586 | R61: =IS!AD33 -> 19162 | S61: =IS!AE33 -> 37759 | T61: =IS!AF33 -> 93413 | V61: =IS!AH33 -> 18699 | W61: =IS!AI33 -> 21706 | X61: =X40-X43-X46-X49-X58 -> 27354.456 | Y61: =Y40-Y43-Y46-Y49-Y58 -> 38788.138 | Z61: =SUM(V61:Y61) -> 106547.59 | AB61: =AB40-AB43-AB46-AB49-AB58 -> 28297.472 | AC61: =AC40-AC43-AC46-AC49-AC58 -> 28298.491 | AD61: =AD40-AD43-AD46-AD49-AD58 -> 28299.51 | AE61: =AE40-AE43-AE46-AE49-AE58 -> 28300.527 | AF61: =SUM(AB61:AE61) -> 113196 | AH61: =AH40-AH43-AH46-AH49-AH58 -> 147035.96 | AJ61: =AJ40-AJ43-AJ46-AJ49-AJ58 -> 155870.63 | AL61: =AL40-AL43-AL46-AL49-AL58 -> 169854.3
B62: % of sales | D62: =D61/D31 -> 0.50647448 | E62: =E61/E31 -> 0.61547432 | F62: =F61/F31 -> 0.60972133 | G62: =G61/G31 -> 0.66664039 | H62: =H61/H31 -> 0.60147942 | J62: =J61/J31 -> 0.68396897 | K62: =K61/K31 -> 0.51030374 | L62: =L61/L31 -> 0.48594848 | M62: =M61/M31 -> -0.46341569 | N62: =N61/N31 -> 0.41718715 | P62: =P61/P31 -> 0.4454809 | Q62: =Q61/Q31 -> 0.49243224 | R62: =R61/R31 -> 0.46130143 | S62: =S61/S31 -> 0.65190518 | T62: =T61/T31 -> 0.527209 | V62: =V61/V31 -> 0.40786546 | W62: =W61/W31 -> 0.33917215 | X62: =X61/X$31 -> 0.47037476 | Y62: =Y61/Y$31 -> 0.47833796 | Z62: =Z61/Z$31 -> 0.42775253 | AB62: =AB61/AB$31 -> 0.37306703 | AC62: =AC61/AC$31 -> 0.37308047 | AD62: =AD61/AD$31 -> 0.37309389 | AE62: =AE61/AE$31 -> 0.37310731 | AF62: =AF61/AF$31 -> 0.37308717 | AH62: =AH61/AH$31 -> 0.42061214 | AJ62: =AJ61/AJ$31 -> 0.42224014 | AL62: =AL61/AL$31 -> 0.42445589
B64: Basic Weighted Average Shares | D64: =IS!P59 -> 103188.98 | E64: =IS!Q59 -> 103188.98 | F64: =IS!R59 -> 103188.98 | G64: =IS!S59 -> 103188.98 | H64: =IS!T59 -> 103188.98 | J64: =IS!V59 -> 103188.98 | K64: =IS!W59 -> 103188.98 | L64: =IS!X59 -> 103188.98 | M64: =IS!Y59 -> 103188.98 | N64: =IS!Z59 -> 103188.98 | P64: =IS!AB59 -> 103188.98 | Q64: =IS!AC59 -> 103188.98 | R64: =IS!AD59 -> 103188.98 | S64: =IS!AE59 -> 103188.98 | T64: =IS!AF59 -> 103188.98 | V64: =IS!AH59 -> 103188.98 | W64: =IS!AI59 -> 103188.98 | X64: =W64+X101 -> 103270.71 | Y64: =X64+Y101 -> 103334.14 | Z64: =AVERAGE(V64:Y64) -> 103245.7 | AB64: =Y64+AB101 -> 103381.74 | AC64: =AB64+AC101 -> 103427.43 | AD64: =AC64+AD101 -> 103427.43 | AE64: =AD64+AE101 -> 103427.43 | AF64: =AVERAGE(AB64:AE64) -> 103416 | AH64: =AE64+AH101 -> 103586.54 | AJ64: =AF64+AJ101 -> 103563.99 | AL64: =AH64+AL101 -> 103724.63
B65: Diluted Weighted Average Shares | D65: =IS!P60 -> 103188.98 | E65: =IS!Q60 -> 103188.98 | F65: =IS!R60 -> 103188.98 | G65: =IS!S60 -> 103188.98 | H65: =IS!T60 -> 103188.98 | J65: =IS!V60 -> 103188.98 | K65: =IS!W60 -> 103188.98 | L65: =IS!X60 -> 103188.98 | M65: =IS!Y60 -> 103188.98 | N65: =IS!Z60 -> 103188.98 | P65: =IS!AB60 -> 103188.98 | Q65: =IS!AC60 -> 103188.98 | R65: =IS!AD60 -> 103188.98 | S65: =IS!AE60 -> 103188.98 | T65: =IS!AF60 -> 103188.98 | V65: =IS!AH60 -> 103188.98 | W65: =IS!AI60 -> 103188.98 | X65: =W65 -> 103188.98 | Y65: =X65 -> 103188.98 | Z65: =AVERAGE(V65:Y65) -> 103188.98 | AB65: =Y65 -> 103188.98 | AC65: =AB65 -> 103188.98 | AD65: =AC65 -> 103188.98 | AE65: =AD65 -> 103188.98 | AF65: =AVERAGE(AB65:AE65) -> 103188.98 | AH65: =AF65 -> 103188.98 | AJ65: =AH65 -> 103188.98 | AL65: =AJ65 -> 103188.98
B67: Balance Sheet | D67: Q1 22 | E67: Q2 22 | F67: Q3 22 | G67: Q4 22 | H67: FY 22 | J67: Q1 23 | K67: Q2 23 | L67: Q3 23 | M67: Q4 23 | N67: FY 23 | P67: Q1 24 | Q67: Q2 24 | R67: Q3 24 | S67: Q4 24 | T67: FY 24 | V67: Q1 25 | W67: Q2 25 | X67: Q3 25 | Y67: Q4 25 | Z67: FY 25 | AB67: Q1 26 | AC67: Q2 26 | AD67: Q3 26 | AE67: Q4 26 | AF67: FY 26 | AH67: FY 27 | AJ67: FY 28 | AL67: FY 29
B70: Accounts Receivable | D70: =BS!P18 -> 28924 | E70: =BS!Q18 -> 28321 | F70: =BS!R18 -> 29152 | G70: =BS!S18 -> 27790 | H70: =BS!T18 -> 27790 | J70: =BS!V18 -> 54790 | K70: =BS!W18 -> 27629 | L70: =BS!X18 -> 26445 | M70: =BS!Y18 -> 64174 | N70: =BS!Z18 -> 64174 | P70: =BS!AB18 -> 57350 | Q70: =BS!AC18 -> 53573 | R70: =BS!AD18 -> 47112 | S70: =BS!AE18 -> 57612 | T70: =BS!AF18 -> 57612 | V70: =BS!AH18 -> 51788 | W70: =BS!AI18 -> 54156 | X70: =X31*X71/92 -> 50569.217 | Y70: =Y31*Y71/92 -> 70512.522 | Z70: =Y70 -> 70512.522 | AB70: =AB31*AB71/90 -> 75850.906 | AC70: =AC31*AC71/91 -> 75017.379 | AD70: =AD31*AD71/92 -> 74201.973 | AE70: =AE31*AE71/92 -> 74201.973 | AF70: =AE70 -> 74201.973 | AH70: =AH31*AH71/365 -> 86196.849 | AJ70: =AJ31*AJ71/366 -> 90774.984 | AL70: =AL31*AL71/365 -> 98671.93
B71: days sales outstanding | D71: =D70/D31*90 -> 76.262964 | E71: =E70/E31*91 -> 75.132966 | F71: =F70/F31*92 -> 78.014544 | G71: =G70/G31*92 -> 67.18911 | H71: =H70/H31*365 -> 72.007085 | J71: =J70/J31*90 -> 93.517799 | K71: =K70/K31*91 -> 64.283059 | L71: =L70/L31*92 -> 63.308353 | M71: =M70/M31*92 -> 255.46311 | N71: =N70/N31*365 -> 152.71355 | P71: =P70/P31*90 -> 136.00791 | Q71: =Q70/Q31*91 -> 122.5711 | R71: =R70/R31*92 -> 104.343 | S71: =S70/S31*92 -> 91.509194 | T71: =T70/T31*365 -> 118.68103 | V71: =V70/V31*90 -> 101.6647 | W71: =W70/W31*91 -> 77.006672 | X71: 80 | Y71: 80 | Z71: =Z70/Z31*365 -> 103.32563 | AB71: 90 | AC71: 90 | AD71: 90 | AE71: 90 | AF71: =AF70/AF31*365 -> 89.266304 | AH71: 90 | AJ71: 90 | AL71: 90
B73: Inventory | D73: =BS!P19 -> 0 | E73: =BS!Q19 -> 0 | F73: =BS!R19 -> 0 | G73: =BS!S19 -> 0 | H73: =BS!T19 -> 0 | J73: =BS!V19 -> 0 | K73: =BS!W19 -> 0 | L73: =BS!X19 -> 0 | M73: =BS!Y19 -> 0 | N73: =BS!Z19 -> 0 | P73: =BS!AB19 -> 0 | Q73: =BS!AC19 -> 0 | R73: =BS!AD19 -> 0 | S73: =BS!AE19 -> 0 | T73: =BS!AF19 -> 0 | V73: =BS!AH19 -> 0 | W73: =BS!AI19 -> 0 | X73: =X74*X34/92 -> 0 | Y73: =Y74*Y34/92 -> 0 | Z73: =Y73 -> 0 | AB73: =AB74*AB34/92 -> 0 | AC73: =AC74*AC34/92 -> 0 | AD73: =AD74*AD34/92 -> 0 | AE73: =AE74*AE34/92 -> 0 | AF73: =AE73 -> 0 | AH73: =AH74*AH34/365 -> 0 | AJ73: =AJ74*AJ34/366 -> 0 | AL73: =AL74*AL34/365 -> 0
B74: days inventory held | D74: =D73/D34*90 -> 0 | E74: =E73/E34*91 -> 0 | F74: =F73/F34*92 -> 0 | G74: =G73/G34*92 -> 0 | H74: 0 | J74: =J73/J34*90 -> 0 | K74: =K73/K34*91 -> 0 | L74: =L73/L34*92 -> 0 | M74: =M73/M34*92 -> 0 | N74: 0 | P74: =P73/P34*90 -> 0 | Q74: =Q73/Q34*91 -> 0 | R74: =R73/R34*92 -> 0 | S74: =S73/S34*92 -> 0 | T74: 0 | V74: =V73/V34*90 -> 0 | W74: =W73/W34*91 -> 0 | X74: 0 | Y74: 0 | Z74: =Z73/Z34*365 -> 0 | AB74: 0 | AC74: 0 | AD74: 0 | AE74: 0 | AF74: =AF73/AF34*365 -> 0 | AH74: 0 | AJ74: 0 | AL74: 0
B76: Prepaid expenses and Other Current Assets | D76: =BS!P20 -> 448360 | E76: =BS!Q20 -> 411216 | F76: =BS!R20 -> 361385 | G76: =BS!S20 -> 305858 | H76: =BS!T20 -> 305858 | J76: =BS!V20 -> 282502 | K76: =BS!W20 -> 261893 | L76: =BS!X20 -> 198018 | M76: =BS!Y20 -> 384295 | N76: =BS!Z20 -> 384295 | P76: =BS!AB20 -> 453695 | Q76: =BS!AC20 -> 461016 | R76: =BS!AD20 -> 409302 | S76: =BS!AE20 -> 398261 | T76: =BS!AF20 -> 398261 | V76: =BS!AH20 -> 437103 | W76: =BS!AI20 -> 485644 | X76: =X77*X$31 -> 494314.1 | Y76: =Y77*Y$31 -> 567625.8 | Z76: =Y76 -> 567625.8 | AB76: =AB77*AB$31 -> 568881.79 | AC76: =AC77*AC$31 -> 568881.79 | AD76: =AD77*AD$31 -> 568881.79 | AE76: =AE77*AE$31 -> 568881.79 | AF76: =AF77*AF$31 -> 667487.97 | AH76: =AH77*AH$31 -> 769067.44 | AJ76: =AJ77*AJ$31 -> 775218.36 | AL76: =AL77*AL$31 -> 820347.46
B77: % of sales | D77: =D76/D31 -> 13.13529 | E77: =E76/E31 -> 11.988106 | F77: =F76/F31 -> 10.512101 | G77: =G76/G31 -> 8.0378955 | H77: =H76/H31 -> 2.1712691 | J77: =J76/J31 -> 5.357621 | K77: =K76/K31 -> 6.6959757 | L77: =L76/L31 -> 5.1526932 | M77: =M76/M31 -> 16.628229 | N77: =N76/N31 -> 2.5054765 | P77: =P76/P31 -> 11.955072 | Q77: =Q76/Q31 -> 11.590889 | R77: =R76/R31 -> 9.8534389 | S77: =S76/S31 -> 6.8759345 | T77: =T76/T31 -> 2.2477255 | V77: =V76/V31 -> 9.5341578 | W77: =W76/W31 -> 7.5885432 | X77: 8.5 | Y77: 7 | Z77: =Z76/Z$31 -> 2.2788255 | AB77: 7.5 | AC77: 7.5 | AD77: 7.5 | AE77: 7.5 | AF77: 2.2 | AH77: 2.2 | AJ77: 2.1 | AL77: 2.05
B79: Net PP&E (Property, Plant and Equipment) | D79: =BS!P24 -> 2796175 | E79: =BS!Q24 -> 2852444 | F79: =BS!R24 -> 3123185 | G79: =BS!S24 -> 3435286 | H79: =BS!T24 -> 3435286 | J79: =BS!V24 -> 3453936 | K79: =BS!W24 -> 3496179 | L79: =BS!X24 -> 3559898 | M79: =BS!Y24 -> 3792753 | N79: =BS!Z24 -> 3792753 | P79: =BS!AB24 -> 3814842 | Q79: =BS!AC24 -> 3814365 | R79: =BS!AD24 -> 3865233 | S79: =BS!AE24 -> 4043940 | T79: =BS!AF24 -> 4043940 | V79: =BS!AH24 -> 4072450 | W79: =BS!AI24 -> 4089253 | X79: =W79-X80*X106-X109-X52-X37 -> 4087532.7 | Y79: =X79-Y80*Y106-Y109-Y52-Y37 -> 4085779.7 | Z79: =Y79 -> 4085779.7 | AB79: =Y79-AB80*AB106-AB109-AB52-AB37 -> 4083742.1 | AC79: =AB79-AC80*AC106-AC109-AC52-AC37 -> 4081705.6 | AD79: =AC79-AD80*AD106-AD109-AD52-AD37 -> 4079670 | AE79: =AD79-AE80*AE106-AE109-AE52-AE37 -> 4077635.5 | AF79: =AE79 -> 4077635.5 | AH79: =AF79-AH80*AH106-AH109-AH52-AH37 -> 4067435.6 | AJ79: =AH79-AJ80*AJ106-AJ109-AJ52-AJ37 -> 4057265.5 | AL79: =AJ79-AL80*AL106-AL109-AL52-AL37 -> 4047127.6
B80: capex allocation rate | X80: 0.07 | Y80: 0.07 | Z80: =AVERAGE(V80:Y80) -> 0.07 | AB80: 0.07 | AC80: 0.07 | AD80: 0.07 | AE80: 0.07 | AF80: =AVERAGE(AB80:AE80) -> 0.07 | AH80: 0.07 | AJ80: 0.07 | AL80: 0.07
B82: Intangibles | D82: =IF($B$82="Intangibles excl. Goodwill",BS!P29,BS!P27) -> 5511 | E82: =IF($B$82="Intangibles excl. Goodwill",BS!Q29,BS!Q27) -> 5528 | F82: =IF($B$82="Intangibles excl. Goodwill",BS!R29,BS!R27) -> 8596 | G82: =IF($B$82="Intangibles excl. Goodwill",BS!S29,BS!S27) -> 12278 | H82: =IF($B$82="Intangibles excl. Goodwill",BS!T29,BS!T27) -> 12278 | J82: =IF($B$82="Intangibles excl. Goodwill",BS!V29,BS!V27) -> 10432 | K82: =IF($B$82="Intangibles excl. Goodwill",BS!W29,BS!W27) -> 10194 | L82: =IF($B$82="Intangibles excl. Goodwill",BS!X29,BS!X27) -> 9742 | M82: =IF($B$82="Intangibles excl. Goodwill",BS!Y29,BS!Y27) -> 9312 | N82: =IF($B$82="Intangibles excl. Goodwill",BS!Z29,BS!Z27) -> 9312 | P82: =IF($B$82="Intangibles excl. Goodwill",BS!AB29,BS!AB27) -> 32587 | Q82: =IF($B$82="Intangibles excl. Goodwill",BS!AC29,BS!AC27) -> 33636 | R82: =IF($B$82="Intangibles excl. Goodwill",BS!AD29,BS!AD27) -> 38650 | S82: =IF($B$82="Intangibles excl. Goodwill",BS!AE29,BS!AE27) -> 41264 | T82: =IF($B$82="Intangibles excl. Goodwill",BS!AF29,BS!AF27) -> 41264 | V82: =IF($B$82="Intangibles excl. Goodwill",BS!AH29,BS!AH27) -> 41735 | W82: =IF($B$82="Intangibles excl. Goodwill",BS!AI29,BS!AI27) -> 44086 | X82: =W82-(1-X80)*X106-X55+X83*X46 -> 44119.944 | Y82: =X82-(1-Y80)*Y106-Y55+Y83*Y46 -> 44167.274 | Z82: =Y82 -> 44167.274 | AB82: =Y82-(1-AB80)*AB106-AB55+AB83*AB46 -> 44237.816 | AC82: =AB82-(1-AC80)*AC106-AC55+AC83*AC46 -> 44308.357 | AD82: =AC82-(1-AD80)*AD106-AD55+AD83*AD46 -> 44378.898 | AE82: =AD82-(1-AE80)*AE106-AE55+AE83*AE46 -> 44449.44 | AF82: =AE82 -> 44449.44 | AH82: =AF82-(1-AH80)*AH106-AH55+AH83*AH46 -> 45424.757 | AJ82: =AH82-(1-AJ80)*AJ106-AJ55+AJ83*AJ46 -> 46454.69 | AL82: =AJ82-(1-AL80)*AL106-AL55+AL83*AL46 -> 47571.163
B83: r&d capitalization rate | D83: =IFERROR(BS!P57/FCFF!D82,"") -> 0 | E83: =IFERROR(BS!Q57/FCFF!E82,"") -> 0 | F83: =IFERROR(BS!R57/FCFF!F82,"") -> 0 | G83: =IFERROR(BS!S57/FCFF!G82,"") -> 0 | H83: =IFERROR(BS!T57/FCFF!H82,"") -> 0 | J83: =IFERROR(BS!V57/FCFF!J82,"") -> 0 | K83: =IFERROR(BS!W57/FCFF!K82,"") -> 0 | L83: =IFERROR(BS!X57/FCFF!L82,"") -> 0 | M83: =IFERROR(BS!Y57/FCFF!M82,"") -> 0 | N83: =IFERROR(BS!Z57/FCFF!N82,"") -> 0 | P83: =IFERROR(BS!AB57/FCFF!P82,"") -> 0 | Q83: =IFERROR(BS!AC57/FCFF!Q82,"") -> 0 | R83: =IFERROR(BS!AD57/FCFF!R82,"") -> 0 | S83: =IFERROR(BS!AE57/FCFF!S82,"") -> 0 | T83: =IFERROR(BS!AF57/FCFF!T82,"") -> 0 | V83: =IFERROR(BS!AH57/FCFF!V82,"") -> 0 | W83: =IFERROR(BS!AI57/FCFF!W82,"") -> 0 | X83: 0 | Y83: 0 | Z83: =AVERAGE(V83:Y83) -> 0 | AB83: 0 | AC83: 0 | AD83: 0 | AE83: 0 | AF83: =AVERAGE(AB83:AE83) -> 0 | AH83: 0 | AJ83: 0 | AL83: 0
B85: Accounts Payable | D85: =BS!P37 -> 50169 | E85: =BS!Q37 -> 43638 | F85: =BS!R37 -> 82724 | G85: =BS!S37 -> 115496 | H85: =BS!T37 -> 115496 | J85: =BS!V37 -> 109796 | K85: =BS!W37 -> 84330 | L85: =BS!X37 -> 86595 | M85: =BS!Y37 -> 102367 | N85: =BS!Z37 -> 102367 | P85: =BS!AB37 -> 99570 | Q85: =BS!AC37 -> 111863 | R85: =BS!AD37 -> 134204 | S85: =BS!AE37 -> 109922 | T85: =BS!AF37 -> 109922 | V85: =BS!AH37 -> 120197 | W85: =BS!AI37 -> 76519 | X85: =X86*X58/90 -> 84001.089 | Y85: =Y86*Y58/90 -> 117129.13 | Z85: =Y85 -> 117129.13 | AB85: =AB86*AB58/90 -> 112933.57 | AC85: =AC86*AC58/90 -> 112933.57 | AD85: =AD86*AD58/90 -> 112933.57 | AE85: =+AD85*1.1 -> 124226.93 | AF85: =+AE85 -> 124226.93 | AH85: =AH86*AH34/365 -> 143661.42 | AJ85: =AJ86*AJ34/366 -> 151291.64 | AL85: =AL86*AL34/365 -> 164453.22
B86: days payable outstanding | D86: =D85/D58*90 -> -11288.025 | E86: =E85/E58*90 -> -6175.1887 | F86: =F85/F58*90 -> -2581.5395 | G86: =G85/G58*90 -> 1260.8734 | H86: =H85/H58*90 -> 2403.9408 | J86: =J85/J58*90 -> 868.18134 | K86: =K85/K58*90 -> 3950.911 | L86: =L85/L58*90 -> -3516.9449 | M86: =M85/M58*90 -> 508.10887 | N86: =N85/N58*90 -> 315.30956 | P86: =P85/P58*90 -> -1844.2684 | Q86: =Q85/Q58*90 -> 1115.2841 | R86: =R85/R58*90 -> 1939.0528 | S86: =S85/S58*90 -> -2324.4784 | T86: =T85/T58*90 -> 1610.9722 | V86: =V85/V58*90 -> 931.75969 | W86: =W85/W58*90 -> 179.7815 | X86: 650 | Y86: 650 | Z86: =Z85/Z34*365 -> 741.29278 | AA86: 678 | AB86: 670 | AC86: 670 | AD86: 670 | AE86: 670 | AF86: =AF85/AF34*365 -> 747.23611 | AG86: 678 | AH86: 1000 | AI86: 678 | AJ86: 1000 | AK86: 678 | AL86: 1000
AD87: =+AE86/4 -> 167.5 | AE87: =+AVERAGE(AB86:AE86)/4 -> 167.5 | AH87: =300/4 -> 75
B88: Accrued Expenses and Other Current Liabilities | D88: =BS!P40 -> 97861 | E88: =BS!Q40 -> 96529 | F88: =BS!R40 -> 84641 | G88: =BS!S40 -> 101678 | H88: =BS!T40 -> 101678 | J88: =BS!V40 -> 100152 | K88: =BS!W40 -> 84748 | L88: =BS!X40 -> 87059 | M88: =BS!Y40 -> 89242 | N88: =BS!Z40 -> 89242 | P88: =BS!AB40 -> 122178 | Q88: =BS!AC40 -> 113466 | R88: =BS!AD40 -> 127183 | S88: =BS!AE40 -> 143540 | T88: =BS!AF40 -> 143540 | V88: =BS!AH40 -> 146764 | W88: =BS!AI40 -> 160436 | X88: =X89*X43 -> 168648.34 | Y88: =Y89*Y43 -> 243268.2 | Z88: =Y88 -> 243268.2 | AB88: =AB89*AB43 -> 273063.26 | AC88: =AC89*AC43 -> 273063.26 | AD88: =AD89*AD43 -> 273063.26 | AE88: =+AE89*AE43 -> 273063.26 | AF88: =+AE88 -> 273063.26 | AH88: =AH89*AH43 -> 314618.5 | AJ88: =AJ89*AJ43 -> 332236.44 | AL88: =AL89*AL43 -> 360152.54
B89: % of sg&a | D89: =D88/D43 -> 10.434055 | E89: =E88/E43 -> 11.667956 | F89: =F88/F43 -> 9.755763 | G89: =G88/G43 -> 13.268694 | H89: =H88/H43 -> 2.9913212 | J89: =J88/J43 -> 9.7452564 | K89: =K88/K43 -> 7.2267417 | L89: =L88/L43 -> 8.0782221 | M89: =M88/M43 -> 7.0956508 | N89: =N88/N43 -> 1.967503 | P89: =P88/P43 -> 9.8340309 | Q89: =Q88/Q43 -> 10.507084 | R89: =R88/R43 -> 11.167179 | S89: =S88/S43 -> 11.246572 | T89: =T88/T43 -> 3.0298681 | V89: =V88/V43 -> 21.092843 | W89: =W88/W43 -> 12.705789 | X89: 14.5 | Y89: 15 | Z89: =Z88/Z43 -> 5.1285834 | AB89: 18 | AC89: 18 | AD89: 18 | AE89: 18 | AF89: =AF88/AF43 -> 4.5 | AH89: 4.5 | AJ89: 4.5 | AL89: 4.5
W90: =+AVERAGE(V89:W89) -> 16.899316
B91: Cash Flow Statement | D91: Q1 22 | E91: Q2 22 | F91: Q3 22 | G91: Q4 22 | H91: FY 22 | J91: Q1 23 | K91: Q2 23 | L91: Q3 23 | M91: Q4 23 | N91: FY 23 | P91: Q1 24 | Q91: Q2 24 | R91: Q3 24 | S91: Q4 24 | T91: FY 24 | V91: Q1 25 | W91: Q2 25 | X91: Q3 25 | Y91: Q4 25 | Z91: FY 25 | AB91: Q1 26 | AC91: Q2 26 | AD91: Q3 26 | AE91: Q4 26 | AF91: FY 26 | AH91: FY 27 | AJ91: FY 28 | AL91: FY 29
B94: D&A (Depreciation & Amortization) | D94: =CF!P17 -> 173 | E94: =CF!Q17 -> 194 | F94: =CF!R17 -> 243 | G94: =CF!S17 -> 305 | H94: =CF!T17 -> 915 | J94: =CF!V17 -> 480 | K94: =CF!W17 -> 562 | L94: =CF!X17 -> 476 | M94: =CF!Y17 -> 459 | N94: =CF!Z17 -> 1977 | P94: =CF!AB17 -> 1055 | Q94: =CF!AC17 -> 1119 | R94: =CF!AD17 -> 1189 | S94: =CF!AE17 -> 1181 | T94: =CF!AF17 -> 4544 | V94: =CF!AH17 -> 1621 | W94: =CF!AI17 -> 1818 | X94: =X37+X49 -> 1722.8441 | Y94: =Y37+Y49 -> 1756.5617 | Z94: =SUM(V94:Y94) -> 6918.4059 | AB94: =AB37+AB49 -> 2042.8899 | AC94: =AC37+AC49 -> 2041.8711 | AD94: =AD37+AD49 -> 2040.8528 | AE94: =AE37+AE49 -> 2039.835 | AF94: =SUM(AB94:AE94) -> 8165.4487 | AH94: =AH37+AH49 -> 10273.293 | AJ94: =AJ37+AJ49 -> 10247.595 | AL94: =AL37+AL49 -> 10221.972
B95: % of net pp&e and intangibles excl. Goodwill | D95: =D94/(D82+D79) -> 6.1748533e-05 | E95: =E94/(E82+E79) -> 6.7880301e-05 | F95: =F94/(F82+F79) -> 7.7591632e-05 | G95: =G94/(G82+G79) -> 8.8468263e-05 | H95: =H94/(H82+H79) -> 0.00026540479 | J95: =J94/(J82+J79) -> 0.00013855341 | K95: =K94/(K82+K79) -> 0.00016027958 | L95: =L94/(L82+L79) -> 0.00013334678 | M95: =M94/(M82+M79) -> 0.00012072387 | N95: =N94/(N82+N79) -> 0.00051998059 | P95: =P94/(P82+P79) -> 0.00027420909 | Q95: =Q94/(Q82+Q79) -> 0.00029080034 | R95: =R94/(R82+R79) -> 0.00030456855 | S95: =S94/(S82+S79) -> 0.00028909205 | T95: =T94/(T82+T79) -> 0.0011123068 | V95: =V94/(V82+V79) -> 0.0003940027 | W95: =W94/(W82+W79) -> 0.00043983811 | X95: =X94/(X79+X82) -> 0.00041698668 | Y95: =Y94/(Y79+Y82) -> 0.00042532307 | Z95: =Z94/(Z79+Z82) -> 0.0016751803 | AB95: =AB94/(AB79+AB82) -> 0.00049488851 | AC95: =AC94/(AC79+AC82) -> 0.00049487741 | AD95: =AD94/(AD79+AD82) -> 0.00049486629 | AE95: =AE94/(AE79+AE82) -> 0.00049485516 | AF95: =AF94/(AF79+AF82) -> 0.0019809026 | AH95: =AH94/(AH79+AH82) -> 0.0024978462 | AJ95: =AJ94/(AJ79+AJ82) -> 0.0024971475 | AL95: =AL94/(AL79+AL82) -> 0.0024963917
B97: Stock-Based Compensation Expense | D97: =CF!P18 -> 0 | E97: =CF!Q18 -> 0 | F97: =CF!R18 -> 0 | G97: =CF!S18 -> 0 | H97: =CF!T18 -> 0 | J97: =CF!V18 -> 0 | K97: =CF!W18 -> 0 | L97: =CF!X18 -> 375 | M97: =CF!Y18 -> 353 | N97: =CF!Z18 -> 728 | P97: =CF!AB18 -> 1832 | Q97: =CF!AC18 -> -2644 | R97: =CF!AD18 -> 0 | S97: =CF!AE18 -> 0 | T97: =CF!AF18 -> -812 | V97: =CF!AH18 -> 132 | W97: =CF!AI18 -> -135 | X97: =X98*X43 -> 116.3092 | Y97: =Y98*Y43 -> 162.1788 | Z97: =SUM(V97:Y97) -> 275.488 | AB97: =AB98*AB43 -> 151.70181 | AC97: =AC98*AC43 -> 151.70181 | AD97: =AD98*AD43 -> 151.70181 | AE97: =AE98*AE43 -> 151.70181 | AF97: =SUM(AB97:AE97) -> 606.80725 | AH97: =AH98*AH43 -> 699.15222 | AJ97: =AJ98*AJ43 -> 738.3032 | AL97: =AL98*AL43 -> 800.33898
B98: % of sg&a | D98: =D97/D43 -> 0 | E98: =E97/E43 -> 0 | F98: =F97/F43 -> 0 | G98: =G97/G43 -> 0 | H98: =H97/H43 -> 0 | J98: =J97/J43 -> 0 | K98: =K97/K43 -> 0 | L98: =L97/L43 -> 0.034796326 | M98: =M97/M43 -> 0.028067107 | N98: =N97/N43 -> 0.01605009 | P98: =P97/P43 -> 0.14745654 | Q98: =Q97/Q43 -> -0.24483748 | R98: =R97/R43 -> 0 | S98: =S97/S43 -> 0 | T98: =T97/T43 -> -0.017139842 | V98: =V97/V43 -> 0.018970969 | W98: =W97/W43 -> -0.010691376 | X98: 0.01 | Y98: 0.01 | Z98: =Z97/Z43 -> 0.0058078417 | AB98: 0.01 | AC98: 0.01 | AD98: 0.01 | AE98: 0.01 | AF98: =AF97/AF43 -> 0.01 | AH98: 0.01 | AJ98: 0.01 | AL98: 0.01
B99: implied equity value (p/s multiple) | X99: 0.65 | Y99: 1.06 | Z99: 0.95 | AB99: 1.18 | AC99: 1.18 | AD99: 1.18 | AE99: 1.18 | AF99: =AVERAGE(AB99:AE99) -> 1.18 | AH99: 1.3 | AJ99: 1.4 | AL99: 1.5
B100: implied share price (for dilution) | X100: =X99*(X31+W31+V31+S31)/W64 -> 1.4230889 | Y100: =Y99*(Y31+X31+W31+V31)/X64 -> 2.5566999 | Z100: =AVERAGE(V100:Y100) -> 1.9898944 | AB100: =AB99*(AB31+Y31+X31+W31)/Y64 -> 3.1870245 | AC100: =AC99*(AC31+AB31+Y31+X31)/AB64 -> 3.3208577 | AD100: =AD99*(AD31+AC31+AB31+Y31)/AC64 -> 3.5212875 | AE100: =AE99*(AE31+AD31+AC31+AB31)/AD64 -> 3.4615217 | AF100: =AVERAGE(AB100:AE100) -> 3.3726728 | AH100: =AH99*AH31/AE64 -> 4.3938921 | AJ100: =AJ99*AJ31/AH64 -> 4.9891831 | AL100: =AL99*AL31/AJ64 -> 5.7959747
B101: sbc dilution (shares issued) | X101: =X97/X100 -> 81.730103 | Y101: =Y97/Y100 -> 63.432864 | Z101: =AVERAGE(V101:Y101) -> 72.581484 | AB101: =AB97/AB100 -> 47.599826 | AC101: =AC97/AC100 -> 45.681516 | AD101: 0 | AE101: 0 | AF101: =AVERAGE(AB101:AE101) -> 23.320335 | AH101: =AH97/AH100 -> 159.11912 | AJ101: =AJ97/AJ100 -> 147.98078 | AL101: =AL97/AL100 -> 138.08531
B103: Changes in Net Working Capital | E103: =-((E70+E73+E76-E85-E88)-(D70+D73+D76-D85-D88)) -> 29884 | F103: =-((F70+F73+F76-F85-F88)-(E70+E73+E76-E85-E88)) -> 76198 | G103: =-((G70+G73+G76-G85-G88)-(F70+F73+F76-F85-F88)) -> 106698 | H103: =+SUM(D103:G103) -> 212780 | J103: =-((J70+J73+J76-J85-J88)-(G70+G73+G76-G85-G88)) -> -10870 | K103: =-((K70+K73+K76-K85-K88)-(J70+J73+J76-J85-J88)) -> 6900 | L103: =-((L70+L73+L76-L85-L88)-(K70+K73+K76-K85-K88)) -> 69635 | M103: =-((M70+M73+M76-M85-M88)-(L70+L73+L76-L85-L88)) -> -206051 | N103: =+SUM(J103:M103) -> -140386 | P103: =-((P70+P73+P76-P85-P88)-(M70+M73+M76-M85-M88)) -> -32437 | Q103: =-((Q70+Q73+Q76-Q85-Q88)-(P70+P73+P76-P85-P88)) -> 37 | R103: =-((R70+R73+R76-R85-R88)-(Q70+Q73+Q76-Q85-Q88)) -> 94233 | S103: =-((S70+S73+S76-S85-S88)-(R70+R73+R76-R85-R88)) -> -7384 | T103: =+SUM(P103:S103) -> 54449 | V103: =-((V70+V73+V76-V85-V88)-(S70+S73+S76-S85-S88)) -> -19519 | W103: =-((W70+W73+W76-W85-W88)-(V70+V73+V76-V85-V88)) -> -80915 | X103: =-((X70+X73+X76-X85-X88)-(W70+W73+W76-W85-W88)) -> 10611.111 | Y103: =-((Y70+Y73+Y76-Y85-Y88)-(X70+X73+X76-X85-X88)) -> 14492.9 | Z103: =SUM(V103:Y103) -> -75329.988 | AB103: =-((AB70+AB73+AB76-AB85-AB88)-(Y70+Y73+Y76-Y85-Y88)) -> 19005.121 | AC103: =-((AC70+AC73+AC76-AC85-AC88)-(AB70+AB73+AB76-AB85-AB88)) -> 833.52644 | AD103: =-((AD70+AD73+AD76-AD85-AD88)-(AC70+AC73+AC76-AC85-AC88)) -> 815.4063 | AE103: =-((AE70+AE73+AE76-AE85-AE88)-(AD70+AD73+AD76-AD85-AD88)) -> 11293.357 | AF103: =SUM(AB103:AE103) -> 31947.411 | AH103: =-((AH70+AH73+AH76-AH85-AH88)-(AF70+AF73+AF76-AF85-AF88)) -> -52584.623 | AJ103: =-((AJ70+AJ73+AJ76-AJ85-AJ88)-(AH70+AH73+AH76-AH85-AH88)) -> 14519.113 | AL103: =-((AL70+AL73+AL76-AL85-AL88)-(AJ70+AJ73+AJ76-AJ85-AJ88)) -> -11948.365
B104: % of change in sales | D104: =D103/(D31-IS!M18) -> 0 | E104: =E103/(E31-D31) -> 177.88095 | F104: =F103/(F31-E31) -> 1002.6053 | G104: =G103/(G31-F31) -> 29.041372 | H104: =H103/IS!N18 -> 2.4206503 | J104: =J103/(J31-IS!S18) -> -0.74061457 | K104: =K103/(K31-J31) -> -0.50671954 | L104: =L103/(L31-K31) -> -102.10411 | M104: =M103/(M31-L31) -> 13.450682 | N104: =N103/IS!T18 -> -0.99659251 | P104: =P103/(P31-IS!Y18) -> -2.185929 | Q104: =Q103/(Q31-P31) -> 0.020285088 | R104: =R103/(R31-Q31) -> 53.389802 | S104: =S103/(S31-R31) -> -0.45073862 | T104: =T103/IS!Z18 -> 0.3549895 | V104: =V103/(V31-IS!AE18) -> -10.449143 | W104: =W103/(W31-V31) -> -4.4578811 | X104: =X103/(X31-W31) -> -1.8162248 | Y104: =Y103/(Y31-X31) -> 0.63191744 | Z104: =Z103/(Z31-T31) -> -1.0476613 | AB104: =AB103/(AB31-IS!AK18) -> -3.627974 | AC104: =AC103/(AC31-AB31) -> #DIV/0! | AD104: =AD103/(AD31-AC31) -> #DIV/0! | AE104: =AE103/(AE31-AD31) -> #DIV/0! | AF104: =AF103/(AF31-Z31) -> 0.58817005 | AH104: =AH103/(AH31-AF31) -> -1.1388735 | AJ104: =AJ103/(AJ31-AH31) -> 0.74169861 | AL104: =AL103/(AL31-AJ31) -> -0.38520879
B106: Capital Expenditures | D106: =CF!P28 -> -63.727 | E106: =CF!Q28 -> -56.269 | F106: =CF!R28 -> -270.741 | G106: =CF!S28 -> -213.108 | H106: =CF!T28 -> -603.845 | J106: =CF!V28 -> -27.851 | K106: =CF!W28 -> -42.243 | L106: =CF!X28 -> -63.719 | M106: =CF!Y28 -> 0 | N106: =CF!Z28 -> -133.813 | P106: =CF!AB28 -> -26.808 | Q106: =CF!AC28 -> -6.614 | R106: =CF!AD28 -> -50.868 | S106: =CF!AE28 -> 0 | T106: =CF!AF28 -> -84.29 | V106: =CF!AH28 -> -28.51 | W106: =CF!AI28 -> -18.294 | X106: =-X$31*(X107+Sensitivity!$U$38) -> -36.498698 | Y106: =-Y$31*(Y107+Sensitivity!$U$38) -> -50.892922 | Z106: =SUM(V106:Y106) -> -134.19562 | AB106: =-AB$31*(AB107+Sensitivity!$U$38) -> -75.850906 | AC106: =-AC$31*(AC107+Sensitivity!$U$38) -> -75.850906 | AD106: =-AD$31*(AD107+Sensitivity!$U$38) -> -75.850906 | AE106: =-AE$31*(AE107+Sensitivity!$U$38) -> -75.850906 | AF106: =SUM(AB106:AE106) -> -303.40362 | AH106: =-AH$31*(AH107+Sensitivity!$U$38) -> -1048.7283 | AJ106: =-AJ$31*(AJ107+Sensitivity!$U$38) -> -1107.4548 | AL106: =-AL$31*(AL107+Sensitivity!$U$38) -> -1200.5085
B107: % of sales | D107: =-D106/D31 -> 0.0018669655 | E107: =-E106/E31 -> 0.0016404 | F107: =-F106/F31 -> 0.0078754145 | G107: =-G106/G31 -> 0.0056004415 | H107: =-H106/H31 -> 0.0042866625 | J107: =-J106/J31 -> 0.00052819132 | K107: =-K106/K31 -> 0.0010800522 | L107: =-L106/L31 -> 0.0016580536 | M107: =-M106/M31 -> 0 | N107: =-N106/N31 -> 0.00087241658 | P107: =-P106/P31 -> 0.00070640316 | Q107: =-Q106/Q31 -> 0.00016628954 | R107: =-R106/R31 -> 0.0012245841 | S107: =-S106/S31 -> 0 | T107: =-T106/T31 -> 0.00047572016 | V107: =-V106/V31 -> 0.0006218645 | W107: =-W106/W31 -> 0.00028585715 | X107: 0.00062761497 | Y107: 0.00062761497 | Z107: =-Z106/Z$31 -> 0.00053874999 | AB107: 0.001 | AC107: 0.001 | AD107: 0.001 | AE107: 0.001 | AF107: =-AF106/AF$31 -> 0.001 | AH107: 0.003 | AJ107: 0.003 | AL107: 0.003
B109: Proceeds from Asset Disposals | D109: =CF!P29 -> 0 | E109: =CF!Q29 -> 0 | F109: =CF!R29 -> 0 | G109: =CF!S29 -> 0 | H109: =CF!T29 -> 0 | J109: =CF!V29 -> 0 | K109: =CF!W29 -> 0 | L109: =CF!X29 -> 0 | M109: =CF!Y29 -> 124 | N109: =CF!Z29 -> 124 | P109: =CF!AB29 -> 0 | Q109: =CF!AC29 -> 0 | R109: =CF!AD29 -> 0 | S109: =CF!AE29 -> 17.5 | T109: =CF!AF29 -> 17.5 | V109: =CF!AH29 -> 0 | W109: =CF!AI29 -> 0 | X109: =X110*X$106 -> 0 | Y109: =Y110*Y$106 -> 0 | Z109: =SUM(V109:Y109) -> 0 | AB109: =AB110*AB$106 -> 0 | AC109: =AC110*AC$106 -> 0 | AD109: =AD110*AD$106 -> 0 | AE109: =AE110*AE$106 -> 0 | AF109: =SUM(AB109:AE109) -> 0 | AH109: =AH110*AH$106 -> 0 | AJ109: =AJ110*AJ$106 -> 0 | AL109: =AL110*AL$106 -> 0
B110: % of capex | D110: =-D109/D106 -> 0 | E110: =-E109/E106 -> 0 | F110: =-F109/F106 -> 0 | G110: =-G109/G106 -> 0 | H110: =-H109/H106 -> 0 | J110: =-J109/J106 -> 0 | K110: =-K109/K106 -> 0 | L110: =-L109/L106 -> 0 | M110: =-M109/M106 -> #DIV/0! | N110: =-N109/N106 -> 0.92666632 | P110: =-P109/P106 -> 0 | Q110: =-Q109/Q106 -> 0 | R110: =-R109/R106 -> 0 | S110: =-S109/S106 -> #DIV/0! | T110: =-T109/T106 -> 0.20761656 | V110: =-V109/V106 -> 0 | W110: =-W109/W106 -> 0 | Z110: =-Z109/Z$31 -> 0 | AF110: =-AF109/AF$31 -> 0 | AH110: 0 | AJ110: 0 | AL110: 0
B112: Dividends | D112: =CF!P39 -> 0 | E112: =CF!Q39 -> 0 | F112: =CF!R39 -> 0 | G112: =CF!S39 -> 0 | H112: =CF!T39 -> 0 | J112: =CF!V39 -> 0 | K112: =CF!W39 -> 0 | L112: =CF!X39 -> 0 | M112: =CF!Y39 -> 0 | N112: =CF!Z39 -> 0 | P112: =CF!AB39 -> 0 | Q112: =CF!AC39 -> 0 | R112: =CF!AD39 -> 0 | S112: =CF!AE39 -> 0 | T112: =CF!AF39 -> 0 | V112: =CF!AH39 -> 0 | W112: =CF!AI39 -> 0 | X112: =-X113*X126 -> 0 | Y112: =-Y113*Y126 -> 0 | Z112: =SUM(V112:Y112) -> 0 | AB112: =-AB113*AB126 -> 0 | AC112: =-AC113*AC126 -> 0 | AD112: =-AD113*AD126 -> 0 | AE112: =-AE113*AE126 -> 0 | AF112: =SUM(AB112:AE112) -> 0 | AH112: =-AH113*AH126 -> 0 | AJ112: =-AJ113*AJ126 -> 0 | AL112: =-AL113*AL126 -> 0
B113: % of NOPAT | D113: =-D112/D126 -> 0 | E113: =-E112/E126 -> 0 | F113: =-F112/F126 -> 0 | G113: =-G112/G126 -> 0 | H113: =-H112/H126 -> 0 | J113: =-J112/J126 -> 0 | K113: =-K112/K126 -> 0 | L113: =-L112/L126 -> 0 | M113: =-M112/M126 -> 0 | N113: =-N112/N126 -> 0 | P113: =-P112/P126 -> 0 | Q113: =-Q112/Q126 -> 0 | R113: =-R112/R126 -> 0 | S113: =-S112/S126 -> 0 | T113: =-T112/T126 -> 0 | V113: =-V112/V126 -> 0 | W113: =-W112/W126 -> 0 | X113: 0 | Y113: 0 | Z113: =-Z112/Z126 -> 0 | AB113: 0 | AC113: 0 | AD113: 0 | AE113: 0 | AF113: =-AF112/AF126 -> 0 | AH113: 0 | AJ113: 0 | AL113: 0
B115: Repurchase of Stock | D115: =CF!P40 -> 0 | E115: =CF!Q40 -> 0 | F115: =CF!R40 -> 0 | G115: =CF!S40 -> 0 | H115: =CF!T40 -> 0 | J115: =CF!V40 -> 0 | K115: =CF!W40 -> 0 | L115: =CF!X40 -> 0 | M115: =CF!Y40 -> 0 | N115: =CF!Z40 -> 0 | P115: =CF!AB40 -> 0 | Q115: =CF!AC40 -> 0 | R115: =CF!AD40 -> 0 | S115: =CF!AE40 -> 0 | T115: =CF!AF40 -> 0 | V115: =CF!AH40 -> 0 | W115: =CF!AI40 -> 0 | X115: 0 | Y115: 0 | Z115: =SUM(V115:Y115) -> 0 | AB115: 0 | AC115: 0 | AD115: 0 | AE115: 0 | AF115: =SUM(AB115:AE115) -> 0 | AH115: 0 | AJ115: 0 | AL115: 0
A117: x | B117: Free Cash Flow to Firm
D118: =D$8 -> 2022 | E118: =F118 -> 0 | F118: =F$8 -> 0 | G118: =F118 -> 0 | H118: =F118 -> 0 | J118: =J$8 -> 2023 | K118: =L118 -> 0 | L118: =L$8 -> 0 | M118: =L118 -> 0 | N118: =L118 -> 0 | P118: =P$8 -> 2024 | Q118: =R118 -> 0 | R118: =R$8 -> 0 | S118: =R118 -> 0 | T118: =R118 -> 0 | V118: =V$8 -> 2025 | W118: =X118 -> 0 | X118: =X$8 -> 0 | Y118: =X118 -> 0 | Z118: =X118 -> 0 | AB118: =AB$8 -> 2026 | AC118: =AD118 -> 0 | AD118: =AD$8 -> 0 | AE118: =AD118 -> 0 | AF118: =AD118 -> 0 | AH118: =AH$8 -> 2027 | AJ118: =AJ$8 -> 2028 | AL118: =AL$8 -> 2029
D119: Q1 | E119: Q2 | F119: Q3 | G119: Q4 | H119: FY | J119: Q1 | K119: Q2 | L119: Q3 | M119: Q4 | N119: FY | P119: Q1 | Q119: Q2 | R119: Q3 | S119: Q4 | T119: FY | V119: Q1 | W119: Q2 | X119: Q3 | Y119: Q4 | Z119: FY | AB119: Q1 | AC119: Q2 | AD119: Q3 | AE119: Q4 | AF119: FY | AH119: FY | AJ119: FY | AL119: FY
B122: EBIT (Operating Income) | D122: =D61 -> 17288 | E122: =E61 -> 21112 | F122: =F61 -> 20961 | G122: =G61 -> 25367 | H122: =H61 -> 84728 | J122: =J61 -> 36065 | K122: =K61 -> 19959 | L122: =L61 -> 18675 | M122: =M61 -> -10710 | N122: =N61 -> 63989 | P122: =P61 -> 16906 | Q122: =Q61 -> 19586 | R122: =R61 -> 19162 | S122: =S61 -> 37759 | T122: =T61 -> 93413 | V122: =V61 -> 18699 | W122: =W61 -> 21706 | X122: =X61 -> 27354.456 | Y122: =Y61 -> 38788.138 | Z122: =Z61 -> 106547.59 | AB122: =AB61 -> 28297.472 | AC122: =AC61 -> 28298.491 | AD122: =AD61 -> 28299.51 | AE122: =AE61 -> 28300.527 | AF122: =AF61 -> 113196 | AH122: =AH61 -> 147035.96 | AJ122: =AJ61 -> 155870.63 | AL122: =AL61 -> 169854.3
B124: Tax Rate | D124: =IS!P45/IS!P42 -> -0.46440307 | E124: =IS!Q45/IS!Q42 -> -0.32732026 | F124: =IS!R45/IS!R42 -> 0.22309003 | G124: =IS!S45/IS!S42 -> -0.15532103 | H124: =IS!T45/IS!T42 -> -0.50465019 | J124: =IS!V45/IS!V42 -> 0.32547699 | K124: =IS!W45/IS!W42 -> -0.35169774 | L124: =IS!X45/IS!X42 -> -1.801054 | M124: =IS!Y45/IS!Y42 -> -0.04288168 | N124: =IS!Z45/IS!Z42 -> -0.18858624 | P124: =IS!AB45/IS!AB42 -> -0.21257403 | Q124: =IS!AC45/IS!AC42 -> -0.20807262 | R124: =IS!AD45/IS!AD42 -> -0.15492102 | S124: =IS!AE45/IS!AE42 -> -1.4330835 | T124: =IS!AF45/IS!AF42 -> -0.25191391 | V124: =IS!AH45/IS!AH42 -> -0.09243031 | W124: =IS!AI45/IS!AI42 -> -0.085290304 | X124: -0.08 | Y124: -0.08 | Z124: =AVERAGE(V124:Y124) -> -0.084430154 | AB124: -0.07 | AC124: -0.07 | AD124: -0.07 | AE124: -0.07 | AF124: -0.07 | AH124: -0.05 | AJ124: -0.04 | AL124: -0.03
B126: NOPAT (Net Operating Profit After Taxes) | D126: =D122*(1-D124) -> 25316.6 | E126: =E122*(1-E124) -> 28022.385 | F126: =F122*(1-F124) -> 16284.81 | G126: =G122*(1-G124) -> 29307.029 | H126: =H122*(1-H124) -> 127486 | J126: =J122*(1-J124) -> 24326.672 | K126: =K122*(1-K124) -> 26978.535 | L126: =L122*(1-L124) -> 52309.684 | M126: =M122*(1-M124) -> -11169.263 | N126: =N122*(1-N124) -> 76056.445 | P126: =P122*(1-P124) -> 20499.777 | Q126: =Q122*(1-Q124) -> 23661.31 | R126: =R122*(1-R124) -> 22130.597 | S126: =S122*(1-S124) -> 91870.8 | T126: =T122*(1-T124) -> 116945.03 | V126: =V122*(1-V124) -> 20427.354 | W126: =W122*(1-W124) -> 23557.311 | X126: =X122*(1-X124) -> 29542.812 | Y126: =Y122*(1-Y124) -> 41891.189 | Z126: =SUM(V126:Y126) -> 115418.67 | AB126: =AB122*(1-AB124) -> 30278.296 | AC126: =AC122*(1-AC124) -> 30279.386 | AD126: =AD122*(1-AD124) -> 30280.475 | AE126: =AE122*(1-AE124) -> 30281.564 | AF126: =SUM(AB126:AE126) -> 121119.72 | AH126: =AH122*(1-AH124) -> 154387.76 | AJ126: =AJ122*(1-AJ124) -> 162105.45 | AL126: =AL122*(1-AL124) -> 174949.93
B128: D&A (Depreciation & Amortization) | D128: =D94 -> 173 | E128: =E94 -> 194 | F128: =F94 -> 243 | G128: =G94 -> 305 | H128: =H94 -> 915 | J128: =J94 -> 480 | K128: =K94 -> 562 | L128: =L94 -> 476 | M128: =M94 -> 459 | N128: =N94 -> 1977 | P128: =P94 -> 1055 | Q128: =Q94 -> 1119 | R128: =R94 -> 1189 | S128: =S94 -> 1181 | T128: =T94 -> 4544 | V128: =V94 -> 1621 | W128: =W94 -> 1818 | X128: =X94 -> 1722.8441 | Y128: =Y94 -> 1756.5617 | Z128: =Z94 -> 6918.4059 | AB128: =AB94 -> 2042.8899 | AC128: =AC94 -> 2041.8711 | AD128: =AD94 -> 2040.8528 | AE128: =AE94 -> 2039.835 | AF128: =AF94 -> 8165.4487 | AH128: =AH94 -> 10273.293 | AJ128: =AJ94 -> 10247.595 | AL128: =AL94 -> 10221.972
B130: Stock-Based Compensation | D130: =D97 -> 0 | E130: =E97 -> 0 | F130: =F97 -> 0 | G130: =G97 -> 0 | H130: =H97 -> 0 | J130: =J97 -> 0 | K130: =K97 -> 0 | L130: =L97 -> 375 | M130: =M97 -> 353 | N130: =N97 -> 728 | P130: =P97 -> 1832 | Q130: =Q97 -> -2644 | R130: =R97 -> 0 | S130: =S97 -> 0 | T130: =T97 -> -812 | V130: =V97 -> 132 | W130: =W97 -> -135 | X130: =X97 -> 116.3092 | Y130: =Y97 -> 162.1788 | Z130: =Z97 -> 275.488 | AB130: =AB97 -> 151.70181 | AC130: =AC97 -> 151.70181 | AD130: =AD97 -> 151.70181 | AE130: =AE97 -> 151.70181 | AF130: =AF97 -> 606.80725 | AH130: =AH97 -> 699.15222 | AJ130: =AJ97 -> 738.3032 | AL130: =AL97 -> 800.33898
B132: Changes in Net Working Capital | D132: =D103 -> 0 | E132: =E103 -> 29884 | F132: =F103 -> 76198 | G132: =G103 -> 106698 | H132: =H103 -> 212780 | J132: =J103 -> -10870 | K132: =K103 -> 6900 | L132: =L103 -> 69635 | M132: =M103 -> -206051 | N132: =N103 -> -140386 | P132: =P103 -> -32437 | Q132: =Q103 -> 37 | R132: =R103 -> 94233 | S132: =S103 -> -7384 | T132: =T103 -> 54449 | V132: =V103 -> -19519 | W132: =W103 -> -80915 | X132: =X103 -> 10611.111 | Y132: =Y103 -> 14492.9 | Z132: =Z103 -> -75329.988 | AB132: =AB103 -> 19005.121 | AC132: =AC103 -> 833.52644 | AD132: =AD103 -> 815.4063 | AE132: =AE103 -> 11293.357 | AF132: =AF103 -> 31947.411 | AH132: =AH103 -> -52584.623 | AJ132: =AJ103 -> 14519.113 | AL132: =AL103 -> -11948.365
B134: Net CapEx | D134: =D106+D109 -> -63.727 | E134: =E106+E109 -> -56.269 | F134: =F106+F109 -> -270.741 | G134: =G106+G109 -> -213.108 | H134: =H106+H109 -> -603.845 | J134: =J106+J109 -> -27.851 | K134: =K106+K109 -> -42.243 | L134: =L106+L109 -> -63.719 | M134: =M106+M109 -> 124 | N134: =N106+N109 -> -9.813 | P134: =P106+P109 -> -26.808 | Q134: =Q106+Q109 -> -6.614 | R134: =R106+R109 -> -50.868 | S134: =S106+S109 -> 17.5 | T134: =T106+T109 -> -66.79 | V134: =V106+V109 -> -28.51 | W134: =W106+W109 -> -18.294 | X134: =X106+X109 -> -36.498698 | Y134: =Y106+Y109 -> -50.892922 | Z134: =Z106+Z109 -> -134.19562 | AB134: =AB106+AB109 -> -75.850906 | AC134: =AC106+AC109 -> -75.850906 | AD134: =AD106+AD109 -> -75.850906 | AE134: =AE106+AE109 -> -75.850906 | AF134: =AF106+AF109 -> -303.40362 | AH134: =AH106+AH109 -> -1048.7283 | AJ134: =AJ106+AJ109 -> -1107.4548 | AL134: =AL106+AL109 -> -1200.5085
B136: FCFF (Free Cash Flow to Firm) | D136: =D126+D94+D97+D103+D134 -> 25425.873 | E136: =E126+E94+E97+E103+E134 -> 58044.116 | F136: =F126+F94+F97+F103+F134 -> 92455.069 | G136: =G126+G94+G97+G103+G134 -> 136096.92 | H136: =H126+H94+H97+H103+H134 -> 340577.16 | J136: =J126+J94+J97+J103+J134 -> 13908.821 | K136: =K126+K94+K97+K103+K134 -> 34398.292 | L136: =L126+L94+L97+L103+L134 -> 122731.96 | M136: =M126+M94+M97+M103+M134 -> -216284.26 | N136: =N126+N94+N97+N103+N134 -> -61634.368 | P136: =P126+P94+P97+P103+P134 -> -9077.0314 | Q136: =Q126+Q94+Q97+Q103+Q134 -> 22166.696 | R136: =R126+R94+R97+R103+R134 -> 117501.73 | S136: =S126+S94+S97+S103+S134 -> 85685.3 | T136: =T126+T94+T97+T103+T134 -> 175059.24 | V136: =V126+V94+V97+V103+V134 -> 2632.8444 | W136: =W126+W94+W97+W103+W134 -> -55692.983 | X136: =X126+X128+X130+X132+X134 -> 41956.578 | Y136: =Y126+Y128+Y130+Y132+Y134 -> 58251.937 | Z136: =Z126+Z128+Z130+Z132+Z134 -> 47148.377 | AB136: =AB126+AB128+AB130+AB132+AB134 -> 51402.157 | AC136: =AC126+AC128+AC130+AC132+AC134 -> 33230.634 | AD136: =AD126+AD128+AD130+AD132+AD134 -> 33212.585 | AE136: =AE126+AE128+AE130+AE132+AE134 -> 43690.607 | AF136: =AF126+AF128+AF130+AF132+AF134 -> 161535.98 | AH136: =AH126+AH128+AH130+AH132+AH134 -> 111726.85 | AJ136: =AJ126+AJ128+AJ130+AJ132+AJ134 -> 186503.01 | AL136: =AL126+AL128+AL130+AL132+AL134 -> 172823.37
A138: x | B138: Valuation Summary
V139: =V$8 -> 2025 | W139: =X139 -> 0 | X139: =X$8 -> 0 | Y139: =X139 -> 0 | Z139: =X139 -> 0 | AB139: =AB$8 -> 2026 | AC139: =AD139 -> 0 | AD139: =AD$8 -> 0 | AE139: =AD139 -> 0 | AF139: =AD139 -> 0 | AH139: =AH$8 -> 2027 | AJ139: =AJ$8 -> 2028 | AL139: =AL$8 -> 2029
V140: Q1 | W140: Q2 | X140: Q3 | Y140: Q4 | Z140: FY | AB140: Q1 | AC140: Q2 | AD140: Q3 | AE140: Q4 | AF140: FY | AH140: FY | AJ140: FY | AL140: FY
B143: Discounted Cash Flows (DCF)
B146: Discount Period | X146: =YEARFRAC(TODAY(),Inputs!$D$18+92) -> 0.083333333 | Y146: =YEARFRAC(TODAY(),Inputs!$D$18+184) -> 0.16944444 | AB146: =YEARFRAC(TODAY(),Inputs!$D$17+365+90) -> 0.47222222 | AC146: =YEARFRAC(TODAY(),Inputs!$D$17+365+90+91) -> 0.71944444 | AD146: =YEARFRAC(TODAY(),Inputs!$D$17+365+90+91+92) -> 0.96944444 | AE146: =YEARFRAC(TODAY(),Inputs!$D$17+720) -> 1.1944444 | AH146: =YEARFRAC(TODAY(),Inputs!$D$17+730+365) -> 2.2222222 | AJ146: =YEARFRAC(TODAY(),Inputs!$D$17+730+731) -> 3.2222222 | AL146: =YEARFRAC(TODAY(),Inputs!$D$17+730+731+365) -> 4.2222222
B147: Mid-Quarter/Year Convention Discount Period | X147: =X146/2 -> 0.041666667 | Y147: =X146+(Y146-X146)/2 -> 0.12638889 | AB147: =Y146+(AB146-Y146)/2 -> 0.32083333 | AC147: =AB146+(AC146-AB146)/2 -> 0.59583333 | AD147: =AC146+(AD146-AC146)/2 -> 0.84444444 | AE147: =AD146+(AE146-AD146)/2 -> 1.0819444 | AH147: =AE146+(AH146-AE146)/2 -> 1.7083333 | AJ147: =AH146+(AJ146-AH146)/2 -> 2.7222222 | AL147: =AJ146+(AL146-AJ146)/2 -> 3.7222222
B149: Rolling WACC (Weighted Average Cost of Capital) | X149: =WACC!$D$39+Sensitivity!U41 -> 0.11163883 | Y149: =WACC!$D$39+Sensitivity!U41 -> 0.11163883 | AB149: =WACC!$E$39+Sensitivity!U41 -> 0.10047495 | AC149: =WACC!$E$39+Sensitivity!U41 -> 0.10047495 | AD149: =WACC!$E$39+Sensitivity!U41 -> 0.10047495 | AE149: =WACC!$E$39+Sensitivity!U41 -> 0.10047495 | AH149: =WACC!$F$39+Sensitivity!U41 -> 0.10278022 | AJ149: =WACC!$G$39+Sensitivity!U41 -> 0.10514357 | AL149: =WACC!$H$39+Sensitivity!U41 -> 0.1046239
B150: Cumulative Discount Factor | X150: =(1+X149)^X147 -> 1.0044195 | Y150: =((1+X149)^X147)*((1+Y149)^Y147) -> 1.0179453 | AB150: =((1+X149)^X147)*((1+Y149)^Y147)*((1+AB149)^AB147) -> 1.0496989 | AC150: =((1+X149)^X147)*((1+Y149)^Y147)*((1+AB149)^AB147)*((1+AC149)^AC147) -> 1.1113212 | AD150: =((1+X149)^X147)*((1+Y149)^Y147)*((1+AB149)^AB147)*((1+AC149)^AC147)*((1+AD149)^AD147) -> 1.204902 | AE150: =((1+X149)^X147)*((1+Y149)^Y147)*((1+AB149)^AB147)*((1+AC149)^AC147)*((1+AD149)^AD147)*((1+AE149)^AE147) -> 1.3364083 | AH150: =((1+X149)^X147)*((1+Y149)^Y147)*((1+AB149)^AB147)*((1+AC149)^AC147)*((1+AD149)^AD147)*((1+AE149)^AE147)*((1+AH149)^AH147) -> 1.5795177 | AJ150: =((1+X149)^X147)*((1+Y149)^Y147)*((1+AB149)^AB147)*((1+AC149)^AC147)*((1+AD149)^AD147)*((1+AE149)^AE147)*((1+AH149)^AH147)*((1+AJ149)^AJ147) -> 2.0735754 | AL150: =((1+X149)^X147)*((1+Y149)^Y147)*((1+AB149)^AB147)*((1+AC149)^AC147)*((1+AD149)^AD147)*((1+AE149)^AE147)*((1+AH149)^AH147)*((1+AJ149)^AJ147)*((1+AL149)^AL147) -> 3.0031261
B152: Present Value of FCFF | X152: =X136/X150*(Inputs!$D$17-92-TODAY())/92 -> -170720.21 | Y152: =Y136/Y150 -> 57225.015 | AB152: =AB136/AB150 -> 48968.476 | AC152: =AC136/AC150 -> 29901.916 | AD152: =AD136/AD150 -> 27564.552 | AE152: =AE136/AE150 -> 32692.559 | AH152: =AH136/AH150 -> 70734.789 | AJ152: =AJ136/AJ150 -> 89942.716 | AL152: =AL136/AL150 -> 57547.822
B154: Terminal Value
Q157: Preferred Method: | R157: Revenue Exit | V157: EBITDA Exit Multiple | AB157: Revenue Exit Multiple | AH157: Gordon's Growth Model
V159: Current EV/EBITDA | Z159: 31 | AB159: Current EV/Sales | AF159: 15.6 | AH159: Current Growth Rate | AL159: =+AL136/AJ136-1 -> -0.073348097
V160: Exit EV/EBITDA | Z160: 44 | AB160: Exit EV/Sales | AF160: 20 | AH160: Terminal Growth Rate | AL160: 0.03
R161: =R157 -> Revenue Exit | V161: Terminal Value | Z161: =(Z160+Sensitivity!U43)*(AL122+AL128) -> 7923355.9 | AB161: Terminal Value | AF161: =(AF160+Sensitivity!U44)*(AL31) -> 8003389.8 | AH161: Terminal Value | AL161: =AL136*(1+AL160+Sensitivity!U42)/(AL149-AL160-Sensitivity!U42) -> 2385402.9 | AN161: 8000000
R162: =IF($R$161="Revenue Exit",$AF$171,IF($R$161="EBITDA Exit",$Z$171,$AL$171)) -> -0.30525663 | V162: PV of Terminal Value | Z162: =Z161/AL150 -> 2638369.4 | AB162: PV of Terminal Value | AF162: =AF161/AL150 -> 2665019.6 | AH162: PV of Terminal Value | AL162: =AL161/AL150 -> 794306.62
R163: =1-R162 -> 1.3052566 | V163: Implied Enterprise Value | Z163: =Z162+SUM(V152:AL152) -> 2882227 | AB163: Implied Enterprise Value | AF163: =AF162+SUM(V152:AL152) -> 2908877.2 | AH163: Implied Enterprise Value | AL163: =AL162+SUM(V152:AL152) -> 1038164.3
R164: =IF(R162>0,"Upside","Downside") -> Downside | V164: (-) Net Debt | Z164: =BS!AI45+BS!AI44+BS!AI39+BS!AI38-BS!AI15 -> 1685831 | AB164: (-) Net Debt | AF164: =BS!AI45+BS!AI44+BS!AI39+BS!AI38-BS!AI15 -> 1685831 | AH164: (-) Net Debt | AL164: =BS!AI45+BS!AI44+BS!AI39+BS!AI38-BS!AI15 -> 1685831
V165: (-) Preferred Stock Market Cap | Z165: =Inputs!U63 -> 0 | AB165: (-) Preferred Stock Market Cap | AF165: =Inputs!U63 -> 0 | AH165: (-) Preferred Stock Market Cap | AL165: =Inputs!U63 -> 0
...

Sheet Sensitivity
B7: Monte-Carlo Simulations | R7: Tornado Chart – Effect on Price Target
AD28: {=_xlfn.SORTBY(R38:Z44,Z38:Z44,1)} -> COGS Margin | AE28: 0 | AF28: 0.02 | AG28: 0 | AH28: 3.27 | AI28: 3.32 | AJ28: -0.03 | AK28: 0.02 | AL28: 0.03
AD29: Capex Intensity | AE29: 0 | AF29: 0.01 | AG29: 0 | AH29: 3.24 | AI29: 3.36 | AJ29: -0.06 | AK29: 0.06 | AL29: 0.06
AD30: SG&A Margin | AE30: 0 | AF30: 0.01 | AG30: 0 | AH30: 2.98 | AI30: 3.62 | AJ30: -0.32 | AK30: 0.32 | AL30: 0.32
AD31: EBITDA Exit | AE31: 0 | AF31: 1.5 | AG31: 0 | AH31: 2.19 | AI31: 3.9 | AJ31: -1.11 | AK31: 0.6 | AL31: 1.11
R32: Reference Price Target | V32: Base Price Target | Z32: Reference | AD32: Revenue Exit | AE32: 0 | AF32: 1 | AG32: 0 | AH32: 2.03 | AI32: 4.56 | AJ32: -1.27 | AK32: 1.26 | AL32: 1.27
R33: Gordon PT | T33: =+FCFF!AL169 -> -15.041035 | V33: Base Gordon PT | Z33: Revenue | AD33: WACC | AE33: 0 | AF33: 0.005 | AG33: 0 | AH33: 1.95 | AI33: 4.72 | AJ33: -1.35 | AK33: 1.42 | AL33: 1.42
R34: EBITDA PT | T34: =+FCFF!Z169 -> 2.7374117 | V34: Base EBITDA PT | X34: 3.04 | AD34: Terminal g | AE34: 0 | AF34: 0.005 | AG34: 0 | AH34: 0 | AI34: 0 | AJ34: -3.3 | AK34: -3.3 | AL34: 3.3
R35: Revenue PT | T35: =FCFF!AF169 -> 2.9943439 | V35: Base Revenue PT | X35: 3.3
T37: Δ | U37: Δ Applied | V37: PT Low | W37: PT High | X37: Δ Low | Y37: Δ High | Z37: Max
R38: Capex Intensity | T38: 0.01 | V38: 3.24 | W38: 3.36 | X38: {=+V38-_xlfn.IFS($Z$33="EBITDA",$X$34,$Z$33="Revenue",$X$35,$Z$33="Gordon",$X$33)} -> -0.06 | Y38: {=+W38-_xlfn.IFS($Z$33="EBITDA",$X$34,$Z$33="Revenue",$X$35,$Z$33="Gordon",$X$33)} -> 0.06 | Z38: =MAX(ABS(X38),ABS(Y38)) -> 0.06
R39: COGS Margin | T39: 0.02 | V39: 3.27 | W39: 3.32 | X39: {=+V39-_xlfn.IFS($Z$33="EBITDA",$X$34,$Z$33="Revenue",$X$35,$Z$33="Gordon",$X$33)} -> -0.03 | Y39: {=+W39-_xlfn.IFS($Z$33="EBITDA",$X$34,$Z$33="Revenue",$X$35,$Z$33="Gordon",$X$33)} -> 0.02 | Z39: =MAX(ABS(X39),ABS(Y39)) -> 0.03
C40: Historical VaR (based on actual past returns): | R40: SG&A Margin | T40: 0.01 | V40: 2.98 | W40: 3.62 | X40: {=+V40-_xlfn.IFS($Z$33="EBITDA",$X$34,$Z$33="Revenue",$X$35,$Z$33="Gordon",$X$33)} -> -0.32 | Y40: {=+W40-_xlfn.IFS($Z$33="EBITDA",$X$34,$Z$33="Revenue",$X$35,$Z$33="Gordon",$X$33)} -> 0.32 | Z40: =MAX(ABS(X40),ABS(Y40)) -> 0.32
C41: 95% confidence: On 95% of trading days, HBR stock won't lose more than 4.29% in a single day | R41: WACC | T41: 0.005 | V41: 1.95 | W41: 4.72 | X41: {=+V41-_xlfn.IFS($Z$33="EBITDA",$X$34,$Z$33="Revenue",$X$35,$Z$33="Gordon",$X$33)} -> -1.35 | Y41: {=+W41-_xlfn.IFS($Z$33="EBITDA",$X$34,$Z$33="Revenue",$X$35,$Z$33="Gordon",$X$33)} -> 1.42 | Z41: =MAX(ABS(X41),ABS(Y41)) -> 1.42
C42: 99% confidence: On 99% of trading days, it won't lose more than 6.57% in a single day | R42: Terminal g | T42: 0.005 | X42: {=+V42-_xlfn.IFS($Z$33="EBITDA",$X$34,$Z$33="Revenue",$X$35,$Z$33="Gordon",$X$33)} -> -3.3 | Y42: {=+W42-_xlfn.IFS($Z$33="EBITDA",$X$34,$Z$33="Revenue",$X$35,$Z$33="Gordon",$X$33)} -> -3.3 | Z42: =MAX(ABS(X42),ABS(Y42)) -> 3.3
C43: Parametric VaR (assumes normal distribution): | R43: EBITDA Exit | T43: 1.5 | V43: 2.19 | W43: 3.9 | X43: {=+V43-_xlfn.IFS($Z$33="EBITDA",$X$34,$Z$33="Revenue",$X$35,$Z$33="Gordon",$X$33)} -> -1.11 | Y43: {=+W43-_xlfn.IFS($Z$33="EBITDA",$X$34,$Z$33="Revenue",$X$35,$Z$33="Gordon",$X$33)} -> 0.6 | Z43: =MAX(ABS(X43),ABS(Y43)) -> 1.11
C44: 95% confidence: Based on average volatility patterns, daily losses should stay below 4.84% on 95% of days | R44: Revenue Exit | T44: 1 | V44: 2.03 | W44: 4.56 | X44: {=+V44-_xlfn.IFS($Z$33="EBITDA",$X$34,$Z$33="Revenue",$X$35,$Z$33="Gordon",$X$33)} -> -1.27 | Y44: {=+W44-_xlfn.IFS($Z$33="EBITDA",$X$34,$Z$33="Revenue",$X$35,$Z$33="Gordon",$X$33)} -> 1.26 | Z44: =MAX(ABS(X44),ABS(Y44)) -> 1.27
C45: 99% confidence: Daily losses should stay below 6.88% on 99% of days
C46: Monte Carlo VaR (simulated future scenarios over 1 year):
C47: 95% confidence: Over a one-year holding period, there's a 95% chance you won't lose more than 52.71%
C48: 99% confidence: Over a one-year holding period, there's a 99% chance you won't lose more than 66.25%

Sheet IS
B7: Income Statement | D7: 2020 | E7: 2020 | F7: 2020 | G7: 2020 | H7: 2020 | J7: 2021 | K7: 2021 | L7: 2021 | M7: 2021 | N7: 2021 | P7: 2022 | Q7: 2022 | R7: 2022 | S7: 2022 | T7: 2022 | V7: 2023 | W7: 2023 | X7: 2023 | Y7: 2023 | Z7: 2023 | AB7: 2024 | AC7: 2024 | AD7: 2024 | AE7: 2024 | AF7: 2024 | AH7: 2025 | AI7: 2025 | AJ7: 2025 | AK7: 2025 | AL7: 2025 | AN7: 2025 | AO7: 2025 | AP7: 2025 | AQ7: 2025 | AR7: 2025
D8: 2020 | J8: 2021 | P8: 2022 | V8: 2023 | AB8: 2024 | AH8: 2025 | AN8: 2026 | AT8: 2027 | AV8: 2028 | AX8: 2029
D9: Q1 | E9: Q2 | F9: Q3 | G9: Q4 | H9: FY | J9: Q1 | K9: Q2 | L9: Q3 | M9: Q4 | N9: FY | P9: Q1 | Q9: Q2 | R9: Q3 | S9: Q4 | T9: FY | V9: Q1 | W9: Q2 | X9: Q3 | Y9: Q4 | Z9: FY | AB9: Q1 | AC9: Q2 | AD9: Q3 | AE9: Q4 | AF9: FY | AH9: Q1 | AI9: Q2 | AJ9: Q3 | AK9: Q4 | AL9: FY | AN9: Q1 | AO9: Q2 | AP9: Q3 | AQ9: Q4 | AR9: FY | AT9: FY | AV9: FY | AX9: FY
B12: Revenue:
B13: ComVem | H13: 12513 | N13: 11799 | P13: 3799 | Q13: 4345 | R13: 4263 | S13: 4845 | T13: 17252 | V13: 5383 | W13: 6445 | X13: 4847 | Y13: 5228 | Z13: 21903 | AB13: 5301 | AC13: 5429 | AD13: 6314 | AE13: 6552 | AF13: 23596 | AH13: =0.1329*AH18 -> 6092.9334 | AI13: =0.1329*AI18 -> 8505.2013 | AJ13: =0.14*AJ18 -> 8141.644 | AK13: =0.145*AK18 -> 11757.963 | AL13: =SUM(AH13:AK13) -> 34497.742 | AM13: =0.1329*AM18 -> 0 | AN13: =0.155*AN18 -> 9967.4706 | AO13: =0.165*AO18 -> 10610.533 | AP13: =0.175*AP18 -> 11428.596 | AQ13: =0.18*AQ18 -> 11395.127 | AR13: =SUM(AN13:AQ13) -> 43401.727 | AS13: =(0.1329-0.01)*AS18 -> 0 | AT13: =0.19*AT18 -> 53812.75 | AU13: =(0.1329-0.01)*AU18 -> 0 | AV13: =0.2*AV18 -> 62636.8 | AW13: =(0.1329-0.01)*AW18 -> 0 | AX13: =0.21*AX18 -> 71316.84
B14: HBR 3A | H14: 24451 | N14: 8417 | P14: 7737 | Q14: 7647 | R14: 7466 | S14: 7646 | T14: 30496 | U14: 7690 | V14: 7690 | W14: 7832 | X14: 7788 | Y14: 7804 | Z14: 31114 | AB14: 7785 | AC14: 7733 | AD14: 8071 | AE14: 8466 | AF14: 32055 | AH14: =0.1902*AH18 -> 8719.9092 | AI14: =0.1902*AI18 -> 12172.229 | AJ14: =0.195*AJ18 -> 11340.147 | AK14: =0.2*AK18 -> 16217.88 | AL14: =SUM(AH14:AK14) -> 48450.166 | AM14: =0.1902*AM18 -> 0 | AN14: =0.21*AN18 -> 13504.315 | AO14: =0.22*AO18 -> 14147.378 | AP14: =0.23*AP18 -> 15020.44 | AQ14: =(0.235*AQ18) -> 14876.972 | AR14: =SUM(AN14:AQ14) -> 57549.104 | AS14: =(0.1902-0.04)*AS18 -> 0 | AT14: =0.245*AT18 -> 69390.125 | AU14: =(0.1902-0.04)*AU18 -> 0 | AV14: =0.25*AV18 -> 78296 | AW14: =(0.1902-0.04)*AW18 -> 0 | AX14: =0.255*AX18 -> 86599.02
B15: HBR Malls | H15: 31749 | N15: 37328 | P15: 15286 | Q15: 12965 | R15: 13301 | S15: 14842 | T15: 56394 | V15: 12871 | W15: 12671 | X15: 14359 | Y15: 15805 | Z15: 55706 | AB15: 14831 | AC15: 14262 | AD15: 14908 | AE15: 17113 | AF15: 61114 | AH15: =0.3596*AH18 -> 16486.222 | AI15: =0.3596*AI18 -> 23013.321 | AJ15: =0.355*AJ18 -> 20644.883 | AK15: =0.35*AK18 -> 28381.29 | AL15: =SUM(AH15:AK15) -> 88525.716 | AM15: =0.3596*AM18 -> 0 | AN15: =0.345*AN18 -> 22185.66 | AO15: =0.34*AO18 -> 21864.129 | AP15: =0.335*AP18 -> 21877.598 | AQ15: =0.33*AQ18 -> 20891.066 | AR15: =SUM(AN15:AQ15) -> 86818.453 | AS15: =(0.3596+0.06)*AS18 -> 0 | AT15: =0.325*AT18 -> 92048.125 | AU15: =(0.3596+0.06)*AU18 -> 0 | AV15: =0.32*AV18 -> 100218.88 | AW15: =(0.3596+0.06)*AW18 -> 0 | AX15: =0.315*AX18 -> 106975.26
B16: HBR Opportunities | H16: 8620 | N16: 30358 | P16: 9452 | Q16: 10696 | R16: 10820 | S16: 11947 | T16: 42915 | V16: 11741 | W16: 12755 | X16: 13022 | Y16: 12095 | Z16: 49613 | AB16: 11281 | AC16: 13239 | AD16: 13432 | AE16: 13363 | AF16: 51315 | AH16: =0.2961*AH18 -> 13575.001 | AI16: =0.2961*AI18 -> 18949.512 | AJ16: =0.28*AJ18 -> 16283.288 | AK16: =0.285*AK18 -> 23110.479 | AL16: =SUM(AH16:AK16) -> 71918.279 | AM16: =0.2961*AM18 -> 0 | AN16: =0.27*AN18 -> 17362.691 | AO16: =0.26*AO18 -> 16719.628 | AP16: =0.25*AP18 -> 16326.565 | AQ16: =0.245*AQ18 -> 15510.034 | AR16: =SUM(AN16:AQ16) -> 65918.918 | AS16: =(0.2961-0.01)*AS18 -> 0 | AT16: =0.23*AT18 -> 65141.75 | AU16: =(0.2961-0.01)*AU18 -> 0 | AV16: =0.22*AV18 -> 68900.48 | AW16: =(0.2961-0.01)*AW18 -> 0 | AX16: =0.21*AX18 -> 71316.84 | AY16: =(0.2961-0.01)*AY18 -> 0
B17: Other income and holding activities | H17: 0 | N17: 0 | P17: 1139 | Q17: 1164 | R17: 1034 | S17: 1046 | T17: 4383 | V17: 1037 | W17: 980 | X17: 995 | Y17: 997 | Z17: 4009 | AB17: 809 | AC17: 1187 | AD17: 1001 | AE17: 1099 | AF17: 4096 | AH17: =0.0212*AH18 -> 971.9352 | AI17: =0.0212*AI18 -> 1356.7364 | AJ17: =0.02*AJ18 -> 1163.092 | AK17: =0.02*AK18 -> 1621.788 | AL17: =SUM(AH17:AK17) -> 5113.5516 | AM17: =0.0212*AM18 -> 0 | AN17: =0.02*AN18 -> 1286.1252 | AO17: =0.02*AO18 -> 1286.1252 | AP17: =0.02*AP18 -> 1306.1252 | AQ17: =0.02*AQ18 -> 1266.1252 | AR17: =SUM(AN17:AQ17) -> 5144.5009 | AS17: =0.02*AS18 -> 0 | AT17: =0.019*AT18 -> 5381.275 | AU17: =0.02*AU18 -> 0 | AV17: =0.019*AV18 -> 5950.496 | AW17: =0.02*AW18 -> 0 | AX17: =0.019*AX18 -> 6452.476
B18: Total revenue | D18: 19810 | E18: 18309 | F18: 20789 | G18: 21861 | H18: 77333 | J18: 19127 | K18: 17498 | L18: 22105 | M18: 47678 | N18: 87902 | P18: 34134 | Q18: 34302 | R18: 34378 | S18: 38052 | T18: 140866 | V18: 52729 | W18: 39112 | X18: 38430 | Y18: 23111 | Z18: 153382 | AB18: 37691 | AC18: 39774 | AD18: 41539 | AE18: 43978 | AF18: 162982 | AH18: 45846 | AI18: 63997 | AJ18: 58154.6 | AK18: 81089.4 | AL18: 249087 | AN18: 64306.262 | AO18: 64306.262 | AP18: 65306.262 | AQ18: 63306.262 | AR18: 257225 | AT18: 283225 | AV18: 313184 | AX18: 339604
A20: x | B20: Cost of revenue:
B21: Cost of goods and services | D21: 0 | E21: 0 | F21: 0 | G21: 0 | H21: 0 | J21: 0 | K21: 0 | L21: 0 | M21: 0 | N21: 0 | P21: 7004 | Q21: 4944 | R21: 4459 | S21: 5892 | T21: =+SUM(P21:S21) -> 22299 | V21: 5907 | W21: 6864 | X21: 8319 | Y21: 8013 | Z21: =+SUM(V21:Y21) -> 29103 | AB21: 7197 | AC21: 8176 | AD21: 8130 | AE21: 9500 | AF21: =SUM(AB21:AE21) -> 33003 | AH21: 15902 | AI21: 27846 | AJ21: 13885.132 | AK21: 14700.41 | AL21: 72333.543 | AN21: 15660.996 | AO21: 15974.216 | AP21: 16547.077 | AQ21: 16361.13 | AR21: 64543.42 | AT21: 73646.314 | AV21: 81427.894 | AX21: 88297.126
B22: Depreciation & amortization | D22: 0 | E22: 0 | F22: 0 | G22: 0 | H22: 0 | J22: 0 | K22: 0 | L22: 0 | M22: 0 | N22: 0 | P22: 0 | Q22: 0 | R22: 0 | S22: 0 | T22: 0 | V22: 0 | W22: 0 | X22: 0 | Y22: 0 | Z22: 0 | AB22: 0 | AC22: 0 | AD22: 0 | AE22: 0 | AF22: 0 | AH22: 0 | AI22: 0
B23: Total cost of revenue | D23: 0 | E23: 0 | F23: 0 | G23: 0 | H23: 0 | J23: 0 | K23: 0 | L23: 0 | M23: 0 | N23: 0 | P23: 0 | Q23: 0 | R23: 0 | S23: 0 | T23: 0 | V23: 0 | W23: 0 | X23: 0 | Y23: 0 | Z23: 0 | AB23: 0 | AC23: 0 | AD23: 0 | AE23: 0 | AF23: 0 | AH23: 0 | AI23: 0
B24: Gross margin | D24: 0 | E24: 0 | F24: 0 | G24: 0 | H24: 0 | J24: 0 | K24: 0 | L24: 0 | M24: 0 | N24: 0 | P24: =+(P18-P21) -> 27130 | Q24: =+(Q18-Q21) -> 29358 | R24: =+(R18-R21) -> 29919 | S24: =+(S18-S21) -> 32160 | T24: =+(T18-T21) -> 118567 | U24: =+(U18-U21) -> 0 | V24: =+(V18-V21) -> 46822 | W24: =+(W18-W21) -> 32248 | ... AL24: =+(AL18-AL21) -> 176753.46 | AN24: =+(AN18-AN21)/AN18 -> 0.75646235 | AO24: =+(AO18-AO21)/AO18 -> 0.75159159 | AP24: =+(AP18-AP21)/AP18 -> 0.74662342 | AQ24: =+(AQ18-AQ21)/AQ18 -> 0.74155589 | AR24: =+(AR18-AR21)/AR18 -> 0.74907797 | AT24: =+(AT18-AT21)/AT18 -> 0.73997241 | AV24: =+(AV18-AV21)/AV18 -> 0.73999983 | AX24: =+(AX18-AX21)/AX18 -> 0.73999975
A26: x | B26: Operating expenses:
B27: Selling, general and administrative | D27: 3583 | E27: 3556 | F27: 10205 | G27: 9082 | H27: 26426 | J27: 4718 | K27: 9186 | L27: 7218 | M27: 8249 | N27: 29371 | P27: 9379 | Q27: 8273 | R27: 8676 | S27: 7663 | T27: 33991 | V27: 10277 | W27: 11727 | X27: 10777 | Y27: 12577 | Z27: 45358 | AB27: 12424 | AC27: 10799 | AD27: 11389 | AE27: 12763 | AF27: 47375 | AH27: 6958 | AI27: 12627 | AJ27: 13339.948 | AK27: 14123.216 | AL27: 47048.164 | AN27: 14726.134 | AO27: 14726.134 | AP27: 14955.134 | AQ27: 14497.134 | AR27: 58904.536 | AT27: 64865.408 | AV27: 71719.184 | AX27: 77769.392
B28: Depreciation and amortization | D28: 118 | E28: 379 | F28: 134 | G28: 135 | H28: 766 | J28: 144 | K28: 157 | L28: 166 | M28: 155 | N28: 622 | P28: 173 | Q28: 194 | R28: 243 | S28: 305 | T28: 915 | V28: 480 | W28: 562 | X28: 476 | Y28: 459 | Z28: 1977 | AB28: 1055 | AC28: 1119 | AD28: 0 | AE28: 0 | AF28: 2174 | AH28: 1621 | AI28: 1818
B29: Research and development | D29: 0 | E29: 0 | F29: 0 | G29: 0 | J29: 0 | K29: 0 | L29: 0 | M29: 0 | N29: 0 | P29: 0 | Q29: 0 | R29: 0 | T29: 0 | V29: 0 | W29: 0 | X29: 0 | Y29: 0 | Z29: 0 | AB29: 0 | AC29: 0 | AD29: 0 | AE29: 0 | AF29: 0 | AH29: 0 | AI29: 0
B30: Other operating expenses | D30: -38 | E30: 2079 | F30: -7985 | G30: -39765 | H30: =+SUM(D30:G30) -> -45709 | J30: -1247 | K30: -4107 | L30: -4499 | M30: -257757 | N30: =+SUM(J30:M30) -> -267610 | P30: -2085 | Q30: -3550 | R30: -3531 | S30: =-162658+159134 -> -3524 | T30: =+SUM(P30:S30) -> -12690 | V30: -4370 | W30: -4863 | X30: -2275 | Y30: =-379967+388175 -> 8208 | Z30: =+SUM(V30:Y30) -> -3300 | AB30: -5118 | AC30: 1308 | AD30: -1759 | AE30: =-197251+192995 -> -4256 | AF30: =+SUM(AB30:AE30) -> -9825 | AH30: 11377 | AI30: 15219
B31: Total operating expenses | D31: 3663 | E31: 6014 | F31: 2354 | G31: -30548 | H31: =+SUM(D31:G31) -> -18517 | J31: 3615 | K31: 5236 | L31: 2885 | M31: -249353 | N31: =+SUM(J31:M31) -> -237617 | P31: 7467 | Q31: 4917 | R31: 5388 | S31: -154690 | T31: =+SUM(P31:S31) -> -136918 | V31: 6387 | W31: 7426 | X31: 8978 | Y31: -366931 | Z31: =+SUM(V31:Y31) -> -344140 | AB31: 8361 | AC31: 13226 | AD31: 9630 | AE31: -184488 | AF31: =+SUM(AB31:AE31) -> -153271 | AH31: 19956 | AI31: 29664
B32: Other operating income | D32: 303 | E32: 0 | F32: 3133 | G32: 0 | H32: =+SUM(D32:G32) -> 3436 | J32: 0 | K32: 0 | L32: 751 | M32: 17755 | N32: =+SUM(J32:M32) -> 18506 | P32: 1685 | Q32: 2914 | R32: 647 | S32: 11768 | T32: =+SUM(P32:S32) -> 17014 | V32: 15752 | W32: 6784 | X32: 59 | Y32: 9924 | Z32: =+SUM(V32:Y32) -> 32519 | AB32: 259 | AC32: 7719 | AD32: 7988 | AE32: 0 | AF32: =+SUM(AB32:AE32) -> 15966 | AH32: 233 | AI32: 23087
B33: Operating income | D33: 12564 | E33: 8739 | F33: 8230 | G33: 5416 | H33: 34949 | J33: 10794 | K33: 3076 | L33: 12002 | M33: 35743 | N33: 61615 | P33: 17288 | Q33: 21112 | R33: 20961 | S33: 25367 | T33: 84728 | V33: 36065 | W33: 19959 | X33: 18675 | Y33: -10710 | Z33: 63989 | AB33: 16906 | AC33: 19586 | AD33: 19162 | AE33: 37759 | AF33: =+SUM(AB33:AE33) -> 93413 | AH33: 18699 | AI33: 21706
B34: EBITDA | D34: =+D33++D28 -> 12682 | E34: =+E33++E28 -> 9118 | F34: =+F33++F28 -> 8364 | G34: =+G33++G28 -> 5551 | H34: =+H33++H28 -> 35715 | J34: =+J33++J28 -> 10938 | K34: =+K33++K28 -> 3233 | L34: =+L33++L28 -> 12168 | M34: =+M33++M28 -> 35898 | N34: =+N33++N28 -> 62237 | P34: =+P33++P28 -> 17461 | Q34: =+Q33++Q28 -> 21306 | R34: =+R33++R28 -> 21204 | S34: =+S33++S28 -> 25672 | T34: =+T33++T28 -> 85643 | V34: =+V33++V28 -> 36545 | W34: =+W33++W28 -> 20521 | X34: =+X33++X28 -> 19151 | Y34: =+Y33++Y28 -> -10251 | Z34: =+Z33++Z28 -> 65966 | AB34: =+AB33++AB28 -> 17961 | AC34: =+AC33++AC28 -> 20705 | AD34: =+AD33++AD28 -> 19162 | AE34: =+AE33++AE28 -> 37759 | AF34: =+SUM(AB34:AE34) -> 95587 | AH34: =+AH33++AH28 -> 20320 | AI34: =+AI33++AI28 -> 23524 | AJ34: =+AJ33++AJ28 -> 0 | AK34: =+AK33++AK28 -> 0 | AL34: =+AL33++AL28 -> 0 | AN34: =+AN33++AN28 -> 0 | AO34: =+AO33++AO28 -> 0 | AP34: =+AP33++AP28 -> 0 | AQ34: =+AQ33++AQ28 -> 0 | AR34: =+AR33++AR28 -> 0 | AT34: =+AT33++AT28 -> 0 | AV34: =+AV33++AV28 -> 0 | AX34: =+AX33++AX28 -> 0
A35: x | B35: Non-operating (income) loss:
B36: Interest expense | D36: 20364 | E36: 13575 | F36: 14419 | G36: 22627 | H36: 70985 | J36: 25392 | K36: 24138 | L36: 28016 | M36: 36303 | N36: 113849 | P36: 26752 | Q36: 32929 | R36: 24021 | S36: 31943 | T36: =+SUM(P36:S36) -> 115645 | V36: 35517 | W36: 32996 | X36: 26290 | Y36: 27880 | Z36: 122683 | AB36: 31922 | AC36: 36616 | AD36: 36346 | AE36: 38914 | AF36: 143798 | AH36: 41955 | AI36: 51975
B37: Interest income | D37: 0 | E37: 0 | F37: 0 | G37: 0 | H37: 0 | J37: 0 | K37: 0 | L37: 0 | M37: 0 | N37: 0 | P37: 0 | Q37: 0 | R37: 0 | S37: 0 | V37: 0 | W37: 0 | X37: 0 | Y37: 0 | Z37: 0 | AB37: 0 | AC37: 0 | AD37: 0 | AE37: 0 | AF37: 0 | AH37: 0 | AI37: 0
A38: x | B38: Net interest (income) expense | D38: 20364 | E38: 13575 | F38: 14419 | G38: 22627 | H38: 70985 | J38: 25392 | K38: 24138 | L38: 28016 | M38: 36303 | N38: 113849 | P38: 26752 | Q38: 32929 | R38: 24021 | S38: 31943 | T38: =+SUM(P38:S38) -> 115645 | V38: 35517 | W38: 32996 | X38: 26290 | Y38: 27880 | Z38: 122683 | AB38: 31922 | AC38: 36616 | AD38: 36346 | AE38: 38914 | AF38: 143798 | AH38: 41955 | AI38: 51975
B39: Foreign exchange (gains) losses | D39: 0 | E39: 0 | F39: 0 | G39: 0 | H39: 0 | J39: 0 | K39: 0 | L39: 0 | M39: 0 | N39: 0 | P39: 0 | Q39: 0 | R39: 0 | S39: 0 | T39: 0 | V39: 0 | W39: 0 | X39: 0 | Y39: 0 | Z39: 0 | AB39: 0 | AC39: 0 | AD39: 0 | AE39: 0 | AF39: 0 | AH39: 0 | AI39: 0
B40: Other non-operating (income) expenses | D40: -25514 | E40: 19256 | F40: -15955 | G40: 6879 | H40: -15334 | J40: -257 | K40: 1582 | L40: -7562 | M40: -3307 | N40: -9544 | P40: -6725 | Q40: -7992 | R40: -10102 | S40: 5837 | T40: =+SUM(P40:S40) -> -18982 | V40: -7471 | W40: -7029 | X40: -6097 | Y40: 13227 | Z40: -7370 | AB40: -4041 | AC40: -5683 | AD40: -4016 | AE40: 713 | AF40: -13027 | AH40: 1963 | AI40: -2505
B41: Total non-operating expenses | D41: -5150 | E41: 32831 | F41: -1536 | G41: 29506 | H41: 55651 | J41: 25135 | K41: 25720 | L41: 20454 | M41: 32996 | N41: 104305 | P41: 20027 | Q41: 24937 | R41: 13919 | S41: 37780 | T41: 96663 | V41: 28046 | W41: 25967 | X41: 20193 | Y41: 41107 | Z41: 115313 | AB41: 27881 | AC41: 30933 | AD41: 32330 | AE41: 39627 | AF41: 130771 | AH41: 43918 | AI41: 49470
B42: Pre-tax income | D42: 17714 | E42: -24092 | F42: 9766 | G42: -24090 | H42: -20702 | J42: -14341 | K42: -22644 | L42: -8452 | M42: 2747 | N42: -42690 | P42: -2739 | Q42: -3825 | R42: 7042 | S42: -12413 | T42: -11935 | V42: 8019 | W42: -6008 | X42: -1518 | Y42: -51817 | Z42: -51324 | AB42: -10975 | AC42: -11347 | AD42: -13168 | AE42: -1868 | AF42: =+SUM(AB42:AE42) -> -37358 | AH42: -25219 | AI42: -27764
A44: x | B44: Tax & net income:
B45: Income tax expenses (benefits) | D45: 240 | E45: 540 | F45: 604 | G45: 85 | H45: =+SUM(D45:G45) -> 1469 | J45: 247 | K45: 286 | L45: 458 | M45: 1167 | N45: =+SUM(J45:M45) -> 2158 | P45: 1272 | Q45: 1252 | R45: 1571 | S45: 1928 | T45: =+SUM(P45:S45) -> 6023 | V45: 2610 | W45: 2113 | X45: 2734 | Y45: 2222 | Z45: =+SUM(V45:Y45) -> 9679 | AB45: 2333 | AC45: 2361 | AD45: 2040 | AE45: 2677 | AF45: =+SUM(AB45:AE45) -> 9411 | AH45: 2331 | AI45: 2368
B46: Net extraordinary losses (gains) | D46: 0 | E46: 0 | F46: 0 | G46: 0 | H46: 0 | J46: 0 | K46: 0 | L46: 0 | M46: 0 | N46: 0 | P46: 0 | Q46: 0 | R46: 0 | S46: 0 | T46: 0 | V46: 0 | W46: 0 | X46: 0 | Y46: 0 | Z46: 0 | AB46: 0 | AC46: 0 | AD46: 0 | AE46: 0 | AF46: 0 | AH46: 0 | AI46: 0
B47: Net income including minority interest | D47: 18270 | E47: -25036 | F47: 9077 | G47: -54729.26 | H47: -52418.26 | J47: -9722 | K47: -18663 | L47: -4410 | M47: 46268.26 | N47: 13473.26 | P47: -4007 | Q47: -5081 | R47: 5471 | S47: 19072.56 | T47: 15455.56 | V47: 5409 | W47: -8121 | X47: -4252 | Y47: 17984.5 | Z47: 11020.5 | AB47: -13308 | AC47: -12833.58 | AD47: -15208 | AE47: 51520.3 | AF47: 10679.72 | AH47: -27550 | AI47: -30132
A49: x | B49: Attribution:
B50: Preferred dividends | D50: 0 | E50: 0 | F50: 0 | G50: 0 | H50: 0 | J50: 0 | K50: 0 | L50: 0 | M50: 0 | N50: 0 | P50: 0 | Q50: 0 | R50: 0 | S50: 0 | T50: 0 | V50: 0 | W50: 0 | X50: 0 | Y50: 0 | Z50: 0 | AB50: 0 | AC50: 0 | AD50: 0 | AE50: 0 | AF50: 0 | AH50: 0 | AI50: 0
B51: Income attributable to non-controlling interests | D51: 344 | E51: -4241 | F51: 4077 | G51: -6781 | H51: -6601 | J51: -416 | K51: -471 | L51: 608 | M51: 24595 | N51: 24316 | P51: 1509 | Q51: 2334 | R51: 1615 | S51: 51988 | T51: 57446 | V51: 6913 | W51: 2652 | X51: 2847 | Y51: 122987 | Z51: 135399 | AB51: 2968 | AC51: 4084 | AD51: 3407 | AE51: 77420 | AF51: 87879 | AH51: 880 | AI51: 2926
B52: Net income attributable to common shareholders | D52: 17926 | E52: -20795 | F52: 5000 | G52: -60838 | H52: -58707 | J52: -9306 | K52: -18192 | L52: -5018 | M52: -64360 | N52: -96876 | P52: -5516 | Q52: -7415 | R52: 3856 | S52: -87021 | T52: -96096 | V52: -1504 | W52: -10773 | X52: -7099 | Y52: -236982 | Z52: -256358 | AB52: -16276 | AC52: -15613 | AD52: -18615 | AE52: -91518 | AF52: -141513 | AH52: -28430 | AI52: -33058
A54: x | B54: Earnings per share:
B55: EPS basic | D55: 0.0919 | E55: -0.1067 | F55: 0.0256 | G55: -0.7378 | H55: -0.705 | J55: -0.0902 | K55: -0.1763 | L55: -0.0486 | M55: 0.21 | N55: -0.1051 | P55: -0.0535 | Q55: -0.0719 | R55: 0.0374 | S55: -0.319 | T55: -0.4069 | V55: -0.0146 | W55: -0.1044 | X55: -0.0688 | Y55: -1.0176 | Z55: -1.2053 | AB55: -0.1577 | AC55: -0.1639 | AD55: -0.1804 | AE55: -0.251 | AF55: -0.7481 | AH55: -0.2755 | AI55: -0.3204
B56: EPS diluted | D56: 0.0919 | E56: -0.1067 | F56: 0.0256 | G56: -0.7378 | H56: -0.705 | J56: -0.0902 | K56: -0.1763 | L56: -0.0486 | M56: 0.21 | N56: -0.1051 | P56: -0.0535 | Q56: -0.0719 | R56: 0.0374 | S56: -0.319 | T56: -0.4069 | V56: -0.0146 | W56: -0.1044 | X56: -0.0688 | Y56: -1.0176 | Z56: -1.2053 | AB56: -0.1577 | AC56: -0.1639 | AD56: -0.1804 | AE56: -0.251 | AF56: -0.7481 | AH56: -0.2755 | AI56: -0.3204
A58: x | B58: Shares used in computing earnings per share:
B59: Basic weighted average shares | D59: 194966.94 | E59: 194966.94 | F59: 194966.94 | G59: 64988.981 | H59: 64988.981 | J59: 103188.98 | K59: 103188.98 | L59: 103188.98 | M59: 103188.98 | N59: 103188.98 | P59: 103188.98 | Q59: 103188.98 | R59: 103188.98 | S59: 103188.98 | T59: 103188.98 | V59: 103188.98 | W59: 103188.98 | X59: 103188.98 | Y59: 103188.98 | Z59: 103188.98 | AB59: 103188.98 | AC59: 103188.98 | AD59: 103188.98 | AE59: 103188.98 | AF59: 103188.98 | AH59: 103188.98 | AI59: 103188.98
B60: Diluted weighted average shares | D60: 194966.94 | E60: 194966.94 | F60: 194966.94 | G60: 64988.981 | H60: 64988.981 | J60: 103188.98 | K60: 103188.98 | L60: 103188.98 | M60: 103188.98 | N60: 103188.98 | P60: 103188.98 | Q60: 103188.98 | R60: 103188.98 | S60: 103188.98 | T60: 103188.98 | V60: 103188.98 | W60: 103188.98 | X60: 103188.98 | Y60: 103188.98 | Z60: 103188.98 | AB60: 103188.98 | AC60: 103188.98 | AD60: 103188.98 | AE60: 103188.98 | AF60: 103188.98 | AH60: 103188.98 | AI60: 103188.98
B62: Additional Items
B64: Depreciation (from opex)
B65: Amortization (form opex)

Sheet BS
AH1: 0
B7: Balance Sheet | D7: 2020 | E7: 2020 | F7: 2020 | G7: 2020 | H7: 2020 | J7: 2021 | K7: 2021 | L7: 2021 | M7: 2021 | N7: 2021 | P7: 2022 | Q7: 2022 | R7: 2022 | S7: 2022 | T7: 2022 | V7: 2023 | W7: 2023 | X7: 2023 | Y7: 2023 | Z7: 2023 | AB7: 2024 | AC7: 2024 | AD7: 2024 | AE7: 2024 | AF7: 2024 | AH7: 2025 | AI7: 2025 | AJ7: 2025 | AK7: 2025 | AL7: 2025 | AN7: 2025 | AO7: 2025 | AP7: 2025 | AQ7: 2025 | AR7: 2025
D8: 2020 | J8: 2021 | P8: 2022 | V8: 2023 | AB8: 2024 | AH8: 2025 | AN8: 2026 | AT8: 2027 | AV8: 2028 | AX8: 2029
D9: Q1 | E9: Q2 | F9: Q3 | G9: Q4 | H9: FY | J9: Q1 | K9: Q2 | L9: Q3 | M9: Q4 | N9: FY | P9: Q1 | Q9: Q2 | R9: Q3 | S9: Q4 | T9: FY | V9: Q1 | W9: Q2 | X9: Q3 | Y9: Q4 | Z9: FY | AB9: Q1 | AC9: Q2 | AD9: Q3 | AE9: Q4 | AF9: FY | AH9: Q1 | AI9: Q2 | AJ9: Q3 | AK9: Q4 | AL9: FY | AN9: Q1 | AO9: Q2 | AP9: Q3 | AQ9: Q4 | AR9: FY | AT9: FY | AV9: FY | AX9: FY
B12: Assets
A14: x | B14: Current assets:
B15: Cash & cash equivalents & short-term investments | D15: 41671 | E15: 70713 | F15: 31172 | G15: 99051 | H15: 99051 | J15: 38707 | K15: 26006 | L15: 38223 | M15: 50645 | N15: 50645 | P15: 43854 | Q15: 46264 | R15: 40483 | S15: 43307 | T15: 43307 | V15: 42873 | W15: 46430 | X15: 43264 | Y15: 20876 | Z15: 20876 | AB15: 25651 | AC15: 22969 | AD15: 24232 | AE15: 27239 | AF15: 27239 | AH15: 13518 | AI15: 23556
B16: Cash & cash equivalents | D16: 0 | E16: 0 | F16: 0 | G16: 0 | H16: 0 | J16: 0 | K16: 0 | L16: 0 | M16: 0 | N16: 0 | P16: 0 | Q16: 0 | R16: 0 | S16: 0 | T16: 0 | V16: 0 | W16: 0 | X16: 0 | Y16: 0 | Z16: 0 | AB16: 0 | AC16: 0 | AD16: 0 | AE16: 0 | AF16: 0 | AH16: 0 | AI16: 0
B17: Short-term investments | D17: 41671 | E17: 70713 | F17: 31172 | G17: 99051 | H17: 99051 | J17: 38707 | K17: 26006 | L17: 38223 | M17: 50645 | N17: 50645 | P17: 43854 | Q17: 46264 | R17: 40483 | S17: 43307 | T17: 43307 | V17: 42873 | W17: 46430 | X17: 43264 | Y17: 20876 | Z17: 20876 | AB17: 25651 | AC17: 22969 | AD17: 24232 | AE17: 27239 | AF17: 27239 | AH17: 13518 | AI17: 23556
B18: Accounts receivable | D18: 14152 | E18: 17972 | F18: 21234 | G18: 18812 | H18: 18812 | J18: 18180 | K18: 18258 | L18: 15835 | M18: 28398 | N18: 28398 | P18: 28924 | Q18: 28321 | R18: 29152 | S18: 27790 | T18: 27790 | V18: 54790 | W18: 27629 | X18: 26445 | Y18: 64174 | Z18: 64174 | AB18: 57350 | AC18: 53573 | AD18: 47112 | AE18: 57612 | AF18: 57612 | AH18: 51788 | AI18: 54156
B19: Inventory | D19: 0 | E19: 0 | F19: 0 | G19: 0 | H19: 0 | J19: 0 | K19: 0 | L19: 0 | M19: 0 | N19: 0 | P19: 0 | Q19: 0 | R19: 0 | S19: 0 | T19: 0 | V19: 0 | W19: 0 | X19: 0 | Y19: 0 | Z19: 0 | AB19: 0 | AC19: 0 | AD19: 0 | AE19: 0 | AF19: 0 | AH19: 0 | AI19: 0
B20: Prepaid expenses and other current assets | D20: 89937 | E20: 88512 | F20: 44623 | G20: 36928 | H20: 36928 | J20: 635241 | K20: 588303 | L20: 534797 | M20: 488090 | N20: 488090 | P20: 448360 | Q20: 411216 | R20: 361385 | S20: 305858 | T20: 305858 | V20: 282502 | W20: 261893 | X20: 198018 | Y20: 384295 | Z20: 384295 | AB20: 453695 | AC20: 461016 | AD20: 409302 | AE20: 398261 | AF20: 398261 | AH20: 437103 | AI20: 485644
B21: Total current assets | D21: 145760 | E21: 177197 | F21: 97029 | G21: 154791 | H21: 154791 | J21: 692128 | K21: 632567 | L21: 588855 | M21: 567133 | N21: 567133 | P21: 521138 | Q21: 485801 | R21: 431020 | S21: 376955 | T21: 376955 | V21: 380165 | W21: 335952 | X21: 267727 | Y21: 469345 | Z21: 469345 | AB21: 536696 | AC21: 537558 | AD21: 480646 | AE21: 483112 | AF21: 483112 | AH21: 502409 | AI21: 563356
A23: x | B23: Non-current assets:
B24: Net PP&E (Property, Plant and Equipment) | D24: 1825821 | E24: 1845073 | F24: 1846874 | G24: 1985311 | H24: 1985311 | J24: 2075933 | K24: 2138031 | L24: 2209517 | M24: 2732448 | N24: 2732448 | P24: 2796175 | Q24: 2852444 | R24: 3123185 | S24: 3435286 | T24: 3435286 | V24: 3453936 | W24: 3496179 | X24: 3559898 | Y24: 3792753 | Z24: 3792753 | AB24: 3814842 | AC24: 3814365 | AD24: 3865233 | AE24: 4043940 | AF24: 4043940 | AH24: 4072450 | AI24: 4089253
B25: Gross PP&E (Property, Plant and Equipment) | D25: 0 | E25: 0 | F25: 0 | G25: 0 | H25: 0 | J25: 0 | K25: 0 | L25: 0 | M25: 0 | N25: 0 | P25: 0 | Q25: 0 | R25: 0 | S25: 0 | T25: 0 | V25: 0 | W25: 0 | X25: 0 | Y25: 0 | Z25: 0 | AB25: 0 | AC25: 0 | AD25: 0 | AE25: 0 | AF25: 0 | AH25: 0 | AI25: 0
B26: Accumulated Depreciation | D26: 0 | E26: 0 | F26: 0 | G26: 0 | H26: 0 | J26: 0 | K26: 0 | L26: 0 | M26: 0 | N26: 0 | P26: 0 | Q26: 0 | R26: 0 | S26: 0 | T26: 0 | V26: 0 | W26: 0 | X26: 0 | Y26: 0 | Z26: 0 | AB26: 0 | AC26: 0 | AD26: 0 | AE26: 0 | AF26: 0 | AH26: 0 | AI26: 0
B27: Intangibles | D27: 345 | E27: 352 | F27: 4220 | G27: 3619 | H27: 3619 | J27: 4469 | K27: 4590 | L27: 4996 | M27: 5349 | N27: 5349 | P27: 5511 | Q27: 5528 | R27: 8596 | S27: 12278 | T27: 12278 | V27: 10432 | W27: 10194 | X27: 9742 | Y27: 9312 | Z27: 9312 | AB27: 32587 | AC27: 33636 | AD27: 38650 | AE27: 41264 | AF27: 41264 | AH27: 41735 | AI27: 44086
B28: Goodwill | D28: 0 | E28: 0 | F28: 0 | G28: 0 | H28: 0 | J28: 0 | K28: 0 | L28: 0 | M28: 0 | N28: 0 | P28: 0 | Q28: 0 | R28: 0 | S28: 0 | T28: 0 | V28: 0 | W28: 0 | X28: 0 | Y28: 0 | Z28: 0 | AB28: 0 | AC28: 0 | AD28: 0 | AE28: 0 | AF28: 0 | AH28: 0 | AI28: 0
B29: Intangibles excl. Goodwill | D29: 0 | E29: 0 | F29: 0 | G29: 0 | H29: 0 | J29: 0 | K29: 0 | L29: 0 | M29: 0 | N29: 0 | P29: 0 | Q29: 0 | R29: 0 | S29: 0 | T29: 0 | V29: 0 | W29: 0 | X29: 0 | Y29: 0 | Z29: 0 | AB29: 0 | AC29: 0 | AD29: 0 | AE29: 0 | AF29: 0 | AH29: 0 | AI29: 0
B30: Other Non-Current Assets | D30: -1826166 | E30: -1845425 | F30: -1851094 | G30: -1988930 | H30: -1988930 | J30: -2080402 | K30: -2142621 | L30: -2214513 | M30: -2737797 | N30: -2737797 | P30: -2801686 | Q30: -2857972 | R30: -3131781 | S30: -3447564 | T30: -3447564 | V30: -3464368 | W30: -3506373 | X30: -3569640 | Y30: -3802065 | Z30: -3802065 | AB30: -3847429 | AC30: -3848001 | AD30: -3903883 | AE30: -4085204 | AF30: -4085204 | AH30: -4114185 | AI30: -4133339
B31: Total Non-Current Assets | D31: 0 | E31: 0 | F31: 0 | G31: 0 | H31: 0 | J31: 0 | K31: 0 | L31: 0 | M31: 0 | N31: 0 | P31: 0 | Q31: 0 | R31: 0 | S31: 0 | T31: 0 | V31: 0 | W31: 0 | X31: 0 | Y31: 0 | Z31: 0 | AB31: 0 | AC31: 0 | AD31: 0 | AE31: 0 | AF31: 0 | AH31: 0 | AI31: 0
B32: Total Assets | D32: 2389873 | E32: 2432811 | F32: 2397051 | G32: 2613689 | H32: 2613689 | J32: 3350102 | K32: 3379668 | L32: 3420892 | M32: 3768362 | N32: 3768362 | P32: 3785695 | Q32: 3803913 | R32: 4027977 | S32: 4281969 | T32: 4281969 | V32: 4310432 | W32: 4306721 | X32: 4308741 | Y32: 4689030 | Z32: 4689030 | AB32: 4816140 | AC32: 4825492 | AD32: 4832493 | AE32: 5090774 | AF32: 5090774 | AH32: 5127447 | AI32: 5204727
B34: Liabilities & shareholders' equity
A36: x | B36: Current Liabilities:
B37: Accounts payable | D37: 23541 | E37: 21514 | F37: 67050 | G37: 117968 | H37: 117968 | J37: 94253 | K37: 46331 | L37: 50028 | M37: 44764 | N37: 44764 | P37: 50169 | Q37: 43638 | R37: 82724 | S37: 115496 | T37: 115496 | V37: 109796 | W37: 84330 | X37: 86595 | Y37: 102367 | Z37: 102367 | AB37: 99570 | AC37: 111863 | AD37: 134204 | AE37: 109922 | AF37: 109922 | AH37: 120197 | AI37: 76519
B38: Short-term borrowings | D38: 10718 | E38: 14207 | F38: 32748 | G38: 74377 | H38: =+G38 -> 74377 | J38: 140033 | K38: 148085 | L38: 130658 | M38: 90509 | N38: =+M38 -> 90509 | P38: 85598 | Q38: 84568 | R38: 101454 | S38: 98245 | T38: =+S38 -> 98245 | V38: 104881 | W38: 119268 | X38: 89879 | Y38: 93022 | Z38: =+Y38 -> 93022 | AB38: 68718 | AC38: 59985 | AD38: 57346 | AE38: 41726 | AF38: =+AE38 -> 41726 | AH38: 52837 | AI38: 64006
B39: Current portion of lease liabilities | D39: 0 | E39: 0 | F39: 0 | G39: 0 | H39: 0 | J39: 0 | K39: 0 | L39: 0 | M39: 0 | N39: 0 | P39: 0 | Q39: 0 | R39: 0 | S39: 0 | T39: 0 | V39: 0 | W39: 0 | X39: 0 | Y39: 0 | Z39: 0 | AB39: 0 | AC39: 0 | AD39: 0 | AE39: 0 | AF39: 0 | AH39: 0 | AI39: 0
B40: Accrued expenses and other current liabilities | D40: 59550 | E40: 55586 | F40: 52118 | G40: 61838 | H40: 61838 | J40: 73401 | K40: 86301 | L40: 96527 | M40: 102482 | N40: 102482 | P40: 97861 | Q40: 96529 | R40: 84641 | S40: 101678 | T40: 101678 | V40: 100152 | W40: 84748 | X40: 87059 | Y40: 89242 | Z40: 89242 | AB40: 122178 | AC40: 113466 | AD40: 127183 | AE40: 143540 | AF40: 143540 | AH40: 146764 | AI40: 160436
B41: Total current liabilities | D41: 93809 | E41: 91307 | F41: 151916 | G41: 254183 | H41: 254183 | J41: 307687 | K41: 280717 | L41: 277213 | M41: 237755 | N41: 237755 | P41: 233628 | Q41: 224735 | R41: 268819 | S41: 315419 | T41: 315419 | V41: 314829 | W41: 288346 | X41: 263533 | Y41: 284631 | Z41: 284631 | AB41: 290466 | AC41: 285314 | AD41: 318733 | AE41: 295188 | AF41: 295188 | AH41: 319798 | AI41: 300961
A43: x | B43: Non-current liabilities:
B44: Long-term borrowings | D44: 727086 | E44: 782459 | F44: 782554 | G44: 884348 | H44: =+G44 -> 884348 | J44: 908974 | K44: 979577 | L44: 1010307 | M44: 1067774 | N44: =+M44 -> 1067774 | P44: 1081127 | Q44: 1090680 | R44: 1094554 | S44: 1169849 | T44: =+S44 -> 1169849 | V44: 1170939 | W44: 1167804 | X44: 1166618 | Y44: 1246193 | Z44: =+Y44 -> 1246193 | AB44: 1389375 | AC44: 1447492 | AD44: 1451399 | AE44: 1526458 | AF44: =+AE44 -> 1526458 | AH44: 1570323 | AI44: 1645381
B45: Long-term operating lease liabilities | D45: 0 | E45: 0 | F45: 0 | G45: 0 | H45: 0 | J45: 0 | K45: 0 | L45: 0 | M45: 0 | N45: 0 | P45: 0 | Q45: 0 | R45: 0 | S45: 0 | T45: 0 | V45: 0 | W45: 0 | X45: 0 | Y45: 0 | Z45: 0 | AB45: 0 | AC45: 0 | AD45: 0 | AE45: 0 | AF45: 0 | AH45: 0 | AI45: 0
B46: Other non-current liabilities | D46: -727086 | E46: -782459 | F46: -782554 | G46: -884348 | H46: -884348 | J46: -908974 | K46: -979577 | L46: -1010307 | M46: -1067774 | N46: -1067774 | P46: -1081127 | Q46: -1090680 | R46: -1094554 | S46: -1169849 | T46: -1169849 | V46: -1170939 | W46: -1167804 | X46: -1166618 | Y46: -1246193 | Z46: -1246193 | AB46: -1389375 | AC46: -1447492 | AD46: -1451399 | AE46: -1526458 | AF46: -1526458 | AH46: -1570323 | AI46: -1645381
B47: Total non-current liabilities | D47: 0 | E47: 0 | F47: 0 | G47: 0 | H47: 0 | J47: 0 | K47: 0 | L47: 0 | M47: 0 | N47: 0 | P47: 0 | Q47: 0 | R47: 0 | S47: 0 | T47: 0 | V47: 0 | W47: 0 | X47: 0 | Y47: 0 | Z47: 0 | AB47: 0 | AC47: 0 | AD47: 0 | AE47: 0 | AF47: 0 | AH47: 0 | AI47: 0
B48: Total liabilities | D48: 968317 | E48: 1025299 | F48: 995044 | G48: 1250134 | H48: 1250134 | J48: 1311087 | K48: 1332640 | L48: 1362372 | M48: 1416865 | N48: 1416865 | P48: 1430237 | Q48: 1434270 | R48: 1640707 | S48: 1808505 | T48: 1808505 | V48: 1819303 | W48: 1816862 | X48: 1802605 | Y48: 1957532 | Z48: 1957532 | AB48: 2068157 | AC48: 2088557 | AD48: 2093960 | AE48: 2141191 | AF48: 2141191 | AH48: 2195108 | AI48: 2285757
A50: x | B50: Shareholders' equity:
B51: Common equity | D51: 1130021 | E51: 1109226 | F51: 1114226 | G51: 1101941 | H51: 1101941 | J51: 1775527 | K51: 1772948 | L51: 1767559 | M51: 1893431 | N51: 1893431 | P51: 1888279 | Q51: 1881228 | R51: 1885333 | S51: 1928590 | T51: 1928590 | V51: 1917881 | W51: 1906872 | X51: 1908598 | Y51: 2024551 | Z51: 2024551 | AB51: 2030123 | AC51: 2010964 | AD51: 1993009 | AE51: 2068676 | AF51: 2068676 | AH51: 2040586 | AI51: 2006511
B52: Preferred equity | D52: 0 | E52: 0 | F52: 0 | G52: 0 | H52: 0 | J52: 0 | K52: 0 | L52: 0 | M52: 0 | N52: 0 | P52: 0 | Q52: 0 | R52: 0 | S52: 0 | T52: 0 | V52: 0 | W52: 0 | X52: 0 | Y52: 0 | Z52: 0 | AB52: 0 | AC52: 0 | AD52: 0 | AE52: 0 | AF52: 0 | AH52: 0 | AI52: 0
B53: Non-controlling interest | D53: 291535 | E53: 298286 | F53: 287781 | G53: 261614 | H53: 261614 | J53: 263488 | K53: 274080 | L53: 290961 | M53: 458066 | N53: 458066 | P53: 467179 | Q53: 488415 | R53: 501937 | S53: 544874 | T53: 544874 | V53: 573248 | W53: 582987 | X53: 597538 | Y53: 706947 | Z53: 706947 | AB53: 717860 | AC53: 725971 | AD53: 745524 | AE53: 880907 | AF53: 880907 | AH53: 891753 | AI53: 912459
B54: Total equity | D54: 1421556 | E54: 1407512 | F54: 1402007 | G54: 1363555 | H54: 1363555 | J54: 2039015 | K54: 2047028 | L54: 2058520 | M54: 2351497 | N54: 2351497 | P54: 2355458 | Q54: 2369643 | R54: 2387270 | S54: 2473464 | T54: 2473464 | V54: 2491129 | W54: 2489859 | X54: 2506136 | Y54: 2731498 | Z54: 2731498 | AB54: 2747983 | AC54: 2736935 | AD54: 2738533 | AE54: 2949583 | AF54: 2949583 | AH54: 2932339 | AI54: 2918970
B55: Total liabilities and shareholders' equity | D55: 2389873 | E55: 2432811 | F55: 2397051 | G55: 2613689 | H55: 2613689 | J55: 3350102 | K55: 3379668 | L55: 3420892 | M55: 3768362 | N55: 3768362 | P55: 3785695 | Q55: 3803913 | R55: 4027977 | S55: 4281969 | T55: 4281969 | V55: 4310432 | W55: 4306721 | X55: 4308741 | Y55: 4689030 | Z55: 4689030 | AB55: 4816140 | AC55: 4825492 | AD55: 4832493 | AE55: 5090774 | AF55: 5090774 | AH55: 5127447 | AI55: 5204727
B57: Capitalized R&D | D57: 0 | E57: 0 | F57: 0 | G57: 0 | H57: 0 | J57: 0 | K57: 0 | L57: 0 | M57: 0 | N57: 0 | P57: 0 | Q57: 0 | R57: 0 | S57: 0 | T57: 0 | V57: 0 | W57: 0 | X57: 0 | Y57: 0 | Z57: 0 | AB57: 0 | AC57: 0 | AD57: 0 | AE57: 0 | AF57: 0 | AH57: 0 | AI57: 0

Sheet CF
A7: x | B7: Cash Flow Statement | D7: 2020 | E7: 2020 | F7: 2020 | G7: 2020 | H7: 2020 | J7: 2021 | K7: 2021 | L7: 2021 | M7: 2021 | N7: 2021 | P7: 2022 | Q7: 2022 | R7: 2022 | S7: 2022 | T7: 2022 | V7: 2023 | W7: 2023 | X7: 2023 | Y7: 2023 | Z7: 2023 | AB7: 2024 | AC7: 2024 | AD7: 2024 | AE7: 2024 | AF7: 2024 | AH7: 2025 | AI7: 2025 | AJ7: 2025 | AK7: 2025 | AL7: 2025 | AN7: 2025 | AO7: 2025 | AP7: 2025 | AQ7: 2025 | AR7: 2025
D8: 2020 | J8: 2021 | P8: 2022 | V8: 2023 | AB8: 2024 | AH8: 2025 | AN8: 2026 | AT8: 2027 | AV8: 2028 | AX8: 2029
D9: Q1 | E9: Q2 | F9: Q3 | G9: Q4 | H9: FY | J9: Q1 | K9: Q2 | L9: Q3 | M9: Q4 | N9: FY | P9: Q1 | Q9: Q2 | R9: Q3 | S9: Q4 | T9: FY | V9: Q1 | W9: Q2 | X9: Q3 | Y9: Q4 | Z9: FY | AB9: Q1 | AC9: Q2 | AD9: Q3 | AE9: Q4 | AF9: FY | AH9: Q1 | AI9: Q2 | AJ9: Q3 | AK9: Q4 | AL9: FY | AN9: Q1 | AO9: Q2 | AP9: Q3 | AQ9: Q4 | AR9: FY | AT9: FY | AV9: FY | AX9: FY
B12: Cash and cash equivalents, beginning balances | D12: 0 | E12: 41671 | F12: 70713 | G12: 31172 | H12: 99051 | J12: 99051 | K12: 38707 | L12: 26006 | M12: 38223 | N12: 50645 | P12: 50645 | Q12: 43854 | R12: 46264 | S12: 40483 | T12: 43307 | V12: 43307 | W12: 42873 | X12: 46430 | Y12: 43264 | Z12: 20876 | AB12: 20876 | AC12: 25651 | AD12: 22969 | AE12: 24232 | AF12: 27239 | AH12: 27239 | AI12: 13518
A14: x | B14: Operating activities:
B15: Net income | D15: 17926 | E15: -20795 | F15: 5000 | G15: -22927 | H15: -20796 | J15: -9306 | K15: -18192 | L15: -5018 | M15: 188679 | N15: 156163 | P15: -5516 | Q15: -7415 | R15: 3856 | S15: 72113 | T15: 63038 | V15: -1504 | W15: -10773 | X15: -7099 | Y15: 151193 | Z15: 131817 | AB15: -16017 | AC15: -19450 | AD15: -17257 | AE15: 100369 | AF15: 47645 | AH15: -28197 | AI15: -33058
B16: Adjustments to reconcile to cash from operations:
B17: Depreciation and amortization | D17: 118 | E17: 134 | F17: 134 | G17: 135 | H17: 521 | J17: 144 | K17: 157 | L17: 166 | M17: 155 | N17: 622 | P17: 173 | Q17: 194 | R17: 243 | S17: 305 | T17: 915 | V17: 480 | W17: 562 | X17: 476 | Y17: 459 | Z17: 1977 | AB17: 1055 | AC17: 1119 | AD17: 1189 | AE17: 1181 | AF17: 4544 | AH17: 1621 | AI17: 1818
B18: Stock-based compensation expense | D18: 0 | E18: 0 | F18: 0 | G18: 0 | H18: 0 | J18: 0 | K18: 0 | L18: 0 | M18: 0 | N18: 0 | P18: 0 | Q18: 0 | R18: 0 | S18: 0 | T18: 0 | V18: 0 | W18: 0 | X18: 375 | Y18: 353 | Z18: 728 | AB18: 1832 | AC18: -2644 | AD18: 0 | AE18: 0 | AF18: -812 | AH18: 132 | AI18: -135
B19: Other | D19: 0 | E19: 0 | F19: 0 | G19: 0 | H19: 0 | J19: 0 | K19: 0 | L19: 0 | M19: 0 | N19: 0 | P19: 0 | Q19: 0 | R19: 0 | S19: 0 | T19: 0 | V19: 0 | W19: 0 | X19: 0 | Y19: 0 | Z19: 0 | AB19: 0 | AC19: 0 | AD19: 0 | AE19: 0 | AF19: 0 | AH19: 0 | AI19: 0
B20: Changes in working capital:
B21: Accounts receivable | D21: 0 | E21: 0 | F21: 0 | G21: 0 | H21: 0 | J21: 0 | K21: 0 | L21: 0 | M21: 0 | N21: 0 | P21: -640 | Q21: 1885 | R21: 1173 | S21: 880 | T21: =+SUM(P21:S21) -> 3298 | V21: =-26425-31 -> -26456 | W21: 26337 | X21: =1042-78 -> 964 | Y21: =-38608-43 -> -38651 | Z21: =+SUM(V21:Y21) -> -37806 | AB21: =3902-52 -> 3850 | AC21: =5743-12528 -> -6785 | AD21: =6388+2269 -> 8657 | AE21: =-11448-189 -> -11637 | AF21: =+SUM(AB21:AE21) -> -5915 | AH21: 6153 | AI21: -2593
B22: Inventories | D22: 0 | E22: 0 | F22: 0 | G22: 0 | H22: 0 | J22: 0 | K22: 0 | L22: 0 | M22: 0 | N22: 0
B23: Accounts payable | D23: 0 | E23: 0 | F23: 0 | G23: 0 | H23: 0 | J23: 0 | K23: 0 | L23: 0 | M23: 0 | N23: 0
B24: Other | D24: 0 | E24: 0 | F24: 0 | G24: 0 | H24: 0 | J24: 0 | K24: 0 | L24: 0 | M24: 0 | N24: 0
B25: Cash provided by operating activities | D25: 26614 | E25: -9162 | F25: 56387 | G25: 43310 | H25: 117149 | J25: 39546 | K25: -6783 | L25: -8881 | M25: 215755 | N25: 239637 | P25: 1381 | Q25: 29485 | R25: 60858 | S25: 78745 | T25: 170469 | V25: 15559 | W25: 37619 | X25: -3311 | Y25: -248041 | Z25: =+SUM(V25:Y25) -> -198174 | AB25: -45655 | AC25: -57721 | AD25: -16258 | AE25: 21921 | AF25: -97713 | AH25: 23813 | AI25: 12577
A27: x | B27: Investing activities:
B28: Purchase of fixed assets and intangibles | D28: {=_xll.BDH("HBRE3 BZ Equity","CF_CAP_EXPEND_PRPTY_ADD","FQ1 2020","FQ1 2020","Currency=BRL","Period=FQ","BEST_FPERIOD_OVERRIDE=FQ","FILING_STATUS=MR","EQY_CONSOLIDATED=Y","ACCOUNTING_STANDARD_OVERRIDE=MIXED","SCALING_FORMAT=MLN","Sort=A","Dates=H","DateFormat=P","Fill=—","Direction=H","UseDPDF=Y")} -> -30.159 | E28: {=_xll.BDH("HBRE3 BZ Equity","CF_CAP_EXPEND_PRPTY_ADD","FQ2 2020","FQ2 2020","Currency=BRL","Period=FQ","BEST_FPERIOD_OVERRIDE=FQ","FILING_STATUS=MR","EQY_CONSOLIDATED=Y","ACCOUNTING_STANDARD_OVERRIDE=MIXED","SCALING_FORMAT=MLN","Sort=A","Dates=H","DateFormat=P","Fill=—","Direction=H","UseDPDF=Y")} -> -19.252 | F28: {=_xll.BDH("HBRE3 BZ Equity","CF_CAP_EXPEND_PRPTY_ADD","FQ3 2020","FQ3 2020","Currency=BRL","Period=FQ","BEST_FPERIOD_OVERRIDE=FQ","FILING_STATUS=MR","EQY_CONSOLIDATED=Y","ACCOUNTING_STANDARD_OVERRIDE=MIXED","SCALING_FORMAT=MLN","Sort=A","Dates=H","DateFormat=P","Fill=—","Direction=H","UseDPDF=Y")} -> -5.195 | G28: {=_xll.BDH("HBRE3 BZ Equity","CF_CAP_EXPEND_PRPTY_ADD","FQ4 2020","FQ4 2020","Currency=BRL","Period=FQ","BEST_FPERIOD_OVERRIDE=FQ","FILING_STATUS=MR","EQY_CONSOLIDATED=Y","ACCOUNTING_STANDARD_OVERRIDE=MIXED","SCALING_FORMAT=MLN","Sort=A","Dates=H","DateFormat=P","Fill=—","Direction=H","UseDPDF=Y")} -> -100.373 | H28: =+SUM(D28:G28) -> -154.979 | J28: {=_xll.BDH("HBRE3 BZ Equity","CF_CAP_EXPEND_PRPTY_ADD","FQ1 2021","FQ1 2021","Currency=BRL","Period=FQ","BEST_FPERIOD_OVERRIDE=FQ","FILING_STATUS=MR","EQY_CONSOLIDATED=Y","ACCOUNTING_STANDARD_OVERRIDE=MIXED","SCALING_FORMAT=MLN","Sort=A","Dates=H","DateFormat=P","Fill=—","Direction=H","UseDPDF=Y")} -> -90.622 | K28: {=_xll.BDH("HBRE3 BZ Equity","CF_CAP_EXPEND_PRPTY_ADD","FQ2 2021","FQ2 2021","Currency=BRL","Period=FQ","BEST_FPERIOD_OVERRIDE=FQ","FILING_STATUS=MR","EQY_CONSOLIDATED=Y","ACCOUNTING_STANDARD_OVERRIDE=MIXED","SCALING_FORMAT=MLN","Sort=A","Dates=H","DateFormat=P","Fill=—","Direction=H","UseDPDF=Y")} -> -62.098 | L28: {=_xll.BDH("HBRE3 BZ Equity","CF_CAP_EXPEND_PRPTY_ADD","FQ3 2021","FQ3 2021","Currency=BRL","Period=FQ","BEST_FPERIOD_OVERRIDE=FQ","FILING_STATUS=MR","EQY_CONSOLIDATED=Y","ACCOUNTING_STANDARD_OVERRIDE=MIXED","SCALING_FORMAT=MLN","Sort=A","Dates=H","DateFormat=P","Fill=—","Direction=H","UseDPDF=Y")} -> -71.486 | M28: {=_xll.BDH("HBRE3 BZ Equity","CF_CAP_EXPEND_PRPTY_ADD","FQ4 2021","FQ4 2021","Currency=BRL","Period=FQ","BEST_FPERIOD_OVERRIDE=FQ","FILING_STATUS=MR","EQY_CONSOLIDATED=Y","ACCOUNTING_STANDARD_OVERRIDE=MIXED","SCALING_FORMAT=MLN","Sort=A","Dates=H","DateFormat=P","Fill=—","Direction=H","UseDPDF=Y")} -> -426.15 | N28: =+SUM(J28:M28) -> -650.356 | P28: {=_xll.BDH("HBRE3 BZ Equity","CF_CAP_EXPEND_PRPTY_ADD","FQ1 2022","FQ1 2022","Currency=BRL","Period=FQ","BEST_FPERIOD_OVERRIDE=FQ","FILING_STATUS=MR","EQY_CONSOLIDATED=Y","ACCOUNTING_STANDARD_OVERRIDE=MIXED","SCALING_FORMAT=MLN","Sort=A","Dates=H","DateFormat=P","Fill=—","Direction=H","UseDPDF=Y")} -> -63.727 | Q28: {=_xll.BDH("HBRE3 BZ Equity","CF_CAP_EXPEND_PRPTY_ADD","FQ2 2022","FQ2 2022","Currency=BRL","Period=FQ","BEST_FPERIOD_OVERRIDE=FQ","FILING_STATUS=MR","EQY_CONSOLIDATED=Y","ACCOUNTING_STANDARD_OVERRIDE=MIXED","SCALING_FORMAT=MLN","Sort=A","Dates=H","DateFormat=P","Fill=—","Direction=H","UseDPDF=Y")} -> -56.269 | R28: {=_xll.BDH("HBRE3 BZ Equity","CF_CAP_EXPEND_PRPTY_ADD","FQ3 2022","FQ3 2022","Currency=BRL","Period=FQ","BEST_FPERIOD_OVERRIDE=FQ","FILING_STATUS=MR","EQY_CONSOLIDATED=Y","ACCOUNTING_STANDARD_OVERRIDE=MIXED","SCALING_FORMAT=MLN","Sort=A","Dates=H","DateFormat=P","Fill=—","Direction=H","UseDPDF=Y")} -> -270.741 | S28: {=_xll.BDH("HBRE3 BZ Equity","CF_CAP_EXPEND_PRPTY_ADD","FQ4 2022","FQ4 2022","Currency=BRL","Period=FQ","BEST_FPERIOD_OVERRIDE=FQ","FILING_STATUS=MR","EQY_CONSOLIDATED=Y","ACCOUNTING_STANDARD_OVERRIDE=MIXED","SCALING_FORMAT=MLN","Sort=A","Dates=H","DateFormat=P","Fill=—","Direction=H","UseDPDF=Y")} -> -213.108 | T28: =+SUM(P28:S28) -> -603.845 | V28: {=_xll.BDH("HBRE3 BZ Equity","CF_CAP_EXPEND_PRPTY_ADD","FQ1 2023","FQ1 2023","Currency=BRL","Period=FQ","BEST_FPERIOD_OVERRIDE=FQ","FILING_STATUS=MR","EQY_CONSOLIDATED=Y","ACCOUNTING_STANDARD_OVERRIDE=MIXED","SCALING_FORMAT=MLN","Sort=A","Dates=H","DateFormat=P","Fill=—","Direction=H","UseDPDF=Y")} -> -27.851 | W28: {=_xll.BDH("HBRE3 BZ Equity","CF_CAP_EXPEND_PRPTY_ADD","FQ2 2023","FQ2 2023","Currency=BRL","Period=FQ","BEST_FPERIOD_OVERRIDE=FQ","FILING_STATUS=MR","EQY_CONSOLIDATED=Y","ACCOUNTING_STANDARD_OVERRIDE=MIXED","SCALING_FORMAT=MLN","Sort=A","Dates=H","DateFormat=P","Fill=—","Direction=H","UseDPDF=Y")} -> -42.243 | X28: {=_xll.BDH("HBRE3 BZ Equity","CF_CAP_EXPEND_PRPTY_ADD","FQ3 2023","FQ3 2023","Currency=BRL","Period=FQ","BEST_FPERIOD_OVERRIDE=FQ","FILING_STATUS=MR","EQY_CONSOLIDATED=Y","ACCOUNTING_STANDARD_OVERRIDE=MIXED","SCALING_FORMAT=MLN","Sort=A","Dates=H","DateFormat=P","Fill=—","Direction=H","UseDPDF=Y")} -> -63.719 | Y28: {=_xll.BDH("HBRE3 BZ Equity","CF_CAP_EXPEND_PRPTY_ADD","FQ4 2023","FQ4 2023","Currency=BRL","Period=FQ","BEST_FPERIOD_OVERRIDE=FQ","FILING_STATUS=MR","EQY_CONSOLIDATED=Y","ACCOUNTING_STANDARD_OVERRIDE=MIXED","SCALING_FORMAT=MLN","Sort=A","Dates=H","DateFormat=P","Fill=—","Direction=H","UseDPDF=Y")} -> 0 | Z28: =+SUM(V28:Y28) -> -133.813 | AB28: {=_xll.BDH("HBRE3 BZ Equity","CF_CAP_EXPEND_PRPTY_ADD","FQ1 2024","FQ1 2024","Currency=BRL","Period=FQ","BEST_FPERIOD_OVERRIDE=FQ","FILING_STATUS=MR","EQY_CONSOLIDATED=Y","ACCOUNTING_STANDARD_OVERRIDE=MIXED","SCALING_FORMAT=MLN","Sort=A","Dates=H","DateFormat=P","Fill=—","Direction=H","UseDPDF=Y")} -> -26.808 | AC28: {=_xll.BDH("HBRE3 BZ Equity","CF_CAP_EXPEND_PRPTY_ADD","FQ2 2024","FQ2 2024","Currency=BRL","Period=FQ","BEST_FPERIOD_OVERRIDE=FQ","FILING_STATUS=MR","EQY_CONSOLIDATED=Y","ACCOUNTING_STANDARD_OVERRIDE=MIXED","SCALING_FORMAT=MLN","Sort=A","Dates=H","DateFormat=P","Fill=—","Direction=H","UseDPDF=Y")} -> -6.614 | AD28: {=_xll.BDH("HBRE3 BZ Equity","CF_CAP_EXPEND_PRPTY_ADD","FQ3 2024","FQ3 2024","Currency=BRL","Period=FQ","BEST_FPERIOD_OVERRIDE=FQ","FILING_STATUS=MR","EQY_CONSOLIDATED=Y","ACCOUNTING_STANDARD_OVERRIDE=MIXED","SCALING_FORMAT=MLN","Sort=A","Dates=H","DateFormat=P","Fill=—","Direction=H","UseDPDF=Y")} -> -50.868 | AE28: {=_xll.BDH("HBRE3 BZ Equity","CF_CAP_EXPEND_PRPTY_ADD","FQ4 2024","FQ4 2024","Currency=BRL","Period=FQ","BEST_FPERIOD_OVERRIDE=FQ","FILING_STATUS=MR","EQY_CONSOLIDATED=Y","ACCOUNTING_STANDARD_OVERRIDE=MIXED","SCALING_FORMAT=MLN","Sort=A","Dates=H","DateFormat=P","Fill=—","Direction=H","UseDPDF=Y")} -> 0 | AF28: =+SUM(AB28:AE28) -> -84.29 | AH28: {=_xll.BDH("HBRE3 BZ Equity","CF_CAP_EXPEND_PRPTY_ADD","FQ1 2025","FQ1 2025","Currency=BRL","Period=FQ","BEST_FPERIOD_OVERRIDE=FQ","FILING_STATUS=MR","EQY_CONSOLIDATED=Y","ACCOUNTING_STANDARD_OVERRIDE=MIXED","SCALING_FORMAT=MLN","Sort=A","Dates=H","DateFormat=P","Fill=—","Direction=H","UseDPDF=Y")} -> -28.51 | AI28: {=_xll.BDH("HBRE3 BZ Equity","CF_CAP_EXPEND_PRPTY_ADD","FQ2 2025","FQ2 2025","Currency=BRL","Period=FQ","BEST_FPERIOD_OVERRIDE=FQ","FILING_STATUS=MR","EQY_CONSOLIDATED=Y","ACCOUNTING_STANDARD_OVERRIDE=MIXED","SCALING_FORMAT=MLN","Sort=A","Dates=H","DateFormat=P","Fill=—","Direction=H","UseDPDF=Y")} -> -18.294
B29: Disposal of fixed assets and intangibles | D29: 0 | E29: 0 | F29: 0 | G29: 0 | H29: 0 | J29: 0 | K29: 0 | L29: 0 | M29: 0 | N29: 0 | P29: 0 | Q29: 0 | R29: 0 | S29: 0 | T29: 0 | V29: 0 | W29: 0 | X29: 0 | Y29: 124 | Z29: 124 | AB29: 0 | AC29: 0 | AD29: 0 | AE29: 17.5 | AF29: 17.5 | AH29: 0 | AI29: 0
B30: Acquisitions | D30: 0 | E30: 0 | F30: 0 | G30: 0 | H30: 0 | J30: 0 | K30: 0 | L30: 0 | M30: 0 | N30: 0 | P30: 0 | Q30: 0 | R30: 0 | S30: 0 | T30: 0 | V30: 0 | W30: 0 | X30: 0 | Y30: 0 | Z30: 0 | AB30: 0 | AC30: 0 | AD30: 0 | AE30: 0 | AF30: 0 | AH30: 0 | AI30: 0
B31: Divestitures | D31: 0 | E31: 0 | F31: 0 | G31: 0 | H31: 0 | J31: 0 | K31: 0 | L31: 0 | M31: 0 | N31: 0 | P31: 0 | Q31: 0 | R31: 0 | S31: 0 | T31: 0 | V31: 0 | W31: 0 | X31: 0 | Y31: 0 | Z31: 0 | AB31: 0 | AC31: 0 | AD31: 0 | AE31: 0 | AF31: 0 | AH31: 0 | AI31: 0
B32: Joint Ventures | D32: 0 | E32: 0 | F32: 0 | G32: 0 | H32: 0 | J32: 0 | K32: 0 | L32: 0 | M32: 0 | N32: 0 | P32: 0 | Q32: 0 | R32: 0 | S32: 0 | T32: 0 | V32: 0 | W32: 0 | X32: 0 | Y32: 0 | Z32: 0 | AB32: 0 | AC32: 0 | AD32: 0 | AE32: 0 | AF32: 0 | AH32: 0 | AI32: 0
B33: Increase in long-term investments | D33: 0 | E33: 0 | F33: 0 | G33: 0 | H33: 0 | J33: 0 | K33: 0 | L33: 0 | M33: 0 | N33: 0 | P33: 0 | Q33: 0 | R33: 0 | S33: 0 | T33: 0 | V33: 0 | W33: 0 | X33: 0 | Y33: 0 | Z33: 0 | AB33: 0 | AC33: 0 | AD33: 0 | AE33: 0 | AF33: 0 | AH33: 0 | AI33: 0
B34: Decrease in long-term investments | D34: 591 | E34: -15363 | F34: 17786 | G34: -3697 | H34: -683 | J34: -706248 | K34: 44074 | L34: 49862 | M34: 67320 | N34: -544992 | P34: 69088 | Q34: 32079 | R34: 22690 | S34: 30362 | T34: 154219 | V34: 21312 | W34: 40504 | X34: 32814 | Y34: -20044 | Z34: 74586 | AB34: -60991 | AC34: 23641 | AD34: 57413 | AE34: -57075 | AF34: -37012 | AH34: -14353 | AI34: -29897
B35: Other investing inflows/(outflows) | D35: -11881 | E35: -9462 | F35: -20578 | G35: -43222 | H35: -85143 | J35: -91864 | K35: -42724 | L35: -43484 | M35: -426602 | N35: -604674 | P35: -65303 | Q35: -56114 | R35: -53360 | S35: -123519 | T35: -298296 | V35: -29100 | W35: -37974 | X35: -56322 | Y35: 155963 | Z35: 32567 | AB35: -22677 | AC35: -6330 | AD35: -45656 | AE35: -2177 | AF35: -76840 | AH35: -32958 | AI35: -25236
B36: Cash provided by/(used in) investing activities | D36: -11290 | E36: -24825 | F36: -2792 | G36: -46919 | H36: -85826 | J36: -798112 | K36: 1350 | L36: 6378 | M36: -359282 | N36: -1149666 | P36: 3785 | Q36: -24035 | R36: -30670 | S36: -93157 | T36: -144077 | V36: -7788 | W36: 2530 | X36: -23508 | Y36: 135919 | Z36: 107153 | AB36: -83668 | AC36: 17311 | AD36: 11757 | AE36: -59252 | AF36: -113852 | AH36: -47311 | AI36: -55133
A38: x | B38: Financing activities:
B39: Payment of dividends | D39: 0 | E39: 0 | F39: 0 | G39: 0 | H39: 0 | J39: 0 | K39: 0 | L39: 0 | M39: 0 | N39: 0 | P39: 0 | Q39: 0 | R39: 0 | S39: 0 | T39: 0 | V39: 0 | W39: 0 | X39: 0 | Y39: 0 | Z39: 0 | AB39: 0 | AC39: 0 | AD39: 0 | AE39: 0 | AF39: 0 | AH39: 0 | AI39: 0
B40: Issuance (repurchase) of common shares | D40: 0 | E40: 0 | F40: 0 | G40: 0 | H40: 0 | J40: 682892 | K40: -1768 | L40: -1241 | M40: -1625 | N40: 678258 | P40: 0 | Q40: 0 | R40: 0 | S40: 0 | T40: 0 | V40: 0 | W40: 0 | X40: 0 | Y40: 0 | Z40: 0 | AB40: 0 | AC40: 0 | AD40: 0 | AE40: 0 | AF40: 0 | AH40: 0 | AI40: 0
B41: Cash from (repayment) of short-term debt | D41: 0 | E41: 0 | F41: 0 | G41: 0 | H41: 0 | J41: 0 | K41: 0 | L41: 0 | M41: 0 | N41: 0 | P41: 0 | Q41: 0 | R41: 0 | S41: 0 | T41: 0 | V41: 0 | W41: 0 | X41: 0 | Y41: 0 | Z41: 0 | AB41: 0 | AC41: 0 | AD41: 0 | AE41: 0 | AF41: 0 | AH41: 0 | AI41: 0
B42: Proceeds from issuance of long-term debt | D42: 4500 | E42: 0 | F42: 0 | G42: 0 | H42: 4500 | J42: 24300 | K42: 0 | L42: 0 | M42: 0 | N42: 24300 | P42: -1400 | Q42: 0 | R42: 0 | S42: 0 | T42: -1400 | V42: 19100 | W42: 0 | X42: 0 | Y42: 0 | Z42: 19100 | AB42: 15500 | AC42: 0 | AD42: 0 | AE42: 0 | AF42: 15500 | AH42: 64300 | AI42: 0
B43: Repayments of long-term debt | D43: -34900 | E43: 0 | F43: 0 | G43: 0 | H43: -34900 | J43: -9100 | K43: -9100 | L43: -9100 | M43: -9100 | N43: =+SUM(J43:M43) -> -36400 | P43: -13900 | Q43: 0 | R43: 0 | S43: 0 | T43: -13900 | V43: -41400 | W43: 0 | X43: 0 | Y43: 0 | Z43: -41400 | AB43: -28900 | AC43: 0 | AD43: 0 | AE43: 0 | AF43: -28900 | AH43: -64500 | AI43: 34800
B44: Other financing inflows/(outflows) | D44: -3018 | E44: 63029 | F44: -93136 | G44: 71488 | H44: 38363 | J44: 130 | K44: 3600 | L44: 25061 | M44: 166674 | N44: =+SUM(J44:M44) -> 195465 | P44: 3343 | Q44: -3040 | R44: -35969 | S44: 17236 | T44: -18430 | V44: 14095 | W44: -36592 | X44: 23653 | Y44: 89734 | Z44: 90890 | AB44: 147498 | AC44: 37728 | AD44: 5764 | AE44: 40338 | AF44: 231328 | AH44: 9977 | AI44: 17794
B45: Cash provided by/(used in) financing activities | D45: -33418 | E45: 63029 | F45: -93136 | G45: 71488 | H45: 7963 | J45: 698222 | K45: -7268 | L45: 14720 | M45: 155949 | N45: 861623 | P45: -11957 | Q45: -3040 | R45: -35969 | S45: 17236 | T45: -33730 | V45: -8205 | W45: -36592 | X45: 23653 | Y45: 89734 | Z45: 68590 | AB45: 134098 | AC45: 37728 | AD45: 5764 | AE45: 40338 | AF45: 217928 | AH45: 9777 | AI45: 52594
A47: x | B47: Effects of foreign exchange | D47: 0 | E47: 0 | F47: 0 | G47: 0 | H47: 0 | J47: 0 | K47: 0 | L47: 0 | M47: 0 | N47: 0 | P47: 0 | Q47: 0 | R47: 0 | S47: 0 | T47: 0 | V47: 0 | W47: 0 | X47: 0 | Y47: 0 | Z47: 0 | AB47: 0 | AC47: 0 | AD47: 0 | AE47: 0 | AF47: 0 | AH47: 0 | AI47: 0
A49: x | B49: Increase/(Decrease) in cash and cash equivalents | D49: -18094 | E49: 29042 | F49: -39541 | G49: 67879 | H49: 39286 | J49: -60344 | K49: -12701 | L49: 12217 | M49: 12422 | N49: -48406 | P49: -6791 | Q49: 2410 | R49: -5781 | S49: 2824 | T49: -7338 | V49: -434 | W49: 3557 | X49: -3166 | Y49: -22388 | Z49: -22431 | AB49: 4775 | AC49: -2682 | AD49: 1263 | AE49: 3007 | AF49: 6363 | AH49: -13721 | AI49: 10038
B50: Cash and cash equivalents, ending balances | D50: 41671 | E50: 70713 | F50: 31172 | G50: 99051 | H50: 99051 | J50: 38707 | K50: 26006 | L50: 38223 | M50: 50645 | N50: 50645 | P50: 43854 | Q50: 46264 | R50: 40483 | S50: 43307 | T50: 43307 | V50: 42873 | W50: 46430 | X50: 43264 | Y50: 20876 | Z50: 20876 | AB50: 25651 | AC50: 22969 | AD50: 24232 | AE50: 27239 | AF50: 27239 | AH50: 13518 | AI50: 23556
P59: 0 | Q59: 0 | R59: 0 | S59: 0 | T59: 0 | V59: 0 | W59: 0 | X59: 0 | Y59: 0 | Z59: 0 | AB59: 0 | AC59: 0 | AD59: 0 | AE59: 0 | AF59: 0 | AH59: 0 | AI59: 0
P60: 7118 | Q60: -2840 | R60: -869 | S60: -1484 | T60: =+SUM(P60:S60) -> 1925 | V60: 7783 | W60: 178 | X60: -751 | Y60: -2399 | Z60: =+SUM(V60:Y60) -> 4811 | AB60: 2370 | AC60: -1326 | AD60: 1381 | AE60: -7656 | AF60: =+SUM(AB60:AE60) -> -5231 | AH60: 2387 | AI60: 3790
P61: -39634 | Q61: -4402 | R61: 37064 | S61: 15285 | T61: =+SUM(P61:S61) -> 8313 | V61: -1886 | W61: -10146 | X61: -6348 | Y61: -144306 | Z61: =+SUM(V61:Y61) -> -162686 | AB61: -48718 | AC61: -35349 | AD61: -13756 | AE61: -25953 | AF61: =+SUM(AB61:AE61) -> -123776 | AH61: -9938 | AI61: -3487

Sheet Error Check
B7: Income Statement – Sum of the Quarters = FY | D7: =F7 -> 2020 | E7: =F7 -> 2020 | F7: 2020 | G7: =F7 -> 2020 | H7: =F7 -> 2020 | J7: =L7 -> 2021 | K7: =L7 -> 2021 | L7: 2021 | M7: =L7 -> 2021 | N7: =L7 -> 2021 | P7: =R7 -> 2022 | Q7: =R7 -> 2022 | R7: 2022 | S7: =R7 -> 2022 | T7: =R7 -> 2022 | V7: =X7 -> 2023 | W7: =X7 -> 2023 | X7: 2023 | Y7: =X7 -> 2023 | Z7: =X7 -> 2023 | AB7: =AD7 -> 2024 | AC7: =AD7 -> 2024 | AD7: 2024 | AE7: =AD7 -> 2024 | AF7: =AD7 -> 2024 | AH7: =AJ7 -> 2025 | AI7: =AJ7 -> 2025 | AJ7: 2025 | AK7: =AJ7 -> 2025 | AL7: =AJ7 -> 2025 | AN7: =AP7 -> 2025 | AO7: =AP7 -> 2025 | AP7: 2025 | AQ7: =AP7 -> 2025 | AR7: =AP7 -> 2025
D8: 2020 | J8: =D8+1 -> 2021 | P8: =J8+1 -> 2022 | V8: =P8+1 -> 2023 | AB8: =V8+1 -> 2024 | AH8: =AB8+1 -> 2025 | AN8: =AH8+1 -> 2026 | AT8: =AN8+1 -> 2027 | AV8: =+AT8+1 -> 2028 | AX8: =+AV8+1 -> 2029
D9: Q1 | E9: Q2 | F9: Q3 | G9: Q4 | H9: FY | J9: Q1 | K9: Q2 | L9: Q3 | M9: Q4 | N9: FY | P9: Q1 | Q9: Q2 | R9: Q3 | S9: Q4 | T9: FY | V9: Q1 | W9: Q2 | X9: Q3 | Y9: Q4 | Z9: FY | AB9: Q1 | AC9: Q2 | AD9: Q3 | AE9: Q4 | AF9: FY | AH9: Q1 | AI9: Q2 | AJ9: Q3 | AK9: Q4 | AL9: FY | AN9: Q1 | AO9: Q2 | AP9: Q3 | AQ9: Q4 | AR9: FY | AT9: FY | AV9: FY | AX9: FY
A12: x | B12: Revenue:
B13: Segment 1 | H13: =IF(ROUND(SUM(IS!D13:G13),1)=ROUND(IS!H13,1),"OK","ERROR") -> ERROR | N13: =IF(ROUND(SUM(IS!J13:M13),1)=ROUND(IS!N13,1),"OK","ERROR") -> ERROR | T13: =IF(ROUND(SUM(IS!P13:S13),1)=ROUND(IS!T13,1),"OK","ERROR") -> OK | Z13: =IF(ROUND(SUM(IS!V13:Y13),1)=ROUND(IS!Z13,1),"OK","ERROR") -> OK | AF13: =IF(ROUND(SUM(IS!AB13:AE13),1)=ROUND(IS!AF13,1),"OK","ERROR") -> OK | AL13: =IF(ROUND(SUM(IS!AH13:AK13),1)=ROUND(IS!AL13,1),"OK","ERROR") -> OK | AR13: =IF(ROUND(SUM(IS!AN13:AQ13),1)=ROUND(IS!AR13,1),"OK","ERROR") -> OK
B14: Segment 2 | H14: =IF(ROUND(SUM(IS!D14:G14),1)=ROUND(IS!H14,1),"OK","ERROR") -> ERROR | N14: =IF(ROUND(SUM(IS!J14:M14),1)=ROUND(IS!N14,1),"OK","ERROR") -> ERROR | T14: =IF(ROUND(SUM(IS!P14:S14),1)=ROUND(IS!T14,1),"OK","ERROR") -> OK | Z14: =IF(ROUND(SUM(IS!V14:Y14),1)=ROUND(IS!Z14,1),"OK","ERROR") -> OK | AF14: =IF(ROUND(SUM(IS!AB14:AE14),1)=ROUND(IS!AF14,1),"OK","ERROR") -> OK | AL14: =IF(ROUND(SUM(IS!AH14:AK14),1)=ROUND(IS!AL14,1),"OK","ERROR") -> OK | AR14: =IF(ROUND(SUM(IS!AN14:AQ14),1)=ROUND(IS!AR14,1),"OK","ERROR") -> OK
B15: Segment 3 | H15: =IF(ROUND(SUM(IS!D15:G15),1)=ROUND(IS!H15,1),"OK","ERROR") -> ERROR | N15: =IF(ROUND(SUM(IS!J15:M15),1)=ROUND(IS!N15,1),"OK","ERROR") -> ERROR | T15: =IF(ROUND(SUM(IS!P15:S15),1)=ROUND(IS!T15,1),"OK","ERROR") -> OK | Z15: =IF(ROUND(SUM(IS!V15:Y15),1)=ROUND(IS!Z15,1),"OK","ERROR") -> OK | AF15: =IF(ROUND(SUM(IS!AB15:AE15),1)=ROUND(IS!AF15,1),"OK","ERROR") -> OK | AL15: =IF(ROUND(SUM(IS!AH15:AK15),1)=ROUND(IS!AL15,1),"OK","ERROR") -> OK | AR15: =IF(ROUND(SUM(IS!AN15:AQ15),1)=ROUND(IS!AR15,1),"OK","ERROR") -> OK
B16: Segment 4 | H16: =IF(ROUND(SUM(IS!D16:G16),1)=ROUND(IS!H16,1),"OK","ERROR") -> ERROR | N16: =IF(ROUND(SUM(IS!J16:M16),1)=ROUND(IS!N16,1),"OK","ERROR") -> ERROR | T16: =IF(ROUND(SUM(IS!P16:S16),1)=ROUND(IS!T16,1),"OK","ERROR") -> OK | Z16: =IF(ROUND(SUM(IS!V16:Y16),1)=ROUND(IS!Z16,1),"OK","ERROR") -> OK | AF16: =IF(ROUND(SUM(IS!AB16:AE16),1)=ROUND(IS!AF16,1),"OK","ERROR") -> OK | AL16: =IF(ROUND(SUM(IS!AH16:AK16),1)=ROUND(IS!AL16,1),"OK","ERROR") -> OK | AR16: =IF(ROUND(SUM(IS!AN16:AQ16),1)=ROUND(IS!AR16,1),"OK","ERROR") -> OK
B17: Segment 5 | D17: t | H17: =IF(ROUND(SUM(IS!D17:G17),1)=ROUND(IS!H17,1),"OK","ERROR") -> OK | N17: =IF(ROUND(SUM(IS!J17:M17),1)=ROUND(IS!N17,1),"OK","ERROR") -> OK | T17: =IF(ROUND(SUM(IS!P17:S17),1)=ROUND(IS!T17,1),"OK","ERROR") -> OK | Z17: =IF(ROUND(SUM(IS!V17:Y17),1)=ROUND(IS!Z17,1),"OK","ERROR") -> OK | AF17: =IF(ROUND(SUM(IS!AB17:AE17),1)=ROUND(IS!AF17,1),"OK","ERROR") -> OK | AL17: =IF(ROUND(SUM(IS!AH17:AK17),1)=ROUND(IS!AL17,1),"OK","ERROR") -> OK | AR17: =IF(ROUND(SUM(IS!AN17:AQ17),1)=ROUND(IS!AR17,1),"OK","ERROR") -> OK
B18: Total revenue | H18: =IF(ROUND(SUM(IS!D18:G18),1)=ROUND(IS!H18,1),"OK","ERROR") -> ERROR | N18: =IF(ROUND(SUM(IS!J18:M18),1)=ROUND(IS!N18,1),"OK","ERROR") -> ERROR | T18: =IF(ROUND(SUM(IS!P18:S18),1)=ROUND(IS!T18,1),"OK","ERROR") -> OK | Z18: =IF(ROUND(SUM(IS!V18:Y18),1)=ROUND(IS!Z18,1),"OK","ERROR") -> OK | AF18: =IF(ROUND(SUM(IS!AB18:AE18),1)=ROUND(IS!AF18,1),"OK","ERROR") -> OK | AL18: =IF(ROUND(SUM(IS!AH18:AK18),1)=ROUND(IS!AL18,1),"OK","ERROR") -> OK | AR18: =IF(ROUND(SUM(IS!AN18:AQ18),1)=ROUND(IS!AR18,1),"OK","ERROR") -> OK
A20: x | B20: Cost of revenue:
B21: Cost of goods and services | H21: =IF(ROUND(SUM(IS!D21:G21),1)=ROUND(IS!H21,1),"OK","ERROR") -> OK | N21: =IF(ROUND(SUM(IS!J21:M21),1)=ROUND(IS!N21,1),"OK","ERROR") -> OK | T21: =IF(ROUND(SUM(IS!P21:S21),1)=ROUND(IS!T21,1),"OK","ERROR") -> OK | Z21: =IF(ROUND(SUM(IS!V21:Y21),1)=ROUND(IS!Z21,1),"OK","ERROR") -> OK | AF21: =IF(ROUND(SUM(IS!AB21:AE21),1)=ROUND(IS!AF21,1),"OK","ERROR") -> OK | AL21: =IF(ROUND(SUM(IS!AH21:AK21),1)=ROUND(IS!AL21,1),"OK","ERROR") -> OK | AR21: =IF(ROUND(SUM(IS!AN21:AQ21),1)=ROUND(IS!AR21,1),"OK","ERROR") -> OK
B22: Depreciation & amortization | H22: =IF(ROUND(SUM(IS!D22:G22),1)=ROUND(IS!H22,1),"OK","ERROR") -> OK | N22: =IF(ROUND(SUM(IS!J22:M22),1)=ROUND(IS!N22,1),"OK","ERROR") -> OK | T22: =IF(ROUND(SUM(IS!P22:S22),1)=ROUND(IS!T22,1),"OK","ERROR") -> OK | Z22: =IF(ROUND(SUM(IS!V22:Y22),1)=ROUND(IS!Z22,1),"OK","ERROR") -> OK | AF22: =IF(ROUND(SUM(IS!AB22:AE22),1)=ROUND(IS!AF22,1),"OK","ERROR") -> OK | AL22: =IF(ROUND(SUM(IS!AH22:AK22),1)=ROUND(IS!AL22,1),"OK","ERROR") -> OK | AR22: =IF(ROUND(SUM(IS!AN22:AQ22),1)=ROUND(IS!AR22,1),"OK","ERROR") -> OK
B23: Total cost of revenue | H23: =IF(ROUND(SUM(IS!D23:G23),1)=ROUND(IS!H23,1),"OK","ERROR") -> OK | N23: =IF(ROUND(SUM(IS!J23:M23),1)=ROUND(IS!N23,1),"OK","ERROR") -> OK | T23: =IF(ROUND(SUM(IS!P23:S23),1)=ROUND(IS!T23,1),"OK","ERROR") -> OK | Z23: =IF(ROUND(SUM(IS!V23:Y23),1)=ROUND(IS!Z23,1),"OK","ERROR") -> OK | AF23: =IF(ROUND(SUM(IS!AB23:AE23),1)=ROUND(IS!AF23,1),"OK","ERROR") -> OK | AL23: =IF(ROUND(SUM(IS!AH23:AK23),1)=ROUND(IS!AL23,1),"OK","ERROR") -> OK | AR23: =IF(ROUND(SUM(IS!AN23:AQ23),1)=ROUND(IS!AR23,1),"OK","ERROR") -> OK
B24: Gross margin | H24: =IF(ROUND(SUM(IS!D24:G24),1)=ROUND(IS!H24,1),"OK","ERROR") -> OK | N24: =IF(ROUND(SUM(IS!J24:M24),1)=ROUND(IS!N24,1),"OK","ERROR") -> OK | T24: =IF(ROUND(SUM(IS!P24:S24),1)=ROUND(IS!T24,1),"OK","ERROR") -> OK | Z24: =IF(ROUND(SUM(IS!V24:Y24),1)=ROUND(IS!Z24,1),"OK","ERROR") -> OK | AF24: =IF(ROUND(SUM(IS!AB24:AE24),1)=ROUND(IS!AF24,1),"OK","ERROR") -> OK | AL24: =IF(ROUND(SUM(IS!AH24:AK24),1)=ROUND(IS!AL24,1),"OK","ERROR") -> OK | AR24: =IF(ROUND(SUM(IS!AN24:AQ24),1)=ROUND(IS!AR24,1),"OK","ERROR") -> ERROR
A26: x | B26: Operating expenses:
B27: Selling, general and administrative | H27: =IF(ROUND(SUM(IS!D27:G27),1)=ROUND(IS!H27,1),"OK","ERROR") -> OK | N27: =IF(ROUND(SUM(IS!J27:M27),1)=ROUND(IS!N27,1),"OK","ERROR") -> OK | T27: =IF(ROUND(SUM(IS!P27:S27),1)=ROUND(IS!T27,1),"OK","ERROR") -> OK | Z27: =IF(ROUND(SUM(IS!V27:Y27),1)=ROUND(IS!Z27,1),"OK","ERROR") -> OK | AF27: =IF(ROUND(SUM(IS!AB27:AE27),1)=ROUND(IS!AF27,1),"OK","ERROR") -> OK | AL27: =IF(ROUND(SUM(IS!AH27:AK27),1)=ROUND(IS!AL27,1),"OK","ERROR") -> OK | AR27: =IF(ROUND(SUM(IS!AN27:AQ27),1)=ROUND(IS!AR27,1),"OK","ERROR") -> OK
B28: Depreciation and amortization | H28: =IF(ROUND(SUM(IS!D28:G28),1)=ROUND(IS!H28,1),"OK","ERROR") -> OK | N28: =IF(ROUND(SUM(IS!J28:M28),1)=ROUND(IS!N28,1),"OK","ERROR") -> OK | T28: =IF(ROUND(SUM(IS!P28:S28),1)=ROUND(IS!T28,1),"OK","ERROR") -> OK | Z28: =IF(ROUND(SUM(IS!V28:Y28),1)=ROUND(IS!Z28,1),"OK","ERROR") -> OK | AF28: =IF(ROUND(SUM(IS!AB28:AE28),1)=ROUND(IS!AF28,1),"OK","ERROR") -> OK | AL28: =IF(ROUND(SUM(IS!AH28:AK28),1)=ROUND(IS!AL28,1),"OK","ERROR") -> ERROR | AR28: =IF(ROUND(SUM(IS!AN28:AQ28),1)=ROUND(IS!AR28,1),"OK","ERROR") -> OK
B29: Research and development | H29: =IF(ROUND(SUM(IS!D29:G29),1)=ROUND(IS!H29,1),"OK","ERROR") -> OK | N29: =IF(ROUND(SUM(IS!J29:M29),1)=ROUND(IS!N29,1),"OK","ERROR") -> OK | T29: =IF(ROUND(SUM(IS!P29:S29),1)=ROUND(IS!T29,1),"OK","ERROR") -> OK | Z29: =IF(ROUND(SUM(IS!V29:Y29),1)=ROUND(IS!Z29,1),"OK","ERROR") -> OK | AF29: =IF(ROUND(SUM(IS!AB29:AE29),1)=ROUND(IS!AF29,1),"OK","ERROR") -> OK | AL29: =IF(ROUND(SUM(IS!AH29:AK29),1)=ROUND(IS!AL29,1),"OK","ERROR") -> OK | AR29: =IF(ROUND(SUM(IS!AN29:AQ29),1)=ROUND(IS!AR29,1),"OK","ERROR") -> OK
B30: Other operating expenses | H30: =IF(ROUND(SUM(IS!D30:G30),1)=ROUND(IS!H30,1),"OK","ERROR") -> OK | N30: =IF(ROUND(SUM(IS!J30:M30),1)=ROUND(IS!N30,1),"OK","ERROR") -> OK | T30: =IF(ROUND(SUM(IS!P30:S30),1)=ROUND(IS!T30,1),"OK","ERROR") -> OK | Z30: =IF(ROUND(SUM(IS!V30:Y30),1)=ROUND(IS!Z30,1),"OK","ERROR") -> OK | AF30: =IF(ROUND(SUM(IS!AB30:AE30),1)=ROUND(IS!AF30,1),"OK","ERROR") -> OK | AL30: =IF(ROUND(SUM(IS!AH30:AK30),1)=ROUND(IS!AL30,1),"OK","ERROR") -> ERROR | AR30: =IF(ROUND(SUM(IS!AN30:AQ30),1)=ROUND(IS!AR30,1),"OK","ERROR") -> OK
B31: Total operating expenses | H31: =IF(ROUND(SUM(IS!D31:G31),1)=ROUND(IS!H31,1),"OK","ERROR") -> OK | N31: =IF(ROUND(SUM(IS!J31:M31),1)=ROUND(IS!N31,1),"OK","ERROR") -> OK | T31: =IF(ROUND(SUM(IS!P31:S31),1)=ROUND(IS!T31,1),"OK","ERROR") -> OK | Z31: =IF(ROUND(SUM(IS!V31:Y31),1)=ROUND(IS!Z31,1),"OK","ERROR") -> OK | AF31: =IF(ROUND(SUM(IS!AB31:AE31),1)=ROUND(IS!AF31,1),"OK","ERROR") -> OK | AL31: =IF(ROUND(SUM(IS!AH31:AK31),1)=ROUND(IS!AL31,1),"OK","ERROR") -> ERROR | AR31: =IF(ROUND(SUM(IS!AN31:AQ31),1)=ROUND(IS!AR31,1),"OK","ERROR") -> OK
B32: Other operating income | H32: =IF(ROUND(SUM(IS!D32:G32),1)=ROUND(IS!H32,1),"OK","ERROR") -> OK | N32: =IF(ROUND(SUM(IS!J32:M32),1)=ROUND(IS!N32,1),"OK","ERROR") -> OK | T32: =IF(ROUND(SUM(IS!P32:S32),1)=ROUND(IS!T32,1),"OK","ERROR") -> OK | Z32: =IF(ROUND(SUM(IS!V32:Y32),1)=ROUND(IS!Z32,1),"OK","ERROR") -> OK | AF32: =IF(ROUND(SUM(IS!AB32:AE32),1)=ROUND(IS!AF32,1),"OK","ERROR") -> OK | AL32: =IF(ROUND(SUM(IS!AH32:AK32),1)=ROUND(IS!AL32,1),"OK","ERROR") -> ERROR | AR32: =IF(ROUND(SUM(IS!AN32:AQ32),1)=ROUND(IS!AR32,1),"OK","ERROR") -> OK
B33: Operating income | H33: =IF(ROUND(SUM(IS!D33:G33),1)=ROUND(IS!H33,1),"OK","ERROR") -> OK | N33: =IF(ROUND(SUM(IS!J33:M33),1)=ROUND(IS!N33,1),"OK","ERROR") -> OK | T33: =IF(ROUND(SUM(IS!P33:S33),1)=ROUND(IS!T33,1),"OK","ERROR") -> OK | Z33: =IF(ROUND(SUM(IS!V33:Y33),1)=ROUND(IS!Z33,1),"OK","ERROR") -> OK | AF33: =IF(ROUND(SUM(IS!AB33:AE33),1)=ROUND(IS!AF33,1),"OK","ERROR") -> OK | AL33: =IF(ROUND(SUM(IS!AH33:AK33),1)=ROUND(IS!AL33,1),"OK","ERROR") -> ERROR | AR33: =IF(ROUND(SUM(IS!AN33:AQ33),1)=ROUND(IS!AR33,1),"OK","ERROR") -> OK
A35: x | B35: Non-operating (income) loss:
B36: Interest expense | H36: =IF(ROUND(SUM(IS!D36:G36),1)=ROUND(IS!H36,1),"OK","ERROR") -> OK | N36: =IF(ROUND(SUM(IS!J36:M36),1)=ROUND(IS!N36,1),"OK","ERROR") -> OK | T36: =IF(ROUND(SUM(IS!P36:S36),1)=ROUND(IS!T36,1),"OK","ERROR") -> OK | Z36: =IF(ROUND(SUM(IS!V36:Y36),1)=ROUND(IS!Z36,1),"OK","ERROR") -> OK | AF36: =IF(ROUND(SUM(IS!AB36:AE36),1)=ROUND(IS!AF36,1),"OK","ERROR") -> OK | AL36: =IF(ROUND(SUM(IS!AH36:AK36),1)=ROUND(IS!AL36,1),"OK","ERROR") -> ERROR | AR36: =IF(ROUND(SUM(IS!AN36:AQ36),1)=ROUND(IS!AR36,1),"OK","ERROR") -> OK
B37: Interest income | H37: =IF(ROUND(SUM(IS!D37:G37),1)=ROUND(IS!H37,1),"OK","ERROR") -> OK | N37: =IF(ROUND(SUM(IS!J37:M37),1)=ROUND(IS!N37,1),"OK","ERROR") -> OK | T37: =IF(ROUND(SUM(IS!P37:S37),1)=ROUND(IS!T37,1),"OK","ERROR") -> OK | Z37: =IF(ROUND(SUM(IS!V37:Y37),1)=ROUND(IS!Z37,1),"OK","ERROR") -> OK | AF37: =IF(ROUND(SUM(IS!AB37:AE37),1)=ROUND(IS!AF37,1),"OK","ERROR") -> OK | AL37: =IF(ROUND(SUM(IS!AH37:AK37),1)=ROUND(IS!AL37,1),"OK","ERROR") -> OK | AR37: =IF(ROUND(SUM(IS!AN37:AQ37),1)=ROUND(IS!AR37,1),"OK","ERROR") -> OK
A38: x | B38: Net interest (income) expense | H38: =IF(ROUND(SUM(IS!D38:G38),1)=ROUND(IS!H38,1),"OK","ERROR") -> OK | N38: =IF(ROUND(SUM(IS!J38:M38),1)=ROUND(IS!N38,1),"OK","ERROR") -> OK | T38: =IF(ROUND(SUM(IS!P38:S38),1)=ROUND(IS!T38,1),"OK","ERROR") -> OK | Z38: =IF(ROUND(SUM(IS!V38:Y38),1)=ROUND(IS!Z38,1),"OK","ERROR") -> OK | AF38: =IF(ROUND(SUM(IS!AB38:AE38),1)=ROUND(IS!AF38,1),"OK","ERROR") -> OK | AL38: =IF(ROUND(SUM(IS!AH38:AK38),1)=ROUND(IS!AL38,1),"OK","ERROR") -> ERROR | AR38: =IF(ROUND(SUM(IS!AN38:AQ38),1)=ROUND(IS!AR38,1),"OK","ERROR") -> OK
B39: Foreign exchange (gains) losses | H39: =IF(ROUND(SUM(IS!D39:G39),1)=ROUND(IS!H39,1),"OK","ERROR") -> OK | N39: =IF(ROUND(SUM(IS!J39:M39),1)=ROUND(IS!N39,1),"OK","ERROR") -> OK | T39: =IF(ROUND(SUM(IS!P39:S39),1)=ROUND(IS!T39,1),"OK","ERROR") -> OK | Z39: =IF(ROUND(SUM(IS!V39:Y39),1)=ROUND(IS!Z39,1),"OK","ERROR") -> OK | AF39: =IF(ROUND(SUM(IS!AB39:AE39),1)=ROUND(IS!AF39,1),"OK","ERROR") -> OK | AL39: =IF(ROUND(SUM(IS!AH39:AK39),1)=ROUND(IS!AL39,1),"OK","ERROR") -> OK | AR39: =IF(ROUND(SUM(IS!AN39:AQ39),1)=ROUND(IS!AR39,1),"OK","ERROR") -> OK
B40: Other non-operating (income) expenses | H40: =IF(ROUND(SUM(IS!D40:G40),1)=ROUND(IS!H40,1),"OK","ERROR") -> OK | N40: =IF(ROUND(SUM(IS!J40:M40),1)=ROUND(IS!N40,1),"OK","ERROR") -> OK | T40: =IF(ROUND(SUM(IS!P40:S40),1)=ROUND(IS!T40,1),"OK","ERROR") -> OK | Z40: =IF(ROUND(SUM(IS!V40:Y40),1)=ROUND(IS!Z40,1),"OK","ERROR") -> OK | AF40: =IF(ROUND(SUM(IS!AB40:AE40),1)=ROUND(IS!AF40,1),"OK","ERROR") -> OK | AL40: =IF(ROUND(SUM(IS!AH40:AK40),1)=ROUND(IS!AL40,1),"OK","ERROR") -> ERROR | AR40: =IF(ROUND(SUM(IS!AN40:AQ40),1)=ROUND(IS!AR40,1),"OK","ERROR") -> OK
B41: Total non-operating expenses | H41: =IF(ROUND(SUM(IS!D41:G41),1)=ROUND(IS!H41,1),"OK","ERROR") -> OK | N41: =IF(ROUND(SUM(IS!J41:M41),1)=ROUND(IS!N41,1),"OK","ERROR") -> OK | T41: =IF(ROUND(SUM(IS!P41:S41),1)=ROUND(IS!T41,1),"OK","ERROR") -> OK | Z41: =IF(ROUND(SUM(IS!V41:Y41),1)=ROUND(IS!Z41,1),"OK","ERROR") -> OK | AF41: =IF(ROUND(SUM(IS!AB41:AE41),1)=ROUND(IS!AF41,1),"OK","ERROR") -> OK | AL41: =IF(ROUND(SUM(IS!AH41:AK41),1)=ROUND(IS!AL41,1),"OK","ERROR") -> ERROR | AR41: =IF(ROUND(SUM(IS!AN41:AQ41),1)=ROUND(IS!AR41,1),"OK","ERROR") -> OK
B42: Pre-tax income | H42: =IF(ROUND(SUM(IS!D42:G42),1)=ROUND(IS!H42,1),"OK","ERROR") -> OK | N42: =IF(ROUND(SUM(IS!J42:M42),1)=ROUND(IS!N42,1),"OK","ERROR") -> OK | T42: =IF(ROUND(SUM(IS!P42:S42),1)=ROUND(IS!T42,1),"OK","ERROR") -> OK | Z42: =IF(ROUND(SUM(IS!V42:Y42),1)=ROUND(IS!Z42,1),"OK","ERROR") -> OK | AF42: =IF(ROUND(SUM(IS!AB42:AE42),1)=ROUND(IS!AF42,1),"OK","ERROR") -> OK | AL42: =IF(ROUND(SUM(IS!AH42:AK42),1)=ROUND(IS!AL42,1),"OK","ERROR") -> ERROR | AR42: =IF(ROUND(SUM(IS!AN42:AQ42),1)=ROUND(IS!AR42,1),"OK","ERROR") -> OK
A44: x | B44: Tax & net income:
B45: Income tax expenses (benefits) | H45: =IF(ROUND(SUM(IS!D45:G45),1)=ROUND(IS!H45,1),"OK","ERROR") -> OK | N45: =IF(ROUND(SUM(IS!J45:M45),1)=ROUND(IS!N45,1),"OK","ERROR") -> OK | T45: =IF(ROUND(SUM(IS!P45:S45),1)=ROUND(IS!T45,1),"OK","ERROR") -> OK | Z45: =IF(ROUND(SUM(IS!V45:Y45),1)=ROUND(IS!Z45,1),"OK","ERROR") -> OK | AF45: =IF(ROUND(SUM(IS!AB45:AE45),1)=ROUND(IS!AF45,1),"OK","ERROR") -> OK | AL45: =IF(ROUND(SUM(IS!AH45:AK45),1)=ROUND(IS!AL45,1),"OK","ERROR") -> ERROR | AR45: =IF(ROUND(SUM(IS!AN45:AQ45),1)=ROUND(IS!AR45,1),"OK","ERROR") -> OK
B46: Net extraordinary losses (gains) | H46: =IF(ROUND(SUM(IS!D46:G46),1)=ROUND(IS!H46,1),"OK","ERROR") -> OK | N46: =IF(ROUND(SUM(IS!J46:M46),1)=ROUND(IS!N46,1),"OK","ERROR") -> OK | T46: =IF(ROUND(SUM(IS!P46:S46),1)=ROUND(IS!T46,1),"OK","ERROR") -> OK | Z46: =IF(ROUND(SUM(IS!V46:Y46),1)=ROUND(IS!Z46,1),"OK","ERROR") -> OK | AF46: =IF(ROUND(SUM(IS!AB46:AE46),1)=ROUND(IS!AF46,1),"OK","ERROR") -> OK | AL46: =IF(ROUND(SUM(IS!AH46:AK46),1)=ROUND(IS!AL46,1),"OK","ERROR") -> OK | AR46: =IF(ROUND(SUM(IS!AN46:AQ46),1)=ROUND(IS!AR46,1),"OK","ERROR") -> OK
B47: Net income including minority interest | H47: =IF(ROUND(SUM(IS!D47:G47),1)=ROUND(IS!H47,1),"OK","ERROR") -> OK | N47: =IF(ROUND(SUM(IS!J47:M47),1)=ROUND(IS!N47,1),"OK","ERROR") -> OK | T47: =IF(ROUND(SUM(IS!P47:S47),1)=ROUND(IS!T47,1),"OK","ERROR") -> OK | Z47: =IF(ROUND(SUM(IS!V47:Y47),1)=ROUND(IS!Z47,1),"OK","ERROR") -> OK | AF47: =IF(ROUND(SUM(IS!AB47:AE47),1)=ROUND(IS!AF47,1),"OK","ERROR") -> ERROR | AL47: =IF(ROUND(SUM(IS!AH47:AK47),1)=ROUND(IS!AL47,1),"OK","ERROR") -> ERROR | AR47: =IF(ROUND(SUM(IS!AN47:AQ47),1)=ROUND(IS!AR47,1),"OK","ERROR") -> OK
A49: x | B49: Attribution:
B50: Preferred dividends | H50: =IF(ROUND(SUM(IS!D50:G50),1)=ROUND(IS!H50,1),"OK","ERROR") -> OK | N50: =IF(ROUND(SUM(IS!J50:M50),1)=ROUND(IS!N50,1),"OK","ERROR") -> OK | T50: =IF(ROUND(SUM(IS!P50:S50),1)=ROUND(IS!T50,1),"OK","ERROR") -> OK | Z50: =IF(ROUND(SUM(IS!V50:Y50),1)=ROUND(IS!Z50,1),"OK","ERROR") -> OK | AF50: =IF(ROUND(SUM(IS!AB50:AE50),1)=ROUND(IS!AF50,1),"OK","ERROR") -> OK | AL50: =IF(ROUND(SUM(IS!AH50:AK50),1)=ROUND(IS!AL50,1),"OK","ERROR") -> OK | AR50: =IF(ROUND(SUM(IS!AN50:AQ50),1)=ROUND(IS!AR50,1),"OK","ERROR") -> OK
B51: Income attributable to non-controlling interests | H51: =IF(ROUND(SUM(IS!D51:G51),1)=ROUND(IS!H51,1),"OK","ERROR") -> OK | N51: =IF(ROUND(SUM(IS!J51:M51),1)=ROUND(IS!N51,1),"OK","ERROR") -> OK | T51: =IF(ROUND(SUM(IS!P51:S51),1)=ROUND(IS!T51,1),"OK","ERROR") -> OK | Z51: =IF(ROUND(SUM(IS!V51:Y51),1)=ROUND(IS!Z51,1),"OK","ERROR") -> OK | AF51: =IF(ROUND(SUM(IS!AB51:AE51),1)=ROUND(IS!AF51,1),"OK","ERROR") -> OK | AL51: =IF(ROUND(SUM(IS!AH51:AK51),1)=ROUND(IS!AL51,1),"OK","ERROR") -> ERROR | AR51: =IF(ROUND(SUM(IS!AN51:AQ51),1)=ROUND(IS!AR51,1),"OK","ERROR") -> OK
B52: Net income attributable to common shareholders | H52: =IF(ROUND(SUM(IS!D52:G52),1)=ROUND(IS!H52,1),"OK","ERROR") -> OK | N52: =IF(ROUND(SUM(IS!J52:M52),1)=ROUND(IS!N52,1),"OK","ERROR") -> OK | T52: =IF(ROUND(SUM(IS!P52:S52),1)=ROUND(IS!T52,1),"OK","ERROR") -> OK | Z52: =IF(ROUND(SUM(IS!V52:Y52),1)=ROUND(IS!Z52,1),"OK","ERROR") -> OK | AF52: =IF(ROUND(SUM(IS!AB52:AE52),1)=ROUND(IS!AF52,1),"OK","ERROR") -> ERROR | AL52: =IF(ROUND(SUM(IS!AH52:AK52),1)=ROUND(IS!AL52,1),"OK","ERROR") -> ERROR | AR52: =IF(ROUND(SUM(IS!AN52:AQ52),1)=ROUND(IS!AR52,1),"OK","ERROR") -> OK
A54: x | B54: Earnings per share:
B55: EPS basic | H55: =IF(ROUND(AVERAGE(IS!D55:G55),0)-ROUND(IS!H55,0)<0.01*ROUND(IS!H55,0),"OK","ERROR") -> ERROR | N55: =IF(ROUND(AVERAGE(IS!J55:M55),0)-ROUND(IS!N55,0)<0.01*ROUND(IS!N55,0),"OK","ERROR") -> ERROR | T55: =IF(ROUND(AVERAGE(IS!P55:S55),0)-ROUND(IS!T55,0)<0.01*ROUND(IS!T55,0),"OK","ERROR") -> ERROR | Z55: =IF(ROUND(AVERAGE(IS!V55:Y55),0)-ROUND(IS!Z55,0)<0.01*ROUND(IS!Z55,0),"OK","ERROR") -> ERROR | AF55: =IF(ROUND(AVERAGE(IS!AB55:AE55),0)-ROUND(IS!AF55,0)<0.01*ROUND(IS!AF55,0),"OK","ERROR") -> ERROR | AL55: =IF(ROUND(AVERAGE(IS!AH55:AK55),0)-ROUND(IS!AL55,0)<0.01*ROUND(IS!AL55,0),"OK","ERROR") -> ERROR | AR55: =IF(ROUND(AVERAGE(IS!AN55:AQ55),0)-ROUND(IS!AR55,0)<0.01*ROUND(IS!AR55,0),"OK","ERROR") -> #DIV/0!
B56: EPS diluted | H56: =IF(ROUND(AVERAGE(IS!D56:G56),0)-ROUND(IS!H56,0)<0.01*ROUND(IS!H56,0),"OK","ERROR") -> ERROR | N56: =IF(ROUND(AVERAGE(IS!J56:M56),0)-ROUND(IS!N56,0)<0.01*ROUND(IS!N56,0),"OK","ERROR") -> ERROR | T56: =IF(ROUND(AVERAGE(IS!P56:S56),0)-ROUND(IS!T56,0)<0.01*ROUND(IS!T56,0),"OK","ERROR") -> ERROR | Z56: =IF(ROUND(AVERAGE(IS!V56:Y56),0)-ROUND(IS!Z56,0)<0.01*ROUND(IS!Z56,0),"OK","ERROR") -> ERROR | AF56: =IF(ROUND(AVERAGE(IS!AB56:AE56),0)-ROUND(IS!AF56,0)<0.01*ROUND(IS!AF56,0),"OK","ERROR") -> ERROR | AL56: =IF(ROUND(AVERAGE(IS!AH56:AK56),0)-ROUND(IS!AL56,0)<0.01*ROUND(IS!AL56,0),"OK","ERROR") -> ERROR | AR56: =IF(ROUND(AVERAGE(IS!AN56:AQ56),0)-ROUND(IS!AR56,0)<0.01*ROUND(IS!AR56,0),"OK","ERROR") -> #DIV/0!
A58: x | B58: Shares used in computing earnings per share:
B59: Basic weighted average shares | H59: =IF(ROUND(AVERAGE(IS!D59:G59),0)-ROUND(IS!H59,0)<0.01*ROUND(IS!H59,0),"OK","ERROR") -> ERROR | N59: =IF(ROUND(AVERAGE(IS!J59:M59),0)-ROUND(IS!N59,0)<0.01*ROUND(IS!N59,0),"OK","ERROR") -> OK | T59: =IF(ROUND(AVERAGE(IS!P59:S59),0)-ROUND(IS!T59,0)<0.01*ROUND(IS!T59,0),"OK","ERROR") -> OK | Z59: =IF(ROUND(AVERAGE(IS!V59:Y59),0)-ROUND(IS!Z59,0)<0.01*ROUND(IS!Z59,0),"OK","ERROR") -> OK | AF59: =IF(ROUND(AVERAGE(IS!AB59:AE59),0)-ROUND(IS!AF59,0)<0.01*ROUND(IS!AF59,0),"OK","ERROR") -> OK | AL59: =IF(ROUND(AVERAGE(IS!AH59:AK59),0)-ROUND(IS!AL59,0)<0.01*ROUND(IS!AL59,0),"OK","ERROR") -> ERROR | AR59: =IF(ROUND(AVERAGE(IS!AN59:AQ59),0)-ROUND(IS!AR59,0)<0.01*ROUND(IS!AR59,0),"OK","ERROR") -> #DIV/0!
B60: Diluted weighted average shares | H60: =IF(ROUND(AVERAGE(IS!D60:G60),0)-ROUND(IS!H60,0)<0.01*ROUND(IS!H60,0),"OK","ERROR") -> ERROR | N60: =IF(ROUND(AVERAGE(IS!J60:M60),0)-ROUND(IS!N60,0)<0.01*ROUND(IS!N60,0),"OK","ERROR") -> OK | T60: =IF(ROUND(AVERAGE(IS!P60:S60),0)-ROUND(IS!T60,0)<0.01*ROUND(IS!T60,0),"OK","ERROR") -> OK | Z60: =IF(ROUND(AVERAGE(IS!V60:Y60),0)-ROUND(IS!Z60,0)<0.01*ROUND(IS!Z60,0),"OK","ERROR") -> OK | AF60: =IF(ROUND(AVERAGE(IS!AB60:AE60),0)-ROUND(IS!AF60,0)<0.01*ROUND(IS!AF60,0),"OK","ERROR") -> OK | AL60: =IF(ROUND(AVERAGE(IS!AH60:AK60),0)-ROUND(IS!AL60,0)<0.01*ROUND(IS!AL60,0),"OK","ERROR") -> ERROR | AR60: =IF(ROUND(AVERAGE(IS!AN60:AQ60),0)-ROUND(IS!AR60,0)<0.01*ROUND(IS!AR60,0),"OK","ERROR") -> #DIV/0!
B62: Income Statement - Metrics | D62: =F62 -> 2020 | E62: =F62 -> 2020 | F62: 2020 | G62: =F62 -> 2020 | H62: =F62 -> 2020 | J62: =L62 -> 2021 | K62: =L62 -> 2021 | L62: 2021 | M62: =L62 -> 2021 | N62: =L62 -> 2021 | P62: =R62 -> 2022 | Q62: =R62 -> 2022 | R62: 2022 | S62: =R62 -> 2022 | T62: =R62 -> 2022 | V62: =X62 -> 2023 | W62: =X62 -> 2023 | X62: 2023 | Y62: =X62 -> 2023 | Z62: =X62 -> 2023 | AB62: =AD62 -> 2024 | AC62: =AD62 -> 2024 | AD62: 2024 | AE62: =AD62 -> 2024 | AF62: =AD62 -> 2024 | AH62: =AJ62 -> 2025 | AI62: =AJ62 -> 2025 | AJ62: 2025 | AK62: =AJ62 -> 2025 | AL62: =AJ62 -> 2025 | AN62: =AP62 -> 2025 | AO62: =AP62 -> 2025 | AP62: 2025 | AQ62: =AP62 -> 2025 | AR62: =AP62 -> 2025
D63: 2020 | J63: =D63+1 -> 2021 | P63: =J63+1 -> 2022 | V63: =P63+1 -> 2023 | AB63: =V63+1 -> 2024 | AH63: =AB63+1 -> 2025 | AN63: =AH63+1 -> 2026 | AT63: =AN63+1 -> 2027 | AV63: =+AT63+1 -> 2028 | AX63: =+AV63+1 -> 2029
D64: Q1 | E64: Q2 | F64: Q3 | G64: Q4 | H64: FY | J64: Q1 | K64: Q2 | L64: Q3 | M64: Q4 | N64: FY | P64: Q1 | Q64: Q2 | R64: Q3 | S64: Q4 | T64: FY | V64: Q1 | W64: Q2 | X64: Q3 | Y64: Q4 | Z64: FY | AB64: Q1 | AC64: Q2 | AD64: Q3 | AE64: Q4 | AF64: FY | AH64: Q1 | AI64: Q2 | AJ64: Q3 | AK64: Q4 | AL64: FY | AN64: Q1 | AO64: Q2 | AP64: Q3 | AQ64: Q4 | AR64: FY | AT64: FY | AV64: FY | AX64: FY
A67: x | B67: Revenue:
B68: Total revenue | D68: =IF(ROUND(SUM(IS!D13:D17),0)=IS!D18,"OK","ERROR") -> ERROR | E68: =IF(ROUND(SUM(IS!E13:E17),0)=IS!E18,"OK","ERROR") -> ERROR | F68: =IF(ROUND(SUM(IS!F13:F17),0)=IS!F18,"OK","ERROR") -> ERROR | G68: =IF(ROUND(SUM(IS!G13:G17),0)=IS!G18,"OK","ERROR") -> ERROR | H68: =IF(ROUND(SUM(IS!H13:H17),0)=IS!H18,"OK","ERROR") -> OK | J68: =IF(ROUND(SUM(IS!J13:J17),0)=IS!J18,"OK","ERROR") -> ERROR | K68: =IF(ROUND(SUM(IS!K13:K17),0)=IS!K18,"OK","ERROR") -> ERROR | L68: =IF(ROUND(SUM(IS!L13:L17),0)=IS!L18,"OK","ERROR") -> ERROR | M68: =IF(ROUND(SUM(IS!M13:M17),0)=IS!M18,"OK","ERROR") -> ERROR | N68: =IF(ROUND(SUM(IS!N13:N17),0)=IS!N18,"OK","ERROR") -> OK | P68: =IF(ROUND(SUM(IS!P13:P17),0)=IS!P18,"OK","ERROR") -> ERROR | Q68: =IF(ROUND(SUM(IS!Q13:Q17),0)=IS!Q18,"OK","ERROR") -> ERROR | R68: =IF(ROUND(SUM(IS!R13:R17),0)=IS!R18,"OK","ERROR") -> ERROR | S68: =IF(ROUND(SUM(IS!S13:S17),0)=IS!S18,"OK","ERROR") -> ERROR | T68: =IF(ROUND(SUM(IS!T13:T17),0)=IS!T18,"OK","ERROR") -> ERROR | V68: =IF(ROUND(SUM(IS!V13:V17),0)=IS!V18,"OK","ERROR") -> ERROR | W68: =IF(ROUND(SUM(IS!W13:W17),0)=IS!W18,"OK","ERROR") -> ERROR | X68: =IF(ROUND(SUM(IS!X13:X17),0)=IS!X18,"OK","ERROR") -> ERROR | Y68: =IF(ROUND(SUM(IS!Y13:Y17),0)=IS!Y18,"OK","ERROR") -> ERROR | Z68: =IF(ROUND(SUM(IS!Z13:Z17),0)=IS!Z18,"OK","ERROR") -> ERROR | AB68: =IF(ROUND(SUM(IS!AB13:AB17),0)=IS!AB18,"OK","ERROR") -> ERROR | AC68: =IF(ROUND(SUM(IS!AC13:AC17),0)=IS!AC18,"OK","ERROR") -> ERROR | AD68: =IF(ROUND(SUM(IS!AD13:AD17),0)=IS!AD18,"OK","ERROR") -> ERROR | AE68: =IF(ROUND(SUM(IS!AE13:AE17),0)=IS!AE18,"OK","ERROR") -> ERROR | AF68: =IF(ROUND(SUM(IS!AF13:AF17),0)=IS!AF18,"OK","ERROR") -> ERROR | AH68: =IF(ROUND(SUM(IS!AH13:AH17),0)=IS!AH18,"OK","ERROR") -> OK | AI68: =IF(ROUND(SUM(IS!AI13:AI17),0)=IS!AI18,"OK","ERROR") -> OK | AJ68: =IF(ROUND(SUM(IS!AJ13:AJ17),0)=IS!AJ18,"OK","ERROR") -> ERROR | AK68: =IF(ROUND(SUM(IS!AK13:AK17),0)=IS!AK18,"OK","ERROR") -> ERROR | AL68: =IF(ROUND(SUM(IS!AL13:AL17),0)=IS!AL18,"OK","ERROR") -> ERROR | AN68: =IF(ROUND(SUM(IS!AN13:AN17),0)=IS!AN18,"OK","ERROR") -> ERROR | AO68: =IF(ROUND(SUM(IS!AO13:AO17),0)=IS!AO18,"OK","ERROR") -> ERROR | AP68: =IF(ROUND(SUM(IS!AP13:AP17),0)=IS!AP18,"OK","ERROR") -> ERROR | AQ68: =IF(ROUND(SUM(IS!AQ13:AQ17),0)=IS!AQ18,"OK","ERROR") -> ERROR | AR68: =IF(ROUND(SUM(IS!AR13:AR17),0)=IS!AR18,"OK","ERROR") -> ERROR | AT68: =IF(ROUND(SUM(IS!AT13:AT17),0)=IS!AT18,"OK","ERROR") -> ERROR | AV68: =IF(ROUND(SUM(IS!AV13:AV17),0)=IS!AV18,"OK","ERROR") -> ERROR | AX68: =IF(ROUND(SUM(IS!AX13:AX17),0)=IS!AX18,"OK","ERROR") -> ERROR
A70: x | B70: Cost of revenue:
