Workbook
Name COOLFUCNTION: _xlfn.LAMBDA(_xldudf_BOARDFLARE_EXEC("workbook-settings:coolfucntion"))
Name COOLFUCNTION: _xlfn.LAMBDA(_xldudf_BOARDFLARE_EXEC("workbook-settings:coolfucntion"))
Name COOLFUCNTION: _xlfn.LAMBDA(_xldudf_BOARDFLARE_EXEC("workbook-settings:coolfucntion"))
Name COOLFUCNTION: _xlfn.LAMBDA(_xldudf_BOARDFLARE_EXEC("workbook-settings:coolfucntion"))
Name COOLFUCNTION: _xlfn.LAMBDA(_xldudf_BOARDFLARE_EXEC("workbook-settings:coolfucntion"))
Name COOLFUCNTION: _xlfn.LAMBDA(_xldudf_BOARDFLARE_EXEC("workbook-settings:coolfucntion"))
Name COOLFUCNTION: _xlfn.LAMBDA(_xldudf_BOARDFLARE_EXEC("workbook-settings:coolfucntion"))
Name COOLFUCNTION: _xlfn.LAMBDA(_xldudf_BOARDFLARE_EXEC("workbook-settings:coolfucntion"))
Name COOLFUCNTION: _xlfn.LAMBDA(_xldudf_BOARDFLARE_EXEC("workbook-settings:coolfucntion"))
Name COOLFUCNTION: _xlfn.LAMBDA(_xldudf_BOARDFLARE_EXEC("workbook-settings:coolfucntion"))
Name COOLFUCNTION: _xlfn.LAMBDA(_xldudf_BOARDFLARE_EXEC("workbook-settings:coolfucntion"))
Name Sectors: #REF!
Name Sectors: #REF!
Name Sectors: #REF!
Name Sectors: #REF!
Name Sectors: #REF!
Name Sectors: #REF!
Name Sectors: #REF!
Name Sectors: #REF!

Sheet Dashboard
C154: =+C155+1 -> 45984
C155: =+C156+1 -> 45983
C156: =+C157+1 -> 45982
C157: =+C158+1 -> 45981
C158: =+C159+1 -> 45980
C159: =+C160+1 -> 45979
C160: =+C161+1 -> 45978 | L160: =IF(FCFF!$R$165="Revenue Exit",FCFF!$AF$177,IF(FCFF!$R$165="EBITDA Exit",FCFF!Z177,FCFF!AL177)) -> #NAME?
C161: =+C162+1 -> 45977
C162: =+C163+1 -> 45976 | E162: =IF(FCFF!$R$165="Revenue Exit",FCFF!$AF$177,IF(FCFF!$R$165="EBITDA Exit",FCFF!Z177,FCFF!AL177)) -> #NAME?
C163: =+C164+1 -> 45975 | E163: =E164+($E$162-$E$193)/COUNTA($C$162:$C$192) -> #NAME?
C164: =+C165+1 -> 45974 | E164: =E165+($E$162-$E$193)/COUNTA($C$162:$C$192) -> #NAME?
C165: =+C166+1 -> 45973 | E165: =E166+($E$162-$E$193)/COUNTA($C$162:$C$192) -> #NAME?
C166: =+C167+1 -> 45972 | E166: =E167+($E$162-$E$193)/COUNTA($C$162:$C$192) -> #NAME?
C167: =+C168+1 -> 45971 | E167: =E168+($E$162-$E$193)/COUNTA($C$162:$C$192) -> #NAME?
C168: =+C169+1 -> 45970 | E168: =E169+($E$162-$E$193)/COUNTA($C$162:$C$192) -> #NAME?
C169: =+C170+1 -> 45969 | E169: =E170+($E$162-$E$193)/COUNTA($C$162:$C$192) -> #NAME?
C170: =+C171+1 -> 45968 | E170: =E171+($E$162-$E$193)/COUNTA($C$162:$C$192) -> #NAME?
C171: =+C172+1 -> 45967 | E171: =E172+($E$162-$E$193)/COUNTA($C$162:$C$192) -> #NAME?
C172: =+C173+1 -> 45966 | E172: =E173+($E$162-$E$193)/COUNTA($C$162:$C$192) -> #NAME?
C173: =+C174+1 -> 45965 | E173: =E174+($E$162-$E$193)/COUNTA($C$162:$C$192) -> #NAME?
C174: =+C175+1 -> 45964 | E174: =E175+($E$162-$E$193)/COUNTA($C$162:$C$192) -> #NAME?
... C192: =+C193+1 -> 45946 | E192: =E193+($E$162-$E$193)/COUNTA($C$162:$C$192) -> #NAME?
B193: TODAY | C193: =+'Stock Data'!AM4 -> 45945 | D193: =_xlfn.XLOOKUP(C193,'Stock Data'!$AM$4:$AM$1051,'Stock Data'!$AN$4:$AN$1051) -> 141.83 | E193: =D193 -> 141.83
C194: =+'Stock Data'!AM5 -> 45944 | D194: =_xlfn.XLOOKUP(C194,'Stock Data'!$AM$4:$AM$1051,'Stock Data'!$AN$4:$AN$1051) -> 141.83
C195: =+'Stock Data'!AM6 -> 45943 | D195: =_xlfn.XLOOKUP(C195,'Stock Data'!$AM$4:$AM$1051,'Stock Data'!$AN$4:$AN$1051) -> 144.43
C196: =+'Stock Data'!AM7 -> 45942 | D196: =_xlfn.XLOOKUP(C196,'Stock Data'!$AM$4:$AM$1051,'Stock Data'!$AN$4:$AN$1051) -> 144.43
C197: =+'Stock Data'!AM8 -> 45941 | D197: =_xlfn.XLOOKUP(C197,'Stock Data'!$AM$4:$AM$1051,'Stock Data'!$AN$4:$AN$1051) -> 144.43
C198: =+'Stock Data'!AM9 -> 45940 | D198: =_xlfn.XLOOKUP(C198,'Stock Data'!$AM$4:$AM$1051,'Stock Data'!$AN$4:$AN$1051) -> 141.81
C199: =+'Stock Data'!AM10 -> 45939 | D199: =_xlfn.XLOOKUP(C199,'Stock Data'!$AM$4:$AM$1051,'Stock Data'!$AN$4:$AN$1051) -> 135.64
C200: =+'Stock Data'!AM11 -> 45938 | D200: =_xlfn.XLOOKUP(C200,'Stock Data'!$AM$4:$AM$1051,'Stock Data'!$AN$4:$AN$1051) -> 137.37
C201: =+'Stock Data'!AM12 -> 45937 | D201: =_xlfn.XLOOKUP(C201,'Stock Data'!$AM$4:$AM$1051,'Stock Data'!$AN$4:$AN$1051) -> 136.85
C202: =+'Stock Data'!AM13 -> 45936 | D202: =_xlfn.XLOOKUP(C202,'Stock Data'!$AM$4:$AM$1051,'Stock Data'!$AN$4:$AN$1051) -> 136.85
C203: =+'Stock Data'!AM14 -> 45935 | D203: =_xlfn.XLOOKUP(C203,'Stock Data'!$AM$4:$AM$1051,'Stock Data'!$AN$4:$AN$1051) -> 136.85
C204: =+'Stock Data'!AM15 -> 45934 | D204: =_xlfn.XLOOKUP(C204,'Stock Data'!$AM$4:$AM$1051,'Stock Data'!$AN$4:$AN$1051) -> 136.85
C205: =+'Stock Data'!AM16 -> 45933 | D205: =_xlfn.XLOOKUP(C205,'Stock Data'!$AM$4:$AM$1051,'Stock Data'!$AN$4:$AN$1051) -> 136.84
... C558: =+'Stock Data'!AM369 -> 45580 | D558: =_xlfn.XLOOKUP(C558,'Stock Data'!$AM$4:$AM$1051,'Stock Data'!$AN$4:$AN$1051) -> 131.81

Sheet Key Info
B7: Analysts | F7: LIS – Equity Research | J7: Stock Performance
B12: Ana Luiza Costa, Team Leader | F12: Recommendation: | H12: Hold
B13: Bsc in Economics, ISEG – Ulisboa | F13: Target Price (FCFF): | H13: =FCFF!AL177 -> #NAME?
B14: analuiza@aln.iseg.ulisboa.pt | F14: Upside(Downside): | H14: =FCFF!AL179 -> #NAME?
B15: John Stavale, Analyst
B16: Bsc in Economics, ISEG – Ulisboa | F16: Ticker | H16: MIDD
B17: johnstavale@aln.iseg.ulisboa.pt | F17: Stock Exchange | H17: NASDAQ
B18: Manuel Jáco, Analyst
B19: Bsc in MAEG, ISEG – Ulisboa | F19: Current Price | H19: ='Stock Data'!AN4 -> 141.83
B20: manueljaco@aln.iseg.ulisboa.pt | F20: ="Market Cap (in "&IF(Inputs!$D$14="BLN","billions",IF(Inputs!$D$14="MLN","millions","thousands"))&")" -> Market Cap (in thousands) | H20: ='Stock Data'!AQ4 -> 7188282.8
F21: Beta | H21: ='Stock Data'!E164 -> 0.98372155
F22: % of 52-Week High | H22: ='Stock Data'!E165 -> 0.24535887
F23: 100-Day Moving Average | H23: ='Stock Data'!E166 -> 141.4245
B25: Reviewed by: | F25: Avg Vol (1 month) | H25: ='Stock Data'!E168 -> 1068818.6
B26: NAME, Analyst | F26: Shares Outstanding (millions) | H26: ='Stock Data'!E169 -> 50.68239
B27: Bsc in XXX, ISEG – Ulisboa | F27: % Float | H27: ='Stock Data'!E170 -> 0.9198911
B28: email@aln.iseg.ulisboa.pt | F28: Short % of Float | H28: =IFERROR('Stock Data'!E171,0) -> 0.06098394
B30: LISBON INVESTMENT SOCIETY | F30: % Held by Insiders | H30: ='Stock Data'!E173 -> 0.015432757
B31: ISEG – Rua do Quelhas, 6 | F31: % Held by Institutions | H31: ='Stock Data'!E174 -> 1.2342792
B32: lis@iseg.ulisboa.pt
B34: Disclaimer: This report was prepared by members of the Lisbon Investment Society (LIS), an independent, student-led, non-profit organization based at ISEG – Lisbon School of Economics & Management, and is intended solely for academic and educational purposes. All analyses, forecasts, and opinions expressed in this report reflect the independent judgment of the authors as of the date of publication and are subject to change without notice. The views presented herein do not represent those of ISEG, its faculty, or any affiliated entity. This document does not constitute, and should not be interpreted as, investment advice, an offer, or a solicitation to buy or sell any security or financial instrument. Nothing in this report should be construed as a recommendation to make or refrain from making any investment decision. The content is intended for informational purposes only, and readers are strongly encouraged to conduct their own research and seek advice from a qualified financial professional before making any financial decisions. The information contained in this report has been obtained from publicly available sources believed to be reliable; however, no representation or warranty is made regarding the accuracy, completeness, or timeliness of such information. LIS and its members accept no liability whatsoever for any direct or indirect loss arising from the use of this report or its contents. This report incorporates terminology, financial metrics, and methodologies commonly used in professional equity research, including but not limited to Discounted Cash Flow (DCF), trading multiples, Monte Carlo simulations, and strategic analysis tools such as Porter’s Five Forces. Definitions and assumptions used in these models are disclosed within the report and reflect a hypothetical investment thesis designed solely for academic discussion. All valuations, projections, and target prices presented herein are based on publicly available data and subject to the limitations of modeling assumptions. These are not guarantees of future performance and should not be relied upon as such, as past performance is not indicative of future results. Any company names, logos, trademarks, or brand references mentioned in this report are the property of their respective owners and are used strictly for identification and academic purposes. This document may not be reproduced, redistributed, or quoted in whole or in part without the prior written consent of the Lisbon Investment Society. About LIS – Lisbon Investment Society: The Lisbon Investment Society (LIS) is a non-profit academic association headquartered at ISEG – Lisbon School of Economics & Management. Founded in 2016, LIS is committed to fostering student interest in finance and investment through applied research, skill development, and institutional engagement. The Society operates independently and autonomously from any political, religious, or commercial affiliation, and is composed of selected students and collaborators who are invited through a rigorous recruitment process and share a commitment to excellence, analytical rigor, and ethical standards. Its activities include equity research, portfolio management, macroeconomic analysis, and investment education. This report was prepared by the Equity Research team at the Lisbon Investment Society, whose analysts combine rigorous financial modeling, critical thinking, and collaborative research to deliver high-quality, student-led investment analysis. We welcome your feedback, discussion, and questions regarding this report or our research process, and invite you to reach out to our team as we are always open to engagement.

Sheet Industry
D6: 584.17 | E6: 627.76 | F6: 676.06 | G6: 729.63 | H6: 789.13 | I6: 855.3 | J6: 929 | K6: 997.69 | L6: 1067.63 | M6: 1137.57
A7: x | B7: Industry Growth Forecast | O7: Industry Index
D9: 2022 | E9: =+D9+1 -> 2023 | F9: =+E9+1 -> 2024 | G9: =+F9+1 -> 2025 | H9: =+G9+1 -> 2026 | I9: =+H9+1 -> 2027 | J9: =+I9+1 -> 2028 | K9: =+J9+1 -> 2029 | M9: ="CAGR "&$G$9&" - "&$K$9 -> CAGR 2025 - 2029
B12: Market Size (Commercial Foodservice Machinery) | F12: 39071 | G12: =F12*(1+0.07) -> 41805.97 | H12: =G12*(1+0.07) -> 44732.388 | I12: =H12*(1+0.07) -> 47863.655 | J12: =I12*(1+0.07) -> 51214.111 | K12: =J12*(1+0.07) -> 54799.099 | M12: =(K12/G12)^(1/5)-1 -> 0.055618571 | X12: Global | Y12: North America
B13: Market Share | M13: =((K13*K12)/(G13*G12))^(1/5)-1 -> #DIV/0! | W13: Commercial Foodservice Machinery | X13: =M12 -> 0.055618571 | Y13: =M18 -> 0.02551911
B14: Market Size (Food Processing Machinery) | E14: 52690 | F14: =E14*(1+0.04) -> 54797.6 | G14: =F14*(1+0.04) -> 56989.504 | H14: =G14*(1+0.04) -> 59269.084 | I14: =H14*(1+0.04) -> 61639.848 | J14: =I14*(1+0.04) -> 64105.441 | K14: =J14*(1+0.04) -> 66669.659 | M14: =(K14/G14)^(1/5)-1 -> 0.031874004 | W14: Food Processing Machinery | X14: =M14 -> 0.031874004 | Y14: =M20 -> 0.02631401
B15: Market Share | M15: =((K15*K14)/(G15*G14))^(1/5)-1 -> #DIV/0! | W15: Household Kitchen Appliances | X15: =M16 -> 0.033461197 | Y15: =M22 -> 0.021542301
B16: Market Size (Household Kitchen Appliances) | F16: 269270 | G16: =F16*(1+0.042) -> 280579.34 | H16: =G16*(1+0.042) -> 292363.67 | I16: =H16*(1+0.042) -> 304642.95 | J16: =I16*(1+0.042) -> 317437.95 | K16: =J16*(1+0.042) -> 330770.34 | M16: =(K16/G16)^(1/5)-1 -> 0.033461197
B17: Market Share | M17: =((K17*K16)/(G17*G16))^(1/5)-1 -> #DIV/0!
B18: Market Size (NA Commercial Foodservice Machinery) | F18: 10738 | G18: =F18*(1+0.032) -> 11081.616 | H18: =G18*(1+0.032) -> 11436.228 | I18: =H18*(1+0.032) -> 11802.187 | J18: =I18*(1+0.032) -> 12179.857 | K18: =J18*(1+0.032) -> 12569.612 | M18: =(K18/G18)^(1/5)-1 -> 0.02551911
B19: Market Share | M19: =((K19*K18)/(G19*G18))^(1/5)-1 -> #DIV/0!
B20: Market Size (NA Food Processing Equipment) | D20: 9609 | E20: =D20*(1+0.033) -> 9926.097 | F20: =E20*(1+0.033) -> 10253.658 | G20: =F20*(1+0.033) -> 10592.029 | H20: =G20*(1+0.033) -> 10941.566 | I20: =H20*(1+0.033) -> 11302.638 | J20: =I20*(1+0.033) -> 11675.625 | K20: =J20*(1+0.033) -> 12060.92 | M20: =(K20/G20)^(1/5)-1 -> 0.02631401
B21: Market Share | M21: =((K21*K20)/(G21*G20))^(1/5)-1 -> #DIV/0!
B22: Market Size (NA Household Kitchen Appliances) | F22: 68120 | G22: =F22*(1+0.027) -> 69959.24 | H22: =G22*(1+0.027) -> 71848.139 | I22: =H22*(1+0.027) -> 73788.039 | J22: =I22*(1+0.027) -> 75780.316 | K22: =J22*(1+0.027) -> 77826.385 | M22: =(K22/G22)^(1/5)-1 -> 0.021542301
B23: Market Share | M23: =((K23*K22)/(G23*G22))^(1/5)-1 -> #DIV/0!
A25: x
B27: Industry Driver | D27: Description | O27: Porter's Five Forces
B29: Commercial Foodservice Machinery - net openings and equipments cycle | D29: Highly dependant on commercial foodservices openings (full and quick service restaurants) and equipments renewal, the industry benefits from decreasing interest rates and increasing consumer confidence and discretionary spending.
B30: Food Processing Machinery - demand for processed food | D30: Increasing demand for processed and ultra-processed food all over the world increases confidence on the industry growth, as more machinery and equipments will be required. APAC demand increase might be the highest, so a strong position would be highly rewarded. Supply chain optimizations may also be a competitive advantage, due to risks of distruption and dependance on commodities.
B31: Residential Kitchen Machinery - house constructions and renewals | D31: As long as there's a demand for house constructions and renewals, householders will need kitchen equipments. Therefore, lower interest rates, as well as higher GDP growth and employment rates and wages increase the demand for refurbished and new houses.
O34: Rivalry Among Existing Competitors | R34: 5
O35: Threat of New Entrants | R35: 2
O36: Threat of Substitutes | R36: 3
O37: Bargaining Power of Customers | R37: 3
O38: Bargaining Power of Suppliers | R38: 4

Sheet ESG
A7: x | B7: ESG Analysis
B12: ESG Scores | G12: GHG Scope 1 Emissions, Water Consumption, Energy Consumption and Waste Production per Sales
B15: LSEG ESG Score | D15: 55
B16: E-Score | D16: 37
B17: S-Score | D17: 46
B18: G-Score | D18: 88
B19: S&P Global ESG Score | D19: 26
B20: Sustainalytics | D20: 31.62
B21: ISS ESG Corporate Rating | D21: D+
B22: SDG Impact Rating | D22: -6.5
B23: Governance Quality Score | D23: 1
B24: MSCI ESG Ratings | D24: BBB
B30: Key Info | G30: Environmental
H32: Overview | I32: Targets | J32: Improvements | K32: Comments
B33: GICS Sector | C33: Industrials | G33: GHG Scope 1 Emissions | I33: Net-zero CO₂ emissions by 2050. | K33: Increase in Scope 1 and Scope 2 emissions from 2022 to 2023 due to business growth and the impact of additional Middleby locations reporting metrics.
B34: GICS Industry Group | C34: Capital Goods
B35: GICS Industry | C35: Machinery | G35: Water Consumption | J35: Slight decrease in Water Intensity (total water withdrawal per 1,000-square feet of facility) | K35: Reported water withdrawals in fiscal year 2023 increased slightly from the previous reporting year as a result of the acquisition of additional businesses and facilities.
B36: GICS Sub-Industry | C36: Special Industrial Machinery
G37: Energy Consumption | J37: Energy usage and GJ-intensity decreased in 2023 versus the previous year. | K37: Energy sources include Indirect Purchased Energy (Electrical Grid), Fuel Combustion, and Self-Generated Renewables (solar, wind, geothermal, bioenergy, hydro and tidal energy). Energy 1,
B38: Headquarters | C38: Elgin, Illinois, USA
B39: Numer of Employees | C39: 10616 | G39: Waste Management | J39: Available waste metrics point to a 16.2% decrease in hazardous waste in 2023 compared to 2022. | K39: Non-hazardous waste increased in 2023 compared to 2022, primarily as a result of acquisitions made of additional businesses and facilities while Waste Intensity decreased.
B41: Annual Report | C41: Form 10K 2024 | G41: Other
B42: Sustainability Report | C42: 2024 Sustainability Report Update
C43: 2023 Sustainability Report
B44: Recent Headlines | G44: Social
H46: Overview | I46: Targets | J46: Improvements | K46: Comments
G47: Employee Turnover % | K47: After a period of growth, Middleby's total number of employees decreased by 4.85% from 2022 to 2023, and by a further 0.99% from 2023 to 2024, ending at 10,616 in December 2024. The company does not disclose Employee Turnover rates.
G49: Salaries & Compensation | K49: Middleby employees attributed a compensation and benefits rating of 3.2/5 stars to their company on Glassdoor.
G51: Reputation
G53: Discrimination Events | K53: No reported discrimination events; standard EEO policies in place.
G55: Work Safety | K55: No recent confirmation of any major safety incidents involving worker injuries at Middleby in the last years from credible news or regulatory sources.
G57: Damage to consumer health | K57: 2017 Viking recall handled proactively as it strengthened product safety program in place with no major incidents since.
G59: Pension Plan | K59: The company does not offer a traditional defined benefit pension plan but instead provides a defined contribution plan,the Middleby Corporation Profit Sharing Plan, which functions as a 401(k) and a savings plan for eligible employees.
G61: Supply chain | K61: Middleby recognizes supply-chain risks and has a Supplier Code of Conduct.
G63: Community involvement | K63: Middleby engages communities via ‘Middleby Cares,’ donations, volunteering, and nonprofit partnerships.
G65: Public Sector | K65: Limited reliance on government contracts; primary exposure is compliance with food safety and labor standards.
G67: Litigation | K67: Routine product-liability claims, mostly insured and not material to financials.
B70: Board of Directors | G70: Governance
B72: Name | C72: Position | E72: M/F – Age | H72: Overview | I72: Targets | J72: Improvements | K72: Comments
B73: Gordon O'Brien | C73: Chairman | E73: M - 59 | G73: Diversity (Gender, Age, Industry, Region) | K73: Women account for 30% of the board.
B74: Julie Bowerman | C74: Independent Director | E74: F - 56
B75: Sarah Palisi Chapin | C75: Independent Director | E75: F - 63 | G75: % Independence | K75: 90% of the Directors are Independent.
B76: Timothy FitzGerald | C76: CEO | E76: M - 54
B77: Ed Garden | C77: Independent Director | E77: M - 63 | G77: Average time as independent directors | K77: Avg. Tenure = 9 years
B78: Cathy L. McCarthy | C78: Independent Director | E78: F - 77
B79: Robert A. Nerbonne | C79: Independent Director | E79: M - 67 | G79: Departures of C-level executives | K79: Feb. 2019: Selim Bassoul retired as Chairman, President, and CEO after ~25 years with the company.
B80: Stephen Scherger | C80: Independent Director | E80: M - 60
B81: Tejas Shah | C81: Independent Director | E81: M - 45 | G81: CEO/Chairman duality | K81: After 2019, Timothy FitzGerald was appointed CEO, while the Board separated the Chairman role (currently held by a non-executive director).
B82: Nassem Ziyad | C82: Independent Director | E82: M - 59
G83: Transparency when reporting | K83: Bloomberg ESG Disclosure Score (2023): 54.4; Environmental: 56.6; Social: 21.49; Governance: 84.98.
G85: Time taken to report | K85: 10-K filed on February 26, 2025, within SEC deadlines, this reflects strong internal controls and transparency.
G87: CEO or Chairman in other boards? | K87: Chairman Gordon O-Brien is currently a Managing Partner at Cannon Capital.
G89: Audit / Consulting | K89: Audit related fees tiny relative to the audit fees (~0.2%), no "All other fees" in 2024 and 2023.
G91: ESG-compensation related | K91: Middleby does not prominently link ESG performance to executive pay.
G93: Management compensation schemes | K93: Primarily tied to financial metrics (revenue, profitability, TSR) with little to no ESG linkage.

Sheet Segments
A7: x | B7: Segments | D7: =F7 -> 2020 | E7: =F7 -> 2020 | F7: 2020 | G7: =F7 -> 2020 | H7: =F7 -> 2020 | J7: =L7 -> 2021 | K7: =L7 -> 2021 | L7: 2021 | M7: =L7 -> 2021 | N7: =L7 -> 2021 | P7: =R7 -> 2022 | Q7: =R7 -> 2022 | R7: 2022 | S7: =R7 -> 2022 | T7: =R7 -> 2022 | V7: =X7 -> 2023 | W7: =X7 -> 2023 | X7: 2023 | Y7: =X7 -> 2023 | Z7: =X7 -> 2023 | AB7: =AD7 -> 2024 | AC7: =AD7 -> 2024 | AD7: 2024 | AE7: =AD7 -> 2024 | AF7: =AD7 -> 2024 | AH7: =AJ7 -> 2025 | AI7: =AJ7 -> 2025 | AJ7: 2025 | AK7: =AJ7 -> 2025 | AL7: =AJ7 -> 2025 | AN7: =AP7 -> 2025 | AO7: =AP7 -> 2025 | AP7: 2025 | AQ7: =AP7 -> 2025 | AR7: =AP7 -> 2025 | AZ7: Products
D8: 2020 | J8: =D8+1 -> 2021 | P8: =J8+1 -> 2022 | V8: =P8+1 -> 2023 | AB8: =V8+1 -> 2024 | AH8: =AB8+1 -> 2025 | AN8: =AH8+1 -> 2026 | AT8: =AN8+1 -> 2027 | AV8: =+AT8+1 -> 2028 | AX8: =+AV8+1 -> 2029
D9: Q1 | E9: Q2 | F9: Q3 | G9: Q4 | H9: FY | J9: Q1 | K9: Q2 | L9: Q3 | M9: Q4 | N9: FY | P9: Q1 | Q9: Q2 | R9: Q3 | S9: Q4 | T9: FY | V9: Q1 | W9: Q2 | X9: Q3 | Y9: Q4 | Z9: FY | AB9: Q1 | AC9: Q2 | AD9: Q3 | AE9: Q4 | AF9: FY | AH9: Q1 | AI9: Q2 | AJ9: Q3 | AK9: Q4 | AL9: FY | AN9: Q1 | AO9: Q2 | AP9: Q3 | AQ9: Q4 | AR9: FY | AT9: FY | AV9: FY | AX9: FY
B12: Revenue by segment:
B13: Commercial Foodservice Equipment Group | H13: 1510279 | N13: 2032761 | T13: 2394762 | Z13: 2521471 | AF13: 2419236 | AL13: =FCFF!Z11 -> 2368431.2 | AR13: =FCFF!AF11 -> 2434945.4 | AT13: =FCFF!AH11 -> 2530368 | AV13: =FCFF!AJ11 -> 2622378.5 | AX13: =FCFF!AL11 -> 2720762.4
B14: Food Processing Equipment Group | H14: 437272 | N14: 480746 | T14: 589969 | Z14: 720618 | AF14: 794516 | AL14: =FCFF!Z17 -> 796982.56 | AR14: =FCFF!AF17 -> 865326.67 | AT14: =FCFF!AH17 -> 924724.45 | AV14: =FCFF!AJ17 -> 980517.65 | AX14: =FCFF!AL17 -> 1032242.1
B15: Residential Kitchen Equipment Group. | H15: 565706 | N15: 737285 | T15: 1048122 | Z15: 794516 | AF15: 724923 | AL15: =FCFF!Z23 -> 713547.48 | AR15: =FCFF!AF23 -> 726878.53 | AT15: =FCFF!AH23 -> 746028.25 | AV15: =FCFF!AJ23 -> 769238.05 | AX15: =FCFF!AL23 -> 793226.3
B18: Total revenue | D18: =IS!D18 -> 677459 | E18: =IS!E18 -> 471977 | F18: =IS!F18 -> 634525 | G18: =IS!G18 -> 729296 | H18: =IS!H18 -> 2513257 | J18: =IS!J18 -> 758058 | K18: =IS!K18 -> 808773 | L18: =IS!L18 -> 817545 | M18: =IS!M18 -> 866416 | N18: =IS!N18 -> 3250792 | P18: =IS!P18 -> 994676 | Q18: =IS!Q18 -> 1013601 | R18: =IS!R18 -> 992871 | S18: =IS!S18 -> 1031705 | T18: =IS!T18 -> 4032853 | V18: =IS!V18 -> 1007396 | W18: =IS!W18 -> 1039982 | X18: =IS!X18 -> 980651 | Y18: =IS!Y18 -> 1008576 | Z18: =IS!Z18 -> 4036605 | AB18: =IS!AB18 -> 926926 | AC18: =IS!AC18 -> 991546 | AD18: =IS!AD18 -> 942809 | AE18: =IS!AE18 -> 1013881 | AF18: =IS!AF18 -> 3875162 | AH18: =IS!AH18 -> 906627 | AI18: =IS!AI18 -> 977859 | AJ18: =IS!AJ18 -> 0 | AK18: =IS!AK18 -> 0 | AL18: =SUM(AL13:AL15) -> 3878961.2 | AN18: =IS!AN18 -> 0 | AO18: =IS!AO18 -> 0 | AP18: =IS!AP18 -> 0 | AQ18: =IS!AQ18 -> 0 | AR18: =SUM(AR13:AR15) -> 4027150.6 | AT18: =SUM(AT13:AT15) -> 4201120.7 | AV18: =SUM(AV13:AV15) -> 4372134.2 | AX18: =SUM(AX13:AX15) -> 4546230.8
B20: Revenue by region:
B21: United States and Canada | H21: 1752778 | N21: 2236775 | T21: 2879019 | Z21: 2821061 | AF21: 2614872 | AL21: =FCFF!Z12+FCFF!Z18+FCFF!Z24 -> 2560457.1 | AR21: =FCFF!AF12+FCFF!AF24+FCFF!AF18 -> 2621789.5 | AT21: =FCFF!AH12+FCFF!AH18+FCFF!AH24 -> 2716262.5 | AV21: =FCFF!AJ12+FCFF!AJ18+FCFF!AJ24 -> 2810723.6 | AX21: =FCFF!AL12+FCFF!AL18+FCFF!AL24 -> 2908939.5
B22: Asia | H22: 189231 | N22: 233227 | T22: 264609 | Z22: 285858 | AF22: 262705 | AL22: =FCFF!Z13+FCFF!Z19+FCFF!Z25 -> 257988.88 | AR22: =FCFF!AF13+FCFF!AF19+FCFF!AF25 -> 268396.75 | AT22: =FCFF!AH13+FCFF!AH19+FCFF!AH25 -> 278429.41 | AV22: =FCFF!AJ13+FCFF!AJ19+FCFF!AJ25 -> 289808.54 | AX22: =FCFF!AL13+FCFF!AL19+FCFF!AL25 -> 302462.65
B23: Europe and Middle East | H23: 508454 | N23: 687452 | T23: 768199 | Z23: 773317 | AF23: 826913 | AL23: =FCFF!Z14+FCFF!Z20+FCFF!Z26 -> 876487.64 | AR23: =FCFF!AF14+FCFF!AF20+FCFF!AF26 -> 934158.97 | AT23: =FCFF!AH14+FCFF!AH20+FCFF!AH26 -> 989078.49 | AV23: =FCFF!AJ14+FCFF!AJ20+FCFF!AJ26 -> 1041087.5 | AX23: =FCFF!AL14+FCFF!AL20+FCFF!AL26 -> 1092720.5
B24: Latin America | H24: 62794 | N24: 93338 | T24: 121026 | Z24: 156369 | AF24: 170672 | AL24: =FCFF!Z15+FCFF!Z21+FCFF!Z27 -> 184027.54 | AR24: =FCFF!AF15+FCFF!AF21+FCFF!AF27 -> 202805.39 | AT24: =FCFF!AH15+FCFF!AH21+FCFF!AH27 -> 217350.24 | AV24: =FCFF!AJ15+FCFF!AJ21+FCFF!AJ27 -> 230514.49 | AX24: =FCFF!AL15+FCFF!AL21+FCFF!AL27 -> 242108.19
B26: Total revenue | D26: =IS!D18 -> 677459 | E26: =IS!E18 -> 471977 | F26: =IS!F18 -> 634525 | G26: =IS!G18 -> 729296 | H26: =IS!H18 -> 2513257 | J26: =IS!J18 -> 758058 | K26: =IS!K18 -> 808773 | L26: =IS!L18 -> 817545 | M26: =IS!M18 -> 866416 | N26: =IS!N18 -> 3250792 | P26: =IS!P18 -> 994676 | Q26: =IS!Q18 -> 1013601 | R26: =IS!R18 -> 992871 | S26: =IS!S18 -> 1031705 | T26: =IS!T18 -> 4032853 | V26: =IS!V18 -> 1007396 | W26: =IS!W18 -> 1039982 | X26: =IS!X18 -> 980651 | Y26: =IS!Y18 -> 1008576 | Z26: =IS!Z18 -> 4036605 | AB26: =IS!AB18 -> 926926 | AC26: =IS!AC18 -> 991546 | AD26: =IS!AD18 -> 942809 | AE26: =IS!AE18 -> 1013881 | AF26: =IS!AF18 -> 3875162 | AH26: =IS!AH18 -> 906627 | AI26: =IS!AI18 -> 977859 | AJ26: =IS!AJ18 -> 0 | AK26: =IS!AK18 -> 0 | AL26: =SUM(AL21:AL24) -> 3878961.2 | AN26: =IS!AN18 -> 0 | AO26: =IS!AO18 -> 0 | AP26: =IS!AP18 -> 0 | AQ26: =IS!AQ18 -> 0 | AR26: =IFERROR(SUM(AR21:AR24), " ") -> 4027150.6 | AS26: =IFERROR(SUM(AS21:AS24), " ") -> 0 | AT26: =IFERROR(SUM(AT21:AT24), " ") -> 4201120.7 | AV26: =IFERROR(SUM(AV21:AV24), " ") -> 4372134.2 | AX26: =IFERROR(SUM(AX21:AX24), " ") -> 4546230.8
B28: Products:
B29: Product 1
B30: Product 2
B31: Product 3
B32: Product 4
B33: Product 5
A35: x | B35: Notes & Forecasts
B40: Dividends | H40: The company’s Board of Directors currently intends to retain any future earnings to support its operations and to finance the growth and development of the company’s business and does not intend to declare or pay cash dividends on its common stock for the foreseeable future.
B41: Announced Separation of Food Processing Business for 2026 | H41: Middleby Board of Directors unanimously approved a plan to separate our Food Processing segment into a standalone public company This action will create two independent and innovative leaders: The Middleby Corporation and Middleby Food Processing. The separation will be executed through a tax-free spin-off and is expected to be completed in early 2026.
B42: Expectations for 2025 revenue | H42: For 2025, Middleby corp is expecting a: • Total revenue of $3.81-3.87 billion; • Adjusted EBITDA of $770-800 million; and • Adjusted Earnings Per Share of $8.65-9.05

Sheet Peers
B7: Peers
A12: x | B12: Growth | C12: MIDDLEBY CORP | D12: NORDSON CORP | E12: STANLEY BLACK & | F12: HILLENBRAND INC | G12: TENNANT CO | H12: KADANT INC | I12: JBT MAREL CORP | J12: MSA SAFETY INC | K12: ENERPAC TOOL GRO | L12: SNAP-ON INC | M12: THERMON GROUP HO | N12: FED SIGNAL CORP | O12: DOUGLAS DYNAMICS | P12: ESAB CORP | Q12: FORTUNE BRANDS I | R12: GEA GROUP AG
B14: Revenue (LTM) | C14: -0.017023573 | D14: 0.0448811 | E14: -0.027123451 | F14: -0.080019305 | G14: -0.003815277 | H14: 0.017405109 | I14: 0.64980521 | J14: 0.0054899989 | K14: 0.028227695 | L14: 0.028227695 | M14: -0.0076128224 | N14: -0.0076128224 | O14: -0.0076128224 | P14: -0.0076128224 | Q14: -0.0076128224 | R14: =_xll.BQL( Inputs!$Q$24, "(sales_rev_turn(fpt=ltm,fa_adjusted=y) / sales_rev_turn(fpt=ltm,fa_adjusted=y,fa_period_offset=-1)) - 1" ) -> #NAME?
B15: Revenue (3-yr CAGR) | C15: 0.013269195 | D15: 0.035740049 | E15: -0.031488222 | F15: -0.0098965482 | G15: 0.048693214 | H15: 0.057317114 | I15: 0.1381728 | J15: 0.079385688 | K15: 0.024913716 | L15: 0.023562645 | M15: 0.089939808 | N15: 0.1505117 | O15: 0.0067282557 | P15: 0.029262877 | Q15: -0.10847821 | R15: =_xll.BQL( Inputs!$Q$25, "(sales_rev_turn(fpt=ltm,fa_adjusted=y) / sales_rev_turn(fpt=ltm,fa_adjusted=y,fa_period_offset=-3))^(1/3) - 1" ) -> #NAME?
B16: Gross profit (LTM) | C16: -0.017806707 | D16: 0.035261735 | E16: 0.0054829186 | F16: -0.070683662 | G16: -0.036417142 | H16: 0.045651093 | I16: 0.64607028 | J16: -0.022288876 | K16: 0.0094937127 | L16: 0.0094937127 | M16: 0.003503961 | N16: 0.003503961 | O16: 0.003503961 | P16: 0.003503961 | Q16: 0.003503961 | R16: =_xll.BQL( Inputs!$Q$24, "(gross_profit(fpt=ltm,fa_adjusted=y) / gross_profit(fpt=ltm,fa_adjusted=y,fa_period_offset=-1)) - 1" ) -> #NAME?
B17: EBIT (LTM) | C17: 0.020717435 | D17: 0.045871902 | E17: 0.014782516 | F17: -0.13530443 | G17: -0.10562414 | H17: -0.058583492 | I17: 0.47714604 | J17: -0.010764279 | K17: -0.0098607551 | L17: -0.0098607551 | M17: -0.016612304 | N17: -0.016612304 | O17: -0.016612304 | P17: -0.016612304 | Q17: -0.016612304 | R17: =_xll.BQL( Inputs!$Q$24, "(is_oper_inc(fpt=ltm,fa_adjusted=y) / is_oper_inc(fpt=ltm,fa_adjusted=y,fa_period_offset=-1)) - 1" ) -> #NAME?
B18: EBITDA (LTM) | C18: 0.013216806 | D18: 0.060447768 | E18: -0.018241042 | F18: -0.039993045 | G18: -0.063157895 | H18: -0.0025983024 | I18: 0.6860119 | J18: -9.4824773e-05 | K18: -0.0071547076 | L18: -0.0071547076 | M18: -0.01644319 | N18: -0.01644319 | O18: -0.01644319 | P18: -0.01644319 | Q18: -0.01644319 | R18: =_xll.BQL( Inputs!$Q$24, "(ebitda(fpt=ltm,fa_adjusted=y) / ebitda(fpt=ltm,fa_adjusted=y,fa_period_offset=-1)) - 1" ) -> #NAME?
B19: FCF (LTM) | C19: 0.17272461 | D19: -0.18941188 | E19: -0.11681914 | F19: -0.0043572985 | G19: -0.58454106 | H19: 0.0042260369 | I19: =(282.9-195.7)/195.7 -> 0.44557997 | J19: 3.8351067 | K19: 0.0044426198 | L19: 0.070619335 | M19: -0.037678152 | N19: 0.16209628 | O19: 16.105236 | P19: -0.43123296 | Q19: -0.40635556 | R19: {=_xll.BDP(Inputs!$Q$25,"FREE_CASH_FLOW_1_YEAR_GROWTH")/100} -> #NAME?
A21: x | B21: Margins | C21: MIDDLEBY CORP | D21: NORDSON CORP | E21: STANLEY BLACK & | F21: HILLENBRAND INC | G21: TENNANT CO | H21: KADANT INC | I21: JBT MAREL CORP | J21: MSA SAFETY INC | K21: ENERPAC TOOL GRO | L21: SNAP-ON INC | M21: THERMON GROUP HO | N21: FED SIGNAL CORP | O21: DOUGLAS DYNAMICS | P21: ESAB CORP | Q21: FORTUNE BRANDS I | R21: =R12 -> GEA GROUP AG
B23: Gross margin | C23: 0.3794342 | D23: 0.55248054 | E23: 0.29379722 | F23: 0.33194043 | G23: 0.42745007 | H23: 0.44252428 | I23: 0.36509324 | J23: 0.475873 | K23: 0.5106122 | L23: 0.51969305 | M23: 0.44739636 | N23: 0.28632823 | O23: 0.25828666 | P23: 0.37852228 | Q23: 0.44831851 | R23: {=_xll.BDP(Inputs!$Q$25,"GROSS_MARGIN")/100} -> #NAME?
B24: EBIT margin | C24: 0.16933176 | D24: 0.25056535 | E24: 0.036483857 | F24: -0.0056239789 | G24: 0.088831896 | H24: 0.16257319 | I24: 0.068997669 | J24: 0.21724811 | K24: 0.20625095 | L24: 0.26342886 | M24: 0.16008808 | N24: 0.15116841 | O24: 0.15603936 | P24: 0.16325508 | Q24: 0.1600998 | R24: {=_xll.BDP(Inputs!$Q$25,"OPER_MARGIN")/100} -> #NAME?
B25: EBITDA margin | C25: 0.19962376 | D25: 0.29642082 | E25: 0.081297488 | F25: 0.12681426 | G25: 0.11561478 | H25: 0.20586044 | I25: 0.098033428 | J25: 0.24003587 | K25: 0.23173036 | L25: 0.27490189 | M25: 0.20363877 | N25: 0.19340626 | O25: 0.21771093 | P25: 0.1852217 | Q25: 0.18819787 | R25: {=_xll.BDP(Inputs!$Q$25,"EBITDA_MARGIN")/100} -> #NAME?
B26: Net margin | C26: 0.11055873 | D26: 0.17371663 | E26: 0.019153049 | F26: -0.066293829 | G26: 0.065050128 | H26: 0.10594237 | I26: 0.0497669 | J26: 0.15756634 | K26: 0.14545809 | L26: 0.2043497 | M26: 0.10741519 | N26: 0.11619662 | O26: 0.096864754 | P26: 0.096629345 | Q26: 0.10238663 | R26: {=_xll.BDP(Inputs!$Q$25,"NET_INCOME_TO_COMMON_MARGIN")/100} -> #NAME?
B27: SG&A margin | C27: =754.3/3841.2 -> 0.19637093 | D27: 0.30191519 | E27: 0.19404908 | F27: =603.5/2859.3 -> 0.21106565 | G27: 0.3045776 | H27: 0.26573405 | I27: 0.29527972 | J27: 0.21829449 | K27: 0.28594087 | L27: =1368.2/5070.9 -> 0.26981404 | M27: 0.25954473 | N27: 0.11904378 | O27: 0.16126887 | P27: 0.21153582 | Q27: 0.26884357 | R27: {=_xll.BDP(Inputs!$Q$25,"TRAILING_12_MONTH_SG&A_EXPENSE")/_xll.BDP(Inputs!$Q$25,"TRAIL_12M_NET_SALES")} -> #NAME?
B28: R&D margin | C28: #VALUE! | D28: #VALUE! | G28: 0.03351153 | H28: 0.014014945 | J28: 0.036219432 | R28: {=_xll.BDP(Inputs!$Q$25,"TRAILING_12M_R&D_%_SALES")/100} -> #NAME? | T28: {=_xll.BDP(Inputs!$Q$25,"TRAILING_12M_R&D_%_SALES")/100} -> #NAME?
A30: x | B30: Returns | C30: MIDDLEBY CORP | D30: NORDSON CORP | E30: STANLEY BLACK & | F30: HILLENBRAND INC | G30: TENNANT CO | H30: KADANT INC | I30: JBT MAREL CORP | J30: MSA SAFETY INC | K30: ENERPAC TOOL GRO | L30: SNAP-ON INC | M30: THERMON GROUP HO | N30: FED SIGNAL CORP | O30: DOUGLAS DYNAMICS | P30: ESAB CORP | Q30: FORTUNE BRANDS I | R30: =R21 -> GEA GROUP AG
B32: ROIC | C32: 0.075913294 | D32: 0.10707024 | E32: 0.01785057 | F32: 0.0098943027 | G32: 0.077376435 | H32: 0.1004689 | I32: 0.044793926 | J32: 0.13465844 | K32: 0.16106336 | L32: 0.14832808 | M32: 0.088298512 | N32: 0.15936523 | O32: 0.14343477 | P32: 0.11254756 | Q32: 0.092949498 | R32: {=_xll.BDP(Inputs!$Q$25,"RETURN_ON_INV_CAPITAL")/100} -> #NAME?
B33: CROIC | C33: 0.098830754 | D33: 0.089585189 | E33: 0.048898009 | F33: 0.03887046 | G33: 0.07673433 | H33: 0.11316121 | I33: 0.024325641 | J33: 0.13442093 | K33: 0.10665185 | L33: 0.16815196 | M33: 0.079964365 | N33: 0.12801235 | O33: 0.068402685 | P33: 0.051996055 | Q33: 0.088195387 | R33: {=_xll.BDP(Inputs!$Q$25,"CF_FREE_CASH_FLOW")/_xll.BDP(Inputs!$Q$25,"TOTAL_INVESTED_CAPITAL")} -> #NAME?
B34: ROCE | C34: 0.33664098 | D34: 0.58653972 | E34: 0.20313802 | F34: -0.029576999 | G34: 0.20926401 | H34: 0.38087909 | I34: 0.17184325 | J34: 0.41817568 | K34: 0.40065047 | L34: 0.34276617 | M34: 0.32352893 | N34: 0.41122315 | O34: 0.31658833 | P34: 0.42003869 | Q34: 0.3368176 | R34: {=_xll.BDP(Inputs!$Q$25,"IS_OPER_INC")/_xll.BDP(Inputs!$Q$25,"CAPITAL_EMPLOYED")} -> #NAME?
B35: RONA | C35: 0.18034917 | D35: 0.22986251 | E35: 0.064289728 | F35: -0.012282146 | G35: 0.18373252 | H35: 0.19956463 | I35: 0.076674006 | J35: 0.34357428 | K35: 0.31018754 | L35: 0.24842164 | M35: 0.16102278 | N35: 0.23724812 | O35: 0.33574551 | P35: 0.24744933 | Q35: 0.30466557 | R35: {=_xll.BDP(Inputs!$Q$25,"IS_OPER_INC")/_xll.BDP(Inputs!$Q$25,"NET_ASSETS")} -> #NAME?
B36: ROE | C36: 0.12059906 | D36: 0.1559437 | E36: 0.053787202 | F36: -0.013206163 | G36: 0.095103799 | H36: 0.12209507 | I36: -0.046727862 | J36: 0.24300715 | K36: 0.22160309 | L36: 0.18178843 | M36: 0.10877001 | N36: 0.18765348 | O36: 0.25758892 | P36: 0.13565749 | Q36: 0.1684508 | R36: {=_xll.BDP(Inputs!$Q$25,"RETURN_COM_EQY")/100} -> #NAME?
B37: ROA | C37: 0.059154418 | D37: 0.08114939 | E37: 0.021282939 | F37: -0.0036188179 | G37: 0.050394355 | H37: 0.071986631 | I37: -0.025167463 | J37: 0.11555469 | K37: 0.1129384 | L37: 0.12529994 | M37: 0.0704007 | N37: 0.12285516 | O37: 0.10286409 | P37: 0.061010963 | Q37: 0.059293423 | R37: {=_xll.BDP(Inputs!$Q$25,"RETURN_ON_ASSET")/100} -> #NAME?
A39: x | B39: Efficiency | C39: MIDDLEBY CORP | D39: NORDSON CORP | E39: STANLEY BLACK & | F39: HILLENBRAND INC | G39: TENNANT CO | H39: KADANT INC | I39: JBT MAREL CORP | J39: MSA SAFETY INC | K39: ENERPAC TOOL GRO | L39: SNAP-ON INC | M39: THERMON GROUP HO | N39: FED SIGNAL CORP | O39: DOUGLAS DYNAMICS | P39: ESAB CORP | Q39: FORTUNE BRANDS I | R39: =R30 -> GEA GROUP AG
B41: Asset turnover | C41: 0.53492067 | D41: 0.49658077 | E41: 0.67464647 | F41: 0.57484922 | G41: 1.0405147 | H41: 0.69655159 | I41: 0.4953622 | J41: 0.76258411 | K41: 0.77093222 | L41: 0.63538345 | M41: 0.64636868 | N41: 1.0947193 | O41: 0.90394881 | P41: 0.6518813 | Q41: 0.67760897 | R41: {=_xll.BDP(Inputs!$Q$25,"ASSET_TURNOVER")} -> #NAME?
B42: Net operating asset turnover | C42: 0.95152718 | D42: 0.75460738 | E42: 1.0268719 | F42: 1.0668723 | G42: 1.5391148 | H42: 1.041133 | I42: 1.9073024 | J42: 1.2157794 | K42: 1.5468116 | L42: 0.97451354 | M42: 0.88299036 | N42: 1.309348 | O42: 1.5532642 | P42: 1.0117853 | Q42: 1.3740572 | R42: {=_xll.BDP(Inputs!$Q$25,"SALES_REV_TURN")/(_xll.BDP(Inputs!$Q$25,"BS_TOT_ASSET")-_xll.BDP(Inputs!$Q$25,"BS_CASH_CASH_EQUIVALENTS_AND_STI")-_xll.BDP(Inputs!$Q$25,"SHORT_AND_LONG_TERM_DEBT"))} -> #NAME?
B43: Fixed asset turnover | C43: 7.1458754 | D43: 5.0467619 | E43: 6.0011479 | F43: 7.2469902 | G43: 5.3331915 | H43: 5.8704694 | I43: 5.1837047 | J43: 6.0267371 | K43: 13.642154 | L43: 8.0394768 | M43: 5.8225123 | N43: 7.9878641 | O43: 6.1923173 | P43: 6.9100918 | Q43: 3.8419074 | R43: {=_xll.BDP(Inputs!$Q$25,"NET_FIX_ASSET_TURN")} -> #NAME?
B44: Revenue per employee thsnd of USD | C44: 361.82894 | D44: 348.04363 | E44: 312.61031 | F44: 273.61722 | G44: 278.51111 | H44: 292.606 | I44: 222.15574 | J44: 351.50596 | K44: 304.0495 | L44: 390.06923 | M44: 313.76212 | N44: 420.12766 | O44: 348.08189 | P44: #VALUE! | Q44: 408.70909 | R44: =_xll.BQL( Inputs!$Q$25, "sales_rev_turn(fpt=ltm,fa_adjusted=y,fs=mr)/1k", "currency=USD" )/IFERROR(VALUE(_xll.BDP(Inputs!$Q$25,"NUM_OF_EMPLOYEES")),_xll.BDP(Inputs!$Q$25,"NUM_OF_EMPLOYEES_CSR")) -> #NAME?
B45: EBIT per employee thsnd of USD | C45: 66.143086 | D45: 91.15375 | E45: 19.674227 | F45: 33.023923 | G45: 28.977778 | H45: 46.602 | I45: 21.721311 | J45: 74.2975 | K45: 67.979 | L45: 99.723077 | M45: 49.382653 | N45: 67.962295 | O45: 35.285117 | P45: #VALUE! | Q45: 66.581818 | R45: =_xll.BQL( Inputs!$Q$25, "is_oper_inc(fpt=ltm,fa_adjusted=y,fs=mr)/1k", "currency=USD" )/IFERROR(VALUE(_xll.BDP(Inputs!$Q$25,"NUM_OF_EMPLOYEES")),_xll.BDP(Inputs!$Q$25,"NUM_OF_EMPLOYEES_CSR")) -> #NAME?
A47: x | B47: Working Capital | C47: MIDDLEBY CORP | D47: NORDSON CORP | E47: STANLEY BLACK & | F47: HILLENBRAND INC | G47: TENNANT CO | H47: KADANT INC | I47: JBT MAREL CORP | J47: MSA SAFETY INC | K47: ENERPAC TOOL GRO | L47: SNAP-ON INC | M47: THERMON GROUP HO | N47: FED SIGNAL CORP | O47: DOUGLAS DYNAMICS | P47: ESAB CORP | Q47: FORTUNE BRANDS I | R47: =R39 -> GEA GROUP AG
B49: DSO | C49: 61.143465 | D49: 73.9014 | E49: 33.438371 | F49: 40.300248 | G49: 77.773279 | H49: 53.716178 | I49: 43.236265 | J49: 63.182689 | K49: 66.27633 | L49: 103.11503 | M49: 73.966846 | N49: 41.766307 | O49: 88.177052 | P49: 60.121953 | Q49: 48.607011 | R49: {=_xll.BDP(Inputs!$Q$25,"ACCT_RCV_DAYS")} -> #NAME?
B50: DIO | C50: 138.34164 | D50: 129.44811 | E50: 156.3695 | F50: 92.332358 | G50: 96.354195 | H50: 110.50205 | I50: 96.440021 | J50: 124.83803 | K50: 100.37075 | L50: 146.63249 | M50: 130.98696 | N50: 89.009777 | O50: 135.24814 | P50: 98.021133 | Q50: 148.18013 | R50: {=_xll.BDP(Inputs!$Q$25,"INVENT_DAYS")} -> #NAME?
B51: DPO | C51: 36.775726 | D51: 32.323259 | E51: 83.452523 | F51: 88.826772 | G51: 62.314651 | H51: 34.852499 | I51: 36.15084 | J51: 47.365705 | K51: 51.270962 | L51: 39.875162 | M51: 40.705335 | N51: 24.209184 | O51: 26.866385 | P51: 76.197769 | Q51: 78.588576 | R51: {=_xll.BDP(Inputs!$Q$25,"ACCOUNTS_PAYABLE_TURNOVER_DAYS")} -> #NAME?
B52: CCC | C52: 160.66554 | D52: 186.76316 | E52: 99.978206 | F52: 59.591557 | G52: 102.84946 | H52: 111.14823 | I52: 82.856363 | J52: 129.59446 | K52: 96.438209 | L52: 206.39789 | M52: 154.66168 | N52: 105.33915 | O52: 149.75598 | P52: 69.293602 | Q52: 102.3307 | R52: {=_xll.BDP(Inputs!$Q$25,"CASH_CONVERSION_CYCLE")} -> #NAME?
B53: Working capital intensity | C53: 0.34693594 | D53: 0.22439913 | E53: 0.056982772 | F53: 0.11885776 | G53: 0.24391606 | H53: 0.25790556 | I53: 0.10474855 | J53: 0.30410115 | K53: 0.39168622 | L53: 0.60996076 | M53: 0.32977627 | N53: 0.20794085 | O53: 0.27548636 | P53: 0.22121758 | Q53: 0.16952489 | R53: {=_xll.BDP(Inputs!$Q$25,"WORKING_CAPITAL_TO_SALES")} -> #NAME?
B54: Cash conversion ratio | C54: 1.0466756 | D54: 0.82521094 | E54: 1.9744916 | F54: -10.687151 | G54: 0.7847769 | H54: 0.90664635 | I54: 1.964527 | J54: 0.75462495 | K54: 0.66881328 | L54: 0.9047336 | M54: 0.79137881 | N54: 0.82196162 | O54: 0.46366209 | P54: 0.79427646 | Q54: 0.90500068 | R54: {=_xll.BDP(Inputs!$Q$25,"CF_CASH_FROM_OPER")/_xll.BDP(Inputs!$Q$25,"IS_OPER_INC")} -> #NAME?
B55: CFO margin | C55: 0.17723543 | D55: 0.20676927 | E55: 0.07203707 | F55: 0.060104311 | G55: 0.06971322 | H55: 0.14739639 | I55: 0.13554779 | J55: 0.16394085 | K55: 0.13794338 | L55: 0.23833294 | M55: 0.12669031 | N55: 0.12425463 | O55: 0.072349535 | P55: 0.12966966 | Q55: 0.14489043 | R55: {=_xll.BDP(Inputs!$Q$25,"CF_CASH_FROM_OPER")/_xll.BDP(Inputs!$Q$25,"SALES_REV_TURN")} -> #NAME?
A57: x | B57: Leverage & Coverage | C57: MIDDLEBY CORP | D57: NORDSON CORP | E57: STANLEY BLACK & | F57: HILLENBRAND INC | G57: TENNANT CO | H57: KADANT INC | I57: JBT MAREL CORP | J57: MSA SAFETY INC | K57: ENERPAC TOOL GRO | L57: SNAP-ON INC | M57: THERMON GROUP HO | N57: FED SIGNAL CORP | O57: DOUGLAS DYNAMICS | P57: ESAB CORP | Q57: FORTUNE BRANDS I | R57: =R47 -> GEA GROUP AG
B59: Net debt / EBITDA | C59: 2.4668918 | D59: 2.5118248 | E59: 5.5423495 | F59: 4.4426365 | G59: 1.15804 | H59: 0.72857238 | I59: 6.8110651 | J59: 1.3195478 | K59: 0.36584498 | L59: -0.11319943 | M59: 1.1470465 | N59: 0.60617963 | O59: 1.9587875 | P59: 1.6217217 | Q59: 3.2630895 | R59: {=_xll.BDP(Inputs!$Q$25,"NET_DEBT_TO_EBITDA")} -> #NAME?
B60: Net debt / FCF | C60: 2.8729361 | D60: 4.4824628 | E60: 8.3722444 | F60: 13.543399 | G60: 2.2456395 | H60: 1.7075674 | I60: 0.29429892 | J60: 1.6078818 | K60: 0.90542434 | L60: -0.058377425 | M60: 2.1212998 | N60: 0.84583115 | O60: 6.4145434 | P60: 5.5108232 | Q60: 5.1534247 | R60: {=_xll.BDP(Inputs!$Q$25,"NET_DEBT")/_xll.BDP(Inputs!$Q$25,"CF_FREE_CASH_FLOW")} -> #NAME?
B61: Interest coverage | C61: =695/79.6 -> 8.7311558 | D61: 7.5795173 | E61: 1.1243482 | F61: -0.1473251 | G61: 12.56044 | H61: 8.5506291 | I61: 6.1030928 | J61: 10.648567 | K61: =135.8/9.4 -> 14.446809 | L61: 27.131048 | M61: 7.7246489 | N61: 22.512 | O61: 5.8131717 | P61: =452.9/72.4 -> 6.2555249 | Q61: 6.1236515 | R61: {=_xll.BDP(Inputs!$Q$25,"IS_OPER_INC")/_xll.BDP(Inputs!$Q$25,"IS_INT_EXPENSE")} -> #NAME?
B62: Debt / capital | C62: 0.40929556 | D62: 0.44175764 | E62: 0.43061895 | F62: 0.58519994 | G62: 0.29016431 | H62: 0.27403164 | I62: 0.45432701 | J62: 0.32639591 | K62: 0.36889551 | L62: 0.19285384 | M62: 0.23444714 | N62: 0.17546055 | O62: 0.45305368 | P62: 0.37300398 | Q62: 0.53852603 | R62: {=_xll.BDP(Inputs!$Q$25,"TOT_DEBT_TO_TOT_CAP")/100} -> #NAME?
B63: Short term debt / total debt | C63: 0.02851474 | D63: 0.054411165 | E63: 0.095074908 | F63: 0.020718837 | G63: 0.077860794 | H63: 0.033956125 | I63: 0.0092556584 | J63: 0.047637442 | K63: 0.063128216 | L63: 0.030286641 | M63: 0.14518617 | N63: 0.10380349 | O63: 0.033784463 | P63: 0.013943903 | Q63: 0.18790688 | R63: {=_xll.BDP(Inputs!$Q$25,"BS_ST_BORROW")/_xll.BDP(Inputs!$Q$25,"SHORT_AND_LONG_TERM_DEBT")} -> #NAME?
A65: x | B65: Liquidity | C65: MIDDLEBY CORP | D65: NORDSON CORP | E65: STANLEY BLACK & | F65: HILLENBRAND INC | G65: TENNANT CO | H65: KADANT INC | I65: JBT MAREL CORP | J65: MSA SAFETY INC | K65: ENERPAC TOOL GRO | L65: SNAP-ON INC | M65: THERMON GROUP HO | N65: FED SIGNAL CORP | O65: DOUGLAS DYNAMICS | P65: ESAB CORP | Q65: FORTUNE BRANDS I | R65: =R57 -> GEA GROUP AG
B67: Current ratio | C67: 2.8095758 | D67: 2.4126537 | E67: 1.2970978 | F67: 1.2697839 | G67: 1.973306 | H67: 2.3090126 | I67: 3.4795518 | J67: 2.7873985 | K67: 2.8769562 | L67: 4.149142 | M67: 2.4346236 | N67: 2.6571547 | O67: 3.3939053 | P67: 1.8169135 | Q67: 1.2528241 | R67: {=_xll.BDP(Inputs!$Q$25,"CUR_RATIO")} -> #NAME?
B68: Quick ratio | C68: 1.607202 | D68: 1.2832328 | E68: 0.26577722 | F68: 0.46203011 | G68: 1.2282683 | H68: 1.2378148 | I68: 2.74155 | J68: 1.5403811 | K68: 2.0977101 | L68: 2.8979719 | M68: 1.3257858 | N68: 1.1889992 | O68: 1.3181844 | P68: 0.98042563 | Q68: 0.5588841 | R68: {=_xll.BDP(Inputs!$Q$25,"QUICK_RATIO")} -> #NAME?
B69: Cash ratio | C69: 0.83144183 | D69: 0.21940785 | E69: 0.059081942 | F69: 0.16760575 | G69: 0.34154689 | H69: 0.49414037 | I69: 2.2939309 | J69: 0.57120444 | K69: 1.2913682 | L69: 1.4149766 | M69: 0.35093154 | N69: 0.37675765 | O69: 0.072928539 | P69: 0.39452196 | Q69: 0.2378456 | R69: {=_xll.BDP(Inputs!$Q$25,"CASH_RATIO")} -> #NAME?
A71: x | B71: Cash Deployment | C71: MIDDLEBY CORP | D71: NORDSON CORP | E71: STANLEY BLACK & | F71: HILLENBRAND INC | G71: TENNANT CO | H71: KADANT INC | I71: JBT MAREL CORP | J71: MSA SAFETY INC | K71: ENERPAC TOOL GRO | L71: SNAP-ON INC | M71: THERMON GROUP HO | N71: FED SIGNAL CORP | O71: DOUGLAS DYNAMICS | P71: ESAB CORP | Q71: FORTUNE BRANDS I | R71: =R65 -> GEA GROUP AG
B73: Capex intensity | C73: 0.012745274 | D73: 0.023944941 | E73: 0.023031818 | F73: 0.017029031 | G73: 0.016243103 | H73: 0.019940497 | I73: 0.022086247 | J73: 0.029988275 | K73: 0.021735 | L73: 0.016345627 | M73: 0.02057177 | N73: 0.021810368 | O73: 0.01373781 | P73: 0.07495723 | Q73: 0.041939683 | R73: {=-_xll.BDP(Inputs!$Q$25,"ACQUIS_OF_FIXED_INTANG")/_xll.BDP(Inputs!$Q$25,"SALES_REV_TURN")} -> #NAME?
B74: Capex / depreciation | C74: 0.38836555 | D74: 0.47299431 | E74: 0.60033927 | F74: 0.34303797 | G74: 0.37931034 | H74: 0.42359893 | I74: 0.42393736 | J74: 0.84284893 | K74: 0.96519774 | L74: 0.85204082 | M74: 0.45879404 | N74: 0.63536776 | O74: 0.43655674 | P74: 3.0759545 | Q74: 0.99845041 | R74: {=-_xll.BDP(Inputs!$Q$25,"ACQUIS_OF_FIXED_INTANG")/_xll.BDP(Inputs!$Q$25,"CF_DEPR_AMORT")} -> #NAME?
B75: R&D capitalization rate | C75: #VALUE! | D75: #VALUE! | E75: #VALUE! | F75: #VALUE! | G75: #VALUE! | H75: #VALUE! | I75: #VALUE! | J75: #VALUE! | K75: #VALUE! | L75: #VALUE! | M75: #VALUE! | N75: #VALUE! | O75: #VALUE! | P75: #VALUE! | Q75: #VALUE! | R75: {=_xll.BDP(Inputs!$Q$25,"EXPND_INCUR_ON_R&D_CAPITALZD")/_xll.BDP(Inputs!$Q$25,"IS_RD_EXPEND")} -> #NAME?
B76: R&D capitalization test | C76: #VALUE! | D76: #VALUE! | E76: #VALUE! | F76: #VALUE! | G76: #VALUE! | H76: #VALUE! | I76: #VALUE! | J76: #VALUE! | K76: #VALUE! | L76: #VALUE! | M76: #VALUE! | N76: #VALUE! | O76: #VALUE! | P76: #VALUE! | Q76: #VALUE! | R76: {=_xll.BDP(Inputs!$Q$25,"EXPND_INCUR_ON_R&D_CAPITALZD")/IFERROR(VALUE(_xll.BDP(Inputs!$Q$25,"AMORTIZATION_OF_R&D")),_xll.BDP(Inputs!$Q$25,"BEST_AMORTIZATION"))} -> #NAME?
B77: Dividend payout | C77: 0 | D77: 0.34504995 | E77: 1.7156829 | F77: #VALUE! | G77: 0.25475626 | H77: 0.1347336 | I77: 0.15130024 | J77: 0.27638276 | K77: 0.026438624 | L77: 0.38899511 | M77: 0 | N77: 0.13546001 | O77: 0.49440931 | P77: 0.016835113 | Q77: 0.25652893 | R77: {=_xll.BDP(Inputs!$Q$25,"DVD_PAYOUT_RATIO")/100} -> #NAME?
B78: FCF payout | C78: #VALUE! | D78: 0.32815056 | E78: 0.61938911 | F78: 0.43950401 | G78: 0.39094848 | H78: 0.10003724 | I78: 0.065742167 | J78: 0.47722735 | K78: 0.58642221 | L78: 0.53070427 | M78: #VALUE! | N78: 0.17825626 | O78: 0.81708627 | P78: 0.032237586 | Q78: #VALUE! | R78: {=_xll.BDP(Inputs!$Q$25,"TOTAL_PAYOUT")/_xll.BDP(Inputs!$Q$25,"CF_FREE_CASH_FLOW")} -> #NAME?
B79: Buybacks as % CFO | C79: 0.050464753 | D79: 0.059941423 | E79: 0.015990604 | F79: 0 | G79: 0.21850613 | H79: 0 | I79: 0 | J79: 0.12596651 | K79: 0.47164869 | L79: 0.23819302 | M79: 0.37022719 | N79: 0.055339386 | O79: 0 | P79: 0 | Q79: 0.35998802 | R79: {=-_xll.BDP(Inputs!$Q$25,"CF_DECR_CAP_STOCK")/_xll.BDP(Inputs!$Q$25,"CF_CASH_FROM_OPER")} -> #NAME?
A81: x | B81: Earnings Quality | C81: MIDDLEBY CORP | D81: NORDSON CORP | E81: STANLEY BLACK & | F81: HILLENBRAND INC | G81: TENNANT CO | H81: KADANT INC | I81: JBT MAREL CORP | J81: MSA SAFETY INC | K81: ENERPAC TOOL GRO | L81: SNAP-ON INC | M81: THERMON GROUP HO | N81: FED SIGNAL CORP | O81: DOUGLAS DYNAMICS | P81: ESAB CORP | Q81: FORTUNE BRANDS I | R81: =R71 -> GEA GROUP AG
B83: Cash/earnings conversion | C83: 6.4068657 | D83: 3.328006 | E83: 6.1024892 | F83: 4.2796421 | G83: 3.2093023 | H83: 6.0414397 | I83: 2.9858793 | J83: 4.0634407 | K83: 2.9251439 | L83: 4.9536574 | M83: 5.633021 | N83: 3.479713 | O83: 5.5960544 | P83: 4.5505634 | Q83: 4.9380708 | R83: {=_xll.BDP(Inputs!$Q$25,"cf_cash_from_oper")/_xll.BDP(Inputs!$Q$25,"BEST_NET_INCOME")} -> #NAME?
B84: FCF / net income | C84: 5.9468843 | D84: 2.9426058 | E84: 4.1513907 | F84: 3.0671141 | G84: 2.4615385 | H84: 5.2241245 | I84: 2.4993582 | J84: 3.3201508 | K84: 2.4642446 | L84: 4.6139199 | M84: 4.71834 | N84: 2.8689203 | O84: 4.5334694 | P84: 1.9200512 | Q84: 3.5087071 | R84: {=_xll.BDP(Inputs!$Q$25,"cf_free_cash_flow")/_xll.BDP(Inputs!$Q$25,"BEST_NET_INCOME")} -> #NAME?
A86: x | B86: Per Share & Dilution | C86: MIDDLEBY CORP | D86: NORDSON CORP | E86: STANLEY BLACK & | F86: HILLENBRAND INC | G86: TENNANT CO | H86: KADANT INC | I86: JBT MAREL CORP | J86: MSA SAFETY INC | K86: ENERPAC TOOL GRO | L86: SNAP-ON INC | M86: THERMON GROUP HO | N86: FED SIGNAL CORP | O86: DOUGLAS DYNAMICS | P86: ESAB CORP | Q86: FORTUNE BRANDS I | R86: =R81 -> GEA GROUP AG
B88: Diluted share count YoY | C88: 0.0087647475 | D88: 0.0076955366 | E88: 0.0053958866 | F88: 0 | G88: 0.016461869 | H88: 0.0027259562 | I88: 0.00625 | J88: 0.0041655025 | K88: 0.0096805065 | L88: 0.017110266 | M88: 0.010396257 | N88: 0.013136289 | O88: 0.018010226 | P88: 0.011159113 | Q88: 0.0072115385 | R88: {=_xll.BDP(Inputs!$Q$25,"PERIODIC_SHARE_DILUTION_FACTOR")-1} -> #NAME?
B89: SBC / revenue | C89: 0.0093289003 | D89: 0.0070474189 | E89: 0.0068594337 | F89: 0.0063780319 | G89: 0.0092484651 | H89: 0.010099831 | I89: 0.0085664336 | J89: 0.010057296 | K89: 0.018542518 | L89: 0.0055986219 | M89: 0.010525745 | N89: 0.0083803384 | O89: 0.0085487525 | P89: 0.0072168631 | Q89: 0.0085267954 | R89: {=_xll.BDP(Inputs!$Q$25,"CF_STOCK_BASED_COMPENSATION")/_xll.BDP(Inputs!$Q$25,"sales_rev_turn")} -> #NAME?
B90: SBC / CFO | C90: 0.05263564 | D90: 0.034083493 | E90: 0.095220887 | F90: 0.10611605 | G90: 0.13266444 | H90: 0.06852156 | I90: 0.063198624 | J90: 0.061347106 | K90: 0.13442123 | L90: 0.02349076 | M90: 0.08308248 | N90: 0.067444877 | O90: 0.11815905 | P90: 0.055655756 | Q90: 0.058849955 | R90: {=_xll.BDP(Inputs!$Q$25,"CF_STOCK_BASED_COMPENSATION")/_xll.BDP(Inputs!$Q$25,"cf_cash_from_oper")} -> #NAME?
B91: EPS in USD | C91: 8.817411 | D91: 8.741705 | E91: 4.88338 | F91: 1.829678 | G91: 4.940425 | H91: 9.158319 | I91: 0.762993 | J91: 7.321204 | K91: 1.795852 | L91: 19.075446 | M91: 1.559858 | N91: 3.551408 | O91: 1.540469 | P91: 5.465386 | Q91: 3.720706 | R91: =_xll.BQL( Inputs!$Q$25, "is_eps(fpt=ltm,fa_adjusted=y,fs=mr)", "currency=USD" ) -> #NAME?

Sheet Trading Comps
B7: ="in "&IF(Inputs!$R$18="k","thousands",IF(Inputs!$R$18="MLN","millions","billions")&" of "&Inputs!$R$17) -> in thousands | D7: Current | E7: % of | I7: Enterprise Value / | S7: LTM | T7: Net | V7: Price / | Z7: LT
D8: Share | E8: 52-week | F8: Equity | G8: Enterprise | I8: LTM | J8: 2025 | K8: 2026 | L8: LTM | M8: 2025E | N8: 2026E | O8: LTM | P8: 2025E | Q8: 2026E | S8: EBITDA | T8: Debt / | V8: LTM | W8: 2025E | X8: 2026E | Z8: EPS
B9: Company | C9: Ticker | D9: Price | E9: High | F9: Value | G9: Value | I9: Sales | J9: Sales | K9: Sales | L9: EBITDA | M9: EBITDA | N9: EBITDA | O9: EBIT | P9: EBIT | Q9: EBIT | S9: Margin | T9: EBITDA | V9: EPS | W9: EPS | X9: EPS | Z9: Growth
B12: Tier I
B15: =+Inputs!B21 -> NORDSON CORP | C15: =+_xll.BDP(Inputs!E21,"TICKER_AND_EXCH_CODE") -> NDSN US | D15: =CONCATENATE(_xll.BDP(Inputs!E21,"CRNCY")," ",_xll.BDP(Inputs!E21,"PX_YEST_CLOSE")) -> USD 227 | E15: =_xll.BDP(Inputs!E21,"PX_YEST_CLOSE")/_xll.BDP(Inputs!E21,"HIGH_52WEEK") -> 0.85063329 | F15: =_xll.BDP(Inputs!$E21, "CUR_MKT_CAP", "SCALING_FORMAT=" & Inputs!$R$18) -> 12743054 | G15: =_xll.BDP(Inputs!$E21, "ENTERPRISE_VALUE", "SCALING_FORMAT=" & Inputs!$R$18) -> 14162691 | I15: {=G15/_xll.BQL(Inputs!$E21, "sales_rev_turn(fpt = ltm, fa_adjusted = y, fs = mr)/1"&IF(Inputs!$R$18="BLN","b",IF(Inputs!$R$18="MLN","m","k")))} -> 5.0865358 | J15: {=G15/_xll.BQL(Inputs!$E21, "sales_rev_turn(fpr = 2025, fpt = a, ae = e, fa_adjusted = y, fs = mr)/1"&IF(Inputs!$R$18="BLN","b",IF(Inputs!$R$18="MLN","m","k")))} -> 5.0503971 | K15: =G15/_xll.BQL(Inputs!$E21, "sales_rev_turn(fpr = 2026, fpt = a, ae = e, fa_adjusted = y, fs = mr)/1"&IF(Inputs!$R$18="BLN","b",IF(Inputs!$R$18="MLN","m","k"))) -> 4.8326333 | L15: =G15/_xll.BQL(Inputs!$E21, "ebitda(fpt = ltm, fa_adjusted = y, fs = mr)/1"&IF(Inputs!$R$18="BLN","b",IF(Inputs!$R$18="MLN","m","k"))) -> 16.126715 | M15: =G15/_xll.BQL(Inputs!$E21, "ebitda(fpr = 2025, fpt = a, ae = e, fa_adjusted = y, fs = mr)/1"&IF(Inputs!$R$18="BLN","b",IF(Inputs!$R$18="MLN","m","k"))) -> 15.808339 | N15: {=G15/_xll.BQL(Inputs!$E21,"EBITDA(fpr = 2026, fpt = a, ae = e, fa_adjusted = y, fs = mr)/1"&IF(Inputs!$R$18="BLN","b",IF(Inputs!$R$18="MLN","m","k")))} -> 15.042688 | O15: =G15/_xll.BQL(Inputs!$E21, "is_oper_inc(fpt = ltm, fa_adjusted = y, fs = mr)/1"&IF(Inputs!$R$18="BLN","b",IF(Inputs!$R$18="MLN","m","k"))) -> 19.421432 | P15: =G15/_xll.BQL(Inputs!$E21, "is_oper_inc(fpr = 2025, fpt = a, ae = e, fa_adjusted = y, fs = mr)/1"&IF(Inputs!$R$18="BLN","b",IF(Inputs!$R$18="MLN","m","k"))) -> 19.149122 | Q15: =G15/_xll.BQL(Inputs!$E21, "is_oper_inc(fpr = 2026, fpt = a, ae = e, fa_adjusted = y, fs = mr)/1"&IF(Inputs!$R$18="BLN","b",IF(Inputs!$R$18="MLN","m","k"))) -> 17.74369 | S15: =_xll.BQL(Inputs!$E21, "ebitda(fpt = ltm, fa_adjusted = y, fs = mr)/1"&IF(Inputs!$R$18="BLN","b",IF(Inputs!$R$18="MLN","m","k")))/_xll.BQL(Inputs!$E21, "sales_rev_turn(fpt = ltm, fa_adjusted = y, fs = mr)/1"&IF(Inputs!$R$18="BLN","b",IF(Inputs!$R$18="MLN","m","k"))) -> 0.31541053 | T15: =_xll.BDP(Inputs!$E21,"TOT_DEBT_TO_EBITDA") -> 2.6908882 | V15: =F15/_xll.BQL(Inputs!$E21, "earn_for_common(fpt = ltm, fa_adjusted = y, fs = mr)/1"&IF(Inputs!$R$18="BLN","b",IF(Inputs!$R$18="MLN","m","k"))) -> 25.632215 | W15: =F15/_xll.BQL(Inputs!$E21, "EARN_FOR_COMMON(fpr = 2025, fpt = a, ae = e, fa_adjusted = y, fs = mr)/1"&IF(Inputs!$R$18="BLN","b",IF(Inputs!$R$18="MLN","m","k"))) -> 22.385689 | X15: =F15/_xll.BQL(Inputs!$E21, "EARN_FOR_COMMON(fpr = 2026, fpt = a, ae = e, fa_adjusted = y, fs = mr)/1"&IF(Inputs!$R$18="BLN","b",IF(Inputs!$R$18="MLN","m","k"))) -> 20.628172 | Z15: =(_xll.BQL(Inputs!$E21, "EARN_FOR_COMMON(fpr = 2028, fpt = a, ae = e, fa_adjusted = y, fs = mr)")/_xll.BQL(Inputs!$E21, "EARN_FOR_COMMON(fpr = 2025, fpt = a, ae = e, fa_adjusted = y, fs = mr)"))^(1/3)-1 -> 0.084951831
B16: =+Inputs!B22 -> STANLEY BLACK & | C16: SWK US | D16: USD 76,67 | E16: 0.69146825 | F16: =_xll.BDP(Inputs!$E22, "CUR_MKT_CAP", "SCALING_FORMAT=" & Inputs!$R$18) -> 11361751 | G16: =_xll.BDP(Inputs!$E22, "ENTERPRISE_VALUE", "SCALING_FORMAT=" & Inputs!$R$18) -> 17300578 | I16: {=G16/_xll.BQL(Inputs!$E22, "sales_rev_turn(fpt = ltm, fa_adjusted = y, fs = mr)/1"&IF(Inputs!$R$18="BLN","b",IF(Inputs!$R$18="MLN","m","k")))} -> 1.1410786 | J16: =G16/_xll.BQL(Inputs!$E22, "sales_rev_turn(fpr = 2025, fpt = a, ae = e, fa_adjusted = y, fs = mr)/1"&IF(Inputs!$R$18="BLN","b",IF(Inputs!$R$18="MLN","m","k"))) -> 1.1330178 | K16: =G16/_xll.BQL(Inputs!$E22, "sales_rev_turn(fpr = 2026, fpt = a, ae = e, fa_adjusted = y, fs = mr)/1"&IF(Inputs!$R$18="BLN","b",IF(Inputs!$R$18="MLN","m","k"))) -> 1.0890227 | L16: =G16/_xll.BQL(Inputs!$E22, "ebitda(fpt = ltm, fa_adjusted = y, fs = mr)/1"&IF(Inputs!$R$18="BLN","b",IF(Inputs!$R$18="MLN","m","k"))) -> 11.480144 | M16: {=G16/_xll.BQL(Inputs!$E22, "ebitda(fpr = 2025, fpt = a, ae = e, fa_adjusted = y, fs = mr)/1"&IF(Inputs!$R$18="BLN","b",IF(Inputs!$R$18="MLN","m","k")))} -> 10.344761 | N16: =G16/_xll.BQL(Inputs!$E22, "ebitda(fpr = 2026, fpt = a, ae = e, fa_adjusted = y, fs = mr)/1"&IF(Inputs!$R$18="BLN","b",IF(Inputs!$R$18="MLN","m","k"))) -> 9.0514626 | O16: =G16/_xll.BQL(Inputs!$E22, "is_oper_inc(fpt = ltm, fa_adjusted = y, fs = mr)/1"&IF(Inputs!$R$18="BLN","b",IF(Inputs!$R$18="MLN","m","k"))) -> 18.130976 | P16: =G16/_xll.BQL(Inputs!$E22, "is_oper_inc(fpr = 2025, fpt = a, ae = e, fa_adjusted = y, fs = mr)/1"&IF(Inputs!$R$18="BLN","b",IF(Inputs!$R$18="MLN","m","k"))) -> 12.179217 | Q16: =G16/_xll.BQL(Inputs!$E22, "is_oper_inc(fpr = 2026, fpt = a, ae = e, fa_adjusted = y, fs = mr)/1"&IF(Inputs!$R$18="BLN","b",IF(Inputs!$R$18="MLN","m","k"))) -> 10.404276 | S16: =_xll.BQL(Inputs!$E22, "ebitda(fpt = ltm, fa_adjusted = y, fs = mr)/1"&IF(Inputs!$R$18="BLN","b",IF(Inputs!$R$18="MLN","m","k")))/_xll.BQL(Inputs!$E22, "sales_rev_turn(fpt = ltm, fa_adjusted = y, fs = mr)/1"&IF(Inputs!$R$18="BLN","b",IF(Inputs!$R$18="MLN","m","k"))) -> 0.099395842 | T16: =_xll.BDP(Inputs!$E22,"TOT_DEBT_TO_EBITDA") -> 5.7953107 | V16: =F16/_xll.BQL(Inputs!$E22, "earn_for_common(fpt = ltm, fa_adjusted = y, fs = mr)/1"&IF(Inputs!$R$18="BLN","b",IF(Inputs!$R$18="MLN","m","k"))) -> 15.4204 | W16: =F16/_xll.BQL(Inputs!$E22, "EARN_FOR_COMMON(fpr = 2025, fpt = a, ae = e, fa_adjusted = y, fs = mr)/1"&IF(Inputs!$R$18="BLN","b",IF(Inputs!$R$18="MLN","m","k"))) -> 16.189772 | X16: =F16/_xll.BQL(Inputs!$E22, "EARN_FOR_COMMON(fpr = 2026, fpt = a, ae = e, fa_adjusted = y, fs = mr)/1"&IF(Inputs!$R$18="BLN","b",IF(Inputs!$R$18="MLN","m","k"))) -> 12.83717 | Z16: =(_xll.BQL(Inputs!$E22, "EARN_FOR_COMMON(fpr = 2028, fpt = a, ae = e, fa_adjusted = y, fs = mr)")/_xll.BQL(Inputs!$E22, "EARN_FOR_COMMON(fpr = 2025, fpt = a, ae = e, fa_adjusted = y, fs = mr)"))^(1/3)-1 -> 0.14970242
B17: =+Inputs!B23 -> HILLENBRAND INC | C17: HI US | D17: USD 24,62 | E17: 0.69176735 | F17: =_xll.BDP(Inputs!$E23, "CUR_MKT_CAP", "SCALING_FORMAT=" & Inputs!$R$18) -> 1848744.1 | G17: =_xll.BDP(Inputs!$E23, "ENTERPRISE_VALUE", "SCALING_FORMAT=" & Inputs!$R$18) -> 3059528 | I17: {=G17/_xll.BQL(Inputs!$E23, "sales_rev_turn(fpt = ltm, fa_adjusted = y, fs = mr)/1"&IF(Inputs!$R$18="BLN","b",IF(Inputs!$R$18="MLN","m","k")))} -> 1.0700269 | J17: =G17/_xll.BQL(Inputs!$E23, "sales_rev_turn(fpr = 2025, fpt = a, ae = e, fa_adjusted = y, fs = mr)/1"&IF(Inputs!$R$18="BLN","b",IF(Inputs!$R$18="MLN","m","k"))) -> 1.1705511 | K17: =G17/_xll.BQL(Inputs!$E23, "sales_rev_turn(fpr = 2026, fpt = a, ae = e, fa_adjusted = y, fs = mr)/1"&IF(Inputs!$R$18="BLN","b",IF(Inputs!$R$18="MLN","m","k"))) -> 1.2758666 | L17: =G17/_xll.BQL(Inputs!$E23, "ebitda(fpt = ltm, fa_adjusted = y, fs = mr)/1"&IF(Inputs!$R$18="BLN","b",IF(Inputs!$R$18="MLN","m","k"))) -> 5.5416193 | M17: =G17/_xll.BQL(Inputs!$E23, "ebitda(fpr = 2025, fpt = a, ae = e, fa_adjusted = y, fs = mr)/1"&IF(Inputs!$R$18="BLN","b",IF(Inputs!$R$18="MLN","m","k"))) -> 8.1316359 | N17: =G17/_xll.BQL(Inputs!$E23, "ebitda(fpr = 2026, fpt = a, ae = e, fa_adjusted = y, fs = mr)/1"&IF(Inputs!$R$18="BLN","b",IF(Inputs!$R$18="MLN","m","k"))) -> 8.1641841 | O17: =G17/_xll.BQL(Inputs!$E23, "is_oper_inc(fpt = ltm, fa_adjusted = y, fs = mr)/1"&IF(Inputs!$R$18="BLN","b",IF(Inputs!$R$18="MLN","m","k"))) -> 8.8656274 | P17: =G17/_xll.BQL(Inputs!$E23, "is_oper_inc(fpr = 2025, fpt = a, ae = e, fa_adjusted = y, fs = mr)/1"&IF(Inputs!$R$18="BLN","b",IF(Inputs!$R$18="MLN","m","k"))) -> 8.9722229 | Q17: =G17/_xll.BQL(Inputs!$E23, "is_oper_inc(fpr = 2026, fpt = a, ae = e, fa_adjusted = y, fs = mr)/1"&IF(Inputs!$R$18="BLN","b",IF(Inputs!$R$18="MLN","m","k"))) -> 10.130887 | S17: =_xll.BQL(Inputs!$E23, "ebitda(fpt = ltm, fa_adjusted = y, fs = mr)/1"&IF(Inputs!$R$18="BLN","b",IF(Inputs!$R$18="MLN","m","k")))/_xll.BQL(Inputs!$E23, "sales_rev_turn(fpt = ltm, fa_adjusted = y, fs = mr)/1"&IF(Inputs!$R$18="BLN","b",IF(Inputs!$R$18="MLN","m","k"))) -> 0.19308922 | T17: =_xll.BDP(Inputs!$E23,"TOT_DEBT_TO_EBITDA") -> 4.8916161 | V17: =F17/_xll.BQL(Inputs!$E23, "earn_for_common(fpt = ltm, fa_adjusted = y, fs = mr)/1"&IF(Inputs!$R$18="BLN","b",IF(Inputs!$R$18="MLN","m","k"))) -> 14.313848 | W17: =F17/_xll.BQL(Inputs!$E23, "EARN_FOR_COMMON(fpr = 2025, fpt = a, ae = e, fa_adjusted = y, fs = mr)/1"&IF(Inputs!$R$18="BLN","b",IF(Inputs!$R$18="MLN","m","k"))) -> 11.590872 | X17: =F17/_xll.BQL(Inputs!$E23, "EARN_FOR_COMMON(fpr = 2026, fpt = a, ae = e, fa_adjusted = y, fs = mr)/1"&IF(Inputs!$R$18="BLN","b",IF(Inputs!$R$18="MLN","m","k"))) -> 11.590872 | Z17: =(_xll.BQL(Inputs!$E23, "EARN_FOR_COMMON(fpr = 2028, fpt = a, ae = e, fa_adjusted = y, fs = mr)")/_xll.BQL(Inputs!$E23, "EARN_FOR_COMMON(fpr = 2025, fpt = a, ae = e, fa_adjusted = y, fs = mr)"))^(1/3)-1 -> #VALUE!
B18: =+Inputs!B24 -> TENNANT CO | C18: TNC US | D18: USD 80,66 | E18: 0.81871701 | F18: =_xll.BDP(Inputs!$E24, "CUR_MKT_CAP", "SCALING_FORMAT=" & Inputs!$R$18) -> 1475960.4 | G18: =_xll.BDP(Inputs!$E24, "ENTERPRISE_VALUE", "SCALING_FORMAT=" & Inputs!$R$18) -> 1605484.6 | I18: {=G18/_xll.BQL(Inputs!$E24, "sales_rev_turn(fpt = ltm, fa_adjusted = y, fs = mr)/1"&IF(Inputs!$R$18="BLN","b",IF(Inputs!$R$18="MLN","m","k")))} -> 1.2810058 | J18: =G18/_xll.BQL(Inputs!$E24, "sales_rev_turn(fpr = 2025, fpt = a, ae = e, fa_adjusted = y, fs = mr)/1"&IF(Inputs!$R$18="BLN","b",IF(Inputs!$R$18="MLN","m","k"))) -> 1.3003385 | K18: =G18/_xll.BQL(Inputs!$E24, "sales_rev_turn(fpr = 2026, fpt = a, ae = e, fa_adjusted = y, fs = mr)/1"&IF(Inputs!$R$18="BLN","b",IF(Inputs!$R$18="MLN","m","k"))) -> 1.2286872 | L18: =G18/_xll.BQL(Inputs!$E24, "ebitda(fpt = ltm, fa_adjusted = y, fs = mr)/1"&IF(Inputs!$R$18="BLN","b",IF(Inputs!$R$18="MLN","m","k"))) -> 8.5900729 | M18: =G18/_xll.BQL(Inputs!$E24, "ebitda(fpr = 2025, fpt = a, ae = e, fa_adjusted = y, fs = mr)/1"&IF(Inputs!$R$18="BLN","b",IF(Inputs!$R$18="MLN","m","k"))) -> 8.1496681 | N18: =G18/_xll.BQL(Inputs!$E24, "ebitda(fpr = 2026, fpt = a, ae = e, fa_adjusted = y, fs = mr)/1"&IF(Inputs!$R$18="BLN","b",IF(Inputs!$R$18="MLN","m","k"))) -> 7.4673703 | O18: =G18/_xll.BQL(Inputs!$E24, "is_oper_inc(fpt = ltm, fa_adjusted = y, fs = mr)/1"&IF(Inputs!$R$18="BLN","b",IF(Inputs!$R$18="MLN","m","k"))) -> 12.311999 | P18: =G18/_xll.BQL(Inputs!$E24, "is_oper_inc(fpr = 2025, fpt = a, ae = e, fa_adjusted = y, fs = mr)/1"&IF(Inputs!$R$18="BLN","b",IF(Inputs!$R$18="MLN","m","k"))) -> 14.207828 | Q18: =G18/_xll.BQL(Inputs!$E24, "is_oper_inc(fpr = 2026, fpt = a, ae = e, fa_adjusted = y, fs = mr)/1"&IF(Inputs!$R$18="BLN","b",IF(Inputs!$R$18="MLN","m","k"))) -> 11.495117 | S18: =_xll.BQL(Inputs!$E24, "ebitda(fpt = ltm, fa_adjusted = y, fs = mr)/1"&IF(Inputs!$R$18="BLN","b",IF(Inputs!$R$18="MLN","m","k")))/_xll.BQL(Inputs!$E24, "sales_rev_turn(fpt = ltm, fa_adjusted = y, fs = mr)/1"&IF(Inputs!$R$18="BLN","b",IF(Inputs!$R$18="MLN","m","k"))) -> 0.14912631 | T18: =_xll.BDP(Inputs!$E24,"TOT_DEBT_TO_EBITDA") -> 1.7108351 | V18: =F18/_xll.BQL(Inputs!$E24, "earn_for_common(fpt = ltm, fa_adjusted = y, fs = mr)/1"&IF(Inputs!$R$18="BLN","b",IF(Inputs!$R$18="MLN","m","k"))) -> 15.979077 | W18: =F18/_xll.BQL(Inputs!$E24, "EARN_FOR_COMMON(fpr = 2025, fpt = a, ae = e, fa_adjusted = y, fs = mr)/1"&IF(Inputs!$R$18="BLN","b",IF(Inputs!$R$18="MLN","m","k"))) -> 14.908691 | X18: =F18/_xll.BQL(Inputs!$E24, "EARN_FOR_COMMON(fpr = 2026, fpt = a, ae = e, fa_adjusted = y, fs = mr)/1"&IF(Inputs!$R$18="BLN","b",IF(Inputs!$R$18="MLN","m","k"))) -> 13.02318 | Z18: =(_xll.BQL(Inputs!$E24, "EARN_FOR_COMMON(fpr = 2028, fpt = a, ae = e, fa_adjusted = y, fs = mr)")/_xll.BQL(Inputs!$E24, "EARN_FOR_COMMON(fpr = 2025, fpt = a, ae = e, fa_adjusted = y, fs = mr)"))^(1/3)-1 -> 0.14342805
B19: =+Inputs!B25 -> KADANT INC | C19: KAI US | D19: USD 305,45 | E19: 0.71043145 | F19: =_xll.BDP(Inputs!$E25, "CUR_MKT_CAP", "SCALING_FORMAT=" & Inputs!$R$18) -> 3514513.9 | G19: =_xll.BDP(Inputs!$E25, "ENTERPRISE_VALUE", "SCALING_FORMAT=" & Inputs!$R$18) -> 3857415.9 | I19: {=G19/_xll.BQL(Inputs!$E25, "sales_rev_turn(fpt = ltm, fa_adjusted = y, fs = mr)/1"&IF(Inputs!$R$18="BLN","b",IF(Inputs!$R$18="MLN","m","k")))} -> 3.7665627 | J19: =G19/_xll.BQL(Inputs!$E25, "sales_rev_turn(fpr = 2025, fpt = a, ae = e, fa_adjusted = y, fs = mr)/1"&IF(Inputs!$R$18="BLN","b",IF(Inputs!$R$18="MLN","m","k"))) -> 3.747793 | K19: =G19/_xll.BQL(Inputs!$E25, "sales_rev_turn(fpr = 2026, fpt = a, ae = e, fa_adjusted = y, fs = mr)/1"&IF(Inputs!$R$18="BLN","b",IF(Inputs!$R$18="MLN","m","k"))) -> 3.5675523 | L19: =G19/_xll.BQL(Inputs!$E25, "ebitda(fpt = ltm, fa_adjusted = y, fs = mr)/1"&IF(Inputs!$R$18="BLN","b",IF(Inputs!$R$18="MLN","m","k"))) -> 18.106024 | M19: =G19/_xll.BQL(Inputs!$E25, "ebitda(fpr = 2025, fpt = a, ae = e, fa_adjusted = y, fs = mr)/1"&IF(Inputs!$R$18="BLN","b",IF(Inputs!$R$18="MLN","m","k"))) -> 18.567586 | N19: =G19/_xll.BQL(Inputs!$E25, "ebitda(fpr = 2026, fpt = a, ae = e, fa_adjusted = y, fs = mr)/1"&IF(Inputs!$R$18="BLN","b",IF(Inputs!$R$18="MLN","m","k"))) -> 16.955674 | O19: =G19/_xll.BQL(Inputs!$E25, "is_oper_inc(fpt = ltm, fa_adjusted = y, fs = mr)/1"&IF(Inputs!$R$18="BLN","b",IF(Inputs!$R$18="MLN","m","k"))) -> 23.649604 | P19: =G19/_xll.BQL(Inputs!$E25, "is_oper_inc(fpr = 2025, fpt = a, ae = e, fa_adjusted = y, fs = mr)/1"&IF(Inputs!$R$18="BLN","b",IF(Inputs!$R$18="MLN","m","k"))) -> 24.298683 | Q19: =G19/_xll.BQL(Inputs!$E25, "is_oper_inc(fpr = 2026, fpt = a, ae = e, fa_adjusted = y, fs = mr)/1"&IF(Inputs!$R$18="BLN","b",IF(Inputs!$R$18="MLN","m","k"))) -> 21.701356 | S19: =_xll.BQL(Inputs!$E25, "ebitda(fpt = ltm, fa_adjusted = y, fs = mr)/1"&IF(Inputs!$R$18="BLN","b",IF(Inputs!$R$18="MLN","m","k")))/_xll.BQL(Inputs!$E25, "sales_rev_turn(fpt = ltm, fa_adjusted = y, fs = mr)/1"&IF(Inputs!$R$18="BLN","b",IF(Inputs!$R$18="MLN","m","k"))) -> 0.20802815 | T19: =_xll.BDP(Inputs!$E25,"TOT_DEBT_TO_EBITDA") -> 1.1807035 | V19: =F19/_xll.BQL(Inputs!$E25, "earn_for_common(fpt = ltm, fa_adjusted = y, fs = mr)/1"&IF(Inputs!$R$18="BLN","b",IF(Inputs!$R$18="MLN","m","k"))) -> 32.64512 | W19: =F19/_xll.BQL(Inputs!$E25, "EARN_FOR_COMMON(fpr = 2025, fpt = a, ae = e, fa_adjusted = y, fs = mr)/1"&IF(Inputs!$R$18="BLN","b",IF(Inputs!$R$18="MLN","m","k"))) -> 32.617299 | X19: =F19/_xll.BQL(Inputs!$E25, "EARN_FOR_COMMON(fpr = 2026, fpt = a, ae = e, fa_adjusted = y, fs = mr)/1"&IF(Inputs!$R$18="BLN","b",IF(Inputs!$R$18="MLN","m","k"))) -> 28.515326 | Z19: =(_xll.BQL(Inputs!$E25, "EARN_FOR_COMMON(fpr = 2028, fpt = a, ae = e, fa_adjusted = y, fs = mr)")/_xll.BQL(Inputs!$E25, "EARN_FOR_COMMON(fpr = 2025, fpt = a, ae = e, fa_adjusted = y, fs = mr)"))^(1/3)-1 -> #VALUE!
B21: Mean | I21: =AVERAGE(I15:I19) -> 2.469042 | J21: =AVERAGE(J15:J19) -> 2.4804195 | K21: =AVERAGE(K15:K19) -> 2.3987524 | L21: =AVERAGE(L15:L19) -> 11.968915 | M21: =AVERAGE(M15:M19) -> 12.200398 | N21: =AVERAGE(N15:N19) -> 11.336276 | O21: =AVERAGE(O15:O19) -> 16.475928 | P21: =AVERAGE(P15:P19) -> 15.761415 | Q21: =AVERAGE(Q15:Q19) -> 14.295065 | S21: =AVERAGE(S15:S19) -> 0.19301001 | T21: =AVERAGE(T15:T19) -> 3.2538707 | V21: =AVERAGE(V15:V19) -> 20.798132 | W21: =AVERAGE(W15:W19) -> 19.538465 | X21: =AVERAGE(X15:X19) -> 17.318944 | Z21: =AVERAGE(Z15:Z19) -> #VALUE!
B22: Median | I22: =MEDIAN(I15:I19) -> 1.2810058 | J22: =MEDIAN(J15:J19) -> 1.3003385 | K22: =MEDIAN(K15:K19) -> 1.2758666 | L22: =MEDIAN(L15:L19) -> 11.480144 | M22: =MEDIAN(M15:M19) -> 10.344761 | N22: =MEDIAN(N15:N19) -> 9.0514626 | O22: =MEDIAN(O15:O19) -> 18.130976 | P22: =MEDIAN(P15:P19) -> 14.207828 | Q22: =MEDIAN(Q15:Q19) -> 11.495117 | S22: =MEDIAN(S15:S19) -> 0.19308922 | T22: =MEDIAN(T15:T19) -> 2.6908882 | V22: =MEDIAN(V15:V19) -> 15.979077 | W22: =MEDIAN(W15:W19) -> 16.189772 | X22: =MEDIAN(X15:X19) -> 13.02318 | Z22: =MEDIAN(Z15:Z19) -> #VALUE!
B24: Tier II
B27: =+Inputs!H21 -> JBT MAREL CORP | C27: =+_xll.BDP(Inputs!K21,"TICKER_AND_EXCH_CODE") -> JBTM US | D27: =CONCATENATE(_xll.BDP(Inputs!K21,"CRNCY")," ",_xll.BDP(Inputs!K21,"PX_YEST_CLOSE")) -> USD 137,35 | E27: =_xll.BDP(Inputs!K21,"PX_YEST_CLOSE")/_xll.BDP(Inputs!K21,"HIGH_52WEEK") -> 0.92326824 | F27: =_xll.BDP(Inputs!$K21, "CUR_MKT_CAP", "SCALING_FORMAT=" & Inputs!$R$18) -> 7123062.3 | G27: =_xll.BDP(Inputs!$K21, "ENTERPRISE_VALUE", "SCALING_FORMAT=" & Inputs!$R$18) -> 8059605.3 | I27: =G27/_xll.BQL(Inputs!$K21, "sales_rev_turn(fpt = ltm, fa_adjusted = y, fs = mr)/1"&IF(Inputs!$R$18="BLN","b",IF(Inputs!$R$18="MLN","m","k"))) -> 2.9736949 | J27: =G27/_xll.BQL(Inputs!$K21, "sales_rev_turn(fpr = 2025, fpt = a, ae = e, fa_adjusted = y, fs = mr)/1"&IF(Inputs!$R$18="BLN","b",IF(Inputs!$R$18="MLN","m","k"))) -> 2.1753321 | K27: =G27/_xll.BQL(Inputs!$K21, "sales_rev_turn(fpr = 2026, fpt = a, ae = e, fa_adjusted = y, fs = mr)/1"&IF(Inputs!$R$18="BLN","b",IF(Inputs!$R$18="MLN","m","k"))) -> 2.0757199 | L27: =G27/_xll.BQL(Inputs!$K21, "ebitda(fpt = ltm, fa_adjusted = y, fs = mr)/1"&IF(Inputs!$R$18="BLN","b",IF(Inputs!$R$18="MLN","m","k"))) -> 17.783772 | M27: =G27/_xll.BQL(Inputs!$K21, "ebitda(fpr = 2025, fpt = a, ae = e, fa_adjusted = y, fs = mr)/1"&IF(Inputs!$R$18="BLN","b",IF(Inputs!$R$18="MLN","m","k"))) -> 13.67967 | N27: =G27/_xll.BQL(Inputs!$K21, "ebitda(fpr = 2026, fpt = a, ae = e, fa_adjusted = y, fs = mr)/1"&IF(Inputs!$R$18="BLN","b",IF(Inputs!$R$18="MLN","m","k"))) -> 12.211523 | O27: =G27/_xll.BQL(Inputs!$K21, "is_oper_inc(fpt = ltm, fa_adjusted = y, fs = mr)/1"&IF(Inputs!$R$18="BLN","b",IF(Inputs!$R$18="MLN","m","k"))) -> 30.413605 | P27: =G27/_xll.BQL(Inputs!$K21, "is_oper_inc(fpr = 2025, fpt = a, ae = e, fa_adjusted = y, fs = mr)/1"&IF(Inputs!$R$18="BLN","b",IF(Inputs!$R$18="MLN","m","k"))) -> 17.752435 | Q27: =G27/_xll.BQL(Inputs!$K21, "is_oper_inc(fpr = 2026, fpt = a, ae = e, fa_adjusted = y, fs = mr)/1"&IF(Inputs!$R$18="BLN","b",IF(Inputs!$R$18="MLN","m","k"))) -> 14.795053 | S27: =_xll.BQL(Inputs!$K21, "ebitda(fpt = ltm, fa_adjusted = y, fs = mr)/1"&IF(Inputs!$R$18="BLN","b",IF(Inputs!$R$18="MLN","m","k")))/_xll.BQL(Inputs!$K21, "sales_rev_turn(fpt = ltm, fa_adjusted = y, fs = mr)/1"&IF(Inputs!$R$18="BLN","b",IF(Inputs!$R$18="MLN","m","k"))) -> 0.16721396 | T27: =_xll.BDP(Inputs!$K21,"TOT_DEBT_TO_EBITDA") -> 7.2318404 | V27: =F27/_xll.BQL(Inputs!$K21, "earn_for_common(fpt = ltm, fa_adjusted = y, fs = mr)/1"&IF(Inputs!$R$18="BLN","b",IF(Inputs!$R$18="MLN","m","k"))) -> -556.53321 | W27: =F27/_xll.BQL(Inputs!$K21, "EARN_FOR_COMMON(fpr = 2025, fpt = a, ae = e, fa_adjusted = y, fs = mr)/1"&IF(Inputs!$R$18="BLN","b",IF(Inputs!$R$18="MLN","m","k"))) -> 23.258979 | X27: =F27/_xll.BQL(Inputs!$K21, "EARN_FOR_COMMON(fpr = 2026, fpt = a, ae = e, fa_adjusted = y, fs = mr)/1"&IF(Inputs!$R$18="BLN","b",IF(Inputs!$R$18="MLN","m","k"))) -> 19.986146 | Z27: =(_xll.BQL(Inputs!$K21, "EARN_FOR_COMMON(fpr = 2028, fpt = a, ae = e, fa_adjusted = y, fs = mr)")/_xll.BQL(Inputs!$K21, "EARN_FOR_COMMON(fpr = 2025, fpt = a, ae = e, fa_adjusted = y, fs = mr)"))^(1/3)-1 -> #VALUE!
B28: =+Inputs!H22 -> MSA SAFETY INC | C28: =+_xll.BDP(Inputs!K22,"TICKER_AND_EXCH_CODE") -> MSA US | D28: =CONCATENATE(_xll.BDP(Inputs!K22,"CRNCY")," ",_xll.BDP(Inputs!K22,"PX_YEST_CLOSE")) -> USD 170,88 | E28: =_xll.BDP(Inputs!K22,"PX_YEST_CLOSE")/_xll.BDP(Inputs!K22,"HIGH_52WEEK") -> 0.93451095 | F28: =_xll.BDP(Inputs!$K22, "CUR_MKT_CAP", "SCALING_FORMAT=" & Inputs!$R$18) -> 6664720.4 | G28: =_xll.BDP(Inputs!$K22, "ENTERPRISE_VALUE", "SCALING_FORMAT=" & Inputs!$R$18) -> 7140078.8 | I28: =G28/_xll.BQL(Inputs!$K22, "sales_rev_turn(fpt = ltm, fa_adjusted = y, fs = mr)/1"&IF(Inputs!$R$18="BLN","b",IF(Inputs!$R$18="MLN","m","k"))) -> 3.9063123 | J28: =G28/_xll.BQL(Inputs!$K22, "sales_rev_turn(fpt = ltm, fa_adjusted = y, fs = mr)/1"&IF(Inputs!$R$18="BLN","b",IF(Inputs!$R$18="MLN","m","k"))) -> 3.9063123 | K28: =G28/_xll.BQL(Inputs!$K22, "sales_rev_turn(fpr = 2026, fpt = a, ae = e, fa_adjusted = y, fs = mr)/1"&IF(Inputs!$R$18="BLN","b",IF(Inputs!$R$18="MLN","m","k"))) -> 3.5955076 | L28: =G28/_xll.BQL(Inputs!$K22, "ebitda(fpt = ltm, fa_adjusted = y, fs = mr)/1"&IF(Inputs!$R$18="BLN","b",IF(Inputs!$R$18="MLN","m","k"))) -> 15.74699 | M28: =G28/_xll.BQL(Inputs!$K22, "ebitda(fpr = 2025, fpt = a, ae = e, fa_adjusted = y, fs = mr)/1"&IF(Inputs!$R$18="BLN","b",IF(Inputs!$R$18="MLN","m","k"))) -> 15.186272 | N28: =G28/_xll.BQL(Inputs!$K22, "ebitda(fpr = 2026, fpt = a, ae = e, fa_adjusted = y, fs = mr)/1"&IF(Inputs!$R$18="BLN","b",IF(Inputs!$R$18="MLN","m","k"))) -> 14.036852 | O28: =G28/_xll.BQL(Inputs!$K22, "is_oper_inc(fpt = ltm, fa_adjusted = y, fs = mr)/1"&IF(Inputs!$R$18="BLN","b",IF(Inputs!$R$18="MLN","m","k"))) -> 18.481 | P28: =G28/_xll.BQL(Inputs!$K22, "is_oper_inc(fpr = 2025, fpt = a, ae = e, fa_adjusted = y, fs = mr)/1"&IF(Inputs!$R$18="BLN","b",IF(Inputs!$R$18="MLN","m","k"))) -> 17.23824 | Q28: =G28/_xll.BQL(Inputs!$K22, "is_oper_inc(fpr = 2026, fpt = a, ae = e, fa_adjusted = y, fs = mr)/1"&IF(Inputs!$R$18="BLN","b",IF(Inputs!$R$18="MLN","m","k"))) -> 15.937676 | S28: =_xll.BQL(Inputs!$K22, "ebitda(fpt = ltm, fa_adjusted = y, fs = mr)/1"&IF(Inputs!$R$18="BLN","b",IF(Inputs!$R$18="MLN","m","k")))/_xll.BQL(Inputs!$K22, "sales_rev_turn(fpt = ltm, fa_adjusted = y, fs = mr)/1"&IF(Inputs!$R$18="BLN","b",IF(Inputs!$R$18="MLN","m","k"))) -> 0.24806724 | T28: =_xll.BDP(Inputs!$K22,"TOT_DEBT_TO_EBITDA") -> 1.654567 | V28: =F28/_xll.BQL(Inputs!$K22, "earn_for_common(fpt = ltm, fa_adjusted = y, fs = mr)/1"&IF(Inputs!$R$18="BLN","b",IF(Inputs!$R$18="MLN","m","k"))) -> 23.143303 | W28: =F28/_xll.BQL(Inputs!$K22, "EARN_FOR_COMMON(fpr = 2025, fpt = a, ae = e, fa_adjusted = y, fs = mr)/1"&IF(Inputs!$R$18="BLN","b",IF(Inputs!$R$18="MLN","m","k"))) -> 21.697408 | X28: =F28/_xll.BQL(Inputs!$K22, "EARN_FOR_COMMON(fpr = 2026, fpt = a, ae = e, fa_adjusted = y, fs = mr)/1"&IF(Inputs!$R$18="BLN","b",IF(Inputs!$R$18="MLN","m","k"))) -> 19.421235 | Z28: =(_xll.BQL(Inputs!$K22, "EARN_FOR_COMMON(fpr = 2028, fpt = a, ae = e, fa_adjusted = y, fs = mr)")/_xll.BQL(Inputs!$K22, "EARN_FOR_COMMON(fpr = 2025, fpt = a, ae = e, fa_adjusted = y, fs = mr)"))^(1/3)-1 -> 0.11518051
B29: =+Inputs!H23 -> ENERPAC TOOL GRO | C29: =+_xll.BDP(Inputs!K23,"TICKER_AND_EXCH_CODE") -> EPAC US | D29: =CONCATENATE(_xll.BDP(Inputs!K23,"CRNCY")," ",_xll.BDP(Inputs!K23,"PX_YEST_CLOSE")) -> USD 40,2 | E29: =_xll.BDP(Inputs!K23,"PX_YEST_CLOSE")/_xll.BDP(Inputs!K23,"HIGH_52WEEK") -> 0.77441726 | F29: =_xll.BDP(Inputs!$K23, "CUR_MKT_CAP", "SCALING_FORMAT=" & Inputs!$R$18) -> 2169089.6 | G29: =_xll.BDP(Inputs!$K23, "ENTERPRISE_VALUE", "SCALING_FORMAT=" & Inputs!$R$18) -> 2364189 | I29: =G29/_xll.BQL(Inputs!$K23, "sales_rev_turn(fpt = ltm, fa_adjusted = y, fs = mr)/1"&IF(Inputs!$R$18="BLN","b",IF(Inputs!$R$18="MLN","m","k"))) -> 3.8878358 | J29: =G29/_xll.BQL(Inputs!$K23, "sales_rev_turn(fpr = 2025, fpt = a, ae = e, fa_adjusted = y, fs = mr)/1"&IF(Inputs!$R$18="BLN","b",IF(Inputs!$R$18="MLN","m","k"))) -> 3.8546561 | K29: =G29/_xll.BQL(Inputs!$K23, "sales_rev_turn(fpr = 2026, fpt = a, ae = e, fa_adjusted = y, fs = mr)/1"&IF(Inputs!$R$18="BLN","b",IF(Inputs!$R$18="MLN","m","k"))) -> 3.7056255 | L29: =G29/_xll.BQL(Inputs!$K23, "ebitda(fpt = ltm, fa_adjusted = y, fs = mr)/1"&IF(Inputs!$R$18="BLN","b",IF(Inputs!$R$18="MLN","m","k"))) -> 15.432043 | M29: =G29/_xll.BQL(Inputs!$K23, "ebitda(fpr = 2025, fpt = a, ae = e, fa_adjusted = y, fs = mr)/1"&IF(Inputs!$R$18="BLN","b",IF(Inputs!$R$18="MLN","m","k"))) -> 15.452216 | N29: =G29/_xll.BQL(Inputs!$K23, "ebitda(fpr = 2026, fpt = a, ae = e, fa_adjusted = y, fs = mr)/1"&IF(Inputs!$R$18="BLN","b",IF(Inputs!$R$18="MLN","m","k"))) -> 14.504227 | O29: =G29/_xll.BQL(Inputs!$K23, "is_oper_inc(fpt = ltm, fa_adjusted = y, fs = mr)/1"&IF(Inputs!$R$18="BLN","b",IF(Inputs!$R$18="MLN","m","k"))) -> 17.389113 | P29: =G29/_xll.BQL(Inputs!$K23, "is_oper_inc(fpr = 2025, fpt = a, ae = e, fa_adjusted = y, fs = mr)/1"&IF(Inputs!$R$18="BLN","b",IF(Inputs!$R$18="MLN","m","k"))) -> 17.731418 | Q29: =G29/_xll.BQL(Inputs!$K23, "is_oper_inc(fpr = 2026, fpt = a, ae = e, fa_adjusted = y, fs = mr)/1"&IF(Inputs!$R$18="BLN","b",IF(Inputs!$R$18="MLN","m","k"))) -> 15.867041 | S29: =_xll.BQL(Inputs!$K23, "ebitda(fpt = ltm, fa_adjusted = y, fs = mr)/1"&IF(Inputs!$R$18="BLN","b",IF(Inputs!$R$18="MLN","m","k")))/_xll.BQL(Inputs!$K23, "sales_rev_turn(fpt = ltm, fa_adjusted = y, fs = mr)/1"&IF(Inputs!$R$18="BLN","b",IF(Inputs!$R$18="MLN","m","k"))) -> 0.25193266 | T29: =_xll.BDP(Inputs!$K23,"TOT_DEBT_TO_EBITDA") -> 1.3863412 | V29: =F29/_xll.BQL(Inputs!$K23, "earn_for_common(fpt = ltm, fa_adjusted = y, fs = mr)/1"&IF(Inputs!$R$18="BLN","b",IF(Inputs!$R$18="MLN","m","k"))) -> 22.26812 | W29: =F29/_xll.BQL(Inputs!$K23, "EARN_FOR_COMMON(fpr = 2025, fpt = a, ae = e, fa_adjusted = y, fs = mr)/1"&IF(Inputs!$R$18="BLN","b",IF(Inputs!$R$18="MLN","m","k"))) -> 22.021215 | X29: =F29/_xll.BQL(Inputs!$K23, "EARN_FOR_COMMON(fpr = 2026, fpt = a, ae = e, fa_adjusted = y, fs = mr)/1"&IF(Inputs!$R$18="BLN","b",IF(Inputs!$R$18="MLN","m","k"))) -> 21.059123 | Z29: =(_xll.BQL(Inputs!$K23, "EARN_FOR_COMMON(fpr = 2028, fpt = a, ae = e, fa_adjusted = y, fs = mr)")/_xll.BQL(Inputs!$K23, "EARN_FOR_COMMON(fpr = 2025, fpt = a, ae = e, fa_adjusted = y, fs = mr)"))^(1/3)-1 -> #VALUE!
B30: =+Inputs!H24 -> SNAP-ON INC | C30: =+_xll.BDP(Inputs!K24,"TICKER_AND_EXCH_CODE") -> SNA US | D30: =CONCATENATE(_xll.BDP(Inputs!K24,"CRNCY")," ",_xll.BDP(Inputs!K24,"PX_YEST_CLOSE")) -> USD 341,91 | E30: =_xll.BDP(Inputs!K24,"PX_YEST_CLOSE")/_xll.BDP(Inputs!K24,"HIGH_52WEEK") -> 0.91445459 | F30: =_xll.BDP(Inputs!$K24, "CUR_MKT_CAP", "SCALING_FORMAT=" & Inputs!$R$18) -> 17877952 | G30: =_xll.BDP(Inputs!$K24, "ENTERPRISE_VALUE", "SCALING_FORMAT=" & Inputs!$R$18) -> 16088968 | I30: =G30/_xll.BQL(Inputs!$K24, "sales_rev_turn(fpt = ltm, fa_adjusted = y, fs = mr)/1"&IF(Inputs!$R$18="BLN","b",IF(Inputs!$R$18="MLN","m","k"))) -> 3.1728033 | J30: =G30/_xll.BQL(Inputs!$K24, "sales_rev_turn(fpr = 2025, fpt = a, ae = e, fa_adjusted = y, fs = mr)/1"&IF(Inputs!$R$18="BLN","b",IF(Inputs!$R$18="MLN","m","k"))) -> 3.4180214 | K30: =G30/_xll.BQL(Inputs!$K24, "sales_rev_turn(fpr = 2026, fpt = a, ae = e, fa_adjusted = y, fs = mr)/1"&IF(Inputs!$R$18="BLN","b",IF(Inputs!$R$18="MLN","m","k"))) -> 3.2864811 | L30: =G30/_xll.BQL(Inputs!$K24, "ebitda(fpt = ltm, fa_adjusted = y, fs = mr)/1"&IF(Inputs!$R$18="BLN","b",IF(Inputs!$R$18="MLN","m","k"))) -> 11.544069 | M30: =G30/_xll.BQL(Inputs!$K24, "ebitda(fpr = 2025, fpt = a, ae = e, fa_adjusted = y, fs = mr)/1"&IF(Inputs!$R$18="BLN","b",IF(Inputs!$R$18="MLN","m","k"))) -> 11.554609 | N30: =G30/_xll.BQL(Inputs!$K24, "ebitda(fpr = 2026, fpt = a, ae = e, fa_adjusted = y, fs = mr)/1"&IF(Inputs!$R$18="BLN","b",IF(Inputs!$R$18="MLN","m","k"))) -> 10.862667 | O30: =G30/_xll.BQL(Inputs!$K24, "is_oper_inc(fpt = ltm, fa_adjusted = y, fs = mr)/1"&IF(Inputs!$R$18="BLN","b",IF(Inputs!$R$18="MLN","m","k"))) -> 12.410497 | P30: =G30/_xll.BQL(Inputs!$K24, "is_oper_inc(fpr = 2025, fpt = a, ae = e, fa_adjusted = y, fs = mr)/1"&IF(Inputs!$R$18="BLN","b",IF(Inputs!$R$18="MLN","m","k"))) -> 12.34953 | Q30: =G30/_xll.BQL(Inputs!$K24, "is_oper_inc(fpr = 2026, fpt = a, ae = e, fa_adjusted = y, fs = mr)/1"&IF(Inputs!$R$18="BLN","b",IF(Inputs!$R$18="MLN","m","k"))) -> 11.61472 | S30: =_xll.BQL(Inputs!$K24, "ebitda(fpt = ltm, fa_adjusted = y, fs = mr)/1"&IF(Inputs!$R$18="BLN","b",IF(Inputs!$R$18="MLN","m","k")))/_xll.BQL(Inputs!$K24, "sales_rev_turn(fpt = ltm, fa_adjusted = y, fs = mr)/1"&IF(Inputs!$R$18="BLN","b",IF(Inputs!$R$18="MLN","m","k"))) -> 0.27484273 | T30: =_xll.BDP(Inputs!$K24,"TOT_DEBT_TO_EBITDA") -> 0.93292683 | V30: =F30/_xll.BQL(Inputs!$K24, "earn_for_common(fpt = ltm, fa_adjusted = y, fs = mr)/1"&IF(Inputs!$R$18="BLN","b",IF(Inputs!$R$18="MLN","m","k"))) -> 17.88219 | W30: =F30/_xll.BQL(Inputs!$K24, "EARN_FOR_COMMON(fpr = 2025, fpt = a, ae = e, fa_adjusted = y, fs = mr)/1"&IF(Inputs!$R$18="BLN","b",IF(Inputs!$R$18="MLN","m","k"))) -> 17.849393 | X30: =F30/_xll.BQL(Inputs!$K24, "EARN_FOR_COMMON(fpr = 2026, fpt = a, ae = e, fa_adjusted = y, fs = mr)/1"&IF(Inputs!$R$18="BLN","b",IF(Inputs!$R$18="MLN","m","k"))) -> 16.655443 | Z30: =(_xll.BQL(Inputs!$K24, "EARN_FOR_COMMON(fpr = 2028, fpt = a, ae = e, fa_adjusted = y, fs = mr)")/_xll.BQL(Inputs!$K24, "EARN_FOR_COMMON(fpr = 2025, fpt = a, ae = e, fa_adjusted = y, fs = mr)"))^(1/3)-1 -> 0.08603573
B31: =+Inputs!H25 -> THERMON GROUP HO | C31: =+_xll.BDP(Inputs!K25,"TICKER_AND_EXCH_CODE") -> THR US | D31: =CONCATENATE(_xll.BDP(Inputs!K25,"CRNCY")," ",_xll.BDP(Inputs!K25,"PX_YEST_CLOSE")) -> USD 26,58 | E31: =_xll.BDP(Inputs!K25,"PX_YEST_CLOSE")/_xll.BDP(Inputs!K25,"HIGH_52WEEK") -> 0.7993985 | F31: =_xll.BDP(Inputs!$K25, "CUR_MKT_CAP", "SCALING_FORMAT=" & Inputs!$R$18) -> 871428.68 | G31: =_xll.BDP(Inputs!$K25, "ENTERPRISE_VALUE", "SCALING_FORMAT=" & Inputs!$R$18) -> 1043244 | I31: =G31/_xll.BQL(Inputs!$K25, "sales_rev_turn(fpt = ltm, fa_adjusted = y, fs = mr)/1"&IF(Inputs!$R$18="BLN","b",IF(Inputs!$R$18="MLN","m","k"))) -> 2.1205052 | J31: =G31/_xll.BQL(Inputs!$K25, "sales_rev_turn(fpr = 2025, fpt = a, ae = e, fa_adjusted = y, fs = mr)/1"&IF(Inputs!$R$18="BLN","b",IF(Inputs!$R$18="MLN","m","k"))) -> 2.0959197 | K31: =G31/_xll.BQL(Inputs!$K25, "sales_rev_turn(fpr = 2026, fpt = a, ae = e, fa_adjusted = y, fs = mr)/1"&IF(Inputs!$R$18="BLN","b",IF(Inputs!$R$18="MLN","m","k"))) -> 2.0617471 | L31: =G31/_xll.BQL(Inputs!$K25, "ebitda(fpt = ltm, fa_adjusted = y, fs = mr)/1"&IF(Inputs!$R$18="BLN","b",IF(Inputs!$R$18="MLN","m","k"))) -> 10.44602 | M31: =G31/_xll.BQL(Inputs!$K25, "ebitda(fpr = 2025, fpt = a, ae = e, fa_adjusted = y, fs = mr)/1"&IF(Inputs!$R$18="BLN","b",IF(Inputs!$R$18="MLN","m","k"))) -> 9.682079 | N31: =G31/_xll.BQL(Inputs!$K25, "ebitda(fpr = 2026, fpt = a, ae = e, fa_adjusted = y, fs = mr)/1"&IF(Inputs!$R$18="BLN","b",IF(Inputs!$R$18="MLN","m","k"))) -> 10.148288 | O31: =G31/_xll.BQL(Inputs!$K25, "is_oper_inc(fpt = ltm, fa_adjusted = y, fs = mr)/1"&IF(Inputs!$R$18="BLN","b",IF(Inputs!$R$18="MLN","m","k"))) -> 13.473035 | P31: =G31/_xll.BQL(Inputs!$K25, "is_oper_inc(fpr = 2025, fpt = a, ae = e, fa_adjusted = y, fs = mr)/1"&IF(Inputs!$R$18="BLN","b",IF(Inputs!$R$18="MLN","m","k"))) -> 13.155662 | Q31: =G31/_xll.BQL(Inputs!$K25, "is_oper_inc(fpr = 2026, fpt = a, ae = e, fa_adjusted = y, fs = mr)/1"&IF(Inputs!$R$18="BLN","b",IF(Inputs!$R$18="MLN","m","k"))) -> 14.482795 | S31: =_xll.BQL(Inputs!$K25, "ebitda(fpt = ltm, fa_adjusted = y, fs = mr)/1"&IF(Inputs!$R$18="BLN","b",IF(Inputs!$R$18="MLN","m","k")))/_xll.BQL(Inputs!$K25, "sales_rev_turn(fpt = ltm, fa_adjusted = y, fs = mr)/1"&IF(Inputs!$R$18="BLN","b",IF(Inputs!$R$18="MLN","m","k"))) -> 0.20299647 | T31: =_xll.BDP(Inputs!$K25,"TOT_DEBT_TO_EBITDA") -> 1.5116683 | V31: =F31/_xll.BQL(Inputs!$K25, "earn_for_common(fpt = ltm, fa_adjusted = y, fs = mr)/1"&IF(Inputs!$R$18="BLN","b",IF(Inputs!$R$18="MLN","m","k"))) -> 16.637692 | W31: =F31/_xll.BQL(Inputs!$K25, "EARN_FOR_COMMON(fpr = 2025, fpt = a, ae = e, fa_adjusted = y, fs = mr)/1"&IF(Inputs!$R$18="BLN","b",IF(Inputs!$R$18="MLN","m","k"))) -> 14.02514 | X31: =F31/_xll.BQL(Inputs!$K25, "EARN_FOR_COMMON(fpr = 2026, fpt = a, ae = e, fa_adjusted = y, fs = mr)/1"&IF(Inputs!$R$18="BLN","b",IF(Inputs!$R$18="MLN","m","k"))) -> 14.864455 | Z31: =(_xll.BQL(Inputs!$K25, "EARN_FOR_COMMON(fpr = 2028, fpt = a, ae = e, fa_adjusted = y, fs = mr)")/_xll.BQL(Inputs!$K25, "EARN_FOR_COMMON(fpr = 2025, fpt = a, ae = e, fa_adjusted = y, fs = mr)"))^(1/3)-1 -> #VALUE!
B33: Mean | I33: =AVERAGE(I27:I31) -> 3.2122303 | J33: =AVERAGE(J27:J31) -> 3.0900483 | K33: =AVERAGE(K27:K31) -> 2.9450162 | L33: =AVERAGE(L27:L31) -> 14.190579 | M33: =AVERAGE(M27:M31) -> 13.110969 | N33: =AVERAGE(N27:N31) -> 12.352712 | O33: =AVERAGE(O27:O31) -> 18.43345 | P33: =AVERAGE(P27:P31) -> 15.645457 | Q33: =AVERAGE(Q27:Q31) -> 14.539457 | S33: =AVERAGE(S27:S31) -> 0.22901061 | T33: =AVERAGE(T27:T31) -> 2.5434687 | V33: =AVERAGE(V27:V31) -> -95.32038 | W33: =AVERAGE(W27:W31) -> 19.770427 | X33: =AVERAGE(X27:X31) -> 18.39728 | Z33: =AVERAGE(Z27:Z31) -> #VALUE!
B34: Median | I34: =MEDIAN(I27:I31) -> 3.1728033 | J34: =MEDIAN(J27:J31) -> 3.4180214 | K34: =MEDIAN(K27:K31) -> 3.2864811 | L34: =MEDIAN(L27:L31) -> 15.432043 | M34: =MEDIAN(M27:M31) -> 13.67967 | N34: =MEDIAN(N27:N31) -> 12.211523 | O34: =MEDIAN(O27:O31) -> 17.389113 | P34: =MEDIAN(P27:P31) -> 17.23824 | Q34: =MEDIAN(Q27:Q31) -> 14.795053 | S34: =MEDIAN(S27:S31) -> 0.24806724 | T34: =MEDIAN(T27:T31) -> 1.5116683 | V34: =MEDIAN(V27:V31) -> 17.88219 | W34: =MEDIAN(W27:W31) -> 21.697408 | X34: =MEDIAN(X27:X31) -> 19.421235 | Z34: =MEDIAN(Z27:Z31) -> #VALUE!
B36: Tier III
B39: =+Inputs!N21 -> FED SIGNAL CORP | C39: =+_xll.BDP(Inputs!Q21,"TICKER_AND_EXCH_CODE") -> FSS US | D39: =CONCATENATE(_xll.BDP(Inputs!Q21,"CRNCY")," ",_xll.BDP(Inputs!Q21,"PX_YEST_CLOSE")) -> USD 122,24 | E39: =_xll.BDP(Inputs!Q21,"PX_YEST_CLOSE")/_xll.BDP(Inputs!Q21,"HIGH_52WEEK") -> 0.93814275 | F39: =_xll.BDP(Inputs!$Q21, "CUR_MKT_CAP", "SCALING_FORMAT=" & Inputs!$R$18) -> 7247002 | G39: =_xll.BDP(Inputs!$Q21, "ENTERPRISE_VALUE", "SCALING_FORMAT=" & Inputs!$R$18) -> 6701836 | I39: =G39/_xll.BQL(Inputs!$Q21, "sales_rev_turn(fpt = ltm, fa_adjusted = y, fs = mr)/1"&IF(Inputs!$R$18="BLN","b",IF(Inputs!$R$18="MLN","m","k"))) -> 3.3940221 | J39: =G39/_xll.BQL(Inputs!$Q21, "sales_rev_turn(fpr = 2025, fpt = a, ae = e, fa_adjusted = y, fs = mr)/1"&IF(Inputs!$R$18="BLN","b",IF(Inputs!$R$18="MLN","m","k"))) -> 3.1764407 | K39: =G39/_xll.BQL(Inputs!$Q21, "sales_rev_turn(fpr = 2026, fpt = a, ae = e, fa_adjusted = y, fs = mr)/1"&IF(Inputs!$R$18="BLN","b",IF(Inputs!$R$18="MLN","m","k"))) -> 2.867709 | L39: =G39/_xll.BQL(Inputs!$Q21, "ebitda(fpt = ltm, fa_adjusted = y, fs = mr)/1"&IF(Inputs!$R$18="BLN","b",IF(Inputs!$R$18="MLN","m","k"))) -> 17.099889 | M39: =G39/_xll.BQL(Inputs!$Q21, "ebitda(fpr = 2025, fpt = a, ae = e, fa_adjusted = y, fs = mr)/1"&IF(Inputs!$R$18="BLN","b",IF(Inputs!$R$18="MLN","m","k"))) -> 15.875754 | N39: =G39/_xll.BQL(Inputs!$Q21, "ebitda(fpr = 2026, fpt = a, ae = e, fa_adjusted = y, fs = mr)/1"&IF(Inputs!$R$18="BLN","b",IF(Inputs!$R$18="MLN","m","k"))) -> 14.315792 | O39: =G39/_xll.BQL(Inputs!$Q21, "is_oper_inc(fpt = ltm, fa_adjusted = y, fs = mr)/1"&IF(Inputs!$R$18="BLN","b",IF(Inputs!$R$18="MLN","m","k"))) -> 20.981083 | P39: =G39/_xll.BQL(Inputs!$Q21, "is_oper_inc(fpr = 2025, fpt = a, ae = e, fa_adjusted = y, fs = mr)/1"&IF(Inputs!$R$18="BLN","b",IF(Inputs!$R$18="MLN","m","k"))) -> 19.425612 | Q39: =G39/_xll.BQL(Inputs!$Q21, "is_oper_inc(fpr = 2026, fpt = a, ae = e, fa_adjusted = y, fs = mr)/1"&IF(Inputs!$R$18="BLN","b",IF(Inputs!$R$18="MLN","m","k"))) -> 17.009736 | S39: =_xll.BQL(Inputs!$Q21, "ebitda(fpt = ltm, fa_adjusted = y, fs = mr)/1"&IF(Inputs!$R$18="BLN","b",IF(Inputs!$R$18="MLN","m","k")))/_xll.BQL(Inputs!$Q21, "sales_rev_turn(fpt = ltm, fa_adjusted = y, fs = mr)/1"&IF(Inputs!$R$18="BLN","b",IF(Inputs!$R$18="MLN","m","k"))) -> 0.19848212 | T39: =_xll.BDP(Inputs!$Q21,"TOT_DEBT_TO_EBITDA") -> 0.77559571 | V39: =F39/_xll.BQL(Inputs!$Q21, "earn_for_common(fpt = ltm, fa_adjusted = y, fs = mr)/1"&IF(Inputs!$R$18="BLN","b",IF(Inputs!$R$18="MLN","m","k"))) -> 33.516472 | W39: =F39/_xll.BQL(Inputs!$Q21, "EARN_FOR_COMMON(fpr = 2025, fpt = a, ae = e, fa_adjusted = y, fs = mr)/1"&IF(Inputs!$R$18="BLN","b",IF(Inputs!$R$18="MLN","m","k"))) -> 29.204959 | X39: =F39/_xll.BQL(Inputs!$Q21, "EARN_FOR_COMMON(fpr = 2026, fpt = a, ae = e, fa_adjusted = y, fs = mr)/1"&IF(Inputs!$R$18="BLN","b",IF(Inputs!$R$18="MLN","m","k"))) -> 25.88215 | Z39: =(_xll.BQL(Inputs!$Q21, "EARN_FOR_COMMON(fpr = 2028, fpt = a, ae = e, fa_adjusted = y, fs = mr)")/_xll.BQL(Inputs!$Q21, "EARN_FOR_COMMON(fpr = 2025, fpt = a, ae = e, fa_adjusted = y, fs = mr)"))^(1/3)-1 -> 0.12360491
B40: =+Inputs!N22 -> DOUGLAS DYNAMICS | C40: =+_xll.BDP(Inputs!Q22,"TICKER_AND_EXCH_CODE") -> PLOW US | D40: =CONCATENATE(_xll.BDP(Inputs!Q22,"CRNCY")," ",_xll.BDP(Inputs!Q22,"PX_YEST_CLOSE")) -> USD 31,5 | E40: =_xll.BDP(Inputs!Q22,"PX_YEST_CLOSE")/_xll.BDP(Inputs!Q22,"HIGH_52WEEK") -> 0.91970803 | F40: =_xll.BDP(Inputs!$Q22, "CUR_MKT_CAP", "SCALING_FORMAT=" & Inputs!$R$18) -> 714728.04 | G40: =_xll.BDP(Inputs!$Q22, "ENTERPRISE_VALUE", "SCALING_FORMAT=" & Inputs!$R$18) -> 927353.67 | I40: =G40/_xll.BQL(Inputs!$Q22, "sales_rev_turn(fpt = ltm, fa_adjusted = y, fs = mr)/1"&IF(Inputs!$R$18="BLN","b",IF(Inputs!$R$18="MLN","m","k"))) -> 1.5924582 | J40: =G40/_xll.BQL(Inputs!$Q22, "sales_rev_turn(fpr = 2025, fpt = a, ae = e, fa_adjusted = y, fs = mr)/1"&IF(Inputs!$R$18="BLN","b",IF(Inputs!$R$18="MLN","m","k"))) -> 1.4565765 | K40: =G40/_xll.BQL(Inputs!$Q22, "sales_rev_turn(fpr = 2026, fpt = a, ae = e, fa_adjusted = y, fs = mr)/1"&IF(Inputs!$R$18="BLN","b",IF(Inputs!$R$18="MLN","m","k"))) -> 1.353801 | L40: =G40/_xll.BQL(Inputs!$Q22, "ebitda(fpt = ltm, fa_adjusted = y, fs = mr)/1"&IF(Inputs!$R$18="BLN","b",IF(Inputs!$R$18="MLN","m","k"))) -> 10.685152 | M40: =G40/_xll.BQL(Inputs!$Q22, "ebitda(fpr = 2025, fpt = a, ae = e, fa_adjusted = y, fs = mr)/1"&IF(Inputs!$R$18="BLN","b",IF(Inputs!$R$18="MLN","m","k"))) -> 9.9040976 | N40: =G40/_xll.BQL(Inputs!$Q22, "ebitda(fpr = 2026, fpt = a, ae = e, fa_adjusted = y, fs = mr)/1"&IF(Inputs!$R$18="BLN","b",IF(Inputs!$R$18="MLN","m","k"))) -> 8.8319398 | O40: =G40/_xll.BQL(Inputs!$Q22, "is_oper_inc(fpt = ltm, fa_adjusted = y, fs = mr)/1"&IF(Inputs!$R$18="BLN","b",IF(Inputs!$R$18="MLN","m","k"))) -> 15.709339 | P40: =G40/_xll.BQL(Inputs!$Q22, "is_oper_inc(fpr = 2025, fpt = a, ae = e, fa_adjusted = y, fs = mr)/1"&IF(Inputs!$R$18="BLN","b",IF(Inputs!$R$18="MLN","m","k"))) -> 12.634246 | Q40: =G40/_xll.BQL(Inputs!$Q22, "is_oper_inc(fpr = 2026, fpt = a, ae = e, fa_adjusted = y, fs = mr)/1"&IF(Inputs!$R$18="BLN","b",IF(Inputs!$R$18="MLN","m","k"))) -> 11.206691 | S40: =_xll.BQL(Inputs!$Q22, "ebitda(fpt = ltm, fa_adjusted = y, fs = mr)/1"&IF(Inputs!$R$18="BLN","b",IF(Inputs!$R$18="MLN","m","k")))/_xll.BQL(Inputs!$Q22, "sales_rev_turn(fpt = ltm, fa_adjusted = y, fs = mr)/1"&IF(Inputs!$R$18="BLN","b",IF(Inputs!$R$18="MLN","m","k"))) -> 0.14903467 | T40: =_xll.BDP(Inputs!$Q22,"TOT_DEBT_TO_EBITDA") -> 2.0217302 | V40: =F40/_xll.BQL(Inputs!$Q22, "earn_for_common(fpt = ltm, fa_adjusted = y, fs = mr)/1"&IF(Inputs!$R$18="BLN","b",IF(Inputs!$R$18="MLN","m","k"))) -> 20.067027 | W40: =F40/_xll.BQL(Inputs!$Q22, "EARN_FOR_COMMON(fpr = 2025, fpt = a, ae = e, fa_adjusted = y, fs = mr)/1"&IF(Inputs!$R$18="BLN","b",IF(Inputs!$R$18="MLN","m","k"))) -> 15.554473 | X40: =F40/_xll.BQL(Inputs!$Q22, "EARN_FOR_COMMON(fpr = 2026, fpt = a, ae = e, fa_adjusted = y, fs = mr)/1"&IF(Inputs!$R$18="BLN","b",IF(Inputs!$R$18="MLN","m","k"))) -> 13.523709 | Z40: =(_xll.BQL(Inputs!$Q22, "EARN_FOR_COMMON(fpr = 2028, fpt = a, ae = e, fa_adjusted = y, fs = mr)")/_xll.BQL(Inputs!$Q22, "EARN_FOR_COMMON(fpr = 2025, fpt = a, ae = e, fa_adjusted = y, fs = mr)"))^(1/3)-1 -> #VALUE!
B41: =+Inputs!N23 -> ESAB CORP | C41: =+_xll.BDP(Inputs!Q23,"TICKER_AND_EXCH_CODE") -> ESAB US | D41: =CONCATENATE(_xll.BDP(Inputs!Q23,"CRNCY")," ",_xll.BDP(Inputs!Q23,"PX_YEST_CLOSE")) -> USD 110,06 | E41: =_xll.BDP(Inputs!Q23,"PX_YEST_CLOSE")/_xll.BDP(Inputs!Q23,"HIGH_52WEEK") -> 0.80944326 | F41: =_xll.BDP(Inputs!$Q23, "CUR_MKT_CAP", "SCALING_FORMAT=" & Inputs!$R$18) -> 6643473.8 | G41: =_xll.BDP(Inputs!$Q23, "ENTERPRISE_VALUE", "SCALING_FORMAT=" & Inputs!$R$18) -> 8478906.8 | I41: =G41/_xll.BQL(Inputs!$Q23, "sales_rev_turn(fpt = ltm, fa_adjusted = y, fs = mr)/1"&IF(Inputs!$R$18="BLN","b",IF(Inputs!$R$18="MLN","m","k"))) -> 3.0970573 | J41: =G41/_xll.BQL(Inputs!$Q23, "sales_rev_turn(fpr = 2025, fpt = a, ae = e, fa_adjusted = y, fs = mr)/1"&IF(Inputs!$R$18="BLN","b",IF(Inputs!$R$18="MLN","m","k"))) -> 3.1849248 | K41: =G41/_xll.BQL(Inputs!$Q23, "sales_rev_turn(fpr = 2026, fpt = a, ae = e, fa_adjusted = y, fs = mr)/1"&IF(Inputs!$R$18="BLN","b",IF(Inputs!$R$18="MLN","m","k"))) -> 3.0008518 | L41: =G41/_xll.BQL(Inputs!$Q23, "ebitda(fpt = ltm, fa_adjusted = y, fs = mr)/1"&IF(Inputs!$R$18="BLN","b",IF(Inputs!$R$18="MLN","m","k"))) -> 14.652858 | M41: =G41/_xll.BQL(Inputs!$Q23, "ebitda(fpr = 2025, fpt = a, ae = e, fa_adjusted = y, fs = mr)/1"&IF(Inputs!$R$18="BLN","b",IF(Inputs!$R$18="MLN","m","k"))) -> 15.949787 | N41: =G41/_xll.BQL(Inputs!$Q23, "ebitda(fpr = 2026, fpt = a, ae = e, fa_adjusted = y, fs = mr)/1"&IF(Inputs!$R$18="BLN","b",IF(Inputs!$R$18="MLN","m","k"))) -> 14.566066 | O41: =G41/_xll.BQL(Inputs!$Q23, "is_oper_inc(fpt = ltm, fa_adjusted = y, fs = mr)/1"&IF(Inputs!$R$18="BLN","b",IF(Inputs!$R$18="MLN","m","k"))) -> 16.692534 | P41: =G41/_xll.BQL(Inputs!$Q23, "is_oper_inc(fpr = 2025, fpt = a, ae = e, fa_adjusted = y, fs = mr)/1"&IF(Inputs!$R$18="BLN","b",IF(Inputs!$R$18="MLN","m","k"))) -> 18.800237 | Q41: =G41/_xll.BQL(Inputs!$Q23, "is_oper_inc(fpr = 2026, fpt = a, ae = e, fa_adjusted = y, fs = mr)/1"&IF(Inputs!$R$18="BLN","b",IF(Inputs!$R$18="MLN","m","k"))) -> 16.784375 | S41: =_xll.BQL(Inputs!$Q23, "ebitda(fpt = ltm, fa_adjusted = y, fs = mr)/1"&IF(Inputs!$R$18="BLN","b",IF(Inputs!$R$18="MLN","m","k")))/_xll.BQL(Inputs!$Q23, "sales_rev_turn(fpt = ltm, fa_adjusted = y, fs = mr)/1"&IF(Inputs!$R$18="BLN","b",IF(Inputs!$R$18="MLN","m","k"))) -> 0.21136199 | T41: =_xll.BDP(Inputs!$Q23,"TOT_DEBT_TO_EBITDA") -> 2.1309499 | V41: =F41/_xll.BQL(Inputs!$Q23, "earn_for_common(fpt = ltm, fa_adjusted = y, fs = mr)/1"&IF(Inputs!$R$18="BLN","b",IF(Inputs!$R$18="MLN","m","k"))) -> 20.046178 | W41: =F41/_xll.BQL(Inputs!$Q23, "EARN_FOR_COMMON(fpr = 2025, fpt = a, ae = e, fa_adjusted = y, fs = mr)/1"&IF(Inputs!$R$18="BLN","b",IF(Inputs!$R$18="MLN","m","k"))) -> 20.593533 | X41: =F41/_xll.BQL(Inputs!$Q23, "EARN_FOR_COMMON(fpr = 2026, fpt = a, ae = e, fa_adjusted = y, fs = mr)/1"&IF(Inputs!$R$18="BLN","b",IF(Inputs!$R$18="MLN","m","k"))) -> 18.286468 | Z41: =(_xll.BQL(Inputs!$Q23, "EARN_FOR_COMMON(fpr = 2028, fpt = a, ae = e, fa_adjusted = y, fs = mr)")/_xll.BQL(Inputs!$Q23, "EARN_FOR_COMMON(fpr = 2025, fpt = a, ae = e, fa_adjusted = y, fs = mr)"))^(1/3)-1 -> 0.11276246
B42: =+Inputs!N24 -> FORTUNE BRANDS | C42: =+_xll.BDP(Inputs!Q24,"TICKER_AND_EXCH_CODE") -> #NAME? | D42: =CONCATENATE(_xll.BDP(Inputs!Q24,"CRNCY")," ",_xll.BDP(Inputs!Q24,"PX_YEST_CLOSE")) -> #NAME? | E42: =_xll.BDP(Inputs!Q24,"PX_YEST_CLOSE")/_xll.BDP(Inputs!Q24,"HIGH_52WEEK") -> #NAME? | F42: =_xll.BDP(Inputs!$Q24, "CUR_MKT_CAP", "SCALING_FORMAT=" & Inputs!$R$18) -> #NAME? | G42: =_xll.BDP(Inputs!$Q24, "ENTERPRISE_VALUE", "SCALING_FORMAT=" & Inputs!$R$18) -> #NAME? | I42: =G42/_xll.BQL(Inputs!$Q24, "sales_rev_turn(fpt = ltm, fa_adjusted = y, fs = mr)/1"&IF(Inputs!$R$18="BLN","b",IF(Inputs!$R$18="MLN","m","k"))) -> #NAME? | J42: =G42/_xll.BQL(Inputs!$Q24, "sales_rev_turn(fpr = 2025, fpt = a, ae = e, fa_adjusted = y, fs = mr)/1"&IF(Inputs!$R$18="BLN","b",IF(Inputs!$R$18="MLN","m","k"))) -> #NAME? | K42: =G42/_xll.BQL(Inputs!$Q24, "sales_rev_turn(fpr = 2026, fpt = a, ae = e, fa_adjusted = y, fs = mr)/1"&IF(Inputs!$R$18="BLN","b",IF(Inputs!$R$18="MLN","m","k"))) -> #NAME? | L42: =G42/_xll.BQL(Inputs!$Q24, "ebitda(fpt = ltm, fa_adjusted = y, fs = mr)/1"&IF(Inputs!$R$18="BLN","b",IF(Inputs!$R$18="MLN","m","k"))) -> #NAME? | M42: =G42/_xll.BQL(Inputs!$Q24, "ebitda(fpr = 2025, fpt = a, ae = e, fa_adjusted = y, fs = mr)/1"&IF(Inputs!$R$18="BLN","b",IF(Inputs!$R$18="MLN","m","k"))) -> #NAME? | N42: =G42/_xll.BQL(Inputs!$Q24, "ebitda(fpr = 2026, fpt = a, ae = e, fa_adjusted = y, fs = mr)/1"&IF(Inputs!$R$18="BLN","b",IF(Inputs!$R$18="MLN","m","k"))) -> #NAME? | O42: =G42/_xll.BQL(Inputs!$Q24, "is_oper_inc(fpt = ltm, fa_adjusted = y, fs = mr)/1"&IF(Inputs!$R$18="BLN","b",IF(Inputs!$R$18="MLN","m","k"))) -> #NAME? | P42: =G42/_xll.BQL(Inputs!$Q24, "is_oper_inc(fpr = 2025, fpt = a, ae = e, fa_adjusted = y, fs = mr)/1"&IF(Inputs!$R$18="BLN","b",IF(Inputs!$R$18="MLN","m","k"))) -> #NAME? | Q42: =G42/_xll.BQL(Inputs!$Q24, "is_oper_inc(fpr = 2026, fpt = a, ae = e, fa_adjusted = y, fs = mr)/1"&IF(Inputs!$R$18="BLN","b",IF(Inputs!$R$18="MLN","m","k"))) -> #NAME? | S42: =_xll.BQL(Inputs!$Q24, "ebitda(fpt = ltm, fa_adjusted = y, fs = mr)/1"&IF(Inputs!$R$18="BLN","b",IF(Inputs!$R$18="MLN","m","k")))/_xll.BQL(Inputs!$Q24, "sales_rev_turn(fpt = ltm, fa_adjusted = y, fs = mr)/1"&IF(Inputs!$R$18="BLN","b",IF(Inputs!$R$18="MLN","m","k"))) -> #NAME? | T42: =_xll.BDP(Inputs!$Q24,"TOT_DEBT_TO_EBITDA") -> #NAME? | V42: =F42/_xll.BQL(Inputs!$Q24, "earn_for_common(fpt = ltm, fa_adjusted = y, fs = mr)/1"&IF(Inputs!$R$18="BLN","b",IF(Inputs!$R$18="MLN","m","k"))) -> #NAME? | W42: =F42/_xll.BQL(Inputs!$Q24, "EARN_FOR_COMMON(fpr = 2025, fpt = a, ae = e, fa_adjusted = y, fs = mr)/1"&IF(Inputs!$R$18="BLN","b",IF(Inputs!$R$18="MLN","m","k"))) -> #NAME? | X42: =F42/_xll.BQL(Inputs!$Q24, "EARN_FOR_COMMON(fpr = 2026, fpt = a, ae = e, fa_adjusted = y, fs = mr)/1"&IF(Inputs!$R$18="BLN","b",IF(Inputs!$R$18="MLN","m","k"))) -> #NAME? | Z42: =(_xll.BQL(Inputs!$Q24, "EARN_FOR_COMMON(fpr = 2028, fpt = a, ae = e, fa_adjusted = y, fs = mr)")/_xll.BQL(Inputs!$Q24, "EARN_FOR_COMMON(fpr = 2025, fpt = a, ae = e, fa_adjusted = y, fs = mr)"))^(1/3)-1 -> #NAME?
B43: =+Inputs!N25 -> GEA GROUP AG | C43: =+_xll.BDP(Inputs!Q25,"TICKER_AND_EXCH_CODE") -> #NAME? | D43: =CONCATENATE(_xll.BDP(Inputs!Q25,"CRNCY")," ",_xll.BDP(Inputs!Q25,"PX_YEST_CLOSE")) -> #NAME? | E43: =_xll.BDP(Inputs!Q25,"PX_YEST_CLOSE")/_xll.BDP(Inputs!Q25,"HIGH_52WEEK") -> #NAME? | F43: =_xll.BDP(Inputs!$Q25, "CUR_MKT_CAP", "SCALING_FORMAT=" & Inputs!$R$18) -> #NAME? | G43: =_xll.BDP(Inputs!$Q25, "ENTERPRISE_VALUE", "SCALING_FORMAT=" & Inputs!$R$18) -> #NAME? | I43: =G43/_xll.BQL(Inputs!$Q25, "sales_rev_turn(fpt = ltm, fa_adjusted = y, fs = mr)/1"&IF(Inputs!$R$18="BLN","b",IF(Inputs!$R$18="MLN","m","k"))) -> #NAME? | J43: =G43/_xll.BQL(Inputs!$Q25, "sales_rev_turn(fpr = 2025, fpt = a, ae = e, fa_adjusted = y, fs = mr)/1"&IF(Inputs!$R$18="BLN","b",IF(Inputs!$R$18="MLN","m","k"))) -> #NAME? | K43: =G43/_xll.BQL(Inputs!$Q25, "sales_rev_turn(fpr = 2026, fpt = a, ae = e, fa_adjusted = y, fs = mr)/1"&IF(Inputs!$R$18="BLN","b",IF(Inputs!$R$18="MLN","m","k"))) -> #NAME? | L43: =G43/_xll.BQL(Inputs!$Q25, "ebitda(fpt = ltm, fa_adjusted = y, fs = mr)/1"&IF(Inputs!$R$18="BLN","b",IF(Inputs!$R$18="MLN","m","k"))) -> #NAME? | M43: =G43/_xll.BQL(Inputs!$Q25, "ebitda(fpr = 2025, fpt = a, ae = e, fa_adjusted = y, fs = mr)/1"&IF(Inputs!$R$18="BLN","b",IF(Inputs!$R$18="MLN","m","k"))) -> #NAME? | N43: =G43/_xll.BQL(Inputs!$Q25, "ebitda(fpr = 2026, fpt = a, ae = e, fa_adjusted = y, fs = mr)/1"&IF(Inputs!$R$18="BLN","b",IF(Inputs!$R$18="MLN","m","k"))) -> #NAME? | O43: =G43/_xll.BQL(Inputs!$Q25, "is_oper_inc(fpt = ltm, fa_adjusted = y, fs = mr)/1"&IF(Inputs!$R$18="BLN","b",IF(Inputs!$R$18="MLN","m","k"))) -> #NAME? | P43: =G43/_xll.BQL(Inputs!$Q25, "is_oper_inc(fpr = 2025, fpt = a, ae = e, fa_adjusted = y, fs = mr)/1"&IF(Inputs!$R$18="BLN","b",IF(Inputs!$R$18="MLN","m","k"))) -> #NAME? | Q43: =G43/_xll.BQL(Inputs!$Q25, "is_oper_inc(fpr = 2026, fpt = a, ae = e, fa_adjusted = y, fs = mr)/1"&IF(Inputs!$R$18="BLN","b",IF(Inputs!$R$18="MLN","m","k"))) -> #NAME? | S43: =_xll.BQL(Inputs!$Q25, "ebitda(fpt = ltm, fa_adjusted = y, fs = mr)/1"&IF(Inputs!$R$18="BLN","b",IF(Inputs!$R$18="MLN","m","k")))/_xll.BQL(Inputs!$Q25, "sales_rev_turn(fpt = ltm, fa_adjusted = y, fs = mr)/1"&IF(Inputs!$R$18="BLN","b",IF(Inputs!$R$18="MLN","m","k"))) -> #NAME? | T43: =_xll.BDP(Inputs!$Q25,"TOT_DEBT_TO_EBITDA") -> #NAME? | V43: =F43/_xll.BQL(Inputs!$Q25, "earn_for_common(fpt = ltm, fa_adjusted = y, fs = mr)/1"&IF(Inputs!$R$18="BLN","b",IF(Inputs!$R$18="MLN","m","k"))) -> #NAME? | W43: =F43/_xll.BQL(Inputs!$Q25, "EARN_FOR_COMMON(fpr = 2025, fpt = a, ae = e, fa_adjusted = y, fs = mr)/1"&IF(Inputs!$R$18="BLN","b",IF(Inputs!$R$18="MLN","m","k"))) -> #NAME? | X43: =F43/_xll.BQL(Inputs!$Q25, "EARN_FOR_COMMON(fpr = 2026, fpt = a, ae = e, fa_adjusted = y, fs = mr)/1"&IF(Inputs!$R$18="BLN","b",IF(Inputs!$R$18="MLN","m","k"))) -> #NAME? | Z43: =(_xll.BQL(Inputs!$Q25, "EARN_FOR_COMMON(fpr = 2028, fpt = a, ae = e, fa_adjusted = y, fs = mr)")/_xll.BQL(Inputs!$Q25, "EARN_FOR_COMMON(fpr = 2025, fpt = a, ae = e, fa_adjusted = y, fs = mr)"))^(1/3)-1 -> #NAME?
B45: Mean | I45: =AVERAGE(I39:I43) -> #NAME? | J45: =AVERAGE(J39:J43) -> #NAME? | K45: =AVERAGE(K39:K43) -> #NAME? | L45: =AVERAGE(L39:L43) -> #NAME? | M45: =AVERAGE(M39:M43) -> #NAME? | N45: =AVERAGE(N39:N43) -> #NAME? | O45: =AVERAGE(O39:O43) -> #NAME? | P45: =AVERAGE(P39:P43) -> #NAME? | Q45: =AVERAGE(Q39:Q43) -> #NAME? | S45: =AVERAGE(S39:S43) -> #NAME? | T45: =AVERAGE(T39:T43) -> #NAME? | V45: =AVERAGE(V39:V43) -> #NAME? | W45: =AVERAGE(W39:W43) -> #NAME? | X45: =AVERAGE(X39:X43) -> #NAME? | Z45: =AVERAGE(Z39:Z43) -> #VALUE!
B46: Median | I46: =MEDIAN(I39:I43) -> #NAME? | J46: =MEDIAN(J39:J43) -> #NAME? | K46: =MEDIAN(K39:K43) -> #NAME? | L46: =MEDIAN(L39:L43) -> #NAME? | M46: =MEDIAN(M39:M43) -> #NAME? | N46: =MEDIAN(N39:N43) -> #NAME? | O46: =MEDIAN(O39:O43) -> #NAME? | P46: =MEDIAN(P39:P43) -> #NAME? | Q46: =MEDIAN(Q39:Q43) -> #NAME? | S46: =MEDIAN(S39:S43) -> #NAME? | T46: =MEDIAN(T39:T43) -> #NAME? | V46: =MEDIAN(V39:V43) -> #NAME? | W46: =MEDIAN(W39:W43) -> #NAME? | X46: =MEDIAN(X39:X43) -> #NAME? | Z46: =MEDIAN(Z39:Z43) -> #VALUE!
B48: Overall
B51: Mean | I51: =AVERAGE(I39:I43,I27:I32,I15:I19) -> #NAME? | J51: =AVERAGE(J39:J43,J27:J32,J15:J19) -> #NAME? | K51: =AVERAGE(K39:K43,K27:K32,K15:K19) -> #NAME? | L51: =AVERAGE(L39:L43,L27:L32,L15:L19) -> #NAME? | M51: =AVERAGE(M39:M43,M27:M32,M15:M19) -> #NAME? | N51: =AVERAGE(N39:N43,N27:N32,N15:N19) -> #NAME? | O51: =AVERAGE(O39:O43,O27:O32,O15:O19) -> #NAME? | P51: =AVERAGE(P39:P43,P27:P32,P15:P19) -> #NAME? | Q51: =AVERAGE(Q39:Q43,Q27:Q32,Q15:Q19) -> #NAME? | S51: =AVERAGE(S39:S43,S27:S32,S15:S19) -> #NAME? | T51: =AVERAGE(T39:T43,T27:T32,T15:T19) -> #NAME? | V51: =AVERAGE(V39:V43,V27:V32,V15:V19) -> #NAME? | W51: =AVERAGE(W39:W43,W27:W32,W15:W19) -> #NAME? | X51: =AVERAGE(X39:X43,X27:X32,X15:X19) -> #NAME? | Z51: =AVERAGE(Z39:Z43,Z27:Z32,Z15:Z19) -> #VALUE!
B52: Median | I52: =MEDIAN(I39:I43,I27:I31,I15:I19) -> #NAME? | J52: =MEDIAN(J39:J43,J27:J31,J15:J19) -> #NAME? | K52: =MEDIAN(K39:K43,K27:K31,K15:K19) -> #NAME? | L52: =MEDIAN(L39:L43,L27:L31,L15:L19) -> #NAME? | M52: =MEDIAN(M39:M43,M27:M31,M15:M19) -> #NAME? | N52: =MEDIAN(N39:N43,N27:N31,N15:N19) -> #NAME? | O52: =MEDIAN(O39:O43,O27:O31,O15:O19) -> #NAME? | P52: =MEDIAN(P39:P43,P27:P31,P15:P19) -> #NAME? | Q52: =MEDIAN(Q39:Q43,Q27:Q31,Q15:Q19) -> #NAME? | S52: =MEDIAN(S39:S43,S27:S31,S15:S19) -> #NAME? | T52: =MEDIAN(T39:T43,T27:T31,T15:T19) -> #NAME? | V52: =MEDIAN(V39:V43,V27:V31,V15:V19) -> #NAME? | W52: =MEDIAN(W39:W43,W27:W31,W15:W19) -> #NAME? | X52: =MEDIAN(X39:X43,X27:X31,X15:X19) -> #NAME? | Z52: =MEDIAN(Z39:Z43,Z27:Z31,Z15:Z19) -> #VALUE!
B54: High | I54: =MAX(I39:I43,I27:I31,I15:I19) -> #NAME? | J54: =MAX(J39:J43,J27:J31,J15:J19) -> #NAME? | K54: =MAX(K39:K43,K27:K31,K15:K19) -> #NAME? | L54: =MAX(L39:L43,L27:L31,L15:L19) -> #NAME? | M54: =MAX(M39:M43,M27:M31,M15:M19) -> #NAME? | N54: =MAX(N39:N43,N27:N31,N15:N19) -> #NAME? | O54: =MAX(O39:O43,O27:O31,O15:O19) -> #NAME? | P54: =MAX(P39:P43,P27:P31,P15:P19) -> #NAME? | ... T54: =MAX(T39:T43,T27:T31,T15:T19) -> #NAME? | V54: =MAX(V39:V43,V27:V31,V15:V19) -> #NAME? | W54: =MAX(W39:W43,W27:W31,W15:W19) -> #NAME? | X54: =MAX(X39:X43,X27:X31,X15:X19) -> #NAME? | Z54: =MAX(Z39:Z43,Z27:Z31,Z15:Z19) -> #VALUE!
B55: Low | I55: =MIN(I39:I43,I27:I31,I15:I19) -> #NAME? | J55: =MIN(J39:J43,J27:J31,J15:J19) -> #NAME? | K55: =MIN(K39:K43,K27:K31,K15:K19) -> #NAME? | L55: =MIN(L39:L43,L27:L31,L15:L19) -> #NAME? | M55: =MIN(M39:M43,M27:M31,M15:M19) -> #NAME? | N55: =MIN(N39:N43,N27:N31,N15:N19) -> #NAME? | O55: =MIN(O39:O43,O27:O31,O15:O19) -> #NAME? | P55: =MIN(P39:P43,P27:P31,P15:P19) -> #NAME? | ... T55: =MIN(T39:T43,T27:T31,T15:T19) -> #NAME? | V55: =MIN(V39:V43,V27:V31,V15:V19) -> #NAME? | W55: =MIN(W39:W43,W27:W31,W15:W19) -> #NAME? | X55: =MIN(X39:X43,X27:X31,X15:X19) -> #NAME? | Z55: =MIN(Z39:Z43,Z27:Z31,Z15:Z19) -> #VALUE!

Sheet WACC
A7: x | B7: Rolling WACC | K7: Equity Risk Premium
P8: Weights
D9: 2025 | E9: =+D9+1 -> 2026 | F9: =+E9+1 -> 2027 | G9: =+F9+1 -> 2028 | H9: =+G9+1 -> 2029 | M9: ERP | N9: 2025 | O9: =+N9+1 -> 2026 | P9: =+O9+1 -> 2027 | Q9: =+P9+1 -> 2028 | R9: =+Q9+1 -> 2029
B12: Equity: | K12: =+Segments!B21 -> United States and Canada | M12: 0.0433 | N12: =+Segments!AL21/Segments!AL$26 -> 0.66008836 | O12: =Segments!AR21/Segments!AR$26 -> 0.65102842 | P12: =Segments!AT21/Segments!AT$26 -> 0.64655666 | Q12: =+Segments!AR21/Segments!AR$26 -> 0.65102842 | R12: =+Segments!AT21/Segments!AT$26 -> 0.64655666
B13: Market Cap | D13: =+Inputs!J13 -> 7188282.8 | E13: =+FCFF!AF107*FCFF!AF39 -> 7651586.1 | F13: =+FCFF!AH107*FCFF!AH39 -> 7562017.2 | G13: =+FCFF!AJ107*FCFF!AJ39 -> 7869841.6 | H13: =+FCFF!AL107*FCFF!AL39 -> 8183215.4 | K13: =+Segments!B22 -> Asia | M13: =5.27% -> 0.0527 | N13: =+Segments!AL22/Segments!AL$26 -> 0.066509786 | O13: =Segments!AR22/Segments!AR$26 -> 0.066646812 | P13: =Segments!AT22/Segments!AT$26 -> 0.066275032 | Q13: =+Segments!AR22/Segments!AR$26 -> 0.066646812 | R13: =+Segments!AT22/Segments!AT$26 -> 0.066275032
B14: % of Equity | D14: =IFERROR(D13/D35,"") -> 0.7494532 | E14: =IFERROR(E13/E35,"") -> 0.79278017 | F14: =IFERROR(E13/F35,"") -> 0.817301 | G14: =IFERROR(F13/G35,"") -> 0.76617413 | H14: =IFERROR(G13/H35,"") -> 0.77282482 | K14: =+Segments!B23 -> Europe and Middle East | M14: 0.0513 | N14: =+Segments!AL23/Segments!AL$26 -> 0.22595937 | O14: =Segments!AR23/Segments!AR$26 -> 0.23196524 | P14: =Segments!AT23/Segments!AT$26 -> 0.23543206 | Q14: =+Segments!AR23/Segments!AR$26 -> 0.23196524 | R14: =+Segments!AT23/Segments!AT$26 -> 0.23543206
B15: Risk-Free Rate | D15: 0.0416 | E15: 0.038 | F15: 0.036 | G15: 0.034 | H15: 0.034 | K15: =+Segments!B24 -> Latin America | M15: =7.96% -> 0.0796 | N15: =+Segments!AL24/Segments!AL$26 -> 0.047442481 | O15: =Segments!AR24/Segments!AR$26 -> 0.050359525 | P15: =Segments!AT24/Segments!AT$26 -> 0.051736253 | Q15: =+Segments!AR24/Segments!AR$26 -> 0.050359525 | R15: =+Segments!AT24/Segments!AT$26 -> 0.051736253
B16: Beta | D16: =+Inputs!M18 -> 0.98372155 | E16: =+D17*(1+(E28/E13)*(1-E32)) -> 0.9371742 | F16: =+E17*(1+(F28/F13)*(1-F32)) -> 0.92378549 | G16: =+F17*(1+(G28/G13)*(1-G32)) -> 0.93336517 | H16: =+G17*(1+(H28/H13)*(1-H32)) -> 0.92756007
B17: Unlevered Beta | D17: =+D16/(1+(D28/D13)*(1-D32)) -> 0.78177521 | E17: =+E16/(1+(E28/E13)*(1-E32)) -> 0.78177521 | F17: =+F16/(1+(F28/F13)*(1-F32)) -> 0.78177521 | G17: =+G16/(1+(G28/G13)*(1-G32)) -> 0.78177521 | H17: =+H16/(1+(H28/H13)*(1-H32)) -> 0.78177521
B18: Equity Risk Premium | D18: =+N18 -> 0.047455029 | E18: =+O18 -> 0.047610253 | F18: =+P18 -> 0.047684468 | G18: =+Q18 -> 0.047610253 | H18: =+R18 -> 0.047684468 | K18: ERP | N18: =+SUMPRODUCT($M12:$M16,N12:N16) -> 0.047455029 | O18: =+SUMPRODUCT($M12:$M16,O12:O16) -> 0.047610253 | P18: =+SUMPRODUCT($M12:$M16,P12:P16) -> 0.047684468 | Q18: =+SUMPRODUCT($M12:$M16,Q12:Q16) -> 0.047610253 | R18: =+SUMPRODUCT($M12:$M16,R12:R16) -> 0.047684468
B19: Ke (Cost of Equity) | D19: =IFERROR(+D15+D16*D18,"") -> 0.088282535 | E19: =IFERROR(+E15+E16*E18,"") -> 0.082619101 | F19: =IFERROR(+F15+F16*F18,"") -> 0.080050219 | G19: =IFERROR(+G15+G16*G18,"") -> 0.078437752 | H19: =IFERROR(+H15+H16*H18,"") -> 0.078230208
B21: Preferred Equity: | K21: ROIC vs WACC
B22: Market Capitalization | D22: =IFERROR(Inputs!J14,0) -> 0 | E22: =+D22*(E13/D13) -> 0 | F22: =+E22*(F13/E13) -> 0 | G22: =+F22*(G13/F13) -> 0 | H22: =+G22*(H13/G13) -> 0
B23: % of Preferred Equity | D23: =+D22/D35 -> 0 | E23: =+E22/E35 -> 0 | F23: =+F22/F35 -> 0 | G23: =+G22/G35 -> 0 | H23: =+H22/H35 -> 0
B24: Preferred Dividends | D24: =+IS!AF50 -> 0 | E24: =D24 -> 0 | F24: =E24 -> 0 | G24: =F24 -> 0 | H24: =G24 -> 0
B25: Kp (Cost of Preferred Equity) | D25: =IFERROR(D24/D22,0) -> 0 | E25: =IFERROR(E24/E22,0) -> 0 | F25: =IFERROR(F24/F22,0) -> 0 | G25: =IFERROR(G24/G22,0) -> 0 | H25: =IFERROR(H24/H22,0) -> 0
B27: Debt:
B28: Debt | C28: =+BS!AF38+BS!AF39+BS!AF44+BS!AF45 -> 2521047 | D28: =+BS!AI38+BS!AI39+BS!AI44+BS!AI45 -> 2403087 | E28: 2000000 | F28: 1800000 | G28: 2000000 | H28: 2000000
B29: % of Debt | D29: =IFERROR(D28/D35,"") -> 0.2505468 | E29: =IFERROR(E28/E35,"") -> 0.20721983 | F29: =IFERROR(F28/F35,"") -> 0.19226626 | G29: =IFERROR(G28/G35,"") -> 0.2026375 | H29: =IFERROR(H28/H35,"") -> 0.19640162
B30: Debt Spread | D30: =+D31-D15 -> -0.033342288
B31: Cost of Debt | D31: =+IS!AI36/WACC!D28 -> 0.0082577119 | E31: =+E30+E15 -> 0.038 | F31: =+F30+F15 -> 0.036 | G31: =+G30+G15 -> 0.034 | H31: =+H30+H15 -> 0.034
B32: Tax Rate | D32: =+FCFF!Z132 -> 0.22730203 | E32: =+FCFF!AF132 -> 0.23952002 | F32: =+FCFF!AH132 -> 0.23686206 | G32: =+FCFF!AJ132 -> 0.237 | H32: =+FCFF!AL132 -> 0.237
B33: Kd (After-Tax Cost of Debt) | D33: =+D31*(1-D32) -> 0.0063807171 | E33: =+E31*(1-E32) -> 0.028898239 | F33: =+F31*(1-F32) -> 0.027472966 | G33: =+G31*(1-G32) -> 0.025942 | H33: =+H31*(1-H32) -> 0.025942
B35: Total | D35: =+D13+D24+D28 -> 9591369.8 | E35: =+E13+E24+E28 -> 9651586.1 | F35: =+F13+F24+F28 -> 9362017.2 | G35: =+G13+G24+G28 -> 9869841.6 | H35: =+H13+H24+H28 -> 10183215
B37: Country/Conglomerate/... Risk Premium | D37: 0 | E37: 0 | F37: 0 | G37: 0 | H37: 0
A39: x | B39: WACC | D39: =+D19*D14+D25*D23+D33*D29+D37 -> 0.067762297 | E39: =D39 -> 0.067762297 | F39: =E39 -> 0.067762297 | G39: =F39 -> 0.067762297 | H39: =G39 -> 0.067762297
B41: NOPAT | D41: =+FCFF!Z134 -> 481811.57 | E41: =+FCFF!AF134 -> 541147.93 | F41: =+FCFF!AH134 -> 631773.75 | G41: =+FCFF!AJ134 -> 728476.74 | H41: =+FCFF!AL134 -> 786115.74
B42: Total Payout | D42: =+FCFF!Z120+FCFF!Z123 -> -513804.83 | E42: =+FCFF!AF120+FCFF!AF123 -> -114140.5 | F42: =+FCFF!AH120+FCFF!AH123 -> -74455.167 | G42: =+FCFF!AJ120+FCFF!AJ123 -> -74455.167 | H42: =+FCFF!AL120+FCFF!AL123 -> -74455.167
B43: Book Value of Equity | C43: =+BS!AF54 -> 3638431 | D43: =+C43+D41+D42 -> 3606437.7 | E43: =+D43+E41+E42 -> 4033445.2 | F43: =+E43+F41+F42 -> 4590763.8 | G43: =+F43+G41+G42 -> 5244785.3 | H43: =+G43+H41+H42 -> 5956445.9
B44: Invested Capital | C44: =+C43+C28 -> 6159478 | D44: =+D43+D28 -> 6009524.7 | E44: =+E43+E28 -> 6033445.2 | F44: =+F43+F28 -> 6390763.8 | G44: =+G43+G28 -> 7244785.3 | H44: =+H43+H28 -> 7956445.9
A45: x | B45: ROIC | D45: =+D41/((D44+C44)/2) -> 0.079186698 | E45: =+E41/((E44+D44)/2) -> 0.089869515 | F45: =+F41/((F44+E44)/2) -> 0.10170044 | G45: =+G41/((G44+F44)/2) -> 0.10684964 | H45: =+H41/((H44+G44)/2) -> 0.1034279
W49: ,

Sheet Revenue
E2: 2022A | K2: 2023A | Q2: 2024A | W2: 2025A | AC2: 2026E | AI2: 2027E | AK2: 2028E | AM2: 2029E
E3: Q1 | F3: Q2 | G3: Q3 | H3: Q4 | I3: FY | K3: Q1 | L3: Q2 | M3: Q3 | N3: Q4 | O3: FY | Q3: Q1 | R3: Q2 | S3: Q3 | T3: Q4 | U3: FY | W3: Q1 | X3: Q2 | Y3: Q3 | Z3: Q4 | AA3: FY | AC3: Q1 | AD3: Q2 | AE3: Q3 | AF3: Q4 | AG3: FY | AI3: FY | AK3: FY | AM3: FY
B4: X | C4: Analyst
C5: Commercial Foodservice | E5: 543653 | F5: 609679 | G5: 623662 | H5: 633272 | I5: 2410266 | K5: 613935 | L5: 645663 | M5: 634009 | N5: 627864 | O5: 2521471 | Q5: 590344 | R5: 619379 | S5: 600068 | T5: 609445 | U5: 2419236 | W5: 562717 | X5: 580605 | Y5: =SUM(Y6:Y9) -> 593316.11 | Z5: =SUM(Z6:Z9) -> 605444.67 | AA5: =SUM(AA6:AA9) -> 2342082.8 | AC5: =SUM(AC6:AC9) -> 574279.13 | AD5: =SUM(AD6:AD9) -> 592653.51 | AE5: =SUM(AE6:AE9) -> 606673.33 | AF5: =SUM(AF6:AF9) -> 619159.38 | AG5: =SUM(AG6:AG9) -> 2392765.4 | AI5: =SUM(AI6:AI9) -> 2497982.4 | AK5: =SUM(AK6:AK9) -> 2592943.5 | AM5: =SUM(AM6:AM9) -> 2697062.5
C6: US & Canada | E6: 374909 | F6: 454464 | G6: 464053 | H6: 472831 | I6: 1766257 | K6: 452655 | L6: 474745 | M6: 458529 | N6: 442487 | O6: 1828416 | Q6: 426528 | R6: 442395 | S6: 419515 | T6: 421923 | U6: 1710361 | W6: 413860 | X6: 412575 | Y6: =S6*(1+Y28) -> 399170.84 | Z6: =T6*(1+Z28) -> 398580.36 | AA6: =SUM(W6:Z6) -> 1624186.2 | AC6: =W6*(1+AC28) -> 422137.2 | AD6: =X6*(1+AD28) -> 420826.5 | AE6: =Y6*(1+AE28) -> 407154.26 | AF6: =Z6*(1+AF28) -> 406551.96 | AG6: =SUM(AC6:AF6) -> 1656669.9 | AI6: =AG6*(1+AI28) -> 1739503.4 | AK6: =AI6*(1+AK28) -> 1809083.6 | AM6: =AK6*(1+AM28) -> 1881446.9
C7: Asia | E7: 52016 | F7: 45802 | G7: 55243 | H7: 59132 | I7: 212193 | K7: 56526 | L7: 57453 | M7: 59922 | N7: 59138 | O7: 233039 | Q7: 51387 | R7: 55992 | S7: 53725 | T7: 54154 | U7: 215258 | W7: 48715 | X7: 51835 | Y7: =S7*(1+Y29) -> 53222.154 | Z7: =T7*(1+Z29) -> 51874.767 | AA7: =SUM(W7:Z7) -> 205646.92 | AC7: =W7*(1+AC29) -> 48346.245 | AD7: =X7*(1+AD29) -> 51442.628 | AE7: =Y7*(1+AE29) -> 53020.718 | AF7: =Z7*(1+AF29) -> 51776.599 | AG7: =SUM(AC7:AF7) -> 204586.19 | AI7: =AG7*(1+AI29) -> 204586.19 | AK7: =AI7*(1+AK29) -> 206632.05 | AM7: =AK7*(1+AM29) -> 210764.69
C8: EME | E8: 100291 | F8: 92328 | G8: 86962 | H8: 84562 | I8: 364143 | K8: 86965 | L8: 94175 | M8: 91112 | N8: 97571 | O8: 369823 | Q8: 90465 | R8: 98266 | S8: 99494 | T8: 108612 | U8: 396837 | W8: 82051 | X8: 96244 | Y8: =S8*(1+Y30) -> 106444.58 | Z8: =T8*(1+Z30) -> 123111.62 | AA8: =SUM(W8:Z8) -> 407851.2 | AC8: =W8*(1+AC30) -> 84332.018 | AD8: =X8*(1+AD30) -> 98919.583 | AE8: =Y8*(1+AE30) -> 109403.74 | AF8: =Z8*(1+AF30) -> 126534.12 | AG8: =SUM(AC8:AF8) -> 419189.46 | AI8: =AG8*(1+AI30) -> 435957.04 | AK8: =AI8*(1+AK30) -> 453395.32 | AM8: =AK8*(1+AM30) -> 476065.09
C9: LATAM | E9: 16437 | F9: 17085 | G9: 17404 | H9: 16747 | I9: 67673 | K9: 17789 | L9: 19290 | M9: 24446 | N9: 28668 | O9: 90193 | Q9: 21964 | R9: 22726 | S9: 27334 | T9: 24756 | U9: 96780 | W9: 18091 | X9: 19951 | Y9: =S9*(1+Y31) -> 34478.528 | Z9: =T9*(1+Z31) -> 31877.933 | AA9: =SUM(W9:Z9) -> 104398.46 | AC9: =W9*(1+AC31) -> 19463.669 | AD9: =X9*(1+AD31) -> 21464.798 | AE9: =Y9*(1+AE31) -> 37094.614 | AF9: =Z9*(1+AF31) -> 34296.697 | AG9: =SUM(AC9:AF9) -> 112319.78 | AI9: =AG9*(1+AI31) -> 117935.77 | AK9: =AI9*(1+AK31) -> 123832.56 | AM9: =AK9*(1+AM31) -> 128785.86
C11: Food Processing | E11: 119943 | F11: 123913 | G11: 148244 | H11: 182365 | I11: 574465 | K11: 173503 | L11: 188748 | M11: 166667 | N11: 191700 | O11: 720618 | Q11: 162683 | R11: 179404 | S11: 169523 | T11: 219393 | U11: 731003 | W11: 167906 | X11: 216195 | Y11: =SUM(Y12:Y15) -> 186908.31 | Z11: =SUM(Z12:Z15) -> 238830.83 | AA11: =SUM(AA12:AA15) -> 809840.14 | AC11: =SUM(AC12:AC15) -> 192569.13 | AD11: =SUM(AD12:AD15) -> 244383.07 | AE11: =SUM(AE12:AE15) -> 212183.44 | AF11: =SUM(AF12:AF15) -> 274934.47 | AG11: =SUM(AG12:AG15) -> 924070.11 | AI11: =SUM(AI12:AI15) -> 1019758.3 | AK11: =SUM(AK12:AK15) -> 1107569.2 | AM11: =SUM(AM12:AM15) -> 1186555.1
C12: US & Canada | E12: 94797 | F12: 87873 | G12: 104367 | H12: 123816 | I12: 410853 | K12: 116900 | L12: 126953 | M12: 111092 | N12: 124367 | O12: 479312 | Q12: 103030 | R12: 108659 | S12: 103391 | T12: 128324 | U12: 443404 | W12: 93163 | X12: 124950 | Y12: =S12*(1+Y34) -> 103138.48 | Z12: =T12*(1+Z34) -> 130650.98 | AA12: =SUM(W12:Z12) -> 451902.46 | AC12: =W12*(1+AC34) -> 95957.89 | AD12: =X12*(1+AD34) -> 129948 | AE12: =Y12*(1+AE34) -> 108295.4 | AF12: =Z12*(1+AF34) -> 138490.04 | AG12: =SUM(AC12:AF12) -> 472691.33 | AI12: =AG12*(1+AI34) -> 501052.81 | AK12: =AI12*(1+AK34) -> 536126.51 | AM12: =AK12*(1+AM34) -> 573655.36
C13: Asia | E13: 3743 | F13: 4114 | G13: 7805 | H13: 4633 | I13: 20295 | K13: 8587 | L13: 15531 | M13: 6389 | N13: 9701 | O13: 40208 | Q13: 6368 | R13: 6951 | S13: 7437 | T13: 8229 | U13: 28985 | W13: 3704 | X13: 7456 | Y13: =S13*(1+Y35) -> 7372.3344 | Z13: =T13*(1+Z35) -> 12105.496 | AA13: =SUM(W13:Z13) -> 30637.83 | AC13: =W13*(1+AC35) -> 4466.2752 | AD13: =X13*(1+AD35) -> 7997.689 | AE13: =Y13*(1+AE35) -> 7740.9511 | AF13: =Z13*(1+AF35) -> 17808.12 | AG13: =SUM(AC13:AF13) -> 38013.036 | AI13: =AG13*(1+AI35) -> 43334.861 | AK13: =AI13*(1+AK35) -> 48535.044 | AM13: =AK13*(1+AM35) -> 53388.548
C14: EME | E14: 14200 | F14: 20460 | G14: 24264 | H14: 41292 | I14: 100216 | K14: 34059 | L14: 33499 | M14: 34250 | N14: 43485 | O14: 145293 | Q14: 41825 | R14: 50354 | S14: 45280 | T14: 56643 | U14: 194102 | W14: 54688 | X14: 65223 | Y14: =S14*(1+Y36) -> 61888.704 | Z14: =T14*(1+Z36) -> 66716.863 | AA14: =SUM(W14:Z14) -> 248516.57 | AC14: =W14*(1+AC36) -> 69332.337 | AD14: =X14*(1+AD36) -> 84482.657 | AE14: =Y14*(1+AE36) -> 80455.316 | AF14: =Z14*(1+AF36) -> 78582.346 | AG14: =SUM(AC14:AF14) -> 312852.66 | AI14: =AG14*(1+AI36) -> 359780.55 | AK14: =AI14*(1+AK36) -> 395758.61 | AM14: =AK14*(1+AM36) -> 423461.71
C15: LATAM | E15: 7203 | F15: 11466 | G15: 11808 | H15: 12624 | I15: 43101 | K15: 13957 | L15: 12765 | M15: 14936 | N15: 14147 | O15: 55805 | Q15: 11460 | R15: 13440 | S15: 13415 | T15: 26197 | U15: 64512 | W15: 16351 | X15: 18566 | Y15: =S15*(1+Y37) -> 14508.796 | Z15: =T15*(1+Z37) -> 29357.49 | AA15: =SUM(W15:Z15) -> 78783.287 | AC15: =W15*(1+AC37) -> 22812.627 | AD15: =X15*(1+AD37) -> 21954.724 | AE15: =Y15*(1+AE37) -> 15691.776 | AF15: =Z15*(1+AF37) -> 40053.962 | AG15: =SUM(AC15:AF15) -> 100513.09 | AI15: =AG15*(1+AI37) -> 115590.05 | AK15: =AI15*(1+AK37) -> 127149.06 | AM15: =AK15*(1+AM37) -> 136049.49
C17: Residential Kitchen | E17: 331080 | F17: 280009 | G17: 220965 | H17: 216068 | I17: 1048122 | K17: 219958 | L17: 205571 | M17: 179975 | N17: 189012 | O17: 794516 | Q17: 173899 | R17: 192763 | S17: 173218 | T17: 185043 | U17: 724923 | W17: 176004 | X17: 181059 | Y17: =SUM(Y18:Y21) -> 156588 | Z17: =SUM(Z18:Z21) -> 188864.98 | AA17: =SUM(AA18:AA21) -> 702515.99 | AC17: =SUM(AC18:AC21) -> 177185.17 | AD17: =SUM(AD18:AD21) -> 182685.69 | AE17: =SUM(AE18:AE21) -> 158296.75 | AF17: =SUM(AF18:AF21) -> 192226.47 | AG17: =SUM(AG18:AG21) -> 710394.07 | AI17: =SUM(AI18:AI21) -> 729398.6 | AK17: =SUM(AK18:AK21) -> 755997.83 | AM17: =SUM(AM18:AM21) -> 783613.53
C18: US & Canada | E18: 229599 | F18: 189729 | G18: 145757 | H18: 136824 | I18: 701909 | K18: 143959 | L18: 134755 | M18: 116522 | N18: 118097 | O18: 513333 | Q18: 107041 | R18: 124777 | S18: 112912 | T18: 116377 | U18: 461107 | W18: 112851 | X18: 111122 | Y18: =S18*(1+Y40) -> 99839.34 | Z18: =T18*(1+Z40) -> 117540.77 | AA18: =SUM(W18:Z18) -> 441353.11 | AC18: =W18*(1+AC40) -> 113979.51 | AD18: =X18*(1+AD40) -> 112233.22 | AE18: =Y18*(1+AE40) -> 100837.73 | AF18: =Z18*(1+AF40) -> 118716.18 | AG18: =SUM(AC18:AF18) -> 445766.64 | AI18: =AG18*(1+AI40) -> 456910.81 | AK18: =AI18*(1+AK40) -> 472902.69 | AM18: =AK18*(1+AM40) -> 489454.28
C19: Asia | E19: 6005 | F19: 10072 | G19: 11647 | H19: 4397 | I19: 32121 | K19: 3189 | L19: 2092 | M19: 3371 | N19: 3959 | O19: 12611 | Q19: 2596 | R19: 3843 | S19: 5994 | T19: 6029 | U19: 18462 | W19: 2808 | X19: 3198 | Y19: =S19*(1+Y41) -> 6196.4118 | Z19: =T19*(1+Z41) -> 7304.8749 | AA19: =SUM(W19:Z19) -> 19507.287 | AC19: =W19*(1+AC41) -> 2271.4566 | AD19: =X19*(1+AD41) -> 3066.7381 | AE19: =Y19*(1+AE41) -> 6405.6589 | AF19: =Z19*(1+AF41) -> 8850.7542 | AG19: =SUM(AC19:AF19) -> 20594.608 | AI19: =AG19*(1+AI41) -> 21212.446 | AK19: =AI19*(1+AK41) -> 21848.819 | AM19: =AK19*(1+AM41) -> 22504.284
C20: EME | E20: 93583 | F20: 78382 | G20: 60200 | H20: 71675 | I20: 303840 | K20: 70386 | L20: 66771 | M20: 57474 | N20: 63570 | O20: 258201 | Q20: 62157 | R20: 61468 | S20: 52952 | T20: 59397 | U20: 235974 | W20: 58920 | X20: 64673 | Y20: =S20*(1+Y42) -> 49669.997 | Z20: =T20*(1+Z42) -> 60584.94 | AA20: =SUM(W20:Z20) -> 233847.94 | AC20: =W20*(1+AC42) -> 59509.2 | AD20: =X20*(1+AD42) -> 65319.73 | AE20: =Y20*(1+AE42) -> 50166.697 | AF20: =Z20*(1+AF42) -> 61190.789 | AG20: =SUM(AC20:AF20) -> 236186.42 | AI20: =AG20*(1+AI42) -> 243272.01 | AK20: =AI20*(1+AK42) -> 253002.89 | AM20: =AK20*(1+AM42) -> 263123
C21: LATAM | E21: 1893 | F21: 1826 | G21: 3361 | H21: 3172 | I21: 10252 | K21: 2424 | L21: 1953 | M21: 2608 | N21: 3386 | O21: 10371 | Q21: 2105 | R21: 2675 | S21: 1360 | T21: 3240 | U21: 9380 | W21: 1425 | X21: 2066 | Y21: =S21*(1+Y43) -> 882.25371 | Z21: =T21*(1+Z43) -> 3434.4 | AA21: =SUM(W21:Z21) -> 7807.6537 | AC21: =W21*(1+AC43) -> 1425 | AD21: =X21*(1+AD43) -> 2066 | AE21: =Y21*(1+AE43) -> 886.66498 | AF21: =Z21*(1+AF43) -> 3468.744 | AG21: =SUM(AC21:AF21) -> 7846.409 | AI21: =AG21*(1+AI43) -> 8003.3372 | AK21: =AI21*(1+AK43) -> 8243.4373 | AM21: =AK21*(1+AM43) -> 8531.9576
B22: x
C23: Consolidated | E23: =E17+E11+E5 -> 994676 | F23: =F17+F11+F5 -> 1013601 | G23: =G17+G11+G5 -> 992871 | H23: =H17+H11+H5 -> 1031705 | I23: =I17+I11+I5 -> 4032853 | K23: =K17+K11+K5 -> 1007396 | L23: =L17+L11+L5 -> 1039982 | M23: =M17+M11+M5 -> 980651 | N23: =N17+N11+N5 -> 1008576 | O23: =O17+O11+O5 -> 4036605 | Q23: =Q17+Q11+Q5 -> 926926 | R23: =R17+R11+R5 -> 991546 | S23: =S17+S11+S5 -> 942809 | T23: =T17+T11+T5 -> 1013881 | U23: =U17+U11+U5 -> 3875162 | W23: =W17+W11+W5 -> 906627 | X23: =X17+X11+X5 -> 977859 | Y23: =Y17+Y11+Y5 -> 936812.42 | Z23: =Z17+Z11+Z5 -> 1033140.5 | AA23: =AA17+AA11+AA5 -> 3854438.9 | AC23: =AC17+AC11+AC5 -> 944033.43 | AD23: =AD17+AD11+AD5 -> 1019722.3 | AE23: =AE17+AE11+AE5 -> 977153.53 | AF23: =AF17+AF11+AF5 -> 1086320.3 | AG23: =AG17+AG11+AG5 -> 4027229.5 | AI23: =AI17+AI11+AI5 -> 4247139.3 | AK23: =AK17+AK11+AK5 -> 4456510.5 | AM23: =AM17+AM11+AM5 -> 4667231.2
C26: % growth yoy
C27: Commercial Foodservice | K27: 0.12927731 | L27: 0.059021223 | M27: 0.016590717 | N27: -0.0085397744 | O27: 0.046138061 | Q27: -0.038425892 | R27: -0.040708543 | S27: -0.05353394 | T27: -0.029335971 | U27: -0.040545777 | W27: -0.046798138 | X27: -0.062601412 | Y27: =Y5/S5-1 -> -0.01125188 | Z27: =Z5/T5-1 -> -0.0065638874 | AA27: =AA5/U5-1 -> -0.031891565 | AC27: =AC5/W5-1 -> 0.020546976 | AD27: =AD5/X5-1 -> 0.020751647 | AE27: =AE5/Y5-1 -> 0.022512834 | AF27: =AF5/Z5-1 -> 0.022652286 | AG27: =AG5/AA5-1 -> 0.021639959 | AI27: =AI5/AG5-1 -> 0.043972997 | AK27: =AK5/AI5-1 -> 0.038015107 | AM27: =AM5/AK5-1 -> 0.040154771 | AP27: =(AM5/U5)^(1/5)-1 -> 0.021980375
C28: US & Canada | K28: 0.20737299 | L28: 0.044626197 | M28: -0.011903813 | N28: -0.064175149 | O28: 0.0351925 | Q28: -0.057719455 | R28: -0.068141845 | S28: -0.085085131 | T28: -0.046473682 | U28: -0.064566816 | W28: -0.029700278 | X28: -0.067405825 | Y28: =AVERAGE(S28,M28) -> -0.048494472 | Z28: =AVERAGE(T28,N28) -> -0.055324415 | AA28: =AA6/U6-1 -> -0.050383984 | AC28: 0.02 | AD28: 0.02 | AE28: 0.02 | AF28: 0.02 | AG28: =AG6/AA6-1 -> 0.02 | AI28: 0.05 | AK28: 0.04 | AM28: 0.04 | AP28: =(AM6/U6)^(1/5)-1 -> 0.019250272
C29: Asia | K29: 0.086704091 | L29: 0.25437754 | M29: 0.084698514 | N29: 0.0001014679 | O29: 0.098240753 | Q29: -0.090913916 | R29: -0.025429481 | S29: -0.10341778 | T29: -0.084277453 | U29: -0.076300533 | W29: -0.051997587 | X29: -0.074242749 | Y29: =AVERAGE(S29,M29) -> -0.0093596313 | Z29: =AVERAGE(T29,N29) -> -0.042087992 | AA29: =AA7/U7-1 -> -0.044649116 | AC29: =AVERAGE(AA29,U29,O29) -> -0.0075696322 | AD29: -0.0075696322 | AE29: =AD29/2 -> -0.0037848161 | AF29: =AE29/2 -> -0.001892408 | AG29: =AG7/AA7-1 -> -0.0051580194 | AI29: 0 | AK29: 0.01 | AM29: 0.02 | AP29: =(AM7/U7)^(1/5)-1 -> -0.004210112
C30: EME | K30: -0.13287334 | L30: 0.020004766 | M30: 0.047721994 | N30: 0.15383979 | O30: 0.015598268 | Q30: 0.040246076 | R30: 0.043440404 | S30: 0.091996663 | T30: 0.11315862 | U30: 0.073045754 | W30: -0.093008346 | X30: -0.020576802 | Y30: =AVERAGE(S30,M30) -> 0.069859328 | Z30: =AVERAGE(T30,N30) -> 0.1334992 | AA30: =AA8/U8-1 -> 0.027754972 | AC30: 0.0278 | AD30: 0.0278 | AE30: 0.0278 | AF30: 0.0278 | AG30: =AG8/AA8-1 -> 0.0278 | AI30: 0.04 | AK30: 0.04 | AM30: 0.05 | AP30: =(AM8/U8)^(1/5)-1 -> 0.037076601
C31: LATAM | K31: 0.082253453 | L31: 0.12906058 | M31: 0.40461963 | N31: 0.71182898 | O31: 0.33277674 | Q31: 0.2346956 | R31: 0.17812338 | S31: 0.11813794 | T31: -0.13645877 | U31: 0.073032275 | W31: -0.176334 | X31: -0.12210684 | Y31: =AVERAGE(S31,M31) -> 0.26137878 | Z31: =AVERAGE(T31,N31) -> 0.28768511 | AA31: =AA9/U9-1 -> 0.078719365 | AC31: =AVERAGE(AA31,U31) -> 0.07587582 | AD31: 0.07587582 | AE31: 0.07587582 | AF31: 0.07587582 | AG31: =AG9/AA9-1 -> 0.07587582 | AI31: 0.05 | AK31: 0.05 | AM31: 0.04 | AP31: =(AM9/U9)^(1/5)-1 -> 0.058806288
C33: Food Processing | K33: 0.44654544 | L33: 0.52323001 | M33: 0.12427484 | N33: 0.05118855 | O33: 0.25441585 | Q33: -0.062362034 | R33: -0.04950516 | S33: 0.017135966 | T33: 0.14446009 | U33: 0.014411241 | W33: 0.032105383 | X33: 0.20507347 | Y33: =Y11/S11-1 -> 0.10255429 | Z33: =Z11/T11-1 -> 0.088598222 | AA33: =AA11/U11-1 -> 0.1078479 | AC33: =AC11/W11-1 -> 0.14688652 | AD33: =AD11/X11-1 -> 0.13038262 | AE33: =AE11/Y11-1 -> 0.13522743 | AF33: =AF11/Z11-1 -> 0.15116825 | AG33: =AG11/AA11-1 -> 0.14105249 | AI33: =AI11/AG11-1 -> 0.10355076 | AK33: =AK11/AI11-1 -> 0.086109564 | AM33: =AM11/AK11-1 -> 0.071314637 | AP33: =(AM11/U11)^(1/5)-1 -> 0.10172639
C34: US & Canada | K34: 0.23316139 | L34: 0.44473274 | M34: 0.064436077 | N34: 0.0044501518 | O34: 0.16662651 | Q34: -0.11864842 | R34: -0.14410057 | S34: -0.069320923 | T34: 0.031817122 | U34: -0.074915713 | W34: -0.095768223 | X34: 0.14992776 | Y34: =AVERAGE(S34,M34) -> -0.0024424233 | Z34: =AVERAGE(T34,N34) -> 0.018133637 | AA34: =AA12/U12-1 -> 0.019166395 | AC34: 0.03 | AD34: 0.04 | AE34: 0.05 | AF34: 0.06 | AG34: =AG12/AA12-1 -> 0.046003009 | AI34: 0.06 | AK34: 0.07 | AM34: 0.07 | AP34: =(AM12/U12)^(1/5)-1 -> 0.052859184
C35: Asia | K35: 1.2941491 | L35: 2.775158 | M35: -0.18142217 | N35: 1.0938916 | O35: 0.98117763 | Q35: -0.25841388 | R35: -0.5524435 | S35: 0.16403193 | T35: -0.15173693 | U35: -0.27912356 | W35: -0.41834171 | X35: 0.072651417 | Y35: =AVERAGE(S35,M35) -> -0.0086951177 | Z35: =AVERAGE(T35,N35) -> 0.47107736 | AA35: =AA13/U13-1 -> 0.057023632 | AC35: =AVERAGE(W35,Q35,K35) -> 0.20579783 | AD35: =X35 -> 0.072651417 | AE35: 0.05 | AF35: =AVERAGE(Z35,T35,N35) -> 0.47107736 | AG35: =AG13/AA13-1 -> 0.2407222 | AI35: 0.14 | AK35: 0.12 | AM35: 0.1 | AP35: =(AM13/U13)^(1/5)-1 -> 0.1299389
C36: EME | K36: 1.3985211 | L36: 0.63729228 | M36: 0.41155621 | N36: 0.053109561 | O36: 0.44979844 | Q36: 0.22801609 | R36: 0.50314935 | S36: 0.3220438 | T36: 0.3025871 | U36: 0.33593497 | W36: 0.30754334 | X36: 0.29528935 | Y36: =AVERAGE(S36,M36) -> 0.36680001 | Z36: =AVERAGE(T36,N36) -> 0.17784833 | AA36: =AA14/U14-1 -> 0.28034006 | AC36: =AVERAGE(W36,Q36) -> 0.26777971 | AD36: =X36 -> 0.29528935 | AE36: 0.3 | AF36: =AVERAGE(Z36,T36,N36) -> 0.17784833 | AG36: =AG14/AA14-1 -> 0.25888048 | AI36: 0.15 | AK36: 0.1 | AM36: 0.07 | AP36: =(AM14/U14)^(1/5)-1 -> 0.16884474
C37: LATAM | K37: 0.93766486 | L37: 0.11329147 | M37: 0.26490515 | N37: 0.12064322 | O37: 0.29474954 | Q37: -0.17890664 | R37: 0.052878966 | S37: -0.10183449 | T37: 0.85177069 | U37: 0.15602545 | W37: 0.42678883 | X37: 0.38139881 | Y37: =AVERAGE(S37,M37) -> 0.081535328 | Z37: =N37 -> 0.12064322 | AA37: =AA15/U15-1 -> 0.2212191 | AC37: =AVERAGE(W37,Q37,K37) -> 0.39518235 | AD37: =AVERAGE(X37,R37,L37) -> 0.18252308 | AE37: =AVERAGE(Y37,S37,M37) -> 0.081535328 | AF37: =AVERAGE(Z37,T37,N37) -> 0.36435238 | AG37: =AG15/AA15-1 -> 0.2758174 | AI37: 0.15 | AK37: 0.1 | AM37: 0.07 | AP37: =(AM15/U15)^(1/5)-1 -> 0.16094403
C39: Residential Kitchen | K39: -0.33563489 | L39: -0.26584146 | M39: -0.18550449 | N39: -0.12521984 | O39: -0.24196229 | Q39: -0.20939907 | R39: -0.062304508 | S39: -0.037544103 | T39: -0.020998667 | U39: -0.087591691 | W39: 0.012104727 | X39: -0.060717046 | Y39: =Y17/S17-1 -> -0.096006173 | Z39: =Z17/T17-1 -> 0.020654577 | AA39: =AA17/U17-1 -> -0.030909507 | AC39: =AC17/W17-1 -> 0.0067110212 | AD39: =AD17/X17-1 -> 0.0089842984 | AE39: =AE17/Y17-1 -> 0.010912405 | AF39: =AF17/Z17-1 -> 0.017798325 | AG39: =AG17/AA17-1 -> 0.011214103 | AI39: =AI17/AG17-1 -> 0.026752088 | AK39: =AK17/AI17-1 -> 0.036467347 | AM39: =AM17/AK17-1 -> 0.036528801 | AP39: =(AM17/U17)^(1/5)-1 -> 0.015691947
C40: US & Canada | K40: -0.37299814 | L40: -0.28975012 | M40: -0.20057356 | N40: -0.13686926 | O40: -0.26866161 | Q40: -0.25644802 | R40: -0.07404549 | S40: -0.030981274 | T40: -0.014564299 | U40: -0.10173903 | W40: 0.054278267 | X40: -0.10943523 | Y40: =AVERAGE(S40,M40) -> -0.11577742 | Z40: 0.01 | AA40: =AA18/U18-1 -> -0.042840142 | AC40: 0.01 | AD40: 0.01 | AE40: 0.01 | AF40: 0.01 | AG40: =AG18/AA18-1 -> 0.01 | AI40: 0.025 | AK40: 0.035 | AM40: 0.035 | AP40: =(AM18/U18)^(1/5)-1 -> 0.01200366
C41: Asia | K41: -0.46894255 | L41: -0.79229547 | M41: -0.71056925 | N41: -0.099613373 | O41: -0.6073908 | Q41: -0.18595171 | R41: 0.83699809 | S41: 0.77810739 | T41: 0.52285931 | U41: 0.46396003 | W41: 0.081664099 | X41: -0.16783763 | Y41: =AVERAGE(S41,M41) -> 0.033769071 | Z41: =AVERAGE(T41,N41) -> 0.21162297 | AA41: =AA19/U19-1 -> 0.05661828 | AC41: =AVERAGE(W41,Q41,K41) -> -0.19107672 | AD41: =AVERAGE(X41,R41,L41) -> -0.041045004 | AE41: =AVERAGE(Y41,S41,M41) -> 0.033769071 | AF41: =AVERAGE(Z41,T41,N41) -> 0.21162297 | AG41: =AG19/AA19-1 -> 0.055739224 | AI41: 0.03 | AK41: 0.03 | AM41: 0.03 | AP41: =(AM19/U19)^(1/5)-1 -> 0.040392685
C42: EME | K42: -0.24787622 | L42: -0.1481335 | M42: -0.045282392 | N42: -0.11307987 | O42: -0.15020735 | Q42: -0.11691245 | R42: -0.079420707 | S42: -0.078679055 | T42: -0.065644172 | U42: -0.086084097 | W42: -0.052077803 | X42: 0.052140951 | Y42: =AVERAGE(S42,M42) -> -0.061980723 | Z42: 0.02 | AA42: =AA20/U20-1 -> -0.0090097353 | AC42: 0.01 | AD42: 0.01 | AE42: 0.01 | AF42: 0.01 | AG42: =AG20/AA20-1 -> 0.01 | AI42: 0.03 | AK42: 0.04 | AM42: 0.04 | AP42: =(AM20/U20)^(1/5)-1 -> 0.022018914
C43: LATAM | K43: 0.28050713 | L43: 0.069550931 | M43: -0.22404046 | N43: 0.067465322 | O43: 0.011607491 | Q43: -0.13160066 | R43: 0.36968766 | S43: -0.47852761 | T43: -0.043118724 | U43: -0.095554913 | W43: -0.32304038 | X43: -0.22766355 | Y43: =AVERAGE(S43,M43) -> -0.35128404 | Z43: 0.06 | AA43: =AA21/U21-1 -> -0.16762754 | AC43: 0 | AD43: 0 | AE43: 0.005 | AF43: 0.01 | AG43: =AG21/AA21-1 -> 0.0049637535 | AI43: 0.02 | AK43: 0.03 | AM43: 0.035 | AP43: =(AM21/U21)^(1/5)-1 -> -0.018773723
C45: Consolidated | K45: =K23/E23-1 -> 0.012788084 | L45: =L23/F23-1 -> 0.026027007 | M45: =M23/G23-1 -> -0.012307742 | N45: =N23/H23-1 -> -0.02241823 | O45: =O23/I23-1 -> 0.00093035873 | Q45: =Q23/K23-1 -> -0.079879213 | R45: =R23/L23-1 -> -0.046573883 | S45: =S23/M23-1 -> -0.038588652 | T45: =T23/N23-1 -> 0.0052598912 | U45: =U23/O23-1 -> -0.039994748 | W45: =W23/Q23-1 -> -0.021899267 | X45: =X23/R23-1 -> -0.013803696 | Y45: =Y23/S23-1 -> -0.0063603335 | Z45: =Z23/T23-1 -> 0.018995805 | AA45: =AA23/U23-1 -> -0.0053476715 | AC45: =AC23/W23-1 -> 0.041258895 | AD45: =AD23/X23-1 -> 0.042811149 | AE45: =AE23/Y23-1 -> 0.0430621 | AF45: =AF23/Z23-1 -> 0.051473952 | AG45: =AG23/AA23-1 -> 0.044828997 | AI45: =AI23/AG23-1 -> 0.054605717 | AK45: =AK23/AI23-1 -> 0.049297004 | AM45: =AM23/AK23-1 -> 0.047283775 | AO45: CAGR 2024-29 | AP45: =(AM23/U23)^(1/5)-1 -> 0.037896124
E53: 2024A | K53: 2025A | Q53: 2026E | W53: 2027E | Y53: 2028E | AA53: 2029E
E54: Q1 | F54: Q2 | G54: Q3 | H54: Q4 | I54: FY | K54: Q1 | L54: Q2 | M54: Q3 | N54: Q4 | O54: FY | Q54: Q1 | R54: Q2 | S54: Q3 | T54: Q4 | U54: FY | W54: FY | Y54: FY | AA54: FY
C55: Market CAGR
C56: Commercial Foodservice | E56: 590344 | F56: 619379 | G56: 600068 | H56: 609445 | I56: 2419236 | K56: 562717 | L56: 580605 | M56: =SUM(M57:M60) -> 620815.75 | N56: =SUM(N57:N60) -> 630641.81 | O56: =SUM(O57:O60) -> 2394779.6 | Q56: =SUM(Q57:Q60) -> 581557.55 | R56: =SUM(R57:R60) -> 600479.14 | S56: =SUM(S57:S60) -> 642395.23 | T56: =SUM(T57:T60) -> 652693.46 | U56: =SUM(U57:U60) -> 2477125.4 | W56: =SUM(W57:W60) -> 2562753.5 | Y56: =SUM(Y57:Y60) -> 2651813.5 | AA56: =SUM(AA57:AA60) -> 2744462.2
B57: =Industry!$M$18 -> 0.02551911 | C57: US & Canada | E57: 426528 | F57: 442395 | G57: 419515 | H57: 421923 | I57: 1710361 | K57: 413860 | L57: 412575 | M57: =G57*(1+$B$57) -> 430220.65 | N57: =H57*(1+$B$57) -> 432690.1 | O57: =SUM(K57:N57) -> 1689345.7 | Q57: =K57*(1+$B57) -> 424421.34 | R57: =L57*(1+$B57) -> 423103.55 | S57: =M57*(1+$B57) -> 441199.5 | T57: =N57*(1+$B57) -> 443731.97 | U57: =SUM(Q57:T57) -> 1732456.4 | W57: =U57*(1+$B57) -> 1776667.1 | Y57: =W57*(1+$B57) -> 1822006.1 | AA57: =Y57*(1+$B57) -> 1868502
B58: =Industry!$M$12 -> 0.055618571 | C58: Asia | E58: 51387 | F58: 55992 | G58: 53725 | H58: 54154 | I58: 215258 | K58: 48715 | L58: 51835 | M58: =G58*(1+$B$58) -> 56713.108 | N58: =H58*(1+$B$58) -> 57165.968 | O58: =SUM(K58:N58) -> 214429.08 | Q58: =K58*(1+$B58) -> 51424.459 | R58: =L58*(1+$B58) -> 54717.989 | S58: =M58*(1+$B58) -> 59867.41 | T58: =N58*(1+$B58) -> 60345.458 | U58: =SUM(Q58:T58) -> 226355.31 | W58: =U58*(1+$B58) -> 238944.87 | Y58: =W58*(1+$B58) -> 252234.65 | AA58: =Y58*(1+$B58) -> 266263.58
B59: =Industry!$M$12 -> 0.055618571 | C59: EME | E59: 90465 | F59: 98266 | G59: 99494 | H59: 108612 | I59: 396837 | K59: 82051 | L59: 96244 | M59: =G59*(1+$B$59) -> 105027.71 | N59: =H59*(1+$B$59) -> 114652.84 | O59: =SUM(K59:N59) -> 397975.56 | Q59: =K59*(1+$B59) -> 86614.559 | R59: =L59*(1+$B59) -> 101596.95 | S59: =M59*(1+$B59) -> 110869.21 | T59: =N59*(1+$B59) -> 121029.67 | U59: =SUM(Q59:T59) -> 420110.39 | W59: =U59*(1+$B59) -> 443476.33 | Y59: =W59*(1+$B59) -> 468141.85 | AA59: =Y59*(1+$B59) -> 494179.23
B60: =Industry!$M$12 -> 0.055618571 | C60: LATAM | E60: 21964 | F60: 22726 | G60: 27334 | H60: 24756 | I60: 96780 | K60: 18091 | L60: 19951 | M60: =G60*(1+$B$60) -> 28854.278 | N60: =H60*(1+$B$60) -> 26132.893 | O60: =SUM(K60:N60) -> 93029.171 | Q60: =K60*(1+$B60) -> 19097.196 | R60: =L60*(1+$B60) -> 21060.646 | S60: =M60*(1+$B60) -> 30459.112 | T60: =N60*(1+$B60) -> 27586.368 | U60: =SUM(Q60:T60) -> 98203.321 | W60: =U60*(1+$B60) -> 103665.25 | Y60: =W60*(1+$B60) -> 109430.96 | AA60: =Y60*(1+$B60) -> 115517.36
C62: Food Processing | E62: 162683 | F62: 179404 | G62: 169523 | H62: 219393 | I62: 731003 | K62: 167906 | L62: 216195 | M62: =SUM(M63:M66) -> 174351.52 | N62: =SUM(N63:N66) -> 225672.45 | O62: =SUM(O63:O66) -> 784124.98 | Q62: =SUM(Q63:Q66) -> 172739.85 | R62: =SUM(R63:R66) -> 222391.28 | S62: =SUM(S63:S66) -> 179318.82 | T62: =SUM(T63:T66) -> 232133.28 | U62: =SUM(U63:U66) -> 806583.24 | W62: =SUM(W63:W66) -> 829690.63 | Y62: =SUM(Y63:Y66) -> 853466.08 | AA62: =SUM(AA63:AA66) -> 877929.1
B63: =Industry!$M$20 -> 0.02631401 | C63: US & Canada | E63: 103030 | F63: 108659 | G63: 103391 | H63: 128324 | I63: 443404 | K63: 93163 | L63: 124950 | M63: =G63*(1+$B$63) -> 106111.63 | N63: =H63*(1+$B$63) -> 131700.72 | O63: =SUM(K63:N63) -> 455925.35 | Q63: =K63*(1+$B$63) -> 95614.492 | R63: =L63*(1+$B$63) -> 128237.94 | S63: =M63*(1+$B$63) -> 108903.85 | T63: =N63*(1+$B$63) -> 135166.29 | U63: =SUM(Q63:T63) -> 467922.57 | W63: =U63*(1+$B63) -> 480235.49 | Y63: =W63*(1+$B63) -> 492872.42 | AA63: =Y63*(1+$B63) -> 505841.86
B64: =Industry!$M$14 -> 0.031874004 | C64: Asia | E64: 6368 | F64: 6951 | G64: 7437 | H64: 8229 | I64: 28985 | K64: 3704 | L64: 7456 | M64: =G64*(1+$B$64) -> 7674.047 | N64: =H64*(1+$B$64) -> 8491.2912 | O64: =SUM(K64:N64) -> 27325.338 | Q64: =K64*(1+$B64) -> 3822.0613 | R64: =L64*(1+$B64) -> 7693.6526 | S64: =M64*(1+$B64) -> 7918.6496 | T64: =N64*(1+$B64) -> 8761.9426 | U64: =SUM(Q64:T64) -> 28196.306 | W64: =U64*(1+$B64) -> 29095.035 | Y64: =W64*(1+$B64) -> 30022.411 | AA64: =Y64*(1+$B64) -> 30979.345
B65: =Industry!$M$14 -> 0.031874004 | C65: EME | E65: 41825 | F65: 50354 | G65: 45280 | H65: 56643 | I65: 194102 | K65: 54688 | L65: 65223 | M65: =G65*(1+$B$65) -> 46723.255 | N65: =H65*(1+$B$65) -> 58448.439 | O65: =SUM(K65:N65) -> 225082.69 | Q65: =K65*(1+$B65) -> 56431.126 | R65: =L65*(1+$B65) -> 67301.918 | S65: =M65*(1+$B65) -> 48212.512 | T65: =N65*(1+$B65) -> 60311.425 | U65: =SUM(Q65:T65) -> 232256.98 | W65: =U65*(1+$B65) -> 239659.94 | Y65: =W65*(1+$B65) -> 247298.86 | AA65: =Y65*(1+$B65) -> 255181.27
B66: =Industry!$M$14 -> 0.031874004 | C66: LATAM | E66: 11460 | F66: 13440 | G66: 13415 | H66: 26197 | I66: 64512 | K66: 16351 | L66: 18566 | M66: =G66*(1+$B$66) -> 13842.59 | N66: =H66*(1+$B$66) -> 27032.003 | O66: =SUM(K66:N66) -> 75791.593 | Q66: =K66*(1+$B66) -> 16872.172 | R66: =L66*(1+$B66) -> 19157.773 | S66: =M66*(1+$B66) -> 14283.809 | T66: =N66*(1+$B66) -> 27893.621 | U66: =SUM(Q66:T66) -> 78207.375 | W66: =U66*(1+$B66) -> 80700.157 | Y66: =W66*(1+$B66) -> 83272.394 | AA66: =Y66*(1+$B66) -> 85926.619
C68: Residential Kitchen | E68: 173899 | F68: 192763 | G68: 173218 | H68: 185043 | I68: 724923 | K68: 176004 | L68: 181059 | M68: =SUM(M69:M72) -> 177668.3 | N68: =SUM(N69:N72) -> 189847.67 | O68: =SUM(O69:O72) -> 724578.97 | Q68: =SUM(Q69:Q72) -> 180548.25 | R68: =SUM(R69:R72) -> 185793 | S68: =SUM(S69:S72) -> 182238.51 | T68: =SUM(T69:T72) -> 194783.24 | U68: =SUM(U69:U72) -> 743362.99 | W68: =SUM(W69:W72) -> 762657.91 | Y68: =SUM(Y69:Y72) -> 782478.27 | AA68: =SUM(AA69:AA72) -> 802839.07
B69: =Industry!$M$22 -> 0.021542301 | C69: US & Canada | E69: 107041 | F69: 124777 | G69: 112912 | H69: 116377 | I69: 461107 | K69: 112851 | L69: 111122 | M69: =G69*(1+$B$69) -> 115344.38 | N69: =H69*(1+$B$69) -> 118884.03 | O69: =SUM(K69:N69) -> 458201.41 | Q69: =K69*(1+$B$69) -> 115282.07 | R69: =L69*(1+$B$69) -> 113515.82 | S69: =M69*(1+$B$69) -> 117829.17 | T69: =N69*(1+$B$69) -> 121445.06 | U69: =SUM(Q69:T69) -> 468072.13 | W69: =U69*(1+$B69) -> 478155.48 | Y69: =W69*(1+$B69) -> 488456.04 | AA69: =Y69*(1+$B69) -> 498978.51
B70: =Industry!$M$16 -> 0.033461197 | C70: Asia | E70: 2596 | F70: 3843 | G70: 5994 | H70: 6029 | I70: 18462 | K70: 2808 | L70: 3198 | M70: =G70*(1+$B70) -> 6194.5664 | N70: =H70*(1+$B70) -> 6230.7376 | O70: =SUM(K70:N70) -> 18431.304 | Q70: =K70*(1+$B70) -> 2901.959 | R70: =L70*(1+$B70) -> 3305.0089 | S70: =M70*(1+$B70) -> 6401.844 | T70: =N70*(1+$B70) -> 6439.2255 | U70: =SUM(Q70:T70) -> 19048.037 | W70: =U70*(1+$B70) -> 19685.408 | Y70: =W70*(1+$B70) -> 20344.105 | AA70: =Y70*(1+$B70) -> 21024.843
B71: =Industry!$M$16 -> 0.033461197 | C71: EME | E71: 62157 | F71: 61468 | G71: 52952 | H71: 59397 | I71: 235974 | K71: 58920 | L71: 64673 | M71: =G71*(1+$B71) -> 54723.837 | N71: =H71*(1+$B71) -> 61384.495 | O71: =SUM(K71:N71) -> 239701.33 | Q71: =K71*(1+$B71) -> 60891.534 | R71: =L71*(1+$B71) -> 66837.036 | S71: =M71*(1+$B71) -> 56554.962 | T71: =N71*(1+$B71) -> 63438.493 | U71: =SUM(Q71:T71) -> 247722.03 | W71: =U71*(1+$B71) -> 256011.1 | Y71: =W71*(1+$B71) -> 264577.54 | AA71: =Y71*(1+$B71) -> 273430.62
B72: =Industry!$M$16 -> 0.033461197 | C72: LATAM | E72: 2105 | F72: 2675 | G72: 1360 | H72: 3240 | I72: 9380 | K72: 1425 | L72: 2066 | M72: =G72*(1+$B72) -> 1405.5072 | N72: =H72*(1+$B72) -> 3348.4143 | O72: =SUM(K72:N72) -> 8244.9215 | Q72: =K72*(1+$B72) -> 1472.6822 | R72: =L72*(1+$B72) -> 2135.1308 | S72: =M72*(1+$B72) -> 1452.5372 | T72: =N72*(1+$B72) -> 3460.4562 | U72: =SUM(Q72:T72) -> 8520.8065 | W72: =U72*(1+$B72) -> 8805.9228 | Y72: =W72*(1+$B72) -> 9100.5796 | AA72: =Y72*(1+$B72) -> 9405.0959
C74: Consolidated | E74: =E68+E62+E56 -> 926926 | F74: =F68+F62+F56 -> 991546 | G74: =G68+G62+G56 -> 942809 | H74: =H68+H62+H56 -> 1013881 | I74: =I68+I62+I56 -> 3875162 | K74: =K68+K62+K56 -> 906627 | L74: =L68+L62+L56 -> 977859 | M74: =M68+M62+M56 -> 972835.57 | N74: =N68+N62+N56 -> 1046161.9 | O74: =O68+O62+O56 -> 3903483.5 | Q74: =Q68+Q62+Q56 -> 934845.65 | R74: =R68+R62+R56 -> 1008663.4 | S74: =S68+S62+S56 -> 1003952.6 | T74: =T68+T62+T56 -> 1079610 | U74: =U68+U62+U56 -> 4027071.6 | W74: =W68+W62+W56 -> 4155102.1 | Y74: =Y68+Y62+Y56 -> 4287757.9 | AA74: =AA68+AA62+AA56 -> 4425230.4
F76: Values in USD (thousands)
F77: Operating assumptions | I77: 2024A | J77: 2025A | K77: 2026E | L77: 2027E | M77: 2028E | N77: 2029E
F78: Revenue by segment:
F79: =C56 -> Commercial Foodservice | I79: =I56 -> 2419236 | J79: =O56 -> 2394779.6 | K79: =U56 -> 2477125.4 | L79: =W56 -> 2562753.5 | M79: =Y56 -> 2651813.5 | N79: =AA56 -> 2744462.2
F80: %YoY Growth | I80: =I79/O5-1 -> -0.040545777 | J80: =J79/I79-1 -> -0.010109161 | K80: =K79/J79-1 -> 0.034385554 | L80: =L79/K79-1 -> 0.034567557 | M80: =M79/L79-1 -> 0.034751672 | N80: =N79/M79-1 -> 0.034937856
F81: =C62 -> Food Processing | I81: =I62 -> 731003 | J81: =O62 -> 784124.98 | K81: =U62 -> 806583.24 | L81: =W62 -> 829690.63 | M81: =Y62 -> 853466.08 | N81: =AA62 -> 877929.1
F82: =F80 -> %YoY Growth | I82: =U11/O11-1 -> 0.014411241 | J82: =J81/I81-1 -> 0.072669984 | K82: =K81/J81-1 -> 0.028641174 | L82: =L81/K81-1 -> 0.028648488 | M82: =M81/L81-1 -> 0.028655808 | N82: =N81/M81-1 -> 0.028663135
F83: =C68 -> Residential Kitchen | I83: =I68 -> 724923 | J83: =O68 -> 724578.97 | K83: =U68 -> 743362.99 | L83: =W68 -> 762657.91 | M83: =Y68 -> 782478.27 | N83: =AA68 -> 802839.07
F84: =F82 -> %YoY Growth | I84: =U17/O17-1 -> -0.087591691 | J84: =J83/I83-1 -> -0.00047457435 | K84: =K83/J83-1 -> 0.025924054 | L84: =L83/K83-1 -> 0.025956246 | M84: =M83/L83-1 -> 0.025988534 | N84: =N83/M83-1 -> 0.026020918
F85: Revenue by region:
F86: US & Canada | I86: =Segments!AF21 -> 2614872 | J86: =Segments!AL21 -> 2560457.1 | K86: =Segments!AR21 -> 2621789.5 | L86: =Segments!AT21 -> 2716262.5 | M86: =Segments!AV21 -> 2810723.6 | N86: =Segments!AX21 -> 2908939.5
F87: %YoY Growth | I87: =I86/Segments!Z21-1 -> -0.073089168 | J87: =J86/I86-1 -> -0.020809761 | K87: =K86/J86-1 -> 0.023953665 | L87: =L86/K86-1 -> 0.036033816 | M87: =M86/L86-1 -> 0.034776124 | N87: =N86/M86-1 -> 0.034943258
F88: Asia | I88: =I58+I64+I70 -> 262705 | J88: =O58+O64+O70 -> 260185.72 | K88: =U58+U64+U70 -> 273599.66 | L88: =W58+W64+W70 -> 287725.32 | M88: =Y58+Y64+Y70 -> 302601.16 | N88: =AA58+AA64+AA70 -> 318267.77
F89: %YoY Growth | I89: =I88/Segments!Z22-1 -> -0.08099476 | J89: =J88/I88-1 -> -0.0095897756 | K89: =K88/J88-1 -> 0.051555252 | L89: =L88/K88-1 -> 0.051628934 | M89: =M88/L88-1 -> 0.051701551 | N89: =N88/M88-1 -> 0.05177311
F90: EME | I90: =Segments!AF23 -> 826913 | J90: =Segments!AL23 -> 876487.64 | K90: =Segments!AR23 -> 934158.97 | L90: =Segments!AT23 -> 989078.49 | M90: =Segments!AV23 -> 1041087.5 | N90: =Segments!AX23 -> 1092720.5
F91: %YoY Growth | I91: =I90/Segments!Z23-1 -> 0.069306636 | J91: =J90/I90-1 -> 0.059951463 | K91: =K90/J90-1 -> 0.065798214 | L91: =L90/K90-1 -> 0.058790339 | M91: =M90/L90-1 -> 0.052583338 | N91: =N90/M90-1 -> 0.049595182
F92: LATAM | I92: =Segments!AF24 -> 170672 | J92: =Segments!AL24 -> 184027.54 | K92: =Segments!AR24 -> 202805.39 | L92: =Segments!AT24 -> 217350.24 | M92: =Segments!AV24 -> 230514.49 | N92: =Segments!AX24 -> 242108.19
F93: %YoY Growth | I93: =I92/Segments!Z24-1 -> 0.091469537 | J93: =J92/I92-1 -> 0.078252691 | K93: =K92/J92-1 -> 0.10203823 | L93: =L92/K92-1 -> 0.07171828 | M93: =M92/L92-1 -> 0.060566991 | N93: =N92/M92-1 -> 0.050294866
F94: Total Revenue | I94: =U23 -> 3875162 | J94: =O74 -> 3903483.5 | K94: =U74 -> 4027071.6 | L94: =W74 -> 4155102.1 | M94: =Y74 -> 4287757.9 | N94: =AA74 -> 4425230.4
F95: %YoY Growth | I95: =U23/O23-1 -> -0.039994748 | J95: =J94/I94-1 -> 0.007308469 | K95: =K94/J94-1 -> 0.031660978 | L95: =L94/K94-1 -> 0.031792451 | M95: =M94/L94-1 -> 0.031925999 | N95: =N94/M94-1 -> 0.032061627
C148: Company Projections
C149: Commercial Foodservice
C150: US & Canada
C151: Asia
C152: EME
C153: LATAM
C155: Food Processing
C156: US & Canada
C157: Asia
C158: EME
C159: LATAM
C161: Residential Kitchen
... C185: LATAM

Sheet FCFF
A7: x | B7: Market Assumptions
D8: 2022 | J8: =D8+1 -> 2023 | P8: =J8+1 -> 2024 | V8: =P8+1 -> 2025 | AB8: =V8+1 -> 2026 | AH8: =AB8+1 -> 2027 | AJ8: =+AH8+1 -> 2028 | AL8: =+AJ8+1 -> 2029
D9: Q1 | E9: Q2 | F9: Q3 | G9: Q4 | H9: FY | J9: Q1 | K9: Q2 | L9: Q3 | M9: Q4 | N9: FY | P9: Q1 | Q9: Q2 | R9: Q3 | S9: Q4 | T9: FY | V9: Q1 | W9: Q2 | X9: Q3 | Y9: Q4 | Z9: FY | AB9: Q1 | AC9: Q2 | AD9: Q3 | AE9: Q4 | AF9: FY | AH9: FY | AJ9: FY | AL9: FY
B11: Commercial Foodservice | D11: =Revenue!E5 -> 543653 | E11: =Revenue!F5 -> 609679 | F11: =Revenue!G5 -> 623662 | G11: =Revenue!H5 -> 633272 | H11: =Revenue!I5 -> 2410266 | I11: =Revenue!J5 -> 0 | J11: =Revenue!K5 -> 613935 | K11: =Revenue!L5 -> 645663 | ... W11: =Revenue!X5 -> 580605 | X11: =AVERAGE(Revenue!Y5,Revenue!M56) -> 607065.93 | Y11: =AVERAGE(Revenue!Z5,Revenue!N56) -> 618043.24 | Z11: =SUM(V11:Y11) -> 2368431.2 | AB11: =AVERAGE(Revenue!AC5,Revenue!Q56) -> 577918.34 | AC11: =AVERAGE(Revenue!AD5,Revenue!R56) -> 596566.32 | AD11: =AVERAGE(Revenue!AE5,Revenue!S56) -> 624534.28 | AE11: =AVERAGE(Revenue!AF5,Revenue!T56) -> 635926.42 | AF11: =SUM(AB11:AE11) -> 2434945.4 | AH11: =AVERAGE(Revenue!AI5,Revenue!W56) -> 2530368 | AJ11: =AVERAGE(Revenue!AK5,Revenue!Y56) -> 2622378.5 | AL11: =AVERAGE(Revenue!AM5,Revenue!AA56) -> 2720762.4
B12: US & Canada | D12: =Revenue!E6 -> 374909 | E12: =Revenue!F6 -> 454464 | F12: =Revenue!G6 -> 464053 | G12: =Revenue!H6 -> 472831 | H12: =Revenue!I6 -> 1766257 | I12: =Revenue!J6 -> 0 | J12: =Revenue!K6 -> 452655 | K12: =Revenue!L6 -> 474745 | ... W12: =Revenue!X6 -> 412575 | X12: =AVERAGE(Revenue!Y6,Revenue!M57) -> 414695.75 | Y12: =AVERAGE(Revenue!Z6,Revenue!N57) -> 415635.23 | Z12: =SUM(V12:Y12) -> 1656766 | AB12: =AVERAGE(Revenue!AC6,Revenue!Q57) -> 423279.27 | AC12: =AVERAGE(Revenue!AD6,Revenue!R57) -> 421965.02 | AD12: =AVERAGE(Revenue!AE6,Revenue!S57) -> 424176.88 | AE12: =AVERAGE(Revenue!AF6,Revenue!T57) -> 425141.96 | AF12: =SUM(AB12:AE12) -> 1694563.1 | AH12: =AVERAGE(Revenue!AI6,Revenue!W57) -> 1758085.3 | AJ12: =AVERAGE(Revenue!AK6,Revenue!Y57) -> 1815544.8 | AL12: =AVERAGE(Revenue!AM6,Revenue!AA57) -> 1874974.5
B13: Asia | D13: =Revenue!E7 -> 52016 | E13: =Revenue!F7 -> 45802 | F13: =Revenue!G7 -> 55243 | G13: =Revenue!H7 -> 59132 | H13: =Revenue!I7 -> 212193 | I13: =Revenue!J7 -> 0 | J13: =Revenue!K7 -> 56526 | K13: =Revenue!L7 -> 57453 | ... W13: =Revenue!X7 -> 51835 | X13: =AVERAGE(Revenue!Y7,Revenue!M58) -> 54967.631 | Y13: =AVERAGE(Revenue!Z7,Revenue!N58) -> 54520.367 | Z13: =SUM(V13:Y13) -> 210038 | AB13: =AVERAGE(Revenue!AC7,Revenue!Q58) -> 49885.352 | AC13: =AVERAGE(Revenue!AD7,Revenue!R58) -> 53080.308 | AD13: =AVERAGE(Revenue!AE7,Revenue!S58) -> 56444.064 | AE13: =AVERAGE(Revenue!AF7,Revenue!T58) -> 56061.028 | AF13: =SUM(AB13:AE13) -> 215470.75 | AH13: =AVERAGE(Revenue!AI7,Revenue!W58) -> 221765.53 | AJ13: =AVERAGE(Revenue!AK7,Revenue!Y58) -> 229433.35 | AL13: =AVERAGE(Revenue!AM7,Revenue!AA58) -> 238514.14
B14: EME | D14: =Revenue!E8 -> 100291 | E14: =Revenue!F8 -> 92328 | F14: =Revenue!G8 -> 86962 | G14: =Revenue!H8 -> 84562 | H14: =Revenue!I8 -> 364143 | I14: =Revenue!J8 -> 0 | J14: =Revenue!K8 -> 86965 | K14: =Revenue!L8 -> 94175 | ... W14: =Revenue!X8 -> 96244 | X14: =AVERAGE(Revenue!Y8,Revenue!M59) -> 105736.15 | Y14: =AVERAGE(Revenue!Z8,Revenue!N59) -> 118882.23 | Z14: =SUM(V14:Y14) -> 402913.38 | AB14: =AVERAGE(Revenue!AC8,Revenue!Q59) -> 85473.289 | AC14: =AVERAGE(Revenue!AD8,Revenue!R59) -> 100258.27 | AD14: =AVERAGE(Revenue!AE8,Revenue!S59) -> 110136.47 | AE14: =AVERAGE(Revenue!AF8,Revenue!T59) -> 123781.9 | AF14: =SUM(AB14:AE14) -> 419649.93 | AH14: =AVERAGE(Revenue!AI8,Revenue!W59) -> 439716.69 | AJ14: =AVERAGE(Revenue!AK8,Revenue!Y59) -> 460768.59 | AL14: =AVERAGE(Revenue!AM8,Revenue!AA59) -> 485122.16
B15: LATAM | D15: =Revenue!E9 -> 16437 | E15: =Revenue!F9 -> 17085 | F15: =Revenue!G9 -> 17404 | G15: =Revenue!H9 -> 16747 | H15: =Revenue!I9 -> 67673 | I15: =Revenue!J9 -> 0 | J15: =Revenue!K9 -> 17789 | K15: =Revenue!L9 -> 19290 | ... W15: =Revenue!X9 -> 19951 | X15: =AVERAGE(Revenue!Y9,Revenue!M60) -> 31666.403 | Y15: =AVERAGE(Revenue!Z9,Revenue!N60) -> 29005.413 | Z15: =SUM(V15:Y15) -> 98713.816 | AB15: =AVERAGE(Revenue!AC9,Revenue!Q60) -> 19280.433 | AC15: =AVERAGE(Revenue!AD9,Revenue!R60) -> 21262.722 | AD15: =AVERAGE(Revenue!AE9,Revenue!S60) -> 33776.863 | AE15: =AVERAGE(Revenue!AF9,Revenue!T60) -> 30941.532 | AF15: =SUM(AB15:AE15) -> 105261.55 | AH15: =AVERAGE(Revenue!AI9,Revenue!W60) -> 110800.51 | AJ15: =AVERAGE(Revenue!AK9,Revenue!Y60) -> 116631.76 | AL15: =AVERAGE(Revenue!AM9,Revenue!AA60) -> 122151.61 | AS15: 2022 | AT15: =+AS15+1 -> 2023 | AU15: =+AT15+1 -> 2024 | AV15: =+AU15+1 -> 2025 | AW15: =+AV15+1 -> 2026 | AX15: =+AW15+1 -> 2027 | AY15: =+AX15+1 -> 2028 | AZ15: =+AY15+1 -> 2029
AR16: EBITDA | AS16: =H69+H136 -> 801402 | AT16: =N69+N136 -> 856484 | AU16: =T69+T136 -> 837271 | AV16: =Z69+Z136 -> 752861.07 | AW16: =AF69+AF136 -> 837794.44 | AX16: =AH69+AH136 -> 956610.38 | AY16: =AJ69+AJ136 -> 1081244.6 | AZ16: =AL69+AL136 -> 1155438.9
B17: Food Processing | D17: =Revenue!E11 -> 119943 | E17: =Revenue!F11 -> 123913 | F17: =Revenue!G11 -> 148244 | G17: =Revenue!H11 -> 182365 | H17: =Revenue!I11 -> 574465 | I17: =Revenue!J11 -> 0 | J17: =Revenue!K11 -> 173503 | K17: =Revenue!L11 -> 188748 | ... W17: =Revenue!X11 -> 216195 | X17: =AVERAGE(Revenue!Y11,Revenue!M62) -> 180629.92 | Y17: =AVERAGE(Revenue!Z11,Revenue!N62) -> 232251.64 | Z17: =SUM(V17:Y17) -> 796982.56 | AB17: =AVERAGE(Revenue!AC11,Revenue!Q62) -> 182654.49 | AC17: =AVERAGE(Revenue!AD11,Revenue!R62) -> 233387.17 | AD17: =AVERAGE(Revenue!AE11,Revenue!S62) -> 195751.13 | AE17: =AVERAGE(Revenue!AF11,Revenue!T62) -> 253533.87 | AF17: =SUM(AB17:AE17) -> 865326.67 | AH17: =AVERAGE(Revenue!AI11,Revenue!W62) -> 924724.45 | AJ17: =AVERAGE(Revenue!AK11,Revenue!Y62) -> 980517.65 | AL17: =AVERAGE(Revenue!AM11,Revenue!AA62) -> 1032242.1
B18: US & Canada | D18: =Revenue!E12 -> 94797 | E18: =Revenue!F12 -> 87873 | F18: =Revenue!G12 -> 104367 | G18: =Revenue!H12 -> 123816 | H18: =Revenue!I12 -> 410853 | I18: =Revenue!J12 -> 0 | J18: =Revenue!K12 -> 116900 | K18: =Revenue!L12 -> 126953 | ... W18: =Revenue!X12 -> 124950 | X18: =AVERAGE(Revenue!Y12,Revenue!M63) -> 104625.05 | Y18: =AVERAGE(Revenue!Z12,Revenue!N63) -> 131175.85 | Z18: =SUM(V18:Y18) -> 453913.9 | AB18: =AVERAGE(Revenue!AC12,Revenue!Q63) -> 95786.191 | AC18: =AVERAGE(Revenue!AD12,Revenue!R63) -> 129092.97 | AD18: =AVERAGE(Revenue!AE12,Revenue!S63) -> 108599.63 | AE18: =AVERAGE(Revenue!AF12,Revenue!T63) -> 136828.17 | AF18: =SUM(AB18:AE18) -> 470306.95 | AH18: =AVERAGE(Revenue!AI12,Revenue!W63) -> 490644.15 | AJ18: =AVERAGE(Revenue!AK12,Revenue!Y63) -> 514499.46 | AL18: =AVERAGE(Revenue!AM12,Revenue!AA63) -> 539748.61
B19: Asia | D19: =Revenue!E13 -> 3743 | E19: =Revenue!F13 -> 4114 | F19: =Revenue!G13 -> 7805 | G19: =Revenue!H13 -> 4633 | H19: =Revenue!I13 -> 20295 | I19: =Revenue!J13 -> 0 | J19: =Revenue!K13 -> 8587 | K19: =Revenue!L13 -> 15531 | ... W19: =Revenue!X13 -> 7456 | X19: =AVERAGE(Revenue!Y13,Revenue!M64) -> 7523.1907 | Y19: =AVERAGE(Revenue!Z13,Revenue!N64) -> 10298.393 | Z19: =SUM(V19:Y19) -> 28981.584 | AB19: =AVERAGE(Revenue!AC13,Revenue!Q64) -> 4144.1682 | AC19: =AVERAGE(Revenue!AD13,Revenue!R64) -> 7845.6708 | AD19: =AVERAGE(Revenue!AE13,Revenue!S64) -> 7829.8004 | AE19: =AVERAGE(Revenue!AF13,Revenue!T64) -> 13285.032 | AF19: =SUM(AB19:AE19) -> 33104.671 | AH19: =AVERAGE(Revenue!AI13,Revenue!W64) -> 36214.948 | AJ19: =AVERAGE(Revenue!AK13,Revenue!Y64) -> 39278.727 | AL19: =AVERAGE(Revenue!AM13,Revenue!AA64) -> 42183.947
B20: EME | D20: =Revenue!E14 -> 14200 | E20: =Revenue!F14 -> 20460 | F20: =Revenue!G14 -> 24264 | G20: =Revenue!H14 -> 41292 | H20: =Revenue!I14 -> 100216 | I20: =Revenue!J14 -> 0 | J20: =Revenue!K14 -> 34059 | K20: =Revenue!L14 -> 33499 | ... W20: =Revenue!X14 -> 65223 | X20: =AVERAGE(Revenue!Y14,Revenue!M65) -> 54305.98 | Y20: =AVERAGE(Revenue!Z14,Revenue!N65) -> 62582.651 | Z20: =SUM(V20:Y20) -> 236799.63 | AB20: =AVERAGE(Revenue!AC14,Revenue!Q65) -> 62881.731 | AC20: =AVERAGE(Revenue!AD14,Revenue!R65) -> 75892.288 | AD20: =AVERAGE(Revenue!AE14,Revenue!S65) -> 64333.914 | AE20: =AVERAGE(Revenue!AF14,Revenue!T65) -> 69446.885 | AF20: =SUM(AB20:AE20) -> 272554.82 | AH20: =AVERAGE(Revenue!AI14,Revenue!W65) -> 299720.25 | AJ20: =AVERAGE(Revenue!AK14,Revenue!Y65) -> 321528.74 | AL20: =AVERAGE(Revenue!AM14,Revenue!AA65) -> 339321.49 | AR20: FCFF | AS20: =H144 -> 400810.94 | AT20: =N144 -> 628304.98 | AU20: =T144 -> 679159.64 | AV20: =Z144 -> 634502.52 | AW20: =AF144 -> 668909.18 | AX20: =AH144 -> 663689.03 | AY20: =AJ144 -> 750720.23 | AZ20: =AL144 -> 795208.35
B21: LATAM | D21: =Revenue!E15 -> 7203 | E21: =Revenue!F15 -> 11466 | F21: =Revenue!G15 -> 11808 | G21: =Revenue!H15 -> 12624 | H21: =Revenue!I15 -> 43101 | I21: =Revenue!J15 -> 0 | J21: =Revenue!K15 -> 13957 | K21: =Revenue!L15 -> 12765 | ... W21: =Revenue!X15 -> 18566 | X21: =AVERAGE(Revenue!Y15,Revenue!M66) -> 14175.693 | Y21: =AVERAGE(Revenue!Z15,Revenue!N66) -> 28194.747 | Z21: =SUM(V21:Y21) -> 77287.44 | AB21: =AVERAGE(Revenue!AC15,Revenue!Q66) -> 19842.399 | AC21: =AVERAGE(Revenue!AD15,Revenue!R66) -> 20556.248 | AD21: =AVERAGE(Revenue!AE15,Revenue!S66) -> 14987.792 | AE21: =AVERAGE(Revenue!AF15,Revenue!T66) -> 33973.792 | AF21: =SUM(AB21:AE21) -> 89360.231 | AH21: =AVERAGE(Revenue!AI15,Revenue!W66) -> 98145.104 | AJ21: =AVERAGE(Revenue!AK15,Revenue!Y66) -> 105210.73 | AL21: =AVERAGE(Revenue!AM15,Revenue!AA66) -> 110988.05
B23: Residential Kitchen | D23: =Revenue!E17 -> 331080 | E23: =Revenue!F17 -> 280009 | F23: =Revenue!G17 -> 220965 | G23: =Revenue!H17 -> 216068 | H23: =Revenue!I17 -> 1048122 | I23: =Revenue!J17 -> 0 | J23: =Revenue!K17 -> 219958 | K23: =Revenue!L17 -> 205571 | ... W23: =Revenue!X17 -> 181059 | X23: =AVERAGE(Revenue!Y17,Revenue!M68) -> 167128.15 | Y23: =AVERAGE(Revenue!Z17,Revenue!N68) -> 189356.33 | Z23: =SUM(V23:Y23) -> 713547.48 | AB23: =AVERAGE(Revenue!AC17,Revenue!Q68) -> 178866.71 | AC23: =AVERAGE(Revenue!AD17,Revenue!R68) -> 184239.34 | AD23: =AVERAGE(Revenue!AE17,Revenue!S68) -> 170267.63 | AE23: =AVERAGE(Revenue!AF17,Revenue!T68) -> 193504.85 | AF23: =SUM(AB23:AE23) -> 726878.53 | AH23: =AVERAGE(Revenue!AI17,Revenue!W68) -> 746028.25 | AJ23: =AVERAGE(Revenue!AK17,Revenue!Y68) -> 769238.05 | AL23: =AVERAGE(Revenue!AM17,Revenue!AA68) -> 793226.3
B24: US & Canada | D24: =Revenue!E18 -> 229599 | E24: =Revenue!F18 -> 189729 | F24: =Revenue!G18 -> 145757 | G24: =Revenue!H18 -> 136824 | H24: =Revenue!I18 -> 701909 | I24: =Revenue!J18 -> 0 | J24: =Revenue!K18 -> 143959 | K24: =Revenue!L18 -> 134755 | ... W24: =Revenue!X18 -> 111122 | X24: =AVERAGE(Revenue!Y18,Revenue!M69) -> 107591.86 | Y24: =AVERAGE(Revenue!Z18,Revenue!N69) -> 118212.4 | Z24: =SUM(V24:Y24) -> 449777.26 | AB24: =AVERAGE(Revenue!AC18,Revenue!Q69) -> 114630.79 | AC24: =AVERAGE(Revenue!AD18,Revenue!R69) -> 112874.52 | AD24: =AVERAGE(Revenue!AE18,Revenue!S69) -> 109333.45 | AE24: =AVERAGE(Revenue!AF18,Revenue!T69) -> 120080.62 | AF24: =SUM(AB24:AE24) -> 456919.38 | AH24: =AVERAGE(Revenue!AI18,Revenue!W69) -> 467533.14 | AJ24: =AVERAGE(Revenue!AK18,Revenue!Y69) -> 480679.37 | AL24: =AVERAGE(Revenue!AM18,Revenue!AA69) -> 494216.4
B25: Asia | D25: =Revenue!E19 -> 6005 | E25: =Revenue!F19 -> 10072 | F25: =Revenue!G19 -> 11647 | G25: =Revenue!H19 -> 4397 | H25: =Revenue!I19 -> 32121 | I25: =Revenue!J19 -> 0 | J25: =Revenue!K19 -> 3189 | K25: =Revenue!L19 -> 2092 | ... W25: =Revenue!X19 -> 3198 | X25: =AVERAGE(Revenue!Y19,Revenue!M70) -> 6195.4891 | Y25: =AVERAGE(Revenue!Z19,Revenue!N70) -> 6767.8062 | Z25: =SUM(V25:Y25) -> 18969.295 | AB25: =AVERAGE(Revenue!AC19,Revenue!Q70) -> 2586.7078 | AC25: =AVERAGE(Revenue!AD19,Revenue!R70) -> 3185.8735 | AD25: =AVERAGE(Revenue!AE19,Revenue!S70) -> 6403.7515 | AE25: =AVERAGE(Revenue!AF19,Revenue!T70) -> 7644.9898 | AF25: =SUM(AB25:AE25) -> 19821.323 | AH25: =AVERAGE(Revenue!AI19,Revenue!W70) -> 20448.927 | AJ25: =AVERAGE(Revenue!AK19,Revenue!Y70) -> 21096.462 | AL25: =AVERAGE(Revenue!AM19,Revenue!AA70) -> 21764.563
B26: EME | D26: =Revenue!E20 -> 93583 | E26: =Revenue!F20 -> 78382 | F26: =Revenue!G20 -> 60200 | G26: =Revenue!H20 -> 71675 | H26: =Revenue!I20 -> 303840 | I26: =Revenue!J20 -> 0 | J26: =Revenue!K20 -> 70386 | K26: =Revenue!L20 -> 66771 | ... W26: =Revenue!X20 -> 64673 | X26: =AVERAGE(Revenue!Y20,Revenue!M71) -> 52196.917 | Y26: =AVERAGE(Revenue!Z20,Revenue!N71) -> 60984.717 | Z26: =SUM(V26:Y26) -> 236774.63 | AB26: =AVERAGE(Revenue!AC20,Revenue!Q71) -> 60200.367 | AC26: =AVERAGE(Revenue!AD20,Revenue!R71) -> 66078.383 | AD26: =AVERAGE(Revenue!AE20,Revenue!S71) -> 53360.83 | AE26: =AVERAGE(Revenue!AF20,Revenue!T71) -> 62314.641 | AF26: =SUM(AB26:AE26) -> 241954.22 | AH26: =AVERAGE(Revenue!AI20,Revenue!W71) -> 249641.55 | AJ26: =AVERAGE(Revenue!AK20,Revenue!Y71) -> 258790.21 | AL26: =AVERAGE(Revenue!AM20,Revenue!AA71) -> 268276.81 | AR26: Revenue Growth | AS26: =H40 -> 0.24057553 | AT26: =N40 -> 0.00093035873 | AU26: =T40 -> -0.039994748 | AV26: =Z40 -> 0.00098039872 | AW26: =AF40 -> 0.038203364 | AX26: =AH40 -> 0.043199307 | AY26: =+AJ40 -> 0.040706642 | AZ26: =+AL40 -> 0.039819585
B27: LATAM | D27: =Revenue!E21 -> 1893 | E27: =Revenue!F21 -> 1826 | F27: =Revenue!G21 -> 3361 | G27: =Revenue!H21 -> 3172 | H27: =Revenue!I21 -> 10252 | I27: =Revenue!J21 -> 0 | J27: =Revenue!K21 -> 2424 | K27: =Revenue!L21 -> 1953 | ... W27: =Revenue!X21 -> 2066 | X27: =AVERAGE(Revenue!Y21,Revenue!M72) -> 1143.8805 | Y27: =AVERAGE(Revenue!Z21,Revenue!N72) -> 3391.4071 | Z27: =SUM(V27:Y27) -> 8026.2876 | AB27: =AVERAGE(Revenue!AC21,Revenue!Q72) -> 1448.8411 | AC27: =AVERAGE(Revenue!AD21,Revenue!R72) -> 2100.5654 | AD27: =AVERAGE(Revenue!AE21,Revenue!S72) -> 1169.6011 | AE27: =AVERAGE(Revenue!AF21,Revenue!T72) -> 3464.6001 | AF27: =SUM(AB27:AE27) -> 8183.6077 | AH27: =AVERAGE(Revenue!AI21,Revenue!W72) -> 8404.63 | AJ27: =AVERAGE(Revenue!AK21,Revenue!Y72) -> 8672.0084 | AL27: =AVERAGE(Revenue!AM21,Revenue!AA72) -> 8968.5267
B29: Revenue | X29: =SUM(X11+X17+X23) -> 954823.99 | Y29: =SUM(Y11+Y17+Y23) -> 1039651.2 | AB29: =SUM(AB11+AB17+AB23) -> 939439.54 | AC29: =SUM(AC11+AC17+AC23) -> 1014192.8 | AD29: =SUM(AD11+AD17+AD23) -> 990553.05 | AE29: =SUM(AE11+AE17+AE23) -> 1082965.1 | AH29: =SUM(AH11+AH17+AH23) -> 4201120.7 | AJ29: =SUM(AJ11+AJ17+AJ23) -> 4372134.2 | AL29: =SUM(AL11+AL17+AL23) -> 4546230.8
A31: x | B31: Operating Assumptions
D32: =D$8 -> 2022 | E32: =F32 -> 0 | F32: =F$8 -> 0 | G32: =F32 -> 0 | H32: =F32 -> 0 | J32: =J$8 -> 2023 | K32: =L32 -> 0 | L32: =L$8 -> 0 | M32: =L32 -> 0 | N32: =L32 -> 0 | P32: =P$8 -> 2024 | Q32: =R32 -> 0 | R32: =R$8 -> 0 | S32: =R32 -> 0 | T32: =R32 -> 0 | V32: =V$8 -> 2025 | W32: =X32 -> 0 | X32: =X$8 -> 0 | Y32: =X32 -> 0 | Z32: =X32 -> 0 | AB32: =AB$8 -> 2026 | AC32: =AD32 -> 0 | AD32: =AD$8 -> 0 | AE32: =AD32 -> 0 | AF32: =AD32 -> 0 | AH32: =AH$8 -> 2027 | AJ32: =AJ$8 -> 2028 | AL32: =AL$8 -> 2029 | AM32: =AN32 -> 0
D33: Q1 | E33: Q2 | F33: Q3 | G33: Q4 | H33: FY | J33: Q1 | K33: Q2 | L33: Q3 | M33: Q4 | N33: FY | P33: Q1 | Q33: Q2 | R33: Q3 | S33: Q4 | T33: FY | V33: Q1 | W33: Q2 | X33: Q3 | Y33: Q4 | Z33: FY | AB33: Q1 | AC33: Q2 | AD33: Q3 | AE33: Q4 | AF33: FY | AH33: FY | AJ33: FY | AL33: FY
B36: Income Statement
B39: Revenue | D39: =IS!P18 -> 994676 | E39: =IS!Q18 -> 1013601 | F39: =IS!R18 -> 992871 | G39: =IS!S18 -> 1031705 | H39: =IS!T18 -> 4032853 | J39: =IS!V18 -> 1007396 | K39: =IS!W18 -> 1039982 | L39: =IS!X18 -> 980651 | M39: =IS!Y18 -> 1008576 | N39: =IS!Z18 -> 4036605 | P39: =IS!AB18 -> 926926 | Q39: =IS!AC18 -> 991546 | R39: =IS!AD18 -> 942809 | S39: =IS!AE18 -> 1013881 | T39: =IS!AF18 -> 3875162 | V39: =IS!AH18 -> 906627 | W39: =IS!AI18 -> 977859 | X39: =X29 -> 954823.99 | Y39: =Y29 -> 1039651.2 | Z39: =SUM(V39:Y39) -> 3878961.2 | AB39: =AB29 -> 939439.54 | AC39: =AC29 -> 1014192.8 | AD39: =AD29 -> 990553.05 | AE39: =AE29 -> 1082965.1 | AF39: =SUM(AB39:AE39) -> 4027150.6 | AH39: =AH29 -> 4201120.7 | AJ39: =AJ29 -> 4372134.2 | AL39: =AL29 -> 4546230.8
B40: % of growth | D40: =D39/IS!J18-1 -> 0.31213707 | E40: =E39/IS!K18-1 -> 0.25325771 | F40: =F39/IS!L18-1 -> 0.21445425 | G40: =G39/IS!M18-1 -> 0.19077325 | H40: =H39/IS!N18-1 -> 0.24057553 | J40: =J39/IS!P18-1 -> 0.012788084 | K40: =K39/IS!Q18-1 -> 0.026027007 | L40: =L39/IS!R18-1 -> -0.012307742 | M40: =M39/IS!S18-1 -> -0.02241823 | N40: =N39/H39-1 -> 0.00093035873 | P40: =P39/IS!V18-1 -> -0.079879213 | Q40: =Q39/IS!W18-1 -> -0.046573883 | R40: =R39/IS!X18-1 -> -0.038588652 | S40: =S39/IS!Y18-1 -> 0.0052598912 | T40: =T39/N39-1 -> -0.039994748 | V40: =V39/IS!AB18-1 -> -0.021899267 | W40: =W39/IS!AC18-1 -> -0.013803696 | X40: =X39/IS!AD18-1 -> 0.012743826 | Y40: =Y39/IS!AE18-1 -> 0.025417391 | Z40: =Z39/T39-1 -> 0.00098039872 | AB40: =AB39/IS!AH18-1 -> 0.036191883 | AC40: =AC39/IS!AI18-1 -> 0.037156523 | AD40: =AD39/X39-1 -> 0.037419515 | AE40: =AE39/Y39-1 -> 0.041661989 | AF40: =AF39/Z39-1 -> 0.038203364 | AH40: =AH39/AF39-1 -> 0.043199307 | AJ40: =AJ39/AH39-1 -> 0.040706642 | AL40: =AL39/AJ39-1 -> 0.039819585
B42: Cost of Goods & Services | D42: =IS!P21 -> 664166 | E42: =IS!Q21 -> 652859 | F42: =IS!R21 -> 627639 | G42: =IS!S21 -> 641635 | H42: =IS!T21 -> 2537399 | J42: =IS!V21 -> 628661 | K42: =IS!W21 -> 646746 | L42: =IS!X21 -> 605329 | M42: =IS!Y21 -> 621807 | N42: =IS!Z21 -> 2449443 | P42: =IS!AB21 -> 580568 | Q42: =IS!AC21 -> 611904 | R42: =IS!AD21 -> 587375 | S42: =IS!AE21 -> 624946 | T42: =IS!AF21 -> 2347093 | V42: =IS!AH21 -> 560694 | W42: =IS!AI21 -> 606568 | X42: =(X43+Sensitivity!$U$39)*X$39 -> 595944.95 | Y42: =(Y43+Sensitivity!$U$39)*Y$39 -> 642790.95 | Z42: =SUM(V42:Y42) -> 2405997.9 | AB42: =(AB43+Sensitivity!$U$39)*AB$39 -> 573567.45 | AC42: =(AC43+Sensitivity!$U$39)*AC$39 -> 632332.07 | AD42: =(AD43+Sensitivity!$U$39)*AD$39 -> 609464.52 | AE42: =(AE43+Sensitivity!$U$39)*AE$39 -> 660783.39 | AF42: =SUM(AB42:AE42) -> 2476147.4 | AH42: =(AH43+Sensitivity!$U$39)*AH$39 -> 2541678 | AJ42: =(AJ43+Sensitivity!$U$39)*AJ$39 -> 2601419.8 | AL42: =(AL43+Sensitivity!$U$39)*AL$39 -> 2682276.2
B43: % of sales | D43: =D42/D39 -> 0.66772095 | E43: =E42/E39 -> 0.64409861 | F43: =F42/F39 -> 0.63214557 | G43: =G42/G39 -> 0.62191712 | H43: =H42/H39 -> 0.62918212 | J43: =J42/J39 -> 0.62404556 | K43: =K42/K39 -> 0.62188192 | L43: =L42/L39 -> 0.61727261 | M43: =M42/M39 -> 0.61651973 | N43: =N42/N39 -> 0.6068077 | P43: =P42/P39 -> 0.62633695 | Q43: =Q42/Q39 -> 0.61712114 | R43: =R42/R39 -> 0.6230053 | S43: =S42/S39 -> 0.61638989 | T43: =T42/T39 -> 0.6056761 | V43: =V42/V39 -> 0.61843956 | W43: =W42/W39 -> 0.62030211 | X43: =AVERAGE(R43,L43,F43) -> 0.62414116 | Y43: =AVERAGE(S43,M43,G43) -> 0.61827558 | Z43: =Z42/Z39 -> 0.62026862 | AB43: =V43-(P43-V43) -> 0.61054217 | AC43: =W43-(Q43-W43) -> 0.62348308 | AD43: =(X43-(R43-X43))-1% -> 0.61527702 | AE43: =(Y43-(S43-Y43))-1% -> 0.61016127 | AF43: =AF42/AF39 -> 0.61486338 | AH43: 0.605 | AJ43: =AH43-1% -> 0.595 | AL43: =AJ43-0.5% -> 0.59
B45: COGS Depreciation & Amortization | D45: =IS!P22 -> 0 | E45: =IS!Q22 -> 0 | F45: =IS!R22 -> 0 | G45: =IS!S22 -> 0 | H45: =IS!T22 -> 0 | J45: =IS!V22 -> 0 | K45: =IS!W22 -> 0 | L45: =IS!X22 -> 0 | M45: =IS!Y22 -> 0 | N45: =IS!Z22 -> 0 | P45: =IS!AB22 -> 0 | Q45: =IS!AC22 -> 0 | R45: =IS!AD22 -> 0 | S45: =IS!AE22 -> 0 | T45: =IS!AF22 -> 0 | V45: =IS!AH22 -> 0 | W45: =IS!AI22 -> 0 | X45: =X46*X42 -> 0 | Y45: =Y46*Y42 -> 0 | Z45: =SUM(V45:Y45) -> 0 | AB45: =AB46*AB42 -> 0 | AC45: =AC46*AC42 -> 0 | AD45: =AD46*AD42 -> 0 | AE45: =AE46*AE42 -> 0 | AF45: =SUM(AB45:AE45) -> 0 | AH45: =AH46*AH42 -> 0 | AJ45: =AJ46*AJ42 -> 0 | AL45: =AL46*AL42 -> 0
B46: % of cost of goods & services | D46: =D45/D42 -> 0 | E46: =E45/E42 -> 0 | F46: =F45/F42 -> 0 | G46: =G45/G42 -> 0 | H46: =H45/H42 -> 0 | J46: =J45/J42 -> 0 | K46: =K45/K42 -> 0 | L46: =L45/L42 -> 0 | M46: =M45/M42 -> 0 | N46: =N45/N42 -> 0 | P46: =P45/P42 -> 0 | Q46: =Q45/Q42 -> 0 | R46: =R45/R42 -> 0 | S46: =S45/S42 -> 0 | T46: =T45/T42 -> 0 | V46: =V45/V42 -> 0 | W46: =W45/W42 -> 0 | X46: 0 | Y46: 0 | AB46: 0 | AC46: 0 | AD46: 0 | AE46: 0 | AH46: 0 | AJ46: 0 | AL46: 0
B48: Gross Profit | D48: =IS!P24 -> 330510 | E48: =IS!Q24 -> 360742 | F48: =IS!R24 -> 365232 | G48: =IS!S24 -> 390070 | H48: =IS!T24 -> 1495454 | J48: =IS!V24 -> 378735 | K48: =IS!W24 -> 393236 | L48: =IS!X24 -> 375322 | M48: =IS!Y24 -> 386769 | N48: =IS!Z24 -> 1587162 | P48: =IS!AB24 -> 346358 | Q48: =IS!AC24 -> 379642 | R48: =IS!AD24 -> 355434 | S48: =IS!AE24 -> 388935 | T48: =IS!AF24 -> 1528069 | V48: =IS!AH24 -> 345933 | W48: =IS!AI24 -> 371291 | X48: =X39-X42-X45 -> 358879.04 | Y48: =Y39-Y42-Y45 -> 396860.26 | Z48: =SUM(V48:Y48) -> 1472963.3 | AB48: =AB39-AB42-AB45 -> 365872.09 | AC48: =AC39-AC42-AC45 -> 381860.77 | AD48: =AD39-AD42-AD45 -> 381088.52 | AE48: =AE39-AE42-AE45 -> 422181.76 | AF48: =SUM(AB48:AE48) -> 1551003.1 | AH48: =AH39-AH42-AH45 -> 1659442.7 | AJ48: =AJ39-AJ42-AJ45 -> 1770714.4 | AL48: =AL39-AL42-AL45 -> 1863954.6
B49: % of sales | D49: =D48/D39 -> 0.33227905 | E49: =E48/E39 -> 0.35590139 | F49: =F48/F39 -> 0.36785443 | G49: =G48/G39 -> 0.37808288 | H49: =H48/H39 -> 0.37081788 | J49: =J48/J39 -> 0.37595444 | K49: =K48/K39 -> 0.37811808 | L49: =L48/L39 -> 0.38272739 | M49: =M48/M39 -> 0.38348027 | N49: =N48/N39 -> 0.3931923 | P49: =P48/P39 -> 0.37366305 | Q49: =Q48/Q39 -> 0.38287886 | R49: =R48/R39 -> 0.3769947 | S49: =S48/S39 -> 0.38361011 | T49: =T48/T39 -> 0.3943239 | V49: =V48/V39 -> 0.38156044 | W49: =W48/W39 -> 0.37969789 | X49: =X48/X39 -> 0.37585884 | Y49: =Y48/Y39 -> 0.38172442 | Z49: =Z48/Z$39 -> 0.37973138 | AB49: =AB48/AB39 -> 0.38945783 | AC49: =AC48/AC39 -> 0.37651692 | AD49: =AD48/AD39 -> 0.38472298 | AE49: =AE48/AE39 -> 0.38983873 | AF49: =AF48/AF$39 -> 0.38513662 | AH49: =AH48/AH39 -> 0.395 | AJ49: =AJ48/AJ39 -> 0.405 | AL49: =AL48/AL39 -> 0.41
B51: SG&A (Selling, General & Administrative) | D51: =IS!P27 -> 159329 | E51: =IS!Q27 -> 160451 | F51: =IS!R27 -> 170060 | G51: =IS!S27 -> 169333 | H51: =IS!T27 -> 659173 | J51: =IS!V27 -> 180460 | K51: =IS!W27 -> 172691 | L51: =IS!X27 -> 163152 | M51: =IS!Y27 -> 158039 | N51: =IS!Z27 -> 674342 | P51: =IS!AB27 -> 173638 | Q51: =IS!AC27 -> 166938 | R51: =IS!AD27 -> 148696 | S51: =IS!AE27 -> 146056 | T51: =IS!AF27 -> 635328 | V51: =IS!AH27 -> 170461 | W51: =IS!AI27 -> 181421 | X51: =(X52+Sensitivity!$U$40)*X$39 -> 157663.12 | Y51: =(Y52+Sensitivity!$U$40)*Y$39 -> 161104.63 | Z51: =SUM(V51:Y51) -> 670649.75 | AB51: =(AB52+Sensitivity!$U$40)*AB$39 -> 167235.91 | AC51: =(AC52+Sensitivity!$U$40)*AC$39 -> 178020.05 | AD51: =(AD52+Sensitivity!$U$40)*AD$39 -> 153657.27 | AE51: =(AE52+Sensitivity!$U$40)*AE$39 -> 156986.92 | AF51: =SUM(AB51:AE51) -> 655900.14 | AH51: =(AH52+Sensitivity!$U$40)*AH$39 -> 642223.37 | AJ51: =(AJ52+Sensitivity!$U$40)*AJ$39 -> 624644.78 | AL51: =(AL52+Sensitivity!$U$40)*AL$39 -> 636472.31
B52: % of sales | D52: =D51/D39 -> 0.16018181 | E52: =E51/E39 -> 0.15829799 | F52: =F51/F39 -> 0.17128106 | G52: =G51/G39 -> 0.16412928 | H52: =H51/H39 -> 0.16345079 | J52: =J51/J39 -> 0.17913512 | K52: =K51/K39 -> 0.16605191 | L52: =L51/L39 -> 0.16637111 | M52: =M51/M39 -> 0.15669518 | N52: =N51/N39 -> 0.16705672 | P52: =P51/P39 -> 0.18732671 | Q52: =Q51/Q39 -> 0.16836133 | R52: =R51/R39 -> 0.15771593 | S52: =S51/S39 -> 0.14405635 | T52: =T51/T39 -> 0.16394876 | V52: =V51/V39 -> 0.18801668 | W52: =W51/W39 -> 0.18552879 | X52: =AVERAGE(R52,L52,F52) -> 0.1651227 | Y52: =AVERAGE(S52,M52,G52) -> 0.15496027 | Z52: =Z51/Z39 -> 0.17289416 | AB52: =V52-1% -> 0.17801668 | AC52: =W52-1% -> 0.17552879 | AD52: =X52-1% -> 0.1551227 | AE52: =Y52-1% -> 0.14496027 | AF52: =AF51/AF39 -> 0.16286954 | AH52: =AF52-1% -> 0.15286954 | AJ52: =AH52-1% -> 0.14286954 | AL52: 0.14
B54: R&D (Research & Development) | D54: =IS!P29 -> 0 | E54: =IS!Q29 -> 0 | F54: =IS!R29 -> 0 | G54: =IS!S29 -> 0 | H54: =IS!T29 -> 48900 | J54: =IS!V29 -> 0 | K54: =IS!W29 -> 0 | L54: =IS!X29 -> 0 | M54: =IS!Y29 -> 0 | N54: =IS!Z29 -> 53100 | P54: =IS!AB29 -> 0 | Q54: =IS!AC29 -> 0 | R54: =IS!AD29 -> 0 | S54: =IS!AE29 -> 0 | T54: =IS!AF29 -> 57700 | V54: =IS!AH29 -> 0 | W54: =IS!AI29 -> 0 | X54: =Z54/2 -> 29459.266 | Y54: =Z54/2 -> 29459.266 | Z54: =Z55*Z48 -> 58918.532 | AB54: =AB55*AB48 -> 14634.883 | AC54: =AC55*AC48 -> 15274.431 | AD54: =AD55*AD48 -> 15243.541 | AE54: =AE55*AE48 -> 16887.27 | AF54: =SUM(AB54:AE54) -> 62040.126 | AH54: =AH55*AH48 -> 66377.707 | AJ54: =AJ55*AJ48 -> 70828.574 | AL54: =AL55*AL48 -> 78286.094
B55: % of gross profit | D55: =D54/D48 -> 0 | E55: =E54/E48 -> 0 | F55: =F54/F48 -> 0 | G55: =G54/G48 -> 0 | H55: =H54/H48 -> 0.0326991 | J55: =J54/J48 -> 0 | K55: =K54/K48 -> 0 | L55: =L54/L48 -> 0 | M55: =M54/M48 -> 0 | N55: =N54/N48 -> 0.033455942 | P55: =P54/P48 -> 0 | Q55: =Q54/Q48 -> 0 | R55: =R54/R48 -> 0 | S55: =S54/S48 -> 0 | T55: =T54/T48 -> 0.037760075 | V55: =V54/V48 -> 0 | W55: =W54/W48 -> 0 | X55: =X54/X48 -> 0.082086894 | Y55: =Y54/Y48 -> 0.074230829 | Z55: =4% -> 0.04 | AB55: 0.04 | AC55: 0.04 | AD55: 0.04 | AE55: 0.04 | AF55: =AF54/AF48 -> 0.04 | AH55: =AF55 -> 0.04 | AJ55: =AF55 -> 0.04 | AL55: 0.042
B57: D&A (Depreciation & Amortization) | D57: =IS!P28 -> 46742 | E57: =IS!Q28 -> 29035 | F57: =IS!R28 -> 31140 | G57: =IS!S28 -> 31144 | H57: =IS!T28 -> 138061 | J57: =IS!V28 -> 34947 | K57: =IS!W28 -> 30830 | L57: =IS!X28 -> 33281 | M57: =IS!Y28 -> 33546 | N57: =IS!Z28 -> 132604 | P57: =IS!AB28 -> 32410 | Q57: =IS!AC28 -> 31646 | R57: =IS!AD28 -> 30780 | S57: =IS!AE28 -> 32338 | T57: =IS!AF28 -> 127174 | V57: =IS!AH28 -> 32145 | W57: =IS!AI28 -> 32190 | X57: =X60+X63 -> 33797.553 | Y57: =Y60+Y63 -> 32460.217 | Z57: =SUM(V57:Y57) -> 130592.77 | AB57: =AB60+AB63 -> 32539.462 | AC57: =AC60+AC63 -> 29957.436 | AD57: =AD60+AD63 -> 32912.663 | AE57: =AE60+AE63 -> 31679.008 | AF57: =SUM(AB57:AE57) -> 127088.57 | AH57: =AH60+AH63 -> 128747.26 | AJ57: =AJ60+AJ63 -> 126491.34 | AL57: =AL60+AL63 -> 125143.03
B58: % of net pp&e and intangibles excl. Goodwill | D58: =D57/(D87+D90) -> 0.010493982 | E58: =E57/(E87+E90) -> 0.0065337577 | F58: =F57/(F87+F90) -> 0.0069305221 | G58: =G57/(G87+G90) -> 0.0066982192 | H58: =H57/(H87+H90) -> 0.02969313 | J58: =J57/(J87+J90) -> 0.0074641865 | K58: =K57/(K87+K90) -> 0.0065238998 | L58: =L57/(L87+L90) -> 0.007040862 | M58: =M57/(M87+M90) -> 0.0071522321 | N58: =N57/(N87+N90) -> 0.028272062 | P58: =P57/(P87+P90) -> 0.0069684913 | Q58: =Q57/(Q87+Q90) -> 0.0068389079 | R58: =R57/(R87+R90) -> 0.0065933685 | S58: =S57/(S87+S90) -> 0.0069466045 | T58: =T57/(T87+T90) -> 0.027318557 | V58: =V57/(V87+V90) -> 0.0068388233 | W58: =W57/(W87+W90) -> 0.0067388971 | X58: =X57/( X87+X90) -> 0.0070972772 | Y58: =Y57/( Y87+Y90) -> 0.0068331865 | Z58: =Z57/( Z87+Z90) -> 0.027491029 | AB58: =AB57/( AB87+AB90) -> 0.00686703 | AC58: =AC57/( AC87+AC90) -> 0.0063323437 | AD58: =AD57/( AD87+AD90) -> 0.0069734057 | AE58: =AE57/( AE87+AE90) -> 0.0067232113 | AF58: =AF57/( AF87+AF90) -> 0.026971908 | AH58: =AH57/( AH87+AH90) -> 0.027486805 | AJ58: =AJ57/( AJ87+AJ90) -> 0.027079271 | AL58: =AL57/( AL87+AL90) -> 0.026830493
B60: Depreciation | D60: =IS!P64 -> 11372 | E60: =IS!Q64 -> 10574 | F60: =IS!R64 -> 9479 | G60: =IS!S64 -> 13011 | H60: =IS!T64 -> 44436 | J60: =IS!V64 -> 11977 | K60: =IS!W64 -> 12219 | L60: =IS!X64 -> 12588 | M60: =IS!Y64 -> 13328 | N60: =IS!Z64 -> 50112 | P60: =IS!AB64 -> 13273 | Q60: =IS!AC64 -> 13151 | R60: =IS!AD64 -> 13975 | S60: =IS!AE64 -> 14781 | T60: =IS!AF64 -> 55180 | V60: =IS!AH64 -> 14356 | W60: =IS!AI64 -> 14300 | X60: =X61*W87 -> 15003.357 | Y60: =Y61*X87 -> 15169.736 | Z60: =SUM(V60:Y60) -> 58829.093 | AB60: =AB61*Y87 -> 14237.809 | AC60: =AC61*AB87 -> 13866.346 | AD60: =AD61*AC87 -> 14184.361 | AE60: =AE61*AD87 -> 14453.888 | AF60: =SUM(AB60:AE60) -> 56742.405 | AH60: =AH61*AF87 -> 57537.325 | AJ60: =AJ61*AH87 -> 55430.441 | AL60: =AL61*AJ87 -> 54093.36
B61: % of net pp&e | D61: =D60/D87 -> 0.029724968 | E61: =E60/E87 -> 0.025315547 | F61: =F60/F87 -> 0.022358927 | G61: =G60/G87 -> 0.029335239 | H61: =H60/H87 -> 0.10018759 | J61: =J60/J87 -> 0.025939514 | K61: =K60/K87 -> 0.025294785 | L61: =L60/L87 -> 0.025232976 | M61: =M60/M87 -> 0.026087399 | N61: =N60/N87 -> 0.098086115 | P61: =P60/P87 -> 0.026120754 | Q61: =Q60/Q87 -> 0.026059077 | R61: =R60/R87 -> 0.027372173 | S61: =S60/S87 -> 0.02810263 | T61: =T60/T87 -> 0.10491192 | V61: =V60/V87 -> 0.026066936 | W61: =W60/W87 -> 0.025069511 | X61: =AVERAGE(R61,L61) -> 0.026302575 | Y61: =AVERAGE(S61,M61) -> 0.027095015 | Z61: =Z60/Z87 -> 0.1076044 | AB61: =AVERAGE(V61,P61,J61) -> 0.026042401 | AC61: =AVERAGE(W61,Q61,K61) -> 0.025474458 | AD61: =AVERAGE(X61,R61,L61) -> 0.026302575 | AE61: =AVERAGE(Y61,S61,M61) -> 0.027095015 | AF61: =AF60/AF87 -> 0.10848027 | AH61: 0.11 | AJ61: 0.11 | AL61: 0.11
B63: Amortization | D63: =IS!P65 -> 33565 | E63: =IS!Q65 -> 16488 | F63: =IS!R65 -> 21661 | G63: =IS!S65 -> 16346 | H63: =IS!T65 -> 88060 | J63: =IS!V65 -> 21183 | K63: =IS!W65 -> 16520 | L63: =IS!X65 -> 20693 | M63: =IS!Y65 -> 18432 | N63: =IS!Z65 -> 76828 | P63: =IS!AB65 -> 17350 | Q63: =IS!AC65 -> 16288 | R63: =IS!AD65 -> 16805 | S63: =IS!AE65 -> 15770 | T63: =IS!AF65 -> 66213 | V63: =IS!AH65 -> 15992 | W63: =IS!AI65 -> 15416 | X63: =X64*W90 -> 18794.196 | Y63: =Y64*X90 -> 17290.481 | Z63: =SUM(V63:Y63) -> 67492.677 | AB63: =AB64*Y90 -> 18301.653 | AC63: =AC64*AB90 -> 16091.09 | AD63: =AD64*AC90 -> 18728.302 | AE63: =AE64*AD90 -> 17225.12 | AF63: =SUM(AB63:AE63) -> 70346.165 | AH63: =AH64*AF90 -> 71209.938 | AJ63: =AJ64*AH90 -> 71060.901 | AL63: =AL64*AJ90 -> 71049.671
B64: % of intangibles excl. goodwill | D64: =D63/D90 -> 0.008243692 | E64: =E63/E90 -> 0.0040952213 | F64: =F63/F90 -> 0.0053231319 | G64: =G63/G90 -> 0.0038862918 | H64: =H63/H90 -> 0.020936428 | J64: =J63/J90 -> 0.0050193959 | K64: =K63/K90 -> 0.0038938047 | L64: =L63/L90 -> 0.0048943168 | M64: =M63/M90 -> 0.0044102172 | N64: =N63/N90 -> 0.018382605 | P64: =P63/P90 -> 0.0041879939 | Q64: =Q63/Q90 -> 0.0039508224 | R64: =R63/R90 -> 0.0040418282 | S64: =S63/S90 -> 0.0038190872 | T64: =T63/T90 -> 0.01603508 | V64: =V63/V90 -> 0.0038538339 | W64: =W63/W90 -> 0.0036649508 | X64: =AVERAGE(R64,L64) -> 0.0044680725 | Y64: =AVERAGE(S64,M64) -> 0.0041146522 | Z64: =Z63/Z90 -> 0.016055689 | AB64: =AVERAGE(V64,P64,J64) -> 0.0043537412 | AC64: =AVERAGE(W64,Q64,K64) -> 0.003836526 | AD64: =AVERAGE(X64,R64,L64) -> 0.0044680725 | AE64: =AVERAGE(Y64,S64,M64) -> 0.0041146522 | AF64: =AF63/AF90 -> 0.016793791 | AH64: 0.017 | AJ64: 0.017 | AL64: 0.017
B66: Other Operating (Income) Expenses | D66: =IS!P30+IS!P32 -> -14250 | E66: =IS!Q30+IS!Q32 -> 2280 | F66: =IS!R30+IS!R32 -> -3189 | G66: =IS!S30+IS!S32 -> 1138 | H66: =IS!T30+IS!T32 -> -14021 | J66: =IS!V30+IS!V32 -> -1304 | K66: =IS!W30+IS!W32 -> 276 | L66: =IS!X30+IS!X32 -> -111 | M66: =IS!Y30+IS!Y32 -> 7494 | N66: =IS!Z30+IS!Z32 -> 3236 | P66: =IS!AB30+IS!AB32 -> -1030 | Q66: =IS!AC30+IS!AC32 -> 1165 | R66: =IS!AD30+IS!AD32 -> 1169 | S66: =IS!AE30+IS!AE32 -> -4046 | T66: =IS!AF30+IS!AF32 -> -2230 | V66: =IS!AH30+IS!AH32 -> -5917 | W66: =IS!AI30+IS!AI32 -> -5875 | X66: =X67*X$39 -> 537.91045 | Y66: =Y67*Y$39 -> 1788.0293 | Z66: =SUM(V66:Y66) -> -9466.0602 | AB66: =AB67*AB$39 -> -5462.4388 | AC66: =AC67*AC$39 -> -587.79973 | AD66: =AD67*AD$39 -> -376.85965 | AE66: =AE67*AE$39 -> 1695.527 | AF66: =SUM(AB66:AE66) -> -4731.5712 | AH66: =AH67*AH$39 -> -5768.7844 | AJ66: =AJ67*AJ$39 -> -6003.6123 | AL66: =AL67*AL$39 -> -6242.6736
B67: % of sales | D67: =D66/D39 -> -0.014326273 | E67: =E66/E39 -> 0.0022494058 | F67: =F66/F39 -> -0.0032118976 | G67: =G66/G39 -> 0.0011030285 | H67: =H66/H39 -> -0.003476695 | J67: =J66/J39 -> -0.0012944264 | K67: =K66/K39 -> 0.00026538921 | L67: =L66/L39 -> -0.00011319012 | M67: =M66/M39 -> 0.0074302779 | N67: =N66/N39 -> 0.00080166377 | P67: =P66/P39 -> -0.0011111998 | Q67: =Q66/Q39 -> 0.0011749329 | R67: =R66/R39 -> 0.0012399118 | S67: =S66/S39 -> -0.0039906064 | T67: =T66/T39 -> -0.00057545981 | V67: =V66/V39 -> -0.0065263885 | W67: =W66/W39 -> -0.0060080237 | X67: =AVERAGE(R67,L67) -> 0.00056336084 | Y67: =AVERAGE(S67,M67) -> 0.0017198358 | Z67: =Z66/Z$39 -> -0.0024403596 | AB67: =AVERAGE(D67,J67,P67,V67) -> -0.0058145719 | AC67: =AVERAGE(E67,K67,Q67,W67) -> -0.00057957393 | AD67: =AVERAGE(F67,L67,R67,X67) -> -0.00038045377 | AE67: =AVERAGE(G67,M67,S67,Y67) -> 0.0015656339 | AF67: =AF66/AF$39 -> -0.0011749179 | AH67: =AVERAGE($AF$67,$Z$67,$T$67,$N$67,$H$67) -> -0.0013731537 | AJ67: =AVERAGE($AF$67,$Z$67,$T$67,$N$67,$H$67) -> -0.0013731537 | AL67: =AVERAGE($AF$67,$Z$67,$T$67,$N$67,$H$67) -> -0.0013731537
B69: EBIT (Operating Income) | D69: =IS!P33 -> 138689 | E69: =IS!Q33 -> 168976 | F69: =IS!R33 -> 167221 | G69: =IS!S33 -> 188455 | H69: =IS!T33 -> 663341 | J69: =IS!V33 -> 164632 | K69: =IS!W33 -> 189439 | L69: =IS!X33 -> 179000 | M69: =IS!Y33 -> 187690 | N69: =IS!Z33 -> 723880 | P69: =IS!AB33 -> 141340 | Q69: =IS!AC33 -> 179893 | R69: =IS!AD33 -> 174789 | S69: =IS!AE33 -> 214587 | T69: =IS!AF33 -> 710097 | V69: =IS!AH33 -> 149244 | W69: =IS!AI33 -> 163555 | X69: =X48-X51-X54-X57-X66 -> 137421.19 | Y69: =Y48-Y51-Y54-Y57-Y66 -> 172048.11 | Z69: =SUM(V69:Y69) -> 622268.3 | AB69: =AB48-AB51-AB54-AB57-AB66 -> 156924.27 | AC69: =AC48-AC51-AC54-AC57-AC66 -> 159196.66 | AD69: =AD48-AD51-AD54-AD57-AD66 -> 179651.91 | AE69: =AE48-AE51-AE54-AE57-AE66 -> 214933.03 | AF69: =SUM(AB69:AE69) -> 710705.87 | AH69: =AH48-AH51-AH54-AH57-AH66 -> 827863.12 | AJ69: =AJ48-AJ51-AJ54-AJ57-AJ66 -> 954753.27 | AL69: =AL48-AL51-AL54-AL57-AL66 -> 1030295.9
B70: % of sales | D70: =D69/D39 -> 0.13943133 | E70: =E69/E39 -> 0.1667086 | F70: =F69/F39 -> 0.16842168 | G70: =G69/G39 -> 0.18266365 | H70: =H69/H39 -> 0.1644843 | J70: =J69/J39 -> 0.16342332 | K70: =K69/K39 -> 0.18215604 | L70: =L69/L39 -> 0.18253181 | M70: =M69/M39 -> 0.18609406 | N70: =N69/N39 -> 0.17932892 | P70: =P69/P39 -> 0.15248251 | Q70: =Q69/Q39 -> 0.18142678 | R70: =R69/R39 -> 0.18539174 | S70: =S69/S39 -> 0.2116491 | T70: =T69/T39 -> 0.18324318 | V70: =V69/V39 -> 0.16461455 | W70: =W69/W39 -> 0.16725827 | X70: =X69/X$39 -> 0.14392306 | Y70: =Y69/Y$39 -> 0.16548637 | Z70: =Z69/Z$39 -> 0.16042138 | AB70: =AB69/AB$39 -> 0.16704031 | AC70: =AC69/AC$39 -> 0.15696882 | AD70: =AD69/AD$39 -> 0.18136526 | AE70: =AE69/AE$39 -> 0.19846718 | AF70: =AF69/AF$39 -> 0.17647859 | AH70: =AH69/AH$39 -> 0.19705769 | AJ70: =AJ69/AJ$39 -> 0.21837236 | AL70: =AL69/AL$39 -> 0.22662639
B72: Basic Weighted Average Shares | D72: =IS!P59 -> 54669 | E72: =IS!Q59 -> 54033 | F72: =IS!R59 -> 53867 | G72: =IS!S59 -> 53809 | H72: =IS!T59 -> 54095 | J72: =IS!V59 -> 53594 | K72: =IS!W59 -> 53527 | L72: =IS!X59 -> 53588 | M72: =IS!Y59 -> 53601 | N72: =IS!Z59 -> 53577 | P72: =IS!AB59 -> 53654 | Q72: =IS!AC59 -> 53765 | R72: =IS!AD59 -> 53770 | S72: =IS!AE59 -> 53764 | T72: =IS!AF59 -> 53738 | V72: =IS!AH59 -> 53594 | W72: =IS!AI59 -> 52616 | X72: =W72+X109 -> 52652.93 | Y72: =X72+Y109 -> 52697.937 | Z72: =AVERAGE(V72:Y72) -> 52890.217 | AB72: =Y72+AB109 -> 52761.961 | AC72: =AB72+AC109 -> 52819.323 | AD72: =AC72+AD109 -> 52881.284 | AE72: =AD72+AE109 -> 52947.081 | AF72: =AVERAGE(AB72:AE72) -> 52852.412 | AH72: =AE72+AH109 -> 53191.04 | AJ72: =AF72+AJ109 -> 53081.464 | AL72: =AH72+AL109 -> 53415.029
B73: Diluted Weighted Average Shares | D73: =IS!P60 -> 56363 | E73: =IS!Q60 -> 54654 | F73: =IS!R60 -> 54384 | G73: =IS!S60 -> 54388 | H73: =IS!T60 -> 54947 | J73: =IS!V60 -> 54377 | K73: =IS!W60 -> 54042 | L73: =IS!X60 -> 54157 | M73: =IS!Y60 -> 53768 | N73: =IS!Z60 -> 54086 | P73: =IS!AB60 -> 54394 | Q73: =IS!AC60 -> 54072 | R73: =IS!AD60 -> 54037 | S73: =IS!AE60 -> 54334 | T73: =IS!AF60 -> 54209 | V73: =IS!AH60 -> 54621 | W73: =IS!AI60 -> 53154 | X73: =W73 -> 53154 | Y73: =X73 -> 53154 | Z73: =AVERAGE(V73:Y73) -> 53520.75 | AB73: =Y73 -> 53154 | AC73: =AB73 -> 53154 | AD73: =AC73 -> 53154 | AE73: =AD73 -> 53154 | AF73: =AVERAGE(AB73:AE73) -> 53154 | AH73: =AF73 -> 53154 | AJ73: =AH73 -> 53154 | AL73: =AJ73 -> 53154
B75: Balance Sheet | D75: Q1 22 | E75: Q2 22 | F75: Q3 22 | G75: Q4 22 | H75: FY 22 | J75: Q1 23 | K75: Q2 23 | L75: Q3 23 | M75: Q4 23 | N75: FY 23 | P75: Q1 24 | Q75: Q2 24 | R75: Q3 24 | S75: Q4 24 | T75: FY 24 | V75: Q1 25 | W75: Q2 25 | X75: Q3 25 | Y75: Q4 25 | Z75: FY 25 | AB75: Q1 26 | AC75: Q2 26 | AD75: Q3 26 | AE75: Q4 26 | AF75: FY 26 | AH75: FY 27 | AJ75: FY 28 | AL75: FY 29
B78: Accounts Receivable | D78: =BS!P18 -> 629855 | E78: =BS!Q18 -> 627276 | F78: =BS!R18 -> 593514 | G78: =BS!S18 -> 631134 | H78: =BS!T18 -> 631134 | J78: =BS!V18 -> 652949 | K78: =BS!W18 -> 643405 | L78: =BS!X18 -> 633169 | M78: =BS!Y18 -> 644576 | N78: =BS!Z18 -> 644576 | P78: =BS!AB18 -> 605180 | Q78: =BS!AC18 -> 624622 | R78: =BS!AD18 -> 614976 | S78: =BS!AE18 -> 643355 | T78: =BS!AF18 -> 643355 | V78: =BS!AH18 -> 645511 | W78: =BS!AI18 -> 665833 | X78: =X39*X79/92 -> 664225.39 | Y78: =Y39*Y79/92 -> 678033.4 | Z78: =Y78 -> 678033.4 | AB78: =AB39*AB79/90 -> 621500.92 | AC78: =AC39*AC79/91 -> 646138.42 | AD78: =AD39*AD79/92 -> 641722.41 | AE78: =AE39*AE79/92 -> 687020.83 | AF78: =AE78 -> 687020.83 | AH78: =AH39*AH79/365 -> 716699.65 | AJ78: =AJ39*AJ79/366 -> 743836.18 | AL78: =AL39*AL79/365 -> 775574.48
B79: days sales outstanding | D79: =D78/D39*90 -> 56.990367 | E79: =E78/E39*91 -> 56.31616 | F79: =F78/F39*92 -> 54.99535 | G79: =G78/G39*92 -> 56.279972 | H79: =H78/H39*365 -> 57.121822 | J79: =J78/J39*90 -> 58.333972 | K79: =K78/K39*91 -> 56.298912 | L79: =L78/L39*92 -> 59.400896 | M79: =M78/M39*92 -> 58.796751 | N79: =N78/N39*365 -> 58.284187 | P79: =P78/P39*90 -> 58.76003 | Q79: =Q78/Q39*91 -> 57.325229 | R79: =R78/R39*92 -> 60.009813 | S79: =S78/S39*92 -> 58.378311 | T79: =T78/T39*365 -> 60.597357 | V79: =V78/V39*90 -> 64.079263 | W79: =W78/W39*91 -> 61.96272 | X79: 64 | Y79: 60 | Z79: =Z78/Z39*365 -> 63.801151 | AB79: =AVERAGE(V79,J79,P79,D79) -> 59.540908 | AC79: =AVERAGE(W79,K79,Q79,E79) -> 57.975755 | AD79: =AVERAGE(X79,L79,R79,F79) -> 59.601515 | AE79: =AVERAGE(Y79,M79,S79,G79) -> 58.363758 | AF79: =AF78/AF39*365 -> 62.267998 | AH79: =AF79 -> 62.267998 | AJ79: =AF79 -> 62.267998 | AL79: =AF79 -> 62.267998
B81: Inventory | D81: =BS!P19 -> 924763 | E81: =BS!Q19 -> 1008920 | F81: =BS!R19 -> 1062634 | G81: =BS!S19 -> 1077729 | H81: =BS!T19 -> 1077729 | J81: =BS!V19 -> 1116364 | K81: =BS!W19 -> 1082523 | L81: =BS!X19 -> 1015047 | M81: =BS!Y19 -> 935867 | N81: =BS!Z19 -> 935867 | P81: =BS!AB19 -> 943679 | Q81: =BS!AC19 -> 920096 | R81: =BS!AD19 -> 905865 | S81: =BS!AE19 -> 841567 | T81: =BS!AF19 -> 841567 | V81: =BS!AH19 -> 877729 | W81: =BS!AI19 -> 888670 | X81: =X82*X42/92 -> 838852.26 | Y81: =Y82*Y42/92 -> 763745.42 | Z81: =Y81 -> 763745.42 | AB81: =AB82*AB42/92 -> 844692.1 | AC81: =AC82*AC42/92 -> 892215.34 | AD81: =AD82*AD42/92 -> 842078.94 | AE81: =AE82*AE42/92 -> 752244.81 | AF81: =AE81 -> 752244.81 | AH81: =AH82*AH42/365 -> 772152.77 | AJ81: =AJ82*AJ42/366 -> 788142.83 | AL81: =AL82*AL42/365 -> 814865.99
B82: days inventory held | D82: =D81/D42*90 -> 125.31305 | E82: =E81/E42*91 -> 140.63024 | F82: =F81/F42*92 -> 155.76204 | G82: =G81/G42*92 -> 154.52877 | H82: =H81/H42*365 -> 155.02926 | J82: =J81/J42*90 -> 159.82025 | K82: =K81/K42*91 -> 152.31574 | L82: =L81/L42*92 -> 154.27036 | M82: =M81/M42*92 -> 138.46702 | N82: =N81/N42*365 -> 139.45679 | P82: =P81/P42*90 -> 146.28969 | Q82: =Q81/Q42*91 -> 136.83312 | R82: =R81/R42*92 -> 141.88479 | S82: =S81/S42*92 -> 123.88937 | T82: =T81/T42*365 -> 130.87336 | V82: =V81/V42*90 -> 140.88899 | W82: =W81/W42*91 -> 133.32218 | X82: =R82-(L82-R82) -> 129.49922 | Y82: =S82-(M82-S82) -> 109.31171 | Z82: =Z81/Z42*365 -> 115.86339 | AB82: =V82-(P82-V82) -> 135.48829 | AC82: =W82-(Q82-W82) -> 129.81124 | AD82: =X82-(R82-X82)+10 -> 127.11365 | AE82: =Y82-(S82-Y82)+10 -> 104.73405 | AF82: =AF81/AF42*365 -> 110.88571 | AH82: =AF82 -> 110.88571 | AJ82: =AF82 -> 110.88571 | AL82: =AF82 -> 110.88571
B84: Prepaid expenses and Other Current Assets | D84: =BS!P20 -> 122526 | E84: =BS!Q20 -> 132475 | F84: =BS!R20 -> 149472 | G84: =BS!S20 -> 135132 | H84: =BS!T20 -> 135132 | J84: =BS!V20 -> 134682 | K84: =BS!W20 -> 152997 | L84: =BS!X20 -> 145452 | M84: =BS!Y20 -> 137920 | N84: =BS!Z20 -> 137920 | P84: =BS!AB20 -> 132046 | Q84: =BS!AC20 -> 139164 | R84: =BS!AD20 -> 164765 | S84: =BS!AE20 -> 155588 | T84: =BS!AF20 -> 155588 | V84: =BS!AH20 -> 145380 | W84: =BS!AI20 -> 193588 | X84: =X85*X$39 -> 150743.41 | Y84: =Y85*Y$39 -> 145961.63 | Z84: =Y84 -> 145961.63 | AB84: =AB85*AB$39 -> 167454.53 | AC84: =AC85*AC$39 -> 200781.06 | AD84: =AD85*AD$39 -> 139659.58 | AE84: =AE85*AE$39 -> 137895.85 | AF84: =AE84 -> 137895.85 | AH84: =AH85*AH$39 -> 143852.86 | AJ84: =AJ85*AJ$39 -> 149708.62 | AL84: =AL85*AL$39 -> 155669.96
B85: % of sales | D85: =D84/D39 -> 0.12318182 | E85: =E84/E39 -> 0.13069738 | F85: =F84/F39 -> 0.15054524 | G85: =G84/G39 -> 0.1309793 | H85: =H84/H39 -> 0.033507792 | J85: =J84/J39 -> 0.13369321 | K85: =K84/K39 -> 0.14711505 | L85: =L84/L39 -> 0.14832188 | M85: =M84/M39 -> 0.13674726 | N85: =N84/N39 -> 0.034167326 | P85: =P84/P39 -> 0.14245582 | Q85: =Q84/Q39 -> 0.14035052 | R85: =R84/R39 -> 0.17475968 | S85: =S84/S39 -> 0.15345785 | T85: =T84/T39 -> 0.040150063 | V85: =V84/V39 -> 0.1603526 | W85: =W84/W39 -> 0.19797128 | X85: =AVERAGE(R85,L85,F85) -> 0.1578756 | Y85: =AVERAGE(S85,M85,G85) -> 0.1403948 | Z85: =Z84/Z$39 -> 0.03762905 | AB85: =V85+(V85-P85) -> 0.17824939 | AC85: =W85 -> 0.19797128 | AD85: =X85+(X85-R85) -> 0.14099152 | AE85: =Y85+(Y85-S85) -> 0.12733175 | AF85: =AF84/AF$39 -> 0.034241544 | AH85: =AF85 -> 0.034241544 | AJ85: =AF85 -> 0.034241544 | AL85: =AF85 -> 0.034241544
B87: Net PP&E (Property, Plant and Equipment) | D87: =BS!P24 -> 382574 | E87: =BS!Q24 -> 417688 | F87: =BS!R24 -> 423947 | G87: =BS!S24 -> 443528 | H87: =BS!T24 -> 443528 | J87: =BS!V24 -> 461728 | K87: =BS!W24 -> 483064 | L87: =BS!X24 -> 498871 | M87: =BS!Y24 -> 510898 | N87: =BS!Z24 -> 510898 | P87: =BS!AB24 -> 508140 | Q87: =BS!AC24 -> 504661 | R87: =BS!AD24 -> 510555 | S87: =BS!AE24 -> 525965 | T87: =BS!AF24 -> 525965 | V87: =BS!AH24 -> 550736 | W87: =BS!AI24 -> 570414 | X87: =W87-X88*X114-X117-X60-X45 -> 559871.86 | Y87: =X87-Y88*Y114-Y117-Y60-Y45 -> 546716.44 | Z87: =Y87 -> 546716.44 | AB87: =Y87-AB88*AB114-AB117-AB60-AB45 -> 544323.51 | AC87: =AB87-AC88*AC114-AC117-AC60-AC45 -> 539276.54 | AD87: =AC87-AD88*AD114-AD117-AD60-AD45 -> 533451.94 | AE87: =AD87-AE88*AE114-AE117-AE60-AE45 -> 523066.59 | AF87: =AE87 -> 523066.59 | AH87: =AF87-AH88*AH114-AH117-AH60-AH45 -> 503913.1 | AJ87: =AH87-AJ88*AJ114-AJ117-AJ60-AJ45 -> 491757.82 | AL87: =AJ87-AL88*AL114-AL117-AL60-AL45 -> 482662.82
B88: capex allocation rate | E88: =(-E114-E60)/(-E114) -> 0.40043094 | F88: =(-F114-F60)/(-F114) -> 0.50737969 | G88: =(-G114-G60)/(-G114) -> 0.27341263 | H88: =AVERAGE(D88:G88) -> 0.39374109 | J88: =(-J114-J60)/(-J114) -> 0.5582073 | K88: =(-K114-K60)/(-K114) -> 0.46897001 | L88: =(-L114-L60)/(-L114) -> 0.40984529 | M88: =(-M114-M60)/(-M114) -> 0.14201107 | N88: =AVERAGE(J88:M88) -> 0.39475842 | P88: =(-P114-P60)/(-P114) -> 0.039788758 | Q88: =(-Q114-Q60)/(-Q114) -> -0.20243211 | R88: =(-R114-R60)/(-R114) -> -0.21638089 | S88: =(-S114-S60)/(-S114) -> -0.12480024 | T88: =AVERAGE(P88:S88) -> -0.12595612 | V88: =(-V114-V60)/(-V114) -> 0.58801584 | W88: =(-W114-W60)/(-W114) -> 0.31641092 | X88: =AVERAGE(R88,L88,F88) -> 0.2336147 | Y88: =AVERAGE(S88,M88,G88) -> 0.096874487 | Z88: =AVERAGE(V88:Y88) -> 0.30872899 | AB88: =AVERAGE(D88,J88,V88) -> 0.57311157 | AC88: =AVERAGE(E88,K88,W88) -> 0.39527062 | AD88: =AVERAGE(F88,L88,X88) -> 0.38361323 | AE88: =AVERAGE(G88,M88,Y88) -> 0.17076606 | AF88: =AVERAGE(AB88:AE88) -> 0.38069037 | AH88: =AF88 -> 0.38069037 | AJ88: =AF88 -> 0.38069037 | AL88: =AF88 -> 0.38069037
B90: Intangibles | D90: =IF($B$90="Intangibles excl. Goodwill",BS!P29,BS!P27) -> 4071598 | E90: =IF($B$90="Intangibles excl. Goodwill",BS!Q29,BS!Q27) -> 4026156 | F90: =IF($B$90="Intangibles excl. Goodwill",BS!R29,BS!R27) -> 4069221 | G90: =IF($B$90="Intangibles excl. Goodwill",BS!S29,BS!S27) -> 4206066 | H90: =IF($B$90="Intangibles excl. Goodwill",BS!T29,BS!T27) -> 4206066 | J90: =IF($B$90="Intangibles excl. Goodwill",BS!V29,BS!V27) -> 4220229 | K90: =IF($B$90="Intangibles excl. Goodwill",BS!W29,BS!W27) -> 4242637 | L90: =IF($B$90="Intangibles excl. Goodwill",BS!X29,BS!X27) -> 4227965 | M90: =IF($B$90="Intangibles excl. Goodwill",BS!Y29,BS!Y27) -> 4179386 | N90: =IF($B$90="Intangibles excl. Goodwill",BS!Z29,BS!Z27) -> 4179386 | P90: =IF($B$90="Intangibles excl. Goodwill",BS!AB29,BS!AB27) -> 4142795 | Q90: =IF($B$90="Intangibles excl. Goodwill",BS!AC29,BS!AC27) -> 4122686 | R90: =IF($B$90="Intangibles excl. Goodwill",BS!AD29,BS!AD27) -> 4157772 | S90: =IF($B$90="Intangibles excl. Goodwill",BS!AE29,BS!AE27) -> 4129259 | T90: =IF($B$90="Intangibles excl. Goodwill",BS!AF29,BS!AF27) -> 4129259 | V90: =IF($B$90="Intangibles excl. Goodwill",BS!AH29,BS!AH27) -> 4149634 | W90: =IF($B$90="Intangibles excl. Goodwill",BS!AI29,BS!AI27) -> 4206332 | X90: =W90-(1-X88)*X114-X63+X91*X54 -> 4202173.1 | Y90: =X90-(1-Y88)*Y114-Y63+Y91*Y54 -> 4203661.3 | Z90: =Y90 -> 4203661.3 | AB90: =Y90-(1-AB88)*AB114-AB63+AB91*AB54 -> 4194182.4 | AC90: =AB90-(1-AC88)*AC114-AC63+AC91*AC54 -> 4191584.2 | AD90: =AC90-(1-AD88)*AD114-AD63+AD91*AD54 -> 4186288.3 | AE90: =AD90-(1-AE88)*AE114-AE63+AE91*AE54 -> 4188819.9 | AF90: =AE90 -> 4188819.9 | AH90: =AF90-(1-AH88)*AH114-AH63+AH91*AH54 -> 4180053 | AJ90: =AH90-(1-AJ88)*AJ114-AJ63+AJ91*AJ54 -> 4179392.4 | AL90: =AJ90-(1-AL88)*AL114-AL63+AL91*AL54 -> 4181546.4
B91: r&d capitalization rate | D91: =IFERROR(BS!P57/FCFF!D90,"") -> 0 | E91: =IFERROR(BS!Q57/FCFF!E90,"") -> 0 | F91: =IFERROR(BS!R57/FCFF!F90,"") -> 0 | G91: =IFERROR(BS!S57/FCFF!G90,"") -> 0 | H91: =IFERROR(BS!T57/FCFF!H90,"") -> 0 | J91: =IFERROR(BS!V57/FCFF!J90,"") -> 0 | K91: =IFERROR(BS!W57/FCFF!K90,"") -> 0 | L91: =IFERROR(BS!X57/FCFF!L90,"") -> 0 | M91: =IFERROR(BS!Y57/FCFF!M90,"") -> 0 | N91: =IFERROR(BS!Z57/FCFF!N90,"") -> 0 | P91: =IFERROR(BS!AB57/FCFF!P90,"") -> 0 | Q91: =IFERROR(BS!AC57/FCFF!Q90,"") -> 0 | R91: =IFERROR(BS!AD57/FCFF!R90,"") -> 0 | S91: =IFERROR(BS!AE57/FCFF!S90,"") -> 0 | T91: =IFERROR(BS!AF57/FCFF!T90,"") -> 0 | V91: =IFERROR(BS!AH57/FCFF!V90,"") -> 0 | W91: =IFERROR(BS!AI57/FCFF!W90,"") -> 0 | X91: 0 | Y91: 0 | Z91: =AVERAGE(V91:Y91) -> 0 | AB91: 0 | AC91: 0 | AD91: 0 | AE91: 0 | AF91: =AVERAGE(AB91:AE91) -> 0 | AH91: 0 | AJ91: 0 | AL91: 0
B93: Accounts Payable | D93: =BS!P37 -> 556304 | E93: =BS!Q37 -> 555919 | F93: =BS!R37 -> 506211 | G93: =BS!S37 -> 538060 | H93: =BS!T37 -> 538060 | J93: =BS!V37 -> 751157 | K93: =BS!W37 -> 496222 | L93: =BS!X37 -> 480175 | M93: =BS!Y37 -> 480393 | N93: =BS!Z37 -> 480393 | P93: =BS!AB37 -> 507054 | Q93: =BS!AC37 -> 520258 | R93: =BS!AD37 -> 469035 | S93: =BS!AE37 -> 475313 | T93: =BS!AF37 -> 475313 | V93: =BS!AH37 -> 529098 | W93: =BS!AI37 -> 516153 | X93: =X94*X42/92 -> 474304.74 | Y93: =Y94*Y42/92 -> 492744.98 | Z93: =Y93 -> 492744.98 | AB93: =AB94*AB42/90 -> 541702.59 | AC93: =AC94*AC42/91 -> 514204.1 | AD93: =AD94*AD42/92 -> 486686.77 | AE93: =AE94*AE42/92 -> 509952.39 | AF93: =AE93 -> 509952.39 | AH93: =AH94*AH42/365 -> 523448.15 | AJ93: =AJ94*AJ42/366 -> 534287.93 | AL93: =AL94*AL42/365 -> 552403.76
B94: days payable outstanding | D94: =D93/D42*90 -> 75.383805 | E94: =E93/E42*91 -> 77.487833 | F94: =F93/F42*92 -> 74.200953 | G94: =G93/G42*92 -> 77.149033 | H94: =H93/H42*365 -> 77.398903 | J94: =J93/J42*90 -> 107.5367 | K94: =K93/K42*91 -> 69.820613 | L94: =L93/L42*92 -> 72.978661 | M94: =M93/M42*92 -> 71.076968 | N94: =N93/N42*365 -> 71.585028 | P94: =P93/P42*90 -> 78.603816 | Q94: =Q93/Q42*91 -> 77.370761 | R94: =R93/R42*92 -> 73.464516 | S94: =S93/S42*92 -> 69.972119 | T94: =T93/T42*365 -> 73.916647 | V94: =V93/V42*90 -> 84.928357 | W94: =W93/W42*91 -> 77.435544 | X94: =AVERAGE(R94,L94) -> 73.221589 | Y94: =AVERAGE(S94,M94) -> 70.524543 | Z94: =Z93/Z42*365 -> 74.751486 | AB94: 85 | AC94: 74 | AD94: =AVERAGE(X94,L94,R94,F94) -> 73.46643 | AE94: 71 | AF94: =AF93/AF42*365 -> 75.170251 | AH94: =AF94 -> 75.170251 | AJ94: =AF94 -> 75.170251 | AL94: =AF94 -> 75.170251
B96: Accrued Expenses and Other Current Liabilities | D96: =BS!P40 -> 312397 | E96: =BS!Q40 -> 348047 | F96: =BS!R40 -> 362987 | G96: =BS!S40 -> 379391 | H96: =BS!T40 -> 379391 | J96: =BS!V40 -> 169023 | K96: =BS!W40 -> 311093 | L96: =BS!X40 -> 313108 | M96: =BS!Y40 -> 299462 | N96: =BS!Z40 -> 299462 | P96: =BS!AB40 -> 263208 | Q96: =BS!AC40 -> 266987 | R96: =BS!AD40 -> 276431 | S96: =BS!AE40 -> 282122 | T96: =BS!AF40 -> 282122 | V96: =BS!AH40 -> 285437 | W96: =BS!AI40 -> 293314 | X96: =X97*X39 -> 292407.8 | Y96: =Y97*Y39 -> 298990.76 | Z96: =Y96 -> 298990.76 | AB96: =AB97*AB39 -> 281831.86 | AC96: =AC97*AC39 -> 304257.85 | AD96: =AD97*AD39 -> 297165.91 | AE96: =AE97*AE39 -> 324889.54 | AF96: =AE96 -> 324889.54 | AH96: =AH97*AH39 -> 336089.65 | AJ96: =AJ97*AJ39 -> 349770.74 | AL96: =AL97*AL39 -> 363698.46
B97: % of sales | D97: =D96/D39 -> 0.3140691 | E97: =E96/E39 -> 0.34337673 | F97: =F96/F39 -> 0.36559331 | G97: =G96/G39 -> 0.36773206 | H97: =H96/H39 -> 0.094075088 | J97: =J96/J39 -> 0.16778208 | K97: =K96/K39 -> 0.29913306 | L97: =L96/L39 -> 0.31928586 | M97: =M96/M39 -> 0.29691565 | N97: =N96/N39 -> 0.0741866 | P97: =P96/P39 -> 0.28395794 | Q97: =Q96/Q39 -> 0.26926335 | R97: =R96/R39 -> 0.29319936 | S97: =S96/S39 -> 0.27825948 | T97: =T96/T39 -> 0.072802634 | V97: =V96/V39 -> 0.31483399 | W97: =W96/W39 -> 0.29995531 | X97: =AVERAGE(R97,L97) -> 0.30624261 | Y97: =AVERAGE(S97,M97) -> 0.28758757 | Z97: =Z96/Z39 -> 0.077080111 | AB97: 0.3 | AC97: 0.3 | AD97: 0.3 | AE97: 0.3 | AF97: =AF96/AF39 -> 0.080674794 | AH97: 0.08 | AJ97: 0.08 | AL97: 0.08
B99: Cash Flow Statement | D99: Q1 22 | E99: Q2 22 | F99: Q3 22 | G99: Q4 22 | H99: FY 22 | J99: Q1 23 | K99: Q2 23 | L99: Q3 23 | M99: Q4 23 | N99: FY 23 | P99: Q1 24 | Q99: Q2 24 | R99: Q3 24 | S99: Q4 24 | T99: FY 24 | V99: Q1 25 | W99: Q2 25 | X99: Q3 25 | Y99: Q4 25 | Z99: FY 25 | AB99: Q1 26 | AC99: Q2 26 | AD99: Q3 26 | AE99: Q4 26 | AF99: FY 26 | AH99: FY 27 | AJ99: FY 28 | AL99: FY 29
B102: D&A (Depreciation & Amortization) | D102: =CF!P17 -> 46742 | E102: =CF!Q17 -> 29035 | F102: =CF!R17 -> 31140 | G102: =CF!S17 -> 31144 | H102: =CF!T17 -> 138061 | J102: =CF!V17 -> 34947 | K102: =CF!W17 -> 30830 | L102: =CF!X17 -> 33281 | M102: =CF!Y17 -> 33546 | N102: =CF!Z17 -> 132604 | P102: =CF!AB17 -> 32410 | Q102: =CF!AC17 -> 31646 | R102: =CF!AD17 -> 30780 | S102: =CF!AE17 -> 32338 | T102: =CF!AF17 -> 127174 | V102: =CF!AH17 -> 32145 | W102: =CF!AI17 -> 32190 | X102: =X45+X57 -> 33797.553 | Y102: =Y45+Y57 -> 32460.217 | Z102: =SUM(V102:Y102) -> 130592.77 | AB102: =AB45+AB57 -> 32539.462 | AC102: =AC45+AC57 -> 29957.436 | AD102: =AD45+AD57 -> 32912.663 | AE102: =AE45+AE57 -> 31679.008 | AF102: =SUM(AB102:AE102) -> 127088.57 | AH102: =AH45+AH57 -> 128747.26 | AJ102: =AJ45+AJ57 -> 126491.34 | AL102: =AL45+AL57 -> 125143.03
B103: % of net pp&e and intangibles excl. Goodwill | D103: =D102/(D90+D87) -> 0.010493982 | E103: =E102/(E90+E87) -> 0.0065337577 | F103: =F102/(F90+F87) -> 0.0069305221 | G103: =G102/(G90+G87) -> 0.0066982192 | H103: =H102/(H90+H87) -> 0.02969313 | J103: =J102/(J90+J87) -> 0.0074641865 | K103: =K102/(K90+K87) -> 0.0065238998 | L103: =L102/(L90+L87) -> 0.007040862 | M103: =M102/(M90+M87) -> 0.0071522321 | N103: =N102/(N90+N87) -> 0.028272062 | P103: =P102/(P90+P87) -> 0.0069684913 | Q103: =Q102/(Q90+Q87) -> 0.0068389079 | R103: =R102/(R90+R87) -> 0.0065933685 | S103: =S102/(S90+S87) -> 0.0069466045 | T103: =T102/(T90+T87) -> 0.027318557 | V103: =V102/(V90+V87) -> 0.0068388233 | W103: =W102/(W90+W87) -> 0.0067388971 | X103: =X102/(X87+X90) -> 0.0070972772 | Y103: =Y102/(Y87+Y90) -> 0.0068331865 | Z103: =Z102/(Z87+Z90) -> 0.027491029 | AB103: =AB102/(AB87+AB90) -> 0.00686703 | AC103: =AC102/(AC87+AC90) -> 0.0063323437 | AD103: =AD102/(AD87+AD90) -> 0.0069734057 | AE103: =AE102/(AE87+AE90) -> 0.0067232113 | AF103: =AF102/(AF87+AF90) -> 0.026971908 | AH103: =AH102/(AH87+AH90) -> 0.027486805 | AJ103: =AJ102/(AJ87+AJ90) -> 0.027079271 | AL103: =AL102/(AL87+AL90) -> 0.026830493
B105: Stock-Based Compensation Expense | D105: =CF!P18 -> 13723 | E105: =CF!Q18 -> 13157 | F105: =CF!R18 -> 15761 | G105: =CF!S18 -> 15727 | H105: =CF!T18 -> 58368 | J105: =CF!V18 -> 12232 | K105: =CF!W18 -> 9898 | L105: =CF!X18 -> 13175 | M105: =CF!Y18 -> 15742 | N105: =CF!Z18 -> 51047 | P105: =CF!AB18 -> 13822 | Q105: =CF!AC18 -> 7648 | R105: =CF!AD18 -> 8669 | S105: =CF!AE18 -> 6012 | T105: =CF!AF18 -> 36151 | V105: =CF!AH18 -> 2488 | W105: =CF!AI18 -> 6224 | X105: =X106*X51 -> 5408.9397 | Y105: =Y106*Y51 -> 6631.4363 | Z105: =SUM(V105:Y105) -> 20752.376 | AB105: =AB106*AB51 -> 9029.6487 | AC105: =AC106*AC51 -> 8155.4903 | AD105: =AD106*AD51 -> 8879.3421 | AE105: =AE106*AE51 -> 9520.3627 | AF105: =SUM(AB105:AE105) -> 35584.844 | AH105: =AH106*AH51 -> 34842.832 | AJ105: =AJ106*AJ51 -> 33889.133 | AL105: =AL106*AL51 -> 34530.817
B106: % of sg&a | D106: =D105/D51 -> 0.086129958 | E106: =E105/E51 -> 0.082000112 | F106: =F105/F51 -> 0.092679054 | G106: =G105/G51 -> 0.092876167 | H106: =H105/H51 -> 0.088547316 | J106: =J105/J51 -> 0.067782334 | K106: =K105/K51 -> 0.057316247 | L106: =L105/L51 -> 0.080752918 | M106: =M105/M51 -> 0.099608325 | N106: =N105/N51 -> 0.075698978 | P106: =P105/P51 -> 0.079602391 | Q106: =Q105/Q51 -> 0.045813416 | R106: =R105/R51 -> 0.058300156 | S106: =S105/S51 -> 0.041162294 | T106: =T105/T51 -> 0.056901317 | V106: =V105/V51 -> 0.014595714 | W106: =W105/W51 -> 0.034306944 | X106: =W106 -> 0.034306944 | Y106: =S106 -> 0.041162294 | Z106: =Z105/Z51 -> 0.030943687 | AB106: =AVERAGE(V106,P106,J106) -> 0.05399348 | AC106: =AVERAGE(W106,Q106,K106) -> 0.045812202 | AD106: =AVERAGE(X106,R106,L106) -> 0.057786672 | AE106: =AVERAGE(Y106,S106,M106) -> 0.060644304 | AF106: =AF105/AF51 -> 0.054253447 | AH106: =AF106 -> 0.054253447 | AJ106: =AF106 -> 0.054253447 | AL106: =AF106 -> 0.054253447
B107: implied equity value (p/s multiple) | X107: 2 | Y107: 2 | Z107: =AVERAGE(V107:Y107) -> 2 | AB107: 1.9 | AC107: 1.9 | AD107: 1.9 | AE107: 1.9 | AF107: =AVERAGE(AB107:AE107) -> 1.9 | AH107: 1.8 | AJ107: 1.8 | AL107: 1.8
B108: implied share price (for dilution) | X108: =X107*(X39+W39+V39+S39)/W72 -> 146.46461 | Y108: =Y107*(Y39+X39+W39+V39)/X72 -> 147.34075 | Z108: =AVERAGE(V108:Y108) -> 146.90268 | AB108: =AB107*(AB39+Y39+X39+W39)/Y72 -> 141.03721 | AC108: =AC107*(AC39+AB39+Y39+X39)/AB72 -> 142.17448 | AD108: =AD107*(AD39+AC39+AB39+Y39)/AC72 -> 143.30531 | AE108: =AE107*(AE39+AD39+AC39+AB39)/AD72 -> 144.69365 | AF108: =AVERAGE(AB108:AE108) -> 142.80266 | AH108: =AH107*AH39/AE72 -> 142.82217 | AJ108: =AJ107*AJ39/AH72 -> 147.95427 | AL108: =AL107*AL39/AJ72 -> 154.16333
B109: sbc dilution (shares issued) | X109: =X105/X108 -> 36.930011 | Y109: =Y105/Y108 -> 45.007482 | Z109: =AVERAGE(V109:Y109) -> 40.968746 | AB109: =AB105/AB108 -> 64.023165 | AC109: =AC105/AC108 -> 57.362546 | AD109: =AD105/AD108 -> 61.961011 | AE109: =AE105/AE108 -> 65.796686 | AF109: =AVERAGE(AB109:AE109) -> 62.285852 | AH109: =AH105/AH108 -> 243.95954 | AJ109: =AJ105/AJ108 -> 229.0514 | AL109: =AL105/AL108 -> 223.98852
B111: Changes in Net Working Capital | D111: =SUM(CF!P21:P24) -> -152461 | E111: =SUM(CF!Q21:Q24) -> -28579 | F111: =SUM(CF!R21:R24) -> -51399 | G111: =SUM(CF!S21:S24) -> -6557 | H111: =SUM(CF!T21:T24) -> -238996 | J111: =SUM(CF!V21:V24) -> -58900 | K111: =SUM(CF!W21:W24) -> -84221 | L111: =SUM(CF!X21:X24) -> 71438 | M111: =SUM(CF!Y21:Y24) -> 47773 | N111: =SUM(CF!Z21:Z24) -> -23910 | P111: =SUM(CF!AB21:AB24) -> 17397 | Q111: =SUM(CF!AC21:AC24) -> 10562 | R111: =SUM(CF!AD21:AD24) -> -39057 | S111: =SUM(CF!AE21:AE24) -> 47033 | T111: =SUM(CF!AF21:AF24) -> 35935 | V111: =SUM(CF!AH21:AH24) -> 22205 | W111: =SUM(CF!AI21:AI24) -> -67824 | X111: =-((X78+X81+X84-X93-X96)-(W78+W81+W84-W93-W96)) -> 51515.474 | Y111: =-((Y78+Y81+Y84-Y93-Y96)-(X78+X81+X84-X93-X96)) -> 91103.828 | Z111: =SUM(V111:Y111) -> 97000.303 | AB111: =-((AB78+AB81+AB84-AB93-AB96)-(Y78+Y81+Y84-Y93-Y96)) -> -14108.397 | AC111: =-((AC78+AC81+AC84-AC93-AC96)-(AB78+AB81+AB84-AB93-AB96)) -> -110559.77 | AD111: =-((AD78+AD81+AD84-AD93-AD96)-(AC78+AC81+AC84-AC93-AC96)) -> 81064.618 | AE111: =-((AE78+AE81+AE84-AE93-AE96)-(AD78+AD81+AD84-AD93-AD96)) -> 97288.695 | AF111: =SUM(AB111:AE111) -> 53685.146 | AH111: =-((AH78+AH81+AH84-AH93-AH96)-(AF78+AF81+AF84-AF93-AF96)) -> -30847.923 | AJ111: =-((AJ78+AJ81+AJ84-AJ93-AJ96)-(AH78+AH81+AH84-AH93-AH96)) -> -24461.493 | AL111: =-((AL78+AL81+AL84-AL93-AL96)-(AJ78+AJ81+AJ84-AJ93-AJ96)) -> -32379.241
B112: % of change in sales | D112: =D111/(D39-IS!M18) -> -1.188687 | E112: =E111/(E39-D39) -> -1.5101189 | F112: =F111/(F39-E39) -> 2.4794501 | G112: =G111/(G39-F39) -> -0.16884689 | H112: =H111/IS!N18 -> -0.073519315 | J112: =J111/(J39-IS!S18) -> 2.4229709 | K112: =K111/(K39-J39) -> -2.5845762 | L112: =L111/(L39-K39) -> -1.2040586 | M112: =M111/(M39-L39) -> 1.710761 | N112: =N111/IS!T18 -> -0.0059288052 | P112: =P111/(P39-IS!Y18) -> -0.21306797 | Q112: =Q111/(Q39-P39) -> 0.16344785 | R112: =R111/(R39-Q39) -> 0.80138293 | S112: =S111/(S39-R39) -> 0.66176553 | T112: =T111/IS!Z18 -> 0.008902283 | V112: =V111/(V39-IS!AE18) -> -0.20703191 | W112: =W111/(W39-V39) -> -0.95215633 | X112: =X111/(X39-W39) -> -2.2363995 | Y112: =Y111/(Y39-X39) -> 1.0739929 | Z112: =Z111/(Z39-T39) -> 25.531745 | AB112: =AB111/(AB39-IS!AK18) -> -0.015017887 | AC112: =AC111/(AC39-AB39) -> -1.4789951 | AD112: =AD111/(AD39-AC39) -> -3.429159 | AE112: =AE111/(AE39-AD39) -> 1.0527701 | AF112: =AF111/(AF39-Z39) -> 0.36227394 | AH112: =AH111/(AH39-AF39) -> -0.17731737 | AJ112: =AJ111/(AJ39-AH39) -> -0.14303836 | AL112: =AL111/(AL39-AJ39) -> -0.18598437
