Workbook
Name COOLFUCNTION: _xlfn.LAMBDA(_xldudf_BOARDFLARE_EXEC("workbook-settings:coolfucntion"))
Name COOLFUCNTION: _xlfn.LAMBDA(_xldudf_BOARDFLARE_EXEC("workbook-settings:coolfucntion"))
Name COOLFUCNTION: _xlfn.LAMBDA(_xldudf_BOARDFLARE_EXEC("workbook-settings:coolfucntion"))
Name COOLFUCNTION: _xlfn.LAMBDA(_xldudf_BOARDFLARE_EXEC("workbook-settings:coolfucntion"))
Name COOLFUCNTION: _xlfn.LAMBDA(_xldudf_BOARDFLARE_EXEC("workbook-settings:coolfucntion"))
Name COOLFUCNTION: _xlfn.LAMBDA(_xldudf_BOARDFLARE_EXEC("workbook-settings:coolfucntion"))
Name COOLFUCNTION: _xlfn.LAMBDA(_xldudf_BOARDFLARE_EXEC("workbook-settings:coolfucntion"))
Name COOLFUCNTION: _xlfn.LAMBDA(_xldudf_BOARDFLARE_EXEC("workbook-settings:coolfucntion"))
Name COOLFUCNTION: _xlfn.LAMBDA(_xldudf_BOARDFLARE_EXEC("workbook-settings:coolfucntion"))
Name COOLFUCNTION: _xlfn.LAMBDA(_xldudf_BOARDFLARE_EXEC("workbook-settings:coolfucntion"))
Name COOLFUCNTION: _xlfn.LAMBDA(_xldudf_BOARDFLARE_EXEC("workbook-settings:coolfucntion"))
Name Sectors: #REF!
Name Sectors: #REF!
Name Sectors: #REF!
Name Sectors: #REF!
Name Sectors: #REF!
Name Sectors: #REF!
Name Sectors: #REF!
Name Sectors: #REF!

Sheet Dashboard
C154: =+C155+1 -> 45947
C155: =+C156+1 -> 45946
C156: =+C157+1 -> 45945
C157: =+C158+1 -> 45944
C158: =+C159+1 -> 45943
C159: =+C160+1 -> 45942
C160: =+C161+1 -> 45941 | L160: =IF(FCFF!$R$157="Revenue Exit",FCFF!$AF$169,IF(FCFF!$R$157="EBITDA Exit",FCFF!Z169,FCFF!AL169)) -> 20.277514
C161: =+C162+1 -> 45940
C162: =+C163+1 -> 45939 | E162: =IF(FCFF!$R$157="Revenue Exit",FCFF!$AF$169,IF(FCFF!$R$157="EBITDA Exit",FCFF!Z169,FCFF!AL169)) -> 20.277514
C163: =+C164+1 -> 45938 | E163: =E164+($E$162-$E$193)/COUNTA($C$162:$C$192) -> 19.95711
C164: =+C165+1 -> 45937 | E164: =E165+($E$162-$E$193)/COUNTA($C$162:$C$192) -> 19.636707
C165: =+C166+1 -> 45936 | E165: =E166+($E$162-$E$193)/COUNTA($C$162:$C$192) -> 19.316303
C166: =+C167+1 -> 45935 | E166: =E167+($E$162-$E$193)/COUNTA($C$162:$C$192) -> 18.995899
C167: =+C168+1 -> 45934 | E167: =E168+($E$162-$E$193)/COUNTA($C$162:$C$192) -> 18.675496
C168: =+C169+1 -> 45933 | E168: =E169+($E$162-$E$193)/COUNTA($C$162:$C$192) -> 18.355092
C169: =+C170+1 -> 45932 | E169: =E170+($E$162-$E$193)/COUNTA($C$162:$C$192) -> 18.034688
C170: =+C171+1 -> 45931 | E170: =E171+($E$162-$E$193)/COUNTA($C$162:$C$192) -> 17.714285
C171: =+C172+1 -> 45930 | E171: =E172+($E$162-$E$193)/COUNTA($C$162:$C$192) -> 17.393881
C172: =+C173+1 -> 45929 | E172: =E173+($E$162-$E$193)/COUNTA($C$162:$C$192) -> 17.073477
C173: =+C174+1 -> 45928 | E173: =E174+($E$162-$E$193)/COUNTA($C$162:$C$192) -> 16.753073
C174: =+C175+1 -> 45927 | E174: =E175+($E$162-$E$193)/COUNTA($C$162:$C$192) -> 16.43267
... C192: =+C193+1 -> 45909 | E192: =E193+($E$162-$E$193)/COUNTA($C$162:$C$192) -> 10.665404
B193: TODAY | C193: =+'Stock Data'!AM4 -> 45908 | D193: =_xlfn.XLOOKUP(C193,'Stock Data'!$AM$4:$AM$1051,'Stock Data'!$AN$4:$AN$1051) -> 10.345 | E193: =D193 -> 10.345
C194: =+'Stock Data'!AM5 -> 45907 | D194: =_xlfn.XLOOKUP(C194,'Stock Data'!$AM$4:$AM$1051,'Stock Data'!$AN$4:$AN$1051) -> 10.46
C195: =+'Stock Data'!AM6 -> 45906 | D195: =_xlfn.XLOOKUP(C195,'Stock Data'!$AM$4:$AM$1051,'Stock Data'!$AN$4:$AN$1051) -> 10.46
C196: =+'Stock Data'!AM7 -> 45905 | D196: =_xlfn.XLOOKUP(C196,'Stock Data'!$AM$4:$AM$1051,'Stock Data'!$AN$4:$AN$1051) -> 10.46
C197: =+'Stock Data'!AM8 -> 45904 | D197: =_xlfn.XLOOKUP(C197,'Stock Data'!$AM$4:$AM$1051,'Stock Data'!$AN$4:$AN$1051) -> 10.45
C198: =+'Stock Data'!AM9 -> 45903 | D198: =_xlfn.XLOOKUP(C198,'Stock Data'!$AM$4:$AM$1051,'Stock Data'!$AN$4:$AN$1051) -> 10.11
C199: =+'Stock Data'!AM10 -> 45902 | D199: =_xlfn.XLOOKUP(C199,'Stock Data'!$AM$4:$AM$1051,'Stock Data'!$AN$4:$AN$1051) -> 10.29
C200: =+'Stock Data'!AM11 -> 45901 | D200: =_xlfn.XLOOKUP(C200,'Stock Data'!$AM$4:$AM$1051,'Stock Data'!$AN$4:$AN$1051) -> 10.21
C201: =+'Stock Data'!AM12 -> 45900 | D201: =_xlfn.XLOOKUP(C201,'Stock Data'!$AM$4:$AM$1051,'Stock Data'!$AN$4:$AN$1051) -> 10.21
C202: =+'Stock Data'!AM13 -> 45899 | D202: =_xlfn.XLOOKUP(C202,'Stock Data'!$AM$4:$AM$1051,'Stock Data'!$AN$4:$AN$1051) -> 10.21
C203: =+'Stock Data'!AM14 -> 45898 | D203: =_xlfn.XLOOKUP(C203,'Stock Data'!$AM$4:$AM$1051,'Stock Data'!$AN$4:$AN$1051) -> 10.21
C204: =+'Stock Data'!AM15 -> 45897 | D204: =_xlfn.XLOOKUP(C204,'Stock Data'!$AM$4:$AM$1051,'Stock Data'!$AN$4:$AN$1051) -> 10.16
C205: =+'Stock Data'!AM16 -> 45896 | D205: =_xlfn.XLOOKUP(C205,'Stock Data'!$AM$4:$AM$1051,'Stock Data'!$AN$4:$AN$1051) -> 10.15
... C558: =+'Stock Data'!AM369 -> 45543 | D558: =_xlfn.XLOOKUP(C558,'Stock Data'!$AM$4:$AM$1051,'Stock Data'!$AN$4:$AN$1051) -> 4.07

Sheet Key Info
B7: Analysts | F7: LIS – Equity Research | J7: Stock Performance
B12: Mariana Zhu, Co-Head of Equity Research | F12: Recommendation: | H12: Strong Buy
B13: MSc in Mathematical Finance, ISEG – Ulisboa | F13: Target Price (FCFF):
B14: 63113l@aln.iseg.ulisboa.pt | F14: Upside:
B15: João Garcia, Analyst
B16: BSc in MAEG, ISEG – Ulisboa | F16: Ticker | H16: 005930
B17: joaogarcia@aln.iseg.ulisboa.pt | F17: Stock Exchange | H17: KRX
B18: Maria Inês Ferreira, Analyst
B19: BSc in Management, ISEG – Ulisboa | F19: Current Price | H19: 10.345
B20: 61624@aln.iseg.ulisboa.pt | F20: Market Cap (in millions) | H20: -296.62353
B21: Name, Analyst | F21: Beta | H21: 1.2550896
B22: BSc in XXX, ISEG – Ulisboa | F22: % of 52-Week High | H22: 0.49721275
B23: email@aln.iseg.ulisboa.pt | F23: 100-Day Moving Average | H23: 11.4455
B25: Reviewed by: | F25: Avg Vol (1 month) | H25: 1152697
B26: Name, Co-Head of Equity Research | F26: Shares Outstanding (millions) | H26: 28.35789
B27: BSc in XXX, ISEG – Ulisboa | F27: % Float | H27: 0.9377795
B28: email@aln.iseg.ulisboa.pt | F28: Short % of Float | H28: 0.1964122
B30: LISBON INVESTMENT SOCIETY | F30: % Held by Insiders | H30: 0.062220497
B31: ISEG – Rua do Quelhas, 6 | F31: % Held by Institutions | H31: 0.71446345
B32: lis@iseg.ulisboa.pt
B34: Disclaimer: This report was prepared by members of the Lisbon Investment Society (LIS), an independent, student-led, non-profit organization based at ISEG – Lisbon School of Economics & Management, and is intended solely for academic and educational purposes. All analyses, forecasts, and opinions expressed in this report reflect the independent judgment of the authors as of the date of publication and are subject to change without notice. The views presented herein do not represent those of ISEG, its faculty, or any affiliated entity. This document does not constitute, and should not be interpreted as, investment advice, an offer, or a solicitation to buy or sell any security or financial instrument. Nothing in this report should be construed as a recommendation to make or refrain from making any investment decision. The content is intended for informational purposes only, and readers are strongly encouraged to conduct their own research and seek advice from a qualified financial professional before making any financial decisions. The information contained in this report has been obtained from publicly available sources believed to be reliable; however, no representation or warranty is made regarding the accuracy, completeness, or timeliness of such information. LIS and its members accept no liability whatsoever for any direct or indirect loss arising from the use of this report or its contents. This report incorporates terminology, financial metrics, and methodologies commonly used in professional equity research, including but not limited to Discounted Cash Flow (DCF), trading multiples, Monte Carlo simulations, and strategic analysis tools such as Porter’s Five Forces. Definitions and assumptions used in these models are disclosed within the report and reflect a hypothetical investment thesis designed solely for academic discussion. All valuations, projections, and target prices presented herein are based on publicly available data and subject to the limitations of modeling assumptions. These are not guarantees of future performance and should not be relied upon as such, as past performance is not indicative of future results. Any company names, logos, trademarks, or brand references mentioned in this report are the property of their respective owners and are used strictly for identification and academic purposes. This document may not be reproduced, redistributed, or quoted in whole or in part without the prior written consent of the Lisbon Investment Society. About LIS – Lisbon Investment Society: The Lisbon Investment Society (LIS) is a non-profit academic association headquartered at ISEG – Lisbon School of Economics & Management. Founded in 2016, LIS is committed to fostering student interest in finance and investment through applied research, skill development, and institutional engagement. The Society operates independently and autonomously from any political, religious, or commercial affiliation, and is composed of selected students and collaborators who are invited through a rigorous recruitment process and share a commitment to excellence, analytical rigor, and ethical standards. Its activities include equity research, portfolio management, macroeconomic analysis, and investment education. This report was prepared by the Equity Research team at the Lisbon Investment Society, whose analysts combine rigorous financial modeling, critical thinking, and collaborative research to deliver high-quality, student-led investment analysis. We welcome your feedback, discussion, and questions regarding this report or our research process, and invite you to reach out to our team as we are always open to engagement.

Sheet Industry
D6: 584.17 | E6: 627.76 | F6: 676.06 | G6: 729.63 | H6: 789.13 | I6: 855.3 | J6: 929 | K6: 997.69 | L6: 1067.63 | M6: 1137.57
A7: x | B7: Industry Growth Forecast | O7: Industry Index
B9: (in trillions) | D9: 2022 | E9: =+D9+1 -> 2023 | F9: =+E9+1 -> 2024 | G9: =+F9+1 -> 2025 | H9: =+G9+1 -> 2026 | I9: =+H9+1 -> 2027 | J9: =+I9+1 -> 2028 | K9: =+J9+1 -> 2029 | M9: ="CAGR "&$G$9&" - "&$K$9 -> CAGR 2025 - 2029
B12: Market Size (FinTech Market Industry) | F12: 0.34 | G12: 0.39 | H12: =G12*(1+L12)^1 -> 0.45318 | I12: =G12*(1+L12)^2 -> 0.52659516 | J12: =G12*(1+L12)^3 -> 0.61190358 | K12: =G12*(1+L12)^4 -> 0.71103196 | L12: 0.162 | M12: =(K12/G12)^(1/5)-1 -> 0.12762554
B13: Market Share | F13: =Segments!AF14/(F12*10^6) -> 0.00154695 | G13: =Segments!AL14/(G12*10^6) -> 0.0018552644 | H13: =Segments!AR14/(H12*10^6) -> 0.0018767786 | I13: =Segments!AT14/(I12*10^6) -> 0.0019184593 | J13: =Segments!AV14/(J12*10^6) -> 0.0021224791 | K13: =Segments!AX14/(K12*10^6) -> 0.0023296484 | M13: =((K13*K12)/(G13*G12))^(1/5)-1 -> 0.18016251
B14: Market Size (Financial Services Industry) | E14: 30.9 | F14: 33.77 | G14: 36.13 | H14: =G14*(1+L14)^1 -> 38.69523 | I14: =G14*(1+L14)^2 -> 41.442591 | J14: =G14*(1+L14)^3 -> 44.385015 | K14: 47.55 | L14: 0.071 | M14: =(K14/G14)^(1/5)-1 -> 0.056468401
B15: Market Share | E15: =Segments!Z14/(Industry!E14*10^6) -> 1.6470841e-05 | F15: =Segments!AF14/(Industry!F14*10^6) -> 1.5574859e-05 | G15: =Segments!AL14/(Industry!G14*10^6) -> 2.002638e-05 | H15: =Segments!AR14/(Industry!H14*10^6) -> 2.1979932e-05 | I15: =Segments!AN14/(Industry!I14*10^6) -> 3.9208101e-06 | J15: =Segments!AV14/(Industry!J14*10^6) -> 2.9261059e-05 | K15: =Segments!AX14/(Industry!K14*10^6) -> 3.4836055e-05 | M15: =((K15*K14)/(G15*G14))^(1/5)-1 -> 0.18016251
B16: Market Size (Micro Lending Market) | F16: 0.1 | G16: 0.11 | H16: =G16*(1+L16)^1 -> 0.12166 | I16: =G16*(1+L16)^2 -> 0.13455596 | J16: =G16*(1+L16)^3 -> 0.14881889 | K16: =G16*(1+L16)^4 -> 0.16459369 | L16: 0.106 | M16: =(K16/G16)^(1/5)-1 -> 0.083937151
B17: Market Share | F17: =Segments!AF14/(F16*10^6) -> 0.00525963 | G17: =Segments!AL14/(G16*(10^6)) -> 0.0065777556 | H17: =Segments!AR14/(H16*10^6) -> 0.0069909464 | I17: =Segments!AT14/(I16*10^6) -> 0.007508039 | J17: =Segments!AV14/(J16*10^6) -> 0.0087270678 | K17: =Segments!AX14/(K16*10^6) -> 0.0100639 | M17: =((K17*K16)/(G17*G16))^(1/5)-1 -> 0.18016251
A19: x
B21: Industry Driver | D21: Description | O21: Porter's Five Forces
B23: Government Policy | D23: OppFi’s model is highly sensitive to regulation. Interest rate caps and oversight of bank partnerships directly shape how it can lend and what margins it earns.
B24: Macroeconomic Trends | D24: Economic stress drives more customers to OppFi but also raises default risk, making growth closely tied to broader financial cycles.
B25: Consumer Behavior | D25: Borrowers increasingly expect fast, online credit. This shift supports OppFi’s digital installment loan model and helps it reach underbanked customers.
B26: Access to capital | D26: Dependence on bank partners and investors makes OppFi vulnerable to funding costs. Cheap capital fuels growth, but tighter markets compress margins.
B27: Technology | D27: Digital platforms and algorithms allow OppFi to approve and deliver loans quickly, giving it an edge in serving non-prime borrowers banks often overlook.
O28: Rivalry Among Existing Competitors | R28: 4
O29: Threat of New Entrants | R29: 4
O30: Threat of Substitutes | R30: 5
O31: Bargaining Power of Customers | R31: 4
O32: Bargaining Power of Suppliers | R32: 3

Sheet ESG
A7: x | B7: ESG Analysis
B12: ESG Scores | G12: GHG Scope 1 Emissions, Water Consumption, Energy Consumption and Waste Production per Sales | M12: ISS ESG Corporate Rating
B15: LSEG ESG Score | D15: 28
B16: E-Score | D16: 2
B17: S-Score | D17: 27
B18: G-Score | D18: 38
B19: S&P Global ESG Score | D19: N/A
B20: Environmental | D20: N/A
B21: Social | D21: N/A
B22: Governance & Economic | D22: N/A
B23: Sustainalytics | D23: Low/Average
B24: ISS ESG Corporate Rating | D24: D+
B25: SDG Impact Rating | D25: 2.8
B26: Governance Quality Score | D26: 9
B27: MSCI ESG Ratings | D27: N/A
B30: Key Info | G30: Environmental
H32: Overview | I32: Targets | J32: Improvements | K32: Comments
B33: GICS Sector | C33: Financials | G33: GHG Scope 1 Emissions | I33: - | J33: - | K33: -
B34: GICS Industry Group | C34: Financial Services
B35: GICS Industry | C35: Consumer Finance | G35: Water Consumption | I35: - | J35: - | K35: -
B36: GICS Sub-Industry | C36: Consumer Finance
G37: Energy Consumption | I37: - | J37: - | K37: -
B38: Headquarters | C38: Chicago
B39: Number of Employees | C39: 450 | G39: Waste Management | I39: - | J39: - | K39: -
B41: Annual Report | C41: 45727 | G41: Other | I41: - | J41: - | K41: -
B42: Sustainability Report | C42: N/A
B44: Recent Headlines | G44: Social
H46: Overview | I46: Targets | J46: Improvements | K46: Comments
G47: Employee Turnover % | I47: - | J47: - | K47: -
G49: Salaries & Compensation | I49: - | J49: - | K49: Good pay for high-end, engineering, data analyst jobs (~81k - ~160k). Lower level jobs pay way worse, at 16,5$/hour, such as entry level, remote jobs and customer service roles.
G51: Reputation | I51: - | J51: - | K51: Although their mission is to supposedly include people marginalized from the traditional credit system to give them na opportunity, OppFi is most of the times regarded as a predatory company whose goal is to take advantage of their customers to have very high interest on their loans.
G53: Discrimination Events | I53: - | J53: - | K53: -
G55: Work Safety | I55: - | J55: - | K55: -
G57: Damage to consumer health | I57: - | J57: - | K57: -
G59: Pension Plan | I59: - | J59: - | K59: Typical 401k pension plans that is competitive in the job market.
G61: Supply chain | I61: - | J61: - | K61: -
G63: Community involvement | I63: - | J63: - | K63: Just the nature of the business model is very predatory IMO.
G65: Public Sector | I65: - | J65: Not much room for improvement with the current business model, maybe try to get better at lobying. | K65: Because the company functions as a nonbank fintech lender, it bypasses bank regulations. This makes the relationship with the public sector more complicated, as they aren't well regarded by law-makers and public entities, having minimal chance for public partnerships and low trust.
G67: Litigation | I67: - | J67: See above | K67: Many ongoing litigation tied to lending practices regarding high interest rates and regulatory evasion.
B70: Board of Directors | G70: Governance
B72: Name | C72: Position | E72: M/F – Age | H72: Overview | I72: Targets | J72: Improvements | K72: Comments
B73: Todd Schwartz | C73: CEO/Executive Chairman | E73: M - 43 | G73: Diversity (Gender, Age, Industry, Region) | I73: - | J73: - | K73: 4 men, 2 women, msotly kind of old, but in a field where experience matters more so it's justified.
B74: Ted Schwartz | C74: Director | E74: M - 71
B75: David Vennettilli | C75: Director | E75: M - 37 | G75: % Independence | I75: - | J75: - | K75: All independent except CEO
B76: Jocelyn Moore | C76: Lead Ind. Director | E76: W - 48
B77: Greg Zeeman | C77: Ind. Director | E77: M - 56 | G77: Average time as independent directors | I77: - | J77: - | K77: 3 of the 5 members that aren't the CEO have been there for 4 years, in a 16 year old company that is ok.
B78: Christina Favilla | C78: Ind. Director | E78: W - 57
G79: Departures of C-level executives | I79: - | J79: - | K79: No departures reported in the last 3 years
G81: CEO/Chairman duality | I81: - | J81: - | K81: It is the founder of the company
G83: Transparency when reporting | I83: - | J83: - | K83: No ESG Report since 2020
G85: Time taken to report | I85: - | J85: - | K85: See above
G87: CEO or Chairman in other boards? | I87: - | J87: - | K87: Nothing besides his own "Schwartz Capital Group"
G89: Audit / Consulting | I89: - | J89: Report with more transparency | K89: Nothing unusul jumps to the eye, but also not much disclosure in terms of "audit vs non-audit services"
G91: ESG-compensation related | I91: - | J91: - | K91: No mention of anything ESG-related.
G93: Management compensation schemes | I93: - | J93: - | K93: Every compensation is basically determined by equity and stock performance-based pay. Very short sighted objectives, high incentive to boost stock.

Sheet Segments
A7: x | B7: Segments | D7: =F7 -> 2020 | E7: =F7 -> 2020 | F7: 2020 | G7: =F7 -> 2020 | H7: =F7 -> 2020 | J7: =L7 -> 2021 | K7: =L7 -> 2021 | L7: 2021 | M7: =L7 -> 2021 | N7: =L7 -> 2021 | P7: =R7 -> 2022 | Q7: =R7 -> 2022 | R7: 2022 | S7: =R7 -> 2022 | T7: =R7 -> 2022 | V7: =X7 -> 2023 | W7: =X7 -> 2023 | X7: 2023 | Y7: =X7 -> 2023 | Z7: =X7 -> 2023 | AB7: =AD7 -> 2024 | AC7: =AD7 -> 2024 | AD7: 2024 | AE7: =AD7 -> 2024 | AF7: =AD7 -> 2024 | AH7: =AJ7 -> 2025 | AI7: =AJ7 -> 2025 | AJ7: 2025 | AK7: =AJ7 -> 2025 | AL7: =AJ7 -> 2025 | AN7: =AP7 -> 2025 | AO7: =AP7 -> 2025 | AP7: 2025 | AQ7: =AP7 -> 2025 | AR7: =AP7 -> 2025 | AZ7: Products
D8: 2020 | J8: =D8+1 -> 2021 | P8: =J8+1 -> 2022 | V8: =P8+1 -> 2023 | AB8: =V8+1 -> 2024 | AH8: =AB8+1 -> 2025 | AN8: =AH8+1 -> 2026 | AT8: =AN8+1 -> 2027 | AV8: =+AT8+1 -> 2028 | AX8: =+AV8+1 -> 2029
D9: Q1 | E9: Q2 | F9: Q3 | G9: Q4 | H9: FY | J9: Q1 | K9: Q2 | L9: Q3 | M9: Q4 | N9: FY | P9: Q1 | Q9: Q2 | R9: Q3 | S9: Q4 | T9: FY | V9: Q1 | W9: Q2 | X9: Q3 | Y9: Q4 | Z9: FY | AB9: Q1 | AC9: Q2 | AD9: Q3 | AE9: Q4 | AF9: FY | AH9: Q1 | AI9: Q2 | AJ9: Q3 | AK9: Q4 | AL9: FY | AN9: Q1 | AO9: Q2 | AP9: Q3 | AQ9: Q4 | AR9: FY | AT9: FY | AV9: FY | AX9: FY
B12: Revenue by segment:
B13: Financial services
B14: Total revenue | D14: =IS!D18 -> 0 | E14: =IS!E18 -> 0 | F14: =IS!F18 -> 0 | G14: =IS!G18 -> 0 | H14: =IS!H18 -> 0 | J14: =IS!J18 -> 0 | K14: =IS!K18 -> 0 | L14: =IS!L18 -> 91.448 | M14: =IS!M18 -> 95.958 | N14: =IS!N18 -> 349.029 | P14: =IS!P18 -> 100.336 | Q14: =IS!Q18 -> 107.873 | R14: =IS!R18 -> 123.605 | S14: =IS!S18 -> 120.03 | T14: =IS!T18 -> 452.859 | V14: =IS!V18 -> 120.374 | W14: =IS!W18 -> 122.486 | X14: =IS!X18 -> 133.165 | Y14: =IS!Y18 -> 132.924 | Z14: =IS!Z18 -> 508.949 | AB14: =IS!AB18 -> 127.343 | AC14: =IS!AC18 -> 126.304 | AD14: =IS!AD18 -> 136.593 | AE14: =IS!AE18 -> 135.723 | AF14: =IS!AF18 -> 525.963 | AH14: =IS!AH18 -> 140.268 | AI14: =IS!AI18 -> 142.443 | AJ14: =IS!AJ18 -> 150.10346 | AK14: =IS!AK18 -> 156.13393 | AL14: =IS!AL18 -> 723.55312 | AN14: =IS!AN18 -> 162.48853 | AO14: =IS!AO18 -> 168.79837 | AP14: =IS!AP18 -> 176.86832 | AQ14: =IS!AQ18 -> 186.71815 | AR14: =IS!AR18 -> 850.51853 | AT14: =IS!AT18 -> 1010.2514 | AV14: =IS!AV18 -> 1298.7526 | AX14: =IS!AX18 -> 1656.4544
B16: Revenue by region:
B17: USA | H17: =H18 -> 0 | J17: =J18 -> 0 | K17: =K18 -> 0 | L17: =L18 -> 91.448 | M17: =M18 -> 95.958 | N17: =N18 -> 349.029 | P17: =P18 -> 100.336 | Q17: =Q18 -> 107.873 | R17: =R18 -> 123.605 | S17: =S18 -> 120.03 | T17: =T18 -> 452.859 | V17: =V18 -> 120.374 | W17: =W18 -> 122.486 | X17: =X18 -> 133.165 | Y17: =Y18 -> 132.924 | Z17: =Z18 -> 508.949 | AB17: =AB18 -> 127.343 | AC17: =AC18 -> 126.304 | AD17: =AD18 -> 136.593 | AE17: =AE18 -> 135.723 | AF17: =AF18 -> 525.963 | AL17: =AL18 -> 723.55312 | AN17: =AN18 -> 162.48853 | AO17: =AO18 -> 168.79837 | AP17: =AP18 -> 176.86832 | AQ17: =AQ18 -> 186.71815 | AR17: =AR18 -> 850.51853 | AT17: =AT18 -> 1010.2514 | AV17: =AV18 -> 1298.7526 | AX17: =AX18 -> 1656.4544
B18: Total revenue | D18: =IS!D18 -> 0 | E18: =IS!E18 -> 0 | F18: =IS!F18 -> 0 | G18: =IS!G18 -> 0 | H18: =IS!H18 -> 0 | J18: =IS!J18 -> 0 | K18: =IS!K18 -> 0 | L18: =IS!L18 -> 91.448 | M18: =IS!M18 -> 95.958 | N18: =IS!N18 -> 349.029 | P18: =IS!P18 -> 100.336 | Q18: =IS!Q18 -> 107.873 | R18: =IS!R18 -> 123.605 | S18: =IS!S18 -> 120.03 | T18: =IS!T18 -> 452.859 | V18: =IS!V18 -> 120.374 | W18: =IS!W18 -> 122.486 | X18: =IS!X18 -> 133.165 | Y18: =IS!Y18 -> 132.924 | Z18: =IS!Z18 -> 508.949 | AB18: =IS!AB18 -> 127.343 | AC18: =IS!AC18 -> 126.304 | AD18: =IS!AD18 -> 136.593 | AE18: =IS!AE18 -> 135.723 | AF18: =IS!AF18 -> 525.963 | AH18: =IS!AH18 -> 140.268 | AI18: =IS!AI18 -> 142.443 | AJ18: =IS!AJ18 -> 150.10346 | AK18: =IS!AK18 -> 156.13393 | AL18: =IS!AL18 -> 723.55312 | AN18: =IS!AN18 -> 162.48853 | AO18: =IS!AO18 -> 168.79837 | AP18: =IS!AP18 -> 176.86832 | AQ18: =IS!AQ18 -> 186.71815 | AR18: =IS!AR18 -> 850.51853 | AT18: =IS!AT18 -> 1010.2514 | AV18: =IS!AV18 -> 1298.7526 | AX18: =IS!AX18 -> 1656.4544
B20: Products:
B21: Opploans
B22: SalaryTap
B23: Oppfi Card
A25: x | B25: Notes & Forecasts
B30: Revenue | H30: Revenue is fully generated from financial services in the U.S., with OppLoans as the main product and other offerings like SalaryTap and the OppFi Card still immaterial.
B31: Growth | H31: Growth is primarily driven by higher loan originations, larger receivables, and stable yields, although charge-offs remain elevated.Forecasts reflect strong near-term expansion supported by management guidance, followed by more moderate growth as the business matures and credit risk stabilizes.
B32: Financial Inclusion | H32: OppFi places financial inclusion at the core of its mission. The company provides credit products through its OppLoans platform to consumers who are often underserved by traditional banking systems.
B33: Financial Health Surveys | H33: OppFi conducts semi-annual Financial Health Surveys to assess the well-being of its customers. The Spring 2025 survey indicated modest gains in financial health among respondents, despite ongoing economic challenges such as inflation and increased living costs.
B34: SalaryTap | H34: A payroll-deductible loan that allows consumers to access funds securely, with automatic repayments from their paycheck. Provides a safe, short-term cash solution between pay periods.
B35: OppCard | H35: A credit card for consumers with limited or poor credit history, designed to help responsibly build or improve credit while expanding access to revolving credit.
B36: Bitty Holdings | H36: OppFi holds a 35% stake in Bitty Holdings, a company that provides small businesses with revenue-based financing and other working capital solutions. This segment allows OppFi to expand beyond consumer lending, targeting small businesses that often struggle to access traditional credit.

Sheet Peers
B7: Peers
A12: x | B12: Growth | C12: OPPFI INC | D12: ENOVA INTERNATIO | E12: REGIONAL MANAGEM | F12: WORLD ACCEPTANCE | G12: EZCORP INC-A | H12: ONEMAIN HOLDINGS | I12: LENDINGCLUB CORP | J12: UPSTART HOLDINGS | K12: SOFI TECHNOLOGIE | L12: OPORTUN FINANCIA | M12: GREEN DOT CORP-A | N12: SYNCHRONY FINANC | O12: DISCOVER FINANCI | P12: CAPITAL ONE FINA | Q12: ALLY FINANCIAL I | R12: AFFIRM HOLDINGS
B14: Revenue (LTM) | C14: 0.067901781 | D14: 0.23418337 | E14: 0.073190377 | F14: 0.0077193326 | G14: 0.083064183 | H14: 0.09321879 | I14: 0.15904538 | J14: 0.60621769 | K14: 0.22595016 | L14: 0.22595016 | M14: 0.21783936 | N14: 0.21783936 | O14: -0.014687101 | P14: 0.088791107 | Q14: 0.096750129 | R14: -0.051558315
B15: Revenue (3-yr CAGR) | C15: 0.11947342 | D15: 0.25622651 | E15: 0.08815074 | F15: -0.023977107 | G15: 0.13381423 | H15: 0.06089953 | I15: 0.017755776 | J15: -0.073675667 | K15: 0.45917291 | L15: -0.044159498 | M15: 0.10373992 | N15: 0.11684866 | O15: 0.2100027 | P15: 0.18934416 | Q15: 0.12706483 | R15: 0.33694906
B16: Gross profit (LTM) | C16: #N/A | D16: 0.23541343 | E16: #N/A | F16: #N/A | G16: 0.084966065 | H16: #N/A | I16: #N/A | J16: #N/A | K16: #N/A | L16: #N/A | M16: #N/A | N16: #N/A | O16: #N/A | P16: #N/A | Q16: #N/A | R16: #N/A
B17: EBIT (LTM) | C17: 0.96601966 | D17: 0.33535563 | E17: 0.37996088 | F17: 0.0082506089 | G17: 0.2913342 | H17: 0.12823674 | I17: 0.70427297 | J17: -1.3924433 | K17: 3.1551344 | L17: 3.1551344 | M17: -1.2303798 | N17: -1.2303798 | O17: 0.4854641 | P17: 1.1523713 | Q17: -0.98610387 | R17: 0.42587421
B18: EBITDA (LTM) | C18: 0.758944 | D18: 0.31151631 | E18: 0.19649027 | F18: 0.051861299 | G18: 0.13305368 | H18: 0.11369863 | I18: 0.21994808 | J18: -1.667427 | K18: 0.2796766 | L18: 0.2796766 | M18: 0.76592956 | N18: 0.76592956 | O18: 0.1538255 | P18: 0.39953811 | Q18: -0.22781958 | R18: -0.0092804919
B19: FCF (LTM) | C19: 0.082328359 | D19: 0.33302129 | E19: 0.079349951 | F19: -0.036062258 | G19: 0.25230466 | H19: 0.071456927 | I19: -1.2476848 | J19: #VALUE! | K19: 0.82638636 | L19: 0.0033552845 | M19: -0.6711313 | N19: 0.14604911 | O19: -0.012469734 | P19: -0.13556643 | Q19: -0.40600667 | R19: 1.0688896
A21: x | B21: Margins | C21: OPPFI INC | D21: ENOVA INTERNATIO | E21: REGIONAL MANAGEM | F21: WORLD ACCEPTANCE | G21: EZCORP INC-A | H21: ONEMAIN HOLDINGS | I21: LENDINGCLUB CORP | J21: UPSTART HOLDINGS | K21: SOFI TECHNOLOGIE | L21: OPORTUN FINANCIA | M21: GREEN DOT CORP-A | N21: SYNCHRONY FINANC | O21: DISCOVER FINANCI | P21: CAPITAL ONE FINA | Q21: ALLY FINANCIAL I | R21: AFFIRM HOLDINGS
B23: Gross margin | C23: #VALUE! | D23: 0.57545677 | E23: #VALUE! | F23: #VALUE! | G23: 0.58735522 | H23: #VALUE! | I23: #VALUE! | J23: #VALUE! | K23: #VALUE! | L23: #VALUE! | M23: #VALUE! | N23: #VALUE! | O23: #VALUE! | P23: #VALUE! | Q23: #VALUE! | R23: #VALUE!
B24: EBIT margin | C24: 0.26474106 | D24: 0.2200158 | E24: 0.10520981 | F24: 0.21447719 | G24: 0.096874833 | H24: 0.14701345 | I24: 0.082674829 | J24: -0.27156072 | K24: 0.087236374 | L24: -0.3901607 | M24: -0.000967587 | N24: 0.28235659 | O24: 0.33914015 | P24: 0.15110452 | Q24: 0.093753505 | R24: -0.02706633
B25: EBITDA margin | C25: 0.30645356 | D25: 0.24088419 | E25: 0.22827795 | F25: 0.33684815 | G25: 0.20170403 | H25: 0.39859555 | I25: 0.42870633 | J25: -0.032314039 | K25: 0.39361319 | L25: 0.47388362 | M25: 0.088878249 | N25: 0.55709657 | O25: 0.5155911 | P25: 0.30627692 | Q25: 0.56113215 | R25: 0.033732972
B26: Net margin | C26: 0.01379945 | D26: 0.078805027 | E26: 0.080212385 | F26: 0.17187496 | G26: 0.071534829 | H26: 0.11218867 | I26: 0.065221452 | J26: -0.20200368 | K26: 0.18642665 | L26: -0.26653433 | M26: -0.015489513 | N26: 0.21252713 | O26: 0.24824121 | P26: 0.11364799 | Q26: 0.0625771 | R26: 0.016184656
B27: SG&A margin | C27: 0.12993062 | D27: 0.25069451 | E27: #VALUE! | F27: #VALUE! | G27: 0.065564789 | H27: #VALUE! | I27: #VALUE! | J27: 0.55907256 | K27: #VALUE! | L27: #VALUE! | M27: 0.27340666 | N27: #VALUE! | O27: #VALUE! | P27: #VALUE! | Q27: #VALUE! | R27: 0.30390037
B28: R&D margin | C28: 0.03181647 | D28: 0 | E28: #VALUE! | F28: #VALUE! | G28: 0 | H28: #VALUE! | I28: #VALUE! | J28: 0.30380644 | K28: #VALUE! | L28: #VALUE! | M28: #VALUE! | N28: #VALUE! | O28: #VALUE! | P28: #VALUE! | Q28: #VALUE! | R28: 0.18289319
A30: x | B30: Returns | C30: OPPFI INC | D30: ENOVA INTERNATIO | E30: REGIONAL MANAGEM | F30: WORLD ACCEPTANCE | G30: EZCORP INC-A | H30: ONEMAIN HOLDINGS | I30: LENDINGCLUB CORP | J30: UPSTART HOLDINGS | K30: SOFI TECHNOLOGIE | L30: OPORTUN FINANCIA | M30: GREEN DOT CORP-A | N30: SYNCHRONY FINANC | O30: DISCOVER FINANCI | P30: CAPITAL ONE FINA | Q30: ALLY FINANCIAL I | R30: AFFIRM HOLDINGS
B32: ROIC | C32: 0.27863713 | D32: 0.10934619 | E32: 0.13157101 | F32: 0.2396028 | G32: 0.06373359 | H32: 0.097710315 | I32: 0.17398179 | J32: -0.021888272 | K32: 0.058716681 | L32: -0.0027901529 | M32: 0.073094913 | N32: 0.21198824 | O32: 0.21951616 | P32: 0.12212293 | Q32: 0.063865048 | R32: 0.090657329
B33: CROIC | C33: 0.54885257 | D33: 0.31174745 | E33: 0.12810184 | F33: 0.241935 | G33: 0.060353901 | H33: 0.098088385 | I33: -1.8600427 | J33: 0.084549093 | K33: -0.13051477 | L33: 0.20602886 | M33: 0.0075504141 | N33: 0.24195966 | O33: 0.2043132 | P33: 0.12856385 | Q33: 0.030717018 | R33: 0.10206325
B34: ROCE | C34: 1.796604 | D34: 0.11344948 | E34: #VALUE! | F34: #VALUE! | G34: 0.092322839 | H34: #VALUE! | I34: #VALUE! | J34: -0.10103474 | K34: #VALUE! | L34: #VALUE! | M34: 0.0013573158 | N34: #VALUE! | O34: #VALUE! | P34: #VALUE! | Q34: #VALUE! | R34: -0.0089245239
B35: RONA | C35: 0.59451866 | D35: 0.48855046 | E35: 0.1514375 | F35: 0.25481309 | G35: 0.13986336 | H35: 0.20902538 | I35: 0.048494072 | J35: -0.27298024 | K35: 0.035760951 | L35: -0.3255344 | M35: -0.0019093734 | N35: 0.27460796 | O35: 0.33883744 | P35: 0.097229534 | Q35: 0.060130907 | R35: -0.028436867
B36: ROE | C36: -2.0949373 | D36: 0.21564244 | E36: 0.098110627 | F36: 0.19081034 | G36: 0.10952195 | H36: 0.20466121 | I36: 0.054956607 | J36: -0.0096497357 | K36: 0.088010303 | L36: -0.012633799 | M36: -0.026790884 | N36: 0.21359029 | O36: 0.2978683 | P36: -0.0037936793 | Q36: 0.040589474 | R36: 0.017992077
B37: ROA | C37: -0.053747068 | D37: 0.048606866 | E37: 0.018488982 | F37: 0.078300427 | G37: 0.057823944 | H37: 0.025641521 | I37: 0.0072712153 | J37: -0.0029561954 | K37: 0.015228892 | L37: -0.0014297568 | M37: -0.0043220238 | N37: 0.027278687 | O37: 0.03185597 | P37: 0 | Q37: 0.003099444 | R37: 0.0050483329
A39: x | B39: Efficiency | C39: OPPFI INC | D39: ENOVA INTERNATIO | E39: REGIONAL MANAGEM | F39: WORLD ACCEPTANCE | G39: EZCORP INC-A | H39: ONEMAIN HOLDINGS | I39: LENDINGCLUB CORP | J39: UPSTART HOLDINGS | K39: SOFI TECHNOLOGIE | L39: OPORTUN FINANCIA | M39: GREEN DOT CORP-A | N39: SYNCHRONY FINANC | O39: DISCOVER FINANCI | P39: CAPITAL ONE FINA | Q39: ALLY FINANCIAL I | R39: AFFIRM HOLDINGS
B41: Asset turnover | C41: 0.89055957 | D41: 0.55570145 | E41: 0.32563855 | F41: 0.54790663 | G41: 0.72616217 | H41: 0.23131514 | I41: 0.12263666 | J41: 0.3963461 | K41: 0.11290849 | L41: 0.19032164 | M41: 0.34732882 | N41: 0.19207947 | O41: 0.15639897 | P41: 0.10068078 | Q41: 0.081575062 | R41: 0.31192092
B42: Net operating asset turnover | C42: 2.1227444 | D42: 1.6683165 | E42: #VALUE! | F42: #VALUE! | G42: 1.5369538 | H42: #VALUE! | I42: #VALUE! | J42: 5.0482037 | K42: #VALUE! | L42: #VALUE! | M42: 0.45870262 | N42: #VALUE! | O42: #VALUE! | P42: #VALUE! | Q42: #VALUE! | R42: 0.52675299
B43: Fixed asset turnover | C43: 22.097223 | D43: 21.402802 | E43: 11.699487 | F43: 5.7707081 | G43: 4.1173013 | H43: #N/A N/A | I43: 5.5164573 | J43: 9.9952592 | K43: 10.934092 | L43: 45.782841 | M43: 9.9721808 | N43: #N/A N/A | O43: 21.497028 | P43: 11.373004 | Q43: 1.6388115 | R43: 6.4467481
B44: Revenue per employee thsnd of USD | C44: 1247.2517 | D44: 1639.0929 | E44: 286.99155 | F44: 200.05855 | G44: 164.26907 | H44: 664.55556 | I44: 1246.0339 | J44: 713.96982 | K44: 832.747 | L44: 265.53849 | M44: 1676.3626 | N44: 1157.25 | O44: 1119.381 | P44: 1090.057 | Q44: 1456.1682 | R44: 1461.6555
B45: EBIT per employee thsnd of USD | C45: 359.62697 | D45: 372.0873 | E45: 21.521821 | F45: 35.545235 | G45: 18.3856 | H45: 101.66667 | I45: 98.597804 | J45: 46.274099 | K45: 62.9694 | L45: 9.2902249 | M45: 86.307826 | N45: 212.05 | O45: 304.71429 | P45: 1.5209125 | Q45: 151.61363 | R45: 750.13146
A47: x | B47: Working Capital | C47: OPPFI INC | D47: ENOVA INTERNATIO | E47: REGIONAL MANAGEM | F47: WORLD ACCEPTANCE | G47: EZCORP INC-A | H47: ONEMAIN HOLDINGS | I47: LENDINGCLUB CORP | J47: UPSTART HOLDINGS | K47: SOFI TECHNOLOGIE | L47: OPORTUN FINANCIA | M47: GREEN DOT CORP-A | N47: SYNCHRONY FINANC | O47: DISCOVER FINANCI | P47: CAPITAL ONE FINA | Q47: ALLY FINANCIAL I | R47: AFFIRM HOLDINGS
B49: DSO | C49: #N/A N/A | D49: #N/A N/A | E49: #N/A N/A | F49: #N/A N/A | G49: 81.968855 | H49: #N/A N/A | I49: #N/A N/A | J49: #N/A N/A | K49: #N/A N/A | L49: #N/A N/A | M49: 7.6650649 | N49: #N/A N/A | O49: #N/A N/A | P49: #N/A N/A | Q49: #N/A N/A | R49: 44.102588
B50: DIO | C50: #N/A N/A | D50: #N/A N/A | E50: #N/A N/A | F50: #N/A N/A | G50: 142.45583 | H50: #N/A N/A | I50: #N/A N/A | J50: #N/A N/A | K50: #N/A N/A | L50: #N/A N/A | M50: #N/A N/A | N50: #N/A N/A | O50: #N/A N/A | P50: #N/A N/A | Q50: #N/A N/A | R50: #N/A N/A
B51: DPO | C51: #N/A N/A | D51: 86.492746 | E51: #N/A N/A | F51: #N/A N/A | G51: 12.070037 | H51: #N/A N/A | I51: #N/A N/A | J51: #N/A N/A | K51: #N/A N/A | L51: #N/A N/A | M51: #N/A N/A | N51: #N/A N/A | O51: #N/A N/A | P51: #N/A N/A | Q51: #N/A N/A | R51: #N/A N/A
B52: CCC | C52: #N/A N/A | D52: #N/A N/A | E52: #N/A N/A | F52: #N/A N/A | G52: 202.82374 | H52: #N/A N/A | I52: #N/A N/A | J52: #N/A N/A | K52: #N/A N/A | L52: #N/A N/A | M52: #N/A N/A | N52: #N/A N/A | O52: #N/A N/A | P52: #N/A N/A | Q52: #N/A N/A | R52: #N/A N/A
B53: Working capital intensity | C53: 0.091221688 | D53: 1.5406443 | E53: #N/A N/A | F53: #N/A N/A | G53: 0.55650973 | H53: #N/A N/A | I53: #N/A N/A | J53: 1.7243862 | K53: #N/A N/A | L53: #N/A N/A | M53: -0.94821448 | N53: #N/A N/A | O53: #N/A N/A | P53: #N/A N/A | Q53: #N/A N/A | R53: 2.6322636
B54: Cash conversion ratio | C54: 2.3254575 | D54: 2.6311329 | E54: 4.9732224 | F54: 2.2696142 | G54: 1.0409224 | H54: 4.0464768 | I54: -40.484646 | J54: -1.0779551 | K54: -4.7989329 | L54: -3.4166717 | M54: -48.790767 | N54: 2.1629695 | O54: 1.3870596 | P54: 3.0725888 | Q54: 5.4162679 | R54: -9.0968455
B55: CFO margin | C55: 0.61564407 | D55: 0.57889081 | E55: 0.45696793 | F55: 0.44997334 | G55: 0.10083919 | H55: 0.47168822 | I55: -2.2690244 | J55: 0.29273025 | K55: -0.29733113 | L55: 0.73781409 | M55: 0.047209312 | N55: 0.40751469 | O55: 0.35647796 | P55: 0.33666432 | Q55: 0.27628287 | R55: 0.24621823
A57: x | B57: Leverage & Coverage | C57: OPPFI INC | D57: ENOVA INTERNATIO | E57: REGIONAL MANAGEM | F57: WORLD ACCEPTANCE | G57: EZCORP INC-A | H57: ONEMAIN HOLDINGS | I57: LENDINGCLUB CORP | J57: UPSTART HOLDINGS | K57: SOFI TECHNOLOGIE | L57: OPORTUN FINANCIA | M57: GREEN DOT CORP-A | N57: SYNCHRONY FINANC | O57: DISCOVER FINANCI | P57: CAPITAL ONE FINA | Q57: ALLY FINANCIAL I | R57: AFFIRM HOLDINGS
B59: Net debt / EBITDA | C59: 1.6053442 | D59: 5.5850469 | E59: 11.050548 | F59: 2.8271658 | G59: 1.1669517 | H59: 8.9278523 | I59: -2.1390077 | J59: #N/A N/A | K59: 1.1663719 | L59: 2.9805829 | M59: 0.42831546 | N59: -0.2674112 | O59: 0.22054455 | P59: -0.36689255 | Q59: 1.0454078 | R59: 5.3496033
B60: Net debt / FCF | C60: 0.87101507 | D60: 2.3577558 | E60: 5.7172428 | F60: 2.059364 | G60: 4.8718708 | H60: 7.8332716 | I60: 0.52243576 | J60: 3.5316461 | K60: -0.51157862 | L60: 4.0097979 | M60: 4.9930947 | N60: 0.076259139 | O60: 0.95365943 | P60: 0.15075199 | Q60: 8.2659176 | R60: 0.9670129
B61: Interest coverage | C61: 3.1145209 | D61: 2.0133383 | E61: #VALUE! | F61: #VALUE! | G61: 8.2834008 | H61: #VALUE! | I61: #VALUE! | J61: -4.2751218 | K61: #VALUE! | L61: #VALUE! | M61: -0.30294224 | N61: #VALUE! | O61: #VALUE! | P61: #VALUE! | Q61: #VALUE! | R61: #VALUE!
B62: Debt / capital | C62: 0.58638976 | D62: 0.75043497 | E62: 0.80901396 | F62: 0.54459865 | G62: 0.41336976 | H62: 0.87128393 | I62: 0.020800842 | J62: 0.69639501 | K62: 0.32835928 | L62: 0.8220427 | M62: 0.063850239 | N62: 0.48255415 | O62: 0.47552591 | P62: 0.42963311 | Q62: 0.5789904 | R62: 0.47777194
B63: Short term debt / total debt | C63: 0.0074747329 | D63: 0.00096440295 | E63: 0 | F63: 0.04368782 | G63: 0.28586698 | H63: 0.0029166667 | I63: 0.47922953 | J63: 0 | K63: 0 | L63: 0.0070737213 | M63: 0.040548479 | N63: 0 | O63: 0 | P63: 0.0051325733 | Q63: 0.08498954 | R63: 0.0059033013
A65: x | B65: Liquidity | C65: OPPFI INC | D65: ENOVA INTERNATIO | E65: REGIONAL MANAGEM | F65: WORLD ACCEPTANCE | G65: EZCORP INC-A | H65: ONEMAIN HOLDINGS | I65: LENDINGCLUB CORP | J65: UPSTART HOLDINGS | K65: SOFI TECHNOLOGIE | L65: OPORTUN FINANCIA | M65: GREEN DOT CORP-A | N65: SYNCHRONY FINANC | O65: DISCOVER FINANCI | P65: CAPITAL ONE FINA | Q65: ALLY FINANCIAL I | R65: AFFIRM HOLDINGS
B67: Current ratio | C67: 2.4680756 | D67: 19.256527 | E67: #N/A N/A | F67: #N/A N/A | G67: 2.706237 | H67: #N/A N/A | I67: #N/A N/A | J67: 29.624034 | K67: #N/A N/A | L67: #N/A N/A | M67: 0.53929996 | N67: #N/A N/A | O67: #N/A N/A | P67: #N/A N/A | Q67: #N/A N/A | R67: 20.330683
B68: Quick ratio | C68: 1.7148608 | D68: 0.29567548 | E68: #N/A N/A | F68: #N/A N/A | G68: 1.6504638 | H68: #N/A N/A | I68: #N/A N/A | J68: 13.102588 | K68: #N/A N/A | L68: #N/A N/A | M68: 0.36690161 | N68: #N/A N/A | O68: #N/A N/A | P68: #N/A N/A | Q68: #N/A N/A | R68: 5.5685418
B69: Cash ratio | C69: 1.7148608 | D69: 0.29567548 | E69: #N/A N/A | F69: #N/A N/A | G69: 0.6329902 | H69: #N/A N/A | I69: #N/A N/A | J69: 13.102588 | K69: #N/A N/A | L69: #N/A N/A | M69: 0.35903351 | N69: #N/A N/A | O69: #N/A N/A | P69: #N/A N/A | Q69: #N/A N/A | R69: 4.6736951
A71: x | B71: Cash Deployment | C71: OPPFI INC | D71: ENOVA INTERNATIO | E71: REGIONAL MANAGEM | F71: WORLD ACCEPTANCE | G71: EZCORP INC-A | H71: ONEMAIN HOLDINGS | I71: LENDINGCLUB CORP | J71: UPSTART HOLDINGS | K71: SOFI TECHNOLOGIE | L71: OPORTUN FINANCIA | M71: GREEN DOT CORP-A | N71: SYNCHRONY FINANC | O71: DISCOVER FINANCI | P71: CAPITAL ONE FINA | Q71: ALLY FINANCIAL I | R71: AFFIRM HOLDINGS
B73: Capex intensity | C73: 0.02473558 | D73: 0.016337572 | E73: #VALUE! | F73: #VALUE! | G73: 0.030788514 | H73: #VALUE! | I73: #VALUE! | J73: 0.015694518 | K73: #VALUE! | L73: #VALUE! | M73: 0.043093007 | N73: #VALUE! | O73: #VALUE! | P73: #VALUE! | Q73: #VALUE! | R73: 0.059604356
B74: Capex / depreciation | C74: 1.3522503 | D74: 1.0799612 | E74: #VALUE! | F74: #VALUE! | G74: 1.0814963 | H74: #VALUE! | I74: #VALUE! | J74: 0.48615504 | K74: #VALUE! | L74: #VALUE! | M74: 0.87707057 | N74: #VALUE! | O74: #VALUE! | P74: #VALUE! | Q74: #VALUE! | R74: 0.85388491
B75: R&D capitalization rate | C75: #VALUE! | D75: #VALUE! | E75: #VALUE! | F75: #VALUE! | G75: #VALUE! | H75: #VALUE! | I75: #VALUE! | J75: #VALUE! | K75: #VALUE! | L75: #VALUE! | M75: #VALUE! | N75: #VALUE! | O75: #VALUE! | P75: #VALUE! | Q75: #VALUE! | R75: #VALUE!
B76: R&D capitalization test | C76: #VALUE! | D76: #VALUE! | E76: #VALUE! | F76: #VALUE! | G76: #VALUE! | H76: #VALUE! | I76: #VALUE! | J76: #VALUE! | K76: #VALUE! | L76: #VALUE! | M76: #VALUE! | N76: #VALUE! | O76: #VALUE! | P76: #VALUE! | Q76: #VALUE! | R76: #VALUE!
B77: Dividend payout | C77: 0 | D77: 0 | E77: 0.28059282 | F77: 0 | G77: 0 | H77: 0.978389 | I77: 0 | J77: #VALUE! | K77: 0 | L77: #VALUE! | M77: #VALUE! | N77: 0.11613656 | O77: 0.15924426 | P77: 0.2098154 | Q77: 0.65884723 | R77: 0
B78: FCF payout | C78: 0.011583161 | D78: 0.13703815 | E78: 0.043839271 | F78: 0.2069321 | G78: 0.11303921 | H78: 0.19595072 | I78: 0 | J78: -0.16501551 | K78: 0.016802033 | L78: #VALUE! | M78: -0.70405862 | N78: 0.14587446 | O78: 0.085202893 | P78: 0.078965802 | Q78: 0.37985901 | R78: #VALUE!
B79: Buybacks as % CFO | C79: 0.015089282 | D79: 0.18802581 | E79: 0.013163424 | F79: 0.21323102 | G79: 0.10251419 | H79: 0.012967766 | I79: 0 | J79: 0 | K79: 0 | L79: 0 | M79: 0 | N79: 0.10235581 | O79: 0.009851632 | P79: 0.040420728 | Q79: 0.0083922261 | R79: 0.69757491
A81: x | B81: Earnings Quality | C81: OPPFI INC | D81: ENOVA INTERNATIO | E81: REGIONAL MANAGEM | F81: WORLD ACCEPTANCE | G81: EZCORP INC-A | H81: ONEMAIN HOLDINGS | I81: LENDINGCLUB CORP | J81: UPSTART HOLDINGS | K81: SOFI TECHNOLOGIE | L81: OPORTUN FINANCIA | M81: GREEN DOT CORP-A | N81: SYNCHRONY FINANC | O81: DISCOVER FINANCI | P81: CAPITAL ONE FINA | Q81: ALLY FINANCIAL I | R81: AFFIRM HOLDINGS
B83: Cash/earnings conversion | C83: 11.20436 | D83: 19.356566 | E83: 18.388171 | F83: 32.689852 | G83: 5.1300749 | H83: 14.013499 | I83: -74.813235 | J83: 4.0659655 | K83: -11.108425 | L83: 31.271615 | M83: -32.683936 | N83: 12.086253 | O83: 9.6553747 | P83: 6.8755156 | Q83: 14.600564 | R83: 18.342282
B84: FCF / net income | C84: 10.754187 | D84: 18.810281 | E84: 18.042598 | F84: 32.216054 | G84: 3.5637455 | H84: 14.013499 | I84: -76.355467 | J84: 3.8479717 | K84: -12.638725 | L84: 31.201208 | M84: -2.8497992 | N84: 12.086253 | O84: 9.3482364 | P84: 6.4196469 | Q84: 3.4437727 | R84: 13.901994
A86: x | B86: Per Share & Dilution | C86: OPPFI INC | D86: ENOVA INTERNATIO | E86: REGIONAL MANAGEM | F86: WORLD ACCEPTANCE | G86: EZCORP INC-A | H86: ONEMAIN HOLDINGS | I86: LENDINGCLUB CORP | J86: UPSTART HOLDINGS | K86: SOFI TECHNOLOGIE | L86: OPORTUN FINANCIA | M86: GREEN DOT CORP-A | N86: SYNCHRONY FINANC | O86: DISCOVER FINANCI | P86: CAPITAL ONE FINA | Q86: ALLY FINANCIAL I | R86: AFFIRM HOLDINGS
B88: Diluted share count YoY | C88: 0 | D88: 0.047622585 | E88: 0.032883817 | F88: 0.015022073 | G88: 0.53723491 | H88: 0.0038501402 | I88: 0.012452493 | J88: #VALUE! | K88: 0.048724123 | L88: #VALUE! | M88: 0 | N88: 0.010340479 | O88: 0 | P88: 0.0023517115 | Q88: 0.010579545 | R88: 0.056284924
B89: SBC / revenue | C89: 0.010019716 | D89: 0.011970803 | E89: 0.018982061 | F89: -0.034857512 | G89: 0.0089583179 | H89: 0.0052429221 | I89: 0.03451463 | J89: 0.20957444 | K89: 0.065358273 | L89: 0.024353066 | M89: 0.017360877 | N89: #VALUE! | O89: #VALUE! | P89: 0.010549149 | Q89: #VALUE! | R89: 0.099687323
B90: SBC / CFO | C90: 0.016275177 | D90: 0.020678861 | E90: 0.041539154 | F90: -0.077465726 | G90: 0.088837666 | H90: 0.011115228 | I90: -0.01521122 | J90: 0.71593025 | K90: -0.21981645 | L90: 0.033007049 | M90: 0.36774265 | N90: #VALUE! | O90: #VALUE! | P90: 0.031334325 | Q90: #VALUE! | R90: 0.40487386
B91: EPS in USD | C91: -1.108228 | D91: 9.961823 | E91: 3.634958 | F91: 14.881312 | G91: 1.751297 | H91: 5.91427 | I91: 0.65 | J91: 0.239299 | K91: 0.514272 | L91: 0.127381 | M91: 0.929111 | N91: 8.31 | O91: 18.72 | P91: 3.030808 | Q91: 4.306464 | R91: 4.222697

Sheet Trading Comps
B7: ="in "&IF(Inputs!$R$18="k","thousands",IF(Inputs!$R$18="MLN","millions","billions")&" of "&Inputs!$R$17) -> in millions of usd | D7: Current | E7: % of | I7: Enterprise Value / | S7: LTM | T7: Net | V7: Price / | Z7: LT
D8: Share | E8: 52-week | F8: Equity | G8: Enterprise | I8: LTM | J8: 2025 | K8: 2026 | L8: LTM | M8: 2025E | N8: 2026E | O8: LTM | P8: 2025E | Q8: 2026E | S8: EBITDA | T8: Debt / | V8: LTM | W8: 2025E | X8: 2026E | Z8: EPS
B9: Company | C9: Ticker | D9: Price | E9: High | F9: Value | G9: Value | I9: Sales | J9: Sales | K9: Sales | L9: EBITDA | M9: EBITDA | N9: EBITDA | O9: EBIT | P9: EBIT | Q9: EBIT | S9: Margin | T9: EBITDA | V9: EPS | W9: EPS | X9: EPS | Z9: Growth
B12: Tier I: Fintech
N14: =G14/_xll.BQL(Inputs!$E20, "ebitda(fpr = 2026, fpt = a, ae = e, fa_adjusted = y, fs = mr)/1"&IF(Inputs!$R$18="BLN","b",IF(Inputs!$R$18="MLN","m","k"))) -> #NAME? | Q14: =G14/_xll.BQL(Inputs!$E20, "is_oper_inc(fpr = 2026, fpt = a, ae = e, fa_adjusted = y, fs = mr)/1"&IF(Inputs!$R$18="BLN","b",IF(Inputs!$R$18="MLN","m","k"))) -> #NAME?
B15: =+Inputs!B21 -> ENOVA INTERNATIO | C15: =+_xll.BDP(Inputs!E21,"TICKER_AND_EXCH_CODE") -> ENVA US | D15: =CONCATENATE(_xll.BDP(Inputs!E21,"CRNCY")," ",_xll.BDP(Inputs!E21,"PX_YEST_CLOSE")) -> USD 125,34 | E15: =_xll.BDP(Inputs!E21,"PX_YEST_CLOSE")/_xll.BDP(Inputs!E21,"HIGH_52WEEK") -> 0.96166461 | F15: =_xll.BDP(Inputs!$E21, "CUR_MKT_CAP", "SCALING_FORMAT=" & Inputs!$R$18) -> 3119.9483 | G15: =_xll.BDP(Inputs!$E21, "ENTERPRISE_VALUE", "SCALING_FORMAT=" & Inputs!$R$18) -> 6736.4175 | I15: =G15/_xll.BQL(Inputs!$E21, "sales_rev_turn(fpt = ltm, fa_adjusted = y, fs = mr)/1"&IF(Inputs!$R$18="BLN","b",IF(Inputs!$R$18="MLN","m","k"))) -> #NAME? | J15: =G15/_xll.BQL(Inputs!$E21, "sales_rev_turn(fpr = 2025, fpt = a, ae = e, fa_adjusted = y, fs = mr)/1"&IF(Inputs!$R$18="BLN","b",IF(Inputs!$R$18="MLN","m","k"))) -> #NAME? | K15: =G15/_xll.BQL(Inputs!$E21, "sales_rev_turn(fpr = 2026, fpt = a, ae = e, fa_adjusted = y, fs = mr)/1"&IF(Inputs!$R$18="BLN","b",IF(Inputs!$R$18="MLN","m","k"))) -> #NAME? | L15: =G15/_xll.BQL(Inputs!$E21, "ebitda(fpt = ltm, fa_adjusted = y, fs = mr)/1"&IF(Inputs!$R$18="BLN","b",IF(Inputs!$R$18="MLN","m","k"))) -> #NAME? | M15: =G15/_xll.BQL(Inputs!$E21, "ebitda(fpr = 2025, fpt = a, ae = e, fa_adjusted = y, fs = mr)/1"&IF(Inputs!$R$18="BLN","b",IF(Inputs!$R$18="MLN","m","k"))) -> #NAME? | N15: =G15/_xll.BQL(Inputs!$E21, "ebitda(fpr = 2026, fpt = a, ae = e, fa_adjusted = y, fs = mr)/1"&IF(Inputs!$R$18="BLN","b",IF(Inputs!$R$18="MLN","m","k"))) -> #NAME? | O15: =G15/_xll.BQL(Inputs!$E21, "is_oper_inc(fpt = ltm, fa_adjusted = y, fs = mr)/1"&IF(Inputs!$R$18="BLN","b",IF(Inputs!$R$18="MLN","m","k"))) -> #NAME? | P15: =G15/_xll.BQL(Inputs!$E21, "is_oper_inc(fpr = 2025, fpt = a, ae = e, fa_adjusted = y, fs = mr)/1"&IF(Inputs!$R$18="BLN","b",IF(Inputs!$R$18="MLN","m","k"))) -> #NAME? | Q15: =G15/_xll.BQL(Inputs!$E21, "is_oper_inc(fpr = 2026, fpt = a, ae = e, fa_adjusted = y, fs = mr)/1"&IF(Inputs!$R$18="BLN","b",IF(Inputs!$R$18="MLN","m","k"))) -> #NAME? | R15: is_oper_inc(fpr=2026,fpt=a,ae=e,fa_adjusted=y,fs=mr)/1m | S15: =_xll.BQL(Inputs!$E21, "ebitda(fpt = ltm, fa_adjusted = y, fs = mr)/1"&IF(Inputs!$R$18="BLN","b",IF(Inputs!$R$18="MLN","m","k")))/_xll.BQL(Inputs!$E21, "sales_rev_turn(fpt = ltm, fa_adjusted = y, fs = mr)/1"&IF(Inputs!$R$18="BLN","b",IF(Inputs!$R$18="MLN","m","k"))) -> #NAME? | T15: =_xll.BDP(Inputs!$E21,"TOT_DEBT_TO_EBITDA") -> #NAME? | V15: =F15/_xll.BQL(Inputs!$E21, "earn_for_common(fpt = ltm, fa_adjusted = y, fs = mr)/1"&IF(Inputs!$R$18="BLN","b",IF(Inputs!$R$18="MLN","m","k"))) -> #NAME? | W15: =F15/_xll.BQL(Inputs!$E21, "EARN_FOR_COMMON(fpr = 2025, fpt = a, ae = e, fa_adjusted = y, fs = mr)/1"&IF(Inputs!$R$18="BLN","b",IF(Inputs!$R$18="MLN","m","k"))) -> #NAME? | X15: =F15/_xll.BQL(Inputs!$E21, "EARN_FOR_COMMON(fpr = 2026, fpt = a, ae = e, fa_adjusted = y, fs = mr)/1"&IF(Inputs!$R$18="BLN","b",IF(Inputs!$R$18="MLN","m","k"))) -> #NAME? | Y15: EARN_FOR_COMMON(fpr=2026,fpt=a,ae=e,fa_adjusted=y,fs=mr)/1m | Z15: =(_xll.BQL(Inputs!$E21, "EARN_FOR_COMMON(fpr = 2028, fpt = a, ae = e, fa_adjusted = y, fs = mr)")/_xll.BQL(Inputs!$E21, "EARN_FOR_COMMON(fpr = 2025, fpt = a, ae = e, fa_adjusted = y, fs = mr)"))^(1/3)-1 -> #NAME? | AA15: EARN_FOR_COMMON(fpr=2028,fpt=a,ae=e,fa_adjusted=y,fs=mr)
B16: =+Inputs!B22 -> REGIONAL MANAGEM | C16: =+_xll.BDP(Inputs!E22,"TICKER_AND_EXCH_CODE") -> RM US | D16: =CONCATENATE(_xll.BDP(Inputs!E22,"CRNCY")," ",_xll.BDP(Inputs!E22,"PX_YEST_CLOSE")) -> USD 43,46 | E16: =_xll.BDP(Inputs!E22,"PX_YEST_CLOSE")/_xll.BDP(Inputs!E22,"HIGH_52WEEK") -> 0.94478261 | F16: =_xll.BDP(Inputs!$E22, "CUR_MKT_CAP", "SCALING_FORMAT=" & Inputs!$R$18) -> 422.92769 | G16: =_xll.BDP(Inputs!$E22, "ENTERPRISE_VALUE", "SCALING_FORMAT=" & Inputs!$R$18) -> 1833.757 | I16: =G16/_xll.BQL(Inputs!$E22, "sales_rev_turn(fpt = ltm, fa_adjusted = y, fs = mr)/1"&IF(Inputs!$R$18="BLN","b",IF(Inputs!$R$18="MLN","m","k"))) -> #NAME? | J16: =G16/_xll.BQL(Inputs!$E22, "sales_rev_turn(fpr = 2025, fpt = a, ae = e, fa_adjusted = y, fs = mr)/1"&IF(Inputs!$R$18="BLN","b",IF(Inputs!$R$18="MLN","m","k"))) -> #NAME? | K16: =G16/_xll.BQL(Inputs!$E22, "sales_rev_turn(fpr = 2026, fpt = a, ae = e, fa_adjusted = y, fs = mr)/1"&IF(Inputs!$R$18="BLN","b",IF(Inputs!$R$18="MLN","m","k"))) -> #NAME? | L16: =G16/_xll.BQL(Inputs!$E22, "ebitda(fpt = ltm, fa_adjusted = y, fs = mr)/1"&IF(Inputs!$R$18="BLN","b",IF(Inputs!$R$18="MLN","m","k"))) -> #NAME? | M16: =G16/_xll.BQL(Inputs!$E22, "ebitda(fpr = 2025, fpt = a, ae = e, fa_adjusted = y, fs = mr)/1"&IF(Inputs!$R$18="BLN","b",IF(Inputs!$R$18="MLN","m","k"))) -> #NAME? | N16: =G16/_xll.BQL(Inputs!$E22, "ebitda(fpr = 2026, fpt = a, ae = e, fa_adjusted = y, fs = mr)/1"&IF(Inputs!$R$18="BLN","b",IF(Inputs!$R$18="MLN","m","k"))) -> #NAME? | O16: =G16/_xll.BQL(Inputs!$E22, "is_oper_inc(fpt = ltm, fa_adjusted = y, fs = mr)/1"&IF(Inputs!$R$18="BLN","b",IF(Inputs!$R$18="MLN","m","k"))) -> #NAME? | P16: =G16/_xll.BQL(Inputs!$E22, "is_oper_inc(fpr = 2025, fpt = a, ae = e, fa_adjusted = y, fs = mr)/1"&IF(Inputs!$R$18="BLN","b",IF(Inputs!$R$18="MLN","m","k"))) -> #NAME? | Q16: =G16/_xll.BQL(Inputs!$E22, "is_oper_inc(fpr = 2026, fpt = a, ae = e, fa_adjusted = y, fs = mr)/1"&IF(Inputs!$R$18="BLN","b",IF(Inputs!$R$18="MLN","m","k"))) -> #NAME? | R16: #N/A | S16: =_xll.BQL(Inputs!$E22, "ebitda(fpt = ltm, fa_adjusted = y, fs = mr)/1"&IF(Inputs!$R$18="BLN","b",IF(Inputs!$R$18="MLN","m","k")))/_xll.BQL(Inputs!$E22, "sales_rev_turn(fpt = ltm, fa_adjusted = y, fs = mr)/1"&IF(Inputs!$R$18="BLN","b",IF(Inputs!$R$18="MLN","m","k"))) -> #NAME? | T16: =_xll.BDP(Inputs!$E22,"TOT_DEBT_TO_EBITDA") -> #NAME? | V16: =F16/_xll.BQL(Inputs!$E22, "earn_for_common(fpt = ltm, fa_adjusted = y, fs = mr)/1"&IF(Inputs!$R$18="BLN","b",IF(Inputs!$R$18="MLN","m","k"))) -> #NAME? | W16: =F16/_xll.BQL(Inputs!$E22, "EARN_FOR_COMMON(fpr = 2025, fpt = a, ae = e, fa_adjusted = y, fs = mr)/1"&IF(Inputs!$R$18="BLN","b",IF(Inputs!$R$18="MLN","m","k"))) -> #NAME? | X16: =F16/_xll.BQL(Inputs!$E22, "EARN_FOR_COMMON(fpr = 2026, fpt = a, ae = e, fa_adjusted = y, fs = mr)/1"&IF(Inputs!$R$18="BLN","b",IF(Inputs!$R$18="MLN","m","k"))) -> #NAME? | Y16: #N/A | Z16: =(_xll.BQL(Inputs!$E22, "EARN_FOR_COMMON(fpr = 2028, fpt = a, ae = e, fa_adjusted = y, fs = mr)")/_xll.BQL(Inputs!$E22, "EARN_FOR_COMMON(fpr = 2025, fpt = a, ae = e, fa_adjusted = y, fs = mr)"))^(1/3)-1 -> #NAME? | AA16: #N/A
B17: =+Inputs!B23 -> WORLD ACCEPTANCE | C17: =+_xll.BDP(Inputs!E23,"TICKER_AND_EXCH_CODE") -> WRLD US | D17: =CONCATENATE(_xll.BDP(Inputs!E23,"CRNCY")," ",_xll.BDP(Inputs!E23,"PX_YEST_CLOSE")) -> USD 175,41 | E17: =_xll.BDP(Inputs!E23,"PX_YEST_CLOSE")/_xll.BDP(Inputs!E23,"HIGH_52WEEK") -> 0.9831848 | F17: =_xll.BDP(Inputs!$E23, "CUR_MKT_CAP", "SCALING_FORMAT=" & Inputs!$R$18) -> 964.12231 | G17: =_xll.BDP(Inputs!$E23, "ENTERPRISE_VALUE", "SCALING_FORMAT=" & Inputs!$R$18) -> 1439.4902 | I17: =G17/_xll.BQL(Inputs!$E23, "sales_rev_turn(fpt = ltm, fa_adjusted = y, fs = mr)/1"&IF(Inputs!$R$18="BLN","b",IF(Inputs!$R$18="MLN","m","k"))) -> #NAME? | J17: =G17/_xll.BQL(Inputs!$E23, "sales_rev_turn(fpr = 2025, fpt = a, ae = e, fa_adjusted = y, fs = mr)/1"&IF(Inputs!$R$18="BLN","b",IF(Inputs!$R$18="MLN","m","k"))) -> #NAME? | K17: =G17/_xll.BQL(Inputs!$E23, "sales_rev_turn(fpr = 2026, fpt = a, ae = e, fa_adjusted = y, fs = mr)/1"&IF(Inputs!$R$18="BLN","b",IF(Inputs!$R$18="MLN","m","k"))) -> #NAME? | L17: =G17/_xll.BQL(Inputs!$E23, "ebitda(fpt = ltm, fa_adjusted = y, fs = mr)/1"&IF(Inputs!$R$18="BLN","b",IF(Inputs!$R$18="MLN","m","k"))) -> #NAME? | M17: =G17/_xll.BQL(Inputs!$E23, "ebitda(fpr = 2025, fpt = a, ae = e, fa_adjusted = y, fs = mr)/1"&IF(Inputs!$R$18="BLN","b",IF(Inputs!$R$18="MLN","m","k"))) -> #NAME? | N17: =G17/_xll.BQL(Inputs!$E23, "ebitda(fpr = 2026, fpt = a, ae = e, fa_adjusted = y, fs = mr)/1"&IF(Inputs!$R$18="BLN","b",IF(Inputs!$R$18="MLN","m","k"))) -> #NAME? | O17: =G17/_xll.BQL(Inputs!$E23, "is_oper_inc(fpt = ltm, fa_adjusted = y, fs = mr)/1"&IF(Inputs!$R$18="BLN","b",IF(Inputs!$R$18="MLN","m","k"))) -> #NAME? | P17: =G17/_xll.BQL(Inputs!$E23, "is_oper_inc(fpr = 2025, fpt = a, ae = e, fa_adjusted = y, fs = mr)/1"&IF(Inputs!$R$18="BLN","b",IF(Inputs!$R$18="MLN","m","k"))) -> #NAME? | Q17: =G17/_xll.BQL(Inputs!$E23, "is_oper_inc(fpr = 2026, fpt = a, ae = e, fa_adjusted = y, fs = mr)/1"&IF(Inputs!$R$18="BLN","b",IF(Inputs!$R$18="MLN","m","k"))) -> #NAME? | R17: #N/A | S17: =_xll.BQL(Inputs!$E23, "ebitda(fpt = ltm, fa_adjusted = y, fs = mr)/1"&IF(Inputs!$R$18="BLN","b",IF(Inputs!$R$18="MLN","m","k")))/_xll.BQL(Inputs!$E23, "sales_rev_turn(fpt = ltm, fa_adjusted = y, fs = mr)/1"&IF(Inputs!$R$18="BLN","b",IF(Inputs!$R$18="MLN","m","k"))) -> #NAME? | T17: =_xll.BDP(Inputs!$E23,"TOT_DEBT_TO_EBITDA") -> #NAME? | V17: =F17/_xll.BQL(Inputs!$E23, "earn_for_common(fpt = ltm, fa_adjusted = y, fs = mr)/1"&IF(Inputs!$R$18="BLN","b",IF(Inputs!$R$18="MLN","m","k"))) -> #NAME? | W17: =F17/_xll.BQL(Inputs!$E23, "EARN_FOR_COMMON(fpr = 2025, fpt = a, ae = e, fa_adjusted = y, fs = mr)/1"&IF(Inputs!$R$18="BLN","b",IF(Inputs!$R$18="MLN","m","k"))) -> #NAME? | X17: =F17/_xll.BQL(Inputs!$E23, "EARN_FOR_COMMON(fpr = 2026, fpt = a, ae = e, fa_adjusted = y, fs = mr)/1"&IF(Inputs!$R$18="BLN","b",IF(Inputs!$R$18="MLN","m","k"))) -> #NAME? | Y17: #N/A | Z17: =(_xll.BQL(Inputs!$E23, "EARN_FOR_COMMON(fpr = 2028, fpt = a, ae = e, fa_adjusted = y, fs = mr)")/_xll.BQL(Inputs!$E23, "EARN_FOR_COMMON(fpr = 2025, fpt = a, ae = e, fa_adjusted = y, fs = mr)"))^(1/3)-1 -> #NAME? | AA17: #N/A
B18: =+Inputs!B24 -> EZCORP INC-A | C18: =+_xll.BDP(Inputs!E24,"TICKER_AND_EXCH_CODE") -> EZPW US | D18: =CONCATENATE(_xll.BDP(Inputs!E24,"CRNCY")," ",_xll.BDP(Inputs!E24,"PX_YEST_CLOSE")) -> USD 17,96 | E18: =_xll.BDP(Inputs!E24,"PX_YEST_CLOSE")/_xll.BDP(Inputs!E24,"HIGH_52WEEK") -> 0.97874659 | F18: =_xll.BDP(Inputs!$E24, "CUR_MKT_CAP", "SCALING_FORMAT=" & Inputs!$R$18) -> 1107.0918 | G18: =_xll.BDP(Inputs!$E24, "ENTERPRISE_VALUE", "SCALING_FORMAT=" & Inputs!$R$18) -> 1136.1593 | I18: =G18/_xll.BQL(Inputs!$E24, "sales_rev_turn(fpt = ltm, fa_adjusted = y, fs = mr)/1"&IF(Inputs!$R$18="BLN","b",IF(Inputs!$R$18="MLN","m","k"))) -> 0.92219377 | J18: =G18/_xll.BQL(Inputs!$E24, "sales_rev_turn(fpr = 2025, fpt = a, ae = e, fa_adjusted = y, fs = mr)/1"&IF(Inputs!$R$18="BLN","b",IF(Inputs!$R$18="MLN","m","k"))) -> 0.90762049 | K18: =G18/_xll.BQL(Inputs!$E24, "sales_rev_turn(fpr = 2026, fpt = a, ae = e, fa_adjusted = y, fs = mr)/1"&IF(Inputs!$R$18="BLN","b",IF(Inputs!$R$18="MLN","m","k"))) -> 0.85361332 | L18: =G18/_xll.BQL(Inputs!$E24, "ebitda(fpt = ltm, fa_adjusted = y, fs = mr)/1"&IF(Inputs!$R$18="BLN","b",IF(Inputs!$R$18="MLN","m","k"))) -> 4.5775222 | M18: =G18/_xll.BQL(Inputs!$E24, "ebitda(fpr = 2025, fpt = a, ae = e, fa_adjusted = y, fs = mr)/1"&IF(Inputs!$R$18="BLN","b",IF(Inputs!$R$18="MLN","m","k"))) -> 6.1248481 | N18: =G18/_xll.BQL(Inputs!$E24, "ebitda(fpr = 2026, fpt = a, ae = e, fa_adjusted = y, fs = mr)/1"&IF(Inputs!$R$18="BLN","b",IF(Inputs!$R$18="MLN","m","k"))) -> 5.4940006 | O18: =G18/_xll.BQL(Inputs!$E24, "is_oper_inc(fpt = ltm, fa_adjusted = y, fs = mr)/1"&IF(Inputs!$R$18="BLN","b",IF(Inputs!$R$18="MLN","m","k"))) -> 8.2394869 | P18: =G18/_xll.BQL(Inputs!$E24, "is_oper_inc(fpr = 2025, fpt = a, ae = e, fa_adjusted = y, fs = mr)/1"&IF(Inputs!$R$18="BLN","b",IF(Inputs!$R$18="MLN","m","k"))) -> 7.7080009 | Q18: =G18/_xll.BQL(Inputs!$E24, "is_oper_inc(fpr = 2026, fpt = a, ae = e, fa_adjusted = y, fs = mr)/1"&IF(Inputs!$R$18="BLN","b",IF(Inputs!$R$18="MLN","m","k"))) -> 6.6911621 | S18: =_xll.BQL(Inputs!$E24, "ebitda(fpt = ltm, fa_adjusted = y, fs = mr)/1"&IF(Inputs!$R$18="BLN","b",IF(Inputs!$R$18="MLN","m","k")))/_xll.BQL(Inputs!$E24, "sales_rev_turn(fpt = ltm, fa_adjusted = y, fs = mr)/1"&IF(Inputs!$R$18="BLN","b",IF(Inputs!$R$18="MLN","m","k"))) -> 0.20146134 | T18: =_xll.BDP(Inputs!$E24,"TOT_DEBT_TO_EBITDA") -> 3.0666793 | V18: =F18/_xll.BQL(Inputs!$E24, "earn_for_common(fpt = ltm, fa_adjusted = y, fs = mr)/1"&IF(Inputs!$R$18="BLN","b",IF(Inputs!$R$18="MLN","m","k"))) -> 11.30888 | W18: =F18/_xll.BQL(Inputs!$E24, "EARN_FOR_COMMON(fpr = 2025, fpt = a, ae = e, fa_adjusted = y, fs = mr)/1"&IF(Inputs!$R$18="BLN","b",IF(Inputs!$R$18="MLN","m","k"))) -> 10.330561 | X18: =F18/_xll.BQL(Inputs!$E24, "EARN_FOR_COMMON(fpr = 2026, fpt = a, ae = e, fa_adjusted = y, fs = mr)/1"&IF(Inputs!$R$18="BLN","b",IF(Inputs!$R$18="MLN","m","k"))) -> 9.8262582 | Z18: =(_xll.BQL(Inputs!$E24, "EARN_FOR_COMMON(fpr = 2028, fpt = a, ae = e, fa_adjusted = y, fs = mr)")/_xll.BQL(Inputs!$E24, "EARN_FOR_COMMON(fpr = 2025, fpt = a, ae = e, fa_adjusted = y, fs = mr)"))^(1/3)-1 -> 0.093174362
B19: =+Inputs!B25 -> ONEMAIN HOLDINGS | C19: =+_xll.BDP(Inputs!E25,"TICKER_AND_EXCH_CODE") -> OMF US | D19: =CONCATENATE(_xll.BDP(Inputs!E25,"CRNCY")," ",_xll.BDP(Inputs!E25,"PX_YEST_CLOSE")) -> USD 60,41 | E19: =_xll.BDP(Inputs!E25,"PX_YEST_CLOSE")/_xll.BDP(Inputs!E25,"HIGH_52WEEK") -> 0.95517432 | F19: =_xll.BDP(Inputs!$E25, "CUR_MKT_CAP", "SCALING_FORMAT=" & Inputs!$R$18) -> 7198.9738 | G19: =_xll.BDP(Inputs!$E25, "ENTERPRISE_VALUE", "SCALING_FORMAT=" & Inputs!$R$18) -> 28058.848 | I19: =G19/_xll.BQL(Inputs!$E25, "sales_rev_turn(fpt = ltm, fa_adjusted = y, fs = mr)/1"&IF(Inputs!$R$18="BLN","b",IF(Inputs!$R$18="MLN","m","k"))) -> 4.6913306 | J19: =G19/_xll.BQL(Inputs!$E25, "sales_rev_turn(fpr = 2025, fpt = a, ae = e, fa_adjusted = y, fs = mr)/1"&IF(Inputs!$R$18="BLN","b",IF(Inputs!$R$18="MLN","m","k"))) -> 5.6728951 | K19: =G19/_xll.BQL(Inputs!$E25, "sales_rev_turn(fpr = 2026, fpt = a, ae = e, fa_adjusted = y, fs = mr)/1"&IF(Inputs!$R$18="BLN","b",IF(Inputs!$R$18="MLN","m","k"))) -> 5.354888 | L19: =G19/_xll.BQL(Inputs!$E25, "ebitda(fpt = ltm, fa_adjusted = y, fs = mr)/1"&IF(Inputs!$R$18="BLN","b",IF(Inputs!$R$18="MLN","m","k"))) -> 11.504243 | M19: =G19/_xll.BQL(Inputs!$E25, "ebitda(fpr = 2025, fpt = a, ae = e, fa_adjusted = y, fs = mr)/1"&IF(Inputs!$R$18="BLN","b",IF(Inputs!$R$18="MLN","m","k"))) -> 11.39677 | N19: =G19/_xll.BQL(Inputs!$E25, "ebitda(fpr = 2026, fpt = a, ae = e, fa_adjusted = y, fs = mr)/1"&IF(Inputs!$R$18="BLN","b",IF(Inputs!$R$18="MLN","m","k"))) -> 10.181004 | O19: =G19/_xll.BQL(Inputs!$E25, "is_oper_inc(fpt = ltm, fa_adjusted = y, fs = mr)/1"&IF(Inputs!$R$18="BLN","b",IF(Inputs!$R$18="MLN","m","k"))) -> 30.665408 | P19: =G19/_xll.BQL(Inputs!$E25, "is_oper_inc(fpr = 2025, fpt = a, ae = e, fa_adjusted = y, fs = mr)/1"&IF(Inputs!$R$18="BLN","b",IF(Inputs!$R$18="MLN","m","k"))) -> 35.528773 | Q19: =G19/_xll.BQL(Inputs!$E25, "is_oper_inc(fpr = 2026, fpt = a, ae = e, fa_adjusted = y, fs = mr)/1"&IF(Inputs!$R$18="BLN","b",IF(Inputs!$R$18="MLN","m","k"))) -> 31.464927 | S19: =_xll.BQL(Inputs!$E25, "ebitda(fpt = ltm, fa_adjusted = y, fs = mr)/1"&IF(Inputs!$R$18="BLN","b",IF(Inputs!$R$18="MLN","m","k")))/_xll.BQL(Inputs!$E25, "sales_rev_turn(fpt = ltm, fa_adjusted = y, fs = mr)/1"&IF(Inputs!$R$18="BLN","b",IF(Inputs!$R$18="MLN","m","k"))) -> 0.40779134 | T19: =_xll.BDP(Inputs!$E25,"TOT_DEBT_TO_EBITDA") -> 9.2504195 | V19: =F19/_xll.BQL(Inputs!$E25, "earn_for_common(fpt = ltm, fa_adjusted = y, fs = mr)/1"&IF(Inputs!$R$18="BLN","b",IF(Inputs!$R$18="MLN","m","k"))) -> 10.190352 | W19: =F19/_xll.BQL(Inputs!$E25, "EARN_FOR_COMMON(fpr = 2025, fpt = a, ae = e, fa_adjusted = y, fs = mr)/1"&IF(Inputs!$R$18="BLN","b",IF(Inputs!$R$18="MLN","m","k"))) -> 9.4516068 | X19: =F19/_xll.BQL(Inputs!$E25, "EARN_FOR_COMMON(fpr = 2026, fpt = a, ae = e, fa_adjusted = y, fs = mr)/1"&IF(Inputs!$R$18="BLN","b",IF(Inputs!$R$18="MLN","m","k"))) -> 7.5842539 | Z19: =(_xll.BQL(Inputs!$E25, "EARN_FOR_COMMON(fpr = 2028, fpt = a, ae = e, fa_adjusted = y, fs = mr)")/_xll.BQL(Inputs!$E25, "EARN_FOR_COMMON(fpr = 2025, fpt = a, ae = e, fa_adjusted = y, fs = mr)"))^(1/3)-1 -> 0.19812496
B21: Mean | I21: =AVERAGE(I15:I19) -> #NAME? | J21: =AVERAGE(J15:J19) -> #NAME? | K21: =AVERAGE(K15:K19) -> #NAME? | L21: =AVERAGE(L15:L19) -> #NAME? | M21: =AVERAGE(M15:M19) -> #NAME? | N21: =AVERAGE(N15:N19) -> #NAME? | O21: =AVERAGE(O15:O19) -> #NAME? | P21: =AVERAGE(P15:P19) -> #NAME? | Q21: =AVERAGE(Q15:Q19) -> #NAME? | S21: =AVERAGE(S15:S19) -> #NAME? | T21: =AVERAGE(T15:T19) -> #NAME? | V21: =AVERAGE(V15:V19) -> #NAME? | W21: =AVERAGE(W15:W19) -> #NAME? | X21: =AVERAGE(X15:X19) -> #NAME? | Z21: =AVERAGE(Z15:Z19) -> #NAME?
B22: Median | I22: =MEDIAN(I15:I19) -> #NAME? | J22: =MEDIAN(J15:J19) -> #NAME? | K22: =MEDIAN(K15:K19) -> #NAME? | L22: =MEDIAN(L15:L19) -> #NAME? | M22: =MEDIAN(M15:M19) -> #NAME? | N22: =MEDIAN(N15:N19) -> #NAME? | O22: =MEDIAN(O15:O19) -> #NAME? | P22: =MEDIAN(P15:P19) -> #NAME? | Q22: =MEDIAN(Q15:Q19) -> #NAME? | S22: =MEDIAN(S15:S19) -> #NAME? | T22: =MEDIAN(T15:T19) -> #NAME? | V22: =MEDIAN(V15:V19) -> #NAME? | W22: =MEDIAN(W15:W19) -> #NAME? | X22: =MEDIAN(X15:X19) -> #NAME? | Z22: =MEDIAN(Z15:Z19) -> #NAME?
B24: Tier II: Other Fintech and Credit
B27: =+Inputs!H21 -> LENDINGCLUB CORP | C27: =+_xll.BDP(Inputs!K21,"TICKER_AND_EXCH_CODE") -> LC US | D27: =CONCATENATE(_xll.BDP(Inputs!K21,"CRNCY")," ",_xll.BDP(Inputs!K21,"PX_YEST_CLOSE")) -> USD 17,13 | E27: =_xll.BDP(Inputs!K21,"PX_YEST_CLOSE")/_xll.BDP(Inputs!K21,"HIGH_52WEEK") -> 0.9136 | F27: =_xll.BDP(Inputs!$K21, "CUR_MKT_CAP", "SCALING_FORMAT=" & Inputs!$R$18) -> 1951.1562 | G27: =_xll.BDP(Inputs!$K21, "ENTERPRISE_VALUE", "SCALING_FORMAT=" & Inputs!$R$18) -> 235.41797 | I27: =G27/_xll.BQL(Inputs!$K21, "sales_rev_turn(fpt = ltm, fa_adjusted = y, fs = mr)/1"&IF(Inputs!$R$18="BLN","b",IF(Inputs!$R$18="MLN","m","k"))) -> 0.18855672 | J27: =G27/_xll.BQL(Inputs!$K21, "sales_rev_turn(fpr = 2025, fpt = a, ae = e, fa_adjusted = y, fs = mr)/1"&IF(Inputs!$R$18="BLN","b",IF(Inputs!$R$18="MLN","m","k"))) -> 0.23988862 | K27: =G27/_xll.BQL(Inputs!$K21, "sales_rev_turn(fpr = 2026, fpt = a, ae = e, fa_adjusted = y, fs = mr)/1"&IF(Inputs!$R$18="BLN","b",IF(Inputs!$R$18="MLN","m","k"))) -> 0.2075497 | L27: =G27/_xll.BQL(Inputs!$K21, "ebitda(fpt = ltm, fa_adjusted = y, fs = mr)/1"&IF(Inputs!$R$18="BLN","b",IF(Inputs!$R$18="MLN","m","k"))) -> 0.43982724 | M27: =G27/_xll.BQL(Inputs!$K21, "ebitda(fpr = 2025, fpt = a, ae = e, fa_adjusted = y, fs = mr)/1"&IF(Inputs!$R$18="BLN","b",IF(Inputs!$R$18="MLN","m","k"))) -> 0.79265309 | N27: =G27/_xll.BQL(Inputs!$K21, "ebitda(fpr = 2026, fpt = a, ae = e, fa_adjusted = y, fs = mr)/1"&IF(Inputs!$R$18="BLN","b",IF(Inputs!$R$18="MLN","m","k"))) -> 0.4940566 | O27: =G27/_xll.BQL(Inputs!$K21, "is_oper_inc(fpt = ltm, fa_adjusted = y, fs = mr)/1"&IF(Inputs!$R$18="BLN","b",IF(Inputs!$R$18="MLN","m","k"))) -> 2.3828936 | P27: =G27/_xll.BQL(Inputs!$K21, "is_oper_inc(fpr = 2025, fpt = a, ae = e, fa_adjusted = y, fs = mr)/1"&IF(Inputs!$R$18="BLN","b",IF(Inputs!$R$18="MLN","m","k"))) -> 1.6936544 | Q27: =G27/_xll.BQL(Inputs!$K21, "is_oper_inc(fpr = 2026, fpt = a, ae = e, fa_adjusted = y, fs = mr)/1"&IF(Inputs!$R$18="BLN","b",IF(Inputs!$R$18="MLN","m","k"))) -> 1.4354754 | S27: =_xll.BQL(Inputs!$K21, "ebitda(fpt = ltm, fa_adjusted = y, fs = mr)/1"&IF(Inputs!$R$18="BLN","b",IF(Inputs!$R$18="MLN","m","k")))/_xll.BQL(Inputs!$K21, "sales_rev_turn(fpt = ltm, fa_adjusted = y, fs = mr)/1"&IF(Inputs!$R$18="BLN","b",IF(Inputs!$R$18="MLN","m","k"))) -> 0.42870633 | T27: =_xll.BDP(Inputs!$K21,"TOT_DEBT_TO_EBITDA") -> 0.06717596 | V27: =F27/_xll.BQL(Inputs!$K21, "earn_for_common(fpt = ltm, fa_adjusted = y, fs = mr)/1"&IF(Inputs!$R$18="BLN","b",IF(Inputs!$R$18="MLN","m","k"))) -> 26.357715 | W27: =F27/_xll.BQL(Inputs!$K21, "EARN_FOR_COMMON(fpr = 2025, fpt = a, ae = e, fa_adjusted = y, fs = mr)/1"&IF(Inputs!$R$18="BLN","b",IF(Inputs!$R$18="MLN","m","k"))) -> 16.244594 | X27: =F27/_xll.BQL(Inputs!$K21, "EARN_FOR_COMMON(fpr = 2026, fpt = a, ae = e, fa_adjusted = y, fs = mr)/1"&IF(Inputs!$R$18="BLN","b",IF(Inputs!$R$18="MLN","m","k"))) -> 11.746091 | Z27: =(_xll.BQL(Inputs!$K21, "EARN_FOR_COMMON(fpr = 2028, fpt = a, ae = e, fa_adjusted = y, fs = mr)")/_xll.BQL(Inputs!$K21, "EARN_FOR_COMMON(fpr = 2025, fpt = a, ae = e, fa_adjusted = y, fs = mr)"))^(1/3)-1 -> #VALUE!
B28: =+Inputs!H22 -> UPSTART HOLDINGS | C28: =+_xll.BDP(Inputs!K22,"TICKER_AND_EXCH_CODE") -> UPST US | D28: =CONCATENATE(_xll.BDP(Inputs!K22,"CRNCY")," ",_xll.BDP(Inputs!K22,"PX_YEST_CLOSE")) -> USD 62,38 | E28: =_xll.BDP(Inputs!K22,"PX_YEST_CLOSE")/_xll.BDP(Inputs!K22,"HIGH_52WEEK") -> 0.64689815 | F28: =_xll.BDP(Inputs!$K22, "CUR_MKT_CAP", "SCALING_FORMAT=" & Inputs!$R$18) -> 6074.2261 | G28: =_xll.BDP(Inputs!$K22, "ENTERPRISE_VALUE", "SCALING_FORMAT=" & Inputs!$R$18) -> 7250.3101 | I28: =G28/_xll.BQL(Inputs!$K22, "sales_rev_turn(fpt = ltm, fa_adjusted = y, fs = mr)/1"&IF(Inputs!$R$18="BLN","b",IF(Inputs!$R$18="MLN","m","k"))) -> 8.5120914 | J28: =G28/_xll.BQL(Inputs!$K22, "sales_rev_turn(fpt = ltm, fa_adjusted = y, fs = mr)/1"&IF(Inputs!$R$18="BLN","b",IF(Inputs!$R$18="MLN","m","k"))) -> 8.5120914 | K28: =G28/_xll.BQL(Inputs!$K22, "sales_rev_turn(fpr = 2026, fpt = a, ae = e, fa_adjusted = y, fs = mr)/1"&IF(Inputs!$R$18="BLN","b",IF(Inputs!$R$18="MLN","m","k"))) -> 5.3914241 | L28: =G28/_xll.BQL(Inputs!$K22, "ebitda(fpt = ltm, fa_adjusted = y, fs = mr)/1"&IF(Inputs!$R$18="BLN","b",IF(Inputs!$R$18="MLN","m","k"))) -> 93.507746 | M28: =G28/_xll.BQL(Inputs!$K22, "ebitda(fpr = 2025, fpt = a, ae = e, fa_adjusted = y, fs = mr)/1"&IF(Inputs!$R$18="BLN","b",IF(Inputs!$R$18="MLN","m","k"))) -> 32.683592 | N28: =G28/_xll.BQL(Inputs!$K22, "ebitda(fpr = 2026, fpt = a, ae = e, fa_adjusted = y, fs = mr)/1"&IF(Inputs!$R$18="BLN","b",IF(Inputs!$R$18="MLN","m","k"))) -> 22.215877 | O28: =G28/_xll.BQL(Inputs!$K22, "is_oper_inc(fpt = ltm, fa_adjusted = y, fs = mr)/1"&IF(Inputs!$R$18="BLN","b",IF(Inputs!$R$18="MLN","m","k"))) -> 131.3343 | P28: =G28/_xll.BQL(Inputs!$K22, "is_oper_inc(fpr = 2025, fpt = a, ae = e, fa_adjusted = y, fs = mr)/1"&IF(Inputs!$R$18="BLN","b",IF(Inputs!$R$18="MLN","m","k"))) -> 228.13348 | Q28: =G28/_xll.BQL(Inputs!$K22, "is_oper_inc(fpr = 2026, fpt = a, ae = e, fa_adjusted = y, fs = mr)/1"&IF(Inputs!$R$18="BLN","b",IF(Inputs!$R$18="MLN","m","k"))) -> 48.381436 | S28: =_xll.BQL(Inputs!$K22, "ebitda(fpt = ltm, fa_adjusted = y, fs = mr)/1"&IF(Inputs!$R$18="BLN","b",IF(Inputs!$R$18="MLN","m","k")))/_xll.BQL(Inputs!$K22, "sales_rev_turn(fpt = ltm, fa_adjusted = y, fs = mr)/1"&IF(Inputs!$R$18="BLN","b",IF(Inputs!$R$18="MLN","m","k"))) -> 0.09103087 | T28: =_xll.BDP(Inputs!$K22,"TOT_DEBT_TO_EBITDA") -> #N/A N/A | V28: =F28/_xll.BQL(Inputs!$K22, "earn_for_common(fpt = ltm, fa_adjusted = y, fs = mr)/1"&IF(Inputs!$R$18="BLN","b",IF(Inputs!$R$18="MLN","m","k"))) -> 252.44649 | W28: =F28/_xll.BQL(Inputs!$K22, "EARN_FOR_COMMON(fpr = 2025, fpt = a, ae = e, fa_adjusted = y, fs = mr)/1"&IF(Inputs!$R$18="BLN","b",IF(Inputs!$R$18="MLN","m","k"))) -> 34.194722 | X28: =F28/_xll.BQL(Inputs!$K22, "EARN_FOR_COMMON(fpr = 2026, fpt = a, ae = e, fa_adjusted = y, fs = mr)/1"&IF(Inputs!$R$18="BLN","b",IF(Inputs!$R$18="MLN","m","k"))) -> 23.798957 | Z28: =(_xll.BQL(Inputs!$K22, "EARN_FOR_COMMON(fpr = 2028, fpt = a, ae = e, fa_adjusted = y, fs = mr)")/_xll.BQL(Inputs!$K22, "EARN_FOR_COMMON(fpr = 2025, fpt = a, ae = e, fa_adjusted = y, fs = mr)"))^(1/3)-1 -> 0.23302189
B29: =+Inputs!H23 -> SOFI TECHNOLOGIE | C29: =+_xll.BDP(Inputs!K23,"TICKER_AND_EXCH_CODE") -> SOFI US | D29: =CONCATENATE(_xll.BDP(Inputs!K23,"CRNCY")," ",_xll.BDP(Inputs!K23,"PX_YEST_CLOSE")) -> USD 29,09 | E29: =_xll.BDP(Inputs!K23,"PX_YEST_CLOSE")/_xll.BDP(Inputs!K23,"HIGH_52WEEK") -> 0.96006601 | F29: =_xll.BDP(Inputs!$K23, "CUR_MKT_CAP", "SCALING_FORMAT=" & Inputs!$R$18) -> 34456.627 | G29: =_xll.BDP(Inputs!$K23, "ENTERPRISE_VALUE", "SCALING_FORMAT=" & Inputs!$R$18) -> 22187.364 | I29: =G29/_xll.BQL(Inputs!$K23, "sales_rev_turn(fpt = ltm, fa_adjusted = y, fs = mr)/1"&IF(Inputs!$R$18="BLN","b",IF(Inputs!$R$18="MLN","m","k"))) -> 5.3287168 | J29: =G29/_xll.BQL(Inputs!$K23, "sales_rev_turn(fpr = 2025, fpt = a, ae = e, fa_adjusted = y, fs = mr)/1"&IF(Inputs!$R$18="BLN","b",IF(Inputs!$R$18="MLN","m","k"))) -> 6.5663596 | K29: =G29/_xll.BQL(Inputs!$K23, "sales_rev_turn(fpr = 2026, fpt = a, ae = e, fa_adjusted = y, fs = mr)/1"&IF(Inputs!$R$18="BLN","b",IF(Inputs!$R$18="MLN","m","k"))) -> 5.2314295 | L29: =G29/_xll.BQL(Inputs!$K23, "ebitda(fpt = ltm, fa_adjusted = y, fs = mr)/1"&IF(Inputs!$R$18="BLN","b",IF(Inputs!$R$18="MLN","m","k"))) -> 13.545441 | M29: =G29/_xll.BQL(Inputs!$K23, "ebitda(fpr = 2025, fpt = a, ae = e, fa_adjusted = y, fs = mr)/1"&IF(Inputs!$R$18="BLN","b",IF(Inputs!$R$18="MLN","m","k"))) -> 22.581954 | N29: =G29/_xll.BQL(Inputs!$K23, "ebitda(fpr = 2026, fpt = a, ae = e, fa_adjusted = y, fs = mr)/1"&IF(Inputs!$R$18="BLN","b",IF(Inputs!$R$18="MLN","m","k"))) -> 15.608706 | O29: =G29/_xll.BQL(Inputs!$K23, "is_oper_inc(fpt = ltm, fa_adjusted = y, fs = mr)/1"&IF(Inputs!$R$18="BLN","b",IF(Inputs!$R$18="MLN","m","k"))) -> 70.470306 | P29: =G29/_xll.BQL(Inputs!$K23, "is_oper_inc(fpr = 2025, fpt = a, ae = e, fa_adjusted = y, fs = mr)/1"&IF(Inputs!$R$18="BLN","b",IF(Inputs!$R$18="MLN","m","k"))) -> 47.452353 | Q29: =G29/_xll.BQL(Inputs!$K23, "is_oper_inc(fpr = 2026, fpt = a, ae = e, fa_adjusted = y, fs = mr)/1"&IF(Inputs!$R$18="BLN","b",IF(Inputs!$R$18="MLN","m","k"))) -> 24.500955 | S29: =_xll.BQL(Inputs!$K23, "ebitda(fpt = ltm, fa_adjusted = y, fs = mr)/1"&IF(Inputs!$R$18="BLN","b",IF(Inputs!$R$18="MLN","m","k")))/_xll.BQL(Inputs!$K23, "sales_rev_turn(fpt = ltm, fa_adjusted = y, fs = mr)/1"&IF(Inputs!$R$18="BLN","b",IF(Inputs!$R$18="MLN","m","k"))) -> 0.39339559 | T29: =_xll.BDP(Inputs!$K23,"TOT_DEBT_TO_EBITDA") -> 2.4614483 | V29: =F29/_xll.BQL(Inputs!$K23, "earn_for_common(fpt = ltm, fa_adjusted = y, fs = mr)/1"&IF(Inputs!$R$18="BLN","b",IF(Inputs!$R$18="MLN","m","k"))) -> 61.433015 | W29: =F29/_xll.BQL(Inputs!$K23, "EARN_FOR_COMMON(fpr = 2025, fpt = a, ae = e, fa_adjusted = y, fs = mr)/1"&IF(Inputs!$R$18="BLN","b",IF(Inputs!$R$18="MLN","m","k"))) -> 89.317293 | X29: =F29/_xll.BQL(Inputs!$K23, "EARN_FOR_COMMON(fpr = 2026, fpt = a, ae = e, fa_adjusted = y, fs = mr)/1"&IF(Inputs!$R$18="BLN","b",IF(Inputs!$R$18="MLN","m","k"))) -> 50.163319 | Z29: =(_xll.BQL(Inputs!$K23, "EARN_FOR_COMMON(fpr = 2028, fpt = a, ae = e, fa_adjusted = y, fs = mr)")/_xll.BQL(Inputs!$K23, "EARN_FOR_COMMON(fpr = 2025, fpt = a, ae = e, fa_adjusted = y, fs = mr)"))^(1/3)-1 -> 0.43417347
B30: =+Inputs!H24 -> OPORTUN FINANCIA | C30: =+_xll.BDP(Inputs!K24,"TICKER_AND_EXCH_CODE") -> OPRT US | D30: =CONCATENATE(_xll.BDP(Inputs!K24,"CRNCY")," ",_xll.BDP(Inputs!K24,"PX_YEST_CLOSE")) -> USD 6,73 | E30: =_xll.BDP(Inputs!K24,"PX_YEST_CLOSE")/_xll.BDP(Inputs!K24,"HIGH_52WEEK") -> 0.72796106 | F30: =_xll.BDP(Inputs!$K24, "CUR_MKT_CAP", "SCALING_FORMAT=" & Inputs!$R$18) -> 287.16133 | G30: =_xll.BDP(Inputs!$K24, "ENTERPRISE_VALUE", "SCALING_FORMAT=" & Inputs!$R$18) -> 1182.2453 | I30: =G30/_xll.BQL(Inputs!$K24, "sales_rev_turn(fpt = ltm, fa_adjusted = y, fs = mr)/1"&IF(Inputs!$R$18="BLN","b",IF(Inputs!$R$18="MLN","m","k"))) -> 1.9257162 | J30: =G30/_xll.BQL(Inputs!$K24, "sales_rev_turn(fpr = 2025, fpt = a, ae = e, fa_adjusted = y, fs = mr)/1"&IF(Inputs!$R$18="BLN","b",IF(Inputs!$R$18="MLN","m","k"))) -> 1.2405512 | K30: =G30/_xll.BQL(Inputs!$K24, "sales_rev_turn(fpr = 2026, fpt = a, ae = e, fa_adjusted = y, fs = mr)/1"&IF(Inputs!$R$18="BLN","b",IF(Inputs!$R$18="MLN","m","k"))) -> 1.1682266 | L30: =G30/_xll.BQL(Inputs!$K24, "ebitda(fpt = ltm, fa_adjusted = y, fs = mr)/1"&IF(Inputs!$R$18="BLN","b",IF(Inputs!$R$18="MLN","m","k"))) -> 3.6409827 | M30: =G30/_xll.BQL(Inputs!$K24, "ebitda(fpr = 2025, fpt = a, ae = e, fa_adjusted = y, fs = mr)/1"&IF(Inputs!$R$18="BLN","b",IF(Inputs!$R$18="MLN","m","k"))) -> 8.4566902 | N30: =G30/_xll.BQL(Inputs!$K24, "ebitda(fpr = 2026, fpt = a, ae = e, fa_adjusted = y, fs = mr)/1"&IF(Inputs!$R$18="BLN","b",IF(Inputs!$R$18="MLN","m","k"))) -> 6.5101613 | O30: =G30/_xll.BQL(Inputs!$K24, "is_oper_inc(fpt = ltm, fa_adjusted = y, fs = mr)/1"&IF(Inputs!$R$18="BLN","b",IF(Inputs!$R$18="MLN","m","k"))) -> 55.041915 | P30: =G30/_xll.BQL(Inputs!$K24, "is_oper_inc(fpr = 2025, fpt = a, ae = e, fa_adjusted = y, fs = mr)/1"&IF(Inputs!$R$18="BLN","b",IF(Inputs!$R$18="MLN","m","k"))) -> 45.470973 | Q30: =G30/_xll.BQL(Inputs!$K24, "is_oper_inc(fpr = 2026, fpt = a, ae = e, fa_adjusted = y, fs = mr)/1"&IF(Inputs!$R$18="BLN","b",IF(Inputs!$R$18="MLN","m","k"))) -> 28.148698 | S30: =_xll.BQL(Inputs!$K24, "ebitda(fpt = ltm, fa_adjusted = y, fs = mr)/1"&IF(Inputs!$R$18="BLN","b",IF(Inputs!$R$18="MLN","m","k")))/_xll.BQL(Inputs!$K24, "sales_rev_turn(fpt = ltm, fa_adjusted = y, fs = mr)/1"&IF(Inputs!$R$18="BLN","b",IF(Inputs!$R$18="MLN","m","k"))) -> 0.52890011 | T30: =_xll.BDP(Inputs!$K24,"TOT_DEBT_TO_EBITDA") -> 3.3133651 | V30: =F30/_xll.BQL(Inputs!$K24, "earn_for_common(fpt = ltm, fa_adjusted = y, fs = mr)/1"&IF(Inputs!$R$18="BLN","b",IF(Inputs!$R$18="MLN","m","k"))) -> 31.369334 | W30: =F30/_xll.BQL(Inputs!$K24, "EARN_FOR_COMMON(fpr = 2025, fpt = a, ae = e, fa_adjusted = y, fs = mr)/1"&IF(Inputs!$R$18="BLN","b",IF(Inputs!$R$18="MLN","m","k"))) -> 4.9891519 | X30: =F30/_xll.BQL(Inputs!$K24, "EARN_FOR_COMMON(fpr = 2026, fpt = a, ae = e, fa_adjusted = y, fs = mr)/1"&IF(Inputs!$R$18="BLN","b",IF(Inputs!$R$18="MLN","m","k"))) -> 3.690342 | Z30: =(_xll.BQL(Inputs!$K24, "EARN_FOR_COMMON(fpr = 2028, fpt = a, ae = e, fa_adjusted = y, fs = mr)")/_xll.BQL(Inputs!$K24, "EARN_FOR_COMMON(fpr = 2025, fpt = a, ae = e, fa_adjusted = y, fs = mr)"))^(1/3)-1 -> #VALUE!
B31: =+Inputs!H25 -> GREEN DOT CORP-A | C31: =+_xll.BDP(Inputs!K25,"TICKER_AND_EXCH_CODE") -> GDOT US | D31: =CONCATENATE(_xll.BDP(Inputs!K25,"CRNCY")," ",_xll.BDP(Inputs!K25,"PX_YEST_CLOSE")) -> USD 14,8 | E31: =_xll.BDP(Inputs!K25,"PX_YEST_CLOSE")/_xll.BDP(Inputs!K25,"HIGH_52WEEK") -> 0.96042155 | F31: =_xll.BDP(Inputs!$K25, "CUR_MKT_CAP", "SCALING_FORMAT=" & Inputs!$R$18) -> 810.39527 | G31: =_xll.BDP(Inputs!$K25, "ENTERPRISE_VALUE", "SCALING_FORMAT=" & Inputs!$R$18) -> 670.47064 | I31: =G31/_xll.BQL(Inputs!$K25, "sales_rev_turn(fpt = ltm, fa_adjusted = y, fs = mr)/1"&IF(Inputs!$R$18="BLN","b",IF(Inputs!$R$18="MLN","m","k"))) -> 0.34778749 | J31: =G31/_xll.BQL(Inputs!$K25, "sales_rev_turn(fpr = 2025, fpt = a, ae = e, fa_adjusted = y, fs = mr)/1"&IF(Inputs!$R$18="BLN","b",IF(Inputs!$R$18="MLN","m","k"))) -> 0.32684627 | K31: =G31/_xll.BQL(Inputs!$K25, "sales_rev_turn(fpr = 2026, fpt = a, ae = e, fa_adjusted = y, fs = mr)/1"&IF(Inputs!$R$18="BLN","b",IF(Inputs!$R$18="MLN","m","k"))) -> 0.29193206 | L31: =G31/_xll.BQL(Inputs!$K25, "ebitda(fpt = ltm, fa_adjusted = y, fs = mr)/1"&IF(Inputs!$R$18="BLN","b",IF(Inputs!$R$18="MLN","m","k"))) -> 3.6240481 | M31: =G31/_xll.BQL(Inputs!$K25, "ebitda(fpr = 2025, fpt = a, ae = e, fa_adjusted = y, fs = mr)/1"&IF(Inputs!$R$18="BLN","b",IF(Inputs!$R$18="MLN","m","k"))) -> 4.0882356 | N31: =G31/_xll.BQL(Inputs!$K25, "ebitda(fpr = 2026, fpt = a, ae = e, fa_adjusted = y, fs = mr)/1"&IF(Inputs!$R$18="BLN","b",IF(Inputs!$R$18="MLN","m","k"))) -> 3.8385724 | O31: =G31/_xll.BQL(Inputs!$K25, "is_oper_inc(fpt = ltm, fa_adjusted = y, fs = mr)/1"&IF(Inputs!$R$18="BLN","b",IF(Inputs!$R$18="MLN","m","k"))) -> 6.7550994 | P31: =G31/_xll.BQL(Inputs!$K25, "is_oper_inc(fpr = 2025, fpt = a, ae = e, fa_adjusted = y, fs = mr)/1"&IF(Inputs!$R$18="BLN","b",IF(Inputs!$R$18="MLN","m","k"))) -> 16.486983 | Q31: =G31/_xll.BQL(Inputs!$K25, "is_oper_inc(fpr = 2026, fpt = a, ae = e, fa_adjusted = y, fs = mr)/1"&IF(Inputs!$R$18="BLN","b",IF(Inputs!$R$18="MLN","m","k"))) -> 12.080552 | S31: =_xll.BQL(Inputs!$K25, "ebitda(fpt = ltm, fa_adjusted = y, fs = mr)/1"&IF(Inputs!$R$18="BLN","b",IF(Inputs!$R$18="MLN","m","k")))/_xll.BQL(Inputs!$K25, "sales_rev_turn(fpt = ltm, fa_adjusted = y, fs = mr)/1"&IF(Inputs!$R$18="BLN","b",IF(Inputs!$R$18="MLN","m","k"))) -> 0.095966578 | T31: =_xll.BDP(Inputs!$K25,"TOT_DEBT_TO_EBITDA") -> 0.42831546 | V31: =F31/_xll.BQL(Inputs!$K25, "earn_for_common(fpt = ltm, fa_adjusted = y, fs = mr)/1"&IF(Inputs!$R$18="BLN","b",IF(Inputs!$R$18="MLN","m","k"))) -> 15.991914 | W31: =F31/_xll.BQL(Inputs!$K25, "EARN_FOR_COMMON(fpr = 2025, fpt = a, ae = e, fa_adjusted = y, fs = mr)/1"&IF(Inputs!$R$18="BLN","b",IF(Inputs!$R$18="MLN","m","k"))) -> 10.89241 | X31: =F31/_xll.BQL(Inputs!$K25, "EARN_FOR_COMMON(fpr = 2026, fpt = a, ae = e, fa_adjusted = y, fs = mr)/1"&IF(Inputs!$R$18="BLN","b",IF(Inputs!$R$18="MLN","m","k"))) -> 9.6018397 | Z31: =(_xll.BQL(Inputs!$K25, "EARN_FOR_COMMON(fpr = 2028, fpt = a, ae = e, fa_adjusted = y, fs = mr)")/_xll.BQL(Inputs!$K25, "EARN_FOR_COMMON(fpr = 2025, fpt = a, ae = e, fa_adjusted = y, fs = mr)"))^(1/3)-1 -> 0.28807573
B33: Mean | I33: =AVERAGE(I27:I31) -> 3.2605737 | J33: =AVERAGE(J27:J31) -> 3.3771474 | K33: =AVERAGE(K27:K31) -> 2.4581124 | L33: =AVERAGE(L27:L31) -> 22.951609 | M33: =AVERAGE(M27:M31) -> 13.720625 | N33: =AVERAGE(N27:N31) -> 9.7334746 | O33: =AVERAGE(O27:O31) -> 53.196903 | P33: =AVERAGE(P27:P31) -> 67.847488 | Q33: =AVERAGE(Q27:Q31) -> 22.909423 | S33: =AVERAGE(S27:S31) -> 0.3075999 | T33: =AVERAGE(T27:T31) -> 1.5675762 | V33: =AVERAGE(V27:V31) -> 77.519693 | W33: =AVERAGE(W27:W31) -> 31.127634 | X33: =AVERAGE(X27:X31) -> 19.80011 | Z33: =AVERAGE(Z27:Z31) -> #VALUE!
B34: Median | I34: =MEDIAN(I27:I31) -> 1.9257162 | J34: =MEDIAN(J27:J31) -> 1.2405512 | K34: =MEDIAN(K27:K31) -> 1.1682266 | L34: =MEDIAN(L27:L31) -> 3.6409827 | M34: =MEDIAN(M27:M31) -> 8.4566902 | N34: =MEDIAN(N27:N31) -> 6.5101613 | O34: =MEDIAN(O27:O31) -> 55.041915 | P34: =MEDIAN(P27:P31) -> 45.470973 | Q34: =MEDIAN(Q27:Q31) -> 24.500955 | S34: =MEDIAN(S27:S31) -> 0.39339559 | T34: =MEDIAN(T27:T31) -> 1.4448819 | V34: =MEDIAN(V27:V31) -> 31.369334 | W34: =MEDIAN(W27:W31) -> 16.244594 | X34: =MEDIAN(X27:X31) -> 11.746091 | Z34: =MEDIAN(Z27:Z31) -> #VALUE!
B36: Tier III: BNPL and Others
B39: =+Inputs!N21 -> SYNCHRONY FINANC | C39: =+_xll.BDP(Inputs!Q21,"TICKER_AND_EXCH_CODE") -> SYF US | D39: =CONCATENATE(_xll.BDP(Inputs!Q21,"CRNCY")," ",_xll.BDP(Inputs!Q21,"PX_YEST_CLOSE")) -> USD 74,74 | E39: =_xll.BDP(Inputs!Q21,"PX_YEST_CLOSE")/_xll.BDP(Inputs!Q21,"HIGH_52WEEK") -> 0.96550833 | F39: =_xll.BDP(Inputs!$Q21, "CUR_MKT_CAP", "SCALING_FORMAT=" & Inputs!$R$18) -> 27707.126 | G39: =_xll.BDP(Inputs!$Q21, "ENTERPRISE_VALUE", "SCALING_FORMAT=" & Inputs!$R$18) -> 22625.465 | I39: =G39/_xll.BQL(Inputs!$Q21, "sales_rev_turn(fpt = ltm, fa_adjusted = y, fs = mr)/1"&IF(Inputs!$R$18="BLN","b",IF(Inputs!$R$18="MLN","m","k"))) -> 0.97755305 | J39: =G39/_xll.BQL(Inputs!$Q21, "sales_rev_turn(fpr = 2025, fpt = a, ae = e, fa_adjusted = y, fs = mr)/1"&IF(Inputs!$R$18="BLN","b",IF(Inputs!$R$18="MLN","m","k"))) -> 1.5028171 | K39: =G39/_xll.BQL(Inputs!$Q21, "sales_rev_turn(fpr = 2026, fpt = a, ae = e, fa_adjusted = y, fs = mr)/1"&IF(Inputs!$R$18="BLN","b",IF(Inputs!$R$18="MLN","m","k"))) -> 1.4226587 | L39: =G39/_xll.BQL(Inputs!$Q21, "ebitda(fpt = ltm, fa_adjusted = y, fs = mr)/1"&IF(Inputs!$R$18="BLN","b",IF(Inputs!$R$18="MLN","m","k"))) -> 1.7547282 | M39: =G39/_xll.BQL(Inputs!$Q21, "ebitda(fpr = 2025, fpt = a, ae = e, fa_adjusted = y, fs = mr)/1"&IF(Inputs!$R$18="BLN","b",IF(Inputs!$R$18="MLN","m","k"))) -> 3.4730932 | N39: =G39/_xll.BQL(Inputs!$Q21, "ebitda(fpr = 2026, fpt = a, ae = e, fa_adjusted = y, fs = mr)/1"&IF(Inputs!$R$18="BLN","b",IF(Inputs!$R$18="MLN","m","k"))) -> 3.6960656 | O39: =G39/_xll.BQL(Inputs!$Q21, "is_oper_inc(fpt = ltm, fa_adjusted = y, fs = mr)/1"&IF(Inputs!$R$18="BLN","b",IF(Inputs!$R$18="MLN","m","k"))) -> 5.3349364 | P39: =G39/_xll.BQL(Inputs!$Q21, "is_oper_inc(fpr = 2025, fpt = a, ae = e, fa_adjusted = y, fs = mr)/1"&IF(Inputs!$R$18="BLN","b",IF(Inputs!$R$18="MLN","m","k"))) -> 5.2922589 | Q39: =G39/_xll.BQL(Inputs!$Q21, "is_oper_inc(fpr = 2026, fpt = a, ae = e, fa_adjusted = y, fs = mr)/1"&IF(Inputs!$R$18="BLN","b",IF(Inputs!$R$18="MLN","m","k"))) -> 4.2580428 | S39: =_xll.BQL(Inputs!$Q21, "ebitda(fpt = ltm, fa_adjusted = y, fs = mr)/1"&IF(Inputs!$R$18="BLN","b",IF(Inputs!$R$18="MLN","m","k")))/_xll.BQL(Inputs!$Q21, "sales_rev_turn(fpt = ltm, fa_adjusted = y, fs = mr)/1"&IF(Inputs!$R$18="BLN","b",IF(Inputs!$R$18="MLN","m","k"))) -> 0.55709657 | T39: =_xll.BDP(Inputs!$Q21,"TOT_DEBT_TO_EBITDA") -> 1.2415852 | V39: =F39/_xll.BQL(Inputs!$Q21, "earn_for_common(fpt = ltm, fa_adjusted = y, fs = mr)/1"&IF(Inputs!$R$18="BLN","b",IF(Inputs!$R$18="MLN","m","k"))) -> 8.650367 | W39: =F39/_xll.BQL(Inputs!$Q21, "EARN_FOR_COMMON(fpr = 2025, fpt = a, ae = e, fa_adjusted = y, fs = mr)/1"&IF(Inputs!$R$18="BLN","b",IF(Inputs!$R$18="MLN","m","k"))) -> 8.5785001 | X39: =F39/_xll.BQL(Inputs!$Q21, "EARN_FOR_COMMON(fpr = 2026, fpt = a, ae = e, fa_adjusted = y, fs = mr)/1"&IF(Inputs!$R$18="BLN","b",IF(Inputs!$R$18="MLN","m","k"))) -> 8.7894022 | Z39: =(_xll.BQL(Inputs!$Q21, "EARN_FOR_COMMON(fpr = 2028, fpt = a, ae = e, fa_adjusted = y, fs = mr)")/_xll.BQL(Inputs!$Q21, "EARN_FOR_COMMON(fpr = 2025, fpt = a, ae = e, fa_adjusted = y, fs = mr)"))^(1/3)-1 -> -0.021423399
B40: =+Inputs!N22 -> DISCOVER FINANCI | C40: =+_xll.BDP(Inputs!Q22,"TICKER_AND_EXCH_CODE") -> DFS US | D40: =CONCATENATE(_xll.BDP(Inputs!Q22,"CRNCY")," ",_xll.BDP(Inputs!Q22,"PX_YEST_CLOSE")) -> #NAME? | E40: =_xll.BDP(Inputs!Q22,"PX_YEST_CLOSE")/_xll.BDP(Inputs!Q22,"HIGH_52WEEK") -> #VALUE! | F40: =_xll.BDP(Inputs!$Q22, "CUR_MKT_CAP", "SCALING_FORMAT=" & Inputs!$R$18) -> #N/A N/A | G40: =_xll.BDP(Inputs!$Q22, "ENTERPRISE_VALUE", "SCALING_FORMAT=" & Inputs!$R$18) -> 46682.071 | I40: =G40/_xll.BQL(Inputs!$Q22, "sales_rev_turn(fpt = ltm, fa_adjusted = y, fs = mr)/1"&IF(Inputs!$R$18="BLN","b",IF(Inputs!$R$18="MLN","m","k"))) -> 1.9858796 | J40: =G40/_xll.BQL(Inputs!$Q22, "sales_rev_turn(fpr = 2025, fpt = a, ae = e, fa_adjusted = y, fs = mr)/1"&IF(Inputs!$R$18="BLN","b",IF(Inputs!$R$18="MLN","m","k"))) -> 2.6836102 | K40: =G40/_xll.BQL(Inputs!$Q22, "sales_rev_turn(fpr = 2026, fpt = a, ae = e, fa_adjusted = y, fs = mr)/1"&IF(Inputs!$R$18="BLN","b",IF(Inputs!$R$18="MLN","m","k"))) -> 2.5815268 | L40: =G40/_xll.BQL(Inputs!$Q22, "ebitda(fpt = ltm, fa_adjusted = y, fs = mr)/1"&IF(Inputs!$R$18="BLN","b",IF(Inputs!$R$18="MLN","m","k"))) -> 3.851656 | M40: =G40/_xll.BQL(Inputs!$Q22, "ebitda(fpr = 2025, fpt = a, ae = e, fa_adjusted = y, fs = mr)/1"&IF(Inputs!$R$18="BLN","b",IF(Inputs!$R$18="MLN","m","k"))) -> 6.8368587 | N40: =G40/_xll.BQL(Inputs!$Q22, "ebitda(fpr = 2026, fpt = a, ae = e, fa_adjusted = y, fs = mr)/1"&IF(Inputs!$R$18="BLN","b",IF(Inputs!$R$18="MLN","m","k"))) -> 6.3991872 | O40: =G40/_xll.BQL(Inputs!$Q22, "is_oper_inc(fpt = ltm, fa_adjusted = y, fs = mr)/1"&IF(Inputs!$R$18="BLN","b",IF(Inputs!$R$18="MLN","m","k"))) -> 7.2952135 | P40: =G40/_xll.BQL(Inputs!$Q22, "is_oper_inc(fpr = 2025, fpt = a, ae = e, fa_adjusted = y, fs = mr)/1"&IF(Inputs!$R$18="BLN","b",IF(Inputs!$R$18="MLN","m","k"))) -> 9.3701467 | Q40: =G40/_xll.BQL(Inputs!$Q22, "is_oper_inc(fpr = 2026, fpt = a, ae = e, fa_adjusted = y, fs = mr)/1"&IF(Inputs!$R$18="BLN","b",IF(Inputs!$R$18="MLN","m","k"))) -> 6.5043989 | S40: =_xll.BQL(Inputs!$Q22, "ebitda(fpt = ltm, fa_adjusted = y, fs = mr)/1"&IF(Inputs!$R$18="BLN","b",IF(Inputs!$R$18="MLN","m","k")))/_xll.BQL(Inputs!$Q22, "sales_rev_turn(fpt = ltm, fa_adjusted = y, fs = mr)/1"&IF(Inputs!$R$18="BLN","b",IF(Inputs!$R$18="MLN","m","k"))) -> 0.5155911 | T40: =_xll.BDP(Inputs!$Q22,"TOT_DEBT_TO_EBITDA") -> 1.199505 | V40: =F40/_xll.BQL(Inputs!$Q22, "earn_for_common(fpt = ltm, fa_adjusted = y, fs = mr)/1"&IF(Inputs!$R$18="BLN","b",IF(Inputs!$R$18="MLN","m","k"))) -> #VALUE! | W40: =F40/_xll.BQL(Inputs!$Q22, "EARN_FOR_COMMON(fpr = 2025, fpt = a, ae = e, fa_adjusted = y, fs = mr)/1"&IF(Inputs!$R$18="BLN","b",IF(Inputs!$R$18="MLN","m","k"))) -> #VALUE! | X40: =F40/_xll.BQL(Inputs!$Q22, "EARN_FOR_COMMON(fpr = 2026, fpt = a, ae = e, fa_adjusted = y, fs = mr)/1"&IF(Inputs!$R$18="BLN","b",IF(Inputs!$R$18="MLN","m","k"))) -> #VALUE! | Z40: =(_xll.BQL(Inputs!$Q22, "EARN_FOR_COMMON(fpr = 2028, fpt = a, ae = e, fa_adjusted = y, fs = mr)")/_xll.BQL(Inputs!$Q22, "EARN_FOR_COMMON(fpr = 2025, fpt = a, ae = e, fa_adjusted = y, fs = mr)"))^(1/3)-1 -> 0.008081625
B41: =+Inputs!N23 -> CAPITAL ONE FINA | C41: =+_xll.BDP(Inputs!Q23,"TICKER_AND_EXCH_CODE") -> COF US | D41: =CONCATENATE(_xll.BDP(Inputs!Q23,"CRNCY")," ",_xll.BDP(Inputs!Q23,"PX_YEST_CLOSE")) -> USD 223,02 | E41: =_xll.BDP(Inputs!Q23,"PX_YEST_CLOSE")/_xll.BDP(Inputs!Q23,"HIGH_52WEEK") -> 0.95941439 | F41: =_xll.BDP(Inputs!$Q23, "CUR_MKT_CAP", "SCALING_FORMAT=" & Inputs!$R$18) -> 143718.72 | G41: =_xll.BDP(Inputs!$Q23, "ENTERPRISE_VALUE", "SCALING_FORMAT=" & Inputs!$R$18) -> 135027.7 | I41: =G41/_xll.BQL(Inputs!$Q23, "sales_rev_turn(fpt = ltm, fa_adjusted = y, fs = mr)/1"&IF(Inputs!$R$18="BLN","b",IF(Inputs!$R$18="MLN","m","k"))) -> 2.3549837 | J41: =G41/_xll.BQL(Inputs!$Q23, "sales_rev_turn(fpr = 2025, fpt = a, ae = e, fa_adjusted = y, fs = mr)/1"&IF(Inputs!$R$18="BLN","b",IF(Inputs!$R$18="MLN","m","k"))) -> 2.556164 | K41: =G41/_xll.BQL(Inputs!$Q23, "sales_rev_turn(fpr = 2026, fpt = a, ae = e, fa_adjusted = y, fs = mr)/1"&IF(Inputs!$R$18="BLN","b",IF(Inputs!$R$18="MLN","m","k"))) -> 2.1615569 | L41: =G41/_xll.BQL(Inputs!$Q23, "ebitda(fpt = ltm, fa_adjusted = y, fs = mr)/1"&IF(Inputs!$R$18="BLN","b",IF(Inputs!$R$18="MLN","m","k"))) -> 7.4338087 | M41: =G41/_xll.BQL(Inputs!$Q23, "ebitda(fpr = 2025, fpt = a, ae = e, fa_adjusted = y, fs = mr)/1"&IF(Inputs!$R$18="BLN","b",IF(Inputs!$R$18="MLN","m","k"))) -> 10.919418 | N41: =G41/_xll.BQL(Inputs!$Q23, "ebitda(fpr = 2026, fpt = a, ae = e, fa_adjusted = y, fs = mr)/1"&IF(Inputs!$R$18="BLN","b",IF(Inputs!$R$18="MLN","m","k"))) -> 8.7806714 | O41: =G41/_xll.BQL(Inputs!$Q23, "is_oper_inc(fpt = ltm, fa_adjusted = y, fs = mr)/1"&IF(Inputs!$R$18="BLN","b",IF(Inputs!$R$18="MLN","m","k"))) -> 1687.8463 | P41: =G41/_xll.BQL(Inputs!$Q23, "is_oper_inc(fpr = 2025, fpt = a, ae = e, fa_adjusted = y, fs = mr)/1"&IF(Inputs!$R$18="BLN","b",IF(Inputs!$R$18="MLN","m","k"))) -> 26.145864 | Q41: =G41/_xll.BQL(Inputs!$Q23, "is_oper_inc(fpr = 2026, fpt = a, ae = e, fa_adjusted = y, fs = mr)/1"&IF(Inputs!$R$18="BLN","b",IF(Inputs!$R$18="MLN","m","k"))) -> 9.1500781 | S41: =_xll.BQL(Inputs!$Q23, "ebitda(fpt = ltm, fa_adjusted = y, fs = mr)/1"&IF(Inputs!$R$18="BLN","b",IF(Inputs!$R$18="MLN","m","k")))/_xll.BQL(Inputs!$Q23, "sales_rev_turn(fpt = ltm, fa_adjusted = y, fs = mr)/1"&IF(Inputs!$R$18="BLN","b",IF(Inputs!$R$18="MLN","m","k"))) -> 0.31679369 | T41: =_xll.BDP(Inputs!$Q23,"TOT_DEBT_TO_EBITDA") -> 2.9990319 | V41: =F41/_xll.BQL(Inputs!$Q23, "earn_for_common(fpt = ltm, fa_adjusted = y, fs = mr)/1"&IF(Inputs!$R$18="BLN","b",IF(Inputs!$R$18="MLN","m","k"))) -> 871.19828 | W41: =F41/_xll.BQL(Inputs!$Q23, "EARN_FOR_COMMON(fpr = 2025, fpt = a, ae = e, fa_adjusted = y, fs = mr)/1"&IF(Inputs!$R$18="BLN","b",IF(Inputs!$R$18="MLN","m","k"))) -> 18.294523 | X41: =F41/_xll.BQL(Inputs!$Q23, "EARN_FOR_COMMON(fpr = 2026, fpt = a, ae = e, fa_adjusted = y, fs = mr)/1"&IF(Inputs!$R$18="BLN","b",IF(Inputs!$R$18="MLN","m","k"))) -> 12.2205 | Z41: =(_xll.BQL(Inputs!$Q23, "EARN_FOR_COMMON(fpr = 2028, fpt = a, ae = e, fa_adjusted = y, fs = mr)")/_xll.BQL(Inputs!$Q23, "EARN_FOR_COMMON(fpr = 2025, fpt = a, ae = e, fa_adjusted = y, fs = mr)"))^(1/3)-1 -> 0.23609337
B42: =+Inputs!N24 -> ALLY FINANCIAL I | C42: =+_xll.BDP(Inputs!Q24,"TICKER_AND_EXCH_CODE") -> ALLY US | D42: =CONCATENATE(_xll.BDP(Inputs!Q24,"CRNCY")," ",_xll.BDP(Inputs!Q24,"PX_YEST_CLOSE")) -> USD 42,68 | E42: =_xll.BDP(Inputs!Q24,"PX_YEST_CLOSE")/_xll.BDP(Inputs!Q24,"HIGH_52WEEK") -> 0.95204104 | F42: =_xll.BDP(Inputs!$Q24, "CUR_MKT_CAP", "SCALING_FORMAT=" & Inputs!$R$18) -> 13004.889 | G42: =_xll.BDP(Inputs!$Q24, "ENTERPRISE_VALUE", "SCALING_FORMAT=" & Inputs!$R$18) -> 23452.29 | I42: =G42/_xll.BQL(Inputs!$Q24, "sales_rev_turn(fpt = ltm, fa_adjusted = y, fs = mr)/1"&IF(Inputs!$R$18="BLN","b",IF(Inputs!$R$18="MLN","m","k"))) -> 1.5051851 | J42: =G42/_xll.BQL(Inputs!$Q24, "sales_rev_turn(fpr = 2025, fpt = a, ae = e, fa_adjusted = y, fs = mr)/1"&IF(Inputs!$R$18="BLN","b",IF(Inputs!$R$18="MLN","m","k"))) -> 2.9403767 | K42: =G42/_xll.BQL(Inputs!$Q24, "sales_rev_turn(fpr = 2026, fpt = a, ae = e, fa_adjusted = y, fs = mr)/1"&IF(Inputs!$R$18="BLN","b",IF(Inputs!$R$18="MLN","m","k"))) -> 2.583016 | L42: =G42/_xll.BQL(Inputs!$Q24, "ebitda(fpt = ltm, fa_adjusted = y, fs = mr)/1"&IF(Inputs!$R$18="BLN","b",IF(Inputs!$R$18="MLN","m","k"))) -> 2.3758138 | M42: =G42/_xll.BQL(Inputs!$Q24, "ebitda(fpr = 2025, fpt = a, ae = e, fa_adjusted = y, fs = mr)/1"&IF(Inputs!$R$18="BLN","b",IF(Inputs!$R$18="MLN","m","k"))) -> 5.2139372 | N42: =G42/_xll.BQL(Inputs!$Q24, "ebitda(fpr = 2026, fpt = a, ae = e, fa_adjusted = y, fs = mr)/1"&IF(Inputs!$R$18="BLN","b",IF(Inputs!$R$18="MLN","m","k"))) -> 4.5265952 | O42: =G42/_xll.BQL(Inputs!$Q24, "is_oper_inc(fpt = ltm, fa_adjusted = y, fs = mr)/1"&IF(Inputs!$R$18="BLN","b",IF(Inputs!$R$18="MLN","m","k"))) -> 14.456502 | P42: =G42/_xll.BQL(Inputs!$Q24, "is_oper_inc(fpr = 2025, fpt = a, ae = e, fa_adjusted = y, fs = mr)/1"&IF(Inputs!$R$18="BLN","b",IF(Inputs!$R$18="MLN","m","k"))) -> 13.784653 | Q42: =G42/_xll.BQL(Inputs!$Q24, "is_oper_inc(fpr = 2026, fpt = a, ae = e, fa_adjusted = y, fs = mr)/1"&IF(Inputs!$R$18="BLN","b",IF(Inputs!$R$18="MLN","m","k"))) -> 8.6786156 | S42: =_xll.BQL(Inputs!$Q24, "ebitda(fpt = ltm, fa_adjusted = y, fs = mr)/1"&IF(Inputs!$R$18="BLN","b",IF(Inputs!$R$18="MLN","m","k")))/_xll.BQL(Inputs!$Q24, "sales_rev_turn(fpt = ltm, fa_adjusted = y, fs = mr)/1"&IF(Inputs!$R$18="BLN","b",IF(Inputs!$R$18="MLN","m","k"))) -> 0.63354508 | T42: =_xll.BDP(Inputs!$Q24,"TOT_DEBT_TO_EBITDA") -> 2.2568912 | V42: =F42/_xll.BQL(Inputs!$Q24, "earn_for_common(fpt = ltm, fa_adjusted = y, fs = mr)/1"&IF(Inputs!$R$18="BLN","b",IF(Inputs!$R$18="MLN","m","k"))) -> 9.7852622 | W42: =F42/_xll.BQL(Inputs!$Q24, "EARN_FOR_COMMON(fpr = 2025, fpt = a, ae = e, fa_adjusted = y, fs = mr)/1"&IF(Inputs!$R$18="BLN","b",IF(Inputs!$R$18="MLN","m","k"))) -> 11.912448 | X42: =F42/_xll.BQL(Inputs!$Q24, "EARN_FOR_COMMON(fpr = 2026, fpt = a, ae = e, fa_adjusted = y, fs = mr)/1"&IF(Inputs!$R$18="BLN","b",IF(Inputs!$R$18="MLN","m","k"))) -> 7.6927909 | Z42: =(_xll.BQL(Inputs!$Q24, "EARN_FOR_COMMON(fpr = 2028, fpt = a, ae = e, fa_adjusted = y, fs = mr)")/_xll.BQL(Inputs!$Q24, "EARN_FOR_COMMON(fpr = 2025, fpt = a, ae = e, fa_adjusted = y, fs = mr)"))^(1/3)-1 -> #VALUE!
B43: =+Inputs!N25 -> AFFIRM HOLDINGS | C43: =+_xll.BDP(Inputs!Q25,"TICKER_AND_EXCH_CODE") -> AFRM US | D43: =CONCATENATE(_xll.BDP(Inputs!Q25,"CRNCY")," ",_xll.BDP(Inputs!Q25,"PX_YEST_CLOSE")) -> USD 82,73 | E43: =_xll.BDP(Inputs!Q25,"PX_YEST_CLOSE")/_xll.BDP(Inputs!Q25,"HIGH_52WEEK") -> 0.8273 | F43: =_xll.BDP(Inputs!$Q25, "CUR_MKT_CAP", "SCALING_FORMAT=" & Inputs!$R$18) -> 27097.58 | G43: =_xll.BDP(Inputs!$Q25, "ENTERPRISE_VALUE", "SCALING_FORMAT=" & Inputs!$R$18) -> 23060.17 | I43: =G43/_xll.BQL(Inputs!$Q25, "sales_rev_turn(fpt = ltm, fa_adjusted = y, fs = mr)/1"&IF(Inputs!$R$18="BLN","b",IF(Inputs!$R$18="MLN","m","k"))) -> 7.1517442 | J43: =G43/_xll.BQL(Inputs!$Q25, "sales_rev_turn(fpr = 2025, fpt = a, ae = e, fa_adjusted = y, fs = mr)/1"&IF(Inputs!$R$18="BLN","b",IF(Inputs!$R$18="MLN","m","k"))) -> 7.2377799 | K43: =G43/_xll.BQL(Inputs!$Q25, "sales_rev_turn(fpr = 2026, fpt = a, ae = e, fa_adjusted = y, fs = mr)/1"&IF(Inputs!$R$18="BLN","b",IF(Inputs!$R$18="MLN","m","k"))) -> 5.7978001 | L43: =G43/_xll.BQL(Inputs!$Q25, "ebitda(fpt = ltm, fa_adjusted = y, fs = mr)/1"&IF(Inputs!$R$18="BLN","b",IF(Inputs!$R$18="MLN","m","k"))) -> 12.189442 | M43: =G43/_xll.BQL(Inputs!$Q25, "ebitda(fpr = 2025, fpt = a, ae = e, fa_adjusted = y, fs = mr)/1"&IF(Inputs!$R$18="BLN","b",IF(Inputs!$R$18="MLN","m","k"))) -> 29.326202 | N43: =G43/_xll.BQL(Inputs!$Q25, "ebitda(fpr = 2026, fpt = a, ae = e, fa_adjusted = y, fs = mr)/1"&IF(Inputs!$R$18="BLN","b",IF(Inputs!$R$18="MLN","m","k"))) -> 24.354434 | O43: =G43/_xll.BQL(Inputs!$Q25, "is_oper_inc(fpt = ltm, fa_adjusted = y, fs = mr)/1"&IF(Inputs!$R$18="BLN","b",IF(Inputs!$R$18="MLN","m","k"))) -> 13.935406 | P43: =G43/_xll.BQL(Inputs!$Q25, "is_oper_inc(fpr = 2025, fpt = a, ae = e, fa_adjusted = y, fs = mr)/1"&IF(Inputs!$R$18="BLN","b",IF(Inputs!$R$18="MLN","m","k"))) -> 30.849726 | Q43: =G43/_xll.BQL(Inputs!$Q25, "is_oper_inc(fpr = 2026, fpt = a, ae = e, fa_adjusted = y, fs = mr)/1"&IF(Inputs!$R$18="BLN","b",IF(Inputs!$R$18="MLN","m","k"))) -> 21.852332 | S43: =_xll.BQL(Inputs!$Q25, "ebitda(fpt = ltm, fa_adjusted = y, fs = mr)/1"&IF(Inputs!$R$18="BLN","b",IF(Inputs!$R$18="MLN","m","k")))/_xll.BQL(Inputs!$Q25, "sales_rev_turn(fpt = ltm, fa_adjusted = y, fs = mr)/1"&IF(Inputs!$R$18="BLN","b",IF(Inputs!$R$18="MLN","m","k"))) -> 0.58671628 | T43: =_xll.BDP(Inputs!$Q25,"TOT_DEBT_TO_EBITDA") -> 25.81389 | V43: =F43/_xll.BQL(Inputs!$Q25, "earn_for_common(fpt = ltm, fa_adjusted = y, fs = mr)/1"&IF(Inputs!$R$18="BLN","b",IF(Inputs!$R$18="MLN","m","k"))) -> 19.87638 | W43: =F43/_xll.BQL(Inputs!$Q25, "EARN_FOR_COMMON(fpr = 2025, fpt = a, ae = e, fa_adjusted = y, fs = mr)/1"&IF(Inputs!$R$18="BLN","b",IF(Inputs!$R$18="MLN","m","k"))) -> 985.62254 | X43: =F43/_xll.BQL(Inputs!$Q25, "EARN_FOR_COMMON(fpr = 2026, fpt = a, ae = e, fa_adjusted = y, fs = mr)/1"&IF(Inputs!$R$18="BLN","b",IF(Inputs!$R$18="MLN","m","k"))) -> 82.674586 | Z43: =(_xll.BQL(Inputs!$Q25, "EARN_FOR_COMMON(fpr = 2028, fpt = a, ae = e, fa_adjusted = y, fs = mr)")/_xll.BQL(Inputs!$Q25, "EARN_FOR_COMMON(fpr = 2025, fpt = a, ae = e, fa_adjusted = y, fs = mr)"))^(1/3)-1 -> 2.286461
B45: Mean | I45: =AVERAGE(I39:I43) -> 2.7950691 | J45: =AVERAGE(J39:J43) -> 3.3841496 | K45: =AVERAGE(K39:K43) -> 2.9093117 | L45: =AVERAGE(L39:L43) -> 5.5210898 | M45: =AVERAGE(M39:M43) -> 11.153902 | N45: =AVERAGE(N39:N43) -> 9.5513907 | O45: =AVERAGE(O39:O43) -> 345.77367 | P45: =AVERAGE(P39:P43) -> 17.08853 | Q45: =AVERAGE(Q39:Q43) -> 10.088693 | S45: =AVERAGE(S39:S43) -> 0.52194854 | T45: =AVERAGE(T39:T43) -> 6.7021807 | V45: =AVERAGE(V39:V43) -> #VALUE! | W45: =AVERAGE(W39:W43) -> #VALUE! | X45: =AVERAGE(X39:X43) -> #VALUE! | Z45: =AVERAGE(Z39:Z43) -> #VALUE!
B46: Median | I46: =MEDIAN(I39:I43) -> 1.9858796 | J46: =MEDIAN(J39:J43) -> 2.6836102 | K46: =MEDIAN(K39:K43) -> 2.5815268 | L46: =MEDIAN(L39:L43) -> 3.851656 | M46: =MEDIAN(M39:M43) -> 6.8368587 | N46: =MEDIAN(N39:N43) -> 6.3991872 | O46: =MEDIAN(O39:O43) -> 13.935406 | P46: =MEDIAN(P39:P43) -> 13.784653 | Q46: =MEDIAN(Q39:Q43) -> 8.6786156 | S46: =MEDIAN(S39:S43) -> 0.55709657 | T46: =MEDIAN(T39:T43) -> 2.2568912 | V46: =MEDIAN(V39:V43) -> #VALUE! | W46: =MEDIAN(W39:W43) -> #VALUE! | X46: =MEDIAN(X39:X43) -> #VALUE! | Z46: =MEDIAN(Z39:Z43) -> #VALUE!
B48: Overall
B51: Mean | I51: =AVERAGE(I39:I43,I27:I32,I15:I19) -> #NAME? | J51: =AVERAGE(J39:J43,J27:J32,J15:J19) -> #NAME? | K51: =AVERAGE(K39:K43,K27:K32,K15:K19) -> #NAME? | L51: =AVERAGE(L39:L43,L27:L32,L15:L19) -> #NAME? | M51: =AVERAGE(M39:M43,M27:M32,M15:M19) -> #NAME? | N51: =AVERAGE(N39:N43,N27:N32,N15:N19) -> #NAME? | O51: =AVERAGE(O39:O43,O27:O32,O15:O19) -> #NAME? | P51: =AVERAGE(P39:P43,P27:P32,P15:P19) -> #NAME? | Q51: =AVERAGE(Q39:Q43,Q27:Q32,Q15:Q19) -> #NAME? | S51: =AVERAGE(S39:S43,S27:S32,S15:S19) -> #NAME? | T51: =AVERAGE(T39:T43,T27:T32,T15:T19) -> #NAME? | V51: =AVERAGE(V39:V43,V27:V32,V15:V19) -> #VALUE! | W51: =AVERAGE(W39:W43,W27:W32,W15:W19) -> #VALUE! | X51: =AVERAGE(X39:X43,X27:X32,X15:X19) -> #VALUE! | Z51: =AVERAGE(Z39:Z43,Z27:Z32,Z15:Z19) -> #VALUE!
B52: Median | I52: =MEDIAN(I39:I43,I27:I31,I15:I19) -> #NAME? | J52: =MEDIAN(J39:J43,J27:J31,J15:J19) -> #NAME? | K52: =MEDIAN(K39:K43,K27:K31,K15:K19) -> #NAME? | L52: =MEDIAN(L39:L43,L27:L31,L15:L19) -> #NAME? | M52: =MEDIAN(M39:M43,M27:M31,M15:M19) -> #NAME? | N52: =MEDIAN(N39:N43,N27:N31,N15:N19) -> #NAME? | O52: =MEDIAN(O39:O43,O27:O31,O15:O19) -> #NAME? | P52: =MEDIAN(P39:P43,P27:P31,P15:P19) -> #NAME? | Q52: =MEDIAN(Q39:Q43,Q27:Q31,Q15:Q19) -> #NAME? | S52: =MEDIAN(S39:S43,S27:S31,S15:S19) -> #NAME? | T52: =MEDIAN(T39:T43,T27:T31,T15:T19) -> #NAME? | V52: =MEDIAN(V39:V43,V27:V31,V15:V19) -> #VALUE! | W52: =MEDIAN(W39:W43,W27:W31,W15:W19) -> #VALUE! | X52: =MEDIAN(X39:X43,X27:X31,X15:X19) -> #VALUE! | Z52: =MEDIAN(Z39:Z43,Z27:Z31,Z15:Z19) -> #VALUE!
B54: High | I54: =MAX(I39:I43,I27:I31,I15:I19) -> #NAME? | J54: =MAX(J39:J43,J27:J31,J15:J19) -> #NAME? | K54: =MAX(K39:K43,K27:K31,K15:K19) -> #NAME? | L54: =MAX(L39:L43,L27:L31,L15:L19) -> #NAME? | M54: =MAX(M39:M43,M27:M31,M15:M19) -> #NAME? | N54: =MAX(N39:N43,N27:N31,N15:N19) -> #NAME? | O54: =MAX(O39:O43,O27:O31,O15:O19) -> #NAME? | P54: =MAX(P39:P43,P27:P31,P15:P19) -> #NAME? | ... T54: =MAX(T39:T43,T27:T31,T15:T19) -> #NAME? | V54: =MAX(V39:V43,V27:V31,V15:V19) -> #VALUE! | W54: =MAX(W39:W43,W27:W31,W15:W19) -> #VALUE! | X54: =MAX(X39:X43,X27:X31,X15:X19) -> #VALUE! | Z54: =MAX(Z39:Z43,Z27:Z31,Z15:Z19) -> #VALUE!
B55: Low | I55: =MIN(I39:I43,I27:I31,I15:I19) -> #NAME? | J55: =MIN(J39:J43,J27:J31,J15:J19) -> #NAME? | K55: =MIN(K39:K43,K27:K31,K15:K19) -> #NAME? | L55: =MIN(L39:L43,L27:L31,L15:L19) -> #NAME? | M55: =MIN(M39:M43,M27:M31,M15:M19) -> #NAME? | N55: =MIN(N39:N43,N27:N31,N15:N19) -> #NAME? | O55: =MIN(O39:O43,O27:O31,O15:O19) -> #NAME? | P55: =MIN(P39:P43,P27:P31,P15:P19) -> #NAME? | ... T55: =MIN(T39:T43,T27:T31,T15:T19) -> #NAME? | V55: =MIN(V39:V43,V27:V31,V15:V19) -> #VALUE! | W55: =MIN(W39:W43,W27:W31,W15:W19) -> #VALUE! | X55: =MIN(X39:X43,X27:X31,X15:X19) -> #VALUE! | Z55: =MIN(Z39:Z43,Z27:Z31,Z15:Z19) -> #VALUE!

Sheet WACC
A7: x | B7: Rolling WACC | K7: Equity Risk Premium
P8: Weights
D9: 2025 | E9: =+D9+1 -> 2026 | F9: =+E9+1 -> 2027 | G9: =+F9+1 -> 2028 | H9: =+G9+1 -> 2029 | M9: ERP | N9: 2025 | O9: =+N9+1 -> 2026 | P9: =+O9+1 -> 2027 | Q9: =+P9+1 -> 2028 | R9: =+Q9+1 -> 2029
B12: Equity: | K12: =+Segments!B17 -> USA | M12: 0.0433 | N12: =+Segments!AL17/Segments!AL$18 -> 1 | O12: =+Segments!AN17/Segments!AN$18 -> 1 | P12: =+Segments!AP17/Segments!AP$18 -> 1 | Q12: =+Segments!AR17/Segments!AR$18 -> 1 | R12: =+Segments!AT17/Segments!AT$18 -> 1
B13: Market Cap (in billions) | D13: =+Inputs!J13 -> 0.946398 | E13: 0.836 | F13: 0.803 | G13: 0.819 | H13: 0.839
B14: % of Equity | D14: =IFERROR(D13/D35,"") -> 0.0029646608 | E14: =IFERROR(E13/E35,"") -> 0.0026056926 | F14: =IFERROR(E13/F35,"") -> 0.0026059607 | G14: =IFERROR(F13/G35,"") -> 0.002502969 | H14: =IFERROR(G13/H35,"") -> 0.0025526822
B15: Risk-Free Rate | D15: 0.0371 | E15: 0.0371 | F15: 0.0371 | G15: 0.0371 | H15: 0.0371
B16: Beta | D16: =+Inputs!M18 -> 1.73 | E16: =+D17*(1+(E28/E13)*(1-E32)) -> 1.9931715 | F16: =+E17*(1+(F28/F13)*(1-F32)) -> 2.0743615 | G16: =+F17*(1+(G28/G13)*(1-G32)) -> 2.0339588 | H16: =+G17*(1+(H28/H13)*(1-H32)) -> 1.9856226
B17: Unlevered Beta | D17: =+D16/(1+(D28/D13)*(1-D32)) -> 0.0062526032 | E17: =+E16/(1+(E28/E13)*(1-E32)) -> 0.0062526032 | F17: =+F16/(1+(F28/F13)*(1-F32)) -> 0.0062526032 | G17: =+G16/(1+(G28/G13)*(1-G32)) -> 0.0062526032 | H17: =+H16/(1+(H28/H13)*(1-H32)) -> 0.0062526032
B18: Equity Risk Premium | D18: =+N18 -> 0.0433 | E18: =+O18 -> 0.0433 | F18: =+P18 -> 0.0433 | G18: =+Q18 -> 0.0433 | H18: =+R18 -> 0.0433 | K18: ERP | N18: =+SUMPRODUCT($M12:$M16,N12:N16) -> 0.0433 | O18: =+SUMPRODUCT($M12:$M16,O12:O16) -> 0.0433 | P18: =+SUMPRODUCT($M12:$M16,P12:P16) -> 0.0433 | Q18: =+SUMPRODUCT($M12:$M16,Q12:Q16) -> 0.0433 | R18: =+SUMPRODUCT($M12:$M16,R12:R16) -> 0.0433
B19: Ke (Cost of Equity) | D19: =IFERROR(+D15+D16*D18,"") -> 0.112009 | E19: =IFERROR(+E15+E16*E18,"") -> 0.12340433 | F19: =IFERROR(+F15+F16*F18,"") -> 0.12691985 | G19: =IFERROR(+G15+G16*G18,"") -> 0.12517042 | H19: =IFERROR(+H15+H16*H18,"") -> 0.12307746
B21: Preferred Equity: | K21: ROIC vs WACC
B22: Market Capitalization | D22: =IFERROR(Inputs!J14,0) -> 0 | E22: =+D22*(E13/D13) -> 0 | F22: =+E22*(F13/E13) -> 0 | G22: =+F22*(G13/F13) -> 0 | H22: =+G22*(H13/G13) -> 0
B23: % of Preferred Equity | D23: =+D22/D35 -> 0 | E23: =+E22/E35 -> 0 | F23: =+F22/F35 -> 0 | G23: =+G22/G35 -> 0 | H23: =+H22/H35 -> 0
B24: Preferred Dividends | D24: =+IS!AF50 -> 0 | E24: =D24 -> 0 | F24: =E24 -> 0 | G24: =F24 -> 0 | H24: =G24 -> 0
B25: Kp (Cost of Preferred Equity) | D25: =IFERROR(D24/D22,0) -> 0 | E25: =IFERROR(E24/E22,0) -> 0 | F25: =IFERROR(F24/F22,0) -> 0 | G25: =IFERROR(G24/G22,0) -> 0 | H25: =IFERROR(H24/H22,0) -> 0
B27: Debt:
B28: Debt (in millions) | C28: =+BS!AF38+BS!AF39+BS!AF44+BS!AF45 -> 332.052 | D28: =+BS!AI38+BS!AI39+BS!AI44+BS!AI45 -> 318.28 | E28: 320 | F28: 320 | G28: 320 | H28: 320
B29: % of Debt | D29: =IFERROR(D28/D35,"") -> 0.99703534 | E29: =IFERROR(E28/E35,"") -> 0.99739431 | F29: =IFERROR(F28/F35,"") -> 0.99749691 | G29: =IFERROR(G28/G35,"") -> 0.99744716 | H29: =IFERROR(H28/H35,"") -> 0.99738498
B30: Debt Spread | D30: =+D31-D15 -> -0.006815345 | E30: 0.0675 | F30: 0.0675 | G30: 0.0675 | H30: 0.0675
B31: Cost of Debt | D31: =+IS!AI36/WACC!D28 -> 0.030284655 | E31: =+E30+E15 -> 0.1046 | F31: =+F30+F15 -> 0.1046 | G31: =+G30+G15 -> 0.1046 | H31: =+H30+H15 -> 0.1046
B32: Tax Rate | D32: =+FCFF!Z124 -> 0.18025794 | E32: =+FCFF!AF124 -> 0.16981367 | F32: =+FCFF!AH124 -> 0.17 | G32: =+FCFF!AJ124 -> 0.17 | H32: =+FCFF!AL124 -> 0.17
B33: Kd (After-Tax Cost of Debt) | D33: =+D31*(1-D32) -> 0.024825606 | E33: =+E31*(1-E32) -> 0.08683749 | F33: =+F31*(1-F32) -> 0.086818 | G33: =+G31*(1-G32) -> 0.086818 | H33: =+H31*(1-H32) -> 0.086818
B35: Total | D35: =+D13+D24+D28 -> 319.2264 | E35: =+E13+E24+E28 -> 320.836 | F35: =+F13+F24+F28 -> 320.803 | G35: =+G13+G24+G28 -> 320.819 | H35: =+H13+H24+H28 -> 320.839
B37: Country/Conglomerate/... Risk Premium | D37: 0 | E37: 0 | F37: 0 | G37: 0 | H37: 0
A39: x | B39: WACC | D39: =+D19*D14+D25*D23+D33*D29+D37 -> 0.025084075 | E39: =+E19*E14+E25*E23+E33*E29+E37 -> 0.086932772 | F39: =+F19*F14+F25*F23+F33*F29+F37 -> 0.086931435 | G39: =+G19*G14+G25*G23+G33*G29+G37 -> 0.086909665 | H39: =+H19*H14+H25*H23+H33*H29+H37 -> 0.086905147
B41: NOPAT | D41: =+FCFF!Z126 -> 143.24968 | E41: =+FCFF!AF126 -> 170.00085 | F41: =+FCFF!AH126 -> 251.5526 | G41: =+FCFF!AJ126 -> 323.38939 | H41: =+FCFF!AL126 -> 412.45715
B42: Total Payout | D42: =+FCFF!Z112+FCFF!Z115 -> -2.409 | E42: =+FCFF!AF112+FCFF!AF115 -> -2.315961 | F42: =+FCFF!AH112+FCFF!AH115 -> -3.5465779 | G42: =+FCFF!AJ112+FCFF!AJ115 -> -5.7016816 | H42: =+FCFF!AL112+FCFF!AL115 -> -8.3737146
B43: Book Value of Equity | C43: =+BS!AF54 -> 234.213 | D43: =+C43+D41+D42 -> 375.05368 | E43: =+D43+E41+E42 -> 542.73857 | F43: =+E43+F41+F42 -> 790.7446 | G43: =+F43+G41+G42 -> 1108.4323 | H43: =+G43+H41+H42 -> 1512.5157
B44: Invested Capital | C44: =+C43+C28 -> 566.265 | D44: =+D43+D28 -> 693.33368 | E44: =+E43+E28 -> 862.73857 | F44: =+F43+F28 -> 1110.7446 | G44: =+G43+G28 -> 1428.4323 | H44: =+H43+H28 -> 1832.5157
A45: x | B45: ROIC | D45: =+D41/((D44+C44)/2) -> 0.2274529 | E45: =+E41/((E44+D44)/2) -> 0.21849994 | F45: =+F41/((F44+E44)/2) -> 0.2549326 | G45: =+G41/((G44+F44)/2) -> 0.25471986 | H45: =+H41/((H44+G44)/2) -> 0.25296763
W49: ,

Sheet FCFF
A7: x | B7: Market Assumptions
D8: 2022 | J8: =D8+1 -> 2023 | P8: =J8+1 -> 2024 | V8: =P8+1 -> 2025 | AB8: =V8+1 -> 2026 | AH8: =AB8+1 -> 2027 | AJ8: =+AH8+1 -> 2028 | AL8: =+AJ8+1 -> 2029
D9: Q1 | E9: Q2 | F9: Q3 | G9: Q4 | H9: FY | J9: Q1 | K9: Q2 | L9: Q3 | M9: Q4 | N9: FY | P9: Q1 | Q9: Q2 | R9: Q3 | S9: Q4 | T9: FY | V9: Q1 | W9: Q2 | X9: Q3 | Y9: Q4 | Z9: FY | AB9: Q1 | AC9: Q2 | AD9: Q3 | AE9: Q4 | AF9: FY | AH9: FY | AJ9: FY | AL9: FY
B10: Average receivables | D10: =AVERAGE(D11:D12) -> 339 | E10: =AVERAGE(E11:E12) -> 369 | F10: =AVERAGE(F11:F12) -> 401 | G10: =AVERAGE(G11:G12) -> 403 | H10: =AVERAGE(H11:H12) -> 420.5 | J10: =AVERAGE(J11:J12) -> 386.5 | K10: =AVERAGE(K11:K12) -> 384 | L10: =AVERAGE(L11:L12) -> 407 | M10: =AVERAGE(M11:M12) -> 416.5 | N10: =AVERAGE(N11:N12) -> 460 | P10: =AVERAGE(P11:P12) -> 394 | Q10: =AVERAGE(Q11:Q12) -> 379 | R10: =AVERAGE(R11:R12) -> 400.5 | S10: =AVERAGE(S11:S12) -> 419.5 | T10: =AVERAGE(T11:T12) -> 468.5 | V10: =AVERAGE(V11:V12) -> 416 | W10: =AVERAGE(W11:W12) -> 422.5 | X10: =AVERAGE(X11:X12) -> 446.03126 | Y10: =AVERAGE(Y11:Y12) -> 463.33765 | Z10: =AVERAGE(Z11:Z12) -> 534.675 | AB10: =AVERAGE(AB11:AB12) -> 480.28846 | AC10: =AVERAGE(AC11:AC12) -> 499.37678 | AD10: =AVERAGE(AD11:AD12) -> 524.11626 | AE10: =AVERAGE(AE11:AE12) -> 552.92393 | AF10: =AVERAGE(AF11:AF12) -> 629.32152 | AH10: =AVERAGE(AH11:AH12) -> 763.64363 | AJ10: =AVERAGE(AJ11:AJ12) -> 980.06516 | AL10: =AVERAGE(AL11:AL12) -> 1237.8117
B11: Beginning Receivable | D11: - | E11: 339 | F11: 399 | G11: 403 | H11: 384 | J11: 403 | K11: 370 | L11: 398 | M11: =L12 -> 416 | N11: 457 | P11: 417 | Q11: 371 | R11: 387 | S11: 414 | T11: =463 -> 463 | V11: 425 | W11: 407 | X11: 438 | Y11: =X12 -> 454.06253 | Z11: =T12 -> 474 | AB11: =Y12 -> 472.61277 | AC11: =AB12 -> 487.96415 | AD11: =AC12 -> 510.78942 | AE11: =AD12 -> 537.44311 | AF11: =Z12 -> 595.35 | AH11: =AF12 -> 663.29305 | AJ11: =AH12 -> 863.99421 | AL11: =AJ12 -> 1096.1361
B12: Ending Receivables (Fair Value) | D12: 339 | E12: 399 | F12: 403 | G12: 403 | H12: 457 | J12: 370 | K12: 398 | L12: 416 | M12: 417 | N12: 463 | P12: 371 | Q12: 387 | R12: 414 | S12: 425 | T12: 474 | V12: 407 | W12: 438 | X12: =X11+X14-X15-X16 -> 454.06253 | Y12: =Y11+Y14-Y15-Y16 -> 472.61277 | Z12: =Z11+Z14-Z15-Z16 -> 595.35 | AB12: =AB11+AB14-AB15-AB16 -> 487.96415 | AC12: =AC11+AC14-AC15-AC16 -> 510.78942 | AD12: =AD11+AD14-AD15-AD16 -> 537.44311 | AE12: =AE11+AE14-AE15-AE16 -> 568.40475 | AF12: =AF11+AF14-AF15-AF16 -> 663.29305 | AH12: =AH11+AH14-AH15-AH16 -> 863.99421 | AJ12: =AJ11+AJ14-AJ15-AJ16 -> 1096.1361 | AL12: =AL11+AL14-AL15-AL16 -> 1379.4872
B13: Retained Originations | D13: N/A | E13: N/A | F13: N/A | G13: N/A | H13: N/A | J13: 156 | K13: 195 | L13: 191 | M13: =N13-J13-K13-L13 -> 191 | N13: 733 | P13: 153 | Q13: 189 | R13: 219 | S13: =T13-P13-Q13-R13 -> 162 | T13: 723 | V13: 169 | W13: 206 | X13: =(R13+S13+V13+W13)/4 -> 189 | Y13: =(S13+R13+W13+X13)/4 -> 194 | Z13: =SUM(V13:Y13) -> 758 | AB13: =(V13+W13+X13+Y13)/4 -> 189.5 | AC13: =(W13+X13+Y13+AB13)/4 -> 194.625 | AD13: =(X13+Y13+AB13+AC13)/4 -> 191.78125 | AE13: =(Y13+AB13+AC13+AD13)/4 -> 192.47656 | AF13: =SUM(AB13:AE13) -> 768.38281 | AH13: =AF13*(AF13/Z13) -> 778.90785 | AJ13: =AH13*(AH13/AF13) -> 789.57705 | AL13: =AJ13*(AJ13/AH13) -> 800.39239
B14: Total Net originations | D14: 163 | E14: 225 | F14: 182 | G14: =H14-D14-E14-F14 -> 189 | H14: 759 | J14: 160 | K14: 201 | L14: 196 | M14: =N14-J14-K14-L14 -> 191 | N14: 748 | P14: 164 | Q14: 206 | R14: 219 | S14: =T14-P14-Q14-R14 -> 213 | T14: 802 | V14: 190 | W14: 234 | X14: =(R14+S14+V14+W14)/4 -> 214 | Y14: =(S14+V14+W14+X14)/4 -> 212.75 | Z14: =SUM(V14:Y14) -> 850.75 | AB14: =Y14*1.05 -> 223.3875 | AC14: =AB14*1.05 -> 234.55688 | AD14: =AC14*1.05 -> 246.28472 | AE14: =AD14*1.05 -> 258.59895 | AF14: =SUM(AB14:AE14) -> 962.82805 | AH14: =AF14*(1.05)^4 -> 1170.3235 | AJ14: =AH14*(1.05)^4 -> 1422.5355 | AL14: =AJ14*(1.05)^4 -> 1729.1008
B15: Repayment | D15: 108 | E15: 103 | F15: 110 | G15: =H15-D15-E15-F15 -> 113 | H15: 434 | J15: 130 | K15: 119 | L15: 119 | M15: =N15-J15-K15-L15 -> 118 | N15: 486 | P15: 137 | Q15: 128 | R15: 128 | S15: =T15-P15-Q15-R15 -> 125 | T15: 518 | V15: 137 | W15: 124 | X15: =X18*X11 -> 137.93747 | Y15: =Y18*Y11 -> 141.19975 | Z15: =Z18*Z11 -> 521.4 | AB15: =AB18*AB11 -> 148.03612 | AC15: =AC18*AC11 -> 151.73161 | AD15: =AD18*AD11 -> 159.63102 | AE15: =AE18*AE11 -> 167.63732 | AF15: =AF18*AF11 -> 654.885 | AH15: =AH18*AH11 -> 729.62235 | AJ15: =AJ18*AJ11 -> 950.39363 | AL15: =AL18*AL11 -> 1205.7497 | AS15: 2022 | AT15: =+AS15+1 -> 2023 | AU15: =+AT15+1 -> 2024 | AV15: =+AU15+1 -> 2025 | AW15: =+AV15+1 -> 2026 | AX15: =+AW15+1 -> 2027 | AY15: =+AX15+1 -> 2028 | AZ15: =+AY15+1 -> 2029
B16: Net Charge Off | D16: 50 | E16: 42 | F16: 71 | G16: =H16-D16-E16-F16 -> 69 | H16: 232 | J16: 65 | K16: 44 | L16: 57 | M16: =N16-J16-K16-L16 -> 65 | N16: 231 | P16: 64 | Q16: 40 | R16: 45 | S16: =T16-P16-Q16-R16 -> 57 | T16: 206 | V16: 49 | W16: 46 | X16: 60 | Y16: =(S16+V16+W16+X16)/4 -> 53 | Z16: =SUM(V16:Y16) -> 208 | AB16: 60 | AC16: 60 | AD16: 60 | AE16: 60 | AF16: =SUM(AB16:AE16) -> 240 | AH16: 240 | AJ16: 240 | AL16: 240 | AR16: EBITDA | AS16: =H61+H128 -> 45.972 | AT16: =N61+N128 -> 118.63 | AU16: =T61+T128 -> 160.889 | AV16: =Z61+Z128 -> 181.10565 | AW16: =AF61+AF128 -> 211.71607 | AX16: =AH61+AH128 -> 308.89122 | AY16: =AJ61+AJ128 -> 395.44157 | AZ16: =AL61+AL128 -> 502.75213
B17: Average yield | D17: 1.199 | E17: 1.193 | F17: 1.203 | G17: =AVERAGE(F17,H17) -> 1.2015 | H17: 1.2 | J17: 1.263 | K17: 1.288 | L17: 1.285 | M17: =AVERAGE(L17,N17) -> 1.279 | N17: 1.273 | P17: 1.295 | Q17: 1.348 | R17: 1.339 | S17: =AVERAGE(R17,T17) -> 1.3265 | T17: 1.314 | V17: 1.358 | W17: 1.361 | X17: =(R17+S17+V17+W17)/4 -> 1.346125 | Y17: =(S17+V17+W17+X17)/4 -> 1.3479062 | Z17: =SUM(V17:Y17)/4 -> 1.3532578 | AB17: =(V17+W17+X17+Y17)/4 -> 1.3532578 | AC17: =(W17+X17+Y17+AB17)/4 -> 1.3520723 | AD17: =(X17+Y17+AB17+AC17)/4 -> 1.3498403 | AE17: =(Y17+AB17+AC17+AD17)/4 -> 1.3507692 | AF17: =SUM(AB17:AE17)/4 -> 1.3514849 | AH17: =(AF17+T17+Z17+N17)/4 -> 1.3229357 | AJ17: =(AF17+AH17+Z17+N17)/4 -> 1.3251696 | AL17: =(AJ17+AH17+AF17+Z17)/4 -> 1.338212 | AR17: FCFF | AS17: =H136 -> 22.875883 | AT17: =N136 -> 87.99761 | AU17: =T136 -> 134.14672 | AV17: =Z136 -> 131.95953 | AW17: =AF136 -> 158.1875 | AX17: =AH136 -> 229.36175 | AY17: =AJ136 -> 295.58581 | AZ17: =AL136 -> 374.28245
B18: Repayment rate | D18: =D15/D12 -> 0.31858407 | E18: =E15/E11 -> 0.30383481 | F18: =F15/F11 -> 0.27568922 | G18: =G15/G11 -> 0.28039702 | H18: =H15/H11 -> 1.1302083 | J18: =J15/J11 -> 0.32258065 | K18: =K15/K11 -> 0.32162162 | L18: =L15/L11 -> 0.29899497 | M18: =M15/M11 -> 0.28365385 | N18: =N15/N11 -> 1.0634573 | P18: =P15/P11 -> 0.32853717 | Q18: =Q15/Q11 -> 0.34501348 | R18: =R15/R11 -> 0.33074935 | S18: =S15/S11 -> 0.30193237 | T18: =T15/T11 -> 1.1187905 | V18: =V15/V11 -> 0.32235294 | W18: =W15/W11 -> 0.3046683 | X18: =(R18+S18+V18+W18)/4 -> 0.31492574 | Y18: =(S18+V18+W18+X18)/4 -> 0.31096984 | Z18: 1.1 | AB18: =(V18+W18+X18+Y18)/4 -> 0.31322921 | AC18: =(W18+X18+Y18+AB18)/4 -> 0.31094827 | AD18: =(X18+Y18+AB18+AC18)/4 -> 0.31251826 | AE18: =(Y18+AB18+AC18+AD18)/4 -> 0.3119164 | AF18: 1.1 | AH18: =AF18*(AF18/Z18) -> 1.1 | AJ18: =AH18*(AH18/AF18) -> 1.1 | AL18: =AJ18*(AJ18/AH18) -> 1.1 | AR18: Revenue Growth | AS18: =H32 -> 0.29748244 | AT18: =N32 -> 0.12385754 | AU18: =T32 -> 0.033429676 | AV18: =Z32 -> 0.37567304 | AW18: =AF32 -> 0.1754749 | AX18: =AH32 -> 0.18780645 | AY18: =+AJ32 -> 0.28557363 | AZ18: =+AL32 -> 0.27541957
B21: Revenue | X21: =X17*X10*0.25 -> 150.10346 | Y21: =Y17*Y10*0.25 -> 156.13393 | Z21: =Z17*Z10 -> 723.55312 | AB21: =AB17*AB10*0.25 -> 162.48853 | AC21: =AC17*AC10*0.25 -> 168.79837 | AD21: =AD17*AD10*0.25 -> 176.86832 | AE21: =AE17*AE10*0.25 -> 186.71815 | AF21: =AF17*AF10 -> 850.51853 | AH21: =AH17*AH10 -> 1010.2514 | AJ21: =AJ17*AJ10 -> 1298.7526 | AL21: =AL17*AL10 -> 1656.4544
A23: x | B23: Operating Assumptions
D24: =D$8 -> 2022 | E24: =F24 -> 0 | F24: =F$8 -> 0 | G24: =F24 -> 0 | H24: =F24 -> 0 | J24: =J$8 -> 2023 | K24: =L24 -> 0 | L24: =L$8 -> 0 | M24: =L24 -> 0 | N24: =L24 -> 0 | P24: =P$8 -> 2024 | Q24: =R24 -> 0 | R24: =R$8 -> 0 | S24: =R24 -> 0 | T24: =R24 -> 0 | V24: =V$8 -> 2025 | W24: =X24 -> 0 | X24: =X$8 -> 0 | Y24: =X24 -> 0 | Z24: =X24 -> 0 | AB24: =AB$8 -> 2026 | AC24: =AD24 -> 0 | AD24: =AD$8 -> 0 | AE24: =AD24 -> 0 | AF24: =AD24 -> 0 | AH24: =AH$8 -> 2027 | AJ24: =AJ$8 -> 2028 | AL24: =AL$8 -> 2029 | AM24: =AN24 -> 0
D25: Q1 | E25: Q2 | F25: Q3 | G25: Q4 | H25: FY | J25: Q1 | K25: Q2 | L25: Q3 | M25: Q4 | N25: FY | P25: Q1 | Q25: Q2 | R25: Q3 | S25: Q4 | T25: FY | V25: Q1 | W25: Q2 | X25: Q3 | Y25: Q4 | Z25: FY | AB25: Q1 | AC25: Q2 | AD25: Q3 | AE25: Q4 | AF25: FY | AH25: FY | AJ25: FY | AL25: FY
B28: Income Statement
B31: Revenue | D31: =IS!P18 -> 100.336 | E31: =IS!Q18 -> 107.873 | F31: =IS!R18 -> 123.605 | G31: =IS!S18 -> 120.03 | H31: =IS!T18 -> 452.859 | J31: =IS!V18 -> 120.374 | K31: =IS!W18 -> 122.486 | L31: =IS!X18 -> 133.165 | M31: =IS!Y18 -> 132.924 | N31: =IS!Z18 -> 508.949 | P31: =IS!AB18 -> 127.343 | Q31: =IS!AC18 -> 126.304 | R31: =IS!AD18 -> 136.593 | S31: =IS!AE18 -> 135.723 | T31: =IS!AF18 -> 525.963 | V31: =IS!AH18 -> 140.268 | W31: =IS!AI18 -> 142.443 | X31: =X21 -> 150.10346 | Y31: =Y21 -> 156.13393 | Z31: =Z21 -> 723.55312 | AB31: =AB21 -> 162.48853 | AC31: =AC21 -> 168.79837 | AD31: =AD21 -> 176.86832 | AE31: =AE21 -> 186.71815 | AF31: =AF21 -> 850.51853 | AH31: =AH21 -> 1010.2514 | AJ31: =AJ21 -> 1298.7526 | AL31: =AL21 -> 1656.4544
B32: % of growth | D32: =D31/IS!J18-1 -> #DIV/0! | E32: =E31/IS!K18-1 -> #DIV/0! | F32: =F31/IS!L18-1 -> 0.35164246 | G32: =G31/IS!M18-1 -> 0.25085975 | H32: =H31/IS!N18-1 -> 0.29748244 | J32: =J31/IS!P18-1 -> 0.19970898 | K32: =K31/IS!Q18-1 -> 0.13546485 | L32: =L31/IS!R18-1 -> 0.07734315 | M32: =M31/IS!S18-1 -> 0.10742314 | N32: =N31/H31-1 -> 0.12385754 | P32: =P31/IS!V18-1 -> 0.057894562 | Q32: =Q31/IS!W18-1 -> 0.031170909 | R32: =R31/IS!X18-1 -> 0.0257425 | S32: =S31/IS!Y18-1 -> 0.021057145 | T32: =T31/N31-1 -> 0.033429676 | V32: =V31/IS!AB18-1 -> 0.10149753 | W32: =W31/IS!AC18-1 -> 0.12777901 | X32: =X31/IS!AD18-1 -> 0.098910327 | Y32: =Y31/IS!AE18-1 -> 0.15038666 | Z32: =Z31/T31-1 -> 0.37567304 | AB32: =AB31/IS!AH18-1 -> 0.15841481 | AC32: =AC31/IS!AI18-1 -> 0.18502401 | AD32: =AD31/X31-1 -> 0.17830941 | AE32: =AE31/Y31-1 -> 0.19588452 | AF32: =AF31/Z31-1 -> 0.1754749 | AH32: =AH31/AF31-1 -> 0.18780645 | AJ32: =AJ31/AH31-1 -> 0.28557363 | AL32: =AL31/AJ31-1 -> 0.27541957
B34: Cost of Goods & Services | D34: =IS!P21 -> 23.402 | E34: =IS!Q21 -> 29.396 | F34: =IS!R21 -> 24.728 | G34: =IS!S21 -> 26.348 | H34: =IS!T21 -> 103.874 | J34: =IS!V21 -> 24.289 | K34: =IS!W21 -> 27.014 | L34: =IS!X21 -> 29.141 | M34: =IS!Y21 -> 27.307 | N34: =IS!Z21 -> 107.751 | P34: =IS!AB21 -> 41.802 | Q34: =IS!AC21 -> 25.448 | R34: =IS!AD21 -> 26.58 | S34: =IS!AE21 -> 28.065 | T34: =IS!AF21 -> 101.035 | V34: =IS!AH21 -> 22.165 | W34: =IS!AI21 -> 23.053 | X34: =(X35+Sensitivity!$U$39)*X$31 -> 27.064902 | Y34: =(Y35+Sensitivity!$U$39)*Y$31 -> 27.594677 | Z34: =SUM(V34:Y34) -> 99.877578 | AB34: =(AB35+Sensitivity!$U$39)*AB$31 -> 27.49731 | AC34: =(AC35+Sensitivity!$U$39)*AC$31 -> 29.038041 | AD34: =(AD35+Sensitivity!$U$39)*AD$31 -> 30.876772 | AE34: =(AE35+Sensitivity!$U$39)*AE$31 -> 32.328673 | AF34: =SUM(AB34:AE34) -> 119.7408 | AH34: =(AH35+Sensitivity!$U$39)*AH$31 -> 140.84081 | AJ34: =(AJ35+Sensitivity!$U$39)*AJ$31 -> 181.95347 | AL34: =(AL35+Sensitivity!$U$39)*AL$31 -> 232.06702
B35: % of sales | D35: =D34/D31 -> 0.23323633 | E35: =E34/E31 -> 0.27250563 | F35: =F34/F31 -> 0.20005663 | G35: =G34/G31 -> 0.21951179 | H35: =H34/H31 -> 0.22937382 | J35: =J34/J31 -> 0.20177945 | K35: =K34/K31 -> 0.22054765 | L35: =L34/L31 -> 0.21883378 | M35: =M34/M31 -> 0.20543318 | N35: =N34/N31 -> 0.21171276 | P35: =P34/P31 -> 0.32826304 | Q35: =Q34/Q31 -> 0.20148214 | R35: =R34/R31 -> 0.1945927 | S35: =S34/S31 -> 0.20678146 | T35: =T34/T31 -> 0.19209526 | V35: =V34/V31 -> 0.15801894 | W35: =W34/W31 -> 0.16184017 | X35: =AVERAGE(V35:W35,R35:S35) -> 0.18030832 | Y35: =AVERAGE(V35:X35,S35) -> 0.17673722 | Z35: =Z34/Z$31 -> 0.13803766 | AB35: =AVERAGE(V35:Y35) -> 0.16922616 | AC35: =AVERAGE(W35:Y35,AB35) -> 0.17202797 | AD35: =AVERAGE(X35:Y35,AB35:AC35) -> 0.17457492 | AE35: =AVERAGE(AB35:AD35,Y35) -> 0.17314157 | AF35: =AF34/AF$31 -> 0.14078564 | AH35: =AVERAGE(AF35,Z35) -> 0.13941165 | AJ35: =AVERAGE(AF35:AH35) -> 0.14009864 | AL35: =AVERAGE(AF35:AJ35) -> 0.14009864
B37: COGS Depreciation & Amortization | D37: =IS!P22 -> 0 | E37: =IS!Q22 -> 0 | F37: =IS!R22 -> 0 | G37: =IS!S22 -> 0 | H37: =IS!T22 -> 0 | J37: =IS!V22 -> 0 | K37: =IS!W22 -> 0 | L37: =IS!X22 -> 0 | M37: =IS!Y22 -> 0 | N37: =IS!Z22 -> 0 | P37: =IS!AB22 -> 0 | Q37: =IS!AC22 -> 0 | R37: =IS!AD22 -> 0 | S37: =IS!AE22 -> 0 | T37: =IS!AF22 -> 0 | V37: =IS!AH22 -> 0 | W37: =IS!AI22 -> 0 | X37: =IS!AJ22 -> 0 | Y37: =IS!AK22 -> 0 | Z37: =IS!AL79 -> 0 | AA37: =IS!AM79 -> 0 | AB37: =IS!AN79 -> 0 | AC37: =IS!AO79 -> 0 | AD37: =IS!AP79 -> 0 | AE37: =IS!AQ79 -> 0 | AF37: =IS!AR79 -> 0 | AG37: =IS!AS79 -> 0 | ... AL37: =IS!AX79 -> 0
B38: % of cost of goods & services | D38: =D37/D34 -> 0 | E38: =E37/E34 -> 0 | F38: =F37/F34 -> 0 | G38: =G37/G34 -> 0 | H38: =H37/H34 -> 0 | J38: =J37/J34 -> 0 | K38: =K37/K34 -> 0 | L38: =L37/L34 -> 0 | M38: =M37/M34 -> 0 | N38: =N37/N34 -> 0 | P38: =P37/P34 -> 0 | Q38: =Q37/Q34 -> 0 | R38: =R37/R34 -> 0 | S38: =S37/S34 -> 0 | T38: =T37/T34 -> 0 | V38: =V37/V34 -> 0 | W38: =W37/W34 -> 0 | X38: 0 | Y38: 0 | Z38: =Z37/Z$34 -> 0 | AB38: 0 | AC38: 0 | AD38: 0 | AE38: 0 | AF38: 0 | AH38: 0 | AJ38: 0 | AL38: 0
B40: Gross Profit | D40: =IS!P24 -> 76.934 | E40: =IS!Q24 -> 78.477 | F40: =IS!R24 -> 98.877 | G40: =IS!S24 -> 93.682 | H40: =IS!T24 -> 348.985 | J40: =IS!V24 -> 96.085 | K40: =IS!W24 -> 95.472 | L40: =IS!X24 -> 104.024 | M40: =IS!Y24 -> 105.617 | N40: =IS!Z24 -> 401.198 | P40: =IS!AB24 -> 85.541 | Q40: =IS!AC24 -> 100.856 | R40: =IS!AD24 -> 110.013 | S40: =IS!AE24 -> 107.658 | T40: =IS!AF24 -> 424.928 | V40: =IS!AH24 -> 118.103 | W40: =IS!AI24 -> 119.39 | X40: =X31-X34-X37 -> 123.03856 | Y40: =Y31-Y34-Y37 -> 128.53925 | Z40: =SUM(V40:Y40) -> 489.07081 | AB40: =AB31-AB34-AB37 -> 134.99122 | AC40: =AC31-AC34-AC37 -> 139.76033 | AD40: =AD31-AD34-AD37 -> 145.99155 | AE40: =AE31-AE34-AE37 -> 154.38948 | AF40: =SUM(AB40:AE40) -> 575.13257 | AH40: =AH31-AH34-AH37 -> 869.41058 | AJ40: =AJ31-AJ34-AJ37 -> 1116.7991 | AL40: =AL31-AL34-AL37 -> 1424.3874
B41: % of sales | D41: =D40/D31 -> 0.76676367 | E41: =E40/E31 -> 0.72749437 | F41: =F40/F31 -> 0.79994337 | G41: =G40/G31 -> 0.78048821 | H41: =H40/H31 -> 0.77062618 | J41: =J40/J31 -> 0.79822055 | K41: =K40/K31 -> 0.77945235 | L41: =L40/L31 -> 0.78116622 | M41: =M40/M31 -> 0.79456682 | N41: =N40/N31 -> 0.78828724 | P41: =P40/P31 -> 0.67173696 | Q41: =Q40/Q31 -> 0.79851786 | R41: =R40/R31 -> 0.8054073 | S41: =S40/S31 -> 0.79321854 | T41: =T40/T31 -> 0.80790474 | V41: =V40/V31 -> 0.84198106 | W41: =W40/W31 -> 0.83815983 | X41: =X40/X31 -> 0.81969168 | Y41: =Y40/Y31 -> 0.82326278 | Z41: =Z40/Z$31 -> 0.67592937 | AB41: =AB40/AB31 -> 0.83077384 | AC41: =AC40/AC31 -> 0.82797203 | AD41: =AD40/AD31 -> 0.82542508 | AE41: =AE40/AE31 -> 0.82685843 | AF41: =AF40/AF$31 -> 0.67621404 | AH41: =AH40/AH31 -> 0.86058835 | AJ41: =AJ40/AJ31 -> 0.85990136 | AL41: =AL40/AL31 -> 0.85990136
B43: SG&A (Selling, General & Administrative) | D43: =IS!P27 -> 16.61 | E43: =IS!Q27 -> 22.371 | F43: =IS!R27 -> 15.841 | G43: =IS!S27 -> 28.356 | H43: =IS!T27 -> 70.159 | J43: =IS!V27 -> 13.639 | K43: =IS!W27 -> 16.737 | L43: =IS!X27 -> 17.825 | M43: =IS!Y27 -> 24.965 | N43: =IS!Z27 -> 64.205 | P43: =IS!AB27 -> 13.292 | Q43: =IS!AC27 -> 16.667 | R43: =IS!AD27 -> 17.159 | S43: =IS!AE27 -> 24.991 | T43: =IS!AF27 -> 64.261 | V43: =IS!AH27 -> 14.152 | W43: =IS!AI27 -> 15.813 | X43: =(X44+Sensitivity!$U$40)*X$31 -> 19.575711 | Y43: =(Y44+Sensitivity!$U$40)*Y$31 -> 20.549277 | Z43: =SUM(V43:Y43) -> 70.089988 | AB43: =(AB44+Sensitivity!$U$40)*AB$31 -> 19.252183 | AC43: =(AC44+Sensitivity!$U$40)*AC$31 -> 20.742117 | AD43: =(AD44+Sensitivity!$U$40)*AD$31 -> 22.258537 | AE43: =(AE44+Sensitivity!$U$40)*AE$31 -> 23.284947 | AF43: =SUM(AB43:AE43) -> 85.537784 | AH43: =(AH44+Sensitivity!$U$40)*AH$31 -> 112.58505 | AJ43: =(AJ44+Sensitivity!$U$40)*AJ$31 -> 139.96036 | AL43: =(AL44+Sensitivity!$U$40)*AL$31 -> 172.53975
B44: % of sales | D44: =D43/D31 -> 0.16554377 | E44: =E43/E31 -> 0.20738276 | F44: =F43/F31 -> 0.12815825 | G44: =G43/G31 -> 0.23624094 | H44: =H43/H31 -> 0.1549246 | J44: =J43/J31 -> 0.1133052 | K44: =K43/K31 -> 0.13664419 | L44: =L43/L31 -> 0.13385649 | M44: =M43/M31 -> 0.18781409 | N44: =N43/N31 -> 0.12615213 | P44: =P43/P31 -> 0.10437951 | Q44: =Q43/Q31 -> 0.1319594 | R44: =R43/R31 -> 0.12562137 | S44: =S43/S31 -> 0.18413239 | T44: =T43/T31 -> 0.1221778 | V44: =V43/V31 -> 0.10089258 | W44: =W43/W31 -> 0.11101283 | X44: =AVERAGE(V44:W44,R44:S44) -> 0.13041479 | Y44: =AVERAGE(W44:X44,V44,S44) -> 0.13161315 | Z44: =Z43/Z$31 -> 0.096869168 | AB44: =AVERAGE(V44:Y44) -> 0.11848333 | AC44: =AVERAGE(W44:Y44,AB44) -> 0.12288102 | AD44: =AVERAGE(AB44:AC44,X44:Y44) -> 0.12584807 | AE44: =AVERAGE(AB44:AD44,Y44) -> 0.12470639 | AF44: =AF43/AF$31 -> 0.10057133 | AH44: =AVERAGE(AF44,Z44,T44,N44) -> 0.11144261 | AJ44: =AVERAGE(AH44,AF44,Z44,T44) -> 0.10776523 | AL44: =AVERAGE(AJ44,AH44,AF44,Z44) -> 0.10416208
AJ45: =AVERAGE(AH44,AC44:AE44) -> 0.12121952
B46: R&D (Research & Development) | D46: =IS!P29 -> 3.135 | E46: =IS!Q29 -> 3.287 | F46: =IS!R29 -> 3.301 | G46: =IS!S29 -> 8.59 | H46: =IS!T29 -> 13.054 | J46: =IS!V29 -> 3.166 | K46: =IS!W29 -> 3.28 | L46: =IS!X29 -> 3.141 | M46: =IS!Y29 -> 9.696 | N46: =IS!Z29 -> 12.543 | P46: =IS!AB29 -> 3.058 | Q46: =IS!AC29 -> 2.963 | R46: =IS!AD29 -> 3.041 | S46: =IS!AE29 -> 8.275 | T46: =IS!AF29 -> 12.171 | V46: =IS!AH29 -> 2.961 | W46: =IS!AI29 -> 3.382 | X46: =X47*X40 -> 3.3738204 | Y46: =Y47*Y40 -> 3.517541 | Z46: =SUM(V46:Y46) -> 13.234361 | AB46: =AB47*AB40 -> 3.6510065 | AC46: =AC47*AC40 -> 3.8494847 | AD46: =AD47*AD40 -> 3.9829684 | AE46: =AE47*AE40 -> 4.1928048 | AF46: =SUM(AB46:AE46) -> 15.676264 | AH46: =AH47*AH40 -> 23.697792 | AJ46: =AJ47*AJ40 -> 30.412781 | AL46: =AL47*AL40 -> 38.849707
B47: % of gross profit | D47: =D46/D40 -> 0.040749214 | E47: =E46/E40 -> 0.041884883 | F47: =F46/F40 -> 0.033384913 | G47: =G46/G40 -> 0.091693175 | H47: =H46/H40 -> 0.037405619 | J47: =J46/J40 -> 0.032949992 | K47: =K46/K40 -> 0.034355623 | L47: =L46/L40 -> 0.030194955 | M47: =M46/M40 -> 0.091803403 | N47: =N46/N40 -> 0.031263865 | P47: =P46/P40 -> 0.035748939 | Q47: =Q46/Q40 -> 0.02937852 | R47: =R46/R40 -> 0.027642188 | S47: =S46/S40 -> 0.076863772 | T47: =T46/T40 -> 0.028642499 | V47: =V46/V40 -> 0.025071336 | W47: =W46/W40 -> 0.028327331 | X47: =AVERAGE(V47:W47,T47,R47) -> 0.027420838 | Y47: =AVERAGE(V47:X47,T47) -> 0.027365501 | Z47: =Z46/Z$40 -> 0.027060215 | AB47: =AVERAGE(V47:Y47) -> 0.027046252 | AC47: =AVERAGE(W47:Z47) -> 0.027543471 | AD47: =AVERAGE(X47:AA47) -> 0.027282185 | AE47: =AVERAGE(Y47:AB47) -> 0.027157323 | AF47: =AF46/AF$40 -> 0.027256784 | AH47: =AVERAGE(AB47:AE47) -> 0.027257308 | AI47: =AVERAGE(AC47:AF47) -> 0.027309941 | AJ47: =AVERAGE(AD47:AG47) -> 0.027232097 | AK47: =AVERAGE(AE47:AH47) -> 0.027223805 | AL47: =AVERAGE(AF47:AI47) -> 0.027274678
B49: D&A (Depreciation & Amortization) | D49: =IS!P28 -> 3.238 | E49: =IS!Q28 -> 3.366 | F49: =IS!R28 -> 3.452 | G49: =IS!S28 -> 0 | H49: =IS!T28 -> 13.581 | J49: =IS!V28 -> 3.391 | K49: =IS!W28 -> 3.317 | L49: =IS!X28 -> 3.119 | M49: =IS!Y28 -> 0 | N49: =IS!Z28 -> 12.735 | P49: =IS!AB28 -> 2.725 | Q49: =IS!AC28 -> 2.49 | R49: =IS!AD28 -> 2.28 | S49: =IS!AE28 -> 0 | T49: =IS!AF28 -> 9.621 | V49: =IS!AH28 -> 1.76 | W49: =IS!AI28 -> 1.502 | X49: =X94 -> 1.74474 | Y49: =Y94 -> 1.74474 | Z49: =SUM(V49:Y49) -> 6.75148 | AB49: =AB94 -> 1.74474 | AC49: =AC94 -> 1.74474 | AD49: =AD94 -> 1.74474 | AE49: =AE94 -> 1.74474 | AF49: =SUM(AB49:AE49) -> 6.97896 | AH49: =AH94 -> 5.8158 | AJ49: =AJ94 -> 5.8158 | AL49: =AL94 -> 5.8158
B50: % of net pp&e and intangibles excl. Goodwill | D50: =D49/(D79+D82) -> 0.10674843 | E50: =E49/(E79+E82) -> 0.11328375 | F50: =F49/(F79+F82) -> 0.11844634 | G50: =G49/(G79+G82) -> 0 | H50: =H49/(H79+H82) -> 0.49160211 | J50: =J49/(J79+J82) -> 0.13047828 | K50: =K49/(K79+K82) -> 0.13293524 | L50: =L49/(L79+L82) -> 0.13168672 | M50: =M49/(M79+M82) -> 0 | N50: =N49/(N79+N82) -> 0.56670523 | P50: =P49/(P79+P82) -> 0.12697451 | Q50: =Q49/(Q79+Q82) -> 0.11769711 | R50: =R49/(R79+R82) -> 0.10190855 | S50: =S49/(S79+S82) -> 0 | T50: =T49/(T79+T82) -> 0.39659508 | V50: =V49/(V79+V82) -> 0.066826138 | W50: =W49/(W79+W82) -> 0.051652395 | X50: =X95 -> 0.06 | Y50: =Y95 -> 0.06 | Z50: =Z49/( Z79+Z82) -> 0.17359118 | AB50: =AB95 -> 0.06 | AC50: =AC95 -> 0.06 | AD50: =AD95 -> 0.06 | AE50: =AE95 -> 0.06 | AF50: =AF95 -> 0.24 | AH50: =AH95 -> 0.2 | AJ50: =AJ95 -> 0.2 | AL50: =AL95 -> 0.2
B52: Depreciation | D52: =IS!P64 -> 0 | E52: =IS!Q64 -> 0 | F52: =IS!R64 -> 0 | G52: =IS!S64 -> 0 | H52: =IS!T64 -> 0 | J52: =IS!V64 -> 0 | K52: =IS!W64 -> 0 | L52: =IS!X64 -> 0 | M52: =IS!Y64 -> 0 | N52: =IS!Z64 -> 0 | P52: =IS!AB64 -> 0 | Q52: =IS!AC64 -> 0 | R52: =IS!AD64 -> 0 | S52: =IS!AE64 -> 0 | T52: =IS!AF64 -> 0 | V52: =IS!AH64 -> 0 | W52: =IS!AI64 -> 0 | X52: =X53*W79 -> 0 | Y52: =Y53*X79 -> 0 | Z52: =SUM(V52:Y52) -> 0 | AB52: =AB53*Y79 -> 0 | AC52: =AC53*AB79 -> 0 | AD52: =AD53*AC79 -> 0 | AE52: =AE53*AD79 -> 0 | AF52: =SUM(AB52:AE52) -> 0 | AH52: =AH53*AF79 -> 0 | AJ52: =AJ53*AH79 -> 0 | AL52: =AL53*AJ79 -> 0
B53: % of net pp&e | D53: =D52/D79 -> 0 | E53: =E52/E79 -> 0 | F53: =F52/F79 -> 0 | G53: =G52/G79 -> 0 | H53: =H52/H79 -> 0 | J53: =J52/J79 -> 0 | K53: =K52/K79 -> 0 | L53: =L52/L79 -> 0 | M53: =M52/M79 -> 0 | N53: =N52/N79 -> 0 | P53: =P52/P79 -> 0 | Q53: =Q52/Q79 -> 0 | R53: =R52/R79 -> 0 | S53: =S52/S79 -> 0 | T53: =T52/T79 -> 0 | V53: =V52/V79 -> 0 | W53: =W52/W79 -> 0 | X53: 0 | Y53: 0 | Z53: =Z52/Z79 -> 0 | AB53: 0 | AC53: 0 | AD53: 0 | AE53: 0 | AF53: =AF52/AF79 -> 0 | AH53: 0 | AJ53: 0 | AL53: 0
B55: Amortization | D55: =IS!P65 -> 0 | E55: =IS!Q65 -> 0 | F55: =IS!R65 -> 0 | G55: =IS!S65 -> 0 | H55: =IS!T65 -> 0 | J55: =IS!V65 -> 0 | K55: =IS!W65 -> 0 | L55: =IS!X65 -> 0 | M55: =IS!Y65 -> 0 | N55: =IS!Z65 -> 0 | P55: =IS!AB65 -> 0 | Q55: =IS!AC65 -> 0 | R55: =IS!AD65 -> 0 | S55: =IS!AE65 -> 0 | T55: =IS!AF65 -> 0 | V55: =IS!AH65 -> 0 | W55: =IS!AI65 -> 0 | X55: =X56*W82 -> 0 | Y55: =Y56*X82 -> 0 | Z55: =SUM(V55:Y55) -> 0 | AB55: =AB56*Y82 -> 0 | AC55: =AC56*AB82 -> 0 | AD55: =AD56*AC82 -> 0 | AE55: =AE56*AD82 -> 0 | AF55: =SUM(AB55:AE55) -> 0 | AH55: =AH56*AF82 -> 0 | AJ55: =AJ56*AH82 -> 0 | AL55: =AL56*AJ82 -> 0
B56: % of intangibles excl. goodwill | D56: =D55/D82 -> #DIV/0! | E56: =E55/E82 -> #DIV/0! | F56: =F55/F82 -> #DIV/0! | G56: =G55/G82 -> #DIV/0! | H56: =H55/H82 -> #DIV/0! | J56: =J55/J82 -> #DIV/0! | K56: =K55/K82 -> #DIV/0! | L56: =L55/L82 -> #DIV/0! | M56: =M55/M82 -> #DIV/0! | N56: =N55/N82 -> #DIV/0! | P56: =P55/P82 -> #DIV/0! | Q56: =Q55/Q82 -> #DIV/0! | R56: =R55/R82 -> #DIV/0! | S56: =S55/S82 -> #DIV/0! | T56: =T55/T82 -> #DIV/0! | V56: =V55/V82 -> #DIV/0! | W56: =W55/W82 -> #DIV/0! | Y56: 0 | Z56: =Z55/Z82 -> 0 | AB56: 0 | AC56: 0 | AD56: 0 | AE56: 0 | AF56: =AF55/AF82 -> 0
B58: Other Operating (Income) Expenses | D58: =IS!P30+IS!P32 -> 72.814 | E58: =IS!Q30+IS!Q32 -> 73.594 | F58: =IS!R30+IS!R32 -> 103.183 | G58: =IS!S30+IS!S32 -> 89.915 | H58: =IS!T30+IS!T32 -> 323.674 | J58: =IS!V30+IS!V32 -> 85.077 | K58: =IS!W30+IS!W32 -> 80.818 | L58: =IS!X30+IS!X32 -> 91.841 | M58: =IS!Y30+IS!Y32 -> 69.673 | N58: =IS!Z30+IS!Z32 -> 313.571 | P58: =IS!AB30+IS!AB32 -> 102.984 | Q58: =IS!AC30+IS!AC32 -> 73.897 | R58: =IS!AD30+IS!AD32 -> 77.054 | S58: =IS!AE30+IS!AE32 -> 65.834 | T58: =IS!AF30+IS!AF32 -> 288.642 | V58: =IS!AH30+IS!AH32 -> 80.351 | W58: =IS!AI30+IS!AI32 -> 76.438 | X58: =X59*X$31 -> 81.004687 | Y58: =Y59*Y$31 -> 83.304528 | Z58: =SUM(V58:Y58) -> 321.09821 | AB58: =AB59*AB$31 -> 79.11782 | AC58: =AC59*AC$31 -> 76.993735 | AD58: =AD59*AD$31 -> 81.131297 | AE58: =AE59*AE$31 -> 84.679207 | AF58: =SUM(AB58:AE58) -> 321.92206 | AH58: =AH59*AH$31 -> 325.02393 | AJ58: =AJ59*AJ$31 -> 355.16587 | AL58: =AL59*AL$31 -> 385.03767
B59: % of sales | D59: =D58/D31 -> 0.72570164 | E59: =E58/E31 -> 0.68222818 | F59: =F58/F31 -> 0.83478015 | G59: =G58/G31 -> 0.74910439 | H59: =H58/H31 -> 0.71473461 | J59: =J58/J31 -> 0.70677223 | K59: =K58/K31 -> 0.65981418 | L59: =L58/L31 -> 0.68967822 | M59: =M58/M31 -> 0.52415666 | N59: =N58/N31 -> 0.61611478 | P59: =P58/P31 -> 0.80871347 | Q59: =Q58/Q31 -> 0.58507252 | R59: =R58/R31 -> 0.56411383 | S59: =S58/S31 -> 0.48506149 | T59: =T58/T31 -> 0.54878765 | V59: =V58/V31 -> 0.57283914 | W59: =W58/W31 -> 0.53662167 | X59: =AVERAGE(V59:W59,R59:S59) -> 0.53965903 | Y59: =AVERAGE(V59:X59,S59) -> 0.53354533 | Z59: =Z58/Z$31 -> 0.44377974 | AB59: =V59*0.85 -> 0.48691327 | AC59: =W59*0.85 -> 0.45612842 | AD59: =X59*0.85 -> 0.45871017 | AE59: =Y59*0.85 -> 0.45351353 | AF59: =AF58/AF$31 -> 0.37850093 | AH59: =AF59*0.85 -> 0.32172579 | AJ59: =AH59*0.85 -> 0.27346692 | AL59: =AJ59*0.85 -> 0.23244689
B61: EBIT (Operating Income) | D61: =IS!P33 -> 5.287 | E61: =IS!Q33 -> 5.259 | F61: =IS!R33 -> -0.894 | G61: =IS!S33 -> -6.831 | H61: =IS!T33 -> 32.391 | J61: =IS!V33 -> 15.101 | K61: =IS!W33 -> 18.334 | L61: =IS!X33 -> 17.239 | M61: =IS!Y33 -> 28.59 | N61: =IS!Z33 -> 105.895 | P61: =IS!AB33 -> 5.284 | Q61: =IS!AC33 -> 30.287 | R61: =IS!AD33 -> 37.059 | S61: =IS!AE33 -> 36.623 | T61: =IS!AF33 -> 151.268 | V61: =IS!AH33 -> 41.044 | W61: =IS!AI33 -> 45.308 | X61: =X62*X31 -> 43.22362 | Y61: =Y62*Y31 -> 44.778546 | Z61: =SUM(V61:Y61) -> 174.35417 | AB61: =AB62*AB31 -> 48.155262 | AC61: =AC62*AC31 -> 50.183491 | AD61: =AD62*AD31 -> 51.663856 | AE61: =AE62*AE31 -> 54.734496 | AF61: =SUM(AB61:AE61) -> 204.73711 | AH61: =AH62*AH31 -> 303.07542 | AJ61: =AJ62*AJ31 -> 389.62577 | AL61: =AL62*AL31 -> 496.93633
B62: % of sales | D62: =D61/D31 -> 0.052692952 | E62: =E61/E31 -> 0.048751773 | F62: =F61/F31 -> -0.0072327171 | G62: =G61/G31 -> -0.056910772 | H62: =H61/H31 -> 0.071525574 | J62: =J61/J31 -> 0.12545068 | K62: =K61/K31 -> 0.14968241 | L62: =L61/L31 -> 0.12945594 | M62: =M61/M31 -> 0.21508531 | N62: =N61/N31 -> 0.20806603 | P62: =P61/P31 -> 0.041494232 | Q62: =Q61/Q31 -> 0.23979446 | R62: =R61/R31 -> 0.27130966 | S62: =S61/S31 -> 0.26983636 | T62: =T61/T31 -> 0.28760198 | V62: =V61/V31 -> 0.29261129 | W62: =W61/W31 -> 0.31807811 | X62: =AVERAGE(V62:W62,R62:S62) -> 0.28795885 | Y62: =AVERAGE(W62:X62,R62:S62) -> 0.28679574 | Z62: =Z61/Z$31 -> 0.24096941 | AB62: =AVERAGE(V62:Y62) -> 0.296361 | AC62: =AVERAGE(AB62,W62:Y62) -> 0.29729843 | AD62: =AVERAGE(AB62:AC62,X62:Y62) -> 0.29210351 | AE62: =AVERAGE(AB62:AD62,Y62) -> 0.29313967 | AF62: =AVERAGE(AB62:AE62) -> 0.29472565 | AH62: 0.3 | AJ62: 0.3 | AL62: 0.3
B64: Basic Weighted Average Shares | D64: =IS!P59 -> 13.5818 | E64: =IS!Q59 -> 13.5251 | F64: =IS!R59 -> 13.973 | G64: =IS!S59 -> 14.5632 | H64: =IS!T59 -> 13.9136 | J64: =IS!V59 -> 15.0373 | K64: =IS!W59 -> 15.6321 | L64: =IS!X59 -> 16.7723 | M64: =IS!Y59 -> 18.0876 | N64: =IS!Z59 -> 16.3912 | P64: =IS!AB59 -> 19.2054 | Q64: =IS!AC59 -> 19.6759 | R64: =IS!AD59 -> 20.248 | S64: =IS!AE59 -> 21.4425 | T64: =IS!AF59 -> 20.1456 | V64: =IS!AH59 -> 23.6918 | W64: =IS!AI59 -> 26.6103 | X64: =W64+X101 -> 26.661678 | Y64: =X64+Y101 -> 26.713842 | Z64: =AVERAGE(V64:Y64) -> 25.919405 | AB64: =Y64+AB101 -> 26.761029 | AC64: =AB64+AC101 -> 26.809852 | AD64: =AC64+AD101 -> 26.860226 | AE64: =AD64+AE101 -> 26.910697 | AF64: =AVERAGE(AB64:AE64) -> 26.835451 | AH64: =AE64+AH101 -> 27.078866 | AJ64: =AF64+AJ101 -> 27.053631 | AL64: =AH64+AL101 -> 27.289554
B65: Diluted Weighted Average Shares | D65: =IS!P60 -> 13.6355 | E65: =IS!Q60 -> 84.2831 | F65: =IS!R60 -> 13.973 | G65: =IS!S60 -> 14.5632 | H65: =IS!T60 -> 84.2561 | J65: =IS!V60 -> 15.1899 | K65: =IS!W60 -> 15.8738 | L65: =IS!X60 -> 17.0578 | M65: =IS!Y60 -> 18.0876 | N65: =IS!Z60 -> 16.3912 | P65: =IS!AB60 -> 86.2435 | Q65: =IS!AC60 -> 19.6759 | R65: =IS!AD60 -> 20.248 | S65: =IS!AE60 -> 21.4425 | T65: =IS!AF60 -> 20.1456 | V65: =IS!AH60 -> 23.6918 | W65: =IS!AI60 -> 26.6103 | X65: =W65 -> 26.6103 | Y65: =X65 -> 26.6103 | Z65: =AVERAGE(V65:Y65) -> 25.880675 | AB65: =Y65 -> 26.6103 | AC65: =AB65 -> 26.6103 | AD65: =AC65 -> 26.6103 | AE65: =AD65 -> 26.6103 | AF65: =AVERAGE(AB65:AE65) -> 26.6103 | AH65: =AF65 -> 26.6103 | AJ65: =AH65 -> 26.6103 | AL65: =AJ65 -> 26.6103
B67: Balance Sheet | D67: Q1 22 | E67: Q2 22 | F67: Q3 22 | G67: Q4 22 | H67: FY 22 | J67: Q1 23 | K67: Q2 23 | L67: Q3 23 | M67: Q4 23 | N67: FY 23 | P67: Q1 24 | Q67: Q2 24 | R67: Q3 24 | S67: Q4 24 | T67: FY 24 | V67: Q1 25 | W67: Q2 25 | X67: Q3 25 | Y67: Q4 25 | Z67: FY 25 | AB67: Q1 26 | AC67: Q2 26 | AD67: Q3 26 | AE67: Q4 26 | AF67: FY 26 | AH67: FY 27 | AJ67: FY 28 | AL67: FY 29
B70: Accounts Receivable | D70: =BS!P18 -> 0 | E70: =BS!Q18 -> 0 | F70: =BS!R18 -> 0 | G70: =BS!S18 -> 0 | H70: =BS!T18 -> 0 | J70: =BS!V18 -> 0 | K70: =BS!W18 -> 0 | L70: =BS!X18 -> 0 | M70: =BS!Y18 -> 0 | N70: =BS!Z18 -> 0 | P70: =BS!AB18 -> 0 | Q70: =BS!AC18 -> 0 | R70: =BS!AD18 -> 0 | S70: =BS!AE18 -> 0 | T70: =BS!AF18 -> 0 | V70: =BS!AH18 -> 0 | W70: =BS!AI18 -> 0 | X70: =X31*X71/92 -> 0 | Y70: =Y31*Y71/92 -> 0 | Z70: =Y70 -> 0 | AB70: =AB31*AB71/90 -> 0 | AC70: =AC31*AC71/91 -> 0 | AD70: =AD31*AD71/92 -> 0 | AE70: =AE31*AE71/92 -> 0 | AF70: =AE70 -> 0 | AH70: =AH31*AH71/365 -> 0 | AJ70: =AJ31*AJ71/366 -> 0 | AL70: =AL31*AL71/365 -> 0
B71: days sales outstanding | D71: =D70/D31*90 -> 0 | E71: =E70/E31*91 -> 0 | F71: =F70/F31*92 -> 0 | G71: =G70/G31*92 -> 0 | H71: =H70/H31*365 -> 0 | J71: =J70/J31*90 -> 0 | K71: =K70/K31*91 -> 0 | L71: =L70/L31*92 -> 0 | M71: =M70/M31*92 -> 0 | N71: =N70/N31*365 -> 0 | P71: =P70/P31*90 -> 0 | Q71: =Q70/Q31*91 -> 0 | R71: =R70/R31*92 -> 0 | S71: =S70/S31*92 -> 0 | T71: =T70/T31*365 -> 0 | V71: =V70/V31*90 -> 0 | W71: =W70/W31*91 -> 0 | X71: 0 | Y71: 0 | AB71: 0 | AC71: 0 | AD71: 0 | AE71: 0 | AF71: 0 | AH71: 0 | AJ71: 0 | AL71: 0
B73: Inventory | D73: =BS!P19 -> 0 | E73: =BS!Q19 -> 0 | F73: =BS!R19 -> 0 | G73: =BS!S19 -> 0 | H73: =BS!T19 -> 0 | J73: =BS!V19 -> 0 | K73: =BS!W19 -> 0 | L73: =BS!X19 -> 0 | M73: =BS!Y19 -> 0 | N73: =BS!Z19 -> 0 | P73: =BS!AB19 -> 0 | Q73: =BS!AC19 -> 0 | R73: =BS!AD19 -> 0 | S73: =BS!AE19 -> 0 | T73: =BS!AF19 -> 0 | V73: =BS!AH19 -> 0 | W73: =BS!AI19 -> 0 | X73: =X74*X34/92 -> 0 | Y73: =Y74*Y34/92 -> 0 | Z73: =Y73 -> 0 | AB73: =AB74*AB34/92 -> 0 | AC73: =AC74*AC34/92 -> 0 | AD73: =AD74*AD34/92 -> 0 | AE73: =AE74*AE34/92 -> 0 | AF73: =AE73 -> 0 | AH73: =AH74*AH34/365 -> 0 | AJ73: =AJ74*AJ34/366 -> 0 | AL73: =AL74*AL34/365 -> 0
B74: days inventory held | D74: =D73/D34*90 -> 0 | E74: =E73/E34*91 -> 0 | F74: =F73/F34*92 -> 0 | G74: =G73/G34*92 -> 0 | H74: =H73/H34*365 -> 0 | J74: =J73/J34*90 -> 0 | K74: =K73/K34*91 -> 0 | L74: =L73/L34*92 -> 0 | M74: =M73/M34*92 -> 0 | N74: =N73/N34*365 -> 0 | P74: =P73/P34*90 -> 0 | Q74: =Q73/Q34*91 -> 0 | R74: =R73/R34*92 -> 0 | S74: =S73/S34*92 -> 0 | T74: =T73/T34*365 -> 0 | V74: =V73/V34*90 -> 0 | W74: =W73/W34*91 -> 0 | X74: 0 | Y74: 0 | Z74: =Z73/Z34*365 -> 0 | AB74: 0 | AC74: 0 | AD74: 0 | AE74: 0 | AF74: =AF73/AF34*365 -> 0 | AH74: 0 | AJ74: 0 | AK74: 0 | AL74: 0
B76: Prepaid expenses and Other Current Assets | D76: =BS!P20 -> 32.921 | E76: =BS!Q20 -> 34.166 | F76: =BS!R20 -> 36.458 | G76: =BS!S20 -> 33.431 | H76: =BS!T20 -> 33.431 | J76: =BS!V20 -> 39.189 | K76: =BS!W20 -> 35.31 | L76: =BS!X20 -> 34.902 | M76: =BS!Y20 -> 42.152 | N76: =BS!Z20 -> 42.152 | P76: =BS!AB20 -> 41.538 | Q76: =BS!AC20 -> 34.215 | R76: =BS!AD20 -> 29.395 | S76: =BS!AE20 -> 26.944 | T76: =BS!AF20 -> 26.944 | V76: =BS!AH20 -> 32.814 | W76: =BS!AI20 -> 33.038 | X76: =X77*X$31 -> 33.007737 | Y76: =Y77*Y$31 -> 34.517237 | Z76: =Y76 -> 34.517237 | AB76: =AB77*AB$31 -> 36.83821 | AC76: =AC77*AC$31 -> 37.963832 | AD76: =AD77*AD$31 -> 39.467879 | AE76: =AE77*AE$31 -> 41.817489 | AF76: =AE76 -> 41.817489 | AH76: =AH77*AH$31 -> 48.932658 | AJ76: =AJ77*AJ$31 -> 63.381185 | AL76: =AL77*AL$31 -> 80.534915
B77: % of sales | D77: =D76/D31 -> 0.32810756 | E77: =E76/E31 -> 0.3167243 | F77: =F76/F31 -> 0.29495571 | G77: =G76/G31 -> 0.27852204 | H77: =H76/H31 -> 0.073822095 | J77: =J76/J31 -> 0.32556034 | K77: =K76/K31 -> 0.28827784 | L77: =L76/L31 -> 0.2620959 | M77: =M76/M31 -> 0.31711354 | N77: =N76/N31 -> 0.082821658 | P77: =P76/P31 -> 0.3261899 | Q77: =Q76/Q31 -> 0.27089403 | R77: =R76/R31 -> 0.21520136 | S77: =S76/S31 -> 0.19852199 | T77: =T76/T31 -> 0.051227938 | V77: =V76/V31 -> 0.23393789 | W77: =W76/W31 -> 0.23193839 | X77: =AVERAGE(V77,W77,R77:S77) -> 0.21989991 | Y77: =AVERAGE(V77:X77,S77) -> 0.22107454 | Z77: =Z76/Z$31 -> 0.047705187 | AB77: =AVERAGE(V77:Y77) -> 0.22671268 | AC77: =AVERAGE(W77:Y77,AB77) -> 0.22490638 | AD77: =AVERAGE(AB77:AC77,X77:Y77) -> 0.22314838 | AE77: =AVERAGE(AB77:AD77,Y77) -> 0.2239605 | AF77: =AF76/AF$31 -> 0.049167053 | AH77: =AVERAGE(AF77,Z77) -> 0.04843612 | AJ77: =AVERAGE(AF77:AH77) -> 0.048801586 | AL77: =AVERAGE(AH77:AJ77) -> 0.048618853
B79: Net PP&E (Property, Plant and Equipment) | D79: =BS!P24 -> 30.333 | E79: =BS!Q24 -> 29.713 | F79: =BS!R24 -> 29.144 | G79: =BS!S24 -> 27.626 | H79: =BS!T24 -> 27.626 | J79: =BS!V24 -> 25.989 | K79: =BS!W24 -> 24.952 | L79: =BS!X24 -> 23.685 | M79: =BS!Y24 -> 22.472 | N79: =BS!Z24 -> 22.472 | P79: =BS!AB24 -> 21.461 | Q79: =BS!AC24 -> 21.156 | R79: =BS!AD24 -> 22.373 | S79: =BS!AE24 -> 24.259 | T79: =BS!AF24 -> 24.259 | V79: =BS!AH24 -> 26.337 | W79: =BS!AI24 -> 29.079 | X79: =W79-X80*X106-X109-X52-X37 -> 29.079 | Y79: =X79-Y80*Y106-Y109-Y52-Y37 -> 29.079 | Z79: =Y79 -> 29.079 | AB79: =Y79-AB80*AB106-AB109-AB52-AB37 -> 29.079 | AC79: =AB79-AC80*AC106-AC109-AC52-AC37 -> 29.079 | AD79: =AC79-AD80*AD106-AD109-AD52-AD37 -> 29.079 | AE79: =AD79-AE80*AE106-AE109-AE52-AE37 -> 29.079 | AF79: =AE79 -> 29.079 | AH79: =AF79-AH80*AH106-AH109-AH52-AH37 -> 29.079 | AJ79: =AH79-AJ80*AJ106-AJ109-AJ52-AJ37 -> 29.079 | AL79: =AJ79-AL80*AL106-AL109-AL52-AL37 -> 29.079
B80: capex allocation rate | Z80: =AVERAGE(V80:Y80) -> #DIV/0! | AF80: =AVERAGE(AB80:AE80) -> #DIV/0!
B82: Intangibles | D82: =IF($B$82="Intangibles excl. Goodwill",BS!P29,BS!P27) -> 0 | E82: =IF($B$82="Intangibles excl. Goodwill",BS!Q29,BS!Q27) -> 0 | F82: =IF($B$82="Intangibles excl. Goodwill",BS!R29,BS!R27) -> 0 | G82: =IF($B$82="Intangibles excl. Goodwill",BS!S29,BS!S27) -> 0 | H82: =IF($B$82="Intangibles excl. Goodwill",BS!T29,BS!T27) -> 0 | J82: =IF($B$82="Intangibles excl. Goodwill",BS!V29,BS!V27) -> 0 | K82: =IF($B$82="Intangibles excl. Goodwill",BS!W29,BS!W27) -> 0 | L82: =IF($B$82="Intangibles excl. Goodwill",BS!X29,BS!X27) -> 0 | M82: =IF($B$82="Intangibles excl. Goodwill",BS!Y29,BS!Y27) -> 0 | N82: =IF($B$82="Intangibles excl. Goodwill",BS!Z29,BS!Z27) -> 0 | P82: =IF($B$82="Intangibles excl. Goodwill",BS!AB29,BS!AB27) -> 0 | Q82: =IF($B$82="Intangibles excl. Goodwill",BS!AC29,BS!AC27) -> 0 | R82: =IF($B$82="Intangibles excl. Goodwill",BS!AD29,BS!AD27) -> 0 | S82: =IF($B$82="Intangibles excl. Goodwill",BS!AE29,BS!AE27) -> 0 | T82: =IF($B$82="Intangibles excl. Goodwill",BS!AF29,BS!AF27) -> 0 | V82: =IF($B$82="Intangibles excl. Goodwill",BS!AH29,BS!AH27) -> 0 | W82: =IF($B$82="Intangibles excl. Goodwill",BS!AI29,BS!AI27) -> 0 | X82: =W82-(1-X80)*X106-X55+X83*X46 -> 4.8189584 | Y82: =X82-(1-Y80)*Y106-Y55+Y83*Y46 -> 9.8139904 | Z82: =Y82 -> 9.8139904 | AB82: =Y82-(1-AB80)*AB106-AB55+AB83*AB46 -> 15.176112 | AC82: =AB82-(1-AC80)*AC106-AC55+AC83*AC46 -> 20.746458 | AD82: =AC82-(1-AD80)*AD106-AD55+AD83*AD46 -> 26.583113 | AE82: =AD82-(1-AE80)*AE106-AE55+AE83*AE46 -> 32.744812 | AF82: =AE82 -> 32.744812 | AH82: =AF82-(1-AH80)*AH106-AH55+AH83*AH46 -> 67.093359 | AJ82: =AH82-(1-AJ80)*AJ106-AJ55+AJ83*AJ46 -> 112.5497 | AL82: =AJ82-(1-AL80)*AL106-AL55+AL83*AL46 -> 170.5256
B83: r&d capitalization rate | D83: =IFERROR(BS!P57/FCFF!D82,"") | E83: =IFERROR(BS!Q57/FCFF!E82,"") | F83: =IFERROR(BS!R57/FCFF!F82,"") | G83: =IFERROR(BS!S57/FCFF!G82,"") | H83: =IFERROR(BS!T57/FCFF!H82,"") | J83: =IFERROR(BS!V57/FCFF!J82,"") | K83: =IFERROR(BS!W57/FCFF!K82,"") | L83: =IFERROR(BS!X57/FCFF!L82,"") | M83: =IFERROR(BS!Y57/FCFF!M82,"") | N83: =IFERROR(BS!Z57/FCFF!N82,"") | P83: =IFERROR(BS!AB57/FCFF!P82,"") | Q83: =IFERROR(BS!AC57/FCFF!Q82,"") | R83: =IFERROR(BS!AD57/FCFF!R82,"") | S83: =IFERROR(BS!AE57/FCFF!S82,"") | T83: =IFERROR(BS!AF57/FCFF!T82,"") | V83: =IFERROR(BS!AH57/FCFF!V82,"") | W83: =IFERROR(BS!AI57/FCFF!W82,"") | X83: 0 | Y83: 0 | Z83: =AVERAGE(V83:Y83) -> 0 | AB83: 0 | AC83: 0 | AD83: 0 | AE83: 0 | AF83: =AVERAGE(AB83:AE83) -> 0 | AH83: 0 | AJ83: 0 | AL83: 0
B85: Accounts Payable | D85: =BS!P37 -> 25.407 | E85: =BS!Q37 -> 29.584 | F85: =BS!R37 -> 26.242 | G85: =BS!S37 -> 27.258 | H85: =BS!T37 -> 27.258 | J85: =BS!V37 -> 20.582 | K85: =BS!W37 -> 26.833 | L85: =BS!X37 -> 25.472 | M85: =BS!Y37 -> 26.448 | N85: =BS!Z37 -> 26.448 | P85: =BS!AB37 -> 24.012 | Q85: =BS!AC37 -> 28.001 | R85: =BS!AD37 -> 30.42 | S85: =BS!AE37 -> 33.29 | T85: =BS!AF37 -> 33.29 | V85: =BS!AH37 -> 32.924 | W85: =BS!AI37 -> 29.84 | X85: =X86*X34/92 -> 34.264821 | Y85: =Y86*Y34/92 -> 35.774094 | Z85: =Y85 -> 35.774094 | AB85: =AB86*AB34/90 -> 37.214694 | AC85: =AC86*AC34/91 -> 37.92024 | AD85: =AD86*AD34/92 -> 39.970727 | AE85: =AE86*AE34/92 -> 42.080589 | AF85: =AE85 -> 42.080589 | AH85: =AH86*AH34/365 -> 48.782558 | AJ85: =AJ86*AJ34/366 -> 63.871222 | AL85: =AL86*AL34/365 -> 81.207178
B86: days payable outstanding | D86: =D85/D34*90 -> 97.710879 | E86: =E85/E34*91 -> 91.581984 | F86: =F85/F34*92 -> 97.632805 | G86: =G85/G34*92 -> 95.177471 | H86: =H85/H34*365 -> 95.781139 | J86: =J85/J34*90 -> 76.264152 | K86: =K85/K34*91 -> 90.390279 | L86: =L85/L34*92 -> 80.416732 | M86: =M85/M34*92 -> 89.105944 | N86: =N85/N34*365 -> 89.591001 | P86: =P85/P34*90 -> 51.698005 | Q86: =Q85/Q34*91 -> 100.12932 | R86: =R85/R34*92 -> 105.2912 | S86: =S85/S34*92 -> 109.1281 | T86: =T85/T34*365 -> 120.26377 | V86: =V85/V34*90 -> 133.68644 | W86: =W85/W34*91 -> 117.79118 | X86: =AVERAGE(V86:W86,R86:S86) -> 116.47423 | Y86: =AVERAGE(V86:X86,S86) -> 119.26999 | Z86: =Z85/Z34*365 -> 130.73549 | AB86: =AVERAGE(V86:Y86) -> 121.80546 | AC86: =AVERAGE(W86:Y86,AB86) -> 118.83521 | AD86: =AVERAGE(AB86:AC86,X86:Y86) -> 119.09622 | AE86: =AVERAGE(AB86:AD86,Y86) -> 119.75172 | AF86: =AF85/AF34*365 -> 128.2722 | AH86: =AVERAGE(AF86,Z86,T86) -> 126.42382 | AJ86: =AVERAGE(AF86:AH86,Z86) -> 128.47717 | AL86: =AVERAGE(AF86:AJ86) -> 127.7244
B88: Accrued Expenses and Other Current Liabilities | D88: =BS!P40 -> 0 | E88: =BS!Q40 -> 0 | F88: =BS!R40 -> 0 | G88: =BS!S40 -> 0 | H88: =BS!T40 -> 0 | J88: =BS!V40 -> 0 | K88: =BS!W40 -> 0 | L88: =BS!X40 -> 0 | M88: =BS!Y40 -> 0 | N88: =BS!Z40 -> 0 | P88: =BS!AB40 -> 0 | Q88: =BS!AC40 -> 0 | R88: =BS!AD40 -> 0 | S88: =BS!AE40 -> 0 | T88: =BS!AF40 -> 0 | V88: =BS!AH40 -> 0 | W88: =BS!AI40 -> 0 | X88: =X89*X43 -> 0 | Y88: =Y89*Y43 -> 0 | Z88: =Y88 -> 0 | AB88: =AB89*AB43 -> 0 | AC88: =AC89*AC43 -> 0 | AD88: =AD89*AD43 -> 0 | AE88: =AE89*AE43 -> 0 | AF88: =AE88 -> 0 | AH88: =AH89*AH43 -> 0 | AJ88: =AJ89*AJ43 -> 0 | AL88: =AL89*AL43 -> 0
B89: % of sg&a | D89: =D88/D43 -> 0 | E89: =E88/E43 -> 0 | F89: =F88/F43 -> 0 | G89: =G88/G43 -> 0 | H89: =H88/H43 -> 0 | J89: =J88/J43 -> 0 | K89: =K88/K43 -> 0 | L89: =L88/L43 -> 0 | M89: =M88/M43 -> 0 | N89: =N88/N43 -> 0 | P89: =P88/P43 -> 0 | Q89: =Q88/Q43 -> 0 | R89: =R88/R43 -> 0 | S89: =S88/S43 -> 0 | T89: =T88/T43 -> 0 | V89: =V88/V43 -> 0 | W89: =W88/W43 -> 0 | X89: 0 | Y89: 0 | Z89: =Z88/Z43 -> 0 | AB89: 0 | AC89: 0 | AD89: 0 | AE89: 0 | AF89: =AF88/AF43 -> 0 | AH89: 0 | AJ89: 0 | AL89: 0
B91: Cash Flow Statement | D91: Q1 22 | E91: Q2 22 | F91: Q3 22 | G91: Q4 22 | H91: FY 22 | J91: Q1 23 | K91: Q2 23 | L91: Q3 23 | M91: Q4 23 | N91: FY 23 | P91: Q1 24 | Q91: Q2 24 | R91: Q3 24 | S91: Q4 24 | T91: FY 24 | V91: Q1 25 | W91: Q2 25 | X91: Q3 25 | Y91: Q4 25 | Z91: FY 25 | AB91: Q1 26 | AC91: Q2 26 | AD91: Q3 26 | AE91: Q4 26 | AF91: FY 26 | AH91: FY 27 | AJ91: FY 28 | AL91: FY 29
B94: D&A (Depreciation & Amortization) | D94: =CF!P17 -> 3.238 | E94: =CF!Q17 -> 3.366 | F94: =CF!R17 -> 3.452 | G94: =CF!S17 -> 3.525 | H94: =CF!T17 -> 13.581 | J94: =CF!V17 -> 3.391 | K94: =CF!W17 -> 3.317 | L94: =CF!X17 -> 6.219 | M94: =CF!Y17 -> 2.907 | N94: =CF!Z17 -> 12.735 | P94: =CF!AB17 -> 2.725 | Q94: =CF!AC17 -> 2.49 | R94: =CF!AD17 -> 4.58 | S94: =CF!AE17 -> 2.126 | T94: =CF!AF17 -> 9.621 | V94: =CF!AH17 -> 1.76 | W94: =CF!AI17 -> 1.502 | X94: =X79*X95 -> 1.74474 | Y94: =Y79*Y95 -> 1.74474 | Z94: =SUM(V94:Y94) -> 6.75148 | AB94: =AB79*AB95 -> 1.74474 | AC94: =AC79*AC95 -> 1.74474 | AD94: =AD79*AD95 -> 1.74474 | AE94: =AE79*AE95 -> 1.74474 | AF94: =SUM(AB94:AE94) -> 6.97896 | AH94: =AH79*AH95 -> 5.8158 | AJ94: =AJ79*AJ95 -> 5.8158 | AL94: =AL79*AL95 -> 5.8158
B95: % of net pp&e and intangibles excl. Goodwill | D95: =D94/(D82+D79) -> 0.10674843 | E95: =E94/(E82+E79) -> 0.11328375 | F95: =F94/(F82+F79) -> 0.11844634 | G95: =G94/(G82+G79) -> 0.12759719 | H95: =H94/(H82+H79) -> 0.49160211 | J95: =J94/(J82+J79) -> 0.13047828 | K95: =K94/(K82+K79) -> 0.13293524 | L95: =L94/(L82+L79) -> 0.26257125 | M95: =M94/(M82+M79) -> 0.12936098 | N95: =N94/(N82+N79) -> 0.56670523 | P95: =P94/(P82+P79) -> 0.12697451 | Q95: =Q94/(Q82+Q79) -> 0.11769711 | R95: =R94/(R82+R79) -> 0.20471104 | S95: =S94/(S82+S79) -> 0.087637578 | T95: =T94/(T82+T79) -> 0.39659508 | V95: =V94/(V82+V79) -> 0.066826138 | W95: =W94/(W82+W79) -> 0.051652395 | X95: 0.06 | Y95: 0.06 | Z95: =Z94/(Z79+Z82) -> 0.17359118 | AB95: 0.06 | AC95: 0.06 | AD95: 0.06 | AE95: 0.06 | AF95: =AF94/AF79 -> 0.24 | AH95: 0.2 | AI95: 0.1 | AJ95: 0.2 | AK95: 0.1 | AL95: 0.2
B97: Stock-Based Compensation Expense | D97: =CF!P18 -> 0 | E97: =CF!Q18 -> 0 | F97: =CF!R18 -> 0 | G97: =CF!S18 -> 0 | H97: =CF!T18 -> 3.354 | J97: =CF!V18 -> 1.139 | K97: =CF!W18 -> 0.845 | L97: =CF!X18 -> 1.086 | M97: =CF!Y18 -> 0.997 | N97: =CF!Z18 -> 4.067 | P97: =CF!AB18 -> 1.004 | Q97: =CF!AC18 -> 2.092 | R97: =CF!AD18 -> 1.086 | S97: =CF!AE18 -> 1.088 | T97: =CF!AF18 -> 5.27 | V97: =CF!AH18 -> 1.261 | W97: =CF!AI18 -> 5.091 | X97: =X98*X43 -> 1.1745427 | Y97: =Y98*Y43 -> 1.2329566 | Z97: =SUM(V97:Y97) -> 8.7594993 | AB97: =AB98*AB43 -> 1.155131 | AC97: =AC98*AC43 -> 1.244527 | AD97: =AD98*AD43 -> 1.3355122 | AE97: =AE98*AE43 -> 1.3970968 | AF97: =SUM(AB97:AE97) -> 5.132267 | AH97: =AH98*AH43 -> 6.755103 | AJ97: =AJ98*AJ43 -> 11.196829 | AL97: =AL98*AL43 -> 13.80318
B98: % of sg&a | D98: =D97/D43 -> 0 | E98: =E97/E43 -> 0 | F98: =F97/F43 -> 0 | G98: =G97/G43 -> 0 | H98: =H97/H43 -> 0.047805698 | J98: =J97/J43 -> 0.083510521 | K98: =K97/K43 -> 0.050486945 | L98: =L97/L43 -> 0.060925666 | M98: =M97/M43 -> 0.03993591 | N98: =N97/N43 -> 0.063343976 | P98: =P97/P43 -> 0.075534156 | Q98: =Q97/Q43 -> 0.12551749 | R98: =R97/R43 -> 0.063290402 | S98: =S97/S43 -> 0.043535673 | T98: =T97/T43 -> 0.082009306 | V98: =V97/V43 -> 0.089104014 | W98: =W97/W43 -> 0.32195029 | X98: 0.06 | Y98: 0.06 | Z98: =Z97/Z43 -> 0.12497504 | AB98: 0.06 | AC98: 0.06 | AD98: 0.06 | AE98: 0.06 | AF98: =AF97/AF43 -> 0.06 | AH98: 0.06 | AJ98: 0.08 | AL98: 0.08
B99: implied equity value (p/s multiple) | X99: =1.07 -> 1.07 | Y99: =1.07 -> 1.07 | Z99: =AVERAGE(V99:Y99) -> 1.07 | AB99: 1.07 | AC99: 1.07 | AD99: 1.07 | AE99: 1.07 | AF99: =AVERAGE(AB99:AE99) -> 1.07 | AH99: 1.07 | AJ99: 1.07 | AL99: 1.07
B100: implied share price (for dilution) | X100: =X99*(X31+W31+V31+S31)/W64 -> 22.860888 | Y100: =Y99*(Y31+X31+W31+V31)/X64 -> 23.635976 | Z100: =AVERAGE(V100:Y100) -> 23.248432 | AB100: =AB99*(AB31+Y31+X31+W31)/Y64 -> 24.479846 | AC100: =AC99*(AC31+AB31+Y31+X31)/AB64 -> 25.490462 | AD100: =AD99*(AD31+AC31+AB31+Y31)/AC64 -> 26.512245 | AE100: =AE99*(AE31+AD31+AC31+AB31)/AD64 -> 27.680873 | AF100: =AVERAGE(AB100:AE100) -> 26.040857 | AH100: =AH99*AH31/AE64 -> 40.168747 | AJ100: =AJ99*AJ31/AH64 -> 51.319182 | AL100: =AL99*AL31/AJ64 -> 65.514541
B101: sbc dilution (shares issued) | X101: =X97/X100 -> 0.051377824 | Y101: =Y97/Y100 -> 0.052164406 | Z101: =AVERAGE(V101:Y101) -> 0.051771115 | AB101: =AB97/AB100 -> 0.04718702 | AC101: =AC97/AC100 -> 0.048823244 | AD101: =AD97/AD100 -> 0.050373411 | AE101: =AE97/AE100 -> 0.050471559 | AF101: =AVERAGE(AB101:AE101) -> 0.049213808 | AH101: =AH97/AH100 -> 0.16816813 | AJ101: =AJ97/AJ100 -> 0.21818019 | AL101: =AL97/AL100 -> 0.21068879
B103: Changes in Net Working Capital | D103: =SUM(CF!P21:P24) -> -7.517 | E103: =SUM(CF!Q21:Q24) -> 3.22 | F103: =SUM(CF!R21:R24) -> -5.461 | G103: =SUM(CF!S21:S24) -> 0.42 | H103: =SUM(CF!T21:T24) -> -9.338 | J103: =SUM(CF!V21:V24) -> -5.832 | K103: =SUM(CF!W21:W24) -> 4.707 | L103: =SUM(CF!X21:X24) -> -2.449 | M103: =SUM(CF!Y21:Y24) -> 1.621 | N103: =SUM(CF!Z21:Z24) -> -1.953 | P103: =SUM(CF!AB21:AB24) -> 0.6 | Q103: =SUM(CF!AC21:AC24) -> 2.677 | R103: =SUM(CF!AD21:AD24) -> -5.062 | S103: =SUM(CF!AE21:AE24) -> 8.21 | T103: =SUM(CF!AF21:AF24) -> 6.425 | V103: =SUM(CF!AH21:AH24) -> -12.992 | W103: =SUM(CF!AI21:AI24) -> 0.58 | X103: =-((X70+X73+X76-X85-X88)-(W70+W73+W76-W85-W88)) -> 4.4550843 | Y103: =-((Y70+Y73+Y76-Y85-Y88)-(X70+X73+X76-X85-X88)) -> -0.00022696479 | Z103: =SUM(V103:Y103) -> -7.9571426 | AB103: =-((AB70+AB73+AB76-AB85-AB88)-(Y70+Y73+Y76-Y85-Y88)) -> -0.88037379 | AC103: =-((AC70+AC73+AC76-AC85-AC88)-(AB70+AB73+AB76-AB85-AB88)) -> -0.42007543 | AD103: =-((AD70+AD73+AD76-AD85-AD88)-(AC70+AC73+AC76-AC85-AC88)) -> 0.54643998 | AE103: =-((AE70+AE73+AE76-AE85-AE88)-(AD70+AD73+AD76-AD85-AD88)) -> -0.23974884 | AF103: =SUM(AB103:AE103) -> -0.99375808 | AH103: =-((AH70+AH73+AH76-AH85-AH88)-(AF70+AF73+AF76-AF85-AF88)) -> -0.41319925 | AJ103: =-((AJ70+AJ73+AJ76-AJ85-AJ88)-(AH70+AH73+AH76-AH85-AH88)) -> 0.64013701 | AL103: =-((AL70+AL73+AL76-AL85-AL88)-(AJ70+AJ73+AJ76-AJ85-AJ88)) -> 0.18222608
B104: % of change in sales | D104: =D103/(D31-IS!M18) -> -1.7169941 | E104: =E103/(E31-D31) -> 0.42722569 | F104: =F103/(F31-E31) -> -0.34712688 | G104: =G103/(G31-F31) -> -0.11748252 | H104: =H103/IS!N18 -> -0.026754224 | J104: =J103/(J31-IS!S18) -> -16.953488 | K104: =K103/(K31-J31) -> 2.2286932 | L104: =L103/(L31-K31) -> -0.22932859 | M104: =M103/(M31-L31) -> -6.7261411 | N104: =N103/IS!T18 -> -0.0043126006 | P104: =P103/(P31-IS!Y18) -> -0.10750762 | Q104: =Q103/(Q31-P31) -> -2.5765159 | R104: =R103/(R31-Q31) -> -0.49198173 | S104: =S103/(S31-R31) -> -9.4367816 | T104: =T103/IS!Z18 -> 0.012624055 | V104: =V103/(V31-IS!AE18) -> -2.8585259 | W104: =W103/(W31-V31) -> 0.26666667 | X104: =X103/(X31-W31) -> 0.5815689 | Y104: =Y103/(Y31-X31) -> -3.7636334e-05 | Z104: =Z103/(Z31-T31) -> -0.040270954 | AB104: =AB103/(AB31-IS!AK18) -> -0.13854118 | AC104: =AC103/(AC31-AB31) -> -0.066574593 | AD104: =AD103/(AD31-AC31) -> 0.067712988 | AE104: =AE103/(AE31-AD31) -> -0.024340402 | AF104: =AF103/(AF31-Z31) -> -0.0078269984 | AH104: =AH103/(AH31-AF31) -> -0.0025868143 | AJ104: =AJ103/(AJ31-AH31) -> 0.0022188369 | AL104: =AL103/(AL31-AJ31) -> 0.00050943563
B106: Capital Expenditures | D106: =CF!P28 -> -3.814 | E106: =CF!Q28 -> -3.099 | F106: =CF!R28 -> -3.237 | G106: =CF!S28 -> -3.1 | H106: =CF!T28 -> -13.25 | J106: =CF!V28 -> -2.115 | K106: =CF!W28 -> -2.518 | L106: =CF!X28 -> -2.254 | M106: =CF!Y28 -> -2.104 | N106: =CF!Z28 -> -8.991 | P106: =CF!AB28 -> -2.129 | Q106: =CF!AC28 -> -2.592 | R106: =CF!AD28 -> -3.886 | S106: =CF!AE28 -> -4.403 | T106: =CF!AF28 -> -13.01 | V106: =CF!AH28 -> -4.39 | W106: =CF!AI28 -> -4.64 | X106: =-X$31*(X107+Sensitivity!$U$38) -> -4.8189584 | Y106: =-Y$31*(Y107+Sensitivity!$U$38) -> -4.995032 | Z106: =SUM(V106:Y106) -> -18.84399 | AB106: =-AB$31*(AB107+Sensitivity!$U$38) -> -5.3621214 | AC106: =-AC$31*(AC107+Sensitivity!$U$38) -> -5.5703464 | AD106: =-AD$31*(AD107+Sensitivity!$U$38) -> -5.8366545 | AE106: =-AE$31*(AE107+Sensitivity!$U$38) -> -6.1616989 | AF106: =SUM(AB106:AE106) -> -22.930821 | AH106: =-AH$31*(AH107+Sensitivity!$U$38) -> -34.348548 | AJ106: =-AJ$31*(AJ107+Sensitivity!$U$38) -> -45.456339 | AL106: =-AL$31*(AL107+Sensitivity!$U$38) -> -57.975905
B107: % of sales | D107: =-D106/D31 -> 0.038012279 | E107: =-E106/E31 -> 0.028728227 | F107: =-F106/F31 -> 0.026188261 | G107: =-G106/G31 -> 0.025826877 | H107: =-H106/H31 -> 0.029258555 | J107: =-J106/J31 -> 0.017570239 | K107: =-K106/K31 -> 0.020557451 | L107: =-L106/L31 -> 0.01692637 | M107: =-M106/M31 -> 0.015828594 | N107: =-N106/N31 -> 0.017665817 | P107: =-P106/P31 -> 0.016718626 | Q107: =-Q106/Q31 -> 0.020521915 | R107: =-R106/R31 -> 0.028449481 | S107: =-S106/S31 -> 0.032441075 | T107: =-T106/T31 -> 0.02473558 | V107: =-V106/V31 -> 0.031297231 | W107: =-W106/W31 -> 0.032574433 | X107: =AVERAGE(V107:W107,S107) -> 0.032104246 | Y107: =AVERAGE(V107:X107) -> 0.03199197 | Z107: =-Z106/Z$31 -> 0.026043686 | AB107: 0.033 | AC107: 0.033 | AD107: 0.033 | AE107: 0.033 | AF107: =-AF106/AF$31 -> 0.026960989 | AH107: 0.034 | AJ107: 0.035 | AL107: 0.035
B109: Proceeds from Asset Disposals | D109: =CF!P29 -> 0 | E109: =CF!Q29 -> 0 | F109: =CF!R29 -> 0 | G109: =CF!S29 -> 0 | H109: =CF!T29 -> 0 | J109: =CF!V29 -> 0 | K109: =CF!W29 -> 0 | L109: =CF!X29 -> 0 | M109: =CF!Y29 -> 0 | N109: =CF!Z29 -> 0 | P109: =CF!AB29 -> 0 | Q109: =CF!AC29 -> 0 | R109: =CF!AD29 -> 0 | S109: =CF!AE29 -> 0 | T109: =CF!AF29 -> 0 | V109: =CF!AH29 -> 0 | W109: =CF!AI29 -> 0 | X109: =X110*X$106 -> 0 | Y109: =Y110*Y$106 -> 0 | Z109: =SUM(V109:Y109) -> 0 | AB109: =AB110*AB$106 -> 0 | AC109: =AC110*AC$106 -> 0 | AD109: =AD110*AD$106 -> 0 | AE109: =AE110*AE$106 -> 0 | AF109: =SUM(AB109:AE109) -> 0 | AH109: =AH110*AH$106 -> 0 | AJ109: =AJ110*AJ$106 -> 0 | AL109: =AL110*AL$106 -> 0
B110: % of capex | D110: =-D109/D106 -> 0 | E110: =-E109/E106 -> 0 | F110: =-F109/F106 -> 0 | G110: =-G109/G106 -> 0 | H110: =-H109/H106 -> 0 | J110: =-J109/J106 -> 0 | K110: =-K109/K106 -> 0 | L110: =-L109/L106 -> 0 | M110: =-M109/M106 -> 0 | N110: =-N109/N106 -> 0 | P110: =-P109/P106 -> 0 | Q110: =-Q109/Q106 -> 0 | R110: =-R109/R106 -> 0 | S110: =-S109/S106 -> 0 | T110: =-T109/T106 -> 0 | V110: =-V109/V106 -> 0 | W110: =-W109/W106 -> 0 | X110: 0 | Y110: 0 | Z110: =-Z109/Z$31 -> 0 | AB110: 0 | AC110: 0 | AD110: 0 | AE110: 0 | AF110: =-AF109/AF$31 -> 0 | AH110: 0 | AJ110: 0 | AL110: 0
B112: Dividends | D112: =CF!P39 -> 0 | E112: =CF!Q39 -> 0 | F112: =CF!R39 -> 0 | G112: =CF!S39 -> 0 | H112: =CF!T39 -> 0 | J112: =CF!V39 -> 0 | K112: =CF!W39 -> 0 | L112: =CF!X39 -> 0 | M112: =CF!Y39 -> 0 | N112: =CF!Z39 -> 0 | P112: =CF!AB39 -> 0 | Q112: =CF!AC39 -> -2.374 | R112: =CF!AD39 -> 0 | S112: =CF!AE39 -> 0 | T112: =CF!AF39 -> -2.374 | V112: =CF!AH39 -> 0 | W112: =CF!AI39 -> -6.414 | X112: =-X113*X126 -> 0 | Y112: =-Y113*Y126 -> 0 | Z112: =SUM(V112:Y112) -> -6.414 | AB112: =-AB113*AB126 -> 0 | AC112: =-AC113*AC126 -> -6.315961 | AD112: =-AD113*AD126 -> 0 | AE112: =-AE113*AE126 -> 0 | AF112: =SUM(AB112:AE112) -> -6.315961 | AH112: =-AH113*AH126 -> -7.5465779 | AJ112: =-AJ113*AJ126 -> -9.7016816 | AL112: =-AL113*AL126 -> -12.373715
B113: % of NOPAT | D113: =-D112/D126 -> 0 | E113: =-E112/E126 -> 0 | F113: =-F112/F126 -> 0 | G113: =-G112/G126 -> 0 | H113: =-H112/H126 -> 0 | J113: =-J112/J126 -> 0 | K113: =-K112/K126 -> 0 | L113: =-L112/L126 -> 0 | M113: =-M112/M126 -> 0 | N113: =-N112/N126 -> 0 | P113: =-P112/P126 -> 0 | Q113: =-Q112/Q126 -> 0.085097762 | R113: =-R112/R126 -> 0 | S113: =-S112/S126 -> 0 | T113: =-T112/T126 -> 0.018865118 | V113: =-V112/V126 -> 0 | W113: =-W112/W126 -> 0.1612742 | X113: 0 | Y113: 0 | Z113: =-Z112/Z126 -> 0.044774968 | AB113: 0 | AC113: 0.15 | AD113: 0 | AE113: 0 | AF113: =-AF112/AF126 -> 0.037152526 | AH113: 0.03 | AJ113: 0.03 | AL113: 0.03
B115: Repurchase of Stock | D115: =CF!P40 -> -1.037 | E115: =CF!Q40 -> -1.116 | F115: =CF!R40 -> -0.307 | G115: =CF!S40 -> 0 | H115: =CF!T40 -> -2.46 | J115: =CF!V40 -> 0 | K115: =CF!W40 -> 0 | L115: =CF!X40 -> 0 | M115: =CF!Y40 -> 0.059 | N115: =CF!Z40 -> 0.059 | P115: =CF!AB40 -> -0.189 | Q115: =CF!AC40 -> 0.189 | R115: =CF!AD40 -> -4.555 | S115: =CF!AE40 -> -0.331 | T115: =CF!AF40 -> -4.886 | V115: =CF!AH40 -> -0.848 | W115: =CF!AI40 -> 0.853 | X115: 4 | Y115: 0 | Z115: =SUM(V115:Y115) -> 4.005 | AB115: 0 | AC115: 4 | AD115: 0 | AE115: 0 | AF115: =SUM(AB115:AE115) -> 4 | AH115: 4 | AJ115: 4 | AL115: 4
A117: x | B117: Free Cash Flow to Firm
D118: =D$8 -> 2022 | E118: =F118 -> 0 | F118: =F$8 -> 0 | G118: =F118 -> 0 | H118: =F118 -> 0 | J118: =J$8 -> 2023 | K118: =L118 -> 0 | L118: =L$8 -> 0 | M118: =L118 -> 0 | N118: =L118 -> 0 | P118: =P$8 -> 2024 | Q118: =R118 -> 0 | R118: =R$8 -> 0 | S118: =R118 -> 0 | T118: =R118 -> 0 | V118: =V$8 -> 2025 | W118: =X118 -> 0 | X118: =X$8 -> 0 | Y118: =X118 -> 0 | Z118: =X118 -> 0 | AB118: =AB$8 -> 2026 | AC118: =AD118 -> 0 | AD118: =AD$8 -> 0 | AE118: =AD118 -> 0 | AF118: =AD118 -> 0 | AH118: =AH$8 -> 2027 | AJ118: =AJ$8 -> 2028 | AL118: =AL$8 -> 2029
D119: Q1 | E119: Q2 | F119: Q3 | G119: Q4 | H119: FY | J119: Q1 | K119: Q2 | L119: Q3 | M119: Q4 | N119: FY | P119: Q1 | Q119: Q2 | R119: Q3 | S119: Q4 | T119: FY | V119: Q1 | W119: Q2 | X119: Q3 | Y119: Q4 | Z119: FY | AB119: Q1 | AC119: Q2 | AD119: Q3 | AE119: Q4 | AF119: FY | AH119: FY | AJ119: FY | AL119: FY
B122: EBIT (Operating Income) | D122: =D61 -> 5.287 | E122: =E61 -> 5.259 | F122: =F61 -> -0.894 | G122: =G61 -> -6.831 | H122: =H61 -> 32.391 | J122: =J61 -> 15.101 | K122: =K61 -> 18.334 | L122: =L61 -> 17.239 | M122: =M61 -> 28.59 | N122: =N61 -> 105.895 | P122: =P61 -> 5.284 | Q122: =Q61 -> 30.287 | R122: =R61 -> 37.059 | S122: =S61 -> 36.623 | T122: =T61 -> 151.268 | V122: =V61 -> 41.044 | W122: =W61 -> 45.308 | X122: =X61 -> 43.22362 | Y122: =Y61 -> 44.778546 | Z122: =Z61 -> 174.35417 | AB122: =AB61 -> 48.155262 | AC122: =AC61 -> 50.183491 | AD122: =AD61 -> 51.663856 | AE122: =AE61 -> 54.734496 | AF122: =AF61 -> 204.73711 | AH122: =AH61 -> 303.07542 | AJ122: =AJ61 -> 389.62577 | AL122: =AL61 -> 496.93633
B124: Tax Rate | D124: =IS!P45/IS!P42 -> -0.015736041 | E124: =IS!Q45/IS!Q42 -> -0.0044413277 | F124: =IS!R45/IS!R42 -> 2.3913753 | G124: =IS!S45/IS!S42 -> 0.32575281 | H124: =IS!T45/IS!T42 -> 0.11923425 | J124: =IS!V45/IS!V42 -> 0.18239169 | K124: =IS!W45/IS!W42 -> 0.19700967 | L124: =IS!X45/IS!X42 -> 0.26334334 | M124: =IS!Y45/IS!Y42 -> 0.24792768 | N124: =IS!Z45/IS!Z42 -> 0.22432967 | P124: =IS!AB45/IS!AB42 -> 0.21296793 | Q124: =IS!AC45/IS!AC42 -> 0.078900987 | R124: =IS!AD45/IS!AD42 -> 0.28650092 | S124: =IS!AE45/IS!AE42 -> 0.067948883 | T124: =IS!AF45/IS!AF42 -> 0.16809425 | V124: =IS!AH45/IS!AH42 -> 0.25748558 | W124: =IS!AI45/IS!AI42 -> 0.12221297 | X124: =AVERAGE(V124:W124,R124:S124) -> 0.18353709 | Y124: =AVERAGE(V124:X124,S124) -> 0.15779613 | Z124: =AVERAGE(V124:Y124) -> 0.18025794 | AB124: =AVERAGE(V124:Y124) -> 0.18025794 | AC124: =AVERAGE(W124:Y124,AB124) -> 0.16095103 | AD124: =AVERAGE(AB124:AC124,X124:Y124) -> 0.17063555 | AE124: =AVERAGE(AB124:AD124,Y124) -> 0.16741016 | AF124: =AVERAGE(AB124:AE124) -> 0.16981367 | AH124: 0.17 | AJ124: 0.17 | AL124: 0.17
B126: NOPAT (Net Operating Profit After Taxes) | D126: =D122*(1-D124) -> 5.3701964 | E126: =E122*(1-E124) -> 5.2823569 | F126: =F122*(1-F124) -> 1.2438895 | G126: =G122*(1-G124) -> -4.6057826 | H126: =H122*(1-H124) -> 28.528883 | J126: =J122*(1-J124) -> 12.346703 | K126: =K122*(1-K124) -> 14.722025 | L126: =L122*(1-L124) -> 12.699224 | M126: =M122*(1-M124) -> 21.501748 | N126: =N122*(1-N124) -> 82.13961 | P126: =P122*(1-P124) -> 4.1586775 | Q126: =Q122*(1-Q124) -> 27.897326 | R126: =R122*(1-R124) -> 26.441562 | S126: =S122*(1-S124) -> 34.134508 | T126: =T122*(1-T124) -> 125.84072 | V126: =V122*(1-V124) -> 30.475762 | W126: =W122*(1-W124) -> 39.770775 | X126: =X122*(1-X124) -> 35.290482 | Y126: =Y122*(1-Y124) -> 37.712665 | Z126: =SUM(V126:Y126) -> 143.24968 | AB126: =AB122*(1-AB124) -> 39.474894 | AC126: =AC122*(1-AC124) -> 42.106406 | AD126: =AD122*(1-AD124) -> 42.848165 | AE126: =AE122*(1-AE124) -> 45.571385 | AF126: =SUM(AB126:AE126) -> 170.00085 | AH126: =AH122*(1-AH124) -> 251.5526 | AJ126: =AJ122*(1-AJ124) -> 323.38939 | AL126: =AL122*(1-AL124) -> 412.45715
B128: D&A (Depreciation & Amortization) | D128: =D94 -> 3.238 | E128: =E94 -> 3.366 | F128: =F94 -> 3.452 | G128: =G94 -> 3.525 | H128: =H94 -> 13.581 | J128: =J94 -> 3.391 | K128: =K94 -> 3.317 | L128: =L94 -> 6.219 | M128: =M94 -> 2.907 | N128: =N94 -> 12.735 | P128: =P94 -> 2.725 | Q128: =Q94 -> 2.49 | R128: =R94 -> 4.58 | S128: =S94 -> 2.126 | T128: =T94 -> 9.621 | V128: =V94 -> 1.76 | W128: =W94 -> 1.502 | X128: =X94 -> 1.74474 | Y128: =Y94 -> 1.74474 | Z128: =Z94 -> 6.75148 | AB128: =AB94 -> 1.74474 | AC128: =AC94 -> 1.74474 | AD128: =AD94 -> 1.74474 | AE128: =AE94 -> 1.74474 | AF128: =AF94 -> 6.97896 | AH128: =AH94 -> 5.8158 | AJ128: =AJ94 -> 5.8158 | AL128: =AL94 -> 5.8158
B130: Stock-Based Compensation | D130: =D97 -> 0 | E130: =E97 -> 0 | F130: =F97 -> 0 | G130: =G97 -> 0 | H130: =H97 -> 3.354 | J130: =J97 -> 1.139 | K130: =K97 -> 0.845 | L130: =L97 -> 1.086 | M130: =M97 -> 0.997 | N130: =N97 -> 4.067 | P130: =P97 -> 1.004 | Q130: =Q97 -> 2.092 | R130: =R97 -> 1.086 | S130: =S97 -> 1.088 | T130: =T97 -> 5.27 | V130: =V97 -> 1.261 | W130: =W97 -> 5.091 | X130: =X97 -> 1.1745427 | Y130: =Y97 -> 1.2329566 | Z130: =Z97 -> 8.7594993 | AB130: =AB97 -> 1.155131 | AC130: =AC97 -> 1.244527 | AD130: =AD97 -> 1.3355122 | AE130: =AE97 -> 1.3970968 | AF130: =AF97 -> 5.132267 | AH130: =AH97 -> 6.755103 | AJ130: =AJ97 -> 11.196829 | AL130: =AL97 -> 13.80318
B132: Changes in Net Working Capital | D132: =D103 -> -7.517 | E132: =E103 -> 3.22 | F132: =F103 -> -5.461 | G132: =G103 -> 0.42 | H132: =H103 -> -9.338 | J132: =J103 -> -5.832 | K132: =K103 -> 4.707 | L132: =L103 -> -2.449 | M132: =M103 -> 1.621 | N132: =N103 -> -1.953 | P132: =P103 -> 0.6 | Q132: =Q103 -> 2.677 | R132: =R103 -> -5.062 | S132: =S103 -> 8.21 | T132: =T103 -> 6.425 | V132: =V103 -> -12.992 | W132: =W103 -> 0.58 | X132: =X103 -> 4.4550843 | Y132: =Y103 -> -0.00022696479 | Z132: =Z103 -> -7.9571426 | AB132: =AB103 -> -0.88037379 | AC132: =AC103 -> -0.42007543 | AD132: =AD103 -> 0.54643998 | AE132: =AE103 -> -0.23974884 | AF132: =AF103 -> -0.99375808 | AH132: =AH103 -> -0.41319925 | AJ132: =AJ103 -> 0.64013701 | AL132: =AL103 -> 0.18222608
B134: Net CapEx | D134: =D106+D109 -> -3.814 | E134: =E106+E109 -> -3.099 | F134: =F106+F109 -> -3.237 | G134: =G106+G109 -> -3.1 | H134: =H106+H109 -> -13.25 | J134: =J106+J109 -> -2.115 | K134: =K106+K109 -> -2.518 | L134: =L106+L109 -> -2.254 | M134: =M106+M109 -> -2.104 | N134: =N106+N109 -> -8.991 | P134: =P106+P109 -> -2.129 | Q134: =Q106+Q109 -> -2.592 | R134: =R106+R109 -> -3.886 | S134: =S106+S109 -> -4.403 | T134: =T106+T109 -> -13.01 | V134: =V106+V109 -> -4.39 | W134: =W106+W109 -> -4.64 | X134: =X106+X109 -> -4.8189584 | Y134: =Y106+Y109 -> -4.995032 | Z134: =Z106+Z109 -> -18.84399 | AB134: =AB106+AB109 -> -5.3621214 | AC134: =AC106+AC109 -> -5.5703464 | AD134: =AD106+AD109 -> -5.8366545 | AE134: =AE106+AE109 -> -6.1616989 | AF134: =AF106+AF109 -> -22.930821 | AH134: =AH106+AH109 -> -34.348548 | AJ134: =AJ106+AJ109 -> -45.456339 | AL134: =AL106+AL109 -> -57.975905
B136: FCFF (Free Cash Flow to Firm) | D136: =D126+D94+D97+D103+D134 -> -2.7228036 | E136: =E126+E94+E97+E103+E134 -> 8.7693569 | F136: =F126+F94+F97+F103+F134 -> -4.0021105 | G136: =G126+G94+G97+G103+G134 -> -3.7607826 | H136: =H126+H94+H97+H103+H134 -> 22.875883 | J136: =J126+J94+J97+J103+J134 -> 8.929703 | K136: =K126+K94+K97+K103+K134 -> 21.073025 | L136: =L126+L94+L97+L103+L134 -> 15.301224 | M136: =M126+M94+M97+M103+M134 -> 24.922748 | N136: =N126+N94+N97+N103+N134 -> 87.99761 | P136: =P126+P94+P97+P103+P134 -> 6.3586775 | Q136: =Q126+Q94+Q97+Q103+Q134 -> 32.564326 | R136: =R126+R94+R97+R103+R134 -> 23.159562 | S136: =S126+S94+S97+S103+S134 -> 41.155508 | T136: =T126+T94+T97+T103+T134 -> 134.14672 | V136: =V126+V94+V97+V103+V134 -> 16.114762 | W136: =W126+W94+W97+W103+W134 -> 42.303775 | X136: =X126+X128+X130+X132+X134 -> 37.845891 | Y136: =Y126+Y128+Y130+Y132+Y134 -> 35.695103 | Z136: =Z126+Z128+Z130+Z132+Z134 -> 131.95953 | AB136: =AB126+AB128+AB130+AB132+AB134 -> 36.13227 | AC136: =AC126+AC128+AC130+AC132+AC134 -> 39.105252 | AD136: =AD126+AD128+AD130+AD132+AD134 -> 40.638203 | AE136: =AE126+AE128+AE130+AE132+AE134 -> 42.311775 | AF136: =AF126+AF128+AF130+AF132+AF134 -> 158.1875 | AH136: =AH126+AH128+AH130+AH132+AH134 -> 229.36175 | AJ136: =AJ126+AJ128+AJ130+AJ132+AJ134 -> 295.58581 | AL136: =AL126+AL128+AL130+AL132+AL134 -> 374.28245
A138: x | B138: Valuation Summary
V139: =V$8 -> 2025 | W139: =X139 -> 0 | X139: =X$8 -> 0 | Y139: =X139 -> 0 | Z139: =X139 -> 0 | AB139: =AB$8 -> 2026 | AC139: =AD139 -> 0 | AD139: =AD$8 -> 0 | AE139: =AD139 -> 0 | AF139: =AD139 -> 0 | AH139: =AH$8 -> 2027 | AJ139: =AJ$8 -> 2028 | AL139: =AL$8 -> 2029
V140: Q1 | W140: Q2 | X140: Q3 | Y140: Q4 | Z140: FY | AB140: Q1 | AC140: Q2 | AD140: Q3 | AE140: Q4 | AF140: FY | AH140: FY | AJ140: FY | AL140: FY
B143: Discounted Cash Flows (DCF)
B146: Discount Period | Y146: =YEARFRAC(TODAY(),"2025-12-31") -> 0.19444444 | AB146: =YEARFRAC(TODAY(),Inputs!$D$17+365+90) -> 1.4444444 | AC146: =YEARFRAC(TODAY(),Inputs!$D$17+365+90+91) -> 1.6916667 | AD146: =YEARFRAC(TODAY(),Inputs!$D$17+365+90+91+92) -> 1.9416667 | AE146: =YEARFRAC(TODAY(),Inputs!$D$17+720) -> 2.1666667 | AH146: =YEARFRAC(TODAY(),Inputs!$D$17+730+365) -> 3.1916667 | AJ146: =YEARFRAC(TODAY(),Inputs!$D$17+730+731) -> 4.1944444 | AL146: =YEARFRAC(TODAY(),Inputs!$D$17+730+731+365) -> 5.1944444
B147: Mid-Quarter/Year Convention Discount Period | X147: =X146/2 -> 0 | Y147: =X146+(Y146-X146)/2 -> 0.097222222 | AB147: =Y146+(AB146-Y146)/2 -> 0.81944444 | AC147: =AB146+(AC146-AB146)/2 -> 1.5680556 | AD147: =AC146+(AD146-AC146)/2 -> 1.8166667 | AE147: =AD146+(AE146-AD146)/2 -> 2.0541667 | AH147: =AE146+(AH146-AE146)/2 -> 2.6791667 | AJ147: =AH146+(AJ146-AH146)/2 -> 3.6930556 | AL147: =AJ146+(AL146-AJ146)/2 -> 4.6944444
B149: Rolling WACC (Weighted Average Cost of Capital) | X149: =WACC!$D$39+Sensitivity!U41 -> 0.025084075 | Y149: =WACC!$D$39+Sensitivity!U41 -> 0.025084075 | AB149: =WACC!$E$39+Sensitivity!U41 -> 0.086932772 | AC149: =WACC!$E$39+Sensitivity!U41 -> 0.086932772 | AD149: =WACC!$E$39+Sensitivity!U41 -> 0.086932772 | AE149: =WACC!$E$39+Sensitivity!U41 -> 0.086932772 | AH149: =WACC!$F$39+Sensitivity!U41 -> 0.086931435 | AJ149: =WACC!$G$39+Sensitivity!U41 -> 0.086909665 | AL149: =WACC!$H$39+Sensitivity!U41 -> 0.086905147
B150: Cumulative Discount Factor | X150: =(1+X149)^X147 -> 1 | Y150: =((1+X149)^X147)*((1+Y149)^Y147) -> 1.0024115 | AB150: =((1+X149)^X147)*((1+Y149)^Y147)*((1+AB149)^AB147) -> 1.0732778 | AC150: =((1+X149)^X147)*((1+Y149)^Y147)*((1+AB149)^AB147)*((1+AC149)^AC147) -> 1.2231507 | AD150: =((1+X149)^X147)*((1+Y149)^Y147)*((1+AB149)^AB147)*((1+AC149)^AC147)*((1+AD149)^AD147) -> 1.4231418 | AE150: =((1+X149)^X147)*((1+Y149)^Y147)*((1+AB149)^AB147)*((1+AC149)^AC147)*((1+AD149)^AD147)*((1+AE149)^AE147) -> 1.6889412 | AH150: =((1+X149)^X147)*((1+Y149)^Y147)*((1+AB149)^AB147)*((1+AC149)^AC147)*((1+AD149)^AD147)*((1+AE149)^AE147)*((1+AH149)^AH147) -> 2.1115731 | AJ150: =((1+X149)^X147)*((1+Y149)^Y147)*((1+AB149)^AB147)*((1+AC149)^AC147)*((1+AD149)^AD147)*((1+AE149)^AE147)*((1+AH149)^AH147)*((1+AJ149)^AJ147) -> 2.8725694 | AL150: =((1+X149)^X147)*((1+Y149)^Y147)*((1+AB149)^AB147)*((1+AC149)^AC147)*((1+AD149)^AD147)*((1+AE149)^AE147)*((1+AH149)^AH147)*((1+AJ149)^AJ147)*((1+AL149)^AL147) -> 4.2478601
B152: Present Value of FCFF | X152: =X136/X150*(Inputs!$D$17-92-TODAY())/92 -> -8.638736 | Y152: =Y136/Y150 -> 35.609229 | AB152: =AB136/AB150 -> 33.665347 | AC152: =AC136/AC150 -> 31.970919 | AD152: =AD136/AD150 -> 28.555273 | AE152: =AE136/AE150 -> 25.052249 | AH152: =AH136/AH150 -> 108.62127 | AJ152: =AJ136/AJ150 -> 102.89945 | AL152: =AL136/AL150 -> 88.110824
B154: Terminal Value
Q157: Preferred Method: | R157: Revenue Exit | V157: EBITDA Exit Multiple | AB157: Revenue Exit Multiple | AH157: Gordon's Growth Model
V159: Current EV/EBITDA | Z159: =Inputs!M14 -> 2.8890262 | AB159: Current EV/Sales | AF159: =Inputs!M13 -> 0.86185609 | AH159: Current Growth Rate | AL159: =AL136/AJ136-1 -> 0.26623957
V160: Exit EV/EBITDA | Z160: 5 | AB160: Exit EV/Sales | AF160: 1.5 | AH160: Terminal Growth Rate | AL160: 0.02
R161: =R157 -> Revenue Exit | V161: Terminal Value | Z161: =(Z160+Sensitivity!U43)*(AL122+AL128) -> 2513.7606 | AB161: Terminal Value | AF161: =(AF160+Sensitivity!U44)*(AL31) -> 2484.6816 | AH161: Terminal Value | AL161: =AL136*(1+AL160+Sensitivity!U42)/(AL149-AL160-Sensitivity!U42) -> 5706.1096
R162: =IF($R$161="Revenue Exit",$AF$171,IF($R$161="EBITDA Exit",$Z$171,$AL$171)) -> 0.96012701 | V162: PV of Terminal Value | Z162: =Z161/AL150 -> 591.77105 | AB162: PV of Terminal Value | AF162: =AF161/AL150 -> 584.92549 | AH162: PV of Terminal Value | AL162: =AL161/AL150 -> 1343.2904
...

Sheet LBO
A7: x | B7: Key Assumptions
B10: Entry | G10: Capital Structure | J10: Interest | K10: Weight | L10: Amount
B11: LTM EBITDA | E11: =(G86+G77) -> 160.889 | G11: Revolver | L11: =K11*$E$13 -> 0
B12: Entry Multiple | G12: Bank Loan | L12: =K12*$E$13 -> 0
B13: Enterprise Value | E13: =E11*E12 -> 0 | G13: Senior Notes | L13: =K13*$E$13 -> 0
B14: Existing Net Debt | E14: =BS!AJ38+BS!AJ39+BS!AJ44+BS!AJ45-BS!AJ15 -> 0
B15: Equity Value | E15: =E13-E14 -> 0 | G15: IRR (For reference)
G16: MOIC | L16: =L180 -> #DIV/0!
B17: Fees & Expenses | E17: =0.03*E13 -> 0 | G17: IRR | L17: =L181 -> #DIV/0!
B19: Exit
B20: Exit Multiple
A22: x | B22: Sources & Uses
B25: Sources | G25: Uses
C26: Amount | D26: xEBITDA | E26: % Capital | J26: Amount | K26: xEBITDA | L26: % Capital
B27: Revolver | C27: =L11 -> 0 | D27: =C27/$E$11 -> 0 | E27: =C27/$C$34 -> #DIV/0! | G27: Debt Refinancing | J27: =E14 -> 0 | K27: =J27/$E$11 -> 0 | L27: =J27/$J$34 -> #DIV/0!
B28: Bank Loan | C28: =L12 -> 0 | D28: =C28/$E$11 -> 0 | E28: =C28/$C$34 -> #DIV/0! | G28: Equity Payments | J28: =E15 -> 0 | K28: =J28/$E$11 -> 0 | L28: =J28/$J$34 -> #DIV/0!
B29: Senior Notes | C29: =L13 -> 0 | D29: =C29/$E$11 -> 0 | E29: =C29/$C$34 -> #DIV/0!
B30: Total | C30: =SUM(C27:C29) -> 0 | D30: =C30/$E$11 -> 0 | E30: =C30/$C$34 -> #DIV/0! | G30: Fees & Expenses | J30: =E17 -> 0 | K30: =J30/$E$11 -> 0 | L30: =J30/$J$34 -> #DIV/0!
B32: Sponsor Equity | C32: =C34-C30 -> 0 | D32: =C32/$E$11 -> 0 | E32: =C32/$C$34 -> #DIV/0!
B34: Total Sources | C34: =J34 -> 0 | D34: =C34/$E$11 -> 0 | E34: =C34/$C$34 -> #DIV/0! | G34: Total Uses | J34: =J27+J28+J30 -> 0 | K34: =J34/$E$11 -> 0 | L34: =J34/$J$34 -> #DIV/0!
B36: Market Assumptions
A38: x | E38: 2022 | F38: =+E38+1 -> 2023 | G38: =+F38+1 -> 2024 | H38: =+G38+1 -> 2025 | I38: =+H38+1 -> 2026 | J38: =+I38+1 -> 2027 | K38: =+J38+1 -> 2028 | L38: =+K38+1 -> 2029
B50: Sales | H50: 350000 | I50: 352000 | J50: 350000 | K50: 352000 | L50: 350000
B52: Operating Assumptions
A57: x | B57: Income Statement | E57: 2022 | F57: =+E57+1 -> 2023 | G57: =+F57+1 -> 2024 | H57: =+G57+1 -> 2025 | I57: =+H57+1 -> 2026 | J57: =+I57+1 -> 2027 | K57: =+J57+1 -> 2028 | L57: =+K57+1 -> 2029
B59: Revenue | D59: =+_xlfn.XLOOKUP($B59,#REF!,#REF!) -> #REF! | E59: =FCFF!H31 -> 452.859 | F59: =FCFF!N31 -> 508.949 | G59: =FCFF!T31 -> 525.963 | H59: =+H50 -> 350000 | I59: =+I50 -> 352000 | J59: =+J50 -> 350000 | K59: =+K50 -> 352000 | L59: =+L50 -> 350000
B60: % of growth | E60: =E59/IS!N18-1 -> 0.29748244 | F60: =F59/E59-1 -> 0.12385754 | G60: =G59/F59-1 -> 0.033429676 | H60: =H59/G59-1 -> 664.44605 | I60: =I59/H59-1 -> 0.0057142857 | J60: =J59/I59-1 -> -0.0056818182 | K60: =K59/J59-1 -> 0.0057142857 | L60: =L59/K59-1 -> -0.0056818182
B62: Cost of Goods & Services | E62: =FCFF!H34 -> 103.874 | F62: =FCFF!N34 -> 107.751 | G62: =FCFF!T34 -> 101.035 | H62: =H63*H$59 -> 0 | I62: =I63*I$59 -> 0 | J62: =J63*J$59 -> 0 | K62: =K63*K$59 -> 0 | L62: =L63*L$59 -> 0
B63: % of sales | E63: =E62/E59 -> 0.22937382 | F63: =F62/F59 -> 0.21171276 | G63: =G62/G59 -> 0.19209526
B65: COGS Depreciation & Amortization | E65: =FCFF!H37 -> 0 | F65: =FCFF!N37 -> 0 | G65: =FCFF!T37 -> 0 | H65: =+H66*H62 -> 0 | I65: =+I66*I62 -> 0 | J65: =+J66*J62 -> 0 | K65: =+K66*K62 -> 0 | L65: =+L66*L62 -> 0
B66: % of cost of goods & services | E66: =E65/E62 -> 0 | F66: =F65/F62 -> 0 | G66: =G65/G62 -> 0
B68: Gross Profit | E68: =FCFF!H40 -> 348.985 | F68: =FCFF!N40 -> 401.198 | G68: =FCFF!T40 -> 424.928 | H68: =+H59-H62-H65 -> 350000 | I68: =+I59-I62-I65 -> 352000 | J68: =+J59-J62-J65 -> 350000 | K68: =+K59-K62-K65 -> 352000 | L68: =+L59-L62-L65 -> 350000
B69: % of sales | E69: =E68/E59 -> 0.77062618 | F69: =F68/F59 -> 0.78828724 | G69: =G68/G59 -> 0.80790474 | H69: =IFERROR(H68/H$59,"") -> 1 | I69: =IFERROR(I68/I$59,"") -> 1 | J69: =IFERROR(J68/J$59,"") -> 1 | K69: =IFERROR(K68/K$59,"") -> 1 | L69: =IFERROR(L68/L$59,"") -> 1
B71: SG&A (Selling, General & Administrative) | E71: =FCFF!H43 -> 70.159 | F71: =FCFF!N43 -> 64.205 | G71: =FCFF!T43 -> 64.261 | H71: =+H72*H59 -> 0 | I71: =+I72*I59 -> 0 | J71: =+J72*J59 -> 0 | K71: =+K72*K59 -> 0 | L71: =+L72*L59 -> 0
B72: % of sales | E72: =E71/E59 -> 0.1549246 | F72: =F71/F59 -> 0.12615213 | G72: =G71/G59 -> 0.1221778
B74: R&D (Research & Development) | E74: =FCFF!H46 -> 13.054 | F74: =FCFF!N46 -> 12.543 | G74: =FCFF!T46 -> 12.171 | H74: =+H75*H68 -> 0 | I74: =+I75*I68 -> 0 | J74: =+J75*J68 -> 0 | K74: =+K75*K68 -> 0 | L74: =+L75*L68 -> 0
B75: % of gross profit | E75: =E74/E68 -> 0.037405619 | F75: =F74/F68 -> 0.031263865 | G75: =G74/G68 -> 0.028642499
B77: D&A (Depreciation & Amortization) | E77: =FCFF!H49 -> 13.581 | F77: =FCFF!N49 -> 12.735 | G77: =FCFF!T49 -> 9.621 | H77: =+H80+H83 -> 0 | I77: =+I80+I83 -> 0 | J77: =+J80+J83 -> 0 | K77: =+K80+K83 -> 0 | L77: =+L80+L83 -> 0
B78: % of net pp&e and intangibles excl. Goodwill | E78: =E77/(E111+E114) -> 0.49160211 | F78: =F77/(F111+F114) -> 0.56670523 | G78: =G77/(G111+G114) -> 0.39659508 | H78: =H77/(H111+H114) -> 0 | I78: =I77/(I111+I114) -> 0 | J78: =J77/(J111+J114) -> 0 | K78: =K77/(K111+K114) -> 0 | L78: =L77/(L111+L114) -> 0
B80: Depreciation | E80: =FCFF!H52 -> 0 | F80: =FCFF!N52 -> 0 | G80: =FCFF!T52 -> 0 | H80: =H81*G111 -> 0 | I80: =I81*H111 -> 0 | J80: =J81*I111 -> 0 | K80: =K81*J111 -> 0 | L80: =L81*K111 -> 0
B81: % of net pp&e | E81: =E80/E111 -> 0 | F81: =FCFF!N53 -> 0 | G81: =FCFF!T53 -> 0
B83: Amortization | E83: =FCFF!H55 -> 0 | F83: =FCFF!N55 -> 0 | G83: =FCFF!T55 -> 0 | H83: =H84*G114 -> 0 | I83: =I84*H114 -> 0 | J83: =J84*I114 -> 0 | K83: =K84*J114 -> 0 | L83: =L84*K114 -> 0
B84: % of intangibles excl. goodwill | E84: =E83/E114 -> #DIV/0! | F84: =F83/F114 -> #DIV/0! | G84: =G83/G114 -> #DIV/0!
B86: EBIT (Operating Income) | E86: =FCFF!H61 -> 32.391 | F86: =FCFF!N61 -> 105.895 | G86: =FCFF!T61 -> 151.268 | H86: =H68-H71-H74-H77 -> 350000 | I86: =I68-I71-I74-I77 -> 352000 | J86: =J68-J71-J74-J77 -> 350000 | K86: =K68-K71-K74-K77 -> 352000 | L86: =L68-L71-L74-L77 -> 350000
B87: % of sales | E87: =E86/E59 -> 0.071525574 | F87: =F86/F59 -> 0.20806603 | G87: =G86/G59 -> 0.28760198 | H87: =H86/H59 -> 1 | I87: =I86/I59 -> 1 | J87: =J86/J59 -> 1 | K87: =K86/K59 -> 1 | L87: =L86/L59 -> 1
B89: Net Interest (Income) Expense | E89: =IS!T38 -> 0 | F89: =IS!Z38 -> 0 | G89: =IS!AF38 -> 44.708 | H89: =+H164 -> 0 | I89: =+I164 -> 0 | J89: =+J164 -> 0 | K89: =+K164 -> 0 | L89: =+L164 -> 0
B91: Pre-tax income | E91: =IS!T42 -> 6.634 | F91: =IS!Z42 -> 54.6 | G91: =IS!AF42 -> 100.076 | H91: =+H86-H89 -> 350000 | I91: =+I86-I89 -> 352000 | J91: =+J86-J89 -> 350000 | K91: =+K86-K89 -> 352000 | L91: =+L86-L89 -> 350000
B92: % of sales | E92: =E91/E59 -> 0.014649151 | F92: =F91/F59 -> 0.1072799 | G92: =G91/G59 -> 0.19027194 | H92: =H91/H59 -> 1 | I92: =I91/I59 -> 1 | J92: =J91/J59 -> 1 | K92: =K91/K59 -> 1 | L92: =L91/L59 -> 1
B94: Income tax expenses (benefits) | E94: =IS!T45 -> 0.791 | F94: =IS!Z45 -> 12.2484 | G94: =IS!AF45 -> 16.8222 | H94: =H95*H91 -> 0 | I94: =I95*I91 -> 0 | J94: =J95*J91 -> 0 | K94: =K95*K91 -> 0 | L94: =L95*L91 -> 0
B95: % tax rate | E95: =E94/E91 -> 0.11923425 | F95: =F94/F91 -> 0.22432967 | G95: =G94/G91 -> 0.16809425
B97: Net income | E97: =IS!T47 -> 5.843 | F97: =IS!Z47 -> 42.3516 | G97: =IS!AF47 -> 83.2538 | H97: =H91-H94 -> 350000 | I97: =I91-I94 -> 352000 | J97: =J91-J94 -> 350000 | K97: =K91-K94 -> 352000 | L97: =L91-L94 -> 350000
B98: % of sales | E98: =E97/E59 -> 0.012902471 | F98: =F97/F59 -> 0.083213839 | G98: =G97/G59 -> 0.15828832 | H98: =H97/H59 -> 1 | I98: =I97/I59 -> 1 | J98: =J97/J59 -> 1 | K98: =K97/K59 -> 1 | L98: =L97/L59 -> 1
A100: x | B100: Balance Sheet | E100: =E57 -> 2022 | F100: =F57 -> 2023 | G100: =G57 -> 2024 | H100: =H57 -> 2025 | I100: =I57 -> 2026 | J100: =J57 -> 2027 | K100: =K57 -> 2028 | L100: =L57 -> 2029
B102: Accounts Receivable | E102: =FCFF!H70 -> 0 | F102: =FCFF!N70 -> 0 | G102: =FCFF!T70 -> 0 | H102: =+H103*H59/365 -> 0 | I102: =+I103*I59/365 -> 0 | J102: =+J103*J59/365 -> 0 | K102: =+K103*K59/366 -> 0 | L102: =+L103*L59/365 -> 0
B103: days sales outstanding | E103: =FCFF!H71 -> 0 | F103: =FCFF!N71 -> 0 | G103: =FCFF!T71 -> 0
B105: Inventory | E105: =FCFF!H73 -> 0 | F105: =FCFF!N73 -> 0 | G105: =FCFF!T73 -> 0 | H105: =+H106*H62/365 -> 0 | I105: =+I106*I62/365 -> 0 | J105: =+J106*J62/365 -> 0 | K105: =+K106*K62/366 -> 0 | L105: =+L106*L62/365 -> 0
B106: days inventory held | E106: =FCFF!H74 -> 0 | F106: =FCFF!N74 -> 0 | G106: =FCFF!T74 -> 0
B108: Prepaid expenses and Other Current Assets | E108: =FCFF!H76 -> 33.431 | F108: =FCFF!N76 -> 42.152 | G108: =FCFF!T76 -> 26.944 | H108: =+H109*H59 -> 0 | I108: =+I109*I59 -> 0 | J108: =+J109*J59 -> 0 | K108: =+K109*K59 -> 0 | L108: =+L109*L59 -> 0
B109: % of sales | E109: =FCFF!H77 -> 0.073822095 | F109: =FCFF!N77 -> 0.082821658 | G109: =FCFF!T77 -> 0.051227938
B111: Net PP&E (Property, Plant and Equipment) | E111: =FCFF!H79 -> 27.626 | F111: =FCFF!N79 -> 22.472 | G111: =FCFF!T79 -> 24.259 | H111: =+G111-H112*H131-H80-H65 -> 24.259 | I111: =+H111-I112*I131-I80-I65 -> 24.259 | J111: =+I111-J112*J131-J80-J65 -> 24.259 | K111: =+J111-K112*K131-K80-K65 -> 24.259 | L111: =+K111-L112*L131-L80-L65 -> 24.259
B112: capex allocation rate | E112: =FCFF!H80 -> 0 | F112: =FCFF!N80 -> 0 | G112: =FCFF!T80 -> 0
B114: Intangibles excl. Goodwill | E114: =FCFF!H82 -> 0 | F114: =FCFF!N82 -> 0 | G114: =FCFF!T82 -> 0 | H114: =+G114+H115*H74-(1-H112)*H131-H83 -> 70000 | I114: =+H114+I115*I74-(1-I112)*I131-I83 -> 140400 | J114: =+I114+J115*J74-(1-J112)*J131-J83 -> 210400 | K114: =+J114+K115*K74-(1-K112)*K131-K83 -> 280800 | L114: =+K114+L115*L74-(1-L112)*L131-L83 -> 350800
B115: r&d conversion rate | E115: =FCFF!H83 | F115: =FCFF!N83 | G115: =FCFF!T83
B117: Accounts Payable | E117: =FCFF!H85 -> 27.258 | F117: =FCFF!N85 -> 26.448 | G117: =FCFF!T85 -> 33.29 | H117: =+H118*H62/365 -> 0 | I117: =+I118*I62/365 -> 0 | J117: =+J118*J62/365 -> 0 | K117: =+K118*K62/366 -> 0 | L117: =+L118*L62/365 -> 0
B118: days payable outstanding | E118: =FCFF!H86 -> 95.781139 | F118: =FCFF!N86 -> 89.591001 | G118: =FCFF!T86 -> 120.26377
B120: Accrued Expenses and Other Current Liabilities | E120: =FCFF!H88 -> 0 | F120: =FCFF!N88 -> 0 | G120: =FCFF!T88 -> 0 | H120: =+H121*H71 -> 0 | I120: =+I121*I71 -> 0 | J120: =+J121*J71 -> 0 | K120: =+K121*K71 -> 0 | L120: =+L121*L71 -> 0
B121: % of sg&a | E121: =FCFF!H89 -> 0 | F121: =FCFF!N89 -> 0 | G121: =FCFF!T89 -> 0
A123: x | B123: Cash Flow | E123: =E57 -> 2022 | F123: =F57 -> 2023 | G123: =G57 -> 2024 | H123: =H57 -> 2025 | I123: =I57 -> 2026 | J123: =J57 -> 2027 | K123: =K57 -> 2028 | L123: =L57 -> 2029
B125: D&A (Depreciation & Amortization) | E125: =FCFF!H94 -> 13.581 | F125: =FCFF!N94 -> 12.735 | G125: =FCFF!T94 -> 9.621 | H125: =+H77+H65 -> 0 | I125: =+I77+I65 -> 0 | J125: =+J77+J65 -> 0 | K125: =+K77+K65 -> 0 | L125: =+L77+L65 -> 0
B126: % of net pp&e and intangibles excl. Goodwill | E126: =FCFF!H95 -> 0.49160211 | F126: =FCFF!N95 -> 0.56670523 | G126: =FCFF!T95 -> 0.39659508 | H126: =+H125/(H111+H114) -> 0 | I126: =+I125/(I111+I114) -> 0 | J126: =+J125/(J111+J114) -> 0 | K126: =+K125/(K111+K114) -> 0 | L126: =+L125/(L111+L114) -> 0
B128: Changes in Net Working Capital | E128: =FCFF!H103 -> -9.338 | F128: =FCFF!N103 -> -1.953 | G128: =FCFF!T103 -> 6.425 | H128: =-((H102+H105+H108-H117-H120)-(G102+G105+G108-G117-G120)) -> -6.346 | I128: =-((I102+I105+I108-I117-I120)-(H102+H105+H108-H117-H120)) -> 0 | J128: =-((J102+J105+J108-J117-J120)-(I102+I105+I108-I117-I120)) -> 0 | K128: =-((K102+K105+K108-K117-K120)-(J102+J105+J108-J117-J120)) -> 0 | L128: =-((L102+L105+L108-L117-L120)-(K102+K105+K108-K117-K120)) -> 0
B129: % of change in sales | E129: =FCFF!H104 -> -0.026754224 | F129: =FCFF!N104 -> -0.0043126006 | G129: =FCFF!T104 -> 0.012624055 | H129: =H128/(H59-G59) -> -1.8158717e-05 | I129: =I128/(I59-H59) -> 0 | J129: =J128/(J59-I59) -> 0 | K129: =K128/(K59-J59) -> 0 | L129: =L128/(L59-K59) -> 0
B131: Net CapEx | E131: =FCFF!H106+FCFF!H109 -> -13.25 | F131: =FCFF!N106+FCFF!N109 -> -8.991 | G131: =FCFF!T106+FCFF!T109 -> -13.01 | H131: =-H132*H59 -> -70000 | I131: =-I132*I59 -> -70400 | J131: =-J132*J59 -> -70000 | K131: =-K132*K59 -> -70400 | L131: =-L132*L59 -> -70000
B132: % of sales | E132: =FCFF!H107 -> 0.029258555 | F132: =FCFF!N107 -> 0.017665817 | G132: =FCFF!T107 -> 0.02473558 | H132: 0.2 | I132: 0.2 | J132: 0.2 | K132: 0.2 | L132: 0.2
A134: x | B134: Levered Free Cash Flow | H134: =H57 -> 2025 | I134: =I57 -> 2026 | J134: =J57 -> 2027 | K134: =K57 -> 2028 | L134: =L57 -> 2029
B136: Net Income | H136: =H97 -> 350000 | I136: =I97 -> 352000 | J136: =J97 -> 350000 | K136: =K97 -> 352000 | L136: =L97 -> 350000
B137: Changes in NWC | H137: =+H125 -> 0 | I137: =+I125 -> 0 | J137: =+J125 -> 0 | K137: =+K125 -> 0 | L137: =+L125 -> 0
B138: D&A (Depreciation & Amortization) | H138: =+H128 -> -6.346 | I138: =+I128 -> 0 | J138: =+J128 -> 0 | K138: =+K128 -> 0 | L138: =+L128 -> 0
B139: Net CapEx | H139: =+H131 -> -70000 | I139: =+I131 -> -70400 | J139: =+J131 -> -70000 | K139: =+K131 -> -70400 | L139: =+L131 -> -70000
B140: Leveraged Free Cash Flow | H140: =H136+H137+H138+H139 -> 279993.65 | I140: =I136+I137+I138+I139 -> 281600 | J140: =J136+J137+J138+J139 -> 280000 | K140: =K136+K137+K138+K139 -> 281600 | L140: =L136+L137+L138+L139 -> 280000
A142: x | B142: Debt Schedule | H142: =H134 -> 2025 | I142: =I134 -> 2026 | J142: =J134 -> 2027 | K142: =K134 -> 2028 | L142: =L134 -> 2029
B144: Revolver
B145: Beginning Balance | H145: =G148 -> 0 | I145: =H148 -> 0 | J145: =I148 -> 0 | K145: =J148 -> 0 | L145: =K148 -> 0
B146: Interest | H146: =H145*$J$11 -> 0 | I146: =I145*$J$11 -> 0 | J146: =J145*$J$11 -> 0 | K146: =K145*$J$11 -> 0 | L146: =L145*$J$11 -> 0
B147: Paydown | H147: =MIN(H140,H145) -> 0 | I147: =MIN(I140,I145) -> 0 | J147: =MIN(J140,J145) -> 0 | K147: =MIN(K140,K145) -> 0 | L147: =MIN(L140,L145) -> 0
B148: Ending Balance | G148: =L11 -> 0 | H148: =H145-H147 -> 0 | I148: =I145-I147 -> 0 | J148: =J145-J147 -> 0 | K148: =K145-K147 -> 0 | L148: =L145-L147 -> 0
B150: Bank Loan
B151: Beginning Balance | H151: =G154 -> 0 | I151: =H154 -> 0 | J151: =I154 -> 0 | K151: =J154 -> 0 | L151: =K154 -> 0
B152: Interest | H152: =H151*$J$12 -> 0 | I152: =I151*$J$12 -> 0 | J152: =J151*$J$12 -> 0 | K152: =K151*$J$12 -> 0 | L152: =L151*$J$12 -> 0
B153: Paydown | H153: =MIN(H151,H140-H147) -> 0 | I153: =MIN(I151,I140-I147) -> 0 | J153: =MIN(J151,J140-J147) -> 0 | K153: =MIN(K151,K140-K147) -> 0 | L153: =MIN(L151,L140-L147) -> 0
B154: Ending Balance | G154: =L12 -> 0 | H154: =H151-H153 -> 0 | I154: =I151-I153 -> 0 | J154: =J151-J153 -> 0 | K154: =K151-K153 -> 0 | L154: =L151-L153 -> 0
B156: Senior Note
B157: Beginning Balance | H157: =G160 -> 0 | I157: =H160 -> 0 | J157: =I160 -> 0 | K157: =J160 -> 0 | L157: =K160 -> 0
B158: Interest | H158: =H157*$J$13 -> 0 | I158: =I157*$J$13 -> 0 | J158: =J157*$J$13 -> 0 | K158: =K157*$J$13 -> 0 | L158: =L157*$J$13 -> 0
B159: Paydown | H159: =MIN(H157,H140-H147-H153) -> 0 | I159: =MIN(I157,I140-I147-I153) -> 0 | J159: =MIN(J157,J140-J147-J153) -> 0 | K159: =MIN(K157,K140-K147-K153) -> 0 | L159: =MIN(L157,L140-L147-L153) -> 0
B160: Ending Balance | G160: =L13 -> 0 | H160: =H157-H159 -> 0 | I160: =I157-I159 -> 0 | J160: =J157-J159 -> 0 | K160: =K157-K159 -> 0 | L160: =L157-L159 -> 0
B162: Total Debt
B163: Beginning Balance | H163: =H145+H151+H157 -> 0 | I163: =I145+I151+I157 -> 0 | J163: =J145+J151+J157 -> 0 | K163: =K145+K151+K157 -> 0 | L163: =L145+L151+L157 -> 0
B164: Interest | H164: =H146+H152+H158 -> 0 | I164: =I146+I152+I158 -> 0 | J164: =J146+J152+J158 -> 0 | K164: =K146+K152+K158 -> 0 | L164: =L146+L152+L158 -> 0
B165: Paydown | H165: =H147+H153+H159 -> 0 | I165: =I147+I153+I159 -> 0 | J165: =J147+J153+J159 -> 0 | K165: =K147+K153+K159 -> 0 | L165: =L147+L153+L159 -> 0
...

Sheet Sensitivity
B7: Monte-Carlo Simulations | R7: Tornado Chart – Effect on Price Target
AD28: {=_xlfn.SORTBY(R38:Z44,Z38:Z44,1)} -> SG&A Margin | AE28: 0 | AF28: 0.05 | AG28: 0 | AH28: 20.259715 | AI28: 20.337796 | AJ28: -0.041032428 | AK28: 0.037048987 | AL28: 0.041032428
AD29: COGS Margin | AE29: 0 | AF29: 0.05 | AG29: 0 | AH29: 19.748927 | AI29: 20.897701 | AJ29: -0.55182044 | AK29: 0.59695399 | AL29: 0.59695399
AD30: Capex Intensity | AE30: 0 | AF30: 0.02 | AG30: 0 | AH30: 18.861958 | AI30: 21.739537 | AJ30: -1.4387895 | AK30: 1.4387895 | AL30: 1.4387895
AD31: EBITDA Exit | AE31: 0 | AF31: 0.5 | AG31: 0 | AH31: 18.153392 | AI31: 22.448103 | AJ31: -2.1473554 | AK31: 2.1473554 | AL31: 2.1473554
R32: Reference Price Target | V32: Base Price Target | Z32: Reference | AD32: WACC | AE32: 0 | AF32: 0.005 | AG32: 0 | AH32: 17.948104 | AI32: 22.847076 | AJ32: -2.3526438 | AK32: 2.5463281 | AL32: 2.5463281
R33: Gordon PT | T33: =+FCFF!AL169 -> 48.067081 | V33: Base Gordon PT | X33: 47.57748 | Z33: EBITDA | AD33: Revenue Exit | AE33: 0 | AF33: 0.5 | AG33: 0 | AH33: 12.977293 | AI33: 27.127393 | AJ33: -7.3234542 | AK33: 6.8266452 | AL33: 7.3234542
R34: EBITDA PT | T34: =+FCFF!Z169 -> 20.528363 | V34: Base EBITDA PT | X34: 20.300747 | AD34: Terminal g | AE34: 0 | AF34: 0.01 | AG34: 0 | AH34: 40.821951 | AI34: 56.707688 | AJ34: 20.521203 | AK34: 36.40694 | AL34: 36.40694
R35: Revenue PT | T35: =FCFF!AF169 -> 20.277514 | V35: Base Revenue PT | X35: 20.052343
T37: Δ | U37: Δ Applied | V37: PT Low | W37: PT High | X37: Δ Low | Y37: Δ High | Z37: Max
R38: Capex Intensity | T38: 0.02 | V38: 18.861958 | W38: 21.739537 | X38: {=+V38-_xlfn.IFS($Z$33="EBITDA",$X$34,$Z$33="Revenue",$X$35,$Z$33="Gordon",$X$33)} -> -1.4387895 | Y38: {=+W38-_xlfn.IFS($Z$33="EBITDA",$X$34,$Z$33="Revenue",$X$35,$Z$33="Gordon",$X$33)} -> 1.4387895 | Z38: =MAX(ABS(X38),ABS(Y38)) -> 1.4387895
R39: COGS Margin | T39: 0.05 | V39: 19.748927 | W39: 20.897701 | X39: {=+V39-_xlfn.IFS($Z$33="EBITDA",$X$34,$Z$33="Revenue",$X$35,$Z$33="Gordon",$X$33)} -> -0.55182044 | Y39: {=+W39-_xlfn.IFS($Z$33="EBITDA",$X$34,$Z$33="Revenue",$X$35,$Z$33="Gordon",$X$33)} -> 0.59695399 | Z39: =MAX(ABS(X39),ABS(Y39)) -> 0.59695399
R40: SG&A Margin | T40: 0.05 | V40: 20.259715 | W40: 20.337796 | X40: {=+V40-_xlfn.IFS($Z$33="EBITDA",$X$34,$Z$33="Revenue",$X$35,$Z$33="Gordon",$X$33)} -> -0.041032428 | Y40: {=+W40-_xlfn.IFS($Z$33="EBITDA",$X$34,$Z$33="Revenue",$X$35,$Z$33="Gordon",$X$33)} -> 0.037048987 | Z40: =MAX(ABS(X40),ABS(Y40)) -> 0.041032428
R41: WACC | T41: 0.005 | V41: 17.948104 | W41: 22.847076 | X41: {=+V41-_xlfn.IFS($Z$33="EBITDA",$X$34,$Z$33="Revenue",$X$35,$Z$33="Gordon",$X$33)} -> -2.3526438 | Y41: {=+W41-_xlfn.IFS($Z$33="EBITDA",$X$34,$Z$33="Revenue",$X$35,$Z$33="Gordon",$X$33)} -> 2.5463281 | Z41: =MAX(ABS(X41),ABS(Y41)) -> 2.5463281
R42: Terminal g | T42: 0.01 | V42: 40.821951 | W42: 56.707688 | X42: {=+V42-_xlfn.IFS($Z$33="EBITDA",$X$34,$Z$33="Revenue",$X$35,$Z$33="Gordon",$X$33)} -> 20.521203 | Y42: {=+W42-_xlfn.IFS($Z$33="EBITDA",$X$34,$Z$33="Revenue",$X$35,$Z$33="Gordon",$X$33)} -> 36.40694 | Z42: =MAX(ABS(X42),ABS(Y42)) -> 36.40694
R43: EBITDA Exit | T43: 0.5 | V43: 18.153392 | W43: 22.448103 | X43: {=+V43-_xlfn.IFS($Z$33="EBITDA",$X$34,$Z$33="Revenue",$X$35,$Z$33="Gordon",$X$33)} -> -2.1473554 | Y43: {=+W43-_xlfn.IFS($Z$33="EBITDA",$X$34,$Z$33="Revenue",$X$35,$Z$33="Gordon",$X$33)} -> 2.1473554 | Z43: =MAX(ABS(X43),ABS(Y43)) -> 2.1473554
R44: Revenue Exit | T44: 0.5 | V44: 12.977293 | W44: 27.127393 | X44: {=+V44-_xlfn.IFS($Z$33="EBITDA",$X$34,$Z$33="Revenue",$X$35,$Z$33="Gordon",$X$33)} -> -7.3234542 | Y44: {=+W44-_xlfn.IFS($Z$33="EBITDA",$X$34,$Z$33="Revenue",$X$35,$Z$33="Gordon",$X$33)} -> 6.8266452 | Z44: =MAX(ABS(X44),ABS(Y44)) -> 7.3234542
F46: Historical VaR | H46: Parametric VaR | J46: Monte Carlos VaR
C47: Confidence Level 95.0% | F47: 0.0661 | H47: 0.072 | J47: 0.669
C48: Confidence Level 99.0% | F48: 0.0893 | H48: 0.104 | J48: 0.782

Sheet IS
B7: Income Statement | D7: 2020 | E7: 2020 | F7: 2020 | G7: 2020 | H7: 2020 | J7: 2021 | K7: 2021 | L7: 2021 | M7: 2021 | N7: 2021 | P7: 2022 | Q7: 2022 | R7: 2022 | S7: 2022 | T7: 2022 | V7: 2023 | W7: 2023 | X7: 2023 | Y7: 2023 | Z7: 2023 | AB7: 2024 | AC7: 2024 | AD7: 2024 | AE7: 2024 | AF7: 2024 | AH7: 2025 | AI7: 2025 | AJ7: 2025 | AK7: 2025 | AL7: 2025 | AN7: 2025 | AO7: 2025 | AP7: 2025 | AQ7: 2025 | AR7: 2025
D8: 2020 | J8: 2021 | P8: 2022 | V8: 2023 | AB8: 2024 | AH8: 2025 | AN8: 2026 | AT8: 2027 | AV8: 2028 | AX8: 2029
D9: Q1 | E9: Q2 | F9: Q3 | G9: Q4 | H9: FY | J9: Q1 | K9: Q2 | L9: Q3 | M9: Q4 | N9: FY | P9: Q1 | Q9: Q2 | R9: Q3 | S9: Q4 | T9: FY | V9: Q1 | W9: Q2 | X9: Q3 | Y9: Q4 | Z9: FY | AB9: Q1 | AC9: Q2 | AD9: Q3 | AE9: Q4 | AF9: FY | AH9: Q1 | AI9: Q2 | AJ9: Q3 | AK9: Q4 | AL9: FY | AN9: Q1 | AO9: Q2 | AP9: Q3 | AQ9: Q4 | AR9: FY | AT9: FY | AV9: FY | AX9: FY
B12: Revenue:
B13: Segment 1 | D13: 0 | E13: 0 | F13: 0 | G13: 0 | H13: 0 | J13: 0 | K13: 0 | L13: 0 | M13: 0 | N13: 0 | P13: 0 | Q13: 0 | R13: 0 | S13: 0 | T13: 0 | V13: 0 | W13: 0 | X13: 0 | Y13: 0 | Z13: 0 | AB13: 0 | AC13: 0 | AD13: 0 | AE13: 0 | AF13: 0 | AH13: 0 | AI13: 0 | AJ13: 0 | AK13: 0 | AL13: 0 | AN13: 0 | AO13: 0 | AP13: 0 | AQ13: 0 | AR13: 0 | AT13: 0 | AV13: 0 | AX13: 0
B14: Segment 2 | D14: 0 | E14: 0 | F14: 0 | G14: 0 | H14: 0 | J14: 0 | K14: 0 | L14: 0 | M14: 0 | N14: 0 | P14: 0 | Q14: 0 | R14: 0 | S14: 0 | T14: 0 | V14: 0 | W14: 0 | X14: 0 | Y14: 0 | Z14: 0 | AB14: 0 | AC14: 0 | AD14: 0 | AE14: 0 | AF14: 0 | AH14: 0 | AI14: 0 | AJ14: 0 | AK14: 0 | AL14: 0 | AN14: 0 | AO14: 0 | AP14: 0 | AQ14: 0 | AR14: 0 | AT14: 0 | AV14: 0 | AX14: 0
B15: Segment 3 | D15: 0 | E15: 0 | F15: 0 | G15: 0 | H15: 0 | J15: 0 | K15: 0 | L15: 0 | M15: 0 | N15: 0 | P15: 0 | Q15: 0 | R15: 0 | S15: 0 | T15: 0 | V15: 0 | W15: 0 | X15: 0 | Y15: 0 | Z15: 0 | AB15: 0 | AC15: 0 | AD15: 0 | AE15: 0 | AF15: 0 | AH15: 0 | AI15: 0 | AJ15: 0 | AK15: 0 | AL15: 0 | AN15: 0 | AO15: 0 | AP15: 0 | AQ15: 0 | AR15: 0 | AT15: 0 | AV15: 0 | AX15: 0
B16: Segment 4 | D16: 0 | E16: 0 | F16: 0 | G16: 0 | H16: 0 | J16: 0 | K16: 0 | L16: 0 | M16: 0 | N16: 0 | P16: 0 | Q16: 0 | R16: 0 | S16: 0 | T16: 0 | V16: 0 | W16: 0 | X16: 0 | Y16: 0 | Z16: 0 | AB16: 0 | AC16: 0 | AD16: 0 | AE16: 0 | AF16: 0 | AH16: 0 | AI16: 0 | AJ16: 0 | AK16: 0 | AL16: 0 | AN16: 0 | AO16: 0 | AP16: 0 | AQ16: 0 | AR16: 0 | AT16: 0 | AV16: 0 | AX16: 0
B17: Segment 5 | D17: 0 | E17: 0 | F17: 0 | G17: 0 | H17: 0 | J17: 0 | K17: 0 | L17: 0 | M17: 0 | N17: 0 | P17: 0 | Q17: 0 | R17: 0 | S17: 0 | T17: 0 | V17: 0 | W17: 0 | X17: 0 | Y17: 0 | Z17: 0 | AB17: 0 | AC17: 0 | AD17: 0 | AE17: 0 | AF17: 0 | AH17: 0 | AI17: 0 | AJ17: 0 | AK17: 0 | AL17: 0 | AN17: 0 | AO17: 0 | AP17: 0 | AQ17: 0 | AR17: 0 | AT17: 0 | AV17: 0 | AX17: 0
B18: Total revenue | D18: 0 | E18: 0 | F18: 0 | G18: 0 | H18: 0 | J18: 0 | K18: 0 | L18: 91.448 | M18: 95.958 | N18: 349.029 | P18: 100.336 | Q18: 107.873 | R18: 123.605 | S18: 120.03 | T18: 452.859 | V18: 120.374 | W18: 122.486 | X18: 133.165 | Y18: 132.924 | Z18: 508.949 | AB18: 127.343 | AC18: 126.304 | AD18: 136.593 | AE18: 135.723 | AF18: 525.963 | AH18: 140.268 | AI18: 142.443 | AJ18: =FCFF!X31 -> 150.10346 | AK18: =FCFF!Y31 -> 156.13393 | AL18: =FCFF!Z31 -> 723.55312 | AM18: =FCFF!AA31 -> 0 | AN18: =FCFF!AB31 -> 162.48853 | AO18: =FCFF!AC31 -> 168.79837 | AP18: =FCFF!AD31 -> 176.86832 | AQ18: =FCFF!AE31 -> 186.71815 | ... AX18: =FCFF!AL31 -> 1656.4544
A20: x | B20: Cost of revenue:
B21: Cost of goods and services | D21: 0 | E21: 0 | F21: 0.001 | G21: 0 | H21: 0 | J21: 0 | K21: 0 | L21: 0 | M21: 0 | N21: 0 | P21: =P75 -> 23.402 | Q21: =Q75 -> 29.396 | R21: =R75 -> 24.728 | S21: =S75 -> 26.348 | T21: =T75 -> 103.874 | U21: =U75 -> 0 | V21: =V75 -> 24.289 | W21: =W75 -> 27.014 | ... AI21: =AI75 -> 23.053 | AJ21: 0 | AK21: 0 | AL21: 0 | AN21: 0 | AO21: 0 | AP21: 0 | AQ21: 0 | AR21: 0 | AT21: 0 | AV21: 0 | AX21: 0
B22: Depreciation & amortization | D22: 0 | E22: 0 | F22: 0 | G22: 0 | H22: 0 | J22: 0 | K22: 0 | L22: 0 | M22: 0 | N22: 0 | P22: 0 | Q22: 0 | R22: 0 | S22: 0 | T22: 0 | V22: 0 | W22: 0 | X22: 0 | Y22: 0 | Z22: 0 | AB22: 0 | AC22: 0 | AD22: 0 | AE22: 0 | AF22: 0 | AH22: 0 | AI22: 0 | AJ22: 0 | AK22: 0 | AL22: 0 | AN22: 0 | AO22: 0 | AP22: 0 | AQ22: 0 | AR22: 0 | AT22: 0 | AV22: 0 | AX22: 0
B23: Total cost of revenue | D23: 0 | E23: 0 | F23: 0.001 | G23: 0 | H23: 0 | J23: 0 | K23: 0 | L23: 0 | M23: 0 | N23: 0 | P23: 0 | Q23: 0 | R23: 0 | S23: 0 | T23: 0 | V23: 0 | W23: 0 | X23: 0 | Y23: 0 | Z23: 0 | AB23: 0 | AC23: 0 | AD23: 0 | AE23: 0 | AF23: 0 | AH23: 0 | AI23: 0 | AJ23: 25000 | AK23: 25000 | AL23: 50000 | AN23: 22000 | AO23: 22000 | AP23: 22000 | AQ23: 22000 | AR23: 88000 | AT23: 90000 | AV23: 87000 | AX23: 105000
B24: Gross margin | D24: 0 | E24: 0 | F24: 0 | G24: 0 | H24: 0 | J24: 0 | K24: 0 | L24: 0 | M24: 0 | N24: 0 | P24: =P76 -> 76.934 | Q24: =Q76 -> 78.477 | R24: =R76 -> 98.877 | S24: =S76 -> 93.682 | T24: =T76 -> 348.985 | U24: =U76 -> 0 | V24: =V76 -> 96.085 | W24: =W76 -> 95.472 | ... AI24: =AI76 -> 119.39 | AJ24: 25000 | AK24: 25000 | AL24: 50000 | AN24: 22000 | AO24: 22000 | AP24: 22000 | AQ24: 22000 | AR24: 88000 | AT24: 90000 | AV24: 87000 | AX24: 105000
A26: x | B26: Operating expenses:
B27: Selling, general and administrative | D27: 0 | E27: 0 | F27: 0 | G27: 0 | H27: 0 | J27: 1.811 | K27: 0.5436 | L27: 19.716 | M27: 33.661 | N27: 66.322 | P27: 16.61 | Q27: 22.371 | R27: 15.841 | S27: 28.356 | T27: 70.159 | V27: 13.639 | W27: 16.737 | X27: 17.825 | Y27: 24.965 | Z27: 64.205 | AB27: 13.292 | AC27: 16.667 | AD27: 17.159 | AE27: 24.991 | AF27: 64.261 | AH27: 14.152 | AI27: 15.813 | AJ27: 0 | AK27: 0 | AL27: 29.965 | AN27: 0 | AO27: 0 | AP27: 0 | AQ27: 0 | AR27: 0 | AT27: 0 | AV27: 0 | AX27: 0
B28: Depreciation and amortization | D28: 0 | E28: 0 | F28: 0 | G28: 0 | H28: 0 | J28: 0 | K28: 0 | L28: 2.712 | M28: 0 | N28: 10.282 | P28: 3.238 | Q28: 3.366 | R28: 3.452 | S28: 0 | T28: 13.581 | V28: 3.391 | W28: 3.317 | X28: 3.119 | Y28: 0 | Z28: 12.735 | AB28: 2.725 | AC28: 2.49 | AD28: 2.28 | AE28: 0 | AF28: 9.621 | AH28: 1.76 | AI28: 1.502 | AJ28: 0 | AK28: 0 | AL28: 3.262 | AN28: 0 | AO28: 0 | AP28: 0 | AQ28: 0 | AR28: 0 | AT28: 0 | AV28: 0 | AX28: 0
B29: Research and development | D29: 0 | E29: 0 | F29: 0 | G29: 0 | H29: 0 | J29: 0 | K29: 0 | L29: 2.696 | M29: 7.774 | N29: 10.064 | P29: 3.135 | Q29: 3.287 | R29: 3.301 | S29: 8.59 | T29: 13.054 | V29: 3.166 | W29: 3.28 | X29: 3.141 | Y29: 9.696 | Z29: 12.543 | AB29: 3.058 | AC29: 2.963 | AD29: 3.041 | AE29: 8.275 | AF29: 12.171 | AH29: 2.961 | AI29: 3.382 | AJ29: 0 | AK29: 0 | AL29: 6.343 | AN29: 0 | AO29: 0 | AP29: 0 | AQ29: 0 | AR29: 0 | AT29: 0 | AV29: 0 | AX29: 0
B30: Other operating expenses | D30: 0 | E30: 0 | F30: 0 | G30: 0 | H30: 0 | J30: 0 | K30: 0 | L30: 55.341 | M30: 51.149 | N30: 182.387 | P30: 72.44 | Q30: 73.592 | R30: 102.544 | S30: 89.915 | T30: 323.674 | V30: 85.077 | W30: 80.818 | X30: 91.841 | Y30: 69.673 | Z30: 313.571 | AB30: 102.984 | AC30: 73.897 | AD30: 77.054 | AE30: 65.834 | AF30: 288.642 | AH30: 80.351 | AI30: 76.438 | AJ30: 0 | AK30: 0 | AL30: 156.789 | AN30: 0 | AO30: 0 | AP30: 0 | AQ30: 0 | AR30: 0 | AT30: 0 | AV30: 0 | AX30: 0
B31: Total operating expenses | D31: 0 | E31: 0 | F31: 0 | G31: 0 | H31: 0 | J31: 1.811 | K31: 0.5436 | L31: 80.465 | M31: 92.584 | N31: 269.055 | P31: 95.423 | Q31: 102.616 | R31: 125.138 | S31: 126.861 | T31: 420.468 | V31: 105.273 | W31: 104.152 | X31: 115.926 | Y31: 104.334 | Z31: 403.054 | AB31: 122.059 | AC31: 96.017 | AD31: 99.534 | AE31: 99.1 | AF31: 374.695 | AH31: 99.224 | AI31: 97.135 | AJ31: 0 | AK31: 0 | AL31: 196.359 | AN31: 0 | AO31: 0 | AP31: 0 | AQ31: 0 | AR31: 0 | AT31: 0 | AV31: 0 | AX31: 0
B32: Other operating income | D32: 0 | E32: 0 | F32: 0 | G32: 0 | H32: 0 | J32: 0 | K32: 0 | L32: 0.529 | M32: 0 | N32: 1.539 | P32: 0.374 | Q32: 0.002 | R32: 0.639 | S32: 0 | T32: 0 | V32: 0 | W32: 0 | X32: 0 | Y32: 0 | Z32: 0 | AB32: 0 | AC32: 0 | AD32: 0 | AE32: 0 | AF32: 0 | AH32: 0 | AI32: 0
B33: Operating income | D33: 0 | E33: 0 | F33: -0.001 | G33: 0 | H33: 0 | J33: -1.811 | K33: -0.5436 | L33: 11.512 | M33: 3.374 | N33: 81.513 | P33: 5.287 | Q33: 5.259 | R33: -0.894 | S33: -6.831 | T33: 32.391 | V33: 15.101 | W33: 18.334 | X33: 17.239 | Y33: 28.59 | Z33: 105.895 | AB33: 5.284 | AC33: 30.287 | AD33: 37.059 | AE33: 36.623 | AF33: 151.268 | AH33: 41.044 | AI33: 45.308 | AJ33: 25000 | AK33: 25000 | AL33: 50086.352 | AN33: 22000 | AO33: 22000 | AP33: 22000 | AQ33: 22000 | AR33: 88000 | AT33: 90000 | AV33: 87000 | AX33: 105000
A35: x | B35: Non-operating (income) loss:
B36: Interest expense | D36: 0 | E36: 0 | F36: 0 | G36: 0 | H36: 0 | J36: 0 | K36: 0 | L36: 0 | M36: 0 | N36: 24.119 | P36: 7.448 | Q36: 0 | R36: 0 | S36: 0 | T36: 35.162 | V36: 11.371 | W36: 0 | X36: 0 | Y36: 12.071 | Z36: 46.75 | AB36: 0 | AC36: 0 | AD36: 0 | AE36: 11.029 | AF36: 44.708 | AH36: 0 | AI36: 9.639
B37: Interest income | D37: 0 | E37: 0 | F37: 0 | G37: 0 | H37: 0 | J37: 0 | K37: 0 | L37: 0 | M37: 0 | N37: 0 | P37: 0 | Q37: 0 | R37: 0 | S37: 0 | T37: 0 | V37: 0 | W37: 0 | X37: 0 | Y37: 0 | Z37: 0 | AB37: 0 | AC37: 0 | AD37: 0 | AE37: 0 | AF37: 0 | AH37: 0 | AI37: 0
A38: x | B38: Net interest (income) expense | D38: 0 | E38: 0 | F38: 0 | G38: 0 | H38: 0 | J38: 0 | K38: 0 | L38: 0 | M38: 0 | N38: 0 | P38: 7.448 | Q38: 0 | R38: 0 | S38: 0 | T38: 0 | V38: 11.371 | W38: 0 | X38: 0 | Y38: 0 | Z38: 0 | AB38: 0 | AC38: 0 | AD38: 0 | AE38: 11.029 | AF38: 44.708 | AH38: 0 | AI38: 0
B39: Foreign exchange (gains) losses | D39: 0 | E39: 0 | F39: 0 | G39: 0 | H39: 0 | J39: 0 | K39: 0 | L39: 0 | M39: 0 | N39: 0 | P39: 0 | Q39: 0 | R39: 0 | S39: 0 | T39: 0 | V39: 0 | W39: 0 | X39: 0 | Y39: 0 | Z39: 0 | AB39: 0 | AC39: 0 | AD39: 0 | AE39: 0 | AF39: 0 | AH39: 0 | AI39: 0
B40: Other non-operating (income) expenses | D40: 0 | E40: 0 | F40: 0 | G40: 0 | H40: 0 | J40: 1.275 | K40: -0.0061 | L40: -39.166 | M40: -26.532 | N40: -41.442 | P40: 0.006 | Q40: -3.297 | R40: -1.323 | S40: -2.381 | T40: 25.757 | V40: -1.279 | W40: -2.667 | X40: -0.414 | Y40: 17.805 | Z40: 51.295 | AB40: -6.283 | AC40: 0.897 | AD40: 0.738 | AE40: 10.1 | AF40: 6.484 | AH40: -1.765 | AI40: 32.104
B41: Total non-operating expenses | D41: 0 | E41: 0 | F41: 0 | G41: 0 | H41: 0 | J41: 1.275 | K41: -0.0061 | L41: -39.166 | M41: -26.532 | N41: -41.442 | P41: 7.454 | Q41: -3.297 | R41: -1.323 | S41: -2.381 | T41: 25.757 | V41: 10.092 | W41: -2.667 | X41: -0.414 | Y41: 17.805 | Z41: 51.295 | AB41: -6.283 | AC41: 0.897 | AD41: 0.738 | AE41: 21.129 | AF41: 51.192 | AH41: -1.765 | AI41: 32.104
B42: Pre-tax income | D42: 0 | E42: 0 | F42: -0.001 | G42: 0 | H42: 0 | J42: -3.086 | K42: -0.5376 | L42: 50.678 | M42: 29.906 | N42: 122.955 | P42: -2.167 | Q42: 8.556 | R42: 0.429 | S42: -4.45 | T42: 6.634 | V42: 5.009 | W42: 21.001 | X42: 17.653 | Y42: 10.785 | Z42: 54.6 | AB42: 11.567 | AC42: 29.39 | AD42: 36.321 | AE42: 15.494 | AF42: 100.076 | AH42: 42.809 | AI42: 13.204
A44: x | B44: Tax & net income:
B45: Income tax expenses (benefits) | D45: 0 | E45: 0 | F45: 0 | G45: 0 | H45: 0 | J45: 0 | K45: 0 | L45: 4.8154 | M45: 2.3939 | N45: 7.2093 | P45: 0.0341 | Q45: -0.038 | R45: 1.0259 | S45: -1.4496 | T45: 0.791 | V45: 0.9136 | W45: 4.1374 | X45: 4.6488 | Y45: 2.6739 | Z45: 12.2484 | AB45: 2.4634 | AC45: 2.3189 | AD45: 10.406 | AE45: 1.0528 | AF45: 16.8222 | AH45: 11.0227 | AI45: 1.6137
B46: Net extraordinary losses (gains) | D46: 0 | E46: 0 | F46: 0 | G46: 0 | H46: 0 | J46: 0 | K46: 3.302 | L46: 0 | M46: 0 | N46: 0 | P46: 0 | Q46: 0 | R46: 0 | S46: 0 | T46: 0 | V46: 0 | W46: 0 | X46: 0 | Y46: 0 | Z46: 0 | AB46: 0 | AC46: 0 | AD46: 0 | AE46: 0 | AF46: 0 | AH46: 0 | AI46: 0
B47: Net income including minority interest | D47: 0 | E47: 0 | F47: -0.001 | G47: 0 | H47: 0 | J47: -3.086 | K47: -3.8396 | L47: 45.8626 | M47: 27.5121 | N47: 115.7457 | P47: -2.2011 | Q47: 8.594 | R47: -0.5969 | S47: -3.0004 | T47: 5.843 | V47: 4.0954 | W47: 16.8636 | X47: 13.0042 | Y47: 8.1111 | Z47: 42.3516 | AB47: 9.1036 | AC47: 27.0711 | AD47: 25.915 | AE47: 14.4412 | AF47: 83.2538 | AH47: 31.7863 | AI47: 11.5903
A49: x | B49: Attribution:
B50: Preferred dividends | D50: 0 | E50: 0 | F50: 0 | G50: 0 | H50: 0 | J50: 0 | K50: 0 | L50: 0 | M50: 0 | N50: 0 | P50: 0 | Q50: 0 | R50: 0 | S50: 0 | T50: 0 | V50: 0 | W50: 0 | X50: 0 | Y50: 0 | Z50: 0 | AB50: 0 | AC50: 0 | AD50: 0 | AE50: 0 | AF50: 0 | AH50: 0 | AI50: 0
B51: Income attributable to non-controlling interests | D51: 0 | E51: 0 | F51: 0 | G51: 0 | H51: 0 | J51: 0 | K51: 0 | L51: 16.267 | M51: 5.603 | N51: 64.241 | P51: -1.373 | Q51: 6.039 | R51: -0.09 | S51: -8.335 | T51: -3.758 | V51: 3.679 | W51: 15.934 | X51: 13.363 | Y51: 7.509 | Z51: 40.484 | AB51: 4.594 | AC51: 24.61 | AD51: 27.793 | AE51: 19.582 | AF51: 76.579 | AH51: 31.762 | AI51: 32.26
