Workbook
Name COOLFUCNTION: _xlfn.LAMBDA(_xldudf_BOARDFLARE_EXEC("workbook-settings:coolfucntion"))
Name COOLFUCNTION: _xlfn.LAMBDA(_xldudf_BOARDFLARE_EXEC("workbook-settings:coolfucntion"))
Name COOLFUCNTION: _xlfn.LAMBDA(_xldudf_BOARDFLARE_EXEC("workbook-settings:coolfucntion"))
Name COOLFUCNTION: _xlfn.LAMBDA(_xldudf_BOARDFLARE_EXEC("workbook-settings:coolfucntion"))
Name COOLFUCNTION: _xlfn.LAMBDA(_xldudf_BOARDFLARE_EXEC("workbook-settings:coolfucntion"))
Name COOLFUCNTION: _xlfn.LAMBDA(_xldudf_BOARDFLARE_EXEC("workbook-settings:coolfucntion"))
Name COOLFUCNTION: _xlfn.LAMBDA(_xldudf_BOARDFLARE_EXEC("workbook-settings:coolfucntion"))
Name COOLFUCNTION: _xlfn.LAMBDA(_xldudf_BOARDFLARE_EXEC("workbook-settings:coolfucntion"))
Name COOLFUCNTION: _xlfn.LAMBDA(_xldudf_BOARDFLARE_EXEC("workbook-settings:coolfucntion"))
Name COOLFUCNTION: _xlfn.LAMBDA(_xldudf_BOARDFLARE_EXEC("workbook-settings:coolfucntion"))
Name COOLFUCNTION: _xlfn.LAMBDA(_xldudf_BOARDFLARE_EXEC("workbook-settings:coolfucntion"))
Name Sectors: #REF!
Name Sectors: #REF!
Name Sectors: #REF!
Name Sectors: #REF!
Name Sectors: #REF!
Name Sectors: #REF!
Name Sectors: #REF!
Name Sectors: #REF!

Sheet Dashboard
C154: =+C155+1 -> 45990
C155: =+C156+1 -> 45989
C156: =+C157+1 -> 45988
C157: =+C158+1 -> 45987
C158: =+C159+1 -> 45986
C159: =+C160+1 -> 45985
C160: =+C161+1 -> 45984 | L160: =IF(FCFF!$R$157="Revenue Exit",FCFF!$AF$169,IF(FCFF!$R$157="EBITDA Exit",FCFF!Z169,FCFF!AL169)) -> 188.76742
C161: =+C162+1 -> 45983
C162: =+C163+1 -> 45982 | E162: =IF(FCFF!$R$157="Revenue Exit",FCFF!$AF$169,IF(FCFF!$R$157="EBITDA Exit",FCFF!Z169,FCFF!AL169)) -> 188.76742
C163: =+C164+1 -> 45981 | E163: =E164+($E$162-$E$193)/COUNTA($C$162:$C$192) -> 189.64718
C164: =+C165+1 -> 45980 | E164: =E165+($E$162-$E$193)/COUNTA($C$162:$C$192) -> 190.52694
C165: =+C166+1 -> 45979 | E165: =E166+($E$162-$E$193)/COUNTA($C$162:$C$192) -> 191.4067
C166: =+C167+1 -> 45978 | E166: =E167+($E$162-$E$193)/COUNTA($C$162:$C$192) -> 192.28646
C167: =+C168+1 -> 45977 | E167: =E168+($E$162-$E$193)/COUNTA($C$162:$C$192) -> 193.16622
C168: =+C169+1 -> 45976 | E168: =E169+($E$162-$E$193)/COUNTA($C$162:$C$192) -> 194.04599
C169: =+C170+1 -> 45975 | E169: =E170+($E$162-$E$193)/COUNTA($C$162:$C$192) -> 194.92575
C170: =+C171+1 -> 45974 | E170: =E171+($E$162-$E$193)/COUNTA($C$162:$C$192) -> 195.80551
C171: =+C172+1 -> 45973 | E171: =E172+($E$162-$E$193)/COUNTA($C$162:$C$192) -> 196.68527
C172: =+C173+1 -> 45972 | E172: =E173+($E$162-$E$193)/COUNTA($C$162:$C$192) -> 197.56503
C173: =+C174+1 -> 45971 | E173: =E174+($E$162-$E$193)/COUNTA($C$162:$C$192) -> 198.44479
C174: =+C175+1 -> 45970 | E174: =E175+($E$162-$E$193)/COUNTA($C$162:$C$192) -> 199.32455
... C192: =+C193+1 -> 45952 | E192: =E193+($E$162-$E$193)/COUNTA($C$162:$C$192) -> 215.16024
B193: TODAY | C193: =+'Stock Data'!AM4 -> 45951 | D193: =_xlfn.XLOOKUP(C193,'Stock Data'!$AM$4:$AM$1051,'Stock Data'!$AN$4:$AN$1051) -> 216.04 | E193: =D193 -> 216.04
C194: =+'Stock Data'!AM5 -> 45950 | D194: =_xlfn.XLOOKUP(C194,'Stock Data'!$AM$4:$AM$1051,'Stock Data'!$AN$4:$AN$1051) -> 216.04
C195: =+'Stock Data'!AM6 -> 45949 | D195: =_xlfn.XLOOKUP(C195,'Stock Data'!$AM$4:$AM$1051,'Stock Data'!$AN$4:$AN$1051) -> 215.19
C196: =+'Stock Data'!AM7 -> 45948 | D196: =_xlfn.XLOOKUP(C196,'Stock Data'!$AM$4:$AM$1051,'Stock Data'!$AN$4:$AN$1051) -> 216.05
C197: =+'Stock Data'!AM8 -> 45947 | D197: =_xlfn.XLOOKUP(C197,'Stock Data'!$AM$4:$AM$1051,'Stock Data'!$AN$4:$AN$1051) -> 217.26
C198: =+'Stock Data'!AM9 -> 45946 | D198: =_xlfn.XLOOKUP(C198,'Stock Data'!$AM$4:$AM$1051,'Stock Data'!$AN$4:$AN$1051) -> 220.31
C199: =+'Stock Data'!AM10 -> 45945 | D199: =_xlfn.XLOOKUP(C199,'Stock Data'!$AM$4:$AM$1051,'Stock Data'!$AN$4:$AN$1051) -> 220.31
C200: =+'Stock Data'!AM11 -> 45944 | D200: =_xlfn.XLOOKUP(C200,'Stock Data'!$AM$4:$AM$1051,'Stock Data'!$AN$4:$AN$1051) -> 220.31
C201: =+'Stock Data'!AM12 -> 45943 | D201: =_xlfn.XLOOKUP(C201,'Stock Data'!$AM$4:$AM$1051,'Stock Data'!$AN$4:$AN$1051) -> 223.06
C202: =+'Stock Data'!AM13 -> 45942 | D202: =_xlfn.XLOOKUP(C202,'Stock Data'!$AM$4:$AM$1051,'Stock Data'!$AN$4:$AN$1051) -> 221.76
C203: =+'Stock Data'!AM14 -> 45941 | D203: =_xlfn.XLOOKUP(C203,'Stock Data'!$AM$4:$AM$1051,'Stock Data'!$AN$4:$AN$1051) -> 221.99
C204: =+'Stock Data'!AM15 -> 45940 | D204: =_xlfn.XLOOKUP(C204,'Stock Data'!$AM$4:$AM$1051,'Stock Data'!$AN$4:$AN$1051) -> 223.57
C205: =+'Stock Data'!AM16 -> 45939 | D205: =_xlfn.XLOOKUP(C205,'Stock Data'!$AM$4:$AM$1051,'Stock Data'!$AN$4:$AN$1051) -> 223.57
... C558: =+'Stock Data'!AM369 -> 45586 | D558: =_xlfn.XLOOKUP(C558,'Stock Data'!$AM$4:$AM$1051,'Stock Data'!$AN$4:$AN$1051) -> 248.89

Sheet Key Info
B7: Analysts | F7: LIS – Equity Research | J7: Stock Performance
B12: Mafalda Joana Bento, Co-Head of Equity Research | F12: Recommendation: | H12: Hold
B13: Bsc in Economics, ISEG – Ulisboa | F13: Target Price (FCFF): | H13: 187.91713
B14: mafaldajbento@aln.iseg.ulisboa.pt | F14: Downside: | H14: -0.13017434
B15: Deolize Neto, Analyst
B16: Bsc in Finance, ISEG – Ulisboa | F16: Ticker | H16: UNP
B17: l62144@aln.iseg.ulisboa.pt | F17: Stock Exchange | H17: NYS
B18: Guilherme Tomás, Analyst
B19: Bsc in Applied Mathematics, ISEG – Ulisboa | F19: Current Price | H19: ='Stock Data'!AN4 -> 216.04
B20: l63853@aln.iseg.ulisboa.pt | F20: ="Market Cap (in "&IF(Inputs!$D$14="BLN","billions",IF(Inputs!$D$14="MLN","millions","thousands"))&")" -> Market Cap (in millions) | H20: ='Stock Data'!AQ4 -> 128121.15
F21: Beta | H21: ='Stock Data'!E164 -> 0,81448
F22: % of 52-Week High | H22: ='Stock Data'!E165 -> 0,615945
F23: 100-Day Moving Average | H23: ='Stock Data'!E166 -> 2255855
B25: Reviewed by: | F25: Avg Vol (1 month) | H25: ='Stock Data'!E168 -> 4889126
B26: NAME, Analyst | F26: Shares Outstanding (millions) | H26: ='Stock Data'!E169 -> 5930437
B27: Bsc in XXX, ISEG – Ulisboa | F27: % Float | H27: ='Stock Data'!E170 -> 0.99
B28: email@aln.iseg.ulisboa.pt | F28: Short % of Float | H28: =IFERROR('Stock Data'!E171,0) -> 0.02
B30: LISBON INVESTMENT SOCIETY | F30: % Held by Insiders | H30: ='Stock Data'!E173 -> 0
B31: ISEG – Rua do Quelhas, 6 | F31: % Held by Institutions | H31: ='Stock Data'!E174 -> 0.85
B32: lis@iseg.ulisboa.pt
B34: Disclaimer: This report was prepared by members of the Lisbon Investment Society (LIS), an independent, student-led, non-profit organization based at ISEG – Lisbon School of Economics & Management, and is intended solely for academic and educational purposes. All analyses, forecasts, and opinions expressed in this report reflect the independent judgment of the authors as of the date of publication and are subject to change without notice. The views presented herein do not represent those of ISEG, its faculty, or any affiliated entity. This document does not constitute, and should not be interpreted as, investment advice, an offer, or a solicitation to buy or sell any security or financial instrument. Nothing in this report should be construed as a recommendation to make or refrain from making any investment decision. The content is intended for informational purposes only, and readers are strongly encouraged to conduct their own research and seek advice from a qualified financial professional before making any financial decisions. The information contained in this report has been obtained from publicly available sources believed to be reliable; however, no representation or warranty is made regarding the accuracy, completeness, or timeliness of such information. LIS and its members accept no liability whatsoever for any direct or indirect loss arising from the use of this report or its contents. This report incorporates terminology, financial metrics, and methodologies commonly used in professional equity research, including but not limited to Discounted Cash Flow (DCF), trading multiples, Monte Carlo simulations, and strategic analysis tools such as Porter’s Five Forces. Definitions and assumptions used in these models are disclosed within the report and reflect a hypothetical investment thesis designed solely for academic discussion. All valuations, projections, and target prices presented herein are based on publicly available data and subject to the limitations of modeling assumptions. These are not guarantees of future performance and should not be relied upon as such, as past performance is not indicative of future results. Any company names, logos, trademarks, or brand references mentioned in this report are the property of their respective owners and are used strictly for identification and academic purposes. This document may not be reproduced, redistributed, or quoted in whole or in part without the prior written consent of the Lisbon Investment Society. About LIS – Lisbon Investment Society: The Lisbon Investment Society (LIS) is a non-profit academic association headquartered at ISEG – Lisbon School of Economics & Management. Founded in 2016, LIS is committed to fostering student interest in finance and investment through applied research, skill development, and institutional engagement. The Society operates independently and autonomously from any political, religious, or commercial affiliation, and is composed of selected students and collaborators who are invited through a rigorous recruitment process and share a commitment to excellence, analytical rigor, and ethical standards. Its activities include equity research, portfolio management, macroeconomic analysis, and investment education. This report was prepared by the Equity Research team at the Lisbon Investment Society, whose analysts combine rigorous financial modeling, critical thinking, and collaborative research to deliver high-quality, student-led investment analysis. We welcome your feedback, discussion, and questions regarding this report or our research process, and invite you to reach out to our team as we are always open to engagement.

Sheet ESG
A7: x | B7: ESG Analysis
B12: ESG Scores | G12: GHG Scope 1 Emissions, Water Consumption, Energy Consumption and Waste Production per Sales
B15: LSEG ESG Score | D15: 71
B16: E-Score | D16: 53
B17: S-Score | D17: 93
B18: G-Score | D18: 64
B19: S&P Global ESG Score | D19: 60
B20: Environmental | D20: N/A
B21: Social | D21: N/A
B22: Governance & Economic | D22: N/A
B23: Sustainalytics | D23: 24.8
B24: ISS ESG Corporate Rating | D24: C+
B25: SDG Impact Rating | D25: 3.2
B26: Governance Quality Score | D26: 1
B27: MSCI ESG Ratings
B30: Key Info | G30: Environmental
H32: Overview | I32: Targets | J32: Improvements | K32: Comments
B33: GICS Sector | C33: Industrials | G33: GHG Scope 1 Emissions | I33: Reduce aboslute Scope 1,2,3 by 50.4% until 2030 | J33: Managed to achieve 37% of their set target as of 2024
B34: GICS Industry Group | C34: Transportation
B35: GICS Industry | C35: Road & Rail | G35: Water Consumption | I35: N/A | J35: The company implements policies and has commitments to reduce water consumption volume as mentioned in their 2024 CDP Questionnaire | K35: While the company recognize the importance of water conservation and responsible water management, it is not a significant part of their day-to-day operations. The commitment to sustainability and environmental responsibility is primarily addressed through various initiatives related to energy efficiency, emissions reduction, and resource conservation.
B36: GICS Sub-Industry | C36: Railroads
G37: Energy Consumption | I37: According to the Investor Pitchbook in May 2024, increase low-carbon fuel share (goal: 20% low-carbon fuels by 2030); reduce absolute Scope 1/2 as above. Conserving energy and investing in developing energy alternatives. Achieve full implementation of EMS (Energy Management System) by 2026 on locomotive fleet. | J37: Fuel-efficiency programs (Energy Management System on locomotives) reduced fuel intensity; biofuel % climbed to >6% (progress toward 20% goal).
B38: Headquarters | C38: Union Pacific Center, Omaha, Nebraska, United States
B39: Numer of Employees | C39: 32439 | G39: Waste Management | I39: N/A | J39: Year-on-year volumes fluctuate; sustainability metrics now disclose disposal tonnages and some diversion measures. However, in average, there was a decrease in waste generated in 2024 from to 2023
B41: Annual Report | C41: 45695 | G41: Other
B42: Sustainability Report | C42: 45411
B44: Recent Headlines | G44: Social
H46: Overview | I46: Targets | J46: Improvements | K46: Comments
B47: https://www.businesswire.com/news/home/20250922776661/en/SMART-TD-and-Union-Pacific-Announce-Landmark-Agreement-Securing-Jobs-and-the-Future-of-Railroading | G47: Employee Turnover % | I47: N/A | J47: There was a decline of ~ 1.62% from 2023 to 2024. (-534 employees)
B49: https://investor.unionpacific.com/news-releases/news-release-details/union-pacific-railroad-announces-pay-raises-and-labor-agreements | G49: Salaries & Compensation | I49: Continue competitive compensation/pay equity | J49: Railroad craft workers got a 24% raise, boosting their average salary to $110,000 in 2024. Overall, the median annual compensation reported in sustainability metrics shows increases over time; althought there was a slight decrease of 4.67% from 2023 to 2024
B51: Largest US rail union endorses Union Pacific, Norfolk Southern merger | Reuters | G51: Reputation | I51: The target revolves in improving safety culture and mantain inclusion scores. | J51: Ranked 4th of 940 companies included in the JUST 100 Index in 2025; 2025 Industry Leader in JUST; Inclusion metrics strong (HRC score 100%) in 2022; Honored by the Women’s Choice Awards as a top workplace for women, diversity, and millennials in 2022; safety/regulatory attention is a material reputational risk and UP is responding with safety initiatives.
B53: https://www.wsj.com/articles/union-pacific-ordered-to-pay-damages-for-retaliating-against-worker-264ee9f0? | G53: Discrimination Events | I53: The company demonstrate its will to minimize incidents | J53: Company documents policies, pay-equity audits, and DEI programs; still some litigation and EEOC/ADA cases reported in past years. | K53: Some litigations are reported such as U.S. Equal Employment Opportunity Commission v. Union Pacific Railroad Company;
B55: https://www.theguardian.com/us-news/2025/aug/25/union-pacific-norfolk-southern-railroad-merger? | G55: Work Safety | I55: The company strives for continuos reduction and making safety a core pillar. | J55: Based on its the most recent sustainability report - Building America Report - released in april 2024 for the year of 2023, the railroad reduced year-over-year serious injuries by 15% from 2022. The reportable derailment rate declined 6% compared with 2022, and over the past 10 years, track-related derailments declined 28%. Also there was 23% reduction in personal injury rates and a 20% decrease in derailment incidents compared to 2023. | K55: FRA review / audit concerns surfaced (safety culture issues flagged) when in July 2024 U.S. railroad Union Pacific interfered in a federal safety audit after employees were coached to provide specific response to FRA questions if they were approached for a safety cullture interview, prompting the federal rail agency to end the review. Cantwell, the Senator, said she was "deeply concerned about these FRA findings and the chilling effect the Union Pacific actions have on employee reporting of safety issues." She added she is concerned this indicates a weak safety culture and cited Union Pacific’s derailment rate that is 30% higher than the next-highest major railroad.
G57: Damage to consumer health | I57: N/A | J57: N/A | K57: Taking in account some comments from the "work safety" , the freight incidents that may affect communities (derailments) still is something that the company needs to work more deligent on it to improve with better system and technology, despite small improvements the company presents on its recent sustainability report.
G59: Pension Plan | I59: N/A | J59: N/A | K59: The Company provides retirement benefits through a tax-qualified defined benefit Pension Plan for eligible employees and a non-qualified Supplemental Pension Plan for executives (including the NEOs). The Pension Plan offers competitive retirement benefits to employees based on years of service, salary, bonus, and age. The Supplemental Pension Plan enhances retirement benefits for executives by covering compensation and deferred pay that exceed government limits.
G61: Supply chain | I61: N/A | J61: N/A | K61: Union Pacific Corporation conducts supplier category risk assessments, which include human rights and safety topics, and in-person supplier audits on topics such as safety. We also ask our critical and strategic Tier 1 suppliers to complete a self-assessment annually on various sustainability topics.
G63: Community involvement | I63: The 2024 Sustainability metrics reports that Union Pacific Corp aims to provide care for the community they served in many aspects. | J63: Regular community grant programs and volunteer hours reported in sustainability docs. | K63: The company disclosed on the report the amount spent on the Community Ties Giving Program registering 19.9 Millions of US Dollars in 2024
G65: Public Sector | I65: Maintain regulatory compliance; improve safety culture & transparency. | J65: Regulatory scrutiny increased after safety audit issues; UP publicly responded to inquiries and is providing documentation per requests.
G67: Litigation | I67: Reduce litigation through improved compliance & remediation | J67: To address these challenges, Union Pacific is streamlining management, enhancing safety at crossings, strengthening maintenance protocols, and working closely with regulators to ensure compliance with labor, safety, and environmental standards. | K67: Union Pacific currently faces active litigation involving employment discrimination, privacy violations, and environmental liability. Key cases include the James Hess employment suit, the Clay privacy case, and the Rowena Fire lawsuit, all of which remain in progress.
B70: Board of Directors | G70: Governance
B72: Name | C72: Position | E72: M/F – Age | H72: Overview | I72: Targets | J72: Improvements | K72: Comments
B73: Michael R. McCarthy | C73: Chair of the Board Member of Corporate Governance, Nominating and Sustainability Committee. Member of Finance Committee | E73: M - 73 | G73: Diversity (Gender, Age, Industry, Region) | I73: N/A | J73: N/A | K73: The board is composed of approximately 36 % women (4 women) and 64% man (7 man), which is quite acceptable althought it could be better, with an average age of the member is 66~67% and from multiple range of professional backgrounds, including finance, transportation, energy, and technology.
B74: Jim Vena | C74: Director/Board Member | E74: M - 66
B75: Deborah Hopkins | C75: Director/Board Member - Member of Compensation and Talent Committee. Chair of Finance Committee | E75: F - 70 | G75: % Independence | I75: Maintain independent governance; committee oversight. | J75: 10 out of 11 Directors are independent which makes approximately 91%. | K75: This composition underscores the company's commitment to strong corporate governance and shareholder interests.
B76: David B. Dillon | C76: Director/Board Member - Chair of Audit Committee. Member of Corporate Governance, Nominating and Sustainability Committee. | E76: M - 74
B77: Sheri H. Edison | C77: Director/Board Member - Member of Compensation and Talent Committee. Chair of Corporate Governance, Nominating and Sustainability Committee | E77: F - 68 | G77: Average time as independent directors | I77: N/A | J77: N/A | K77: The average tenure of these independent directors is approximately 5.4 years. Union Pacific's board emphasizes a balance between experienced leadership and fresh perspectives, as reflected in its average board tenure.
B78: Christopher Williams | C78: Director/Board Member - Member of Audit Committee. Member of Finance Committee | E78: M - 67
B79: John Tien | C79: Director/Board Member Member of Audit Committee. Member of Finance Committee | E79: M - 61 | G79: Departures of C-level executives | I79: N/A | J79: N/A | K79: Beth Whited announced her decision to step down from her role, effective July 1, 2025, after a distinguished 37-year career with the company and will shift to a strategic adviser role through early 2026.
B80: Jane Lute | C80: Director/Board Member Member of Corporate Governance, Nominating and Sustainability Committee. Chair of Safety and Service Quality Committee | E80: F - 68
B81: Teresa M. Finley | C81: Director/Board Member Member of Audit Committee. Member of Finance Committee | E81: F - 63 | G81: CEO/Chairman duality | I81: Governance best practice: separate roles maintained. | J81: The split was explicitly implemented in Aug 2023 (new CEO + separate chairman). | K81: CEO (Jim Vena) is separate from Chairman (Mike McCarthy) — roles split in 2023; no CEO/Chairman duality currently.
B82: Doyle R. Simons | C82: Director/Board Member Chair of Compensation and Talent Committee. Member of Safety and Service Quality Committee | E82: M - 61
B83: John P. Wiehoff | C83: Director/Board Member Member of Audit Committee. Member of Finance Committee | E83: M - 63 | G83: Transparency when reporting | I83: Keep demonstrating a robust commitment to transparency in its financial, sustainability, and governance reporting. | J83: N/A | K83: Overall, Union Pacific in 2025 has strong transparency practices — it publishes detailed financial reports, proxy statements, and sustainability reports, and maintains open communication with shareholders. Its sustainability reporting includes environmental initiatives and community engagement, overseen by its governance committees.
G85: Time taken to report | I85: N/A | J85: N/A | K85: Union Pacific follows a consistent reporting schedule: quarterly financial results are released soon after each quarter ends, sustainability reports are issued biennially with annual updates, and annual 10‑K filings occur each February, ensuring regular transparency for stakeholders.
G87: CEO or Chairman in other boards? | I87: Maintain a policy that requires its CEO and senior officers to seek approval from the Corporate Governance and Nominating Committee before accepting positions on outside boards of directors. This policy ensures that such commitments do not conflict with their responsibilities at Union Pacific. | J87: N/A | K87: Regarding Union Pacific's leadership, CEO Jim Vena does not currently serve on any external boards. The company's governance guidelines stipulate that any invitation for the CEO to serve on an outside board must be presented to the Corporate Governance and Nominating Committee for consideration.
G89: Audit / Consulting | I89: Union Pacific Corp strives to maintan a policy requiring the Audit Committee to pre-approve all audit and non-audit services to ensure compliance with auditor independence standards. This policy includes reviewing and approving budgets for audit-related, tax, and other services, with no further approval needed for specific projects within these categories. | J89: N/A | K89: Regarding non-audit services, Union Pacific reported no fees for tax services or other non-audit services in 2024, aligning with the SEC's regulations that limit the provision of such services by auditors to maintain independence.
G91: ESG-compensation related | I91: Evolve and expand ESG KPIs in scorecards; tie operational sustainability KPIs to incentives. | J91: Company explicitly states that trip plan compliance and biofuel goals (which affect emissions) are tied to executive compensation; UP is gradually integrating ESG KPIs into incentive plans.
G93: Management compensation schemes | I93: N/A | J93: N/A | K93: As of 2025, Union Pacific’s executive compensation heavily ties to performance, with about 91% of the CEO’s pay and 84% of other executives’ pay based on financial results and stock performance. Most long-term incentives come from performance stock units and stock options.

Sheet Industry
D6: 584.17 | E6: 627.76 | F6: 676.06 | G6: 729.63 | H6: 789.13 | I6: 855.3 | J6: 929 | K6: 997.69 | L6: 1067.63 | M6: 1137.57
A7: x | B7: Industry Growth Forecast | O7: Industry Index
D9: 2022 | E9: =+D9+1 -> 2023 | F9: =+E9+1 -> 2024 | G9: =+F9+1 -> 2025 | H9: =+G9+1 -> 2026 | I9: =+H9+1 -> 2027 | J9: =+I9+1 -> 2028 | K9: =+J9+1 -> 2029 | M9: ="CAGR "&$G$9&" - "&$K$9 -> CAGR 2025 - 2029
B12: Market Size (Railroad) - www.futuremarketinsights.com/reports/railroad-market? ; www.thebusinessresearchcompany.com/market-insights/rail-freight-market-insights-2025? ; www.prnewswire.com/news-releases/rail-freight-industry-overview-2023-2027-estimated-market-size-competitive-landscape-and-major-trend--by-the-business-research-company-301944301.html? | D12: 258.77 | E12: 273.23 | F12: 296.8 | G12: 330.2 | H12: 348.68 | I12: 367.99 | J12: 388.5 | K12: 410.23 | M12: =(K12/G12)^(1/5)-1 -> 0.044359615
B13: Market Share | D13: 0.233 | E13: 0.245 | F13: 0.244 | M13: =((K13*K12)/(G13*G12))^(1/5)-1 -> #DIV/0!
B14: Market Size | M14: =(K14/G14)^(1/5)-1 -> #DIV/0!
B15: Market Share | M15: =((K15*K14)/(G15*G14))^(1/5)-1 -> #DIV/0!
B16: Market Size | M16: =(K16/G16)^(1/5)-1 -> #DIV/0!
B17: Market Share | M17: =((K17*K16)/(G17*G16))^(1/5)-1 -> #DIV/0!
B18: Market Size | M18: =(K18/G18)^(1/5)-1 -> #DIV/0!
B19: Market Share | M19: =((K19*K18)/(G19*G18))^(1/5)-1 -> #DIV/0!
B20: Market Size | M20: =(K20/G20)^(1/5)-1 -> #DIV/0!
B21: Market Share | M21: =((K21*K20)/(G21*G20))^(1/5)-1 -> #DIV/0!
A23: x
B25: Industry Driver | D25: Description | O25: Porter's Five Forces
B27: Industrial Production and Economic Growth | D27: Demand for freight rail services is closely tied to industrial output, construction, agriculture, and overall economic health. Higher production volumes result in increased shipments of commodities like coal, grain, metals, and chemicals—key freight categories for Union Pacific.
B28: Environmental and Sustainability Regulations | D28: Rising demand for lower-emission transport and regulatory pressure are encouraging shifts from trucking to rail, which is more fuel-efficient per ton-mile. Union Pacific is targeting emissions reduction and investing in cleaner technologies to align with ESG goals.
B29: Urbanization and Infrastructure Development | D29: Urban expansion increases demand for construction materials, energy, and consumer goods—all of which rely on freight transport. Union Pacific benefits from hauling such freight into rapidly growing metro areas, supported by federal infrastructure investment.
B30: Shift in Modal Preferences (Rail vs. Trucking) | D30: Trucking faces headwinds like driver shortages, fuel volatility, and stricter regulations. These challenges make rail a more appealing option for shippers—especially for long-haul and bulk cargo. Union Pacific’s efficiency gives it a competitive edge.
O32: Rivalry Among Existing Competitors | R32: 3
O33: Threat of New Entrants | R33: 1
O34: Threat of Substitutes | R34: 3
O35: Bargaining Power of Customers | R35: 4
O36: Bargaining Power of Suppliers | R36: 5

Sheet Segments
A7: x | B7: Segments | D7: =F7 -> 2020 | E7: =F7 -> 2020 | F7: 2020 | G7: =F7 -> 2020 | H7: =F7 -> 2020 | J7: =L7 -> 2021 | K7: =L7 -> 2021 | L7: 2021 | M7: =L7 -> 2021 | N7: =L7 -> 2021 | P7: =R7 -> 2022 | Q7: =R7 -> 2022 | R7: 2022 | S7: =R7 -> 2022 | T7: =R7 -> 2022 | V7: =X7 -> 2023 | W7: =X7 -> 2023 | X7: 2023 | Y7: =X7 -> 2023 | Z7: =X7 -> 2023 | AB7: =AD7 -> 2024 | AC7: =AD7 -> 2024 | AD7: 2024 | AE7: =AD7 -> 2024 | AF7: =AD7 -> 2024 | AH7: =AJ7 -> 2025 | AI7: =AJ7 -> 2025 | AJ7: 2025 | AK7: =AJ7 -> 2025 | AL7: =AJ7 -> 2025 | AN7: =AP7 -> 2025 | AO7: =AP7 -> 2025 | AP7: 2025 | AQ7: =AP7 -> 2025 | AR7: =AP7 -> 2025 | AZ7: Products
D8: 2020 | J8: =D8+1 -> 2021 | P8: =J8+1 -> 2022 | V8: =P8+1 -> 2023 | AB8: =V8+1 -> 2024 | AH8: =AB8+1 -> 2025 | AN8: =AH8+1 -> 2026 | AT8: =AN8+1 -> 2027 | AV8: =+AT8+1 -> 2028 | AX8: =+AV8+1 -> 2029
D9: Q1 | E9: Q2 | F9: Q3 | G9: Q4 | H9: FY | J9: Q1 | K9: Q2 | L9: Q3 | M9: Q4 | N9: FY | P9: Q1 | Q9: Q2 | R9: Q3 | S9: Q4 | T9: FY | V9: Q1 | W9: Q2 | X9: Q3 | Y9: Q4 | Z9: FY | AB9: Q1 | AC9: Q2 | AD9: Q3 | AE9: Q4 | AF9: FY | AH9: Q1 | AI9: Q2 | AJ9: Q3 | AK9: Q4 | AL9: FY | AN9: Q1 | AO9: Q2 | AP9: Q3 | AQ9: Q4 | AR9: FY | AT9: FY | AV9: FY | AX9: FY
B12: Revenue by segment:
B18: Total revenue | D18: =IS!D18 -> 5229 | E18: =IS!E18 -> 4244 | F18: =IS!F18 -> 4919 | G18: =IS!G18 -> 5141 | H18: =IS!H18 -> 19533 | J18: =IS!J18 -> 5001 | K18: =IS!K18 -> 5504 | L18: =IS!L18 -> 5566 | M18: =IS!M18 -> 5733 | N18: =IS!N18 -> 21804 | P18: =IS!P18 -> 5860 | Q18: =IS!Q18 -> 6269 | R18: =IS!R18 -> 6566 | S18: =IS!S18 -> 6180 | T18: =IS!T18 -> 24875 | V18: =IS!V18 -> 6056 | W18: =IS!W18 -> 5963 | X18: =IS!X18 -> 5941 | Y18: =IS!Y18 -> 6159 | Z18: =IS!Z18 -> 24119 | AB18: =IS!AB18 -> 6031 | AC18: =IS!AC18 -> 6007 | AD18: =IS!AD18 -> 6091 | AE18: =IS!AE18 -> 6121 | AF18: =IS!AF18 -> 24250 | AH18: =IS!AH18 -> 6027 | AI18: =IS!AI18 -> 6154 | AJ18: =IS!AJ18 -> 0 | AK18: =IS!AK18 -> 0 | AL18: =IS!AL18 -> 0 | AN18: =IS!AN18 -> 0 | AO18: =IS!AO18 -> 0 | AP18: =IS!AP18 -> 0 | AQ18: =IS!AQ18 -> 0 | AR18: =IS!AR18 -> 0 | AT18: =IS!AT18 -> 0 | AV18: =IS!AV18 -> 0 | AX18: =IS!AX18 -> 0
B20: Operations
B21: Bulk | D21: 1534 | E21: 1386 | F21: 1478 | G21: =H21-F21-E21-D21 -> 1562 | H21: 5960 | J21: 1512 | K21: 1648 | L21: 1687 | M21: =N21-L21-K21-J21 -> 1809 | N21: 6656 | P21: 1832 | Q21: 1813 | R21: 1959 | S21: =T21-R21-Q21-P21 -> 1933 | T21: 7537 | V21: 1897 | W21: 1757 | X21: 1766 | Y21: =Z21-X21-W21-V21 -> 1938 | Z21: 7358 | AB21: 1817 | AC21: 1721 | AD21: 1805 | AE21: =AF21-AD21-AC21-AB21 -> 1864 | AF21: 7207 | AH21: 1836 | AI21: 1901 | AL21: =Anexo_projections!AA60 -> 7502.4757 | AR21: =Anexo_projections!AG60 -> 7727.1069 | AT21: =Anexo_projections!AI60 -> 7927.8107 | AV21: =Anexo_projections!AK60 -> 8179.4589 | AX21: =Anexo_projections!AM60 -> 8453.6025
B22: Industrial | D22: 1894 | E22: 1500 | F22: 1567 | G22: =H22-F22-E22-D22 -> 1661 | H22: 6622 | J22: 1656 | K22: 1859 | L22: 1911 | M22: =N22-L22-K22-J22 -> 1897 | N22: 7323 | P22: 1921 | Q22: 2091 | R22: 2194 | S22: =T22-R22-Q22-P22 -> 1999 | T22: 8205 | V22: 2017 | W22: 2086 | X22: 2057 | Y22: =Z22-X22-W22-V22 -> 2078 | Z22: 8238 | AB22: 2104 | AC22: 2123 | AD22: 2121 | AE22: =AF22-AD22-AC22-AB22 -> 2092 | AF22: 8440 | AH22: 2082 | AI22: 2212 | AL22: =Anexo_projections!AA69 -> 8434.437 | AR22: =Anexo_projections!AG69 -> 8683.6106 | AT22: =Anexo_projections!AI69 -> 8963.96 | AV22: =Anexo_projections!AK69 -> 9222.7948 | AX22: =Anexo_projections!AM69 -> 9476.3775
B23: Premium | D23: 1452 | E23: 1086 | F23: 1551 | G23: =H23-F23-E23-D23 -> 1580 | H23: 5669 | J23: 1481 | K23: 1625 | L23: 1568 | M23: =N23-L23-K23-J23 -> 1591 | N23: 6265 | P23: 1687 | Q23: 1938 | R23: 1956 | S23: =T23-R23-Q23-P23 -> 1836 | T23: 7417 | V23: 1742 | W23: 1726 | X23: 1722 | Y23: =Z23-X23-W23-V23 -> 1785 | Z23: 6975 | AB23: 1695 | AC23: 1794 | AD23: 1842 | AE23: =AF23-AD23-AC23-AB23 -> 1833 | AF23: 7164 | AH23: 1773 | AI23: 1730 | AL23: =Anexo_projections!AA74 -> 8043.9583 | AR23: =Anexo_projections!AG74 -> 8278.1383 | AT23: =Anexo_projections!AI74 -> 8436.0022 | AV23: =Anexo_projections!AK74 -> 8757.9669 | AX23: =Anexo_projections!AM74 -> 8904.1805
B24: Other revenues | D24: =214+11+18 -> 243 | E24: =150+103+19 -> 272 | F24: =193+114+16 -> 323 | G24: =H24-F24-E24-D24 -> 444 | H24: =743+473+66 -> 1282 | J24: =177+161+14 -> 352 | K24: =180+176+16 -> 372 | L24: =182+198+20 -> 400 | M24: =N24-L24-K24-J24 -> 436 | N24: =741+752+67 -> 1560 | P24: =205+151+14 -> 370 | Q24: =233+183+11 -> 427 | R24: =231+212+14 -> 457 | S24: =T24-R24-Q24-P24 -> 462 | T24: =884+779+53 -> 1716 | V24: =235+151+14 -> 400 | W24: =220+149+25 -> 394 | X24: =226+142+28 -> 396 | Y24: =Z24-X24-W24-V24 -> 358 | Z24: =872+584+92 -> 1548 | AB24: =217+174+24 -> 415 | AC24: =212+131+26 -> 369 | AD24: =179+122+22 -> 323 | AE24: =AF24-AD24-AC24-AB24 -> 332 | AF24: =788+554+97 -> 1439 | AH24: =194+118+24 -> 336 | AI24: =181+107+23 -> 311 | AL24: =Anexo_projections!AA77 -> 1500 | AR24: =Anexo_projections!AG77 -> 1500 | AT24: =Anexo_projections!AI77 -> 1500 | AV24: =Anexo_projections!AK77 -> 1500 | AX24: =Anexo_projections!AM77 -> 1500
B26: Total revenue | D26: =IS!D18 -> 5229 | E26: =IS!E18 -> 4244 | F26: =IS!F18 -> 4919 | G26: =IS!G18 -> 5141 | H26: =IS!H18 -> 19533 | J26: =IS!J18 -> 5001 | K26: =IS!K18 -> 5504 | L26: =IS!L18 -> 5566 | M26: =IS!M18 -> 5733 | N26: =IS!N18 -> 21804 | P26: =IS!P18 -> 5860 | Q26: =IS!Q18 -> 6269 | R26: =IS!R18 -> 6566 | S26: =IS!S18 -> 6180 | T26: =IS!T18 -> 24875 | V26: =IS!V18 -> 6056 | W26: =IS!W18 -> 5963 | X26: =IS!X18 -> 5941 | Y26: =IS!Y18 -> 6159 | Z26: =IS!Z18 -> 24119 | AB26: =IS!AB18 -> 6031 | AC26: =IS!AC18 -> 6007 | AD26: =IS!AD18 -> 6091 | AE26: =IS!AE18 -> 6121 | AF26: =IS!AF18 -> 24250 | AH26: =IS!AH18 -> 6027 | AI26: =IS!AI18 -> 6154 | AJ26: =IS!AJ18 -> 0 | AK26: =IS!AK18 -> 0 | AL26: =SUM(AL21:AL24) -> 25480.871 | AN26: =IS!AN18 -> 0 | AO26: =IS!AO18 -> 0 | AP26: =IS!AP18 -> 0 | AQ26: =IS!AQ18 -> 0 | AR26: =IS!AR18 -> 0 | AT26: =IS!AT18 -> 0 | AV26: =IS!AV18 -> 0 | AX26: =IS!AX18 -> 0
B28: Operations:
B29: Bulk
B30: Industrial
B31: Premium
A35: x | B35: Notes & Forecasts
B40: Operations | D40: Company only has one segment, railroad, but discloses data in terms of operations and other revenues. Although, they disclose data in their railroad network, by commodity group, Bulk, Industrial and Premium.
B41: Freight revenues | D41: Bulk: This shipments consist of grain products, fertilizer, food and refrigerated, and coal and renewables. The company connects the large grain markets, from the Midwest and Western US, producing areas to export terminals in the Pacififc Northwest and Gulf Coast port as well as Mexico. Industrial: network facilitates movement of different commodities throughout North America. This group includes several categories, including construction, industrial chemicals, plastics, forest products, specialized products, metals and ores, petroleum, liquide petroleum gases, soda ash, and sand. Premium:This group includes finished automobiles, automotive parts, and merchandise in intermodal containers, both domestic and international. International business consists of import and export traffic moving in 20 or 40-foot shipping containers, that mainly pass through West Coast ports, destined for one of the Company's many inland intermodal terminals. Domestic business includes container and trailer traffic picked up and delivered within North America for intermodal marketing companies as well as truckload carriers.

Sheet Peers
B7: Peers
A12: x | B12: Growth | C12: Union Pacific Corp | D12: CAN NATL RAILWAY | E12: CSX CORP | F12: CANADIAN PACIFIC | G12: NORFOLK SOUTHERN | H12: BNSF RAILWAY CO | I12: {=TRANSPOSE(Inputs!H21:H25)} -> BOEING CO/THE | J12: LOCKHEED MARTIN | K12: NORTHROP GRUMMAN | L12: GENERAL DYNAMICS | M12: 3M CO | N12: {=TRANSPOSE(Inputs!N21:N25)} -> DEERE & CO | O12: ILLINOIS TOOL WO | P12: HONEYWELL INTL | Q12: AUTOMATIC DATA | R12: WASTE MANAGEMENT
B14: Revenue (LTM) | C14: 0.01 | D14: 0.01 | E14: -0.03 | F14: 0.05 | G14: 0.01 | H14: 0.01 | I14: 0.02 | J14: 0.01 | K14: -0.01 | L14: -0.01 | M14: 0.12 | N14: 0.12 | O14: 0.12 | P14: 0.12 | Q14: 0.12 | R14: 0.12
B15: Revenue (3-yr CAGR) | C15: 0.01 | D15: 0.04 | E15: 0 | F15: 0.14 | G15: 0.01 | H15: -0.01 | I15: 0.07 | J15: 0.04 | K15: 0.05 | L15: 0.09 | M15: -0.11 | N15: -0.03 | O15: 0.01 | P15: 0.05 | Q15: 0.08 | R15: 0.08
B16: Gross profit (LTM) | C16: - | D16: - | E16: - | F16: - | G16: - | H16: - | I16: -1.04 | J16: -0.31 | K16: 0.14 | L16: 0.14 | M16: 0.1 | N16: 0.1 | O16: 0.1 | P16: 0.1 | Q16: 0.1 | R16: 0.1
B17: EBIT (LTM) | C17: 0.05 | D17: -0.02 | E17: -0.09 | F17: 0.1 | G17: 0.55 | H17: 0.07 | I17: 2.76 | J17: -0.16 | K17: 0.43 | L17: 0.43 | M17: 0.14 | N17: 0.14 | O17: 0.14 | P17: 0.14 | Q17: 0.14 | R17: 0.14
B18: EBITDA (LTM) | C18: 0.05 | D18: 0 | E18: -0.06 | F18: 0.09 | G18: 0.39 | H18: 0.05 | I18: 8.41 | J18: -0.12 | K18: 0.31 | L18: 0.31 | M18: 0.13 | N18: 0.13 | O18: 0.13 | P18: 0.13 | Q18: 0.13 | R18: 0.13
B19: FCF (LTM) | C19: 0.23 | D19: -0.17 | E19: -0.17 | F19: 0.49 | G19: 1.01 | H19: 0.12 | I19: - | J19: -0.15 | K19: 0.25 | L19: -0.16 | M19: -0.87 | N19: 0.07 | O19: -0.08 | P19: 0.15 | Q19: 0.21 | R19: 0.18
A21: x | B21: Margins | C21: =C12 -> Union Pacific Corp | D21: =D12 -> CAN NATL RAILWAY | E21: =E12 -> CSX CORP | F21: =F12 -> CANADIAN PACIFIC | G21: =G12 -> NORFOLK SOUTHERN | H21: =H12 -> BNSF RAILWAY CO | I21: =I12 -> BOEING CO/THE | J21: =J12 -> LOCKHEED MARTIN | ... R21: =R12 -> WASTE MANAGEMENT
G22: -
B23: Gross margin | C23: - | D23: - | E23: - | F23: - | G23: - | H23: 0.66 | I23: -0.03 | J23: 0.1 | K23: 0.2 | L23: 0.15 | M23: 0.41 | N23: 0.4 | O23: 0.44 | P23: 0.38 | Q23: 0.46 | R23: 0.39
B24: EBIT margin | C24: 0.4 | D24: 0.37 | E24: 0.36 | F24: 0.36 | G24: 0.34 | H24: 0.32 | I24: -0.16 | J24: 0.1 | K24: 0.11 | L24: 0.1 | M24: 0.2 | N24: 0.24 | O24: 0.27 | P24: 0.19 | Q24: 0.26 | R24: 0.18
B25: EBITDA margin | C25: 0.5 | D25: 0.49 | E25: 0.46 | F25: 0.49 | G25: 0.53 | H25: 0.45 | I25: -0.1 | J25: 0.11 | K25: 0.14 | L25: 0.12 | M25: 0.24 | N25: 0.27 | O25: 0.29 | P25: 0.23 | Q25: 0.3 | R25: 0.28
B26: Net margin | C26: 0.28 | D26: 0.26 | E26: 0.24 | F26: 0.26 | G26: 0.22 | H26: 0.31 | I26: -0.18 | J26: 0.08 | K26: 0.1 | L26: 0.08 | M26: 0.17 | N26: 0.14 | O26: 0.22 | P26: 0.15 | Q26: 0.2 | R26: 0.12
B27: SG&A margin | C27: - | D27: - | E27: - | F27: - | G27: - | H27: - | I27: 0.07 | J27: - | K27: 0.1 | L27: 0.04 | M27: 0.17 | N27: 0.1 | O27: 0.17 | P27: 0.14 | Q27: 0.2 | R27: 0.11
B28: R&D margin | C28: 0 | D28: - | E28: - | F28: - | G28: - | H28: - | I28: 0.05 | J28: - | K28: - | L28: 0.01 | M28: 0.05 | N28: 0.05 | O28: - | P28: 0.05 | Q28: 0 | R28: -
A30: x | B30: Returns | C30: =C21 -> Union Pacific Corp | D30: =D21 -> CAN NATL RAILWAY | E30: =E21 -> CSX CORP | F30: =F21 -> CANADIAN PACIFIC | G30: =G21 -> NORFOLK SOUTHERN | H30: =H21 -> BNSF RAILWAY CO | I30: =I21 -> BOEING CO/THE | J30: =J21 -> LOCKHEED MARTIN | ... R30: =R21 -> WASTE MANAGEMENT
B32: ROIC | C32: 0.12 | D32: 0.08 | E32: 0.11 | F32: 0.05 | G32: 0.12 | H32: 0.08 | I32: -0.23 | J32: 0.19 | K32: 0.08 | L32: 0.13 | M32: 0.22 | N32: 0.08 | O32: 0.27 | P32: 0.11 | Q32: 0.43 | R32: 0.12
B33: CROIC | C33: 0.09 | D33: 0.06 | E33: 0.07 | F33: 0.03 | G33: 0.04 | H33: 0.07 | I33: -0.28 | J33: 0.17 | K33: 0.07 | L33: 0.1 | M33: 0.05 | N33: 0.05 | O33: 0.25 | P33: 0.09 | Q33: 0.44 | R33: 0.06
B34: ROCE | C34: 0.17 | D34: 0.13 | E34: 0.15 | F34: 0.1 | G34: 0.12 | H34: 0.11 | I34: -0.3 | J34: 0.84 | K34: 0.34 | L34: 0.36 | M34: 0.35 | N34: 2.07 | O34: 0.95 | P34: 0.54 | Q34: 1.8 | R34: 0.21
B35: RONA | C35: 0.58 | D35: 0.3 | E35: 0.42 | F35: 0.11 | G35: 0.28 | H35: 0.1 | I35: 2.74 | J35: 1.11 | K35: 0.29 | L35: 0.22 | M35: 1.24 | N35: 0.55 | O35: 1.29 | P35: 0.39 | Q35: 0.87 | R35: 0.49
B36: ROE | C36: 0.42 | D36: 0.22 | E36: 0.25 | F36: 0.09 | G36: 0.24 | H36: 0.1 | I36: - | J36: 0.73 | K36: 0.27 | L36: 0.18 | M36: 0.96 | N36: 0.22 | O36: 1.09 | P36: 0.35 | Q36: 0.76 | R36: 0.33
B37: ROA | C37: 0.1 | D37: 0.08 | E37: 0.07 | F37: 0.05 | G37: 0.08 | H37: 0.08 | I37: -0.07 | J37: 0.07 | K37: 0.08 | L37: 0.07 | M37: 0.1 | N37: 0.05 | O37: 0.21 | P37: 0.08 | Q37: 0.08 | R37: 0.07
A39: x | B39: Efficiency | C39: =C30 -> Union Pacific Corp | D39: =D30 -> CAN NATL RAILWAY | E39: =E30 -> CSX CORP | F39: =F30 -> CANADIAN PACIFIC | G39: =G30 -> NORFOLK SOUTHERN | H39: =H30 -> BNSF RAILWAY CO | I39: =I30 -> BOEING CO/THE | J39: =J30 -> LOCKHEED MARTIN | ... R39: =R30 -> WASTE MANAGEMENT
B41: Asset turnover | C41: 0,4x | D41: 0,3x | E41: 0,3x | F41: 0,2x | G41: 0,3x | H41: 0,2x | I41: 0,5x | J41: 1,3x | K41: 0,8x | L41: 0,9x | M41: 0,6x | N41: 0,4x | O41: 1,0x | P41: 0,5x | Q41: 0,4x | R41: 0,6x
B42: Net operating asset turnover | C42: 0,7x | D42: 0,5x | E42: 0,6x | F42: 0,2x | G42: 0,5x | H42: 0,3x | I42: 0,9x | J42: 2,2x | K42: 1,5x | L42: 1,1x | M42: 1,3x | N42: 1,5x | O42: 2,6x | P42: 1,2x | Q42: 0,5x | R42: 1,2x
B43: Fixed asset turnover | C43: 0,4x | D43: 0,4x | E43: 0,4x | F43: 0,3x | G43: 0,3x | H43: 0,3x | I43: 6,7x | J43: 8,4x | K43: 3,4x | L43: 7,8x | M43: 3,1x | N43: 3,0x | O43: 7,5x | P43: 5,6x | Q43: 19,7x | R43: 1,3x
B44: Revenue per employee thsnd of USD | C44: 804 | D44: 498 | E44: 601 | F44: 540 | G44: 621 | H44: - | I44: 438 | J44: 594 | K44: 418 | L44: 430 | M44: 400 | N44: 1 262 | O44: 359 | P44: 392 | Q44: 307 | R44: 388
B45: EBIT per employee thsnd of USD | C45: 324 | D45: 186 | E45: 208 | F45: 213 | G45: 234 | H45: - | I45: -59 | J45: 62 | K45: 41 | L45: 44 | M45: 97 | N45: 276 | O45: 93 | P45: 80 | Q45: 81 | R45: 71
A47: x | B47: Working Capital | C47: =C39 -> Union Pacific Corp | D47: =D39 -> CAN NATL RAILWAY | E47: =E39 -> CSX CORP | F47: =F39 -> CANADIAN PACIFIC | G47: =G39 -> NORFOLK SOUTHERN | H47: =H39 -> BNSF RAILWAY CO | I47: =I39 -> BOEING CO/THE | J47: =J39 -> LOCKHEED MARTIN | ... R47: =R39 -> WASTE MANAGEMENT
B49: DSO | C49: 30 | D49: 25 | E49: 37 | F49: 48 | G49: 73 | H49: 32 | I49: 16 | J49: 16 | K49: 18 | L49: 24 | M49: 54 | N49: 56 | O49: 76 | P49: 76 | Q49: 62 | R49: 47
B50: DIO | C50: - | D50: - | E50: - | F50: - | G50: - | H50: - | I50: 414 | J50: 19 | K50: 17 | L50: 84 | M50: 102 | N50: 105 | O50: 73 | P50: 98 | Q50: - | R50: 5
B51: DPO | C51: - | D51: - | E51: - | F51: - | G51: - | H51: - | I51: 54 | J51: 19 | K51: 28 | L51: 26 | M51: 71 | N51: 39 | O51: 25 | P51: 97 | Q51: 4 | R51: 48
B52: CCC | C52: - | D52: - | E52: - | F52: - | G52: - | H52: 53 | I52: 400 | J52: 18 | K52: 0 | L52: 78 | M52: 86 | N52: 96 | O52: 116 | P52: 66 | Q52: - | R52: 3
B53: Working capital intensity | C53: -0.04 | D53: -0.07 | E53: -0.01 | F53: -0.11 | G53: -0.09 | H53: -0.03 | I53: 0.28 | J53: 0.03 | K53: 0.02 | L53: 0.13 | M53: 0.22 | N53: -0.22 | O53: 0.12 | P53: 0.13 | Q53: 0.06 | R53: -0.01
B54: Cash conversion ratio | C54: 1,0x | D54: 1,1x | E54: 1,0x | F54: 1,0x | G54: 1,0x | H54: 1,3x | I54: 1,1x | J54: 1,0x | K54: 1,0x | L54: 0,9x | M54: 0,4x | N54: 0,7x | O54: 0,8x | P54: 0,8x | Q54: 0,9x | R54: 1,3x
B55: CFO margin | C55: 0.39 | D55: 0.39 | E55: 0.36 | F55: 0.36 | G55: 0.33 | H55: 0.41 | I55: -0.18 | J55: 0.1 | K55: 0.11 | L55: 0.09 | M55: 0.07 | N55: 0.18 | O55: 0.21 | P55: 0.16 | Q55: 0.24 | R55: 0.24
A57: x | B57: Leverage & Coverage | C57: =C47 -> Union Pacific Corp | D57: =D47 -> CAN NATL RAILWAY | E57: =E47 -> CSX CORP | F57: =F47 -> CANADIAN PACIFIC | G57: =G47 -> NORFOLK SOUTHERN | H57: =H47 -> BNSF RAILWAY CO | I57: =I47 -> BOEING CO/THE | J57: =J47 -> LOCKHEED MARTIN | ... R57: =R47 -> WASTE MANAGEMENT
B59: Net debt / EBITDA | C59: 2,7x | D59: 2,5x | E59: 3,0x | F59: 2,9x | G59: 2,5x | H59: 0,1x | I59: - | J59: 2,7x | K59: 2,8x | L59: 1,5x | M59: 1,6x | N59: 0,2x | O59: 1,8x | P59: 2,9x | Q59: -0,6x | R59: 3,5x
B60: Net debt / FCF | C60: 5,3x | D60: 6,7x | E60: 6,6x | F60: 9,1x | G60: 9,5x | H60: 0,2x | I60: -2,1x | J60: 3,6x | K60: 5,4x | L60: 2,8x | M60: 9,2x | N60: 0,4x | O60: 2,5x | P60: 4,3x | Q60: -0,7x | R60: 11,4x
B61: Interest coverage | C61: 7,7x | D61: 7,0x | E61: 6,3x | F61: - | G61: 5,0x | H61: 1071,6x | I61: -3,9x | J61: 6,8x | K61: 7,0x | L61: 12,2x | M61: 4,0x | N61: 3,7x | O61: 15,1x | P61: 7,0x | Q61: 11,9x | R61: 6,8x
B62: Debt / capital | C62: 0.66 | D62: 0.5 | E62: 0.6 | F62: 0.32 | G62: 0.55 | H62: 0.02 | I62: 1.08 | J62: 0.77 | K62: 0.55 | L62: 0.33 | M62: 0.78 | N62: 0.74 | O62: 0.71 | P62: 0.63 | Q62: 0.42 | R62: 0.75
B63: Short term debt / total debt | C63: 0.05 | D63: 0.06 | E63: 0.04 | F63: 0.13 | G63: 0.04 | H63: 0.21 | I63: 0.03 | J63: 0.04 | K63: 0.1 | L63: 0.17 | M63: 0.15 | N63: 0.34 | O63: 0.2 | P63: 0.18 | Q63: 0.03 | R63: 0.06
A65: x | B65: Liquidity | C65: =C57 -> Union Pacific Corp | D65: =D57 -> CAN NATL RAILWAY | E65: =E57 -> CSX CORP | F65: =F57 -> CANADIAN PACIFIC | G65: =G57 -> NORFOLK SOUTHERN | H65: =H57 -> BNSF RAILWAY CO | I65: =I57 -> BOEING CO/THE | J65: =J57 -> LOCKHEED MARTIN | ... R65: =R57 -> WASTE MANAGEMENT
B67: Current ratio | C67: 0,8x | D67: 0,7x | E67: 0,9x | F67: 0,6x | G67: 0,9x | H67: 0,9x | I67: 1,3x | J67: 1,1x | K67: 1,0x | L67: 1,4x | M67: 1,4x | N67: 0,7x | O67: 1,4x | P67: 1,3x | Q67: 1,0x | R67: 0,8x
B68: Quick ratio | C68: 0,6x | D68: 0,4x | E68: 0,7x | F68: 0,5x | G68: 0,8x | H68: 0,6x | I68: 0,3x | J68: 0,2x | K68: 0,4x | L68: 0,3x | M68: 1,0x | N68: 0,4x | O68: 0,9x | P68: 0,9x | Q68: 0,3x | R68: 0,6x
B69: Cash ratio | C69: 0,2x | D69: 0,1x | E69: 0,3x | F69: 0,1x | G69: 0,5x | H69: 0,1x | I69: 0,3x | J69: 0,1x | K69: 0,3x | L69: 0,1x | M69: 0,7x | N69: 0,2x | O69: 0,2x | P69: 0,5x | Q69: 0,2x | R69: 0,1x
A71: x | B71: Cash Deployment | C71: =C65 -> Union Pacific Corp | D71: =D65 -> CAN NATL RAILWAY | E71: =E65 -> CSX CORP | F71: =F65 -> CANADIAN PACIFIC | G71: =G65 -> NORFOLK SOUTHERN | H71: =H65 -> BNSF RAILWAY CO | I71: =I65 -> BOEING CO/THE | J71: =J65 -> LOCKHEED MARTIN | ... R71: =R65 -> WASTE MANAGEMENT
B73: Capex intensity | C73: 0.14 | D73: 0.21 | E73: 0.17 | F73: 0.19 | G73: 0.2 | H73: 0.16 | I73: 0.03 | J73: 0.02 | K73: 0.04 | L73: 0.02 | M73: 0.05 | N73: 0.09 | O73: 0.03 | P73: 0.03 | Q73: 0.03 | R73: 0.15
B74: Capex / depreciation | C74: 1.44 | D74: 1.88 | E74: 1.53 | F74: 1.49 | G74: 1.76 | H74: 1.4 | I74: 1.21 | J74: 1.08 | K74: 1.29 | L74: 1.03 | M74: 0.87 | N74: 2.27 | O74: 1.09 | P74: 0.87 | Q74: 0.94 | R74: 1.43
B75: R&D capitalization rate | C75: - | D75: - | E75: - | F75: - | G75: - | H75: - | I75: - | J75: - | K75: - | L75: - | M75: - | N75: - | O75: - | P75: - | Q75: - | R75: -
B76: R&D capitalization test | C76: - | D76: - | E76: - | F76: - | G76: - | H76: - | I76: - | J76: - | K76: - | L76: - | M76: - | N76: - | O76: - | P76: - | Q76: - | R76: -
B77: Dividend payout | C77: 0.48 | D77: 0.48 | E77: 0.27 | F77: 0.19 | G77: 0.47 | H77: 0 | I77: - | J77: 0.57 | K77: 0.28 | L77: 0.41 | M77: 0.5 | N77: 0.23 | O77: 0.49 | P77: 0.5 | Q77: 0.6 | R77: 0.44
B78: FCF payout | C78: 0.8 | D78: 1.51 | E78: 1.15 | F78: 0.26 | G78: 0.72 | H78: 0 | I78: 1.27 | J78: 1.3 | K78: 1.47 | L78: 0.95 | M78: 5.74 | N78: 1.28 | O78: 1.11 | P78: 0.84 | Q78: 0.78 | R78: 0.67
B79: Buybacks as % CFO | C79: 0.16 | D79: 0.4 | E79: 0.43 | F79: 0 | G79: 0 | H79: 0 | I79: -0.01 | J79: 0.53 | K79: 0.57 | L79: 0.37 | M79: 0.99 | N79: 0.43 | O79: 0.46 | P79: 0.27 | Q79: 0.26 | R79: 0.05
A81: x | B81: Earnings Quality | C81: =C71 -> Union Pacific Corp | D81: =D71 -> CAN NATL RAILWAY | E81: =E71 -> CSX CORP | F81: =F71 -> CANADIAN PACIFIC | G81: =G71 -> NORFOLK SOUTHERN | H81: =H71 -> BNSF RAILWAY CO | I81: =I71 -> BOEING CO/THE | J81: =J71 -> LOCKHEED MARTIN | ... R81: =R71 -> WASTE MANAGEMENT
B83: Cash/earnings conversion | C83: 5,2x | D83: 5,8x | E83: 6,4x | F83: 5,0x | G83: 5,4x | H83: - | I83: 24,4x | J83: 4,8x | K83: 4,7x | L83: 4,1x | M83: 1,6x | N83: 8,6x | O83: 4,1x | P83: 3,7x | Q83: 5,0x | R83: 6,5x
B84: FCF / net income | C84: 3,3x | D84: 2,7x | E84: 3,3x | F84: 2,3x | G84: 2,2x | H84: - | I84: 28,9x | J84: 3,6x | K84: 2,8x | L84: 3,2x | M84: 0,6x | N84: 4,1x | O84: 3,6x | P84: 3,0x | Q84: 4,8x | R84: 2,6x
A86: x | B86: Per Share & Dilution | C86: =C81 -> Union Pacific Corp | D86: =D81 -> CAN NATL RAILWAY | E86: =E81 -> CSX CORP | F86: =F81 -> CANADIAN PACIFIC | G86: =G81 -> NORFOLK SOUTHERN | H86: =H81 -> BNSF RAILWAY CO | I86: =I81 -> BOEING CO/THE | J86: =J81 -> LOCKHEED MARTIN | ... R86: =R81 -> WASTE MANAGEMENT
B88: Diluted share count YoY | C88: 0,165% | D88: 0,158% | E88: 0,206% | F88: 0,171% | G88: 0,000% | H88: - | I88: - | J88: 0 | K88: 0 | L88: 0.01 | M88: 0 | N88: 0 | O88: 0 | P88: 0.01 | Q88: 0 | R88: 0
B89: SBC / revenue | C89: - | D89: - | E89: - | F89: - | G89: - | H89: - | I89: 0.01 | J89: 0 | K89: 0 | L89: 0 | M89: 0.01 | N89: 0 | O89: 0 | P89: 0.01 | Q89: 0.01 | R89: 0.01
B90: SBC / CFO | C90: - | D90: - | E90: - | F90: - | G90: - | H90: - | I90: -0.03 | J90: 0.04 | K90: 0.02 | L90: 0.04 | M90: 0.16 | N90: 0.02 | O90: 0.02 | P90: 0.03 | Q90: 0.05 | R90: 0.02
B91: EPS in USD | C91: 11,54 | D91: 05,21 | E91: 01,65 | F91: 03,29 | G91: 13,24 | H91: - | I91: -18,01 | J91: 23,11 | K91: 23,66 | L91: 15,06 | M91: 08,70 | N91: 19,46 | O91: 11,36 | P91: 09,72 | Q91: 10,01 | R91: 07,18
B105: Metrics | C105: Union Pacific Corp | D105: CAN NATL RAILWAY | E105: CSX CORP | F105: CANADIAN PACIFIC | G105: NORFOLK SOUTHERN | H105: BNSF RAILWAY CO | I105: BOEING CO/THE | J105: LOCKHEED MARTIN | K105: NORTHROP GRUMMAN | L105: GENERAL DYNAMICS | M105: 3M CO | N105: DEERE & CO | O105: ILLINOIS TOOL WO | P105: HONEYWELL INTL | Q105: AUTOMATIC DATA | R105: WASTE MANAGEMENT
B107: EBIT margin | C107: 0.4 | D107: 0.37 | E107: 0.36 | F107: 0.36 | G107: 0.34 | H107: 0.32 | I107: -0.16 | J107: 0.1 | K107: 0.11 | L107: 0.1 | M107: 0.2 | N107: 0.24 | O107: 0.27 | P107: 0.19 | Q107: 0.26 | R107: 0.18
B108: EBITDA margin | C108: 0.5 | D108: 0.49 | E108: 0.46 | F108: 0.49 | G108: 0.53 | H108: 0.45 | I108: -0.1 | J108: 0.11 | K108: 0.14 | L108: 0.12 | M108: 0.24 | N108: 0.27 | O108: 0.29 | P108: 0.23 | Q108: 0.3 | R108: 0.28
B109: RONA | C109: 0.58 | D109: 0.3 | E109: 0.42 | F109: 0.11 | G109: 0.28 | H109: 0.1 | I109: 2.74 | J109: 1.11 | K109: 0.29 | L109: 0.22 | M109: 1.24 | N109: 0.55 | O109: 1.29 | P109: 0.39 | Q109: 0.87 | R109: 0.49
B110: ROE | C110: 0.42 | D110: 0.22 | E110: 0.25 | F110: 0.09 | G110: 0.24 | H110: 0.1 | I110: #NAME? | J110: 0.73 | K110: 0.27 | L110: 0.18 | M110: 0.96 | N110: 0.22 | O110: 1.09 | P110: 0.35 | Q110: 0.76 | R110: 0.33
B111: Net operating asset turnover | C111: 0,7x | D111: 0,5x | E111: 0,6x | F111: 0,2x | G111: 0,5x | H111: 0,3x | I111: 0,9x | J111: 2,2x | K111: 1,5x | L111: 1,1x | M111: 1,3x | N111: 1,5x | O111: 2,6x | P111: 1,2x | Q111: 0,5x | R111: 1,2x
B112: Net debt / EBITDA | C112: 2,7x | D112: 2,5x | E112: 3,0x | F112: 2,9x | G112: 2,5x | H112: 0,1x | I112: #N/A N/A | J112: 2,7x | K112: 2,8x | L112: 1,5x | M112: 1,6x | N112: 0,2x | O112: 1,8x | P112: 2,9x | Q112: -0,6x | R112: 3,5x
B113: Capex intensity | C113: 0.14 | D113: 0.21 | E113: 0.17 | F113: 0.19 | G113: 0.2 | H113: 0.16 | I113: 0.03 | J113: 0.02 | K113: 0.04 | L113: 0.02 | M113: 0.05 | N113: 0.09 | O113: 0.03 | P113: 0.03 | Q113: 0.03 | R113: 0.15
B114: Dividend payout | C114: 0.48 | D114: 0.48 | E114: 0.27 | F114: 0.19 | G114: 0.47 | H114: 0 | I114: {=_xll.BDP(Inputs!$K$21,"DVD_PAYOUT_RATIO")/100} -> #VALUE! | J114: 0.57 | K114: 0.28 | L114: 0.41 | M114: 0.5 | N114: 0.23 | O114: 0.49 | P114: 0.5 | Q114: 0.6 | R114: 0.44
B115: Cash/earnings conversion | C115: 5,2x | D115: 5,8x | E115: 6,4x | F115: 5,0x | G115: 5,4x | H115: {=_xll.BDP(Inputs!$E$25,"cf_cash_from_oper")/_xll.BDP(Inputs!$E$25,"BEST_NET_INCOME")} -> #VALUE! | I115: 24,4x | J115: 4,8x | K115: 4,7x | L115: 4,1x | M115: 1,6x | N115: 8,6x | O115: 4,1x | P115: 3,7x | Q115: 5,0x | R115: 6,5x
B116: EPS in USD | C116: 11,54 | D116: 05,21 | E116: 01,65 | F116: 03,29 | G116: 13,24 | H116: #N/A | I116: -18,01 | J116: 23,11 | K116: 23,66 | L116: 15,06 | M116: 08,70 | N116: 19,46 | O116: 11,36 | P116: 09,72 | Q116: 10,01 | R116: 07,18

Sheet Trading Comps
D7: Current | E7: % of | I7: Enterprise Value / | S7: LTM | T7: Net | V7: Price / | Z7: LT
D8: Share | E8: 52-week | F8: Equity | G8: Enterprise | I8: LTM | J8: 2025 | K8: 2026 | L8: LTM | M8: 2025E | N8: 2026E | O8: LTM | P8: 2025E | Q8: 2026E | S8: EBITDA | T8: Debt / | V8: LTM | W8: 2025E | X8: 2026E | Z8: EPS | AB8: S
B9: Company | C9: Ticker | D9: Price | E9: High | F9: Value | G9: Value | I9: Sales | J9: Sales | K9: Sales | L9: EBITDA | M9: EBITDA | N9: EBITDA | O9: EBIT | P9: EBIT | Q9: EBIT | S9: Margin | T9: EBITDA | V9: EPS | W9: EPS | X9: EPS | Z9: Growth
B12: UNION PAC CORP | C12: UNP US | D12: USD 227,98 | E12: 88,8% | F12: 135 202 | G12: 169 336 | I12: 6,9x | J12: 6,9x | K12: 6,6x | L12: 13,8x | M12: 13,4x | N12: 12,7x | O12: 17,2x | P12: 16,8x | Q12: 15,7x | S12: 0.5 | T12: 2,8x | V12: 19,5x | W12: 19,3x | X12: 18,0x | Z12: 0.1
B17: =+Inputs!B21 -> CAN NATL RAILWAY | C17: CNR CN | D17: CAD 127,52 | E17: 79,3% | F17: 79 609 | G17: 109 390 | I17: 6,4x | J17: 6,3x | K17: 6,0x | L17: 13,1x | M17: 12,6x | N17: 11,8x | O17: 17,1x | P17: 16,5x | Q17: 15,3x | S17: 0.49 | T17: 2,5x | V17: 17,4x | W17: 16,8x | X17: 15,7x | Z17: 0.07
B18: =+Inputs!B22 -> CSX CORP | C18: CSX US | D18: USD 34,07 | E18: 91,5% | F18: 63 516 | G18: 80 093 | I18: 5,7x | J18: 5,6x | K18: 5,4x | L18: 12,2x | M18: 12,2x | N18: 11,2x | O18: 16,4x | P18: 16,5x | Q18: 15,0x | S18: 0.46 | T18: 3,0x | V18: 20,1x | W18: 20,4x | X18: 18,2x | Z18: 0.09
B19: =+Inputs!B23 -> CANADIAN PACIFIC | C19: CP CN | D19: CAD 102,63 | E19: 86,4% | F19: 93 765 | G19: 122 100 | I19: 8,2x | J19: 8,0x | K19: 7,5x | L19: 15,6x | M19: 15,4x | N19: 14,1x | O19: 20,8x | P19: 20,1x | Q19: 18,0x | S19: 0.52 | T19: 3,0x | V19: 22,0x | W19: 21,5x | X19: 19,4x | Z19: 0.09
B20: =+Inputs!B24 -> NORFOLK SOUTHERN | C20: NSC US | D20: USD 292,08 | E20: 99,1% | F20: 65 606 | G20: 73 559 | I20: 6,0x | J20: 6,0x | K20: 5,7x | L20: 12,4x | M20: 12,7x | N20: 11,9x | O20: 16,1x | P20: 16,8x | Q20: 15,5x | S20: 0.49 | T20: 2,7x | V20: 21,9x | W20: 22,9x | X20: 20,9x | Z20: 0.09
B21: =+Inputs!B25 -> BNSF RAILWAY CO | C21: BNI1 US | D21: USD #N/A N/A | E21: - | F21: #N/A N/A | G21: #N/A N/A | I21: - | J21: - | K21: - | L21: - | M21: - | N21: - | O21: - | P21: - | Q21: - | S21: 0.45 | T21: 0,1x | V21: - | W21: - | X21: - | Z21: -
Z22: -
B23: Mean | I23: 6,6x | J23: 6,5x | K23: 6,2x | L23: 13,3x | M23: 13,2x | N23: 12,2x | O23: 17,6x | P23: 17,5x | Q23: 16,0x | S23: 48,2% | T23: 2,3x | V23: 20,4x | W23: 20,4x | X23: 18,6x | Z23: 8,6%
B24: Median | I24: 6,2x | J24: 6,1x | K24: 5,9x | L24: 12,7x | M24: 12,7x | N24: 11,8x | O24: 16,7x | P24: 16,7x | Q24: 15,4x | S24: 48,6% | T24: 2,7x | V24: 21,0x | W24: 21,0x | X24: 18,8x | Z24: 9,0%
B29: =+Inputs!H21 -> BOEING CO/THE | C29: BA US | D29: USD 215,1 | E29: 88,6% | F29: 162 650 | G29: 194 431 | I29: 2,6x | J29: 2,3x | K29: 2,0x | L29: -23,3x | M29: 66,7x | N29: 25,4x | O29: -19,0x | P29: 249,7x | Q29: 37,0x | S29: -0.11 | T29: #N/A N/A | V29: -13,6x | W29: -109,2x | X29: 60,9x | Z29: -2.75
B30: =+Inputs!H22 -> LOCKHEED MARTIN | C30: LMT US | D30: USD 486,25 | E30: 78,6% | F30: 113 522 | G30: 126 738 | I30: 1,8x | J30: 1,8x | K30: 1,6x | L30: 13,8x | M30: 13,7x | N30: 11,6x | O30: 16,8x | P30: 16,7x | Q30: 13,7x | S30: 0.13 | T30: 2,8x | V30: 20,8x | W30: 22,2x | X30: 17,1x | Z30: 0.12
B31: =+Inputs!H23 -> NORTHROP GRUMMAN | C31: NOC US | D31: USD 586,27 | E31: 97,6% | F31: 83 944 | G31: 87 252 | I31: 2,2x | J31: 2,1x | K31: 2,0x | L31: 16,1x | M31: 14,9x | N31: 13,7x | O31: 21,9x | P31: 19,6x | Q31: 17,9x | S31: 0.13 | T31: 3,1x | V31: 24,5x | W31: 23,0x | X31: 20,7x | Z31: 0.08
B32: =+Inputs!H24 -> GENERAL DYNAMICS | C32: GD US | D32: USD 323,62 | E32: 98,0% | F32: 87 052 | G32: 87 303 | I32: 1,7x | J32: 1,7x | K32: 1,6x | L32: 14,4x | M32: 14,1x | N32: 13,0x | O32: 16,9x | P32: 16,6x | Q32: 15,1x | S32: 0.12 | T32: 1,7x | V32: 21,3x | W32: 21,1x | X32: 19,1x | Z32: 0.08
B33: =+Inputs!H25 -> 3M CO | C33: MMM US | D33: USD 154,6 | E33: 94,2% | F33: 82 345 | G33: 90 661 | I33: 3,7x | J33: 3,8x | K33: 3,6x | L33: 12,6x | M33: 13,4x | N33: 12,6x | O33: 15,1x | P33: 16,1x | Q33: 15,2x | S33: 0.29 | T33: 2,3x | V33: 17,4x | W33: 19,3x | X33: 18,1x | Z33: 0.07
B35: Mean | I35: 2,4x | J35: 2,3x | K35: 2,2x | L35: 6,7x | M35: 24,5x | N35: 15,3x | O35: 10,4x | P35: 63,7x | Q35: 19,8x | S35: 11,3% | T35: 2,5x | V35: 14,1x | W35: -4,7x | X35: 27,2x | Z35: -48,0%
B36: Median | I36: 2,2x | J36: 2,1x | K36: 2,0x | L36: 13,8x | M36: 14,1x | N36: 13,0x | O36: 16,8x | P36: 16,7x | Q36: 15,2x | S36: 12,8% | T36: 2,6x | V36: 20,8x | W36: 21,1x | X36: 19,1x | Z36: 7,6%
B41: =+Inputs!N21 -> DEERE & CO | C41: DE US | D41: USD 468,94 | E41: 87,9% | F41: 126 768 | G41: 142 321 | I41: 3,2x | J41: 3,7x | K41: 3,5x | L41: 12,0x | M41: 20,1x | N41: 17,7x | O41: 14,7x | P41: 24,8x | Q41: 21,3x | S41: 0.27 | T41: 5,6x | V41: 24,0x | W41: 25,2x | X41: 22,9x | Z41: 0.18
B42: =+Inputs!N22 -> ILLINOIS TOOL WO | C42: ITW US | D42: USD 259,56 | E42: 93,0% | F42: 75 662 | G42: 80 223 | I42: 5,1x | J42: 5,0x | K42: 4,8x | L42: 17,8x | M42: 17,3x | N42: 16,4x | O42: 19,6x | P42: 18,9x | Q42: 17,9x | S42: 0.29 | T42: 2,0x | V42: 22,6x | W42: 24,9x | X42: 23,5x | Z42: 0.06
B43: =+Inputs!N23 -> HONEYWELL INTL | C43: HON US | D43: USD 208,6 | E43: 85,9% | F43: 132 439 | G43: 175 386 | I43: 4,4x | J43: 4,3x | K43: 4,1x | L43: 18,2x | M43: 16,6x | N43: 15,6x | O43: 21,6x | P43: 18,5x | Q43: 17,3x | S43: 0.24 | T43: 4,1x | V43: 21,1x | W43: 19,5x | X43: 18,4x | Z43: 0.07
B44: =+Inputs!N24 -> AUTOMATIC DATA | C44: ADP US | D44: USD 291,5 | E44: 88,4% | F44: 118 070 | G44: 121 583 | I44: 5,9x | J44: 5,9x | K44: 5,6x | L44: 19,9x | M44: 20,6x | N44: 19,1x | O44: 22,5x | P44: 22,7x | Q44: 20,9x | S44: 0.3 | T44: 0,7x | V44: 29,0x | W44: 29,0x | X44: 26,7x | Z44: 0.08
B45: =+Inputs!N25 -> WASTE MANAGEMENT | C45: WM US | D45: USD 219,42 | E45: 90,5% | F45: 88 389 | G45: 115 704 | I45: 4,8x | J45: 4,6x | K45: 4,3x | L45: 16,6x | M45: 15,4x | N45: 14,2x | O45: 26,3x | P45: 24,2x | Q45: 21,6x | S45: 0.29 | T45: 3,5x | V45: 30,6x | W45: 29,0x | X45: 25,6x | Z45: 0.12
B47: Mean | I47: 4,7x | J47: 4.7x | K47: 4,5x | L47: 16,9x | M47: 18,0x | N47: 16,6x | O47: 20,9x | P47: 21,8x | Q47: 19,8x | S47: 27,6% | T47: 3,2x | V47: 25,5x | W47: 25,5x | X47: 23,4x | Z47: 0.1
B48: Median | I48: 4,8x | J48: 4,6x | K48: 4,3x | L48: 17,8x | M48: 17,3x | N48: 16,4x | O48: 21,6x | P48: 22,7x | Q48: 20,9x | S48: 28,5% | T48: 3,5x | V48: 24,0x | W48: 25,2x | X48: 23,5x | Z48: 0.08
B50: Overall
B53: Mean | I53: 4,4x | J53: 4,4x | K53: 4,1x | L53: 12,2x | M53: 19,2x | N53: 14,9x | O53: 16,2x | P53: 38,0x | Q53: 18,7x | S53: 29,0% | T53: 2,7x | V53: 19,9x | W53: 14,8x | X53: 23,5x | Z53: -0.1
B54: Median | I54: 4,6x | J54: 4,4x | K54: 4,2x | L54: 14,1x | M54: 15,1x | N54: 13,9x | O54: 17,0x | P54: 18,7x | Q54: 17,6x | S54: 29,1% | T54: 2,8x | V54: 21,8x | W54: 21,9x | X54: 20,2x | Z54: 0.08
B56: High | I56: 8,2x | J56: 8,0x | K56: 7,5x | L56: 19,9x | M56: 70,5x | N56: 25,3x | O56: 26,3x | P56: 283,9x | Q56: 37,6x | S56: 52,5% | T56: 5,6x | V56: 30,5x | W56: 29,0x | X56: 62,9x | Z56: 0.18
B57: Low | I57: 1,7x | J57: 1,7x | K57: 1,6x | L57: -23,3x | M57: 12,2x | N57: 11,2x | O57: -19,0x | P57: 16,1x | Q57: 13,7x | S57: -11,1% | T57: 0,1x | V57: -14,0x | W57: -87,7x | X57: 15,7x | Z57: -2.57

Sheet WACC
A7: x | B7: Rolling WACC | K7: Equity Risk Premium
P8: Weights
D9: 2025 | E9: =+D9+1 -> 2026 | F9: =+E9+1 -> 2027 | G9: =+F9+1 -> 2028 | H9: =+G9+1 -> 2029 | M9: ERP | N9: 2025 | O9: =+N9+1 -> 2026 | P9: =+O9+1 -> 2027 | Q9: =+P9+1 -> 2028 | R9: =+Q9+1 -> 2029
B12: Equity: | K12: United States | M12: 0.0433 | N12: 0.6 | O12: 0.6 | P12: 0.6 | Q12: 0.6 | R12: 0.6
B13: Market Cap (in billions) | D13: =+Inputs!J13 -> 128121.15 | E13: =FCFF!AF99*FCFF!AF31 -> 133563.16 | F13: =FCFF!AH99*FCFF!AH31 -> 134138.86 | G13: =FCFF!AJ99*FCFF!AJ31 -> 138301.1 | H13: =FCFF!AL99*FCFF!AL31 -> 141670.8 | K13: Outside of US | M13: =((0.0687+0.0433)/2) -> 0.056 | N13: 0.4 | O13: 0.4 | P13: 0.4 | Q13: 0.4 | R13: 0.4
B14: % of Equity | D14: =IFERROR(D13/D35,"") -> 0.79049484 | E14: =IFERROR(E13/E35,"") -> 0.79408161 | F14: =IFERROR(E13/F35,"") -> 0.78813817 | G14: =IFERROR(F13/G35,"") -> 0.76942951 | H14: =IFERROR(G13/H35,"") -> 0.775118 | N14: - | O14: - | P14: - | Q14: - | R14: -
B15: Risk-Free Rate | D15: 0.0416 | E15: 0.0362 | F15: 0.0355 | G15: 0.0356 | H15: 0.0368 | N15: - | O15: - | P15: - | Q15: - | R15: -
B16: Beta | D16: =+Inputs!M18 -> 0.82 | E16: =+D17*(1+(E28/E13)*(1-E32)) -> 0.81700366 | F16: =+E17*(1+(F28/F13)*(1-F32)) -> 0.81912802 | G16: =+F17*(1+(G28/G13)*(1-G32)) -> 0.81765064 | H16: =+G17*(1+(H28/H13)*(1-H32)) -> 0.81706845 | N16: - | O16: - | P16: - | Q16: - | R16: -
B17: Unlevered Beta | D17: =+D16/(1+(D28/D13)*(1-D32)) -> 0.6810216 | E17: =+E16/(1+(E28/E13)*(1-E32)) -> 0.6810216 | F17: =+F16/(1+(F28/F13)*(1-F32)) -> 0.6810216 | G17: =+G16/(1+(G28/G13)*(1-G32)) -> 0.6810216 | H17: =+H16/(1+(H28/H13)*(1-H32)) -> 0.6810216
B18: Equity Risk Premium | D18: =+N18 -> 0.04838 | E18: =+O18 -> 0.04838 | F18: =+P18 -> 0.04838 | G18: =+Q18 -> 0.04838 | H18: =+R18 -> 0.04838 | K18: ERP | N18: =+SUMPRODUCT($M12:$M16,N12:N16) -> 0.04838 | O18: =+SUMPRODUCT($M12:$M16,O12:O16) -> 0.04838 | P18: =+SUMPRODUCT($M12:$M16,P12:P16) -> 0.04838 | Q18: =+SUMPRODUCT($M12:$M16,Q12:Q16) -> 0.04838 | R18: =+SUMPRODUCT($M12:$M16,R12:R16) -> 0.04838
B19: Ke (Cost of Equity) | D19: =IFERROR(+D15+D16*D18,"") -> 0.0812716 | E19: =IFERROR(+E15+E16*E18,"") -> 0.075726637 | F19: =IFERROR(+F15+F16*F18,"") -> 0.075129414 | G19: =IFERROR(+G15+G16*G18,"") -> 0.075157938 | H19: =IFERROR(+H15+H16*H18,"") -> 0.076329772
B21: Preferred Equity: | K21: ROIC vs WACC
B22: Market Capitalization | D22: =IFERROR(Inputs!J14,0) -> 0 | E22: =+D22*(E13/D13) -> 0 | F22: =+E22*(F13/E13) -> 0 | G22: =+F22*(G13/F13) -> 0 | H22: =+G22*(H13/G13) -> 0
B23: % of Preferred Equity | D23: =+D22/D35 -> 0 | E23: =+E22/E35 -> 0 | F23: =+F22/F35 -> 0 | G23: =+G22/G35 -> 0 | H23: =+H22/H35 -> 0
B24: Preferred Dividends | D24: =+IS!AF50 -> 0 | E24: =D24 -> 0 | F24: =E24 -> 0 | G24: =F24 -> 0 | H24: =G24 -> 0
B25: Kp (Cost of Preferred Equity) | D25: =IFERROR(D24/D22,0) -> 0 | E25: =IFERROR(E24/E22,0) -> 0 | F25: =IFERROR(F24/F22,0) -> 0 | G25: =IFERROR(G24/G22,0) -> 0 | H25: =IFERROR(H24/H22,0) -> 0
B27: Debt:
B28: Debt (in millions) | C28: =+BS!AF38+BS!AF39+BS!AF44+BS!AF45 -> 32463 | D28: =+BS!AI38+BS!AI39+BS!AI44+BS!AI45 -> 33956 | E28: =D28*1.02 -> 34635.12 | F28: =E28*1.02 -> 35327.822 | G28: =F28*1.02 -> 36034.379 | H28: =G28*1.02 -> 36755.066
B29: % of Debt | D29: =IFERROR(D28/D35,"") -> 0.20950516 | E29: =IFERROR(E28/E35,"") -> 0.20591839 | F29: =IFERROR(F28/F35,"") -> 0.2084647 | G29: =IFERROR(G28/G35,"") -> 0.20669561 | H29: =IFERROR(H28/H35,"") -> 0.20599629
B30: Debt Spread | D30: =+D31-D15 -> -0.0038158087 | E30: 0.005 | F30: 0.005 | G30: 0.005 | H30: 0.005
B31: Cost of Debt | D31: =+(IS!AI36+IS!AH36+IS!AE36+IS!AD36)/WACC!D28 -> 0.037784191 | E31: =+E30+E15 -> 0.0412 | F31: =+F30+F15 -> 0.0405 | G31: =+G30+G15 -> 0.0406 | H31: =+H30+H15 -> 0.0418
B32: Tax Rate | D32: =+FCFF!Z124 -> 0.23 | E32: =+FCFF!AF124 -> 0.23 | F32: =+FCFF!AH124 -> 0.23 | G32: =+FCFF!AJ124 -> 0.23 | H32: =+FCFF!AL124 -> 0.23
B33: Kd (After-Tax Cost of Debt) | D33: =+D31*(1-D32) -> 0.029093827 | E33: =+E31*(1-E32) -> 0.031724 | F33: =+F31*(1-F32) -> 0.031185 | G33: =+G31*(1-G32) -> 0.031262 | H33: =+H31*(1-H32) -> 0.032186
B35: Total | D35: =+D13+D24+D28 -> 162077.15 | E35: =+E13+E24+E28 -> 168198.28 | F35: =+F13+F24+F28 -> 169466.69 | G35: =+G13+G24+G28 -> 174335.48 | H35: =+H13+H24+H28 -> 178425.87
B37: Country/Conglomerate/... Risk Premium | D37: 0 | E37: 0 | F37: 0 | G37: 0 | H37: 0
A39: x | B39: WACC | D39: =+D19*D14+D25*D23+D33*D29+D37 -> 0.070340087 | E39: =+E19*E14+E25*E23+E33*E29+E37 -> 0.066665685 | F39: =+F19*F14+F25*F23+F33*F29+F37 -> 0.06571333 | G39: =+G19*G14+G25*G23+G33*G29+G37 -> 0.064290454 | H39: =+H19*H14+H25*H23+H33*H29+H37 -> 0.065794777
B41: NOPAT | D41: =+FCFF!Z126 -> 8401.4117 | E41: =+FCFF!AF126 -> 8620.0282 | F41: =+FCFF!AH126 -> 9149.7741 | G41: =+FCFF!AJ126 -> 9662.704 | H41: =+FCFF!AL126 -> 10204.503
B42: Total Payout | D42: =+FCFF!Z112+FCFF!Z115 -> -8091.607 | E42: =+FCFF!AF112+FCFF!AF115 -> -7906.6121 | F42: =+FCFF!AH112+FCFF!AH115 -> -8184.4029 | G42: =+FCFF!AJ112+FCFF!AJ115 -> -4058.3357 | H42: =+FCFF!AL112+FCFF!AL115 -> -4183.8464
B43: Book Value of Equity | C43: =+BS!AF54 -> 16890 | D43: =+C43+D41+D42 -> 17199.805 | E43: =+D43+E41+E42 -> 17913.221 | F43: =+E43+F41+F42 -> 18878.592 | G43: =+F43+G41+G42 -> 24482.96 | H43: =+G43+H41+H42 -> 30503.617
B44: Invested Capital | C44: =+C43+C28 -> 49353 | D44: =+D43+D28 -> 51155.805 | E44: =+E43+E28 -> 52548.341 | F44: =+F43+F28 -> 54206.414 | G44: =+G43+G28 -> 60517.339 | H44: =+H43+H28 -> 67258.684
A45: x | B45: ROIC | D45: =+D41/((D44+C44)/2) -> 0.16717763 | E45: =+E41/((E44+D44)/2) -> 0.16624269 | F45: =+F41/((F44+E44)/2) -> 0.1714167 | G45: =+G41/((G44+F44)/2) -> 0.16845167 | H45: =+H41/((H44+G44)/2) -> 0.15972486
W49: ,

Sheet FCFF
A7: x | B7: Market Assumptions
D8: 2022 | J8: =D8+1 -> 2023 | P8: =J8+1 -> 2024 | V8: =P8+1 -> 2025 | AB8: =V8+1 -> 2026 | AH8: =AB8+1 -> 2027 | AJ8: =+AH8+1 -> 2028 | AL8: =+AJ8+1 -> 2029
D9: Q1 | E9: Q2 | F9: Q3 | G9: Q4 | H9: FY | J9: Q1 | K9: Q2 | L9: Q3 | M9: Q4 | N9: FY | P9: Q1 | Q9: Q2 | R9: Q3 | S9: Q4 | T9: FY | V9: Q1 | W9: Q2 | X9: Q3 | Y9: Q4 | Z9: FY | AB9: Q1 | AC9: Q2 | AD9: Q3 | AE9: Q4 | AF9: FY | AH9: FY | AJ9: FY | AL9: FY
B11: Bulk | H11: =Segments!T21 -> 7537 | N11: =Segments!Z21 -> 7358 | T11: =Segments!AF21 -> 7207 | Z11: =Anexo_projections!AA60 -> 7502.4757 | AF11: =Anexo_projections!AG60 -> 7727.1069 | AH11: =Anexo_projections!AI60 -> 7927.8107 | AJ11: =Anexo_projections!AK60 -> 8179.4589 | AL11: =Anexo_projections!AM60 -> 8453.6025
B12: Industrials | H12: =Segments!T22 -> 8205 | N12: =Segments!Z22 -> 8238 | T12: =Segments!AF22 -> 8440 | Z12: =Anexo_projections!AA69 -> 8434.437 | AF12: =Anexo_projections!AG69 -> 8683.6106 | AH12: =Anexo_projections!AI69 -> 8963.96 | AJ12: =Anexo_projections!AK69 -> 9222.7948 | AL12: =Anexo_projections!AM69 -> 9476.3775
B13: Premium | H13: =Segments!T23 -> 7417 | N13: =Segments!Z23 -> 6975 | T13: =Segments!AF23 -> 7164 | Z13: =Anexo_projections!AA74 -> 8043.9583 | AF13: =Anexo_projections!AG74 -> 8278.1383 | AH13: =Anexo_projections!AI74 -> 8436.0022 | AJ13: =Anexo_projections!AK74 -> 8757.9669 | AL13: =Anexo_projections!AM74 -> 8904.1805
B14: Other revenues | H14: =Segments!T24 -> 1716 | N14: =Segments!Z24 -> 1548 | T14: =Segments!AF24 -> 1439 | Z14: =Anexo_projections!AA77 -> 1500 | AF14: =Anexo_projections!AG77 -> 1500 | AH14: =Anexo_projections!AI77 -> 1500 | AJ14: =Anexo_projections!AK77 -> 1500 | AL14: =Anexo_projections!AM77 -> 1500
B21: Revenue | H21: =SUM(H11:H19) -> 24875 | N21: =SUM(N11:N19) -> 24119 | T21: =SUM(T11:T19) -> 24250 | Z21: =SUM(Z11:Z19) -> 25480.871 | AA21: =SUM(AA11:AA19) -> 0 | AF21: =SUM(AF11:AF19) -> 26188.856 | AG21: =SUM(AG11:AG19) -> 0 | AH21: =SUM(AH11:AH19) -> 26827.773 | AI21: =SUM(AI11:AI19) -> 0 | AJ21: =SUM(AJ11:AJ19) -> 27660.221 | AK21: =SUM(AK11:AK19) -> 0 | AL21: =SUM(AL11:AL19) -> 28334.16
A23: x | B23: Operating Assumptions
D24: =D$8 -> 2022 | E24: =F24 -> 0 | F24: =F$8 -> 0 | G24: =F24 -> 0 | H24: =F24 -> 0 | J24: =J$8 -> 2023 | K24: =L24 -> 0 | L24: =L$8 -> 0 | M24: =L24 -> 0 | N24: =L24 -> 0 | P24: =P$8 -> 2024 | Q24: =R24 -> 0 | R24: =R$8 -> 0 | S24: =R24 -> 0 | T24: =R24 -> 0 | V24: =V$8 -> 2025 | W24: =X24 -> 0 | X24: =X$8 -> 0 | Y24: =X24 -> 0 | Z24: =X24 -> 0 | AB24: =AB$8 -> 2026 | AC24: =AD24 -> 0 | AD24: =AD$8 -> 0 | AE24: =AD24 -> 0 | AF24: =AD24 -> 0 | AH24: =AH$8 -> 2027 | AJ24: =AJ$8 -> 2028 | AL24: =AL$8 -> 2029 | AM24: =AN24 -> 0
D25: Q1 | E25: Q2 | F25: Q3 | G25: Q4 | H25: FY | J25: Q1 | K25: Q2 | L25: Q3 | M25: Q4 | N25: FY | P25: Q1 | Q25: Q2 | R25: Q3 | S25: Q4 | T25: FY | V25: Q1 | W25: Q2 | X25: Q3 | Y25: Q4 | Z25: FY | AB25: Q1 | AC25: Q2 | AD25: Q3 | AE25: Q4 | AF25: FY | AH25: FY | AJ25: FY | AL25: FY
B28: Income Statement
B31: Revenue | D31: =IS!P18 -> 5860 | E31: =IS!Q18 -> 6269 | F31: =IS!R18 -> 6566 | G31: =IS!S18 -> 6180 | H31: =IS!T18 -> 24875 | J31: =IS!V18 -> 6056 | K31: =IS!W18 -> 5963 | L31: =IS!X18 -> 5941 | M31: =IS!Y18 -> 6159 | N31: =IS!Z18 -> 24119 | P31: =IS!AB18 -> 6031 | Q31: =IS!AC18 -> 6007 | R31: =IS!AD18 -> 6091 | S31: =IS!AE18 -> 6121 | T31: =IS!AF18 -> 24250 | V31: =IS!AH18 -> 6027 | W31: =IS!AI18 -> 6154 | Z31: =Z21 -> 25480.871 | AF31: =AF21 -> 26188.856 | AH31: =AH21 -> 26827.773 | AI31: =AI21 -> 0 | AJ31: =AJ21 -> 27660.221 | AK31: =AK21 -> 0 | AL31: =AL21 -> 28334.16
B32: % of growth | D32: =D31/IS!J18-1 -> 0.17176565 | E32: =E31/IS!K18-1 -> 0.13898983 | F32: =F31/IS!L18-1 -> 0.17966223 | G32: =G31/IS!M18-1 -> 0.077969649 | H32: =H31/IS!N18-1 -> 0.14084572 | J32: =J31/IS!P18-1 -> 0.033447099 | K32: =K31/IS!Q18-1 -> -0.048811613 | L32: =L31/IS!R18-1 -> -0.095187329 | M32: =M31/IS!S18-1 -> -0.0033980583 | N32: =N31/H31-1 -> -0.03039196 | P32: =P31/IS!V18-1 -> -0.0041281374 | Q32: =Q31/IS!W18-1 -> 0.0073788362 | R32: =R31/IS!X18-1 -> 0.025248275 | S32: =S31/IS!Y18-1 -> -0.0061698328 | T32: =T31/N31-1 -> 0.0054314026 | V32: =V31/IS!AB18-1 -> -0.00066323993 | W32: =W31/IS!AC18-1 -> 0.02447145 | X32: =X31/IS!AD18-1 -> -1 | Y32: =Y31/IS!AE18-1 -> -1 | Z32: =Z31/T31-1 -> 0.050757567 | AB32: =AB31/IS!AH18-1 -> -1 | AC32: =AC31/IS!AI18-1 -> -1 | AD32: =AD31/X31-1 -> #DIV/0! | AE32: =AE31/Y31-1 -> #DIV/0! | AF32: =AF31/Z31-1 -> 0.027784954 | AH32: =AH31/AF31-1 -> 0.024396527 | AJ32: =AJ31/AH31-1 -> 0.031029324 | AL32: =AL31/AJ31-1 -> 0.024364949
B34: Cost of Goods & Services | D34: =IS!P21 -> 0 | E34: =IS!Q21 -> 0 | F34: =IS!R21 -> 0 | G34: =IS!S21 -> 0 | H34: =IS!T21 -> 0 | J34: =IS!V21 -> 0 | K34: =IS!W21 -> 0 | L34: =IS!X21 -> 0 | M34: =IS!Y21 -> 0 | N34: =IS!Z21 -> 0 | P34: =IS!AB21 -> 0 | Q34: =IS!AC21 -> 0 | R34: =IS!AD21 -> 0 | S34: =IS!AE21 -> 0 | T34: =IS!AF21 -> 0 | V34: =IS!AH21 -> 0 | W34: =IS!AI21 -> 0 | X34: =(X35+Sensitivity!$U$39)*X$31 -> 0 | Y34: =(Y35+Sensitivity!$U$39)*Y$31 -> 0 | Z34: =(Z35+Sensitivity!$U$39)*Z$31 -> 0 | AB34: =(AB35+Sensitivity!$U$39)*AB$31 -> 0 | AC34: =(AC35+Sensitivity!$U$39)*AC$31 -> 0 | AD34: =(AD35+Sensitivity!$U$39)*AD$31 -> 0 | AE34: =(AE35+Sensitivity!$U$39)*AE$31 -> 0 | AF34: =(AF35+Sensitivity!$U$39)*AF$31 -> 0 | AH34: =(AH35+Sensitivity!$U$39)*AH$31 -> 0 | AJ34: =(AJ35+Sensitivity!$U$39)*AJ$31 -> 0 | AL34: =(AL35+Sensitivity!$U$39)*AL$31 -> 0
B35: % of sales | D35: =D34/D31 -> 0 | E35: =E34/E31 -> 0 | F35: =F34/F31 -> 0 | G35: =G34/G31 -> 0 | H35: =H34/H31 -> 0 | J35: =J34/J31 -> 0 | K35: =K34/K31 -> 0 | L35: =L34/L31 -> 0 | M35: =M34/M31 -> 0 | N35: =N34/N31 -> 0 | P35: =P34/P31 -> 0 | Q35: =Q34/Q31 -> 0 | R35: =R34/R31 -> 0 | S35: =S34/S31 -> 0 | T35: =T34/T31 -> 0 | V35: =V34/V31 -> 0 | W35: =W34/W31 -> 0 | Z35: =AVERAGE(T35,N35,H35) -> 0 | AF35: 0 | AH35: 0 | AJ35: 0 | AL35: 0
B37: COGS Depreciation & Amortization | D37: =IS!P22 -> 0 | E37: =IS!Q22 -> 0 | F37: =IS!R22 -> 0 | G37: =IS!S22 -> 0 | H37: =IS!T22 -> 0 | J37: =IS!V22 -> 0 | K37: =IS!W22 -> 0 | L37: =IS!X22 -> 0 | M37: =IS!Y22 -> 0 | N37: =IS!Z22 -> 0 | P37: =IS!AB22 -> 0 | Q37: =IS!AC22 -> 0 | R37: =IS!AD22 -> 0 | S37: =IS!AE22 -> 0 | T37: =IS!AF22 -> 0 | V37: =IS!AH22 -> 0 | W37: =IS!AI22 -> 0 | X37: =X38*X34 -> 0 | Y37: =Y38*Y34 -> 0 | Z37: =SUM(V37:Y37) -> 0 | AB37: =AB38*AB34 -> 0 | AC37: =AC38*AC34 -> 0 | AD37: =AD38*AD34 -> 0 | AE37: =AE38*AE34 -> 0 | AF37: =SUM(AB37:AE37) -> 0 | AH37: =AH38*AH34 -> 0 | AJ37: =AJ38*AJ34 -> 0 | AL37: =AL38*AL34 -> 0
B38: % of cost of goods & services | D38: =D37/D34 -> #DIV/0! | E38: =E37/E34 -> #DIV/0! | F38: =F37/F34 -> #DIV/0! | G38: =G37/G34 -> #DIV/0! | H38: =H37/H34 -> #DIV/0! | J38: =J37/J34 -> #DIV/0! | K38: =K37/K34 -> #DIV/0! | L38: =L37/L34 -> #DIV/0! | M38: =M37/M34 -> #DIV/0! | N38: =N37/N34 -> #DIV/0! | P38: =P37/P34 -> #DIV/0! | Q38: =Q37/Q34 -> #DIV/0! | R38: =R37/R34 -> #DIV/0! | S38: =S37/S34 -> #DIV/0! | T38: =T37/T34 -> #DIV/0! | V38: =V37/V34 -> #DIV/0! | W38: =W37/W34 -> #DIV/0! | Z38: 0 | AF38: 0 | AH38: 0 | AJ38: 0 | AL38: 0
B40: Gross Profit | D40: =IS!P24 -> 5860 | E40: =IS!Q24 -> 6269 | F40: =IS!R24 -> 6566 | G40: =IS!S24 -> 6180 | H40: =IS!T24 -> 24875 | J40: =IS!V24 -> 6056 | K40: =IS!W24 -> 5963 | L40: =IS!X24 -> 5941 | M40: =IS!Y24 -> 6159 | N40: =IS!Z24 -> 24119 | P40: =IS!AB24 -> 6031 | Q40: =IS!AC24 -> 6007 | R40: =IS!AD24 -> 6091 | S40: =IS!AE24 -> 6121 | T40: =IS!AF24 -> 24250 | V40: =IS!AH24 -> 6027 | W40: =IS!AI24 -> 6154 | X40: =X31-X34-X37 -> 0 | Y40: =Y31-Y34-Y37 -> 0 | Z40: =Z31 -> 25480.871 | AB40: =AB31-AB34-AB37 -> 0 | AC40: =AC31-AC34-AC37 -> 0 | AD40: =AD31-AD34-AD37 -> 0 | AE40: =AE31-AE34-AE37 -> 0 | AF40: =AF31 -> 26188.856 | AH40: =AH31-AH34-AH37 -> 26827.773 | AJ40: =AJ31-AJ34-AJ37 -> 27660.221 | AL40: =AL31-AL34-AL37 -> 28334.16
B41: % of sales | D41: =D40/D31 -> 1 | E41: =E40/E31 -> 1 | F41: =F40/F31 -> 1 | G41: =G40/G31 -> 1 | H41: =H40/H31 -> 1 | J41: =J40/J31 -> 1 | K41: =K40/K31 -> 1 | L41: =L40/L31 -> 1 | M41: =M40/M31 -> 1 | N41: =N40/N31 -> 1 | P41: =P40/P31 -> 1 | Q41: =Q40/Q31 -> 1 | R41: =R40/R31 -> 1 | S41: =S40/S31 -> 1 | T41: =T40/T31 -> 1 | V41: =V40/V31 -> 1 | W41: =W40/W31 -> 1 | X41: =X40/X31 -> #DIV/0! | Y41: =Y40/Y31 -> #DIV/0! | Z41: =Z40/Z$31 -> 1 | AB41: =AB40/AB31 -> #DIV/0! | AC41: =AC40/AC31 -> #DIV/0! | AD41: =AD40/AD31 -> #DIV/0! | AE41: =AE40/AE31 -> #DIV/0! | AF41: =AF40/AF$31 -> 1 | AH41: =AH40/AH31 -> 1 | AJ41: =AJ40/AJ31 -> 1 | AL41: =AL40/AL31 -> 1
B43: SG&A (Selling, General & Administrative) | D43: =IS!P27 -> 0 | E43: =IS!Q27 -> 0 | F43: =IS!R27 -> 0 | G43: =IS!S27 -> 0 | H43: =IS!T27 -> 0 | J43: =IS!V27 -> 0 | K43: =IS!W27 -> 0 | L43: =IS!X27 -> 0 | M43: =IS!Y27 -> 0 | N43: =IS!Z27 -> 0 | P43: =IS!AB27 -> 0 | Q43: =IS!AC27 -> 0 | R43: =IS!AD27 -> 0 | S43: =IS!AE27 -> 0 | T43: =IS!AF27 -> 0 | V43: =IS!AH27 -> 0 | W43: =IS!AI27 -> 0 | X43: =(X44+Sensitivity!$U$40)*X$31 -> 0 | Y43: =(Y44+Sensitivity!$U$40)*Y$31 -> 0 | Z43: =SUM(V43:Y43) -> 0 | AB43: =(AB44+Sensitivity!$U$40)*AB$31 -> 0 | AC43: =(AC44+Sensitivity!$U$40)*AC$31 -> 0 | AD43: =(AD44+Sensitivity!$U$40)*AD$31 -> 0 | AE43: =(AE44+Sensitivity!$U$40)*AE$31 -> 0 | AF43: =SUM(AB43:AE43) -> 0 | AH43: =(AH44+Sensitivity!$U$40)*AH$31 -> 0 | AJ43: =(AJ44+Sensitivity!$U$40)*AJ$31 -> 0 | AL43: =(AL44+Sensitivity!$U$40)*AL$31 -> 0
B44: % of sales | D44: =D43/D31 -> 0 | E44: =E43/E31 -> 0 | F44: =F43/F31 -> 0 | G44: =G43/G31 -> 0 | H44: =H43/H31 -> 0 | J44: =J43/J31 -> 0 | K44: =K43/K31 -> 0 | L44: =L43/L31 -> 0 | M44: =M43/M31 -> 0 | N44: =N43/N31 -> 0 | P44: =P43/P31 -> 0 | Q44: =Q43/Q31 -> 0 | R44: =R43/R31 -> 0 | S44: =S43/S31 -> 0 | T44: =T43/T31 -> 0 | V44: =V43/V31 -> 0 | W44: =W43/W31 -> 0 | X44: 0 | Y44: 0 | AB44: 0 | AC44: 0 | AD44: 0 | AE44: 0 | AH44: 0 | AJ44: 0 | AL44: 0
B46: R&D (Research & Development) | D46: =IS!P29 -> 0 | E46: =IS!Q29 -> 0 | F46: =IS!R29 -> 0 | G46: =IS!S29 -> 0 | H46: =IS!T29 -> 0 | J46: =IS!V29 -> 0 | K46: =IS!W29 -> 0 | L46: =IS!X29 -> 0 | M46: =IS!Y29 -> 0 | N46: =IS!Z29 -> 0 | P46: =IS!AB29 -> 0 | Q46: =IS!AC29 -> 0 | R46: =IS!AD29 -> 0 | S46: =IS!AE29 -> 0 | T46: =IS!AF29 -> 0 | V46: =IS!AH29 -> 0 | W46: =IS!AI29 -> 0 | X46: =X47*X40 -> 0 | Y46: =Y47*Y40 -> 0 | Z46: =SUM(V46:Y46) -> 0 | AB46: =AB47*AB40 -> 0 | AC46: =AC47*AC40 -> 0 | AD46: =AD47*AD40 -> 0 | AE46: =AE47*AE40 -> 0 | AF46: =SUM(AB46:AE46) -> 0 | AH46: =AH47*AH40 -> 0 | AJ46: =AJ47*AJ40 -> 0 | AL46: =AL47*AL40 -> 0
B47: % of gross profit | D47: =D46/D40 -> 0 | E47: =E46/E40 -> 0 | F47: =F46/F40 -> 0 | G47: =G46/G40 -> 0 | H47: =H46/H40 -> 0 | J47: =J46/J40 -> 0 | K47: =K46/K40 -> 0 | L47: =L46/L40 -> 0 | M47: =M46/M40 -> 0 | N47: =N46/N40 -> 0 | P47: =P46/P40 -> 0 | Q47: =Q46/Q40 -> 0 | R47: =R46/R40 -> 0 | S47: =S46/S40 -> 0 | T47: =T46/T40 -> 0 | V47: =V46/V40 -> 0 | W47: =W46/W40 -> 0 | X47: 0 | Y47: 0 | Z47: =Z46/Z$40 -> 0 | AB47: 0 | AC47: 0 | AD47: 0 | AE47: 0 | AF47: 0 | AH47: 0 | AJ47: 0 | AL47: 0
B49: D&A (Depreciation & Amortization) | D49: =IS!P28 -> 555 | E49: =IS!Q28 -> 559 | F49: =IS!R28 -> 563 | G49: =IS!S28 -> 569 | H49: =IS!T28 -> 2246 | J49: =IS!V28 -> 572 | K49: =IS!W28 -> 577 | L49: =IS!X28 -> 580 | M49: =IS!Y28 -> 589 | N49: =IS!Z28 -> 2318 | P49: =IS!AB28 -> 594 | Q49: =IS!AC28 -> 596 | R49: =IS!AD28 -> 602 | S49: =IS!AE28 -> 606 | T49: =IS!AF28 -> 2398 | V49: =IS!AH28 -> 610 | W49: =IS!AI28 -> 613 | X49: =X52+X55 -> 0 | Y49: =Y52+Y55 -> 0 | Z49: =Z52 -> 2385.6 | AB49: =AB52+AB55 -> 0 | AC49: =AC52+AC55 -> 0 | AD49: =AD52+AD55 -> 0 | AE49: =AE52+AE55 -> 0 | AF49: =AF52 -> 2425.856 | AH49: =AH52+AH55 -> 2476.8218 | AJ49: =AJ52+AJ55 -> 2527.9844 | AL49: =AL52+AL55 -> 2559.6341
B50: % of net pp&e and intangibles excl. Goodwill | D50: =D49/(D79+D82) -> 0.0097726752 | E50: =E49/(E79+E82) -> 0.0098034058 | F50: =F49/(F79+F82) -> 0.0098097296 | G50: =G49/(G79+G82) -> 0.009859643 | H50: =H49/(H79+H82) -> 0.038918732 | J50: =J49/(J79+J82) -> 0.0098664919 | K50: =K49/(K79+K82) -> 0.0098984423 | L50: =L49/(L79+L82) -> 0.0098841172 | M50: =M49/(M79+M82) -> 0.0099761183 | N50: =N49/(N79+N82) -> 0.039260853 | P50: =P49/(P79+P82) -> 0.010060464 | Q50: =Q49/(Q79+Q82) -> 0.010063998 | R50: =R49/(R79+R82) -> 0.010137923 | S50: =S49/(S79+S82) -> 0.010160966 | T50: =T49/(T79+T82) -> 0.040207914 | V50: =V49/(V79+V82) -> 0.010191806 | W50: =W49/(W79+W82) -> 0.010181033 | X50: =X49/( X79+X82) -> 0 | Y50: =Y49/( Y79+Y82) -> 0 | Z50: 0.04 | AB50: =AB49/( AB79+AB82) -> 0 | AC50: =AC49/( AC79+AC82) -> 0 | AD50: =AD49/( AD79+AD82) -> 0 | AE50: =AE49/( AE79+AE82) -> 0 | AF50: 0.04 | AH50: 0.04 | AJ50: 0.04 | AL50: 0.04
B52: Depreciation | D52: =IS!P64 -> 0 | E52: =IS!Q64 -> 0 | F52: =IS!R64 -> 0 | G52: =IS!S64 -> 0 | H52: =IS!T64 -> 0 | J52: =IS!V64 -> 0 | K52: =IS!W64 -> 0 | L52: =IS!X64 -> 0 | M52: =IS!Y64 -> 0 | N52: =IS!Z64 -> 0 | P52: =IS!AB64 -> 0 | Q52: =IS!AC64 -> 0 | R52: =IS!AD64 -> 0 | S52: =IS!AE64 -> 0 | T52: =IS!AF64 -> 0 | V52: =IS!AH64 -> 0 | W52: =IS!AI64 -> 0 | X52: =X53*W79 -> 0 | Y52: =Y53*X79 -> 0 | Z52: =Z53*T79 -> 2385.6 | AB52: =AB53*Y79 -> 0 | AC52: =AC53*AB79 -> 0 | AD52: =AD53*AC79 -> 0 | AE52: =AE53*AD79 -> 0 | AF52: =AF53*Z79 -> 2425.856 | AH52: =AH53*AF79 -> 2476.8218 | AJ52: =AJ53*AH79 -> 2527.9844 | AL52: =AL53*AJ79 -> 2559.6341
B53: % of net pp&e | D53: =D52/D79 -> 0 | E53: =E52/E79 -> 0 | F53: =F52/F79 -> 0 | G53: =G52/G79 -> 0 | H53: =H52/H79 -> 0 | J53: =J52/J79 -> 0 | K53: =K52/K79 -> 0 | L53: =L52/L79 -> 0 | M53: =M52/M79 -> 0 | N53: =N52/N79 -> 0 | P53: =P52/P79 -> 0 | Q53: =Q52/Q79 -> 0 | R53: =R52/R79 -> 0 | S53: =S52/S79 -> 0 | T53: =T52/T79 -> 0 | V53: =V52/V79 -> 0 | W53: =W52/W79 -> 0 | Z53: 0.04 | AF53: 0.04 | AH53: 0.04 | AJ53: 0.04 | AL53: 0.04
B55: Amortization | D55: =IS!P65 -> 0 | E55: =IS!Q65 -> 0 | F55: =IS!R65 -> 0 | G55: =IS!S65 -> 0 | H55: =IS!T65 -> 0 | J55: =IS!V65 -> 0 | K55: =IS!W65 -> 0 | L55: =IS!X65 -> 0 | M55: =IS!Y65 -> 0 | N55: =IS!Z65 -> 0 | P55: =IS!AB65 -> 0 | Q55: =IS!AC65 -> 0 | R55: =IS!AD65 -> 0 | S55: =IS!AE65 -> 0 | T55: =IS!AF65 -> 0 | V55: =IS!AH65 -> 0 | W55: =IS!AI65 -> 0 | X55: =X56*W82 -> 0 | Y55: =Y56*X82 -> 0 | Z55: =SUM(V55:Y55) -> 0 | AB55: =AB56*Y82 -> 0 | AC55: =AC56*AB82 -> 0 | AD55: =AD56*AC82 -> 0 | AE55: =AE56*AD82 -> 0 | AF55: =SUM(AB55:AE55) -> 0 | AH55: =AH56*AF82 -> 0 | AJ55: =AJ56*AH82 -> 0 | AL55: =AL56*AJ82 -> 0
B56: % of intangibles excl. goodwill | D56: =D55/D82 -> #DIV/0! | E56: =E55/E82 -> #DIV/0! | F56: =F55/F82 -> #DIV/0! | G56: =G55/G82 -> #DIV/0! | H56: =H55/H82 -> #DIV/0! | J56: =J55/J82 -> #DIV/0! | K56: =K55/K82 -> #DIV/0! | L56: =L55/L82 -> #DIV/0! | M56: =M55/M82 -> #DIV/0! | N56: =N55/N82 -> #DIV/0! | P56: =P55/P82 -> #DIV/0! | Q56: =Q55/Q82 -> #DIV/0! | R56: =R55/R82 -> #DIV/0! | S56: =S55/S82 -> #DIV/0! | T56: =T55/T82 -> #DIV/0! | V56: =V55/V82 -> #DIV/0! | W56: =W55/W82 -> #DIV/0! | X56: 0 | Y56: 0 | Z56: =Z55/Z82 -> 0 | AB56: 0 | AC56: 0 | AD56: 0 | AE56: 0 | AF56: =AF55/AF82 -> 0 | AH56: 0 | AJ56: 0 | AL56: 0
B58: Other Operating (Income) Expenses | D58: =IS!P30+IS!P32 -> 2928 | E58: =IS!Q30+IS!Q32 -> 3215 | F58: =IS!R30+IS!R32 -> 3256 | G58: =IS!S30+IS!S32 -> 3221 | H58: =IS!T30+IS!T32 -> 12620 | J58: =IS!V30+IS!V32 -> 3190 | K58: =IS!W30+IS!W32 -> 3182 | L58: =IS!X30+IS!X32 -> 3184 | M58: =IS!Y30+IS!Y32 -> 3163 | N58: =IS!Z30+IS!Z32 -> 12719 | P58: =IS!AB30+IS!AB32 -> 3065 | Q58: =IS!AC30+IS!AC32 -> 3011 | R58: =IS!AD30+IS!AD32 -> 3073 | S58: =IS!AE30+IS!AE32 -> 2990 | T58: =IS!AF30+IS!AF32 -> 12139 | V58: =IS!AH30+IS!AH32 -> 3046 | W58: =IS!AI30+IS!AI32 -> 3016 | X58: =X59*X$31 -> 0 | Y58: =Y59*Y$31 -> 0 | Z58: =Anexo_projections!BM24 -> 12184.347 | AB58: =AB59*AB$31 -> 0 | AC58: =AC59*AC$31 -> 0 | AD58: =AD59*AD$31 -> 0 | AE58: =AE59*AE$31 -> 0 | AF58: =Anexo_projections!BS24 -> 12568.158 | AH58: =Anexo_projections!BU24 -> 12468.128 | AJ58: =Anexo_projections!BW24 -> 12583.27 | AL58: =Anexo_projections!BY24 -> 12521.924
B59: % of sales | D59: =D58/D31 -> 0.4996587 | E59: =E58/E31 -> 0.51284096 | F59: =F58/F31 -> 0.49588791 | G59: =G58/G31 -> 0.52119741 | H59: =H58/H31 -> 0.50733668 | J59: =J58/J31 -> 0.52675033 | K59: =K58/K31 -> 0.53362401 | L59: =L58/L31 -> 0.53593671 | M59: =M58/M31 -> 0.5135574 | N59: =N58/N31 -> 0.52734359 | P59: =P58/P31 -> 0.50820759 | Q59: =Q58/Q31 -> 0.50124854 | R59: =R58/R31 -> 0.50451486 | S59: =S58/S31 -> 0.48848227 | T59: =T58/T31 -> 0.50057732 | V59: =V58/V31 -> 0.5053924 | W59: =W58/W31 -> 0.49008775 | Z59: =Z58/Z31 -> 0.47817622 | AF59: =AF58/AF31 -> 0.47990482 | AH59: =AH58/AH31 -> 0.46474702 | AJ59: =AJ58/AJ31 -> 0.45492298 | AL59: =AL58/AL31 -> 0.44193737
B61: EBIT (Operating Income) | D61: =IS!P33 -> 2377 | E61: =IS!Q33 -> 2495 | F61: =IS!R33 -> 2747 | G61: =IS!S33 -> 2390 | H61: =IS!T33 -> 10009 | J61: =IS!V33 -> 2294 | K61: =IS!W33 -> 2204 | L61: =IS!X33 -> 2177 | M61: =IS!Y33 -> 2407 | N61: =IS!Z33 -> 9082 | P61: =IS!AB33 -> 2372 | Q61: =IS!AC33 -> 2400 | R61: =IS!AD33 -> 2416 | S61: =IS!AE33 -> 2525 | T61: =IS!AF33 -> 9713 | V61: =IS!AH33 -> 2371 | W61: =IS!AI33 -> 2525 | X61: =X40-X43-X46-X49-X58 -> 0 | Y61: =Y40-Y43-Y46-Y49-Y58 -> 0 | Z61: =Z40-Z43-Z46-Z49-Z58 -> 10910.924 | AB61: =AB40-AB43-AB46-AB49-AB58 -> 0 | AC61: =AC40-AC43-AC46-AC49-AC58 -> 0 | AD61: =AD40-AD43-AD46-AD49-AD58 -> 0 | AE61: =AE40-AE43-AE46-AE49-AE58 -> 0 | AF61: =AF40-AF43-AF46-AF49-AF58 -> 11194.842 | AH61: =AH40-AH43-AH46-AH49-AH58 -> 11882.824 | AJ61: =AJ40-AJ43-AJ46-AJ49-AJ58 -> 12548.966 | AL61: =AL40-AL43-AL46-AL49-AL58 -> 13252.602
B62: % of sales | D62: =D61/D31 -> 0.4056314 | E62: =E61/E31 -> 0.39799011 | F62: =F61/F31 -> 0.41836735 | G62: =G61/G31 -> 0.38673139 | H62: =H61/H31 -> 0.40237186 | J62: =J61/J31 -> 0.37879789 | K62: =K61/K31 -> 0.36961261 | L62: =L61/L31 -> 0.36643663 | M62: =M61/M31 -> 0.3908102 | N62: =N61/N31 -> 0.37654961 | P62: =P61/P31 -> 0.39330128 | Q62: =Q61/Q31 -> 0.39953388 | R62: =R61/R31 -> 0.3966508 | S62: =S61/S31 -> 0.4125143 | T62: =T61/T31 -> 0.40053608 | V62: =V61/V31 -> 0.39339638 | W62: =W61/W31 -> 0.41030224 | X62: =X61/X$31 -> #DIV/0! | Y62: =Y61/Y$31 -> #DIV/0! | Z62: =Z61/Z$31 -> 0.4282006 | AB62: =AB61/AB$31 -> #DIV/0! | AC62: =AC61/AC$31 -> #DIV/0! | AD62: =AD61/AD$31 -> #DIV/0! | AE62: =AE61/AE$31 -> #DIV/0! | AF62: =AF61/AF$31 -> 0.42746586 | AH62: =AH61/AH$31 -> 0.44292993 | AJ62: =AJ61/AJ$31 -> 0.4536828 | AL62: =AL61/AL$31 -> 0.46772524
B64: Basic Weighted Average Shares | D64: =IS!P59 -> 632.2 | E64: =IS!Q59 -> 625.6 | F64: =IS!R59 -> 620.4 | G64: =IS!S59 -> 612.7 | H64: =IS!T59 -> 622.7 | J64: =IS!V59 -> 610.6 | K64: =IS!W59 -> 608.7 | L64: =IS!X59 -> 608.7 | M64: =IS!Y59 -> 608.9 | N64: =IS!Z59 -> 609.2 | P64: =IS!AB59 -> 609.2 | Q64: =IS!AC59 -> 609.4 | R64: =IS!AD59 -> 607.6 | S64: =IS!AE59 -> 604.2 | T64: =IS!AF59 -> 607.6 | V64: =IS!AH59 -> 601 | W64: =IS!AI59 -> 594.1 | X64: =W64+X101 -> 594.1 | Y64: =X64+Y101 -> 594.1 | Z64: =AVERAGE(V64:Y64) -> 595.825 | AB64: =Y64+AB101 -> 594.1 | AC64: =AB64+AC101 -> 594.1 | AD64: =AC64+AD101 -> 594.1 | AE64: =AD64+AE101 -> 594.1 | AF64: =AVERAGE(AB64:AE64) -> 594.1 | AH64: =AE64+AH101 -> 594.1 | AJ64: =AF64+AJ101 -> 594.1 | AL64: =AH64+AL101 -> 594.1
B65: Diluted Weighted Average Shares | D65: =IS!P60 -> 633.6 | E65: =IS!Q60 -> 626.8 | F65: =IS!R60 -> 621.5 | G65: =IS!S60 -> 613.7 | H65: =IS!T60 -> 624 | J65: =IS!V60 -> 611.5 | K65: =IS!W60 -> 609.5 | L65: =IS!X60 -> 609.8 | M65: =IS!Y60 -> 609.9 | N65: =IS!Z60 -> 610.2 | P65: =IS!AB60 -> 610.2 | Q65: =IS!AC60 -> 610.3 | R65: =IS!AD60 -> 608.6 | S65: =IS!AE60 -> 605.2 | T65: =IS!AF60 -> 608.6 | V65: =IS!AH60 -> 601.9 | W65: =IS!AI60 -> 594.8 | X65: =W65 -> 594.8 | Y65: =X65 -> 594.8 | Z65: =AVERAGE(V65:Y65) -> 596.575 | AB65: =Y65 -> 594.8 | AC65: =AB65 -> 594.8 | AD65: =AC65 -> 594.8 | AE65: =AD65 -> 594.8 | AF65: =AVERAGE(AB65:AE65) -> 594.8 | AH65: =AF65 -> 594.8 | AJ65: =AH65 -> 594.8 | AL65: =AJ65 -> 594.8
B67: Balance Sheet | D67: Q1 22 | E67: Q2 22 | F67: Q3 22 | G67: Q4 22 | H67: FY 22 | J67: Q1 23 | K67: Q2 23 | L67: Q3 23 | M67: Q4 23 | N67: FY 23 | P67: Q1 24 | Q67: Q2 24 | R67: Q3 24 | S67: Q4 24 | T67: FY 24 | V67: Q1 25 | W67: Q2 25 | X67: Q3 25 | Y67: Q4 25 | Z67: FY 25 | AB67: Q1 26 | AC67: Q2 26 | AD67: Q3 26 | AE67: Q4 26 | AF67: FY 26 | AH67: FY 27 | AJ67: FY 28 | AL67: FY 29
B70: Accounts Receivable | D70: =BS!P18 -> 1958 | E70: =BS!Q18 -> 2052 | F70: =BS!R18 -> 2052 | G70: =BS!S18 -> 1891 | H70: =BS!T18 -> 1891 | J70: =BS!V18 -> 1955 | K70: =BS!W18 -> 1826 | L70: =BS!X18 -> 1934 | M70: =BS!Y18 -> 2073 | N70: =BS!Z18 -> 2073 | P70: =BS!AB18 -> 2162 | Q70: =BS!AC18 -> 2118 | R70: =BS!AD18 -> 2036 | S70: =BS!AE18 -> 1894 | T70: =BS!AF18 -> 1894 | V70: =BS!AH18 -> 1965 | W70: =BS!AI18 -> 1915 | X70: =X31*X71/92 -> 0 | Y70: =Y31*Y71/92 -> 0 | Z70: =Z31*Z71/365 -> 1954.697 | AB70: =AB31*AB71/90 -> 0 | AC70: =AC31*AC71/91 -> 0 | AD70: =AD31*AD71/92 -> 0 | AE70: =AE31*AE71/92 -> 0 | AF70: =AF31*AF71/365 -> 2009.0081 | AH70: =AH31*AH71/365 -> 2058.0209 | AJ70: =AJ31*AJ71/366 -> 2267.2312 | AL70: =AL31*AL71/365 -> 2173.5794
B71: days sales outstanding | D71: =D70/D31*90 -> 30.071672 | E71: =E70/E31*91 -> 29.786569 | F71: =F70/F31*92 -> 28.751751 | G71: =G70/G31*92 -> 28.150809 | H71: =H70/H31*365 -> 27.747337 | J71: =J70/J31*90 -> 29.053831 | K71: =K70/K31*91 -> 27.866175 | L71: =L70/L31*92 -> 29.949167 | M71: =M70/M31*92 -> 30.965416 | N71: =N70/N31*365 -> 31.371326 | P71: =P70/P31*90 -> 32.263306 | Q71: =Q70/Q31*91 -> 32.085567 | R71: =R70/R31*92 -> 30.752257 | S71: =S70/S31*92 -> 28.467244 | T71: =T70/T31*365 -> 28.507629 | V71: =V70/V31*90 -> 29.342957 | W71: =W70/W31*91 -> 28.317355 | Z71: 28 | AF71: 28 | AH71: 28 | AJ71: 30 | AL71: 28
B73: Inventory | D73: =BS!P19 -> 726 | E73: =BS!Q19 -> 790 | F73: =BS!R19 -> 794 | G73: =BS!S19 -> 741 | H73: =BS!T19 -> 741 | J73: =BS!V19 -> 728 | K73: =BS!W19 -> 742 | L73: =BS!X19 -> 770 | M73: =BS!Y19 -> 743 | N73: =BS!Z19 -> 743 | P73: =BS!AB19 -> 770 | Q73: =BS!AC19 -> 807 | R73: =BS!AD19 -> 775 | S73: =BS!AE19 -> 769 | T73: =BS!AF19 -> 769 | V73: =BS!AH19 -> 747 | W73: =BS!AI19 -> 774 | X73: =X74*X31 -> 0 | Y73: =Y74*Y31 -> 0 | Z73: =Z74*Z31 -> 815.38787 | AB73: =AB74*AB31 -> 0 | AC73: =AC74*AC31 -> 0 | AD73: =AD74*AD31 -> 0 | AE73: =AE74*AE31 -> 0 | AF73: =AF74*AF31 -> 838.04339 | AH73: =AH74*AH31 -> 858.48873 | AJ73: =AJ74*AJ31 -> 885.12706 | AL73: =AL74*AL31 -> 906.69314
B74: % of revenues | D74: =D73/D31 -> 0.12389078 | E74: =E73/E31 -> 0.12601691 | F74: =F73/F31 -> 0.12092598 | G74: =G73/G31 -> 0.11990291 | H74: =H73/H31 -> 0.029788945 | J74: =J73/J31 -> 0.12021136 | K74: =K73/K31 -> 0.12443401 | L74: =L73/L31 -> 0.12960781 | M74: =M73/M31 -> 0.12063647 | N74: =N73/N31 -> 0.030805589 | P74: =P73/P31 -> 0.12767369 | Q74: =Q73/Q31 -> 0.13434327 | R74: =R73/R31 -> 0.12723691 | S74: =S73/S31 -> 0.12563307 | T74: =T73/T31 -> 0.03171134 | V74: =V73/V31 -> 0.12394226 | W74: =W73/W31 -> 0.12577186 | Z74: 0.032 | AF74: 0.032 | AH74: 0.032 | AJ74: 0.032 | AL74: 0.032
B76: Prepaid expenses and Other Current Assets | D76: =BS!P20 -> 237 | E76: =BS!Q20 -> 300 | F76: =BS!R20 -> 246 | G76: =BS!S20 -> 301 | H76: =BS!T20 -> 301 | J76: =BS!V20 -> 296 | K76: =BS!W20 -> 354 | L76: =BS!X20 -> 343 | M76: =BS!Y20 -> 261 | N76: =BS!Z20 -> 261 | P76: =BS!AB20 -> 317 | Q76: =BS!AC20 -> 416 | R76: =BS!AD20 -> 371 | S76: =BS!AE20 -> 322 | T76: =BS!AF20 -> 322 | V76: =BS!AH20 -> 416 | W76: =BS!AI20 -> 434 | X76: =X77*X$31 -> 0 | Y76: =Y77*Y$31 -> 0 | Z76: =Z77*Z31 -> 331.25132 | AB76: =AB77*AB$31 -> 0 | AC76: =AC77*AC$31 -> 0 | AD76: =AD77*AD$31 -> 0 | AE76: =AE77*AE$31 -> 0 | AF76: =AF77*AF31 -> 314.26627 | AH76: =AH77*AH$31 -> 321.93328 | AJ76: =AJ77*AJ$31 -> 331.92265 | AL76: =AL77*AL$31 -> 340.00993
B77: % of sales | D77: =D76/D31 -> 0.040443686 | E77: =E76/E31 -> 0.047854522 | F77: =F76/F31 -> 0.037465733 | G77: =G76/G31 -> 0.048705502 | H77: =H76/H31 -> 0.012100503 | J77: =J76/J31 -> 0.048877147 | K77: =K76/K31 -> 0.059366091 | L77: =L76/L31 -> 0.057734388 | M77: =M76/M31 -> 0.042377009 | N77: =N76/N31 -> 0.010821344 | P77: =P76/P31 -> 0.052561764 | Q77: =Q76/Q31 -> 0.069252539 | R77: =R76/R31 -> 0.060909539 | S77: =S76/S31 -> 0.052605783 | T77: =T76/T31 -> 0.013278351 | V77: =V76/V31 -> 0.069022731 | W77: =W76/W31 -> 0.070523237 | Z77: 0.013 | AF77: 0.012 | AH77: 0.012 | AJ77: 0.012 | AL77: 0.012
B79: Net PP&E (Property, Plant and Equipment) | D79: =BS!P24 -> 56791 | E79: =BS!Q24 -> 57021 | F79: =BS!R24 -> 57392 | G79: =BS!S24 -> 57710 | H79: =BS!T24 -> 57710 | J79: =BS!V24 -> 57974 | K79: =BS!W24 -> 58292 | L79: =BS!X24 -> 58680 | M79: =BS!Y24 -> 59041 | N79: =BS!Z24 -> 59041 | P79: =BS!AB24 -> 59043 | Q79: =BS!AC24 -> 59221 | R79: =BS!AD24 -> 59381 | S79: =BS!AE24 -> 59640 | T79: =BS!AF24 -> 59640 | V79: =BS!AH24 -> 59852 | W79: =BS!AI24 -> 60210 | X79: =W79-X80*X106-X109-X52-X37 -> 60210 | Y79: =X79-Y80*Y106-Y109-Y52-Y37 -> 60210 | Z79: =T79-Z80*Z106-Z109-Z49-Z37 -> 60646.4 | AB79: =Y79-AB80*AB106-AB109-AB52-AB37 -> 60210 | AC79: =AB79-AC80*AC106-AC109-AC52-AC37 -> 60210 | AD79: =AC79-AD80*AD106-AD109-AD52-AD37 -> 60210 | AE79: =AD79-AE80*AE106-AE109-AE52-AE37 -> 60210 | AF79: =Z79-AF80*AF106-AF109-AF49 -> 61920.544 | AH79: =AF79-AH80*AH106-AH109-AH52-AH37 -> 63199.61 | AJ79: =AH79-AJ80*AJ106-AJ109-AJ52-AJ37 -> 63990.853 | AL79: =AJ79-AL80*AL106-AL109-AL49-AL37 -> 64264.634
B80: capex allocation rate | Z80: 1 | AF80: 1 | AH80: 1 | AJ80: 1 | AL80: 1
B82: Intangibles | D82: =IF($B$82="Intangibles excl. Goodwill",BS!P29,BS!P27) -> 0 | E82: =IF($B$82="Intangibles excl. Goodwill",BS!Q29,BS!Q27) -> 0 | F82: =IF($B$82="Intangibles excl. Goodwill",BS!R29,BS!R27) -> 0 | G82: =IF($B$82="Intangibles excl. Goodwill",BS!S29,BS!S27) -> 0 | H82: =IF($B$82="Intangibles excl. Goodwill",BS!T29,BS!T27) -> 0 | J82: =IF($B$82="Intangibles excl. Goodwill",BS!V29,BS!V27) -> 0 | K82: =IF($B$82="Intangibles excl. Goodwill",BS!W29,BS!W27) -> 0 | L82: =IF($B$82="Intangibles excl. Goodwill",BS!X29,BS!X27) -> 0 | M82: =IF($B$82="Intangibles excl. Goodwill",BS!Y29,BS!Y27) -> 0 | N82: =IF($B$82="Intangibles excl. Goodwill",BS!Z29,BS!Z27) -> 0 | P82: =IF($B$82="Intangibles excl. Goodwill",BS!AB29,BS!AB27) -> 0 | Q82: =IF($B$82="Intangibles excl. Goodwill",BS!AC29,BS!AC27) -> 0 | R82: =IF($B$82="Intangibles excl. Goodwill",BS!AD29,BS!AD27) -> 0 | S82: =IF($B$82="Intangibles excl. Goodwill",BS!AE29,BS!AE27) -> 0 | T82: =IF($B$82="Intangibles excl. Goodwill",BS!AF29,BS!AF27) -> 0 | V82: =IF($B$82="Intangibles excl. Goodwill",BS!AH29,BS!AH27) -> 0 | W82: =IF($B$82="Intangibles excl. Goodwill",BS!AI29,BS!AI27) -> 0 | X82: =W82-(1-X80)*X106-X55+X83*X46 -> 800 | Y82: =X82-(1-Y80)*Y106-Y55+Y83*Y46 -> 1550 | Z82: =Y82 -> 1550 | AB82: =Y82-(1-AB80)*AB106-AB55+AB83*AB46 -> 1550 | AC82: =AB82-(1-AC80)*AC106-AC55+AC83*AC46 -> 1550 | AD82: =AC82-(1-AD80)*AD106-AD55+AD83*AD46 -> 1550 | AE82: =AD82-(1-AE80)*AE106-AE55+AE83*AE46 -> 1550 | AF82: =AE82 -> 1550 | AH82: =AF82-(1-AH80)*AH106-AH55+AH83*AH46 -> 1550 | AJ82: =AH82-(1-AJ80)*AJ106-AJ55+AJ83*AJ46 -> 1550 | AL82: =AJ82-(1-AL80)*AL106-AL55+AL83*AL46 -> 1550
B83: r&d capitalization rate | D83: =IFERROR(BS!P57/FCFF!D82,"") | E83: =IFERROR(BS!Q57/FCFF!E82,"") | F83: =IFERROR(BS!R57/FCFF!F82,"") | G83: =IFERROR(BS!S57/FCFF!G82,"") | H83: =IFERROR(BS!T57/FCFF!H82,"") | J83: =IFERROR(BS!V57/FCFF!J82,"") | K83: =IFERROR(BS!W57/FCFF!K82,"") | L83: =IFERROR(BS!X57/FCFF!L82,"") | M83: =IFERROR(BS!Y57/FCFF!M82,"") | N83: =IFERROR(BS!Z57/FCFF!N82,"") | P83: =IFERROR(BS!AB57/FCFF!P82,"") | Q83: =IFERROR(BS!AC57/FCFF!Q82,"") | R83: =IFERROR(BS!AD57/FCFF!R82,"") | S83: =IFERROR(BS!AE57/FCFF!S82,"") | T83: =IFERROR(BS!AF57/FCFF!T82,"") | V83: =IFERROR(BS!AH57/FCFF!V82,"") | W83: =IFERROR(BS!AI57/FCFF!W82,"") | Z83: 0.025 | AF83: 0.025 | AH83: 0 | AJ83: 0 | AL83: 0
B85: Accounts Payable | D85: =BS!P37 -> 2936 | E85: =BS!Q37 -> 2637 | F85: =BS!R37 -> 3225 | G85: =BS!S37 -> 3080 | H85: =BS!T37 -> 3080 | J85: =BS!V37 -> 2854 | K85: =BS!W37 -> 2743 | L85: =BS!X37 -> 2856 | M85: =BS!Y37 -> 2868 | N85: =BS!Z37 -> 2868 | P85: =BS!AB37 -> 2995 | Q85: =BS!AC37 -> 2794 | R85: =BS!AD37 -> 2913 | S85: =BS!AE37 -> 2870 | T85: =BS!AF37 -> 2870 | V85: =BS!AH37 -> 3085 | W85: =BS!AI37 -> 3134 | X85: =X31*X86 -> 0 | Y85: =Y31*Y86 -> 0 | Z85: =Z86*Z58 -> 2680.5563 | AB85: =AB31*AB86 -> 0 | AC85: =AC31*AC86 -> 0 | AD85: =AD31*AD86 -> 0 | AE85: =AE31*AE86 -> 0 | AF85: =AF86*AF58 -> 2764.9948 | AH85: {=AH86*AH58:AI58} -> 2742.9881 | AI85: 0 | AJ85: {=AJ86*AJ58:AK58} -> 2768.3194 | AK85: 0 | AL85: {=AL86*AL58:AM58} -> 2754.8234 | AM85: 0
B86: % of Opex | D86: =D85/D58 -> 1.0027322 | E86: =E85/E58 -> 0.82021773 | F86: =F85/F58 -> 0.99047912 | G86: =G85/G58 -> 0.95622477 | H86: =H85/H58 -> 0.24405705 | J86: =J85/J58 -> 0.89467085 | K86: =K85/K58 -> 0.86203646 | L86: =L85/L58 -> 0.89698492 | M86: =M85/M58 -> 0.90673411 | N86: =N85/N58 -> 0.22548943 | P86: =P85/P58 -> 0.9771615 | Q86: =Q85/Q58 -> 0.92793092 | R86: =R85/R58 -> 0.94793362 | S86: =S85/S58 -> 0.95986622 | T86: =T85/T58 -> 0.23642804 | V86: =V85/V58 -> 1.0128037 | W86: =W85/W58 -> 1.0391247 | Z86: 0.22 | AF86: 0.22 | AH86: 0.22 | AJ86: 0.22 | AK86: 2 | AL86: 0.22
B88: Accrued Expenses and Other Current Liabilities | D88: =BS!P40 -> 662 | E88: =BS!Q40 -> 717 | F88: =BS!R40 -> 483 | G88: =BS!S40 -> 431 | H88: =BS!T40 -> 431 | J88: =BS!V40 -> 419 | K88: =BS!W40 -> 415 | L88: =BS!X40 -> 362 | M88: =BS!Y40 -> 460 | N88: =BS!Z40 -> 460 | P88: =BS!AB40 -> 484 | Q88: =BS!AC40 -> 449 | R88: =BS!AD40 -> 452 | S88: =BS!AE40 -> 613 | T88: =BS!AF40 -> 613 | V88: =BS!AH40 -> 606 | W88: =BS!AI40 -> 484 | X88: =X89*X31 -> 0 | Y88: =Y89*Y31 -> 0 | Z88: =Z89*Z31 -> 637.02177 | AB88: =AB89*AB31 -> 0 | AC88: =AC89*AC31 -> 0 | AD88: =AD89*AD31 -> 0 | AE88: =AE89*AE31 -> 0 | AF88: =AF89*AF31 -> 523.77712 | AH88: =AH89*AH31 -> 536.55546 | AJ88: =AJ89*AJ31 -> 553.20441 | AL88: =AL89*AL31 -> 566.68321
B89: % of sales | D89: =D88/D31 -> 0.11296928 | E89: =E88/E31 -> 0.11437231 | F89: =F88/F31 -> 0.073560768 | G89: =G88/G31 -> 0.0697411 | H89: =H88/H31 -> 0.017326633 | J89: =J88/J31 -> 0.069187583 | K89: =K88/K31 -> 0.069595841 | L89: =L88/L31 -> 0.060932503 | M89: =M88/M31 -> 0.074687449 | N89: =N88/N31 -> 0.019072101 | P89: =P88/P31 -> 0.080252031 | Q89: =Q88/Q31 -> 0.07474613 | R89: =R88/R31 -> 0.074207848 | S89: =S88/S31 -> 0.10014703 | T89: =T88/T31 -> 0.025278351 | V89: =V88/V31 -> 0.10054754 | W89: =W88/W31 -> 0.078648034 | Z89: 0.025 | AF89: 0.02 | AH89: 0.02 | AJ89: 0.02 | AL89: 0.02
B91: Cash Flow Statement | D91: Q1 22 | E91: Q2 22 | F91: Q3 22 | G91: Q4 22 | H91: FY 22 | J91: Q1 23 | K91: Q2 23 | L91: Q3 23 | M91: Q4 23 | N91: FY 23 | P91: Q1 24 | Q91: Q2 24 | R91: Q3 24 | S91: Q4 24 | T91: FY 24 | V91: Q1 25 | W91: Q2 25 | X91: Q3 25 | Y91: Q4 25 | Z91: FY 25 | AB91: Q1 26 | AC91: Q2 26 | AD91: Q3 26 | AE91: Q4 26 | AF91: FY 26 | AH91: FY 27 | AJ91: FY 28 | AL91: FY 29
B94: D&A (Depreciation & Amortization) | D94: =CF!P17 -> 555 | E94: =CF!Q17 -> 559 | F94: =CF!R17 -> 563 | G94: =CF!S17 -> 569 | H94: =CF!T17 -> 2246 | J94: =CF!V17 -> 572 | K94: =CF!W17 -> 577 | L94: =CF!X17 -> 580 | M94: =CF!Y17 -> 589 | N94: =CF!Z17 -> 2318 | P94: =CF!AB17 -> 594 | Q94: =CF!AC17 -> 596 | R94: =CF!AD17 -> 602 | S94: =CF!AE17 -> 606 | T94: =CF!AF17 -> 2398 | V94: =CF!AH17 -> 610 | W94: =CF!AI17 -> 613 | X94: =X37+X49 -> 0 | Y94: =Y37+Y49 -> 0 | Z94: =Z49 -> 2385.6 | AB94: =AB37+AB49 -> 0 | AC94: =AC37+AC49 -> 0 | AD94: =AD37+AD49 -> 0 | AE94: =AE37+AE49 -> 0 | AF94: =AF49 -> 2425.856 | AH94: =AH37+AH49 -> 2476.8218 | AJ94: =AJ37+AJ49 -> 2527.9844 | AL94: =AL37+AL49 -> 2559.6341
B95: % of net pp&e and intangibles excl. Goodwill | D95: =D94/(D82+D79) -> 0.0097726752 | E95: =E94/(E82+E79) -> 0.0098034058 | F95: =F94/(F82+F79) -> 0.0098097296 | G95: =G94/(G82+G79) -> 0.009859643 | H95: =H94/(H82+H79) -> 0.038918732 | J95: =J94/(J82+J79) -> 0.0098664919 | K95: =K94/(K82+K79) -> 0.0098984423 | L95: =L94/(L82+L79) -> 0.0098841172 | M95: =M94/(M82+M79) -> 0.0099761183 | N95: =N94/(N82+N79) -> 0.039260853 | P95: =P94/(P82+P79) -> 0.010060464 | Q95: =Q94/(Q82+Q79) -> 0.010063998 | R95: =R94/(R82+R79) -> 0.010137923 | S95: =S94/(S82+S79) -> 0.010160966 | T95: =T94/(T82+T79) -> 0.040207914 | V95: =V94/(V82+V79) -> 0.010191806 | W95: =W94/(W82+W79) -> 0.010181033 | X95: =X94/(X79+X82) -> 0 | Y95: =Y94/(Y79+Y82) -> 0 | Z95: =Z94/(Z79+Z82) -> 0.038355918 | AB95: =AB94/(AB79+AB82) -> 0 | AC95: =AC94/(AC79+AC82) -> 0 | AD95: =AD94/(AD79+AD82) -> 0 | AE95: =AE94/(AE79+AE82) -> 0 | AF95: =AF94/(AF79+AF82) -> 0.038220186 | AH95: =AH94/(AH79+AH82) -> 0.038252304 | AJ95: =AJ94/(AJ79+AJ82) -> 0.038571125 | AL95: =AL94/(AL79+AL82) -> 0.038891564
B97: Stock-Based Compensation Expense | D97: =CF!P18 -> 0 | E97: =CF!Q18 -> 0 | F97: =CF!R18 -> 0 | G97: =CF!S18 -> 0 | H97: =CF!T18 -> 0 | J97: =CF!V18 -> 0 | K97: =CF!W18 -> 0 | L97: =CF!X18 -> 0 | M97: =CF!Y18 -> 0 | N97: =CF!Z18 -> 0 | P97: =CF!AB18 -> 0 | Q97: =CF!AC18 -> 0 | R97: =CF!AD18 -> 0 | S97: =CF!AE18 -> 0 | T97: =CF!AF18 -> 0 | V97: =CF!AH18 -> 0 | W97: =CF!AI18 -> 0 | X97: =X98*X43 -> 0 | Y97: =Y98*Y43 -> 0 | Z97: =SUM(V97:Y97) -> 0 | AB97: =AB98*AB43 -> 0 | AC97: =AC98*AC43 -> 0 | AD97: =AD98*AD43 -> 0 | AE97: =AE98*AE43 -> 0 | AF97: =SUM(AB97:AE97) -> 0 | AH97: =AH98*AH43 -> 0 | AJ97: =AJ98*AJ43 -> 0 | AL97: =AL98*AL43 -> 0
B98: % of sg&a | D98: - | E98: - | F98: - | G98: - | H98: - | J98: - | K98: - | L98: - | M98: - | N98: - | P98: - | Q98: - | R98: - | S98: - | T98: - | V98: - | W98: - | X98: 0 | Y98: 0 | Z98: 0 | AB98: 0 | AC98: 0 | AD98: 0 | AE98: 0 | AF98: 0 | AH98: 0 | AJ98: 0 | AL98: 0
B99: implied equity value (p/s multiple) | Z99: 5.2 | AF99: 5.1 | AH99: 5 | AJ99: 5 | AL99: 5
B100: implied share price (for dilution) | X100: 0 | Y100: 0 | Z100: 0 | AB100: 0 | AC100: 0 | AD100: 0 | AE100: 0 | AF100: 0 | AH100: 0 | AJ100: 0 | AL100: 0
B101: sbc dilution (shares issued) | X101: 0 | Y101: 0 | Z101: 0 | AB101: 0 | AC101: 0 | AD101: 0 | AE101: 0 | AF101: 0 | AH101: 0 | AJ101: 0 | AL101: 0
B103: Changes in Net Working Capital | D103: =SUM(CF!P21:P24) -> 34 | E103: =SUM(CF!Q21:Q24) -> -487 | F103: =SUM(CF!R21:R24) -> 399 | G103: =SUM(CF!S21:S24) -> 62 | H103: =SUM(CF!T21:T24) -> 8 | J103: =SUM(CF!V21:V24) -> -297 | K103: =SUM(CF!W21:W24) -> -103 | L103: =SUM(CF!X21:X24) -> -10 | M103: =SUM(CF!Y21:Y24) -> 107 | N103: =SUM(CF!Z21:Z24) -> -303 | P103: =SUM(CF!AB21:AB24) -> -56 | Q103: =SUM(CF!AC21:AC24) -> -390 | R103: =SUM(CF!AD21:AD24) -> 328 | S103: =SUM(CF!AE21:AE24) -> 304 | T103: =SUM(CF!AF21:AF24) -> 186 | V103: =SUM(CF!AH21:AH24) -> 3 | W103: =SUM(CF!AI21:AI24) -> -19 | X103: =-((X70+X73+X76-X85-X88)-(W70+W73+W76-W85-W88)) -> -495 | Y103: =-((Y70+Y73+Y76-Y85-Y88)-(X70+X73+X76-X85-X88)) -> 0 | Z103: =-((Z70+Z73+Z76-Z85-Z88)-(T70+T73+T76-T85-T88)) -> -281.7581 | AB103: =-((AB70+AB73+AB76-AB85-AB88)-(Y70+Y73+Y76-Y85-Y88)) -> 0 | AC103: =-((AC70+AC73+AC76-AC85-AC88)-(AB70+AB73+AB76-AB85-AB88)) -> 0 | AD103: =-((AD70+AD73+AD76-AD85-AD88)-(AC70+AC73+AC76-AC85-AC88)) -> 0 | AE103: =-((AE70+AE73+AE76-AE85-AE88)-(AD70+AD73+AD76-AD85-AD88)) -> 0 | AF103: =-((AF70+AF73+AF76-AF85-AF88)-(Z70+Z73+Z76-Z85-Z88)) -> -88.787788 | AH103: =-((AH70+AH73+AH76-AH85-AH88)-(AF70+AF73+AF76-AF85-AF88)) -> -86.353515 | AJ103: =-((AJ70+AJ73+AJ76-AJ85-AJ88)-(AH70+AH73+AH76-AH85-AH88)) -> -203.85769 | AL103: =-((AL70+AL73+AL76-AL85-AL88)-(AJ70+AJ73+AJ76-AJ85-AJ88)) -> 63.981191
B104: % of change in sales | D104: =D103/(D31-IS!M18) -> 0.26771654 | E104: =E103/(E31-D31) -> -1.190709 | F104: =F103/(F31-E31) -> 1.3434343 | G104: =G103/(G31-F31) -> -0.16062176 | H104: =H103/IS!N18 -> 0.00036690516 | J104: =J103/(J31-IS!S18) -> 2.3951613 | K104: =K103/(K31-J31) -> 1.1075269 | L104: =L103/(L31-K31) -> 0.45454545 | M104: =M103/(M31-L31) -> 0.49082569 | N104: =N103/IS!T18 -> -0.012180905 | P104: =P103/(P31-IS!Y18) -> 0.4375 | Q104: =Q103/(Q31-P31) -> 16.25 | R104: =R103/(R31-Q31) -> 3.9047619 | S104: =S103/(S31-R31) -> 10.133333 | T104: =T103/IS!Z18 -> 0.0077117625 | V104: =V103/(V31-IS!AE18) -> -0.031914894 | W104: =W103/(W31-V31) -> -0.1496063 | X104: =X103/(X31-W31) -> 0.080435489 | Y104: =Y103/(Y31-X31) -> #DIV/0! | Z104: =Z103/(Z31-T31) -> -0.22890953 | AB104: =AB103/(AB31-IS!AK18) -> #DIV/0! | AC104: =AC103/(AC31-AB31) -> #DIV/0! | AD104: =AD103/(AD31-AC31) -> #DIV/0! | AE104: =AE103/(AE31-AD31) -> #DIV/0! | AF104: =AF103/(AF31-Z31) -> -0.12540917 | AH104: =AH103/(AH31-AF31) -> -0.13515605 | AJ104: =AJ103/(AJ31-AH31) -> -0.24488949 | AL104: =AL103/(AL31-AJ31) -> 0.094936051
B106: Capital Expenditures | D106: =CF!P28 -> -848 | E106: =CF!Q28 -> -797 | F106: =CF!R28 -> -1045 | G106: =CF!S28 -> -930 | H106: =CF!T28 -> -3620 | J106: =CF!V28 -> -772 | K106: =CF!W28 -> -835 | L106: =CF!X28 -> -1020 | M106: =CF!Y28 -> -1024 | N106: =CF!Z28 -> -3606 | P106: =CF!AB28 -> -797 | Q106: =CF!AC28 -> -902 | R106: =CF!AD28 -> -831 | S106: =CF!AE28 -> -922 | T106: =CF!AF28 -> -3452 | V106: =CF!AH28 -> -906 | W106: =CF!AI28 -> -936 | X106: -800 | Y106: -750 | Z106: =SUM(V106:Y106) -> -3392 | AB106: =-AB$31*(AB107+Sensitivity!$U$38) -> 0 | AC106: =-AC$31*(AC107+Sensitivity!$U$38) -> 0 | AD106: =-AD$31*(AD107+Sensitivity!$U$38) -> 0 | AE106: =-AE$31*(AE107+Sensitivity!$U$38) -> 0 | AF106: -3700 | AH106: =-AH$31*(AH107+Sensitivity!$U$38) -> -3755.8882 | AJ106: =-AJ$31*(AJ107+Sensitivity!$U$38) -> -3319.2265 | AL106: =-AL$31*(AL107+Sensitivity!$U$38) -> -2833.416
B107: % of sales | D107: =-D106/D31 -> 0.1447099 | E107: =-E106/E31 -> 0.12713351 | F107: =-F106/F31 -> 0.15915321 | G107: =-G106/G31 -> 0.15048544 | H107: =-H106/H31 -> 0.14552764 | J107: =-J106/J31 -> 0.12747688 | K107: =-K106/K31 -> 0.14003019 | L107: =-L106/L31 -> 0.17168827 | M107: =-M106/M31 -> 0.16626076 | N107: =-N106/N31 -> 0.14950869 | P107: =-P106/P31 -> 0.13215056 | Q107: =-Q106/Q31 -> 0.15015815 | R107: =-R106/R31 -> 0.1364308 | S107: =-S106/S31 -> 0.15062898 | T107: =-T106/T31 -> 0.14235052 | V107: =-V106/V31 -> 0.15032354 | W107: =-W106/W31 -> 0.1520962 | Z107: =-Z106/Z$31 -> 0.13311947 | AF107: 0.14 | AH107: 0.14 | AJ107: 0.12 | AL107: 0.1
B109: Proceeds from Asset Disposals | D109: =CF!P29 -> 32 | E109: =CF!Q29 -> 88 | F109: =CF!R29 -> 52 | G109: =CF!S29 -> 22 | H109: =CF!T29 -> 194 | J109: =CF!V29 -> 12 | K109: =CF!W29 -> 33 | L109: =CF!X29 -> 0 | M109: =CF!Y29 -> 0 | N109: =CF!Z29 -> 0 | P109: =CF!AB29 -> 0 | Q109: =CF!AC29 -> 0 | R109: =CF!AD29 -> 0 | S109: =CF!AE29 -> 0 | T109: =CF!AF29 -> 0 | V109: =CF!AH29 -> 0 | W109: =CF!AI29 -> 0 | X109: =X110*X$106 -> 0 | Y109: =Y110*Y$106 -> 0 | Z109: =SUM(V109:Y109) -> 0 | AB109: =AB110*AB$106 -> 0 | AC109: =AC110*AC$106 -> 0 | AD109: =AD110*AD$106 -> 0 | AE109: =AE110*AE$106 -> 0 | AF109: =SUM(AB109:AE109) -> 0 | AH109: =AH110*AH$106 -> 0 | AJ109: =AJ110*AJ$106 -> 0 | AL109: =AL110*AL$106 -> 0
B110: % of capex | D110: =-D109/D106 -> 0.037735849 | E110: =-E109/E106 -> 0.11041405 | F110: =-F109/F106 -> 0.049760766 | G110: =-G109/G106 -> 0.023655914 | H110: =-H109/H106 -> 0.05359116 | J110: =-J109/J106 -> 0.015544041 | K110: =-K109/K106 -> 0.039520958 | L110: =-L109/L106 -> 0 | M110: =-M109/M106 -> 0 | N110: =-N109/N106 -> 0 | P110: =-P109/P106 -> 0 | Q110: =-Q109/Q106 -> 0 | R110: =-R109/R106 -> 0 | S110: =-S109/S106 -> 0 | T110: =-T109/T106 -> 0 | V110: =-V109/V106 -> 0 | W110: =-W109/W106 -> 0 | X110: 0 | Y110: 0 | Z110: 0 | AB110: 0 | AC110: 0 | AD110: 0 | AE110: 0 | AF110: 0 | AH110: 0 | AJ110: 0 | AL110: 0
B112: Dividends | D112: =CF!P39 -> -743 | E112: =CF!Q39 -> -813 | F112: =CF!R39 -> -806 | G112: =CF!S39 -> -797 | H112: =CF!T39 -> -3159 | J112: =CF!V39 -> -795 | K112: =CF!W39 -> -793 | L112: =CF!X39 -> -792 | M112: =CF!Y39 -> -793 | N112: =CF!Z39 -> -3173 | P112: =CF!AB39 -> -795 | Q112: =CF!AC39 -> -793 | R112: =CF!AD39 -> -815 | S112: =CF!AE39 -> -810 | T112: =CF!AF39 -> -3213 | V112: =CF!AH39 -> -804 | W112: =CF!AI39 -> -795 | X112: =-X113*X126 -> 0 | Y112: =-Y113*Y126 -> 0 | Z112: =-Z113*Z126 -> -3612.607 | AB112: =-AB113*AB126 -> 0 | AC112: =-AC113*AC126 -> 0 | AD112: =-AD113*AD126 -> 0 | AE112: =-AE113*AE126 -> 0 | AF112: =-AF113*AF126 -> -3706.6121 | AH112: =-AH113*AH126 -> -3934.4029 | AJ112: =-AJ113*AJ126 -> -4058.3357 | AL112: =-AL113*AL126 -> -4183.8464
B113: % of NOPAT | D113: =-D112/D126 -> 0.40596901 | E113: =-E112/E126 -> 0.41603297 | F113: =-F112/F126 -> 0.37857572 | G113: =-G112/G126 -> 0.44209319 | H113: =-H112/H126 -> 0.40926907 | J113: =-J112/J126 -> 0.45541316 | K113: =-K112/K126 -> 0.44900517 | L113: =-L112/L126 -> 0.46403981 | M113: =-M112/M126 -> 0.43555167 | N113: =-N112/N126 -> 0.45091438 | P113: =-P112/P126 -> 0.43707668 | Q113: =-Q112/Q126 -> 0.43133891 | R113: =-R112/R126 -> 0.44190609 | S113: =-S112/S126 -> 0.41528191 | T113: =-T112/T126 -> 0.43115466 | V113: =-V112/V126 -> 0.44357948 | W113: =-W112/W126 -> 0.38819376 | Z113: 0.43 | AF113: 0.43 | AH113: 0.43 | AJ113: 0.42 | AL113: 0.41
B115: Repurchase of Stock | D115: =CF!P40 -> -2743 | E115: =CF!Q40 -> -730 | F115: =CF!R40 -> -2024 | G115: =CF!S40 -> -785 | H115: =CF!T40 -> -6282 | J115: =CF!V40 -> -575 | K115: =CF!W40 -> -130 | L115: =CF!X40 -> 0 | M115: =CF!Y40 -> 0 | N115: =CF!Z40 -> -705 | P115: =CF!AB40 -> 0 | Q115: =CF!AC40 -> -100 | R115: =CF!AD40 -> -731 | S115: =CF!AE40 -> -674 | T115: =CF!AF40 -> -1505 | V115: =CF!AH40 -> -1420 | W115: =CF!AI40 -> -1259 | Z115: =SUM(V115:W115)-1800 -> -4479 | AF115: -4200 | AH115: -4250 | AJ115: 0 | AL115: 0
A117: x | B117: Free Cash Flow to Firm
D118: =D$8 -> 2022 | E118: =F118 -> 0 | F118: =F$8 -> 0 | G118: =F118 -> 0 | H118: =F118 -> 0 | J118: =J$8 -> 2023 | K118: =L118 -> 0 | L118: =L$8 -> 0 | M118: =L118 -> 0 | N118: =L118 -> 0 | P118: =P$8 -> 2024 | Q118: =R118 -> 0 | R118: =R$8 -> 0 | S118: =R118 -> 0 | T118: =R118 -> 0 | V118: =V$8 -> 2025 | W118: =X118 -> 0 | X118: =X$8 -> 0 | Y118: =X118 -> 0 | Z118: =X118 -> 0 | AB118: =AB$8 -> 2026 | AC118: =AD118 -> 0 | AD118: =AD$8 -> 0 | AE118: =AD118 -> 0 | AF118: =AD118 -> 0 | AH118: =AH$8 -> 2027 | AJ118: =AJ$8 -> 2028 | AL118: =AL$8 -> 2029
D119: Q1 | E119: Q2 | F119: Q3 | G119: Q4 | H119: FY | J119: Q1 | K119: Q2 | L119: Q3 | M119: Q4 | N119: FY | P119: Q1 | Q119: Q2 | R119: Q3 | S119: Q4 | T119: FY | V119: Q1 | W119: Q2 | X119: Q3 | Y119: Q4 | Z119: FY | AB119: Q1 | AC119: Q2 | AD119: Q3 | AE119: Q4 | AF119: FY | AH119: FY | AJ119: FY | AL119: FY
B122: EBIT (Operating Income) | D122: =D61 -> 2377 | E122: =E61 -> 2495 | F122: =F61 -> 2747 | G122: =G61 -> 2390 | H122: =H61 -> 10009 | J122: =J61 -> 2294 | K122: =K61 -> 2204 | L122: =L61 -> 2177 | M122: =M61 -> 2407 | N122: =N61 -> 9082 | P122: =P61 -> 2372 | Q122: =Q61 -> 2400 | R122: =R61 -> 2416 | S122: =S61 -> 2525 | T122: =T61 -> 9713 | V122: =V61 -> 2371 | W122: =W61 -> 2525 | X122: =X61 -> 0 | Y122: =Y61 -> 0 | Z122: =Z61 -> 10910.924 | AB122: =AB61 -> 0 | AC122: =AC61 -> 0 | AD122: =AD61 -> 0 | AE122: =AE61 -> 0 | AF122: =AF61 -> 11194.842 | AH122: =AH61 -> 11882.824 | AJ122: =AJ61 -> 12548.966 | AL122: =AL61 -> 13252.602
B124: Tax Rate | D124: =IS!P45/IS!P42 -> 0.23004251 | E124: =IS!Q45/IS!Q42 -> 0.21676471 | F124: =IS!R45/IS!R42 -> 0.22496088 | G124: =IS!S45/IS!S42 -> 0.24569567 | H124: =IS!T45/IS!T42 -> 0.22883021 | J124: =IS!V45/IS!V42 -> 0.23902894 | K124: =IS!W45/IS!W42 -> 0.19867211 | L124: =IS!X45/IS!X42 -> 0.21600821 | M124: =IS!Y45/IS!Y42 -> 0.24358974 | N124: =IS!Z45/IS!Z42 -> 0.2251913 | P124: =IS!AB45/IS!AB42 -> 0.23317757 | Q124: =IS!AC45/IS!AC42 -> 0.23397436 | R124: =IS!AD45/IS!AD42 -> 0.23663773 | S124: =IS!AE45/IS!AE42 -> 0.22753178 | T124: =IS!AF45/IS!AF42 -> 0.23277234 | V124: =IS!AH45/IS!AH42 -> 0.23554302 | W124: =IS!AI45/IS!AI42 -> 0.18893212 | Z124: 0.23 | AF124: 0.23 | AH124: 0.23 | AJ124: 0.23 | AL124: 0.23
B126: NOPAT (Net Operating Profit After Taxes) | D126: =D122*(1-D124) -> 1830.1889 | E126: =E122*(1-E124) -> 1954.1721 | F126: =F122*(1-F124) -> 2129.0325 | G126: =G122*(1-G124) -> 1802.7873 | H126: =H122*(1-H124) -> 7718.6385 | J126: =J122*(1-J124) -> 1745.6676 | K126: =K122*(1-K124) -> 1766.1267 | L126: =L122*(1-L124) -> 1706.7501 | M126: =M122*(1-M124) -> 1820.6795 | N126: =N122*(1-N124) -> 7036.8126 | P126: =P122*(1-P124) -> 1818.9028 | Q126: =Q122*(1-Q124) -> 1838.4615 | R126: =R122*(1-R124) -> 1844.2832 | S126: =S122*(1-S124) -> 1950.4822 | T126: =T122*(1-T124) -> 7452.0822 | V126: =V122*(1-V124) -> 1812.5275 | W126: =W122*(1-W124) -> 2047.9464 | X126: =X122*(1-X124) -> 0 | Y126: =Y122*(1-Y124) -> 0 | Z126: =Z122*(1-Z124) -> 8401.4117 | AB126: =AB122*(1-AB124) -> 0 | AC126: =AC122*(1-AC124) -> 0 | AD126: =AD122*(1-AD124) -> 0 | AE126: =AE122*(1-AE124) -> 0 | AF126: =AF122*(1-AF124) -> 8620.0282 | AH126: =AH122*(1-AH124) -> 9149.7741 | AJ126: =AJ122*(1-AJ124) -> 9662.704 | AL126: =AL122*(1-AL124) -> 10204.503
B128: D&A (Depreciation & Amortization) | D128: =D94 -> 555 | E128: =E94 -> 559 | F128: =F94 -> 563 | G128: =G94 -> 569 | H128: =H94 -> 2246 | J128: =J94 -> 572 | K128: =K94 -> 577 | L128: =L94 -> 580 | M128: =M94 -> 589 | N128: =N94 -> 2318 | P128: =P94 -> 594 | Q128: =Q94 -> 596 | R128: =R94 -> 602 | S128: =S94 -> 606 | T128: =T94 -> 2398 | V128: =V94 -> 610 | W128: =W94 -> 613 | X128: =X94 -> 0 | Y128: =Y94 -> 0 | Z128: =Z94 -> 2385.6 | AB128: =AB94 -> 0 | AC128: =AC94 -> 0 | AD128: =AD94 -> 0 | AE128: =AE94 -> 0 | AF128: =AF94 -> 2425.856 | AH128: =AH94 -> 2476.8218 | AJ128: =AJ94 -> 2527.9844 | AL128: =AL94 -> 2559.6341
B130: Stock-Based Compensation | D130: =D97 -> 0 | E130: =E97 -> 0 | F130: =F97 -> 0 | G130: =G97 -> 0 | H130: =H97 -> 0 | J130: =J97 -> 0 | K130: =K97 -> 0 | L130: =L97 -> 0 | M130: =M97 -> 0 | N130: =N97 -> 0 | P130: =P97 -> 0 | Q130: =Q97 -> 0 | R130: =R97 -> 0 | S130: =S97 -> 0 | T130: =T97 -> 0 | V130: =V97 -> 0 | W130: =W97 -> 0 | X130: =X97 -> 0 | Y130: =Y97 -> 0 | Z130: =Z97 -> 0 | AB130: =AB97 -> 0 | AC130: =AC97 -> 0 | AD130: =AD97 -> 0 | AE130: =AE97 -> 0 | AF130: =AF97 -> 0 | AH130: =AH97 -> 0 | AJ130: =AJ97 -> 0 | AL130: =AL97 -> 0
B132: Changes in Net Working Capital | D132: =D103 -> 34 | E132: =E103 -> -487 | F132: =F103 -> 399 | G132: =G103 -> 62 | H132: =H103 -> 8 | J132: =J103 -> -297 | K132: =K103 -> -103 | L132: =L103 -> -10 | M132: =M103 -> 107 | N132: =N103 -> -303 | P132: =P103 -> -56 | Q132: =Q103 -> -390 | R132: =R103 -> 328 | S132: =S103 -> 304 | T132: =T103 -> 186 | V132: =V103 -> 3 | W132: =W103 -> -19 | X132: =X103 -> -495 | Y132: =Y103 -> 0 | Z132: =Z103 -> -281.7581 | AB132: =AB103 -> 0 | AC132: =AC103 -> 0 | AD132: =AD103 -> 0 | AE132: =AE103 -> 0 | AF132: =AF103 -> -88.787788 | AH132: =AH103 -> -86.353515 | AJ132: =AJ103 -> -203.85769 | AL132: =AL103 -> 63.981191
B134: Net CapEx | D134: =D106+D109 -> -816 | E134: =E106+E109 -> -709 | F134: =F106+F109 -> -993 | G134: =G106+G109 -> -908 | H134: =H106+H109 -> -3426 | J134: =J106+J109 -> -760 | K134: =K106+K109 -> -802 | L134: =L106+L109 -> -1020 | M134: =M106+M109 -> -1024 | N134: =N106+N109 -> -3606 | P134: =P106+P109 -> -797 | Q134: =Q106+Q109 -> -902 | R134: =R106+R109 -> -831 | S134: =S106+S109 -> -922 | T134: =T106+T109 -> -3452 | V134: =V106+V109 -> -906 | W134: =W106+W109 -> -936 | X134: =X106+X109 -> -800 | Y134: =Y106+Y109 -> -750 | Z134: =Z106+Z109 -> -3392 | AB134: =AB106+AB109 -> 0 | AC134: =AC106+AC109 -> 0 | AD134: =AD106+AD109 -> 0 | AE134: =AE106+AE109 -> 0 | AF134: =AF106+AF109 -> -3700 | AH134: =AH106+AH109 -> -3755.8882 | AJ134: =AJ106+AJ109 -> -3319.2265 | AL134: =AL106+AL109 -> -2833.416
B136: FCFF (Free Cash Flow to Firm) | D136: =D126+D94+D97+D103+D134 -> 1603.1889 | E136: =E126+E94+E97+E103+E134 -> 1317.1721 | F136: =F126+F94+F97+F103+F134 -> 2098.0325 | G136: =G126+G94+G97+G103+G134 -> 1525.7873 | H136: =H126+H94+H97+H103+H134 -> 6546.6385 | J136: =J126+J94+J97+J103+J134 -> 1260.6676 | K136: =K126+K94+K97+K103+K134 -> 1438.1267 | L136: =L126+L94+L97+L103+L134 -> 1256.7501 | M136: =M126+M94+M97+M103+M134 -> 1492.6795 | N136: =N126+N94+N97+N103+N134 -> 5445.8126 | P136: =P126+P94+P97+P103+P134 -> 1559.9028 | Q136: =Q126+Q94+Q97+Q103+Q134 -> 1142.4615 | R136: =R126+R94+R97+R103+R134 -> 1943.2832 | S136: =S126+S94+S97+S103+S134 -> 1938.4822 | T136: =T126+T94+T97+T103+T134 -> 6584.0822 | V136: =V126+V94+V97+V103+V134 -> 1519.5275 | W136: =W126+W94+W97+W103+W134 -> 1705.9464 | X136: =X126+X128+X130+X132+X134 -> -1295 | Y136: =Y126+Y128+Y130+Y132+Y134 -> -750 | Z136: =Z126+Z128+Z130+Z132+Z134 -> 7113.2536 | AB136: =AB126+AB128+AB130+AB132+AB134 -> 0 | AC136: =AC126+AC128+AC130+AC132+AC134 -> 0 | AD136: =AD126+AD128+AD130+AD132+AD134 -> 0 | AE136: =AE126+AE128+AE130+AE132+AE134 -> 0 | AF136: =AF126+AF128+AF130+AF132+AF134 -> 7257.0964 | AH136: =AH126+AH128+AH130+AH132+AH134 -> 7784.3542 | AJ136: =AJ126+AJ128+AJ130+AJ132+AJ134 -> 8667.6042 | AL136: =AL126+AL128+AL130+AL132+AL134 -> 9994.7027 | AN136: =+(AL136/Z136)^0.2-1 -> 0.070385747
A138: x | B138: Valuation Summary
V139: =V$8 -> 2025 | W139: =X139 -> 0 | X139: =X$8 -> 0 | Y139: =X139 -> 0 | Z139: =X139 -> 0 | AB139: =AB$8 -> 2026 | AC139: =AD139 -> 0 | AD139: =AD$8 -> 0 | AE139: =AD139 -> 0 | AF139: =AD139 -> 0 | AH139: =AH$8 -> 2027 | AJ139: =AJ$8 -> 2028 | AL139: =AL$8 -> 2029
V140: Q1 | W140: Q2 | X140: Q3 | Y140: Q4 | Z140: FY | AB140: Q1 | AC140: Q2 | AD140: Q3 | AE140: Q4 | AF140: FY | AH140: FY | AJ140: FY | AL140: FY
B143: Discounted Cash Flows (DCF)
B146: Discount Period | Z146: =YEARFRAC(TODAY(),"2025-12-31") -> 0.19444444 | AF146: =Z146+1 -> 1.1944444 | AH146: =AF146+1 -> 2.1944444 | AJ146: =AH146+1 -> 3.1944444 | AL146: =AJ146+1 -> 4.1944444
B147: Mid-Quarter/Year Convention Discount Period | Z147: =W146+(Z146-W146)/2 -> 0.097222222 | AF147: =+Z147+1 -> 1.0972222 | AH147: =+AF147+1 -> 2.0972222 | AJ147: =+AH147+1 -> 3.0972222 | AL147: =+AJ147+1 -> 4.0972222
B149: Rolling WACC (Weighted Average Cost of Capital) | Z149: =+WACC!D39 -> 0.070340087 | AF149: =WACC!E39 -> 0.066665685 | AH149: =WACC!F39 -> 0.06571333 | AJ149: =WACC!G39 -> 0.064290454 | AL149: =WACC!H39 -> 0.065794777
B150: Cumulative Discount Factor | Z150: =+(1+Z149)^Z147 -> 1.0066307 | AF150: =1.01*(1+AF149)^AF147 -> 1.0841133 | AH150: =AF150*(1+AH149)^AH147 -> 1.2389185 | AJ150: =AH150*(1+AJ149)^AJ147 -> 1.502637 | AL150: =AJ150*(1+AL149)^AL147 -> 1.9509176
B152: Present Value of FCFF | Z152: =Z136/Z150 -> 7066.3984 | AF152: =AF136/AF150 -> 6694.0387 | AH152: =AH136/AH150 -> 6283.1851 | AJ152: =AJ136/AJ150 -> 5768.2622 | AL152: =AL136/AL150 -> 5123.0779
B154: Terminal Value
Q157: Preferred Method: | R157: Gordon's Growth Model | V157: EBITDA Exit Multiple | AB157: Revenue Exit Multiple | AH157: Gordon's Growth Model
V159: Current EV/EBITDA | Z159: =Inputs!M14 -> 13.124972 | AB159: Current EV/Sales | AF159: =Inputs!M13 -> 6.6009574 | AH159: Current Growth Rate | AL159: =AL136/AJ136-1 -> 0.15311018
V160: Exit EV/EBITDA | Z160: 13.5 | AB160: Exit EV/Sales | AF160: 7 | AH160: Terminal Growth Rate | AL160: 0.02
R161: =R157 -> Gordon's Growth Model | V161: Terminal Value | Z161: =(Z160+Sensitivity!U43)*(AL122+AL128) -> 213465.19 | AB161: Terminal Value | AF161: =(AF160+Sensitivity!U44)*(AL31) -> 198339.12 | AH161: Terminal Value | AL161: =AL136*(1+AL160+Sensitivity!U42)/(AL149-AL160-Sensitivity!U42) -> 222614.84
R162: =IF($R$161="Revenue Exit",$AF$171,IF($R$161="EBITDA Exit",$Z$171,$AL$171)) -> -0.12623856 | V162: PV of Terminal Value | Z162: =Z161/AL150 -> 109417.84 | AB162: PV of Terminal Value | AF162: =AF161/AL150 -> 101664.53 | AH162: PV of Terminal Value | AL162: =AL161/AL150 -> 114107.76
R163: =1-R162 -> 1.1262386 | V163: Implied Enterprise Value | Z163: =Z162+SUM(V152:AL152) -> 140352.8 | AB163: Implied Enterprise Value | AF163: =AF162+SUM(V152:AL152) -> 132599.5 | AH163: Implied Enterprise Value | AL163: =AL162+SUM(V152:AL152) -> 145042.73
R164: =IF(R162>0,"Upside","Downside") -> Downside | V164: (-) Net Debt | Z164: =BS!AI45+BS!AI44+BS!AI39+BS!AI38-BS!AI15 -> 32896 | AB164: (-) Net Debt | AF164: =BS!AI45+BS!AI44+BS!AI39+BS!AI38-BS!AI15 -> 32896 | AH164: (-) Net Debt | AL164: =BS!AI45+BS!AI44+BS!AI39+BS!AI38-BS!AI15 -> 32896
V165: (-) Preferred Stock Market Cap | Z165: =Inputs!U63 -> 0 | AB165: (-) Preferred Stock Market Cap | AF165: =Inputs!U63 -> 0 | AH165: (-) Preferred Stock Market Cap | AL165: =Inputs!U63 -> 0
V166: (-) Non-controlling Interest | Z166: =BS!AI53 -> 0 | AB166: (-) Non-controlling Interest | AF166: =BS!AI53 -> 0 | AH166: (-) Non-controlling Interest | AL166: =BS!AI53 -> 0
V167: Implied Equity Value | Z167: =Z163-Z164-Z165-Z166 -> 107456.8 | AB167: Implied Equity Value | AF167: =AF163-AF164-AF165-AF166 -> 99703.496 | AH167: Implied Equity Value | AL167: =AL163-AL164-AL165-AL166 -> 112146.73
V168: Shares Outstanding | Z168: =AL64 -> 594.1 | AB168: Shares Outstanding | AF168: =AL64 -> 594.1 | AH168: Shares Outstanding | AL168: =AL64 -> 594.1
...

Sheet Anexo_projections
C3: Market Assumptions | AO3: Opex forecast
E4: 2022 | K4: =E4+1 -> 2023 | Q4: =K4+1 -> 2024 | W4: =Q4+1 -> 2025 | AC4: =W4+1 -> 2026 | AI4: =AC4+1 -> 2027 | AK4: =+AI4+1 -> 2028 | AM4: =+AK4+1 -> 2029 | AQ4: 2022 | AW4: =AQ4+1 -> 2023 | BC4: =AW4+1 -> 2024 | BI4: =BC4+1 -> 2025 | BO4: =BI4+1 -> 2026 | BU4: =BO4+1 -> 2027 | BW4: =+BU4+1 -> 2028 | BY4: =+BW4+1 -> 2029
E5: Q1 | F5: Q2 | G5: Q3 | H5: Q4 | I5: FY | K5: Q1 | L5: Q2 | M5: Q3 | N5: Q4 | O5: FY | Q5: Q1 | R5: Q2 | S5: Q3 | T5: Q4 | U5: FY | W5: Q1 | X5: Q2 | Y5: Q3 | Z5: Q4 | AA5: FY | AC5: Q1 | AD5: Q2 | AE5: Q3 | AF5: Q4 | AG5: FY | AI5: FY | AK5: FY | AM5: FY | AQ5: Q1 | AR5: Q2 | AS5: Q3 | AT5: Q4 | AU5: FY | AW5: Q1 | AX5: Q2 | AY5: Q3 | AZ5: Q4 | BA5: FY | BC5: Q1 | BD5: Q2 | BE5: Q3 | BF5: Q4 | BG5: FY | BI5: Q1 | BJ5: Q2 | BK5: Q3 | BL5: Q4 | BM5: FY | BO5: Q1 | BP5: Q2 | BQ5: Q3 | BR5: Q4 | BS5: FY | BU5: FY | BW5: FY | BY5: FY
C6: Revenue carloads
C7: Grain & products | I7: 798 | O7: 798 | U7: 850 | AA7: =U7*(1+AA8) -> 918 | AG7: =AA7*(1+AG8) -> 963.9 | AI7: =AG7*(1+AI8) -> 1012.095 | AK7: =AI7*(1+AK8) -> 1052.5788 | AM7: =AK7*(1+AM8) -> 1094.682 | AO7: Revenues | AU7: =IS!T18 -> 24875 | BA7: =IS!Z18 -> 24119 | BG7: =IS!AF18 -> 24250 | BM7: =AA79 -> 25480.871 | BS7: =AG79 -> 26188.856 | BU7: =AI79 -> 26827.773 | BW7: =AK79 -> 27660.221 | BY7: =AM79 -> 28334.16
C8: %growth | O8: =O7/I7-1 -> 0 | U8: =U7/O7-1 -> 0.065162907 | AA8: 0.08 | AG8: 0.05 | AI8: 0.05 | AK8: 0.04 | AM8: 0.04
C9: Fertilizer | I9: 190 | O9: 191 | U9: 213 | AA9: =U9*(1+AA10) -> 234.3 | AG9: =AA9*(1+AG10) -> 253.044 | AI9: =AG9*(1+AI10) -> 263.16576 | AK9: =AI9*(1+AK10) -> 273.69239 | AM9: =AK9*(1+AM10) -> 281.90316 | AO9: Operating Expenses
C10: %growth | O10: =O9/I9-1 -> 0.0052631579 | U10: =U9/O9-1 -> 0.11518325 | AA10: 0.1 | AG10: 0.08 | AI10: 0.04 | AK10: 0.04 | AM10: 0.03 | AO10: Compensation & benefits | AU10: 4645 | BA10: 4818 | BG10: 4899 | BM10: =BM12/BM13 -> 4608.4743 | BS10: =BS12/BS13 -> 4615.3299 | BU10: =BU12/BU13 -> 4593.75 | BW10: =BW12/BW13 -> 4593.75 | BY10: =BY12/BY13 -> 4531.25
C11: Food & reefrigerated | I11: 187 | O11: 175 | U11: 177 | AA11: =U11*(1+AA12) -> 182.31 | AG11: =AA11*(1+AG12) -> 187.7793 | AI11: =AG11*(1+AI12) -> 193.41268 | AK11: =AI11*(1+AK12) -> 197.28093 | AM11: =AK11*(1+AM12) -> 201.22655 | AO11: % growth | BA11: =BA10/AU10-1 -> 0.037244349 | BG11: =BG10/BA10-1 -> 0.016811955 | BM11: =BM10/BG10-1 -> -0.059303066 | BS11: =BS10/BM10-1 -> 0.0014876158 | BU11: =BU10/BS10-1 -> -0.0046757044 | BW11: =BW10/BU10-1 -> 0 | BY11: =BY10/BW10-1 -> -0.013605442
C12: %growth | O12: =O11/I11-1 -> -0.064171123 | U12: =U11/O11-1 -> 0.011428571 | AA12: 0.03 | AG12: 0.03 | AI12: 0.03 | AK12: 0.02 | AM12: 0.02 | AO12: Number of employees on average | AU12: 30717 | BA12: 31490 | BG12: 30336 | BM12: 29711 | BS12: 29500 | BU12: 29400 | BW12: 29400 | BY12: 29000
C13: Coal & renewables | I13: 885 | O13: 867 | U13: 702 | AA13: =U13*(1+AA14) -> 631.8 | AG13: =AA13*(1+AG14) -> 581.256 | AI13: =AG13*(1+AI14) -> 552.1932 | AK13: =AI13*(1+AK14) -> 552.1932 | AM13: =AK13*(1+AM14) -> 563.23706 | AO13: Average benefits per employee | AU13: =AU12/AU10 -> 6.6129171 | BA13: =BA12/BA10 -> 6.535907 | BG13: =BG12/BG10 -> 6.1922841 | BM13: =AVERAGE(AU13:BG13) -> 6.4470361 | BS13: =AVERAGE(BA13:BM13) -> 6.3917424 | BU13: 6.4 | BW13: 6.4 | BY13: 6.4
C14: %growth | O14: =O13/I13-1 -> -0.020338983 | U14: =U13/O13-1 -> -0.19031142 | AA14: -0.1 | AG14: -0.08 | AI14: -0.05 | AK14: 0 | AM14: 0.02 | AO14: Purchased services and materials | AU14: 2442 | BA14: 2616 | BG14: 2520 | BM14: =BM7*BM15 -> 2637.6998 | BS14: =BS7*BS15 -> 2757.6568 | BU14: =BU7*BU15 -> 2816.9162 | BW14: =BW7*BW15 -> 2904.3232 | BY14: =BY7*BY15 -> 2975.0869
C15: Bulk | I15: =SUM(I7:I13) -> 2060 | O15: =SUM(O7:O13) -> 2030.9411 | U15: =SUM(U7:U13) -> 1942.1918 | AA15: =SUM(AA7:AA13) -> 1966.62 | AG15: =SUM(AG7:AG13) -> 1986.1393 | AI15: =SUM(AI7:AI13) -> 2020.9866 | AK15: =SUM(AK7:AK13) -> 2075.8453 | AM15: =SUM(AM7:AM13) -> 2141.1387 | AO15: % of sales | AU15: =AU14/AU7 -> 0.098170854 | BA15: =BA14/BA7 -> 0.10846221 | BG15: =BG14/BG7 -> 0.10391753 | BM15: =AVERAGE(BG15,BA15,AU15) -> 0.10351686 | BS15: =AVERAGE(BM15,BG15,BA15) -> 0.10529887 | BU15: 0.105 | BW15: 0.105 | BY15: 0.105
AO16: Fuel | AU16: 3439 | BA16: 2891 | BG16: 2474 | BM16: =BM18/BM17 -> 2573.7236 | BS16: =BS18/BS17 -> 2736.7489 | BU16: =BU18/BU17 -> 2578.8522 | BW16: =BW18/BW17 -> 2535.3739 | BY16: =BY18/BY17 -> 2419.4319
C17: Industrial chemicals & plastics | I17: 637 | O17: 645 | U17: 672 | AA17: =U17*(1+AA18) -> 702.24 | AG17: =AA17*(1+AG18) -> 730.3296 | AI17: =AG17*(1+AI18) -> 759.54278 | AK17: =AI17*(1+AK18) -> 789.9245 | AM17: =AK17*(1+AM18) -> 813.62223 | AO17: Average fuel price | AU17: 3.65 | BA17: 3.09 | BG17: 2.64 | BM17: 2.46 | BS17: 2.35 | BU17: 2.3 | BW17: 2.3 | BY17: 2.3
C18: %growth | O18: =O17/I17-1 -> 0.01255887 | U18: =U17/O17-1 -> 0.041860465 | AA18: 0.045 | AG18: 0.04 | AI18: 0.04 | AK18: 0.04 | AM18: 0.03 | AO18: Machines/venhicles that need fuel | AU18: =AU17*AU16 -> 12552.35 | BA18: =BA17*BA16 -> 8933.19 | BG18: =BG17*BG16 -> 6531.36 | BM18: =BG18-200 -> 6331.36 | BS18: =AVERAGE(BG18:BM18) -> 6431.36 | BU18: =AVERAGE(BC18:BS18)-500 -> 5931.36 | BW18: =AVERAGE(BM18:BU18)-400 -> 5831.36 | BY18: =AVERAGE(BO18:BW18)-500 -> 5564.6933
C19: Metals & minerals | I19: 785 | O19: 793 | U19: 719 | AA19: =U19*(1+AA20) -> 690.24 | AG19: =AA19*(1+AG20) -> 690.24 | AI19: =AG19*(1+AI20) -> 697.1424 | AK19: =AI19*(1+AK20) -> 711.08525 | AM19: =AK19*(1+AM20) -> 725.30695 | AO19: Equipment and other rents | AU19: 898 | BA19: 947 | BG19: 920 | BM19: =(BM20)*BM21 -> 950.65559 | BS19: =(BS20)*BS21 -> 972.99824 | BU19: =(BU20)*BU21 -> 986.22845 | BW19: =(BW20)*BW21 -> 1002.3958 | BY19: =(BY20)*BY21 -> 1006.6845
C20: %growth | O20: =O19/I19-1 -> 0.010191083 | U20: =U19/O19-1 -> -0.09331652 | AA20: -0.04 | AG20: 0 | AI20: 0.01 | AK20: 0.02 | AM20: 0.02 | AO20: % of Net PP&E | AU20: =AU19/AU21 -> 0.015560561 | BA20: =BA19/BA21 -> 0.016039701 | BG20: =BG19/BG21 -> 0.015425889 | BM20: =AVERAGE(AU20:BG20) -> 0.015675384 | BS20: =AVERAGE(BA20:BM20) -> 0.015713658 | BU20: =AVERAGE(BG20:BS20) -> 0.015604977 | BW20: =AVERAGE(BI20:BU20) -> 0.015664673 | BY20: =AVERAGE(BK20:BW20) -> 0.015664673
C21: Forest products | I21: 241 | O21: 213 | U21: 213 | AA21: =U21*(1+AA22) -> 215.13 | AG21: =AA21*(1+AG22) -> 217.2813 | AI21: =AG21*(1+AI22) -> 219.45411 | AK21: =AI21*(1+AK22) -> 223.8432 | AM21: =AK21*(1+AM22) -> 228.32006 | AO21: Net PP&E | AU21: =FCFF!H79 -> 57710 | BA21: =FCFF!N79 -> 59041 | BG21: =FCFF!T79 -> 59640 | BM21: =FCFF!Z79 -> 60646.4 | BS21: =FCFF!AF79 -> 61920.544 | BU21: =FCFF!AH79 -> 63199.61 | BW21: =FCFF!AJ79 -> 63990.853 | BY21: =FCFF!AL79 -> 64264.634
C22: %growth | O22: =O21/I21-1 -> -0.11618257 | U22: =U21/O21-1 -> 0 | AA22: 0.01 | AG22: 0.01 | AI22: 0.01 | AK22: 0.02 | AM22: 0.02 | AO22: Other | AU22: 1288 | BA22: 1447 | BG22: 1326 | BM22: =BM23*BM7 -> 1413.7934 | BS22: =BS23*BS7 -> 1485.4241 | BU22: =BU23*BU7 -> 1492.3809 | BW22: =BW23*BW7 -> 1547.4272 | BY22: =BY23*BY7 -> 1589.4713
C23: Energy & specialized markets | I23: 552 | O23: 582 | U23: 607 | AA23: =U23*(1+AA24) -> 631.28 | AG23: =AA23*(1+AG24) -> 656.5312 | AI23: =AG23*(1+AI24) -> 682.79245 | AK23: =AI23*(1+AK24) -> 710.10415 | AM23: =AK23*(1+AM24) -> 731.40727 | AO23: % of sales | AU23: =AU22/AU7 -> 0.051778894 | BA23: =BA22/BA7 -> 0.059994195 | BG23: =BG22/BG7 -> 0.054680412 | BM23: =AVERAGE(AU23:BG23) -> 0.055484501 | BS23: =AVERAGE(BA23:BM23) -> 0.056719703 | BU23: =AVERAGE(BC23:BS23) -> 0.055628205 | BW23: =AVERAGE(BM23,BS23,BU23) -> 0.055944136 | BY23: =AVERAGE(BS23:BW23) -> 0.056097348
C24: %growth | O24: =O23/I23-1 -> 0.054347826 | U24: =U23/O23-1 -> 0.042955326 | AA24: 0.04 | AG24: 0.04 | AI24: 0.04 | AK24: 0.04 | AM24: 0.03 | AO24: Total Opex | AU24: =+AU22+AU19+AU16+AU14+AU10 -> 12712 | BA24: =+BA22+BA19+BA16+BA14+BA10 -> 12719 | BG24: =+BG22+BG19+BG16+BG14+BG10 -> 12139 | BM24: =+BM22+BM19+BM16+BM14+BM10 -> 12184.347 | BS24: =+BS22+BS19+BS16+BS14+BS10 -> 12568.158 | BU24: =+BU22+BU19+BU16+BU14+BU10 -> 12468.128 | BW24: =+BW22+BW19+BW16+BW14+BW10 -> 12583.27 | BY24: =+BY22+BY19+BY16+BY14+BY10 -> 12521.924
C25: Industrials | I25: =SUM(I17:I23) -> 2215 | O25: =SUM(O17:O23) -> 2232.9066 | U25: =SUM(U17:U23) -> 2210.9485 | AA25: =SUM(AA17:AA23) -> 2238.905 | AG25: =SUM(AG17:AG23) -> 2294.4321 | AI25: =SUM(AI17:AI23) -> 2358.9917 | AK25: =SUM(AK17:AK23) -> 2435.0371 | AM25: =SUM(AM17:AM23) -> 2498.7265
C27: Automotive | I27: 778 | O27: 820 | U27: 824 | AA27: =U27*(1+AA28) -> 824 | AG27: =AA27*(1+AG28) -> 832.24 | AI27: =AG27*(1+AI28) -> 840.5624 | AK27: =AI27*(1+AK28) -> 857.37365 | AM27: =AK27*(1+AM28) -> 874.52112
C28: %growth | O28: =O27/I27-1 -> 0.053984576 | U28: =U27/O27-1 -> 0.0048780488 | AA28: 0 | AG28: 0.01 | AI28: 0.01 | AK28: 0.02 | AM28: 0.02
C29: Intermodal | I29: 3116 | O29: 3028 | U29: 3357 | AA29: =U29*(1+AA30) -> 3692.7 | AG29: =AA29*(1+AG30) -> 3877.335 | AI29: =AG29*(1+AI30) -> 4032.4284 | AK29: =AI29*(1+AK30) -> 4153.4013 | AM29: =AK29*(1+AM30) -> 4236.4693
C30: %growth | O30: =O29/I29-1 -> -0.028241335 | U30: =U29/O29-1 -> 0.10865258 | AA30: 0.1 | AG30: 0.05 | AI30: 0.04 | AK30: 0.03 | AM30: 0.02
C31: Premium | I31: =SUM(I27:I29) -> 3894 | O31: =SUM(O27:O29) -> 3848.054 | U31: =SUM(U27:U29) -> 4181.0049 | AA31: =SUM(AA27:AA29) -> 4516.7 | AG31: =SUM(AG27:AG29) -> 4709.585 | AI31: =SUM(AI27:AI29) -> 4873.0008 | AK31: =SUM(AK27:AK29) -> 5010.7949 | AM31: =SUM(AM27:AM29) -> 5111.0104
C32: Total | I32: =I31+I25+I15 -> 8169 | O32: =O31+O25+O15 -> 8111.9016 | U32: =U31+U25+U15 -> 8334.1452 | AA32: =AA31+AA25+AA15 -> 8722.225 | AG32: =AG31+AG25+AG15 -> 8990.1564 | AI32: =AI31+AI25+AI15 -> 9252.9792 | AK32: =AK31+AK25+AK15 -> 9521.6773 | AM32: =AM31+AM25+AM15 -> 9750.8756
C34: Average revenue per car
C35: Grain & products | I35: 4.509 | O35: 4.567 | U35: 4.505 | AA35: 4.5 | AG35: =AVERAGE(O35:AA35) -> 4.524 | AI35: =AVERAGE(U35:AG35) -> 4.5096667 | AK35: =AVERAGE(AA35:AI35) -> 4.5112222 | AM35: =AVERAGE(AC35:AK35) -> 4.514963
C36: Fertilizer | I36: 3.749 | O36: 3.962 | U36: 3.809 | AA36: 3.7 | AG36: =AVERAGE(O36:AA36) -> 3.8236667 | AI36: =AVERAGE(U36:AG36) -> 3.7775556 | AK36: =AVERAGE(AA36:AI36) -> 3.7670741 | AM36: =AVERAGE(AC36:AK36) -> 3.7894321
C37: Food & reefrigerated | I37: 5.844 | O37: 5.929 | U37: 6.104 | AA37: =AVERAGE(I37:U37) -> 5.959 | AG37: =AVERAGE(O37:AA37) -> 5.9973333 | AI37: =AVERAGE(U37:AG37) -> 6.0201111 | AK37: =AVERAGE(AA37:AI37) -> 5.9921481 | AM37: =AVERAGE(AC37:AK37) -> 6.0031975
C38: Coal & renewables | I38: 2.41 | O38: 2.211 | U38: 2.113 | AA38: =AVERAGE(U38,O38,I38) -> 2.2446667 | AG38: =AVERAGE(O38:AA38) -> 2.1895556 | AI38: =AVERAGE(U38:AG38) -> 2.1824074 | AK38: =AVERAGE(AA38:AI38) -> 2.2055432 | AM38: =AVERAGE(AC38:AK38) -> 2.1925021
C39: Bulk | I39: =I60/I15 -> 3.6587379 | O39: =O60/O15 -> 3.622951 | U39: =U60/U15 -> 3.7107561 | AA39: =AVERAGE(U39,O39,I39) -> 3.6641483 | AG39: =AVERAGE(O39:AA39) -> 3.6659518 | AI39: =AVERAGE(U39:AG39) -> 3.6802854 | AK39: =AVERAGE(AA39:AI39) -> 3.6701285 | AM39: =AVERAGE(AC39:AK39) -> 3.6721219
O40: =O39/I39-1 -> -0.0097812128 | U40: =U39/O39-1 -> 0.024235808
C41: Industrial chemicals & plastics | I41: 3.388 | O41: 3.374 | U41: 3.493 | AA41: =AVERAGE(I41:U41) -> 3.4183333 | AG41: =AVERAGE(O41:AA41) -> 3.4284444 | AI41: =AVERAGE(U41:AG41) -> 3.4465926 | AK41: =AVERAGE(AA41:AI41) -> 3.4311235 | AM41: =AVERAGE(AC41:AK41) -> 3.4353868
C42: Metals & minerals | I42: 2.797 | O42: 2.765 | U42: 2.893 | AA42: =AVERAGE(I42:U42) -> 2.8183333 | AG42: =AVERAGE(O42:AA42) -> 2.8254444 | AI42: =AVERAGE(U42:AG42) -> 2.8455926 | AK42: =AVERAGE(AA42:AI42) -> 2.8297901 | AM42: =AVERAGE(AC42:AK42) -> 2.8336091
C43: Forest products | I43: 6.092 | O43: 6.31 | U43: 6.229 | AA43: =AVERAGE(I43:U43) -> 6.2103333 | AG43: =AVERAGE(O43:AA43) -> 6.2497778 | AI43: =AVERAGE(U43:AG43) -> 6.2297037 | AK43: =AVERAGE(AA43:AI43) -> 6.2299383 | AM43: =AVERAGE(AC43:AK43) -> 6.2364733
C44: Energy & specialized markets | I44: 4.32 | O44: 4.335 | U44: 4.426 | AA44: =AVERAGE(I44:U44) -> 4.3603333 | AG44: =AVERAGE(O44:AA44) -> 4.3737778 | AI44: =AVERAGE(U44:AG44) -> 4.3867037 | AK44: =AVERAGE(AA44:AI44) -> 4.3736049 | AM44: =AVERAGE(AC44:AK44) -> 4.3780288
C45: Industrials | I45: =I69/I25 -> 3.7042889 | O45: =O69/O25 -> 3.6893617 | U45: =U69/U25 -> 3.8173661 | AA45: =AA69/AA25 -> 3.7672152 | AG45: =AG69/AG25 -> 3.7846449 | AI45: =AI69/AI25 -> 3.7999116 | AK45: =AK69/AK25 -> 3.7875377 | AM45: =AM69/AM25 -> 3.7924829
C46: Automotive | I46: 2.902 | O46: 2.955 | U46: 2.976 | AA46: =AVERAGE(I46:U46) -> 2.9443333 | AG46: =AVERAGE(O46:AA46) -> 2.9584444 | AI46: =AVERAGE(U46:AG46) -> 2.9595926 | AK46: =AVERAGE(AA46:AI46) -> 2.9541235 | AM46: =AVERAGE(AC46:AK46) -> 2.9573868
C47: Intermodal | I47: 1.656 | O47: 1.504 | U47: 1.404 | AA47: =AVERAGE(I47:U47) -> 1.5213333 | AG47: 1.5 | AI47: =AVERAGE(U47:AG47) -> 1.4751111 | AK47: =AVERAGE(AA47:AI47) -> 1.4988148 | AM47: =AVERAGE(AC47:AK47) -> 1.4913086
C48: Premium | I48: =I74/I31 -> 1.9047252 | O48: =O74/O31 -> 1.8126045 | U48: =U74/U31 -> 1.7134637 | AA48: =AA74/AA31 -> 1.780937 | AG48: =AG74/AG31 -> 1.7577214 | AI48: =AI74/AI31 -> 1.7311719 | AK48: =AK74/AK31 -> 1.7478199 | AM48: =AM74/AM31 -> 1.7421566
C49: Total | I49: =I75/I32 -> 2.8349859 | O49: =O75/O32 -> 2.7824548 | U49: =U75/U32 -> 2.7370533 | AA49: =AA75/AA32 -> 2.7493983 | AG49: =AG75/AG32 -> 2.7462098 | AI49: =AI75/AI32 -> 2.737256 | AK49: =AK75/AK32 -> 2.7474383 | AM49: =AM75/AM32 -> 2.7519744
C51: Freight Revenues
C52: Grain & products | I52: 3598 | O52: 3644 | U52: 3828 | AA52: =AA35*AA7 -> 4131 | AG52: =AG35*AG7 -> 4360.6836 | AI52: =AI35*AI7 -> 4564.2111 | AK52: =AK35*AK7 -> 4748.4169 | AM52: =AM35*AM7 -> 4942.4485
C53: %growth | O53: =O52/I52-1 -> 0.01278488 | U53: =U52/O52-1 -> 0.050493963 | AA53: =AA52/U52-1 -> 0.079153605 | AG53: =AG52/AA52-1 -> 0.0556 | AI53: =AI52/AG52-1 -> 0.046673298 | AK53: =AK52/AI52-1 -> 0.040358736 | AM53: =AM52/AK52-1 -> 0.040862376
C54: Fertilizer | I54: 712 | O54: 757 | U54: 811 | AA54: =AA36*AA9 -> 866.91 | AG54: =AG36*AG9 -> 967.55591 | AI54: =AI36*AI9 -> 994.12328 | AK54: =AK36*AK9 -> 1031.0195 | AM54: =AM36*AM9 -> 1068.2529
C55: %growth | O55: =O54/I54-1 -> 0.063202247 | U55: =U54/O54-1 -> 0.071334214 | AA55: =AA54/U54-1 -> 0.068939581 | AG55: =AG54/AA54-1 -> 0.1160973 | AI55: =AI54/AG54-1 -> 0.027458228 | AK55: =AK54/AI54-1 -> 0.03711434 | AM55: =AM54/AK54-1 -> 0.03611317
C56: Food & reefrigerated | I56: 1093 | O56: 1041 | U56: 1085 | AA56: =AA37*AA11 -> 1086.3853 | AG56: =AG37*AG11 -> 1126.1751 | AI56: =AI37*AI11 -> 1164.3658 | AK56: =AK37*AK11 -> 1182.1366 | AM56: =AM37*AM11 -> 1208.0027
C57: %growth | O57: =O56/I56-1 -> -0.04757548 | U57: =U56/O56-1 -> 0.042267051 | AA57: =AA56/U56-1 -> 0.001276765 | AG57: =AG56/AA56-1 -> 0.036625832 | AI57: =AI56/AG56-1 -> 0.033911924 | AK57: =AK56/AI56-1 -> 0.015262177 | AM57: =AM56/AK56-1 -> 0.021880856
C58: Coal & renewables | I58: 2134 | O58: 1916 | U58: 1483 | AA58: =AA38*AA13 -> 1418.1804 | AG58: =AG38*AG13 -> 1272.6923 | AI58: =AI38*AI13 -> 1205.1105 | AK58: =AK38*AK13 -> 1217.886 | AM58: =AM38*AM13 -> 1234.8984
C59: %growth | O59: =O58/I58-1 -> -0.10215558 | U59: =U58/O58-1 -> -0.22599165 | AA59: =AA58/U58-1 -> -0.043708429 | AG59: =AG58/AA58-1 -> -0.10258786 | AI59: =AI58/AG58-1 -> -0.053101424 | AK59: =AK58/AI58-1 -> 0.010601047 | AM59: =AM58/AK58-1 -> 0.013968844
C60: Bulk | I60: =Segments!T21 -> 7537 | O60: =Segments!Z21 -> 7358 | U60: =Segments!AF21 -> 7207 | AA60: =+AA58+AA56+AA52+AA54 -> 7502.4757 | AG60: =+AG58+AG56+AG52+AG54 -> 7727.1069 | AI60: =+AI58+AI56+AI52+AI54 -> 7927.8107 | AK60: =+AK58+AK56+AK52+AK54 -> 8179.4589 | AM60: =+AM58+AM56+AM52+AM54 -> 8453.6025
C61: Industrial chemicals & plastics | I61: 2158 | O61: 2176 | U61: 2345 | AA61: =AA41*AA17 -> 2400.4904 | AG61: =AG41*AG17 -> 2503.8945 | AI61: =AI41*AI17 -> 2617.8345 | AK61: =AK41*AK17 -> 2710.3285 | AM61: =AM41*AM17 -> 2795.1071
C62: %growth | O62: =O61/I61-1 -> 0.0083410565 | U62: =U61/O61-1 -> 0.077665441 | AA62: =AA61/U61-1 -> 0.023663284 | AG62: =AG61/AA61-1 -> 0.043076223 | AI62: =AI61/AG61-1 -> 0.045505142 | AK62: =AK61/AI61-1 -> 0.03533223 | AM62: =AM61/AK61-1 -> 0.031279836
C63: Metals & minerals | I63: 2196 | O63: 2194 | U63: 2081 | AA63: =AA42*AA19 -> 1945.3264 | AG63: =AG42*AG19 -> 1950.2348 | AI63: =AI42*AI19 -> 1983.7832 | AK63: =AK42*AK19 -> 2012.222 | AM63: =AM42*AM19 -> 2055.2363
C64: %growth | O64: =O63/I63-1 -> -0.00091074681 | U64: =U63/O63-1 -> -0.051504102 | AA64: =AA63/U63-1 -> -0.065196348 | AG64: =AG63/AA63-1 -> 0.0025231618 | AI64: =AI63/AG63-1 -> 0.017202276 | AK64: =AK63/AI63-1 -> 0.01433562 | AM64: =AM63/AK63-1 -> 0.021376536
C65: Forest products | I65: 1465 | O65: 1347 | U65: 1326 | AA65: =AA43*AA21 -> 1336.029 | AG65: =AG43*AG21 -> 1357.9598 | AI65: =AI43*AI21 -> 1367.1341 | AK65: =AK43*AK21 -> 1394.5293 | AM65: =AM43*AM21 -> 1423.9119
C66: %growth | O66: =O65/I65-1 -> -0.080546075 | U66: =U65/O65-1 -> -0.0155902 | AA66: =AA65/U65-1 -> 0.007563356 | AG66: =AG65/AA65-1 -> 0.016414936 | AI66: =AI65/AG65-1 -> 0.0067559143 | AK66: =AK65/AI65-1 -> 0.020038406 | AM66: =AM65/AK65-1 -> 0.021069943
C67: Energy & specialized markets | I67: 2386 | O67: 2521 | U67: 2688 | AA67: =AA44*AA23 -> 2752.5912 | AG67: =AG44*AG23 -> 2871.5216 | AI67: =AI44*AI23 -> 2995.2082 | AK67: =AK44*AK23 -> 3105.715 | AM67: =AM44*AM23 -> 3202.1221
C68: %growth | O68: =O67/I67-1 -> 0.05658005 | U68: =U67/O67-1 -> 0.066243554 | AA68: =AA67/U67-1 -> 0.024029474 | AG68: =AG67/AA67-1 -> 0.043206687 | AI68: =AI67/AG67-1 -> 0.043073536 | AK68: =AK67/AI67-1 -> 0.036894544 | AM68: =AM67/AK67-1 -> 0.031041837
C69: Industrials | I69: =Segments!T22 -> 8205 | O69: =Segments!Z22 -> 8238 | U69: =Segments!AF22 -> 8440 | AA69: =AA67+AA65+AA63+AA61 -> 8434.437 | AG69: =AG67+AG65+AG63+AG61 -> 8683.6106 | AI69: =AI67+AI65+AI63+AI61 -> 8963.96 | AK69: =AK67+AK65+AK63+AK61 -> 9222.7948 | AM69: =AM67+AM65+AM63+AM61 -> 9476.3775
C70: Automotive | I70: 2257 | O70: 2421 | U70: 2452 | AA70: =AA46*AA27 -> 2426.1307 | AG70: =AG46*AG27 -> 2462.1358 | AI70: =AI46*AI27 -> 2487.7223 | AK70: =AK46*AK27 -> 2532.7876 | AM70: =AM46*AM27 -> 2586.2972
C71: %growth | O71: =O70/I70-1 -> 0.072662827 | U71: =U70/O70-1 -> 0.012804626 | AA71: =AA70/U70-1 -> -0.010550299 | AG71: =AG70/AA70-1 -> 0.01484056 | AI71: =AI70/AG70-1 -> 0.010391973 | AK71: =AK70/AI70-1 -> 0.018115106 | AM71: =AM70/AK70-1 -> 0.021126778
C72: Intermodal | I72: 5160 | O72: 4554 | U72: 4712 | AA72: =AA47*AA29 -> 5617.8276 | AG72: =AG47*AG29 -> 5816.0025 | AI72: =AI47*AI29 -> 5948.2799 | AK72: =AK47*AK29 -> 6225.1793 | AM72: =AM47*AM29 -> 6317.8832
C73: %growth | O73: =O72/I72-1 -> -0.11744186 | U73: =U72/O72-1 -> 0.034694774 | AA73: =AA72/U72-1 -> 0.19223846 | AG73: =AG72/AA72-1 -> 0.035276074 | AI73: =AI72/AG72-1 -> 0.022743704 | AK73: =AK72/AI72-1 -> 0.04655117 | AM73: =AM72/AK72-1 -> 0.014891766
C74: Premium | I74: =Segments!T23 -> 7417 | O74: =Segments!Z23 -> 6975 | U74: =Segments!AF23 -> 7164 | AA74: =+AA72+AA70 -> 8043.9583 | AG74: =+AG72+AG70 -> 8278.1383 | AI74: =+AI72+AI70 -> 8436.0022 | AK74: =+AK72+AK70 -> 8757.9669 | AM74: =+AM72+AM70 -> 8904.1805
C75: Total | I75: =I74+I69+I60 -> 23159 | O75: =O74+O69+O60 -> 22571 | U75: =U74+U69+U60 -> 22811 | AA75: =AA74+AA69+AA60 -> 23980.871 | AG75: =AG74+AG69+AG60 -> 24688.856 | AI75: =AI74+AI69+AI60 -> 25327.773 | AK75: =AK74+AK69+AK60 -> 26160.221 | AM75: =AM74+AM69+AM60 -> 26834.16
C77: Other revenues | I77: =Segments!T24 -> 1716 | O77: =Segments!Z24 -> 1548 | U77: =Segments!AF24 -> 1439 | AA77: 1500 | AG77: 1500 | AI77: 1500 | AK77: 1500 | AM77: 1500
C79: Total revenues | I79: =I75+I77 -> 24875 | O79: =O75+O77 -> 24119 | U79: =U75+U77 -> 24250 | AA79: =AA75+AA77 -> 25480.871 | AG79: =AG75+AG77 -> 26188.856 | AI79: =AI75+AI77 -> 26827.773 | AK79: =AK75+AK77 -> 27660.221 | AM79: =AM75+AM77 -> 28334.16
AA80: =AA79/U79-1 -> 0.050757567 | AG80: =AG79/AA79-1 -> 0.027784954 | AI80: =AI79/AG79-1 -> 0.024396527 | AK80: =AK79/AI79-1 -> 0.031029324 | AM80: =AM79/AK79-1 -> 0.024364949

Sheet LBO
A7: x | B7: Key Assumptions
N9: Forecast based on projections of company acquisition of Norfolk, synergies created might reach a 2.75 Bi in synergies, due to new revenues and productivity oportunities
B10: Entry | G10: Capital Structure | J10: Interest | K10: Weight | L10: Amount | N10: Repurchase of stock upon transaction is stopped
B11: LTM EBITDA | E11: =(G86+G77) -> 12111 | G11: Revolver | L11: =K11*$E$13 -> 0 | N11: If transaction is not happening we have a reverse termination fee paid by the UNP of 2.5 Bi to be paid included in the base forecast of FCFF
B12: Entry Multiple | G12: Bank Loan | L12: =K12*$E$13 -> 0 | N12: Debt/EBITDA has to be maintained at max 3.3x
B13: Enterprise Value | E13: =E11*E12 -> 0 | G13: Senior Notes | L13: =K13*$E$13 -> 0 | N13: Debt/EBITDA reduced to 2.2x in year 2 post acquisition ( 2029)
B14: Existing Net Debt | E14: =BS!AJ38+BS!AJ39+BS!AJ44+BS!AJ45-BS!AJ15 -> 0
B15: Equity Value | E15: =E13-E14 -> 0 | G15: IRR (For reference)
G16: MOIC | L16: =L180 -> #DIV/0!
B17: Fees & Expenses | E17: =0.03*E13 -> 0 | G17: IRR | L17: =L181 -> #DIV/0!
B19: Exit
B20: Exit Multiple
A22: x | B22: Sources & Uses
B25: Sources | G25: Uses
C26: Amount | D26: xEBITDA | E26: % Capital | J26: Amount | K26: xEBITDA | L26: % Capital
B27: Revolver | C27: =L11 -> 0 | D27: =C27/$E$11 -> 0 | E27: =C27/$C$34 -> #DIV/0! | G27: Debt Refinancing | J27: =E14 -> 0 | K27: =J27/$E$11 -> 0 | L27: =J27/$J$34 -> #DIV/0!
B28: Bank Loan | C28: =L12 -> 0 | D28: =C28/$E$11 -> 0 | E28: =C28/$C$34 -> #DIV/0! | G28: Equity Payments | J28: =E15 -> 0 | K28: =J28/$E$11 -> 0 | L28: =J28/$J$34 -> #DIV/0!
B29: Senior Notes | C29: =L13 -> 0 | D29: =C29/$E$11 -> 0 | E29: =C29/$C$34 -> #DIV/0!
B30: Total | C30: =SUM(C27:C29) -> 0 | D30: =C30/$E$11 -> 0 | E30: =C30/$C$34 -> #DIV/0! | G30: Fees & Expenses | J30: =E17 -> 0 | K30: =J30/$E$11 -> 0 | L30: =J30/$J$34 -> #DIV/0!
B32: Sponsor Equity | C32: =C34-C30 -> 0 | D32: =C32/$E$11 -> 0 | E32: =C32/$C$34 -> #DIV/0!
B34: Total Sources | C34: =J34 -> 0 | D34: =C34/$E$11 -> 0 | E34: =C34/$C$34 -> #DIV/0! | G34: Total Uses | J34: =J27+J28+J30 -> 0 | K34: =J34/$E$11 -> 0 | L34: =J34/$J$34 -> #DIV/0!
B36: Market Assumptions
A38: x | E38: 2022 | F38: =+E38+1 -> 2023 | G38: =+F38+1 -> 2024 | H38: =+G38+1 -> 2025 | I38: =+H38+1 -> 2026 | J38: =+I38+1 -> 2027 | K38: =+J38+1 -> 2028 | L38: =+K38+1 -> 2029
B50: Sales | H50: =SUM(H39:H49) -> 0 | I50: =SUM(I39:I49) -> 0 | J50: =SUM(J39:J49) -> 0 | K50: =SUM(K39:K49) -> 0 | L50: =SUM(L39:L49) -> 0
B52: Operating Assumptions
A57: x | B57: Income Statement | E57: 2022 | F57: =+E57+1 -> 2023 | G57: =+F57+1 -> 2024 | H57: =+G57+1 -> 2025 | I57: =+H57+1 -> 2026 | J57: =+I57+1 -> 2027 | K57: =+J57+1 -> 2028 | L57: =+K57+1 -> 2029
B59: Revenue | D59: =+_xlfn.XLOOKUP($B59,#REF!,#REF!) -> #REF! | E59: =FCFF!H31 -> 24875 | F59: =FCFF!N31 -> 24119 | G59: =FCFF!T31 -> 24250 | H59: =+H50 -> 0 | I59: =+I50 -> 0 | J59: =+J50 -> 0 | K59: =+K50 -> 0 | L59: =+L50 -> 0
B60: % of growth | E60: =E59/IS!N18-1 -> 0.14084572 | F60: =F59/E59-1 -> -0.03039196 | G60: =G59/F59-1 -> 0.0054314026 | H60: =H59/G59-1 -> -1 | I60: =I59/H59-1 -> #DIV/0! | J60: =J59/I59-1 -> #DIV/0! | K60: =K59/J59-1 -> #DIV/0! | L60: =L59/K59-1 -> #DIV/0!
B62: Cost of Goods & Services | E62: =FCFF!H34 -> 0 | F62: =FCFF!N34 -> 0 | G62: =FCFF!T34 -> 0 | H62: =H63*H$59 -> 0 | I62: =I63*I$59 -> 0 | J62: =J63*J$59 -> 0 | K62: =K63*K$59 -> 0 | L62: =L63*L$59 -> 0
B63: % of sales | E63: =E62/E59 -> 0 | F63: =F62/F59 -> 0 | G63: =G62/G59 -> 0
B65: COGS Depreciation & Amortization | E65: =FCFF!H37 -> 0 | F65: =FCFF!N37 -> 0 | G65: =FCFF!T37 -> 0 | H65: =+H66*H62 -> 0 | I65: =+I66*I62 -> 0 | J65: =+J66*J62 -> 0 | K65: =+K66*K62 -> 0 | L65: =+L66*L62 -> 0
B66: % of cost of goods & services | E66: - | F66: - | G66: - | H66: 0 | I66: 0 | J66: 0 | K66: 0 | L66: 0
B68: Gross Profit | E68: =FCFF!H40 -> 24875 | F68: =FCFF!N40 -> 24119 | G68: =FCFF!T40 -> 24250 | H68: =+H59-H62-H65 -> 0 | I68: =+I59-I62-I65 -> 0 | J68: =+J59-J62-J65 -> 0 | K68: =+K59-K62-K65 -> 0 | L68: =+L59-L62-L65 -> 0
B69: % of sales | E69: =E68/E59 -> 1 | F69: =F68/F59 -> 1 | G69: =G68/G59 -> 1 | H69: =IFERROR(H68/H$59,"") | I69: =IFERROR(I68/I$59,"") | J69: =IFERROR(J68/J$59,"") | K69: =IFERROR(K68/K$59,"") | L69: =IFERROR(L68/L$59,"")
B71: SG&A (Selling, General & Administrative) | E71: =FCFF!H43 -> 0 | F71: =FCFF!N43 -> 0 | G71: =FCFF!T43 -> 0 | H71: =+H72*H59 -> 0 | I71: =+I72*I59 -> 0 | J71: =+J72*J59 -> 0 | K71: =+K72*K59 -> 0 | L71: =+L72*L59 -> 0
B72: % of sales | E72: =E71/E59 -> 0 | F72: =F71/F59 -> 0 | G72: =G71/G59 -> 0
B74: R&D (Research & Development) | E74: =FCFF!H46 -> 0 | F74: =FCFF!N46 -> 0 | G74: =FCFF!T46 -> 0 | H74: =+H75*H68 -> 0 | I74: =+I75*I68 -> 0 | J74: =+J75*J68 -> 0 | K74: =+K75*K68 -> 0 | L74: =+L75*L68 -> 0
B75: % of gross profit | E75: =E74/E68 -> 0 | F75: =F74/F68 -> 0 | G75: =G74/G68 -> 0
B77: D&A (Depreciation & Amortization) | E77: =FCFF!H49 -> 2246 | F77: =FCFF!N49 -> 2318 | G77: =FCFF!T49 -> 2398 | H77: =+H80+H83 -> 0 | I77: =+I80+I83 -> 0 | J77: =+J80+J83 -> 0 | K77: =+K80+K83 -> 0 | L77: =+L80+L83 -> 0
B78: % of net pp&e and intangibles excl. Goodwill | E78: =E77/(E111+E114) -> 0.038918732 | F78: =F77/(F111+F114) -> 0.039260853 | G78: =G77/(G111+G114) -> 0.040207914 | H78: =H77/(H111+H114) -> 0 | I78: =I77/(I111+I114) -> 0 | J78: =J77/(J111+J114) -> 0 | K78: =K77/(K111+K114) -> 0 | L78: =L77/(L111+L114) -> 0
B80: Depreciation | E80: =FCFF!H52 -> 0 | F80: =FCFF!N52 -> 0 | G80: =FCFF!T52 -> 0 | H80: =H81*G111 -> 0 | I80: =I81*H111 -> 0 | J80: =J81*I111 -> 0 | K80: =K81*J111 -> 0 | L80: =L81*K111 -> 0
B81: % of net pp&e | E81: =E80/E111 -> 0 | F81: =FCFF!N53 -> 0 | G81: =FCFF!T53 -> 0
B83: Amortization | E83: =FCFF!H55 -> 0 | F83: =FCFF!N55 -> 0 | G83: =FCFF!T55 -> 0 | H83: =H84*G114 -> 0 | I83: =I84*H114 -> 0 | J83: =J84*I114 -> 0 | K83: =K84*J114 -> 0 | L83: =L84*K114 -> 0
B84: % of intangibles excl. goodwill | E84: =E83/E114 -> #DIV/0! | F84: =F83/F114 -> #DIV/0! | G84: =G83/G114 -> #DIV/0!
B86: EBIT (Operating Income) | E86: =FCFF!H61 -> 10009 | F86: =FCFF!N61 -> 9082 | G86: =FCFF!T61 -> 9713 | H86: =H68-H71-H74-H77 -> 0 | I86: =I68-I71-I74-I77 -> 0 | J86: =J68-J71-J74-J77 -> 0 | K86: =K68-K71-K74-K77 -> 0 | L86: =L68-L71-L74-L77 -> 0
B87: % of sales | E87: =E86/E59 -> 0.40237186 | F87: =F86/F59 -> 0.37654961 | G87: =G86/G59 -> 0.40053608 | H87: =H86/H59 -> #DIV/0! | I87: =I86/I59 -> #DIV/0! | J87: =J86/J59 -> #DIV/0! | K87: =K86/K59 -> #DIV/0! | L87: =L86/L59 -> #DIV/0!
B89: Net Interest (Income) Expense | E89: =IS!T38 -> 0 | F89: =IS!Z38 -> 1340 | G89: =IS!AF38 -> 1269 | H89: =+H164 -> 0 | I89: =+I164 -> 0 | J89: =+J164 -> 0 | K89: =+K164 -> 0 | L89: =+L164 -> 0
B91: Pre-tax income | E91: =IS!T42 -> 9164 | F91: =IS!Z42 -> 8233 | G91: =IS!AF42 -> 8794 | H91: =+H86-H89 -> 0 | I91: =+I86-I89 -> 0 | J91: =+J86-J89 -> 0 | K91: =+K86-K89 -> 0 | L91: =+L86-L89 -> 0
B92: % of sales | E92: =E91/E59 -> 0.36840201 | F92: =F91/F59 -> 0.34134914 | G92: =G91/G59 -> 0.36263918 | H92: =H91/H59 -> #DIV/0! | I92: =I91/I59 -> #DIV/0! | J92: =J91/J59 -> #DIV/0! | K92: =K91/K59 -> #DIV/0! | L92: =L91/L59 -> #DIV/0!
B94: Income tax expenses (benefits) | E94: =IS!T45 -> 2097 | F94: =IS!Z45 -> 1854 | G94: =IS!AF45 -> 2047 | H94: =H95*H91 -> 0 | I94: =I95*I91 -> 0 | J94: =J95*J91 -> 0 | K94: =K95*K91 -> 0 | L94: =L95*L91 -> 0
B95: % tax rate | E95: =E94/E91 -> 0.22883021 | F95: =F94/F91 -> 0.2251913 | G95: =G94/G91 -> 0.23277234
B97: Net income | E97: =IS!T47 -> 7067 | F97: =IS!Z47 -> 6379 | G97: =IS!AF47 -> 6747 | H97: =H91-H94 -> 0 | I97: =I91-I94 -> 0 | J97: =J91-J94 -> 0 | K97: =K91-K94 -> 0 | L97: =L91-L94 -> 0
B98: % of sales | E98: =E97/E59 -> 0.2841005 | F98: =F97/F59 -> 0.26448029 | G98: =G97/G59 -> 0.2782268 | H98: =H97/H59 -> #DIV/0! | I98: =I97/I59 -> #DIV/0! | J98: =J97/J59 -> #DIV/0! | K98: =K97/K59 -> #DIV/0! | L98: =L97/L59 -> #DIV/0!
A100: x | B100: Balance Sheet | E100: =E57 -> 2022 | F100: =F57 -> 2023 | G100: =G57 -> 2024 | H100: =H57 -> 2025 | I100: =I57 -> 2026 | J100: =J57 -> 2027 | K100: =K57 -> 2028 | L100: =L57 -> 2029
B102: Accounts Receivable | E102: =FCFF!H70 -> 1891 | F102: =FCFF!N70 -> 2073 | G102: =FCFF!T70 -> 1894 | H102: =+H103*H59/365 -> 0 | I102: =+I103*I59/365 -> 0 | J102: =+J103*J59/365 -> 0 | K102: =+K103*K59/366 -> 0 | L102: =+L103*L59/365 -> 0
B103: days sales outstanding | E103: =FCFF!H71 -> 27.747337 | F103: =FCFF!N71 -> 31.371326 | G103: =FCFF!T71 -> 28.507629
B105: Inventory | E105: =FCFF!H73 -> 741 | F105: =FCFF!N73 -> 743 | G105: =FCFF!T73 -> 769 | H105: =+H106*H59 -> 0 | I105: =+I106*I59 -> 0 | J105: =+J106*J59 -> 0 | K105: =+K106*K59 -> 0 | L105: =+L106*L59 -> 0
B106: % of revenues | E106: =FCFF!H74 -> 0.029788945 | F106: =FCFF!N74 -> 0.030805589 | G106: =FCFF!T74 -> 0.03171134
B108: Prepaid expenses and Other Current Assets | E108: =FCFF!H76 -> 301 | F108: =FCFF!N76 -> 261 | G108: =FCFF!T76 -> 322 | H108: =+H109*H59 -> 0 | I108: =+I109*I59 -> 0 | J108: =+J109*J59 -> 0 | K108: =+K109*K59 -> 0 | L108: =+L109*L59 -> 0
B109: % of sales | E109: =FCFF!H77 -> 0.012100503 | F109: =FCFF!N77 -> 0.010821344 | G109: =FCFF!T77 -> 0.013278351
B111: Net PP&E (Property, Plant and Equipment) | E111: =FCFF!H79 -> 57710 | F111: =FCFF!N79 -> 59041 | G111: =FCFF!T79 -> 59640 | H111: =+G111-H112*H131-H80-H65 -> 59640 | I111: =+H111-I112*I131-I80-I65 -> 59640 | J111: =+I111-J112*J131-J80-J65 -> 59640 | K111: =+J111-K112*K131-K80-K65 -> 59640 | L111: =+K111-L112*L131-L80-L65 -> 59640
B112: capex allocation rate | E112: =FCFF!H80 -> 0 | F112: =FCFF!N80 -> 0 | G112: =FCFF!T80 -> 0
B114: Intangibles excl. Goodwill | E114: =FCFF!H82 -> 0 | F114: =FCFF!N82 -> 0 | G114: =FCFF!T82 -> 0 | H114: =+G114+H115*H74-(1-H112)*H131-H83 -> 0 | I114: =+H114+I115*I74-(1-I112)*I131-I83 -> 0 | J114: =+I114+J115*J74-(1-J112)*J131-J83 -> 0 | K114: =+J114+K115*K74-(1-K112)*K131-K83 -> 0 | L114: =+K114+L115*L74-(1-L112)*L131-L83 -> 0
B115: r&d conversion rate | E115: =FCFF!H83 | F115: =FCFF!N83 | G115: =FCFF!T83
B117: Accounts Payable | E117: =FCFF!H85 -> 3080 | F117: =FCFF!N85 -> 2868 | G117: =FCFF!T85 -> 2870 | H117: =+H118*H62/365 -> 0 | I117: =+I118*I62/365 -> 0 | J117: =+J118*J62/365 -> 0 | K117: =+K118*K62/366 -> 0 | L117: =+L118*L62/365 -> 0
B118: days payable outstanding | E118: =FCFF!H86 -> 0.24405705 | F118: =FCFF!N86 -> 0.22548943 | G118: =FCFF!T86 -> 0.23642804
B120: Accrued Expenses and Other Current Liabilities | E120: =FCFF!H88 -> 431 | F120: =FCFF!N88 -> 460 | G120: =FCFF!T88 -> 613 | H120: =+H121*H71 -> 0 | I120: =+I121*I71 -> 0 | J120: =+J121*J71 -> 0 | K120: =+K121*K71 -> 0 | L120: =+L121*L71 -> 0
B121: % of sg&a | E121: =FCFF!H89 -> 0.017326633 | F121: =FCFF!N89 -> 0.019072101 | G121: =FCFF!T89 -> 0.025278351
A123: x | B123: Cash Flow | E123: =E57 -> 2022 | F123: =F57 -> 2023 | G123: =G57 -> 2024 | H123: =H57 -> 2025 | I123: =I57 -> 2026 | J123: =J57 -> 2027 | K123: =K57 -> 2028 | L123: =L57 -> 2029
B125: D&A (Depreciation & Amortization) | E125: =FCFF!H94 -> 2246 | F125: =FCFF!N94 -> 2318 | G125: =FCFF!T94 -> 2398 | H125: =+H77+H65 -> 0 | I125: =+I77+I65 -> 0 | J125: =+J77+J65 -> 0 | K125: =+K77+K65 -> 0 | L125: =+L77+L65 -> 0
B126: % of net pp&e and intangibles excl. Goodwill | E126: =FCFF!H95 -> 0.038918732 | F126: =FCFF!N95 -> 0.039260853 | G126: =FCFF!T95 -> 0.040207914 | H126: =+H125/(H111+H114) -> 0 | I126: =+I125/(I111+I114) -> 0 | J126: =+J125/(J111+J114) -> 0 | K126: =+K125/(K111+K114) -> 0 | L126: =+L125/(L111+L114) -> 0
B128: Changes in Net Working Capital | E128: =FCFF!H103 -> 8 | F128: =FCFF!N103 -> -303 | G128: =FCFF!T103 -> 186 | H128: =-((H102+H105+H108-H117-H120)-(G102+G105+G108-G117-G120)) -> -498 | I128: =-((I102+I105+I108-I117-I120)-(H102+H105+H108-H117-H120)) -> 0 | J128: =-((J102+J105+J108-J117-J120)-(I102+I105+I108-I117-I120)) -> 0 | K128: =-((K102+K105+K108-K117-K120)-(J102+J105+J108-J117-J120)) -> 0 | L128: =-((L102+L105+L108-L117-L120)-(K102+K105+K108-K117-K120)) -> 0
B129: % of change in sales | E129: =FCFF!H104 -> 0.00036690516 | F129: =FCFF!N104 -> -0.012180905 | G129: =FCFF!T104 -> 0.0077117625 | H129: =H128/(H59-G59) -> 0.020536082 | I129: =I128/(I59-H59) -> #DIV/0! | J129: =J128/(J59-I59) -> #DIV/0! | K129: =K128/(K59-J59) -> #DIV/0! | L129: =L128/(L59-K59) -> #DIV/0!
B131: Net CapEx | E131: =FCFF!H106+FCFF!H109 -> -3426 | F131: =FCFF!N106+FCFF!N109 -> -3606 | G131: =FCFF!T106+FCFF!T109 -> -3452 | H131: =-H132*H59 -> 0 | I131: =-I132*I59 -> 0 | J131: =-J132*J59 -> 0 | K131: =-K132*K59 -> 0 | L131: =-L132*L59 -> 0
B132: % of sales | E132: =FCFF!H107 -> 0.14552764 | F132: =FCFF!N107 -> 0.14950869 | G132: =FCFF!T107 -> 0.14235052
A134: x | B134: Levered Free Cash Flow | H134: =H57 -> 2025 | I134: =I57 -> 2026 | J134: =J57 -> 2027 | K134: =K57 -> 2028 | L134: =L57 -> 2029
B136: Net Income | H136: =H97 -> 0 | I136: =I97 -> 0 | J136: =J97 -> 0 | K136: =K97 -> 0 | L136: =L97 -> 0
B137: Changes in NWC | H137: =+H125 -> 0 | I137: =+I125 -> 0 | J137: =+J125 -> 0 | K137: =+K125 -> 0 | L137: =+L125 -> 0
B138: D&A (Depreciation & Amortization) | H138: =+H128 -> -498 | I138: =+I128 -> 0 | J138: =+J128 -> 0 | K138: =+K128 -> 0 | L138: =+L128 -> 0
B139: Net CapEx | H139: =+H131 -> 0 | I139: =+I131 -> 0 | J139: =+J131 -> 0 | K139: =+K131 -> 0 | L139: =+L131 -> 0
B140: Leveraged Free Cash Flow | H140: =H136+H137+H138+H139 -> -498 | I140: =I136+I137+I138+I139 -> 0 | J140: =J136+J137+J138+J139 -> 0 | K140: =K136+K137+K138+K139 -> 0 | L140: =L136+L137+L138+L139 -> 0
A142: x | B142: Debt Schedule | H142: =H134 -> 2025 | I142: =I134 -> 2026 | J142: =J134 -> 2027 | K142: =K134 -> 2028 | L142: =L134 -> 2029
B144: Revolver
B145: Beginning Balance | H145: =G148 -> 0 | I145: =H148 -> 498 | J145: =I148 -> 498 | K145: =J148 -> 498 | L145: =K148 -> 498
B146: Interest | H146: =H145*$J$11 -> 0 | I146: =I145*$J$11 -> 0 | J146: =J145*$J$11 -> 0 | K146: =K145*$J$11 -> 0 | L146: =L145*$J$11 -> 0
B147: Paydown | H147: =MIN(H140,H145) -> -498 | I147: =MIN(I140,I145) -> 0 | J147: =MIN(J140,J145) -> 0 | K147: =MIN(K140,K145) -> 0 | L147: =MIN(L140,L145) -> 0
B148: Ending Balance | G148: =L11 -> 0 | H148: =H145-H147 -> 498 | I148: =I145-I147 -> 498 | J148: =J145-J147 -> 498 | K148: =K145-K147 -> 498 | L148: =L145-L147 -> 498
B150: Bank Loan
B151: Beginning Balance | H151: =G154 -> 0 | I151: =H154 -> 0 | J151: =I154 -> 0 | K151: =J154 -> 0 | L151: =K154 -> 0
B152: Interest | H152: =H151*$J$12 -> 0 | I152: =I151*$J$12 -> 0 | J152: =J151*$J$12 -> 0 | K152: =K151*$J$12 -> 0 | L152: =L151*$J$12 -> 0
B153: Paydown | H153: =MIN(H151,H140-H147) -> 0 | I153: =MIN(I151,I140-I147) -> 0 | J153: =MIN(J151,J140-J147) -> 0 | K153: =MIN(K151,K140-K147) -> 0 | L153: =MIN(L151,L140-L147) -> 0
B154: Ending Balance | G154: =L12 -> 0 | H154: =H151-H153 -> 0 | I154: =I151-I153 -> 0 | J154: =J151-J153 -> 0 | K154: =K151-K153 -> 0 | L154: =L151-L153 -> 0
B156: Senior Note
B157: Beginning Balance | H157: =G160 -> 0 | I157: =H160 -> 0 | J157: =I160 -> 0 | K157: =J160 -> 0 | L157: =K160 -> 0
B158: Interest | H158: =H157*$J$13 -> 0 | I158: =I157*$J$13 -> 0 | J158: =J157*$J$13 -> 0 | K158: =K157*$J$13 -> 0 | L158: =L157*$J$13 -> 0
B159: Paydown | H159: =MIN(H157,H140-H147-H153) -> 0 | I159: =MIN(I157,I140-I147-I153) -> 0 | J159: =MIN(J157,J140-J147-J153) -> 0 | K159: =MIN(K157,K140-K147-K153) -> 0 | L159: =MIN(L157,L140-L147-L153) -> 0
B160: Ending Balance | G160: =L13 -> 0 | H160: =H157-H159 -> 0 | I160: =I157-I159 -> 0 | J160: =J157-J159 -> 0 | K160: =K157-K159 -> 0 | L160: =L157-L159 -> 0
B162: Total Debt
B163: Beginning Balance | H163: =H145+H151+H157 -> 0 | I163: =I145+I151+I157 -> 498 | J163: =J145+J151+J157 -> 498 | K163: =K145+K151+K157 -> 498 | L163: =L145+L151+L157 -> 498
B164: Interest | H164: =H146+H152+H158 -> 0 | I164: =I146+I152+I158 -> 0 | J164: =J146+J152+J158 -> 0 | K164: =K146+K152+K158 -> 0 | L164: =L146+L152+L158 -> 0
...

Sheet Sensitivity
B7: Monte-Carlo Simulations | R7: Tornado Chart – Effect on Price Target
AD28: {=_xlfn.SORTBY(R38:Z44,Z38:Z44,1)} -> WACC | AE28: 0 | AF28: 0.005 | AG28: 0 | AH28: 167.05365 | AI28: 187.91713 | AJ28: -12.999921 | AK28: 7.8635637 | AL28: 12.999921
AD29: Capex Intensity | AE29: 0 | AF29: 0.02 | AG29: 0 | AH29: 165.20161 | AI29: 177.91214 | AJ29: -14.85196 | AK29: -2.1414272 | AL29: 14.85196
AD30: EBITDA Exit | AE30: 0 | AF30: 1.5 | AG30: 0 | AH30: 167.05365 | AI30: 200.43804 | AJ30: -12.999921 | AK30: 20.384468 | AL30: 20.384468
AD31: Revenue Exit | AE31: 0 | AF31: 1.5 | AG31: 0 | AH31: 180.05357 | AI31: 203.58085 | AJ31: 0 | AK31: 23.527283 | AL31: 23.527283
R32: Reference Price Target | V32: Base Price Target | Z32: Reference | AD32: Terminal g | AE32: 0 | AF32: 0.005 | AG32: 0 | AH32: 167.05365 | AI32: 212.41949 | AJ32: -12.999921 | AK32: 32.365917 | AL32: 32.365917
R33: Gordon PT | T33: =+FCFF!AL169 -> 188.76742 | V33: Base Gordon PT | X33: 187.91713 | Z33: EBITDA | AD33: COGS Margin | AE33: 0 | AF33: 0 | AG33: 0 | AH33: 0 | AI33: 0 | AJ33: -180.05357 | AK33: -180.05357 | AL33: 180.05357
R34: EBITDA PT | T34: =+FCFF!Z169 -> 180.87326 | V34: Base EBITDA PT | X34: 180.05357 | AD34: SG&A Margin | AE34: 0 | AF34: 0 | AG34: 0 | AH34: 0 | AI34: 0 | AJ34: -180.05357 | AK34: -180.05357 | AL34: 180.05357
R35: Revenue PT | T35: =FCFF!AF169 -> 167.82275 | V35: Base Revenue PT | X35: 167.05365
AB36: \
T37: Δ | U37: Δ Applied | V37: PT Low | W37: PT High | X37: Δ Low | Y37: Δ High | Z37: Max
R38: Capex Intensity | T38: 0.02 | V38: 165.20161 | W38: 177.91214 | X38: {=+V38-_xlfn.IFS($Z$33="EBITDA",$X$34,$Z$33="Revenue",$X$35,$Z$33="Gordon",$X$33)} -> -14.85196 | Y38: {=+W38-_xlfn.IFS($Z$33="EBITDA",$X$34,$Z$33="Revenue",$X$35,$Z$33="Gordon",$X$33)} -> -2.1414272 | Z38: =MAX(ABS(X38),ABS(Y38)) -> 14.85196
R39: COGS Margin | X39: {=+V39-_xlfn.IFS($Z$33="EBITDA",$X$34,$Z$33="Revenue",$X$35,$Z$33="Gordon",$X$33)} -> -180.05357 | Y39: {=+W39-_xlfn.IFS($Z$33="EBITDA",$X$34,$Z$33="Revenue",$X$35,$Z$33="Gordon",$X$33)} -> -180.05357 | Z39: =MAX(ABS(X39),ABS(Y39)) -> 180.05357
R40: SG&A Margin | X40: {=+V40-_xlfn.IFS($Z$33="EBITDA",$X$34,$Z$33="Revenue",$X$35,$Z$33="Gordon",$X$33)} -> -180.05357 | Y40: {=+W40-_xlfn.IFS($Z$33="EBITDA",$X$34,$Z$33="Revenue",$X$35,$Z$33="Gordon",$X$33)} -> -180.05357 | Z40: =MAX(ABS(X40),ABS(Y40)) -> 180.05357
R41: WACC | T41: 0.005 | V41: 167.05365 | W41: 187.91713 | X41: {=+V41-_xlfn.IFS($Z$33="EBITDA",$X$34,$Z$33="Revenue",$X$35,$Z$33="Gordon",$X$33)} -> -12.999921 | Y41: {=+W41-_xlfn.IFS($Z$33="EBITDA",$X$34,$Z$33="Revenue",$X$35,$Z$33="Gordon",$X$33)} -> 7.8635637 | Z41: =MAX(ABS(X41),ABS(Y41)) -> 12.999921
R42: Terminal g | T42: 0.005 | V42: 167.05365 | W42: 212.41949 | X42: {=+V42-_xlfn.IFS($Z$33="EBITDA",$X$34,$Z$33="Revenue",$X$35,$Z$33="Gordon",$X$33)} -> -12.999921 | Y42: {=+W42-_xlfn.IFS($Z$33="EBITDA",$X$34,$Z$33="Revenue",$X$35,$Z$33="Gordon",$X$33)} -> 32.365917 | Z42: =MAX(ABS(X42),ABS(Y42)) -> 32.365917
H43: VaR | R43: EBITDA Exit | T43: 1.5 | V43: 167.05365 | W43: 200.43804 | X43: {=+V43-_xlfn.IFS($Z$33="EBITDA",$X$34,$Z$33="Revenue",$X$35,$Z$33="Gordon",$X$33)} -> -12.999921 | Y43: {=+W43-_xlfn.IFS($Z$33="EBITDA",$X$34,$Z$33="Revenue",$X$35,$Z$33="Gordon",$X$33)} -> 20.384468 | Z43: =MAX(ABS(X43),ABS(Y43)) -> 20.384468
D44: Historical VaR for UNP: | R44: Revenue Exit | T44: 1.5 | V44: 180.05357 | W44: 203.58085 | X44: {=+V44-_xlfn.IFS($Z$33="EBITDA",$X$34,$Z$33="Revenue",$X$35,$Z$33="Gordon",$X$33)} -> 0 | Y44: {=+W44-_xlfn.IFS($Z$33="EBITDA",$X$34,$Z$33="Revenue",$X$35,$Z$33="Gordon",$X$33)} -> 23.527283 | Z44: =MAX(ABS(X44),ABS(Y44)) -> 23.527283
D45: Confidence Level 95.0%: | H45: -0.0204
D46: Confidence Level 99.0%: | H46: -0.0447
D49: Parametric VaR for UNP:
D50: Confidence Level 95.0%: | H50: -0.02475041201637026
D51: Confidence Level 99.0%: | H51: -0.03510351834824588
D53: Monte Carlos VaR for UNP:
D54: Confidence Level 95.0%: | H54: 0.27516547692197724
D55: Confidence Level 99.0%: | H55: 0.18853451908821353

Sheet IS
B7: Income Statement | D7: 2020 | E7: 2020 | F7: 2020 | G7: 2020 | H7: 2020 | J7: 2021 | K7: 2021 | L7: 2021 | M7: 2021 | N7: 2021 | P7: 2022 | Q7: 2022 | R7: 2022 | S7: 2022 | T7: 2022 | V7: 2023 | W7: 2023 | X7: 2023 | Y7: 2023 | Z7: 2023 | AB7: 2024 | AC7: 2024 | AD7: 2024 | AE7: 2024 | AF7: 2024 | AH7: 2025 | AI7: 2025 | AJ7: 2025 | AK7: 2025 | AL7: 2025 | AN7: 2025 | AO7: 2025 | AP7: 2025 | AQ7: 2025 | AR7: 2025
D8: 2020 | J8: 2021 | P8: 2022 | V8: 2023 | AB8: 2024 | AH8: 2025 | AN8: 2026 | AT8: 2027 | AV8: 2028 | AX8: 2029
D9: Q1 | E9: Q2 | F9: Q3 | G9: Q4 | H9: FY | J9: Q1 | K9: Q2 | L9: Q3 | M9: Q4 | N9: FY | P9: Q1 | Q9: Q2 | R9: Q3 | S9: Q4 | T9: FY | V9: Q1 | W9: Q2 | X9: Q3 | Y9: Q4 | Z9: FY | AB9: Q1 | AC9: Q2 | AD9: Q3 | AE9: Q4 | AF9: FY | AH9: Q1 | AI9: Q2 | AJ9: Q3 | AK9: Q4 | AL9: FY | AN9: Q1 | AO9: Q2 | AP9: Q3 | AQ9: Q4 | AR9: FY | AT9: FY | AV9: FY | AX9: FY
B12: Revenue:
B13: Segment 1
B14: Segment 2
B15: Segment 3
B16: Segment 4
B17: Segment 5
B18: Total revenue | D18: 5229 | E18: 4244 | F18: 4919 | G18: 5141 | H18: 19533 | J18: 5001 | K18: 5504 | L18: 5566 | M18: 5733 | N18: 21804 | P18: 5860 | Q18: 6269 | R18: 6566 | S18: 6180 | T18: 24875 | V18: 6056 | W18: 5963 | X18: 5941 | Y18: 6159 | Z18: 24119 | AB18: 6031 | AC18: 6007 | AD18: 6091 | AE18: 6121 | AF18: 24250 | AH18: 6027 | AI18: 6154
A20: x | B20: Cost of revenue:
B21: Cost of goods and services | D21: 0 | E21: 0 | F21: 0 | G21: 0 | H21: 0 | J21: 0 | K21: 0 | L21: 0 | M21: 0 | N21: 0 | P21: 0 | Q21: 0 | R21: 0 | S21: 0 | AH21: 0 | AI21: 0
B22: Depreciation & amortization | D22: 0 | E22: 0 | F22: 0 | G22: 0 | H22: 0 | J22: 0 | K22: 0 | L22: 0 | M22: 0 | N22: 0 | P22: 0 | Q22: 0 | R22: 0 | S22: 0 | T22: 0 | V22: 0 | W22: 0 | X22: 0 | Y22: 0 | Z22: 0 | AB22: 0 | AC22: 0 | AD22: 0 | AE22: 0 | AF22: 0 | AH22: 0 | AI22: 0
B23: Total cost of revenue | D23: 0 | E23: 0 | F23: 0 | G23: 0 | H23: 0 | J23: 0 | K23: 0 | L23: 0 | M23: 0 | N23: 0 | P23: 0 | Q23: 0 | R23: 0 | S23: 0 | T23: 0 | V23: 0 | W23: 0 | X23: 0 | Y23: 0 | Z23: 0 | AB23: 0 | AC23: 0 | AD23: 0 | AE23: 0 | AF23: 0 | AH23: 0 | AI23: 0
B24: Gross margin | D24: =D18 -> 5229 | E24: =E18 -> 4244 | F24: =F18 -> 4919 | G24: =G18 -> 5141 | H24: =H18-H21 -> 19533 | J24: =J18 -> 5001 | K24: =K18 -> 5504 | L24: =L18 -> 5566 | M24: =M18 -> 5733 | N24: =N18-N21 -> 21804 | P24: =P18 -> 5860 | Q24: =Q18 -> 6269 | R24: =R18 -> 6566 | S24: =S18 -> 6180 | T24: =T18-T21 -> 24875 | V24: =V18 -> 6056 | W24: =W18 -> 5963 | X24: =X18 -> 5941 | Y24: =Y18 -> 6159 | Z24: =Z18-Z21 -> 24119 | AB24: =AB18 -> 6031 | AC24: =AC18 -> 6007 | AD24: =AD18 -> 6091 | AE24: =AE18 -> 6121 | AF24: =AF18-AF21 -> 24250 | AH24: =AH18 -> 6027 | AI24: =AI18 -> 6154
A26: x | B26: Operating expenses:
B27: Selling, general and administrative | D27: 0 | E27: 0 | F27: 0 | G27: 0 | H27: 0 | J27: 0 | K27: 0 | L27: 0 | M27: 0 | N27: 0 | P27: 0 | Q27: 0 | R27: 0 | S27: 0 | T27: 0 | V27: 0 | W27: 0 | X27: 0 | Y27: 0 | Z27: 0 | AB27: 0 | AC27: 0 | AD27: 0 | AE27: 0 | AF27: 0 | AH27: 0 | AI27: 0
B28: Depreciation and amortization | D28: 547 | E28: 551 | F28: 555 | G28: 557 | H28: 2210 | J28: 549 | K28: 550 | L28: 553 | M28: 556 | N28: 2208 | P28: 555 | Q28: 559 | R28: 563 | S28: 569 | T28: 2246 | V28: 572 | W28: 577 | X28: 580 | Y28: 589 | Z28: 2318 | AB28: 594 | AC28: 596 | AD28: 602 | AE28: 606 | AF28: 2398 | AH28: 610 | AI28: 613
B29: Research and development | D29: 0 | E29: 0 | F29: 0 | G29: 0 | H29: 0 | J29: 0 | K29: 0 | L29: 0 | M29: 0 | N29: 0 | P29: 0 | Q29: 0 | R29: 0 | S29: 0 | T29: 0 | V29: 0 | W29: 0 | X29: 0 | Y29: 0 | Z29: 0 | AB29: 0 | AC29: 0 | AD29: 0 | AE29: 0 | AF29: 0 | AH29: 0 | AI29: 0
B30: Other operating expenses | D30: 2539 | E30: 2108 | F30: 2333 | G30: 2300 | H30: 9280 | J30: 2459 | K30: 2481 | L30: 2581 | M30: 2737 | N30: 10258 | P30: 2928 | Q30: 3215 | R30: 3256 | S30: 3221 | T30: =12620-T21 -> 12620 | V30: 3190 | W30: 3182 | X30: 3184 | Y30: 3163 | Z30: =12719-Z21 -> 12719 | AB30: 3065 | AC30: 3011 | AD30: 3073 | AE30: 2990 | AF30: =12139-AF21 -> 12139 | AH30: 3046 | AI30: 3016
B31: Total operating expenses | D31: 3086 | E31: 2659 | F31: 2888 | G31: 2857 | H31: 11490 | J31: 3008 | K31: 3031 | L31: 3134 | M31: 3293 | N31: 12466 | P31: 3483 | Q31: 3774 | R31: 3819 | S31: 3790 | T31: 14866 | V31: 3762 | W31: 3759 | X31: 3764 | Y31: 3752 | Z31: 15037 | AB31: 3659 | AC31: 3607 | AD31: 3675 | AE31: 3596 | AF31: 14537 | AH31: 3656 | AI31: 3629
B32: Other operating income | D32: 0 | E32: 0 | F32: 0 | G32: 0 | H32: 0 | J32: 0 | K32: 0 | L32: 0 | M32: 0 | N32: 0 | P32: 0 | Q32: 0 | R32: 0 | S32: 0 | T32: 0 | V32: 0 | W32: 0 | X32: 0 | Y32: 0 | Z32: 0 | AB32: 0 | AC32: 0 | AD32: 0 | AE32: 0 | AF32: 0 | AH32: 0 | AI32: 0
B33: Operating income | D33: 2143 | E33: 1585 | F33: 2031 | G33: 2284 | H33: 8043 | J33: 1993 | K33: 2473 | L33: 2432 | M33: 2440 | N33: 9338 | P33: 2377 | Q33: 2495 | R33: 2747 | S33: 2390 | T33: 10009 | V33: 2294 | W33: 2204 | X33: 2177 | Y33: 2407 | Z33: 9082 | AB33: 2372 | AC33: 2400 | AD33: 2416 | AE33: 2525 | AF33: 9713 | AH33: 2371 | AI33: 2525
A35: x | B35: Non-operating (income) loss:
B36: Interest expense | D36: 278 | E36: 289 | F36: 295 | G36: 279 | H36: 1141 | J36: 290 | K36: 282 | L36: 290 | M36: 295 | N36: 1157 | P36: 307 | Q36: 316 | R36: 315 | S36: 333 | T36: 1271 | V36: 336 | W36: 339 | X36: 334 | Y36: 331 | Z36: 1340 | AB36: 324 | AC36: 319 | AD36: 314 | AE36: 312 | AF36: 1269 | AH36: 322 | AI36: 335
B37: Interest income | D37: 6 | E37: 3 | F37: 2 | G37: 1 | H37: 12 | J37: 1 | K37: 1 | L37: 0 | M37: 1 | N37: 5 | P37: 0 | Q37: 0 | R37: 0 | S37: 0 | T37: 0 | V37: 0 | W37: 0 | X37: 0 | Y37: 0 | Z37: 0 | AB37: 0 | AC37: 0 | AD37: 0 | AE37: 0 | AF37: 0 | AH37: 0 | AI37: 0
A38: x | B38: Net interest (income) expense | D38: 272 | E38: 286 | F38: 293 | G38: 278 | H38: 1129 | J38: 289 | K38: 281 | L38: 290 | M38: 294 | N38: 1152 | P38: 0 | Q38: 0 | R38: 0 | S38: 0 | T38: 0 | V38: 0 | W38: 0 | X38: 0 | Y38: 0 | Z38: 1340 | AB38: 0 | AC38: 0 | AD38: 0 | AE38: 0 | AF38: 1269 | AH38: 0 | AI38: 0
B39: Foreign exchange (gains) losses | D39: 0 | E39: 0 | F39: 0 | G39: 0 | H39: 0 | J39: 0 | K39: 0 | L39: 0 | M39: 0 | N39: 0 | P39: 0 | Q39: 0 | R39: 0 | S39: 0 | T39: 0 | V39: 0 | W39: 0 | X39: 0 | Y39: 0 | Z39: 0 | AB39: 0 | AC39: 0 | AD39: 0 | AE39: 0 | AF39: 0 | AH39: 0 | AI39: 0
B40: Other non-operating (income) expenses | D40: -36 | E40: -45 | F40: -32 | G40: -47 | H40: -275 | J40: -50 | K40: -41 | L40: -38 | M40: -40 | N40: -158 | P40: 260 | Q40: 251 | R40: 191 | S40: 241 | T40: 845 | V40: 152 | W40: 246 | X40: 228 | Y40: 223 | Z40: -491 | AB40: 232 | AC40: 216 | AD40: 227 | AE40: 244 | AF40: -350 | AH40: 244 | AI40: 212
B41: Total non-operating expenses | D41: 236 | E41: 241 | F41: 261 | G41: 231 | H41: 854 | J41: 239 | K41: 240 | L41: 252 | M41: 254 | N41: 994 | P41: 260 | Q41: 251 | R41: 191 | S41: 241 | T41: 845 | V41: 152 | W41: 246 | X41: 228 | Y41: 223 | Z41: 849 | AB41: 232 | AC41: 216 | AD41: 227 | AE41: 244 | AF41: 919 | AH41: 244 | AI41: 212
B42: Pre-tax income | D42: 1907 | E42: 1344 | F42: 1770 | G42: 2053 | H42: 7189 | J42: 1754 | K42: 2233 | L42: 2180 | M42: 2186 | N42: 8344 | P42: 2117 | Q42: 2244 | R42: 2556 | S42: 2149 | T42: 9164 | V42: 2142 | W42: 1958 | X42: 1949 | Y42: 2184 | Z42: 8233 | AB42: 2140 | AC42: 2184 | AD42: 2189 | AE42: 2281 | AF42: 8794 | AH42: 2127 | AI42: 2313
A44: x | B44: Tax & net income:
B45: Income tax expenses (benefits) | D45: 441.69 | E45: 259.544 | F45: 409.37 | G45: 478.22 | H45: 1678.537 | J45: 413 | K45: 500.57 | L45: 507 | M45: 508.18 | N45: 1926.86 | P45: 487 | Q45: 486.42 | R45: 575 | S45: 528 | T45: 2097 | V45: 512 | W45: 389 | X45: 421 | Y45: 532 | Z45: 1854 | AB45: 499 | AC45: 511 | AD45: 518 | AE45: 519 | AF45: 2047 | AH45: 501 | AI45: 437
B46: Net extraordinary losses (gains) | D46: 0 | E46: 0 | F46: 0 | G46: 0 | H46: 0 | J46: 0 | K46: 0 | L46: 0 | M46: 0 | N46: 0 | P46: 0 | Q46: 0 | R46: 0 | S46: 0 | T46: 0 | V46: 0 | W46: 0 | X46: 0 | Y46: 0 | Z46: 0 | AB46: 0 | AC46: 0 | AD46: 0 | AE46: 0 | AF46: 0 | AH46: 0 | AI46: 0
B47: Net income including minority interest | D47: 1465.31 | E47: 1084.456 | F47: 1360.63 | G47: 1574.78 | H47: 5510.463 | J47: 1341 | K47: 1732.43 | L47: 1673 | M47: 1677.82 | N47: 6417.14 | P47: 1630 | Q47: 1757.58 | R47: 1981 | S47: 1621 | T47: 7067 | V47: 1630 | W47: 1569 | X47: 1528 | Y47: 1652 | Z47: 6379 | AB47: 1641 | AC47: 1673 | AD47: 1671 | AE47: 1762 | AF47: 6747 | AH47: 1626 | AI47: 1876
A49: x | B49: Attribution:
B50: Preferred dividends | D50: 0 | E50: 0 | F50: 0 | G50: 0 | H50: 0 | J50: 0 | K50: 0 | L50: 0 | M50: 0 | N50: 0 | P50: 0 | Q50: 0 | R50: 0 | S50: 0 | T50: 0 | V50: 0 | W50: 0 | X50: 0 | Y50: 0 | Z50: 0 | AB50: 0 | AC50: 0 | AD50: 0 | AE50: 0 | AF50: 0 | AH50: 0 | AI50: 0
B51: Income attributable to non-controlling interests | D51: 0 | E51: 0 | F51: 0 | G51: 0 | H51: 0 | J51: 0 | K51: 0 | L51: 0 | M51: 0 | N51: 0 | P51: 0 | Q51: 0 | R51: 0 | S51: 0 | T51: 0 | V51: 0 | W51: 0 | X51: 0 | Y51: 0 | Z51: 0 | AB51: 0 | AC51: 0 | AD51: 0 | AE51: 0 | AF51: 0 | AH51: 0 | AI51: 0
B52: Net income attributable to common shareholders | D52: 1465.31 | E52: 1084.456 | F52: 1360.63 | G52: 1574.78 | H52: 5510.463 | J52: 1341 | K52: 1732.43 | L52: 1673 | M52: 1677.82 | N52: 6417.14 | P52: 1630 | Q52: 1757.58 | R52: 1981 | S52: 1621 | T52: 7067 | V52: 1630 | W52: 1569 | X52: 1528 | Y52: 1652 | Z52: 6379 | AB52: 1641 | AC52: 1673 | AD52: 1671 | AE52: 1762 | AF52: 6747 | AH52: 1626 | AI52: 1876
A54: x | B54: Earnings per share:
B55: EPS basic | D55: 2.1413 | E55: 1.6002 | F55: 2.0157 | G55: 2.3427 | H55: 8.1359 | J55: 2.01 | K55: 2.6309 | L55: 2.58 | M55: 2.62 | N55: 9.8151 | P55: 2.58 | Q55: 2.8094 | R55: 3.1931 | S55: 2.6457 | T55: 11.349 | V55: 2.67 | W55: 2.58 | X55: 2.51 | Y55: 2.71 | Z55: 10.47 | AB55: 2.69 | AC55: 2.75 | AD55: 2.75 | AE55: 2.92 | AF55: 11.1 | AH55: 2.71 | AI55: 3.16
B56: EPS diluted | D56: 2.1373 | E56: 1.6 | F56: 2.0065 | G56: 2.3389 | H56: 8.1178 | J56: 2 | K56: 2.6207 | L56: 2.57 | M56: 2.6083 | N56: 9.7885 | P56: 2.57 | Q56: 2.8065 | R56: 3.1884 | S56: 2.6423 | T56: 11.3206 | V56: 2.67 | W56: 2.57 | X56: 2.51 | Y56: 2.71 | Z56: 10.45 | AB56: 2.69 | AC56: 2.74 | AD56: 2.75 | AE56: 2.91 | AF56: 11.09 | AH56: 2.7 | AI56: 3.15
A58: x | B58: Shares used in computing earnings per share:
B59: Basic weighted average shares | D59: 684.3 | E59: 677.7 | F59: 675 | G59: 672.2 | H59: 677.3 | J59: 667.6 | K59: 658.5 | L59: 648.7 | M59: 640.4 | N59: 653.8 | P59: 632.2 | Q59: 625.6 | R59: 620.4 | S59: 612.7 | T59: 622.7 | V59: 610.6 | W59: 608.7 | X59: 608.7 | Y59: 608.9 | Z59: 609.2 | AB59: 609.2 | AC59: 609.4 | AD59: 607.6 | AE59: 604.2 | AF59: 607.6 | AH59: 601 | AI59: 594.1
B60: Diluted weighted average shares | D60: 686.2 | E60: 679.2 | F60: 676.8 | G60: 674.1 | H60: 679.1 | J60: 669.2 | K60: 660.1 | L60: 650.3 | M60: 642.1 | N60: 655.4 | P60: 633.6 | Q60: 626.8 | R60: 621.5 | S60: 613.7 | T60: 624 | V60: 611.5 | W60: 609.5 | X60: 609.8 | Y60: 609.9 | Z60: 610.2 | AB60: 610.2 | AC60: 610.3 | AD60: 608.6 | AE60: 605.2 | AF60: 608.6 | AH60: 601.9 | AI60: 594.8
B62: Additional Items
B64: Depreciation (from opex)
B65: Amortization (form opex)

Sheet BS
AH1: 0
B7: Balance Sheet | D7: 2020 | E7: 2020 | F7: 2020 | G7: 2020 | H7: 2020 | J7: 2021 | K7: 2021 | L7: 2021 | M7: 2021 | N7: 2021 | P7: 2022 | Q7: 2022 | R7: 2022 | S7: 2022 | T7: 2022 | V7: 2023 | W7: 2023 | X7: 2023 | Y7: 2023 | Z7: 2023 | AB7: 2024 | AC7: 2024 | AD7: 2024 | AE7: 2024 | AF7: 2024 | AH7: 2025 | AI7: 2025 | AJ7: 2025 | AK7: 2025 | AL7: 2025 | AN7: 2025 | AO7: 2025 | AP7: 2025 | AQ7: 2025 | AR7: 2025
D8: 2020 | J8: 2021 | P8: 2022 | V8: 2023 | AB8: 2024 | AH8: 2025 | AN8: 2026 | AT8: 2027 | AV8: 2028 | AX8: 2029
D9: Q1 | E9: Q2 | F9: Q3 | G9: Q4 | H9: FY | J9: Q1 | K9: Q2 | L9: Q3 | M9: Q4 | N9: FY | P9: Q1 | Q9: Q2 | R9: Q3 | S9: Q4 | T9: FY | V9: Q1 | W9: Q2 | X9: Q3 | Y9: Q4 | Z9: FY | AB9: Q1 | AC9: Q2 | AD9: Q3 | AE9: Q4 | AF9: FY | AH9: Q1 | AI9: Q2 | AJ9: Q3 | AK9: Q4 | AL9: FY | AN9: Q1 | AO9: Q2 | AP9: Q3 | AQ9: Q4 | AR9: FY | AT9: FY | AV9: FY | AX9: FY
B12: Assets
A14: x | B14: Current assets:
B15: Cash & cash equivalents & short-term investments | D15: 1190 | E15: 2766 | F15: 2661 | G15: 1859 | H15: 1859 | J15: 1243 | K15: 1161 | L15: 1240 | M15: 1006 | N15: 1006 | P15: 955 | Q15: 834 | R15: 1313 | S15: 1019 | T15: 1019 | V15: 1079 | W15: 830 | X15: 766 | Y15: 1071 | Z15: 1071 | AB15: 945 | AC15: 1157 | AD15: 967 | AE15: 1036 | AF15: 1036 | AH15: 1411 | AI15: 1060 | AJ15: 0
B16: Cash & cash equivalents | D16: 60 | E16: 60 | F16: 60 | G16: 60 | H16: 60 | J16: 60 | K16: 46 | L16: 46 | M16: 46 | N16: 46 | P16: 46 | Q16: 46 | R16: 46 | S16: 46 | T16: 46 | V16: 0 | W16: 0 | X16: 16 | Y16: 16 | Z16: 16 | AB16: 20 | AC16: 20 | AD16: 20 | AE16: 20 | AF16: 20 | AH16: 0 | AI16: 0 | AJ16: 0
B17: Short-term investments | D17: 1130 | E17: 2706 | F17: 2601 | G17: 1799 | H17: 1799 | J17: 1183 | K17: 1115 | L17: 1194 | M17: 960 | N17: 960 | P17: 909 | Q17: 788 | R17: 1267 | S17: 973 | T17: 973 | V17: 1079 | W17: 830 | X17: 750 | Y17: 1055 | Z17: 1055 | AB17: 925 | AC17: 1137 | AD17: 947 | AE17: 1016 | AF17: 1016 | AH17: 1411 | AI17: 1060 | AJ17: 0
B18: Accounts receivable | D18: 1669 | E18: 1388 | F18: 1565 | G18: 1505 | H18: 1505 | J18: 1610 | K18: 1666 | L18: 1679 | M18: 1722 | N18: 1722 | P18: 1958 | Q18: 2052 | R18: 2052 | S18: 1891 | T18: 1891 | V18: 1955 | W18: 1826 | X18: 1934 | Y18: 2073 | Z18: 2073 | AB18: 2162 | AC18: 2118 | AD18: 2036 | AE18: 1894 | AF18: 1894 | AH18: 1965 | AI18: 1915 | AJ18: 0
B19: Inventory | D19: 692 | E19: 668 | F19: 649 | G19: 638 | H19: 638 | J19: 659 | K19: 688 | L19: 664 | M19: 621 | N19: 621 | P19: 726 | Q19: 790 | R19: 794 | S19: 741 | T19: 741 | V19: 728 | W19: 742 | X19: 770 | Y19: 743 | Z19: 743 | AB19: 770 | AC19: 807 | AD19: 775 | AE19: 769 | AF19: 769 | AH19: 747 | AI19: 774 | AJ19: 0
B20: Prepaid expenses and other current assets | D20: 253 | E20: 261 | F20: 255 | G20: 212 | H20: 212 | J20: 207 | K20: 249 | L20: 227 | M20: 202 | N20: 202 | P20: 237 | Q20: 300 | R20: 246 | S20: 301 | T20: 301 | V20: 296 | W20: 354 | X20: 343 | Y20: 261 | Z20: 261 | AB20: 317 | AC20: 416 | AD20: 371 | AE20: 322 | AF20: 322 | AH20: 416 | AI20: 434 | AJ20: 0
B21: Total current assets | D21: 3804 | E21: 5083 | F21: 5130 | G21: 4214 | H21: 4214 | J21: 3719 | K21: 3764 | L21: 3810 | M21: 3551 | N21: 3551 | P21: 3876 | Q21: 3976 | R21: 4405 | S21: 3952 | T21: 3952 | V21: 4058 | W21: 3752 | X21: 3813 | Y21: 4148 | Z21: 4148 | AB21: 4194 | AC21: 4498 | AD21: 4149 | AE21: 4021 | AF21: 4021 | AH21: 4539 | AI21: 4183 | AJ21: 0
A23: x | B23: Non-current assets:
B24: Net PP&E (Property, Plant and Equipment) | D24: 55894 | E24: 55970 | F24: 56017 | G24: 55771 | H24: 55771 | J24: 55643 | K24: 55783 | L24: 55992 | M24: 56658 | N24: 56658 | P24: 56791 | Q24: 57021 | R24: 57392 | S24: 57710 | T24: 57710 | V24: 57974 | W24: 58292 | X24: 58680 | Y24: 59041 | Z24: 59041 | AB24: 59043 | AC24: 59221 | AD24: 59381 | AE24: 59640 | AF24: 59640 | AH24: 59852 | AI24: 60210 | AJ24: 0
B25: Gross PP&E (Property, Plant and Equipment) | D25: 76431 | E25: 76717 | F25: 77029 | G25: 77030 | H25: 77030 | J25: 77201 | K25: 77617 | L25: 78118 | M25: 79062 | N25: 79062 | P25: 79322 | Q25: 79779 | R25: 80444 | S25: 80927 | T25: 80927 | V25: 81541 | W25: 82162 | X25: 82802 | Y25: 83376 | Z25: 83376 | AB25: 83724 | AC25: 84114 | AD25: 84614 | AE25: 85137 | AF25: 85137 | AH25: 85700 | AI25: 86366 | AJ25: 0
B26: Accumulated Depreciation | D26: 20537 | E26: 20747 | F26: 21012 | G26: 21259 | H26: 21259 | J26: 21558 | K26: 21834 | L26: 22126 | M26: 22404 | N26: 22404 | P26: 22531 | Q26: 22758 | R26: 23052 | S26: 23217 | T26: 23217 | V26: 23567 | W26: 23870 | X26: 24122 | Y26: 24335 | Z26: 24335 | AB26: 24681 | AC26: 24893 | AD26: 25233 | AE26: 25497 | AF26: 25497 | AH26: 25848 | AI26: 26156 | AJ26: 0
B27: Intangibles | D27: 0 | E27: 0 | F27: 0 | G27: 0 | H27: 0 | J27: 0 | K27: 0 | L27: 0 | M27: 0 | N27: 0 | P27: 0 | Q27: 0 | R27: 0 | S27: 0 | T27: 0 | V27: 0 | W27: 0 | X27: 0 | Y27: 0 | Z27: 0 | AB27: 0 | AC27: 0 | AD27: 0 | AE27: 0 | AF27: 0 | AH27: 0 | AI27: 0 | AJ27: 0
B28: Goodwill | D28: 0 | E28: 0 | F28: 0 | G28: 0 | H28: 0 | J28: 0 | K28: 0 | L28: 0 | M28: 0 | N28: 0 | P28: 0 | Q28: 0 | R28: 0 | S28: 0 | T28: 0 | V28: 0 | W28: 0 | X28: 0 | Y28: 0 | Z28: 0 | AB28: 0 | AC28: 0 | AD28: 0 | AE28: 0 | AF28: 0 | AH28: 0 | AI28: 0 | AJ28: 0
B29: Intangibles excl. Goodwill | D29: 0 | E29: 0 | F29: 0 | G29: 0 | H29: 0 | J29: 0 | K29: 0 | L29: 0 | M29: 0 | N29: 0 | P29: 0 | Q29: 0 | R29: 0 | S29: 0 | T29: 0 | V29: 0 | W29: 0 | X29: 0 | Y29: 0 | Z29: 0 | AB29: 0 | AC29: 0 | AD29: 0 | AE29: 0 | AF29: 0 | AH29: 0 | AI29: 0 | AJ29: 0
B30: Other Non-Current Assets | D30: 2518 | E30: 2502 | F30: 2567 | G30: 2413 | H30: 2413 | J30: 2431 | K30: 2526 | L30: 2558 | M30: 3316 | N30: 3316 | P30: 3384 | Q30: 3443 | R30: 3546 | S30: 3787 | T30: 3787 | V30: 3936 | W30: 3989 | X30: 4047 | Y30: 3943 | Z30: 3943 | AB30: 4029 | AC30: 4098 | AD30: 4040 | AE30: 4054 | AF30: 4054 | AH30: 4101 | AI30: 4183 | AJ30: 0
B31: Total Non-Current Assets | D31: 58412 | E31: 58472 | F31: 58584 | G31: 58184 | H31: 58184 | J31: 58074 | K31: 58309 | L31: 58550 | M31: 59974 | N31: 59974 | P31: 60175 | Q31: 60464 | R31: 60938 | S31: 61497 | T31: 61497 | V31: 61910 | W31: 62281 | X31: 62727 | Y31: 62984 | Z31: 62984 | AB31: 63072 | AC31: 63319 | AD31: 63421 | AE31: 63694 | AF31: 63694 | AH31: 63953 | AI31: 64393 | AJ31: 0
B32: Total Assets | D32: 62216 | E32: 63555 | F32: 63714 | G32: 62398 | H32: 62398 | J32: 61793 | K32: 62073 | L32: 62360 | M32: 63525 | N32: 63525 | P32: 64051 | Q32: 64440 | R32: 65343 | S32: 65449 | T32: 65449 | V32: 65968 | W32: 66033 | X32: 66540 | Y32: 67132 | Z32: 67132 | AB32: 67266 | AC32: 67817 | AD32: 67570 | AE32: 67715 | AF32: 67715 | AH32: 68492 | AI32: 68576 | AJ32: 0
B34: Liabilities & shareholders' equity
A36: x | B36: Current Liabilities:
B37: Accounts payable | D37: 2317 | E37: 2517 | F37: 2029 | G37: 2191 | H37: 2191 | J37: 2436 | K37: 2336 | L37: 2281 | M37: 2542 | N37: 2542 | P37: 2936 | Q37: 2637 | R37: 3225 | S37: 3080 | T37: 3080 | V37: 2854 | W37: 2743 | X37: 2856 | Y37: 2868 | Z37: 2868 | AB37: 2995 | AC37: 2794 | AD37: 2913 | AE37: 2870 | AF37: 2870 | AH37: 3085 | AI37: 3134 | AJ37: 0
B38: Short-term borrowings | D38: 1392 | E38: 1885 | F38: 1885 | G38: 960 | H38: 960 | J38: 1565 | K38: 1110 | L38: 1835 | M38: 2074 | N38: 2074 | P38: 1559 | Q38: 2334 | R38: 1678 | S38: 1611 | T38: 1611 | V38: 2592 | W38: 1745 | X38: 1724 | Y38: 1374 | Z38: 1374 | AB38: 733 | AC38: 727 | AD38: 1652 | AE38: 1388 | AF38: 1388 | AH38: 2227 | AI38: 2522 | AJ38: 0
B39: Current portion of lease liabilities | D39: 445 | E39: 424 | F39: 403 | G39: 430 | H39: 430 | J39: 294 | K39: 297 | L39: 306 | M39: 422 | N39: 422 | P39: 305 | Q39: 314 | R39: 326 | S39: 398 | T39: 398 | V39: 344 | W39: 346 | X39: 362 | Y39: 404 | Z39: 404 | AB39: 322 | AC39: 317 | AD39: 349 | AE39: 383 | AF39: 383 | AH39: 304 | AI39: 312 | AJ39: 0
B40: Accrued expenses and other current liabilities | D40: 487 | E40: 453 | F40: 524 | G40: 592 | H40: 592 | J40: 576 | K40: 614 | L40: 689 | M40: 706 | N40: 706 | P40: 662 | Q40: 717 | R40: 483 | S40: 431 | T40: 431 | V40: 419 | W40: 415 | X40: 362 | Y40: 460 | Z40: 460 | AB40: 484 | AC40: 449 | AD40: 452 | AE40: 613 | AF40: 613 | AH40: 606 | AI40: 484 | AJ40: 0
B41: Total current liabilities | D41: 4641 | E41: 5279 | F41: 4841 | G41: 4173 | H41: 4173 | J41: 4871 | K41: 4357 | L41: 5111 | M41: 5744 | N41: 5744 | P41: 5462 | Q41: 6002 | R41: 5712 | S41: 5520 | T41: 5520 | V41: 6209 | W41: 5249 | X41: 5304 | Y41: 5106 | Z41: 5106 | AB41: 4534 | AC41: 4287 | AD41: 5366 | AE41: 5254 | AF41: 5254 | AH41: 6222 | AI41: 6452 | AJ41: 0
AI42: =+AI38+AI39+AI44+AI45 -> 33956
A43: x | B43: Non-current liabilities:
B44: Long-term borrowings | D44: 25932 | E44: 26012 | F44: 25706 | G44: 25320 | H44: 25320 | J44: 25117 | K44: 27702 | L44: 27560 | M44: 27319 | N44: 27319 | P44: 30680 | Q44: 29673 | R44: 31744 | S44: 31481 | T44: 31481 | V44: 31192 | W44: 31557 | X44: 31153 | Y44: 31047 | Z44: 31047 | AB44: 31195 | AC44: 31165 | AD44: 29761 | AE44: 29695 | AF44: 29695 | AH44: 30615 | AI44: 30291 | AJ44: 0
B45: Long-term operating lease liabilities | D45: 1772 | E45: 1747 | F45: 1667 | G45: 1623 | H45: 1623 | J45: 1171 | K45: 1256 | L45: 1262 | M45: 1673 | N45: 1673 | P45: 1291 | Q45: 1295 | R45: 1303 | S45: 1467 | T45: 1467 | V45: 1233 | W45: 1217 | X45: 1244 | Y45: 1354 | Z45: 1354 | AB45: 1016 | AC45: 988 | AD45: 934 | AE45: 997 | AF45: 997 | AH45: 758 | AI45: 831 | AJ45: 0
B46: Other non-current liabilities | D46: 13880 | E46: 14065 | F46: 14301 | G46: 14324 | H46: 14324 | J46: 14380 | K46: 14455 | L46: 14510 | M46: 14628 | N46: 14628 | P46: 14721 | Q46: 14760 | R46: 14841 | S46: 14818 | T46: 14818 | V46: 14880 | W46: 14816 | X46: 14835 | Y46: 14837 | Z46: 14837 | AB46: 14856 | AC46: 14888 | AD46: 14925 | AE46: 14879 | AF46: 14879 | AH46: 14858 | AI46: 14744 | AJ46: 0
B47: Total non-current liabilities | D47: 41584 | E47: 41824 | F47: 41674 | G47: 41267 | H47: 41267 | J47: 40668 | K47: 43413 | L47: 43332 | M47: 43620 | N47: 43620 | P47: 46692 | Q47: 45728 | R47: 47888 | S47: 47766 | T47: 47766 | V47: 47305 | W47: 47590 | X47: 47232 | Y47: 47238 | Z47: 47238 | AB47: 47067 | AC47: 47041 | AD47: 45620 | AE47: 45571 | AF47: 45571 | AH47: 46231 | AI47: 45866 | AJ47: 0
B48: Total liabilities | D48: 46225 | E48: 47103 | F48: 46515 | G48: 45440 | H48: 45440 | J48: 45539 | K48: 47770 | L48: 48443 | M48: 49364 | N48: 49364 | P48: 52154 | Q48: 51730 | R48: 53600 | S48: 53286 | T48: 53286 | V48: 53514 | W48: 52839 | X48: 52536 | Y48: 52344 | Z48: 52344 | AB48: 51601 | AC48: 51328 | AD48: 50986 | AE48: 50825 | AF48: 50825 | AH48: 52453 | AI48: 52318 | AJ48: 0
A50: x | B50: Shareholders' equity:
B51: Common equity | D51: 15991 | E51: 16452 | F51: 17199 | G51: 16958 | H51: 16958 | J51: 16254 | K51: 14303 | L51: 13917 | M51: 14161 | N51: 14161 | P51: 11897 | Q51: 12710 | R51: 11743 | S51: 12163 | T51: 12163 | V51: 12454 | W51: 13194 | X51: 14004 | Y51: 14788 | Z51: 14788 | AB51: 15665 | AC51: 16489 | AD51: 16584 | AE51: 16890 | AF51: 16890 | AH51: 16039 | AI51: 16258 | AJ51: 0
B52: Preferred equity | D52: 0 | E52: 0 | F52: 0 | G52: 0 | H52: 0 | J52: 0 | K52: 0 | L52: 0 | M52: 0 | N52: 0 | P52: 0 | Q52: 0 | R52: 0 | S52: 0 | T52: 0 | V52: 0 | W52: 0 | X52: 0 | Y52: 0 | Z52: 0 | AB52: 0 | AC52: 0 | AD52: 0 | AE52: 0 | AF52: 0 | AH52: 0 | AI52: 0 | AJ52: 0
B53: Non-controlling interest | D53: 0 | E53: 0 | F53: 0 | G53: 0 | H53: 0 | J53: 0 | K53: 0 | L53: 0 | M53: 0 | N53: 0 | P53: 0 | Q53: 0 | R53: 0 | S53: 0 | T53: 0 | V53: 0 | W53: 0 | X53: 0 | Y53: 0 | Z53: 0 | AB53: 0 | AC53: 0 | AD53: 0 | AE53: 0 | AF53: 0 | AH53: 0 | AI53: 0 | AJ53: 0
B54: Total equity | D54: 15991 | E54: 16452 | F54: 17199 | G54: 16958 | H54: 16958 | J54: 16254 | K54: 14303 | L54: 13917 | M54: 14161 | N54: 14161 | P54: 11897 | Q54: 12710 | R54: 11743 | S54: 12163 | T54: 12163 | V54: 12454 | W54: 13194 | X54: 14004 | Y54: 14788 | Z54: 14788 | AB54: 15665 | AC54: 16489 | AD54: 16584 | AE54: 16890 | AF54: 16890 | AH54: 16039 | AI54: 16258 | AJ54: 0
B55: Total liabilities and shareholders' equity | D55: 62216 | E55: 63555 | F55: 63714 | G55: 62398 | H55: 62398 | J55: 61793 | K55: 62073 | L55: 62360 | M55: 63525 | N55: 63525 | P55: 64051 | Q55: 64440 | R55: 65343 | S55: 65449 | T55: 65449 | V55: 65968 | W55: 66033 | X55: 66540 | Y55: 67132 | Z55: 67132 | AB55: 67266 | AC55: 67817 | AD55: 67570 | AE55: 67715 | AF55: 67715 | AH55: 68492 | AI55: 68576 | AJ55: 0
B57: Capitalized R&D | D57: 0 | E57: 0 | F57: 0 | G57: 0 | H57: 0 | J57: 0 | K57: 0 | L57: 0 | M57: 0 | N57: 0 | P57: 0 | Q57: 0 | R57: 0 | S57: 0 | T57: 0 | V57: 0 | W57: 0 | X57: 0 | Y57: 0 | Z57: 0 | AB57: 0 | AC57: 0 | AD57: 0 | AE57: 0 | AF57: 0 | AH57: 0 | AI57: 0 | AJ57: 0

Sheet CF
A7: x | B7: Cash Flow Statement | D7: 2020 | E7: 2020 | F7: 2020 | G7: 2020 | H7: 2020 | J7: 2021 | K7: 2021 | L7: 2021 | M7: 2021 | N7: 2021 | P7: 2022 | Q7: 2022 | R7: 2022 | S7: 2022 | T7: 2022 | V7: 2023 | W7: 2023 | X7: 2023 | Y7: 2023 | Z7: 2023 | AB7: 2024 | AC7: 2024 | AD7: 2024 | AE7: 2024 | AF7: 2024 | AH7: 2025 | AI7: 2025 | AJ7: 2025 | AK7: 2025 | AL7: 2025 | AN7: 2025 | AO7: 2025 | AP7: 2025 | AQ7: 2025 | AR7: 2025
D8: 2020 | J8: 2021 | P8: 2022 | V8: 2023 | AB8: 2024 | AH8: 2025 | AN8: 2026 | AT8: 2027 | AV8: 2028 | AX8: 2029
D9: Q1 | E9: Q2 | F9: Q3 | G9: Q4 | H9: FY | J9: Q1 | K9: Q2 | L9: Q3 | M9: Q4 | N9: FY | P9: Q1 | Q9: Q2 | R9: Q3 | S9: Q4 | T9: FY | V9: Q1 | W9: Q2 | X9: Q3 | Y9: Q4 | Z9: FY | AB9: Q1 | AC9: Q2 | AD9: Q3 | AE9: Q4 | AF9: FY | AH9: Q1 | AI9: Q2 | AJ9: Q3 | AK9: Q4 | AL9: FY | AN9: Q1 | AO9: Q2 | AP9: Q3 | AQ9: Q4 | AR9: FY | AT9: FY | AV9: FY | AX9: FY
B12: Cash and cash equivalents, beginning balances | D12: 831 | E12: 1130 | F12: 2706 | G12: 2601 | H12: 1799 | J12: 1799 | K12: 1183 | L12: 1115 | M12: 1194 | N12: 960 | P12: 960 | Q12: 909 | R12: 788 | S12: 1267 | T12: 973 | V12: 973 | W12: 1079 | X12: 830 | Y12: 750 | Z12: 1055 | AB12: 1055 | AC12: 925 | AD12: 1137 | AE12: 947 | AF12: 1016 | AH12: 1016 | AI12: 1411 | AJ12: 1060
A14: x | B14: Operating activities:
B15: Net income | D15: 1474 | E15: 1132 | F15: 1363 | G15: 1380 | H15: 5349 | J15: 1341 | K15: 1798 | L15: 1673 | M15: 1711 | N15: 6523 | P15: 1630 | Q15: 1835 | R15: 1895 | S15: 1638 | T15: 6998 | V15: 1630 | W15: 1569 | X15: 1528 | Y15: 1652 | Z15: 6379 | AB15: 1641 | AC15: 1673 | AD15: 1671 | AE15: 1762 | AF15: 6747 | AH15: 1626 | AI15: 1876 | AJ15: 0
B16: Adjustments to reconcile to cash from operations:
B17: Depreciation and amortization | D17: 547 | E17: 551 | F17: 555 | G17: 557 | H17: 2210 | J17: 549 | K17: 550 | L17: 553 | M17: 556 | N17: 2208 | P17: 555 | Q17: 559 | R17: 563 | S17: 569 | T17: 2246 | V17: 572 | W17: 577 | X17: 580 | Y17: 589 | Z17: 2318 | AB17: 594 | AC17: 596 | AD17: 602 | AE17: 606 | AF17: 2398 | AH17: 610 | AI17: 613 | AJ17: 0
B18: Stock-based compensation expense | D18: 0 | E18: 0 | F18: 0 | G18: 0 | H18: 0 | J18: 0 | K18: 0 | L18: 0 | M18: 0 | N18: 0 | P18: 0 | Q18: 0 | R18: 0 | S18: 0 | T18: 0 | V18: 0 | W18: 0 | X18: 0 | Y18: 0 | Z18: 0 | AB18: 0 | AC18: 0 | AD18: 0 | AE18: 0 | AF18: 0 | AH18: 0 | AI18: 0 | AJ18: 0
B19: Other | D19: 27 | E19: 135 | F19: 284 | G19: 269 | H19: 715 | J19: -77 | K19: 77 | L19: 122 | M19: -24 | N19: 98 | P19: 17 | Q19: 24 | R19: 46 | S19: 23 | T19: 110 | V19: -65 | W19: -25 | X19: 28 | Y19: 47 | Z19: -15 | AB19: -57 | AC19: 32 | AD19: 50 | AE19: -10 | AF19: 15 | AH19: -29 | AI19: -137 | AJ19: 0
B20: Changes in working capital:
B21: Accounts receivable | D21: -74 | E21: 281 | F21: -177 | G21: 60 | H21: 90 | J21: -105 | K21: -56 | L21: -13 | M21: -43 | N21: -217 | P21: -236 | Q21: -94 | R21: 0 | S21: 161 | T21: -169 | V21: -59 | W21: 129 | X21: -108 | Y21: -139 | Z21: -177 | AB21: -89 | AC21: 44 | AD21: 82 | AE21: 142 | AF21: 179 | AH21: -71 | AI21: 50 | AJ21: 0
B22: Inventories | D22: 59 | E22: 24 | F22: 19 | G22: 11 | H22: 113 | J22: -21 | K22: -29 | L22: 24 | M22: 43 | N22: 17 | P22: -105 | Q22: -64 | R22: -4 | S22: 53 | T22: -120 | V22: 13 | W22: -14 | X22: -28 | Y22: 27 | Z22: -2 | AB22: -27 | AC22: -37 | AD22: 32 | AE22: 6 | AF22: -26 | AH22: 22 | AI22: -27 | AJ22: 0
B23: Accounts payable | D23: 0 | E23: 0 | F23: 0 | G23: 0 | H23: 0 | J23: 0 | K23: 0 | L23: 0 | M23: 0 | N23: 0 | P23: 0 | Q23: 0 | R23: 0 | S23: 0 | T23: 0 | V23: 0 | W23: 0 | X23: 0 | Y23: 0 | Z23: 0 | AB23: 0 | AC23: 0 | AD23: 0 | AE23: 0 | AF23: 0 | AH23: 0 | AI23: 0 | AJ23: 0
B24: Other | D24: 122 | E24: 114 | F24: -443 | G24: 270 | H24: 63 | J24: 271 | K24: -79 | L24: -75 | M24: 286 | N24: 403 | P24: 375 | Q24: -329 | R24: 403 | S24: -152 | T24: 297 | V24: -251 | W24: -218 | X24: 126 | Y24: 219 | Z24: -124 | AB24: 60 | AC24: -397 | AD24: 214 | AE24: 156 | AF24: 33 | AH24: 52 | AI24: -42 | AJ24: 0
B25: Cash provided by operating activities | D25: 2155 | E25: 2237 | F25: 1601 | G25: 2547 | H25: 8540 | J25: 1958 | K25: 2261 | L25: 2284 | M25: 2529 | N25: 9032 | P25: 2236 | Q25: 1931 | R25: 2903 | S25: 2292 | T25: 9362 | V25: 1840 | W25: 2018 | X25: 2126 | Y25: 2395 | Z25: 8379 | AB25: 2122 | AC25: 1911 | AD25: 2651 | AE25: 2662 | AF25: 9346 | AH25: 2210 | AI25: 2333 | AJ25: 0
A27: x | B27: Investing activities:
B28: Purchase of fixed assets and intangibles | D28: -807 | E28: -792 | F28: -695 | G28: -633 | H28: -2927 | J28: -536 | K28: -654 | L28: -755 | M28: -991 | N28: -2936 | P28: -848 | Q28: -797 | R28: -1045 | S28: -930 | T28: -3620 | V28: -772 | W28: -835 | X28: -1020 | Y28: -1024 | Z28: -3606 | AB28: -797 | AC28: -902 | AD28: -831 | AE28: -922 | AF28: -3452 | AH28: -906 | AI28: -936 | AJ28: 0
B29: Disposal of fixed assets and intangibles | D29: 8 | E29: 99 | F29: 12 | G29: 30 | H29: 149 | J29: 17 | K29: 84 | L29: 19 | M29: 58 | N29: 178 | P29: 32 | Q29: 88 | R29: 52 | S29: 22 | T29: 194 | V29: 12 | W29: 33 | X29: 0 | Y29: 0 | Z29: 0 | AB29: 0 | AC29: 0 | AD29: 0 | AE29: 0 | AF29: 0 | AH29: 0 | AI29: 0 | AJ29: 0
B30: Acquisitions | D30: 0 | E30: 0 | F30: 0 | G30: 0 | H30: 0 | J30: 0 | K30: 0 | L30: 0 | M30: 0 | N30: 0 | P30: 0 | Q30: 0 | R30: 0 | S30: 0 | T30: 0 | V30: 0 | W30: 0 | X30: 0 | Y30: 0 | Z30: 0 | AB30: 0 | AC30: 0 | AD30: 0 | AE30: 0 | AF30: 0 | AH30: 0 | AI30: 0 | AJ30: 0
B31: Divestitures | D31: 0 | E31: 0 | F31: 0 | G31: 0 | H31: 0 | J31: 0 | K31: 0 | L31: 0 | M31: 0 | N31: 0 | P31: 0 | Q31: 0 | R31: 0 | S31: 0 | T31: 0 | V31: 0 | W31: 0 | X31: 0 | Y31: 0 | Z31: 0 | AB31: 0 | AC31: 0 | AD31: 0 | AE31: 0 | AF31: 0 | AH31: 0 | AI31: 0 | AJ31: 0
B32: Joint Ventures | D32: 0 | E32: 0 | F32: 0 | G32: 0 | H32: 0 | J32: 0 | K32: 0 | L32: 0 | M32: 0 | N32: 0 | P32: 0 | Q32: 0 | R32: 0 | S32: 0 | T32: 0 | V32: 0 | W32: 0 | X32: 0 | Y32: 0 | Z32: 0 | AB32: 0 | AC32: 0 | AD32: 0 | AE32: 0 | AF32: 0 | AH32: 0 | AI32: 0 | AJ32: 0
B33: Increase in long-term investments | D33: 0 | E33: 0 | F33: 0 | G33: 0 | H33: 0 | J33: 0 | K33: 0 | L33: 0 | M33: 0 | N33: 0 | P33: 0 | Q33: 0 | R33: 0 | S33: 0 | T33: 0 | V33: 0 | W33: 0 | X33: 0 | Y33: 0 | Z33: 0 | AB33: 0 | AC33: 0 | AD33: 0 | AE33: 0 | AF33: 0 | AH33: 0 | AI33: 0 | AJ33: 0
B34: Decrease in long-term investments | D34: 0 | E34: 0 | F34: 0 | G34: 0 | H34: 0 | J34: 0 | K34: 0 | L34: 0 | M34: 0 | N34: 0 | P34: 0 | Q34: 0 | R34: 0 | S34: 0 | T34: 0 | V34: 0 | W34: 0 | X34: 0 | Y34: 0 | Z34: 0 | AB34: 0 | AC34: 0 | AD34: 0 | AE34: 0 | AF34: 0 | AH34: 0 | AI34: 0 | AJ34: 0
B35: Other investing inflows/(outflows) | D35: -8 | E35: 83 | F35: 19 | G35: 8 | H35: 102 | J35: 14 | K35: 4 | L35: 15 | M35: 16 | N35: 49 | P35: -20 | Q35: 5 | R35: -26 | S35: -4 | T35: -45 | V35: -45 | W35: -67 | X35: 44 | Y35: 7 | Z35: -61 | AB35: -5 | AC35: 112 | AD35: -3 | AE35: 23 | AF35: 127 | AH35: -32 | AI35: 35 | AJ35: 0
B36: Cash provided by/(used in) investing activities | D36: -807 | E36: -610 | F36: -664 | G36: -595 | H36: -2676 | J36: -505 | K36: -566 | L36: -721 | M36: -917 | N36: -2709 | P36: -836 | Q36: -704 | R36: -1019 | S36: -912 | T36: -3471 | V36: -805 | W36: -869 | X36: -976 | Y36: -1017 | Z36: -3667 | AB36: -802 | AC36: -790 | AD36: -834 | AE36: -899 | AF36: -3325 | AH36: -938 | AI36: -901 | AJ36: 0
A38: x | B38: Financing activities:
B39: Payment of dividends | D39: -660 | E39: -659 | F39: -655 | G39: -652 | H39: -2626 | J39: -650 | K39: -700 | L39: -695 | M39: -755 | N39: -2800 | P39: -743 | Q39: -813 | R39: -806 | S39: -797 | T39: -3159 | V39: -795 | W39: -793 | X39: -792 | Y39: -793 | Z39: -3173 | AB39: -795 | AC39: -793 | AD39: -815 | AE39: -810 | AF39: -3213 | AH39: -804 | AI39: -795 | AJ39: 0
B40: Issuance (repurchase) of common shares | D40: -2556 | E40: 0 | F40: -400 | G40: -749 | H40: -3705 | J40: -1347 | K40: -2738 | L40: -1761 | M40: -1445 | N40: -7291 | P40: -2743 | Q40: -730 | R40: -2024 | S40: -785 | T40: -6282 | V40: -575 | W40: -130 | X40: 0 | Y40: 0 | Z40: -705 | AB40: 0 | AC40: -100 | AD40: -731 | AE40: -674 | AF40: -1505 | AH40: -1420 | AI40: -1259 | AJ40: 0
B41: Cash from (repayment) of short-term debt | D41: 0 | E41: 0 | F41: 0 | G41: 0 | H41: 0 | J41: 0 | K41: 0 | L41: 0 | M41: 0 | N41: 0 | P41: 0 | Q41: 0 | R41: 0 | S41: 0 | T41: 0 | V41: 0 | W41: 0 | X41: 0 | Y41: 0 | Z41: 0 | AB41: 0 | AC41: 0 | AD41: 0 | AE41: 0 | AF41: 0 | AH41: 0 | AI41: 0 | AJ41: 0
B42: Proceeds from issuance of long-term debt | D42: 0 | E42: 0 | F42: 0 | G42: 0 | H42: 0 | J42: 0 | K42: 0 | L42: 0 | M42: 0 | N42: 0 | P42: 0 | Q42: 0 | R42: 0 | S42: 0 | T42: 0 | V42: 0 | W42: 0 | X42: 0 | Y42: 0 | Z42: 0 | AB42: 0 | AC42: 0 | AD42: 0 | AE42: 0 | AF42: 0 | AH42: 0 | AI42: 0 | AJ42: 0
B43: Repayments of long-term debt | D43: 0 | E43: 0 | F43: 0 | G43: 0 | H43: 0 | J43: 0 | K43: 0 | L43: 0 | M43: 0 | N43: 0 | P43: 0 | Q43: 0 | R43: 0 | S43: 0 | T43: 0 | V43: 0 | W43: 0 | X43: 0 | Y43: 0 | Z43: 0 | AB43: 0 | AC43: 0 | AD43: 0 | AE43: 0 | AF43: 0 | AH43: 0 | AI43: 0 | AJ43: 0
B44: Other financing inflows/(outflows) | D44: 2219 | E44: 549 | F44: 12 | G44: -1351 | H44: 1429 | J44: -76 | K44: 1704 | L44: 972 | M44: 333 | N44: 2933 | P44: 2033 | Q44: 200 | R44: 1416 | S44: -95 | T44: 3554 | V44: 443 | W44: -478 | X44: -420 | Y44: -292 | Z44: -747 | AB44: -656 | AC44: -24 | AD44: -461 | AE44: -208 | AF44: -1349 | AH44: 1346 | AI44: 283 | AJ44: 0
B45: Cash provided by/(used in) financing activities | D45: -997 | E45: -110 | F45: -1043 | G45: -2752 | H45: -4902 | J45: -2073 | K45: -1734 | L45: -1484 | M45: -1867 | N45: -7158 | P45: -1453 | Q45: -1343 | R45: -1414 | S45: -1677 | T45: -5887 | V45: -927 | W45: -1401 | X45: -1212 | Y45: -1085 | Z45: -4625 | AB45: -1451 | AC45: -917 | AD45: -2007 | AE45: -1692 | AF45: -6067 | AH45: -878 | AI45: -1771 | AJ45: 0
A47: x | B47: Effects of foreign exchange | D47: 0 | E47: 0 | F47: 0 | G47: 0 | H47: 0 | J47: 0 | K47: 0 | L47: 0 | M47: 0 | N47: 0 | P47: 0 | Q47: 0 | R47: 0 | S47: 0 | T47: 0 | V47: 0 | W47: 0 | X47: 0 | Y47: 0 | Z47: 0 | AB47: 0 | AC47: 0 | AD47: 0 | AE47: 0 | AF47: 0 | AH47: 0 | AI47: 0 | AJ47: 0
A49: x | B49: Increase/(Decrease) in cash and cash equivalents | D49: 351 | E49: 1517 | F49: -106 | G49: -800 | H49: 962 | J49: -620 | K49: -39 | L49: 79 | M49: -255 | N49: -835 | P49: -53 | Q49: -116 | R49: 470 | S49: -297 | T49: 4 | V49: 108 | W49: -252 | X49: -62 | Y49: 293 | Z49: 87 | AB49: -131 | AC49: 204 | AD49: -190 | AE49: 71 | AF49: -46 | AH49: 394 | AI49: -339 | AJ49: 0
B50: Cash and cash equivalents, ending balances | D50: 1130 | E50: 2706 | F50: 2601 | G50: 1799 | H50: 1799 | J50: 1183 | K50: 1115 | L50: 1194 | M50: 960 | N50: 960 | P50: 909 | Q50: 788 | R50: 1267 | S50: 973 | T50: 973 | V50: 1079 | W50: 830 | X50: 750 | Y50: 1055 | Z50: 1055 | AB50: 925 | AC50: 1137 | AD50: 947 | AE50: 1016 | AF50: 1016 | AH50: 1411 | AI50: 1060 | AJ50: 0

Sheet Error Check
B7: Income Statement – Sum of the Quarters = FY | D7: =F7 -> 2020 | E7: =F7 -> 2020 | F7: 2020 | G7: =F7 -> 2020 | H7: =F7 -> 2020 | J7: =L7 -> 2021 | K7: =L7 -> 2021 | L7: 2021 | M7: =L7 -> 2021 | N7: =L7 -> 2021 | P7: =R7 -> 2022 | Q7: =R7 -> 2022 | R7: 2022 | S7: =R7 -> 2022 | T7: =R7 -> 2022 | V7: =X7 -> 2023 | W7: =X7 -> 2023 | X7: 2023 | Y7: =X7 -> 2023 | Z7: =X7 -> 2023 | AB7: =AD7 -> 2024 | AC7: =AD7 -> 2024 | AD7: 2024 | AE7: =AD7 -> 2024 | AF7: =AD7 -> 2024 | AH7: =AJ7 -> 2025 | AI7: =AJ7 -> 2025 | AJ7: 2025 | AK7: =AJ7 -> 2025 | AL7: =AJ7 -> 2025 | AN7: =AP7 -> 2025 | AO7: =AP7 -> 2025 | AP7: 2025 | AQ7: =AP7 -> 2025 | AR7: =AP7 -> 2025
D8: 2020 | J8: =D8+1 -> 2021 | P8: =J8+1 -> 2022 | V8: =P8+1 -> 2023 | AB8: =V8+1 -> 2024 | AH8: =AB8+1 -> 2025 | AN8: =AH8+1 -> 2026 | AT8: =AN8+1 -> 2027 | AV8: =+AT8+1 -> 2028 | AX8: =+AV8+1 -> 2029
D9: Q1 | E9: Q2 | F9: Q3 | G9: Q4 | H9: FY | J9: Q1 | K9: Q2 | L9: Q3 | M9: Q4 | N9: FY | P9: Q1 | Q9: Q2 | R9: Q3 | S9: Q4 | T9: FY | V9: Q1 | W9: Q2 | X9: Q3 | Y9: Q4 | Z9: FY | AB9: Q1 | AC9: Q2 | AD9: Q3 | AE9: Q4 | AF9: FY | AH9: Q1 | AI9: Q2 | AJ9: Q3 | AK9: Q4 | AL9: FY | AN9: Q1 | AO9: Q2 | AP9: Q3 | AQ9: Q4 | AR9: FY | AT9: FY | AV9: FY | AX9: FY
A12: x | B12: Revenue:
B13: Segment 1 | H13: =IF(ROUND(SUM(IS!D13:G13),1)=ROUND(IS!H13,1),"OK","ERROR") -> OK | N13: =IF(ROUND(SUM(IS!J13:M13),1)=ROUND(IS!N13,1),"OK","ERROR") -> OK | T13: =IF(ROUND(SUM(IS!P13:S13),1)=ROUND(IS!T13,1),"OK","ERROR") -> OK | Z13: =IF(ROUND(SUM(IS!V13:Y13),1)=ROUND(IS!Z13,1),"OK","ERROR") -> OK | AF13: =IF(ROUND(SUM(IS!AB13:AE13),1)=ROUND(IS!AF13,1),"OK","ERROR") -> OK | AL13: =IF(ROUND(SUM(IS!AH13:AK13),1)=ROUND(IS!AL13,1),"OK","ERROR") -> OK | AR13: =IF(ROUND(SUM(IS!AN13:AQ13),1)=ROUND(IS!AR13,1),"OK","ERROR") -> OK
B14: Segment 2 | H14: =IF(ROUND(SUM(IS!D14:G14),1)=ROUND(IS!H14,1),"OK","ERROR") -> OK | N14: =IF(ROUND(SUM(IS!J14:M14),1)=ROUND(IS!N14,1),"OK","ERROR") -> OK | T14: =IF(ROUND(SUM(IS!P14:S14),1)=ROUND(IS!T14,1),"OK","ERROR") -> OK | Z14: =IF(ROUND(SUM(IS!V14:Y14),1)=ROUND(IS!Z14,1),"OK","ERROR") -> OK | AF14: =IF(ROUND(SUM(IS!AB14:AE14),1)=ROUND(IS!AF14,1),"OK","ERROR") -> OK | AL14: =IF(ROUND(SUM(IS!AH14:AK14),1)=ROUND(IS!AL14,1),"OK","ERROR") -> OK | AR14: =IF(ROUND(SUM(IS!AN14:AQ14),1)=ROUND(IS!AR14,1),"OK","ERROR") -> OK
B15: Segment 3 | H15: =IF(ROUND(SUM(IS!D15:G15),1)=ROUND(IS!H15,1),"OK","ERROR") -> OK | N15: =IF(ROUND(SUM(IS!J15:M15),1)=ROUND(IS!N15,1),"OK","ERROR") -> OK | T15: =IF(ROUND(SUM(IS!P15:S15),1)=ROUND(IS!T15,1),"OK","ERROR") -> OK | Z15: =IF(ROUND(SUM(IS!V15:Y15),1)=ROUND(IS!Z15,1),"OK","ERROR") -> OK | AF15: =IF(ROUND(SUM(IS!AB15:AE15),1)=ROUND(IS!AF15,1),"OK","ERROR") -> OK | AL15: =IF(ROUND(SUM(IS!AH15:AK15),1)=ROUND(IS!AL15,1),"OK","ERROR") -> OK | AR15: =IF(ROUND(SUM(IS!AN15:AQ15),1)=ROUND(IS!AR15,1),"OK","ERROR") -> OK
B16: Segment 4 | H16: =IF(ROUND(SUM(IS!D16:G16),1)=ROUND(IS!H16,1),"OK","ERROR") -> OK | N16: =IF(ROUND(SUM(IS!J16:M16),1)=ROUND(IS!N16,1),"OK","ERROR") -> OK | T16: =IF(ROUND(SUM(IS!P16:S16),1)=ROUND(IS!T16,1),"OK","ERROR") -> OK | Z16: =IF(ROUND(SUM(IS!V16:Y16),1)=ROUND(IS!Z16,1),"OK","ERROR") -> OK | AF16: =IF(ROUND(SUM(IS!AB16:AE16),1)=ROUND(IS!AF16,1),"OK","ERROR") -> OK | AL16: =IF(ROUND(SUM(IS!AH16:AK16),1)=ROUND(IS!AL16,1),"OK","ERROR") -> OK | AR16: =IF(ROUND(SUM(IS!AN16:AQ16),1)=ROUND(IS!AR16,1),"OK","ERROR") -> OK
B17: Segment 5 | H17: =IF(ROUND(SUM(IS!D17:G17),1)=ROUND(IS!H17,1),"OK","ERROR") -> OK | N17: =IF(ROUND(SUM(IS!J17:M17),1)=ROUND(IS!N17,1),"OK","ERROR") -> OK | T17: =IF(ROUND(SUM(IS!P17:S17),1)=ROUND(IS!T17,1),"OK","ERROR") -> OK | Z17: =IF(ROUND(SUM(IS!V17:Y17),1)=ROUND(IS!Z17,1),"OK","ERROR") -> OK | AF17: =IF(ROUND(SUM(IS!AB17:AE17),1)=ROUND(IS!AF17,1),"OK","ERROR") -> OK | AL17: =IF(ROUND(SUM(IS!AH17:AK17),1)=ROUND(IS!AL17,1),"OK","ERROR") -> OK | AR17: =IF(ROUND(SUM(IS!AN17:AQ17),1)=ROUND(IS!AR17,1),"OK","ERROR") -> OK
B18: Total revenue | H18: =IF(ROUND(SUM(IS!D18:G18),1)=ROUND(IS!H18,1),"OK","ERROR") -> OK | N18: =IF(ROUND(SUM(IS!J18:M18),1)=ROUND(IS!N18,1),"OK","ERROR") -> OK | T18: =IF(ROUND(SUM(IS!P18:S18),1)=ROUND(IS!T18,1),"OK","ERROR") -> OK | Z18: =IF(ROUND(SUM(IS!V18:Y18),1)=ROUND(IS!Z18,1),"OK","ERROR") -> OK | AF18: =IF(ROUND(SUM(IS!AB18:AE18),1)=ROUND(IS!AF18,1),"OK","ERROR") -> OK | AL18: =IF(ROUND(SUM(IS!AH18:AK18),1)=ROUND(IS!AL18,1),"OK","ERROR") -> ERROR | AR18: =IF(ROUND(SUM(IS!AN18:AQ18),1)=ROUND(IS!AR18,1),"OK","ERROR") -> OK
A20: x | B20: Cost of revenue:
B21: Cost of goods and services | H21: =IF(ROUND(SUM(IS!D21:G21),1)=ROUND(IS!H21,1),"OK","ERROR") -> OK | N21: =IF(ROUND(SUM(IS!J21:M21),1)=ROUND(IS!N21,1),"OK","ERROR") -> OK | T21: =IF(ROUND(SUM(IS!P21:S21),1)=ROUND(IS!T21,1),"OK","ERROR") -> OK | Z21: =IF(ROUND(SUM(IS!V21:Y21),1)=ROUND(IS!Z21,1),"OK","ERROR") -> OK | AF21: =IF(ROUND(SUM(IS!AB21:AE21),1)=ROUND(IS!AF21,1),"OK","ERROR") -> OK | AL21: =IF(ROUND(SUM(IS!AH21:AK21),1)=ROUND(IS!AL21,1),"OK","ERROR") -> OK | AR21: =IF(ROUND(SUM(IS!AN21:AQ21),1)=ROUND(IS!AR21,1),"OK","ERROR") -> OK
B22: Depreciation & amortization | H22: =IF(ROUND(SUM(IS!D22:G22),1)=ROUND(IS!H22,1),"OK","ERROR") -> OK | N22: =IF(ROUND(SUM(IS!J22:M22),1)=ROUND(IS!N22,1),"OK","ERROR") -> OK | T22: =IF(ROUND(SUM(IS!P22:S22),1)=ROUND(IS!T22,1),"OK","ERROR") -> OK | Z22: =IF(ROUND(SUM(IS!V22:Y22),1)=ROUND(IS!Z22,1),"OK","ERROR") -> OK | AF22: =IF(ROUND(SUM(IS!AB22:AE22),1)=ROUND(IS!AF22,1),"OK","ERROR") -> OK | AL22: =IF(ROUND(SUM(IS!AH22:AK22),1)=ROUND(IS!AL22,1),"OK","ERROR") -> OK | AR22: =IF(ROUND(SUM(IS!AN22:AQ22),1)=ROUND(IS!AR22,1),"OK","ERROR") -> OK
B23: Total cost of revenue | H23: =IF(ROUND(SUM(IS!D23:G23),1)=ROUND(IS!H23,1),"OK","ERROR") -> OK | N23: =IF(ROUND(SUM(IS!J23:M23),1)=ROUND(IS!N23,1),"OK","ERROR") -> OK | T23: =IF(ROUND(SUM(IS!P23:S23),1)=ROUND(IS!T23,1),"OK","ERROR") -> OK | Z23: =IF(ROUND(SUM(IS!V23:Y23),1)=ROUND(IS!Z23,1),"OK","ERROR") -> OK | AF23: =IF(ROUND(SUM(IS!AB23:AE23),1)=ROUND(IS!AF23,1),"OK","ERROR") -> OK | AL23: =IF(ROUND(SUM(IS!AH23:AK23),1)=ROUND(IS!AL23,1),"OK","ERROR") -> OK | AR23: =IF(ROUND(SUM(IS!AN23:AQ23),1)=ROUND(IS!AR23,1),"OK","ERROR") -> OK
B24: Gross margin | H24: =IF(ROUND(SUM(IS!D24:G24),1)=ROUND(IS!H24,1),"OK","ERROR") -> OK | N24: =IF(ROUND(SUM(IS!J24:M24),1)=ROUND(IS!N24,1),"OK","ERROR") -> OK | T24: =IF(ROUND(SUM(IS!P24:S24),1)=ROUND(IS!T24,1),"OK","ERROR") -> OK | Z24: =IF(ROUND(SUM(IS!V24:Y24),1)=ROUND(IS!Z24,1),"OK","ERROR") -> OK | AF24: =IF(ROUND(SUM(IS!AB24:AE24),1)=ROUND(IS!AF24,1),"OK","ERROR") -> OK | AL24: =IF(ROUND(SUM(IS!AH24:AK24),1)=ROUND(IS!AL24,1),"OK","ERROR") -> ERROR | AR24: =IF(ROUND(SUM(IS!AN24:AQ24),1)=ROUND(IS!AR24,1),"OK","ERROR") -> OK
A26: x | B26: Operating expenses:
B27: Selling, general and administrative | H27: =IF(ROUND(SUM(IS!D27:G27),1)=ROUND(IS!H27,1),"OK","ERROR") -> OK | N27: =IF(ROUND(SUM(IS!J27:M27),1)=ROUND(IS!N27,1),"OK","ERROR") -> OK | T27: =IF(ROUND(SUM(IS!P27:S27),1)=ROUND(IS!T27,1),"OK","ERROR") -> OK | Z27: =IF(ROUND(SUM(IS!V27:Y27),1)=ROUND(IS!Z27,1),"OK","ERROR") -> OK | AF27: =IF(ROUND(SUM(IS!AB27:AE27),1)=ROUND(IS!AF27,1),"OK","ERROR") -> OK | AL27: =IF(ROUND(SUM(IS!AH27:AK27),1)=ROUND(IS!AL27,1),"OK","ERROR") -> OK | AR27: =IF(ROUND(SUM(IS!AN27:AQ27),1)=ROUND(IS!AR27,1),"OK","ERROR") -> OK
B28: Depreciation and amortization | H28: =IF(ROUND(SUM(IS!D28:G28),1)=ROUND(IS!H28,1),"OK","ERROR") -> OK | N28: =IF(ROUND(SUM(IS!J28:M28),1)=ROUND(IS!N28,1),"OK","ERROR") -> OK | T28: =IF(ROUND(SUM(IS!P28:S28),1)=ROUND(IS!T28,1),"OK","ERROR") -> OK | Z28: =IF(ROUND(SUM(IS!V28:Y28),1)=ROUND(IS!Z28,1),"OK","ERROR") -> OK | AF28: =IF(ROUND(SUM(IS!AB28:AE28),1)=ROUND(IS!AF28,1),"OK","ERROR") -> OK | AL28: =IF(ROUND(SUM(IS!AH28:AK28),1)=ROUND(IS!AL28,1),"OK","ERROR") -> ERROR | AR28: =IF(ROUND(SUM(IS!AN28:AQ28),1)=ROUND(IS!AR28,1),"OK","ERROR") -> OK
B29: Research and development | H29: =IF(ROUND(SUM(IS!D29:G29),1)=ROUND(IS!H29,1),"OK","ERROR") -> OK | N29: =IF(ROUND(SUM(IS!J29:M29),1)=ROUND(IS!N29,1),"OK","ERROR") -> OK | T29: =IF(ROUND(SUM(IS!P29:S29),1)=ROUND(IS!T29,1),"OK","ERROR") -> OK | Z29: =IF(ROUND(SUM(IS!V29:Y29),1)=ROUND(IS!Z29,1),"OK","ERROR") -> OK | AF29: =IF(ROUND(SUM(IS!AB29:AE29),1)=ROUND(IS!AF29,1),"OK","ERROR") -> OK | AL29: =IF(ROUND(SUM(IS!AH29:AK29),1)=ROUND(IS!AL29,1),"OK","ERROR") -> OK | AR29: =IF(ROUND(SUM(IS!AN29:AQ29),1)=ROUND(IS!AR29,1),"OK","ERROR") -> OK
