Workbook
Name businessresearchinsights: Segments!$D$38,Segments!$B$38
Name Sectors: 'Sector Impact'!$K$4:$K$16

Sheet OP
B2: 45039 | C2: Team 4 | E2: =Inputs!H3 -> #VALUE! | L2: NASDAQ | M2: SIC:
D3: COMPANY DESCRIPTION | H3: CEO & BOARD OF DIRECTORS
D4: {=_FV(Inputs!H3,"Description")} -> Comcast Corporation is a global media and technology company. It delivers broadband, wireless, and video through Xfinity, Comcast Business, and Sky; produce, distribute, and stream entertainment, sports, and news through brands, including NBC, Telemundo, Universal, Peacock, and Sky; and brings theme parks and attractions to life through Universal Destinations and Experiences. It operates through two primary businesses: Connectivity & Platforms and Content & Experiences. The Connectivity & Platforms segment contains its broadband, wireless, video and wireline voice businesses in the United States, United Kingdom and Italy. It also includes the operations of its Sky-branded entertainment television networks in the United Kingdom, and Italy. The Content & Experiences segment contains media and entertainment businesses that produce and distribute entertainment, sports, news and other content for audiences and that own and operate theme parks and attractions in the United States and Asia. | H4: Name | I4: Gender | J4: Age | K4: Tenure | L4: Executive? | M4: Other roles
H5: Brian L. Roberts | I5: M | J5: 64 | K5: 37 | L5: YES | M5: CEO of Comcast Corporation
H6: Thomas J. Baltimore, Jr. | I6: M | J6: 58 | K6: 0 | L6: NO | M6: Chairman, President and CEO of Park Hotels & Resorts, Inc.
H7: Madeline S. Bell | I7: F | J7: 61 | K7: 7 | L7: NO | M7: President and CEO of Children’s Hospital of Philadelphia
H8: Edward D. Breen | I8: M | J8: 67 | K8: 9 | L8: NO | M8: Executive Chairman and CEO of DuPont de Nemours, Inc.
H9: Gerald L. Hassell | I9: M | J9: 71 | K9: 15 | L9: NO | M9: CEO of The Bank of New York Mellon
H10: Jeffrey A. Honickman | I10: M | J10: 66 | K10: 18 | L10: NO | M10: CEO of Pepsi-Cola & National Brand Beverages, Ltd.
H11: Maritza G. Montiel | I11: F | J11: 71 | K11: 5 | L11: NO | M11: Deputy CEO of Deloitte LLP
H12: Asuka Nakahara | I12: M | J12: 67 | K12: 6 | L12: NO | M12: Co-founder Incompass Labs, Inc.
H13: David C. Novak | I13: M | J13: 70 | K13: 7 | L13: NO | M13: Founder of David Novak Leadership, Inc.
H14: Kenneth J. Bacon | I14: M | J14: 68 | K14: 21 | L14: NO | M14: Partner at RailField Partners
B16: USD MILLIONS
B17: COMPANY OVERVIEW
B18: Stock | D18: Liquidity and Solvency | F18: Segments | I18: Profitability (2022) | L18: Multiples
B19: Last Price | C19: {=_FV(E2,"Price")} -> 40.545 | D19: Total Assets | E19: =_xlfn.XLOOKUP(D19,'Fin. Data'!A:A,'Fin. Data'!B:B,,0) -> 257275 | F19: Regions | H19: % Sales | I19: Reporting Year | J19: 2022 | L19: Float | M19: 0.99
B20: Outstanding Shares | C20: {=_FV(E2,"Shares outstanding",TRUE)} -> 3872502000 | D20: Total Liabilities | E20: =_xlfn.XLOOKUP(D20,'Fin. Data'!A:A,'Fin. Data'!B:B,,0) -> 176332 | F20: =Segments!C5 -> United Kingdom | H20: =Segments!B5 -> 0.11018966 | I20: End of Year | J20: 1 October 2022 | L20: Insiders Own | M20: 0.0074
B21: Market Cap. | C21: =C19*C20/1000000 -> 157010.59 | D21: Cash/Share | E21: =_xlfn.XLOOKUP("Cash & Eq.",'Fin. Data'!A:A,'Fin. Data'!B:B,,0)*1000000/C20 -> 1.2263389 | F21: =Segments!C6 -> United States | H21: =Segments!B6 -> 0.79423028 | I21: EBITDA | K21: =_xlfn.XLOOKUP(I21,'Fin. Data'!A:A,'Fin. Data'!B:B,,0) -> 28723 | L21: b (Yahoo) | M21: 1.05
B22: +Total Debt | C22: ='Fin. Data'!B58 -> 105022 | D22: EBIDTA/Net Financial Cost (NFC) | E22: ='Fin. Data (Common Size)'!B19/(-'Fin. Data (Common Size)'!B14) -> 7.3724333 | F22: Other | H22: =Segments!B8 -> 0.09558006 | I22: Depreciation & Amortization | K22: =_xlfn.XLOOKUP(I22,'Fin. Data'!A:A,'Fin. Data'!B:B,,0) -> 13821 | L22: Score (S&P) | M22: A-
B23: -Cash | C23: ='Fin. Data'!B39 -> 4749 | D23: Debt/EBITDA | E23: =_xlfn.XLOOKUP("Total Debt",'Fin. Data'!A:A,'Fin. Data'!B:B,,0)/_xlfn.XLOOKUP("EBITDA",'Fin. Data'!A:A,'Fin. Data'!B:B,,0) -> 3.6563729 | I23: EBIT | K23: =_xlfn.XLOOKUP(I23,'Fin. Data'!A:A,'Fin. Data'!B:B,,0) -> 14902 | L23: Price/Book Value | M23: =IFERROR((C19*C20/(E19-E20))/1000000,"") -> 1.9397674
B24: =Enterprise Value | C24: =C21+C22-C23 -> 257283.59 | D24: "Others Assets"/Asset | E24: =_xlfn.XLOOKUP("Other Assets",'Fin. Data'!A:A,'Fin. Data'!B:B,,0)/_xlfn.XLOOKUP("Total Assets",'Fin. Data'!A:A,'Fin. Data'!B:B,,0) -> 0.67224565 | I24: Net Income | K24: =_xlfn.XLOOKUP(I24,'Fin. Data'!A:A,'Fin. Data'!B:B,,0) -> 4925 | L24: NCF(3y avg)/Asset | M24: =IFERROR(K30/E19,"") -> 0.038167978
B25: Holdings (nac/int'l) | C25: - | D25: Debt/Assets | E25: =_xlfn.XLOOKUP(D25,'Fin. Data'!A:A,'Fin. Data'!B:B,,0) -> 0.40820911 | F25: Categories | H25: % Sales | I25: EPS | K25: =1000000*K24/C20 -> 1.2717876 | L25: Price/Net Inc. (3y avg) | M25: =IFERROR(C21/K29,"") -> 15.989402
B26: t liq. (Holdings/Vol.) | C26: - | D26: EBITDA Margin (average) | E26: =AVERAGE(_xlfn.XLOOKUP("EBITDA Margin",'Fin. Data'!A:A,'Fin. Data'!B:D,,0)) -> 0.26541817 | F26: =Segments!C14 -> Cable Communications | H26: =Segments!B14 -> 0.52 | I26: ROA | K26: =K24/E19 -> 0.01914294 | L26: EV/Asset | M26: =IFERROR(C24/E19,"") -> 1.0000334
B27: % Short | C27: 0.0095 | D27: Operating Margin (average) | E27: =AVERAGE(_xlfn.XLOOKUP("Operating Margin",'Fin. Data'!A:A,'Fin. Data'!B:D,,0)) -> 0.15446885 | F27: =Segments!C15 -> Media | H27: =Segments!B15 -> 0.19 | I27: ROIC | K27: =K24/(E19-(E20-C22)) -> 0.026483478 | L27: EV/Ebidta (3y average) | M27: =IFERROR(C24/K28,"") -> 8.5551122
B28: Traffic ESG | D28: Net Income Margin (average) | E28: =AVERAGE(_xlfn.XLOOKUP("Net Income Margin",'Fin. Data'!A:A,'Fin. Data'!B:D,,0)) -> 0.087580761 | F28: =Segments!C16 -> Studios | H28: =Segments!B16 -> 0.09 | I28: EBITDA (3y average) | K28: =AVERAGE(_xlfn.XLOOKUP("EBITDA",'Fin. Data'!A:A,'Fin. Data'!B:D,,0)) -> 30073.667 | L28: Price/NCF (3y average) | M28: =IFERROR(C21/K30,"") -> 15.989402
B29: E | F29: =Segments!C17 -> Theme Parks | H29: =Segments!B17 -> 0.06 | I29: Net Income (3y average) | K29: =AVERAGE(_xlfn.XLOOKUP("Net Income",'Fin. Data'!A:A,'Fin. Data'!B:D,,0)) -> 9819.6667 | L29: Bonds 1,3,5a (USD) | M29: -
B30: S | D30: Net Financial Cost/Avg Net Debt | E30: =-_xlfn.XLOOKUP("Net Financial Cost",'Fin. Data'!A:A,'Fin. Data'!B:B,,0)/AVERAGE(_xlfn.XLOOKUP("Net Debt",'Fin. Data'!A:A,'Fin. Data'!B:D,,0)) -> 0.039594971 | F30: =Segments!C18 -> Sky | H30: =Segments!B18 -> 0.14 | I30: NCF (3y average) | K30: =AVERAGE(_xlfn.XLOOKUP("Net Income",'Fin. Data'!A:A,'Fin. Data'!B:D,,0)) -> 9819.6667 | L30: Div+Rep.(3y avg)/Price | M30: =-IFERROR(SUM(E51:E53)/(3*C21),"") -> 0.067823449
B31: G | L31: Div. Yield | M31: =-IFERROR(L52/C21,"") -> 0.030195415
B32: INVESTMENT THESIS
B33: Pillars of Recommendation | H33: Recommendation | I33: Valuation Assumptions
B34: Pillar | C34: Explanation | H34: BUY | I34: Check DCF
B35: Strong Market Position and Diversified Service Portfolio | C35: Comcast holds a dominant position in the telecommunications and media industry, making it a reliable and stable investment option. With a diversified service portfolio, Comcast has multiple revenue streams. This diversification reduces the company's reliance on any single business segment, making it better positioned to face market fluctuations and changes in consumer preferences.
B36: Robust Infrastructure and Technological Advancements | C36: Comcast has made significant investments in building and maintaining a state-of-the-art network infrastructure, allowing it to deliver high-quality services to millions of customers. The company's focus on technological advancements ensures it stays competitive and relevant in the rapidly evolving telecommunications landscape. Comcast's infrastructure investments provide a competitive edge and support future growth opportunities.
B37: Expansion into the Streaming and On-Demand Market | C37: Comcast's ownership of NBCUniversal gives it a strong position in the content creation and distribution space. The company's streaming platform, Peacock, has the potential for significant growth as the trend of online content consumption continues to rise. With a vast library of content from NBCUniversal's properties and original programming, Comcast can capitalize on the growing popularity of streaming services and attract new subscribers. This expansion into the streaming market allows Comcast to tap into a broader audience and diversify its revenue sources beyond traditional cable TV offerings.
B38: Risks of Investment | H38: Price Target | I38: Valuation
B39: Risk | C39: Explanation | H39: =DCF!D75 -> 56.095131 | I39: Discount Rate | J39: =DCF!F50 -> 0.0925 | L39: Upside | M39: =DCF!D74 -> 0.3835277
B40: Intense Competition and Market Disruptions | C40: The telecommunications and media industry is highly competitive, with various players vying for market share. Comcast faces competition not only from traditional cable providers but also from emerging streaming services and digital content platforms. As consumer preferences shift towards on-demand content consumption and cord-cutting becomes more prevalent, Comcast's traditional cable TV business could face challenges.
B41: Customer Service Issues and Reputation | C41: Comcast has faced criticism in the past for its customer service practices, including complaints about long wait times, service outages, and billing problems. Poor customer service experiences can lead to customer dissatisfaction, higher churn rates, and damage to the company's reputation.
B42: Regulatory and Legal Challenges | C42: The telecommunications industry is subject to extensive regulatory oversight, and changes in regulations can significantly affect Comcast's operations and profitability. Additionally, the company may face legal challenges related to antitrust, data privacy, or content distribution issues.
B43: FINANCIAL PERFORMANCE
A44: v | B44: Year | C44: Net Sales | D44: Operating Margin | E44: Dividends + Share Buyback | F44: Net Cash Flow | G44: Debt/Assets | H44: Depreciation & Amortization | I44: Capex + Investments | J44: Cash Flow
B45: =B46-1 -> 2014 | C45: {=_xlfn.SORTBY(TRANSPOSE(_xlfn.XLOOKUP(C$44,'Fin. Data'!$A:$A,'Fin. Data'!$B:$J,,0)),$B$45:$B$53,-1)} -> 68775 | D45: {=_xlfn.SORTBY(TRANSPOSE(_xlfn.XLOOKUP(D$44,'Fin. Data'!$A:$A,'Fin. Data'!$B:$J,,0)),$B$45:$B$53,-1)} -> 0.21670665 | E45: {=_xlfn.SORTBY(TRANSPOSE(_xlfn.XLOOKUP(E$44,'Fin. Data'!$A:$A,'Fin. Data'!$B:$J,,0)),$B$45:$B$53,-1)} -> -2254 | F45: =Inputs!J77 -> 2192 | G45: {=_xlfn.SORTBY(TRANSPOSE(_xlfn.XLOOKUP(G$44,'Fin. Data'!$A:$A,'Fin. Data'!$B:$J,,0)),$B$45:$B$53,-1)} -> 0.27555187 | H45: {=_xlfn.SORTBY(TRANSPOSE(_xlfn.XLOOKUP(H$44,'Fin. Data'!$A:$A,'Fin. Data'!$B:$J,,0)),$B$45:$B$53,-1)} -> 8019 | I45: {=_xlfn.SORTBY(TRANSPOSE(_xlfn.XLOOKUP(I$44,'Fin. Data'!$A:$A,'Fin. Data'!$B:$J,,0)),$B$45:$B$53,-1)} -> -7897 | L45: =J19 -> 2022 | M45: =L45-1 -> 2021
B46: =B47-1 -> 2015 | C46: 74510 | D46: 0.21470943 | E46: -2437 | F46: =Inputs!I77 -> -1615 | G46: 0.29412753 | H46: 8680 | I46: -10285 | J46: Net Income | L46: =_xlfn.XLOOKUP($J46,'Fin. Data'!$A:$A,'Fin. Data'!B:B,,0) -> 4925 | M46: =_xlfn.XLOOKUP($J46,'Fin. Data'!$A:$A,'Fin. Data'!C:C,,0) -> 13833 | N46: =(C46/C45)-1 -> 0.083387859 | O46: =(D46/D45)-1 -> -0.0092162245
B47: =B48-1 -> 2016 | C47: 80736 | D47: 0.20846958 | E47: -7953 | F47: =Inputs!H77 -> 992 | G47: 0.30784488 | H47: 9426 | I47: -13064 | J47: Operating CF | L47: =_xlfn.XLOOKUP($J47,'Fin. Data'!$A:$A,'Fin. Data'!B:B,,0) -> 26413 | M47: =_xlfn.XLOOKUP($J47,'Fin. Data'!$A:$A,'Fin. Data'!C:C,,0) -> 29146 | N47: =(C47/C46)-1 -> 0.083559254 | O47: =(D47/D46)-1 -> -0.029061858 | Q47: =F47/F46-1 -> -1.6142415 | R47: =H47/H46-1 -> 0.0859447 | S47: =I47/I46-1 -> 0.27019932
B48: =B49-1 -> 2017 | C48: 85029 | D48: 0.21190417 | E48: -8318 | F48: =Inputs!G77 -> 156 | G48: 0.31698157 | H48: 9688 | I48: -10082 | J48: Investing CF | L48: =_xlfn.XLOOKUP($J48,'Fin. Data'!$A:$A,'Fin. Data'!B:B,,0) -> -14140 | M48: =_xlfn.XLOOKUP($J48,'Fin. Data'!$A:$A,'Fin. Data'!C:C,,0) -> -13446 | N48: =(C48/C47)-1 -> 0.053173306 | O48: =(D48/D47)-1 -> 0.016475277 | Q48: =F48/F47-1 -> -0.84274194 | R48: =H48/H47-1 -> 0.027795459 | S48: =I48/I47-1 -> -0.22826087
B49: =B50-1 -> 2018 | C49: 94507 | D49: 0.20113854 | E49: -8672 | F49: =Inputs!F77 -> 338 | G49: 0.42650705 | H49: 10676 | I49: -47993 | J49: Net Capex | L49: =_xlfn.XLOOKUP($J49,'Fin. Data'!$A:$A,'Fin. Data'!B:B,,0) -> -10626 | M49: =_xlfn.XLOOKUP($J49,'Fin. Data'!$A:$A,'Fin. Data'!C:C,,0) -> -9174 | N49: =(C49/C48)-1 -> 0.11146785 | O49: =(D49/D48)-1 -> -0.050804256 | Q49: =F49/F48-1 -> 1.1666667 | R49: =H49/H48-1 -> 0.10198183 | S49: =I49/I48-1 -> 3.7602658
B50: =B51-1 -> 2019 | C50: 108942 | D50: 0.19391052 | E50: -4239 | F50: =Inputs!E77 -> 1680 | G50: 0.4082433 | H50: 12953 | I50: -10323 | J50: Investments & Acquisitions | L50: =_xlfn.XLOOKUP($J50,'Fin. Data'!$A:$A,'Fin. Data'!B:B,,0) -> -12 | M50: =_xlfn.XLOOKUP($J50,'Fin. Data'!$A:$A,'Fin. Data'!C:C,,0) -> -1374 | N50: =(C50/C49)-1 -> 0.15274001 | O50: =(D50/D49)-1 -> -0.035935524 | Q50: =F50/F49-1 -> 3.9704142 | R50: =H50/H49-1 -> 0.21328213 | S50: =I50/I49-1 -> -0.78490613
B51: =B52-1 -> 2020 | C51: 103564 | D51: 0.16891005 | E51: -4674 | F51: =Inputs!D77 -> 6179 | G51: 0.40252822 | H51: 13100 | I51: -9412 | J51: Financing CF | L51: =_xlfn.XLOOKUP($J51,'Fin. Data'!$A:$A,'Fin. Data'!B:B,,0) -> -16184 | M51: =_xlfn.XLOOKUP($J51,'Fin. Data'!$A:$A,'Fin. Data'!C:C,,0) -> -18618 | N51: =(C51/C50)-1 -> -0.049365718 | O51: =(D51/D50)-1 -> -0.12892789 | Q51: =F51/F50-1 -> 2.6779762 | R51: =H51/H50-1 -> 0.011348722 | S51: =I51/I50-1 -> -0.08824954
B52: =B53-1 -> 2021 | C52: 116385 | D52: 0.17886326 | E52: -9204 | F52: =Inputs!C$77 -> -2989 | G52: 0.38102608 | H52: 13804 | I52: -10548 | J52: Dividends | L52: =_xlfn.XLOOKUP($J52,'Fin. Data'!$A:$A,'Fin. Data'!B:B,,0) -> -4741 | M52: =_xlfn.XLOOKUP($J52,'Fin. Data'!$A:$A,'Fin. Data'!C:C,,0) -> -4532 | N52: =(C52/C51)-1 -> 0.12379784 | O52: =(D52/D51)-1 -> 0.058926096 | Q52: =F52/F51-1 -> -1.4837352 | R52: =H52/H51-1 -> 0.053740458 | S52: =I52/I51-1 -> 0.12069698
B53: =J19 -> 2022 | C53: 121427 | D53: 0.11563326 | E53: -18069 | F53: =Inputs!B77 -> -3997 | G53: 0.40820911 | H53: 13821 | I53: -10638 | J53: Share Buyback | L53: =_xlfn.XLOOKUP($J53,'Fin. Data'!$A:$A,'Fin. Data'!B:B,,0) -> -13328 | M53: =_xlfn.XLOOKUP($J53,'Fin. Data'!$A:$A,'Fin. Data'!C:C,,0) -> -4672 | N53: =(C53/C52)-1 -> 0.043321734 | O53: =(D53/D52)-1 -> -0.35351025 | Q53: =F53/F52-1 -> 0.33723653 | R53: =H53/H52-1 -> 0.0012315271 | S53: =I53/I52-1 -> 0.0085324232
B54: Annual Growth Rate | C54: =IFERROR((C53/C45)^(1/8)-1,"") -> 0.073644697 | D54: =IFERROR((D53/D45)^(1/8)-1,"") -> -0.075511919 | F54: =IFERROR((F53/F45)^(1/8)-1,"") | H54: =IFERROR((H53/H45)^(1/8)-1,"") -> 0.070415543 | J54: FX | L54: =_xlfn.XLOOKUP($J54,'Fin. Data'!$A:$A,'Fin. Data'!B:B,,0) -> -86 | M54: =_xlfn.XLOOKUP($J54,'Fin. Data'!$A:$A,'Fin. Data'!C:C,,0) -> -71 | N54: =(C54/C53)-1 -> -0.99999939 | O54: =(D54/D53)-1 -> -1.6530294
B55: Average Growth Rate | C55: =IFERROR(AVERAGE(N46:N53),"") -> 0.075260268 | D55: =IFERROR(AVERAGE(O46:O53),"") -> -0.066506829 | F55: =IFERROR(AVERAGE(Q46:Q53),"") -> 0.60165356 | H55: =IFERROR(AVERAGE(S46:S53),"") -> 0.43689686 | J55: Changes in Cash | L55: =L47-L48+L51-L52-L53 -> 42438 | M55: =M47-M48+M51-M52-M53 -> 33178
B56: CVAR | C56: =IFERROR(STDEV(C46:C53)/AVERAGE(C46:C53),"") -> 0.17512716 | D56: =IFERROR(STDEV(D45:D53)/AVERAGE(D45:D53),"") -> 0.17035171 | F56: =IFERROR(STDEV(F45:F53)/AVERAGE(F45:F53),"") -> 9.2908856 | H56: =IFERROR(STDEV(H45:H53)/AVERAGE(H45:H53),"") -> 0.20701081 | J56: Inventory/D Revenues | L56: =IFERROR(SUM(I50:I53)/(C53-C49),"") -> -1.5200966 | M56: =IFERROR((SUM(I50:I53)-SUM(H50:H53))/(C53-C49),"") -> -3.5140788
B57: Last Year | C57: =IFERROR(C53/C52-1,"") -> 0.043321734 | D57: =IFERROR(1-(D53/D52),"") -> 0.35351025 | F57: =IFERROR(1-(F53/F52),"") -> -0.33723653 | H57: =IFERROR(1-(H53/H52),"") -> -0.0012315271 | J57: t inversiones; t adq. neto dep. | L57: =IFERROR(L56/E26,"") -> -5.7271761 | M57: =IFERROR(M56/E26,"") -> -13.239782
B58: QUALITATIVE ANALYSIS
B59: SWOT ANALYSIS | J59: HOLDERS
B60: Pros | E60: Cons | J60: Name | M60: % Stake
B61: Strong Market Presence Diverse Service Portfolio Well-known brand and costumer loyalty | E61: Customer Services Issues Regulation Issues due to being a regional monopoly in some areas Technological Disruption in the industry (on-demand content)
B71: Opportunities | E71: Risks
B72: Expanding Broadband Services Content Streaming through their Peacock platform Integrated Smart Home Services | E72: Highly competitive market Uncertain Regulatory Environment Mass adoption of streaming instead of cable TV
B81: NOTES | G81: STOCK PERFORMANCE (5 years)

Sheet Segments
B2: ="Regions "&"("&OP!$J$19&")" -> Regions (2022) | Q2: Products
D3: Nominal value | K3: YoY Growth
B4: Weight | C4: Region | D4: =OP!J19 -> 2022 | E4: =D4-1 -> 2021 | F4: =E4-1 -> 2020 | G4: =F4-1 -> 2019 | H4: =G4-1 -> 2018 | I4: =H4-1 -> 2017 | K4: =OP!J19 -> 2022 | L4: =K4-1 -> 2021 | M4: =L4-1 -> 2020 | N4: =M4-1 -> 2019 | O4: =N4-1 -> 2018 | P4: =O4-1 -> 2017
B5: =IFERROR(D5/$D$9,"") -> 0.11018966 | C5: United Kingdom | D5: 13380 | E5: 13999 | F5: 20460 | G5: 21553 | K5: =(D5-E5)/E5 -> -0.044217444 | L5: =(E5-F5)/F5 -> -0.3157869 | M5: =(F5-G5)/G5 -> -0.050712198 | N5: =(G5-H5)/H5 -> #DIV/0! | O5: =(H5-I5)/I5 -> #DIV/0!
B6: =IFERROR(D6/$D$9,"") -> 0.79423028 | C6: United States | D6: 96441 | E6: 90926 | F6: 80327 | G6: 82952 | H6: 82233 | I6: 77246 | K6: =(D6-E6)/E6 -> 0.060653718 | L6: =(E6-F6)/F6 -> 0.13194816 | M6: =(F6-G6)/G6 -> -0.031644807 | N6: =(G6-H6)/H6 -> 0.0087434485 | O6: =(H6-I6)/I6 -> 0.064559977
B7: =IFERROR(D7/$D$9,"") -> 0
B8: =IFERROR(D8/$D$9,"") -> 0.09558006 | C8: Other | D8: 11606 | E8: 11460 | F8: 2777 | G8: 4437 | H8: 12274 | I8: 7783 | K8: =(D8-E8)/E8 -> 0.012739965 | L8: =(E8-F8)/F8 -> 3.1267555 | M8: =(F8-G8)/G8 -> -0.37412666 | N8: =(G8-H8)/H8 -> -0.63850416 | O8: =K14=(H8-I8)/I8 -> FALSE
B9: =SUM(B5:B8) -> 1 | C9: TOTAL | D9: =SUM(D5:D8) -> 121427 | E9: =SUM(E5:E8) -> 116385 | F9: =SUM(F5:F8) -> 103564 | G9: =SUM(G5:G8) -> 108942 | H9: =SUM(H5:H8) -> 94507 | I9: =SUM(I5:I8) -> 85029 | K9: =(D9-E9)/E9 -> 0.043321734 | L9: =(E9-F9)/F9 -> 0.12379784 | M9: =(F9-G9)/G9 -> -0.049365718 | N9: =(G9-H9)/H9 -> 0.15274001 | O9: =(H9-I9)/I9 -> 0.11146785 | P9: 0.037
B11: ="Categories "&"("&OP!$J$19&")" -> Categories (2022)
D12: Nominal value | K12: YoY Growth
B13: Weight | C13: Category | D13: =OP!J19 -> 2022 | E13: =D13-1 -> 2021 | F13: =E13-1 -> 2020 | G13: =F13-1 -> 2019 | H13: =G13-1 -> 2018 | I13: =H13-1 -> 2017 | K13: =OP!J19 -> 2022 | L13: =K13-1 -> 2021 | M13: =L13-1 -> 2020 | N13: =M13-1 -> 2019 | O13: =N13-1 -> 2018 | P13: =O13-1 -> 2017 | Q13: TV and streaming
B14: 0.52 | C14: Cable Communications | D14: 66318 | E14: 64328 | F14: 60051 | G14: 58082 | K14: =(D14-E14)/E14 -> 0.030935207 | L14: =(E14-F14)/F14 -> 0.071222794 | M14: =(F14-G14)/G14 -> 0.033900348 | N14: =(G14-H14)/H14 -> #DIV/0! | O14: =(H14-I14)/I14 -> #DIV/0!
B15: 0.19 | C15: Media | D15: 23406 | E15: 22780 | F15: 18936 | G15: 19947 | K15: =(D15-E15)/E15 -> 0.027480246 | L15: =(E15-F15)/F15 -> 0.20299958 | M15: =(F15-G15)/G15 -> -0.050684313 | N15: =(G15-H15)/H15 -> #DIV/0! | O15: =(H15-I15)/I15 -> #DIV/0!
B16: 0.09 | C16: Studios | D16: 11622 | E16: 9449 | F16: 8134 | G16: 9352 | K16: =(D16-E16)/E16 -> 0.22997143 | L16: =(E16-F16)/F16 -> 0.16166708 | M16: =(F16-G16)/G16 -> -0.13023952 | N16: =(G16-H16)/H16 -> #DIV/0! | O16: =(H16-I16)/I16 -> #DIV/0!
B17: 0.06 | C17: Theme Parks | D17: 7541 | E17: 5051 | F17: 2094 | G17: 6213 | K17: =(D17-E17)/E17 -> 0.49297169 | L17: =(E17-F17)/F17 -> 1.4121299 | M17: =(F17-G17)/G17 -> -0.66296475 | N17: =(G17-H17)/H17 -> #DIV/0! | O17: =(H17-I17)/I17 -> #DIV/0!
B18: 0.14 | C18: Sky | D18: 17946 | E18: 20285 | F18: 18594 | G18: 19219 | K18: =(D18-E18)/E18 -> -0.11530688 | L18: =(E18-F18)/F18 -> 0.090943315 | M18: =(F18-G18)/G18 -> -0.032519902 | N18: =(G18-H18)/H18 -> #DIV/0! | O18: =(H18-I18)/I18 -> #DIV/0!
B19: =SUM(B14:B18) -> 1 | C19: TOTAL | D19: =SUM(D14:D18) -> 126833 | E19: =SUM(E14:E18) -> 121893 | F19: =SUM(F14:F18) -> 107809 | G19: =SUM(G14:G18) -> 112813 | H19: =SUM(H14:H18) -> 0 | I19: =SUM(I14:I18) -> 0 | K19: =(D19-E19)/E19 -> 0.040527348 | L19: =(E19-F19)/F19 -> 0.13063844 | M19: =(F19-G19)/G19 -> -0.04435659 | N19: =(G19-H19)/H19 -> #DIV/0! | O19: =(H19-I19)/I19 -> #DIV/0! | P19: 0.037
B21: Categories | D21: Description | I21: Graphs
B22: Cable Communications | D22: Consists of the operations of Comcast Cable, which is a provider of broadband, video, voice, wireless, and other services. These services are provided to residencial customers in the United States under the Xfinity brand and are also provided to business costumers. Also selling of advertising. | X22: studios
B23: Media | D23: Consists primerily of NBCUniversal's(acquired between 2011 and 2013) television and streaming platforms, including nacional, regional and internacional cable networks
B24: Studios | D24: Consists primarily of NBCUniversal's film and television studio production and distribution operations
B25: Theme Parks | D25: Consists primarily of Universal theme parks in Orlando, Florida, Hollywood, California, Osaka, Japan and China
B26: Sky | D26: Consists primarily of the operations of sky (acquired in 2018), an intertainment company, wich includes a direct-to-consumer business, providing video, broadband, voice and wireless phone services, and a content business, operating entertainment network, the sky News broadcast network and Sky Sports networks | Q26: theme parks
B29: Industry | J29: Graphs (Industry Forecasts)
B30: Drivers | D30: Description
B31: Consumption Patterns | D31: Consumers are incrisingly turning to streaming services, decreasing their consumption of cable communications and television networks
B32: Personalized user experience | D32: The sucesse of media and entertainment content depends on consumer tastes and preferences that usually chages in unpredictable ways, making harder to be consistent in creating personalized content.
B33: Tecnological developments | D33: Tecnological developments are rapidly changing the way streaming services are produced and distributed and the quality and speed of this services are increasing almost by the day, which is making harder for the companies to catch up
B34: Digital safety | D34: Technology brings along with all the developments,a bunch of concerns regarding the safety of confidencial information and the security needed to prevent cyber attacks and tecnhology disruptions
B36: Source | D36: Market Growth CGAR | G36: Period
B37: Research and Markets | D37: 0.2082 | G37: 2021-2027
B38: Business Research Insights | D38: 0.059 | G38: 2022-2028
B39: Vault | D39: 0.13 | G39: 2021-2026
B40: Statista | D40: 0.105 | G40: 2022-2027
B41: Company's Strategy / Extra Notes
B44: "PHILADELPH"IA--(BUSINESS WIRE)--Jul. 27, 2023-- Comcast Corporation (Nasdaq: CMCSA) announced that its Board of Directors declared a quarterly dividend of $0.29 a share on the company’s common stock. The quarterly dividend is payable on October 25, 2023, to shareholders of record as of the close of business on October 4, 2023."

Sheet Acuerdo
A1: Invertir
A2: NO invertir
A3: Mantener sin elevar posición
A4: Mantener (y seguir comprando)
A5: Liquidar
A6: PENDIENTE

Sheet Peers
B1: Peer Logo | C1: Peer Name | D1: Description
C2: =D8 -> #VALUE! | D2: {=_FV(D8,"description")} -> AT&T Inc. is a holding company. The Company is a provider of telecommunications and technology services globally. The Company operates through two segments: Communications and Latin America. The Communications segment provides wireless and wireline telecom and broadband services to consumers located in the United States and businesses globally. The business units of the Communication segment include Mobility, Business Wireline and Consumer Wireline. Mobility provides nationwide wireless service and equipment. Business Wireline provides advanced ethernet-based fiber services, IP Voice and managed professional services, as well as traditional voice and data services and related equipment to business customers. Consumer Wireline provides broadband services, including fiber connections. Consumer Wireline provides legacy telephony voice communication services. The Latin America segment provides wireless services and equipment in Mexico.
C3: =E8 -> #VALUE! | D3: {=_FV(E8,"description")} -> Paramount Global is a media, streaming and entertainment company. The Company has three segments. TV Media segment consists of its broadcast operations: CBS Television Network, CBS Stations and its international free-to-air networks; domestic premium and basic cable networks, including Paramount+ with Showtime, MTV, Comedy Central, Paramount Network, The Smithsonian Channel, Nickelodeon, BET Media Group, CBS Sports Network and international extensions of certain of these brands, and domestic and international television studio operations. Direct-to-Consumer segment includes its portfolio of domestic and international pay and free streaming services, including Paramount+, Pluto TV, BET+ and Noggin. Filmed Entertainment segment consists of Paramount Pictures, Paramount Players, Paramount Animation, Nickelodeon Studio, Awesomeness and Miramax. Filmed Entertainment segment consists of Paramount Pictures, Paramount Players, Paramount Animation, Nickelodeon Studio, Awesomeness and Miramax.
C4: =F8 -> #VALUE! | D4: {=_FV(F8,"description")} -> Lumen Technologies, Inc. is a facilities-based technology and communications company. The Company provides a range of integrated products and services to its domestic and global business customers and its domestic mass markets customers. It operates through two segments: Business segment and Mass Markets segment. Its Business segment provides its products and services under four sales channels to meet the needs of its enterprise and commercial customers. Its products and services in this segment include Dark Fiber, Edge Cloud Services, Internet Protocol (IP), Managed Security Services, Software-Defined Wide Area Networks (SD WAN), Secure Access Service Edge (SASE), Optical Services, Ethernet, VPN Data Networks, Voice Services, IT Solutions and Other Legacy Services. Its Mass Markets segment provides products and services to residential and small business customers. Its products and services in this segment include Fiber Broadband, Other Broadband and Voice and Other.
C5: =G8 -> #VALUE! | D5: {=_FV(G8,"description")} -> Verizon Communications Inc. is a holding company. The Company, through its subsidiaries, provides communications, information and entertainment products and services to consumers, businesses and governmental agencies. Its reportable segments are Verizon Consumer Group and Verizon Business Group. Its Consumer segment provides wireless and wireline communications services. Its wireless services are provided across wireless networks in the United States (U.S.) under the Verizon brands. Its wireline services are provided in nine states in the Mid-Atlantic and Northeastern U.S., as well as Washington D.C., over its fiber-optic network under the Fios brand and over a traditional copper-based network. Its Business segment provides wireless and wireline communications services and products, including data, video and conferencing services, security and managed network services, local and long-distance voice services and network access to deliver various Internet of Things services and products.
C6: =H8 -> #VALUE! | D6: {=_FV(H8,"Description")} -> T-Mobile US, Inc. is a provider of mobile communications services, including voice, messaging and data, under its flagship brands, T-Mobile and Metro by T-Mobile in the United States, Puerto Rico and the United States Virgin Islands. The Company provides mobile communications services primarily using its 4G Long Term Evolution (LTE) network and its 5G technology network. It also offers a selection of wireless devices, including handsets, tablets and other mobile communication devices, and accessories for sale, as well as financing through equipment installment plans (EIP). The Company’s primary service plan offering is Go5G Plus, which includes unlimited talk, text and data on its network, 5G access at no extra cost, scam protection features and more. In addition to its mobile wireless communications services, the Company also offers high speed Internet, which includes a fixed wireless product that utilizes the excess capacity of its nationwide 5G network.
B8: In Millions USD (exc Market Cap) | C8: =OP!E2 -> #VALUE! | D8: #VALUE! | E8: #VALUE! | F8: #VALUE! | G8: #VALUE! | H8: #VALUE! | I8: AVERAGE
B9: Company Info | I9: =IFERROR(AVERAGE(C9:H9),"")
B10: Market Cap | C10: {=_FV(C8,"Market cap",TRUE)} -> 155326000000 | D10: {=_FV(D8,"Market cap",TRUE)} -> 154447000000 | E10: {=_FV(E8,"Market cap",TRUE)} -> 7396970000 | F10: {=_FV(F8,"Market cap",TRUE)} -> 7015989000 | G10: {=_FV(G8,"Market cap",TRUE)} -> 185408308400 | H10: {=_FV(H8,"Market cap",TRUE)} -> 235071972480 | I10: =IFERROR(AVERAGE(C10:H10),"") -> 124111039980
B11: Net Sales (current) | C11: =C53 -> 121427 | D11: =D53 -> 120741 | E11: =E53 -> 30154 | F11: =F53 -> 17478 | G11: =G53 -> 136835 | H11: =H53 -> 79571 | I11: =IFERROR(AVERAGE(C11:H11),"") -> 84367.667
B12: Profitability | I12: =IFERROR(AVERAGE(C12:H12),"")
B13: Sales Growth (ttm) | C13: =C53/C52-1 -> 0.043321734 | D13: =D53/D52-1 -> -0.099203211 | E13: =E53/E52-1 -> 0.054852025 | F13: =F53/F52-1 -> -0.11220602 | G13: =G53/G52-1 -> 0.02411442 | H13: =H53/H52-1 -> -0.0068274295 | I13: =IFERROR(AVERAGE(C13:H13),"") -> -0.015991414
B14: Sales Growth (36m) | C14: =C53/C51-1 -> 0.11460227 | D14: =D53/D51-1 -> -0.3336332 | E14: =E53/E51-1 -> 0.11689755 | F14: =F53/F51-1 -> -0.21976697 | G14: =G53/G51-1 -> 0.037666454 | H14: =H53/H51-1 -> 0.76832304 | I14: =IFERROR(AVERAGE(C14:H14),"") -> 0.080681522
B15: Operating Margin | C15: =C56/C53 -> 0.11563326 | D15: =D56/D53 -> 0.18975327 | E15: =E56/E53 -> 0.0736884 | F15: =F56/F53 -> 0.18840828 | G15: =G56/G53 -> 0.22265502 | H15: =H56/H53 -> 0.10188385 | I15: =IFERROR(AVERAGE(C15:H15),"") -> 0.14867035
B16: Net Income Margin | C16: =C59/C53 -> 0.040559348 | D16: =D59/D53 -> -0.058430856 | E16: =E59/E53 -> 0.036612058 | F16: =F59/F53 -> -0.088568486 | G16: =G59/G53 -> 0.15534037 | H16: =H59/H53 -> 0.032549547 | I16: =IFERROR(AVERAGE(C16:H16),"") -> 0.019676997
B17: Return on Equity (RoE) | C17: =C59/C70 -> 0.061679691 | D17: =D59/D70 -> -0.066270889 | E17: =E59/E70 -> 0.047697226 | F17: =F59/F70 -> -0.14831848 | G17: =G59/G70 -> 0.22988655 | H17: =H59/H70 -> 0.037182727 | I17: =IFERROR(AVERAGE(C17:H17),"") -> 0.026976137
B18: Return on Invested Capital (ROIC) | C18: =(C59+C58)/(C69+C70) -> 0.0030616109 | D18: =(D59+D58)/(D69+D70) -> -0.012541358 | E18: =(E59+E58)/(E69+E70) -> 0.02154156 | F18: =(F59+F58)/(F69+F70) -> -0.046181523 | G18: =(G59+G58)/(G69+G70) -> 0.038803729 | H18: =(H59+H58)/(H69+H70) -> 0.0096243932 | I18: =IFERROR(AVERAGE(C18:H18),"") -> 0.0023847355
B19: Solvency | I19: =IFERROR(AVERAGE(C19:H19),"")
B20: Debt/Assets | C20: =C69/C66 -> 0.40820911 | D20: =D69/D66 -> 0.38395891 | E20: =E69/E66 -> 0.30082373 | F20: =F69/F66 -> 0.77102301 | G20: =G69/G66 -> 0.75647124 | H20: =H69/H66 -> 0.67040475 | I20: =IFERROR(AVERAGE(C20:H20),"") -> 0.54848179
B21: Net Debt/EBITDA | C21: =(C69-C61)/C55 -> 3.4910351 | D21: =(D69-D61)/D55 -> 7.1774661 | E21: =(E69-E61)/E56 -> 6.6071107 | F21: =(F69-F61)/F55 -> 9.4673184 | G21: =(G69-G61)/G55 -> 5.810424 | H21: =(H69-H61)/H55 -> 6.803978 | I21: =IFERROR(AVERAGE(C21:H21),"") -> 6.5595554 | S21: 1000000 | T21: 1000000 | U21: 1000000 | V21: 1000000 | W21: 1000000 | X21: 1000000
B22: Interest Coverage Ratio | C22: =-C55/C57 -> 7.3724333 | D22: =-D55/D57 -> -3.4438441 | E22: =-E56/E57 -> 2.6998785 | F22: =-F55/F57 -> 2.6876877 | G22: =-G55/G57 -> 14.128353 | H22: =-H55/H57 -> 5.9931629 | I22: =IFERROR(AVERAGE(C22:H22),"") -> 4.9062785 | S22: 1000000 | T22: 1000000 | U22: 1000000 | V22: 1000000 | W22: 1000000 | X22: 1000000
B23: Liquidity | S23: 1000000 | T23: 1000000 | U23: 1000000 | V23: 1000000 | W23: 1000000 | X23: 1000000
B24: Current Ratio | C24: =C64/C68 -> 0.78265859 | D24: =D64/D68 -> 0.58939348 | E24: =E64/E68 -> 1.2272362 | F24: =F64/F68 -> 1.1284614 | G24: =G64/G68 -> 0.75455941 | H24: =H64/H68 -> 0.77063293 | I24: =IFERROR(AVERAGE(C24:H24),"") -> 0.87549033
B25: Quick Ratio | C25: =(C61+C62)/C68 -> 0.62466382 | D25: =(D61+D62)/D68 -> 0.27000516 | E25: =(E61+E62)/E68 -> 0.92011438 | F25: =(F61+F62)/F68 -> 0.56797835 | G25: =(G61+G62)/G68 -> 0.54037193 | H25: =(H61+H62)/H68 -> 0.36181392 | I25: =IFERROR(AVERAGE(C25:H25),"") -> 0.54749126
B26: Activity | I26: =IFERROR(AVERAGE(C26:H26),"")
B27: Inventory Turnover | C27: =C54/C63 -> #DIV/0! | D27: =D54/D63 -> 34.385207 | E27: =E54/E63 -> 14.78763 | F27: =F54/F63 -> 46.381356 | G27: =G54/G63 -> 37.382328 | H27: =H54/H63 -> 19.217622 | I27: =IFERROR(AVERAGE(C27:H27),"")
B28: Acc. Receivable Turnover | C28: =C53/C62 -> 9.5830637 | D28: =D53/D62 -> 10.530351 | E28: =E53/E62 -> 4.0682677 | F28: =F53/F62 -> 11.833446 | G28: =G53/G62 -> 5.5837346 | H28: =H53/H62 -> 17.901237 | I28: =IFERROR(AVERAGE(C28:H28),"") -> 9.9166833
A29: Price/Sales | B29: Payables Turnover | C29: =C54/C67 -> 6.774713 | D29: =D54/D67 -> 2.5181737 | E29: =E54/E67 -> 14.14469 | F29: =F54/F67 -> 11.522105 | G29: =G54/G67 -> 10.202171 | H29: =H54/H67 -> 5.019548 | I29: =IFERROR(AVERAGE(C29:H29),"") -> 8.3635669
B30: Fixed Asset Turnover | C30: =C53/C65 -> 2.1884654 | D30: =D53/D65 -> 0.94739692 | E30: =E53/E65 -> 17.113507 | F30: =F53/F65 -> 0.91192737 | G30: =G53/G65 -> 1.2736657 | H30: =H53/H65 -> 1075.2838 | I30: =IFERROR(AVERAGE(C30:H30),"") -> 182.95312
B31: Total Asset Turnover | C31: =C53/C66 -> 0.47197357 | D31: =D53/D66 -> 0.29971478 | E31: =E53/E66 -> 0.51639751 | F31: =F53/F66 -> 0.38344924 | G31: =G53/G66 -> 0.3603956 | H31: =H53/H66 -> 0.37651061 | I31: =IFERROR(AVERAGE(C31:H31),"") -> 0.40140689
B32: Valuation | I32: =IFERROR(AVERAGE(C32:H32),"")
B33: Price/Earnings | C33: =C10/C59/S21 -> 31.538274 | D33: =D10/D59/T21 -> -21.89185 | E33: =E10/E59/U21 -> 6.700154 | F33: =F10/F59/V21 -> -4.5322926 | G33: =G10/G59/W21 -> 8.722634 | H33: =H10/H59/X21 -> 90.761379 | I33: =IFERROR(AVERAGE(C33:H33),"") -> 18.549717
B34: Price/Sales | C34: =C10/C53/S22 -> 1.2791718 | D34: =D10/D53/T22 -> 1.2791595 | E34: =E10/E53/U22 -> 0.24530643 | F34: =F10/F53/V22 -> 0.4014183 | G34: =G10/G53/W22 -> 1.3549772 | H34: =H10/H53/X22 -> 2.9542418 | I34: =IFERROR(AVERAGE(C34:H34),"") -> 1.2523792
B35: Price/Book | C35: =C10/C70/S23 -> 1.945271 | D35: =D10/D70/T23 -> 1.4507923 | E35: =E10/E70/U23 -> 0.31957876 | F35: =F10/F70/V23 -> 0.67222277 | G35: =G10/G70/W23 -> 2.0052162 | H35: =H10/H70/X23 -> 3.3747555 | I35: =IFERROR(AVERAGE(C35:H35),"") -> 1.6279728
B36: EV/Sales | C36: =(C69+(C10/1000000)-C61)/C53 -> 2.1049602 | D36: =(D69+(D10/1000000)-D61)/D53 -> 2.5295881 | E36: =(E69+(E10/1000000)-E61)/E53 -> 0.73217384 | F36: =(F69+(F10/1000000)-F61)/F53 -> 2.340599 | G36: =(G69+(G10/1000000)-G61)/G53 -> 3.4349421 | H36: =(H69+(H10/1000000)-H61)/H53 -> 4.6781739 | I36: =IFERROR(AVERAGE(C36:H36),"") -> 2.6367395
B37: EV/EBITDA | C37: =(C69+(C10/1000000)-C61)/C55 -> 8.8987571 | D37: =(D69+(D10/1000000)-D61)/D55 -> 14.519848 | E37: =(E69+(E10/1000000)-E61)/E55 -> 8.1921967 | F37: =(F69+(F10/1000000)-F61)/F55 -> 11.427092 | G37: =(G69+(G10/1000000)-G61)/G55 -> 9.5955803 | H37: =(H69+(H10/1000000)-H61)/H55 -> 18.463716 | I37: =IFERROR(AVERAGE(C37:H37),"") -> 11.849532
B38: Stock Info | I38: =IFERROR(AVERAGE(C38:H38),"")
B39: Float | C39: =OP!M19 -> 0.99 | D39: 0.991 | E39: 0.1734 | F39: 0.5269 | G39: 0.9949 | H39: 0.9964 | I39: =IFERROR(AVERAGE(C39:H39),"") -> 0.77876667
B40: b (Yahoo) | C40: =OP!M21 -> 1.05 | D40: 0.66 | E40: 0.99 | F40: 0.17 | G40: 0.55 | H40: 0.79 | I40: =IFERROR(AVERAGE(C40:H40),"") -> 0.70166667
B41: Dividend Yield (yahoo finance) | C41: =OP!M31 -> 0.030195415 | D41: 0.0252 | E41: 0 | F41: 0.0262 | G41: 0 | H41: 0.0197 | I41: =IFERROR(AVERAGE(C41:H41),"") -> 0.016882569
B42: Stock Performance
B43: 1y | C43: =(40.43-1)/C45 -> 0.87176653 | D43: =(D45-1)/D45 -> 0.93079585 | E43: =(16.06-1)/E45 -> 0.79013641 | F43: =(3.4-1)/F45 -> 1.3636364 | G43: =(34.03-1)/G45 -> 0.97061416 | H43: =(137.22-1)/H45 -> 0.99242314 | I43: =IFERROR(AVERAGE(C43:H43),"") -> 0.98656208
B44: 3y | C44: =(37.17-1)/C45 -> 0.79969047 | D44: =(20.41-1)/D45 -> 1.3432526 | E44: =(35.28-1)/E45 -> 1.798531 | F44: =(12.07-1)/F45 -> 6.2897727 | G44: =(56.99-1)/G45 -> 1.645313 | H44: =(83.9-1)/H45 -> 0.60396328 | I44: =IFERROR(AVERAGE(C44:H44),"") -> 2.0800872
B45: Current Price | C45: 45.23 | D45: 14.45 | E45: 19.06 | F45: 1.76 | G45: 34.03 | H45: 137.26 | I45: =IFERROR(AVERAGE(C45:H45),"") -> 41.965
B46: Average Target Price | C46: 45.75 | D46: 17.54 | E46: 18.4 | F46: 2.89 | G46: 36.56 | H46: 179.05 | I46: =IFERROR(AVERAGE(C46:H46),"") -> 50.031667
B47: Upside/Downside | C47: =C46/C45-1 -> 0.011496794 | D47: =D46/D45-1 -> 0.21384083 | E47: =E46/E45-1 -> -0.034627492 | F47: =F46/F45-1 -> 0.64204545 | G47: =G46/G45-1 -> 0.074346165 | H47: =H46/H45-1 -> 0.30445869 | I47: =IFERROR(AVERAGE(C47:H47),"") -> 0.20192674
B49: Financial Data | C49: =OP!E2 -> #VALUE! | D49: =D8 -> #VALUE! | E49: =E8 -> #VALUE! | F49: =F8 -> #VALUE! | G49: =G8 -> #VALUE! | H49: =H8 -> #VALUE!
B50: IS
B51: Net Sales (36m ago) | C51: ='Fin. Data'!E5 -> 108942 | D51: 181193 | E51: 26998 | F51: 22401 | G51: 131868 | H51: 44998
B52: Net Sales (12m ago) | C52: ='Fin. Data'!C5 -> 116385 | D52: 134038 | E52: 28586 | F52: 19687 | G52: 133613 | H52: 80118
B53: Net Sales (current) | C53: ='Fin. Data'!B5 -> 121427 | D53: 120741 | E53: 30154 | F53: 17478 | G53: 136835 | H53: 79571
B54: COGS | C54: ='Fin. Data'!B5-'Fin. Data'!B7 -> 84982 | D54: 107385 | E54: 19845 | F54: =7868+3078 -> 10946 | G54: =28637+30496+30136 -> 89269 | H54: 36206
B55: EBITDA | C55: ='Fin. Data'!B19 -> 28723 | D55: 21035 | E55: 2695 | F55: 3580 | G55: 48983 | H55: 20161
B56: Operating Income | C56: ='Fin. Data'!B11 -> 14041 | D56: 22911 | E56: 2222 | F56: 3293 | G56: 30467 | H56: 8107
B57: Net Financial Cost | C57: ='Fin. Data'!B14 -> -3896 | D57: 6108 | E57: -823 | F57: -1332 | G57: -3467 | H57: -3364
B58: Taxes | C58: ='Fin. Data'!B21 -> -4359 | D58: 3780 | E58: -227 | F58: -557 | G58: -6523 | H58: -556
B59: Net Income | C59: ='Fin. Data'!B23 -> 4925 | D59: -7055 | E59: 1104 | F59: -1548 | G59: 21256 | H59: 2590
B60: BS
B61: Cash & Eq. | C61: ='Fin. Data'!B39 -> 4749 | D61: 3701 | E61: 2885 | F61: 1251 | G61: 2605 | H61: 4507
B62: Acc. Receivables | C62: ='Fin. Data'!B40 -> 12671 | D62: 11466 | E62: 7412 | F62: 1477 | G62: 24506 | H62: 4445
B63: Inventory | C63: ='Fin. Data'!B41 -> 0 | D63: 3123 | E63: 1342 | F63: 236 | G63: 2388 | H63: 1884
B64: Current Assets | C64: =Inputs!B27 -> 21826 | D64: 33108 | E64: 13734 | F64: 5420 | G64: 37857 | H64: 19067
B65: Fixed Assets | C65: ='Fin. Data'!B42 -> 55485 | D65: 127445 | E65: 1762 | F65: 19166 | G65: 107434 | H65: 74
B66: Total Assets | C66: ='Fin. Data'!B44 -> 257275 | D66: 402853 | E66: 58393 | F66: 45581 | G66: 379680 | H66: 211338
B67: Acc. Payable | C67: =Inputs!B43 -> 12544 | D67: 42644 | E67: 1403 | F67: 950 | G67: 8750 | H67: 7213
B68: Current Liabilities | C68: =Inputs!B42 -> 27887 | D68: 56173 | E68: 11191 | F68: 4803 | G68: 50171 | H68: 24742
B69: Total Debt | C69: ='Fin. Data'!B58 -> 105022 | D69: 154679 | E69: 17566 | F69: =+F66-F70 -> 35144 | G69: =+G66-G70 -> 287217 | H69: =+H66-H70 -> 141682
B70: Total Equity | C70: ='Fin. Data'!B64 -> 79848 | D70: 106457 | E70: 23146 | F70: 10437 | G70: 92463 | H70: 69656

Sheet ESG
B1: Company GICS Sector: | T1: Yes
B2: Communication Services | C2: <- Select Industry | I2: 9+ | T2: No
B3: ESG Analysis | K3: Relative ESG Analysis
B4: Parameters | C4: Impact | D4: Do they report? | E4: Ranking | F4: Mitigation Plan | G4: Traffic Lights | H4: Improvement over time? | I4: Targets / Goals? | J4: Comments | K4: Parameters | L4: Comcast Corporation | M4: AT&T Inc. | N4: Paramount Global | O4: Lumen Technologies, Inc. | P4: Verizon Communications Inc. | Q4: T-Mobile US, Inc.
B5: Environmental | K5: Ratios
A6: 1 | B6: CO2 Direct Emissions | C6: low | D6: Yes | E6: Medium | J6: Goal to become carbon neutral by 2035 for Scope 1 and 2 emissions across our global operations. | K6: CO2 Emissions/$M Sales | L6: =L12/L$11 -> 0.15500021 | M6: =M12/M$11 -> 0.15193879 | N6: =N12/N$11 -> 0.071383334 | O6: =O12/O$11 -> 0.090473409 | P6: =P12/P$11 -> 0.11426427 | Q6: =Q12/Q$11 -> 0.091541114
A7: 2 | B7: Total Water Consumption | C7: =VLOOKUP($B$2,'Sector Impact'!$K$4:$AA$16,A7+1,FALSE) -> Low | K7: Water Consumption/$M Sales | L7: =L13/L$11 -> 0 | M7: =M13/M$11 -> 7.5724794e-05 | N7: =N13/N$11 -> 0 | O7: =O13/O$11 -> 0.021893653 | P7: =P13/P$11 -> 1.5118289e-05 | Q7: =Q13/Q$11 -> 0.013162872
A8: 3 | B8: Total Energy Consumption | C8: =VLOOKUP($B$2,'Sector Impact'!$K$4:$AA$16,A8+1,FALSE) -> Medium | D8: Yes | E8: Medium | F8: Yes | J8: Utilizing the latest clean technologies to green our operations and network. This means investing in clean and renewable energy, piloting electric and hybrid vehicles, and building for the future. | K8: Energy Consumption/$M Sales | L8: =L14/L$11 -> 0.18862853 | M8: =M14/M$11 -> 0.12682971 | N8: =N14/N$11 -> 0.22978206 | O8: =O14/O$11 -> 0.26529827 | P8: =P14/P$11 -> 0.04916101 | Q8: =Q14/Q$11 -> 0.10020714
A9: 4 | B9: Waste Management | C9: =VLOOKUP($B$2,'Sector Impact'!$K$4:$AA$16,A9+1,FALSE) -> Low | K9: Waste Production/$M Sales | L9: =L15/L$11 -> 0 | M9: =M15/M$11 -> 0.0014191722 | N9: =N15/N$11 -> 0 | O9: =O15/O$11 -> 0.0019890283 | P9: =P15/P$11 -> 0.00032481869 | Q9: =Q15/Q$11 -> 0.00014478644
A10: 5 | B10: Land Degradation/Deforestation/Biodiversity loss/Animal sufering/… | C10: =VLOOKUP($B$2,'Sector Impact'!$K$4:$AA$16,A10+1,FALSE) -> Low | K10: Inputs
B11: Social | K11: Net Sales ($M) | L11: =Peers!C52 -> 116385 | M11: =Peers!D52 -> 134038 | N11: =Peers!E52 -> 28586 | O11: =Peers!F52 -> 19687 | P11: =Peers!G52 -> 133613 | Q11: =Peers!H52 -> 80118
A12: 6 | B12: Employee Turnover % | C12: =VLOOKUP($B$2,'Sector Impact'!$K$4:$AA$16,A12+1,FALSE) -> Medium | D12: No | E12: Medium High | F12: No | K12: CO2 Emissions Total (Tonnes) | L12: 18039.7 | M12: 20365.571 | N12: 2040.564 | O12: 1781.15 | P12: 15267.192 | Q12: 7334.091
A13: 7 | B13: Salaries & Compensation | C13: =VLOOKUP($B$2,'Sector Impact'!$K$4:$AA$16,A13+1,FALSE) -> Medium | D13: No | E13: Medium High | F13: No | K13: Water Consumption Total (Cubic Meters) | L13: 0 | M13: 10.15 | N13: 0 | O13: 431.02034 | P13: 2.02 | Q13: 1054.583
A14: 8 | B14: Reputation | C14: =VLOOKUP($B$2,'Sector Impact'!$K$4:$AA$16,A14+1,FALSE) -> Low | K14: Energy Consumption Total (Gigajoules) | L14: 21953.532 | M14: 17000 | N14: 6568.55 | O14: 5222.927 | P14: 6568.55 | Q14: 8028.396
A15: 9 | B15: Discrimination Events | C15: =VLOOKUP($B$2,'Sector Impact'!$K$4:$AA$16,A15+1,FALSE) -> Low | F15: Yes | K15: Waste Production Total (Tonnes) | L15: 0 | M15: 190.223 | N15: 0 | O15: 39.158 | P15: 43.4 | Q15: 11.6
A16: 10 | B16: Work Safety | C16: =VLOOKUP($B$2,'Sector Impact'!$K$4:$AA$16,A16+1,FALSE) -> High | D16: Yes | E16: Medium High | F16: Yes | I16: None | J16: Robust Employee Assistance Program and generous portfolio of mental and behavioral health resources | K16: ESG Scores
A17: 11 | B17: Damage to consumer health | C17: =VLOOKUP($B$2,'Sector Impact'!$K$4:$AA$16,A17+1,FALSE) -> Low | I17: None | K17: Refinitiv | L17: 66/100 | M17: 76/100 | N17: 69/100 | P17: 72/100 | Q17: 64/100
A18: 12 | B18: PXP? | C18: =VLOOKUP($B$2,'Sector Impact'!$K$4:$AA$16,A18+1,FALSE) -> Low | K18: Sustainalytics | L18: 23,1 (Medium risk) | M18: 23,9 (Medium Risk) | N18: 15,0 (Low Risk) | O18: 26,1 (Medium Risk) | P18: 18,6 (Low Risk) | Q18: 24,7 (Medium Risk)
A19: 13 | B19: Supply chain | C19: =VLOOKUP($B$2,'Sector Impact'!$K$4:$AA$16,A19+1,FALSE) -> Low | I19: None | K19: ISS
A20: 14 | B20: Community involvement | C20: =VLOOKUP($B$2,'Sector Impact'!$K$4:$AA$16,A20+1,FALSE) -> Low | K20: CDP | L20: B | M20: A | N20: B | O20: B | P20: B | Q20: A-
A21: 15 | B21: Public Sector | C21: =VLOOKUP($B$2,'Sector Impact'!$K$4:$AA$16,A21+1,FALSE) -> Low | I21: None
A22: 16 | B22: Litigation | C22: =VLOOKUP($B$2,'Sector Impact'!$K$4:$AA$16,A22+1,FALSE) -> Medium | D22: Yes | E22: Medium | F22: No | H22: Yes | I22: None | J22: No major law-suits in the last 5 years
B23: Corporate Governance | K23: PARAMETERS
A24: 17 | B24: Diversity (Gender, Age, Industry, Region) | E24: Medium | F24: Yes | I24: Aspiration to have 50% women and 33% people of color at every level of our workforce. | J24: Board of Directors is 50% diverse by people of color and gender | K24: IMPACT | L24: RANKING | M24: MITIGATION PLAN
A25: 18 | B25: % Independence | E25: Medium High | F25: No | I25: None | J25: 89% of Board membersand are independent (1 out of 9 is non-independent) | K25: Low | L25: "Best in class" | M25: Evidence / plan?
A26: 19 | B26: average time as independent directors | E26: Medium High | F26: No | I26: None | J26: Independence director tenure has an average of10 years | K26: Medium | L26: Medium High
A27: 20 | B27: Recent departures of directors / C-level executives? | E27: Medium High | F27: No | I27: None | J27: Maritza G. Montiel has been a director since 2018, being the most recent change to the board | K27: High | L27: Medium
A28: 21 | B28: CEO/Chairman duality | E28: Medium | F28: No | I28: None | J28: Brian L. Roberts is the Chairman, President and Chief Executive Officer of Comcast | K28: Very high | L28: "Villain"
A29: 22 | B29: Transparency (ESG, segments, acquisitions, other) | E29: Medium High | F29: No | I29: None | J29: The information of the board about their public profile is available and accurately disclosed
A30: 23 | B30: Time taken to report after the end of the quarter / year | E30: Medium High | F30: No | I30: None | J30: On Jan. 26, 2023, Comcast Corporation reported results for the quarter and year ended December 31, 2022.
A31: 24 | B31: Additional participation of the CEO in other boards or excessive participation of Ch. | E31: Medium | F31: No | I31: None | J31: The Ceo and Chairman, Brian L. Roberts is not present in any other committee
A32: 25 | B32: Audit / Consulting | D32: Yes | E32: Medium | F32: No | J32: In 2021 they paid 27,4 millions for the services of Deloitte
A33: 26 | B33: ESG-compensation related | D33: No | E33: Medium | F33: No | I33: None | J33: None
A34: 27 | B34: Management compensation schemes | D34: Yes | E34: Medium High | F34: No | I34: None | J34: Base salary, Annueal Cash Bonus, Annueal PSU Grants and Annual Stock Option Grants

Sheet DCF
A1: VALUATION MODEL
G3: Short Term | K3: Long Term
A4: Section | B4: Line # | C4: ITEM | D4: 2020 (Real) | E4: 2021 (Real) | F4: 2022 (Real) | G4: 2023 | H4: =G4+1 -> 2024 | I4: =H4+1 -> 2025 | J4: =I4+1 -> 2026 | K4: =J4+1 -> 2027 | L4: =K4+1 -> 2028 | M4: =L4+1 -> 2029 | N4: =M4+1 -> 2030 | O4: =N4+1 -> 2031 | ... AF4: =AE4+1 -> 2048
A5: INCOME STATEMENT | B5: 1 | C5: Growth | D5: ='Fin. Data'!D6 -> -0.049365718 | E5: =+E6/D6-1 -> 0.12379784 | F5: =+F6/E6-1 -> 0.043321734 | G5: =+G6/F6-1 -> 0.035 | H5: =+H6/G6-1 -> 0.036428571 | I5: =+I6/H6-1 -> 0.038095238 | J5: =+J6/I6-1 -> 0.039761905 | K5: =+K6/J6-1 -> 0.041428571 | L5: =+L6/K6-1 -> 0.043095238 | ... AF5: =+AF6/AE6-1 -> 0.02
B6: 2 | C6: Revenues/Sales | D6: 103564 | E6: 116385 | F6: 121427 | G6: =Assum.!I8 -> 125676.94 | H6: =Assum.!J8 -> 130255.18 | I6: =Assum.!K8 -> 135217.28 | J6: =Assum.!L8 -> 140593.78 | K6: =Assum.!M8 -> 146418.37 | L6: =Assum.!N8 -> 152728.31 | M6: =Assum.!O8 -> 159564.72 | N6: =Assum.!P8 -> 166745.13 | ... AF6: =Assum.!AH8 -> 250028.98
B7: 3 | C7: EBIT/Operating Margin | D7: =D8/D6 -> 0.16891005 | E7: =E8/E6 -> 0.17886326 | F7: =F8/F6 -> 0.11563326 | G7: =0.126 -> 0.126 | H7: =+G7*(1+H5) -> 0.13059 | I7: =+$G$7*(1+I5) -> 0.1308 | J7: =+$G$7*(1+J5) -> 0.13101 | K7: =+$G$7*(1+K5) -> 0.13122 | L7: =+$G$7*(1+L5) -> 0.13143 | M7: =+$G$7*(1+M5) -> 0.13164 | N7: =+$G$7*(1+N5) -> 0.13167 | O7: =+$G$7*(1+O5) -> 0.13104 | P7: =+$G$7*(1+P5) -> 0.13041 | ... AF7: =+$G$7*(1+AF5) -> 0.12852
B8: 4 | C8: EBIT | D8: ='Fin. Data'!D11 -> 17493 | E8: ='Fin. Data'!C11 -> 20817 | F8: ='Fin. Data'!B11 -> 14041 | G8: =G7*G6 -> 15835.295 | H8: =H7*H6 -> 17010.024 | I8: =I7*I6 -> 17686.42 | J8: =J7*J6 -> 18419.19 | K8: =K7*K6 -> 19213.019 | L8: =L7*L6 -> 20073.082 | M8: =M7*M6 -> 21005.1 | N8: =N7*N6 -> 21955.331 | ... AF8: =AF7*AF6 -> 32133.724
B9: 5a | C9: (Dep) | D9: -8320 | E9: -8628 | F9: -8724 | G9: =$D$53*DCF!F40 -> -8886.892 | H9: =$D$53*DCF!G40 -> -10520.905 | I9: =$D$53*DCF!H40 -> -12214.442 | J9: =$D$53*DCF!I40 -> -13972.495 | K9: =$E$53*DCF!J40 -> -15303.671 | L9: =$E$53*DCF!K40 -> -17147.504 | M9: =$E$53*DCF!L40 -> -19070.797 | N9: =$E$53*DCF!M40 -> -21080.18 | O9: =$E$53*DCF!N40 -> -23179.986 | P9: =$E$53*DCF!O40 -> -25363.783 | Q9: =$E$53*DCF!P40 -> -27624.014 | R9: =$E$53*DCF!Q40 -> -29952.052 | ... AF9: =$E$53*DCF!AE40 -> -68069.679 | AG9: =SUM(D9:AF9) -> -942949.43
B10: 5b | C10: Amort | D10: -4780 | E10: -5176 | F10: -5097 | G10: =F38*$D$54 -> -4833.5105 | H10: =G38*$D$54 -> -5097.1993 | I10: =H38*$D$54 -> -5375.2734 | J10: =I38*$D$54 -> -5668.5177 | K10: =J38*$E$54 -> -4382.98 | L10: =K38*$E$54 -> -4558.2992 | M10: =L38*$E$54 -> -4740.6312 | N10: =M38*$E$54 -> -4930.2565 | O10: =N38*$E$54 -> -5127.4667 | P10: =O38*$E$54 -> -5332.5654 | Q10: =P38*$E$54 -> -5545.868 | R10: =Q38*$E$54 -> -5767.7027 | ... AF10: =AE38*$E$54 -> -9987.795
B11: 5c | C11: (Stock based compensation) | D11: =D20 -> -1193 | E11: =E20 -> -1315 | F11: =F20 -> -1336 | G11: =G6*$D$55 -> -1305.3487 | H11: =H6*$D$55 -> -1352.9006 | I11: =I6*$D$55 -> -1404.4397 | J11: =J6*$D$55 -> -1460.2829 | K11: =K6*$D$55 -> -1520.7804 | L11: =L6*$D$55 -> -1586.3187 | M11: =M6*$D$55 -> -1657.3254 | N11: =N6*$D$55 -> -1731.905 | ... AF11: =AF6*$D$55 -> -2596.9361
B12: 6 | C12: EBIDTA | D12: =D8-D9-D10 -> 30593 | E12: =E8-E9-E10 -> 34621 | F12: =F8-F9-F10 -> 27862 | G12: =G8-G9-G10 -> 29555.698 | H12: =H8-H9-H10 -> 32628.127 | I12: =I8-I9-I10 -> 35276.135 | J12: =J8-J9-J10 -> 38060.203 | K12: =K8-K9-K10 -> 38899.67 | ... AF12: =AF8-AF9-AF10 -> 110191.2
B13: 7 | C13: (Net financing cost) | D13: ='Fin. Data'!D14 -> -4588 | E13: ='Fin. Data'!C14 -> -4281 | F13: ='Fin. Data'!B14 -> -3896 | G13: =F43*$D$58-F44*$D$57 -> -3897.3799 | H13: =G43*$D$58-G44*$D$57 -> -3807.0092 | I13: =H43*$D$58-H44*$D$57 -> -3628.1916 | J13: =I43*$D$58-I44*$D$57 -> -3389.5502 | K13: =J43*$E$58-J44*$E$57 -> -4007.1143 | L13: =K43*$E$58-K44*$E$57 -> -3704.5513 | M13: =L43*$E$58-L44*$E$57 -> -3575.0124 | N13: =M43*$E$58-M44*$E$57 -> -3521.5208 | O13: =N43*$E$58-N44*$E$57 -> -3426.3004 | P13: =O43*$E$58-O44*$E$57 -> -3275.9099 | Q13: =P43*$E$58-P44*$E$57 -> -3070.7374 | R13: =Q43*$E$58-Q44*$E$57 -> -2806.3797 | ... AF13: =AE43*$E$58-AE44*$E$57 -> 7288.3211
B14: 8 | C14: Other income/(cost) | D14: ='Fin. Data'!D15 -> 1160 | E14: ='Fin. Data'!C15 -> 2556 | F14: ='Fin. Data'!B15 -> -861 | G14: =AVERAGE(D14:F14)*(1+G5) -> 984.975 | H14: =AVERAGE(E14:G14)*(1+H5) -> 925.86755 | I14: =AVERAGE(F14:H14)*(1+I5) -> 363.27885 | J14: =AVERAGE(G14:I14)*(1+J5) -> 788.1816 | K14: =AVERAGE(H14:J14)*(1+K5) -> 721.12958 | L14: =AVERAGE(I14:K14)*(1+L5) -> 651.09658 | M14: =AVERAGE(J14:L14)*(1+M5) -> 752.37058 | N14: =AVERAGE(K14:M14)*(1+N5) -> 740.06786 | ... AF14: =AVERAGE(AC14:AE14)*(1+AF5) -> 899.18941
B15: 9 | C15: Earnings before taxes | D15: =D8+D13+D14 -> 14065 | E15: =E8+E13+E14 -> 19092 | F15: =F8+F13+F14 -> 9284 | G15: =G8+G13+G14 -> 12922.89 | H15: =H8+H13+H14 -> 14128.882 | I15: =I8+I13+I14 -> 14421.507 | J15: =J8+J13+J14 -> 15817.822 | K15: =K8+K13+K14 -> 15927.034 | ... AF15: =AF8+AF13+AF14 -> 40321.235
B16: 10 | C16: (Income tax) | D16: ='Fin. Data'!D21 -> -3364 | E16: ='Fin. Data'!C21 -> -5259 | F16: ='Fin. Data'!B21 -> -4359 | G16: =-(1*$D$56)*G15 -> -3077.6863 | H16: =-(1*$D$56)*H15 -> -3364.9025 | I16: =-(1*$D$56)*I15 -> -3434.5935 | J16: =-(1*$D$56)*J15 -> -3767.1367 | K16: =-(1*$E$56)*K15 -> -4300.2993 | L16: =-(1*$E$56)*L15 -> -4595.2993 | M16: =-(1*$E$56)*M15 -> -4909.2636 | N16: =-(1*$E$56)*N15 -> -5176.9472 | O16: =-(1*$E$56)*O15 -> -5411.093 | P16: =-(1*$E$56)*P15 -> -5643.5174 | Q16: =-(1*$E$56)*Q15 -> -5857.8059 | R16: =-(1*$E$56)*R15 -> -6061.0154 | ... AF16: =-(1*$E$56)*AF15 -> -10886.733
B17: 11 | C17: Net income | D17: ='Fin. Data'!D23 -> 10701 | E17: ='Fin. Data'!C23 -> 13833 | F17: ='Fin. Data'!B23 -> 4925 | G17: =G16+G15 -> 9845.2039 | H17: =H16+H15 -> 10763.979 | I17: =I16+I15 -> 10986.914 | J17: =J16+J15 -> 12050.685 | K17: =K16+K15 -> 11626.735 | L17: =L16+L15 -> 12424.328 | M17: =M16+M15 -> 13273.194 | N17: =N16+N15 -> 13996.931 | ... AF17: =AF16+AF15 -> 29434.501
A19: CASH FLOW STATEMENT | B19: 12 | C19: Operating cash flows before WK | D19: =D17-D9-D10-550-D11+24737-23073 -> 26108 | E19: =E17-E9-E10+1892-E11+29146-28030 -> 31960 | F19: =F17-F9-F10-F11+8583+2090 -> 30755 | G19: =G17-G10-G9-G11 -> 24870.955 | H19: =H17-H10-H9-H11 -> 27734.984 | I19: =I17-I10-I9-I11 -> 29981.069 | J19: =J17-J10-J9-J11 -> 33151.981 | K19: =K17-K10-K9-K11 -> 32834.167 | L19: =L17-L10-L9-L11 -> 35716.449 | M19: =M17-M10-M9-M11 -> 38741.948 | N19: =N17-N10-N9-N11 -> 41739.273 | ... AF19: =AF17-AF10-AF9-AF11 -> 110088.91
B20: 13 | C20: (Stock-based compensation) | D20: -1193 | E20: -1315 | F20: -1336 | G20: =G11 -> -1305.3487 | H20: =H11 -> -1352.9006 | I20: =I11 -> -1404.4397 | J20: =J11 -> -1460.2829 | K20: =K11 -> -1520.7804 | L20: =L11 -> -1586.3187 | M20: =M11 -> -1657.3254 | N20: =N11 -> -1731.905 | ... AF20: =AF11 -> -2596.9361
B21: 14 | C21: (Working Capital Flows) | D21: =Inputs!D62 -> -178 | E21: =Inputs!C62 -> -1499 | F21: =Inputs!B62 -> -3006 | G21: =$D$60*(G6-F6) -> -573.28206 | H21: =$D$60*(H6-G6) -> -617.56518 | I21: =$D$60*(I6-H6) -> -669.34608 | J21: =$D$60*(J6-I6) -> -725.24445 | K21: =$E$60*(K6-J6) -> -785.68976 | L21: =$E$60*(L6-K6) -> -851.15746 | M21: =$E$60*(M6-L6) -> -922.17458 | N21: =$E$60*(N6-M6) -> -968.57762 | O21: =$E$60*(O6-N6) -> -899.70099 | P21: =$E$60*(P6-O6) -> -818.7279 | Q21: =$E$60*(Q6-P6) -> -726.32861 | R21: =$E$60*(R6-Q6) -> -623.43205 | ... AF21: =$E$60*(AF6-AE6) -> -661.31019
B22: 15 | C22: -Total Operating Cash Flow | D22: =D19+D20+D21 -> 24737 | E22: =E19+E20+E21 -> 29146 | F22: =F19+F20+F21 -> 26413 | G22: =G19+G20+G21 -> 22992.324 | H22: =H19+H20+H21 -> 25764.518 | I22: =I19+I20+I21 -> 27907.283 | J22: =J19+J20+J21 -> 30966.454 | K22: =K19+K20+K21 -> 30527.696 | ... AF22: =AF19+AF20+AF21 -> 106830.66
B23: 16 | C23: (CAPEX) | D23: ='Fin. Data'!D32 -> -9179 | E23: ='Fin. Data'!C32 -> -9174 | F23: ='Fin. Data'!B32 -> -10626 | G23: =G6*$D$62 -> -11304.556 | H23: =H6*$D$62 -> -11716.364 | I23: =I6*$D$62 -> -12162.702 | J23: =J6*$D$62 -> -12646.314 | K23: =K6*$E$62 -> -13170.233 | L23: =L6*$E$62 -> -13737.807 | M23: =M6*$E$62 -> -14352.738 | N23: =N6*$E$62 -> -14998.611 | O23: =O6*$E$62 -> -15598.555 | P23: =P6*$E$62 -> -16144.505 | Q23: =Q6*$E$62 -> -16628.84 | R23: =R6*$E$62 -> -17044.561 | ... AF23: =AF6*$E$62 -> -22489.936 | AG23: =SUM(D23:AF23) -> -476198.93
B24: 17 | C24: Adq | D24: =Inputs!D66 -> -233 | E24: ='Fin. Data'!C33 -> -1374 | F24: ='Fin. Data'!B33 -> -12 | G24: =G6*$D$63 -> -555.09983 | H24: =H6*$D$63 -> -575.32132 | I24: =I6*$D$63 -> -597.23832 | J24: =J6*$D$63 -> -620.98566 | K24: =K6*$E$63 -> -6895.7318 | L24: =L6*$E$63 -> -7192.905 | M24: =M6*$E$63 -> -7514.8731 | N24: =N6*$E$63 -> -7853.0424 | O24: =O6*$E$63 -> -8167.1641 | P24: =P6*$E$63 -> -8453.0149 | Q24: =Q6*$E$63 -> -8706.6053 | R24: =R6*$E$63 -> -8924.2705 | ... AF24: =AF6*$E$63 -> -11775.385 | AH24: =AG9-AG23 -> -466750.51
B25: 18 | C25: (Other investing flows) | D25: =Inputs!D67 -> -2635 | E25: =Inputs!C67 -> -2898 | F25: =Inputs!B67 -> -3502 | G25: =(1+G5)*AVERAGE(D25:F25) -> -3117.075 | H25: =(1+H5)*AVERAGE(E25:G25) -> -3287.9228 | I25: =(1+I5)*AVERAGE(F25:H25) -> -3428.1358 | J25: =(1+J5)*AVERAGE(G25:I25) -> -3408.0392 | K25: =(1+K5)*AVERAGE(H25:J25) -> -3514.5082 | L25: =(1+L5)*AVERAGE(I25:K25) -> -3598.9161 | M25: =(1+M5)*AVERAGE(J25:L25) -> -3664.1414 | N25: =(1+N5)*AVERAGE(K25:M25) -> -3754.1854 | ... AF25: =(1+AF5)*AVERAGE(AC25:AE25) -> -4560.2077
B26: 19 | C26: -Total Investing Flows | D26: =D23+D24+D25 -> -12047 | E26: =E23+E24+E25 -> -13446 | F26: =F23+F24+F25 -> -14140 | G26: =G23+G24+G25 -> -14976.73 | H26: =H23+H24+H25 -> -15579.609 | I26: =I23+I24+I25 -> -16188.076 | J26: =J23+J24+J25 -> -16675.339 | K26: =K23+K24+K25 -> -23580.473 | ... AF26: =AF23+AF24+AF25 -> -38825.529
B27: 20 | C27: (Flows related to leases) | D27: =Inputs!D71+Inputs!D72 -> 0 | E27: =Inputs!C71+Inputs!C72 -> 0 | F27: =Inputs!B71+Inputs!B72 -> 0 | G27: 0 | H27: 0 | I27: 0 | J27: 0 | K27: 0 | L27: 0 | M27: 0 | N27: 0 | O27: 0 | P27: 0 | Q27: 0 | R27: 0 | S27: 0 | T27: 0 | U27: 0 | V27: 0 | W27: 0 | X27: 0 | Y27: 0 | Z27: 0 | AA27: 0 | AB27: 0 | AC27: 0 | AD27: 0 | AE27: 0 | AF27: 0
B28: 21 | C28: Flows related to debt | D28: =+SUM(Inputs!D69:D70) -> -133 | E28: =+SUM(Inputs!C69:C70) -> -8870 | F28: =+SUM(Inputs!B69:B70) -> 438 | G28: =G44-F44 -> -4532.6282 | H28: =H44-G44 -> -2604.9896 | I28: =I44-H44 -> -9694.0437 | J28: =J44-I44 -> -4457.8915 | K28: =K44-J44 -> -9823.0737 | L28: =L44-K44 -> -2885.2696 | M28: =M44-L44 -> 682.34028 | N28: =N44-M44 -> 242.20781 | ... AF28: =AF44-AE44 -> 410.1073
B29: 22 | C29: (Respurchases)/Issuance of stock | D29: ='Fin. Data'!D28 -> -534 | E29: ='Fin. Data'!C28 -> -4672 | F29: ='Fin. Data'!B28 -> -13328 | G29: =-G17*$D$65 -> -2151.0915 | H29: =-H17*$D$65 -> -2351.836 | I29: =-I17*$D$65 -> -2400.5452 | J29: =-J17*$D$65 -> -2632.9701 | K29: =-K17*$E$65 -> -2540.3406 | L29: =-L17*$E$65 -> -2714.6077 | M29: =-M17*$E$65 -> -2900.0776 | N29: =-N17*$E$65 -> -3058.2079 | O29: =-O17*$E$65 -> -3196.5262 | P29: =-P17*$E$65 -> -3333.8276 | Q29: =-Q17*$E$65 -> -3460.4155 | R29: =-R17*$E$65 -> -3580.4586 | ... AF29: =-AF17*$E$65 -> -6431.1829
B30: 23 | C30: (Dividends) | D30: ='Fin. Data'!D27 -> -4140 | E30: ='Fin. Data'!C27 -> -4532 | F30: ='Fin. Data'!B27 -> -4741 | G30: =-$D$64*G17 -> -3212.6855 | H30: =-$D$64*H17 -> -3512.5002 | I30: =-$D$64*I17 -> -3585.2481 | J30: =-$D$64*J17 -> -3932.3779 | K30: =-$E$64*K17 -> -3794.0345 | L30: =-$E$64*L17 -> -4054.3048 | M30: =-$E$64*M17 -> -4331.3068 | N30: =-$E$64*N17 -> -4567.4766 | O30: =-$E$64*O17 -> -4774.0569 | P30: =-$E$64*P17 -> -4979.1186 | Q30: =-$E$64*Q17 -> -5168.1793 | R30: =-$E$64*R17 -> -5347.4655 | ... AF30: =-$E$64*AF17 -> -9605.0623
B31: 24 | C31: Other financing flows | D31: =Inputs!D75 -> -1706 | E31: =Inputs!C75 -> -544 | F31: =Inputs!B75 -> 1447 | G31: =(1+G5)*AVERAGE(D31:F31) -> -277.035 | H31: =(1+H5)*AVERAGE(E31:G31) -> 216.256 | I31: =(1+I5)*AVERAGE(F31:H31) -> 479.67647 | J31: =(1+J5)*AVERAGE(G31:I31) -> 145.18455 | K31: =(1+K5)*AVERAGE(H31:J31) -> 291.98777 | L31: =(1+L5)*AVERAGE(I31:K31) -> 318.78687 | M31: =(1+M5)*AVERAGE(J31:L31) -> 263.26578 | N31: =(1+N5)*AVERAGE(K31:M31) -> 304.45741 | ... AF31: =(1+AF5)*AVERAGE(AC31:AE31) -> 361.46152
B32: 25 | C32: -Total Financing flows | D32: =D27+D28+D29+D30+D31 -> -6513 | E32: =E27+E28+E29+E30+E31 -> -18618 | F32: =F27+F28+F29+F30+F31 -> -16184 | G32: =G27+G28+G29+G30+G31 -> -10173.44 | H32: =H27+H28+H29+H30+H31 -> -8253.0697 | I32: =I27+I28+I29+I30+I31 -> -15200.161 | J32: =J27+J28+J29+J30+J31 -> -10878.055 | K32: =K27+K28+K29+K30+K31 -> -15865.461 | ... AF32: =AF27+AF28+AF29+AF30+AF31 -> -15264.676
A34: SUMMARY | B34: 26 | C34: Cash before shareholder returns | D34: =D22+D26+D27+D28+D31 -> 10851 | E34: =E22+E26+E27+E28+E31 -> 6286 | F34: =F22+F26+F27+F28+F31 -> 14158 | G34: =G22+G26+G27+G28+G31 -> 3205.9308 | H34: =H22+H26+H27+H28+H31 -> 7796.176 | I34: =I22+I26+I27+I28+I31 -> 2504.8397 | J34: =J22+J26+J27+J28+J31 -> 9978.4074 | K34: =K22+K26+K27+K28+K31 -> -2583.8626 | ... AF34: =AF22+AF26+AF27+AF28+AF31 -> 68776.704
B35: 27 | C35: Returns to shareholders | D35: =-1*(D29+D30) -> 4674 | E35: =-1*(E29+E30) -> 9204 | F35: =-1*(F29+F30) -> 18069 | G35: =-1*(G29+G30) -> 5363.7771 | H35: =-1*(H29+H30) -> 5864.3362 | I35: =-1*(I29+I30) -> 5985.7934 | J35: =-1*(J29+J30) -> 6565.348 | K35: =-1*(K29+K30) -> 6334.3751 | ... AF35: =-1*(AF29+AF30) -> 16036.245
B36: 28 | C36: Excess cash acumulation | D36: =D34-D35 -> 6177 | E36: =E34-E35 -> -2918 | F36: =F34-F35 -> -3911 | G36: =G34-G35 -> -2157.8463 | H36: =H34-H35 -> 1931.8398 | I36: =I34-I35 -> -3480.9536 | J36: =J34-J35 -> 3413.0595 | K36: =K34-K35 -> -8918.2377 | ... AF36: =AF34-AF35 -> 52740.459
A38: BALANCE SHEET | B38: 29 | C38: Intangible assets | D38: =114579-19825 -> 94754 | E38: =116491-23545 -> 92946 | F38: =114500-25900 -> 88600 | G38: =+F38+(-G10) -> 93433.511 | H38: =+G38+(-H10) -> 98530.71 | I38: =+H38+(-I10) -> 103905.98 | J38: =+I38+(-J10) -> 109574.5 | K38: =+J38+(-K10) -> 113957.48 | L38: =+K38+(-L10) -> 118515.78 | M38: =+L38+(-M10) -> 123256.41 | N38: =+M38+(-N10) -> 128186.67 | ... AF38: =+AE38+(-AF10) -> 259682.67 | AG38: =SUM(G38:AF38) -> 4308257.1
B39: 30 | C39: Accumulated amorization | D39: 19825 | E39: 23545 | F39: 25900 | G39: =F39-G10 -> 30733.511 | H39: =G39-H10 -> 35830.71 | I39: =H39-I10 -> 41205.983 | J39: =I39-J10 -> 46874.501 | K39: =J39-K10 -> 51257.481 | L39: =K39-L10 -> 55815.78 | M39: =L39-M10 -> 60556.411 | N39: =M39-N10 -> 65486.668 | ... AF39: =AE39-AF10 -> 196982.67 | AG39: =SUM(G39:AF39) -> 2678057.1
B40: 31 | C40: PPE+Right of use Assets | D40: =+Inputs!D33+Inputs!D34 -> 55779 | E40: =+Inputs!C33+Inputs!C34 -> 60514 | F40: =+Inputs!B33+Inputs!B34 -> 61482 | G40: =F40+(-G23) -> 72786.556 | H40: =G40+(-H23) -> 84502.92 | I40: =H40+(-I23) -> 96665.622 | J40: =I40+(-J23) -> 109311.94 | K40: =J40+(-K23) -> 122482.17 | L40: =K40+(-L23) -> 136219.98 | M40: =L40+(-M23) -> 150572.71 | N40: =M40+(-N23) -> 165571.33 | ... AF40: =AE40+(-AF23) -> 508701.93 | AG40: =SUM(G40:AF40) -> 6988962
B41: 32 | C41: Accumulated depreciation | D41: 54388 | E41: 55611 | F41: 56900 | G41: =F41-G9 -> 65786.892 | H41: =G41-H9 -> 76307.797 | I41: =H41-I9 -> 88522.239 | J41: =I41-J9 -> 102494.73 | K41: =J41-K9 -> 117798.4 | L41: =K41-L9 -> 134945.91 | M41: =L41-M9 -> 154016.71 | N41: =M41-N9 -> 175096.89 | ... AF41: =AE41-AF9 -> 974177.43 | AG41: =SUM(G41:AF41) -> 10378847
A43: CASH & DEBT & DISCOUNTING | B43: 33 | C43: Ending cash balance | D43: ='Fin. Data'!D39 -> 11740 | E43: =E36+D43 -> 8822 | F43: =F36+E43 -> 4911 | G43: =G36+F43 -> 2753.1537 | H43: =H36+G43 -> 4684.9935 | I43: =I36+H43 -> 1204.0399 | J43: =J36+I43 -> 4617.0993 | K43: =K36+J43 -> -4301.1384 | L43: =L36+K43 -> -4887.1889 | ... AF43: =AF36+AE43 -> 443126.84
B44: 34 | C44: Total Debt | D44: ='Fin. Data'!D58 -> 110240 | E44: ='Fin. Data'!C58 -> 105127 | F44: ='Fin. Data'!B58 -> 105022 | G44: =G12*3.4 -> 100489.37 | H44: =H12*3 -> 97884.382 | I44: =I12*2.5 -> 88190.339 | J44: =J12*2.2 -> 83732.447 | K44: =K12*1.9 -> 73909.373 | L44: =L12*Assum.!L22 -> 71024.104 | M44: =M12*Assum.!M22 -> 71706.444 | N44: =N12*Assum.!N22 -> 71948.652 | O44: =O12*Assum.!O22 -> 71444.444 | P44: =P12*Assum.!P22 -> 70333.792 | Q44: =Q12*Assum.!Q22 -> 68594.616 | R44: =R12*Assum.!R22 -> 66211.729 | S44: =S12*Assum.!S22 -> 63177.115 | ... AF44: =AF12*Assum.!AF22 -> 11019.12
B45: 35 | C45: Discount factor | F45: =1/((1+$F$50)^G50) -> 1 | G45: =1/((1+$F$50)^G49) -> 0.91533181 | H45: =1/((1+$F$50)^H49) -> 0.83783232 | I45: =1/((1+$F$50)^I49) -> 0.76689457 | J45: =1/((1+$F$50)^J49) -> 0.70196299 | K45: =1/((1+$F$50)^K49) -> 0.64252906 | L45: =1/((1+$F$50)^L49) -> 0.58812728 | M45: =1/((1+$F$50)^M49) -> 0.53833161 | N45: =1/((1+$F$50)^N49) -> 0.49275204 | ... AF45: =1/((1+$F$50)^AF49) -> 0.10024031
B46: 36 | C46: DF + 0.1% | E46: +0.1% | F46: =1/((1+$F$50+0.001)^G50) -> 1 | G46: =1/((1+$F$50+0.001)^G49) -> 0.91449474 | H46: =1/((1+$F$50+0.001)^H49) -> 0.83630063 | I46: =1/((1+$F$50+0.001)^I49) -> 0.76479253 | J46: =1/((1+$F$50+0.001)^J49) -> 0.69939875 | K46: =1/((1+$F$50+0.001)^K49) -> 0.63959648 | L46: =1/((1+$F$50+0.001)^L49) -> 0.58490762 | M46: =1/((1+$F$50+0.001)^M49) -> 0.53489494 | N46: =1/((1+$F$50+0.001)^N49) -> 0.48915861 | ... AF46: =1/((1+$F$50+0.001)^AF49) -> 0.097883959
B47: 37 | C47: DF+0.5% | E47: +0.5% | F47: =1/((1+$F$50+0.005)^G50) -> 1 | G47: =1/((1+$F$50+0.005)^G49) -> 0.91116173 | H47: =1/((1+$F$50+0.005)^H49) -> 0.8302157 | I47: =1/((1+$F$50+0.005)^I49) -> 0.75646077 | J47: =1/((1+$F$50+0.005)^J49) -> 0.68925811 | K47: =1/((1+$F$50+0.005)^K49) -> 0.62802561 | L47: =1/((1+$F$50+0.005)^L49) -> 0.5722329 | M47: =1/((1+$F$50+0.005)^M49) -> 0.52139672 | N47: =1/((1+$F$50+0.005)^N49) -> 0.47507674 | ... AF47: =1/((1+$F$50+0.005)^AF49) -> 0.089018905
A49: Discount Rate | C49: Risk free rate | D49: Equity premium | E49: Firm premium | F49: Total | G49: 1 | H49: 2 | I49: 3 | J49: 4 | K49: 5 | L49: 6 | M49: 7 | N49: 8 | O49: 9 | P49: 10 | Q49: 11 | R49: 12 | S49: 13 | T49: 14 | U49: 15 | V49: 16 | W49: 17 | X49: 18 | Y49: 19 | Z49: 20 | AA49: 21 | AB49: 22 | AC49: 23 | AD49: 24 | AE49: 25 | AF49: 26
C50: 0.04 | D50: 0.045 | E50: 0.0075 | F50: =E50+D50+C50 -> 0.0925 | G50: 0
A52: Modelling factors | D52: Short Term | E52: Long Term | F52: Reference (line)
C53: Depreciation factor | D53: =Assum.!I15 -> -0.14454461 | E53: =-0.14 -> -0.14 | F53: % PPE
C54: Amortization factor | D54: =Assum.!I16 -> -0.054554295 | E54: =-0.04 -> -0.04 | F54: % IA
C55: Stock-based comp | D55: =Assum.!I19 -> -0.01038654 | E55: =+-0.01 -> -0.01 | F55: % revenue
C56: Tax Rate | D56: =-Assum.!I34 -> 0.23815774 | E56: 0.27 | F56: % (line 9)
C57: Interest Rate on debt | D57: =+Assum.!O65 -> 0.038980594 | E57: =+Assum.!N65 -> 0.048958993 | F57: % debt (l29)
C58: Interest Rate on cash | D58: 0.04 | E58: 0.02 | F58: % of cash (l28)
C59: PPE+ROA | F59: Growing with capex
C60: Working capital flows | D60: =Assum.!O45 -> -0.13489164 | E60: =D60 -> -0.13489164 | F60: % of change revenues (l2)
C61: Intangible Assets | D61: =D54 -> -0.054554295 | E61: =D61 -> -0.054554295 | F61: Growing with amortization
C62: Capex | D62: =+Assum.!I13 -> -0.089949319 | E62: =D62 -> -0.089949319 | F62: % revenue (l2)
C63: Acquisition factor | D63: =Assum.!I14 -> -0.0044168787 | E63: =Assum.!J14 -> -0.047096082 | F63: % revenue (l2)
C64: Dividends | D64: =-Assum.!J27 -> 0.32631986 | E64: =-Assum.!J27 -> 0.32631986 | F64: % net income (11)
C65: Repurchases | D65: =-Assum.!I30 -> 0.21849131 | E65: =-Assum.!I30 -> 0.21849131 | F65: % net income (11)
C66: Leases | F66: % revenue (l2)
C67: Cash Costs for EBIT | F67: % revenue (l2)
A69: Valuation | D69: $ millions
C70: Value of flows | D70: =SUMPRODUCT(G35:AF35,G45:AF45)+((AF43-AF44)*AF45) -> 122136.12 | E70: =D70/D72 -> 0.56224718
C71: Value of perpetuity | D71: =(AF34/(F50-AF5))*AF45 -> 95092.391 | E71: =D71/D72 -> 0.43775282
C72: Total Value | D72: =D70+D71 -> 217228.51
C73: Actual share price | D73: =OP!C19 -> 40.545
C74: Total value vs Mkt Cap | D74: =D75/D73-1 -> 0.3835277
C75: Estimated NPV per share | D75: =D72*1000000/OP!C20 -> 56.095131
A77: Sensibility | C77: Sensitivity +0.1% | D77: =(SUMPRODUCT(G35:AF35,G45:AF45)+((AF43-AF44)*AF45)+(AF34/(F50+0.001-AF5))*AF45)*1000000/OP!C20 -> 55.761038 | E77: =D77/D75-1 -> -0.0059558207
C78: Sensitivity +0.5% | D78: =(SUMPRODUCT(G35:AF35,G45:AF45)+((AF43-AF44)*AF45)+(AF34/(F50+0.005-AF5))*AF45)*1000000/OP!C20 -> 54.510886 | E78: =D78/D75-1 -> -0.028242117
A80: Notes

Sheet Fin. Data (Common Size)
A1: =Inputs!H3 -> #VALUE!
A2: =Inputs!G2 -> Figures in Millions of USD
A3: Results
B4: =OP!J19 -> 2022 | C4: =B4-1 -> 2021 | D4: =C4-1 -> 2020 | E4: =D4-1 -> 2019 | F4: =E4-1 -> 2018 | G4: =F4-1 -> 2017 | H4: =G4-1 -> 2016 | I4: =H4-1 -> 2015 | J4: =I4-1 -> 2014 | ... M4: =L4-1 -> 2011
A5: Net Sales | B5: =_xlfn.XLOOKUP($A5,Inputs!$A:$A,Inputs!B:B,,0) -> 121427 | C5: =_xlfn.XLOOKUP($A5,Inputs!$A:$A,Inputs!C:C,,0) -> 116385 | D5: =_xlfn.XLOOKUP($A5,Inputs!$A:$A,Inputs!D:D,,0) -> 103564 | E5: =_xlfn.XLOOKUP($A5,Inputs!$A:$A,Inputs!E:E,,0) -> 108942 | F5: =_xlfn.XLOOKUP($A5,Inputs!$A:$A,Inputs!F:F,,0) -> 94507 | G5: =_xlfn.XLOOKUP($A5,Inputs!$A:$A,Inputs!G:G,,0) -> 85029 | H5: =_xlfn.XLOOKUP($A5,Inputs!$A:$A,Inputs!H:H,,0) -> 80736 | I5: =_xlfn.XLOOKUP($A5,Inputs!$A:$A,Inputs!I:I,,0) -> 74510 | J5: =_xlfn.XLOOKUP($A5,Inputs!$A:$A,Inputs!J:J,,0) -> 68775 | K5: =_xlfn.XLOOKUP($A5,Inputs!$A:$A,Inputs!K:K,,0) -> 64657 | L5: =_xlfn.XLOOKUP($A5,Inputs!$A:$A,Inputs!L:L,,0) -> 62570 | M5: =_xlfn.XLOOKUP($A5,Inputs!$A:$A,Inputs!M:M,,0) -> 55842
A6: Growth vs. Previous year | B6: =IFERROR(B5/C5-1,"-") -> 0.043321734 | C6: =IFERROR(C5/D5-1,"-") -> 0.12379784 | D6: =IFERROR(D5/E5-1,"-") -> -0.049365718 | E6: =IFERROR(E5/F5-1,"-") -> 0.15274001 | F6: =IFERROR(F5/G5-1,"-") -> 0.11146785 | G6: =IFERROR(G5/H5-1,"-") -> 0.053173306 | H6: =IFERROR(H5/I5-1,"-") -> 0.083559254 | I6: =IFERROR(I5/J5-1,"-") -> 0.083387859 | ... M6: =IFERROR(M5/N5-1,"-") -> -
A7: Gross Profit | B7: =_xlfn.XLOOKUP($A7,Inputs!$A:$A,Inputs!B:B,,0) -> 36445 | C7: =_xlfn.XLOOKUP($A7,Inputs!$A:$A,Inputs!C:C,,0) -> 34621 | D7: =_xlfn.XLOOKUP($A7,Inputs!$A:$A,Inputs!D:D,,0) -> 30593 | E7: =_xlfn.XLOOKUP($A7,Inputs!$A:$A,Inputs!E:E,,0) -> 34078 | F7: =_xlfn.XLOOKUP($A7,Inputs!$A:$A,Inputs!F:F,,0) -> 29685 | G7: =_xlfn.XLOOKUP($A7,Inputs!$A:$A,Inputs!G:G,,0) -> 27706 | H7: =_xlfn.XLOOKUP($A7,Inputs!$A:$A,Inputs!H:H,,0) -> 26257 | I7: =_xlfn.XLOOKUP($A7,Inputs!$A:$A,Inputs!I:I,,0) -> 24678 | J7: =_xlfn.XLOOKUP($A7,Inputs!$A:$A,Inputs!J:J,,0) -> 22923 | K7: =_xlfn.XLOOKUP($A7,Inputs!$A:$A,Inputs!K:K,,0) -> 21434 | L7: =_xlfn.XLOOKUP($A7,Inputs!$A:$A,Inputs!L:L,,0) -> 19977 | M7: =_xlfn.XLOOKUP($A7,Inputs!$A:$A,Inputs!M:M,,0) -> 24440
A8: % over sales | B8: =IFERROR(B7/B$5,"-") -> 0.30013918 | C8: =IFERROR(C7/C$5,"-") -> 0.29746961 | D8: =IFERROR(D7/D$5,"-") -> 0.29540188 | E8: =IFERROR(E7/E$5,"-") -> 0.31280865 | F8: =IFERROR(F7/F$5,"-") -> 0.31410372 | G8: =IFERROR(G7/G$5,"-") -> 0.32584177 | H8: =IFERROR(H7/H$5,"-") -> 0.32522047 | I8: =IFERROR(I7/I$5,"-") -> 0.33120387 | ... M8: =IFERROR(M7/M$5,"-") -> 0.43766341
A9: Operating expenses | B9: =B5-B11 -> 107386 | C9: =C5-C11 -> 95568 | D9: =D5-D11 -> 86071 | E9: =E5-E11 -> 87817 | F9: =F5-F11 -> 75498 | G9: =G5-G11 -> 67011 | H9: =H5-H11 -> 63905 | I9: =I5-I11 -> 58512 | ... M9: =M5-M11 -> 45121
A10: % over sales | B10: =IFERROR(B9/B$5,"-") -> 0.88436674 | C10: =IFERROR(C9/C$5,"-") -> 0.82113674 | D10: =IFERROR(D9/D$5,"-") -> 0.83108995 | E10: =IFERROR(E9/E$5,"-") -> 0.80608948 | F10: =IFERROR(F9/F$5,"-") -> 0.79886146 | G10: =IFERROR(G9/G$5,"-") -> 0.78809583 | H10: =IFERROR(H9/H$5,"-") -> 0.79153042 | I10: =IFERROR(I9/I$5,"-") -> 0.78529057 | ... M10: =IFERROR(M9/M$5,"-") -> 0.80801189
A11: Operating Income | B11: =_xlfn.XLOOKUP($A11,Inputs!$A:$A,Inputs!B:B,,0) -> 14041 | C11: =_xlfn.XLOOKUP($A11,Inputs!$A:$A,Inputs!C:C,,0) -> 20817 | D11: =_xlfn.XLOOKUP($A11,Inputs!$A:$A,Inputs!D:D,,0) -> 17493 | E11: =_xlfn.XLOOKUP($A11,Inputs!$A:$A,Inputs!E:E,,0) -> 21125 | F11: =_xlfn.XLOOKUP($A11,Inputs!$A:$A,Inputs!F:F,,0) -> 19009 | G11: =_xlfn.XLOOKUP($A11,Inputs!$A:$A,Inputs!G:G,,0) -> 18018 | H11: =_xlfn.XLOOKUP($A11,Inputs!$A:$A,Inputs!H:H,,0) -> 16831 | I11: =_xlfn.XLOOKUP($A11,Inputs!$A:$A,Inputs!I:I,,0) -> 15998 | J11: =_xlfn.XLOOKUP($A11,Inputs!$A:$A,Inputs!J:J,,0) -> 14904 | K11: =_xlfn.XLOOKUP($A11,Inputs!$A:$A,Inputs!K:K,,0) -> 13563 | L11: =_xlfn.XLOOKUP($A11,Inputs!$A:$A,Inputs!L:L,,0) -> 12179 | M11: =_xlfn.XLOOKUP($A11,Inputs!$A:$A,Inputs!M:M,,0) -> 10721
A12: % over sales | B12: =IFERROR(B11/B$5,"-") -> 0.11563326 | C12: =IFERROR(C11/C$5,"-") -> 0.17886326 | D12: =IFERROR(D11/D$5,"-") -> 0.16891005 | E12: =IFERROR(E11/E$5,"-") -> 0.19391052 | F12: =IFERROR(F11/F$5,"-") -> 0.20113854 | G12: =IFERROR(G11/G$5,"-") -> 0.21190417 | H12: =IFERROR(H11/H$5,"-") -> 0.20846958 | I12: =IFERROR(I11/I$5,"-") -> 0.21470943 | ... M12: =IFERROR(M11/M$5,"-") -> 0.19198811
A13: Growth vs. Previous year | B13: =IFERROR(B12/C12-1,"-") -> -0.35351025 | C13: =IFERROR(C12/D12-1,"-") -> 0.058926096 | D13: =IFERROR(D12/E12-1,"-") -> -0.12892789 | E13: =IFERROR(E12/F12-1,"-") -> -0.035935524 | F13: =IFERROR(F12/G12-1,"-") -> -0.050804256 | G13: =IFERROR(G12/H12-1,"-") -> 0.016475277 | H13: =IFERROR(H12/I12-1,"-") -> -0.029061858 | I13: =IFERROR(I12/J12-1,"-") -> -0.0092162245 | ... M13: =IFERROR(M12/N12-1,"-") -> -
A14: Net Financial Cost | B14: =_xlfn.XLOOKUP($A14,Inputs!$A:$A,Inputs!B:B,,0) -> -3896 | C14: =_xlfn.XLOOKUP($A14,Inputs!$A:$A,Inputs!C:C,,0) -> -4281 | D14: =_xlfn.XLOOKUP($A14,Inputs!$A:$A,Inputs!D:D,,0) -> -4588 | E14: =_xlfn.XLOOKUP($A14,Inputs!$A:$A,Inputs!E:E,,0) -> -4567 | F14: =_xlfn.XLOOKUP($A14,Inputs!$A:$A,Inputs!F:F,,0) -> -3542 | G14: =_xlfn.XLOOKUP($A14,Inputs!$A:$A,Inputs!G:G,,0) -> -3086 | H14: =_xlfn.XLOOKUP($A14,Inputs!$A:$A,Inputs!H:H,,0) -> -2942 | I14: =_xlfn.XLOOKUP($A14,Inputs!$A:$A,Inputs!I:I,,0) -> -2702 | J14: =_xlfn.XLOOKUP($A14,Inputs!$A:$A,Inputs!J:J,,0) -> -2617 | K14: =_xlfn.XLOOKUP($A14,Inputs!$A:$A,Inputs!K:K,,0) -> -2574 | L14: =_xlfn.XLOOKUP($A14,Inputs!$A:$A,Inputs!L:L,,0) -> -2521 | M14: =_xlfn.XLOOKUP($A14,Inputs!$A:$A,Inputs!M:M,,0) -> -2505
A15: Other Expenses (Revenues) | B15: =_xlfn.XLOOKUP($A15,Inputs!$A:$A,Inputs!B:B,,0) -> -861 | C15: =_xlfn.XLOOKUP($A15,Inputs!$A:$A,Inputs!C:C,,0) -> 2556 | D15: =_xlfn.XLOOKUP($A15,Inputs!$A:$A,Inputs!D:D,,0) -> 1160 | E15: =_xlfn.XLOOKUP($A15,Inputs!$A:$A,Inputs!E:E,,0) -> 438 | F15: =_xlfn.XLOOKUP($A15,Inputs!$A:$A,Inputs!F:F,,0) -> -225 | G15: =_xlfn.XLOOKUP($A15,Inputs!$A:$A,Inputs!G:G,,0) -> 421 | H15: =_xlfn.XLOOKUP($A15,Inputs!$A:$A,Inputs!H:H,,0) -> 437 | I15: =_xlfn.XLOOKUP($A15,Inputs!$A:$A,Inputs!I:I,,0) -> 76 | J15: =_xlfn.XLOOKUP($A15,Inputs!$A:$A,Inputs!J:J,,0) -> 178 | K15: =_xlfn.XLOOKUP($A15,Inputs!$A:$A,Inputs!K:K,,0) -> 126 | L15: =_xlfn.XLOOKUP($A15,Inputs!$A:$A,Inputs!L:L,,0) -> 1951 | M15: =_xlfn.XLOOKUP($A15,Inputs!$A:$A,Inputs!M:M,,0) -> -9
A16: EBIT | B16: =B11-B15 -> 14902 | C16: =C11-C15 -> 18261 | D16: =D11-D15 -> 16333 | E16: =E11-E15 -> 20687 | F16: =F11-F15 -> 19234 | G16: =G11-G15 -> 17597 | H16: =H11-H15 -> 16394 | I16: =I11-I15 -> 15922 | ... M16: =M11-M15 -> 10730
A17: Depreciation and Amortization | B17: ='Fin. Data'!B17 -> 13821 | C17: ='Fin. Data'!C17 -> 13804 | D17: ='Fin. Data'!D17 -> 13100 | E17: ='Fin. Data'!E17 -> 12953 | F17: ='Fin. Data'!F17 -> 10676 | G17: ='Fin. Data'!G17 -> 9688 | H17: ='Fin. Data'!H17 -> 9426 | I17: ='Fin. Data'!I17 -> 8680 | ... M17: ='Fin. Data'!M17 -> 7636
A18: Changes Net Working Capital | B18: =_xlfn.XLOOKUP($A18,Inputs!$A:$A,Inputs!B:B,,0) -> 2442 | C18: =_xlfn.XLOOKUP($A18,Inputs!$A:$A,Inputs!C:C,,0) -> 543 | D18: =_xlfn.XLOOKUP($A18,Inputs!$A:$A,Inputs!D:D,,0) -> -3395 | E18: =_xlfn.XLOOKUP($A18,Inputs!$A:$A,Inputs!E:E,,0) -> -831 | F18: =_xlfn.XLOOKUP($A18,Inputs!$A:$A,Inputs!F:F,,0) -> -491 | G18: =_xlfn.XLOOKUP($A18,Inputs!$A:$A,Inputs!G:G,,0) -> -603 | H18: =_xlfn.XLOOKUP($A18,Inputs!$A:$A,Inputs!H:H,,0) -> -305 | I18: =_xlfn.XLOOKUP($A18,Inputs!$A:$A,Inputs!I:I,,0) -> -381 | J18: =_xlfn.XLOOKUP($A18,Inputs!$A:$A,Inputs!J:J,,0) -> -1234 | K18: =_xlfn.XLOOKUP($A18,Inputs!$A:$A,Inputs!K:K,,0) -> 1119 | L18: =_xlfn.XLOOKUP($A18,Inputs!$A:$A,Inputs!L:L,,0) -> -1386 | M18: =_xlfn.XLOOKUP($A18,Inputs!$A:$A,Inputs!M:M,,0) -> -6288
A19: EBITDA | B19: =B11-B15+B17 -> 28723 | C19: =C11-C15+C17 -> 32065 | D19: =D11-D15+D17 -> 29433 | E19: =E11-E15+E17 -> 33640 | F19: =F11-F15+F17 -> 29910 | G19: =G11-G15+G17 -> 27285 | H19: =H11-H15+H17 -> 25820 | I19: =I11-I15+I17 -> 24602 | ... M19: =M11-M15+M17 -> 18366
A20: % over sales | B20: =IFERROR(B19/B$5,"-") -> 0.23654541 | C20: =IFERROR(C19/C$5,"-") -> 0.27550801 | D20: =IFERROR(D19/D$5,"-") -> 0.28420107 | E20: =IFERROR(E19/E$5,"-") -> 0.30878816 | F20: =IFERROR(F19/F$5,"-") -> 0.31648449 | G20: =IFERROR(G19/G$5,"-") -> 0.32089052 | H20: =IFERROR(H19/H$5,"-") -> 0.31980777 | I20: =IFERROR(I19/I$5,"-") -> 0.33018387 | ... M20: =IFERROR(M19/M$5,"-") -> 0.32889223
A21: Taxes | B21: =_xlfn.XLOOKUP($A21,Inputs!$A:$A,Inputs!B:B,,0) -> -4359 | C21: =_xlfn.XLOOKUP($A21,Inputs!$A:$A,Inputs!C:C,,0) -> -5259 | D21: =_xlfn.XLOOKUP($A21,Inputs!$A:$A,Inputs!D:D,,0) -> -3364 | E21: =_xlfn.XLOOKUP($A21,Inputs!$A:$A,Inputs!E:E,,0) -> -3673 | F21: =_xlfn.XLOOKUP($A21,Inputs!$A:$A,Inputs!F:F,,0) -> -3380 | G21: =_xlfn.XLOOKUP($A21,Inputs!$A:$A,Inputs!G:G,,0) -> 7569 | H21: =_xlfn.XLOOKUP($A21,Inputs!$A:$A,Inputs!H:H,,0) -> -5298 | I21: =_xlfn.XLOOKUP($A21,Inputs!$A:$A,Inputs!I:I,,0) -> -4959 | J21: =_xlfn.XLOOKUP($A21,Inputs!$A:$A,Inputs!J:J,,0) -> -3873 | K21: =_xlfn.XLOOKUP($A21,Inputs!$A:$A,Inputs!K:K,,0) -> -3980 | L21: =_xlfn.XLOOKUP($A21,Inputs!$A:$A,Inputs!L:L,,0) -> -3744 | M21: =_xlfn.XLOOKUP($A21,Inputs!$A:$A,Inputs!M:M,,0) -> -3050
A22: % Tax | B22: =IFERROR(B21/B$5,"-") -> -0.035898112 | C22: =IFERROR(C21/C$5,"-") -> -0.045186235 | D22: =IFERROR(D21/D$5,"-") -> -0.03248233 | E22: =IFERROR(E21/E$5,"-") -> -0.033715188 | F22: =IFERROR(F21/F$5,"-") -> -0.035764547 | G22: =IFERROR(G21/G$5,"-") -> 0.089016688 | H22: =IFERROR(H21/H$5,"-") -> -0.065621284 | I22: =IFERROR(I21/I$5,"-") -> -0.066554825 | ... M22: =IFERROR(M21/M$5,"-") -> -0.054618388
A23: Net income | B23: =_xlfn.XLOOKUP($A23,Inputs!$A:$A,Inputs!B:B,,0) -> 4925 | C23: =_xlfn.XLOOKUP($A23,Inputs!$A:$A,Inputs!C:C,,0) -> 13833 | D23: =_xlfn.XLOOKUP($A23,Inputs!$A:$A,Inputs!D:D,,0) -> 10701 | E23: =_xlfn.XLOOKUP($A23,Inputs!$A:$A,Inputs!E:E,,0) -> 13323 | F23: =_xlfn.XLOOKUP($A23,Inputs!$A:$A,Inputs!F:F,,0) -> 11862 | G23: =_xlfn.XLOOKUP($A23,Inputs!$A:$A,Inputs!G:G,,0) -> 22922 | H23: =_xlfn.XLOOKUP($A23,Inputs!$A:$A,Inputs!H:H,,0) -> 9028 | I23: =_xlfn.XLOOKUP($A23,Inputs!$A:$A,Inputs!I:I,,0) -> 8413 | J23: =_xlfn.XLOOKUP($A23,Inputs!$A:$A,Inputs!J:J,,0) -> 8592 | K23: =_xlfn.XLOOKUP($A23,Inputs!$A:$A,Inputs!K:K,,0) -> 7135 | L23: =_xlfn.XLOOKUP($A23,Inputs!$A:$A,Inputs!L:L,,0) -> 7865 | M23: =_xlfn.XLOOKUP($A23,Inputs!$A:$A,Inputs!M:M,,0) -> 5157
A24: % over sales | B24: =IFERROR(B23/B$5,"-") -> 0.040559348 | C24: =IFERROR(C23/C$5,"-") -> 0.11885552 | D24: =IFERROR(D23/D$5,"-") -> 0.10332741 | E24: =IFERROR(E23/E$5,"-") -> 0.12229443 | F24: =IFERROR(F23/F$5,"-") -> 0.12551451 | G24: =IFERROR(G23/G$5,"-") -> 0.26957861 | H24: =IFERROR(H23/H$5,"-") -> 0.11182124 | I24: =IFERROR(I23/I$5,"-") -> 0.11291102 | ... M24: =IFERROR(M23/M$5,"-") -> 0.092349844
A25: Growth vs. Previous year | B25: =IFERROR(B24/C24-1,"-") -> -0.65875083 | C25: =IFERROR(C24/D24-1,"-") -> 0.15028066 | D25: =IFERROR(D24/E24-1,"-") -> -0.15509309 | E25: =IFERROR(E24/F24-1,"-") -> -0.025655043 | F25: =IFERROR(F24/G24-1,"-") -> -0.53440479 | G25: =IFERROR(G24/H24-1,"-") -> 1.4107996 | H25: =IFERROR(H24/I24-1,"-") -> -0.0096516188 | I25: =IFERROR(I24/J24-1,"-") -> -0.096199336 | ... M25: =IFERROR(M24/N24-1,"-") -> -
A26: Cash Generated | B26: =B39-C39 -> -3962 | C26: =C39-D39 -> -3029 | D26: =D39-E39 -> 6240 | E26: =E39-F39 -> 1686 | F26: =F39-G39 -> 386 | G26: =G39-H39 -> 127 | H26: =H39-I39 -> 1006 | I26: =I39-J39 -> -1615 | ... M26: =M39-N39 -> 1620
A27: Dividends | B27: =_xlfn.XLOOKUP($A27,Inputs!$A:$A,Inputs!B:B,,0) -> -4741 | C27: =_xlfn.XLOOKUP($A27,Inputs!$A:$A,Inputs!C:C,,0) -> -4532 | D27: =_xlfn.XLOOKUP($A27,Inputs!$A:$A,Inputs!D:D,,0) -> -4140 | E27: =_xlfn.XLOOKUP($A27,Inputs!$A:$A,Inputs!E:E,,0) -> -3735 | F27: =_xlfn.XLOOKUP($A27,Inputs!$A:$A,Inputs!F:F,,0) -> -3352 | G27: =_xlfn.XLOOKUP($A27,Inputs!$A:$A,Inputs!G:G,,0) -> -2883 | H27: =_xlfn.XLOOKUP($A27,Inputs!$A:$A,Inputs!H:H,,0) -> -2601 | I27: =_xlfn.XLOOKUP($A27,Inputs!$A:$A,Inputs!I:I,,0) -> -2437 | J27: =_xlfn.XLOOKUP($A27,Inputs!$A:$A,Inputs!J:J,,0) -> -2254 | K27: =_xlfn.XLOOKUP($A27,Inputs!$A:$A,Inputs!K:K,,0) -> -1964 | L27: =_xlfn.XLOOKUP($A27,Inputs!$A:$A,Inputs!L:L,,0) -> -1608 | M27: =_xlfn.XLOOKUP($A27,Inputs!$A:$A,Inputs!M:M,,0) -> -1187
A28: Share buyback | B28: =_xlfn.XLOOKUP($A28,Inputs!$A:$A,Inputs!B:B,,0) -> -13328 | C28: =_xlfn.XLOOKUP($A28,Inputs!$A:$A,Inputs!C:C,,0) -> -4672 | D28: =_xlfn.XLOOKUP($A28,Inputs!$A:$A,Inputs!D:D,,0) -> -534 | E28: =_xlfn.XLOOKUP($A28,Inputs!$A:$A,Inputs!E:E,,0) -> -504 | F28: =_xlfn.XLOOKUP($A28,Inputs!$A:$A,Inputs!F:F,,0) -> -5320 | G28: =_xlfn.XLOOKUP($A28,Inputs!$A:$A,Inputs!G:G,,0) -> -5435 | H28: =_xlfn.XLOOKUP($A28,Inputs!$A:$A,Inputs!H:H,,0) -> -5352 | I28: =_xlfn.XLOOKUP($A28,Inputs!$A:$A,Inputs!I:I,,0) -> 0 | J28: =_xlfn.XLOOKUP($A28,Inputs!$A:$A,Inputs!J:J,,0) -> 0 | K28: =_xlfn.XLOOKUP($A28,Inputs!$A:$A,Inputs!K:K,,0) -> -2000 | L28: =_xlfn.XLOOKUP($A28,Inputs!$A:$A,Inputs!L:L,,0) -> -3000 | M28: =_xlfn.XLOOKUP($A28,Inputs!$A:$A,Inputs!M:M,,0) -> -2141
A29: FNP | B29: =SUM(B26:B28) -> -22031 | C29: =SUM(C26:C28) -> -12233 | D29: =SUM(D26:D28) -> 1566 | E29: =SUM(E26:E28) -> -2553 | F29: =SUM(F26:F28) -> -8286 | G29: =SUM(G26:G28) -> -8191 | H29: =SUM(H26:H28) -> -6947 | I29: =SUM(I26:I28) -> -4052 | ... M29: =SUM(M26:M28) -> -1708
A30: FNP'' | B30: =+B29-(B58-C29) -> -132504 | C30: =+C29-(C58-D29) -> -108555 | D30: =+D29-(D58-E29) -> -106769 | E30: =+E29-(E58-F29) -> -113770 | F30: =+F29-(F58-G29) -> -123822 | G30: =+G29-(G58-H29) -> -74560 | H30: =+H29-(H58-I29) -> -66565 | I30: =+I29-(I58-J29) -> -53108 | ... M30: =+M29-(M58-N29) -> -39650
A31: FNP' | B31: =+B30+B33 -> -132516 | C31: =+C30+C33 -> -109929 | D31: =+D30+D33 -> -107002 | E31: =+E30+E33 -> -114140 | F31: =+F30+F33 -> -162041 | G31: =+G30+G33 -> -75092 | H31: =+H30+H33 -> -70494 | I31: =+I30+I33 -> -54894 | ... M31: =+M30+M33 -> -39650
A32: Net Capex | B32: =_xlfn.XLOOKUP($A32,Inputs!$A:$A,Inputs!B:B,,0) -> -10626 | C32: =_xlfn.XLOOKUP($A32,Inputs!$A:$A,Inputs!C:C,,0) -> -9174 | D32: =_xlfn.XLOOKUP($A32,Inputs!$A:$A,Inputs!D:D,,0) -> -9179 | E32: =_xlfn.XLOOKUP($A32,Inputs!$A:$A,Inputs!E:E,,0) -> -9953 | F32: =_xlfn.XLOOKUP($A32,Inputs!$A:$A,Inputs!F:F,,0) -> -9774 | G32: =_xlfn.XLOOKUP($A32,Inputs!$A:$A,Inputs!G:G,,0) -> -9550 | H32: =_xlfn.XLOOKUP($A32,Inputs!$A:$A,Inputs!H:H,,0) -> -9135 | I32: =_xlfn.XLOOKUP($A32,Inputs!$A:$A,Inputs!I:I,,0) -> -8499 | J32: =_xlfn.XLOOKUP($A32,Inputs!$A:$A,Inputs!J:J,,0) -> -7420 | K32: =_xlfn.XLOOKUP($A32,Inputs!$A:$A,Inputs!K:K,,0) -> -6596 | L32: =_xlfn.XLOOKUP($A32,Inputs!$A:$A,Inputs!L:L,,0) -> -5714 | M32: =_xlfn.XLOOKUP($A32,Inputs!$A:$A,Inputs!M:M,,0) -> -5307
A33: Investments & Acquisitions | B33: =_xlfn.XLOOKUP($A33,Inputs!$A:$A,Inputs!B:B,,0) -> -12 | C33: =_xlfn.XLOOKUP($A33,Inputs!$A:$A,Inputs!C:C,,0) -> -1374 | D33: =_xlfn.XLOOKUP($A33,Inputs!$A:$A,Inputs!D:D,,0) -> -233 | E33: =_xlfn.XLOOKUP($A33,Inputs!$A:$A,Inputs!E:E,,0) -> -370 | F33: =_xlfn.XLOOKUP($A33,Inputs!$A:$A,Inputs!F:F,,0) -> -38219 | G33: =_xlfn.XLOOKUP($A33,Inputs!$A:$A,Inputs!G:G,,0) -> -532 | H33: =_xlfn.XLOOKUP($A33,Inputs!$A:$A,Inputs!H:H,,0) -> -3929 | I33: =_xlfn.XLOOKUP($A33,Inputs!$A:$A,Inputs!I:I,,0) -> -1786 | J33: =_xlfn.XLOOKUP($A33,Inputs!$A:$A,Inputs!J:J,,0) -> -477 | K33: =_xlfn.XLOOKUP($A33,Inputs!$A:$A,Inputs!K:K,,0) -> -1904 | L33: =_xlfn.XLOOKUP($A33,Inputs!$A:$A,Inputs!L:L,,0) -> 0 | M33: =_xlfn.XLOOKUP($A33,Inputs!$A:$A,Inputs!M:M,,0) -> 0
A34: Capex + Investments | B34: =+B32+B33 -> -10638 | C34: =+C32+C33 -> -10548 | D34: =+D32+D33 -> -9412 | E34: =+E32+E33 -> -10323 | F34: =+F32+F33 -> -47993 | G34: =+G32+G33 -> -10082 | H34: =+H32+H33 -> -13064 | I34: =+I32+I33 -> -10285 | ... M34: =+M32+M33 -> -5307
A35: Dividends + Share Buyback | B35: =+B27+B28 -> -18069 | C35: =+C27+C28 -> -9204 | D35: =+D27+D28 -> -4674 | E35: =+E27+E28 -> -4239 | F35: =+F27+F28 -> -8672 | G35: =+G27+G28 -> -8318 | H35: =+H27+H28 -> -7953 | I35: =+I27+I28 -> -2437 | ... M35: =+M27+M28 -> -3328
A36: Payout Ratio | B36: =IFERROR(B35/B23,"-") -> -3.6688325 | C36: =IFERROR(C35/C23,"-") -> -0.66536543 | D36: =IFERROR(D35/D23,"-") -> -0.43678161 | E36: =IFERROR(E35/E23,"-") -> -0.31817158 | F36: =IFERROR(F35/F23,"-") -> -0.73107402 | G36: =IFERROR(G35/G23,"-") -> -0.36288282 | H36: =IFERROR(H35/H23,"-") -> -0.88092601 | I36: =IFERROR(I35/I23,"-") -> -0.28967075 | ... M36: =IFERROR(M35/M23,"-") -> -0.64533644
A38: Assets
A39: Cash & Eq. | B39: =_xlfn.XLOOKUP($A39,Inputs!$A:$A,Inputs!B:B,,0) -> 4749 | C39: =_xlfn.XLOOKUP($A39,Inputs!$A:$A,Inputs!C:C,,0) -> 8711 | D39: =_xlfn.XLOOKUP($A39,Inputs!$A:$A,Inputs!D:D,,0) -> 11740 | E39: =_xlfn.XLOOKUP($A39,Inputs!$A:$A,Inputs!E:E,,0) -> 5500 | F39: =_xlfn.XLOOKUP($A39,Inputs!$A:$A,Inputs!F:F,,0) -> 3814 | G39: =_xlfn.XLOOKUP($A39,Inputs!$A:$A,Inputs!G:G,,0) -> 3428 | H39: =_xlfn.XLOOKUP($A39,Inputs!$A:$A,Inputs!H:H,,0) -> 3301 | I39: =_xlfn.XLOOKUP($A39,Inputs!$A:$A,Inputs!I:I,,0) -> 2295 | J39: =_xlfn.XLOOKUP($A39,Inputs!$A:$A,Inputs!J:J,,0) -> 3910 | K39: =_xlfn.XLOOKUP($A39,Inputs!$A:$A,Inputs!K:K,,0) -> 1718 | L39: =_xlfn.XLOOKUP($A39,Inputs!$A:$A,Inputs!L:L,,0) -> 10951 | M39: =_xlfn.XLOOKUP($A39,Inputs!$A:$A,Inputs!M:M,,0) -> 1620
A40: Accounts Receivable | B40: =_xlfn.XLOOKUP($A40,Inputs!$A:$A,Inputs!B:B,,0) -> 12671 | C40: =_xlfn.XLOOKUP($A40,Inputs!$A:$A,Inputs!C:C,,0) -> 12008 | D40: =_xlfn.XLOOKUP($A40,Inputs!$A:$A,Inputs!D:D,,0) -> 11466 | E40: =_xlfn.XLOOKUP($A40,Inputs!$A:$A,Inputs!E:E,,0) -> 11292 | F40: =_xlfn.XLOOKUP($A40,Inputs!$A:$A,Inputs!F:F,,0) -> 11104 | G40: =_xlfn.XLOOKUP($A40,Inputs!$A:$A,Inputs!G:G,,0) -> 8834 | H40: =_xlfn.XLOOKUP($A40,Inputs!$A:$A,Inputs!H:H,,0) -> 8372 | I40: =_xlfn.XLOOKUP($A40,Inputs!$A:$A,Inputs!I:I,,0) -> 7369 | J40: =_xlfn.XLOOKUP($A40,Inputs!$A:$A,Inputs!J:J,,0) -> 6680 | K40: =_xlfn.XLOOKUP($A40,Inputs!$A:$A,Inputs!K:K,,0) -> 6751 | L40: =_xlfn.XLOOKUP($A40,Inputs!$A:$A,Inputs!L:L,,0) -> 5828 | M40: =_xlfn.XLOOKUP($A40,Inputs!$A:$A,Inputs!M:M,,0) -> 4854
A41: Inventory | B41: =_xlfn.XLOOKUP($A41,Inputs!$A:$A,Inputs!B:B,,0) -> 0 | C41: =_xlfn.XLOOKUP($A41,Inputs!$A:$A,Inputs!C:C,,0) -> 0 | D41: =_xlfn.XLOOKUP($A41,Inputs!$A:$A,Inputs!D:D,,0) -> 0 | E41: =_xlfn.XLOOKUP($A41,Inputs!$A:$A,Inputs!E:E,,0) -> 0 | F41: =_xlfn.XLOOKUP($A41,Inputs!$A:$A,Inputs!F:F,,0) -> 0 | G41: =_xlfn.XLOOKUP($A41,Inputs!$A:$A,Inputs!G:G,,0) -> 0 | H41: =_xlfn.XLOOKUP($A41,Inputs!$A:$A,Inputs!H:H,,0) -> 0 | I41: =_xlfn.XLOOKUP($A41,Inputs!$A:$A,Inputs!I:I,,0) -> 0 | J41: =_xlfn.XLOOKUP($A41,Inputs!$A:$A,Inputs!J:J,,0) -> 0 | K41: =_xlfn.XLOOKUP($A41,Inputs!$A:$A,Inputs!K:K,,0) -> 0 | L41: =_xlfn.XLOOKUP($A41,Inputs!$A:$A,Inputs!L:L,,0) -> 0 | M41: =_xlfn.XLOOKUP($A41,Inputs!$A:$A,Inputs!M:M,,0) -> 0
A42: Property, Plant and Equipment | B42: =_xlfn.XLOOKUP($A42,Inputs!$A:$A,Inputs!B:B,,0) -> 55485 | C42: =_xlfn.XLOOKUP($A42,Inputs!$A:$A,Inputs!C:C,,0) -> 54047 | D42: =_xlfn.XLOOKUP($A42,Inputs!$A:$A,Inputs!D:D,,0) -> 51995 | E42: =_xlfn.XLOOKUP($A42,Inputs!$A:$A,Inputs!E:E,,0) -> 48322 | F42: =_xlfn.XLOOKUP($A42,Inputs!$A:$A,Inputs!F:F,,0) -> 44437 | G42: =_xlfn.XLOOKUP($A42,Inputs!$A:$A,Inputs!G:G,,0) -> 38470 | H42: =_xlfn.XLOOKUP($A42,Inputs!$A:$A,Inputs!H:H,,0) -> 36253 | I42: =_xlfn.XLOOKUP($A42,Inputs!$A:$A,Inputs!I:I,,0) -> 33665 | J42: =_xlfn.XLOOKUP($A42,Inputs!$A:$A,Inputs!J:J,,0) -> 30953 | K42: =_xlfn.XLOOKUP($A42,Inputs!$A:$A,Inputs!K:K,,0) -> 29840 | L42: =_xlfn.XLOOKUP($A42,Inputs!$A:$A,Inputs!L:L,,0) -> 27232 | M42: =_xlfn.XLOOKUP($A42,Inputs!$A:$A,Inputs!M:M,,0) -> 27559
A43: Other Assets | B43: =_xlfn.XLOOKUP($A43,Inputs!$A:$A,Inputs!B:B,,0) -> 172952 | C43: =_xlfn.XLOOKUP($A43,Inputs!$A:$A,Inputs!C:C,,0) -> 188561 | D43: =_xlfn.XLOOKUP($A43,Inputs!$A:$A,Inputs!D:D,,0) -> 188878 | E43: =_xlfn.XLOOKUP($A43,Inputs!$A:$A,Inputs!E:E,,0) -> 188915 | F43: =_xlfn.XLOOKUP($A43,Inputs!$A:$A,Inputs!F:F,,0) -> 188294 | G43: =_xlfn.XLOOKUP($A43,Inputs!$A:$A,Inputs!G:G,,0) -> 133184 | H43: =_xlfn.XLOOKUP($A43,Inputs!$A:$A,Inputs!H:H,,0) -> 130198 | I43: =_xlfn.XLOOKUP($A43,Inputs!$A:$A,Inputs!I:I,,0) -> 122567 | J43: =_xlfn.XLOOKUP($A43,Inputs!$A:$A,Inputs!J:J,,0) -> 116624 | K43: =_xlfn.XLOOKUP($A43,Inputs!$A:$A,Inputs!K:K,,0) -> 119515 | L43: =_xlfn.XLOOKUP($A43,Inputs!$A:$A,Inputs!L:L,,0) -> 119796 | M43: =_xlfn.XLOOKUP($A43,Inputs!$A:$A,Inputs!M:M,,0) -> 118905
A44: Total Assets | B44: =_xlfn.XLOOKUP($A44,Inputs!$A:$A,Inputs!B:B,,0) -> 257275 | C44: =_xlfn.XLOOKUP($A44,Inputs!$A:$A,Inputs!C:C,,0) -> 275905 | D44: =_xlfn.XLOOKUP($A44,Inputs!$A:$A,Inputs!D:D,,0) -> 273869 | E44: =_xlfn.XLOOKUP($A44,Inputs!$A:$A,Inputs!E:E,,0) -> 263414 | F44: =_xlfn.XLOOKUP($A44,Inputs!$A:$A,Inputs!F:F,,0) -> 251684 | G44: =_xlfn.XLOOKUP($A44,Inputs!$A:$A,Inputs!G:G,,0) -> 187462 | H44: =_xlfn.XLOOKUP($A44,Inputs!$A:$A,Inputs!H:H,,0) -> 180500 | I44: =_xlfn.XLOOKUP($A44,Inputs!$A:$A,Inputs!I:I,,0) -> 166574 | J44: =_xlfn.XLOOKUP($A44,Inputs!$A:$A,Inputs!J:J,,0) -> 159186 | K44: =_xlfn.XLOOKUP($A44,Inputs!$A:$A,Inputs!K:K,,0) -> 158813 | L44: =_xlfn.XLOOKUP($A44,Inputs!$A:$A,Inputs!L:L,,0) -> 164971 | M44: =_xlfn.XLOOKUP($A44,Inputs!$A:$A,Inputs!M:M,,0) -> 157818
A47: Liabilities
A48: Current Liabilities | B48: =_xlfn.XLOOKUP($A48,Inputs!$A:$A,Inputs!B:B,,0) -> 27887 | C48: =_xlfn.XLOOKUP($A48,Inputs!$A:$A,Inputs!C:C,,0) -> 29348 | D48: =_xlfn.XLOOKUP($A48,Inputs!$A:$A,Inputs!D:D,,0) -> 28796 | E48: =_xlfn.XLOOKUP($A48,Inputs!$A:$A,Inputs!E:E,,0) -> 30292 | F48: =_xlfn.XLOOKUP($A48,Inputs!$A:$A,Inputs!F:F,,0) -> 27603 | G48: =_xlfn.XLOOKUP($A48,Inputs!$A:$A,Inputs!G:G,,0) -> 21993 | H48: =_xlfn.XLOOKUP($A48,Inputs!$A:$A,Inputs!H:H,,0) -> 21535 | I48: =_xlfn.XLOOKUP($A48,Inputs!$A:$A,Inputs!I:I,,0) -> 18178 | J48: =_xlfn.XLOOKUP($A48,Inputs!$A:$A,Inputs!J:J,,0) -> 17410 | K48: =_xlfn.XLOOKUP($A48,Inputs!$A:$A,Inputs!K:K,,0) -> 18912 | L48: =_xlfn.XLOOKUP($A48,Inputs!$A:$A,Inputs!L:L,,0) -> 16714 | M48: =_xlfn.XLOOKUP($A48,Inputs!$A:$A,Inputs!M:M,,0) -> 13241
A49: Short-Term Debt | B49: =_xlfn.XLOOKUP($A49,Inputs!$A:$A,Inputs!B:B,,0) -> 0 | C49: =_xlfn.XLOOKUP($A49,Inputs!$A:$A,Inputs!C:C,,0) -> 0 | D49: =_xlfn.XLOOKUP($A49,Inputs!$A:$A,Inputs!D:D,,0) -> 0 | E49: =_xlfn.XLOOKUP($A49,Inputs!$A:$A,Inputs!E:E,,0) -> 0 | F49: =_xlfn.XLOOKUP($A49,Inputs!$A:$A,Inputs!F:F,,0) -> 0 | G49: =_xlfn.XLOOKUP($A49,Inputs!$A:$A,Inputs!G:G,,0) -> 0 | H49: =_xlfn.XLOOKUP($A49,Inputs!$A:$A,Inputs!H:H,,0) -> 0 | I49: =_xlfn.XLOOKUP($A49,Inputs!$A:$A,Inputs!I:I,,0) -> 0 | J49: =_xlfn.XLOOKUP($A49,Inputs!$A:$A,Inputs!J:J,,0) -> 0 | K49: =_xlfn.XLOOKUP($A49,Inputs!$A:$A,Inputs!K:K,,0) -> 0 | L49: =_xlfn.XLOOKUP($A49,Inputs!$A:$A,Inputs!L:L,,0) -> 0 | M49: =_xlfn.XLOOKUP($A49,Inputs!$A:$A,Inputs!M:M,,0) -> 0
A50: Short-Term Leases | B50: =_xlfn.XLOOKUP($A50,Inputs!$A:$A,Inputs!B:B,,0) -> 675 | C50: =_xlfn.XLOOKUP($A50,Inputs!$A:$A,Inputs!C:C,,0) -> 766 | D50: =_xlfn.XLOOKUP($A50,Inputs!$A:$A,Inputs!D:D,,0) -> 718 | E50: =_xlfn.XLOOKUP($A50,Inputs!$A:$A,Inputs!E:E,,0) -> 715 | F50: =_xlfn.XLOOKUP($A50,Inputs!$A:$A,Inputs!F:F,,0) -> 0 | G50: =_xlfn.XLOOKUP($A50,Inputs!$A:$A,Inputs!G:G,,0) -> 0 | H50: =_xlfn.XLOOKUP($A50,Inputs!$A:$A,Inputs!H:H,,0) -> 0 | I50: =_xlfn.XLOOKUP($A50,Inputs!$A:$A,Inputs!I:I,,0) -> 0 | J50: =_xlfn.XLOOKUP($A50,Inputs!$A:$A,Inputs!J:J,,0) -> 0 | K50: =_xlfn.XLOOKUP($A50,Inputs!$A:$A,Inputs!K:K,,0) -> 0 | L50: =_xlfn.XLOOKUP($A50,Inputs!$A:$A,Inputs!L:L,,0) -> 0 | M50: =_xlfn.XLOOKUP($A50,Inputs!$A:$A,Inputs!M:M,,0) -> 0
A51: Other current liabilities | B51: =_xlfn.XLOOKUP($A51,Inputs!$A:$A,Inputs!B:B,,0) -> 14668 | C51: =_xlfn.XLOOKUP($A51,Inputs!$A:$A,Inputs!C:C,,0) -> 16127 | D51: =_xlfn.XLOOKUP($A51,Inputs!$A:$A,Inputs!D:D,,0) -> 16714 | E51: =_xlfn.XLOOKUP($A51,Inputs!$A:$A,Inputs!E:E,,0) -> 18751 | F51: =_xlfn.XLOOKUP($A51,Inputs!$A:$A,Inputs!F:F,,0) -> 19109 | G51: =_xlfn.XLOOKUP($A51,Inputs!$A:$A,Inputs!G:G,,0) -> 15085 | H51: =_xlfn.XLOOKUP($A51,Inputs!$A:$A,Inputs!H:H,,0) -> 14620 | I51: =_xlfn.XLOOKUP($A51,Inputs!$A:$A,Inputs!I:I,,0) -> 11963 | J51: =_xlfn.XLOOKUP($A51,Inputs!$A:$A,Inputs!J:J,,0) -> 11772 | K51: =_xlfn.XLOOKUP($A51,Inputs!$A:$A,Inputs!K:K,,0) -> 13384 | L51: =_xlfn.XLOOKUP($A51,Inputs!$A:$A,Inputs!L:L,,0) -> 10508 | M51: =_xlfn.XLOOKUP($A51,Inputs!$A:$A,Inputs!M:M,,0) -> 7536
A52: Non-current Liabilities | B52: =_xlfn.XLOOKUP($A52,Inputs!$A:$A,Inputs!B:B,,0) -> 148445 | C52: =_xlfn.XLOOKUP($A52,Inputs!$A:$A,Inputs!C:C,,0) -> 150465 | D52: =_xlfn.XLOOKUP($A52,Inputs!$A:$A,Inputs!D:D,,0) -> 154750 | E52: =_xlfn.XLOOKUP($A52,Inputs!$A:$A,Inputs!E:E,,0) -> 150396 | F52: =_xlfn.XLOOKUP($A52,Inputs!$A:$A,Inputs!F:F,,0) -> 152468 | G52: =_xlfn.XLOOKUP($A52,Inputs!$A:$A,Inputs!G:G,,0) -> 96853 | H52: =_xlfn.XLOOKUP($A52,Inputs!$A:$A,Inputs!H:H,,0) -> 105022 | I52: =_xlfn.XLOOKUP($A52,Inputs!$A:$A,Inputs!I:I,,0) -> 96127 | J52: =_xlfn.XLOOKUP($A52,Inputs!$A:$A,Inputs!J:J,,0) -> 89065 | K52: =_xlfn.XLOOKUP($A52,Inputs!$A:$A,Inputs!K:K,,0) -> 89207 | L52: =_xlfn.XLOOKUP($A52,Inputs!$A:$A,Inputs!L:L,,0) -> 98901 | M52: =_xlfn.XLOOKUP($A52,Inputs!$A:$A,Inputs!M:M,,0) -> 97303
A53: Long-Term Debt | B53: =_xlfn.XLOOKUP($A53,Inputs!$A:$A,Inputs!B:B,,0) -> 98240 | C53: =_xlfn.XLOOKUP($A53,Inputs!$A:$A,Inputs!C:C,,0) -> 97888 | D53: =_xlfn.XLOOKUP($A53,Inputs!$A:$A,Inputs!D:D,,0) -> 105782 | E53: =_xlfn.XLOOKUP($A53,Inputs!$A:$A,Inputs!E:E,,0) -> 102931 | F53: =_xlfn.XLOOKUP($A53,Inputs!$A:$A,Inputs!F:F,,0) -> 107345 | G53: =_xlfn.XLOOKUP($A53,Inputs!$A:$A,Inputs!G:G,,0) -> 59422 | H53: =_xlfn.XLOOKUP($A53,Inputs!$A:$A,Inputs!H:H,,0) -> 55566 | I53: =_xlfn.XLOOKUP($A53,Inputs!$A:$A,Inputs!I:I,,0) -> 48994 | J53: =_xlfn.XLOOKUP($A53,Inputs!$A:$A,Inputs!J:J,,0) -> 43864 | K53: =_xlfn.XLOOKUP($A53,Inputs!$A:$A,Inputs!K:K,,0) -> 44567 | L53: =_xlfn.XLOOKUP($A53,Inputs!$A:$A,Inputs!L:L,,0) -> 38082 | M53: =_xlfn.XLOOKUP($A53,Inputs!$A:$A,Inputs!M:M,,0) -> 37942
A54: Long-Term Leases | B54: =_xlfn.XLOOKUP($A54,Inputs!$A:$A,Inputs!B:B,,0) -> 6107 | C54: =_xlfn.XLOOKUP($A54,Inputs!$A:$A,Inputs!C:C,,0) -> 6473 | D54: =_xlfn.XLOOKUP($A54,Inputs!$A:$A,Inputs!D:D,,0) -> 3740 | E54: =_xlfn.XLOOKUP($A54,Inputs!$A:$A,Inputs!E:E,,0) -> 3891 | F54: =_xlfn.XLOOKUP($A54,Inputs!$A:$A,Inputs!F:F,,0) -> 0 | G54: =_xlfn.XLOOKUP($A54,Inputs!$A:$A,Inputs!G:G,,0) -> 0 | H54: =_xlfn.XLOOKUP($A54,Inputs!$A:$A,Inputs!H:H,,0) -> 0 | I54: =_xlfn.XLOOKUP($A54,Inputs!$A:$A,Inputs!I:I,,0) -> 0 | J54: =_xlfn.XLOOKUP($A54,Inputs!$A:$A,Inputs!J:J,,0) -> 0 | K54: =_xlfn.XLOOKUP($A54,Inputs!$A:$A,Inputs!K:K,,0) -> 0 | L54: =_xlfn.XLOOKUP($A54,Inputs!$A:$A,Inputs!L:L,,0) -> 0 | M54: =_xlfn.XLOOKUP($A54,Inputs!$A:$A,Inputs!M:M,,0) -> 0
A55: Other non-current liabilities | B55: =_xlfn.XLOOKUP($A55,Inputs!$A:$A,Inputs!B:B,,0) -> 44098 | C55: =_xlfn.XLOOKUP($A55,Inputs!$A:$A,Inputs!C:C,,0) -> 46104 | D55: =_xlfn.XLOOKUP($A55,Inputs!$A:$A,Inputs!D:D,,0) -> 45228 | E55: =_xlfn.XLOOKUP($A55,Inputs!$A:$A,Inputs!E:E,,0) -> 43574 | F55: =_xlfn.XLOOKUP($A55,Inputs!$A:$A,Inputs!F:F,,0) -> 45123 | G55: =_xlfn.XLOOKUP($A55,Inputs!$A:$A,Inputs!G:G,,0) -> 37431 | H55: =_xlfn.XLOOKUP($A55,Inputs!$A:$A,Inputs!H:H,,0) -> 49456 | I55: =_xlfn.XLOOKUP($A55,Inputs!$A:$A,Inputs!I:I,,0) -> 47133 | J55: =_xlfn.XLOOKUP($A55,Inputs!$A:$A,Inputs!J:J,,0) -> 45201 | K55: =_xlfn.XLOOKUP($A55,Inputs!$A:$A,Inputs!K:K,,0) -> 44640 | L55: =_xlfn.XLOOKUP($A55,Inputs!$A:$A,Inputs!L:L,,0) -> 60819 | M55: =_xlfn.XLOOKUP($A55,Inputs!$A:$A,Inputs!M:M,,0) -> 59361
A56: Total Liabilities | B56: =_xlfn.XLOOKUP($A56,Inputs!$A:$A,Inputs!B:B,,0) -> 176332 | C56: =_xlfn.XLOOKUP($A56,Inputs!$A:$A,Inputs!C:C,,0) -> 179813 | D56: =_xlfn.XLOOKUP($A56,Inputs!$A:$A,Inputs!D:D,,0) -> 183546 | E56: =_xlfn.XLOOKUP($A56,Inputs!$A:$A,Inputs!E:E,,0) -> 180688 | F56: =_xlfn.XLOOKUP($A56,Inputs!$A:$A,Inputs!F:F,,0) -> 180071 | G56: =_xlfn.XLOOKUP($A56,Inputs!$A:$A,Inputs!G:G,,0) -> 118846 | H56: =_xlfn.XLOOKUP($A56,Inputs!$A:$A,Inputs!H:H,,0) -> 126557 | I56: =_xlfn.XLOOKUP($A56,Inputs!$A:$A,Inputs!I:I,,0) -> 114305 | J56: =_xlfn.XLOOKUP($A56,Inputs!$A:$A,Inputs!J:J,,0) -> 106475 | K56: =_xlfn.XLOOKUP($A56,Inputs!$A:$A,Inputs!K:K,,0) -> 108119 | L56: =_xlfn.XLOOKUP($A56,Inputs!$A:$A,Inputs!L:L,,0) -> 115615 | M56: =_xlfn.XLOOKUP($A56,Inputs!$A:$A,Inputs!M:M,,0) -> 110544
A58: Debt | B58: =B49+B53 -> 98240 | C58: =C49+C53 -> 97888 | D58: =D49+D53 -> 105782 | E58: =E49+E53 -> 102931 | F58: =F49+F53 -> 107345 | G58: =G49+G53 -> 59422 | H58: =H49+H53 -> 55566 | I58: =I49+I53 -> 48994 | ... M58: =M49+M53 -> 37942
A59: Debt/Assets | B59: =IFERROR(B58/B44,"-") -> 0.38184822 | C59: =IFERROR(C58/C44,"-") -> 0.35478879 | D59: =IFERROR(D58/D44,"-") -> 0.38625036 | E59: =IFERROR(E58/E44,"-") -> 0.39075751 | F59: =IFERROR(F58/F44,"-") -> 0.42650705 | G59: =IFERROR(G58/G44,"-") -> 0.31698157 | H59: =IFERROR(H58/H44,"-") -> 0.30784488 | I59: =IFERROR(I58/I44,"-") -> 0.29412753 | ... M59: =IFERROR(M58/M44,"-") -> 0.24041618
A61: Minority Interest | B61: =_xlfn.XLOOKUP($A61,Inputs!$A:$A,Inputs!B:B,,0) -> 1095 | C61: =_xlfn.XLOOKUP($A61,Inputs!$A:$A,Inputs!C:C,,0) -> 1917 | D61: =_xlfn.XLOOKUP($A61,Inputs!$A:$A,Inputs!D:D,,0) -> 2695 | E61: =_xlfn.XLOOKUP($A61,Inputs!$A:$A,Inputs!E:E,,0) -> 2520 | F61: =_xlfn.XLOOKUP($A61,Inputs!$A:$A,Inputs!F:F,,0) -> 2205 | G61: =_xlfn.XLOOKUP($A61,Inputs!$A:$A,Inputs!G:G,,0) -> 2200 | H61: =_xlfn.XLOOKUP($A61,Inputs!$A:$A,Inputs!H:H,,0) -> 3677 | I61: =_xlfn.XLOOKUP($A61,Inputs!$A:$A,Inputs!I:I,,0) -> 2930 | J61: =_xlfn.XLOOKUP($A61,Inputs!$A:$A,Inputs!J:J,,0) -> 1423 | K61: =_xlfn.XLOOKUP($A61,Inputs!$A:$A,Inputs!K:K,,0) -> 1321 | L61: =_xlfn.XLOOKUP($A61,Inputs!$A:$A,Inputs!L:L,,0) -> 17438 | M61: =_xlfn.XLOOKUP($A61,Inputs!$A:$A,Inputs!M:M,,0) -> 16395
A63: Shareholder's Equity | B63: =_xlfn.XLOOKUP($A63,Inputs!$A:$A,Inputs!B:B,,0) -> 79848 | C63: =_xlfn.XLOOKUP($A63,Inputs!$A:$A,Inputs!C:C,,0) -> 94175 | D63: =_xlfn.XLOOKUP($A63,Inputs!$A:$A,Inputs!D:D,,0) -> 87628 | E63: =_xlfn.XLOOKUP($A63,Inputs!$A:$A,Inputs!E:E,,0) -> 80206 | F63: =_xlfn.XLOOKUP($A63,Inputs!$A:$A,Inputs!F:F,,0) -> 69408 | G63: =_xlfn.XLOOKUP($A63,Inputs!$A:$A,Inputs!G:G,,0) -> 66416 | H63: =_xlfn.XLOOKUP($A63,Inputs!$A:$A,Inputs!H:H,,0) -> 50266 | I63: =_xlfn.XLOOKUP($A63,Inputs!$A:$A,Inputs!I:I,,0) -> 49339 | J63: =_xlfn.XLOOKUP($A63,Inputs!$A:$A,Inputs!J:J,,0) -> 51288 | K63: =_xlfn.XLOOKUP($A63,Inputs!$A:$A,Inputs!K:K,,0) -> 49373 | L63: =_xlfn.XLOOKUP($A63,Inputs!$A:$A,Inputs!L:L,,0) -> 31918 | M63: =_xlfn.XLOOKUP($A63,Inputs!$A:$A,Inputs!M:M,,0) -> 30879
A66: Other Data
A67: Number of employees | B67: =_xlfn.XLOOKUP($A67,Inputs!$A:$A,Inputs!B:B,,0) -> #N/A | C67: =_xlfn.XLOOKUP($A67,Inputs!$A:$A,Inputs!C:C,,0) -> #N/A | D67: =_xlfn.XLOOKUP($A67,Inputs!$A:$A,Inputs!D:D,,0) -> #N/A | E67: =_xlfn.XLOOKUP($A67,Inputs!$A:$A,Inputs!E:E,,0) -> #N/A | F67: =_xlfn.XLOOKUP($A67,Inputs!$A:$A,Inputs!F:F,,0) -> #N/A | G67: =_xlfn.XLOOKUP($A67,Inputs!$A:$A,Inputs!G:G,,0) -> #N/A | H67: =_xlfn.XLOOKUP($A67,Inputs!$A:$A,Inputs!H:H,,0) -> #N/A | I67: =_xlfn.XLOOKUP($A67,Inputs!$A:$A,Inputs!I:I,,0) -> #N/A | J67: =_xlfn.XLOOKUP($A67,Inputs!$A:$A,Inputs!J:J,,0) -> #N/A | K67: =_xlfn.XLOOKUP($A67,Inputs!$A:$A,Inputs!K:K,,0) -> #N/A | L67: =_xlfn.XLOOKUP($A67,Inputs!$A:$A,Inputs!L:L,,0) -> #N/A | M67: =_xlfn.XLOOKUP($A67,Inputs!$A:$A,Inputs!M:M,,0) -> #N/A
A68: Shares Outstanding | B68: =_xlfn.XLOOKUP($A68,Inputs!$A:$A,Inputs!B:B,,0) -> #N/A | C68: =_xlfn.XLOOKUP($A68,Inputs!$A:$A,Inputs!C:C,,0) -> #N/A | D68: =_xlfn.XLOOKUP($A68,Inputs!$A:$A,Inputs!D:D,,0) -> #N/A | E68: =_xlfn.XLOOKUP($A68,Inputs!$A:$A,Inputs!E:E,,0) -> #N/A | F68: =_xlfn.XLOOKUP($A68,Inputs!$A:$A,Inputs!F:F,,0) -> #N/A | G68: =_xlfn.XLOOKUP($A68,Inputs!$A:$A,Inputs!G:G,,0) -> #N/A | H68: =_xlfn.XLOOKUP($A68,Inputs!$A:$A,Inputs!H:H,,0) -> #N/A | I68: =_xlfn.XLOOKUP($A68,Inputs!$A:$A,Inputs!I:I,,0) -> #N/A | J68: =_xlfn.XLOOKUP($A68,Inputs!$A:$A,Inputs!J:J,,0) -> #N/A | K68: =_xlfn.XLOOKUP($A68,Inputs!$A:$A,Inputs!K:K,,0) -> #N/A | L68: =_xlfn.XLOOKUP($A68,Inputs!$A:$A,Inputs!L:L,,0) -> #N/A | M68: =_xlfn.XLOOKUP($A68,Inputs!$A:$A,Inputs!M:M,,0) -> #N/A
A69: Float | B69: =_xlfn.XLOOKUP($A69,Inputs!$A:$A,Inputs!B:B,,0) -> 0.99 | C69: =_xlfn.XLOOKUP($A69,Inputs!$A:$A,Inputs!C:C,,0) -> Yahoo finance | D69: =_xlfn.XLOOKUP($A69,Inputs!$A:$A,Inputs!D:D,,0) -> 0 | E69: =_xlfn.XLOOKUP($A69,Inputs!$A:$A,Inputs!E:E,,0) -> 0 | F69: =_xlfn.XLOOKUP($A69,Inputs!$A:$A,Inputs!F:F,,0) -> 0 | G69: =_xlfn.XLOOKUP($A69,Inputs!$A:$A,Inputs!G:G,,0) -> 0 | H69: =_xlfn.XLOOKUP($A69,Inputs!$A:$A,Inputs!H:H,,0) -> 0 | I69: =_xlfn.XLOOKUP($A69,Inputs!$A:$A,Inputs!I:I,,0) -> 0 | J69: =_xlfn.XLOOKUP($A69,Inputs!$A:$A,Inputs!J:J,,0) -> 0 | K69: =_xlfn.XLOOKUP($A69,Inputs!$A:$A,Inputs!K:K,,0) -> 0 | L69: =_xlfn.XLOOKUP($A69,Inputs!$A:$A,Inputs!L:L,,0) -> 0 | M69: =_xlfn.XLOOKUP($A69,Inputs!$A:$A,Inputs!M:M,,0) -> 0
A70: Insiders Own | B70: =_xlfn.XLOOKUP($A70,Inputs!$A:$A,Inputs!B:B,,0) -> 0.0074 | C70: =_xlfn.XLOOKUP($A70,Inputs!$A:$A,Inputs!C:C,,0) -> Yahoo finance | D70: =_xlfn.XLOOKUP($A70,Inputs!$A:$A,Inputs!D:D,,0) -> 0 | E70: =_xlfn.XLOOKUP($A70,Inputs!$A:$A,Inputs!E:E,,0) -> 0 | F70: =_xlfn.XLOOKUP($A70,Inputs!$A:$A,Inputs!F:F,,0) -> 0 | G70: =_xlfn.XLOOKUP($A70,Inputs!$A:$A,Inputs!G:G,,0) -> 0 | H70: =_xlfn.XLOOKUP($A70,Inputs!$A:$A,Inputs!H:H,,0) -> 0 | I70: =_xlfn.XLOOKUP($A70,Inputs!$A:$A,Inputs!I:I,,0) -> 0 | J70: =_xlfn.XLOOKUP($A70,Inputs!$A:$A,Inputs!J:J,,0) -> 0 | K70: =_xlfn.XLOOKUP($A70,Inputs!$A:$A,Inputs!K:K,,0) -> 0 | L70: =_xlfn.XLOOKUP($A70,Inputs!$A:$A,Inputs!L:L,,0) -> 0 | M70: =_xlfn.XLOOKUP($A70,Inputs!$A:$A,Inputs!M:M,,0) -> 0
A71: Fitch/ S&P Rating | B71: =_xlfn.XLOOKUP($A71,Inputs!$A:$A,Inputs!B:B,,0) -> A- | C71: =_xlfn.XLOOKUP($A71,Inputs!$A:$A,Inputs!C:C,,0) -> 10-K | D71: =_xlfn.XLOOKUP($A71,Inputs!$A:$A,Inputs!D:D,,0) -> 0 | E71: =_xlfn.XLOOKUP($A71,Inputs!$A:$A,Inputs!E:E,,0) -> 0 | F71: =_xlfn.XLOOKUP($A71,Inputs!$A:$A,Inputs!F:F,,0) -> 0 | G71: =_xlfn.XLOOKUP($A71,Inputs!$A:$A,Inputs!G:G,,0) -> 0 | H71: =_xlfn.XLOOKUP($A71,Inputs!$A:$A,Inputs!H:H,,0) -> 0 | I71: =_xlfn.XLOOKUP($A71,Inputs!$A:$A,Inputs!I:I,,0) -> 0 | J71: =_xlfn.XLOOKUP($A71,Inputs!$A:$A,Inputs!J:J,,0) -> 0 | K71: =_xlfn.XLOOKUP($A71,Inputs!$A:$A,Inputs!K:K,,0) -> 0 | L71: =_xlfn.XLOOKUP($A71,Inputs!$A:$A,Inputs!L:L,,0) -> 0 | M71: =_xlfn.XLOOKUP($A71,Inputs!$A:$A,Inputs!M:M,,0) -> 0
A72: Dividend Yield | B72: =_xlfn.XLOOKUP($A72,Inputs!$A:$A,Inputs!B:B,,0) -> #N/A | C72: =_xlfn.XLOOKUP($A72,Inputs!$A:$A,Inputs!C:C,,0) -> #N/A | D72: =_xlfn.XLOOKUP($A72,Inputs!$A:$A,Inputs!D:D,,0) -> #N/A | E72: =_xlfn.XLOOKUP($A72,Inputs!$A:$A,Inputs!E:E,,0) -> #N/A | F72: =_xlfn.XLOOKUP($A72,Inputs!$A:$A,Inputs!F:F,,0) -> #N/A | G72: =_xlfn.XLOOKUP($A72,Inputs!$A:$A,Inputs!G:G,,0) -> #N/A | H72: =_xlfn.XLOOKUP($A72,Inputs!$A:$A,Inputs!H:H,,0) -> #N/A | I72: =_xlfn.XLOOKUP($A72,Inputs!$A:$A,Inputs!I:I,,0) -> #N/A | J72: =_xlfn.XLOOKUP($A72,Inputs!$A:$A,Inputs!J:J,,0) -> #N/A | K72: =_xlfn.XLOOKUP($A72,Inputs!$A:$A,Inputs!K:K,,0) -> #N/A | L72: =_xlfn.XLOOKUP($A72,Inputs!$A:$A,Inputs!L:L,,0) -> #N/A | M72: =_xlfn.XLOOKUP($A72,Inputs!$A:$A,Inputs!M:M,,0) -> #N/A
A73: Daily Volume in Millions of USD | B73: =_xlfn.XLOOKUP($A73,Inputs!$A:$A,Inputs!B:B,,0) -> 0 | C73: =_xlfn.XLOOKUP($A73,Inputs!$A:$A,Inputs!C:C,,0) -> Yahoo Finance | D73: =_xlfn.XLOOKUP($A73,Inputs!$A:$A,Inputs!D:D,,0) -> 0 | E73: =_xlfn.XLOOKUP($A73,Inputs!$A:$A,Inputs!E:E,,0) -> 0 | F73: =_xlfn.XLOOKUP($A73,Inputs!$A:$A,Inputs!F:F,,0) -> 0 | G73: =_xlfn.XLOOKUP($A73,Inputs!$A:$A,Inputs!G:G,,0) -> 0 | H73: =_xlfn.XLOOKUP($A73,Inputs!$A:$A,Inputs!H:H,,0) -> 0 | I73: =_xlfn.XLOOKUP($A73,Inputs!$A:$A,Inputs!I:I,,0) -> 0 | J73: =_xlfn.XLOOKUP($A73,Inputs!$A:$A,Inputs!J:J,,0) -> 0 | K73: =_xlfn.XLOOKUP($A73,Inputs!$A:$A,Inputs!K:K,,0) -> 0 | L73: =_xlfn.XLOOKUP($A73,Inputs!$A:$A,Inputs!L:L,,0) -> 0 | M73: =_xlfn.XLOOKUP($A73,Inputs!$A:$A,Inputs!M:M,,0) -> 0
B75: 2020 | C75: 2021 | D75: 2022
A76: Short % of Float | B76: 0 | C76: 0 | D76: 0
A77: EPS | B77: 0 | C77: 0 | D77: 0
A79: Corporate Bonds 3, 5 Y 10 | B79: Average Price | C79: Moody's | D79: YTM | E79: DIVISA
B80: =VLOOKUP($A80,Inputs!$A$5:$M$98,MATCH(B$4,Inputs!$B$5:$M$5,0)+1,FALSE) -> #N/A | C80: =VLOOKUP($A80,Inputs!$A$5:$M$98,MATCH(C$4,Inputs!$B$5:$M$5,0)+1,FALSE) -> #N/A | D80: =VLOOKUP($A80,Inputs!$A$5:$M$98,MATCH(D$4,Inputs!$B$5:$M$5,0)+1,FALSE) -> #N/A | E80: =VLOOKUP($A80,Inputs!$A$5:$M$98,MATCH(E$4,Inputs!$B$5:$M$5,0)+1,FALSE) -> #N/A

Sheet Assum.
B2: Growth Average last 3 years | E2: =+AVERAGE(DCF!D5:F5) -> 0.039251287
B3: Growth Average last 5 years | E3: =AVERAGE('Fin. Data'!B6:F6) -> 0.076392344
B4: Next 5 Years (per annum) | E4: 0.0696
B6: Real | I6: Forecast
B7: (millions) | C7: 2017 | D7: 2018 | E7: 2019 | F7: 2020 | G7: 2021 | H7: 2022 | I7: 2023 | J7: =+I7+1 -> 2024 | K7: =+J7+1 -> 2025 | L7: =+K7+1 -> 2026 | M7: =+L7+1 -> 2027 | N7: =+M7+1 -> 2028 | O7: =+N7+1 -> 2029 | P7: =+O7+1 -> 2030 | Q7: =+P7+1 -> 2031 | ... AH7: =+AG7+1 -> 2048
B8: Sales | C8: ='Fin. Data'!G5 -> 85029 | D8: ='Fin. Data'!F5 -> 94507 | E8: ='Fin. Data'!E5 -> 108942 | F8: ='Fin. Data'!D5 -> 103564 | G8: ='Fin. Data'!C5 -> 116385 | H8: ='Fin. Data'!B5 -> 121427 | I8: =+H8*(1+I9) -> 125676.94 | J8: =+I8*(1+J9) -> 130255.18 | K8: =+J8*(1+K9) -> 135217.28 | L8: =+K8*(1+L9) -> 140593.78 | M8: =+L8*(1+M9) -> 146418.37 | N8: =+M8*(1+N9) -> 152728.31 | O8: =+N8*(1+O9) -> 159564.72 | P8: =+O8*(1+P9) -> 166745.13 | ... AH8: =+AG8*(1+AH9) -> 250028.98
B9: % Growth | D9: =(D8/C8)-1 -> 0.11146785 | E9: =(E8/D8)-1 -> 0.15274001 | F9: =(F8/E8)-1 -> -0.049365718 | G9: =(G8/F8)-1 -> 0.12379784 | H9: =(H8/G8)-1 -> 0.043321734 | I9: 0.035 | J9: =I9+($P9-$I9)/7 -> 0.036428571 | K9: =J9+($P9-$I9)/6 -> 0.038095238 | L9: =K9+($P9-$I9)/6 -> 0.039761905 | M9: =L9+($P9-$I9)/6 -> 0.041428571 | N9: =M9+($P9-$I9)/6 -> 0.043095238 | O9: =N9+($P9-$I9)/6 -> 0.044761905 | P9: 0.045 | Q9: =+P9+($U$9-$P$9)/5 -> 0.04 | R9: =+Q9+($U$9-$P$9)/5 -> 0.035 | S9: =+R9+($U$9-$P$9)/5 -> 0.03 | T9: =+S9+($U$9-$P$9)/5 -> 0.025 | U9: 0.02 | V9: 0.02 | W9: 0.02 | X9: 0.02 | Y9: 0.02 | Z9: 0.02 | AA9: 0.02 | AB9: 0.02 | AC9: 0.02 | AD9: 0.02 | AE9: 0.02 | AF9: 0.02 | AG9: 0.02 | AH9: 0.02
D12: 2018 | E12: 2019 | F12: 2020 | G12: 2021 | H12: 2022 | I12: Average/Target
B13: Capex % sales | D13: =+'Fin. Data'!F32/'Fin. Data'!F5 -> -0.10342091 | E13: =+'Fin. Data'!E32/'Fin. Data'!E5 -> -0.09136054 | F13: =+'Fin. Data'!D32/'Fin. Data'!D5 -> -0.088631185 | G13: =+'Fin. Data'!C32/'Fin. Data'!C5 -> -0.078824591 | H13: =+'Fin. Data'!B32/'Fin. Data'!B5 -> -0.087509368 | I13: =AVERAGE(D13:H13) -> -0.089949319 | J13: {=+AVERAGE('Fin. Data'!B32:L32/'Fin. Data'!B5:L5)} -> -0.099136182
B14: Acquisitions | D14: =+'Fin. Data'!F33 -> -38219 | E14: =+'Fin. Data'!E33 -> -370 | F14: =+'Fin. Data'!D33 -> -233 | G14: =+'Fin. Data'!C33 -> -1374 | H14: =+'Fin. Data'!B33 -> -12 | I14: =(AVERAGE(E14:H14)/AVERAGE(E8:H8)) -> -0.0044168787 | J14: =(AVERAGE('Fin. Data'!B33:M33)/AVERAGE('Fin. Data'!B5:M5)) -> -0.047096082
B15: Depreciation | F15: =+DCF!D9/DCF!D40 -> -0.14916008 | G15: =+DCF!E9/DCF!E40 -> -0.14257858 | H15: =+DCF!F9/DCF!F40 -> -0.14189519 | I15: =AVERAGE(F15:H15) -> -0.14454461
B16: Amortizations | F16: =+DCF!D10/DCF!D38 -> -0.050446419 | G16: =+DCF!E10/DCF!E38 -> -0.055688249 | H16: =+DCF!F10/DCF!F38 -> -0.057528217 | I16: =AVERAGE(F16:H16) -> -0.054554295
B18: Stock base compensation expense % sales
D19: =-826/D8 -> -0.0087400933 | E19: =-1021/E8 -> -0.0093719594 | F19: =DCF!D11/DCF!D6 -> -0.011519447 | G19: =DCF!E11/DCF!E6 -> -0.011298707 | H19: =DCF!F11/DCF!F6 -> -0.011002495 | I19: =AVERAGE(D19:H19) -> -0.01038654
B22: Debt/EBITDA | D22: ='Fin. Data'!F58/'Fin. Data'!F19 -> 3.5889335 | E22: ='Fin. Data'!E58/'Fin. Data'!E19 -> 3.1967004 | F22: ='Fin. Data'!D58/'Fin. Data'!D19 -> 3.7454558 | G22: ='Fin. Data'!C58/'Fin. Data'!C19 -> 3.2785592 | H22: ='Fin. Data'!B58/'Fin. Data'!B19 -> 3.6563729 | I22: =AVERAGE(D22:H22) -> 3.4932043 | J22: =2-0.1 -> 1.9 | K22: =+J22-0.1 -> 1.8 | L22: =+K22-0.1 -> 1.7 | M22: =+L22-0.1 -> 1.6 | N22: =+M22-0.1 -> 1.5 | O22: =+N22-0.1 -> 1.4 | P22: =+O22-0.1 -> 1.3 | Q22: =+P22-0.1 -> 1.2 | R22: =+Q22-0.1 -> 1.1 | ... AB22: =+AA22-0.1 -> 0.1 | AC22: 0.1 | AD22: 0.1 | AE22: 0.1 | AF22: 0.1
B23: Target
B24: Net debt-to-EBITDA | J24: =+(DCF!G44-DCF!G43)/DCF!G12 -> 3.3068486 | K24: =+(DCF!H44-DCF!H43)/DCF!H12 -> 2.8564124 | L24: =+(DCF!I44-DCF!I43)/DCF!I12 -> 2.4658681 | M24: =+(DCF!J44-DCF!J43)/DCF!J12 -> 2.0786896 | N24: =+(DCF!K44-DCF!K43)/DCF!K12 -> 2.01057 | O24: =+(DCF!L44-DCF!L43)/DCF!L12 -> 1.8169775 | P24: =+(DCF!M44-DCF!M43)/DCF!M12 -> 1.6120998 | Q24: =+(DCF!N44-DCF!N43)/DCF!N12 -> 1.3996855 | ... AI24: =+(DCF!AF44-DCF!AF43)/DCF!AF12 -> -3.921436
B26: Dividends
B27: % past year net income | D27: ='Fin. Data'!F27/'Fin. Data'!F23 -> -0.28258304 | E27: ='Fin. Data'!E27/'Fin. Data'!E23 -> -0.28034227 | F27: ='Fin. Data'!D27/'Fin. Data'!D23 -> -0.38687973 | G27: ='Fin. Data'!C27/'Fin. Data'!C23 -> -0.32762235 | H27: ='Fin. Data'!B27/'Fin. Data'!B23 -> -0.96263959 | I27: =AVERAGE(D27:H27) -> -0.4480134 | J27: {=AVERAGE('Fin. Data'!B27:M27/'Fin. Data'!B23:M23)} -> -0.32631986
B29: Repurchase
B30: % past year net income | D30: =+'Fin. Data'!F28/'Fin. Data'!F23 -> -0.44849098 | E30: =+'Fin. Data'!E28/'Fin. Data'!E23 -> -0.037829318 | F30: =+'Fin. Data'!D28/'Fin. Data'!D23 -> -0.049901878 | G30: =+'Fin. Data'!C28/'Fin. Data'!C23 -> -0.33774308 | H30: =+'Fin. Data'!B28/'Fin. Data'!B23 -> -2.7061929 | I30: =AVERAGE(D30:G30) -> -0.21849131 | K30: {=AVERAGE(('Fin. Data'!B28:K28/'Fin. Data'!B23:K23))} -> -0.46903973
B32: Payout ratio 5 Y average (dividends+ share repurchases) | I32: =-AVERAGE('Fin. Data'!C36:G36) -> 0.50285509
B34: Tax rate | D34: -0.222 | E34: -0.216 | F34: =DCF!D16/DCF!D15 -> -0.23917526 | G34: =DCF!E16/DCF!E15 -> -0.27545569 | H34: =DCF!F16/DCF!F15 -> -0.46951745 | I34: =AVERAGE(D34:G34) -> -0.23815774 | J34: =-3013/10970 -> -0.27465816
B37: Segments | C37: Weight | D37: Country Risk Premium | F37: Equity Risk Premium
B38: U.S. | C38: =Segments!B5 -> 0.11018966 | D38: 0 | F38: 0.05
B39: U.K. | C39: =Segments!B6 -> 0.79423028 | D39: 0.0091 | F39: 0.0591
B40: =Segments!C8 -> Other | C40: =Segments!B8 -> 0.09558006 | D40: =+(0+0.0333+0.0091+0.0061)/4 -> 0.012125 | F40: =+(0.05+0.0833+0.0591+0.0561)/4 -> 0.062125
B41: Total | C41: =SUM(C38:C40) -> 1 | D41: =D38*C38+C39*D39+C40*D40 -> 0.0083864038 | F41: =F38*C38+C39*F39+C40*F40 -> 0.058386404
B44: Estimating Working Capital | D44: 2022 | E44: 2021 | F44: 2020 | G44: 2019 | H44: 2018 | I44: 2017 | J44: 2016 | K44: 2015 | L44: 2014 | M44: 2013 | N44: 2012 | O44: AVERAGE
B45: % of change revenues | D45: =+Inputs!B62/(Inputs!B6-Inputs!C6) -> -0.59619199 | E45: =+Inputs!C62/(Inputs!C6-Inputs!D6) -> -0.11691756 | F45: =+Inputs!D62/(Inputs!D6-Inputs!E6) -> 0.033097806 | G45: =+Inputs!E62/(Inputs!E6-Inputs!F6) -> -0.16175961 | H45: =+Inputs!F62/(Inputs!F6-Inputs!G6) -> -0.13853134 | I45: =+Inputs!G62/(Inputs!G6-Inputs!H6) -> -0.12718379 | J45: =+Inputs!H62/(Inputs!H6-Inputs!I6) -> -0.22550594 | K45: =+Inputs!I62/(Inputs!I6-Inputs!J6) -> -0.046556234 | ... N45: =+Inputs!L62/(Inputs!L6-Inputs!M6) -> -0.062128419 | O45: =AVERAGE(D45:N45) -> -0.13489164
B47: Cost of Debt | D47: 2022 | E47: 2021 | F47: 2020 | G47: 2019 | H47: 2018 | I47: AVERAGE
B48: Interest Coverage ratio | D48: =+'Fin. Data'!B16/3896 -> 3.8249487 | E48: =+'Fin. Data'!C16/4281 -> 4.2655922 | F48: =+'Fin. Data'!D16/4588 -> 3.559939 | G48: =+'Fin. Data'!E16/4567 -> 4.5296694 | H48: =+'Fin. Data'!F16/3542 -> 5.4302654 | I48: =AVERAGE(D48:H48) -> 4.3220829
B50: A3/A-(current level)
B51: Default spread | I51: 0.0162
B52: 30Y US Bond Yield | I52: 0.0391
B53: 5Y US Bond Yield | I53: 0.0418
B54: Country default spread (US) | I54: 0
B55: Short-term cost debt | I55: =I51+I53+I54 -> 0.058
B56: Long-term cost of debt | I56: =I54+I52+I51 -> 0.0553
B58: Operating margin
B59: Last 7y average | D59: =AVERAGE('Fin. Data'!B12:H12) -> 0.18268991 | F59: 2023 1Q | G59: =6709/30513 -> 0.2198735 | H59: 2022 1Q | I59: =6367/30016 -> 0.2121202
B60: Last 10Y average | D60: =AVERAGE('Fin. Data'!B12:K12) -> 0.19200139 | F60: 2023 2Q | G60: =12355/60205 -> 0.20521551 | H60: 2022 2Q | I60: =11936/61026 -> 0.19558877
B62: Debt/Ebitda | C62: 2022 | D62: =+C62-1 -> 2021 | E62: =+D62-1 -> 2020 | F62: =+E62-1 -> 2019 | G62: =+F62-1 -> 2018 | H62: =+G62-1 -> 2017 | I62: =+H62-1 -> 2016 | J62: =+I62-1 -> 2015 | K62: =+J62-1 -> 2014 | ... M62: =+L62-1 -> 2012 | N62: Average 10Y | O62: Average 5Y
C63: ='Fin. Data'!B58/'Fin. Data'!B19 -> 3.6563729 | D63: ='Fin. Data'!C58/'Fin. Data'!C19 -> 3.2785592 | E63: ='Fin. Data'!D58/'Fin. Data'!D19 -> 3.7454558 | F63: ='Fin. Data'!E58/'Fin. Data'!E19 -> 3.1967004 | G63: ='Fin. Data'!F58/'Fin. Data'!F19 -> 3.5889335 | H63: ='Fin. Data'!G58/'Fin. Data'!G19 -> 2.1778266 | I63: ='Fin. Data'!H58/'Fin. Data'!H19 -> 2.1520527 | J63: ='Fin. Data'!I58/'Fin. Data'!I19 -> 1.9914641 | ... M63: ='Fin. Data'!L58/'Fin. Data'!L19 -> 2.1126151 | N63: =AVERAGE(C63:M63) -> 2.7200049
B65: Interest expense/Debt | C65: =-Inputs!B10/+'Fin. Data'!B58 -> 0.037096989 | D65: =-Inputs!C10/+'Fin. Data'!C58 -> 0.040722174 | E65: =-Inputs!D10/+'Fin. Data'!D58 -> 0.041618287 | F65: =-Inputs!E10/+'Fin. Data'!E58 -> 0.042469104 | G65: =-Inputs!F10/+'Fin. Data'!F58 -> 0.032996413 | H65: =-Inputs!G10/+'Fin. Data'!G58 -> 0.051933627 | I65: =-Inputs!H10/+'Fin. Data'!H58 -> 0.052946046 | J65: =-Inputs!I10/+'Fin. Data'!I58 -> 0.05514961 | ... M65: =-Inputs!L10/+'Fin. Data'!L58 -> 0.066199254 | N65: =+AVERAGE(C65:M65) -> 0.048958993 | O65: =+AVERAGE(C65:G65) -> 0.038980594
B69: Notes
B70: Effective Tax Rate Benchmarks of Communication Services : https://finbox.com/NASDAQGS:CMCS.A/explorer/effect_tax_rate/
B71: Debt to Ebitda https://www.discoverci.com/companies/CMCSA/debt-to-ebitda
B72: Country Default Spreads and Risk Premiums https://pages.stern.nyu.edu/~adamodar/New_Home_Page/datafile/ctryprem.html

Sheet Fin. Data
A1: =Inputs!H3 -> #VALUE!
A2: =Inputs!G2 -> Figures in Millions of USD
A3: Results
B4: =OP!J19 -> 2022 | C4: =B4-1 -> 2021 | D4: =C4-1 -> 2020 | E4: =D4-1 -> 2019 | F4: =E4-1 -> 2018 | G4: =F4-1 -> 2017 | H4: =G4-1 -> 2016 | I4: =H4-1 -> 2015 | J4: =I4-1 -> 2014 | ... M4: =L4-1 -> 2011
A5: Net Sales | B5: =_xlfn.XLOOKUP($A5,Inputs!$A:$A,Inputs!B:B,,0) -> 121427 | C5: =_xlfn.XLOOKUP($A5,Inputs!$A:$A,Inputs!C:C,,0) -> 116385 | D5: =_xlfn.XLOOKUP($A5,Inputs!$A:$A,Inputs!D:D,,0) -> 103564 | E5: =_xlfn.XLOOKUP($A5,Inputs!$A:$A,Inputs!E:E,,0) -> 108942 | F5: =_xlfn.XLOOKUP($A5,Inputs!$A:$A,Inputs!F:F,,0) -> 94507 | G5: =_xlfn.XLOOKUP($A5,Inputs!$A:$A,Inputs!G:G,,0) -> 85029 | H5: =_xlfn.XLOOKUP($A5,Inputs!$A:$A,Inputs!H:H,,0) -> 80736 | I5: =_xlfn.XLOOKUP($A5,Inputs!$A:$A,Inputs!I:I,,0) -> 74510 | J5: =_xlfn.XLOOKUP($A5,Inputs!$A:$A,Inputs!J:J,,0) -> 68775 | K5: =_xlfn.XLOOKUP($A5,Inputs!$A:$A,Inputs!K:K,,0) -> 64657 | L5: =_xlfn.XLOOKUP($A5,Inputs!$A:$A,Inputs!L:L,,0) -> 62570 | M5: =_xlfn.XLOOKUP($A5,Inputs!$A:$A,Inputs!M:M,,0) -> 55842
A6: Growth vs. Previous year | B6: =IFERROR(B5/C5-1,"-") -> 0.043321734 | C6: =IFERROR(C5/D5-1,"-") -> 0.12379784 | D6: =IFERROR(D5/E5-1,"-") -> -0.049365718 | E6: =IFERROR(E5/F5-1,"-") -> 0.15274001 | F6: =IFERROR(F5/G5-1,"-") -> 0.11146785 | G6: =IFERROR(G5/H5-1,"-") -> 0.053173306 | H6: =IFERROR(H5/I5-1,"-") -> 0.083559254 | I6: =IFERROR(I5/J5-1,"-") -> 0.083387859 | ... L6: =IFERROR(L5/M5-1,"-") -> 0.12048279 | M6: =IFERROR(M5/#REF!-1,"-") -> -
A7: Gross Profit | B7: =_xlfn.XLOOKUP($A7,Inputs!$A:$A,Inputs!B:B,,0) -> 36445 | C7: =_xlfn.XLOOKUP($A7,Inputs!$A:$A,Inputs!C:C,,0) -> 34621 | D7: =_xlfn.XLOOKUP($A7,Inputs!$A:$A,Inputs!D:D,,0) -> 30593 | E7: =_xlfn.XLOOKUP($A7,Inputs!$A:$A,Inputs!E:E,,0) -> 34078 | F7: =_xlfn.XLOOKUP($A7,Inputs!$A:$A,Inputs!F:F,,0) -> 29685 | G7: =_xlfn.XLOOKUP($A7,Inputs!$A:$A,Inputs!G:G,,0) -> 27706 | H7: =_xlfn.XLOOKUP($A7,Inputs!$A:$A,Inputs!H:H,,0) -> 26257 | I7: =_xlfn.XLOOKUP($A7,Inputs!$A:$A,Inputs!I:I,,0) -> 24678 | J7: =_xlfn.XLOOKUP($A7,Inputs!$A:$A,Inputs!J:J,,0) -> 22923 | K7: =_xlfn.XLOOKUP($A7,Inputs!$A:$A,Inputs!K:K,,0) -> 21434 | L7: =_xlfn.XLOOKUP($A7,Inputs!$A:$A,Inputs!L:L,,0) -> 19977 | M7: =_xlfn.XLOOKUP($A7,Inputs!$A:$A,Inputs!M:M,,0) -> 24440
A8: % over sales | B8: =IFERROR(B7/B$5,"-") -> 0.30013918 | C8: =IFERROR(C7/C$5,"-") -> 0.29746961 | D8: =IFERROR(D7/D$5,"-") -> 0.29540188 | E8: =IFERROR(E7/E$5,"-") -> 0.31280865 | F8: =IFERROR(F7/F$5,"-") -> 0.31410372 | G8: =IFERROR(G7/G$5,"-") -> 0.32584177 | H8: =IFERROR(H7/H$5,"-") -> 0.32522047 | I8: =IFERROR(I7/I$5,"-") -> 0.33120387 | ... M8: =IFERROR(M7/M$5,"-") -> 0.43766341
A9: Operating expenses | B9: =B5-B11 -> 107386 | C9: =C5-C11 -> 95568 | D9: =D5-D11 -> 86071 | E9: =E5-E11 -> 87817 | F9: =F5-F11 -> 75498 | G9: =G5-G11 -> 67011 | H9: =H5-H11 -> 63905 | I9: =I5-I11 -> 58512 | ... M9: =M5-M11 -> 45121
A10: % over sales | B10: =IFERROR(B9/B$5,"-") -> 0.88436674 | C10: =IFERROR(C9/C$5,"-") -> 0.82113674 | D10: =IFERROR(D9/D$5,"-") -> 0.83108995 | E10: =IFERROR(E9/E$5,"-") -> 0.80608948 | F10: =IFERROR(F9/F$5,"-") -> 0.79886146 | G10: =IFERROR(G9/G$5,"-") -> 0.78809583 | H10: =IFERROR(H9/H$5,"-") -> 0.79153042 | I10: =IFERROR(I9/I$5,"-") -> 0.78529057 | ... M10: =IFERROR(M9/M$5,"-") -> 0.80801189
A11: Operating Income | B11: =_xlfn.XLOOKUP($A11,Inputs!$A:$A,Inputs!B:B,,0) -> 14041 | C11: =_xlfn.XLOOKUP($A11,Inputs!$A:$A,Inputs!C:C,,0) -> 20817 | D11: =_xlfn.XLOOKUP($A11,Inputs!$A:$A,Inputs!D:D,,0) -> 17493 | E11: =_xlfn.XLOOKUP($A11,Inputs!$A:$A,Inputs!E:E,,0) -> 21125 | F11: =_xlfn.XLOOKUP($A11,Inputs!$A:$A,Inputs!F:F,,0) -> 19009 | G11: =_xlfn.XLOOKUP($A11,Inputs!$A:$A,Inputs!G:G,,0) -> 18018 | H11: =_xlfn.XLOOKUP($A11,Inputs!$A:$A,Inputs!H:H,,0) -> 16831 | I11: =_xlfn.XLOOKUP($A11,Inputs!$A:$A,Inputs!I:I,,0) -> 15998 | J11: =_xlfn.XLOOKUP($A11,Inputs!$A:$A,Inputs!J:J,,0) -> 14904 | K11: =_xlfn.XLOOKUP($A11,Inputs!$A:$A,Inputs!K:K,,0) -> 13563 | L11: =_xlfn.XLOOKUP($A11,Inputs!$A:$A,Inputs!L:L,,0) -> 12179 | M11: =_xlfn.XLOOKUP($A11,Inputs!$A:$A,Inputs!M:M,,0) -> 10721
A12: Operating Margin | B12: =IFERROR(B11/B$5,"-") -> 0.11563326 | C12: =IFERROR(C11/C$5,"-") -> 0.17886326 | D12: =IFERROR(D11/D$5,"-") -> 0.16891005 | E12: =IFERROR(E11/E$5,"-") -> 0.19391052 | F12: =IFERROR(F11/F$5,"-") -> 0.20113854 | G12: =IFERROR(G11/G$5,"-") -> 0.21190417 | H12: =IFERROR(H11/H$5,"-") -> 0.20846958 | I12: =IFERROR(I11/I$5,"-") -> 0.21470943 | ... M12: =IFERROR(M11/M$5,"-") -> 0.19198811
A13: Growth vs. Previous year | B13: =IFERROR(B12/C12-1,"-") -> -0.35351025 | C13: =IFERROR(C12/D12-1,"-") -> 0.058926096 | D13: =IFERROR(D12/E12-1,"-") -> -0.12892789 | E13: =IFERROR(E12/F12-1,"-") -> -0.035935524 | F13: =IFERROR(F12/G12-1,"-") -> -0.050804256 | G13: =IFERROR(G12/H12-1,"-") -> 0.016475277 | H13: =IFERROR(H12/I12-1,"-") -> -0.029061858 | I13: =IFERROR(I12/J12-1,"-") -> -0.0092162245 | ... L13: =IFERROR(L12/M12-1,"-") -> 0.01384402 | M13: =IFERROR(M12/#REF!-1,"-") -> -
A14: Net Financial Cost | B14: =_xlfn.XLOOKUP($A14,Inputs!$A:$A,Inputs!B:B,,0) -> -3896 | C14: =_xlfn.XLOOKUP($A14,Inputs!$A:$A,Inputs!C:C,,0) -> -4281 | D14: =_xlfn.XLOOKUP($A14,Inputs!$A:$A,Inputs!D:D,,0) -> -4588 | E14: =_xlfn.XLOOKUP($A14,Inputs!$A:$A,Inputs!E:E,,0) -> -4567 | F14: =_xlfn.XLOOKUP($A14,Inputs!$A:$A,Inputs!F:F,,0) -> -3542 | G14: =_xlfn.XLOOKUP($A14,Inputs!$A:$A,Inputs!G:G,,0) -> -3086 | H14: =_xlfn.XLOOKUP($A14,Inputs!$A:$A,Inputs!H:H,,0) -> -2942 | I14: =_xlfn.XLOOKUP($A14,Inputs!$A:$A,Inputs!I:I,,0) -> -2702 | J14: =_xlfn.XLOOKUP($A14,Inputs!$A:$A,Inputs!J:J,,0) -> -2617 | K14: =_xlfn.XLOOKUP($A14,Inputs!$A:$A,Inputs!K:K,,0) -> -2574 | L14: =_xlfn.XLOOKUP($A14,Inputs!$A:$A,Inputs!L:L,,0) -> -2521 | M14: =_xlfn.XLOOKUP($A14,Inputs!$A:$A,Inputs!M:M,,0) -> -2505
A15: Other Expenses (Revenues) | B15: =_xlfn.XLOOKUP($A15,Inputs!$A:$A,Inputs!B:B,,0) -> -861 | C15: =_xlfn.XLOOKUP($A15,Inputs!$A:$A,Inputs!C:C,,0) -> 2556 | D15: =_xlfn.XLOOKUP($A15,Inputs!$A:$A,Inputs!D:D,,0) -> 1160 | E15: =_xlfn.XLOOKUP($A15,Inputs!$A:$A,Inputs!E:E,,0) -> 438 | F15: =_xlfn.XLOOKUP($A15,Inputs!$A:$A,Inputs!F:F,,0) -> -225 | G15: =_xlfn.XLOOKUP($A15,Inputs!$A:$A,Inputs!G:G,,0) -> 421 | H15: =_xlfn.XLOOKUP($A15,Inputs!$A:$A,Inputs!H:H,,0) -> 437 | I15: =_xlfn.XLOOKUP($A15,Inputs!$A:$A,Inputs!I:I,,0) -> 76 | J15: =_xlfn.XLOOKUP($A15,Inputs!$A:$A,Inputs!J:J,,0) -> 178 | K15: =_xlfn.XLOOKUP($A15,Inputs!$A:$A,Inputs!K:K,,0) -> 126 | L15: =_xlfn.XLOOKUP($A15,Inputs!$A:$A,Inputs!L:L,,0) -> 1951 | M15: =_xlfn.XLOOKUP($A15,Inputs!$A:$A,Inputs!M:M,,0) -> -9 | O15: =AVERAGE(B15:L15) -> 568.81818
A16: EBIT | B16: =B11-B15 -> 14902 | C16: =C11-C15 -> 18261 | D16: =D11-D15 -> 16333 | E16: =E11-E15 -> 20687 | F16: =F11-F15 -> 19234 | G16: =G11-G15 -> 17597 | H16: =H11-H15 -> 16394 | I16: =I11-I15 -> 15922 | ... M16: =M11-M15 -> 10730
A17: Depreciation & Amortization | B17: =_xlfn.XLOOKUP($A17,Inputs!$A:$A,Inputs!B:B,,0) -> 13821 | C17: =_xlfn.XLOOKUP($A17,Inputs!$A:$A,Inputs!C:C,,0) -> 13804 | D17: =_xlfn.XLOOKUP($A17,Inputs!$A:$A,Inputs!D:D,,0) -> 13100 | E17: =_xlfn.XLOOKUP($A17,Inputs!$A:$A,Inputs!E:E,,0) -> 12953 | F17: =_xlfn.XLOOKUP($A17,Inputs!$A:$A,Inputs!F:F,,0) -> 10676 | G17: =_xlfn.XLOOKUP($A17,Inputs!$A:$A,Inputs!G:G,,0) -> 9688 | H17: =_xlfn.XLOOKUP($A17,Inputs!$A:$A,Inputs!H:H,,0) -> 9426 | I17: =_xlfn.XLOOKUP($A17,Inputs!$A:$A,Inputs!I:I,,0) -> 8680 | J17: =_xlfn.XLOOKUP($A17,Inputs!$A:$A,Inputs!J:J,,0) -> 8019 | K17: =_xlfn.XLOOKUP($A17,Inputs!$A:$A,Inputs!K:K,,0) -> 7871 | L17: =_xlfn.XLOOKUP($A17,Inputs!$A:$A,Inputs!L:L,,0) -> 7798 | M17: =_xlfn.XLOOKUP($A17,Inputs!$A:$A,Inputs!M:M,,0) -> 7636
A18: Changes Net Working Capital | B18: =_xlfn.XLOOKUP($A18,Inputs!$A:$A,Inputs!B:B,,0) -> 2442 | C18: =_xlfn.XLOOKUP($A18,Inputs!$A:$A,Inputs!C:C,,0) -> 543 | D18: =_xlfn.XLOOKUP($A18,Inputs!$A:$A,Inputs!D:D,,0) -> -3395 | E18: =_xlfn.XLOOKUP($A18,Inputs!$A:$A,Inputs!E:E,,0) -> -831 | F18: =_xlfn.XLOOKUP($A18,Inputs!$A:$A,Inputs!F:F,,0) -> -491 | G18: =_xlfn.XLOOKUP($A18,Inputs!$A:$A,Inputs!G:G,,0) -> -603 | H18: =_xlfn.XLOOKUP($A18,Inputs!$A:$A,Inputs!H:H,,0) -> -305 | I18: =_xlfn.XLOOKUP($A18,Inputs!$A:$A,Inputs!I:I,,0) -> -381 | J18: =_xlfn.XLOOKUP($A18,Inputs!$A:$A,Inputs!J:J,,0) -> -1234 | K18: =_xlfn.XLOOKUP($A18,Inputs!$A:$A,Inputs!K:K,,0) -> 1119 | L18: =_xlfn.XLOOKUP($A18,Inputs!$A:$A,Inputs!L:L,,0) -> -1386 | M18: =_xlfn.XLOOKUP($A18,Inputs!$A:$A,Inputs!M:M,,0) -> -6288
A19: EBITDA | B19: =B11-B15+B17 -> 28723 | C19: =C11-C15+C17 -> 32065 | D19: =D11-D15+D17 -> 29433 | E19: =E11-E15+E17 -> 33640 | F19: =F11-F15+F17 -> 29910 | G19: =G11-G15+G17 -> 27285 | H19: =H11-H15+H17 -> 25820 | I19: =I11-I15+I17 -> 24602 | ... M19: =M11-M15+M17 -> 18366
A20: EBITDA Margin | B20: =IFERROR(B19/B$5,"-") -> 0.23654541 | C20: =IFERROR(C19/C$5,"-") -> 0.27550801 | D20: =IFERROR(D19/D$5,"-") -> 0.28420107 | E20: =IFERROR(E19/E$5,"-") -> 0.30878816 | F20: =IFERROR(F19/F$5,"-") -> 0.31648449 | G20: =IFERROR(G19/G$5,"-") -> 0.32089052 | H20: =IFERROR(H19/H$5,"-") -> 0.31980777 | I20: =IFERROR(I19/I$5,"-") -> 0.33018387 | ... M20: =IFERROR(M19/M$5,"-") -> 0.32889223
A21: Taxes | B21: =_xlfn.XLOOKUP($A21,Inputs!$A:$A,Inputs!B:B,,0) -> -4359 | C21: =_xlfn.XLOOKUP($A21,Inputs!$A:$A,Inputs!C:C,,0) -> -5259 | D21: =_xlfn.XLOOKUP($A21,Inputs!$A:$A,Inputs!D:D,,0) -> -3364 | E21: =_xlfn.XLOOKUP($A21,Inputs!$A:$A,Inputs!E:E,,0) -> -3673 | F21: =_xlfn.XLOOKUP($A21,Inputs!$A:$A,Inputs!F:F,,0) -> -3380 | G21: =_xlfn.XLOOKUP($A21,Inputs!$A:$A,Inputs!G:G,,0) -> 7569 | H21: =_xlfn.XLOOKUP($A21,Inputs!$A:$A,Inputs!H:H,,0) -> -5298 | I21: =_xlfn.XLOOKUP($A21,Inputs!$A:$A,Inputs!I:I,,0) -> -4959 | J21: =_xlfn.XLOOKUP($A21,Inputs!$A:$A,Inputs!J:J,,0) -> -3873 | K21: =_xlfn.XLOOKUP($A21,Inputs!$A:$A,Inputs!K:K,,0) -> -3980 | L21: =_xlfn.XLOOKUP($A21,Inputs!$A:$A,Inputs!L:L,,0) -> -3744 | M21: =_xlfn.XLOOKUP($A21,Inputs!$A:$A,Inputs!M:M,,0) -> -3050
A22: % Tax | B22: =IFERROR(B21/B$5,"-") -> -0.035898112 | C22: =IFERROR(C21/C$5,"-") -> -0.045186235 | D22: =IFERROR(D21/D$5,"-") -> -0.03248233 | E22: =IFERROR(E21/E$5,"-") -> -0.033715188 | F22: =IFERROR(F21/F$5,"-") -> -0.035764547 | G22: =IFERROR(G21/G$5,"-") -> 0.089016688 | H22: =IFERROR(H21/H$5,"-") -> -0.065621284 | I22: =IFERROR(I21/I$5,"-") -> -0.066554825 | ... M22: =IFERROR(M21/M$5,"-") -> -0.054618388
A23: Net Income | B23: =_xlfn.XLOOKUP($A23,Inputs!$A:$A,Inputs!B:B,,0) -> 4925 | C23: =_xlfn.XLOOKUP($A23,Inputs!$A:$A,Inputs!C:C,,0) -> 13833 | D23: =_xlfn.XLOOKUP($A23,Inputs!$A:$A,Inputs!D:D,,0) -> 10701 | E23: =_xlfn.XLOOKUP($A23,Inputs!$A:$A,Inputs!E:E,,0) -> 13323 | F23: =_xlfn.XLOOKUP($A23,Inputs!$A:$A,Inputs!F:F,,0) -> 11862 | G23: =_xlfn.XLOOKUP($A23,Inputs!$A:$A,Inputs!G:G,,0) -> 22922 | H23: =_xlfn.XLOOKUP($A23,Inputs!$A:$A,Inputs!H:H,,0) -> 9028 | I23: =_xlfn.XLOOKUP($A23,Inputs!$A:$A,Inputs!I:I,,0) -> 8413 | J23: =_xlfn.XLOOKUP($A23,Inputs!$A:$A,Inputs!J:J,,0) -> 8592 | K23: =_xlfn.XLOOKUP($A23,Inputs!$A:$A,Inputs!K:K,,0) -> 7135 | L23: =_xlfn.XLOOKUP($A23,Inputs!$A:$A,Inputs!L:L,,0) -> 7865 | M23: =_xlfn.XLOOKUP($A23,Inputs!$A:$A,Inputs!M:M,,0) -> 5157
A24: Net Income Margin | B24: =IFERROR(B23/B$5,"-") -> 0.040559348 | C24: =IFERROR(C23/C$5,"-") -> 0.11885552 | D24: =IFERROR(D23/D$5,"-") -> 0.10332741 | E24: =IFERROR(E23/E$5,"-") -> 0.12229443 | F24: =IFERROR(F23/F$5,"-") -> 0.12551451 | G24: =IFERROR(G23/G$5,"-") -> 0.26957861 | H24: =IFERROR(H23/H$5,"-") -> 0.11182124 | I24: =IFERROR(I23/I$5,"-") -> 0.11291102 | ... M24: =IFERROR(M23/M$5,"-") -> 0.092349844
A25: Growth vs. Previous year | B25: =IFERROR(B24/C24-1,"-") -> -0.65875083 | C25: =IFERROR(C24/D24-1,"-") -> 0.15028066 | D25: =IFERROR(D24/E24-1,"-") -> -0.15509309 | E25: =IFERROR(E24/F24-1,"-") -> -0.025655043 | F25: =IFERROR(F24/G24-1,"-") -> -0.53440479 | G25: =IFERROR(G24/H24-1,"-") -> 1.4107996 | H25: =IFERROR(H24/I24-1,"-") -> -0.0096516188 | I25: =IFERROR(I24/J24-1,"-") -> -0.096199336 | ... L25: =IFERROR(L24/M24-1,"-") -> 0.36111997 | M25: =IFERROR(M24/#REF!-1,"-") -> -
A26: Cash Generated | B26: =B39-C39 -> -3962 | C26: =C39-D39 -> -3029 | D26: =D39-E39 -> 6240 | E26: =E39-F39 -> 1686 | F26: =F39-G39 -> 386 | G26: =G39-H39 -> 127 | H26: =H39-I39 -> 1006 | I26: =I39-J39 -> -1615 | ... M26: =M39-N39 -> 1620
A27: Dividends | B27: =_xlfn.XLOOKUP($A27,Inputs!$A:$A,Inputs!B:B,,0) -> -4741 | C27: =_xlfn.XLOOKUP($A27,Inputs!$A:$A,Inputs!C:C,,0) -> -4532 | D27: =_xlfn.XLOOKUP($A27,Inputs!$A:$A,Inputs!D:D,,0) -> -4140 | E27: =_xlfn.XLOOKUP($A27,Inputs!$A:$A,Inputs!E:E,,0) -> -3735 | F27: =_xlfn.XLOOKUP($A27,Inputs!$A:$A,Inputs!F:F,,0) -> -3352 | G27: =_xlfn.XLOOKUP($A27,Inputs!$A:$A,Inputs!G:G,,0) -> -2883 | H27: =_xlfn.XLOOKUP($A27,Inputs!$A:$A,Inputs!H:H,,0) -> -2601 | I27: =_xlfn.XLOOKUP($A27,Inputs!$A:$A,Inputs!I:I,,0) -> -2437 | J27: =_xlfn.XLOOKUP($A27,Inputs!$A:$A,Inputs!J:J,,0) -> -2254 | K27: =_xlfn.XLOOKUP($A27,Inputs!$A:$A,Inputs!K:K,,0) -> -1964 | L27: =_xlfn.XLOOKUP($A27,Inputs!$A:$A,Inputs!L:L,,0) -> -1608 | M27: =_xlfn.XLOOKUP($A27,Inputs!$A:$A,Inputs!M:M,,0) -> -1187
A28: Share buyback | B28: =_xlfn.XLOOKUP($A28,Inputs!$A:$A,Inputs!B:B,,0) -> -13328 | C28: =_xlfn.XLOOKUP($A28,Inputs!$A:$A,Inputs!C:C,,0) -> -4672 | D28: =_xlfn.XLOOKUP($A28,Inputs!$A:$A,Inputs!D:D,,0) -> -534 | E28: =_xlfn.XLOOKUP($A28,Inputs!$A:$A,Inputs!E:E,,0) -> -504 | F28: =_xlfn.XLOOKUP($A28,Inputs!$A:$A,Inputs!F:F,,0) -> -5320 | G28: =_xlfn.XLOOKUP($A28,Inputs!$A:$A,Inputs!G:G,,0) -> -5435 | H28: =_xlfn.XLOOKUP($A28,Inputs!$A:$A,Inputs!H:H,,0) -> -5352 | I28: =_xlfn.XLOOKUP($A28,Inputs!$A:$A,Inputs!I:I,,0) -> 0 | J28: =_xlfn.XLOOKUP($A28,Inputs!$A:$A,Inputs!J:J,,0) -> 0 | K28: =_xlfn.XLOOKUP($A28,Inputs!$A:$A,Inputs!K:K,,0) -> -2000 | L28: =_xlfn.XLOOKUP($A28,Inputs!$A:$A,Inputs!L:L,,0) -> -3000 | M28: =_xlfn.XLOOKUP($A28,Inputs!$A:$A,Inputs!M:M,,0) -> -2141
A29: Net Cash Flow | B29: =SUM(B26:B28) -> -22031 | C29: =SUM(C26:C28) -> -12233 | D29: =SUM(D26:D28) -> 1566 | E29: =SUM(E26:E28) -> -2553 | F29: =SUM(F26:F28) -> -8286 | G29: =SUM(G26:G28) -> -8191 | H29: =SUM(H26:H28) -> -6947 | I29: =SUM(I26:I28) -> -4052 | ... M29: =SUM(M26:M28) -> -1708
A30: FNP'' | B30: =+B29-(B58-C29) -> -139286 | C30: =+C29-(C58-D29) -> -115794 | D30: =+D29-(D58-E29) -> -111227 | E30: =+E29-(E58-F29) -> -118376 | F30: =+F29-(F58-G29) -> -123822 | G30: =+G29-(G58-H29) -> -74560 | H30: =+H29-(H58-I29) -> -66565 | I30: =+I29-(I58-J29) -> -53108 | ... M30: =+M29-(M58-N29) -> -39650
A31: FNP' | B31: =+B30+B33 -> -139298 | C31: =+C30+C33 -> -117168 | D31: =+D30+D33 -> -111460 | E31: =+E30+E33 -> -118746 | F31: =+F30+F33 -> -162041 | G31: =+G30+G33 -> -75092 | H31: =+H30+H33 -> -70494 | I31: =+I30+I33 -> -54894 | ... M31: =+M30+M33 -> -39650
A32: Net Capex | B32: =_xlfn.XLOOKUP($A32,Inputs!$A:$A,Inputs!B:B,,0) -> -10626 | C32: =_xlfn.XLOOKUP($A32,Inputs!$A:$A,Inputs!C:C,,0) -> -9174 | D32: =_xlfn.XLOOKUP($A32,Inputs!$A:$A,Inputs!D:D,,0) -> -9179 | E32: =_xlfn.XLOOKUP($A32,Inputs!$A:$A,Inputs!E:E,,0) -> -9953 | F32: =_xlfn.XLOOKUP($A32,Inputs!$A:$A,Inputs!F:F,,0) -> -9774 | G32: =_xlfn.XLOOKUP($A32,Inputs!$A:$A,Inputs!G:G,,0) -> -9550 | H32: =_xlfn.XLOOKUP($A32,Inputs!$A:$A,Inputs!H:H,,0) -> -9135 | I32: =_xlfn.XLOOKUP($A32,Inputs!$A:$A,Inputs!I:I,,0) -> -8499 | J32: =_xlfn.XLOOKUP($A32,Inputs!$A:$A,Inputs!J:J,,0) -> -7420 | K32: =_xlfn.XLOOKUP($A32,Inputs!$A:$A,Inputs!K:K,,0) -> -6596 | L32: =_xlfn.XLOOKUP($A32,Inputs!$A:$A,Inputs!L:L,,0) -> -5714 | M32: =_xlfn.XLOOKUP($A32,Inputs!$A:$A,Inputs!M:M,,0) -> -5307
A33: Investments & Acquisitions | B33: =_xlfn.XLOOKUP($A33,Inputs!$A:$A,Inputs!B:B,,0) -> -12 | C33: =_xlfn.XLOOKUP($A33,Inputs!$A:$A,Inputs!C:C,,0) -> -1374 | D33: =_xlfn.XLOOKUP($A33,Inputs!$A:$A,Inputs!D:D,,0) -> -233 | E33: =_xlfn.XLOOKUP($A33,Inputs!$A:$A,Inputs!E:E,,0) -> -370 | F33: =_xlfn.XLOOKUP($A33,Inputs!$A:$A,Inputs!F:F,,0) -> -38219 | G33: =_xlfn.XLOOKUP($A33,Inputs!$A:$A,Inputs!G:G,,0) -> -532 | H33: =_xlfn.XLOOKUP($A33,Inputs!$A:$A,Inputs!H:H,,0) -> -3929 | I33: =_xlfn.XLOOKUP($A33,Inputs!$A:$A,Inputs!I:I,,0) -> -1786 | J33: =_xlfn.XLOOKUP($A33,Inputs!$A:$A,Inputs!J:J,,0) -> -477 | K33: =_xlfn.XLOOKUP($A33,Inputs!$A:$A,Inputs!K:K,,0) -> -1904 | L33: =_xlfn.XLOOKUP($A33,Inputs!$A:$A,Inputs!L:L,,0) -> 0 | M33: =_xlfn.XLOOKUP($A33,Inputs!$A:$A,Inputs!M:M,,0) -> 0
A34: Capex + Investments | B34: =+B32+B33 -> -10638 | C34: =+C32+C33 -> -10548 | D34: =+D32+D33 -> -9412 | E34: =+E32+E33 -> -10323 | F34: =+F32+F33 -> -47993 | G34: =+G32+G33 -> -10082 | H34: =+H32+H33 -> -13064 | I34: =+I32+I33 -> -10285 | ... M34: =+M32+M33 -> -5307
A35: Dividends + Share Buyback | B35: =+B27+B28 -> -18069 | C35: =+C27+C28 -> -9204 | D35: =+D27+D28 -> -4674 | E35: =+E27+E28 -> -4239 | F35: =+F27+F28 -> -8672 | G35: =+G27+G28 -> -8318 | H35: =+H27+H28 -> -7953 | I35: =+I27+I28 -> -2437 | ... M35: =+M27+M28 -> -3328
A36: Payout Ratio | B36: =IFERROR(B35/B23,"-") -> -3.6688325 | C36: =IFERROR(C35/C23,"-") -> -0.66536543 | D36: =IFERROR(D35/D23,"-") -> -0.43678161 | E36: =IFERROR(E35/E23,"-") -> -0.31817158 | F36: =IFERROR(F35/F23,"-") -> -0.73107402 | G36: =IFERROR(G35/G23,"-") -> -0.36288282 | H36: =IFERROR(H35/H23,"-") -> -0.88092601 | I36: =IFERROR(I35/I23,"-") -> -0.28967075 | ... M36: =IFERROR(M35/M23,"-") -> -0.64533644
A38: Assets
A39: Cash & Eq. | B39: =_xlfn.XLOOKUP($A39,Inputs!$A:$A,Inputs!B:B,,0) -> 4749 | C39: =_xlfn.XLOOKUP($A39,Inputs!$A:$A,Inputs!C:C,,0) -> 8711 | D39: =_xlfn.XLOOKUP($A39,Inputs!$A:$A,Inputs!D:D,,0) -> 11740 | E39: =_xlfn.XLOOKUP($A39,Inputs!$A:$A,Inputs!E:E,,0) -> 5500 | F39: =_xlfn.XLOOKUP($A39,Inputs!$A:$A,Inputs!F:F,,0) -> 3814 | G39: =_xlfn.XLOOKUP($A39,Inputs!$A:$A,Inputs!G:G,,0) -> 3428 | H39: =_xlfn.XLOOKUP($A39,Inputs!$A:$A,Inputs!H:H,,0) -> 3301 | I39: =_xlfn.XLOOKUP($A39,Inputs!$A:$A,Inputs!I:I,,0) -> 2295 | J39: =_xlfn.XLOOKUP($A39,Inputs!$A:$A,Inputs!J:J,,0) -> 3910 | K39: =_xlfn.XLOOKUP($A39,Inputs!$A:$A,Inputs!K:K,,0) -> 1718 | L39: =_xlfn.XLOOKUP($A39,Inputs!$A:$A,Inputs!L:L,,0) -> 10951 | M39: =_xlfn.XLOOKUP($A39,Inputs!$A:$A,Inputs!M:M,,0) -> 1620
A40: Accounts Receivable | B40: =_xlfn.XLOOKUP($A40,Inputs!$A:$A,Inputs!B:B,,0) -> 12671 | C40: =_xlfn.XLOOKUP($A40,Inputs!$A:$A,Inputs!C:C,,0) -> 12008 | D40: =_xlfn.XLOOKUP($A40,Inputs!$A:$A,Inputs!D:D,,0) -> 11466 | E40: =_xlfn.XLOOKUP($A40,Inputs!$A:$A,Inputs!E:E,,0) -> 11292 | F40: =_xlfn.XLOOKUP($A40,Inputs!$A:$A,Inputs!F:F,,0) -> 11104 | G40: =_xlfn.XLOOKUP($A40,Inputs!$A:$A,Inputs!G:G,,0) -> 8834 | H40: =_xlfn.XLOOKUP($A40,Inputs!$A:$A,Inputs!H:H,,0) -> 8372 | I40: =_xlfn.XLOOKUP($A40,Inputs!$A:$A,Inputs!I:I,,0) -> 7369 | J40: =_xlfn.XLOOKUP($A40,Inputs!$A:$A,Inputs!J:J,,0) -> 6680 | K40: =_xlfn.XLOOKUP($A40,Inputs!$A:$A,Inputs!K:K,,0) -> 6751 | L40: =_xlfn.XLOOKUP($A40,Inputs!$A:$A,Inputs!L:L,,0) -> 5828 | M40: =_xlfn.XLOOKUP($A40,Inputs!$A:$A,Inputs!M:M,,0) -> 4854
A41: Inventory | B41: =_xlfn.XLOOKUP($A41,Inputs!$A:$A,Inputs!B:B,,0) -> 0 | C41: =_xlfn.XLOOKUP($A41,Inputs!$A:$A,Inputs!C:C,,0) -> 0 | D41: =_xlfn.XLOOKUP($A41,Inputs!$A:$A,Inputs!D:D,,0) -> 0 | E41: =_xlfn.XLOOKUP($A41,Inputs!$A:$A,Inputs!E:E,,0) -> 0 | F41: =_xlfn.XLOOKUP($A41,Inputs!$A:$A,Inputs!F:F,,0) -> 0 | G41: =_xlfn.XLOOKUP($A41,Inputs!$A:$A,Inputs!G:G,,0) -> 0 | H41: =_xlfn.XLOOKUP($A41,Inputs!$A:$A,Inputs!H:H,,0) -> 0 | I41: =_xlfn.XLOOKUP($A41,Inputs!$A:$A,Inputs!I:I,,0) -> 0 | J41: =_xlfn.XLOOKUP($A41,Inputs!$A:$A,Inputs!J:J,,0) -> 0 | K41: =_xlfn.XLOOKUP($A41,Inputs!$A:$A,Inputs!K:K,,0) -> 0 | L41: =_xlfn.XLOOKUP($A41,Inputs!$A:$A,Inputs!L:L,,0) -> 0 | M41: =_xlfn.XLOOKUP($A41,Inputs!$A:$A,Inputs!M:M,,0) -> 0
A42: Property, Plant and Equipment | B42: =_xlfn.XLOOKUP($A42,Inputs!$A:$A,Inputs!B:B,,0) -> 55485 | C42: =_xlfn.XLOOKUP($A42,Inputs!$A:$A,Inputs!C:C,,0) -> 54047 | D42: =_xlfn.XLOOKUP($A42,Inputs!$A:$A,Inputs!D:D,,0) -> 51995 | E42: =_xlfn.XLOOKUP($A42,Inputs!$A:$A,Inputs!E:E,,0) -> 48322 | F42: =_xlfn.XLOOKUP($A42,Inputs!$A:$A,Inputs!F:F,,0) -> 44437 | G42: =_xlfn.XLOOKUP($A42,Inputs!$A:$A,Inputs!G:G,,0) -> 38470 | H42: =_xlfn.XLOOKUP($A42,Inputs!$A:$A,Inputs!H:H,,0) -> 36253 | I42: =_xlfn.XLOOKUP($A42,Inputs!$A:$A,Inputs!I:I,,0) -> 33665 | J42: =_xlfn.XLOOKUP($A42,Inputs!$A:$A,Inputs!J:J,,0) -> 30953 | K42: =_xlfn.XLOOKUP($A42,Inputs!$A:$A,Inputs!K:K,,0) -> 29840 | L42: =_xlfn.XLOOKUP($A42,Inputs!$A:$A,Inputs!L:L,,0) -> 27232 | M42: =_xlfn.XLOOKUP($A42,Inputs!$A:$A,Inputs!M:M,,0) -> 27559
A43: Other Assets | B43: =_xlfn.XLOOKUP($A43,Inputs!$A:$A,Inputs!B:B,,0) -> 172952 | C43: =_xlfn.XLOOKUP($A43,Inputs!$A:$A,Inputs!C:C,,0) -> 188561 | D43: =_xlfn.XLOOKUP($A43,Inputs!$A:$A,Inputs!D:D,,0) -> 188878 | E43: =_xlfn.XLOOKUP($A43,Inputs!$A:$A,Inputs!E:E,,0) -> 188915 | F43: =_xlfn.XLOOKUP($A43,Inputs!$A:$A,Inputs!F:F,,0) -> 188294 | G43: =_xlfn.XLOOKUP($A43,Inputs!$A:$A,Inputs!G:G,,0) -> 133184 | H43: =_xlfn.XLOOKUP($A43,Inputs!$A:$A,Inputs!H:H,,0) -> 130198 | I43: =_xlfn.XLOOKUP($A43,Inputs!$A:$A,Inputs!I:I,,0) -> 122567 | J43: =_xlfn.XLOOKUP($A43,Inputs!$A:$A,Inputs!J:J,,0) -> 116624 | K43: =_xlfn.XLOOKUP($A43,Inputs!$A:$A,Inputs!K:K,,0) -> 119515 | L43: =_xlfn.XLOOKUP($A43,Inputs!$A:$A,Inputs!L:L,,0) -> 119796 | M43: =_xlfn.XLOOKUP($A43,Inputs!$A:$A,Inputs!M:M,,0) -> 118905
A44: Total Assets | B44: =_xlfn.XLOOKUP($A44,Inputs!$A:$A,Inputs!B:B,,0) -> 257275 | C44: =_xlfn.XLOOKUP($A44,Inputs!$A:$A,Inputs!C:C,,0) -> 275905 | D44: =_xlfn.XLOOKUP($A44,Inputs!$A:$A,Inputs!D:D,,0) -> 273869 | E44: =_xlfn.XLOOKUP($A44,Inputs!$A:$A,Inputs!E:E,,0) -> 263414 | F44: =_xlfn.XLOOKUP($A44,Inputs!$A:$A,Inputs!F:F,,0) -> 251684 | G44: =_xlfn.XLOOKUP($A44,Inputs!$A:$A,Inputs!G:G,,0) -> 187462 | H44: =_xlfn.XLOOKUP($A44,Inputs!$A:$A,Inputs!H:H,,0) -> 180500 | I44: =_xlfn.XLOOKUP($A44,Inputs!$A:$A,Inputs!I:I,,0) -> 166574 | J44: =_xlfn.XLOOKUP($A44,Inputs!$A:$A,Inputs!J:J,,0) -> 159186 | K44: =_xlfn.XLOOKUP($A44,Inputs!$A:$A,Inputs!K:K,,0) -> 158813 | L44: =_xlfn.XLOOKUP($A44,Inputs!$A:$A,Inputs!L:L,,0) -> 164971 | M44: =_xlfn.XLOOKUP($A44,Inputs!$A:$A,Inputs!M:M,,0) -> 157818
A47: Liabilities
A48: Current Liabilities | B48: =_xlfn.XLOOKUP($A48,Inputs!$A:$A,Inputs!B:B,,0) -> 27887 | C48: =_xlfn.XLOOKUP($A48,Inputs!$A:$A,Inputs!C:C,,0) -> 29348 | D48: =_xlfn.XLOOKUP($A48,Inputs!$A:$A,Inputs!D:D,,0) -> 28796 | E48: =_xlfn.XLOOKUP($A48,Inputs!$A:$A,Inputs!E:E,,0) -> 30292 | F48: =_xlfn.XLOOKUP($A48,Inputs!$A:$A,Inputs!F:F,,0) -> 27603 | G48: =_xlfn.XLOOKUP($A48,Inputs!$A:$A,Inputs!G:G,,0) -> 21993 | H48: =_xlfn.XLOOKUP($A48,Inputs!$A:$A,Inputs!H:H,,0) -> 21535 | I48: =_xlfn.XLOOKUP($A48,Inputs!$A:$A,Inputs!I:I,,0) -> 18178 | J48: =_xlfn.XLOOKUP($A48,Inputs!$A:$A,Inputs!J:J,,0) -> 17410 | K48: =_xlfn.XLOOKUP($A48,Inputs!$A:$A,Inputs!K:K,,0) -> 18912 | L48: =_xlfn.XLOOKUP($A48,Inputs!$A:$A,Inputs!L:L,,0) -> 16714 | M48: =_xlfn.XLOOKUP($A48,Inputs!$A:$A,Inputs!M:M,,0) -> 13241
A49: Short-Term Debt | B49: =_xlfn.XLOOKUP($A49,Inputs!$A:$A,Inputs!B:B,,0) -> 0 | C49: =_xlfn.XLOOKUP($A49,Inputs!$A:$A,Inputs!C:C,,0) -> 0 | D49: =_xlfn.XLOOKUP($A49,Inputs!$A:$A,Inputs!D:D,,0) -> 0 | E49: =_xlfn.XLOOKUP($A49,Inputs!$A:$A,Inputs!E:E,,0) -> 0 | F49: =_xlfn.XLOOKUP($A49,Inputs!$A:$A,Inputs!F:F,,0) -> 0 | G49: =_xlfn.XLOOKUP($A49,Inputs!$A:$A,Inputs!G:G,,0) -> 0 | H49: =_xlfn.XLOOKUP($A49,Inputs!$A:$A,Inputs!H:H,,0) -> 0 | I49: =_xlfn.XLOOKUP($A49,Inputs!$A:$A,Inputs!I:I,,0) -> 0 | J49: =_xlfn.XLOOKUP($A49,Inputs!$A:$A,Inputs!J:J,,0) -> 0 | K49: =_xlfn.XLOOKUP($A49,Inputs!$A:$A,Inputs!K:K,,0) -> 0 | L49: =_xlfn.XLOOKUP($A49,Inputs!$A:$A,Inputs!L:L,,0) -> 0 | M49: =_xlfn.XLOOKUP($A49,Inputs!$A:$A,Inputs!M:M,,0) -> 0
A50: Short-Term Leases | B50: =_xlfn.XLOOKUP($A50,Inputs!$A:$A,Inputs!B:B,,0) -> 675 | C50: =_xlfn.XLOOKUP($A50,Inputs!$A:$A,Inputs!C:C,,0) -> 766 | D50: =_xlfn.XLOOKUP($A50,Inputs!$A:$A,Inputs!D:D,,0) -> 718 | E50: =_xlfn.XLOOKUP($A50,Inputs!$A:$A,Inputs!E:E,,0) -> 715 | F50: =_xlfn.XLOOKUP($A50,Inputs!$A:$A,Inputs!F:F,,0) -> 0 | G50: =_xlfn.XLOOKUP($A50,Inputs!$A:$A,Inputs!G:G,,0) -> 0 | H50: =_xlfn.XLOOKUP($A50,Inputs!$A:$A,Inputs!H:H,,0) -> 0 | I50: =_xlfn.XLOOKUP($A50,Inputs!$A:$A,Inputs!I:I,,0) -> 0 | J50: =_xlfn.XLOOKUP($A50,Inputs!$A:$A,Inputs!J:J,,0) -> 0 | K50: =_xlfn.XLOOKUP($A50,Inputs!$A:$A,Inputs!K:K,,0) -> 0 | L50: =_xlfn.XLOOKUP($A50,Inputs!$A:$A,Inputs!L:L,,0) -> 0 | M50: =_xlfn.XLOOKUP($A50,Inputs!$A:$A,Inputs!M:M,,0) -> 0
A51: Other current liabilities | B51: =_xlfn.XLOOKUP($A51,Inputs!$A:$A,Inputs!B:B,,0) -> 14668 | C51: =_xlfn.XLOOKUP($A51,Inputs!$A:$A,Inputs!C:C,,0) -> 16127 | D51: =_xlfn.XLOOKUP($A51,Inputs!$A:$A,Inputs!D:D,,0) -> 16714 | E51: =_xlfn.XLOOKUP($A51,Inputs!$A:$A,Inputs!E:E,,0) -> 18751 | F51: =_xlfn.XLOOKUP($A51,Inputs!$A:$A,Inputs!F:F,,0) -> 19109 | G51: =_xlfn.XLOOKUP($A51,Inputs!$A:$A,Inputs!G:G,,0) -> 15085 | H51: =_xlfn.XLOOKUP($A51,Inputs!$A:$A,Inputs!H:H,,0) -> 14620 | I51: =_xlfn.XLOOKUP($A51,Inputs!$A:$A,Inputs!I:I,,0) -> 11963 | J51: =_xlfn.XLOOKUP($A51,Inputs!$A:$A,Inputs!J:J,,0) -> 11772 | K51: =_xlfn.XLOOKUP($A51,Inputs!$A:$A,Inputs!K:K,,0) -> 13384 | L51: =_xlfn.XLOOKUP($A51,Inputs!$A:$A,Inputs!L:L,,0) -> 10508 | M51: =_xlfn.XLOOKUP($A51,Inputs!$A:$A,Inputs!M:M,,0) -> 7536
A52: Non-current Liabilities | B52: =_xlfn.XLOOKUP($A52,Inputs!$A:$A,Inputs!B:B,,0) -> 148445 | C52: =_xlfn.XLOOKUP($A52,Inputs!$A:$A,Inputs!C:C,,0) -> 150465 | D52: =_xlfn.XLOOKUP($A52,Inputs!$A:$A,Inputs!D:D,,0) -> 154750 | E52: =_xlfn.XLOOKUP($A52,Inputs!$A:$A,Inputs!E:E,,0) -> 150396 | F52: =_xlfn.XLOOKUP($A52,Inputs!$A:$A,Inputs!F:F,,0) -> 152468 | G52: =_xlfn.XLOOKUP($A52,Inputs!$A:$A,Inputs!G:G,,0) -> 96853 | H52: =_xlfn.XLOOKUP($A52,Inputs!$A:$A,Inputs!H:H,,0) -> 105022 | I52: =_xlfn.XLOOKUP($A52,Inputs!$A:$A,Inputs!I:I,,0) -> 96127 | J52: =_xlfn.XLOOKUP($A52,Inputs!$A:$A,Inputs!J:J,,0) -> 89065 | K52: =_xlfn.XLOOKUP($A52,Inputs!$A:$A,Inputs!K:K,,0) -> 89207 | L52: =_xlfn.XLOOKUP($A52,Inputs!$A:$A,Inputs!L:L,,0) -> 98901 | M52: =_xlfn.XLOOKUP($A52,Inputs!$A:$A,Inputs!M:M,,0) -> 97303
A53: Long-Term Debt | B53: =_xlfn.XLOOKUP($A53,Inputs!$A:$A,Inputs!B:B,,0) -> 98240 | C53: =_xlfn.XLOOKUP($A53,Inputs!$A:$A,Inputs!C:C,,0) -> 97888 | D53: =_xlfn.XLOOKUP($A53,Inputs!$A:$A,Inputs!D:D,,0) -> 105782 | E53: =_xlfn.XLOOKUP($A53,Inputs!$A:$A,Inputs!E:E,,0) -> 102931 | F53: =_xlfn.XLOOKUP($A53,Inputs!$A:$A,Inputs!F:F,,0) -> 107345 | G53: =_xlfn.XLOOKUP($A53,Inputs!$A:$A,Inputs!G:G,,0) -> 59422 | H53: =_xlfn.XLOOKUP($A53,Inputs!$A:$A,Inputs!H:H,,0) -> 55566 | I53: =_xlfn.XLOOKUP($A53,Inputs!$A:$A,Inputs!I:I,,0) -> 48994 | J53: =_xlfn.XLOOKUP($A53,Inputs!$A:$A,Inputs!J:J,,0) -> 43864 | K53: =_xlfn.XLOOKUP($A53,Inputs!$A:$A,Inputs!K:K,,0) -> 44567 | L53: =_xlfn.XLOOKUP($A53,Inputs!$A:$A,Inputs!L:L,,0) -> 38082 | M53: =_xlfn.XLOOKUP($A53,Inputs!$A:$A,Inputs!M:M,,0) -> 37942
A54: Long-Term Leases | B54: =_xlfn.XLOOKUP($A54,Inputs!$A:$A,Inputs!B:B,,0) -> 6107 | C54: =_xlfn.XLOOKUP($A54,Inputs!$A:$A,Inputs!C:C,,0) -> 6473 | D54: =_xlfn.XLOOKUP($A54,Inputs!$A:$A,Inputs!D:D,,0) -> 3740 | E54: =_xlfn.XLOOKUP($A54,Inputs!$A:$A,Inputs!E:E,,0) -> 3891 | F54: =_xlfn.XLOOKUP($A54,Inputs!$A:$A,Inputs!F:F,,0) -> 0 | G54: =_xlfn.XLOOKUP($A54,Inputs!$A:$A,Inputs!G:G,,0) -> 0 | H54: =_xlfn.XLOOKUP($A54,Inputs!$A:$A,Inputs!H:H,,0) -> 0 | I54: =_xlfn.XLOOKUP($A54,Inputs!$A:$A,Inputs!I:I,,0) -> 0 | J54: =_xlfn.XLOOKUP($A54,Inputs!$A:$A,Inputs!J:J,,0) -> 0 | K54: =_xlfn.XLOOKUP($A54,Inputs!$A:$A,Inputs!K:K,,0) -> 0 | L54: =_xlfn.XLOOKUP($A54,Inputs!$A:$A,Inputs!L:L,,0) -> 0 | M54: =_xlfn.XLOOKUP($A54,Inputs!$A:$A,Inputs!M:M,,0) -> 0
A55: Other non-current liabilities | B55: =_xlfn.XLOOKUP($A55,Inputs!$A:$A,Inputs!B:B,,0) -> 44098 | C55: =_xlfn.XLOOKUP($A55,Inputs!$A:$A,Inputs!C:C,,0) -> 46104 | D55: =_xlfn.XLOOKUP($A55,Inputs!$A:$A,Inputs!D:D,,0) -> 45228 | E55: =_xlfn.XLOOKUP($A55,Inputs!$A:$A,Inputs!E:E,,0) -> 43574 | F55: =_xlfn.XLOOKUP($A55,Inputs!$A:$A,Inputs!F:F,,0) -> 45123 | G55: =_xlfn.XLOOKUP($A55,Inputs!$A:$A,Inputs!G:G,,0) -> 37431 | H55: =_xlfn.XLOOKUP($A55,Inputs!$A:$A,Inputs!H:H,,0) -> 49456 | I55: =_xlfn.XLOOKUP($A55,Inputs!$A:$A,Inputs!I:I,,0) -> 47133 | J55: =_xlfn.XLOOKUP($A55,Inputs!$A:$A,Inputs!J:J,,0) -> 45201 | K55: =_xlfn.XLOOKUP($A55,Inputs!$A:$A,Inputs!K:K,,0) -> 44640 | L55: =_xlfn.XLOOKUP($A55,Inputs!$A:$A,Inputs!L:L,,0) -> 60819 | M55: =_xlfn.XLOOKUP($A55,Inputs!$A:$A,Inputs!M:M,,0) -> 59361
A56: Total Liabilities | B56: =_xlfn.XLOOKUP($A56,Inputs!$A:$A,Inputs!B:B,,0) -> 176332 | C56: =_xlfn.XLOOKUP($A56,Inputs!$A:$A,Inputs!C:C,,0) -> 179813 | D56: =_xlfn.XLOOKUP($A56,Inputs!$A:$A,Inputs!D:D,,0) -> 183546 | E56: =_xlfn.XLOOKUP($A56,Inputs!$A:$A,Inputs!E:E,,0) -> 180688 | F56: =_xlfn.XLOOKUP($A56,Inputs!$A:$A,Inputs!F:F,,0) -> 180071 | G56: =_xlfn.XLOOKUP($A56,Inputs!$A:$A,Inputs!G:G,,0) -> 118846 | H56: =_xlfn.XLOOKUP($A56,Inputs!$A:$A,Inputs!H:H,,0) -> 126557 | I56: =_xlfn.XLOOKUP($A56,Inputs!$A:$A,Inputs!I:I,,0) -> 114305 | J56: =_xlfn.XLOOKUP($A56,Inputs!$A:$A,Inputs!J:J,,0) -> 106475 | K56: =_xlfn.XLOOKUP($A56,Inputs!$A:$A,Inputs!K:K,,0) -> 108119 | L56: =_xlfn.XLOOKUP($A56,Inputs!$A:$A,Inputs!L:L,,0) -> 115615 | M56: =_xlfn.XLOOKUP($A56,Inputs!$A:$A,Inputs!M:M,,0) -> 110544
A58: Total Debt | B58: =B49+B53+B50+B54 -> 105022 | C58: =C49+C53+C50+C54 -> 105127 | D58: =D49+D53+D50+D54 -> 110240 | E58: =E49+E53+E50+E54 -> 107537 | F58: =F49+F53+F50+F54 -> 107345 | G58: =G49+G53+G50+G54 -> 59422 | H58: =H49+H53+H50+H54 -> 55566 | I58: =I49+I53+I50+I54 -> 48994 | ... M58: =M49+M53+M50+M54 -> 37942
A59: Debt/Assets | B59: =IFERROR(B58/B44,"-") -> 0.40820911 | C59: =IFERROR(C58/C44,"-") -> 0.38102608 | D59: =IFERROR(D58/D44,"-") -> 0.40252822 | E59: =IFERROR(E58/E44,"-") -> 0.4082433 | F59: =IFERROR(F58/F44,"-") -> 0.42650705 | G59: =IFERROR(G58/G44,"-") -> 0.31698157 | H59: =IFERROR(H58/H44,"-") -> 0.30784488 | I59: =IFERROR(I58/I44,"-") -> 0.29412753 | ... M59: =IFERROR(M58/M44,"-") -> 0.24041618
A60: Net Debt | B60: =B58-B39 -> 100273 | C60: =C58-C39 -> 96416 | D60: =D58-D39 -> 98500 | E60: =E58-E39 -> 102037 | F60: =F58-F39 -> 103531 | G60: =G58-G39 -> 55994 | H60: =H58-H39 -> 52265 | I60: =I58-I39 -> 46699 | ... M60: =M58-M39 -> 36322
A62: Minority Interest | B62: =_xlfn.XLOOKUP($A62,Inputs!$A:$A,Inputs!B:B,,0) -> 1095 | C62: =_xlfn.XLOOKUP($A62,Inputs!$A:$A,Inputs!C:C,,0) -> 1917 | D62: =_xlfn.XLOOKUP($A62,Inputs!$A:$A,Inputs!D:D,,0) -> 2695 | E62: =_xlfn.XLOOKUP($A62,Inputs!$A:$A,Inputs!E:E,,0) -> 2520 | F62: =_xlfn.XLOOKUP($A62,Inputs!$A:$A,Inputs!F:F,,0) -> 2205 | G62: =_xlfn.XLOOKUP($A62,Inputs!$A:$A,Inputs!G:G,,0) -> 2200 | H62: =_xlfn.XLOOKUP($A62,Inputs!$A:$A,Inputs!H:H,,0) -> 3677 | I62: =_xlfn.XLOOKUP($A62,Inputs!$A:$A,Inputs!I:I,,0) -> 2930 | J62: =_xlfn.XLOOKUP($A62,Inputs!$A:$A,Inputs!J:J,,0) -> 1423 | K62: =_xlfn.XLOOKUP($A62,Inputs!$A:$A,Inputs!K:K,,0) -> 1321 | L62: =_xlfn.XLOOKUP($A62,Inputs!$A:$A,Inputs!L:L,,0) -> 17438 | M62: =_xlfn.XLOOKUP($A62,Inputs!$A:$A,Inputs!M:M,,0) -> 16395
A64: Shareholder's Equity | B64: =_xlfn.XLOOKUP($A64,Inputs!$A:$A,Inputs!B:B,,0) -> 79848 | C64: =_xlfn.XLOOKUP($A64,Inputs!$A:$A,Inputs!C:C,,0) -> 94175 | D64: =_xlfn.XLOOKUP($A64,Inputs!$A:$A,Inputs!D:D,,0) -> 87628 | E64: =_xlfn.XLOOKUP($A64,Inputs!$A:$A,Inputs!E:E,,0) -> 80206 | F64: =_xlfn.XLOOKUP($A64,Inputs!$A:$A,Inputs!F:F,,0) -> 69408 | G64: =_xlfn.XLOOKUP($A64,Inputs!$A:$A,Inputs!G:G,,0) -> 66416 | H64: =_xlfn.XLOOKUP($A64,Inputs!$A:$A,Inputs!H:H,,0) -> 50266 | I64: =_xlfn.XLOOKUP($A64,Inputs!$A:$A,Inputs!I:I,,0) -> 49339 | J64: =_xlfn.XLOOKUP($A64,Inputs!$A:$A,Inputs!J:J,,0) -> 51288 | K64: =_xlfn.XLOOKUP($A64,Inputs!$A:$A,Inputs!K:K,,0) -> 49373 | L64: =_xlfn.XLOOKUP($A64,Inputs!$A:$A,Inputs!L:L,,0) -> 31918 | M64: =_xlfn.XLOOKUP($A64,Inputs!$A:$A,Inputs!M:M,,0) -> 30879
A66: Cash Flow
A67: Operating CF | B67: =_xlfn.XLOOKUP($A67,Inputs!$A:$A,Inputs!B:B,,0) -> 26413 | C67: =_xlfn.XLOOKUP($A67,Inputs!$A:$A,Inputs!C:C,,0) -> 29146 | D67: =_xlfn.XLOOKUP($A67,Inputs!$A:$A,Inputs!D:D,,0) -> 24737 | E67: =_xlfn.XLOOKUP($A67,Inputs!$A:$A,Inputs!E:E,,0) -> 25697 | F67: =_xlfn.XLOOKUP($A67,Inputs!$A:$A,Inputs!F:F,,0) -> 24297 | G67: =_xlfn.XLOOKUP($A67,Inputs!$A:$A,Inputs!G:G,,0) -> 21261 | H67: =_xlfn.XLOOKUP($A67,Inputs!$A:$A,Inputs!H:H,,0) -> 19691 | I67: =_xlfn.XLOOKUP($A67,Inputs!$A:$A,Inputs!I:I,,0) -> 18778 | J67: =_xlfn.XLOOKUP($A67,Inputs!$A:$A,Inputs!J:J,,0) -> 16945 | K67: =_xlfn.XLOOKUP($A67,Inputs!$A:$A,Inputs!K:K,,0) -> 14160 | L67: =_xlfn.XLOOKUP($A67,Inputs!$A:$A,Inputs!L:L,,0) -> 14854 | M67: =_xlfn.XLOOKUP($A67,Inputs!$A:$A,Inputs!M:M,,0) -> 14345
A68: Investing CF | B68: =_xlfn.XLOOKUP($A68,Inputs!$A:$A,Inputs!B:B,,0) -> -14140 | C68: =_xlfn.XLOOKUP($A68,Inputs!$A:$A,Inputs!C:C,,0) -> -13446 | D68: =_xlfn.XLOOKUP($A68,Inputs!$A:$A,Inputs!D:D,,0) -> -12047 | E68: =_xlfn.XLOOKUP($A68,Inputs!$A:$A,Inputs!E:E,,0) -> -14841 | F68: =_xlfn.XLOOKUP($A68,Inputs!$A:$A,Inputs!F:F,,0) -> -50854 | G68: =_xlfn.XLOOKUP($A68,Inputs!$A:$A,Inputs!G:G,,0) -> -13533 | H68: =_xlfn.XLOOKUP($A68,Inputs!$A:$A,Inputs!H:H,,0) -> -18265 | I68: =_xlfn.XLOOKUP($A68,Inputs!$A:$A,Inputs!I:I,,0) -> -11964 | J68: =_xlfn.XLOOKUP($A68,Inputs!$A:$A,Inputs!J:J,,0) -> -8733 | K68: =_xlfn.XLOOKUP($A68,Inputs!$A:$A,Inputs!K:K,,0) -> -9514 | L68: =_xlfn.XLOOKUP($A68,Inputs!$A:$A,Inputs!L:L,,0) -> -1486 | M68: =_xlfn.XLOOKUP($A68,Inputs!$A:$A,Inputs!M:M,,0) -> -12508
A69: Net Capex | B69: =_xlfn.XLOOKUP($A69,Inputs!$A:$A,Inputs!B:B,,0) -> -10626 | C69: =_xlfn.XLOOKUP($A69,Inputs!$A:$A,Inputs!C:C,,0) -> -9174 | D69: =_xlfn.XLOOKUP($A69,Inputs!$A:$A,Inputs!D:D,,0) -> -9179 | E69: =_xlfn.XLOOKUP($A69,Inputs!$A:$A,Inputs!E:E,,0) -> -9953 | F69: =_xlfn.XLOOKUP($A69,Inputs!$A:$A,Inputs!F:F,,0) -> -9774 | G69: =_xlfn.XLOOKUP($A69,Inputs!$A:$A,Inputs!G:G,,0) -> -9550 | H69: =_xlfn.XLOOKUP($A69,Inputs!$A:$A,Inputs!H:H,,0) -> -9135 | I69: =_xlfn.XLOOKUP($A69,Inputs!$A:$A,Inputs!I:I,,0) -> -8499 | J69: =_xlfn.XLOOKUP($A69,Inputs!$A:$A,Inputs!J:J,,0) -> -7420 | K69: =_xlfn.XLOOKUP($A69,Inputs!$A:$A,Inputs!K:K,,0) -> -6596 | L69: =_xlfn.XLOOKUP($A69,Inputs!$A:$A,Inputs!L:L,,0) -> -5714 | M69: =_xlfn.XLOOKUP($A69,Inputs!$A:$A,Inputs!M:M,,0) -> -5307
A70: Investments & Acquisitions | B70: =_xlfn.XLOOKUP($A70,Inputs!$A:$A,Inputs!B:B,,0) -> -12 | C70: =_xlfn.XLOOKUP($A70,Inputs!$A:$A,Inputs!C:C,,0) -> -1374 | D70: =_xlfn.XLOOKUP($A70,Inputs!$A:$A,Inputs!D:D,,0) -> -233 | E70: =_xlfn.XLOOKUP($A70,Inputs!$A:$A,Inputs!E:E,,0) -> -370 | F70: =_xlfn.XLOOKUP($A70,Inputs!$A:$A,Inputs!F:F,,0) -> -38219 | G70: =_xlfn.XLOOKUP($A70,Inputs!$A:$A,Inputs!G:G,,0) -> -532 | H70: =_xlfn.XLOOKUP($A70,Inputs!$A:$A,Inputs!H:H,,0) -> -3929 | I70: =_xlfn.XLOOKUP($A70,Inputs!$A:$A,Inputs!I:I,,0) -> -1786 | J70: =_xlfn.XLOOKUP($A70,Inputs!$A:$A,Inputs!J:J,,0) -> -477 | K70: =_xlfn.XLOOKUP($A70,Inputs!$A:$A,Inputs!K:K,,0) -> -1904 | L70: =_xlfn.XLOOKUP($A70,Inputs!$A:$A,Inputs!L:L,,0) -> 0 | M70: =_xlfn.XLOOKUP($A70,Inputs!$A:$A,Inputs!M:M,,0) -> 0
A71: Financing CF | B71: =_xlfn.XLOOKUP($A71,Inputs!$A:$A,Inputs!B:B,,0) -> -16184 | C71: =_xlfn.XLOOKUP($A71,Inputs!$A:$A,Inputs!C:C,,0) -> -18618 | D71: =_xlfn.XLOOKUP($A71,Inputs!$A:$A,Inputs!D:D,,0) -> -6513 | E71: =_xlfn.XLOOKUP($A71,Inputs!$A:$A,Inputs!E:E,,0) -> -9181 | F71: =_xlfn.XLOOKUP($A71,Inputs!$A:$A,Inputs!F:F,,0) -> 27140 | G71: =_xlfn.XLOOKUP($A71,Inputs!$A:$A,Inputs!G:G,,0) -> -7572 | H71: =_xlfn.XLOOKUP($A71,Inputs!$A:$A,Inputs!H:H,,0) -> -434 | I71: =_xlfn.XLOOKUP($A71,Inputs!$A:$A,Inputs!I:I,,0) -> -8429 | J71: =_xlfn.XLOOKUP($A71,Inputs!$A:$A,Inputs!J:J,,0) -> -6020 | K71: =_xlfn.XLOOKUP($A71,Inputs!$A:$A,Inputs!K:K,,0) -> -13879 | L71: =_xlfn.XLOOKUP($A71,Inputs!$A:$A,Inputs!L:L,,0) -> -4037 | M71: =_xlfn.XLOOKUP($A71,Inputs!$A:$A,Inputs!M:M,,0) -> -6201
A72: Dividends | B72: =_xlfn.XLOOKUP($A72,Inputs!$A:$A,Inputs!B:B,,0) -> -4741 | C72: =_xlfn.XLOOKUP($A72,Inputs!$A:$A,Inputs!C:C,,0) -> -4532 | D72: =_xlfn.XLOOKUP($A72,Inputs!$A:$A,Inputs!D:D,,0) -> -4140 | E72: =_xlfn.XLOOKUP($A72,Inputs!$A:$A,Inputs!E:E,,0) -> -3735 | F72: =_xlfn.XLOOKUP($A72,Inputs!$A:$A,Inputs!F:F,,0) -> -3352 | G72: =_xlfn.XLOOKUP($A72,Inputs!$A:$A,Inputs!G:G,,0) -> -2883 | H72: =_xlfn.XLOOKUP($A72,Inputs!$A:$A,Inputs!H:H,,0) -> -2601 | I72: =_xlfn.XLOOKUP($A72,Inputs!$A:$A,Inputs!I:I,,0) -> -2437 | J72: =_xlfn.XLOOKUP($A72,Inputs!$A:$A,Inputs!J:J,,0) -> -2254 | K72: =_xlfn.XLOOKUP($A72,Inputs!$A:$A,Inputs!K:K,,0) -> -1964 | L72: =_xlfn.XLOOKUP($A72,Inputs!$A:$A,Inputs!L:L,,0) -> -1608 | M72: =_xlfn.XLOOKUP($A72,Inputs!$A:$A,Inputs!M:M,,0) -> -1187
A73: Share buyback | B73: =_xlfn.XLOOKUP($A73,Inputs!$A:$A,Inputs!B:B,,0) -> -13328 | C73: =_xlfn.XLOOKUP($A73,Inputs!$A:$A,Inputs!C:C,,0) -> -4672 | D73: =_xlfn.XLOOKUP($A73,Inputs!$A:$A,Inputs!D:D,,0) -> -534 | E73: =_xlfn.XLOOKUP($A73,Inputs!$A:$A,Inputs!E:E,,0) -> -504 | F73: =_xlfn.XLOOKUP($A73,Inputs!$A:$A,Inputs!F:F,,0) -> -5320 | G73: =_xlfn.XLOOKUP($A73,Inputs!$A:$A,Inputs!G:G,,0) -> -5435 | H73: =_xlfn.XLOOKUP($A73,Inputs!$A:$A,Inputs!H:H,,0) -> -5352 | I73: =_xlfn.XLOOKUP($A73,Inputs!$A:$A,Inputs!I:I,,0) -> 0 | J73: =_xlfn.XLOOKUP($A73,Inputs!$A:$A,Inputs!J:J,,0) -> 0 | K73: =_xlfn.XLOOKUP($A73,Inputs!$A:$A,Inputs!K:K,,0) -> -2000 | L73: =_xlfn.XLOOKUP($A73,Inputs!$A:$A,Inputs!L:L,,0) -> -3000 | M73: =_xlfn.XLOOKUP($A73,Inputs!$A:$A,Inputs!M:M,,0) -> -2141
A74: FX | B74: =_xlfn.XLOOKUP($A74,Inputs!$A:$A,Inputs!B:B,,0) -> -86 | C74: =_xlfn.XLOOKUP($A74,Inputs!$A:$A,Inputs!C:C,,0) -> -71 | D74: =_xlfn.XLOOKUP($A74,Inputs!$A:$A,Inputs!D:D,,0) -> 2 | E74: =_xlfn.XLOOKUP($A74,Inputs!$A:$A,Inputs!E:E,,0) -> 5 | F74: =_xlfn.XLOOKUP($A74,Inputs!$A:$A,Inputs!F:F,,0) -> -245 | G74: =_xlfn.XLOOKUP($A74,Inputs!$A:$A,Inputs!G:G,,0) -> 0 | H74: =_xlfn.XLOOKUP($A74,Inputs!$A:$A,Inputs!H:H,,0) -> 0 | I74: =_xlfn.XLOOKUP($A74,Inputs!$A:$A,Inputs!I:I,,0) -> 0 | J74: =_xlfn.XLOOKUP($A74,Inputs!$A:$A,Inputs!J:J,,0) -> 0 | K74: =_xlfn.XLOOKUP($A74,Inputs!$A:$A,Inputs!K:K,,0) -> 0 | L74: =_xlfn.XLOOKUP($A74,Inputs!$A:$A,Inputs!L:L,,0) -> 0 | M74: =_xlfn.XLOOKUP($A74,Inputs!$A:$A,Inputs!M:M,,0) -> 0
A75: Changes in cash | B75: =_xlfn.XLOOKUP($A75,Inputs!$A:$A,Inputs!B:B,,0) -> -3997 | C75: =_xlfn.XLOOKUP($A75,Inputs!$A:$A,Inputs!C:C,,0) -> -2989 | D75: =_xlfn.XLOOKUP($A75,Inputs!$A:$A,Inputs!D:D,,0) -> 6179 | E75: =_xlfn.XLOOKUP($A75,Inputs!$A:$A,Inputs!E:E,,0) -> 1680 | F75: =_xlfn.XLOOKUP($A75,Inputs!$A:$A,Inputs!F:F,,0) -> 338 | G75: =_xlfn.XLOOKUP($A75,Inputs!$A:$A,Inputs!G:G,,0) -> 156 | H75: =_xlfn.XLOOKUP($A75,Inputs!$A:$A,Inputs!H:H,,0) -> 992 | I75: =_xlfn.XLOOKUP($A75,Inputs!$A:$A,Inputs!I:I,,0) -> -1615 | J75: =_xlfn.XLOOKUP($A75,Inputs!$A:$A,Inputs!J:J,,0) -> 2192 | K75: =_xlfn.XLOOKUP($A75,Inputs!$A:$A,Inputs!K:K,,0) -> -9233 | L75: =_xlfn.XLOOKUP($A75,Inputs!$A:$A,Inputs!L:L,,0) -> 9331 | M75: =_xlfn.XLOOKUP($A75,Inputs!$A:$A,Inputs!M:M,,0) -> -4364
A77: Other Data
A78: Number of employees | B78: =_xlfn.XLOOKUP($A78,Inputs!$A:$A,Inputs!B:B,,0) -> #N/A | C78: =_xlfn.XLOOKUP($A78,Inputs!$A:$A,Inputs!C:C,,0) -> #N/A | D78: =_xlfn.XLOOKUP($A78,Inputs!$A:$A,Inputs!D:D,,0) -> #N/A | E78: =_xlfn.XLOOKUP($A78,Inputs!$A:$A,Inputs!E:E,,0) -> #N/A | F78: =_xlfn.XLOOKUP($A78,Inputs!$A:$A,Inputs!F:F,,0) -> #N/A | G78: =_xlfn.XLOOKUP($A78,Inputs!$A:$A,Inputs!G:G,,0) -> #N/A | H78: =_xlfn.XLOOKUP($A78,Inputs!$A:$A,Inputs!H:H,,0) -> #N/A | I78: =_xlfn.XLOOKUP($A78,Inputs!$A:$A,Inputs!I:I,,0) -> #N/A | J78: =_xlfn.XLOOKUP($A78,Inputs!$A:$A,Inputs!J:J,,0) -> #N/A | K78: =_xlfn.XLOOKUP($A78,Inputs!$A:$A,Inputs!K:K,,0) -> #N/A | L78: =_xlfn.XLOOKUP($A78,Inputs!$A:$A,Inputs!L:L,,0) -> #N/A | M78: =_xlfn.XLOOKUP($A78,Inputs!$A:$A,Inputs!M:M,,0) -> #N/A
A79: Shares Outstanding | B79: =_xlfn.XLOOKUP($A79,Inputs!$A:$A,Inputs!B:B,,0) -> #N/A | C79: =_xlfn.XLOOKUP($A79,Inputs!$A:$A,Inputs!C:C,,0) -> #N/A | D79: =_xlfn.XLOOKUP($A79,Inputs!$A:$A,Inputs!D:D,,0) -> #N/A | E79: =_xlfn.XLOOKUP($A79,Inputs!$A:$A,Inputs!E:E,,0) -> #N/A | F79: =_xlfn.XLOOKUP($A79,Inputs!$A:$A,Inputs!F:F,,0) -> #N/A | G79: =_xlfn.XLOOKUP($A79,Inputs!$A:$A,Inputs!G:G,,0) -> #N/A | H79: =_xlfn.XLOOKUP($A79,Inputs!$A:$A,Inputs!H:H,,0) -> #N/A | I79: =_xlfn.XLOOKUP($A79,Inputs!$A:$A,Inputs!I:I,,0) -> #N/A | J79: =_xlfn.XLOOKUP($A79,Inputs!$A:$A,Inputs!J:J,,0) -> #N/A | K79: =_xlfn.XLOOKUP($A79,Inputs!$A:$A,Inputs!K:K,,0) -> #N/A | L79: =_xlfn.XLOOKUP($A79,Inputs!$A:$A,Inputs!L:L,,0) -> #N/A | M79: =_xlfn.XLOOKUP($A79,Inputs!$A:$A,Inputs!M:M,,0) -> #N/A
A80: Float | B80: =_xlfn.XLOOKUP($A80,Inputs!$A:$A,Inputs!B:B,,0) -> 0.99 | C80: =_xlfn.XLOOKUP($A80,Inputs!$A:$A,Inputs!C:C,,0) -> Yahoo finance | D80: =_xlfn.XLOOKUP($A80,Inputs!$A:$A,Inputs!D:D,,0) -> 0 | E80: =_xlfn.XLOOKUP($A80,Inputs!$A:$A,Inputs!E:E,,0) -> 0 | F80: =_xlfn.XLOOKUP($A80,Inputs!$A:$A,Inputs!F:F,,0) -> 0 | G80: =_xlfn.XLOOKUP($A80,Inputs!$A:$A,Inputs!G:G,,0) -> 0 | H80: =_xlfn.XLOOKUP($A80,Inputs!$A:$A,Inputs!H:H,,0) -> 0 | I80: =_xlfn.XLOOKUP($A80,Inputs!$A:$A,Inputs!I:I,,0) -> 0 | J80: =_xlfn.XLOOKUP($A80,Inputs!$A:$A,Inputs!J:J,,0) -> 0 | K80: =_xlfn.XLOOKUP($A80,Inputs!$A:$A,Inputs!K:K,,0) -> 0 | L80: =_xlfn.XLOOKUP($A80,Inputs!$A:$A,Inputs!L:L,,0) -> 0 | M80: =_xlfn.XLOOKUP($A80,Inputs!$A:$A,Inputs!M:M,,0) -> 0
A81: Insiders Own | B81: =_xlfn.XLOOKUP($A81,Inputs!$A:$A,Inputs!B:B,,0) -> 0.0074 | C81: =_xlfn.XLOOKUP($A81,Inputs!$A:$A,Inputs!C:C,,0) -> Yahoo finance | D81: =_xlfn.XLOOKUP($A81,Inputs!$A:$A,Inputs!D:D,,0) -> 0 | E81: =_xlfn.XLOOKUP($A81,Inputs!$A:$A,Inputs!E:E,,0) -> 0 | F81: =_xlfn.XLOOKUP($A81,Inputs!$A:$A,Inputs!F:F,,0) -> 0 | G81: =_xlfn.XLOOKUP($A81,Inputs!$A:$A,Inputs!G:G,,0) -> 0 | H81: =_xlfn.XLOOKUP($A81,Inputs!$A:$A,Inputs!H:H,,0) -> 0 | I81: =_xlfn.XLOOKUP($A81,Inputs!$A:$A,Inputs!I:I,,0) -> 0 | J81: =_xlfn.XLOOKUP($A81,Inputs!$A:$A,Inputs!J:J,,0) -> 0 | K81: =_xlfn.XLOOKUP($A81,Inputs!$A:$A,Inputs!K:K,,0) -> 0 | L81: =_xlfn.XLOOKUP($A81,Inputs!$A:$A,Inputs!L:L,,0) -> 0 | M81: =_xlfn.XLOOKUP($A81,Inputs!$A:$A,Inputs!M:M,,0) -> 0
A82: Fitch/ S&P Rating | B82: =_xlfn.XLOOKUP($A82,Inputs!$A:$A,Inputs!B:B,,0) -> A- | C82: =_xlfn.XLOOKUP($A82,Inputs!$A:$A,Inputs!C:C,,0) -> 10-K | D82: =_xlfn.XLOOKUP($A82,Inputs!$A:$A,Inputs!D:D,,0) -> 0 | E82: =_xlfn.XLOOKUP($A82,Inputs!$A:$A,Inputs!E:E,,0) -> 0 | F82: =_xlfn.XLOOKUP($A82,Inputs!$A:$A,Inputs!F:F,,0) -> 0 | G82: =_xlfn.XLOOKUP($A82,Inputs!$A:$A,Inputs!G:G,,0) -> 0 | H82: =_xlfn.XLOOKUP($A82,Inputs!$A:$A,Inputs!H:H,,0) -> 0 | I82: =_xlfn.XLOOKUP($A82,Inputs!$A:$A,Inputs!I:I,,0) -> 0 | J82: =_xlfn.XLOOKUP($A82,Inputs!$A:$A,Inputs!J:J,,0) -> 0 | K82: =_xlfn.XLOOKUP($A82,Inputs!$A:$A,Inputs!K:K,,0) -> 0 | L82: =_xlfn.XLOOKUP($A82,Inputs!$A:$A,Inputs!L:L,,0) -> 0 | M82: =_xlfn.XLOOKUP($A82,Inputs!$A:$A,Inputs!M:M,,0) -> 0
A83: Dividend Yield | B83: =_xlfn.XLOOKUP($A83,Inputs!$A:$A,Inputs!B:B,,0) -> #N/A | C83: =_xlfn.XLOOKUP($A83,Inputs!$A:$A,Inputs!C:C,,0) -> #N/A | D83: =_xlfn.XLOOKUP($A83,Inputs!$A:$A,Inputs!D:D,,0) -> #N/A | E83: =_xlfn.XLOOKUP($A83,Inputs!$A:$A,Inputs!E:E,,0) -> #N/A | F83: =_xlfn.XLOOKUP($A83,Inputs!$A:$A,Inputs!F:F,,0) -> #N/A | G83: =_xlfn.XLOOKUP($A83,Inputs!$A:$A,Inputs!G:G,,0) -> #N/A | H83: =_xlfn.XLOOKUP($A83,Inputs!$A:$A,Inputs!H:H,,0) -> #N/A | I83: =_xlfn.XLOOKUP($A83,Inputs!$A:$A,Inputs!I:I,,0) -> #N/A | J83: =_xlfn.XLOOKUP($A83,Inputs!$A:$A,Inputs!J:J,,0) -> #N/A | K83: =_xlfn.XLOOKUP($A83,Inputs!$A:$A,Inputs!K:K,,0) -> #N/A | L83: =_xlfn.XLOOKUP($A83,Inputs!$A:$A,Inputs!L:L,,0) -> #N/A | M83: =_xlfn.XLOOKUP($A83,Inputs!$A:$A,Inputs!M:M,,0) -> #N/A
A84: Daily Volume in Millions of USD | B84: =_xlfn.XLOOKUP($A84,Inputs!$A:$A,Inputs!B:B,,0) -> 0 | C84: =_xlfn.XLOOKUP($A84,Inputs!$A:$A,Inputs!C:C,,0) -> Yahoo Finance | D84: =_xlfn.XLOOKUP($A84,Inputs!$A:$A,Inputs!D:D,,0) -> 0 | E84: =_xlfn.XLOOKUP($A84,Inputs!$A:$A,Inputs!E:E,,0) -> 0 | F84: =_xlfn.XLOOKUP($A84,Inputs!$A:$A,Inputs!F:F,,0) -> 0 | G84: =_xlfn.XLOOKUP($A84,Inputs!$A:$A,Inputs!G:G,,0) -> 0 | H84: =_xlfn.XLOOKUP($A84,Inputs!$A:$A,Inputs!H:H,,0) -> 0 | I84: =_xlfn.XLOOKUP($A84,Inputs!$A:$A,Inputs!I:I,,0) -> 0 | J84: =_xlfn.XLOOKUP($A84,Inputs!$A:$A,Inputs!J:J,,0) -> 0 | K84: =_xlfn.XLOOKUP($A84,Inputs!$A:$A,Inputs!K:K,,0) -> 0 | L84: =_xlfn.XLOOKUP($A84,Inputs!$A:$A,Inputs!L:L,,0) -> 0 | M84: =_xlfn.XLOOKUP($A84,Inputs!$A:$A,Inputs!M:M,,0) -> 0
B86: 2020 | C86: 2021 | D86: 2022
A87: Short % of Float | B87: 0 | C87: 0 | D87: 0
A88: EPS | B88: 0 | C88: 0 | D88: 0
A90: Corporate Bonds 3, 5 Y 10 | B90: Average Price | C90: Moody's | D90: YTM | E90: DIVISA
B91: =VLOOKUP($A91,Inputs!$A$5:$M$98,MATCH(B$4,Inputs!$B$5:$M$5,0)+1,FALSE) -> #N/A | C91: =VLOOKUP($A91,Inputs!$A$5:$M$98,MATCH(C$4,Inputs!$B$5:$M$5,0)+1,FALSE) -> #N/A | D91: =VLOOKUP($A91,Inputs!$A$5:$M$98,MATCH(D$4,Inputs!$B$5:$M$5,0)+1,FALSE) -> #N/A | E91: =VLOOKUP($A91,Inputs!$A$5:$M$98,MATCH(E$4,Inputs!$B$5:$M$5,0)+1,FALSE) -> #N/A

Sheet Inputs
G2: Figures in Millions of USD
G3: Company | H3: #VALUE!
D4: Report in millions
A5: RESULTS | B5: =OP!J19 -> 2022 | C5: =B5-1 -> 2021 | D5: =C5-1 -> 2020 | E5: =D5-1 -> 2019 | F5: =E5-1 -> 2018 | G5: =F5-1 -> 2017 | H5: =G5-1 -> 2016 | I5: =H5-1 -> 2015 | J5: =I5-1 -> 2014 | ... M5: =L5-1 -> 2011 | Q5: Hoja | R5: Nombre campo Bloomberg | T5: Cambio de signo | Z5: 2016 | AA5: 2015 | AB5: 2014 | AC5: 2013 | AD5: 2012 | AE5: 2011 | AF5: 2010 | AG5: 2009
A6: Net Sales | B6: 121427 | C6: 116385 | D6: 103564 | E6: 108942 | F6: 94507 | G6: 85029 | H6: 80736 | I6: 74510 | J6: 68775 | K6: 64657 | L6: 62570 | M6: 55842 | N6: Income Statement | O6: Sales | Q6: Ingreso | R6: Ingreso | Z6: 38537 | AA6: 47011 | AB6: 55184 | AC6: 55656 | AD6: 65875 | AE6: 60138 | AF6: 42588 | AG6: 32396
A7: Gross Profit | B7: 36445 | C7: 34621 | D7: 30593 | E7: 34078 | F7: 29685 | G7: 27706 | H7: 26257 | I7: 24678 | J7: 22923 | K7: 21434 | L7: 19977 | M7: 24440 | N7: Income Statement | O7: =+A7 -> Gross Profit | Q7: Ingreso | R7: + Coste de bienes y servicios | Z7: =Z6-28044 -> 10493 | AA7: =AA6-33546 -> 13465 | AB7: =AB6-40718 -> 14466 | AC7: =AC6-40727 -> 14929 | AD7: =+AD6-47055 -> 18820 | AE7: =+AE6-43578 -> 16560 | AF7: =+AF6-30367 -> 12221 | AG7: =+AG6-23886 -> 8510
A8: Operating Income | B8: 14041 | C8: 20817 | D8: 17493 | E8: 21125 | F8: 19009 | G8: 18018 | H8: 16831 | I8: 15998 | J8: 14904 | K8: 13563 | L8: 12179 | M8: 10721 | N8: Income Statement | O8: Operating Income | Q8: Ingreso | R8: + Ventas, generales y admin | Z8: =Z7-4383 -> 6110 | AA8: =AA7-4951 -> 8514 | AB8: =AB7-6529 -> 7937 | AC8: =AC7-5547 -> 9382 | AD8: =AD7-5919-2466-797-580-485 -> 8573 | AE8: =+AE7-5203-2297-826-1081 -> 7153 | AF8: =+AF7-4248-1905-914-1191 -> 3963 | AG8: =+AG7-3645-1421-1045-1822 -> 577
A9: Other Expenses (Revenues) | B9: -861 | C9: 2556 | D9: 1160 | E9: 438 | F9: -225 | G9: 421 | H9: 437 | I9: 76 | J9: 178 | K9: 126 | L9: 1951 | M9: -9 | N9: Income Statement | O9: investment income+other income expense+income loss+minority interest+non controlling interest+share onf net profit+gain8losses) on equity investments+share of result from associates nd joint ventures+non operating profit+ | Q9: Ingreso | R9: + Investigación y desarrollo | S9: + Coste de financiación de beneficio | T9: + Otro gasto operativo | U9: - Beneficio (pérdida) de filiales | V9: - Minoritarios | Z9: =1853+596+595+1904+6+8 -> 4962 | AA9: =2119+587+2023+11 -> 4740 | AB9: =2380+624+1619-8+16 -> 4631 | AC9: =2046+727+981+6+14 -> 3774 | AD9: =-14+41 -> 27 | AE9: 53 | AF9: =58+24 -> 82 | AG9: =12-68 -> -56
A10: Net Financial Cost | B10: -3896 | C10: -4281 | D10: -4588 | E10: -4567 | F10: -3542 | G10: -3086 | H10: -2942 | I10: -2702 | J10: -2617 | K10: -2574 | L10: -2521 | M10: -2505 | N10: Income Statement | O10: interest expense+financial income and expenses+other financial expense-income+interest and other net+ | Q10: Ingreso | R10: - Ingreso (pérdida) no operacional | Z10: =505+518 -> 1023 | AA10: =507-161 -> 346 | AB10: =484-322 -> 162 | AC10: =465+35 -> 500 | AD10: =467-130 -> 337 | AE10: =396+32 -> 428 | AF10: =343-130 -> 213 | AG10: =389-381 -> 8
A11: Taxes | B11: -4359 | C11: -5259 | D11: -3364 | E11: -3673 | F11: -3380 | G11: 7569 | H11: -5298 | I11: -4959 | J11: -3873 | K11: -3980 | L11: -3744 | M11: -3050 | N11: Income Statement | O11: Taxes | Q11: Ingreso | R11: - Gasto de impuesto a la renta (Beneficio) | Z11: 192 | AA11: 916 | AB11: 692 | AC11: 1319 | AD11: =2528 -> 2528 | AE11: =1720 -> 1720 | AF11: =968 -> 968 | AG11: =-270 -> -270
A12: Net Income | B12: 4925 | C12: 13833 | D12: 10701 | E12: 13323 | F12: 11862 | G12: 22922 | H12: 9028 | I12: 8413 | J12: 8592 | K12: 7135 | L12: 7865 | M12: 5157 | N12: Income Statement | O12: Net Income | Q12: Flujo de caja | R12: + Ingreso neto | Z12: -67 | AA12: 2512 | AB12: 2452 | AC12: 3789 | AD12: 5681 | AE12: =4928+24 -> 4952 | AF12: 2700 | AG12: 895
B13: =SUM(B8:B11) -> 4925 | C13: =SUM(C8:C11) -> 13833 | D13: =SUM(D8:D11) -> 10701 | E13: =SUM(E8:E11) -> 13323 | F13: =SUM(F8:F11) -> 11862 | G13: =SUM(G8:G11) -> 22922 | H13: =SUM(H8:H11) -> 9028 | I13: =SUM(I8:I11) -> 8413 | ... M13: =SUM(M8:M11) -> 5157 | Z13: =Z8-Z10-Z9-Z11 -> -67 | AA13: =AA8-AA10-AA9-AA11 -> 2512 | AB13: =AB8-AB10-AB9-AB11 -> 2452 | AC13: =AC8-AC10-AC9-AC11 -> 3789 | AD13: =AD8-AD10-AD9-AD11 -> 5681 | AE13: =AE8-AE10-AE9-AE11 -> 4952 | AF13: =AF8-AF10-AF9-AF11 -> 2700 | AG13: =AG8-AG10-AG9-AG11 -> 895
A14: FINANCIAL POSITION | B14: =B12-B13 -> 0 | C14: =C12-C13 -> 0 | D14: =D12-D13 -> 0 | E14: =E12-E13 -> 0 | F14: =F12-F13 -> 0 | G14: =G12-G13 -> 0 | H14: =H12-H13 -> 0 | I14: =I12-I13 -> 0 | ... M14: =M12-M13 -> 0 | Z14: =Z12-Z13 -> 0 | AA14: =AA12-AA13 -> 0 | AB14: =AB12-AB13 -> 0 | AC14: =AC12-AC13 -> 0 | AD14: =AD12-AD13 -> 0 | AE14: =AE12-AE13 -> 0 | AF14: =AF12-AF13 -> 0 | AG14: =AG12-AG13 -> 0
A16: Weighted Average Shares (Basic NI) | B16: 4406 | C16: 4584 | D16: 4574 | E16: 4548 | F16: 4584 | G16: 4708 | H16: 4819 | I16: 4972 | J16: 5166 | K16: 5250 | L16: 5356 | M16: 5492
A17: Weighted Average Shares (Diluted NI) | B17: 4430 | C17: 4654 | D17: 4624 | E17: 4610 | F17: 4640 | G17: 4786 | H17: 4875 | I17: 5036 | J17: 5240 | K17: 5330 | L17: 5356 | M17: 5556
A19: Net gains (losses) from ForEx | B19: -4242 | C19: -664 | D19: 1213 | E19: 1375 | F19: -916 | G19: 147 | H19: 102 | I19: -89 | J19: -38 | K19: -29 | L19: 0 | M19: -12
A20: Total Comprehensive Income | B20: 1280 | C20: 13755 | D20: 11371 | E20: 14472 | F20: 10908 | G20: 22822 | H20: 8950 | I20: 8135 | J20: 8178 | K20: 6883 | L20: 6370 | M20: 4107
A22: Changes Net Working Capital | B22: =B23-C23 -> 2442 | C22: =C23-D23 -> 543 | D22: =D23-E23 -> -3395 | E22: =E23-F23 -> -831 | F22: =F23-G23 -> -491 | G22: =G23-H23 -> -603 | H22: =H23-I23 -> -305 | I22: =I23-J23 -> -381 | ... M22: =M23-N23 -> -6288 | N22: cash flows | O22: NWC | Q22: Flujo de caja
A23: Net Working Capital | B23: =B27-B42-B28 -> -10810 | C23: =C27-C42-C28 -> -13252 | D23: =D27-D42-D28 -> -13795 | E23: =E27-E42-E28 -> -10400 | F23: =F27-F42-F28 -> -9569 | G23: =G27-G42-G28 -> -9078 | H23: =H27-H42-H28 -> -8475 | I23: =I27-I42-I28 -> -8170 | ... M23: =M27-M42-M28 -> -6288
A24: 2625 | B24: 2625 | C24: 2625 | D24: 2625 | E24: 2625 | F24: 2625 | G24: 2625 | H24: 2625 | I24: 2625 | J24: 2625 | K24: 2625 | L24: 2625 | M24: 2625 | N24: 2625 | Q24: Flujo de caja | R24: + Dividendos pagados | T24: Cambiar signo | Z24: 1799 | AA24: 1757 | AB24: 1620 | AC24: 1111 | AD24: 1617 | AE24: 1159 | AF24: 1084 | AG24: 1029
A25: BALANCE SHEET | B25: 2625 | C25: 2625 | D25: 2625 | E25: 2625 | F25: 2625 | G25: 2625 | H25: 2625 | I25: 2625 | J25: 2625 | K25: 2625 | L25: 2625 | M25: 2625 | N25: 2625 | Q25: Flujo de caja | R25: + Aumento en capital | S25: + Baja en capital | T25: Cambiar signo y hacer suma | Z25: 23 | AA25: =-33+2025 -> 1992 | AB25: 3817 | AC25: 1776 | AD25: -244 | AE25: -312 | AF25: -449 | AG25: -110
A26: ASSETS | N26: 1922 | O26: 2625
A27: Current | B27: 21826 | C27: 24807 | D27: 26741 | E27: 25392 | F27: 21848 | G27: 16343 | H27: 16361 | I27: 12303 | J27: 13531 | K27: 14075 | L27: 19991 | M27: 8573
A28: Cash & Eq. | B28: 4749 | C28: 8711 | D28: 11740 | E28: 5500 | F28: 3814 | G28: 3428 | H28: 3301 | I28: 2295 | J28: 3910 | K28: 1718 | L28: 10951 | M28: 1620 | N28: Balance Sheet | O28: Cash & Eq.
A29: Accounts Receivable | B29: 12671 | C29: 12008 | D29: 11466 | E29: 11292 | F29: 11104 | G29: 8834 | H29: 8372 | I29: 7369 | J29: 6680 | K29: 6751 | L29: 5828 | M29: 4854 | N29: Balance Sheet | O29: Accounts Receivable
A30: Inventory | B30: 0 | C30: 0 | D30: 0 | E30: 0 | F30: 0 | G30: 0 | H30: 0 | I30: 0 | J30: 0 | K30: 0 | L30: 0 | M30: 0 | N30: Balance Sheet | O30: Inventory | Q30: Balance | R30: + Efectivo, equivalentes y STI | Z30: 7168 | AA30: 6460 | AB30: 7341 | AC30: 6081 | AD30: 5490 | AE30: 3057 | AF30: 3592 | AG30: 4867
A31: Other Current Assets | B31: =B27-SUM(B28:B30) -> 4406 | C31: =C27-SUM(C28:C30) -> 4088 | D31: =D27-SUM(D28:D30) -> 3535 | E31: =E27-SUM(E28:E30) -> 8600 | F31: =F27-SUM(F28:F30) -> 6930 | G31: =G27-SUM(G28:G30) -> 4081 | H31: =H27-SUM(H28:H30) -> 4688 | I31: =I27-SUM(I28:I30) -> 2639 | ... M31: =M27-SUM(M28:M30) -> 2099 | N31: Balance Sheet | O31: Inventory | Q31: Balance | R31: + Cuentas y notas por cobrar | S31: + Activos derivados y de cobertura | T31: + Inversiones y cuentas por cobrar a LP | Z31: =5981+8522+1029+13556 -> 29088 | AA31: =6695+8991+1170+13651 -> 30507 | AB31: =7737+9027+1364+14644 -> 32772 | AC31: 33499 | AD31: 33911 | AE31: 31031 | AF31: 28849 | AG31: 27162
A32: Non-current | B32: =B38-B27 -> 235449 | C32: =C38-C27 -> 251098 | D32: =D38-D27 -> 247128 | E32: =E38-E27 -> 238022 | F32: =F38-F27 -> 229836 | G32: =G38-G27 -> 171119 | H32: =H38-H27 -> 164139 | I32: =I38-I27 -> 154271 | ... M32: =M38-M27 -> 149245
A33: Property, Plant and Equipment | B33: 55485 | C33: 54047 | D33: 51995 | E33: 48322 | F33: 44437 | G33: 38470 | H33: 36253 | I33: 33665 | J33: 30953 | K33: 29840 | L33: 27232 | M33: 27559 | Q33: Balance | R33: + Inventarios | Z33: 8614 | AA33: 9700 | AB33: 12205 | AC33: 12625 | AD33: 15547 | AE33: 14544 | AF33: 9587 | AG33: 6360
A34: Operating leases | B34: 5997 | C34: 6467 | D34: 3784 | E34: 4038 | F34: 0 | G34: 0 | H34: 0 | I34: 0 | J34: 0 | K34: 0 | L34: 0 | M34: 0
A35: Equity Method Investments | B35: 5421 | C35: 6111 | D35: 6006 | E35: 5347 | F35: 4035 | G35: 3546 | H35: 2376 | I35: 678 | J35: 1019 | K35: 989 | L35: 1164 | M35: 4880
A36: Other Non-Current Assets | B36: =B32-SUM(B33:B35) -> 168546 | C36: =C32-SUM(C33:C35) -> 184473 | D36: =D32-SUM(D33:D35) -> 185343 | E36: =E32-SUM(E33:E35) -> 180315 | F36: =F32-SUM(F33:F35) -> 181364 | G36: =G32-SUM(G33:G35) -> 129103 | H36: =H32-SUM(H33:H35) -> 125510 | I36: =I32-SUM(I33:I35) -> 119928 | ... M36: =M32-SUM(M33:M35) -> 116806 | N36: Balance Sheet | O36: Property, Plant and Equipment
A37: Other Assets | B37: =B31+B36 -> 172952 | C37: =C31+C36 -> 188561 | D37: =D31+D36 -> 188878 | E37: =E31+E36 -> 188915 | F37: =F31+F36 -> 188294 | G37: =G31+G36 -> 133184 | H37: =H31+H36 -> 130198 | I37: =I31+I36 -> 122567 | ... M37: =M31+M36 -> 118905 | N37: Balance Sheet
A38: Total Assets | B38: 257275 | C38: 275905 | D38: 273869 | E38: 263414 | F38: 251684 | G38: 187462 | H38: 180500 | I38: 166574 | J38: 159186 | K38: 158813 | L38: 164971 | M38: 157818 | N38: Balance Sheet | O38: Total Assets | Q38: Balance | R38: + Propiedad, planta y equipo; neto | Z38: 15322 | AA38: 16090 | AB38: =16577 -> 16577 | AC38: 17075 | AD38: 16461 | AE38: 14395 | AF38: 12539 | AG38: 12386
N39: Balance Sheet | Z39: =Z40-SUM(Z30:Z38) -> 14512 | AA39: =AA40-SUM(AA30:AA38) -> 15585 | AB39: =AB40-SUM(AB30:AB38) -> 15786 | AC39: =AC40-SUM(AC30:AC38) -> 15616 | AD39: =AD40-SUM(AD30:AD38) -> 17947 | AE39: =AE40-SUM(AE30:AE38) -> 18419 | AF39: =AF40-SUM(AF30:AF38) -> 9453 | AG39: =AG40-SUM(AG30:AG38) -> 9263
N40: Balance Sheet | Q40: Balance | R40: Activos totales | Z40: 74704 | AA40: 78342 | AB40: 84681 | AC40: 84896 | AD40: 89356 | AE40: 81446 | AF40: 64020 | AG40: 60038
A41: LIABILITIES | N41: Balance Sheet
A42: Current Liabilities | B42: 27887 | C42: 29348 | D42: 28796 | E42: 30292 | F42: 27603 | G42: 21993 | H42: 21535 | I42: 18178 | J42: 17410 | K42: 18912 | L42: 16714 | M42: 13241 | N42: Balance Sheet | O42: Current Liabilities
A43: Payables | B43: 12544 | C43: 12455 | D43: 11364 | E43: 10826 | F43: 8494 | G43: 6908 | H43: 6915 | I43: 6215 | J43: 5638 | K43: 5528 | L43: 6206 | M43: 5705
A44: Short-Term Debt | B44: 0 | C44: 0 | D44: 0 | E44: 0 | F44: 0 | G44: 0 | H44: 0 | I44: 0 | J44: 0 | K44: 0 | L44: 0 | M44: 0 | N44: Balance Sheet | O44: Short term Debt | Q44: Balance | R44: Pasivos totales corrientes | Z44: 26132 | AA44: 26242 | AB44: 27877 | AC44: 27297 | AD44: 29415 | AE44: =93+3895+8161+3386+2410+2691+298+1967+558+5102 -> 28561 | AF44: =204+3852+5856+2880+1670+1831+281+1521+495+3430 -> 22020 | AG44: =433+3650+2993+3351+797+1217+262+888+302+5399 -> 19292
A45: Short-Term Leases | B45: 675 | C45: 766 | D45: 718 | E45: 715 | F45: 0 | G45: 0 | H45: 0 | I45: 0 | J45: 0 | K45: 0 | L45: 0 | M45: 0
A46: Other current liabilities | B46: =B42-SUM(B43:B45) -> 14668 | C46: =C42-SUM(C43:C45) -> 16127 | D46: =D42-SUM(D43:D45) -> 16714 | E46: =E42-SUM(E43:E45) -> 18751 | F46: =F42-SUM(F43:F45) -> 19109 | G46: =G42-SUM(G43:G45) -> 15085 | H46: =H42-SUM(H43:H45) -> 14620 | I46: =I42-SUM(I43:I45) -> 11963 | ... M46: =M42-SUM(M43:M45) -> 7536 | N46: Balance Sheet | R46: + Préstamos CP | Z46: 7303 | AA46: 6967 | AB46: 4708 | AC46: 3679 | AD46: 5287 | AE46: 5660 | AF46: 3925 | AG46: 5701
A47: Non-current Liabilities | B47: =B51-B42 -> 148445 | C47: =C51-C42 -> 150465 | D47: =D51-D42 -> 154750 | E47: =E51-E42 -> 150396 | F47: =F51-F42 -> 152468 | G47: =G51-G42 -> 96853 | H47: =H51-H42 -> 105022 | I47: =I51-I42 -> 96127 | ... M47: =M51-M42 -> 97303 | N47: Balance Sheet | O47: Total non current liabilities
A48: Long-Term Debt | B48: 98240 | C48: 97888 | D48: 105782 | E48: 102931 | F48: 107345 | G48: 59422 | H48: 55566 | I48: 48994 | J48: 43864 | K48: 44567 | L48: 38082 | M48: 37942 | N48: Balance Sheet | O48: Long term debt | Z48: =Z44-Z46 -> 18829 | AA48: =AA44-AA46 -> 19275 | AB48: =AB44-AB46 -> 23169 | AC48: =AC44-AC46 -> 23618 | AD48: =AD44-AD46 -> 24128 | AE48: =AE44-AE46 -> 22901 | AF48: =AF44-AF46 -> 18095 | AG48: =AG44-AG46 -> 13591
A49: Long-Term Leases | B49: 6107 | C49: 6473 | D49: 3740 | E49: 3891 | F49: 0 | G49: 0 | H49: 0 | I49: 0 | J49: 0 | K49: 0 | L49: 0 | M49: 0 | Q49: Balance | R49: Pasivos totales no corrientes | Z49: =61491-Z44 -> 35359 | AA49: =63457-AA44 -> 37215 | AB49: =67855-AB44 -> 39978 | AC49: 36721 | AD49: 41973 | AE49: =8415+16529+10956+3583 -> 39483 | AF49: =4505+15932+7584+2654 -> 30675 | AG49: =5652+16195+7420+2179 -> 31446
A50: Other non-current liabilities | B50: =B47-SUM(B48:B49) -> 44098 | C50: =C47-SUM(C48:C49) -> 46104 | D50: =D47-SUM(D48:D49) -> 45228 | E50: =E47-SUM(E48:E49) -> 43574 | F50: =F47-SUM(F48:F49) -> 45123 | G50: =G47-SUM(G48:G49) -> 37431 | H50: =H47-SUM(H48:H49) -> 49456 | I50: =I47-SUM(I48:I49) -> 47133 | ... M50: =M47-SUM(M48:M49) -> 59361 | N50: Balance Sheet | O50: Other non current Liabilities | R50: + Préstamos a largo plazo | Z50: 22818 | AA50: 25169 | AB50: 27784 | AC50: 26719 | AD50: 27752 | AE50: 24944 | AF50: 20437 | AG50: 21847
A51: Total Liabilities | B51: 176332 | C51: 179813 | D51: 183546 | E51: 180688 | F51: 180071 | G51: 118846 | H51: 126557 | I51: 114305 | J51: 106475 | K51: 108119 | L51: 115615 | M51: 110544 | N51: Balance Sheet | O51: Total Liabilities
N52: Balance Sheet | Z52: =Z49-Z50 -> 12541 | AA52: =AA49-AA50 -> 12046 | AB52: =AB49-AB50 -> 12194 | AC52: =AC49-AC50 -> 10002 | AD52: =AD49-AD50 -> 14221 | AE52: =AE49-AE50 -> 14539 | AF52: =AF49-AF50 -> 10238 | AG52: =AG49-AG50 -> 9599
N53: Balance Sheet | Z53: =+Z49+Z44 -> 61491 | AA53: =+AA49+AA44 -> 63457 | AB53: =+AB49+AB44 -> 67855 | AC53: =AC44+AC49 -> 64018 | AD53: =AD49+AD44 -> 71388 | AE53: =AE49+AE44 -> 68044 | AF53: =AF49+AF44 -> 52695 | AG53: =AG49+AG44 -> 50738
A54: Minority Interest | B54: =411+684 -> 1095 | C54: =519+1398 -> 1917 | D54: =1280+1415 -> 2695 | E54: =1372+1148 -> 2520 | F54: =1316+889 -> 2205 | G54: =1357+843 -> 2200 | H54: =1446+2231 -> 3677 | I54: =1221+1709 -> 2930 | J54: =1066+357 -> 1423 | K54: =957+364 -> 1321 | L54: =16998+440 -> 17438 | M54: =16014+381 -> 16395 | N54: Balance Sheet | O54: Minority Interest
N55: Balance Sheet
A56: Shareholder's Equity | B56: =B38-B51-B54 -> 79848 | C56: =C38-C51-C54 -> 94175 | D56: =D38-D51-D54 -> 87628 | E56: =E38-E51-E54 -> 80206 | F56: =F38-F51-F54 -> 69408 | G56: =G38-G51-G54 -> 66416 | H56: =H38-H51-H54 -> 50266 | I56: =I38-I51-I54 -> 49339 | ... M56: =M38-M51-M54 -> 30879 | N56: Balance Sheet | Q56: Balance | R56: + Participación minoritaria/no dominante
A58: CASH FLOW
A59: Operating CF | B59: 26413 | C59: 29146 | D59: 24737 | E59: 25697 | F59: 24297 | G59: 21261 | H59: 19691 | I59: 18778 | J59: 16945 | K59: 14160 | L59: 14854 | M59: 14345
A60: Net Income | B60: 4925 | C60: 13833 | D60: 10701 | E60: 13323 | F60: 11862 | G60: 22922 | H60: 9028 | I60: 8413 | J60: 8592 | K60: 7135 | L60: 7865 | M60: 5157
A61: Depreciation & Amortization | B61: 13821 | C61: 13804 | D61: 13100 | E61: 12953 | F61: 10676 | G61: 9688 | H61: 9426 | I61: 8680 | J61: 8019 | K61: 7871 | L61: 7798 | M61: 7636
A62: Changes in assets and liabilities | B62: -3006 | C62: -1499 | D62: -178 | E62: -2335 | F62: -1313 | G62: -546 | H62: -1404 | I62: -267 | J62: -357 | K62: 93 | L62: -418 | M62: -603
A63: Other Adjustments | B63: =B59-B60-B61-B62 -> 10673 | C63: =C59-C60-C61-C62 -> 3008 | D63: =D59-D60-D61-D62 -> 1114 | E63: =E59-E60-E61-E62 -> 1756 | F63: =F59-F60-F61-F62 -> 3072 | G63: =G59-G60-G61-G62 -> -10803 | H63: =H59-H60-H61-H62 -> 2641 | I63: =I59-I60-I61-I62 -> 1952 | ... M63: =M59-M60-M61-M62 -> 2155
A64: Investing CF | B64: -14140 | C64: -13446 | D64: -12047 | E64: -14841 | F64: -50854 | G64: -13533 | H64: -18265 | I64: -11964 | J64: -8733 | K64: -9514 | L64: -1486 | M64: -12508
A65: Net Capex | B65: -10626 | C65: -9174 | D65: -9179 | E65: -9953 | F65: -9774 | G65: -9550 | H65: -9135 | I65: -8499 | J65: -7420 | K65: -6596 | L65: -5714 | M65: -5307
A66: Investments & Acquisitions | B66: -12 | C66: -1374 | D66: -233 | E66: -370 | F66: -38219 | G66: -532 | H66: -3929 | I66: -1786 | J66: -477 | K66: -1904 | L66: 0 | M66: 0
A67: Other Inflows (Outflows) | B67: =B64-B65-B66 -> -3502 | C67: =C64-C65-C66 -> -2898 | D67: =D64-D65-D66 -> -2635 | E67: =E64-E65-E66 -> -4518 | F67: -24 | G67: 4 | H67: 20 | I67: 31 | J67: 10 | K67: 39 | L67: 41 | M67: 28
A68: Financing CF | B68: -16184 | C68: -18618 | D68: -6513 | E68: -9181 | F68: 27140 | G68: -7572 | H68: -434 | I68: -8429 | J68: -6020 | K68: -13879 | L68: -4037 | M68: -6201
A69: Debt Borrowing | B69: 2745 | C69: 2628 | D69: 18644 | E69: 5479 | F69: 44781 | G69: 11466 | H69: 9231 | I69: 5486 | J69: 4182 | K69: 2933 | L69: 4544 | M69: 0
A70: Debt Repayment | B70: -2307 | C70: -11498 | D70: -18777 | E70: -14354 | F70: -8798 | G70: -6364 | H70: -3052 | I70: -4378 | J70: -3175 | K70: -2444 | L70: -2881 | M70: -3216
A71: Lease Increases | B71: 0 | C71: 0 | D71: 0 | E71: 0 | F71: 0 | G71: 0 | H71: 0 | I71: 0 | J71: 0 | K71: 0 | L71: 0 | M71: 0
A72: Lease Payments | B72: 0 | C72: 0 | D72: 0 | E72: 0 | F72: 0 | G72: 0 | H72: 0 | I72: 0 | J72: 0 | K72: 0 | L72: 0 | M72: 0
A73: Dividends | B73: -4741 | C73: -4532 | D73: -4140 | E73: -3735 | F73: -3352 | G73: -2883 | H73: -2601 | I73: -2437 | J73: -2254 | K73: -1964 | L73: -1608 | M73: -1187 | N73: cash flows FINANCING | O73: Dividends paid
A74: Share buyback | B74: -13328 | C74: -4672 | D74: -534 | E74: -504 | F74: -5320 | G74: -5435 | H74: -5352 | I74: 0 | J74: 0 | K74: -2000 | L74: -3000 | M74: -2141 | N74: cash flows FINANCING | O74: =+A74 -> Share buyback
A75: Other Inflows (Outflows) | B75: =B68-B69-B70-B71-B72-B73-B74 -> 1447 | C75: =C68-C69-C70-C71-C72-C73-C74 -> -544 | D75: =D68-D69-D70-D71-D72-D73-D74 -> -1706 | E75: =E68-E69-E70-E71-E72-E73-E74 -> 3933 | F75: =F68-F69-F70-F71-F72-F73-F74 -> -171 | G75: =G68-G69-G70-G71-G72-G73-G74 -> -4356 | H75: =H68-H69-H70-H71-H72-H73-H74 -> 1340 | I75: =I68-I69-I70-I71-I72-I73-I74 -> -7100 | ... M75: =M68-M69-M70-M71-M72-M73-M74 -> 343
A76: FX | B76: -86 | C76: -71 | D76: 2 | E76: 5 | F76: -245 | G76: 0 | H76: 0 | I76: 0 | J76: 0 | K76: 0 | L76: 0 | M76: 0
A77: Changes in cash | B77: =B59+B64+B68+B76 -> -3997 | C77: =C59+C64+C68+C76 -> -2989 | D77: =D59+D64+D68+D76 -> 6179 | E77: =E59+E64+E68+E76 -> 1680 | F77: =F59+F64+F68+F76 -> 338 | G77: =G59+G64+G68+G76 -> 156 | H77: =H59+H64+H68+H76 -> 992 | I77: =I59+I64+I68+I76 -> -1615 | ... M77: =M59+M64+M68+M76 -> -4364
O78: (Vitalis will later fill this info)
A79: Other Data | E79: Corporate Bonds 3, 5 Y 10 | H79: Average Price | J79: Moody's | K79: YTM | L79: DIVISA
A80: Number of employees | B80: 142000 | C80: 10-K | N80: bloomberg
A81: Shares Outstanding (Thousands) | B81: 285620 | C81: Yahoo finance | N81: bloomberg
A82: Float | B82: =OP!M19 -> 0.99 | C82: Yahoo finance | N82: bloomberg
A83: Insiders Own | B83: =OP!M20 -> 0.0074 | C83: Yahoo finance | N83: bloomberg
A84: Fitch/ S&P Rating | B84: =OP!M22 -> A- | C84: 10-K | N84: bloomberg
A85: Dividend Yield(Yahoo Finance) | B85: =Peers!C35 -> 1.945271 | C85: Yahoo finance | N85: bloomberg
A86: Daily Volume in Millions of USD | C86: Yahoo Finance | N86: bloomberg
B87: 2020 | C87: =B87+1 -> 2021 | D87: =C87+1 -> 2022
A88: Short % of Float | D88: 0.0086 | E88: Yahoo Finance
A89: EPS | B89: 2.3 | C89: 3.12 | D89: 1.27 | E89: Yahoo Finance

Sheet Sector Impact
E2: Sector | F2: Sub-Industry | H2: Low | K2: Sector | L2: Environment | Q2: Social
E3: Communication Services | F3: Interactive Home Entertainment | H3: Medium | L3: CO2 | M3: Water | N3: Energy | O3: Waste | P3: Degradation | Q3: Turnover | R3: Compensation | S3: Reputation | T3: Discrimination | U3: Security | V3: Damage | W3: Pension | X3: Supply | Y3: Community | Z3: Public | AA3: Litigation
E4: Communication Services | F4: Interactive Media & Services | H4: High | K4: Communication Services | L4: Low | M4: Low | N4: Medium | O4: Low | P4: Low | Q4: Medium | R4: Medium | S4: Low | T4: Low | U4: High | V4: Low | W4: Low | X4: Low | Y4: Low | Z4: Low | AA4: Medium
B5: Environmental | E5: Communication Services | F5: Integrated Telecommunication Services | H5: Very High | K5: Consumer Discretionary | L5: Low | M5: Low | N5: Medium | O5: Medium | P5: Low | Q5: Medium | R5: Medium | S5: Low | T5: Low | U5: Medium | V5: Medium | W5: Medium | X5: High | Y5: Low | Z5: High | AA5: Low
B6: Direct CO2 emissions | E6: Communication Services | F6: Cable & Satellite | K6: Consumer Staples | L6: High | M6: Very High | N6: High | O6: High | P6: High | Q6: Medium | R6: High | S6: High | T6: Low | U6: Medium | V6: Medium | W6: Low | X6: High | Y6: Low | Z6: Very High | AA6: Low
B7: Total Water Use | E7: Communication Services | F7: Broadcasting | K7: Energy | L7: Very High | M7: Very High | N7: Medium | O7: Very High | P7: High | Q7: High | R7: Medium | S7: Medium | T7: Medium | U7: Medium | V7: High | W7: Medium | X7: Medium | Y7: High | Z7: High | AA7: Low
K8: Renewable Energy | L8: Low | M8: Low | N8: Low | O8: Medium | P8: Medium | Q8: Low | R8: Medium | S8: Medium | T8: High | U8: Medium | V8: Low | W8: Low | X8: Medium | Y8: Medium | Z8: High | AA8: Low
B9: Total Energy Consumption | E9: Communication Services | F9: Movies & Entertainment | K9: Financials | L9: Low | M9: Low | N9: Low | O9: Low | P9: Low | Q9: Low | R9: Low | S9: Medium | T9: High | U9: Medium | V9: Low | W9: Low | X9: Low | Y9: Low | Z9: Medium | AA9: Low
K10: Forestry | L10: Low | M10: Medium | N10: Low | O10: Medium | P10: High | Q10: Low | R10: Low | S10: Low | T10: Low | U10: Low | V10: Low | W10: Low | X10: Low | Y10: Medium | Z10: Low | AA10: Low
B11: Waste Management | E11: Communication Services | F11: Advertising | K11: Health Care | L11: Low | M11: Medium | N11: Low | O11: Low | P11: Low | Q11: Low | R11: Low | S11: Medium | T11: Low | U11: High | V11: Low | W11: Low | X11: Low | Y11: Low | Z11: Low | AA11: Low
B12: Land Degradation/Deforestation/Biodiversity loss/Animal sufering/... | E12: Communication Services | F12: Alternative Carriers | K12: Industrials | L12: Very High | M12: Very High | N12: Very High | O12: High | P12: High | Q12: Low | R12: Medium | S12: High | T12: Very High | U12: Medium | V12: Very High | W12: Medium | X12: Very High | Y12: Very High | Z12: Very High | AA12: High
B13: Social | E13: Communication Services | F13: Publishing | K13: Information Technology | L13: Medium | M13: Low | N13: High | O13: Low | P13: Low | Q13: Low | R13: Low | S13: Low | T13: Low | U13: High | V13: Low | W13: Low | X13: Low | Y13: Low | Z13: Medium | AA13: Very High
B14: Employee turnover | E14: Communication Services | F14: Wireless Telecommunication Services | K14: Materials | L14: Very High | M14: Very High | N14: Very High | O14: Very High | P14: High | Q14: High | R14: High | S14: Medium | T14: High | U14: Low | V14: Very High | W14: Medium | X14: Medium | Y14: Very High | Z14: High | AA14: Medium
B15: Salaries and compensation | E15: Consumer Discretionary | F15: Automotive Retail | K15: Real Estate | L15: Low | M15: Low | N15: Medium | O15: Low | P15: Low | Q15: Medium | R15: Low | S15: Low | T15: Low | U15: High | V15: Low | W15: Medium | X15: Low | Y15: Medium | Z15: Low | AA15: Low
B16: Reputational issues | E16: Consumer Discretionary | F16: Internet & Direct Marketing Retail | K16: Utilities | L16: Very High | M16: High | N16: High | O16: Medium | P16: High | Q16: Low | R16: Medium | S16: Medium | T16: Low | U16: Medium | V16: Medium | W16: Medium | X16: Medium | Y16: Low | Z16: Medium | AA16: Low
B17: Discrimination issues | E17: Consumer Discretionary | F17: Auto Parts & Equipment
B18: Job security | E18: Consumer Discretionary | F18: Specialty Stores
B19: Health injuries | E19: Consumer Discretionary | F19: Computer & Electronics Retail | L19: Communication Services | M19: Consumer Discretionary | N19: Consumer Staples | O19: Energy | P19: Financials | Q19: Health Care | R19: Industrials | S19: Information Technology | T19: Materials | U19: Real Estate | V19: Utilities
B20: PXP? | E20: Consumer Discretionary | F20: Hotels, Resorts & Cruise Lines | L20: Interactive Home Entertainment | M20: Automotive Retail | N20: Tobacco | O20: Oil & Gas Exploration & Production | P20: Life & Health Insurance | Q20: Health Care Equipment | R20: Industrial Conglomerates | S20: IT Consulting & Other Services | T20: Industrial Gases | U20: Office REITs | V20: Independent Power Producers & Energy Traders
B21: Supply chain | E21: Consumer Discretionary | F21: Restaurants | L21: Interactive Media & Services | M21: Internet & Direct Marketing Retail | N21: Agricultural Products | O21: Oil & Gas Equipment & Services | P21: Property & Casualty Insurance | Q21: Pharmaceuticals | R21: Airlines | S21: Application Software | T21: Specialty Chemicals | U21: Specialized REITs | V21: Electric Utilities
B22: Community involvement | E22: Consumer Discretionary | F22: Homebuilding | L22: Integrated Telecommunication Services | M22: Auto Parts & Equipment | N22: Distillers & Vintners | O22: Integrated Oil & Gas | P22: Consumer Finance | Q22: Health Care Supplies | R22: Building Products | S22: Semiconductors | T22: Paper Packaging | U22: Residential REITs | V22: Multi-Utilities
B23: Public Sector | E23: Consumer Discretionary | F23: General Merchandise Stores | L23: Cable & Satellite | M23: Specialty Stores | N23: Packaged Foods & Meats | O23: Oil & Gas Refining & Marketing | P23: Asset Management & Custody Banks | Q23: Health Care Distributors | R23: Electrical Components & Equipment | S23: Internet Services & Infrastructure | T23: Metal & Glass Containers | U23: Real Estate Services | V23: Water Utilities
B24: Litigation | E24: Consumer Discretionary | F24: Automobile Manufacturers | L24: Broadcasting | M24: Computer & Electronics Retail | N24: Household Products | O24: Oil & Gas Storage & Transportation | P24: Insurance Brokers | Q24: Biotechnology | R24: Aerospace & Defense | S24: Electronic Components | T24: Fertilizers & Agricultural Chemicals | U24: Industrial REITs | V24: Gas Utilities
E25: Consumer Discretionary | F25: Apparel Retail | L25: Movies & Entertainment | M25: Hotels, Resorts & Cruise Lines | N25: Soft Drinks | P25: Multi-line Insurance | Q25: Managed Health Care | R25: Air Freight & Logistics | S25: Technology Hardware, Storage & Peripherals | T25: Commodity Chemicals | U25: Retail REITs
E26: Consumer Discretionary | F26: Consumer Electronics | L26: Advertising | M26: Restaurants | N26: Hypermarkets & Super Centers | P26: Diversified Banks | Q26: Life Sciences Tools & Services | R26: Construction Machinery & Heavy Trucks | S26: Semiconductor Equipment | T26: Diversified Chemicals | U26: Health Care REITs
E27: Consumer Discretionary | F27: Apparel, Accessories & Luxury Goods | L27: Alternative Carriers | M27: Homebuilding | N27: Personal Products | P27: Multi-Sector Holdings | Q27: Health Care Technology | R27: Diversified Support Services | S27: Communications Equipment | T27: Copper | U27: Hotel & Resort REITs
E28: Consumer Discretionary | F28: Leisure Products | L28: Publishing | M28: General Merchandise Stores | N28: Food Retail | P28: Financial Exchanges & Data | Q28: Health Care Services | R28: Railroads | S28: Data Processing & Outsourced Services | T28: Construction Materials
E29: Consumer Discretionary | F29: Home Improvement Retail | L29: Wireless Telecommunication Services | M29: Automobile Manufacturers | N29: Brewers | P29: Investment Banking & Brokerage | Q29: Health Care Facilities | R29: Industrial Machinery | S29: Technology Distributors | T29: Gold
E30: Consumer Discretionary | F30: Casinos & Gaming | M30: Apparel Retail | N30: Food Distributors | P30: Regional Banks | R30: Agricultural & Farm Machinery | S30: Electronic Equipment & Instruments | T30: Steel
E31: Consumer Discretionary | F31: Home Furnishings | M31: Consumer Electronics | N31: Drug Retail | P31: Reinsurance | R31: Research & Consulting Services | S31: Systems Software
E32: Consumer Discretionary | F32: Distributors | M32: Apparel, Accessories & Luxury Goods | P32: Thrifts & Mortgage Finance | R32: Construction & Engineering | S32: Electronic Manufacturing Services
E33: Consumer Discretionary | F33: Housewares & Specialties | M33: Leisure Products | R33: Trucking
E34: Consumer Discretionary | F34: Household Appliances | M34: Home Improvement Retail | R34: Environmental & Facilities Services
E35: Consumer Staples | F35: Tobacco | M35: Casinos & Gaming | R35: Human Resource & Employment Services
E36: Consumer Staples | F36: Agricultural Products | M36: Home Furnishings | R36: Trading Companies & Distributors
E37: Consumer Staples | F37: Distillers & Vintners | M37: Distributors
E38: Consumer Staples | F38: Packaged Foods & Meats | M38: Housewares & Specialties
E39: Consumer Staples | F39: Household Products | M39: Household Appliances
E40: Consumer Staples | F40: Soft Drinks
E41: Consumer Staples | F41: Hypermarkets & Super Centers
E42: Consumer Staples | F42: Personal Products
E43: Consumer Staples | F43: Food Retail
E44: Consumer Staples | F44: Brewers
E45: Consumer Staples | F45: Food Distributors
E46: Consumer Staples | F46: Drug Retail
E47: Energy | F47: Oil & Gas Exploration & Production
E48: Energy | F48: Oil & Gas Equipment & Services
E49: Energy | F49: Integrated Oil & Gas
E50: Energy | F50: Oil & Gas Refining & Marketing
E51: Energy | F51: Oil & Gas Storage & Transportation
... E128: Utilities | F128: Gas Utilities
