Workbook
Name Sectors: '[1]Sector Impact'!$K$4:$K$16
Name Sectors: 'Sector Impact'!$K$4:$K$16

Sheet OP
B2: 45138 | C2: Team 2 | D2: 8th August | E2: =Inputs!H3 -> Daikin Industries,Ltd. (6367.T) | L2: TSE | M2: SIC:
D3: COMPANY DESCRIPTION | H3: CEO & BOARD OF DIRECTORS
D4: Daikin is a leading Japanese company specializing in HVAC (Heating, Ventilation, and Air Conditioning) systems and refrigerants. Established in 1924, Daikin has become a global industry leader known for its innovative technologies and commitment to environmental sustainability. With a strong focus on research and development, Daikin continues to provide cutting-edge cooling solutions and maintain a prominent presence in the international market. | H4: Name | I4: Gender | J4: Age | K4: Tenure | L4: Executive? | M4: Other roles
H5: Noriyuki Inoue | I5: M | J5: 88 | K5: 9 | L5: Y- Chairman of the Board | M5: Chairman Daikin Foundation for Contemporary Arts and Kansai Philharmonic Orchestra
H6: Masanori Togawa | I6: M | J6: 74 | K6: 9 | L6: Y- President and CEO | M6: N/A
H7: Tatsuo Kawada | I7: M | J7: 83 | K7: 7 | L7: N | M7: Chairman and CEO of Seiren Co., Ltd.; External Director of Hokuriku Electric Power Company
H8: Akiji Makino | I8: M | J8: 82 | K8: 7 | L8: N | M8: Chairman and CEO of Iwatani Corporation; Chairman of the Board of Iwatani Industrial Gases Corp
H9: Shingo Torii | I9: M | J9: 70 | K9: 3 | L9: N | M9: Director and Vice Chairman of the Board of Suntory Holdings Limited
H10: Yuko Arai | I10: F | J10: 62 | K10: 2 | L10: N | M10: Senior Advisor of ANA Akindo Co., Ltd.; Outside Director of Aichi Steel Corp
H11: Ken Tayano | I11: M | J11: 76 | K11: 9 | L11: Y | M11: Chairman of the Board and President of Daikin (China) Investment Co., Ltd.
H12: Masatsugu Minaka | I12: M | J12: 70 | K12: 12 | L12: Y | M12: Chairman of the Board of Daikin Europe N.V
H13: Takashi Matsuzaki | I13: M | J13: 65 | K13: 3 | L13: Y | M13: N/A
B14: JPY MILLIONS | H14: Kanwal Jeet Jawa | I14: M | J14: 64 | K14: 4 | L14: Y | M14: Managing Director and CEO of Daikin Airconditioning India Pvt. Ltd
B15: COMPANY OVERVIEW
B16: Stock | D16: Liquidity and Solvency | F16: Segments | I16: Profitability (2022) | L16: Multiples
B17: Last Price | C17: 25025 | D17: Total Assets | E17: =_xlfn.XLOOKUP(D17,'Fin. Data'!A:A,'Fin. Data'!B:B,,0) -> 4303682 | F17: Regions | H17: % Sales | I17: Reporting Year | J17: 2022 | L17: Float | M17: =2.68/2.93 -> 0.91467577
B18: Outstanding Shares | C18: 292680000 | D18: Total Liabilities | E18: =_xlfn.XLOOKUP(D18,'Fin. Data'!A:A,'Fin. Data'!B:B,,0) -> 2065534 | F18: =Segments!C5 -> Japan | H18: =Segments!B5 -> 0.17182367 | I18: End of Year | J18: 31 March 2023 | L18: Insiders Own | M18: 0
B19: Market Cap. | C19: =C17*C18/1000000 -> 7324317 | D19: Cash/Share | E19: =_xlfn.XLOOKUP("Cash & Eq.",'Fin. Data'!A:A,'Fin. Data'!B:B,,0)*1000000/C18 -> 2110.3697 | F19: =Segments!C6 -> U.S. | H19: =Segments!B6 -> 0.32022948 | I19: EBITDA | K19: =_xlfn.XLOOKUP(I19,'Fin. Data'!A:A,'Fin. Data'!B:B,,0) -> 537584 | L19: b (Yahoo) | M19: 0.9
B20: +Total Debt | C20: ='Fin. Data'!B58 -> 813766 | D20: EBIDTA/Net Financial Cost (NFC) | E20: ='Fin. Data (Common Size)'!B19/(-'Fin. Data (Common Size)'!B14) -> 61.578923 | F20: =Segments!C9 -> Europe | H20: =Segments!B9 -> 0.17800765 | I20: Depreciation & Amortization | K20: =_xlfn.XLOOKUP(I20,'Fin. Data'!A:A,'Fin. Data'!B:B,,0) -> 182224 | L20: Score (Moodys) | M20: A2
B21: -Cash | C21: ='Fin. Data'!B39 -> 617663 | D21: Debt/EBITDA | E21: =_xlfn.XLOOKUP("Total Debt",'Fin. Data'!A:A,'Fin. Data'!B:B,,0)/_xlfn.XLOOKUP("EBITDA",'Fin. Data'!A:A,'Fin. Data'!B:B,,0) -> 1.5137467 | F21: =Segments!C10 -> Asian and Oceania | H21: =Segments!B10 -> 0.14577092 | I21: EBIT | K21: =_xlfn.XLOOKUP(I21,'Fin. Data'!A:A,'Fin. Data'!B:B,,0) -> 355360 | L21: Price/Book Value | M21: =IFERROR((C17*C18/(E17-E18))/1000000,"") -> 3.27249
B22: =Enterprise Value | C22: =C19+C20-C21 -> 7520420 | D22: "Others Assets"/Asset | E22: =_xlfn.XLOOKUP("Other Assets",'Fin. Data'!A:A,'Fin. Data'!B:B,,0)/_xlfn.XLOOKUP("Total Assets",'Fin. Data'!A:A,'Fin. Data'!B:B,,0) -> 0.21323509 | F22: =Segments!C11 -> China | H22: =Segments!B11 -> 0.12269915 | I22: Net Income | K22: =_xlfn.XLOOKUP(I22,'Fin. Data'!A:A,'Fin. Data'!B:B,,0) -> 257755 | L22: NCF(3y avg)/Asset | M22: =IFERROR(K28/E17,"") -> -0.00051088037
B23: Holdings (nac/int'l) | C23: - | D23: Debt/Assets | E23: =_xlfn.XLOOKUP(D23,'Fin. Data'!A:A,'Fin. Data'!B:B,,0) -> 0.189086 | F23: =Segments!C12 -> Other | H23: =Segments!B12 -> 0.061469127 | I23: EPS | K23: =1000000*K22/C18 -> 880.67172 | L23: Price/Net Inc. (3y avg) | M23: =IFERROR(C19/K27,"") -> 34.783013
B24: t liq. (Holdings/Vol.) | C24: - | D24: EBITDA Margin (average) | E24: =AVERAGE(_xlfn.XLOOKUP("EBITDA Margin",'Fin. Data'!A:A,'Fin. Data'!B:D,,0)) -> 0.14402521 | F24: Categories | H24: % Sales | I24: ROA | K24: =K22/E17 -> 0.059891739 | L24: EV/Asset | M24: =IFERROR(C22/E17,"") -> 1.7474386
B25: % Short | C25: N/A | D25: Operating Margin (average) | E25: =AVERAGE(_xlfn.XLOOKUP("Operating Margin",'Fin. Data'!A:A,'Fin. Data'!B:D,,0)) -> 0.095731488 | F25: =Segments!C18 -> Air Conditioning | H25: =Segments!B18 -> 0.91218284 | I25: ROIC | K25: =K22/(E17-(E18-C20)) -> 0.084456836 | L25: EV/Ebidta (3y average) | M25: =IFERROR(C22/K26,"") -> 16.500737
B26: Traffic ESG | D26: Net Income Margin (average) | E26: =AVERAGE(_xlfn.XLOOKUP("Net Income Margin",'Fin. Data'!A:A,'Fin. Data'!B:D,,0)) -> 0.065808676 | F26: =Segments!C19 -> Chemicals | H26: =Segments!B19 -> 0.071565775 | I26: EBITDA (3y average) | K26: =AVERAGE(_xlfn.XLOOKUP("EBITDA",'Fin. Data'!A:A,'Fin. Data'!B:D,,0)) -> 455762.67 | L26: Price/NCF (3y average) | M26: =IFERROR(C19/K28,"") -> -3331.2539
B27: E | F27: =Segments!C20 -> Others | H27: =Segments!B20 -> 0.022603155 | I27: Net Income (3y average) | K27: =AVERAGE(_xlfn.XLOOKUP("Net Income",'Fin. Data'!A:A,'Fin. Data'!B:D,,0)) -> 210571.67 | L27: Bonds 1,3,5a (USD) | M27: -
B28: S | D28: Net Financial Cost/Avg Net Debt | E28: =-_xlfn.XLOOKUP("Net Financial Cost",'Fin. Data'!A:A,'Fin. Data'!B:B,,0)/AVERAGE(_xlfn.XLOOKUP("Net Debt",'Fin. Data'!A:A,'Fin. Data'!B:D,,0)) -> -0.11778727 | F28: =Segments!C21 -> Eliminations and Corporate | H28: =Segments!B21 -> -0.006351769 | I28: NFC (3y average) | K28: =AVERAGE(_xlfn.XLOOKUP("Net Financial Cost",'Fin. Data'!A:A,'Fin. Data'!B:D,,0)) -> -2198.6667 | L28: Div+Rep.(3y avg)/Price | M28: =-IFERROR(SUM(E51:E53)/(3*C19),"") -> 0.0071877009
B29: G | L29: Div. Yield | M29: =-IFERROR(L52/C19,"") -> 0.0083923184
B30: INVESTMENT THESIS
B31: Pillars of Recommendation | H31: Recommendation | I31: Valuation Assumptions
B32: Pillar | C32: Explanation | H32: HOLD | I32: CHECK DCF
B33: Market Leadership | C33: Daikin is the world's biggest AC manufacturer (segment represents 91% of revenue FY 2022) and has a very consolidated position with an envious 12% global market share
B34: Energy transition | C34: Daikin is specially well positioned to seize the added value generated by switching from higher polluting items to more eco-friendly ones. Specially in the HC segment (Within AC) which is forecasted to grow by a considerable amount in the near future
B35: AI and Machine Learning | C35: Daikin is already developing several AI and machine learning solutions to some problems reported by consumer and in-house feedback and since it has better and with more value added products and spends a bigger percentage of revenue in R&D than the average of it's peers, it's well positioned to take advantage of the current and following AI booms
B36: Fusion 25 | C36: Daikin's Fusion 25 company strategy is showing incredible results surpassing every forecast and strenghtenning Daikin's reputation for delivering results. Plus it has more objectives that we feel have a very good impact on the companies' outlook
B37: Risks of Investment | H37: Price Target | I37: Valuation
B38: Risk | C38: Explanation | H38: =DCF!D75 -> 13800.241 | I38: Discount Rate | J38: =DCF!F50 -> 0.0948598 | L38: Upside | M38: =DCF!D74 -> -0.4485418
B39: Low brand recognition | C39: Daikin's low brand recognition means that they lose customers run to peers that are more focused on marketing on the long
B40: Higher cost products compared to peers | C40: Daikin's higher prices reflect their superior products. However, because the AC market is not commonly known as a "premium items" market, people have a hard time justifying choosing a Daikin product over, say, a Carrier one.
B41: Hard time penetrating in new markets | C41: Because of the previous two risks of investment, Daikin has had a hard time penetrating new markets. Most notably the North American one. They solved this problem through several acquisitions and extensive Capex and now the US market is one of their biggest growth drivers. However the difficulty Daikin has in entering new markets should be noted. Especially when they plan to do so, for example in India.
B42: Valuation | C42: According to the DCF analysis, the company seems to be highly overvalued. However it should be noted that we feel like this is due to overall overvaluation of the market as a whole and is not specific to Daikin or it's industry
B43: FINANCIAL PERFORMANCE
B44: Year | C44: Net Sales | D44: Operating Margin | E44: Dividends + Share Buyback | F44: Net Cash Flow | G44: Debt/Assets | H44: Depreciation & Amortization | I44: Capex + Investments | J44: Cash Flow
B45: =B46-1 -> 2014 | C45: {=_xlfn.SORTBY(TRANSPOSE(_xlfn.XLOOKUP(C$44,'Fin. Data'!$A:$A,'Fin. Data'!$B:$J,,0)),$B$45:$B$53,-1)} -> 1915013 | D45: {=_xlfn.SORTBY(TRANSPOSE(_xlfn.XLOOKUP(D$44,'Fin. Data'!$A:$A,'Fin. Data'!$B:$J,,0)),$B$45:$B$53,-1)} -> 0.096757046 | E45: {=_xlfn.SORTBY(TRANSPOSE(_xlfn.XLOOKUP(E$44,'Fin. Data'!$A:$A,'Fin. Data'!$B:$J,,0)),$B$45:$B$53,-1)} -> -19545 | F45: =Inputs!J77 -> 29656 | G45: {=_xlfn.SORTBY(TRANSPOSE(_xlfn.XLOOKUP(G$44,'Fin. Data'!$A:$A,'Fin. Data'!$B:$J,,0)),$B$45:$B$53,-1)} -> 0.27535514 | H45: {=_xlfn.SORTBY(TRANSPOSE(_xlfn.XLOOKUP(H$44,'Fin. Data'!$A:$A,'Fin. Data'!$B:$J,,0)),$B$45:$B$53,-1)} -> 77766 | I45: {=_xlfn.SORTBY(TRANSPOSE(_xlfn.XLOOKUP(I$44,'Fin. Data'!$A:$A,'Fin. Data'!$B:$J,,0)),$B$45:$B$53,-1)} -> -72763 | L45: =J17 -> 2022 | M45: =L45-1 -> 2021
B46: =B47-1 -> 2015 | C46: 2043691 | D46: 0.10543962 | E46: -33567 | F46: =Inputs!I77 -> 4255 | G46: 0.24464277 | H46: 84202 | I46: -102825 | J46: Net Income | L46: =_xlfn.XLOOKUP($J46,'Fin. Data'!$A:$A,'Fin. Data'!B:B,,0) -> 257755 | M46: =_xlfn.XLOOKUP($J46,'Fin. Data'!$A:$A,'Fin. Data'!C:C,,0) -> 217710 | N46: =(C46/C45)-1 -> 0.067194322 | O46: =(D46/D45)-1 -> 0.089735825 | Q46: =F46/F45-1 -> -0.85652145 | R46: =H46/H45-1 -> 0.082761104 | S46: =I46/I45-1 -> 0.41314954
B47: =B48-1 -> 2016 | C47: 2043968 | D47: 0.11292398 | E47: -36518 | F47: =Inputs!H77 -> 52888 | G47: 0.22589837 | H47: 85029 | I47: -120363 | J47: Operating CF | L47: =_xlfn.XLOOKUP($J47,'Fin. Data'!$A:$A,'Fin. Data'!B:B,,0) -> 158326 | M47: =_xlfn.XLOOKUP($J47,'Fin. Data'!$A:$A,'Fin. Data'!C:C,,0) -> 243485 | N47: =(C47/C46)-1 -> 0.00013553908 | O47: =(D47/D46)-1 -> 0.070982431 | Q47: =F47/F46-1 -> 11.429612 | R47: =H47/H46-1 -> 0.0098216194 | S47: =I47/I46-1 -> 0.17056163
B48: =B49-1 -> 2017 | C48: 2290560 | D48: 0.10949986 | E48: -39473 | F48: =Inputs!G77 -> 12933 | G48: 0.19282605 | H48: 94833 | I48: -122150 | J48: Investing CF | L48: =_xlfn.XLOOKUP($J48,'Fin. Data'!$A:$A,'Fin. Data'!B:B,,0) -> -229793 | M48: =_xlfn.XLOOKUP($J48,'Fin. Data'!$A:$A,'Fin. Data'!C:C,,0) -> -180789 | N48: =(C48/C47)-1 -> 0.12064377 | O48: =(D48/D47)-1 -> -0.030322337 | Q48: =F48/F47-1 -> -0.75546438 | R48: =H48/H47-1 -> 0.11530184 | S48: =I48/I47-1 -> 0.014846755
B49: =B50-1 -> 2018 | C49: 2481109 | D49: 0.11094192 | E49: -42407 | F49: =Inputs!F77 -> 10163 | G49: 0.18262647 | H49: 99315 | I49: -159724 | J49: Net Capex | L49: =_xlfn.XLOOKUP($J49,'Fin. Data'!$A:$A,'Fin. Data'!B:B,,0) -> -175076 | M49: =_xlfn.XLOOKUP($J49,'Fin. Data'!$A:$A,'Fin. Data'!C:C,,0) -> -114106 | N49: =(C49/C48)-1 -> 0.083188827 | O49: =(D49/D48)-1 -> 0.013169526 | Q49: =F49/F48-1 -> -0.21418078 | R49: =H49/H48-1 -> 0.047262029 | S49: =I49/I48-1 -> 0.3076054
B50: =B51-1 -> 2019 | C50: 2550305 | D50: 0.094754941 | E50: -49730 | F50: =Inputs!E77 -> -46037 | G50: 0.1679104 | H50: 128485 | I50: -139379 | J50: Investments & Acquisitions | L50: =_xlfn.XLOOKUP($J50,'Fin. Data'!$A:$A,'Fin. Data'!B:B,,0) -> -34920 | M50: =_xlfn.XLOOKUP($J50,'Fin. Data'!$A:$A,'Fin. Data'!C:C,,0) -> -46221 | N50: =(C50/C49)-1 -> 0.027889142 | O50: =(D50/D49)-1 -> -0.14590499 | Q50: =F50/F49-1 -> -5.5298632 | R50: =H50/H49-1 -> 0.29371193 | S50: =I50/I49-1 -> -0.12737597
B51: =B52-1 -> 2020 | C51: 2493386 | D51: 0.095423252 | E51: -46721 | F51: =Inputs!D77 -> 341116 | G51: 0.20833408 | H51: 133593 | I51: -148342 | J51: Financing CF | L51: =_xlfn.XLOOKUP($J51,'Fin. Data'!$A:$A,'Fin. Data'!B:B,,0) -> -113088 | M51: =_xlfn.XLOOKUP($J51,'Fin. Data'!$A:$A,'Fin. Data'!C:C,,0) -> -48698 | N51: =(C51/C50)-1 -> -0.022318507 | O51: =(D51/D50)-1 -> 0.0070530431 | Q51: =F51/F50-1 -> -8.4096053 | R51: =H51/H50-1 -> 0.039755613 | S51: =I51/I50-1 -> 0.064306675
B52: =B53-1 -> 2021 | C52: 3109106 | D52: 0.10012589 | E52: -49746 | F52: =Inputs!C$77 -> 55536 | G52: 0.12041 | H52: 148062 | I52: -160327 | J52: Dividends | L52: =_xlfn.XLOOKUP($J52,'Fin. Data'!$A:$A,'Fin. Data'!B:B,,0) -> -61468 | M52: =_xlfn.XLOOKUP($J52,'Fin. Data'!$A:$A,'Fin. Data'!C:C,,0) -> -49746 | N52: =(C52/C51)-1 -> 0.24694131 | O52: =(D52/D51)-1 -> 0.049281872 | Q52: =F52/F51-1 -> -0.83719321 | R52: =H52/H51-1 -> 0.10830657 | S52: =I52/I51-1 -> 0.080793032
B53: =J17 -> 2022 | C53: 3981578 | D53: 0.091645323 | E53: -61468 | F53: =Inputs!B77 -> -169559 | G53: 0.189086 | H53: 182224 | I53: -209996 | J53: Share Buyback | L53: =_xlfn.XLOOKUP($J53,'Fin. Data'!$A:$A,'Fin. Data'!B:B,,0) -> 0 | M53: =_xlfn.XLOOKUP($J53,'Fin. Data'!$A:$A,'Fin. Data'!C:C,,0) -> 0 | N53: =(C53/C52)-1 -> 0.28061829 | O53: =(D53/D52)-1 -> -0.084699031 | Q53: =F53/F52-1 -> -4.0531367 | R53: =H53/H52-1 -> 0.23072767 | S53: =I53/I52-1 -> 0.3097981
B54: Annual Growth Rate | C54: =IFERROR((C53/C45)^(1/8)-1,"") -> 0.09581045 | D54: =IFERROR((D53/D45)^(1/8)-1,"") -> -0.006761688 | F54: =IFERROR((F53/F45)^(1/8)-1,"") | H54: =IFERROR((H53/H45)^(1/8)-1,"") -> 0.11231291 | J54: FX | L54: =_xlfn.XLOOKUP($J54,'Fin. Data'!$A:$A,'Fin. Data'!B:B,,0) -> 14996 | M54: =_xlfn.XLOOKUP($J54,'Fin. Data'!$A:$A,'Fin. Data'!C:C,,0) -> 41538
B55: Average Growth Rate | C55: =IFERROR(AVERAGE(N46:N53),"") -> 0.10053659 | D55: =IFERROR(AVERAGE(O46:O53),"") -> -0.0038379582 | F55: =IFERROR(AVERAGE(Q46:Q53),"") -> -1.1532941 | H55: =IFERROR(AVERAGE(S46:S53),"") -> 0.15421065 | J55: Changes in Cash | L55: =L47-L48+L51-L52-L53 -> 336499 | M55: =M47-M48+M51-M52-M53 -> 425322
B56: CVAR | C56: =IFERROR(STDEV(C46:C53)/AVERAGE(C46:C53),"") -> 0.24551172 | D56: =IFERROR(STDEV(D45:D53)/AVERAGE(D45:D53),"") -> 0.077649441 | F56: =IFERROR(STDEV(F45:F53)/AVERAGE(F45:F53),"") -> 4.1626711 | H56: =IFERROR(STDEV(H45:H53)/AVERAGE(H45:H53),"") -> 0.30827103 | J56: Inventory/D Revenues | L56: =IFERROR(SUM(I50:I53)/(C53-C49),"") -> -0.43855888 | M56: =IFERROR((SUM(I50:I53)-SUM(H50:H53))/(C53-C49),"") -> -0.83334477
B57: Last Year | C57: =IFERROR(C53/C52-1,"") -> 0.28061829 | D57: =IFERROR(1-(D53/D52),"") -> 0.084699031 | F57: =IFERROR(1-(F53/F52),"") -> 4.0531367 | H57: =IFERROR(1-(H53/H52),"") -> -0.23072767 | J57: t inversiones; t adq. neto dep. | L57: =IFERROR(L56/E24,"") -> -3.0450147 | M57: =IFERROR(M56/E24,"") -> -5.7861037
B58: QUALITATIVE ANALYSIS
B59: SWOT ANALYSIS | J59: HOLDERS
B60: Pros | E60: Cons | J60: Name | M60: % Stake
B61: Number of Acquisitions: Daikin has always been successful in a number of acquisitions including its acquiring McQuay International, OYL Industries etc. These acquisitions made Daikin Industries, which made the company a major global HVAC manufacturer. Frequent Quality Inspection: Energizing the new examination guarantees the capacity to adjust tactile components, for example, light and smell. They will keep on recognizing potential open doors and look for arrangements to make the world’s spaces more joyful and more aDaikinable. Innovations: As the forerunner in India’s heating, ventilation, and cooling (HVAC) fragment, they are figuring out and embracing new systems. Future Expansions: Their momentum fabricating limits combined with nearby exploration and improvement will guarantee that they serve new business sectors and new topographies like Sri Lanka, Bangladesh and East Africa. Strong Brand Network: Selling products in over 130 countries including operations in Japan, China, Australia, United States, India, Southeast Asia, Europe, Middle East, Latin America, and Africa. Huge Manpower Force: With an employee force of around 80,000+, Daikin is among the top Air conditioning products providers in the world. | E61: High Prices: As compared to its competitors, Daikin products price seems somehow on a higher side which makes the purchasing customer feel that Daikin is overpriced. Marketing Not Up to the Mark: Daikin is not very good at promoting its products as compared to its competitors. It is very hard for its customers to recall the brand name due to Daikin’s low promotion strategy. Zero Presence in Other Segments: Daikin is the major seller of air conditioners, ventilation systems and ducted-Ac, it has zero to no presence in other segments like refrigerators, Microwave ovens, small kitchens appliances etc. where its competitors like Voltas and IFB are playing very well. Lack of Differentiation: The consumer electronics sector is saturated with brands that clone each other’s products, and there is nothing that can be done to differentiate between them. Daikin, too, is lacking in distinctiveness. Dependency: The corporation is heavily reliant on the Japanese market, as well as some Asian regions. As a result, it loses market share to other brands in other countries, as well as revenue opportunities. | J61: Nomura Asset Management Co., Ltd. | M61: 0.0585
J62: Sumitomo Mitsui Banking Corp | M62: 0.0307
J63: Nikko Asset Management Co., Ltd. | M63: 0.028
J64: Daiwa Asset Management Co., Ltd. | M64: 0.0275
J65: Mitsubishi UFJ Trust and Banking Corporation | M65: 0.0247
J66: The Vanguard Group, Inc. | M66: 0.0247
J67: BlackRock Japan Co., Ltd. | M67: 0.0205
J68: Norges Bank Investment Management (NBIM) | M68: 0.0181
J69: MUFG Bank, Ltd. | M69: 0.0158
J70: Mitsubishi UFJ Kokusai Asset Management Co., Ltd. | M70: 0.0155
B71: Opportunities | E71: Risks | J71: BlackRock Fund Advisors | M71: 0.0153
B72: Technological Advancement: The need for Air moulding is expanding among clients everywhere, this is a gigantic chance for Daikin to use upon. Increase the Depth of Product Portfolio: One of the potentials for Daikin is to increase the depth of its product portfolio. It will be able to sell additional things to its already large consumer base. Emerging Markets: Daikin has the opportunity to focus on developing and emerging markets, particularly in Africa and Asia. These expanding markets can assist Daikin in establishing its brand in a new area, hence increasing revenue. Introducing Small Appliances: Daikin is well recognized for its large appliances and household appliances. However, there are a number of small appliances that are not included in Daikin’s product line. LG has already done this, and Daikin can do the same to broaden its intended consumer base and provide additional items under its brand. Skilled Labour: The number of skilled workers accessible in the country has expanded as a result of increasing education and training given by different institutes. This means Daikin will have to spend less on training and development if it can hire skilled labour, resulting in cost savings. | E72: Mature Markets: The Japanese and other Asian markets are mature markets with many brands present and well-established. As a result, establishing a presence in these areas is becoming increasingly challenging. Intense Competition: The severe rivalry in this industry is a big issue for Daikin. As a result, rival brands are stealing market share from Daikin, and revenue is stagnating. The competition will not subside in the near future. As a result, Daikin must consider other income and profit-generating opportunities. Dropping Margins: Dropping margins pose a serious threat to Daikin because they directly jeopardize the company’s expansion and survival. Shortage of Skilled Human Resources: Due to significant employee turnover and a growing reliance on creative solutions, the company name may experience a shortage of skilled human resources shortly. Saturation in Urban Markets & Stagnation in Rural Markets: This is an ongoing concern for Daikin in its area. One of the causes is that product acceptance is slow in the rural market. Second, due to the wide distances and lack of infrastructure, serving rural clients is more expensive for Daikin than serving urban ones. | J72: Capital Research Global Investors | M72: 0.0147
J73: Sumitomo Life Insurance Co. | M73: 0.0123
J74: Sumitomo Realty & Development Co Ltd | M74: 0.0123
J75: Capital World Investors | M75: 0.0121
J76: BlackRock Institutional Trust Company, N.A. | M76: 0.0116
J77: MFS Investment Management | M77: 0.0114
J78: BlackRock Asset Management Ireland Limited | M78: 0.007
J79: BlackRock Advisors (UK) Limited | M79: 0.0065
J80: DWS Investment GmbH | M80: 0.0058
B81: NOTES | G81: STOCK PERFORMANCE (5 years)
B82: Sales in over 170 countries; 76 thousand employees
G106: =E2 -> Daikin Industries,Ltd. (6367.T) | I106: =Peers!D7 -> #VALUE! | J106: =Peers!E7 -> #VALUE! | K106: =Peers!F7 -> #VALUE! | L106: =Peers!G7 -> #VALUE!
D109: Operating and Net Margins (nyu.edu) | E109: Industry Averages
D111: Comparing Average Dividend Yield by Sector - Dividend.com | F111: Dividend Yield Industry Averages

Sheet Segments
B2: ="Regions "&"("&OP!$J$17&")" -> Regions (2022) | Q2: Products
D3: Nominal value | K3: YoY Growth
B4: Weight | C4: Region | D4: =OP!J17 -> 2022 | E4: =D4-1 -> 2021 | F4: =E4-1 -> 2020 | G4: =F4-1 -> 2019 | H4: =G4-1 -> 2018 | I4: =H4-1 -> 2017 | K4: =OP!J17 -> 2022 | L4: =K4-1 -> 2021 | M4: =L4-1 -> 2020 | N4: =M4-1 -> 2019 | O4: =N4-1 -> 2018 | P4: =O4-1 -> 2017
B5: =IFERROR(D5/$D$13,"") -> 0.17182367 | C5: Japan | D5: 684129 | E5: 638447 | F5: 585573 | G5: 596978 | H5: 585106 | I5: 542725 | K5: =(D5-E5)/E5 -> 0.07155175 | L5: =(E5-F5)/F5 -> 0.090294464 | M5: =(F5-G5)/G5 -> -0.019104557 | N5: =(G5-H5)/H5 -> 0.020290341 | O5: =(H5-I5)/I5 -> 0.078089272 | P5: =(I5-518453)/518453 -> 0.046816201
B6: =IFERROR(D6/$D$13,"") -> 0.32022948 | C6: U.S. | D6: 1275018 | E6: 840455 | F6: 641295 | G6: 666305 | H6: 625041 | I6: 551819 | K6: =(D6-E6)/E6 -> 0.51705683 | L6: =(E6-F6)/F6 -> 0.3105591 | M6: =(F6-G6)/G6 -> -0.037535363 | N6: =(G6-H6)/H6 -> 0.066018069 | O6: =(H6-I6)/I6 -> 0.13269206 | P6: =(I6-503489)/503489 -> 0.095990181
B7: =IFERROR(D7/$D$13,"") -> 0 | K7: =(D7-E7)/E7 -> #DIV/0! | L7: =(E7-F7)/F7 -> #DIV/0! | M7: =(F7-G7)/G7 -> #DIV/0! | N7: =(G7-H7)/H7 -> #DIV/0! | O7: =(H7-I7)/I7 -> #DIV/0!
B8: =IFERROR(D8/$D$13,"") -> 0 | K8: =(D8-E8)/E8 -> #DIV/0! | L8: =(E8-F8)/F8 -> #DIV/0! | M8: =(F8-G8)/G8 -> #DIV/0! | N8: =(G8-H8)/H8 -> #DIV/0! | O8: =(H8-I8)/I8 -> #DIV/0!
B9: =IFERROR(D9/$D$13,"") -> 0.17800765 | C9: Europe | D9: 708751 | E9: 553214 | F9: 417225 | G9: 405610 | H9: 366670 | I9: 332955 | K9: =(D9-E9)/E9 -> 0.2811516 | L9: =(E9-F9)/F9 -> 0.32593684 | M9: =(F9-G9)/G9 -> 0.028635882 | N9: =(G9-H9)/H9 -> 0.10619903 | O9: =(H9-I9)/I9 -> 0.10125993 | P9: =(I9-274054)/274054 -> 0.2149248
B10: =IFERROR(D10/$D$13,"") -> 0.14577092 | C10: Asian and Oceania | D10: 580398 | E10: 426107 | F10: 351044 | G10: 395461 | H10: 387092 | I10: 349189 | K10: =(D10-E10)/E10 -> 0.3620945 | L10: =(E10-F10)/F10 -> 0.2138279 | M10: =(F10-G10)/G10 -> -0.11231702 | N10: =(G10-H10)/H10 -> 0.021620183 | O10: =(H10-I10)/I10 -> 0.1085458 | P10: =(I10-303416)/303416 -> 0.15085889
B11: =IFERROR(D11/$D$13,"") -> 0.12269915 | C11: China | D11: 488536 | E11: 478121 | F11: 369818 | G11: 341284 | H11: 379628 | I11: 381665 | K11: =(D11-E11)/E11 -> 0.021783189 | L11: =(E11-F11)/F11 -> 0.29285486 | M11: =(F11-G11)/G11 -> 0.083607787 | N11: =(G11-H11)/H11 -> -0.10100414 | O11: =(H11-I11)/I11 -> -0.0053371412 | P11: =(I11-329247)/329247 -> 0.1592057
B12: =IFERROR(D12/$D$13,"") -> 0.061469127 | C12: Other | D12: 244744 | E12: 172758 | F12: 128429 | G12: 144665 | H12: 137570 | I12: 132204 | K12: =(D12-E12)/E12 -> 0.41668693 | L12: =(E12-F12)/F12 -> 0.34516348 | M12: =(F12-G12)/G12 -> -0.11223171 | N12: =(G12-H12)/H12 -> 0.051573744 | O12: =(H12-I12)/I12 -> 0.040588787 | P12: =(I12-115307)/115307 -> 0.14653924
B13: =SUM(B5:B12) -> 1 | C13: TOTAL | D13: =SUM(D5:D12) -> 3981576 | E13: =SUM(E5:E12) -> 3109102 | F13: =SUM(F5:F12) -> 2493384 | G13: =SUM(G5:G12) -> 2550303 | H13: =SUM(H5:H12) -> 2481107 | I13: =SUM(I5:I12) -> 2290557 | K13: =(D13-E13)/E13 -> 0.28061929 | L13: =(E13-F13)/F13 -> 0.2469407 | M13: =(F13-G13)/G13 -> -0.022318525 | N13: =(G13-H13)/H13 -> 0.027889164 | O13: =(H13-I13)/I13 -> 0.083189373 | P13: 0.037
B15: ="Categories "&"("&OP!$J$17&")" -> Categories (2022)
D16: Nominal value | K16: YoY Growth
B17: Weight | C17: Category | D17: =OP!J17 -> 2022 | E17: =D17-1 -> 2021 | F17: =E17-1 -> 2020 | G17: =F17-1 -> 2019 | H17: =G17-1 -> 2018 | I17: =H17-1 -> 2017 | K17: =OP!J17 -> 2022 | L17: =K17-1 -> 2021 | M17: =L17-1 -> 2020 | N17: =M17-1 -> 2019 | O17: =N17-1 -> 2018 | P17: =O17-1 -> 2017
B18: =IFERROR(D18/$D$22,"") -> 0.91218284 | C18: Air Conditioning | D18: 3631918 | E18: 2830662 | F18: 2275497 | G18: 2309986 | H18: 2222886 | I18: 2053469 | K18: =(D18-E18)/E18 -> 0.28306311 | L18: =(E18-F18)/F18 -> 0.24397527 | M18: =(F18-G18)/G18 -> -0.014930394 | N18: =(G18-H18)/H18 -> 0.039183296 | O18: =(H18-I18)/I18 -> 0.082502828 | P18: =(I18-1835764)/1835764 -> 0.11859095
B19: =IFERROR(D19/$D$22,"") -> 0.071565775 | C19: Chemicals | D19: 284944 | E19: 224643 | F19: 173782 | G19: 193733 | H19: 218913 | I19: 198535 | K19: =(D19-E19)/E19 -> 0.26843035 | L19: =(E19-F19)/F19 -> 0.29267128 | M19: =(F19-G19)/G19 -> -0.10298194 | N19: =(G19-H19)/H19 -> -0.11502286 | O19: =(H19-I19)/I19 -> 0.10264185 | P19: =(I19-169019)/169019 -> 0.17463125
B20: =IFERROR(D20/$D$22,"") -> 0.022603155 | C20: Others | D20: 89996 | E20: 69357 | F20: 56281 | G20: 62002 | H20: 58791 | I20: 54957 | K20: =(D20-E20)/E20 -> 0.29757631 | L20: =(E20-F20)/F20 -> 0.23233418 | M20: =(F20-G20)/G20 -> -0.092271217 | N20: =(G20-H20)/H20 -> 0.054617203 | O20: =(H20-I20)/I20 -> 0.069763633 | P20: =(I20-52357)/52357 -> 0.049659071
B21: =IFERROR(D21/$D$22,"") -> -0.006351769 | C21: Eliminations and Corporate | D21: -25290 | E21: -15566 | F21: -12175 | G21: -15418 | H21: -19483 | I21: -16401 | K21: =(D21-E21)/E21 -> 0.62469485 | L21: =(E21-F21)/F21 -> 0.27852156 | M21: =(F21-G21)/G21 -> -0.21033857 | N21: =(G21-H21)/H21 -> -0.20864343 | O21: =(H21-I21)/I21 -> 0.18791537 | P21: =(I21--13173)/-13173 -> 0.24504669
B22: =SUM(B18:B21) -> 1 | C22: TOTAL | D22: =SUM(D18:D21) -> 3981568 | E22: =SUM(E18:E21) -> 3109096 | F22: =SUM(F18:F21) -> 2493385 | G22: =SUM(G18:G21) -> 2550303 | H22: =SUM(H18:H21) -> 2481107 | I22: =SUM(I18:I21) -> 2290560 | K22: =(D22-E22)/E22 -> 0.28061919 | L22: =(E22-F22)/F22 -> 0.2469378 | M22: =(F22-G22)/G22 -> -0.022318132 | N22: =(G22-H22)/H22 -> 0.027889164 | O22: =(H22-I22)/I22 -> 0.083187954 | P22: 0.037
B24: Categories | D24: Description | I24: Graphs
B25: Air Conditioning | D25: Engaged in the manufacture (including installation work) and sale of air-conditioning and refrigeration equipment
B26: Chemicals | D26: Engaged in the manufacture and sale of chemicals
B28: Others | D28: “Others” segment is a business segment not included in reported segments. It includes the oil hydraulic equipment business, the defense systems business, and the electronics business
B29: Eliminations and Corporate | D29: Intersegment revenue
B32: Industry | J32: Graphs (Industry Forecasts)
B33: Drivers | D33: Description | J33: Forecast of the global heating & cooling market revenue from 2018 to 2028(in billion U.S. dollars)
B34: Weather and climate patterns- Global Warming | D34: Long-term shifts in temperatures and weather patterns leads to higher demand in HVAC
B35: Population growth and urbanization | D35: Population growth lead to higher demand for housing and infrastructure. With more people living and working in urban areas, there is a greater need for HVAC installations in various buildings, such as apartments, offices, schools, hospitals, and shopping malls
B36: Energy transition- Government policies and regulations | D36: Sustainable heating, cooling and refrigeration solutions. Ex. Carbon pricing mechanisms or carbon taxes to put a cost on carbon emissions. This encourages businesses and consumers to choose energy-efficient HVAC options to minimize their carbon footprint and reduce their tax burden.
B37: Sales forecast
B38: Source | D38: Market Growth CGAR | G38: Period
B39: Statista | D39: 0.0308 | G39: 2023-2028
B40: Grand View Research | D40: 0.062 | G40: 2021-2028
B41: Mordor Intelligence | D41: 0.0608 | G41: 2023-2028
B42: GlobeNewswire | D42: 0.06 | G42: 2022-2032
B43: Company's Strategy / Extra Notes
B44: FUSION 25
S48: B2B or B2C ?
T49: Japan | U49: U.S. | V49: Europe | W49: Asia and Oceania | X49: China | Y49: Total
S50: % sales | T50: =B5 -> 0.17182367 | U50: =B6 -> 0.32022948 | V50: =B9 -> 0.17800765 | W50: =B10 -> 0.14577092 | X50: =B11 -> 0.12269915 | Y50: =SUM(T50:X50) -> 0.93853087
S51: B2B | T51: =1-T52 -> 0.7 | U51: =1-U52 -> 0.45 | V51: =1-V52 -> 0.6 | W51: =1-W52 -> 0.4 | X51: =1-X52 -> 0.45
S52: B2C | T52: 0.3 | U52: 0.55 | V52: 0.4 | W52: 0.6 | X52: 0.55
S53: TOTAL B2B | T53: =T50*T51 -> 0.12027657 | U53: =U50*U51 -> 0.14410326 | V53: =V50*V51 -> 0.10680459 | W53: =W50*W51 -> 0.058308368 | X53: =X50*X51 -> 0.055214619 | Y53: =SUM(T53:X53) -> 0.48470741
S54: TOTAL B2C | T54: =T52*T50 -> 0.051547101 | U54: =U52*U50 -> 0.17612621 | V54: =V52*V50 -> 0.071203061 | W54: =W52*W50 -> 0.087462553 | X54: =X52*X50 -> 0.067484534 | Y54: =SUM(T54:X54) -> 0.45382346
J58: Source: Statista
B70: =AVERAGE(D39:F42) -> 0.0534

Sheet Acuerdo
A1: Invertir
A2: NO invertir
A3: Mantener sin elevar posición
A4: Mantener (y seguir comprando)
A5: Liquidar
A6: PENDIENTE

Sheet Peers
B1: Peer Logo | C1: Peer Name | D1: Description
C2: =D7 -> #VALUE! | D2: {=_FV(C2,"Description")} -> Johnson Controls International plc offers smart, healthy and sustainable buildings, serving a range of customers. It operates through four segments: Building Solutions North America, Building Solutions EMEA/LA, Building Solutions Asia Pacific, and Global Products. Its Building Solutions North America, Building Solutions EMEA/LA, and Building Solutions Asia Pacific segments design, sell, install, and services heating, ventilation and air conditioning (HVAC), controls, building management, refrigeration, integrated electronic security, integrated fire detection and suppression systems, and provides technical services. Its Global Products segment designs, manufactures and sells HVAC equipment, controls software and software services for residential and commercial applications to commercial, industrial, retail, residential, small business, institutional and governmental customers worldwide. Global Products segment also designs, manufactures and sells refrigeration equipment and controls.
C3: =E7 -> #VALUE! | D3: {=_FV(C3,"Description")} -> Carrier Global Corporation is engaged in offering intelligent climate and energy solutions with a focus on providing differentiated, digitally enabled lifecycle solutions. The Company operates through three segments: HVAC, Refrigeration, and Fire & Security. Its HVAC segment provides products, controls, services and solutions to meet the heating, cooling and ventilation needs of residential and commercial customers. Its Refrigeration segment includes transport refrigeration and monitoring products, services and digital solutions for trucks, trailers, shipping containers, and intermodal and rail. Its Fire & Security segment provides a range of residential, commercial and industrial technologies designed to help protect people and property. This segment offers products, such as fire, flame, gas, smoke and carbon monoxide detection, portable fire extinguishers, and others. The Company's portfolio includes brands, such as Carrier, Carrier Transicold, Viessmann, and others.
C4: =F7 -> #VALUE! | D4: {=_FV(C4,"Description")} -> Trane Technologies PLC is a global climate innovator. Through its brands, such as Trane and Thermo King, and its portfolio of products and services, it brings climate solutions to buildings, homes, and transportation. Its segments include the Americas, EMEA and Asia Pacific. Its Americas segment serves customers in North America and Latin America and includes commercial heating and cooling systems, building controls, and energy services and solutions; residential heating and cooling; and transport refrigeration systems and solutions. Its EMEA segment serves customers in the Europe, Middle East and Africa region and includes heating and cooling systems, services and solutions for commercial buildings, and transport refrigeration systems and solutions. Its Asia Pacific segment serves customers throughout the Asia Pacific region and includes heating and cooling systems and solutions. It also offers cloud-based connected workplace and enterprise asset management products and solutions.
C5: =G7 -> #VALUE! | D5: {=_FV(C5,"Description")} -> Lennox International Inc. is a provider of climate control solutions. The Company designs, manufactures and markets a range of products for the heating, ventilation, air conditioning and refrigeration (HVACR) markets. It operates through three segments: Home Comfort Solutions, Building Climate Solutions, and Corporate and Other. Home Comfort Solutions segment manufacture and market a broad range of furnaces, air conditioners, heat pumps, packaged heating and cooling systems, indoor air quality equipment, comfort control products, replacement parts and supplies and related products. Building Climate Solutions segment manufacture and sell unitary heating and air conditioning equipment, applied systems, controls, installation and service of commercial heating and cooling equipment, variable refrigerant flow commercial products, curb, curb adapters, drop box diffusers, HVAC recycling and salvage service, condensing units, unit coolers, fluid coolers, air cooled condensers, and others.
B7: In Millions JPY | C7: =OP!E2 -> Daikin Industries,Ltd. (6367.T) | D7: #VALUE! | E7: #VALUE! | F7: #VALUE! | G7: #VALUE! | H7: AVERAGE
B8: Company Info | H8: =IFERROR(AVERAGE(C8:G8),"")
B9: Market Cap | C9: =OP!C19 -> 7324317 | D9: 6697803.4 | E9: 6971591.5 | F9: 6388924.2 | G9: 1978040 | H9: =IFERROR(AVERAGE(C9:G9),"") -> 5872135.2
B10: Net Sales (current) | C10: =C54 -> 3981578 | D10: =D54 -> 3464289.3 | E10: =E54 -> 3148268.4 | F10: =F54 -> 2164367.6 | G10: =G54 -> 692443 | H10: =IFERROR(AVERAGE(C10:G10),"") -> 2690189.3
B11: Profitability | H11: =IFERROR(AVERAGE(C11:G11),"")
B12: Sales Growth (ttm) | C12: =C54/C53-1 -> 0.28061829 | D12: =D54/D53-1 -> -0.053866832 | E12: =E54/E53-1 -> 0.17451626 | F12: =F54/F53-1 -> 0.031099766 | G12: =G54/G53-1 -> 0.11803191 | H12: =IFERROR(AVERAGE(C12:G12),"") -> 0.11007988
B13: Sales Growth (36m) | C13: =C54/C52-1 -> 0.5612164 | D13: =D54/D52-1 -> 0.47156481 | E13: =E54/E52-1 -> 0.74663967 | F13: =F54/F52-1 -> 0.68296099 | G13: =G54/G52-1 -> 0.84528939 | H13: =IFERROR(AVERAGE(C13:G13),"") -> 0.66153425
B14: Operating Margin | C14: =C57/C54 -> 0.091645323 | D14: =D57/D54 -> 0.096424337 | E14: =E57/E54 -> 0.097383247 | F14: =F57/F54 -> 0.15012884 | G14: =G57/G54 -> 0.15147731 | H14: =IFERROR(AVERAGE(C14:G14),"") -> 0.11741181 | K14: Best value
B15: Net Income Margin | C15: =C60/C54 -> 0.064736896 | D15: =D60/D54 -> 0.053309318 | E15: =E60/E54 -> 0.098712264 | F15: =F60/F54 -> 0.11062446 | G15: =G60/G54 -> 0.11491025 | H15: =IFERROR(AVERAGE(C15:G15),"") -> 0.088458638
B16: Return on Equity (RoE) | C16: =C60/C71 -> 0.11731061 | D16: =D60/D71 -> 0.081449821 | E16: =E60/E71 -> 0.25989385 | F16: =F60/F71 -> 0.29787094 | G16: =G60/G71 -> 8.8099472 | H16: =IFERROR(AVERAGE(C16:G16),"") -> 1.9132945
B17: Return on Invested Capital (ROIC) | C17: =(C60+C59)/(C70+C71) -> 0.049756108 | D17: =(D60+D59)/(D70+D71) -> 0.050868576 | E17: =(E60+E59)/(E70+E71) -> 0.091447457 | F17: =(F60+F59)/(F70+F71) -> 0.13003932 | G17: =(G60+G59)/(G70+G71) -> 0.2252738 | H17: =IFERROR(AVERAGE(C17:G17),"") -> 0.10947705 | K17: Worst value
B18: Solvency | H18: =IFERROR(AVERAGE(C18:G18),"")
B19: Debt/Assets | C19: =C70/C67 -> 0.189086 | D19: =D70/D67 -> 0.27222478 | E19: =E70/E67 -> 0.35283823 | F19: =F70/F67 -> 0.2698772 | G19: =G70/G67 -> 0.60436725 | H19: =IFERROR(AVERAGE(C19:G19),"") -> 0.33767869
B20: Net Debt/EBITDA | C20: =(C70-C62)/C56 -> 0.36478578 | D20: =(D70-D62)/D56 -> 2.9626846 | E20: =(E70-E62)/E56 -> 2.3122377 | F20: =(F70-F62)/F56 -> 1.514681 | G20: =(G70-G62)/G56 -> 2.16741 | H20: =IFERROR(AVERAGE(C20:G20),"") -> 1.8643598
B21: Interest Coverage Ratio | C21: =-C56/C58 -> 61.578923 | D21: =-D56/D58 -> 13.508121 | E21: =-E56/E58 -> 11.762322 | F21: =-F56/F58 -> 12.835535 | G21: =-G56/G58 -> 15.441656 | H21: =IFERROR(AVERAGE(C21:G21),"") -> 23.025311
B22: Liquidity
B23: Current Ratio | C23: =C65/C69 -> 1.6746338 | D23: =D65/D69 -> 1.0284609 | E23: =E65/E69 -> 1.6267245 | F23: =F65/F69 -> 1.2573581 | G23: =G65/G69 -> 1.0487398 | H23: =IFERROR(AVERAGE(C23:G23),"") -> 1.3271834
B24: Quick Ratio | C24: =(C62+C63)/C69 -> 0.90028227 | D24: =(D62+D63)/D69 -> 0.64315082 | E24: =(E62+E63)/E69 -> 1.1227141 | F24: =(F62+F63)/F69 -> 0.72751179 | G24: =(G62+G63)/G69 -> 0.51380672 | H24: =IFERROR(AVERAGE(C24:G24),"") -> 0.78149315
B25: Activity | H25: =IFERROR(AVERAGE(C25:G25),"")
B26: Inventory Turnover | C26: =C55/C64 -> 2.6677545 | D26: =D55/D64 -> 5.6646983 | E26: =E55/E64 -> 5.9107081 | F26: =F55/F64 -> 4.7713873 | G26: =G55/G64 -> 3.9900713 | H26: =IFERROR(AVERAGE(C26:G26),"") -> 4.6009239
B27: Acc. Receivable Turnover | C27: =C54/C63 -> 5.7944625 | D27: =D54/D63 -> 4.3473844 | E27: =E54/E63 -> 5.7575201 | F27: =F54/F63 -> 5.7767536 | G27: =G54/G63 -> 5.6891878 | H27: =IFERROR(AVERAGE(C27:G27),"") -> 5.4730617
A28: Price/Sales | B28: Payables Turnover | C28: =C55/C68 -> 7.514886 | D28: =D55/D68 -> 3.9710212 | E28: =E55/E68 -> 5.3968202 | F28: =F55/F68 -> 5.6979009 | G28: =G55/G68 -> 7.2654789 | H28: =IFERROR(AVERAGE(C28:G28),"") -> 5.9692215
B29: Fixed Asset Turnover | C29: =C54/C66 -> 4.4193402 | D29: =D54/D66 -> 5.9074036 | E29: =E54/E66 -> 7.624388 | F29: =F54/F66 -> 10.302725 | G29: =G54/G66 -> 5.8337174 | H29: =IFERROR(AVERAGE(C29:G29),"") -> 6.8175148
B30: Total Asset Turnover | C30: =C54/C67 -> 0.92515618 | D30: =D54/D67 -> 0.60094426 | E30: =E54/E67 -> 0.83020087 | F30: =F54/F67 -> 0.91085855 | G30: =G54/G67 -> 1.6098346 | H30: =IFERROR(AVERAGE(C30:G30),"") -> 0.9753989
B31: Valuation | H31: =IFERROR(AVERAGE(C31:G31),"")
B32: Price/Earnings | C32: =C9/C60 -> 28.41581 | D32: =D9/D60 -> 36.267291 | E32: =E9/E60 -> 22.433089 | F32: =F9/F60 -> 26.683669 | G32: =G9/G60 -> 24.859493 | H32: =IFERROR(AVERAGE(C32:G32),"") -> 27.73187
B33: Price/Sales | C33: =C9/C54 -> 1.8395513 | D33: =D9/D54 -> 1.9333845 | E33: =E9/E54 -> 2.2144209 | F33: =F9/F54 -> 2.9518665 | G33: =G9/G54 -> 2.8566106 | H33: =IFERROR(AVERAGE(C33:G33),"") -> 2.3591668
B34: Price/Book | C34: =C9/C71 -> 3.3334761 | D34: =D9/D71 -> 2.9539643 | E34: =E9/E71 -> 5.8302218 | F34: =F9/F71 -> 7.9482896 | G34: =G9/G71 -> 219.01082 | H34: =IFERROR(AVERAGE(C34:G34),"") -> 47.815354
B35: EV/Sales | C35: =(C9+C70-C62)/C54 -> 1.8888039 | D35: =(D9+D70-D62)/D54 -> 2.3106888 | E35: =(E9+E70-E62)/E54 -> 2.4923642 | F35: =(F9+F70-F62)/F54 -> 3.2056513 | G35: =(G9+G70-G62)/G54 -> 3.2213229 | H35: =IFERROR(AVERAGE(C35:G35),"") -> 2.6237662
B36: EV/EBITDA | C36: =(C9+C70-C62)/C56 -> 13.989293 | D36: =(D9+D70-D62)/D56 -> 18.144089 | E36: =(E9+E70-E62)/E56 -> 20.734226 | F36: =(F9+F70-F62)/F56 -> 19.132505 | G36: =(G9+G70-G62)/G56 -> 19.143657 | H36: =IFERROR(AVERAGE(C36:G36),"") -> 18.228754
B37: Stock Info | H37: =IFERROR(AVERAGE(C37:G37),"")
B38: Float | C38: =OP!M17 -> 0.91467577 | D38: 0.997 | E38: 0.9884 | F38: 0.9967 | G38: 0.981 | H38: =IFERROR(AVERAGE(C38:G38),"") -> 0.97555515
B39: b (Yahoo) | C39: =OP!M19 -> 0.9 | D39: 1.24 | E39: 1.24 | F39: 1.21 | G39: 0.72 | H39: =IFERROR(AVERAGE(C39:G39),"") -> 1.062
B40: Dividend Yield (yahoo finance) | C40: 0.0084 | D40: 0.0203 | E40: 0.0125 | F40: 0.014 | G40: 0.0193 | H40: =IFERROR(AVERAGE(C40:G40),"") -> 0.0149
B41: Stock Performance
B42: 1y | C42: =(20200/C44) -> 0.80719281 | D42: =(69.19*114.14)/D44 -> 0.65665994 | E42: =(45.03*114.14)/E44 -> 0.48252004 | F42: =(184.97*114.14)/F44 -> 0.36370683 | G42: =1313.5/G44 -> 0.64276976 | H42: =IFERROR(AVERAGE(C42:G42),"") -> 0.59056987
B43: 3y | C43: =22920/C44 -> 0.91588412 | D43: =(74.8*114.14)/D44 -> 0.70990263 | E43: =(36.53*114.14)/E44 -> 0.39143808 | F43: =(153.24*114.14)/F44 -> 0.30131608 | G43: =1557/G44 -> 0.76192806 | H43: =IFERROR(AVERAGE(C43:G43),"") -> 0.6160938
B44: Current Price | C44: =OP!C17 -> 25025 | D44: {=(_FV(D7,"Price"))*141.14} -> 12026.539 | E44: {=(_FV(E7,"Price"))*141.14} -> 10651.836 | F44: {=(_FV(F7,"Price"))*141.14} -> 58048.059 | G44: =2043.5 -> 2043.5 | H44: =IFERROR(AVERAGE(C44:G44),"") -> 21558.987
B45: Average Target Price | C45: 28563.2 | D45: 8401.8454 | E45: 6055.127 | F45: 22539.226 | G45: 2073.1 | H45: =IFERROR(AVERAGE(C45:G45),"") -> 13526.5
B46: Upside/Downside | C46: =C45/C44-1 -> 0.14138661 | D46: =D45/D44-1 -> -0.30139127 | E46: =E45/E44-1 -> -0.43154146 | F46: =F45/F44-1 -> -0.61171439 | G46: =G45/G44-1 -> 0.014484952 | H46: =IFERROR(AVERAGE(C46:G46),"") -> -0.23775511
B47: Extra
B48: Investment in R&D | C48: =83200 -> 83200 | D48: =42700 -> 42700 | E48: =70750 -> 70750 | F48: =211*147.37 -> 31095.07 | G48: =212300 -> 212300 | H48: =IFERROR(AVERAGE(C48:G48),"") -> 88009.014
B49: R&D/Net Sales | C49: =C48/C10 -> 0.020896238 | D49: =D48/D10 -> 0.01232576 | E49: =E48/E10 -> 0.022472671 | F49: =F48/F10 -> 0.014366816 | G49: =G48/G10 -> 0.30659563 | H49: =IFERROR(AVERAGE(C49:G49),"") -> 0.075331424
B50: Financial Data | C50: =OP!E2 -> Daikin Industries,Ltd. (6367.T) | D50: #VALUE! | E50: #VALUE! | F50: =F7 -> #VALUE! | G50: =G7 -> #VALUE!
B51: IS
B52: Net Sales (36m ago) | C52: ='Fin. Data'!E5 -> 2550305 | D52: 2354153.4 | E52: 1802471.6 | F52: 1286047.4 | G52: 375249
B53: Net Sales (12m ago) | C53: ='Fin. Data'!C5 -> 3109106 | D53: 3661524 | E53: 2680480.9 | F53: 2099086.5 | G53: 619341
B54: Net Sales (current) | C54: ='Fin. Data'!B5 -> 3981578 | D54: 3464289.3 | E54: 3148268.4 | F54: 2164367.6 | G54: 692443
B55: COGS | C55: ='Fin. Data'!B5-'Fin. Data'!B7 -> 2650102 | D55: 2292355 | E55: 2301651 | F55: 1484693.5 | G55: 492778.2
B56: EBITDA | C56: ='Fin. Data'!B19 -> 537584 | D56: 441184.7 | E56: 378438.6 | F56: 362639.8 | G56: 116518.1
B57: Operating Income | C57: ='Fin. Data'!B11 -> 364893 | D57: 334041.8 | E57: 306588.6 | F57: 324934 | G57: 104889.4
B58: Net Financial Cost | C58: =Inputs!B10 -> -8730 | D58: -32660.7 | E58: -32173.8 | F58: -28252.8 | G58: -7545.7
B59: Taxes | C59: ='Fin. Data'!B21 -> -107941 | D59: 10488.6 | E59: -79063.8 | F59: -51513.6 | G59: -18972.4
B60: Net Income | C60: ='Fin. Data'!B23 -> 257755 | D60: 184678.9 | E60: 310772.7 | F60: 239432 | G60: 79568.8
B61: BS
B62: Cash & Eq. | C62: ='Fin. Data'!B39 -> 617663 | D62: 262214.8 | E62: 462984.9 | F62: 91994.3 | G62: 7415.8
B63: Acc. Receivables | C63: ='Fin. Data'!B40 -> 687135 | D63: 796867.5 | E63: 546809.8 | F63: 374668.5 | G63: 121712.1
B64: Inventory | C64: ='Fin. Data'!B41 -> 993383 | D64: 404673.8 | E64: 389403.6 | F64: 311166 | G64: 123501.1
B65: Current Assets | C65: =Inputs!B27 -> 2427082 | D65: 1693575.9 | E65: 1463113.1 | F65: 806533 | G65: 263565.2
B66: Fixed Assets | C66: ='Fin. Data'!B42 -> 900944 | D66: 586431.8 | E66: 412920.8 | F66: 210077.2 | G66: 118696.7
B67: Total Assets | C67: ='Fin. Data'!B44 -> 4303682 | D67: 5764743.1 | E67: 3792176.7 | F67: 2376184.1 | G67: 430133
B68: Acc. Payable | C68: =Inputs!B43 -> 352647 | D68: 577270.9 | E68: 426482.8 | F68: 260568.5 | G68: 67824.6
B69: Current Liabilities | C69: =Inputs!B42 -> 1449321 | D69: 1646709.1 | E69: 899422.8 | F69: 641450.5 | G69: 251316.1
B70: Total Debt | C70: ='Fin. Data'!B58 -> 813766 | D70: 1569305.9 | E70: 1338024.9 | F70: 641277.9 | G70: 259958.3
B71: Total Equity | C71: ='Fin. Data'!B64 -> 2197201 | D71: 2267394.8 | E71: 1195767.8 | F71: 803811.2 | G71: 9031.7
C74: =C50 -> Daikin Industries,Ltd. (6367.T) | D74: #VALUE! | E74: #VALUE! | F74: #VALUE! | G74: =G7 -> #VALUE!
B75: Float, b, Div. Yield | E75: Source: https://finviz.com/quote.ashx?t=CARR&p=d

Sheet ESG
B1: Company GICS Sector: | T1: Yes
B2: Industrials | C2: <- Select Industry | T2: No
B3: ESG Analysis | K3: Relative ESG Analysis
B4: Parameters | C4: Impact | D4: Do they report? | E4: Ranking | F4: Mitigation Plan | G4: Traffic Lights | H4: Improvement over time? | I4: Targets / Goals? | J4: Comments | K4: Parameters | L4: =Peers!C7 -> Daikin Industries,Ltd. (6367.T) | M4: =Peers!D7 -> #VALUE! | N4: =Peers!E7 -> #VALUE! | O4: =Peers!F7 -> #VALUE! | P4: =Peers!G7 -> #VALUE!
B5: Environmental | K5: Ratios
A6: 1 | B6: CO2 Direct Emissions | C6: =VLOOKUP($B$2,'[1]Sector Impact'!$K$4:$AA$16,A6+1,FALSE) -> Very High | D6: Yes | E6: Medium | F6: Yes | H6: No | I6: Achieve carbon neutrality by 2050 | J6: Increased 13% (2020-2021). Highest value per sales of the last 3 years. Achieve 30% reduction in 2025 and over 50% in 2030 | K6: CO2 Emissions/$M Sales | L6: =L12/L$11 -> 0.067865168 | M6: =M12/M$11 -> 0.21884363 | N6: =N12/N$11 -> 0.14331639 | O6: =O12/O$11 -> 0.21966106 | P6: =P12/P$11 -> 1.8582644
A7: 2 | B7: Total Water Consumption | C7: =VLOOKUP($B$2,'[1]Sector Impact'!$K$4:$AA$16,A7+1,FALSE) -> Very High | D7: Yes | E7: Medium | F7: Yes | H7: No | I7: None | J7: Increased 5% (2020-2021). Highest value (2021) in % of sales of the last 2 years | K7: Water Consumption/$M Sales | L7: =L13/L$11 -> 0.002035955 | M7: =M13/M$11 -> 0.36494513 | N7: =N13/N$11 -> 0.00036927043 | O7: =O13/O$11 -> 1.4462547 | P7: =P13/P$11 -> 0.0060311502
A8: 3 | B8: Total Energy Consumption | C8: =VLOOKUP($B$2,'[1]Sector Impact'!$K$4:$AA$16,A8+1,FALSE) -> Very High | D8: Yes | E8: "Villain" | F8: Yes | H8: No | I8: None | J8: Increased 17% (2020-2021). Highest value (2021) in % of sales of the last 4 years | K8: Energy Consumption/$M Sales | L8: =L14/L$11 -> 5.313831 | M8: =M14/M$11 -> 2.1205332 | N8: =N14/N$11 -> 1.6316118 | O8: =O14/O$11 -> 1.4907933 | P8: =P14/P$11 -> 1.1860324
A9: 4 | B9: Waste Management | C9: =VLOOKUP($B$2,'[1]Sector Impact'!$K$4:$AA$16,A9+1,FALSE) -> High | D9: Yes | E9: Medium High | F9: Yes | H9: No | I9: None | J9: Increased 28% (2020-2021). Highest value (2021) in % of sales of the last 5 years. | K9: Waste Production/$M Sales | L9: =L15/L$11 -> 0.013284848 | M9: =M15/M$11 -> 0.021336587 | N9: =N15/N$11 -> 0.026152995 | O9: =O15/O$11 -> 0.003768269 | P9: =P15/P$11 -> 9.6275028e-05
A10: 5 | B10: Land Degradation/Deforestation/Biodiversity loss/Animal sufering/… | C10: =VLOOKUP($B$2,'[1]Sector Impact'!$K$4:$AA$16,A10+1,FALSE) -> High | D10: Yes | E10: Medium High | F10: Yes | H10: None | I10: None | J10: No information | K10: Inputs
B11: Social | K11: Net Sales (¥M) | L11: =M46 -> 3109106 | M11: =M47 -> 3345708.5 | N11: =M48 -> 2913853.7 | O11: =M49 -> 1998265 | P11: =M50 -> 4476758
A12: 6 | B12: Employee Turnover % | C12: =VLOOKUP($B$2,'[1]Sector Impact'!$K$4:$AA$16,A12+1,FALSE) -> Low | D12: Yes | E12: Medium | F12: Yes | H12: No | I12: None | J12: 4,4% (2021), 3,7% (2020), 3,9% (2019), 4% (2018) | K12: CO2 Emissions Total (Tonnes) | L12: 211000 | M12: =M76 -> 732187 | N12: =M78 -> 417603 | O12: =M80 -> 438941 | P12: =M82 -> 8319000
A13: 7 | B13: Salaries & Compensation | C13: =VLOOKUP($B$2,'[1]Sector Impact'!$K$4:$AA$16,A13+1,FALSE) -> Medium | D13: Yes | E13: Medium | F13: Yes | H13: None | I13: None | J13: Starting salary: University grad- 235000 ¥ (1657 $); Masters- 254800 ¥ (1797$); PhD- 278800 ¥ (1966$) | K13: Water Consumption Total (Cubic Meters) | L13: 6330 | M13: =W59 -> 1221000 | N13: =W61 -> 1076 | O13: =W63 -> 2890000 | P13: =W65 -> 27000
A14: 8 | B14: Reputation | C14: =VLOOKUP($B$2,'[1]Sector Impact'!$K$4:$AA$16,A14+1,FALSE) -> High | D14: Yes | E14: Medium High | F14: Yes | H14: None | I14: None | J14: Percentage of Employees in Union: 87% | K14: Energy Consumption Total (Gigajoules) | L14: 16521264 | M14: =M59 -> 7094686 | N14: =M61 -> 4754278 | O14: =M63 -> 2979000 | P14: =M65 -> 5309580
A15: 9 | B15: Discrimination Events | C15: =VLOOKUP($B$2,'[1]Sector Impact'!$K$4:$AA$16,A15+1,FALSE) -> Very High | D15: Yes | E15: Medium | F15: Yes | H15: No | I15: None | J15: Women as % of all employees: 28%. Employment rate of people with disabilities: 2,6% or 362 people (2021) | K15: Waste Production Total (Tonnes) | L15: 41304 | M15: =W76 -> 71386 | N15: =W78 -> 76206 | O15: =W80 -> 7530 | P15: =W82 -> 431
A16: 10 | B16: Work Safety | C16: =VLOOKUP($B$2,'[1]Sector Impact'!$K$4:$AA$16,A16+1,FALSE) -> Medium | D16: Yes | E16: Medium High | F16: Yes | H16: None | I16: None | J16: Percentage of employees taking checkup: 99% (2021); Percentage of employees requiring treatment: 63% (2021) | K16: ESG Scores
A17: 11 | B17: Damage to consumer health | C17: =VLOOKUP($B$2,'[1]Sector Impact'!$K$4:$AA$16,A17+1,FALSE) -> Very High | D17: Yes | E17: Medium | F17: Yes | H17: None | I17: None | J17: Average Hours of Overtime per Employee: 212 hours (2021); 193 (2020): 208 (2019). Percentage of Employees Taking All Paid Leave: 95,8% (2021), Percentage of Japanese workers in the manufacturing industry: 61,6% (2021) | K17: Refinitiv | L17: 67 (119/638) (48/77/75) | M17: 78 (42/638) (95/94/37) | N17: 60 (183/638) (52/82/41) | O17: 80 (34/638) (68/93/78) | P17: 83 (6/66) (98/89/51)
A18: 12 | B18: PXP? | C18: =VLOOKUP($B$2,'[1]Sector Impact'!$K$4:$AA$16,A18+1,FALSE) -> Medium | D18: Yes | E18: Medium High | F18: Yes | H18: None | I18: None | J18: No information | K18: Sustainalytics | L18: 21.7 (medium risk) | M18: 14.4 (Low risk) | N18: 20.4 (medium risk) | O18: 15.2 (Low risk) | P18: 20.8 (medium risk)
A19: 13 | B19: Supply chain | C19: =VLOOKUP($B$2,'[1]Sector Impact'!$K$4:$AA$16,A19+1,FALSE) -> Very High | D19: Yes | E19: Medium | F19: Yes | H19: None | I19: Increase Class A CSR procurement achievment rate among all suppliers | J19: 72% Class A CSR Procurement Achievement Rate (2021) | K19: ISS | L19: C+ | M19: B- | N19: C+ | O19: B- | P19: C+
A20: 14 | B20: Community involvement | C20: =VLOOKUP($B$2,'[1]Sector Impact'!$K$4:$AA$16,A20+1,FALSE) -> Very High | D20: Yes | E20: Medium High | F20: Yes | H20: None | I20: Contribution to environmental conservation, education support, and cooperation with the local community | J20: 1388 million ¥ (10 million $) Expenditure for Social Contribution Activities in 2021 | K20: CDP | L20: A / A- | M20: A-/ B | N20: F/ F | O20: A / B | P20: A-/ A-
A21: 15 | B21: Public Sector | C21: =VLOOKUP($B$2,'[1]Sector Impact'!$K$4:$AA$16,A21+1,FALSE) -> Very High | D21: Yes | E21: Medium | F21: No | H21: None | I21: None | J21: No information | O21: USD/JPY | P21: 141.36
A22: 16 | B22: Litigation | C22: =VLOOKUP($B$2,'[1]Sector Impact'!$K$4:$AA$16,A22+1,FALSE) -> High | D22: Yes | E22: Medium High | F22: Yes | H22: None | I22: None | J22: No major legal violations in the last 3 years. Patent dispute with Chemours-July 2022: Settled before trial (terms were not disclosed)
B23: Corporate Governance
A24: 17 | B24: Diversity (Gender, Age, Industry, Region) | E24: Medium High | F24: Yes | H24: None | I24: Appointment of female officers from inside the compoany: 1 or more in fiscal 2025 | J24: Out of 10 board members: 1 female (10%); Average age of 73 years old; 1 non-Japanese
A25: 18 | B25: % Independence | E25: Medium High | F25: No | H25: None | I25: None | J25: 4 out of 10 are independent (40%)
A26: 19 | B26: Average time as independent directors/ Average Appointment Term for Director | E26: Medium High | F26: No | H26: None | I26: None | J26: 4.75 years/ 9.7 (2021)
A27: 20 | B27: Recent departures of directors / C-level executives? | E27: Medium High | F27: No | H27: None | I27: None | J27: None
A28: 21 | B28: CEO/Chairman duality | E28: Medium High | F28: No | H28: None | I28: None | J28: No. Noriyuki Inoue- Chairman of the board (since 2014); Masanori Togawa- CEO (since 2014)
A29: 22 | B29: Transparency (ESG, segments, acquisitions, other) | E29: Medium High | F29: Yes | H29: None | I29: None | J29: Well reported
A30: 23 | B30: Time taken to report after the end of the quarter / year | E30: Medium | F30: No | H30: None | I30: None | J30: 1 month and 9 days (31st march-9th may)
A31: 24 | B31: Additional participation of the CEO in other boards or excessive participation of Ch. | E31: Medium | F31: No | H31: None | I31: None | J31: Noriyuki Inoue: Chairman of The Daikin Foundation for Contemporary Arts and Nonprofit Corporation of Kansai Philharmonic Orchestra
A32: 25 | B32: Audit / Consulting | D32: Yes | E32: Medium | F32: No | H32: None | I32: None | J32: Deloitte Touche Tohmatsu LLC; Audit expenses: 255 million ¥ (1,8 million $)
A33: 26 | B33: ESG-compensation related | D33: No | E33: Medium | F33: No | H33: None | I33: None | J33: No information
A34: 27 | B34: Management compensation schemes | D34: Yes | E34: Medium High | F34: No | H34: None | I34: None | J34: Down below
B36: PARAMETERS
B37: IMPACT | C37: RANKING | D37: MITIGATION PLAN
B38: Low | C38: "Best in class" | D38: Evidence / plan?
B39: Medium | C39: Medium High
B40: High | C40: Medium
B41: Very high | C41: "Villain"
M44: Sales (in millions JPY)
M45: 2021 FY | N45: 2020 FY | O45: 2019 FY | P45: 2018 FY | Q45: 2017 FY
L46: =Peers!C7 -> Daikin Industries,Ltd. (6367.T) | M46: 3109106 | N46: 2493386 | O46: 2550305 | P46: 2481109 | Q46: 2290560
L47: #VALUE! | M47: =23668*P21 -> 3345708.5 | N47: =22317*P21 -> 3154731.1 | O47: =23968*P21 -> 3388116.5
L48: #VALUE! | M48: =20613*P21 -> 2913853.7 | N48: =17456*P21 -> 2467580.2 | O48: =18608*P21 -> 2630426.9
L49: #VALUE! | M49: =14136*P21 -> 1998265 | N49: =12454*P21 -> 1760497.4 | O49: =16598*P21 -> 2346293.3
L50: Mitsubishi Corporation (8058.T) | M50: 4476758 | N50: 4191433 | O50: 4462509
M55: Energy Consumption Total (Gigajoules) | W55: Water Consumption Total (Cubic Meters)
M56: 2021 | N56: 2020 | O56: 2019 | P56: 2018 | Q56: 2017 | W56: 2021 | X56: 2020 | Y56: 2019 | Z56: 2018 | AA56: 2017
L57: Daikin Industries,Ltd. (6367.T) | M57: 16521264 | N57: 14108119 | O57: 14991148 | P57: 15079769 | Q57: 14738297 | R57: =(M57-N57)/N57 -> 0.17104654 | S57: =(N57-O57)/O57 -> -0.058903361 | T57: =(O57-P57)/P57 -> -0.0058768142 | U57: =(P57-Q57)/Q57 -> 0.023169027 | V57: Daikin Industries,Ltd. (6367.T) | W57: 6330 | X57: 6030 | Y57: 6530 | Z57: 6950 | AA57: 6600 | AB57: =(W57-X57)/X57 -> 0.049751244 | AC57: =(X57-Y57)/Y57 -> -0.076569678 | AD57: =(Y57-Z57)/Z57 -> -0.060431655 | AE57: =(Z57-AA57)/AA57 -> 0.053030303
L58: % sales | M58: =M57/M46 -> 5.313831 | N58: =N57/N46 -> 5.658217 | O58: =O57/O46 -> 5.8781785 | P58: =P57/P46 -> 6.0778341 | Q58: =Q57/Q46 -> 6.4343641 | V58: % sales | W58: =W57/M46 -> 0.002035955 | X58: =X57/N46 -> 0.0024183981 | Y58: =Y57/O46 -> 0.0025604781 | Z58: =Z57/P46 -> 0.0028011667 | AA58: =AA57/Q46 -> 0.0028813915
L59: #VALUE! | M59: 7094686 | N59: 7484324 | O59: 8107715 | V59: #VALUE! | W59: 1221000 | X59: 1241000 | Y59: 938000
L60: % sales | M60: =M59/M47 -> 2.1205332 | N60: =N59/N47 -> 2.3724126 | O60: =O59/O47 -> 2.3929859 | V60: % sales | W60: =W59/M47 -> 0.36494513 | X60: =X59/N47 -> 0.39337742 | Y60: =Y59/O47 -> 0.27684999
L61: #VALUE! | M61: 4754278 | N61: 4194215 | O61: 4217538 | V61: #VALUE! | W61: 1076 | X61: 967 | Y61: 1135
L62: % sales | M62: =M61/M48 -> 1.6316118 | N62: =N61/N48 -> 1.699728 | O62: =O61/O48 -> 1.6033664 | V62: % sales | W62: =W61/M48 -> 0.00036927043 | X62: =X61/N48 -> 0.0003918819 | Y62: =Y61/O48 -> 0.0004314889
L63: #VALUE! | M63: 2979000 | N63: 2861000 | O63: 3075000 | V63: #VALUE! | W63: 2890000 | X63: 2780000 | Y63: 2940000
L64: % sales | M64: =M63/M49 -> 1.4907933 | N64: =N63/N49 -> 1.6251089 | O64: =O63/O49 -> 1.3105778 | V64: % sales | W64: =W63/M49 -> 1.4462547 | X64: =X63/N49 -> 1.5790991 | Y64: =Y63/O49 -> 1.2530403
L65: Mitsubishi Corporation (8058.T) | M65: 5309580 | N65: 4165874 | O65: 4399057 | V65: Mitsubishi Corporation (8058.T) | W65: 27000 | X65: 25000 | Y65: 38000
L66: % sales | M66: =M65/M50 -> 1.1860324 | N66: =N65/N50 -> 0.99390209 | O66: =O65/O50 -> 0.98578109 | V66: % sales | W66: =W65/M50 -> 0.0060311502 | X66: =X65/N50 -> 0.0059645472 | Y66: =Y65/O50 -> 0.008515389
B67: https://www.daikin.com/csr/nav/data
B68: https://www.johnsoncontrols.com/-/media/jci/corporate-sustainability/reporting-and-policies/2023/report/hq2302005_2023-sustainability-report-final.pdf?la=en&hash=93BADD3C91131A642345467E91290903D661E5AE
B69: https://www.corporate.carrier.com/Images/Corporate-Carrier-2022-ESG-Report-0822_tcm558-181752.pdf
B70: https://www.tranetechnologies.com/en/index/sustainability/sustainability-reports/esg-report/report-and-data/data-center.html
B71: https://www.mitsubishicorp.com/jp/en/ir/library/ar/pdf/areport/2022/all.pdf
M72: GHG Scope 1 & 2 Emissions per Million Sales (Tonnes) | W72: Waste Production Total (Tonnes)
M73: 2021 | N73: 2020 | O73: 2019 | P73: 2018 | Q73: 2017 | W73: 2021 | X73: 2020 | Y73: 2019 | Z73: 2018 | AA73: 2017
L74: Daikin Industries,Ltd. (6367.T) | M74: 211000 | N74: 186800 | O74: 186800 | P74: 194900 | Q74: 194000 | R74: =(M74-N74)/N74 -> 0.12955032 | S74: =(N74-O74)/O74 -> 0 | T74: =(O74-P74)/P74 -> -0.041559774 | U74: =(P74-Q74)/Q74 -> 0.0046391753 | V74: Daikin Industries,Ltd. (6367.T) | W74: 41304 | X74: 32304 | Y74: 37198 | Z74: 36298 | AA74: 27193 | AB74: =(W74-X74)/X74 -> 0.27860327 | AC74: =(X74-Y74)/Y74 -> -0.13156621 | AD74: =(Y74-Z74)/Z74 -> 0.024794755 | AE74: =(Z74-AA74)/AA74 -> 0.33482882
L75: % sales | M75: =M74/M46 -> 0.067865168 | N75: =N74/N46 -> 0.074918204 | O75: =O74/O46 -> 0.073246141 | P75: =P74/P46 -> 0.078553582 | Q75: =Q74/Q46 -> 0.084695446 | V75: % sales | W75: =W74/M46 -> 0.013284848 | X75: =X74/N46 -> 0.012955876 | Y75: =Y74/O46 -> 0.014585706 | Z75: =Z74/P46 -> 0.014629748 | AA75: =AA74/Q46 -> 0.011871769
L76: #VALUE! | M76: 732187 | N76: 858884 | O76: 1189805 | V76: #VALUE! | W76: 71386 | X76: 72429 | Y76: 99181
L77: % sales | M77: =M76/M47 -> 0.21884363 | N77: =N76/N47 -> 0.27225268 | O77: =O76/O47 -> 0.35117004 | V77: % sales | W77: =W76/M47 -> 0.021336587 | X77: =X76/N47 -> 0.02295885 | Y77: =Y76/O47 -> 0.029273197
L78: #VALUE! | M78: 417603 | N78: 382845 | O78: 396492 | V78: #VALUE! | W78: 76206 | X78: 77489 | Y78: 74400
L79: % sales | M79: =M78/M48 -> 0.14331639 | N79: =N78/N48 -> 0.15514997 | O79: =O78/O48 -> 0.15073295 | V79: % sales | W79: =W78/M48 -> 0.026152995 | X79: =X78/N48 -> 0.03140283 | Y79: =Y78/O48 -> 0.028284382
L80: #VALUE! | M80: 438941 | N80: 461964 | O80: 520017 | V80: #VALUE! | W80: 7530 | X80: 9654 | Y80: 11597
L81: % sales | M81: =M80/M49 -> 0.21966106 | N81: =N80/N49 -> 0.26240538 | O81: =O80/O49 -> 0.22163342 | V81: % sales | W81: =W80/M49 -> 0.003768269 | X81: =X80/N49 -> 0.0054836774 | Y81: =Y80/O49 -> 0.0049426899
L82: Mitsubishi Corporation (8058.T) | M82: 8319000 | N82: 9185000 | O82: 9437000 | V82: Mitsubishi Corporation (8058.T) | W82: 431 | X82: 411 | Y82: 506
L83: % sales | M83: =M82/M50 -> 1.8582644 | N83: =N82/N50 -> 2.1913746 | O83: =O82/O50 -> 2.1147296 | V83: % sales | W83: =W82/M50 -> 9.6275028e-05 | X83: =X82/N50 -> 9.8057156e-05 | Y83: =Y82/O50 -> 0.00011338913

Sheet DCF
A1: VALUATION MODEL
G3: Short Term | K3: Long Term
A4: Section | B4: Line # | C4: ITEM | D4: 2020 (Real) | E4: 2021 (Real) | F4: 2022 (Real) | G4: 2023 | H4: =G4+1 -> 2024 | I4: =H4+1 -> 2025 | J4: =I4+1 -> 2026 | K4: =J4+1 -> 2027 | L4: =K4+1 -> 2028 | M4: =L4+1 -> 2029 | N4: =M4+1 -> 2030 | O4: =N4+1 -> 2031 | ... AF4: =AE4+1 -> 2048
A5: INCOME STATEMENT | B5: 1 | C5: Growth | D5: ='Fin. Data'!D6 -> -0.022318507 | E5: =+E6/D6-1 -> 0.24694131 | F5: =+F6/E6-1 -> 0.28061829 | G5: =+G6/F6-1 -> 0.029742479 | H5: =+H6/G6-1 -> 0.042682927 | I5: =+I6/H6-1 -> 0.064327485 | J5: =+J6/I6-1 -> 0.08 | K5: =+K6/J6-1 -> 0.08 | L5: =+L6/K6-1 -> 0.08 | ... AF5: =+AF6/AE6-1 -> 0.03
B6: 2 | C6: Revenues/Sales | D6: =Inputs!D6 -> 2493386 | E6: =Inputs!C6 -> 3109106 | F6: =Inputs!B6 -> 3981578 | G6: 4100000 | H6: 4275000 | I6: 4550000 | J6: =I6*1.08 -> 4914000 | K6: =J6*1.08 -> 5307120 | L6: =K6*1.08 -> 5731689.6 | M6: =L6*1.08 -> 6190224.8 | N6: =M6*1.08 -> 6685442.7 | O6: =N6*1.06 -> 7086569.3 | P6: =O6*1.06 -> 7511763.5 | Q6: =P6*1.06 -> 7962469.3 | R6: =Q6*1.06 -> 8440217.4 | S6: =R6*1.06 -> 8946630.5 | T6: =S6*1.04 -> 9304495.7 | U6: =T6*1.04 -> 9676675.5 | V6: =U6*1.04 -> 10063743 | W6: =V6*1.04 -> 10466292 | X6: =W6*1.04 -> 10884944 | Y6: =X6*1.03 -> 11211492 | Z6: =Y6*1.03 -> 11547837 | AA6: =Z6*1.03 -> 11894272 | AB6: =AA6*1.03 -> 12251100 | AC6: =AB6*1.03 -> 12618633 | AD6: =AC6*1.03 -> 12997192 | AE6: =AD6*1.03 -> 13387108 | AF6: =AE6*1.03 -> 13788721
B7: 3 | C7: EBIT/Operating Margin | D7: =D8/D6 -> 0.095423252 | E7: =E8/E6 -> 0.10012589 | F7: =F8/F6 -> 0.091645323 | G7: 0.098 | H7: 0.105 | I7: 0.11 | J7: 0.115 | K7: 0.12 | L7: =$K$7 -> 0.12 | M7: =$K$7 -> 0.12 | N7: =$K$7 -> 0.12 | O7: =$K$7 -> 0.12 | P7: =$K$7 -> 0.12 | Q7: =$K$7 -> 0.12 | R7: =$K$7 -> 0.12 | S7: =$K$7 -> 0.12 | ... AF7: =$K$7 -> 0.12
B8: 4 | C8: EBIT | D8: ='Fin. Data'!D11 -> 237927 | E8: ='Fin. Data'!C11 -> 311302 | F8: ='Fin. Data'!B11 -> 364893 | G8: =G7*G6 -> 401800 | H8: =H7*H6 -> 448875 | I8: =I7*I6 -> 500500 | J8: =J7*J6 -> 565110 | K8: =K7*K6 -> 636854.4 | L8: =L7*L6 -> 687802.75 | M8: =M7*M6 -> 742826.97 | N8: =N7*N6 -> 802253.13 | ... AF8: =AF7*AF6 -> 1654646.6
B9: 5a | C9: (Dep) | D9: -36178 | E9: -40952 | F9: -51181 | G9: =$D$53*DCF!F40 -> -48773.182 | H9: =$D$53*DCF!G40 -> -52636.51 | I9: =$D$53*DCF!H40 -> -56664.736 | J9: =$D$53*DCF!I40 -> -60952.089 | K9: =$E$53*DCF!J40 -> -65582.429 | L9: =$E$53*DCF!K40 -> -69415.597 | M9: =$E$53*DCF!L40 -> -73555.418 | N9: =$E$53*DCF!M40 -> -78026.425 | O9: =$E$53*DCF!N40 -> -82855.112 | P9: =$E$53*DCF!O40 -> -87973.521 | Q9: =$E$53*DCF!P40 -> -93399.034 | R9: =$E$53*DCF!Q40 -> -99150.078 | ... AF9: =$E$53*DCF!AE40 -> -210156.04 | AG9: =SUM(D9:AF9) -> -3156751.1
B10: 5b | C10: Amort | D10: -30050 | E10: -32684 | F10: -39496 | G10: =F38*$D$54 -> -39612.826 | H10: =G38*$D$54 -> -44043.986 | I10: =H38*$D$54 -> -48970.825 | J10: =I38*$D$54 -> -54448.788 | K10: =J38*$E$54 -> -60539.526 | L10: =K38*$E$54 -> -67311.584 | M10: =L38*$E$54 -> -74841.177 | N10: =M38*$E$54 -> -83213.044 | O10: =N38*$E$54 -> -92521.402 | P10: =O38*$E$54 -> -102871.01 | Q10: =P38*$E$54 -> -114378.34 | R10: =Q38*$E$54 -> -127172.91 | ... AF10: =AE38*$E$54 -> -561184.63
B11: 5c | C11: (Stock based compensation) | D11: =D20 -> 0 | E11: =E20 -> 0 | F11: =F20 -> 0 | G11: =G6*$D$55 -> 0 | H11: =H6*$D$55 -> 0 | I11: =I6*$D$55 -> 0 | J11: =J6*$D$55 -> 0 | K11: =K6*$D$55 -> 0 | L11: =L6*$D$55 -> 0 | M11: =M6*$D$55 -> 0 | N11: =N6*$D$55 -> 0 | ... AF11: =AF6*$D$55 -> 0
B12: 6 | C12: EBIDTA | D12: =D8-D9-D10 -> 304155 | E12: =E8-E9-E10 -> 384938 | F12: =F8-F9-F10 -> 455570 | G12: =G8-G9-G10 -> 490186.01 | H12: =H8-H9-H10 -> 545555.5 | I12: =I8-I9-I10 -> 606135.56 | J12: =J8-J9-J10 -> 680510.88 | K12: =K8-K9-K10 -> 762976.35 | ... AF12: =AF8-AF9-AF10 -> 2425987.2
B13: 7 | C13: (Net financing cost) | D13: ='Fin. Data'!D14 -> 2772 | E13: ='Fin. Data'!C14 -> -638 | F13: ='Fin. Data'!B14 -> -8730 | G13: =F43*$D$58-F44*$D$57 -> -19995.127 | H13: =G43*$D$58-G44*$D$57 -> -17501.524 | I13: =H43*$D$58-H44*$D$57 -> -18993.626 | J13: =I43*$D$58-I44*$D$57 -> -21805.284 | K13: =J43*$E$58-J44*$E$57 -> -39408.87 | L13: =K43*$E$58-K44*$E$57 -> -44508.181 | M13: =L43*$E$58-L44*$E$57 -> -48577.912 | N13: =M43*$E$58-M44*$E$57 -> -52987.785 | O13: =N43*$E$58-N44*$E$57 -> -57760.004 | P13: =O43*$E$58-O44*$E$57 -> -61322.204 | Q13: =P43*$E$58-P44*$E$57 -> -65078.923 | R13: =Q43*$E$58-Q44*$E$57 -> -69038.772 | ... AF13: =AE43*$E$58-AE44*$E$57 -> -114722.59
B14: 8 | C14: Other income/(cost) | D14: ='Fin. Data'!D15 -> -8652 | E14: ='Fin. Data'!C15 -> 9832 | F14: ='Fin. Data'!B15 -> 9533 | G14: =AVERAGE(D14:F14)*(1+G5) -> 3677.2104 | H14: =AVERAGE(E14:G14)*(1+H5) -> 8008.5731 | I14: =AVERAGE(F14:H14)*(1+I5) -> 7527.9115 | J14: =AVERAGE(G14:I14)*(1+J5) -> 6916.9302 | K14: =AVERAGE(H14:J14)*(1+K5) -> 8083.2293 | L14: =AVERAGE(I14:K14)*(1+L5) -> 8110.1056 | M14: =AVERAGE(J14:L14)*(1+M5) -> 8319.6954 | N14: =AVERAGE(K14:M14)*(1+N5) -> 8824.6909 | ... AF14: =AVERAGE(AC14:AE14)*(1+AF5) -> 12395.794
B15: 9 | C15: Earnings before taxes | D15: =D8+D13+D14 -> 232047 | E15: =E8+E13+E14 -> 320496 | F15: =F8+F13+F14 -> 365696 | G15: =G8+G13+G14 -> 385482.08 | H15: =H8+H13+H14 -> 439382.05 | I15: =I8+I13+I14 -> 489034.29 | J15: =J8+J13+J14 -> 550221.65 | K15: =K8+K13+K14 -> 605528.76 | ... AF15: =AF8+AF13+AF14 -> 1552319.8
B16: 10 | C16: (Income tax) | D16: ='Fin. Data'!D21 -> -75797 | E16: ='Fin. Data'!C21 -> -102786 | F16: ='Fin. Data'!B21 -> -107941 | G16: =-(1*24%)*G15 -> -92515.7 | H16: =-(1*$D$56)*H15 -> -134450.91 | I16: =-(1*$D$56)*I15 -> -149644.49 | J16: =-(1*$D$56)*J15 -> -168367.82 | K16: =-(1*$E$56)*K15 -> -185291.8 | L16: =-(1*$E$56)*L15 -> -199329.83 | M16: =-(1*$E$56)*M15 -> -214986.04 | N16: =-(1*$E$56)*N15 -> -231975.55 | O16: =-(1*$E$56)*O15 -> -245274.78 | P16: =-(1*$E$56)*P15 -> -259885.79 | Q16: =-(1*$E$56)*Q15 -> -275382.48 | R16: =-(1*$E$56)*R15 -> -291789.43 | ... AF16: =-(1*$E$56)*AF15 -> -475009.85
B17: 11 | C17: Net income | D17: ='Fin. Data'!D23 -> 156250 | E17: ='Fin. Data'!C23 -> 217710 | F17: ='Fin. Data'!B23 -> 257755 | G17: =G16+G15 -> 292966.38 | H17: =H16+H15 -> 304931.14 | I17: =I16+I15 -> 339389.79 | J17: =J16+J15 -> 381853.82 | K17: =K16+K15 -> 420236.96 | L17: =L16+L15 -> 452074.85 | M17: =M16+M15 -> 487582.72 | N17: =N16+N15 -> 526114.48 | ... AF17: =AF16+AF15 -> 1077309.9
A19: CASH FLOW STATEMENT | B19: 12 | C19: Operating cash flows before WK | D19: =D22-D20-D21 -> 373351 | E19: =E22-E20-E21 -> 471462 | F19: =F22-F20-F21 -> 551490 | G19: =G17-G10-G9-G11 -> 381352.39 | H19: =H17-H10-H9-H11 -> 401611.64 | I19: =I17-I10-I9-I11 -> 445025.36 | J19: =J17-J10-J9-J11 -> 497254.7 | K19: =K17-K10-K9-K11 -> 546358.91 | L19: =L17-L10-L9-L11 -> 588802.03 | M19: =M17-M10-M9-M11 -> 635979.31 | N19: =N17-N10-N9-N11 -> 687353.95 | ... AF19: =AF17-AF10-AF9-AF11 -> 1848650.6
B20: 13 | C20: (Stock-based compensation) | D20: 0 | E20: 0 | F20: 0 | G20: =G11 -> 0 | H20: =H11 -> 0 | I20: =I11 -> 0 | J20: =J11 -> 0 | K20: =K11 -> 0 | L20: =L11 -> 0 | M20: =M11 -> 0 | N20: =N11 -> 0 | ... AF20: =AF11 -> 0
B21: 14 | C21: (Working Capital Flows) | D21: =Inputs!D62 -> 1282 | E21: =Inputs!C62 -> -227977 | F21: =Inputs!B62 -> -393164 | G21: =$D$60*(G6-F6) -> -68114.428 | H21: =$D$60*(H6-G6) -> -100657.18 | I21: =$D$60*(I6-H6) -> -158175.57 | J21: =$D$60*(J6-I6) -> -209366.94 | K21: =$E$60*(K6-J6) -> -226116.3 | L21: =$E$60*(L6-K6) -> -244205.6 | M21: =$E$60*(M6-L6) -> -263742.05 | N21: =$E$60*(N6-M6) -> -284841.41 | O21: =$E$60*(O6-N6) -> -230721.54 | P21: =$E$60*(P6-O6) -> -244564.84 | Q21: =$E$60*(Q6-P6) -> -259238.73 | R21: =$E$60*(R6-Q6) -> -274793.05 | ... AF21: =$E$60*(AF6-AE6) -> -231001.47
B22: 15 | C22: -Total Operating Cash Flow | D22: =Inputs!D59 -> 374633 | E22: =Inputs!C59 -> 243485 | F22: =Inputs!B59 -> 158326 | G22: =G19+G20+G21 -> 313237.96 | H22: =H19+H20+H21 -> 300954.45 | I22: =I19+I20+I21 -> 286849.78 | J22: =J19+J20+J21 -> 287887.76 | K22: =K19+K20+K21 -> 320242.62 | L22: =L19+L20+L21 -> 344596.43 | M22: =M19+M20+M21 -> 372237.26 | N22: =N19+N20+N21 -> 402512.54 | ... AF22: =AF19+AF20+AF21 -> 1617649.1
B23: 16 | C23: (CAPEX) | D23: ='Fin. Data'!D32 -> -104971 | E23: ='Fin. Data'!C32 -> -114106 | F23: ='Fin. Data'!B32 -> -175076 | G23: =G6*$D$62 -> -160466.34 | H23: =H6*$D$62 -> -167315.52 | I23: =I6*$D$62 -> -178078.5 | J23: =J6*$D$62 -> -192324.78 | K23: =K6*$E$62 -> -159213.6 | L23: =L6*$E$62 -> -171950.69 | M23: =M6*$E$62 -> -185706.74 | N23: =N6*$E$62 -> -200563.28 | O23: =O6*$E$62 -> -212597.08 | P23: =P6*$E$62 -> -225352.9 | Q23: =Q6*$E$62 -> -238874.08 | R23: =R6*$E$62 -> -253206.52 | ... AF23: =AF6*$E$62 -> -413661.64 | AG23: =SUM(D23:AF23) -> -7510977.2
B24: 17 | C24: Adq | D24: =Inputs!D66 -> -43371 | E24: ='Fin. Data'!C33 -> -46221 | F24: ='Fin. Data'!B33 -> -34920 | G24: =G6*$D$63 -> -71455.043 | H24: =H6*$D$63 -> -74504.953 | I24: =I6*$D$63 -> -79297.669 | J24: =J6*$D$63 -> -85641.483 | K24: =K6*$E$63 -> -79606.8 | L24: =L6*$E$63 -> -85975.344 | M24: =M6*$E$63 -> -92853.372 | N24: =N6*$E$63 -> -100281.64 | O24: =O6*$E$63 -> -106298.54 | P24: =P6*$E$63 -> -112676.45 | Q24: =Q6*$E$63 -> -119437.04 | R24: =R6*$E$63 -> -126603.26 | ... AF24: =AF6*$E$63 -> -206830.82 | AH24: =AG9-AG23 -> 4354226
B25: 18 | C25: (Other investing flows) | D25: =Inputs!D67 -> -11324 | E25: =Inputs!C67 -> -20462 | F25: =Inputs!B67 -> -19797 | G25: =(1+G5)*AVERAGE(D25:F25) -> -17705.735 | H25: =(1+H5)*AVERAGE(E25:G25) -> -20146.28 | I25: =(1+I5)*AVERAGE(F25:H25) -> -20452.477 | J25: =(1+J5)*AVERAGE(G25:I25) -> -20989.617 | K25: =(1+K5)*AVERAGE(H25:J25) -> -22171.815 | L25: =(1+L5)*AVERAGE(I25:K25) -> -22901.007 | M25: =(1+M5)*AVERAGE(J25:L25) -> -23782.478 | N25: =(1+N5)*AVERAGE(K25:M25) -> -24787.908 | ... AF25: =(1+AF5)*AVERAGE(AC25:AE25) -> -35049.562
B26: 19 | C26: -Total Investing Flows | D26: =D23+D24+D25 -> -159666 | E26: =E23+E24+E25 -> -180789 | F26: =F23+F24+F25 -> -229793 | G26: =G23+G24+G25 -> -249627.12 | H26: =H23+H24+H25 -> -261966.75 | I26: =I23+I24+I25 -> -277828.65 | J26: =J23+J24+J25 -> -298955.88 | K26: =K23+K24+K25 -> -260992.21 | ... AF26: =AF23+AF24+AF25 -> -655542.02
B27: 20 | C27: (Flows related to leases) | D27: =Inputs!D71+Inputs!D72 -> -28085 | E27: =Inputs!C71+Inputs!C72 -> -27507 | F27: =Inputs!B71+Inputs!B72 -> -40953 | G27: 0 | H27: 0 | I27: 0 | J27: 0 | K27: 0 | L27: 0 | M27: 0 | N27: 0 | O27: 0 | P27: 0 | Q27: 0 | R27: 0 | S27: 0 | T27: 0 | U27: 0 | V27: 0 | W27: 0 | X27: 0 | Y27: 0 | Z27: 0 | AA27: 0 | AB27: 0 | AC27: 0 | AD27: 0 | AE27: 0 | AF27: 0
B28: 21 | C28: Flows related to debt | D28: =+SUM(Inputs!D69:D70) -> 149976 | E28: =+SUM(Inputs!C69:C70) -> 8335 | F28: =+SUM(Inputs!B69:B70) -> -42259 | G28: =G44-F44 -> -140976.16 | H28: =H44-G44 -> 75995.702 | I28: =I44-H44 -> 83147.319 | J28: =J44-I44 -> 102081.57 | K28: =K44-J44 -> 113185.48 | L28: =L44-K44 -> 84483.485 | M28: =M44-L44 -> 91538.312 | N28: =N44-M44 -> 99190.653 | ... AF28: =AF44-AE44 -> 156909.35
B29: 22 | C29: (Respurchases)/Issuance of stock | D29: ='Fin. Data'!D28 -> 0 | E29: ='Fin. Data'!C28 -> 0 | F29: ='Fin. Data'!B28 -> 0 | G29: =-G17*$D$65 -> 0 | H29: =-H17*$D$65 -> 0 | I29: =-I17*$D$65 -> 0 | J29: =-J17*$D$65 -> 0 | K29: =-K17*$E$65 -> 0 | L29: =-L17*$E$65 -> 0 | M29: =-M17*$E$65 -> 0 | N29: =-N17*$E$65 -> 0 | O29: =-O17*$E$65 -> 0 | P29: =-P17*$E$65 -> 0 | Q29: =-Q17*$E$65 -> 0 | R29: =-R17*$E$65 -> 0 | ... AF29: =-AF17*$E$65 -> 0
B30: 23 | C30: (Dividends) | D30: ='Fin. Data'!D27 -> -46721 | E30: ='Fin. Data'!C27 -> -49746 | F30: ='Fin. Data'!B27 -> -61468 | G30: =-$D$64*G17 -> -75091.87 | H30: =-$D$64*H17 -> -78158.625 | I30: =-$D$64*I17 -> -86990.917 | J30: =-$D$64*J17 -> -97875.112 | K30: =-$H$60*K17 -> -168094.78 | L30: =-$H$60*L17 -> -180829.94 | M30: =-$H$60*M17 -> -195033.09 | N30: =-$H$60*N17 -> -210445.79 | O30: =-$H$60*O17 -> -222510.72 | P30: =-$H$60*P17 -> -235765.67 | Q30: =-$H$60*Q17 -> -249824.1 | R30: =-$H$60*R17 -> -264708.32 | ... U30: =-$H$60*U17 -> -303005.39 | V30: =-$H$61*V17 -> -472896.21 | W30: =-$H$61*W17 -> -491382.31 | X30: =-$H$61*X17 -> -510651.3 | Y30: =-$H$61*Y17 -> -525240.3 | Z30: =-$H$61*Z17 -> -540868.31 | AA30: =-$H$61*AA17 -> -557018.31 | AB30: =-$H$61*AB17 -> -573706.15 | AC30: =-$H$61*AC17 -> -590967.09 | ... AF30: =-$H$61*AF17 -> -646385.95
B31: 24 | C31: Other financing flows | D31: =Inputs!D75 -> 23772 | E31: =Inputs!C75 -> 20220 | F31: =Inputs!B75 -> 31592 | G31: =(1+G5)*AVERAGE(D31:F31) -> 25944.019 | H31: =(1+H5)*AVERAGE(E31:G31) -> 27024.958 | I31: =(1+I5)*AVERAGE(F31:H31) -> 30000.19 | J31: =(1+J5)*AVERAGE(G31:I31) -> 29868.9 | K31: =(1+K5)*AVERAGE(H31:J31) -> 31281.857 | L31: =(1+L5)*AVERAGE(I31:K31) -> 32814.341 | M31: =(1+M5)*AVERAGE(J31:L31) -> 33827.435 | N31: =(1+N5)*AVERAGE(K31:M31) -> 35252.508 | ... AF31: =(1+AF5)*AVERAGE(AC31:AE31) -> 49909.163
B32: 25 | C32: -Total Financing flows | D32: =D27+D28+D29+D30+D31 -> 98942 | E32: =E27+E28+E29+E30+E31 -> -48698 | F32: =F27+F28+F29+F30+F31 -> -113088 | G32: =G27+G28+G29+G30+G31 -> -190124.01 | H32: =H27+H28+H29+H30+H31 -> 24862.035 | I32: =I27+I28+I29+I30+I31 -> 26156.593 | J32: =J27+J28+J29+J30+J31 -> 34075.357 | K32: =K27+K28+K29+K30+K31 -> -23627.451 | ... AF32: =AF27+AF28+AF29+AF30+AF31 -> -439567.43
A34: SUMMARY | B34: 26 | C34: Cash before shareholder returns | D34: =D22+D26+D27+D28+D31 -> 360630 | E34: =E22+E26+E27+E28+E31 -> 63744 | F34: =F22+F26+F27+F28+F31 -> -123087 | G34: =G22+G26+G27+G28+G31 -> -51421.298 | H34: =H22+H26+H27+H28+H31 -> 142008.36 | I34: =I22+I26+I27+I28+I31 -> 122168.64 | J34: =J22+J26+J27+J28+J31 -> 120882.34 | K34: =K22+K26+K27+K28+K31 -> 203717.73 | ... AF34: =AF22+AF26+AF27+AF28+AF31 -> 1168925.6
B35: 27 | C35: Returns to shareholders | D35: =-1*(D29+D30) -> 46721 | E35: =-1*(E29+E30) -> 49746 | F35: =-1*(F29+F30) -> 61468 | G35: =-1*(G29+G30) -> 75091.87 | H35: =-1*(H29+H30) -> 78158.625 | I35: =-1*(I29+I30) -> 86990.917 | J35: =-1*(J29+J30) -> 97875.112 | K35: =-1*(K29+K30) -> 168094.78 | ... AF35: =-1*(AF29+AF30) -> 646385.95
B36: 28 | C36: Excess cash acumulation | D36: =D34-D35 -> 313909 | E36: =E34-E35 -> 13998 | F36: =F34-F35 -> -184555 | G36: =G34-G35 -> -126513.17 | H36: =H34-H35 -> 63849.74 | I36: =I34-I35 -> 35177.723 | J36: =J34-J35 -> 23007.23 | K36: =K34-K35 -> 35622.951 | ... AF36: =AF34-AF35 -> 522539.66
A38: BALANCE SHEET | B38: 29 | C38: Intangible assets | D38: 274077 | E38: 306540 | F38: 354123 | G38: =+F38+(-G10) -> 393735.83 | H38: =+G38+(-H10) -> 437779.81 | I38: =+H38+(-I10) -> 486750.64 | J38: =+I38+(-J10) -> 541199.42 | K38: =+J38+(-K10) -> 601738.95 | L38: =+K38+(-L10) -> 669050.53 | M38: =+L38+(-M10) -> 743891.71 | N38: =+M38+(-N10) -> 827104.76 | ... AF38: =+AE38+(-AF10) -> 5577953.4 | AG38: =SUM(G38:AF38) -> 51922809
B39: 30 | C39: Accumulated amorization | F39: =-SUM(D10:F10) -> 102230 | G39: =F39-G10 -> 141842.83 | H39: =G39-H10 -> 185886.81 | I39: =H39-I10 -> 234857.64 | J39: =I39-J10 -> 289306.42 | K39: =J39-K10 -> 349845.95 | L39: =K39-L10 -> 417157.53 | M39: =L39-M10 -> 491998.71 | N39: =M39-N10 -> 575211.76 | ... AF39: =AE39-AF10 -> 5326060.4 | AG39: =SUM(G39:AF39) -> 45373591
B40: 31 | C40: PPE+Right of use Assets | D40: 1533306 | E40: 1752487 | F40: 2025832 | G40: =F40+(-G23) -> 2186298.3 | H40: =G40+(-H23) -> 2353613.9 | I40: =H40+(-I23) -> 2531692.4 | J40: =I40+(-J23) -> 2724017.2 | K40: =J40+(-K23) -> 2883230.8 | L40: =K40+(-L23) -> 3055181.4 | M40: =L40+(-M23) -> 3240888.2 | N40: =M40+(-N23) -> 3441451.5 | ... AF40: =AE40+(-AF23) -> 9142656.2 | AG40: =SUM(G40:AF40) -> 1.3290544e+08
B41: 32 | C41: Accumulated depreciation | D41: 885895 | E41: 1009123 | F41: 1124887 | G41: =F41-G9 -> 1173660.2 | H41: =G41-H9 -> 1226296.7 | I41: =H41-I9 -> 1282961.4 | J41: =I41-J9 -> 1343913.5 | K41: =J41-K9 -> 1409495.9 | L41: =K41-L9 -> 1478911.5 | M41: =L41-M9 -> 1552467 | N41: =M41-N9 -> 1630493.4 | ... AF41: =AE41-AF9 -> 4153327.1 | AG41: =SUM(G41:AF41) -> 60774747
A43: CASH & DEBT & DISCOUNTING | B43: 33 | C43: Ending cash balance | D43: ='Fin. Data'!D39 -> 736098 | E43: =E36+D43 -> 750096 | F43: =F36+E43 -> 565541 | G43: =G36+F43 -> 439027.83 | H43: =H36+G43 -> 502877.57 | I43: =I36+H43 -> 538055.29 | J43: =J36+I43 -> 561062.52 | K43: =K36+J43 -> 596685.48 | L43: =L36+K43 -> 596922.75 | ... AF43: =AF36+AE43 -> 4343202.2
B44: 34 | C44: Total Debt | D44: ='Fin. Data'!D58 -> 674932 | E44: ='Fin. Data'!C58 -> 460332 | F44: ='Fin. Data'!B58 -> 813766 | G44: =G12*Assumptions!$I$18 -> 672789.84 | H44: =H12*Assumptions!$I$18 -> 748785.55 | I44: =I12*Assumptions!$I$18 -> 831932.86 | J44: =J12*Assumptions!$I$18 -> 934014.43 | K44: =K12*Assumptions!$I$18 -> 1047199.9 | L44: =L12*Assumptions!$I$18 -> 1131683.4 | M44: =M12*Assumptions!$I$18 -> 1223221.7 | N44: =N12*Assumptions!$I$18 -> 1322412.4 | ... AF44: =AF12*Assumptions!$I$18 -> 3329714.7
B45: 35 | C45: Discount factor | F45: =1/((1+$F$50)^G50) -> 1 | G45: =1/((1+$F$50)^G49) -> 0.91335895 | H45: =1/((1+$F$50)^H49) -> 0.83422458 | I45: =1/((1+$F$50)^I49) -> 0.76194648 | J45: =1/((1+$F$50)^J49) -> 0.69593064 | K45: =1/((1+$F$50)^K49) -> 0.63563448 | L45: =1/((1+$F$50)^L49) -> 0.58056245 | M45: =1/((1+$F$50)^M49) -> 0.53026191 | N45: =1/((1+$F$50)^N49) -> 0.48431946 | ... AF45: =1/((1+$F$50)^AF49) -> 0.094771715
B46: 36 | C46: DF + 0.1% | E46: +0.1% | F46: =1/((1+$F$50+0.001)^G50) -> 1 | G46: =1/((1+$F$50+0.001)^G49) -> 0.91252549 | H46: =1/((1+$F$50+0.001)^H49) -> 0.83270277 | I46: =1/((1+$F$50+0.001)^I49) -> 0.7598625 | J46: =1/((1+$F$50+0.001)^J49) -> 0.6933939 | K46: =1/((1+$F$50+0.001)^K49) -> 0.63273961 | L46: =1/((1+$F$50+0.001)^L49) -> 0.57739102 | M46: =1/((1+$F$50+0.001)^M49) -> 0.52688402 | N46: =1/((1+$F$50+0.001)^N49) -> 0.4807951 | ... AF46: =1/((1+$F$50+0.001)^AF49) -> 0.092548655
B47: 37 | C47: DF + 0.5% | E47: +0.5% | F47: =1/((1+$F$50+0.005)^G50) -> 1 | G47: =1/((1+$F$50+0.005)^G49) -> 0.90920679 | H47: =1/((1+$F$50+0.005)^H49) -> 0.82665699 | I47: =1/((1+$F$50+0.005)^I49) -> 0.75160215 | J47: =1/((1+$F$50+0.005)^J49) -> 0.68336178 | K47: =1/((1+$F$50+0.005)^K49) -> 0.62131717 | L47: =1/((1+$F$50+0.005)^L49) -> 0.56490579 | M47: =1/((1+$F$50+0.005)^M49) -> 0.51361618 | N47: =1/((1+$F$50+0.005)^N49) -> 0.46698332 | ... AF47: =1/((1+$F$50+0.005)^AF49) -> 0.084183979
A49: Discount Rate | B49: 38 | C49: Risk free rate | D49: Equity premium | E49: Firm premium | F49: Total | G49: 1 | H49: 2 | I49: 3 | J49: 4 | K49: 5 | L49: 6 | M49: 7 | N49: 8 | O49: 9 | P49: 10 | Q49: 11 | R49: 12 | S49: 13 | T49: 14 | U49: 15 | V49: 16 | W49: 17 | X49: 18 | Y49: 19 | Z49: 20 | AA49: 21 | AB49: 22 | AC49: 23 | AD49: 24 | AE49: 25 | AF49: 26
C50: 0.034 | D50: =Assumptions!G7 -> 0.0533598 | E50: 0.0075 | F50: =E50+D50+C50 -> 0.0948598 | G50: 0
A52: Modelling factors | D52: Short Term | E52: Long Term | F52: Reference (line)
C53: Depreciation factor | D53: =-Assumptions!G22 -> -0.02407563 | E53: =-Assumptions!G22 -> -0.02407563 | F53: % PPE
C54: Amortization factor | D54: =-Assumptions!G26 -> -0.11186177 | E54: =-Assumptions!G26 -> -0.11186177 | F54: % IA
C55: Stock-based comp | D55: 0 | E55: 0 | F55: - -
C56: Tax Rate | D56: 0.306 | E56: 0.306 | F56: % (line 9)
C57: Interest Rate on debt | D57: =C50+0.0142 -> 0.0482 | E57: =C50+0.0142 -> 0.0482 | F57: Credit Rating (Moody's A2) Spread
C58: Interest Rate on cash | D58: =C50 -> 0.034 | E58: 0.01 | F58: Risk Free Rate (l38)
C59: PPE+ROA | D59: - - | E59: - - | F59: Growing with capex
C60: Working capital flows | D60: =Assumptions!I37 -> -0.5751839 | E60: =Assumptions!I37 -> -0.5751839 | F60: % of change revenues (l2) | H60: 0.4
C61: Intangible Assets | D61: - - | E61: - - | F61: Growing with amortization | H61: 0.6
C62: Capex | D62: =-Assumptions!I14 -> -0.039138133 | E62: -0.03 | F62: % revenue (l2)
C63: Acquisition factor | D63: =-Assumptions!I30 -> -0.017428059 | E63: -0.015 | F63: % revenue (l2)
C64: Dividends | D64: =-Assumptions!I39 -> 0.25631565 | E64: 40%/60% | F64: % net income (l11)
C65: Repurchases | D65: 0 | E65: 0 | F65: - -
C66: Leases | D66: =Assumptions!I34 -> 0.026661327 | E66: 0.03 | F66: % revenue (l2)
C67: Cash Costs for EBIT | D67: - - | E67: - - | F67: - -
A69: Valuation | D69: ¥ millions
C70: Value of flows | D70: =SUMPRODUCT(G35:AF35,G45:AF45)+((AF43-AF44)*AF45) -> 2331046.2 | E70: =D70/D72 -> 0.57712669
C71: Value of perpetuity | D71: =(AF34/(F50-AF5))*AF45 -> 1708008.4 | E71: =D71/D72 -> 0.42287331
C72: Total Value | D72: =D70+D71 -> 4039054.7
C73: Actual share price | D73: =OP!C17 -> 25025
C74: Total value vs Mkt Cap | D74: =D75/D73-1 -> -0.4485418
C75: Estimated NPV per share | D75: =D72*1000000/OP!C18 -> 13800.241
A77: Sensibility | C77: Sensitivity +0.1% | D77: =(SUMPRODUCT(G35:AF35,G45:AF45)+((AF43-AF44)*AF45)+(AF34/(F50+0.001-AF5))*AF45)*1000000/OP!C18 -> 13711.633 | E77: =D77/D75-1 -> -0.0064208107
C78: Sensitivity +0.5% | D78: =(SUMPRODUCT(G35:AF35,G45:AF45)+((AF43-AF44)*AF45)+(AF34/(F50+0.005-AF5))*AF45)*1000000/OP!C18 -> 13382.565 | E78: =D78/D75-1 -> -0.030265855
A80: Notes
A81: https://www.daikin.com/-/media/Project/Daikin/daikin_com/investor/financial/images/Financial-Data/Financial-Date-2023-pdf.pdf?rev=-1&hash=F47CDEB12C0ECC8948405606CEFBA9D9
A82: https://www.daikin.com/-/media/Project/Daikin/daikin_com/investor/data/fusion/fusion25-h2/presentation-pdf.pdf?rev=-1&hash=D64833AF0BC0FDCB111A54637AB91CE2
A83: https://www.cnbc.com/2023/06/13/investing-is-japan-inc-finally-serious-about-corporate-governance-.html

Sheet Assumptions
B2: Tax rate | C2: =107941/373384 -> 0.28908845
B4: Weight | C4: Region | D4: Equity Risk Premium
B5: 0.17 | C5: Japan | E5: 0.0607
B6: 0.32 | C6: US | E6: 0.05 | G6: Weighted Average
B7: 0.18 | C7: Europe | E7: 0.05 | G7: =E5*B5+E6*B6+E7*B7+E8*B8+E9*B9+E10*B10 -> 0.0533598
B8: 0.15 | C8: Asia and Oceania | E8: 0.05
B9: 0.12 | C9: China | E9: 0.0607
B10: 0.06 | C10: Other | E10: =AVERAGEA(E5:E9) -> 0.05428
B12: Year | C12: 2022 | D12: 2021 | E12: 2020 | F12: 2019 | G12: 2018
B13: Capex | C13: 175076 | D13: 114106 | E13: 104971 | F13: 98094 | G13: 85487 | I13: Average
B14: Revenue | C14: 3981578 | D14: 3109106 | E14: 2493386 | F14: 2550305 | G14: 2481109 | I14: =AVERAGE(C15:G15) -> 0.039138133
B15: Capex/Revenue | C15: =C13/C14 -> 0.043971511 | D15: =D13/D14 -> 0.036700582 | E15: =E13/E14 -> 0.042099779 | F15: =F13/F14 -> 0.038463635 | G15: =G13/G14 -> 0.034455157
B17: Debt | C17: ='Fin. Data'!B58 -> 813766 | D17: ='Fin. Data'!C58 -> 460332 | E17: ='Fin. Data'!D58 -> 674932 | F17: ='Fin. Data'!E58 -> 447903 | G17: ='Fin. Data'!F58 -> 493254 | I17: Average
B18: EBITDA | C18: ='Fin. Data'!B19 -> 537584 | D18: ='Fin. Data'!C19 -> 449532 | E18: ='Fin. Data'!D19 -> 380172 | F18: ='Fin. Data'!E19 -> 359040 | G18: ='Fin. Data'!F19 -> 378846 | I18: =AVERAGE(C19:G19) -> 1.3725195
B19: Debt/EBITDA | C19: ='Fin. Data'!B58/'Fin. Data'!B19 -> 1.5137467 | D19: ='Fin. Data'!C58/'Fin. Data'!C19 -> 1.024025 | E19: ='Fin. Data'!D58/'Fin. Data'!D19 -> 1.7753333 | F19: ='Fin. Data'!E58/'Fin. Data'!E19 -> 1.2475017 | G19: ='Fin. Data'!F58/'Fin. Data'!F19 -> 1.3019908
B21: Depreciation | C21: 51181 | D21: 40952 | E21: 36178 | G21: Average
B22: PPE | C22: 2025832 | D22: 1752487 | E22: 1533306 | G22: =AVERAGE(C23:E23) -> 0.02407563
B23: Depreciation/PPE | C23: =C21/C22 -> 0.025264188 | D23: =D21/D22 -> 0.023367934 | E23: =E21/E22 -> 0.023594768
B25: Amortization | C25: 39496 | D25: 32684 | E25: 30050 | G25: Average
B26: Intangible Assets | C26: 274077 | D26: 306540 | E26: 354123 | G26: =AVERAGE(C27:E27) -> 0.11186177
B27: Amortization/Intangible Assets | C27: =C25/C26 -> 0.14410549 | D27: =D25/D26 -> 0.1066223 | E27: =E25/E26 -> 0.084857521
B29: Aquisitions | C29: 34920 | D29: 46221 | E29: 43371 | F29: 41285 | G29: 74237 | I29: Average
B30: Revenue | C30: 3981578 | D30: 3109106 | E30: 2493386 | F30: 2550305 | G30: 2481109 | I30: =AVERAGE(C31:G31) -> 0.017428059
B31: Aquisitions/Revenue | C31: =C29/C30 -> 0.008770392 | D31: =D29/D30 -> 0.014866331 | E31: =E29/E30 -> 0.017394419 | F31: =F29/F30 -> 0.01618826 | G31: =G29/G30 -> 0.029920894
B33: Leases | C33: =Inputs!B49+Inputs!B45 -> 127039 | D33: =Inputs!C49+Inputs!C45 -> 102384 | E33: =Inputs!D49+Inputs!D45 -> 85375 | F33: =Inputs!E49+Inputs!E45 -> 75782 | G33: =Inputs!F49+Inputs!F45 -> 11200 | I33: Average
B34: Revenue | C34: 3981578 | D34: 3109106 | E34: 2493386 | F34: 2550305 | G34: 2481109 | I34: =AVERAGE(C35:G35) -> 0.026661327
B35: Leases/Revenue | C35: =C33/C34 -> 0.031906696 | D35: =D33/D34 -> 0.032930366 | E35: =E33/E34 -> 0.034240587 | F35: =F33/F34 -> 0.029714877 | G35: =G33/G34 -> 0.0045141104
I36: Average
B37: Working Capital Flows/Revenue Change | C37: =Inputs!B62/(Inputs!B6-Inputs!C6) -> -0.45063223 | D37: =Inputs!C62/(Inputs!C6-Inputs!D6) -> -0.37026083 | E37: =Inputs!D62/(Inputs!D6-Inputs!E6) -> -0.022523235 | F37: =Inputs!E62/(Inputs!E6-Inputs!F6) -> -1.3815683 | G37: =Inputs!F62/(Inputs!F6-Inputs!G6) -> -0.65093493 | I37: =AVERAGE(C37:G37) -> -0.5751839
B39: Payout ratio | C39: ='Fin. Data'!B36 -> -0.23847452 | D39: ='Fin. Data'!C36 -> -0.22849662 | E39: ='Fin. Data'!D36 -> -0.2990144 | F39: ='Fin. Data'!E36 -> -0.29127521 | G39: ='Fin. Data'!F36 -> -0.2243175 | I39: =AVERAGE(C39:G39) -> -0.25631565
B41: Company | C41: =Peers!C74 -> Daikin Industries,Ltd. (6367.T) | D41: =Peers!D74 -> #VALUE! | E41: =Peers!E74 -> #VALUE! | F41: =Peers!F74 -> #VALUE! | G41: =Peers!G74 -> #VALUE! | I41: Average
B42: Investment in R&D | C42: =102202*1000 -> 102202000 | D42: =(295*1000000)*147.37 -> 43474150000 | E42: =(539*1000000)*147.37 -> 79432430000 | F42: =(212.2*1000000)*147.37 -> 31271914000 | G42: =212.3*1000000000 -> 212300000000 | I42: =(C42*0.0076+D42+E42+F42+G42*0.0076)/5 -> 3.115855e+10
B43: Net Sales | C43: =Peers!C10*1000 -> 3981578000 | D43: =(25299*1000000)*147.37 -> 3728313630000 | E43: =20421*1000000*147.37 -> 3009442770000 | F43: =12640.8*1000000*147.37 -> 1862874696000 | G43: =Peers!G10*1000000 -> 692443000000 | I43: =(C43*0.0076+D43+E43+F43+G43*0.0076)/5 -> 1.7211848e+12
B44: R&D/Net Sales | C44: =C42/C43 -> 0.025668717 | D44: =D42/D43 -> 0.01166054 | E44: =E42/E43 -> 0.026394398 | F44: =F42/F43 -> 0.016786912 | G44: =G42/G43 -> 0.30659563 | I44: =AVERAGE(C44:G44) -> 0.07742124
G45: =59.1/1947.1 -> 0.030352832
B46: Investment in R&D (in dollars $) | C46: =C42*0.0076 -> 776735.2 | G46: =G42*0.0076 -> 1613480000
B47: Net Sales (in dollars $) | C47: =C43*0.0076 -> 30259993 | G47: =G43*0.0076 -> 5262566800

Sheet Fin. Data
A1: =Inputs!H3 -> Daikin Industries,Ltd. (6367.T)
A2: =Inputs!G2 -> Figures in Millions of JPY
A3: Results
B4: =OP!J17 -> 2022 | C4: =B4-1 -> 2021 | D4: =C4-1 -> 2020 | E4: =D4-1 -> 2019 | F4: =E4-1 -> 2018 | G4: =F4-1 -> 2017 | H4: =G4-1 -> 2016 | I4: =H4-1 -> 2015 | J4: =I4-1 -> 2014 | ... M4: =L4-1 -> 2011
A5: Net Sales | B5: =_xlfn.XLOOKUP($A5,Inputs!$A:$A,Inputs!B:B,,0) -> 3981578 | C5: =_xlfn.XLOOKUP($A5,Inputs!$A:$A,Inputs!C:C,,0) -> 3109106 | D5: =_xlfn.XLOOKUP($A5,Inputs!$A:$A,Inputs!D:D,,0) -> 2493386 | E5: =_xlfn.XLOOKUP($A5,Inputs!$A:$A,Inputs!E:E,,0) -> 2550305 | F5: =_xlfn.XLOOKUP($A5,Inputs!$A:$A,Inputs!F:F,,0) -> 2481109 | G5: =_xlfn.XLOOKUP($A5,Inputs!$A:$A,Inputs!G:G,,0) -> 2290560 | H5: =_xlfn.XLOOKUP($A5,Inputs!$A:$A,Inputs!H:H,,0) -> 2043968 | I5: =_xlfn.XLOOKUP($A5,Inputs!$A:$A,Inputs!I:I,,0) -> 2043691 | J5: =_xlfn.XLOOKUP($A5,Inputs!$A:$A,Inputs!J:J,,0) -> 1915013 | K5: =_xlfn.XLOOKUP($A5,Inputs!$A:$A,Inputs!K:K,,0) -> 1787679 | L5: =_xlfn.XLOOKUP($A5,Inputs!$A:$A,Inputs!L:L,,0) -> 1290903 | M5: =_xlfn.XLOOKUP($A5,Inputs!$A:$A,Inputs!M:M,,0) -> 1218700
A6: Growth vs. Previous year | B6: =IFERROR(B5/C5-1,"-") -> 0.28061829 | C6: =IFERROR(C5/D5-1,"-") -> 0.24694131 | D6: =IFERROR(D5/E5-1,"-") -> -0.022318507 | E6: =IFERROR(E5/F5-1,"-") -> 0.027889142 | F6: =IFERROR(F5/G5-1,"-") -> 0.083188827 | G6: =IFERROR(G5/H5-1,"-") -> 0.12064377 | H6: =IFERROR(H5/I5-1,"-") -> 0.00013553908 | I6: =IFERROR(I5/J5-1,"-") -> 0.067194322 | ... L6: =IFERROR(L5/M5-1,"-") -> 0.059245918 | M6: =IFERROR(M5/#REF!-1,"-") -> -
A7: Gross Profit | B7: =_xlfn.XLOOKUP($A7,Inputs!$A:$A,Inputs!B:B,,0) -> 1331476 | C7: =_xlfn.XLOOKUP($A7,Inputs!$A:$A,Inputs!C:C,,0) -> 1057339 | D7: =_xlfn.XLOOKUP($A7,Inputs!$A:$A,Inputs!D:D,,0) -> 864136 | E7: =_xlfn.XLOOKUP($A7,Inputs!$A:$A,Inputs!E:E,,0) -> 884898 | F7: =_xlfn.XLOOKUP($A7,Inputs!$A:$A,Inputs!F:F,,0) -> 868923 | G7: =_xlfn.XLOOKUP($A7,Inputs!$A:$A,Inputs!G:G,,0) -> 798829 | H7: =_xlfn.XLOOKUP($A7,Inputs!$A:$A,Inputs!H:H,,0) -> 730935 | I7: =_xlfn.XLOOKUP($A7,Inputs!$A:$A,Inputs!I:I,,0) -> 711576 | J7: =_xlfn.XLOOKUP($A7,Inputs!$A:$A,Inputs!J:J,,0) -> 649901 | K7: =_xlfn.XLOOKUP($A7,Inputs!$A:$A,Inputs!K:K,,0) -> 568323 | L7: =_xlfn.XLOOKUP($A7,Inputs!$A:$A,Inputs!L:L,,0) -> 388047 | M7: =_xlfn.XLOOKUP($A7,Inputs!$A:$A,Inputs!M:M,,0) -> 371901
A8: % over sales | B8: =IFERROR(B7/B$5,"-") -> 0.33440912 | C8: =IFERROR(C7/C$5,"-") -> 0.34007814 | D8: =IFERROR(D7/D$5,"-") -> 0.34657129 | E8: =IFERROR(E7/E$5,"-") -> 0.34697732 | F8: =IFERROR(F7/F$5,"-") -> 0.35021557 | G8: =IFERROR(G7/G$5,"-") -> 0.34874834 | H8: =IFERROR(H7/H$5,"-") -> 0.35760589 | I8: =IFERROR(I7/I$5,"-") -> 0.34818179 | ... M8: =IFERROR(M7/M$5,"-") -> 0.30516206
A9: Operating expenses | B9: =B5-B11 -> 3616685 | C9: =C5-C11 -> 2797804 | D9: =D5-D11 -> 2255459 | E9: =E5-E11 -> 2308651 | F9: =F5-F11 -> 2205850 | G9: =G5-G11 -> 2039744 | H9: =H5-H11 -> 1813155 | I9: =I5-I11 -> 1828205 | ... M9: =M5-M11 -> 1139702
A10: % over sales | B10: =IFERROR(B9/B$5,"-") -> 0.90835468 | C10: =IFERROR(C9/C$5,"-") -> 0.89987411 | D10: =IFERROR(D9/D$5,"-") -> 0.90457675 | E10: =IFERROR(E9/E$5,"-") -> 0.90524506 | F10: =IFERROR(F9/F$5,"-") -> 0.88905808 | G10: =IFERROR(G9/G$5,"-") -> 0.89050014 | H10: =IFERROR(H9/H$5,"-") -> 0.88707602 | I10: =IFERROR(I9/I$5,"-") -> 0.89456038 | ... M10: =IFERROR(M9/M$5,"-") -> 0.93517847
A11: Operating Income | B11: =_xlfn.XLOOKUP($A11,Inputs!$A:$A,Inputs!B:B,,0) -> 364893 | C11: =_xlfn.XLOOKUP($A11,Inputs!$A:$A,Inputs!C:C,,0) -> 311302 | D11: =_xlfn.XLOOKUP($A11,Inputs!$A:$A,Inputs!D:D,,0) -> 237927 | E11: =_xlfn.XLOOKUP($A11,Inputs!$A:$A,Inputs!E:E,,0) -> 241654 | F11: =_xlfn.XLOOKUP($A11,Inputs!$A:$A,Inputs!F:F,,0) -> 275259 | G11: =_xlfn.XLOOKUP($A11,Inputs!$A:$A,Inputs!G:G,,0) -> 250816 | H11: =_xlfn.XLOOKUP($A11,Inputs!$A:$A,Inputs!H:H,,0) -> 230813 | I11: =_xlfn.XLOOKUP($A11,Inputs!$A:$A,Inputs!I:I,,0) -> 215486 | J11: =_xlfn.XLOOKUP($A11,Inputs!$A:$A,Inputs!J:J,,0) -> 185291 | K11: =_xlfn.XLOOKUP($A11,Inputs!$A:$A,Inputs!K:K,,0) -> 155203 | L11: =_xlfn.XLOOKUP($A11,Inputs!$A:$A,Inputs!L:L,,0) -> 75352 | M11: =_xlfn.XLOOKUP($A11,Inputs!$A:$A,Inputs!M:M,,0) -> 78998
A12: Operating Margin | B12: =IFERROR(B11/B$5,"-") -> 0.091645323 | C12: =IFERROR(C11/C$5,"-") -> 0.10012589 | D12: =IFERROR(D11/D$5,"-") -> 0.095423252 | E12: =IFERROR(E11/E$5,"-") -> 0.094754941 | F12: =IFERROR(F11/F$5,"-") -> 0.11094192 | G12: =IFERROR(G11/G$5,"-") -> 0.10949986 | H12: =IFERROR(H11/H$5,"-") -> 0.11292398 | I12: =IFERROR(I11/I$5,"-") -> 0.10543962 | ... M12: =IFERROR(M11/M$5,"-") -> 0.064821531
A13: Growth vs. Previous year | B13: =IFERROR(B12/C12-1,"-") -> -0.084699031 | C13: =IFERROR(C12/D12-1,"-") -> 0.049281872 | D13: =IFERROR(D12/E12-1,"-") -> 0.0070530431 | E13: =IFERROR(E12/F12-1,"-") -> -0.14590499 | F13: =IFERROR(F12/G12-1,"-") -> 0.013169526 | G13: =IFERROR(G12/H12-1,"-") -> -0.030322337 | H13: =IFERROR(H12/I12-1,"-") -> 0.070982431 | I13: =IFERROR(I12/J12-1,"-") -> 0.089735825 | ... L13: =IFERROR(L12/M12-1,"-") -> -0.099503791 | M13: =IFERROR(M12/#REF!-1,"-") -> -
A14: Net Financial Cost | B14: =_xlfn.XLOOKUP($A14,Inputs!$A:$A,Inputs!B:B,,0) -> -8730 | C14: =_xlfn.XLOOKUP($A14,Inputs!$A:$A,Inputs!C:C,,0) -> -638 | D14: =_xlfn.XLOOKUP($A14,Inputs!$A:$A,Inputs!D:D,,0) -> 2772 | E14: =_xlfn.XLOOKUP($A14,Inputs!$A:$A,Inputs!E:E,,0) -> -3039 | F14: =_xlfn.XLOOKUP($A14,Inputs!$A:$A,Inputs!F:F,,0) -> -2293 | G14: =_xlfn.XLOOKUP($A14,Inputs!$A:$A,Inputs!G:G,,0) -> -3838 | H14: =_xlfn.XLOOKUP($A14,Inputs!$A:$A,Inputs!H:H,,0) -> -3174 | I14: =_xlfn.XLOOKUP($A14,Inputs!$A:$A,Inputs!I:I,,0) -> -1526 | J14: =_xlfn.XLOOKUP($A14,Inputs!$A:$A,Inputs!J:J,,0) -> -3097 | K14: =_xlfn.XLOOKUP($A14,Inputs!$A:$A,Inputs!K:K,,0) -> -5129 | L14: =_xlfn.XLOOKUP($A14,Inputs!$A:$A,Inputs!L:L,,0) -> -4043 | M14: =_xlfn.XLOOKUP($A14,Inputs!$A:$A,Inputs!M:M,,0) -> -3165
A15: Other Expenses (Revenues) | B15: =_xlfn.XLOOKUP($A15,Inputs!$A:$A,Inputs!B:B,,0) -> 9533 | C15: =_xlfn.XLOOKUP($A15,Inputs!$A:$A,Inputs!C:C,,0) -> 9832 | D15: =_xlfn.XLOOKUP($A15,Inputs!$A:$A,Inputs!D:D,,0) -> -8652 | E15: =_xlfn.XLOOKUP($A15,Inputs!$A:$A,Inputs!E:E,,0) -> 11099 | F15: =_xlfn.XLOOKUP($A15,Inputs!$A:$A,Inputs!F:F,,0) -> -4272 | G15: =_xlfn.XLOOKUP($A15,Inputs!$A:$A,Inputs!G:G,,0) -> -1017 | H15: =_xlfn.XLOOKUP($A15,Inputs!$A:$A,Inputs!H:H,,0) -> -3012 | I15: =_xlfn.XLOOKUP($A15,Inputs!$A:$A,Inputs!I:I,,0) -> -12882 | J15: =_xlfn.XLOOKUP($A15,Inputs!$A:$A,Inputs!J:J,,0) -> 5446 | K15: =_xlfn.XLOOKUP($A15,Inputs!$A:$A,Inputs!K:K,,0) -> -1328 | L15: =_xlfn.XLOOKUP($A15,Inputs!$A:$A,Inputs!L:L,,0) -> 6612 | M15: =_xlfn.XLOOKUP($A15,Inputs!$A:$A,Inputs!M:M,,0) -> 1288
A16: EBIT | B16: =B11-B15 -> 355360 | C16: =C11-C15 -> 301470 | D16: =D11-D15 -> 246579 | E16: =E11-E15 -> 230555 | F16: =F11-F15 -> 279531 | G16: =G11-G15 -> 251833 | H16: =H11-H15 -> 233825 | I16: =I11-I15 -> 228368 | ... M16: =M11-M15 -> 77710
A17: Depreciation & Amortization | B17: =_xlfn.XLOOKUP($A17,Inputs!$A:$A,Inputs!B:B,,0) -> 182224 | C17: =_xlfn.XLOOKUP($A17,Inputs!$A:$A,Inputs!C:C,,0) -> 148062 | D17: =_xlfn.XLOOKUP($A17,Inputs!$A:$A,Inputs!D:D,,0) -> 133593 | E17: =_xlfn.XLOOKUP($A17,Inputs!$A:$A,Inputs!E:E,,0) -> 128485 | F17: =_xlfn.XLOOKUP($A17,Inputs!$A:$A,Inputs!F:F,,0) -> 99315 | G17: =_xlfn.XLOOKUP($A17,Inputs!$A:$A,Inputs!G:G,,0) -> 94833 | H17: =_xlfn.XLOOKUP($A17,Inputs!$A:$A,Inputs!H:H,,0) -> 85029 | I17: =_xlfn.XLOOKUP($A17,Inputs!$A:$A,Inputs!I:I,,0) -> 84202 | J17: =_xlfn.XLOOKUP($A17,Inputs!$A:$A,Inputs!J:J,,0) -> 77766 | K17: =_xlfn.XLOOKUP($A17,Inputs!$A:$A,Inputs!K:K,,0) -> 78900 | L17: =_xlfn.XLOOKUP($A17,Inputs!$A:$A,Inputs!L:L,,0) -> 51523 | M17: =_xlfn.XLOOKUP($A17,Inputs!$A:$A,Inputs!M:M,,0) -> 50525
A18: Changes Net Working Capital | B18: =_xlfn.XLOOKUP($A18,Inputs!$A:$A,Inputs!B:B,,0) -> 318333 | C18: =_xlfn.XLOOKUP($A18,Inputs!$A:$A,Inputs!C:C,,0) -> -189514 | D18: =_xlfn.XLOOKUP($A18,Inputs!$A:$A,Inputs!D:D,,0) -> -8398 | E18: =_xlfn.XLOOKUP($A18,Inputs!$A:$A,Inputs!E:E,,0) -> 58668 | F18: =_xlfn.XLOOKUP($A18,Inputs!$A:$A,Inputs!F:F,,0) -> -63926 | G18: =_xlfn.XLOOKUP($A18,Inputs!$A:$A,Inputs!G:G,,0) -> 55820 | H18: =_xlfn.XLOOKUP($A18,Inputs!$A:$A,Inputs!H:H,,0) -> -22721 | I18: =_xlfn.XLOOKUP($A18,Inputs!$A:$A,Inputs!I:I,,0) -> -58205 | J18: =_xlfn.XLOOKUP($A18,Inputs!$A:$A,Inputs!J:J,,0) -> 93592 | K18: =_xlfn.XLOOKUP($A18,Inputs!$A:$A,Inputs!K:K,,0) -> -58679 | L18: =_xlfn.XLOOKUP($A18,Inputs!$A:$A,Inputs!L:L,,0) -> 138068 | M18: =_xlfn.XLOOKUP($A18,Inputs!$A:$A,Inputs!M:M,,0) -> 97060
A19: EBITDA | B19: =B11-B15+B17 -> 537584 | C19: =C11-C15+C17 -> 449532 | D19: =D11-D15+D17 -> 380172 | E19: =E11-E15+E17 -> 359040 | F19: =F11-F15+F17 -> 378846 | G19: =G11-G15+G17 -> 346666 | H19: =H11-H15+H17 -> 318854 | I19: =I11-I15+I17 -> 312570 | ... M19: =M11-M15+M17 -> 128235
A20: EBITDA Margin | B20: =IFERROR(B19/B$5,"-") -> 0.13501782 | C20: =IFERROR(C19/C$5,"-") -> 0.14458561 | D20: =IFERROR(D19/D$5,"-") -> 0.15247218 | E20: =IFERROR(E19/E$5,"-") -> 0.14078316 | F20: =IFERROR(F19/F$5,"-") -> 0.1526922 | G20: =IFERROR(G19/G$5,"-") -> 0.15134552 | H20: =IFERROR(H19/H$5,"-") -> 0.15599755 | I20: =IFERROR(I19/I$5,"-") -> 0.15294386 | ... M20: =IFERROR(M19/M$5,"-") -> 0.10522278
A21: Taxes | B21: =_xlfn.XLOOKUP($A21,Inputs!$A:$A,Inputs!B:B,,0) -> -107941 | C21: =_xlfn.XLOOKUP($A21,Inputs!$A:$A,Inputs!C:C,,0) -> -102786 | D21: =_xlfn.XLOOKUP($A21,Inputs!$A:$A,Inputs!D:D,,0) -> -75797 | E21: =_xlfn.XLOOKUP($A21,Inputs!$A:$A,Inputs!E:E,,0) -> -78982 | F21: =_xlfn.XLOOKUP($A21,Inputs!$A:$A,Inputs!F:F,,0) -> -79645 | G21: =_xlfn.XLOOKUP($A21,Inputs!$A:$A,Inputs!G:G,,0) -> -56908 | H21: =_xlfn.XLOOKUP($A21,Inputs!$A:$A,Inputs!H:H,,0) -> -70688 | I21: =_xlfn.XLOOKUP($A21,Inputs!$A:$A,Inputs!I:I,,0) -> -64090 | J21: =_xlfn.XLOOKUP($A21,Inputs!$A:$A,Inputs!J:J,,0) -> -67965 | K21: =_xlfn.XLOOKUP($A21,Inputs!$A:$A,Inputs!K:K,,0) -> -55959 | L21: =_xlfn.XLOOKUP($A21,Inputs!$A:$A,Inputs!L:L,,0) -> -34336 | M21: =_xlfn.XLOOKUP($A21,Inputs!$A:$A,Inputs!M:M,,0) -> -35948
A22: % Tax | B22: =IFERROR(B21/B$5,"-") -> -0.027110106 | C22: =IFERROR(C21/C$5,"-") -> -0.033059664 | D22: =IFERROR(D21/D$5,"-") -> -0.030399224 | E22: =IFERROR(E21/E$5,"-") -> -0.030969629 | F22: =IFERROR(F21/F$5,"-") -> -0.032100565 | G22: =IFERROR(G21/G$5,"-") -> -0.024844579 | H22: =IFERROR(H21/H$5,"-") -> -0.034583712 | I22: =IFERROR(I21/I$5,"-") -> -0.031359927 | ... M22: =IFERROR(M21/M$5,"-") -> -0.029497005
A23: Net Income | B23: =_xlfn.XLOOKUP($A23,Inputs!$A:$A,Inputs!B:B,,0) -> 257755 | C23: =_xlfn.XLOOKUP($A23,Inputs!$A:$A,Inputs!C:C,,0) -> 217710 | D23: =_xlfn.XLOOKUP($A23,Inputs!$A:$A,Inputs!D:D,,0) -> 156250 | E23: =_xlfn.XLOOKUP($A23,Inputs!$A:$A,Inputs!E:E,,0) -> 170732 | F23: =_xlfn.XLOOKUP($A23,Inputs!$A:$A,Inputs!F:F,,0) -> 189049 | G23: =_xlfn.XLOOKUP($A23,Inputs!$A:$A,Inputs!G:G,,0) -> 189053 | H23: =_xlfn.XLOOKUP($A23,Inputs!$A:$A,Inputs!H:H,,0) -> 153939 | I23: =_xlfn.XLOOKUP($A23,Inputs!$A:$A,Inputs!I:I,,0) -> 136988 | J23: =_xlfn.XLOOKUP($A23,Inputs!$A:$A,Inputs!J:J,,0) -> 119675 | K23: =_xlfn.XLOOKUP($A23,Inputs!$A:$A,Inputs!K:K,,0) -> 92787 | L23: =_xlfn.XLOOKUP($A23,Inputs!$A:$A,Inputs!L:L,,0) -> 43585 | M23: =_xlfn.XLOOKUP($A23,Inputs!$A:$A,Inputs!M:M,,0) -> 41173
A24: Net Income Margin | B24: =IFERROR(B23/B$5,"-") -> 0.064736896 | C24: =IFERROR(C23/C$5,"-") -> 0.070023344 | D24: =IFERROR(D23/D$5,"-") -> 0.062665789 | E24: =IFERROR(E23/E$5,"-") -> 0.066945718 | F24: =IFERROR(F23/F$5,"-") -> 0.076195363 | G24: =IFERROR(G23/G$5,"-") -> 0.082535712 | H24: =IFERROR(H23/H$5,"-") -> 0.075313801 | I24: =IFERROR(I23/I$5,"-") -> 0.067029703 | ... M24: =IFERROR(M23/M$5,"-") -> 0.03378436
A25: Growth vs. Previous year | B25: =IFERROR(B24/C24-1,"-") -> -0.075495517 | C25: =IFERROR(C24/D24-1,"-") -> 0.11740945 | D25: =IFERROR(D24/E24-1,"-") -> -0.063931343 | E25: =IFERROR(E24/F24-1,"-") -> -0.1213938 | F25: =IFERROR(F24/G24-1,"-") -> -0.076819464 | G25: =IFERROR(G24/H24-1,"-") -> 0.095890929 | H25: =IFERROR(H24/I24-1,"-") -> 0.12358848 | I25: =IFERROR(I24/J24-1,"-") -> 0.072594543 | ... L25: =IFERROR(L24/M24-1,"-") -> -0.00062670743 | M25: =IFERROR(M24/#REF!-1,"-") -> -
A26: Cash Generated | B26: =B39-C39 -> -199956 | C26: =C39-D39 -> 81521 | D26: =D39-E39 -> 365305 | E26: =E39-F39 -> 3012 | F26: =F39-G39 -> 10754 | G26: =G39-H39 -> 12934 | H26: =H39-I39 -> 52888 | I26: =I39-J39 -> 4256 | ... M26: =M39-N39 -> 135648
A27: Dividends | B27: =_xlfn.XLOOKUP($A27,Inputs!$A:$A,Inputs!B:B,,0) -> -61468 | C27: =_xlfn.XLOOKUP($A27,Inputs!$A:$A,Inputs!C:C,,0) -> -49746 | D27: =_xlfn.XLOOKUP($A27,Inputs!$A:$A,Inputs!D:D,,0) -> -46721 | E27: =_xlfn.XLOOKUP($A27,Inputs!$A:$A,Inputs!E:E,,0) -> -49730 | F27: =_xlfn.XLOOKUP($A27,Inputs!$A:$A,Inputs!F:F,,0) -> -42407 | G27: =_xlfn.XLOOKUP($A27,Inputs!$A:$A,Inputs!G:G,,0) -> -39473 | H27: =_xlfn.XLOOKUP($A27,Inputs!$A:$A,Inputs!H:H,,0) -> -36518 | I27: =_xlfn.XLOOKUP($A27,Inputs!$A:$A,Inputs!I:I,,0) -> -33567 | J27: =_xlfn.XLOOKUP($A27,Inputs!$A:$A,Inputs!J:J,,0) -> -19545 | K27: =_xlfn.XLOOKUP($A27,Inputs!$A:$A,Inputs!K:K,,0) -> -11946 | L27: =_xlfn.XLOOKUP($A27,Inputs!$A:$A,Inputs!L:L,,0) -> -10479 | M27: =_xlfn.XLOOKUP($A27,Inputs!$A:$A,Inputs!M:M,,0) -> -10489
A28: Share buyback | B28: =_xlfn.XLOOKUP($A28,Inputs!$A:$A,Inputs!B:B,,0) -> 0 | C28: =_xlfn.XLOOKUP($A28,Inputs!$A:$A,Inputs!C:C,,0) -> 0 | D28: =_xlfn.XLOOKUP($A28,Inputs!$A:$A,Inputs!D:D,,0) -> 0 | E28: =_xlfn.XLOOKUP($A28,Inputs!$A:$A,Inputs!E:E,,0) -> 0 | F28: =_xlfn.XLOOKUP($A28,Inputs!$A:$A,Inputs!F:F,,0) -> 0 | G28: =_xlfn.XLOOKUP($A28,Inputs!$A:$A,Inputs!G:G,,0) -> 0 | H28: =_xlfn.XLOOKUP($A28,Inputs!$A:$A,Inputs!H:H,,0) -> 0 | I28: =_xlfn.XLOOKUP($A28,Inputs!$A:$A,Inputs!I:I,,0) -> 0 | J28: =_xlfn.XLOOKUP($A28,Inputs!$A:$A,Inputs!J:J,,0) -> 0 | K28: =_xlfn.XLOOKUP($A28,Inputs!$A:$A,Inputs!K:K,,0) -> 0 | L28: =_xlfn.XLOOKUP($A28,Inputs!$A:$A,Inputs!L:L,,0) -> 0 | M28: =_xlfn.XLOOKUP($A28,Inputs!$A:$A,Inputs!M:M,,0) -> 0
A29: Net Cash Flow | B29: =SUM(B26:B28) -> -261424 | C29: =SUM(C26:C28) -> 31775 | D29: =SUM(D26:D28) -> 318584 | E29: =SUM(E26:E28) -> -46718 | F29: =SUM(F26:F28) -> -31653 | G29: =SUM(G26:G28) -> -26539 | H29: =SUM(H26:H28) -> 16370 | I29: =SUM(I26:I28) -> -29311 | ... M29: =SUM(M26:M28) -> 125159
A30: FNP'' | B30: =+B29-(B58-C29) -> -1043415 | C30: =+C29-(C58-D29) -> -109973 | D30: =+D29-(D58-E29) -> -403066 | E30: =+E29-(E58-F29) -> -526274 | F30: =+F29-(F58-G29) -> -551446 | G30: =+G29-(G58-H29) -> -487550 | H30: =+H29-(H58-I29) -> -545191 | I30: =+I29-(I58-J29) -> -555240 | ... M30: =+M29-(M58-N29) -> -207441
A31: FNP' | B31: =+B30+B33 -> -1078335 | C31: =+C30+C33 -> -156194 | D31: =+D30+D33 -> -446437 | E31: =+E30+E33 -> -567559 | F31: =+F30+F33 -> -625683 | G31: =+G30+G33 -> -524021 | H31: =+H30+H33 -> -577219 | I31: =+I30+I33 -> -561369 | ... M31: =+M30+M33 -> -227328
A32: Net Capex | B32: =_xlfn.XLOOKUP($A32,Inputs!$A:$A,Inputs!B:B,,0) -> -175076 | C32: =_xlfn.XLOOKUP($A32,Inputs!$A:$A,Inputs!C:C,,0) -> -114106 | D32: =_xlfn.XLOOKUP($A32,Inputs!$A:$A,Inputs!D:D,,0) -> -104971 | E32: =_xlfn.XLOOKUP($A32,Inputs!$A:$A,Inputs!E:E,,0) -> -98094 | F32: =_xlfn.XLOOKUP($A32,Inputs!$A:$A,Inputs!F:F,,0) -> -85487 | G32: =_xlfn.XLOOKUP($A32,Inputs!$A:$A,Inputs!G:G,,0) -> -85679 | H32: =_xlfn.XLOOKUP($A32,Inputs!$A:$A,Inputs!H:H,,0) -> -88335 | I32: =_xlfn.XLOOKUP($A32,Inputs!$A:$A,Inputs!I:I,,0) -> -96696 | J32: =_xlfn.XLOOKUP($A32,Inputs!$A:$A,Inputs!J:J,,0) -> -71759 | K32: =_xlfn.XLOOKUP($A32,Inputs!$A:$A,Inputs!K:K,,0) -> -53647 | L32: =_xlfn.XLOOKUP($A32,Inputs!$A:$A,Inputs!L:L,,0) -> -53045 | M32: =_xlfn.XLOOKUP($A32,Inputs!$A:$A,Inputs!M:M,,0) -> -42459
A33: Investments & Acquisitions | B33: =_xlfn.XLOOKUP($A33,Inputs!$A:$A,Inputs!B:B,,0) -> -34920 | C33: =_xlfn.XLOOKUP($A33,Inputs!$A:$A,Inputs!C:C,,0) -> -46221 | D33: =_xlfn.XLOOKUP($A33,Inputs!$A:$A,Inputs!D:D,,0) -> -43371 | E33: =_xlfn.XLOOKUP($A33,Inputs!$A:$A,Inputs!E:E,,0) -> -41285 | F33: =_xlfn.XLOOKUP($A33,Inputs!$A:$A,Inputs!F:F,,0) -> -74237 | G33: =_xlfn.XLOOKUP($A33,Inputs!$A:$A,Inputs!G:G,,0) -> -36471 | H33: =_xlfn.XLOOKUP($A33,Inputs!$A:$A,Inputs!H:H,,0) -> -32028 | I33: =_xlfn.XLOOKUP($A33,Inputs!$A:$A,Inputs!I:I,,0) -> -6129 | J33: =_xlfn.XLOOKUP($A33,Inputs!$A:$A,Inputs!J:J,,0) -> -1004 | K33: =_xlfn.XLOOKUP($A33,Inputs!$A:$A,Inputs!K:K,,0) -> -26186 | L33: =_xlfn.XLOOKUP($A33,Inputs!$A:$A,Inputs!L:L,,0) -> -164983 | M33: =_xlfn.XLOOKUP($A33,Inputs!$A:$A,Inputs!M:M,,0) -> -19887
A34: Capex + Investments | B34: =+B32+B33 -> -209996 | C34: =+C32+C33 -> -160327 | D34: =+D32+D33 -> -148342 | E34: =+E32+E33 -> -139379 | F34: =+F32+F33 -> -159724 | G34: =+G32+G33 -> -122150 | H34: =+H32+H33 -> -120363 | I34: =+I32+I33 -> -102825 | ... M34: =+M32+M33 -> -62346
A35: Dividends + Share Buyback | B35: =+B27+B28 -> -61468 | C35: =+C27+C28 -> -49746 | D35: =+D27+D28 -> -46721 | E35: =+E27+E28 -> -49730 | F35: =+F27+F28 -> -42407 | G35: =+G27+G28 -> -39473 | H35: =+H27+H28 -> -36518 | I35: =+I27+I28 -> -33567 | ... M35: =+M27+M28 -> -10489
A36: Payout Ratio | B36: =IFERROR(B35/B23,"-") -> -0.23847452 | C36: =IFERROR(C35/C23,"-") -> -0.22849662 | D36: =IFERROR(D35/D23,"-") -> -0.2990144 | E36: =IFERROR(E35/E23,"-") -> -0.29127521 | F36: =IFERROR(F35/F23,"-") -> -0.2243175 | G36: =IFERROR(G35/G23,"-") -> -0.2087933 | H36: =IFERROR(H35/H23,"-") -> -0.23722384 | I36: =IFERROR(I35/I23,"-") -> -0.24503606 | ... M36: =IFERROR(M35/M23,"-") -> -0.25475433
A38: Assets
A39: Cash & Eq. | B39: =_xlfn.XLOOKUP($A39,Inputs!$A:$A,Inputs!B:B,,0) -> 617663 | C39: =_xlfn.XLOOKUP($A39,Inputs!$A:$A,Inputs!C:C,,0) -> 817619 | D39: =_xlfn.XLOOKUP($A39,Inputs!$A:$A,Inputs!D:D,,0) -> 736098 | E39: =_xlfn.XLOOKUP($A39,Inputs!$A:$A,Inputs!E:E,,0) -> 370793 | F39: =_xlfn.XLOOKUP($A39,Inputs!$A:$A,Inputs!F:F,,0) -> 367781 | G39: =_xlfn.XLOOKUP($A39,Inputs!$A:$A,Inputs!G:G,,0) -> 357027 | H39: =_xlfn.XLOOKUP($A39,Inputs!$A:$A,Inputs!H:H,,0) -> 344093 | I39: =_xlfn.XLOOKUP($A39,Inputs!$A:$A,Inputs!I:I,,0) -> 291205 | J39: =_xlfn.XLOOKUP($A39,Inputs!$A:$A,Inputs!J:J,,0) -> 286949 | K39: =_xlfn.XLOOKUP($A39,Inputs!$A:$A,Inputs!K:K,,0) -> 257295 | L39: =_xlfn.XLOOKUP($A39,Inputs!$A:$A,Inputs!L:L,,0) -> 185571 | M39: =_xlfn.XLOOKUP($A39,Inputs!$A:$A,Inputs!M:M,,0) -> 135648
A40: Accounts Receivable | B40: =_xlfn.XLOOKUP($A40,Inputs!$A:$A,Inputs!B:B,,0) -> 687135 | C40: =_xlfn.XLOOKUP($A40,Inputs!$A:$A,Inputs!C:C,,0) -> 578148 | D40: =_xlfn.XLOOKUP($A40,Inputs!$A:$A,Inputs!D:D,,0) -> 455256 | E40: =_xlfn.XLOOKUP($A40,Inputs!$A:$A,Inputs!E:E,,0) -> 430194 | F40: =_xlfn.XLOOKUP($A40,Inputs!$A:$A,Inputs!F:F,,0) -> 438684 | G40: =_xlfn.XLOOKUP($A40,Inputs!$A:$A,Inputs!G:G,,0) -> 392331 | H40: =_xlfn.XLOOKUP($A40,Inputs!$A:$A,Inputs!H:H,,0) -> 360845 | I40: =_xlfn.XLOOKUP($A40,Inputs!$A:$A,Inputs!I:I,,0) -> 349367 | J40: =_xlfn.XLOOKUP($A40,Inputs!$A:$A,Inputs!J:J,,0) -> 347584 | K40: =_xlfn.XLOOKUP($A40,Inputs!$A:$A,Inputs!K:K,,0) -> 310986 | L40: =_xlfn.XLOOKUP($A40,Inputs!$A:$A,Inputs!L:L,,0) -> 257096 | M40: =_xlfn.XLOOKUP($A40,Inputs!$A:$A,Inputs!M:M,,0) -> 204269
A41: Inventory | B41: =_xlfn.XLOOKUP($A41,Inputs!$A:$A,Inputs!B:B,,0) -> 993383 | C41: =_xlfn.XLOOKUP($A41,Inputs!$A:$A,Inputs!C:C,,0) -> 671461 | D41: =_xlfn.XLOOKUP($A41,Inputs!$A:$A,Inputs!D:D,,0) -> 469396 | E41: =_xlfn.XLOOKUP($A41,Inputs!$A:$A,Inputs!E:E,,0) -> 433782 | F41: =_xlfn.XLOOKUP($A41,Inputs!$A:$A,Inputs!F:F,,0) -> 436356 | G41: =_xlfn.XLOOKUP($A41,Inputs!$A:$A,Inputs!G:G,,0) -> 387225 | H41: =_xlfn.XLOOKUP($A41,Inputs!$A:$A,Inputs!H:H,,0) -> 358301 | I41: =_xlfn.XLOOKUP($A41,Inputs!$A:$A,Inputs!I:I,,0) -> 333650 | J41: =_xlfn.XLOOKUP($A41,Inputs!$A:$A,Inputs!J:J,,0) -> 354158 | K41: =_xlfn.XLOOKUP($A41,Inputs!$A:$A,Inputs!K:K,,0) -> 317559 | L41: =_xlfn.XLOOKUP($A41,Inputs!$A:$A,Inputs!L:L,,0) -> 285167 | M41: =_xlfn.XLOOKUP($A41,Inputs!$A:$A,Inputs!M:M,,0) -> 243598
A42: Property, Plant and Equipment | B42: =_xlfn.XLOOKUP($A42,Inputs!$A:$A,Inputs!B:B,,0) -> 900944 | C42: =_xlfn.XLOOKUP($A42,Inputs!$A:$A,Inputs!C:C,,0) -> 743364 | D42: =_xlfn.XLOOKUP($A42,Inputs!$A:$A,Inputs!D:D,,0) -> 647410 | E42: =_xlfn.XLOOKUP($A42,Inputs!$A:$A,Inputs!E:E,,0) -> 579980 | F42: =_xlfn.XLOOKUP($A42,Inputs!$A:$A,Inputs!F:F,,0) -> 482962 | G42: =_xlfn.XLOOKUP($A42,Inputs!$A:$A,Inputs!G:G,,0) -> 454834 | H42: =_xlfn.XLOOKUP($A42,Inputs!$A:$A,Inputs!H:H,,0) -> 424527 | I42: =_xlfn.XLOOKUP($A42,Inputs!$A:$A,Inputs!I:I,,0) -> 385099 | J42: =_xlfn.XLOOKUP($A42,Inputs!$A:$A,Inputs!J:J,,0) -> 347755 | K42: =_xlfn.XLOOKUP($A42,Inputs!$A:$A,Inputs!K:K,,0) -> 299716 | L42: =_xlfn.XLOOKUP($A42,Inputs!$A:$A,Inputs!L:L,,0) -> 274201 | M42: =_xlfn.XLOOKUP($A42,Inputs!$A:$A,Inputs!M:M,,0) -> 224357
A43: Other Assets | B43: =_xlfn.XLOOKUP($A43,Inputs!$A:$A,Inputs!B:B,,0) -> 917696 | C43: =_xlfn.XLOOKUP($A43,Inputs!$A:$A,Inputs!C:C,,0) -> 796178 | D43: =_xlfn.XLOOKUP($A43,Inputs!$A:$A,Inputs!D:D,,0) -> 701296 | E43: =_xlfn.XLOOKUP($A43,Inputs!$A:$A,Inputs!E:E,,0) -> 669611 | F43: =_xlfn.XLOOKUP($A43,Inputs!$A:$A,Inputs!F:F,,0) -> 663256 | G43: =_xlfn.XLOOKUP($A43,Inputs!$A:$A,Inputs!G:G,,0) -> 573160 | H43: =_xlfn.XLOOKUP($A43,Inputs!$A:$A,Inputs!H:H,,0) -> 613573 | I43: =_xlfn.XLOOKUP($A43,Inputs!$A:$A,Inputs!I:I,,0) -> 596434 | J43: =_xlfn.XLOOKUP($A43,Inputs!$A:$A,Inputs!J:J,,0) -> 668160 | K43: =_xlfn.XLOOKUP($A43,Inputs!$A:$A,Inputs!K:K,,0) -> 633349 | L43: =_xlfn.XLOOKUP($A43,Inputs!$A:$A,Inputs!L:L,,0) -> 586003 | M43: =_xlfn.XLOOKUP($A43,Inputs!$A:$A,Inputs!M:M,,0) -> 234440
A44: Total Assets | B44: =_xlfn.XLOOKUP($A44,Inputs!$A:$A,Inputs!B:B,,0) -> 4303682 | C44: =_xlfn.XLOOKUP($A44,Inputs!$A:$A,Inputs!C:C,,0) -> 3823038 | D44: =_xlfn.XLOOKUP($A44,Inputs!$A:$A,Inputs!D:D,,0) -> 3239662 | E44: =_xlfn.XLOOKUP($A44,Inputs!$A:$A,Inputs!E:E,,0) -> 2667512 | F44: =_xlfn.XLOOKUP($A44,Inputs!$A:$A,Inputs!F:F,,0) -> 2700890 | G44: =_xlfn.XLOOKUP($A44,Inputs!$A:$A,Inputs!G:G,,0) -> 2475708 | H44: =_xlfn.XLOOKUP($A44,Inputs!$A:$A,Inputs!H:H,,0) -> 2356148 | I44: =_xlfn.XLOOKUP($A44,Inputs!$A:$A,Inputs!I:I,,0) -> 2191105 | J44: =_xlfn.XLOOKUP($A44,Inputs!$A:$A,Inputs!J:J,,0) -> 2263989 | K44: =_xlfn.XLOOKUP($A44,Inputs!$A:$A,Inputs!K:K,,0) -> 2011870 | L44: =_xlfn.XLOOKUP($A44,Inputs!$A:$A,Inputs!L:L,,0) -> 1735836 | M44: =_xlfn.XLOOKUP($A44,Inputs!$A:$A,Inputs!M:M,,0) -> 1160564
A47: Liabilities
A48: Current Liabilities | B48: =_xlfn.XLOOKUP($A48,Inputs!$A:$A,Inputs!B:B,,0) -> 1449321 | C48: =_xlfn.XLOOKUP($A48,Inputs!$A:$A,Inputs!C:C,,0) -> 1306239 | D48: =_xlfn.XLOOKUP($A48,Inputs!$A:$A,Inputs!D:D,,0) -> 765984 | E48: =_xlfn.XLOOKUP($A48,Inputs!$A:$A,Inputs!E:E,,0) -> 693957 | F48: =_xlfn.XLOOKUP($A48,Inputs!$A:$A,Inputs!F:F,,0) -> 768815 | G48: =_xlfn.XLOOKUP($A48,Inputs!$A:$A,Inputs!G:G,,0) -> 603331 | H48: =_xlfn.XLOOKUP($A48,Inputs!$A:$A,Inputs!H:H,,0) -> 626676 | I48: =_xlfn.XLOOKUP($A48,Inputs!$A:$A,Inputs!I:I,,0) -> 563727 | J48: =_xlfn.XLOOKUP($A48,Inputs!$A:$A,Inputs!J:J,,0) -> 525624 | K48: =_xlfn.XLOOKUP($A48,Inputs!$A:$A,Inputs!K:K,,0) -> 533467 | L48: =_xlfn.XLOOKUP($A48,Inputs!$A:$A,Inputs!L:L,,0) -> 382627 | M48: =_xlfn.XLOOKUP($A48,Inputs!$A:$A,Inputs!M:M,,0) -> 396339
A49: Short-Term Debt | B49: =_xlfn.XLOOKUP($A49,Inputs!$A:$A,Inputs!B:B,,0) -> 372541 | C49: =_xlfn.XLOOKUP($A49,Inputs!$A:$A,Inputs!C:C,,0) -> 97376 | D49: =_xlfn.XLOOKUP($A49,Inputs!$A:$A,Inputs!D:D,,0) -> 40754 | E49: =_xlfn.XLOOKUP($A49,Inputs!$A:$A,Inputs!E:E,,0) -> 48937 | F49: =_xlfn.XLOOKUP($A49,Inputs!$A:$A,Inputs!F:F,,0) -> 146066 | G49: =_xlfn.XLOOKUP($A49,Inputs!$A:$A,Inputs!G:G,,0) -> 45530 | H49: =_xlfn.XLOOKUP($A49,Inputs!$A:$A,Inputs!H:H,,0) -> 57699 | I49: =_xlfn.XLOOKUP($A49,Inputs!$A:$A,Inputs!I:I,,0) -> 54675 | J49: =_xlfn.XLOOKUP($A49,Inputs!$A:$A,Inputs!J:J,,0) -> 57897 | K49: =_xlfn.XLOOKUP($A49,Inputs!$A:$A,Inputs!K:K,,0) -> 43325 | L49: =_xlfn.XLOOKUP($A49,Inputs!$A:$A,Inputs!L:L,,0) -> 65334 | M49: =_xlfn.XLOOKUP($A49,Inputs!$A:$A,Inputs!M:M,,0) -> 90448
A50: Short-Term Leases | B50: =_xlfn.XLOOKUP($A50,Inputs!$A:$A,Inputs!B:B,,0) -> 30442 | C50: =_xlfn.XLOOKUP($A50,Inputs!$A:$A,Inputs!C:C,,0) -> 25876 | D50: =_xlfn.XLOOKUP($A50,Inputs!$A:$A,Inputs!D:D,,0) -> 20639 | E50: =_xlfn.XLOOKUP($A50,Inputs!$A:$A,Inputs!E:E,,0) -> 17300 | F50: =_xlfn.XLOOKUP($A50,Inputs!$A:$A,Inputs!F:F,,0) -> 1241 | G50: =_xlfn.XLOOKUP($A50,Inputs!$A:$A,Inputs!G:G,,0) -> 1499 | H50: =_xlfn.XLOOKUP($A50,Inputs!$A:$A,Inputs!H:H,,0) -> 1797 | I50: =_xlfn.XLOOKUP($A50,Inputs!$A:$A,Inputs!I:I,,0) -> 1943 | J50: =_xlfn.XLOOKUP($A50,Inputs!$A:$A,Inputs!J:J,,0) -> 1913 | K50: =_xlfn.XLOOKUP($A50,Inputs!$A:$A,Inputs!K:K,,0) -> 1731 | L50: =_xlfn.XLOOKUP($A50,Inputs!$A:$A,Inputs!L:L,,0) -> 1464 | M50: =_xlfn.XLOOKUP($A50,Inputs!$A:$A,Inputs!M:M,,0) -> 2042
A51: Other current liabilities | B51: =_xlfn.XLOOKUP($A51,Inputs!$A:$A,Inputs!B:B,,0) -> 693691 | C51: =_xlfn.XLOOKUP($A51,Inputs!$A:$A,Inputs!C:C,,0) -> 880366 | D51: =_xlfn.XLOOKUP($A51,Inputs!$A:$A,Inputs!D:D,,0) -> 474845 | E51: =_xlfn.XLOOKUP($A51,Inputs!$A:$A,Inputs!E:E,,0) -> 437877 | F51: =_xlfn.XLOOKUP($A51,Inputs!$A:$A,Inputs!F:F,,0) -> 416973 | G51: =_xlfn.XLOOKUP($A51,Inputs!$A:$A,Inputs!G:G,,0) -> 372311 | H51: =_xlfn.XLOOKUP($A51,Inputs!$A:$A,Inputs!H:H,,0) -> 394033 | I51: =_xlfn.XLOOKUP($A51,Inputs!$A:$A,Inputs!I:I,,0) -> 351071 | J51: =_xlfn.XLOOKUP($A51,Inputs!$A:$A,Inputs!J:J,,0) -> 311877 | K51: =_xlfn.XLOOKUP($A51,Inputs!$A:$A,Inputs!K:K,,0) -> 326327 | L51: =_xlfn.XLOOKUP($A51,Inputs!$A:$A,Inputs!L:L,,0) -> 188465 | M51: =_xlfn.XLOOKUP($A51,Inputs!$A:$A,Inputs!M:M,,0) -> 193741
A52: Non-current Liabilities | B52: =_xlfn.XLOOKUP($A52,Inputs!$A:$A,Inputs!B:B,,0) -> 616213 | C52: =_xlfn.XLOOKUP($A52,Inputs!$A:$A,Inputs!C:C,,0) -> 545526 | D52: =_xlfn.XLOOKUP($A52,Inputs!$A:$A,Inputs!D:D,,0) -> 805970 | E52: =_xlfn.XLOOKUP($A52,Inputs!$A:$A,Inputs!E:E,,0) -> 536700 | F52: =_xlfn.XLOOKUP($A52,Inputs!$A:$A,Inputs!F:F,,0) -> 514280 | G52: =_xlfn.XLOOKUP($A52,Inputs!$A:$A,Inputs!G:G,,0) -> 574314 | H52: =_xlfn.XLOOKUP($A52,Inputs!$A:$A,Inputs!H:H,,0) -> 616756 | I52: =_xlfn.XLOOKUP($A52,Inputs!$A:$A,Inputs!I:I,,0) -> 611851 | J52: =_xlfn.XLOOKUP($A52,Inputs!$A:$A,Inputs!J:J,,0) -> 712648 | K52: =_xlfn.XLOOKUP($A52,Inputs!$A:$A,Inputs!K:K,,0) -> 675707 | L52: =_xlfn.XLOOKUP($A52,Inputs!$A:$A,Inputs!L:L,,0) -> 733756 | M52: =_xlfn.XLOOKUP($A52,Inputs!$A:$A,Inputs!M:M,,0) -> 260414
A53: Long-Term Debt | B53: =_xlfn.XLOOKUP($A53,Inputs!$A:$A,Inputs!B:B,,0) -> 314186 | C53: =_xlfn.XLOOKUP($A53,Inputs!$A:$A,Inputs!C:C,,0) -> 260572 | D53: =_xlfn.XLOOKUP($A53,Inputs!$A:$A,Inputs!D:D,,0) -> 548803 | E53: =_xlfn.XLOOKUP($A53,Inputs!$A:$A,Inputs!E:E,,0) -> 323184 | F53: =_xlfn.XLOOKUP($A53,Inputs!$A:$A,Inputs!F:F,,0) -> 335988 | G53: =_xlfn.XLOOKUP($A53,Inputs!$A:$A,Inputs!G:G,,0) -> 421051 | H53: =_xlfn.XLOOKUP($A53,Inputs!$A:$A,Inputs!H:H,,0) -> 463292 | I53: =_xlfn.XLOOKUP($A53,Inputs!$A:$A,Inputs!I:I,,0) -> 477491 | J53: =_xlfn.XLOOKUP($A53,Inputs!$A:$A,Inputs!J:J,,0) -> 560874 | K53: =_xlfn.XLOOKUP($A53,Inputs!$A:$A,Inputs!K:K,,0) -> 550475 | L53: =_xlfn.XLOOKUP($A53,Inputs!$A:$A,Inputs!L:L,,0) -> 633033 | M53: =_xlfn.XLOOKUP($A53,Inputs!$A:$A,Inputs!M:M,,0) -> 238108
A54: Long-Term Leases | B54: =_xlfn.XLOOKUP($A54,Inputs!$A:$A,Inputs!B:B,,0) -> 96597 | C54: =_xlfn.XLOOKUP($A54,Inputs!$A:$A,Inputs!C:C,,0) -> 76508 | D54: =_xlfn.XLOOKUP($A54,Inputs!$A:$A,Inputs!D:D,,0) -> 64736 | E54: =_xlfn.XLOOKUP($A54,Inputs!$A:$A,Inputs!E:E,,0) -> 58482 | F54: =_xlfn.XLOOKUP($A54,Inputs!$A:$A,Inputs!F:F,,0) -> 9959 | G54: =_xlfn.XLOOKUP($A54,Inputs!$A:$A,Inputs!G:G,,0) -> 9301 | H54: =_xlfn.XLOOKUP($A54,Inputs!$A:$A,Inputs!H:H,,0) -> 9462 | I54: =_xlfn.XLOOKUP($A54,Inputs!$A:$A,Inputs!I:I,,0) -> 1929 | J54: =_xlfn.XLOOKUP($A54,Inputs!$A:$A,Inputs!J:J,,0) -> 2717 | K54: =_xlfn.XLOOKUP($A54,Inputs!$A:$A,Inputs!K:K,,0) -> 0 | L54: =_xlfn.XLOOKUP($A54,Inputs!$A:$A,Inputs!L:L,,0) -> 1912 | M54: =_xlfn.XLOOKUP($A54,Inputs!$A:$A,Inputs!M:M,,0) -> 2002
A55: Other non-current liabilities | B55: =_xlfn.XLOOKUP($A55,Inputs!$A:$A,Inputs!B:B,,0) -> 205430 | C55: =_xlfn.XLOOKUP($A55,Inputs!$A:$A,Inputs!C:C,,0) -> 208446 | D55: =_xlfn.XLOOKUP($A55,Inputs!$A:$A,Inputs!D:D,,0) -> 192431 | E55: =_xlfn.XLOOKUP($A55,Inputs!$A:$A,Inputs!E:E,,0) -> 155034 | F55: =_xlfn.XLOOKUP($A55,Inputs!$A:$A,Inputs!F:F,,0) -> 168333 | G55: =_xlfn.XLOOKUP($A55,Inputs!$A:$A,Inputs!G:G,,0) -> 143962 | H55: =_xlfn.XLOOKUP($A55,Inputs!$A:$A,Inputs!H:H,,0) -> 144002 | I55: =_xlfn.XLOOKUP($A55,Inputs!$A:$A,Inputs!I:I,,0) -> 132431 | J55: =_xlfn.XLOOKUP($A55,Inputs!$A:$A,Inputs!J:J,,0) -> 149057 | K55: =_xlfn.XLOOKUP($A55,Inputs!$A:$A,Inputs!K:K,,0) -> 125232 | L55: =_xlfn.XLOOKUP($A55,Inputs!$A:$A,Inputs!L:L,,0) -> 98811 | M55: =_xlfn.XLOOKUP($A55,Inputs!$A:$A,Inputs!M:M,,0) -> 20304
A56: Total Liabilities | B56: =_xlfn.XLOOKUP($A56,Inputs!$A:$A,Inputs!B:B,,0) -> 2065534 | C56: =_xlfn.XLOOKUP($A56,Inputs!$A:$A,Inputs!C:C,,0) -> 1851765 | D56: =_xlfn.XLOOKUP($A56,Inputs!$A:$A,Inputs!D:D,,0) -> 1571954 | E56: =_xlfn.XLOOKUP($A56,Inputs!$A:$A,Inputs!E:E,,0) -> 1230657 | F56: =_xlfn.XLOOKUP($A56,Inputs!$A:$A,Inputs!F:F,,0) -> 1283095 | G56: =_xlfn.XLOOKUP($A56,Inputs!$A:$A,Inputs!G:G,,0) -> 1177645 | H56: =_xlfn.XLOOKUP($A56,Inputs!$A:$A,Inputs!H:H,,0) -> 1243432 | I56: =_xlfn.XLOOKUP($A56,Inputs!$A:$A,Inputs!I:I,,0) -> 1175578 | J56: =_xlfn.XLOOKUP($A56,Inputs!$A:$A,Inputs!J:J,,0) -> 1238272 | K56: =_xlfn.XLOOKUP($A56,Inputs!$A:$A,Inputs!K:K,,0) -> 1209174 | L56: =_xlfn.XLOOKUP($A56,Inputs!$A:$A,Inputs!L:L,,0) -> 1116383 | M56: =_xlfn.XLOOKUP($A56,Inputs!$A:$A,Inputs!M:M,,0) -> 656753
A58: Total Debt | B58: =B49+B53+B50+B54 -> 813766 | C58: =C49+C53+C50+C54 -> 460332 | D58: =D49+D53+D50+D54 -> 674932 | E58: =E49+E53+E50+E54 -> 447903 | F58: =F49+F53+F50+F54 -> 493254 | G58: =G49+G53+G50+G54 -> 477381 | H58: =H49+H53+H50+H54 -> 532250 | I58: =I49+I53+I50+I54 -> 536038 | ... M58: =M49+M53+M50+M54 -> 332600
A59: Debt/Assets | B59: =IFERROR(B58/B44,"-") -> 0.189086 | C59: =IFERROR(C58/C44,"-") -> 0.12041 | D59: =IFERROR(D58/D44,"-") -> 0.20833408 | E59: =IFERROR(E58/E44,"-") -> 0.1679104 | F59: =IFERROR(F58/F44,"-") -> 0.18262647 | G59: =IFERROR(G58/G44,"-") -> 0.19282605 | H59: =IFERROR(H58/H44,"-") -> 0.22589837 | I59: =IFERROR(I58/I44,"-") -> 0.24464277 | ... M59: =IFERROR(M58/M44,"-") -> 0.2865848
A60: Net Debt | B60: =B58-B39 -> 196103 | C60: =C58-C39 -> -357287 | D60: =D58-D39 -> -61166 | E60: =E58-E39 -> 77110 | F60: =F58-F39 -> 125473 | G60: =G58-G39 -> 120354 | H60: =H58-H39 -> 188157 | I60: =I58-I39 -> 244833 | ... M60: =M58-M39 -> 196952
A62: Minority Interest | B62: =_xlfn.XLOOKUP($A62,Inputs!$A:$A,Inputs!B:B,,0) -> 40947 | C62: =_xlfn.XLOOKUP($A62,Inputs!$A:$A,Inputs!C:C,,0) -> 35876 | D62: =_xlfn.XLOOKUP($A62,Inputs!$A:$A,Inputs!D:D,,0) -> 30787 | E62: =_xlfn.XLOOKUP($A62,Inputs!$A:$A,Inputs!E:E,,0) -> 25736 | F62: =_xlfn.XLOOKUP($A62,Inputs!$A:$A,Inputs!F:F,,0) -> 29054 | G62: =_xlfn.XLOOKUP($A62,Inputs!$A:$A,Inputs!G:G,,0) -> 26258 | H62: =_xlfn.XLOOKUP($A62,Inputs!$A:$A,Inputs!H:H,,0) -> 22893 | I62: =_xlfn.XLOOKUP($A62,Inputs!$A:$A,Inputs!I:I,,0) -> 21942 | J62: =_xlfn.XLOOKUP($A62,Inputs!$A:$A,Inputs!J:J,,0) -> 22594 | K62: =_xlfn.XLOOKUP($A62,Inputs!$A:$A,Inputs!K:K,,0) -> 21162 | L62: =_xlfn.XLOOKUP($A62,Inputs!$A:$A,Inputs!L:L,,0) -> 16543 | M62: =_xlfn.XLOOKUP($A62,Inputs!$A:$A,Inputs!M:M,,0) -> 12110
A64: Shareholder's Equity | B64: =_xlfn.XLOOKUP($A64,Inputs!$A:$A,Inputs!B:B,,0) -> 2197201 | C64: =_xlfn.XLOOKUP($A64,Inputs!$A:$A,Inputs!C:C,,0) -> 1935397 | D64: =_xlfn.XLOOKUP($A64,Inputs!$A:$A,Inputs!D:D,,0) -> 1636921 | E64: =_xlfn.XLOOKUP($A64,Inputs!$A:$A,Inputs!E:E,,0) -> 1411119 | F64: =_xlfn.XLOOKUP($A64,Inputs!$A:$A,Inputs!F:F,,0) -> 1388741 | G64: =_xlfn.XLOOKUP($A64,Inputs!$A:$A,Inputs!G:G,,0) -> 1271805 | H64: =_xlfn.XLOOKUP($A64,Inputs!$A:$A,Inputs!H:H,,0) -> 1089823 | I64: =_xlfn.XLOOKUP($A64,Inputs!$A:$A,Inputs!I:I,,0) -> 993585 | J64: =_xlfn.XLOOKUP($A64,Inputs!$A:$A,Inputs!J:J,,0) -> 1003123 | K64: =_xlfn.XLOOKUP($A64,Inputs!$A:$A,Inputs!K:K,,0) -> 781534 | L64: =_xlfn.XLOOKUP($A64,Inputs!$A:$A,Inputs!L:L,,0) -> 602910 | M64: =_xlfn.XLOOKUP($A64,Inputs!$A:$A,Inputs!M:M,,0) -> 491701
A66: Cash Flow
A67: Operating CF | B67: =_xlfn.XLOOKUP($A67,Inputs!$A:$A,Inputs!B:B,,0) -> 158326 | C67: =_xlfn.XLOOKUP($A67,Inputs!$A:$A,Inputs!C:C,,0) -> 243485 | D67: =_xlfn.XLOOKUP($A67,Inputs!$A:$A,Inputs!D:D,,0) -> 374633 | E67: =_xlfn.XLOOKUP($A67,Inputs!$A:$A,Inputs!E:E,,0) -> 302112 | F67: =_xlfn.XLOOKUP($A67,Inputs!$A:$A,Inputs!F:F,,0) -> 249943 | G67: =_xlfn.XLOOKUP($A67,Inputs!$A:$A,Inputs!G:G,,0) -> 223738 | H67: =_xlfn.XLOOKUP($A67,Inputs!$A:$A,Inputs!H:H,,0) -> 267662 | I67: =_xlfn.XLOOKUP($A67,Inputs!$A:$A,Inputs!I:I,,0) -> 226184 | J67: =_xlfn.XLOOKUP($A67,Inputs!$A:$A,Inputs!J:J,,0) -> 160223 | K67: =_xlfn.XLOOKUP($A67,Inputs!$A:$A,Inputs!K:K,,0) -> 179911 | L67: =_xlfn.XLOOKUP($A67,Inputs!$A:$A,Inputs!L:L,,0) -> 105268 | M67: =_xlfn.XLOOKUP($A67,Inputs!$A:$A,Inputs!M:M,,0) -> 36816
A68: Investing CF | B68: =_xlfn.XLOOKUP($A68,Inputs!$A:$A,Inputs!B:B,,0) -> -229793 | C68: =_xlfn.XLOOKUP($A68,Inputs!$A:$A,Inputs!C:C,,0) -> -180789 | D68: =_xlfn.XLOOKUP($A68,Inputs!$A:$A,Inputs!D:D,,0) -> -159666 | E68: =_xlfn.XLOOKUP($A68,Inputs!$A:$A,Inputs!E:E,,0) -> -156187 | F68: =_xlfn.XLOOKUP($A68,Inputs!$A:$A,Inputs!F:F,,0) -> -165773 | G68: =_xlfn.XLOOKUP($A68,Inputs!$A:$A,Inputs!G:G,,0) -> -127458 | H68: =_xlfn.XLOOKUP($A68,Inputs!$A:$A,Inputs!H:H,,0) -> -128823 | I68: =_xlfn.XLOOKUP($A68,Inputs!$A:$A,Inputs!I:I,,0) -> -105493 | J68: =_xlfn.XLOOKUP($A68,Inputs!$A:$A,Inputs!J:J,,0) -> -77330 | K68: =_xlfn.XLOOKUP($A68,Inputs!$A:$A,Inputs!K:K,,0) -> -80834 | L68: =_xlfn.XLOOKUP($A68,Inputs!$A:$A,Inputs!L:L,,0) -> -218386 | M68: =_xlfn.XLOOKUP($A68,Inputs!$A:$A,Inputs!M:M,,0) -> -62955
A69: Net Capex | B69: =_xlfn.XLOOKUP($A69,Inputs!$A:$A,Inputs!B:B,,0) -> -175076 | C69: =_xlfn.XLOOKUP($A69,Inputs!$A:$A,Inputs!C:C,,0) -> -114106 | D69: =_xlfn.XLOOKUP($A69,Inputs!$A:$A,Inputs!D:D,,0) -> -104971 | E69: =_xlfn.XLOOKUP($A69,Inputs!$A:$A,Inputs!E:E,,0) -> -98094 | F69: =_xlfn.XLOOKUP($A69,Inputs!$A:$A,Inputs!F:F,,0) -> -85487 | G69: =_xlfn.XLOOKUP($A69,Inputs!$A:$A,Inputs!G:G,,0) -> -85679 | H69: =_xlfn.XLOOKUP($A69,Inputs!$A:$A,Inputs!H:H,,0) -> -88335 | I69: =_xlfn.XLOOKUP($A69,Inputs!$A:$A,Inputs!I:I,,0) -> -96696 | J69: =_xlfn.XLOOKUP($A69,Inputs!$A:$A,Inputs!J:J,,0) -> -71759 | K69: =_xlfn.XLOOKUP($A69,Inputs!$A:$A,Inputs!K:K,,0) -> -53647 | L69: =_xlfn.XLOOKUP($A69,Inputs!$A:$A,Inputs!L:L,,0) -> -53045 | M69: =_xlfn.XLOOKUP($A69,Inputs!$A:$A,Inputs!M:M,,0) -> -42459
A70: Investments & Acquisitions | B70: =_xlfn.XLOOKUP($A70,Inputs!$A:$A,Inputs!B:B,,0) -> -34920 | C70: =_xlfn.XLOOKUP($A70,Inputs!$A:$A,Inputs!C:C,,0) -> -46221 | D70: =_xlfn.XLOOKUP($A70,Inputs!$A:$A,Inputs!D:D,,0) -> -43371 | E70: =_xlfn.XLOOKUP($A70,Inputs!$A:$A,Inputs!E:E,,0) -> -41285 | F70: =_xlfn.XLOOKUP($A70,Inputs!$A:$A,Inputs!F:F,,0) -> -74237 | G70: =_xlfn.XLOOKUP($A70,Inputs!$A:$A,Inputs!G:G,,0) -> -36471 | H70: =_xlfn.XLOOKUP($A70,Inputs!$A:$A,Inputs!H:H,,0) -> -32028 | I70: =_xlfn.XLOOKUP($A70,Inputs!$A:$A,Inputs!I:I,,0) -> -6129 | J70: =_xlfn.XLOOKUP($A70,Inputs!$A:$A,Inputs!J:J,,0) -> -1004 | K70: =_xlfn.XLOOKUP($A70,Inputs!$A:$A,Inputs!K:K,,0) -> -26186 | L70: =_xlfn.XLOOKUP($A70,Inputs!$A:$A,Inputs!L:L,,0) -> -164983 | M70: =_xlfn.XLOOKUP($A70,Inputs!$A:$A,Inputs!M:M,,0) -> -19887
A71: Financing CF | B71: =_xlfn.XLOOKUP($A71,Inputs!$A:$A,Inputs!B:B,,0) -> -113088 | C71: =_xlfn.XLOOKUP($A71,Inputs!$A:$A,Inputs!C:C,,0) -> -48698 | D71: =_xlfn.XLOOKUP($A71,Inputs!$A:$A,Inputs!D:D,,0) -> 98942 | E71: =_xlfn.XLOOKUP($A71,Inputs!$A:$A,Inputs!E:E,,0) -> -169933 | F71: =_xlfn.XLOOKUP($A71,Inputs!$A:$A,Inputs!F:F,,0) -> -68721 | G71: =_xlfn.XLOOKUP($A71,Inputs!$A:$A,Inputs!G:G,,0) -> -93954 | H71: =_xlfn.XLOOKUP($A71,Inputs!$A:$A,Inputs!H:H,,0) -> -73543 | I71: =_xlfn.XLOOKUP($A71,Inputs!$A:$A,Inputs!I:I,,0) -> -85421 | J71: =_xlfn.XLOOKUP($A71,Inputs!$A:$A,Inputs!J:J,,0) -> -83073 | K71: =_xlfn.XLOOKUP($A71,Inputs!$A:$A,Inputs!K:K,,0) -> -38249 | L71: =_xlfn.XLOOKUP($A71,Inputs!$A:$A,Inputs!L:L,,0) -> 143520 | M71: =_xlfn.XLOOKUP($A71,Inputs!$A:$A,Inputs!M:M,,0) -> -1113
A72: Dividends | B72: =_xlfn.XLOOKUP($A72,Inputs!$A:$A,Inputs!B:B,,0) -> -61468 | C72: =_xlfn.XLOOKUP($A72,Inputs!$A:$A,Inputs!C:C,,0) -> -49746 | D72: =_xlfn.XLOOKUP($A72,Inputs!$A:$A,Inputs!D:D,,0) -> -46721 | E72: =_xlfn.XLOOKUP($A72,Inputs!$A:$A,Inputs!E:E,,0) -> -49730 | F72: =_xlfn.XLOOKUP($A72,Inputs!$A:$A,Inputs!F:F,,0) -> -42407 | G72: =_xlfn.XLOOKUP($A72,Inputs!$A:$A,Inputs!G:G,,0) -> -39473 | H72: =_xlfn.XLOOKUP($A72,Inputs!$A:$A,Inputs!H:H,,0) -> -36518 | I72: =_xlfn.XLOOKUP($A72,Inputs!$A:$A,Inputs!I:I,,0) -> -33567 | J72: =_xlfn.XLOOKUP($A72,Inputs!$A:$A,Inputs!J:J,,0) -> -19545 | K72: =_xlfn.XLOOKUP($A72,Inputs!$A:$A,Inputs!K:K,,0) -> -11946 | L72: =_xlfn.XLOOKUP($A72,Inputs!$A:$A,Inputs!L:L,,0) -> -10479 | M72: =_xlfn.XLOOKUP($A72,Inputs!$A:$A,Inputs!M:M,,0) -> -10489
A73: Share buyback | B73: =_xlfn.XLOOKUP($A73,Inputs!$A:$A,Inputs!B:B,,0) -> 0 | C73: =_xlfn.XLOOKUP($A73,Inputs!$A:$A,Inputs!C:C,,0) -> 0 | D73: =_xlfn.XLOOKUP($A73,Inputs!$A:$A,Inputs!D:D,,0) -> 0 | E73: =_xlfn.XLOOKUP($A73,Inputs!$A:$A,Inputs!E:E,,0) -> 0 | F73: =_xlfn.XLOOKUP($A73,Inputs!$A:$A,Inputs!F:F,,0) -> 0 | G73: =_xlfn.XLOOKUP($A73,Inputs!$A:$A,Inputs!G:G,,0) -> 0 | H73: =_xlfn.XLOOKUP($A73,Inputs!$A:$A,Inputs!H:H,,0) -> 0 | I73: =_xlfn.XLOOKUP($A73,Inputs!$A:$A,Inputs!I:I,,0) -> 0 | J73: =_xlfn.XLOOKUP($A73,Inputs!$A:$A,Inputs!J:J,,0) -> 0 | K73: =_xlfn.XLOOKUP($A73,Inputs!$A:$A,Inputs!K:K,,0) -> 0 | L73: =_xlfn.XLOOKUP($A73,Inputs!$A:$A,Inputs!L:L,,0) -> 0 | M73: =_xlfn.XLOOKUP($A73,Inputs!$A:$A,Inputs!M:M,,0) -> 0
A74: FX | B74: =_xlfn.XLOOKUP($A74,Inputs!$A:$A,Inputs!B:B,,0) -> 14996 | C74: =_xlfn.XLOOKUP($A74,Inputs!$A:$A,Inputs!C:C,,0) -> 41538 | D74: =_xlfn.XLOOKUP($A74,Inputs!$A:$A,Inputs!D:D,,0) -> 27207 | E74: =_xlfn.XLOOKUP($A74,Inputs!$A:$A,Inputs!E:E,,0) -> -22029 | F74: =_xlfn.XLOOKUP($A74,Inputs!$A:$A,Inputs!F:F,,0) -> -5286 | G74: =_xlfn.XLOOKUP($A74,Inputs!$A:$A,Inputs!G:G,,0) -> 10607 | H74: =_xlfn.XLOOKUP($A74,Inputs!$A:$A,Inputs!H:H,,0) -> -12408 | I74: =_xlfn.XLOOKUP($A74,Inputs!$A:$A,Inputs!I:I,,0) -> -31015 | J74: =_xlfn.XLOOKUP($A74,Inputs!$A:$A,Inputs!J:J,,0) -> 29836 | K74: =_xlfn.XLOOKUP($A74,Inputs!$A:$A,Inputs!K:K,,0) -> 10896 | L74: =_xlfn.XLOOKUP($A74,Inputs!$A:$A,Inputs!L:L,,0) -> 19740 | M74: =_xlfn.XLOOKUP($A74,Inputs!$A:$A,Inputs!M:M,,0) -> -4616
A75: Changes in cash | B75: =_xlfn.XLOOKUP($A75,Inputs!$A:$A,Inputs!B:B,,0) -> -169559 | C75: =_xlfn.XLOOKUP($A75,Inputs!$A:$A,Inputs!C:C,,0) -> 55536 | D75: =_xlfn.XLOOKUP($A75,Inputs!$A:$A,Inputs!D:D,,0) -> 341116 | E75: =_xlfn.XLOOKUP($A75,Inputs!$A:$A,Inputs!E:E,,0) -> -46037 | F75: =_xlfn.XLOOKUP($A75,Inputs!$A:$A,Inputs!F:F,,0) -> 10163 | G75: =_xlfn.XLOOKUP($A75,Inputs!$A:$A,Inputs!G:G,,0) -> 12933 | H75: =_xlfn.XLOOKUP($A75,Inputs!$A:$A,Inputs!H:H,,0) -> 52888 | I75: =_xlfn.XLOOKUP($A75,Inputs!$A:$A,Inputs!I:I,,0) -> 4255 | J75: =_xlfn.XLOOKUP($A75,Inputs!$A:$A,Inputs!J:J,,0) -> 29656 | K75: =_xlfn.XLOOKUP($A75,Inputs!$A:$A,Inputs!K:K,,0) -> 71724 | L75: =_xlfn.XLOOKUP($A75,Inputs!$A:$A,Inputs!L:L,,0) -> 50142 | M75: =_xlfn.XLOOKUP($A75,Inputs!$A:$A,Inputs!M:M,,0) -> -31868
A77: Other Data
A78: Number of employees | B78: =_xlfn.XLOOKUP($A78,Inputs!$A:$A,Inputs!B:B,,0) -> #N/A | C78: =_xlfn.XLOOKUP($A78,Inputs!$A:$A,Inputs!C:C,,0) -> #N/A | D78: =_xlfn.XLOOKUP($A78,Inputs!$A:$A,Inputs!D:D,,0) -> #N/A | E78: =_xlfn.XLOOKUP($A78,Inputs!$A:$A,Inputs!E:E,,0) -> #N/A | F78: =_xlfn.XLOOKUP($A78,Inputs!$A:$A,Inputs!F:F,,0) -> #N/A | G78: =_xlfn.XLOOKUP($A78,Inputs!$A:$A,Inputs!G:G,,0) -> #N/A | H78: =_xlfn.XLOOKUP($A78,Inputs!$A:$A,Inputs!H:H,,0) -> #N/A | I78: =_xlfn.XLOOKUP($A78,Inputs!$A:$A,Inputs!I:I,,0) -> #N/A | J78: =_xlfn.XLOOKUP($A78,Inputs!$A:$A,Inputs!J:J,,0) -> #N/A | K78: =_xlfn.XLOOKUP($A78,Inputs!$A:$A,Inputs!K:K,,0) -> #N/A | L78: =_xlfn.XLOOKUP($A78,Inputs!$A:$A,Inputs!L:L,,0) -> #N/A | M78: =_xlfn.XLOOKUP($A78,Inputs!$A:$A,Inputs!M:M,,0) -> #N/A
A79: Shares Outstanding | B79: =_xlfn.XLOOKUP($A79,Inputs!$A:$A,Inputs!B:B,,0) -> #N/A | C79: =_xlfn.XLOOKUP($A79,Inputs!$A:$A,Inputs!C:C,,0) -> #N/A | D79: =_xlfn.XLOOKUP($A79,Inputs!$A:$A,Inputs!D:D,,0) -> #N/A | E79: =_xlfn.XLOOKUP($A79,Inputs!$A:$A,Inputs!E:E,,0) -> #N/A | F79: =_xlfn.XLOOKUP($A79,Inputs!$A:$A,Inputs!F:F,,0) -> #N/A | G79: =_xlfn.XLOOKUP($A79,Inputs!$A:$A,Inputs!G:G,,0) -> #N/A | H79: =_xlfn.XLOOKUP($A79,Inputs!$A:$A,Inputs!H:H,,0) -> #N/A | I79: =_xlfn.XLOOKUP($A79,Inputs!$A:$A,Inputs!I:I,,0) -> #N/A | J79: =_xlfn.XLOOKUP($A79,Inputs!$A:$A,Inputs!J:J,,0) -> #N/A | K79: =_xlfn.XLOOKUP($A79,Inputs!$A:$A,Inputs!K:K,,0) -> #N/A | L79: =_xlfn.XLOOKUP($A79,Inputs!$A:$A,Inputs!L:L,,0) -> #N/A | M79: =_xlfn.XLOOKUP($A79,Inputs!$A:$A,Inputs!M:M,,0) -> #N/A
A80: Float | B80: =_xlfn.XLOOKUP($A80,Inputs!$A:$A,Inputs!B:B,,0) -> 0.91467577 | C80: =_xlfn.XLOOKUP($A80,Inputs!$A:$A,Inputs!C:C,,0) -> Yahoo Finance | D80: =_xlfn.XLOOKUP($A80,Inputs!$A:$A,Inputs!D:D,,0) -> 0 | E80: =_xlfn.XLOOKUP($A80,Inputs!$A:$A,Inputs!E:E,,0) -> 0 | F80: =_xlfn.XLOOKUP($A80,Inputs!$A:$A,Inputs!F:F,,0) -> 0 | G80: =_xlfn.XLOOKUP($A80,Inputs!$A:$A,Inputs!G:G,,0) -> 0 | H80: =_xlfn.XLOOKUP($A80,Inputs!$A:$A,Inputs!H:H,,0) -> 0 | I80: =_xlfn.XLOOKUP($A80,Inputs!$A:$A,Inputs!I:I,,0) -> 0 | J80: =_xlfn.XLOOKUP($A80,Inputs!$A:$A,Inputs!J:J,,0) -> 0 | K80: =_xlfn.XLOOKUP($A80,Inputs!$A:$A,Inputs!K:K,,0) -> 0 | L80: =_xlfn.XLOOKUP($A80,Inputs!$A:$A,Inputs!L:L,,0) -> 0 | M80: =_xlfn.XLOOKUP($A80,Inputs!$A:$A,Inputs!M:M,,0) -> 0
A81: Insiders Own | B81: =_xlfn.XLOOKUP($A81,Inputs!$A:$A,Inputs!B:B,,0) -> 0 | C81: =_xlfn.XLOOKUP($A81,Inputs!$A:$A,Inputs!C:C,,0) -> Yahoo Finance | D81: =_xlfn.XLOOKUP($A81,Inputs!$A:$A,Inputs!D:D,,0) -> 0 | E81: =_xlfn.XLOOKUP($A81,Inputs!$A:$A,Inputs!E:E,,0) -> 0 | F81: =_xlfn.XLOOKUP($A81,Inputs!$A:$A,Inputs!F:F,,0) -> 0 | G81: =_xlfn.XLOOKUP($A81,Inputs!$A:$A,Inputs!G:G,,0) -> 0 | H81: =_xlfn.XLOOKUP($A81,Inputs!$A:$A,Inputs!H:H,,0) -> 0 | I81: =_xlfn.XLOOKUP($A81,Inputs!$A:$A,Inputs!I:I,,0) -> 0 | J81: =_xlfn.XLOOKUP($A81,Inputs!$A:$A,Inputs!J:J,,0) -> 0 | K81: =_xlfn.XLOOKUP($A81,Inputs!$A:$A,Inputs!K:K,,0) -> 0 | L81: =_xlfn.XLOOKUP($A81,Inputs!$A:$A,Inputs!L:L,,0) -> 0 | M81: =_xlfn.XLOOKUP($A81,Inputs!$A:$A,Inputs!M:M,,0) -> 0
A82: Fitch/ S&P Rating | B82: =_xlfn.XLOOKUP($A82,Inputs!$A:$A,Inputs!B:B,,0) -> A2 | C82: =_xlfn.XLOOKUP($A82,Inputs!$A:$A,Inputs!C:C,,0) -> 10-K | D82: =_xlfn.XLOOKUP($A82,Inputs!$A:$A,Inputs!D:D,,0) -> 0 | E82: =_xlfn.XLOOKUP($A82,Inputs!$A:$A,Inputs!E:E,,0) -> 0 | F82: =_xlfn.XLOOKUP($A82,Inputs!$A:$A,Inputs!F:F,,0) -> 0 | G82: =_xlfn.XLOOKUP($A82,Inputs!$A:$A,Inputs!G:G,,0) -> 0 | H82: =_xlfn.XLOOKUP($A82,Inputs!$A:$A,Inputs!H:H,,0) -> 0 | I82: =_xlfn.XLOOKUP($A82,Inputs!$A:$A,Inputs!I:I,,0) -> 0 | J82: =_xlfn.XLOOKUP($A82,Inputs!$A:$A,Inputs!J:J,,0) -> 0 | K82: =_xlfn.XLOOKUP($A82,Inputs!$A:$A,Inputs!K:K,,0) -> 0 | L82: =_xlfn.XLOOKUP($A82,Inputs!$A:$A,Inputs!L:L,,0) -> 0 | M82: =_xlfn.XLOOKUP($A82,Inputs!$A:$A,Inputs!M:M,,0) -> 0
A83: Dividend Yield | B83: =_xlfn.XLOOKUP($A83,Inputs!$A:$A,Inputs!B:B,,0) -> #N/A | C83: =_xlfn.XLOOKUP($A83,Inputs!$A:$A,Inputs!C:C,,0) -> #N/A | D83: =_xlfn.XLOOKUP($A83,Inputs!$A:$A,Inputs!D:D,,0) -> #N/A | E83: =_xlfn.XLOOKUP($A83,Inputs!$A:$A,Inputs!E:E,,0) -> #N/A | F83: =_xlfn.XLOOKUP($A83,Inputs!$A:$A,Inputs!F:F,,0) -> #N/A | G83: =_xlfn.XLOOKUP($A83,Inputs!$A:$A,Inputs!G:G,,0) -> #N/A | H83: =_xlfn.XLOOKUP($A83,Inputs!$A:$A,Inputs!H:H,,0) -> #N/A | I83: =_xlfn.XLOOKUP($A83,Inputs!$A:$A,Inputs!I:I,,0) -> #N/A | J83: =_xlfn.XLOOKUP($A83,Inputs!$A:$A,Inputs!J:J,,0) -> #N/A | K83: =_xlfn.XLOOKUP($A83,Inputs!$A:$A,Inputs!K:K,,0) -> #N/A | L83: =_xlfn.XLOOKUP($A83,Inputs!$A:$A,Inputs!L:L,,0) -> #N/A | M83: =_xlfn.XLOOKUP($A83,Inputs!$A:$A,Inputs!M:M,,0) -> #N/A
A84: Daily Volume in Millions of USD | B84: =_xlfn.XLOOKUP($A84,Inputs!$A:$A,Inputs!B:B,,0) -> 3.238 | C84: =_xlfn.XLOOKUP($A84,Inputs!$A:$A,Inputs!C:C,,0) -> Yahoo Finance | D84: =_xlfn.XLOOKUP($A84,Inputs!$A:$A,Inputs!D:D,,0) -> 0 | E84: =_xlfn.XLOOKUP($A84,Inputs!$A:$A,Inputs!E:E,,0) -> 0 | F84: =_xlfn.XLOOKUP($A84,Inputs!$A:$A,Inputs!F:F,,0) -> 0 | G84: =_xlfn.XLOOKUP($A84,Inputs!$A:$A,Inputs!G:G,,0) -> 0 | H84: =_xlfn.XLOOKUP($A84,Inputs!$A:$A,Inputs!H:H,,0) -> 0 | I84: =_xlfn.XLOOKUP($A84,Inputs!$A:$A,Inputs!I:I,,0) -> 0 | J84: =_xlfn.XLOOKUP($A84,Inputs!$A:$A,Inputs!J:J,,0) -> 0 | K84: =_xlfn.XLOOKUP($A84,Inputs!$A:$A,Inputs!K:K,,0) -> 0 | L84: =_xlfn.XLOOKUP($A84,Inputs!$A:$A,Inputs!L:L,,0) -> 0 | M84: =_xlfn.XLOOKUP($A84,Inputs!$A:$A,Inputs!M:M,,0) -> 0
B86: 2020 | C86: 2021 | D86: 2022
A87: Short % of Float | B87: 0 | C87: 0 | D87: 0
A88: EPS | B88: 0 | C88: 0 | D88: 0
A90: Corporate Bonds 3, 5 Y 10 | B90: Average Price | C90: Moody's | D90: YTM | E90: DIVISA
B91: =VLOOKUP($A91,Inputs!$A$5:$M$98,MATCH(B$4,Inputs!$B$5:$M$5,0)+1,FALSE) -> #N/A | C91: =VLOOKUP($A91,Inputs!$A$5:$M$98,MATCH(C$4,Inputs!$B$5:$M$5,0)+1,FALSE) -> #N/A | D91: =VLOOKUP($A91,Inputs!$A$5:$M$98,MATCH(D$4,Inputs!$B$5:$M$5,0)+1,FALSE) -> #N/A | E91: =VLOOKUP($A91,Inputs!$A$5:$M$98,MATCH(E$4,Inputs!$B$5:$M$5,0)+1,FALSE) -> #N/A

Sheet Fin. Data (Common Size)
A1: =Inputs!H3 -> Daikin Industries,Ltd. (6367.T)
A2: =Inputs!G2 -> Figures in Millions of JPY
A3: Results
B4: =OP!J17 -> 2022 | C4: =B4-1 -> 2021 | D4: =C4-1 -> 2020 | E4: =D4-1 -> 2019 | F4: =E4-1 -> 2018 | G4: =F4-1 -> 2017 | H4: =G4-1 -> 2016 | I4: =H4-1 -> 2015 | J4: =I4-1 -> 2014 | ... M4: =L4-1 -> 2011
A5: Net Sales | B5: =_xlfn.XLOOKUP($A5,Inputs!$A:$A,Inputs!B:B,,0) -> 3981578 | C5: =_xlfn.XLOOKUP($A5,Inputs!$A:$A,Inputs!C:C,,0) -> 3109106 | D5: =_xlfn.XLOOKUP($A5,Inputs!$A:$A,Inputs!D:D,,0) -> 2493386 | E5: =_xlfn.XLOOKUP($A5,Inputs!$A:$A,Inputs!E:E,,0) -> 2550305 | F5: =_xlfn.XLOOKUP($A5,Inputs!$A:$A,Inputs!F:F,,0) -> 2481109 | G5: =_xlfn.XLOOKUP($A5,Inputs!$A:$A,Inputs!G:G,,0) -> 2290560 | H5: =_xlfn.XLOOKUP($A5,Inputs!$A:$A,Inputs!H:H,,0) -> 2043968 | I5: =_xlfn.XLOOKUP($A5,Inputs!$A:$A,Inputs!I:I,,0) -> 2043691 | J5: =_xlfn.XLOOKUP($A5,Inputs!$A:$A,Inputs!J:J,,0) -> 1915013 | K5: =_xlfn.XLOOKUP($A5,Inputs!$A:$A,Inputs!K:K,,0) -> 1787679 | L5: =_xlfn.XLOOKUP($A5,Inputs!$A:$A,Inputs!L:L,,0) -> 1290903 | M5: =_xlfn.XLOOKUP($A5,Inputs!$A:$A,Inputs!M:M,,0) -> 1218700
A6: Growth vs. Previous year | B6: =IFERROR(B5/C5-1,"-") -> 0.28061829 | C6: =IFERROR(C5/D5-1,"-") -> 0.24694131 | D6: =IFERROR(D5/E5-1,"-") -> -0.022318507 | E6: =IFERROR(E5/F5-1,"-") -> 0.027889142 | F6: =IFERROR(F5/G5-1,"-") -> 0.083188827 | G6: =IFERROR(G5/H5-1,"-") -> 0.12064377 | H6: =IFERROR(H5/I5-1,"-") -> 0.00013553908 | I6: =IFERROR(I5/J5-1,"-") -> 0.067194322 | ... M6: =IFERROR(M5/N5-1,"-") -> -
A7: Gross Profit | B7: =_xlfn.XLOOKUP($A7,Inputs!$A:$A,Inputs!B:B,,0) -> 1331476 | C7: =_xlfn.XLOOKUP($A7,Inputs!$A:$A,Inputs!C:C,,0) -> 1057339 | D7: =_xlfn.XLOOKUP($A7,Inputs!$A:$A,Inputs!D:D,,0) -> 864136 | E7: =_xlfn.XLOOKUP($A7,Inputs!$A:$A,Inputs!E:E,,0) -> 884898 | F7: =_xlfn.XLOOKUP($A7,Inputs!$A:$A,Inputs!F:F,,0) -> 868923 | G7: =_xlfn.XLOOKUP($A7,Inputs!$A:$A,Inputs!G:G,,0) -> 798829 | H7: =_xlfn.XLOOKUP($A7,Inputs!$A:$A,Inputs!H:H,,0) -> 730935 | I7: =_xlfn.XLOOKUP($A7,Inputs!$A:$A,Inputs!I:I,,0) -> 711576 | J7: =_xlfn.XLOOKUP($A7,Inputs!$A:$A,Inputs!J:J,,0) -> 649901 | K7: =_xlfn.XLOOKUP($A7,Inputs!$A:$A,Inputs!K:K,,0) -> 568323 | L7: =_xlfn.XLOOKUP($A7,Inputs!$A:$A,Inputs!L:L,,0) -> 388047 | M7: =_xlfn.XLOOKUP($A7,Inputs!$A:$A,Inputs!M:M,,0) -> 371901
A8: % over sales | B8: =IFERROR(B7/B$5,"-") -> 0.33440912 | C8: =IFERROR(C7/C$5,"-") -> 0.34007814 | D8: =IFERROR(D7/D$5,"-") -> 0.34657129 | E8: =IFERROR(E7/E$5,"-") -> 0.34697732 | F8: =IFERROR(F7/F$5,"-") -> 0.35021557 | G8: =IFERROR(G7/G$5,"-") -> 0.34874834 | H8: =IFERROR(H7/H$5,"-") -> 0.35760589 | I8: =IFERROR(I7/I$5,"-") -> 0.34818179 | ... M8: =IFERROR(M7/M$5,"-") -> 0.30516206
A9: Operating expenses | B9: =B5-B11 -> 3616685 | C9: =C5-C11 -> 2797804 | D9: =D5-D11 -> 2255459 | E9: =E5-E11 -> 2308651 | F9: =F5-F11 -> 2205850 | G9: =G5-G11 -> 2039744 | H9: =H5-H11 -> 1813155 | I9: =I5-I11 -> 1828205 | ... M9: =M5-M11 -> 1139702
A10: % over sales | B10: =IFERROR(B9/B$5,"-") -> 0.90835468 | C10: =IFERROR(C9/C$5,"-") -> 0.89987411 | D10: =IFERROR(D9/D$5,"-") -> 0.90457675 | E10: =IFERROR(E9/E$5,"-") -> 0.90524506 | F10: =IFERROR(F9/F$5,"-") -> 0.88905808 | G10: =IFERROR(G9/G$5,"-") -> 0.89050014 | H10: =IFERROR(H9/H$5,"-") -> 0.88707602 | I10: =IFERROR(I9/I$5,"-") -> 0.89456038 | ... M10: =IFERROR(M9/M$5,"-") -> 0.93517847
A11: Operating Income | B11: =_xlfn.XLOOKUP($A11,Inputs!$A:$A,Inputs!B:B,,0) -> 364893 | C11: =_xlfn.XLOOKUP($A11,Inputs!$A:$A,Inputs!C:C,,0) -> 311302 | D11: =_xlfn.XLOOKUP($A11,Inputs!$A:$A,Inputs!D:D,,0) -> 237927 | E11: =_xlfn.XLOOKUP($A11,Inputs!$A:$A,Inputs!E:E,,0) -> 241654 | F11: =_xlfn.XLOOKUP($A11,Inputs!$A:$A,Inputs!F:F,,0) -> 275259 | G11: =_xlfn.XLOOKUP($A11,Inputs!$A:$A,Inputs!G:G,,0) -> 250816 | H11: =_xlfn.XLOOKUP($A11,Inputs!$A:$A,Inputs!H:H,,0) -> 230813 | I11: =_xlfn.XLOOKUP($A11,Inputs!$A:$A,Inputs!I:I,,0) -> 215486 | J11: =_xlfn.XLOOKUP($A11,Inputs!$A:$A,Inputs!J:J,,0) -> 185291 | K11: =_xlfn.XLOOKUP($A11,Inputs!$A:$A,Inputs!K:K,,0) -> 155203 | L11: =_xlfn.XLOOKUP($A11,Inputs!$A:$A,Inputs!L:L,,0) -> 75352 | M11: =_xlfn.XLOOKUP($A11,Inputs!$A:$A,Inputs!M:M,,0) -> 78998
A12: % over sales | B12: =IFERROR(B11/B$5,"-") -> 0.091645323 | C12: =IFERROR(C11/C$5,"-") -> 0.10012589 | D12: =IFERROR(D11/D$5,"-") -> 0.095423252 | E12: =IFERROR(E11/E$5,"-") -> 0.094754941 | F12: =IFERROR(F11/F$5,"-") -> 0.11094192 | G12: =IFERROR(G11/G$5,"-") -> 0.10949986 | H12: =IFERROR(H11/H$5,"-") -> 0.11292398 | I12: =IFERROR(I11/I$5,"-") -> 0.10543962 | ... M12: =IFERROR(M11/M$5,"-") -> 0.064821531
A13: Growth vs. Previous year | B13: =IFERROR(B12/C12-1,"-") -> -0.084699031 | C13: =IFERROR(C12/D12-1,"-") -> 0.049281872 | D13: =IFERROR(D12/E12-1,"-") -> 0.0070530431 | E13: =IFERROR(E12/F12-1,"-") -> -0.14590499 | F13: =IFERROR(F12/G12-1,"-") -> 0.013169526 | G13: =IFERROR(G12/H12-1,"-") -> -0.030322337 | H13: =IFERROR(H12/I12-1,"-") -> 0.070982431 | I13: =IFERROR(I12/J12-1,"-") -> 0.089735825 | ... M13: =IFERROR(M12/N12-1,"-") -> -
A14: Net Financial Cost | B14: =_xlfn.XLOOKUP($A14,Inputs!$A:$A,Inputs!B:B,,0) -> -8730 | C14: =_xlfn.XLOOKUP($A14,Inputs!$A:$A,Inputs!C:C,,0) -> -638 | D14: =_xlfn.XLOOKUP($A14,Inputs!$A:$A,Inputs!D:D,,0) -> 2772 | E14: =_xlfn.XLOOKUP($A14,Inputs!$A:$A,Inputs!E:E,,0) -> -3039 | F14: =_xlfn.XLOOKUP($A14,Inputs!$A:$A,Inputs!F:F,,0) -> -2293 | G14: =_xlfn.XLOOKUP($A14,Inputs!$A:$A,Inputs!G:G,,0) -> -3838 | H14: =_xlfn.XLOOKUP($A14,Inputs!$A:$A,Inputs!H:H,,0) -> -3174 | I14: =_xlfn.XLOOKUP($A14,Inputs!$A:$A,Inputs!I:I,,0) -> -1526 | J14: =_xlfn.XLOOKUP($A14,Inputs!$A:$A,Inputs!J:J,,0) -> -3097 | K14: =_xlfn.XLOOKUP($A14,Inputs!$A:$A,Inputs!K:K,,0) -> -5129 | L14: =_xlfn.XLOOKUP($A14,Inputs!$A:$A,Inputs!L:L,,0) -> -4043 | M14: =_xlfn.XLOOKUP($A14,Inputs!$A:$A,Inputs!M:M,,0) -> -3165
A15: Other Expenses (Revenues) | B15: =_xlfn.XLOOKUP($A15,Inputs!$A:$A,Inputs!B:B,,0) -> 9533 | C15: =_xlfn.XLOOKUP($A15,Inputs!$A:$A,Inputs!C:C,,0) -> 9832 | D15: =_xlfn.XLOOKUP($A15,Inputs!$A:$A,Inputs!D:D,,0) -> -8652 | E15: =_xlfn.XLOOKUP($A15,Inputs!$A:$A,Inputs!E:E,,0) -> 11099 | F15: =_xlfn.XLOOKUP($A15,Inputs!$A:$A,Inputs!F:F,,0) -> -4272 | G15: =_xlfn.XLOOKUP($A15,Inputs!$A:$A,Inputs!G:G,,0) -> -1017 | H15: =_xlfn.XLOOKUP($A15,Inputs!$A:$A,Inputs!H:H,,0) -> -3012 | I15: =_xlfn.XLOOKUP($A15,Inputs!$A:$A,Inputs!I:I,,0) -> -12882 | J15: =_xlfn.XLOOKUP($A15,Inputs!$A:$A,Inputs!J:J,,0) -> 5446 | K15: =_xlfn.XLOOKUP($A15,Inputs!$A:$A,Inputs!K:K,,0) -> -1328 | L15: =_xlfn.XLOOKUP($A15,Inputs!$A:$A,Inputs!L:L,,0) -> 6612 | M15: =_xlfn.XLOOKUP($A15,Inputs!$A:$A,Inputs!M:M,,0) -> 1288
A16: EBIT | B16: =B11-B15 -> 355360 | C16: =C11-C15 -> 301470 | D16: =D11-D15 -> 246579 | E16: =E11-E15 -> 230555 | F16: =F11-F15 -> 279531 | G16: =G11-G15 -> 251833 | H16: =H11-H15 -> 233825 | I16: =I11-I15 -> 228368 | ... M16: =M11-M15 -> 77710
A17: Depreciation and Amortization | B17: ='Fin. Data'!B17 -> 182224 | C17: ='Fin. Data'!C17 -> 148062 | D17: ='Fin. Data'!D17 -> 133593 | E17: ='Fin. Data'!E17 -> 128485 | F17: ='Fin. Data'!F17 -> 99315 | G17: ='Fin. Data'!G17 -> 94833 | H17: ='Fin. Data'!H17 -> 85029 | I17: ='Fin. Data'!I17 -> 84202 | ... M17: ='Fin. Data'!M17 -> 50525
A18: Changes Net Working Capital | B18: =_xlfn.XLOOKUP($A18,Inputs!$A:$A,Inputs!B:B,,0) -> 318333 | C18: =_xlfn.XLOOKUP($A18,Inputs!$A:$A,Inputs!C:C,,0) -> -189514 | D18: =_xlfn.XLOOKUP($A18,Inputs!$A:$A,Inputs!D:D,,0) -> -8398 | E18: =_xlfn.XLOOKUP($A18,Inputs!$A:$A,Inputs!E:E,,0) -> 58668 | F18: =_xlfn.XLOOKUP($A18,Inputs!$A:$A,Inputs!F:F,,0) -> -63926 | G18: =_xlfn.XLOOKUP($A18,Inputs!$A:$A,Inputs!G:G,,0) -> 55820 | H18: =_xlfn.XLOOKUP($A18,Inputs!$A:$A,Inputs!H:H,,0) -> -22721 | I18: =_xlfn.XLOOKUP($A18,Inputs!$A:$A,Inputs!I:I,,0) -> -58205 | J18: =_xlfn.XLOOKUP($A18,Inputs!$A:$A,Inputs!J:J,,0) -> 93592 | K18: =_xlfn.XLOOKUP($A18,Inputs!$A:$A,Inputs!K:K,,0) -> -58679 | L18: =_xlfn.XLOOKUP($A18,Inputs!$A:$A,Inputs!L:L,,0) -> 138068 | M18: =_xlfn.XLOOKUP($A18,Inputs!$A:$A,Inputs!M:M,,0) -> 97060
A19: EBITDA | B19: =B11-B15+B17 -> 537584 | C19: =C11-C15+C17 -> 449532 | D19: =D11-D15+D17 -> 380172 | E19: =E11-E15+E17 -> 359040 | F19: =F11-F15+F17 -> 378846 | G19: =G11-G15+G17 -> 346666 | H19: =H11-H15+H17 -> 318854 | I19: =I11-I15+I17 -> 312570 | ... M19: =M11-M15+M17 -> 128235
A20: % over sales | B20: =IFERROR(B19/B$5,"-") -> 0.13501782 | C20: =IFERROR(C19/C$5,"-") -> 0.14458561 | D20: =IFERROR(D19/D$5,"-") -> 0.15247218 | E20: =IFERROR(E19/E$5,"-") -> 0.14078316 | F20: =IFERROR(F19/F$5,"-") -> 0.1526922 | G20: =IFERROR(G19/G$5,"-") -> 0.15134552 | H20: =IFERROR(H19/H$5,"-") -> 0.15599755 | I20: =IFERROR(I19/I$5,"-") -> 0.15294386 | ... M20: =IFERROR(M19/M$5,"-") -> 0.10522278
A21: Taxes | B21: =_xlfn.XLOOKUP($A21,Inputs!$A:$A,Inputs!B:B,,0) -> -107941 | C21: =_xlfn.XLOOKUP($A21,Inputs!$A:$A,Inputs!C:C,,0) -> -102786 | D21: =_xlfn.XLOOKUP($A21,Inputs!$A:$A,Inputs!D:D,,0) -> -75797 | E21: =_xlfn.XLOOKUP($A21,Inputs!$A:$A,Inputs!E:E,,0) -> -78982 | F21: =_xlfn.XLOOKUP($A21,Inputs!$A:$A,Inputs!F:F,,0) -> -79645 | G21: =_xlfn.XLOOKUP($A21,Inputs!$A:$A,Inputs!G:G,,0) -> -56908 | H21: =_xlfn.XLOOKUP($A21,Inputs!$A:$A,Inputs!H:H,,0) -> -70688 | I21: =_xlfn.XLOOKUP($A21,Inputs!$A:$A,Inputs!I:I,,0) -> -64090 | J21: =_xlfn.XLOOKUP($A21,Inputs!$A:$A,Inputs!J:J,,0) -> -67965 | K21: =_xlfn.XLOOKUP($A21,Inputs!$A:$A,Inputs!K:K,,0) -> -55959 | L21: =_xlfn.XLOOKUP($A21,Inputs!$A:$A,Inputs!L:L,,0) -> -34336 | M21: =_xlfn.XLOOKUP($A21,Inputs!$A:$A,Inputs!M:M,,0) -> -35948
A22: % Tax | B22: =IFERROR(B21/B$5,"-") -> -0.027110106 | C22: =IFERROR(C21/C$5,"-") -> -0.033059664 | D22: =IFERROR(D21/D$5,"-") -> -0.030399224 | E22: =IFERROR(E21/E$5,"-") -> -0.030969629 | F22: =IFERROR(F21/F$5,"-") -> -0.032100565 | G22: =IFERROR(G21/G$5,"-") -> -0.024844579 | H22: =IFERROR(H21/H$5,"-") -> -0.034583712 | I22: =IFERROR(I21/I$5,"-") -> -0.031359927 | ... M22: =IFERROR(M21/M$5,"-") -> -0.029497005
A23: Net income | B23: =_xlfn.XLOOKUP($A23,Inputs!$A:$A,Inputs!B:B,,0) -> 257755 | C23: =_xlfn.XLOOKUP($A23,Inputs!$A:$A,Inputs!C:C,,0) -> 217710 | D23: =_xlfn.XLOOKUP($A23,Inputs!$A:$A,Inputs!D:D,,0) -> 156250 | E23: =_xlfn.XLOOKUP($A23,Inputs!$A:$A,Inputs!E:E,,0) -> 170732 | F23: =_xlfn.XLOOKUP($A23,Inputs!$A:$A,Inputs!F:F,,0) -> 189049 | G23: =_xlfn.XLOOKUP($A23,Inputs!$A:$A,Inputs!G:G,,0) -> 189053 | H23: =_xlfn.XLOOKUP($A23,Inputs!$A:$A,Inputs!H:H,,0) -> 153939 | I23: =_xlfn.XLOOKUP($A23,Inputs!$A:$A,Inputs!I:I,,0) -> 136988 | J23: =_xlfn.XLOOKUP($A23,Inputs!$A:$A,Inputs!J:J,,0) -> 119675 | K23: =_xlfn.XLOOKUP($A23,Inputs!$A:$A,Inputs!K:K,,0) -> 92787 | L23: =_xlfn.XLOOKUP($A23,Inputs!$A:$A,Inputs!L:L,,0) -> 43585 | M23: =_xlfn.XLOOKUP($A23,Inputs!$A:$A,Inputs!M:M,,0) -> 41173
A24: % over sales | B24: =IFERROR(B23/B$5,"-") -> 0.064736896 | C24: =IFERROR(C23/C$5,"-") -> 0.070023344 | D24: =IFERROR(D23/D$5,"-") -> 0.062665789 | E24: =IFERROR(E23/E$5,"-") -> 0.066945718 | F24: =IFERROR(F23/F$5,"-") -> 0.076195363 | G24: =IFERROR(G23/G$5,"-") -> 0.082535712 | H24: =IFERROR(H23/H$5,"-") -> 0.075313801 | I24: =IFERROR(I23/I$5,"-") -> 0.067029703 | ... M24: =IFERROR(M23/M$5,"-") -> 0.03378436
A25: Growth vs. Previous year | B25: =IFERROR(B24/C24-1,"-") -> -0.075495517 | C25: =IFERROR(C24/D24-1,"-") -> 0.11740945 | D25: =IFERROR(D24/E24-1,"-") -> -0.063931343 | E25: =IFERROR(E24/F24-1,"-") -> -0.1213938 | F25: =IFERROR(F24/G24-1,"-") -> -0.076819464 | G25: =IFERROR(G24/H24-1,"-") -> 0.095890929 | H25: =IFERROR(H24/I24-1,"-") -> 0.12358848 | I25: =IFERROR(I24/J24-1,"-") -> 0.072594543 | ... M25: =IFERROR(M24/N24-1,"-") -> -
A26: Cash Generated | B26: =B39-C39 -> -199956 | C26: =C39-D39 -> 81521 | D26: =D39-E39 -> 365305 | E26: =E39-F39 -> 3012 | F26: =F39-G39 -> 10754 | G26: =G39-H39 -> 12934 | H26: =H39-I39 -> 52888 | I26: =I39-J39 -> 4256 | ... M26: =M39-N39 -> 135648
A27: Dividends | B27: =_xlfn.XLOOKUP($A27,Inputs!$A:$A,Inputs!B:B,,0) -> -61468 | C27: =_xlfn.XLOOKUP($A27,Inputs!$A:$A,Inputs!C:C,,0) -> -49746 | D27: =_xlfn.XLOOKUP($A27,Inputs!$A:$A,Inputs!D:D,,0) -> -46721 | E27: =_xlfn.XLOOKUP($A27,Inputs!$A:$A,Inputs!E:E,,0) -> -49730 | F27: =_xlfn.XLOOKUP($A27,Inputs!$A:$A,Inputs!F:F,,0) -> -42407 | G27: =_xlfn.XLOOKUP($A27,Inputs!$A:$A,Inputs!G:G,,0) -> -39473 | H27: =_xlfn.XLOOKUP($A27,Inputs!$A:$A,Inputs!H:H,,0) -> -36518 | I27: =_xlfn.XLOOKUP($A27,Inputs!$A:$A,Inputs!I:I,,0) -> -33567 | J27: =_xlfn.XLOOKUP($A27,Inputs!$A:$A,Inputs!J:J,,0) -> -19545 | K27: =_xlfn.XLOOKUP($A27,Inputs!$A:$A,Inputs!K:K,,0) -> -11946 | L27: =_xlfn.XLOOKUP($A27,Inputs!$A:$A,Inputs!L:L,,0) -> -10479 | M27: =_xlfn.XLOOKUP($A27,Inputs!$A:$A,Inputs!M:M,,0) -> -10489
A28: Share buyback | B28: =_xlfn.XLOOKUP($A28,Inputs!$A:$A,Inputs!B:B,,0) -> 0 | C28: =_xlfn.XLOOKUP($A28,Inputs!$A:$A,Inputs!C:C,,0) -> 0 | D28: =_xlfn.XLOOKUP($A28,Inputs!$A:$A,Inputs!D:D,,0) -> 0 | E28: =_xlfn.XLOOKUP($A28,Inputs!$A:$A,Inputs!E:E,,0) -> 0 | F28: =_xlfn.XLOOKUP($A28,Inputs!$A:$A,Inputs!F:F,,0) -> 0 | G28: =_xlfn.XLOOKUP($A28,Inputs!$A:$A,Inputs!G:G,,0) -> 0 | H28: =_xlfn.XLOOKUP($A28,Inputs!$A:$A,Inputs!H:H,,0) -> 0 | I28: =_xlfn.XLOOKUP($A28,Inputs!$A:$A,Inputs!I:I,,0) -> 0 | J28: =_xlfn.XLOOKUP($A28,Inputs!$A:$A,Inputs!J:J,,0) -> 0 | K28: =_xlfn.XLOOKUP($A28,Inputs!$A:$A,Inputs!K:K,,0) -> 0 | L28: =_xlfn.XLOOKUP($A28,Inputs!$A:$A,Inputs!L:L,,0) -> 0 | M28: =_xlfn.XLOOKUP($A28,Inputs!$A:$A,Inputs!M:M,,0) -> 0
A29: FNP | B29: =SUM(B26:B28) -> -261424 | C29: =SUM(C26:C28) -> 31775 | D29: =SUM(D26:D28) -> 318584 | E29: =SUM(E26:E28) -> -46718 | F29: =SUM(F26:F28) -> -31653 | G29: =SUM(G26:G28) -> -26539 | H29: =SUM(H26:H28) -> 16370 | I29: =SUM(I26:I28) -> -29311 | ... M29: =SUM(M26:M28) -> 125159
A30: FNP'' | B30: =+B29-(B58-C29) -> -916376 | C30: =+C29-(C58-D29) -> -7589 | D30: =+D29-(D58-E29) -> -317691 | E30: =+E29-(E58-F29) -> -450492 | F30: =+F29-(F58-G29) -> -540246 | G30: =+G29-(G58-H29) -> -476750 | H30: =+H29-(H58-I29) -> -533932 | I30: =+I29-(I58-J29) -> -551368 | ... M30: =+M29-(M58-N29) -> -203397
A31: FNP' | B31: =+B30+B33 -> -951296 | C31: =+C30+C33 -> -53810 | D31: =+D30+D33 -> -361062 | E31: =+E30+E33 -> -491777 | F31: =+F30+F33 -> -614483 | G31: =+G30+G33 -> -513221 | H31: =+H30+H33 -> -565960 | I31: =+I30+I33 -> -557497 | ... M31: =+M30+M33 -> -223284
A32: Net Capex | B32: =_xlfn.XLOOKUP($A32,Inputs!$A:$A,Inputs!B:B,,0) -> -175076 | C32: =_xlfn.XLOOKUP($A32,Inputs!$A:$A,Inputs!C:C,,0) -> -114106 | D32: =_xlfn.XLOOKUP($A32,Inputs!$A:$A,Inputs!D:D,,0) -> -104971 | E32: =_xlfn.XLOOKUP($A32,Inputs!$A:$A,Inputs!E:E,,0) -> -98094 | F32: =_xlfn.XLOOKUP($A32,Inputs!$A:$A,Inputs!F:F,,0) -> -85487 | G32: =_xlfn.XLOOKUP($A32,Inputs!$A:$A,Inputs!G:G,,0) -> -85679 | H32: =_xlfn.XLOOKUP($A32,Inputs!$A:$A,Inputs!H:H,,0) -> -88335 | I32: =_xlfn.XLOOKUP($A32,Inputs!$A:$A,Inputs!I:I,,0) -> -96696 | J32: =_xlfn.XLOOKUP($A32,Inputs!$A:$A,Inputs!J:J,,0) -> -71759 | K32: =_xlfn.XLOOKUP($A32,Inputs!$A:$A,Inputs!K:K,,0) -> -53647 | L32: =_xlfn.XLOOKUP($A32,Inputs!$A:$A,Inputs!L:L,,0) -> -53045 | M32: =_xlfn.XLOOKUP($A32,Inputs!$A:$A,Inputs!M:M,,0) -> -42459
A33: Investments & Acquisitions | B33: =_xlfn.XLOOKUP($A33,Inputs!$A:$A,Inputs!B:B,,0) -> -34920 | C33: =_xlfn.XLOOKUP($A33,Inputs!$A:$A,Inputs!C:C,,0) -> -46221 | D33: =_xlfn.XLOOKUP($A33,Inputs!$A:$A,Inputs!D:D,,0) -> -43371 | E33: =_xlfn.XLOOKUP($A33,Inputs!$A:$A,Inputs!E:E,,0) -> -41285 | F33: =_xlfn.XLOOKUP($A33,Inputs!$A:$A,Inputs!F:F,,0) -> -74237 | G33: =_xlfn.XLOOKUP($A33,Inputs!$A:$A,Inputs!G:G,,0) -> -36471 | H33: =_xlfn.XLOOKUP($A33,Inputs!$A:$A,Inputs!H:H,,0) -> -32028 | I33: =_xlfn.XLOOKUP($A33,Inputs!$A:$A,Inputs!I:I,,0) -> -6129 | J33: =_xlfn.XLOOKUP($A33,Inputs!$A:$A,Inputs!J:J,,0) -> -1004 | K33: =_xlfn.XLOOKUP($A33,Inputs!$A:$A,Inputs!K:K,,0) -> -26186 | L33: =_xlfn.XLOOKUP($A33,Inputs!$A:$A,Inputs!L:L,,0) -> -164983 | M33: =_xlfn.XLOOKUP($A33,Inputs!$A:$A,Inputs!M:M,,0) -> -19887
A34: Capex + Investments | B34: =+B32+B33 -> -209996 | C34: =+C32+C33 -> -160327 | D34: =+D32+D33 -> -148342 | E34: =+E32+E33 -> -139379 | F34: =+F32+F33 -> -159724 | G34: =+G32+G33 -> -122150 | H34: =+H32+H33 -> -120363 | I34: =+I32+I33 -> -102825 | ... M34: =+M32+M33 -> -62346
A35: Dividends + Share Buyback | B35: =+B27+B28 -> -61468 | C35: =+C27+C28 -> -49746 | D35: =+D27+D28 -> -46721 | E35: =+E27+E28 -> -49730 | F35: =+F27+F28 -> -42407 | G35: =+G27+G28 -> -39473 | H35: =+H27+H28 -> -36518 | I35: =+I27+I28 -> -33567 | ... M35: =+M27+M28 -> -10489
A36: Payout Ratio | B36: =IFERROR(B35/B23,"-") -> -0.23847452 | C36: =IFERROR(C35/C23,"-") -> -0.22849662 | D36: =IFERROR(D35/D23,"-") -> -0.2990144 | E36: =IFERROR(E35/E23,"-") -> -0.29127521 | F36: =IFERROR(F35/F23,"-") -> -0.2243175 | G36: =IFERROR(G35/G23,"-") -> -0.2087933 | H36: =IFERROR(H35/H23,"-") -> -0.23722384 | I36: =IFERROR(I35/I23,"-") -> -0.24503606 | ... M36: =IFERROR(M35/M23,"-") -> -0.25475433
A38: Assets
A39: Cash & Eq. | B39: =_xlfn.XLOOKUP($A39,Inputs!$A:$A,Inputs!B:B,,0) -> 617663 | C39: =_xlfn.XLOOKUP($A39,Inputs!$A:$A,Inputs!C:C,,0) -> 817619 | D39: =_xlfn.XLOOKUP($A39,Inputs!$A:$A,Inputs!D:D,,0) -> 736098 | E39: =_xlfn.XLOOKUP($A39,Inputs!$A:$A,Inputs!E:E,,0) -> 370793 | F39: =_xlfn.XLOOKUP($A39,Inputs!$A:$A,Inputs!F:F,,0) -> 367781 | G39: =_xlfn.XLOOKUP($A39,Inputs!$A:$A,Inputs!G:G,,0) -> 357027 | H39: =_xlfn.XLOOKUP($A39,Inputs!$A:$A,Inputs!H:H,,0) -> 344093 | I39: =_xlfn.XLOOKUP($A39,Inputs!$A:$A,Inputs!I:I,,0) -> 291205 | J39: =_xlfn.XLOOKUP($A39,Inputs!$A:$A,Inputs!J:J,,0) -> 286949 | K39: =_xlfn.XLOOKUP($A39,Inputs!$A:$A,Inputs!K:K,,0) -> 257295 | L39: =_xlfn.XLOOKUP($A39,Inputs!$A:$A,Inputs!L:L,,0) -> 185571 | M39: =_xlfn.XLOOKUP($A39,Inputs!$A:$A,Inputs!M:M,,0) -> 135648
A40: Accounts Receivable | B40: =_xlfn.XLOOKUP($A40,Inputs!$A:$A,Inputs!B:B,,0) -> 687135 | C40: =_xlfn.XLOOKUP($A40,Inputs!$A:$A,Inputs!C:C,,0) -> 578148 | D40: =_xlfn.XLOOKUP($A40,Inputs!$A:$A,Inputs!D:D,,0) -> 455256 | E40: =_xlfn.XLOOKUP($A40,Inputs!$A:$A,Inputs!E:E,,0) -> 430194 | F40: =_xlfn.XLOOKUP($A40,Inputs!$A:$A,Inputs!F:F,,0) -> 438684 | G40: =_xlfn.XLOOKUP($A40,Inputs!$A:$A,Inputs!G:G,,0) -> 392331 | H40: =_xlfn.XLOOKUP($A40,Inputs!$A:$A,Inputs!H:H,,0) -> 360845 | I40: =_xlfn.XLOOKUP($A40,Inputs!$A:$A,Inputs!I:I,,0) -> 349367 | J40: =_xlfn.XLOOKUP($A40,Inputs!$A:$A,Inputs!J:J,,0) -> 347584 | K40: =_xlfn.XLOOKUP($A40,Inputs!$A:$A,Inputs!K:K,,0) -> 310986 | L40: =_xlfn.XLOOKUP($A40,Inputs!$A:$A,Inputs!L:L,,0) -> 257096 | M40: =_xlfn.XLOOKUP($A40,Inputs!$A:$A,Inputs!M:M,,0) -> 204269
A41: Inventory | B41: =_xlfn.XLOOKUP($A41,Inputs!$A:$A,Inputs!B:B,,0) -> 993383 | C41: =_xlfn.XLOOKUP($A41,Inputs!$A:$A,Inputs!C:C,,0) -> 671461 | D41: =_xlfn.XLOOKUP($A41,Inputs!$A:$A,Inputs!D:D,,0) -> 469396 | E41: =_xlfn.XLOOKUP($A41,Inputs!$A:$A,Inputs!E:E,,0) -> 433782 | F41: =_xlfn.XLOOKUP($A41,Inputs!$A:$A,Inputs!F:F,,0) -> 436356 | G41: =_xlfn.XLOOKUP($A41,Inputs!$A:$A,Inputs!G:G,,0) -> 387225 | H41: =_xlfn.XLOOKUP($A41,Inputs!$A:$A,Inputs!H:H,,0) -> 358301 | I41: =_xlfn.XLOOKUP($A41,Inputs!$A:$A,Inputs!I:I,,0) -> 333650 | J41: =_xlfn.XLOOKUP($A41,Inputs!$A:$A,Inputs!J:J,,0) -> 354158 | K41: =_xlfn.XLOOKUP($A41,Inputs!$A:$A,Inputs!K:K,,0) -> 317559 | L41: =_xlfn.XLOOKUP($A41,Inputs!$A:$A,Inputs!L:L,,0) -> 285167 | M41: =_xlfn.XLOOKUP($A41,Inputs!$A:$A,Inputs!M:M,,0) -> 243598
A42: Property, Plant and Equipment | B42: =_xlfn.XLOOKUP($A42,Inputs!$A:$A,Inputs!B:B,,0) -> 900944 | C42: =_xlfn.XLOOKUP($A42,Inputs!$A:$A,Inputs!C:C,,0) -> 743364 | D42: =_xlfn.XLOOKUP($A42,Inputs!$A:$A,Inputs!D:D,,0) -> 647410 | E42: =_xlfn.XLOOKUP($A42,Inputs!$A:$A,Inputs!E:E,,0) -> 579980 | F42: =_xlfn.XLOOKUP($A42,Inputs!$A:$A,Inputs!F:F,,0) -> 482962 | G42: =_xlfn.XLOOKUP($A42,Inputs!$A:$A,Inputs!G:G,,0) -> 454834 | H42: =_xlfn.XLOOKUP($A42,Inputs!$A:$A,Inputs!H:H,,0) -> 424527 | I42: =_xlfn.XLOOKUP($A42,Inputs!$A:$A,Inputs!I:I,,0) -> 385099 | J42: =_xlfn.XLOOKUP($A42,Inputs!$A:$A,Inputs!J:J,,0) -> 347755 | K42: =_xlfn.XLOOKUP($A42,Inputs!$A:$A,Inputs!K:K,,0) -> 299716 | L42: =_xlfn.XLOOKUP($A42,Inputs!$A:$A,Inputs!L:L,,0) -> 274201 | M42: =_xlfn.XLOOKUP($A42,Inputs!$A:$A,Inputs!M:M,,0) -> 224357
A43: Other Assets | B43: =_xlfn.XLOOKUP($A43,Inputs!$A:$A,Inputs!B:B,,0) -> 917696 | C43: =_xlfn.XLOOKUP($A43,Inputs!$A:$A,Inputs!C:C,,0) -> 796178 | D43: =_xlfn.XLOOKUP($A43,Inputs!$A:$A,Inputs!D:D,,0) -> 701296 | E43: =_xlfn.XLOOKUP($A43,Inputs!$A:$A,Inputs!E:E,,0) -> 669611 | F43: =_xlfn.XLOOKUP($A43,Inputs!$A:$A,Inputs!F:F,,0) -> 663256 | G43: =_xlfn.XLOOKUP($A43,Inputs!$A:$A,Inputs!G:G,,0) -> 573160 | H43: =_xlfn.XLOOKUP($A43,Inputs!$A:$A,Inputs!H:H,,0) -> 613573 | I43: =_xlfn.XLOOKUP($A43,Inputs!$A:$A,Inputs!I:I,,0) -> 596434 | J43: =_xlfn.XLOOKUP($A43,Inputs!$A:$A,Inputs!J:J,,0) -> 668160 | K43: =_xlfn.XLOOKUP($A43,Inputs!$A:$A,Inputs!K:K,,0) -> 633349 | L43: =_xlfn.XLOOKUP($A43,Inputs!$A:$A,Inputs!L:L,,0) -> 586003 | M43: =_xlfn.XLOOKUP($A43,Inputs!$A:$A,Inputs!M:M,,0) -> 234440
A44: Total Assets | B44: =_xlfn.XLOOKUP($A44,Inputs!$A:$A,Inputs!B:B,,0) -> 4303682 | C44: =_xlfn.XLOOKUP($A44,Inputs!$A:$A,Inputs!C:C,,0) -> 3823038 | D44: =_xlfn.XLOOKUP($A44,Inputs!$A:$A,Inputs!D:D,,0) -> 3239662 | E44: =_xlfn.XLOOKUP($A44,Inputs!$A:$A,Inputs!E:E,,0) -> 2667512 | F44: =_xlfn.XLOOKUP($A44,Inputs!$A:$A,Inputs!F:F,,0) -> 2700890 | G44: =_xlfn.XLOOKUP($A44,Inputs!$A:$A,Inputs!G:G,,0) -> 2475708 | H44: =_xlfn.XLOOKUP($A44,Inputs!$A:$A,Inputs!H:H,,0) -> 2356148 | I44: =_xlfn.XLOOKUP($A44,Inputs!$A:$A,Inputs!I:I,,0) -> 2191105 | J44: =_xlfn.XLOOKUP($A44,Inputs!$A:$A,Inputs!J:J,,0) -> 2263989 | K44: =_xlfn.XLOOKUP($A44,Inputs!$A:$A,Inputs!K:K,,0) -> 2011870 | L44: =_xlfn.XLOOKUP($A44,Inputs!$A:$A,Inputs!L:L,,0) -> 1735836 | M44: =_xlfn.XLOOKUP($A44,Inputs!$A:$A,Inputs!M:M,,0) -> 1160564
A47: Liabilities
A48: Current Liabilities | B48: =_xlfn.XLOOKUP($A48,Inputs!$A:$A,Inputs!B:B,,0) -> 1449321 | C48: =_xlfn.XLOOKUP($A48,Inputs!$A:$A,Inputs!C:C,,0) -> 1306239 | D48: =_xlfn.XLOOKUP($A48,Inputs!$A:$A,Inputs!D:D,,0) -> 765984 | E48: =_xlfn.XLOOKUP($A48,Inputs!$A:$A,Inputs!E:E,,0) -> 693957 | F48: =_xlfn.XLOOKUP($A48,Inputs!$A:$A,Inputs!F:F,,0) -> 768815 | G48: =_xlfn.XLOOKUP($A48,Inputs!$A:$A,Inputs!G:G,,0) -> 603331 | H48: =_xlfn.XLOOKUP($A48,Inputs!$A:$A,Inputs!H:H,,0) -> 626676 | I48: =_xlfn.XLOOKUP($A48,Inputs!$A:$A,Inputs!I:I,,0) -> 563727 | J48: =_xlfn.XLOOKUP($A48,Inputs!$A:$A,Inputs!J:J,,0) -> 525624 | K48: =_xlfn.XLOOKUP($A48,Inputs!$A:$A,Inputs!K:K,,0) -> 533467 | L48: =_xlfn.XLOOKUP($A48,Inputs!$A:$A,Inputs!L:L,,0) -> 382627 | M48: =_xlfn.XLOOKUP($A48,Inputs!$A:$A,Inputs!M:M,,0) -> 396339
A49: Short-Term Debt | B49: =_xlfn.XLOOKUP($A49,Inputs!$A:$A,Inputs!B:B,,0) -> 372541 | C49: =_xlfn.XLOOKUP($A49,Inputs!$A:$A,Inputs!C:C,,0) -> 97376 | D49: =_xlfn.XLOOKUP($A49,Inputs!$A:$A,Inputs!D:D,,0) -> 40754 | E49: =_xlfn.XLOOKUP($A49,Inputs!$A:$A,Inputs!E:E,,0) -> 48937 | F49: =_xlfn.XLOOKUP($A49,Inputs!$A:$A,Inputs!F:F,,0) -> 146066 | G49: =_xlfn.XLOOKUP($A49,Inputs!$A:$A,Inputs!G:G,,0) -> 45530 | H49: =_xlfn.XLOOKUP($A49,Inputs!$A:$A,Inputs!H:H,,0) -> 57699 | I49: =_xlfn.XLOOKUP($A49,Inputs!$A:$A,Inputs!I:I,,0) -> 54675 | J49: =_xlfn.XLOOKUP($A49,Inputs!$A:$A,Inputs!J:J,,0) -> 57897 | K49: =_xlfn.XLOOKUP($A49,Inputs!$A:$A,Inputs!K:K,,0) -> 43325 | L49: =_xlfn.XLOOKUP($A49,Inputs!$A:$A,Inputs!L:L,,0) -> 65334 | M49: =_xlfn.XLOOKUP($A49,Inputs!$A:$A,Inputs!M:M,,0) -> 90448
A50: Short-Term Leases | B50: =_xlfn.XLOOKUP($A50,Inputs!$A:$A,Inputs!B:B,,0) -> 30442 | C50: =_xlfn.XLOOKUP($A50,Inputs!$A:$A,Inputs!C:C,,0) -> 25876 | D50: =_xlfn.XLOOKUP($A50,Inputs!$A:$A,Inputs!D:D,,0) -> 20639 | E50: =_xlfn.XLOOKUP($A50,Inputs!$A:$A,Inputs!E:E,,0) -> 17300 | F50: =_xlfn.XLOOKUP($A50,Inputs!$A:$A,Inputs!F:F,,0) -> 1241 | G50: =_xlfn.XLOOKUP($A50,Inputs!$A:$A,Inputs!G:G,,0) -> 1499 | H50: =_xlfn.XLOOKUP($A50,Inputs!$A:$A,Inputs!H:H,,0) -> 1797 | I50: =_xlfn.XLOOKUP($A50,Inputs!$A:$A,Inputs!I:I,,0) -> 1943 | J50: =_xlfn.XLOOKUP($A50,Inputs!$A:$A,Inputs!J:J,,0) -> 1913 | K50: =_xlfn.XLOOKUP($A50,Inputs!$A:$A,Inputs!K:K,,0) -> 1731 | L50: =_xlfn.XLOOKUP($A50,Inputs!$A:$A,Inputs!L:L,,0) -> 1464 | M50: =_xlfn.XLOOKUP($A50,Inputs!$A:$A,Inputs!M:M,,0) -> 2042
A51: Other current liabilities | B51: =_xlfn.XLOOKUP($A51,Inputs!$A:$A,Inputs!B:B,,0) -> 693691 | C51: =_xlfn.XLOOKUP($A51,Inputs!$A:$A,Inputs!C:C,,0) -> 880366 | D51: =_xlfn.XLOOKUP($A51,Inputs!$A:$A,Inputs!D:D,,0) -> 474845 | E51: =_xlfn.XLOOKUP($A51,Inputs!$A:$A,Inputs!E:E,,0) -> 437877 | F51: =_xlfn.XLOOKUP($A51,Inputs!$A:$A,Inputs!F:F,,0) -> 416973 | G51: =_xlfn.XLOOKUP($A51,Inputs!$A:$A,Inputs!G:G,,0) -> 372311 | H51: =_xlfn.XLOOKUP($A51,Inputs!$A:$A,Inputs!H:H,,0) -> 394033 | I51: =_xlfn.XLOOKUP($A51,Inputs!$A:$A,Inputs!I:I,,0) -> 351071 | J51: =_xlfn.XLOOKUP($A51,Inputs!$A:$A,Inputs!J:J,,0) -> 311877 | K51: =_xlfn.XLOOKUP($A51,Inputs!$A:$A,Inputs!K:K,,0) -> 326327 | L51: =_xlfn.XLOOKUP($A51,Inputs!$A:$A,Inputs!L:L,,0) -> 188465 | M51: =_xlfn.XLOOKUP($A51,Inputs!$A:$A,Inputs!M:M,,0) -> 193741
A52: Non-current Liabilities | B52: =_xlfn.XLOOKUP($A52,Inputs!$A:$A,Inputs!B:B,,0) -> 616213 | C52: =_xlfn.XLOOKUP($A52,Inputs!$A:$A,Inputs!C:C,,0) -> 545526 | D52: =_xlfn.XLOOKUP($A52,Inputs!$A:$A,Inputs!D:D,,0) -> 805970 | E52: =_xlfn.XLOOKUP($A52,Inputs!$A:$A,Inputs!E:E,,0) -> 536700 | F52: =_xlfn.XLOOKUP($A52,Inputs!$A:$A,Inputs!F:F,,0) -> 514280 | G52: =_xlfn.XLOOKUP($A52,Inputs!$A:$A,Inputs!G:G,,0) -> 574314 | H52: =_xlfn.XLOOKUP($A52,Inputs!$A:$A,Inputs!H:H,,0) -> 616756 | I52: =_xlfn.XLOOKUP($A52,Inputs!$A:$A,Inputs!I:I,,0) -> 611851 | J52: =_xlfn.XLOOKUP($A52,Inputs!$A:$A,Inputs!J:J,,0) -> 712648 | K52: =_xlfn.XLOOKUP($A52,Inputs!$A:$A,Inputs!K:K,,0) -> 675707 | L52: =_xlfn.XLOOKUP($A52,Inputs!$A:$A,Inputs!L:L,,0) -> 733756 | M52: =_xlfn.XLOOKUP($A52,Inputs!$A:$A,Inputs!M:M,,0) -> 260414
A53: Long-Term Debt | B53: =_xlfn.XLOOKUP($A53,Inputs!$A:$A,Inputs!B:B,,0) -> 314186 | C53: =_xlfn.XLOOKUP($A53,Inputs!$A:$A,Inputs!C:C,,0) -> 260572 | D53: =_xlfn.XLOOKUP($A53,Inputs!$A:$A,Inputs!D:D,,0) -> 548803 | E53: =_xlfn.XLOOKUP($A53,Inputs!$A:$A,Inputs!E:E,,0) -> 323184 | F53: =_xlfn.XLOOKUP($A53,Inputs!$A:$A,Inputs!F:F,,0) -> 335988 | G53: =_xlfn.XLOOKUP($A53,Inputs!$A:$A,Inputs!G:G,,0) -> 421051 | H53: =_xlfn.XLOOKUP($A53,Inputs!$A:$A,Inputs!H:H,,0) -> 463292 | I53: =_xlfn.XLOOKUP($A53,Inputs!$A:$A,Inputs!I:I,,0) -> 477491 | J53: =_xlfn.XLOOKUP($A53,Inputs!$A:$A,Inputs!J:J,,0) -> 560874 | K53: =_xlfn.XLOOKUP($A53,Inputs!$A:$A,Inputs!K:K,,0) -> 550475 | L53: =_xlfn.XLOOKUP($A53,Inputs!$A:$A,Inputs!L:L,,0) -> 633033 | M53: =_xlfn.XLOOKUP($A53,Inputs!$A:$A,Inputs!M:M,,0) -> 238108
A54: Long-Term Leases | B54: =_xlfn.XLOOKUP($A54,Inputs!$A:$A,Inputs!B:B,,0) -> 96597 | C54: =_xlfn.XLOOKUP($A54,Inputs!$A:$A,Inputs!C:C,,0) -> 76508 | D54: =_xlfn.XLOOKUP($A54,Inputs!$A:$A,Inputs!D:D,,0) -> 64736 | E54: =_xlfn.XLOOKUP($A54,Inputs!$A:$A,Inputs!E:E,,0) -> 58482 | F54: =_xlfn.XLOOKUP($A54,Inputs!$A:$A,Inputs!F:F,,0) -> 9959 | G54: =_xlfn.XLOOKUP($A54,Inputs!$A:$A,Inputs!G:G,,0) -> 9301 | H54: =_xlfn.XLOOKUP($A54,Inputs!$A:$A,Inputs!H:H,,0) -> 9462 | I54: =_xlfn.XLOOKUP($A54,Inputs!$A:$A,Inputs!I:I,,0) -> 1929 | J54: =_xlfn.XLOOKUP($A54,Inputs!$A:$A,Inputs!J:J,,0) -> 2717 | K54: =_xlfn.XLOOKUP($A54,Inputs!$A:$A,Inputs!K:K,,0) -> 0 | L54: =_xlfn.XLOOKUP($A54,Inputs!$A:$A,Inputs!L:L,,0) -> 1912 | M54: =_xlfn.XLOOKUP($A54,Inputs!$A:$A,Inputs!M:M,,0) -> 2002
A55: Other non-current liabilities | B55: =_xlfn.XLOOKUP($A55,Inputs!$A:$A,Inputs!B:B,,0) -> 205430 | C55: =_xlfn.XLOOKUP($A55,Inputs!$A:$A,Inputs!C:C,,0) -> 208446 | D55: =_xlfn.XLOOKUP($A55,Inputs!$A:$A,Inputs!D:D,,0) -> 192431 | E55: =_xlfn.XLOOKUP($A55,Inputs!$A:$A,Inputs!E:E,,0) -> 155034 | F55: =_xlfn.XLOOKUP($A55,Inputs!$A:$A,Inputs!F:F,,0) -> 168333 | G55: =_xlfn.XLOOKUP($A55,Inputs!$A:$A,Inputs!G:G,,0) -> 143962 | H55: =_xlfn.XLOOKUP($A55,Inputs!$A:$A,Inputs!H:H,,0) -> 144002 | I55: =_xlfn.XLOOKUP($A55,Inputs!$A:$A,Inputs!I:I,,0) -> 132431 | J55: =_xlfn.XLOOKUP($A55,Inputs!$A:$A,Inputs!J:J,,0) -> 149057 | K55: =_xlfn.XLOOKUP($A55,Inputs!$A:$A,Inputs!K:K,,0) -> 125232 | L55: =_xlfn.XLOOKUP($A55,Inputs!$A:$A,Inputs!L:L,,0) -> 98811 | M55: =_xlfn.XLOOKUP($A55,Inputs!$A:$A,Inputs!M:M,,0) -> 20304
A56: Total Liabilities | B56: =_xlfn.XLOOKUP($A56,Inputs!$A:$A,Inputs!B:B,,0) -> 2065534 | C56: =_xlfn.XLOOKUP($A56,Inputs!$A:$A,Inputs!C:C,,0) -> 1851765 | D56: =_xlfn.XLOOKUP($A56,Inputs!$A:$A,Inputs!D:D,,0) -> 1571954 | E56: =_xlfn.XLOOKUP($A56,Inputs!$A:$A,Inputs!E:E,,0) -> 1230657 | F56: =_xlfn.XLOOKUP($A56,Inputs!$A:$A,Inputs!F:F,,0) -> 1283095 | G56: =_xlfn.XLOOKUP($A56,Inputs!$A:$A,Inputs!G:G,,0) -> 1177645 | H56: =_xlfn.XLOOKUP($A56,Inputs!$A:$A,Inputs!H:H,,0) -> 1243432 | I56: =_xlfn.XLOOKUP($A56,Inputs!$A:$A,Inputs!I:I,,0) -> 1175578 | J56: =_xlfn.XLOOKUP($A56,Inputs!$A:$A,Inputs!J:J,,0) -> 1238272 | K56: =_xlfn.XLOOKUP($A56,Inputs!$A:$A,Inputs!K:K,,0) -> 1209174 | L56: =_xlfn.XLOOKUP($A56,Inputs!$A:$A,Inputs!L:L,,0) -> 1116383 | M56: =_xlfn.XLOOKUP($A56,Inputs!$A:$A,Inputs!M:M,,0) -> 656753
A58: Debt | B58: =B49+B53 -> 686727 | C58: =C49+C53 -> 357948 | D58: =D49+D53 -> 589557 | E58: =E49+E53 -> 372121 | F58: =F49+F53 -> 482054 | G58: =G49+G53 -> 466581 | H58: =H49+H53 -> 520991 | I58: =I49+I53 -> 532166 | ... M58: =M49+M53 -> 328556
A59: Debt/Assets | B59: =IFERROR(B58/B44,"-") -> 0.15956732 | C59: =IFERROR(C58/C44,"-") -> 0.093629203 | D59: =IFERROR(D58/D44,"-") -> 0.18198102 | E59: =IFERROR(E58/E44,"-") -> 0.13950115 | F59: =IFERROR(F58/F44,"-") -> 0.17847969 | G59: =IFERROR(G58/G44,"-") -> 0.18846366 | H59: =IFERROR(H58/H44,"-") -> 0.22111981 | I59: =IFERROR(I58/I44,"-") -> 0.24287563 | ... M59: =IFERROR(M58/M44,"-") -> 0.28310029
A61: Minority Interest | B61: =_xlfn.XLOOKUP($A61,Inputs!$A:$A,Inputs!B:B,,0) -> 40947 | C61: =_xlfn.XLOOKUP($A61,Inputs!$A:$A,Inputs!C:C,,0) -> 35876 | D61: =_xlfn.XLOOKUP($A61,Inputs!$A:$A,Inputs!D:D,,0) -> 30787 | E61: =_xlfn.XLOOKUP($A61,Inputs!$A:$A,Inputs!E:E,,0) -> 25736 | F61: =_xlfn.XLOOKUP($A61,Inputs!$A:$A,Inputs!F:F,,0) -> 29054 | G61: =_xlfn.XLOOKUP($A61,Inputs!$A:$A,Inputs!G:G,,0) -> 26258 | H61: =_xlfn.XLOOKUP($A61,Inputs!$A:$A,Inputs!H:H,,0) -> 22893 | I61: =_xlfn.XLOOKUP($A61,Inputs!$A:$A,Inputs!I:I,,0) -> 21942 | J61: =_xlfn.XLOOKUP($A61,Inputs!$A:$A,Inputs!J:J,,0) -> 22594 | K61: =_xlfn.XLOOKUP($A61,Inputs!$A:$A,Inputs!K:K,,0) -> 21162 | L61: =_xlfn.XLOOKUP($A61,Inputs!$A:$A,Inputs!L:L,,0) -> 16543 | M61: =_xlfn.XLOOKUP($A61,Inputs!$A:$A,Inputs!M:M,,0) -> 12110
A63: Shareholder's Equity | B63: =_xlfn.XLOOKUP($A63,Inputs!$A:$A,Inputs!B:B,,0) -> 2197201 | C63: =_xlfn.XLOOKUP($A63,Inputs!$A:$A,Inputs!C:C,,0) -> 1935397 | D63: =_xlfn.XLOOKUP($A63,Inputs!$A:$A,Inputs!D:D,,0) -> 1636921 | E63: =_xlfn.XLOOKUP($A63,Inputs!$A:$A,Inputs!E:E,,0) -> 1411119 | F63: =_xlfn.XLOOKUP($A63,Inputs!$A:$A,Inputs!F:F,,0) -> 1388741 | G63: =_xlfn.XLOOKUP($A63,Inputs!$A:$A,Inputs!G:G,,0) -> 1271805 | H63: =_xlfn.XLOOKUP($A63,Inputs!$A:$A,Inputs!H:H,,0) -> 1089823 | I63: =_xlfn.XLOOKUP($A63,Inputs!$A:$A,Inputs!I:I,,0) -> 993585 | J63: =_xlfn.XLOOKUP($A63,Inputs!$A:$A,Inputs!J:J,,0) -> 1003123 | K63: =_xlfn.XLOOKUP($A63,Inputs!$A:$A,Inputs!K:K,,0) -> 781534 | L63: =_xlfn.XLOOKUP($A63,Inputs!$A:$A,Inputs!L:L,,0) -> 602910 | M63: =_xlfn.XLOOKUP($A63,Inputs!$A:$A,Inputs!M:M,,0) -> 491701
A66: Other Data
A67: Number of employees | B67: =_xlfn.XLOOKUP($A67,Inputs!$A:$A,Inputs!B:B,,0) -> #N/A | C67: =_xlfn.XLOOKUP($A67,Inputs!$A:$A,Inputs!C:C,,0) -> #N/A | D67: =_xlfn.XLOOKUP($A67,Inputs!$A:$A,Inputs!D:D,,0) -> #N/A | E67: =_xlfn.XLOOKUP($A67,Inputs!$A:$A,Inputs!E:E,,0) -> #N/A | F67: =_xlfn.XLOOKUP($A67,Inputs!$A:$A,Inputs!F:F,,0) -> #N/A | G67: =_xlfn.XLOOKUP($A67,Inputs!$A:$A,Inputs!G:G,,0) -> #N/A | H67: =_xlfn.XLOOKUP($A67,Inputs!$A:$A,Inputs!H:H,,0) -> #N/A | I67: =_xlfn.XLOOKUP($A67,Inputs!$A:$A,Inputs!I:I,,0) -> #N/A | J67: =_xlfn.XLOOKUP($A67,Inputs!$A:$A,Inputs!J:J,,0) -> #N/A | K67: =_xlfn.XLOOKUP($A67,Inputs!$A:$A,Inputs!K:K,,0) -> #N/A | L67: =_xlfn.XLOOKUP($A67,Inputs!$A:$A,Inputs!L:L,,0) -> #N/A | M67: =_xlfn.XLOOKUP($A67,Inputs!$A:$A,Inputs!M:M,,0) -> #N/A
A68: Shares Outstanding | B68: =_xlfn.XLOOKUP($A68,Inputs!$A:$A,Inputs!B:B,,0) -> #N/A | C68: =_xlfn.XLOOKUP($A68,Inputs!$A:$A,Inputs!C:C,,0) -> #N/A | D68: =_xlfn.XLOOKUP($A68,Inputs!$A:$A,Inputs!D:D,,0) -> #N/A | E68: =_xlfn.XLOOKUP($A68,Inputs!$A:$A,Inputs!E:E,,0) -> #N/A | F68: =_xlfn.XLOOKUP($A68,Inputs!$A:$A,Inputs!F:F,,0) -> #N/A | G68: =_xlfn.XLOOKUP($A68,Inputs!$A:$A,Inputs!G:G,,0) -> #N/A | H68: =_xlfn.XLOOKUP($A68,Inputs!$A:$A,Inputs!H:H,,0) -> #N/A | I68: =_xlfn.XLOOKUP($A68,Inputs!$A:$A,Inputs!I:I,,0) -> #N/A | J68: =_xlfn.XLOOKUP($A68,Inputs!$A:$A,Inputs!J:J,,0) -> #N/A | K68: =_xlfn.XLOOKUP($A68,Inputs!$A:$A,Inputs!K:K,,0) -> #N/A | L68: =_xlfn.XLOOKUP($A68,Inputs!$A:$A,Inputs!L:L,,0) -> #N/A | M68: =_xlfn.XLOOKUP($A68,Inputs!$A:$A,Inputs!M:M,,0) -> #N/A
A69: Float | B69: =_xlfn.XLOOKUP($A69,Inputs!$A:$A,Inputs!B:B,,0) -> 0.91467577 | C69: =_xlfn.XLOOKUP($A69,Inputs!$A:$A,Inputs!C:C,,0) -> Yahoo Finance | D69: =_xlfn.XLOOKUP($A69,Inputs!$A:$A,Inputs!D:D,,0) -> 0 | E69: =_xlfn.XLOOKUP($A69,Inputs!$A:$A,Inputs!E:E,,0) -> 0 | F69: =_xlfn.XLOOKUP($A69,Inputs!$A:$A,Inputs!F:F,,0) -> 0 | G69: =_xlfn.XLOOKUP($A69,Inputs!$A:$A,Inputs!G:G,,0) -> 0 | H69: =_xlfn.XLOOKUP($A69,Inputs!$A:$A,Inputs!H:H,,0) -> 0 | I69: =_xlfn.XLOOKUP($A69,Inputs!$A:$A,Inputs!I:I,,0) -> 0 | J69: =_xlfn.XLOOKUP($A69,Inputs!$A:$A,Inputs!J:J,,0) -> 0 | K69: =_xlfn.XLOOKUP($A69,Inputs!$A:$A,Inputs!K:K,,0) -> 0 | L69: =_xlfn.XLOOKUP($A69,Inputs!$A:$A,Inputs!L:L,,0) -> 0 | M69: =_xlfn.XLOOKUP($A69,Inputs!$A:$A,Inputs!M:M,,0) -> 0
A70: Insiders Own | B70: =_xlfn.XLOOKUP($A70,Inputs!$A:$A,Inputs!B:B,,0) -> 0 | C70: =_xlfn.XLOOKUP($A70,Inputs!$A:$A,Inputs!C:C,,0) -> Yahoo Finance | D70: =_xlfn.XLOOKUP($A70,Inputs!$A:$A,Inputs!D:D,,0) -> 0 | E70: =_xlfn.XLOOKUP($A70,Inputs!$A:$A,Inputs!E:E,,0) -> 0 | F70: =_xlfn.XLOOKUP($A70,Inputs!$A:$A,Inputs!F:F,,0) -> 0 | G70: =_xlfn.XLOOKUP($A70,Inputs!$A:$A,Inputs!G:G,,0) -> 0 | H70: =_xlfn.XLOOKUP($A70,Inputs!$A:$A,Inputs!H:H,,0) -> 0 | I70: =_xlfn.XLOOKUP($A70,Inputs!$A:$A,Inputs!I:I,,0) -> 0 | J70: =_xlfn.XLOOKUP($A70,Inputs!$A:$A,Inputs!J:J,,0) -> 0 | K70: =_xlfn.XLOOKUP($A70,Inputs!$A:$A,Inputs!K:K,,0) -> 0 | L70: =_xlfn.XLOOKUP($A70,Inputs!$A:$A,Inputs!L:L,,0) -> 0 | M70: =_xlfn.XLOOKUP($A70,Inputs!$A:$A,Inputs!M:M,,0) -> 0
A71: Fitch/ S&P Rating | B71: =_xlfn.XLOOKUP($A71,Inputs!$A:$A,Inputs!B:B,,0) -> A2 | C71: =_xlfn.XLOOKUP($A71,Inputs!$A:$A,Inputs!C:C,,0) -> 10-K | D71: =_xlfn.XLOOKUP($A71,Inputs!$A:$A,Inputs!D:D,,0) -> 0 | E71: =_xlfn.XLOOKUP($A71,Inputs!$A:$A,Inputs!E:E,,0) -> 0 | F71: =_xlfn.XLOOKUP($A71,Inputs!$A:$A,Inputs!F:F,,0) -> 0 | G71: =_xlfn.XLOOKUP($A71,Inputs!$A:$A,Inputs!G:G,,0) -> 0 | H71: =_xlfn.XLOOKUP($A71,Inputs!$A:$A,Inputs!H:H,,0) -> 0 | I71: =_xlfn.XLOOKUP($A71,Inputs!$A:$A,Inputs!I:I,,0) -> 0 | J71: =_xlfn.XLOOKUP($A71,Inputs!$A:$A,Inputs!J:J,,0) -> 0 | K71: =_xlfn.XLOOKUP($A71,Inputs!$A:$A,Inputs!K:K,,0) -> 0 | L71: =_xlfn.XLOOKUP($A71,Inputs!$A:$A,Inputs!L:L,,0) -> 0 | M71: =_xlfn.XLOOKUP($A71,Inputs!$A:$A,Inputs!M:M,,0) -> 0
A72: Dividend Yield | B72: =_xlfn.XLOOKUP($A72,Inputs!$A:$A,Inputs!B:B,,0) -> #N/A | C72: =_xlfn.XLOOKUP($A72,Inputs!$A:$A,Inputs!C:C,,0) -> #N/A | D72: =_xlfn.XLOOKUP($A72,Inputs!$A:$A,Inputs!D:D,,0) -> #N/A | E72: =_xlfn.XLOOKUP($A72,Inputs!$A:$A,Inputs!E:E,,0) -> #N/A | F72: =_xlfn.XLOOKUP($A72,Inputs!$A:$A,Inputs!F:F,,0) -> #N/A | G72: =_xlfn.XLOOKUP($A72,Inputs!$A:$A,Inputs!G:G,,0) -> #N/A | H72: =_xlfn.XLOOKUP($A72,Inputs!$A:$A,Inputs!H:H,,0) -> #N/A | I72: =_xlfn.XLOOKUP($A72,Inputs!$A:$A,Inputs!I:I,,0) -> #N/A | J72: =_xlfn.XLOOKUP($A72,Inputs!$A:$A,Inputs!J:J,,0) -> #N/A | K72: =_xlfn.XLOOKUP($A72,Inputs!$A:$A,Inputs!K:K,,0) -> #N/A | L72: =_xlfn.XLOOKUP($A72,Inputs!$A:$A,Inputs!L:L,,0) -> #N/A | M72: =_xlfn.XLOOKUP($A72,Inputs!$A:$A,Inputs!M:M,,0) -> #N/A
A73: Daily Volume in Millions of USD | B73: =_xlfn.XLOOKUP($A73,Inputs!$A:$A,Inputs!B:B,,0) -> 3.238 | C73: =_xlfn.XLOOKUP($A73,Inputs!$A:$A,Inputs!C:C,,0) -> Yahoo Finance | D73: =_xlfn.XLOOKUP($A73,Inputs!$A:$A,Inputs!D:D,,0) -> 0 | E73: =_xlfn.XLOOKUP($A73,Inputs!$A:$A,Inputs!E:E,,0) -> 0 | F73: =_xlfn.XLOOKUP($A73,Inputs!$A:$A,Inputs!F:F,,0) -> 0 | G73: =_xlfn.XLOOKUP($A73,Inputs!$A:$A,Inputs!G:G,,0) -> 0 | H73: =_xlfn.XLOOKUP($A73,Inputs!$A:$A,Inputs!H:H,,0) -> 0 | I73: =_xlfn.XLOOKUP($A73,Inputs!$A:$A,Inputs!I:I,,0) -> 0 | J73: =_xlfn.XLOOKUP($A73,Inputs!$A:$A,Inputs!J:J,,0) -> 0 | K73: =_xlfn.XLOOKUP($A73,Inputs!$A:$A,Inputs!K:K,,0) -> 0 | L73: =_xlfn.XLOOKUP($A73,Inputs!$A:$A,Inputs!L:L,,0) -> 0 | M73: =_xlfn.XLOOKUP($A73,Inputs!$A:$A,Inputs!M:M,,0) -> 0
B75: 2020 | C75: 2021 | D75: 2022
A76: Short % of Float | B76: 0 | C76: 0 | D76: 0
A77: EPS | B77: 0 | C77: 0 | D77: 0
A79: Corporate Bonds 3, 5 Y 10 | B79: Average Price | C79: Moody's | D79: YTM | E79: DIVISA
B80: =VLOOKUP($A80,Inputs!$A$5:$M$98,MATCH(B$4,Inputs!$B$5:$M$5,0)+1,FALSE) -> #N/A | C80: =VLOOKUP($A80,Inputs!$A$5:$M$98,MATCH(C$4,Inputs!$B$5:$M$5,0)+1,FALSE) -> #N/A | D80: =VLOOKUP($A80,Inputs!$A$5:$M$98,MATCH(D$4,Inputs!$B$5:$M$5,0)+1,FALSE) -> #N/A | E80: =VLOOKUP($A80,Inputs!$A$5:$M$98,MATCH(E$4,Inputs!$B$5:$M$5,0)+1,FALSE) -> #N/A

Sheet Inputs
G2: Figures in Millions of JPY
G3: Company | H3: Daikin Industries,Ltd. (6367.T)
D4: Report in millions
A5: RESULTS | B5: =OP!J17 -> 2022 | C5: 2021 | D5: =C5-1 -> 2020 | E5: =D5-1 -> 2019 | F5: =E5-1 -> 2018 | G5: =F5-1 -> 2017 | H5: =G5-1 -> 2016 | I5: =H5-1 -> 2015 | J5: =I5-1 -> 2014 | K5: =J5-1 -> 2013 | ... M5: =L5-1 -> 2011 | Q5: Hoja | R5: Nombre campo Bloomberg | T5: Cambio de signo | Z5: 2016 | AA5: 2015 | AB5: 2014 | AC5: 2013 | AD5: 2012 | AE5: 2011 | AF5: 2010 | AG5: 2009
A6: Net Sales | B6: 3981578 | C6: 3109106 | D6: 2493386 | E6: 2550305 | F6: 2481109 | G6: 2290560 | H6: 2043968 | I6: 2043691 | J6: 1915013 | K6: 1787679 | L6: 1290903 | M6: 1218700 | N6: Income Statement | O6: Sales | Q6: Ingreso | R6: Ingreso | Z6: 38537 | AA6: 47011 | AB6: 55184 | AC6: 55656 | AD6: 65875 | AE6: 60138 | AF6: 42588 | AG6: 32396 | AY6: 1160330
A7: Gross Profit | B7: 1331476 | C7: 1057339 | D7: 864136 | E7: 884898 | F7: 868923 | G7: 798829 | H7: 730935 | I7: 711576 | J7: 649901 | K7: 568323 | L7: 388047 | M7: 371901 | N7: Income Statement | O7: =+A7 -> Gross Profit | Q7: Ingreso | R7: + Coste de bienes y servicios | Z7: =Z6-28044 -> 10493 | AA7: =AA6-33546 -> 13465 | AB7: =AB6-40718 -> 14466 | AC7: =AC6-40727 -> 14929 | AD7: =+AD6-47055 -> 18820 | AE7: =+AE6-43578 -> 16560 | AF7: =+AF6-30367 -> 12221 | AG7: =+AG6-23886 -> 8510 | AY7: 361664
A8: Operating Income | B8: 364893 | C8: 311302 | D8: 237927 | E8: 241654 | F8: 275259 | G8: 250816 | H8: 230813 | I8: 215486 | J8: 185291 | K8: 155203 | L8: 75352 | M8: 78998 | N8: Income Statement | O8: Operating Income | Q8: Ingreso | R8: + Ventas, generales y admin | Z8: =Z7-4383 -> 6110 | AA8: =AA7-4951 -> 8514 | AB8: =AB7-6529 -> 7937 | AC8: =AC7-5547 -> 9382 | AD8: =AD7-5919-2466-797-580-485 -> 8573 | AE8: =+AE7-5203-2297-826-1081 -> 7153 | AF8: =+AF7-4248-1905-914-1191 -> 3963 | AG8: =+AG7-3645-1421-1045-1822 -> 577 | AY8: 47690
A9: Other Expenses (Revenues) | B9: =-17461+26994 -> 9533 | C9: =-6738+16570 -> 9832 | D9: -8652 | E9: =-5480+16579 -> 11099 | F9: -4272 | G9: =-6579+5562 -> -1017 | H9: =-7062+4050 -> -3012 | I9: =-5383+-7499 -> -12882 | J9: =-5301+10747 -> 5446 | K9: =-5669+4341 -> -1328 | L9: =-3068+9680 -> 6612 | M9: =-4992+6280 -> 1288 | N9: Income Statement | O9: investment income+other income expense+income loss+minority interest+non controlling interest+share onf net profit+gain8losses) on equity investments+share of result from associates nd joint ventures+non operating profit+ | Q9: Ingreso | R9: + Investigación y desarrollo | S9: + Coste de financiación de beneficio | T9: + Otro gasto operativo | U9: - Beneficio (pérdida) de filiales | V9: - Minoritarios | Z9: =1853+596+595+1904+6+8 -> 4962 | AA9: =2119+587+2023+11 -> 4740 | AB9: =2380+624+1619-8+16 -> 4631 | AC9: =2046+727+981+6+14 -> 3774 | AD9: =-14+41 -> 27 | AE9: 53 | AF9: =58+24 -> 82 | AG9: =12-68 -> -56 | AY9: 1404
A10: Net Financial Cost | B10: -8730 | C10: -638 | D10: =-2309+5081 -> 2772 | E10: -3039 | F10: =-4732+2439 -> -2293 | G10: -3838 | H10: -3174 | I10: -1526 | J10: -3097 | K10: -5129 | L10: -4043 | M10: -3165 | N10: Income Statement | O10: interest expense+financial income and expenses+other financial expense-income+interest and other net+ | Q10: Ingreso | R10: - Ingreso (pérdida) no operacional | Z10: =505+518 -> 1023 | AA10: =507-161 -> 346 | AB10: =484-322 -> 162 | AC10: =465+35 -> 500 | AD10: =467-130 -> 337 | AE10: =396+32 -> 428 | AF10: =343-130 -> 213 | AG10: =389-381 -> 8 | AY10: -2727
A11: Taxes | B11: -107941 | C11: -102786 | D11: -75797 | E11: -78982 | F11: -79645 | G11: -56908 | H11: -70688 | I11: -64090 | J11: -67965 | K11: -55959 | L11: -34336 | M11: -35948 | N11: Income Statement | O11: Taxes | Q11: Ingreso | R11: - Gasto de impuesto a la renta (Beneficio) | Z11: 192 | AA11: 916 | AB11: 692 | AC11: 1319 | AD11: =2528 -> 2528 | AE11: =1720 -> 1720 | AF11: =968 -> 968 | AG11: =-270 -> -270 | AJ11: -8726 | AK11: 1189 | AL11: -834 | AM11: 781 | AN11: 3153 | AO11: -220 | AP11: -605 | AQ11: 800 | AR11: 4 | AS11: -124 | AT11: -1 | AU11: -1115 | AV11: 1404 | AY11: 22067
A12: Net Income | B12: 257755 | C12: 217710 | D12: 156250 | E12: 170732 | F12: 189049 | G12: 189053 | H12: 153939 | I12: 136988 | J12: 119675 | K12: 92787 | L12: 43585 | M12: 41173 | N12: Income Statement | O12: Net Income | Q12: Flujo de caja | R12: + Ingreso neto | Z12: -67 | AA12: 2512 | AB12: 2452 | AC12: 3789 | AD12: 5681 | AE12: =4928+24 -> 4952 | AF12: 2700 | AG12: 895 | AJ12: -1047 | AK12: -367 | AL12: -1322 | AM12: 205 | AN12: -809 | AO12: -463 | AP12: -475 | AQ12: -1078 | AR12: -437 | AS12: -176 | AT12: 489 | AU12: -430 | AV12: -656 | AY12: 19876
B13: =SUM(B8:B11) -> 257755 | C13: =SUM(C8:C11) -> 217710 | D13: =SUM(D8:D11) -> 156250 | E13: =SUM(E8:E11) -> 170732 | F13: =SUM(F8:F11) -> 189049 | G13: =SUM(G8:G11) -> 189053 | H13: =SUM(H8:H11) -> 153939 | I13: =SUM(I8:I11) -> 136988 | ... M13: =SUM(M8:M11) -> 41173 | Z13: =Z8-Z10-Z9-Z11 -> -67 | AA13: =AA8-AA10-AA9-AA11 -> 2512 | AB13: =AB8-AB10-AB9-AB11 -> 2452 | AC13: =AC8-AC10-AC9-AC11 -> 3789 | AD13: =AD8-AD10-AD9-AD11 -> 5681 | AE13: =AE8-AE10-AE9-AE11 -> 4952 | AF13: =AF8-AF10-AF9-AF11 -> 2700 | AG13: =AG8-AG10-AG9-AG11 -> 895 | AJ13: -7688 | AK13: -7560 | AL13: -6496 | AM13: -6466 | AN13: -6616 | AO13: -5896 | AP13: -5982 | AQ13: -5105 | AR13: -4868 | AS13: -5369 | AT13: -3556 | AU13: -3447 | AV13: -3768 | AY13: =SUM(AY8:AY11) -> 68434
A14: FINANCIAL POSITION | B14: =B12-B13 -> 0 | C14: =C12-C13 -> 0 | D14: =D12-D13 -> 0 | E14: =E12-E13 -> 0 | F14: =F12-F13 -> 0 | G14: =G12-G13 -> 0 | H14: =H12-H13 -> 0 | I14: =I12-I13 -> 0 | ... M14: =M12-M13 -> 0 | X14: Interest Expense | Z14: =Z12-Z13 -> 0 | AA14: =AA12-AA13 -> 0 | AB14: =AB12-AB13 -> 0 | AC14: =AC12-AC13 -> 0 | AD14: =AD12-AD13 -> 0 | AE14: =AE12-AE13 -> 0 | AF14: =AF12-AF13 -> 0 | AG14: =AG12-AG13 -> 0 | AJ14: =SUM(AJ11:AJ13) -> -17461 | AK14: =SUM(AK11:AK13) -> -6738 | AL14: =SUM(AL11:AL13) -> -8652 | AM14: =SUM(AM11:AM13) -> -5480 | AN14: =SUM(AN11:AN13) -> -4272 | AO14: =SUM(AO11:AO13) -> -6579 | AP14: =SUM(AP11:AP13) -> -7062 | AQ14: =SUM(AQ11:AQ13) -> -5383 | ... AV14: =SUM(AV11:AV13) -> -3020 | AY14: =AY12-AY13 -> -48558
X15: Financial Income and Expenses
A16: Weighted Average Shares (Basic NI) | B16: 293 | C16: 293 | D16: 293 | E16: 293 | F16: 292 | G16: 292 | H16: 292 | I16: 292 | J16: 292 | K16: 291 | L16: 291 | M16: 291 | X16: Other Financial Expense | AY16: 292
A17: Weighted Average Shares (Diluted NI) | B17: 293 | C17: 293 | D17: 393 | E17: 293 | F17: 293 | G17: 293 | H17: 292 | I17: 292 | J17: 292 | K17: 292 | L17: 291 | M17: 291 | X17: Income | AY17: 292
X18: Interest and other Net
A19: Net gains (losses) from ForEx | B19: 103267 | C19: 143222 | D19: 75637 | E19: -69586 | F19: -8109 | G19: 11672 | H19: -32609 | I19: -86963 | J19: 93434 | K19: 59499 | L19: 64782 | M19: -12968
A20: Total Comprehensive Income | B20: 354228 | C20: 366141 | D20: 284851 | E20: 73322 | F20: 169829 | G20: 230616 | H20: 136343 | I20: 25590 | J20: 248650 | K20: 183328 | L20: 131768 | M20: 26949 | X20: Investement Income
X21: Other Income Expense
A22: Changes Net Working Capital | B22: =B23-C23 -> 318333 | C22: =C23-D23 -> -189514 | D22: =D23-E23 -> -8398 | E22: =E23-F23 -> 58668 | F22: =F23-G23 -> -63926 | G22: =G23-H23 -> 55820 | H22: =H23-I23 -> -22721 | I22: =I23-J23 -> -58205 | ... M22: =M23-N23 -> 97060 | N22: cash flows | O22: NWC | Q22: Flujo de caja | X22: Income Loss | AY22: =AY23-AZ23 -> 103585
A23: Net Working Capital | B23: =B27-B42-B28 -> 360098 | C23: =C27-C42-C28 -> 41765 | D23: =D27-D42-D28 -> 231279 | E23: =E27-E42-E28 -> 239677 | F23: =F27-F42-F28 -> 181009 | G23: =G27-G42-G28 -> 244935 | H23: =H27-H42-H28 -> 189115 | I23: =I27-I42-I28 -> 211836 | ... M23: =M27-M42-M28 -> 97060 | X23: Minority Interest | AY23: =AY27-AY42-AY28 -> 103585
A24: 2625 | C24: 2625 | D24: 2625 | E24: 2625 | F24: 2625 | G24: 2625 | H24: 2625 | I24: 2625 | J24: 2625 | K24: 2625 | L24: 2625 | M24: 2625 | N24: 2625 | Q24: Flujo de caja | R24: + Dividendos pagados | T24: Cambiar signo | X24: Non Controlling Interest | Z24: 1799 | AA24: 1757 | AB24: 1620 | AC24: 1111 | AD24: 1617 | AE24: 1159 | AF24: 1084 | AG24: 1029 | AY24: 2625
A25: BALANCE SHEET | C25: 2625 | D25: 2625 | E25: 2625 | F25: 2625 | G25: 2625 | H25: 2625 | I25: 2625 | J25: 2625 | K25: 2625 | L25: 2625 | M25: 2625 | N25: 2625 | Q25: Flujo de caja | R25: + Aumento en capital | S25: + Baja en capital | T25: Cambiar signo y hacer suma | X25: Share of Net Profit | Z25: 23 | AA25: =-33+2025 -> 1992 | AB25: 3817 | AC25: 1776 | AD25: -244 | AE25: -312 | AF25: -449 | AG25: -110 | AY25: 2625
A26: ASSETS | N26: 1922 | O26: 2625 | X26: Gain and Loss on Equity Investements
A27: Current | B27: 2427082 | C27: 2165623 | D27: 1733361 | E27: 1304427 | F27: 1317605 | G27: 1205293 | H27: 1159884 | I27: 1066768 | J27: 1082614 | K27: 967211 | L27: 803326 | M27: 629047 | X27: Share of Result from Associates and Joint Ventures | AY27: 599110
A28: Cash & Eq. | B28: 617663 | C28: 817619 | D28: 736098 | E28: 370793 | F28: 367781 | G28: 357027 | H28: 344093 | I28: 291205 | J28: 286949 | K28: 257295 | L28: 185571 | M28: 135648 | N28: Balance Sheet | O28: Cash & Eq. | X28: Non Operating Profit | AY28: 167718
A29: Accounts Receivable | B29: 687135 | C29: 578148 | D29: 455256 | E29: 430194 | F29: 438684 | G29: 392331 | H29: 360845 | I29: 349367 | J29: 347584 | K29: 310986 | L29: 257096 | M29: 204269 | N29: Balance Sheet | O29: Accounts Receivable | AY29: 193968
A30: Inventory | B30: 993383 | C30: 671461 | D30: 469396 | E30: 433782 | F30: 436356 | G30: 387225 | H30: 358301 | I30: 333650 | J30: 354158 | K30: 317559 | L30: 285167 | M30: 243598 | N30: Balance Sheet | O30: Inventory | Q30: Balance | R30: + Efectivo, equivalentes y STI | Z30: 7168 | AA30: 6460 | AB30: 7341 | AC30: 6081 | AD30: 5490 | AE30: 3057 | AF30: 3592 | AG30: 4867 | AY30: 201771
A31: Other Current Assets | B31: =B27-SUM(B28:B30) -> 128901 | C31: =C27-SUM(C28:C30) -> 98395 | D31: =D27-SUM(D28:D30) -> 72611 | E31: =E27-SUM(E28:E30) -> 69658 | F31: =F27-SUM(F28:F30) -> 74784 | G31: =G27-SUM(G28:G30) -> 68710 | H31: =H27-SUM(H28:H30) -> 96645 | I31: =I27-SUM(I28:I30) -> 92546 | ... M31: =M27-SUM(M28:M30) -> 45532 | N31: Balance Sheet | O31: Inventory | Q31: Balance | R31: + Cuentas y notas por cobrar | S31: + Activos derivados y de cobertura | T31: + Inversiones y cuentas por cobrar a LP | Z31: =5981+8522+1029+13556 -> 29088 | AA31: =6695+8991+1170+13651 -> 30507 | AB31: =7737+9027+1364+14644 -> 32772 | AC31: 33499 | AD31: 33911 | AE31: 31031 | AF31: 28849 | AG31: 27162 | AY31: =AY27-SUM(AY28:AY30) -> 35653
A32: Non-current | B32: =B38-B27 -> 1876600 | C32: =C38-C27 -> 1657415 | D32: =D38-D27 -> 1506301 | E32: =E38-E27 -> 1363085 | F32: =F38-F27 -> 1383285 | G32: =G38-G27 -> 1270415 | H32: =H38-H27 -> 1196264 | I32: =I38-I27 -> 1124337 | ... M32: =M38-M27 -> 531517 | AY32: =AY38-AY27 -> 533388
A33: Property, Plant and Equipment | B33: 900944 | C33: 743364 | D33: 647410 | E33: 579980 | F33: 482962 | G33: 454834 | H33: 424527 | I33: 385099 | J33: 347755 | K33: 299716 | L33: 274201 | M33: 224357 | Q33: Balance | R33: + Inventarios | Z33: 8614 | AA33: 9700 | AB33: 12205 | AC33: 12625 | AD33: 15547 | AE33: 14544 | AF33: 9587 | AG33: 6360 | AJ33: 270467 | AK33: 268684 | AL33: 281969 | AM33: 322318 | AN33: 309282 | AO33: 330876 | AP33: 329753 | AQ33: 369964 | AR33: 361667 | AS33: 348411 | AT33: 166276 | AU33: 170561 | AY33: 214005
A34: Operating leases | B34: 0 | C34: 0 | D34: 0 | E34: 8888 | F34: 89052 | G34: 66162 | H34: 56810 | I34: 45763 | J34: 38648 | K34: 34415 | L34: 30680 | M34: 19283 | AJ34: 306540 | AK34: 274077 | AL34: 260687 | AM34: 295822 | AN34: 206777 | AO34: 206087 | AP34: 189108 | AQ34: 206760 | AR34: 184089 | AS34: 162477 | AT34: 14210 | AU34: 8466 | AY34: 179027
A35: Equity Method Investments | B35: 186861 | C35: 216268 | D35: 230206 | E35: 174264 | F35: 222799 | G35: 244969 | H35: 197999 | I35: 189587 | J35: 220735 | K35: 158550 | L35: 117118 | M35: 98969 | AJ35: =AJ34+AJ33 -> 577007 | AK35: =AK34+AK33 -> 542761 | AL35: =AL34+AL33 -> 542656 | AM35: =AM34+AM33 -> 618140 | AN35: =AN34+AN33 -> 516059 | AO35: =AO34+AO33 -> 536963 | AP35: =AP34+AP33 -> 518861 | AQ35: =AQ34+AQ33 -> 576724 | ... AU35: =AU34+AU33 -> 179027 | AY35: 105897
A36: Other Non-Current Assets | B36: =B32-SUM(B33:B35) -> 788795 | C36: =C32-SUM(C33:C35) -> 697783 | D36: =D32-SUM(D33:D35) -> 628685 | E36: =E32-SUM(E33:E35) -> 599953 | F36: =F32-SUM(F33:F35) -> 588472 | G36: =G32-SUM(G33:G35) -> 504450 | H36: =H32-SUM(H33:H35) -> 516928 | I36: =I32-SUM(I33:I35) -> 503888 | ... M36: =M32-SUM(M33:M35) -> 188908 | N36: Balance Sheet | O36: Property, Plant and Equipment | AY36: =AY32-SUM(AY33:AY35) -> 34459
A37: Other Assets | B37: =B31+B36 -> 917696 | C37: =C31+C36 -> 796178 | D37: =D31+D36 -> 701296 | E37: =E31+E36 -> 669611 | F37: =F31+F36 -> 663256 | G37: =G31+G36 -> 573160 | H37: =H31+H36 -> 613573 | I37: =I31+I36 -> 596434 | ... M37: =M31+M36 -> 234440 | N37: Balance Sheet | AY37: =AY31+AY36 -> 70112
A38: Total Assets | B38: 4303682 | C38: 3823038 | D38: 3239662 | E38: 2667512 | F38: 2700890 | G38: 2475708 | H38: 2356148 | I38: 2191105 | J38: 2263989 | K38: 2011870 | L38: 1735836 | M38: 1160564 | N38: Balance Sheet | O38: Total Assets | Q38: Balance | R38: + Propiedad, planta y equipo; neto | Z38: 15322 | AA38: 16090 | AB38: =16577 -> 16577 | AC38: 17075 | AD38: 16461 | AE38: 14395 | AF38: 12539 | AG38: 12386 | AJ38: 97376 | AK38: 40754 | AL38: 48937 | AM38: 146066 | AN38: 45530 | AO38: 57699 | AP38: 54675 | AQ38: 57897 | AR38: 43325 | AS38: 65334 | AT38: 90448 | AU38: 73977 | AY38: 1132498
N39: Balance Sheet | Z39: =Z40-SUM(Z30:Z38) -> 14512 | AA39: =AA40-SUM(AA30:AA38) -> 15585 | AB39: =AB40-SUM(AB30:AB38) -> 15786 | AC39: =AC40-SUM(AC30:AC38) -> 15616 | AD39: =AD40-SUM(AD30:AD38) -> 17947 | AE39: =AE40-SUM(AE30:AE38) -> 18419 | AF39: =AF40-SUM(AF30:AF38) -> 9453 | AG39: =AG40-SUM(AG30:AG38) -> 9263 | AJ39: 390415 | AK39: 96917 | AL39: 123200 | AM39: 93626 | AN39: 78487 | AO39: 78974 | AP39: 74882 | AQ39: 40923 | AR39: 95885 | AS39: 5589 | AT39: 59330 | AU39: 3690
N40: Balance Sheet | Q40: Balance | R40: Activos totales | Z40: 74704 | AA40: 78342 | AB40: 84681 | AC40: 84896 | AD40: 89356 | AE40: 81446 | AF40: 64020 | AG40: 60038 | AJ40: =AJ39+AJ38 -> 487791 | AK40: =AK39+AK38 -> 137671 | AL40: =AL39+AL38 -> 172137 | AM40: =AM39+AM38 -> 239692 | AN40: =AN39+AN38 -> 124017 | AO40: =AO39+AO38 -> 136673 | AP40: =AP39+AP38 -> 129557 | AQ40: =AQ39+AQ38 -> 98820 | ... AU40: =AU39+AU38 -> 77667
A41: LIABILITIES | N41: Balance Sheet
A42: Current Liabilities | B42: 1449321 | C42: 1306239 | D42: 765984 | E42: 693957 | F42: 768815 | G42: 603331 | H42: 626676 | I42: 563727 | J42: 525624 | K42: 533467 | L42: 382627 | M42: 396339 | N42: Balance Sheet | O42: Current Liabilities | AY42: 327807
A43: Payables | B43: 352647 | C43: 302621 | D43: 229746 | E43: 189843 | F43: 204535 | G43: 183991 | H43: 173147 | I43: 156038 | J43: 153937 | K43: 162084 | L43: 127364 | M43: 110108 | AJ43: 1189 | AK43: -834 | AL43: 781 | AM43: 3153 | AN43: -220 | AO43: -605 | AP43: 800 | AQ43: 4 | AR43: -124 | AS43: -1 | AT43: -1115 | AU43: 1404 | AY43: 116905
A44: Short-Term Debt | B44: 372541 | C44: 97376 | D44: 40754 | E44: 48937 | F44: 146066 | G44: 45530 | H44: 57699 | I44: 54675 | J44: 57897 | K44: 43325 | L44: 65334 | M44: 90448 | N44: Balance Sheet | O44: Short term Debt | Q44: Balance | R44: Pasivos totales corrientes | Z44: 26132 | AA44: 26242 | AB44: 27877 | AC44: 27297 | AD44: 29415 | AE44: =93+3895+8161+3386+2410+2691+298+1967+558+5102 -> 28561 | AF44: =204+3852+5856+2880+1670+1831+281+1521+495+3430 -> 22020 | AG44: =433+3650+2993+3351+797+1217+262+888+302+5399 -> 19292 | AJ44: -367 | AK44: -1322 | AL44: 205 | AM44: -809 | AN44: -463 | AO44: -475 | AP44: -1078 | AQ44: -437 | AR44: -176 | AS44: 489 | AT44: -430 | AU44: -656 | AY44: 77667
A45: Short-Term Leases | B45: 30442 | C45: 25876 | D45: 20639 | E45: 17300 | F45: 1241 | G45: 1499 | H45: 1797 | I45: 1943 | J45: 1913 | K45: 1731 | L45: 1464 | M45: 2042 | AJ45: =AJ44+AJ43 -> 822 | AK45: =AK44+AK43 -> -2156 | AL45: =AL44+AL43 -> 986 | AM45: =AM44+AM43 -> 2344 | AN45: =AN44+AN43 -> -683 | AO45: =AO44+AO43 -> -1080 | AP45: =AP44+AP43 -> -278 | AQ45: =AQ44+AQ43 -> -433 | ... AU45: =AU44+AU43 -> 748 | AY45: 50354
A46: Other current liabilities | B46: =B42-SUM(B43:B45) -> 693691 | C46: =C42-SUM(C43:C45) -> 880366 | D46: =D42-SUM(D43:D45) -> 474845 | E46: =E42-SUM(E43:E45) -> 437877 | F46: =F42-SUM(F43:F45) -> 416973 | G46: =G42-SUM(G43:G45) -> 372311 | H46: =H42-SUM(H43:H45) -> 394033 | I46: =I42-SUM(I43:I45) -> 351071 | ... M46: =M42-SUM(M43:M45) -> 193741 | N46: Balance Sheet | R46: + Préstamos CP | Z46: 7303 | AA46: 6967 | AB46: 4708 | AC46: 3679 | AD46: 5287 | AE46: 5660 | AF46: 3925 | AG46: 5701 | AY46: =AY42-SUM(AY43:AY45) -> 82881
A47: Non-current Liabilities | B47: =B51-B42 -> 616213 | C47: =C51-C42 -> 545526 | D47: =D51-D42 -> 805970 | E47: =E51-E42 -> 536700 | F47: =F51-F42 -> 514280 | G47: =G51-G42 -> 574314 | H47: =H51-H42 -> 616756 | I47: =I51-I42 -> 611851 | ... M47: =M51-M42 -> 260414 | N47: Balance Sheet | O47: Total non current liabilities | AY47: =AY51-AY42 -> -765984
A48: Long-Term Debt | B48: 314186 | C48: 260572 | D48: 548803 | E48: 323184 | F48: 335988 | G48: 421051 | H48: 463292 | I48: 477491 | J48: 560874 | K48: 550475 | L48: 633033 | M48: 238108 | N48: Balance Sheet | O48: Long term debt | Z48: =Z44-Z46 -> 18829 | AA48: =AA44-AA46 -> 19275 | AB48: =AB44-AB46 -> 23169 | AC48: =AC44-AC46 -> 23618 | AD48: =AD44-AD46 -> 24128 | AE48: =AE44-AE46 -> 22901 | AF48: =AF44-AF46 -> 18095 | AG48: =AG44-AG46 -> 13591 | AY48: 294812
A49: Long-Term Leases | B49: 96597 | C49: 76508 | D49: 64736 | E49: 58482 | F49: 9959 | G49: 9301 | H49: 9462 | I49: 1929 | J49: 2717 | K49: 0 | L49: 1912 | M49: 2002 | Q49: Balance | R49: Pasivos totales no corrientes | Z49: =61491-Z44 -> 35359 | AA49: =63457-AA44 -> 37215 | AB49: =67855-AB44 -> 39978 | AC49: 36721 | AD49: 41973 | AE49: =8415+16529+10956+3583 -> 39483 | AF49: =4505+15932+7584+2654 -> 30675 | AG49: =5652+16195+7420+2179 -> 31446 | AY49: 2459
A50: Other non-current liabilities | B50: =B47-SUM(B48:B49) -> 205430 | C50: =C47-SUM(C48:C49) -> 208446 | D50: =D47-SUM(D48:D49) -> 192431 | E50: =E47-SUM(E48:E49) -> 155034 | F50: =F47-SUM(F48:F49) -> 168333 | G50: =G47-SUM(G48:G49) -> 143962 | H50: =H47-SUM(H48:H49) -> 144002 | I50: =I47-SUM(I48:I49) -> 132431 | ... M50: =M47-SUM(M48:M49) -> 20304 | N50: Balance Sheet | O50: Other non current Liabilities | R50: + Préstamos a largo plazo | Z50: 22818 | AA50: 25169 | AB50: 27784 | AC50: 26719 | AD50: 27752 | AE50: 24944 | AF50: 20437 | AG50: 21847 | AY50: =AY47-SUM(AY48:AY49) -> 0
A51: Total Liabilities | B51: 2065534 | C51: 1851765 | D51: 1571954 | E51: 1230657 | F51: 1283095 | G51: 1177645 | H51: 1243432 | I51: 1175578 | J51: 1238272 | K51: 1209174 | L51: 1116383 | M51: 656753 | N51: Balance Sheet | O51: Total Liabilities | AY51: =AY47+AY42 -> 327807
N52: Balance Sheet | Z52: =Z49-Z50 -> 12541 | AA52: =AA49-AA50 -> 12046 | AB52: =AB49-AB50 -> 12194 | AC52: =AC49-AC50 -> 10002 | AD52: =AD49-AD50 -> 14221 | AE52: =AE49-AE50 -> 14539 | AF52: =AF49-AF50 -> 10238 | AG52: =AG49-AG50 -> 9599
N53: Balance Sheet | Z53: =+Z49+Z44 -> 61491 | AA53: =+AA49+AA44 -> 63457 | AB53: =+AB49+AB44 -> 67855 | AC53: =AC44+AC49 -> 64018 | AD53: =AD49+AD44 -> 71388 | AE53: =AE49+AE44 -> 68044 | AF53: =AF49+AF44 -> 52695 | AG53: =AG49+AG44 -> 50738
A54: Minority Interest | B54: 40947 | C54: 35876 | D54: 30787 | E54: 25736 | F54: 29054 | G54: 26258 | H54: 22893 | I54: 21942 | J54: 22594 | K54: 21162 | L54: 16543 | M54: 12110 | N54: Balance Sheet | O54: Minority Interest | AY54: 11759
N55: Balance Sheet
A56: Shareholder's Equity | B56: =B38-B51-B54 -> 2197201 | C56: =C38-C51-C54 -> 1935397 | D56: =D38-D51-D54 -> 1636921 | E56: =E38-E51-E54 -> 1411119 | F56: =F38-F51-F54 -> 1388741 | G56: =G38-G51-G54 -> 1271805 | H56: =H38-H51-H54 -> 1089823 | I56: =I38-I51-I54 -> 993585 | ... M56: =M38-M51-M54 -> 491701 | N56: Balance Sheet | Q56: Balance | R56: + Participación minoritaria/no dominante | AY56: =AY38-AY51-AY54 -> 804691
A58: CASH FLOW
A59: Operating CF | B59: 158326 | C59: 243485 | D59: 374633 | E59: 302112 | F59: 249943 | G59: 223738 | H59: 267662 | I59: 226184 | J59: 160223 | K59: 179911 | L59: 105268 | M59: 36816 | AI59: -4656 | AJ59: 1215 | AK59: 13046 | AL59: -647 | AM59: -2730 | AN59: 1079 | AO59: -249 | AP59: 490 | AQ59: -1698 | AR59: 14053 | AS59: -3157 | AT59: 28509 | AY59: 78408
A60: Net Income | B60: 373384 | C60: 328056 | D60: 238543 | E60: 256180 | F60: 275310 | G60: 251857 | H60: 230609 | I60: 206183 | J60: 192508 | K60: 154115 | L60: 81477 | M60: 80568 | AI60: -227977 | AJ60: 1282 | AK60: -95599 | AL60: -124035 | AM60: -120222 | AN60: -49055 | AO60: -63952 | AP60: -110541 | AQ60: -51406 | AR60: -41785 | AS60: -91120 | AT60: -47520 | AY60: 45708
A61: Depreciation & Amortization | B61: 182224 | C61: 148062 | D61: 133593 | E61: 128485 | F61: 99315 | G61: 94833 | H61: 85029 | I61: 84202 | J61: 77766 | K61: 78900 | L61: 51523 | M61: 50525 | AI61: =AI59+AI60 -> -232633 | AJ61: =AJ59+AJ60 -> 2497 | AK61: =AK59+AK60 -> -82553 | AL61: =AL59+AL60 -> -124682 | AM61: =AM59+AM60 -> -122952 | AN61: =AN59+AN60 -> -47976 | AO61: =AO59+AO60 -> -64201 | AP61: =AP59+AP60 -> -110051 | ... AT61: =AT59+AT60 -> -19011 | AY61: 51711
A62: Changes in assets and liabilities | B62: -393164 | C62: -227977 | D62: 1282 | E62: -95599 | F62: -124035 | G62: -120222 | H62: -49055 | I62: -63952 | J62: -110541 | K62: -51406 | L62: -41785 | M62: -91120 | AY62: -47520
A63: Other Adjustments | B63: =B59-B60-B61-B62 -> -4118 | C63: =C59-C60-C61-C62 -> -4656 | D63: =D59-D60-D61-D62 -> 1215 | E63: =E59-E60-E61-E62 -> 13046 | F63: =F59-F60-F61-F62 -> -647 | G63: =G59-G60-G61-G62 -> -2730 | H63: =H59-H60-H61-H62 -> 1079 | I63: =I59-I60-I61-I62 -> -249 | ... M63: =M59-M60-M61-M62 -> -3157 | AY63: =AY59-AY60-AY61-AY62 -> 28509
A64: Investing CF | B64: -229793 | C64: -180789 | D64: -159666 | E64: -156187 | F64: -165773 | G64: -127458 | H64: -128823 | I64: -105493 | J64: -77330 | K64: -80834 | L64: -218386 | M64: -62955 | AY64: -23307
A65: Net Capex | B65: -175076 | C65: -114106 | D65: -104971 | E65: -98094 | F65: -85487 | G65: -85679 | H65: -88335 | I65: -96696 | J65: -71759 | K65: -53647 | L65: -53045 | M65: -42459 | AY65: -24578
A66: Investments & Acquisitions | B66: -34920 | C66: -46221 | D66: -43371 | E66: -41285 | F66: -74237 | G66: -36471 | H66: -32028 | I66: -6129 | J66: -1004 | K66: -26186 | L66: -164983 | M66: -19887 | AI66: -16879 | AJ66: -15608 | AK66: -11086 | AL66: -6827 | AM66: -17470 | AN66: -12414 | AO66: -4491 | AP66: 0 | AQ66: -1265 | AR66: -163651 | AS66: -21203 | AT66: 0 | AY66: -614
A67: Other Inflows (Outflows) | B67: =B64-B65-B66 -> -19797 | C67: =C64-C65-C66 -> -20462 | D67: =D64-D65-D66 -> -11324 | E67: =E64-E65-E66 -> -16808 | F67: =F64-F65-F66 -> -6049 | G67: -24 | H67: 4 | I67: 20 | J67: 31 | K67: 10 | L67: 39 | M67: 41 | AI67: -14185 | AJ67: -17957 | AK67: -52908 | AL67: -591 | AM67: 0 | AN67: 0 | AO67: 0 | AP67: 0 | AQ67: 0 | AR67: 0 | AS67: 0 | AT67: 0 | AY67: 28
A68: Financing CF | B68: -113088 | C68: -48698 | D68: 98942 | E68: -169933 | F68: -68721 | G68: -93954 | H68: -73543 | I68: -85421 | J68: -83073 | K68: -38249 | L68: 143520 | M68: -1113 | AI68: -29822 | AJ68: -15135 | AK68: -3838 | AL68: -68707 | AM68: -22855 | AN68: -22617 | AO68: -2943 | AP68: -12020 | AQ68: -26742 | AR68: -4877 | AS68: -1304 | AT68: -614 | AY68: -37622
A69: Debt Borrowing | B69: 386170 | C69: 125417 | D69: 293216 | E69: 102562 | F69: 100640 | G69: 45180 | H69: 60294 | I69: 0 | J69: 38252 | K69: 15 | L69: 383246 | M69: 17233 | AI69: =SUM(AI66:AI68) -> -60886 | AJ69: =SUM(AJ66:AJ68) -> -48700 | AK69: =SUM(AK66:AK68) -> -67832 | AL69: =SUM(AL66:AL68) -> -76125 | AM69: =SUM(AM66:AM68) -> -40325 | AN69: =SUM(AN66:AN68) -> -35031 | AO69: =SUM(AO66:AO68) -> -7434 | AP69: =SUM(AP66:AP68) -> -12020 | ... AT69: =SUM(AT66:AT68) -> -614
A70: Debt Repayment | B70: -428429 | C70: -117082 | D70: -143240 | E70: -213056 | F70: -118172 | G70: -91515 | H70: -92506 | I70: -42914 | J70: -95921 | K70: -24202 | L70: -226221 | M70: -2320 | AY70: -12689
A71: Lease Increases | B71: 0 | C71: 0 | D71: 0 | E71: 0 | F71: 0 | G71: 0 | H71: 0 | I71: 0 | J71: 0 | K71: 0 | L71: 0 | M71: 0 | AY71: 0
A72: Lease Payments | B72: -40953 | C72: -27507 | D72: -28085 | E72: -20918 | F72: -1520 | G72: 0 | H72: 0 | I72: 0 | J72: 0 | K72: 0 | L72: 0 | M72: 0 | AY72: 0
A73: Dividends | B73: -61468 | C73: -49746 | D73: -46721 | E73: -49730 | F73: -42407 | G73: -39473 | H73: -36518 | I73: -33567 | J73: -19545 | K73: -11946 | L73: -10479 | M73: -10489 | N73: cash flows FINANCING | O73: Dividends paid | AK73: -69489 | AL73: -16879 | AM73: -15608 | AN73: -11086 | AO73: -6827 | AP73: -17470 | AQ73: -12414 | AR73: -4491 | AS73: 0 | AT73: -1265 | AU73: -163651 | AV73: -21203 | AY73: -9916
A74: Share buyback | B74: 0 | C74: 0 | D74: 0 | E74: 0 | F74: 0 | G74: 0 | H74: 0 | I74: 0 | J74: 0 | K74: 0 | L74: 0 | M74: 0 | N74: cash flows FINANCING | O74: =+A74 -> Share buyback | AK74: -- | AL74: 437 | AM74: -- | AN74: -- | AO74: 21 | AP74: 368 | AQ74: 705 | AR74: 120 | AS74: 1793 | AT74: 0 | AU74: 1882 | AV74: -- | AY74: 0
A75: Other Inflows (Outflows) | B75: =B68-B69-B70-B71-B72-B73-B74 -> 31592 | C75: =C68-C69-C70-C71-C72-C73-C74 -> 20220 | D75: =D68-D69-D70-D71-D72-D73-D74 -> 23772 | E75: =E68-E69-E70-E71-E72-E73-E74 -> 11209 | F75: =F68-F69-F70-F71-F72-F73-F74 -> -7262 | G75: =G68-G69-G70-G71-G72-G73-G74 -> -8146 | H75: =H68-H69-H70-H71-H72-H73-H74 -> -4813 | I75: =I68-I69-I70-I71-I72-I73-I74 -> -8940 | ... M75: =M68-M69-M70-M71-M72-M73-M74 -> -5537 | AK75: 6857 | AL75: 5345 | AM75: 4723 | AN75: 3962 | AO75: 1821 | AP75: 2393 | AQ75: 2252 | AR75: 992 | AS75: 1772 | AT75: 1738 | AU75: 1146 | AV75: 728 | AY75: =AY68-AY69-AY70-AY71-AY72-AY73-AY74 -> -15017
A76: FX | B76: 14996 | C76: 41538 | D76: 27207 | E76: -22029 | F76: -5286 | G76: 10607 | H76: -12408 | I76: -31015 | J76: 29836 | K76: 10896 | L76: 19740 | M76: -4616 | AK76: 40592 | AL76: 8883 | AM76: 606 | AN76: 22585 | AO76: 46 | AP76: 1093 | AQ76: 46 | AR76: 193 | AS76: 7451 | AT76: 83 | AU76: 517 | AV76: 1892 | AY76: -9503
A77: Changes in cash | B77: =B59+B64+B68+B76 -> -169559 | C77: =C59+C64+C68+C76 -> 55536 | D77: =D59+D64+D68+D76 -> 341116 | E77: =E59+E64+E68+E76 -> -46037 | F77: =F59+F64+F68+F76 -> 10163 | G77: =G59+G64+G68+G76 -> 12933 | H77: =H59+H64+H68+H76 -> 52888 | I77: =I59+I64+I68+I76 -> 4255 | ... M77: =M59+M64+M68+M76 -> -31868 | AK77: 31967 | AL77: -14185 | AM77: -17957 | AN77: -52908 | AO77: -591 | AP77: -- | AQ77: -- | AR77: -- | AS77: -- | AT77: -- | AU77: -- | AV77: -- | AY77: =AY59+AY64+AY68+AY76 -> 7976
O78: (Vitalis will later fill this info) | AK78: -44847 | AL78: -29822 | AM78: -15135 | AN78: -3838 | AO78: -68707 | AP78: -22855 | AQ78: -22617 | AR78: -2943 | AS78: -12020 | AT78: -26742 | AU78: -4877 | AV78: -1304
A79: Other Data | E79: Corporate Bonds 3, 5 Y 10 | H79: Average Price | J79: Moody's | K79: YTM | L79: DIVISA | AK79: =SUM(AK73:AK78) -> -34920 | AL79: =SUM(AL73:AL78) -> -46221 | AM79: =SUM(AM73:AM78) -> -43371 | AN79: =SUM(AN73:AN78) -> -41285 | AO79: =SUM(AO73:AO78) -> -74237 | AP79: =SUM(AP73:AP78) -> -36471 | AQ79: =SUM(AQ73:AQ78) -> -32028 | AR79: =SUM(AR73:AR78) -> -6129 | ... AV79: =SUM(AV73:AV78) -> -19887
A80: Number of employees | B80: 84870 | C80: 10-K | N80: bloomberg
A81: Shares Outstanding (Thousands) | B81: =OP!C18/1000 -> 292680 | C81: Yahoo Finance | N81: bloomberg
A82: Float | B82: =OP!M17 -> 0.91467577 | C82: Yahoo Finance | N82: bloomberg
A83: Insiders Own | B83: =OP!M18 -> 0 | C83: Yahoo Finance | N83: bloomberg
A84: Fitch/ S&P Rating | B84: =OP!M20 -> A2 | C84: 10-K | N84: bloomberg
A85: Dividend Yield(Yahoo Finance) | B85: =Peers!C34 -> 3.3334761 | C85: Yahoo Finance | N85: bloomberg
A86: Daily Volume in Millions of USD | B86: 3.238 | C86: Yahoo Finance | N86: bloomberg
B87: 2020 | C87: =B87+1 -> 2021 | D87: =C87+1 -> 2022 | AO87: Short Term Debt, Net | AP87: 270217 | AQ87: 57048 | AR87: -9252 | AS87: -93943 | AT87: 100640 | AU87: -14336 | AV87: -1243 | AW87: -2838 | AX87: 13345 | AY87: -19179 | AZ87: -42867 | BA87: 14237
A88: Short % of Float | B88: N/A | E88: Yahoo Finance | AO88: Long Term Debt Issued | AP88: 115953 | AQ88: 68369 | AR88: 293216 | AS88: 102562 | AT88: 0 | AU88: 45180 | AV88: 60294 | AW88: 0 | AX88: 24907 | AY88: 15 | AZ88: 383246 | BA88: 2996
A89: EPS | B89: 533.97 | C89: 743.88 | D89: 880.59 | E89: Yahoo Finance | AO89: Long Term Debt Reduction | AP89: -428429 | AQ89: -117082 | AR89: -133988 | AS89: -119113 | AT89: -118172 | AU89: -77179 | AV89: -91263 | AW89: -40076 | AX89: -95921 | AY89: -5023 | AZ89: -183354 | BA89: -2320
AO94: Debt Borrowing | AP94: =IF(AP87>=0,AP87+AP88,AP88) -> 386170 | AQ94: =IF(AQ87>=0,AQ87+AQ88,AQ88) -> 125417 | AR94: =IF(AR87>=0,AR87+AR88,AR88) -> 293216 | AS94: =IF(AS87>=0,AS87+AS88,AS88) -> 102562 | AT94: =IF(AT87>=0,AT87+AT88,AT88) -> 100640 | AU94: =IF(AU87>=0,AU87+AU88,AU88) -> 45180 | AV94: =IF(AV87>=0,AV87+AV88,AV88) -> 60294 | AW94: =IF(AW87>=0,AW87+AW88,AW88) -> 0 | ... BA94: =IF(BA87>=0,BA87+BA88,BA88) -> 17233
AO95: Debt Repayment | AP95: =IF(AP87<=0,AP87+AP89,AP89) -> -428429 | AQ95: =IF(AQ87<=0,AQ87+AQ89,AQ89) -> -117082 | AR95: =IF(AR87<=0,AR87+AR89,AR89) -> -143240 | AS95: =IF(AS87<=0,AS87+AS89,AS89) -> -213056 | AT95: =IF(AT87<=0,AT87+AT89,AT89) -> -118172 | AU95: =IF(AU87<=0,AU87+AU89,AU89) -> -91515 | AV95: =IF(AV87<=0,AV87+AV89,AV89) -> -92506 | AW95: =IF(AW87<=0,AW87+AW89,AW89) -> -42914 | ... BA95: =IF(BA87<=0,BA87+BA89,BA89) -> -2320

Sheet Sector Impact
E2: Sector | F2: Sub-Industry | H2: Low | K2: Sector | L2: Environment | Q2: Social
E3: Communication Services | F3: Interactive Home Entertainment | H3: Medium | L3: CO2 | M3: Water | N3: Energy | O3: Waste | P3: Degradation | Q3: Turnover | R3: Compensation | S3: Reputation | T3: Discrimination | U3: Security | V3: Damage | W3: Pension | X3: Supply | Y3: Community | Z3: Public | AA3: Litigation
E4: Communication Services | F4: Interactive Media & Services | H4: High | K4: Communication Services | L4: Low | M4: Low | N4: Medium | O4: Low | P4: Low | Q4: Medium | R4: Medium | S4: Low | T4: Low | U4: High | V4: Low | W4: Low | X4: Low | Y4: Low | Z4: Low | AA4: Medium
B5: Environmental | E5: Communication Services | F5: Integrated Telecommunication Services | H5: Very High | K5: Consumer Discretionary | L5: Low | M5: Low | N5: Medium | O5: Medium | P5: Low | Q5: Medium | R5: Medium | S5: Low | T5: Low | U5: Medium | V5: Medium | W5: Medium | X5: High | Y5: Low | Z5: High | AA5: Low
B6: Direct CO2 emissions | E6: Communication Services | F6: Cable & Satellite | K6: Consumer Staples | L6: High | M6: Very High | N6: High | O6: High | P6: High | Q6: Medium | R6: High | S6: High | T6: Low | U6: Medium | V6: Medium | W6: Low | X6: High | Y6: Low | Z6: Very High | AA6: Low
B7: Total Water Use | E7: Communication Services | F7: Broadcasting | K7: Energy | L7: Very High | M7: Very High | N7: Medium | O7: Very High | P7: High | Q7: High | R7: Medium | S7: Medium | T7: Medium | U7: Medium | V7: High | W7: Medium | X7: Medium | Y7: High | Z7: High | AA7: Low
K8: Renewable Energy | L8: Low | M8: Low | N8: Low | O8: Medium | P8: Medium | Q8: Low | R8: Medium | S8: Medium | T8: High | U8: Medium | V8: Low | W8: Low | X8: Medium | Y8: Medium | Z8: High | AA8: Low
