Workbook
Name Sectors: '[1]Sector Impact'!$K$4:$K$16
Name Sectors: 'Sector Impact'!$K$4:$K$16

Sheet OP
B2: 45039 | C2: Team 1 | E2: =Inputs!H3 -> #VALUE! | L2: NASDAQ | M2: SIC:
D3: COMPANY DESCRIPTION | H3: CEO & BOARD OF DIRECTORS
D4: {=_FV(Inputs!H3,"Description")} -> Netflix, Inc. is a provider of entertainment services. The Company acquires, licenses and produces content, including original programming. The Company provides paid memberships in approximately 190 countries offering television (TV) series, films and games across a wide variety of genres and languages. Its members can play, pause and resume watching as much as they want, anytime, anywhere, and can change their plans at any time. The Company offers members the ability to receive streaming content through a host of Internet-connected devices, including TVs, digital video players, TV set-top boxes and mobile devices. The Company also has agreements with various cable, satellite and telecommunications operators to make its service available through TV set-top boxes. The Company's paid plans range from the United States dollar equivalent of $1 to $28 per month, and pricing on its extra member sub accounts range from the United States dollar equivalent of $2 to $8 per month. | H4: Name (Gender; Age) | I4: Tenure | J4: Executive? | K4: Other roles
H5: Theodore Sarandos (Male; 59) | I5: July 2020 3 Years | J5: Yes (Co-CEO) | K5: Board of Directors of Spotify Technologies SA, International Documentary Association, Exploring the Arts, Inc., American Film Institute Inc.
H6: Gregory Peters (Male; 52) | I6: January 2023 1 Year | J6: Yes (Co-CEO) | K6: Board of Directors of Highland Transcend Partners I Corp. and Doordash Inc.
H7: Reed Hastings (Male; 63) | I7: August 1998 25 Years | J7: Yes (Founder) | K7: Board of Directors of several Non-Profit Institutions
H8: Anne Sweeney (Female; 66) | I8: March 2015 9 Years | J8: No | K8: Board of Lego A/S, Board of Trustees at the Mayo Clinic and J.P. Getty Trust
H9: Richard Barton (Male; 56) | I9: April 2002 21 Years | J9: No | K9: CEO of Zillow Group, Board of Directors of QVC Group, Art.sy, Inc., Barton Family Foundation, Avvo, Inc. and Atom Digital, Inc.
H10: Timothy Haley (Male; 65) | I10: March 1998 26 Years | J10: No | K10: Managing Director of Insitutional Venture Partners
H11: Jay Hoag (Male; 62) | I11: May 1999 24 Years | J11: No | K11: Board of Directors of Zillow Group, Trip Advisor, Inc., Peloton Interactive, Inc., Menlo School, Vanderbilt University, Technology Crossover Management VIII Ltd. and Founder of TCMI, Inc.
H12: Ann Mather (Female; 63) | I12: July 2010 13 Years | J12: No | K12: Board of Directos of Bumble, Inc., Alphabet, Inc (also audit commitie), Blend Labs, Inc., Color Health, Inc., Dodge and Cox Funds
H13: Mathias Döpfner (Male; 61) | I13: September 2018 5 Years | J13: No | K13: CEO and part owner of Axel Springer SE, Board of Directors of Warner Music Group, office at American Academy, the American Jewish Commitie and the European Publisher Council
H14: Leslie Kilgore (Female; 58) | I14: January 2012 12 Years | J14: No | K14: Board of Directors of Pinterest Inc., Nextdoor Inc., Discord Inc.
H15: Strive Masiyiwa (Male; 63) | I15: December 2020 3 Years | J15: No | K15: Econet South Africa (Pty) Ltd CEO, Board of Directors of Unilever PLC, Bill & Melinda Gates Foundation, The Micronutrient Initiative/L'initiative Pour Les Micronutrim, Econet Investments Ltd. and Founder of Delta Philanthropies
H16: Susan Rice (Female; 59) | I16: September 2023 6 Months | J16: No | K16: Member of the Aspen Strategy Group, the American Academy of Diplomacy, and the Council on Foreign Relations, USA Ambassador at UN, President Bill Clinton and Barack Obama National Security Advisor, President Biden Domestic Policy Advisor
B17: USD MILLIONS | H17: Bradford Smith (Male; 65) | I17: March 2015 9 Years | J17: No | K17: Vice chair and President of Microsoft, Board of Directors of Code.org, The Seattle Foundation, Washington Roundtable and Leadership Council on Legal Diversity, Inc., chairman of Kind, Inc. (United States)
B18: COMPANY OVERVIEW
B19: Stock | D19: Liquidity and Solvency | F19: Segments | I19: Profitability (2023) | L19: Multiples
B20: Last Price | C20: {=_FV(E2,"Price")} -> 818.39 | D20: Total Assets | E20: =_xlfn.XLOOKUP(D20,'Fin. Data'!A:A,'Fin. Data'!B:B,,0) -> 48732 | F20: Regions | H20: % Sales | I20: Reporting Year | J20: 2023 | L20: Float | M20: 0.9848
B21: Outstanding Shares | C21: {=_FV(E2,"Shares outstanding",TRUE)} -> 427458100 | D21: Total Liabilities | E21: =_xlfn.XLOOKUP(D21,'Fin. Data'!A:A,'Fin. Data'!B:B,,0) -> 28144 | F21: =Segments!C5 -> United States and Canada (UCAN) | H21: =Segments!B5 -> 0.4435 | I21: End of Year | J21: 31 December 2023 | L21: Insiders Own | M21: 0.0138
B22: Market Cap. | C22: =C20*C21/1000000 -> 349827.43 | D22: Cash/Share | E22: =_xlfn.XLOOKUP("Cash & Eq.",'Fin. Data'!A:A,'Fin. Data'!B:B,,0)*1000000/C21 -> 16.698713 | F22: =Segments!C6 -> Europe, Middle East and Africa (EMEA) | H22: =Segments!B6 -> 0.313 | I22: EBITDA | K22: =_xlfn.XLOOKUP(I22,'Fin. Data'!A:A,'Fin. Data'!B:B,,0) -> 21508.3 | L22: b (Yahoo) | M22: 1.22
B23: +Total Debt | C23: ='Fin. Data'!B58 -> 16572 | D23: EBITDA/Net Financial Cost (NFC) | E23: =_xlfn.XLOOKUP("EBITDA",'Fin. Data'!A:A,'Fin. Data'!B:B,,0)/_xlfn.XLOOKUP("Net Financial Cost",'Fin. Data'!A:A,'Fin. Data'!B:B,,0) -> -28.716021 | F23: =Segments!C7 -> Latin America (LATAM) | H23: =Segments!B7 -> 0.1318 | I23: Depreciation & Amortization | K23: =_xlfn.XLOOKUP(I23,'Fin. Data'!A:A,'Fin. Data'!B:B,,0) -> 14554.3 | L23: Score (S&P) | M23: BBB+
B24: -Cash | C24: ='Fin. Data'!B39 -> 7138 | D24: Debt/EBITDA | E24: =_xlfn.XLOOKUP("Total Debt",'Fin. Data'!A:A,'Fin. Data'!B:B,,0)/_xlfn.XLOOKUP("EBITDA",'Fin. Data'!A:A,'Fin. Data'!B:B,,0) -> 0.77049325 | F24: =Segments!C8 -> Asia-Pacific (APAC) | H24: =Segments!B8 -> 0.1116 | I24: EBIT | K24: =_xlfn.XLOOKUP(I24,'Fin. Data'!A:A,'Fin. Data'!B:B,,0) -> 6954 | L24: Price/Book Value | M24: =IFERROR((C20*C21/(E20-E21))/1000000,"") -> 16.991812
B25: =Enterprise Value | C25: =C22+C23-C24 -> 359261.43 | D25: "Others Assets"/Asset | E25: =_xlfn.XLOOKUP("Other Assets",'Fin. Data'!A:A,'Fin. Data'!B:B,,0)/_xlfn.XLOOKUP("Total Assets",'Fin. Data'!A:A,'Fin. Data'!B:B,,0) -> 0.68648937 | F25: =Segments!C9 -> 0 | H25: =Segments!B9 -> 0 | I25: Net Income | K25: =_xlfn.XLOOKUP(I25,'Fin. Data'!A:A,'Fin. Data'!B:B,,0) -> 5408 | L25: NCF(3y avg)/Asset | M25: =IFERROR(K31/E20,"") -> 0.10271143
B26: Holdings (nac/int'l) | C26: - | D26: Debt/Assets | E26: =_xlfn.XLOOKUP(D26,'Fin. Data'!A:A,'Fin. Data'!B:B,,0) -> 0.34006402 | F26: Categories | H26: % Sales | I26: EPS | K26: =1000000*K25/C21 -> 12.651532 | L26: Price/Net Inc. (3y avg) | M26: =IFERROR(C22/K30,"") -> 69.890937
B27: t liq. (Holdings/Vol.) | C27: - | D27: EBITDA Margin (average) | E27: =AVERAGE(_xlfn.XLOOKUP("EBITDA Margin",'Fin. Data'!A:A,'Fin. Data'!B:D,,0)) -> 0.62582343 | F27: =Segments!C18 -> Streaming Content Services | H27: =Segments!B18 -> 0.99754357 | I27: ROA | K27: =K25/E20 -> 0.11097431 | L27: EV/Asset | M27: =IFERROR(C25/E20,"") -> 7.3721874
B28: % Short | C28: 0.0187 | D28: Operating Margin (average) | E28: =AVERAGE(_xlfn.XLOOKUP("Operating Margin",'Fin. Data'!A:A,'Fin. Data'!B:D,,0)) -> 0.19765953 | F28: =Segments!C20 -> 0 | H28: =Segments!B20 -> 0 | I28: ROIC | K28: =Peers!C17 -> 0.20187845 | L28: EV/Ebitda (3y average) | M28: =IFERROR(C25/K29,"") -> 18.109487
B29: Traffic ESG | D29: Net Income Margin (average) | E29: =AVERAGE(_xlfn.XLOOKUP("Net Income Margin",'Fin. Data'!A:A,'Fin. Data'!B:D,,0)) -> 0.15823759 | F29: =Segments!C21 -> 0 | H29: =Segments!B21 -> 0 | I29: EBITDA (3y average) | K29: =AVERAGE(_xlfn.XLOOKUP("EBITDA",'Fin. Data'!A:A,'Fin. Data'!B:D,,0)) -> 19838.3 | L29: Price/NCF (3y average) | M29: =IFERROR(C22/K31,"") -> 69.890937
B30: E | F30: =Segments!C22 -> 0 | H30: =Segments!B22 -> 0 | I30: Net Income (3y average) | K30: =AVERAGE(_xlfn.XLOOKUP("Net Income",'Fin. Data'!A:A,'Fin. Data'!B:D,,0)) -> 5005.3333 | L30: Bonds 1,3,5a (USD) | M30: -
B31: S | D31: Net Financial Cost/Avg Net Debt | E31: =-_xlfn.XLOOKUP("Net Financial Cost",'Fin. Data'!A:A,'Fin. Data'!B:B,,0)/AVERAGE(_xlfn.XLOOKUP("Net Debt",'Fin. Data'!A:A,'Fin. Data'!B:D,,0)) -> 0.070892226 | F31: =Segments!C23 -> 0 | H31: =Segments!B23 -> 0 | I31: NCF (3y average) | K31: =AVERAGE(_xlfn.XLOOKUP("Net Income",'Fin. Data'!A:A,'Fin. Data'!B:D,,0)) -> 5005.3333 | L31: Div+Rep.(3y avg)/Price | M31: =-IFERROR(SUM(E52:E54)/(3*C22),"") -> 0.0063319791
B32: G | L32: Div. Yield | M32: =-IFERROR(L53/C22,"") -> 0
B33: INVESTMENT THESIS
B34: Pillars of Recommendation | H34: Recommendation | I34: Valuation Assumptions
B35: Pillar | C35: Explanation | H35: SELL | I35: Check DCF
B36: Healthy Growth | C36: Since their global launch in 2016, they’ve been able to invest heavily in our slate — with content amortization up almost 3X from $4.8B in 2016 to $14.2B in 2023 — while steadily increasing our operating margins (up more than 5X, from 4% to 21% over the same period) and growing our free cash flow (from negative $3.3B in 2019 to positive $6.9B in 2023).
B37: Strategy and Inovation | C37: Netflix plans to continue to invest in and build ads business, expecting strong growth in 2024 but off a small base so it’s not yet a primary driver of the overall revenue growth. However it aims to make ads a more substantial revenue stream that contributes to sustained, healthy revenue growth in 2025 and beyond.
B38: Improvement | C38: Netflix is establishing itself in new areas like advertising and games, which they believe to have a lot more room to grow. Theres a $600B+ opportunity revenue market across pay TV, film, games and branded advertising — and today Netflix accounts for only roughly 5% of that addressable market. And their share of TV viewing is still less than 10% in every country.
B39: Risks of Investment | H39: Price Target | I39: Valuation
B40: Risk | C40: Explanation | H40: =DCF!D76 -> 354.75131 | I40: Discount Rate | J40: =DCF!F50 -> 0.088 | L40: Price M. Upside | M40: =#REF! -> #REF!
B41: Content Costs | C41: With the persuit of original content, Netflix sees its costs increse significantly potentially lowering its margins
B42: Competition | C42: The satuarition of the streaming market means any move by competitors could impact growth and subscriber numbers | I42: Downside | J42: =DCF!D75 -> -0.56652537 | L42: EV M. Upside | M42: =#REF! -> #REF!
B43: Membership Growth | C43: Changes in content and membership price make Netflix lose and retain subscribers
B44: FINANCIAL PERFORMANCE
B45: Year | C45: Net Sales | D45: Operating Margin | E45: Dividends + Share Buyback | F45: Net Cash Flow | G45: Debt/Assets | H45: Depreciation & Amortization | I45: Capex + Investments | J45: Cash Flow
B46: =B47-1 -> 2015 | C46: {=_xlfn.SORTBY(TRANSPOSE(_xlfn.XLOOKUP(C$45,'Fin. Data'!$A:$A,'Fin. Data'!$B:$J,,0)),$B$46:$B$54,-1)} -> 6780 | D46: {=_xlfn.SORTBY(TRANSPOSE(_xlfn.XLOOKUP(D$45,'Fin. Data'!$A:$A,'Fin. Data'!$B:$J,,0)),$B$46:$B$54,-1)} -> 0.045132743 | E46: {=_xlfn.SORTBY(TRANSPOSE(_xlfn.XLOOKUP(E$45,'Fin. Data'!$A:$A,'Fin. Data'!$B:$J,,0)),$B$46:$B$54,-1)} -> 0 | F46: =Inputs!J77 -> 695.8 | G46: {=_xlfn.SORTBY(TRANSPOSE(_xlfn.XLOOKUP(G$45,'Fin. Data'!$A:$A,'Fin. Data'!$B:$J,,0)),$B$46:$B$54,-1)} -> 0.2497976 | H46: {=_xlfn.SORTBY(TRANSPOSE(_xlfn.XLOOKUP(H$45,'Fin. Data'!$A:$A,'Fin. Data'!$B:$J,,0)),$B$46:$B$54,-1)} -> #VALUE! | I46: {=_xlfn.SORTBY(TRANSPOSE(_xlfn.XLOOKUP(I$45,'Fin. Data'!$A:$A,'Fin. Data'!$B:$J,,0)),$B$46:$B$54,-1)} -> -541.1 | L46: =J20 -> 2023 | M46: =L46-1 -> 2022
B47: =B48-1 -> 2016 | C47: 8831 | D47: 0.043030234 | E47: 0 | F47: =Inputs!I77 -> -341.8 | G47: 0.34339662 | I47: -372 | J47: Net Income | L47: =_xlfn.XLOOKUP($J47,'Fin. Data'!$A:$A,'Fin. Data'!B:B,,0) -> 5408 | M47: =_xlfn.XLOOKUP($J47,'Fin. Data'!$A:$A,'Fin. Data'!C:C,,0) -> 4492 | N47: =(C47/C46)-1 -> 0.30250737 | O47: =(D47/D46)-1 -> -0.046585002
B48: =B49-1 -> 2017 | C48: 11693 | D48: 0.07175233 | E48: 0 | F48: =Inputs!H77 -> 1355.2 | G48: 0.3999384 | I48: -301.8 | J48: Operating CF | L48: =_xlfn.XLOOKUP($J48,'Fin. Data'!$A:$A,'Fin. Data'!B:B,,0) -> 7274.3 | M48: =_xlfn.XLOOKUP($J48,'Fin. Data'!$A:$A,'Fin. Data'!C:C,,0) -> 2026.3 | N48: =(C48/C47)-1 -> 0.32408561 | O48: =(D48/D47)-1 -> 0.6674864 | Q48: =F48/F47-1 -> -4.9648917 | R48: =H48/H47-1 -> #DIV/0! | S48: =I48/I47-1 -> -0.18870968
B49: =B50-1 -> 2018 | C49: 15794 | D49: 0.10162087 | E49: 0 | F49: =Inputs!G77 -> 989.2 | G49: 0.3988604 | I49: -212.5 | J49: Investing CF | L49: =_xlfn.XLOOKUP($J49,'Fin. Data'!$A:$A,'Fin. Data'!B:B,,0) -> 541.8 | M49: =_xlfn.XLOOKUP($J49,'Fin. Data'!$A:$A,'Fin. Data'!C:C,,0) -> -2076.4 | N49: =(C49/C48)-1 -> 0.35072265 | O49: =(D49/D48)-1 -> 0.41627273 | Q49: =F49/F48-1 -> -0.27007084 | R49: =H49/H48-1 -> #DIV/0! | S49: =I49/I48-1 -> -0.29589132
B50: =B51-1 -> 2019 | C50: 20156 | D50: 0.1291923 | E50: 0 | F50: =Inputs!F77 -> 1231.8 | G50: 0.48189899 | I50: -253 | J50: Net Capex | L50: =_xlfn.XLOOKUP($J50,'Fin. Data'!$A:$A,'Fin. Data'!B:B,,0) -> -348.6 | M50: =_xlfn.XLOOKUP($J50,'Fin. Data'!$A:$A,'Fin. Data'!C:C,,0) -> -407.7 | N50: =(C50/C49)-1 -> 0.27618083 | O50: =(D50/D49)-1 -> 0.27131663 | Q50: =F50/F49-1 -> 0.24524869 | R50: =H50/H49-1 -> #DIV/0! | S50: =I50/I49-1 -> 0.19058824
B51: =B52-1 -> 2020 | C51: 24996 | D51: 0.18342935 | E51: 0 | F51: =Inputs!E77 -> 3195.1 | G51: 0.45852851 | I51: -497.9 | J51: Investments & Acquisitions | L51: =_xlfn.XLOOKUP($J51,'Fin. Data'!$A:$A,'Fin. Data'!B:B,,0) -> -504.9 | M51: =_xlfn.XLOOKUP($J51,'Fin. Data'!$A:$A,'Fin. Data'!C:C,,0) -> -1668.7 | N51: =(C51/C50)-1 -> 0.24012701 | O51: =(D51/D50)-1 -> 0.41981642 | Q51: =F51/F50-1 -> 1.5938464 | R51: =H51/H50-1 -> #DIV/0! | S51: =I51/I50-1 -> 0.96798419
B52: =B53-1 -> 2021 | C52: 29698 | D52: 0.20859991 | E52: -600 | F52: =Inputs!D77 -> -2183.8 | G52: 0.39062465 | I52: -1312.9 | J52: Financing CF | L52: =_xlfn.XLOOKUP($J52,'Fin. Data'!$A:$A,'Fin. Data'!B:B,,0) -> -5950.8 | M52: =_xlfn.XLOOKUP($J52,'Fin. Data'!$A:$A,'Fin. Data'!C:C,,0) -> -664.3 | N52: =(C52/C51)-1 -> 0.1881101 | O52: =(D52/D51)-1 -> 0.13722208 | Q52: =F52/F51-1 -> -1.6834841 | R52: =H52/H51-1 -> #DIV/0! | S52: =I52/I51-1 -> 1.6368749
B53: =B54-1 -> 2022 | C53: 31616 | D53: 0.17816928 | E53: 0 | F53: =Inputs!C$77 -> -884.5 | G53: 0.34843091 | I53: -2076.4 | J53: Dividends | L53: =_xlfn.XLOOKUP($J53,'Fin. Data'!$A:$A,'Fin. Data'!B:B,,0) -> 0 | M53: =_xlfn.XLOOKUP($J53,'Fin. Data'!$A:$A,'Fin. Data'!C:C,,0) -> 0 | N53: =(C53/C52)-1 -> 0.064583474 | O53: =(D53/D52)-1 -> -0.14588034 | Q53: =F53/F52-1 -> -0.59497207 | R53: =H53/H52-1 -> #DIV/0! | S53: =I53/I52-1 -> 0.58153706
B54: =J20 -> 2023 | C54: 33723 | D54: 0.20620941 | E54: -6045.3 | F54: =Inputs!B77 -> 1948 | G54: 0.34006402 | I54: -853.5 | J54: Share Buyback | L54: =_xlfn.XLOOKUP($J54,'Fin. Data'!$A:$A,'Fin. Data'!B:B,,0) -> -6045.3 | M54: =_xlfn.XLOOKUP($J54,'Fin. Data'!$A:$A,'Fin. Data'!C:C,,0) -> 0 | N54: =(C54/C53)-1 -> 0.066643472 | O54: =(D54/D53)-1 -> 0.15737915 | Q54: =F54/F53-1 -> -3.2023742 | R54: =H54/H53-1 -> #VALUE! | S54: =I54/I53-1 -> -0.58895203
B55: Annual Growth Rate | C55: =IFERROR((C54/C46)^(1/8)-1,"") -> 0.22204462 | D55: =IFERROR((D54/D46)^(1/8)-1,"") -> 0.20914141 | F55: =IFERROR((F54/F46)^(1/8)-1,"") -> 0.13733411 | H55: =IFERROR((H54/H46)^(1/8)-1,"") | J55: FX | L55: =_xlfn.XLOOKUP($J55,'Fin. Data'!$A:$A,'Fin. Data'!B:B,,0) -> 82.7 | M55: =_xlfn.XLOOKUP($J55,'Fin. Data'!$A:$A,'Fin. Data'!C:C,,0) -> -170.1 | N55: =(C55/C54)-1 -> -0.99999342 | O55: =(D55/D54)-1 -> 0.014218533
B56: Average Growth Rate | C56: =IFERROR(AVERAGE(N47:N54),"") -> 0.22662006 | D56: =IFERROR(AVERAGE(O47:O54),"") -> 0.23462851 | F56: =IFERROR(AVERAGE(Q47:Q54),"") -> -1.2680997 | H56: =IFERROR(AVERAGE(S47:S54),"") -> 0.32906162 | J56: Changes in Cash | L56: =L48+L49+L52-L53-L54 -> 7910.6 | M56: =M48+M49+M52-M53-M54 -> -714.4
B57: CVAR | C57: =IFERROR(STDEV(C47:C54)/AVERAGE(C47:C54),"") -> 0.4264416 | D57: =IFERROR(STDEV(D46:D54)/AVERAGE(D46:D54),"") -> 0.51817825 | F57: =IFERROR(STDEV(F46:F54)/AVERAGE(F46:F54),"") -> 2.3980837 | H57: =IFERROR(STDEV(H46:H54)/AVERAGE(H46:H54),"") | J57: Inventory/D Revenues | L57: =IFERROR(SUM(I51:I54)/(C54-C50),"") -> -0.34942876 | M57: =IFERROR((SUM(I51:I54)-SUM(H51:H54))/(C54-C50),"") -> -0.34942876
B58: Last Year | C58: =IFERROR(C54/C53-1,"") -> 0.066643472 | D58: =IFERROR(D54/D53-1,"") -> 0.15737915 | F58: =IFERROR(1-(F54/F53),"") -> 3.2023742 | H58: =IFERROR(1-(H54/H53),"") | J58: t inversiones; t adq. neto dep. | L58: =IFERROR(L57/E27,"") -> -0.55835039 | M58: =IFERROR(M57/E27,"") -> -0.55835039
B59: QUALITATIVE ANALYSIS
B60: SWOT ANALYSIS | J60: HOLDERS
B61: Pros | E61: Cons | J61: Name | M61: % Stake
B62: Netflix shows impressive financial strength and growth potential. The company maintains high margins, contributing to its profitability. . Additionally, the average price target set by analysts has been strongly revised upwards in the last quarter, signaling optimism about netflix’s future performance. Netflix also relies on a strong brand name and a high adaptability, constantly adapting its services. | E62: The company has limited rights to stream content from other sources. It also has a high debt burden that limits its ability to invest in new projects. Netflix struggles to produce original content that appeals to diverse audiences across the world. Netflix has poor customer service quality. Despite its high valuation, some analysts’ consensus view and target prices indicate that the stock has limited upside potential and may face downward pressure in the future. | J62: Vanguard Group Inc. | M62: 0.0842
J63: Blackrock Inc. | M63: 0.0714
J64: FMR, LLC. | M64: 0.0507
J65: State Street Corporation | M65: 0.0387
J66: Prince (T.Rowe) Associates Inc. | M66: 0.0273
J67: Capital World Investors | M67: 0.0271
J68: JP Morgan Chase & Company | M68: 0.0215
J69: Capital International Investors | M69: 0.0205
J70: Geode Capital Management, LLC | M70: 0.0199
J71: Capital Research Global Investors | M71: 0.0158
B72: Opportunities | E72: Risks
B73: The company can leverage its customer base and global reach to offer more products and services that cater to different tastes and preferences. Netflix can diversify its portfolio by adding videogames, comic books, podcasts, and other forms of entertainment. Netflix can also form strategic alliances with other content providers, such as studios, networks, and celebrities, to create exclusive and original content that appeals to niche audiences. Furthermore, Netflix can adopt a flexible pricing strategy that allows it to offer lower-cost mobile-only streaming plans in emerging markets. | E73: Netflix is facing competition from other streaming services as the market becomes saturated with streaming options. . Another challenge for Netflix is the regulation from sovereign governments, especially in countries where censorship or content restrictions are prevalent having to comply with local laws and regulations. Piracy is also an heavy threat as it has significantly increased needing to increased their security in order to preserve their intelectual property. Finally account sharing is one of the biggest issues in Netflix ammongst their users, account sharing also affects Netflix’s data and analytics, which are crucial for understanding customer preferences and behaviors.
B82: NOTES | G82: STOCK PERFORMANCE (5 years)
G107: #VALUE! | I107: #VALUE! | J107: #VALUE! | K107: #VALUE! | L107: #VALUE!

Sheet Segments
B2: ="Regions "&"("&OP!$J$20&")" -> Regions (2023) | Q2: Products
D3: Nominal value | K3: YoY Growth
B4: Weight | C4: Region | D4: 2023 | E4: =D4-1 -> 2022 | F4: =E4-1 -> 2021 | G4: =F4-1 -> 2020 | H4: =G4-1 -> 2019 | I4: =H4-1 -> 2018 | K4: =OP!J20 -> 2023 | L4: =K4-1 -> 2022 | M4: =L4-1 -> 2021 | N4: =M4-1 -> 2020 | O4: =N4-1 -> 2019 | P4: =O4-1 -> 2018
B5: 0.4435 | C5: United States and Canada (UCAN) | D5: 14957 | E5: 14230 | F5: 13154 | G5: 11695 | K5: =(D5-E5)/E5 -> 0.051089248 | L5: =(E5-F5)/F5 -> 0.081800213 | M5: =(F5-G5)/G5 -> 0.12475417 | P5: -
B6: 0.313 | C6: Europe, Middle East and Africa (EMEA) | D6: 10556 | E6: 9745 | F6: 9700 | G6: 7772 | K6: =(D6-E6)/E6 -> 0.083222165 | L6: =(E6-F6)/F6 -> 0.0046391753 | M6: =(F6-G6)/G6 -> 0.24806999 | P6: -
B7: 0.1318 | C7: Latin America (LATAM) | D7: 4446 | E7: 4070 | F7: 3577 | G7: 3157 | K7: =(D7-E7)/E7 -> 0.092383292 | L7: =(E7-F7)/F7 -> 0.13782499 | M7: =(F7-G7)/G7 -> 0.13303769 | P7: -
B8: 0.1116 | C8: Asia-Pacific (APAC) | D8: 3764 | E8: 3570 | F8: 3267 | G8: 2372 | K8: =(D8-E8)/E8 -> 0.054341737 | L8: =(E8-F8)/F8 -> 0.092745638 | M8: =(F8-G8)/G8 -> 0.37731872 | P8: -
P9: -
P10: -
B11: =IFERROR(D11/$D$13,"") -> 0
B12: =IFERROR(D12/$D$13,"") -> 0
B13: =SUM(B5:B12) -> 0.9999 | C13: TOTAL | D13: =SUM(D5:D12) -> 33723 | E13: =SUM(E5:E12) -> 31615 | F13: =SUM(F5:F12) -> 29698 | G13: =SUM(G5:G12) -> 24996 | H13: =SUM(H5:H12) -> 0 | I13: =SUM(I5:I12) -> 0 | K13: =(D13-E13)/E13 -> 0.06667721 | L13: =(E13-F13)/F13 -> 0.064549801 | M13: =(F13-G13)/G13 -> 0.1881101 | N13: =(G13-H13)/H13 -> #DIV/0! | O13: =(H13-I13)/I13 -> #DIV/0! | P13: -
B15: ="Categories "&"("&OP!$J$20&")" -> Categories (2023)
D16: Nominal value | K16: YoY Growth
B17: Weight | C17: Category | D17: 2023 | E17: =D17-1 -> 2022 | F17: =E17-1 -> 2021 | G17: =F17-1 -> 2020 | H17: =G17-1 -> 2019 | I17: =H17-1 -> 2018 | K17: =OP!J20 -> 2023 | L17: =K17-1 -> 2022 | M17: =L17-1 -> 2021 | N17: =M17-1 -> 2020 | O17: =N17-1 -> 2019 | P17: =O17-1 -> 2018
B18: =IFERROR(D18/$D$24,"") -> 0.99754357 | C18: Streaming Content Services | D18: 33640.458 | E18: 31468.852 | F18: 29515.496 | G18: 24756.675 | H18: 19859.23 | I18: 15428.752 | K18: =(D18-E18)/E18 -> 0.06900811 | L18: =(E18-F18)/F18 -> 0.066180694 | M18: =(F18-G18)/G18 -> 0.19222375 | N18: =(G18-H18)/H18 -> 0.246608 | O18: =(H18-I18)/I18 -> 0.28715725 | P18: -
B19: =IFERROR(D19/$D$24,"") -> 0.0024564324 | C19: DVD services | D19: 82.839 | E19: 145.698 | F19: 182.348 | G19: 239.381 | H19: 297.217 | I19: 365.589
B20: =IFERROR(D20/$D$24,"") -> 0
B21: =IFERROR(D21/$D$24,"") -> 0
B22: =IFERROR(D22/$D$24,"") -> 0
B23: =IFERROR(D23/$D$24,"") -> 0 | P23: -
B24: =SUM(B18:B23) -> 1 | C24: TOTAL | D24: =SUM(D18:D23) -> 33723.297 | E24: =SUM(E18:E23) -> 31614.55 | F24: =SUM(F18:F23) -> 29697.844 | G24: =SUM(G18:G23) -> 24996.056 | H24: =SUM(H18:H23) -> 20156.447 | I24: =SUM(I18:I23) -> 15794.341 | K24: =(D24-E24)/E24 -> 0.066701788 | L24: =(E24-F24)/F24 -> 0.064540241 | M24: =(F24-G24)/G24 -> 0.18810119 | N24: =(G24-H24)/H24 -> 0.24010229 | O24: =(H24-I24)/I24 -> 0.27618158 | P24: -
B26: Categories | D26: Description | I26: Graphs
B27: Streaming content services | D27: Consists in revenues earned mostly from membership fees for services related to streaming content to their members.
B28: DVD services | D28: DVD-by-mail service. This operation was discontinued in september 29, 2023
B34: Industry | J34: Graphs (Industry Forecasts)
B35: Drivers | D35: Description
B36: AI | D36: By providing real-time insight into stream quality, user behavior, and content optimization on a micro level, AI can help aid engineering, development, and marketing teams simultaneously.
B37: Subscription Tiers | D37: Panning ads, no ads, access to all content, access to limited content, monthly and yearly subscriptions, bundles, and potentially new innovations such as loyalty plans. With more options, streamers may be better able to reduce churn—the rate at which people cancel their subscriptions—and keep more subscribers around for longer.
B38: Sales forecast
B39: Source | D39: Market Growth CAGR | G39: Period
B40: Statista | D40: 0.0989 | G40: 2024-2028
B41: Grand View Research | D41: 0.215 | G41: 2023-2030
B44: Company's Strategy / Extra Notes
B47: "Our core strategy is to grow our business globally within the parameters of our operating margin target. We strive to continuously improve our members' experience by offering compelling content that delights them and attracts new members. We seek to drive conversation around our content to further enhance member joy, and we are continuously enhancing our user interface to help our members more easily choose content that they will find enjoyable."

Sheet Acuerdo
A1: Invertir
A2: NO invertir
A3: Mantener sin elevar posición
A4: Mantener (y seguir comprando)
A5: Liquidar
A6: PENDIENTE

Sheet Peers
B1: Peer Logo | C1: Peer Name | D1: Description
C2: #VALUE! | D2: The Walt Disney Company is a diversified company that offers a variety of streaming services to cater to different interests: Disney+: This flagship service focuses on family-friendly content, including Disney and Marvel movies and TV shows. Hulu (US only): Provides a mix of original shows, popular network programs, and movies, geared towards a more general audience. ESPN+: A sports fan's haven, offering live and on-demand sports events, documentaries, and original programming. With this range of options (there is more 2 than this), Disney covers a wide spectrum of viewers, from families with young children to sports enthusiasts and those seeking general entertainment.
C3: #VALUE! | D3: Warner Bros. Discovery is a global media and entertainement company. They has streamlined its streaming offerings into two main services: Max: This is the home for scripted dramas, comedies, movies, and animation. It boasts content from Warner Bros., HBO, DC Comics, and even some Discovery Channel favorites. Discovery+: For reality TV and documentary lovers, Discovery+ offers a vast library of shows on nature, science, exploration, true crime, and lifestyle topics from channels like Discovery, TLC, HGTV, and Food Network. This combined approach lets Warner Bros. Discovery cater to both fans of scripted entertainment and those who prefer factual programming.
C4: #VALUE! | D4: Amazon.com,Inc. provides a range of products and services to costumers. The streaming landscape can be broken down into two main parts: Prime Video: This is included with a Prime membership, offering a mix of Amazon Original movies and TV shows, popular licensed content, and rentals/purchases. Prime Video caters to a broad audience with something for families, action movie buffs, and comedy lovers. Prime Video Channels: This is an add-on service where you can subscribe to individual channels like Paramount+, Starz, or AMC+, providing access to their specific libraries of shows and movies. Prime Video Channels allows viewers to personalize their streaming experience by adding channels that align with their interests. So, Amazon offers both a general streaming service with Prime Video and the option to expand your choices with targeted channels.
C5: #VALUE! | D5: Apple.Inc designs, manufactures and sell smartphones, personal computers, tablets, wearable and accessories, and, as well, a variety of related services. Apple takes a more focused approach to streaming with its service: Apple TV+: This subscription service features Apple Originals – critically acclaimed shows, movies, and documentaries across genres, from comedies and dramas to kids content. New Apple Originals are added regularly, giving viewers something fresh to discover. While Apple TV+ doesn't offer the vast library of other streaming services, it emphasizes high-quality, exclusive content. It caters to viewers who value curated entertainment and are willing to pay for a smaller but prestigious selection.
B7: In Millions USD | C7: =OP!E2 -> #VALUE! | D7: =C2 -> #VALUE! | E7: =C3 -> #VALUE! | F7: =C4 -> #VALUE! | G7: =C5 -> #VALUE! | H7: AVERAGE | I7: Deviation from Average
B8: Company Info | H8: =IFERROR(AVERAGE(C8:G8),"") | K8: TRAFFIC
B9: Market Cap | C9: {=_FV(C7,"Market cap",TRUE)/1000000} -> 349827.43 | D9: {=_FV(D7,"Market cap",TRUE)/1000000} -> 182700.75 | E9: {=_FV(E7,"Market cap",TRUE)/1000000} -> 22545.294 | F9: {=_FV(F7,"Market cap",TRUE)/1000000} -> 2194587.7 | G9: {=_FV(G7,"Market cap",TRUE)/1000000} -> 3387939 | H9: =IFERROR(AVERAGE(C9:G9),"") -> 1227520 | I9: =SQRT((C9-H9)^2) -> 877692.6 | L9: Best Value
B10: Net Sales (current) | C10: =C55 -> 33723 | D10: =D55 -> 88935 | E10: =E55 -> 41321 | F10: =F55 -> 574785 | G10: =G55 -> 385706 | H10: =IFERROR(AVERAGE(C10:G10),"") -> 224894 | I10: =SQRT((C10-H10)^2) -> 191171
B11: Profitability | H11: =IFERROR(AVERAGE(C11:G11),"") | L11: Important Value
B12: Sales Growth (ttm) | C12: =C55/C54-1 -> 0.066643472 | D12: =D55/D54-1 -> 0.075106985 | E12: =E55/E54-1 -> 0.22190023 | F12: =F55/F54-1 -> 0.11829574 | G12: =G55/G54-1 -> -0.021865046 | H12: =IFERROR(AVERAGE(C12:G12),"") -> 0.092016276 | I12: =SQRT((C12-H12)^2) -> 0.025372804
B13: Sales Growth (36m) | C13: =C55/C53-1 -> 0.34913586 | D13: =D55/D53-1 -> 0.36011195 | E13: =E55/E53-1 -> 2.8722706 | F13: =F55/F53-1 -> 0.48883346 | G13: =G55/G53-1 -> 0.40504526 | H13: =IFERROR(AVERAGE(C13:G13),"") -> 0.89507943 | I13: =SQRT((C13-H13)^2) -> 0.54594357 | L13: Worst Value
B14: Operating Margin | C14: =C58/C55 -> 0.20620941 | D14: =D58/D55 -> 0.1117108 | E14: =E58/E55 -> -0.021441882 | F14: =F58/F55 -> 0.064114408 | G14: =G58/G55 -> 0.30763846 | H14: =IFERROR(AVERAGE(C14:G14),"") -> 0.13364624 | I14: =SQRT((C14-H14)^2) -> 0.072563172
B15: Net Income Margin | C15: =C61/C55 -> 0.16036533 | D15: =D61/D55 -> 0.033575083 | E15: =E61/E55 -> -0.075651606 | F15: =F61/F55 -> 0.052932836 | G15: =G61/G55 -> 0.26163192 | H15: =IFERROR(AVERAGE(C15:G15),"") -> 0.086570712 | I15: =SQRT((C15-H15)^2) -> 0.073794618
B16: Return on Equity (RoE) | C16: =C61/C73 -> 0.26267729 | D16: =D61/D73 -> 0.026421973 | E16: =E61/E73 -> -0.067266311 | F16: =F61/F73 -> 0.15071207 | G16: =G61/G73 -> 1.6238052 | H16: =IFERROR(AVERAGE(C16:G16),"") -> 0.39927005 | I16: =SQRT((C16-H16)^2) -> 0.13659276
B17: Return on Invested Capital (ROIC) | C17: =(1+C60/(C58+C59))*C58/(C72+C73-C64) -> 0.20187845 | D17: =(1+D60/(D58+D59))*D58/(D72+D73-D64) -> 0.053965889 | E17: =(1+E60/(E58+E59))*E58/(E72+E73-E64) -> -0.0075122454 | F17: =(1+F60/(F58+F59))*F58/(F72+F73-F64) -> 0.11841239 | G17: =(1+G60/(G58+G59))*G58/(G72+G73-G64) -> 0.90483586 | H17: =IFERROR(AVERAGE(C17:G17),"") -> 0.25431607 | I17: =SQRT((C17-H17)^2) -> 0.052437618
B18: Solvency | H18: =IFERROR(AVERAGE(C18:G18),"")
B19: Debt/Assets | C19: =C72/C69 -> 0.34006402 | D19: =D72/D69 -> 0.24270475 | E19: =E72/E69 -> 0.35573531 | F19: =F72/F69 -> 0.25691005 | G19: =G72/G69 -> 0.31506908 | H19: =IFERROR(AVERAGE(C19:G19),"") -> 0.30209664 | I19: =SQRT((C19-H19)^2) -> 0.03796738
B20: Net Debt/EBITDA | C20: =(C72-C64)/C57 -> 0.43862137 | D20: =(D72-D64)/D57 -> 2.7036869 | E20: =(E72-E64)/E57 -> 1.7833862 | F20: =(F72-F64)/F57 -> 0.54619583 | G20: =(G72-G64)/G57 -> 0.37109764 | H20: =IFERROR(AVERAGE(C20:G20),"") -> 1.1685976 | I20: =SQRT((C20-H20)^2) -> 0.72997622
B21: Interest Coverage Ratio | C21: =-C57/C59 -> 28.716021 | D21: =-D57/D59 -> 11.436364 | E21: =-E57/E59 -> 10.953477 | F21: =-F57/F59 -> 383.69957 | G21: =-G57/G59 -> 236.24248 | H21: =IFERROR(AVERAGE(C21:G21),"") -> 134.20958 | I21: =SQRT((C21-H21)^2) -> 105.49356
B22: Liquidity
B23: Current Ratio | C23: =C67/C71 -> 1.1192868 | D23: =D67/D71 -> 1.0521532 | E23: =E67/E71 -> 0.92734151 | F23: =F67/F71 -> 1.0450772 | G23: =G67/G71 -> 0.98801167 | H23: =IFERROR(AVERAGE(C23:G23),"") -> 1.0263741 | I23: =SQRT((C23-H23)^2) -> 0.09291268
B24: Quick Ratio | C24: =(C64+C65)/C71 -> 0.95079562 | D24: =(D64+D65)/D71 -> 0.78233084 | E24: =(E64+E65)/E71 -> 0.64094704 | F24: =(F64+F65)/F71 -> 0.84304832 | G24: =(G64+G65)/G71 -> 0.62668951 | H24: =IFERROR(AVERAGE(C24:G24),"") -> 0.76876227 | I24: =SQRT((C24-H24)^2) -> 0.18203335
B25: Activity | H25: =IFERROR(AVERAGE(C25:G25),"")
B26: Inventory Turnover | C26: 0 | D26: =D56/D66 -> 29.751401 | E26: 0 | F26: =F56/F66 -> 14.436041 | G26: =G56/G66 -> 33.49155 | H26: =IFERROR(AVERAGE(C26:G26),"") -> 15.535798 | I26: =SQRT((C26-H26)^2) -> 15.535798
B27: Acc. Receivable Turnover | C27: =C55/C65 -> 26.202797 | D27: =D55/D65 -> 8.7371058 | E27: =E55/E65 -> 6.8333058 | F27: =F55/F65 -> 11.000038 | G27: =G55/G65 -> 13.071235 | H27: =IFERROR(AVERAGE(C27:G27),"") -> 13.168896 | I27: =SQRT((C27-H27)^2) -> 13.033901
A28: Price/Sales | B28: Payables Turnover | C28: =C56/C70 -> 3.7811661 | D28: =D56/D70 -> 3.8612893 | E28: =E56/E70 -> 19.465079 | F28: =F56/F70 -> 5.6598534 | G28: =G56/G70 -> 3.3865455 | H28: =IFERROR(AVERAGE(C28:G28),"") -> 7.2307867 | I28: =SQRT((C28-H28)^2) -> 3.4496206
B29: Fixed Asset Turnover | C29: =C55/C68 -> 7.624463 | D29: =D55/D68 -> 1.1467937 | E29: =E55/E68 -> 4.569896 | F29: =F55/F68 -> 1.4485473 | G29: =G55/G68 -> 3.3657013 | H29: =IFERROR(AVERAGE(C29:G29),"") -> 3.6310803 | I29: =SQRT((C29-H29)^2) -> 3.9933828
B30: Total Asset Turnover | C30: =C55/C69 -> 0.69200936 | D30: =D55/D69 -> 0.43260742 | E30: =E55/E69 -> 0.3366081 | F30: =F55/F69 -> 1.0889091 | G30: =G55/G69 -> 1.0939438 | H30: =IFERROR(AVERAGE(C30:G30),"") -> 0.72881555 | I30: =SQRT((C30-H30)^2) -> 0.036806195
B31: Valuation | H31: =IFERROR(AVERAGE(C31:G31),"")
B32: Price/Earnings | C32: =C9/C61 -> 64.687026 | D32: =D9/D61 -> 61.185785 | E32: =E9/E61 -> -7.2121862 | F32: =F9/F61 -> 72.131068 | G32: =G9/G61 -> 33.572869 | H32: =IFERROR(AVERAGE(C32:G32),"") -> 44.872912 | I32: =SQRT((C32-H32)^2) -> 19.814113
B33: Price/Sales | C33: =C9/C55 -> 10.373556 | D33: =D9/D55 -> 2.0543178 | E33: =E9/E55 -> 0.54561347 | F33: =F9/F55 -> 3.818102 | G33: =G9/G55 -> 8.7837342 | H33: =IFERROR(AVERAGE(C33:G33),"") -> 5.1150647 | I33: =SQRT((C33-H33)^2) -> 5.2584914
B34: Price/Book | C34: =C9/C73 -> 16.991812 | D34: =D9/D73 -> 1.6166492 | E34: =E9/E73 -> 0.48513716 | F34: =F9/F73 -> 10.871023 | G34: =G9/G73 -> 54.515801 | H34: =IFERROR(AVERAGE(C34:G34),"") -> 16.896085 | I34: =SQRT((C34-H34)^2) -> 0.09572792
B35: EV/Sales | C35: =(C72+C9-C64)/C55 -> 10.653306 | D35: =(D72+D9-D64)/D55 -> 2.4558807 | E35: =(E72+E9-E64)/E55 -> 1.510958 | F35: =(F72+F9-F64)/F55 -> 3.9030572 | G35: =(G72+G9-G64)/G55 -> 8.9121558 | H35: =IFERROR(AVERAGE(C35:G35),"") -> 5.4870715 | I35: =SQRT((C35-H35)^2) -> 5.1662344
B36: EV/EBITDA | C36: =(C72+C9-C64)/C57 -> 16.703386 | D36: =(D72+D9-D64)/D57 -> 16.535223 | E36: =(E72+E9-E64)/E57 -> 2.7913575 | F36: =(F72+F9-F64)/F57 -> 25.093608 | G36: =(G72+G9-G64)/G57 -> 25.753291 | H36: =IFERROR(AVERAGE(C36:G36),"") -> 17.375373 | I36: =SQRT((C36-H36)^2) -> 0.67198702
B37: Stock Info | H37: =IFERROR(AVERAGE(C37:G37),"")
B38: Float | C38: =OP!M20 -> 0.9848 | D38: 1 | E38: 0.902 | F38: 0.887 | G38: 0.998 | H38: =IFERROR(AVERAGE(C38:G38),"") -> 0.95436 | I38: =SQRT((C38-H38)^2) -> 0.03044
B39: b (Yahoo) | C39: =OP!M22 -> 1.22 | D39: 1.41 | E39: 1.51 | F39: 1.17 | G39: 1.29 | H39: =IFERROR(AVERAGE(C39:G39),"") -> 1.32 | I39: =SQRT((C39-H39)^2) -> 0.1
B40: Dividend Yield (yahoo finance) | C40: =OP!M32 -> 0 | D40: 0.0027 | E40: 0 | F40: 0 | G40: 0.0056 | H40: =IFERROR(AVERAGE(C40:G40),"") -> 0.00166 | I40: =SQRT((C40-H40)^2) -> 0.00166
B41: Stock Performance
B42: 1y | C42: 1.0606 | D42: 0.19 | E42: -0.3773 | F42: 0.8971 | G42: 13.46 | H42: =IFERROR(AVERAGE(C42:G42),"") -> 3.04608 | I42: =SQRT((C42-H42)^2) -> 1.98548
B43: 3y | C43: =+(C44-293.51)/293.51 -> 1.7882866 | D43: -0.0966 | E43: -0.63 | F43: -0.07 | G43: 0.44 | H43: =IFERROR(AVERAGE(C43:G43),"") -> 0.28633732 | I43: =SQRT((C43-H43)^2) -> 1.5019493
B44: Current Price | C44: {=_FV(C7,"Price")} -> 818.39 | D44: {=_FV(D7,"Price")} -> 100.74 | E44: {=_FV(E7,"Price")} -> 9.195 | F44: {=_FV(F7,"Price")} -> 208.71 | G44: {=_FV(G7,"Price")} -> 224.132 | H44: =IFERROR(AVERAGE(C44:G44),"") -> 272.2334 | I44: =SQRT((C44-H44)^2) -> 546.1566
B45: Average Target Price | C45: 534.57 | D45: 117.61 | E45: 13.48 | F45: 206.2 | G45: 201.28 | H45: =IFERROR(AVERAGE(C45:G45),"") -> 214.628 | I45: =SQRT((C45-H45)^2) -> 319.942
B46: Upside/Downside | C46: =C45/C44-1 -> -0.34680287 | D46: =D45/D44-1 -> 0.16746079 | E46: =E45/E44-1 -> 0.46601414 | F46: =F45/F44-1 -> -0.012026257 | G46: =G45/G44-1 -> -0.10195777 | H46: =IFERROR(AVERAGE(C46:G46),"") -> 0.034537606 | I46: =SQRT((C46-H46)^2) -> 0.38134047
B47: Extra | H47: =IFERROR(AVERAGE(C47:G47),"")
B48: 3y Operating Cash Flow | C48: =(Inputs!B59-Inputs!E59)/Inputs!E59 -> 1.9971159 | D48: 2.4 | E48: -4.2411 | F48: 11.66 | G48: 0.3843 | H48: =IFERROR(AVERAGE(C48:G48),"") -> 2.4400632 | I48: =SQRT((C48-H48)^2) -> 0.44294728
B49: R&D/Net Sales | C49: =C62/C10 -> 0.079352371 | D49: =D62/D10 -> 0 | E49: =E62/E10 -> 0 | F49: =F62/F10 -> 0.14896353 | G49: =G62/G10 -> 0.077779449 | H49: =IFERROR(AVERAGE(C49:G49),"") -> 0.061219069 | I49: =SQRT((C49-H49)^2) -> 0.018133302
B51: x | C51: =OP!E2 -> #VALUE! | D51: =D7 -> #VALUE! | E51: =E7 -> #VALUE! | F51: =F7 -> #VALUE! | G51: =G7 -> #VALUE!
B52: IS
B53: Net Sales (36m ago) | C53: ='Fin. Data'!E5 -> 24996 | D53: 65388 | E53: 10671 | F53: 386064 | G53: 274515
B54: Net Sales (12m ago) | C54: ='Fin. Data'!C5 -> 31616 | D54: 82722 | E54: 33817 | F54: 513983 | G54: 394328
B55: Net Sales (current) | C55: ='Fin. Data'!B5 -> 33723 | D55: 88935 | E55: 41321 | F55: 574785 | G55: 385706
B56: COGS | C56: ='Fin. Data'!B5-'Fin. Data'!B7 -> 19715 | D56: 58402 | E56: 24526 | F56: 480980 | G56: 212035
B57: EBITDA | C57: ='Fin. Data'!B19 -> 21508.3 | D57: 13209 | E57: 22367 | F57: 89402 | G57: 133477
B58: Operating Income | C58: ='Fin. Data'!B11 -> 6954 | D58: 9935 | E58: -886 | F58: 36852 | G58: 118658
B59: Net Financial Cost | C59: ='Fin. Data'!B14 -> -749 | D59: -1155 | E59: -2042 | F59: -233 | G59: =-183-382 -> -565
B60: Taxes | C60: ='Fin. Data'!B21 -> -797 | D60: -1687 | E60: 784 | F60: -7120 | G60: -17523
B61: Net Income | C61: ='Fin. Data'!B23 -> 5408 | D61: 2986 | E61: -3126 | F61: 30425 | G61: 100913
B62: R&D | C62: 2676 | D62: 0 | E62: 0 | F62: 85622 | G62: 30000
B63: BS
B64: Cash & Eq. | C64: ='Fin. Data'!B39 -> 7138 | D64: 14182 | E64: 3780 | F64: 86780 | G64: 61555
B65: Acc. Receivables | C65: ='Fin. Data'!B40 -> 1287 | D65: 10179 | E65: 6047 | F65: 52253 | G65: 29508
B66: Inventory | C66: ='Fin. Data'!B41 -> 0 | D66: 1963 | F66: 33318 | G66: 6331
B67: Current Assets | C67: =Inputs!B27 -> 9918 | D67: 32763 | E67: 14218 | F67: 172351 | G67: 143566
B68: Fixed Assets | C68: ='Fin. Data'!B42 -> 4423 | D68: 77551 | E68: 9042 | F68: 396801 | G68: 114599
B69: Total Assets | C69: ='Fin. Data'!B44 -> 48732 | D69: 205579 | E69: 122757 | F69: 527854 | G69: 352583
B70: Acc. Payable | C70: =Inputs!B43 -> 5214 | D70: 15125 | E70: 1260 | F70: 84981 | G70: 62611
B71: Current Liabilities | C71: =Inputs!B42 -> 8861 | D71: 31139 | E71: 15332 | F71: 164917 | G71: 145308
B72: Total Debt | C72: ='Fin. Data'!B58 -> 16572 | D72: 49895 | E72: 43669 | F72: 135611 | G72: 111088
B73: Total Equity | C73: ='Fin. Data'!B64 -> 20588 | D73: 113012 | E73: 46472 | F73: 201875 | G73: 62146
C103: {=_FV(C2,"Description")} -> The Walt Disney Company is a diversified worldwide entertainment company. The Company's segments include Entertainment, Sports and Experiences. The Entertainment segment generally encompasses the Company’s non-sports focused global film, television and direct-to-consumer (DTC) video streaming content production and distribution activities. Its line of business includes Linear Networks, Direct-to-Consumer, and Content Sales/Licensing. The Sports segment generally encompasses the Company’s sports-focused global television and DTC video streaming content production and distribution activities. Its line of business includes ESPN and Star. Experiences segment includes Parks and Experiences and Consumer Products. Parks and Experiences consists of Walt Disney World Resort in Florida, Disneyland Resort in California, Disney Cruise Line, Disney Vacation Club, and Disneyland Paris, among others. Consumer Products includes licensing of its trade names, characters, visual, literary and other IPs.

Sheet ESG
B1: Company GICS Sector: | T1: Yes
B2: Communication Services | C2: <- Select Industry | T2: No
B3: ESG Analysis | K3: Relative ESG Analysis
B4: Parameters | C4: Impact | D4: Do they report? | E4: Ranking | F4: Mitigation Plan | G4: Traffic Lights | H4: Improvement over time? | I4: Targets / Goals? | J4: Comments | K4: Parameters | L4: =Peers!C7 -> #VALUE! | M4: =Peers!D7 -> #VALUE! | N4: =Peers!E7 -> #VALUE! | O4: =Peers!F7 -> #VALUE! | P4: =Peers!G7 -> #VALUE! | Q4: =Peers!#REF! -> #REF! | R4: AVERAGE
B5: Environmental | K5: Ratios
A6: 1 | B6: CO2 Direct Emissions | C6: =VLOOKUP($B$2,'Sector Impact'!$K$4:$AA$16,A6+1,FALSE) -> Low | K6: CO2 Emissions/$M Sales | L6: =L12/L$11 -> 34.097483 | M6: =M12/M$11 -> 75.335919 | N6: =N12/N$11 -> 65.390479 | O6: =O12/O$11 -> 124.46393 | P6: =P12/P$11 -> 53.408555 | Q6: 0 | R6: =IFERROR(AVERAGE(L6:P6),"") -> 70.539273
A7: 2 | B7: Total Water Consumption | C7: =VLOOKUP($B$2,'Sector Impact'!$K$4:$AA$16,A7+1,FALSE) -> Low | K7: Water Consumption/$M Sales | L7: =L13/L$11 -> #VALUE! | M7: =M13/M$11 -> 340.50711 | N7: =N13/N$11 -> #VALUE! | O7: =O13/O$11 -> #VALUE! | P7: =P13/P$11 -> 13.870668 | Q7: 0 | R7: =IFERROR(AVERAGE(L7:P7),"")
A8: 3 | B8: Total Energy Consumption | C8: =VLOOKUP($B$2,'Sector Impact'!$K$4:$AA$16,A8+1,FALSE) -> Medium | D8: Yes | E8: Medium | F8: Yes | K8: Energy Consumption/$M Sales | L8: =L14/L$11 -> #VALUE! | M8: =M14/M$11 -> #VALUE! | N8: =N14/N$11 -> #VALUE! | O8: =O14/O$11 -> #VALUE! | P8: =P14/P$11 -> #VALUE! | Q8: 0 | R8: =IFERROR(AVERAGE(L8:P8),"")
A9: 4 | B9: Waste Management | C9: =VLOOKUP($B$2,'Sector Impact'!$K$4:$AA$16,A9+1,FALSE) -> Low | K9: Waste Production/$M Sales | L9: =L15/L$11 -> #VALUE! | M9: =M15/M$11 -> 1.7091134 | N9: =N15/N$11 -> #VALUE! | O9: =O15/O$11 -> 0.55846969 | P9: =P15/P$11 -> 0.13608811 | Q9: 0 | R9: =IFERROR(AVERAGE(L9:P9),"")
A10: 5 | B10: Land Degradation/Deforestation/Biodiversity loss/Animal sufering/… | C10: =VLOOKUP($B$2,'Sector Impact'!$K$4:$AA$16,A10+1,FALSE) -> Low | K10: Inputs
B11: Social | K11: Net Sales ($M) | L11: 33616 | M11: 88935 | N11: 41321 | O11: 574785 | P11: 385706
A12: 6 | B12: Employee Turnover % | C12: =VLOOKUP($B$2,'Sector Impact'!$K$4:$AA$16,A12+1,FALSE) -> Medium | D12: No | E12: "Best in class" | F12: No | J12: Their employee turnover is only 11% a year, which is below the 13% annual average for tech companies. | K12: CO2 Emissions Total (Tonnes) | L12: 1146221 | M12: 6700000 | N12: 2702000 | O12: 71540000 | P12: 20600000
A13: 7 | B13: Salaries & Compensation | C13: =VLOOKUP($B$2,'Sector Impact'!$K$4:$AA$16,A13+1,FALSE) -> Medium | D13: No | E13: Medium High | F13: No | J13: The company's employees rate the overall compensation and benefits package at 4.5 out of 5 stars. | K13: Water Consumption Total (Cubic Meters) | L13: N / A | M13: 30283000 | N13: N/A | O13: N / A | P13: 5350000
A14: 8 | B14: Reputation | C14: =VLOOKUP($B$2,'Sector Impact'!$K$4:$AA$16,A14+1,FALSE) -> Low | K14: Energy Consumption Total (Gigajoules) | L14: N / A | M14: N / A | N14: N / A | O14: N / A | P14: N / A
A15: 9 | B15: Discrimination Events | C15: =VLOOKUP($B$2,'Sector Impact'!$K$4:$AA$16,A15+1,FALSE) -> Low | F15: Yes | K15: Waste Production Total (Tonnes) | L15: N / A | M15: 152000 | N15: N / A | O15: 321000 | P15: 52490
A16: 10 | B16: Work Safety | C16: =VLOOKUP($B$2,'Sector Impact'!$K$4:$AA$16,A16+1,FALSE) -> High | D16: Yes | E16: Medium High | F16: Yes | I16: None | J16: Netflix employees rate work safety at 4.2 ou of 5 stars. | K16: ESG Scores
A17: 11 | B17: Damage to consumer health | C17: =VLOOKUP($B$2,'Sector Impact'!$K$4:$AA$16,A17+1,FALSE) -> Low | I17: None | K17: Refinitiv | L17: 40 | M17: 68 | N17: 60 | O17: 78 | P17: 80
A18: 12 | B18: PXP? | C18: =VLOOKUP($B$2,'Sector Impact'!$K$4:$AA$16,A18+1,FALSE) -> Low | K18: Sustainalytics | L18: 16.3 (Low risk) | M18: 15.7 (Low risk) | N18: 19.9 (Low risk) | O18: 30.5 (High risk) | P18: 17.2 (Low risk)
A19: 13 | B19: Supply chain | C19: =VLOOKUP($B$2,'Sector Impact'!$K$4:$AA$16,A19+1,FALSE) -> Low | I19: None | K19: ISS | L19: C- | M19: C | N19: D+ | O19: C- | P19: B
A20: 14 | B20: Community involvement | C20: =VLOOKUP($B$2,'Sector Impact'!$K$4:$AA$16,A20+1,FALSE) -> Low | K20: CDP | L20: F | M20: B | N20: N / A | O20: B | P20: A-
A21: 15 | B21: Public Sector | C21: =VLOOKUP($B$2,'Sector Impact'!$K$4:$AA$16,A21+1,FALSE) -> Low | I21: None
A22: 16 | B22: Litigation | C22: =VLOOKUP($B$2,'Sector Impact'!$K$4:$AA$16,A22+1,FALSE) -> Medium | D22: No | E22: Medium High | F22: No | I22: None | J22: Netflix was just the target of a lawsuit recently regarding account sharing, but won in court
B23: Corporate Governance | K23: PARAMETERS
A24: 17 | B24: Diversity (Gender, Age, Industry, Region) | E24: Medium | F24: No | I24: None | J24: The board is composed by 3 women,9 men, 1 black peaople and 11 white people. The average age is 66 years old. | K24: IMPACT | L24: RANKING | M24: MITIGATION PLAN | O24: TRAFFIC
A25: 18 | B25: % Independence | E25: Medium High | F25: No | I25: None | J25: 75% of the board is independent. | K25: Low | L25: "Best in class" | M25: Is there evidence of a plan/program ?
A26: 19 | B26: average time as independent directors | E26: Medium | F26: No | I26: None | J26: The average age of independent directors is 14 years old. | K26: Medium | L26: Medium High
A27: 20 | B27: Recent departures of directors / C-level executives? | E27: Medium High | F27: No | I27: None | K27: High | L27: Medium
A28: 21 | B28: CEO/Chairman duality | E28: "Best in class" | F28: No | I28: None | J28: The CEO and Chairman are not the same person. | K28: Very high | L28: "Villain"
A29: 22 | B29: Transparency (ESG, segments, acquisitions, other) | E29: Medium High | F29: No | I29: None
A30: 23 | B30: Time taken to report after the end of the quarter / year | E30: "Best in class" | F30: No | I30: None | J30: They took about 1 month to report their last year's anunal report.
A31: 24 | B31: Additional participation of the CEO in other boards or excessive participation of Ch. | E31: Medium | F31: No | I31: None | J31: 9 of the 12 board members are members of the board of directors part of other companies.
A32: 25 | B32: Audit / Consulting | D32: Yes | E32: Medium | F32: No | I32: None | J32: Netflix paid a lot of tax fees in the last year
A33: 26 | B33: ESG-compensation related | D33: No | E33: Medium | F33: No | I33: None
A34: 27 | B34: Management compensation schemes | D34: No | E34: Medium | F34: No | I34: None | J34: Netflix recognizes that they don't have wide support for our executive compensation model of the last 20 years.

Sheet DCF
A1: VALUATION MODEL
G3: Short Term | K3: Long Term
A4: Section | B4: Line # | C4: ITEM | D4: 2021 (Real) | E4: 2022 (Real) | F4: 2023 (Real) | G4: 2024 | H4: =G4+1 -> 2025 | I4: =H4+1 -> 2026 | J4: =I4+1 -> 2027 | K4: =J4+1 -> 2028 | L4: =K4+1 -> 2029 | M4: =L4+1 -> 2030 | N4: =M4+1 -> 2031 | O4: =N4+1 -> 2032 | ... AF4: =AE4+1 -> 2049
A5: INCOME STATEMENT | B5: 1 | C5: Growth | D5: ='Fin. Data'!D6 -> 0.1881101 | E5: =+E6/D6-1 -> 0.064583474 | F5: =+F6/E6-1 -> 0.066643472 | G5: =+G6/F6-1 -> 0.13345669 | H5: =+H6/G6-1 -> 0.13876535 | I5: =+I6/H6-1 -> 0.14407401 | J5: =+J6/I6-1 -> 0.14938268 | K5: =+K6/J6-1 -> 0.15469134 | L5: =+L6/K6-1 -> 0.16 | ... AF5: =+AF6/AE6-1 -> 0.02
B6: 2 | C6: Revenues/Sales | D6: =Inputs!D6 -> 29698 | E6: =Inputs!C6 -> 31616 | F6: =Inputs!B6 -> 33723 | G6: =Assumptions!C66 -> 38223.56 | H6: =Assumptions!D66 -> 43527.666 | I6: =Assumptions!E66 -> 49798.871 | J6: =Assumptions!F66 -> 57237.96 | K6: =Assumptions!G66 -> 66092.177 | L6: =Assumptions!H66 -> 76666.925 | M6: =Assumptions!I66 -> 87193.958 | N6: =Assumptions!J66 -> 97187.896 | ... AF6: =Assumptions!AB66 -> 155769.04
B7: 3 | C7: EBIT/Operating Margin | D7: =D8/D6 -> 0.20859991 | E7: =E8/E6 -> 0.17816928 | F7: =F8/F6 -> 0.20620941 | G7: =Assumptions!C77 -> 0.24 | H7: =Assumptions!D77 -> 0.242 | I7: =Assumptions!E77 -> 0.244 | J7: =Assumptions!F77 -> 0.246 | K7: =Assumptions!G77 -> 0.248 | L7: =Assumptions!H77 -> 0.25 | M7: =Assumptions!I77 -> 0.252 | N7: =Assumptions!J77 -> 0.254 | ... AF7: =Assumptions!AB77 -> 0.26
B8: 4 | C8: EBIT | D8: ='Fin. Data'!D11 -> 6195 | E8: ='Fin. Data'!C11 -> 5633 | F8: ='Fin. Data'!B11 -> 6954 | G8: =G7*G6 -> 9173.6544 | H8: =H7*H6 -> 10533.695 | I8: =I7*I6 -> 12150.925 | J8: =J7*J6 -> 14080.538 | K8: =K7*K6 -> 16390.86 | L8: =L7*L6 -> 19166.731 | M8: =M7*M6 -> 21972.877 | N8: =N7*N6 -> 24685.726 | ... AF8: =AF7*AF6 -> 40499.951
B9: 5a | C9: (Dep) | D9: -208 | E9: -337 | F9: -357 | G9: =$D$53*DCF!F40 -> -451.14636 | H9: =$D$53*DCF!G40 -> -508.35612 | I9: =$D$53*DCF!H40 -> -573.5046 | J9: =$D$53*DCF!I40 -> -648.03929 | K9: =$E$53*DCF!J40 -> -431.5927 | L9: =$E$53*DCF!K40 -> -460.68712 | M9: =$E$53*DCF!L40 -> -494.43666 | N9: =$E$53*DCF!M40 -> -532.82029 | O9: =$E$53*DCF!N40 -> -575.60335 | P9: =$E$53*DCF!O40 -> -622.31929 | Q9: =$E$53*DCF!P40 -> -672.26959 | R9: =$E$53*DCF!Q40 -> -723.2189 | ... AF9: =$E$53*DCF!AE40 -> -1553.3572 | AG9: =SUM(D9:AF9) -> -23680.307
B10: 5b | C10: (Amort) | D10: -12230 | E10: -14026 | F10: -14197 | G10: =F38*$D$54 -> -13006.713 | H10: =G38*$D$54 -> -14209.072 | I10: =H38*$D$54 -> -15522.579 | J10: =I38*$D$54 -> -16957.508 | K10: =J38*$E$54 -> -13526.871 | L10: =K38*$E$54 -> -14439.935 | M10: =L38*$E$54 -> -15414.631 | N10: =M38*$E$54 -> -16455.118 | O10: =N38*$E$54 -> -17565.839 | P10: =O38*$E$54 -> -18751.533 | Q10: =P38*$E$54 -> -20017.262 | R10: =Q38*$E$54 -> -21368.427 | ... AF10: =AE38*$E$54 -> -53324.024
B11: 5c | C11: (Stock based compensation) | D11: =D20 -> -403 | E11: =E20 -> -575 | F11: =F20 -> -339 | G11: =G6*$D$55 -> -322.42626 | H11: =H6*$D$55 -> -367.16785 | I11: =I6*$D$55 -> -420.06719 | J11: =J6*$D$55 -> -482.81796 | K11: =K6*$D$55 -> -557.50571 | L11: =L6*$D$55 -> -646.70663 | M11: =M6*$D$55 -> -735.50505 | N11: =N6*$D$55 -> -819.80667 | ... AF11: =AF6*$D$55 -> -1313.9548
B12: 6 | C12: EBITDA | D12: =D8-D9-D10 -> 18633 | E12: =E8-E9-E10 -> 19996 | F12: =F8-F9-F10 -> 21508 | G12: =G8-G9-G10 -> 22631.514 | H12: =H8-H9-H10 -> 25251.123 | I12: =I8-I9-I10 -> 28247.008 | J12: =J8-J9-J10 -> 31686.086 | K12: =K8-K9-K10 -> 30349.324 | ... AF12: =AF8-AF9-AF10 -> 95377.333
B13: 7 | C13: (Net financing cost) | D13: ='Fin. Data'!D14 -> -354 | E13: ='Fin. Data'!C14 -> -369 | F13: ='Fin. Data'!B14 -> -749 | G13: =F43*$D$58-F44*$D$57 -> -507.70461 | H13: =G43*$D$58-G44*$D$57 -> -187.74073 | I13: =H43*$D$58-H44*$D$57 -> 126.97657 | J13: =I43*$D$58-I44*$D$57 -> 488.84954 | K13: =J43*$E$58-J44*$E$57 -> 912.05123 | L13: =K43*$E$58-K44*$E$57 -> 1171.1603 | M13: =L43*$E$58-L44*$E$57 -> 1431.2667 | N13: =M43*$E$58-M44*$E$57 -> 1713.2226 | O13: =N43*$E$58-N44*$E$57 -> 2024.8916 | P13: =O43*$E$58-O44*$E$57 -> 2368.9001 | Q13: =P43*$E$58-P44*$E$57 -> 2747.9897 | R13: =Q43*$E$58-Q44*$E$57 -> 3179.7221 | ... AF13: =AE43*$E$58-AE44*$E$57 -> 13023.284
B14: 8 | C14: Other income/(cost) | D14: ='Fin. Data'!D15 -> 254 | E14: ='Fin. Data'!C15 -> 369 | F14: ='Fin. Data'!B15 -> 0 | G14: =AVERAGE(D14:F14)*(1+G5) -> 235.38117 | H14: =AVERAGE(E14:G14)*(1+H5) -> 229.41611 | I14: =AVERAGE(F14:H14)*(1+I5) -> 177.25417 | J14: =AVERAGE(G14:I14)*(1+J5) -> 245.98761 | K14: =AVERAGE(H14:J14)*(1+K5) -> 251.20614 | L14: =AVERAGE(I14:K14)*(1+L5) -> 260.78652 | M14: =AVERAGE(J14:L14)*(1+M5) -> 287.35251 | N14: =AVERAGE(K14:M14)*(1+N5) -> 296.98799 | ... AF14: =AVERAGE(AC14:AE14)*(1+AF5) -> 366.84506
B15: 9 | C15: Earnings before taxes | D15: =D8+D13+D14 -> 6095 | E15: =E8+E13+E14 -> 5633 | F15: =F8+F13+F14 -> 6205 | G15: =G8+G13+G14 -> 8901.331 | H15: =H8+H13+H14 -> 10575.371 | I15: =I8+I13+I14 -> 12455.155 | J15: =J8+J13+J14 -> 14815.375 | K15: =K8+K13+K14 -> 17554.117 | ... AF15: =AF8+AF13+AF14 -> 53890.08
B16: 10 | C16: (Income tax) | D16: ='Fin. Data'!D21 -> -979 | E16: ='Fin. Data'!C21 -> -1141 | F16: ='Fin. Data'!B21 -> -797 | G16: =-$D$56*G15 -> -1484.0209 | H16: =-$D$56*H15 -> -1763.115 | I16: =-$D$56*I15 -> -2076.5109 | J16: =-$D$56*J15 -> -2470.0043 | K16: =-$E$56*K15 -> -3159.7411 | L16: =-$E$56*L15 -> -3707.762 | M16: =-$E$56*M15 -> -4264.4694 | N16: =-$E$56*N15 -> -4805.2685 | O16: =-$E$56*O15 -> -5309.9507 | P16: =-$E$56*P15 -> -5753.1386 | Q16: =-$E$56*Q15 -> -5967.6656 | R16: =-$E$56*R15 -> -6154.7284 | ... AF16: =-$E$56*AF15 -> -9700.2144
B17: 11 | C17: Net income | D17: ='Fin. Data'!D23 -> 5116 | E17: ='Fin. Data'!C23 -> 4492 | F17: ='Fin. Data'!B23 -> 5408 | G17: =G16+G15 -> 7417.3101 | H17: =H16+H15 -> 8812.2555 | I17: =I16+I15 -> 10378.644 | J17: =J16+J15 -> 12345.371 | K17: =K16+K15 -> 14394.376 | L17: =L16+L15 -> 16890.916 | M17: =M16+M15 -> 19427.027 | N17: =N16+N15 -> 21890.668 | ... AF17: =AF16+AF15 -> 44189.866
A19: CASH FLOW STATEMENT | B19: 12 | C19: Operating cash flows before WK | D19: =392.6+403+242 -> 1037.6 | E19: =2026.3+575+758 -> 3359.3 | F19: =7274.3+339+116 -> 7729.3 | G19: =(G17-G10-G9-G11)*(1+$D$59) -> 10233.081 | H19: =(H17-H10-H9-H11)*(1+$D$59) -> 11536.139 | I19: =(I17-I10-I9-I11)*(1+$D$59) -> 12983.388 | J19: =(J17-J10-J9-J11)*(1+$D$59) -> 14691.802 | K19: =(K17-K10-K9-K11)*(1+$E$59) -> 11388.205 | L19: =(L17-L10-L9-L11)*(1+$E$59) -> 12777.896 | M19: =(M17-M10-M9-M11)*(1+$E$59) -> 14209.127 | N19: =(N17-N10-N9-N11)*(1+$E$59) -> 15637.781 | O19: =(O17-O10-O9-O11)*(1+$E$59) -> 17027.501 | P19: =(P17-P10-P9-P11)*(1+$E$59) -> 18332.679 | Q19: =(Q17-Q10-Q9-Q11)*(1+$E$59) -> 19243.454 | R19: =(R17-R10-R9-R11)*(1+$E$59) -> 20139.142 | ... AF19: =(AF17-AF10-AF9-AF11)*(1+$E$59) -> 39541.613
B20: 13 | C20: (Stock-based compensation) | D20: -403 | E20: -575 | F20: -339 | G20: =G11 -> -322.42626 | H20: =H11 -> -367.16785 | I20: =I11 -> -420.06719 | J20: =J11 -> -482.81796 | K20: =K11 -> -557.50571 | L20: =L11 -> -646.70663 | M20: =M11 -> -735.50505 | N20: =N11 -> -819.80667 | ... AF20: =AF11 -> -1313.9548
B21: 14 | C21: (Working Capital Flows) | D21: =Inputs!D62 -> -242 | E21: =Inputs!C62 -> -758.1 | F21: =Inputs!B62 -> -116.1 | G21: =$D$60*(G6-F6) -> -448.75806 | H21: =$D$60*(H6-G6) -> -528.8809 | I21: =$D$60*(I6-H6) -> -625.31197 | J21: =$D$60*(J6-I6) -> -741.76347 | K21: =$E$60*(K6-J6) -> -882.86815 | L21: =$E$60*(L6-K6) -> -1054.4251 | M21: =$E$60*(M6-L6) -> -1049.6673 | N21: =$E$60*(N6-M6) -> -996.5116 | O21: =$E$60*(O6-N6) -> -890.83275 | P21: =$E$60*(P6-O6) -> -732.61291 | Q21: =$E$60*(Q6-P6) -> -226.28413 | R21: =$E$60*(R6-Q6) -> -230.80982 | ... AF21: =$E$60*(AF6-AE6) -> -304.54865
B22: 15 | C22: -Total Operating Cash Flow | D22: =D19+D20+D21 -> 392.6 | E22: =E19+E20+E21 -> 2026.2 | F22: =F19+F20+F21 -> 7274.2 | G22: =G19+G20+G21 -> 9461.8962 | H22: =H19+H20+H21 -> 10640.09 | I22: =I19+I20+I21 -> 11938.009 | J22: =J19+J20+J21 -> 13467.22 | K22: =K19+K20+K21 -> 9947.8313 | ... AF22: =AF19+AF20+AF21 -> 37923.11
B23: 16 | C23: (CAPEX) | D23: ='Fin. Data'!D32 -> -524.6 | E23: ='Fin. Data'!C32 -> -407.7 | F23: ='Fin. Data'!B32 -> -348.6 | G23: =G6*$D$62 -> -560.87951 | H23: =H6*$D$62 -> -638.71015 | I23: =I6*$D$62 -> -730.73169 | J23: =J6*$D$62 -> -839.89034 | K23: =K6*$E$62 -> -484.90705 | L23: =L6*$E$62 -> -562.49218 | M23: =M6*$E$62 -> -639.72723 | N23: =N6*$E$62 -> -713.05105 | O23: =O6*$E$62 -> -778.59897 | P23: =P6*$E$62 -> -832.505 | Q23: =Q6*$E$62 -> -849.1551 | R23: =R6*$E$62 -> -866.1382 | ... AF23: =AF6*$E$62 -> -1142.851 | AG23: =SUM(D23:AF23) -> -23890.037
B24: 17 | C24: Adq | D24: =Inputs!D66 -> -788.3 | E24: ='Fin. Data'!C33 -> -1668.7 | F24: ='Fin. Data'!B33 -> -504.9 | G24: =G6*$D$63 -> -720.86645 | H24: =H6*$D$63 -> -820.89774 | I24: =I6*$D$63 -> -939.16778 | J24: =J6*$D$63 -> -1079.4632 | K24: =K6*$E$63 -> -623.22339 | L24: =L6*$E$63 -> -722.93913 | M24: =M6*$E$63 -> -822.20493 | N24: =N6*$E$63 -> -916.44386 | O24: =O6*$E$63 -> -1000.6889 | P24: =P6*$E$63 -> -1069.9712 | Q24: =Q6*$E$63 -> -1091.3706 | R24: =R6*$E$63 -> -1113.198 | ... AF24: =AF6*$E$63 -> -1468.8412 | AH24: =AG9-AG23 -> 209.73043
B25: 18 | C25: (Other investing flows) | D25: =Inputs!D67 -> -27 | E25: =Inputs!C67 -> 0 | F25: =Inputs!B67 -> 1395.3 | G25: =(1+G5)*AVERAGE(D25:F25) -> 516.9696 | H25: =(1+H5)*AVERAGE(E25:G25) -> 725.87545 | I25: =(1+I5)*AVERAGE(F25:H25) -> 1006.0777 | J25: =(1+J5)*AVERAGE(G25:I25) -> 861.6243 | K25: =(1+K5)*AVERAGE(H25:J25) -> 998.26049 | L25: =(1+L5)*AVERAGE(I25:K25) -> 1108.1722 | M25: =(1+M5)*AVERAGE(J25:L25) -> 1125.199 | N25: =(1+N5)*AVERAGE(K25:M25) -> 1200.6775 | ... AF25: =(1+AF5)*AVERAGE(AC25:AE25) -> 1479.2528
B26: 19 | C26: -Total Investing Flows | D26: =D23+D24+D25 -> -1339.9 | E26: =E23+E24+E25 -> -2076.4 | F26: =F23+F24+F25 -> 541.8 | G26: =G23+G24+G25 -> -764.77637 | H26: =H23+H24+H25 -> -733.73244 | I26: =I23+I24+I25 -> -663.82173 | J26: =J23+J24+J25 -> -1057.7292 | K26: =K23+K24+K25 -> -109.86995 | ... AF26: =AF23+AF24+AF25 -> -1132.4393
B27: 20 | C27: (Flows related to leases) | D27: =Inputs!D71+Inputs!D72 -> 0 | E27: =Inputs!C71+Inputs!C72 -> 0 | F27: =Inputs!B71+Inputs!B72 -> 0 | G27: =$D$66*G6 -> 0 | H27: =$D$66*H6 -> 0 | I27: =$D$66*I6 -> 0 | J27: =$D$66*J6 -> 0 | K27: =$E$66*K6 -> 0 | L27: =$E$66*L6 -> 0 | M27: =$E$66*M6 -> 0 | N27: =$E$66*N6 -> 0 | O27: =$E$66*O6 -> 0 | P27: =$E$66*P6 -> 0 | Q27: =$E$66*Q6 -> 0 | R27: =$E$66*R6 -> 0 | ... AF27: =$E$66*AF6 -> 0
B28: 21 | C28: Flows related to debt | D28: =+SUM(Inputs!D69:D70) -> 0 | E28: =+SUM(Inputs!C69:C70) -> 0 | F28: =+SUM(Inputs!B69:B70) -> 0 | G28: =G44-F44 -> -5256.2431 | H28: =H44-G44 -> 1309.8048 | I28: =I44-H44 -> 1497.9424 | J28: =J44-I44 -> 1719.5387 | K28: =K44-J44 -> -668.38087 | L28: =L44-K44 -> 1859.0148 | M28: =M44-L44 -> 1907.2956 | N28: =N44-M44 -> 1895.8597 | ... AF28: =AF44-AE44 -> 2116.56
B29: 22 | C29: (Repurchases)/Issuance of stock | D29: ='Fin. Data'!D28 -> -600 | E29: ='Fin. Data'!C28 -> 0 | F29: ='Fin. Data'!B28 -> -6045.3 | G29: =-G17*$D$65 -> -1483.462 | H29: =-H17*$D$65 -> -1762.4511 | I29: =-I17*$D$65 -> -2075.7289 | J29: =-J17*$D$65 -> -2469.0742 | K29: =-K17*$E$65 -> -3555.7652 | L29: =-L17*$E$65 -> -4172.472 | M29: =-M17*$E$65 -> -4798.9539 | N29: =-N17*$E$65 -> -5407.5337 | O29: =-O17*$E$65 -> -5975.4699 | P29: =-P17*$E$65 -> -6474.2045 | Q29: =-Q17*$E$65 -> -6715.619 | R29: =-R17*$E$65 -> -6926.1273 | ... AF29: =-AF17*$E$65 -> -10915.984
B30: 23 | C30: (Dividends) | D30: ='Fin. Data'!D27 -> 0 | E30: ='Fin. Data'!C27 -> 0 | F30: ='Fin. Data'!B27 -> 0 | G30: =-$D$64*G17 -> 0 | H30: =-$D$64*H17 -> 0 | I30: =-$D$64*I17 -> 0 | J30: =-$D$64*J17 -> 0 | K30: =-$E$64*K17 -> 0 | L30: =-$E$64*L17 -> 0 | M30: =-$E$64*M17 -> 0 | N30: =-$E$64*N17 -> 0 | O30: =-$E$64*O17 -> 0 | P30: =-$E$64*P17 -> 0 | Q30: =-$E$64*Q17 -> 0 | R30: =-$E$64*R17 -> 0 | ... AF30: =-$E$64*AF17 -> 0
B31: 24 | C31: Other financing flows | D31: =Inputs!D75 -> -549.8 | E31: =Inputs!C75 -> -664.3 | F31: =Inputs!B75 -> 94.5 | G31: =(1+G5)*AVERAGE(D31:F31) -> -423.00604 | H31: =(1+H5)*AVERAGE(E31:G31) -> -376.85771 | I31: =(1+I5)*AVERAGE(F31:H31) -> -268.99611 | J31: =(1+J5)*AVERAGE(G31:I31) -> -409.50967 | K31: =(1+K5)*AVERAGE(H31:J31) -> -406.20636 | L31: =(1+L5)*AVERAGE(I31:K31) -> -419.42202 | M31: =(1+M5)*AVERAGE(J31:L31) -> -468.2444 | N31: =(1+N5)*AVERAGE(K31:M31) -> -480.72434 | ... AF31: =(1+AF5)*AVERAGE(AC31:AE31) -> -594.5432
B32: 25 | C32: -Total Financing flows | D32: =D27+D28+D29+D30+D31 -> -1149.8 | E32: =E27+E28+E29+E30+E31 -> -664.3 | F32: =F27+F28+F29+F30+F31 -> -5950.8 | G32: =G27+G28+G29+G30+G31 -> -7162.7111 | H32: =H27+H28+H29+H30+H31 -> -829.50405 | I32: =I27+I28+I29+I30+I31 -> -846.78262 | J32: =J27+J28+J29+J30+J31 -> -1159.0451 | K32: =K27+K28+K29+K30+K31 -> -4630.3524 | ... AF32: =AF27+AF28+AF29+AF30+AF31 -> -9393.9677
A34: SUMMARY | B34: 26 | C34: Cash before shareholder returns | D34: =D22+D26+D27+D28+D31 -> -1497.1 | E34: =E22+E26+E27+E28+E31 -> -714.5 | F34: =F22+F26+F27+F28+F31 -> 7910.5 | G34: =G22+G26+G27+G28+G31 -> 3017.8708 | H34: =H22+H26+H27+H28+H31 -> 10839.305 | I34: =I22+I26+I27+I28+I31 -> 12503.133 | J34: =J22+J26+J27+J28+J31 -> 13719.52 | K34: =K22+K26+K27+K28+K31 -> 8763.3741 | ... AF34: =AF22+AF26+AF27+AF28+AF31 -> 38312.687
B35: 27 | C35: Returns to shareholders | D35: =-1*(D29+D30) -> 600 | E35: =-1*(E29+E30) -> 0 | F35: =-1*(F29+F30) -> 6045.3 | G35: =-1*(G29+G30) -> 1483.462 | H35: =-1*(H29+H30) -> 1762.4511 | I35: =-1*(I29+I30) -> 2075.7289 | J35: =-1*(J29+J30) -> 2469.0742 | K35: =-1*(K29+K30) -> 3555.7652 | ... AF35: =-1*(AF29+AF30) -> 10915.984
B36: 28 | C36: Excess cash acumulation | D36: =D34-D35 -> -2097.1 | E36: =E34-E35 -> -714.5 | F36: =F34-F35 -> 1865.2 | G36: =G34-G35 -> 1534.4088 | H36: =H34-H35 -> 9076.8535 | I36: =I34-I35 -> 10427.404 | J36: =J34-J35 -> 11250.446 | K36: =K34-K35 -> 5207.6089 | ... AF36: =AF34-AF35 -> 27396.703
A38: BALANCE SHEET | B38: 29 | C38: Intangible assets | D38: 30920 | E38: 32737 | F38: 31658 | G38: =+(F38+(-G10*$D$61)) -> 34584.51 | H38: =+(G38+(-H10*$D$61)) -> 37781.552 | I38: =+(H38+(-I10*$D$61)) -> 41274.132 | J38: =+(I38+(-J10*$D$61)) -> 45089.571 | K38: =+(J38+(-K10*$E$61)) -> 48133.117 | L38: =+(K38+(-L10*$E$61)) -> 51382.103 | M38: =+(L38+(-M10*$E$61)) -> 54850.395 | N38: =+(M38+(-N10*$E$61)) -> 58552.796 | O38: =+(N38+(-O10*$E$61)) -> 62505.11 | P38: =+(O38+(-P10*$E$61)) -> 66724.205 | Q38: =+(P38+(-Q10*$E$61)) -> 71228.089 | R38: =+(Q38+(-R10*$E$61)) -> 76035.985 | ... AF38: =+(AE38+(-AF10*$E$61)) -> 189744.65 | AG38: =SUM(G38:AF38) -> 2446423.1
B39: 30 | C39: Accumulated amortization | D39: 16859 | E39: 17741 | F39: 18660 | G39: =F39-(G10*$D$61) -> 21586.51 | H39: =G39-(H10*$D$61) -> 24783.552 | I39: =H39-(I10*$D$61) -> 28276.132 | J39: =I39-(J10*$D$61) -> 32091.571 | K39: =J39-(K10*$D$61) -> 35135.117 | L39: =K39-(L10*$D$61) -> 38384.103 | M39: =L39-(M10*$D$61) -> 41852.395 | N39: =M39-(N10*$D$61) -> 45554.796 | ... AF39: =AE39-(AF10*$D$61) -> 176746.65 | AG39: =SUM(G39:AF39) -> 2108475.1
B40: 31 | C40: PPE+Right of use Assets | D40: 4386 | E40: 4379 | F40: 4423 | G40: =F40+(-G23) -> 4983.8795 | H40: =G40+(-H23) -> 5622.5897 | I40: =H40+(-I23) -> 6353.3213 | J40: =I40+(-J23) -> 7193.2117 | K40: =J40+(-K23) -> 7678.1187 | L40: =K40+(-L23) -> 8240.6109 | M40: =L40+(-M23) -> 8880.3381 | N40: =M40+(-N23) -> 9593.3892 | ... AF40: =AE40+(-AF23) -> 27032.137 | AG40: =SUM(G40:AF40) -> 387279.6
B41: 32 | C41: Accumulated depreciation | D41: 616 | E41: 754 | F41: 855 | G41: =F41-G9 -> 1306.1464 | H41: =G41-H9 -> 1814.5025 | I41: =H41-I9 -> 2388.0071 | J41: =I41-J9 -> 3036.0464 | K41: =J41-K9 -> 3467.6391 | L41: =K41-L9 -> 3928.3262 | M41: =L41-M9 -> 4422.7629 | N41: =M41-N9 -> 4955.5831 | ... AF41: =AE41-AF9 -> 23633.307 | AG41: =SUM(G41:AF41) -> 264090.49
A43: CASH & DEBT & DISCOUNTING | B43: 33 | C43: Ending cash balance | D43: ='Fin. Data'!D39 -> 6028 | E43: =E36+D43 -> 5313.5 | F43: =F36+E43 -> 7178.7 | G43: =G36+F43 -> 8713.1088 | H43: =H36+G43 -> 17789.962 | I43: =I36+H43 -> 28217.367 | J43: =J36+I43 -> 39467.813 | K43: =K36+J43 -> 44675.422 | L43: =L36+K43 -> 52842.047 | ... AF43: =AF36+AE43 -> 381104.81
B44: 34 | C44: Total Debt | D44: ='Fin. Data'!D58 -> 17416 | E44: ='Fin. Data'!C58 -> 16932 | F44: ='Fin. Data'!B58 -> 16572 | G44: =G12*$D$68 -> 11315.757 | H44: =H12*$D$68 -> 12625.562 | I44: =I12*$D$68 -> 14123.504 | J44: =J12*$D$68 -> 15843.043 | K44: =K12*$E$68 -> 15174.662 | L44: =L12*$E$68 -> 17033.677 | M44: =M12*$E$68 -> 18940.972 | N44: =N12*$E$68 -> 20836.832 | O44: =O12*$E$68 -> 22654.336 | P44: =P12*$E$68 -> 24324.467 | Q44: =Q12*$E$68 -> 25390.796 | R44: =R12*$E$68 -> 26392.774 | ... AF44: =AF12*$E$68 -> 47688.666
B45: 35 | C45: Discount factor | F45: =1/((1+$F$50)^G50) -> 1 | G45: =1/((1+$F$50)^G49) -> 0.91911765 | H45: =1/((1+$F$50)^H49) -> 0.84477725 | I45: =1/((1+$F$50)^I49) -> 0.77644968 | J45: =1/((1+$F$50)^J49) -> 0.7136486 | K45: =1/((1+$F$50)^K49) -> 0.65592702 | L45: =1/((1+$F$50)^L49) -> 0.6028741 | M45: =1/((1+$F$50)^M49) -> 0.55411223 | N45: =1/((1+$F$50)^N49) -> 0.50929433 | ... AF45: =1/((1+$F$50)^AF49) -> 0.11159602
B46: 36 | C46: DF + 0.1% | E46: +0.1% | F46: =1/((1+$F$50+0.001)^G50) -> 1 | G46: =1/((1+$F$50+0.001)^G49) -> 0.91827365 | H46: =1/((1+$F$50+0.001)^H49) -> 0.84322649 | I46: =1/((1+$F$50+0.001)^I49) -> 0.77431266 | J46: =1/((1+$F$50+0.001)^J49) -> 0.71103091 | K46: =1/((1+$F$50+0.001)^K49) -> 0.65292095 | L46: =1/((1+$F$50+0.001)^L49) -> 0.5995601 | M46: =1/((1+$F$50+0.001)^M49) -> 0.55056024 | N46: =1/((1+$F$50+0.001)^N49) -> 0.50556496 | ... AF46: =1/((1+$F$50+0.001)^AF49) -> 0.10896202
B47: 37 | C47: DF+0.5% | E47: +0.5% | F47: =1/((1+$F$50+0.005)^G50) -> 1 | G47: =1/((1+$F$50+0.005)^G49) -> 0.91491308 | H47: =1/((1+$F$50+0.005)^H49) -> 0.83706595 | I47: =1/((1+$F$50+0.005)^I49) -> 0.76584259 | J47: =1/((1+$F$50+0.005)^J49) -> 0.7006794 | K47: =1/((1+$F$50+0.005)^K49) -> 0.64106075 | L47: =1/((1+$F$50+0.005)^L49) -> 0.58651487 | M47: =1/((1+$F$50+0.005)^M49) -> 0.53661013 | N47: =1/((1+$F$50+0.005)^N49) -> 0.49095163 | ... AF47: =1/((1+$F$50+0.005)^AF49) -> 0.09905486
A49: Discount Rate | C49: Risk free rate | D49: Equity premium | E49: Firm premium | F49: Total | G49: 1 | H49: 2 | I49: 3 | J49: 4 | K49: 5 | L49: 6 | M49: 7 | N49: 8 | O49: 9 | P49: 10 | Q49: 11 | R49: 12 | S49: 13 | T49: 14 | U49: 15 | V49: 16 | W49: 17 | X49: 18 | Y49: 19 | Z49: 20 | AA49: 21 | AB49: 22 | AC49: 23 | AD49: 24 | AE49: 25 | AF49: 26
C50: 0.04 | D50: 0.045 | E50: 0.003 | F50: =E50+D50+C50 -> 0.088 | G50: 0
A52: Modelling factors | D52: Short Term | E52: Long Term | F52: Reference (line)
C53: Depreciation factor | D53: =Assumptions!K36 -> -0.10200008 | E53: =Assumptions!L36 -> -0.06 | F53: % PPE
C54: Amortization factor | D54: =Assumptions!K37 -> -0.41085075 | E54: =Assumptions!L37 -> -0.3 | F54: % IA
C55: Stock-based comp | D55: =Assumptions!K38 -> -0.0084352754 | E55: =Assumptions!L38 -> -0.0084352754 | F55: % revenue
C56: Tax Rate | D56: =Assumptions!K39 -> 0.16671899 | E56: =Assumptions!L39 -> 0.18 | F56: % (line 9)
C57: Interest Rate on debt | D57: =Assumptions!K40 -> 0.0487 | E57: =Assumptions!L40 -> 0.0503 | F57: % debt (l29)
C58: Interest Rate on cash | D58: =Assumptions!K41 -> 0.0417 | E58: =Assumptions!L41 -> 0.0433 | F58: % of cash (l28)
C59: Operanting CF before WC | D59: =Assumptions!K42 -> -0.51725278 | E59: =Assumptions!L42 -> -0.60608548 | F59: Decreasing with addictions to content
C60: Working capital flows | D60: =Assumptions!K43 -> -0.099711604 | E60: =Assumptions!L43 -> -0.099711604 | F60: % of change revenues (l2)
C61: Intangible Assets | D61: =Assumptions!K44 -> 0.225 | E61: =Assumptions!L44 -> 0.225 | F61: Growing with amortization
C62: Capex | D62: =Assumptions!K45 -> -0.01467366 | E62: =Assumptions!L45 -> -0.0073368298 | F62: % revenue (l2)
C63: Acquisition factor | D63: =Assumptions!K46 -> -0.018859218 | E63: =Assumptions!L46 -> -0.009429609 | F63: % revenue (l2)
C64: Dividends | D64: =Assumptions!K47 -> 0 | E64: =Assumptions!L47 -> 0 | F64: % net income (11)
C65: Repurchases | D65: =-Assumptions!K48 -> 0.2 | E65: =-Assumptions!L48 -> 0.24702461 | F65: % net income (11)
C66: Leases | D66: =Assumptions!K49 -> 0 | E66: =Assumptions!L49 -> 0 | F66: % revenue (l2)
C67: Cash Costs for EBIT | F67: % revenue (l2)
C68: Total Debt | D68: =Assumptions!K51 -> 0.5 | E68: =Assumptions!L51 -> 0.5 | F68: % EBITDA
A70: Valuation | D70: $ millions
C71: Value of flows | D71: =SUMPRODUCT(G35:AF35,G45:AF45)+((AF43-AF44)*AF45) -> 88765.678 | E71: =D71/D73 -> 0.58536604
C72: Value of perpetuity | D72: =(AF34/(F50-AF5))*AF45 -> 62875.641 | E72: =D72/D73 -> 0.41463396
C73: Total Value | D73: =D71+D72 -> 151641.32
C74: Actual share price | D74: =OP!C20 -> 818.39
C75: Total value vs Mkt Cap | D75: =D76/D74-1 -> -0.56652537
C76: Estimated NPV per share | D76: =D73*1000000/OP!C21 -> 354.75131
A78: Sensibility | C78: Sensitivity +0.1% | D78: =(SUMPRODUCT(G35:AF35,G45:AF45)+((AF43-AF44)*AF45)+(AF34/(F50+0.001-AF5))*AF45)*1000000/OP!C21 -> 352.61954 | E78: =D78/D76-1 -> -0.0060091879
C79: Sensitivity +0.5% | D79: =(SUMPRODUCT(G35:AF35,G45:AF45)+((AF43-AF44)*AF45)+(AF34/(F50+0.005-AF5))*AF45)*1000000/OP!C21 -> 344.67651 | E79: =D79/D76-1 -> -0.028399586
A81: Notes

Sheet Assumptions
B2: Assumptions
B4: Prospects:
B6: Links:
C8: 2023 | D8: =C8-1 -> 2022 | E8: =D8-1 -> 2021 | F8: =E8-1 -> 2020 | G8: =F8-1 -> 2019 | I8: Average | K8: Short Term Forecast | L8: Long Term Forecast
B9: Revenue growth | C9: =(Inputs!B6-Inputs!C6)/Inputs!C6 -> 0.066643472 | D9: =(Inputs!C6-Inputs!D6)/Inputs!D6 -> 0.064583474 | E9: =(Inputs!D6-Inputs!E6)/Inputs!E6 -> 0.1881101 | F9: =(Inputs!E6-Inputs!F6)/Inputs!F6 -> 0.24012701 | G9: =(Inputs!F6-Inputs!G6)/Inputs!G6 -> 0.27618083 | I9: =AVERAGE(C9:G9) -> 0.16712898
B10: Operating Margin | C10: =Inputs!B8/Inputs!B6 -> 0.20620941 | D10: =Inputs!C8/Inputs!C6 -> 0.17816928 | E10: =Inputs!D8/Inputs!D6 -> 0.20859991 | F10: =Inputs!E8/Inputs!E6 -> 0.18342935 | G10: =Inputs!F8/Inputs!F6 -> 0.1291923 | I10: =AVERAGE(C10:G10) -> 0.18112005
B12: Tax rate | C12: =+C14/C13 -> 0.1284448 | D12: =+D14/D13 -> 0.21675532 | E12: =+E14/E13 -> 0.16763699 | F12: =+F14/F13 -> 0.16411379 | G12: =+G14/G13 -> 0.15664403
B13: Net Income before Taxes | C13: 6205 | D13: 5264 | E13: 5840 | F13: 3199 | G13: 2062
B14: Income taxes | C14: 797 | D14: 1141 | E14: 979 | F14: 525 | G14: 323
B16: Aa2/AA(current level)
B17: Default spread | I17: 0.007
B18: 30Y US Bond Yield | I18: 0.0433
B19: 5Y US Bond Yield | I19: 0.0417
B20: Country default spread (US) | I20: 0
B21: Short-term cost debt | I21: =I17+I19+I20 -> 0.0487
B22: Long-term cost of debt | I22: =I20+I18+I17 -> 0.0503
B24: Segments | C24: Weight | D24: Country Risk Premium | F24: Equity Risk Premium
B25: =Segments!C5 -> United States and Canada (UCAN) | C25: =Segments!B5 -> 0.4435 | D25: 0 | F25: 0.046
B26: =Segments!C6 -> Europe, Middle East and Africa (EMEA) | C26: =Segments!B6 -> 0.313 | D26: =+(0.88+0.72+0)/300 -> 0.0053333333 | F26: =+(5.48+4.6+5.32)/300 -> 0.051333333
B27: =Segments!C7 -> Latin America (LATAM) | C27: =Segments!B7 -> 0.1318 | D27: =+(4.4+2.78)/200 -> 0.0359 | F27: =+(9+7.38)/200 -> 0.0819
B28: =Segments!C8 -> Asia-Pacific (APAC) | C28: =Segments!B8 -> 0.1116 | D28: =+(3.21+1.03+0)/300 -> 0.014133333 | F28: =+(7.81+5.63+4.6)/300 -> 0.060133333
B29: Total | C29: =SUM(C25:C27) -> 0.8883 | D29: =D25*C25+C26*D26+C27*D27+C28*D28 -> 0.0079782333 | F29: =F25*C25+C26*F26+C27*F27+C28*F28 -> 0.053973633
B32: Modelling Factors
C34: Last 5 Years
C35: =C8 -> 2023 | D35: =D8 -> 2022 | E35: =E8 -> 2021 | F35: =F8 -> 2020 | G35: =G8 -> 2019 | I35: Average | K35: Short Term Forecast | L35: Long Term Forecast | N35: Reference
B36: Depreciation factor | C36: =DCF!F9/(DCF!F40) -> -0.080714447 | D36: =DCF!E9/(DCF!E40) -> -0.07695821 | E36: =DCF!D9/(DCF!D40) -> -0.047423621 | F36: -0.12083333 | G36: -0.1840708 | I36: =AVERAGE(C36:G36) -> -0.10200008 | K36: =I36 -> -0.10200008 | L36: -0.06 | N36: % PPE
B37: Amortization factor | C37: =DCF!E10/(DCF!E38) -> -0.42844488 | D37: =DCF!E10/(DCF!E38) -> -0.42844488 | E37: =DCF!D10/(DCF!D38) -> -0.39553687 | F37: -0.42574062 | G37: -0.37608651 | I37: =AVERAGE(C37:G37) -> -0.41085075 | K37: =I37 -> -0.41085075 | L37: -0.3 | N37: % IA
B38: Stock-based comp | C38: =DCF!F11/DCF!F6 -> -0.010052486 | D38: =DCF!E11/DCF!E6 -> -0.018186994 | E38: =DCF!D11/DCF!D6 -> -0.013569937 | F38: -0.00016602656 | G38: -0.00020093272 | I38: =AVERAGE(C38:G38) -> -0.0084352754 | K38: =I38 -> -0.0084352754 | L38: =K38 -> -0.0084352754 | N38: % revenue
B39: Tax Rate | C39: =C12 -> 0.1284448 | D39: =D12 -> 0.21675532 | E39: =E12 -> 0.16763699 | F39: =F12 -> 0.16411379 | G39: =G12 -> 0.15664403 | I39: =AVERAGE(C39:G39) -> 0.16671899 | K39: =I39 -> 0.16671899 | L39: 0.18 | N39: % (line 9)
B40: Interest Rate on debt | C40: ='Fin. Data'!B14/'Fin. Data'!B58 -> -0.045196717 | D40: ='Fin. Data'!C14/'Fin. Data'!C58 -> -0.021793055 | E40: ='Fin. Data'!D14/'Fin. Data'!D58 -> -0.020326137 | F40: ='Fin. Data'!E14/'Fin. Data'!E58 -> -0.076952973 | G40: ='Fin. Data'!F14/'Fin. Data'!F58 -> -0.03310328 | I40: =AVERAGE(C40:G40) -> -0.039474432 | K40: =I21 -> 0.0487 | L40: =I22 -> 0.0503 | N40: % debt (l29)
B41: Interest Rate on cash | I41: =AVERAGE(C41:G41) -> #DIV/0! | K41: =I19 -> 0.0417 | L41: =I18 -> 0.0433 | N41: % of cash (l28)
B42: Operating cash flows before WK | C42: =C89 -> -0.3591792 | D42: =D89 -> -0.50303011 | E42: =E89 -> -0.5764698 | F42: =F89 -> -0.4518763 | G42: =G89 -> -0.69570847 | I42: =AVERAGE(C42:G42) -> -0.51725278 | K42: =I42 -> -0.51725278 | L42: =C88 -> -0.60608548 | N42: reducing with addicitons to content
B43: Working capital flows | C43: =+Inputs!B62/(Inputs!B6-Inputs!C6) -> -0.055102041 | D43: =+Inputs!C62/(Inputs!C6-Inputs!D6) -> -0.39525547 | E43: =+Inputs!D62/(Inputs!D6-Inputs!E6) -> -0.051467461 | F43: =+Inputs!E62/(Inputs!E6-Inputs!F6) -> -0.0065909091 | G43: =+Inputs!F62/(Inputs!F6-Inputs!G6) -> 0.0098578634 | I43: =AVERAGE(C43:G43) -> -0.099711604 | K43: =I43 -> -0.099711604 | L43: =K43 -> -0.099711604 | N43: % of change revenues (l2)
B44: Intangible Assets | I44: =AVERAGE(C44:G44) -> #DIV/0! | K44: =0.9/4 -> 0.225 | L44: =K44 -> 0.225 | N44: Growing with amortization
B45: CAPEX | C45: =+'Fin. Data'!B32/'Fin. Data'!B5 -> -0.010337159 | D45: =+'Fin. Data'!C32/'Fin. Data'!C5 -> -0.012895369 | E45: =+'Fin. Data'!D32/'Fin. Data'!D5 -> -0.017664489 | F45: =+'Fin. Data'!E32/'Fin. Data'!E5 -> -0.019919187 | G45: =+'Fin. Data'!F32/'Fin. Data'!F5 -> -0.012552094 | I45: =AVERAGE(C45:G45) -> -0.01467366 | K45: =I45 -> -0.01467366 | L45: =K45/2 -> -0.0073368298 | N45: % revenue (l2)
B46: Acquisition factor | C46: =+'Fin. Data'!B33/'Fin. Data'!B5 -> -0.014971978 | D46: =+'Fin. Data'!C33/'Fin. Data'!C5 -> -0.052780238 | E46: =+'Fin. Data'!D33/'Fin. Data'!D5 -> -0.026543875 | F46: =+'Fin. Data'!E33/'Fin. Data'!E5 -> 0 | G46: =+'Fin. Data'!F33/'Fin. Data'!F5 -> 0 | I46: =AVERAGE(C46:G46) -> -0.018859218 | K46: =I46 -> -0.018859218 | L46: =K46/2 -> -0.009429609 | N46: % revenue (l2)
B47: Dividends | C47: 0 | D47: 0 | E47: 0 | F47: 0 | G47: 0 | I47: =AVERAGE(C47:G47) -> 0 | K47: =I47 -> 0 | L47: =K47 -> 0 | N47: % net income (11)
B48: Repurchases | C48: =+'Fin. Data'!B28/'Fin. Data'!B23 -> -1.1178439 | D48: =+'Fin. Data'!C28/'Fin. Data'!C23 -> 0 | E48: =+'Fin. Data'!D28/'Fin. Data'!D23 -> -0.11727912 | F48: =+'Fin. Data'!E28/'Fin. Data'!E23 -> 0 | G48: =+'Fin. Data'!F28/'Fin. Data'!F23 -> 0 | I48: =AVERAGE(C48:G48) -> -0.24702461 | K48: -0.2 | L48: =I48 -> -0.24702461 | N48: % net income (11)
B49: Leases | C49: 0 | D49: 0 | E49: 0 | F49: 0 | G49: 0 | I49: =AVERAGE(C49:G49) -> 0 | K49: =I49 -> 0 | L49: =K49 -> 0 | N49: % revenue (l2)
B50: Cash Costs for EBIT | I50: =AVERAGE(C50:G50) -> #DIV/0! | K50: =I50 -> #DIV/0! | L50: =K50 -> #DIV/0! | N50: % revenue (l2)
B51: Total Debt | C51: ='Fin. Data'!B58/'Fin. Data'!B19 -> 0.77049325 | D51: ='Fin. Data'!C58/'Fin. Data'!C19 -> 0.86269794 | E51: ='Fin. Data'!D58/'Fin. Data'!D19 -> 0.947562 | F51: ='Fin. Data'!E58/'Fin. Data'!E19 -> 1.1679831 | G51: ='Fin. Data'!F58/'Fin. Data'!F19 -> 1.3880364 | I51: =AVERAGE(C51:G51) -> 1.0273545 | K51: 0.5 | L51: 0.5 | N51: % EBITDA
B54: Forecasts
B57: Switches to change scenarios | E57: Conservative Case - 1 | G57: Base Case - 2 | I57: Optimistic Case - 3
B58: Revenue Growth | C58: 2 | E58: 0.8 | G58: 1 | I58: 1.2
B59: Operating Margin | C59: 2 | E59: 0.9 | G59: 1 | I59: 1.1
C64: 2024 | D64: =+C64+1 -> 2025 | E64: =+D64+1 -> 2026 | F64: =+E64+1 -> 2027 | G64: =+F64+1 -> 2028 | H64: =+G64+1 -> 2029 | I64: =+H64+1 -> 2030 | J64: =+I64+1 -> 2031 | K64: =+J64+1 -> 2032 | ... AB64: =+AA64+1 -> 2049
B66: Net Sales | C66: =+DCF!F6*(1+Assumptions!C67) -> 38223.56 | D66: =+C66*(1+D67) -> 43527.666 | E66: =+D66*(1+E67) -> 49798.871 | F66: =+E66*(1+F67) -> 57237.96 | G66: =+F66*(1+G67) -> 66092.177 | H66: =+G66*(1+H67) -> 76666.925 | I66: =+H66*(1+I67) -> 87193.958 | J66: =+I66*(1+J67) -> 97187.896 | K66: =+J66*(1+K67) -> 106121.99 | ... AB66: =+AA66*(1+AB67) -> 155769.04
B67: %Growth | C67: =OFFSET(C$67,Assumptions!$C$58,0) -> 0.13345669 | D67: =D69 -> 0.13876535 | E67: =E69 -> 0.14407401 | F67: =F69 -> 0.14938268 | G67: =G69 -> 0.15469134 | H67: =H69 -> 0.16 | I67: =I69 -> 0.13730866 | J67: =J69 -> 0.11461732 | K67: =K69 -> 0.091925985 | ... AB67: =AB69 -> 0.02
B68: Conservative scenario | C68: =+C69*0.8 -> 0.10676535 | D68: =+C68+($M68-$C68)/($M$64-$C$64) -> 0.097088818 | E68: =+D68+($M68-$C68)/($M$64-$C$64) -> 0.087412282 | F68: =+E68+($M68-$C68)/($M$64-$C$64) -> 0.077735747 | G68: =+F68+($M68-$C68)/($M$64-$C$64) -> 0.068059212 | H68: =+G68+($M68-$C68)/($M$64-$C$64) -> 0.058382677 | I68: =+H68+($M68-$C68)/($M$64-$C$64) -> 0.048706141 | J68: =+I68+($M68-$C68)/($M$64-$C$64) -> 0.039029606 | K68: =+J68+($M68-$C68)/($M$64-$C$64) -> 0.029353071 | L68: =+K68+($M68-$C68)/($M$64-$C$64) -> 0.019676535 | M68: 0.01 | N68: =M68 -> 0.01 | O68: =N68 -> 0.01 | P68: =O68 -> 0.01 | Q68: =P68 -> 0.01 | R68: =Q68 -> 0.01 | S68: =R68 -> 0.01 | T68: =S68 -> 0.01 | U68: =T68 -> 0.01 | ... AB68: =AA68 -> 0.01
B69: Base scenario | C69: =C74 -> 0.13345669 | D69: =+C69+($H69-$C69)/($H$64-$C$64) -> 0.13876535 | E69: =+D69+($H69-$C69)/($H$64-$C$64) -> 0.14407401 | F69: =+E69+($H69-$C69)/($H$64-$C$64) -> 0.14938268 | G69: =+F69+($H69-$C69)/($H$64-$C$64) -> 0.15469134 | H69: 0.16 | I69: =+H69+($M$69-$C$69)/($M$64-$H$64) -> 0.13730866 | J69: =+I69+($M$69-$C$69)/($M$64-$H$64) -> 0.11461732 | K69: =+J69+($M$69-$C$69)/($M$64-$H$64) -> 0.091925985 | L69: =+K69+($M$69-$C$69)/($M$64-$H$64) -> 0.069234647 | M69: 0.02 | N69: =M69 -> 0.02 | O69: =N69 -> 0.02 | P69: =O69 -> 0.02 | Q69: =P69 -> 0.02 | R69: =Q69 -> 0.02 | S69: =R69 -> 0.02 | T69: =S69 -> 0.02 | U69: =T69 -> 0.02 | ... AB69: =AA69 -> 0.02
B70: Optimistic scenario | C70: =+C69*1.2 -> 0.16014803 | D70: =+C70+($M70-$C70)/($M$64-$C$64) -> 0.14713323 | E70: =+D70+($M70-$C70)/($M$64-$C$64) -> 0.13411842 | F70: =+E70+($M70-$C70)/($M$64-$C$64) -> 0.12110362 | G70: =+F70+($M70-$C70)/($M$64-$C$64) -> 0.10808882 | H70: =+G70+($M70-$C70)/($M$64-$C$64) -> 0.095074015 | I70: =+H70+($M70-$C70)/($M$64-$C$64) -> 0.082059212 | J70: =+I70+($M70-$C70)/($M$64-$C$64) -> 0.069044409 | K70: =+J70+($M70-$C70)/($M$64-$C$64) -> 0.056029606 | L70: =+K70+($M70-$C70)/($M$64-$C$64) -> 0.043014803 | M70: 0.03 | N70: =M70 -> 0.03 | O70: =N70 -> 0.03 | P70: =O70 -> 0.03 | Q70: =P70 -> 0.03 | R70: =Q70 -> 0.03 | S70: =R70 -> 0.03 | T70: =S70 -> 0.03 | U70: =T70 -> 0.03 | ... AB70: =AA70 -> 0.03
B72: 5Y Average | C72: =I9 -> 0.16712898
B73: Target | C73: double digit
B74: S&P Estimate | C74: =(38223.56-Inputs!B6)/Inputs!B6 -> 0.13345669
B77: Operating Margin | C77: =OFFSET(C$77,Assumptions!$C$59,0) -> 0.24 | D77: =D79 -> 0.242 | E77: =E79 -> 0.244 | F77: =F79 -> 0.246 | G77: =G79 -> 0.248 | H77: =H79 -> 0.25 | I77: =I79 -> 0.252 | J77: =J79 -> 0.254 | K77: =K79 -> 0.256 | ... AB77: =AB79 -> 0.26
B78: Conservative scenario | C78: =+C79*$E$59 -> 0.216 | D78: =+D79*$E$59 -> 0.2178 | E78: =+E79*$E$59 -> 0.2196 | F78: =+F79*$E$59 -> 0.2214 | G78: =+G79*$E$59 -> 0.2232 | H78: =+H79*$E$59 -> 0.225 | I78: =+I79*$E$59 -> 0.2268 | J78: =+J79*$E$59 -> 0.2286 | ... AB78: =+AB79*$E$59 -> 0.234
B79: Base scenario | C79: 0.24 | D79: =+C79+($M$79-$C$79)/($M$64-$C$64) -> 0.242 | E79: =+D79+($M$79-$C$79)/($M$64-$C$64) -> 0.244 | F79: =+E79+($M$79-$C$79)/($M$64-$C$64) -> 0.246 | G79: =+F79+($M$79-$C$79)/($M$64-$C$64) -> 0.248 | H79: =+G79+($M$79-$C$79)/($M$64-$C$64) -> 0.25 | I79: =+H79+($M$79-$C$79)/($M$64-$C$64) -> 0.252 | J79: =+I79+($M$79-$C$79)/($M$64-$C$64) -> 0.254 | K79: =+J79+($M$79-$C$79)/($M$64-$C$64) -> 0.256 | L79: =+K79+($M$79-$C$79)/($M$64-$C$64) -> 0.258 | M79: 0.26 | N79: =M79 -> 0.26 | O79: =N79 -> 0.26 | P79: =O79 -> 0.26 | Q79: =P79 -> 0.26 | R79: =Q79 -> 0.26 | S79: =R79 -> 0.26 | T79: =S79 -> 0.26 | U79: =T79 -> 0.26 | ... AB79: =AA79 -> 0.26
B80: Optimistic scenario | C80: =+C79*$I$59 -> 0.264 | D80: =+D79*$I$59 -> 0.2662 | E80: =+E79*$I$59 -> 0.2684 | F80: =+F79*$I$59 -> 0.2706 | G80: =+G79*$I$59 -> 0.2728 | H80: =+H79*$I$59 -> 0.275 | I80: =+I79*$I$59 -> 0.2772 | J80: =+J79*$I$59 -> 0.2794 | ... AB80: =+AB79*$I$59 -> 0.286
B82: 5Y Average | C82: =I10 -> 0.18112005
B83: Target | C83: 0.24
B86: Operating Cash-Flow before WK
B87: Addictions to contante assets | C87: -12112.6 | D87: -15903.8 | E87: -17120 | F87: -11295.1 | G87: -14022.7 | H87: -11756.4 | I87: -8525.6 | J87: -6731.2 | K87: -4533.4 | L87: -3139.2
B88: Average 10Y | C88: =+AVERAGE(C89:L89) -> -0.60608548
B89: %revenue | C89: =+C87/Inputs!B6 -> -0.3591792 | D89: =+D87/Inputs!C6 -> -0.50303011 | E89: =+E87/Inputs!D6 -> -0.5764698 | F89: =+F87/Inputs!E6 -> -0.4518763 | G89: =+G87/Inputs!F6 -> -0.69570847 | H89: =+H87/Inputs!G6 -> -0.74435862 | I89: =+I87/Inputs!H6 -> -0.72911999 | J89: =+J87/Inputs!I6 -> -0.76222398 | ... L89: =+L87/Inputs!K6 -> -0.57024523
B90: Average 5Y | C90: =AVERAGE(C89:G89) -> -0.51725278

Sheet Fin. Data
A1: =Inputs!H3 -> #VALUE!
A2: =Inputs!G2 -> Figures in Millions of USD
A3: Results
B4: =OP!J20 -> 2023 | C4: =B4-1 -> 2022 | D4: =C4-1 -> 2021 | E4: =D4-1 -> 2020 | F4: =E4-1 -> 2019 | G4: =F4-1 -> 2018 | H4: =G4-1 -> 2017 | I4: =H4-1 -> 2016 | J4: =I4-1 -> 2015 | ... M4: =L4-1 -> 2012
A5: Net Sales | B5: =_xlfn.XLOOKUP($A5,Inputs!$A:$A,Inputs!B:B,,0) -> 33723 | C5: =_xlfn.XLOOKUP($A5,Inputs!$A:$A,Inputs!C:C,,0) -> 31616 | D5: =_xlfn.XLOOKUP($A5,Inputs!$A:$A,Inputs!D:D,,0) -> 29698 | E5: =_xlfn.XLOOKUP($A5,Inputs!$A:$A,Inputs!E:E,,0) -> 24996 | F5: =_xlfn.XLOOKUP($A5,Inputs!$A:$A,Inputs!F:F,,0) -> 20156 | G5: =_xlfn.XLOOKUP($A5,Inputs!$A:$A,Inputs!G:G,,0) -> 15794 | H5: =_xlfn.XLOOKUP($A5,Inputs!$A:$A,Inputs!H:H,,0) -> 11693 | I5: =_xlfn.XLOOKUP($A5,Inputs!$A:$A,Inputs!I:I,,0) -> 8831 | J5: =_xlfn.XLOOKUP($A5,Inputs!$A:$A,Inputs!J:J,,0) -> 6780 | K5: =_xlfn.XLOOKUP($A5,Inputs!$A:$A,Inputs!K:K,,0) -> 5505 | L5: =_xlfn.XLOOKUP($A5,Inputs!$A:$A,Inputs!L:L,,0) -> 4375 | M5: =_xlfn.XLOOKUP($A5,Inputs!$A:$A,Inputs!M:M,,0) -> 3609
A6: Growth vs. Previous year | B6: =IFERROR(B5/C5-1,"-") -> 0.066643472 | C6: =IFERROR(C5/D5-1,"-") -> 0.064583474 | D6: =IFERROR(D5/E5-1,"-") -> 0.1881101 | E6: =IFERROR(E5/F5-1,"-") -> 0.24012701 | F6: =IFERROR(F5/G5-1,"-") -> 0.27618083 | G6: =IFERROR(G5/H5-1,"-") -> 0.35072265 | H6: =IFERROR(H5/I5-1,"-") -> 0.32408561 | I6: =IFERROR(I5/J5-1,"-") -> 0.30250737 | ... L6: =IFERROR(L5/M5-1,"-") -> 0.21224716 | M6: =IFERROR(M5/#REF!-1,"-") -> -
A7: Gross Profit | B7: =_xlfn.XLOOKUP($A7,Inputs!$A:$A,Inputs!B:B,,0) -> 14008 | C7: =_xlfn.XLOOKUP($A7,Inputs!$A:$A,Inputs!C:C,,0) -> 12447 | D7: =_xlfn.XLOOKUP($A7,Inputs!$A:$A,Inputs!D:D,,0) -> 12365 | E7: =_xlfn.XLOOKUP($A7,Inputs!$A:$A,Inputs!E:E,,0) -> 10821 | F7: =_xlfn.XLOOKUP($A7,Inputs!$A:$A,Inputs!F:F,,0) -> 7716 | G7: =_xlfn.XLOOKUP($A7,Inputs!$A:$A,Inputs!G:G,,0) -> 5827 | H7: =_xlfn.XLOOKUP($A7,Inputs!$A:$A,Inputs!H:H,,0) -> 4033 | I7: =_xlfn.XLOOKUP($A7,Inputs!$A:$A,Inputs!I:I,,0) -> 2801 | J7: =_xlfn.XLOOKUP($A7,Inputs!$A:$A,Inputs!J:J,,0) -> 2188 | K7: =_xlfn.XLOOKUP($A7,Inputs!$A:$A,Inputs!K:K,,0) -> 1752 | L7: =_xlfn.XLOOKUP($A7,Inputs!$A:$A,Inputs!L:L,,0) -> 1257 | M7: =_xlfn.XLOOKUP($A7,Inputs!$A:$A,Inputs!M:M,,0) -> 957
A8: % over sales | B8: =IFERROR(B7/B$5,"-") -> 0.41538416 | C8: =IFERROR(C7/C$5,"-") -> 0.39369307 | D8: =IFERROR(D7/D$5,"-") -> 0.416358 | E8: =IFERROR(E7/E$5,"-") -> 0.43290927 | F8: =IFERROR(F7/F$5,"-") -> 0.38281405 | G8: =IFERROR(G7/G$5,"-") -> 0.36893757 | H8: =IFERROR(H7/H$5,"-") -> 0.34490721 | I8: =IFERROR(I7/I$5,"-") -> 0.31717812 | ... M8: =IFERROR(M7/M$5,"-") -> 0.26517041
A9: Operating expenses | B9: =B5-B11 -> 26769 | C9: =C5-C11 -> 25983 | D9: =D5-D11 -> 23503 | E9: =E5-E11 -> 20411 | F9: =F5-F11 -> 17552 | G9: =G5-G11 -> 14189 | H9: =H5-H11 -> 10854 | I9: =I5-I11 -> 8451 | ... M9: =M5-M11 -> 3559
A10: % over sales | B10: =IFERROR(B9/B$5,"-") -> 0.79379059 | C10: =IFERROR(C9/C$5,"-") -> 0.82183072 | D10: =IFERROR(D9/D$5,"-") -> 0.79140009 | E10: =IFERROR(E9/E$5,"-") -> 0.81657065 | F10: =IFERROR(F9/F$5,"-") -> 0.8708077 | G10: =IFERROR(G9/G$5,"-") -> 0.89837913 | H10: =IFERROR(H9/H$5,"-") -> 0.92824767 | I10: =IFERROR(I9/I$5,"-") -> 0.95696977 | ... M10: =IFERROR(M9/M$5,"-") -> 0.98614575
A11: Operating Income | B11: =_xlfn.XLOOKUP($A11,Inputs!$A:$A,Inputs!B:B,,0) -> 6954 | C11: =_xlfn.XLOOKUP($A11,Inputs!$A:$A,Inputs!C:C,,0) -> 5633 | D11: =_xlfn.XLOOKUP($A11,Inputs!$A:$A,Inputs!D:D,,0) -> 6195 | E11: =_xlfn.XLOOKUP($A11,Inputs!$A:$A,Inputs!E:E,,0) -> 4585 | F11: =_xlfn.XLOOKUP($A11,Inputs!$A:$A,Inputs!F:F,,0) -> 2604 | G11: =_xlfn.XLOOKUP($A11,Inputs!$A:$A,Inputs!G:G,,0) -> 1605 | H11: =_xlfn.XLOOKUP($A11,Inputs!$A:$A,Inputs!H:H,,0) -> 839 | I11: =_xlfn.XLOOKUP($A11,Inputs!$A:$A,Inputs!I:I,,0) -> 380 | J11: =_xlfn.XLOOKUP($A11,Inputs!$A:$A,Inputs!J:J,,0) -> 306 | K11: =_xlfn.XLOOKUP($A11,Inputs!$A:$A,Inputs!K:K,,0) -> 403 | L11: =_xlfn.XLOOKUP($A11,Inputs!$A:$A,Inputs!L:L,,0) -> 203 | M11: =_xlfn.XLOOKUP($A11,Inputs!$A:$A,Inputs!M:M,,0) -> 50
A12: Operating Margin | B12: =IFERROR(B11/B$5,"-") -> 0.20620941 | C12: =IFERROR(C11/C$5,"-") -> 0.17816928 | D12: =IFERROR(D11/D$5,"-") -> 0.20859991 | E12: =IFERROR(E11/E$5,"-") -> 0.18342935 | F12: =IFERROR(F11/F$5,"-") -> 0.1291923 | G12: =IFERROR(G11/G$5,"-") -> 0.10162087 | H12: =IFERROR(H11/H$5,"-") -> 0.07175233 | I12: =IFERROR(I11/I$5,"-") -> 0.043030234 | ... M12: =IFERROR(M11/M$5,"-") -> 0.013854253
A13: Growth vs. Previous year | B13: =IFERROR(B12/C12-1,"-") -> 0.15737915 | C13: =IFERROR(C12/D12-1,"-") -> -0.14588034 | D13: =IFERROR(D12/E12-1,"-") -> 0.13722208 | E13: =IFERROR(E12/F12-1,"-") -> 0.41981642 | F13: =IFERROR(F12/G12-1,"-") -> 0.27131663 | G13: =IFERROR(G12/H12-1,"-") -> 0.41627273 | H13: =IFERROR(H12/I12-1,"-") -> 0.6674864 | I13: =IFERROR(I12/J12-1,"-") -> -0.046585002 | ... L13: =IFERROR(L12/M12-1,"-") -> 2.349152 | M13: =IFERROR(M12/#REF!-1,"-") -> -
A14: Net Financial Cost | B14: =_xlfn.XLOOKUP($A14,Inputs!$A:$A,Inputs!B:B,,0) -> -749 | C14: =_xlfn.XLOOKUP($A14,Inputs!$A:$A,Inputs!C:C,,0) -> -369 | D14: =_xlfn.XLOOKUP($A14,Inputs!$A:$A,Inputs!D:D,,0) -> -354 | E14: =_xlfn.XLOOKUP($A14,Inputs!$A:$A,Inputs!E:E,,0) -> -1386 | F14: =_xlfn.XLOOKUP($A14,Inputs!$A:$A,Inputs!F:F,,0) -> -542 | G14: =_xlfn.XLOOKUP($A14,Inputs!$A:$A,Inputs!G:G,,0) -> -379 | H14: =_xlfn.XLOOKUP($A14,Inputs!$A:$A,Inputs!H:H,,0) -> -353 | I14: =_xlfn.XLOOKUP($A14,Inputs!$A:$A,Inputs!I:I,,0) -> -119 | J14: =_xlfn.XLOOKUP($A14,Inputs!$A:$A,Inputs!J:J,,0) -> -164 | K14: =_xlfn.XLOOKUP($A14,Inputs!$A:$A,Inputs!K:K,,0) -> -53 | L14: =_xlfn.XLOOKUP($A14,Inputs!$A:$A,Inputs!L:L,,0) -> -32 | M14: =_xlfn.XLOOKUP($A14,Inputs!$A:$A,Inputs!M:M,,0) -> 17
A15: Other Expenses (Revenues) | B15: =_xlfn.XLOOKUP($A15,Inputs!$A:$A,Inputs!B:B,,0) -> 0 | C15: =_xlfn.XLOOKUP($A15,Inputs!$A:$A,Inputs!C:C,,0) -> 369 | D15: =_xlfn.XLOOKUP($A15,Inputs!$A:$A,Inputs!D:D,,0) -> 254 | E15: =_xlfn.XLOOKUP($A15,Inputs!$A:$A,Inputs!E:E,,0) -> 87 | F15: =_xlfn.XLOOKUP($A15,Inputs!$A:$A,Inputs!F:F,,0) -> 128 | G15: =_xlfn.XLOOKUP($A15,Inputs!$A:$A,Inputs!G:G,,0) -> 29 | H15: =_xlfn.XLOOKUP($A15,Inputs!$A:$A,Inputs!H:H,,0) -> -80 | I15: =_xlfn.XLOOKUP($A15,Inputs!$A:$A,Inputs!I:I,,0) -> 0 | J15: =_xlfn.XLOOKUP($A15,Inputs!$A:$A,Inputs!J:J,,0) -> 0 | K15: =_xlfn.XLOOKUP($A15,Inputs!$A:$A,Inputs!K:K,,0) -> 0 | L15: =_xlfn.XLOOKUP($A15,Inputs!$A:$A,Inputs!L:L,,0) -> 0 | M15: =_xlfn.XLOOKUP($A15,Inputs!$A:$A,Inputs!M:M,,0) -> 0
A16: EBIT | B16: =B11-B15 -> 6954 | C16: =C11-C15 -> 5264 | D16: =D11-D15 -> 5941 | E16: =E11-E15 -> 4498 | F16: =F11-F15 -> 2476 | G16: =G11-G15 -> 1576 | H16: =H11-H15 -> 919 | I16: =I11-I15 -> 380 | ... M16: =M11-M15 -> 50
A17: Depreciation & Amortization | B17: =_xlfn.XLOOKUP($A17,Inputs!$A:$A,Inputs!B:B,,0) -> 14554.3 | C17: =_xlfn.XLOOKUP($A17,Inputs!$A:$A,Inputs!C:C,,0) -> 14362.8 | D17: =_xlfn.XLOOKUP($A17,Inputs!$A:$A,Inputs!D:D,,0) -> 12438.8 | E17: =_xlfn.XLOOKUP($A17,Inputs!$A:$A,Inputs!E:E,,0) -> 10922.6 | F17: =_xlfn.XLOOKUP($A17,Inputs!$A:$A,Inputs!F:F,,0) -> 9319.8 | G17: =_xlfn.XLOOKUP($A17,Inputs!$A:$A,Inputs!G:G,,0) -> 7656.5 | H17: =_xlfn.XLOOKUP($A17,Inputs!$A:$A,Inputs!H:H,,0) -> 6330.4 | I17: =_xlfn.XLOOKUP($A17,Inputs!$A:$A,Inputs!I:I,,0) -> 4925 | J17: =_xlfn.XLOOKUP($A17,Inputs!$A:$A,Inputs!J:J,,0) -> 3547.1 | K17: =_xlfn.XLOOKUP($A17,Inputs!$A:$A,Inputs!K:K,,0) -> 2781.8 | L17: =_xlfn.XLOOKUP($A17,Inputs!$A:$A,Inputs!L:L,,0) -> 0 | M17: =_xlfn.XLOOKUP($A17,Inputs!$A:$A,Inputs!M:M,,0) -> 0
A18: Changes Net Working Capital | B18: =_xlfn.XLOOKUP($A18,Inputs!$A:$A,Inputs!B:B,,0) -> -1358 | C18: =_xlfn.XLOOKUP($A18,Inputs!$A:$A,Inputs!C:C,,0) -> 1724 | D18: =_xlfn.XLOOKUP($A18,Inputs!$A:$A,Inputs!D:D,,0) -> -197 | E18: =_xlfn.XLOOKUP($A18,Inputs!$A:$A,Inputs!E:E,,0) -> -555 | F18: =_xlfn.XLOOKUP($A18,Inputs!$A:$A,Inputs!F:F,,0) -> -5108 | G18: =_xlfn.XLOOKUP($A18,Inputs!$A:$A,Inputs!G:G,,0) -> 0 | H18: =_xlfn.XLOOKUP($A18,Inputs!$A:$A,Inputs!H:H,,0) -> 32 | I18: =_xlfn.XLOOKUP($A18,Inputs!$A:$A,Inputs!I:I,,0) -> -18 | J18: =_xlfn.XLOOKUP($A18,Inputs!$A:$A,Inputs!J:J,,0) -> -192 | K18: =_xlfn.XLOOKUP($A18,Inputs!$A:$A,Inputs!K:K,,0) -> -409 | L18: =_xlfn.XLOOKUP($A18,Inputs!$A:$A,Inputs!L:L,,0) -> 0 | M18: =_xlfn.XLOOKUP($A18,Inputs!$A:$A,Inputs!M:M,,0) -> 0
A19: EBITDA | B19: =B11-B15+B17 -> 21508.3 | C19: =C11-C15+C17 -> 19626.8 | D19: =D11-D15+D17 -> 18379.8 | E19: =E11-E15+E17 -> 15420.6 | F19: =F11-F15+F17 -> 11795.8 | G19: =G11-G15+G17 -> 9232.5 | H19: =H11-H15+H17 -> 7249.4 | I19: =I11-I15+I17 -> 5305 | ... M19: =M11-M15+M17 -> 50
A20: EBITDA Margin | B20: =IFERROR(B19/B$5,"-") -> 0.6377932 | C20: =IFERROR(C19/C$5,"-") -> 0.62078694 | D20: =IFERROR(D19/D$5,"-") -> 0.61889016 | E20: =IFERROR(E19/E$5,"-") -> 0.61692271 | F20: =IFERROR(F19/F$5,"-") -> 0.58522524 | G20: =IFERROR(G19/G$5,"-") -> 0.58455743 | H20: =IFERROR(H19/H$5,"-") -> 0.61997776 | I20: =IFERROR(I19/I$5,"-") -> 0.60072472 | ... M20: =IFERROR(M19/M$5,"-") -> 0.013854253
A21: Taxes | B21: =_xlfn.XLOOKUP($A21,Inputs!$A:$A,Inputs!B:B,,0) -> -797 | C21: =_xlfn.XLOOKUP($A21,Inputs!$A:$A,Inputs!C:C,,0) -> -1141 | D21: =_xlfn.XLOOKUP($A21,Inputs!$A:$A,Inputs!D:D,,0) -> -979 | E21: =_xlfn.XLOOKUP($A21,Inputs!$A:$A,Inputs!E:E,,0) -> -525 | F21: =_xlfn.XLOOKUP($A21,Inputs!$A:$A,Inputs!F:F,,0) -> -323 | G21: =_xlfn.XLOOKUP($A21,Inputs!$A:$A,Inputs!G:G,,0) -> -44 | H21: =_xlfn.XLOOKUP($A21,Inputs!$A:$A,Inputs!H:H,,0) -> 153 | I21: =_xlfn.XLOOKUP($A21,Inputs!$A:$A,Inputs!I:I,,0) -> -74 | J21: =_xlfn.XLOOKUP($A21,Inputs!$A:$A,Inputs!J:J,,0) -> -19 | K21: =_xlfn.XLOOKUP($A21,Inputs!$A:$A,Inputs!K:K,,0) -> -83 | L21: =_xlfn.XLOOKUP($A21,Inputs!$A:$A,Inputs!L:L,,0) -> -59 | M21: =_xlfn.XLOOKUP($A21,Inputs!$A:$A,Inputs!M:M,,0) -> -13
A22: % Tax | B22: =IFERROR(B21/B$5,"-") -> -0.023633722 | C22: =IFERROR(C21/C$5,"-") -> -0.036089322 | D22: =IFERROR(D21/D$5,"-") -> -0.032965183 | E22: =IFERROR(E21/E$5,"-") -> -0.021003361 | F22: =IFERROR(F21/F$5,"-") -> -0.016025005 | G22: =IFERROR(G21/G$5,"-") -> -0.0027858681 | H22: =IFERROR(H21/H$5,"-") -> 0.013084752 | I22: =IFERROR(I21/I$5,"-") -> -0.008379572 | ... M22: =IFERROR(M21/M$5,"-") -> -0.0036021058
A23: Net Income | B23: =_xlfn.XLOOKUP($A23,Inputs!$A:$A,Inputs!B:B,,0) -> 5408 | C23: =_xlfn.XLOOKUP($A23,Inputs!$A:$A,Inputs!C:C,,0) -> 4492 | D23: =_xlfn.XLOOKUP($A23,Inputs!$A:$A,Inputs!D:D,,0) -> 5116 | E23: =_xlfn.XLOOKUP($A23,Inputs!$A:$A,Inputs!E:E,,0) -> 2761 | F23: =_xlfn.XLOOKUP($A23,Inputs!$A:$A,Inputs!F:F,,0) -> 1867 | G23: =_xlfn.XLOOKUP($A23,Inputs!$A:$A,Inputs!G:G,,0) -> 1211 | H23: =_xlfn.XLOOKUP($A23,Inputs!$A:$A,Inputs!H:H,,0) -> 559 | I23: =_xlfn.XLOOKUP($A23,Inputs!$A:$A,Inputs!I:I,,0) -> 187 | J23: =_xlfn.XLOOKUP($A23,Inputs!$A:$A,Inputs!J:J,,0) -> 123 | K23: =_xlfn.XLOOKUP($A23,Inputs!$A:$A,Inputs!K:K,,0) -> 267 | L23: =_xlfn.XLOOKUP($A23,Inputs!$A:$A,Inputs!L:L,,0) -> 112 | M23: =_xlfn.XLOOKUP($A23,Inputs!$A:$A,Inputs!M:M,,0) -> 17
A24: Net Income Margin | B24: =IFERROR(B23/B$5,"-") -> 0.16036533 | C24: =IFERROR(C23/C$5,"-") -> 0.14207996 | D24: =IFERROR(D23/D$5,"-") -> 0.17226749 | E24: =IFERROR(E23/E$5,"-") -> 0.11045767 | F24: =IFERROR(F23/F$5,"-") -> 0.092627505 | G24: =IFERROR(G23/G$5,"-") -> 0.076674687 | H24: =IFERROR(H23/H$5,"-") -> 0.04780638 | I24: =IFERROR(I23/I$5,"-") -> 0.021175405 | ... M24: =IFERROR(M23/M$5,"-") -> 0.0047104461
A25: Growth vs. Previous year | B25: =IFERROR(B24/C24-1,"-") -> 0.12869774 | C25: =IFERROR(C24/D24-1,"-") -> -0.17523639 | D25: =IFERROR(D24/E24-1,"-") -> 0.55957923 | E25: =IFERROR(E24/F24-1,"-") -> 0.19249323 | F25: =IFERROR(F24/G24-1,"-") -> 0.20805848 | G25: =IFERROR(G24/H24-1,"-") -> 0.60385887 | H25: =IFERROR(H24/I24-1,"-") -> 1.2576371 | I25: =IFERROR(I24/J24-1,"-") -> 0.16722963 | ... L25: =IFERROR(L24/M24-1,"-") -> 4.4347294 | M25: =IFERROR(M24/#REF!-1,"-") -> -
A26: Cash Generated | B26: =B39-C39 -> 1080 | C26: =C39-D39 -> 30 | D26: =D39-E39 -> -2178 | E26: =E39-F39 -> 3188 | F26: =F39-G39 -> 1224 | G26: =G39-H39 -> 0 | H26: =H39-I39 -> 971 | I26: =I39-J39 -> 1089 | ... M26: =M39-N39 -> 0
A27: Dividends | B27: =_xlfn.XLOOKUP($A27,Inputs!$A:$A,Inputs!B:B,,0) -> 0 | C27: =_xlfn.XLOOKUP($A27,Inputs!$A:$A,Inputs!C:C,,0) -> 0 | D27: =_xlfn.XLOOKUP($A27,Inputs!$A:$A,Inputs!D:D,,0) -> 0 | E27: =_xlfn.XLOOKUP($A27,Inputs!$A:$A,Inputs!E:E,,0) -> 0 | F27: =_xlfn.XLOOKUP($A27,Inputs!$A:$A,Inputs!F:F,,0) -> 0 | G27: =_xlfn.XLOOKUP($A27,Inputs!$A:$A,Inputs!G:G,,0) -> 0 | H27: =_xlfn.XLOOKUP($A27,Inputs!$A:$A,Inputs!H:H,,0) -> 0 | I27: =_xlfn.XLOOKUP($A27,Inputs!$A:$A,Inputs!I:I,,0) -> 0 | J27: =_xlfn.XLOOKUP($A27,Inputs!$A:$A,Inputs!J:J,,0) -> 0 | K27: =_xlfn.XLOOKUP($A27,Inputs!$A:$A,Inputs!K:K,,0) -> 0 | L27: =_xlfn.XLOOKUP($A27,Inputs!$A:$A,Inputs!L:L,,0) -> 0 | M27: =_xlfn.XLOOKUP($A27,Inputs!$A:$A,Inputs!M:M,,0) -> 0
A28: Share buyback | B28: =_xlfn.XLOOKUP($A28,Inputs!$A:$A,Inputs!B:B,,0) -> -6045.3 | C28: =_xlfn.XLOOKUP($A28,Inputs!$A:$A,Inputs!C:C,,0) -> 0 | D28: =_xlfn.XLOOKUP($A28,Inputs!$A:$A,Inputs!D:D,,0) -> -600 | E28: =_xlfn.XLOOKUP($A28,Inputs!$A:$A,Inputs!E:E,,0) -> 0 | F28: =_xlfn.XLOOKUP($A28,Inputs!$A:$A,Inputs!F:F,,0) -> 0 | G28: =_xlfn.XLOOKUP($A28,Inputs!$A:$A,Inputs!G:G,,0) -> 0 | H28: =_xlfn.XLOOKUP($A28,Inputs!$A:$A,Inputs!H:H,,0) -> 0 | I28: =_xlfn.XLOOKUP($A28,Inputs!$A:$A,Inputs!I:I,,0) -> 0 | J28: =_xlfn.XLOOKUP($A28,Inputs!$A:$A,Inputs!J:J,,0) -> 0 | K28: =_xlfn.XLOOKUP($A28,Inputs!$A:$A,Inputs!K:K,,0) -> 0 | L28: =_xlfn.XLOOKUP($A28,Inputs!$A:$A,Inputs!L:L,,0) -> 0 | M28: =_xlfn.XLOOKUP($A28,Inputs!$A:$A,Inputs!M:M,,0) -> 0
A29: Net Cash Flow | B29: =SUM(B26:B28) -> -4965.3 | C29: =SUM(C26:C28) -> 30 | D29: =SUM(D26:D28) -> -2778 | E29: =SUM(E26:E28) -> 3188 | F29: =SUM(F26:F28) -> 1224 | G29: =SUM(G26:G28) -> 0 | H29: =SUM(H26:H28) -> 971 | I29: =SUM(I26:I28) -> 1089 | ... M29: =SUM(M26:M28) -> 0
A30: FNP'' | B30: =+B29-(B58-C29) -> -21507.3 | C30: =+C29-(C58-D29) -> -19680 | D30: =+D29-(D58-E29) -> -17006 | E30: =+E29-(E58-F29) -> -13599 | F30: =+F29-(F58-G29) -> -15149 | G30: =+G29-(G58-H29) -> -9389 | H30: =+H29-(H58-I29) -> -8328 | I30: =+I29-(I58-J29) -> -6017 | ... M30: =+M29-(M58-N29) -> 0
A31: FNP' | B31: =+B30+B33 -> -22012.2 | C31: =+C30+C33 -> -21348.7 | D31: =+D30+D33 -> -17794.3 | E31: =+E30+E33 -> -13599 | F31: =+F30+F33 -> -15149 | G31: =+G30+G33 -> -9389 | H31: =+H30+H33 -> -8402.8 | I31: =+I30+I33 -> -6204.2 | ... M31: =+M30+M33 -> 0
A32: Net Capex | B32: =_xlfn.XLOOKUP($A32,Inputs!$A:$A,Inputs!B:B,,0) -> -348.6 | C32: =_xlfn.XLOOKUP($A32,Inputs!$A:$A,Inputs!C:C,,0) -> -407.7 | D32: =_xlfn.XLOOKUP($A32,Inputs!$A:$A,Inputs!D:D,,0) -> -524.6 | E32: =_xlfn.XLOOKUP($A32,Inputs!$A:$A,Inputs!E:E,,0) -> -497.9 | F32: =_xlfn.XLOOKUP($A32,Inputs!$A:$A,Inputs!F:F,,0) -> -253 | G32: =_xlfn.XLOOKUP($A32,Inputs!$A:$A,Inputs!G:G,,0) -> -212.5 | H32: =_xlfn.XLOOKUP($A32,Inputs!$A:$A,Inputs!H:H,,0) -> -227 | I32: =_xlfn.XLOOKUP($A32,Inputs!$A:$A,Inputs!I:I,,0) -> -184.8 | J32: =_xlfn.XLOOKUP($A32,Inputs!$A:$A,Inputs!J:J,,0) -> -169.2 | K32: =_xlfn.XLOOKUP($A32,Inputs!$A:$A,Inputs!K:K,,0) -> -144.5 | L32: =_xlfn.XLOOKUP($A32,Inputs!$A:$A,Inputs!L:L,,0) -> 0 | M32: =_xlfn.XLOOKUP($A32,Inputs!$A:$A,Inputs!M:M,,0) -> 0
A33: Investments & Acquisitions | B33: =_xlfn.XLOOKUP($A33,Inputs!$A:$A,Inputs!B:B,,0) -> -504.9 | C33: =_xlfn.XLOOKUP($A33,Inputs!$A:$A,Inputs!C:C,,0) -> -1668.7 | D33: =_xlfn.XLOOKUP($A33,Inputs!$A:$A,Inputs!D:D,,0) -> -788.3 | E33: =_xlfn.XLOOKUP($A33,Inputs!$A:$A,Inputs!E:E,,0) -> 0 | F33: =_xlfn.XLOOKUP($A33,Inputs!$A:$A,Inputs!F:F,,0) -> 0 | G33: =_xlfn.XLOOKUP($A33,Inputs!$A:$A,Inputs!G:G,,0) -> 0 | H33: =_xlfn.XLOOKUP($A33,Inputs!$A:$A,Inputs!H:H,,0) -> -74.8 | I33: =_xlfn.XLOOKUP($A33,Inputs!$A:$A,Inputs!I:I,,0) -> -187.2 | J33: =_xlfn.XLOOKUP($A33,Inputs!$A:$A,Inputs!J:J,,0) -> -371.9 | K33: =_xlfn.XLOOKUP($A33,Inputs!$A:$A,Inputs!K:K,,0) -> -426.9 | L33: =_xlfn.XLOOKUP($A33,Inputs!$A:$A,Inputs!L:L,,0) -> 0 | M33: =_xlfn.XLOOKUP($A33,Inputs!$A:$A,Inputs!M:M,,0) -> 0
A34: Capex + Investments | B34: =+B32+B33 -> -853.5 | C34: =+C32+C33 -> -2076.4 | D34: =+D32+D33 -> -1312.9 | E34: =+E32+E33 -> -497.9 | F34: =+F32+F33 -> -253 | G34: =+G32+G33 -> -212.5 | H34: =+H32+H33 -> -301.8 | I34: =+I32+I33 -> -372 | ... M34: =+M32+M33 -> 0
A35: Dividends + Share Buyback | B35: =+B27+B28 -> -6045.3 | C35: =+C27+C28 -> 0 | D35: =+D27+D28 -> -600 | E35: =+E27+E28 -> 0 | F35: =+F27+F28 -> 0 | G35: =+G27+G28 -> 0 | H35: =+H27+H28 -> 0 | I35: =+I27+I28 -> 0 | ... M35: =+M27+M28 -> 0
A36: Payout Ratio | B36: =IFERROR(B35/B23,"-") -> -1.1178439 | C36: =IFERROR(C35/C23,"-") -> 0 | D36: =IFERROR(D35/D23,"-") -> -0.11727912 | E36: =IFERROR(E35/E23,"-") -> 0 | F36: =IFERROR(F35/F23,"-") -> 0 | G36: =IFERROR(G35/G23,"-") -> 0 | H36: =IFERROR(H35/H23,"-") -> 0 | I36: =IFERROR(I35/I23,"-") -> 0 | ... M36: =IFERROR(M35/M23,"-") -> 0
A38: Assets
A39: Cash & Eq. | B39: =_xlfn.XLOOKUP($A39,Inputs!$A:$A,Inputs!B:B,,0) -> 7138 | C39: =_xlfn.XLOOKUP($A39,Inputs!$A:$A,Inputs!C:C,,0) -> 6058 | D39: =_xlfn.XLOOKUP($A39,Inputs!$A:$A,Inputs!D:D,,0) -> 6028 | E39: =_xlfn.XLOOKUP($A39,Inputs!$A:$A,Inputs!E:E,,0) -> 8206 | F39: =_xlfn.XLOOKUP($A39,Inputs!$A:$A,Inputs!F:F,,0) -> 5018 | G39: =_xlfn.XLOOKUP($A39,Inputs!$A:$A,Inputs!G:G,,0) -> 3794 | H39: =_xlfn.XLOOKUP($A39,Inputs!$A:$A,Inputs!H:H,,0) -> 3794 | I39: =_xlfn.XLOOKUP($A39,Inputs!$A:$A,Inputs!I:I,,0) -> 2823 | J39: =_xlfn.XLOOKUP($A39,Inputs!$A:$A,Inputs!J:J,,0) -> 1734 | K39: =_xlfn.XLOOKUP($A39,Inputs!$A:$A,Inputs!K:K,,0) -> 2311 | L39: =_xlfn.XLOOKUP($A39,Inputs!$A:$A,Inputs!L:L,,0) -> 0 | M39: =_xlfn.XLOOKUP($A39,Inputs!$A:$A,Inputs!M:M,,0) -> 0
A40: Accounts Receivable | B40: =_xlfn.XLOOKUP($A40,Inputs!$A:$A,Inputs!B:B,,0) -> 1287 | C40: =_xlfn.XLOOKUP($A40,Inputs!$A:$A,Inputs!C:C,,0) -> 989 | D40: =_xlfn.XLOOKUP($A40,Inputs!$A:$A,Inputs!D:D,,0) -> 804 | E40: =_xlfn.XLOOKUP($A40,Inputs!$A:$A,Inputs!E:E,,0) -> 611 | F40: =_xlfn.XLOOKUP($A40,Inputs!$A:$A,Inputs!F:F,,0) -> 454 | G40: =_xlfn.XLOOKUP($A40,Inputs!$A:$A,Inputs!G:G,,0) -> 363 | H40: =_xlfn.XLOOKUP($A40,Inputs!$A:$A,Inputs!H:H,,0) -> 0 | I40: =_xlfn.XLOOKUP($A40,Inputs!$A:$A,Inputs!I:I,,0) -> 0 | J40: =_xlfn.XLOOKUP($A40,Inputs!$A:$A,Inputs!J:J,,0) -> 0 | K40: =_xlfn.XLOOKUP($A40,Inputs!$A:$A,Inputs!K:K,,0) -> 0 | L40: =_xlfn.XLOOKUP($A40,Inputs!$A:$A,Inputs!L:L,,0) -> 0 | M40: =_xlfn.XLOOKUP($A40,Inputs!$A:$A,Inputs!M:M,,0) -> 0
A41: Inventory | B41: =_xlfn.XLOOKUP($A41,Inputs!$A:$A,Inputs!B:B,,0) -> 0 | C41: =_xlfn.XLOOKUP($A41,Inputs!$A:$A,Inputs!C:C,,0) -> 0 | D41: =_xlfn.XLOOKUP($A41,Inputs!$A:$A,Inputs!D:D,,0) -> 0 | E41: =_xlfn.XLOOKUP($A41,Inputs!$A:$A,Inputs!E:E,,0) -> 0 | F41: =_xlfn.XLOOKUP($A41,Inputs!$A:$A,Inputs!F:F,,0) -> 0 | G41: =_xlfn.XLOOKUP($A41,Inputs!$A:$A,Inputs!G:G,,0) -> 0 | H41: =_xlfn.XLOOKUP($A41,Inputs!$A:$A,Inputs!H:H,,0) -> 0 | I41: =_xlfn.XLOOKUP($A41,Inputs!$A:$A,Inputs!I:I,,0) -> 0 | J41: =_xlfn.XLOOKUP($A41,Inputs!$A:$A,Inputs!J:J,,0) -> 0 | K41: =_xlfn.XLOOKUP($A41,Inputs!$A:$A,Inputs!K:K,,0) -> 0 | L41: =_xlfn.XLOOKUP($A41,Inputs!$A:$A,Inputs!L:L,,0) -> 0 | M41: =_xlfn.XLOOKUP($A41,Inputs!$A:$A,Inputs!M:M,,0) -> 0
A42: Property, Plant and Equipment | B42: =_xlfn.XLOOKUP($A42,Inputs!$A:$A,Inputs!B:B,,0) -> 4423 | C42: =_xlfn.XLOOKUP($A42,Inputs!$A:$A,Inputs!C:C,,0) -> 4379 | D42: =_xlfn.XLOOKUP($A42,Inputs!$A:$A,Inputs!D:D,,0) -> 4386 | E42: =_xlfn.XLOOKUP($A42,Inputs!$A:$A,Inputs!E:E,,0) -> 3493 | F42: =_xlfn.XLOOKUP($A42,Inputs!$A:$A,Inputs!F:F,,0) -> 2513 | G42: =_xlfn.XLOOKUP($A42,Inputs!$A:$A,Inputs!G:G,,0) -> 787 | H42: =_xlfn.XLOOKUP($A42,Inputs!$A:$A,Inputs!H:H,,0) -> 787 | I42: =_xlfn.XLOOKUP($A42,Inputs!$A:$A,Inputs!I:I,,0) -> 641 | J42: =_xlfn.XLOOKUP($A42,Inputs!$A:$A,Inputs!J:J,,0) -> 545 | K42: =_xlfn.XLOOKUP($A42,Inputs!$A:$A,Inputs!K:K,,0) -> 471 | L42: =_xlfn.XLOOKUP($A42,Inputs!$A:$A,Inputs!L:L,,0) -> 0 | M42: =_xlfn.XLOOKUP($A42,Inputs!$A:$A,Inputs!M:M,,0) -> 0
A43: Other Assets | B43: =_xlfn.XLOOKUP($A43,Inputs!$A:$A,Inputs!B:B,,0) -> 33454 | C43: =_xlfn.XLOOKUP($A43,Inputs!$A:$A,Inputs!C:C,,0) -> 34591 | D43: =_xlfn.XLOOKUP($A43,Inputs!$A:$A,Inputs!D:D,,0) -> 30643 | E43: =_xlfn.XLOOKUP($A43,Inputs!$A:$A,Inputs!E:E,,0) -> 24768 | F43: =_xlfn.XLOOKUP($A43,Inputs!$A:$A,Inputs!F:F,,0) -> 24378 | G43: =_xlfn.XLOOKUP($A43,Inputs!$A:$A,Inputs!G:G,,0) -> 19322 | H43: =_xlfn.XLOOKUP($A43,Inputs!$A:$A,Inputs!H:H,,0) -> 19685 | I43: =_xlfn.XLOOKUP($A43,Inputs!$A:$A,Inputs!I:I,,0) -> 14812 | J43: =_xlfn.XLOOKUP($A43,Inputs!$A:$A,Inputs!J:J,,0) -> 11308 | K43: =_xlfn.XLOOKUP($A43,Inputs!$A:$A,Inputs!K:K,,0) -> 6891 | L43: =_xlfn.XLOOKUP($A43,Inputs!$A:$A,Inputs!L:L,,0) -> 0 | M43: =_xlfn.XLOOKUP($A43,Inputs!$A:$A,Inputs!M:M,,0) -> 0
A44: Total Assets | B44: =_xlfn.XLOOKUP($A44,Inputs!$A:$A,Inputs!B:B,,0) -> 48732 | C44: =_xlfn.XLOOKUP($A44,Inputs!$A:$A,Inputs!C:C,,0) -> 48595 | D44: =_xlfn.XLOOKUP($A44,Inputs!$A:$A,Inputs!D:D,,0) -> 44585 | E44: =_xlfn.XLOOKUP($A44,Inputs!$A:$A,Inputs!E:E,,0) -> 39280 | F44: =_xlfn.XLOOKUP($A44,Inputs!$A:$A,Inputs!F:F,,0) -> 33976 | G44: =_xlfn.XLOOKUP($A44,Inputs!$A:$A,Inputs!G:G,,0) -> 25974 | H44: =_xlfn.XLOOKUP($A44,Inputs!$A:$A,Inputs!H:H,,0) -> 25974 | I44: =_xlfn.XLOOKUP($A44,Inputs!$A:$A,Inputs!I:I,,0) -> 19013 | J44: =_xlfn.XLOOKUP($A44,Inputs!$A:$A,Inputs!J:J,,0) -> 13587 | K44: =_xlfn.XLOOKUP($A44,Inputs!$A:$A,Inputs!K:K,,0) -> 10203 | L44: =_xlfn.XLOOKUP($A44,Inputs!$A:$A,Inputs!L:L,,0) -> 0 | M44: =_xlfn.XLOOKUP($A44,Inputs!$A:$A,Inputs!M:M,,0) -> 0
A47: Liabilities
A48: Current Liabilities | B48: =_xlfn.XLOOKUP($A48,Inputs!$A:$A,Inputs!B:B,,0) -> 8861 | C48: =_xlfn.XLOOKUP($A48,Inputs!$A:$A,Inputs!C:C,,0) -> 7931 | D48: =_xlfn.XLOOKUP($A48,Inputs!$A:$A,Inputs!D:D,,0) -> 8489 | E48: =_xlfn.XLOOKUP($A48,Inputs!$A:$A,Inputs!E:E,,0) -> 7806 | F48: =_xlfn.XLOOKUP($A48,Inputs!$A:$A,Inputs!F:F,,0) -> 6856 | G48: =_xlfn.XLOOKUP($A48,Inputs!$A:$A,Inputs!G:G,,0) -> 6487 | H48: =_xlfn.XLOOKUP($A48,Inputs!$A:$A,Inputs!H:H,,0) -> 6487 | I48: =_xlfn.XLOOKUP($A48,Inputs!$A:$A,Inputs!I:I,,0) -> 5466 | J48: =_xlfn.XLOOKUP($A48,Inputs!$A:$A,Inputs!J:J,,0) -> 4587 | K48: =_xlfn.XLOOKUP($A48,Inputs!$A:$A,Inputs!K:K,,0) -> 3530 | L48: =_xlfn.XLOOKUP($A48,Inputs!$A:$A,Inputs!L:L,,0) -> 0 | M48: =_xlfn.XLOOKUP($A48,Inputs!$A:$A,Inputs!M:M,,0) -> 0
A49: Short-Term Debt | B49: =_xlfn.XLOOKUP($A49,Inputs!$A:$A,Inputs!B:B,,0) -> 0 | C49: =_xlfn.XLOOKUP($A49,Inputs!$A:$A,Inputs!C:C,,0) -> 0 | D49: =_xlfn.XLOOKUP($A49,Inputs!$A:$A,Inputs!D:D,,0) -> 0 | E49: =_xlfn.XLOOKUP($A49,Inputs!$A:$A,Inputs!E:E,,0) -> 0 | F49: =_xlfn.XLOOKUP($A49,Inputs!$A:$A,Inputs!F:F,,0) -> 0 | G49: =_xlfn.XLOOKUP($A49,Inputs!$A:$A,Inputs!G:G,,0) -> 0 | H49: =_xlfn.XLOOKUP($A49,Inputs!$A:$A,Inputs!H:H,,0) -> 0 | I49: =_xlfn.XLOOKUP($A49,Inputs!$A:$A,Inputs!I:I,,0) -> 0 | J49: =_xlfn.XLOOKUP($A49,Inputs!$A:$A,Inputs!J:J,,0) -> 0 | K49: =_xlfn.XLOOKUP($A49,Inputs!$A:$A,Inputs!K:K,,0) -> 0 | L49: =_xlfn.XLOOKUP($A49,Inputs!$A:$A,Inputs!L:L,,0) -> 0 | M49: =_xlfn.XLOOKUP($A49,Inputs!$A:$A,Inputs!M:M,,0) -> 0
A50: Short-Term Leases | B50: =_xlfn.XLOOKUP($A50,Inputs!$A:$A,Inputs!B:B,,0) -> 383 | C50: =_xlfn.XLOOKUP($A50,Inputs!$A:$A,Inputs!C:C,,0) -> 356 | D50: =_xlfn.XLOOKUP($A50,Inputs!$A:$A,Inputs!D:D,,0) -> 315 | E50: =_xlfn.XLOOKUP($A50,Inputs!$A:$A,Inputs!E:E,,0) -> 256 | F50: =_xlfn.XLOOKUP($A50,Inputs!$A:$A,Inputs!F:F,,0) -> 191 | G50: =_xlfn.XLOOKUP($A50,Inputs!$A:$A,Inputs!G:G,,0) -> 0 | H50: =_xlfn.XLOOKUP($A50,Inputs!$A:$A,Inputs!H:H,,0) -> 0 | I50: =_xlfn.XLOOKUP($A50,Inputs!$A:$A,Inputs!I:I,,0) -> 0 | J50: =_xlfn.XLOOKUP($A50,Inputs!$A:$A,Inputs!J:J,,0) -> 0 | K50: =_xlfn.XLOOKUP($A50,Inputs!$A:$A,Inputs!K:K,,0) -> 0 | L50: =_xlfn.XLOOKUP($A50,Inputs!$A:$A,Inputs!L:L,,0) -> 0 | M50: =_xlfn.XLOOKUP($A50,Inputs!$A:$A,Inputs!M:M,,0) -> 0
A51: Other current liabilities | B51: =_xlfn.XLOOKUP($A51,Inputs!$A:$A,Inputs!B:B,,0) -> 3264 | C51: =_xlfn.XLOOKUP($A51,Inputs!$A:$A,Inputs!C:C,,0) -> 2423 | D51: =_xlfn.XLOOKUP($A51,Inputs!$A:$A,Inputs!D:D,,0) -> 3044 | E51: =_xlfn.XLOOKUP($A51,Inputs!$A:$A,Inputs!E:E,,0) -> 2464 | F51: =_xlfn.XLOOKUP($A51,Inputs!$A:$A,Inputs!F:F,,0) -> 1577 | G51: =_xlfn.XLOOKUP($A51,Inputs!$A:$A,Inputs!G:G,,0) -> 1242 | H51: =_xlfn.XLOOKUP($A51,Inputs!$A:$A,Inputs!H:H,,0) -> 1238 | I51: =_xlfn.XLOOKUP($A51,Inputs!$A:$A,Inputs!I:I,,0) -> 933 | J51: =_xlfn.XLOOKUP($A51,Inputs!$A:$A,Inputs!J:J,,0) -> 641 | K51: =_xlfn.XLOOKUP($A51,Inputs!$A:$A,Inputs!K:K,,0) -> 487 | L51: =_xlfn.XLOOKUP($A51,Inputs!$A:$A,Inputs!L:L,,0) -> 0 | M51: =_xlfn.XLOOKUP($A51,Inputs!$A:$A,Inputs!M:M,,0) -> 0
A52: Non-current Liabilities | B52: =_xlfn.XLOOKUP($A52,Inputs!$A:$A,Inputs!B:B,,0) -> 19283 | C52: =_xlfn.XLOOKUP($A52,Inputs!$A:$A,Inputs!C:C,,0) -> 19886 | D52: =_xlfn.XLOOKUP($A52,Inputs!$A:$A,Inputs!D:D,,0) -> 20246 | E52: =_xlfn.XLOOKUP($A52,Inputs!$A:$A,Inputs!E:E,,0) -> 20409 | F52: =_xlfn.XLOOKUP($A52,Inputs!$A:$A,Inputs!F:F,,0) -> 19538 | G52: =_xlfn.XLOOKUP($A52,Inputs!$A:$A,Inputs!G:G,,0) -> 14249 | H52: =_xlfn.XLOOKUP($A52,Inputs!$A:$A,Inputs!H:H,,0) -> 14249 | I52: =_xlfn.XLOOKUP($A52,Inputs!$A:$A,Inputs!I:I,,0) -> 9965 | J52: =_xlfn.XLOOKUP($A52,Inputs!$A:$A,Inputs!J:J,,0) -> 6320 | K52: =_xlfn.XLOOKUP($A52,Inputs!$A:$A,Inputs!K:K,,0) -> 4449 | L52: =_xlfn.XLOOKUP($A52,Inputs!$A:$A,Inputs!L:L,,0) -> 0 | M52: =_xlfn.XLOOKUP($A52,Inputs!$A:$A,Inputs!M:M,,0) -> 0
A53: Long-Term Debt | B53: =_xlfn.XLOOKUP($A53,Inputs!$A:$A,Inputs!B:B,,0) -> 14143 | C53: =_xlfn.XLOOKUP($A53,Inputs!$A:$A,Inputs!C:C,,0) -> 14353 | D53: =_xlfn.XLOOKUP($A53,Inputs!$A:$A,Inputs!D:D,,0) -> 14693 | E53: =_xlfn.XLOOKUP($A53,Inputs!$A:$A,Inputs!E:E,,0) -> 15809 | F53: =_xlfn.XLOOKUP($A53,Inputs!$A:$A,Inputs!F:F,,0) -> 14759 | G53: =_xlfn.XLOOKUP($A53,Inputs!$A:$A,Inputs!G:G,,0) -> 10360 | H53: =_xlfn.XLOOKUP($A53,Inputs!$A:$A,Inputs!H:H,,0) -> 10388 | I53: =_xlfn.XLOOKUP($A53,Inputs!$A:$A,Inputs!I:I,,0) -> 6529 | J53: =_xlfn.XLOOKUP($A53,Inputs!$A:$A,Inputs!J:J,,0) -> 3394 | K53: =_xlfn.XLOOKUP($A53,Inputs!$A:$A,Inputs!K:K,,0) -> 2400 | L53: =_xlfn.XLOOKUP($A53,Inputs!$A:$A,Inputs!L:L,,0) -> 0 | M53: =_xlfn.XLOOKUP($A53,Inputs!$A:$A,Inputs!M:M,,0) -> 0
A54: Long-Term Leases | B54: =_xlfn.XLOOKUP($A54,Inputs!$A:$A,Inputs!B:B,,0) -> 2046 | C54: =_xlfn.XLOOKUP($A54,Inputs!$A:$A,Inputs!C:C,,0) -> 2223 | D54: =_xlfn.XLOOKUP($A54,Inputs!$A:$A,Inputs!D:D,,0) -> 2408 | E54: =_xlfn.XLOOKUP($A54,Inputs!$A:$A,Inputs!E:E,,0) -> 1946 | F54: =_xlfn.XLOOKUP($A54,Inputs!$A:$A,Inputs!F:F,,0) -> 1423 | G54: =_xlfn.XLOOKUP($A54,Inputs!$A:$A,Inputs!G:G,,0) -> 0 | H54: =_xlfn.XLOOKUP($A54,Inputs!$A:$A,Inputs!H:H,,0) -> 0 | I54: =_xlfn.XLOOKUP($A54,Inputs!$A:$A,Inputs!I:I,,0) -> 0 | J54: =_xlfn.XLOOKUP($A54,Inputs!$A:$A,Inputs!J:J,,0) -> 0 | K54: =_xlfn.XLOOKUP($A54,Inputs!$A:$A,Inputs!K:K,,0) -> 0 | L54: =_xlfn.XLOOKUP($A54,Inputs!$A:$A,Inputs!L:L,,0) -> 0 | M54: =_xlfn.XLOOKUP($A54,Inputs!$A:$A,Inputs!M:M,,0) -> 0
A55: Other non-current liabilities | B55: =_xlfn.XLOOKUP($A55,Inputs!$A:$A,Inputs!B:B,,0) -> 3094 | C55: =_xlfn.XLOOKUP($A55,Inputs!$A:$A,Inputs!C:C,,0) -> 3310 | D55: =_xlfn.XLOOKUP($A55,Inputs!$A:$A,Inputs!D:D,,0) -> 3145 | E55: =_xlfn.XLOOKUP($A55,Inputs!$A:$A,Inputs!E:E,,0) -> 2654 | F55: =_xlfn.XLOOKUP($A55,Inputs!$A:$A,Inputs!F:F,,0) -> 3356 | G55: =_xlfn.XLOOKUP($A55,Inputs!$A:$A,Inputs!G:G,,0) -> 3889 | H55: =_xlfn.XLOOKUP($A55,Inputs!$A:$A,Inputs!H:H,,0) -> 3861 | I55: =_xlfn.XLOOKUP($A55,Inputs!$A:$A,Inputs!I:I,,0) -> 3436 | J55: =_xlfn.XLOOKUP($A55,Inputs!$A:$A,Inputs!J:J,,0) -> 2926 | K55: =_xlfn.XLOOKUP($A55,Inputs!$A:$A,Inputs!K:K,,0) -> 2049 | L55: =_xlfn.XLOOKUP($A55,Inputs!$A:$A,Inputs!L:L,,0) -> 0 | M55: =_xlfn.XLOOKUP($A55,Inputs!$A:$A,Inputs!M:M,,0) -> 0
A56: Total Liabilities | B56: =_xlfn.XLOOKUP($A56,Inputs!$A:$A,Inputs!B:B,,0) -> 28144 | C56: =_xlfn.XLOOKUP($A56,Inputs!$A:$A,Inputs!C:C,,0) -> 27817 | D56: =_xlfn.XLOOKUP($A56,Inputs!$A:$A,Inputs!D:D,,0) -> 28735 | E56: =_xlfn.XLOOKUP($A56,Inputs!$A:$A,Inputs!E:E,,0) -> 28215 | F56: =_xlfn.XLOOKUP($A56,Inputs!$A:$A,Inputs!F:F,,0) -> 26394 | G56: =_xlfn.XLOOKUP($A56,Inputs!$A:$A,Inputs!G:G,,0) -> 20736 | H56: =_xlfn.XLOOKUP($A56,Inputs!$A:$A,Inputs!H:H,,0) -> 20736 | I56: =_xlfn.XLOOKUP($A56,Inputs!$A:$A,Inputs!I:I,,0) -> 15431 | J56: =_xlfn.XLOOKUP($A56,Inputs!$A:$A,Inputs!J:J,,0) -> 10907 | K56: =_xlfn.XLOOKUP($A56,Inputs!$A:$A,Inputs!K:K,,0) -> 7979 | L56: =_xlfn.XLOOKUP($A56,Inputs!$A:$A,Inputs!L:L,,0) -> 0 | M56: =_xlfn.XLOOKUP($A56,Inputs!$A:$A,Inputs!M:M,,0) -> 0
A58: Total Debt | B58: =B49+B53+B50+B54 -> 16572 | C58: =C49+C53+C50+C54 -> 16932 | D58: =D49+D53+D50+D54 -> 17416 | E58: =E49+E53+E50+E54 -> 18011 | F58: =F49+F53+F50+F54 -> 16373 | G58: =G49+G53+G50+G54 -> 10360 | H58: =H49+H53+H50+H54 -> 10388 | I58: =I49+I53+I50+I54 -> 6529 | ... M58: =M49+M53+M50+M54 -> 0
A59: Debt/Assets | B59: =IFERROR(B58/B44,"-") -> 0.34006402 | C59: =IFERROR(C58/C44,"-") -> 0.34843091 | D59: =IFERROR(D58/D44,"-") -> 0.39062465 | E59: =IFERROR(E58/E44,"-") -> 0.45852851 | F59: =IFERROR(F58/F44,"-") -> 0.48189899 | G59: =IFERROR(G58/G44,"-") -> 0.3988604 | H59: =IFERROR(H58/H44,"-") -> 0.3999384 | I59: =IFERROR(I58/I44,"-") -> 0.34339662 | ... M59: =IFERROR(M58/M44,"-") -> -
A60: Net Debt | B60: =B58-B39 -> 9434 | C60: =C58-C39 -> 10874 | D60: =D58-D39 -> 11388 | E60: =E58-E39 -> 9805 | F60: =F58-F39 -> 11355 | G60: =G58-G39 -> 6566 | H60: =H58-H39 -> 6594 | I60: =I58-I39 -> 3706 | ... M60: =M58-M39 -> 0
A62: Minority Interest | B62: =_xlfn.XLOOKUP($A62,Inputs!$A:$A,Inputs!B:B,,0) -> 0 | C62: =_xlfn.XLOOKUP($A62,Inputs!$A:$A,Inputs!C:C,,0) -> 0 | D62: =_xlfn.XLOOKUP($A62,Inputs!$A:$A,Inputs!D:D,,0) -> 0 | E62: =_xlfn.XLOOKUP($A62,Inputs!$A:$A,Inputs!E:E,,0) -> 0 | F62: =_xlfn.XLOOKUP($A62,Inputs!$A:$A,Inputs!F:F,,0) -> 0 | G62: =_xlfn.XLOOKUP($A62,Inputs!$A:$A,Inputs!G:G,,0) -> 0 | H62: =_xlfn.XLOOKUP($A62,Inputs!$A:$A,Inputs!H:H,,0) -> 0 | I62: =_xlfn.XLOOKUP($A62,Inputs!$A:$A,Inputs!I:I,,0) -> 0 | J62: =_xlfn.XLOOKUP($A62,Inputs!$A:$A,Inputs!J:J,,0) -> 0 | K62: =_xlfn.XLOOKUP($A62,Inputs!$A:$A,Inputs!K:K,,0) -> 0 | L62: =_xlfn.XLOOKUP($A62,Inputs!$A:$A,Inputs!L:L,,0) -> 0 | M62: =_xlfn.XLOOKUP($A62,Inputs!$A:$A,Inputs!M:M,,0) -> 0
A64: Shareholder's Equity | B64: =_xlfn.XLOOKUP($A64,Inputs!$A:$A,Inputs!B:B,,0) -> 20588 | C64: =_xlfn.XLOOKUP($A64,Inputs!$A:$A,Inputs!C:C,,0) -> 20778 | D64: =_xlfn.XLOOKUP($A64,Inputs!$A:$A,Inputs!D:D,,0) -> 15850 | E64: =_xlfn.XLOOKUP($A64,Inputs!$A:$A,Inputs!E:E,,0) -> 11065 | F64: =_xlfn.XLOOKUP($A64,Inputs!$A:$A,Inputs!F:F,,0) -> 7582 | G64: =_xlfn.XLOOKUP($A64,Inputs!$A:$A,Inputs!G:G,,0) -> 5238 | H64: =_xlfn.XLOOKUP($A64,Inputs!$A:$A,Inputs!H:H,,0) -> 5238 | I64: =_xlfn.XLOOKUP($A64,Inputs!$A:$A,Inputs!I:I,,0) -> 3582 | J64: =_xlfn.XLOOKUP($A64,Inputs!$A:$A,Inputs!J:J,,0) -> 2680 | K64: =_xlfn.XLOOKUP($A64,Inputs!$A:$A,Inputs!K:K,,0) -> 2224 | L64: =_xlfn.XLOOKUP($A64,Inputs!$A:$A,Inputs!L:L,,0) -> 0 | M64: =_xlfn.XLOOKUP($A64,Inputs!$A:$A,Inputs!M:M,,0) -> 0
A66: Cash Flow
A67: Operating CF | B67: =_xlfn.XLOOKUP($A67,Inputs!$A:$A,Inputs!B:B,,0) -> 7274.3 | C67: =_xlfn.XLOOKUP($A67,Inputs!$A:$A,Inputs!C:C,,0) -> 2026.3 | D67: =_xlfn.XLOOKUP($A67,Inputs!$A:$A,Inputs!D:D,,0) -> 392.6 | E67: =_xlfn.XLOOKUP($A67,Inputs!$A:$A,Inputs!E:E,,0) -> 2427.1 | F67: =_xlfn.XLOOKUP($A67,Inputs!$A:$A,Inputs!F:F,,0) -> -2887.3 | G67: =_xlfn.XLOOKUP($A67,Inputs!$A:$A,Inputs!G:G,,0) -> -2680.5 | H67: =_xlfn.XLOOKUP($A67,Inputs!$A:$A,Inputs!H:H,,0) -> -1785.9 | I67: =_xlfn.XLOOKUP($A67,Inputs!$A:$A,Inputs!I:I,,0) -> -1474 | J67: =_xlfn.XLOOKUP($A67,Inputs!$A:$A,Inputs!J:J,,0) -> -749.4 | K67: =_xlfn.XLOOKUP($A67,Inputs!$A:$A,Inputs!K:K,,0) -> 16.5 | L67: =_xlfn.XLOOKUP($A67,Inputs!$A:$A,Inputs!L:L,,0) -> 0 | M67: =_xlfn.XLOOKUP($A67,Inputs!$A:$A,Inputs!M:M,,0) -> 0
A68: Investing CF | B68: =_xlfn.XLOOKUP($A68,Inputs!$A:$A,Inputs!B:B,,0) -> 541.8 | C68: =_xlfn.XLOOKUP($A68,Inputs!$A:$A,Inputs!C:C,,0) -> -2076.4 | D68: =_xlfn.XLOOKUP($A68,Inputs!$A:$A,Inputs!D:D,,0) -> -1339.9 | E68: =_xlfn.XLOOKUP($A68,Inputs!$A:$A,Inputs!E:E,,0) -> -505.4 | F68: =_xlfn.XLOOKUP($A68,Inputs!$A:$A,Inputs!F:F,,0) -> -387.1 | G68: =_xlfn.XLOOKUP($A68,Inputs!$A:$A,Inputs!G:G,,0) -> -339.1 | H68: =_xlfn.XLOOKUP($A68,Inputs!$A:$A,Inputs!H:H,,0) -> 34.3 | I68: =_xlfn.XLOOKUP($A68,Inputs!$A:$A,Inputs!I:I,,0) -> 49.8 | J68: =_xlfn.XLOOKUP($A68,Inputs!$A:$A,Inputs!J:J,,0) -> -179.2 | K68: =_xlfn.XLOOKUP($A68,Inputs!$A:$A,Inputs!K:K,,0) -> -42.9 | L68: =_xlfn.XLOOKUP($A68,Inputs!$A:$A,Inputs!L:L,,0) -> 0 | M68: =_xlfn.XLOOKUP($A68,Inputs!$A:$A,Inputs!M:M,,0) -> 0
A69: Net Capex | B69: =_xlfn.XLOOKUP($A69,Inputs!$A:$A,Inputs!B:B,,0) -> -348.6 | C69: =_xlfn.XLOOKUP($A69,Inputs!$A:$A,Inputs!C:C,,0) -> -407.7 | D69: =_xlfn.XLOOKUP($A69,Inputs!$A:$A,Inputs!D:D,,0) -> -524.6 | E69: =_xlfn.XLOOKUP($A69,Inputs!$A:$A,Inputs!E:E,,0) -> -497.9 | F69: =_xlfn.XLOOKUP($A69,Inputs!$A:$A,Inputs!F:F,,0) -> -253 | G69: =_xlfn.XLOOKUP($A69,Inputs!$A:$A,Inputs!G:G,,0) -> -212.5 | H69: =_xlfn.XLOOKUP($A69,Inputs!$A:$A,Inputs!H:H,,0) -> -227 | I69: =_xlfn.XLOOKUP($A69,Inputs!$A:$A,Inputs!I:I,,0) -> -184.8 | J69: =_xlfn.XLOOKUP($A69,Inputs!$A:$A,Inputs!J:J,,0) -> -169.2 | K69: =_xlfn.XLOOKUP($A69,Inputs!$A:$A,Inputs!K:K,,0) -> -144.5 | L69: =_xlfn.XLOOKUP($A69,Inputs!$A:$A,Inputs!L:L,,0) -> 0 | M69: =_xlfn.XLOOKUP($A69,Inputs!$A:$A,Inputs!M:M,,0) -> 0
A70: Investments & Acquisitions | B70: =_xlfn.XLOOKUP($A70,Inputs!$A:$A,Inputs!B:B,,0) -> -504.9 | C70: =_xlfn.XLOOKUP($A70,Inputs!$A:$A,Inputs!C:C,,0) -> -1668.7 | D70: =_xlfn.XLOOKUP($A70,Inputs!$A:$A,Inputs!D:D,,0) -> -788.3 | E70: =_xlfn.XLOOKUP($A70,Inputs!$A:$A,Inputs!E:E,,0) -> 0 | F70: =_xlfn.XLOOKUP($A70,Inputs!$A:$A,Inputs!F:F,,0) -> 0 | G70: =_xlfn.XLOOKUP($A70,Inputs!$A:$A,Inputs!G:G,,0) -> 0 | H70: =_xlfn.XLOOKUP($A70,Inputs!$A:$A,Inputs!H:H,,0) -> -74.8 | I70: =_xlfn.XLOOKUP($A70,Inputs!$A:$A,Inputs!I:I,,0) -> -187.2 | J70: =_xlfn.XLOOKUP($A70,Inputs!$A:$A,Inputs!J:J,,0) -> -371.9 | K70: =_xlfn.XLOOKUP($A70,Inputs!$A:$A,Inputs!K:K,,0) -> -426.9 | L70: =_xlfn.XLOOKUP($A70,Inputs!$A:$A,Inputs!L:L,,0) -> 0 | M70: =_xlfn.XLOOKUP($A70,Inputs!$A:$A,Inputs!M:M,,0) -> 0
A71: Financing CF | B71: =_xlfn.XLOOKUP($A71,Inputs!$A:$A,Inputs!B:B,,0) -> -5950.8 | C71: =_xlfn.XLOOKUP($A71,Inputs!$A:$A,Inputs!C:C,,0) -> -664.3 | D71: =_xlfn.XLOOKUP($A71,Inputs!$A:$A,Inputs!D:D,,0) -> -1149.8 | E71: =_xlfn.XLOOKUP($A71,Inputs!$A:$A,Inputs!E:E,,0) -> 1237.3 | F71: =_xlfn.XLOOKUP($A71,Inputs!$A:$A,Inputs!F:F,,0) -> 4505.7 | G71: =_xlfn.XLOOKUP($A71,Inputs!$A:$A,Inputs!G:G,,0) -> 4048.5 | H71: =_xlfn.XLOOKUP($A71,Inputs!$A:$A,Inputs!H:H,,0) -> 3077 | I71: =_xlfn.XLOOKUP($A71,Inputs!$A:$A,Inputs!I:I,,0) -> 1091.6 | J71: =_xlfn.XLOOKUP($A71,Inputs!$A:$A,Inputs!J:J,,0) -> 1640.3 | K71: =_xlfn.XLOOKUP($A71,Inputs!$A:$A,Inputs!K:K,,0) -> 541.7 | L71: =_xlfn.XLOOKUP($A71,Inputs!$A:$A,Inputs!L:L,,0) -> 0 | M71: =_xlfn.XLOOKUP($A71,Inputs!$A:$A,Inputs!M:M,,0) -> 0
A72: Dividends | B72: =_xlfn.XLOOKUP($A72,Inputs!$A:$A,Inputs!B:B,,0) -> 0 | C72: =_xlfn.XLOOKUP($A72,Inputs!$A:$A,Inputs!C:C,,0) -> 0 | D72: =_xlfn.XLOOKUP($A72,Inputs!$A:$A,Inputs!D:D,,0) -> 0 | E72: =_xlfn.XLOOKUP($A72,Inputs!$A:$A,Inputs!E:E,,0) -> 0 | F72: =_xlfn.XLOOKUP($A72,Inputs!$A:$A,Inputs!F:F,,0) -> 0 | G72: =_xlfn.XLOOKUP($A72,Inputs!$A:$A,Inputs!G:G,,0) -> 0 | H72: =_xlfn.XLOOKUP($A72,Inputs!$A:$A,Inputs!H:H,,0) -> 0 | I72: =_xlfn.XLOOKUP($A72,Inputs!$A:$A,Inputs!I:I,,0) -> 0 | J72: =_xlfn.XLOOKUP($A72,Inputs!$A:$A,Inputs!J:J,,0) -> 0 | K72: =_xlfn.XLOOKUP($A72,Inputs!$A:$A,Inputs!K:K,,0) -> 0 | L72: =_xlfn.XLOOKUP($A72,Inputs!$A:$A,Inputs!L:L,,0) -> 0 | M72: =_xlfn.XLOOKUP($A72,Inputs!$A:$A,Inputs!M:M,,0) -> 0
A73: Share buyback | B73: =_xlfn.XLOOKUP($A73,Inputs!$A:$A,Inputs!B:B,,0) -> -6045.3 | C73: =_xlfn.XLOOKUP($A73,Inputs!$A:$A,Inputs!C:C,,0) -> 0 | D73: =_xlfn.XLOOKUP($A73,Inputs!$A:$A,Inputs!D:D,,0) -> -600 | E73: =_xlfn.XLOOKUP($A73,Inputs!$A:$A,Inputs!E:E,,0) -> 0 | F73: =_xlfn.XLOOKUP($A73,Inputs!$A:$A,Inputs!F:F,,0) -> 0 | G73: =_xlfn.XLOOKUP($A73,Inputs!$A:$A,Inputs!G:G,,0) -> 0 | H73: =_xlfn.XLOOKUP($A73,Inputs!$A:$A,Inputs!H:H,,0) -> 0 | I73: =_xlfn.XLOOKUP($A73,Inputs!$A:$A,Inputs!I:I,,0) -> 0 | J73: =_xlfn.XLOOKUP($A73,Inputs!$A:$A,Inputs!J:J,,0) -> 0 | K73: =_xlfn.XLOOKUP($A73,Inputs!$A:$A,Inputs!K:K,,0) -> 0 | L73: =_xlfn.XLOOKUP($A73,Inputs!$A:$A,Inputs!L:L,,0) -> 0 | M73: =_xlfn.XLOOKUP($A73,Inputs!$A:$A,Inputs!M:M,,0) -> 0
A74: FX | B74: =_xlfn.XLOOKUP($A74,Inputs!$A:$A,Inputs!B:B,,0) -> 82.7 | C74: =_xlfn.XLOOKUP($A74,Inputs!$A:$A,Inputs!C:C,,0) -> -170.1 | D74: =_xlfn.XLOOKUP($A74,Inputs!$A:$A,Inputs!D:D,,0) -> -86.7 | E74: =_xlfn.XLOOKUP($A74,Inputs!$A:$A,Inputs!E:E,,0) -> 36.1 | F74: =_xlfn.XLOOKUP($A74,Inputs!$A:$A,Inputs!F:F,,0) -> 0.5 | G74: =_xlfn.XLOOKUP($A74,Inputs!$A:$A,Inputs!G:G,,0) -> -39.7 | H74: =_xlfn.XLOOKUP($A74,Inputs!$A:$A,Inputs!H:H,,0) -> 29.8 | I74: =_xlfn.XLOOKUP($A74,Inputs!$A:$A,Inputs!I:I,,0) -> -9.2 | J74: =_xlfn.XLOOKUP($A74,Inputs!$A:$A,Inputs!J:J,,0) -> -15.9 | K74: =_xlfn.XLOOKUP($A74,Inputs!$A:$A,Inputs!K:K,,0) -> -6.7 | L74: =_xlfn.XLOOKUP($A74,Inputs!$A:$A,Inputs!L:L,,0) -> 0 | M74: =_xlfn.XLOOKUP($A74,Inputs!$A:$A,Inputs!M:M,,0) -> 0
A75: Changes in cash | B75: =_xlfn.XLOOKUP($A75,Inputs!$A:$A,Inputs!B:B,,0) -> 1948 | C75: =_xlfn.XLOOKUP($A75,Inputs!$A:$A,Inputs!C:C,,0) -> -884.5 | D75: =_xlfn.XLOOKUP($A75,Inputs!$A:$A,Inputs!D:D,,0) -> -2183.8 | E75: =_xlfn.XLOOKUP($A75,Inputs!$A:$A,Inputs!E:E,,0) -> 3195.1 | F75: =_xlfn.XLOOKUP($A75,Inputs!$A:$A,Inputs!F:F,,0) -> 1231.8 | G75: =_xlfn.XLOOKUP($A75,Inputs!$A:$A,Inputs!G:G,,0) -> 989.2 | H75: =_xlfn.XLOOKUP($A75,Inputs!$A:$A,Inputs!H:H,,0) -> 1355.2 | I75: =_xlfn.XLOOKUP($A75,Inputs!$A:$A,Inputs!I:I,,0) -> -341.8 | J75: =_xlfn.XLOOKUP($A75,Inputs!$A:$A,Inputs!J:J,,0) -> 695.8 | K75: =_xlfn.XLOOKUP($A75,Inputs!$A:$A,Inputs!K:K,,0) -> 508.6 | L75: =_xlfn.XLOOKUP($A75,Inputs!$A:$A,Inputs!L:L,,0) -> 0 | M75: =_xlfn.XLOOKUP($A75,Inputs!$A:$A,Inputs!M:M,,0) -> 0
A77: Other Data
A78: Number of employees | B78: =_xlfn.XLOOKUP($A78,Inputs!$A:$A,Inputs!B:B,,0) -> #N/A | C78: =_xlfn.XLOOKUP($A78,Inputs!$A:$A,Inputs!C:C,,0) -> #N/A | D78: =_xlfn.XLOOKUP($A78,Inputs!$A:$A,Inputs!D:D,,0) -> #N/A | E78: =_xlfn.XLOOKUP($A78,Inputs!$A:$A,Inputs!E:E,,0) -> #N/A | F78: =_xlfn.XLOOKUP($A78,Inputs!$A:$A,Inputs!F:F,,0) -> #N/A | G78: =_xlfn.XLOOKUP($A78,Inputs!$A:$A,Inputs!G:G,,0) -> #N/A | H78: =_xlfn.XLOOKUP($A78,Inputs!$A:$A,Inputs!H:H,,0) -> #N/A | I78: =_xlfn.XLOOKUP($A78,Inputs!$A:$A,Inputs!I:I,,0) -> #N/A | J78: =_xlfn.XLOOKUP($A78,Inputs!$A:$A,Inputs!J:J,,0) -> #N/A | K78: =_xlfn.XLOOKUP($A78,Inputs!$A:$A,Inputs!K:K,,0) -> #N/A | L78: =_xlfn.XLOOKUP($A78,Inputs!$A:$A,Inputs!L:L,,0) -> #N/A | M78: =_xlfn.XLOOKUP($A78,Inputs!$A:$A,Inputs!M:M,,0) -> #N/A
A79: Shares Outstanding | B79: =_xlfn.XLOOKUP($A79,Inputs!$A:$A,Inputs!B:B,,0) -> #N/A | C79: =_xlfn.XLOOKUP($A79,Inputs!$A:$A,Inputs!C:C,,0) -> #N/A | D79: =_xlfn.XLOOKUP($A79,Inputs!$A:$A,Inputs!D:D,,0) -> #N/A | E79: =_xlfn.XLOOKUP($A79,Inputs!$A:$A,Inputs!E:E,,0) -> #N/A | F79: =_xlfn.XLOOKUP($A79,Inputs!$A:$A,Inputs!F:F,,0) -> #N/A | G79: =_xlfn.XLOOKUP($A79,Inputs!$A:$A,Inputs!G:G,,0) -> #N/A | H79: =_xlfn.XLOOKUP($A79,Inputs!$A:$A,Inputs!H:H,,0) -> #N/A | I79: =_xlfn.XLOOKUP($A79,Inputs!$A:$A,Inputs!I:I,,0) -> #N/A | J79: =_xlfn.XLOOKUP($A79,Inputs!$A:$A,Inputs!J:J,,0) -> #N/A | K79: =_xlfn.XLOOKUP($A79,Inputs!$A:$A,Inputs!K:K,,0) -> #N/A | L79: =_xlfn.XLOOKUP($A79,Inputs!$A:$A,Inputs!L:L,,0) -> #N/A | M79: =_xlfn.XLOOKUP($A79,Inputs!$A:$A,Inputs!M:M,,0) -> #N/A
A80: Float | B80: =_xlfn.XLOOKUP($A80,Inputs!$A:$A,Inputs!B:B,,0) -> 0.99017931 | C80: =_xlfn.XLOOKUP($A80,Inputs!$A:$A,Inputs!C:C,,0) -> Yahoo finance | D80: =_xlfn.XLOOKUP($A80,Inputs!$A:$A,Inputs!D:D,,0) -> 0 | E80: =_xlfn.XLOOKUP($A80,Inputs!$A:$A,Inputs!E:E,,0) -> 0 | F80: =_xlfn.XLOOKUP($A80,Inputs!$A:$A,Inputs!F:F,,0) -> 0 | G80: =_xlfn.XLOOKUP($A80,Inputs!$A:$A,Inputs!G:G,,0) -> 0 | H80: =_xlfn.XLOOKUP($A80,Inputs!$A:$A,Inputs!H:H,,0) -> 0 | I80: =_xlfn.XLOOKUP($A80,Inputs!$A:$A,Inputs!I:I,,0) -> 0 | J80: =_xlfn.XLOOKUP($A80,Inputs!$A:$A,Inputs!J:J,,0) -> 0 | K80: =_xlfn.XLOOKUP($A80,Inputs!$A:$A,Inputs!K:K,,0) -> 0 | L80: =_xlfn.XLOOKUP($A80,Inputs!$A:$A,Inputs!L:L,,0) -> 0 | M80: =_xlfn.XLOOKUP($A80,Inputs!$A:$A,Inputs!M:M,,0) -> 0
A81: Insiders Own | B81: =_xlfn.XLOOKUP($A81,Inputs!$A:$A,Inputs!B:B,,0) -> 0.0138 | C81: =_xlfn.XLOOKUP($A81,Inputs!$A:$A,Inputs!C:C,,0) -> Yahoo finance | D81: =_xlfn.XLOOKUP($A81,Inputs!$A:$A,Inputs!D:D,,0) -> 0 | E81: =_xlfn.XLOOKUP($A81,Inputs!$A:$A,Inputs!E:E,,0) -> 0 | F81: =_xlfn.XLOOKUP($A81,Inputs!$A:$A,Inputs!F:F,,0) -> 0 | G81: =_xlfn.XLOOKUP($A81,Inputs!$A:$A,Inputs!G:G,,0) -> 0 | H81: =_xlfn.XLOOKUP($A81,Inputs!$A:$A,Inputs!H:H,,0) -> 0 | I81: =_xlfn.XLOOKUP($A81,Inputs!$A:$A,Inputs!I:I,,0) -> 0 | J81: =_xlfn.XLOOKUP($A81,Inputs!$A:$A,Inputs!J:J,,0) -> 0 | K81: =_xlfn.XLOOKUP($A81,Inputs!$A:$A,Inputs!K:K,,0) -> 0 | L81: =_xlfn.XLOOKUP($A81,Inputs!$A:$A,Inputs!L:L,,0) -> 0 | M81: =_xlfn.XLOOKUP($A81,Inputs!$A:$A,Inputs!M:M,,0) -> 0
A82: Fitch/ S&P Rating | B82: =_xlfn.XLOOKUP($A82,Inputs!$A:$A,Inputs!B:B,,0) -> 0 | C82: =_xlfn.XLOOKUP($A82,Inputs!$A:$A,Inputs!C:C,,0) -> 10-K | D82: =_xlfn.XLOOKUP($A82,Inputs!$A:$A,Inputs!D:D,,0) -> 0 | E82: =_xlfn.XLOOKUP($A82,Inputs!$A:$A,Inputs!E:E,,0) -> 0 | F82: =_xlfn.XLOOKUP($A82,Inputs!$A:$A,Inputs!F:F,,0) -> 0 | G82: =_xlfn.XLOOKUP($A82,Inputs!$A:$A,Inputs!G:G,,0) -> 0 | H82: =_xlfn.XLOOKUP($A82,Inputs!$A:$A,Inputs!H:H,,0) -> 0 | I82: =_xlfn.XLOOKUP($A82,Inputs!$A:$A,Inputs!I:I,,0) -> 0 | J82: =_xlfn.XLOOKUP($A82,Inputs!$A:$A,Inputs!J:J,,0) -> 0 | K82: =_xlfn.XLOOKUP($A82,Inputs!$A:$A,Inputs!K:K,,0) -> 0 | L82: =_xlfn.XLOOKUP($A82,Inputs!$A:$A,Inputs!L:L,,0) -> 0 | M82: =_xlfn.XLOOKUP($A82,Inputs!$A:$A,Inputs!M:M,,0) -> 0
A83: Dividend Yield | B83: =_xlfn.XLOOKUP($A83,Inputs!$A:$A,Inputs!B:B,,0) -> #N/A | C83: =_xlfn.XLOOKUP($A83,Inputs!$A:$A,Inputs!C:C,,0) -> #N/A | D83: =_xlfn.XLOOKUP($A83,Inputs!$A:$A,Inputs!D:D,,0) -> #N/A | E83: =_xlfn.XLOOKUP($A83,Inputs!$A:$A,Inputs!E:E,,0) -> #N/A | F83: =_xlfn.XLOOKUP($A83,Inputs!$A:$A,Inputs!F:F,,0) -> #N/A | G83: =_xlfn.XLOOKUP($A83,Inputs!$A:$A,Inputs!G:G,,0) -> #N/A | H83: =_xlfn.XLOOKUP($A83,Inputs!$A:$A,Inputs!H:H,,0) -> #N/A | I83: =_xlfn.XLOOKUP($A83,Inputs!$A:$A,Inputs!I:I,,0) -> #N/A | J83: =_xlfn.XLOOKUP($A83,Inputs!$A:$A,Inputs!J:J,,0) -> #N/A | K83: =_xlfn.XLOOKUP($A83,Inputs!$A:$A,Inputs!K:K,,0) -> #N/A | L83: =_xlfn.XLOOKUP($A83,Inputs!$A:$A,Inputs!L:L,,0) -> #N/A | M83: =_xlfn.XLOOKUP($A83,Inputs!$A:$A,Inputs!M:M,,0) -> #N/A
A84: Daily Volume in Millions of USD | B84: =_xlfn.XLOOKUP($A84,Inputs!$A:$A,Inputs!B:B,,0) -> 0 | C84: =_xlfn.XLOOKUP($A84,Inputs!$A:$A,Inputs!C:C,,0) -> Yahoo Finance | D84: =_xlfn.XLOOKUP($A84,Inputs!$A:$A,Inputs!D:D,,0) -> 0 | E84: =_xlfn.XLOOKUP($A84,Inputs!$A:$A,Inputs!E:E,,0) -> 0 | F84: =_xlfn.XLOOKUP($A84,Inputs!$A:$A,Inputs!F:F,,0) -> 0 | G84: =_xlfn.XLOOKUP($A84,Inputs!$A:$A,Inputs!G:G,,0) -> 0 | H84: =_xlfn.XLOOKUP($A84,Inputs!$A:$A,Inputs!H:H,,0) -> 0 | I84: =_xlfn.XLOOKUP($A84,Inputs!$A:$A,Inputs!I:I,,0) -> 0 | J84: =_xlfn.XLOOKUP($A84,Inputs!$A:$A,Inputs!J:J,,0) -> 0 | K84: =_xlfn.XLOOKUP($A84,Inputs!$A:$A,Inputs!K:K,,0) -> 0 | L84: =_xlfn.XLOOKUP($A84,Inputs!$A:$A,Inputs!L:L,,0) -> 0 | M84: =_xlfn.XLOOKUP($A84,Inputs!$A:$A,Inputs!M:M,,0) -> 0
B86: 2020 | C86: 2021 | D86: 2022
A87: Short % of Float | B87: 0 | C87: 0 | D87: 0
A88: EPS | B88: 0 | C88: 0 | D88: 0
A90: Corporate Bonds 3, 5 Y 10 | B90: Average Price | C90: Moody's | D90: YTM | E90: DIVISA
B91: =VLOOKUP($A91,Inputs!$A$5:$M$98,MATCH(B$4,Inputs!$B$5:$M$5,0)+1,FALSE) -> #N/A | C91: =VLOOKUP($A91,Inputs!$A$5:$M$98,MATCH(C$4,Inputs!$B$5:$M$5,0)+1,FALSE) -> #N/A | D91: =VLOOKUP($A91,Inputs!$A$5:$M$98,MATCH(D$4,Inputs!$B$5:$M$5,0)+1,FALSE) -> #N/A | E91: =VLOOKUP($A91,Inputs!$A$5:$M$98,MATCH(E$4,Inputs!$B$5:$M$5,0)+1,FALSE) -> #N/A

Sheet Sector Impact
E2: Sector | F2: Sub-Industry | H2: Low | K2: Sector | L2: Environment | Q2: Social
E3: Communication Services | F3: Interactive Home Entertainment | H3: Medium | L3: CO2 | M3: Water | N3: Energy | O3: Waste | P3: Degradation | Q3: Turnover | R3: Compensation | S3: Reputation | T3: Discrimination | U3: Security | V3: Damage | W3: Pension | X3: Supply | Y3: Community | Z3: Public | AA3: Litigation
E4: Communication Services | F4: Interactive Media & Services | H4: High | K4: Communication Services | L4: Low | M4: Low | N4: Medium | O4: Low | P4: Low | Q4: Medium | R4: Medium | S4: Low | T4: Low | U4: High | V4: Low | W4: Low | X4: Low | Y4: Low | Z4: Low | AA4: Medium
B5: Environmental | E5: Communication Services | F5: Integrated Telecommunication Services | H5: Very High | K5: Consumer Discretionary | L5: Low | M5: Low | N5: Medium | O5: Medium | P5: Low | Q5: Medium | R5: Medium | S5: Low | T5: Low | U5: Medium | V5: Medium | W5: Medium | X5: High | Y5: Low | Z5: High | AA5: Low
B6: Direct CO2 emissions | E6: Communication Services | F6: Cable & Satellite | K6: Consumer Staples | L6: High | M6: Very High | N6: High | O6: High | P6: High | Q6: Medium | R6: High | S6: High | T6: Low | U6: Medium | V6: Medium | W6: Low | X6: High | Y6: Low | Z6: Very High | AA6: Low
B7: Total Water Use | E7: Communication Services | F7: Broadcasting | K7: Energy | L7: Very High | M7: Very High | N7: Medium | O7: Very High | P7: High | Q7: High | R7: Medium | S7: Medium | T7: Medium | U7: Medium | V7: High | W7: Medium | X7: Medium | Y7: High | Z7: High | AA7: Low
K8: Renewable Energy | L8: Low | M8: Low | N8: Low | O8: Medium | P8: Medium | Q8: Low | R8: Medium | S8: Medium | T8: High | U8: Medium | V8: Low | W8: Low | X8: Medium | Y8: Medium | Z8: High | AA8: Low
B9: Total Energy Consumption | E9: Communication Services | F9: Movies & Entertainment | K9: Financials | L9: Low | M9: Low | N9: Low | O9: Low | P9: Low | Q9: Low | R9: Low | S9: Medium | T9: High | U9: Medium | V9: Low | W9: Low | X9: Low | Y9: Low | Z9: Medium | AA9: Low
K10: Forestry | L10: Low | M10: Medium | N10: Low | O10: Medium | P10: High | Q10: Low | R10: Low | S10: Low | T10: Low | U10: Low | V10: Low | W10: Low | X10: Low | Y10: Medium | Z10: Low | AA10: Low
B11: Waste Management | E11: Communication Services | F11: Advertising | K11: Health Care | L11: Low | M11: Medium | N11: Low | O11: Low | P11: Low | Q11: Low | R11: Low | S11: Medium | T11: Low | U11: High | V11: Low | W11: Low | X11: Low | Y11: Low | Z11: Low | AA11: Low
B12: Land Degradation/Deforestation/Biodiversity loss/Animal sufering/... | E12: Communication Services | F12: Alternative Carriers | K12: Industrials | L12: Very High | M12: Very High | N12: Very High | O12: High | P12: High | Q12: Low | R12: Medium | S12: High | T12: Very High | U12: Medium | V12: Very High | W12: Medium | X12: Very High | Y12: Very High | Z12: Very High | AA12: High
B13: Social | E13: Communication Services | F13: Publishing | K13: Information Technology | L13: Medium | M13: Low | N13: High | O13: Low | P13: Low | Q13: Low | R13: Low | S13: Low | T13: Low | U13: High | V13: Low | W13: Low | X13: Low | Y13: Low | Z13: Medium | AA13: Very High
B14: Employee turnover | E14: Communication Services | F14: Wireless Telecommunication Services | K14: Materials | L14: Very High | M14: Very High | N14: Very High | O14: Very High | P14: High | Q14: High | R14: High | S14: Medium | T14: High | U14: Low | V14: Very High | W14: Medium | X14: Medium | Y14: Very High | Z14: High | AA14: Medium
B15: Salaries and compensation | E15: Consumer Discretionary | F15: Automotive Retail | K15: Real Estate | L15: Low | M15: Low | N15: Medium | O15: Low | P15: Low | Q15: Medium | R15: Low | S15: Low | T15: Low | U15: High | V15: Low | W15: Medium | X15: Low | Y15: Medium | Z15: Low | AA15: Low
B16: Reputational issues | E16: Consumer Discretionary | F16: Internet & Direct Marketing Retail | K16: Utilities | L16: Very High | M16: High | N16: High | O16: Medium | P16: High | Q16: Low | R16: Medium | S16: Medium | T16: Low | U16: Medium | V16: Medium | W16: Medium | X16: Medium | Y16: Low | Z16: Medium | AA16: Low
B17: Discrimination issues | E17: Consumer Discretionary | F17: Auto Parts & Equipment
B18: Job security | E18: Consumer Discretionary | F18: Specialty Stores
B19: Health injuries | E19: Consumer Discretionary | F19: Computer & Electronics Retail | L19: Communication Services | M19: Consumer Discretionary | N19: Consumer Staples | O19: Energy | P19: Financials | Q19: Health Care | R19: Industrials | S19: Information Technology | T19: Materials | U19: Real Estate | V19: Utilities
B20: PXP? | E20: Consumer Discretionary | F20: Hotels, Resorts & Cruise Lines | L20: Interactive Home Entertainment | M20: Automotive Retail | N20: Tobacco | O20: Oil & Gas Exploration & Production | P20: Life & Health Insurance | Q20: Health Care Equipment | R20: Industrial Conglomerates | S20: IT Consulting & Other Services | T20: Industrial Gases | U20: Office REITs | V20: Independent Power Producers & Energy Traders
B21: Supply chain | E21: Consumer Discretionary | F21: Restaurants | L21: Interactive Media & Services | M21: Internet & Direct Marketing Retail | N21: Agricultural Products | O21: Oil & Gas Equipment & Services | P21: Property & Casualty Insurance | Q21: Pharmaceuticals | R21: Airlines | S21: Application Software | T21: Specialty Chemicals | U21: Specialized REITs | V21: Electric Utilities
B22: Community involvement | E22: Consumer Discretionary | F22: Homebuilding | L22: Integrated Telecommunication Services | M22: Auto Parts & Equipment | N22: Distillers & Vintners | O22: Integrated Oil & Gas | P22: Consumer Finance | Q22: Health Care Supplies | R22: Building Products | S22: Semiconductors | T22: Paper Packaging | U22: Residential REITs | V22: Multi-Utilities
B23: Public Sector | E23: Consumer Discretionary | F23: General Merchandise Stores | L23: Cable & Satellite | M23: Specialty Stores | N23: Packaged Foods & Meats | O23: Oil & Gas Refining & Marketing | P23: Asset Management & Custody Banks | Q23: Health Care Distributors | R23: Electrical Components & Equipment | S23: Internet Services & Infrastructure | T23: Metal & Glass Containers | U23: Real Estate Services | V23: Water Utilities
B24: Litigation | E24: Consumer Discretionary | F24: Automobile Manufacturers | L24: Broadcasting | M24: Computer & Electronics Retail | N24: Household Products | O24: Oil & Gas Storage & Transportation | P24: Insurance Brokers | Q24: Biotechnology | R24: Aerospace & Defense | S24: Electronic Components | T24: Fertilizers & Agricultural Chemicals | U24: Industrial REITs | V24: Gas Utilities
E25: Consumer Discretionary | F25: Apparel Retail | L25: Movies & Entertainment | M25: Hotels, Resorts & Cruise Lines | N25: Soft Drinks | P25: Multi-line Insurance | Q25: Managed Health Care | R25: Air Freight & Logistics | S25: Technology Hardware, Storage & Peripherals | T25: Commodity Chemicals | U25: Retail REITs
E26: Consumer Discretionary | F26: Consumer Electronics | L26: Advertising | M26: Restaurants | N26: Hypermarkets & Super Centers | P26: Diversified Banks | Q26: Life Sciences Tools & Services | R26: Construction Machinery & Heavy Trucks | S26: Semiconductor Equipment | T26: Diversified Chemicals | U26: Health Care REITs
E27: Consumer Discretionary | F27: Apparel, Accessories & Luxury Goods | L27: Alternative Carriers | M27: Homebuilding | N27: Personal Products | P27: Multi-Sector Holdings | Q27: Health Care Technology | R27: Diversified Support Services | S27: Communications Equipment | T27: Copper | U27: Hotel & Resort REITs
E28: Consumer Discretionary | F28: Leisure Products | L28: Publishing | M28: General Merchandise Stores | N28: Food Retail | P28: Financial Exchanges & Data | Q28: Health Care Services | R28: Railroads | S28: Data Processing & Outsourced Services | T28: Construction Materials
E29: Consumer Discretionary | F29: Home Improvement Retail | L29: Wireless Telecommunication Services | M29: Automobile Manufacturers | N29: Brewers | P29: Investment Banking & Brokerage | Q29: Health Care Facilities | R29: Industrial Machinery | S29: Technology Distributors | T29: Gold
E30: Consumer Discretionary | F30: Casinos & Gaming | M30: Apparel Retail | N30: Food Distributors | P30: Regional Banks | R30: Agricultural & Farm Machinery | S30: Electronic Equipment & Instruments | T30: Steel
E31: Consumer Discretionary | F31: Home Furnishings | M31: Consumer Electronics | N31: Drug Retail | P31: Reinsurance | R31: Research & Consulting Services | S31: Systems Software
E32: Consumer Discretionary | F32: Distributors | M32: Apparel, Accessories & Luxury Goods | P32: Thrifts & Mortgage Finance | R32: Construction & Engineering | S32: Electronic Manufacturing Services
E33: Consumer Discretionary | F33: Housewares & Specialties | M33: Leisure Products | R33: Trucking
E34: Consumer Discretionary | F34: Household Appliances | M34: Home Improvement Retail | R34: Environmental & Facilities Services
E35: Consumer Staples | F35: Tobacco | M35: Casinos & Gaming | R35: Human Resource & Employment Services
E36: Consumer Staples | F36: Agricultural Products | M36: Home Furnishings | R36: Trading Companies & Distributors
E37: Consumer Staples | F37: Distillers & Vintners | M37: Distributors
E38: Consumer Staples | F38: Packaged Foods & Meats | M38: Housewares & Specialties
E39: Consumer Staples | F39: Household Products | M39: Household Appliances
E40: Consumer Staples | F40: Soft Drinks
E41: Consumer Staples | F41: Hypermarkets & Super Centers
E42: Consumer Staples | F42: Personal Products
E43: Consumer Staples | F43: Food Retail
E44: Consumer Staples | F44: Brewers
E45: Consumer Staples | F45: Food Distributors
E46: Consumer Staples | F46: Drug Retail
E47: Energy | F47: Oil & Gas Exploration & Production
E48: Energy | F48: Oil & Gas Equipment & Services
E49: Energy | F49: Integrated Oil & Gas
E50: Energy | F50: Oil & Gas Refining & Marketing
E51: Energy | F51: Oil & Gas Storage & Transportation
... E128: Utilities | F128: Gas Utilities

Sheet Inputs
G2: Figures in Millions of USD
G3: Company | H3: #VALUE!
D4: Report in millions
A5: RESULTS | B5: 2023 | C5: =B5-1 -> 2022 | D5: =C5-1 -> 2021 | E5: =D5-1 -> 2020 | F5: =E5-1 -> 2019 | G5: =F5-1 -> 2018 | H5: =G5-1 -> 2017 | I5: =H5-1 -> 2016 | J5: =I5-1 -> 2015 | ... M5: =L5-1 -> 2012 | Q5: Hoja | R5: Nombre campo Bloomberg | T5: Cambio de signo | Z5: 2016 | AA5: 2015 | AB5: 2014 | AC5: 2013 | AD5: 2012 | AE5: 2011 | AF5: 2010 | AG5: 2009
A6: Net Sales | B6: 33723 | C6: 31616 | D6: 29698 | E6: 24996 | F6: 20156 | G6: 15794 | H6: 11693 | I6: 8831 | J6: 6780 | K6: 5505 | L6: 4375 | M6: 3609 | N6: Income Statement | O6: Sales | Q6: Ingreso | R6: Ingreso | Z6: 38537 | AA6: 47011 | AB6: 55184 | AC6: 55656 | AD6: 65875 | AE6: 60138 | AF6: 42588 | AG6: 32396
A7: Gross Profit | B7: 14008 | C7: 12447 | D7: 12365 | E7: 10821 | F7: 7716 | G7: 5827 | H7: 4033 | I7: 2801 | J7: 2188 | K7: 1752 | L7: 1257 | M7: 957 | N7: Income Statement | O7: =+A7 -> Gross Profit | Q7: Ingreso | R7: + Coste de bienes y servicios | Z7: =Z6-28044 -> 10493 | AA7: =AA6-33546 -> 13465 | AB7: =AB6-40718 -> 14466 | AC7: =AC6-40727 -> 14929 | AD7: =+AD6-47055 -> 18820 | AE7: =+AE6-43578 -> 16560 | AF7: =+AF6-30367 -> 12221 | AG7: =+AG6-23886 -> 8510
A8: Operating Income | B8: 6954 | C8: 5633 | D8: 6195 | E8: 4585 | F8: 2604 | G8: 1605 | H8: 839 | I8: 380 | J8: 306 | K8: 403 | L8: 203 | M8: 50 | N8: Income Statement | O8: Operating Income | Q8: Ingreso | R8: + Ventas, generales y admin | Z8: =Z7-4383 -> 6110 | AA8: =AA7-4951 -> 8514 | AB8: =AB7-6529 -> 7937 | AC8: =AC7-5547 -> 9382 | AD8: =AD7-5919-2466-797-580-485 -> 8573 | AE8: =+AE7-5203-2297-826-1081 -> 7153 | AF8: =+AF7-4248-1905-914-1191 -> 3963 | AG8: =+AG7-3645-1421-1045-1822 -> 577
A9: Other Expenses (Revenues) | C9: 369 | D9: 254 | E9: =1101-1014 -> 87 | F9: 128 | G9: 29 | H9: -80 | N9: Income Statement | O9: investment income+other income expense+income loss+minority interest+non controlling interest+share onf net profit+gain8losses) on equity investments+share of result from associates nd joint ventures+non operating profit+ | Q9: Ingreso | R9: + Investigación y desarrollo | S9: + Coste de financiación de beneficio | T9: + Otro gasto operativo | U9: - Beneficio (pérdida) de filiales | V9: - Minoritarios | Z9: =1853+596+595+1904+6+8 -> 4962 | AA9: =2119+587+2023+11 -> 4740 | AB9: =2380+624+1619-8+16 -> 4631 | AC9: =2046+727+981+6+14 -> 3774 | AD9: =-14+41 -> 27 | AE9: 53 | AF9: =58+24 -> 82 | AG9: =12-68 -> -56
A10: Net Financial Cost | B10: -749 | C10: -369 | D10: -354 | E10: -1386 | F10: -542 | G10: -379 | H10: -353 | I10: -119 | J10: -164 | K10: -53 | L10: -32 | M10: 17 | N10: Income Statement | O10: interest expense+financial income and expenses+other financial expense-income+interest and other net+ | Q10: Ingreso | R10: - Ingreso (pérdida) no operacional | Z10: =505+518 -> 1023 | AA10: =507-161 -> 346 | AB10: =484-322 -> 162 | AC10: =465+35 -> 500 | AD10: =467-130 -> 337 | AE10: =396+32 -> 428 | AF10: =343-130 -> 213 | AG10: =389-381 -> 8
A11: Taxes | B11: -797 | C11: -1141 | D11: -979 | E11: -525 | F11: -323 | G11: -44 | H11: 153 | I11: -74 | J11: -19 | K11: -83 | L11: -59 | M11: -13 | N11: Income Statement | O11: Taxes | Q11: Ingreso | R11: - Gasto de impuesto a la renta (Beneficio) | Z11: 192 | AA11: 916 | AB11: 692 | AC11: 1319 | AD11: =2528 -> 2528 | AE11: =1720 -> 1720 | AF11: =968 -> 968 | AG11: =-270 -> -270
A12: Net Income | B12: 5408 | C12: 4492 | D12: 5116 | E12: 2761 | F12: 1867 | G12: 1211 | H12: 559 | I12: 187 | J12: 123 | K12: 267 | L12: 112 | M12: 17 | N12: Income Statement | O12: Net Income | Q12: Flujo de caja | R12: + Ingreso neto | Z12: -67 | AA12: 2512 | AB12: 2452 | AC12: 3789 | AD12: 5681 | AE12: =4928+24 -> 4952 | AF12: 2700 | AG12: 895
B13: =SUM(B8:B11) -> 5408 | C13: =SUM(C8:C11) -> 4492 | D13: =SUM(D8:D11) -> 5116 | E13: =SUM(E8:E11) -> 2761 | F13: =SUM(F8:F11) -> 1867 | G13: =SUM(G8:G11) -> 1211 | H13: =SUM(H8:H11) -> 559 | I13: =SUM(I8:I11) -> 187 | ... M13: =SUM(M8:M11) -> 54 | Z13: =Z8-Z10-Z9-Z11 -> -67 | AA13: =AA8-AA10-AA9-AA11 -> 2512 | AB13: =AB8-AB10-AB9-AB11 -> 2452 | AC13: =AC8-AC10-AC9-AC11 -> 3789 | AD13: =AD8-AD10-AD9-AD11 -> 5681 | AE13: =AE8-AE10-AE9-AE11 -> 4952 | AF13: =AF8-AF10-AF9-AF11 -> 2700 | AG13: =AG8-AG10-AG9-AG11 -> 895
A14: FINANCIAL POSITION | B14: =B12-B13 -> 0 | C14: =C12-C13 -> 0 | D14: =D12-D13 -> 0 | E14: =E12-E13 -> 0 | F14: =F12-F13 -> 0 | G14: =G12-G13 -> 0 | H14: =H12-H13 -> 0 | I14: =I12-I13 -> 0 | ... M14: =M12-M13 -> -37 | Z14: =Z12-Z13 -> 0 | AA14: =AA12-AA13 -> 0 | AB14: =AB12-AB13 -> 0 | AC14: =AC12-AC13 -> 0 | AD14: =AD12-AD13 -> 0 | AE14: =AE12-AE13 -> 0 | AF14: =AF12-AF13 -> 0 | AG14: =AG12-AG13 -> 0
A16: Weighted Average Shares (Basic NI) | B16: 442 | C16: 445 | D16: 443 | E16: 441 | F16: 438 | G16: 435 | H16: 432 | I16: 429 | J16: 426 | K16: 421 | L16: 407 | M16: 389
A17: Weighted Average Shares (Diluted NI) | B17: 449 | C17: 451 | D17: 455 | E17: 454 | F17: 452 | G17: 451 | H17: 447 | I17: 439 | J17: 436 | K17: 432 | L17: 425 | M17: 412
A19: Net gains (losses) from ForEx | B19: 113 | C19: -177 | D19: -85 | E19: 68 | F19: -4 | G19: 0.975 | H19: 27 | I19: 5 | J19: 38 | K19: -8 | L19: 2 | M19: 1
A20: Total Comprehensive Income | B20: 5401 | C20: 4315 | D20: 5031 | E20: 2829 | F20: 1862 | G20: 1212 | H20: 586 | I20: 181 | J20: 83 | K20: 259 | L20: 113 | M20: 19
A22: Changes Net Working Capital | B22: =B23-C23 -> -1358 | C22: =C23-D23 -> 1724 | D22: =D23-E23 -> -197 | E22: =E23-F23 -> -555 | F22: =F23-G23 -> -5108 | G22: =G23-H23 -> 0 | H22: =H23-I23 -> 32 | I22: =I23-J23 -> -18 | ... M22: =M23-N23 -> 0 | N22: cash flows | O22: NWC | Q22: Flujo de caja
A23: Net Working Capital | B23: =B27-B42-B28 -> -6081 | C23: =C27-C42-C28 -> -4723 | D23: =D27-D42-D28 -> -6447 | E23: =E27-E42-E28 -> -6250 | F23: =F27-F42-F28 -> -5695 | G23: =G27-G42-G28 -> -587 | H23: =H27-H42-H28 -> -587 | I23: =I27-I42-I28 -> -619 | ... M23: =M27-M42-M28 -> 0
A24: 2625 | B24: 2625 | C24: 2625 | D24: 2625 | E24: 2625 | F24: 2625 | G24: 2625 | H24: 2625 | I24: 2625 | J24: 2625 | K24: 2625 | L24: 2625 | M24: 2625 | N24: 2625 | Q24: Flujo de caja | R24: + Dividendos pagados | T24: Cambiar signo | Z24: 1799 | AA24: 1757 | AB24: 1620 | AC24: 1111 | AD24: 1617 | AE24: 1159 | AF24: 1084 | AG24: 1029
A25: BALANCE SHEET | B25: 2625 | C25: 2625 | D25: 2625 | E25: 2625 | F25: 2625 | G25: 2625 | H25: 2625 | I25: 2625 | J25: 2625 | K25: 2625 | L25: 2625 | M25: 2625 | N25: 2625 | Q25: Flujo de caja | R25: + Aumento en capital | S25: + Baja en capital | T25: Cambiar signo y hacer suma | Z25: 23 | AA25: =-33+2025 -> 1992 | AB25: 3817 | AC25: 1776 | AD25: -244 | AE25: -312 | AF25: -449 | AG25: -110
A26: ASSETS | N26: 1922 | O26: 2625
A27: Current | B27: 9918 | C27: 9266 | D27: 8070 | E27: 9762 | F27: 6179 | G27: 9694 | H27: 9694 | I27: 7670 | J27: 5720 | K27: 5432
A28: Cash & Eq. | B28: 7138 | C28: 6058 | D28: 6028 | E28: 8206 | F28: 5018 | G28: 3794 | H28: 3794 | I28: 2823 | J28: 1734 | K28: 2311 | N28: Balance Sheet | O28: Cash & Eq.
A29: Accounts Receivable | B29: 1287 | C29: 989 | D29: 804 | E29: 611 | F29: 454 | G29: 363 | H29: 0 | I29: 0 | J29: 0 | K29: 0 | N29: Balance Sheet | O29: Accounts Receivable
A30: Inventory | B30: 0 | C30: 0 | D30: 0 | E30: 0 | F30: 0 | G30: 0 | H30: 0 | I30: 0 | J30: 0 | K30: 0 | N30: Balance Sheet | O30: Inventory | Q30: Balance | R30: + Efectivo, equivalentes y STI | Z30: 7168 | AA30: 6460 | AB30: 7341 | AC30: 6081 | AD30: 5490 | AE30: 3057 | AF30: 3592 | AG30: 4867
A31: Other Current Assets | B31: =B27-SUM(B28:B30) -> 1493 | C31: =C27-SUM(C28:C30) -> 2219 | D31: =D27-SUM(D28:D30) -> 1238 | E31: =E27-SUM(E28:E30) -> 945 | F31: =F27-SUM(F28:F30) -> 707 | G31: =G27-SUM(G28:G30) -> 5537 | H31: =H27-SUM(H28:H30) -> 5900 | I31: =I27-SUM(I28:I30) -> 4847 | ... M31: =M27-SUM(M28:M30) -> 0 | N31: Balance Sheet | O31: Inventory | Q31: Balance | R31: + Cuentas y notas por cobrar | S31: + Activos derivados y de cobertura | T31: + Inversiones y cuentas por cobrar a LP | Z31: =5981+8522+1029+13556 -> 29088 | AA31: =6695+8991+1170+13651 -> 30507 | AB31: =7737+9027+1364+14644 -> 32772 | AC31: 33499 | AD31: 33911 | AE31: 31031 | AF31: 28849 | AG31: 27162
A32: Non-current | B32: =B38-B27 -> 38814 | C32: =C38-C27 -> 39329 | D32: =D38-D27 -> 36515 | E32: =E38-E27 -> 29518 | F32: =F38-F27 -> 27797 | G32: =G38-G27 -> 16280 | H32: =H38-H27 -> 16280 | I32: =I38-I27 -> 11343 | ... M32: =M38-M27 -> 0
A33: Property, Plant and Equipment | B33: 4423 | C33: 4379 | D33: 4386 | E33: 3493 | F33: 2513 | G33: 787 | H33: 787 | I33: 641 | J33: 545 | K33: 471 | Q33: Balance | R33: + Inventarios | Z33: 8614 | AA33: 9700 | AB33: 12205 | AC33: 12625 | AD33: 15547 | AE33: 14544 | AF33: 9587 | AG33: 6360
A34: Operating leases | B34: 2430 | C34: 2578 | D34: 2724 | E34: 2202 | F34: 1613 | G34: 1708 | H34: 1708 | I34: 737 | J34: 0 | K34: 530
A35: Equity Method Investments | B35: 0 | C35: 0 | D35: 0 | E35: 0 | F35: 0 | G35: 0 | H35: 0 | I35: 0 | J35: 0 | K35: 0
A36: Other Non-Current Assets | B36: =B32-SUM(B33:B35) -> 31961 | C36: =C32-SUM(C33:C35) -> 32372 | D36: =D32-SUM(D33:D35) -> 29405 | E36: =E32-SUM(E33:E35) -> 23823 | F36: =F32-SUM(F33:F35) -> 23671 | G36: =G32-SUM(G33:G35) -> 13785 | H36: =H32-SUM(H33:H35) -> 13785 | I36: =I32-SUM(I33:I35) -> 9965 | ... M36: =M32-SUM(M33:M35) -> 0 | N36: Balance Sheet | O36: Property, Plant and Equipment
A37: Other Assets | B37: =B31+B36 -> 33454 | C37: =C31+C36 -> 34591 | D37: =D31+D36 -> 30643 | E37: =E31+E36 -> 24768 | F37: =F31+F36 -> 24378 | G37: =G31+G36 -> 19322 | H37: =H31+H36 -> 19685 | I37: =I31+I36 -> 14812 | ... M37: =M31+M36 -> 0 | N37: Balance Sheet
A38: Total Assets | B38: 48732 | C38: 48595 | D38: 44585 | E38: 39280 | F38: 33976 | G38: 25974 | H38: 25974 | I38: 19013 | J38: 13587 | K38: 10203 | N38: Balance Sheet | O38: Total Assets | Q38: Balance | R38: + Propiedad, planta y equipo; neto | Z38: 15322 | AA38: 16090 | AB38: =16577 -> 16577 | AC38: 17075 | AD38: 16461 | AE38: 14395 | AF38: 12539 | AG38: 12386
N39: Balance Sheet | Z39: =Z40-SUM(Z30:Z38) -> 14512 | AA39: =AA40-SUM(AA30:AA38) -> 15585 | AB39: =AB40-SUM(AB30:AB38) -> 15786 | AC39: =AC40-SUM(AC30:AC38) -> 15616 | AD39: =AD40-SUM(AD30:AD38) -> 17947 | AE39: =AE40-SUM(AE30:AE38) -> 18419 | AF39: =AF40-SUM(AF30:AF38) -> 9453 | AG39: =AG40-SUM(AG30:AG38) -> 9263
N40: Balance Sheet | Q40: Balance | R40: Activos totales | Z40: 74704 | AA40: 78342 | AB40: 84681 | AC40: 84896 | AD40: 89356 | AE40: 81446 | AF40: 64020 | AG40: 60038
A41: LIABILITIES | N41: Balance Sheet
A42: Current Liabilities | B42: 8861 | C42: 7931 | D42: 8489 | E42: 7806 | F42: 6856 | G42: 6487 | H42: 6487 | I42: 5466 | J42: 4587 | K42: 3530 | N42: Balance Sheet | O42: Current Liabilities
A43: Payables | B43: 5214 | C43: 5152 | D43: 5130 | E43: 5086 | F43: 5088 | G43: 5245 | H43: 5249 | I43: 4533 | J43: 3946 | K43: 3043
A44: Short-Term Debt | B44: 0 | C44: 0 | D44: 0 | E44: 0 | F44: 0 | G44: 0 | H44: 0 | I44: 0 | J44: 0 | K44: 0 | N44: Balance Sheet | O44: Short term Debt | Q44: Balance | R44: Pasivos totales corrientes | Z44: 26132 | AA44: 26242 | AB44: 27877 | AC44: 27297 | AD44: 29415 | AE44: =93+3895+8161+3386+2410+2691+298+1967+558+5102 -> 28561 | AF44: =204+3852+5856+2880+1670+1831+281+1521+495+3430 -> 22020 | AG44: =433+3650+2993+3351+797+1217+262+888+302+5399 -> 19292
A45: Short-Term Leases | B45: 383 | C45: 356 | D45: 315 | E45: 256 | F45: 191
A46: Other current liabilities | B46: =B42-SUM(B43:B45) -> 3264 | C46: =C42-SUM(C43:C45) -> 2423 | D46: =D42-SUM(D43:D45) -> 3044 | E46: =E42-SUM(E43:E45) -> 2464 | F46: =F42-SUM(F43:F45) -> 1577 | G46: =G42-SUM(G43:G45) -> 1242 | H46: =H42-SUM(H43:H45) -> 1238 | I46: =I42-SUM(I43:I45) -> 933 | ... M46: =M42-SUM(M43:M45) -> 0 | N46: Balance Sheet | R46: + Préstamos CP | Z46: 7303 | AA46: 6967 | AB46: 4708 | AC46: 3679 | AD46: 5287 | AE46: 5660 | AF46: 3925 | AG46: 5701
A47: Non-current Liabilities | B47: =B51-B42 -> 19283 | C47: =C51-C42 -> 19886 | D47: =D51-D42 -> 20246 | E47: =E51-E42 -> 20409 | F47: =F51-F42 -> 19538 | G47: =G51-G42 -> 14249 | H47: =H51-H42 -> 14249 | I47: =I51-I42 -> 9965 | ... M47: =M51-M42 -> 0 | N47: Balance Sheet | O47: Total non current liabilities
A48: Long-Term Debt | B48: 14143 | C48: 14353 | D48: 14693 | E48: 15809 | F48: 14759 | G48: 10360 | H48: 10388 | I48: 6529 | J48: 3394 | K48: 2400 | N48: Balance Sheet | O48: Long term debt | Z48: =Z44-Z46 -> 18829 | AA48: =AA44-AA46 -> 19275 | AB48: =AB44-AB46 -> 23169 | AC48: =AC44-AC46 -> 23618 | AD48: =AD44-AD46 -> 24128 | AE48: =AE44-AE46 -> 22901 | AF48: =AF44-AF46 -> 18095 | AG48: =AG44-AG46 -> 13591
A49: Long-Term Leases | B49: 2046 | C49: 2223 | D49: 2408 | E49: 1946 | F49: 1423 | Q49: Balance | R49: Pasivos totales no corrientes | Z49: =61491-Z44 -> 35359 | AA49: =63457-AA44 -> 37215 | AB49: =67855-AB44 -> 39978 | AC49: 36721 | AD49: 41973 | AE49: =8415+16529+10956+3583 -> 39483 | AF49: =4505+15932+7584+2654 -> 30675 | AG49: =5652+16195+7420+2179 -> 31446
A50: Other non-current liabilities | B50: =B47-SUM(B48:B49) -> 3094 | C50: =C47-SUM(C48:C49) -> 3310 | D50: =D47-SUM(D48:D49) -> 3145 | E50: =E47-SUM(E48:E49) -> 2654 | F50: =F47-SUM(F48:F49) -> 3356 | G50: =G47-SUM(G48:G49) -> 3889 | H50: =H47-SUM(H48:H49) -> 3861 | I50: =I47-SUM(I48:I49) -> 3436 | ... M50: =M47-SUM(M48:M49) -> 0 | N50: Balance Sheet | O50: Other non current Liabilities | R50: + Préstamos a largo plazo | Z50: 22818 | AA50: 25169 | AB50: 27784 | AC50: 26719 | AD50: 27752 | AE50: 24944 | AF50: 20437 | AG50: 21847
A51: Total Liabilities | B51: 28144 | C51: 27817 | D51: 28735 | E51: 28215 | F51: 26394 | G51: 20736 | H51: 20736 | I51: 15431 | J51: 10907 | K51: 7979 | N51: Balance Sheet | O51: Total Liabilities
N52: Balance Sheet | Z52: =Z49-Z50 -> 12541 | AA52: =AA49-AA50 -> 12046 | AB52: =AB49-AB50 -> 12194 | AC52: =AC49-AC50 -> 10002 | AD52: =AD49-AD50 -> 14221 | AE52: =AE49-AE50 -> 14539 | AF52: =AF49-AF50 -> 10238 | AG52: =AG49-AG50 -> 9599
N53: Balance Sheet | Z53: =+Z49+Z44 -> 61491 | AA53: =+AA49+AA44 -> 63457 | AB53: =+AB49+AB44 -> 67855 | AC53: =AC44+AC49 -> 64018 | AD53: =AD49+AD44 -> 71388 | AE53: =AE49+AE44 -> 68044 | AF53: =AF49+AF44 -> 52695 | AG53: =AG49+AG44 -> 50738
A54: Minority Interest | B54: 0 | C54: 0 | D54: 0 | E54: 0 | F54: 0 | G54: 0 | H54: 0 | I54: 0 | J54: 0 | K54: 0 | N54: Balance Sheet | O54: Minority Interest
N55: Balance Sheet
A56: Shareholder's Equity | B56: =B38-B51-B54 -> 20588 | C56: =C38-C51-C54 -> 20778 | D56: =D38-D51-D54 -> 15850 | E56: =E38-E51-E54 -> 11065 | F56: =F38-F51-F54 -> 7582 | G56: =G38-G51-G54 -> 5238 | H56: =H38-H51-H54 -> 5238 | I56: =I38-I51-I54 -> 3582 | ... M56: =M38-M51-M54 -> 0 | N56: Balance Sheet | Q56: Balance | R56: + Participación minoritaria/no dominante
A58: CASH FLOW
A59: Operating CF | B59: 7274.3 | C59: 2026.3 | D59: 392.6 | E59: 2427.1 | F59: -2887.3 | G59: -2680.5 | H59: -1785.9 | I59: -1474 | J59: -749.4 | K59: 16.5
A60: Net Income | B60: =B12 -> 5408 | C60: =C12 -> 4492 | D60: =D12 -> 5116 | E60: =E12 -> 2761 | F60: =F12 -> 1867 | G60: =G12 -> 1211 | H60: =H12 -> 559 | I60: =I12 -> 187 | ... M60: =M12 -> 17
A61: Depreciation & Amortization | B61: 14554.3 | C61: 14362.8 | D61: 12438.8 | E61: 10922.6 | F61: 9319.8 | G61: 7656.5 | H61: 6330.4 | I61: 4925 | J61: 3547.1 | K61: 2781.8
A62: Changes in assets and liabilities | B62: -116.1 | C62: -758.1 | D62: -242 | E62: -31.9 | F62: 43 | G62: 293.8 | H62: 59 | I62: 192.4 | J62: 172.9 | K62: 137.1
A63: Other Adjustments | B63: =B59-B60-B61-B62 -> -12571.9 | C63: =C59-C60-C61-C62 -> -16070.4 | D63: =D59-D60-D61-D62 -> -16920.2 | E63: =E59-E60-E61-E62 -> -11224.6 | F63: =F59-F60-F61-F62 -> -14117.1 | G63: =G59-G60-G61-G62 -> -11841.8 | H63: =H59-H60-H61-H62 -> -8734.3 | I63: =I59-I60-I61-I62 -> -6778.4 | ... M63: =M59-M60-M61-M62 -> -17
A64: Investing CF | B64: 541.8 | C64: -2076.4 | D64: -1339.9 | E64: -505.4 | F64: -387.1 | G64: -339.1 | H64: 34.3 | I64: 49.8 | J64: -179.2 | K64: -42.9
A65: Net Capex | B65: -348.6 | C65: -407.7 | D65: -524.6 | E65: -497.9 | F65: -253 | G65: -212.5 | H65: -227 | I65: -184.8 | J65: -169.2 | K65: -144.5
A66: Investments & Acquisitions | B66: -504.9 | C66: -1668.7 | D66: -788.3 | E66: 0 | F66: 0 | G66: 0 | H66: -74.8 | I66: -187.2 | J66: -371.9 | K66: -426.9
A67: Other Inflows (Outflows) | B67: =B64-B65-B66 -> 1395.3 | C67: =C64-C65-C66 -> 0 | D67: =D64-D65-D66 -> -27 | E67: =E64-E65-E66 -> -7.5 | F67: =F64-F65-F66 -> -134.1 | G67: =G64-G65-G66 -> -126.6 | H67: =H64-H65-H66 -> 336.1 | I67: =I64-I65-I66 -> 421.8 | ... M67: =M64-M65-M66 -> 0
A68: Financing CF | B68: -5950.8 | C68: -664.3 | D68: -1149.8 | E68: 1237.3 | F68: 4505.7 | G68: 4048.5 | H68: 3077 | I68: 1091.6 | J68: 1640.3 | K68: 541.7
A69: Debt Borrowing | B69: 0 | C69: 0 | D69: 0 | E69: 1009.5 | F69: 4469.3 | G69: 3961.9 | H69: 3020.5 | I69: 1000 | J69: 1500 | K69: 400
A70: Debt Repayment | B70: 0 | C70: 0 | D70: 0 | E70: 0 | F70: 0 | G70: 0 | H70: 0 | I70: 0 | J70: 0 | K70: 0
A71: Lease Increases
A72: Lease Payments
A73: Dividends | B73: 0 | C73: 0 | D73: 0 | E73: 0 | F73: 0 | G73: 0 | H73: 0 | I73: 0 | J73: 0 | K73: 0 | N73: cash flows FINANCING | O73: Dividends paid
A74: Share buyback | B74: -6045.3 | C74: 0 | D74: -600 | E74: 0 | F74: 0 | G74: 0 | H74: 0 | I74: 0 | J74: 0 | K74: 0 | N74: cash flows FINANCING | O74: =+A74 -> Share buyback
A75: Other Inflows (Outflows) | B75: =B68-B69-B70-B71-B72-B73-B74 -> 94.5 | C75: =C68-C69-C70-C71-C72-C73-C74 -> -664.3 | D75: =D68-D69-D70-D71-D72-D73-D74 -> -549.8 | E75: =E68-E69-E70-E71-E72-E73-E74 -> 227.8 | F75: =F68-F69-F70-F71-F72-F73-F74 -> 36.4 | G75: =G68-G69-G70-G71-G72-G73-G74 -> 86.6 | H75: =H68-H69-H70-H71-H72-H73-H74 -> 56.5 | I75: =I68-I69-I70-I71-I72-I73-I74 -> 91.6 | ... M75: =M68-M69-M70-M71-M72-M73-M74 -> 0
A76: FX | B76: 82.7 | C76: -170.1 | D76: -86.7 | E76: 36.1 | F76: 0.5 | G76: -39.7 | H76: 29.8 | I76: -9.2 | J76: -15.9 | K76: -6.7
A77: Changes in cash | B77: =B59+B64+B68+B76 -> 1948 | C77: =C59+C64+C68+C76 -> -884.5 | D77: =D59+D64+D68+D76 -> -2183.8 | E77: =E59+E64+E68+E76 -> 3195.1 | F77: =F59+F64+F68+F76 -> 1231.8 | G77: =G59+G64+G68+G76 -> 989.2 | H77: =H59+H64+H68+H76 -> 1355.2 | I77: =I59+I64+I68+I76 -> -341.8 | ... M77: =M59+M64+M68+M76 -> 0
O78: (Vitalis will later fill this info)
A79: Other Data | E79: Corporate Bonds 3, 5 Y 10 | H79: Average Price | J79: Moody's | K79: YTM | L79: DIVISA
A80: Number of employees | B80: 13000 | C80: 10-K | N80: bloomberg
A81: Shares Outstanding (Thousands) | B81: 432760 | C81: Yahoo finance | N81: bloomberg
A82: Float | B82: =428510/B81 -> 0.99017931 | C82: Yahoo finance | N82: bloomberg
A83: Insiders Own | B83: 0.0138 | C83: Yahoo finance | N83: bloomberg
A84: Fitch/ S&P Rating | C84: 10-K | N84: bloomberg
A85: Dividend Yield(Yahoo Finance) | B85: 0 | C85: Yahoo finance | N85: bloomberg
A86: Daily Volume in Millions of USD | C86: Yahoo Finance | N86: bloomberg
B87: =B5 -> 2023 | C87: =C5 -> 2022 | D87: =D5 -> 2021
A88: Short % of Float | E88: Yahoo Finance
A89: EPS | E89: Yahoo Finance
