Workbook
Name Sectors: '[1]Sector Impact'!$K$4:$K$16
Name Sectors: 'Sector Impact'!$K$4:$K$16

Sheet OP
B2: 45270 | C2: Team 1 | E2: =Inputs!I3 -> #VALUE! | L2: NYSE | M2: SIC: 3577
B3: #VALUE! | D3: COMPANY DESCRIPTION | H3: CEO & BOARD OF DIRECTORS
D4: {=_FV(Inputs!I3,"Description")} -> Fortinet, Inc. provides an integrated platform, the Fortinet Security Fabric, that spans networking, unified Secure Access Service Edge (SASE) and AI-driven security operations to deliver cybersecurity where customers need it. It offers solutions to enterprises, such as in the financial services, retail and operational technology market verticals, communication and security service providers, government organizations and small and medium-sized businesses. Its Secure Networking solutions focuses on the convergence of networking and security via its network firewall and its switches, access points and other secure connectivity solutions. Its Unified SASE solution is a single-vendor SASE solution that includes Firewall, SD-WAN, Secure Web Gateway, Cloud Access Services Broker, and Data Loss Prevention, Zero Trust Network Access and cloud security. Its Security Operations solutions are delivered as a platform that automates detection and response to accelerate discovery and remediation. | H4: Name (Gender; Age) | I4: Tenure | J4: Executive? | K4: Other roles
H5: Kenneth Xie (M, 60) | I5: 10.8 | J5: Co-Founder, Chairman, CEO | K5: Founder of Netscreen Technologies and Stanford Infosystems Intl, Ken Xie 2007 Annuity Trust Trustee
H6: Michael Xie (M, 54) | I6: 22.8 | J6: Co-Founder, President, Director & CTO | K6: Relevant past positions: Vice President-Engineering at ServGate Technologies, Software Director at NetScreen Technologies, Senior Software Engineer for Milkyway Networks Corporation
H7: William H Neukon (M, 81) | I7: 5.6 | J7: Lead Independent Director | K7: Founder of World Justice Project and Neukom Family Foundation, board member of The Asia Foundation, Pacific Council on International Policy and Center for Advanced Study in the Behavioral Sciences; Relevant past positions: Partner at K&L Gates and Preston Gates & Ellis, Chairman of Kirkpatrick & Lockhart, Preston Gates & Ellis and Volterra, EVP-Law & Corporate Affairs at Microsoft, Semiconductor, President at American Bar Association
H8: Ming Hsieh(M, 67) | I8: 10.6 | J8: Independent Director | K8: Founder of Gemalto Cogent, A-MAX Technology and Cogent and Founder, Chairman & CEO of Fulgent Genetics, Board Member of the University of Southern California, Fudan University and Fulgent Pharma
H9: Judith Sim (F, 54) | I9: 8.4 | J9: Independent Director | K9: Board member of DataStax and First Advantage; Relevant past postions: Chiief Marketing Officer of Oracle
H10: Jean X Hu (F, 59) | I10: 4.1 | J10: Independent Director | K10: CFO, Treasurer & Executive VP of Advanced Micro Devices, CFO at Marvell Technology Holdings; Relevant past positions: CEO & CFO, SVP at QLogic, CEO & CFO at Kinoma, President & CFO at Cavium, CFO, Treasurer & SVP-Business Development at Conexant Systems
H11: Kenneth A Goldman (M, 74) | I11: 3.1 | J11: Independent Director | K11: President of Hillspire, Member of The Financial Executives Institute, Advisor at Illuminate Ventures and ForgePoint Capital Management, Principal Executive & Financial Officer, Director at Aabaco Holdings, Member of Sustainability Accounting Standards Board, Managing Member at Gv Partners, Board Member of 17 other companies | N11: ..
H12: James G Starvidis (M, 68) | I12: 2.1 | J12: Independent Director | K12: Member-Advisory Board at Utilidata, Chairman for The Rockefeller Foundation, Managing Director & Vice Chairman-Global Affairs at The Carlyle Group and Board Member of 21 other companies
B17: USD MILLIONS
B18: COMPANY OVERVIEW
B19: Stock | D19: Liquidity and Solvency | F19: Segments | I19: Profitability (2023 TTM) | L19: Multiples
B20: Last Price | C20: {=_FV(E2,"Price")} -> 76.64 | D20: Total Assets | E20: =_xlfn.XLOOKUP(D20,'Fin. Data'!A:A,'Fin. Data'!B:B,,0) -> 7479.3 | F20: Regions | H20: % Sales | I20: Reporting Year | J20: 2023 | L20: Float | M20: 0.842
B21: Outstanding Shares | C21: {=_FV(E2,"Shares outstanding",TRUE)} -> 764908000 | D21: Total Liabilities | E21: =_xlfn.XLOOKUP(D21,'Fin. Data'!A:A,'Fin. Data'!B:B,,0) -> 7405.2 | F21: =Segments!C5 -> United States | H21: =Segments!B5 -> 0.30386452 | I21: Last Report | J21: 2 November 2023 | L21: Insiders Own | M21: 0.1741
B22: Market Cap. | C22: =C20*C21/1000000 -> 58622.549 | D22: Cash/Share | E22: =_xlfn.XLOOKUP("Cash & Eq.",'Fin. Data'!A:A,'Fin. Data'!B:B,,0)*1000000/C21 -> 2.8589059 | F22: =Segments!C6 -> Other Americas | H22: =Segments!B6 -> 0.10739072 | I22: EBITDA | K22: =_xlfn.XLOOKUP(I22,'Fin. Data'!A:A,'Fin. Data'!B:B,,0) -> 1407.2 | L22: b (Yahoo) | M22: 1.14
B23: +Total Debt | C23: ='Fin. Data'!C58 -> 1086.1 | D23: EBITDA/Net Financial Cost (NFC) | E23: =_xlfn.XLOOKUP("EBITDA",'Fin. Data'!A:A,'Fin. Data'!B:B,,0)/_xlfn.XLOOKUP("Net Financial Cost",'Fin. Data'!A:A,'Fin. Data'!B:B,,0) -> 17.994885 | F23: =Segments!C7 -> Europe, Middle East and Africa (EMEA) | H23: =Segments!B7 -> 0.38807586 | I23: Depreciation & Amortization | K23: =_xlfn.XLOOKUP(I23,'Fin. Data'!A:A,'Fin. Data'!B:B,,0) -> 110.5 | L23: Score (S&P) | M23: BBB+
B24: -Cash | C24: ='Fin. Data'!C39 -> 1682.9 | D24: Debt/EBITDA | E24: =_xlfn.XLOOKUP("Total Debt",'Fin. Data'!A:A,'Fin. Data'!B:B,,0)/_xlfn.XLOOKUP("EBITDA",'Fin. Data'!A:A,'Fin. Data'!B:B,,0) -> 0.74921831 | F24: =Segments!C8 -> Asia Pacific (APAC) | H24: =Segments!B8 -> 0.2006689 | I24: EBIT | K24: =_xlfn.XLOOKUP(I24,'Fin. Data'!A:A,'Fin. Data'!B:B,,0) -> 1296.7 | L24: Price/Book Value | M24: =IFERROR((C20*C21/(E20-E21))/1000000,"") -> 791.12752
B25: =Enterprise Value | C25: =C22+C23-C24 -> 58025.749 | D25: "Others Assets"/Asset | E25: =_xlfn.XLOOKUP("Other Assets",'Fin. Data'!A:A,'Fin. Data'!B:B,,0)/_xlfn.XLOOKUP("Total Assets",'Fin. Data'!A:A,'Fin. Data'!B:B,,0) -> 0.32882756 | I25: Net Income | K25: =_xlfn.XLOOKUP(I25,'Fin. Data'!A:A,'Fin. Data'!B:B,,0) -> 1150.7 | L25: NCF(3y avg)/Asset | M25: =IFERROR(K31/E20,"") -> 0.11653497
B26: Holdings (nac/int'l) | C26: - | D26: Debt/Assets | E26: =_xlfn.XLOOKUP(D26,'Fin. Data'!A:A,'Fin. Data'!B:B,,0) -> 0.14096239 | F26: Categories | H26: % Sales | I26: EPS | K26: =1000000*K25/C21 -> 1.5043639 | L26: Price/Net Inc. (3y avg) | M26: =IFERROR(C22/K30,"") -> 67.258546
B27: t liq. (Holdings/Vol.) | C27: - | D27: EBITDA Margin (average) | E27: =AVERAGE(_xlfn.XLOOKUP("EBITDA Margin",'Fin. Data'!A:A,'Fin. Data'!B:D,,0)) -> 0.25184651 | F27: =Segments!C16 -> Products | H27: =Segments!B16 -> 0.38269696 | I27: ROA | K27: =K25/E20 -> 0.1538513 | L27: EV/Asset | M27: =IFERROR(C25/E20,"") -> 7.7581791
B28: % Short | C28: 0.0181 | D28: Operating Margin (average) | E28: =AVERAGE(_xlfn.XLOOKUP("Operating Margin",'Fin. Data'!A:A,'Fin. Data'!B:D,,0)) -> 0.21623167 | F28: =Segments!C18 -> Technical support and other | H28: =Segments!B18 -> 0.27356211 | I28: ROIC | K28: =K25/(E20-(E21-C23)) -> 0.99181176 | L28: EV/Ebitda (3y average) | M28: =IFERROR(C25/K29,"") -> 52.701174
B29: Traffic ESG | D29: Net Income Margin (average) | E29: =AVERAGE(_xlfn.XLOOKUP("Net Income Margin",'Fin. Data'!A:A,'Fin. Data'!B:D,,0)) -> 0.19936228 | F29: =Segments!C17 -> Security subscription | H29: =Segments!B17 -> 0.34374094 | I29: EBITDA (3y average) | K29: =AVERAGE(_xlfn.XLOOKUP("EBITDA",'Fin. Data'!A:A,'Fin. Data'!B:D,,0)) -> 1101.0333 | L29: Price/NCF (3y average) | M29: =IFERROR(C22/K31,"") -> 67.258546
B30: E | I30: Net Income (3y average) | K30: =AVERAGE(_xlfn.XLOOKUP("Net Income",'Fin. Data'!A:A,'Fin. Data'!B:D,,0)) -> 871.6 | L30: Bonds 1,3,5a (USD) | M30: -
B31: S | D31: Net Financial Cost/Avg Net Debt | E31: =-_xlfn.XLOOKUP("Net Financial Cost",'Fin. Data'!A:A,'Fin. Data'!B:B,,0)/AVERAGE(_xlfn.XLOOKUP("Net Debt",'Fin. Data'!A:A,'Fin. Data'!B:D,,0)) -> 0.11770018 | I31: NCF (3y average) | K31: =AVERAGE(_xlfn.XLOOKUP("Net Income",'Fin. Data'!A:A,'Fin. Data'!B:D,,0)) -> 871.6 | L31: Div+Rep.(3y avg)/Price | M31: =-IFERROR(SUM(E52:E54)/(3*C22),"") -> 0.018976202
B32: G | L32: Div. Yield | M32: =-IFERROR(L53/C22,"") -> 0
B33: INVESTMENT THESIS
B34: Pillars of Recommendation | H34: Recommendation | I34: Valuation Assumptions
B35: Pillar | C35: Explanation | H35: SELL | I35: check DCF
B36: High Price | C36: Fortinet is a well-established company with healthy growth and strong strategy being adapted to constantly changing industry trends. Nevertheless, the share price is too high, which was impossible to justify with our valuation. Having that in mind, we issue recommendation to sell.
B39: Risks of Investment | H39: Price Target | I39: Valuation
B40: Risk | C40: Explanation | H40: =DCF!D76 -> 35.199604 | I40: Discount Rate | J40: =DCF!F50 -> 0.112543 | L40: Price M. Upside | M40: =SARD!AJ14 -> #NUM!
B41: adverse economic conditions | C41: Stubborn inflation, rising borrowing costs and risk of recession or staglfation might relust in longer sales cycles, increased products' cost structure, higher default rates from channel partners, reduced sales and growth declining in much faster pace
B42: high competition | C42: Fortinet might fail to innovate enough, develop less effetive products or could not adjust to constantly changing market trends, hence losse its competitive advantage to larger or faster growing competitors. It could result in major decline in sales growth and fall of the share price | I42: Upside | J42: =DCF!D75 -> -0.54071498 | L42: EV M. Upside | M42: =SARD!AM14 -> #NUM!
B43: debt | C43: Company might witness reduced sales growth, hence not be able to maintain its liquidity, taking under consideration recent significant increase of debt. It might affect the assumptions' reliability
B44: FINANCIAL PERFORMANCE
B45: Year | C45: Net Sales | D45: Operating Margin | E45: Dividends + Share Buyback | F45: Net Cash Flow | G45: Debt/Assets | H45: Depreciation & Amortization | I45: Capex + Investments | J45: Cash Flow
B46: =B47-1 -> 2015 | C46: {=_xlfn.SORTBY(TRANSPOSE(_xlfn.XLOOKUP(C$45,'Fin. Data'!$A:$A,'Fin. Data'!$B:$J,,0)),$B$46:$B$54,-1)} -> 1009.3 | D46: {=_xlfn.SORTBY(TRANSPOSE(_xlfn.XLOOKUP(D$45,'Fin. Data'!$A:$A,'Fin. Data'!$B:$J,,0)),$B$46:$B$54,-1)} -> 0.014762707 | E46: {=_xlfn.SORTBY(TRANSPOSE(_xlfn.XLOOKUP(E$45,'Fin. Data'!$A:$A,'Fin. Data'!$B:$J,,0)),$B$46:$B$54,-1)} -> -60 | F46: =Inputs!K77 -> 167.3 | G46: {=_xlfn.SORTBY(TRANSPOSE(_xlfn.XLOOKUP(G$45,'Fin. Data'!$A:$A,'Fin. Data'!$B:$J,,0)),$B$46:$B$54,-1)} -> 0 | H46: {=_xlfn.SORTBY(TRANSPOSE(_xlfn.XLOOKUP(H$45,'Fin. Data'!$A:$A,'Fin. Data'!$B:$J,,0)),$B$46:$B$54,-1)} -> 31.6 | I46: {=_xlfn.SORTBY(TRANSPOSE(_xlfn.XLOOKUP(I$45,'Fin. Data'!$A:$A,'Fin. Data'!$B:$J,,0)),$B$46:$B$54,-1)} -> -1 | L46: =J20 -> 2023 | M46: =L46-1 -> 2022
B47: =B48-1 -> 2016 | C47: 1275.4 | D47: 0.033636506 | E47: -110.8 | F47: =Inputs!J77 -> 259.9 | G47: 0 | H47: 48.5 | I47: -74.1 | J47: Net Income | L47: =_xlfn.XLOOKUP($J47,'Fin. Data'!$A:$A,'Fin. Data'!B:B,,0) -> 1150.7 | M47: =_xlfn.XLOOKUP($J47,'Fin. Data'!$A:$A,'Fin. Data'!C:C,,0) -> 857.3 | N47: =(C47/C46)-1 -> 0.26364807 | O47: =(D47/D46)-1 -> 1.2784782
B48: =B49-1 -> 2017 | C48: 1494.9 | D48: 0.073449729 | E48: -446.3 | F48: =Inputs!I77 -> 165.7 | G48: 0 | H48: 55.5 | I48: -76.8 | J48: Operating CF | L48: =_xlfn.XLOOKUP($J48,'Fin. Data'!$A:$A,'Fin. Data'!B:B,,0) -> 2271.9 | M48: =_xlfn.XLOOKUP($J48,'Fin. Data'!$A:$A,'Fin. Data'!C:C,,0) -> 1730.6 | N48: =(C48/C47)-1 -> 0.17210287 | O48: =(D48/D47)-1 -> 1.1836313 | Q48: =F48/F47-1 -> -0.3624471 | R48: =H48/H47-1 -> 0.1443299 | S48: =I48/I47-1 -> 0.036437247
B49: =B50-1 -> 2018 | C49: 1801.2 | D49: 0.12824783 | E49: -211.8 | F49: =Inputs!H77 -> 102 | G49: 0 | H49: 55.7 | I49: -134.9 | J49: Investing CF | L49: =_xlfn.XLOOKUP($J49,'Fin. Data'!$A:$A,'Fin. Data'!B:B,,0) -> -360.3 | M49: =_xlfn.XLOOKUP($J49,'Fin. Data'!$A:$A,'Fin. Data'!C:C,,0) -> 763.9 | N49: =(C49/C48)-1 -> 0.20489665 | O49: =(D49/D48)-1 -> 0.74606273 | Q49: =F49/F48-1 -> -0.38442969 | R49: =H49/H48-1 -> 0.0036036036 | S49: =I49/I48-1 -> 0.75651042
B50: =B51-1 -> 2019 | C50: 2163 | D50: 0.1605178 | E50: -145.1 | F50: =Inputs!G77 -> 301.4 | G50: 0.011864625 | H50: 61.6 | I50: -502.3 | J50: Net Capex | L50: =_xlfn.XLOOKUP($J50,'Fin. Data'!$A:$A,'Fin. Data'!B:B,,0) -> -208.1 | M50: =_xlfn.XLOOKUP($J50,'Fin. Data'!$A:$A,'Fin. Data'!C:C,,0) -> -281.2 | N50: explain otliers and suuden changes | O50: =(D50/D49)-1 -> 0.25162191 | Q50: =F50/F49-1 -> 1.954902 | R50: =H50/H49-1 -> 0.1059246 | S50: =I50/I49-1 -> 2.7234989
B51: =B52-1 -> 2020 | C51: 2594.4 | D51: 0.20332254 | E51: -1080.1 | F51: =Inputs!F77 -> 110.1 | G51: 0.013128941 | H51: 68.8 | I51: -72.8 | J51: Investments & Acquisitions | L51: =_xlfn.XLOOKUP($J51,'Fin. Data'!$A:$A,'Fin. Data'!B:B,,0) -> 152.2 | M51: =_xlfn.XLOOKUP($J51,'Fin. Data'!$A:$A,'Fin. Data'!C:C,,0) -> 1045.1 | N51: =(C51/C50)-1 -> 0.19944521 | O51: =(D51/D50)-1 -> 0.26666664 | Q51: =F51/F50-1 -> -0.63470471 | R51: =H51/H50-1 -> 0.11688312 | S51: =I51/I50-1 -> -0.85506669
B52: =B53-1 -> 2021 | C52: 3342.2 | D52: 0.19460236 | E52: -741.8 | F52: =Inputs!E77 -> -160.7 | G52: 0.17827035 | H52: 84.4 | I52: -1325.1 | J52: Financing CF | L52: =_xlfn.XLOOKUP($J52,'Fin. Data'!$A:$A,'Fin. Data'!B:B,,0) -> -687.7 | M52: =_xlfn.XLOOKUP($J52,'Fin. Data'!$A:$A,'Fin. Data'!C:C,,0) -> -2130.3 | N52: =(C52/C51)-1 -> 0.2882362 | O52: =(D52/D51)-1 -> -0.042888423 | Q52: =F52/F51-1 -> -2.4595822 | R52: =H52/H51-1 -> 0.22674419 | S52: =I52/I51-1 -> 17.201923
B53: =B54-1 -> 2022 | C53: 4417.4 | D53: 0.21949563 | E53: -1991.2 | F53: =Inputs!D$77 -> 257.3 | G53: 0.17438985 | H53: 104.3 | I53: 763.9 | J53: Dividends | L53: =_xlfn.XLOOKUP($J53,'Fin. Data'!$A:$A,'Fin. Data'!B:B,,0) -> 0 | M53: =_xlfn.XLOOKUP($J53,'Fin. Data'!$A:$A,'Fin. Data'!C:C,,0) -> 0 | N53: =(C53/C52)-1 -> 0.32170427 | O53: =(D53/D52)-1 -> 0.12791866 | Q53: =F53/F52-1 -> -2.6011201 | R53: =H53/H52-1 -> 0.23578199 | S53: =I53/I52-1 -> -1.5764848
B54: =J20 -> 2023 | C54: 5172.7 | D54: 0.23459702 | E54: -604.3 | F54: =Inputs!C77 -> 363.8 | G54: 0.14096239 | H54: 110.5 | I54: -55.9 | J54: Share Buyback | L54: =_xlfn.XLOOKUP($J54,'Fin. Data'!$A:$A,'Fin. Data'!B:B,,0) -> -604.3 | M54: =_xlfn.XLOOKUP($J54,'Fin. Data'!$A:$A,'Fin. Data'!C:C,,0) -> -1991.2 | N54: =(C54/C53)-1 -> 0.17098293 | O54: =(D54/D53)-1 -> 0.068800404 | Q54: =F54/F53-1 -> 0.41391372 | R54: =H54/H53-1 -> 0.059443912 | S54: =I54/I53-1 -> -1.0731771
B55: Annual Growth Rate | C55: =IFERROR((C54/C46)^(1/8)-1,"") -> 0.22662589 | D55: =IFERROR((D54/D46)^(1/8)-1,"") -> 0.41300781 | F55: =IFERROR((F54/F46)^(1/8)-1,"") -> 0.10197272 | H55: =IFERROR((H54/H46)^(1/8)-1,"") -> 0.16939006 | J55: FX | L55: =_xlfn.XLOOKUP($J55,'Fin. Data'!$A:$A,'Fin. Data'!B:B,,0) -> -0.7 | M55: =_xlfn.XLOOKUP($J55,'Fin. Data'!$A:$A,'Fin. Data'!C:C,,0) -> -0.4 | N55: =(C55/C54)-1 -> -0.99995619 | O55: =(D55/D54)-1 -> 0.76049896
B56: Average Growth Rate | C56: =IFERROR(AVERAGE(N47:N54),"") -> 0.23157374 | D56: =IFERROR(AVERAGE(O47:O54),"") -> 0.48503644 | F56: =IFERROR(AVERAGE(Q47:Q54),"") -> -0.58192402 | H56: =IFERROR(AVERAGE(S47:S54),"") -> 2.4590916 | J56: Changes in Cash | L56: =L48-L49+L52-L53-L54 -> 2548.8 | M56: =M48-M49+M52-M53-M54 -> 827.6
B57: CVAR | C57: =IFERROR(STDEV(C47:C54)/AVERAGE(C47:C54),"") -> 0.5084177 | D57: =IFERROR(STDEV(D46:D54)/AVERAGE(D46:D54),"") -> 0.58694462 | F57: =IFERROR(STDEV(F46:F54)/AVERAGE(F46:F54),"") -> 0.88051528 | H57: =IFERROR(STDEV(H46:H54)/AVERAGE(H46:H54),"") -> 0.37793175 | J57: Inventory/D Revenues | L57: =IFERROR(SUM(I51:I54)/(C54-C50),"") -> -0.2292255 | M57: =IFERROR((SUM(I51:I54)-SUM(H51:H54))/(C54-C50),"") -> -0.35149683
B58: Last Year | C58: =IFERROR(C54/C53-1,"") -> 0.17098293 | D58: =IFERROR(D54/D53-1,"") -> 0.068800404 | F58: =IFERROR(1-(F54/F53),"") -> -0.41391372 | H58: =IFERROR(1-(H54/H53),"") -> -0.059443912 | J58: t inversiones; t adq. neto dep. | L58: =IFERROR(L57/E27,"") -> -0.91017939 | M58: =IFERROR(M57/E27,"") -> -1.3956788
B59: QUALITATIVE ANALYSIS
B60: SWOT ANALYSIS | J60: HOLDERS (24.11.2023)
B61: Pros | E61: Cons | J61: Name | M61: % Stake
B62: - Successful record of integrating complimentary firms through M&As. - Strategic Partnerships with other technology leaders(Google, Microsoft, IBM, Cisco) - Strong brand and record of consumer driven innovation with R&D - High and growing operating margins (since 2018 constantly above ‘the rule of 40’ in non-GAAP terms) - Strong and consistent revenue growth (total CAGR 23,49%) | E62: - Significant percentage of the operating expenses that are fixed in nature - Majority of revenues dependent on only few products that have a discretionary nature - Reliance on third party channel partners for substantial part of the revenue, and vulnerability to their non-compliance with regulations - Small number of distributors representing large percentage of revenue and gross accounts receivable - High and sudden indebtedness (990,4 million in 2022) - CEO holding position of the Chairman (possible conflict of interest) | J62: Xie Michael | M62: 0.0908
J63: Vanguard Group Inc | M63: 0.088
J64: Xie Kenneth | M64: 0.0825
J65: Blackrock Inc | M65: 0.0423
J66: AllianceBernstein LP | M66: 0.0379
J67: State Street Corporation | M67: 0.0333
J68: Geode Capital Management LLC | M68: 0.0184
J69: Invesco Capital Management(QQQ Trust) | M69: 0.0176
J70: Walter Scott & Partners Ltd | M70: 0.014
J71: Nordea Funds Oy | M71: 0.0123
B72: Opportunities | E72: Risks | J72: Fidelity Management & Research Company LLC | M72: 0.0114
B73: - Rising popularity of new IT solutions - IoT, OT security, AI, cloud computing - Significant growth opportunities in SASE - Convergence of Networking & Security on the market, and possible rise of demand for Fortinets’ products in that segment - Working at home and resulting rise in the need of an additional cybersecurity coverage - Rising demand for security products due to digital transformation and increasing importance of IT for businesses across all industries - Rising risk of cyber-attacks giving growth opportunities for cybersecurity companies | E73: - International operations that increase compliance regulatory requirements risk, collection risk and currency exchange risk - Adverse economic conditions (recession, stagflation, rising interest rates) - Uncertainty of protecting IP rights in some countries - Vulnerability to protectionist policies, constantly changing industry and political environment - High competition - Skills shortage | J73: Columbia Threadneedle Investments | M73: 0.011
J74: First Trust Advisors | M74: 0.01
J75: Swedbank Robur Fonder AB | M75: 0.01
J76: Arrowstreet Capital LP | M76: 0.0099
J77: Viking Global Investors LP | M77: 0.0092
J78: T. Rowe Price Investment Management Inc | M78: 0.009
J79: Norges Bank Investment Management | M79: 0.0083
J80: T. Rowe Price Associates Inc | M80: 0.0072
J81: Legal and General Investment Management Ltd | M81: 0.0072
B82: NOTES | G82: STOCK PERFORMANCE (5 years)
B83: Latest News: - Michael Xie bought 10,6M worth of shares on 20.11.2023, having become the largest shareholder of Fortinet - Fortinet announced acquiring above 8M of shares of Oring Industrial Networking Corp. in august 2023 - Fortinet's FTNT short percent of float has fallen 11.44% since its last report - NetworkWorld reported that Fortinet introduced new AI and ML-based security services utilizing telemetry from its global network - In 2023, Fortinet Fortiguard devices were revealed by Microsoft and members of the Five Eyes intelligence network to be the subject of a wide-ranging and ongoing cyberattack by a state-sponsored entity in China - Fortinet expands its Global SASE Points-of-Presence with Google Cloud - Foertinet expand its Universal SASE Offering to securely connect any user to any application - Fortinet Named a SD-WAN Leader Challenger in the 2023 Gartner Magic Quadrant for single-vendor SASE
G107: #VALUE! | I107: #VALUE! | J107: #VALUE! | K107: #VALUE! | L107: #VALUE! | M107: #VALUE!

Sheet Segments
B2: ="Regions "&"("&OP!$J$20&")" -> Regions (2023) | P2: Products
D3: Nominal value | K3: YoY Growth
B4: Weight | C4: Region | D4: =OP!J20 -> 2023 | E4: =D4-1 -> 2022 | F4: =E4-1 -> 2021 | G4: =F4-1 -> 2020 | H4: =G4-1 -> 2019 | I4: =H4-1 -> 2018 | K4: =OP!J20 -> 2023 | L4: =K4-1 -> 2022 | M4: =L4-1 -> 2021 | N4: =M4-1 -> 2020 | O4: =N4-1 -> 2019
B5: =IFERROR(D5/$D$11,"") -> 0.30386452 | C5: United States | D5: 1571.8 | E5: 1325 | F5: 1006.8 | G5: 813.3 | H5: 695.5 | I5: 577.2 | K5: =(D5-E5)/E5 -> 0.18626415 | L5: =(E5-F5)/F5 -> 0.31605085 | M5: =(F5-G5)/G5 -> 0.23791959 | N5: =(G5-H5)/H5 -> 0.16937455 | O5: =(H5-I5)/I5 -> 0.20495495
B6: =IFERROR(D6/$D$11,"") -> 0.10739072 | C6: Other Americas | D6: 555.5 | E6: 460 | F6: 352 | G6: 263.9 | H6: 224.7 | I6: 185.7 | K6: =(D6-E6)/E6 -> 0.2076087 | L6: =(E6-F6)/F6 -> 0.30681818 | M6: =(F6-G6)/G6 -> 0.33383858 | N6: =(G6-H6)/H6 -> 0.17445483 | O6: =(H6-I6)/I6 -> 0.21001616
B7: =IFERROR(D7/$D$11,"") -> 0.38807586 | C7: Europe, Middle East and Africa (EMEA) | D7: 2007.4 | E7: 1691.8 | F7: 1275.9 | G7: 991.9 | H7: 816.5 | I7: 678 | K7: =(D7-E7)/E7 -> 0.18654687 | L7: =(E7-F7)/F7 -> 0.32596598 | M7: =(F7-G7)/G7 -> 0.28631919 | N7: =(G7-H7)/H7 -> 0.21481935 | O7: =(H7-I7)/I7 -> 0.20427729
B8: =IFERROR(D8/$D$11,"") -> 0.2006689 | C8: Asia Pacific (APAC) | D8: 1038 | E8: 940.6 | F8: 707.5 | G8: 525.3 | H8: 426.3 | I8: 360.3 | K8: =(D8-E8)/E8 -> 0.10355092 | L8: =(E8-F8)/F8 -> 0.32946996 | M8: =(F8-G8)/G8 -> 0.34684942 | N8: =(G8-H8)/H8 -> 0.23223082 | O8: =(H8-I8)/I8 -> 0.18318068
B9: =IFERROR(D9/$D$11,"") -> 0 | K9: =(D9-E9)/E9 -> #DIV/0!
B10: =IFERROR(D10/$D$11,"") -> 0 | K10: =(D10-E10)/E10 -> #DIV/0!
B11: =SUM(B5:B10) -> 1 | C11: TOTAL | D11: =SUM(D5:D10) -> 5172.7 | E11: =SUM(E5:E10) -> 4417.4 | F11: =SUM(F5:F10) -> 3342.2 | G11: =SUM(G5:G10) -> 2594.4 | H11: =SUM(H5:H10) -> 2163 | I11: =SUM(I5:I10) -> 1801.2 | K11: =(D11-E11)/E11 -> 0.17098293 | L11: =(E11-F11)/F11 -> 0.32170427 | M11: =(F11-G11)/G11 -> 0.2882362 | N11: =(G11-H11)/H11 -> 0.19944521 | O11: =(H11-I11)/I11 -> 0.20086609
B13: ="Categories "&"("&OP!$J$20&")" -> Categories (2023)
D14: Nominal value | K14: YoY Growth
B15: Weight | C15: Category | D15: =OP!J20 -> 2023 | E15: =D15-1 -> 2022 | F15: =E15-1 -> 2021 | G15: =F15-1 -> 2020 | H15: =G15-1 -> 2019 | I15: =H15-1 -> 2018 | K15: =OP!J20 -> 2023 | L15: =K15-1 -> 2022 | M15: =L15-1 -> 2021 | N15: =M15-1 -> 2020 | O15: =N15-1 -> 2019
B16: =IFERROR(D16/$D$19,"") -> 0.38269696 | C16: Products | D16: 1979.5 | E16: 1780.5 | F16: 1255 | G16: 916.4 | H16: 788.5 | I16: 674.4 | K16: =(D16-E16)/E16 -> 0.11176636 | L16: =(E16-F16)/F16 -> 0.4187251 | M16: =(F16-G16)/G16 -> 0.36948931 | N16: =(G16-H16)/H16 -> 0.16220672 | O16: =(H16-I16)/I16 -> 0.16918743
B17: =IFERROR(D17/$D$19,"") -> 0.34374094 | C17: Security subscription | D17: 1778 | E17: 1427 | F17: 1125 | G17: 918.7 | H17: 750.8 | I17: 602.6 | K17: =(D17-E17)/E17 -> 0.24597057 | L17: =(E17-F17)/F17 -> 0.26844444 | M17: =(F17-G17)/G17 -> 0.22455644 | N17: =(G17-H17)/H17 -> 0.22362813 | O17: =(H17-I17)/I17 -> 0.24593428
B18: =IFERROR(D18/$D$19,"") -> 0.27356211 | C18: Technical support and other | D18: 1415 | E18: 1209.9 | F18: 962.2 | G18: 759.3 | H18: 623.7 | I18: 524.2 | K18: =(D18-E18)/E18 -> 0.16951814 | L18: =(E18-F18)/F18 -> 0.25743089 | M18: =(F18-G18)/G18 -> 0.26721981 | N18: =(G18-H18)/H18 -> 0.21741222 | O18: =(H18-I18)/I18 -> 0.18981305
B19: =SUM(B16:B18) -> 1 | C19: TOTAL | D19: =SUM(D16:D18) -> 5172.5 | E19: =SUM(E16:E18) -> 4417.4 | F19: =SUM(F16:F18) -> 3342.2 | G19: =SUM(G16:G18) -> 2594.4 | H19: =SUM(H16:H18) -> 2163 | I19: =SUM(I16:I18) -> 1801.2 | K19: =(D19-E19)/E19 -> 0.17093766 | L19: =(E19-F19)/F19 -> 0.32170427 | M19: =(F19-G19)/G19 -> 0.2882362 | N19: =(G19-H19)/H19 -> 0.19944521 | O19: =(H19-I19)/I19 -> 0.20086609
B21: Categories | D21: Description | I21: Graphs
B22: Products | D22: FortiGate network security products, Fortinet Security Fabric platform products and other products
B23: Security Subscription | D23: Subscriptions for online security solutions for applications; content; web traffic; devices; and users.
B24: Technical Support and other | D24: Service to ensure efficient, effective operations and maintenance of their products
B25: - | D25: -
B26: - | D26: -
B29: Industry | J29: Graphs (Industry Forecasts)
B30: Drivers | D30: Description
B31: Security Driven Networking
B32: Heightned awareness
B33: Increased Investments
B34: Sales forecast
B35: Source | D35: Market Growth CAGR | G35: Period
B36: Mordor Intelligence | D36: 0.176 | G36: 2018-2028
B37: Business Research Insights | D37: 0.1227 | G37: 2022-2031
B38: Vault | D38: 0.2358 | G38: 2019-2015
B39: Statista | D39: 0.0737 | G39: 2023-2028
B40: Average | D40: =AVERAGE(D36:D39) -> 0.15205
B41: Company's Strategy / Extra Notes

Sheet Acuerdo
A1: Invertir
A2: NO invertir
A3: Mantener sin elevar posición
A4: Mantener (y seguir comprando)
A5: Liquidar
A6: PENDIENTE

Sheet Peers
B1: Peer Logo | C1: Peer Name | D1: Description
C2: #VALUE! | D2: Palo Alto NetWorks, Inc. is a gloval cybersecurity provider. The Company's platforms and services help secure entreprise users, networks, clouds and endpoints dy delivering value in four areas, NetWork Security, Cloud Secuirty, Secuirty Operations, Threat Intelligence and Secuirty Consulting. Those solutions are delivered through its Cortex portfolio.
C3: #VALUE! | D3: CrowdStrike Holdings, Inc. is a cybersecuirty company that provides cloud-delivered protection of endpoints, cloud workloads, identity and data via a software-as-a-service (SaaS) subscription-based model. The comapny offers Falcon platform in a SaaS subscription-based model, which delivers technologies that deliver protection and performance, while reducing costumer complexity.
C4: #VALUE! | D4: Check Point develops, markets and supports a wide range of products and services for IT security by offering a multilevel security architecture that defends enterprises’ cloud, network, mobile devices, Endpoints information and IOT solutions. Their solutions operate under a unified security architecture, Infinity, that enables end-to-end security with a single line of unified security gateways and allow a single agent for all endpoint security that can be managed from a single unified management console.
C5: #VALUE! | D5: Cisco designs and sells a broad range of technologies that power the Internet. They are integrating a product portfolios across networking, security, collaboration, applications and the cloud to create highly secure, intelligent platforms for its customers’ digital businesses. The End-to-End Security product category, the segment where Cisco competes with Fortinet, consists of Cloud and Application Security, Industrial Security, Network Security, and User and Device Security offerings. Cisco continues to invest in resources across the security portfolio focused on cloud-based offerings, AI-driven threat detection and end-to-end security architectures. Additionally, the company is invesnting in expanding their SASE architecture by delivering combined network and security functionality in a single cloud-native service.
C6: #VALUE! | D6: Zscaler, Inc. is a cloud security company that developed a platform incorporating core security functionalities needed to enable fast and secure access to cloud resources based on identity, context and organization’s policies. Their solution is a purpose-built, multi-tenant, distributed cloud platform that incorporates the security functionality needed to enable users, applications, and devices to safely and efficiently utilize authorized applications and services based on an organization’s business policies. Zscaler delivers solutions using a software-as-a-service ("SaaS") business model and sell subscriptions to customers to access our cloud platform, together with related support services.
B8: In Millions USD | C8: =OP!E2 -> #VALUE! | D8: =C2 -> #VALUE! | E8: =C3 -> #VALUE! | F8: #VALUE! | G8: =C5 -> #VALUE! | H8: =C6 -> #VALUE! | I8: AVERAGE | J8: Deviation from Average
B9: Company Info | I9: =IFERROR(AVERAGE(C9:H9),"") | L9: TRAFFIC
B10: Market Cap | C10: 39170 | D10: {=_FV(D8,"Market cap",TRUE)/1000000} -> 113172 | E10: {=_FV(E8,"Market cap",TRUE)/1000000} -> 62146.896 | F10: {=_FV(F8,"Market cap",TRUE)/1000000} -> 21435.29 | G10: {=_FV(G8,"Market cap",TRUE)/1000000} -> 195985 | H10: {=_FV(H8,"Market cap",TRUE)/1000000} -> 24442.321 | I10: =IFERROR(AVERAGE(C10:H10),"") -> 76058.584 | J10: =SQRT((C10-I10)^2) -> 36888.584 | M10: Best Value
B11: Net Sales (current) | C11: =C56 -> 5172.7 | D11: =D56 -> 7207.4 | E11: =E56 -> 2847.59 | F11: =F56 -> 2389.7 | G11: =G56 -> 3898 | H11: =H56 -> 1758.11 | I11: =IFERROR(AVERAGE(C11:H11),"") -> 3878.9167 | J11: =SQRT((C11-I11)^2) -> 1293.7833
B12: Profitability | I12: =IFERROR(AVERAGE(C12:H12),"") | M12: Important Value
B13: Sales Growth (ttm) | C13: =C56/C55-1 -> 0.17098293 | D13: =D56/D55-1 -> 0.31007907 | E13: =E56/E55-1 -> 0.39938964 | F13: =F56/F55-1 -> 0.043309321 | G13: =G56/G55-1 -> 0.044200375 | H13: =H56/H55-1 -> 0.44583792 | I13: =IFERROR(AVERAGE(C13:H13),"") -> 0.23563321 | J13: =SQRT((C13-I13)^2) -> 0.06465028
B14: Sales Growth (36m) | C14: =C56/C54-1 -> 0.99379433 | D14: =D56/D54-1 -> 1.1145992 | E14: =E56/E54-1 -> 2.7388593 | F14: =F56/F54-1 -> 0.15729575 | G14: =G56/G54-1 -> 0.21850578 | H14: =H56/H54-1 -> 2.6607463 | I14: =IFERROR(AVERAGE(C14:H14),"") -> 1.3139668 | J14: =SQRT((C14-I14)^2) -> 0.32017244 | M14: Worst Value
B15: Operating Margin | C15: =C59/C56 -> 0.23459702 | D15: =D59/D56 -> 0.085176347 | E15: =E59/E56 -> -0.032718896 | F15: =F59/F56 -> 0.37716031 | H15: =H59/H56 -> -0.12035083 | I15: =IFERROR(AVERAGE(C15:H15),"") -> 0.10877279 | J15: =SQRT((C15-I15)^2) -> 0.12582423
B16: Net Income Margin | C16: =C62/C56 -> 0.22245636 | D16: =D62/D56 -> 0.085176347 | E16: =E62/E56 -> -0.0046671045 | F16: =F62/F56 -> 0.36029627 | H16: =H62/H56 -> -0.057271729 | I16: =IFERROR(AVERAGE(C16:H16),"") -> 0.12119803 | J16: =SQRT((C16-I16)^2) -> 0.10125833
B17: Return on Equity (RoE) | C17: =C62/C74 -> 15.529015 | D17: =D62/D74 -> 0.28283806 | E17: =E62/E74 -> -0.0064487954 | F17: =F62/F74 -> 0.30924503 | H17: =H62/H74 -> -0.12468887 | I17: =IFERROR(AVERAGE(C17:H17),"") -> 3.1979921 | J17: =SQRT((C17-I17)^2) -> 12.331023
B18: Return on Invested Capital (ROIC) | C18: =(C62+C61)/(C73+C74) -> 0.96853952 | D18: =(D62+D61)/(D73+D74) -> 0.1854086 | E18: =(E62+E61)/(E73+E74) -> 0.0037292919 | F18: =(F62+F61)/(F73+F74) -> 0.18043651 | H18: =(H62+H61)/(H73+H74) -> -0.03789354 | I18: =IFERROR(AVERAGE(C18:H18),"") -> 0.26004408 | J18: =SQRT((C18-I18)^2) -> 0.70849545
B19: Solvency | I19: =IFERROR(AVERAGE(C19:H19),"")
B20: Debt/Assets | C20: =C73/C70 -> 0.14096239 | D20: =D73/D70 -> 0.15008272 | E20: =E73/E70 -> 1.3680986 | F20: =F73/F70 -> 0.48458876 | H20: =H73/H70 -> 0.3612364 | I20: =IFERROR(AVERAGE(C20:H20),"") -> 0.50099377 | J20: =SQRT((C20-I20)^2) -> 0.36003138
B21: Net Debt/EBITDA | C21: =(C73-C65)/C58 -> -0.80478965 | D21: =(D73-D65)/D58 -> -0.30178712 | E21: =(E73-E65)/E58 -> -57.863987 | F21: =(F73-F65)/F58 -> 2.4781867 | H21: =(H73-H65)/H58 -> 1.0262991 | I21: =IFERROR(AVERAGE(C21:H21),"") -> -11.093216 | J21: =SQRT((C21-I21)^2) -> 10.288426
B22: Interest Coverage Ratio | C22: =-C58/C60 -> -17.994885 | D22: =-D58/D60 -> 51.427746 | E22: =-E58/E60 -> -1.4624367 | F22: =-F58/F60 -> -39.724576 | H22: =-H58/H60 -> -16.990442 | I22: =IFERROR(AVERAGE(C22:H22),"") -> -4.9489189 | J22: =SQRT((C22-I22)^2) -> 13.045966
B23: Liquidity
B24: Current Ratio | C24: =C68/C72 -> 1.3024664 | D24: =D68/D72 -> 0.86213964 | E24: =E68/E72 -> 1.7354898 | F24: =F68/F72 -> 2.0808971 | H24: =H68/H72 -> 1.9611712 | I24: =IFERROR(AVERAGE(C24:H24),"") -> 1.5884328 | J24: =SQRT((C24-I24)^2) -> 0.28596641
B25: Quick Ratio | C25: =(C65+C66)/C72 -> 0.87711702 | D25: =(D65+D66)/D72 -> 0.51960497 | E25: =(E65+E66)/E72 -> 1.5021741 | F25: =(F65+F66)/F72 -> 0.72461504 | H25: =(H65+H66)/H72 -> 1.1723661 | I25: =IFERROR(AVERAGE(C25:H25),"") -> 0.95917544 | J25: =SQRT((C25-I25)^2) -> 0.082058421
B26: Activity | I26: =IFERROR(AVERAGE(C26:H26),"")
B27: Inventory Turnover | C27: =C57/C67 -> 0.99101604 | D27: =D57/D67 -> #DIV/0! | E27: =E57/E67 -> #DIV/0! | F27: =F57/F67 -> #DIV/0! | H27: =H57/H67 -> #DIV/0! | I27: =IFERROR(AVERAGE(C27:H27),"") | J27: =SQRT((C27-I27)^2) -> #VALUE!
B28: Acc. Receivable Turnover | C28: =C56/C66 -> 5.1022884 | D28: =D56/D66 -> 5.1007785 | E28: =E56/E66 -> 5.0680584 | F28: =F56/F66 -> 6.7315493 | H28: =H56/H66 -> 4.7925799 | I28: =IFERROR(AVERAGE(C28:H28),"") -> 5.3590509 | J28: =SQRT((C28-I28)^2) -> 0.25676248
A29: Price/Sales | B29: Payables Turnover | C29: =C57/C71 -> 1.8247341 | D29: =D57/D71 -> 14.518209 | E29: =E57/E71 -> 12.686677 | F29: =F57/F71 -> 0.59175084 | H29: =H57/H71 -> 17.112785 | I29: =IFERROR(AVERAGE(C29:H29),"") -> 9.3468314 | J29: =SQRT((C29-I29)^2) -> 7.5220972
B30: Fixed Asset Turnover | C30: =C56/C69 -> 3.7754179 | D30: =D56/D69 -> 20.440726 | E30: =E56/E69 -> 4.9008502 | F30: =F56/F69 -> 29.321472 | H30: =H56/H69 -> 6.6196393 | I30: =IFERROR(AVERAGE(C30:H30),"") -> 13.011621 | J30: =SQRT((C30-I30)^2) -> 9.2362033
B31: Total Asset Turnover | C31: =C56/C70 -> 0.69160216 | D31: =D56/D70 -> 0.48670696 | E31: =E56/E70 -> 4.9008502 | F31: =F56/F70 -> 0.44238138 | H31: =H56/H70 -> 0.5223795 | I31: =IFERROR(AVERAGE(C31:H31),"") -> 1.408784 | J31: =SQRT((C31-I31)^2) -> 0.71718188
B32: Valuation | I32: =IFERROR(AVERAGE(C32:H32),"")
B33: Price/Earnings | C33: =C10/C62 -> 34.040149 | D33: 144.17 | E33: Negative | F33: =F10/F62 -> 24.895807 | H33: Negative | I33: =IFERROR(AVERAGE(C33:H33),"") -> 67.701986 | J33: =SQRT((C33-I33)^2) -> 33.661836
B34: Price/Sales | C34: =C10/C56 -> 7.5724477 | D34: =D10/D56 -> 15.702195 | E34: =E10/E56 -> 21.824383 | F34: =F10/F56 -> 8.9698665 | H34: =H10/H56 -> 13.902612 | I34: =IFERROR(AVERAGE(C34:H34),"") -> 13.594301 | J34: =SQRT((C34-I34)^2) -> 6.0218532
B35: Price/Book | C35: =C10/C74 -> 528.60999 | D35: =D10/D74 -> 52.140981 | E35: =E10/E74 -> 30.155953 | F35: =F10/F74 -> 7.6989045 | H35: =H10/H74 -> 30.268004 | I35: =IFERROR(AVERAGE(C35:H35),"") -> 129.77477 | J35: =SQRT((C35-I35)^2) -> 398.83522
B36: EV/Sales | C36: =(C73+C10-C65)/C56 -> 7.3535098 | D36: =(D73+D10-D65)/D56 -> 15.664942 | E36: =(E73+E10-E65)/E56 -> 21.060948 | F36: =(F73+F10-F65)/F56 -> 9.9420806 | H36: =(H73+H10-H65)/H56 -> 13.819597 | I36: =IFERROR(AVERAGE(C36:H36),"") -> 13.568215 | J36: =SQRT((C36-I36)^2) -> 6.2147056
B37: EV/EBITDA | C37: =(C73+C10-C65)/C58 -> 27.030628 | D37: =(D73+D10-D65)/D58 -> 126.90064 | E37: =(E73+E10-E65)/E58 -> 1596.2988 | F37: =(F73+F10-F65)/F58 -> 25.342496 | H37: =(H73+H10-H65)/H58 -> -170.84854 | I37: =IFERROR(AVERAGE(C37:H37),"") -> 320.94481 | J37: =SQRT((C37-I37)^2) -> 293.91418
B38: Stock Info | I38: =IFERROR(AVERAGE(C38:H38),"")
B39: Float | C39: =OP!M20 -> 0.842 | D39: 0.9886 | E39: 93,46% | F39: 77,92% | H39: 60,86% | I39: =IFERROR(AVERAGE(C39:H39),"") -> 0.9153 | J39: =SQRT((C39-I39)^2) -> 0.0733
B40: b (Yahoo) | C40: 1,05 | D40: 1,17 | E40: 1,05 | F40: 0,64 | H40: 0,87 | I40: =IFERROR(AVERAGE(C40:H40),"") | J40: =SQRT((C40-I40)^2) -> #VALUE!
B41: Dividend Yield (yahoo finance) | C41: =OP!M32 -> 0 | D41: 0 | E41: 0 | F41: 0 | H41: 0 | I41: =IFERROR(AVERAGE(C41:H41),"") -> 0 | J41: =SQRT((C41-I41)^2) -> 0
B42: Stock Performance
B43: 1y | C43: 0,33% | D43: 76,13% | E43: 110,62% | F43: 9,86% | H43: 72,63% | I43: =IFERROR(AVERAGE(C43:H43),"") | J43: =SQRT((C43-I43)^2) -> #VALUE!
B44: 3y | C44: 205,2% | D44: 296,6% | E44: 1.56 | F44: 22,34% | H44: 28,73% | I44: =IFERROR(AVERAGE(C44:H44),"") -> 1.56 | J44: =SQRT((C44-I44)^2) -> #VALUE!
B45: Current Price | C45: 51.01 | D45: 293,59 | E45: 239,72 | F45: 144,5 | H45: 200,20 | I45: =IFERROR(AVERAGE(C45:H45),"") -> 51.01 | J45: =SQRT((C45-I45)^2) -> 0
B46: Average Target Price | C46: 57.08 | D46: 282,66 | E46: 236,00 | F46: 143,09 | H46: 210,14 | I46: =IFERROR(AVERAGE(C46:H46),"") -> 57.08 | J46: =SQRT((C46-I46)^2) -> 0
B47: Upside/Downside | C47: =C46/C45-1 -> 0.11899628 | D47: =D46/D45-1 -> -0.037228788 | E47: =E46/E45-1 -> -0.015518104 | F47: =F46/F45-1 -> -0.0097577855 | G47: =G46/G45-1 -> #DIV/0! | H47: =H46/H45-1 -> 0.04965035 | I47: =IFERROR(AVERAGE(C47:H47),"") | J47: =SQRT((C47-I47)^2) -> #VALUE!
B48: Extra | I48: =IFERROR(AVERAGE(C48:H48),"")
B49: 3y Operating Cash Flow | C49: =(Inputs!C59-Inputs!F59)/Inputs!F59 -> 1.1418317 | D49: 268,17% | E49: 1093,11% | F49: -0.09 | H49: 582,90% | I49: =IFERROR(AVERAGE(C49:H49),"") -> 0.52591584 | J49: =SQRT((C49-I49)^2) -> 0.61591584
B50: R&D/Net Sales | C50: =C63/C11 -> 0.11725018 | D50: =D63/D11 -> 0.22777978 | E50: =E63/E11 -> 0.26209532 | F50: =F63/F11 -> 0.15052099 | G50: =G63/G11 -> 0 | H50: =H63/H11 -> 0.22087924 | I50: =IFERROR(AVERAGE(C50:H50),"") -> 0.16308758 | J50: =SQRT((C50-I50)^2) -> 0.045837405
B52: Financial Data | C52: =OP!E2 -> #VALUE! | D52: =D8 -> #VALUE! | E52: =E8 -> #VALUE! | F52: #VALUE! | G52: =G8 -> #VALUE! | H52: =H8 -> #VALUE!
B53: IS
B54: Net Sales (36m ago) | C54: ='Fin. Data'!E5 -> 2594.4 | D54: 3408.4 | E54: 761.62 | F54: 2064.9 | G54: =3154+861-816 -> 3199 | H54: 480.26
B55: Net Sales (12m ago) | C55: ='Fin. Data'!C5 -> 4417.4 | D55: 5501.5 | E55: 2034.88 | F55: 2290.5 | G55: =3699+895-861 -> 3733 | H55: 1215.98
B56: Net Sales (current) | C56: ='Fin. Data'!B5 -> 5172.7 | D56: 7207.4 | E56: 2847.59 | F56: 2389.7 | G56: =3859+1010-971 -> 3898 | H56: 1758.11
B57: COGS | C57: ='Fin. Data'!C5-'Fin. Data'!B7 -> 463.3 | D57: 1913.5 | E57: 722.76 | F57: 281.2 | H57: 397.53
B58: EBITDA | C58: ='Fin. Data'!B19 -> 1407.2 | D58: 889.7 | E58: 37.57 | F58: 937.5 | H58: -142.21
B59: Operating Income | C59: ='Fin. Data'!B11 -> 1213.5 | D59: 613.9 | E59: -93.17 | F59: 901.3 | H59: -211.59
B60: Net Financial Cost | C60: ='Fin. Data'!B14 -> 78.2 | D60: -17.3 | E60: 25.69 | F60: 23.6 | H60: -8.37
B61: Taxes | C61: ='Fin. Data'!B21 -> -57.8 | D61: 200.6 | E61: 23.94 | F61: 113.7 | H61: 24.02
B62: Net Income | C62: ='Fin. Data'!B23 -> 1150.7 | D62: 613.9 | E62: -13.29 | F62: 861 | H62: -100.69
B63: R&D | C63: 606.5 | D63: 1641.7 | E63: 746.34 | F63: 359.7 | H63: 388.33
B65: Cash & Eq. | C65: ='Fin. Data'!B39 -> 2186.8 | D65: 2491 | E65: 2968.87 | F65: 294.4 | H65: 1361.72
B66: Acc. Receivables | C66: ='Fin. Data'!B40 -> 1013.8 | D66: 1413 | E66: 561.87 | F66: 355 | H66: 366.84
B67: Inventory | C67: ='Fin. Data'!B41 -> 467.5 | D67: 0 | E67: 0 | F67: 0 | H67: 0
B68: Current Assets | C68: =Inputs!B27 -> 4752.7 | D68: 6477.6 | E68: 4079.13 | F68: 1864.9 | H68: 2891.59
B69: Fixed Assets | C69: ='Fin. Data'!B42 -> 1370.1 | D69: 352.6 | E69: 581.04 | F69: 81.5 | H69: 265.59
B70: Total Assets | C70: ='Fin. Data'!B44 -> 7479.3 | D70: 14808.5 | E70: 581.04 | F70: 5401.9 | H70: 3365.58
B71: Acc. Payable | C71: =Inputs!B43 -> 253.9 | D71: 131.8 | E71: 56.97 | F71: 475.2 | H71: 23.23
B72: Current Liabilities | C72: =Inputs!B42 -> 3649 | D72: 7513.4 | E72: 2350.42 | F72: 896.2 | H72: 1474.42
B73: Total Debt | C73: ='Fin. Data'!B58 -> 1054.3 | D73: 2222.5 | E73: 794.92 | F73: 2617.7 | H73: 1215.77
B74: Total Equity | C74: ='Fin. Data'!B64 -> 74.1 | D74: 2170.5 | E74: 2060.85 | F74: 2784.2 | H74: 807.53
D76: Note: Total Debt=convertible senior notes + long-term leases | G76: Cisco Net sales are TTM End-to-end segment sales reported on their financial statements
C77: =C73/C59 -> 0.86880923 | D77: Net sales (32m ago) are the 2020 TTM sales. Current sales are the ttm and 12m ago sales are ttm for the last year | G77: Asset base, liabilities, depreciation, interest expenses and other financial metrics
D78: 2022 TTM data is used for net sales(12m ago) | G78: can't be attributed to a specific segment. As such, only net sales are benchamarked and
D79: 2020 data is used for net sales(36m ago) | G79: the business model are compared qualitatively, as Cisco is the industry leader
D80: 2022 data is used for financial cost. There's no data for TTM | G80: through it's network products ecossystem.
B85: WC Simplified | C85: =C66+C67-C71 -> 1227.4 | D85: =D66+D67-D71 -> 1281.2 | E85: =E66+E67-E71 -> 504.9 | F85: =F66+F67-F71 -> -120.2 | G85: =G66+G67-G71 -> 0 | H85: =H66+H67-H71 -> 343.61
B86: WC Simplified/Current Sales | C86: =C85/C56 -> 0.2372842 | D86: =D85/D56 -> 0.17776174 | E86: =E85/E56 -> 0.17730783 | F86: =F85/F56 -> -0.050299201 | G86: =G85/G56 -> 0 | H86: =H85/H56 -> 0.19544283
B87: Average of Peers | C87: =AVERAGE(D86:F86,H86) -> 0.1250533
D89: qualitative analysis
E91: CrowdStrike is in financial distress due to its excessive debt burden. The company feed its growth with debt. To restore their financial health, CrowdStrike needs to lower their selling cost to gain control over their operating margin and pay interest and
E92: CrowdStrike cash flow was negative untill 2020, year which it turned positive. Since then, it has had great free cash flow growth despite negative net income and high debt.
E93: Fortinet has negative net debt, deriving from its strong cash position. It gives Fortinet the possibility to do strategic acquisitions as a groth strategy and also take on debt to fuel growth through spending
E95: The high PB ratio of Fortinet comes from its particular financing and equity structure
E97: Its the best operatig margin when taking into consideration sales growth
E98: Palo Alto is

Sheet SARD
A1: 1769 | F1: Variables | K1: Rankings | P1: Difference | U1: Results | Y1: Additional Information | AD1: =#REF! -> #REF! | AE1: Selected Peers | AJ1: Price Multiples (TTM) | AM1: Enterprise Value Multiples (TTM)
B2: Ticker | C2: Company Name | D2: TRBC Industry | E2: Country | F2: ROE | G2: DEBT/EBIT | H2: Market Cap | I2: EPS Growth (2019-2023) (Refinitiv Smart Estimate) | J2: EBIT Margin | K2: ROE | L2: DEBT/EBIT | M2: Market Cap | N2: EPS Growth | O2: EBIT Margin | P2: ROE | Q2: DEBT/EBIT | R2: Market Cap | S2: EPS Growth | T2: EBIT Margin | U2: SARD Result | V2: SARD Peers | W2: SARD Peers adjusted Rank | Y2: Suitability | Z2: Relevant Information Missing | AA2: Author's Override | AB2: Observations | AE2: SARD Peers adjusted Rank | AF2: SARD Result | AG2: Ticker | AH2: Company Name | AI2: Country | AJ2: P / E | AK2: P / B | AL2: Price / Sales | AM2: EV / Sales | AN2: EV / EBITDA
A3: Benchmark | C3: Fortinet | D3: Software | E3: United States of America | F3: =Peers!C17% -> 0.15529015 | G3: 0.86880923 | H3: =Peers!C10*1000000 -> 39170000000 | I3: 16.62 | J3: 0.2346 | K3: =IFERROR(_xlfn.RANK.EQ(F3,F$3:F$1770),"N/A") -> 135 | L3: =IFERROR(_xlfn.RANK.EQ(G3,G$3:G$1770),"N/A") -> N/A | M3: =IFERROR(_xlfn.RANK.EQ(H3,H$3:H$1770),"N/A") -> 16 | N3: =IFERROR(_xlfn.RANK.EQ(I3,I$3:I$1770),"N/A") -> 186 | O3: =IFERROR(_xlfn.RANK.EQ(J3,J$3:J$1770),"N/A") -> 206 | P3: - | Q3: - | R3: - | S3: - | T3: - | U3: - | V3: - | W3: - | Y3: =IF(OR(Z3="Y",AA3="Y"),"Not suitable","") | Z3: =IF(N3="N/A","Y","") | AE3: {=_xlfn._xlws.SORT(_xlfn._xlws.FILTER(SARD!W3:W61,SARD!W3:W61<=SMALL(W3:W61,6)),,1)} -> #VALUE! | AF3: =_xlfn.XLOOKUP($AE3,$W:$W,U:U,,0) -> #VALUE! | AG3: =_xlfn.XLOOKUP($AE3,$W:$W,B:B,,0) -> #VALUE! | AH3: =_xlfn.XLOOKUP($AE3,$W:$W,C:C,,0) -> #VALUE! | AI3: =_xlfn.XLOOKUP($AE3,$W:$W,E:E,,0) -> #VALUE!
A4: Comparison | B4: MSFT.OQ | C4: Microsoft Corp | D4: Software | F4: -0.034 | G4: 2.804055 | H4: 2.7569977e+12 | I4: 6.17 | J4: 0.503 | K4: =IFERROR(_xlfn.RANK.EQ(F4,F$3:F$1770),"N/A") -> 335 | L4: =IFERROR(_xlfn.RANK.EQ(G4,G$3:G$1770),"N/A") -> N/A | M4: =IFERROR(_xlfn.RANK.EQ(H4,H$3:H$1770),"N/A") -> 1 | N4: =IFERROR(_xlfn.RANK.EQ(I4,I$3:I$1770),"N/A") -> 261 | O4: =IFERROR(_xlfn.RANK.EQ(J4,J$3:J$1770),"N/A") -> 20 | P4: 4.75 | Q4: 18.09 | R4: 6.02 | S4: 135.55 | T4: 268,966,447.00 | U4: =SUM(P4:T4) -> 0 | V4: =_xlfn.RANK.EQ(U4,$U$4:$U$61,1) -> 1 | W4: =IF(Y4="Not suitable","-",V4) -> 1 | Y4: =IF(OR(Z4="Y",AA4="Y"),"Not suitable","") | Z4: =IF(N4="N/A","Y","") | AF4: =_xlfn.XLOOKUP($AE4,$W:$W,U:U,,0) -> Results | AG4: =_xlfn.XLOOKUP($AE4,$W:$W,B:B,,0) -> 0 | AH4: =_xlfn.XLOOKUP($AE4,$W:$W,C:C,,0) -> 0 | AI4: =_xlfn.XLOOKUP($AE4,$W:$W,E:E,,0) -> 0
B5: ORCL.N | C5: Oracle Corp | D5: Software | F5: 0.393 | G5: 0.71692644 | H5: 3.0919338e+11 | I5: 4.75 | J5: 0.402 | K5: =IFERROR(_xlfn.RANK.EQ(F5,F$3:F$1770),"N/A") -> 32 | L5: =IFERROR(_xlfn.RANK.EQ(G5,G$3:G$1770),"N/A") -> N/A | M5: =IFERROR(_xlfn.RANK.EQ(H5,H$3:H$1770),"N/A") -> 2 | N5: =IFERROR(_xlfn.RANK.EQ(I5,I$3:I$1770),"N/A") -> 272 | O5: =IFERROR(_xlfn.RANK.EQ(J5,J$3:J$1770),"N/A") -> 56 | P5: 19.40 | Q5: 44.78 | R5: 20.15 | S5: 1,118.06 | T5: 24,713,557.00 | U5: =SUM(P5:T5) -> 0 | V5: =_xlfn.RANK.EQ(U5,$U$4:$U$61,1) -> 1 | W5: =IF(Y5="Not suitable","-",V5) -> 1 | Y5: =IF(OR(Z5="Y",AA5="Y"),"Not suitable","") | Z5: =IF(N5="N/A","Y","") | AF5: =_xlfn.XLOOKUP($AE5,$W:$W,U:U,,0) -> Results | AG5: =_xlfn.XLOOKUP($AE5,$W:$W,B:B,,0) -> 0 | AH5: =_xlfn.XLOOKUP($AE5,$W:$W,C:C,,0) -> 0 | AI5: =_xlfn.XLOOKUP($AE5,$W:$W,E:E,,0) -> 0
B6: ADBE.OQ | C6: Adobe Inc | D6: Software | F6: -6.079 | G6: 6.5694475 | H6: 277177534000 | I6: 9.84 | J6: 0.385 | K6: =IFERROR(_xlfn.RANK.EQ(F6,F$3:F$1770),"N/A") -> 506 | L6: =IFERROR(_xlfn.RANK.EQ(G6,G$3:G$1770),"N/A") -> N/A | M6: =IFERROR(_xlfn.RANK.EQ(H6,H$3:H$1770),"N/A") -> 3 | N6: =IFERROR(_xlfn.RANK.EQ(I6,I$3:I$1770),"N/A") -> 230 | O6: =IFERROR(_xlfn.RANK.EQ(J6,J$3:J$1770),"N/A") -> 63 | P6: 0.78 | Q6: 13.59 | S6: 0.07 | T6: 160,694,556.00 | U6: =SUM(P6:T6) -> 0 | V6: =_xlfn.RANK.EQ(U6,$U$4:$U$61,1) -> 1 | W6: =IF(Y6="Not suitable","-",V6) -> 1 | Y6: =IF(OR(Z6="Y",AA6="Y"),"Not suitable","") | Z6: =IF(N6="N/A","Y","") | AF6: =_xlfn.XLOOKUP($AE6,$W:$W,U:U,,0) -> Results | AG6: =_xlfn.XLOOKUP($AE6,$W:$W,B:B,,0) -> 0 | AH6: =_xlfn.XLOOKUP($AE6,$W:$W,C:C,,0) -> 0 | AI6: =_xlfn.XLOOKUP($AE6,$W:$W,E:E,,0) -> 0
B7: SAPG.DE | C7: SAP SE | D7: Software | F7: 0.448 | G7: 0.65167298 | H7: 1.9502593e+11 | I7: -4,05 | J7: 0.254 | K7: =IFERROR(_xlfn.RANK.EQ(F7,F$3:F$1770),"N/A") -> 20 | L7: =IFERROR(_xlfn.RANK.EQ(G7,G$3:G$1770),"N/A") -> N/A | M7: =IFERROR(_xlfn.RANK.EQ(H7,H$3:H$1770),"N/A") -> 4 | N7: =IFERROR(_xlfn.RANK.EQ(I7,I$3:I$1770),"N/A") -> N/A | O7: =IFERROR(_xlfn.RANK.EQ(J7,J$3:J$1770),"N/A") -> 175 | P7: 5.80 | Q7: 22.73 | R7: 4.83 | S7: 159.92 | T7: 1,228,504,232.00 | U7: =SUM(P7:T7) -> 0 | V7: =_xlfn.RANK.EQ(U7,$U$4:$U$61,1) -> 1 | W7: =IF(Y7="Not suitable","-",V7) -> - | Y7: =IF(OR(Z7="Y",AA7="Y"),"Not suitable","") -> Not suitable | Z7: =IF(N7="N/A","Y","") -> Y | AF7: =_xlfn.XLOOKUP($AE7,$W:$W,U:U,,0) -> Results | AG7: =_xlfn.XLOOKUP($AE7,$W:$W,B:B,,0) -> 0 | AH7: =_xlfn.XLOOKUP($AE7,$W:$W,C:C,,0) -> 0 | AI7: =_xlfn.XLOOKUP($AE7,$W:$W,E:E,,0) -> 0
B8: NOW.N | C8: ServiceNow Inc | D8: Software | F8: 0.121 | G8: 2.4128711 | H8: 140974400000 | I8: 12.87 | J8: 0.138 | K8: =IFERROR(_xlfn.RANK.EQ(F8,F$3:F$1770),"N/A") -> 173 | L8: =IFERROR(_xlfn.RANK.EQ(G8,G$3:G$1770),"N/A") -> N/A | M8: =IFERROR(_xlfn.RANK.EQ(H8,H$3:H$1770),"N/A") -> 5 | N8: =IFERROR(_xlfn.RANK.EQ(I8,I$3:I$1770),"N/A") -> 207 | O8: =IFERROR(_xlfn.RANK.EQ(J8,J$3:J$1770),"N/A") -> 372 | S8: 0.01 | T8: 1,411,269,476.00 | U8: =SUM(P8:T8) -> 0 | V8: =_xlfn.RANK.EQ(U8,$U$4:$U$61,1) -> 1 | W8: =IF(Y8="Not suitable","-",V8) -> 1 | Y8: =IF(OR(Z8="Y",AA8="Y"),"Not suitable","") | Z8: =IF(N8="N/A","Y","") | AF8: =_xlfn.XLOOKUP($AE8,$W:$W,U:U,,0) -> Results | AG8: =_xlfn.XLOOKUP($AE8,$W:$W,B:B,,0) -> 0 | AH8: =_xlfn.XLOOKUP($AE8,$W:$W,C:C,,0) -> 0 | AI8: =_xlfn.XLOOKUP($AE8,$W:$W,E:E,,0) -> 0
B9: PANW.OQ | C9: Palo Alto Networks Inc | D9: Software | F9: 0.354 | G9: 4.1859155 | H9: 92575233000 | I9: 18.39 | J9: 0.117 | K9: =IFERROR(_xlfn.RANK.EQ(F9,F$3:F$1770),"N/A") -> 38 | L9: =IFERROR(_xlfn.RANK.EQ(G9,G$3:G$1770),"N/A") -> N/A | M9: =IFERROR(_xlfn.RANK.EQ(H9,H$3:H$1770),"N/A") -> 6 | N9: =IFERROR(_xlfn.RANK.EQ(I9,I$3:I$1770),"N/A") -> 180 | O9: =IFERROR(_xlfn.RANK.EQ(J9,J$3:J$1770),"N/A") -> 439 | P9: 2.83 | R9: 0.73 | S9: 34.85 | T9: 65,514,133.00 | U9: =SUM(P9:T9) -> 0 | V9: =_xlfn.RANK.EQ(U9,$U$4:$U$61,1) -> 1 | W9: =IF(Y9="Not suitable","-",V9) -> 1 | Y9: =IF(OR(Z9="Y",AA9="Y"),"Not suitable","") | Z9: =IF(N9="N/A","Y","") | AE9: Median | AJ9: =MEDIAN(AJ3:AJ8) -> #NUM! | AK9: =MEDIAN(AK3:AK8) -> #NUM! | AL9: =MEDIAN(AL3:AL8) -> #NUM! | AM9: =MEDIAN(AM3:AM8) -> #NUM! | AN9: =MEDIAN(AN3:AN8) -> #NUM!
B10: SNPS.OQ | C10: Synopsys Inc | D10: Software | F10: 1.471 | G10: 5.1420088 | H10: 81219109950 | I10: 10.03 | J10: 0.274 | K10: =IFERROR(_xlfn.RANK.EQ(F10,F$3:F$1770),"N/A") -> 3 | L10: =IFERROR(_xlfn.RANK.EQ(G10,G$3:G$1770),"N/A") -> N/A | M10: =IFERROR(_xlfn.RANK.EQ(H10,H$3:H$1770),"N/A") -> 7 | N10: =IFERROR(_xlfn.RANK.EQ(I10,I$3:I$1770),"N/A") -> 229 | O10: =IFERROR(_xlfn.RANK.EQ(J10,J$3:J$1770),"N/A") -> 153 | P10: 14.47 | Q10: 37.56 | R10: 13.63 | S10: 608.78 | T10: 455,300,000.00 | U10: =SUM(P10:T10) -> 0 | V10: =_xlfn.RANK.EQ(U10,$U$4:$U$61,1) -> 1 | W10: =IF(Y10="Not suitable","-",V10) -> 1 | Y10: =IF(OR(Z10="Y",AA10="Y"),"Not suitable","") | Z10: =IF(N10="N/A","Y","") | AE10: Benchmark Data | AJ10: Price / Share
B11: WDAY.OQ | C11: Workday Inc | D11: Software | F11: 0.298 | G11: 0.013279358 | H11: 71635940000 | I11: 6.89 | J11: 0.043 | K11: =IFERROR(_xlfn.RANK.EQ(F11,F$3:F$1770),"N/A") -> 51 | L11: =IFERROR(_xlfn.RANK.EQ(G11,G$3:G$1770),"N/A") -> N/A | M11: =IFERROR(_xlfn.RANK.EQ(H11,H$3:H$1770),"N/A") -> 8 | N11: =IFERROR(_xlfn.RANK.EQ(I11,I$3:I$1770),"N/A") -> 254 | O11: =IFERROR(_xlfn.RANK.EQ(J11,J$3:J$1770),"N/A") -> 617 | S11: 0.00 | T11: 25,990,731.00 | U11: =SUM(P11:T11) -> 0 | V11: =_xlfn.RANK.EQ(U11,$U$4:$U$61,1) -> 1 | W11: =IF(Y11="Not suitable","-",V11) -> 1 | Y11: =IF(OR(Z11="Y",AA11="Y"),"Not suitable","") | Z11: =IF(N11="N/A","Y","") | AE11: Benchmark | AF11: Multiplier | AG11: # Shares | AH11: -Debt + Cash | AJ11: P / E | AK11: P / B | AL11: Price / Sales | AM11: EV / Sales | AN11: EV / EBITDA
B12: CDNS.OQ | C12: Cadence Design Systems Inc | D12: Software | F12: 0.188 | G12: -13,3930423 | H12: 70591927140 | I12: 9.26 | J12: 0.325 | K12: =IFERROR(_xlfn.RANK.EQ(F12,F$3:F$1770),"N/A") -> 105 | L12: =IFERROR(_xlfn.RANK.EQ(G12,G$3:G$1770),"N/A") -> N/A | M12: =IFERROR(_xlfn.RANK.EQ(H12,H$3:H$1770),"N/A") -> 9 | N12: =IFERROR(_xlfn.RANK.EQ(I12,I$3:I$1770),"N/A") -> 233 | O12: =IFERROR(_xlfn.RANK.EQ(J12,J$3:J$1770),"N/A") -> 99 | P12: 2.34 | Q12: 23.03 | R12: 0.42 | S12: 10.15 | T12: 34,166,450.00 | U12: =SUM(P12:T12) -> 0 | V12: =_xlfn.RANK.EQ(U12,$U$4:$U$61,1) -> 1 | W12: =IF(Y12="Not suitable","-",V12) -> 1 | Y12: =IF(OR(Z12="Y",AA12="Y"),"Not suitable","") | Z12: =IF(N12="N/A","Y","") | AE12: =C3 -> Fortinet | AF12: 1000000 | AH12: =-'Fin. Data'!C58*SARD!AF12+'Fin. Data'!C39*SARD!AF12 -> 596800000 | AJ12: =AJ9*'Fin. Data'!C23*AF$12/AG$12 -> #NUM! | AK12: =AK9*'Fin. Data'!C64*AF$12/AG$12 -> #NUM! | AL12: =AL9*'Fin. Data'!C5*AF$12/AG$12 -> #NUM! | AM12: =(AM9*'Fin. Data'!C5*$AF12+$AH12)/$AG12 -> #NUM! | AN12: =(AN9*'Fin. Data'!C19*$AF12+$AH12)/$AG12 -> #NUM!
B13: DAST.PA | C13: Dassault Systemes SE | D13: Software | F13: 0.428 | G13: 0.69670246 | H13: 6.3032618e+10 | I13: 5.7 | K13: =IFERROR(_xlfn.RANK.EQ(F13,F$3:F$1770),"N/A") -> 25 | L13: =IFERROR(_xlfn.RANK.EQ(G13,G$3:G$1770),"N/A") -> N/A | M13: =IFERROR(_xlfn.RANK.EQ(H13,H$3:H$1770),"N/A") -> 10 | N13: =IFERROR(_xlfn.RANK.EQ(I13,I$3:I$1770),"N/A") -> 264 | O13: =IFERROR(_xlfn.RANK.EQ(J13,J$3:J$1770),"N/A") -> 708 | P13: 10.63 | Q13: 26.13 | R13: 14.17 | S13: 534.80 | T13: 106,822,117.00 | U13: =SUM(P13:T13) -> 0 | V13: =_xlfn.RANK.EQ(U13,$U$4:$U$61,1) -> 1 | W13: =IF(Y13="Not suitable","-",V13) -> 1 | Y13: =IF(OR(Z13="Y",AA13="Y"),"Not suitable","") | Z13: =IF(N13="N/A","Y","") | AE13: By Consolidated Average | AJ13: =AVERAGE(AJ12:AL12) -> #NUM! | AM13: =AVERAGE(AM12:AN12) -> #NUM!
B14: ROP.OQ | C14: Roper Technologies Inc | D14: Software | F14: 0.224 | G14: 2.7048498 | H14: 5.7128468e+10 | I14: 3.39 | J14: 0.407 | K14: =IFERROR(_xlfn.RANK.EQ(F14,F$3:F$1770),"N/A") -> 84 | L14: =IFERROR(_xlfn.RANK.EQ(G14,G$3:G$1770),"N/A") -> N/A | M14: =IFERROR(_xlfn.RANK.EQ(H14,H$3:H$1770),"N/A") -> 11 | N14: =IFERROR(_xlfn.RANK.EQ(I14,I$3:I$1770),"N/A") -> 284 | O14: =IFERROR(_xlfn.RANK.EQ(J14,J$3:J$1770),"N/A") -> 55 | P14: 2.52 | R14: -0.03 | S14: 0.85 | T14: 2,144,492,465.00 | U14: =SUM(P14:T14) -> 0 | V14: =_xlfn.RANK.EQ(U14,$U$4:$U$61,1) -> 1 | W14: =IF(Y14="Not suitable","-",V14) -> 1 | Y14: =IF(OR(Z14="Y",AA14="Y"),"Not suitable","") | Z14: =IF(N14="N/A","Y","") | AE14: Upside | AJ14: =AJ13/OP!C20-1 -> #NUM! | AM14: =AM13/OP!C20-1 -> #NUM!
B15: CSU.TO | C15: Constellation Software Inc | D15: Software | F15: 0.07 | G15: 4.3697606 | H15: 5.1019146e+10 | I15: 0.44 | J15: 0.259 | K15: =IFERROR(_xlfn.RANK.EQ(F15,F$3:F$1770),"N/A") -> 229 | L15: =IFERROR(_xlfn.RANK.EQ(G15,G$3:G$1770),"N/A") -> N/A | M15: =IFERROR(_xlfn.RANK.EQ(H15,H$3:H$1770),"N/A") -> 12 | N15: =IFERROR(_xlfn.RANK.EQ(I15,I$3:I$1770),"N/A") -> 306 | O15: =IFERROR(_xlfn.RANK.EQ(J15,J$3:J$1770),"N/A") -> 168 | P15: 15.62 | S15: 0.03 | T15: 16,331,032.00 | U15: =SUM(P15:T15) -> 0 | V15: =_xlfn.RANK.EQ(U15,$U$4:$U$61,1) -> 1 | W15: =IF(Y15="Not suitable","-",V15) -> 1 | Y15: =IF(OR(Z15="Y",AA15="Y"),"Not suitable","") | Z15: =IF(N15="N/A","Y","")
B16: TEAM.OQ | C16: Atlassian Corp | D16: Software | G16: 2.0261364 | H16: 4.8476349e+10 | I16: 7.46 | J16: -3,1% | K16: =IFERROR(_xlfn.RANK.EQ(F16,F$3:F$1770),"N/A") -> 316 | L16: =IFERROR(_xlfn.RANK.EQ(G16,G$3:G$1770),"N/A") -> N/A | M16: =IFERROR(_xlfn.RANK.EQ(H16,H$3:H$1770),"N/A") -> 13 | N16: =IFERROR(_xlfn.RANK.EQ(I16,I$3:I$1770),"N/A") -> 248 | O16: =IFERROR(_xlfn.RANK.EQ(J16,J$3:J$1770),"N/A") -> N/A | P16: 14.01 | S16: 0.06 | T16: 121,556,731.00 | U16: =SUM(P16:T16) -> 0 | V16: =_xlfn.RANK.EQ(U16,$U$4:$U$61,1) -> 1 | W16: =IF(Y16="Not suitable","-",V16) -> 1 | Y16: =IF(OR(Z16="Y",AA16="Y"),"Not suitable","") | Z16: =IF(N16="N/A","Y","")
B17: ADSK.OQ | C17: Autodesk Inc | D17: Software | F17: 1.003 | G17: -5,338907642 | H17: 47882806348 | I17: 11.13 | J17: 0.236 | K17: =IFERROR(_xlfn.RANK.EQ(F17,F$3:F$1770),"N/A") -> 9 | L17: =IFERROR(_xlfn.RANK.EQ(G17,G$3:G$1770),"N/A") -> N/A | M17: =IFERROR(_xlfn.RANK.EQ(H17,H$3:H$1770),"N/A") -> 14 | N17: =IFERROR(_xlfn.RANK.EQ(I17,I$3:I$1770),"N/A") -> 219 | O17: =IFERROR(_xlfn.RANK.EQ(J17,J$3:J$1770),"N/A") -> 204 | P17: 2.59 | Q17: 11.60 | R17: 0.20 | S17: 3.06 | T17: 252,577,656.00 | U17: =SUM(P17:T17) -> 0 | V17: =_xlfn.RANK.EQ(U17,$U$4:$U$61,1) -> 1 | W17: =IF(Y17="Not suitable","-",V17) -> 1 | Y17: =IF(OR(Z17="Y",AA17="Y"),"Not suitable","") | Z17: =IF(N17="N/A","Y","")
B18: FTNT.OQ | C18: Fortinet Inc | D18: Software | F18: 1.409 | G18: 2.2102713 | H18: 3.9409121e+10 | I18: 16.62 | J18: 0.255 | K18: =IFERROR(_xlfn.RANK.EQ(F18,F$3:F$1770),"N/A") -> 4 | L18: =IFERROR(_xlfn.RANK.EQ(G18,G$3:G$1770),"N/A") -> N/A | M18: =IFERROR(_xlfn.RANK.EQ(H18,H$3:H$1770),"N/A") -> 15 | N18: =IFERROR(_xlfn.RANK.EQ(I18,I$3:I$1770),"N/A") -> 186 | O18: =IFERROR(_xlfn.RANK.EQ(J18,J$3:J$1770),"N/A") -> 173 | P18: 0.93 | S18: 0.26 | T18: 108,008,562.00 | U18: =SUM(P18:T18) -> 0 | V18: =_xlfn.RANK.EQ(U18,$U$4:$U$61,1) -> 1 | W18: =IF(Y18="Not suitable","-",V18) -> 1 | Y18: =IF(OR(Z18="Y",AA18="Y"),"Not suitable","") | Z18: =IF(N18="N/A","Y","")
B19: DDOG.OQ | C19: Datadog Inc | D19: Software | F19: -6.486 | G19: 1.0263212 | H19: 37783672740 | I19: 31.03 | J19: -2,8% | K19: =IFERROR(_xlfn.RANK.EQ(F19,F$3:F$1770),"N/A") -> 507 | L19: =IFERROR(_xlfn.RANK.EQ(G19,G$3:G$1770),"N/A") -> N/A | M19: =IFERROR(_xlfn.RANK.EQ(H19,H$3:H$1770),"N/A") -> 17 | N19: =IFERROR(_xlfn.RANK.EQ(I19,I$3:I$1770),"N/A") -> 141 | O19: =IFERROR(_xlfn.RANK.EQ(J19,J$3:J$1770),"N/A") -> N/A | P19: 1.19 | Q19: 232.61 | S19: 1.76 | T19: 6,574,863.00 | U19: =SUM(P19:T19) -> 0 | V19: =_xlfn.RANK.EQ(U19,$U$4:$U$61,1) -> 1 | W19: =IF(Y19="Not suitable","-",V19) -> 1 | Y19: =IF(OR(Z19="Y",AA19="Y"),"Not suitable","") | Z19: =IF(N19="N/A","Y","")
B20: PLTR.N | C20: Palantir Technologies Inc | D20: Software | F20: 0.276 | G20: -12,58790357 | H20: 3.7453231e+10 | I20: 11.11 | J20: 0.031 | K20: =IFERROR(_xlfn.RANK.EQ(F20,F$3:F$1770),"N/A") -> 60 | L20: =IFERROR(_xlfn.RANK.EQ(G20,G$3:G$1770),"N/A") -> N/A | M20: =IFERROR(_xlfn.RANK.EQ(H20,H$3:H$1770),"N/A") -> 18 | N20: =IFERROR(_xlfn.RANK.EQ(I20,I$3:I$1770),"N/A") -> 220 | O20: =IFERROR(_xlfn.RANK.EQ(J20,J$3:J$1770),"N/A") -> 651 | P20: 1.47 | Q20: 6.21 | R20: 0.13 | S20: 1.62 | T20: 14,535,195.00 | U20: =SUM(P20:T20) -> 0 | V20: =_xlfn.RANK.EQ(U20,$U$4:$U$61,1) -> 1 | W20: =IF(Y20="Not suitable","-",V20) -> 1 | Y20: =IF(OR(Z20="Y",AA20="Y"),"Not suitable","") | Z20: =IF(N20="N/A","Y","")
B21: EA.OQ | C21: Electronic Arts Inc | D21: Software | F21: 0.038 | G21: 0 | H21: 3.6458402e+10 | I21: 3.9 | J21: 0.262 | K21: =IFERROR(_xlfn.RANK.EQ(F21,F$3:F$1770),"N/A") -> 270 | L21: =IFERROR(_xlfn.RANK.EQ(G21,G$3:G$1770),"N/A") -> N/A | M21: =IFERROR(_xlfn.RANK.EQ(H21,H$3:H$1770),"N/A") -> 19 | N21: =IFERROR(_xlfn.RANK.EQ(I21,I$3:I$1770),"N/A") -> 279 | O21: =IFERROR(_xlfn.RANK.EQ(J21,J$3:J$1770),"N/A") -> 162 | P21: 2.31 | Q21: 12.77 | R21: 0.03 | S21: 1.05 | T21: 83,207,397.00 | U21: =SUM(P21:T21) -> 0 | V21: =_xlfn.RANK.EQ(U21,$U$4:$U$61,1) -> 1 | W21: =IF(Y21="Not suitable","-",V21) -> 1 | Y21: =IF(OR(Z21="Y",AA21="Y"),"Not suitable","") | Z21: =IF(N21="N/A","Y","")
B22: TTD.OQ | C22: Trade Desk Inc | D22: Software | F22: 0.241 | G22: 1.2677006 | H22: 3.3722629e+10 | I22: 9.2 | J22: 0.12 | K22: =IFERROR(_xlfn.RANK.EQ(F22,F$3:F$1770),"N/A") -> 72 | L22: =IFERROR(_xlfn.RANK.EQ(G22,G$3:G$1770),"N/A") -> N/A | M22: =IFERROR(_xlfn.RANK.EQ(H22,H$3:H$1770),"N/A") -> 20 | N22: =IFERROR(_xlfn.RANK.EQ(I22,I$3:I$1770),"N/A") -> 235 | O22: =IFERROR(_xlfn.RANK.EQ(J22,J$3:J$1770),"N/A") -> 424 | P22: 9.02 | Q22: 38.02 | R22: 6.60 | S22: 223.84 | T22: 213,915,325.00 | U22: =SUM(P22:T22) -> 0 | V22: =_xlfn.RANK.EQ(U22,$U$4:$U$61,1) -> 1 | W22: =IF(Y22="Not suitable","-",V22) -> 1 | Y22: =IF(OR(Z22="Y",AA22="Y"),"Not suitable","") | Z22: =IF(N22="N/A","Y","")
B23: ZS.OQ | C23: Zscaler Inc | D23: Software | F23: 0.287 | G23: 0 | H23: 2.9672106e+10 | I23: 32.92 | J23: -7,9% | K23: =IFERROR(_xlfn.RANK.EQ(F23,F$3:F$1770),"N/A") -> 58 | L23: =IFERROR(_xlfn.RANK.EQ(G23,G$3:G$1770),"N/A") -> N/A | M23: =IFERROR(_xlfn.RANK.EQ(H23,H$3:H$1770),"N/A") -> 21 | N23: =IFERROR(_xlfn.RANK.EQ(I23,I$3:I$1770),"N/A") -> 134 | O23: =IFERROR(_xlfn.RANK.EQ(J23,J$3:J$1770),"N/A") -> N/A | P23: 0.18 | Q23: 0.20 | S23: 0.30 | T23: 14,920,585.00 | U23: =SUM(P23:T23) -> 0 | V23: =_xlfn.RANK.EQ(U23,$U$4:$U$61,1) -> 1 | W23: =IF(Y23="Not suitable","-",V23) -> 1 | Y23: =IF(OR(Z23="Y",AA23="Y"),"Not suitable","") | Z23: =IF(N23="N/A","Y","")
B24: MDB.OQ | C24: MongoDB Inc | D24: Software | F24: 0.429 | G24: -4,995788973 | H24: 2.7649709e+10 | J24: -14,0% | K24: =IFERROR(_xlfn.RANK.EQ(F24,F$3:F$1770),"N/A") -> 23 | L24: =IFERROR(_xlfn.RANK.EQ(G24,G$3:G$1770),"N/A") -> N/A | M24: =IFERROR(_xlfn.RANK.EQ(H24,H$3:H$1770),"N/A") -> 22 | N24: =IFERROR(_xlfn.RANK.EQ(I24,I$3:I$1770),"N/A") -> N/A | O24: =IFERROR(_xlfn.RANK.EQ(J24,J$3:J$1770),"N/A") -> N/A | S24: 0.00 | T24: 3,302,597.00 | U24: =SUM(P24:T24) -> 0 | V24: =_xlfn.RANK.EQ(U24,$U$4:$U$61,1) -> 1 | W24: =IF(Y24="Not suitable","-",V24) -> - | Y24: =IF(OR(Z24="Y",AA24="Y"),"Not suitable","") -> Not suitable | Z24: =IF(N24="N/A","Y","") -> Y
B25: FICO.N | C25: Fair Isaac Corp | D25: Software | F25: 0.092 | G25: -3,430076012 | H25: 2.763124e+10 | I25: 10.62 | J25: 0.432 | K25: =IFERROR(_xlfn.RANK.EQ(F25,F$3:F$1770),"N/A") -> 203 | L25: =IFERROR(_xlfn.RANK.EQ(G25,G$3:G$1770),"N/A") -> N/A | M25: =IFERROR(_xlfn.RANK.EQ(H25,H$3:H$1770),"N/A") -> 23 | N25: =IFERROR(_xlfn.RANK.EQ(I25,I$3:I$1770),"N/A") -> 222 | O25: =IFERROR(_xlfn.RANK.EQ(J25,J$3:J$1770),"N/A") -> 45 | P25: 1.01 | Q25: 14.27 | S25: 1.42 | T25: 44,732,379.00 | U25: =SUM(P25:T25) -> 0 | V25: =_xlfn.RANK.EQ(U25,$U$4:$U$61,1) -> 1 | W25: =IF(Y25="Not suitable","-",V25) -> 1 | Y25: =IF(OR(Z25="Y",AA25="Y"),"Not suitable","") | Z25: =IF(N25="N/A","Y","")
B26: TTWO.OQ | C26: Take-Two Interactive Software Inc | D26: Software | F26: -0.671 | G26: 2.9048057 | H26: 2.6226128e+10 | I26: -15,03 | J26: 0.132 | K26: =IFERROR(_xlfn.RANK.EQ(F26,F$3:F$1770),"N/A") -> 485 | L26: =IFERROR(_xlfn.RANK.EQ(G26,G$3:G$1770),"N/A") -> N/A | M26: =IFERROR(_xlfn.RANK.EQ(H26,H$3:H$1770),"N/A") -> 24 | N26: =IFERROR(_xlfn.RANK.EQ(I26,I$3:I$1770),"N/A") -> N/A | O26: =IFERROR(_xlfn.RANK.EQ(J26,J$3:J$1770),"N/A") -> 391 | P26: 1.92 | Q26: 10.41 | R26: 0.09 | S26: 1.47 | T26: 83,874,458.00 | U26: =SUM(P26:T26) -> 0 | V26: =_xlfn.RANK.EQ(U26,$U$4:$U$61,1) -> 1 | W26: =IF(Y26="Not suitable","-",V26) -> - | Y26: =IF(OR(Z26="Y",AA26="Y"),"Not suitable","") -> Not suitable | Z26: =IF(N26="N/A","Y","") -> Y
B27: SPLK.OQ | C27: Splunk Inc | D27: Software | F27: 0.352 | G27: -3,342522249 | H27: 25445185000 | J27: 0.019 | K27: =IFERROR(_xlfn.RANK.EQ(F27,F$3:F$1770),"N/A") -> 39 | L27: =IFERROR(_xlfn.RANK.EQ(G27,G$3:G$1770),"N/A") -> N/A | M27: =IFERROR(_xlfn.RANK.EQ(H27,H$3:H$1770),"N/A") -> 25 | N27: =IFERROR(_xlfn.RANK.EQ(I27,I$3:I$1770),"N/A") -> N/A | O27: =IFERROR(_xlfn.RANK.EQ(J27,J$3:J$1770),"N/A") -> 668 | P27: 1.85 | Q27: 15.54 | R27: 0.12 | S27: 3.35 | T27: 57,337,611.00 | U27: =SUM(P27:T27) -> 0 | V27: =_xlfn.RANK.EQ(U27,$U$4:$U$61,1) -> 1 | W27: =IF(Y27="Not suitable","-",V27) -> - | Y27: =IF(OR(Z27="Y",AA27="Y"),"Not suitable","") -> Not suitable | Z27: =IF(N27="N/A","Y","") -> Y
B28: RBLX.N | C28: Roblox Corp | D28: Software | F28: 8.901 | G28: -16,45369969 | H28: 2.4862157e+10 | I28: 38.38 | J28: -38,4% | K28: =IFERROR(_xlfn.RANK.EQ(F28,F$3:F$1770),"N/A") -> 1 | L28: =IFERROR(_xlfn.RANK.EQ(G28,G$3:G$1770),"N/A") -> N/A | M28: =IFERROR(_xlfn.RANK.EQ(H28,H$3:H$1770),"N/A") -> 26 | N28: =IFERROR(_xlfn.RANK.EQ(I28,I$3:I$1770),"N/A") -> 113 | O28: =IFERROR(_xlfn.RANK.EQ(J28,J$3:J$1770),"N/A") -> N/A | P28: 1.15 | Q28: 8.84 | S28: 2.24 | T28: 21,187,619.00 | U28: =SUM(P28:T28) -> 0 | V28: =_xlfn.RANK.EQ(U28,$U$4:$U$61,1) -> 1 | W28: =IF(Y28="Not suitable","-",V28) -> 1 | Y28: =IF(OR(Z28="Y",AA28="Y"),"Not suitable","") | Z28: =IF(N28="N/A","Y","")
B29: ANSS.OQ | C29: ANSYS Inc | D29: Software | F29: -2.075 | G29: -1,07057927 | H29: 2.4855178e+10 | I29: 3.39 | J29: 0.308 | K29: =IFERROR(_xlfn.RANK.EQ(F29,F$3:F$1770),"N/A") -> 499 | L29: 0.46 | M29: =IFERROR(_xlfn.RANK.EQ(H29,H$3:H$1770),"N/A") -> 27 | N29: =IFERROR(_xlfn.RANK.EQ(I29,I$3:I$1770),"N/A") -> 284 | O29: =IFERROR(_xlfn.RANK.EQ(J29,J$3:J$1770),"N/A") -> 118 | P29: 5.77 | Q29: 24.22 | R29: 0.39 | S29: 14.79 | T29: 1,024,369,074.00 | U29: =SUM(P29:T29) -> 0 | V29: =_xlfn.RANK.EQ(U29,$U$4:$U$61,1) -> 1 | W29: =IF(Y29="Not suitable","-",V29) -> 1 | Y29: =IF(OR(Z29="Y",AA29="Y"),"Not suitable","") | Z29: =IF(N29="N/A","Y","")
B30: HUBS.N | C30: HubSpot Inc | D30: Software | F30: 0.149 | G30: 1.2497226 | H30: 2.476464e+10 | I30: 25.84 | J30: -1,6% | K30: =IFERROR(_xlfn.RANK.EQ(F30,F$3:F$1770),"N/A") -> 142 | M30: =IFERROR(_xlfn.RANK.EQ(H30,H$3:H$1770),"N/A") -> 28 | N30: =IFERROR(_xlfn.RANK.EQ(I30,I$3:I$1770),"N/A") -> 156 | O30: =IFERROR(_xlfn.RANK.EQ(J30,J$3:J$1770),"N/A") -> N/A | P30: 1.19 | Q30: 4.36 | S30: 0.08 | T30: 124,603,134.00 | U30: =SUM(P30:T30) -> 0 | V30: =_xlfn.RANK.EQ(U30,$U$4:$U$61,1) -> 1 | W30: =IF(Y30="Not suitable","-",V30) -> 1 | Y30: =IF(OR(Z30="Y",AA30="Y"),"Not suitable","") | Z30: =IF(N30="N/A","Y","")
B31: SNAP.N | C31: Snap Inc | D31: Software | F31: 0.152 | G31: -4,163362389 | H31: 2.4300797e+10 | I31: 7.58 | J31: -27,6% | K31: =IFERROR(_xlfn.RANK.EQ(F31,F$3:F$1770),"N/A") -> 139 | M31: =IFERROR(_xlfn.RANK.EQ(H31,H$3:H$1770),"N/A") -> 29 | N31: =IFERROR(_xlfn.RANK.EQ(I31,I$3:I$1770),"N/A") -> 247 | O31: =IFERROR(_xlfn.RANK.EQ(J31,J$3:J$1770),"N/A") -> N/A | S31: 0.04 | T31: 10,004,131.00 | U31: =SUM(P31:T31) -> 0 | V31: =_xlfn.RANK.EQ(U31,$U$4:$U$61,1) -> 1 | W31: =IF(Y31="Not suitable","-",V31) -> 1 | Y31: =IF(OR(Z31="Y",AA31="Y"),"Not suitable","") | Z31: =IF(N31="N/A","Y","")
B32: SE.N | C32: Sea Ltd | D32: Software | F32: 0.087 | G32: -3,102332063 | H32: 2.390367e+10 | I32: -18,65 | J32: 0.106 | K32: =IFERROR(_xlfn.RANK.EQ(F32,F$3:F$1770),"N/A") -> 207 | L32: 0.94 | M32: =IFERROR(_xlfn.RANK.EQ(H32,H$3:H$1770),"N/A") -> 30 | N32: =IFERROR(_xlfn.RANK.EQ(I32,I$3:I$1770),"N/A") -> N/A | O32: =IFERROR(_xlfn.RANK.EQ(J32,J$3:J$1770),"N/A") -> 468 | P32: 0.89 | Q32: 6.34 | R32: 1.02 | S32: 9.62 | T32: 49,093,055.00 | U32: =SUM(P32:T32) -> 0 | V32: =_xlfn.RANK.EQ(U32,$U$4:$U$61,1) -> 1 | W32: =IF(Y32="Not suitable","-",V32) -> - | Y32: =IF(OR(Z32="Y",AA32="Y"),"Not suitable","") -> Not suitable | Z32: =IF(N32="N/A","Y","") -> Y
B33: ZM.OQ | C33: Zoom Video Communications Inc | D33: Software | F33: -0.344 | G33: -4,229138283 | H33: 2.1897182e+10 | I33: 2.03 | J33: 0.088 | K33: =IFERROR(_xlfn.RANK.EQ(F33,F$3:F$1770),"N/A") -> 455 | L33: 5.11 | M33: =IFERROR(_xlfn.RANK.EQ(H33,H$3:H$1770),"N/A") -> 31 | N33: =IFERROR(_xlfn.RANK.EQ(I33,I$3:I$1770),"N/A") -> 294 | O33: =IFERROR(_xlfn.RANK.EQ(J33,J$3:J$1770),"N/A") -> 524 | P33: 17.92 | Q33: 54.99 | R33: 4.23 | S33: 259.47 | T33: 272,062,000.00 | U33: =SUM(P33:T33) -> 0 | V33: =_xlfn.RANK.EQ(U33,$U$4:$U$61,1) -> 1 | W33: =IF(Y33="Not suitable","-",V33) -> 1 | Y33: =IF(OR(Z33="Y",AA33="Y"),"Not suitable","") | Z33: =IF(N33="N/A","Y","")
B34: 688111.SS | C34: Beijing Kingsoft Office Software Inc | D34: Software | F34: 0.222 | G34: 0 | H34: 2.0106474e+10 | I34: 1.54 | J34: 0.214 | K34: =IFERROR(_xlfn.RANK.EQ(F34,F$3:F$1770),"N/A") -> 85 | L34: 11.28 | M34: =IFERROR(_xlfn.RANK.EQ(H34,H$3:H$1770),"N/A") -> 32 | N34: =IFERROR(_xlfn.RANK.EQ(I34,I$3:I$1770),"N/A") -> 300 | O34: =IFERROR(_xlfn.RANK.EQ(J34,J$3:J$1770),"N/A") -> 231 | P34: 12.38 | Q34: 24.56 | R34: 9.69 | S34: 370.95 | T34: 7,432,262,329.00 | U34: =SUM(P34:T34) -> 0 | V34: =_xlfn.RANK.EQ(U34,$U$4:$U$61,1) -> 1 | W34: =IF(Y34="Not suitable","-",V34) -> 1 | Y34: =IF(OR(Z34="Y",AA34="Y"),"Not suitable","") | Z34: =IF(N34="N/A","Y","")
B35: PTC.OQ | C35: PTC Inc | D35: Software | F35: 0.136 | G35: 0.15017724 | H35: 1.9465514e+10 | I35: 5.78 | J35: 0.277 | K35: =IFERROR(_xlfn.RANK.EQ(F35,F$3:F$1770),"N/A") -> 155 | L35: 0.94 | M35: =IFERROR(_xlfn.RANK.EQ(H35,H$3:H$1770),"N/A") -> 33 | N35: =IFERROR(_xlfn.RANK.EQ(I35,I$3:I$1770),"N/A") -> 263 | O35: =IFERROR(_xlfn.RANK.EQ(J35,J$3:J$1770),"N/A") -> 151 | P35: 2.86 | Q35: 10.91 | R35: 0.89 | S35: 10.68 | T35: 45,589,575.00 | U35: =SUM(P35:T35) -> 0 | V35: =_xlfn.RANK.EQ(U35,$U$4:$U$61,1) -> 1 | W35: =IF(Y35="Not suitable","-",V35) -> 1 | Y35: =IF(OR(Z35="Y",AA35="Y"),"Not suitable","") | Z35: =IF(N35="N/A","Y","")
B36: DIDIY.PK | C36: DiDi Global Inc | D36: Software | F36: 0.208 | G36: 3.5572377 | H36: 1.8611964e+10 | J36: -21,8% | K36: =IFERROR(_xlfn.RANK.EQ(F36,F$3:F$1770),"N/A") -> 92 | L36: 8.68 | M36: =IFERROR(_xlfn.RANK.EQ(H36,H$3:H$1770),"N/A") -> 34 | N36: =IFERROR(_xlfn.RANK.EQ(I36,I$3:I$1770),"N/A") -> N/A | O36: =IFERROR(_xlfn.RANK.EQ(J36,J$3:J$1770),"N/A") -> N/A | P36: 5.00 | Q36: 20.08 | R36: 7.51 | S36: 199.32 | T36: 63,330,441.00 | U36: =SUM(P36:T36) -> 0 | V36: =_xlfn.RANK.EQ(U36,$U$4:$U$61,1) -> 1 | W36: =IF(Y36="Not suitable","-",V36) -> - | Y36: =IF(OR(Z36="Y",AA36="Y"),"Not suitable","") -> Not suitable | Z36: =IF(N36="N/A","Y","") -> Y
B37: IOT.N | C37: Samsara Inc | D37: Software | G37: -0,288371877 | H37: 1.8220805e+10 | I37: 46.44 | J37: -28,8% | K37: =IFERROR(_xlfn.RANK.EQ(F37,F$3:F$1770),"N/A") -> 316 | M37: =IFERROR(_xlfn.RANK.EQ(H37,H$3:H$1770),"N/A") -> 35 | N37: =IFERROR(_xlfn.RANK.EQ(I37,I$3:I$1770),"N/A") -> 90 | O37: =IFERROR(_xlfn.RANK.EQ(J37,J$3:J$1770),"N/A") -> N/A | P37: 0.88 | S37: 0.01 | T37: 428,707,430.00 | U37: =SUM(P37:T37) -> 0 | V37: =_xlfn.RANK.EQ(U37,$U$4:$U$61,1) -> 1 | W37: =IF(Y37="Not suitable","-",V37) -> 1 | Y37: =IF(OR(Z37="Y",AA37="Y"),"Not suitable","") | Z37: =IF(N37="N/A","Y","")
B38: TYL.N | C38: Tyler Technologies Inc | D38: Software | F38: -0.067 | G38: 0 | H38: 1.693982e+10 | I38: 5.28 | J38: 0.182 | K38: =IFERROR(_xlfn.RANK.EQ(F38,F$3:F$1770),"N/A") -> 360 | L38: 2.75 | M38: =IFERROR(_xlfn.RANK.EQ(H38,H$3:H$1770),"N/A") -> 36 | N38: =IFERROR(_xlfn.RANK.EQ(I38,I$3:I$1770),"N/A") -> 268 | O38: =IFERROR(_xlfn.RANK.EQ(J38,J$3:J$1770),"N/A") -> 285 | P38: 2.76 | Q38: 11.55 | R38: 1.92 | S38: 51.27 | T38: 143,500,000.00 | U38: =SUM(P38:T38) -> 0 | V38: =_xlfn.RANK.EQ(U38,$U$4:$U$61,1) -> 1 | W38: =IF(Y38="Not suitable","-",V38) -> 1 | Y38: =IF(OR(Z38="Y",AA38="Y"),"Not suitable","") | Z38: =IF(N38="N/A","Y","")
B39: CHKP.OQ | C39: Check Point Software Technologies Ltd | D39: Software | F39: 0.129 | G39: 4.507617 | H39: 1.6911446e+10 | I39: 3.26 | J39: 0.395 | K39: =IFERROR(_xlfn.RANK.EQ(F39,F$3:F$1770),"N/A") -> 166 | L39: 0.26 | M39: =IFERROR(_xlfn.RANK.EQ(H39,H$3:H$1770),"N/A") -> 37 | N39: =IFERROR(_xlfn.RANK.EQ(I39,I$3:I$1770),"N/A") -> 287 | O39: =IFERROR(_xlfn.RANK.EQ(J39,J$3:J$1770),"N/A") -> 59 | P39: 0.99 | Q39: 5.52 | R39: 2.35 | S39: 4.65 | T39: 30,901,440.00 | U39: =SUM(P39:T39) -> 0 | V39: =_xlfn.RANK.EQ(U39,$U$4:$U$61,1) -> 1 | W39: =IF(Y39="Not suitable","-",V39) -> 1 | Y39: =IF(OR(Z39="Y",AA39="Y"),"Not suitable","") | Z39: =IF(N39="N/A","Y","")
B40: 002230.SZ | C40: iFLYTEK Co Ltd | D40: Software | F40: 0.302 | G40: 0 | H40: 1.5228665e+10 | I40: 19.09 | J40: -2,5% | K40: =IFERROR(_xlfn.RANK.EQ(F40,F$3:F$1770),"N/A") -> 49 | L40: 5.57 | M40: =IFERROR(_xlfn.RANK.EQ(H40,H$3:H$1770),"N/A") -> 38 | N40: =IFERROR(_xlfn.RANK.EQ(I40,I$3:I$1770),"N/A") -> 179 | O40: =IFERROR(_xlfn.RANK.EQ(J40,J$3:J$1770),"N/A") -> N/A | P40: 7.58 | Q40: 18.83 | R40: 5.04 | S40: 112.87 | T40: 2,739,376,061.00 | U40: =SUM(P40:T40) -> 0 | V40: =_xlfn.RANK.EQ(U40,$U$4:$U$61,1) -> 1 | W40: =IF(Y40="Not suitable","-",V40) -> 1 | Y40: =IF(OR(Z40="Y",AA40="Y"),"Not suitable","") | Z40: =IF(N40="N/A","Y","")
B41: WTC.AX | C41: WiseTech Global Ltd | D41: Software | F41: 0.034 | G41: 12.010567 | H41: 1.5044428e+10 | J41: 0.513 | K41: =IFERROR(_xlfn.RANK.EQ(F41,F$3:F$1770),"N/A") -> 275 | M41: =IFERROR(_xlfn.RANK.EQ(H41,H$3:H$1770),"N/A") -> 39 | N41: =IFERROR(_xlfn.RANK.EQ(I41,I$3:I$1770),"N/A") -> N/A | O41: =IFERROR(_xlfn.RANK.EQ(J41,J$3:J$1770),"N/A") -> 19 | S41: 0.00 | T41: 29,273,376.00 | U41: =SUM(P41:T41) -> 0 | V41: =_xlfn.RANK.EQ(U41,$U$4:$U$61,1) -> 1 | W41: =IF(Y41="Not suitable","-",V41) -> - | Y41: =IF(OR(Z41="Y",AA41="Y"),"Not suitable","") -> Not suitable | Z41: =IF(N41="N/A","Y","") -> Y
B42: BSY.OQ | C42: Bentley Systems Inc | D42: Software | F42: 0.154 | G42: 0.85097909 | H42: 1.4985499e+10 | I42: 18.37 | J42: 0.266 | K42: =IFERROR(_xlfn.RANK.EQ(F42,F$3:F$1770),"N/A") -> 137 | L42: 4.89 | M42: =IFERROR(_xlfn.RANK.EQ(H42,H$3:H$1770),"N/A") -> 40 | N42: =IFERROR(_xlfn.RANK.EQ(I42,I$3:I$1770),"N/A") -> 181 | O42: =IFERROR(_xlfn.RANK.EQ(J42,J$3:J$1770),"N/A") -> 159 | P42: 9.95 | Q42: 35.90 | R42: 4.27 | S42: 163.24 | T42: 119,244,754.00 | U42: =SUM(P42:T42) -> 0 | V42: =_xlfn.RANK.EQ(U42,$U$4:$U$61,1) -> 1 | W42: =IF(Y42="Not suitable","-",V42) -> 1 | Y42: =IF(OR(Z42="Y",AA42="Y"),"Not suitable","") | Z42: =IF(N42="N/A","Y","")
B43: SGE.L | C43: Sage Group PLC | D43: Software | F43: 0.588 | G43: 7.5415193 | H43: 1.4895834e+10 | I43: 2.3 | J43: 0.238 | K43: =IFERROR(_xlfn.RANK.EQ(F43,F$3:F$1770),"N/A") -> 14 | M43: =IFERROR(_xlfn.RANK.EQ(H43,H$3:H$1770),"N/A") -> 41 | N43: =IFERROR(_xlfn.RANK.EQ(I43,I$3:I$1770),"N/A") -> 290 | O43: =IFERROR(_xlfn.RANK.EQ(J43,J$3:J$1770),"N/A") -> 201 | P43: -3.52 | S43: 0.01 | T43: 1,150,623,769.00 | U43: =SUM(P43:T43) -> 0 | V43: =_xlfn.RANK.EQ(U43,$U$4:$U$61,1) -> 1 | W43: =IF(Y43="Not suitable","-",V43) -> 1 | Y43: =IF(OR(Z43="Y",AA43="Y"),"Not suitable","") | Z43: =IF(N43="N/A","Y","")
B44: GEN.OQ | C44: Gen Digital Inc | D44: Software | F44: 0.235 | G44: 3.0509709 | H44: 1.4268729e+10 | I44: 5.07 | J44: 0.452 | K44: =IFERROR(_xlfn.RANK.EQ(F44,F$3:F$1770),"N/A") -> 76 | M44: =IFERROR(_xlfn.RANK.EQ(H44,H$3:H$1770),"N/A") -> 42 | N44: =IFERROR(_xlfn.RANK.EQ(I44,I$3:I$1770),"N/A") -> 269 | O44: =IFERROR(_xlfn.RANK.EQ(J44,J$3:J$1770),"N/A") -> 38 | P44: 0.57 | Q44: 43.36 | S44: 0.68 | T44: 83,875,016.00 | U44: =SUM(P44:T44) -> 0 | V44: =_xlfn.RANK.EQ(U44,$U$4:$U$61,1) -> 1 | W44: =IF(Y44="Not suitable","-",V44) -> 1 | Y44: =IF(OR(Z44="Y",AA44="Y"),"Not suitable","") | Z44: =IF(N44="N/A","Y","")
B45: PATH.N | C45: UiPath Inc | D45: Software | F45: 1.064 | G45: 7.5324074 | H45: 1.3251892e+10 | I45: 97.3 | J45: -15,8% | K45: =IFERROR(_xlfn.RANK.EQ(F45,F$3:F$1770),"N/A") -> 7 | M45: =IFERROR(_xlfn.RANK.EQ(H45,H$3:H$1770),"N/A") -> 43 | N45: =IFERROR(_xlfn.RANK.EQ(I45,I$3:I$1770),"N/A") -> 36 | O45: =IFERROR(_xlfn.RANK.EQ(J45,J$3:J$1770),"N/A") -> N/A | P45: 1.34 | Q45: 3.65 | S45: 0.01 | T45: 920,766,869.00 | U45: =SUM(P45:T45) -> 0 | V45: =_xlfn.RANK.EQ(U45,$U$4:$U$61,1) -> 1 | W45: =IF(Y45="Not suitable","-",V45) -> 1 | Y45: =IF(OR(Z45="Y",AA45="Y"),"Not suitable","") | Z45: =IF(N45="N/A","Y","")
B46: NICE.TA | C46: Nice Ltd | D46: Software | F46: 0.042 | G46: 0 | H46: 1.260893e+10 | I46: 6.98 | J46: 0.249 | K46: =IFERROR(_xlfn.RANK.EQ(F46,F$3:F$1770),"N/A") -> 263 | L46: 0.99 | M46: =IFERROR(_xlfn.RANK.EQ(H46,H$3:H$1770),"N/A") -> 44 | N46: =IFERROR(_xlfn.RANK.EQ(I46,I$3:I$1770),"N/A") -> 252 | O46: =IFERROR(_xlfn.RANK.EQ(J46,J$3:J$1770),"N/A") -> 180 | P46: 9.51 | Q46: 118.15 | R46: 0.93 | S46: 84.33 | T46: 25,373,280.00 | U46: =SUM(P46:T46) -> 0 | V46: =_xlfn.RANK.EQ(U46,$U$4:$U$61,1) -> 1 | W46: =IF(Y46="Not suitable","-",V46) -> 1 | Y46: =IF(OR(Z46="Y",AA46="Y"),"Not suitable","") | Z46: =IF(N46="N/A","Y","")
B47: TWLO.N | C47: Twilio Inc | D47: Software | F47: 0.152 | G47: 1.9827934 | H47: 1.2452128e+10 | J47: -5,4% | K47: =IFERROR(_xlfn.RANK.EQ(F47,F$3:F$1770),"N/A") -> 139 | M47: =IFERROR(_xlfn.RANK.EQ(H47,H$3:H$1770),"N/A") -> 45 | N47: =IFERROR(_xlfn.RANK.EQ(I47,I$3:I$1770),"N/A") -> N/A | O47: =IFERROR(_xlfn.RANK.EQ(J47,J$3:J$1770),"N/A") -> N/A | P47: 1.07 | Q47: 9.00 | S47: 1.77 | T47: 49,262,803.00 | U47: =SUM(P47:T47) -> 0 | V47: =_xlfn.RANK.EQ(U47,$U$4:$U$61,1) -> 1 | W47: =IF(Y47="Not suitable","-",V47) -> - | Y47: =IF(OR(Z47="Y",AA47="Y"),"Not suitable","") -> Not suitable | Z47: =IF(N47="N/A","Y","") -> Y
B48: AZPN.OQ | C48: Aspen Technology Inc | D48: Software | F48: -0.01 | G48: -1,001722635 | H48: 1.2450676e+10 | I48: -2,87 | J48: 0.286 | K48: =IFERROR(_xlfn.RANK.EQ(F48,F$3:F$1770),"N/A") -> 323 | L48: 4.23 | M48: =IFERROR(_xlfn.RANK.EQ(H48,H$3:H$1770),"N/A") -> 46 | N48: =IFERROR(_xlfn.RANK.EQ(I48,I$3:I$1770),"N/A") -> N/A | O48: =IFERROR(_xlfn.RANK.EQ(J48,J$3:J$1770),"N/A") -> 141 | P48: 4.34 | Q48: 12.73 | R48: 4.10 | S48: 53.09 | T48: 43,565,346.00 | U48: =SUM(P48:T48) -> 0 | V48: =_xlfn.RANK.EQ(U48,$U$4:$U$61,1) -> 1 | W48: =IF(Y48="Not suitable","-",V48) -> - | Y48: =IF(OR(Z48="Y",AA48="Y"),"Not suitable","") -> Not suitable | Z48: =IF(N48="N/A","Y","") -> Y
B49: APP.OQ | C49: Applovin Corp | D49: Software | F49: 0.028 | G49: 0 | H49: 1.237093e+10 | I49: 8.29 | J49: 0.356 | K49: =IFERROR(_xlfn.RANK.EQ(F49,F$3:F$1770),"N/A") -> 288 | M49: =IFERROR(_xlfn.RANK.EQ(H49,H$3:H$1770),"N/A") -> 47 | N49: =IFERROR(_xlfn.RANK.EQ(I49,I$3:I$1770),"N/A") -> 242 | O49: =IFERROR(_xlfn.RANK.EQ(J49,J$3:J$1770),"N/A") -> 77 | S49: 0.03 | T49: 317,009,000.00 | U49: =SUM(P49:T49) -> 0 | V49: =_xlfn.RANK.EQ(U49,$U$4:$U$61,1) -> 1 | W49: =IF(Y49="Not suitable","-",V49) -> 1 | Y49: =IF(OR(Z49="Y",AA49="Y"),"Not suitable","") | Z49: =IF(N49="N/A","Y","")
B50: 600845.SS | C50: Shanghai Baosight Software Co Ltd | D50: Software | F50: -0.095 | G50: 7.2709371 | H50: 1.2369978e+10 | I50: 45.95 | J50: 0.201 | K50: =IFERROR(_xlfn.RANK.EQ(F50,F$3:F$1770),"N/A") -> 377 | M50: =IFERROR(_xlfn.RANK.EQ(H50,H$3:H$1770),"N/A") -> 48 | N50: =IFERROR(_xlfn.RANK.EQ(I50,I$3:I$1770),"N/A") -> 93 | O50: =IFERROR(_xlfn.RANK.EQ(J50,J$3:J$1770),"N/A") -> 253 | P50: 0.34 | S50: 1.59 | T50: 20,990,819.00 | U50: =SUM(P50:T50) -> 0 | V50: =_xlfn.RANK.EQ(U50,$U$4:$U$61,1) -> 1 | W50: =IF(Y50="Not suitable","-",V50) -> 1 | Y50: =IF(OR(Z50="Y",AA50="Y"),"Not suitable","") | Z50: =IF(N50="N/A","Y","")
B51: GRAB.OQ | C51: Grab Holdings Ltd | D51: Software | F51: 0.231 | G51: 0.38450835 | H51: 12141440000 | I51: 86.04 | J51: -20,3% | K51: =IFERROR(_xlfn.RANK.EQ(F51,F$3:F$1770),"N/A") -> 78 | M51: =IFERROR(_xlfn.RANK.EQ(H51,H$3:H$1770),"N/A") -> 49 | N51: =IFERROR(_xlfn.RANK.EQ(I51,I$3:I$1770),"N/A") -> 44 | O51: =IFERROR(_xlfn.RANK.EQ(J51,J$3:J$1770),"N/A") -> N/A | P51: 1.26 | Q51: 3.58 | S51: 0.37 | T51: 113,294,832.00 | U51: =SUM(P51:T51) -> 0 | V51: =_xlfn.RANK.EQ(U51,$U$4:$U$61,1) -> 1 | W51: =IF(Y51="Not suitable","-",V51) -> 1 | Y51: =IF(OR(Z51="Y",AA51="Y"),"Not suitable","") | Z51: =IF(N51="N/A","Y","")
B52: U.N | C52: Unity Software Inc | D52: Software | F52: -0.23 | G52: -1,061430793 | H52: 1.2122607e+10 | J52: -18,5% | K52: =IFERROR(_xlfn.RANK.EQ(F52,F$3:F$1770),"N/A") -> 426 | M52: =IFERROR(_xlfn.RANK.EQ(H52,H$3:H$1770),"N/A") -> 50 | N52: =IFERROR(_xlfn.RANK.EQ(I52,I$3:I$1770),"N/A") -> N/A | O52: =IFERROR(_xlfn.RANK.EQ(J52,J$3:J$1770),"N/A") -> N/A | S52: 0.00 | T52: 22,212,217.00 | U52: =SUM(P52:T52) -> 0 | V52: =_xlfn.RANK.EQ(U52,$U$4:$U$61,1) -> 1 | W52: =IF(Y52="Not suitable","-",V52) -> - | Y52: =IF(OR(Z52="Y",AA52="Y"),"Not suitable","") -> Not suitable | Z52: =IF(N52="N/A","Y","") -> Y
B53: TRMB.OQ | C53: Trimble Inc | D53: Software | F53: -0.163 | G53: -3,242295693 | H53: 1.1629884e+10 | I53: 1.8 | J53: 0.209 | K53: =IFERROR(_xlfn.RANK.EQ(F53,F$3:F$1770),"N/A") -> 402 | L53: 1.21 | M53: =IFERROR(_xlfn.RANK.EQ(H53,H$3:H$1770),"N/A") -> 51 | N53: =IFERROR(_xlfn.RANK.EQ(I53,I$3:I$1770),"N/A") -> 297 | O53: =IFERROR(_xlfn.RANK.EQ(J53,J$3:J$1770),"N/A") -> 240 | P53: 10.03 | Q53: 22.47 | R53: 1.07 | S53: 47.16 | T53: 75,404,000.00 | U53: =SUM(P53:T53) -> 0 | V53: =_xlfn.RANK.EQ(U53,$U$4:$U$61,1) -> 1 | W53: =IF(Y53="Not suitable","-",V53) -> 1 | Y53: =IF(OR(Z53="Y",AA53="Y"),"Not suitable","") | Z53: =IF(N53="N/A","Y","")
B54: ESTC.N | C54: Elastic NV | D54: Software | F54: 0.165 | G54: 3.2604033 | H54: 1.1277176e+10 | J54: -9,8% | K54: =IFERROR(_xlfn.RANK.EQ(F54,F$3:F$1770),"N/A") -> 124 | L54: 0.12 | M54: =IFERROR(_xlfn.RANK.EQ(H54,H$3:H$1770),"N/A") -> 52 | N54: =IFERROR(_xlfn.RANK.EQ(I54,I$3:I$1770),"N/A") -> N/A | O54: =IFERROR(_xlfn.RANK.EQ(J54,J$3:J$1770),"N/A") -> N/A | P54: 2.94 | Q54: 26.30 | R54: 0.11 | S54: 2.96 | T54: 78,941,800.00 | U54: =SUM(P54:T54) -> 0 | V54: =_xlfn.RANK.EQ(U54,$U$4:$U$61,1) -> 1 | W54: =IF(Y54="Not suitable","-",V54) -> - | Y54: =IF(OR(Z54="Y",AA54="Y"),"Not suitable","") -> Not suitable | Z54: =IF(N54="N/A","Y","") -> Y
B55: PAYC.N | C55: Paycom Software Inc | D55: Software | F55: 0.062 | G55: -3,120133922 | H55: 1.115787e+10 | I55: 14.3 | J55: 0.341 | K55: =IFERROR(_xlfn.RANK.EQ(F55,F$3:F$1770),"N/A") -> 239 | M55: =IFERROR(_xlfn.RANK.EQ(H55,H$3:H$1770),"N/A") -> 53 | N55: =IFERROR(_xlfn.RANK.EQ(I55,I$3:I$1770),"N/A") -> 198 | O55: =IFERROR(_xlfn.RANK.EQ(J55,J$3:J$1770),"N/A") -> 83 | S55: 0.00 | T55: 5,049,255,341.00 | U55: =SUM(P55:T55) -> 0 | V55: =_xlfn.RANK.EQ(U55,$U$4:$U$61,1) -> 1 | W55: =IF(Y55="Not suitable","-",V55) -> 1 | Y55: =IF(OR(Z55="Y",AA55="Y"),"Not suitable","") | Z55: =IF(N55="N/A","Y","")
B56: OTEX.TO | C56: Open Text Corp | D56: Software | F56: 0.344 | G56: 0.076582013 | H56: 1.0805463e+10 | I56: -0,04 | J56: 0.304 | K56: =IFERROR(_xlfn.RANK.EQ(F56,F$3:F$1770),"N/A") -> 40 | M56: =IFERROR(_xlfn.RANK.EQ(H56,H$3:H$1770),"N/A") -> 54 | N56: =IFERROR(_xlfn.RANK.EQ(I56,I$3:I$1770),"N/A") -> N/A | O56: =IFERROR(_xlfn.RANK.EQ(J56,J$3:J$1770),"N/A") -> 125 | S56: 0.00 | T56: 753,377,447.00 | U56: =SUM(P56:T56) -> 0 | V56: =_xlfn.RANK.EQ(U56,$U$4:$U$61,1) -> 1 | W56: =IF(Y56="Not suitable","-",V56) -> - | Y56: =IF(OR(Z56="Y",AA56="Y"),"Not suitable","") -> Not suitable | Z56: =IF(N56="N/A","Y","") -> Y
B57: CDAY.N | C57: Ceridian HCM Holding Inc | D57: Software | F57: 0.221 | G57: 12.975 | H57: 1.0368395e+10 | I57: 25.28 | J57: 0.152 | K57: =IFERROR(_xlfn.RANK.EQ(F57,F$3:F$1770),"N/A") -> 86 | M57: =IFERROR(_xlfn.RANK.EQ(H57,H$3:H$1770),"N/A") -> 55 | N57: =IFERROR(_xlfn.RANK.EQ(I57,I$3:I$1770),"N/A") -> 159 | O57: =IFERROR(_xlfn.RANK.EQ(J57,J$3:J$1770),"N/A") -> 333 | S57: 0.01 | T57: 44,701,000.00 | U57: =SUM(P57:T57) -> 0 | V57: =_xlfn.RANK.EQ(U57,$U$4:$U$61,1) -> 1 | W57: =IF(Y57="Not suitable","-",V57) -> 1 | Y57: =IF(OR(Z57="Y",AA57="Y"),"Not suitable","") | Z57: =IF(N57="N/A","Y","")
B58: XRO.AX | C58: Xero Ltd | D58: Software | F58: 0.056 | G58: 95.40625 | H58: 1.0359526e+10 | J58: 0.251 | K58: =IFERROR(_xlfn.RANK.EQ(F58,F$3:F$1770),"N/A") -> 250 | M58: =IFERROR(_xlfn.RANK.EQ(H58,H$3:H$1770),"N/A") -> 56 | N58: =IFERROR(_xlfn.RANK.EQ(I58,I$3:I$1770),"N/A") -> N/A | O58: =IFERROR(_xlfn.RANK.EQ(J58,J$3:J$1770),"N/A") -> 178 | S58: 0.02 | T58: 47,722,000.00 | U58: =SUM(P58:T58) -> 0 | V58: =_xlfn.RANK.EQ(U58,$U$4:$U$61,1) -> 1 | W58: =IF(Y58="Not suitable","-",V58) -> - | Y58: =IF(OR(Z58="Y",AA58="Y"),"Not suitable","") -> Not suitable | Z58: =IF(N58="N/A","Y","") -> Y
B59: 4716.T | C59: Oracle Corp Japan | D59: Software | F59: 0.029 | G59: 11.71627 | H59: 1.0053952e+10 | I59: -6,42 | J59: 0.334 | K59: =IFERROR(_xlfn.RANK.EQ(F59,F$3:F$1770),"N/A") -> 284 | M59: =IFERROR(_xlfn.RANK.EQ(H59,H$3:H$1770),"N/A") -> 57 | N59: =IFERROR(_xlfn.RANK.EQ(I59,I$3:I$1770),"N/A") -> N/A | O59: =IFERROR(_xlfn.RANK.EQ(J59,J$3:J$1770),"N/A") -> 92 | S59: 0.02 | T59: 10,800,200.00 | U59: =SUM(P59:T59) -> 0 | V59: =_xlfn.RANK.EQ(U59,$U$4:$U$61,1) -> 1 | W59: =IF(Y59="Not suitable","-",V59) -> - | Y59: =IF(OR(Z59="Y",AA59="Y"),"Not suitable","") -> Not suitable | Z59: =IF(N59="N/A","Y","") -> Y
B60: DOCU.OQ | C60: DocuSign Inc | D60: Software | F60: 0.37 | G60: 0 | H60: 9.640049e+09 | I60: 15.08 | J60: 0.056 | K60: =IFERROR(_xlfn.RANK.EQ(F60,F$3:F$1770),"N/A") -> 35 | M60: =IFERROR(_xlfn.RANK.EQ(H60,H$3:H$1770),"N/A") -> 58 | N60: =IFERROR(_xlfn.RANK.EQ(I60,I$3:I$1770),"N/A") -> 197 | O60: =IFERROR(_xlfn.RANK.EQ(J60,J$3:J$1770),"N/A") -> 591 | S60: 0.03 | T60: 32,227,406.00 | U60: =SUM(P60:T60) -> 0 | V60: =_xlfn.RANK.EQ(U60,$U$4:$U$61,1) -> 1 | W60: =IF(Y60="Not suitable","-",V60) -> 1 | Y60: =IF(OR(Z60="Y",AA60="Y"),"Not suitable","") | Z60: =IF(N60="N/A","Y","")
B61: NEKG.DE | C61: Nemetschek SE | D61: Software | F61: 0.938 | G61: -13,76534324 | H61: 9.5835665e+09 | I61: 4.14 | J61: 0.292 | K61: =IFERROR(_xlfn.RANK.EQ(F61,F$3:F$1770),"N/A") -> 10 | M61: =IFERROR(_xlfn.RANK.EQ(H61,H$3:H$1770),"N/A") -> 59 | N61: =IFERROR(_xlfn.RANK.EQ(I61,I$3:I$1770),"N/A") -> 278 | O61: =IFERROR(_xlfn.RANK.EQ(J61,J$3:J$1770),"N/A") -> 135 | P61: 1.83 | Q61: 4.92 | S61: 0.38 | T61: 91,449,602.00 | U61: =SUM(P61:T61) -> 0 | V61: =_xlfn.RANK.EQ(U61,$U$4:$U$61,1) -> 1 | W61: =IF(Y61="Not suitable","-",V61) -> 1 | Y61: =IF(OR(Z61="Y",AA61="Y"),"Not suitable","") | Z61: =IF(N61="N/A","Y","")
B62: DBX.OQ | C62: Dropbox Inc | D62: Software | F62: 0.615 | G62: 0.75315028 | H62: 9577507126 | I62: 9.26 | J62: 0.212 | K62: =IFERROR(_xlfn.RANK.EQ(F62,F$3:F$1770),"N/A") -> 13 | L62: 7.77 | M62: =IFERROR(_xlfn.RANK.EQ(H62,H$3:H$1770),"N/A") -> 60 | N62: =IFERROR(_xlfn.RANK.EQ(I62,I$3:I$1770),"N/A") -> 233 | O62: =IFERROR(_xlfn.RANK.EQ(J62,J$3:J$1770),"N/A") -> 234 | P62: 9.12 | Q62: 49.79 | R62: 7.60 | S62: 402.14 | T62: 42,124,186.00 | U62: =SUM(P62:T62) -> 0 | V62: =_xlfn.RANK.EQ(U62,$U$4:$U$61,1) -> 1 | W62: =IF(Y62="Not suitable","-",V62) -> 1 | Y62: =IF(OR(Z62="Y",AA62="Y"),"Not suitable","") | Z62: =IF(N62="N/A","Y","")
B63: GTLB.OQ | C63: GitLab Inc | D63: Software | F63: -1.258 | G63: 4.5849637 | H63: 9197199000 | I63: 31.72 | J63: -34,5% | K63: =IFERROR(_xlfn.RANK.EQ(F63,F$3:F$1770),"N/A") -> 494 | M63: =IFERROR(_xlfn.RANK.EQ(H63,H$3:H$1770),"N/A") -> 61 | N63: =IFERROR(_xlfn.RANK.EQ(I63,I$3:I$1770),"N/A") -> 137 | O63: =IFERROR(_xlfn.RANK.EQ(J63,J$3:J$1770),"N/A") -> N/A | P63: 1.86 | Q63: 12.09 | S63: 1.17 | T63: 4,242,957.00 | U63: =SUM(P63:T63) -> 0 | V63: =_xlfn.RANK.EQ(U63,$U$4:$U$61,1) -> 1 | W63: =IF(Y63="Not suitable","-",V63) -> 1 | Y63: =IF(OR(Z63="Y",AA63="Y"),"Not suitable","") | Z63: =IF(N63="N/A","Y","")
B64: 688256.SS | C64: Cambricon Technologies Corp Ltd | D64: Software | F64: -0.088 | G64: 0 | H64: 9.1871588e+09 | I64: 35.26 | J64: -567,6% | K64: =IFERROR(_xlfn.RANK.EQ(F64,F$3:F$1770),"N/A") -> 373 | L64: 1.97 | M64: =IFERROR(_xlfn.RANK.EQ(H64,H$3:H$1770),"N/A") -> 62 | N64: =IFERROR(_xlfn.RANK.EQ(I64,I$3:I$1770),"N/A") -> 125 | O64: =IFERROR(_xlfn.RANK.EQ(J64,J$3:J$1770),"N/A") -> N/A | P64: 6.13 | Q64: 13.58 | R64: 1.78 | S64: 22.27 | T64: 640,715,270.00 | U64: =SUM(P64:T64) -> 0 | V64: =_xlfn.RANK.EQ(U64,$U$4:$U$61,1) -> 1 | W64: =IF(Y64="Not suitable","-",V64) -> 1 | Y64: =IF(OR(Z64="Y",AA64="Y"),"Not suitable","") | Z64: =IF(N64="N/A","Y","")
B65: 9697.T | C65: Capcom Co Ltd | D65: Software | F65: -0.234 | G65: -0,071316163 | H65: 8.9860392e+09 | I65: 3.01 | J65: 0.429 | K65: =IFERROR(_xlfn.RANK.EQ(F65,F$3:F$1770),"N/A") -> 427 | M65: =IFERROR(_xlfn.RANK.EQ(H65,H$3:H$1770),"N/A") -> 63 | N65: =IFERROR(_xlfn.RANK.EQ(I65,I$3:I$1770),"N/A") -> 288 | O65: =IFERROR(_xlfn.RANK.EQ(J65,J$3:J$1770),"N/A") -> 47 | P65: 2.44 | S65: 0.00 | T65: 294,382,630.00 | U65: =SUM(P65:T65) -> 0 | V65: =_xlfn.RANK.EQ(U65,$U$4:$U$61,1) -> 1 | W65: =IF(Y65="Not suitable","-",V65) -> 1 | Y65: =IF(OR(Z65="Y",AA65="Y"),"Not suitable","") | Z65: =IF(N65="N/A","Y","")
B66: PCTY.OQ | C66: Paylocity Holding Corp | D66: Software | F66: 0.239 | G66: 0.23132331 | H66: 8.6242763e+09 | I66: 20.64 | J66: 0.199 | K66: =IFERROR(_xlfn.RANK.EQ(F66,F$3:F$1770),"N/A") -> 74 | L66: 0.92 | M66: =IFERROR(_xlfn.RANK.EQ(H66,H$3:H$1770),"N/A") -> 64 | N66: =IFERROR(_xlfn.RANK.EQ(I66,I$3:I$1770),"N/A") -> 174 | O66: =IFERROR(_xlfn.RANK.EQ(J66,J$3:J$1770),"N/A") -> 254 | P66: 3.71 | Q66: 12.36 | R66: 1.03 | S66: 24.81 | T66: 55,256,617.00 | U66: =SUM(P66:T66) -> 0 | V66: =_xlfn.RANK.EQ(U66,$U$4:$U$61,1) -> 1 | W66: =IF(Y66="Not suitable","-",V66) -> 1 | Y66: =IF(OR(Z66="Y",AA66="Y"),"Not suitable","") | Z66: =IF(N66="N/A","Y","")
B67: CYBR.OQ | C67: Cyberark Software Ltd | D67: Software | F67: 0.401 | G67: 0 | H67: 8.436961e+09 | J67: -17,6% | K67: =IFERROR(_xlfn.RANK.EQ(F67,F$3:F$1770),"N/A") -> 28 | L67: 1.57 | M67: =IFERROR(_xlfn.RANK.EQ(H67,H$3:H$1770),"N/A") -> 65 | N67: =IFERROR(_xlfn.RANK.EQ(I67,I$3:I$1770),"N/A") -> N/A | O67: =IFERROR(_xlfn.RANK.EQ(J67,J$3:J$1770),"N/A") -> N/A | P67: 0.91 | Q67: 5.25 | R67: 1.12 | S67: 19.97 | T67: 13,997,173.00 | U67: =SUM(P67:T67) -> 0 | V67: =_xlfn.RANK.EQ(U67,$U$4:$U$61,1) -> 1 | W67: =IF(Y67="Not suitable","-",V67) -> - | Y67: =IF(OR(Z67="Y",AA67="Y"),"Not suitable","") -> Not suitable | Z67: =IF(N67="N/A","Y","") -> Y
B68: MNDY.OQ | C68: Monday.Com Ltd | D68: Software | F68: -0.025 | G68: -3,734627747 | H68: 8.404147e+09 | J68: -5,8% | K68: =IFERROR(_xlfn.RANK.EQ(F68,F$3:F$1770),"N/A") -> 330 | L68: 2.63 | M68: =IFERROR(_xlfn.RANK.EQ(H68,H$3:H$1770),"N/A") -> 66 | N68: =IFERROR(_xlfn.RANK.EQ(I68,I$3:I$1770),"N/A") -> N/A | O68: =IFERROR(_xlfn.RANK.EQ(J68,J$3:J$1770),"N/A") -> N/A | P68: 3.89 | Q68: 18.51 | R68: 2.65 | S68: 46.75 | T68: 248,767,565.00 | U68: =SUM(P68:T68) -> 0 | V68: =_xlfn.RANK.EQ(U68,$U$4:$U$61,1) -> 1 | W68: =IF(Y68="Not suitable","-",V68) -> - | Y68: =IF(OR(Z68="Y",AA68="Y"),"Not suitable","") -> Not suitable | Z68: =IF(N68="N/A","Y","") -> Y
B69: PCOR.N | C69: Procore Technologies Inc | D69: Software | F69: -0.193 | G69: 0 | H69: 8.400047e+09 | I69: 25.86 | J69: -20,0% | K69: =IFERROR(_xlfn.RANK.EQ(F69,F$3:F$1770),"N/A") -> 411 | L69: 1.40 | M69: =IFERROR(_xlfn.RANK.EQ(H69,H$3:H$1770),"N/A") -> 67 | N69: =IFERROR(_xlfn.RANK.EQ(I69,I$3:I$1770),"N/A") -> 155 | O69: =IFERROR(_xlfn.RANK.EQ(J69,J$3:J$1770),"N/A") -> N/A | P69: 7.72 | Q69: 17.62 | R69: 1.25 | S69: 33.50 | T69: 266,505,623.00 | U69: =SUM(P69:T69) -> 0 | V69: =_xlfn.RANK.EQ(U69,$U$4:$U$61,1) -> 1 | W69: =IF(Y69="Not suitable","-",V69) -> 1 | Y69: =IF(OR(Z69="Y",AA69="Y"),"Not suitable","") | Z69: =IF(N69="N/A","Y","")
B70: DLB.N | C70: Dolby Laboratories Inc | D70: Software | F70: -0.061 | G70: -0,168765922 | H70: 8.3928632e+09 | I70: -1,44 | J70: 0.258 | K70: =IFERROR(_xlfn.RANK.EQ(F70,F$3:F$1770),"N/A") -> 351 | M70: =IFERROR(_xlfn.RANK.EQ(H70,H$3:H$1770),"N/A") -> 68 | N70: =IFERROR(_xlfn.RANK.EQ(I70,I$3:I$1770),"N/A") -> N/A | O70: =IFERROR(_xlfn.RANK.EQ(J70,J$3:J$1770),"N/A") -> 169 | P70: 0.28 | Q70: 2.80 | S70: 10.41 | T70: 11,417,900.00 | U70: =SUM(P70:T70) -> 0 | V70: =_xlfn.RANK.EQ(U70,$U$4:$U$61,1) -> 1 | W70: =IF(Y70="Not suitable","-",V70) -> - | Y70: =IF(OR(Z70="Y",AA70="Y"),"Not suitable","") -> Not suitable | Z70: =IF(N70="N/A","Y","") -> Y
B71: 600588.SS | C71: Yonyou Network Technology Co Ltd | D71: Software | G71: 0 | H71: 8.2324411e+09 | J71: -11,6% | K71: =IFERROR(_xlfn.RANK.EQ(F71,F$3:F$1770),"N/A") -> 316 | M71: =IFERROR(_xlfn.RANK.EQ(H71,H$3:H$1770),"N/A") -> 69 | N71: =IFERROR(_xlfn.RANK.EQ(I71,I$3:I$1770),"N/A") -> N/A | O71: =IFERROR(_xlfn.RANK.EQ(J71,J$3:J$1770),"N/A") -> N/A | P71: 0.79 | Q71: 4.80 | R71: 0.76 | S71: 10.46 | T71: 18,287,000.00 | U71: =SUM(P71:T71) -> 0 | V71: =_xlfn.RANK.EQ(U71,$U$4:$U$61,1) -> 1 | W71: =IF(Y71="Not suitable","-",V71) -> - | Y71: =IF(OR(Z71="Y",AA71="Y"),"Not suitable","") -> Not suitable | Z71: =IF(N71="N/A","Y","") -> Y
B72: TOST.N | C72: Toast Inc | D72: Software | F72: 0.024 | G72: 41.505898 | H72: 8.135531e+09 | I72: 72.91 | J72: -8,4% | K72: =IFERROR(_xlfn.RANK.EQ(F72,F$3:F$1770),"N/A") -> 293 | M72: =IFERROR(_xlfn.RANK.EQ(H72,H$3:H$1770),"N/A") -> 70 | N72: =IFERROR(_xlfn.RANK.EQ(I72,I$3:I$1770),"N/A") -> 52 | O72: =IFERROR(_xlfn.RANK.EQ(J72,J$3:J$1770),"N/A") -> N/A | S72: 0.35 | T72: 142,697,197.00 | U72: =SUM(P72:T72) -> 0 | V72: =_xlfn.RANK.EQ(U72,$U$4:$U$61,1) -> 1 | W72: =IF(Y72="Not suitable","-",V72) -> 1 | Y72: =IF(OR(Z72="Y",AA72="Y"),"Not suitable","") | Z72: =IF(N72="N/A","Y","")
B73: GWRE.N | C73: Guidewire Software Inc | D73: Software | F73: -0.251 | G73: 0 | H73: 8.0988293e+09 | J73: -10,1% | K73: =IFERROR(_xlfn.RANK.EQ(F73,F$3:F$1770),"N/A") -> 435 | M73: =IFERROR(_xlfn.RANK.EQ(H73,H$3:H$1770),"N/A") -> 71 | N73: =IFERROR(_xlfn.RANK.EQ(I73,I$3:I$1770),"N/A") -> N/A | O73: =IFERROR(_xlfn.RANK.EQ(J73,J$3:J$1770),"N/A") -> N/A | P73: 1.95 | Q73: 27.31 | S73: 1.92 | T73: 38,666,746.00 | U73: =SUM(P73:T73) -> 0 | V73: =_xlfn.RANK.EQ(U73,$U$4:$U$61,1) -> 1 | W73: =IF(Y73="Not suitable","-",V73) -> - | Y73: =IF(OR(Z73="Y",AA73="Y"),"Not suitable","") -> Not suitable | Z73: =IF(N73="N/A","Y","") -> Y
B74: 301269.SZ | C74: Empyrean Technology Co Ltd | D74: Software | F74: 0.022 | G74: -2,710121391 | H74: 8.0850905e+09 | J74: 0.183 | K74: =IFERROR(_xlfn.RANK.EQ(F74,F$3:F$1770),"N/A") -> 296 | L74: 1.66 | M74: =IFERROR(_xlfn.RANK.EQ(H74,H$3:H$1770),"N/A") -> 72 | N74: =IFERROR(_xlfn.RANK.EQ(I74,I$3:I$1770),"N/A") -> N/A | O74: =IFERROR(_xlfn.RANK.EQ(J74,J$3:J$1770),"N/A") -> 281 | P74: 2.23 | Q74: 5.03 | R74: -3.85 | S74: 26.22 | T74: 127,416,314.00 | U74: =SUM(P74:T74) -> 0 | V74: =_xlfn.RANK.EQ(U74,$U$4:$U$61,1) -> 1 | W74: =IF(Y74="Not suitable","-",V74) -> - | Y74: =IF(OR(Z74="Y",AA74="Y"),"Not suitable","") -> Not suitable | Z74: =IF(N74="N/A","Y","") -> Y
B75: INFA.N | C75: Informatica Inc | D75: Software | F75: 0.073 | G75: 0.51219976 | H75: 7.8866278e+09 | I75: 59.76 | J75: 0.148 | K75: =IFERROR(_xlfn.RANK.EQ(F75,F$3:F$1770),"N/A") -> 222 | L75: 13.61 | M75: =IFERROR(_xlfn.RANK.EQ(H75,H$3:H$1770),"N/A") -> 73 | N75: =IFERROR(_xlfn.RANK.EQ(I75,I$3:I$1770),"N/A") -> 72 | O75: =IFERROR(_xlfn.RANK.EQ(J75,J$3:J$1770),"N/A") -> 349 | P75: 13.64 | Q75: 49.54 | R75: 11.09 | S75: 534.15 | T75: 152,053,000.00 | U75: =SUM(P75:T75) -> 0 | V75: =_xlfn.RANK.EQ(U75,$U$4:$U$61,1) -> 1 | W75: =IF(Y75="Not suitable","-",V75) -> 1 | Y75: =IF(OR(Z75="Y",AA75="Y"),"Not suitable","") | Z75: =IF(N75="N/A","Y","")
B76: 4704.T | C76: Trend Micro Inc | D76: Software | F76: 0.111 | G76: 71.886498 | H76: 7.8299593e+09 | I76: -12,24 | J76: 0.253 | K76: =IFERROR(_xlfn.RANK.EQ(F76,F$3:F$1770),"N/A") -> 183 | M76: =IFERROR(_xlfn.RANK.EQ(H76,H$3:H$1770),"N/A") -> 74 | N76: =IFERROR(_xlfn.RANK.EQ(I76,I$3:I$1770),"N/A") -> N/A | O76: =IFERROR(_xlfn.RANK.EQ(J76,J$3:J$1770),"N/A") -> 177 | P76: 10.46 | Q76: 106.50 | S76: 0.78 | T76: 1,093,332,092.00 | U76: =SUM(P76:T76) -> 0 | V76: =_xlfn.RANK.EQ(U76,$U$4:$U$61,1) -> 1 | W76: =IF(Y76="Not suitable","-",V76) -> - | Y76: =IF(OR(Z76="Y",AA76="Y"),"Not suitable","") -> Not suitable | Z76: =IF(N76="N/A","Y","") -> Y
B77: MSTR.OQ | C77: Microstrategy Inc | D77: Software | F77: 0.134 | G77: 0 | H77: 7.8084405e+09 | I77: 42.35 | J77: 0.042 | K77: =IFERROR(_xlfn.RANK.EQ(F77,F$3:F$1770),"N/A") -> 162 | M77: =IFERROR(_xlfn.RANK.EQ(H77,H$3:H$1770),"N/A") -> 75 | N77: =IFERROR(_xlfn.RANK.EQ(I77,I$3:I$1770),"N/A") -> 104 | O77: =IFERROR(_xlfn.RANK.EQ(J77,J$3:J$1770),"N/A") -> 623 | S77: 0.00 | T77: 15,090,902.00 | U77: =SUM(P77:T77) -> 0 | V77: =_xlfn.RANK.EQ(U77,$U$4:$U$61,1) -> 1 | W77: =IF(Y77="Not suitable","-",V77) -> 1 | Y77: =IF(OR(Z77="Y",AA77="Y"),"Not suitable","") | Z77: =IF(N77="N/A","Y","")
B78: 600570.SS | C78: Hundsun Technologies Inc | D78: Software | G78: 225.62728 | H78: 7.7337879e+09 | I78: 8.88 | J78: 0.129 | K78: =IFERROR(_xlfn.RANK.EQ(F78,F$3:F$1770),"N/A") -> 316 | M78: =IFERROR(_xlfn.RANK.EQ(H78,H$3:H$1770),"N/A") -> 76 | N78: =IFERROR(_xlfn.RANK.EQ(I78,I$3:I$1770),"N/A") -> 236 | O78: =IFERROR(_xlfn.RANK.EQ(J78,J$3:J$1770),"N/A") -> 402 | S78: 0.29 | T78: 123,071,379.00 | U78: =SUM(P78:T78) -> 0 | V78: =_xlfn.RANK.EQ(U78,$U$4:$U$61,1) -> 1 | W78: =IF(Y78="Not suitable","-",V78) -> 1 | Y78: =IF(OR(Z78="Y",AA78="Y"),"Not suitable","") | Z78: =IF(N78="N/A","Y","")
B79: YMM.N | C79: Full Truck Alliance Co Ltd | D79: Software | F79: 0.174 | G79: 0.20601352 | H79: 7.6856194e+09 | J79: 0.092 | K79: =IFERROR(_xlfn.RANK.EQ(F79,F$3:F$1770),"N/A") -> 115 | M79: =IFERROR(_xlfn.RANK.EQ(H79,H$3:H$1770),"N/A") -> 77 | N79: =IFERROR(_xlfn.RANK.EQ(I79,I$3:I$1770),"N/A") -> N/A | O79: =IFERROR(_xlfn.RANK.EQ(J79,J$3:J$1770),"N/A") -> 519 | S79: 0.06 | T79: 20,687,833.00 | U79: =SUM(P79:T79) -> 0 | V79: =_xlfn.RANK.EQ(U79,$U$4:$U$61,1) -> 1 | W79: =IF(Y79="Not suitable","-",V79) -> - | Y79: =IF(OR(Z79="Y",AA79="Y"),"Not suitable","") -> Not suitable | Z79: =IF(N79="N/A","Y","") -> Y
B80: BILL.N | C80: BILL Holdings Inc | D80: Software | F80: 0.041 | G80: 0 | H80: 7.4056425e+09 | J80: -15,3% | K80: =IFERROR(_xlfn.RANK.EQ(F80,F$3:F$1770),"N/A") -> 265 | M80: =IFERROR(_xlfn.RANK.EQ(H80,H$3:H$1770),"N/A") -> 78 | N80: =IFERROR(_xlfn.RANK.EQ(I80,I$3:I$1770),"N/A") -> N/A | O80: =IFERROR(_xlfn.RANK.EQ(J80,J$3:J$1770),"N/A") -> N/A | P80: 143.94 | S80: 0.01 | T80: 268,074,709.00 | U80: =SUM(P80:T80) -> 0 | V80: =_xlfn.RANK.EQ(U80,$U$4:$U$61,1) -> 1 | W80: =IF(Y80="Not suitable","-",V80) -> - | Y80: =IF(OR(Z80="Y",AA80="Y"),"Not suitable","") -> Not suitable | Z80: =IF(N80="N/A","Y","") -> Y
B81: CCCS.OQ | C81: CCC Intelligent Solutions Holdings Inc | D81: Software | F81: 0.048 | G81: -6,220405514 | H81: 7.3138127e+09 | I81: 61.03 | J81: 0.223 | K81: =IFERROR(_xlfn.RANK.EQ(F81,F$3:F$1770),"N/A") -> 258 | L81: 0.61 | M81: =IFERROR(_xlfn.RANK.EQ(H81,H$3:H$1770),"N/A") -> 79 | N81: =IFERROR(_xlfn.RANK.EQ(I81,I$3:I$1770),"N/A") -> 68 | O81: =IFERROR(_xlfn.RANK.EQ(J81,J$3:J$1770),"N/A") -> 218 | P81: 1.30 | Q81: 7.87 | R81: 0.07 | S81: 7.61 | T81: 24,753,028.00 | U81: =SUM(P81:T81) -> 0 | V81: =_xlfn.RANK.EQ(U81,$U$4:$U$61,1) -> 1 | W81: =IF(Y81="Not suitable","-",V81) -> 1 | Y81: =IF(OR(Z81="Y",AA81="Y"),"Not suitable","") | Z81: =IF(N81="N/A","Y","")
B82: 9766.T | C82: Konami Group Corp | D82: Software | F82: 0.09 | G82: 13.630075 | H82: 7.2816679e+09 | I82: -7,22 | J82: 0.242 | K82: =IFERROR(_xlfn.RANK.EQ(F82,F$3:F$1770),"N/A") -> 204 | L82: 0.00 | M82: =IFERROR(_xlfn.RANK.EQ(H82,H$3:H$1770),"N/A") -> 80 | N82: =IFERROR(_xlfn.RANK.EQ(I82,I$3:I$1770),"N/A") -> N/A | O82: =IFERROR(_xlfn.RANK.EQ(J82,J$3:J$1770),"N/A") -> 194 | P82: 1.38 | Q82: 8.57 | S82: 0.26 | T82: 90,477,798.00 | U82: =SUM(P82:T82) -> 0 | V82: =_xlfn.RANK.EQ(U82,$U$4:$U$61,1) -> 1 | W82: =IF(Y82="Not suitable","-",V82) -> - | Y82: =IF(OR(Z82="Y",AA82="Y"),"Not suitable","") -> Not suitable | Z82: =IF(N82="N/A","Y","") -> Y
B83: CFLT.OQ | C83: Confluent Inc | D83: Software | F83: 0.096 | G83: 1.1271717 | H83: 7.0934418e+09 | I83: 28.55 | J83: -63,5% | K83: =IFERROR(_xlfn.RANK.EQ(F83,F$3:F$1770),"N/A") -> 197 | M83: =IFERROR(_xlfn.RANK.EQ(H83,H$3:H$1770),"N/A") -> 81 | N83: =IFERROR(_xlfn.RANK.EQ(I83,I$3:I$1770),"N/A") -> 148 | O83: =IFERROR(_xlfn.RANK.EQ(J83,J$3:J$1770),"N/A") -> N/A | S83: 16.36 | T83: 33,578,100.00 | U83: =SUM(P83:T83) -> 0 | V83: =_xlfn.RANK.EQ(U83,$U$4:$U$61,1) -> 1 | W83: =IF(Y83="Not suitable","-",V83) -> 1 | Y83: =IF(OR(Z83="Y",AA83="Y"),"Not suitable","") | Z83: =IF(N83="N/A","Y","")
B84: DSG.TO | C84: Descartes Systems Group Inc | D84: Software | F84: -0.199 | G84: -2,34398302 | H84: 7.0558167e+09 | I84: 11.9 | J84: 0.377 | K84: =IFERROR(_xlfn.RANK.EQ(F84,F$3:F$1770),"N/A") -> 415 | M84: =IFERROR(_xlfn.RANK.EQ(H84,H$3:H$1770),"N/A") -> 82 | N84: =IFERROR(_xlfn.RANK.EQ(I84,I$3:I$1770),"N/A") -> 212 | O84: =IFERROR(_xlfn.RANK.EQ(J84,J$3:J$1770),"N/A") -> 66 | S84: 0.00 | T84: 506,286,159.00 | U84: =SUM(P84:T84) -> 0 | V84: =_xlfn.RANK.EQ(U84,$U$4:$U$61,1) -> 1 | W84: =IF(Y84="Not suitable","-",V84) -> 1 | Y84: =IF(OR(Z84="Y",AA84="Y"),"Not suitable","") | Z84: =IF(N84="N/A","Y","")
B85: S.N | C85: SentinelOne Inc | D85: Software | F85: 0.097 | G85: 0 | H85: 6.9949633e+09 | I85: 35.95 | J85: -63,2% | K85: =IFERROR(_xlfn.RANK.EQ(F85,F$3:F$1770),"N/A") -> 195 | L85: 0.25 | M85: =IFERROR(_xlfn.RANK.EQ(H85,H$3:H$1770),"N/A") -> 83 | N85: =IFERROR(_xlfn.RANK.EQ(I85,I$3:I$1770),"N/A") -> 121 | O85: =IFERROR(_xlfn.RANK.EQ(J85,J$3:J$1770),"N/A") -> N/A | P85: 10.21 | Q85: 23.16 | R85: 0.18 | S85: 7.79 | T85: 80,926,511.00 | U85: =SUM(P85:T85) -> 0 | V85: =_xlfn.RANK.EQ(U85,$U$4:$U$61,1) -> 1 | W85: =IF(Y85="Not suitable","-",V85) -> 1 | Y85: =IF(OR(Z85="Y",AA85="Y"),"Not suitable","") | Z85: =IF(N85="N/A","Y","")
B86: SPSC.OQ | C86: SPS Commerce Inc | D86: Software | F86: -0.118 | G86: 0 | H86: 6.6837353e+09 | I86: 10.71 | J86: 0.208 | K86: =IFERROR(_xlfn.RANK.EQ(F86,F$3:F$1770),"N/A") -> 389 | M86: =IFERROR(_xlfn.RANK.EQ(H86,H$3:H$1770),"N/A") -> 84 | N86: =IFERROR(_xlfn.RANK.EQ(I86,I$3:I$1770),"N/A") -> 221 | O86: =IFERROR(_xlfn.RANK.EQ(J86,J$3:J$1770),"N/A") -> 243 | S86: 0.00 | T86: 52,773,718.00 | U86: =SUM(P86:T86) -> 0 | V86: =_xlfn.RANK.EQ(U86,$U$4:$U$61,1) -> 1 | W86: =IF(Y86="Not suitable","-",V86) -> 1 | Y86: =IF(OR(Z86="Y",AA86="Y"),"Not suitable","") | Z86: =IF(N86="N/A","Y","")
B87: TEMN.S | C87: Temenos AG | D87: Software | F87: 0.171 | G87: 0 | H87: 6.5525389e+09 | I87: -4,61 | K87: =IFERROR(_xlfn.RANK.EQ(F87,F$3:F$1770),"N/A") -> 119 | M87: =IFERROR(_xlfn.RANK.EQ(H87,H$3:H$1770),"N/A") -> 85 | N87: =IFERROR(_xlfn.RANK.EQ(I87,I$3:I$1770),"N/A") -> N/A | O87: =IFERROR(_xlfn.RANK.EQ(J87,J$3:J$1770),"N/A") -> 708 | P87: -0.28 | Q87: -13.58 | S87: 2.35 | T87: 2,584,293.00 | U87: =SUM(P87:T87) -> 0 | V87: =_xlfn.RANK.EQ(U87,$U$4:$U$61,1) -> 1 | W87: =IF(Y87="Not suitable","-",V87) -> - | Y87: =IF(OR(Z87="Y",AA87="Y"),"Not suitable","") -> Not suitable | Z87: =IF(N87="N/A","Y","") -> Y
B88: APPF.OQ | C88: Appfolio Inc | D88: Software | F88: 0.395 | G88: 4.7028722 | H88: 6.4815245e+09 | J88: -3,1% | K88: =IFERROR(_xlfn.RANK.EQ(F88,F$3:F$1770),"N/A") -> 31 | M88: =IFERROR(_xlfn.RANK.EQ(H88,H$3:H$1770),"N/A") -> 86 | N88: =IFERROR(_xlfn.RANK.EQ(I88,I$3:I$1770),"N/A") -> N/A | O88: =IFERROR(_xlfn.RANK.EQ(J88,J$3:J$1770),"N/A") -> N/A | S88: 0.00 | T88: 141,591,534.00 | U88: =SUM(P88:T88) -> 0 | V88: =_xlfn.RANK.EQ(U88,$U$4:$U$61,1) -> 1 | W88: =IF(Y88="Not suitable","-",V88) -> - | Y88: =IF(OR(Z88="Y",AA88="Y"),"Not suitable","") -> Not suitable | Z88: =IF(N88="N/A","Y","") -> Y
B89: TTEX.NS | C89: Tata Elxsi Ltd | D89: Software | G89: 0 | H89: 6.2517454e+09 | I89: 62.02 | J89: 0.299 | K89: =IFERROR(_xlfn.RANK.EQ(F89,F$3:F$1770),"N/A") -> 316 | M89: =IFERROR(_xlfn.RANK.EQ(H89,H$3:H$1770),"N/A") -> 87 | N89: =IFERROR(_xlfn.RANK.EQ(I89,I$3:I$1770),"N/A") -> 65 | O89: =IFERROR(_xlfn.RANK.EQ(J89,J$3:J$1770),"N/A") -> 132 | S89: 0.00 | T89: 125,169,865.00 | U89: =SUM(P89:T89) -> 0 | V89: =_xlfn.RANK.EQ(U89,$U$4:$U$61,1) -> 1 | W89: =IF(Y89="Not suitable","-",V89) -> 1 | Y89: =IF(OR(Z89="Y",AA89="Y"),"Not suitable","") | Z89: =IF(N89="N/A","Y","")
B90: SMAR.N | C90: Smartsheet Inc | D90: Software | F90: 0.41 | G90: 0.20714436 | H90: 6.0661098e+09 | J90: -13,2% | K90: =IFERROR(_xlfn.RANK.EQ(F90,F$3:F$1770),"N/A") -> 26 | M90: =IFERROR(_xlfn.RANK.EQ(H90,H$3:H$1770),"N/A") -> 88 | N90: =IFERROR(_xlfn.RANK.EQ(I90,I$3:I$1770),"N/A") -> N/A | O90: =IFERROR(_xlfn.RANK.EQ(J90,J$3:J$1770),"N/A") -> N/A | S90: 0.03 | T90: 48,242,605.00 | U90: =SUM(P90:T90) -> 0 | V90: =_xlfn.RANK.EQ(U90,$U$4:$U$61,1) -> 1 | W90: =IF(Y90="Not suitable","-",V90) -> - | Y90: =IF(OR(Z90="Y",AA90="Y"),"Not suitable","") -> Not suitable | Z90: =IF(N90="N/A","Y","") -> Y
B91: FRSH.OQ | C91: Freshworks Inc | D91: Software | F91: -0.059 | G91: 0 | H91: 5.9264574e+09 | J91: -31,8% | K91: =IFERROR(_xlfn.RANK.EQ(F91,F$3:F$1770),"N/A") -> 349 | M91: =IFERROR(_xlfn.RANK.EQ(H91,H$3:H$1770),"N/A") -> 89 | N91: =IFERROR(_xlfn.RANK.EQ(I91,I$3:I$1770),"N/A") -> N/A | O91: =IFERROR(_xlfn.RANK.EQ(J91,J$3:J$1770),"N/A") -> N/A | P91: 0.62 | Q91: 14.49 | S91: 0.01 | T91: 4,526,135,442.00 | U91: =SUM(P91:T91) -> 0 | V91: =_xlfn.RANK.EQ(U91,$U$4:$U$61,1) -> 1 | W91: =IF(Y91="Not suitable","-",V91) -> - | Y91: =IF(OR(Z91="Y",AA91="Y"),"Not suitable","") -> Not suitable | Z91: =IF(N91="N/A","Y","") -> Y
B92: HQY.OQ | C92: Healthequity Inc | D92: Software | F92: -0.017 | G92: 0 | H92: 5.7986957e+09 | I92: -8,02 | J92: 0.268 | K92: =IFERROR(_xlfn.RANK.EQ(F92,F$3:F$1770),"N/A") -> 325 | M92: =IFERROR(_xlfn.RANK.EQ(H92,H$3:H$1770),"N/A") -> 90 | N92: =IFERROR(_xlfn.RANK.EQ(I92,I$3:I$1770),"N/A") -> N/A | O92: =IFERROR(_xlfn.RANK.EQ(J92,J$3:J$1770),"N/A") -> 157 | P92: 1.07 | R92: -0.16 | S92: 0.04 | T92: 324,778,056.00 | U92: =SUM(P92:T92) -> 0 | V92: =_xlfn.RANK.EQ(U92,$U$4:$U$61,1) -> 1 | W92: =IF(Y92="Not suitable","-",V92) -> - | Y92: =IF(OR(Z92="Y",AA92="Y"),"Not suitable","") -> Not suitable | Z92: =IF(N92="N/A","Y","") -> Y
B93: FIVN.OQ | C93: Five9 Inc | D93: Software | F93: 0.061 | G93: 24.575412 | H93: 5.7480676e+09 | I93: 13 | J93: -4,0% | K93: =IFERROR(_xlfn.RANK.EQ(F93,F$3:F$1770),"N/A") -> 240 | L93: 1.73 | M93: =IFERROR(_xlfn.RANK.EQ(H93,H$3:H$1770),"N/A") -> 91 | N93: =IFERROR(_xlfn.RANK.EQ(I93,I$3:I$1770),"N/A") -> 205 | O93: =IFERROR(_xlfn.RANK.EQ(J93,J$3:J$1770),"N/A") -> N/A | P93: 3.32 | Q93: 189.64 | R93: -0.04 | S93: 51.84 | T93: 83,555,919.00 | U93: =SUM(P93:T93) -> 0 | V93: =_xlfn.RANK.EQ(U93,$U$4:$U$61,1) -> 1 | W93: =IF(Y93="Not suitable","-",V93) -> 1 | Y93: =IF(OR(Z93="Y",AA93="Y"),"Not suitable","") | Z93: =IF(N93="N/A","Y","")
B94: ALTTU.PA | C94: TaTaTu SpA | D94: Software | F94: 0.41 | G94: -10,04946184 | H94: 5.6465705e+09 | K94: =IFERROR(_xlfn.RANK.EQ(F94,F$3:F$1770),"N/A") -> 26 | L94: 3.13 | M94: =IFERROR(_xlfn.RANK.EQ(H94,H$3:H$1770),"N/A") -> 92 | N94: =IFERROR(_xlfn.RANK.EQ(I94,I$3:I$1770),"N/A") -> N/A | O94: =IFERROR(_xlfn.RANK.EQ(J94,J$3:J$1770),"N/A") -> 708 | P94: 5.24 | Q94: 39.27 | R94: 3.56 | S94: 154.21 | T94: 170,067,620.00 | U94: =SUM(P94:T94) -> 0 | V94: =_xlfn.RANK.EQ(U94,$U$4:$U$61,1) -> 1 | W94: =IF(Y94="Not suitable","-",V94) -> - | Y94: =IF(OR(Z94="Y",AA94="Y"),"Not suitable","") -> Not suitable | Z94: =IF(N94="N/A","Y","") -> Y
B95: TOI.V | C95: Topicus.com Inc | D95: Software | H95: 5.6215988e+09 | J95: 0.303 | K95: =IFERROR(_xlfn.RANK.EQ(F95,F$3:F$1770),"N/A") -> 316 | M95: =IFERROR(_xlfn.RANK.EQ(H95,H$3:H$1770),"N/A") -> 93 | N95: =IFERROR(_xlfn.RANK.EQ(I95,I$3:I$1770),"N/A") -> N/A | O95: =IFERROR(_xlfn.RANK.EQ(J95,J$3:J$1770),"N/A") -> 126 | P95: 0.65 | Q95: 5.27 | S95: 4.34 | T95: 9,100,000.00 | U95: =SUM(P95:T95) -> 0 | V95: =_xlfn.RANK.EQ(U95,$U$4:$U$61,1) -> 1 | W95: =IF(Y95="Not suitable","-",V95) -> - | Y95: =IF(OR(Z95="Y",AA95="Y"),"Not suitable","") -> Not suitable | Z95: =IF(N95="N/A","Y","") -> Y
B96: DV.N | C96: DoubleVerify Holdings Inc | D96: Software | G96: 2.8979786 | H96: 5.5806421e+09 | I96: 42.41 | J96: 0.22 | K96: =IFERROR(_xlfn.RANK.EQ(F96,F$3:F$1770),"N/A") -> 316 | L96: 0.23 | M96: =IFERROR(_xlfn.RANK.EQ(H96,H$3:H$1770),"N/A") -> 94 | N96: =IFERROR(_xlfn.RANK.EQ(I96,I$3:I$1770),"N/A") -> 103 | O96: =IFERROR(_xlfn.RANK.EQ(J96,J$3:J$1770),"N/A") -> 222 | P96: 10.81 | Q96: 26.76 | R96: 0.20 | S96: 9.80 | T96: 325,676,272.00 | U96: =SUM(P96:T96) -> 0 | V96: =_xlfn.RANK.EQ(U96,$U$4:$U$61,1) -> 1 | W96: =IF(Y96="Not suitable","-",V96) -> 1 | Y96: =IF(OR(Z96="Y",AA96="Y"),"Not suitable","") | Z96: =IF(N96="N/A","Y","")
B97: 0020.HK | C97: SenseTime Group Inc | D97: Software | F97: 0.206 | G97: 0.040413216 | H97: 5.4845315e+09 | J97: -75,7% | K97: =IFERROR(_xlfn.RANK.EQ(F97,F$3:F$1770),"N/A") -> 94 | L97: 0.04 | M97: =IFERROR(_xlfn.RANK.EQ(H97,H$3:H$1770),"N/A") -> 95 | N97: =IFERROR(_xlfn.RANK.EQ(I97,I$3:I$1770),"N/A") -> N/A | O97: =IFERROR(_xlfn.RANK.EQ(J97,J$3:J$1770),"N/A") -> N/A | P97: 2.95 | Q97: 16.85 | R97: 0.04 | S97: 1.02 | T97: 161,155,072.00 | U97: =SUM(P97:T97) -> 0 | V97: =_xlfn.RANK.EQ(U97,$U$4:$U$61,1) -> 1 | W97: =IF(Y97="Not suitable","-",V97) -> - | Y97: =IF(OR(Z97="Y",AA97="Y"),"Not suitable","") -> Not suitable | Z97: =IF(N97="N/A","Y","") -> Y
B98: BRZE.OQ | C98: Braze Inc | D98: Software | F98: -0.156 | G98: -1,386429832 | H98: 5.3575955e+09 | I98: 49.65 | J98: -32,8% | K98: =IFERROR(_xlfn.RANK.EQ(F98,F$3:F$1770),"N/A") -> 400 | M98: =IFERROR(_xlfn.RANK.EQ(H98,H$3:H$1770),"N/A") -> 96 | N98: =IFERROR(_xlfn.RANK.EQ(I98,I$3:I$1770),"N/A") -> 86 | O98: =IFERROR(_xlfn.RANK.EQ(J98,J$3:J$1770),"N/A") -> N/A | P98: 0.58 | Q98: 5.63 | R98: 1.07 | S98: 12.59 | T98: 22,000,000.00 | U98: =SUM(P98:T98) -> 0 | V98: =_xlfn.RANK.EQ(U98,$U$4:$U$61,1) -> 1 | W98: =IF(Y98="Not suitable","-",V98) -> 1 | Y98: =IF(OR(Z98="Y",AA98="Y"),"Not suitable","") | Z98: =IF(N98="N/A","Y","")
B99: 300496.SZ | C99: Thunder Software Technology Co Ltd | D99: Software | F99: -0.128 | G99: 0 | H99: 5.2331798e+09 | I99: 33.9 | J99: 0.107 | K99: =IFERROR(_xlfn.RANK.EQ(F99,F$3:F$1770),"N/A") -> 394 | M99: =IFERROR(_xlfn.RANK.EQ(H99,H$3:H$1770),"N/A") -> 97 | N99: =IFERROR(_xlfn.RANK.EQ(I99,I$3:I$1770),"N/A") -> 132 | O99: =IFERROR(_xlfn.RANK.EQ(J99,J$3:J$1770),"N/A") -> 466 | S99: 0.00 | T99: 1,156,380,000.00 | U99: =SUM(P99:T99) -> 0 | V99: =_xlfn.RANK.EQ(U99,$U$4:$U$61,1) -> 1 | W99: =IF(Y99="Not suitable","-",V99) -> 1 | Y99: =IF(OR(Z99="Y",AA99="Y"),"Not suitable","") | Z99: =IF(N99="N/A","Y","")
B100: WK.N | C100: Workiva Inc | D100: Software | F100: 0.122 | G100: 0.20206824 | H100: 5.1740186e+09 | J100: -14,4% | K100: =IFERROR(_xlfn.RANK.EQ(F100,F$3:F$1770),"N/A") -> 172 | M100: =IFERROR(_xlfn.RANK.EQ(H100,H$3:H$1770),"N/A") -> 98 | N100: =IFERROR(_xlfn.RANK.EQ(I100,I$3:I$1770),"N/A") -> N/A | O100: =IFERROR(_xlfn.RANK.EQ(J100,J$3:J$1770),"N/A") -> N/A | P100: 46.81 | S100: 0.04 | T100: 5,404,331.00 | U100: =SUM(P100:T100) -> 0 | V100: =_xlfn.RANK.EQ(U100,$U$4:$U$61,1) -> 1 | W100: =IF(Y100="Not suitable","-",V100) -> - | Y100: =IF(OR(Z100="Y",AA100="Y"),"Not suitable","") -> Not suitable | Z100: =IF(N100="N/A","Y","") -> Y
...

Sheet ESG
B1: Company GICS Sector: | T1: Yes
B2: Information Technology | C2: <- Select Industry | T2: No
B3: ESG Analysis | K3: Relative ESG Analysis
B4: Parameters | C4: Impact | D4: Do they report? | E4: Ranking | F4: Mitigation Plan | G4: Traffic Lights | H4: Improvement over time? | I4: Targets / Goals? | J4: Comments | K4: Parameters | L4: =Peers!C8 -> #VALUE! | M4: =Peers!D8 -> #VALUE! | N4: =Peers!E8 -> #VALUE! | O4: =Peers!F8 -> #VALUE! | P4: =Peers!G8 -> #VALUE! | Q4: =Peers!H8 -> #VALUE! | R4: AVERAGE | S4: AVERAGE (ex. Cisco)
B5: Environmental | K5: Ratios
A6: 1 | B6: CO2 Direct Emissions | C6: =VLOOKUP($B$2,'Sector Impact'!$K$4:$AA$16,A6+1,FALSE) -> Medium | D6: Yes | E6: Medium | F6: Yes | H6: No | I6: To be carbon neutral by 2050 | J6: Since 2020 CO2 Direct direct emissions has been relatively constant | K6: CO2 Emissions/$M Sales | L6: =L12/L$11 -> 0.23306977 | M6: =M12/M$11 -> 0.12120876 | N6: =N12/N$11 -> #VALUE! | O6: =O12/O$11 -> 0.037661631 | P6: =P12/P$11 -> 116.02847 | Q6: =Q12/Q$11 -> 0.15755556 | R6: =IFERROR(AVERAGE(L6,M6,O6,P6,Q6),"") -> 23.315594 | S6: =IFERROR(AVERAGE(L6,M6,O6,Q6),"") -> 0.13737393
A7: 2 | B7: Total Water Consumption | C7: =VLOOKUP($B$2,'Sector Impact'!$K$4:$AA$16,A7+1,FALSE) -> Low | E7: Medium | K7: Water Consumption/$M Sales | L7: =L13/L$11 -> #VALUE! | M7: =M13/M$11 -> 13.138996 | N7: =N13/N$11 -> #VALUE! | O7: =O13/O$11 -> #VALUE! | P7: =P13/P$11 -> 4.6084916 | Q7: =Q13/Q$11 -> #VALUE! | R7: =IFERROR(AVERAGE(M7,P7),"") -> 8.8737438 | S7: =IFERROR(AVERAGE(M7),"") -> 13.138996
A8: 3 | B8: Total Energy Consumption | C8: =VLOOKUP($B$2,'Sector Impact'!$K$4:$AA$16,A8+1,FALSE) -> High | D8: Yes | E8: Medium | F8: Yes | H8: Has actually seen an increase in consumption levels in the last 3 years | I8: No | J8: Increased focus on renewabilitiy and re-using energy | K8: Energy Consumption/$M Sales | L8: =L14/L$11 -> 27.512904 | M8: =M14/M$11 -> 26.804395 | N8: =N14/N$11 -> #VALUE! | O8: =O14/O$11 -> 30.123865 | P8: =P14/P$11 -> 1136.7613 | Q8: =Q14/Q$11 -> 35.037626 | R8: =IFERROR(AVERAGE(L8,M8,O8,P8,Q8),"") -> 251.24801 | S8: =IFERROR(AVERAGE(L8,M8,O8,Q8),"") -> 29.869698
A9: 4 | B9: Waste Management | C9: =VLOOKUP($B$2,'Sector Impact'!$K$4:$AA$16,A9+1,FALSE) -> Low | H9: No improvement but rather an increase in waste by double, however they have roughly 20% of that waste being recycled | I9: They don't actively have a target/goal byt are commited to implementing the circular economy | K9: Waste Production/$M Sales | L9: =L15/L$11 -> 0.012971949 | M9: =M15/M$11 -> 0.15803202 | N9: =N15/N$11 -> #VALUE! | O9: =O15/O$11 -> #VALUE! | P9: =P15/P$11 -> 4.7462032 | Q9: =Q15/Q$11 -> #VALUE! | R9: =IFERROR(AVERAGE(L9,M9,P9),"") -> 1.6390691 | S9: =IFERROR(AVERAGE(L9,M9),"") -> 0.085501986
A10: 5 | B10: Land Degradation/Deforestation/Biodiversity loss/Animal sufering/… | C10: =VLOOKUP($B$2,'Sector Impact'!$K$4:$AA$16,A10+1,FALSE) -> Low | K10: Inputs
B11: Social | K11: Net Sales ($M) | L11: 5172.7 | M11: =Peers!D11 -> 7207.4 | N11: =Peers!E11 -> 2847.59 | O11: =Peers!F11 -> 2389.7 | P11: 51557 | Q11: =Peers!H11 -> 1758.11
A12: 6 | B12: Employee Turnover % | C12: =VLOOKUP($B$2,'Sector Impact'!$K$4:$AA$16,A12+1,FALSE) -> Low | H12: No improvement but rather saw an increase from 9% to 12% since 2020 | I12: No | K12: CO2 Emissions Total (Tonnes) | L12: 1205.6 | M12: 873.6 | N12: N/A | O12: 90 | P12: 5982080 | Q12: 277
A13: 7 | B13: Salaries & Compensation | C13: =VLOOKUP($B$2,'Sector Impact'!$K$4:$AA$16,A13+1,FALSE) -> Low | H13: Hasn't seen the best improvement and doesn't have the best of average and median salaries in their industry | I13: No | K13: Water Consumption Total (Cubic Meters) | L13: N/A | M13: 94698 | N13: N/A | O13: N/A | P13: 237600 | Q13: N/A
A14: 8 | B14: Reputation | C14: =VLOOKUP($B$2,'Sector Impact'!$K$4:$AA$16,A14+1,FALSE) -> Low | H14: Was recognized as one of the best places to work in 2023 in the United States of America | I14: No specific goals, but are focused on making sure employees are heard and happy | K14: Energy Consumption Total (Gigajoules) | L14: 142316 | M14: 193190 | N14: N/A | O14: 71987 | P14: 58608000 | Q14: 61600
A15: 9 | B15: Discrimination Events | C15: =VLOOKUP($B$2,'Sector Impact'!$K$4:$AA$16,A15+1,FALSE) -> Low | F15: Yes | K15: Waste Production Total (Tonnes) | L15: 67.1 | M15: 1139 | N15: N/A | O15: N/A | P15: 244700 | Q15: N/A
A16: 10 | B16: Work Safety | C16: =VLOOKUP($B$2,'Sector Impact'!$K$4:$AA$16,A16+1,FALSE) -> High | D16: Yes | E16: "Best in class" | F16: Yes | H16: No | I16: No | J16: Have safeguards implemented, improvements over time haven't really been visible because they already excel in the work safety aspect | K16: ESG Scores
A17: 11 | B17: Damage to consumer health | C17: =VLOOKUP($B$2,'Sector Impact'!$K$4:$AA$16,A17+1,FALSE) -> Low | H17: No | I17: No | K17: Refinitiv | L17: 58 | M17: 48 | N17: 27 | O17: 70 | P17: 83 | Q17: 34
A18: 12 | B18: PXP? | C18: =VLOOKUP($B$2,'Sector Impact'!$K$4:$AA$16,A18+1,FALSE) -> Low | K18: Sustainalytics | L18: 18.9 | M18: 13.9 | N18: 18.2 | O18: 18.1 | P18: 13.9 | Q18: 18.3
A19: 13 | B19: Supply chain | C19: =VLOOKUP($B$2,'Sector Impact'!$K$4:$AA$16,A19+1,FALSE) -> Low | H19: No | I19: No | K19: ISS | L19: C | M19: C+ | N19: C | O19: C+ | P19: B- | Q19: C-
A20: 14 | B20: Community involvement | C20: =VLOOKUP($B$2,'Sector Impact'!$K$4:$AA$16,A20+1,FALSE) -> Low | K20: CDP | L20: B- | M20: A | N20: F | O20: D- | P20: A | Q20: Not Scored
A21: 15 | B21: Public Sector | C21: =VLOOKUP($B$2,'Sector Impact'!$K$4:$AA$16,A21+1,FALSE) -> Medium | D21: Yes | E21: "Villain" | H21: A lot of controversy regarding decisions or actions influenced by governments recently | I21: No | J21: Whistleblower lawsuit in 2019 regarding the sale of chinese equipment to the governement without disclosure, also involved in scandel regarding the use of equipment by chinese government for cyberattacks
A22: 16 | B22: Litigation | C22: =VLOOKUP($B$2,'Sector Impact'!$K$4:$AA$16,A22+1,FALSE) -> Very High | D22: No | E22: Medium | F22: No | H22: Had a whistleblower lawsuit in 2019, has a current court case regarding improper use of patented technology | I22: No | J22: CEO also being sued which isn't good for company image, despite not really being related about Fortinet
B23: Corporate Governance | K23: PARAMETERS
A24: 17 | B24: Diversity (Gender, Age, Industry, Region) | E24: Medium | F24: Yes | H24: Small increase in diversity between 2020-2022 | I24: Partnered with Women in Cybersecurity (WiCyS). Goal is to train 1 Million women by 2026 | J24: Increase in % of women employees and managers in last 4 years, however reduced number of women directors from 3 to 2 recently, have a 25% of board members female (roughly the average in the industry) | K24: IMPACT | L24: RANKING | M24: MITIGATION PLAN | O24: TRAFFIC
A25: 18 | B25: % Independence | E25: "Best in class" | F25: Yes | H25: Have always had about the same % of independent directors within the board | I25: No | J25: Decrease in board by 1 independent member, but high % of independence amongst board of directors | K25: Low | L25: "Best in class" | M25: Is there evidence of a plan/program ?
A26: 19 | B26: average time as independent directors | E26: Medium | F26: Yes | H26: 4/8 directors within the 3-7 year tenure | I26: no | J26: Out of the 4/8 not within the 3-7 year tenure, 3 have been 10+ years | K26: Medium | L26: Medium High
A27: 20 | B27: Recent departures of directors / C-level executives? | E27: Medium | F27: Yes | H27: One departure over last two years | I27: No | J27: No major reason/no scndal behind departure | K27: High | L27: Medium
A28: 21 | B28: CEO/Chairman duality | E28: "Best in class" | F28: No | H28: Stayed the same | I28: No | J28: Co-Founder has remained CEO and Chairman since the foundation of Fortinet | K28: Very high | L28: "Villain"
A29: 22 | B29: Transparency (ESG, segments, acquisitions, other) | E29: Medium High | F29: Yes | H29: Disclose a lot of information | I29: No | J29: Fortinet website has a page on all board members with specific information on each individual
A30: 23 | B30: Time taken to report after the end of the quarter / year | E30: Medium High | F30: No | H30: Has always remained withing the 1.5-2 month disclosure period | I30: No | J30: Time taken to report has been consistent, always report the 10-K within the 60 day limit set by the SEC
A31: 24 | B31: Additional participation of the CEO in other boards or excessive participation of Ch. | E31: Medium High | F31: No | H31: No | I31: No
A32: 25 | B32: Audit / Consulting | D32: Yes | E32: "Best in class" | F32: Yes | H32: Has remained at a high level for the last 5 years | I32: No | J32: Have 100% independent comittie and consistent auditing happening
A33: 26 | B33: ESG-compensation related | D33: Yes | E33: "Villain" | F33: No | H33: Haven't done much in the past | I33: Have a decarbonization plan in developing stages however only scheduled for validation by 2024 | J33: Their new headquarters used 30% less of energy than normal buildings in production and the new site only use 100% renewable energy
A34: 27 | B34: Management compensation schemes | D34: Yes | E34: Medium High | F34: No | H34: Has almost tripled since 2018 | I34: No | J34: Has decreased in relation to revenue since 2018, depite a 2.5x increase in total senior executive compensation

Sheet DCF
A1: VALUATION MODEL
G3: Short Term | K3: Long Term
A4: Section | B4: Line # | C4: ITEM | D4: 2020 (Real) | E4: 2021 (Real) | F4: 2022 (Real) | G4: 2023 | H4: =G4+1 -> 2024 | I4: =H4+1 -> 2025 | J4: =I4+1 -> 2026 | K4: =J4+1 -> 2027 | L4: =K4+1 -> 2028 | M4: =L4+1 -> 2029 | N4: =M4+1 -> 2030 | O4: =N4+1 -> 2031 | ... AF4: =AE4+1 -> 2048
A5: INCOME STATEMENT | B5: 1 | C5: Growth | D5: ='Fin. Data'!E6 -> 0.19944521 | E5: =+E6/D6-1 -> 0.2882362 | F5: =+F6/E6-1 -> 0.32170427 | G5: =+G6/F6-1 -> 0.1998687 | H5: =+H6/G6-1 -> 0.18433686 | I5: =+I6/H6-1 -> 0.18420727 | J5: =+J6/I6-1 -> 0.18420727 | K5: =+K6/J6-1 -> 0.18420727 | L5: =+L6/K6-1 -> 0.137725 | M5: =+M6/L6-1 -> 0.137725 | N5: 0.137725 | O5: =Assumptions!AA95 -> 0.137725 | P5: =Assumptions!AB95 -> 0.137725 | Q5: =Assumptions!AC95 -> 0.13 | R5: =Assumptions!AD95 -> 0.13 | S5: =Assumptions!AE95 -> 0.13 | T5: =Assumptions!AF95 -> 0.12 | U5: =Assumptions!AG95 -> 0.11 | V5: =Assumptions!AH95 -> 0.11 | ... AF5: =Assumptions!AR95 -> 0.06
B6: 2 | C6: Revenues/Sales | D6: =Inputs!E6 -> 2594.4 | E6: =Inputs!D6 -> 3342.2 | F6: =Inputs!C6 -> 4417.4 | G6: 5300.3 | H6: =Assumptions!T96 -> 6277.3406 | I6: =Assumptions!U96 -> 7433.6724 | J6: =Assumptions!V96 -> 8803.0089 | K6: =Assumptions!W96 -> 10424.587 | L6: =Assumptions!X96 -> 11860.313 | M6: =Assumptions!Y96 -> 13493.775 | N6: =Assumptions!Z96 -> 15352.205 | O6: =N6*(1+O5) -> 17466.588 | P6: =O6*(1+P5) -> 19872.174 | Q6: =P6*(1+Q5) -> 22455.556 | R6: =Q6*(1+R5) -> 25374.778 | S6: =R6*(1+S5) -> 28673.5 | T6: =S6*(1+T5) -> 32114.32 | U6: =T6*(1+U5) -> 35646.895 | V6: =U6*(1+V5) -> 39568.053 | ... AF6: =AE6*(1+AF5) -> 86148.509
B7: 3 | C7: EBIT/Operating Margin | D7: =D8/D6 -> 0.20332254 | E7: =E8/E6 -> 0.19460236 | F7: =F8/F6 -> 0.21949563 | G7: =Assumptions!S113 -> 0.21 | H7: =Assumptions!T113 -> 0.2 | I7: =Assumptions!U113 -> 0.205 | J7: =Assumptions!V113 -> 0.21 | K7: =Assumptions!W113 -> 0.215 | L7: =Assumptions!X113 -> 0.22 | M7: =Assumptions!Y113 -> 0.225 | N7: =Assumptions!Z113 -> 0.23 | O7: 0.21394157 | P7: 0.21539291 | Q7: 0.21685411 | R7: 0.21832521 | S7: 0.2198063 | T7: 0.22129743 | U7: 0.22279868 | V7: 0.22431011 | W7: 0.2258318 | X7: 0.2273638 | Y7: 0.22890621 | Z7: 0.23045907 | AA7: 0.23202247 | AB7: 0.23359647 | AC7: 0.23518116 | AD7: 0.23677659 | AE7: 0.23838285 | AF7: 0.24
B8: 4 | C8: EBIT | D8: ='Fin. Data'!E11 -> 527.5 | E8: ='Fin. Data'!D11 -> 650.4 | F8: ='Fin. Data'!C11 -> 969.6 | G8: =G7*G6 -> 1113.063 | H8: =H7*H6 -> 1255.4681 | I8: =I7*I6 -> 1523.9028 | J8: =J7*J6 -> 1848.6319 | K8: =K7*K6 -> 2241.2862 | L8: =L7*L6 -> 2609.269 | M8: =M7*M6 -> 3036.0994 | N8: =N7*N6 -> 3531.0072 | ... AF8: =AF7*AF6 -> 20675.642
B9: 5a | C9: (Dep) | D9: -55.5 | E9: -65.9 | F9: -81 | G9: -91.2 | H9: =$D$53*DCF!G40 -> -133.9965 | I9: =$D$53*DCF!H40 -> -167.64304 | J9: =$D$53*DCF!I40 -> -205.10875 | K9: =$E$53*DCF!J40 -> -154.602 | L9: =$E$53*DCF!K40 -> -188.48191 | M9: =$E$53*DCF!L40 -> -227.02792 | N9: =$E$53*DCF!M40 -> -270.88269 | O9: =$E$53*DCF!N40 -> -320.77736 | P9: =$E$53*DCF!O40 -> -377.54377 | Q9: =$E$53*DCF!P40 -> -442.12834 | R9: =$E$53*DCF!Q40 -> -515.10889 | ... AF9: =$E$53*DCF!AE40 -> -2842.5274 | AG9: =SUM(D9:AF9) -> -24745.652
B10: 5b | C10: Amort | D10: -13.3 | E10: -18.5 | F10: -23.3 | G10: =F38*$D$54 -> -21.352 | H10: =G38*$D$54 -> -24.98184 | I10: =H38*$D$54 -> -29.228753 | J10: =I38*$D$54 -> -34.197641 | K10: =J38*$E$54 -> -32.950433 | L10: =K38*$E$54 -> -37.563493 | M10: =L38*$E$54 -> -42.822382 | N10: =M38*$E$54 -> -48.817516 | O10: =N38*$E$54 -> -55.651968 | P10: =O38*$E$54 -> -63.443244 | Q10: =P38*$E$54 -> -72.325298 | R10: =Q38*$E$54 -> -82.450839 | ... AF10: =AE38*$E$54 -> -516.25349
B11: 5c | C11: (Stock based compensation) | D11: -191.7 | E11: -207.9 | F11: -217.3 | G11: =-G6*$D$55 -> -265.015 | H11: =-H6*$D$55 -> -313.86703 | I11: =-I6*$D$55 -> -371.68362 | J11: =-J6*$D$55 -> -440.15045 | K11: =-K6*$D$55 -> -521.22936 | L11: =-L6*$D$55 -> -593.01567 | M11: =-M6*$D$55 -> -674.68876 | N11: =-N6*$D$55 -> -767.61026 | ... AH11: =-AH6*$D$55 -> 0 | AI11: jk
B12: 6 | C12: EBITDA | D12: =D8-D9-D10 -> 596.3 | E12: =E8-E9-E10 -> 734.8 | F12: =F8-F9-F10 -> 1073.9 | G12: =G8-G9-G10 -> 1225.615 | H12: =H8-H9-H10 -> 1414.4465 | I12: =I8-I9-I10 -> 1720.7746 | J12: =J8-J9-J10 -> 2087.9383 | K12: =K8-K9-K10 -> 2428.8387 | ... AF12: =AF8-AF9-AF10 -> 24034.423
B13: 7 | C13: (Net financing cost) | D13: ='Fin. Data'!E14 -> 12.2 | E13: ='Fin. Data'!D14 -> -18.6 | F13: ='Fin. Data'!C14 -> -5.2 | G13: =F43*$D$58-F44*$D$57 -> 3.43518 | H13: =G43*$D$58-G44*$D$57 -> -21.327643 | I13: =H43*$D$58-H44*$D$57 -> -22.296696 | J13: =I43*$D$58-I44*$D$57 -> -34.973551 | K13: =J43*$E$58-J44*$E$57 -> -60.769532 | L13: =K43*$E$58-K44*$E$57 -> -40.415322 | M13: =L43*$E$58-L44*$E$57 -> -47.77687 | N13: =M43*$E$58-M44*$E$57 -> -54.238686 | O13: =N43*$E$58-N44*$E$57 -> -59.457654 | P13: =O43*$E$58-O44*$E$57 -> -63.758795 | Q13: =P43*$E$58-P44*$E$57 -> -70.84761 | R13: =Q43*$E$58-Q44*$E$57 -> -77.573734 | ... AF13: =AE43*$E$58-AE44*$E$57 -> -356.19185
B14: 8 | C14: Other income/(cost) | D14: ='Fin. Data'!E15 -> 2 | E14: ='Fin. Data'!D15 -> -10.9 | F14: ='Fin. Data'!C15 -> -76.3 | G14: =AVERAGE(D14:F14)*(1+G5) -> -34.076271 | H14: =AVERAGE(E14:G14)*(1+H5) -> -47.877319 | I14: =AVERAGE(F14:H14)*(1+I5) -> -62.468351 | J14: =AVERAGE(G14:I14)*(1+J5) -> -57.008504 | K14: =AVERAGE(H14:J14)*(1+K5) -> -66.060677 | L14: =AVERAGE(I14:K14)*(1+L5) -> -70.363563 | M14: =AVERAGE(J14:L14)*(1+M5) -> -73.357756 | N14: =AVERAGE(K14:M14)*(1+N5) -> -79.558074 | ... AF14: =AVERAGE(AC14:AE14)*(1+AF5) -> -184.99701
B15: 9 | C15: Earnings before taxes | D15: =D8+D13+D14 -> 541.7 | E15: =E8+E13+E14 -> 620.9 | F15: =F8+F13+F14 -> 888.1 | G15: =G8+G13+G14 -> 1082.4219 | H15: =H8+H13+H14 -> 1186.2632 | I15: =I8+I13+I14 -> 1439.1378 | J15: =J8+J13+J14 -> 1756.6498 | K15: =K8+K13+K14 -> 2114.456 | ... AF15: =AF8+AF13+AF14 -> 20134.453
B16: 10 | C16: (Income tax) | D16: ='Fin. Data'!E21 -> -53.2 | E16: ='Fin. Data'!D21 -> -14.1 | F16: ='Fin. Data'!C21 -> -30.8 | G16: =-(1*$D$56)*G15 -> -81.431266 | H16: =-(1*$D$56)*H15 -> -89.243308 | I16: =-(1*$D$56)*I15 -> -108.26722 | J16: =-(1*$D$56)*J15 -> -132.15385 | K16: =-(1*$E$56)*K15 -> -482.8039 | L16: =-(1*$E$56)*L15 -> -570.49223 | M16: =-(1*$E$56)*M15 -> -665.5879 | N16: =-(1*$E$56)*N15 -> -775.70137 | O16: =-(1*$E$56)*O15 -> -820.33722 | P16: =-(1*$E$56)*P15 -> -942.21477 | Q16: =-(1*$E$56)*Q15 -> -1073.8427 | R16: =-(1*$E$56)*R15 -> -1223.9797 | ... AF16: =-(1*$E$56)*AF15 -> -4597.3964
B17: 11 | C17: Net income | D17: ='Fin. Data'!E23 -> 488.5 | E17: ='Fin. Data'!D23 -> 606.8 | F17: ='Fin. Data'!C23 -> 857.3 | G17: =G16+G15 -> 1000.9906 | H17: =H16+H15 -> 1097.0199 | I17: =I16+I15 -> 1330.8706 | J17: =J16+J15 -> 1624.496 | K17: =K16+K15 -> 1631.6521 | L17: =L16+L15 -> 1927.9978 | M17: =M16+M15 -> 2249.3769 | N17: =N16+N15 -> 2621.5091 | ... AF17: =AF16+AF15 -> 15537.057
A19: CASH FLOW STATEMENT | B19: 12 | C19: Operating cash flows before WK | D19: =Inputs!E59-D21-D20 -> 1085.4 | E19: =Inputs!D59-DCF!E21-E20 -> 1305.2 | F19: =Inputs!C59-DCF!F20-DCF!F21 -> 1714.9 | G19: =G17-G10-G9-G11 -> 1378.5576 | H19: =H17-H10-H9-H11 -> 1569.8652 | I19: =I17-I10-I9-I11 -> 1899.426 | J19: =J17-J10-J9-J11 -> 2303.9528 | K19: =K17-K10-K9-K11 -> 2340.4339 | L19: =L17-L10-L9-L11 -> 2747.0589 | M19: =M17-M10-M9-M11 -> 3193.9159 | N19: =N17-N10-N9-N11 -> 3708.8196 | ... AF19: =AF17-AF10-AF9-AF11 -> 23203.263
B20: 13 | C20: (Stock-based compensation) | D20: -191.7 | E20: -207.9 | F20: -217.3 | G20: =G11 -> -265.015 | H20: =H11 -> -313.86703 | I20: =I11 -> -371.68362 | J20: =J11 -> -440.15045 | K20: =K11 -> -521.22936 | L20: =L11 -> -593.01567 | M20: =M11 -> -674.68876 | N20: =N11 -> -767.61026 | ... AF20: =AF11 -> -4307.4254
B21: 14 | C21: (Working Capital Flows) | D21: =Inputs!E62 -> 190 | E21: =Inputs!D62 -> 402.4 | F21: =Inputs!C62 -> 233 | G21: =$D$60*(G6-F6) -> 220.725 | H21: =$D$60*(H6-G6) -> 244.26016 | I21: =$D$60*(I6-H6) -> 289.08295 | J21: =$D$60*(J6-I6) -> 342.33413 | K21: =$E$60*(K6-J6) -> 324.31565 | L21: =$E$60*(L6-K6) -> 287.14525 | M21: =$E$60*(M6-L6) -> 326.69233 | N21: =$E$60*(N6-M6) -> 371.68604 | O21: =$E$60*(O6-N6) -> 422.87649 | P21: =$E$60*(P6-O6) -> 481.11716 | Q21: =$E$60*(Q6-P6) -> 516.67651 | R21: =$E$60*(R6-Q6) -> 583.84446 | ... AF21: =$E$60*(AF6-AE6) -> 975.26614
B22: 15 | C22: -Total Operating Cash Flow | D22: =D19+D20+D21 -> 1083.7 | E22: =E19+E20+E21 -> 1499.7 | F22: =F19+F20+F21 -> 1730.6 | G22: =G19+G20+G21 -> 1334.2676 | H22: =H19+H20+H21 -> 1500.2584 | I22: =I19+I20+I21 -> 1816.8253 | J22: =J19+J20+J21 -> 2206.1365 | K22: =K19+K20+K21 -> 2143.5202 | ... AF22: =AF19+AF20+AF21 -> 19871.104
B23: 16 | C23: (CAPEX) | D23: ='Fin. Data'!E32 -> -125.9 | E23: ='Fin. Data'!D32 -> -295.9 | F23: ='Fin. Data'!C32 -> -281.2 | G23: =G6*Assumptions!D85 -> -399.95623 | H23: =H6*Assumptions!E85 -> -420.58182 | I23: =I6*Assumptions!F85 -> -468.32136 | J23: =J6*Assumptions!G85 -> -528.18054 | K23: =K6*$E$62 -> -677.59817 | L23: =L6*$E$62 -> -770.92037 | M23: =M6*$E$62 -> -877.09538 | N23: =N6*$E$62 -> -997.89334 | O23: =O6*$E$62 -> -1135.3282 | P23: =P6*$E$62 -> -1291.6913 | Q23: =Q6*$E$62 -> -1459.6111 | R23: =R6*$E$62 -> -1649.3606 | ... AF23: =AF6*$E$62 -> -5599.6531 | AG23: =SUM(D23:AF23) -> -61878.201
B24: 17 | C24: Adq | D24: =Inputs!E66 -> 53.1 | E24: ='Fin. Data'!D33 -> -1029.2 | F24: ='Fin. Data'!C33 -> 1045.1 | G24: =G6*$D$63 -> -303.7623 | H24: =H6*$D$63 -> -359.75689 | I24: =I6*$D$63 -> -426.02672 | J24: =J6*$D$63 -> -504.50394 | K24: =K6*$E$63 -> -552.50312 | L24: =L6*$E$63 -> -628.59661 | M24: =M6*$E$63 -> -715.17008 | N24: =N6*$E$63 -> -813.66688 | O24: =O6*$E$63 -> -925.72915 | P24: =P6*$E$63 -> -1053.2252 | Q24: =Q6*$E$63 -> -1190.1445 | R24: =R6*$E$63 -> -1344.8633 | ... AF24: =AF6*$E$63 -> -4565.871 | AH24: =AG9-AG23 -> 37132.549
B25: 18 | C25: (Other investing flows) | D25: =Inputs!E67 -> 0 | E25: =Inputs!D67 -> 0 | F25: =Inputs!C67 -> 0 | G25: =(1+G5)*AVERAGE(D25:F25) -> 0 | H25: =(1+H5)*AVERAGE(E25:G25) -> 0 | I25: =(1+I5)*AVERAGE(F25:H25) -> 0 | J25: =(1+J5)*AVERAGE(G25:I25) -> 0 | K25: =(1+K5)*AVERAGE(H25:J25) -> 0 | L25: =(1+L5)*AVERAGE(I25:K25) -> 0 | M25: =(1+M5)*AVERAGE(J25:L25) -> 0 | N25: =(1+N5)*AVERAGE(K25:M25) -> 0 | ... AF25: =(1+AF5)*AVERAGE(AC25:AE25) -> 0
B26: 19 | C26: -Total Investing Flows | D26: =D23+D24+D25 -> -72.8 | E26: =E23+E24+E25 -> -1325.1 | F26: =F23+F24+F25 -> 763.9 | G26: =G23+G24+G25 -> -703.71853 | H26: =H23+H24+H25 -> -780.33871 | I26: =I23+I24+I25 -> -894.34808 | J26: =J23+J24+J25 -> -1032.6845 | K26: =K23+K24+K25 -> -1230.1013 | ... AF26: =AF23+AF24+AF25 -> -10165.524
B27: 20 | C27: (Flows related to leases) | D27: =Inputs!E71+Inputs!E72 -> 0 | E27: =Inputs!D71+Inputs!D72 -> 0.1 | F27: =Inputs!C71+Inputs!C72 -> -0.7 | G27: 0 | H27: 0 | I27: 0 | J27: 0 | K27: 0 | L27: 0 | M27: 0 | N27: 0 | O27: 0 | P27: 0 | Q27: 0 | R27: 0 | S27: 0 | T27: 0 | U27: 0 | V27: 0 | W27: 0 | X27: 0 | Y27: 0 | Z27: 0 | AA27: 0 | AB27: 0 | AC27: 0 | AD27: 0 | AE27: 0 | AF27: 0
B28: 21 | C28: Flows related to debt | D28: =+SUM(Inputs!E69:E70) -> 0 | E28: =+SUM(Inputs!D69:D70) -> 989.4 | F28: =+SUM(Inputs!C69:C70) -> 0 | G28: =G44-F44 -> 16.9535 | H28: =H44-G44 -> 169.94832 | I28: =I44-H44 -> 275.69536 | J28: =J44-I44 -> 330.44726 | K28: =K44-J44 -> -786.16704 | L28: =L44-K44 -> 182.91406 | M28: =M44-L44 -> 211.78591 | N28: =N44-M44 -> 245.14097 | ... AF28: =AF44-AE44 -> 733.17736
B29: 22 | C29: (Repurchases)/Issuance of stock | D29: ='Fin. Data'!E28 -> -1080.1 | E29: ='Fin. Data'!D28 -> -741.8 | F29: ='Fin. Data'!C28 -> -1991.2 | G29: =-Assumptions!I96 -> -1050 | H29: =-Assumptions!I97 -> -480 | I29: =-I17*D65 -> -902.33025 | J29: =-J17*D65 -> -1101.4083 | K29: =-K17*$E$65 -> -734.24346 | L29: =-L17*$E$65 -> -867.59903 | M29: =-M17*$E$65 -> -1012.2196 | N29: =-N17*$E$65 -> -1179.6791 | O29: =-O17*$E$65 -> -1247.5609 | P29: =-P17*$E$65 -> -1432.911 | Q29: =-Q17*$E$65 -> -1633.0895 | R29: =-R17*Assumptions!$O$97 -> -2275.0644 | S29: =-S17*Assumptions!$O$97 -> -2587.4539 | T29: =-T17*Assumptions!$O$97 -> -2917.3836 | U29: =-U17*Assumptions!$O$97 -> -3259.9146 | V29: =-V17*Assumptions!$O$97 -> -3643.2051 | W29: =-W17*Assumptions!$O$97 -> -3998.1621 | X29: =-X17*Assumptions!$O$97 -> -4387.3729 | Y29: =-Y17*Assumptions!$O$97 -> -4816.1893 | ... AF29: =-AF17*Assumptions!$O$97 -> -8545.3813
B30: 23 | C30: (Dividends) | D30: ='Fin. Data'!E27 -> 0 | E30: ='Fin. Data'!D27 -> 0 | F30: ='Fin. Data'!C27 -> 0 | G30: =-$D$64*G17 -> 0 | H30: =-$D$64*H17 -> 0 | I30: =-$D$64*I17 -> 0 | J30: =-$D$64*J17 -> 0 | K30: =-$E$64*K17 -> 0 | L30: =-$E$64*L17 -> 0 | M30: =-$E$64*M17 -> 0 | N30: =-$E$64*N17 -> 0 | O30: =-$E$64*O17 -> 0 | P30: =-$E$64*P17 -> 0 | Q30: =-$E$64*Q17 -> 0 | R30: =-$E$64*R17 -> 0 | ... AF30: =-$E$64*AF17 -> 0
B31: 24 | C31: Other financing flows | D31: =Inputs!E75 -> -91.5 | E31: =Inputs!D75 -> -164.9 | F31: =Inputs!C75 -> -138.4 | G31: =(1+G5)*AVERAGE(D31:F31) -> -157.90272 | H31: =(1+H5)*AVERAGE(E31:G31) -> -182.07313 | I31: =(1+I5)*AVERAGE(F31:H31) -> -188.83205 | J31: =(1+J5)*AVERAGE(G31:I31) -> -208.73939 | K31: =(1+K5)*AVERAGE(H31:J31) -> -228.80644 | L31: =(1+L5)*AVERAGE(I31:K31) -> -237.54859 | M31: =(1+M5)*AVERAGE(J31:L31) -> -256.02393 | N31: =(1+N5)*AVERAGE(K31:M31) -> -273.9562 | ... AF31: =(1+AF5)*AVERAGE(AC31:AE31) -> -637.82896
B32: 25 | C32: -Total Financing flows | D32: =D27+D28+D29+D30+D31 -> -1171.6 | E32: =E27+E28+E29+E30+E31 -> 82.8 | F32: =F27+F28+F29+F30+F31 -> -2130.3 | G32: =G27+G28+G29+G30+G31 -> -1190.9492 | H32: =H27+H28+H29+H30+H31 -> -492.12481 | I32: =I27+I28+I29+I30+I31 -> -815.46694 | J32: =J27+J28+J29+J30+J31 -> -979.70039 | K32: =K27+K28+K29+K30+K31 -> -1749.2169 | ... AF32: =AF27+AF28+AF29+AF30+AF31 -> -8450.0329
A34: SUMMARY | B34: 26 | C34: Cash before shareholder returns | D34: =D22+D26+D27+D28+D31 -> 919.4 | E34: =E22+E26+E27+E28+E31 -> 999.2 | F34: =F22+F26+F27+F28+F31 -> 2355.4 | G34: =G22+G26+G27+G28+G31 -> 489.59989 | H34: =H22+H26+H27+H28+H31 -> 707.79484 | I34: =I22+I26+I27+I28+I31 -> 1009.3405 | J34: =J22+J26+J27+J28+J31 -> 1295.1599 | K34: =K22+K26+K27+K28+K31 -> -101.55454 | ... AF34: =AF22+AF26+AF27+AF28+AF31 -> 9800.9283
B35: 27 | C35: Returns to shareholders | D35: =-1*(D29+D30) -> 1080.1 | E35: =-1*(E29+E30) -> 741.8 | F35: =-1*(F29+F30) -> 1991.2 | G35: =-1*(G29+G30) -> 1050 | H35: =-1*(H29+H30) -> 480 | I35: =-1*(I29+I30) -> 902.33025 | J35: =-1*(J29+J30) -> 1101.4083 | K35: =-1*(K29+K30) -> 734.24346 | ... AF35: =-1*(AF29+AF30) -> 8545.3813
B36: 28 | C36: Excess cash acumulation | D36: =D34-D35 -> -160.7 | E36: =E34-E35 -> 257.4 | F36: =F34-F35 -> 364.2 | G36: =G34-G35 -> -560.40011 | H36: =H34-H35 -> 227.79484 | I36: =I34-I35 -> 107.0103 | J36: =J34-J35 -> 193.75163 | K36: =K34-K35 -> -835.79801 | ... AF36: =AF34-AF35 -> 1255.547
A38: BALANCE SHEET | B38: 29 | C38: Intangible assets | D38: 84.1 | E38: 115.3 | F38: 125.6 | G38: =+F38+(-G10) -> 146.952 | H38: =+G38+(-H10) -> 171.93384 | I38: =+H38+(-I10) -> 201.16259 | J38: =+I38+(-J10) -> 235.36023 | K38: =+J38+(-K10) -> 268.31067 | L38: =+K38+(-L10) -> 305.87416 | M38: =+L38+(-M10) -> 348.69654 | N38: =+M38+(-N10) -> 397.51406 | ... AF38: =+AE38+(-AF10) -> 4203.7784 | AG38: =SUM(G38:AF38) -> 33069.671
B39: 30 | C39: Accumulated amortization | D39: 52.5 | E39: 51.7 | F39: 69.6 | G39: =F39-G10 -> 90.952 | H39: =G39-H10 -> 115.93384 | I39: =H39-I10 -> 145.16259 | J39: =I39-J10 -> 179.36023 | K39: =J39-K10 -> 212.31067 | L39: =K39-L10 -> 249.87416 | M39: =L39-M10 -> 292.69654 | N39: =M39-N10 -> 341.51406 | ... AF39: =AE39-AF10 -> 4147.7784 | AG39: =SUM(G39:AF39) -> 31613.671
B40: 31 | C40: PPE+Right of use Assets | D40: 669.8 | E40: 964.4 | F40: 1275 | G40: =F40+(-G23) -> 1674.9562 | H40: =G40+(-H23) -> 2095.5381 | I40: =H40+(-I23) -> 2563.8594 | J40: =I40+(-J23) -> 3092.04 | K40: =J40+(-K23) -> 3769.6381 | L40: =K40+(-L23) -> 4540.5585 | M40: =L40+(-M23) -> 5417.6539 | N40: =M40+(-N23) -> 6415.5472 | ... AF40: =AE40+(-AF23) -> 62450.201 | AG40: =SUM(G40:AF40) -> 547690.64
B41: 32 | C41: Accumulated depreciation | D41: 172.5 | E41: 211.7 | F41: 280.2 | G41: =F41-G9 -> 371.4 | H41: =G41-H9 -> 505.3965 | I41: =H41-I9 -> 673.03954 | J41: =I41-J9 -> 878.1483 | K41: =J41-K9 -> 1032.7503 | L41: =K41-L9 -> 1221.2322 | M41: =L41-M9 -> 1448.2601 | N41: =M41-N9 -> 1719.1428 | ... AF41: =AE41-AF9 -> 24823.452 | AG41: =SUM(G41:AF41) -> 187702.33
A43: CASH & DEBT & DISCOUNTING | B43: 33 | C43: Ending cash balance | D43: ='Fin. Data'!E39 -> 1061.8 | E43: =E36+D43 -> 1319.2 | F43: =F36+E43 -> 1683.4 | G43: =G36+F43 -> 1122.9999 | H43: =H36+G43 -> 1350.7947 | I43: =I36+H43 -> 1457.805 | J43: =J36+I43 -> 1651.5567 | K43: =K36+J43 -> 815.75864 | L43: =L36+K43 -> 935.19659 | ... AF43: =AF36+AE43 -> 9255.6069
B44: 34 | C44: Total Debt | D44: ='Fin. Data'!E58 -> 53.1 | E44: ='Fin. Data'!D58 -> 1055.2 | F44: ='Fin. Data'!C58 -> 1086.1 | G44: =G12*$D$68 -> 1103.0535 | H44: =H12*$D$68 -> 1273.0018 | I44: =I12*$D$68 -> 1548.6972 | J44: =J12*$D$68 -> 1879.1444 | K44: =K12*$E$68 -> 1092.9774 | L44: =L12*$E$68 -> 1275.8915 | M44: =M12*$E$68 -> 1487.6774 | N44: =N12*$E$68 -> 1732.8183 | O44: =O12*$E$68 -> 1850.9663 | P44: =P12*$E$68 -> 2124.5906 | Q44: =Q12*$E$68 -> 2422.8149 | R44: =R12*$E$68 -> 2761.8811 | ... AF44: =AF12*$E$68 -> 10815.49
B45: 35 | C45: Discount factor | F45: =1/((1+$F$50)^G50) -> 1 | G45: =1/((1+$F$50)^G49) -> 0.89884166 | H45: =1/((1+$F$50)^H49) -> 0.80791633 | I45: =1/((1+$F$50)^I49) -> 0.72618886 | J45: =1/((1+$F$50)^J49) -> 0.6527288 | K45: =1/((1+$F$50)^K49) -> 0.58669984 | L45: =1/((1+$F$50)^L49) -> 0.52735026 | M45: =1/((1+$F$50)^M49) -> 0.47400439 | N45: =1/((1+$F$50)^N49) -> 0.42605489 | ... AF45: =1/((1+$F$50)^AF49) -> 0.06248317
B46: 36 | C46: DF + 0.1% | E46: +0.1% | F46: =1/((1+$F$50+0.001)^G50) -> 1 | G46: =1/((1+$F$50+0.001)^G49) -> 0.89803447 | H46: =1/((1+$F$50+0.001)^H49) -> 0.80646591 | I46: =1/((1+$F$50+0.001)^I49) -> 0.72423419 | J46: =1/((1+$F$50+0.001)^J49) -> 0.65038727 | K46: =1/((1+$F$50+0.001)^K49) -> 0.58407019 | L46: =1/((1+$F$50+0.001)^L49) -> 0.52451516 | M46: =1/((1+$F$50+0.001)^M49) -> 0.4710327 | N46: =1/((1+$F$50+0.001)^N49) -> 0.4230036 | ... AF46: =1/((1+$F$50+0.001)^AF49) -> 0.061040517
B47: 37 | C47: DF+0.5% | E47: +0.5% | F47: =1/((1+$F$50+0.005)^G50) -> 1 | G47: =1/((1+$F$50+0.005)^G49) -> 0.89482015 | H47: =1/((1+$F$50+0.005)^H49) -> 0.80070311 | I47: =1/((1+$F$50+0.005)^I49) -> 0.71648528 | J47: =1/((1+$F$50+0.005)^J49) -> 0.64112547 | K47: =1/((1+$F$50+0.005)^K49) -> 0.57369199 | L47: =1/((1+$F$50+0.005)^L49) -> 0.51335116 | M47: =1/((1+$F$50+0.005)^M49) -> 0.45935696 | N47: =1/((1+$F$50+0.005)^N49) -> 0.41104187 | ... AF47: =1/((1+$F$50+0.005)^AF49) -> 0.055607029
A49: Discount Rate | C49: Risk free rate | D49: Equity premium | E49: Firm premium | F49: Total | G49: 1 | H49: 2 | I49: 3 | J49: 4 | K49: 5 | L49: 6 | M49: 7 | N49: 8 | O49: 9 | P49: 10 | Q49: 11 | R49: 12 | S49: 13 | T49: 14 | U49: 15 | V49: 16 | W49: 17 | X49: 18 | Y49: 19 | Z49: 20 | AA49: 21 | AB49: 22 | AC49: 23 | AD49: 24 | AE49: 25 | AF49: 26
C50: =Assumptions!C52 -> 0.0423 | D50: =Assumptions!E125 -> 0.062743 | E50: =Assumptions!C135 -> 0.0075 | F50: =E50+D50+C50 -> 0.112543 | G50: 0
A52: Modelling factors | D52: Short Term | E52: Long Term | F52: Reference (line)
C53: Depreciation factor | D53: =Assumptions!L17 -> -0.08 | E53: =Assumptions!M17 -> -0.05 | F53: % PPE
C54: Amortization factor | D54: =Assumptions!L18 -> -0.17 | E54: =Assumptions!M18 -> -0.14 | F54: % IA
C55: Stock-based comp | D55: =Assumptions!L19 -> 0.05 | E55: =Assumptions!M19 -> 0.04 | F55: % revenue
C56: Tax Rate | D56: =Assumptions!L20 -> 0.075230615 | E56: =Assumptions!M20 -> 0.2283348 | F56: % (line 9)
C57: Interest Rate on debt | D57: =Assumptions!F36 -> 0.0624 | E57: =Assumptions!F37 -> 0.0631 | F57: % debt (l29)
C58: Interest Rate on cash | D58: =Assumptions!C52 -> 0.0423 | E58: 0.035 | F58: % of cash (l28)
C59: PPE+ROA | D59: - - | E59: - - | F59: Growing with capex
C60: Working capital flows | D60: 0.25 | E60: 0.2 | F60: % of change revenues (l2)
C61: Intangible Assets | D61: - - | E61: - - | F61: Growing with amortization
C62: Capex | D62: =Assumptions!L22 -> -0.066364792 | E62: =Assumptions!M22 -> -0.065 | F62: % revenue (l2)
C63: Acquisition factor | D63: =Assumptions!L23 -> -0.057310397 | E63: =Assumptions!M23 -> -0.053 | F63: % revenue (l2)
C64: Dividends | D64: =Assumptions!L24 -> 0 | E64: =Assumptions!M24 -> 0 | F64: % net income (11)
C65: Repurchases | D65: =Assumptions!L25 -> 0.678 | E65: 0.45 | F65: % net income (11)
C66: Leases | D66: =Assumptions!L26 -> 0 | E66: =Assumptions!M26 -> 0 | F66: % revenue (l2)
C67: Cash Costs for EBIT | D67: - - | E67: - - | F67: % revenue (l2)
C68: Total Debt | D68: =Assumptions!L27 -> 0.9 | E68: =Assumptions!M27 -> 0.45 | F68: % EBITDA
A70: Valuation | D70: $ millions
C71: Value of flows | D71: =SUMPRODUCT(G35:AF35,G45:AF45)+((AF43-AF44)*AF45) -> 15269.375 | E71: =D71/D73 -> 0.5671191
C72: Value of perpetuity | D72: =(AF34/(F50-AF5))*AF45 -> 11655.084 | E72: =D72/D73 -> 0.4328809
C73: Total Value | D73: =D71+D72 -> 26924.459
C74: Actual share price | D74: =OP!C20 -> 76.64
C75: Total value vs Mkt Cap | D75: =D76/D74-1 -> -0.54071498
C76: Estimated NPV per share | D76: =D73*1000000/OP!C21 -> 35.199604
A78: Sensibility | C78: Sensitivity +0.1% | D78: =(SUMPRODUCT(G35:N35,G45:N45)+((N43-N44)*AF45)+(N34/(F50+0.001-N5))*N45)*1000000/OP!C21 -> -27.959694 | E78: =D78/D76-1 -> -1.7943184
C79: Sensitivity +0.5% | D79: =(SUMPRODUCT(G35:N35,G45:N45)+((N43-N44)*N45)+(N34/(F50+0.005-N5))*N45)*1000000/OP!C21 -> -34.828243 | E79: =D79/D76-1 -> -1.9894498
A81: Notes

Sheet DCF cash flow to the firm
D5: Historical Period | H5: CAGR | J5: Projection period | AD5: CAGR
D6: 2019 | E6: 2020 | F6: 2021 | G6: 2022 | H6: (19-22) | I6: 2023 | J6: 2024 | K6: 2025 | L6: 2026 | M6: 2027 | N6: 2028 | O6: 2029 | P6: 2030 | Q6: 2031 | R6: 2032 | S6: 2033 | T6: 2034 | U6: 2035 | V6: 2036 | W6: 2037 | X6: 2038 | Y6: 2039 | Z6: 2040 | AA6: 2041 | AB6: 2042 | AC6: 2043 | AD6: (23-43)
C7: Sales | D7: 2163 | E7: 2594.4 | F7: 3342.2 | G7: 4417.4 | H7: =(G7/D7)^(1/3)-1 -> 0.26873251 | I7: 5300.3 | J7: 6277.3406 | K7: 7433.6724 | L7: 8803.0089 | M7: 10424.587 | N7: 11860.313 | O7: 13493.775 | P7: 15352.205 | Q7: 17466.588 | R7: 19872.174 | S7: 22455.556 | T7: 25374.778 | U7: 28673.5 | V7: 32114.32 | W7: 35646.895 | X7: 39568.053 | Y7: 43129.178 | Z7: 47010.804 | AA7: 51241.776 | AB7: 55853.536 | AC7: 60880.354 | AD7: =(AC7/I7)^(1/19)-1 -> 0.1371003
C8: %Growth | E8: 0.19944521 | F8: 0.2882362 | G8: 0.32170427 | I8: 0.1998687 | J8: 0.18433686 | K8: 0.18420727 | L8: 0.18420727 | M8: 0.18420727 | N8: 0.137725 | O8: 0.137725 | P8: 0.137725 | Q8: 0.137725 | R8: 0.137725 | S8: 0.13 | T8: 0.13 | U8: 0.13 | V8: 0.12 | W8: 0.11 | X8: 0.11 | Y8: 0.09 | Z8: 0.09 | AA8: 0.09 | AB8: 0.09 | AC8: 0.09
C9: EBITDA | D9: 405.7 | E9: 596.3 | F9: 734.8 | G9: 1073.9 | H9: =(G9/D9)^(1/3)-1 -> 0.3833103 | I9: 1225.615 | J9: 1414.4465 | K9: 1702.1905 | L9: 2043.9232 | M9: 2350.6543 | N9: 2708.8928 | O9: 3120.5638 | P9: 3555.2098 | Q9: 4074.9103 | R9: 4669.8643 | S9: 5317.681 | T9: 6137.5136 | U9: 6994.1867 | V9: 7904.7353 | W9: 8859.3729 | X9: 9925.7603 | Y9: 10938.278 | Z9: 12049.288 | AA9: 13268.416 | AB9: 14606.229 | AC9: 16074.337 | AD9: =(AC9/I9)^(1/19)-1 -> 0.14506588
C10: %margin | D10: 18,8% | E10: =E9/E7 -> 0.2298412 | F10: =F9/F7 -> 0.21985519 | G10: =G9/G7 -> 0.2431068 | I10: =I9/I7 -> 0.23123502 | J10: =J9/J7 -> 0.22532575 | K10: =K9/K7 -> 0.22898379 | L10: =L9/L7 -> 0.23218461 | M10: =M9/M7 -> 0.22549135 | N10: =N9/N7 -> 0.22839976 | O10: =O9/O7 -> 0.23125951 | P10: =P9/P7 -> 0.23157649 | ... AC10: =AC9/AC7 -> 0.26403159
C11: DA | E11: -55.5 | F11: -65.9 | G11: -81 | I11: -91.2 | J11: -133.9965 | K11: -167.64304 | L11: -205.10875 | M11: -154.602 | N11: -180.66347 | O11: -210.31425 | P11: -244.04869 | Q11: -282.4292 | R11: -326.09567 | S11: -375.7761 | T11: -515.10889 | U11: -597.57692 | V11: -690.7658 | W11: -795.13734 | X11: -910.98974 | Y11: -1039.5859 | Z11: -1179.7557 | AA11: -1332.5409 | AB11: -1499.0766 | AC11: -1680.6006
C12: Amort | E12: -13.3 | F12: -18.5 | G12: -23.3 | I12: -21.352 | J12: -24.98184 | K12: -29.228753 | L12: -34.197641 | M12: -32.950433 | N12: -37.563493 | O12: -42.822382 | P12: -48.817516 | Q12: -55.651968 | R12: -63.443244 | S12: -72.325298 | T12: -82.450839 | U12: -93.993957 | V12: -107.15311 | W12: -122.15455 | X12: -139.25618 | Y12: -158.75205 | Z12: -180.97734 | AA12: -206.31416 | AB12: -235.19814 | AC12: -268.12589
C13: EBIT | D13: 344.1 | E13: =E9+E11+E12 -> 527.5 | F13: =F9+F11+F12 -> 650.4 | G13: =G9+G11+G12 -> 969.6 | H13: =(G13/D13)^(1/3)-1 -> 0.41243773 | I13: =I9+I11+I12 -> 1113.063 | J13: =J9+J11+J12 -> 1255.4681 | K13: =K9+K11+K12 -> 1505.3187 | L13: =L9+L11+L12 -> 1804.6168 | M13: =M9+M11+M12 -> 2163.1018 | N13: =N9+N11+N12 -> 2490.6658 | O13: =O9+O11+O12 -> 2867.4272 | P13: =P9+P11+P12 -> 3262.3436 | ... S13: =S9+S11+S12 -> 4869.5796 | T13: 5539.9539 | U13: 6302.6158 | V13: 7106.8164 | W13: 7942.081 | X13: 8875.5144 | Y13: 9739.9397 | Z13: 10688.555 | AA13: 11729.561 | AB13: 12871.954 | AC13: 14125.61 | AD13: =(AC13/I13)^(1/19)-1 -> 0.14308437
C14: %margin | E14: =E13/E7 -> 0.20332254 | F14: =F13/F7 -> 0.19460236 | G14: =G13/G7 -> 0.21949563 | I14: =I13/I7 -> 0.21 | J14: =J13/J7 -> 0.2 | K14: =K13/K7 -> 0.2025 | L14: =L13/L7 -> 0.205 | M14: =M13/M7 -> 0.2075 | N14: =N13/N7 -> 0.21 | O14: =O13/O7 -> 0.2125 | P14: =P13/P7 -> 0.2125 | ... S14: =S13/S7 -> 0.21685411 | T14: 0.21832521 | U14: 0.2198063 | V14: 0.22129743 | W14: 0.22279868 | X14: 0.22431011 | Y14: 0.2258318 | Z14: 0.2273638 | AA14: 0.22890621 | AB14: 0.23045907 | AC14: 0.23202247
C15: Taxes | D15: 56.4 | E15: -53.2 | F15: -14.1 | G15: -30.8 | I15: -81.431266 | J15: -89.243308 | K15: -108.26722 | L15: -132.15385 | M15: -482.8039 | N15: -570.49223 | O15: -665.5879 | P15: -714.35612 | Q15: -820.20167 | R15: -941.3015 | S15: -1072.9159 | T15: -1223.0391 | U15: -1391.0925 | V15: -1568.5824 | W15: -1752.8516 | X15: -1959.0492 | Y15: -2150.0032 | Z15: -2359.3857 | AA15: -2590.0757 | AB15: -2844.2632 | AC15: -3124.1128
C16: EBIAT | D16: =D13-D15 -> 287.7 | E16: =E13-E15 -> 580.7 | F16: =F13-F15 -> 664.5 | G16: =G13-G15 -> 1000.4 | H16: =(G16/D16)^(1/3)-1 -> 0.51499526 | I16: =I13-J15 -> 1202.3063 | J16: =J13-K15 -> 1363.7353 | K16: =K13-L15 -> 1637.4725 | L16: =L13-M15 -> 2287.4207 | M16: =M13-N15 -> 2733.5941 | N16: =N13-O15 -> 3156.2537 | O16: =O13-P15 -> 3581.7833 | P16: =P13-Q15 -> 4082.5453 | ... AC16: =AC13-AD15 -> 14125.61 | AD16: =(AC16/I16)^(1/19)-1 -> 0.1384537
C17: (+) DA | E17: =E11+E12 -> -68.8 | F17: =F11+F12 -> -84.4 | G17: =G11+G12 -> -104.3 | I17: =I11+I12 -> -112.552 | J17: =J11+J12 -> -158.97834 | K17: =K11+K12 -> -196.8718 | L17: =L11+L12 -> -239.30639 | M17: =M11+M12 -> -187.55243 | N17: =N11+N12 -> -218.22696 | O17: =O11+O12 -> -253.13663 | P17: =P11+P12 -> -292.8662 | ... AC17: =AC11+AC12 -> -1948.7265
C18: (-) CapEx | E18: -125.9 | F18: -295.9 | G18: -281.2 | I18: -399.95623 | J18: -420.58182 | K18: -468.32136 | L18: -528.18054 | M18: -521.22936 | N18: -593.01567 | O18: -674.68876 | P18: -767.61026 | Q18: -873.32939 | R18: -993.60868 | S18: -1122.7778 | T18: -1649.3606 | U18: -1863.7775 | V18: -2087.4308 | W18: -2317.0482 | X18: -2571.9235 | Y18: -2803.3966 | Z18: -3055.7023 | AA18: -3330.7155 | AB18: -3630.4799 | AC18: -3957.223
C19: (-) Change in NWC | E19: 190 | F19: 402.4 | G19: 233 | I19: 220.725 | J19: 244.26016 | K19: 289.08295 | L19: 342.33413 | M19: 324.31565 | N19: 287.14525 | O19: 326.69233 | P19: 371.68604 | Q19: 422.87649 | R19: 481.11716 | S19: 516.67651 | T19: 583.84446 | U19: 659.74424 | V19: 688.16399 | W19: 706.51503 | X19: 784.23168 | Y19: 712.22496 | Z19: 776.3252 | AA19: 846.19447 | AB19: 922.35197 | AC19: 1005.3637
C20: Unlevered Free Cash Fow | I20: =I16+I17+I18-I19 -> 469.07307 | J20: =J16+J17+J18-J19 -> 539.91503 | K20: =K16+K17+K18-K19 -> 683.19641 | L20: =L16+L17+L18-L19 -> 1177.5997 | M20: =M16+M17+M18-M19 -> 1700.4966 | N20: =N16+N17+N18-N19 -> 2057.8658 | O20: =O16+O17+O18-O19 -> 2327.2656 | P20: =P16+P17+P18-P19 -> 2650.3828 | ... AC20: =AC16+AC17+AC18-AC19 -> 7214.297
C22: WACC | D22: =$V$43 -> 0.1091169
C23: Discount factor | I23: =1-D22 -> 0.8908831 | J23: =I23*(1-$D$22) -> 0.7936727 | K23: =J23*(1-$D$22) -> 0.70706959 | L23: =K23*(1-$D$22) -> 0.62991635 | M23: =L23*(1-$D$22) -> 0.56118183 | N23: =M23*(1-$D$22) -> 0.49994741 | O23: =N23*(1-$D$22) -> 0.4453947 | P23: =O23*(1-$D$22) -> 0.39679461 | Q23: =P23*(1-$D$22) -> 0.35349761 | ... AC23: =AB23*(1-$D$22) -> 0.088355814
C25: Present Value of Free Cash Flow | I25: =I23*I20 -> 417.88927 | J25: =J23*J20 -> 428.51582 | K25: =K23*K20 -> 483.06741 | L25: =L23*L20 -> 741.78929 | M25: =M23*M20 -> 954.28782 | N25: =N23*N20 -> 1028.8247 | O25: =O23*O20 -> 1036.5518 | P25: =P23*P20 -> 1051.6576 | ... AC25: =AC23*AC20 -> 637.42508
C29: Enterprise Value | G29: Implied Perpetuity Growth Rate | N29: Implied Equity Value and Share Price | U29: WACC Data
C30: Comulative Present Value of FCF | E30: =SUM(I25:AC25) -> 19279.612 | G30: Terminal year FCF (2043) | L30: =S20 -> 4005.0629 | N30: Enterprise Value | S30: =E40 -> 25797.33 | U30: Market premium | V30: 0.0627
G31: WACC | L31: =D22 -> 0.1091169 | N31: (-) Total Debt | S31: 1054 | U31: Tax rate | V31: 0.21
C32: Terminal Value | G32: Terminal Value | L32: =L30*(1+L34)/(L31-L34) -> 73766.717 | N32: (-) Non controlling interest | S32: =0 -> 0 | U32: US10Y | V32: 0.0423
C33: Terminal Year EBITDA (2033) | E33: =AC9 -> 16074.337 | N33: (+)Cash and Cash equivalents | S33: 2187 | U33: Beta | V33: 1.1
C34: Exit Multiple | E34: =L37 -> 5.0898469 | G34: Perpetuity Growth Rate | L34: 0.052 | U34: Cost of Debt | V34: 0.05
C35: Terminal Value | E35: =L32 -> 73766.717 | N35: Implied Equity Value | S35: =S30-S31-S32+S33 -> 26930.33 | U35: Cost of Capital | V35: =V33*V30+V32 -> 0.11127
C36: Discount factor | E36: =AC23 -> 0.088355814 | U36: Size premium
C37: Present Value of Terminal Value | E37: =E35*E36 -> 6517.7183 | G37: Implied Exit MUltiple | L37: =L32*(1+L31)/E33 -> 5.0898469 | N37: Market Cap | S37: =OP!C22 -> 58622.549
C38: % of Enterprise Value | E38: =E37/E40 -> 0.25265088 | U38: Optimal Capital Structure
N39: Total Value vs Market Cap | S39: =S35/S37-1 -> -0.54061482 | U39: Debt | V39: 0.03
C40: Enterprise Value | E40: =E37+E30 -> 25797.33 | U40: Equity | V40: 0.97
U43: WACC | V43: =V39*V34*(1-V31)+V40*V35 -> 0.1091169
D75: {=D76/'DCF cash flow to the firm'!S39D74-1} -> #NAME?

Sheet Assumptions
B2: Assumptions
B4: Prospects:
B6: Links:
C8: 2022 | D8: =C8-1 -> 2021 | E8: =D8-1 -> 2020 | F8: =E8-1 -> 2019 | G8: =F8-1 -> 2018 | I8: Average | K8: Short Term Forecast | L8: Long Term Forecast
B9: Revenue growth | C9: =(Inputs!C6-Inputs!D6)/Inputs!D6 -> 0.32170427 | D9: =(Inputs!D6-Inputs!E6)/Inputs!E6 -> 0.2882362 | E9: =(Inputs!E6-Inputs!F6)/Inputs!F6 -> 0.19944521 | F9: =(Inputs!F6-Inputs!G6)/Inputs!G6 -> 0.20086609 | G9: =(Inputs!G6-Inputs!H6)/Inputs!H6 -> 0.20489665 | I9: =AVERAGE(C9:G9) -> 0.24302968 | K9: =T77 -> 0.18420727 | L9: =U92 -> 0.137725
B10: Operating Margin | C10: =Inputs!C8/Inputs!C6 -> 0.21949563 | D10: =Inputs!D8/Inputs!D6 -> 0.19460236 | E10: =Inputs!E8/Inputs!E6 -> 0.20332254 | F10: =Inputs!F8/Inputs!F6 -> 0.1605178 | G10: =Inputs!G8/Inputs!G6 -> 0.12824783 | I10: =AVERAGE(C10:G10) -> 0.18123723
B13: Modelling Factors
C15: Last 5 Years
C16: =C8 -> 2022 | D16: =D8 -> 2021 | E16: =E8 -> 2020 | F16: =F8 -> 2019 | G16: =G8 -> 2018 | I16: Average 5y | K16: average 12y | L16: Short Term Forecast | M16: Long Term Forecast | O16: Reference
B17: Depreciation factor | C17: =D58 -> -0.063529412 | D17: =E58 -> -0.068332642 | E17: =F58 -> -0.082860555 | F17: =G58 -> -0.096461187 | G17: =H58 -> -0.12218734 | I17: =AVERAGE(C17:G17) -> -0.086674227 | K17: =AVERAGE(D58:O58) -> -0.14397888 | L17: -0.08 | M17: -0.05
B18: Amortization factor | C18: =D64 -> -0.18550955 | D18: =E64 -> -0.160451 | E18: =F64 -> -0.15814507 | F18: =G64 -> -0.15181058 | G18: =H64 -> -0.1734104 | I18: =AVERAGE(C18:G18) -> -0.16586532 | K18: =AVERAGE(D64:O64) -> -0.17749099 | L18: -0.17 | M18: -0.14
B19: Stock-based comp | C19: =D70 -> 0.049757776 | D19: =E70 -> 0.06319191 | E19: =F70 -> 0.074699352 | F19: =G70 -> 0.080743901 | G19: =H70 -> 0.090439707 | I19: =AVERAGE(C19:G19) -> 0.071766529 | K19: =AVERAGE(D70:O70) -> 0.074255328 | L19: 0.05 | M19: 0.04
B20: Tax Rate | C20: =D47 -> 0.034680779 | D20: =E47 -> 0.022708971 | E20: =F47 -> 0.098209341 | F20: =G47 -> 0.14532337 | G20: =H47 -> -0.52175905 | I20: =AVERAGE(C20:F20) -> 0.075230615 | K20: =AVERAGE(D47:O47) -> 0.2283348 | L20: =I20 -> 0.075230615 | M20: =K20 -> 0.2283348
B21: Working capital flows | C21: =D77 -> 0.21670387 | D21: =E77 -> 0.53811179 | E21: =F77 -> 0.43359197 | F21: =G77 -> 0.38929577 | G21: =H77 -> -0.004244205 | I21: =AVERAGE(C21:G21) -> 0.31469184 | K21: =AVERAGE(D77:O77) -> 0.50512438 | L21: 0.25 | M21: 0.2
B22: CAPEX | C22: =D82 -> -0.063657355 | D22: =E82 -> -0.088534498 | E22: =F82 -> -0.048527598 | F22: =G82 -> -0.042760412 | G22: =H82 -> -0.029424828 | I22: =AVERAGE(C22:G22) -> -0.054580938 | K22: =AVERAGE(D82:O82) -> -0.047271967 | L22: =AVERAGE(D85:G85) -> -0.066364792 | M22: -0.065
B23: Acquisition factor | C23: =D113 -> 0.23658713 | D23: =E113 -> -0.30794088 | E23: =F113 -> 0.02046716 | F23: =G113 -> -0.19019571 | G23: =H113 -> -0.045469687 | I23: =AVERAGE(C23:G23) -> -0.057310397 | K23: =D115 -> -0.0922067 | L23: =I23 -> -0.057310397 | M23: =-5.3% -> -0.053
B24: Dividends | C24: 0 | D24: 0 | E24: 0 | F24: 0 | G24: 0 | I24: =AVERAGE(C24:G24) -> 0 | K24: 0 | L24: 0 | M24: 0
B25: Repurchases | C25: =D91 -> 2.3224076 | D25: =E91 -> 1.2228082 | E25: =F91 -> 2.2108495 | F25: =G91 -> 0.44697904 | G25: =H91 -> 0.58114035 | I25: =AVERAGE(C25:G25) -> 1.3568369 | K25: =AVERAGE(D91:O91) -> 2.0797993 | L25: 0.678 | M25: 0.45
B26: Leases | C26: 0 | D26: 0 | E26: 0 | F26: 0 | G26: 0 | I26: =AVERAGE(C26:G26) -> 0 | K26: 0 | L26: 0 | M26: 0
B27: Total Debt | C27: =D108 -> 1.0113605 | D27: =E108 -> 1.436037 | E27: =F108 -> 0.089049136 | F27: =G108 -> 0.11276908 | G27: =H108 -> 0 | I27: =AVERAGE(C27:G27) -> 0.52984314 | K27: =AVERAGE(D108:O108) -> 0.22076797 | L27: 0.9 | M27: 0.45
B30: Forecasts
B33: Interest Rate on debt | T33: Links: | U33: Gartner, September 2023 - Forecast: Enterprise Network Equipment by Market Segment, Worldwide, 2021-2027, 3Q23 Update Gartner, September 2023 - Forecast: Information Security and Risk Management, Worldwide, 2021-2027, 3Q23 Update Gartner, Forecast Analysis: Secure Access Service Edge, Worldwide Published 10 October 2023 - ID G00784465
B34: Credit Ranking (Moody's) | C34: BBB+ | R34: Revenues | U34: Westland Advisory - Industrial Cybersecurity Industry Analysis, July 2023
B35: Default Spread | C35: 0.02 | U35: https://pages.stern.nyu.edu/~adamodar/New_Home_Page/datafile/histgr.html
B36: 5Y US Bond Yield | C36: 0.0424 | E36: ST multiple | F36: =C36+C35 -> 0.0624 | R36: Short Term forecast | U36: https://investor.fortinet.com/static-files/2d21430a-2c22-4b9d-b7f5-3f4bdaa420b6
B37: 30Y Bond Yield | C37: 0.0431 | E37: LT multiple | F37: =C37+C35 -> 0.0631
R38: past performance | S38: 2022 | T38: 2021 | U38: 2020 | V38: 2019 | W38: 2018 | X38: 2017 | Y38: 2016 | Z38: 2015 | AA38: 2014 | AB38: 2013 | AC38: 2012 | AD38: 2011
B39: Fortinet's bonds | C39: Yield | R39: revenues | S39: 4417.4 | T39: 3342.2 | U39: 2594.4 | V39: 2156.2 | W39: 1801.2 | X39: 1494.9 | Y39: 1275.4 | Z39: 1009.3 | AA39: 770.4 | AB39: 615.3 | AC39: 533.6 | AD39: 433.6
B40: 3Y Bond | C40: 5.961242
B41: 7Y Bond | C41: 6.093001 | U41: comparison with Damodaran's industry data for reference
R42: Fortinet's revenue growth | U42: software(system & application) industry | W42: Fortinet's
R43: average growth total | S43: =AVERAGE(Inputs!C1:M1) -> 0.23607349 | U43: CAGR past 5y | V43: 0.201 | W43: =(S39/X39)^(1/5)-1 -> 0.24196946
B44: tax rate | D44: 2022 | E44: 2021 | F44: 2020 | G44: 2019 | H44: 2018 | I44: 2017 | J44: 2016 | K44: 2015 | L44: 2014 | M44: 2013 | N44: 2012 | O44: 2011 | R44: average growth 3y | S44: =AVERAGE(C9:E9) -> 0.26979523
B45: Net Income Before Taxes | D45: =DCF!F15 -> 888.1 | E45: =DCF!E15 -> 620.9 | F45: =DCF!D15 -> 541.7 | G45: ='Fin. Data'!F11+'Fin. Data'!F14+'Fin. Data'!F15 -> 388.1 | H45: ='Fin. Data'!G11+'Fin. Data'!G14+'Fin. Data'!G15 -> 218.3 | I45: ='Fin. Data'!H11+'Fin. Data'!H14+'Fin. Data'!H15 -> 60.9 | J45: ='Fin. Data'!I11+'Fin. Data'!I14+'Fin. Data'!I15 -> 43.1 | K45: ='Fin. Data'!J11+'Fin. Data'!J14+'Fin. Data'!J15 -> 17 | L45: ='Fin. Data'!K11+'Fin. Data'!K14+'Fin. Data'!K15 -> 61.5 | M45: ='Fin. Data'!L11+'Fin. Data'!L14+'Fin. Data'!L15 -> 75.9 | N45: ='Fin. Data'!M11+'Fin. Data'!M14+'Fin. Data'!M15 -> 105 | O45: ='Fin. Data'!N11+'Fin. Data'!N14+'Fin. Data'!N15 -> 92 | R45: average growth 5y | S45: =I9 -> 0.24302968
B46: tax | D46: -30.8 | E46: -14.1 | F46: -53.2 | G46: -56.4 | H46: 113.9 | I46: -29.5 | J46: -11 | K46: -9 | L46: -36.2 | M46: -31.7 | N46: -38.2 | O46: -29.6 | R46: average growth pre covid | S46: =AVERAGE(Inputs!F1:M1) -> 0.22342784
B47: effective tax rate | D47: =-D46/D45 -> 0.034680779 | E47: =-E46/E45 -> 0.022708971 | F47: =-F46/F45 -> 0.098209341 | G47: =-G46/G45 -> 0.14532337 | H47: =-H46/H45 -> -0.52175905 | I47: =-I46/I45 -> 0.48440066 | J47: =-J46/J45 -> 0.25522042 | K47: =-K46/K45 -> 0.52941176 | ... O47: =-O46/O45 -> 0.32173913 | R47: CAGR past 4y | S47: =(S39/W39)^(1/4)-1 -> 0.25141454
R48: CAGR past total | S48: =(S39/AD39)^(1/11)-1 -> 0.23493303
R50: Industry Breakdown for Forinet | S50: share of revenues
B51: interest rate on cash | C51: 45270 | R51: Secure Networking | S51: 0.7
B52: US 10Y bond | C52: 0.0423 | R52: Security Operations | S52: 0.1
R53: Universal SASE | S53: 0.2
B55: Depreciation factor | D55: 2022 | E55: 2021 | F55: 2020 | G55: 2019 | H55: 2018 | I55: 2017 | J55: 2016 | K55: 2015 | L55: 2014 | M55: 2013 | N55: 2012 | O55: 2011 | R55: Total Adresable Market growth | T55: 2023 | U55: 2027 | V55: CAGR | W55: expected CAGR for Fortinet
B56: depreciation for a year | D56: -81 | E56: -65.9 | F56: -55.5 | G56: -50.7 | H56: -46.7 | I56: -46.9 | J56: -39.2 | K56: -28.4 | L56: -20.5 | M56: -14.1 | N56: -10.6 | O56: -7 | R56: Secure Networking | T56: 62000 | U56: =T56*(1+V56) -> 67580 | V56: 0.09 | W56: =V56*S51 -> 0.063
B57: Gross PPE | D57: 1275 | E57: 964.4 | F57: 669.8 | G57: 525.6 | H57: 382.2 | I57: 340.6 | J57: 207.7 | K57: 140.1 | L57: 114.4 | M57: 78.5 | N57: 56.9 | O57: 31.8 | R57: Security Operations | T57: 46000 | U57: =T57*(1+V57) -> 52440 | V57: 0.14 | W57: =V57*S52 -> 0.014
B58: Depreciaiton/PPE | D58: =D56/D57 -> -0.063529412 | E58: =E56/E57 -> -0.068332642 | F58: =F56/F57 -> -0.082860555 | G58: =G56/G57 -> -0.096461187 | H58: =H56/H57 -> -0.12218734 | I58: =I56/I57 -> -0.13769818 | J58: =J56/J57 -> -0.18873375 | K58: =K56/K57 -> -0.20271235 | ... O58: =O56/O57 -> -0.22012579 | R58: universal SASE | T58: 17000 | U58: =T58*(1+V58) -> 20400 | V58: 0.2 | W58: =V58*S53 -> 0.04
R59: Total | T59: =SUM(T56:T58) -> 125000 | U59: =SUM(U56:U58) -> 140420 | V59: =SUM(V56:V58) -> 0.43 | W59: =SUM(W56:W58) -> 0.117
B61: Amortization factor | D61: 2022 | E61: 2021 | F61: 2020 | G61: 2019 | H61: 2018 | I61: 2017 | J61: 2016 | K61: 2015 | L61: 2014 | M61: 2013 | N61: 2012 | O61: 2011
B62: Amortization | D62: -23.3 | E62: -18.5 | F62: -13.3 | G62: -10.9 | H62: -9 | I62: -8.6 | J62: -9.3 | K62: -3.2 | L62: -1.5 | M62: -1.6 | N62: -1 | O62: 0
B63: gross intangible assets | D63: 125.6 | E63: 115.3 | F63: 84.1 | G63: 71.8 | H63: 51.9 | I63: 38.5 | J63: 38.5 | K63: 23.6 | L63: 6.1 | M63: 9.5 | N63: 3.5 | O63: 0
B64: amortization/gross intangible assets | D64: =D62/D63 -> -0.18550955 | E64: =E62/E63 -> -0.160451 | F64: =F62/F63 -> -0.15814507 | G64: =G62/G63 -> -0.15181058 | H64: =H62/H63 -> -0.1734104 | I64: =I62/I63 -> -0.22337662 | J64: =J62/J63 -> -0.24155844 | K64: =K62/K63 -> -0.13559322 | ... N64: =N62/N63 -> -0.28571429 | O64: 0
B67: stock based compensation factor | D67: 2022 | E67: 2021 | F67: 2020 | G67: 2019 | H67: 2018 | I67: 2017 | J67: 2016 | K67: 2015 | L67: 2014 | M67: 2013 | N67: 2012 | O67: 2011
B68: stock based compensation | D68: 219.8 | E68: 211.2 | F68: 193.8 | G68: 174.1 | H68: 162.9 | I68: 137.2 | J68: 122.4 | K68: 95.1 | L68: 59 | M68: 44.5 | N68: 30.7 | O68: 19
B69: revenues | D69: 4417.4 | E69: 3342.2 | F69: 2594.4 | G69: 2156.2 | H69: 1801.2 | I69: 1494.9 | J69: 1275.4 | K69: 1009.3 | L69: 770.4 | M69: 615.3 | N69: 533.6 | O69: 433.6
B70: stock based compensation/revenues | C70: stock based compensation/revenues | D70: =D68/D69 -> 0.049757776 | E70: =E68/E69 -> 0.06319191 | F70: =F68/F69 -> 0.074699352 | G70: =G68/G69 -> 0.080743901 | H70: =H68/H69 -> 0.090439707 | I70: =I68/I69 -> 0.091778714 | J70: =J68/J69 -> 0.095969892 | K70: =K68/K69 -> 0.094223719 | ... O70: =O68/O69 -> 0.043819188
B73: working capital | D73: 2022 | E73: 2021 | F73: 2020 | G73: 2019 | H73: 2018 | I73: 2017 | J73: 2016 | K73: 2015 | L73: 2014 | M73: 2013 | N73: 2012 | O73: 2011
B74: revenues | D74: 4417.4 | E74: 3342.2 | F74: 2594.4 | G74: 2156.2 | H74: 1801.2 | I74: 1494.9 | J74: 1275.4 | K74: 1009.3 | L74: 770.4 | M74: 615.3 | N74: 533.6 | O74: 433.6
B75: changes in revenues | D75: =D74-E74 -> 1075.2 | E75: =E74-F74 -> 747.8 | F75: =F74-G74 -> 438.2 | G75: =G74-H74 -> 355 | H75: =H74-I74 -> 306.3 | I75: =I74-J74 -> 219.5 | J75: =J74-K74 -> 266.1 | K75: =K74-L74 -> 238.9 | ... O75: =O74-P74 -> 433.6 | R75: Expected CAGR for Fortinet 4y industry based | T75: =W59 -> 0.117
B76: changes in wc | D76: =-456.7-109.1-7.7-318.2-226.4-35.3+105.2+55.2+25+23.5+1177.5 -> 233 | E76: =-72.5-19.4-17.7-294.5-94-19-13.1+49.9+44-0.7+839.4 -> 402.4 | F76: =-176.4-42.2-2.8-205.1-10.5-4.6+37.4+45.8+43.1+9.7+495.6 -> 190 | G76: =-96.7-48.5-2.1-162.3+17.8-1.3+7.7-1.4-2.7-0.2+446.7-18.8 -> 138.2 | H76: =-82-33.4+4.2-136.4-127.8-3.8+14.6+14.5+3.5-0.8+352.1-6 -> -1.3 | I76: =-38.4+9.4-6.7+35.8-1+13.1+14.4+12.6-5.5+300.8+29.5 -> 364 | J76: =-57.875-43.023-27.822+2.616-2.352+0.039-3.21+15.696-5.013+242.961+13.137 -> 135.154 | K76: =-66.464-19.088-29.851-2.63+0.667-2.517+0.883+11.301+2.016+222.346+20.372 -> 137.035 | L76: =-55.888-32.459+9.072-16-1.302+18.033+7.12+10.835+14.318+127.416-3.771 -> 77.374 | M76: =-22.08-35.093-18.75-0.907+1.243+10.485+3.602+6.013-1.948+68.871+22.522 -> 33.958 | N76: =-12.12-11.303-9.254+0.791+2.47+0.961+2.171+4.599-1.87+68.292+28.265 -> 73.002 | O76: =19.687-4.556-2.328-2.136+0.629-0.311+4.287-5.241+3.191-0.525+19.706+12.551 -> 44.954 | R76: past CAGR 4y | T76: =S47 -> 0.25141454
B77: changes in WC/changes in revenues | D77: =D76/D75 -> 0.21670387 | E77: =E76/E75 -> 0.53811179 | F77: =F76/F75 -> 0.43359197 | G77: =G76/G75 -> 0.38929577 | H77: =H76/H75 -> -0.004244205 | I77: =I76/I75 -> 1.6583144 | J77: =J76/J75 -> 0.5079068 | K77: =K76/K75 -> 0.5736082 | ... O77: =O76/O75 -> 0.1036762 | R77: weighted revenue projection for 4y | T77: =AVERAGE(T75:T76) -> 0.18420727
B79: CAPEX | D79: 2022 | E79: 2021 | F79: 2020 | G79: 2019 | H79: 2018 | I79: 2017 | J79: 2016 | K79: 2015 | L79: 2014 | M79: 2013 | N79: 2012 | O79: 2011
B80: capex | D80: -281.2 | E80: -295.9 | F80: -125.9 | G80: -92.2 | H80: -53 | I80: -135.3 | J80: -67.2 | K80: -37.4 | L80: -32.2 | M80: -13.9 | N80: -22.1 | O80: -3.6 | X80: Links: | Y80: https://www.gminsights.com/industry-analysis/secure-access-service-edge-market
B81: revenues | D81: 4417.4 | E81: 3342.2 | F81: 2594.4 | G81: 2156.2 | H81: 1801.2 | I81: 1494.9 | J81: 1275.4 | K81: 1009.3 | L81: 770.4 | M81: 615.3 | N81: 533.6 | O81: 433.6 | R81: Long term forecast | Y81: https://www.verifiedmarketresearch.com/product/secure-access-service-edge-sase-market/
B82: capex/revenues | D82: =D80/D81 -> -0.063657355 | E82: =E80/E81 -> -0.088534498 | F82: =F80/F81 -> -0.048527598 | G82: =G80/G81 -> -0.042760412 | H82: =H80/H81 -> -0.029424828 | I82: =I80/I81 -> -0.090507726 | J82: =J80/J81 -> -0.052689352 | K82: =K80/K81 -> -0.037055385 | ... O82: =O80/O81 -> -0.008302583 | Y82: https://reports.valuates.com/reports/QYRE-Auto-16W5806/global-sase-secure-access-service-edge
R83: Industry Breakdown for Fortinet | S83: share of revenues | U83: average of market foecasts | Y83: https://www.linkedin.com/pulse/sase-secure-access-service-edge-market-3f/
B84: forecast | C84: forecast | D84: 2023 | E84: 2024 | F84: 2025 | G84: 2026 | R84: Secure Networking | S84: 0.55 | U84: SASE | V84: =AVERAGE(20%, 26%,10.4%,18.15%) -> 0.186375 | Y84: https://uk.finance.yahoo.com/news/worldwide-security-operations-center-industry-084300931.html
B85: capex/revenues | C85: capex/revenues | D85: =-400/S96 -> -0.075459169 | E85: -0.067 | F85: -0.063 | G85: -0.06 | R85: Security Operations | S85: 0.15 | U85: SOC | V85: =AVERAGE(10.2%,10.8%,8.1%,11.6%) -> 0.10175 | Y85: https://medium.com/@watsonmac944/security-operation-center-soc-as-a-service-market-2030-market-trends-status-discover-the-share-ae7dbb5a5146
D86: note: expected capex for 2023 - 400-450mil | R86: Universal SASE | S86: 0.3 | U86: Network Security | V86: =AVERAGE(12.5%,11.7%) -> 0.121 | Y86: https://www.globenewswire.com/en/news-release/2023/05/24/2675417/0/en/Security-Operations-Center-Market-worth-USD-69-52-Billion-growing-at-a-8-1-CAGR-by-2030-Report-by-Market-Research-Future-MRFR.html
Y87: https://www.psmarketresearch.com/market-analysis/soc-as-a-service-market
B88: Repurchases | D88: 2022 | E88: 2021 | F88: 2020 | G88: 2019 | H88: 2018 | I88: 2017 | J88: 2016 | K88: 2015 | L88: 2014 | M88: 2013 | N88: 2012 | O88: 2011 | R88: Total Adresable Market growth | T88: CAGR(by 2030) | U88: expected CAGR for Fortinet | Y88: https://www.fortunebusinessinsights.com/industry-reports/network-security-market-100339
B89: share buyback | D89: 1991 | E89: 742 | F89: 1080 | G89: 145 | H89: 212 | I89: 446 | J89: 111 | K89: 60 | L89: 44 | M89: 34 | N89: 0 | O89: 0 | R89: Secure Networking | T89: =V86 -> 0.121 | U89: =T89*S84 -> 0.06655 | Y89: https://www.acumenresearchandconsulting.com/network-security-market
B90: net income | D90: 857.3 | E90: 606.8 | F90: 488.5 | G90: 324.4 | H90: 364.8 | I90: 94.5 | J90: 32.2 | K90: 8 | L90: 25.3 | M90: 44.3 | N90: 67 | O90: 63 | R90: Security Operations | T90: =V85 -> 0.10175 | U90: =T90*S85 -> 0.0152625
B91: share buyback/net income | D91: =D89/D90 -> 2.3224076 | E91: =E89/E90 -> 1.2228082 | F91: =F89/F90 -> 2.2108495 | G91: =G89/G90 -> 0.44697904 | H91: =H89/H90 -> 0.58114035 | I91: =I89/I90 -> 4.7195767 | J91: =J89/J90 -> 3.447205 | K91: =K89/K90 -> 7.5 | ... O91: =O89/O90 -> 0 | R91: universal SASE | T91: =V84 -> 0.186375 | U91: =S86*T91 -> 0.0559125
B92: Forecast | D92: 2023 | E92: 2024 | F92: 2025 | G92: 2026 | H92: 2027 | I92: 2028 | J92: 2029 | K92: 2030 | L92: 2031 | M92: 2032 | N92: 2033 | O92: 2034 | R92: Total | T92: =SUM(T89:T91) -> 0.409125 | U92: =SUM(U89:U91) -> 0.137725
D93: =-I96 -> -1050 | E93: =-I97 -> -480 | F93: =DCF!I29 -> -902.33025 | G93: =DCF!J29 -> -1101.4083 | H93: =DCF!K29 -> -734.24346 | I93: =DCF!L29 -> -867.59903 | J93: =DCF!M29 -> -1012.2196 | K93: =DCF!N29 -> -1179.6791 | L93: =DCF!O29 -> -1247.5609 | M93: =DCF!P29 -> -1432.911 | N93: =DCF!Q29 -> -1633.0895 | O93: 55% of net income in subsiquent years
R94: revenue projection | S94: 2023 | T94: 2024 | U94: 2025 | V94: 2026 | W94: 2027 | X94: 2028 | Y94: 2029 | Z94: 2030 | AA94: 2031 | AB94: 2032 | AC94: 2033 | AD94: 2034 | AE94: 2035 | AF94: 2036 | AG94: 2037 | AH94: 2038 | AI94: 2039 | AJ94: 2040 | AK94: 2041 | AL94: 2042 | AM94: 2043 | AN94: 2044 | AO94: 2045 | AP94: 2046 | AQ94: 2047 | AR94: 2048
H95: cash available for repurchase | I95: 1530 | K95: CAGR 8y | L95: =(D89/M89)^(1/9)-1 -> 0.57180675 | N95: growth | R95: growth rate | S95: 0.2 | T95: =$T$77 -> 0.18420727 | U95: =$T$77 -> 0.18420727 | V95: =$T$77 -> 0.18420727 | W95: =$T$77 -> 0.18420727 | X95: =$U$92 -> 0.137725 | Y95: =$U$92 -> 0.137725 | Z95: =$U$92 -> 0.137725 | AA95: =$U$92 -> 0.137725 | AB95: =$U$92 -> 0.137725 | AC95: 0.13 | AD95: 0.13 | AE95: 0.13 | AF95: 0.12 | AG95: 0.11 | AH95: 0.11 | AI95: 0.09 | AJ95: 0.09 | AK95: 0.09 | AL95: 0.09 | AM95: 0.09 | AN95: 0.09 | AO95: 0.09 | AP95: 0.06 | AQ95: 0.06 | AR95: 0.06
H96: share repurchase 2023 | I96: 1050 | K96: CAGR 5y | L96: =(D89/I89)^(1/5)-1 -> 0.34879914 | N96: long term(2027-2033) | O96: 0.45 | R96: revenues | S96: =S39*(1+S95) -> 5300.88 | T96: =S96*(1+T95) -> 6277.3406 | U96: =T96*(1+U95) -> 7433.6724 | V96: =U96*(1+V95) -> 8803.0089 | W96: =V96*(1+W95) -> 10424.587 | X96: =W96*(1+X95) -> 11860.313 | Y96: =X96*(1+Y95) -> 13493.775 | Z96: =Y96*(1+Z95) -> 15352.205 | AA96: =Z96*(1+AA95) -> 17466.588 | ... AR96: =AQ96*(1+AR95) -> 86148.509
H97: cash available for 2024 | I97: =I95-I96 -> 480 | N97: after 2034 | O97: 0.55
R99: Operating Margin
D100: 2022 | E100: 2021 | F100: 2020 | G100: 2019 | H100: 2018 | I100: 2017 | J100: 2016 | K100: 2015 | L100: 2014 | M100: 2013 | N100: 2012 | O100: 2011
B101: changes in share repurchase | D101: =D89-E89 -> 1249 | E101: =E89-F89 -> -338 | F101: =F89-G89 -> 935 | G101: =G89-H89 -> -67 | H101: =H89-I89 -> -234 | I101: =I89-J89 -> 335 | J101: =J89-K89 -> 51 | K101: =K89-L89 -> 16 | ... M101: =M89-N89 -> 34 | N101: 0 | O101: 0 | Z101: Year of consolidation | AA101: 2055
B102: changes in revenues | D102: =D75 -> 1075.2 | E102: =E75 -> 747.8 | F102: =F75 -> 438.2 | G102: =G75 -> 355 | H102: =H75 -> 306.3 | I102: =I75 -> 219.5 | J102: =J75 -> 266.1 | K102: =K75 -> 238.9 | ... O102: =O75 -> 433.6 | Z102: Growth till 2038
B103: changes in repurchases/changes in revenues | D103: =D101/D102 -> 1.1616443 | E103: =E101/E102 -> -0.45199251 | F103: =F101/F102 -> 2.1337289 | G103: =G101/G102 -> -0.18873239 | H103: =H101/H102 -> -0.7639569 | I103: =I101/I102 -> 1.5261959 | J103: =J101/J102 -> 0.19165727 | K103: =K101/K102 -> 0.066973629 | ... O103: =O101/O102 -> 0 | Z103: 2039-2045 | AA103: 0.09
Z104: 2045-2055 | AA104: 0.06
B105: Total Debt | D105: 2022 | E105: 2021 | F105: 2020 | G105: 2019 | H105: 2018 | I105: 2017 | J105: 2016 | K105: 2015 | L105: 2014 | M105: 2013 | N105: 2012 | O105: 2011 | Z105: 2055+ (perpetuity growth rate)
B106: EBITDA | D106: ='Fin. Data'!C11+'Fin. Data'!C17 -> 1073.9 | E106: ='Fin. Data'!D11+'Fin. Data'!D17 -> 734.8 | F106: ='Fin. Data'!E11+'Fin. Data'!E17 -> 596.3 | G106: ='Fin. Data'!F11+'Fin. Data'!F17 -> 408.8 | H106: ='Fin. Data'!G11+'Fin. Data'!G17 -> 286.7 | I106: ='Fin. Data'!H11+'Fin. Data'!H17 -> 165.3 | J106: ='Fin. Data'!I11+'Fin. Data'!I17 -> 91.4 | K106: ='Fin. Data'!J11+'Fin. Data'!J17 -> 46.5 | ... O106: ='Fin. Data'!N11+'Fin. Data'!N17 -> 95.9 | P106: D/A ratio is higher among competitors
B107: total debt | D107: ='Fin. Data'!C58 -> 1086.1 | E107: ='Fin. Data'!D58 -> 1055.2 | F107: ='Fin. Data'!E58 -> 53.1 | G107: ='Fin. Data'!F58 -> 46.1 | H107: ='Fin. Data'!G58 -> 0 | I107: ='Fin. Data'!H58 -> 0 | J107: ='Fin. Data'!I58 -> 0 | K107: ='Fin. Data'!J58 -> 0 | ... O107: ='Fin. Data'!N58 -> 0
B108: total debt/EBITDA | D108: =D107/D106 -> 1.0113605 | E108: =E107/E106 -> 1.436037 | F108: =F107/F106 -> 0.089049136 | G108: =G107/G106 -> 0.11276908 | H108: =H107/H106 -> 0 | I108: =I107/I106 -> 0 | J108: =J107/J106 -> 0 | K108: =K107/K106 -> 0 | ... O108: =O107/O106 -> 0
B110: acquisition factor | D110: 2022 | E110: 2021 | F110: 2020 | G110: 2019 | H110: 2018 | I110: 2017 | J110: 2016 | K110: 2015 | L110: 2014 | M110: 2013 | N110: 2012 | O110: 2011
B111: investments and acquisitions | D111: =Inputs!C66 -> 1045.1 | E111: =Inputs!D66 -> -1029.2 | F111: =Inputs!E66 -> 53.1 | G111: =Inputs!F66 -> -410.1 | H111: =Inputs!G66 -> -81.9 | I111: =Inputs!H66 -> 58.5 | J111: =Inputs!I66 -> -6.9 | K111: =Inputs!J66 -> 36.4 | ... O111: =Inputs!N66 -> -163.2
B112: revenues | D112: 4417.4 | E112: 3342.2 | F112: 2594.4 | G112: 2156.2 | H112: 1801.2 | I112: 1494.9 | J112: 1275.4 | K112: 1009.3 | L112: 770.4 | M112: 615.3 | N112: 533.6 | O112: 433.6 | R112: operating margin projection | S112: 2023 | T112: 2024 | U112: 2025 | V112: 2026 | W112: 2027 | X112: 2028 | Y112: 2029 | Z112: 2030 | AB112: 2048
B113: acq/revenues | C113: %of revenues | D113: =D111/D112 -> 0.23658713 | E113: =E111/E112 -> -0.30794088 | F113: =F111/F112 -> 0.02046716 | G113: =G111/G112 -> -0.19019571 | H113: =H111/H112 -> -0.045469687 | I113: =I111/I112 -> 0.039133052 | J113: =J111/J112 -> -0.0054100674 | K113: =K111/K112 -> 0.036064599 | ... O113: =O111/O112 -> -0.37638376 | R113: opeating margin | S113: 0.21 | T113: 0.2 | U113: 0.205 | V113: 0.21 | W113: 0.215 | X113: 0.22 | Y113: 0.225 | Z113: 0.23 | AA113: ... | AB113: 0.24
B114: 5y average | D114: =AVERAGE(D113:H113) -> -0.057310397
B115: 12y average | D115: =AVERAGE(D113:O113) -> -0.0922067
B118: Equity Risk Premium
B120: Region | C120: Revenues percent ttm | D120: Equity risk premium (Aswath Damodaran) | E120: Adjusted ERP
B121: United States | C121: 0.31 | D121: 0.05 | E121: =D121*C121 -> 0.0155
B122: Other Americas | C122: 0.11 | D122: 0.0759 | E122: =D122*C122 -> 0.008349
B123: Europe, Middle East and Aftica (EMEA) | C123: 0.38 | D123: 0.0683 | E123: =D123*C123 -> 0.025954
B124: Asia Pacific (APAC) | C124: 0.2 | D124: 0.0647 | E124: =D124*C124 -> 0.01294
...

Sheet Fin. Data
A1: =Inputs!I3 -> #VALUE!
A2: =Inputs!H2 -> Figures in Millions of USD
A3: Results
B4: =OP!J20 -> 2023 | C4: =B4-1 -> 2022 | D4: =C4-1 -> 2021 | E4: =D4-1 -> 2020 | F4: =E4-1 -> 2019 | G4: =F4-1 -> 2018 | H4: =G4-1 -> 2017 | I4: =H4-1 -> 2016 | J4: =I4-1 -> 2015 | ... N4: =M4-1 -> 2011
A5: Net Sales | B5: =_xlfn.XLOOKUP($A5,Inputs!$A:$A,Inputs!B:B,,0) -> 5172.7 | C5: =_xlfn.XLOOKUP($A5,Inputs!$A:$A,Inputs!C:C,,0) -> 4417.4 | D5: =_xlfn.XLOOKUP($A5,Inputs!$A:$A,Inputs!D:D,,0) -> 3342.2 | E5: =_xlfn.XLOOKUP($A5,Inputs!$A:$A,Inputs!E:E,,0) -> 2594.4 | F5: =_xlfn.XLOOKUP($A5,Inputs!$A:$A,Inputs!F:F,,0) -> 2163 | G5: =_xlfn.XLOOKUP($A5,Inputs!$A:$A,Inputs!G:G,,0) -> 1801.2 | H5: =_xlfn.XLOOKUP($A5,Inputs!$A:$A,Inputs!H:H,,0) -> 1494.9 | I5: =_xlfn.XLOOKUP($A5,Inputs!$A:$A,Inputs!I:I,,0) -> 1275.4 | J5: =_xlfn.XLOOKUP($A5,Inputs!$A:$A,Inputs!J:J,,0) -> 1009.3 | K5: =_xlfn.XLOOKUP($A5,Inputs!$A:$A,Inputs!K:K,,0) -> 770.4 | L5: =_xlfn.XLOOKUP($A5,Inputs!$A:$A,Inputs!L:L,,0) -> 615.3 | M5: =_xlfn.XLOOKUP($A5,Inputs!$A:$A,Inputs!M:M,,0) -> 533.6 | N5: =_xlfn.XLOOKUP($A5,Inputs!$A:$A,Inputs!N:N,,0) -> 433.6
A6: Growth vs. Previous year | B6: =IFERROR(B5/C5-1,"-") -> 0.17098293 | C6: =IFERROR(C5/D5-1,"-") -> 0.32170427 | D6: =IFERROR(D5/E5-1,"-") -> 0.2882362 | E6: =IFERROR(E5/F5-1,"-") -> 0.19944521 | F6: =IFERROR(F5/G5-1,"-") -> 0.20086609 | G6: =IFERROR(G5/H5-1,"-") -> 0.20489665 | H6: =IFERROR(H5/I5-1,"-") -> 0.17210287 | I6: =IFERROR(I5/J5-1,"-") -> 0.26364807 | ... M6: =IFERROR(M5/N5-1,"-") -> 0.23062731 | N6: =IFERROR(N5/#REF!-1,"-") -> -
A7: Gross Profit | B7: =_xlfn.XLOOKUP($A7,Inputs!$A:$A,Inputs!B:B,,0) -> 3954.1 | C7: =_xlfn.XLOOKUP($A7,Inputs!$A:$A,Inputs!C:C,,0) -> 3332.5 | D7: =_xlfn.XLOOKUP($A7,Inputs!$A:$A,Inputs!D:D,,0) -> 2559.2 | E7: =_xlfn.XLOOKUP($A7,Inputs!$A:$A,Inputs!E:E,,0) -> 2024.4 | F7: =_xlfn.XLOOKUP($A7,Inputs!$A:$A,Inputs!F:F,,0) -> 1657.1 | G7: =_xlfn.XLOOKUP($A7,Inputs!$A:$A,Inputs!G:G,,0) -> 1350.8 | H7: =_xlfn.XLOOKUP($A7,Inputs!$A:$A,Inputs!H:H,,0) -> 1109.6 | I7: =_xlfn.XLOOKUP($A7,Inputs!$A:$A,Inputs!I:I,,0) -> 937.6 | J7: =_xlfn.XLOOKUP($A7,Inputs!$A:$A,Inputs!J:J,,0) -> 722.5 | K7: =_xlfn.XLOOKUP($A7,Inputs!$A:$A,Inputs!K:K,,0) -> 539.4 | L7: =_xlfn.XLOOKUP($A7,Inputs!$A:$A,Inputs!L:L,,0) -> 434.7 | M7: =_xlfn.XLOOKUP($A7,Inputs!$A:$A,Inputs!M:M,,0) -> 386.2 | N7: =_xlfn.XLOOKUP($A7,Inputs!$A:$A,Inputs!N:N,,0) -> 320
A8: % over sales | B8: =IFERROR(B7/B$5,"-") -> 0.76441704 | C8: =IFERROR(C7/C$5,"-") -> 0.75440304 | D8: =IFERROR(D7/D$5,"-") -> 0.76572318 | E8: =IFERROR(E7/E$5,"-") -> 0.78029602 | F8: =IFERROR(F7/F$5,"-") -> 0.76611188 | G8: =IFERROR(G7/G$5,"-") -> 0.74994448 | H8: =IFERROR(H7/H$5,"-") -> 0.74225701 | I8: =IFERROR(I7/I$5,"-") -> 0.73514192 | ... N8: =IFERROR(N7/N$5,"-") -> 0.73800738
A9: Operating expenses | B9: =B5-B11 -> 3959.2 | C9: =C5-C11 -> 3447.8 | D9: =D5-D11 -> 2691.8 | E9: =E5-E11 -> 2066.9 | F9: =F5-F11 -> 1815.8 | G9: =G5-G11 -> 1570.2 | H9: =H5-H11 -> 1385.1 | I9: =I5-I11 -> 1232.5 | ... N9: =N5-N11 -> 344.7
A10: % over sales | B10: =IFERROR(B9/B$5,"-") -> 0.76540298 | C10: =IFERROR(C9/C$5,"-") -> 0.78050437 | D10: =IFERROR(D9/D$5,"-") -> 0.80539764 | E10: =IFERROR(E9/E$5,"-") -> 0.79667746 | F10: =IFERROR(F9/F$5,"-") -> 0.8394822 | G10: =IFERROR(G9/G$5,"-") -> 0.87175217 | H10: =IFERROR(H9/H$5,"-") -> 0.92655027 | I10: =IFERROR(I9/I$5,"-") -> 0.96636349 | ... N10: =IFERROR(N9/N$5,"-") -> 0.79497232
A11: Operating Income | B11: =_xlfn.XLOOKUP($A11,Inputs!$A:$A,Inputs!B:B,,0) -> 1213.5 | C11: =_xlfn.XLOOKUP($A11,Inputs!$A:$A,Inputs!C:C,,0) -> 969.6 | D11: =_xlfn.XLOOKUP($A11,Inputs!$A:$A,Inputs!D:D,,0) -> 650.4 | E11: =_xlfn.XLOOKUP($A11,Inputs!$A:$A,Inputs!E:E,,0) -> 527.5 | F11: =_xlfn.XLOOKUP($A11,Inputs!$A:$A,Inputs!F:F,,0) -> 347.2 | G11: =_xlfn.XLOOKUP($A11,Inputs!$A:$A,Inputs!G:G,,0) -> 231 | H11: =_xlfn.XLOOKUP($A11,Inputs!$A:$A,Inputs!H:H,,0) -> 109.8 | I11: =_xlfn.XLOOKUP($A11,Inputs!$A:$A,Inputs!I:I,,0) -> 42.9 | J11: =_xlfn.XLOOKUP($A11,Inputs!$A:$A,Inputs!J:J,,0) -> 14.9 | K11: =_xlfn.XLOOKUP($A11,Inputs!$A:$A,Inputs!K:K,,0) -> 59.3 | L11: =_xlfn.XLOOKUP($A11,Inputs!$A:$A,Inputs!L:L,,0) -> 72.1 | M11: =_xlfn.XLOOKUP($A11,Inputs!$A:$A,Inputs!M:M,,0) -> 100.5 | N11: =_xlfn.XLOOKUP($A11,Inputs!$A:$A,Inputs!N:N,,0) -> 88.9
A12: Operating Margin | B12: =IFERROR(B11/B$5,"-") -> 0.23459702 | C12: =IFERROR(C11/C$5,"-") -> 0.21949563 | D12: =IFERROR(D11/D$5,"-") -> 0.19460236 | E12: =IFERROR(E11/E$5,"-") -> 0.20332254 | F12: =IFERROR(F11/F$5,"-") -> 0.1605178 | G12: =IFERROR(G11/G$5,"-") -> 0.12824783 | H12: =IFERROR(H11/H$5,"-") -> 0.073449729 | I12: =IFERROR(I11/I$5,"-") -> 0.033636506 | ... N12: =IFERROR(N11/N$5,"-") -> 0.20502768
A13: Growth vs. Previous year | B13: =IFERROR(B12/C12-1,"-") -> 0.068800404 | C13: =IFERROR(C12/D12-1,"-") -> 0.12791866 | D13: =IFERROR(D12/E12-1,"-") -> -0.042888423 | E13: =IFERROR(E12/F12-1,"-") -> 0.26666664 | F13: =IFERROR(F12/G12-1,"-") -> 0.25162191 | G13: =IFERROR(G12/H12-1,"-") -> 0.74606273 | H13: =IFERROR(H12/I12-1,"-") -> 1.1836313 | I13: =IFERROR(I12/J12-1,"-") -> 1.2784782 | ... M13: =IFERROR(M12/N12-1,"-") -> -0.081376072 | N13: =IFERROR(N12/#REF!-1,"-") -> -
A14: Net Financial Cost | B14: =_xlfn.XLOOKUP($A14,Inputs!$A:$A,Inputs!B:B,,0) -> 78.2 | C14: =_xlfn.XLOOKUP($A14,Inputs!$A:$A,Inputs!C:C,,0) -> -5.2 | D14: =_xlfn.XLOOKUP($A14,Inputs!$A:$A,Inputs!D:D,,0) -> -18.6 | E14: =_xlfn.XLOOKUP($A14,Inputs!$A:$A,Inputs!E:E,,0) -> 12.2 | F14: =_xlfn.XLOOKUP($A14,Inputs!$A:$A,Inputs!F:F,,0) -> 37.8 | G14: =_xlfn.XLOOKUP($A14,Inputs!$A:$A,Inputs!G:G,,0) -> 28.7 | H14: =_xlfn.XLOOKUP($A14,Inputs!$A:$A,Inputs!H:H,,0) -> 13.5 | I14: =_xlfn.XLOOKUP($A14,Inputs!$A:$A,Inputs!I:I,,0) -> 7.3 | J14: =_xlfn.XLOOKUP($A14,Inputs!$A:$A,Inputs!J:J,,0) -> 5.3 | K14: =_xlfn.XLOOKUP($A14,Inputs!$A:$A,Inputs!K:K,,0) -> 5.4 | L14: =_xlfn.XLOOKUP($A14,Inputs!$A:$A,Inputs!L:L,,0) -> 5.3 | M14: =_xlfn.XLOOKUP($A14,Inputs!$A:$A,Inputs!M:M,,0) -> 5 | N14: =_xlfn.XLOOKUP($A14,Inputs!$A:$A,Inputs!N:N,,0) -> 3.5
A15: Other Expenses (Revenues) | B15: =_xlfn.XLOOKUP($A15,Inputs!$A:$A,Inputs!B:B,,0) -> -83.2 | C15: =_xlfn.XLOOKUP($A15,Inputs!$A:$A,Inputs!C:C,,0) -> -76.3 | D15: =_xlfn.XLOOKUP($A15,Inputs!$A:$A,Inputs!D:D,,0) -> -10.9 | E15: =_xlfn.XLOOKUP($A15,Inputs!$A:$A,Inputs!E:E,,0) -> 2 | F15: =_xlfn.XLOOKUP($A15,Inputs!$A:$A,Inputs!F:F,,0) -> 3.1 | G15: =_xlfn.XLOOKUP($A15,Inputs!$A:$A,Inputs!G:G,,0) -> -41.4 | H15: =_xlfn.XLOOKUP($A15,Inputs!$A:$A,Inputs!H:H,,0) -> -62.4 | I15: =_xlfn.XLOOKUP($A15,Inputs!$A:$A,Inputs!I:I,,0) -> -7.1 | J15: =_xlfn.XLOOKUP($A15,Inputs!$A:$A,Inputs!J:J,,0) -> -3.2 | K15: =_xlfn.XLOOKUP($A15,Inputs!$A:$A,Inputs!K:K,,0) -> -3.2 | L15: =_xlfn.XLOOKUP($A15,Inputs!$A:$A,Inputs!L:L,,0) -> -1.5 | M15: =_xlfn.XLOOKUP($A15,Inputs!$A:$A,Inputs!M:M,,0) -> -0.5 | N15: =_xlfn.XLOOKUP($A15,Inputs!$A:$A,Inputs!N:N,,0) -> -0.4
A16: EBIT | B16: =B11-B15 -> 1296.7 | C16: =C11-C15 -> 1045.9 | D16: =D11-D15 -> 661.3 | E16: =E11-E15 -> 525.5 | F16: =F11-F15 -> 344.1 | G16: =G11-G15 -> 272.4 | H16: =H11-H15 -> 172.2 | I16: =I11-I15 -> 50 | ... N16: =N11-N15 -> 89.3
A17: Depreciation & Amortization | B17: =_xlfn.XLOOKUP($A17,Inputs!$A:$A,Inputs!B:B,,0) -> 110.5 | C17: =_xlfn.XLOOKUP($A17,Inputs!$A:$A,Inputs!C:C,,0) -> 104.3 | D17: =_xlfn.XLOOKUP($A17,Inputs!$A:$A,Inputs!D:D,,0) -> 84.4 | E17: =_xlfn.XLOOKUP($A17,Inputs!$A:$A,Inputs!E:E,,0) -> 68.8 | F17: =_xlfn.XLOOKUP($A17,Inputs!$A:$A,Inputs!F:F,,0) -> 61.6 | G17: =_xlfn.XLOOKUP($A17,Inputs!$A:$A,Inputs!G:G,,0) -> 55.7 | H17: =_xlfn.XLOOKUP($A17,Inputs!$A:$A,Inputs!H:H,,0) -> 55.5 | I17: =_xlfn.XLOOKUP($A17,Inputs!$A:$A,Inputs!I:I,,0) -> 48.5 | J17: =_xlfn.XLOOKUP($A17,Inputs!$A:$A,Inputs!J:J,,0) -> 31.6 | K17: =_xlfn.XLOOKUP($A17,Inputs!$A:$A,Inputs!K:K,,0) -> 22 | L17: =_xlfn.XLOOKUP($A17,Inputs!$A:$A,Inputs!L:L,,0) -> 15.6 | M17: =_xlfn.XLOOKUP($A17,Inputs!$A:$A,Inputs!M:M,,0) -> 11.6 | N17: =_xlfn.XLOOKUP($A17,Inputs!$A:$A,Inputs!N:N,,0) -> 7
A18: Changes Net Working Capital | B18: =_xlfn.XLOOKUP($A18,Inputs!$A:$A,Inputs!B:B,,0) -> -3888.4 | C18: =_xlfn.XLOOKUP($A18,Inputs!$A:$A,Inputs!C:C,,0) -> -914.3 | D18: =_xlfn.XLOOKUP($A18,Inputs!$A:$A,Inputs!D:D,,0) -> 114.3 | E18: =_xlfn.XLOOKUP($A18,Inputs!$A:$A,Inputs!E:E,,0) -> -223.8 | F18: =_xlfn.XLOOKUP($A18,Inputs!$A:$A,Inputs!F:F,,0) -> 220.8 | G18: =_xlfn.XLOOKUP($A18,Inputs!$A:$A,Inputs!G:G,,0) -> -26.5 | H18: =_xlfn.XLOOKUP($A18,Inputs!$A:$A,Inputs!H:H,,0) -> -121.7 | I18: =_xlfn.XLOOKUP($A18,Inputs!$A:$A,Inputs!I:I,,0) -> -48.5 | J18: =_xlfn.XLOOKUP($A18,Inputs!$A:$A,Inputs!J:J,,0) -> -218.3 | K18: =_xlfn.XLOOKUP($A18,Inputs!$A:$A,Inputs!K:K,,0) -> 60.6 | L18: =_xlfn.XLOOKUP($A18,Inputs!$A:$A,Inputs!L:L,,0) -> 79.5 | M18: =_xlfn.XLOOKUP($A18,Inputs!$A:$A,Inputs!M:M,,0) -> -57.7 | N18: =_xlfn.XLOOKUP($A18,Inputs!$A:$A,Inputs!N:N,,0) -> 184.7
A19: EBITDA | B19: =B11-B15+B17 -> 1407.2 | C19: =C11-C15+C17 -> 1150.2 | D19: =D11-D15+D17 -> 745.7 | E19: =E11-E15+E17 -> 594.3 | F19: =F11-F15+F17 -> 405.7 | G19: =G11-G15+G17 -> 328.1 | H19: =H11-H15+H17 -> 227.7 | I19: =I11-I15+I17 -> 98.5 | ... N19: =N11-N15+N17 -> 96.3
A20: EBITDA Margin | B20: =IFERROR(B19/B$5,"-") -> 0.27204361 | C20: =IFERROR(C19/C$5,"-") -> 0.26037941 | D20: =IFERROR(D19/D$5,"-") -> 0.22311651 | E20: =IFERROR(E19/E$5,"-") -> 0.22907031 | F20: =IFERROR(F19/F$5,"-") -> 0.18756357 | G20: =IFERROR(G19/G$5,"-") -> 0.18215634 | H20: =IFERROR(H19/H$5,"-") -> 0.15231788 | I20: =IFERROR(I19/I$5,"-") -> 0.077230673 | ... N20: =IFERROR(N19/N$5,"-") -> 0.2220941
A21: Taxes | B21: =_xlfn.XLOOKUP($A21,Inputs!$A:$A,Inputs!B:B,,0) -> -57.8 | C21: =_xlfn.XLOOKUP($A21,Inputs!$A:$A,Inputs!C:C,,0) -> -30.8 | D21: =_xlfn.XLOOKUP($A21,Inputs!$A:$A,Inputs!D:D,,0) -> -14.1 | E21: =_xlfn.XLOOKUP($A21,Inputs!$A:$A,Inputs!E:E,,0) -> -53.2 | F21: =_xlfn.XLOOKUP($A21,Inputs!$A:$A,Inputs!F:F,,0) -> -56.4 | G21: =_xlfn.XLOOKUP($A21,Inputs!$A:$A,Inputs!G:G,,0) -> 113.9 | H21: =_xlfn.XLOOKUP($A21,Inputs!$A:$A,Inputs!H:H,,0) -> -29.5 | I21: =_xlfn.XLOOKUP($A21,Inputs!$A:$A,Inputs!I:I,,0) -> -11 | J21: =_xlfn.XLOOKUP($A21,Inputs!$A:$A,Inputs!J:J,,0) -> -9 | K21: =_xlfn.XLOOKUP($A21,Inputs!$A:$A,Inputs!K:K,,0) -> -36.2 | L21: =_xlfn.XLOOKUP($A21,Inputs!$A:$A,Inputs!L:L,,0) -> -31.7 | M21: =_xlfn.XLOOKUP($A21,Inputs!$A:$A,Inputs!M:M,,0) -> -38.2 | N21: =_xlfn.XLOOKUP($A21,Inputs!$A:$A,Inputs!N:N,,0) -> -29.6
A22: % Tax | B22: =IFERROR(B21/B$5,"-") -> -0.011174048 | C22: =IFERROR(C21/C$5,"-") -> -0.0069724272 | D22: =IFERROR(D21/D$5,"-") -> -0.0042187781 | E22: =IFERROR(E21/E$5,"-") -> -0.020505705 | F22: =IFERROR(F21/F$5,"-") -> -0.026074896 | G22: =IFERROR(G21/G$5,"-") -> 0.063235621 | H22: =IFERROR(H21/H$5,"-") -> -0.019733761 | I22: =IFERROR(I21/I$5,"-") -> -0.0086247452 | ... N22: =IFERROR(N21/N$5,"-") -> -0.068265683
A23: Net Income | B23: =_xlfn.XLOOKUP($A23,Inputs!$A:$A,Inputs!B:B,,0) -> 1150.7 | C23: =_xlfn.XLOOKUP($A23,Inputs!$A:$A,Inputs!C:C,,0) -> 857.3 | D23: =_xlfn.XLOOKUP($A23,Inputs!$A:$A,Inputs!D:D,,0) -> 606.8 | E23: =_xlfn.XLOOKUP($A23,Inputs!$A:$A,Inputs!E:E,,0) -> 488.5 | F23: =_xlfn.XLOOKUP($A23,Inputs!$A:$A,Inputs!F:F,,0) -> 331.7 | G23: =_xlfn.XLOOKUP($A23,Inputs!$A:$A,Inputs!G:G,,0) -> 332.2 | H23: =_xlfn.XLOOKUP($A23,Inputs!$A:$A,Inputs!H:H,,0) -> 31.4 | I23: =_xlfn.XLOOKUP($A23,Inputs!$A:$A,Inputs!I:I,,0) -> 32.2 | J23: =_xlfn.XLOOKUP($A23,Inputs!$A:$A,Inputs!J:J,,0) -> 8 | K23: =_xlfn.XLOOKUP($A23,Inputs!$A:$A,Inputs!K:K,,0) -> 25.3 | L23: =_xlfn.XLOOKUP($A23,Inputs!$A:$A,Inputs!L:L,,0) -> 44.3 | M23: =_xlfn.XLOOKUP($A23,Inputs!$A:$A,Inputs!M:M,,0) -> 66.8 | N23: =_xlfn.XLOOKUP($A23,Inputs!$A:$A,Inputs!N:N,,0) -> 62.5
A24: Net Income Margin | B24: =IFERROR(B23/B$5,"-") -> 0.22245636 | C24: =IFERROR(C23/C$5,"-") -> 0.19407344 | D24: =IFERROR(D23/D$5,"-") -> 0.18155706 | E24: =IFERROR(E23/E$5,"-") -> 0.18829016 | F24: =IFERROR(F23/F$5,"-") -> 0.15335183 | G24: =IFERROR(G23/G$5,"-") -> 0.1844326 | H24: =IFERROR(H23/H$5,"-") -> 0.021004749 | I24: =IFERROR(I23/I$5,"-") -> 0.025246981 | ... N24: =IFERROR(N23/N$5,"-") -> 0.14414207
A25: Growth vs. Previous year | B25: =IFERROR(B24/C24-1,"-") -> 0.14624835 | C25: =IFERROR(C24/D24-1,"-") -> 0.068939091 | D25: =IFERROR(D24/E24-1,"-") -> -0.035759198 | E25: =IFERROR(E24/F24-1,"-") -> 0.22783124 | F25: =IFERROR(F24/G24-1,"-") -> -0.16852104 | G25: =IFERROR(G24/H24-1,"-") -> 7.7805189 | H25: =IFERROR(H24/I24-1,"-") -> -0.16802927 | I25: =IFERROR(I24/J24-1,"-") -> 2.1852223 | ... M25: =IFERROR(M24/N24-1,"-") -> -0.13149985 | N25: =IFERROR(N24/#REF!-1,"-") -> -
A26: Cash Generated | B26: =B39-C39 -> 503.9 | C26: =C39-D39 -> 363.8 | D26: =D39-E39 -> 257.3 | E26: =E39-F39 -> -160.7 | F26: =F39-G39 -> 110.1 | G26: =G39-H39 -> 301.4 | H26: =H39-I39 -> 102 | I26: =I39-J39 -> 166 | ... M26: =M39-N39 -> 51 | N26: =N39-#REF! -> #REF!
A27: Dividends | B27: =_xlfn.XLOOKUP($A27,Inputs!$A:$A,Inputs!B:B,,0) -> 0 | C27: =_xlfn.XLOOKUP($A27,Inputs!$A:$A,Inputs!C:C,,0) -> 0 | D27: =_xlfn.XLOOKUP($A27,Inputs!$A:$A,Inputs!D:D,,0) -> 0 | E27: =_xlfn.XLOOKUP($A27,Inputs!$A:$A,Inputs!E:E,,0) -> 0 | F27: =_xlfn.XLOOKUP($A27,Inputs!$A:$A,Inputs!F:F,,0) -> 0 | G27: =_xlfn.XLOOKUP($A27,Inputs!$A:$A,Inputs!G:G,,0) -> 0 | H27: =_xlfn.XLOOKUP($A27,Inputs!$A:$A,Inputs!H:H,,0) -> 0 | I27: =_xlfn.XLOOKUP($A27,Inputs!$A:$A,Inputs!I:I,,0) -> 0 | J27: =_xlfn.XLOOKUP($A27,Inputs!$A:$A,Inputs!J:J,,0) -> 0 | K27: =_xlfn.XLOOKUP($A27,Inputs!$A:$A,Inputs!K:K,,0) -> 0 | L27: =_xlfn.XLOOKUP($A27,Inputs!$A:$A,Inputs!L:L,,0) -> 0 | M27: =_xlfn.XLOOKUP($A27,Inputs!$A:$A,Inputs!M:M,,0) -> 0 | N27: =_xlfn.XLOOKUP($A27,Inputs!$A:$A,Inputs!N:N,,0) -> 0
A28: Share buyback | B28: =_xlfn.XLOOKUP($A28,Inputs!$A:$A,Inputs!B:B,,0) -> -604.3 | C28: =_xlfn.XLOOKUP($A28,Inputs!$A:$A,Inputs!C:C,,0) -> -1991.2 | D28: =_xlfn.XLOOKUP($A28,Inputs!$A:$A,Inputs!D:D,,0) -> -741.8 | E28: =_xlfn.XLOOKUP($A28,Inputs!$A:$A,Inputs!E:E,,0) -> -1080.1 | F28: =_xlfn.XLOOKUP($A28,Inputs!$A:$A,Inputs!F:F,,0) -> -145.1 | G28: =_xlfn.XLOOKUP($A28,Inputs!$A:$A,Inputs!G:G,,0) -> -211.8 | H28: =_xlfn.XLOOKUP($A28,Inputs!$A:$A,Inputs!H:H,,0) -> -446.3 | I28: =_xlfn.XLOOKUP($A28,Inputs!$A:$A,Inputs!I:I,,0) -> -110.8 | J28: =_xlfn.XLOOKUP($A28,Inputs!$A:$A,Inputs!J:J,,0) -> -60 | K28: =_xlfn.XLOOKUP($A28,Inputs!$A:$A,Inputs!K:K,,0) -> -44 | L28: =_xlfn.XLOOKUP($A28,Inputs!$A:$A,Inputs!L:L,,0) -> -33.5 | M28: =_xlfn.XLOOKUP($A28,Inputs!$A:$A,Inputs!M:M,,0) -> 0 | N28: =_xlfn.XLOOKUP($A28,Inputs!$A:$A,Inputs!N:N,,0) -> 0
A29: Net Cash Flow | B29: =SUM(B26:B28) -> -100.4 | C29: =SUM(C26:C28) -> -1627.4 | D29: =SUM(D26:D28) -> -484.5 | E29: =SUM(E26:E28) -> -1240.8 | F29: =SUM(F26:F28) -> -35 | G29: =SUM(G26:G28) -> 89.6 | H29: =SUM(H26:H28) -> -344.3 | I29: =SUM(I26:I28) -> 55.2 | ... N29: =SUM(N26:N28) -> #REF!
A30: FNP'' | B30: =+B29-(B58-C29) -> -2782.1 | C30: =+C29-(C58-D29) -> -3198 | D30: =+D29-(D58-E29) -> -2780.5 | E30: =+E29-(E58-F29) -> -1328.9 | F30: =+F29-(F58-G29) -> 8.5 | G30: =+G29-(G58-H29) -> -254.7 | H30: =+H29-(H58-I29) -> -289.1 | I30: =+I29-(I58-J29) -> 254.9 | ... N30: =+N29-(N58-O29) -> #REF!
A31: FNP' | B31: =+B30+B33 -> -2629.9 | C31: =+C30+C33 -> -2152.9 | D31: =+D30+D33 -> -3809.7 | E31: =+E30+E33 -> -1275.8 | F31: =+F30+F33 -> -401.6 | G31: =+G30+G33 -> -336.6 | H31: =+H30+H33 -> -230.6 | I31: =+I30+I33 -> 248 | ... N31: =+N30+N33 -> #REF!
A32: Net Capex | B32: =_xlfn.XLOOKUP($A32,Inputs!$A:$A,Inputs!B:B,,0) -> -208.1 | C32: =_xlfn.XLOOKUP($A32,Inputs!$A:$A,Inputs!C:C,,0) -> -281.2 | D32: =_xlfn.XLOOKUP($A32,Inputs!$A:$A,Inputs!D:D,,0) -> -295.9 | E32: =_xlfn.XLOOKUP($A32,Inputs!$A:$A,Inputs!E:E,,0) -> -125.9 | F32: =_xlfn.XLOOKUP($A32,Inputs!$A:$A,Inputs!F:F,,0) -> -92.2 | G32: =_xlfn.XLOOKUP($A32,Inputs!$A:$A,Inputs!G:G,,0) -> -53 | H32: =_xlfn.XLOOKUP($A32,Inputs!$A:$A,Inputs!H:H,,0) -> -135.3 | I32: =_xlfn.XLOOKUP($A32,Inputs!$A:$A,Inputs!I:I,,0) -> -67.2 | J32: =_xlfn.XLOOKUP($A32,Inputs!$A:$A,Inputs!J:J,,0) -> -37.4 | K32: =_xlfn.XLOOKUP($A32,Inputs!$A:$A,Inputs!K:K,,0) -> -32.2 | L32: =_xlfn.XLOOKUP($A32,Inputs!$A:$A,Inputs!L:L,,0) -> -13.9 | M32: =_xlfn.XLOOKUP($A32,Inputs!$A:$A,Inputs!M:M,,0) -> -22.1 | N32: =_xlfn.XLOOKUP($A32,Inputs!$A:$A,Inputs!N:N,,0) -> -3.6
A33: Investments & Acquisitions | B33: =_xlfn.XLOOKUP($A33,Inputs!$A:$A,Inputs!B:B,,0) -> 152.2 | C33: =_xlfn.XLOOKUP($A33,Inputs!$A:$A,Inputs!C:C,,0) -> 1045.1 | D33: =_xlfn.XLOOKUP($A33,Inputs!$A:$A,Inputs!D:D,,0) -> -1029.2 | E33: =_xlfn.XLOOKUP($A33,Inputs!$A:$A,Inputs!E:E,,0) -> 53.1 | F33: =_xlfn.XLOOKUP($A33,Inputs!$A:$A,Inputs!F:F,,0) -> -410.1 | G33: =_xlfn.XLOOKUP($A33,Inputs!$A:$A,Inputs!G:G,,0) -> -81.9 | H33: =_xlfn.XLOOKUP($A33,Inputs!$A:$A,Inputs!H:H,,0) -> 58.5 | I33: =_xlfn.XLOOKUP($A33,Inputs!$A:$A,Inputs!I:I,,0) -> -6.9 | J33: =_xlfn.XLOOKUP($A33,Inputs!$A:$A,Inputs!J:J,,0) -> 36.4 | K33: =_xlfn.XLOOKUP($A33,Inputs!$A:$A,Inputs!K:K,,0) -> 2.8 | L33: =_xlfn.XLOOKUP($A33,Inputs!$A:$A,Inputs!L:L,,0) -> -132.9 | M33: =_xlfn.XLOOKUP($A33,Inputs!$A:$A,Inputs!M:M,,0) -> -160.6 | N33: =_xlfn.XLOOKUP($A33,Inputs!$A:$A,Inputs!N:N,,0) -> -163.2
A34: Capex + Investments | B34: =+B32+B33 -> -55.9 | C34: =+C32+C33 -> 763.9 | D34: =+D32+D33 -> -1325.1 | E34: =+E32+E33 -> -72.8 | F34: =+F32+F33 -> -502.3 | G34: =+G32+G33 -> -134.9 | H34: =+H32+H33 -> -76.8 | I34: =+I32+I33 -> -74.1 | ... N34: =+N32+N33 -> -166.8
A35: Dividends + Share Buyback | B35: =+B27+B28 -> -604.3 | C35: =+C27+C28 -> -1991.2 | D35: =+D27+D28 -> -741.8 | E35: =+E27+E28 -> -1080.1 | F35: =+F27+F28 -> -145.1 | G35: =+G27+G28 -> -211.8 | H35: =+H27+H28 -> -446.3 | I35: =+I27+I28 -> -110.8 | ... N35: =+N27+N28 -> 0
A36: Payout Ratio | B36: =IFERROR(B35/B23,"-") -> -0.5251586 | C36: =IFERROR(C35/C23,"-") -> -2.3226408 | D36: =IFERROR(D35/D23,"-") -> -1.2224786 | E36: =IFERROR(E35/E23,"-") -> -2.2110542 | F36: =IFERROR(F35/F23,"-") -> -0.43744347 | G36: =IFERROR(G35/G23,"-") -> -0.63756773 | H36: =IFERROR(H35/H23,"-") -> -14.213376 | I36: =IFERROR(I35/I23,"-") -> -3.4409938 | ... N36: =IFERROR(N35/N23,"-") -> 0
A38: Assets
A39: Cash & Eq. | B39: =_xlfn.XLOOKUP($A39,Inputs!$A:$A,Inputs!B:B,,0) -> 2186.8 | C39: =_xlfn.XLOOKUP($A39,Inputs!$A:$A,Inputs!C:C,,0) -> 1682.9 | D39: =_xlfn.XLOOKUP($A39,Inputs!$A:$A,Inputs!D:D,,0) -> 1319.1 | E39: =_xlfn.XLOOKUP($A39,Inputs!$A:$A,Inputs!E:E,,0) -> 1061.8 | F39: =_xlfn.XLOOKUP($A39,Inputs!$A:$A,Inputs!F:F,,0) -> 1222.5 | G39: =_xlfn.XLOOKUP($A39,Inputs!$A:$A,Inputs!G:G,,0) -> 1112.4 | H39: =_xlfn.XLOOKUP($A39,Inputs!$A:$A,Inputs!H:H,,0) -> 811 | I39: =_xlfn.XLOOKUP($A39,Inputs!$A:$A,Inputs!I:I,,0) -> 709 | J39: =_xlfn.XLOOKUP($A39,Inputs!$A:$A,Inputs!J:J,,0) -> 543 | K39: =_xlfn.XLOOKUP($A39,Inputs!$A:$A,Inputs!K:K,,0) -> 283.3 | L39: =_xlfn.XLOOKUP($A39,Inputs!$A:$A,Inputs!L:L,,0) -> 115.9 | M39: =_xlfn.XLOOKUP($A39,Inputs!$A:$A,Inputs!M:M,,0) -> 123 | N39: =_xlfn.XLOOKUP($A39,Inputs!$A:$A,Inputs!N:N,,0) -> 72
A40: Accounts Receivable | B40: =_xlfn.XLOOKUP($A40,Inputs!$A:$A,Inputs!B:B,,0) -> 1013.8 | C40: =_xlfn.XLOOKUP($A40,Inputs!$A:$A,Inputs!C:C,,0) -> 1261.7 | D40: =_xlfn.XLOOKUP($A40,Inputs!$A:$A,Inputs!D:D,,0) -> 807.7 | E40: =_xlfn.XLOOKUP($A40,Inputs!$A:$A,Inputs!E:E,,0) -> 720 | F40: =_xlfn.XLOOKUP($A40,Inputs!$A:$A,Inputs!F:F,,0) -> 544.3 | G40: =_xlfn.XLOOKUP($A40,Inputs!$A:$A,Inputs!G:G,,0) -> 444.5 | H40: =_xlfn.XLOOKUP($A40,Inputs!$A:$A,Inputs!H:H,,0) -> 348.2 | I40: =_xlfn.XLOOKUP($A40,Inputs!$A:$A,Inputs!I:I,,0) -> 313 | J40: =_xlfn.XLOOKUP($A40,Inputs!$A:$A,Inputs!J:J,,0) -> 259.6 | K40: =_xlfn.XLOOKUP($A40,Inputs!$A:$A,Inputs!K:K,,0) -> 184.7 | L40: =_xlfn.XLOOKUP($A40,Inputs!$A:$A,Inputs!L:L,,0) -> 130.5 | M40: =_xlfn.XLOOKUP($A40,Inputs!$A:$A,Inputs!M:M,,0) -> 107.6 | N40: =_xlfn.XLOOKUP($A40,Inputs!$A:$A,Inputs!N:N,,0) -> 95.5
A41: Inventory | B41: =_xlfn.XLOOKUP($A41,Inputs!$A:$A,Inputs!B:B,,0) -> 467.5 | C41: =_xlfn.XLOOKUP($A41,Inputs!$A:$A,Inputs!C:C,,0) -> 264.6 | D41: =_xlfn.XLOOKUP($A41,Inputs!$A:$A,Inputs!D:D,,0) -> 175.8 | E41: =_xlfn.XLOOKUP($A41,Inputs!$A:$A,Inputs!E:E,,0) -> 139.8 | F41: =_xlfn.XLOOKUP($A41,Inputs!$A:$A,Inputs!F:F,,0) -> 117.9 | G41: =_xlfn.XLOOKUP($A41,Inputs!$A:$A,Inputs!G:G,,0) -> 90 | H41: =_xlfn.XLOOKUP($A41,Inputs!$A:$A,Inputs!H:H,,0) -> 77.3 | I41: =_xlfn.XLOOKUP($A41,Inputs!$A:$A,Inputs!I:I,,0) -> 106.9 | J41: =_xlfn.XLOOKUP($A41,Inputs!$A:$A,Inputs!J:J,,0) -> 83.9 | K41: =_xlfn.XLOOKUP($A41,Inputs!$A:$A,Inputs!K:K,,0) -> 69.5 | L41: =_xlfn.XLOOKUP($A41,Inputs!$A:$A,Inputs!L:L,,0) -> 48.7 | M41: =_xlfn.XLOOKUP($A41,Inputs!$A:$A,Inputs!M:M,,0) -> 21.1 | N41: =_xlfn.XLOOKUP($A41,Inputs!$A:$A,Inputs!N:N,,0) -> 16.2
A42: Property, Plant and Equipment | B42: =_xlfn.XLOOKUP($A42,Inputs!$A:$A,Inputs!B:B,,0) -> 1370.1 | C42: =_xlfn.XLOOKUP($A42,Inputs!$A:$A,Inputs!C:C,,0) -> 1275 | D42: =_xlfn.XLOOKUP($A42,Inputs!$A:$A,Inputs!D:D,,0) -> 964.4 | E42: =_xlfn.XLOOKUP($A42,Inputs!$A:$A,Inputs!E:E,,0) -> 669.8 | F42: =_xlfn.XLOOKUP($A42,Inputs!$A:$A,Inputs!F:F,,0) -> 525.6 | G42: =_xlfn.XLOOKUP($A42,Inputs!$A:$A,Inputs!G:G,,0) -> 382.2 | H42: =_xlfn.XLOOKUP($A42,Inputs!$A:$A,Inputs!H:H,,0) -> 340.6 | I42: =_xlfn.XLOOKUP($A42,Inputs!$A:$A,Inputs!I:I,,0) -> 207.7 | J42: =_xlfn.XLOOKUP($A42,Inputs!$A:$A,Inputs!J:J,,0) -> 140.1 | K42: =_xlfn.XLOOKUP($A42,Inputs!$A:$A,Inputs!K:K,,0) -> 94.7 | L42: =_xlfn.XLOOKUP($A42,Inputs!$A:$A,Inputs!L:L,,0) -> 78.5 | M42: =_xlfn.XLOOKUP($A42,Inputs!$A:$A,Inputs!M:M,,0) -> 56.9 | N42: =_xlfn.XLOOKUP($A42,Inputs!$A:$A,Inputs!N:N,,0) -> 31.8
A43: Other Assets | B43: =_xlfn.XLOOKUP($A43,Inputs!$A:$A,Inputs!B:B,,0) -> 2459.4 | C43: =_xlfn.XLOOKUP($A43,Inputs!$A:$A,Inputs!C:C,,0) -> 1715.6 | D43: =_xlfn.XLOOKUP($A43,Inputs!$A:$A,Inputs!D:D,,0) -> 2594.6 | E43: =_xlfn.XLOOKUP($A43,Inputs!$A:$A,Inputs!E:E,,0) -> 1403.8 | F43: =_xlfn.XLOOKUP($A43,Inputs!$A:$A,Inputs!F:F,,0) -> 1430.9 | G43: =_xlfn.XLOOKUP($A43,Inputs!$A:$A,Inputs!G:G,,0) -> 1048.9 | H43: =_xlfn.XLOOKUP($A43,Inputs!$A:$A,Inputs!H:H,,0) -> 680.8 | I43: =_xlfn.XLOOKUP($A43,Inputs!$A:$A,Inputs!I:I,,0) -> 803.3 | J43: =_xlfn.XLOOKUP($A43,Inputs!$A:$A,Inputs!J:J,,0) -> 763.9 | K43: =_xlfn.XLOOKUP($A43,Inputs!$A:$A,Inputs!K:K,,0) -> 792.6 | L43: =_xlfn.XLOOKUP($A43,Inputs!$A:$A,Inputs!L:L,,0) -> 794.9 | M43: =_xlfn.XLOOKUP($A43,Inputs!$A:$A,Inputs!M:M,,0) -> 666.9 | N43: =_xlfn.XLOOKUP($A43,Inputs!$A:$A,Inputs!N:N,,0) -> 519.2
A44: Total Assets | B44: =_xlfn.XLOOKUP($A44,Inputs!$A:$A,Inputs!B:B,,0) -> 7479.3 | C44: =_xlfn.XLOOKUP($A44,Inputs!$A:$A,Inputs!C:C,,0) -> 6228 | D44: =_xlfn.XLOOKUP($A44,Inputs!$A:$A,Inputs!D:D,,0) -> 5919.1 | E44: =_xlfn.XLOOKUP($A44,Inputs!$A:$A,Inputs!E:E,,0) -> 4044.5 | F44: =_xlfn.XLOOKUP($A44,Inputs!$A:$A,Inputs!F:F,,0) -> 3885.5 | G44: =_xlfn.XLOOKUP($A44,Inputs!$A:$A,Inputs!G:G,,0) -> 3078 | H44: =_xlfn.XLOOKUP($A44,Inputs!$A:$A,Inputs!H:H,,0) -> 2257.9 | I44: =_xlfn.XLOOKUP($A44,Inputs!$A:$A,Inputs!I:I,,0) -> 2139.9 | J44: =_xlfn.XLOOKUP($A44,Inputs!$A:$A,Inputs!J:J,,0) -> 1790.5 | K44: =_xlfn.XLOOKUP($A44,Inputs!$A:$A,Inputs!K:K,,0) -> 1424.8 | L44: =_xlfn.XLOOKUP($A44,Inputs!$A:$A,Inputs!L:L,,0) -> 1168.5 | M44: =_xlfn.XLOOKUP($A44,Inputs!$A:$A,Inputs!M:M,,0) -> 975.5 | N44: =_xlfn.XLOOKUP($A44,Inputs!$A:$A,Inputs!N:N,,0) -> 734.7
A47: Liabilities
A48: Current Liabilities | B48: =_xlfn.XLOOKUP($A48,Inputs!$A:$A,Inputs!B:B,,0) -> 3649 | C48: =_xlfn.XLOOKUP($A48,Inputs!$A:$A,Inputs!C:C,,0) -> 3078.4 | D48: =_xlfn.XLOOKUP($A48,Inputs!$A:$A,Inputs!D:D,,0) -> 2318.1 | E48: =_xlfn.XLOOKUP($A48,Inputs!$A:$A,Inputs!E:E,,0) -> 1829.5 | F48: =_xlfn.XLOOKUP($A48,Inputs!$A:$A,Inputs!F:F,,0) -> 1 473,6 | G48: =_xlfn.XLOOKUP($A48,Inputs!$A:$A,Inputs!G:G,,0) -> 1 256,4 | H48: =_xlfn.XLOOKUP($A48,Inputs!$A:$A,Inputs!H:H,,0) -> 1 027,2 | I48: =_xlfn.XLOOKUP($A48,Inputs!$A:$A,Inputs!I:I,,0) -> 829,4 | J48: =_xlfn.XLOOKUP($A48,Inputs!$A:$A,Inputs!J:J,,0) -> 678,7 | K48: =_xlfn.XLOOKUP($A48,Inputs!$A:$A,Inputs!K:K,,0) -> 496,5 | L48: =_xlfn.XLOOKUP($A48,Inputs!$A:$A,Inputs!L:L,,0) -> 413,1 | M48: =_xlfn.XLOOKUP($A48,Inputs!$A:$A,Inputs!M:M,,0) -> 319.3 | N48: =_xlfn.XLOOKUP($A48,Inputs!$A:$A,Inputs!N:N,,0) -> 266.9
A49: Short-Term Debt | B49: =_xlfn.XLOOKUP($A49,Inputs!$A:$A,Inputs!B:B,,0) -> 0 | C49: =_xlfn.XLOOKUP($A49,Inputs!$A:$A,Inputs!C:C,,0) -> 0 | D49: =_xlfn.XLOOKUP($A49,Inputs!$A:$A,Inputs!D:D,,0) -> 0 | E49: =_xlfn.XLOOKUP($A49,Inputs!$A:$A,Inputs!E:E,,0) -> 0 | F49: =_xlfn.XLOOKUP($A49,Inputs!$A:$A,Inputs!F:F,,0) -> 0 | G49: =_xlfn.XLOOKUP($A49,Inputs!$A:$A,Inputs!G:G,,0) -> 0 | H49: =_xlfn.XLOOKUP($A49,Inputs!$A:$A,Inputs!H:H,,0) -> 0 | I49: =_xlfn.XLOOKUP($A49,Inputs!$A:$A,Inputs!I:I,,0) -> 0 | J49: =_xlfn.XLOOKUP($A49,Inputs!$A:$A,Inputs!J:J,,0) -> 0 | K49: =_xlfn.XLOOKUP($A49,Inputs!$A:$A,Inputs!K:K,,0) -> 0 | L49: =_xlfn.XLOOKUP($A49,Inputs!$A:$A,Inputs!L:L,,0) -> 0 | M49: =_xlfn.XLOOKUP($A49,Inputs!$A:$A,Inputs!M:M,,0) -> 0 | N49: =_xlfn.XLOOKUP($A49,Inputs!$A:$A,Inputs!N:N,,0) -> 0
A50: Short-Term Leases | B50: =_xlfn.XLOOKUP($A50,Inputs!$A:$A,Inputs!B:B,,0) -> 0 | C50: =_xlfn.XLOOKUP($A50,Inputs!$A:$A,Inputs!C:C,,0) -> 33.2 | D50: =_xlfn.XLOOKUP($A50,Inputs!$A:$A,Inputs!D:D,,0) -> 26.3 | E50: =_xlfn.XLOOKUP($A50,Inputs!$A:$A,Inputs!E:E,,0) -> 19.1 | F50: =_xlfn.XLOOKUP($A50,Inputs!$A:$A,Inputs!F:F,,0) -> 15.5 | G50: 0 | H50: =_xlfn.XLOOKUP($A50,Inputs!$A:$A,Inputs!H:H,,0) -> 0 | I50: =_xlfn.XLOOKUP($A50,Inputs!$A:$A,Inputs!I:I,,0) -> 0 | J50: =_xlfn.XLOOKUP($A50,Inputs!$A:$A,Inputs!J:J,,0) -> 0 | K50: =_xlfn.XLOOKUP($A50,Inputs!$A:$A,Inputs!K:K,,0) -> 0 | L50: =_xlfn.XLOOKUP($A50,Inputs!$A:$A,Inputs!L:L,,0) -> 0 | M50: =_xlfn.XLOOKUP($A50,Inputs!$A:$A,Inputs!M:M,,0) -> 0 | N50: =_xlfn.XLOOKUP($A50,Inputs!$A:$A,Inputs!N:N,,0) -> 0
A51: Other current liabilities | B51: =_xlfn.XLOOKUP($A51,Inputs!$A:$A,Inputs!B:B,,0) -> 3395.1 | C51: =_xlfn.XLOOKUP($A51,Inputs!$A:$A,Inputs!C:C,,0) -> 2801.8 | D51: =_xlfn.XLOOKUP($A51,Inputs!$A:$A,Inputs!D:D,,0) -> 2143.4 | E51: =_xlfn.XLOOKUP($A51,Inputs!$A:$A,Inputs!E:E,,0) -> 1668.8 | F51: =_xlfn.XLOOKUP($A51,Inputs!$A:$A,Inputs!F:F,,0) -> 1361.7 | G51: =_xlfn.XLOOKUP($A51,Inputs!$A:$A,Inputs!G:G,,0) -> 1170 | H51: =_xlfn.XLOOKUP($A51,Inputs!$A:$A,Inputs!H:H,,0) -> 957.2 | I51: =_xlfn.XLOOKUP($A51,Inputs!$A:$A,Inputs!I:I,,0) -> 772.7 | J51: =_xlfn.XLOOKUP($A51,Inputs!$A:$A,Inputs!J:J,,0) -> 617.2 | K51: =_xlfn.XLOOKUP($A51,Inputs!$A:$A,Inputs!K:K,,0) -> 446.6 | L51: =_xlfn.XLOOKUP($A51,Inputs!$A:$A,Inputs!L:L,,0) -> 377.5 | M51: =_xlfn.XLOOKUP($A51,Inputs!$A:$A,Inputs!M:M,,0) -> 298.5 | N51: =_xlfn.XLOOKUP($A51,Inputs!$A:$A,Inputs!N:N,,0) -> 247.1
A52: Non-current Liabilities | B52: =_xlfn.XLOOKUP($A52,Inputs!$A:$A,Inputs!B:B,,0) -> 3756.2 | C52: =_xlfn.XLOOKUP($A52,Inputs!$A:$A,Inputs!C:C,,0) -> 3431.2 | D52: =_xlfn.XLOOKUP($A52,Inputs!$A:$A,Inputs!D:D,,0) -> 2819.3 | E52: =_xlfn.XLOOKUP($A52,Inputs!$A:$A,Inputs!E:E,,0) -> 1359 | F52: =_xlfn.XLOOKUP($A52,Inputs!$A:$A,Inputs!F:F,,0) -> 1090 | G52: =_xlfn.XLOOKUP($A52,Inputs!$A:$A,Inputs!G:G,,0) -> 811.4 | H52: =_xlfn.XLOOKUP($A52,Inputs!$A:$A,Inputs!H:H,,0) -> 641.3 | I52: =_xlfn.XLOOKUP($A52,Inputs!$A:$A,Inputs!I:I,,0) -> 472.9 | J52: =_xlfn.XLOOKUP($A52,Inputs!$A:$A,Inputs!J:J,,0) -> 356.4 | K52: =_xlfn.XLOOKUP($A52,Inputs!$A:$A,Inputs!K:K,,0) -> 252.3 | L52: =_xlfn.XLOOKUP($A52,Inputs!$A:$A,Inputs!L:L,,0) -> 169.6 | M52: =_xlfn.XLOOKUP($A52,Inputs!$A:$A,Inputs!M:M,,0) -> 145.1 | N52: =_xlfn.XLOOKUP($A52,Inputs!$A:$A,Inputs!N:N,,0) -> 109.5
A53: Long-Term Debt | B53: =_xlfn.XLOOKUP($A53,Inputs!$A:$A,Inputs!B:B,,0) -> 991.8 | C53: =_xlfn.XLOOKUP($A53,Inputs!$A:$A,Inputs!C:C,,0) -> 990.4 | D53: =_xlfn.XLOOKUP($A53,Inputs!$A:$A,Inputs!D:D,,0) -> 988.4 | E53: =_xlfn.XLOOKUP($A53,Inputs!$A:$A,Inputs!E:E,,0) -> 0 | F53: =_xlfn.XLOOKUP($A53,Inputs!$A:$A,Inputs!F:F,,0) -> 0 | G53: =_xlfn.XLOOKUP($A53,Inputs!$A:$A,Inputs!G:G,,0) -> 0 | H53: =_xlfn.XLOOKUP($A53,Inputs!$A:$A,Inputs!H:H,,0) -> 0 | I53: =_xlfn.XLOOKUP($A53,Inputs!$A:$A,Inputs!I:I,,0) -> 0 | J53: =_xlfn.XLOOKUP($A53,Inputs!$A:$A,Inputs!J:J,,0) -> 0 | K53: =_xlfn.XLOOKUP($A53,Inputs!$A:$A,Inputs!K:K,,0) -> 0 | L53: =_xlfn.XLOOKUP($A53,Inputs!$A:$A,Inputs!L:L,,0) -> 0 | M53: =_xlfn.XLOOKUP($A53,Inputs!$A:$A,Inputs!M:M,,0) -> 0 | N53: =_xlfn.XLOOKUP($A53,Inputs!$A:$A,Inputs!N:N,,0) -> 0
A54: Long-Term Leases | B54: =_xlfn.XLOOKUP($A54,Inputs!$A:$A,Inputs!B:B,,0) -> 62.5 | C54: =_xlfn.XLOOKUP($A54,Inputs!$A:$A,Inputs!C:C,,0) -> 62.5 | D54: =_xlfn.XLOOKUP($A54,Inputs!$A:$A,Inputs!D:D,,0) -> 40.5 | E54: =_xlfn.XLOOKUP($A54,Inputs!$A:$A,Inputs!E:E,,0) -> 34 | F54: =_xlfn.XLOOKUP($A54,Inputs!$A:$A,Inputs!F:F,,0) -> 30.6 | G54: =_xlfn.XLOOKUP($A54,Inputs!$A:$A,Inputs!G:G,,0) -> 0 | H54: =_xlfn.XLOOKUP($A54,Inputs!$A:$A,Inputs!H:H,,0) -> 0 | I54: =_xlfn.XLOOKUP($A54,Inputs!$A:$A,Inputs!I:I,,0) -> 0 | J54: =_xlfn.XLOOKUP($A54,Inputs!$A:$A,Inputs!J:J,,0) -> 0 | K54: =_xlfn.XLOOKUP($A54,Inputs!$A:$A,Inputs!K:K,,0) -> 0 | L54: =_xlfn.XLOOKUP($A54,Inputs!$A:$A,Inputs!L:L,,0) -> 0 | M54: =_xlfn.XLOOKUP($A54,Inputs!$A:$A,Inputs!M:M,,0) -> 0 | N54: =_xlfn.XLOOKUP($A54,Inputs!$A:$A,Inputs!N:N,,0) -> 0
A55: Other non-current liabilities | B55: =_xlfn.XLOOKUP($A55,Inputs!$A:$A,Inputs!B:B,,0) -> 2701.9 | C55: =_xlfn.XLOOKUP($A55,Inputs!$A:$A,Inputs!C:C,,0) -> 2378.3 | D55: =_xlfn.XLOOKUP($A55,Inputs!$A:$A,Inputs!D:D,,0) -> 1790.4 | E55: =_xlfn.XLOOKUP($A55,Inputs!$A:$A,Inputs!E:E,,0) -> 1325 | F55: =_xlfn.XLOOKUP($A55,Inputs!$A:$A,Inputs!F:F,,0) -> 1059.4 | G55: =_xlfn.XLOOKUP($A55,Inputs!$A:$A,Inputs!G:G,,0) -> 811.4 | H55: =_xlfn.XLOOKUP($A55,Inputs!$A:$A,Inputs!H:H,,0) -> 641.3 | I55: =_xlfn.XLOOKUP($A55,Inputs!$A:$A,Inputs!I:I,,0) -> 472.9 | J55: =_xlfn.XLOOKUP($A55,Inputs!$A:$A,Inputs!J:J,,0) -> 356.4 | K55: =_xlfn.XLOOKUP($A55,Inputs!$A:$A,Inputs!K:K,,0) -> 252.3 | L55: =_xlfn.XLOOKUP($A55,Inputs!$A:$A,Inputs!L:L,,0) -> 169.6 | M55: =_xlfn.XLOOKUP($A55,Inputs!$A:$A,Inputs!M:M,,0) -> 145.1 | N55: =_xlfn.XLOOKUP($A55,Inputs!$A:$A,Inputs!N:N,,0) -> 109.5
