Workbook
Name _msoanchor_1: Segments!$C$5
Name Sectors: 'Sector Impact'!$K$4:$K$16

Sheet OP
B2: 45039 | C2: Team 1 | E2: =Inputs!H3 -> #VALUE! | L2: NYSE | M2: SIC:
D3: COMPANY DESCRIPTION | H3: CEO & BOARD OF DIRECTORS
D4: Uber Technologies, Inc. is a technology platform that uses a massive network, leading technology, operational excellence and product expertise to power movement from point A to point B. They develop and operate proprietary technology applications supporting a variety of offerings on their platform. Uber connects consumers with independent providers of ride services for ride sharing services, and connects riders and other consumers with restaurants, grocers and other stores with delivery service providers. Uber uses the same network technology, operational excellence and product expertise to connect shippers with carriers in the freight industry. | H4: Name | I4: Gender | J4: Age | K4: Tenure | L4: Executive? | M4: Other roles
H5: Ronald Sugar | I5: Male | J5: 73 | K5: 4 | L5: No | M5: (Chair)Former Chairperson and CEO, Northrop Grumman
H6: Ursula Burns | I6: Female | J6: 63 | K6: 5 | L6: No | M6: Chairman and Former CEO, VEON
H7: Dara Khosrowshahi | I7: Male | J7: 52 | K7: 5 | L7: Yes | M7: CEO, Uber
H8: Wan Ling Martello | I8: Female | J8: 63 | K8: 5 | L8: No | M8: Co-founder and Partner, BayPine; Former Executive Vice President, Nestle
H9: John ThainFormer | I9: Male | J9: 66 | K9: 5 | L9: No | M9: Chairman and CEO, CIT Group
H10: David TrujilloPartner, | I10: Male | J10: 46 | K10: 5 | L10: No | M10: TPG
H11: Amanda GinsbergFormer | I11: Female | J11: 52 | K11: 3 | L11: No | M11: CEO, Match Group
H12: Robert EckertPartner | I12: Male | J12: 67 | K12: 3 | L12: No | M12: FFL Partners; Former CEO, Mattel
H13: Revathi Advaithi | I13: Female | J13: 54 | K13: 2 | L13: No | M13: CEO, Flex Ltd.
B14: USD MILLIONS | H14: Alexander Wynaendts | I14: Male | J14: 61 | K14: 2 | L14: No | M14: Former CEO and Chairman of Aegon
B15: COMPANY OVERVIEW
B16: Stock | D16: Liquidity and Solvency | F16: Segments | I16: Profitability (2022) | L16: Multiples
B17: Last Price | C17: 47.24 | D17: Total Assets | E17: =_xlfn.XLOOKUP(D17,'Fin. Data'!A:A,'Fin. Data'!B:B,,0) -> 32109 | F17: Regions | H17: % Sales | I17: Reporting Year | J17: 2022 | L17: Float | M17: =1-0.17% -> 0.9983
B18: Outstanding Shares | C18: 2009557000 | D18: Total Liabilities | E18: =_xlfn.XLOOKUP(D18,'Fin. Data'!A:A,'Fin. Data'!B:B,,0) -> 23605 | F18: =+Segments!C5 -> North America (US & Canada) | H18: =+Segments!B5 -> 0.609375 | I18: End of Year | J18: 1 October 2022 | L18: Insiders Own | M18: 0.0017
B19: Market Cap. | C19: =C17*C18/1000000 -> 94931.473 | D19: Cash/Share | E19: =_xlfn.XLOOKUP("Cash & Eq.",'Fin. Data'!A:A,'Fin. Data'!B:B,,0)*1000000/C18 -> 2.0939939 | F19: =+Segments!C6 -> EMEA (Europe Middle East and Africa) | H19: =+Segments!B6 -> 0.21875 | I19: EBITDA | K19: =_xlfn.XLOOKUP(I19,'Fin. Data'!A:A,'Fin. Data'!B:B,,0) -> 6144 | L19: b (Yahoo) | M19: 1.22
B20: +Total Debt | C20: ='Fin. Data'!B58 -> 11139 | D20: EBIDTA/Net Financial Cost (NFC) | E20: ='Fin. Data (Common Size)'!B19/(-'Fin. Data (Common Size)'!B14) -> 14.422535 | F20: =+Segments!C7 -> APAC (Asia Pacific) | H20: =+Segments!B7 -> 0.109375 | I20: Depreciation & Amortization | K20: =_xlfn.XLOOKUP(I20,'Fin. Data'!A:A,'Fin. Data'!B:B,,0) -> 947 | L20: Score (S&P) | M20: -
B21: -Cash | C21: ='Fin. Data'!B39 -> 4208 | D21: Debt/EBITDA | E21: =_xlfn.XLOOKUP("Total Debt",'Fin. Data'!A:A,'Fin. Data'!B:B,,0)/_xlfn.XLOOKUP("EBITDA",'Fin. Data'!A:A,'Fin. Data'!B:B,,0) -> 1.8129883 | F21: =+Segments!C8 -> Latin America | H21: =+Segments!B8 -> 0.0625 | I21: EBIT | K21: =_xlfn.XLOOKUP(I21,'Fin. Data'!A:A,'Fin. Data'!B:B,,0) -> 5197 | L21: Price/Book Value | M21: =IFERROR((C17*C18/(E17-E18))/1000000,"") -> 11.163155
B22: =Enterprise Value | C22: =C19+C20-C21 -> 101862.47 | D22: "Others Assets"/Asset | E22: =_xlfn.XLOOKUP("Other Assets",'Fin. Data'!A:A,'Fin. Data'!B:B,,0)/_xlfn.XLOOKUP("Total Assets",'Fin. Data'!A:A,'Fin. Data'!B:B,,0) -> 0.64533308 | I22: Net Income | K22: =_xlfn.XLOOKUP(I22,'Fin. Data'!A:A,'Fin. Data'!B:B,,0) -> -9141 | L22: NCF(3y avg)/Asset | M22: =IFERROR(K28/E17,"") -> -0.17030531
B23: Holdings (nac/int'l) | C23: - | D23: Debt/Assets | E23: =_xlfn.XLOOKUP(D23,'Fin. Data'!A:A,'Fin. Data'!B:B,,0) -> 0.34691208 | F23: Categories | H23: % Sales | I23: EPS | K23: =1000000*K22/C18 -> -4.5487637 | L23: Price/Net Inc. (3y avg) | M23: =IFERROR(C19/K27,"") -> -17.360221
B24: t liq. (Holdings/Vol.) | C24: - | D24: EBITDA Margin (average) | E24: =AVERAGE(_xlfn.XLOOKUP("EBITDA Margin",'Fin. Data'!A:A,'Fin. Data'!B:D,,0)) -> -0.13430104 | F24: =Segments!C16 -> Mobility | H24: =Segments!B16 -> 0.44009788 | I24: ROA | K24: =K22/E17 -> -0.28468654 | L24: EV/Asset | M24: =IFERROR(C22/E17,"") -> 3.1723963
B25: % Short | C25: 0.0249 | D25: Operating Margin (average) | E25: =AVERAGE(_xlfn.XLOOKUP("Operating Margin",'Fin. Data'!A:A,'Fin. Data'!B:D,,0)) -> -0.23789854 | F25: =Segments!C17 -> Delivery | H25: =Segments!B17 -> 0.3419707 | I25: ROIC | K25: =K22/(E17-(E18-C20)) -> -0.46535662 | L25: EV/Ebidta (3y average) | M25: =IFERROR(C22/K26,"") -> -111.40628
B26: Traffic ESG | D26: Net Income Margin (average) | E26: =AVERAGE(_xlfn.XLOOKUP("Net Income Margin",'Fin. Data'!A:A,'Fin. Data'!B:D,,0)) -> -0.30758978 | F26: =Segments!C18 -> Freight | H26: =Segments!B18 -> 0.21793142 | I26: EBITDA (3y average) | K26: =AVERAGE(_xlfn.XLOOKUP("EBITDA",'Fin. Data'!A:A,'Fin. Data'!B:D,,0)) -> -914.33333 | L26: Price/NCF (3y average) | M26: =IFERROR(C19/K28,"") -> -17.360221
B27: E | F27: =Segments!C19 -> All other | H27: =Segments!B19 -> 0 | I27: Net Income (3y average) | K27: =AVERAGE(_xlfn.XLOOKUP("Net Income",'Fin. Data'!A:A,'Fin. Data'!B:D,,0)) -> -5468.3333 | L27: Bonds 1,3,5a (USD) | M27: -
B28: S | D28: Net Financial Cost/Avg Net Debt | E28: =-_xlfn.XLOOKUP("Net Financial Cost",'Fin. Data'!A:A,'Fin. Data'!B:B,,0)/AVERAGE(_xlfn.XLOOKUP("Net Debt",'Fin. Data'!A:A,'Fin. Data'!B:D,,0)) -> 0.073562424 | I28: NCF (3y average) | K28: =AVERAGE(_xlfn.XLOOKUP("Net Income",'Fin. Data'!A:A,'Fin. Data'!B:D,,0)) -> -5468.3333 | L28: Div+Rep.(3y avg)/Price | M28: =-IFERROR(SUM(E49:E51)/(3*C19),"") -> 0
B29: G | L29: Div. Yield | M29: =-IFERROR(L50/C19,"") -> 0
B30: INVESTMENT THESIS
B31: Pillars of Recommendation | H31: Recommendation
B32: Pillar | C32: Explanation | H32: SELL | I32: CHECK DCF
B33: Competitive Position | C33: It is a market leader in the ride-sharing industry, with a significant share of the global market.
B34: Technological Innovation | C34: Investments in emerging technologies, such as autonomous vehicles and electric scooters
B35: Network Effects | C35: Uber's platform benefits from network effects, as more drivers and riders join, making it more attractive to both parties.
B36: Risks of Investment | H36: Price Target | I36: Valuation
B37: Risk | C37: Explanation | H37: =DCF!D75 -> 37.604479 | I37: Discount Rate | J37: =DCF!F50 -> 0.101 | L37: Downside | M37: =DCF!D74 -> -0.20396953
B38: Regulatory Environment | C38: Changes in regulations can significantly impact Uber's operations.
B39: Dependence on Gig Workers | C39: The model of relying on gig workers can lead to labor disputes and potential increased costs.
B40: Competition | C40: Uber faces strong competition from other ride-sharing and food delivery companies, both domestically and internationally.
B41: FINANCIAL PERFORMANCE
B42: Year | C42: Net Sales | D42: Operating Margin | E42: Dividends + Share Buyback | F42: Net Cash Flow | G42: Debt/Assets | H42: Depreciation & Amortization | I42: Capex + Investments | J42: Cash Flow
B43: =B44-1 -> 2014 | C43: {=_xlfn.SORTBY(TRANSPOSE(_xlfn.XLOOKUP(C$42,'Fin. Data'!$A:$A,'Fin. Data'!$B:$J,,0)),$B$43:$B$51,-1)} -> 0 | D43: {=_xlfn.SORTBY(TRANSPOSE(_xlfn.XLOOKUP(D$42,'Fin. Data'!$A:$A,'Fin. Data'!$B:$J,,0)),$B$43:$B$51,-1)} -> - | E43: {=_xlfn.SORTBY(TRANSPOSE(_xlfn.XLOOKUP(E$42,'Fin. Data'!$A:$A,'Fin. Data'!$B:$J,,0)),$B$43:$B$51,-1)} -> 0 | F43: =Inputs!J77 -> 0 | G43: {=_xlfn.SORTBY(TRANSPOSE(_xlfn.XLOOKUP(G$42,'Fin. Data'!$A:$A,'Fin. Data'!$B:$J,,0)),$B$43:$B$51,-1)} -> - | H43: {=_xlfn.SORTBY(TRANSPOSE(_xlfn.XLOOKUP(H$42,'Fin. Data'!$A:$A,'Fin. Data'!$B:$J,,0)),$B$43:$B$51,-1)} -> 0 | I43: {=_xlfn.SORTBY(TRANSPOSE(_xlfn.XLOOKUP(I$42,'Fin. Data'!$A:$A,'Fin. Data'!$B:$J,,0)),$B$43:$B$51,-1)} -> 0 | L43: =J17 -> 2022 | M43: =L43-1 -> 2021
B44: =B45-1 -> 2015 | C44: 0 | D44: - | E44: 0 | F44: =Inputs!I77 -> 0 | G44: - | H44: 0 | I44: 0 | J44: Net Income | L44: =_xlfn.XLOOKUP($J44,'Fin. Data'!$A:$A,'Fin. Data'!B:B,,0) -> -9141 | M44: =_xlfn.XLOOKUP($J44,'Fin. Data'!$A:$A,'Fin. Data'!C:C,,0) -> -496 | O44: =(D44/D43)-1 -> #VALUE!
B45: =B46-1 -> 2016 | C45: 0 | D45: - | E45: 0 | F45: =Inputs!H77 -> 0 | G45: - | H45: 0 | I45: 0 | J45: Operating CF | L45: =_xlfn.XLOOKUP($J45,'Fin. Data'!$A:$A,'Fin. Data'!B:B,,0) -> 642 | M45: =_xlfn.XLOOKUP($J45,'Fin. Data'!$A:$A,'Fin. Data'!C:C,,0) -> -445 | O45: =(D45/D44)-1 -> #VALUE! | Q45: =F45/F44-1 -> #DIV/0! | R45: =H45/H44-1 -> #DIV/0! | S45: =I45/I44-1 -> #DIV/0!
B46: =B47-1 -> 2017 | C46: 7932 | D46: -0.51437216 | E46: -131 | F46: =Inputs!G77 -> -868 | G46: 0 | H46: 510 | I46: 0 | J46: Investing CF | L46: =_xlfn.XLOOKUP($J46,'Fin. Data'!$A:$A,'Fin. Data'!B:B,,0) -> -1637 | M46: =_xlfn.XLOOKUP($J46,'Fin. Data'!$A:$A,'Fin. Data'!C:C,,0) -> -1201 | O46: =(D46/D45)-1 -> #VALUE! | Q46: =F46/F45-1 -> #DIV/0! | R46: =H46/H45-1 -> #DIV/0! | S46: =I46/I45-1 -> #DIV/0!
B47: =B48-1 -> 2018 | C47: 10433 | D47: -0.29071216 | E47: -10 | F47: =Inputs!F77 -> 2285 | G47: 0.28635151 | H47: 426 | I47: -1034 | J47: Net Capex | L47: =_xlfn.XLOOKUP($J47,'Fin. Data'!$A:$A,'Fin. Data'!B:B,,0) -> -252 | M47: =_xlfn.XLOOKUP($J47,'Fin. Data'!$A:$A,'Fin. Data'!C:C,,0) -> -298 | N47: =(C47/C46)-1 -> 0.31530509 | O47: =(D47/D46)-1 -> -0.43482135 | Q47: =F47/F46-1 -> -3.6324885 | R47: =H47/H46-1 -> -0.16470588 | S47: =I47/I46-1 -> #DIV/0!
B48: =B49-1 -> 2019 | C48: 13000 | D48: -0.66123077 | E48: 0 | F48: =Inputs!E77 -> 3824 | G48: 0.23380876 | H48: 472 | I48: -841 | J48: Investments & Acquisitions | L48: =_xlfn.XLOOKUP($J48,'Fin. Data'!$A:$A,'Fin. Data'!B:B,,0) -> -1139 | M48: =_xlfn.XLOOKUP($J48,'Fin. Data'!$A:$A,'Fin. Data'!C:C,,0) -> -618 | N48: =(C48/C47)-1 -> 0.2460462 | O48: =(D48/D47)-1 -> 1.2745205 | Q48: =F48/F47-1 -> 0.67352298 | R48: =H48/H47-1 -> 0.10798122 | S48: =I48/I47-1 -> -0.18665377
B49: =B50-1 -> 2020 | C49: 11139 | D49: -0.4365742 | E49: 0 | F49: =Inputs!D77 -> -4327 | G49: 0.27905088 | H49: 575 | I49: -2747 | J49: Financing CF | L49: =_xlfn.XLOOKUP($J49,'Fin. Data'!$A:$A,'Fin. Data'!B:B,,0) -> 15 | M49: =_xlfn.XLOOKUP($J49,'Fin. Data'!$A:$A,'Fin. Data'!C:C,,0) -> 1780 | N49: =(C49/C48)-1 -> -0.14315385 | O49: =(D49/D48)-1 -> -0.33975517 | Q49: =F49/F48-1 -> -2.1315377 | R49: =H49/H48-1 -> 0.21822034 | S49: =I49/I48-1 -> 2.2663496
B50: =B51-1 -> 2021 | C50: 17455 | D50: -0.21965053 | E50: 0 | F50: =Inputs!C$77 -> 65 | G50: 0.28640326 | H50: 902 | I50: -916 | J50: Dividends | L50: =_xlfn.XLOOKUP($J50,'Fin. Data'!$A:$A,'Fin. Data'!B:B,,0) -> 0 | M50: =_xlfn.XLOOKUP($J50,'Fin. Data'!$A:$A,'Fin. Data'!C:C,,0) -> 0 | N50: =(C50/C49)-1 -> 0.56701679 | O50: =(D50/D49)-1 -> -0.49687698 | Q50: =F50/F49-1 -> -1.015022 | R50: =H50/H49-1 -> 0.56869565 | S50: =I50/I49-1 -> -0.66654532
B51: =J17 -> 2022 | C51: 31877 | D51: -0.057470904 | E51: 0 | F51: =Inputs!B77 -> -1128 | G51: 0.34691208 | H51: 947 | I51: -1391 | J51: Share Buyback | L51: =_xlfn.XLOOKUP($J51,'Fin. Data'!$A:$A,'Fin. Data'!B:B,,0) -> 0 | M51: =_xlfn.XLOOKUP($J51,'Fin. Data'!$A:$A,'Fin. Data'!C:C,,0) -> 0 | N51: =(C51/C50)-1 -> 0.8262389 | O51: =(D51/D50)-1 -> -0.73835299 | Q51: =F51/F50-1 -> -18.353846 | R51: =H51/H50-1 -> 0.049889135 | S51: =I51/I50-1 -> 0.51855895
B52: Annual Growth Rate | C52: =IFERROR((C51/C46)^(1/8)-1,"") -> 0.18990377 | D52: =IFERROR((D51/D46)^(1/8)-1,"") -> -0.23963639 | F52: =IFERROR((F51/F46)^(1/8)-1,"") -> 0.033293439 | H52: =IFERROR((H51/H46)^(1/8)-1,"") -> 0.080432092 | J52: FX | L52: =_xlfn.XLOOKUP($J52,'Fin. Data'!$A:$A,'Fin. Data'!B:B,,0) -> -148 | M52: =_xlfn.XLOOKUP($J52,'Fin. Data'!$A:$A,'Fin. Data'!C:C,,0) -> -69 | N52: =(C52/C51)-1 -> -0.99999404 | O52: =(D52/D51)-1 -> 3.1696994
B53: Average Growth Rate | C53: =IFERROR(AVERAGE(N47:N51),"") -> 0.36229063 | D53: =IFERROR(AVERAGE(O47:O51),"") -> -0.1470572 | F53: =IFERROR(AVERAGE(Q47:Q51),"") -> -4.8918743 | H53: =IFERROR(AVERAGE(S48:S51),"") -> 0.48292736 | J53: Changes in Cash | L53: =L45-L46+L49-L50-L51 -> 2294 | M53: =M45-M46+M49-M50-M51 -> 2536
B54: CVAR | C54: =IFERROR(STDEV(C44:C51)/AVERAGE(C44:C51),"") -> 0.89046009 | D54: =IFERROR(STDEV(D43:D51)/AVERAGE(D43:D51),"") -> -0.59844245 | F54: =IFERROR(STDEV(F43:F51)/AVERAGE(F43:F51),"") -> -136.06483 | H54: =IFERROR(STDEV(H43:H51)/AVERAGE(H43:H51),"") -> 0.86047304 | J54: Inventory/D Revenues | L54: =IFERROR(SUM(I48:I51)/(C51-C47),"") -> -0.27490207 | M54: =IFERROR((SUM(I48:I51)-SUM(H48:H51))/(C51-C47),"") -> -0.4099515
B55: Last Year | C55: =IFERROR(C51/C50-1,"") -> 0.8262389 | D55: =IFERROR(1-(D51/D50),"") -> 0.73835299 | F55: =IFERROR(1-(F51/F50),"") -> 18.353846 | H55: =IFERROR(1-(H51/H50),"") -> -0.049889135 | J55: t inversiones; t adq. neto dep. | L55: =IFERROR(L54/E24,"") -> 2.0469094 | M55: =IFERROR(M54/E24,"") -> 3.0524818
B56: QUALITATIVE ANALYSIS
B57: SWOT ANALYSIS | J57: HOLDERS
B58: Pros | E58: Cons
B59: Well-recognized brand, high standard of service, verified drivers and cars, operational cost are quite low as it relies on customer-to-driver interaction, very little competition. A major competitor is Lyft | E59: Drivers Dependence, meaning that the company´s reputation is dependent on their representatives on the ground. Drivers Unhapiness, Uber does not regulate their prices with economic changes. Increased Competition.
B69: Opportunities | E69: Risks
B70: Exploit new and big markets in countries like India where taxi services are inconvenient and expensive, tap growing markets in suburban areas where taxi services are not available. | E70: Lawsuits and Regulations, the company struggles to comply with the regulations of different countries. Employee Retention, employees can easily leave if they are unhappy with the company. High Competition, passengers have got a lot of options available to them, and they choose the cheapest ride available.
B79: NOTES | G79: STOCK PERFORMANCE (5 years)
G104: Nasdaq | H104: =Peers!C6 -> #VALUE! | J104: =Peers!D6 -> #VALUE! | L104: =Peers!E6 -> #VALUE! | M104: =Peers!F6 -> #VALUE!

Sheet Segments
B2: ="Regions "&"("&OP!J17&")" -> Regions (2022) | Q2: Products
D3: Nominal value | K3: YoY Growth
B4: Weight | C4: Region | D4: =OP!J17 -> 2022 | E4: =D4-1 -> 2021 | F4: =E4-1 -> 2020 | G4: =F4-1 -> 2019 | H4: =G4-1 -> 2018 | I4: =H4-1 -> 2017 | K4: =OP!J17 -> 2022 | L4: =K4-1 -> 2021 | M4: =L4-1 -> 2020 | N4: =M4-1 -> 2019 | O4: =N4-1 -> 2018 | P4: =O4-1 -> 2017
B5: =IFERROR(D5/D11,"") -> 0.609375 | C5: North America (US & Canada) | D5: 19500 | E5: 10000 | F5: 6082 | G5: 8805 | H5: 6521 | K5: =(D5-E5)/E5 -> 0.95 | L5: =(E5-F5)/F5 -> 0.64419599 | M5: =(F5-G5)/G5 -> -0.3092561 | N5: =(G5-H5)/H5 -> 0.35025303 | O5: - | P5: -
B6: =IFERROR(D6/D11,"") -> 0.21875 | C6: EMEA (Europe Middle East and Africa) | D6: 7000 | E6: 3200 | F6: 1800 | G6: 2148 | H6: 1721 | K6: =(D6-E6)/E6 -> 1.1875 | L6: =(E6-F6)/F6 -> 0.77777778 | M6: =(F6-G6)/G6 -> -0.16201117 | N6: =(G6-H6)/H6 -> 0.24811156 | O6: - | P6: -
B7: =IFERROR(D7/D11,"") -> 0.109375 | C7: APAC (Asia Pacific) | D7: 3500 | E7: 2700 | F7: 1500 | G7: 1247 | H7: 1026 | K7: =(D7-E7)/E7 -> 0.2962963 | L7: =(E7-F7)/F7 -> 0.8 | M7: =(F7-G7)/G7 -> 0.20288693 | N7: =(G7-H7)/H7 -> 0.21539961 | O7: - | P7: -
B8: =IFERROR(D8/D11,"") -> 0.0625 | C8: Latin America | D8: 2000 | E8: 1400 | F8: 1300 | G8: 1947 | H8: 2002 | K8: =(D8-E8)/E8 -> 0.42857143 | L8: =(E8-F8)/F8 -> 0.076923077 | M8: =(F8-G8)/G8 -> -0.33230611 | N8: =(G8-H8)/H8 -> -0.027472527 | O8: - | P8: -
B9: =IFERROR(D9/D11,"") -> 0 | G9: =SUM(5032*(D9/$D$11)) -> 0
B10: =IFERROR(D10/D11,"") -> 0 | G10: =SUM(5032*(D10/$D$11)) -> 0
B11: =SUM(B5:B10) -> 1 | C11: TOTAL | D11: =SUM(D5:D10) -> 32000 | E11: =SUM(E5:E10) -> 17300 | F11: =SUM(F5:F10) -> 10682 | G11: =SUM(G5:G10) -> 14147 | H11: =SUM(H5:H10) -> 11270 | I11: =SUM(I5:I10) -> 0 | K11: =(D11-E11)/E11 -> 0.84971098 | L11: =(E11-F11)/F11 -> 0.6195469 | M11: =(F11-G11)/G11 -> -0.24492825 | N11: =(G11-H11)/H11 -> 0.2552795 | O11: =(H11-I11)/I11 -> #DIV/0! | P11: =(I11-J11)/J11 -> #DIV/0!
B13: ="Categories "&"("&OP!J17&")" -> Categories (2022)
D14: Nominal value | K14: YoY Growth
B15: Weight | C15: Category | D15: =OP!J17 -> 2022 | E15: =D15-1 -> 2021 | F15: =E15-1 -> 2020 | G15: =F15-1 -> 2019 | H15: =G15-1 -> 2018 | I15: =H15-1 -> 2017 | K15: =OP!J17 -> 2022 | L15: =K15-1 -> 2021 | M15: =L15-1 -> 2020 | N15: =M15-1 -> 2019 | O15: =N15-1 -> 2018 | P15: =O15-1 -> 2017
B16: =IFERROR(D16/D20,"") -> 0.44009788 | C16: Mobility | D16: 14029 | E16: 6953 | F16: 6089 | G16: 10745 | H16: 9437 | K16: =(D16-E16)/E16 -> 1.0176902 | L16: =(E16-F16)/F16 -> 0.14189522 | M16: =(F16-G16)/G16 -> -0.43331782 | N16: =(G16-H16)/H16 -> 0.13860337 | O16: - | P16: -
B17: =IFERROR(D17/D20,"") -> 0.3419707 | C17: Delivery | D17: 10901 | E17: 8362 | F17: 3904 | G17: 2510 | H17: 1460 | K17: =(D17-E17)/E17 -> 0.30363549 | L17: =(E17-F17)/F17 -> 1.1419057 | M17: =(F17-G16)/G16 -> -0.63666822 | N17: =(G16-H17)/H17 -> 6.359589 | O17: - | P17: -
B18: =IFERROR(D18/D20,"") -> 0.21793142 | C18: Freight | D18: 6947 | E18: 2132 | F18: 1011 | G18: 731 | H18: 356 | K18: =(D18-E18)/E18 -> 2.2584428 | L18: =(E18-F18)/F18 -> 1.1088032 | M18: =(F18-G18)/G18 -> 0.38303694 | N18: =(G18-H18)/H18 -> 1.0533708 | O18: - | P18: -
B19: =IFERROR(D19/D20,"") -> 0 | C19: All other | D19: 0 | E19: 8 | F19: 135 | G19: 119 | H19: 17 | K19: =(D19-E19)/E19 -> -1 | L19: =(E19-F19)/F19 -> -0.94074074 | M19: =(F19-G19)/G19 -> 0.13445378 | N19: =(G19-H19)/H19 -> 6 | O19: - | P19: -
B20: =SUM(B16:B19) -> 1 | C20: TOTAL | D20: =SUM(D16:D19) -> 31877 | E20: =SUM(E16:E19) -> 17455 | F20: =SUM(F16:F19) -> 11139 | G20: =SUM(G16:G19) -> 14105 | H20: =SUM(H16:H19) -> 11270 | K20: =(D20-E20)/E20 -> 0.8262389 | L20: =(E20-F20)/F20 -> 0.56701679 | M20: =(F20-G20)/G20 -> -0.21028004 | N20: =(G20-H20)/H20 -> 0.2515528 | O20: =(H20-I20)/I20 -> #DIV/0! | P20: =(I20-J20)/J20 -> #DIV/0!
B22: Categories | D22: Description | I22: Graphs
B23: Mobility | D23: Mobility products Connect consumers with Drivers who provide rides in a variety of vehicles, such as cars, auto rickshaws, motorbikes, minibuses, or taxis. Mobility also includes activity related to our Financial Partnerships and Transit offerings.
B24: Delivery | D24: Delivery offerings allow consumers to search for and discover local restaurants, order a meal, and either pickup at the restaurant or have the meal delivered. In certain markets, Delivery also includes offerings for grocery, alcohol and convenience store delivery as well as select other goods
B25: Freight | D25: Freight connects carriers with shippers on our platform, and gives carriers upfront, transparent pricing and the ability to book a shipment. Freight also includes transportation management and other logistics services offerings.
B26: All other | D26: This segment includes revenue from other businesses and operations, such as sales of ecosystem products, licensing, and other miscellaneous items.
B30: Industry | I30: Graphs (Industry Forecasts)
B31: Drivers | D31: <
B32: Network effect | D32: One of the most important comparative advantages is the network effect that the platform has. Uber essentially benefits from what can be called hyperlocal network effects. The introduction of a new driver only improves the service for those who live in the same locality. An additional supply unit (i.e. driver) in Lisbon does not necessarily affect someone's experience in Porto. In sum, Uber's strategy is to create such an extensive network that leads to a liquidity network effect. A large driver supply leads to lower wait times and fares, which attracts more riders. Therefore Uber is clearly cheaper than a taxi and on average cheaper than other platforms according to investopedia.
B33: Delivery | D33: Uber Eats stands out from other food applications in its unparalleled understanding of "you." Through meticulous customer order recording and analysis, it accurately discerns individual preferences. By intuitively offering precisely what users desire, the app effortlessly tempts customers, making the ordering process a breeze. Furthermore, UberEats competitors are ignoring a very important perspective of the user ratings and feedback for the creation of a best customer experience. It offers two opinions to customer whether the service and food delivered is good or bad. This customer rating is giving a leverage to UberEATs according to CAA.
B34: Sales forecast
B35: Source | D35: Market Growth CGAR | G35: Period
B36: Grandviewresearch for Mobility | D36: 0.166 | G36: 2023-2030
B37: Grandviewresearch for Delivery | D37: 0.103 | G37: 2023-2030
B38: Coherentmarketinsights for Mobility | D38: 0.19 | G38: 2022-2030
B39: Brandessenceresearch for Mobility | D39: 0.172 | G39: 2018-2025
B40: Average | D40: =AVERAGE(D36:F39) -> 0.15775 | G40: 2023-2028
B41: Company's Strategy / Extra Notes
B42: In view of the need for innovation Uber has launched several iniciatives such as:
B43: 1. "Go-Get" where families can now set up profiles that link multiple Uber accounts together so that customers can pay for rides and deliveries from a centralized account. That centralized account will also be home to real-time location and order updates. This feature is aimes to attract a new set of customers from teens as young as 13 and families who want to link accounts to even those who might feel more comfortable calling for a ride instead of using the app at all.
B44: 2. "Uber Business Comfort" which is a ride type exclusive to business travelers. The offering includes priority pickup, newer cars, more legroom, highly rated drivers, and custom preferences. Travelers using Uber Business Comfort will also have access to a designated, 24/7 personalized support service. Within the Uber and Uber Eats app is a business hub to manage their travel needs, view their employee perks and travel policies, and travel and meal programs. Uber is also experimenting with additional benefits for business travelers, including exclusive Uber One membership promotions and the ability to earn personal perks like Uber Cash.
B45: 3. "Uber Travel", which imports flights, hotel and restaurant reservations into the Uber app to simplify the process of requesting rides related to those bookings. In this app the user will be abel to use Uber Explore, which enables users to book activities from companies including Viator and then reserve a ride to the location as well.
B46: As evident from its track record, Uber exemplifies a proactive and forward-thinking corporate entity that is bound to not only survive but also flourish in the coming years, thanks to its relentless pursuit of innovation and entrepreneurial spirit. The company's unwavering commitment to staying ahead of the curve and anticipating market trends positions it as a potential trailblazer in the ever-evolving business landscape. With its innovative ethos deeply ingrained in its culture, Uber is poised to leverage cutting-edge technologies and novel business models, setting new benchmarks and conquering challenges in the dynamic future ahead.
B47: Some extra notes that should be mentioned, in terms of:
B48: Mobility: Uber's strategy is to create such an extensive network that leads to a liquidity network effect: a large driver supply leads to lower wait times and fares, which attracts more riders. This, in turn, increases the earning potential for drivers, leading to more drivers joining the platform. Therefore, Uber rides will continue to grow, especially since Uber is expanding to other countries (which ones? how many countries are they in already?). Furthermore, the CFO stated, 'Looking ahead, we are focused on extending our product, scale, and platform advantages to sustain market-leading top and bottom-line growth beyond 2023.' They are interested in achieving lower costs and high returns. In the long term, they need to be aware of competitors such as Bolt, Cabify, and Lyft and must innovate to stay competitive.
B49: Delivery: The Uber Eats service is expected to grow not only because of the same motives as the Mobility service but also because it's becoming a useful tool for the younger generations. However, I do not see older generations changing their behavior that much since they are accustomed to other customs. In the long term, I could not find recent innovations to the platform, which leads me to believe that Uber Eats needs to come up with transformations in some way to have an absolute advantage over its competitors such as Glove, DoorDash, Swiggy, and GrubHub.
B50: Freight: The Uber Freight platform is still a young and recent service from Uber. However, it has been growing at tremendous rates. As it is an infant service, the main operations are still centered in the US. However, in other continents such as the EU, Asia, and Africa, the market is still unexplored. Although it's not a new innovation, I believe that because of Uber's well-established brand, it will lead to major growth for the sector and the company.
B51: Remaining Segments: as showed on the data previously described, other segments are beoming increasily irrelevant, therefore I would suggest that innovation will be essential for uber to come up with additional segments of activity.

Sheet Acuerdo
A1: Invertir
A2: NO invertir
A3: Mantener sin elevar posición
A4: Mantener (y seguir comprando)
A5: Liquidar
A6: PENDIENTE

Sheet Peers
B1: Peer Logo | C1: Peer Name | D1: Description
C2: #VALUE! | D2: Didi Global is a leading Chinese transportation technology company founded in 2012. It has grown into one of the world's largest ride-hailing platforms, operating in over 15 countries and 400 cities globally. Didi connects millions of riders with a vast network of drivers, offering a range of transportation options from standard cars to premium vehicles. The company places a strong emphasis on safety, employing advanced technology and comprehensive screening processes. Didi's services extend beyond ride-hailing, encompassing solutions like bike-sharing, food delivery, and more. With a commitment to innovation and accessibility, Didi Global continues to shape the landscape of urban mobility worldwide.
C3: #VALUE! | D3: Lyft is a prominent transportation network company founded in 2012, based in San Francisco, California. It operates a user-friendly mobile app that connects riders with drivers for convenient and reliable ridesharing services. Lyft offers various ride options, including standard vehicles, shared rides, and luxury cars, catering to diverse transportation needs. Committed to safety, Lyft implements stringent driver screening and provides real-time tracking for secure journeys. The company has expanded its services to include bike and scooter rentals, and it actively promotes sustainable transportation solutions. Lyft's dedication to accessibility and innovation has solidified its position as a major player in the global ride-hailing industry.
C4: #VALUE! | D4: Grab is a Southeast Asian super app founded in 2012, headquartered in Singapore. It began as a ride-hailing platform but swiftly evolved into a multi-service platform offering services like food delivery, digital payments, and more. Grab operates in over 400 cities across 8 countries, providing a wide range of services to millions of users. The company emphasizes safety, convenience, and accessibility, and aims to address various everyday needs of its diverse user base, making it a dominant player in the Southeast Asian technology and transportation ecosystem.
B6: In Millions USD (exc Market Cap) | C6: #VALUE! | D6: #VALUE! | E6: #VALUE! | F6: #VALUE! | G6: AVERAGE
B7: Company Info | G7: =IFERROR(AVERAGE(C7:F7),"")
B8: Market Cap | C8: =OP!C19 -> 94931.473 | D8: 15430 | E8: 4230 | F8: 12400 | G8: =IFERROR(AVERAGE(C8:F8),"") -> 31747.868
B9: Net Sales (current) | C9: =C51 -> 31877 | D9: =D51 -> 140791.68 | E9: =E51 -> 4095.135 | F9: =F51 -> 1433 | G9: =IFERROR(AVERAGE(C9:F9),"") -> 44549.204
B10: Profitability | G10: =IFERROR(AVERAGE(C10:F10),"")
B11: Sales Growth (ttm) | C11: =C51/C50-1 -> 0.8262389 | D11: =D51/D50-1 -> -0.1900471 | E11: =E51/E50-1 -> 0.27640983 | F11: =F51/F50-1 -> 1.122963 | G11: =IFERROR(AVERAGE(C11:F11),"") -> 0.50889115
B12: Sales Growth (36m) | C12: =C51/C49-1 -> 1.4520769 | D12: =D51/D49-1 -> -0.090411493 | E12: =E51/E49-1 -> 0.73179173 | F12: =F51/F49-1 -> 2.0554371 | G12: =IFERROR(AVERAGE(C12:F12),"") -> 1.0372236
B13: Operating Margin | C13: =C54/C51 -> -0.057470904 | D13: =D54/D51 -> -0.12660167 | E13: =E54/E51 -> -0.3562559 | F13: =F54/F51 -> -0.9581298 | G13: =IFERROR(AVERAGE(C13:F13),"") -> -0.37461457
B14: Net Income Margin | C14: =C57/C51 -> 0.28675848 | D14: =D57/D51 -> 0.16893043 | E14: =E57/E51 -> -0.38704463 | F14: =F57/F51 -> -1.1744592 | G14: =IFERROR(AVERAGE(C14:F14),"") -> -0.27645372
B15: Return on Equity (RoE) | C15: =C57/C68 -> 1.1321526 | D15: =D57/D68 -> 0.24963217 | E15: =E57/E68 -> -4.0780306 | F15: =F57/F68 -> -0.25281658 | G15: =IFERROR(AVERAGE(C15:F15),"") -> -0.73726561
B16: Return on Invested Capital (ROIC) | C16: =(C57+C56)/(C67+C68) -> 0.46635091 | D16: =(D57+D56)/(D67+D68) -> 0.21584026 | E16: =(E57+E56)/(E67+E68) -> 3.5974785 | F16: =(F57+F56)/(F67+F68) -> -0.21214421 | G16: =IFERROR(AVERAGE(C16:F16),"") -> 1.0168814
B17: Solvency | G17: =IFERROR(AVERAGE(C17:F17),"")
B18: Debt/Assets | C18: =C67/C64 -> 0.34691208 | D18: =D67/D64 -> 0.13373675 | E18: =E67/E64 -> 0.17623443 | F18: =F67/F64 -> 0.13609597 | G18: =IFERROR(AVERAGE(C18:F18),"") -> 0.19824481
B19: Net Debt/EBITDA | C19: =(C67-C59)/C53 -> 1.1280924 | D19: =(D67-D59)/D53 -> 0.26077651 | E19: =(E67-E59)/E53 -> -0.3947882 | F19: =(F67-F59)/F53 -> 0.57704918 | G19: =IFERROR(AVERAGE(C19:F19),"") -> 0.39278248
B20: Interest Coverage Ratio | C20: =-C53/C55 -> 14.422535 | D20: =-D53/D55 -> 11.404098 | E20: =-E53/E55 -> -69.578947 | F20: =-F53/F55 -> -3.4560907 | G20: =IFERROR(AVERAGE(C20:F20),"") -> -11.802101
B21: Liquidity
B22: Current Ratio | C22: =C62/C66 -> 1.0447306 | D22: =D62/D66 -> 2.5212799 | E22: =E62/E66 -> 0.82451941 | F22: =F62/F66 -> 5.1850501 | G22: =IFERROR(AVERAGE(C22:F22),"") -> 2.393895
B23: Quick Ratio | C23: =(C59+C60)/C66 -> 0.78922399 | D23: =(D59+D60)/D66 -> 1.1411726 | E23: =(E59+E60)/E66 -> 0.089731635 | F23: =(F59+F60)/F66 -> 2.118505 | G23: =IFERROR(AVERAGE(C23:F23),"") -> 1.0346583
B24: Activity | G24: =IFERROR(AVERAGE(C24:F24),"")
B25: Inventory Turnover | C25: =C52/C61 -> #DIV/0! | D25: =D52/D61 -> #DIV/0! | E25: =E52/E61 -> #DIV/0! | F25: =F52/F61 -> 28.25 | G25: =IFERROR(AVERAGE(C25:F25),"")
B26: Acc. Receivable Turnover | C26: =C51/C60 -> 11.470673 | D26: =D51/D60 -> 62.518509 | E26: =E51/E60 -> #DIV/0! | F26: =F51/F60 -> 3.8521505 | G26: =IFERROR(AVERAGE(C26:F26),"")
A27: Price/Sales | B27: Payables Turnover | C27: =C52/C65 -> 27.004121 | D27: =D52/D65 -> 40.348396 | E27: =E52/E65 -> 22.594744 | F27: =F52/F65 -> 1.4533762 | G27: =IFERROR(AVERAGE(C27:F27),"") -> 22.850159
B28: Fixed Asset Turnover | C28: =C51/C63 -> 15.310759 | D28: =D51/D63 -> 24.62254 | E28: =E51/E63 -> 13.066716 | F28: =F51/F63 -> 2.9126016 | G28: =IFERROR(AVERAGE(C28:F28),"") -> 13.978154
B29: Total Asset Turnover | C29: =C51/C64 -> 0.99277461 | D29: =D51/D64 -> 1.073001 | E29: =E51/E64 -> 0.89875936 | F29: =F51/F64 -> 0.15627045 | G29: =IFERROR(AVERAGE(C29:F29),"") -> 0.78020136
B30: Valuation | G30: =IFERROR(AVERAGE(C30:F30),"")
B31: Price/Earnings | C31: =C8/C57 -> 10.385239 | D31: =D8/D57 -> 0.64875547 | E31: =E8/E57 -> -2.6687697 | F31: =F8/F57 -> -7.3677956 | G31: =IFERROR(AVERAGE(C31:F31),"") -> 0.24935737
B32: Price/Sales | C32: 2.83 | D32: =D8/D51 -> 0.10959454 | E32: =E8/E51 -> 1.032933 | F32: =F8/F51 -> 8.6531752 | G32: =IFERROR(AVERAGE(C32:F32),"") -> 3.1564257
B33: Price/Book | C33: =12.98 -> 12.98 | D33: =D8/D68 -> 0.16195024 | E33: =E8/E68 -> 10.883325 | F33: =F8/F68 -> 1.8627009 | G33: =IFERROR(AVERAGE(C33:F33),"") -> 6.4719939
B34: EV/Sales | C34: =(C67+C8-C59)/C51 -> 3.1954849 | D34: =(D67+D8-D59)/D51 -> 0.086105939 | E34: =(E67+E8-E59)/E51 -> 1.1603793 | F34: =(F67+F8-F59)/F51 -> 8.1618981 | G34: =IFERROR(AVERAGE(C34:F34),"") -> 3.1509671
B35: EV/EBITDA | C35: =(C67+C8-C59)/C53 -> 16.579178 | D35: =(D67+D8-D59)/D53 -> -0.95597025 | E35: =(E67+E8-E59)/E53 -> -3.5944856 | F35: =(F67+F8-F59)/F53 -> -9.5868852 | G35: =IFERROR(AVERAGE(C35:F35),"") -> 0.61045934
B36: Stock Info | G36: =IFERROR(AVERAGE(C36:F36),"")
B37: Float | C37: =OP!M17 -> 0.9983 | D37: 0.991 | E37: 0.1734 | F37: 0.5269 | G37: =IFERROR(AVERAGE(C37:F37),"") -> 0.6724
B38: b (Yahoo) | C38: =OP!M19 -> 1.22 | D38: 0.66 | E38: 0.99 | F38: 0.17 | G38: =IFERROR(AVERAGE(C38:F38),"") -> 0.76
B39: Dividend Yield (yahoo finance) | C39: =OP!M29 -> 0 | D39: 0.0252 | E39: 0 | F39: 0.0262 | G39: =IFERROR(AVERAGE(C39:F39),"") -> 0.01285
B40: Stock Performance
B41: 1y | C41: 0.59 | D41: 0.94 | E41: -0.18 | F41: 0.2 | G41: =IFERROR(AVERAGE(C41:F41),"") -> 0.3875
B42: 3y | C42: 0.25 | D42: - | E42: -0.56 | F42: - | G42: =IFERROR(AVERAGE(C42:F42),"") -> -0.155
B43: Current Price | C43: {=_FV(C6,"Preço")} -> 74.84 | D43: {=_FV(D6,"Preço")} -> 4.8495 | E43: {=_FV(E6,"Preço")} -> 12.025 | F43: {=_FV(F6,"Preço")} -> 4.63 | G43: =IFERROR(AVERAGE(C43:F43),"") -> 24.086125
B44: Average Target Price | C44: 57.2 | D44: 4.49 | E44: 12.3 | F44: 4.77 | G44: =IFERROR(AVERAGE(C44:F44),"") -> 19.69
B45: Upside/Downside | C45: =C44/C43-1 -> -0.23570283 | D45: =D44/D43-1 -> -0.074131354 | E45: =E44/E43-1 -> 0.022869023 | F45: =F44/F43-1 -> 0.030237581 | G45: =IFERROR(AVERAGE(C45:F45),"") -> -0.064181896
B47: Financial Data | C47: #VALUE! | D47: #VALUE! | E47: #VALUE! | F47: #VALUE!
B48: IS
B49: Net Sales (36m ago) | C49: ='Fin. Data'!E5 -> 13000 | D49: 154786.13 | E49: 2364.681 | F49: 469
B50: Net Sales (12m ago) | C50: ='Fin. Data'!C5 -> 17455 | D50: 173827 | E50: 3208.323 | F50: 675
B51: Net Sales (current) | C51: ='Fin. Data'!B5 -> 31877 | D51: 140791.68 | E51: 4095.135 | F51: 1433
B52: COGS | C52: ='Fin. Data'!B5-'Fin. Data'!B7 -> 19659 | D52: 115799.9 | E52: 2435.736 | F52: 1356
B53: EBITDA | C53: ='Fin. Data'!B19 -> 6144 | D53: -12681.357 | E53: -1322 | F53: -1220
B54: Operating Income | C54: ='Fin. Data'!B11 -> -1832 | D54: -17824.462 | E54: -1458.916 | F54: -1373
B55: Net Financial Cost | C55: ='Fin. Data'!B14 -> -426 | D55: 1112 | E55: -19 | F55: -353
B56: Taxes | C56: =+Inputs!B11 -> -181 | D56: 568 | E56: 5872 | F56: 6
B57: Net Income | C57: 9141 | D57: 23784 | E57: -1585 | F57: -1683
B58: BS
B59: Cash & Eq. | C59: ='Fin. Data'!B39 -> 4208 | D59: 20855 | E59: 281.09 | F59: 1952
B60: Acc. Receivables | C60: ='Fin. Data'!B40 -> 2779 | D60: 2252 | E60: 0 | F60: 372
B61: Inventory | C61: ='Fin. Data'!B41 -> 0 | D61: 0 | E61: 0 | F61: 48
B62: Current Assets | C62: =Inputs!B27 -> 9249 | D62: 51052.061 | E62: 2582.859 | F62: 5688
B63: Fixed Assets | C63: ='Fin. Data'!B42 -> 2082 | D63: 5718 | E63: 313.402 | F63: 492
B64: Total Assets | C64: ='Fin. Data'!B44 -> 32109 | D64: 131213 | E64: 4556.431 | F64: 9170
B65: Acc. Payable | C65: =Inputs!B43 -> 728 | D65: 2870 | E65: 107.801 | F65: 933
B66: Current Liabilities | C66: =Inputs!B42 -> 8853 | D66: 20248.47 | E66: 3132.563 | F66: 1097
B67: Total Debt | C67: ='Fin. Data'!B58 -> 11139 | D67: 17548 | E67: 803 | F67: 1248
B68: Total Equity | C68: ='Fin. Data'!B64 -> 8074 | D68: 95276.181 | E68: 388.668 | F68: 6657
C70: =+C67/C68 -> 1.3796136 | D70: =+D67/D68 -> 0.18418035 | E70: =+E67/E68 -> 2.0660306 | F70: =+F67/F68 -> 0.18747183

Sheet ESG
B1: Company GICS Sector: | T1: Yes
B2: Information Technology | C2: <- Select Industry | T2: No
B3: ESG Analysis | K3: Relative ESG Analysis
B4: Parameters | C4: Impact | D4: Do they report? | E4: Ranking | F4: Mitigation Plan | G4: Traffic Lights | H4: Improvement over time? | I4: Targets / Goals? | J4: Comments | K4: Parameters | L4: UBER TECHNOLOGIES, INC. (XNYS:UBER) | M4: #VALUE! | N4: #VALUE! | O4: #VALUE!
B5: Environmental | K5: Ratios
A6: 1 | B6: CO2 Direct Emissions | C6: =VLOOKUP($B$2,'Sector Impact'!$K$4:$AA$16,A6+1,FALSE) -> Medium | D6: Yes | E6: Medium | F6: Yes | H6: Yes | I6: • Targets • 2030: 100% of rides in Canada, Europe, and the US are zero-emission • 2030: Net-zero climate emissions from all corporate operations (such as offices and data centers) • 2040: 100% of rides globally are in zero-emission vehicles (ZEVs), on micromobility, and/or on public transit • 2040: Net-zero climate emissions across all lines of business (mobility, delivery, and freight) and operations | K6: CO2 Emissions/$M Sales | L6: =L12/L$11 -> 0.72189133 | M6: =M12/M$11 -> 0 | N6: =N12/N$11 -> 0.3395025 | O6: =O12/O$11 -> 4.9144356 | P6: =P12/P$11 -> #DIV/0! | Q6: =Q12/Q$11 -> #DIV/0!
A7: 2 | B7: Total Water Consumption | C7: =VLOOKUP($B$2,'Sector Impact'!$K$4:$AA$16,A7+1,FALSE) -> Low | K7: Water Consumption/$M Sales | L7: =L13/L$11 -> 0.025169495 | M7: =M13/M$11 -> 0 | N7: =N13/N$11 -> 0 | O7: =O13/O$11 -> 0 | P7: =P13/P$11 -> #DIV/0! | Q7: =Q13/Q$11 -> #DIV/0!
A8: 3 | B8: Total Energy Consumption | C8: =VLOOKUP($B$2,'Sector Impact'!$K$4:$AA$16,A8+1,FALSE) -> High | D8: Yes | E8: "Villain" | F8: Yes | H8: No | I8: Uber is committed to matching 100% of energy use in our US workplaces with renewable energy by 2025 | K8: Energy Consumption/$M Sales | L8: =L14/L$11 -> 11.533057 | M8: =M14/M$11 -> 0 | N8: =N14/N$11 -> 0.0004545 | O8: =O14/O$11 -> 116.23975 | P8: =P14/P$11 -> #DIV/0! | Q8: =Q14/Q$11 -> #DIV/0!
A9: 4 | B9: Waste Management | C9: =VLOOKUP($B$2,'Sector Impact'!$K$4:$AA$16,A9+1,FALSE) -> Low | K9: Waste Production/$M Sales | L9: =L15/L$11 -> 0.001 | M9: =M15/M$11 -> 0.001 | N9: =N15/N$11 -> 0.001 | O9: =O15/O$11 -> 0.001 | P9: =P15/P$11 -> #DIV/0! | Q9: =Q15/Q$11 -> #DIV/0!
A10: 5 | B10: Land Degradation/Deforestation/Biodiversity loss/Animal sufering/… | C10: =VLOOKUP($B$2,'Sector Impact'!$K$4:$AA$16,A10+1,FALSE) -> Low | K10: Inputs | L10: UBER TECHNOLOGIES, INC. (XNYS:UBER) | M10: DiDi Global Inc. (OTCM:DIDIY) | N10: LYFT, INC. (XNAS:LYFT) | O10: #VALUE!
B11: Social | K11: Net Sales ($M) | L11: =L15*1000 -> 31877000 | M11: =M15*1000 -> 20412875000 | N11: =N15*1000 -> 4000000 | O11: =O15*1000 -> 675000
A12: 6 | B12: Employee Turnover % | C12: =VLOOKUP($B$2,'Sector Impact'!$K$4:$AA$16,A12+1,FALSE) -> Low | K12: CO2 Emissions Total (Tonnes)/Scope 3 | L12: 23011730 | N12: 1358010 | O12: 3317244
A13: 7 | B13: Salaries & Compensation | C13: =VLOOKUP($B$2,'Sector Impact'!$K$4:$AA$16,A13+1,FALSE) -> Low | K13: Water Consumption Total (Cubic Meters) | L13: 802328
A14: 8 | B14: Reputation | C14: =VLOOKUP($B$2,'Sector Impact'!$K$4:$AA$16,A14+1,FALSE) -> Low | K14: Energy Consumption Total (Gigajoules) | L14: 367639268 | N14: 1818 | O14: 78461833
A15: 9 | B15: Discrimination Events | C15: =VLOOKUP($B$2,'Sector Impact'!$K$4:$AA$16,A15+1,FALSE) -> Low | F15: Yes | K15: Waste Production Total (Tonnes) | L15: 31877 | M15: 20412875 | N15: 4000 | O15: 675
A16: 10 | B16: Work Safety | C16: =VLOOKUP($B$2,'Sector Impact'!$K$4:$AA$16,A16+1,FALSE) -> High | D16: Yes | E16: "Villain" | F16: No | H16: Increase in total recordable incident rate (TRIR) (direct employees/ contractors) | I16: Not clear | J16: Only report US data | K16: ESG Scores
A17: 11 | B17: Damage to consumer health | C17: =VLOOKUP($B$2,'Sector Impact'!$K$4:$AA$16,A17+1,FALSE) -> Low | K17: Refinitiv
A18: 12 | B18: PXP? | C18: =VLOOKUP($B$2,'Sector Impact'!$K$4:$AA$16,A18+1,FALSE) -> Low | K18: Sustainalytics
A19: 13 | B19: Supply chain | C19: =VLOOKUP($B$2,'Sector Impact'!$K$4:$AA$16,A19+1,FALSE) -> Low | K19: ISS
A20: 14 | B20: Community involvement | C20: =VLOOKUP($B$2,'Sector Impact'!$K$4:$AA$16,A20+1,FALSE) -> Low | K20: CDP
A21: 15 | B21: Public Sector | C21: =VLOOKUP($B$2,'Sector Impact'!$K$4:$AA$16,A21+1,FALSE) -> Medium | D21: No | E21: "Villain" | F21: Yes
A22: 16 | B22: Litigation | C22: =VLOOKUP($B$2,'Sector Impact'!$K$4:$AA$16,A22+1,FALSE) -> Very High | D22: Yes | E22: "Villain" | F22: Yes
B23: Corporate Governance | K23: PARAMETERS
A24: 17 | B24: Diversity (Gender, Age, Industry, Region) | E24: "Best in class" | F24: Yes | K24: IMPACT | L24: RANKING | M24: MITIGATION PLAN
A25: 18 | B25: % Independence | E25: "Best in class" | F25: Yes | J25: 90% Independent | K25: Low | L25: "Best in class" | M25: Evidence / plan?
A26: 19 | B26: average time as independent directors | E26: Medium | F26: Yes | J26: 4.4 Avg years of tenure | K26: Medium | L26: Medium High
A27: 20 | B27: Recent departures of directors / C-level executives? | K27: High | L27: Medium
A28: 21 | B28: CEO/Chairman duality | E28: "Best in class" | F28: No | J28: CEO : Dara Khosrowshahi / Ronald Sugar (Chair) | K28: Very high | L28: "Villain"
A29: 22 | B29: Transparency (ESG, segments, acquisitions, other) | E29: "Best in class"
A30: 23 | B30: Time taken to report after the end of the quarter / year | E30: Medium High
A31: 24 | B31: Additional participation of the CEO in other boards or excessive participation of Ch. | E31: "Best in class" | J31: Good balance between Committee Composition
A32: 25 | B32: Audit / Consulting | D32: Yes | E32: Medium High | F32: No | J32: PWC
A33: 26 | B33: ESG-compensation related | D33: Yes | E33: Medium | F33: Yes | I33: CEO’s compensation is tied to the achievement of climate-related objectives | J33: CEO’s compensation is tied to the achievement of climate-related objectives
A34: 27 | B34: Management compensation schemes | D34: Yes | E34: Medium High | F34: Yes | I34: ESG. We continued our progress on our ESG goals in 2022 with the advancement of our zero emission commitments. We started the year with approximately 17,000 average monthly active electric vehicles on the platform and ended the year with approximately 45,700. Usage of our sustainable products (Uber Green, Uber Planet in LATAM, and Comfort Electric in the United States) has also grown by more than 150% year over year. We also submitted our science based targets to the Science Based Targets initiative (SBTi) for validation, and in 2023, Uber’s near and long-term science-based emissions reduction targets were approved by the SBTi. | J34: . The Compensation Committee considers diversity, equity, and inclusion (DEI) metrics when developing compensation plans and includes DEI and cultural goals as metrics in the compensation for Uber’s most senior executives. The Compensation Committee also receives summaries of employee engagement survey results and related matters

Sheet DCF
A1: VALUATION MODEL
G3: Short Term | K3: Long Term
A4: Section | B4: Line # | C4: ITEM | D4: 2020 (Real) | E4: 2021 (Real) | F4: 2022 (Real) | G4: 2023 | H4: =G4+1 -> 2024 | I4: =H4+1 -> 2025 | J4: =I4+1 -> 2026 | K4: =J4+1 -> 2027 | L4: =K4+1 -> 2028 | M4: =L4+1 -> 2029 | N4: =M4+1 -> 2030 | O4: =N4+1 -> 2031 | ... AF4: =AE4+1 -> 2048
A5: INCOME STATEMENT | B5: 1 | C5: Growth | D5: ='Fin. Data'!D6 -> -0.14315385 | E5: =+E6/D6-1 -> 0.56701679 | F5: =+F6/E6-1 -> 0.8262389 | G5: 0.25 | H5: 0.2 | I5: 0.15 | J5: 0.15 | K5: 0.1 | L5: 0.09 | M5: 0.09 | N5: 0.08 | O5: 0.08 | P5: 0.07 | Q5: 0.07 | R5: 0.06 | S5: 0.05 | T5: 0.05 | U5: 0.05 | V5: 0.05 | W5: 0.05 | X5: 0.05 | Y5: =+X5-0.005 -> 0.045 | Z5: =+Y5-0.005 -> 0.04 | AA5: =+Z5-0.005 -> 0.035 | AB5: =+AA5-0.005 -> 0.03 | AC5: =+AB5-0.005 -> 0.025 | AD5: =+AC5-0.005 -> 0.02 | AE5: =+AD5-0.005 -> 0.015 | AF5: =+AE5-0.005 -> 0.01
B6: 2 | C6: Revenues/Sales | D6: =+Inputs!D6 -> 11139 | E6: =+Inputs!C6 -> 17455 | F6: =+Inputs!B6 -> 31877 | G6: =+F6*(1+G5) -> 39846.25 | H6: =+G6*(1+H5) -> 47815.5 | I6: =+H6*(1+I5) -> 54987.825 | J6: =+I6*(1+J5) -> 63235.999 | K6: =+J6*(1+K5) -> 69559.599 | L6: =+K6*(1+L5) -> 75819.963 | M6: =+L6*(1+M5) -> 82643.759 | N6: =+M6*(1+N5) -> 89255.26 | ... AF6: =+AE6*(1+AF5) -> 194672.88
B7: 3 | C7: Operating Margin | D7: =D8/D6 -> -0.4365742 | E7: =E8/E6 -> -0.21965053 | F7: =F8/F6 -> -0.057470904 | G7: -0.036 | H7: =+_xlfn.FORECAST.LINEAR(H4,'Fin. Data'!$B$12:$H$12,'Fin. Data'!$B$4:$H$4) -> -0.01331898 | I7: 0.02 | J7: 0.04 | K7: 0.06 | L7: 0.08 | M7: 0.09 | N7: 0.1 | O7: 0.11 | P7: 0.12 | Q7: 0.13 | R7: 0.14 | S7: 0.14 | T7: 0.14 | U7: 0.14 | V7: 0.13 | W7: 0.12 | X7: 0.11 | Y7: 0.1 | Z7: 0.1 | AA7: 0.1 | AB7: 0.1 | AC7: 0.1 | AD7: 0.1 | AE7: 0.1 | AF7: 0.1
B8: 4 | C8: EBIT | D8: ='Fin. Data'!D11 -> -4863 | E8: ='Fin. Data'!C11 -> -3834 | F8: ='Fin. Data'!B11 -> -1832 | G8: =G7*G6 -> -1434.465 | H8: =H7*H6 -> -636.85367 | I8: =I7*I6 -> 1099.7565 | J8: =J7*J6 -> 2529.4399 | K8: =K7*K6 -> 4173.5759 | L8: =L7*L6 -> 6065.597 | M8: =M7*M6 -> 7437.9383 | N8: =N7*N6 -> 8925.526 | ... AF8: =AF7*AF6 -> 19467.288
B9: 5a | C9: (Dep) | D9: 420 | E9: 463 | F9: 424 | G9: =+Assumptions!I17 -> 473.92944 | H9: =+Assumptions!J17 -> 503.13269 | I9: =+Assumptions!K17 -> 536.71644 | J9: =+Assumptions!L17 -> 575.33775 | K9: =+Assumptions!M17 -> 617.82118 | L9: =+Assumptions!N17 -> 598.08772 | M9: =+Assumptions!O17 -> 643.54313 | N9: =+Assumptions!P17 -> 692.63498 | ... AF9: =+Assumptions!AH17 -> 10691.354 | AG9: =SUM(D9:AF9) -> 95744.379
B10: 5b | C10: Amort | D10: 155 | E10: 439 | F10: 523 | G10: =+Assumptions!I24 -> 259.82767 | H10: =+Assumptions!J24 -> 275.8381 | I10: =+Assumptions!K24 -> 294.25009 | J10: =+Assumptions!L24 -> 315.42389 | K10: =+Assumptions!M24 -> 338.71506 | L10: =+Assumptions!N24 -> 364.10244 | M10: =+Assumptions!O24 -> 391.77468 | N10: =+Assumptions!P24 -> 421.6607 | ... AF10: =+Assumptions!AH24 -> 7227.3385
B11: 5c | C11: (Stock based compensation) | D11: =D20 -> 827 | E11: =E20 -> 1168 | F11: =F20 -> 1793 | G11: =G6*$D$55 -> 2621.9633 | H11: =H6*$D$55 -> 3146.3559 | I11: =I6*$D$55 -> 3618.3093 | J11: =J6*$D$55 -> 4161.0557 | K11: =K6*$D$55 -> 4577.1613 | L11: =L6*$D$55 -> 4989.1058 | M11: =M6*$D$55 -> 5438.1253 | N11: =N6*$D$55 -> 5873.1753 | ... AF11: =AF6*$D$55 -> 12809.866
B12: 6 | C12: EBIDTA | D12: =D8-D9-D10 -> -5438 | E12: =E8-E9-E10 -> -4736 | F12: =F8-F9-F10 -> -2779 | G12: =G8-G9-G10 -> -2168.2221 | H12: =H8-H9-H10 -> -1415.8245 | I12: =I8-I9-I10 -> 268.78997 | J12: =J8-J9-J10 -> 1638.6783 | K12: =K8-K9-K10 -> 3217.0397 | ... AF12: =AF8-AF9-AF10 -> 1548.5954
B13: 7 | C13: (Net financing cost) | D13: ='Fin. Data'!D14 -> -403 | E13: ='Fin. Data'!C14 -> -446 | F13: ='Fin. Data'!B14 -> -426 | G13: =-F44*$D$57 -> 0 | H13: =-G44*$D$57 -> 0 | I13: =-H44*$D$57 -> 0 | J13: =-I44*$D$57 -> 0 | K13: =-J44*$D$57 -> 0 | L13: =-K44*$D$57 -> 0 | M13: =-L44*$D$57 -> 0 | N13: =-M44*$E$57 -> -885.43805 | O13: =-N44*$E$57 -> -952.98805 | P13: =-O44*$E$57 -> -1025.018 | Q13: =-P44*$E$57 -> -1101.7424 | R13: =-Q44*$E$57 -> -1154.7856 | S13: =-R44*$E$57 -> -1208.7495 | T13: =-S44*$E$57 -> -1263.5354 | U13: =-T44*$E$57 -> -1319.03 | ... AF13: =-AE44*$E$57 -> -2665.8932
B14: 8 | C14: Other income/(cost) | D14: ='Fin. Data'!D15 -> -1625 | E14: ='Fin. Data'!C15 -> 3292 | F14: ='Fin. Data'!B15 -> -7029 | G14: =AVERAGE(D14:F14)*(1+G5) -> -2234.1667 | H14: =AVERAGE(E14:G14)*(1+H5) -> -2388.4667 | I14: =AVERAGE(E14:H14)*(1+I5) -> -2403.3946 | J14: =AVERAGE(G14:I14)*(1+J5) -> -2693.3107 | K14: =AVERAGE(H14:J14)*(1+K5) -> -2744.563 | L14: =AVERAGE(I14:K14)*(1+L5) -> -2848.9942 | M14: =AVERAGE(J14:L14)*(1+M5) -> -3010.8953 | N14: =AVERAGE(K14:M14)*(1+N5) -> -3097.6029 | O14: =AVERAGE(L14:N14)*(1+O5) -> -3224.6973 | P14: =AVERAGE(M14:O14)*(1+P5) -> -3328.8397 | Q14: =AVERAGE(N14:P14)*(1+Q5) -> -3442.2399 | ... AF14: =AVERAGE(AC14:AE14)*(1+AF5) -> -4489.1639
B15: 9 | C15: Earnings before taxes | D15: =D8+D13+D14 -> -6891 | E15: =E8+E13+E14 -> -988 | F15: =F8+F13+F14 -> -9287 | G15: =G8+G13+G14 -> -3668.6317 | H15: =H8+H13+H14 -> -3025.3203 | I15: =I8+I13+I14 -> -1303.6381 | J15: =J8+J13+J14 -> -163.87075 | K15: =K8+K13+K14 -> 1429.0129 | ... AF15: =AF8+AF13+AF14 -> 12312.231
B16: 10 | C16: (Income tax) | D16: ='Fin. Data'!D21 -> -192 | E16: ='Fin. Data'!C21 -> -492 | F16: ='Fin. Data'!B21 -> -181 | G16: =(1*$D$56)*G15 -> -541.49003 | H16: =(1*$D$56)*H15 -> -446.53728 | I16: =(1*$D$56)*I15 -> -192.41698 | J16: =(1*$D$56)*J15 -> -24.187323 | K16: =-(1*$E$56)*K15 -> -191.3734 | L16: =-(1*$E$56)*L15 -> -430.76745 | M16: =-(1*$E$56)*M15 -> -592.8696 | N16: =-(1*$E$56)*N15 -> -661.89759 | O16: =-(1*$E$56)*O15 -> -860.54843 | P16: =-(1*$E$56)*P15 -> -1074.4867 | Q16: =-(1*$E$56)*Q15 -> -1312.8528 | R16: =-(1*$E$56)*R15 -> -1565.6994 | ... AF16: =-(1*$E$56)*AF15 -> -1648.8539
B17: 11 | C17: Net income | D17: ='Fin. Data'!D23 -> -6768 | E17: ='Fin. Data'!C23 -> -496 | F17: ='Fin. Data'!B23 -> -9141 | G17: =G16+G15 -> -4210.1217 | H17: =H16+H15 -> -3471.8576 | I17: =I16+I15 -> -1496.0551 | J17: =J16+J15 -> -188.05807 | K17: =K16+K15 -> 1237.6395 | L17: =L16+L15 -> 2785.8354 | M17: =M16+M15 -> 3834.1734 | N17: =N16+N15 -> 4280.5874 | ... AF17: =AF16+AF15 -> 10663.377
I18: =+J8/I8-1 -> 1.3 | J18: =+K8/J8-1 -> 0.65 | K18: =+L8/K8-1 -> 0.45333333 | L18: =+M8/L8-1 -> 0.22625 | M18: =+N8/M8-1 -> 0.2 | N18: =+O8/N8-1 -> 0.188 | O18: =+P8/O8-1 -> 0.16727273 | P18: =+Q8/P8-1 -> 0.15916667 | ... AF18: =+AG8/AF8-1 -> -1
A19: CASH FLOW STATEMENT | B19: 12 | C19: Operating cash flows before WK | D19: =+D22-D21 -> -3583 | E19: =+E22-E21 -> -1186 | F19: =+F22-F21 -> 170 | G19: =+G17+G10+G9 -> -3476.3646 | H19: =+H17+H10+H9 -> -2692.8868 | I19: =+I17+I10+I9 -> -665.08853 | J19: =+J17+J10+J9 -> 702.70356 | K19: =+K17+K10+K9 -> 2194.1757 | L19: =+L17+L10+L9 -> 3748.0255 | M19: =+M17+M10+M9 -> 4869.4912 | N19: =+N17+N10+N9 -> 5394.8831 | ... AF19: =+AF17+AF10+AF9 -> 28582.069
B20: 13 | C20: (Stock-based compensation) | D20: 827 | E20: 1168 | F20: 1793 | G20: =G11 -> 2621.9633 | H20: =H11 -> 3146.3559 | I20: =I11 -> 3618.3093 | J20: =J11 -> 4161.0557 | K20: =K11 -> 4577.1613 | L20: =L11 -> 4989.1058 | M20: =M11 -> 5438.1253 | N20: =N11 -> 5873.1753 | ... AF20: =AF11 -> 12809.866
B21: 14 | C21: (Working Capital Flows) | D21: =+Assumptions!M117 -> 838 | E21: =+Assumptions!N117 -> 741 | F21: =+Assumptions!O117 -> 472 | G21: =+Assumptions!P117 -> 555.58944 | H21: =+Assumptions!Q117 -> 545.33481 | I21: =+Assumptions!R117 -> 500.40809 | J21: =+Assumptions!S117 -> 579.61222 | K21: =+Assumptions!T117 -> 458.13307 | ... AF21: =+Assumptions!AO117 -> 247.10265
B22: 15 | C22: -Total Operating Cash Flow | D22: =+'Fin. Data'!D67 -> -2745 | E22: =+'Fin. Data'!C67 -> -445 | F22: =+'Fin. Data'!B67 -> 642 | G22: =G19+G20+G21 -> -298.8119 | H22: =H19+H20+H21 -> 998.80388 | I22: =I19+I20+I21 -> 3453.6289 | J22: =J19+J20+J21 -> 5443.3715 | K22: =K19+K20+K21 -> 7229.47 | L22: =L19+L20+L21 -> 9197.3214 | M22: =M19+M20+M21 -> 10812.651 | N22: =N19+N20+N21 -> 11765.314 | ... AF22: =AF19+AF20+AF21 -> 41639.038
B23: 16 | C23: (CAPEX) | D23: ='Fin. Data'!D32 -> -616 | E23: ='Fin. Data'!C32 -> -298 | F23: ='Fin. Data'!B32 -> -252 | G23: =+Assumptions!I51 -> -497.637 | H23: =+Assumptions!J51 -> -597.16439 | I23: =+Assumptions!K51 -> -686.73905 | J23: =+Assumptions!L51 -> -789.74991 | K23: =+Assumptions!M51 -> -868.7249 | L23: =+Assumptions!N51 -> -946.91014 | M23: =+Assumptions!O51 -> -1032.1321 | N23: =+Assumptions!P51 -> -1114.7026 | ... AF23: =+Assumptions!AH51 -> -6280.4824 | AG23: =SUM(D23:AF23) -> -91443.814
B24: 17 | C24: Adq | D24: =Inputs!D66 -> -2131 | E24: ='Fin. Data'!C33 -> -618 | F24: ='Fin. Data'!B33 -> -1139 | G24: =G6*$D$63 -> -1356.9881 | H24: =H6*$D$63 -> -1628.3858 | I24: =I6*$D$63 -> -1872.6436 | J24: =J6*$D$63 -> -2153.5402 | K24: =K6*$E$63 -> -2167.7129 | L24: =L6*$E$63 -> -2362.8071 | M24: =M6*$E$63 -> -2575.4597 | N24: =N6*$E$63 -> -2781.4965 | O24: =O6*$E$63 -> -3004.0163 | P24: =P6*$E$63 -> -3214.2974 | Q24: =Q6*$E$63 -> -3439.2982 | R24: =R6*$E$63 -> -3645.6561 | ... AF24: =AF6*$E$63 -> -6066.6669 | AH24: =AG9-AG23 -> 187188.19
B25: 18 | C25: (Other investing flows) | D25: =Inputs!D67 -> -122 | E25: =Inputs!C67 -> -285 | F25: =Inputs!B67 -> -246 | G25: =(1+G5)*AVERAGE(D25:F25) -> -272.08333 | H25: =(1+H5)*AVERAGE(E25:G25) -> -321.23333 | I25: =(1+I5)*AVERAGE(F25:H25) -> -321.73806 | J25: =(1+J5)*AVERAGE(G25:I25) -> -350.77098 | K25: =(1+K5)*AVERAGE(H25:J25) -> -364.3722 | L25: =(1+L5)*AVERAGE(I25:K25) -> -376.73351 | M25: =(1+M5)*AVERAGE(J25:L25) -> -396.7152 | N25: =(1+N5)*AVERAGE(K25:M25) -> -409.61553 | ... AF25: =(1+AF5)*AVERAGE(AC25:AE25) -> -592.91565
B26: 19 | C26: -Total Investing Flows | D26: =D23+D24+D25 -> -2869 | E26: =E23+E24+E25 -> -1201 | F26: =F23+F24+F25 -> -1637 | G26: =G23+G24+G25 -> -2126.7085 | H26: =H23+H24+H25 -> -2546.7835 | I26: =I23+I24+I25 -> -2881.1207 | J26: =J23+J24+J25 -> -3294.0611 | K26: =K23+K24+K25 -> -3400.81 | ... AF26: =AF23+AF24+AF25 -> -12940.065
B27: 20 | C27: (Flows related to leases) | D27: =Inputs!D71+Inputs!D72 -> -224 | E27: =Inputs!C71+Inputs!C72 -> -116 | F27: =Inputs!B71+Inputs!B72 -> -139 | G27: =+Assumptions!I88 -> -384.94039 | H27: =+Assumptions!J88 -> -461.92846 | I27: =+Assumptions!K88 -> -531.21773 | J27: =+Assumptions!L88 -> -610.90039 | K27: =+Assumptions!M88 -> -671.99043 | L27: =+Assumptions!N88 -> -732.46957 | M27: =+Assumptions!O88 -> -798.39183 | N27: =+Assumptions!P88 -> -862.26318 | ... AF27: =+Assumptions!AH88 -> -1880.6651
B28: 21 | C28: Flows related to debt | D28: =+SUM(Inputs!D69:D70) -> 4046 | E28: =+SUM(Inputs!C69:C70) -> 1818 | F28: =+SUM(Inputs!B69:B70) -> 80 | G28: =G44-F44 -> 2921.91 | H28: =H44-G44 -> 2469.4433 | I28: =I44-H44 -> 92.188064 | J28: =J44-I44 -> 1065.9113 | K28: =K44-J44 -> 1384.635 | L28: =L44-K44 -> 1480.76 | M28: =M44-L44 -> 1582.1036 | N28: =N44-M44 -> 1688.7501 | ... AF28: =AF44-AE44 -> 4392.8634
B29: 22 | C29: (Respurchases)/Issuance of stock | D29: ='Fin. Data'!D28 -> 0 | E29: ='Fin. Data'!C28 -> 0 | F29: ='Fin. Data'!B28 -> 0 | G29: =-G17*$D$65 -> 0 | H29: =-H17*$D$65 -> 0 | I29: =-I17*$D$65 -> 0 | J29: =-J17*$D$65 -> 0 | K29: =+Assumptions!N96 -> 247.52789 | L29: =+Assumptions!O96 -> 696.45885 | M29: =+Assumptions!P96 -> 1150.252 | N29: =+Assumptions!Q96 -> 1498.2056 | O29: =+Assumptions!R96 -> 2226.1164 | P29: =+Assumptions!S96 -> 3056.5653 | Q29: =+Assumptions!T96 -> 3734.6393 | R29: =+Assumptions!U96 -> 4453.9058 | ... AF29: =+Assumptions!AI96 -> 4690.4533
B30: 23 | C30: (Dividends) | D30: ='Fin. Data'!D27 -> 0 | E30: ='Fin. Data'!C27 -> 0 | F30: ='Fin. Data'!B27 -> 0 | G30: =-$D$64*G17 -> 0 | H30: =-$D$64*H17 -> 0 | I30: =-$D$64*I17 -> 0 | J30: =-$D$64*J17 -> 0 | K30: =-$D$64*K17 -> 0 | L30: 0 | M30: 0 | N30: =+Assumptions!Q98 -> 428.05874 | O30: =+Assumptions!R98 -> 834.79367 | P30: =+Assumptions!S98 -> 1389.7722 | Q30: =+Assumptions!T98 -> 2122.6022 | R30: =+Assumptions!U98 -> 3037.6814 | S30: =+Assumptions!V98 -> 3587.0105 | T30: =+Assumptions!W98 -> 3792.1261 | U30: =+Assumptions!X98 -> 4011.1524 | ... AF30: =+Assumptions!AI98 -> 3566.7826
B31: 24 | C31: Other financing flows | D31: =Inputs!D75 -> -2443 | E31: =Inputs!C75 -> 78 | F31: =Inputs!B75 -> 74 | G31: =(1+G5)*AVERAGE(E31:F31) -> 95 | H31: =(1+H5)*AVERAGE(E31:G31) -> 98.8 | I31: =(1+I5)*AVERAGE(F31:H31) -> 102.65667 | J31: =(1+J5)*AVERAGE(G31:I31) -> 113.64172 | K31: =(1+K5)*AVERAGE(H31:J31) -> 115.53608 | L31: =(1+L5)*AVERAGE(I31:K31) -> 120.56652 | M31: =(1+M5)*AVERAGE(J31:L31) -> 127.07377 | N31: =(1+N5)*AVERAGE(K31:M31) -> 130.74349 | O31: =(1+O5)*AVERAGE(L31:N31) -> 136.21816 | ... AF31: =(1+AF5)*AVERAGE(AC31:AE31) -> 189.55381
B32: 25 | C32: -Total Financing flows | D32: =D27+D28+D29+D30+D31 -> 1379 | E32: =E27+E28+E29+E30+E31 -> 1780 | F32: =F27+F28+F29+F30+F31 -> 15 | G32: =G27+G28+G29+G30+G31 -> 2631.9696 | H32: =H27+H28+H29+H30+H31 -> 2106.3148 | I32: =I27+I28+I29+I30+I31 -> -336.373 | J32: =J27+J28+J29+J30+J31 -> 568.65259 | K32: =K27+K28+K29+K30+K31 -> 1075.7086 | ... AF32: =AF27+AF28+AF29+AF30+AF31 -> 10958.988
A34: SUMMARY | B34: 26 | C34: Cash before shareholder returns | D34: =D22+D26+D29+D30+D32 -> -4235 | E34: =E22+E26+E29+E30+E32 -> 134 | F34: =F22+F26+F29+F30+F32 -> -980 | G34: =G22+G26+G29+G30+G32 -> 206.44923 | H34: =H22+H26+H29+H30+H32 -> 558.33518 | I34: =I22+I26+I29+I30+I32 -> 236.13511 | J34: =J22+J26+J29+J30+J32 -> 2717.963 | K34: =K22+K26+K29+K30+K32 -> 5151.8965 | ... AF34: =AF22+AF26+AF29+AF30+AF32 -> 47915.197
B35: 27 | C35: Returns to shareholders | D35: =-1*(D29+D30) -> 0 | E35: =-1*(E29+E30) -> 0 | F35: =-1*(F29+F30) -> 0 | G35: =-1*(G29+G30) -> 0 | H35: =-1*(H29+H30) -> 0 | I35: =-1*(I29+I30) -> 0 | J35: =-1*(J29+J30) -> 0 | K35: =-1*(K29+K30) -> -247.52789 | ... AF35: =-1*(AF29+AF30) -> -8257.236
B36: 28 | C36: Excess cash acumulation | D36: =D34-D35 -> -4235 | E36: =E34-E35 -> 134 | F36: =F34-F35 -> -980 | G36: =G34-G35 -> 206.44923 | H36: =H34-H35 -> 558.33518 | I36: =I34-I35 -> 236.13511 | J36: =J34-J35 -> 2717.963 | K36: =K34-K35 -> 5399.4243 | ... AF36: =AF34-AF35 -> 56172.433
A38: BALANCE SHEET | B38: 29 | C38: Intangible assets | D38: 1564 | E38: 2412 | F38: 1847 | G38: =+F38+(G10) -> 2106.8277 | H38: =+G38+(H10) -> 2382.6658 | I38: =+H38+(I10) -> 2676.9159 | J38: =+I38+(J10) -> 2992.3397 | K38: =+J38+(K10) -> 3331.0548 | L38: =+K38+(L10) -> 3695.1572 | M38: =+L38+(M10) -> 4086.9319 | N38: =+M38+(N10) -> 4508.5926 | ... AF38: =+AE38+(AF10) -> 65106.608 | AG38: =SUM(G38:AF38) -> 483547.42
B39: 30 | C39: Accumulated amorization | D39: =+Assumptions!L129 -> 175 | E39: =+Assumptions!M129 -> 620 | F39: =+Assumptions!N129 -> 1119 | G39: =F39+G10 -> 1378.8277 | H39: =G39+H10 -> 1654.6658 | I39: =H39+I10 -> 1948.9159 | J39: =I39+J10 -> 2264.3397 | K39: =J39+K10 -> 2603.0548 | L39: =K39+L10 -> 2967.1572 | M39: =L39+M10 -> 3358.9319 | N39: =M39+N10 -> 3780.5926 | ... AF39: =AE39+AF10 -> 64378.608 | AG39: =SUM(G39:AF39) -> 464619.42
B40: 31 | C40: PPE+Right of use Assets | D40: 1814 | E40: 1853 | F40: 2082 | G40: =F40+(-G23)+G27 -> 2194.6966 | H40: =G40+(-H23)+H27 -> 2329.9325 | I40: =H40+(-I23)+I27 -> 2485.4539 | J40: =I40+(-J23)+J27 -> 2664.3034 | K40: =J40+(-K23)+K27 -> 2861.0378 | L40: =K40+(-L23)+L27 -> 3075.4784 | M40: =L40+(-M23)+M27 -> 3309.2186 | N40: =M40+(-N23)+N27 -> 3561.6581 | ... AF40: =AE40+(-AF23)+AF27 -> 61047.445 | AG40: =SUM(G40:AF40) -> 534337.42
B41: 32 | C41: Accumulated depreciation | D41: =+Assumptions!L130 -> 841 | E41: =+Assumptions!M130 -> 562 | F41: =+Assumptions!N130 -> 166 | G41: =F41+G9 -> 639.92944 | H41: =G41+H9 -> 1143.0621 | I41: =H41+I9 -> 1679.7786 | J41: =I41+J9 -> 2255.1163 | K41: =J41+K9 -> 2872.9375 | L41: =K41+L9 -> 3471.0252 | M41: =L41+M9 -> 4114.5684 | N41: =M41+N9 -> 4807.2033 | ... AF41: =AE41+AF9 -> 94603.379 | AG41: =SUM(G41:AF41) -> 667324.36
A43: CASH & DEBT & DISCOUNTING | B43: 33 | C43: Ending cash balance | D43: ='Fin. Data'!E39+D36 -> 6638 | E43: =+'Fin. Data'!D39+E36 -> 5781 | F43: =+'Fin. Data'!C39+F36 -> 3315 | G43: =G36+F43 -> 3521.4492 | H43: =H36+G43 -> 4079.7844 | I43: =I36+H43 -> 4315.9195 | J43: =J36+I43 -> 7033.8825 | K43: =K36+J43 -> 12433.307 | L43: =L36+K43 -> 20902.411 | M43: =M36+L43 -> 32072.297 | N43: =N36+M43 -> 46267.819 | ... AF43: =AF36+AE43 -> 813824.45
B44: 34 | C44: Total Debt | D44: ='Fin. Data'!D58 -> 9279 | E44: ='Fin. Data'!C58 -> 11105 | F44: ='Fin. Data'!B58 -> 11139 | G44: =+Assumptions!I83 -> 14060.91 | H44: =+Assumptions!J83 -> 16530.353 | I44: =+Assumptions!K83 -> 16622.541 | J44: =+Assumptions!L83 -> 17688.453 | K44: =+Assumptions!M83 -> 19073.088 | L44: =+Assumptions!N83 -> 20553.848 | M44: =+Assumptions!O83 -> 22135.951 | N44: =+Assumptions!P83 -> 23824.701 | ... AF44: =+Assumptions!AH83 -> 71040.193
B45: 35 | C45: Discount factor | F45: =1/((1+$F$50)^G50) -> 1 | G45: =1/((1+$F$50)^G49) -> 0.90826521 | H45: =1/((1+$F$50)^H49) -> 0.8249457 | I45: =1/((1+$F$50)^I49) -> 0.74926948 | J45: =1/((1+$F$50)^J49) -> 0.6805354 | K45: =1/((1+$F$50)^K49) -> 0.61810663 | L45: =1/((1+$F$50)^L49) -> 0.56140475 | M45: =1/((1+$F$50)^M49) -> 0.50990441 | N45: =1/((1+$F$50)^N49) -> 0.46312844 | ... AF45: =1/((1+$F$50)^AF49) -> 0.081946367
B46: 36 | C46: DF + 0.1% | E46: +0.1% | F46: =1/((1+$F$50+0.001)^G50) -> 1 | G46: =1/((1+$F$50+0.001)^G49) -> 0.90744102 | H46: =1/((1+$F$50+0.001)^H49) -> 0.8234492 | I46: =1/((1+$F$50+0.001)^I49) -> 0.74723158 | J46: =1/((1+$F$50+0.001)^J49) -> 0.67806858 | K46: =1/((1+$F$50+0.001)^K49) -> 0.61530724 | L46: =1/((1+$F$50+0.001)^L49) -> 0.55835503 | M46: =1/((1+$F$50+0.001)^M49) -> 0.50667426 | N46: =1/((1+$F$50+0.001)^N49) -> 0.459777 | ... AF46: =1/((1+$F$50+0.001)^AF49) -> 0.080034741
B47: 37 | C47: DF+0.5% | E47: +0.5% | F47: =1/((1+$F$50+0.005)^G50) -> 1 | G47: =1/((1+$F$50+0.005)^G49) -> 0.90415913 | H47: =1/((1+$F$50+0.005)^H49) -> 0.81750374 | I47: =1/((1+$F$50+0.005)^I49) -> 0.73915347 | J47: =1/((1+$F$50+0.005)^J49) -> 0.66831236 | K47: =1/((1+$F$50+0.005)^K49) -> 0.60426072 | L47: =1/((1+$F$50+0.005)^L49) -> 0.54634785 | M47: =1/((1+$F$50+0.005)^M49) -> 0.4939854 | N47: =1/((1+$F$50+0.005)^N49) -> 0.44664141 | ... AF47: =1/((1+$F$50+0.005)^AF49) -> 0.072839457
A49: Discount Rate | C49: Risk free rate | D49: Equity premium | E49: Firm premium | F49: Total | G49: 1 | H49: 2 | I49: 3 | J49: 4 | K49: 5 | L49: 6 | M49: 7 | N49: 8 | O49: 9 | P49: 10 | Q49: 11 | R49: 12 | S49: 13 | T49: 14 | U49: 15 | V49: 16 | W49: 17 | X49: 18 | Y49: 19 | Z49: 20 | AA49: 21 | AB49: 22 | AC49: 23 | AD49: 24 | AE49: 25 | AF49: 26
C50: 0.042 | D50: 0.044 | E50: 0.015 | F50: =E50+D50+C50 -> 0.101 | G50: 0
A52: Modelling factors | D52: Short Term | E52: Long Term | F52: Reference (line)
C53: Depreciation factor | D53: =+Assumptions!H127 -> 0.21594303 | E53: =+Assumptions!I127 -> 0.20312967 | F53: % PPE
C54: Amortization factor | D54: =+Assumptions!H128 -> 0.14570091 | E54: =+Assumptions!I128 -> 0.14570091 | F54: % PPE
C55: Stock-based comp | D55: =+Assumptions!I32 -> 0.065802008 | E55: =+Assumptions!I129 -> 0.065802008 | F55: % revenue
C56: Tax Rate | D56: =+Assumptions!H130 -> 0.1476 | E56: =+Assumptions!I130 -> 0.13392 | F56: % (line 9)
C57: Interest Rate on debt | D57: =+Assumptions!H131 -> 0 | E57: =+Assumptions!I131 -> 0.04 | F57: % debt (l29)
C58: Interest Rate on cash | D58: =+Assumptions!H132 -> 0.044 | E58: =+Assumptions!I132 -> 0.0433 | F58: % of cash (l28)
C59: PPE+ROA | D59: =+Assumptions!H133 -> -0.035798792 | E59: =+Assumptions!I133 -> -0.032261723 | F59: Growing with capex
C60: Working capital flows | D60: =+Assumptions!H134 -> -0.0047895647 | E60: =+Assumptions!I134 -> -0.03998964 | F60: % of change revenues (l2)
C61: Intangible Assets | D61: =+Assumptions!H135 -> 0.068355369 | E61: =+Assumptions!I135 -> 0.081433907 | F61: Growing with amortization
C62: Capex | D62: =+Assumptions!H136 -> -0.035798792 | E62: =+Assumptions!I136 -> -0.032261723 | F62: % revenue (l2)
C63: Acquisition factor | D63: =+Assumptions!H137 -> -0.034055605 | E63: =+Assumptions!I137 -> -0.031163391 | F63: % revenue (l2)
C64: Dividends | D64: =+Assumptions!H138 -> 0 | E64: =+Assumptions!E94 -> 0.33448904 | F64: % net income (11)
C65: Repurchases | D65: 0 | E65: =+Assumptions!H94 -> 0.43986567 | F65: % net income (11)
C66: Leases | D66: 0.05 | E66: 0.05 | F66: % revenue (l2)
C67: Cash Costs for EBIT | D67: =+Assumptions!H141 -> 0 | E67: =+Assumptions!I141 -> 0 | F67: % revenue (l2)
A69: Valuation | D69: $ millions
C70: Value of flows | D70: =SUMPRODUCT(G35:AF35,G45:AF45)+((AF43-AF44)*AF45) -> 32420.253 | E70: =D70/D72 -> 0.42901897
C71: Value of perpetuity | D71: =(AF34/(F50-AF5))*AF45 -> 43148.092 | E71: =D71/D72 -> 0.57098103
C72: Total Value | D72: =D70+D71 -> 75568.345
C73: Actual share price | D73: =OP!C17 -> 47.24
C74: Total value vs Mkt Cap | D74: =D75/D73-1 -> -0.20396953
C75: Estimated NPV per share | D75: =D72*1000000/OP!C18 -> 37.604479
A77: Sensibility | C77: Sensitivity +0.1% | D77: =(SUMPRODUCT(G35:AF35,G45:AF45)+((AF43-AF44)*AF45)+(AF34/(F50+0.001-AF5))*AF45)*1000000/OP!C18 -> 37.371094 | E77: =D77/D75-1 -> -0.0062063156
C78: Sensitivity +0.5% | D78: =(SUMPRODUCT(G35:AF35,G45:AF45)+((AF43-AF44)*AF45)+(AF34/(F50+0.005-AF5))*AF45)*1000000/OP!C18 -> 36.486175 | E78: =D78/D75-1 -> -0.029738595
A80: Notes

Sheet Assumptions
B2: Market Projected to grow at 16,3%
B3: https://www.fortunebusinessinsights.com/ride-sharing-market-103336
C7: Last 5 Years | I7: Short Term Forecast
C8: 2017 | D8: 2018 | E8: 2019 | F8: 2020 | G8: 2021 | H8: 2022 | I8: 2023 | J8: =I8+1 -> 2024 | K8: =J8+1 -> 2025 | L8: =K8+1 -> 2026 | M8: =L8+1 -> 2027 | N8: =M8+1 -> 2028 | O8: =N8+1 -> 2029 | P8: =O8+1 -> 2030 | Q8: =P8+1 -> 2031 | ... AH8: =AG8+1 -> 2048
B9: Net Sales | C9: =+'Fin. Data'!G5 -> 7932 | D9: =+'Fin. Data'!F5 -> 10433 | E9: =+'Fin. Data'!E5 -> 13000 | F9: =+'Fin. Data'!D5 -> 11139 | G9: =+'Fin. Data'!C5 -> 17455 | H9: =+'Fin. Data'!B5 -> 31877 | I9: =+H9*(1+I10) -> 39846.25 | J9: =+I9*(1+J10) -> 47815.5 | K9: =+J9*(1+K10) -> 54987.825 | L9: =+K9*(1+L10) -> 63235.999 | M9: =+L9*(1+M10) -> 69559.599 | N9: =M9*(1+N10) -> 75819.963 | O9: =N9*(1+O10) -> 82643.759 | P9: =O9*(1+P10) -> 89255.26 | Q9: =P9*(1+Q10) -> 96395.681 | R9: =Q9*(1+R10) -> 103143.38 | S9: =R9*(1+S10) -> 110363.41 | T9: =S9*(1+T10) -> 116985.22 | U9: =T9*(1+U10) -> 122834.48 | ... AH9: =AG9*(1+AH10) -> 194672.88
B10: % Growth | D10: =+D9/C9-1 -> 0.31530509 | E10: =+E9/D9-1 -> 0.2460462 | F10: =+F9/E9-1 -> -0.14315385 | G10: =+G9/F9-1 -> 0.56701679 | H10: =+H9/G9-1 -> 0.8262389 | I10: 0.25 | J10: 0.2 | K10: 0.15 | L10: 0.15 | M10: 0.1 | N10: 0.09 | O10: 0.09 | P10: 0.08 | Q10: 0.08 | R10: 0.07 | S10: 0.07 | T10: 0.06 | U10: 0.05 | V10: 0.05 | W10: 0.05 | X10: 0.05 | Y10: 0.05 | Z10: 0.05 | AA10: =+Z10-0.005 -> 0.045 | AB10: =+AA10-0.005 -> 0.04 | AC10: =+AB10-0.005 -> 0.035 | AD10: =+AC10-0.005 -> 0.03 | AE10: =+AD10-0.005 -> 0.025 | AF10: =+AE10-0.005 -> 0.02 | AG10: =+AF10-0.005 -> 0.015 | AH10: =+AG10-0.005 -> 0.01
B11: Actual 5y Average | H11: =+AVERAGE(D10:H10) -> 0.36229063 | M11: =AVERAGE(I10:M10) -> 0.17 | R11: =+AVERAGE(N10:R10) -> 0.082 | W11: =+AVERAGE(S10:W10) -> 0.056 | AB11: =+AVERAGE(X10:AB10) -> 0.047 | AG11: =+AVERAGE(AC10:AG10) -> 0.025
B12: Target 5y Average | M12: 0.163
C15: Last 5 Years | I15: Short Term Forecast
C16: 2017 | D16: 2018 | E16: 2019 | F16: 2020 | G16: 2021 | H16: 2022 | I16: 2023 | J16: =I16+1 -> 2024 | K16: =J16+1 -> 2025 | L16: =K16+1 -> 2026 | M16: =L16+1 -> 2027 | N16: =M16+1 -> 2028 | O16: =N16+1 -> 2029 | P16: =O16+1 -> 2030 | Q16: =P16+1 -> 2031 | ... AH16: =AG16+1 -> 2048
B17: Depretiation | C17: 504 | D17: 411 | E17: 456 | F17: 420 | G17: 463 | H17: 424 | I17: =+DCF!G40*I18 -> 473.92944 | J17: =+DCF!H40*J18 -> 503.13269 | K17: =+DCF!I40*K18 -> 536.71644 | L17: =+DCF!J40*L18 -> 575.33775 | M17: =+DCF!K40*M18 -> 617.82118 | N17: =+DCF!L40*N18 -> 598.08772 | O17: =+DCF!M40*O18 -> 643.54313 | P17: =+DCF!N40*P18 -> 692.63498 | ... AH17: =+DCF!AF40*AH18 -> 10691.354
B18: % of PPE | C18: =+C17/'Fin. Data'!$G$42 -> 0.42281879 | D18: =+D17/'Fin. Data'!F42 -> 0.25045704 | E18: =+E17/'Fin. Data'!E42 -> 0.26343154 | F18: =+F17/'Fin. Data'!D42 -> 0.23153252 | G18: =+G17/'Fin. Data'!C42 -> 0.24986508 | H18: =+H17/'Fin. Data'!B42 -> 0.20365034 | I18: =+$H$19*(1-(-$H$20)) -> 0.21594303 | J18: =+$H$19*(1-(-$H$20)) -> 0.21594303 | K18: =+$H$19*(1-(-$H$20)) -> 0.21594303 | L18: =+$H$19*(1-(-$H$20)) -> 0.21594303 | M18: =+$H$19*(1-(-$H$20)) -> 0.21594303 | N18: =+$N$19 -> 0.19446981 | O18: =+$N$19 -> 0.19446981 | P18: =+$N$19 -> 0.19446981 | Q18: =+$N$19 -> 0.19446981 | R18: =+$N$19 -> 0.19446981 | S18: =+$S$19 -> 0.17513188 | T18: =+$S$19 -> 0.17513188 | U18: =+$S$19 -> 0.17513188 | V18: =+$S$19 -> 0.17513188 | W18: =+$S$19 -> 0.17513188 | X18: =+$S$19 -> 0.17513188 | Y18: =+$S$19 -> 0.17513188 | Z18: =+$S$19 -> 0.17513188 | ... AH18: =+$S$19 -> 0.17513188
B19: Target 5y Average | H19: =+AVERAGE(D18:H18) -> 0.23978731 | N19: =+I18*(1-(-H20)) -> 0.19446981 | S19: =+N19*(1-(-H20)) -> 0.17513188
B20: Average Growth % Sales | D20: =+D18/C18-1 -> -0.40764923 | E20: =+E18/D18-1 -> 0.051803312 | F20: =+F18/E18-1 -> -0.12109035 | G20: =+G18/F18-1 -> 0.079179195 | H20: =+AVERAGE(D20:G20) -> -0.099439268
C22: Last 5 Years | I22: Short Term Forecast
C23: 2017 | D23: 2018 | E23: 2019 | F23: 2020 | G23: 2021 | H23: 2022 | I23: 2023 | J23: =I23+1 -> 2024 | K23: =J23+1 -> 2025 | L23: =K23+1 -> 2026 | M23: =L23+1 -> 2027 | N23: =M23+1 -> 2028 | O23: =N23+1 -> 2029 | P23: =O23+1 -> 2030 | Q23: =P23+1 -> 2031 | ... AH23: =AG23+1 -> 2048
B24: Amortizatioon | C24: 7 | D24: 15 | E24: 16 | F24: 155 | G24: 439 | H24: 523 | I24: =+DCF!G40*I25 -> 259.82767 | J24: =+DCF!H40*J25 -> 275.8381 | K24: =+DCF!I40*K25 -> 294.25009 | L24: =+DCF!J40*L25 -> 315.42389 | M24: =+DCF!K40*M25 -> 338.71506 | N24: =+DCF!L40*N25 -> 364.10244 | O24: =+DCF!M40*O25 -> 391.77468 | P24: =+DCF!N40*P25 -> 421.6607 | ... AH24: =+DCF!AF40*AH25 -> 7227.3385
B25: % of PPE | C25: =+C24/'Fin. Data'!$G$42 -> 0.0058724832 | D25: =+D24/'Fin. Data'!F42 -> 0.0091407678 | E25: =+E24/'Fin. Data'!E42 -> 0.009243212 | F25: =+F24/'Fin. Data'!D42 -> 0.085446527 | G25: =+G24/'Fin. Data'!C42 -> 0.23691311 | H25: =+H24/'Fin. Data'!B42 -> 0.25120077 | I25: =+$H$26 -> 0.11838888 | J25: =+$H$26 -> 0.11838888 | K25: =+$H$26 -> 0.11838888 | L25: =+$H$26 -> 0.11838888 | M25: =+$H$26 -> 0.11838888 | N25: =+$N$26 -> 0.11838888 | O25: =+$N$26 -> 0.11838888 | P25: =+$N$26 -> 0.11838888 | Q25: =+$N$26 -> 0.11838888 | R25: =+$N$26 -> 0.11838888 | S25: =+$S$26 -> 0.11838888 | T25: =+$S$26 -> 0.11838888 | U25: =+$S$26 -> 0.11838888 | V25: =+$S$26 -> 0.11838888 | W25: =+$S$26 -> 0.11838888 | X25: =+$S$26 -> 0.11838888 | Y25: =+$S$26 -> 0.11838888 | Z25: =+$S$26 -> 0.11838888 | ... AH25: =+$S$26 -> 0.11838888
B26: Target 5y Average | H26: =+AVERAGE(D25:H25) -> 0.11838888 | N26: =+I25*(1-(-H27)) -> 0.11838888 | S26: =+N26*(1-(-H27)) -> 0.11838888
B27: Average Growth % Sales
C29: Last 5 Years | I29: Short Term Forecast
C30: 2017 | D30: 2018 | E30: 2019 | F30: 2020 | G30: 2021 | H30: 2022 | I30: 2023 | J30: =I30+1 -> 2024 | K30: =J30+1 -> 2025 | L30: =K30+1 -> 2026 | M30: =L30+1 -> 2027 | N30: =M30+1 -> 2028 | O30: =N30+1 -> 2029 | P30: =O30+1 -> 2030 | Q30: =P30+1 -> 2031 | ... AH30: =AG30+1 -> 2048
B31: Stock-based Compensation | F31: 827 | G31: 1168 | H31: 1793 | I31: =+I32*I9 -> 2621.9633 | J31: =+J32*J9 -> 3146.3559 | K31: =+K32*K9 -> 3618.3093 | L31: =+L32*L9 -> 4161.0557 | M31: =+M32*M9 -> 4577.1613 | N31: =+N32*N9 -> 4989.1058 | O31: =+O32*O9 -> 5438.1253 | P31: =+P32*P9 -> 5873.1753 | ... AH31: =+AH32*AH9 -> 12809.866
B32: % of Sales | C32: =C31/C$9 -> 0 | D32: =D31/D$9 -> 0 | E32: =E31/E$9 -> 0 | F32: =F31/F$9 -> 0.074243648 | G32: =G31/G$9 -> 0.066914924 | H32: =H31/H$9 -> 0.056247451 | I32: =+$H$33 -> 0.065802008 | J32: =+$H$33 -> 0.065802008 | K32: =+$H$33 -> 0.065802008 | L32: =+$H$33 -> 0.065802008 | M32: =+$H$33 -> 0.065802008 | N32: =+$H$33 -> 0.065802008 | O32: =+$H$33 -> 0.065802008 | P32: =+$H$33 -> 0.065802008 | ... AH32: =+$H$33 -> 0.065802008
B33: Target 5y Average | H33: =AVERAGE(F32:H32) -> 0.065802008
B35: Weighted-average interest rate on debt and finance leases
C37: Interest rate
B38: • 3.500% ASML Holding NV Fixed Rate Senior Notes due 2025 (XS2631416950); | C38: 0.035
B39: • 1.375% ASML Holding NV Fixed Rate Senior Notes due 2026 (XS1405780963); | C39: 0.01375
B40: • 1.625% ASML Holding NV Fixed Rate Senior Notes due 2027 (XS1527556192); | C40: 0.01625
B41: • 0.625% ASML Holding NV Fixed Rate Senior Notes due 2029 (XS2166219720); | C41: 0.00625
B42: • 0.250% ASML Holding NV Fixed Rate Senior Notes due 2030 (XS2010032378); and • 2.250% ASML Holding NV Fixed Rate Senior Notes due 2032 (XS2473687106). | C42: 0.0025
C43: =AVERAGE(C38:C42) -> 0.01475
C49: Last 5 Years | I49: Short Term Forecast
C50: 2017 | D50: 2018 | E50: 2019 | F50: 2020 | G50: 2021 | H50: 2022 | I50: 2023 | J50: =I50+1 -> 2024 | K50: =J50+1 -> 2025 | L50: =K50+1 -> 2026 | M50: =L50+1 -> 2027 | N50: =M50+1 -> 2028 | O50: =N50+1 -> 2029 | P50: =O50+1 -> 2030 | Q50: =P50+1 -> 2031 | ... AH50: =AG50+1 -> 2048
B51: CAPEX | C51: =+Inputs!G65 -> 0 | D51: =+Inputs!F65 -> -558 | E51: =+Inputs!E65 -> -588 | F51: =+Inputs!D65 -> -616 | G51: =+Inputs!C65 -> -298 | H51: =+Inputs!B65 -> -252 | I51: =+I52*I9 -> -497.637 | J51: =+J52*J9 -> -597.16439 | K51: =+K52*K9 -> -686.73905 | L51: =+L52*L9 -> -789.74991 | M51: =+M52*M9 -> -868.7249 | N51: =+N52*N9 -> -946.91014 | O51: =+O52*O9 -> -1032.1321 | P51: =+P52*P9 -> -1114.7026 | ... AH51: =+AH52*AH9 -> -6280.4824
B52: % of Sales | C52: =C51/C$9 -> 0 | D52: =D51/D$9 -> -0.053484137 | E52: =E51/E$9 -> -0.045230769 | F52: =F51/F$9 -> -0.055301194 | G52: =G51/G$9 -> -0.017072472 | H52: =H51/H$9 -> -0.0079053863 | I52: =+$H$53 -> -0.012488929 | J52: =+$H$53 -> -0.012488929 | K52: =+$H$53 -> -0.012488929 | L52: =+$H$53 -> -0.012488929 | M52: =+$H$53 -> -0.012488929 | N52: =+$H$53 -> -0.012488929 | O52: =+$H$53 -> -0.012488929 | P52: =+$H$53 -> -0.012488929 | ... R52: =+$H$53 -> -0.012488929 | S52: =+$R$53 -> -0.032261723 | T52: =+$R$53 -> -0.032261723 | U52: =+$R$53 -> -0.032261723 | V52: =+$R$53 -> -0.032261723 | W52: =+$R$53 -> -0.032261723 | X52: =+$R$53 -> -0.032261723 | Y52: =+$R$53 -> -0.032261723 | Z52: =+$R$53 -> -0.032261723 | ... AH52: =+$R$53 -> -0.032261723
B53: Target 5y Average | H53: =AVERAGE(G52:H52) -> -0.012488929 | R53: =+I136 -> -0.032261723 | W53: =AVERAGE(S52:W52) -> -0.032261723 | AB53: =AVERAGE(X52:AB52) -> -0.032261723 | AG53: =AVERAGE(AC52:AG52) -> -0.032261723
C56: Last 5 Years | I56: Short Term Forecast
C57: 2017 | D57: 2018 | E57: 2019 | F57: 2020 | G57: 2021 | H57: 2022 | I57: 2023 | J57: =I57+1 -> 2024 | K57: =J57+1 -> 2025 | L57: =K57+1 -> 2026 | M57: =L57+1 -> 2027 | N57: =M57+1 -> 2028 | O57: =N57+1 -> 2029 | P57: =O57+1 -> 2030 | Q57: =P57+1 -> 2031 | ... AH57: =AG57+1 -> 2048
B58: Change in NWC | D58: =+Inputs!F22 -> 1419 | E58: =+Inputs!E22 -> 3887 | F58: =+Inputs!D22 -> -5269 | G58: =+Inputs!C22 -> -3222 | H58: =+Inputs!B22 -> 601 | I58: =+I59*I9 -> -1623.7124 | J58: =+J59*J9 -> -1948.4549 | K58: =+K59*K9 -> -2240.7231 | L58: =+L59*L9 -> -2576.8316 | M58: =+M59*M9 -> -2834.5147 | N58: =+N59*N9 -> -3089.621 | O58: =+O59*O9 -> -3367.6869 | P58: =+P59*P9 -> -3637.1019 | ... AH58: =+AH59*AH9 -> -7784.8982
B59: % of Sales | D59: =D58/D$9 -> 0.13601074 | E59: =E58/E$9 -> 0.299 | F59: =F58/F$9 -> -0.47302271 | G59: =G58/G$9 -> -0.18458894 | H59: =H58/H$9 -> 0.018853719 | I59: =+$H$60 -> -0.04074944 | J59: =+$H$60 -> -0.04074944 | K59: =+$H$60 -> -0.04074944 | L59: =+$H$60 -> -0.04074944 | M59: =+$H$60 -> -0.04074944 | N59: =+$H$60 -> -0.04074944 | O59: =+$H$60 -> -0.04074944 | P59: =+$H$60 -> -0.04074944 | ... R59: =+$H$60 -> -0.04074944 | S59: =+$R$60 -> -0.03998964 | T59: =+$R$60 -> -0.03998964 | U59: =+$R$60 -> -0.03998964 | V59: =+$R$60 -> -0.03998964 | W59: =+$R$60 -> -0.03998964 | X59: =+$R$60 -> -0.03998964 | Y59: =+$R$60 -> -0.03998964 | Z59: =+$R$60 -> -0.03998964 | ... AH59: =+$R$60 -> -0.03998964
B60: Target 5y Average | H60: =AVERAGE(D59:G59,H59) -> -0.04074944 | R60: =+I134 -> -0.03998964 | W60: =AVERAGE(S59:W59) -> -0.03998964 | AB60: =AVERAGE(X59:AB59) -> -0.03998964 | AG60: =AVERAGE(AC59:AG59) -> -0.03998964
C62: Last 5 Years | I62: Short Term Forecast
C63: 2017 | D63: 2018 | E63: 2019 | F63: 2020 | G63: 2021 | H63: 2022 | I63: 2023 | J63: =I63+1 -> 2024 | K63: =J63+1 -> 2025 | L63: =K63+1 -> 2026 | M63: =L63+1 -> 2027 | N63: =M63+1 -> 2028 | O63: =N63+1 -> 2029 | P63: =O63+1 -> 2030 | Q63: =P63+1 -> 2031 | ... AH63: =AG63+1 -> 2048
B64: Total Assets | D64: =+Inputs!F38 -> 23988 | E64: =+Inputs!E38 -> 31761 | F64: =+Inputs!D38 -> 33252 | G64: =+Inputs!C38 -> 38774 | H64: =+Inputs!B38 -> 32109 | I64: =+H64*(1+I65) -> 35040.175 | J64: =+I64*(1+J65) -> 38238.931 | K64: =+J64*(1+K65) -> 41729.697 | L64: =+K64*(1+L65) -> 45539.129 | M64: =+L64*(1+M65) -> 49696.316 | N64: =+M64*(1+N65) -> 54233.007 | O64: =+N64*(1+O65) -> 59183.844 | P64: =+O64*(1+P65) -> 64586.634 | ... AH64: =+AG64*(1+AH65) -> 167899.89
B65: % of Sales | E65: =+E64/D64-1 -> 0.32403702 | F65: =+F64/E64-1 -> 0.046944366 | G65: =+G64/F64-1 -> 0.1660652 | H65: =+H64/G64-1 -> -0.17189354 | I65: =+$H$66 -> 0.091288262 | J65: =+$H$66 -> 0.091288262 | K65: =+$H$66 -> 0.091288262 | L65: =+$H$66 -> 0.091288262 | M65: =+$H$66 -> 0.091288262 | N65: =+$H$66 -> 0.091288262 | O65: =+$H$66 -> 0.091288262 | P65: =+$H$66 -> 0.091288262 | ... R65: =+$H$66 -> 0.091288262 | S65: =+$R$66 -> 0.05 | T65: =+$R$66 -> 0.05 | U65: =+$R$66 -> 0.05 | V65: =+$R$66 -> 0.05 | W65: =+$R$66 -> 0.05 | X65: =+$R$66 -> 0.05 | Y65: =+$R$66 -> 0.05 | Z65: =+$R$66 -> 0.05 | ... AH65: =+$R$66 -> 0.05
B66: Target 5y Average | H66: =+AVERAGE(E65:H65) -> 0.091288262 | R66: 0.05
B68: Total Liabilities | D68: =+Inputs!F51 -> 17196 | E68: =+Inputs!E51 -> 16578 | F68: =+Inputs!D51 -> 19498 | G68: =+Inputs!C51 -> 23425 | H68: =+Inputs!B51 -> 23605 | I68: =H68*(1+I69) -> 25666.235 | J68: =I68*(1+J69) -> 27907.461 | K68: =J68*(1+K69) -> 30344.395 | L68: =K68*(1+L69) -> 32994.127 | M68: =L68*(1+M69) -> 35875.238 | N68: =M68*(1+N69) -> 39007.934 | O68: =N68*(1+O69) -> 42414.184 | P68: =O68*(1+P69) -> 46117.873 | ... AH68: =AG68*(1+AH69) -> 102121.93
B69: % of Sales | E69: =+E68/D68-1 -> -0.03593859 | F69: =+F68/E68-1 -> 0.17613705 | G69: =+G68/F68-1 -> 0.20140527 | H69: =+H68/G68-1 -> 0.0076840982 | I69: =+$H$70 -> 0.087321957 | J69: =+$H$70 -> 0.087321957 | K69: =+$H$70 -> 0.087321957 | L69: =+$H$70 -> 0.087321957 | M69: =+$H$70 -> 0.087321957 | N69: =+$H$70 -> 0.087321957 | O69: =+$H$70 -> 0.087321957 | P69: =+$H$70 -> 0.087321957 | ... R69: =+$H$70 -> 0.087321957 | S69: =+$R$70 -> 0.04 | T69: =+$R$70 -> 0.04 | U69: =+$R$70 -> 0.04 | V69: =+$R$70 -> 0.04 | W69: =+$R$70 -> 0.04 | X69: =+$R$70 -> 0.04 | Y69: =+$R$70 -> 0.04 | Z69: =+$R$70 -> 0.04 | ... AH69: =+$R$70 -> 0.04
B70: Target 5y Average | H70: =+AVERAGE(C69:H69) -> 0.087321957 | R70: 0.04
B72: Shareholders Equity | C72: =+C64-C68 -> 0 | D72: =+Inputs!F56 -> 6792 | E72: =+Inputs!E56 -> 14872 | F72: =+Inputs!D56 -> 12967 | G72: =+Inputs!C56 -> 15145 | H72: =+Inputs!B56 -> 8074 | I72: =+I64-I68 -> 9373.94 | J72: =+J64-J68 -> 10331.471 | K72: =+K64-K68 -> 11385.302 | L72: =+L64-L68 -> 12545.002 | M72: =+M64-M68 -> 13821.078 | N72: =+N64-N68 -> 15225.072 | O72: =+O64-O68 -> 16769.66 | P72: =+P64-P68 -> 18468.761 | ... AH72: =+AH64-AH68 -> 65777.956
C76: Last 5 Years | I76: Short Term Forecast
C77: 2017 | D77: 2018 | E77: 2019 | F77: 2020 | G77: 2021 | H77: 2022 | I77: 2023 | J77: =I77+1 -> 2024 | K77: =J77+1 -> 2025 | L77: =K77+1 -> 2026 | M77: =L77+1 -> 2027 | N77: =M77+1 -> 2028 | O77: =N77+1 -> 2029 | P77: =O77+1 -> 2030 | Q77: =P77+1 -> 2031 | ... AH77: =AG77+1 -> 2048
B78: Debt/Equity | D78: =+D83/D72 -> 1.0113369 | E78: =+E83/E72 -> 0.4993276 | F78: =+F83/F72 -> 0.71558572 | G78: =+G83/G72 -> 0.7332453 | H78: =+H83/H72 -> 1.3796136 | I78: 1.5 | J78: 1.6 | K78: 1.46 | L78: =+K78-0.05 -> 1.41 | M78: =+L78-0.03 -> 1.38 | N78: =+M78-0.03 -> 1.35 | O78: =+N78-0.03 -> 1.32 | P78: =+O78-0.03 -> 1.29 | Q78: =+P78-0.03 -> 1.26 | R78: =+Q78-0.03 -> 1.23 | S78: =+R78-0.03 -> 1.2 | T78: =+S78-0.03 -> 1.17 | ... W78: =+V78-0.03 -> 1.08 | X78: =+$W$79 -> 1.08 | Y78: =+$W$79 -> 1.08 | Z78: =+$W$79 -> 1.08 | AA78: =+$W$79 -> 1.08 | AB78: =+$W$79 -> 1.08 | AC78: =+$W$79 -> 1.08 | AD78: =+$W$79 -> 1.08 | AE78: =+$W$79 -> 1.08 | ... AH78: =+$W$79 -> 1.08
B79: Target 5y Average | H79: 1 | W79: =+W78 -> 1.08
C81: Last 5 Years | I81: Short Term Forecast
C82: 2017 | D82: 2018 | E82: 2019 | F82: 2020 | G82: 2021 | H82: 2022 | I82: 2023 | J82: =I82+1 -> 2024 | K82: =J82+1 -> 2025 | L82: =K82+1 -> 2026 | M82: =L82+1 -> 2027 | N82: =M82+1 -> 2028 | O82: =N82+1 -> 2029 | P82: =O82+1 -> 2030 | Q82: =P82+1 -> 2031 | ... AH82: =AG82+1 -> 2048
B83: Total Debt | D83: =+'Fin. Data'!F58 -> 6869 | E83: =+'Fin. Data'!E58 -> 7426 | F83: =+'Fin. Data'!D58 -> 9279 | G83: =+'Fin. Data'!C58 -> 11105 | H83: =+'Fin. Data'!B58 -> 11139 | I83: =+I72*I78 -> 14060.91 | J83: =+J72*J78 -> 16530.353 | K83: =+K72*K78 -> 16622.541 | L83: =+L72*L78 -> 17688.453 | M83: =+M72*M78 -> 19073.088 | N83: =+N72*N78 -> 20553.848 | O83: =+O72*O78 -> 22135.951 | P83: =+P72*P78 -> 23824.701 | ... AH83: =+AH72*AH78 -> 71040.193
B84: Flows Related To debt | D84: =+D83-C83 -> 6869 | E84: =+E83-D83 -> 557 | F84: =+F83-E83 -> 1853 | G84: =+G83-F83 -> 1826 | H84: =+H83-G83 -> 34 | I84: =+I83-H83 -> 2921.91 | J84: =+J83-I83 -> 2469.4433 | K84: =+K83-J83 -> 92.188064 | ... AH84: =+AH83-AG83 -> 4392.8634
C86: Last 5 Years | I86: Short Term Forecast
C87: 2017 | D87: 2018 | E87: 2019 | F87: 2020 | G87: 2021 | H87: 2022 | I87: 2023 | J87: =I87+1 -> 2024 | K87: =J87+1 -> 2025 | L87: =K87+1 -> 2026 | M87: =L87+1 -> 2027 | N87: =M87+1 -> 2028 | O87: =N87+1 -> 2029 | P87: =O87+1 -> 2030 | Q87: =P87+1 -> 2031 | ... AH87: =AG87+1 -> 2048
B88: Flows related to Leases | D88: =+Inputs!F71+Inputs!F72 -> -89 | E88: =+Inputs!E71+Inputs!E72 -> 1581 | F88: =+Inputs!D71+Inputs!D72 -> -224 | G88: =+Inputs!B71+Inputs!B72 -> -139 | H88: =+Inputs!B71-Inputs!C71 -> -65 | I88: =+I89*I9 -> -384.94039 | J88: =+J89*J9 -> -461.92846 | K88: =+K89*K9 -> -531.21773 | L88: =+L89*L9 -> -610.90039 | M88: =+M89*M9 -> -671.99043 | N88: =+N89*N9 -> -732.46957 | O88: =+O89*O9 -> -798.39183 | P88: =+P89*P9 -> -862.26318 | ... AH88: =+AH89*AH9 -> -1880.6651
B89: % of Sales | C89: =C88/C$9 -> 0 | D89: =D88/D$9 -> -0.008530624 | E89: =E88/E$9 -> 0.12161538 | F89: =F88/F$9 -> -0.020109525 | G89: =G88/G$9 -> -0.0079633343 | H89: =H88/H$9 -> -0.0020390877 | I89: =+$H$90 -> -0.0096606428 | J89: =+$H$90 -> -0.0096606428 | K89: =+$H$90 -> -0.0096606428 | L89: =+$H$90 -> -0.0096606428 | M89: =+$H$90 -> -0.0096606428 | N89: =+$H$90 -> -0.0096606428 | O89: =+$H$90 -> -0.0096606428 | P89: =+$H$90 -> -0.0096606428 | ... R89: =+$H$90 -> -0.0096606428 | S89: =$R$90 -> -0.0096606428 | T89: =$R$90 -> -0.0096606428 | U89: =$R$90 -> -0.0096606428 | V89: =$R$90 -> -0.0096606428 | W89: =$R$90 -> -0.0096606428 | X89: =$R$90 -> -0.0096606428 | Y89: =$R$90 -> -0.0096606428 | Z89: =$R$90 -> -0.0096606428 | ... AH89: =$R$90 -> -0.0096606428
B90: Target 5y Average | H90: =AVERAGE(D89,F89:H89) -> -0.0096606428 | R90: =+I140 -> -0.0096606428 | W90: =AVERAGE(S89:W89) -> -0.0096606428 | AB90: =AVERAGE(X89:AB89) -> -0.0096606428 | AG90: =AVERAGE(AC89:AG89) -> -0.0096606428
C92: Industry Average | J92: Short Term Forecast
C93: Dividends | D93: Net Iincome | E93: Payout | F93: Dividends + Buybacks | G93: Buybacks | H93: Buybacks % Net Income | I93: Cash Return % Net Income
B94: Net Income distribution | C94: 6209.1 | D94: 18562.94 | E94: 0.33448904 | F94: 14374.3 | G94: =+F94-C94 -> 8165.2 | H94: =+G94/D94 -> 0.43986567 | I94: 0.77435471 | J94: 2023 | K94: =J94+1 -> 2024 | L94: =K94+1 -> 2025 | M94: =L94+1 -> 2026 | N94: =M94+1 -> 2027 | O94: =N94+1 -> 2028 | P94: =O94+1 -> 2029 | Q94: =P94+1 -> 2030 | R94: =Q94+1 -> 2031 | ... AI94: =AH94+1 -> 2048
B95: NET INCOME | J95: =+DCF!G17 -> -4210.1217 | K95: =+DCF!H17 -> -3471.8576 | L95: =+DCF!I17 -> -1496.0551 | M95: =+DCF!J17 -> -188.05807 | N95: =+DCF!K17 -> 1237.6395 | O95: =+DCF!L17 -> 2785.8354 | P95: =+DCF!M17 -> 3834.1734 | Q95: =+DCF!N17 -> 4280.5874 | ... AI95: =+DCF!AF17 -> 10663.377
B96: Buybacks | N96: =+N95*0.2 -> 247.52789 | O96: =+O95*0.25 -> 696.45885 | P96: =+P95*0.3 -> 1150.252 | Q96: =+Q95*0.35 -> 1498.2056 | R96: =+R95*0.4 -> 2226.1164 | S96: =+S95*$S$97 -> 3056.5653 | T96: =+T95*$S$97 -> 3734.6393 | U96: =+U95*$S$97 -> 4453.9058 | V96: =+V95*$S$97 -> 4717.0537 | W96: =+W95*$S$97 -> 4986.7884 | X96: =+X95*$S$97 -> 5274.8162 | Y96: =+Y95*$S$97 -> 5037.8872 | Z96: =+Z95*$S$97 -> 4746.7382 | ... AI96: =+AI95*$S$97 -> 4690.4533
B97: Target Long Term | S97: =+H94 -> 0.43986567
B98: Dividends | Q98: =+Q95*0.1 -> 428.05874 | R98: =+R95*0.15 -> 834.79367 | S98: =+S95*0.2 -> 1389.7722 | T98: =+T95*0.25 -> 2122.6022 | U98: =+U95*0.3 -> 3037.6814 | V98: =+V95*$V$99 -> 3587.0105 | W98: =+W95*$V$99 -> 3792.1261 | X98: =+X95*$V$99 -> 4011.1524 | Y98: =+Y95*$V$99 -> 3830.9834 | Z98: =+Z95*$V$99 -> 3609.5837 | AA98: =+AA95*$V$99 -> 3356.47 | AB98: =+AB95*$V$99 -> 3051.4123 | AC98: =+AC95*$V$99 -> 3185.3996 | ... AI98: =+AI95*$V$99 -> 3566.7826
V99: =+E94 -> 0.33448904
B102: Segments | C102: Weight | D102: Country Risk Premium | E102: Country Equity Risk Premium
B103: North America (US & Canada) | C103: =+Segments!B5 -> 0.609375 | L103: 2019 | M103: 2020 | N103: =M103+1 -> 2021 | O103: =N103+1 -> 2022 | P103: =O103+1 -> 2023 | Q103: =P103+1 -> 2024 | R103: =Q103+1 -> 2025 | S103: =R103+1 -> 2026 | T103: =S103+1 -> 2027 | U103: =T103+1 -> 2028 | ... AO103: =AN103+1 -> 2048
B104: EMEA (Europe Middle East and Africa) | C104: =+Segments!B6 -> 0.21875 | K104: Revenue | L104: =+E9 -> 13000 | M104: =+F9 -> 11139 | N104: =+G9 -> 17455 | O104: =+H9 -> 31877 | P104: =+I9 -> 39846.25 | Q104: =+J9 -> 47815.5 | R104: =+K9 -> 54987.825 | S104: =+L9 -> 63235.999 | ... AO104: =+AH9 -> 194672.88
B105: APAC (Africa) | C105: =+Segments!B7 -> 0.109375 | K105: COGS | L105: 6061 | M105: 5154 | N105: 9351 | O105: 19659 | P105: =+P121 -> 24175.287 | Q105: =+Q121 -> 28532.19 | R105: =+R121 -> 32262.14 | S105: =+S121 -> 36469.101 | T105: =+T121 -> 39420.415 | U105: =+U121 -> 42210.053 | V105: =+V121 -> 45182.52 | W105: =+W121 -> 47904.569 | ... AO105: =+AO121 -> 69442.588
B106: Latin America | C106: =+Segments!B8 -> 0.0625 | K106: AR | L106: 1214 | M106: 1073 | N106: 2439 | O106: 2779
B107: Total | C107: 1 | D107: =D105*$C$105+D106*$C$106 -> 0 | E107: =E105*$C$105+E106*$C$106 -> 0 | K107: AP | L107: 272 | M107: 235 | N107: 860 | O107: 728
K109: DSO | M109: =+ROUNDUP((((L106+M106)/2)/M$104)*365,0) -> 38 | N109: =+ROUNDUP((((M106+N106)/2)/N$104)*365,0) -> 37 | O109: =+ROUNDUP((((N106+O106)/2)/O$104)*365,0) -> 30 | P109: =+AVERAGE(M109:O109) -> 35
B110: Equity premium | C110: =C112+C111*(C113-C112) -> 0.04446 | K110: DPO | M110: =+ROUNDUP((((L107+M107)/2)/M$105)*365,0) -> 18 | N110: =+ROUNDUP((((M107+N107)/2)/N$105)*365,0) -> 22 | O110: =+ROUNDUP((((N107+O107)/2)/O$105)*365,0) -> 15 | P110: =+AVERAGE(M110:O110) -> 18.333333
B111: Beta | C111: 1.23
B112: Rf | C112: 0.042 | I112: AVG DSO*REV/365 | K112: A/R | M112: =+M106 -> 1073 | N112: =+N106 -> 2439 | O112: =+O106 -> 2779 | P112: =+($P109*P104)/365 -> 3820.8733 | Q112: =+($P109*Q104)/365 -> 4585.0479 | R112: =+($P109*R104)/365 -> 5272.8051 | S112: =+($P109*S104)/365 -> 6063.7259 | T112: =+($P109*T104)/365 -> 6670.0985 | U112: =+($P109*U104)/365 -> 7270.4074 | V112: =+($P109*V104)/365 -> 7924.744 | W112: =+($P109*W104)/365 -> 8558.7235 | ... AO112: =+($P109*AO104)/365 -> 18667.262
B113: Rm | C113: 0.044 | I113: AVG DPO*COGS/365 | K113: A/P | M113: =+M107 -> 235 | N113: =+N107 -> 860 | O113: =+O107 -> 728 | P113: =+($P110*P105)/365 -> 1214.2838 | Q113: =+($P110*Q105)/365 -> 1433.1237 | R113: =+($P110*R105)/365 -> 1620.4728 | S113: =+($P110*S105)/365 -> 1831.7813 | T113: =+($P110*T105)/365 -> 1980.0209 | U113: =+($P110*U105)/365 -> 2120.1397 | V113: =+($P110*V105)/365 -> 2269.4417 | W113: =+($P110*W105)/365 -> 2406.1656 | ... AO113: =+($P110*AO105)/365 -> 3487.9839
B115: Risk-Free Rate Calculation | K115: (non-cash WC) | M115: =M112-M113 -> 838 | N115: =N112-N113 -> 1579 | O115: =O112-O113 -> 2051 | P115: =P112-P113 -> 2606.5894 | Q115: =Q112-Q113 -> 3151.9242 | R115: =R112-R113 -> 3652.3323 | S115: =S112-S113 -> 4231.9446 | T115: =T112-T113 -> 4690.0776 | ... AO115: =AO112-AO113 -> 15179.278
B116: Region | C116: Weight | D116: Risk Free | E116: CDS
B117: North America (US & Canada) | C117: =+C103 -> 0.609375 | F117: =C117*(D117-E117) -> 0 | K117: Change in NC WC | M117: =M115-L115 -> 838 | N117: =N115-M115 -> 741 | O117: =O115-N115 -> 472 | P117: =P115-O115 -> 555.58944 | Q117: =Q115-P115 -> 545.33481 | R117: =R115-Q115 -> 500.40809 | S117: =S115-R115 -> 579.61222 | T117: =T115-S115 -> 458.13307 | ... AO117: =AO115-AN115 -> 247.10265
B118: EMEA (Europe Middle East and Africa) | C118: =+C104 -> 0.21875 | F118: =C118*(D118-E118) -> 0
B119: APAC (Africa) | C119: =+C105 -> 0.109375 | F119: =C119*(D119-E119) -> 0
B120: Latin America | C120: =+C106 -> 0.0625 | F120: =C120*(D120-E120) -> 0 | K120: Revenue | L120: =+E9 -> 13000 | M120: =+F9 -> 11139 | N120: =+G9 -> 17455 | O120: =+H9 -> 31877 | P120: =+I9 -> 39846.25 | Q120: =+J9 -> 47815.5 | R120: =+K9 -> 54987.825 | S120: =+L9 -> 63235.999 | ... AO120: =+AH9 -> 194672.88
F121: =SUM(F117:F120) -> 0 | K121: COGS | L121: =+L105 -> 6061 | M121: =+M105 -> 5154 | N121: =+N105 -> 9351 | O121: =+O105 -> 19659 | P121: =+P120*(1-P122) -> 24175.287 | Q121: =+Q120*(1-Q122) -> 28532.19 | R121: =+R120*(1-R122) -> 32262.14 | S121: =+S120*(1-S122) -> 36469.101 | T121: =+T120*(1-T122) -> 39420.415 | U121: =+U120*(1-U122) -> 42210.053 | V121: =+V120*(1-V122) -> 45182.52 | W121: =+W120*(1-W122) -> 47904.569 | ... AO121: =+AO120*(1-AO122) -> 69442.588
K122: Gross PM | M122: =1-M121/M120 -> 0.53730137 | N122: =1-N121/N120 -> 0.46427958 | O122: =1-O121/O120 -> 0.38328575 | P122: =O122+0.01 -> 0.39328575 | Q122: =P122+0.01 -> 0.40328575 | R122: =Q122+0.01 -> 0.41328575 | S122: =R122+0.01 -> 0.42328575 | T122: =S122+0.01 -> 0.43328575 | U122: =T122+0.01 -> 0.44328575 | V122: =U122+0.01 -> 0.45328575 | W122: =V122+0.01 -> 0.46328575 | ... AO122: =AN122+0.01 -> 0.64328575
C125: Last 5 Years
C126: 2018 | D126: 2019 | E126: 2020 | F126: 2021 | G126: 2022 | H126: Short Term Forecast | I126: Long Term Forecast
B127: Depreciation factor | C127: =+D18 -> 0.25045704 | D127: =+E18 -> 0.26343154 | E127: =+F18 -> 0.23153252 | F127: =+G18 -> 0.24986508 | G127: =+H18 -> 0.20365034 | H127: =AVERAGE(C127:G127)*(1-(-H20)) -> 0.21594303 | I127: =+AVERAGE(H19,N19,S19) -> 0.20312967 | L127: 2020 | M127: 2021 | N127: 2022
B128: Amortization factor | C128: =+D25 -> 0.0091407678 | D128: =+E25 -> 0.009243212 | E128: =+F25 -> 0.085446527 | F128: =+G25 -> 0.23691311 | G128: =+H25 -> 0.25120077 | H128: =AVERAGE(D128:G128) -> 0.14570091 | I128: =AVERAGE(D128:H128) -> 0.14570091 | K128: Acc Amort Dep | L128: 1016 | M128: 1182 | N128: 1285
B129: Stock-based comp | E129: =+F32 -> 0.074243648 | F129: =+G32 -> 0.066914924 | G129: =+H32 -> 0.056247451 | H129: =AVERAGE(E129:G129) -> 0.065802008 | I129: =AVERAGE(C129:G129) -> 0.065802008 | K129: Acc Amort | L129: 175 | M129: 620 | N129: 1119
B130: Tax Rate | C130: 0.216 | D130: -0.005 | E130: 0.028 | F130: 0.48 | G130: 0.019 | H130: =AVERAGE(C130:G130) -> 0.1476 | I130: =AVERAGE(D130:H130) -> 0.13392 | K130: Acc Dep | L130: =+L128-L129 -> 841 | M130: =+M128-M129 -> 562 | N130: =+N128-N129 -> 166
B131: Interest Rate on debt | H131: =+F46 -> 0 | I131: 0.04
B132: Interest Rate on cash | H132: 0.044 | I132: 0.0433
...

Sheet Fin. Data
A1: =Inputs!H3 -> #VALUE!
A2: =Inputs!G2 -> Figures in Millions of USD
A3: Results
B4: =OP!J17 -> 2022 | C4: =B4-1 -> 2021 | D4: =C4-1 -> 2020 | E4: =D4-1 -> 2019 | F4: =E4-1 -> 2018 | G4: =F4-1 -> 2017 | H4: =G4-1 -> 2016 | I4: =H4-1 -> 2015 | J4: =I4-1 -> 2014 | ... M4: =L4-1 -> 2011
A5: Net Sales | B5: =_xlfn.XLOOKUP($A5,Inputs!$A:$A,Inputs!B:B,,0) -> 31877 | C5: =_xlfn.XLOOKUP($A5,Inputs!$A:$A,Inputs!C:C,,0) -> 17455 | D5: =_xlfn.XLOOKUP($A5,Inputs!$A:$A,Inputs!D:D,,0) -> 11139 | E5: =_xlfn.XLOOKUP($A5,Inputs!$A:$A,Inputs!E:E,,0) -> 13000 | F5: =_xlfn.XLOOKUP($A5,Inputs!$A:$A,Inputs!F:F,,0) -> 10433 | G5: =_xlfn.XLOOKUP($A5,Inputs!$A:$A,Inputs!G:G,,0) -> 7932 | H5: =_xlfn.XLOOKUP($A5,Inputs!$A:$A,Inputs!H:H,,0) -> 0 | I5: =_xlfn.XLOOKUP($A5,Inputs!$A:$A,Inputs!I:I,,0) -> 0 | J5: =_xlfn.XLOOKUP($A5,Inputs!$A:$A,Inputs!J:J,,0) -> 0 | K5: =_xlfn.XLOOKUP($A5,Inputs!$A:$A,Inputs!K:K,,0) -> 0 | L5: =_xlfn.XLOOKUP($A5,Inputs!$A:$A,Inputs!L:L,,0) -> 0 | M5: =_xlfn.XLOOKUP($A5,Inputs!$A:$A,Inputs!M:M,,0) -> 0
A6: Growth vs. Previous year | B6: =IFERROR(B5/C5-1,"-") -> 0.8262389 | C6: =IFERROR(C5/D5-1,"-") -> 0.56701679 | D6: =IFERROR(D5/E5-1,"-") -> -0.14315385 | E6: =IFERROR(E5/F5-1,"-") -> 0.2460462 | F6: =IFERROR(F5/G5-1,"-") -> 0.31530509 | G6: =IFERROR(G5/H5-1,"-") -> - | H6: =IFERROR(H5/I5-1,"-") -> - | I6: =IFERROR(I5/J5-1,"-") -> - | ... L6: =IFERROR(L5/M5-1,"-") -> - | M6: =IFERROR(M5/#REF!-1,"-") -> -
A7: Gross Profit | B7: =_xlfn.XLOOKUP($A7,Inputs!$A:$A,Inputs!B:B,,0) -> 12218 | C7: =_xlfn.XLOOKUP($A7,Inputs!$A:$A,Inputs!C:C,,0) -> 8104 | D7: =_xlfn.XLOOKUP($A7,Inputs!$A:$A,Inputs!D:D,,0) -> 5985 | E7: =_xlfn.XLOOKUP($A7,Inputs!$A:$A,Inputs!E:E,,0) -> 6939 | F7: =_xlfn.XLOOKUP($A7,Inputs!$A:$A,Inputs!F:F,,0) -> 5647 | G7: =_xlfn.XLOOKUP($A7,Inputs!$A:$A,Inputs!G:G,,0) -> 3772 | H7: =_xlfn.XLOOKUP($A7,Inputs!$A:$A,Inputs!H:H,,0) -> 0 | I7: =_xlfn.XLOOKUP($A7,Inputs!$A:$A,Inputs!I:I,,0) -> 0 | J7: =_xlfn.XLOOKUP($A7,Inputs!$A:$A,Inputs!J:J,,0) -> 0 | K7: =_xlfn.XLOOKUP($A7,Inputs!$A:$A,Inputs!K:K,,0) -> 0 | L7: =_xlfn.XLOOKUP($A7,Inputs!$A:$A,Inputs!L:L,,0) -> 0 | M7: =_xlfn.XLOOKUP($A7,Inputs!$A:$A,Inputs!M:M,,0) -> 0
A8: % over sales | B8: =IFERROR(B7/B$5,"-") -> 0.38328575 | C8: =IFERROR(C7/C$5,"-") -> 0.46427958 | D8: =IFERROR(D7/D$5,"-") -> 0.53730137 | E8: =IFERROR(E7/E$5,"-") -> 0.53376923 | F8: =IFERROR(F7/F$5,"-") -> 0.5412633 | G8: =IFERROR(G7/G$5,"-") -> 0.47554211 | H8: =IFERROR(H7/H$5,"-") -> - | I8: =IFERROR(I7/I$5,"-") -> - | ... M8: =IFERROR(M7/M$5,"-") -> -
A9: Operating expenses | B9: =B5-B11 -> 33709 | C9: =C5-C11 -> 21289 | D9: =D5-D11 -> 16002 | E9: =E5-E11 -> 21596 | F9: =F5-F11 -> 13466 | G9: =G5-G11 -> 12012 | H9: =H5-H11 -> 0 | I9: =I5-I11 -> 0 | ... M9: =M5-M11 -> 0
A10: % over sales | B10: =IFERROR(B9/B$5,"-") -> 1.0574709 | C10: =IFERROR(C9/C$5,"-") -> 1.2196505 | D10: =IFERROR(D9/D$5,"-") -> 1.4365742 | E10: =IFERROR(E9/E$5,"-") -> 1.6612308 | F10: =IFERROR(F9/F$5,"-") -> 1.2907122 | G10: =IFERROR(G9/G$5,"-") -> 1.5143722 | H10: =IFERROR(H9/H$5,"-") -> - | I10: =IFERROR(I9/I$5,"-") -> - | ... M10: =IFERROR(M9/M$5,"-") -> -
A11: Operating Income | B11: =_xlfn.XLOOKUP($A11,Inputs!$A:$A,Inputs!B:B,,0) -> -1832 | C11: =_xlfn.XLOOKUP($A11,Inputs!$A:$A,Inputs!C:C,,0) -> -3834 | D11: =_xlfn.XLOOKUP($A11,Inputs!$A:$A,Inputs!D:D,,0) -> -4863 | E11: =_xlfn.XLOOKUP($A11,Inputs!$A:$A,Inputs!E:E,,0) -> -8596 | F11: =_xlfn.XLOOKUP($A11,Inputs!$A:$A,Inputs!F:F,,0) -> -3033 | G11: =_xlfn.XLOOKUP($A11,Inputs!$A:$A,Inputs!G:G,,0) -> -4080 | H11: =_xlfn.XLOOKUP($A11,Inputs!$A:$A,Inputs!H:H,,0) -> 0 | I11: =_xlfn.XLOOKUP($A11,Inputs!$A:$A,Inputs!I:I,,0) -> 0 | J11: =_xlfn.XLOOKUP($A11,Inputs!$A:$A,Inputs!J:J,,0) -> 0 | K11: =_xlfn.XLOOKUP($A11,Inputs!$A:$A,Inputs!K:K,,0) -> 0 | L11: =_xlfn.XLOOKUP($A11,Inputs!$A:$A,Inputs!L:L,,0) -> 0 | M11: =_xlfn.XLOOKUP($A11,Inputs!$A:$A,Inputs!M:M,,0) -> 0
A12: Operating Margin | B12: =IFERROR(B11/B$5,"-") -> -0.057470904 | C12: =IFERROR(C11/C$5,"-") -> -0.21965053 | D12: =IFERROR(D11/D$5,"-") -> -0.4365742 | E12: =IFERROR(E11/E$5,"-") -> -0.66123077 | F12: =IFERROR(F11/F$5,"-") -> -0.29071216 | G12: =IFERROR(G11/G$5,"-") -> -0.51437216 | H12: =IFERROR(H11/H$5,"-") -> - | I12: =IFERROR(I11/I$5,"-") -> - | ... M12: =IFERROR(M11/M$5,"-") -> -
A13: Growth vs. Previous year | B13: =IFERROR(B12/C12-1,"-") -> -0.73835299 | C13: =IFERROR(C12/D12-1,"-") -> -0.49687698 | D13: =IFERROR(D12/E12-1,"-") -> -0.33975517 | E13: =IFERROR(E12/F12-1,"-") -> 1.2745205 | F13: =IFERROR(F12/G12-1,"-") -> -0.43482135 | G13: =IFERROR(G12/H12-1,"-") -> - | H13: =IFERROR(H12/I12-1,"-") -> - | I13: =IFERROR(I12/J12-1,"-") -> - | ... L13: =IFERROR(L12/M12-1,"-") -> - | M13: =IFERROR(M12/#REF!-1,"-") -> -
A14: Net Financial Cost | B14: =_xlfn.XLOOKUP($A14,Inputs!$A:$A,Inputs!B:B,,0) -> -426 | C14: =_xlfn.XLOOKUP($A14,Inputs!$A:$A,Inputs!C:C,,0) -> -446 | D14: =_xlfn.XLOOKUP($A14,Inputs!$A:$A,Inputs!D:D,,0) -> -403 | E14: =_xlfn.XLOOKUP($A14,Inputs!$A:$A,Inputs!E:E,,0) -> -325 | F14: =_xlfn.XLOOKUP($A14,Inputs!$A:$A,Inputs!F:F,,0) -> -544 | G14: =_xlfn.XLOOKUP($A14,Inputs!$A:$A,Inputs!G:G,,0) -> -408 | H14: =_xlfn.XLOOKUP($A14,Inputs!$A:$A,Inputs!H:H,,0) -> 0 | I14: =_xlfn.XLOOKUP($A14,Inputs!$A:$A,Inputs!I:I,,0) -> 0 | J14: =_xlfn.XLOOKUP($A14,Inputs!$A:$A,Inputs!J:J,,0) -> 0 | K14: =_xlfn.XLOOKUP($A14,Inputs!$A:$A,Inputs!K:K,,0) -> 0 | L14: =_xlfn.XLOOKUP($A14,Inputs!$A:$A,Inputs!L:L,,0) -> 0 | M14: =_xlfn.XLOOKUP($A14,Inputs!$A:$A,Inputs!M:M,,0) -> 0
A15: Other Expenses (Revenues) | B15: =_xlfn.XLOOKUP($A15,Inputs!$A:$A,Inputs!B:B,,0) -> -7029 | C15: =_xlfn.XLOOKUP($A15,Inputs!$A:$A,Inputs!C:C,,0) -> 3292 | D15: =_xlfn.XLOOKUP($A15,Inputs!$A:$A,Inputs!D:D,,0) -> -1625 | E15: =_xlfn.XLOOKUP($A15,Inputs!$A:$A,Inputs!E:E,,0) -> 722 | F15: =_xlfn.XLOOKUP($A15,Inputs!$A:$A,Inputs!F:F,,0) -> 4993 | G15: =_xlfn.XLOOKUP($A15,Inputs!$A:$A,Inputs!G:G,,0) -> -16 | H15: =_xlfn.XLOOKUP($A15,Inputs!$A:$A,Inputs!H:H,,0) -> 0 | I15: =_xlfn.XLOOKUP($A15,Inputs!$A:$A,Inputs!I:I,,0) -> 0 | J15: =_xlfn.XLOOKUP($A15,Inputs!$A:$A,Inputs!J:J,,0) -> 0 | K15: =_xlfn.XLOOKUP($A15,Inputs!$A:$A,Inputs!K:K,,0) -> 0 | L15: =_xlfn.XLOOKUP($A15,Inputs!$A:$A,Inputs!L:L,,0) -> 0 | M15: =_xlfn.XLOOKUP($A15,Inputs!$A:$A,Inputs!M:M,,0) -> 0
A16: EBIT | B16: =B11-B15 -> 5197 | C16: =C11-C15 -> -7126 | D16: =D11-D15 -> -3238 | E16: =E11-E15 -> -9318 | F16: =F11-F15 -> -8026 | G16: =G11-G15 -> -4064 | H16: =H11-H15 -> 0 | I16: =I11-I15 -> 0 | ... M16: =M11-M15 -> 0
A17: Depreciation & Amortization | B17: =_xlfn.XLOOKUP($A17,Inputs!$A:$A,Inputs!B:B,,0) -> 947 | C17: =_xlfn.XLOOKUP($A17,Inputs!$A:$A,Inputs!C:C,,0) -> 902 | D17: =_xlfn.XLOOKUP($A17,Inputs!$A:$A,Inputs!D:D,,0) -> 575 | E17: =_xlfn.XLOOKUP($A17,Inputs!$A:$A,Inputs!E:E,,0) -> 472 | F17: =_xlfn.XLOOKUP($A17,Inputs!$A:$A,Inputs!F:F,,0) -> 426 | G17: =_xlfn.XLOOKUP($A17,Inputs!$A:$A,Inputs!G:G,,0) -> 510 | H17: =_xlfn.XLOOKUP($A17,Inputs!$A:$A,Inputs!H:H,,0) -> 0 | I17: =_xlfn.XLOOKUP($A17,Inputs!$A:$A,Inputs!I:I,,0) -> 0 | J17: =_xlfn.XLOOKUP($A17,Inputs!$A:$A,Inputs!J:J,,0) -> 0 | K17: =_xlfn.XLOOKUP($A17,Inputs!$A:$A,Inputs!K:K,,0) -> 0 | L17: =_xlfn.XLOOKUP($A17,Inputs!$A:$A,Inputs!L:L,,0) -> 0 | M17: =_xlfn.XLOOKUP($A17,Inputs!$A:$A,Inputs!M:M,,0) -> 0
A18: Changes Net Working Capital | B18: =_xlfn.XLOOKUP($A18,Inputs!$A:$A,Inputs!B:B,,0) -> 601 | C18: =_xlfn.XLOOKUP($A18,Inputs!$A:$A,Inputs!C:C,,0) -> -3222 | D18: =_xlfn.XLOOKUP($A18,Inputs!$A:$A,Inputs!D:D,,0) -> -5269 | E18: =_xlfn.XLOOKUP($A18,Inputs!$A:$A,Inputs!E:E,,0) -> 3887 | F18: =_xlfn.XLOOKUP($A18,Inputs!$A:$A,Inputs!F:F,,0) -> 1419 | G18: =_xlfn.XLOOKUP($A18,Inputs!$A:$A,Inputs!G:G,,0) -> 0 | H18: =_xlfn.XLOOKUP($A18,Inputs!$A:$A,Inputs!H:H,,0) -> 0 | I18: =_xlfn.XLOOKUP($A18,Inputs!$A:$A,Inputs!I:I,,0) -> 0 | J18: =_xlfn.XLOOKUP($A18,Inputs!$A:$A,Inputs!J:J,,0) -> 0 | K18: =_xlfn.XLOOKUP($A18,Inputs!$A:$A,Inputs!K:K,,0) -> 0 | L18: =_xlfn.XLOOKUP($A18,Inputs!$A:$A,Inputs!L:L,,0) -> 0 | M18: =_xlfn.XLOOKUP($A18,Inputs!$A:$A,Inputs!M:M,,0) -> 0
A19: EBITDA | B19: =B11-B15+B17 -> 6144 | C19: =C11-C15+C17 -> -6224 | D19: =D11-D15+D17 -> -2663 | E19: =E11-E15+E17 -> -8846 | F19: =F11-F15+F17 -> -7600 | G19: =G11-G15+G17 -> -3554 | H19: =H11-H15+H17 -> 0 | I19: =I11-I15+I17 -> 0 | ... M19: =M11-M15+M17 -> 0
A20: EBITDA Margin | B20: =IFERROR(B19/B$5,"-") -> 0.19274085 | C20: =IFERROR(C19/C$5,"-") -> -0.35657405 | D20: =IFERROR(D19/D$5,"-") -> -0.23906993 | E20: =IFERROR(E19/E$5,"-") -> -0.68046154 | F20: =IFERROR(F19/F$5,"-") -> -0.72845778 | G20: =IFERROR(G19/G$5,"-") -> -0.4480585 | H20: =IFERROR(H19/H$5,"-") -> - | I20: =IFERROR(I19/I$5,"-") -> - | ... M20: =IFERROR(M19/M$5,"-") -> -
A21: Taxes | B21: =_xlfn.XLOOKUP($A21,Inputs!$A:$A,Inputs!B:B,,0) -> -181 | C21: =_xlfn.XLOOKUP($A21,Inputs!$A:$A,Inputs!C:C,,0) -> -492 | D21: =_xlfn.XLOOKUP($A21,Inputs!$A:$A,Inputs!D:D,,0) -> -192 | E21: =_xlfn.XLOOKUP($A21,Inputs!$A:$A,Inputs!E:E,,0) -> 45 | F21: =_xlfn.XLOOKUP($A21,Inputs!$A:$A,Inputs!F:F,,0) -> 283 | G21: =_xlfn.XLOOKUP($A21,Inputs!$A:$A,Inputs!G:G,,0) -> -542 | H21: =_xlfn.XLOOKUP($A21,Inputs!$A:$A,Inputs!H:H,,0) -> 0 | I21: =_xlfn.XLOOKUP($A21,Inputs!$A:$A,Inputs!I:I,,0) -> 0 | J21: =_xlfn.XLOOKUP($A21,Inputs!$A:$A,Inputs!J:J,,0) -> 0 | K21: =_xlfn.XLOOKUP($A21,Inputs!$A:$A,Inputs!K:K,,0) -> 0 | L21: =_xlfn.XLOOKUP($A21,Inputs!$A:$A,Inputs!L:L,,0) -> 0 | M21: =_xlfn.XLOOKUP($A21,Inputs!$A:$A,Inputs!M:M,,0) -> 0
A22: % Tax | B22: =IFERROR(B21/B$5,"-") -> -0.0056780751 | C22: =IFERROR(C21/C$5,"-") -> -0.028186766 | D22: =IFERROR(D21/D$5,"-") -> -0.017236736 | E22: =IFERROR(E21/E$5,"-") -> 0.0034615385 | F22: =IFERROR(F21/F$5,"-") -> 0.027125467 | G22: =IFERROR(G21/G$5,"-") -> -0.068330812 | H22: =IFERROR(H21/H$5,"-") -> - | I22: =IFERROR(I21/I$5,"-") -> - | ... M22: =IFERROR(M21/M$5,"-") -> -
A23: Net Income | B23: =_xlfn.XLOOKUP($A23,Inputs!$A:$A,Inputs!B:B,,0) -> -9141 | C23: =_xlfn.XLOOKUP($A23,Inputs!$A:$A,Inputs!C:C,,0) -> -496 | D23: =_xlfn.XLOOKUP($A23,Inputs!$A:$A,Inputs!D:D,,0) -> -6768 | E23: =_xlfn.XLOOKUP($A23,Inputs!$A:$A,Inputs!E:E,,0) -> -8512 | F23: =_xlfn.XLOOKUP($A23,Inputs!$A:$A,Inputs!F:F,,0) -> 987 | G23: =_xlfn.XLOOKUP($A23,Inputs!$A:$A,Inputs!G:G,,0) -> -4033 | H23: =_xlfn.XLOOKUP($A23,Inputs!$A:$A,Inputs!H:H,,0) -> 0 | I23: =_xlfn.XLOOKUP($A23,Inputs!$A:$A,Inputs!I:I,,0) -> 0 | J23: =_xlfn.XLOOKUP($A23,Inputs!$A:$A,Inputs!J:J,,0) -> 0 | K23: =_xlfn.XLOOKUP($A23,Inputs!$A:$A,Inputs!K:K,,0) -> 0 | L23: =_xlfn.XLOOKUP($A23,Inputs!$A:$A,Inputs!L:L,,0) -> 0 | M23: =_xlfn.XLOOKUP($A23,Inputs!$A:$A,Inputs!M:M,,0) -> 0
A24: Net Income Margin | B24: =IFERROR(B23/B$5,"-") -> -0.28675848 | C24: =IFERROR(C23/C$5,"-") -> -0.028415927 | D24: =IFERROR(D23/D$5,"-") -> -0.60759494 | E24: =IFERROR(E23/E$5,"-") -> -0.65476923 | F24: =IFERROR(F23/F$5,"-") -> 0.094603661 | G24: =IFERROR(G23/G$5,"-") -> -0.5084468 | H24: =IFERROR(H23/H$5,"-") -> - | I24: =IFERROR(I23/I$5,"-") -> - | ... M24: =IFERROR(M23/M$5,"-") -> -
A25: Growth vs. Previous year | B25: =IFERROR(B24/C24-1,"-") -> 9.0914702 | C25: =IFERROR(C24/D24-1,"-") -> -0.95323212 | D25: =IFERROR(D24/E24-1,"-") -> -0.072047207 | E25: =IFERROR(E24/F24-1,"-") -> -7.9211828 | F25: =IFERROR(F24/G24-1,"-") -> -1.186064 | G25: =IFERROR(G24/H24-1,"-") -> - | H25: =IFERROR(H24/I24-1,"-") -> - | I25: =IFERROR(I24/J24-1,"-") -> - | ... L25: =IFERROR(L24/M24-1,"-") -> - | M25: =IFERROR(M24/#REF!-1,"-") -> -
A26: Cash Generated | B26: =B39-C39 -> -87 | C26: =C39-D39 -> -1352 | D26: =D39-E39 -> -5226 | E26: =E39-F39 -> 4467 | F26: =F39-G39 -> 1871 | G26: =G39-H39 -> 4535 | H26: =H39-I39 -> 0 | I26: =I39-J39 -> 0 | ... M26: =M39-N39 -> 0
A27: Dividends | B27: =_xlfn.XLOOKUP($A27,Inputs!$A:$A,Inputs!B:B,,0) -> 0 | C27: =_xlfn.XLOOKUP($A27,Inputs!$A:$A,Inputs!C:C,,0) -> 0 | D27: =_xlfn.XLOOKUP($A27,Inputs!$A:$A,Inputs!D:D,,0) -> 0 | E27: =_xlfn.XLOOKUP($A27,Inputs!$A:$A,Inputs!E:E,,0) -> 0 | F27: =_xlfn.XLOOKUP($A27,Inputs!$A:$A,Inputs!F:F,,0) -> 0 | G27: =_xlfn.XLOOKUP($A27,Inputs!$A:$A,Inputs!G:G,,0) -> 0 | H27: =_xlfn.XLOOKUP($A27,Inputs!$A:$A,Inputs!H:H,,0) -> 0 | I27: =_xlfn.XLOOKUP($A27,Inputs!$A:$A,Inputs!I:I,,0) -> 0 | J27: =_xlfn.XLOOKUP($A27,Inputs!$A:$A,Inputs!J:J,,0) -> 0 | K27: =_xlfn.XLOOKUP($A27,Inputs!$A:$A,Inputs!K:K,,0) -> 0 | L27: =_xlfn.XLOOKUP($A27,Inputs!$A:$A,Inputs!L:L,,0) -> 0 | M27: =_xlfn.XLOOKUP($A27,Inputs!$A:$A,Inputs!M:M,,0) -> 0
A28: Share buyback | B28: =_xlfn.XLOOKUP($A28,Inputs!$A:$A,Inputs!B:B,,0) -> 0 | C28: =_xlfn.XLOOKUP($A28,Inputs!$A:$A,Inputs!C:C,,0) -> 0 | D28: =_xlfn.XLOOKUP($A28,Inputs!$A:$A,Inputs!D:D,,0) -> 0 | E28: =_xlfn.XLOOKUP($A28,Inputs!$A:$A,Inputs!E:E,,0) -> 0 | F28: =_xlfn.XLOOKUP($A28,Inputs!$A:$A,Inputs!F:F,,0) -> -10 | G28: =_xlfn.XLOOKUP($A28,Inputs!$A:$A,Inputs!G:G,,0) -> -131 | H28: =_xlfn.XLOOKUP($A28,Inputs!$A:$A,Inputs!H:H,,0) -> 0 | I28: =_xlfn.XLOOKUP($A28,Inputs!$A:$A,Inputs!I:I,,0) -> 0 | J28: =_xlfn.XLOOKUP($A28,Inputs!$A:$A,Inputs!J:J,,0) -> 0 | K28: =_xlfn.XLOOKUP($A28,Inputs!$A:$A,Inputs!K:K,,0) -> 0 | L28: =_xlfn.XLOOKUP($A28,Inputs!$A:$A,Inputs!L:L,,0) -> 0 | M28: =_xlfn.XLOOKUP($A28,Inputs!$A:$A,Inputs!M:M,,0) -> 0
A29: Net Cash Flow | B29: =SUM(B26:B28) -> -87 | C29: =SUM(C26:C28) -> -1352 | D29: =SUM(D26:D28) -> -5226 | E29: =SUM(E26:E28) -> 4467 | F29: =SUM(F26:F28) -> 1861 | G29: =SUM(G26:G28) -> 4404 | H29: =SUM(H26:H28) -> 0 | I29: =SUM(I26:I28) -> 0 | ... M29: =SUM(M26:M28) -> 0
A30: FNP'' | B30: =+B29-(B58-C29) -> -12578 | C30: =+C29-(C58-D29) -> -17683 | D30: =+D29-(D58-E29) -> -10038 | E30: =+E29-(E58-F29) -> -1098 | F30: =+F29-(F58-G29) -> -604 | G30: =+G29-(G58-H29) -> 4404 | H30: =+H29-(H58-I29) -> 0 | I30: =+I29-(I58-J29) -> 0 | ... M30: =+M29-(M58-N29) -> 0
A31: FNP' | B31: =+B30+B33 -> -13717 | C31: =+C30+C33 -> -18301 | D31: =+D30+D33 -> -12169 | E31: =+E30+E33 -> -1351 | F31: =+F30+F33 -> -1080 | G31: =+G30+G33 -> 4404 | H31: =+H30+H33 -> 0 | I31: =+I30+I33 -> 0 | ... M31: =+M30+M33 -> 0
A32: Net Capex | B32: =_xlfn.XLOOKUP($A32,Inputs!$A:$A,Inputs!B:B,,0) -> -252 | C32: =_xlfn.XLOOKUP($A32,Inputs!$A:$A,Inputs!C:C,,0) -> -298 | D32: =_xlfn.XLOOKUP($A32,Inputs!$A:$A,Inputs!D:D,,0) -> -616 | E32: =_xlfn.XLOOKUP($A32,Inputs!$A:$A,Inputs!E:E,,0) -> -588 | F32: =_xlfn.XLOOKUP($A32,Inputs!$A:$A,Inputs!F:F,,0) -> -558 | G32: =_xlfn.XLOOKUP($A32,Inputs!$A:$A,Inputs!G:G,,0) -> 0 | H32: =_xlfn.XLOOKUP($A32,Inputs!$A:$A,Inputs!H:H,,0) -> 0 | I32: =_xlfn.XLOOKUP($A32,Inputs!$A:$A,Inputs!I:I,,0) -> 0 | J32: =_xlfn.XLOOKUP($A32,Inputs!$A:$A,Inputs!J:J,,0) -> 0 | K32: =_xlfn.XLOOKUP($A32,Inputs!$A:$A,Inputs!K:K,,0) -> 0 | L32: =_xlfn.XLOOKUP($A32,Inputs!$A:$A,Inputs!L:L,,0) -> 0 | M32: =_xlfn.XLOOKUP($A32,Inputs!$A:$A,Inputs!M:M,,0) -> 0
A33: Investments & Acquisitions | B33: =_xlfn.XLOOKUP($A33,Inputs!$A:$A,Inputs!B:B,,0) -> -1139 | C33: =_xlfn.XLOOKUP($A33,Inputs!$A:$A,Inputs!C:C,,0) -> -618 | D33: =_xlfn.XLOOKUP($A33,Inputs!$A:$A,Inputs!D:D,,0) -> -2131 | E33: =_xlfn.XLOOKUP($A33,Inputs!$A:$A,Inputs!E:E,,0) -> -253 | F33: =_xlfn.XLOOKUP($A33,Inputs!$A:$A,Inputs!F:F,,0) -> -476 | G33: =_xlfn.XLOOKUP($A33,Inputs!$A:$A,Inputs!G:G,,0) -> 0 | H33: =_xlfn.XLOOKUP($A33,Inputs!$A:$A,Inputs!H:H,,0) -> 0 | I33: =_xlfn.XLOOKUP($A33,Inputs!$A:$A,Inputs!I:I,,0) -> 0 | J33: =_xlfn.XLOOKUP($A33,Inputs!$A:$A,Inputs!J:J,,0) -> 0 | K33: =_xlfn.XLOOKUP($A33,Inputs!$A:$A,Inputs!K:K,,0) -> 0 | L33: =_xlfn.XLOOKUP($A33,Inputs!$A:$A,Inputs!L:L,,0) -> 0 | M33: =_xlfn.XLOOKUP($A33,Inputs!$A:$A,Inputs!M:M,,0) -> 0
A34: Capex + Investments | B34: =+B32+B33 -> -1391 | C34: =+C32+C33 -> -916 | D34: =+D32+D33 -> -2747 | E34: =+E32+E33 -> -841 | F34: =+F32+F33 -> -1034 | G34: =+G32+G33 -> 0 | H34: =+H32+H33 -> 0 | I34: =+I32+I33 -> 0 | ... M34: =+M32+M33 -> 0
A35: Dividends + Share Buyback | B35: =+B27+B28 -> 0 | C35: =+C27+C28 -> 0 | D35: =+D27+D28 -> 0 | E35: =+E27+E28 -> 0 | F35: =+F27+F28 -> -10 | G35: =+G27+G28 -> -131 | H35: =+H27+H28 -> 0 | I35: =+I27+I28 -> 0 | ... M35: =+M27+M28 -> 0
A36: Payout Ratio | B36: =IFERROR(B35/B23,"-") -> 0 | C36: =IFERROR(C35/C23,"-") -> 0 | D36: =IFERROR(D35/D23,"-") -> 0 | E36: =IFERROR(E35/E23,"-") -> 0 | F36: =IFERROR(F35/F23,"-") -> -0.010131712 | G36: =IFERROR(G35/G23,"-") -> 0.032482023 | H36: =IFERROR(H35/H23,"-") -> - | I36: =IFERROR(I35/I23,"-") -> - | ... M36: =IFERROR(M35/M23,"-") -> -
A38: Assets
A39: Cash & Eq. | B39: =_xlfn.XLOOKUP($A39,Inputs!$A:$A,Inputs!B:B,,0) -> 4208 | C39: =_xlfn.XLOOKUP($A39,Inputs!$A:$A,Inputs!C:C,,0) -> 4295 | D39: =_xlfn.XLOOKUP($A39,Inputs!$A:$A,Inputs!D:D,,0) -> 5647 | E39: =_xlfn.XLOOKUP($A39,Inputs!$A:$A,Inputs!E:E,,0) -> 10873 | F39: =_xlfn.XLOOKUP($A39,Inputs!$A:$A,Inputs!F:F,,0) -> 6406 | G39: =_xlfn.XLOOKUP($A39,Inputs!$A:$A,Inputs!G:G,,0) -> 4535 | H39: =_xlfn.XLOOKUP($A39,Inputs!$A:$A,Inputs!H:H,,0) -> 0 | I39: =_xlfn.XLOOKUP($A39,Inputs!$A:$A,Inputs!I:I,,0) -> 0 | J39: =_xlfn.XLOOKUP($A39,Inputs!$A:$A,Inputs!J:J,,0) -> 0 | K39: =_xlfn.XLOOKUP($A39,Inputs!$A:$A,Inputs!K:K,,0) -> 0 | L39: =_xlfn.XLOOKUP($A39,Inputs!$A:$A,Inputs!L:L,,0) -> 0 | M39: =_xlfn.XLOOKUP($A39,Inputs!$A:$A,Inputs!M:M,,0) -> 0
A40: Accounts Receivable | B40: =_xlfn.XLOOKUP($A40,Inputs!$A:$A,Inputs!B:B,,0) -> 2779 | C40: =_xlfn.XLOOKUP($A40,Inputs!$A:$A,Inputs!C:C,,0) -> 2439 | D40: =_xlfn.XLOOKUP($A40,Inputs!$A:$A,Inputs!D:D,,0) -> 1073 | E40: =_xlfn.XLOOKUP($A40,Inputs!$A:$A,Inputs!E:E,,0) -> 1214 | F40: =_xlfn.XLOOKUP($A40,Inputs!$A:$A,Inputs!F:F,,0) -> 919 | G40: =_xlfn.XLOOKUP($A40,Inputs!$A:$A,Inputs!G:G,,0) -> 739 | H40: =_xlfn.XLOOKUP($A40,Inputs!$A:$A,Inputs!H:H,,0) -> 0 | I40: =_xlfn.XLOOKUP($A40,Inputs!$A:$A,Inputs!I:I,,0) -> 0 | J40: =_xlfn.XLOOKUP($A40,Inputs!$A:$A,Inputs!J:J,,0) -> 0 | K40: =_xlfn.XLOOKUP($A40,Inputs!$A:$A,Inputs!K:K,,0) -> 0 | L40: =_xlfn.XLOOKUP($A40,Inputs!$A:$A,Inputs!L:L,,0) -> 0 | M40: =_xlfn.XLOOKUP($A40,Inputs!$A:$A,Inputs!M:M,,0) -> 0
A41: Inventory | B41: =_xlfn.XLOOKUP($A41,Inputs!$A:$A,Inputs!B:B,,0) -> 0 | C41: =_xlfn.XLOOKUP($A41,Inputs!$A:$A,Inputs!C:C,,0) -> 0 | D41: =_xlfn.XLOOKUP($A41,Inputs!$A:$A,Inputs!D:D,,0) -> 0 | E41: =_xlfn.XLOOKUP($A41,Inputs!$A:$A,Inputs!E:E,,0) -> 0 | F41: =_xlfn.XLOOKUP($A41,Inputs!$A:$A,Inputs!F:F,,0) -> 0 | G41: =_xlfn.XLOOKUP($A41,Inputs!$A:$A,Inputs!G:G,,0) -> 0 | H41: =_xlfn.XLOOKUP($A41,Inputs!$A:$A,Inputs!H:H,,0) -> 0 | I41: =_xlfn.XLOOKUP($A41,Inputs!$A:$A,Inputs!I:I,,0) -> 0 | J41: =_xlfn.XLOOKUP($A41,Inputs!$A:$A,Inputs!J:J,,0) -> 0 | K41: =_xlfn.XLOOKUP($A41,Inputs!$A:$A,Inputs!K:K,,0) -> 0 | L41: =_xlfn.XLOOKUP($A41,Inputs!$A:$A,Inputs!L:L,,0) -> 0 | M41: =_xlfn.XLOOKUP($A41,Inputs!$A:$A,Inputs!M:M,,0) -> 0
A42: Property, Plant and Equipment | B42: =_xlfn.XLOOKUP($A42,Inputs!$A:$A,Inputs!B:B,,0) -> 2082 | C42: =_xlfn.XLOOKUP($A42,Inputs!$A:$A,Inputs!C:C,,0) -> 1853 | D42: =_xlfn.XLOOKUP($A42,Inputs!$A:$A,Inputs!D:D,,0) -> 1814 | E42: =_xlfn.XLOOKUP($A42,Inputs!$A:$A,Inputs!E:E,,0) -> 1731 | F42: =_xlfn.XLOOKUP($A42,Inputs!$A:$A,Inputs!F:F,,0) -> 1641 | G42: =_xlfn.XLOOKUP($A42,Inputs!$A:$A,Inputs!G:G,,0) -> 1192 | H42: =_xlfn.XLOOKUP($A42,Inputs!$A:$A,Inputs!H:H,,0) -> 0 | I42: =_xlfn.XLOOKUP($A42,Inputs!$A:$A,Inputs!I:I,,0) -> 0 | J42: =_xlfn.XLOOKUP($A42,Inputs!$A:$A,Inputs!J:J,,0) -> 0 | K42: =_xlfn.XLOOKUP($A42,Inputs!$A:$A,Inputs!K:K,,0) -> 0 | L42: =_xlfn.XLOOKUP($A42,Inputs!$A:$A,Inputs!L:L,,0) -> 0 | M42: =_xlfn.XLOOKUP($A42,Inputs!$A:$A,Inputs!M:M,,0) -> 0
A43: Other Assets | B43: =_xlfn.XLOOKUP($A43,Inputs!$A:$A,Inputs!B:B,,0) -> 20721 | C43: =_xlfn.XLOOKUP($A43,Inputs!$A:$A,Inputs!C:C,,0) -> 27999 | D43: =_xlfn.XLOOKUP($A43,Inputs!$A:$A,Inputs!D:D,,0) -> 22365 | E43: =_xlfn.XLOOKUP($A43,Inputs!$A:$A,Inputs!E:E,,0) -> 14985 | F43: =_xlfn.XLOOKUP($A43,Inputs!$A:$A,Inputs!F:F,,0) -> 13710 | G43: =_xlfn.XLOOKUP($A43,Inputs!$A:$A,Inputs!G:G,,0) -> 8960 | H43: =_xlfn.XLOOKUP($A43,Inputs!$A:$A,Inputs!H:H,,0) -> 0 | I43: =_xlfn.XLOOKUP($A43,Inputs!$A:$A,Inputs!I:I,,0) -> 0 | J43: =_xlfn.XLOOKUP($A43,Inputs!$A:$A,Inputs!J:J,,0) -> 0 | K43: =_xlfn.XLOOKUP($A43,Inputs!$A:$A,Inputs!K:K,,0) -> 0 | L43: =_xlfn.XLOOKUP($A43,Inputs!$A:$A,Inputs!L:L,,0) -> 0 | M43: =_xlfn.XLOOKUP($A43,Inputs!$A:$A,Inputs!M:M,,0) -> 0
A44: Total Assets | B44: =_xlfn.XLOOKUP($A44,Inputs!$A:$A,Inputs!B:B,,0) -> 32109 | C44: =_xlfn.XLOOKUP($A44,Inputs!$A:$A,Inputs!C:C,,0) -> 38774 | D44: =_xlfn.XLOOKUP($A44,Inputs!$A:$A,Inputs!D:D,,0) -> 33252 | E44: =_xlfn.XLOOKUP($A44,Inputs!$A:$A,Inputs!E:E,,0) -> 31761 | F44: =_xlfn.XLOOKUP($A44,Inputs!$A:$A,Inputs!F:F,,0) -> 23988 | G44: =_xlfn.XLOOKUP($A44,Inputs!$A:$A,Inputs!G:G,,0) -> 15426 | H44: =_xlfn.XLOOKUP($A44,Inputs!$A:$A,Inputs!H:H,,0) -> 0 | I44: =_xlfn.XLOOKUP($A44,Inputs!$A:$A,Inputs!I:I,,0) -> 0 | J44: =_xlfn.XLOOKUP($A44,Inputs!$A:$A,Inputs!J:J,,0) -> 0 | K44: =_xlfn.XLOOKUP($A44,Inputs!$A:$A,Inputs!K:K,,0) -> 0 | L44: =_xlfn.XLOOKUP($A44,Inputs!$A:$A,Inputs!L:L,,0) -> 0 | M44: =_xlfn.XLOOKUP($A44,Inputs!$A:$A,Inputs!M:M,,0) -> 0
A47: Liabilities
A48: Current Liabilities | B48: =_xlfn.XLOOKUP($A48,Inputs!$A:$A,Inputs!B:B,,0) -> 8853 | C48: =_xlfn.XLOOKUP($A48,Inputs!$A:$A,Inputs!C:C,,0) -> 9024 | D48: =_xlfn.XLOOKUP($A48,Inputs!$A:$A,Inputs!D:D,,0) -> 6865 | E48: =_xlfn.XLOOKUP($A48,Inputs!$A:$A,Inputs!E:E,,0) -> 5639 | F48: =_xlfn.XLOOKUP($A48,Inputs!$A:$A,Inputs!F:F,,0) -> 4259 | G48: =_xlfn.XLOOKUP($A48,Inputs!$A:$A,Inputs!G:G,,0) -> 3857 | H48: =_xlfn.XLOOKUP($A48,Inputs!$A:$A,Inputs!H:H,,0) -> 0 | I48: =_xlfn.XLOOKUP($A48,Inputs!$A:$A,Inputs!I:I,,0) -> 0 | J48: =_xlfn.XLOOKUP($A48,Inputs!$A:$A,Inputs!J:J,,0) -> 0 | K48: =_xlfn.XLOOKUP($A48,Inputs!$A:$A,Inputs!K:K,,0) -> 0 | L48: =_xlfn.XLOOKUP($A48,Inputs!$A:$A,Inputs!L:L,,0) -> 0 | M48: =_xlfn.XLOOKUP($A48,Inputs!$A:$A,Inputs!M:M,,0) -> 0
A49: Short-Term Debt | B49: =_xlfn.XLOOKUP($A49,Inputs!$A:$A,Inputs!B:B,,0) -> 0 | C49: =_xlfn.XLOOKUP($A49,Inputs!$A:$A,Inputs!C:C,,0) -> 0 | D49: =_xlfn.XLOOKUP($A49,Inputs!$A:$A,Inputs!D:D,,0) -> 0 | E49: =_xlfn.XLOOKUP($A49,Inputs!$A:$A,Inputs!E:E,,0) -> 0 | F49: =_xlfn.XLOOKUP($A49,Inputs!$A:$A,Inputs!F:F,,0) -> 0 | G49: =_xlfn.XLOOKUP($A49,Inputs!$A:$A,Inputs!G:G,,0) -> 0 | H49: =_xlfn.XLOOKUP($A49,Inputs!$A:$A,Inputs!H:H,,0) -> 0 | I49: =_xlfn.XLOOKUP($A49,Inputs!$A:$A,Inputs!I:I,,0) -> 0 | J49: =_xlfn.XLOOKUP($A49,Inputs!$A:$A,Inputs!J:J,,0) -> 0 | K49: =_xlfn.XLOOKUP($A49,Inputs!$A:$A,Inputs!K:K,,0) -> 0 | L49: =_xlfn.XLOOKUP($A49,Inputs!$A:$A,Inputs!L:L,,0) -> 0 | M49: =_xlfn.XLOOKUP($A49,Inputs!$A:$A,Inputs!M:M,,0) -> 0
A50: Short-Term Leases | B50: =_xlfn.XLOOKUP($A50,Inputs!$A:$A,Inputs!B:B,,0) -> 201 | C50: =_xlfn.XLOOKUP($A50,Inputs!$A:$A,Inputs!C:C,,0) -> 185 | D50: =_xlfn.XLOOKUP($A50,Inputs!$A:$A,Inputs!D:D,,0) -> 175 | E50: =_xlfn.XLOOKUP($A50,Inputs!$A:$A,Inputs!E:E,,0) -> 196 | F50: =_xlfn.XLOOKUP($A50,Inputs!$A:$A,Inputs!F:F,,0) -> 0 | G50: =_xlfn.XLOOKUP($A50,Inputs!$A:$A,Inputs!G:G,,0) -> 0 | H50: =_xlfn.XLOOKUP($A50,Inputs!$A:$A,Inputs!H:H,,0) -> 0 | I50: =_xlfn.XLOOKUP($A50,Inputs!$A:$A,Inputs!I:I,,0) -> 0 | J50: =_xlfn.XLOOKUP($A50,Inputs!$A:$A,Inputs!J:J,,0) -> 0 | K50: =_xlfn.XLOOKUP($A50,Inputs!$A:$A,Inputs!K:K,,0) -> 0 | L50: =_xlfn.XLOOKUP($A50,Inputs!$A:$A,Inputs!L:L,,0) -> 0 | M50: =_xlfn.XLOOKUP($A50,Inputs!$A:$A,Inputs!M:M,,0) -> 0
A51: Other current liabilities | B51: =_xlfn.XLOOKUP($A51,Inputs!$A:$A,Inputs!B:B,,0) -> 7924 | C51: =_xlfn.XLOOKUP($A51,Inputs!$A:$A,Inputs!C:C,,0) -> 7979 | D51: =_xlfn.XLOOKUP($A51,Inputs!$A:$A,Inputs!D:D,,0) -> 6455 | E51: =_xlfn.XLOOKUP($A51,Inputs!$A:$A,Inputs!E:E,,0) -> 5171 | F51: =_xlfn.XLOOKUP($A51,Inputs!$A:$A,Inputs!F:F,,0) -> 4109 | G51: =_xlfn.XLOOKUP($A51,Inputs!$A:$A,Inputs!G:G,,0) -> 3857 | H51: =_xlfn.XLOOKUP($A51,Inputs!$A:$A,Inputs!H:H,,0) -> 0 | I51: =_xlfn.XLOOKUP($A51,Inputs!$A:$A,Inputs!I:I,,0) -> 0 | J51: =_xlfn.XLOOKUP($A51,Inputs!$A:$A,Inputs!J:J,,0) -> 0 | K51: =_xlfn.XLOOKUP($A51,Inputs!$A:$A,Inputs!K:K,,0) -> 0 | L51: =_xlfn.XLOOKUP($A51,Inputs!$A:$A,Inputs!L:L,,0) -> 0 | M51: =_xlfn.XLOOKUP($A51,Inputs!$A:$A,Inputs!M:M,,0) -> 0
A52: Non-current Liabilities | B52: =_xlfn.XLOOKUP($A52,Inputs!$A:$A,Inputs!B:B,,0) -> 14752 | C52: =_xlfn.XLOOKUP($A52,Inputs!$A:$A,Inputs!C:C,,0) -> 14401 | D52: =_xlfn.XLOOKUP($A52,Inputs!$A:$A,Inputs!D:D,,0) -> 12633 | E52: =_xlfn.XLOOKUP($A52,Inputs!$A:$A,Inputs!E:E,,0) -> 10939 | F52: =_xlfn.XLOOKUP($A52,Inputs!$A:$A,Inputs!F:F,,0) -> 12937 | G52: =_xlfn.XLOOKUP($A52,Inputs!$A:$A,Inputs!G:G,,0) -> -3857 | H52: =_xlfn.XLOOKUP($A52,Inputs!$A:$A,Inputs!H:H,,0) -> 0 | I52: =_xlfn.XLOOKUP($A52,Inputs!$A:$A,Inputs!I:I,,0) -> 0 | J52: =_xlfn.XLOOKUP($A52,Inputs!$A:$A,Inputs!J:J,,0) -> 0 | K52: =_xlfn.XLOOKUP($A52,Inputs!$A:$A,Inputs!K:K,,0) -> 0 | L52: =_xlfn.XLOOKUP($A52,Inputs!$A:$A,Inputs!L:L,,0) -> 0 | M52: =_xlfn.XLOOKUP($A52,Inputs!$A:$A,Inputs!M:M,,0) -> 0
A53: Long-Term Debt | B53: =_xlfn.XLOOKUP($A53,Inputs!$A:$A,Inputs!B:B,,0) -> 9265 | C53: =_xlfn.XLOOKUP($A53,Inputs!$A:$A,Inputs!C:C,,0) -> 9276 | D53: =_xlfn.XLOOKUP($A53,Inputs!$A:$A,Inputs!D:D,,0) -> 7560 | E53: =_xlfn.XLOOKUP($A53,Inputs!$A:$A,Inputs!E:E,,0) -> 5707 | F53: =_xlfn.XLOOKUP($A53,Inputs!$A:$A,Inputs!F:F,,0) -> 6869 | G53: =_xlfn.XLOOKUP($A53,Inputs!$A:$A,Inputs!G:G,,0) -> 0 | H53: =_xlfn.XLOOKUP($A53,Inputs!$A:$A,Inputs!H:H,,0) -> 0 | I53: =_xlfn.XLOOKUP($A53,Inputs!$A:$A,Inputs!I:I,,0) -> 0 | J53: =_xlfn.XLOOKUP($A53,Inputs!$A:$A,Inputs!J:J,,0) -> 0 | K53: =_xlfn.XLOOKUP($A53,Inputs!$A:$A,Inputs!K:K,,0) -> 0 | L53: =_xlfn.XLOOKUP($A53,Inputs!$A:$A,Inputs!L:L,,0) -> 0 | M53: =_xlfn.XLOOKUP($A53,Inputs!$A:$A,Inputs!M:M,,0) -> 0
A54: Long-Term Leases | B54: =_xlfn.XLOOKUP($A54,Inputs!$A:$A,Inputs!B:B,,0) -> 1673 | C54: =_xlfn.XLOOKUP($A54,Inputs!$A:$A,Inputs!C:C,,0) -> 1644 | D54: =_xlfn.XLOOKUP($A54,Inputs!$A:$A,Inputs!D:D,,0) -> 1544 | E54: =_xlfn.XLOOKUP($A54,Inputs!$A:$A,Inputs!E:E,,0) -> 1523 | F54: =_xlfn.XLOOKUP($A54,Inputs!$A:$A,Inputs!F:F,,0) -> 0 | G54: =_xlfn.XLOOKUP($A54,Inputs!$A:$A,Inputs!G:G,,0) -> 0 | H54: =_xlfn.XLOOKUP($A54,Inputs!$A:$A,Inputs!H:H,,0) -> 0 | I54: =_xlfn.XLOOKUP($A54,Inputs!$A:$A,Inputs!I:I,,0) -> 0 | J54: =_xlfn.XLOOKUP($A54,Inputs!$A:$A,Inputs!J:J,,0) -> 0 | K54: =_xlfn.XLOOKUP($A54,Inputs!$A:$A,Inputs!K:K,,0) -> 0 | L54: =_xlfn.XLOOKUP($A54,Inputs!$A:$A,Inputs!L:L,,0) -> 0 | M54: =_xlfn.XLOOKUP($A54,Inputs!$A:$A,Inputs!M:M,,0) -> 0
A55: Other non-current liabilities | B55: =_xlfn.XLOOKUP($A55,Inputs!$A:$A,Inputs!B:B,,0) -> 3814 | C55: =_xlfn.XLOOKUP($A55,Inputs!$A:$A,Inputs!C:C,,0) -> 3481 | D55: =_xlfn.XLOOKUP($A55,Inputs!$A:$A,Inputs!D:D,,0) -> 3529 | E55: =_xlfn.XLOOKUP($A55,Inputs!$A:$A,Inputs!E:E,,0) -> 3709 | F55: =_xlfn.XLOOKUP($A55,Inputs!$A:$A,Inputs!F:F,,0) -> 6068 | G55: =_xlfn.XLOOKUP($A55,Inputs!$A:$A,Inputs!G:G,,0) -> -3857 | H55: =_xlfn.XLOOKUP($A55,Inputs!$A:$A,Inputs!H:H,,0) -> 0 | I55: =_xlfn.XLOOKUP($A55,Inputs!$A:$A,Inputs!I:I,,0) -> 0 | J55: =_xlfn.XLOOKUP($A55,Inputs!$A:$A,Inputs!J:J,,0) -> 0 | K55: =_xlfn.XLOOKUP($A55,Inputs!$A:$A,Inputs!K:K,,0) -> 0 | L55: =_xlfn.XLOOKUP($A55,Inputs!$A:$A,Inputs!L:L,,0) -> 0 | M55: =_xlfn.XLOOKUP($A55,Inputs!$A:$A,Inputs!M:M,,0) -> 0
A56: Total Liabilities | B56: =_xlfn.XLOOKUP($A56,Inputs!$A:$A,Inputs!B:B,,0) -> 23605 | C56: =_xlfn.XLOOKUP($A56,Inputs!$A:$A,Inputs!C:C,,0) -> 23425 | D56: =_xlfn.XLOOKUP($A56,Inputs!$A:$A,Inputs!D:D,,0) -> 19498 | E56: =_xlfn.XLOOKUP($A56,Inputs!$A:$A,Inputs!E:E,,0) -> 16578 | F56: =_xlfn.XLOOKUP($A56,Inputs!$A:$A,Inputs!F:F,,0) -> 17196 | G56: =_xlfn.XLOOKUP($A56,Inputs!$A:$A,Inputs!G:G,,0) -> 0 | H56: =_xlfn.XLOOKUP($A56,Inputs!$A:$A,Inputs!H:H,,0) -> 0 | I56: =_xlfn.XLOOKUP($A56,Inputs!$A:$A,Inputs!I:I,,0) -> 0 | J56: =_xlfn.XLOOKUP($A56,Inputs!$A:$A,Inputs!J:J,,0) -> 0 | K56: =_xlfn.XLOOKUP($A56,Inputs!$A:$A,Inputs!K:K,,0) -> 0 | L56: =_xlfn.XLOOKUP($A56,Inputs!$A:$A,Inputs!L:L,,0) -> 0 | M56: =_xlfn.XLOOKUP($A56,Inputs!$A:$A,Inputs!M:M,,0) -> 0
A58: Total Debt | B58: =B49+B53+B50+B54 -> 11139 | C58: =C49+C53+C50+C54 -> 11105 | D58: =D49+D53+D50+D54 -> 9279 | E58: =E49+E53+E50+E54 -> 7426 | F58: =F49+F53+F50+F54 -> 6869 | G58: =G49+G53+G50+G54 -> 0 | H58: =H49+H53+H50+H54 -> 0 | I58: =I49+I53+I50+I54 -> 0 | ... M58: =M49+M53+M50+M54 -> 0
A59: Debt/Assets | B59: =IFERROR(B58/B44,"-") -> 0.34691208 | C59: =IFERROR(C58/C44,"-") -> 0.28640326 | D59: =IFERROR(D58/D44,"-") -> 0.27905088 | E59: =IFERROR(E58/E44,"-") -> 0.23380876 | F59: =IFERROR(F58/F44,"-") -> 0.28635151 | G59: =IFERROR(G58/G44,"-") -> 0 | H59: =IFERROR(H58/H44,"-") -> - | I59: =IFERROR(I58/I44,"-") -> - | ... M59: =IFERROR(M58/M44,"-") -> -
A60: Net Debt | B60: =B58-B39 -> 6931 | C60: =C58-C39 -> 6810 | D60: =D58-D39 -> 3632 | E60: =E58-E39 -> -3447 | F60: =F58-F39 -> 463 | G60: =G58-G39 -> -4535 | H60: =H58-H39 -> 0 | I60: =I58-I39 -> 0 | ... M60: =M58-M39 -> 0
A62: Minority Interest | B62: =_xlfn.XLOOKUP($A62,Inputs!$A:$A,Inputs!B:B,,0) -> 430 | C62: =_xlfn.XLOOKUP($A62,Inputs!$A:$A,Inputs!C:C,,0) -> 204 | D62: =_xlfn.XLOOKUP($A62,Inputs!$A:$A,Inputs!D:D,,0) -> 787 | E62: =_xlfn.XLOOKUP($A62,Inputs!$A:$A,Inputs!E:E,,0) -> 311 | F62: =_xlfn.XLOOKUP($A62,Inputs!$A:$A,Inputs!F:F,,0) -> 0 | G62: =_xlfn.XLOOKUP($A62,Inputs!$A:$A,Inputs!G:G,,0) -> 0 | H62: =_xlfn.XLOOKUP($A62,Inputs!$A:$A,Inputs!H:H,,0) -> 0 | I62: =_xlfn.XLOOKUP($A62,Inputs!$A:$A,Inputs!I:I,,0) -> 0 | J62: =_xlfn.XLOOKUP($A62,Inputs!$A:$A,Inputs!J:J,,0) -> 0 | K62: =_xlfn.XLOOKUP($A62,Inputs!$A:$A,Inputs!K:K,,0) -> 0 | L62: =_xlfn.XLOOKUP($A62,Inputs!$A:$A,Inputs!L:L,,0) -> 0 | M62: =_xlfn.XLOOKUP($A62,Inputs!$A:$A,Inputs!M:M,,0) -> 0
A64: Shareholder's Equity | B64: =_xlfn.XLOOKUP($A64,Inputs!$A:$A,Inputs!B:B,,0) -> 8074 | C64: =_xlfn.XLOOKUP($A64,Inputs!$A:$A,Inputs!C:C,,0) -> 15145 | D64: =_xlfn.XLOOKUP($A64,Inputs!$A:$A,Inputs!D:D,,0) -> 12967 | E64: =_xlfn.XLOOKUP($A64,Inputs!$A:$A,Inputs!E:E,,0) -> 14872 | F64: =_xlfn.XLOOKUP($A64,Inputs!$A:$A,Inputs!F:F,,0) -> 6792 | G64: =_xlfn.XLOOKUP($A64,Inputs!$A:$A,Inputs!G:G,,0) -> 15426 | H64: =_xlfn.XLOOKUP($A64,Inputs!$A:$A,Inputs!H:H,,0) -> 0 | I64: =_xlfn.XLOOKUP($A64,Inputs!$A:$A,Inputs!I:I,,0) -> 0 | J64: =_xlfn.XLOOKUP($A64,Inputs!$A:$A,Inputs!J:J,,0) -> 0 | K64: =_xlfn.XLOOKUP($A64,Inputs!$A:$A,Inputs!K:K,,0) -> 0 | L64: =_xlfn.XLOOKUP($A64,Inputs!$A:$A,Inputs!L:L,,0) -> 0 | M64: =_xlfn.XLOOKUP($A64,Inputs!$A:$A,Inputs!M:M,,0) -> 0
A66: Cash Flow
A67: Operating CF | B67: =_xlfn.XLOOKUP($A67,Inputs!$A:$A,Inputs!B:B,,0) -> 642 | C67: =_xlfn.XLOOKUP($A67,Inputs!$A:$A,Inputs!C:C,,0) -> -445 | D67: =_xlfn.XLOOKUP($A67,Inputs!$A:$A,Inputs!D:D,,0) -> -2745 | E67: =_xlfn.XLOOKUP($A67,Inputs!$A:$A,Inputs!E:E,,0) -> -4321 | F67: =_xlfn.XLOOKUP($A67,Inputs!$A:$A,Inputs!F:F,,0) -> -1541 | G67: =_xlfn.XLOOKUP($A67,Inputs!$A:$A,Inputs!G:G,,0) -> -1418 | H67: =_xlfn.XLOOKUP($A67,Inputs!$A:$A,Inputs!H:H,,0) -> 0 | I67: =_xlfn.XLOOKUP($A67,Inputs!$A:$A,Inputs!I:I,,0) -> 0 | J67: =_xlfn.XLOOKUP($A67,Inputs!$A:$A,Inputs!J:J,,0) -> 0 | K67: =_xlfn.XLOOKUP($A67,Inputs!$A:$A,Inputs!K:K,,0) -> 0 | L67: =_xlfn.XLOOKUP($A67,Inputs!$A:$A,Inputs!L:L,,0) -> 0 | M67: =_xlfn.XLOOKUP($A67,Inputs!$A:$A,Inputs!M:M,,0) -> 0
A68: Investing CF | B68: =_xlfn.XLOOKUP($A68,Inputs!$A:$A,Inputs!B:B,,0) -> -1637 | C68: =_xlfn.XLOOKUP($A68,Inputs!$A:$A,Inputs!C:C,,0) -> -1201 | D68: =_xlfn.XLOOKUP($A68,Inputs!$A:$A,Inputs!D:D,,0) -> -2869 | E68: =_xlfn.XLOOKUP($A68,Inputs!$A:$A,Inputs!E:E,,0) -> -790 | F68: =_xlfn.XLOOKUP($A68,Inputs!$A:$A,Inputs!F:F,,0) -> -695 | G68: =_xlfn.XLOOKUP($A68,Inputs!$A:$A,Inputs!G:G,,0) -> -487 | H68: =_xlfn.XLOOKUP($A68,Inputs!$A:$A,Inputs!H:H,,0) -> 0 | I68: =_xlfn.XLOOKUP($A68,Inputs!$A:$A,Inputs!I:I,,0) -> 0 | J68: =_xlfn.XLOOKUP($A68,Inputs!$A:$A,Inputs!J:J,,0) -> 0 | K68: =_xlfn.XLOOKUP($A68,Inputs!$A:$A,Inputs!K:K,,0) -> 0 | L68: =_xlfn.XLOOKUP($A68,Inputs!$A:$A,Inputs!L:L,,0) -> 0 | M68: =_xlfn.XLOOKUP($A68,Inputs!$A:$A,Inputs!M:M,,0) -> 0
A69: Net Capex | B69: =_xlfn.XLOOKUP($A69,Inputs!$A:$A,Inputs!B:B,,0) -> -252 | C69: =_xlfn.XLOOKUP($A69,Inputs!$A:$A,Inputs!C:C,,0) -> -298 | D69: =_xlfn.XLOOKUP($A69,Inputs!$A:$A,Inputs!D:D,,0) -> -616 | E69: =_xlfn.XLOOKUP($A69,Inputs!$A:$A,Inputs!E:E,,0) -> -588 | F69: =_xlfn.XLOOKUP($A69,Inputs!$A:$A,Inputs!F:F,,0) -> -558 | G69: =_xlfn.XLOOKUP($A69,Inputs!$A:$A,Inputs!G:G,,0) -> 0 | H69: =_xlfn.XLOOKUP($A69,Inputs!$A:$A,Inputs!H:H,,0) -> 0 | I69: =_xlfn.XLOOKUP($A69,Inputs!$A:$A,Inputs!I:I,,0) -> 0 | J69: =_xlfn.XLOOKUP($A69,Inputs!$A:$A,Inputs!J:J,,0) -> 0 | K69: =_xlfn.XLOOKUP($A69,Inputs!$A:$A,Inputs!K:K,,0) -> 0 | L69: =_xlfn.XLOOKUP($A69,Inputs!$A:$A,Inputs!L:L,,0) -> 0 | M69: =_xlfn.XLOOKUP($A69,Inputs!$A:$A,Inputs!M:M,,0) -> 0
A70: Investments & Acquisitions | B70: =_xlfn.XLOOKUP($A70,Inputs!$A:$A,Inputs!B:B,,0) -> -1139 | C70: =_xlfn.XLOOKUP($A70,Inputs!$A:$A,Inputs!C:C,,0) -> -618 | D70: =_xlfn.XLOOKUP($A70,Inputs!$A:$A,Inputs!D:D,,0) -> -2131 | E70: =_xlfn.XLOOKUP($A70,Inputs!$A:$A,Inputs!E:E,,0) -> -253 | F70: =_xlfn.XLOOKUP($A70,Inputs!$A:$A,Inputs!F:F,,0) -> -476 | G70: =_xlfn.XLOOKUP($A70,Inputs!$A:$A,Inputs!G:G,,0) -> 0 | H70: =_xlfn.XLOOKUP($A70,Inputs!$A:$A,Inputs!H:H,,0) -> 0 | I70: =_xlfn.XLOOKUP($A70,Inputs!$A:$A,Inputs!I:I,,0) -> 0 | J70: =_xlfn.XLOOKUP($A70,Inputs!$A:$A,Inputs!J:J,,0) -> 0 | K70: =_xlfn.XLOOKUP($A70,Inputs!$A:$A,Inputs!K:K,,0) -> 0 | L70: =_xlfn.XLOOKUP($A70,Inputs!$A:$A,Inputs!L:L,,0) -> 0 | M70: =_xlfn.XLOOKUP($A70,Inputs!$A:$A,Inputs!M:M,,0) -> 0
A71: Financing CF | B71: =_xlfn.XLOOKUP($A71,Inputs!$A:$A,Inputs!B:B,,0) -> 15 | C71: =_xlfn.XLOOKUP($A71,Inputs!$A:$A,Inputs!C:C,,0) -> 1780 | D71: =_xlfn.XLOOKUP($A71,Inputs!$A:$A,Inputs!D:D,,0) -> 1379 | E71: =_xlfn.XLOOKUP($A71,Inputs!$A:$A,Inputs!E:E,,0) -> 8939 | F71: =_xlfn.XLOOKUP($A71,Inputs!$A:$A,Inputs!F:F,,0) -> 4640 | G71: =_xlfn.XLOOKUP($A71,Inputs!$A:$A,Inputs!G:G,,0) -> 1015 | H71: =_xlfn.XLOOKUP($A71,Inputs!$A:$A,Inputs!H:H,,0) -> 0 | I71: =_xlfn.XLOOKUP($A71,Inputs!$A:$A,Inputs!I:I,,0) -> 0 | J71: =_xlfn.XLOOKUP($A71,Inputs!$A:$A,Inputs!J:J,,0) -> 0 | K71: =_xlfn.XLOOKUP($A71,Inputs!$A:$A,Inputs!K:K,,0) -> 0 | L71: =_xlfn.XLOOKUP($A71,Inputs!$A:$A,Inputs!L:L,,0) -> 0 | M71: =_xlfn.XLOOKUP($A71,Inputs!$A:$A,Inputs!M:M,,0) -> 0
A72: Dividends | B72: =_xlfn.XLOOKUP($A72,Inputs!$A:$A,Inputs!B:B,,0) -> 0 | C72: =_xlfn.XLOOKUP($A72,Inputs!$A:$A,Inputs!C:C,,0) -> 0 | D72: =_xlfn.XLOOKUP($A72,Inputs!$A:$A,Inputs!D:D,,0) -> 0 | E72: =_xlfn.XLOOKUP($A72,Inputs!$A:$A,Inputs!E:E,,0) -> 0 | F72: =_xlfn.XLOOKUP($A72,Inputs!$A:$A,Inputs!F:F,,0) -> 0 | G72: =_xlfn.XLOOKUP($A72,Inputs!$A:$A,Inputs!G:G,,0) -> 0 | H72: =_xlfn.XLOOKUP($A72,Inputs!$A:$A,Inputs!H:H,,0) -> 0 | I72: =_xlfn.XLOOKUP($A72,Inputs!$A:$A,Inputs!I:I,,0) -> 0 | J72: =_xlfn.XLOOKUP($A72,Inputs!$A:$A,Inputs!J:J,,0) -> 0 | K72: =_xlfn.XLOOKUP($A72,Inputs!$A:$A,Inputs!K:K,,0) -> 0 | L72: =_xlfn.XLOOKUP($A72,Inputs!$A:$A,Inputs!L:L,,0) -> 0 | M72: =_xlfn.XLOOKUP($A72,Inputs!$A:$A,Inputs!M:M,,0) -> 0
A73: Share buyback | B73: =_xlfn.XLOOKUP($A73,Inputs!$A:$A,Inputs!B:B,,0) -> 0 | C73: =_xlfn.XLOOKUP($A73,Inputs!$A:$A,Inputs!C:C,,0) -> 0 | D73: =_xlfn.XLOOKUP($A73,Inputs!$A:$A,Inputs!D:D,,0) -> 0 | E73: =_xlfn.XLOOKUP($A73,Inputs!$A:$A,Inputs!E:E,,0) -> 0 | F73: =_xlfn.XLOOKUP($A73,Inputs!$A:$A,Inputs!F:F,,0) -> -10 | G73: =_xlfn.XLOOKUP($A73,Inputs!$A:$A,Inputs!G:G,,0) -> -131 | H73: =_xlfn.XLOOKUP($A73,Inputs!$A:$A,Inputs!H:H,,0) -> 0 | I73: =_xlfn.XLOOKUP($A73,Inputs!$A:$A,Inputs!I:I,,0) -> 0 | J73: =_xlfn.XLOOKUP($A73,Inputs!$A:$A,Inputs!J:J,,0) -> 0 | K73: =_xlfn.XLOOKUP($A73,Inputs!$A:$A,Inputs!K:K,,0) -> 0 | L73: =_xlfn.XLOOKUP($A73,Inputs!$A:$A,Inputs!L:L,,0) -> 0 | M73: =_xlfn.XLOOKUP($A73,Inputs!$A:$A,Inputs!M:M,,0) -> 0
A74: FX | B74: =_xlfn.XLOOKUP($A74,Inputs!$A:$A,Inputs!B:B,,0) -> -148 | C74: =_xlfn.XLOOKUP($A74,Inputs!$A:$A,Inputs!C:C,,0) -> -69 | D74: =_xlfn.XLOOKUP($A74,Inputs!$A:$A,Inputs!D:D,,0) -> -92 | E74: =_xlfn.XLOOKUP($A74,Inputs!$A:$A,Inputs!E:E,,0) -> -4 | F74: =_xlfn.XLOOKUP($A74,Inputs!$A:$A,Inputs!F:F,,0) -> -119 | G74: =_xlfn.XLOOKUP($A74,Inputs!$A:$A,Inputs!G:G,,0) -> 22 | H74: =_xlfn.XLOOKUP($A74,Inputs!$A:$A,Inputs!H:H,,0) -> 0 | I74: =_xlfn.XLOOKUP($A74,Inputs!$A:$A,Inputs!I:I,,0) -> 0 | J74: =_xlfn.XLOOKUP($A74,Inputs!$A:$A,Inputs!J:J,,0) -> 0 | K74: =_xlfn.XLOOKUP($A74,Inputs!$A:$A,Inputs!K:K,,0) -> 0 | L74: =_xlfn.XLOOKUP($A74,Inputs!$A:$A,Inputs!L:L,,0) -> 0 | M74: =_xlfn.XLOOKUP($A74,Inputs!$A:$A,Inputs!M:M,,0) -> 0
A75: Changes in cash | B75: =_xlfn.XLOOKUP($A75,Inputs!$A:$A,Inputs!B:B,,0) -> -1128 | C75: =_xlfn.XLOOKUP($A75,Inputs!$A:$A,Inputs!C:C,,0) -> 65 | D75: =_xlfn.XLOOKUP($A75,Inputs!$A:$A,Inputs!D:D,,0) -> -4327 | E75: =_xlfn.XLOOKUP($A75,Inputs!$A:$A,Inputs!E:E,,0) -> 3824 | F75: =_xlfn.XLOOKUP($A75,Inputs!$A:$A,Inputs!F:F,,0) -> 2285 | G75: =_xlfn.XLOOKUP($A75,Inputs!$A:$A,Inputs!G:G,,0) -> -868 | H75: =_xlfn.XLOOKUP($A75,Inputs!$A:$A,Inputs!H:H,,0) -> 0 | I75: =_xlfn.XLOOKUP($A75,Inputs!$A:$A,Inputs!I:I,,0) -> 0 | J75: =_xlfn.XLOOKUP($A75,Inputs!$A:$A,Inputs!J:J,,0) -> 0 | K75: =_xlfn.XLOOKUP($A75,Inputs!$A:$A,Inputs!K:K,,0) -> 0 | L75: =_xlfn.XLOOKUP($A75,Inputs!$A:$A,Inputs!L:L,,0) -> 0 | M75: =_xlfn.XLOOKUP($A75,Inputs!$A:$A,Inputs!M:M,,0) -> 0
A77: Other Data
A78: Number of employees | B78: =_xlfn.XLOOKUP($A78,Inputs!$A:$A,Inputs!B:B,,0) -> #N/A | C78: =_xlfn.XLOOKUP($A78,Inputs!$A:$A,Inputs!C:C,,0) -> #N/A | D78: =_xlfn.XLOOKUP($A78,Inputs!$A:$A,Inputs!D:D,,0) -> #N/A | E78: =_xlfn.XLOOKUP($A78,Inputs!$A:$A,Inputs!E:E,,0) -> #N/A | F78: =_xlfn.XLOOKUP($A78,Inputs!$A:$A,Inputs!F:F,,0) -> #N/A | G78: =_xlfn.XLOOKUP($A78,Inputs!$A:$A,Inputs!G:G,,0) -> #N/A | H78: =_xlfn.XLOOKUP($A78,Inputs!$A:$A,Inputs!H:H,,0) -> #N/A | I78: =_xlfn.XLOOKUP($A78,Inputs!$A:$A,Inputs!I:I,,0) -> #N/A | J78: =_xlfn.XLOOKUP($A78,Inputs!$A:$A,Inputs!J:J,,0) -> #N/A | K78: =_xlfn.XLOOKUP($A78,Inputs!$A:$A,Inputs!K:K,,0) -> #N/A | L78: =_xlfn.XLOOKUP($A78,Inputs!$A:$A,Inputs!L:L,,0) -> #N/A | M78: =_xlfn.XLOOKUP($A78,Inputs!$A:$A,Inputs!M:M,,0) -> #N/A
A79: Shares Outstanding | B79: =_xlfn.XLOOKUP($A79,Inputs!$A:$A,Inputs!B:B,,0) -> #N/A | C79: =_xlfn.XLOOKUP($A79,Inputs!$A:$A,Inputs!C:C,,0) -> #N/A | D79: =_xlfn.XLOOKUP($A79,Inputs!$A:$A,Inputs!D:D,,0) -> #N/A | E79: =_xlfn.XLOOKUP($A79,Inputs!$A:$A,Inputs!E:E,,0) -> #N/A | F79: =_xlfn.XLOOKUP($A79,Inputs!$A:$A,Inputs!F:F,,0) -> #N/A | G79: =_xlfn.XLOOKUP($A79,Inputs!$A:$A,Inputs!G:G,,0) -> #N/A | H79: =_xlfn.XLOOKUP($A79,Inputs!$A:$A,Inputs!H:H,,0) -> #N/A | I79: =_xlfn.XLOOKUP($A79,Inputs!$A:$A,Inputs!I:I,,0) -> #N/A | J79: =_xlfn.XLOOKUP($A79,Inputs!$A:$A,Inputs!J:J,,0) -> #N/A | K79: =_xlfn.XLOOKUP($A79,Inputs!$A:$A,Inputs!K:K,,0) -> #N/A | L79: =_xlfn.XLOOKUP($A79,Inputs!$A:$A,Inputs!L:L,,0) -> #N/A | M79: =_xlfn.XLOOKUP($A79,Inputs!$A:$A,Inputs!M:M,,0) -> #N/A
A80: Float | B80: =_xlfn.XLOOKUP($A80,Inputs!$A:$A,Inputs!B:B,,0) -> 0.9983 | C80: =_xlfn.XLOOKUP($A80,Inputs!$A:$A,Inputs!C:C,,0) -> Yahoo finance | D80: =_xlfn.XLOOKUP($A80,Inputs!$A:$A,Inputs!D:D,,0) -> 0 | E80: =_xlfn.XLOOKUP($A80,Inputs!$A:$A,Inputs!E:E,,0) -> 0 | F80: =_xlfn.XLOOKUP($A80,Inputs!$A:$A,Inputs!F:F,,0) -> 0 | G80: =_xlfn.XLOOKUP($A80,Inputs!$A:$A,Inputs!G:G,,0) -> 0 | H80: =_xlfn.XLOOKUP($A80,Inputs!$A:$A,Inputs!H:H,,0) -> 0 | I80: =_xlfn.XLOOKUP($A80,Inputs!$A:$A,Inputs!I:I,,0) -> 0 | J80: =_xlfn.XLOOKUP($A80,Inputs!$A:$A,Inputs!J:J,,0) -> 0 | K80: =_xlfn.XLOOKUP($A80,Inputs!$A:$A,Inputs!K:K,,0) -> 0 | L80: =_xlfn.XLOOKUP($A80,Inputs!$A:$A,Inputs!L:L,,0) -> 0 | M80: =_xlfn.XLOOKUP($A80,Inputs!$A:$A,Inputs!M:M,,0) -> 0
A81: Insiders Own | B81: =_xlfn.XLOOKUP($A81,Inputs!$A:$A,Inputs!B:B,,0) -> 0.0017 | C81: =_xlfn.XLOOKUP($A81,Inputs!$A:$A,Inputs!C:C,,0) -> Yahoo finance | D81: =_xlfn.XLOOKUP($A81,Inputs!$A:$A,Inputs!D:D,,0) -> 0 | E81: =_xlfn.XLOOKUP($A81,Inputs!$A:$A,Inputs!E:E,,0) -> 0 | F81: =_xlfn.XLOOKUP($A81,Inputs!$A:$A,Inputs!F:F,,0) -> 0 | G81: =_xlfn.XLOOKUP($A81,Inputs!$A:$A,Inputs!G:G,,0) -> 0 | H81: =_xlfn.XLOOKUP($A81,Inputs!$A:$A,Inputs!H:H,,0) -> 0 | I81: =_xlfn.XLOOKUP($A81,Inputs!$A:$A,Inputs!I:I,,0) -> 0 | J81: =_xlfn.XLOOKUP($A81,Inputs!$A:$A,Inputs!J:J,,0) -> 0 | K81: =_xlfn.XLOOKUP($A81,Inputs!$A:$A,Inputs!K:K,,0) -> 0 | L81: =_xlfn.XLOOKUP($A81,Inputs!$A:$A,Inputs!L:L,,0) -> 0 | M81: =_xlfn.XLOOKUP($A81,Inputs!$A:$A,Inputs!M:M,,0) -> 0
A82: Fitch/ S&P Rating | B82: =_xlfn.XLOOKUP($A82,Inputs!$A:$A,Inputs!B:B,,0) -> - | C82: =_xlfn.XLOOKUP($A82,Inputs!$A:$A,Inputs!C:C,,0) -> 10-K | D82: =_xlfn.XLOOKUP($A82,Inputs!$A:$A,Inputs!D:D,,0) -> 0 | E82: =_xlfn.XLOOKUP($A82,Inputs!$A:$A,Inputs!E:E,,0) -> 0 | F82: =_xlfn.XLOOKUP($A82,Inputs!$A:$A,Inputs!F:F,,0) -> 0 | G82: =_xlfn.XLOOKUP($A82,Inputs!$A:$A,Inputs!G:G,,0) -> 0 | H82: =_xlfn.XLOOKUP($A82,Inputs!$A:$A,Inputs!H:H,,0) -> 0 | I82: =_xlfn.XLOOKUP($A82,Inputs!$A:$A,Inputs!I:I,,0) -> 0 | J82: =_xlfn.XLOOKUP($A82,Inputs!$A:$A,Inputs!J:J,,0) -> 0 | K82: =_xlfn.XLOOKUP($A82,Inputs!$A:$A,Inputs!K:K,,0) -> 0 | L82: =_xlfn.XLOOKUP($A82,Inputs!$A:$A,Inputs!L:L,,0) -> 0 | M82: =_xlfn.XLOOKUP($A82,Inputs!$A:$A,Inputs!M:M,,0) -> 0
A83: Dividend Yield | B83: =_xlfn.XLOOKUP($A83,Inputs!$A:$A,Inputs!B:B,,0) -> #N/A | C83: =_xlfn.XLOOKUP($A83,Inputs!$A:$A,Inputs!C:C,,0) -> #N/A | D83: =_xlfn.XLOOKUP($A83,Inputs!$A:$A,Inputs!D:D,,0) -> #N/A | E83: =_xlfn.XLOOKUP($A83,Inputs!$A:$A,Inputs!E:E,,0) -> #N/A | F83: =_xlfn.XLOOKUP($A83,Inputs!$A:$A,Inputs!F:F,,0) -> #N/A | G83: =_xlfn.XLOOKUP($A83,Inputs!$A:$A,Inputs!G:G,,0) -> #N/A | H83: =_xlfn.XLOOKUP($A83,Inputs!$A:$A,Inputs!H:H,,0) -> #N/A | I83: =_xlfn.XLOOKUP($A83,Inputs!$A:$A,Inputs!I:I,,0) -> #N/A | J83: =_xlfn.XLOOKUP($A83,Inputs!$A:$A,Inputs!J:J,,0) -> #N/A | K83: =_xlfn.XLOOKUP($A83,Inputs!$A:$A,Inputs!K:K,,0) -> #N/A | L83: =_xlfn.XLOOKUP($A83,Inputs!$A:$A,Inputs!L:L,,0) -> #N/A | M83: =_xlfn.XLOOKUP($A83,Inputs!$A:$A,Inputs!M:M,,0) -> #N/A
A84: Daily Volume in Millions of USD | B84: =_xlfn.XLOOKUP($A84,Inputs!$A:$A,Inputs!B:B,,0) -> 0 | C84: =_xlfn.XLOOKUP($A84,Inputs!$A:$A,Inputs!C:C,,0) -> Yahoo Finance | D84: =_xlfn.XLOOKUP($A84,Inputs!$A:$A,Inputs!D:D,,0) -> 0 | E84: =_xlfn.XLOOKUP($A84,Inputs!$A:$A,Inputs!E:E,,0) -> 0 | F84: =_xlfn.XLOOKUP($A84,Inputs!$A:$A,Inputs!F:F,,0) -> 0 | G84: =_xlfn.XLOOKUP($A84,Inputs!$A:$A,Inputs!G:G,,0) -> 0 | H84: =_xlfn.XLOOKUP($A84,Inputs!$A:$A,Inputs!H:H,,0) -> 0 | I84: =_xlfn.XLOOKUP($A84,Inputs!$A:$A,Inputs!I:I,,0) -> 0 | J84: =_xlfn.XLOOKUP($A84,Inputs!$A:$A,Inputs!J:J,,0) -> 0 | K84: =_xlfn.XLOOKUP($A84,Inputs!$A:$A,Inputs!K:K,,0) -> 0 | L84: =_xlfn.XLOOKUP($A84,Inputs!$A:$A,Inputs!L:L,,0) -> 0 | M84: =_xlfn.XLOOKUP($A84,Inputs!$A:$A,Inputs!M:M,,0) -> 0
B86: 2020 | C86: 2021 | D86: 2022
A87: Short % of Float | B87: 0 | C87: 0 | D87: 0
A88: EPS | B88: 0 | C88: 0 | D88: 0
A90: Corporate Bonds 3, 5 Y 10 | B90: Average Price | C90: Moody's | D90: YTM | E90: DIVISA
B91: =VLOOKUP($A91,Inputs!$A$5:$M$98,MATCH(B$4,Inputs!$B$5:$M$5,0)+1,FALSE) -> #N/A | C91: =VLOOKUP($A91,Inputs!$A$5:$M$98,MATCH(C$4,Inputs!$B$5:$M$5,0)+1,FALSE) -> #N/A | D91: =VLOOKUP($A91,Inputs!$A$5:$M$98,MATCH(D$4,Inputs!$B$5:$M$5,0)+1,FALSE) -> #N/A | E91: =VLOOKUP($A91,Inputs!$A$5:$M$98,MATCH(E$4,Inputs!$B$5:$M$5,0)+1,FALSE) -> #N/A

Sheet Fin. Data (Common Size)
A1: =Inputs!H3 -> #VALUE!
A2: =Inputs!G2 -> Figures in Millions of USD
A3: Results
B4: =OP!J17 -> 2022 | C4: =B4-1 -> 2021 | D4: =C4-1 -> 2020 | E4: =D4-1 -> 2019 | F4: =E4-1 -> 2018 | G4: =F4-1 -> 2017 | H4: =G4-1 -> 2016 | I4: =H4-1 -> 2015 | J4: =I4-1 -> 2014 | ... M4: =L4-1 -> 2011
A5: Net Sales | B5: =_xlfn.XLOOKUP($A5,Inputs!$A:$A,Inputs!B:B,,0) -> 31877 | C5: =_xlfn.XLOOKUP($A5,Inputs!$A:$A,Inputs!C:C,,0) -> 17455 | D5: =_xlfn.XLOOKUP($A5,Inputs!$A:$A,Inputs!D:D,,0) -> 11139 | E5: =_xlfn.XLOOKUP($A5,Inputs!$A:$A,Inputs!E:E,,0) -> 13000 | F5: =_xlfn.XLOOKUP($A5,Inputs!$A:$A,Inputs!F:F,,0) -> 10433 | G5: =_xlfn.XLOOKUP($A5,Inputs!$A:$A,Inputs!G:G,,0) -> 7932 | H5: =_xlfn.XLOOKUP($A5,Inputs!$A:$A,Inputs!H:H,,0) -> 0 | I5: =_xlfn.XLOOKUP($A5,Inputs!$A:$A,Inputs!I:I,,0) -> 0 | J5: =_xlfn.XLOOKUP($A5,Inputs!$A:$A,Inputs!J:J,,0) -> 0 | K5: =_xlfn.XLOOKUP($A5,Inputs!$A:$A,Inputs!K:K,,0) -> 0 | L5: =_xlfn.XLOOKUP($A5,Inputs!$A:$A,Inputs!L:L,,0) -> 0 | M5: =_xlfn.XLOOKUP($A5,Inputs!$A:$A,Inputs!M:M,,0) -> 0
A6: Growth vs. Previous year | B6: =IFERROR(B5/C5-1,"-") -> 0.8262389 | C6: =IFERROR(C5/D5-1,"-") -> 0.56701679 | D6: =IFERROR(D5/E5-1,"-") -> -0.14315385 | E6: =IFERROR(E5/F5-1,"-") -> 0.2460462 | F6: =IFERROR(F5/G5-1,"-") -> 0.31530509 | G6: =IFERROR(G5/H5-1,"-") -> - | H6: =IFERROR(H5/I5-1,"-") -> - | I6: =IFERROR(I5/J5-1,"-") -> - | ... M6: =IFERROR(M5/N5-1,"-") -> -
A7: Gross Profit | B7: =_xlfn.XLOOKUP($A7,Inputs!$A:$A,Inputs!B:B,,0) -> 12218 | C7: =_xlfn.XLOOKUP($A7,Inputs!$A:$A,Inputs!C:C,,0) -> 8104 | D7: =_xlfn.XLOOKUP($A7,Inputs!$A:$A,Inputs!D:D,,0) -> 5985 | E7: =_xlfn.XLOOKUP($A7,Inputs!$A:$A,Inputs!E:E,,0) -> 6939 | F7: =_xlfn.XLOOKUP($A7,Inputs!$A:$A,Inputs!F:F,,0) -> 5647 | G7: =_xlfn.XLOOKUP($A7,Inputs!$A:$A,Inputs!G:G,,0) -> 3772 | H7: =_xlfn.XLOOKUP($A7,Inputs!$A:$A,Inputs!H:H,,0) -> 0 | I7: =_xlfn.XLOOKUP($A7,Inputs!$A:$A,Inputs!I:I,,0) -> 0 | J7: =_xlfn.XLOOKUP($A7,Inputs!$A:$A,Inputs!J:J,,0) -> 0 | K7: =_xlfn.XLOOKUP($A7,Inputs!$A:$A,Inputs!K:K,,0) -> 0 | L7: =_xlfn.XLOOKUP($A7,Inputs!$A:$A,Inputs!L:L,,0) -> 0 | M7: =_xlfn.XLOOKUP($A7,Inputs!$A:$A,Inputs!M:M,,0) -> 0
A8: % over sales | B8: =IFERROR(B7/B$5,"-") -> 0.38328575 | C8: =IFERROR(C7/C$5,"-") -> 0.46427958 | D8: =IFERROR(D7/D$5,"-") -> 0.53730137 | E8: =IFERROR(E7/E$5,"-") -> 0.53376923 | F8: =IFERROR(F7/F$5,"-") -> 0.5412633 | G8: =IFERROR(G7/G$5,"-") -> 0.47554211 | H8: =IFERROR(H7/H$5,"-") -> - | I8: =IFERROR(I7/I$5,"-") -> - | ... M8: =IFERROR(M7/M$5,"-") -> -
A9: Operating expenses | B9: =B5-B11 -> 33709 | C9: =C5-C11 -> 21289 | D9: =D5-D11 -> 16002 | E9: =E5-E11 -> 21596 | F9: =F5-F11 -> 13466 | G9: =G5-G11 -> 12012 | H9: =H5-H11 -> 0 | I9: =I5-I11 -> 0 | ... M9: =M5-M11 -> 0
A10: % over sales | B10: =IFERROR(B9/B$5,"-") -> 1.0574709 | C10: =IFERROR(C9/C$5,"-") -> 1.2196505 | D10: =IFERROR(D9/D$5,"-") -> 1.4365742 | E10: =IFERROR(E9/E$5,"-") -> 1.6612308 | F10: =IFERROR(F9/F$5,"-") -> 1.2907122 | G10: =IFERROR(G9/G$5,"-") -> 1.5143722 | H10: =IFERROR(H9/H$5,"-") -> - | I10: =IFERROR(I9/I$5,"-") -> - | ... M10: =IFERROR(M9/M$5,"-") -> -
A11: Operating Income | B11: =_xlfn.XLOOKUP($A11,Inputs!$A:$A,Inputs!B:B,,0) -> -1832 | C11: =_xlfn.XLOOKUP($A11,Inputs!$A:$A,Inputs!C:C,,0) -> -3834 | D11: =_xlfn.XLOOKUP($A11,Inputs!$A:$A,Inputs!D:D,,0) -> -4863 | E11: =_xlfn.XLOOKUP($A11,Inputs!$A:$A,Inputs!E:E,,0) -> -8596 | F11: =_xlfn.XLOOKUP($A11,Inputs!$A:$A,Inputs!F:F,,0) -> -3033 | G11: =_xlfn.XLOOKUP($A11,Inputs!$A:$A,Inputs!G:G,,0) -> -4080 | H11: =_xlfn.XLOOKUP($A11,Inputs!$A:$A,Inputs!H:H,,0) -> 0 | I11: =_xlfn.XLOOKUP($A11,Inputs!$A:$A,Inputs!I:I,,0) -> 0 | J11: =_xlfn.XLOOKUP($A11,Inputs!$A:$A,Inputs!J:J,,0) -> 0 | K11: =_xlfn.XLOOKUP($A11,Inputs!$A:$A,Inputs!K:K,,0) -> 0 | L11: =_xlfn.XLOOKUP($A11,Inputs!$A:$A,Inputs!L:L,,0) -> 0 | M11: =_xlfn.XLOOKUP($A11,Inputs!$A:$A,Inputs!M:M,,0) -> 0
A12: % over sales | B12: =IFERROR(B11/B$5,"-") -> -0.057470904 | C12: =IFERROR(C11/C$5,"-") -> -0.21965053 | D12: =IFERROR(D11/D$5,"-") -> -0.4365742 | E12: =IFERROR(E11/E$5,"-") -> -0.66123077 | F12: =IFERROR(F11/F$5,"-") -> -0.29071216 | G12: =IFERROR(G11/G$5,"-") -> -0.51437216 | H12: =IFERROR(H11/H$5,"-") -> - | I12: =IFERROR(I11/I$5,"-") -> - | ... M12: =IFERROR(M11/M$5,"-") -> -
A13: Growth vs. Previous year | B13: =IFERROR(B12/C12-1,"-") -> -0.73835299 | C13: =IFERROR(C12/D12-1,"-") -> -0.49687698 | D13: =IFERROR(D12/E12-1,"-") -> -0.33975517 | E13: =IFERROR(E12/F12-1,"-") -> 1.2745205 | F13: =IFERROR(F12/G12-1,"-") -> -0.43482135 | G13: =IFERROR(G12/H12-1,"-") -> - | H13: =IFERROR(H12/I12-1,"-") -> - | I13: =IFERROR(I12/J12-1,"-") -> - | ... M13: =IFERROR(M12/N12-1,"-") -> -
A14: Net Financial Cost | B14: =_xlfn.XLOOKUP($A14,Inputs!$A:$A,Inputs!B:B,,0) -> -426 | C14: =_xlfn.XLOOKUP($A14,Inputs!$A:$A,Inputs!C:C,,0) -> -446 | D14: =_xlfn.XLOOKUP($A14,Inputs!$A:$A,Inputs!D:D,,0) -> -403 | E14: =_xlfn.XLOOKUP($A14,Inputs!$A:$A,Inputs!E:E,,0) -> -325 | F14: =_xlfn.XLOOKUP($A14,Inputs!$A:$A,Inputs!F:F,,0) -> -544 | G14: =_xlfn.XLOOKUP($A14,Inputs!$A:$A,Inputs!G:G,,0) -> -408 | H14: =_xlfn.XLOOKUP($A14,Inputs!$A:$A,Inputs!H:H,,0) -> 0 | I14: =_xlfn.XLOOKUP($A14,Inputs!$A:$A,Inputs!I:I,,0) -> 0 | J14: =_xlfn.XLOOKUP($A14,Inputs!$A:$A,Inputs!J:J,,0) -> 0 | K14: =_xlfn.XLOOKUP($A14,Inputs!$A:$A,Inputs!K:K,,0) -> 0 | L14: =_xlfn.XLOOKUP($A14,Inputs!$A:$A,Inputs!L:L,,0) -> 0 | M14: =_xlfn.XLOOKUP($A14,Inputs!$A:$A,Inputs!M:M,,0) -> 0
A15: Other Expenses (Revenues) | B15: =_xlfn.XLOOKUP($A15,Inputs!$A:$A,Inputs!B:B,,0) -> -7029 | C15: =_xlfn.XLOOKUP($A15,Inputs!$A:$A,Inputs!C:C,,0) -> 3292 | D15: =_xlfn.XLOOKUP($A15,Inputs!$A:$A,Inputs!D:D,,0) -> -1625 | E15: =_xlfn.XLOOKUP($A15,Inputs!$A:$A,Inputs!E:E,,0) -> 722 | F15: =_xlfn.XLOOKUP($A15,Inputs!$A:$A,Inputs!F:F,,0) -> 4993 | G15: =_xlfn.XLOOKUP($A15,Inputs!$A:$A,Inputs!G:G,,0) -> -16 | H15: =_xlfn.XLOOKUP($A15,Inputs!$A:$A,Inputs!H:H,,0) -> 0 | I15: =_xlfn.XLOOKUP($A15,Inputs!$A:$A,Inputs!I:I,,0) -> 0 | J15: =_xlfn.XLOOKUP($A15,Inputs!$A:$A,Inputs!J:J,,0) -> 0 | K15: =_xlfn.XLOOKUP($A15,Inputs!$A:$A,Inputs!K:K,,0) -> 0 | L15: =_xlfn.XLOOKUP($A15,Inputs!$A:$A,Inputs!L:L,,0) -> 0 | M15: =_xlfn.XLOOKUP($A15,Inputs!$A:$A,Inputs!M:M,,0) -> 0
A16: EBIT | B16: =B11-B15 -> 5197 | C16: =C11-C15 -> -7126 | D16: =D11-D15 -> -3238 | E16: =E11-E15 -> -9318 | F16: =F11-F15 -> -8026 | G16: =G11-G15 -> -4064 | H16: =H11-H15 -> 0 | I16: =I11-I15 -> 0 | ... M16: =M11-M15 -> 0
A17: Depreciation and Amortization | B17: ='Fin. Data'!B17 -> 947 | C17: ='Fin. Data'!C17 -> 902 | D17: ='Fin. Data'!D17 -> 575 | E17: ='Fin. Data'!E17 -> 472 | F17: ='Fin. Data'!F17 -> 426 | G17: ='Fin. Data'!G17 -> 510 | H17: ='Fin. Data'!H17 -> 0 | I17: ='Fin. Data'!I17 -> 0 | ... M17: ='Fin. Data'!M17 -> 0
A18: Changes Net Working Capital | B18: =_xlfn.XLOOKUP($A18,Inputs!$A:$A,Inputs!B:B,,0) -> 601 | C18: =_xlfn.XLOOKUP($A18,Inputs!$A:$A,Inputs!C:C,,0) -> -3222 | D18: =_xlfn.XLOOKUP($A18,Inputs!$A:$A,Inputs!D:D,,0) -> -5269 | E18: =_xlfn.XLOOKUP($A18,Inputs!$A:$A,Inputs!E:E,,0) -> 3887 | F18: =_xlfn.XLOOKUP($A18,Inputs!$A:$A,Inputs!F:F,,0) -> 1419 | G18: =_xlfn.XLOOKUP($A18,Inputs!$A:$A,Inputs!G:G,,0) -> 0 | H18: =_xlfn.XLOOKUP($A18,Inputs!$A:$A,Inputs!H:H,,0) -> 0 | I18: =_xlfn.XLOOKUP($A18,Inputs!$A:$A,Inputs!I:I,,0) -> 0 | J18: =_xlfn.XLOOKUP($A18,Inputs!$A:$A,Inputs!J:J,,0) -> 0 | K18: =_xlfn.XLOOKUP($A18,Inputs!$A:$A,Inputs!K:K,,0) -> 0 | L18: =_xlfn.XLOOKUP($A18,Inputs!$A:$A,Inputs!L:L,,0) -> 0 | M18: =_xlfn.XLOOKUP($A18,Inputs!$A:$A,Inputs!M:M,,0) -> 0
A19: EBITDA | B19: =B11-B15+B17 -> 6144 | C19: =C11-C15+C17 -> -6224 | D19: =D11-D15+D17 -> -2663 | E19: =E11-E15+E17 -> -8846 | F19: =F11-F15+F17 -> -7600 | G19: =G11-G15+G17 -> -3554 | H19: =H11-H15+H17 -> 0 | I19: =I11-I15+I17 -> 0 | ... M19: =M11-M15+M17 -> 0
A20: % over sales | B20: =IFERROR(B19/B$5,"-") -> 0.19274085 | C20: =IFERROR(C19/C$5,"-") -> -0.35657405 | D20: =IFERROR(D19/D$5,"-") -> -0.23906993 | E20: =IFERROR(E19/E$5,"-") -> -0.68046154 | F20: =IFERROR(F19/F$5,"-") -> -0.72845778 | G20: =IFERROR(G19/G$5,"-") -> -0.4480585 | H20: =IFERROR(H19/H$5,"-") -> - | I20: =IFERROR(I19/I$5,"-") -> - | ... M20: =IFERROR(M19/M$5,"-") -> -
A21: Taxes | B21: =_xlfn.XLOOKUP($A21,Inputs!$A:$A,Inputs!B:B,,0) -> -181 | C21: =_xlfn.XLOOKUP($A21,Inputs!$A:$A,Inputs!C:C,,0) -> -492 | D21: =_xlfn.XLOOKUP($A21,Inputs!$A:$A,Inputs!D:D,,0) -> -192 | E21: =_xlfn.XLOOKUP($A21,Inputs!$A:$A,Inputs!E:E,,0) -> 45 | F21: =_xlfn.XLOOKUP($A21,Inputs!$A:$A,Inputs!F:F,,0) -> 283 | G21: =_xlfn.XLOOKUP($A21,Inputs!$A:$A,Inputs!G:G,,0) -> -542 | H21: =_xlfn.XLOOKUP($A21,Inputs!$A:$A,Inputs!H:H,,0) -> 0 | I21: =_xlfn.XLOOKUP($A21,Inputs!$A:$A,Inputs!I:I,,0) -> 0 | J21: =_xlfn.XLOOKUP($A21,Inputs!$A:$A,Inputs!J:J,,0) -> 0 | K21: =_xlfn.XLOOKUP($A21,Inputs!$A:$A,Inputs!K:K,,0) -> 0 | L21: =_xlfn.XLOOKUP($A21,Inputs!$A:$A,Inputs!L:L,,0) -> 0 | M21: =_xlfn.XLOOKUP($A21,Inputs!$A:$A,Inputs!M:M,,0) -> 0
A22: % Tax | B22: =IFERROR(B21/B$5,"-") -> -0.0056780751 | C22: =IFERROR(C21/C$5,"-") -> -0.028186766 | D22: =IFERROR(D21/D$5,"-") -> -0.017236736 | E22: =IFERROR(E21/E$5,"-") -> 0.0034615385 | F22: =IFERROR(F21/F$5,"-") -> 0.027125467 | G22: =IFERROR(G21/G$5,"-") -> -0.068330812 | H22: =IFERROR(H21/H$5,"-") -> - | I22: =IFERROR(I21/I$5,"-") -> - | ... M22: =IFERROR(M21/M$5,"-") -> -
A23: Net income | B23: =_xlfn.XLOOKUP($A23,Inputs!$A:$A,Inputs!B:B,,0) -> -9141 | C23: =_xlfn.XLOOKUP($A23,Inputs!$A:$A,Inputs!C:C,,0) -> -496 | D23: =_xlfn.XLOOKUP($A23,Inputs!$A:$A,Inputs!D:D,,0) -> -6768 | E23: =_xlfn.XLOOKUP($A23,Inputs!$A:$A,Inputs!E:E,,0) -> -8512 | F23: =_xlfn.XLOOKUP($A23,Inputs!$A:$A,Inputs!F:F,,0) -> 987 | G23: =_xlfn.XLOOKUP($A23,Inputs!$A:$A,Inputs!G:G,,0) -> -4033 | H23: =_xlfn.XLOOKUP($A23,Inputs!$A:$A,Inputs!H:H,,0) -> 0 | I23: =_xlfn.XLOOKUP($A23,Inputs!$A:$A,Inputs!I:I,,0) -> 0 | J23: =_xlfn.XLOOKUP($A23,Inputs!$A:$A,Inputs!J:J,,0) -> 0 | K23: =_xlfn.XLOOKUP($A23,Inputs!$A:$A,Inputs!K:K,,0) -> 0 | L23: =_xlfn.XLOOKUP($A23,Inputs!$A:$A,Inputs!L:L,,0) -> 0 | M23: =_xlfn.XLOOKUP($A23,Inputs!$A:$A,Inputs!M:M,,0) -> 0
A24: % over sales | B24: =IFERROR(B23/B$5,"-") -> -0.28675848 | C24: =IFERROR(C23/C$5,"-") -> -0.028415927 | D24: =IFERROR(D23/D$5,"-") -> -0.60759494 | E24: =IFERROR(E23/E$5,"-") -> -0.65476923 | F24: =IFERROR(F23/F$5,"-") -> 0.094603661 | G24: =IFERROR(G23/G$5,"-") -> -0.5084468 | H24: =IFERROR(H23/H$5,"-") -> - | I24: =IFERROR(I23/I$5,"-") -> - | ... M24: =IFERROR(M23/M$5,"-") -> -
A25: Growth vs. Previous year | B25: =IFERROR(B24/C24-1,"-") -> 9.0914702 | C25: =IFERROR(C24/D24-1,"-") -> -0.95323212 | D25: =IFERROR(D24/E24-1,"-") -> -0.072047207 | E25: =IFERROR(E24/F24-1,"-") -> -7.9211828 | F25: =IFERROR(F24/G24-1,"-") -> -1.186064 | G25: =IFERROR(G24/H24-1,"-") -> - | H25: =IFERROR(H24/I24-1,"-") -> - | I25: =IFERROR(I24/J24-1,"-") -> - | ... M25: =IFERROR(M24/N24-1,"-") -> -
A26: Cash Generated | B26: =B39-C39 -> -87 | C26: =C39-D39 -> -1352 | D26: =D39-E39 -> -5226 | E26: =E39-F39 -> 4467 | F26: =F39-G39 -> 1871 | G26: =G39-H39 -> 4535 | H26: =H39-I39 -> 0 | I26: =I39-J39 -> 0 | ... M26: =M39-N39 -> 0
A27: Dividends | B27: =_xlfn.XLOOKUP($A27,Inputs!$A:$A,Inputs!B:B,,0) -> 0 | C27: =_xlfn.XLOOKUP($A27,Inputs!$A:$A,Inputs!C:C,,0) -> 0 | D27: =_xlfn.XLOOKUP($A27,Inputs!$A:$A,Inputs!D:D,,0) -> 0 | E27: =_xlfn.XLOOKUP($A27,Inputs!$A:$A,Inputs!E:E,,0) -> 0 | F27: =_xlfn.XLOOKUP($A27,Inputs!$A:$A,Inputs!F:F,,0) -> 0 | G27: =_xlfn.XLOOKUP($A27,Inputs!$A:$A,Inputs!G:G,,0) -> 0 | H27: =_xlfn.XLOOKUP($A27,Inputs!$A:$A,Inputs!H:H,,0) -> 0 | I27: =_xlfn.XLOOKUP($A27,Inputs!$A:$A,Inputs!I:I,,0) -> 0 | J27: =_xlfn.XLOOKUP($A27,Inputs!$A:$A,Inputs!J:J,,0) -> 0 | K27: =_xlfn.XLOOKUP($A27,Inputs!$A:$A,Inputs!K:K,,0) -> 0 | L27: =_xlfn.XLOOKUP($A27,Inputs!$A:$A,Inputs!L:L,,0) -> 0 | M27: =_xlfn.XLOOKUP($A27,Inputs!$A:$A,Inputs!M:M,,0) -> 0
A28: Share buyback | B28: =_xlfn.XLOOKUP($A28,Inputs!$A:$A,Inputs!B:B,,0) -> 0 | C28: =_xlfn.XLOOKUP($A28,Inputs!$A:$A,Inputs!C:C,,0) -> 0 | D28: =_xlfn.XLOOKUP($A28,Inputs!$A:$A,Inputs!D:D,,0) -> 0 | E28: =_xlfn.XLOOKUP($A28,Inputs!$A:$A,Inputs!E:E,,0) -> 0 | F28: =_xlfn.XLOOKUP($A28,Inputs!$A:$A,Inputs!F:F,,0) -> -10 | G28: =_xlfn.XLOOKUP($A28,Inputs!$A:$A,Inputs!G:G,,0) -> -131 | H28: =_xlfn.XLOOKUP($A28,Inputs!$A:$A,Inputs!H:H,,0) -> 0 | I28: =_xlfn.XLOOKUP($A28,Inputs!$A:$A,Inputs!I:I,,0) -> 0 | J28: =_xlfn.XLOOKUP($A28,Inputs!$A:$A,Inputs!J:J,,0) -> 0 | K28: =_xlfn.XLOOKUP($A28,Inputs!$A:$A,Inputs!K:K,,0) -> 0 | L28: =_xlfn.XLOOKUP($A28,Inputs!$A:$A,Inputs!L:L,,0) -> 0 | M28: =_xlfn.XLOOKUP($A28,Inputs!$A:$A,Inputs!M:M,,0) -> 0
A29: FNP | B29: =SUM(B26:B28) -> -87 | C29: =SUM(C26:C28) -> -1352 | D29: =SUM(D26:D28) -> -5226 | E29: =SUM(E26:E28) -> 4467 | F29: =SUM(F26:F28) -> 1861 | G29: =SUM(G26:G28) -> 4404 | H29: =SUM(H26:H28) -> 0 | I29: =SUM(I26:I28) -> 0 | ... M29: =SUM(M26:M28) -> 0
A30: FNP'' | B30: =+B29-(B58-C29) -> -10704 | C30: =+C29-(C58-D29) -> -15854 | D30: =+D29-(D58-E29) -> -8319 | E30: =+E29-(E58-F29) -> 621 | F30: =+F29-(F58-G29) -> -604 | G30: =+G29-(G58-H29) -> 4404 | H30: =+H29-(H58-I29) -> 0 | I30: =+I29-(I58-J29) -> 0 | ... M30: =+M29-(M58-N29) -> 0
A31: FNP' | B31: =+B30+B33 -> -11843 | C31: =+C30+C33 -> -16472 | D31: =+D30+D33 -> -10450 | E31: =+E30+E33 -> 368 | F31: =+F30+F33 -> -1080 | G31: =+G30+G33 -> 4404 | H31: =+H30+H33 -> 0 | I31: =+I30+I33 -> 0 | ... M31: =+M30+M33 -> 0
A32: Net Capex | B32: =_xlfn.XLOOKUP($A32,Inputs!$A:$A,Inputs!B:B,,0) -> -252 | C32: =_xlfn.XLOOKUP($A32,Inputs!$A:$A,Inputs!C:C,,0) -> -298 | D32: =_xlfn.XLOOKUP($A32,Inputs!$A:$A,Inputs!D:D,,0) -> -616 | E32: =_xlfn.XLOOKUP($A32,Inputs!$A:$A,Inputs!E:E,,0) -> -588 | F32: =_xlfn.XLOOKUP($A32,Inputs!$A:$A,Inputs!F:F,,0) -> -558 | G32: =_xlfn.XLOOKUP($A32,Inputs!$A:$A,Inputs!G:G,,0) -> 0 | H32: =_xlfn.XLOOKUP($A32,Inputs!$A:$A,Inputs!H:H,,0) -> 0 | I32: =_xlfn.XLOOKUP($A32,Inputs!$A:$A,Inputs!I:I,,0) -> 0 | J32: =_xlfn.XLOOKUP($A32,Inputs!$A:$A,Inputs!J:J,,0) -> 0 | K32: =_xlfn.XLOOKUP($A32,Inputs!$A:$A,Inputs!K:K,,0) -> 0 | L32: =_xlfn.XLOOKUP($A32,Inputs!$A:$A,Inputs!L:L,,0) -> 0 | M32: =_xlfn.XLOOKUP($A32,Inputs!$A:$A,Inputs!M:M,,0) -> 0
A33: Investments & Acquisitions | B33: =_xlfn.XLOOKUP($A33,Inputs!$A:$A,Inputs!B:B,,0) -> -1139 | C33: =_xlfn.XLOOKUP($A33,Inputs!$A:$A,Inputs!C:C,,0) -> -618 | D33: =_xlfn.XLOOKUP($A33,Inputs!$A:$A,Inputs!D:D,,0) -> -2131 | E33: =_xlfn.XLOOKUP($A33,Inputs!$A:$A,Inputs!E:E,,0) -> -253 | F33: =_xlfn.XLOOKUP($A33,Inputs!$A:$A,Inputs!F:F,,0) -> -476 | G33: =_xlfn.XLOOKUP($A33,Inputs!$A:$A,Inputs!G:G,,0) -> 0 | H33: =_xlfn.XLOOKUP($A33,Inputs!$A:$A,Inputs!H:H,,0) -> 0 | I33: =_xlfn.XLOOKUP($A33,Inputs!$A:$A,Inputs!I:I,,0) -> 0 | J33: =_xlfn.XLOOKUP($A33,Inputs!$A:$A,Inputs!J:J,,0) -> 0 | K33: =_xlfn.XLOOKUP($A33,Inputs!$A:$A,Inputs!K:K,,0) -> 0 | L33: =_xlfn.XLOOKUP($A33,Inputs!$A:$A,Inputs!L:L,,0) -> 0 | M33: =_xlfn.XLOOKUP($A33,Inputs!$A:$A,Inputs!M:M,,0) -> 0
A34: Capex + Investments | B34: =+B32+B33 -> -1391 | C34: =+C32+C33 -> -916 | D34: =+D32+D33 -> -2747 | E34: =+E32+E33 -> -841 | F34: =+F32+F33 -> -1034 | G34: =+G32+G33 -> 0 | H34: =+H32+H33 -> 0 | I34: =+I32+I33 -> 0 | ... M34: =+M32+M33 -> 0
A35: Dividends + Share Buyback | B35: =+B27+B28 -> 0 | C35: =+C27+C28 -> 0 | D35: =+D27+D28 -> 0 | E35: =+E27+E28 -> 0 | F35: =+F27+F28 -> -10 | G35: =+G27+G28 -> -131 | H35: =+H27+H28 -> 0 | I35: =+I27+I28 -> 0 | ... M35: =+M27+M28 -> 0
A36: Payout Ratio | B36: =IFERROR(B35/B23,"-") -> 0 | C36: =IFERROR(C35/C23,"-") -> 0 | D36: =IFERROR(D35/D23,"-") -> 0 | E36: =IFERROR(E35/E23,"-") -> 0 | F36: =IFERROR(F35/F23,"-") -> -0.010131712 | G36: =IFERROR(G35/G23,"-") -> 0.032482023 | H36: =IFERROR(H35/H23,"-") -> - | I36: =IFERROR(I35/I23,"-") -> - | ... M36: =IFERROR(M35/M23,"-") -> -
A38: Assets
A39: Cash & Eq. | B39: =_xlfn.XLOOKUP($A39,Inputs!$A:$A,Inputs!B:B,,0) -> 4208 | C39: =_xlfn.XLOOKUP($A39,Inputs!$A:$A,Inputs!C:C,,0) -> 4295 | D39: =_xlfn.XLOOKUP($A39,Inputs!$A:$A,Inputs!D:D,,0) -> 5647 | E39: =_xlfn.XLOOKUP($A39,Inputs!$A:$A,Inputs!E:E,,0) -> 10873 | F39: =_xlfn.XLOOKUP($A39,Inputs!$A:$A,Inputs!F:F,,0) -> 6406 | G39: =_xlfn.XLOOKUP($A39,Inputs!$A:$A,Inputs!G:G,,0) -> 4535 | H39: =_xlfn.XLOOKUP($A39,Inputs!$A:$A,Inputs!H:H,,0) -> 0 | I39: =_xlfn.XLOOKUP($A39,Inputs!$A:$A,Inputs!I:I,,0) -> 0 | J39: =_xlfn.XLOOKUP($A39,Inputs!$A:$A,Inputs!J:J,,0) -> 0 | K39: =_xlfn.XLOOKUP($A39,Inputs!$A:$A,Inputs!K:K,,0) -> 0 | L39: =_xlfn.XLOOKUP($A39,Inputs!$A:$A,Inputs!L:L,,0) -> 0 | M39: =_xlfn.XLOOKUP($A39,Inputs!$A:$A,Inputs!M:M,,0) -> 0
A40: Accounts Receivable | B40: =_xlfn.XLOOKUP($A40,Inputs!$A:$A,Inputs!B:B,,0) -> 2779 | C40: =_xlfn.XLOOKUP($A40,Inputs!$A:$A,Inputs!C:C,,0) -> 2439 | D40: =_xlfn.XLOOKUP($A40,Inputs!$A:$A,Inputs!D:D,,0) -> 1073 | E40: =_xlfn.XLOOKUP($A40,Inputs!$A:$A,Inputs!E:E,,0) -> 1214 | F40: =_xlfn.XLOOKUP($A40,Inputs!$A:$A,Inputs!F:F,,0) -> 919 | G40: =_xlfn.XLOOKUP($A40,Inputs!$A:$A,Inputs!G:G,,0) -> 739 | H40: =_xlfn.XLOOKUP($A40,Inputs!$A:$A,Inputs!H:H,,0) -> 0 | I40: =_xlfn.XLOOKUP($A40,Inputs!$A:$A,Inputs!I:I,,0) -> 0 | J40: =_xlfn.XLOOKUP($A40,Inputs!$A:$A,Inputs!J:J,,0) -> 0 | K40: =_xlfn.XLOOKUP($A40,Inputs!$A:$A,Inputs!K:K,,0) -> 0 | L40: =_xlfn.XLOOKUP($A40,Inputs!$A:$A,Inputs!L:L,,0) -> 0 | M40: =_xlfn.XLOOKUP($A40,Inputs!$A:$A,Inputs!M:M,,0) -> 0
A41: Inventory | B41: =_xlfn.XLOOKUP($A41,Inputs!$A:$A,Inputs!B:B,,0) -> 0 | C41: =_xlfn.XLOOKUP($A41,Inputs!$A:$A,Inputs!C:C,,0) -> 0 | D41: =_xlfn.XLOOKUP($A41,Inputs!$A:$A,Inputs!D:D,,0) -> 0 | E41: =_xlfn.XLOOKUP($A41,Inputs!$A:$A,Inputs!E:E,,0) -> 0 | F41: =_xlfn.XLOOKUP($A41,Inputs!$A:$A,Inputs!F:F,,0) -> 0 | G41: =_xlfn.XLOOKUP($A41,Inputs!$A:$A,Inputs!G:G,,0) -> 0 | H41: =_xlfn.XLOOKUP($A41,Inputs!$A:$A,Inputs!H:H,,0) -> 0 | I41: =_xlfn.XLOOKUP($A41,Inputs!$A:$A,Inputs!I:I,,0) -> 0 | J41: =_xlfn.XLOOKUP($A41,Inputs!$A:$A,Inputs!J:J,,0) -> 0 | K41: =_xlfn.XLOOKUP($A41,Inputs!$A:$A,Inputs!K:K,,0) -> 0 | L41: =_xlfn.XLOOKUP($A41,Inputs!$A:$A,Inputs!L:L,,0) -> 0 | M41: =_xlfn.XLOOKUP($A41,Inputs!$A:$A,Inputs!M:M,,0) -> 0
A42: Property, Plant and Equipment | B42: =_xlfn.XLOOKUP($A42,Inputs!$A:$A,Inputs!B:B,,0) -> 2082 | C42: =_xlfn.XLOOKUP($A42,Inputs!$A:$A,Inputs!C:C,,0) -> 1853 | D42: =_xlfn.XLOOKUP($A42,Inputs!$A:$A,Inputs!D:D,,0) -> 1814 | E42: =_xlfn.XLOOKUP($A42,Inputs!$A:$A,Inputs!E:E,,0) -> 1731 | F42: =_xlfn.XLOOKUP($A42,Inputs!$A:$A,Inputs!F:F,,0) -> 1641 | G42: =_xlfn.XLOOKUP($A42,Inputs!$A:$A,Inputs!G:G,,0) -> 1192 | H42: =_xlfn.XLOOKUP($A42,Inputs!$A:$A,Inputs!H:H,,0) -> 0 | I42: =_xlfn.XLOOKUP($A42,Inputs!$A:$A,Inputs!I:I,,0) -> 0 | J42: =_xlfn.XLOOKUP($A42,Inputs!$A:$A,Inputs!J:J,,0) -> 0 | K42: =_xlfn.XLOOKUP($A42,Inputs!$A:$A,Inputs!K:K,,0) -> 0 | L42: =_xlfn.XLOOKUP($A42,Inputs!$A:$A,Inputs!L:L,,0) -> 0 | M42: =_xlfn.XLOOKUP($A42,Inputs!$A:$A,Inputs!M:M,,0) -> 0
A43: Other Assets | B43: =_xlfn.XLOOKUP($A43,Inputs!$A:$A,Inputs!B:B,,0) -> 20721 | C43: =_xlfn.XLOOKUP($A43,Inputs!$A:$A,Inputs!C:C,,0) -> 27999 | D43: =_xlfn.XLOOKUP($A43,Inputs!$A:$A,Inputs!D:D,,0) -> 22365 | E43: =_xlfn.XLOOKUP($A43,Inputs!$A:$A,Inputs!E:E,,0) -> 14985 | F43: =_xlfn.XLOOKUP($A43,Inputs!$A:$A,Inputs!F:F,,0) -> 13710 | G43: =_xlfn.XLOOKUP($A43,Inputs!$A:$A,Inputs!G:G,,0) -> 8960 | H43: =_xlfn.XLOOKUP($A43,Inputs!$A:$A,Inputs!H:H,,0) -> 0 | I43: =_xlfn.XLOOKUP($A43,Inputs!$A:$A,Inputs!I:I,,0) -> 0 | J43: =_xlfn.XLOOKUP($A43,Inputs!$A:$A,Inputs!J:J,,0) -> 0 | K43: =_xlfn.XLOOKUP($A43,Inputs!$A:$A,Inputs!K:K,,0) -> 0 | L43: =_xlfn.XLOOKUP($A43,Inputs!$A:$A,Inputs!L:L,,0) -> 0 | M43: =_xlfn.XLOOKUP($A43,Inputs!$A:$A,Inputs!M:M,,0) -> 0
A44: Total Assets | B44: =_xlfn.XLOOKUP($A44,Inputs!$A:$A,Inputs!B:B,,0) -> 32109 | C44: =_xlfn.XLOOKUP($A44,Inputs!$A:$A,Inputs!C:C,,0) -> 38774 | D44: =_xlfn.XLOOKUP($A44,Inputs!$A:$A,Inputs!D:D,,0) -> 33252 | E44: =_xlfn.XLOOKUP($A44,Inputs!$A:$A,Inputs!E:E,,0) -> 31761 | F44: =_xlfn.XLOOKUP($A44,Inputs!$A:$A,Inputs!F:F,,0) -> 23988 | G44: =_xlfn.XLOOKUP($A44,Inputs!$A:$A,Inputs!G:G,,0) -> 15426 | H44: =_xlfn.XLOOKUP($A44,Inputs!$A:$A,Inputs!H:H,,0) -> 0 | I44: =_xlfn.XLOOKUP($A44,Inputs!$A:$A,Inputs!I:I,,0) -> 0 | J44: =_xlfn.XLOOKUP($A44,Inputs!$A:$A,Inputs!J:J,,0) -> 0 | K44: =_xlfn.XLOOKUP($A44,Inputs!$A:$A,Inputs!K:K,,0) -> 0 | L44: =_xlfn.XLOOKUP($A44,Inputs!$A:$A,Inputs!L:L,,0) -> 0 | M44: =_xlfn.XLOOKUP($A44,Inputs!$A:$A,Inputs!M:M,,0) -> 0
A47: Liabilities
A48: Current Liabilities | B48: =_xlfn.XLOOKUP($A48,Inputs!$A:$A,Inputs!B:B,,0) -> 8853 | C48: =_xlfn.XLOOKUP($A48,Inputs!$A:$A,Inputs!C:C,,0) -> 9024 | D48: =_xlfn.XLOOKUP($A48,Inputs!$A:$A,Inputs!D:D,,0) -> 6865 | E48: =_xlfn.XLOOKUP($A48,Inputs!$A:$A,Inputs!E:E,,0) -> 5639 | F48: =_xlfn.XLOOKUP($A48,Inputs!$A:$A,Inputs!F:F,,0) -> 4259 | G48: =_xlfn.XLOOKUP($A48,Inputs!$A:$A,Inputs!G:G,,0) -> 3857 | H48: =_xlfn.XLOOKUP($A48,Inputs!$A:$A,Inputs!H:H,,0) -> 0 | I48: =_xlfn.XLOOKUP($A48,Inputs!$A:$A,Inputs!I:I,,0) -> 0 | J48: =_xlfn.XLOOKUP($A48,Inputs!$A:$A,Inputs!J:J,,0) -> 0 | K48: =_xlfn.XLOOKUP($A48,Inputs!$A:$A,Inputs!K:K,,0) -> 0 | L48: =_xlfn.XLOOKUP($A48,Inputs!$A:$A,Inputs!L:L,,0) -> 0 | M48: =_xlfn.XLOOKUP($A48,Inputs!$A:$A,Inputs!M:M,,0) -> 0
A49: Short-Term Debt | B49: =_xlfn.XLOOKUP($A49,Inputs!$A:$A,Inputs!B:B,,0) -> 0 | C49: =_xlfn.XLOOKUP($A49,Inputs!$A:$A,Inputs!C:C,,0) -> 0 | D49: =_xlfn.XLOOKUP($A49,Inputs!$A:$A,Inputs!D:D,,0) -> 0 | E49: =_xlfn.XLOOKUP($A49,Inputs!$A:$A,Inputs!E:E,,0) -> 0 | F49: =_xlfn.XLOOKUP($A49,Inputs!$A:$A,Inputs!F:F,,0) -> 0 | G49: =_xlfn.XLOOKUP($A49,Inputs!$A:$A,Inputs!G:G,,0) -> 0 | H49: =_xlfn.XLOOKUP($A49,Inputs!$A:$A,Inputs!H:H,,0) -> 0 | I49: =_xlfn.XLOOKUP($A49,Inputs!$A:$A,Inputs!I:I,,0) -> 0 | J49: =_xlfn.XLOOKUP($A49,Inputs!$A:$A,Inputs!J:J,,0) -> 0 | K49: =_xlfn.XLOOKUP($A49,Inputs!$A:$A,Inputs!K:K,,0) -> 0 | L49: =_xlfn.XLOOKUP($A49,Inputs!$A:$A,Inputs!L:L,,0) -> 0 | M49: =_xlfn.XLOOKUP($A49,Inputs!$A:$A,Inputs!M:M,,0) -> 0
A50: Short-Term Leases | B50: =_xlfn.XLOOKUP($A50,Inputs!$A:$A,Inputs!B:B,,0) -> 201 | C50: =_xlfn.XLOOKUP($A50,Inputs!$A:$A,Inputs!C:C,,0) -> 185 | D50: =_xlfn.XLOOKUP($A50,Inputs!$A:$A,Inputs!D:D,,0) -> 175 | E50: =_xlfn.XLOOKUP($A50,Inputs!$A:$A,Inputs!E:E,,0) -> 196 | F50: =_xlfn.XLOOKUP($A50,Inputs!$A:$A,Inputs!F:F,,0) -> 0 | G50: =_xlfn.XLOOKUP($A50,Inputs!$A:$A,Inputs!G:G,,0) -> 0 | H50: =_xlfn.XLOOKUP($A50,Inputs!$A:$A,Inputs!H:H,,0) -> 0 | I50: =_xlfn.XLOOKUP($A50,Inputs!$A:$A,Inputs!I:I,,0) -> 0 | J50: =_xlfn.XLOOKUP($A50,Inputs!$A:$A,Inputs!J:J,,0) -> 0 | K50: =_xlfn.XLOOKUP($A50,Inputs!$A:$A,Inputs!K:K,,0) -> 0 | L50: =_xlfn.XLOOKUP($A50,Inputs!$A:$A,Inputs!L:L,,0) -> 0 | M50: =_xlfn.XLOOKUP($A50,Inputs!$A:$A,Inputs!M:M,,0) -> 0
A51: Other current liabilities | B51: =_xlfn.XLOOKUP($A51,Inputs!$A:$A,Inputs!B:B,,0) -> 7924 | C51: =_xlfn.XLOOKUP($A51,Inputs!$A:$A,Inputs!C:C,,0) -> 7979 | D51: =_xlfn.XLOOKUP($A51,Inputs!$A:$A,Inputs!D:D,,0) -> 6455 | E51: =_xlfn.XLOOKUP($A51,Inputs!$A:$A,Inputs!E:E,,0) -> 5171 | F51: =_xlfn.XLOOKUP($A51,Inputs!$A:$A,Inputs!F:F,,0) -> 4109 | G51: =_xlfn.XLOOKUP($A51,Inputs!$A:$A,Inputs!G:G,,0) -> 3857 | H51: =_xlfn.XLOOKUP($A51,Inputs!$A:$A,Inputs!H:H,,0) -> 0 | I51: =_xlfn.XLOOKUP($A51,Inputs!$A:$A,Inputs!I:I,,0) -> 0 | J51: =_xlfn.XLOOKUP($A51,Inputs!$A:$A,Inputs!J:J,,0) -> 0 | K51: =_xlfn.XLOOKUP($A51,Inputs!$A:$A,Inputs!K:K,,0) -> 0 | L51: =_xlfn.XLOOKUP($A51,Inputs!$A:$A,Inputs!L:L,,0) -> 0 | M51: =_xlfn.XLOOKUP($A51,Inputs!$A:$A,Inputs!M:M,,0) -> 0
A52: Non-current Liabilities | B52: =_xlfn.XLOOKUP($A52,Inputs!$A:$A,Inputs!B:B,,0) -> 14752 | C52: =_xlfn.XLOOKUP($A52,Inputs!$A:$A,Inputs!C:C,,0) -> 14401 | D52: =_xlfn.XLOOKUP($A52,Inputs!$A:$A,Inputs!D:D,,0) -> 12633 | E52: =_xlfn.XLOOKUP($A52,Inputs!$A:$A,Inputs!E:E,,0) -> 10939 | F52: =_xlfn.XLOOKUP($A52,Inputs!$A:$A,Inputs!F:F,,0) -> 12937 | G52: =_xlfn.XLOOKUP($A52,Inputs!$A:$A,Inputs!G:G,,0) -> -3857 | H52: =_xlfn.XLOOKUP($A52,Inputs!$A:$A,Inputs!H:H,,0) -> 0 | I52: =_xlfn.XLOOKUP($A52,Inputs!$A:$A,Inputs!I:I,,0) -> 0 | J52: =_xlfn.XLOOKUP($A52,Inputs!$A:$A,Inputs!J:J,,0) -> 0 | K52: =_xlfn.XLOOKUP($A52,Inputs!$A:$A,Inputs!K:K,,0) -> 0 | L52: =_xlfn.XLOOKUP($A52,Inputs!$A:$A,Inputs!L:L,,0) -> 0 | M52: =_xlfn.XLOOKUP($A52,Inputs!$A:$A,Inputs!M:M,,0) -> 0
A53: Long-Term Debt | B53: =_xlfn.XLOOKUP($A53,Inputs!$A:$A,Inputs!B:B,,0) -> 9265 | C53: =_xlfn.XLOOKUP($A53,Inputs!$A:$A,Inputs!C:C,,0) -> 9276 | D53: =_xlfn.XLOOKUP($A53,Inputs!$A:$A,Inputs!D:D,,0) -> 7560 | E53: =_xlfn.XLOOKUP($A53,Inputs!$A:$A,Inputs!E:E,,0) -> 5707 | F53: =_xlfn.XLOOKUP($A53,Inputs!$A:$A,Inputs!F:F,,0) -> 6869 | G53: =_xlfn.XLOOKUP($A53,Inputs!$A:$A,Inputs!G:G,,0) -> 0 | H53: =_xlfn.XLOOKUP($A53,Inputs!$A:$A,Inputs!H:H,,0) -> 0 | I53: =_xlfn.XLOOKUP($A53,Inputs!$A:$A,Inputs!I:I,,0) -> 0 | J53: =_xlfn.XLOOKUP($A53,Inputs!$A:$A,Inputs!J:J,,0) -> 0 | K53: =_xlfn.XLOOKUP($A53,Inputs!$A:$A,Inputs!K:K,,0) -> 0 | L53: =_xlfn.XLOOKUP($A53,Inputs!$A:$A,Inputs!L:L,,0) -> 0 | M53: =_xlfn.XLOOKUP($A53,Inputs!$A:$A,Inputs!M:M,,0) -> 0
A54: Long-Term Leases | B54: =_xlfn.XLOOKUP($A54,Inputs!$A:$A,Inputs!B:B,,0) -> 1673 | C54: =_xlfn.XLOOKUP($A54,Inputs!$A:$A,Inputs!C:C,,0) -> 1644 | D54: =_xlfn.XLOOKUP($A54,Inputs!$A:$A,Inputs!D:D,,0) -> 1544 | E54: =_xlfn.XLOOKUP($A54,Inputs!$A:$A,Inputs!E:E,,0) -> 1523 | F54: =_xlfn.XLOOKUP($A54,Inputs!$A:$A,Inputs!F:F,,0) -> 0 | G54: =_xlfn.XLOOKUP($A54,Inputs!$A:$A,Inputs!G:G,,0) -> 0 | H54: =_xlfn.XLOOKUP($A54,Inputs!$A:$A,Inputs!H:H,,0) -> 0 | I54: =_xlfn.XLOOKUP($A54,Inputs!$A:$A,Inputs!I:I,,0) -> 0 | J54: =_xlfn.XLOOKUP($A54,Inputs!$A:$A,Inputs!J:J,,0) -> 0 | K54: =_xlfn.XLOOKUP($A54,Inputs!$A:$A,Inputs!K:K,,0) -> 0 | L54: =_xlfn.XLOOKUP($A54,Inputs!$A:$A,Inputs!L:L,,0) -> 0 | M54: =_xlfn.XLOOKUP($A54,Inputs!$A:$A,Inputs!M:M,,0) -> 0
A55: Other non-current liabilities | B55: =_xlfn.XLOOKUP($A55,Inputs!$A:$A,Inputs!B:B,,0) -> 3814 | C55: =_xlfn.XLOOKUP($A55,Inputs!$A:$A,Inputs!C:C,,0) -> 3481 | D55: =_xlfn.XLOOKUP($A55,Inputs!$A:$A,Inputs!D:D,,0) -> 3529 | E55: =_xlfn.XLOOKUP($A55,Inputs!$A:$A,Inputs!E:E,,0) -> 3709 | F55: =_xlfn.XLOOKUP($A55,Inputs!$A:$A,Inputs!F:F,,0) -> 6068 | G55: =_xlfn.XLOOKUP($A55,Inputs!$A:$A,Inputs!G:G,,0) -> -3857 | H55: =_xlfn.XLOOKUP($A55,Inputs!$A:$A,Inputs!H:H,,0) -> 0 | I55: =_xlfn.XLOOKUP($A55,Inputs!$A:$A,Inputs!I:I,,0) -> 0 | J55: =_xlfn.XLOOKUP($A55,Inputs!$A:$A,Inputs!J:J,,0) -> 0 | K55: =_xlfn.XLOOKUP($A55,Inputs!$A:$A,Inputs!K:K,,0) -> 0 | L55: =_xlfn.XLOOKUP($A55,Inputs!$A:$A,Inputs!L:L,,0) -> 0 | M55: =_xlfn.XLOOKUP($A55,Inputs!$A:$A,Inputs!M:M,,0) -> 0
A56: Total Liabilities | B56: =_xlfn.XLOOKUP($A56,Inputs!$A:$A,Inputs!B:B,,0) -> 23605 | C56: =_xlfn.XLOOKUP($A56,Inputs!$A:$A,Inputs!C:C,,0) -> 23425 | D56: =_xlfn.XLOOKUP($A56,Inputs!$A:$A,Inputs!D:D,,0) -> 19498 | E56: =_xlfn.XLOOKUP($A56,Inputs!$A:$A,Inputs!E:E,,0) -> 16578 | F56: =_xlfn.XLOOKUP($A56,Inputs!$A:$A,Inputs!F:F,,0) -> 17196 | G56: =_xlfn.XLOOKUP($A56,Inputs!$A:$A,Inputs!G:G,,0) -> 0 | H56: =_xlfn.XLOOKUP($A56,Inputs!$A:$A,Inputs!H:H,,0) -> 0 | I56: =_xlfn.XLOOKUP($A56,Inputs!$A:$A,Inputs!I:I,,0) -> 0 | J56: =_xlfn.XLOOKUP($A56,Inputs!$A:$A,Inputs!J:J,,0) -> 0 | K56: =_xlfn.XLOOKUP($A56,Inputs!$A:$A,Inputs!K:K,,0) -> 0 | L56: =_xlfn.XLOOKUP($A56,Inputs!$A:$A,Inputs!L:L,,0) -> 0 | M56: =_xlfn.XLOOKUP($A56,Inputs!$A:$A,Inputs!M:M,,0) -> 0
A58: Debt | B58: =B49+B53 -> 9265 | C58: =C49+C53 -> 9276 | D58: =D49+D53 -> 7560 | E58: =E49+E53 -> 5707 | F58: =F49+F53 -> 6869 | G58: =G49+G53 -> 0 | H58: =H49+H53 -> 0 | I58: =I49+I53 -> 0 | ... M58: =M49+M53 -> 0
A59: Debt/Assets | B59: =IFERROR(B58/B44,"-") -> 0.28854838 | C59: =IFERROR(C58/C44,"-") -> 0.23923248 | D59: =IFERROR(D58/D44,"-") -> 0.22735475 | E59: =IFERROR(E58/E44,"-") -> 0.17968578 | F59: =IFERROR(F58/F44,"-") -> 0.28635151 | G59: =IFERROR(G58/G44,"-") -> 0 | H59: =IFERROR(H58/H44,"-") -> - | I59: =IFERROR(I58/I44,"-") -> - | ... M59: =IFERROR(M58/M44,"-") -> -
A61: Minority Interest | B61: =_xlfn.XLOOKUP($A61,Inputs!$A:$A,Inputs!B:B,,0) -> 430 | C61: =_xlfn.XLOOKUP($A61,Inputs!$A:$A,Inputs!C:C,,0) -> 204 | D61: =_xlfn.XLOOKUP($A61,Inputs!$A:$A,Inputs!D:D,,0) -> 787 | E61: =_xlfn.XLOOKUP($A61,Inputs!$A:$A,Inputs!E:E,,0) -> 311 | F61: =_xlfn.XLOOKUP($A61,Inputs!$A:$A,Inputs!F:F,,0) -> 0 | G61: =_xlfn.XLOOKUP($A61,Inputs!$A:$A,Inputs!G:G,,0) -> 0 | H61: =_xlfn.XLOOKUP($A61,Inputs!$A:$A,Inputs!H:H,,0) -> 0 | I61: =_xlfn.XLOOKUP($A61,Inputs!$A:$A,Inputs!I:I,,0) -> 0 | J61: =_xlfn.XLOOKUP($A61,Inputs!$A:$A,Inputs!J:J,,0) -> 0 | K61: =_xlfn.XLOOKUP($A61,Inputs!$A:$A,Inputs!K:K,,0) -> 0 | L61: =_xlfn.XLOOKUP($A61,Inputs!$A:$A,Inputs!L:L,,0) -> 0 | M61: =_xlfn.XLOOKUP($A61,Inputs!$A:$A,Inputs!M:M,,0) -> 0
A63: Shareholder's Equity | B63: =_xlfn.XLOOKUP($A63,Inputs!$A:$A,Inputs!B:B,,0) -> 8074 | C63: =_xlfn.XLOOKUP($A63,Inputs!$A:$A,Inputs!C:C,,0) -> 15145 | D63: =_xlfn.XLOOKUP($A63,Inputs!$A:$A,Inputs!D:D,,0) -> 12967 | E63: =_xlfn.XLOOKUP($A63,Inputs!$A:$A,Inputs!E:E,,0) -> 14872 | F63: =_xlfn.XLOOKUP($A63,Inputs!$A:$A,Inputs!F:F,,0) -> 6792 | G63: =_xlfn.XLOOKUP($A63,Inputs!$A:$A,Inputs!G:G,,0) -> 15426 | H63: =_xlfn.XLOOKUP($A63,Inputs!$A:$A,Inputs!H:H,,0) -> 0 | I63: =_xlfn.XLOOKUP($A63,Inputs!$A:$A,Inputs!I:I,,0) -> 0 | J63: =_xlfn.XLOOKUP($A63,Inputs!$A:$A,Inputs!J:J,,0) -> 0 | K63: =_xlfn.XLOOKUP($A63,Inputs!$A:$A,Inputs!K:K,,0) -> 0 | L63: =_xlfn.XLOOKUP($A63,Inputs!$A:$A,Inputs!L:L,,0) -> 0 | M63: =_xlfn.XLOOKUP($A63,Inputs!$A:$A,Inputs!M:M,,0) -> 0
A66: Other Data
A67: Number of employees | B67: =_xlfn.XLOOKUP($A67,Inputs!$A:$A,Inputs!B:B,,0) -> #N/A | C67: =_xlfn.XLOOKUP($A67,Inputs!$A:$A,Inputs!C:C,,0) -> #N/A | D67: =_xlfn.XLOOKUP($A67,Inputs!$A:$A,Inputs!D:D,,0) -> #N/A | E67: =_xlfn.XLOOKUP($A67,Inputs!$A:$A,Inputs!E:E,,0) -> #N/A | F67: =_xlfn.XLOOKUP($A67,Inputs!$A:$A,Inputs!F:F,,0) -> #N/A | G67: =_xlfn.XLOOKUP($A67,Inputs!$A:$A,Inputs!G:G,,0) -> #N/A | H67: =_xlfn.XLOOKUP($A67,Inputs!$A:$A,Inputs!H:H,,0) -> #N/A | I67: =_xlfn.XLOOKUP($A67,Inputs!$A:$A,Inputs!I:I,,0) -> #N/A | J67: =_xlfn.XLOOKUP($A67,Inputs!$A:$A,Inputs!J:J,,0) -> #N/A | K67: =_xlfn.XLOOKUP($A67,Inputs!$A:$A,Inputs!K:K,,0) -> #N/A | L67: =_xlfn.XLOOKUP($A67,Inputs!$A:$A,Inputs!L:L,,0) -> #N/A | M67: =_xlfn.XLOOKUP($A67,Inputs!$A:$A,Inputs!M:M,,0) -> #N/A
A68: Shares Outstanding | B68: =_xlfn.XLOOKUP($A68,Inputs!$A:$A,Inputs!B:B,,0) -> #N/A | C68: =_xlfn.XLOOKUP($A68,Inputs!$A:$A,Inputs!C:C,,0) -> #N/A | D68: =_xlfn.XLOOKUP($A68,Inputs!$A:$A,Inputs!D:D,,0) -> #N/A | E68: =_xlfn.XLOOKUP($A68,Inputs!$A:$A,Inputs!E:E,,0) -> #N/A | F68: =_xlfn.XLOOKUP($A68,Inputs!$A:$A,Inputs!F:F,,0) -> #N/A | G68: =_xlfn.XLOOKUP($A68,Inputs!$A:$A,Inputs!G:G,,0) -> #N/A | H68: =_xlfn.XLOOKUP($A68,Inputs!$A:$A,Inputs!H:H,,0) -> #N/A | I68: =_xlfn.XLOOKUP($A68,Inputs!$A:$A,Inputs!I:I,,0) -> #N/A | J68: =_xlfn.XLOOKUP($A68,Inputs!$A:$A,Inputs!J:J,,0) -> #N/A | K68: =_xlfn.XLOOKUP($A68,Inputs!$A:$A,Inputs!K:K,,0) -> #N/A | L68: =_xlfn.XLOOKUP($A68,Inputs!$A:$A,Inputs!L:L,,0) -> #N/A | M68: =_xlfn.XLOOKUP($A68,Inputs!$A:$A,Inputs!M:M,,0) -> #N/A
A69: Float | B69: =_xlfn.XLOOKUP($A69,Inputs!$A:$A,Inputs!B:B,,0) -> 0.9983 | C69: =_xlfn.XLOOKUP($A69,Inputs!$A:$A,Inputs!C:C,,0) -> Yahoo finance | D69: =_xlfn.XLOOKUP($A69,Inputs!$A:$A,Inputs!D:D,,0) -> 0 | E69: =_xlfn.XLOOKUP($A69,Inputs!$A:$A,Inputs!E:E,,0) -> 0 | F69: =_xlfn.XLOOKUP($A69,Inputs!$A:$A,Inputs!F:F,,0) -> 0 | G69: =_xlfn.XLOOKUP($A69,Inputs!$A:$A,Inputs!G:G,,0) -> 0 | H69: =_xlfn.XLOOKUP($A69,Inputs!$A:$A,Inputs!H:H,,0) -> 0 | I69: =_xlfn.XLOOKUP($A69,Inputs!$A:$A,Inputs!I:I,,0) -> 0 | J69: =_xlfn.XLOOKUP($A69,Inputs!$A:$A,Inputs!J:J,,0) -> 0 | K69: =_xlfn.XLOOKUP($A69,Inputs!$A:$A,Inputs!K:K,,0) -> 0 | L69: =_xlfn.XLOOKUP($A69,Inputs!$A:$A,Inputs!L:L,,0) -> 0 | M69: =_xlfn.XLOOKUP($A69,Inputs!$A:$A,Inputs!M:M,,0) -> 0
A70: Insiders Own | B70: =_xlfn.XLOOKUP($A70,Inputs!$A:$A,Inputs!B:B,,0) -> 0.0017 | C70: =_xlfn.XLOOKUP($A70,Inputs!$A:$A,Inputs!C:C,,0) -> Yahoo finance | D70: =_xlfn.XLOOKUP($A70,Inputs!$A:$A,Inputs!D:D,,0) -> 0 | E70: =_xlfn.XLOOKUP($A70,Inputs!$A:$A,Inputs!E:E,,0) -> 0 | F70: =_xlfn.XLOOKUP($A70,Inputs!$A:$A,Inputs!F:F,,0) -> 0 | G70: =_xlfn.XLOOKUP($A70,Inputs!$A:$A,Inputs!G:G,,0) -> 0 | H70: =_xlfn.XLOOKUP($A70,Inputs!$A:$A,Inputs!H:H,,0) -> 0 | I70: =_xlfn.XLOOKUP($A70,Inputs!$A:$A,Inputs!I:I,,0) -> 0 | J70: =_xlfn.XLOOKUP($A70,Inputs!$A:$A,Inputs!J:J,,0) -> 0 | K70: =_xlfn.XLOOKUP($A70,Inputs!$A:$A,Inputs!K:K,,0) -> 0 | L70: =_xlfn.XLOOKUP($A70,Inputs!$A:$A,Inputs!L:L,,0) -> 0 | M70: =_xlfn.XLOOKUP($A70,Inputs!$A:$A,Inputs!M:M,,0) -> 0
A71: Fitch/ S&P Rating | B71: =_xlfn.XLOOKUP($A71,Inputs!$A:$A,Inputs!B:B,,0) -> - | C71: =_xlfn.XLOOKUP($A71,Inputs!$A:$A,Inputs!C:C,,0) -> 10-K | D71: =_xlfn.XLOOKUP($A71,Inputs!$A:$A,Inputs!D:D,,0) -> 0 | E71: =_xlfn.XLOOKUP($A71,Inputs!$A:$A,Inputs!E:E,,0) -> 0 | F71: =_xlfn.XLOOKUP($A71,Inputs!$A:$A,Inputs!F:F,,0) -> 0 | G71: =_xlfn.XLOOKUP($A71,Inputs!$A:$A,Inputs!G:G,,0) -> 0 | H71: =_xlfn.XLOOKUP($A71,Inputs!$A:$A,Inputs!H:H,,0) -> 0 | I71: =_xlfn.XLOOKUP($A71,Inputs!$A:$A,Inputs!I:I,,0) -> 0 | J71: =_xlfn.XLOOKUP($A71,Inputs!$A:$A,Inputs!J:J,,0) -> 0 | K71: =_xlfn.XLOOKUP($A71,Inputs!$A:$A,Inputs!K:K,,0) -> 0 | L71: =_xlfn.XLOOKUP($A71,Inputs!$A:$A,Inputs!L:L,,0) -> 0 | M71: =_xlfn.XLOOKUP($A71,Inputs!$A:$A,Inputs!M:M,,0) -> 0
A72: Dividend Yield | B72: =_xlfn.XLOOKUP($A72,Inputs!$A:$A,Inputs!B:B,,0) -> #N/A | C72: =_xlfn.XLOOKUP($A72,Inputs!$A:$A,Inputs!C:C,,0) -> #N/A | D72: =_xlfn.XLOOKUP($A72,Inputs!$A:$A,Inputs!D:D,,0) -> #N/A | E72: =_xlfn.XLOOKUP($A72,Inputs!$A:$A,Inputs!E:E,,0) -> #N/A | F72: =_xlfn.XLOOKUP($A72,Inputs!$A:$A,Inputs!F:F,,0) -> #N/A | G72: =_xlfn.XLOOKUP($A72,Inputs!$A:$A,Inputs!G:G,,0) -> #N/A | H72: =_xlfn.XLOOKUP($A72,Inputs!$A:$A,Inputs!H:H,,0) -> #N/A | I72: =_xlfn.XLOOKUP($A72,Inputs!$A:$A,Inputs!I:I,,0) -> #N/A | J72: =_xlfn.XLOOKUP($A72,Inputs!$A:$A,Inputs!J:J,,0) -> #N/A | K72: =_xlfn.XLOOKUP($A72,Inputs!$A:$A,Inputs!K:K,,0) -> #N/A | L72: =_xlfn.XLOOKUP($A72,Inputs!$A:$A,Inputs!L:L,,0) -> #N/A | M72: =_xlfn.XLOOKUP($A72,Inputs!$A:$A,Inputs!M:M,,0) -> #N/A
A73: Daily Volume in Millions of USD | B73: =_xlfn.XLOOKUP($A73,Inputs!$A:$A,Inputs!B:B,,0) -> 0 | C73: =_xlfn.XLOOKUP($A73,Inputs!$A:$A,Inputs!C:C,,0) -> Yahoo Finance | D73: =_xlfn.XLOOKUP($A73,Inputs!$A:$A,Inputs!D:D,,0) -> 0 | E73: =_xlfn.XLOOKUP($A73,Inputs!$A:$A,Inputs!E:E,,0) -> 0 | F73: =_xlfn.XLOOKUP($A73,Inputs!$A:$A,Inputs!F:F,,0) -> 0 | G73: =_xlfn.XLOOKUP($A73,Inputs!$A:$A,Inputs!G:G,,0) -> 0 | H73: =_xlfn.XLOOKUP($A73,Inputs!$A:$A,Inputs!H:H,,0) -> 0 | I73: =_xlfn.XLOOKUP($A73,Inputs!$A:$A,Inputs!I:I,,0) -> 0 | J73: =_xlfn.XLOOKUP($A73,Inputs!$A:$A,Inputs!J:J,,0) -> 0 | K73: =_xlfn.XLOOKUP($A73,Inputs!$A:$A,Inputs!K:K,,0) -> 0 | L73: =_xlfn.XLOOKUP($A73,Inputs!$A:$A,Inputs!L:L,,0) -> 0 | M73: =_xlfn.XLOOKUP($A73,Inputs!$A:$A,Inputs!M:M,,0) -> 0
B75: 2020 | C75: 2021 | D75: 2022
A76: Short % of Float | B76: 0 | C76: 0 | D76: 0
A77: EPS | B77: 0 | C77: 0 | D77: 0
A79: Corporate Bonds 3, 5 Y 10 | B79: Average Price | C79: Moody's | D79: YTM | E79: DIVISA
B80: =VLOOKUP($A80,Inputs!$A$5:$M$98,MATCH(B$4,Inputs!$B$5:$M$5,0)+1,FALSE) -> #N/A | C80: =VLOOKUP($A80,Inputs!$A$5:$M$98,MATCH(C$4,Inputs!$B$5:$M$5,0)+1,FALSE) -> #N/A | D80: =VLOOKUP($A80,Inputs!$A$5:$M$98,MATCH(D$4,Inputs!$B$5:$M$5,0)+1,FALSE) -> #N/A | E80: =VLOOKUP($A80,Inputs!$A$5:$M$98,MATCH(E$4,Inputs!$B$5:$M$5,0)+1,FALSE) -> #N/A

Sheet Inputs
G2: Figures in Millions of USD
G3: Company | H3: #VALUE!
D4: Report in millions
A5: RESULTS | B5: =OP!J17 -> 2022 | C5: =B5-1 -> 2021 | D5: =C5-1 -> 2020 | E5: =D5-1 -> 2019 | F5: =E5-1 -> 2018 | G5: =F5-1 -> 2017 | H5: =G5-1 -> 2016 | I5: =H5-1 -> 2015 | J5: =I5-1 -> 2014 | ... M5: =L5-1 -> 2011 | Q5: Hoja | R5: Nombre campo Bloomberg | T5: Cambio de signo | Z5: 2016 | AA5: 2015 | AB5: 2014 | AC5: 2013 | AD5: 2012 | AE5: 2011 | AF5: 2010 | AG5: 2009
A6: Net Sales | B6: 31877 | C6: 17455 | D6: 11139 | E6: 13000 | F6: 10433 | G6: 7932 | N6: Income Statement | O6: Sales | Q6: Ingreso | R6: Ingreso | Z6: 38537 | AA6: 47011 | AB6: 55184 | AC6: 55656 | AD6: 65875 | AE6: 60138 | AF6: 42588 | AG6: 32396
A7: Gross Profit | B7: 12218 | C7: 8104 | D7: 5985 | E7: 6939 | F7: 5647 | G7: 3772 | N7: Income Statement | O7: =+A7 -> Gross Profit | Q7: Ingreso | R7: + Coste de bienes y servicios | Z7: =Z6-28044 -> 10493 | AA7: =AA6-33546 -> 13465 | AB7: =AB6-40718 -> 14466 | AC7: =AC6-40727 -> 14929 | AD7: =+AD6-47055 -> 18820 | AE7: =+AE6-43578 -> 16560 | AF7: =+AF6-30367 -> 12221 | AG7: =+AG6-23886 -> 8510
A8: Operating Income | B8: -1832 | C8: -3834 | D8: -4863 | E8: -8596 | F8: -3033 | G8: -4080 | N8: Income Statement | O8: Operating Income | Q8: Ingreso | R8: + Ventas, generales y admin | Z8: =Z7-4383 -> 6110 | AA8: =AA7-4951 -> 8514 | AB8: =AB7-6529 -> 7937 | AC8: =AC7-5547 -> 9382 | AD8: =AD7-5919-2466-797-580-485 -> 8573 | AE8: =+AE7-5203-2297-826-1081 -> 7153 | AF8: =+AF7-4248-1905-914-1191 -> 3963 | AG8: =+AG7-3645-1421-1045-1822 -> 577
A9: Other Expenses (Revenues) | B9: -7029 | C9: 3292 | D9: -1625 | E9: 722 | F9: 4993 | G9: -16 | N9: Income Statement | O9: investment income+other income expense+income loss+minority interest+non controlling interest+share onf net profit+gain8losses) on equity investments+share of result from associates nd joint ventures+non operating profit+ | Q9: Ingreso | R9: + Investigación y desarrollo | S9: + Coste de financiación de beneficio | T9: + Otro gasto operativo | U9: - Beneficio (pérdida) de filiales | V9: - Minoritarios | Z9: =1853+596+595+1904+6+8 -> 4962 | AA9: =2119+587+2023+11 -> 4740 | AB9: =2380+624+1619-8+16 -> 4631 | AC9: =2046+727+981+6+14 -> 3774 | AD9: =-14+41 -> 27 | AE9: 53 | AF9: =58+24 -> 82 | AG9: =12-68 -> -56
A10: Net Financial Cost | B10: -426 | C10: -446 | D10: -403 | E10: -325 | F10: -544 | G10: -408 | N10: Income Statement | O10: interest expense+financial income and expenses+other financial expense-income+interest and other net+ | Q10: Ingreso | R10: - Ingreso (pérdida) no operacional | Z10: =505+518 -> 1023 | AA10: =507-161 -> 346 | AB10: =484-322 -> 162 | AC10: =465+35 -> 500 | AD10: =467-130 -> 337 | AE10: =396+32 -> 428 | AF10: =343-130 -> 213 | AG10: =389-381 -> 8
A11: Taxes | B11: -181 | C11: -492 | D11: -192 | E11: 45 | F11: 283 | G11: -542 | N11: Income Statement | O11: Taxes | Q11: Ingreso | R11: - Gasto de impuesto a la renta (Beneficio) | Z11: 192 | AA11: 916 | AB11: 692 | AC11: 1319 | AD11: =2528 -> 2528 | AE11: =1720 -> 1720 | AF11: =968 -> 968 | AG11: =-270 -> -270
A12: Net Income | B12: -9141 | C12: -496 | D12: -6768 | E12: -8512 | F12: 987 | G12: -4033 | N12: Income Statement | O12: Net Income | Q12: Flujo de caja | R12: + Ingreso neto | Z12: -67 | AA12: 2512 | AB12: 2452 | AC12: 3789 | AD12: 5681 | AE12: =4928+24 -> 4952 | AF12: 2700 | AG12: 895
B13: =SUM(B8:B11) -> -9468 | C13: =SUM(C8:C11) -> -1480 | D13: =SUM(D8:D11) -> -7083 | E13: =SUM(E8:E11) -> -8154 | F13: =SUM(F8:F11) -> 1699 | G13: =SUM(G8:G11) -> -5046 | Z13: =Z8-Z10-Z9-Z11 -> -67 | AA13: =AA8-AA10-AA9-AA11 -> 2512 | AB13: =AB8-AB10-AB9-AB11 -> 2452 | AC13: =AC8-AC10-AC9-AC11 -> 3789 | AD13: =AD8-AD10-AD9-AD11 -> 5681 | AE13: =AE8-AE10-AE9-AE11 -> 4952 | AF13: =AF8-AF10-AF9-AF11 -> 2700 | AG13: =AG8-AG10-AG9-AG11 -> 895
A14: FINANCIAL POSITION | B14: =B12-B13 -> 327 | C14: =C12-C13 -> 984 | D14: =D12-D13 -> 315 | E14: =E12-E13 -> -358 | F14: =F12-F13 -> -712 | G14: =G12-G13 -> 1013 | Z14: =Z12-Z13 -> 0 | AA14: =AA12-AA13 -> 0 | AB14: =AB12-AB13 -> 0 | AC14: =AC12-AC13 -> 0 | AD14: =AD12-AD13 -> 0 | AE14: =AE12-AE13 -> 0 | AF14: =AF12-AF13 -> 0 | AG14: =AG12-AG13 -> 0
B15: =+B6/C6-1 -> 0.8262389 | C15: =+C6/D6-1 -> 0.56701679 | D15: =+D6/E6-1 -> -0.14315385 | E15: =+E6/F6-1 -> 0.2460462 | F15: =+F6/G6-1 -> 0.31530509 | G15: =+G6/H6-1 -> #DIV/0!
A16: Weighted Average Shares (Basic NI) | B16: 1972131 | C16: 1892546 | D16: 1752960 | E16: 1248353 | F16: 443368 | G16: 426360
A17: Weighted Average Shares (Diluted NI) | B17: 1974928 | C17: 1895519 | D17: 1752960 | E17: 1248353 | F17: 478999 | G17: 426360
A19: Net gains (losses) from ForEx | B19: -147 | C19: -67 | D19: -128 | E19: -40 | F19: -45 | G19: 42
A20: Total Comprehensive Income | B20: -9060 | C20: -485 | D20: -7116 | E20: -8505 | F20: 812 | G20: -4037
A22: Changes Net Working Capital | B22: =B23-C23 -> 601 | C22: =C23-D23 -> -3222 | D22: =D23-E23 -> -5269 | E22: =E23-F23 -> 3887 | F22: =F23-G23 -> 1419 | N22: cash flows | O22: NWC | Q22: Flujo de caja
A23: Net Working Capital | B23: =B27-B42 -> 396 | C23: =C27-C42 -> -205 | D23: =D27-D42 -> 3017 | E23: =E27-E42 -> 8286 | F23: =F27-F42 -> 4399 | G23: =G27-G42 -> 2980
A24: 2625 | B24: 2625 | C24: 2625 | D24: 2625 | E24: 2625 | F24: 2625 | G24: 2625 | N24: 2625 | Q24: Flujo de caja | R24: + Dividendos pagados | T24: Cambiar signo | Z24: 1799 | AA24: 1757 | AB24: 1620 | AC24: 1111 | AD24: 1617 | AE24: 1159 | AF24: 1084 | AG24: 1029
A25: BALANCE SHEET | B25: 2625 | C25: 2625 | D25: 2625 | E25: 2625 | F25: 2625 | G25: 2625 | N25: 2625 | Q25: Flujo de caja | R25: + Aumento en capital | S25: + Baja en capital | T25: Cambiar signo y hacer suma | Z25: 23 | AA25: =-33+2025 -> 1992 | AB25: 3817 | AC25: 1776 | AD25: -244 | AE25: -312 | AF25: -449 | AG25: -110
A26: ASSETS | N26: 1922 | O26: 2625
A27: Current | B27: 9249 | C27: 8819 | D27: 9882 | E27: 13925 | F27: 8658 | G27: 6837
A28: Cash & Eq. | B28: 4208 | C28: 4295 | D28: 5647 | E28: 10873 | F28: 6406 | G28: 4535 | N28: Balance Sheet | O28: Cash & Eq.
A29: Accounts Receivable | B29: 2779 | C29: 2439 | D29: 1073 | E29: 1214 | F29: 919 | G29: 739 | N29: Balance Sheet | O29: Accounts Receivable
A30: Inventory | B30: 0 | C30: 0 | D30: 0 | E30: 0 | F30: 0 | G30: 0 | N30: Balance Sheet | O30: Inventory | Q30: Balance | R30: + Efectivo, equivalentes y STI | Z30: 7168 | AA30: 6460 | AB30: 7341 | AC30: 6081 | AD30: 5490 | AE30: 3057 | AF30: 3592 | AG30: 4867
A31: Other Current Assets | B31: =B27-SUM(B28:B30) -> 2262 | C31: =C27-SUM(C28:C30) -> 2085 | D31: =D27-SUM(D28:D30) -> 3162 | E31: =E27-SUM(E28:E30) -> 1838 | F31: =F27-SUM(F28:F30) -> 1333 | G31: =G27-SUM(G28:G30) -> 1563 | N31: Balance Sheet | O31: Inventory | Q31: Balance | R31: + Cuentas y notas por cobrar | S31: + Activos derivados y de cobertura | T31: + Inversiones y cuentas por cobrar a LP | Z31: =5981+8522+1029+13556 -> 29088 | AA31: =6695+8991+1170+13651 -> 30507 | AB31: =7737+9027+1364+14644 -> 32772 | AC31: 33499 | AD31: 33911 | AE31: 31031 | AF31: 28849 | AG31: 27162
A32: Non-current | B32: =B38-B27 -> 22860 | C32: =C38-C27 -> 29955 | D32: =D38-D27 -> 23370 | E32: =E38-E27 -> 17836 | F32: =F38-F27 -> 15330 | G32: =G38-G27 -> 8589
A33: Property, Plant and Equipment | B33: 2082 | C33: 1853 | D33: 1814 | E33: 1731 | F33: 1641 | G33: 1192 | Q33: Balance | R33: + Inventarios | Z33: 8614 | AA33: 9700 | AB33: 12205 | AC33: 12625 | AD33: 15547 | AE33: 14544 | AF33: 9587 | AG33: 6360
A34: Operating leases | B34: 1449 | C34: 1388 | D34: 1274 | E34: 1594 | F34: 0
A35: Equity Method Investments | B35: 870 | C35: 800 | D35: 1079 | E35: 1364 | F35: 1312
A36: Other Non-Current Assets | B36: =B32-SUM(B33:B35) -> 18459 | C36: =C32-SUM(C33:C35) -> 25914 | D36: =D32-SUM(D33:D35) -> 19203 | E36: =E32-SUM(E33:E35) -> 13147 | F36: =F32-SUM(F33:F35) -> 12377 | G36: =G32-SUM(G33:G35) -> 7397 | N36: Balance Sheet | O36: Property, Plant and Equipment
A37: Other Assets | B37: =B31+B36 -> 20721 | C37: =C31+C36 -> 27999 | D37: =D31+D36 -> 22365 | E37: =E31+E36 -> 14985 | F37: =F31+F36 -> 13710 | G37: =G31+G36 -> 8960 | N37: Balance Sheet
A38: Total Assets | B38: 32109 | C38: 38774 | D38: 33252 | E38: 31761 | F38: 23988 | G38: 15426 | N38: Balance Sheet | O38: Total Assets | Q38: Balance | R38: + Propiedad, planta y equipo; neto | Z38: 15322 | AA38: 16090 | AB38: =16577 -> 16577 | AC38: 17075 | AD38: 16461 | AE38: 14395 | AF38: 12539 | AG38: 12386
N39: Balance Sheet | Z39: =Z40-SUM(Z30:Z38) -> 14512 | AA39: =AA40-SUM(AA30:AA38) -> 15585 | AB39: =AB40-SUM(AB30:AB38) -> 15786 | AC39: =AC40-SUM(AC30:AC38) -> 15616 | AD39: =AD40-SUM(AD30:AD38) -> 17947 | AE39: =AE40-SUM(AE30:AE38) -> 18419 | AF39: =AF40-SUM(AF30:AF38) -> 9453 | AG39: =AG40-SUM(AG30:AG38) -> 9263
N40: Balance Sheet | Q40: Balance | R40: Activos totales | Z40: 74704 | AA40: 78342 | AB40: 84681 | AC40: 84896 | AD40: 89356 | AE40: 81446 | AF40: 64020 | AG40: 60038
A41: LIABILITIES | N41: Balance Sheet
A42: Current Liabilities | B42: 8853 | C42: 9024 | D42: 6865 | E42: 5639 | F42: 4259 | G42: 3857 | N42: Balance Sheet | O42: Current Liabilities
A43: Payables | B43: 728 | C43: 860 | D43: 235 | E43: 272 | F43: 150
A44: Short-Term Debt | B44: 0 | C44: 0 | D44: 0 | E44: 0 | F44: 0 | N44: Balance Sheet | O44: Short term Debt | Q44: Balance | R44: Pasivos totales corrientes | Z44: 26132 | AA44: 26242 | AB44: 27877 | AC44: 27297 | AD44: 29415 | AE44: =93+3895+8161+3386+2410+2691+298+1967+558+5102 -> 28561 | AF44: =204+3852+5856+2880+1670+1831+281+1521+495+3430 -> 22020 | AG44: =433+3650+2993+3351+797+1217+262+888+302+5399 -> 19292
A45: Short-Term Leases | B45: 201 | C45: 185 | D45: 175 | E45: 196 | F45: 0
A46: Other current liabilities | B46: =B42-SUM(B43:B45) -> 7924 | C46: =C42-SUM(C43:C45) -> 7979 | D46: =D42-SUM(D43:D45) -> 6455 | E46: =E42-SUM(E43:E45) -> 5171 | F46: =F42-SUM(F43:F45) -> 4109 | G46: =G42-SUM(G43:G45) -> 3857 | N46: Balance Sheet | R46: + Préstamos CP | Z46: 7303 | AA46: 6967 | AB46: 4708 | AC46: 3679 | AD46: 5287 | AE46: 5660 | AF46: 3925 | AG46: 5701
A47: Non-current Liabilities | B47: =B51-B42 -> 14752 | C47: =C51-C42 -> 14401 | D47: =D51-D42 -> 12633 | E47: =E51-E42 -> 10939 | F47: =F51-F42 -> 12937 | G47: =G51-G42 -> -3857 | N47: Balance Sheet | O47: Total non current liabilities
A48: Long-Term Debt | B48: 9265 | C48: 9276 | D48: 7560 | E48: 5707 | F48: 6869 | N48: Balance Sheet | O48: Long term debt | Z48: =Z44-Z46 -> 18829 | AA48: =AA44-AA46 -> 19275 | AB48: =AB44-AB46 -> 23169 | AC48: =AC44-AC46 -> 23618 | AD48: =AD44-AD46 -> 24128 | AE48: =AE44-AE46 -> 22901 | AF48: =AF44-AF46 -> 18095 | AG48: =AG44-AG46 -> 13591
A49: Long-Term Leases | B49: 1673 | C49: 1644 | D49: 1544 | E49: 1523 | F49: 0 | Q49: Balance | R49: Pasivos totales no corrientes | Z49: =61491-Z44 -> 35359 | AA49: =63457-AA44 -> 37215 | AB49: =67855-AB44 -> 39978 | AC49: 36721 | AD49: 41973 | AE49: =8415+16529+10956+3583 -> 39483 | AF49: =4505+15932+7584+2654 -> 30675 | AG49: =5652+16195+7420+2179 -> 31446
A50: Other non-current liabilities | B50: =B47-SUM(B48:B49) -> 3814 | C50: =C47-SUM(C48:C49) -> 3481 | D50: =D47-SUM(D48:D49) -> 3529 | E50: =E47-SUM(E48:E49) -> 3709 | F50: =F47-SUM(F48:F49) -> 6068 | G50: =G47-SUM(G48:G49) -> -3857 | N50: Balance Sheet | O50: Other non current Liabilities | R50: + Préstamos a largo plazo | Z50: 22818 | AA50: 25169 | AB50: 27784 | AC50: 26719 | AD50: 27752 | AE50: 24944 | AF50: 20437 | AG50: 21847
A51: Total Liabilities | B51: 23605 | C51: 23425 | D51: 19498 | E51: 16578 | F51: 17196 | N51: Balance Sheet | O51: Total Liabilities
N52: Balance Sheet | Z52: =Z49-Z50 -> 12541 | AA52: =AA49-AA50 -> 12046 | AB52: =AB49-AB50 -> 12194 | AC52: =AC49-AC50 -> 10002 | AD52: =AD49-AD50 -> 14221 | AE52: =AE49-AE50 -> 14539 | AF52: =AF49-AF50 -> 10238 | AG52: =AG49-AG50 -> 9599
N53: Balance Sheet | Z53: =+Z49+Z44 -> 61491 | AA53: =+AA49+AA44 -> 63457 | AB53: =+AB49+AB44 -> 67855 | AC53: =AC44+AC49 -> 64018 | AD53: =AD49+AD44 -> 71388 | AE53: =AE49+AE44 -> 68044 | AF53: =AF49+AF44 -> 52695 | AG53: =AG49+AG44 -> 50738
A54: Minority Interest | B54: 430 | C54: 204 | D54: 787 | E54: 311 | N54: Balance Sheet | O54: Minority Interest
N55: Balance Sheet
A56: Shareholder's Equity | B56: =B38-B51-B54 -> 8074 | C56: =C38-C51-C54 -> 15145 | D56: =D38-D51-D54 -> 12967 | E56: =E38-E51-E54 -> 14872 | F56: =F38-F51-F54 -> 6792 | G56: =G38-G51-G54 -> 15426 | N56: Balance Sheet | Q56: Balance | R56: + Participación minoritaria/no dominante
A58: CASH FLOW
A59: Operating CF | B59: 642 | C59: -445 | D59: -2745 | E59: -4321 | F59: -1541 | G59: -1418
A60: Net Income | B60: =B$12 -> -9141 | C60: =C$12 -> -496 | D60: =D$12 -> -6768 | E60: =E$12 -> -8512 | F60: =F$12 -> 987 | G60: =G$12 -> -4033
A61: Depreciation & Amortization | B61: 947 | C61: 902 | D61: 575 | E61: 472 | F61: 426 | G61: 510
A62: Changes in assets and liabilities | B62: 335 | C62: 1682 | D62: 732 | E62: -500 | F62: 890 | G62: 1910
A63: Other Adjustments | B63: =B59-B60-B61-B62 -> 8501 | C63: =C59-C60-C61-C62 -> -2533 | D63: =D59-D60-D61-D62 -> 2716 | E63: =E59-E60-E61-E62 -> 4219 | F63: =F59-F60-F61-F62 -> -3844 | G63: =G59-G60-G61-G62 -> 195
A64: Investing CF | B64: -1637 | C64: -1201 | D64: -2869 | E64: -790 | F64: -695 | G64: -487
A65: Net Capex | B65: -252 | C65: -298 | D65: -616 | E65: -588 | F65: -558
A66: Investments & Acquisitions | B66: =376+266-14-1708-59 -> -1139 | C66: =2291+500+1000-2314-1113-982 -> -618 | D66: =1360-1471-2101-10+91 -> -2131 | E66: =293+2-100-441-7 -> -253 | F66: =-412-64 -> -476
A67: Other Inflows (Outflows) | B67: =B64-B65-B66 -> -246 | C67: =C64-C65-C66 -> -285 | D67: =D64-D65-D66 -> -122 | E67: =E64-E65-E66 -> 51 | F67: -24 | G67: 4
A68: Financing CF | B68: 15 | C68: 1780 | D68: 1379 | E68: 8939 | F68: 4640 | G68: 1015
A69: Debt Borrowing | B69: 0 | C69: 1484 | D69: 2628 | E69: 1189 | F69: 3466
A70: Debt Repayment | B70: 80 | C70: 334 | D70: =527+891 -> 1418
A71: Lease Increases | B71: =+(B45-C45)+(B49-C49) -> 45 | C71: =+(C45-D45)+(C49-D49) -> 110 | D71: =+(D45-E45)+(D49-E49) -> 0 | E71: =+(E45-F45)+(E49-F49) -> 1719 | F71: =+(F45-G45)+(F49-G49) -> 0 | G71: =+(G45-H45)+(G49-H49) -> 0
A72: Lease Payments | B72: -184 | C72: -226 | D72: -224 | E72: -138 | F72: -89 | G72: 0
A73: Dividends | B73: 0 | C73: 0 | D73: 0 | E73: 0 | F73: 0 | G73: 0 | N73: cash flows FINANCING | O73: Dividends paid
A74: Share buyback | B74: 0 | C74: 0 | D74: 0 | E74: 0 | F74: -10 | G74: -131 | N74: cash flows FINANCING | O74: =+A74 -> Share buyback
A75: Other Inflows (Outflows) | B75: =B68-B69-B70-B71-B72-B73-B74 -> 74 | C75: =C68-C69-C70-C71-C72-C73-C74 -> 78 | D75: =D68-D69-D70-D71-D72-D73-D74 -> -2443 | E75: =E68-E69-E70-E71-E72-E73-E74 -> 6169 | F75: =F68-F69-F70-F71-F72-F73-F74 -> 1273 | G75: =G68-G69-G70-G71-G72-G73-G74 -> 1146
A76: FX | B76: -148 | C76: -69 | D76: -92 | E76: -4 | F76: -119 | G76: 22
A77: Changes in cash | B77: =B59+B64+B68+B76 -> -1128 | C77: =C59+C64+C68+C76 -> 65 | D77: =D59+D64+D68+D76 -> -4327 | E77: =E59+E64+E68+E76 -> 3824 | F77: =F59+F64+F68+F76 -> 2285 | G77: =G59+G64+G68+G76 -> -868
O78: (Vitalis will later fill this info)
A79: Other Data | E79: Corporate Bonds 3, 5 Y 10 | H79: Average Price | J79: Moody's | K79: YTM | L79: DIVISA
A80: Number of employees | B80: 142000 | C80: 10-K | N80: bloomberg
A81: Shares Outstanding (Thousands) | B81: 285620 | C81: Yahoo finance | N81: bloomberg
A82: Float | B82: =OP!M17 -> 0.9983 | C82: Yahoo finance | N82: bloomberg
A83: Insiders Own | B83: =OP!M18 -> 0.0017 | C83: Yahoo finance | N83: bloomberg
A84: Fitch/ S&P Rating | B84: =OP!M20 -> - | C84: 10-K | N84: bloomberg
A85: Dividend Yield(Yahoo Finance) | B85: =Peers!C33 -> 12.98 | C85: Yahoo finance | N85: bloomberg
A86: Daily Volume in Millions of USD | C86: Yahoo Finance | N86: bloomberg
B87: 2020 | C87: =B87+1 -> 2021 | D87: =C87+1 -> 2022
A88: Short % of Float | D88: 2.14 | E88: Yahoo Finance
A89: EPS | B89: -3.86 | C89: -0.29 | D89: -4.65 | E89: Yahoo Finance

Sheet Growth Industry Averages
A1: Date updated: | B1: 44931
A2: Created by: | B2: Aswath Damodaran, adamodar@stern.nyu.edu
A3: What is this data? | B3: Historical (compounded annual) growth rate in net income and revenues - last 5 years | F3: US companies
A4: Home Page: | B4: http://www.damodaran.com
A5: Data website: | B5: https://pages.stern.nyu.edu/~adamodar/New_Home_Page/data.html
A6: Companies in each industry: | B6: https://pages.stern.nyu.edu/~adamodar/pc/datasets/indname.xls
A7: Variable definitions: | B7: https://pages.stern.nyu.edu/~adamodar/New_Home_Page/datafile/variable.htm
A8: Industry Name | B8: Number of Firms | C8: CAGR in Net Income- Last 5 years | D8: CAGR in Revenues- Last 5 years | E8: Expected Growth in Revenues - Next 2 years | F8: Expected Growth in EPS - Next 5 years
A9: Advertising | B9: 58 | C9: 0.233825 | D9: 0.18166952 | E9: 0.20375154 | F9: 0.0079555556
A10: Aerospace/Defense | B10: 77 | C10: 0.050448148 | D10: 0.039922558 | E10: 0.38921953 | F10: 0.081387391
A11: Air Transport | B11: 21 | C11: -0.237 | D11: 0.0224125 | E11: 0.31874667 | F11: 0.22525
A12: Apparel | B12: 39 | C12: 0.11 | D12: 0.058356957 | E12: 0.039632609 | F12: 0.056378571
A13: Auto & Truck | B13: 31 | C13: 0.20132 | D13: 0.280595 | E13: 13.283983 | F13: 0.1737
A14: Auto Parts | B14: 37 | C14: 0.083675 | D14: 0.070743333 | E14: 0.1539125 | F14: 0.22152143
A15: Bank (Money Center) | B15: 7 | C15: 0.01288 | D15: 0.0194 | E15: 0.0656 | F15: 0.019862
A16: Banks (Regional) | B16: 557 | C16: 0.18140366 | D16: 0.11019711 | E16: 0.1359809 | F16: 0.11154444
A17: Beverage (Alcoholic) | B17: 23 | C17: -0.12308 | D17: 0.1254375 | E17: 0.16617778 | F17: 0.46596667
A18: Beverage (Soft) | B18: 31 | C18: 0.1739 | D18: 0.15048545 | E18: 0.17535455 | F18: 0.12113333
A19: Broadcasting | B19: 26 | C19: 0.21364545 | D19: 0.19544111 | E19: 0.02599 | F19: 0.2535
A20: Brokerage & Investment Banking | B20: 30 | C20: 0.276 | D20: 0.1422875 | E20: -0.026243684 | F20: 0.19226
... A26: Chemical (Specialty) | B26: 76 | C26: 0.21611667 | D26: 0.094822449 | E26: 0.12618049 | F26: 0.14015833
A27: Coal & Related Energy | B27: 19 | C27: 0.088033333 | D27: -0.037149 | E27: 6.040926 | F27: #DIV/0!
A28: Computer Services | B28: 80 | C28: 0.16804545 | D28: 0.10479308 | E28: 0.096096552 | F28: 0.13076522
A29: Computers/Peripherals | B29: 42 | C29: 0.10070909 | D29: 0.16357148 | E29: 0.14794417 | F29: 0.12861364
A30: Construction Supplies | B30: 49 | C30: 0.090165217 | D30: 0.050167813 | E30: 0.74913824 | F30: 0.1786
A31: Diversified | B31: 23 | C31: 0.02365 | D31: 0.07692 | E31: 0.039342857 | F31: 0.14035
A32: Drugs (Biotechnology) | B32: 598 | C32: 0.071716667 | D32: 0.27230354 | E32: 0.69618469 | F32: -0.048395652
A33: Drugs (Pharmaceutical) | B33: 281 | C33: 0.30738824 | D33: 0.42345634 | E33: 0.62612549 | F33: 0.10348591
A34: Education | B34: 33 | C34: 0.16761667 | D34: 0.041291875 | E34: 0.10228389 | F34: 0.17142857
A35: Electrical Equipment | B35: 110 | C35: 0.14371889 | D35: 0.138975 | E35: 0.60529481 | F35: 0.1596619
A36: Electronics (Consumer & Office) | B36: 16 | C36: -0.368 | D36: -0.00473 | E36: 0.016857143 | F36: 0.13996667
A37: Electronics (General) | B37: 138 | C37: 0.14106976 | D37: 0.10634929 | E37: 0.29346015 | F37: 0.15550938
A38: Engineering/Construction | B38: 43 | C38: 0.1727625 | D38: 0.12138345 | E38: 0.17060938 | F38: 0.17328
A39: Entertainment | B39: 110 | C39: 0.090211111 | D39: 0.28593125 | E39: 0.21343135 | F39: 0.16553067
... A71: R.E.I.T. | B71: 223 | C71: 0.11296356 | D71: 0.095720324 | E71: 0.12692232 | F71: 0.11285918
A72: Real Estate (Development) | B72: 18 | C72: 0.3935 | D72: 0.10161667 | E72: 0.95046667 | F72: #DIV/0!
A73: Real Estate (General/Diversified) | B73: 12 | C73: 0.10715 | D73: 0.08742 | E73: 0.009 | F73: #DIV/0!
A74: Real Estate (Operations & Services) | B74: 60 | C74: 0.04279 | D74: 0.16003759 | E74: 0.051038889 | F74: 0.078333333
A75: Recreation | B75: 57 | C75: 0.10984118 | D75: 0.077886923 | E75: 0.070694688 | F75: 0.13516364
A76: Reinsurance | B76: 1 | C76: -0.0628 | D76: 0.0563 | E76: 0.0172 | F76: #DIV/0!
A77: Restaurant/Dining | B77: 70 | C77: 0.070419259 | D77: 0.062767619 | E77: 0.15182821 | F77: 0.111536
A78: Retail (Automotive) | B78: 30 | C78: 0.25143333 | D78: 0.17119444 | E78: 0.15070304 | F78: 0.14008933
A79: Retail (Building Supply) | B79: 15 | C79: 0.28625 | D79: 0.13023333 | E79: 0.015692857 | F79: 0.094652
A80: Retail (Distributors) | B80: 69 | C80: 0.30973793 | D80: 0.073269286 | E80: 0.101415 | F80: 0.16125
A81: Retail (General) | B81: 15 | C81: 0.092018182 | D81: 0.043181538 | E81: 0.046272143 | F81: 0.03889
A82: Retail (Grocery and Food) | B82: 13 | C82: 0.17587143 | D82: 0.049611111 | E82: 0.060283333 | F82: 0.11056
A83: Retail (Online) | B83: 63 | C83: -0.22178333 | D83: 0.20712522 | E83: 0.070557 | F83: 0.11249364
A84: Retail (Special Lines) | B84: 78 | C84: 0.15264543 | D84: 0.13322981 | E84: 0.02029037 | F84: 0.081696667
A85: Rubber& Tires | B85: 3 | C85: 0.31925 | D85: 0.12423333 | E85: 0.108 | F85: 0.0201
A86: Semiconductor | B86: 68 | C86: 0.26110609 | D86: 0.088798913 | E86: 0.16620333 | F86: 0.16155364
A87: Semiconductor Equip | B87: 30 | C87: 0.22156842 | D87: 0.15696923 | E87: 0.11841955 | F87: 0.17283571
A88: Shipbuilding & Marine | B88: 8 | C88: 0.5139 | D88: 0.15536667 | E88: -0.02328 | F88: 0.12
... A104: Total Market (without financials) | B104: 5649 | C104: 0.17808675 | D104: 0.1480667 | E104: 0.37771829 | F104: 0.14056901

Sheet Sector Impact
E2: Sector | F2: Sub-Industry | H2: Low | K2: Sector | L2: Environment | Q2: Social
E3: Communication Services | F3: Interactive Home Entertainment | H3: Medium | L3: CO2 | M3: Water | N3: Energy | O3: Waste | P3: Degradation | Q3: Turnover | R3: Compensation | S3: Reputation | T3: Discrimination | U3: Security | V3: Damage | W3: Pension | X3: Supply | Y3: Community | Z3: Public | AA3: Litigation
E4: Communication Services | F4: Interactive Media & Services | H4: High | K4: Communication Services | L4: Low | M4: Low | N4: Medium | O4: Low | P4: Low | Q4: Medium | R4: Medium | S4: Low | T4: Low | U4: High | V4: Low | W4: Low | X4: Low | Y4: Low | Z4: Low | AA4: Medium
B5: Environmental | E5: Communication Services | F5: Integrated Telecommunication Services | H5: Very High | K5: Consumer Discretionary | L5: Low | M5: Low | N5: Medium | O5: Medium | P5: Low | Q5: Medium | R5: Medium | S5: Low | T5: Low | U5: Medium | V5: Medium | W5: Medium | X5: High | Y5: Low | Z5: High | AA5: Low
B6: Direct CO2 emissions | E6: Communication Services | F6: Cable & Satellite | K6: Consumer Staples | L6: High | M6: Very High | N6: High | O6: High | P6: High | Q6: Medium | R6: High | S6: High | T6: Low | U6: Medium | V6: Medium | W6: Low | X6: High | Y6: Low | Z6: Very High | AA6: Low
B7: Total Water Use | E7: Communication Services | F7: Broadcasting | K7: Energy | L7: Very High | M7: Very High | N7: Medium | O7: Very High | P7: High | Q7: High | R7: Medium | S7: Medium | T7: Medium | U7: Medium | V7: High | W7: Medium | X7: Medium | Y7: High | Z7: High | AA7: Low
K8: Renewable Energy | L8: Low | M8: Low | N8: Low | O8: Medium | P8: Medium | Q8: Low | R8: Medium | S8: Medium | T8: High | U8: Medium | V8: Low | W8: Low | X8: Medium | Y8: Medium | Z8: High | AA8: Low
B9: Total Energy Consumption | E9: Communication Services | F9: Movies & Entertainment | K9: Financials | L9: Low | M9: Low | N9: Low | O9: Low | P9: Low | Q9: Low | R9: Low | S9: Medium | T9: High | U9: Medium | V9: Low | W9: Low | X9: Low | Y9: Low | Z9: Medium | AA9: Low
K10: Forestry | L10: Low | M10: Medium | N10: Low | O10: Medium | P10: High | Q10: Low | R10: Low | S10: Low | T10: Low | U10: Low | V10: Low | W10: Low | X10: Low | Y10: Medium | Z10: Low | AA10: Low
B11: Waste Management | E11: Communication Services | F11: Advertising | K11: Health Care | L11: Low | M11: Medium | N11: Low | O11: Low | P11: Low | Q11: Low | R11: Low | S11: Medium | T11: Low | U11: High | V11: Low | W11: Low | X11: Low | Y11: Low | Z11: Low | AA11: Low
B12: Land Degradation/Deforestation/Biodiversity loss/Animal sufering/... | E12: Communication Services | F12: Alternative Carriers | K12: Industrials | L12: Very High | M12: Very High | N12: Very High | O12: High | P12: High | Q12: Low | R12: Medium | S12: High | T12: Very High | U12: Medium | V12: Very High | W12: Medium | X12: Very High | Y12: Very High | Z12: Very High | AA12: High
B13: Social | E13: Communication Services | F13: Publishing | K13: Information Technology | L13: Medium | M13: Low | N13: High | O13: Low | P13: Low | Q13: Low | R13: Low | S13: Low | T13: Low | U13: High | V13: Low | W13: Low | X13: Low | Y13: Low | Z13: Medium | AA13: Very High
B14: Employee turnover | E14: Communication Services | F14: Wireless Telecommunication Services | K14: Materials | L14: Very High | M14: Very High | N14: Very High | O14: Very High | P14: High | Q14: High | R14: High | S14: Medium | T14: High | U14: Low | V14: Very High | W14: Medium | X14: Medium | Y14: Very High | Z14: High | AA14: Medium
B15: Salaries and compensation | E15: Consumer Discretionary | F15: Automotive Retail | K15: Real Estate | L15: Low | M15: Low | N15: Medium | O15: Low | P15: Low | Q15: Medium | R15: Low | S15: Low | T15: Low | U15: High | V15: Low | W15: Medium | X15: Low | Y15: Medium | Z15: Low | AA15: Low
B16: Reputational issues | E16: Consumer Discretionary | F16: Internet & Direct Marketing Retail | K16: Utilities | L16: Very High | M16: High | N16: High | O16: Medium | P16: High | Q16: Low | R16: Medium | S16: Medium | T16: Low | U16: Medium | V16: Medium | W16: Medium | X16: Medium | Y16: Low | Z16: Medium | AA16: Low
B17: Discrimination issues | E17: Consumer Discretionary | F17: Auto Parts & Equipment
B18: Job security | E18: Consumer Discretionary | F18: Specialty Stores
B19: Health injuries | E19: Consumer Discretionary | F19: Computer & Electronics Retail | L19: Communication Services | M19: Consumer Discretionary | N19: Consumer Staples | O19: Energy | P19: Financials | Q19: Health Care | R19: Industrials | S19: Information Technology | T19: Materials | U19: Real Estate | V19: Utilities
B20: PXP? | E20: Consumer Discretionary | F20: Hotels, Resorts & Cruise Lines | L20: Interactive Home Entertainment | M20: Automotive Retail | N20: Tobacco | O20: Oil & Gas Exploration & Production | P20: Life & Health Insurance | Q20: Health Care Equipment | R20: Industrial Conglomerates | S20: IT Consulting & Other Services | T20: Industrial Gases | U20: Office REITs | V20: Independent Power Producers & Energy Traders
B21: Supply chain | E21: Consumer Discretionary | F21: Restaurants | L21: Interactive Media & Services | M21: Internet & Direct Marketing Retail | N21: Agricultural Products | O21: Oil & Gas Equipment & Services | P21: Property & Casualty Insurance | Q21: Pharmaceuticals | R21: Airlines | S21: Application Software | T21: Specialty Chemicals | U21: Specialized REITs | V21: Electric Utilities
B22: Community involvement | E22: Consumer Discretionary | F22: Homebuilding | L22: Integrated Telecommunication Services | M22: Auto Parts & Equipment | N22: Distillers & Vintners | O22: Integrated Oil & Gas | P22: Consumer Finance | Q22: Health Care Supplies | R22: Building Products | S22: Semiconductors | T22: Paper Packaging | U22: Residential REITs | V22: Multi-Utilities
B23: Public Sector | E23: Consumer Discretionary | F23: General Merchandise Stores | L23: Cable & Satellite | M23: Specialty Stores | N23: Packaged Foods & Meats | O23: Oil & Gas Refining & Marketing | P23: Asset Management & Custody Banks | Q23: Health Care Distributors | R23: Electrical Components & Equipment | S23: Internet Services & Infrastructure | T23: Metal & Glass Containers | U23: Real Estate Services | V23: Water Utilities
B24: Litigation | E24: Consumer Discretionary | F24: Automobile Manufacturers | L24: Broadcasting | M24: Computer & Electronics Retail | N24: Household Products | O24: Oil & Gas Storage & Transportation | P24: Insurance Brokers | Q24: Biotechnology | R24: Aerospace & Defense | S24: Electronic Components | T24: Fertilizers & Agricultural Chemicals | U24: Industrial REITs | V24: Gas Utilities
E25: Consumer Discretionary | F25: Apparel Retail | L25: Movies & Entertainment | M25: Hotels, Resorts & Cruise Lines | N25: Soft Drinks | P25: Multi-line Insurance | Q25: Managed Health Care | R25: Air Freight & Logistics | S25: Technology Hardware, Storage & Peripherals | T25: Commodity Chemicals | U25: Retail REITs
E26: Consumer Discretionary | F26: Consumer Electronics | L26: Advertising | M26: Restaurants | N26: Hypermarkets & Super Centers | P26: Diversified Banks | Q26: Life Sciences Tools & Services | R26: Construction Machinery & Heavy Trucks | S26: Semiconductor Equipment | T26: Diversified Chemicals | U26: Health Care REITs
E27: Consumer Discretionary | F27: Apparel, Accessories & Luxury Goods | L27: Alternative Carriers | M27: Homebuilding | N27: Personal Products | P27: Multi-Sector Holdings | Q27: Health Care Technology | R27: Diversified Support Services | S27: Communications Equipment | T27: Copper | U27: Hotel & Resort REITs
E28: Consumer Discretionary | F28: Leisure Products | L28: Publishing | M28: General Merchandise Stores | N28: Food Retail | P28: Financial Exchanges & Data | Q28: Health Care Services | R28: Railroads | S28: Data Processing & Outsourced Services | T28: Construction Materials
E29: Consumer Discretionary | F29: Home Improvement Retail | L29: Wireless Telecommunication Services | M29: Automobile Manufacturers | N29: Brewers | P29: Investment Banking & Brokerage | Q29: Health Care Facilities | R29: Industrial Machinery | S29: Technology Distributors | T29: Gold
E30: Consumer Discretionary | F30: Casinos & Gaming | M30: Apparel Retail | N30: Food Distributors | P30: Regional Banks | R30: Agricultural & Farm Machinery | S30: Electronic Equipment & Instruments | T30: Steel
E31: Consumer Discretionary | F31: Home Furnishings | M31: Consumer Electronics | N31: Drug Retail | P31: Reinsurance | R31: Research & Consulting Services | S31: Systems Software
E32: Consumer Discretionary | F32: Distributors | M32: Apparel, Accessories & Luxury Goods | P32: Thrifts & Mortgage Finance | R32: Construction & Engineering | S32: Electronic Manufacturing Services
E33: Consumer Discretionary | F33: Housewares & Specialties | M33: Leisure Products | R33: Trucking
E34: Consumer Discretionary | F34: Household Appliances | M34: Home Improvement Retail | R34: Environmental & Facilities Services
E35: Consumer Staples | F35: Tobacco | M35: Casinos & Gaming | R35: Human Resource & Employment Services
E36: Consumer Staples | F36: Agricultural Products | M36: Home Furnishings | R36: Trading Companies & Distributors
E37: Consumer Staples | F37: Distillers & Vintners | M37: Distributors
E38: Consumer Staples | F38: Packaged Foods & Meats | M38: Housewares & Specialties
E39: Consumer Staples | F39: Household Products | M39: Household Appliances
E40: Consumer Staples | F40: Soft Drinks
E41: Consumer Staples | F41: Hypermarkets & Super Centers
E42: Consumer Staples | F42: Personal Products
E43: Consumer Staples | F43: Food Retail
E44: Consumer Staples | F44: Brewers
E45: Consumer Staples | F45: Food Distributors
E46: Consumer Staples | F46: Drug Retail
E47: Energy | F47: Oil & Gas Exploration & Production
E48: Energy | F48: Oil & Gas Equipment & Services
E49: Energy | F49: Integrated Oil & Gas
E50: Energy | F50: Oil & Gas Refining & Marketing
E51: Energy | F51: Oil & Gas Storage & Transportation
... E128: Utilities | F128: Gas Utilities

Sheet Industry Averages
