Workbook
Name Sectors: '[1]Sector Impact'!$K$4:$K$16
Name Sectors: '[2]Sector Impact'!$K$4:$K$16
Name Sectors: '[2]Sector Impact'!$K$4:$K$16
Name Sectors: 'Sector Impact'!$K$4:$K$16

Sheet OP
B2: 45039 | C2: Team 1 | E2: =Inputs!H3 -> SALESFORCE, INC. (XNYS:CRM) | L2: NYSE | M2: SIC:
B3: Logo | D3: COMPANY DESCRIPTION | H3: CEO & BOARD OF DIRECTORS
D4: {=_FV(Inputs!H3,"Description")} -> #VALUE! | H4: Name | I4: Gender | J4: Age | K4: Tenure | L4: Executive? | M4: Other roles
H5: Marc Benioff | I5: Male | J5: 58 | K5: 2000 | L5: Yes | M5: Chair, Chief Executive Officer & Co-Founder
H6: Laura Alber | I6: Female | J6: 54 | K6: 2021 | L6: No | M6: President & CEO, Williams-Sonoma, Inc.
H7: Craig Conway | I7: Male | J7: 68 | K7: 2005 | L7: No | M7: Former President & CEO, PeopleSoft, Inc.
H8: Arnold Donald | I8: Male | J8: 68 | K8: 2023 | L8: No | M8: Former President & CEO, Carnival Corporation & plc
H9: Parker Harris | I9: Male | J9: 56 | K9: 2018 | L9: No | M9: Chief Technology Officer & Co-Founder
H10: Neelie Kroes | I10: Female | J10: 81 | K10: 2016 | L10: No | M10: Former Vice President of the European Commission
H11: Sachin Mehra | I11: Male | J11: 52 | K11: 2023 | L11: No | M11: Financial Expert Chief Financial Officer, Mastercard
H12: G. Mason Morfit | I12: Male | J12: 47 | K12: 2023 | L12: No | M12: CEO & Chief Investment Officer, ValueAct Capital
H13: Oscar Munoz | I13: Male | J13: 64 | K13: 2022 | L13: No | M13: Former Executive Chair & CEO, United Airlines Holdings, Inc.
H14: John V. Roos | I14: Male | J14: 68 | K14: 2013 | L14: No | M14: Former U.S. Ambassador to Japan; Co-Founder, Geodesic Capita
H15: Robin Washington | I15: Female | J15: 60 | K15: 2013 | L15: No | M15: Lead Independent Director & Financial Expert Former EVP & CFO, Gilead Sciences, Inc.
H16: Maynard Webb | I16: Male | J16: 67 | K16: 2006 | L16: No | M16: Founder, Webb Investment Network
B17: USD MILLIONS | H17: Susan Wojcicki | I17: Female | J17: 54 | K17: 2014 | L17: No | M17: Former CEO, YouTube
B18: COMPANY OVERVIEW
B19: Stock | D19: Liquidity and Solvency | F19: Segments | I19: Profitability (2022) | L19: Multiples
B20: Last Price | C20: {=+_FV(Inputs!H3,"price")} -> #VALUE! | D20: Total Assets | E20: =_xlfn.XLOOKUP(D20,'Fin. Data'!A:A,'Fin. Data'!B:B,,0) -> 98849 | F20: Regions | H20: % Sales | I20: Reporting Year | J20: 2022 | L20: Float | M20: =943.57/973 -> 0.96975334
B21: Outstanding Shares | C21: {=_FV(E2,"Shares outstanding",TRUE)} -> #VALUE! | D21: Total Liabilities | E21: =_xlfn.XLOOKUP(D21,'Fin. Data'!A:A,'Fin. Data'!B:B,,0) -> 40490 | F21: =Segments!C5 -> Americas | H21: =Segments!B5 -> 0.6788087 | I21: End of Year | J21: 44957 | L21: Insiders Own | M21: 0.0317
B22: Market Cap. | C22: =C20*C21/1000000 -> #VALUE! | D22: Cash/Share | E22: =_xlfn.XLOOKUP("Cash & Eq.",'Fin. Data'!A:A,'Fin. Data'!B:B,,0)*1000000/C21 -> #VALUE! | F22: =Segments!C6 -> Europe | H22: =Segments!B6 -> 0.22708742 | I22: EBITDA | K22: =_xlfn.XLOOKUP(I22,'Fin. Data'!A:A,'Fin. Data'!B:B,,0) -> 4685 | L22: b (Yahoo) | M22: 1.19
B23: +Total Debt | C23: ='Fin. Data'!B58 -> 11392 | D23: EBITDA/Net Financial Cost (NFC) | E23: =_xlfn.XLOOKUP("EBITDA",'Fin. Data'!A:A,'Fin. Data'!B:B,,0)/_xlfn.XLOOKUP("Net Financial Cost",'Fin. Data'!A:A,'Fin. Data'!B:B,,0) -> -35.763359 | F23: =Segments!C7 -> Asia Pacific | H23: =Segments!B7 -> 0.09410388 | I23: Depreciation & Amortization | K23: =_xlfn.XLOOKUP(I23,'Fin. Data'!A:A,'Fin. Data'!B:B,,0) -> 3786 | L23: Score (S&P) | M23: A+
B24: -Cash | C24: ='Fin. Data'!B39 -> 12508 | D24: Debt/EBITDA | E24: =_xlfn.XLOOKUP("Total Debt",'Fin. Data'!A:A,'Fin. Data'!B:B,,0)/_xlfn.XLOOKUP("EBITDA",'Fin. Data'!A:A,'Fin. Data'!B:B,,0) -> 2.4315902 | I24: EBIT | K24: =_xlfn.XLOOKUP(I24,'Fin. Data'!A:A,'Fin. Data'!B:B,,0) -> 899 | L24: Price/Book Value | M24: =IFERROR((C20*C21/(E20-E21))/1000000,"")
B25: =Enterprise Value | C25: =C22+C23-C24 -> #VALUE! | D25: "Others Assets"/Asset | E25: =_xlfn.XLOOKUP("Other Assets",'Fin. Data'!A:A,'Fin. Data'!B:B,,0)/_xlfn.XLOOKUP("Total Assets",'Fin. Data'!A:A,'Fin. Data'!B:B,,0) -> 0.1594351 | I25: Net Income | K25: =_xlfn.XLOOKUP(I25,'Fin. Data'!A:A,'Fin. Data'!B:B,,0) -> 208 | L25: NCF(3y avg)/Asset | M25: =IFERROR(K31/E20,"") -> 0.019302168
B26: Holdings (nac/int'l) | C26: - | D26: Debt/Assets | E26: =_xlfn.XLOOKUP(D26,'Fin. Data'!A:A,'Fin. Data'!B:B,,0) -> 0.11524649 | F26: Categories | H26: % Sales | I26: EPS | K26: =1000000*K25/C21 -> #VALUE! | L26: Price/Net Inc. (3y avg) | M26: =IFERROR(C22/K30,"")
B27: t liq. (Holdings/Vol.) | C27: - | D27: EBITDA Margin (average) | E27: =AVERAGE(_xlfn.XLOOKUP("EBITDA Margin",'Fin. Data'!A:A,'Fin. Data'!B:D,,0)) -> 0.13670732 | F27: =+Segments!C15 -> Professional services and other | H27: =+Segments!B15 -> 0.069266194 | I27: ROA | K27: =K25/E20 -> 0.0021042196 | L27: EV/Asset | M27: =IFERROR(C25/E20,"")
B28: % Short of float | C28: 0.0079 | D28: Operating Margin (average) | E28: =AVERAGE(_xlfn.XLOOKUP("Operating Margin",'Fin. Data'!A:A,'Fin. Data'!B:D,,0)) -> 0.024982669 | F28: =+Segments!C16 -> Subscription and Support | H28: =+Segments!B16 -> 0.93073381 | I28: ROIC | K28: =K25/(E20-(E21-C23)) -> 0.0029820361 | L28: EV/Ebitda (3y average) | M28: =IFERROR(C25/K29,"")
B29: Traffic ESG | D29: Net Income Margin (average) | E29: =AVERAGE(_xlfn.XLOOKUP("Net Income Margin",'Fin. Data'!A:A,'Fin. Data'!B:D,,0)) -> 0.084248954 | I29: EBITDA (3y average) | K29: =AVERAGE(_xlfn.XLOOKUP("EBITDA",'Fin. Data'!A:A,'Fin. Data'!B:D,,0)) -> 3647 | L29: Price/NCF (3y average) | M29: =IFERROR(C22/K31,"")
B30: E | I30: Net Income (3y average) | K30: =AVERAGE(_xlfn.XLOOKUP("Net Income",'Fin. Data'!A:A,'Fin. Data'!B:D,,0)) -> 1908 | L30: Bonds 1,3,5a (USD) | M30: -
B31: S | D31: Net Financial Cost/Avg Net Debt | E31: =-_xlfn.XLOOKUP("Net Financial Cost",'Fin. Data'!A:A,'Fin. Data'!B:B,,0)/AVERAGE(_xlfn.XLOOKUP("Net Debt",'Fin. Data'!A:A,'Fin. Data'!B:D,,0)) -> -0.039934966 | I31: NCF (3y average) | K31: =AVERAGE(_xlfn.XLOOKUP("Net Income",'Fin. Data'!A:A,'Fin. Data'!B:D,,0)) -> 1908 | L31: Div+Rep.(3y avg)/Price | M31: =-IFERROR(SUM(E52:E54)/(3*C22),"") -> #VALUE!
B32: G | L32: Div. Yield | M32: =-IFERROR(L53/C22,"") -> #VALUE!
B33: INVESTMENT THESIS
B34: Pillars of Recommendation | H34: Recommendation | I34: Valuation Assumptions
B35: Pillar | C35: Explanation | H35: HOLD | I35: * Salesforce will start distributing dividends in 2025. * Debt/equity will decrease over time * Revenue growth reducing over time * Net working capital estimated through DPO and DSO
B36: High Discount Rate | C36: Higher discount rate lowers the present value of future earnings for stocks. When this occurs, stock prices tend to face downward pressure, as it is the current case for Salesforce
B37: Loyal Costumers | C37: They work with over 150,000 businesses of all sizes and their subscription services account for around 93% of total revenues. Sticky customers are an industry characteristic,
B38: Indusstry Potential Growth | C38: The growing use of digital channels by customers to communicate with brands and organizations is estimated to boost the customer relationship management (CRM) market growth over the forecast period
B39: Risks of Investment | H39: Price Target | I39: Valuation
B40: Risk | C40: Explanation | H40: =DCF!D76 -> #VALUE! | I40: Discount Rate | L40: =DCF!F50 -> 0.106
B41: Partnership dependence | C41: Partnerships are a key strength for Salesforce, the company depends on these partnerships to deliver certain features and services
B42: Security issues | C42: Salesforce takes great precaution to provide security over their client’s data and remains the top CRM provider in the industry. | I42: Upside/ Downside | L42: =DCF!D75 -> #VALUE!
B43: Increased competition | C43: As this software becomes more popular, larger competitors aim to imitate CRM software
B44: FINANCIAL PERFORMANCE
B45: Year | C45: Net Sales | D45: Operating Margin | E45: Dividends + Share Buyback | F45: Net Cash Flow | G45: Debt/Assets | H45: Depreciation & Amortization | I45: Capex + Investments | J45: Cash Flow
B46: =B47-1 -> 2014 | C46: {=_xlfn.SORTBY(TRANSPOSE(_xlfn.XLOOKUP(C$45,'Fin. Data'!$A:$A,'Fin. Data'!$B:$J,,0)),$B$46:$B$54,-1)} -> 5374 | D46: {=_xlfn.SORTBY(TRANSPOSE(_xlfn.XLOOKUP(D$45,'Fin. Data'!$A:$A,'Fin. Data'!$B:$J,,0)),$B$46:$B$54,-1)} -> -0.027167845 | E46: {=_xlfn.SORTBY(TRANSPOSE(_xlfn.XLOOKUP(E$45,'Fin. Data'!$A:$A,'Fin. Data'!$B:$J,,0)),$B$46:$B$54,-1)} -> 0 | F46: =Inputs!J77 -> 126.4 | G46: {=_xlfn.SORTBY(TRANSPOSE(_xlfn.XLOOKUP(G$45,'Fin. Data'!$A:$A,'Fin. Data'!$B:$J,,0)),$B$46:$B$54,-1)} -> 0.2060947 | H46: {=_xlfn.SORTBY(TRANSPOSE(_xlfn.XLOOKUP(H$45,'Fin. Data'!$A:$A,'Fin. Data'!$B:$J,,0)),$B$46:$B$54,-1)} -> 448.3 | I46: {=_xlfn.SORTBY(TRANSPOSE(_xlfn.XLOOKUP(I$45,'Fin. Data'!$A:$A,'Fin. Data'!$B:$J,,0)),$B$46:$B$54,-1)} -> -290.5 | L46: =J20 -> 2022 | M46: =L46-1 -> 2021
B47: =B48-1 -> 2015 | C47: 6667 | D47: 0.016649168 | E47: 0 | F47: =Inputs!I77 -> 250.3 | G47: 0.16046384 | H47: 525.8 | I47: -768.6 | J47: Net Income | L47: =_xlfn.XLOOKUP($J47,'Fin. Data'!$A:$A,'Fin. Data'!B:B,,0) -> 208 | M47: =_xlfn.XLOOKUP($J47,'Fin. Data'!$A:$A,'Fin. Data'!C:C,,0) -> 1444 | N47: =(C47/C46)-1 -> 0.2406029 | O47: =(D47/D46)-1 -> -1.6128262
B48: =B49-1 -> 2016 | C48: 8437 | D48: 0.025838568 | E48: 0 | F48: =Inputs!H77 -> 449 | G48: 0.15877168 | H48: 632 | I48: -3657 | J48: Operating CF | L48: =_xlfn.XLOOKUP($J48,'Fin. Data'!$A:$A,'Fin. Data'!B:B,,0) -> 7111 | M48: =_xlfn.XLOOKUP($J48,'Fin. Data'!$A:$A,'Fin. Data'!C:C,,0) -> 6000 | N48: =(C48/C47)-1 -> 0.26548673 | O48: =(D48/D47)-1 -> 0.55194355 | Q48: =F48/F47-1 -> 0.79384738 | R48: =H48/H47-1 -> 0.20197794 | S48: =I48/I47-1 -> 3.7580016
B49: =B50-1 -> 2017 | C49: 10540 | D49: 0.043074004 | E49: 0 | F49: =Inputs!G77 -> 936 | G49: 0.078238719 | H49: 753 | I49: -559 | J49: Investing CF | L49: =_xlfn.XLOOKUP($J49,'Fin. Data'!$A:$A,'Fin. Data'!B:B,,0) -> -1989 | M49: =_xlfn.XLOOKUP($J49,'Fin. Data'!$A:$A,'Fin. Data'!C:C,,0) -> -14536 | N49: =(C49/C48)-1 -> 0.24925922 | O49: =(D49/D48)-1 -> 0.66704298 | Q49: =F49/F48-1 -> 1.0846325 | R49: =H49/H48-1 -> 0.1914557 | S49: =I49/I48-1 -> -0.84714247
B50: =B51-1 -> 2018 | C50: 13282 | D50: 0.040280078 | E50: 0 | F50: =Inputs!F77 -> 126 | G50: 0.11861925 | H50: 962 | I50: -5710 | J50: Net Capex | L50: =_xlfn.XLOOKUP($J50,'Fin. Data'!$A:$A,'Fin. Data'!B:B,,0) -> -798 | M50: =_xlfn.XLOOKUP($J50,'Fin. Data'!$A:$A,'Fin. Data'!C:C,,0) -> -717 | N50: =(C50/C49)-1 -> 0.2601518 | O50: =(D50/D49)-1 -> -0.06486338 | Q50: =F50/F49-1 -> -0.86538462 | R50: =H50/H49-1 -> 0.27755644 | S50: =I50/I49-1 -> 9.2146691
B51: =B52-1 -> 2019 | C51: 17098 | D51: 0.017370453 | E51: 0 | F51: =Inputs!E77 -> 1476 | G51: 0.055472917 | H51: 2135 | I51: -1012 | J51: Investments & Acquisitions | L51: =_xlfn.XLOOKUP($J51,'Fin. Data'!$A:$A,'Fin. Data'!B:B,,0) -> -439 | M51: =_xlfn.XLOOKUP($J51,'Fin. Data'!$A:$A,'Fin. Data'!C:C,,0) -> -14876 | N51: =(C51/C50)-1 -> 0.28730613 | O51: =(D51/D50)-1 -> -0.56875822 | Q51: =F51/F50-1 -> 10.714286 | R51: =H51/H50-1 -> 1.2193347 | S51: =I51/I50-1 -> -0.82276708
B52: =B53-1 -> 2020 | C52: 21252 | D52: 0.02140975 | E52: 0 | F52: =Inputs!D77 -> 2050 | G52: 0.042246723 | H52: 2846 | I52: -1991 | J52: Financing CF | L52: =_xlfn.XLOOKUP($J52,'Fin. Data'!$A:$A,'Fin. Data'!B:B,,0) -> -3562 | M52: =_xlfn.XLOOKUP($J52,'Fin. Data'!$A:$A,'Fin. Data'!C:C,,0) -> 7838 | N52: =(C52/C51)-1 -> 0.24295239 | O52: =(D52/D51)-1 -> 0.23253838 | Q52: =F52/F51-1 -> 0.38888889 | R52: =H52/H51-1 -> 0.33302108 | S52: =I52/I51-1 -> 0.9673913
B53: =B54-1 -> 2021 | C53: 26492 | D53: 0.02068549 | E53: 0 | F53: =Inputs!C$77 -> -731 | G53: 0.11529372 | H53: 3298 | I53: -15593 | J53: Dividends | L53: =_xlfn.XLOOKUP($J53,'Fin. Data'!$A:$A,'Fin. Data'!B:B,,0) -> 0 | M53: =_xlfn.XLOOKUP($J53,'Fin. Data'!$A:$A,'Fin. Data'!C:C,,0) -> 0 | N53: =(C53/C52)-1 -> 0.24656503 | O53: =(D53/D52)-1 -> -0.0338285 | Q53: =F53/F52-1 -> -1.3565854 | R53: =H53/H52-1 -> 0.1588194 | S53: =I53/I52-1 -> 6.8317428
B54: =J20 -> 2022 | C54: 31352 | D54: 0.032852769 | E54: -4000 | F54: =Inputs!B77 -> 1552 | G54: 0.11524649 | H54: 3786 | I54: -1237 | J54: Share Buyback | L54: =_xlfn.XLOOKUP($J54,'Fin. Data'!$A:$A,'Fin. Data'!B:B,,0) -> -4000 | M54: =_xlfn.XLOOKUP($J54,'Fin. Data'!$A:$A,'Fin. Data'!C:C,,0) -> 0 | N54: =(C54/C53)-1 -> 0.18345161 | O54: =(D54/D53)-1 -> 0.58820355 | Q54: =F54/F53-1 -> -3.123119 | R54: =H54/H53-1 -> 0.14796847 | S54: =I54/I53-1 -> -0.92066953
B55: Annual Growth Rate | C55: =IFERROR((C54/C46)^(1/8)-1,"") -> 0.24665404 | D55: =IFERROR((D54/D46)^(1/8),"") | F55: =IFERROR((F54/F46)^(1/8)-1,"") -> 0.3681795 | H55: =IFERROR((H54/H46)^(1/8)-1,"") -> 0.30564913 | J55: FX | L55: =_xlfn.XLOOKUP($J55,'Fin. Data'!$A:$A,'Fin. Data'!B:B,,0) -> -8 | M55: =_xlfn.XLOOKUP($J55,'Fin. Data'!$A:$A,'Fin. Data'!C:C,,0) -> -33 | N55: =(C55/C54)-1 -> -0.99999213 | O55: =(D55/D54)-1 -> #VALUE!
B56: Average Growth Rate | C56: =IFERROR(AVERAGE(N47:N54),"") -> 0.24697198 | D56: =IFERROR(AVERAGE(O47:O54),"") -> -0.03006848 | F56: =IFERROR(AVERAGE(Q47:Q54),"") -> 1.0909379 | H56: =IFERROR(AVERAGE(S47:S54),"") -> 2.597318 | J56: Changes in Cash | L56: =L48-L49+L52-L53-L54 -> 9538 | M56: =M48-M49+M52-M53-M54 -> 28374
B57: CVAR | C57: =IFERROR(STDEV(C47:C54)/AVERAGE(C47:C54),"") -> 0.52467769 | D57: =IFERROR(STDEV(D46:D54)/AVERAGE(D46:D54),"") -> 0.96786601 | F57: =IFERROR(STDEV(F46:F54)/AVERAGE(F46:F54),"") -> 1.2684719 | H57: =IFERROR(STDEV(H46:H54)/AVERAGE(H46:H54),"") -> 0.77198957 | J57: Inventory/D Revenues | L57: =IFERROR(SUM(I51:I54)/(C54-C50),"") -> -1.097565 | M57: =IFERROR((SUM(I51:I54)-SUM(H51:H54))/(C54-C50),"") -> -1.7652463
B58: Last Year | C58: =IFERROR(C54/C53-1,"") -> 0.18345161 | D58: =IFERROR(D54/D53-1,"") -> 0.58820355 | F58: =IFERROR(1-(F54/F53),"") -> 3.123119 | H58: =IFERROR(1-(H54/H53),"") -> -0.14796847 | J58: t inversiones; t adq. neto dep. | L58: =IFERROR(L57/E27,"") -> -8.0285752 | M58: =IFERROR(M57/E27,"") -> -12.912595
B59: QUALITATIVE ANALYSIS
B60: SWOT ANALYSIS | J60: HOLDERS
B61: Strengths | E61: Weaknesses | J61: Name | M61: % Stake
B62: 1. Cloud-based software: Salesforce’s software is cloud-based, which means it is accessible from anywhere with an internet connection. 2. Platform for building custom applications: Salesforce offers a platform for building custom applications, allowing businesses to extend the functionality of Salesforce’s software and create custom solutions that meet their specific needs. 3. Strong brand and reputation: The company is known for its innovation, customer-centric approach, and commitment to social responsibility, which has helped it attract and retain and build strong customer relationships. | E62: 1. High cost: Salesforce’s software is relatively expensive, which could make it difficult for small businesses with limited budgets to adopt. 2. Integration challenges: While Salesforce has a robust ecosystem of partners and developers, integrating the software with other systems can be challenging and require specialised expertise. 3. Security concerns: As a cloud-based software provider, Salesforce must maintain strong security protocols to protect customer data. Any security breaches could damage the company’s reputation and lead to loss of business. | J62: The Vanguard Group, Inc. | M62: 0.085059
J63: BlackRock Institutional Trust Company, N.A. | M63: 0.047587
J64: State Street Global Advisors (US) | M64: 0.04692
J65: Fidelity Management & Research Company LLC | M65: 0.037541
J66: Benioff (Marc Russell) | M66: 0.026625
J67: Capital World Investors | M67: 0.019776
J68: Geode Capital Management, L.L.C. | M68: 0.01828
J69: Fisher Investments | M69: 0.014277
J70: T. Rowe Price Associates, Inc. | M70: 0.014232
J71: Wellington Management Company, LLP | M71: 0.012795
B72: Opportunities | E72: Threats | J72: Capital Research Global Investors | M72: 0.01162
B73: 1. Growth through acquisitions: Salesforce has a history of acquiring smaller companies to add new capabilities and expand its product offerings. The company could continue to pursue acquisitions to enter new markets or add new functionality to its software. 2. Expansion of platform capabilities: The company could continue to invest in new technologies, such as artificial intelligence and machine learning, to enhance the capabilities of its platform. | E73: 1. Economic downturns: Salesforce’s business is closely tied to the economy. A downturn could lead to reduced spending on software and services, which could impact Salesforce’s revenue and growth prospects. 2. Changing customer needs: As businesses’ needs to evolve, Salesforce must continue to innovate and develop new solutions to meet those needs. 3. Cybersecurity threats: As a cloud-based software provider, Salesforce is at risk of cyberattacks and data breaches. | J73: Norges Bank Investment Management (NBIM) | M73: 0.01101
J74: Nuveen LLC | M74: 0.009815
J75: JP Morgan Asset Management | M75: 0.009339
J76: Jennison Associates LLC | M76: 0.009318
J77: Polen Capital Management, LLC | M77: 0.008132
J78: Morgan Stanley Smith Barney LLC | M78: 0.008005
J79: Loomis, Sayles & Company, L.P. | M79: 0.007987
J80: Capital International Investors | M80: 0.007315
J81: Legal & General Investment Management Ltd. | M81: 0.006775
B82: NOTES | G82: STOCK PERFORMANCE (5 years)
G107: CRM | I107: ORCL | J107: MSFT | L107: ADBE | M107: SAP

Sheet Segments
B2: ="Regions "&"("&OP!$J$20&")" -> Regions (2022) | Q2: Products
D3: Nominal value | K3: YoY Growth
B4: Weight | C4: Region | D4: =OP!J20 -> 2022 | E4: =D4-1 -> 2021 | F4: =E4-1 -> 2020 | G4: =F4-1 -> 2019 | H4: =G4-1 -> 2018 | I4: =H4-1 -> 2017 | K4: =OP!J20 -> 2022 | L4: =K4-1 -> 2021 | M4: =L4-1 -> 2020 | N4: =M4-1 -> 2019 | O4: =N4-1 -> 2018 | P4: =O4-1 -> 2017
B5: =IFERROR(D5/$D$10,"") -> 0.6788087 | C5: Americas | D5: 17983 | E5: 14736 | F5: 12051 | G5: 9445 | H5: 7621 | I5: 6259 | K5: =(D5-E5)/E5 -> 0.22034473 | L5: =(E5-F5)/F5 -> 0.22280309 | M5: =(F5-G5)/G5 -> 0.27591318 | N5: =(G5-H5)/H5 -> 0.23933867 | O5: =(H5-I5)/I5 -> 0.21760665 | P5: -
B6: =IFERROR(D6/$D$10,"") -> 0.22708742 | C6: Europe | D6: 6016 | E6: 4501 | F6: 3430 | G6: 2553 | H6: 1916 | I6: 1383 | K6: =(D6-E6)/E6 -> 0.33659187 | L6: =(E6-F6)/F6 -> 0.3122449 | M6: =(F6-G6)/G6 -> 0.34351743 | N6: =(G6-H6)/H6 -> 0.33246347 | O6: =(H6-I6)/I6 -> 0.38539407 | P6: -
B7: =IFERROR(D7/$D$10,"") -> 0.09410388 | C7: Asia Pacific | D7: 2493 | E7: 2015 | F7: 1617 | G7: 1284 | H7: 1003 | I7: 795 | K7: =(D7-E7)/E7 -> 0.23722084 | L7: =(E7-F7)/F7 -> 0.24613482 | M7: =(F7-G7)/G7 -> 0.25934579 | N7: =(G7-H7)/H7 -> 0.28015952 | O7: =(H7-I7)/I7 -> 0.26163522 | P7: -
B8: =IFERROR(D8/$D$10,"") -> 0
B9: =IFERROR(D9/$D$10,"") -> 0
B10: =SUM(B5:B9) -> 1 | C10: TOTAL | D10: =SUM(D5:D9) -> 26492 | E10: =SUM(E5:E9) -> 21252 | F10: =SUM(F5:F9) -> 17098 | G10: =SUM(G5:G9) -> 13282 | H10: =SUM(H5:H9) -> 10540 | I10: =SUM(I5:I9) -> 8437 | K10: =(D10-E10)/E10 -> 0.24656503 | L10: =(E10-F10)/F10 -> 0.24295239 | M10: =(F10-G10)/G10 -> 0.28730613 | N10: =(G10-H10)/H10 -> 0.2601518 | O10: =(H10-I10)/I10 -> 0.24925922 | P10: -
B12: ="Categories "&"("&OP!$J$20&")" -> Categories (2022)
D13: Nominal value | K13: YoY Growth
B14: Weight | C14: Category | D14: =OP!J20 -> 2022 | E14: =D14-1 -> 2021 | F14: =E14-1 -> 2020 | G14: =F14-1 -> 2019 | H14: =G14-1 -> 2018 | I14: =H14-1 -> 2017 | K14: =OP!J20 -> 2022 | L14: =K14-1 -> 2021 | M14: =L14-1 -> 2020 | N14: =M14-1 -> 2019 | O14: =N14-1 -> 2018 | P14: =O14-1 -> 2017
B15: =IFERROR(D15/$D$17,"") -> 0.069266194 | C15: Professional services and other | D15: 1835 | E15: 1276 | F15: 1055 | G15: 869 | H15: 774 | I15: 638 | K15: =(D15-E15)/E15 -> 0.43808777 | L15: =(E15-G15)/G15 -> 0.46835443 | M15: =(G15-#REF!)/#REF! -> #REF! | N15: =(#REF!-H15)/H15 -> #REF! | O15: =(H15-I15)/I15 -> 0.21316614 | P15: -
B16: =IFERROR(D16/$D$17,"") -> 0.93073381 | C16: Subscription and Support | D16: 24657 | E16: 19976 | F16: 16043 | G16: 12413 | H16: 9766 | I16: 7799 | K16: =(D16-E16)/E16 -> 0.2343312 | L16: =(E16-F16)/F16 -> 0.24515365 | M16: =(F16-G16)/G16 -> 0.29243535 | N16: =(G16-H16)/H16 -> 0.27104239 | O16: =(H16-I16)/I16 -> 0.25221182 | P16: -
B17: =SUM(B15:B16) -> 1 | C17: TOTAL | D17: =SUM(D15:D16) -> 26492 | E17: =SUM(E15:E16) -> 21252 | F17: =SUM(F15:F16) -> 17098 | G17: =SUM(G15:G16) -> 13282 | H17: =SUM(H15:H16) -> 10540 | I17: =SUM(I15:I16) -> 8437 | K17: =(D17-E17)/E17 -> 0.24656503 | L17: =(E17-F17)/F17 -> 0.24295239 | M17: =(F17-G17)/G17 -> 0.28730613 | N17: =(G17-H17)/H17 -> 0.2601518 | O17: =(H17-I17)/I17 -> 0.24925922 | P17: -
B19: Categories | D19: Description | I19: Graphs
B20: Professional services and other | D20: This segment is category of offerings and activities that are distinct from the core software products provided by Salesforce. This segment encompasses a range of specialized services and solutions that are tailored to meet specific business needs and requirements
B21: Subscription and Support | D21: Subscription and support revenues include subscription fees from customers accessing the enterprise cloud computing services (collectively, “Cloud Services”), software license revenues from the sales of term and perpetual licenses, and support revenues from the sale of support and updates beyond the basic subscription fees or related to the sales of software licenses. Cloud Services allow customers to use the multi-tenant software without taking possession of the software.
B24: Industry | J24: Graphs (Industry Forecasts)
B25: Drivers | D25: Description
B26: Innovative Technology and Product Expansion | D26: Salesforce is recognized as a trailblazer in the realm of cloud computing, offering cutting-edge CRM (Customer Relationship Management) solutions. By leveraging this technology, businesses not only benefit from enhanced scalability and accessibility, but also experience a reduction in the necessity for on-premise infrastructure and associated maintenance costs. The commitment to continuous innovation is a hallmark of Salesforce. Substantial investments in research and development ensure that their platform remains at the forefront of technological advancements. This includes the integration of artificial intelligence (AI), machine learning, Internet of Things (IoT), and other emerging technologies. Furthermore, strategic acquisitions such as Tableau and MuleSoft have expanded Salesforce's capabilities in the realms of data analytics and integration, thereby augmenting its overall value proposition.
B27: Prioritize Customer-Centricity | D27: The Customer Success Platform offered by Salesforce positions itself as a platform that prioritizes the needs and satisfaction of customers. Its primary objective is to assist businesses in establishing and maintaining strong relationships with their customers. This is accomplished through the utilization of a variety of tools and features that facilitate personalized communication, automate sales processes, and enhance customer support. One of the key features of Salesforce is its ability to provide companies with a comprehensive view of their customers. By consolidating data from various touchpoints, businesses are able to gain a holistic understanding of their customers. This, in turn, enables them to implement more personalized marketing strategies, streamline sales processes, and enhance the overall customer service experience. In addition to its platform, Salesforce boasts a thriving community of users, developers, and administrators. These individuals actively engage in forums, share their knowledge, and contribute to a vast array of resources. Furthermore, Salesforce offers extensive training and certification programs, empowering both individuals and companies to fully maximize the potential of the platform.
B28: Sales forecast
B29: Source | D29: Market Growth CAGR | G29: Period
B30: https://www.statista.com/outlook/tmo/software/europe | D30: 0.062 | G30: 2023-2028
B31: https://www.grandviewresearch.com/industry-analysis/software-market-report | D31: 0.151 | G31: 2023-2030
B32: https://www.grandviewresearch.com/industry-analysis/sales-force-automation-software-market | D32: 0.087 | G32: 2023-2030
D33: 0.1
B34: Company's Strategy / Extra Notes

Sheet Acuerdo
A1: Invertir
A2: NO invertir
A3: Mantener sin elevar posición
A4: Mantener (y seguir comprando)
A5: Liquidar
A6: PENDIENTE

Sheet Peers
B1: Peer Logo | C1: Peer Name | D1: Description
C2: #VALUE! | D2: {=_FV(C2,"Descrição")} -> A MICROSOFT CORPORATION é uma empresa de tecnologia. A Empresa desenvolve, licencia e oferece suporte a uma gama de produtos de software, serviços e dispositivos. Seus segmentos são Produtividade e Processos de Negócio, Nuvem Inteligente e Outras Soluções de Computação Pessoal. Seus produtos incluem sistemas operacionais; aplicativos de produtividade de dispositivos cruzados; aplicativos de servidor; aplicativos de soluções de negócio; ferramentas de gerenciamento de desktop e servidor; ferramentas de desenvolvimento de software; videojogos, e treinamento e certificação de integradores e desenvolvedores de sistemas de computador. Ela também projeta, fabrica e vende dispositivos, incluindo computadores pessoais, tablets, consoles para jogos e entretenimento, telefones, outros dispositivos inteligentes e acessórios relacionados, que se integram com suas ofertas baseadas em nuvem. Ela oferece uma variedade de serviços, incluindo soluções baseadas em nuvem, que fornecem aos clientes software, serviços, plataformas e conteúdo, além de oferecer serviços de suporte e consultoria de soluções. Ela também oferece publicidade online.
C3: #VALUE! | D3: {=_FV(C3,"Descrição")} -> A SAP SE (SAP) é uma empresa sediada na Alemanha que oferece software de aplicativos corporativos. A Companhia opera em três segmentos: segmento de Aplicativos, Tecnologia e Serviços, que atua na venda de licenças de software, assinaturas de seus aplicativos na nuvem e serviços relacionados, principalmente serviços de suporte e vários serviços profissionais e serviços de suporte, além de serviços de implementação de seus produtos de software e serviços de educação sobre o uso de seus produtos; o segmento SAP Business Network, que inclui suas redes e serviços de negócios colaborativos baseados na nuvem relacionados ao SAP Business Network, incluindo aplicativos em nuvem, serviços profissionais e serviços educacionais, bem como o mercado da Empresa e vende as ofertas em nuvem desenvolvidas pela SAP Ariba, SAP Fieldglass e Concur e o segmento Customer Experience, que inclui produtos locais e baseados em nuvem que executam funções de front office em toda a experiência do cliente.
C4: #VALUE! | D4: {=_FV(C4,"Descrição")} -> A Oracle Corporation (Oracle) fornece produtos e serviços que atendem a ambientes de tecnologia da informação empresarial. Os negócios da Empresa incluem nuvem e licença, hardware e serviços. Seus produtos e serviços incluem aplicativos e ofertas de infraestrutura que são entregues por meio de uma variedade de modelos de implantação de TI. Seus clientes incluem agências governamentais, instituições educacionais e revendedores. Usando as tecnologias Oracle, seus clientes criam, implantam, executam, gerenciam e dão suporte a seus produtos, serviços e operações comerciais internos e externos. Suas ofertas de Oracle Cloud Services incluem Oracle Software as a Service (SaaS) e infraestrutura Oracle como serviço (IaaS), que fornece uma pilha de aplicativos e serviços de infraestrutura fornecidos por meio de modelos de implantação baseados em nuvem. O Oracle Cloud Services integra o software, hardware e serviços em nome do cliente em um ambiente de TI baseado em nuvem.
C5: #VALUE! | D5: {=_FV(C5,"Descrição")} -> A Adobe Systems Incorporated fornece software de design gráfico, publicação e imagem para impressão, Web e produção de vídeo. Seus clientes incluem profissionais criativos, como designers gráficos, web designers, cinegrafistas, fotógrafos e editores profissionais, usuários corporativos, como gerentes de tecnologia da informação (TI), a linha de gerentes e executivos de negócios e consumidores, como entusiastas e entusiastas de imagem digital e vídeo digital. A Abode categoriza seus produtos em quatro segmentos de negócios: Imagem e Vídeo Digital, Creative Professional, Documentos Inteligentes e Original Equipment Manufacturers (OEM) PostScript e Outros. Em 3 de dezembro de 2005, a Companhia concluiu a aquisição da Macromedia, Inc. Em 21 de abril de 2006, a empresa adquiriu a Trade and Technologies France. Em outubro de 2006, a Companhia adquiriu a Serious Magic Inc., fabricante de software de vídeo para os mercados de negócios, consumo e educação.
C6: #VALUE! | D6: {=_FV(C6,"Descrição")} -> A Zendesk, Inc. é uma empresa de desenvolvimento de software que fornece soluções de software como serviço (SaaS). A Companhia oferece uma variedade de soluções de produtos, que incluem os Zendesk Support, Zendesk Chat, Zendesk Talk, Zendesk Guide, Zendesk Gather, Zendesk Explore, Zendesk Sell e Zendesk Apps. O Zendesk Support é um sistema para rastrear, priorizar e resolver tíquetes de suporte ao cliente em vários canais. O Zendesk Chat é um software de chat e mensagens ao vivo. O Zendesk Talk é um software de call center baseado em nuvem. O Zendesk Guide é uma base de conhecimento que potencializa o autoatendimento do cliente e a produtividade do agente de suporte. O Zendesk Gather é um software de fórum da comunidade. O Zendesk Explore fornece análises para que organizações avaliem e melhorem toda a experiência do cliente. O Zendesk Sell é uma solução de produto de gerenciamento de relacionamento com o cliente (GRC) de vendas. As plataformas da Companhia incluem as Zendesk Sunshine, Sunshine Conversations, Zendesk Sunshine Developer Tools, Zendesk Apps, Zendesk API e outros.
B8: In Millions USD (exc Market Cap) | C8: =OP!E2 -> SALESFORCE, INC. (XNYS:CRM) | D8: =C2 -> #VALUE! | E8: =C3 -> #VALUE! | F8: =C4 -> #VALUE! | G8: =C5 -> #VALUE! | H8: =C6 -> #VALUE! | I8: AVERAGE | J8: Deviation from Average
B9: Company Info | I9: =IFERROR(AVERAGE(C9:H9),"") | L9: TRAFFIC
B10: Market Cap | C10: =OP!C22 -> #VALUE! | D10: 2350000 | E10: 150000 | F10: 295000 | G10: 234000 | H10: 9625 | I10: =IFERROR(AVERAGE(C10:H10),"") | J10: =SQRT((C10-I10)^2) -> #VALUE! | M10: Best Value
B11: Net Sales (current) | C11: =C56 -> 31352 | D11: =D56 -> 198270 | E11: =E56 -> 32974 | F11: =F56 -> 42440 | G11: =G56 -> 17430 | H11: =H56 -> 1.587 | I11: =IFERROR(AVERAGE(C11:H11),"") -> 53744.598 | J11: =SQRT((C11-I11)^2) -> 22392.598
B12: Profitability | I12: =IFERROR(AVERAGE(C12:H12),"") | M12: Middle Ground
B13: Sales Growth (ttm) | C13: =C56/C55-1 -> 0.18345161 | D13: =D56/D55-1 -> 0.17956071 | E13: =E56/E55-1 -> 0.041437686 | F13: =F56/F55-1 -> 0.048444873 | G13: =G56/G55-1 -> 0.10316456 | H13: =H56/H55-1 -> 0.19323308 | I13: =IFERROR(AVERAGE(C13:H13),"") -> 0.12488209 | J13: =SQRT((C13-I13)^2) -> 0.058569523
B14: Sales Growth (36m) | C14: =C56/C54-1 -> 0.83366476 | D14: =D56/D54-1 -> 0.38635807 | E14: =E56/E54-1 -> -0.014230194 | F14: =F56/F54-1 -> 0.086311047 | G14: =G56/G54-1 -> 0.35431235 | H14: =H56/H54-1 -> 0.54227405 | I14: =IFERROR(AVERAGE(C14:H14),"") -> 0.36478168 | J14: =SQRT((C14-I14)^2) -> 0.46888307 | M14: Worst Value
B15: Operating Margin | C15: =C59/C56 -> 0.032852769 | D15: =D59/D56 -> 0.42055278 | E15: =E59/E56 -> 0.15114939 | F15: =F59/F56 -> 0.30850613 | G15: =G59/G56 -> 0.33964429 | H15: =H59/H56 -> -0.16131065 | I15: =IFERROR(AVERAGE(C15:H15),"") -> 0.18189912 | J15: =SQRT((C15-I15)^2) -> 0.14904635
B16: Net Income Margin | C16: =C62/C56 -> 0.0066343455 | D16: =D62/D56 -> 0.36686337 | E16: =E62/E56 -> 0.055285983 | F16: =F62/F56 -> 0.20035344 | G16: =G62/G56 -> 0.2761331 | H16: =H62/H56 -> -0.17769376 | I16: =IFERROR(AVERAGE(C16:H16),"") -> 0.12126275 | J16: =SQRT((C16-I16)^2) -> 0.1146284
B17: Return on Equity (RoE) | C17: =C62/C74 -> 0.0035641461 | D17: =D62/D74 -> 0.43675469 | E17: =E62/E74 -> 0.042505071 | F17: =F62/F74 -> 7.9245107 | G17: =G62/G74 -> 0.3425379 | H17: =H62/H74 -> -0.58506224 | I17: =IFERROR(AVERAGE(C17:H17),"") -> 1.3608017 | J17: =SQRT((C17-I17)^2) -> 1.3572376
B18: Return on Invested Capital (ROIC) | C18: =(C62+C61)/(C73+C74) -> 0.0094622299 | D18: =(D62+D61)/(D73+D74) -> 0.22945949 | E18: =(E62+E61)/(E73+E74) -> 0.042824495 | F18: =(F62+F61)/(F73+F74) -> 0.067910376 | G18: =(G62+G61)/(G73+G74) -> 0.31893599 | H18: =(H62+H61)/(H73+H74) -> -0.11179111 | I18: =IFERROR(AVERAGE(C18:H18),"") -> 0.092800245 | J18: =SQRT((C18-I18)^2) -> 0.083338015
B19: Solvency | I19: =IFERROR(AVERAGE(C19:H19),"")
B20: Debt/Assets | C20: =C73/C70 -> 0.11524649 | D20: =D73/D70 -> 0.54352045 | E20: =E73/E70 -> 0.44308679 | F20: =F73/F70 -> 0.99201536 | G20: =G73/G70 -> 0.17055034 | H20: =H73/H70 -> 0.80334557 | I20: =IFERROR(AVERAGE(C20:H20),"") -> 0.51129417 | J20: =SQRT((C20-I20)^2) -> 0.39604768
B21: Net Debt/EBITDA | C21: =(C73-C65)/C58 -> -0.23820704 | D21: =(D73-D65)/D58 -> 1.8779233 | E21: =(E73-E65)/E58 -> 3.193355 | F21: =(F73-F65)/F58 -> 5.9729441 | G21: =(G73-G65)/G58 -> -0.33562744 | H21: =(H73-H65)/H58 -> -13.45045 | I21: =IFERROR(AVERAGE(C21:H21),"") -> -0.49667707 | J21: =SQRT((C21-I21)^2) -> 0.25847003
B22: Interest Coverage Ratio | C22: =-C58/C60 -> 35.763359 | D22: =-D58/D60 -> -47.588948 | E22: =-E58/E60 -> -3.2617935 | F22: =-F58/F60 -> -5.3463623 | G22: =-G58/G60 -> -38.919643 | H22: =-H58/H60 -> -0.43359375 | I22: =IFERROR(AVERAGE(C22:H22),"") -> -9.964497 | J22: =SQRT((C22-I22)^2) -> 45.727856
B23: Liquidity
B24: Current Ratio | C24: =C68/C72 -> 1.0194662 | D24: =D68/D72 -> 1.784607 | E24: =E68/E72 -> 1.0075697 | F24: =F68/F72 -> 0.90965786 | G24: =G68/G72 -> 1.1067913 | H24: =H68/H72 -> 1.5565313 | I24: =IFERROR(AVERAGE(C24:H24),"") -> 1.2307706 | J24: =SQRT((C24-I24)^2) -> 0.21130433
B25: Quick Ratio | C25: =(C65+C66)/C72 -> 0.96709281 | D25: =(D65+D66)/D72 -> 0.6120191 | E25: =(E65+E66)/E72 -> 0.88983733 | F25: =(F65+F66)/F72 -> 1.2255522 | G25: =(G65+G66)/G72 -> 1.00406 | H25: =(H65+H66)/H72 -> 0.82217344 | I25: =IFERROR(AVERAGE(C25:H25),"") -> 0.92012248 | J25: =SQRT((C25-I25)^2) -> 0.046970328
B26: Activity | I26: =IFERROR(AVERAGE(C26:H26),"")
B27: Inventory Turnover | C27: =IFERROR(C57/C67,"No Inventory") -> No Inventory | D27: =IFERROR(D57/D67,"No Inventory") -> 16.742384 | E27: =IFERROR(E57/E67,"No Inventory") -> No Inventory | F27: =IFERROR(F57/F67,"No Inventory") -> No Inventory | G27: =IFERROR(G57/G67,"No Inventory") -> No Inventory | H27: =IFERROR(H57/H67,"No Inventory") -> No Inventory | I27: =IFERROR(AVERAGE(C27:H27),"") -> 16.742384 | J27: =SQRT((C27-I27)^2) -> #VALUE!
B28: Acc. Receivable Turnover | C28: =C56/C66 -> 2.5019552 | D28: =D56/D66 -> 4.4795644 | E28: =E56/E66 -> 4.7369631 | F28: =F56/F66 -> 6.1373825 | G28: =G56/G66 -> 8.440678 | H28: =H56/H66 -> 5.8131868 | I28: =IFERROR(AVERAGE(C28:H28),"") -> 5.3516217 | J28: =SQRT((C28-I28)^2) -> 2.8496665
A29: Price/Sales | B29: Payables Turnover | C29: =C57/C71 -> #DIV/0! | D29: =D57/D71 -> 1.8575071 | E29: =E57/E71 -> 3.4475309 | F29: =F57/F71 -> 4.1645686 | G29: =G57/G71 -> #DIV/0! | H29: =H57/H71 -> 0 | I29: =IFERROR(AVERAGE(C29:H29),"") | J29: =SQRT((C29-I29)^2) -> #DIV/0!
B30: Fixed Asset Turnover | C30: =C56/C69 -> 4.756068 | D30: =D56/D69 -> 1.0159565 | E30: =E56/E69 -> 0.57600531 | F30: =F56/F69 -> 0.37431646 | G30: =G56/G69 -> 0.95932633 | H30: =H56/H69 -> 1.5377907 | I30: =IFERROR(AVERAGE(C30:H30),"") -> 1.5365772 | J30: =SQRT((C30-I30)^2) -> 3.2194908
B31: Total Asset Turnover | C31: =C56/C70 -> 0.31717063 | D31: =D56/D70 -> 0.5434437 | E31: =E56/E70 -> 0.42816704 | F31: =F56/F70 -> 0.31581376 | G31: =G56/G70 -> 0.64163446 | H31: =H56/H70 -> 0.64749082 | I31: =IFERROR(AVERAGE(C31:H31),"") -> 0.48228673 | J31: =SQRT((C31-I31)^2) -> 0.1651161
B32: Valuation | I32: =IFERROR(AVERAGE(C32:H32),"")
B33: Price/Earnings | C33: =C10/C62 -> #VALUE! | D33: =D10/D62 -> 32.307735 | E33: =E10/E62 -> 82.281953 | F33: =F10/F62 -> 34.693638 | G33: =G10/G62 -> 48.618325 | H33: =H10/H62 -> -34131.206 | I33: =IFERROR(AVERAGE(C33:H33),"") | J33: =SQRT((C33-I33)^2) -> #VALUE!
B34: Price/Sales | C34: =C10/C56 -> #VALUE! | D34: =D10/D56 -> 11.852524 | E34: =E10/E56 -> 4.5490386 | F34: =F10/F56 -> 6.9509896 | G34: =G10/G56 -> 13.425129 | H34: =H10/H56 -> 6064.9023 | I34: =IFERROR(AVERAGE(C34:H34),"") | J34: =SQRT((C34-I34)^2) -> #VALUE!
B35: Price/Book | C35: =C10/C74 -> #VALUE! | D35: =D10/D74 -> 14.110555 | E35: =E10/E74 -> 3.4974003 | F35: =F10/F74 -> 274.9301 | G35: =G10/G74 -> 16.653619 | H35: =H10/H74 -> 19968.88 | I35: =IFERROR(AVERAGE(C35:H35),"") | J35: =SQRT((C35-I35)^2) -> #VALUE!
B36: EV/Sales | C36: =(C73+C10-C65)/C56 -> #VALUE! | D36: =(D73+D10-D65)/D56 -> 12.782403 | E36: =(E73+E10-E65)/E56 -> 5.2923212 | F36: =(F73+F10-F65)/F56 -> 9.5882893 | G36: =(G73+G10-G65)/G56 -> 13.341193 | H36: =(H73+H10-H65)/H56 -> 6065.8431 | I36: =IFERROR(AVERAGE(C36:H36),"") | J36: =SQRT((C36-I36)^2) -> #VALUE!
B37: EV/EBITDA | C37: =(C73+C10-C65)/C58 -> #VALUE! | D37: =(D73+D10-D65)/D58 -> 25.814527 | E37: =(E73+E10-E65)/E58 -> 22.737329 | F37: =(F73+F10-F65)/F58 -> 21.715513 | G37: =(G73+G10-G65)/G58 -> 53.34641 | H37: =(H73+H10-H65)/H58 -> -86725.162 | I37: =IFERROR(AVERAGE(C37:H37),"") | J37: =SQRT((C37-I37)^2) -> #VALUE!
B38: Stock Info | I38: =IFERROR(AVERAGE(C38:H38),"")
B39: Float | C39: =OP!M20 -> 0.96975334 | D39: =7.42/7.43 -> 0.9986541 | E39: =1.03/1.17 -> 0.88034188 | F39: =1.59/2.47 -> 0.6437247 | G39: =454.32/455.3 -> 0.99784757 | I39: =IFERROR(AVERAGE(C39:H39),"") -> 0.89806432 | J39: =SQRT((C39-I39)^2) -> 0.071689021
B40: b (Yahoo) | C40: =OP!M22 -> 1.19 | D40: 0.9 | E40: 0.98 | F40: 1.02 | G40: 1.34 | I40: =IFERROR(AVERAGE(C40:H40),"") -> 1.086 | J40: =SQRT((C40-I40)^2) -> 0.104
B41: Dividend Yield (yahoo finance) | C41: =OP!M32 -> #VALUE! | D41: 0.00092 | E41: 0.0171 | F41: 0.0148 | G41: 0 | I41: =IFERROR(AVERAGE(C41:H41),"") | J41: =SQRT((C41-I41)^2) -> #VALUE!
B42: Stock Performance
B43: 1y | C43: 0.423 | D43: 0.3172 | E43: 0.5762 | F43: 0.7868 | G43: 0.8433 | I43: =IFERROR(AVERAGE(C43:H43),"") -> 0.5893 | J43: =SQRT((C43-I43)^2) -> 0.1663
B44: 3y | C44: -0.2204 | D44: 0.7553 | E44: -0.1379 | F44: 0.8694 | G44: 0.0488 | I44: =IFERROR(AVERAGE(C44:H44),"") -> 0.26304 | J44: =SQRT((C44-I44)^2) -> 0.48344
B45: Current Price | C45: 207 | D45: {=_FV(D8,"Preço")} -> 312.78 | E45: {=_FV(E8,"Preço")} -> 130.49 | F45: {=_FV(F8,"Preço")} -> 104.2 | G45: {=_FV(G8,"Preço")} -> 52.03 | H45: {=_FV(H8,"Preço")} -> 27.31 | I45: =IFERROR(AVERAGE(C45:H45),"") -> 138.96833 | J45: =SQRT((C45-I45)^2) -> 68.031667
B46: Average Target Price | C46: 252.88 | D46: 374.69 | E46: 153.4 | F46: 130.47 | G46: 600 | I46: =IFERROR(AVERAGE(C46:H46),"") -> 302.288 | J46: =SQRT((C46-I46)^2) -> 49.408
B47: Upside/Downside | C47: =C46/C45-1 -> 0.22164251 | D47: =D46/D45-1 -> 0.19793465 | E47: =E46/E45-1 -> 0.17556901 | F47: =F46/F45-1 -> 0.25211132 | G47: =G46/G45-1 -> 10.531809 | H47: =H46/H45-1 -> -1 | I47: =IFERROR(AVERAGE(C47:H47),"") -> 1.7298443 | J47: =SQRT((C47-I47)^2) -> 1.5082018
B48: Extra | I48: =IFERROR(AVERAGE(C48:H48),"")
B49: 3y Operating Cash Flow | C49: =(Inputs!B59-Inputs!E59)/Inputs!E59 -> 0.64188409 | I49: =IFERROR(AVERAGE(C49:H49),"") -> 0.64188409 | J49: =SQRT((C49-I49)^2) -> 0
B50: R&D/Net Sales | C50: =C63/C11 -> 0.16123373 | D50: =D63/D11 -> 0.12362939 | E50: =E63/E11 -> 0.18699581 | F50: =F63/F11 -> 0.20318096 | G50: =G63/G11 -> 0.1713712 | H50: =H63/H11 -> 0 | I50: =IFERROR(AVERAGE(C50:H50),"") -> 0.14106852 | J50: =SQRT((C50-I50)^2) -> 0.020165216
B52: Financial Data | C52: =OP!E2 -> SALESFORCE, INC. (XNYS:CRM) | D52: =D8 -> #VALUE! | E52: =E8 -> #VALUE! | F52: =F8 -> #VALUE! | G52: =G8 -> #VALUE! | H52: =H8 -> #VALUE!
B53: IS
B54: Net Sales (36m ago) | C54: ='Fin. Data'!E5 -> 17098 | D54: 143015 | E54: 33450 | F54: 39068 | G54: 12870 | H54: 1.029
B55: Net Sales (12m ago) | C55: ='Fin. Data'!C5 -> 26492 | D55: 168088 | E55: 31662 | F55: 40479 | G55: 15800 | H55: 1.33
B56: Net Sales (current) | C56: ='Fin. Data'!B5 -> 31352 | D56: 198270 | E56: 32974 | F56: 42440 | G56: 17430 | H56: 1.587
B57: COGS | C57: ='Fin. Data'!B5-'Fin. Data'!B7 -> 8360 | D57: 62650 | E57: 8936 | F57: 13564 | G57: 2165
B58: EBITDA | C58: ='Fin. Data'!B19 -> 4685 | D58: 98176 | E58: 7675 | F58: 18739 | G58: 4359 | H58: -0.111
B59: Operating Income | C59: ='Fin. Data'!B11 -> 1030 | D59: 83383 | E59: 4984 | F59: 13093 | G59: 5920 | H59: -0.256
B60: Net Financial Cost | C60: ='Fin. Data'!B14 -> -131 | D60: 2063 | E60: 2353 | F60: 3505 | G60: 112 | H60: -0.256
B61: Taxes | C61: ='Fin. Data'!B21 -> 452 | D61: 10978 | E61: 1475 | F61: 623 | G61: 1146 | H61: 0.008
B62: Net Income | C62: ='Fin. Data'!B23 -> 208 | D62: 72738 | E62: 1823 | F62: 8503 | G62: 4813 | H62: -0.282
B63: R&D | C63: 5055 | D63: 24512 | E63: 6166 | F63: 8623 | G63: 2987
B64: BS
B65: Cash & Eq. | C65: ='Fin. Data'!B39 -> 12508 | D65: 13931 | E65: 9614 | F65: 21383 | G65: 6096 | H65: 0.476
B66: Acc. Receivables | C66: ='Fin. Data'!B40 -> 12531 | D66: 44261 | E66: 6961 | F66: 6915 | G66: 2065 | H66: 0.273
B67: Inventory | C67: ='Fin. Data'!B41 -> 0 | D67: 3742 | E67: 0 | F67: 0 | G67: 0 | H67: 0
B68: Current Assets | C68: =Inputs!B27 -> 26395 | D68: 169684 | E68: 18768 | F68: 21004 | G68: 8996 | H68: 1.418
B69: Fixed Assets | C69: ='Fin. Data'!B42 -> 6592 | D69: 195156 | E69: 57246 | F69: 113380 | G69: 18169 | H69: 1.032
B70: Total Assets | C70: ='Fin. Data'!B44 -> 98849 | D70: 364840 | E70: 77012 | F70: 134383 | G70: 27165 | H70: 2.451
B71: Acc. Payable | C71: =Inputs!B43 -> 0 | D71: 33728 | E71: 2592 | F71: 3257 | H71: 0.237
B72: Current Liabilities | C72: =Inputs!B42 -> 25891 | D72: 95082 | E72: 18627 | F72: 23090 | G72: 8128 | H72: 0.911
B73: Total Debt | C73: ='Fin. Data'!B58 -> 11392 | D73: =364840-D74 -> 198298 | E73: =77012-E74 -> 34123 | F73: =F70-F74 -> 133310 | G73: 4633 | H73: =H70-H74 -> 1.969
B74: Total Equity | C74: ='Fin. Data'!B64 -> 58359 | D74: 166542 | E74: 42889 | F74: 1073 | G74: 14051 | H74: 0.482

Sheet ESG
B1: Company GICS Sector: | T1: Yes
B2: Information Technology | C2: <- Select Industry | T2: No
B3: ESG Analysis | K3: Relative ESG Analysis
B4: Parameters | C4: Impact | D4: Do they report? | E4: Ranking | F4: Mitigation Plan | G4: Traffic Lights | H4: Improvement over time? | I4: Targets / Goals? | J4: Comments | K4: Parameters | L4: #VALUE! | M4: =Peers!D8 -> #VALUE! | N4: =Peers!E8 -> #VALUE! | O4: =Peers!F8 -> #VALUE! | P4: =Peers!G8 -> #VALUE! | Q4: =Peers!H8 -> #VALUE! | R4: AVERAGE
B5: Environmental | K5: Ratios
A6: 1 | B6: CO2 Direct Emissions | C6: =VLOOKUP($B$2,'Sector Impact'!$K$4:$AA$16,A6+1,FALSE) -> Medium | D6: Yes | E6: Medium High | F6: Yes | H6: Yes. 1. During the last few years they have reduced their net emissions measured by metrics tons of CO2. In 2021 they reduced about 4,5%, in 2022 20,3% and in 2023 44% | I6: They have both a medium term and long term, the first to reduce carbon emissions up to 50% and and the latter up to +90%. Furthermore the data shows they are in a successful path | J6: - | K6: CO2 Emissions/$M Sales | L6: =L12/L$11 -> 42.676703 | M6: =M12/M$11 -> 65.567156 | N6: =N12/N$11 -> 2.5777886 | O6: =O12/O$11 -> 26.263525 | P6: =P12/P$11 -> 30.245209 | Q6: =Q12/Q$11 -> 31073.724 | R6: =IFERROR(AVERAGE(L6:Q6),"") -> 5206.8424
A7: 2 | B7: Total Water Consumption | C7: =VLOOKUP($B$2,'Sector Impact'!$K$4:$AA$16,A7+1,FALSE) -> Low | F7: No | G7: grg | I7: SF considers water consumption to be negligible, since we do not consume water for any products or processes and almost all water is discharged except for trace amounts consumed in the offices. | K7: Water Consumption/$M Sales | L7: =L13/L$11 -> 1.770222e-05 | M7: =M13/M$11 -> 7.7167499e-05 | N7: =N13/N$11 -> 2.6627039e-05 | O7: =O13/O$11 -> 7.5459052e-06 | P7: =P13/P$11 -> 1.6221687e-05 | Q7: =+IFERROR(Q13/Q$11,"N/A") -> N/A | R7: =IFERROR(AVERAGE(L7:Q7),"") -> 2.905287e-05
A8: 3 | B8: Total Energy Consumption | C8: =VLOOKUP($B$2,'Sector Impact'!$K$4:$AA$16,A8+1,FALSE) -> High | D8: Yes | E8: "Best in class" | F8: Yes | H8: Over time they have been increasing their energy use. Although, the energy they use is entierly powered by renewable sources | I8: They have met their main goal this year by achieving 100% renewable energy. | J8: - | K8: Energy Consumption/$M Sales | L8: =L14/L$11 -> 0.02771753 | M8: =M14/M$11 -> 6.808897e-05 | N8: =N14/N$11 -> 0.027476193 | O8: =O14/O$11 -> 0.055225259 | P8: =P14/P$11 -> 0.011846586 | Q8: =Q14/Q$11 -> 4.6616257 | R8: =IFERROR(AVERAGE(L8:Q8),"") -> 0.79732656
A9: 4 | B9: Waste Management | C9: =VLOOKUP($B$2,'Sector Impact'!$K$4:$AA$16,A9+1,FALSE) -> Low | H9: As a software technology company, their operational waste footprint is relatively small. | I9: They provide recycling and compost collection where local infrastructure allows. They offer reusable dishware, cups and cutlery, bulk snack options, and employee fridges for storing leftovers from catered meetings. Furthermore, they also periodically engage in employee-facing education campaigns on proper waste sorting and waste reduction best practices. | K9: Waste Production/$M Sales | L9: =IFERROR(L15/L$11,"N/A") -> N/A | M9: =M14/M$11 -> 6.808897e-05 | N9: =N15/N$11 -> 0.00030326924 | O9: =IFERROR(O15/O$11,"N/A") -> N/A | P9: =P15/P$11 -> 0.00011428571 | Q9: =IFERROR(Q15/Q$11,"N/A") -> N/A | R9: =IFERROR(AVERAGE(L9:Q9),"") -> 0.00016188131
A10: 5 | B10: Land Degradation/Deforestation/Biodiversity loss/Animal sufering/… | C10: =VLOOKUP($B$2,'Sector Impact'!$K$4:$AA$16,A10+1,FALSE) -> Low | H10: Since their ambitious goal was announced, we have supported 20+ projects throughout the world and funded over 40 million trees | I10: Salesforce set a goal to support and mobilize the conservation, restoration, and growth of 100 million trees by the end of 2030. | K10: Inputs
B11: Social | K11: Net Sales ($M) | L11: 31352 | M11: =Peers!D56 -> 198270 | N11: =Peers!E56 -> 32974 | O11: =Peers!F56 -> 42440 | P11: =Peers!G56 -> 17430 | Q11: =Peers!H56 -> 1.587
A12: 6 | B12: Employee Turnover % | C12: =VLOOKUP($B$2,'Sector Impact'!$K$4:$AA$16,A12+1,FALSE) -> Low | H12: About 1/3 of open positions are filled by internal candidates. | I12: - | K12: CO2 Emissions Total (metric tonnes) | L12: 1338000 | M12: 13000000 | N12: 85000 | O12: 1114624 | P12: 527174 | Q12: 49314
A13: 7 | B13: Salaries & Compensation | C13: =VLOOKUP($B$2,'Sector Impact'!$K$4:$AA$16,A13+1,FALSE) -> Low | H13: They have had improvements over time. One of the last iniciatives was thev equal pay startegy, where they try to mitigate any salary disparity based in any factor related to gender, race,, sexual orientation and so on. | I13: - | K13: Water Consumption Total (millions m3) | L13: 0.555 | M13: 15.3 | N13: 0.878 | O13: 0.32024822 | P13: 0.282744 | Q13: Not disclosed
A14: 8 | B14: Reputation | C14: =VLOOKUP($B$2,'Sector Impact'!$K$4:$AA$16,A14+1,FALSE) -> Low | H14: - | I14: - | K14: Energy Consumption Total (Gigawatts) | L14: 869 | M14: 13.5 | N14: 906 | O14: 2343.76 | P14: 206.486 | Q14: 7.398
A15: 9 | B15: Discrimination Events | C15: =VLOOKUP($B$2,'Sector Impact'!$K$4:$AA$16,A15+1,FALSE) -> Low | K15: Waste Production Total (Tonnes) | L15: Near zero | M15: 13.403 | N15: 10 | O15: Near zero | P15: 1.992 | Q15: Not disclosed
A16: 10 | B16: Work Safety | C16: =VLOOKUP($B$2,'Sector Impact'!$K$4:$AA$16,A16+1,FALSE) -> High | D16: Yes | E16: Medium High | F16: Yes | H16: - | I16: - | J16: They implement a health and safety management system which ensures open communication, proactive identification and management of health and safety risks, and compliance with applicable laws and regulations. | K16: ESG Scores
A17: 11 | B17: Damage to consumer health | C17: =VLOOKUP($B$2,'Sector Impact'!$K$4:$AA$16,A17+1,FALSE) -> Low | H17: - | I17: - | J17: safety management system which ensures open communication, proactive identification and | K17: Refinitiv
A18: 12 | B18: PXP? | C18: =VLOOKUP($B$2,'Sector Impact'!$K$4:$AA$16,A18+1,FALSE) -> Low | J18: management of health and safety risks, and compliance with applicable laws and regulations | K18: Sustainalytics | L18: 14.9 | M18: 15.1 | N18: 12.7 | O18: 13.9 | P18: 13.1
A19: 13 | B19: Supply chain | C19: =VLOOKUP($B$2,'Sector Impact'!$K$4:$AA$16,A19+1,FALSE) -> Low | K19: ISS
A20: 14 | B20: Community involvement | C20: =VLOOKUP($B$2,'Sector Impact'!$K$4:$AA$16,A20+1,FALSE) -> Low | K20: CDP | L20: A- | M20: A | N20: A- | O20: B | P20: A | Q20: -
A21: 15 | B21: Public Sector | C21: =VLOOKUP($B$2,'Sector Impact'!$K$4:$AA$16,A21+1,FALSE) -> Medium | D21: No
A22: 16 | B22: Litigation | C22: =VLOOKUP($B$2,'Sector Impact'!$K$4:$AA$16,A22+1,FALSE) -> Very High | D22: No
B23: Corporate Governance | K23: PARAMETERS
A24: 17 | B24: Diversity (Gender, Age, Industry, Region) | E24: "Best in class" | F24: Yes | H24: Over the last 3 years SF has been growing its workforce diversity. The numbers show that the percentage of women, and other ethnicities has been gradually growing. | I24: Keep on the diversification | K24: IMPACT | L24: RANKING | M24: MITIGATION PLAN | O24: TRAFFIC
A25: 18 | B25: % Independence | E25: Medium | J25: A majority of our board members are independent of Salesforce and its management | K25: Low | L25: "Best in class" | M25: Is there evidence of a plan/program ?
A26: 19 | B26: average time as independent directors | E26: Medium | J26: Board average tenure has been decreasing | K26: Medium | L26: Medium High
A27: 20 | B27: Recent departures of directors / C-level executives? | K27: High | L27: Medium
A28: 21 | B28: CEO/Chairman duality | E28: "Best in class" | J28: Management and board are Independent | K28: Very high | L28: "Villain"
A29: 22 | B29: Transparency (ESG, segments, acquisitions, other) | E29: Medium High
A30: 23 | B30: Time taken to report after the end of the quarter / year | E30: Medium | J30: About 2-3 months
A31: 24 | B31: Additional participation of the CEO in other boards or excessive participation of Ch.
A32: 25 | B32: Audit / Consulting | D32: Yes | E32: Medium High
A33: 26 | B33: ESG-compensation related | D33: No
A34: 27 | B34: Management compensation schemes | D34: Yes

Sheet DCF
A1: VALUATION MODEL
G3: Short Term | K3: Long Term
A4: Section | B4: Line # | C4: ITEM | D4: 2020 (Real) | E4: 2021 (Real) | F4: 2022 (Real) | G4: 2023 | H4: =G4+1 -> 2024 | I4: =H4+1 -> 2025 | J4: =I4+1 -> 2026 | K4: =J4+1 -> 2027 | L4: =K4+1 -> 2028 | M4: =L4+1 -> 2029 | N4: =M4+1 -> 2030 | O4: =N4+1 -> 2031 | ... AF4: =AE4+1 -> 2048
A5: INCOME STATEMENT | B5: 1 | C5: Growth | D5: ='Fin. Data'!D6 -> 0.24295239 | E5: =+E6/D6-1 -> 0.24656503 | F5: =+F6/E6-1 -> 0.18345161 | G5: =+G6/F6-1 -> 0.24408539 | H5: =+H6/G6-1 -> 0.19408539 | I5: =+I6/H6-1 -> 0.16908539 | J5: =+J6/I6-1 -> 0.13908539 | K5: =+K6/J6-1 -> 0.11908539 | L5: =+L6/K6-1 -> 0.11408539 | ... AF5: =+AF6/AE6-1 -> 0.02
B6: 2 | C6: Revenues/Sales | D6: =Inputs!D6 -> 21252 | E6: =Inputs!C6 -> 26492 | F6: =Inputs!B6 -> 31352 | G6: =+Assumptions!I41 -> 39004.565 | H6: =+Assumptions!J41 -> 46574.782 | I6: =+Assumptions!K41 -> 54449.897 | J6: =+Assumptions!L41 -> 62023.082 | K6: =+Assumptions!M41 -> 69409.125 | L6: =+Assumptions!N41 -> 77327.692 | M6: =+Assumptions!O41 -> 86072.325 | N6: =+Assumptions!P41 -> 95719.775 | ... AF6: =+Assumptions!AH41 -> 380527.31
B7: 3 | C7: EBIT/Operating Margin | D7: =D8/D6 -> 0.22619048 | E7: =E8/E6 -> 0.18231919 | F7: =F8/F6 -> 0.14180913 | G7: 0.1 | H7: 0.09 | I7: 0.09 | J7: 0.09 | K7: 0.09 | L7: 0.09 | M7: =+_xlfn.FORECAST.LINEAR(M4,'Fin. Data'!$B$12:$M$12,'Fin. Data'!$B$4:$M$4) -> 0.093040236 | N7: =+_xlfn.FORECAST.LINEAR(N4,'Fin. Data'!$B$12:$M$12,'Fin. Data'!$B$4:$M$4) -> 0.10002407 | O7: =+_xlfn.FORECAST.LINEAR(O4,'Fin. Data'!$B$12:$M$12,'Fin. Data'!$B$4:$M$4) -> 0.10700791 | P7: =+_xlfn.FORECAST.LINEAR(P4,'Fin. Data'!$B$12:$M$12,'Fin. Data'!$B$4:$M$4) -> 0.11399175 | Q7: =+_xlfn.FORECAST.LINEAR(Q4,'Fin. Data'!$B$12:$M$12,'Fin. Data'!$B$4:$M$4) -> 0.12097559 | R7: =+_xlfn.FORECAST.LINEAR(R4,'Fin. Data'!$B$12:$M$12,'Fin. Data'!$B$4:$M$4) -> 0.12795943 | S7: =+_xlfn.FORECAST.LINEAR(S4,'Fin. Data'!$B$12:$M$12,'Fin. Data'!$B$4:$M$4) -> 0.13494327 | T7: =+_xlfn.FORECAST.LINEAR(T4,'Fin. Data'!$B$12:$M$12,'Fin. Data'!$B$4:$M$4) -> 0.14192711 | ... AF7: =+_xlfn.FORECAST.LINEAR(AF4,'Fin. Data'!$B$12:$M$12,'Fin. Data'!$B$4:$M$4) -> 0.22573317
B8: 4 | C8: EBITDA | D8: =+D12+D9+D10 -> 4807 | E8: =+E12+E9+E10 -> 4830 | F8: =+F12+F9+F10 -> 4446 | G8: =G7*G6+G9+G10 -> 6827.0785 | H8: =H7*H6+H9+H10 -> 7701.3378 | I8: =I7*I6+I9+I10 -> 9106.2327 | J8: =J7*J6+J9+J10 -> 10601.66 | K8: =K7*K6+K9+K10 -> 10392.55 | L8: =L7*L6+L9+L10 -> 11747.525 | M8: =M7*M6+M9+M10 -> 13511.803 | N8: =N7*N6+N9+N10 -> 15874.399 | ... AF8: =AF7*AF6+AF9+AF10 -> 130070.89
B9: 5a | C9: (Dep) | D9: 2846 | E9: 3298 | F9: 3786 | G9: =$D$53*DCF!F40 -> 2926.622 | H9: =$D$53*DCF!G40 -> 3509.6075 | I9: =$D$53*DCF!H40 -> 4205.742 | J9: =$D$53*DCF!I40 -> 5019.5826 | K9: =$E$53*DCF!J40 -> 4145.7286 | L9: =$E$53*DCF!K40 -> 4788.0325 | M9: =$E$53*DCF!L40 -> 5503.614 | N9: =$E$53*DCF!M40 -> 6300.1173 | O9: =$E$53*DCF!N40 -> 7185.8969 | P9: =$E$53*DCF!O40 -> 8170.0738 | Q9: =$E$53*DCF!P40 -> 9262.5941 | R9: =$E$53*DCF!Q40 -> 10475.292 | ... AF9: =$E$53*DCF!AE40 -> 44173.254 | AG9: =SUM(D9:AF9) -> 443574.28
B10: 5b | C10: Amort | G10: =F38*$D$54 -> 0 | H10: =G38*$D$54 -> 0 | I10: =H38*$D$54 -> 0 | J10: =I38*$D$54 -> 0 | K10: =J38*$E$54 -> 0 | L10: =K38*$E$54 -> 0 | M10: =L38*$E$54 -> 0 | N10: =M38*$E$54 -> 0 | O10: =N38*$E$54 -> 0 | P10: =O38*$E$54 -> 0 | Q10: =P38*$E$54 -> 0 | R10: =Q38*$E$54 -> 0 | ... AF10: =AE38*$E$54 -> 0
B11: 5c | C11: (Stock based compensation) | D11: =D20 -> 1785 | E11: =E20 -> 2190 | F11: =F20 -> 2779 | G11: =G6*$D$55 -> 3319.2527 | H11: =H6*$D$55 -> 3963.4711 | I11: =I6*$D$55 -> 4633.6362 | J11: =J6*$D$55 -> 5278.1073 | K11: =K6*$E55 -> 4511.5931 | L11: =L6*$E55 -> 5026.3 | M11: =M6*$E55 -> 5594.7011 | N11: =N6*$E55 -> 6221.7854 | O11: =O6*$E55 -> 6912.9348 | P11: =P6*$E55 -> 7673.948 | Q11: =Q6*$E55 -> 8518.0823 | R11: =R6*$E55 -> 9455.0713 | ... AF11: =AF6*$E55 -> 24734.275
B12: 6 | C12: EBIT | D12: =D15-D14-D13 -> 1961 | E12: =E15-E14-E13 -> 1532 | F12: =F15-F14-F13 -> 660 | G12: =+G8-G9-G10-G11 -> 581.20386 | H12: =+H8-H9-H10-H11 -> 228.25922 | I12: =+I8-I9-I10-I11 -> 266.85452 | J12: =+J8-J9-J10-J11 -> 303.97009 | K12: =+K8-K9-K10-K11 -> 1735.2281 | L12: =+L8-L9-L10-L11 -> 1933.1923 | M12: =+M8-M9-M10-M11 -> 2413.4883 | N12: =+N8-N9-N10-N11 -> 3352.4965 | ... AF12: =+AF8-AF9-AF10-AF11 -> 61163.359
B13: 7 | C13: (Net financing cost) | D13: ='Fin. Data'!D14 -> -64 | E13: ='Fin. Data'!C14 -> -227 | F13: ='Fin. Data'!B14 -> -131 | G13: =F43*$D$58-F44*$D$57 -> 376.07984 | H13: =G43*$D$58-G44*$D$57 -> 850.63014 | I13: =H43*$D$58-H44*$D$57 -> 1414.0304 | J13: =I43*$D$58-I44*$D$57 -> 2037.3424 | K13: =J43*$E$58-J44*$E$57 -> 1918.6266 | L13: =K43*$E$58-K44*$E$57 -> 2467.185 | M13: =L43*$E$58-L44*$E$57 -> 3111.7727 | N13: =M43*$E$58-M44*$E$57 -> 3835.0547 | O13: =N43*$E$58-N44*$E$57 -> 4767.6657 | P13: =O43*$E$58-O44*$E$57 -> 5870.0993 | Q13: =P43*$E$58-P44*$E$57 -> 7170.5368 | R13: =Q43*$E$58-Q44*$E$57 -> 8698.4132 | ... AF13: =AE43*$E$58-AE44*$E$57 -> 76905.424
B14: 8 | C14: Other income/(cost) | D14: ='Fin. Data'!D15 -> 664 | E14: ='Fin. Data'!C15 -> 227 | F14: ='Fin. Data'!B15 -> 131 | G14: =AVERAGE(D14:F14)*(1+G5) -> 423.81842 | H14: =AVERAGE(E14:G14)*(1+H5) -> 311.18599 | I14: =AVERAGE(F14:H14)*(1+I5) -> 337.4777 | J14: =AVERAGE(G14:I14)*(1+J5) -> 407.21624 | K14: =AVERAGE(H14:J14)*(1+K5) -> 393.87327 | L14: =AVERAGE(I14:K14)*(1+L5) -> 422.82036 | M14: =AVERAGE(J14:L14)*(1+M5) -> 454.1054 | N14: =AVERAGE(K14:M14)*(1+N5) -> 471.07901 | ... AF14: =AVERAGE(AC14:AE14)*(1+AF5) -> 918.14991
B15: 9 | C15: Earnings before taxes | D15: =+D17+D16 -> 2561 | E15: =+E17+E16 -> 1532 | F15: =+F17+F16 -> 660 | G15: =G12+G13+G14 -> 1381.1021 | H15: =H12+H13+H14 -> 1390.0753 | I15: =I12+I13+I14 -> 2018.3626 | J15: =J12+J13+J14 -> 2748.5287 | K15: =K12+K13+K14 -> 4047.728 | L15: =L12+L13+L14 -> 4823.1977 | M15: =M12+M13+M14 -> 5979.3665 | N15: =N12+N13+N14 -> 7658.6303 | ... AF15: =AF12+AF13+AF14 -> 138986.93
B16: 10 | C16: (Income tax) | D16: ='Fin. Data'!D21 -> -1511 | E16: ='Fin. Data'!C21 -> 88 | F16: ='Fin. Data'!B21 -> 452 | G16: =(1*$D$56)*G15 -> 414.33064 | H16: =(1*$D$56)*H15 -> 417.0226 | I16: =(1*$D$56)*I15 -> 605.50878 | J16: =(1*$D$56)*J15 -> 824.55861 | K16: =(1*$E$56)*K15 -> 1649.4492 | L16: =(1*$E$56)*L15 -> 1965.4531 | M16: =(1*$E$56)*M15 -> 2436.5918 | N16: =(1*$E$56)*N15 -> 3120.8918 | O16: =(1*$E$56)*O15 -> 3966.8398 | P16: =(1*$E$56)*P15 -> 4963.832 | Q16: =(1*$E$56)*Q15 -> 6136.9642 | R16: =(1*$E$56)*R15 -> 7514.8686 | ... AF16: =(1*$E$56)*AF15 -> 56637.175
B17: 11 | C17: Net income | D17: ='Fin. Data'!D23 -> 4072 | E17: ='Fin. Data'!C23 -> 1444 | F17: ='Fin. Data'!B23 -> 208 | G17: =+G15-G16 -> 966.77149 | H17: =+H15-H16 -> 973.05274 | I17: =+I15-I16 -> 1412.8538 | J17: =+J15-J16 -> 1923.9701 | K17: =+K15-K16 -> 2398.2789 | L17: =+L15-L16 -> 2857.7446 | M17: =+M15-M16 -> 3542.7746 | N17: =+N15-N16 -> 4537.7384 | ... AF17: =+AF15-AF16 -> 82349.758
A19: CASH FLOW STATEMENT | B19: 12 | C19: Operating cash flows before WK | D19: =+D22-(D21+D20) -> -415 | E19: =+E22-(E21+E20) -> 2972 | F19: =+F22-(F21+F20) -> 4589 | G19: =G17+G10+G9 -> 3893.3935 | H19: =H17+H10+H9 -> 4482.6602 | I19: =I17+I10+I9 -> 5618.5958 | J19: =J17+J10+J9 -> 6943.5527 | K19: =K17+K10+K9 -> 6544.0074 | L19: =L17+L10+L9 -> 7645.7772 | M19: =M17+M10+M9 -> 9046.3886 | N19: =N17+N10+N9 -> 10837.856 | ... AF19: =AF17+AF10+AF9 -> 126523.01
B20: 13 | C20: (Stock-based compensation) | D20: 1785 | E20: 2190 | F20: 2779 | G20: =G11 -> 3319.2527 | H20: =H11 -> 3963.4711 | I20: =I11 -> 4633.6362 | J20: =J11 -> 5278.1073 | K20: =K11 -> 4511.5931 | L20: =L11 -> 5026.3 | M20: =M11 -> 5594.7011 | N20: =N11 -> 6221.7854 | ... AF20: =AF11 -> 24734.275
B21: 14 | C21: (Working Capital Flows) | D21: =+Assumptions!D151 -> 3431 | E21: =+Assumptions!E151 -> 838 | F21: =+Assumptions!F151 -> -257 | G21: =+Assumptions!G151 -> 1390.9345 | H21: =+Assumptions!H151 -> 1048.6307 | I21: =+Assumptions!I151 -> 1090.8654 | J21: =+Assumptions!J151 -> 1049.0419 | K21: =+Assumptions!K151 -> 1023.1189 | ... AF21: =+Assumptions!AF151 -> 1140.5259
B22: 15 | C22: -Total Operating Cash Flow | D22: =+'Fin. Data'!D67 -> 4801 | E22: =+'Fin. Data'!C67 -> 6000 | F22: =+'Fin. Data'!B67 -> 7111 | G22: =G19+G20+G21 -> 8603.5806 | H22: =H19+H20+H21 -> 9494.762 | I22: =I19+I20+I21 -> 11343.097 | J22: =J19+J20+J21 -> 13270.702 | K22: =K19+K20+K21 -> 12078.719 | L22: =L19+L20+L21 -> 14323.32 | M22: =M19+M20+M21 -> 15915.091 | N22: =N19+N20+N21 -> 18465.173 | ... AF22: =AF19+AF20+AF21 -> 152397.81
B23: 16 | C23: (CAPEX) | D23: ='Fin. Data'!D32 -> -710 | E23: ='Fin. Data'!C32 -> -717 | F23: ='Fin. Data'!B32 -> -798 | G23: =G6*$D$62 -> -1313.1318 | H23: =H6*$D$62 -> -1567.9915 | I23: =I6*$D$62 -> -1833.1159 | J23: =J6*$D$62 -> -2088.0756 | K23: =K6*$E$62 -> -2075.2013 | L23: =L6*$E$62 -> -2311.9515 | M23: =M6*$E$62 -> -2573.3994 | N23: =N6*$E$62 -> -2861.8399 | O23: =O6*$E$62 -> -3179.7485 | P23: =P6*$E$62 -> -3529.7924 | Q23: =Q6*$E$62 -> -3918.0695 | R23: =R6*$E$62 -> -4349.0572 | ... AF23: =AF6*$E$62 -> -11377.046 | AG23: =SUM(D23:AF23) -> -149728.14
B24: 17 | C24: Adq | D24: =Inputs!D66 -> -1281 | E24: ='Fin. Data'!C33 -> -14876 | F24: ='Fin. Data'!B33 -> -439 | G24: =G6*$D$63 -> -1246.3317 | H24: =H6*$D$63 -> -1488.2265 | I24: =I6*$D$63 -> -1739.8638 | J24: =J6*$D$63 -> -1981.8535 | K24: =K6*$E$63 -> -1843.3755 | L24: =L6*$E$63 -> -2053.6777 | M24: =M6*$E$63 -> -2285.9187 | N24: =N6*$E$63 -> -2542.1368 | O24: =O6*$E$63 -> -2824.531 | P24: =P6*$E$63 -> -3135.4706 | Q24: =Q6*$E$63 -> -3480.3724 | R24: =R6*$E$63 -> -3863.2134 | ... AF24: =AF6*$E$63 -> -10106.088 | AH24: =AG9-AG23 -> 593302.42
B25: 18 | C25: (Other investing flows) | D25: =Inputs!D67 -> -1980 | E25: =Inputs!C67 -> 1057 | F25: =Inputs!B67 -> -752 | G25: =(1+G5)*AVERAGE(D25:F25) -> -694.61434 | H25: =(1+H5)*AVERAGE(E25:G25) -> -155.0776 | I25: =(1+I5)*AVERAGE(F25:H25) -> -624.17155 | J25: =(1+J5)*AVERAGE(G25:I25) -> -559.61879 | K25: =(1+K5)*AVERAGE(H25:J25) -> -499.43585 | L25: =(1+L5)*AVERAGE(I25:K25) -> -625.08591 | M25: =(1+M5)*AVERAGE(J25:L25) -> -624.86408 | N25: =(1+N5)*AVERAGE(K25:M25) -> -648.48881 | ... AF25: =(1+AF5)*AVERAGE(AC25:AE25) -> -1278.6736
B26: 19 | C26: -Total Investing Flows | D26: =D23+D24+D25 -> -3971 | E26: =E23+E24+E25 -> -14536 | F26: =F23+F24+F25 -> -1989 | G26: =G23+G24+G25 -> -3254.0778 | H26: =H23+H24+H25 -> -3211.2955 | I26: =I23+I24+I25 -> -4197.1513 | J26: =J23+J24+J25 -> -4629.5478 | K26: =K23+K24+K25 -> -4418.0127 | ... AF26: =AF23+AF24+AF25 -> -22761.807
B27: 20 | C27: (Flows related to leases) | D27: =Inputs!D71+Inputs!D72 -> 0 | E27: =Inputs!C71+Inputs!C72 -> 0 | F27: =Inputs!B71+Inputs!B72 -> 0 | G27: 0 | H27: 0 | I27: 0 | J27: 0 | K27: 0 | L27: 0 | M27: 0 | N27: 0 | O27: 0 | P27: 0 | Q27: 0 | R27: 0 | S27: 0 | T27: 0 | U27: 0 | V27: 0 | W27: 0 | X27: 0 | Y27: 0 | Z27: 0 | AA27: 0 | AB27: 0 | AC27: 0 | AD27: 0 | AE27: 0 | AF27: 0
B28: 21 | C28: Flows related to debt | D28: =+SUM(Inputs!D69:D70) -> -107 | E28: =+SUM(Inputs!C69:C70) -> 5192 | F28: =+SUM(Inputs!B69:B70) -> -423 | G28: =G44-F44 -> 3451.3031 | H28: =H44-G44 -> 4197.5713 | I28: =I44-H44 -> 4331.5033 | J28: =J44-I44 -> 2843.7626 | K28: =K44-J44 -> 601.45079 | L28: =L44-K44 -> 424.85261 | M28: =M44-L44 -> 1533.9494 | N28: =N44-M44 -> 1475.8537 | ... AF28: =AF44-AE44 -> 2127.6877
B29: 22 | C29: (Repurchases)/Issuance of stock | D29: ='Fin. Data'!D28 -> 0 | E29: ='Fin. Data'!C28 -> 0 | F29: ='Fin. Data'!B28 -> -4000 | G29: =-G17*$D$65 -> 0 | H29: =+Assumptions!K132 -> 194.61055 | I29: =+Assumptions!L132 -> 282.57076 | J29: =+Assumptions!M132 -> 384.79402 | K29: =+Assumptions!N132 -> 479.65577 | L29: =+Assumptions!O132 -> 571.54893 | M29: =+Assumptions!P132 -> 708.55492 | N29: =+Assumptions!Q132 -> 2198.5946 | O29: =+Assumptions!R132 -> 2794.545 | ... AF29: =+Assumptions!AI132 -> 39899.553
B30: 23 | C30: (Dividends) | D30: ='Fin. Data'!D27 -> 0 | E30: ='Fin. Data'!C27 -> 0 | F30: ='Fin. Data'!B27 -> 0 | G30: =-$D$64*G17 -> 0 | H30: =-$D$64*H17 -> 0 | I30: =+Assumptions!L134 -> 353.21345 | J30: =+Assumptions!M134 -> 480.99252 | K30: =+Assumptions!N134 -> 599.56971 | L30: =+Assumptions!O134 -> 714.43616 | M30: =+Assumptions!P134 -> 885.69366 | N30: =+Assumptions!Q134 -> 1543.3382 | O30: =+Assumptions!R134 -> 1961.675 | P30: =+Assumptions!S134 -> 2454.7059 | ... AF30: =+Assumptions!AI134 -> 28008.122
B31: 24 | C31: Other financing flows | D31: =Inputs!D75 -> 1301 | E31: =Inputs!C75 -> 2646 | F31: =Inputs!B75 -> 861 | G31: =(1+G5)*AVERAGE(D31:F31) -> 1993.8542 | H31: =(1+H5)*AVERAGE(E31:G31) -> 2189.4965 | I31: =(1+I5)*AVERAGE(F31:H31) -> 1965.7589 | J31: =(1+J5)*AVERAGE(G31:I31) -> 2334.787 | K31: =(1+K5)*AVERAGE(H31:J31) -> 2420.9706 | L31: =(1+L5)*AVERAGE(I31:K31) -> 2496.1144 | M31: =(1+M5)*AVERAGE(J31:L31) -> 2690.6509 | N31: =(1+N5)*AVERAGE(K31:M31) -> 2820.1507 | ... AF31: =(1+AF5)*AVERAGE(AC31:AE31) -> 5465.5638
B32: 25 | C32: -Total Financing flows | D32: =D27+D28+D29+D30+D31 -> 1194 | E32: =E27+E28+E29+E30+E31 -> 7838 | F32: =F27+F28+F29+F30+F31 -> -3562 | G32: =G27+G28-G29-G30+G31 -> 5445.1573 | H32: =H27+H28-H29-H30+H31 -> 6192.4573 | I32: =I27+I28-I29-I30+I31 -> 5661.478 | J32: =J27+J28-J29-J30+J31 -> 4312.763 | K32: =K27+K28-K29-K30+K31 -> 1943.1959 | L32: =L27+L28-L29-L30+L31 -> 1634.982 | M32: =M27+M28-M29-M30+M31 -> 2630.3518 | N32: =N27+N28-N29-N30+N31 -> 554.07149 | ... AF32: =AF27+AF28-AF29-AF30+AF31 -> -60314.423
A34: SUMMARY | B34: 26 | C34: Cash before shareholder returns | D34: =D22+D26+D27+D28+D31 -> 2024 | E34: =E22+E26+E27+E28+E31 -> -698 | F34: =F22+F26+F27+F28+F31 -> 5560 | G34: =G22+G26+G27+G28+G31 -> 10794.66 | H34: =H22+H26+H27+H28+H31 -> 12670.534 | I34: =I22+I26+I27+I28+I31 -> 13443.208 | J34: =J22+J26+J27+J28+J31 -> 13819.704 | K34: =K22+K26+K27+K28+K31 -> 10683.128 | ... AF34: =AF22+AF26+AF27+AF28+AF31 -> 137229.26
B35: 27 | C35: Returns to shareholders | D35: =-1*(D29+D30) -> 0 | E35: =-1*(E29+E30) -> 0 | F35: =-1*(F29+F30) -> 4000 | G35: =-1*(G29+G30) -> 0 | H35: =-1*(H29+H30) -> -194.61055 | I35: =-1*(I29+I30) -> -635.78422 | J35: =-1*(J29+J30) -> -865.78654 | K35: =-1*(K29+K30) -> -1079.2255 | ... AF35: =-1*(AF29+AF30) -> -67907.675
B36: 28 | C36: Excess cash acumulation | D36: =D34-D35 -> 2024 | E36: =E34-E35 -> -698 | F36: =F34-F35 -> 1560 | G36: =G34-G35 -> 10794.66 | H36: =H34-H35 -> 12865.145 | I36: =I34-I35 -> 14078.992 | J36: =J34-J35 -> 14685.49 | K36: =K34-K35 -> 11762.354 | ... AF36: =AF34-AF35 -> 205136.93
A38: BALANCE SHEET | B38: 29 | C38: Intangible assets | D38: 4114 | E38: 8978 | F38: 7125 | G38: =+F38+(-G10) -> 7125 | H38: =+G38+(-H10) -> 7125 | I38: =+H38+(-I10) -> 7125 | J38: =+I38+(-J10) -> 7125 | K38: =+J38+(-K10) -> 7125 | L38: =+K38+(-L10) -> 7125 | M38: =+L38+(-M10) -> 7125 | N38: =+M38+(-N10) -> 7125 | ... AF38: =+AE38+(-AF10) -> 7125 | AG38: =SUM(G38:AF38) -> 185250
B39: 30 | C39: Accumulated amortization | D39: 2746 | E39: 3995 | F39: 4713 | G39: =F39-G10 -> 4713 | H39: =G39-H10 -> 4713 | I39: =H39-I10 -> 4713 | J39: =I39-J10 -> 4713 | K39: =J39-K10 -> 4713 | L39: =K39-L10 -> 4713 | M39: =L39-M10 -> 4713 | N39: =M39-N10 -> 4713 | ... AF39: =AE39-AF10 -> 4713 | AG39: =SUM(G39:AF39) -> 122538
B40: 31 | C40: PPE+Right of use Assets | D40: 5663 | E40: 5695 | F40: 6592 | G40: =F40+(-G23) -> 7905.1318 | H40: =G40+(-H23) -> 9473.1233 | I40: =H40+(-I23) -> 11306.239 | J40: =I40+(-J23) -> 13394.315 | K40: =J40+(-K23) -> 15469.516 | L40: =K40+(-L23) -> 17781.468 | M40: =L40+(-M23) -> 20354.867 | N40: =M40+(-N23) -> 23216.707 | ... AF40: =AE40+(-AF23) -> 154095.14 | AG40: =SUM(G40:AF40) -> 1533227.9
B41: 32 | C41: Accumulated depreciation | D41: 1955 | E41: 2401 | F41: 2702 | G41: =F41-G9 -> -224.622 | H41: =G41-H9 -> -3734.2295 | I41: =H41-I9 -> -7939.9715 | J41: =I41-J9 -> -12959.554 | K41: =J41-K9 -> -17105.283 | L41: =K41-L9 -> -21893.315 | M41: =L41-M9 -> -27396.929 | N41: =M41-N9 -> -33697.046 | ... AF41: =AE41-AF9 -> -430942.28 | AG41: =SUM(G41:AF41) -> -3454080.2
A43: CASH & DEBT & DISCOUNTING | B43: 33 | C43: Ending cash balance | D43: ='Fin. Data'!D39 -> 11966 | E43: =E36+D43 -> 11268 | F43: =F36+E43 -> 12828 | G43: =G36+F43 -> 23622.66 | H43: =H36+G43 -> 36487.805 | I43: =I36+H43 -> 50566.797 | J43: =J36+I43 -> 65252.288 | K43: =K36+J43 -> 77014.641 | L43: =L36+K43 -> 90554.198 | ... AF43: =AF36+AE43 -> 1827144.5
B44: 34 | C44: Total Debt | D44: ='Fin. Data'!D58 -> 2801 | E44: ='Fin. Data'!C58 -> 10977 | F44: ='Fin. Data'!B58 -> 11392 | G44: =+Assumptions!I123 -> 14843.303 | H44: =+Assumptions!J123 -> 19040.874 | I44: =+Assumptions!K123 -> 23372.378 | J44: =+Assumptions!L123 -> 26216.14 | K44: =+Assumptions!M123 -> 26817.591 | L44: =+Assumptions!N123 -> 27242.444 | M44: =+Assumptions!O123 -> 28776.393 | N44: =+Assumptions!P123 -> 30252.247 | ... AF44: =+Assumptions!AH123 -> 59426.741
B45: 35 | C45: Discount factor | F45: =1/((1+$F$50)^G50) -> 1 | G45: =1/((1+$F$50)^G49) -> 0.90415913 | H45: =1/((1+$F$50)^H49) -> 0.81750374 | I45: =1/((1+$F$50)^I49) -> 0.73915347 | J45: =1/((1+$F$50)^J49) -> 0.66831236 | K45: =1/((1+$F$50)^K49) -> 0.60426072 | L45: =1/((1+$F$50)^L49) -> 0.54634785 | M45: =1/((1+$F$50)^M49) -> 0.4939854 | N45: =1/((1+$F$50)^N49) -> 0.44664141 | ... AF45: =1/((1+$F$50)^AF49) -> 0.072839457
B46: 36 | C46: DF + 0.1% | E46: +0.1% | F46: =1/((1+$F$50+0.001)^G50) -> 1 | G46: =1/((1+$F$50+0.001)^G49) -> 0.90334237 | H46: =1/((1+$F$50+0.001)^H49) -> 0.81602743 | I46: =1/((1+$F$50+0.001)^I49) -> 0.73715215 | J46: =1/((1+$F$50+0.001)^J49) -> 0.66590077 | K46: =1/((1+$F$50+0.001)^K49) -> 0.60153638 | L46: =1/((1+$F$50+0.001)^L49) -> 0.54339329 | M46: =1/((1+$F$50+0.001)^M49) -> 0.49087018 | N46: =1/((1+$F$50+0.001)^N49) -> 0.44342383 | ... AF46: =1/((1+$F$50+0.001)^AF49) -> 0.071147863
B47: 37 | C47: DF+0.5% | E47: +0.5% | F47: =1/((1+$F$50+0.005)^G50) -> 1 | G47: =1/((1+$F$50+0.005)^G49) -> 0.90009001 | H47: =1/((1+$F$50+0.005)^H49) -> 0.81016202 | I47: =1/((1+$F$50+0.005)^I49) -> 0.72921874 | J47: =1/((1+$F$50+0.005)^J49) -> 0.65636251 | K47: =1/((1+$F$50+0.005)^K49) -> 0.59078533 | L47: =1/((1+$F$50+0.005)^L49) -> 0.53175998 | M47: =1/((1+$F$50+0.005)^M49) -> 0.47863184 | N47: =1/((1+$F$50+0.005)^N49) -> 0.43081174 | ... AF47: =1/((1+$F$50+0.005)^AF49) -> 0.064779034
A49: Discount Rate | C49: Risk free rate | D49: Equity premium | E49: Firm premium | F49: Total | G49: 1 | H49: 2 | I49: 3 | J49: 4 | K49: 5 | L49: 6 | M49: 7 | N49: 8 | O49: 9 | P49: 10 | Q49: 11 | R49: 12 | S49: 13 | T49: 14 | U49: 15 | V49: 16 | W49: 17 | X49: 18 | Y49: 19 | Z49: 20 | AA49: 21 | AB49: 22 | AC49: 23 | AD49: 24 | AE49: 25 | AF49: 26
C50: 0.0483 | D50: 0.0447 | E50: 0.013 | F50: =E50+D50+C50 -> 0.106 | G50: 0
A52: Modelling factors | D52: Short Term | E52: Long Term | F52: Reference (line)
C53: Depreciation factor | D53: =Assumptions!I17 -> 0.44396572 | E53: =Assumptions!J17 -> 0.30951405 | F53: % PPE
C54: Amortization factor | F54: % IA
C55: Stock-based comp | D55: =Assumptions!I18 -> 0.085099081 | E55: =Assumptions!J18 -> 0.065 | F55: % revenue
C56: Tax Rate | D56: =Assumptions!I19 -> 0.3 | E56: =Assumptions!J19 -> 0.4075 | F56: % (line 9)
C57: Interest Rate on debt | D57: =Assumptions!I20 -> 0.025767359 | E57: =Assumptions!J20 -> 0.04915 | F57: % debt (l29)
C58: Interest Rate on cash | D58: 0.0522 | E58: =Assumptions!J21 -> 0.04915 | F58: % of cash (l28)
C59: PPE+ROA | D59: =Assumptions!I22 -> -0.033666105 | E59: =Assumptions!J22 -> -0.029898105 | F59: Growing with capex
C60: Working capital flows | D60: =Assumptions!I23 -> -0.072813896 | E60: =Assumptions!J23 -> -0.061277818 | F60: % of change revenues (l2)
C61: Intangible Assets | D61: =Assumptions!I24 -> 0.1841269 | E61: =Assumptions!J24 -> 0.20548774 | F61: Growing with amortization
C62: Capex | D62: =Assumptions!I25 -> -0.033666105 | E62: =Assumptions!J25 -> -0.029898105 | F62: % revenue (l2)
C63: Acquisition factor | D63: =Assumptions!I26 -> -0.031953483 | E63: =Assumptions!J26 -> -0.026558115 | F63: % revenue (l2)
C64: Dividends | D64: =Assumptions!I27 -> 0 | E64: =+Assumptions!J27 -> 0.34011177 | F64: % net income (11)
C65: Repurchases | D65: =Assumptions!I28 -> 0 | E65: =Assumptions!J28 -> 0.4845133 | F65: % net income (11)
C66: Leases | D66: =Assumptions!I29 -> 0 | E66: =Assumptions!J29 -> 0 | F66: % revenue (l2)
C67: Cash Costs for EBIT | D67: =Assumptions!I30 -> 0 | E67: =Assumptions!J30 -> 0 | F67: % revenue (l2)
C68: Total Debt | D68: =Assumptions!I31 -> 0.27257341 | E68: =Assumptions!J31 -> 0.3275634 | F68: %EQUITY
A70: Valuation | D70: $ millions
C71: Value of flows | D71: =SUMPRODUCT(G35:AF35,G45:AF45)+((AF43-AF44)*AF45) -> 55221.442 | E71: =D71/D73 -> 0.32208376
C72: Value of perpetuity | D72: =(AF34/(F50-AF5))*AF45 -> 116229.12 | E72: =D72/D73 -> 0.67791624
C73: Total Value | D73: =D71+D72 -> 171450.57
C74: Actual share price | D74: =OP!C20 -> #VALUE!
C75: Total value vs Mkt Cap | D75: =D76/D74-1 -> #VALUE!
C76: Estimated NPV per share | D76: =D73*1000000/OP!C21 -> #VALUE!
A78: Sensibility | C78: Sensitivity +0.1% | D78: =(SUMPRODUCT(G35:AF35,G45:AF45)+((AF43-AF44)*AF45)+(AF34/(F50+0.001-AF5))*AF45)*1000000/OP!C21 -> #VALUE! | E78: =D78/D76-1 -> #VALUE!
C79: Sensitivity +0.5% | D79: =(SUMPRODUCT(G35:AF35,G45:AF45)+((AF43-AF44)*AF45)+(AF34/(F50+0.005-AF5))*AF45)*1000000/OP!C21 -> #VALUE! | E79: =D79/D76-1 -> #VALUE!
A81: Notes

Sheet Assumptions
B2: Assumptions
B4: Prospects:
B6: Links:
C8: 2022 | D8: =C8-1 -> 2021 | E8: =D8-1 -> 2020 | F8: =E8-1 -> 2019 | G8: =F8-1 -> 2018 | I8: Average | K8: Short Term Forecast | L8: Long Term Forecast
B9: Revenue growth | C9: =(Inputs!B6-Inputs!C6)/Inputs!C6 -> 0.18345161 | D9: =(Inputs!C6-Inputs!D6)/Inputs!D6 -> 0.24656503 | E9: =(Inputs!D6-Inputs!E6)/Inputs!E6 -> 0.24295239 | F9: =(Inputs!E6-Inputs!F6)/Inputs!F6 -> 0.28730613 | G9: =(Inputs!F6-Inputs!G6)/Inputs!G6 -> 0.2601518 | I9: =AVERAGE(C9:G9) -> 0.24408539 | K9: =+AVERAGE(C9:I9) -> 0.24408539
B10: Operating Margin | C10: =Inputs!B8/Inputs!B6 -> 0.032852769 | D10: =Inputs!C8/Inputs!C6 -> 0.02068549 | E10: =Inputs!D8/Inputs!D6 -> 0.02140975 | F10: =Inputs!E8/Inputs!E6 -> 0.017370453 | G10: =Inputs!F8/Inputs!F6 -> 0.040280078 | I10: =AVERAGE(C10:G10) -> 0.026519708 | K10: =+AVERAGE(C10:I10) -> 0.026519708
B13: Modelling Factors
C15: Last 5 Years
C16: 2018 | D16: 2019 | E16: 2020 | F16: 2021 | G16: 2022 | I16: Short Term Forecast | J16: Long Term Forecast | L16: Reference
B17: Depreciation and Amortization factor | C17: =C50 -> 0.38674884 | D17: =D50 -> 0.46903949 | E17: =E50 -> 0.39427516 | F17: =F50 -> 0.50256048 | G17: =G50 -> 0.57910448 | I17: 0.44396572 | J17: =AVERAGE(M50,M51,R51,W51,AB51,AG51,) -> 0.30951405
B18: Stock-based comp | C18: - | D18: - | E18: =+F64 -> 0.083992095 | F18: =+G64 -> 0.082666465 | G18: =+H64 -> 0.088638683 | I18: =+AVERAGE(E18:G18) -> 0.085099081 | J18: 0.065
B19: Tax Rate | C19: -0.13 | D19: 0.82 | E19: 0.59 | F19: 0.68 | G19: 0.06 | I19: =AVERAGE(C19,E19:G19) -> 0.3 | J19: =AVERAGE(E19,F19:I19) -> 0.4075
B20: Interest Rate on debt | I20: =+F83 -> 0.025767359 | J20: 0.04915
B21: Interest Rate on cash | I21: 0.05477 | J21: 0.04915
B22: PPE+ROA | I22: =I25 -> -0.033666105 | J22: =J25 -> -0.029898105
B23: Working capital flows | C23: 0.0067760879 | D23: -0.1120014 | E23: -0.045925089 | F23: -0.063037898 | G23: -0.08066471 | I23: -0.072813896 | J23: -0.061277818
B24: Intangible Assets | C24: =1027/Assumptions!D41 -> 0.077322692 | D24: =1429/Assumptions!E41 -> 0.083577027 | E24: =DCF!D38/Assumptions!F41 -> 0.19358178 | F24: =DCF!E38/Assumptions!G41 -> 0.33889476 | G24: =DCF!F38/Assumptions!H41 -> 0.22725823 | I24: =AVERAGE(C24:G24) -> 0.1841269 | J24: =AVERAGE(I24,D24:G24) -> 0.20548774
B25: CAPEX | C25: -0.04479747 | D25: -0.037606738 | E25: -0.03340862 | F25: -0.027064774 | G25: -0.025452922 | I25: =+AVERAGE(C25:G25) -> -0.033666105 | J25: =+AVERAGE(E25:I25) -> -0.029898105
B26: Acquisition factor | C26: ='Fin. Data'!F33/Assumptions!D41 -> -0.38510766 | D26: ='Fin. Data'!E33/Assumptions!E41 -> -0.021581472 | E26: ='Fin. Data'!D33/Assumptions!F41 -> -0.06027668 | F26: ='Fin. Data'!C33/Assumptions!G41 -> -0.56152801 | G26: ='Fin. Data'!B33/Assumptions!H41 -> -0.014002297 | I26: =AVERAGE(D26,E26,G26) -> -0.031953483 | J26: =AVERAGE(,E26,G26,I26) -> -0.026558115
B27: Dividends | C27: 0 | D27: 0 | E27: 0 | F27: 0 | G27: 0 | I27: =AVERAGE(C27:G27) -> 0 | J27: =+Q135 -> 0.34011177 | K27: According to the average of the industry the % (in terms of Net Income) of buyback is much more higher than the % o dividends payouts. This may be na indicator that Salesforce is now entering the same trend as the industry due to the recent repurchase they did. And in accordance with our estimates, this might indicate that in the medium term (10y) salesforce will be paying out dividends for their investors at a rate of 10,6% of Net Income. Furthermore, historically speaking when companies make large repurchases it because CFO´s believe that the stock is undervalue.
B28: Repurchases | C28: 0 | D28: 0 | E28: 0 | F28: 0 | G28: ='Fin. Data'!B36 -> -19.230769 | I28: =AVERAGE(C28:F28) -> 0 | J28: =+Q133 -> 0.4845133
B29: Leases
B30: Cash Costs for EBIT
B31: Total Debt | C31: =Assumptions!D123/Assumptions!D41 -> 0.27450685 | D31: =Assumptions!E123/Assumptions!E41 -> 0.17885133 | E31: =Assumptions!F123/Assumptions!F41 -> 0.13179936 | F31: =Assumptions!G123/Assumptions!G41 -> 0.4143515 | G31: =Assumptions!H123/Assumptions!H41 -> 0.363358 | I31: =AVERAGE(C31:G31) -> 0.27257341 | J31: =I31+H126 -> 0.3275634
B34: Forecasts
C39: Last 5 Years | I39: Short Term Forecast
C40: 2017 | D40: 2018 | E40: 2019 | F40: 2020 | G40: 2021 | H40: 2022 | I40: 2023 | J40: =I40+1 -> 2024 | K40: =J40+1 -> 2025 | L40: =K40+1 -> 2026 | M40: =L40+1 -> 2027 | N40: =M40+1 -> 2028 | O40: =N40+1 -> 2029 | P40: =O40+1 -> 2030 | Q40: =P40+1 -> 2031 | ... AH40: =AG40+1 -> 2048
B41: Net Sales | C41: ='Fin. Data'!G5 -> 10540 | D41: ='Fin. Data'!F5 -> 13282 | E41: ='Fin. Data'!E5 -> 17098 | F41: ='Fin. Data'!D5 -> 21252 | G41: ='Fin. Data'!C5 -> 26492 | H41: ='Fin. Data'!B5 -> 31352 | I41: =+H41*(1+$H$43) -> 39004.565 | J41: =+I41*(1+$H$43-0.05) -> 46574.782 | K41: =+J41*(1+$J$42-0.025) -> 54449.897 | L41: =+K41*(1+$K$42-0.03) -> 62023.082 | M41: =+L41*(1+$L$42-0.02) -> 69409.125 | N41: =+M41*(1+$M$42-0.005) -> 77327.692 | O41: =+N41*(1+$N$42-0.001) -> 86072.325 | P41: =+O41*(1+$O$42-0.001) -> 95719.775 | Q41: =+P41*(1+$P$42-0.001) -> 106352.84 | R41: =+Q41*(1+$Q$42-0.001) -> 118060.74 | S41: =+R41*(1+$R$44) -> 131047.42 | T41: =+S41*(1+$R$44) -> 145462.64 | U41: =+T41*(1+$R$44) -> 161463.53 | V41: =+U41*(1+$R$44) -> 179224.51 | W41: =+V41*(1+$R$44) -> 198939.21 | X41: =+W41*(1+$W$44) -> 214854.35 | Y41: =+X41*(1+$W$44) -> 232042.69 | Z41: =+Y41*(1+$W$44) -> 250606.11 | AA41: =+Z41*(1+$W$44) -> 270654.6 | AB41: =+AA41*(1+$W$44) -> 292306.97 | AC41: =+AB41*(1+$AB$44) -> 306922.31 | AD41: =+AC41*(1+$AB$44) -> 322268.43 | AE41: =+AD41*(1+$AB$44) -> 338381.85 | AF41: =+AE41*(1+$AB$44) -> 355300.94 | AG41: =+AF41*(1+$AB$44) -> 373065.99 | AH41: =+AG41*(1+$AG$44) -> 380527.31
B42: % Growth | D42: =D41/C41-1 -> 0.2601518 | E42: =E41/D41-1 -> 0.28730613 | F42: =F41/E41-1 -> 0.24295239 | G42: =G41/F41-1 -> 0.24656503 | H42: =H41/G41-1 -> 0.18345161 | I42: =I41/H41-1 -> 0.24408539 | J42: =J41/I41-1 -> 0.19408539 | K42: =K41/J41-1 -> 0.16908539 | ... R42: =R41/Q41-1 -> 0.11008539 | S42: 0.11 | T42: 0.11 | U42: 0.11 | V42: 0.11 | W42: 0.11 | X42: =X41/W41-1 -> 0.08 | Y42: =Y41/X41-1 -> 0.08 | Z42: =Z41/Y41-1 -> 0.08 | AA42: =AA41/Z41-1 -> 0.08 | AB42: =AB41/AA41-1 -> 0.08 | AC42: =AC41/AB41-1 -> 0.05 | AD42: =AD41/AC41-1 -> 0.05 | AE42: =AE41/AD41-1 -> 0.05 | ... AH42: =AH41/AG41-1 -> 0.02
B43: Actual 5y Average | H43: =AVERAGE(D42:H42) -> 0.24408539 | R43: =+AVERAGE(N42:R42) -> 0.11208539 | AB43: =+AVERAGE(X42:AB42) -> 0.08 | AG43: =+AVERAGE(AC42:AG42) -> 0.05
B44: Target 5y Average | H44: 0.22409 | M44: =+H44 -> 0.22409 | R44: 0.11 | W44: 0.08 | AB44: 0.05 | AG44: 0.02
C47: Last 5 Years | I47: Short Term Forecast
C48: 2017 | D48: 2018 | E48: 2019 | F48: 2020 | G48: 2021 | H48: 2022 | I48: 2023 | J48: =I48+1 -> 2024 | K48: =J48+1 -> 2025 | L48: =K48+1 -> 2026 | M48: =L48+1 -> 2027 | N48: =M48+1 -> 2028 | O48: =N48+1 -> 2029 | P48: =O48+1 -> 2030 | Q48: =P48+1 -> 2031 | ... AH48: =AG48+1 -> 2048
B49: Depretiation | C49: ='Fin. Data'!G17 -> 753 | D49: ='Fin. Data'!F17 -> 962 | E49: ='Fin. Data'!E17 -> 2135 | F49: ='Fin. Data'!D17 -> 2846 | G49: ='Fin. Data'!C17 -> 3298 | H49: ='Fin. Data'!B17 -> 3786 | I49: =I50*DCF!G40 -> 3509.6075 | J49: =J50*DCF!H40 -> 4205.742 | K49: =K50*DCF!I40 -> 5019.5826 | L49: =L50*DCF!J40 -> 5946.6166 | M49: =M50*DCF!K40 -> 6867.9348 | N49: =+M49*(1+$M$44-0.04) -> 8132.2529 | O49: =+N49*(1+$M$44-0.06) -> 9466.6743 | P49: =+O49*(1+$M$44-0.07) -> 10925.394 | Q49: =+P49*(1+$M$44-0.075) -> 12554.261 | R49: =+Q49*(1+$M$44-0.08) -> 14363.205 | S49: =+R49*(1+$R$44) -> 15943.157 | T49: =+S49*(1+$R$44) -> 17696.904 | U49: =+T49*(1+$R$44) -> 19643.564 | V49: =+U49*(1+$R$44) -> 21804.356 | W49: =+V49*(1+$R$44) -> 24202.835 | X49: =+W49*(1+$W$44) -> 26139.062 | Y49: =+X49*(1+$W$44) -> 28230.187 | Z49: =+Y49*(1+$W$44) -> 30488.602 | AA49: =+Z49*(1+$W$44) -> 32927.69 | AB49: =+AA49*(1+$W$44) -> 35561.905 | AC49: =+AB49*(1+$AB$44) -> 37340 | AD49: =+AC49*(1+$AB$44) -> 39207 | AE49: =+AD49*(1+$AB$44) -> 41167.35 | AF49: =+AE49*(1+$AB$44) -> 43225.718 | AG49: =+AF49*(1+$AB$44) -> 45387.004 | AH49: =+AG49*(1+$AG$44) -> 46294.744
B50: % of PPE | C50: =C49/'Fin. Data'!G42 -> 0.38674884 | D50: =D49/'Fin. Data'!F42 -> 0.46903949 | E50: =E49/'Fin. Data'!E42 -> 0.39427516 | F50: =F49/'Fin. Data'!D42 -> 0.50256048 | G50: =G49/'Fin. Data'!C42 -> 0.57910448 | H50: =H49/'Fin. Data'!B42 -> 0.57433252 | I50: =$H$51*(1-(-$H$52)) -> 0.44396572 | J50: =$H$51*(1-(-$H$52)) -> 0.44396572 | K50: =$H$51*(1-(-$H$52)) -> 0.44396572 | L50: =$H$51*(1-(-$H$52)) -> 0.44396572 | M50: =$H$51*(1-(-$H$52)) -> 0.44396572 | N50: =$M$52 -> 0.40695407 | O50: =$M$52 -> 0.40695407 | P50: =$M$52 -> 0.40695407 | Q50: =$M$52 -> 0.40695407 | R50: =$M$52 -> 0.40695407 | S50: =$R$51 -> 0.37302794 | T50: =$R$51 -> 0.37302794 | U50: =$R$51 -> 0.37302794 | V50: =$R$51 -> 0.37302794 | W50: =$R$51 -> 0.37302794 | X50: =$S$50*(1-(-$H$52)) -> 0.34193009 | Y50: =$S$50*(1-(-$H$52)) -> 0.34193009 | Z50: =$S$50*(1-(-$H$52)) -> 0.34193009 | AA50: =$S$50*(1-(-$H$52)) -> 0.34193009 | AB50: =$S$50*(1-(-$H$52)) -> 0.34193009 | AC50: =$X$50*(1-(-$H$52)) -> 0.31342475 | AD50: =$X$50*(1-(-$H$52)) -> 0.31342475 | AE50: =$X$50*(1-(-$H$52)) -> 0.31342475 | AF50: =$X$50*(1-(-$H$52)) -> 0.31342475 | AG50: =$X$50*(1-(-$H$52)) -> 0.31342475 | AH50: =AH49/AG49-1 -> 0.02
B51: Target 5y Average | H51: =AVERAGE(C50:H50) -> 0.4843435 | M51: =$I$50*(1-(-$H$52)) -> 0.40695407 | R51: =$N$50*(1-(-$H$52)) -> 0.37302794 | W51: =$S$50*(1-(-$H$52)) -> 0.34193009 | AB51: =$X$50*(1-(-$H$52)) -> 0.31342475 | AG51: =$AC$50*(1-(-$H$52)) -> 0.28729578
B52: Average Growth % Sales | D52: =C50/D50-1 -> -0.17544503 | E52: =D50/E50-1 -> 0.18962476 | F52: =E50/F50-1 -> -0.21546724 | G52: =F50/G50-1 -> -0.13217649 | H52: =AVERAGE(D52:G52) -> -0.083366001 | M52: =$I$50*(1-(-$H$52)) -> 0.40695407
C54: Last 5 Years | I54: Short Term Forecast
C55: 2017 | D55: 2018 | E55: 2019 | F55: 2020 | G55: 2021 | H55: 2022 | I55: 2023 | J55: =I55+1 -> 2024 | K55: =J55+1 -> 2025 | L55: =K55+1 -> 2026 | M55: =L55+1 -> 2027 | N55: =M55+1 -> 2028 | O55: =N55+1 -> 2029 | P55: =O55+1 -> 2030 | Q55: =P55+1 -> 2031 | ... AH55: =AG55+1 -> 2048
B56: Amortizatioon | I56: =+H56*(1+$H$43) -> 0 | J56: =+I56*(1+$H$43-0.005) -> 0 | K56: =+J56*(1+$H$43-0.01) -> 0 | L56: =+K56*(1+$H$43-0.015) -> 0 | M56: =+L56*(1+$H$43-0.02) -> 0 | N56: =+M56*(1+$M$44-0.04) -> 0 | O56: =+N56*(1+$M$44-0.06) -> 0 | P56: =+O56*(1+$M$44-0.07) -> 0 | Q56: =+P56*(1+$M$44-0.075) -> 0 | R56: =+Q56*(1+$M$44-0.08) -> 0 | S56: =+R56*(1+$R$44) -> 0 | T56: =+S56*(1+$R$44) -> 0 | U56: =+T56*(1+$R$44) -> 0 | V56: =+U56*(1+$R$44) -> 0 | W56: =+V56*(1+$R$44) -> 0 | X56: =+W56*(1+$W$44) -> 0 | Y56: =+X56*(1+$W$44) -> 0 | Z56: =+Y56*(1+$W$44) -> 0 | AA56: =+Z56*(1+$W$44) -> 0 | AB56: =+AA56*(1+$W$44) -> 0 | AC56: =+AB56*(1+$AB$44) -> 0 | AD56: =+AC56*(1+$AB$44) -> 0 | AE56: =+AD56*(1+$AB$44) -> 0 | AF56: =+AE56*(1+$AB$44) -> 0 | AG56: =+AF56*(1+$AB$44) -> 0 | AH56: =+AG56*(1+$AG$44) -> 0
B57: % of PPE | I57: =I56/H56-1 -> #DIV/0! | J57: =J56/I56-1 -> #DIV/0! | K57: =K56/J56-1 -> #DIV/0! | L57: =L56/K56-1 -> #DIV/0! | M57: =M56/L56-1 -> #DIV/0! | N57: =N56/M56-1 -> #DIV/0! | O57: =O56/N56-1 -> #DIV/0! | P57: =P56/O56-1 -> #DIV/0! | ... AH57: =AH56/AG56-1 -> #DIV/0!
B58: Target 5y Average | R58: =+AVERAGE(N57:R57) -> #DIV/0! | AB58: =+AVERAGE(X57:AB57) -> #DIV/0! | AG58: =+AVERAGE(AC57:AG57) -> #DIV/0!
B59: Average Growth % Sales | M59: =+H59 -> 0
C61: Last 5 Years | I61: Short Term Forecast
C62: 2017 | D62: 2018 | E62: 2019 | F62: 2020 | G62: 2021 | H62: 2022 | I62: 2023 | J62: =I62+1 -> 2024 | K62: =J62+1 -> 2025 | L62: =K62+1 -> 2026 | M62: =L62+1 -> 2027 | N62: =M62+1 -> 2028 | O62: =N62+1 -> 2029 | P62: =O62+1 -> 2030 | Q62: =P62+1 -> 2031 | ... AH62: =AG62+1 -> 2048
B63: Stock-based Compensation | C63: 0 | D63: 0 | E63: 0 | F63: 1785 | G63: 2190 | H63: 2779 | I63: =+H63*(1+$H$65) -> 3015.4903 | J63: =+I63*(1+$H$65) -> 3272.1058 | K63: =+J63*(1+$H$65) -> 3550.559 | L63: =+K63*(1+$H$65) -> 3852.7083 | M63: =+L63*(1+$H$65) -> 4180.5702 | N63: =+M63*(1+$M$65) -> 4536.3329 | O63: =+N63*(1+$M$65) -> 4922.3707 | P63: =+O63*(1+$M$65) -> 5341.2599 | Q63: =+P63*(1+$M$65) -> 5795.7962 | R63: =+Q63*(1+$M$65) -> 6289.0132 | S63: =+R63*(1+$R$66) -> 6697.799 | T63: =+S63*(1+$R$66) -> 7133.156 | U63: =+T63*(1+$R$66) -> 7596.8111 | V63: =+U63*(1+$R$66) -> 8090.6038 | W63: =+V63*(1+$R$66) -> 8616.4931 | X63: =+W63*(1+$R$66) -> 9176.5651 | Y63: =+X63*(1+$R$66) -> 9773.0419 | Z63: =+Y63*(1+$R$66) -> 10408.29 | ... AH63: =+AG63*(1+$R$66) -> 17225.674
B64: % of Sales | C64: =C63/C41 -> 0 | D64: =D63/D41 -> 0 | E64: =E63/E41 -> 0 | F64: =F63/F41 -> 0.083992095 | G64: =G63/G41 -> 0.082666465 | H64: =H63/H41 -> 0.088638683 | I64: =I63/H63-1 -> 0.085099081 | J64: =J63/I63-1 -> 0.085099081 | K64: =K63/J63-1 -> 0.085099081 | L64: =L63/K63-1 -> 0.085099081 | M64: =M63/L63-1 -> 0.085099081 | N64: =N63/M63-1 -> 0.085099081 | O64: =O63/N63-1 -> 0.085099081 | P64: =P63/O63-1 -> 0.085099081 | ... AH64: =AH63/AG63-1 -> 0.065
B65: Target 5y Average | H65: =AVERAGE(F64:H64) -> 0.085099081 | I65: =+I41*$H$65 -> 3319.2527 | M65: =+AVERAGE(I64:M64) -> 0.085099081 | R65: =+AVERAGE(N64:R64) -> 0.085099081 | AB65: =+AVERAGE(X64:AB64) -> 0.065 | AG65: =+AVERAGE(AC64:AG64) -> 0.065
R66: 0.065
B67: Industry name | C67: Number of firms | D67: Dividends | E67: Net Income | F67: Payout | G67: Dividends + Buybacks | H67: Buybacks(BB) | I67: BB%ofNetIncome | K67: Short Term Forecast
B68: Software (Entertainment) | C68: 91 | D68: 60.03 | E68: 91628.189 | F68: 0.00065514773 | G68: 106194.39 | H68: =G68-D68 -> 106134.36 | I68: =H68/E68 -> 1.1583156 | K68: 2023 | L68: =K68+1 -> 2024 | M68: =L68+1 -> 2025 | N68: =M68+1 -> 2026 | O68: =N68+1 -> 2027 | P68: =O68+1 -> 2028 | Q68: =P68+1 -> 2029 | R68: =Q68+1 -> 2030 | S68: =R68+1 -> 2031 | ... AJ68: =AI68+1 -> 2048
B69: Software (Internet) | C69: 33 | D69: 0.336 | E69: -5178.9 | F69: 0 | G69: 4187.838 | H69: =G69-D69 -> 4187.502 | I69: =H69/E69 -> -0.80856977 | J69: Net income | K69: {=DCF!G17:AF17} -> 966.77149 | L69: 973.05274 | M69: 1412.8538 | N69: 1923.9701 | O69: 2398.2789 | P69: 2857.7446 | Q69: 3542.7746 | R69: 4537.7384 | S69: 5767.7364 | T69: 7217.3508 | U69: 8923.0707 | V69: 10926.527 | W69: 13270.831 | X69: 16041.116 | Y69: 19233.831 | Z69: 22610.722 | AA69: 26423.546 | AB69: 30738.131 | AC69: 35610.179 | AD69: 41105.138 | AE69: 46622.598 | AF69: 52673.07 | AG69: 59327.75 | AH69: 66634.805 | AI69: 74651.015 | AJ69: 82349.758
B70: Software (System & Application) | C70: 390 | D70: 24238.726 | E70: 71266.943 | F70: 0.34011177 | G70: 81788.362 | H70: =G70-D70 -> 57549.636 | I70: =H70/E70 -> 0.80752216 | J70: Buyback | O70: =O69*0.2 -> 479.65577 | P70: =P69*0.3 -> 857.32339 | Q70: =Q69*0.4 -> 1417.1098 | R70: =R69*0.5 -> 2268.8692 | S70: =S69*0.6 -> 3460.6418 | T70: =T69*0.7 -> 5052.1455 | U70: =U69*0.8 -> 7138.4566 | V70: =V69*0.9 -> 9833.874 | W70: =W69*1 -> 13270.831 | X70: =W71*$X$69 -> 17073.995 | Y70: =$W$71*X69 -> 17073.995 | Z70: =$W$71*Y69 -> 20472.287 | AA70: =$W$71*Z69 -> 24066.615 | AB70: =$W$71*AA69 -> 28124.944 | AC70: =$W$71*AB69 -> 32717.343 | AD70: =$W$71*AC69 -> 37903.1 | AE70: =$W$71*AD69 -> 43751.877 | AF70: =$W$71*AE69 -> 49624.603 | ... AJ70: =$W$71*AI69 -> 79457.754
D71: =AVERAGE(D68:D70) -> 8099.6973 | E71: =AVERAGE(E68:E70) -> 52572.077 | F71: =AVERAGE(F68:F70) -> 0.11358897 | G71: =AVERAGE(G68:G70) -> 64056.863 | H71: =G71-D71 -> 55957.166 | I71: =H71/E71 -> 1.0643895 | J71: Target long-term | W71: =I71 -> 1.0643895
B72: The carrying values of the Company’s borrowings were as follows (in millions): | J72: Dividends | R72: =R69*0.025 -> 113.44346 | S72: =S69*0.05 -> 288.38682 | T72: =T69*0.075 -> 541.30131 | U72: =U69*0.1 -> 892.30707 | V72: =$U$73*V69 -> 1241.1329 | W72: =$U$73*W69 -> 1507.42 | X72: =$U$73*X69 -> 1822.0938 | Y72: =$U$73*Y69 -> 2184.7511 | Z72: =$U$73*Z69 -> 2568.3287 | AA72: =$U$73*AA69 -> 3001.4235 | AB72: =$U$73*AB69 -> 3491.5127 | AC72: =$U$73*AC69 -> 4044.9237 | ... AJ72: =$U$73*AJ69 -> 9354.0243
B73: Instrument | C73: Rate | D73: Principal 2022 | U73: =F71 -> 0.11358897
B74: 2023 Senior Notes | C74: 0.0325 | D74: 1000 | E74: =D74*C74 -> 32.5
B75: Loan assumed on 50 Fremont | C75: 0.0375 | D75: 186 | E75: =D75*C75 -> 6.975
B76: 2024 Senior Notes | C76: 0.00625 | D76: 1000 | E76: =D76*C76 -> 6.25
B77: 2028 Senior Notes | C77: 0.037 | D77: 1500 | E77: =D77*C77 -> 55.5
B78: 2028 Senior Sustainability Notes | C78: 0.015 | D78: 1000 | E78: =D78*C78 -> 15
B79: 2031 Senior Notes | C79: 0.0195 | D79: 1500 | E79: =D79*C79 -> 29.25
B80: 2041 Senior Notes | C80: 0.027 | D80: 1250 | E80: =D80*C80 -> 33.75
B81: 2051 Senior Notes . | C81: 0.029 | D81: 2000 | E81: =D81*C81 -> 58
B82: 2061 Senior Notes . | C82: 0.0305 | D82: 1250 | E82: =D82*C82 -> 38.125
B83: Total carrying value of debt . . | D83: =SUM(D74:D82) -> 10686 | E83: =SUM(E74:E82) -> 275.35 | F83: =E83/D83 -> 0.025767359
B84: Less current portion of debt . .
B85: Total noncurrent debt . .
C90: Last 5 Years | I90: Short Term Forecast
C91: 2017 | D91: 2018 | E91: 2019 | F91: 2020 | G91: 2021 | H91: 2022 | I91: 2023 | J91: =I91+1 -> 2024 | K91: =J91+1 -> 2025 | L91: =K91+1 -> 2026 | M91: =L91+1 -> 2027 | N91: =M91+1 -> 2028 | O91: =N91+1 -> 2029 | P91: =O91+1 -> 2030 | Q91: =P91+1 -> 2031 | ... AH91: =AG91+1 -> 2048
B92: CAPEX | C92: ='Fin. Data'!G32 -> -534 | D92: ='Fin. Data'!F32 -> -595 | E92: ='Fin. Data'!E32 -> -643 | F92: ='Fin. Data'!D32 -> -710 | G92: ='Fin. Data'!C32 -> -717 | H92: ='Fin. Data'!B32 -> -798 | I92: =I41*I93 -> -1204.5883 | J92: =J41*J93 -> -1438.3813 | K92: =K41*K93 -> -1681.5905 | L92: =L41*L93 -> -1915.4752 | M92: =M41*M93 -> -2143.5803 | N92: =N41*N93 -> -2388.1315 | O92: =O41*O93 -> -2658.1943 | P92: =P41*P93 -> -2956.139 | ... AH92: =AH41*AH93 -> -11751.925
B93: % of Sales | C93: =C92/C41 -> -0.050664137 | D93: =D92/D41 -> -0.04479747 | E93: =E92/E41 -> -0.037606738 | F93: =F92/F41 -> -0.03340862 | G93: =G92/G41 -> -0.027064774 | H93: =H92/H41 -> -0.025452922 | I93: =+$H$94 -> -0.030883263 | J93: =+$H$94 -> -0.030883263 | K93: =+$H$94 -> -0.030883263 | L93: =+$H$94 -> -0.030883263 | M93: =+$H$94 -> -0.030883263 | N93: =+$H$94 -> -0.030883263 | O93: =+$H$94 -> -0.030883263 | P93: =+$H$94 -> -0.030883263 | ... AH93: =+$H$94 -> -0.030883263
B94: Target 5y Average | H94: =AVERAGE(E93:H93) -> -0.030883263 | R94: =+H94 -> -0.030883263 | W94: =AVERAGE(S93:W93) -> -0.030883263 | AB94: =AVERAGE(X93:AB93) -> -0.030883263 | AG94: =AVERAGE(AC93:AG93) -> -0.030883263
C97: Last 5 Years | I97: Short Term Forecast
C98: 2017 | D98: 2018 | E98: 2019 | F98: 2020 | G98: 2021 | H98: 2022 | I98: 2023 | J98: =I98+1 -> 2024 | K98: =J98+1 -> 2025 | L98: =K98+1 -> 2026 | M98: =L98+1 -> 2027 | N98: =M98+1 -> 2028 | O98: =N98+1 -> 2029 | P98: =O98+1 -> 2030 | Q98: =P98+1 -> 2031 | ... AH98: =AG98+1 -> 2048
B99: Change in NWC | C99: ='Fin. Data'!G18 -> -1497 | D99: ='Fin. Data'!F18 -> 90 | E99: ='Fin. Data'!E18 -> -1915 | F99: ='Fin. Data'!D18 -> -976 | G99: ='Fin. Data'!C18 -> -1670 | H99: ='Fin. Data'!B18 -> -2529 | I99: =I41*I100 -> -2840.0743 | J99: =J41*J100 -> -3391.2913 | K99: =K41*K100 -> -3964.7091 | L99: =L41*L100 -> -4516.1422 | M99: =M41*M100 -> -5053.9488 | N99: =N41*N100 -> -5630.5305 | O99: =O41*O100 -> -6267.2613 | P99: =P41*P100 -> -6969.7297 | ... AH99: =AH41*AH100 -> -23317.883
B100: % of Sales | C100: =C99/C41 -> -0.14203036 | D100: =D99/D41 -> 0.0067760879 | E100: =E99/E41 -> -0.1120014 | F100: =F99/F41 -> -0.045925089 | G100: =G99/G41 -> -0.063037898 | H100: =H99/H41 -> -0.08066471 | I100: -0.072813896 | J100: -0.072813896 | K100: -0.072813896 | L100: -0.072813896 | M100: -0.072813896 | N100: -0.072813896 | O100: -0.072813896 | P100: -0.072813896 | Q100: -0.072813896 | R100: -0.072813896 | S100: -0.061277818 | T100: -0.061277818 | U100: -0.061277818 | V100: -0.061277818 | W100: -0.061277818 | X100: -0.061277818 | Y100: -0.061277818 | Z100: -0.061277818 | AA100: -0.061277818 | AB100: -0.061277818 | AC100: -0.061277818 | AD100: -0.061277818 | AE100: -0.061277818 | AF100: -0.061277818 | AG100: -0.061277818 | AH100: -0.061277818
B101: Target 5y Average | H101: =AVERAGE(C100:H100) -> -0.072813896 | R101: =AVERAGE(H101,D100:H100) -> -0.061277818 | W101: =AVERAGE(S100:W100) -> -0.061277818 | AB101: =AVERAGE(X100:AB100) -> -0.061277818 | AG101: =AVERAGE(AC100:AG100) -> -0.061277818
C103: Last 5 Years | I103: Short Term Forecast
C104: 2017 | D104: 2018 | E104: 2019 | F104: 2020 | G104: 2021 | H104: 2022 | I104: 2023 | J104: =I104+1 -> 2024 | K104: =J104+1 -> 2025 | L104: =K104+1 -> 2026 | M104: =L104+1 -> 2027 | N104: =M104+1 -> 2028 | O104: =N104+1 -> 2029 | P104: =O104+1 -> 2030 | Q104: =P104+1 -> 2031 | ... AH104: =AG104+1 -> 2048
B105: Total Assets | C105: ='Fin. Data'!G44 -> 21984 | D105: ='Fin. Data'!F44 -> 30737 | E105: ='Fin. Data'!E44 -> 55126 | F105: ='Fin. Data'!D44 -> 66301 | G105: ='Fin. Data'!C44 -> 95209 | H105: ='Fin. Data'!B44 -> 98849 | I105: =+H105*(1+I106) -> 125417.48 | J105: =+I105*(1+J106) -> 152856.12 | K105: =+J105*(1+K106) -> 178654.94 | L105: =+K105*(1+L106) -> 199875.3 | M105: =+L105*(1+M106) -> 213622.42 | N105: =+M105*(1+N106) -> 227246.92 | O105: =+N105*(1+O106) -> 240604.15 | P105: =+O105*(1+P106) -> 253543.47 | ... AH105: =+AG105*(1+AH106) -> 519849.87
B106: % of Sales | D106: =+D105/C105-1 -> 0.3981532 | E106: =+E105/D105-1 -> 0.79347366 | F106: =+F105/E105-1 -> 0.20271741 | G106: =+G105/F105-1 -> 0.43601152 | H106: =+H105/G105-1 -> 0.03823168 | I106: =+$H$107 -> 0.26877845 | J106: =+$H$107-0.05 -> 0.21877845 | K106: =+$J$106-0.05 -> 0.16877845 | L106: =+$K$106-0.05 -> 0.11877845 | M106: =+$L$106-0.05 -> 0.068778454 | N106: =M106-0.005 -> 0.063778454 | O106: =N106-0.005 -> 0.058778454 | P106: =O106-0.005 -> 0.053778454 | Q106: =P106-0.005 -> 0.048778454 | R106: =Q106-0.005 -> 0.043778454 | S106: =+$R$107 -> 0.04 | T106: =+$R$107 -> 0.04 | U106: =+$R$107 -> 0.04 | V106: =+$R$107 -> 0.04 | W106: =+$R$107 -> 0.04 | X106: =+$R$107 -> 0.04 | Y106: =+$R$107 -> 0.04 | Z106: =+$R$107 -> 0.04 | ... AH106: =+$R$107 -> 0.04
B107: Target 5y Average | H107: =AVERAGE(D106,F106:H106) -> 0.26877845 | R107: 0.04
B109: Total Liabilities | C109: ='Fin. Data'!G56 -> 11608 | D109: ='Fin. Data'!F56 -> 15132 | E109: ='Fin. Data'!E56 -> 21241 | F109: ='Fin. Data'!D56 -> 24808 | G109: ='Fin. Data'!C56 -> 37078 | H109: ='Fin. Data'!B56 -> 40490 | I109: =+H109*(1+I110) -> 51200.966 | J109: =+I109*(1+J110) -> 62185.293 | K109: =+J109*(1+K110) -> 72416.864 | L109: =+K109*(1+L110) -> 80711.029 | M109: =+L109*(1+M110) -> 85919.602 | N109: =+M109*(1+N110) -> 91034.706 | O109: =+N109*(1+O110) -> 95999.157 | P109: =+O109*(1+P110) -> 100754.34 | ... R109: =+Q109*(1+R110) -> 109401.86 | S109: =R109*(1+S110) -> 113230.93 | T109: =S109*(1+T110) -> 117194.01 | U109: =T109*(1+U110) -> 121295.8 | V109: =U109*(1+V110) -> 125541.15 | W109: =V109*(1+W110) -> 129935.09 | X109: =W109*(1+X110) -> 134482.82 | Y109: =X109*(1+Y110) -> 139189.72 | Z109: =Y109*(1+Z110) -> 144061.36 | ... AH109: =AG109*(1+AH110) -> 189701.3
B110: % of Sales | D110: =+D109/C109-1 -> 0.30358374 | E110: =+E109/D109-1 -> 0.40371398 | F110: =+F109/E109-1 -> 0.16792995 | G110: =+G109/F109-1 -> 0.49459852 | H110: =+H109/G109-1 -> 0.092022223 | I110: =+$H$111 -> 0.26453361 | J110: =+$I$110-0.05 -> 0.21453361 | K110: =+$J$110-0.05 -> 0.16453361 | L110: =+$K$110-0.05 -> 0.11453361 | M110: =+$L$110-0.05 -> 0.064533606 | N110: =M110-0.005 -> 0.059533606 | O110: =N110-0.005 -> 0.054533606 | P110: =O110-0.005 -> 0.049533606 | Q110: =P110-0.005 -> 0.044533606 | R110: =Q110-0.005 -> 0.039533606 | S110: =+$R$111 -> 0.035 | T110: =+$R$111 -> 0.035 | U110: =+$R$111 -> 0.035 | V110: =+$R$111 -> 0.035 | W110: =+$R$111 -> 0.035 | X110: =+$R$111 -> 0.035 | Y110: =+$R$111 -> 0.035 | Z110: =+$R$111 -> 0.035 | ... AH110: =+$R$111 -> 0.035
B111: Target 5y Average | H111: =AVERAGE(D110,F110:H110) -> 0.26453361 | R111: 0.035
B113: Shareholders Equity | C113: ='Fin. Data'!G64 -> 10376 | D113: ='Fin. Data'!F64 -> 15605 | E113: ='Fin. Data'!E64 -> 33885 | F113: ='Fin. Data'!D64 -> 41493 | G113: ='Fin. Data'!C64 -> 58131 | H113: ='Fin. Data'!B64 -> 58359 | I113: =+I105-I109 -> 74216.516 | J113: =+J105-J109 -> 90670.831 | K113: =+K105-K109 -> 106238.08 | L113: =+L105-L109 -> 119164.27 | M113: =+M105-M109 -> 127702.81 | N113: =+N105-N109 -> 136212.22 | O113: =+O105-O109 -> 144604.99 | P113: =+P105-P109 -> 152789.13 | ... AH113: =+AH105-AH109 -> 330148.56
C116: Last 5 Years | I116: Short Term Forecast
C117: 2017 | D117: 2018 | E117: 2019 | F117: 2020 | G117: 2021 | H117: 2022 | I117: 2023 | J117: 2024 | K117: 2025 | L117: 2026 | M117: 2027 | N117: 2028 | O117: 2029 | P117: 2030 | Q117: 2031 | R117: 2032 | S117: 2033 | T117: 2034 | U117: 2035 | V117: 2036 | W117: 2037 | X117: 2038 | Y117: 2039 | Z117: 2040 | AA117: 2041 | AB117: 2042 | AC117: 2043 | AD117: 2044 | AE117: 2045 | AF117: 2046 | AG117: 2047 | AH117: 2048
B118: Debt/Equity | C118: =C123/C113 -> 0.16576715 | D118: =D123/D113 -> 0.23364306 | E118: =E123/E113 -> 0.090246422 | F118: =F123/F113 -> 0.067505362 | G118: =G123/G113 -> 0.18883212 | H118: =H123/H113 -> 0.19520554 | I118: 0.2 | J118: 0.21 | K118: 0.22 | L118: 0.22 | M118: 0.21 | N118: 0.2 | O118: =+N118-0.001 -> 0.199 | P118: =+O118-0.001 -> 0.198 | Q118: =+P118-0.001 -> 0.197 | R118: =+Q118-0.001 -> 0.196 | S118: =+R118-0.001 -> 0.195 | T118: =+S118-0.001 -> 0.194 | U118: =+T118-0.001 -> 0.193 | V118: =+U118-0.001 -> 0.192 | ... AH118: =+AG118-0.001 -> 0.18
B119: Target 5y Average | H119: =+AVERAGE(C118:D118,G118:H118) -> 0.19586197
C121: Last 5 Years | I121: Short Term Forecast
C122: 2017 | D122: 2018 | E122: 2019 | F122: 2020 | G122: 2021 | H122: 2022 | I122: 2023 | J122: =I122+1 -> 2024 | K122: =J122+1 -> 2025 | L122: =K122+1 -> 2026 | M122: =L122+1 -> 2027 | N122: =M122+1 -> 2028 | O122: =N122+1 -> 2029 | P122: =O122+1 -> 2030 | Q122: =P122+1 -> 2031 | ... AH122: =AG122+1 -> 2048
B123: Total Debt | C123: ='Fin. Data'!G58 -> 1720 | D123: ='Fin. Data'!F58 -> 3646 | E123: ='Fin. Data'!E58 -> 3058 | F123: ='Fin. Data'!D58 -> 2801 | G123: ='Fin. Data'!C58 -> 10977 | H123: ='Fin. Data'!B58 -> 11392 | I123: =+I113*I118 -> 14843.303 | J123: =+J113*J118 -> 19040.874 | K123: =+K113*K118 -> 23372.378 | L123: =+L113*L118 -> 26216.14 | M123: =+M113*M118 -> 26817.591 | N123: =+N113*N118 -> 27242.444 | O123: =+O113*O118 -> 28776.393 | P123: =+P113*P118 -> 30252.247 | ... AH123: =+AH113*AH118 -> 59426.741
B124: Flows Related To debt | C124: =C123 -> 1720 | D124: =D123-C123 -> 1926 | E124: =E123-D123 -> -588 | F124: =F123-E123 -> -257 | G124: =G123-F123 -> 8176 | H124: =H123-G123 -> 415 | I124: =+I123-H123 -> 3451.3031 | J124: =+J123-I123 -> 4197.5713 | K124: =+K123-J123 -> 4331.5033 | L124: =+L123-K123 -> 2843.7626 | M124: =+M123-L123 -> 601.45079 | N124: =+N123-M123 -> 424.85261 | O124: =+O123-N123 -> 1533.9494 | P124: =+P123-O123 -> 1475.8537 | ... AH124: =+AH123-AG123 -> 2127.6877
B125: %of Net Sales | C125: =C124/C41 -> 0.16318786 | D125: =D124/D41 -> 0.14500828 | E125: =E124/E41 -> -0.034389987 | F125: =F124/F41 -> -0.012092979 | G125: =G124/G41 -> 0.30862147 | H125: =H124/H41 -> 0.013236795
H126: =AVERAGE(H125,C125:F125) -> 0.054989993
C128: Industry Average | J128: Short Term Forecast
C129: Dividends | D129: Net Iincome | E129: Payout | F129: Dividends + Buybacks | G129: Buybacks | H129: Buybacks % Net Income | I129: Cash Return % Net Income
B130: Net Income distribution | C130: =+'Industry Averages'!C92 -> 24238.726 | D130: =+'Industry Averages'!D92 -> 71266.943 | E130: =+'Industry Averages'!E92 -> 0.34011177 | F130: =+'Industry Averages'!F92 -> 81788.362 | G130: =+F130-C130 -> 57549.636 | H130: =+G130/D130 -> 0.80752216 | I130: =+'Industry Averages'!G92 -> 1.1476339 | J130: 2023 | K130: =J130+1 -> 2024 | L130: =K130+1 -> 2025 | M130: =L130+1 -> 2026 | N130: =M130+1 -> 2027 | O130: =N130+1 -> 2028 | P130: =O130+1 -> 2029 | Q130: =P130+1 -> 2030 | R130: =Q130+1 -> 2031 | ... AI130: =AH130+1 -> 2048
...

Sheet Fin. Data
A1: =Inputs!H3 -> SALESFORCE, INC. (XNYS:CRM)
A2: =Inputs!G2 -> Figures in Millions of USD
A3: Results
B4: =OP!J20 -> 2022 | C4: =B4-1 -> 2021 | D4: =C4-1 -> 2020 | E4: =D4-1 -> 2019 | F4: =E4-1 -> 2018 | G4: =F4-1 -> 2017 | H4: =G4-1 -> 2016 | I4: =H4-1 -> 2015 | J4: =I4-1 -> 2014 | ... M4: =L4-1 -> 2011
A5: Net Sales | B5: =_xlfn.XLOOKUP($A5,Inputs!$A:$A,Inputs!B:B,,0) -> 31352 | C5: =_xlfn.XLOOKUP($A5,Inputs!$A:$A,Inputs!C:C,,0) -> 26492 | D5: =_xlfn.XLOOKUP($A5,Inputs!$A:$A,Inputs!D:D,,0) -> 21252 | E5: =_xlfn.XLOOKUP($A5,Inputs!$A:$A,Inputs!E:E,,0) -> 17098 | F5: =_xlfn.XLOOKUP($A5,Inputs!$A:$A,Inputs!F:F,,0) -> 13282 | G5: =_xlfn.XLOOKUP($A5,Inputs!$A:$A,Inputs!G:G,,0) -> 10540 | H5: =_xlfn.XLOOKUP($A5,Inputs!$A:$A,Inputs!H:H,,0) -> 8437 | I5: =_xlfn.XLOOKUP($A5,Inputs!$A:$A,Inputs!I:I,,0) -> 6667 | J5: =_xlfn.XLOOKUP($A5,Inputs!$A:$A,Inputs!J:J,,0) -> 5374 | K5: =_xlfn.XLOOKUP($A5,Inputs!$A:$A,Inputs!K:K,,0) -> 4071 | L5: =_xlfn.XLOOKUP($A5,Inputs!$A:$A,Inputs!L:L,,0) -> 3050 | M5: =_xlfn.XLOOKUP($A5,Inputs!$A:$A,Inputs!M:M,,0) -> 2267
A6: Growth vs. Previous year | B6: =IFERROR(B5/C5-1,"-") -> 0.18345161 | C6: =IFERROR(C5/D5-1,"-") -> 0.24656503 | D6: =IFERROR(D5/E5-1,"-") -> 0.24295239 | E6: =IFERROR(E5/F5-1,"-") -> 0.28730613 | F6: =IFERROR(F5/G5-1,"-") -> 0.2601518 | G6: =IFERROR(G5/H5-1,"-") -> 0.24925922 | H6: =IFERROR(H5/I5-1,"-") -> 0.26548673 | I6: =IFERROR(I5/J5-1,"-") -> 0.2406029 | ... L6: =IFERROR(L5/M5-1,"-") -> 0.34539038 | M6: =IFERROR(M5/#REF!-1,"-") -> -
A7: Gross Profit | B7: =_xlfn.XLOOKUP($A7,Inputs!$A:$A,Inputs!B:B,,0) -> 22992 | C7: =_xlfn.XLOOKUP($A7,Inputs!$A:$A,Inputs!C:C,,0) -> 19466 | D7: =_xlfn.XLOOKUP($A7,Inputs!$A:$A,Inputs!D:D,,0) -> 15814 | E7: =_xlfn.XLOOKUP($A7,Inputs!$A:$A,Inputs!E:E,,0) -> 12863 | F7: =_xlfn.XLOOKUP($A7,Inputs!$A:$A,Inputs!F:F,,0) -> 9831 | G7: =_xlfn.XLOOKUP($A7,Inputs!$A:$A,Inputs!G:G,,0) -> 7767 | H7: =_xlfn.XLOOKUP($A7,Inputs!$A:$A,Inputs!H:H,,0) -> 6203 | I7: =_xlfn.XLOOKUP($A7,Inputs!$A:$A,Inputs!I:I,,0) -> 5013 | J7: =_xlfn.XLOOKUP($A7,Inputs!$A:$A,Inputs!J:J,,0) -> 4084 | K7: =_xlfn.XLOOKUP($A7,Inputs!$A:$A,Inputs!K:K,,0) -> 3103 | L7: =_xlfn.XLOOKUP($A7,Inputs!$A:$A,Inputs!L:L,,0) -> 2367 | M7: =_xlfn.XLOOKUP($A7,Inputs!$A:$A,Inputs!M:M,,0) -> 1778
A8: % over sales | B8: =IFERROR(B7/B$5,"-") -> 0.73335034 | C8: =IFERROR(C7/C$5,"-") -> 0.73478786 | D8: =IFERROR(D7/D$5,"-") -> 0.7441182 | E8: =IFERROR(E7/E$5,"-") -> 0.75231021 | F8: =IFERROR(F7/F$5,"-") -> 0.74017467 | G8: =IFERROR(G7/G$5,"-") -> 0.73690702 | H8: =IFERROR(H7/H$5,"-") -> 0.73521394 | I8: =IFERROR(I7/I$5,"-") -> 0.7519124 | ... M8: =IFERROR(M7/M$5,"-") -> 0.78429643
A9: Operating expenses | B9: =B5-B11 -> 30322 | C9: =C5-C11 -> 25944 | D9: =D5-D11 -> 20797 | E9: =E5-E11 -> 16801 | F9: =F5-F11 -> 12747 | G9: =G5-G11 -> 10086 | H9: =H5-H11 -> 8219 | I9: =I5-I11 -> 6556 | ... M9: =M5-M11 -> 2302
A10: % over sales | B10: =IFERROR(B9/B$5,"-") -> 0.96714723 | C10: =IFERROR(C9/C$5,"-") -> 0.97931451 | D10: =IFERROR(D9/D$5,"-") -> 0.97859025 | E10: =IFERROR(E9/E$5,"-") -> 0.98262955 | F10: =IFERROR(F9/F$5,"-") -> 0.95971992 | G10: =IFERROR(G9/G$5,"-") -> 0.956926 | H10: =IFERROR(H9/H$5,"-") -> 0.97416143 | I10: =IFERROR(I9/I$5,"-") -> 0.98335083 | ... M10: =IFERROR(M9/M$5,"-") -> 1.0154389
A11: Operating Income | B11: =_xlfn.XLOOKUP($A11,Inputs!$A:$A,Inputs!B:B,,0) -> 1030 | C11: =_xlfn.XLOOKUP($A11,Inputs!$A:$A,Inputs!C:C,,0) -> 548 | D11: =_xlfn.XLOOKUP($A11,Inputs!$A:$A,Inputs!D:D,,0) -> 455 | E11: =_xlfn.XLOOKUP($A11,Inputs!$A:$A,Inputs!E:E,,0) -> 297 | F11: =_xlfn.XLOOKUP($A11,Inputs!$A:$A,Inputs!F:F,,0) -> 535 | G11: =_xlfn.XLOOKUP($A11,Inputs!$A:$A,Inputs!G:G,,0) -> 454 | H11: =_xlfn.XLOOKUP($A11,Inputs!$A:$A,Inputs!H:H,,0) -> 218 | I11: =_xlfn.XLOOKUP($A11,Inputs!$A:$A,Inputs!I:I,,0) -> 111 | J11: =_xlfn.XLOOKUP($A11,Inputs!$A:$A,Inputs!J:J,,0) -> -146 | K11: =_xlfn.XLOOKUP($A11,Inputs!$A:$A,Inputs!K:K,,0) -> -286 | L11: =_xlfn.XLOOKUP($A11,Inputs!$A:$A,Inputs!L:L,,0) -> -111 | M11: =_xlfn.XLOOKUP($A11,Inputs!$A:$A,Inputs!M:M,,0) -> -35
A12: Operating Margin | B12: =IFERROR(B11/B$5,"-") -> 0.032852769 | C12: =IFERROR(C11/C$5,"-") -> 0.02068549 | D12: =IFERROR(D11/D$5,"-") -> 0.02140975 | E12: =IFERROR(E11/E$5,"-") -> 0.017370453 | F12: =IFERROR(F11/F$5,"-") -> 0.040280078 | G12: =IFERROR(G11/G$5,"-") -> 0.043074004 | H12: =IFERROR(H11/H$5,"-") -> 0.025838568 | I12: =IFERROR(I11/I$5,"-") -> 0.016649168 | ... M12: =IFERROR(M11/M$5,"-") -> -0.015438906
A13: Growth vs. Previous year | B13: =IFERROR(B12/C12-1,"-") -> 0.58820355 | C13: =IFERROR(C12/D12-1,"-") -> -0.0338285 | D13: =IFERROR(D12/E12-1,"-") -> 0.23253838 | E13: =IFERROR(E12/F12-1,"-") -> -0.56875822 | F13: =IFERROR(F12/G12-1,"-") -> -0.06486338 | G13: =IFERROR(G12/H12-1,"-") -> 0.66704298 | H13: =IFERROR(H12/I12-1,"-") -> 0.55194355 | I13: =IFERROR(I12/J12-1,"-") -> -1.6128262 | ... L13: =IFERROR(L12/M12-1,"-") -> 1.3572553 | M13: =IFERROR(M12/#REF!-1,"-") -> -
A14: Net Financial Cost | B14: =_xlfn.XLOOKUP($A14,Inputs!$A:$A,Inputs!B:B,,0) -> -131 | C14: =_xlfn.XLOOKUP($A14,Inputs!$A:$A,Inputs!C:C,,0) -> -227 | D14: =_xlfn.XLOOKUP($A14,Inputs!$A:$A,Inputs!D:D,,0) -> -64 | E14: =_xlfn.XLOOKUP($A14,Inputs!$A:$A,Inputs!E:E,,0) -> -18 | F14: =_xlfn.XLOOKUP($A14,Inputs!$A:$A,Inputs!F:F,,0) -> -94 | G14: =_xlfn.XLOOKUP($A14,Inputs!$A:$A,Inputs!G:G,,0) -> -53 | H14: =_xlfn.XLOOKUP($A14,Inputs!$A:$A,Inputs!H:H,,0) -> -88.98 | I14: =_xlfn.XLOOKUP($A14,Inputs!$A:$A,Inputs!I:I,,0) -> -72.48 | J14: =_xlfn.XLOOKUP($A14,Inputs!$A:$A,Inputs!J:J,,0) -> -73.23 | K14: =_xlfn.XLOOKUP($A14,Inputs!$A:$A,Inputs!K:K,,0) -> -77.21 | L14: =_xlfn.XLOOKUP($A14,Inputs!$A:$A,Inputs!L:L,,0) -> -30.94 | M14: =_xlfn.XLOOKUP($A14,Inputs!$A:$A,Inputs!M:M,,0) -> -17.045
A15: Other Expenses (Revenues) | B15: =_xlfn.XLOOKUP($A15,Inputs!$A:$A,Inputs!B:B,,0) -> 131 | C15: =_xlfn.XLOOKUP($A15,Inputs!$A:$A,Inputs!C:C,,0) -> 227 | D15: =_xlfn.XLOOKUP($A15,Inputs!$A:$A,Inputs!D:D,,0) -> 664 | E15: =_xlfn.XLOOKUP($A15,Inputs!$A:$A,Inputs!E:E,,0) -> 18 | F15: =_xlfn.XLOOKUP($A15,Inputs!$A:$A,Inputs!F:F,,0) -> 94 | G15: =_xlfn.XLOOKUP($A15,Inputs!$A:$A,Inputs!G:G,,0) -> 53 | H15: =_xlfn.XLOOKUP($A15,Inputs!$A:$A,Inputs!H:H,,0) -> -9 | I15: =_xlfn.XLOOKUP($A15,Inputs!$A:$A,Inputs!I:I,,0) -> 15.2 | J15: =_xlfn.XLOOKUP($A15,Inputs!$A:$A,Inputs!J:J,,0) -> 19.8 | K15: =_xlfn.XLOOKUP($A15,Inputs!$A:$A,Inputs!K:K,,0) -> 4.8 | L15: =_xlfn.XLOOKUP($A15,Inputs!$A:$A,Inputs!L:L,,0) -> 5.6 | M15: =_xlfn.XLOOKUP($A15,Inputs!$A:$A,Inputs!M:M,,0) -> 4.45
A16: EBIT | B16: =B11-B15 -> 899 | C16: =C11-C15 -> 321 | D16: =D11-D15 -> -209 | E16: =E11-E15 -> 279 | F16: =F11-F15 -> 441 | G16: =G11-G15 -> 401 | H16: =H11-H15 -> 227 | I16: =I11-I15 -> 95.8 | ... M16: =M11-M15 -> -39.45
A17: Depreciation & Amortization | B17: =_xlfn.XLOOKUP($A17,Inputs!$A:$A,Inputs!B:B,,0) -> 3786 | C17: =_xlfn.XLOOKUP($A17,Inputs!$A:$A,Inputs!C:C,,0) -> 3298 | D17: =_xlfn.XLOOKUP($A17,Inputs!$A:$A,Inputs!D:D,,0) -> 2846 | E17: =_xlfn.XLOOKUP($A17,Inputs!$A:$A,Inputs!E:E,,0) -> 2135 | F17: =_xlfn.XLOOKUP($A17,Inputs!$A:$A,Inputs!F:F,,0) -> 962 | G17: =_xlfn.XLOOKUP($A17,Inputs!$A:$A,Inputs!G:G,,0) -> 753 | H17: =_xlfn.XLOOKUP($A17,Inputs!$A:$A,Inputs!H:H,,0) -> 632 | I17: =_xlfn.XLOOKUP($A17,Inputs!$A:$A,Inputs!I:I,,0) -> 525.8 | J17: =_xlfn.XLOOKUP($A17,Inputs!$A:$A,Inputs!J:J,,0) -> 448.3 | K17: =_xlfn.XLOOKUP($A17,Inputs!$A:$A,Inputs!K:K,,0) -> 369.4 | L17: =_xlfn.XLOOKUP($A17,Inputs!$A:$A,Inputs!L:L,,0) -> 216.8 | M17: =_xlfn.XLOOKUP($A17,Inputs!$A:$A,Inputs!M:M,,0) -> 157.3
A18: Changes Net Working Capital | B18: =_xlfn.XLOOKUP($A18,Inputs!$A:$A,Inputs!B:B,,0) -> -2529 | C18: =_xlfn.XLOOKUP($A18,Inputs!$A:$A,Inputs!C:C,,0) -> -1670 | D18: =_xlfn.XLOOKUP($A18,Inputs!$A:$A,Inputs!D:D,,0) -> -976 | E18: =_xlfn.XLOOKUP($A18,Inputs!$A:$A,Inputs!E:E,,0) -> -1915 | F18: =_xlfn.XLOOKUP($A18,Inputs!$A:$A,Inputs!F:F,,0) -> 90 | G18: =_xlfn.XLOOKUP($A18,Inputs!$A:$A,Inputs!G:G,,0) -> -1497 | H18: =_xlfn.XLOOKUP($A18,Inputs!$A:$A,Inputs!H:H,,0) -> -896 | I18: =_xlfn.XLOOKUP($A18,Inputs!$A:$A,Inputs!I:I,,0) -> -741 | J18: =_xlfn.XLOOKUP($A18,Inputs!$A:$A,Inputs!J:J,,0) -> 269 | K18: =_xlfn.XLOOKUP($A18,Inputs!$A:$A,Inputs!K:K,,0) -> -369 | L18: =_xlfn.XLOOKUP($A18,Inputs!$A:$A,Inputs!L:L,,0) -> -341 | M18: =_xlfn.XLOOKUP($A18,Inputs!$A:$A,Inputs!M:M,,0) -> -1429
A19: EBITDA | B19: =B11-B15+B17 -> 4685 | C19: =C11-C15+C17 -> 3619 | D19: =D11-D15+D17 -> 2637 | E19: =E11-E15+E17 -> 2414 | F19: =F11-F15+F17 -> 1403 | G19: =G11-G15+G17 -> 1154 | H19: =H11-H15+H17 -> 859 | I19: =I11-I15+I17 -> 621.6 | ... M19: =M11-M15+M17 -> 117.85
A20: EBITDA Margin | B20: =IFERROR(B19/B$5,"-") -> 0.14943225 | C20: =IFERROR(C19/C$5,"-") -> 0.13660728 | D20: =IFERROR(D19/D$5,"-") -> 0.12408244 | E20: =IFERROR(E19/E$5,"-") -> 0.1411861 | F20: =IFERROR(F19/F$5,"-") -> 0.10563168 | G20: =IFERROR(G19/G$5,"-") -> 0.10948767 | H20: =IFERROR(H19/H$5,"-") -> 0.10181344 | I20: =IFERROR(I19/I$5,"-") -> 0.093235338 | ... M20: =IFERROR(M19/M$5,"-") -> 0.051985002
A21: Taxes | B21: =_xlfn.XLOOKUP($A21,Inputs!$A:$A,Inputs!B:B,,0) -> 452 | C21: =_xlfn.XLOOKUP($A21,Inputs!$A:$A,Inputs!C:C,,0) -> 88 | D21: =_xlfn.XLOOKUP($A21,Inputs!$A:$A,Inputs!D:D,,0) -> -1511 | E21: =_xlfn.XLOOKUP($A21,Inputs!$A:$A,Inputs!E:E,,0) -> 574 | F21: =_xlfn.XLOOKUP($A21,Inputs!$A:$A,Inputs!F:F,,0) -> -170 | G21: =_xlfn.XLOOKUP($A21,Inputs!$A:$A,Inputs!G:G,,0) -> -66 | H21: =_xlfn.XLOOKUP($A21,Inputs!$A:$A,Inputs!H:H,,0) -> -144 | I21: =_xlfn.XLOOKUP($A21,Inputs!$A:$A,Inputs!I:I,,0) -> 112 | J21: =_xlfn.XLOOKUP($A21,Inputs!$A:$A,Inputs!J:J,,0) -> 50 | K21: =_xlfn.XLOOKUP($A21,Inputs!$A:$A,Inputs!K:K,,0) -> -126 | L21: =_xlfn.XLOOKUP($A21,Inputs!$A:$A,Inputs!L:L,,0) -> 143 | M21: =_xlfn.XLOOKUP($A21,Inputs!$A:$A,Inputs!M:M,,0) -> -22
A22: % Tax | B22: =IFERROR(B21/B$5,"-") -> 0.014416943 | C22: =IFERROR(C21/C$5,"-") -> 0.0033217575 | D22: =IFERROR(D21/D$5,"-") -> -0.071099191 | E22: =IFERROR(E21/E$5,"-") -> 0.033571178 | F22: =IFERROR(F21/F$5,"-") -> -0.012799277 | G22: =IFERROR(G21/G$5,"-") -> -0.0062618596 | H22: =IFERROR(H21/H$5,"-") -> -0.017067678 | I22: =IFERROR(I21/I$5,"-") -> 0.01679916 | ... M22: =IFERROR(M21/M$5,"-") -> -0.0097044552
A23: Net Income | B23: =_xlfn.XLOOKUP($A23,Inputs!$A:$A,Inputs!B:B,,0) -> 208 | C23: =_xlfn.XLOOKUP($A23,Inputs!$A:$A,Inputs!C:C,,0) -> 1444 | D23: =_xlfn.XLOOKUP($A23,Inputs!$A:$A,Inputs!D:D,,0) -> 4072 | E23: =_xlfn.XLOOKUP($A23,Inputs!$A:$A,Inputs!E:E,,0) -> 1266 | F23: =_xlfn.XLOOKUP($A23,Inputs!$A:$A,Inputs!F:F,,0) -> 1110 | G23: =_xlfn.XLOOKUP($A23,Inputs!$A:$A,Inputs!G:G,,0) -> 360 | H23: =_xlfn.XLOOKUP($A23,Inputs!$A:$A,Inputs!H:H,,0) -> 323 | I23: =_xlfn.XLOOKUP($A23,Inputs!$A:$A,Inputs!I:I,,0) -> -47.4 | J23: =_xlfn.XLOOKUP($A23,Inputs!$A:$A,Inputs!J:J,,0) -> -262.7 | K23: =_xlfn.XLOOKUP($A23,Inputs!$A:$A,Inputs!K:K,,0) -> -232.2 | L23: =_xlfn.XLOOKUP($A23,Inputs!$A:$A,Inputs!L:L,,0) -> -270.4 | M23: =_xlfn.XLOOKUP($A23,Inputs!$A:$A,Inputs!M:M,,0) -> -11.6
A24: Net Income Margin | B24: =IFERROR(B23/B$5,"-") -> 0.0066343455 | C24: =IFERROR(C23/C$5,"-") -> 0.054507021 | D24: =IFERROR(D23/D$5,"-") -> 0.1916055 | E24: =IFERROR(E23/E$5,"-") -> 0.074043748 | F24: =IFERROR(F23/F$5,"-") -> 0.083571751 | G24: =IFERROR(G23/G$5,"-") -> 0.034155598 | H24: =IFERROR(H23/H$5,"-") -> 0.03828375 | I24: =IFERROR(I23/I$5,"-") -> -0.0071096445 | ... M24: =IFERROR(M23/M$5,"-") -> -0.0051168946
A25: Growth vs. Previous year | B25: =IFERROR(B24/C24-1,"-") -> -0.87828457 | C25: =IFERROR(C24/D24-1,"-") -> -0.71552475 | D25: =IFERROR(D24/E24-1,"-") -> 1.5877336 | E25: =IFERROR(E24/F24-1,"-") -> -0.11400986 | F25: =IFERROR(F24/G24-1,"-") -> 1.4467952 | G25: =IFERROR(G24/H24-1,"-") -> -0.10783041 | H25: =IFERROR(H24/I24-1,"-") -> -6.3847629 | I25: =IFERROR(I24/J24-1,"-") -> -0.85455946 | ... L25: =IFERROR(L24/M24-1,"-") -> 16.326083 | M25: =IFERROR(M24/#REF!-1,"-") -> -
A26: Cash Generated | B26: =B39-C39 -> 1971 | C26: =C39-D39 -> -1429 | D26: =D39-E39 -> 4019 | E26: =E39-F39 -> 3605 | F26: =F39-G39 -> -179 | G26: =G39-H39 -> 2312 | H26: =H39-I39 -> -516 | I26: =I39-J39 -> 1730 | ... M26: =M39-N39 -> 778
A27: Dividends | B27: =_xlfn.XLOOKUP($A27,Inputs!$A:$A,Inputs!B:B,,0) -> 0 | C27: =_xlfn.XLOOKUP($A27,Inputs!$A:$A,Inputs!C:C,,0) -> 0 | D27: =_xlfn.XLOOKUP($A27,Inputs!$A:$A,Inputs!D:D,,0) -> 0 | E27: =_xlfn.XLOOKUP($A27,Inputs!$A:$A,Inputs!E:E,,0) -> 0 | F27: =_xlfn.XLOOKUP($A27,Inputs!$A:$A,Inputs!F:F,,0) -> 0 | G27: =_xlfn.XLOOKUP($A27,Inputs!$A:$A,Inputs!G:G,,0) -> 0 | H27: =_xlfn.XLOOKUP($A27,Inputs!$A:$A,Inputs!H:H,,0) -> 0 | I27: =_xlfn.XLOOKUP($A27,Inputs!$A:$A,Inputs!I:I,,0) -> 0 | J27: =_xlfn.XLOOKUP($A27,Inputs!$A:$A,Inputs!J:J,,0) -> 0 | K27: =_xlfn.XLOOKUP($A27,Inputs!$A:$A,Inputs!K:K,,0) -> 0 | L27: =_xlfn.XLOOKUP($A27,Inputs!$A:$A,Inputs!L:L,,0) -> 0 | M27: =_xlfn.XLOOKUP($A27,Inputs!$A:$A,Inputs!M:M,,0) -> 0
A28: Share buyback | B28: =_xlfn.XLOOKUP($A28,Inputs!$A:$A,Inputs!B:B,,0) -> -4000 | C28: =_xlfn.XLOOKUP($A28,Inputs!$A:$A,Inputs!C:C,,0) -> 0 | D28: =_xlfn.XLOOKUP($A28,Inputs!$A:$A,Inputs!D:D,,0) -> 0 | E28: =_xlfn.XLOOKUP($A28,Inputs!$A:$A,Inputs!E:E,,0) -> 0 | F28: =_xlfn.XLOOKUP($A28,Inputs!$A:$A,Inputs!F:F,,0) -> 0 | G28: =_xlfn.XLOOKUP($A28,Inputs!$A:$A,Inputs!G:G,,0) -> 0 | H28: =_xlfn.XLOOKUP($A28,Inputs!$A:$A,Inputs!H:H,,0) -> 0 | I28: =_xlfn.XLOOKUP($A28,Inputs!$A:$A,Inputs!I:I,,0) -> 0 | J28: =_xlfn.XLOOKUP($A28,Inputs!$A:$A,Inputs!J:J,,0) -> 0 | K28: =_xlfn.XLOOKUP($A28,Inputs!$A:$A,Inputs!K:K,,0) -> 0 | L28: =_xlfn.XLOOKUP($A28,Inputs!$A:$A,Inputs!L:L,,0) -> 0 | M28: =_xlfn.XLOOKUP($A28,Inputs!$A:$A,Inputs!M:M,,0) -> 0
A29: Net Cash Flow | B29: =SUM(B26:B28) -> -2029 | C29: =SUM(C26:C28) -> -1429 | D29: =SUM(D26:D28) -> 4019 | E29: =SUM(E26:E28) -> 3605 | F29: =SUM(F26:F28) -> -179 | G29: =SUM(G26:G28) -> 2312 | H29: =SUM(H26:H28) -> -516 | I29: =SUM(I26:I28) -> 1730 | ... M29: =SUM(M26:M28) -> 778
A30: FNP'' | B30: =+B29-(B58-C29) -> -14850 | C30: =+C29-(C58-D29) -> -8387 | D30: =+D29-(D58-E29) -> 4823 | E30: =+E29-(E58-F29) -> 368 | F30: =+F29-(F58-G29) -> -1513 | G30: =+G29-(G58-H29) -> 76 | H30: =+H29-(H58-I29) -> -1578 | I30: =+I29-(I58-J29) -> -162 | ... M30: =+M29-(M58-N29) -> 282
A31: FNP' | B31: =+B30+B33 -> -15289 | C31: =+C30+C33 -> -23263 | D31: =+D30+D33 -> 3542 | E31: =+E30+E33 -> -1 | F31: =+F30+F33 -> -6628 | G31: =+G30+G33 -> 51 | H31: =+H30+H33 -> -4771 | I31: =+I30+I33 -> -220.7 | ... M31: =+M30+M33 -> -140.7
A32: Net Capex | B32: =_xlfn.XLOOKUP($A32,Inputs!$A:$A,Inputs!B:B,,0) -> -798 | C32: =_xlfn.XLOOKUP($A32,Inputs!$A:$A,Inputs!C:C,,0) -> -717 | D32: =_xlfn.XLOOKUP($A32,Inputs!$A:$A,Inputs!D:D,,0) -> -710 | E32: =_xlfn.XLOOKUP($A32,Inputs!$A:$A,Inputs!E:E,,0) -> -643 | F32: =_xlfn.XLOOKUP($A32,Inputs!$A:$A,Inputs!F:F,,0) -> -595 | G32: =_xlfn.XLOOKUP($A32,Inputs!$A:$A,Inputs!G:G,,0) -> -534 | H32: =_xlfn.XLOOKUP($A32,Inputs!$A:$A,Inputs!H:H,,0) -> -464 | I32: =_xlfn.XLOOKUP($A32,Inputs!$A:$A,Inputs!I:I,,0) -> -709.9 | J32: =_xlfn.XLOOKUP($A32,Inputs!$A:$A,Inputs!J:J,,0) -> -290.5 | K32: =_xlfn.XLOOKUP($A32,Inputs!$A:$A,Inputs!K:K,,0) -> -299.1 | L32: =_xlfn.XLOOKUP($A32,Inputs!$A:$A,Inputs!L:L,,0) -> -175.6 | M32: =_xlfn.XLOOKUP($A32,Inputs!$A:$A,Inputs!M:M,,0) -> -151.6
A33: Investments & Acquisitions | B33: =_xlfn.XLOOKUP($A33,Inputs!$A:$A,Inputs!B:B,,0) -> -439 | C33: =_xlfn.XLOOKUP($A33,Inputs!$A:$A,Inputs!C:C,,0) -> -14876 | D33: =_xlfn.XLOOKUP($A33,Inputs!$A:$A,Inputs!D:D,,0) -> -1281 | E33: =_xlfn.XLOOKUP($A33,Inputs!$A:$A,Inputs!E:E,,0) -> -369 | F33: =_xlfn.XLOOKUP($A33,Inputs!$A:$A,Inputs!F:F,,0) -> -5115 | G33: =_xlfn.XLOOKUP($A33,Inputs!$A:$A,Inputs!G:G,,0) -> -25 | H33: =_xlfn.XLOOKUP($A33,Inputs!$A:$A,Inputs!H:H,,0) -> -3193 | I33: =_xlfn.XLOOKUP($A33,Inputs!$A:$A,Inputs!I:I,,0) -> -58.7 | J33: =_xlfn.XLOOKUP($A33,Inputs!$A:$A,Inputs!J:J,,0) -> 0 | K33: =_xlfn.XLOOKUP($A33,Inputs!$A:$A,Inputs!K:K,,0) -> -2617.3 | L33: =_xlfn.XLOOKUP($A33,Inputs!$A:$A,Inputs!L:L,,0) -> -579.7 | M33: =_xlfn.XLOOKUP($A33,Inputs!$A:$A,Inputs!M:M,,0) -> -422.7
A34: Capex + Investments | B34: =+B32+B33 -> -1237 | C34: =+C32+C33 -> -15593 | D34: =+D32+D33 -> -1991 | E34: =+E32+E33 -> -1012 | F34: =+F32+F33 -> -5710 | G34: =+G32+G33 -> -559 | H34: =+H32+H33 -> -3657 | I34: =+I32+I33 -> -768.6 | ... M34: =+M32+M33 -> -574.3
A35: Dividends + Share Buyback | B35: =+B27+B28 -> -4000 | C35: =+C27+C28 -> 0 | D35: =+D27+D28 -> 0 | E35: =+E27+E28 -> 0 | F35: =+F27+F28 -> 0 | G35: =+G27+G28 -> 0 | H35: =+H27+H28 -> 0 | I35: =+I27+I28 -> 0 | ... M35: =+M27+M28 -> 0
A36: Payout Ratio | B36: =IFERROR(B35/B23,"-") -> -19.230769 | C36: =IFERROR(C35/C23,"-") -> 0 | D36: =IFERROR(D35/D23,"-") -> 0 | E36: =IFERROR(E35/E23,"-") -> 0 | F36: =IFERROR(F35/F23,"-") -> 0 | G36: =IFERROR(G35/G23,"-") -> 0 | H36: =IFERROR(H35/H23,"-") -> 0 | I36: =IFERROR(I35/I23,"-") -> 0 | ... M36: =IFERROR(M35/M23,"-") -> 0
A38: Assets
A39: Cash & Eq. | B39: =_xlfn.XLOOKUP($A39,Inputs!$A:$A,Inputs!B:B,,0) -> 12508 | C39: =_xlfn.XLOOKUP($A39,Inputs!$A:$A,Inputs!C:C,,0) -> 10537 | D39: =_xlfn.XLOOKUP($A39,Inputs!$A:$A,Inputs!D:D,,0) -> 11966 | E39: =_xlfn.XLOOKUP($A39,Inputs!$A:$A,Inputs!E:E,,0) -> 7947 | F39: =_xlfn.XLOOKUP($A39,Inputs!$A:$A,Inputs!F:F,,0) -> 4342 | G39: =_xlfn.XLOOKUP($A39,Inputs!$A:$A,Inputs!G:G,,0) -> 4521 | H39: =_xlfn.XLOOKUP($A39,Inputs!$A:$A,Inputs!H:H,,0) -> 2209 | I39: =_xlfn.XLOOKUP($A39,Inputs!$A:$A,Inputs!I:I,,0) -> 2725 | J39: =_xlfn.XLOOKUP($A39,Inputs!$A:$A,Inputs!J:J,,0) -> 995 | K39: =_xlfn.XLOOKUP($A39,Inputs!$A:$A,Inputs!K:K,,0) -> 839 | L39: =_xlfn.XLOOKUP($A39,Inputs!$A:$A,Inputs!L:L,,0) -> 868 | M39: =_xlfn.XLOOKUP($A39,Inputs!$A:$A,Inputs!M:M,,0) -> 778
A40: Accounts Receivable | B40: =_xlfn.XLOOKUP($A40,Inputs!$A:$A,Inputs!B:B,,0) -> 12531 | C40: =_xlfn.XLOOKUP($A40,Inputs!$A:$A,Inputs!C:C,,0) -> 11193 | D40: =_xlfn.XLOOKUP($A40,Inputs!$A:$A,Inputs!D:D,,0) -> 8932 | E40: =_xlfn.XLOOKUP($A40,Inputs!$A:$A,Inputs!E:E,,0) -> 7100 | F40: =_xlfn.XLOOKUP($A40,Inputs!$A:$A,Inputs!F:F,,0) -> 5712 | G40: =_xlfn.XLOOKUP($A40,Inputs!$A:$A,Inputs!G:G,,0) -> 4592 | H40: =_xlfn.XLOOKUP($A40,Inputs!$A:$A,Inputs!H:H,,0) -> 3197 | I40: =_xlfn.XLOOKUP($A40,Inputs!$A:$A,Inputs!I:I,,0) -> 2496 | J40: =_xlfn.XLOOKUP($A40,Inputs!$A:$A,Inputs!J:J,,0) -> 1906 | K40: =_xlfn.XLOOKUP($A40,Inputs!$A:$A,Inputs!K:K,,0) -> 1361 | L40: =_xlfn.XLOOKUP($A40,Inputs!$A:$A,Inputs!L:L,,0) -> 873 | M40: =_xlfn.XLOOKUP($A40,Inputs!$A:$A,Inputs!M:M,,0) -> 684
A41: Inventory | B41: =_xlfn.XLOOKUP($A41,Inputs!$A:$A,Inputs!B:B,,0) -> 0 | C41: =_xlfn.XLOOKUP($A41,Inputs!$A:$A,Inputs!C:C,,0) -> 0 | D41: =_xlfn.XLOOKUP($A41,Inputs!$A:$A,Inputs!D:D,,0) -> 0 | E41: =_xlfn.XLOOKUP($A41,Inputs!$A:$A,Inputs!E:E,,0) -> 0 | F41: =_xlfn.XLOOKUP($A41,Inputs!$A:$A,Inputs!F:F,,0) -> 0 | G41: =_xlfn.XLOOKUP($A41,Inputs!$A:$A,Inputs!G:G,,0) -> 0 | H41: =_xlfn.XLOOKUP($A41,Inputs!$A:$A,Inputs!H:H,,0) -> 0 | I41: =_xlfn.XLOOKUP($A41,Inputs!$A:$A,Inputs!I:I,,0) -> 0 | J41: =_xlfn.XLOOKUP($A41,Inputs!$A:$A,Inputs!J:J,,0) -> 0 | K41: =_xlfn.XLOOKUP($A41,Inputs!$A:$A,Inputs!K:K,,0) -> 0 | L41: =_xlfn.XLOOKUP($A41,Inputs!$A:$A,Inputs!L:L,,0) -> 0 | M41: =_xlfn.XLOOKUP($A41,Inputs!$A:$A,Inputs!M:M,,0) -> 0
A42: Property, Plant and Equipment | B42: =_xlfn.XLOOKUP($A42,Inputs!$A:$A,Inputs!B:B,,0) -> 6592 | C42: =_xlfn.XLOOKUP($A42,Inputs!$A:$A,Inputs!C:C,,0) -> 5695 | D42: =_xlfn.XLOOKUP($A42,Inputs!$A:$A,Inputs!D:D,,0) -> 5663 | E42: =_xlfn.XLOOKUP($A42,Inputs!$A:$A,Inputs!E:E,,0) -> 5415 | F42: =_xlfn.XLOOKUP($A42,Inputs!$A:$A,Inputs!F:F,,0) -> 2051 | G42: =_xlfn.XLOOKUP($A42,Inputs!$A:$A,Inputs!G:G,,0) -> 1947 | H42: =_xlfn.XLOOKUP($A42,Inputs!$A:$A,Inputs!H:H,,0) -> 1788 | I42: =_xlfn.XLOOKUP($A42,Inputs!$A:$A,Inputs!I:I,,0) -> 1716 | J42: =_xlfn.XLOOKUP($A42,Inputs!$A:$A,Inputs!J:J,,0) -> 1126 | K42: =_xlfn.XLOOKUP($A42,Inputs!$A:$A,Inputs!K:K,,0) -> 1241 | L42: =_xlfn.XLOOKUP($A42,Inputs!$A:$A,Inputs!L:L,,0) -> 605 | M42: =_xlfn.XLOOKUP($A42,Inputs!$A:$A,Inputs!M:M,,0) -> 528
A43: Other Assets | B43: =_xlfn.XLOOKUP($A43,Inputs!$A:$A,Inputs!B:B,,0) -> 15760 | C43: =_xlfn.XLOOKUP($A43,Inputs!$A:$A,Inputs!C:C,,0) -> 16967 | D43: =_xlfn.XLOOKUP($A43,Inputs!$A:$A,Inputs!D:D,,0) -> 13422 | E43: =_xlfn.XLOOKUP($A43,Inputs!$A:$A,Inputs!E:E,,0) -> 9530 | F43: =_xlfn.XLOOKUP($A43,Inputs!$A:$A,Inputs!F:F,,0) -> 5781 | G43: =_xlfn.XLOOKUP($A43,Inputs!$A:$A,Inputs!G:G,,0) -> 3610 | H43: =_xlfn.XLOOKUP($A43,Inputs!$A:$A,Inputs!H:H,,0) -> 3128 | I43: =_xlfn.XLOOKUP($A43,Inputs!$A:$A,Inputs!I:I,,0) -> 1977 | J43: =_xlfn.XLOOKUP($A43,Inputs!$A:$A,Inputs!J:J,,0) -> 6638 | K43: =_xlfn.XLOOKUP($A43,Inputs!$A:$A,Inputs!K:K,,0) -> 2212 | L43: =_xlfn.XLOOKUP($A43,Inputs!$A:$A,Inputs!L:L,,0) -> 1654 | M43: =_xlfn.XLOOKUP($A43,Inputs!$A:$A,Inputs!M:M,,0) -> 2174
A44: Total Assets | B44: =_xlfn.XLOOKUP($A44,Inputs!$A:$A,Inputs!B:B,,0) -> 98849 | C44: =_xlfn.XLOOKUP($A44,Inputs!$A:$A,Inputs!C:C,,0) -> 95209 | D44: =_xlfn.XLOOKUP($A44,Inputs!$A:$A,Inputs!D:D,,0) -> 66301 | E44: =_xlfn.XLOOKUP($A44,Inputs!$A:$A,Inputs!E:E,,0) -> 55126 | F44: =_xlfn.XLOOKUP($A44,Inputs!$A:$A,Inputs!F:F,,0) -> 30737 | G44: =_xlfn.XLOOKUP($A44,Inputs!$A:$A,Inputs!G:G,,0) -> 21984 | H44: =_xlfn.XLOOKUP($A44,Inputs!$A:$A,Inputs!H:H,,0) -> 17585 | I44: =_xlfn.XLOOKUP($A44,Inputs!$A:$A,Inputs!I:I,,0) -> 12763 | J44: =_xlfn.XLOOKUP($A44,Inputs!$A:$A,Inputs!J:J,,0) -> 10665 | K44: =_xlfn.XLOOKUP($A44,Inputs!$A:$A,Inputs!K:K,,0) -> 9153 | L44: =_xlfn.XLOOKUP($A44,Inputs!$A:$A,Inputs!L:L,,0) -> 5529 | M44: =_xlfn.XLOOKUP($A44,Inputs!$A:$A,Inputs!M:M,,0) -> 4164
A47: Liabilities
A48: Current Liabilities | B48: =_xlfn.XLOOKUP($A48,Inputs!$A:$A,Inputs!B:B,,0) -> 25891 | C48: =_xlfn.XLOOKUP($A48,Inputs!$A:$A,Inputs!C:C,,0) -> 21788 | D48: =_xlfn.XLOOKUP($A48,Inputs!$A:$A,Inputs!D:D,,0) -> 17728 | E48: =_xlfn.XLOOKUP($A48,Inputs!$A:$A,Inputs!E:E,,0) -> 14845 | F48: =_xlfn.XLOOKUP($A48,Inputs!$A:$A,Inputs!F:F,,0) -> 11255 | G48: =_xlfn.XLOOKUP($A48,Inputs!$A:$A,Inputs!G:G,,0) -> 10067 | H48: =_xlfn.XLOOKUP($A48,Inputs!$A:$A,Inputs!H:H,,0) -> 7295 | I48: =_xlfn.XLOOKUP($A48,Inputs!$A:$A,Inputs!I:I,,0) -> 5617 | J48: =_xlfn.XLOOKUP($A48,Inputs!$A:$A,Inputs!J:J,,0) -> 4390 | K48: =_xlfn.XLOOKUP($A48,Inputs!$A:$A,Inputs!K:K,,0) -> 3980 | L48: =_xlfn.XLOOKUP($A48,Inputs!$A:$A,Inputs!L:L,,0) -> 2918 | M48: =_xlfn.XLOOKUP($A48,Inputs!$A:$A,Inputs!M:M,,0) -> 2323
A49: Short-Term Debt | B49: =_xlfn.XLOOKUP($A49,Inputs!$A:$A,Inputs!B:B,,0) -> 0 | C49: =_xlfn.XLOOKUP($A49,Inputs!$A:$A,Inputs!C:C,,0) -> 0 | D49: =_xlfn.XLOOKUP($A49,Inputs!$A:$A,Inputs!D:D,,0) -> 0 | E49: =_xlfn.XLOOKUP($A49,Inputs!$A:$A,Inputs!E:E,,0) -> 0 | F49: =_xlfn.XLOOKUP($A49,Inputs!$A:$A,Inputs!F:F,,0) -> 0 | G49: =_xlfn.XLOOKUP($A49,Inputs!$A:$A,Inputs!G:G,,0) -> 0 | H49: =_xlfn.XLOOKUP($A49,Inputs!$A:$A,Inputs!H:H,,0) -> 0 | I49: =_xlfn.XLOOKUP($A49,Inputs!$A:$A,Inputs!I:I,,0) -> 0 | J49: =_xlfn.XLOOKUP($A49,Inputs!$A:$A,Inputs!J:J,,0) -> 0 | K49: =_xlfn.XLOOKUP($A49,Inputs!$A:$A,Inputs!K:K,,0) -> 0 | L49: =_xlfn.XLOOKUP($A49,Inputs!$A:$A,Inputs!L:L,,0) -> 0 | M49: =_xlfn.XLOOKUP($A49,Inputs!$A:$A,Inputs!M:M,,0) -> 0
A50: Short-Term Leases | B50: =_xlfn.XLOOKUP($A50,Inputs!$A:$A,Inputs!B:B,,0) -> 1439 | C50: =_xlfn.XLOOKUP($A50,Inputs!$A:$A,Inputs!C:C,,0) -> 114 | D50: =_xlfn.XLOOKUP($A50,Inputs!$A:$A,Inputs!D:D,,0) -> 35 | E50: =_xlfn.XLOOKUP($A50,Inputs!$A:$A,Inputs!E:E,,0) -> 53 | F50: =_xlfn.XLOOKUP($A50,Inputs!$A:$A,Inputs!F:F,,0) -> 216 | G50: =_xlfn.XLOOKUP($A50,Inputs!$A:$A,Inputs!G:G,,0) -> 1025 | H50: =_xlfn.XLOOKUP($A50,Inputs!$A:$A,Inputs!H:H,,0) -> 102 | I50: =_xlfn.XLOOKUP($A50,Inputs!$A:$A,Inputs!I:I,,0) -> 15 | J50: =_xlfn.XLOOKUP($A50,Inputs!$A:$A,Inputs!J:J,,0) -> 0 | K50: =_xlfn.XLOOKUP($A50,Inputs!$A:$A,Inputs!K:K,,0) -> 572 | L50: =_xlfn.XLOOKUP($A50,Inputs!$A:$A,Inputs!L:L,,0) -> 521 | M50: =_xlfn.XLOOKUP($A50,Inputs!$A:$A,Inputs!M:M,,0) -> 496
A51: Other current liabilities | B51: =_xlfn.XLOOKUP($A51,Inputs!$A:$A,Inputs!B:B,,0) -> 24452 | C51: =_xlfn.XLOOKUP($A51,Inputs!$A:$A,Inputs!C:C,,0) -> 21674 | D51: =_xlfn.XLOOKUP($A51,Inputs!$A:$A,Inputs!D:D,,0) -> 17693 | E51: =_xlfn.XLOOKUP($A51,Inputs!$A:$A,Inputs!E:E,,0) -> 14792 | F51: =_xlfn.XLOOKUP($A51,Inputs!$A:$A,Inputs!F:F,,0) -> 10874 | G51: =_xlfn.XLOOKUP($A51,Inputs!$A:$A,Inputs!G:G,,0) -> 8966 | H51: =_xlfn.XLOOKUP($A51,Inputs!$A:$A,Inputs!H:H,,0) -> 7081 | I51: =_xlfn.XLOOKUP($A51,Inputs!$A:$A,Inputs!I:I,,0) -> 5531 | J51: =_xlfn.XLOOKUP($A51,Inputs!$A:$A,Inputs!J:J,,0) -> 4294 | K51: =_xlfn.XLOOKUP($A51,Inputs!$A:$A,Inputs!K:K,,0) -> 3343 | L51: =_xlfn.XLOOKUP($A51,Inputs!$A:$A,Inputs!L:L,,0) -> 2397 | M51: =_xlfn.XLOOKUP($A51,Inputs!$A:$A,Inputs!M:M,,0) -> 1794
A52: Non-current Liabilities | B52: =_xlfn.XLOOKUP($A52,Inputs!$A:$A,Inputs!B:B,,0) -> 14599 | C52: =_xlfn.XLOOKUP($A52,Inputs!$A:$A,Inputs!C:C,,0) -> 15290 | D52: =_xlfn.XLOOKUP($A52,Inputs!$A:$A,Inputs!D:D,,0) -> 7080 | E52: =_xlfn.XLOOKUP($A52,Inputs!$A:$A,Inputs!E:E,,0) -> 6396 | F52: =_xlfn.XLOOKUP($A52,Inputs!$A:$A,Inputs!F:F,,0) -> 3877 | G52: =_xlfn.XLOOKUP($A52,Inputs!$A:$A,Inputs!G:G,,0) -> 1541 | H52: =_xlfn.XLOOKUP($A52,Inputs!$A:$A,Inputs!H:H,,0) -> 2790 | I52: =_xlfn.XLOOKUP($A52,Inputs!$A:$A,Inputs!I:I,,0) -> 2143 | J52: =_xlfn.XLOOKUP($A52,Inputs!$A:$A,Inputs!J:J,,0) -> 2300 | K52: =_xlfn.XLOOKUP($A52,Inputs!$A:$A,Inputs!K:K,,0) -> 2134 | L52: =_xlfn.XLOOKUP($A52,Inputs!$A:$A,Inputs!L:L,,0) -> 293 | M52: =_xlfn.XLOOKUP($A52,Inputs!$A:$A,Inputs!M:M,,0) -> 254
A53: Long-Term Debt | B53: =_xlfn.XLOOKUP($A53,Inputs!$A:$A,Inputs!B:B,,0) -> 9419 | C53: =_xlfn.XLOOKUP($A53,Inputs!$A:$A,Inputs!C:C,,0) -> 10592 | D53: =_xlfn.XLOOKUP($A53,Inputs!$A:$A,Inputs!D:D,,0) -> 2673 | E53: =_xlfn.XLOOKUP($A53,Inputs!$A:$A,Inputs!E:E,,0) -> 2673 | F53: =_xlfn.XLOOKUP($A53,Inputs!$A:$A,Inputs!F:F,,0) -> 3173 | G53: =_xlfn.XLOOKUP($A53,Inputs!$A:$A,Inputs!G:G,,0) -> 695 | H53: =_xlfn.XLOOKUP($A53,Inputs!$A:$A,Inputs!H:H,,0) -> 2008 | I53: =_xlfn.XLOOKUP($A53,Inputs!$A:$A,Inputs!I:I,,0) -> 1286 | J53: =_xlfn.XLOOKUP($A53,Inputs!$A:$A,Inputs!J:J,,0) -> 1371 | K53: =_xlfn.XLOOKUP($A53,Inputs!$A:$A,Inputs!K:K,,0) -> 1302 | L53: =_xlfn.XLOOKUP($A53,Inputs!$A:$A,Inputs!L:L,,0) -> 0 | M53: =_xlfn.XLOOKUP($A53,Inputs!$A:$A,Inputs!M:M,,0) -> 0
A54: Long-Term Leases | B54: =_xlfn.XLOOKUP($A54,Inputs!$A:$A,Inputs!B:B,,0) -> 534 | C54: =_xlfn.XLOOKUP($A54,Inputs!$A:$A,Inputs!C:C,,0) -> 271 | D54: =_xlfn.XLOOKUP($A54,Inputs!$A:$A,Inputs!D:D,,0) -> 93 | E54: =_xlfn.XLOOKUP($A54,Inputs!$A:$A,Inputs!E:E,,0) -> 332 | F54: =_xlfn.XLOOKUP($A54,Inputs!$A:$A,Inputs!F:F,,0) -> 257 | G54: =_xlfn.XLOOKUP($A54,Inputs!$A:$A,Inputs!G:G,,0) -> 0 | H54: =_xlfn.XLOOKUP($A54,Inputs!$A:$A,Inputs!H:H,,0) -> 682 | I54: =_xlfn.XLOOKUP($A54,Inputs!$A:$A,Inputs!I:I,,0) -> 747 | J54: =_xlfn.XLOOKUP($A54,Inputs!$A:$A,Inputs!J:J,,0) -> 827 | K54: =_xlfn.XLOOKUP($A54,Inputs!$A:$A,Inputs!K:K,,0) -> 634 | L54: =_xlfn.XLOOKUP($A54,Inputs!$A:$A,Inputs!L:L,,0) -> 0 | M54: =_xlfn.XLOOKUP($A54,Inputs!$A:$A,Inputs!M:M,,0) -> 0
A55: Other non-current liabilities | B55: =_xlfn.XLOOKUP($A55,Inputs!$A:$A,Inputs!B:B,,0) -> 4646 | C55: =_xlfn.XLOOKUP($A55,Inputs!$A:$A,Inputs!C:C,,0) -> 4427 | D55: =_xlfn.XLOOKUP($A55,Inputs!$A:$A,Inputs!D:D,,0) -> 4314 | E55: =_xlfn.XLOOKUP($A55,Inputs!$A:$A,Inputs!E:E,,0) -> 3391 | F55: =_xlfn.XLOOKUP($A55,Inputs!$A:$A,Inputs!F:F,,0) -> 447 | G55: =_xlfn.XLOOKUP($A55,Inputs!$A:$A,Inputs!G:G,,0) -> 846 | H55: =_xlfn.XLOOKUP($A55,Inputs!$A:$A,Inputs!H:H,,0) -> 100 | I55: =_xlfn.XLOOKUP($A55,Inputs!$A:$A,Inputs!I:I,,0) -> 110 | J55: =_xlfn.XLOOKUP($A55,Inputs!$A:$A,Inputs!J:J,,0) -> 102 | K55: =_xlfn.XLOOKUP($A55,Inputs!$A:$A,Inputs!K:K,,0) -> 198 | L55: =_xlfn.XLOOKUP($A55,Inputs!$A:$A,Inputs!L:L,,0) -> 293 | M55: =_xlfn.XLOOKUP($A55,Inputs!$A:$A,Inputs!M:M,,0) -> 254
A56: Total Liabilities | B56: =_xlfn.XLOOKUP($A56,Inputs!$A:$A,Inputs!B:B,,0) -> 40490 | C56: =_xlfn.XLOOKUP($A56,Inputs!$A:$A,Inputs!C:C,,0) -> 37078 | D56: =_xlfn.XLOOKUP($A56,Inputs!$A:$A,Inputs!D:D,,0) -> 24808 | E56: =_xlfn.XLOOKUP($A56,Inputs!$A:$A,Inputs!E:E,,0) -> 21241 | F56: =_xlfn.XLOOKUP($A56,Inputs!$A:$A,Inputs!F:F,,0) -> 15132 | G56: =_xlfn.XLOOKUP($A56,Inputs!$A:$A,Inputs!G:G,,0) -> 11608 | H56: =_xlfn.XLOOKUP($A56,Inputs!$A:$A,Inputs!H:H,,0) -> 10085 | I56: =_xlfn.XLOOKUP($A56,Inputs!$A:$A,Inputs!I:I,,0) -> 7760 | J56: =_xlfn.XLOOKUP($A56,Inputs!$A:$A,Inputs!J:J,,0) -> 6690 | K56: =_xlfn.XLOOKUP($A56,Inputs!$A:$A,Inputs!K:K,,0) -> 6114 | L56: =_xlfn.XLOOKUP($A56,Inputs!$A:$A,Inputs!L:L,,0) -> 3211 | M56: =_xlfn.XLOOKUP($A56,Inputs!$A:$A,Inputs!M:M,,0) -> 2577
A58: Total Debt | B58: =B49+B53+B50+B54 -> 11392 | C58: =C49+C53+C50+C54 -> 10977 | D58: =D49+D53+D50+D54 -> 2801 | E58: =E49+E53+E50+E54 -> 3058 | F58: =F49+F53+F50+F54 -> 3646 | G58: =G49+G53+G50+G54 -> 1720 | H58: =H49+H53+H50+H54 -> 2792 | I58: =I49+I53+I50+I54 -> 2048 | ... M58: =M49+M53+M50+M54 -> 496
A59: Debt/Assets | B59: =IFERROR(B58/B44,"-") -> 0.11524649 | C59: =IFERROR(C58/C44,"-") -> 0.11529372 | D59: =IFERROR(D58/D44,"-") -> 0.042246723 | E59: =IFERROR(E58/E44,"-") -> 0.055472917 | F59: =IFERROR(F58/F44,"-") -> 0.11861925 | G59: =IFERROR(G58/G44,"-") -> 0.078238719 | H59: =IFERROR(H58/H44,"-") -> 0.15877168 | I59: =IFERROR(I58/I44,"-") -> 0.16046384 | ... M59: =IFERROR(M58/M44,"-") -> 0.11911623
A60: Net Debt | B60: =B58-B39 -> -1116 | C60: =C58-C39 -> 440 | D60: =D58-D39 -> -9165 | E60: =E58-E39 -> -4889 | F60: =F58-F39 -> -696 | G60: =G58-G39 -> -2801 | H60: =H58-H39 -> 583 | I60: =I58-I39 -> -677 | ... M60: =M58-M39 -> -282
A62: Minority Interest | B62: =_xlfn.XLOOKUP($A62,Inputs!$A:$A,Inputs!B:B,,0) -> 0 | C62: =_xlfn.XLOOKUP($A62,Inputs!$A:$A,Inputs!C:C,,0) -> 0 | D62: =_xlfn.XLOOKUP($A62,Inputs!$A:$A,Inputs!D:D,,0) -> 0 | E62: =_xlfn.XLOOKUP($A62,Inputs!$A:$A,Inputs!E:E,,0) -> 0 | F62: =_xlfn.XLOOKUP($A62,Inputs!$A:$A,Inputs!F:F,,0) -> 0 | G62: =_xlfn.XLOOKUP($A62,Inputs!$A:$A,Inputs!G:G,,0) -> 0 | H62: =_xlfn.XLOOKUP($A62,Inputs!$A:$A,Inputs!H:H,,0) -> 0 | I62: =_xlfn.XLOOKUP($A62,Inputs!$A:$A,Inputs!I:I,,0) -> 0 | J62: =_xlfn.XLOOKUP($A62,Inputs!$A:$A,Inputs!J:J,,0) -> 0 | K62: =_xlfn.XLOOKUP($A62,Inputs!$A:$A,Inputs!K:K,,0) -> 0 | L62: =_xlfn.XLOOKUP($A62,Inputs!$A:$A,Inputs!L:L,,0) -> 0 | M62: =_xlfn.XLOOKUP($A62,Inputs!$A:$A,Inputs!M:M,,0) -> 0
A64: Shareholder's Equity | B64: =_xlfn.XLOOKUP($A64,Inputs!$A:$A,Inputs!B:B,,0) -> 58359 | C64: =_xlfn.XLOOKUP($A64,Inputs!$A:$A,Inputs!C:C,,0) -> 58131 | D64: =_xlfn.XLOOKUP($A64,Inputs!$A:$A,Inputs!D:D,,0) -> 41493 | E64: =_xlfn.XLOOKUP($A64,Inputs!$A:$A,Inputs!E:E,,0) -> 33885 | F64: =_xlfn.XLOOKUP($A64,Inputs!$A:$A,Inputs!F:F,,0) -> 15605 | G64: =_xlfn.XLOOKUP($A64,Inputs!$A:$A,Inputs!G:G,,0) -> 10376 | H64: =_xlfn.XLOOKUP($A64,Inputs!$A:$A,Inputs!H:H,,0) -> 7500 | I64: =_xlfn.XLOOKUP($A64,Inputs!$A:$A,Inputs!I:I,,0) -> 5003 | J64: =_xlfn.XLOOKUP($A64,Inputs!$A:$A,Inputs!J:J,,0) -> 3975 | K64: =_xlfn.XLOOKUP($A64,Inputs!$A:$A,Inputs!K:K,,0) -> 3039 | L64: =_xlfn.XLOOKUP($A64,Inputs!$A:$A,Inputs!L:L,,0) -> 2318 | M64: =_xlfn.XLOOKUP($A64,Inputs!$A:$A,Inputs!M:M,,0) -> 1587
A66: Cash Flow
A67: Operating CF | B67: =_xlfn.XLOOKUP($A67,Inputs!$A:$A,Inputs!B:B,,0) -> 7111 | C67: =_xlfn.XLOOKUP($A67,Inputs!$A:$A,Inputs!C:C,,0) -> 6000 | D67: =_xlfn.XLOOKUP($A67,Inputs!$A:$A,Inputs!D:D,,0) -> 4801 | E67: =_xlfn.XLOOKUP($A67,Inputs!$A:$A,Inputs!E:E,,0) -> 4331 | F67: =_xlfn.XLOOKUP($A67,Inputs!$A:$A,Inputs!F:F,,0) -> 3398 | G67: =_xlfn.XLOOKUP($A67,Inputs!$A:$A,Inputs!G:G,,0) -> 2738 | H67: =_xlfn.XLOOKUP($A67,Inputs!$A:$A,Inputs!H:H,,0) -> 2162 | I67: =_xlfn.XLOOKUP($A67,Inputs!$A:$A,Inputs!I:I,,0) -> 1672.1 | J67: =_xlfn.XLOOKUP($A67,Inputs!$A:$A,Inputs!J:J,,0) -> 1181.4 | K67: =_xlfn.XLOOKUP($A67,Inputs!$A:$A,Inputs!K:K,,0) -> 875.5 | L67: =_xlfn.XLOOKUP($A67,Inputs!$A:$A,Inputs!L:L,,0) -> 736.9 | M67: =_xlfn.XLOOKUP($A67,Inputs!$A:$A,Inputs!M:M,,0) -> 591.5
A68: Investing CF | B68: =_xlfn.XLOOKUP($A68,Inputs!$A:$A,Inputs!B:B,,0) -> -1989 | C68: =_xlfn.XLOOKUP($A68,Inputs!$A:$A,Inputs!C:C,,0) -> -14536 | D68: =_xlfn.XLOOKUP($A68,Inputs!$A:$A,Inputs!D:D,,0) -> -3971 | E68: =_xlfn.XLOOKUP($A68,Inputs!$A:$A,Inputs!E:E,,0) -> -2980 | F68: =_xlfn.XLOOKUP($A68,Inputs!$A:$A,Inputs!F:F,,0) -> -5308 | G68: =_xlfn.XLOOKUP($A68,Inputs!$A:$A,Inputs!G:G,,0) -> -2011 | H68: =_xlfn.XLOOKUP($A68,Inputs!$A:$A,Inputs!H:H,,0) -> -2684 | I68: =_xlfn.XLOOKUP($A68,Inputs!$A:$A,Inputs!I:I,,0) -> -1487.9 | J68: =_xlfn.XLOOKUP($A68,Inputs!$A:$A,Inputs!J:J,,0) -> -698.4 | K68: =_xlfn.XLOOKUP($A68,Inputs!$A:$A,Inputs!K:K,,0) -> -2431.6 | L68: =_xlfn.XLOOKUP($A68,Inputs!$A:$A,Inputs!L:L,,0) -> -938.9 | M68: =_xlfn.XLOOKUP($A68,Inputs!$A:$A,Inputs!M:M,,0) -> -489.7
A69: Net Capex | B69: =_xlfn.XLOOKUP($A69,Inputs!$A:$A,Inputs!B:B,,0) -> -798 | C69: =_xlfn.XLOOKUP($A69,Inputs!$A:$A,Inputs!C:C,,0) -> -717 | D69: =_xlfn.XLOOKUP($A69,Inputs!$A:$A,Inputs!D:D,,0) -> -710 | E69: =_xlfn.XLOOKUP($A69,Inputs!$A:$A,Inputs!E:E,,0) -> -643 | F69: =_xlfn.XLOOKUP($A69,Inputs!$A:$A,Inputs!F:F,,0) -> -595 | G69: =_xlfn.XLOOKUP($A69,Inputs!$A:$A,Inputs!G:G,,0) -> -534 | H69: =_xlfn.XLOOKUP($A69,Inputs!$A:$A,Inputs!H:H,,0) -> -464 | I69: =_xlfn.XLOOKUP($A69,Inputs!$A:$A,Inputs!I:I,,0) -> -709.9 | J69: =_xlfn.XLOOKUP($A69,Inputs!$A:$A,Inputs!J:J,,0) -> -290.5 | K69: =_xlfn.XLOOKUP($A69,Inputs!$A:$A,Inputs!K:K,,0) -> -299.1 | L69: =_xlfn.XLOOKUP($A69,Inputs!$A:$A,Inputs!L:L,,0) -> -175.6 | M69: =_xlfn.XLOOKUP($A69,Inputs!$A:$A,Inputs!M:M,,0) -> -151.6
A70: Investments & Acquisitions | B70: =_xlfn.XLOOKUP($A70,Inputs!$A:$A,Inputs!B:B,,0) -> -439 | C70: =_xlfn.XLOOKUP($A70,Inputs!$A:$A,Inputs!C:C,,0) -> -14876 | D70: =_xlfn.XLOOKUP($A70,Inputs!$A:$A,Inputs!D:D,,0) -> -1281 | E70: =_xlfn.XLOOKUP($A70,Inputs!$A:$A,Inputs!E:E,,0) -> -369 | F70: =_xlfn.XLOOKUP($A70,Inputs!$A:$A,Inputs!F:F,,0) -> -5115 | G70: =_xlfn.XLOOKUP($A70,Inputs!$A:$A,Inputs!G:G,,0) -> -25 | H70: =_xlfn.XLOOKUP($A70,Inputs!$A:$A,Inputs!H:H,,0) -> -3193 | I70: =_xlfn.XLOOKUP($A70,Inputs!$A:$A,Inputs!I:I,,0) -> -58.7 | J70: =_xlfn.XLOOKUP($A70,Inputs!$A:$A,Inputs!J:J,,0) -> 0 | K70: =_xlfn.XLOOKUP($A70,Inputs!$A:$A,Inputs!K:K,,0) -> -2617.3 | L70: =_xlfn.XLOOKUP($A70,Inputs!$A:$A,Inputs!L:L,,0) -> -579.7 | M70: =_xlfn.XLOOKUP($A70,Inputs!$A:$A,Inputs!M:M,,0) -> -422.7
A71: Financing CF | B71: =_xlfn.XLOOKUP($A71,Inputs!$A:$A,Inputs!B:B,,0) -> -3562 | C71: =_xlfn.XLOOKUP($A71,Inputs!$A:$A,Inputs!C:C,,0) -> 7838 | D71: =_xlfn.XLOOKUP($A71,Inputs!$A:$A,Inputs!D:D,,0) -> 1194 | E71: =_xlfn.XLOOKUP($A71,Inputs!$A:$A,Inputs!E:E,,0) -> 164 | F71: =_xlfn.XLOOKUP($A71,Inputs!$A:$A,Inputs!F:F,,0) -> 2010 | G71: =_xlfn.XLOOKUP($A71,Inputs!$A:$A,Inputs!G:G,,0) -> 221 | H71: =_xlfn.XLOOKUP($A71,Inputs!$A:$A,Inputs!H:H,,0) -> 998 | I71: =_xlfn.XLOOKUP($A71,Inputs!$A:$A,Inputs!I:I,,0) -> 73.2 | J71: =_xlfn.XLOOKUP($A71,Inputs!$A:$A,Inputs!J:J,,0) -> -318.2 | K71: =_xlfn.XLOOKUP($A71,Inputs!$A:$A,Inputs!K:K,,0) -> 1598.2 | L71: =_xlfn.XLOOKUP($A71,Inputs!$A:$A,Inputs!L:L,,0) -> 334.5 | M71: =_xlfn.XLOOKUP($A71,Inputs!$A:$A,Inputs!M:M,,0) -> 75.9
A72: Dividends | B72: =_xlfn.XLOOKUP($A72,Inputs!$A:$A,Inputs!B:B,,0) -> 0 | C72: =_xlfn.XLOOKUP($A72,Inputs!$A:$A,Inputs!C:C,,0) -> 0 | D72: =_xlfn.XLOOKUP($A72,Inputs!$A:$A,Inputs!D:D,,0) -> 0 | E72: =_xlfn.XLOOKUP($A72,Inputs!$A:$A,Inputs!E:E,,0) -> 0 | F72: =_xlfn.XLOOKUP($A72,Inputs!$A:$A,Inputs!F:F,,0) -> 0 | G72: =_xlfn.XLOOKUP($A72,Inputs!$A:$A,Inputs!G:G,,0) -> 0 | H72: =_xlfn.XLOOKUP($A72,Inputs!$A:$A,Inputs!H:H,,0) -> 0 | I72: =_xlfn.XLOOKUP($A72,Inputs!$A:$A,Inputs!I:I,,0) -> 0 | J72: =_xlfn.XLOOKUP($A72,Inputs!$A:$A,Inputs!J:J,,0) -> 0 | K72: =_xlfn.XLOOKUP($A72,Inputs!$A:$A,Inputs!K:K,,0) -> 0 | L72: =_xlfn.XLOOKUP($A72,Inputs!$A:$A,Inputs!L:L,,0) -> 0 | M72: =_xlfn.XLOOKUP($A72,Inputs!$A:$A,Inputs!M:M,,0) -> 0
A73: Share buyback | B73: =_xlfn.XLOOKUP($A73,Inputs!$A:$A,Inputs!B:B,,0) -> -4000 | C73: =_xlfn.XLOOKUP($A73,Inputs!$A:$A,Inputs!C:C,,0) -> 0 | D73: =_xlfn.XLOOKUP($A73,Inputs!$A:$A,Inputs!D:D,,0) -> 0 | E73: =_xlfn.XLOOKUP($A73,Inputs!$A:$A,Inputs!E:E,,0) -> 0 | F73: =_xlfn.XLOOKUP($A73,Inputs!$A:$A,Inputs!F:F,,0) -> 0 | G73: =_xlfn.XLOOKUP($A73,Inputs!$A:$A,Inputs!G:G,,0) -> 0 | H73: =_xlfn.XLOOKUP($A73,Inputs!$A:$A,Inputs!H:H,,0) -> 0 | I73: =_xlfn.XLOOKUP($A73,Inputs!$A:$A,Inputs!I:I,,0) -> 0 | J73: =_xlfn.XLOOKUP($A73,Inputs!$A:$A,Inputs!J:J,,0) -> 0 | K73: =_xlfn.XLOOKUP($A73,Inputs!$A:$A,Inputs!K:K,,0) -> 0 | L73: =_xlfn.XLOOKUP($A73,Inputs!$A:$A,Inputs!L:L,,0) -> 0 | M73: =_xlfn.XLOOKUP($A73,Inputs!$A:$A,Inputs!M:M,,0) -> 0
A74: FX | B74: =_xlfn.XLOOKUP($A74,Inputs!$A:$A,Inputs!B:B,,0) -> -8 | C74: =_xlfn.XLOOKUP($A74,Inputs!$A:$A,Inputs!C:C,,0) -> -33 | D74: =_xlfn.XLOOKUP($A74,Inputs!$A:$A,Inputs!D:D,,0) -> 26 | E74: =_xlfn.XLOOKUP($A74,Inputs!$A:$A,Inputs!E:E,,0) -> -39 | F74: =_xlfn.XLOOKUP($A74,Inputs!$A:$A,Inputs!F:F,,0) -> 26 | G74: =_xlfn.XLOOKUP($A74,Inputs!$A:$A,Inputs!G:G,,0) -> -12 | H74: =_xlfn.XLOOKUP($A74,Inputs!$A:$A,Inputs!H:H,,0) -> -27 | I74: =_xlfn.XLOOKUP($A74,Inputs!$A:$A,Inputs!I:I,,0) -> -7.1 | J74: =_xlfn.XLOOKUP($A74,Inputs!$A:$A,Inputs!J:J,,0) -> -38.4 | K74: =_xlfn.XLOOKUP($A74,Inputs!$A:$A,Inputs!K:K,,0) -> -7.8 | L74: =_xlfn.XLOOKUP($A74,Inputs!$A:$A,Inputs!L:L,,0) -> 7.4 | M74: =_xlfn.XLOOKUP($A74,Inputs!$A:$A,Inputs!M:M,,0) -> 5.3
A75: Changes in cash | B75: =_xlfn.XLOOKUP($A75,Inputs!$A:$A,Inputs!B:B,,0) -> 1552 | C75: =_xlfn.XLOOKUP($A75,Inputs!$A:$A,Inputs!C:C,,0) -> -731 | D75: =_xlfn.XLOOKUP($A75,Inputs!$A:$A,Inputs!D:D,,0) -> 2050 | E75: =_xlfn.XLOOKUP($A75,Inputs!$A:$A,Inputs!E:E,,0) -> 1476 | F75: =_xlfn.XLOOKUP($A75,Inputs!$A:$A,Inputs!F:F,,0) -> 126 | G75: =_xlfn.XLOOKUP($A75,Inputs!$A:$A,Inputs!G:G,,0) -> 936 | H75: =_xlfn.XLOOKUP($A75,Inputs!$A:$A,Inputs!H:H,,0) -> 449 | I75: =_xlfn.XLOOKUP($A75,Inputs!$A:$A,Inputs!I:I,,0) -> 250.3 | J75: =_xlfn.XLOOKUP($A75,Inputs!$A:$A,Inputs!J:J,,0) -> 126.4 | K75: =_xlfn.XLOOKUP($A75,Inputs!$A:$A,Inputs!K:K,,0) -> 34.3 | L75: =_xlfn.XLOOKUP($A75,Inputs!$A:$A,Inputs!L:L,,0) -> 139.9 | M75: =_xlfn.XLOOKUP($A75,Inputs!$A:$A,Inputs!M:M,,0) -> 183
A77: Other Data
A78: Number of employees | B78: =_xlfn.XLOOKUP($A78,Inputs!$A:$A,Inputs!B:B,,0) -> #N/A | C78: =_xlfn.XLOOKUP($A78,Inputs!$A:$A,Inputs!C:C,,0) -> #N/A | D78: =_xlfn.XLOOKUP($A78,Inputs!$A:$A,Inputs!D:D,,0) -> #N/A | E78: =_xlfn.XLOOKUP($A78,Inputs!$A:$A,Inputs!E:E,,0) -> #N/A | F78: =_xlfn.XLOOKUP($A78,Inputs!$A:$A,Inputs!F:F,,0) -> #N/A | G78: =_xlfn.XLOOKUP($A78,Inputs!$A:$A,Inputs!G:G,,0) -> #N/A | H78: =_xlfn.XLOOKUP($A78,Inputs!$A:$A,Inputs!H:H,,0) -> #N/A | I78: =_xlfn.XLOOKUP($A78,Inputs!$A:$A,Inputs!I:I,,0) -> #N/A | J78: =_xlfn.XLOOKUP($A78,Inputs!$A:$A,Inputs!J:J,,0) -> #N/A | K78: =_xlfn.XLOOKUP($A78,Inputs!$A:$A,Inputs!K:K,,0) -> #N/A | L78: =_xlfn.XLOOKUP($A78,Inputs!$A:$A,Inputs!L:L,,0) -> #N/A | M78: =_xlfn.XLOOKUP($A78,Inputs!$A:$A,Inputs!M:M,,0) -> #N/A
A79: Shares Outstanding | B79: =_xlfn.XLOOKUP($A79,Inputs!$A:$A,Inputs!B:B,,0) -> #N/A | C79: =_xlfn.XLOOKUP($A79,Inputs!$A:$A,Inputs!C:C,,0) -> #N/A | D79: =_xlfn.XLOOKUP($A79,Inputs!$A:$A,Inputs!D:D,,0) -> #N/A | E79: =_xlfn.XLOOKUP($A79,Inputs!$A:$A,Inputs!E:E,,0) -> #N/A | F79: =_xlfn.XLOOKUP($A79,Inputs!$A:$A,Inputs!F:F,,0) -> #N/A | G79: =_xlfn.XLOOKUP($A79,Inputs!$A:$A,Inputs!G:G,,0) -> #N/A | H79: =_xlfn.XLOOKUP($A79,Inputs!$A:$A,Inputs!H:H,,0) -> #N/A | I79: =_xlfn.XLOOKUP($A79,Inputs!$A:$A,Inputs!I:I,,0) -> #N/A | J79: =_xlfn.XLOOKUP($A79,Inputs!$A:$A,Inputs!J:J,,0) -> #N/A | K79: =_xlfn.XLOOKUP($A79,Inputs!$A:$A,Inputs!K:K,,0) -> #N/A | L79: =_xlfn.XLOOKUP($A79,Inputs!$A:$A,Inputs!L:L,,0) -> #N/A | M79: =_xlfn.XLOOKUP($A79,Inputs!$A:$A,Inputs!M:M,,0) -> #N/A
A80: Float | B80: =_xlfn.XLOOKUP($A80,Inputs!$A:$A,Inputs!B:B,,0) -> Yahoo finance | C80: =_xlfn.XLOOKUP($A80,Inputs!$A:$A,Inputs!C:C,,0) -> Yahoo finance | D80: =_xlfn.XLOOKUP($A80,Inputs!$A:$A,Inputs!D:D,,0) -> 0 | E80: =_xlfn.XLOOKUP($A80,Inputs!$A:$A,Inputs!E:E,,0) -> 0 | F80: =_xlfn.XLOOKUP($A80,Inputs!$A:$A,Inputs!F:F,,0) -> 0 | G80: =_xlfn.XLOOKUP($A80,Inputs!$A:$A,Inputs!G:G,,0) -> 0 | H80: =_xlfn.XLOOKUP($A80,Inputs!$A:$A,Inputs!H:H,,0) -> 0 | I80: =_xlfn.XLOOKUP($A80,Inputs!$A:$A,Inputs!I:I,,0) -> 0 | J80: =_xlfn.XLOOKUP($A80,Inputs!$A:$A,Inputs!J:J,,0) -> 0 | K80: =_xlfn.XLOOKUP($A80,Inputs!$A:$A,Inputs!K:K,,0) -> 0 | L80: =_xlfn.XLOOKUP($A80,Inputs!$A:$A,Inputs!L:L,,0) -> 0 | M80: =_xlfn.XLOOKUP($A80,Inputs!$A:$A,Inputs!M:M,,0) -> 0
A81: Insiders Own | B81: =_xlfn.XLOOKUP($A81,Inputs!$A:$A,Inputs!B:B,,0) -> Yahoo finance | C81: =_xlfn.XLOOKUP($A81,Inputs!$A:$A,Inputs!C:C,,0) -> Yahoo finance | D81: =_xlfn.XLOOKUP($A81,Inputs!$A:$A,Inputs!D:D,,0) -> 0 | E81: =_xlfn.XLOOKUP($A81,Inputs!$A:$A,Inputs!E:E,,0) -> 0 | F81: =_xlfn.XLOOKUP($A81,Inputs!$A:$A,Inputs!F:F,,0) -> 0 | G81: =_xlfn.XLOOKUP($A81,Inputs!$A:$A,Inputs!G:G,,0) -> 0 | H81: =_xlfn.XLOOKUP($A81,Inputs!$A:$A,Inputs!H:H,,0) -> 0 | I81: =_xlfn.XLOOKUP($A81,Inputs!$A:$A,Inputs!I:I,,0) -> 0 | J81: =_xlfn.XLOOKUP($A81,Inputs!$A:$A,Inputs!J:J,,0) -> 0 | K81: =_xlfn.XLOOKUP($A81,Inputs!$A:$A,Inputs!K:K,,0) -> 0 | L81: =_xlfn.XLOOKUP($A81,Inputs!$A:$A,Inputs!L:L,,0) -> 0 | M81: =_xlfn.XLOOKUP($A81,Inputs!$A:$A,Inputs!M:M,,0) -> 0
A82: Fitch/ S&P Rating | B82: =_xlfn.XLOOKUP($A82,Inputs!$A:$A,Inputs!B:B,,0) -> 10-K | C82: =_xlfn.XLOOKUP($A82,Inputs!$A:$A,Inputs!C:C,,0) -> 10-K | D82: =_xlfn.XLOOKUP($A82,Inputs!$A:$A,Inputs!D:D,,0) -> 0 | E82: =_xlfn.XLOOKUP($A82,Inputs!$A:$A,Inputs!E:E,,0) -> 0 | F82: =_xlfn.XLOOKUP($A82,Inputs!$A:$A,Inputs!F:F,,0) -> 0 | G82: =_xlfn.XLOOKUP($A82,Inputs!$A:$A,Inputs!G:G,,0) -> 0 | H82: =_xlfn.XLOOKUP($A82,Inputs!$A:$A,Inputs!H:H,,0) -> 0 | I82: =_xlfn.XLOOKUP($A82,Inputs!$A:$A,Inputs!I:I,,0) -> 0 | J82: =_xlfn.XLOOKUP($A82,Inputs!$A:$A,Inputs!J:J,,0) -> 0 | K82: =_xlfn.XLOOKUP($A82,Inputs!$A:$A,Inputs!K:K,,0) -> 0 | L82: =_xlfn.XLOOKUP($A82,Inputs!$A:$A,Inputs!L:L,,0) -> 0 | M82: =_xlfn.XLOOKUP($A82,Inputs!$A:$A,Inputs!M:M,,0) -> 0
A83: Dividend Yield | B83: =_xlfn.XLOOKUP($A83,Inputs!$A:$A,Inputs!B:B,,0) -> #N/A | C83: =_xlfn.XLOOKUP($A83,Inputs!$A:$A,Inputs!C:C,,0) -> #N/A | D83: =_xlfn.XLOOKUP($A83,Inputs!$A:$A,Inputs!D:D,,0) -> #N/A | E83: =_xlfn.XLOOKUP($A83,Inputs!$A:$A,Inputs!E:E,,0) -> #N/A | F83: =_xlfn.XLOOKUP($A83,Inputs!$A:$A,Inputs!F:F,,0) -> #N/A | G83: =_xlfn.XLOOKUP($A83,Inputs!$A:$A,Inputs!G:G,,0) -> #N/A | H83: =_xlfn.XLOOKUP($A83,Inputs!$A:$A,Inputs!H:H,,0) -> #N/A | I83: =_xlfn.XLOOKUP($A83,Inputs!$A:$A,Inputs!I:I,,0) -> #N/A | J83: =_xlfn.XLOOKUP($A83,Inputs!$A:$A,Inputs!J:J,,0) -> #N/A | K83: =_xlfn.XLOOKUP($A83,Inputs!$A:$A,Inputs!K:K,,0) -> #N/A | L83: =_xlfn.XLOOKUP($A83,Inputs!$A:$A,Inputs!L:L,,0) -> #N/A | M83: =_xlfn.XLOOKUP($A83,Inputs!$A:$A,Inputs!M:M,,0) -> #N/A
A84: Daily Volume in Millions of USD | B84: =_xlfn.XLOOKUP($A84,Inputs!$A:$A,Inputs!B:B,,0) -> Yahoo Finance | C84: =_xlfn.XLOOKUP($A84,Inputs!$A:$A,Inputs!C:C,,0) -> Yahoo Finance | D84: =_xlfn.XLOOKUP($A84,Inputs!$A:$A,Inputs!D:D,,0) -> 0 | E84: =_xlfn.XLOOKUP($A84,Inputs!$A:$A,Inputs!E:E,,0) -> 0 | F84: =_xlfn.XLOOKUP($A84,Inputs!$A:$A,Inputs!F:F,,0) -> 0 | G84: =_xlfn.XLOOKUP($A84,Inputs!$A:$A,Inputs!G:G,,0) -> 0 | H84: =_xlfn.XLOOKUP($A84,Inputs!$A:$A,Inputs!H:H,,0) -> 0 | I84: =_xlfn.XLOOKUP($A84,Inputs!$A:$A,Inputs!I:I,,0) -> 0 | J84: =_xlfn.XLOOKUP($A84,Inputs!$A:$A,Inputs!J:J,,0) -> 0 | K84: =_xlfn.XLOOKUP($A84,Inputs!$A:$A,Inputs!K:K,,0) -> 0 | L84: =_xlfn.XLOOKUP($A84,Inputs!$A:$A,Inputs!L:L,,0) -> 0 | M84: =_xlfn.XLOOKUP($A84,Inputs!$A:$A,Inputs!M:M,,0) -> 0
B86: 2020 | C86: 2021 | D86: 2022
A87: Short % of Float | B87: 0 | C87: 0 | D87: 0
A88: EPS | B88: 0 | C88: 0 | D88: 0
A90: Corporate Bonds 3, 5 Y 10 | B90: Average Price | C90: Moody's | D90: YTM | E90: DIVISA
B91: =VLOOKUP($A91,Inputs!$A$5:$M$98,MATCH(B$4,Inputs!$B$5:$M$5,0)+1,FALSE) -> #N/A | C91: =VLOOKUP($A91,Inputs!$A$5:$M$98,MATCH(C$4,Inputs!$B$5:$M$5,0)+1,FALSE) -> #N/A | D91: =VLOOKUP($A91,Inputs!$A$5:$M$98,MATCH(D$4,Inputs!$B$5:$M$5,0)+1,FALSE) -> #N/A | E91: =VLOOKUP($A91,Inputs!$A$5:$M$98,MATCH(E$4,Inputs!$B$5:$M$5,0)+1,FALSE) -> #N/A

Sheet Sector Impact
E2: Sector | F2: Sub-Industry | H2: Low | K2: Sector | L2: Environment | Q2: Social
E3: Communication Services | F3: Interactive Home Entertainment | H3: Medium | L3: CO2 | M3: Water | N3: Energy | O3: Waste | P3: Degradation | Q3: Turnover | R3: Compensation | S3: Reputation | T3: Discrimination | U3: Security | V3: Damage | W3: Pension | X3: Supply | Y3: Community | Z3: Public | AA3: Litigation
E4: Communication Services | F4: Interactive Media & Services | H4: High | K4: Communication Services | L4: Low | M4: Low | N4: Medium | O4: Low | P4: Low | Q4: Medium | R4: Medium | S4: Low | T4: Low | U4: High | V4: Low | W4: Low | X4: Low | Y4: Low | Z4: Low | AA4: Medium
B5: Environmental | E5: Communication Services | F5: Integrated Telecommunication Services | H5: Very High | K5: Consumer Discretionary | L5: Low | M5: Low | N5: Medium | O5: Medium | P5: Low | Q5: Medium | R5: Medium | S5: Low | T5: Low | U5: Medium | V5: Medium | W5: Medium | X5: High | Y5: Low | Z5: High | AA5: Low
B6: Direct CO2 emissions | E6: Communication Services | F6: Cable & Satellite | K6: Consumer Staples | L6: High | M6: Very High | N6: High | O6: High | P6: High | Q6: Medium | R6: High | S6: High | T6: Low | U6: Medium | V6: Medium | W6: Low | X6: High | Y6: Low | Z6: Very High | AA6: Low
B7: Total Water Use | E7: Communication Services | F7: Broadcasting | K7: Energy | L7: Very High | M7: Very High | N7: Medium | O7: Very High | P7: High | Q7: High | R7: Medium | S7: Medium | T7: Medium | U7: Medium | V7: High | W7: Medium | X7: Medium | Y7: High | Z7: High | AA7: Low
K8: Renewable Energy | L8: Low | M8: Low | N8: Low | O8: Medium | P8: Medium | Q8: Low | R8: Medium | S8: Medium | T8: High | U8: Medium | V8: Low | W8: Low | X8: Medium | Y8: Medium | Z8: High | AA8: Low
B9: Total Energy Consumption | E9: Communication Services | F9: Movies & Entertainment | K9: Financials | L9: Low | M9: Low | N9: Low | O9: Low | P9: Low | Q9: Low | R9: Low | S9: Medium | T9: High | U9: Medium | V9: Low | W9: Low | X9: Low | Y9: Low | Z9: Medium | AA9: Low
K10: Forestry | L10: Low | M10: Medium | N10: Low | O10: Medium | P10: High | Q10: Low | R10: Low | S10: Low | T10: Low | U10: Low | V10: Low | W10: Low | X10: Low | Y10: Medium | Z10: Low | AA10: Low
B11: Waste Management | E11: Communication Services | F11: Advertising | K11: Health Care | L11: Low | M11: Medium | N11: Low | O11: Low | P11: Low | Q11: Low | R11: Low | S11: Medium | T11: Low | U11: High | V11: Low | W11: Low | X11: Low | Y11: Low | Z11: Low | AA11: Low
B12: Land Degradation/Deforestation/Biodiversity loss/Animal sufering/... | E12: Communication Services | F12: Alternative Carriers | K12: Industrials | L12: Very High | M12: Very High | N12: Very High | O12: High | P12: High | Q12: Low | R12: Medium | S12: High | T12: Very High | U12: Medium | V12: Very High | W12: Medium | X12: Very High | Y12: Very High | Z12: Very High | AA12: High
B13: Social | E13: Communication Services | F13: Publishing | K13: Information Technology | L13: Medium | M13: Low | N13: High | O13: Low | P13: Low | Q13: Low | R13: Low | S13: Low | T13: Low | U13: High | V13: Low | W13: Low | X13: Low | Y13: Low | Z13: Medium | AA13: Very High
B14: Employee turnover | E14: Communication Services | F14: Wireless Telecommunication Services | K14: Materials | L14: Very High | M14: Very High | N14: Very High | O14: Very High | P14: High | Q14: High | R14: High | S14: Medium | T14: High | U14: Low | V14: Very High | W14: Medium | X14: Medium | Y14: Very High | Z14: High | AA14: Medium
B15: Salaries and compensation | E15: Consumer Discretionary | F15: Automotive Retail | K15: Real Estate | L15: Low | M15: Low | N15: Medium | O15: Low | P15: Low | Q15: Medium | R15: Low | S15: Low | T15: Low | U15: High | V15: Low | W15: Medium | X15: Low | Y15: Medium | Z15: Low | AA15: Low
B16: Reputational issues | E16: Consumer Discretionary | F16: Internet & Direct Marketing Retail | K16: Utilities | L16: Very High | M16: High | N16: High | O16: Medium | P16: High | Q16: Low | R16: Medium | S16: Medium | T16: Low | U16: Medium | V16: Medium | W16: Medium | X16: Medium | Y16: Low | Z16: Medium | AA16: Low
B17: Discrimination issues | E17: Consumer Discretionary | F17: Auto Parts & Equipment
B18: Job security | E18: Consumer Discretionary | F18: Specialty Stores
B19: Health injuries | E19: Consumer Discretionary | F19: Computer & Electronics Retail | L19: Communication Services | M19: Consumer Discretionary | N19: Consumer Staples | O19: Energy | P19: Financials | Q19: Health Care | R19: Industrials | S19: Information Technology | T19: Materials | U19: Real Estate | V19: Utilities
B20: PXP? | E20: Consumer Discretionary | F20: Hotels, Resorts & Cruise Lines | L20: Interactive Home Entertainment | M20: Automotive Retail | N20: Tobacco | O20: Oil & Gas Exploration & Production | P20: Life & Health Insurance | Q20: Health Care Equipment | R20: Industrial Conglomerates | S20: IT Consulting & Other Services | T20: Industrial Gases | U20: Office REITs | V20: Independent Power Producers & Energy Traders
B21: Supply chain | E21: Consumer Discretionary | F21: Restaurants | L21: Interactive Media & Services | M21: Internet & Direct Marketing Retail | N21: Agricultural Products | O21: Oil & Gas Equipment & Services | P21: Property & Casualty Insurance | Q21: Pharmaceuticals | R21: Airlines | S21: Application Software | T21: Specialty Chemicals | U21: Specialized REITs | V21: Electric Utilities
B22: Community involvement | E22: Consumer Discretionary | F22: Homebuilding | L22: Integrated Telecommunication Services | M22: Auto Parts & Equipment | N22: Distillers & Vintners | O22: Integrated Oil & Gas | P22: Consumer Finance | Q22: Health Care Supplies | R22: Building Products | S22: Semiconductors | T22: Paper Packaging | U22: Residential REITs | V22: Multi-Utilities
B23: Public Sector | E23: Consumer Discretionary | F23: General Merchandise Stores | L23: Cable & Satellite | M23: Specialty Stores | N23: Packaged Foods & Meats | O23: Oil & Gas Refining & Marketing | P23: Asset Management & Custody Banks | Q23: Health Care Distributors | R23: Electrical Components & Equipment | S23: Internet Services & Infrastructure | T23: Metal & Glass Containers | U23: Real Estate Services | V23: Water Utilities
B24: Litigation | E24: Consumer Discretionary | F24: Automobile Manufacturers | L24: Broadcasting | M24: Computer & Electronics Retail | N24: Household Products | O24: Oil & Gas Storage & Transportation | P24: Insurance Brokers | Q24: Biotechnology | R24: Aerospace & Defense | S24: Electronic Components | T24: Fertilizers & Agricultural Chemicals | U24: Industrial REITs | V24: Gas Utilities
E25: Consumer Discretionary | F25: Apparel Retail | L25: Movies & Entertainment | M25: Hotels, Resorts & Cruise Lines | N25: Soft Drinks | P25: Multi-line Insurance | Q25: Managed Health Care | R25: Air Freight & Logistics | S25: Technology Hardware, Storage & Peripherals | T25: Commodity Chemicals | U25: Retail REITs
E26: Consumer Discretionary | F26: Consumer Electronics | L26: Advertising | M26: Restaurants | N26: Hypermarkets & Super Centers | P26: Diversified Banks | Q26: Life Sciences Tools & Services | R26: Construction Machinery & Heavy Trucks | S26: Semiconductor Equipment | T26: Diversified Chemicals | U26: Health Care REITs
E27: Consumer Discretionary | F27: Apparel, Accessories & Luxury Goods | L27: Alternative Carriers | M27: Homebuilding | N27: Personal Products | P27: Multi-Sector Holdings | Q27: Health Care Technology | R27: Diversified Support Services | S27: Communications Equipment | T27: Copper | U27: Hotel & Resort REITs
E28: Consumer Discretionary | F28: Leisure Products | L28: Publishing | M28: General Merchandise Stores | N28: Food Retail | P28: Financial Exchanges & Data | Q28: Health Care Services | R28: Railroads | S28: Data Processing & Outsourced Services | T28: Construction Materials
E29: Consumer Discretionary | F29: Home Improvement Retail | L29: Wireless Telecommunication Services | M29: Automobile Manufacturers | N29: Brewers | P29: Investment Banking & Brokerage | Q29: Health Care Facilities | R29: Industrial Machinery | S29: Technology Distributors | T29: Gold
E30: Consumer Discretionary | F30: Casinos & Gaming | M30: Apparel Retail | N30: Food Distributors | P30: Regional Banks | R30: Agricultural & Farm Machinery | S30: Electronic Equipment & Instruments | T30: Steel
E31: Consumer Discretionary | F31: Home Furnishings | M31: Consumer Electronics | N31: Drug Retail | P31: Reinsurance | R31: Research & Consulting Services | S31: Systems Software
E32: Consumer Discretionary | F32: Distributors | M32: Apparel, Accessories & Luxury Goods | P32: Thrifts & Mortgage Finance | R32: Construction & Engineering | S32: Electronic Manufacturing Services
E33: Consumer Discretionary | F33: Housewares & Specialties | M33: Leisure Products | R33: Trucking
E34: Consumer Discretionary | F34: Household Appliances | M34: Home Improvement Retail | R34: Environmental & Facilities Services
E35: Consumer Staples | F35: Tobacco | M35: Casinos & Gaming | R35: Human Resource & Employment Services
E36: Consumer Staples | F36: Agricultural Products | M36: Home Furnishings | R36: Trading Companies & Distributors
E37: Consumer Staples | F37: Distillers & Vintners | M37: Distributors
E38: Consumer Staples | F38: Packaged Foods & Meats | M38: Housewares & Specialties
E39: Consumer Staples | F39: Household Products | M39: Household Appliances
E40: Consumer Staples | F40: Soft Drinks
E41: Consumer Staples | F41: Hypermarkets & Super Centers
E42: Consumer Staples | F42: Personal Products
E43: Consumer Staples | F43: Food Retail
E44: Consumer Staples | F44: Brewers
E45: Consumer Staples | F45: Food Distributors
E46: Consumer Staples | F46: Drug Retail
E47: Energy | F47: Oil & Gas Exploration & Production
E48: Energy | F48: Oil & Gas Equipment & Services
E49: Energy | F49: Integrated Oil & Gas
E50: Energy | F50: Oil & Gas Refining & Marketing
E51: Energy | F51: Oil & Gas Storage & Transportation
... E128: Utilities | F128: Gas Utilities

Sheet Inputs
G2: Figures in Millions of USD
G3: Company | H3: SALESFORCE, INC. (XNYS:CRM)
D4: Report in millions
A5: RESULTS | B5: 2022 | C5: =B5-1 -> 2021 | D5: =C5-1 -> 2020 | E5: =D5-1 -> 2019 | F5: =E5-1 -> 2018 | G5: =F5-1 -> 2017 | H5: =G5-1 -> 2016 | I5: =H5-1 -> 2015 | J5: =I5-1 -> 2014 | ... M5: =L5-1 -> 2011 | Q5: Hoja | R5: Nombre campo Bloomberg | T5: Cambio de signo | Z5: 2016 | AA5: 2015 | AB5: 2014 | AC5: 2013 | AD5: 2012 | AE5: 2011 | AF5: 2010 | AG5: 2009
A6: Net Sales | B6: 31352 | C6: 26492 | D6: 21252 | E6: 17098 | F6: 13282 | G6: 10540 | H6: 8437 | I6: 6667 | J6: 5374 | K6: 4071 | L6: 3050 | M6: 2267 | N6: Income Statement | O6: Sales | Q6: Ingreso | R6: Ingreso | Z6: 38537 | AA6: 47011 | AB6: 55184 | AC6: 55656 | AD6: 65875 | AE6: 60138 | AF6: 42588 | AG6: 32396
A7: Gross Profit | B7: 22992 | C7: 19466 | D7: 15814 | E7: 12863 | F7: 9831 | G7: 7767 | H7: 6203 | I7: 5013 | J7: 4084 | K7: 3103 | L7: 2367 | M7: 1778 | N7: Income Statement | O7: =+A7 -> Gross Profit | Q7: Ingreso | R7: + Coste de bienes y servicios | Z7: =Z6-28044 -> 10493 | AA7: =AA6-33546 -> 13465 | AB7: =AB6-40718 -> 14466 | AC7: =AC6-40727 -> 14929 | AD7: =+AD6-47055 -> 18820 | AE7: =+AE6-43578 -> 16560 | AF7: =+AF6-30367 -> 12221 | AG7: =+AG6-23886 -> 8510
A8: Operating Income | B8: 1030 | C8: 548 | D8: 455 | E8: 297 | F8: 535 | G8: 454 | H8: 218 | I8: 111 | J8: -146 | K8: -286 | L8: -111 | M8: -35 | N8: Income Statement | O8: Operating Income | Q8: Ingreso | R8: + Ventas, generales y admin | Z8: =Z7-4383 -> 6110 | AA8: =AA7-4951 -> 8514 | AB8: =AB7-6529 -> 7937 | AC8: =AC7-5547 -> 9382 | AD8: =AD7-5919-2466-797-580-485 -> 8573 | AE8: =+AE7-5203-2297-826-1081 -> 7153 | AF8: =+AF7-4248-1905-914-1191 -> 3963 | AG8: =+AG7-3645-1421-1045-1822 -> 577
A9: Other Expenses (Revenues) | B9: 131 | C9: 227 | D9: 664 | E9: 18 | F9: 94 | G9: 53 | H9: -9 | I9: 15.2 | J9: 19.8 | K9: 4.8 | L9: 5.6 | M9: 4.45 | N9: Income Statement | O9: investment income+other income expense+income loss+minority interest+non controlling interest+share onf net profit+gain8losses) on equity investments+share of result from associates nd joint ventures+non operating profit+ | Q9: Ingreso | R9: + Investigación y desarrollo | S9: + Coste de financiación de beneficio | T9: + Otro gasto operativo | U9: - Beneficio (pérdida) de filiales | V9: - Minoritarios | Z9: =1853+596+595+1904+6+8 -> 4962 | AA9: =2119+587+2023+11 -> 4740 | AB9: =2380+624+1619-8+16 -> 4631 | AC9: =2046+727+981+6+14 -> 3774 | AD9: =-14+41 -> 27 | AE9: 53 | AF9: =58+24 -> 82 | AG9: =12-68 -> -56
A10: Net Financial Cost | B10: -131 | C10: -227 | D10: -64 | E10: -18 | F10: -94 | G10: -53 | H10: -88.98 | I10: -72.48 | J10: -73.23 | K10: -77.21 | L10: -30.94 | M10: -17.045 | N10: Income Statement | O10: interest expense+financial income and expenses+other financial expense-income+interest and other net+ | Q10: Ingreso | R10: - Ingreso (pérdida) no operacional | Z10: =505+518 -> 1023 | AA10: =507-161 -> 346 | AB10: =484-322 -> 162 | AC10: =465+35 -> 500 | AD10: =467-130 -> 337 | AE10: =396+32 -> 428 | AF10: =343-130 -> 213 | AG10: =389-381 -> 8
A11: Taxes | B11: 452 | C11: 88 | D11: -1511 | E11: 574 | F11: -170 | G11: -66 | H11: -144 | I11: 112 | J11: 50 | K11: -126 | L11: 143 | M11: -22 | N11: Income Statement | O11: Taxes | Q11: Ingreso | R11: - Gasto de impuesto a la renta (Beneficio) | Z11: 192 | AA11: 916 | AB11: 692 | AC11: 1319 | AD11: =2528 -> 2528 | AE11: =1720 -> 1720 | AF11: =968 -> 968 | AG11: =-270 -> -270
A12: Net Income | B12: 208 | C12: 1444 | D12: 4072 | E12: 1266 | F12: 1110 | G12: 360 | H12: 323 | I12: -47.4 | J12: -262.7 | K12: -232.2 | L12: -270.4 | M12: -11.6 | N12: Income Statement | O12: Net Income | Q12: Flujo de caja | R12: + Ingreso neto | Z12: -67 | AA12: 2512 | AB12: 2452 | AC12: 3789 | AD12: 5681 | AE12: =4928+24 -> 4952 | AF12: 2700 | AG12: 895
B13: =SUM(B8:B11) -> 1482 | C13: =SUM(C8:C11) -> 636 | D13: =SUM(D8:D11) -> -456 | E13: =SUM(E8:E11) -> 871 | F13: =SUM(F8:F11) -> 365 | G13: =SUM(G8:G11) -> 388 | H13: =SUM(H8:H11) -> -23.98 | I13: =SUM(I8:I11) -> 165.72 | ... M13: =SUM(M8:M11) -> -69.595 | Z13: =Z8-Z10-Z9-Z11 -> -67 | AA13: =AA8-AA10-AA9-AA11 -> 2512 | AB13: =AB8-AB10-AB9-AB11 -> 2452 | AC13: =AC8-AC10-AC9-AC11 -> 3789 | AD13: =AD8-AD10-AD9-AD11 -> 5681 | AE13: =AE8-AE10-AE9-AE11 -> 4952 | AF13: =AF8-AF10-AF9-AF11 -> 2700 | AG13: =AG8-AG10-AG9-AG11 -> 895
A14: FINANCIAL POSITION | B14: =B12-B13 -> -1274 | C14: =C12-C13 -> 808 | D14: =D12-D13 -> 4528 | E14: =E12-E13 -> 395 | F14: =F12-F13 -> 745 | G14: =G12-G13 -> -28 | H14: =H12-H13 -> 346.98 | I14: =I12-I13 -> -213.12 | ... M14: =M12-M13 -> 57.995 | Z14: =Z12-Z13 -> 0 | AA14: =AA12-AA13 -> 0 | AB14: =AB12-AB13 -> 0 | AC14: =AC12-AC13 -> 0 | AD14: =AD12-AD13 -> 0 | AE14: =AE12-AE13 -> 0 | AF14: =AF12-AF13 -> 0 | AG14: =AG12-AG13 -> 0
A16: Weighted Average Shares (Basic NI) | B16: 0.21 | C16: 1.51 | D16: 4.48 | E16: 0.15 | F16: 1.48 | G16: 0.5 | H16: 0.26 | I16: -0.07 | J16: -0.42 | K16: -0.39 | L16: -0.48 | M16: -0.02
A17: Weighted Average Shares (Diluted NI) | B17: 0.21 | C17: 1.51 | D17: 4.48 | E17: 0.15 | F17: 1.48 | G17: 0.5 | H17: 0.26 | I17: -0.07 | J17: -0.42 | K17: -0.39 | L17: -0.48 | M17: -0.02
A19: Net gains (losses) from ForEx | B19: -35 | C19: -55 | D19: 40 | E19: -59 | F19: 26 | G19: 77 | H19: -43.07 | I19: -16.66 | J19: -43.27 | K19: -4.9 | L19: 4.7 | M19: 9.5
A20: Total Comprehensive Income | B20: 100 | C20: 1320 | D20: 4123 | E20: 91 | F20: 1071 | G20: 434 | H20: 153.7 | I20: -73.2 | J20: -304.4 | K20: -231.6 | L20: -265.9 | M20: -5.6
A22: Changes Net Working Capital | B22: =B23-C23 -> -2529 | C22: =C23-D23 -> -1670 | D22: =D23-E23 -> -976 | E22: =E23-F23 -> -1915 | F22: =F23-G23 -> 90 | G22: =G23-H23 -> -1497 | H22: =H23-I23 -> -896 | I22: =I23-J23 -> -741 | ... M22: =M23-N23 -> -1429 | N22: cash flows | O22: NWC | Q22: Flujo de caja
A23: Net Working Capital | B23: =B27-B42-B28 -> -12004 | C23: =C27-C42-C28 -> -9475 | D23: =D27-D42-D28 -> -7805 | E23: =E27-E42-E28 -> -6829 | F23: =F27-F42-F28 -> -4914 | G23: =G27-G42-G28 -> -5004 | H23: =H27-H42-H28 -> -3507 | I23: =I27-I42-I28 -> -2611 | ... M23: =M27-M42-M28 -> -1429
A24: 2625 | B24: 2625 | C24: 2625 | D24: 2625 | E24: 2625 | F24: 2625 | G24: 2625 | H24: 2625 | I24: 2625 | J24: 2625 | K24: 2625 | L24: 2625 | M24: 2625 | N24: 2625 | Q24: Flujo de caja | R24: + Dividendos pagados | T24: Cambiar signo | Z24: 1799 | AA24: 1757 | AB24: 1620 | AC24: 1111 | AD24: 1617 | AE24: 1159 | AF24: 1084 | AG24: 1029
A25: BALANCE SHEET | B25: 2625 | C25: 2625 | D25: 2625 | E25: 2625 | F25: 2625 | G25: 2625 | H25: 2625 | I25: 2625 | J25: 2625 | K25: 2625 | L25: 2625 | M25: 2625 | N25: 2625 | Q25: Flujo de caja | R25: + Aumento en capital | S25: + Baja en capital | T25: Cambiar signo y hacer suma | Z25: 23 | AA25: =-33+2025 -> 1992 | AB25: 3817 | AC25: 1776 | AD25: -244 | AE25: -312 | AF25: -449 | AG25: -110
A26: ASSETS | N26: 1922 | O26: 2625
A27: Current | B27: 26395 | C27: 22850 | D27: 21889 | E27: 15963 | F27: 10683 | G27: 9584 | H27: 5997 | I27: 5731 | J27: 3515 | K27: 2680 | L27: 2016 | M27: 1672
A28: Cash & Eq. | B28: 12508 | C28: 10537 | D28: 11966 | E28: 7947 | F28: 4342 | G28: 4521 | H28: 2209 | I28: 2725 | J28: 995 | K28: 839 | L28: 868 | M28: 778 | N28: Balance Sheet | O28: Cash & Eq.
A29: Accounts Receivable | B29: 12531 | C29: 11193 | D29: 8932 | E29: 7100 | F29: 5712 | G29: 4592 | H29: 3197 | I29: 2496 | J29: 1906 | K29: 1361 | L29: 873 | M29: 684 | N29: Balance Sheet | O29: Accounts Receivable
A30: Inventory | B30: 0 | C30: 0 | D30: 0 | E30: 0 | F30: 0 | G30: 0 | H30: 0 | I30: 0 | J30: 0 | K30: 0 | L30: 0 | M30: 0 | N30: Balance Sheet | O30: Inventory | Q30: Balance | R30: + Efectivo, equivalentes y STI | Z30: 7168 | AA30: 6460 | AB30: 7341 | AC30: 6081 | AD30: 5490 | AE30: 3057 | AF30: 3592 | AG30: 4867
A31: Other Current Assets | B31: =B27-SUM(B28:B30) -> 1356 | C31: =C27-SUM(C28:C30) -> 1120 | D31: =D27-SUM(D28:D30) -> 991 | E31: =E27-SUM(E28:E30) -> 916 | F31: =F27-SUM(F28:F30) -> 629 | G31: =G27-SUM(G28:G30) -> 471 | H31: =H27-SUM(H28:H30) -> 591 | I31: =I27-SUM(I28:I30) -> 510 | ... M31: =M27-SUM(M28:M30) -> 210 | N31: Balance Sheet | O31: Inventory | Q31: Balance | R31: + Cuentas y notas por cobrar | S31: + Activos derivados y de cobertura | T31: + Inversiones y cuentas por cobrar a LP | Z31: =5981+8522+1029+13556 -> 29088 | AA31: =6695+8991+1170+13651 -> 30507 | AB31: =7737+9027+1364+14644 -> 32772 | AC31: 33499 | AD31: 33911 | AE31: 31031 | AF31: 28849 | AG31: 27162
A32: Non-current | B32: =B38-B27 -> 72454 | C32: =C38-C27 -> 72359 | D32: =D38-D27 -> 44412 | E32: =E38-E27 -> 39163 | F32: =F38-F27 -> 20054 | G32: =G38-G27 -> 12400 | H32: =H38-H27 -> 11588 | I32: =I38-I27 -> 7032 | ... M32: =M38-M27 -> 2492
A33: Property, Plant and Equipment | B33: 6592 | C33: 5695 | D33: 5663 | E33: 5415 | F33: 2051 | G33: 1947 | H33: 1788 | I33: 1716 | J33: 1126 | K33: 1241 | L33: 605 | M33: 528 | Q33: Balance | R33: + Inventarios | Z33: 8614 | AA33: 9700 | AB33: 12205 | AC33: 12625 | AD33: 15547 | AE33: 14544 | AF33: 9587 | AG33: 6360
A34: Operating leases | B34: 2890 | C34: 2880
A35: Goodwill | B35: 48568 | C35: 47937 | D35: 26318 | E35: 25134 | F35: 12851 | G35: 7314 | H35: 7263 | I35: 3849 | K35: 3500 | L35: 1529
A36: Other Non-Current Assets | B36: =B32-SUM(B33:B35) -> 14404 | C36: =C32-SUM(C33:C35) -> 15847 | D36: =D32-SUM(D33:D35) -> 12431 | E36: =E32-SUM(E33:E35) -> 8614 | F36: =F32-SUM(F33:F35) -> 5152 | G36: =G32-SUM(G33:G35) -> 3139 | H36: =H32-SUM(H33:H35) -> 2537 | I36: =I32-SUM(I33:I35) -> 1467 | ... M36: =M32-SUM(M33:M35) -> 1964 | N36: Balance Sheet | O36: Property, Plant and Equipment
A37: Other Assets | B37: =B31+B36 -> 15760 | C37: =C31+C36 -> 16967 | D37: =D31+D36 -> 13422 | E37: =E31+E36 -> 9530 | F37: =F31+F36 -> 5781 | G37: =G31+G36 -> 3610 | H37: =H31+H36 -> 3128 | I37: =I31+I36 -> 1977 | ... M37: =M31+M36 -> 2174 | N37: Balance Sheet
A38: Total Assets | B38: 98849 | C38: 95209 | D38: 66301 | E38: 55126 | F38: 30737 | G38: 21984 | H38: 17585 | I38: 12763 | J38: 10665 | K38: 9153 | L38: 5529 | M38: 4164 | N38: Balance Sheet | O38: Total Assets | Q38: Balance | R38: + Propiedad, planta y equipo; neto | Z38: 15322 | AA38: 16090 | AB38: =16577 -> 16577 | AC38: 17075 | AD38: 16461 | AE38: 14395 | AF38: 12539 | AG38: 12386
N39: Balance Sheet | Z39: =Z40-SUM(Z30:Z38) -> 14512 | AA39: =AA40-SUM(AA30:AA38) -> 15585 | AB39: =AB40-SUM(AB30:AB38) -> 15786 | AC39: =AC40-SUM(AC30:AC38) -> 15616 | AD39: =AD40-SUM(AD30:AD38) -> 17947 | AE39: =AE40-SUM(AE30:AE38) -> 18419 | AF39: =AF40-SUM(AF30:AF38) -> 9453 | AG39: =AG40-SUM(AG30:AG38) -> 9263
N40: Balance Sheet | Q40: Balance | R40: Activos totales | Z40: 74704 | AA40: 78342 | AB40: 84681 | AC40: 84896 | AD40: 89356 | AE40: 81446 | AF40: 64020 | AG40: 60038
A41: LIABILITIES | N41: Balance Sheet
A42: Current Liabilities | B42: 25891 | C42: 21788 | D42: 17728 | E42: 14845 | F42: 11255 | G42: 10067 | H42: 7295 | I42: 5617 | J42: 4390 | K42: 3980 | L42: 2918 | M42: 2323 | N42: Balance Sheet | O42: Current Liabilities
A43: Payables | B43: 0 | C43: 0 | D43: 0 | E43: 0 | F43: 165 | G43: 76 | H43: 112 | I43: 71 | J43: 96 | K43: 65 | L43: 0 | M43: 33
A44: Short-Term Debt | B44: 0 | C44: 0 | D44: 0 | E44: 0 | F44: 0 | G44: 0 | H44: 0 | I44: 0 | J44: 0 | K44: 0 | L44: 0 | M44: 0 | N44: Balance Sheet | O44: Short term Debt | Q44: Balance | R44: Pasivos totales corrientes | Z44: 26132 | AA44: 26242 | AB44: 27877 | AC44: 27297 | AD44: 29415 | AE44: =93+3895+8161+3386+2410+2691+298+1967+558+5102 -> 28561 | AF44: =204+3852+5856+2880+1670+1831+281+1521+495+3430 -> 22020 | AG44: =433+3650+2993+3351+797+1217+262+888+302+5399 -> 19292
A45: Short-Term Leases | B45: 1439 | C45: 114 | D45: 35 | E45: 53 | F45: 216 | G45: 1025 | H45: 102 | I45: 15 | J45: 0 | K45: 572 | L45: 521 | M45: 496
A46: Other current liabilities | B46: =B42-SUM(B43:B45) -> 24452 | C46: =C42-SUM(C43:C45) -> 21674 | D46: =D42-SUM(D43:D45) -> 17693 | E46: =E42-SUM(E43:E45) -> 14792 | F46: =F42-SUM(F43:F45) -> 10874 | G46: =G42-SUM(G43:G45) -> 8966 | H46: =H42-SUM(H43:H45) -> 7081 | I46: =I42-SUM(I43:I45) -> 5531 | ... M46: =M42-SUM(M43:M45) -> 1794 | N46: Balance Sheet | R46: + Préstamos CP | Z46: 7303 | AA46: 6967 | AB46: 4708 | AC46: 3679 | AD46: 5287 | AE46: 5660 | AF46: 3925 | AG46: 5701
A47: Non-current Liabilities | B47: =B51-B42 -> 14599 | C47: =C51-C42 -> 15290 | D47: =D51-D42 -> 7080 | E47: =E51-E42 -> 6396 | F47: =F51-F42 -> 3877 | G47: =G51-G42 -> 1541 | H47: =H51-H42 -> 2790 | I47: =I51-I42 -> 2143 | ... M47: =M51-M42 -> 254 | N47: Balance Sheet | O47: Total non current liabilities
A48: Long-Term Debt | B48: 9419 | C48: 10592 | D48: 2673 | E48: 2673 | F48: 3173 | G48: 695 | H48: 2008 | I48: 1286 | J48: 1371 | K48: 1302 | L48: 0 | M48: 0 | N48: Balance Sheet | O48: Long term debt | Z48: =Z44-Z46 -> 18829 | AA48: =AA44-AA46 -> 19275 | AB48: =AB44-AB46 -> 23169 | AC48: =AC44-AC46 -> 23618 | AD48: =AD44-AD46 -> 24128 | AE48: =AE44-AE46 -> 22901 | AF48: =AF44-AF46 -> 18095 | AG48: =AG44-AG46 -> 13591
A49: Long-Term Leases | B49: 534 | C49: 271 | D49: 93 | E49: 332 | F49: 257 | G49: 0 | H49: 682 | I49: 747 | J49: 827 | K49: 634 | L49: 0 | M49: 0 | Q49: Balance | R49: Pasivos totales no corrientes | Z49: =61491-Z44 -> 35359 | AA49: =63457-AA44 -> 37215 | AB49: =67855-AB44 -> 39978 | AC49: 36721 | AD49: 41973 | AE49: =8415+16529+10956+3583 -> 39483 | AF49: =4505+15932+7584+2654 -> 30675 | AG49: =5652+16195+7420+2179 -> 31446
A50: Other non-current liabilities | B50: =B47-SUM(B48:B49) -> 4646 | C50: =C47-SUM(C48:C49) -> 4427 | D50: =D47-SUM(D48:D49) -> 4314 | E50: =E47-SUM(E48:E49) -> 3391 | F50: =F47-SUM(F48:F49) -> 447 | G50: =G47-SUM(G48:G49) -> 846 | H50: =H47-SUM(H48:H49) -> 100 | I50: =I47-SUM(I48:I49) -> 110 | ... M50: =M47-SUM(M48:M49) -> 254 | N50: Balance Sheet | O50: Other non current Liabilities | R50: + Préstamos a largo plazo | Z50: 22818 | AA50: 25169 | AB50: 27784 | AC50: 26719 | AD50: 27752 | AE50: 24944 | AF50: 20437 | AG50: 21847
A51: Total Liabilities | B51: 40490 | C51: 37078 | D51: 24808 | E51: 21241 | F51: 15132 | G51: 11608 | H51: 10085 | I51: 7760 | J51: 6690 | K51: 6114 | L51: 3211 | M51: 2577 | N51: Balance Sheet | O51: Total Liabilities
N52: Balance Sheet | Z52: =Z49-Z50 -> 12541 | AA52: =AA49-AA50 -> 12046 | AB52: =AB49-AB50 -> 12194 | AC52: =AC49-AC50 -> 10002 | AD52: =AD49-AD50 -> 14221 | AE52: =AE49-AE50 -> 14539 | AF52: =AF49-AF50 -> 10238 | AG52: =AG49-AG50 -> 9599
N53: Balance Sheet | Z53: =+Z49+Z44 -> 61491 | AA53: =+AA49+AA44 -> 63457 | AB53: =+AB49+AB44 -> 67855 | AC53: =AC44+AC49 -> 64018 | AD53: =AD49+AD44 -> 71388 | AE53: =AE49+AE44 -> 68044 | AF53: =AF49+AF44 -> 52695 | AG53: =AG49+AG44 -> 50738
A54: Minority Interest | B54: 0 | C54: 0 | D54: 0 | E54: 0 | F54: 0 | G54: 0 | H54: 0 | I54: 0 | J54: 0 | K54: 0 | L54: 0 | M54: 0 | N54: Balance Sheet | O54: Minority Interest
N55: Balance Sheet
A56: Shareholder's Equity | B56: =B38-B51-B54 -> 58359 | C56: =C38-C51-C54 -> 58131 | D56: =D38-D51-D54 -> 41493 | E56: =E38-E51-E54 -> 33885 | F56: =F38-F51-F54 -> 15605 | G56: =G38-G51-G54 -> 10376 | H56: =H38-H51-H54 -> 7500 | I56: =I38-I51-I54 -> 5003 | ... M56: =M38-M51-M54 -> 1587 | N56: Balance Sheet | Q56: Balance | R56: + Participación minoritaria/no dominante
A58: CASH FLOW
A59: Operating CF | B59: 7111 | C59: 6000 | D59: 4801 | E59: 4331 | F59: 3398 | G59: 2738 | H59: 2162 | I59: 1672.1 | J59: 1181.4 | K59: 875.5 | L59: 736.9 | M59: 591.5
A60: Net Income | B60: =B12 -> 208 | C60: =C12 -> 1444 | D60: =D12 -> 4072 | E60: =E12 -> 1266 | F60: =F12 -> 1110 | G60: =G12 -> 360 | H60: =H12 -> 323 | I60: =I12 -> -47.4 | ... M60: =M12 -> -11.6
A61: Depreciation & Amortization | B61: 3786 | C61: 3298 | D61: 2846 | E61: 2135 | F61: 962 | G61: 753 | H61: 632 | I61: 525.8 | J61: 448.3 | K61: 369.4 | L61: 216.8 | M61: 157.3
A62: Changes in assets and liabilities | B62: -2069 | C62: -1658 | D62: -1192 | E62: -330 | F62: -172 | G62: 24 | H62: -83 | I62: 312 | J62: 139.1 | K62: -1.3 | L62: 247.2 | M62: 105
A63: Other Adjustments | B63: =B59-B60-B61-B62 -> 5186 | C63: =C59-C60-C61-C62 -> 2916 | D63: =D59-D60-D61-D62 -> -925 | E63: =E59-E60-E61-E62 -> 1260 | F63: =F59-F60-F61-F62 -> 1498 | G63: =G59-G60-G61-G62 -> 1601 | H63: =H59-H60-H61-H62 -> 1290 | I63: =I59-I60-I61-I62 -> 881.7 | ... M63: =M59-M60-M61-M62 -> 340.8
A64: Investing CF | B64: -1989 | C64: -14536 | D64: -3971 | E64: -2980 | F64: -5308 | G64: -2011 | H64: -2684 | I64: -1487.9 | J64: -698.4 | K64: -2431.6 | L64: -938.9 | M64: -489.7
A65: Net Capex | B65: -798 | C65: -717 | D65: -710 | E65: -643 | F65: -595 | G65: -534 | H65: -464 | I65: -709.9 | J65: -290.5 | K65: -299.1 | L65: -175.6 | M65: -151.6
A66: Investments & Acquisitions | B66: -439 | C66: -14876 | D66: -1281 | E66: -369 | F66: -5115 | G66: -25 | H66: -3193 | I66: -58.7 | J66: 0 | K66: -2617.3 | L66: -579.7 | M66: -422.7
A67: Other Inflows (Outflows) | B67: =B64-B65-B66 -> -752 | C67: =C64-C65-C66 -> 1057 | D67: =D64-D65-D66 -> -1980 | E67: =E64-E65-E66 -> -1968 | F67: =F64-F65-F66 -> 402 | G67: =G64-G65-G66 -> -1452 | H67: =H64-H65-H66 -> 973 | I67: =I64-I65-I66 -> -719.3 | ... M67: =M64-M65-M66 -> 84.6
A68: Financing CF | B68: -3562 | C68: 7838 | D68: 1194 | E68: 164 | F68: 2010 | G68: 221 | H68: 998 | I68: 73.2 | J68: -318.2 | K68: 1598.2 | L68: 334.5 | M68: 75.9
A69: Debt Borrowing | B69: 0 | C69: 6549 | D69: 0 | E69: 0 | F69: 1306 | G69: 0 | H69: 597 | I69: 0 | J69: 297.3 | K69: 1132.2 | L69: 0 | M69: 0
A70: Debt Repayment | B70: -423 | C70: -1357 | D70: -107 | E70: -676 | F70: -1660 | G70: -429 | H70: -648 | I70: -382.3 | J70: -924.5 | K70: -62.1 | L70: -31.8 | M70: -30.5
A71: Lease Increases
A72: Lease Payments
A73: Dividends | B73: 0 | C73: 0 | D73: 0 | E73: 0 | F73: 0 | G73: 0 | H73: 0 | I73: 0 | J73: 0 | K73: 0 | L73: 0 | M73: 0 | N73: cash flows FINANCING | O73: Dividends paid
A74: Share buyback | B74: -4000 | C74: 0 | D74: 0 | E74: 0 | F74: 0 | G74: 0 | H74: 0 | I74: 0 | J74: 0 | K74: 0 | L74: 0 | M74: 0 | N74: cash flows FINANCING | O74: =+A74 -> Share buyback
A75: Other Inflows (Outflows) | B75: =B68-B69-B70-B71-B72-B73-B74 -> 861 | C75: =C68-C69-C70-C71-C72-C73-C74 -> 2646 | D75: =D68-D69-D70-D71-D72-D73-D74 -> 1301 | E75: =E68-E69-E70-E71-E72-E73-E74 -> 840 | F75: =F68-F69-F70-F71-F72-F73-F74 -> 2364 | G75: =G68-G69-G70-G71-G72-G73-G74 -> 650 | H75: =H68-H69-H70-H71-H72-H73-H74 -> 1049 | I75: =I68-I69-I70-I71-I72-I73-I74 -> 455.5 | ... M75: =M68-M69-M70-M71-M72-M73-M74 -> 106.4
A76: FX | B76: -8 | C76: -33 | D76: 26 | E76: -39 | F76: 26 | G76: -12 | H76: -27 | I76: -7.1 | J76: -38.4 | K76: -7.8 | L76: 7.4 | M76: 5.3
A77: Changes in cash | B77: =B59+B64+B68+B76 -> 1552 | C77: =C59+C64+C68+C76 -> -731 | D77: =D59+D64+D68+D76 -> 2050 | E77: =E59+E64+E68+E76 -> 1476 | F77: =F59+F64+F68+F76 -> 126 | G77: =G59+G64+G68+G76 -> 936 | H77: =H59+H64+H68+H76 -> 449 | I77: =I59+I64+I68+I76 -> 250.3 | ... M77: =M59+M64+M68+M76 -> 183
O78: (Vitalis will later fill this info)
A79: Other Data | E79: Corporate Bonds 3, 5 Y 10 | H79: Average Price | J79: Moody's | K79: YTM | L79: DIVISA
A80: Number of employees | B80: 10-K | C80: 10-K | N80: bloomberg
A81: Shares Outstanding (Thousands) | B81: Yahoo finance | C81: Yahoo finance | N81: bloomberg
A82: Float | B82: Yahoo finance | C82: Yahoo finance | N82: bloomberg
A83: Insiders Own | B83: Yahoo finance | C83: Yahoo finance | N83: bloomberg
A84: Fitch/ S&P Rating | B84: 10-K | C84: 10-K | N84: bloomberg
A85: Dividend Yield(Yahoo Finance) | B85: Yahoo finance | C85: Yahoo finance | N85: bloomberg
A86: Daily Volume in Millions of USD | B86: Yahoo Finance | C86: Yahoo Finance | N86: bloomberg
B87: =A87+1 -> 1 | C87: =B87+1 -> 2 | D87: =C87+1 -> 3
A88: Short % of Float | E88: Yahoo Finance
A89: EPS | E89: Yahoo Finance

Sheet Industry Averages
A1: Date updated: | B1: 44931 | H1: YouTube Video explaining estimation choices and processes
A2: Created by: | B2: Aswath Damodaran, adamodar@stern.nyu.edu
A3: What is this data? | B3: Dividends and FCFE (in millions) and ratios | F3: US companies
A4: Home Page: | B4: http://www.damodaran.com
A5: Data website: | B5: https://pages.stern.nyu.edu/~adamodar/New_Home_Page/data.html
A6: Companies in each industry: | B6: https://pages.stern.nyu.edu/~adamodar/pc/datasets/indname.xls
A7: Variable definitions: | B7: https://pages.stern.nyu.edu/~adamodar/New_Home_Page/datafile/variable.htm
A8: Industry name | B8: Number of firms | C8: Dividends | D8: Net Income | E8: Payout | F8: Dividends + Buybacks | G8: Cash Return as % of Net Income | H8: Dividends + Buybacks - Stock Issuances | I8: FCFE (before debt cash flows) | J8: FCFE (after debt cash flows) | K8: Net Cash Returned/FCFE (pre-debt) | L8: Net Cash Returned/FCFE (post-debt) | M8: Net Cash Returned/ Net Income | N8: Cash/ Firm Value
A9: Advertising | B9: 58 | C9: 1053.13 | D9: 1557.116 | E9: 0.67633368 | F9: 2363.398 | G9: 1.5178047 | H9: 2099.321 | I9: 701.916 | J9: 1441.348 | K9: 2.9908436 | L9: 1.4564984 | M9: 1.3482111 | N9: 0.093488854
A10: Aerospace/Defense | B10: 77 | C10: 10261.134 | D10: 14514.276 | E10: 0.70696837 | F10: 27906.123 | G10: 1.9226672 | H10: 26339.716 | I10: 11777.548 | J10: 7574.299 | K10: 2.2364346 | L10: 3.477512 | M10: 1.8147454 | N10: 0.037667224
A11: Air Transport | B11: 21 | C11: 0 | D11: -3270.31 | E11: 0 | F11: 402.293 | G11: NA | H11: -143.959 | I11: -7598.895 | J11: -21052.222 | K11: NA | L11: NA | M11: 0.044019986 | N11: 0.14899071
A12: Apparel | B12: 39 | C12: 1985.68 | D12: 3655.799 | E12: 0.54315896 | F12: 8007.97 | G12: 2.1904842 | H12: 7841.459 | I12: -2499.161 | J12: -1233.149 | K12: NA | L12: NA | M12: 2.1449371 | N12: 0.060170318
A13: Auto & Truck | B13: 31 | C13: 2124.5 | D13: 20137.8 | E13: 0.10549812 | F13: 4627.046 | G13: 0.22976919 | H13: -7894.966 | I13: 2434.309 | J13: -3779.693 | K13: -3.2432062 | L13: NA | M13: -0.3920471 | N13: 0.086707774
A14: Auto Parts | B14: 37 | C14: 694.398 | D14: 1869.701 | E14: 0.37139521 | F14: 1616.736 | G14: 0.86470297 | H14: 1567.872 | I14: -1796.699 | J14: -246.252 | K14: NA | L14: NA | M14: 0.83856831 | N14: 0.071275727
A15: Bank (Money Center) | B15: 7 | C15: 29107.116 | D15: 102625.92 | E15: 0.28362344 | F15: 40359 | G15: 0.39326322 | H15: 40338 | I15: 141352.92 | J15: 280520.92 | K15: 0.28537083 | L15: 0.14379676 | M15: 0.3930586 | N15: 0.44301926
A16: Banks (Regional) | B16: 557 | C16: 19659.992 | D16: 67543.37 | E16: 0.29107213 | F16: 36122.306 | G16: 0.53480165 | H16: 32945.143 | I16: 58434.708 | J16: 192772.18 | K16: 0.56379409 | L16: 0.17090196 | M16: 0.4877628 | N16: 0.176564
A17: Beverage (Alcoholic) | B17: 23 | C17: 1270.6 | D17: 1608.29 | E17: 0.79003165 | F17: 2848.614 | G17: 1.7712067 | H17: 2592.307 | I17: -195.705 | J17: -105.866 | K17: NA | L17: NA | M17: 1.6118405 | N17: 0.018550559
A18: Beverage (Soft) | B18: 31 | C18: 12915.352 | D18: 22852.321 | E18: 0.56516588 | F18: 16206.483 | G18: 0.70918324 | H18: 15024.785 | I18: 21780.18 | J18: 25887.173 | K18: 0.6898375 | L18: 0.58039497 | M18: 0.65747304 | N18: 0.026552309
A19: Broadcasting | B19: 26 | C19: 1266.31 | D19: 8817.25 | E19: 0.14361734 | F19: 3476.686 | G19: 0.39430503 | H19: 3464.83 | I19: -5822.602 | J19: -7578.381 | K19: NA | L19: NA | M19: 0.39296039 | N19: 0.10393631
A20: Brokerage & Investment Banking | B20: 30 | C20: 11022.991 | D20: 38423.511 | E20: 0.28688141 | F20: 24277.15 | G20: 0.6318306 | H20: 23872.69 | I20: 100348.33 | J20: 171525.17 | K20: 0.23789823 | L20: 0.13917893 | M20: 0.62130423 | N20: 0.30759698
A21: Building Materials | B21: 45 | C21: 1861.535 | D21: 14370.389 | E21: 0.12953964 | F21: 11996.663 | G21: 0.83481825 | H21: 11720.668 | I21: 9419.219 | J21: 13041.201 | K21: 1.2443354 | L21: 0.89874146 | M21: 0.81561244 | N21: 0.044413029
A22: Business & Consumer Services | B22: 164 | C22: 3112.873 | D22: 11028.556 | E22: 0.28225572 | F22: 12512.88 | G22: 1.1345892 | H22: 8943.991 | I22: 11231.014 | J22: 16410.594 | K22: 0.7963654 | L22: 0.54501324 | M22: 0.81098477 | N22: 0.048045201
A23: Cable TV | B23: 10 | C23: 5128.4 | D23: 17653.3 | E23: 0.29050659 | F23: 36881.3 | G23: 2.0892015 | H23: 36833 | I23: 18830.08 | J23: 28294.38 | K23: 1.9560724 | L23: 1.301778 | M23: 2.0864654 | N23: 0.014652309
A24: Chemical (Basic) | B24: 38 | C24: 4333.8 | D24: 15819.51 | E24: 0.27395286 | F24: 9664.394 | G24: 0.61091614 | H24: 9181.996 | I24: 9847.045 | J24: 6877.907 | K24: 0.93246207 | L24: 1.3349986 | M24: 0.58042228 | N24: 0.0453822
A25: Chemical (Diversified) | B25: 4 | C25: 330 | D25: 2259.24 | E25: 0.14606682 | F25: 1751.1 | G25: 0.77508366 | H25: 1683.1 | I25: 1824.072 | J25: 1901.908 | K25: 0.92271577 | L25: 0.88495343 | M25: 0.74498504 | N25: 0.098248914
A26: Chemical (Specialty) | B26: 76 | C26: 7557.406 | D26: 18677.567 | E26: 0.40462476 | F26: 20111.847 | G26: 1.0767916 | H26: 19090.45 | I26: 5618.056 | J26: 25052.168 | K26: 3.3980526 | L26: 0.76202786 | M26: 1.0221058 | N26: 0.049966819
A27: Coal & Related Energy | B27: 19 | C27: 513.955 | D27: 2515.23 | E27: 0.20433718 | F27: 573.171 | G27: 0.22788015 | H27: -345.25 | I27: 2307.193 | J27: 1255.099 | K27: -0.14964071 | L27: -0.2750779 | M27: -0.13726379 | N27: 0.12601748
A28: Computer Services | B28: 80 | C28: 7172.661 | D28: 7664.509 | E28: 0.93582785 | F28: 13409.187 | G28: 1.7495168 | H28: 12895.074 | I28: 7927.028 | J28: 13115.963 | K28: 1.6267224 | L28: 0.98315877 | M28: 1.6824397 | N28: 0.052114354
A29: Computers/Peripherals | B29: 42 | C29: 18124.95 | D29: 106948.54 | E29: 0.16947357 | F29: 124125.58 | G29: 1.1606103 | H29: 123564.5 | I29: 107732.42 | J29: 105646.15 | K29: 1.1469574 | L29: 1.1696072 | M29: 1.1553641 | N29: 0.017944828
A30: Construction Supplies | B30: 49 | C30: 4538.96 | D30: 14115.59 | E30: 0.32155652 | F30: 12688.435 | G30: 0.89889512 | H30: 12082.063 | I30: 4323.043 | J30: 10297.306 | K30: 2.7948052 | L30: 1.1733227 | M30: 0.85593751 | N30: 0.041538929
A31: Diversified | B31: 23 | C31: 6865.354 | D31: 4556.31 | E31: 1.5067794 | F31: 25049.29 | G31: 5.4977142 | H31: 23473.133 | I31: -8333.016 | J31: -28355.904 | K31: NA | L31: NA | M31: 5.1517858 | N31: 0.046739476
A32: Drugs (Biotechnology) | B32: 598 | C32: 17685 | D32: 1336.616 | E32: 0.00056919255 | F32: 37299.359 | G32: 27.905815 | H32: 13735.232 | I32: 6456.489 | J32: 513.267 | K32: 2.1273531 | L32: 26.760403 | M32: 10.276124 | N32: 0.071437251
A33: Drugs (Pharmaceutical) | B33: 281 | C33: 37183.45 | D33: 72397.57 | E33: 0.5136008 | F33: 57540.93 | G33: 0.7947909 | H33: 50169.941 | I33: 75076.595 | J33: 72293.14 | K33: 0.66825009 | L33: 0.69397928 | M33: 0.69297824 | N33: 0.025649637
A34: Education | B34: 33 | C34: 90 | D34: 516.077 | E34: 0.17439258 | F34: 2641.935 | G34: 5.1192651 | H34: 2104.625 | I34: 407.232 | J34: -685.191 | K34: 5.1681228 | L34: NA | M34: 4.0781221 | N34: 0.099048606
A35: Electrical Equipment | B35: 110 | C35: 2409.19 | D35: 6991.173 | E35: 0.34460455 | F35: 6707.234 | G35: 0.95938607 | H35: 3687.428 | I35: -116.231 | J35: 10494.278 | K35: NA | L35: 0.3513751 | M35: 0.52744053 | N35: 0.050721749
A36: Electronics (Consumer & Office) | B36: 16 | C36: 0 | D36: 39.389 | E36: 0 | F36: 298.971 | G36: 7.5902155 | H36: 230.063 | I36: -353.914 | J36: -344.213 | K36: NA | L36: NA | M36: 5.8407931 | N36: 0.15076517
A37: Electronics (General) | B37: 138 | C37: 916.428 | D37: 8638.312 | E37: 0.10608878 | F37: 7675.772 | G37: 0.88857314 | H37: 4921.244 | I37: 486.367 | J37: 7877.656 | K37: 10.118376 | L37: 0.62470918 | M37: 0.56969973 | N37: 0.056857388
A38: Engineering/Construction | B38: 43 | C38: 432.1 | D38: 2558.963 | E38: 0.16885746 | F38: 2907.779 | G38: 1.1363115 | H38: 2727.694 | I38: -1888.01 | J38: 3697.797 | K38: NA | L38: 0.7376538 | M38: 1.0659373 | N38: 0.049237984
A39: Entertainment | B39: 110 | C39: 959.84 | D39: 1903.669 | E39: 0.5042053 | F39: 3381.172 | G39: 1.7761344 | H39: 2560.072 | I39: 5417.979 | J39: -1283.676 | K39: 0.4725142 | L39: NA | M39: 1.3448094 | N39: 0.069023483
A40: Environmental & Waste Services | B40: 62 | C40: 2146.7 | D40: 4640.605 | E40: 0.46259055 | F40: 4481.516 | G40: 0.96571805 | H40: 3975.312 | I40: 3314.611 | J40: 8304.54 | K40: 1.1993299 | L40: 0.47869141 | M40: 0.85663658 | N40: 0.0081137078
A41: Farming/Agriculture | B41: 39 | C41: 3015.71 | D41: 14341.239 | E41: 0.21028239 | F41: 8457.15 | G41: 0.58970846 | H41: 8068.017 | I41: -4214.132 | J41: 4957.792 | K41: NA | L41: 1.6273408 | M41: 0.56257461 | N41: 0.023316489
A42: Financial Svcs. (Non-bank & Insurance) | B42: 223 | C42: 13017.3 | D42: 95373.686 | E42: 0.13648733 | F42: 62501.149 | G42: 0.65532907 | H42: 60726.687 | I42: 86528.703 | J42: -162222.92 | K42: 0.70180975 | L42: NA | M42: 0.63672371 | N42: 0.022363595
A43: Food Processing | B43: 92 | C43: 10574.62 | D43: 19663.081 | E43: 0.53779059 | F43: 17404.52 | G43: 0.88513697 | H43: 15571.876 | I43: 11098.263 | J43: 9624.509 | K43: 1.4030913 | L43: 1.6179398 | M43: 0.79193469 | N43: 0.018736494
A44: Food Wholesalers | B44: 14 | C44: 1021.6 | D44: 2343.414 | E44: 0.43594516 | F44: 1909.99 | G44: 0.81504591 | H44: 1699.521 | I44: -1201.281 | J44: -540.283 | K44: NA | L44: NA | M44: 0.72523293 | N44: 0.012964299
A45: Furn/Home Furnishings | B45: 32 | C45: 796.425 | D45: 1170.874 | E45: 0.68019702 | F45: 4007.07 | G45: 3.4222897 | H45: 3857.907 | I45: -1718.251 | J45: 507.546 | K45: NA | L45: 7.6010982 | M45: 3.2948951 | N45: 0.059473626
A46: Green & Renewable Energy | B46: 19 | C46: 657.022 | D46: 1155.759 | E46: 0.56847665 | F46: 208.391 | G46: 0.18030662 | H46: 196.865 | I46: -392.33 | J46: 2042.746 | K46: NA | L46: 0.096372726 | M46: 0.17033395 | N46: 0.043792475
A47: Healthcare Products | B47: 254 | C47: 6570.31 | D47: 14242.595 | E47: 0.46131411 | F47: 18381.618 | G47: 1.2906088 | H47: 14559.379 | I47: 8342.258 | J47: 21726.146 | K47: 1.7452564 | L47: 0.67013169 | M47: 1.022242 | N47: 0.031994528
A48: Healthcare Support Services | B48: 131 | C48: 13557.735 | D48: 41031.689 | E48: 0.33042108 | F48: 49102.03 | G48: 1.1966856 | H48: 44679.361 | I48: 39997.549 | J48: 35170.62 | K48: 1.1170525 | L48: 1.2703603 | M48: 1.0888989 | N48: 0.080849129
A49: Heathcare Information and Technology | B49: 138 | C49: 1581.92 | D49: -529.779 | E49: 0.00043282833 | F49: 10197.432 | G49: NA | H49: 8491.103 | I49: -3101.059 | J49: 4235.215 | K49: NA | L49: 2.0048812 | M49: -16.027632 | N49: 0.029861395
A50: Homebuilding | B50: 32 | C50: 1361.39 | D50: 24986.04 | E50: 0.054486025 | F50: 8113.83 | G50: 0.32473453 | H50: 7894.753 | I50: 9262.75 | J50: 10501.207 | K50: 0.852312 | L50: 0.75179482 | M50: 0.31596656 | N50: 0.093127544
A51: Hospitals/Healthcare Facilities | B51: 34 | C51: 949 | D51: 6999.96 | E51: 0.1355722 | F51: 9977.214 | G51: 1.4253244 | H51: 9476.787 | I51: 2703.885 | J51: 9327.108 | K51: 3.504878 | L51: 1.0160477 | M51: 1.3538345 | N51: 0.018538213
A52: Hotel/Gaming | B52: 69 | C52: 793.833 | D52: 1606.126 | E52: 0.49425325 | F52: 17201.467 | G52: 10.709911 | H52: 15579.423 | I52: 4108.838 | J52: 1538.004 | K52: 3.7916859 | L52: 10.129638 | M52: 9.7000005 | N52: 0.082200351
A53: Household Products | B53: 127 | C53: 14431.342 | D53: 22657.092 | E53: 0.63694591 | F53: 22391.329 | G53: 0.98827021 | H53: 19606.336 | I53: 17895.418 | J53: 24106.838 | K53: 1.0956065 | L53: 0.81331015 | M53: 0.86535095 | N53: 0.022054658
A54: Information Services | B54: 73 | C54: 10475.088 | D54: 37313.93 | E54: 0.28072862 | F54: 48778.196 | G54: 1.3072382 | H54: 46377.008 | I54: 41679.417 | J54: 56500.603 | K54: 1.1127077 | L54: 0.82082324 | M54: 1.2428873 | N54: 0.040524176
A55: Insurance (General) | B55: 21 | C55: 3403.408 | D55: 20197.72 | E55: 0.16850456 | F55: 13786.246 | G55: 0.68256447 | H55: 13417.337 | I55: 11622.087 | J55: 16243.714 | K55: 1.1544688 | L55: 0.8260018 | M55: 0.66429958 | N55: 0.026949929
A56: Insurance (Life) | B56: 27 | C56: 5853.451 | D56: 15306.226 | E56: 0.38242288 | F56: 19119.079 | G56: 1.2491047 | H56: 18439.954 | I56: 15021.271 | J56: 10250.871 | K56: 1.2275895 | L56: 1.798867 | M56: 1.2047355 | N56: 0.1687384
A57: Insurance (Prop/Cas.) | B57: 51 | C57: 7922.51 | D57: 10805.474 | E57: 0.73319412 | F57: 16682.03 | G57: 1.5438499 | H57: 16179.26 | I57: 7392.628 | J57: 8226.391 | K57: 2.1885668 | L57: 1.9667507 | M57: 1.4973207 | N57: 0.051581418
A58: Investments & Asset Management | B58: 600 | C58: 15100.191 | D58: 35375.45 | E58: 0.42685509 | F58: 31935.358 | G58: 0.90275482 | H58: -17337.913 | I58: 32624.117 | J58: 62520.16 | K58: -0.53144467 | L58: -0.27731716 | M58: -0.49011145 | N58: 0.09936122
A59: Machinery | B59: 116 | C59: 5613.083 | D59: 15291.498 | E59: 0.36707215 | F59: 15025.432 | G59: 0.9826004 | H59: 13889.148 | I59: 8070.199 | J59: 26845.629 | K59: 1.7210416 | L59: 0.51737093 | M59: 0.90829218 | N59: 0.031620152
A60: Metals & Mining | B60: 68 | C60: 4009.4 | D60: 6414.921 | E60: 0.62501159 | F60: 6803.609 | G60: 1.0605912 | H60: 6402.722 | I60: 3994.434 | J60: 5889.084 | K60: 1.602911 | L60: 1.0872187 | M60: 0.99809834 | N60: 0.08907141
A61: Office Equipment & Services | B61: 16 | C61: 392.5 | D61: 473.13 | E61: 0.82958172 | F61: 613.323 | G61: 1.2963097 | H61: 576.864 | I61: -167.909 | J61: 929.147 | K61: NA | L61: 0.62085332 | M61: 1.2192505 | N61: 0.071772033
A62: Oil/Gas (Integrated) | B62: 4 | C62: 26119.36 | D62: 99099.3 | E62: 0.26356755 | F62: 40681.1 | G62: 0.41050845 | H62: 40345.1 | I62: 111781.8 | J62: 75992.9 | K62: 0.36092727 | L62: 0.53090618 | M62: 0.40711791 | N62: 0.049056001
A63: Oil/Gas (Production and Exploration) | B63: 174 | C63: 20127.072 | D63: 86953.773 | E63: 0.23146864 | F63: 43823.143 | G63: 0.50398208 | H63: 41719.954 | I63: 59398.571 | J63: 46696.461 | K63: 0.70237303 | L63: 0.8934286 | M63: 0.47979464 | N63: 0.038114747
A64: Oil/Gas Distribution | B64: 23 | C64: 8450.9 | D64: 2683.1 | E64: 3.1496776 | F64: 10131.725 | G64: 3.7761265 | H64: 9512.825 | I64: -192.456 | J64: 1748.884 | K64: NA | L64: 5.4393688 | M64: 3.5454605 | N64: 0.016703539
A65: Oilfield Svcs/Equip. | B65: 101 | C65: 7323.106 | D65: 41659.69 | E65: 0.17578398 | F65: 26426.484 | G65: 0.63434183 | H65: 25266.853 | I65: 34325.066 | J65: 24456.819 | K65: 0.73610501 | L65: 1.033121 | M65: 0.60650603 | N65: 0.069065997
A66: Packaging & Container | B66: 25 | C66: 2718.41 | D66: 9491.266 | E66: 0.28641174 | F66: 9036.095 | G66: 0.95204317 | H66: 8916.465 | I66: 2669.647 | J66: 2600.741 | K66: 3.3399416 | L66: 3.4284325 | M66: 0.93943895 | N66: 0.030228142
A67: Paper/Forest Products | B67: 7 | C67: 99 | D67: 1255.7 | E67: 0.078840487 | F67: 1317.7 | G67: 1.0493749 | H67: 1313.61 | I67: 921.506 | J67: 905.059 | K67: 1.4255035 | L67: 1.4514081 | M67: 1.0461177 | N67: 0.075671085
A68: Power | B68: 48 | C68: 21251.454 | D68: 35093.37 | E68: 0.60556892 | F68: 24354.3 | G68: 0.69398579 | H68: 13635.404 | I68: -35714.937 | J68: 17634.524 | K68: NA | L68: 0.77322212 | M68: 0.38854644 | N68: 0.0102966
A69: Precious Metals | B69: 74 | C69: 1943.3513 | D69: 1211.842 | E69: 1.6036342 | F69: 2335.465 | G69: 1.9272026 | H69: 1658.205 | I69: 243.928 | J69: 1104.428 | K69: 6.7979281 | L69: 1.5014152 | M69: 1.3683343 | N69: 0.074262155
A70: Publishing & Newspapers | B70: 20 | C70: 407.9 | D70: 778.84 | E70: 0.52372759 | F70: 1027.414 | G70: 1.3191593 | H70: 989.166 | I70: 715.576 | J70: 1365.97 | K70: 1.3823353 | L70: 0.72414914 | M70: 1.2700503 | N70: 0.073486465
A71: R.E.I.T. | B71: 223 | C71: 51601.829 | D71: 47868.789 | E71: 1.0779848 | F71: 45691.621 | G71: 0.95451801 | H71: 1818.518 | I71: 88400.759 | J71: 150282.44 | K71: 0.020571294 | L71: 0.012100669 | M71: 0.037989639 | N71: 0.018257813
A72: Real Estate (Development) | B72: 18 | C72: 0 | D72: 538.857 | E72: 0 | F72: 510.262 | G72: 0.94693397 | H72: 469.866 | I72: 787.35 | J72: 879.396 | K72: 0.59676891 | L72: 0.53430536 | M72: 0.87196789 | N72: 0.069451077
A73: Real Estate (General/Diversified) | B73: 12 | C73: 48.1 | D73: 144.88 | E73: 0.3319989 | F73: 89.505 | G73: 0.61778713 | H73: 89.505 | I73: 60.369 | J73: 160.86 | K73: 1.4826318 | L73: 0.55641552 | M73: 0.61778713 | N73: 0.085365154
A74: Real Estate (Operations & Services) | B74: 60 | C74: 229.563 | D74: -830.152 | E74: 0.0033508867 | F74: 4736.773 | G74: NA | H74: 4494.012 | I74: 2587.49 | J74: 2975.1 | K74: 1.7368229 | L74: 1.5105415 | M74: -5.4134809 | N74: 0.081379435
A75: Recreation | B75: 57 | C75: 1069.821 | D75: 784.683 | E75: 1.3633799 | F75: 4051.509 | G75: 5.163243 | H75: 1160.863 | I75: -4087.926 | J75: -1988.654 | K75: NA | L75: NA | M75: 1.4794038 | N75: 0.051786361
A76: Reinsurance | B76: 1 | C76: 201 | D76: 575 | E76: 0.34956522 | F76: 306 | G76: 0.53217391 | H76: 306 | I76: 533.3 | J76: 1264.3 | K76: 0.57378586 | L76: 0.24203116 | M76: 0.53217391 | N76: 0.25486978
A77: Restaurant/Dining | B77: 70 | C77: 8430.284 | D77: 13628.138 | E77: 0.61859397 | F77: 22197.825 | G77: 1.628823 | H77: 20501.448 | I77: 10248.102 | J77: 15970.865 | K77: 2.0005117 | L77: 1.283678 | M77: 1.504347 | N77: 0.017235636
A78: Retail (Automotive) | B78: 30 | C78: 738.77 | D78: 11025.241 | E78: 0.067007152 | F78: 14746.48 | G78: 1.33752 | H78: 12507.544 | I78: 7563.784 | J78: 22789.964 | K78: 1.6536094 | L78: 0.54881807 | M78: 1.1344463 | N78: 0.018942366
A79: Retail (Building Supply) | B79: 15 | C79: 10186.125 | D79: 24750.589 | E79: 0.41155081 | F79: 37946.655 | G79: 1.5331617 | H79: 37174.05 | I79: 12747.225 | J79: 25674.247 | K79: 2.9162465 | L79: 1.447912 | M79: 1.5019461 | N79: 0.014968543
A80: Retail (Distributors) | B80: 69 | C80: 3130.065 | D80: 14460.392 | E80: 0.21645782 | F80: 8303.693 | G80: 0.57423706 | H80: 8006.132 | I80: -3931.773 | J80: 3217.194 | K80: NA | L80: 2.488545 | M80: 0.5536594 | N80: 0.022524355
A81: Retail (General) | B81: 15 | C81: 10568.625 | D81: 26032.6 | E81: 0.40597654 | F81: 33519.867 | G81: 1.2876112 | H81: 33456.719 | I81: -5214.18 | J81: 12954.654 | K81: NA | L81: 2.5826023 | M81: 1.2851855 | N81: 0.028245545
A82: Retail (Grocery and Food) | B82: 13 | C82: 1013.253 | D82: 5113.51 | E82: 0.19815215 | F82: 2880.466 | G82: 0.56330505 | H82: 2585.476 | I82: 2892.689 | J82: 1299.136 | K82: 0.89379674 | L82: 1.9901504 | M82: 0.50561669 | N82: 0.05543602
A83: Retail (Online) | B83: 63 | C83: 513.4 | D83: 3688.548 | E83: 0.13918756 | F83: 13914.338 | G83: 3.7723077 | H83: 12759.242 | I83: -51160.771 | J83: -39972.874 | K83: NA | L83: NA | M83: 3.4591503 | N83: 0.04117521
A84: Retail (Special Lines) | B84: 78 | C84: 5685.908 | D84: 17547.905 | E84: 0.32402204 | F84: 22632.617 | G84: 1.2897618 | H84: 22107.182 | I84: 3438.487 | J84: 8185.596 | K84: 6.4293342 | L84: 2.7007419 | M84: 1.2598189 | N84: 0.040041705
A85: Rubber& Tires | B85: 3 | C85: 0 | D85: 864.122 | E85: 0 | F85: 0 | G85: 0 | H85: -1.46 | I85: -352.392 | J85: 295.701 | K85: NA | L85: -0.0049374199 | M85: -0.0016895762 | N85: 0.099691022
A86: Semiconductor | B86: 68 | C86: 23911.23 | D86: 72801.989 | E86: 0.32844199 | F86: 67067.744 | G86: 0.92123505 | H86: 62269.758 | I86: 36738.156 | J86: 41487.001 | K86: 1.6949614 | L86: 1.5009462 | M86: 0.85533045 | N86: 0.033748762
A87: Semiconductor Equip | B87: 30 | C87: 2591.8 | D87: 18191.87 | E87: 0.14247024 | F87: 17103.58 | G87: 0.94017712 | H87: 16041.224 | I87: 8840.685 | J87: 20856.582 | K87: 1.8144775 | L87: 0.76912046 | M87: 0.88177983 | N87: 0.044292966
A88: Shipbuilding & Marine | B88: 8 | C88: 256.3 | D88: 2071.7 | E88: 0.12371482 | F88: 685.128 | G88: 0.33070811 | H88: 629.338 | I88: 2064.449 | J88: 1634.493 | K88: 0.30484551 | L88: 0.3850356 | M88: 0.30377854 | N88: 0.06439213
A89: Shoe | B89: 13 | C89: 2072.046 | D89: 7698.7 | E89: 0.26914232 | F89: 1351.302 | G89: 0.1755234 | H89: 1090.409 | I89: 6060.83 | J89: 8598.469 | K89: 0.17991084 | L89: 0.12681432 | M89: 0.14163547 | N89: 0.034958749
A90: Software (Entertainment) | B90: 91 | C90: 60.03 | D90: 91628.189 | E90: 0.00065514773 | F90: 106194.39 | G90: 1.1589707 | H90: 103663.72 | I90: 56468.041 | J90: 67774.871 | K90: 1.8357946 | L90: 1.5295304 | M90: 1.1313519 | N90: 0.030718171
A91: Software (Internet) | B91: 33 | C91: 0.336 | D91: -5178.9 | E91: 0 | F91: 4187.838 | G91: NA | H91: 3398.96 | I91: -7707.22 | J91: -6077.91 | K91: NA | L91: NA | M91: -0.65630925 | N91: 0.032900021
A92: Software (System & Application) | B92: 390 | C92: 24238.726 | D92: 71266.943 | E92: 0.34011177 | F92: 81788.362 | G92: 1.1476339 | H92: 64479.064 | I92: 48833.833 | J92: 71160.036 | K92: 1.3203769 | L92: 0.90611343 | M92: 0.90475417 | N92: 0.028066077
A93: Steel | B93: 28 | C93: 1342.77 | D93: 25593.54 | E93: 0.052465192 | F93: 9648.989 | G93: 0.37700877 | H93: 9591.238 | I93: 18329.897 | J93: 16980.166 | K93: 0.52325651 | L93: 0.56484948 | M93: 0.3747523 | N93: 0.088354279
A94: Telecom (Wireless) | B94: 16 | C94: 145.71 | D94: 2321.21 | E94: 0.062773295 | F94: 1034.737 | G94: 0.44577483 | H94: 1011.064 | I94: -3333.422 | J94: -1972.899 | K94: NA | L94: NA | M94: 0.43557627 | N94: 0.026437165
A95: Telecom. Equipment | B95: 79 | C95: 7183.578 | D95: 14067.434 | E95: 0.51065304 | F95: 20791.182 | G95: 1.4779655 | H95: 19482.921 | I95: 9251.846 | J95: 11450.132 | K95: 2.1058415 | L95: 1.7015455 | M95: 1.3849662 | N95: 0.037911017
A96: Telecom. Services | B96: 49 | C96: 21546.925 | D96: 41509.338 | E96: 0.51908621 | F96: 13411.382 | G96: 0.32309313 | H96: 13044.091 | I96: 38803.376 | J96: -4787.07 | K96: 0.33615866 | L96: NA | M96: 0.31424474 | N96: 0.011252986
A97: Tobacco | B97: 15 | C97: 14569.3 | D97: 13594.152 | E97: 1.0717329 | F97: 17679.4 | G97: 1.3005151 | H97: 17637.726 | I97: 12523.433 | J97: 11467.924 | K97: 1.4083779 | L97: 1.5380051 | M97: 1.2974495 | N97: 0.028404797
A98: Transportation | B98: 18 | C98: 6209.1 | D98: 18562.94 | E98: 0.33448904 | F98: 14374.3 | G98: 0.77435471 | H98: 13749.071 | I98: 10682.412 | J98: 10330.74 | K98: 1.2870755 | L98: 1.3308893 | M98: 0.74067314 | N98: 0.062843539
A99: Transportation (Railroads) | B99: 4 | C99: 5115.982 | D99: 14258.8 | E99: 0.35879471 | F99: 19554 | G99: 1.3713636 | H99: 19545 | I99: 11470.98 | J99: 18925.38 | K99: 1.7038649 | L99: 1.0327402 | M99: 1.3707325 | N99: 0.014686917
A100: Trucking | B100: 35 | C100: 729.192 | D100: 2048.537 | E100: 0.35595745 | F100: 9496.512 | G100: 4.6357532 | H100: 9226.793 | I100: -11721.857 | J100: -3931.092 | K100: NA | L100: NA | M100: 4.504089 | N100: 0.057218078
...

Sheet Growth Industry Averages
A1: Date updated: | B1: 44931
A2: Created by: | B2: Aswath Damodaran, adamodar@stern.nyu.edu
A3: What is this data? | B3: Historical (compounded annual) growth rate in net income and revenues - last 5 years | F3: US companies
A4: Home Page: | B4: http://www.damodaran.com
A5: Data website: | B5: https://pages.stern.nyu.edu/~adamodar/New_Home_Page/data.html
A6: Companies in each industry: | B6: https://pages.stern.nyu.edu/~adamodar/pc/datasets/indname.xls
A7: Variable definitions: | B7: https://pages.stern.nyu.edu/~adamodar/New_Home_Page/datafile/variable.htm
A8: Industry Name | B8: Number of Firms | C8: CAGR in Net Income- Last 5 years | D8: CAGR in Revenues- Last 5 years | E8: Expected Growth in Revenues - Next 2 years | F8: Expected Growth in EPS - Next 5 years
A9: Advertising | B9: 58 | C9: 0.233825 | D9: 0.18166952 | E9: 0.20375154 | F9: 0.0079555556
A10: Aerospace/Defense | B10: 77 | C10: 0.050448148 | D10: 0.039922558 | E10: 0.38921953 | F10: 0.081387391
A11: Air Transport | B11: 21 | C11: -0.237 | D11: 0.0224125 | E11: 0.31874667 | F11: 0.22525
A12: Apparel | B12: 39 | C12: 0.11 | D12: 0.058356957 | E12: 0.039632609 | F12: 0.056378571
A13: Auto & Truck | B13: 31 | C13: 0.20132 | D13: 0.280595 | E13: 13.283983 | F13: 0.1737
A14: Auto Parts | B14: 37 | C14: 0.083675 | D14: 0.070743333 | E14: 0.1539125 | F14: 0.22152143
A15: Bank (Money Center) | B15: 7 | C15: 0.01288 | D15: 0.0194 | E15: 0.0656 | F15: 0.019862
A16: Banks (Regional) | B16: 557 | C16: 0.18140366 | D16: 0.11019711 | E16: 0.1359809 | F16: 0.11154444
A17: Beverage (Alcoholic) | B17: 23 | C17: -0.12308 | D17: 0.1254375 | E17: 0.16617778 | F17: 0.46596667
A18: Beverage (Soft) | B18: 31 | C18: 0.1739 | D18: 0.15048545 | E18: 0.17535455 | F18: 0.12113333
A19: Broadcasting | B19: 26 | C19: 0.21364545 | D19: 0.19544111 | E19: 0.02599 | F19: 0.2535
A20: Brokerage & Investment Banking | B20: 30 | C20: 0.276 | D20: 0.1422875 | E20: -0.026243684 | F20: 0.19226
... A26: Chemical (Specialty) | B26: 76 | C26: 0.21611667 | D26: 0.094822449 | E26: 0.12618049 | F26: 0.14015833
A27: Coal & Related Energy | B27: 19 | C27: 0.088033333 | D27: -0.037149 | E27: 6.040926 | F27: #DIV/0!
A28: Computer Services | B28: 80 | C28: 0.16804545 | D28: 0.10479308 | E28: 0.096096552 | F28: 0.13076522
A29: Computers/Peripherals | B29: 42 | C29: 0.10070909 | D29: 0.16357148 | E29: 0.14794417 | F29: 0.12861364
A30: Construction Supplies | B30: 49 | C30: 0.090165217 | D30: 0.050167813 | E30: 0.74913824 | F30: 0.1786
A31: Diversified | B31: 23 | C31: 0.02365 | D31: 0.07692 | E31: 0.039342857 | F31: 0.14035
A32: Drugs (Biotechnology) | B32: 598 | C32: 0.071716667 | D32: 0.27230354 | E32: 0.69618469 | F32: -0.048395652
A33: Drugs (Pharmaceutical) | B33: 281 | C33: 0.30738824 | D33: 0.42345634 | E33: 0.62612549 | F33: 0.10348591
A34: Education | B34: 33 | C34: 0.16761667 | D34: 0.041291875 | E34: 0.10228389 | F34: 0.17142857
A35: Electrical Equipment | B35: 110 | C35: 0.14371889 | D35: 0.138975 | E35: 0.60529481 | F35: 0.1596619
A36: Electronics (Consumer & Office) | B36: 16 | C36: -0.368 | D36: -0.00473 | E36: 0.016857143 | F36: 0.13996667
A37: Electronics (General) | B37: 138 | C37: 0.14106976 | D37: 0.10634929 | E37: 0.29346015 | F37: 0.15550938
A38: Engineering/Construction | B38: 43 | C38: 0.1727625 | D38: 0.12138345 | E38: 0.17060938 | F38: 0.17328
A39: Entertainment | B39: 110 | C39: 0.090211111 | D39: 0.28593125 | E39: 0.21343135 | F39: 0.16553067
... A71: R.E.I.T. | B71: 223 | C71: 0.11296356 | D71: 0.095720324 | E71: 0.12692232 | F71: 0.11285918
A72: Real Estate (Development) | B72: 18 | C72: 0.3935 | D72: 0.10161667 | E72: 0.95046667 | F72: #DIV/0!
A73: Real Estate (General/Diversified) | B73: 12 | C73: 0.10715 | D73: 0.08742 | E73: 0.009 | F73: #DIV/0!
A74: Real Estate (Operations & Services) | B74: 60 | C74: 0.04279 | D74: 0.16003759 | E74: 0.051038889 | F74: 0.078333333
A75: Recreation | B75: 57 | C75: 0.10984118 | D75: 0.077886923 | E75: 0.070694688 | F75: 0.13516364
A76: Reinsurance | B76: 1 | C76: -0.0628 | D76: 0.0563 | E76: 0.0172 | F76: #DIV/0!
A77: Restaurant/Dining | B77: 70 | C77: 0.070419259 | D77: 0.062767619 | E77: 0.15182821 | F77: 0.111536
A78: Retail (Automotive) | B78: 30 | C78: 0.25143333 | D78: 0.17119444 | E78: 0.15070304 | F78: 0.14008933
A79: Retail (Building Supply) | B79: 15 | C79: 0.28625 | D79: 0.13023333 | E79: 0.015692857 | F79: 0.094652
A80: Retail (Distributors) | B80: 69 | C80: 0.30973793 | D80: 0.073269286 | E80: 0.101415 | F80: 0.16125
