Workbook
Name Sectors: 'Sector Impact'!$K$4:$K$16

Sheet OP
B2: 45141 | C2: Team 5 | D2: 45169 | E2: =Inputs!H3 -> #VALUE! | L2: NYSE | M2: SIC:
D3: COMPANY DESCRIPTION | H3: CEO & BOARD OF DIRECTORS
D4: {=_FV(Inputs!H3,"Description")} -> Costco Wholesale Corporation operates membership warehouses and e-commerce websites. The Company operates 861 warehouses, including 591 in the United States and Puerto Rico, 107 in Canada, 40 in Mexico, 33 in Japan, 29 in the United Kingdom, 18 in Korea, 15 in Australia, 14 in Taiwan, five in China, four in Spain, two in France, and one each in Iceland, New Zealand and Sweden. It also operates e-commerce sites in the United States, Canada, the United Kingdom, Mexico, Korea, Taiwan, Japan and Australia. It provides a wide selection of merchandise, convenience of specialty departments and exclusive member services. It operates through three segments: United States Operations, Canadian Operations, and Other International Operations. The Company offers merchandise categories (foods and sundries, non-foods, and fresh foods), warehouse ancillary (gasoline, pharmacy, optical, food court, hearing aids and tire installation) and other businesses (e-commerce, business centers, travel and other). | H4: Name | I4: Gender | J4: Age | K4: Tenure | L4: Executive? | M4: Other roles
H5: W. Craig Jelinek | I5: Male | J5: 70 | K5: 11.6 | L5: Yes | M5: CEO & Director
H6: Ron Vachris | I6: Male | J6: 58 | K6: 1.5 | L6: Yes | M6: President
H7: Richard Galanti | I7: Male | J7: 67 | K7: 28.6 | L7: Yes | M7: Executive VP
H8: Jeffrey Raikes | I8: Male | J8: 65 | K8: 14.7 | L8: No | M8: Independent Director
H9: Kenneth Denman | I9: Male | J9: 64 | K9: 6.4 | L9: No | M9: Independent Vice Chairman of the Board
H10: Susan Decker | I10: Female | J10: 60 | K10: 18.8 | L10: No | M10: Independent Director
H11: Mary Wilderotter | I11: Female | J11: 68 | K11: 7.8 | L11: No | M11: Independent Director
H12: Charles Munger | I12: Male | J12: 99 | K12: 26.6 | L12: No | M12: Independent Director
H13: John Stanton | I13: Male | J13: 68 | K13: 7.8 | L13: No | M13: Independent Director
H14: Hamilton James | I14: Male | J14: 72 | K14: 35 | L14: No | M14: Independent Chairman of the Board
H15: Sarah Margaret Jewell | I15: Female | J15: 67 | K15: 3.6 | L15: No | M15: Independent Director
B17: USD MILLIONS
B18: COMPANY OVERVIEW
B19: Stock | D19: Liquidity and Solvency | F19: Segments | I19: Profitability (2022) | L19: Multiples
B20: Last Price | C20: {=_FV(E2,"Price")} -> 842.9 | D20: Total Assets | E20: =_xlfn.XLOOKUP(D20,'Fin. Data'!A:A,'Fin. Data'!B:B,,0) -> 64166 | F20: Regions | H20: % Sales | I20: Reporting Year | J20: 2022 | L20: Float | M20: =441.99/443.15 -> 0.99738238
B21: Outstanding Shares | C21: {=_FV(E2,"Shares outstanding",TRUE)} -> 443335000 | D21: Total Liabilities | E21: =_xlfn.XLOOKUP(D21,'Fin. Data'!A:A,'Fin. Data'!B:B,,0) -> 43519 | F21: =Segments!C5 -> United States and Canada | H21: =Segments!B5 -> 0.86788072 | I21: End of Year | J21: 1 October 2022 | L21: Insiders Own | M21: 0.002
B22: Market Cap. | C22: =C20*C21/1000000 -> 373687.07 | D22: Cash/Share | E22: =_xlfn.XLOOKUP("Cash & Eq.",'Fin. Data'!A:A,'Fin. Data'!B:B,,0)*1000000/C21 -> 24.922463 | F22: =Segments!C6 -> Other International | H22: =Segments!B6 -> 0.13211928 | I22: EBITDA | K22: =_xlfn.XLOOKUP(I22,'Fin. Data'!A:A,'Fin. Data'!B:B,,0) -> 25546 | L22: b (Yahoo) | M22: 0.79
B23: +Total Debt | C23: ='Fin. Data'!B58 -> 10906 | D23: EBIDTA/Net Financial Cost (NFC) | E23: ='Fin. Data (Common Size)'!B19/(-'Fin. Data (Common Size)'!B14) -> 102.68041 | I23: Depreciation & Amortization | K23: =_xlfn.XLOOKUP(I23,'Fin. Data'!A:A,'Fin. Data'!B:B,,0) -> 1900 | L23: Score (S&P) | M23: A+
B24: -Cash | C24: ='Fin. Data'!B39 -> 11049 | D24: Debt/EBITDA | E24: =_xlfn.XLOOKUP("Total Debt",'Fin. Data'!A:A,'Fin. Data'!B:B,,0)/_xlfn.XLOOKUP("EBITDA",'Fin. Data'!A:A,'Fin. Data'!B:B,,0) -> 0.42691615 | I24: EBIT | K24: =_xlfn.XLOOKUP(I24,'Fin. Data'!A:A,'Fin. Data'!B:B,,0) -> 7919 | L24: Price/Book Value | M24: =IFERROR((C20*C21/(E20-E21))/1000000,"") -> 18.098856
B25: =Enterprise Value | C25: =C22+C23-C24 -> 373544.07 | D25: "Others Assets"/Asset | E25: =_xlfn.XLOOKUP("Other Assets",'Fin. Data'!A:A,'Fin. Data'!B:B,,0)/_xlfn.XLOOKUP("Total Assets",'Fin. Data'!A:A,'Fin. Data'!B:B,,0) -> 0.038821183 | I25: Net Income | K25: =_xlfn.XLOOKUP(I25,'Fin. Data'!A:A,'Fin. Data'!B:B,,0) -> 5844 | L25: NCF(3y avg)/Asset | M25: =IFERROR(K31/E20,"") -> 0.077159243
B26: Holdings (nac/int'l) | C26: - | D26: Debt/Assets | E26: =_xlfn.XLOOKUP(D26,'Fin. Data'!A:A,'Fin. Data'!B:B,,0) -> 0.1699654 | F26: Categories | H26: % Sales | I26: EPS | K26: =1000000*K25/C21 -> 13.181905 | L26: Price/Net Inc. (3y avg) | M26: =IFERROR(C22/K30,"") -> 75.47709
B27: t liq. (Holdings/Vol.) | C27: - | D27: EBITDA Margin (average) | E27: =AVERAGE(_xlfn.XLOOKUP("EBITDA Margin",'Fin. Data'!A:A,'Fin. Data'!B:D,,0)) -> 0.11759095 | F27: =Segments!C14 -> Foods and Sundries | H27: =Segments!B14 -> 0.38445203 | I27: ROA | K27: =K25/E20 -> 0.091076271 | L27: EV/Asset | M27: =IFERROR(C25/E20,"") -> 5.8215265
B28: % Short | D28: Operating Margin (average) | E28: =AVERAGE(_xlfn.XLOOKUP("Operating Margin",'Fin. Data'!A:A,'Fin. Data'!B:D,,0)) -> 0.033721933 | F28: =Segments!C15 -> Non-Foods | H28: =Segments!B15 -> 0.27432317 | I28: ROIC | K28: =K25/(E20-(E21-C23)) -> 0.18521218 | L28: EV/Ebidta (3y average) | M28: =IFERROR(C25/K29,"") -> 16.221769
B29: Traffic ESG | D29: Net Income Margin (average) | E29: =AVERAGE(_xlfn.XLOOKUP("Net Income Margin",'Fin. Data'!A:A,'Fin. Data'!B:D,,0)) -> 0.025101101 | F29: =Segments!C16 -> Fresh Foods | H29: =Segments!B16 -> 0.13256858 | I29: EBITDA (3y average) | K29: =AVERAGE(_xlfn.XLOOKUP("EBITDA",'Fin. Data'!A:A,'Fin. Data'!B:D,,0)) -> 23027.333 | L29: Price/NCF (3y average) | M29: =IFERROR(C22/K31,"") -> 75.47709
B30: E | F30: =Segments!C17 -> Warehouse Ancillary and Other Businesses | H30: =Segments!B17 -> 0.20865622 | I30: Net Income (3y average) | K30: =AVERAGE(_xlfn.XLOOKUP("Net Income",'Fin. Data'!A:A,'Fin. Data'!B:D,,0)) -> 4951 | L30: Bonds 1,3,5a (USD) | M30: -
B31: S | D31: Net Financial Cost/Avg Net Debt | E31: =-_xlfn.XLOOKUP("Net Financial Cost",'Fin. Data'!A:A,'Fin. Data'!B:B,,0)/AVERAGE(_xlfn.XLOOKUP("Net Debt",'Fin. Data'!A:A,'Fin. Data'!B:D,,0)) -> 0.092971246 | F31: =Segments!#REF! -> #REF! | H31: =Segments!#REF! -> #REF! | I31: NCF (3y average) | K31: =AVERAGE(_xlfn.XLOOKUP("Net Income",'Fin. Data'!A:A,'Fin. Data'!B:D,,0)) -> 4951 | L31: Div+Rep.(3y avg)/Price | M31: =-IFERROR(SUM(E53:E55)/(3*C22),"") -> 0.0057365289
B32: G | L32: Div. Yield | M32: =-IFERROR(L54/C22,"") -> 0.0040087017
B33: INVESTMENT THESIS
B34: Pillars of Recommendation | H34: Recommendation | I34: Valuation Assumptions
B35: Pillar | C35: Explanation | H35: BUY | I35: CHECK DCF + ASSUMPTIONS
B36: Expansion Projections | C36: Costco has entered in new markets by partening with local companies, which is apparentely a way to overcoming government regulations, setting up local infrastructure and managing different types of risks in foreign markets
B37: Market share stability | C37: Costco is one of the worlds leading global retailer with its presence in eight countries. In spite of heavy competition in the retail industry, Costco has built a strong brand image by offering high-quality products at low prices with excellent customer service, along with other key factors.
B38: Customer retention and loyalty | C38: Costco has a membership warehouse model, which enables high-quality products at lower prices to its consumers. Unlike other competitors in the market, Costco allowed its customers to cancel their membership any time of the year and also reimbursed the unused portion of the membership
B39: Relationship with employees | C39: Costco has been considered one of the best places to work in the US.
B40: Risks of Investment | H40: Price Target | I40: Valuation
B41: Risk | C41: Explanation | H41: =DCF!D75 -> 623.05999 | I41: Discount Rate | J41: =DCF!F50 -> 0.099456414 | L41: Upside | M41: =DCF!D74 -> -0.26081387
B42: Growth & Expansion Risk | C42: "Our growth is dependent, in part, on our ability to acquire property and build or lease new warehouses and depots. We compete with other retailers and businesses for suitable locations. Local land use and other regulations restricting the construction and operation of our warehouses and depots, as well as local community actions opposed to the location of our warehouses or depots at specific sites and the adoption of local laws restricting our operations and environmental regulations, may impact our ability to find suitable locations and increase the cost of sites and of constructing, leasing and operating warehouses and depots. We also may have difficulty negotiating leases or purchase agreements on acceptable terms. In addition, certain jurisdictions have enacted or proposed laws and regulations that would prevent or restrict the operation or expansion plans of certain large retailers and warehouse clubs, including us. Failure to effectively manage these and other similar factors may affect our ability to timely build or lease and operate new warehouses and depots, which could have a material adverse effect on our future growth and profitability." - 10-K Form
B43: Failure to maintain membership growth | C43: Membership loyalty and growth are essential to our business. The extent to which we achieve growth in our membership base, increase the penetration of Executive membership, and sustain high renewal rates materially influences our profitability. Damage to our brands or reputation may negatively impact comparable sales, diminish member trust, and reduce renewal rates and, accordingly, net sales and membership fee revenue, negatively impacting our results of operations.
B44: Risk of shifting consumer preference | C44: The company uses a warehouse approach as it buys certain items in large quantities and tries to sell them as quickly as possible. This method only works if it can maintain those high volumes. If consumer preferences change, Costco could be left with large amounts of unwanted, and possibly perishable, goods.
B45: FINANCIAL PERFORMANCE
B46: Year | C46: Net Sales | D46: Operating Margin | E46: Dividends + Share Buyback | F46: Net Cash Flow | G46: Debt/Assets | H46: Depreciation & Amortization | I46: Capex + Investments | J46: Cash Flow
B47: =B48-1 -> 2014 | C47: {=_xlfn.SORTBY(TRANSPOSE(_xlfn.XLOOKUP(C$46,'Fin. Data'!$A:$A,'Fin. Data'!$B:$J,,0)),$B$47:$B$55,-1)} -> 112640 | D47: {=_xlfn.SORTBY(TRANSPOSE(_xlfn.XLOOKUP(D$46,'Fin. Data'!$A:$A,'Fin. Data'!$B:$J,,0)),$B$47:$B$55,-1)} -> 0.028924006 | E47: {=_xlfn.SORTBY(TRANSPOSE(_xlfn.XLOOKUP(E$46,'Fin. Data'!$A:$A,'Fin. Data'!$B:$J,,0)),$B$47:$B$55,-1)} -> -1082 | F47: =Inputs!J77 -> -444 | G47: {=_xlfn.SORTBY(TRANSPOSE(_xlfn.XLOOKUP(G$46,'Fin. Data'!$A:$A,'Fin. Data'!$B:$J,,0)),$B$47:$B$55,-1)} -> 0.15422117 | H47: {=_xlfn.SORTBY(TRANSPOSE(_xlfn.XLOOKUP(H$46,'Fin. Data'!$A:$A,'Fin. Data'!$B:$J,,0)),$B$47:$B$55,-1)} -> 1029 | I47: {=_xlfn.SORTBY(TRANSPOSE(_xlfn.XLOOKUP(I$46,'Fin. Data'!$A:$A,'Fin. Data'!$B:$J,,0)),$B$47:$B$55,-1)} -> -2073 | L47: =J20 -> 2022 | M47: =L47-1 -> 2021
B48: =B49-1 -> 2015 | C48: 116199 | D48: 0.031652596 | E48: -1323 | F48: =Inputs!I77 -> -1032 | G48: 0.18581337 | H48: 1127 | I48: -2507 | J48: Net Income | L48: =_xlfn.XLOOKUP($J48,'Fin. Data'!$A:$A,'Fin. Data'!B:B,,0) -> 5844 | M48: =_xlfn.XLOOKUP($J48,'Fin. Data'!$A:$A,'Fin. Data'!C:C,,0) -> 5007 | N48: =(C48/C47)-1 -> 0.031596236 | O48: =(D48/D47)-1 -> 0.094336529
B49: =B50-1 -> 2016 | C49: 118719 | D49: 0.031258686 | E49: -1442 | F49: =Inputs!H77 -> -2221 | G49: 0.15562525 | H49: 1255 | I49: -2375 | J49: Operating CF | L49: =_xlfn.XLOOKUP($J49,'Fin. Data'!$A:$A,'Fin. Data'!B:B,,0) -> 7392 | M49: =_xlfn.XLOOKUP($J49,'Fin. Data'!$A:$A,'Fin. Data'!C:C,,0) -> 8958 | N49: =(C49/C48)-1 -> 0.021686934 | O49: =(D49/D48)-1 -> -0.012444777 | Q49: =F49/F48-1 -> 1.1521318 | R49: =H49/H48-1 -> 0.11357587 | S49: =I49/I48-1 -> -0.052652573
B50: =B51-1 -> 2017 | C50: 129025 | D50: 0.031955047 | E50: -1475 | F50: =Inputs!G77 -> 3104 | G50: 0.18320632 | H50: 1370 | I50: -2370 | J50: Investing CF | L50: =_xlfn.XLOOKUP($J50,'Fin. Data'!$A:$A,'Fin. Data'!B:B,,0) -> -3915 | M50: =_xlfn.XLOOKUP($J50,'Fin. Data'!$A:$A,'Fin. Data'!C:C,,0) -> -3535 | N50: =(C50/C49)-1 -> 0.08681003 | O50: =(D50/D49)-1 -> 0.022277359 | Q50: =F50/F49-1 -> -2.3975687 | R50: =H50/H49-1 -> 0.091633466 | S50: =I50/I49-1 -> -0.0021052632
B51: =B52-1 -> 2018 | C51: 141576 | D51: 0.031968695 | E51: -1234 | F51: =Inputs!F77 -> 1643 | G51: 0.16108254 | H51: 1437 | I51: -2943 | J51: Net Capex | L51: =_xlfn.XLOOKUP($J51,'Fin. Data'!$A:$A,'Fin. Data'!B:B,,0) -> -3891 | M51: =_xlfn.XLOOKUP($J51,'Fin. Data'!$A:$A,'Fin. Data'!C:C,,0) -> -3588 | N51: =(C51/C50)-1 -> 0.097275722 | O51: =(D51/D50)-1 -> 0.00042709333 | Q51: =F51/F50-1 -> -0.47068299 | R51: =H51/H50-1 -> 0.048905109 | S51: =I51/I50-1 -> 0.24177215
B52: =B53-1 -> 2019 | C52: 152703 | D52: 0.031021002 | E52: -1557 | F52: =Inputs!E77 -> 2329 | G52: 0.15955947 | H52: 1492 | I52: -2835 | J52: Investments & Acquisitions | L52: =_xlfn.XLOOKUP($J52,'Fin. Data'!$A:$A,'Fin. Data'!B:B,,0) -> 3 | M52: =_xlfn.XLOOKUP($J52,'Fin. Data'!$A:$A,'Fin. Data'!C:C,,0) -> 101 | N52: =(C52/C51)-1 -> 0.078593829 | O52: =(D52/D51)-1 -> -0.029644429 | Q52: =F52/F51-1 -> 0.41752891 | R52: =H52/H51-1 -> 0.038274182 | S52: =I52/I51-1 -> -0.036697248
B53: =B54-1 -> 2020 | C53: 166761 | D53: 0.032591553 | E53: -2005 | F53: =Inputs!D77 -> -1448 | G53: 0.1995464 | H53: 1645 | I53: -3829 | J53: Financing CF | L53: =_xlfn.XLOOKUP($J53,'Fin. Data'!$A:$A,'Fin. Data'!B:B,,0) -> -3890 | M53: =_xlfn.XLOOKUP($J53,'Fin. Data'!$A:$A,'Fin. Data'!C:C,,0) -> -4283 | N53: =(C53/C52)-1 -> 0.09206106 | O53: =(D53/D52)-1 -> 0.050628656 | Q53: =F53/F52-1 -> -1.6217261 | R53: =H53/H52-1 -> 0.10254692 | S53: =I53/I52-1 -> 0.35061728
B54: =B55-1 -> 2021 | C54: 195929 | D54: 0.034236892 | E54: -2126 | F54: =Inputs!C$77 -> 1186 | G54: 0.19246474 | H54: 1781 | I54: -3487 | J54: Dividends | L54: =_xlfn.XLOOKUP($J54,'Fin. Data'!$A:$A,'Fin. Data'!B:B,,0) -> -1498 | M54: =_xlfn.XLOOKUP($J54,'Fin. Data'!$A:$A,'Fin. Data'!C:C,,0) -> -1318 | N54: =(C54/C53)-1 -> 0.174909 | O54: =(D54/D53)-1 -> 0.050483594 | Q54: =F54/F53-1 -> -1.8190608 | R54: =H54/H53-1 -> 0.082674772 | S54: =I54/I53-1 -> -0.08931836
B55: =J20 -> 2022 | C55: 226954 | D55: 0.034337355 | E55: -2300 | F55: =Inputs!B77 -> -662 | G55: 0.1699654 | H55: 1900 | I55: -3888 | J55: Share Buyback | L55: =_xlfn.XLOOKUP($J55,'Fin. Data'!$A:$A,'Fin. Data'!B:B,,0) -> -802 | M55: =_xlfn.XLOOKUP($J55,'Fin. Data'!$A:$A,'Fin. Data'!C:C,,0) -> -808 | N55: =(C55/C54)-1 -> 0.15834818 | O55: =(D55/D54)-1 -> 0.0029343426 | Q55: =F55/F54-1 -> -1.5581788 | R55: =H55/H54-1 -> 0.066816395 | S55: =I55/I54-1 -> 0.11499857
B56: Annual Growth Rate | C56: =IFERROR((C55/C47)^(1/8)-1,"") -> 0.091517367 | D56: =IFERROR((D55/D47)^(1/8)-1,"") -> 0.021676842 | F56: =IFERROR((F55/F47)^(1/8)-1,"") -> 0.051197641 | H56: =IFERROR((H55/H47)^(1/8)-1,"") -> 0.079673093 | J56: FX | L56: =_xlfn.XLOOKUP($J56,'Fin. Data'!$A:$A,'Fin. Data'!B:B,,0) -> -249 | M56: =_xlfn.XLOOKUP($J56,'Fin. Data'!$A:$A,'Fin. Data'!C:C,,0) -> 46 | N56: =(C56/C55)-1 -> -0.9999996 | O56: =(D56/D55)-1 -> -0.36870961
B57: Average Growth Rate | C57: =IFERROR(AVERAGE(N48:N55),"") -> 0.092660124 | D57: =IFERROR(AVERAGE(O48:O55),"") -> 0.022374796 | F57: =IFERROR(AVERAGE(Q48:Q55),"") -> -0.89965094 | H57: =IFERROR(AVERAGE(S48:S55),"") -> 0.075230651 | J57: Changes in Cash | L57: =L49-L50+L53-L54-L55 -> 9717 | M57: =M49-M50+M53-M54-M55 -> 10336
B58: CVAR | C58: =IFERROR(STDEV(C48:C55)/AVERAGE(C48:C55),"") -> 0.25023995 | D58: =IFERROR(STDEV(D47:D55)/AVERAGE(D47:D55),"") -> 0.051725808 | F58: =IFERROR(STDEV(F47:F55)/AVERAGE(F47:F55),"") -> 6.7629006 | H58: =IFERROR(STDEV(H47:H55)/AVERAGE(H47:H55),"") -> 0.20098587 | J58: Inventory/D Revenues | L58: =IFERROR(SUM(I52:I55)/(C55-C51),"") -> -0.16443346 | M58: =IFERROR((SUM(I52:I55)-SUM(H52:H55))/(C55-C51),"") -> -0.2442901
B59: Last Year | C59: =IFERROR(C55/C54-1,"") -> 0.15834818 | D59: =IFERROR(1-(D55/D54),"") -> -0.0029343426 | F59: =IFERROR(1-(F55/F54),"") -> 1.5581788 | H59: =IFERROR(1-(H55/H54),"") -> -0.066816395 | J59: t inversiones; t adq. neto dep. | L59: =IFERROR(L58/E27,"") -> -1.3983513 | M59: =IFERROR(M58/E27,"") -> -2.0774566
B60: QUALITATIVE ANALYSIS
B61: SWOT ANALYSIS | J61: HOLDERS
B62: Pros | E62: Cons | J62: Name | M62: % Stake
B63: Efficient Supply Chain Management: Costco invests heavily in technology to streamline its Supply Chain operations and ensure that products are delivered to its warehouses promptly and efficiently. | E63: Limited product selection: Costco’s focus on bulk items may lead to excluding some essential products from its inventory, which can be a significant disadvantage for customers looking for specific items. | J63: Vanguard Group Inc | M63: 0.0897
B64: Strong Brand reputation: known for its high-quality products, competitive prices, and excellent customer service, which has helped it build the consumer's loyalty | J64: Blackrock Inc. | M64: 0.0701
B65: Experienced workforce: low employee turnover, emphasis on employee training and development, etc. | J65: State Street Corporation | M65: 0.0424
B66: Unique membership model: enables Costco to maintain low overhead costs while offering products at discounted prices | E66: Minimal customer service: no-frills approach, which means it does not offer many personalized services like other retailers | J66: FMR, LLC | M66: 0.0213
B67: Commitment to sustainability: Costco has implemented several initiatives to reduce its environmental impact, such as reducing waste, using renewable energy sources, and promoting sustainable sourcing, which also helps to improve the brand awareness and reputation. | J67: Morgan Stanley | M67: 0.0193
J68: Geode Capital Management, LLC | M68: 0.0185
J69: Bank of America Corporation | M69: 0.0183
J70: Bank Of New York Mellon Corporation | M70: 0.0126
J71: Northern Trust Corporation | M71: 0.0116
J72: Norges Bank Investment Management | M72: 0.0115
B73: Opportunities | E73: Risks
B74: Partnerships and Acquisitions, in order to consolidate market share in locations that Costco is already established, or new markets in which the company wants to test. | E74: Growth & Expansion Risk: the company has faced challenges opening new stores in some countries due to cultural differences, regulatory barriers, local competition, or economic and political instability. For example, in some regions, there may be concerns about the environmental impact of bulk packaging or the treatment of animals in Costco’s supply chain
B75: Membership rewards: Costco can increase customer loyalty and retention by offering more attractive membership rewards, such as exclusive discounts, cashback programs, and free shipping. | E75: Changes in trade policies and tariffs: as a retailer that imports a significant amount of goods from other countries, Costco is vulnerable to changes in trade policies or tariffs.
B76: NOTES | G76: STOCK PERFORMANCE (5 years)

Sheet Segments
A1: PE
B2: ="Regions "&"("&OP!$J$20&")" -> Regions (2022) | Q2: Products
D3: Nominal value | K3: YoY Growth
B4: Weight | C4: Region | D4: =OP!J20 -> 2022 | E4: =D4-1 -> 2021 | F4: =E4-1 -> 2020 | G4: =F4-1 -> 2019 | H4: =G4-1 -> 2018 | I4: =H4-1 -> 2017 | K4: =OP!J20 -> 2022 | L4: =K4-1 -> 2021 | M4: =L4-1 -> 2020 | N4: =M4-1 -> 2019 | O4: =N4-1 -> 2018 | P4: =O4-1 -> 2017
B5: =IFERROR(D5/$D$9,"") -> 0.86788072 | C5: United States and Canada | D5: =165294+31675 -> 196969 | E5: =141398+27298 -> 168696 | F5: =122142+22434 -> 144576 | G5: =111751+21366 -> 133117 | H5: =102286+20689 -> 122975 | I5: =93889+18775 -> 112664 | K5: =(D5-E5)/E5 -> 0.16759733 | L5: =(E5-F5)/F5 -> 0.16683267 | M5: =(F5-G5)/G5 -> 0.086082168 | N5: =(G5-H5)/H5 -> 0.082472047 | O5: =(H5-I5)/I5 -> 0.091519918
B6: =IFERROR(D6/$D$9,"") -> 0.13211928 | C6: Other International | D6: =29985 -> 29985 | E6: 27233 | F6: 22185 | G6: 19586 | H6: 18601 | I6: 16361 | K6: =(D6-E6)/E6 -> 0.10105387 | L6: =(E6-F6)/F6 -> 0.22754113 | M6: =(F6-G6)/G6 -> 0.13269682 | N6: =(G6-H6)/H6 -> 0.052954142 | O6: =(H6-I6)/I6 -> 0.13691095
B7: =IFERROR(D7/$D$9,"") -> 0
B8: =IFERROR(D8/$D$9,"") -> 0
B9: =SUM(B5:B8) -> 1 | C9: TOTAL | D9: =SUM(D5:D8) -> 226954 | E9: =SUM(E5:E8) -> 195929 | F9: =SUM(F5:F8) -> 166761 | G9: =SUM(G5:G8) -> 152703 | H9: =SUM(H5:H8) -> 141576 | I9: =SUM(I5:I8) -> 129025 | K9: =(D9-E9)/E9 -> 0.15834818 | L9: =(E9-F9)/F9 -> 0.174909 | M9: =(F9-G9)/G9 -> 0.09206106 | N9: =(G9-H9)/H9 -> 0.078593829 | O9: =(H9-I9)/I9 -> 0.097275722 | P9: 0.037
B11: ="Categories "&"("&OP!$J$20&")" -> Categories (2022)
D12: Nominal value | K12: YoY Growth
B13: Weight | C13: Category | D13: =OP!J20 -> 2022 | E13: =D13-1 -> 2021 | F13: =E13-1 -> 2020 | G13: =F13-1 -> 2019 | H13: =G13-1 -> 2018 | I13: =H13-1 -> 2017 | K13: =OP!J20 -> 2022 | L13: =K13-1 -> 2021 | M13: =L13-1 -> 2020 | N13: =M13-1 -> 2019 | O13: =N13-1 -> 2018 | P13: =O13-1 -> 2017
B14: =IFERROR(D14/$D$18,"") -> 0.38445203 | C14: Foods and Sundries | D14: 85629 | E14: 77277 | F14: 68659 | G14: 59672 | H14: 56073 | I14: 52362 | K14: =(D14-E14)/E14 -> 0.10807873 | L14: =(E14-F14)/F14 -> 0.12551887 | M14: =(F14-G14)/G14 -> 0.15060665 | N14: =(G14-H14)/H14 -> 0.064184188 | O14: =(H14-I14)/I14 -> 0.070872006
B15: =IFERROR(D15/$D$18,"") -> 0.27432317 | C15: Non-Foods | D15: 61100 | E15: 55966 | F15: 44807 | G15: =24570+16590 -> 41160 | H15: =22620+15387 -> 38007 | I15: =20583+14537 -> 35120 | K15: =(D15-E15)/E15 -> 0.091734267 | L15: =(E15-F15)/F15 -> 0.24904591 | M15: =(F15-G15)/G15 -> 0.088605442 | N15: =(G15-H15)/H15 -> 0.082958402 | O15: =(H15-I15)/I15 -> 0.082203872
B16: =IFERROR(D16/$D$18,"") -> 0.13256858 | C16: Fresh Foods | D16: 29527 | E16: 27183 | F16: 23204 | G16: 19948 | H16: 18879 | I16: 17849 | K16: =(D16-E16)/E16 -> 0.086230365 | L16: =(E16-F16)/F16 -> 0.17147906 | M16: =(F16-G16)/G16 -> 0.16322438 | N16: =(G16-H16)/H16 -> 0.056623762 | O16: =(H16-I16)/I16 -> 0.057706314
B17: =IFERROR(D17/$D$18,"") -> 0.20865622 | C17: Warehouse Ancillary and Other Businesses | D17: 46474 | E17: 31626 | F17: 26550 | G17: 28571 | H17: 25475 | I17: 20841 | K17: =(D17-E17)/E17 -> 0.46948713 | L17: =(E17-F17)/F17 -> 0.19118644 | M17: =(F17-G17)/G17 -> -0.070736061 | N17: =(G17-H17)/H17 -> 0.12153091 | O17: =(H17-I17)/I17 -> 0.22235018
B18: =SUM(B14:B17) -> 1 | C18: TOTAL | D18: =SUM(D14:D17) -> 222730 | E18: =SUM(E14:E17) -> 192052 | F18: =SUM(F14:F17) -> 163220 | G18: =SUM(G14:G17) -> 149351 | H18: =SUM(H14:H17) -> 138434 | I18: =SUM(I14:I17) -> 126172 | K18: =(D18-E18)/E18 -> 0.15973799 | L18: =(E18-F18)/F18 -> 0.17664502 | M18: =(F18-G18)/G18 -> 0.092861782 | N18: =(G18-H18)/H18 -> 0.078860685 | O18: =(H18-I18)/I18 -> 0.097184795 | P18: 0.037
B20: Categories | D20: Description | I20: Graphs
B21: Foods and Sundries | D21: This categorie includes sundries, dry grocery, candy, cooler, freezer, deli, liquor and tobacco
B22: Non-Foods | D22: Including major appliances, electronics, health and beauty aids, hardware, garden and patio, sporting goods, tires, toys and seasonal, office supplies, automotive care, postage, tickets, apparel, small appliances, furniture, domestics, housewares, special order kiosk and jewelry
B23: Fresh Foods | D23: including meat, produce, service deli and bakery
B24: Warehouse Ancillary and Other Businesses | D24: Warehouse ancillary includes gasoline, pharmacy, optical, food court, hearing aids and tire installation. Other Businesses includes e-commerce, business centers, travel and other
B28: Industry | J28: Graphs (Industry Forecasts)
B29: Drivers | D29: Description
B30: Consumer preferences | D30: Consumer Staples are in constant demand. Usually, economic cycles do not affect this sector, what makes the demand stable and predictable. Also, in 2022, consumer staples earned its reputation as a defensive sector, by outperforming the broad market.
B31: Merchandise Quality and Selection
B32: Distribution Strategy
B33: Price competition | D33: Price competition strategies are common in the sector, which requires economies of scale, as well as, some market share stability.
B34: Sales forecast
B35: Source | D35: Market Growth CGAR | G35: Period
B36: https://simplywall.st/markets/us/consumer-staples | D36: 0.12 | G36: 2023-2027
B40: Company's Strategy / Extra Notes

Sheet Acuerdo
A1: Invertir
A2: NO invertir
A3: Mantener sin elevar posición
A4: Mantener (y seguir comprando)
A5: Liquidar
A6: PENDIENTE

Sheet Peers
B1: Peer Logo | C1: Peer Name | D1: Description
C2: =D8 -> #VALUE! | D2: With over 11,500 stores globally, Walmart is the largest retailer chain in the world and the top Costco competitor in 2021. The retail giant was founded in 1962 by Sam Walton and now employs over 2 million people across 27 countries. In FY2020, Walmart’s annual revenue was $524.4 billion and ranked 19th most valuable brand in the world on Forbes’ Global 2000 list. Walmart offers apparel, appliances, electronics, home improvement, jewelry, games, household essentials, pharmaceutical products, and many more. It also owns Sam’s Club, which a membership-only wholesaler that competes against Costco for bulk buyers. Walmart is Costco’s top competitor for many reasons.
C3: =E8 -> #VALUE! | D3: Established in 1994 by Jeff Bezos, Amazon has grown to become the global powerhouse in the eCommerce sector. Costco’s private labels like Kirkland accounts for 25% of its $118.7 billion in annual sales. Amazon has invested heavily to expand its private-label offerings and currently has 146 private-label brands and 640 exclusive brands. These private labels can eliminate Costco’s main competitive edge. According to a price comparison by Cheapism, items offered by Costco are about 25% cheaper on average compared to Amazon’s prices. Offering consumers value for money can help Costco fend off Amazon’s threat.
C4: =F8 -> #VALUE! | D4: Founded in 1883 in Ohio, Kroger is one of the largest food retailers in the world. The retailer operates over 2,764 supermarkets across 35 states in the US. In 2018, Kroger’s partnership with online retailer Ocado delivered 20 automated fulfillment centers, more than 2,000 pickup locations, and 2,400 delivery locations by 2020. These resources expanded Kroger’s reach to 97% of its customers and boosted its revenue for Q1 2020 by 11.5% year-over-year to $41.5 billion. Kroger has also built a stronger eCommerce than Costco, which boosted its digital sales by 92% in 2020. Kroger’s fulfillment centers and robust eCommerce makes it one of the top Costco competitors in 2021.
C5: =G8 -> #VALUE! | D5: Simply known as Walgreens, WBA was founded in 1901 by Charles Walgreen and provides drug store services primarily in the U.S. and Europe. It has 400 distribution centers and more than 18,750 stores spread across 11 countries. Every year, the chain’s distribution centers reach more than 25,000 pharmacies, doctors, hospitals, and health centers across the world. In 2020, footfall in its stores dropped by about 85% due to the crisis leading to a net loss of $1.71 billion in the third quarter. Its overdependence on medical services is a major weakness over Costco.
C6: =H8 -> #VALUE! | D6: Founded in 1902, Target is one of the largest retailers in the world and a strong Costco competitor. It operates over 1,000 stores in the US alone and 360,000 employees spread across 50 states. Even though both Target and Costco are offering in-store and curbside pickup, Target’s initiatives are more effective and include Shipt, Drive Up services, and Target+ marketplace. In 2020, Target’s gross margins averaged out to 29%, while Costco’s gross margins were only 13%. Target also has a membership program just like Costco. But Target does not charge annual membership fees, which gives it an edge over Costco.
B8: In Millions USD (exc Market Cap) | C8: =OP!E2 -> #VALUE! | D8: #VALUE! | E8: #VALUE! | F8: #VALUE! | G8: #VALUE! | H8: #VALUE! | I8: AVERAGE
B9: Company Info | I9: =IFERROR(AVERAGE(C9:H9),"")
B10: Market Cap | C10: {=_FV(C8,"Market cap",TRUE)/1000000} -> 373687.1 | D10: {=_FV(D8,"Market cap",TRUE)/1000000} -> 556934.9 | E10: {=_FV(E8,"Market cap",TRUE)/1000000} -> 2023985 | F10: {=_FV(F8,"Market cap",TRUE)/1000000} -> 37886.8 | G10: {=_FV(G8,"Market cap",TRUE)/1000000} -> 9927.663 | H10: {=_FV(H8,"Market cap",TRUE)/1000000} -> 70714 | I10: =IFERROR(AVERAGE(C10:H10),"") -> 512189.24
B11: Net Sales (current) | C11: =C53 -> 226954 | D11: =D53 -> 611289 | E11: =E53 -> 513983 | F11: =F53 -> 148258 | G11: =G53 -> 133291 | H11: =H53 -> 109120 | I11: =IFERROR(AVERAGE(C11:H11),"") -> 290482.5
B12: Profitability | I12: =IFERROR(AVERAGE(C12:H12),"")
B13: Sales Growth (ttm) | C13: =C53/C52-1 -> 0.15834818 | D13: =D53/D52-1 -> 0.067280194 | E13: =E53/E52-1 -> 0.093995173 | F13: =F53/F52-1 -> 0.075205964 | G13: =G53/G52-1 -> 0.0044309473 | H13: =H53/H52-1 -> 0.029385406 | I13: =IFERROR(AVERAGE(C13:H13),"") -> 0.071440977
B14: Sales Growth (36m) | C14: =C53/C51-1 -> 0.48624454 | D14: =D53/D51-1 -> 0.16666221 | E14: =E53/E51-1 -> 0.83223776 | F14: =F53/F51-1 -> 0.21237744 | G14: =G53/G51-1 -> -0.044762321 | H14: =H53/H51-1 -> 0.39696846 | I14: =IFERROR(AVERAGE(C14:H14),"") -> 0.34162135
B15: Operating Margin | C15: =C56/C53 -> 0.034337355 | D15: =D56/D53 -> 0.033417909 | E15: =E56/E53 -> 0.023829582 | F15: =F56/F53 -> 0.027829864 | G15: =G56/G53 -> -0.055817722 | H15: =H56/H53 -> 0.03526393 | I15: =IFERROR(AVERAGE(C15:H15),"") -> 0.016476819
B16: Net Income Margin | C16: =C59/C53 -> 0.025749711 | D16: =D59/D53 -> 0.019107165 | E16: =E59/E53 -> 0.005295895 | F16: =F59/F53 -> 0.015135777 | G16: =G59/G53 -> -0.023587489 | H16: =H59/H53 -> 0.02547654 | I16: =IFERROR(AVERAGE(C16:H16),"") -> 0.011196267
B17: Return on Equity (RoE) | C17: =C59/C70 -> 0.2831121 | D17: =D59/D70 -> 0.13940609 | E17: =E59/E70 -> 0.018638346 | F17: =F59/F70 -> 0.22408628 | G17: =G59/G70 -> -0.10339384 | H17: =H59/H70 -> 0.24750712 | I17: =IFERROR(AVERAGE(C17:H17),"") -> 0.13489268
B18: Return on Invested Capital (ROIC) | C18: =(C59+C58)/(C69+C70) -> 0.24625967 | D18: =(D59+D58)/(D69+D70) -> 0.14695229 | E18: =(E59+E58)/(E69+E70) -> 0.040611089 | F18: =(F59+F58)/(F69+F70) -> 0.45443306 | G18: =(G59+G58)/(G69+G70) -> -0.13025727 | H18: =(H59+H58)/(H69+H70) -> 0.22972725 | I18: =IFERROR(AVERAGE(C18:H18),"") -> 0.16462101
B19: Solvency | I19: =IFERROR(AVERAGE(C19:H19),"")
B20: Debt/Assets | C20: =C69/C66 -> 0.1699654 | D20: =D69/D66 -> 0.14247297 | E20: =E69/E66 -> 0.14513427 | F20: =F69/F66 -> 0.026399049 | G20: =G69/G66 -> 0.39364653 | H20: =H69/H66 -> 0.30015937 | I20: =IFERROR(AVERAGE(C20:H20),"") -> 0.19629627
B21: Net Debt/EBITDA | C21: =(C69-C61)/C55 -> -0.0055977452 | D21: =(D69-D61)/D55 -> 0.86490079 | E21: =(E69-E61)/E55 -> 0.34579683 | F21: =(F69-F61)/F55 -> 0.026083238 | G21: =(G69-G61)/G55 -> -11.184344 | H21: =(H69-H61)/H55 -> 2.0891449 | I21: =IFERROR(AVERAGE(C21:H21),"") -> -1.3106694
B22: Interest Coverage Ratio | C22: =-C55/C57 -> -263.36082 | D22: =-D55/D57 -> 16.05603 | E22: =-E55/E57 -> 27.83164 | F22: =-F55/F57 -> 13.114019 | G22: =-G55/G57 -> -6.332618 | H22: =-H55/H57 -> 13.799163 | I22: =IFERROR(AVERAGE(C22:H22),"") -> -33.148765
B23: Liquidity
B24: Current Ratio | C24: =C64/C68 -> 1.0218139 | D24: =D64/D68 -> 0.82057095 | E24: =E64/E68 -> 0.94464358 | F24: =F64/F68 -> 0.73500406 | G24: =G64/G68 -> 0.74843909 | H24: =H64/H68 -> 0.91517949 | I24: =IFERROR(AVERAGE(C24:H24),"") -> 0.86427517
B25: Quick Ratio | C25: =(C61+C62)/C68 -> 0.41533846 | D25: =(D61+D62)/D68 -> 0.17959175 | E25: =(E61+E62)/E68 -> 0.55844858 | F25: =(F61+F62)/F68 -> 0.19497622 | G25: =(G61+G62)/G68 -> 0.33162113 | H25: =(H61+H62)/H68 -> 0.17425641 | I25: =IFERROR(AVERAGE(C25:H25),"") -> 0.30903876
B26: Activity | I26: =IFERROR(AVERAGE(C26:H26),"")
B27: Inventory Turnover | C27: =C54/C63 -> 11.134305 | D27: =D54/D63 -> 8.196426 | E27: =E54/E63 -> 12.973202 | F27: =F54/F63 -> 15.407407 | G27: =G54/G63 -> 12.725847 | H27: =H54/H63 -> 6.091037 | I27: =IFERROR(AVERAGE(C27:H27),"") -> 11.088037
B28: Acc. Receivable Turnover | C28: =C53/C62 -> 101.27354 | D28: =D53/D62 -> 77.056473 | E28: =E53/E62 -> 15.626858 | F28: =F53/F62 -> 66.364369 | G28: =G53/G62 -> 26.567869 | H28: =H53/H62 -> 93.344739 | I28: =IFERROR(AVERAGE(C28:H28),"") -> 63.372308
A29: Price/Sales | B29: Payables Turnover | C29: =C54/C67 -> 11.171112 | D29: =D54/D67 -> 8.6286517 | E29: =E54/E67 -> 5.6073241 | F29: =F54/F67 -> 16.361849 | G29: =G54/G67 -> 9.3746362 | H29: =H54/H67 -> 6.0969081 | I29: =IFERROR(AVERAGE(C29:H29),"") -> 9.5400801
B30: Fixed Asset Turnover | C30: =C53/C65 -> 5.1201101 | D30: =D53/D65 -> 3.6485717 | E30: =E53/E65 -> 3.2067619 | F30: =F53/F65 -> 5.9960366 | G30: =G53/G65 -> 1.9255583 | H30: =H53/H65 -> 3.1405054 | I30: =IFERROR(AVERAGE(C30:H30),"") -> 3.8395907
B31: Total Asset Turnover | C31: =C53/C66 -> 3.5369822 | D31: =D53/D66 -> 2.5135549 | E31: =E53/E66 -> 1.1108943 | F31: =F53/F66 -> 2.9876872 | G31: =G53/G66 -> 1.4789734 | H31: =H53/H66 -> 2.0459361 | I31: =IFERROR(AVERAGE(C31:H31),"") -> 2.2790047
B32: Valuation | I32: =IFERROR(AVERAGE(C32:H32),"")
B33: Price/Earnings | C33: =C10/C59 -> 63.94372 | D33: =D10/D59 -> 47.682783 | E33: =E10/E59 -> 743.56539 | F33: =F10/F59 -> 16.883601 | G33: =G10/G59 -> -3.1576536 | H33: =H10/H59 -> 25.436691 | I33: =IFERROR(AVERAGE(C33:H33),"") -> 149.05909
B34: Price/Sales | C34: =C10/C53 -> 1.6465323 | D34: =D10/D53 -> 0.91108281 | E34: =E10/E53 -> 3.9378442 | F34: =F10/F53 -> 0.25554641 | G34: =G10/G53 -> 0.07448112 | H34: =H10/H53 -> 0.64803886 | I34: =IFERROR(AVERAGE(C34:H34),"") -> 1.2455876
B35: Price/Book | C35: =C10/C70 -> 18.103241 | D35: =D10/D70 -> 6.6472704 | E35: =E10/E70 -> 13.858829 | F35: =F10/F70 -> 3.7833833 | G35: =G10/G70 -> 0.32648195 | H35: =H10/H70 -> 6.2957621 | I35: =IFERROR(AVERAGE(C35:H35),"") -> 8.1691613
B36: EV/Sales | C36: =(C69+C10-C61)/C53 -> 1.6459023 | D36: =(D69+D10-D61)/D53 -> 0.95365515 | E36: =(E69+E10-E61)/E53 -> 3.9636467 | F36: =(F69+F10-F61)/F53 -> 0.25678075 | G36: =(G69+G10-G61)/G53 -> 0.32209724 | H36: =(H69+H10-H61)/H53 -> 0.77432185 | I36: =IFERROR(AVERAGE(C36:H36),"") -> 1.3194006
B37: EV/EBITDA | C37: =(C69+C10-C61)/C55 -> 14.622411 | D37: =(D69+D10-D61)/D55 -> 19.374486 | E37: =(E69+E10-E61)/E55 -> 53.119707 | F37: =(F69+F10-F61)/F55 -> 5.4261403 | G37: =(G69+G10-G61)/G55 -> -14.548513 | H37: =(H69+H10-H61)/H55 -> 12.809885 | I37: =IFERROR(AVERAGE(C37:H37),"") -> 15.134019
B38: Stock Info | I38: =IFERROR(AVERAGE(C38:H38),"")
B39: Float | C39: =OP!M20 -> 0.99738238 | D39: 0.989 | E39: 0.989 | F39: 0.9718 | G39: 0.948 | H39: 0.9789 | I39: =IFERROR(AVERAGE(C39:H39),"") -> 0.97901373
B40: b (Yahoo) | C40: =OP!M22 -> 0.79 | D40: 0.5 | E40: 1.26 | F40: 0.48 | G40: 0.67 | H40: 1.01 | I40: =IFERROR(AVERAGE(C40:H40),"") -> 0.59
B41: Dividend Yield (yahoo finance) | C41: =OP!M32 -> 0.0040087017 | D41: 1.45% | E41: 0 | F41: 0.0241 | G41: 6.27% | H41: 3.23% | I41: =IFERROR(AVERAGE(C41:H41),"") -> 0.0093695672
B42: Stock Performance
B43: 1y | C43: 0.0566 | D43: 0.2251 | E43: 0.0812 | F43: 0.0153 | G43: -0.2043 | H43: -0.1313 | I43: =IFERROR(AVERAGE(C43:H43),"") -> 0.0071
B44: 3y | C44: 0.9042 | D44: 0.2715 | E44: -0.1187 | F44: 0.4767 | G44: -0.1623 | H44: 0.1588 | I44: =IFERROR(AVERAGE(C44:H44),"") -> 0.25503333
B45: Current Price | C45: {=_FV(C8,"Price")} -> 842.9 | D45: {=_FV(D8,"Price")} -> 69.24 | E45: {=_FV(E8,"Price")} -> 194.49 | F45: {=_FV(F8,"Price")} -> 52.49 | G45: {=_FV(G8,"Price")} -> 11.5 | H45: {=_FV(H8,"Price")} -> 152.85 | I45: =IFERROR(AVERAGE(C45:H45),"") -> 220.57833
B46: Average Target Price | C46: 553.25 | D46: 169.44 | E46: 145 | F46: 51.8 | G46: 31.77 | H46: 175.9 | I46: =IFERROR(AVERAGE(C46:H46),"") -> 187.86
B47: Upside/Downside | C47: =C46/C45-1 -> -0.34363507 | D47: =D46/D45-1 -> 1.4471404 | E47: =E46/E45-1 -> -0.25446038 | F47: =F46/F45-1 -> -0.013145361 | G47: =G46/G45-1 -> 1.7626087 | H47: =H46/H45-1 -> 0.15080144 | I47: =IFERROR(AVERAGE(C47:H47),"") -> 0.45821828
B49: Financial Data | C49: =OP!E2 -> #VALUE! | D49: Walmart | E49: Amazon | F49: Kroger | G49: Wallgreens Boots Alliance | H49: Target
B50: IS
B51: Net Sales (36m ago) | C51: ='Fin. Data'!E5 -> 152703 | D51: 523964 | E51: 280522 | F51: 122287 | G51: 139537 | H51: 78112
B52: Net Sales (12m ago) | C52: ='Fin. Data'!C5 -> 195929 | D52: 572754 | E52: 469822 | F52: 137888 | G52: 132703 | H52: 106005
B53: Net Sales (current) | C53: ='Fin. Data'!B5 -> 226954 | D53: 611289 | E53: 513983 | F53: 148258 | G53: 133291 | H53: 109120
B54: COGS | C54: ='Fin. Data'!B5-'Fin. Data'!B7 -> 199382 | D54: 463721 | E54: 446343 | F54: 116480 | G54: 106299 | H54: 82229
B55: EBITDA | C55: ='Fin. Data'!B19 -> 25546 | D55: 30089 | E55: 38352 | F55: 7016 | G55: -2951 | H55: 6596
B56: Operating Income | C56: ='Fin. Data'!B11 -> 7793 | D56: 20428 | E56: 12248 | F56: 4126 | G56: -7440 | H56: 3848
B57: Net Financial Cost | C57: ='Fin. Data'!B14 -> 97 | D57: -1874 | E57: -1378 | F57: -535 | G57: -466 | H57: -478
B58: Taxes | C58: ='Fin. Data'!B21 -> 1925 | D58: 5724 | E58: 5936 | F58: 2902 | G58: -5438 | H58: 3478
B59: Net Income | C59: ='Fin. Data'!B23 -> 5844 | D59: 11680 | E59: 2722 | F59: 2244 | G59: -3144 | H59: 2780
B60: BS
B61: Cash & Eq. | C61: ='Fin. Data'!B39 -> 11049 | D61: 8625 | E61: 53888 | F61: 1127 | G61: 2472 | H61: 2229
B62: Acc. Receivables | C62: ='Fin. Data'!B40 -> 2241 | D62: 7933 | E62: 32891 | F62: 2234 | G62: 5017 | H62: 1169
B63: Inventory | C63: ='Fin. Data'!B41 -> 17907 | D63: 56576 | E63: 34405 | F63: =9756-2196 -> 7560 | G63: 8353 | H63: 13500
B64: Current Assets | C64: =Inputs!B27 -> 32696 | D64: 75655 | E64: 146791 | F64: 12670 | G64: 16902 | H64: 17846
B65: Fixed Assets | C65: ='Fin. Data'!B42 -> 44326 | D65: =100760+13555+4919+28174+20134 -> 167542 | E65: 160281 | F65: 24726 | G65: 69222 | H65: 34746
B66: Total Assets | C66: ='Fin. Data'!B44 -> 64166 | D66: =243197 -> 243197 | E66: 462675 | F66: 49623 | G66: 90124 | H66: 53335
B67: Acc. Payable | C67: =Inputs!B43 -> 17848 | D67: 53742 | E67: 79600 | F67: 7119 | G67: 11339 | H67: 13487
B68: Current Liabilities | C68: =Inputs!B42 -> 31998 | D68: 92198 | E68: 155393 | F68: 17238 | G68: 22583 | H68: 19500
B69: Total Debt | C69: ='Fin. Data'!B58 -> 10906 | D69: 34649 | E69: 67150 | F69: 1310 | G69: 35477 | H69: 16009
B70: Total Equity | C70: ='Fin. Data'!B64 -> 20642 | D70: 83784 | E70: 146043 | F70: 10014 | G70: 30408 | H70: 11232

Sheet ESG
B1: Company GICS Sector: | T1: Yes
B2: Consumer Staples | C2: <- Select Industry | T2: No
B3: ESG Analysis | K3: Relative ESG Analysis
B4: Parameters | C4: Impact | D4: Do they report? | E4: Ranking | F4: Mitigation Plan | G4: Traffic Lights | H4: Improvement over time? | I4: Targets / Goals? | J4: Comments | K4: Parameters | L4: Costco | M4: Walmart | N4: Amazon | O4: Kroger | P4: Walgreens | Q4: Target
B5: Environmental | K5: Ratios
A6: 1 | B6: CO2 Direct Emissions | C6: =VLOOKUP($B$2,'Sector Impact'!$K$4:$AA$16,A6+1,FALSE) -> High | D6: Yes | E6: Medium High | F6: Yes | H6: High | I6: 39% cumulative absolute CO2 reduction 2030 | J6: “We align our decarbonization objectives with our commitments to human rights, diversity, equity and inclusion, life above land and below water, water conservation, and waste reduction,” the company’s mission statement says. | K6: CO2 Emissions/$M Sales | L6: =L12/L$11 -> 0.00063625228 | M6: =M12/M$11 -> 0.00022886065 | N6: =N12/N$11 -> 0.00013866217 | O6: =O12/O$11 -> 0.035417988 | P6: =P12/P$11 -> 0.011831256 | Q6: =Q12/Q$11 -> 0.015460044
A7: 2 | B7: Total Water Consumption | C7: =VLOOKUP($B$2,'Sector Impact'!$K$4:$AA$16,A7+1,FALSE) -> Very High | D7: Yes | E7: Medium | F7: Yes | H7: HIgh | J7: Costco is committed to improving water use efficiency and reducing operational water waste. | K7: Water Consumption/$M Sales | L7: =L13/L$11 -> 73.92 | M7: =M13/M$11 -> 0 | N7: =N13/N$11 -> 0 | O7: =O13/O$11 -> 0 | P7: =P13/P$11 -> 0 | Q7: =Q13/Q$11 -> 0.10446298
A8: 3 | B8: Total Energy Consumption | C8: =VLOOKUP($B$2,'Sector Impact'!$K$4:$AA$16,A8+1,FALSE) -> High | D8: Yes | E8: Medium High | F8: Yes | H8: High | K8: Energy Consumption/$M Sales | L8: =L14/L$11 -> 0 | M8: =M14/M$11 -> 0 | N8: =N14/N$11 -> 0 | O8: =O14/O$11 -> 79.108804 | P8: =P14/P$11 -> 0 | Q8: =Q14/Q$11 -> 184.68824
A9: 4 | B9: Waste Management | C9: =VLOOKUP($B$2,'Sector Impact'!$K$4:$AA$16,A9+1,FALSE) -> High | D9: Yes | E9: Medium | F9: Yes | H9: Medium | I9: "We have a goal to divert 80% of what might otherwise end up in a landfill, by reducing waste through donations, recycling and composting." | J9: Costco’s goal is to continually decrease the amount of waste going to landfills through reducing food waste at source, feeding hungry people and animals, supporting industrial programs (i.e., biofuel), composting and other recycling and donation programs. | K9: Waste Production/$M Sales | L9: =L15/L$11 -> 0 | M9: =M15/M$11 -> 0 | N9: =N15/N$11 -> 0 | O9: =O15/O$11 -> 0.018730861 | P9: =P15/P$11 -> 0.0018080741 | Q9: =Q15/Q$11 -> 0
A10: 5 | B10: Land Degradation/Deforestation/Biodiversity loss/Animal sufering/… | C10: =VLOOKUP($B$2,'Sector Impact'!$K$4:$AA$16,A10+1,FALSE) -> High | D10: No | K10: Inputs
B11: Social | K11: Net Sales ($M) | L11: 226954 | M11: 611289 | N11: 513983 | O11: 148258 | P11: 133291 | Q11: 109120
A12: 6 | B12: Employee Turnover % | C12: =VLOOKUP($B$2,'Sector Impact'!$K$4:$AA$16,A12+1,FALSE) -> Medium | D12: Yes | E12: "Best in class" | F12: Yes | H12: Over 60% of U.S. employees have five or more years with Costco, and over one-third have more than 10 years | J12: With respect to the compensation of their employees, the philosophy is not to seek to minimize their wages and benefits. Rather, Cosco believes that achieving their longer-term objectives of reducing employee turnover and enhancing employee satisfaction requires maintaining compensation levels that are better than the industry average for much of our workforce | K12: CO2 Emissions Total (Tonnes) | L12: 144.4 | M12: 139.9 | N12: 71.27 | O12: 5251 | P12: 1577 | Q12: 1687
A13: 7 | B13: Salaries & Compensation | C13: =VLOOKUP($B$2,'Sector Impact'!$K$4:$AA$16,A13+1,FALSE) -> High | D13: Yes | E13: Medium High | J13: The employees are the foundation of Costco’s business, the heart of the Company’s culture, and the driver for their success. In the spirit of acknowledging and rewarding the excellence of employees, in fiscal 2022, they instituted several wage increases and provided additional benefits to the majority of their employees. | K13: Water Consumption Total (Cubic Meters) | L13: =73.92*'Fin. Data'!B5 -> 16776440 | Q13: 11399
A14: 8 | B14: Reputation | C14: =VLOOKUP($B$2,'Sector Impact'!$K$4:$AA$16,A14+1,FALSE) -> High | D14: No | E14: Medium High | K14: Energy Consumption Total (Gigajoules) | O14: 11728513 | Q14: 20153181
A15: 9 | B15: Discrimination Events | C15: =VLOOKUP($B$2,'Sector Impact'!$K$4:$AA$16,A15+1,FALSE) -> Low | F15: Yes | K15: Waste Production Total (Tonnes) | O15: 2777 | P15: 241
A16: 10 | B16: Work Safety | C16: High | K16: ESG Scores
A17: 11 | B17: Damage to consumer health | C17: =VLOOKUP($B$2,'Sector Impact'!$K$4:$AA$16,A17+1,FALSE) -> Medium | K17: Refinitiv | L17: 72 | M17: 83 | N17: 81 | O17: 85 | P17: 90 | Q17: 85
A18: 12 | B18: PXP? | C18: =VLOOKUP($B$2,'Sector Impact'!$K$4:$AA$16,A18+1,FALSE) -> Low | K18: Sustainalytics | L18: 23.6 | M18: 16.3 | N18: 30.5 | O18: 21.3 | P18: 16.3 | Q18: 14.4
A19: 13 | B19: Supply chain | C19: =VLOOKUP($B$2,'Sector Impact'!$K$4:$AA$16,A19+1,FALSE) -> High | K19: ISS | L19: C- | M19: C- | N19: C- | O19: C | P19: C | Q19: C+
A20: 14 | B20: Community involvement | C20: =VLOOKUP($B$2,'Sector Impact'!$K$4:$AA$16,A20+1,FALSE) -> Low | K20: CDP | L20: D | M20: C | O20: B- | P20: B | Q20: A-
A21: 15 | B21: Public Sector | C21: =VLOOKUP($B$2,'Sector Impact'!$K$4:$AA$16,A21+1,FALSE) -> Very High
A22: 16 | B22: Litigation | C22: =VLOOKUP($B$2,'Sector Impact'!$K$4:$AA$16,A22+1,FALSE) -> Low | D22: Yes
B23: Corporate Governance | K23: PARAMETERS
A24: 17 | B24: Diversity (Gender, Age, Industry, Region) | E24: "Villain" | F24: Yes | K24: IMPACT | L24: RANKING | M24: MITIGATION PLAN
A25: 18 | B25: % Independence | E25: Medium | J25: In 2022, they appointed a new Chief Diversity and Inclusion Officer. Embracing differences is important to the growth of their Company. It leads to more opportunities, innovation, and employee satisfaction and connects us to the communities where they do business. | K25: Low | L25: "Best in class" | M25: Evidence / plan?
A26: 19 | B26: average time as independent directors | E26: "Villain" | K26: Medium | L26: Medium High
A27: 20 | B27: Recent departures of directors / C-level executives? | E27: Medium | K27: High | L27: Medium
A28: 21 | B28: CEO/Chairman duality | E28: "Villain" | K28: Very high | L28: "Villain"
A29: 22 | B29: Transparency (ESG, segments, acquisitions, other)
A30: 23 | B30: Time taken to report after the end of the quarter / year
A31: 24 | B31: Additional participation of the CEO in other boards or excessive participation of Ch.
A32: 25 | B32: Audit / Consulting
A33: 26 | B33: ESG-compensation related
A34: 27 | B34: Management compensation schemes

Sheet DCF
A1: VALUATION MODEL
G3: Short Term | K3: Long Term
A4: Section | B4: Line # | C4: ITEM | D4: 2020 (Real) | E4: 2021 (Real) | F4: 2022 (Real) | G4: 2023 | H4: =G4+1 -> 2024 | I4: =H4+1 -> 2025 | J4: =I4+1 -> 2026 | K4: =J4+1 -> 2027 | L4: =K4+1 -> 2028 | M4: =L4+1 -> 2029 | N4: =M4+1 -> 2030 | O4: =N4+1 -> 2031 | ... AF4: =AE4+1 -> 2048
A5: INCOME STATEMENT | B5: 1 | C5: Growth | D5: ='Fin. Data'!D6 -> 0.09206106 | E5: =+E6/D6-1 -> 0.174909 | F5: =+F6/E6-1 -> 0.15834818 | G5: =+G6/F6-1 -> 0.062 | H5: =+H6/G6-1 -> 0.05 | I5: =+I6/H6-1 -> 0.070178785 | J5: =+J6/I6-1 -> 0.050089392 | K5: =+K6/J6-1 -> 0.03 | L5: =+L6/K6-1 -> 0.063846173 | ... AF5: =+AF6/AE6-1 -> 0.031846173
B6: 2 | C6: Revenues/Sales | D6: ='Fin. Data'!D5 -> 166761 | E6: ='Fin. Data'!C5 -> 195929 | F6: ='Fin. Data'!B5 -> 226954 | G6: ='Assumptions '!I23 -> 241025.15 | H6: ='Assumptions '!J23 -> 253076.41 | I6: ='Assumptions '!K23 -> 270837 | J6: ='Assumptions '!L23 -> 284403.06 | K6: ='Assumptions '!M23 -> 292935.15 | L6: ='Assumptions '!N23 -> 311637.94 | M6: ='Assumptions '!O23 -> 328897.89 | N6: ='Assumptions '!P23 -> 345026.54 | ... AF6: ='Assumptions '!AH23 -> 705773.25
B7: 3 | C7: EBIT/Operating Margin | D7: =D8/D6 -> 0.032591553 | E7: =E8/E6 -> 0.034236892 | F7: =F8/F6 -> 0.034337355 | G7: ='Assumptions '!I36 -> 0.02634165 | H7: ='Assumptions '!J36 -> 0.027126195 | I7: ='Assumptions '!K36 -> 0.027570088 | J7: ='Assumptions '!L36 -> 0.027291366 | K7: ='Assumptions '!M36 -> 0.027012644 | L7: ='Assumptions '!N36 -> 0.030475821 | M7: ='Assumptions '!O36 -> 0.026436856 | N7: ='Assumptions '!P36 -> 0.023407632 | ... AF7: ='Assumptions '!AH36 -> 0.016783516
B8: 4 | C8: EBIT | D8: ='Fin. Data'!D11 -> 5435 | E8: ='Fin. Data'!C11 -> 6708 | F8: ='Fin. Data'!B11 -> 7793 | G8: =G6*G7 -> 6349 | H8: =H6*H7 -> 6865 | I8: =I6*I7 -> 7467 | J8: =J6*J7 -> 7761.7481 | K8: =K6*K7 -> 7912.9531 | L8: =L6*L7 -> 9497.4223 | M8: =M6*M7 -> 8695.0263 | N8: =N6*N7 -> 8076.2544 | ... AF8: =AF6*AF7 -> 11845.357
B9: 5a | C9: (Dep) | D9: -1900 | E9: -1781 | F9: -1645 | G9: =-'Assumptions '!I57 -> -2277.5339 | H9: =-'Assumptions '!J57 -> -2391.4106 | I9: =-'Assumptions '!K57 -> -2559.2369 | J9: =-'Assumptions '!L57 -> -2687.4275 | K9: =-'Assumptions '!M57 -> -2768.0503 | L9: =-'Assumptions '!N57 -> -2793.2234 | M9: =-'Assumptions '!O57 -> -2818.6254 | N9: =-'Assumptions '!P57 -> -2844.2584 | ... AF9: =-'Assumptions '!AH57 -> -3310.3729
B10: 5b | C10: Amort | D10: 0 | E10: 0 | F10: 0 | G10: =F38*(-$D$54) -> -9.3832166 | H10: =G38*(-$D$54) -> -9.471882 | I10: =H38*(-$D$54) -> -9.5613853 | J10: =I38*(-$D$54) -> -9.6517342 | K10: =J38*(-$D$54) -> -9.742937 | L10: =K38*(-$D$54) -> -9.8350015 | M10: =L38*(-$D$54) -> -9.927936 | N10: =M38*(-$D$54) -> -10.021749 | ... AF10: =AE38*(-$D$54) -> -11.870396
B11: 5c | C11: (Stock based compensation) | D11: =-D20 -> -619 | E11: =-E20 -> -665 | F11: =-F20 -> -724 | G11: =-'Assumptions '!I82 -> -869.37632 | H11: =-'Assumptions '!J82 -> -912.84514 | I11: =-'Assumptions '!K82 -> -976.9075 | J11: =-'Assumptions '!L82 -> -1025.8402 | K11: =-'Assumptions '!M82 -> -1056.6154 | L11: =-'Assumptions '!N82 -> -1060.4266 | M11: =-'Assumptions '!O82 -> -1064.2516 | N11: =-'Assumptions '!P82 -> -1068.0903 | ... AF11: =-'Assumptions '!AH82 -> -1139.6046
B12: 6 | C12: EBITDA | D12: =D8-D9-D10 -> 7335 | E12: =E8-E9-E10 -> 8489 | F12: =F8-F9-F10 -> 9438 | G12: =G8-G9-G10 -> 8635.9171 | H12: =H8-H9-H10 -> 9265.8825 | I12: =I8-I9-I10 -> 10035.798 | J12: =J8-J9-J10 -> 10458.827 | K12: =K8-K9-K10 -> 10690.746 | ... AF12: =AF8-AF9-AF10 -> 15167.6
B13: 7 | C13: (Net financing cost) | D13: =-'Fin. Data'!D14 -> -71 | E13: =-'Fin. Data'!C14 -> -130 | F13: =-'Fin. Data'!B14 -> -97 | G13: =F43*$D$58-F44*$D$57 -> 72.10592 | H13: =G43*$D$58-G44*$D$57 -> 8.7244583 | I13: =H43*$D$58-H44*$D$57 -> 137.50118 | J13: =I43*$D$58-I44*$D$57 -> 287.81482 | K13: =J43*$E$58-J44*$E$57 -> 412.14337 | L13: =K43*$E$58-K44*$E$57 -> 566.88107 | M13: =L43*$E$58-L44*$E$57 -> 755.75103 | N13: =M43*$E$58-M44*$E$57 -> 907.21603 | O13: =N43*$E$58-N44*$E$57 -> 1050.756 | P13: =O43*$E$58-O44*$E$57 -> 1189.3487 | Q13: =P43*$E$58-P44*$E$57 -> 1278.9986 | R13: =Q43*$E$58-Q44*$E$57 -> 1448.2725 | ... AF13: =AE43*$E$58-AE44*$E$57 -> 12380.629
B14: 8 | C14: Other income/(cost) | D14: =-160+89-71+7-4 -> -139 | E14: =-171+41-130+56+46 -> -158 | F14: =-158+61-97+106+38 -> -50 | G14: =AVERAGE(D14:F14)*(1+G5) -> -122.838 | H14: =AVERAGE(E14:G14)*(1+H5) -> -115.7933 | I14: =AVERAGE(F14:H14)*(1+I5) -> -102.96236 | J14: =AVERAGE(G14:I14)*(1+J5) -> -119.56796 | K14: =AVERAGE(H14:J14)*(1+K5) -> -116.15778 | L14: =AVERAGE(I14:K14)*(1+L5) -> -120.10401 | M14: =AVERAGE(J14:L14)*(1+M5) -> -125.17908 | N14: =AVERAGE(K14:M14)*(1+N5) -> -126.38846 | ... AF14: =AVERAGE(AC14:AE14)*(1+AF5) -> -180.80622
B15: 9 | C15: Earnings before taxes | D15: =D8+D13+D14 -> 5225 | E15: =E8+E13+E14 -> 6420 | F15: =F8+F13+F14 -> 7646 | G15: =G8+G13+G14 -> 6298.2679 | H15: =H8+H13+H14 -> 6757.9312 | I15: =I8+I13+I14 -> 7501.5388 | J15: =J8+J13+J14 -> 7929.995 | K15: =K8+K13+K14 -> 8208.9387 | ... AF15: =AF8+AF13+AF14 -> 24045.179
B16: 10 | C16: (Income tax) | D16: =-'Fin. Data'!D21 -> -1308 | E16: =-'Fin. Data'!C21 -> -1601 | F16: =-'Fin. Data'!B21 -> -1925 | G16: ='Assumptions '!I47 -> 1561.073 | H16: ='Assumptions '!J47 -> 1687.9455 | I16: ='Assumptions '!K47 -> 1835.9635 | J16: ='Assumptions '!L47 -> 1886.0694 | K16: ='Assumptions '!M47 -> 1937.0172 | L16: ='Assumptions '!N47 -> 2343.7908 | M16: ='Assumptions '!O47 -> 2835.9868 | N16: ='Assumptions '!P47 -> 3431.544 | ... AF16: ='Assumptions '!AH47 -> 106078.22
B17: 11 | C17: Net income | D17: ='Fin. Data'!D23 -> 4002 | E17: ='Fin. Data'!C23 -> 5007 | F17: ='Fin. Data'!B23 -> 5844 | G17: =G16+G15 -> 7859.3409 | H17: =H16+H15 -> 8445.8767 | I17: =I16+I15 -> 9337.5023 | J17: =J16+J15 -> 9816.0644 | K17: =K16+K15 -> 10145.956 | L17: =L16+L15 -> 12287.99 | M17: =M16+M15 -> 12161.585 | N17: =N16+N15 -> 12288.626 | ... AF17: =AF16+AF15 -> 130123.4
A19: CASH FLOW STATEMENT | B19: 12 | C19: Operating cash flows before WK | D19: 4059 | E19: 5079 | F19: 5915 | G19: =G17-G10-G9-G11 -> 11015.634 | H19: =H17-H10-H9-H11 -> 11759.604 | I19: =I17-I10-I9-I11 -> 12883.208 | J19: =J17-J10-J9-J11 -> 13538.984 | K19: =K17-K10-K9-K11 -> 13980.365 | L19: =L17-L10-L9-L11 -> 16151.475 | M19: =M17-M10-M9-M11 -> 16054.39 | N19: =N17-N10-N9-N11 -> 16210.996 | ... AF19: =AF17-AF10-AF9-AF11 -> 134585.25
B20: 13 | C20: (Stock-based compensation) | D20: 619 | E20: 665 | F20: 724 | G20: =G11 -> -869.37632 | H20: =H11 -> -912.84514 | I20: =I11 -> -976.9075 | J20: =J11 -> -1025.8402 | K20: =K11 -> -1056.6154 | L20: =L11 -> -1060.4266 | M20: =M11 -> -1064.2516 | N20: =N11 -> -1068.0903 | ... AF20: =AF11 -> -1139.6046
B21: 14 | C21: (Working Capital Flows) | D21: ='Assumptions '!F72 -> -2447 | E21: ='Assumptions '!G72 -> -1378 | F21: ='Assumptions '!H72 -> 1034 | G21: ='Assumptions '!I72 -> -1360.0919 | H21: ='Assumptions '!J72 -> -1428.0965 | I21: ='Assumptions '!K72 -> -1528.3185 | J21: ='Assumptions '!L72 -> -1604.8711 | K21: ='Assumptions '!M72 -> -1653.0172 | ... AF21: ='Assumptions '!AH72 -> -1467.8001
B22: 15 | C22: -Total Operating Cash Flow | D22: =D19-D20-D21 -> 5887 | E22: =E19-E20-E21 -> 5792 | F22: =F19-F20-F21 -> 4157 | G22: =G19-G20-G21 -> 13245.103 | H22: =H19-H20-H21 -> 14100.546 | I22: =I19-I20-I21 -> 15388.434 | J22: =J19-J20-J21 -> 16169.695 | K22: =K19-K20-K21 -> 16689.997 | ... AF22: =AF19-AF20-AF21 -> 137192.66
B23: 16 | C23: (CAPEX) | D23: ='Fin. Data'!D32 -> -2810 | E23: ='Fin. Data'!C32 -> -3588 | F23: ='Fin. Data'!B32 -> -3891 | G23: =G6*$D$62 -> -4478.807 | H23: =H6*$D$62 -> -4702.7474 | I23: =I6*$D$62 -> -5032.7805 | J23: =J6*$D$62 -> -5284.8694 | K23: =K6*$E$62 -> -5303.466 | L23: =L6*$E$62 -> -5642.072 | M23: =M6*$E$62 -> -5954.556 | N23: =N6*$E$62 -> -6246.5584 | O23: =O6*$E$62 -> -6523.1488 | P23: =P6*$E$62 -> -6718.8433 | Q23: =Q6*$E$62 -> -6932.8127 | R23: =R6*$E$62 -> -7150.3965 | ... AF23: =AF6*$E$62 -> -12777.724 | AG23: =SUM(D23:AF23) -> -218954.04
B24: 17 | C24: Adq | D24: =Inputs!D66 -> -1019 | E24: ='Fin. Data'!C33 -> 101 | F24: ='Fin. Data'!B33 -> 3 | G24: =G6*$D$63 -> -208.76401 | H24: =H6*$D$63 -> -219.20221 | I24: =I6*$D$63 -> -234.58555 | J24: =J6*$D$63 -> -246.3358 | K24: =K6*$E$63 -> -315.23038 | L24: =L6*$E$63 -> -335.35663 | M24: =M6*$E$63 -> -353.93023 | N24: =N6*$E$63 -> -371.28643 | O24: =O6*$E$63 -> -387.72657 | P24: =P6*$E$63 -> -399.35837 | Q24: =Q6*$E$63 -> -412.0764 | R24: =R6*$E$63 -> -425.00927 | ... AF24: =AF6*$E$63 -> -759.48948 | AH24: =AG9-AG23 -> 218954.04
B25: 18 | C25: (Other investing flows) | D25: =Inputs!D67 -> -62 | E25: =Inputs!C67 -> -48 | F25: =Inputs!B67 -> -27 | G25: =(1+G5)*AVERAGE(D25:F25) -> -48.498 | H25: =(1+H5)*AVERAGE(E25:G25) -> -43.2243 | I25: =(1+I5)*AVERAGE(F25:H25) -> -42.351362 | J25: =(1+J5)*AVERAGE(G25:I25) -> -46.929777 | K25: =(1+K5)*AVERAGE(H25:J25) -> -45.493534 | L25: =(1+L5)*AVERAGE(I25:K25) -> -47.793173 | M25: =(1+M5)*AVERAGE(J25:L25) -> -49.327441 | N25: =(1+N5)*AVERAGE(K25:M25) -> -49.869243 | ... AF25: =(1+AF5)*AVERAGE(AC25:AE25) -> -71.408644
B26: 19 | C26: -Total Investing Flows | D26: =D23+D24+D25 -> -3891 | E26: =E23+E24+E25 -> -3535 | F26: =F23+F24+F25 -> -3915 | G26: =G23+G24+G25 -> -4736.0691 | H26: =H23+H24+H25 -> -4965.1739 | I26: =I23+I24+I25 -> -5309.7174 | J26: =J23+J24+J25 -> -5578.135 | K26: =K23+K24+K25 -> -5664.1899 | ... AF26: =AF23+AF24+AF25 -> -13608.622
B27: 20 | C27: (Flows related to leases) | D27: =Inputs!D71+Inputs!D72 -> 0 | E27: =Inputs!C71+Inputs!C72 -> 0 | F27: =Inputs!B71+Inputs!B72 -> 0 | G27: 0 | H27: 0 | I27: 0 | J27: 0 | K27: 0 | L27: 0 | M27: 0 | N27: 0 | O27: 0 | P27: 0 | Q27: 0 | R27: 0 | S27: 0 | T27: 0 | U27: 0 | V27: 0 | W27: 0 | X27: 0 | Y27: 0 | Z27: 0 | AA27: 0 | AB27: 0 | AC27: 0 | AD27: 0 | AE27: 0 | AF27: 0
B28: 21 | C28: Flows related to debt | D28: =+SUM(Inputs!D69:D70) -> 792 | E28: =+SUM(Inputs!C69:C70) -> -94 | F28: =+SUM(Inputs!B69:B70) -> -800 | G28: =G44-F44 -> -7022.7438 | H28: =H44-G44 -> 283.27239 | I28: =I44-H44 -> 346.20299 | J28: =J44-I44 -> 190.22072 | K28: =K44-J44 -> 104.2855 | L28: =L44-K44 -> 723.83865 | M28: =M44-L44 -> -349.34401 | N28: =N44-M44 -> -266.67069 | ... AF28: =AF44-AE44 -> 1475.5583
B29: 22 | C29: (Respurchases)/Issuance of stock | D29: ='Fin. Data'!D28 -> -526 | E29: ='Fin. Data'!C28 -> -808 | F29: ='Fin. Data'!B28 -> -802 | G29: =-G17*$D$65 -> -1375.1758 | H29: =-H17*$D$65 -> -1477.8039 | I29: =-I17*$D$65 -> -1633.8147 | J29: =-J17*$D$65 -> -1717.5504 | K29: =-K17*$E$65 -> -1717.5204 | L29: =-L17*$E$65 -> -2080.1267 | M29: =-M17*$E$65 -> -2058.7287 | N29: =-N17*$E$65 -> -2080.2344 | O29: =-O17*$E$65 -> -2147.9812 | P29: =-P17*$E$65 -> -1929.2997 | Q29: =-Q17*$E$65 -> -2419.3516 | R29: =-R17*$E$65 -> -2894.2702 | ... AF29: =-AF17*$E$65 -> -22027.457
B30: 23 | C30: (Dividends) | D30: ='Fin. Data'!D27 -> -1479 | E30: ='Fin. Data'!C27 -> -1318 | F30: ='Fin. Data'!B27 -> -1498 | G30: =-$D$64*G17 -> -2548.1821 | H30: =-$D$64*H17 -> -2738.3507 | I30: =-$D$64*I17 -> -3027.4366 | J30: =-$D$64*J17 -> -3182.5976 | K30: =-$E$64*K17 -> -3425.5888 | L30: =-$E$64*L17 -> -4148.8059 | M30: =-$E$64*M17 -> -4106.1276 | N30: =-$E$64*N17 -> -4149.0206 | O30: =-$E$64*O17 -> -4284.1414 | P30: =-$E$64*P17 -> -3847.9819 | Q30: =-$E$64*Q17 -> -4825.3888 | R30: =-$E$64*R17 -> -5772.6124 | ... AF30: =-$E$64*AF17 -> -43933.69
B31: 24 | C31: Other financing flows | D31: =Inputs!D75 -> -5275 | E31: =Inputs!C75 -> -2063 | F31: =Inputs!B75 -> -790 | G31: =(1+G5)*AVERAGE(D31:F31) -> -2877.312 | H31: =(1+H5)*AVERAGE(E31:G31) -> -2005.6092 | I31: =(1+I5)*AVERAGE(F31:H31) -> -2023.68 | J31: =(1+J5)*AVERAGE(G31:I31) -> -2417.5162 | K31: =(1+K5)*AVERAGE(H31:J31) -> -2213.4032 | L31: =(1+L5)*AVERAGE(I31:K31) -> -2359.8234 | M31: =(1+M5)*AVERAGE(J31:L31) -> -2459.3075 | N31: =(1+N5)*AVERAGE(K31:M31) -> -2459.1329 | ... AF31: =(1+AF5)*AVERAGE(AC31:AE31) -> -3535.0307
B32: 25 | C32: -Total Financing flows | D32: =D27+D28+D29+D30+D31 -> -6488 | E32: =E27+E28+E29+E30+E31 -> -4283 | F32: =F27+F28+F29+F30+F31 -> -3890 | G32: =G27+G28+G29+G30+G31 -> -13823.414 | H32: =H27+H28+H29+H30+H31 -> -5938.4915 | I32: =I27+I28+I29+I30+I31 -> -6338.7283 | J32: =J27+J28+J29+J30+J31 -> -7127.4435 | K32: =K27+K28+K29+K30+K31 -> -7252.2269 | ... AF32: =AF27+AF28+AF29+AF30+AF31 -> -68020.619
A34: SUMMARY | B34: 26 | C34: Cash before shareholder returns | D34: =D22+D26+D27+D28+D31 -> -2487 | E34: =E22+E26+E27+E28+E31 -> 100 | F34: =F22+F26+F27+F28+F31 -> -1348 | G34: =G22+G26+G27+G28+G31 -> -1391.0223 | H34: =H22+H26+H27+H28+H31 -> 7413.0352 | I34: =I22+I26+I27+I28+I31 -> 8401.2397 | J34: =J22+J26+J27+J28+J31 -> 8364.2647 | K34: =K22+K26+K27+K28+K31 -> 8916.6896 | ... AF34: =AF22+AF26+AF27+AF28+AF31 -> 121524.56
B35: 27 | C35: Returns to shareholders | D35: =-1*(D29+D30) -> 2005 | E35: =-1*(E29+E30) -> 2126 | F35: =-1*(F29+F30) -> 2300 | G35: =-1*(G29+G30) -> 3923.3579 | H35: =-1*(H29+H30) -> 4216.1547 | I35: =-1*(I29+I30) -> 4661.2513 | J35: =-1*(J29+J30) -> 4900.148 | K35: =-1*(K29+K30) -> 5143.1092 | ... AF35: =-1*(AF29+AF30) -> 65961.146
B36: 28 | C36: Excess cash acumulation | D36: =D34-D35 -> -4492 | E36: =E34-E35 -> -2026 | F36: =F34-F35 -> -3648 | G36: =G34-G35 -> -5314.3802 | H36: =H34-H35 -> 3196.8805 | I36: =I34-I35 -> 3739.9884 | J36: =J34-J35 -> 3464.1167 | K36: =K34-K35 -> 3773.5804 | ... AF36: =AF34-AF35 -> 55563.416
A38: BALANCE SHEET | B38: 29 | C38: Intangible assets | D38: 988 | E38: 996 | F38: 993 | G38: =+F38+(-G10) -> 1002.3832 | H38: =+G38+(-H10) -> 1011.8551 | I38: =+H38+(-I10) -> 1021.4165 | J38: =+I38+(-J10) -> 1031.0682 | K38: =+J38+(-K10) -> 1040.8112 | L38: =+K38+(-L10) -> 1050.6462 | M38: =+L38+(-M10) -> 1060.5741 | N38: =+M38+(-N10) -> 1070.5958 | ... AF38: =+AE38+(-AF10) -> 1268.0817 | AG38: =SUM(G38:AF38) -> 29386.221
B39: 30 | C39: Accumulated amorization | D39: -12896 | E39: -14166 | F39: -15286 | G39: =F39-G10 -> -15276.617 | H39: =G39-H10 -> -15267.145 | I39: =H39-I10 -> -15257.584 | J39: =I39-J10 -> -15247.932 | K39: =J39-K10 -> -15238.189 | L39: =K39-L10 -> -15228.354 | M39: =L39-M10 -> -15218.426 | N39: =M39-N10 -> -15208.404 | ... AF39: =AE39-AF10 -> -15010.918 | AG39: =SUM(G39:AF39) -> -393867.78
B40: 31 | C40: PPE+Right of use Assets | D40: =Inputs!D33 -> 38083 | E40: =Inputs!C33 -> 41258 | F40: =Inputs!B33 -> 44326 | G40: =F40+(-G23) -> 48804.807 | H40: =G40+(-H23) -> 53507.554 | I40: =H40+(-I23) -> 58540.335 | J40: =I40+(-J23) -> 63825.204 | K40: =J40+(-K23) -> 69128.67 | L40: =K40+(-L23) -> 74770.742 | M40: =L40+(-M23) -> 80725.298 | N40: =M40+(-N23) -> 86971.857 | ... AF40: =AE40+(-AF23) -> 252991.04 | AG40: =SUM(G40:AF40) -> 3492508.7
B41: 32 | C41: Accumulated depreciation | D41: -1296000 | E41: -14166000 | F41: -15286000 | G41: =F41-G9 -> -15283722 | H41: =G41-H9 -> -15281331 | I41: =H41-I9 -> -15278772 | J41: =I41-J9 -> -15276084 | K41: =J41-K9 -> -15273316 | L41: =K41-L9 -> -15270523 | M41: =L41-M9 -> -15267704 | N41: =M41-N9 -> -15264860 | ... AF41: =AE41-AF9 -> -15209243 | AG41: =SUM(G41:AF41) -> -3.9644799e+08
A43: CASH & DEBT & DISCOUNTING | B43: 33 | C43: Ending cash balance | D43: ='Fin. Data'!D39 -> 13305 | E43: =E36+D43 -> 11279 | F43: =F36+E43 -> 7631 | G43: =G36+F43 -> 2316.6198 | H43: =H36+G43 -> 5513.5004 | I43: =I36+H43 -> 9253.4887 | J43: =J36+I43 -> 12717.605 | K43: =K36+J43 -> 16491.186 | L43: =L36+K43 -> 21456.638 | ... AF43: =AF36+AE43 -> 355681.82
B44: 34 | C44: Total Debt | D44: ='Fin. Data'!D58 -> 11086 | E44: ='Fin. Data'!C58 -> 11407 | F44: ='Fin. Data'!B58 -> 10906 | G44: =G12*'Assumptions '!$H$130 -> 3883.2562 | H44: =H12*'Assumptions '!$H$130 -> 4166.5286 | I44: =I12*'Assumptions '!$H$130 -> 4512.7316 | J44: =J12*'Assumptions '!$H$130 -> 4702.9523 | K44: =K12*'Assumptions '!$H$130 -> 4807.2378 | L44: =L12*'Assumptions '!$H$130 -> 5531.0765 | M44: =M12*'Assumptions '!$H$130 -> 5181.7325 | N44: =N12*'Assumptions '!$H$130 -> 4915.0618 | ... AF44: =AF12*'Assumptions '!$H$130 -> 6820.3153
B45: 35 | C45: Discount factor | F45: =1/((1+$F$50)^G50) -> 1 | G45: =1/((1+$F$50)^G49) -> 0.90954038 | H45: =1/((1+$F$50)^H49) -> 0.8272637 | I45: =1/((1+$F$50)^I49) -> 0.75242973 | J45: =1/((1+$F$50)^J49) -> 0.68436522 | K45: =1/((1+$F$50)^K49) -> 0.6224578 | L45: =1/((1+$F$50)^L49) -> 0.5661505 | M45: =1/((1+$F$50)^M49) -> 0.51493674 | N45: =1/((1+$F$50)^N49) -> 0.46835576 | ... AF45: =1/((1+$F$50)^AF49) -> 0.084990729
B46: 36 | C46: DF + 0.1% | E46: +0.1% | F46: =1/((1+$F$50+0.001)^G50) -> 1 | G46: =1/((1+$F$50+0.001)^G49) -> 0.90871386 | H46: =1/((1+$F$50+0.001)^H49) -> 0.82576089 | I46: =1/((1+$F$50+0.001)^I49) -> 0.75038037 | J46: =1/((1+$F$50+0.001)^J49) -> 0.68188104 | K46: =1/((1+$F$50+0.001)^K49) -> 0.61963476 | L46: =1/((1+$F$50+0.001)^L49) -> 0.56307069 | M46: =1/((1+$F$50+0.001)^M49) -> 0.51167015 | N46: =1/((1+$F$50+0.001)^N49) -> 0.46496176 | ... AF46: =1/((1+$F$50+0.001)^AF49) -> 0.083005335
B47: 37 | C47: DF+0.5% | E47: +0.5% | F47: =1/((1+$F$50+0.005)^G50) -> 1 | G47: =1/((1+$F$50+0.005)^G49) -> 0.90542278 | H47: =1/((1+$F$50+0.005)^H49) -> 0.81979042 | I47: =1/((1+$F$50+0.005)^I49) -> 0.74225692 | J47: =1/((1+$F$50+0.005)^J49) -> 0.67205633 | K47: =1/((1+$F$50+0.005)^K49) -> 0.60849511 | L47: =1/((1+$F$50+0.005)^L49) -> 0.55094534 | M47: =1/((1+$F$50+0.005)^M49) -> 0.49883846 | N47: =1/((1+$F$50+0.005)^N49) -> 0.45165971 | ... AF47: =1/((1+$F$50+0.005)^AF49) -> 0.075533025
A49: Discount Rate | C49: Risk free rate | D49: Equity premium | E49: Firm premium | F49: Total | G49: 1 | H49: 2 | I49: 3 | J49: 4 | K49: 5 | L49: 6 | M49: 7 | N49: 8 | O49: 9 | P49: 10 | Q49: 11 | R49: 12 | S49: 13 | T49: 14 | U49: 15 | V49: 16 | W49: 17 | X49: 18 | Y49: 19 | Z49: 20 | AA49: 21 | AB49: 22 | AC49: 23 | AD49: 24 | AE49: 25 | AF49: 26
C50: 0.04073 | D50: ='Assumptions '!C119 -> 0.048726414 | E50: 0.01 | F50: =E50+D50+C50 -> 0.099456414 | G50: 0
A52: Modelling factors | D52: Short Term | E52: Long Term | F52: Reference (line)
C53: Depreciation factor | D53: ='Assumptions '!H138 -> 0.0094493621 | E53: ='Assumptions '!I138 -> 0.008435647 | F53: % sales
C54: Amortization factor | D54: ='Assumptions '!H139 -> 0.0094493621 | E54: ='Assumptions '!I139 -> 0.0093092295 | F54: % sales
C55: Stock-based comp | D55: ='Assumptions '!H140 -> 0.0036069942 | E55: =D55 -> 0.0036069942 | F55: % revenue
C56: Tax Rate | D56: ='Assumptions '!H141 -> 0.24587699 | E56: =D56 -> 0.24587699 | F56: % (line 9)
C57: Interest Rate on debt | D57: ='Assumptions '!H142 -> 0.023 | E57: ='Assumptions '!I142 -> 0.025129062 | F57: % debt (l29)
C58: Interest Rate on cash | D58: 0.04232 | E58: 0.0417 | F58: % of cash (l28)
C59: PPE+ROA | D59: =D62 -> -0.018582323 | E59: =E62 -> -0.018104573 | F59: Growing with capex
C60: Working capital flows | D60: ='Assumptions '!H145 -> -0.0056429459 | E60: ='Assumptions '!I145 -> -0.0054506897 | F60: % of change revenues (l2)
C61: Intangible Assets | D61: ='Assumptions '!H146 -> 0.0031461071 | E61: ='Assumptions '!I146 -> 0.0037753286 | F61: Growing with amortization
C62: Capex | D62: ='Assumptions '!H147 -> -0.018582323 | E62: ='Assumptions '!I147 -> -0.018104573 | F62: % revenue (l2)
C63: Acquisition factor | D63: ='Assumptions '!H148 -> -0.00086615031 | E63: ='Assumptions '!I148 -> -0.0010761098 | F63: % revenue (l2)
C64: Dividends | D64: ='Assumptions '!H149 -> 0.32422338 | E64: ='Assumptions '!I149 -> 0.33763096 | F64: % net income (11)
C65: Repurchases | D65: ='Assumptions '!H150 -> 0.17497342 | E65: ='Assumptions '!I150 -> 0.16928128 | F65: % net income (11)
C66: Leases | D66: ='Assumptions '!H151 -> 0.04212 | E66: ='Assumptions '!I151 -> 0.036204 | F66: % revenue (l2)
C67: Cash Costs for EBIT | D67: =AVERAGE(D12:F12)/AVERAGE(D6:F6) -> 0.0428428 | E67: =D67 -> 0.0428428 | F67: % revenue (l2)
A69: Valuation | D69: $ millions
C70: Value of flows | D70: =SUMPRODUCT(G35:AF35,G45:AF45)+((AF43-AF44)*AF45) -> 123459.56 | E70: =D70/D72 -> 0.446954
C71: Value of perpetuity | D71: =(AF34/(F50-AF5))*AF45 -> 152764.75 | E71: =D71/D72 -> 0.553046
C72: Total Value | D72: =D70+D71 -> 276224.3
C73: Actual share price | D73: =OP!C20 -> 842.9
C74: Total value vs Mkt Cap | D74: =D75/D73-1 -> -0.26081387
C75: Estimated NPV per share | D75: =D72*1000000/OP!C21 -> 623.05999
A77: Sensibility | C77: Sensitivity +0.1% | D77: =(SUMPRODUCT(G35:AF35,G45:AF45)+((AF43-AF44)*AF45)+(AF34/(F50+0.001-AF5))*AF45)*1000000/OP!C21 -> 618.0377 | E77: =D77/D75-1 -> -0.0080606918
C78: Sensitivity +0.5% | D78: =(SUMPRODUCT(G35:AF35,G45:AF45)+((AF43-AF44)*AF45)+(AF34/(F50+0.005-AF5))*AF45)*1000000/OP!C21 -> 599.33188 | E78: =D78/D75-1 -> -0.038083196
A80: Notes

Sheet Assumptions 
B2: Assumptions
B4: Future perspectives: | C4: Costco to increase its membership fee every 5y. The last time the company raised fees was in July 2017. Therefore, it is expected to raise it again in 2023, 2028, 2033, etc.
C5: Expeced growth opportunities on its international expansion
B8: Average Annual Net Sales Growth (past 5y) | C8: =AVERAGE(D24:H24) -> 0.12023756
B9: Forecast Annual Net Sales Growth (next 5y) | C9: 0.089
B11: Switches | E11: Scenarios
B12: Revenue | C12: 2 | E12: Conservative | G12: Base | I12: Optimistic
B13: EBIT | C13: 2 | E13: Revenue 2023 | F13: =1+($C$9-0.08) -> 1.009 | G13: Revenue 2023 | H13: =I23 -> 241025.15 | I13: Revenue 2023 | J13: =1+($C$9+0.08) -> 1.169
E14: Revenue 2027 | F14: =1+($C$9-0.08) -> 1.009 | G14: Revenue 2027 | H14: ='Inflation Projections'!E24+0.01 -> 0.03 | I14: Revenue 2027 | J14: =1+($C$9+0.08) -> 1.169
E15: EBIT 2023 | F15: 0.9 | G15: EBIT 2023 | H15: =I41 -> 0.02634165 | I15: EBIT 2023 | J15: 1.1
E16: EBIT 2027 | F16: 0.9 | G16: EBIT 2027 | H16: =AVERAGE(I41:K41) -> 0.027012644 | I16: EBIT 2027 | J16: 1.1
B19: I/S
C21: Last 5 Years | I21: Short Term Forecast
C22: 2017 | D22: 2018 | E22: 2019 | F22: 2020 | G22: 2021 | H22: 2022 | I22: 2023 | J22: =I22+1 -> 2024 | K22: =J22+1 -> 2025 | L22: =K22+1 -> 2026 | M22: =L22+1 -> 2027 | N22: =M22+1 -> 2028 | O22: =N22+1 -> 2029 | P22: =O22+1 -> 2030 | Q22: =P22+1 -> 2031 | ... AH22: =AG22+1 -> 2048
B23: Net Sales | C23: =Inputs!G6 -> 129025 | D23: =Inputs!F6 -> 141576 | E23: =Inputs!E6 -> 152703 | F23: =Inputs!D6 -> 166761 | G23: =Inputs!C6 -> 195929 | H23: =Inputs!B6 -> 226954 | I23: =H23*(1+I24) -> 241025.15 | J23: =I23*(1+J24) -> 253076.41 | K23: 270837 | L23: =K23*(1+L24) -> 284403.06 | M23: =L23*(1+M24) -> 292935.15 | N23: =M23*(1+N24) -> 311637.94 | O23: =N23*(1+O24) -> 328897.89 | P23: =O23*(1+P24) -> 345026.54 | Q23: =P23*(1+Q24) -> 360303.92 | R23: =Q23*(1+R24) -> 371113.04 | S23: =R23*(1+S24) -> 382931.57 | ... AH23: =AG23*(1+AH24) -> 705773.25
B24: % Growth | D24: =D23/C23-1 -> 0.097275722 | E24: =E23/D23-1 -> 0.078593829 | F24: =F23/E23-1 -> 0.09206106 | G24: =G23/F23-1 -> 0.174909 | H24: =H23/G23-1 -> 0.15834818 | I24: =I29 -> 0.062 | J24: =J27 -> 0.05 | K24: =K27 -> 0.070178785 | L24: =L27 -> 0.050089392 | M24: =M27 -> 0.03 | N24: =N29 -> 0.063846173 | O24: =O27 -> 0.05538463 | P24: =P27 -> 0.049038472 | Q24: =Q27 -> 0.044278854 | R24: =R27 -> 0.03 | S24: =S29 -> 0.031846173 | T24: =T27 -> 0.03138463 | U24: =U27 -> 0.031038472 | V24: =V27 -> 0.030778854 | W24: =W27 -> 0.03 | X24: =X29 -> 0.062 | Y24: =Y27 -> 0.054 | Z24: =Z27 -> 0.048 | AA24: =AA27 -> 0.0435 | AB24: =AB27 -> 0.03 | AC24: =AC29 -> 0.060153827 | AD24: =AD27 -> 0.05261537 | AE24: =AE27 -> 0.046961528 | AF24: =AF27 -> 0.042721146 | AG24: =AG27 -> 0.03 | AH24: =AH29 -> 0.031846173
B25: Actual 5y Average | H25: =AVERAGE(D24:H24) -> 0.12023756 | M25: =AVERAGE(I24:M24) -> 0.052453635 | R25: =AVERAGE(N24:R24) -> 0.048509626 | W25: =AVERAGE(S24:W24) -> 0.031009626 | AB25: =AVERAGE(X24:AB24) -> 0.0475 | AG25: =AVERAGE(AC24:AG24) -> 0.046490374
B26: Target 5y Average | M26: =C9 -> 0.089 | R26: =H9 -> 0 | W26: =M9 -> 0 | AB26: =R9 -> 0 | AG26: =W9 -> 0
B27: Annual Growth Rate | I27: =OFFSET(I27,$C$12,0) -> 0.062 | J27: =OFFSET(J27,$C$12,0) -> 0.05 | K27: =OFFSET(K27,$C$12,0) -> 0.070178785 | L27: =OFFSET(L27,$C$12,0) -> 0.050089392 | M27: =OFFSET(M27,$C$12,0) -> 0.03 | N27: =OFFSET(N27,$C$12,0) -> 0.063846173 | O27: =OFFSET(O27,$C$12,0) -> 0.05538463 | P27: =OFFSET(P27,$C$12,0) -> 0.049038472 | ... AH27: =OFFSET(AH27,$C$12,0) -> 0.031846173
B28: =E12 -> Conservative | I28: =I24 -> 0.062 | J28: =J29*($F$13) -> 0.05045 | K28: =K29*($F$13) -> 0.070810394 | L28: =L29*($F$13) -> 0.050540197 | M28: =M29*($F$13) -> 0.03027 | N28: =N24 -> 0.063846173 | O28: =O29*($F$13) -> 0.055883092 | P28: =P29*($F$13) -> 0.049479819 | Q28: =Q29*($F$13) -> 0.044677364 | R28: =R29*($F$13) -> 0.03027 | S28: =S24 -> 0.031846173 | T28: =T29*($F$13) -> 0.031667092 | U28: =U29*($F$13) -> 0.031317819 | V28: =V29*($F$13) -> 0.031055864 | W28: =W29*($F$13) -> 0.03027 | X28: =X24 -> 0.062 | Y28: =Y29*($F$13) -> 0.054486 | Z28: =Z29*($F$13) -> 0.048432 | AA28: =AA29*($F$13) -> 0.0438915 | AB28: =AB29*($F$13) -> 0.03027 | AC28: =AC24 -> 0.060153827 | AD28: =AD29*($F$13) -> 0.053088908 | AE28: =AE29*($F$13) -> 0.047384181 | AF28: =AF29*($F$13) -> 0.043105636 | AG28: =AG29*($F$13) -> 0.03027 | AH28: =AH24 -> 0.031846173
B29: =G12 -> Base | I29: 0.062 | J29: 0.05 | K29: =K23/J23-1 -> 0.070178785 | L29: =K29+($M$29-K29)/($M$22-$K$22) -> 0.050089392 | M29: =H14 -> 0.03 | N29: =(('Fin. Data'!G6-'Fin. Data'!H6))/(1+'Inflation Projections'!E24) -> 0.063846173 | O29: =N29+($R$29-N29)/($R$22-$N$22) -> 0.05538463 | P29: =O29+($R$29-O29)/($R$22-$N$22) -> 0.049038472 | Q29: =P29+($R$29-P29)/($R$22-$N$22) -> 0.044278854 | R29: 0.03 | S29: =R29+(N29-I29) -> 0.031846173 | T29: =S29+($R$29-S29)/($R$22-$N$22) -> 0.03138463 | U29: =T29+($R$29-T29)/($R$22-$N$22) -> 0.031038472 | V29: =U29+($R$29-U29)/($R$22-$N$22) -> 0.030778854 | W29: 0.03 | X29: =W29+(N29-S29) -> 0.062 | Y29: =X29+($R$29-X29)/($R$22-$N$22) -> 0.054 | Z29: =Y29+($R$29-Y29)/($R$22-$N$22) -> 0.048 | AA29: =Z29+($R$29-Z29)/($R$22-$N$22) -> 0.0435 | AB29: 0.03 | AC29: =AB29+(X29-S29) -> 0.060153827 | AD29: =AC29+($R$29-AC29)/($R$22-$N$22) -> 0.05261537 | AE29: =AD29+($R$29-AD29)/($R$22-$N$22) -> 0.046961528 | AF29: =AE29+($R$29-AE29)/($R$22-$N$22) -> 0.042721146 | AG29: 0.03 | AH29: =AG29+(X29-AC29) -> 0.031846173
B30: =I12 -> Optimistic | I30: =I24 -> 0.062 | J30: =J29*($J$13) -> 0.05845 | K30: =K29*($J$13) -> 0.082038999 | L30: =L29*($J$13) -> 0.0585545 | M30: =M29*($J$13) -> 0.03507 | N30: =N24 -> 0.063846173 | O30: =O29*($J$13) -> 0.064744632 | P30: =P29*($J$13) -> 0.057325974 | Q30: =Q29*($J$13) -> 0.051761981 | R30: =R29*($J$13) -> 0.03507 | S30: =S24 -> 0.031846173 | T30: =T29*($J$13) -> 0.036688632 | U30: =U29*($J$13) -> 0.036283974 | V30: =V29*($J$13) -> 0.035980481 | W30: =W29*($J$13) -> 0.03507 | X30: =X24 -> 0.062 | Y30: =Y29*($J$13) -> 0.063126 | Z30: =Z29*($J$13) -> 0.056112 | AA30: =AA29*($J$13) -> 0.0508515 | AB30: =AB29*($J$13) -> 0.03507 | AC30: =AC24 -> 0.060153827 | AD30: =AD29*($J$13) -> 0.061507368 | AE30: =AE29*($J$13) -> 0.054898026 | AF30: =AF29*($J$13) -> 0.049941019 | AG30: =AG29*($J$13) -> 0.03507 | AH30: =AH24 -> 0.031846173
C33: Last 5 Years | I33: Short Term Forecast
C34: 2017 | D34: 2018 | E34: 2019 | F34: 2020 | G34: 2021 | H34: 2022 | I34: 2023 | J34: =I34+1 -> 2024 | K34: =J34+1 -> 2025 | L34: =K34+1 -> 2026 | M34: =L34+1 -> 2027 | N34: =M34+1 -> 2028 | O34: =N34+1 -> 2029 | P34: =O34+1 -> 2030 | Q34: =P34+1 -> 2031 | ... AH34: =AG34+1 -> 2048
B35: EBIT | C35: =Inputs!G8 -> 4123 | D35: =Inputs!F8 -> 4526 | E35: =Inputs!E8 -> 4737 | F35: =Inputs!D8 -> 5435 | G35: =Inputs!C8 -> 6708 | H35: =Inputs!B8 -> 7793 | I35: 6349 | J35: 6865 | K35: 7467 | L35: =K35*(1+L36) -> 7670.7846 | M35: =L35*(1+M36) -> 7877.9928 | N35: =M35*(1+N36) -> 8118.0811 | O35: =N35*(1+O36) -> 8332.6977 | P35: =O35*(1+P36) -> 8527.7464 | Q35: =P35*(1+Q36) -> 8707.9864 | R35: =Q35*(1+R36) -> 8832.6844 | S35: =R35*(1+S36) -> 8995.6839 | ... AH35: =AG35*(1+AH36) -> 12787.611
B36: % of Sales | C36: =C35/C23 -> 0.031955047 | D36: =D35/D23 -> 0.031968695 | E36: =E35/E23 -> 0.031021002 | F36: =F35/F23 -> 0.032591553 | G36: =G35/G23 -> 0.034236892 | H36: =H35/H23 -> 0.034337355 | I36: =I41 -> 0.02634165 | J36: =J41 -> 0.027126195 | K36: =K41 -> 0.027570088 | L36: =L41 -> 0.027291366 | M36: =M41 -> 0.027012644 | N36: =N41 -> 0.030475821 | O36: =O41 -> 0.026436856 | P36: =P41 -> 0.023407632 | ... S36: =S41 -> 0.018454132 | T36: =T39 -> 0.021340599 | U36: =U39 -> 0.023505449 | V36: =V39 -> 0.025129087 | W36: =W39 -> 0.017384316 | X36: =X41 -> 0.029406006 | Y36: =Y39 -> 0.029554505 | Z36: =Z39 -> 0.029665878 | AA36: =AA39 -> 0.029749409 | AB36: =AB39 -> 0.014228713 | AC36: =AC41 -> 0.025180587 | AD36: =AD39 -> 0.02638544 | AE36: =AE39 -> 0.02728908 | AF36: =AF39 -> 0.02796681 | AG36: =AG39 -> 0.012558097 | AH36: =AH41 -> 0.016783516
B37: Actual 5y Average | H37: =AVERAGE(D36:H36) -> 0.032831099 | M37: =AVERAGE(I36:M36) -> 0.027068389 | R37: =AVERAGE(N36:R36) -> 0.023155197 | W37: =AVERAGE(S36:W36) -> 0.021162717 | AB37: =AVERAGE(X36:AB36) -> 0.026520902 | AG37: =AVERAGE(AC36:AG36) -> 0.023876003
B38: Target 5y Average | M38: 0.03 | R38: =H20 -> 0 | W38: =M20 -> 0 | AB38: =R20 -> 0 | AG38: =W20 -> 0
B39: Averages | I39: =OFFSET(I39,$C$13,0) -> 0.02634165 | J39: =OFFSET(J39,$C$12,0) -> 0.027126195 | K39: =OFFSET(K39,$C$12,0) -> 0.027570088 | L39: =OFFSET(L39,$C$12,0) -> 0.027291366 | M39: =OFFSET(M39,$C$12,0) -> 0.027012644 | N39: =OFFSET(N39,$C$12,0) -> 0.030475821 | O39: =OFFSET(O39,$C$12,0) -> 0.026436856 | P39: =OFFSET(P39,$C$12,0) -> 0.023407632 | Q39: =OFFSET(Q39,$C$12,0) -> 0.021135714 | ... AH39: =OFFSET(AH39,$C$12,0) -> 0.016783516
B40: =B28 -> Conservative | I40: =I41*$F$15 -> 0.023707485 | J40: =J41*$F$15 -> 0.024413576 | K40: =K41*$F$15 -> 0.024813079 | L40: =L41*$F$15 -> 0.02456223 | M40: =M41*$F$15 -> 0.02431138 | N40: =N41*$F$15 -> 0.027428239 | O40: =O41*$F$15 -> 0.02379317 | P40: =P41*$F$15 -> 0.021066869 | ... R40: =R41*$F$15 -> 0.012887964 | S40: =S36 -> 0.018454132 | T40: =T41*($F$13) -> 0.021532664 | U40: =U41*($F$13) -> 0.023716998 | V40: =V41*($F$13) -> 0.025355249 | W40: =W41*($F$13) -> 0.017540775 | X40: =X36 -> 0.029406006 | Y40: =Y41*($F$13) -> 0.029820495 | Z40: =Z41*($F$13) -> 0.029932871 | AA40: =AA41*($F$13) -> 0.030017154 | AB40: =AB41*($F$13) -> 0.014356771 | AC40: =AC36 -> 0.025180587 | AD40: =AD41*($F$13) -> 0.026622909 | AE40: =AE41*($F$13) -> 0.027534682 | AF40: =AF41*($F$13) -> 0.028218511 | AG40: =AG41*($F$13) -> 0.01267112 | AH40: =AH36 -> 0.016783516
B41: =B29 -> Base | I41: =I35/I23 -> 0.02634165 | J41: =J35/J23 -> 0.027126195 | K41: =K35/K23 -> 0.027570088 | L41: =K41+($M$41-K41)/($M$34-$K$34) -> 0.027291366 | M41: =H16 -> 0.027012644 | N41: =M41*(N29/M29-1) -> 0.030475821 | O41: =N41+($R$41-N41)/($R$34-$N$34) -> 0.026436856 | P41: =O41+($R$41-O41)/($R$34-$N$34) -> 0.023407632 | Q41: =P41+($R$41-P41)/($R$34-$N$34) -> 0.021135714 | R41: =N41*(1+(R27/N27-1)) -> 0.01431996 | S41: =R41+(N41-I41) -> 0.018454132 | T41: =S41+($R$29-S41)/($R$22-$N$22) -> 0.021340599 | U41: =T41+($R$29-T41)/($R$22-$N$22) -> 0.023505449 | V41: =U41+($R$29-U41)/($R$22-$N$22) -> 0.025129087 | W41: =S41*(1+(W27/S27-1)) -> 0.017384316 | X41: =W41+(N41-S41) -> 0.029406006 | Y41: =X41+($R$29-X41)/($R$22-$N$22) -> 0.029554505 | Z41: =Y41+($R$29-Y41)/($R$22-$N$22) -> 0.029665878 | AA41: =Z41+($R$29-Z41)/($R$22-$N$22) -> 0.029749409 | AB41: =X41*(1+(AB27/X27-1)) -> 0.014228713 | AC41: =AB41+(X41-S41) -> 0.025180587 | AD41: =AC41+($R$29-AC41)/($R$22-$N$22) -> 0.02638544 | AE41: =AD41+($R$29-AD41)/($R$22-$N$22) -> 0.02728908 | AF41: =AE41+($R$29-AE41)/($R$22-$N$22) -> 0.02796681 | AG41: =AC41*(1+(AG27/AC27-1)) -> 0.012558097 | AH41: =AG41+(X41-AC41) -> 0.016783516
B42: =B30 -> Optimistic | I42: =I41*$J$15 -> 0.028975815 | J42: =J41*$J$15 -> 0.029838815 | K42: =K41*$J$15 -> 0.030327097 | L42: =L41*$J$15 -> 0.030020503 | M42: =M41*$J$15 -> 0.029713909 | N42: =N36 -> 0.030475821 | O42: =O41*($J$13) -> 0.030904685 | P42: =P41*($J$13) -> 0.027363522 | Q42: =Q41*($J$13) -> 0.02470765 | R42: =R41*($J$13) -> 0.016740033 | S42: =S36 -> 0.018454132 | T42: =T41*($J$13) -> 0.02494716 | U42: =U41*($J$13) -> 0.02747787 | V42: =V41*($J$13) -> 0.029375903 | W42: =W41*($J$13) -> 0.020322266 | X42: =X36 -> 0.029406006 | Y42: =Y41*($J$13) -> 0.034549216 | Z42: =Z41*($J$13) -> 0.034679412 | AA42: =AA41*($J$13) -> 0.034777059 | AB42: =AB41*($J$13) -> 0.016633365 | AC42: =AC36 -> 0.025180587 | AD42: =AD41*($J$13) -> 0.03084458 | AE42: =AE41*($J$13) -> 0.031900935 | AF42: =AF41*($J$13) -> 0.032693201 | AG42: =AG41*($J$13) -> 0.014680416 | AH42: =AH36 -> 0.016783516
C45: Last 5 Years | I45: Short Term Forecast
C46: 2017 | D46: 2018 | E46: 2019 | F46: 2020 | G46: 2021 | H46: 2022 | I46: 2023 | J46: =I46+1 -> 2024 | K46: =J46+1 -> 2025 | L46: =K46+1 -> 2026 | M46: =L46+1 -> 2027 | N46: =M46+1 -> 2028 | O46: =N46+1 -> 2029 | P46: =O46+1 -> 2030 | Q46: =P46+1 -> 2031 | ... AH46: =AG46+1 -> 2048
B47: Taxes | C47: =Inputs!G11 -> 1325 | D47: =Inputs!F11 -> 1263 | E47: =Inputs!E11 -> 1061 | F47: =Inputs!D11 -> 1308 | G47: =Inputs!C11 -> 1601 | H47: =Inputs!B11 -> 1925 | I47: =I48*I35 -> 1561.073 | J47: =J48*J35 -> 1687.9455 | K47: =K48*K35 -> 1835.9635 | L47: =L48*L35 -> 1886.0694 | M47: =M48*M35 -> 1937.0172 | N47: =M47*(1+N48) -> 2343.7908 | O47: =N47*(1+O48) -> 2835.9868 | P47: =O47*(1+P48) -> 3431.544 | Q47: =P47*(1+Q48) -> 4152.1683 | R47: =Q47*(1+R48) -> 5024.1236 | S47: =R47*(1+S48) -> 6079.1896 | T47: =S47*(1+T48) -> 7355.8194 | U47: =T47*(1+U48) -> 8900.5415 | ... AH47: =AG47*(1+AH48) -> 106078.22
B48: % of EBIT | C48: =C47/C35 -> 0.32136794 | D48: =D47/D35 -> 0.27905435 | E48: =E47/E35 -> 0.22398142 | F48: =F47/F35 -> 0.24066237 | G48: =G47/G35 -> 0.23867024 | H48: =H47/H35 -> 0.24701655 | I48: =$H$49 -> 0.24587699 | J48: =$H$49 -> 0.24587699 | K48: =$H$49 -> 0.24587699 | L48: =$H$49 -> 0.24587699 | M48: =$H$49 -> 0.24587699 | N48: 0.21 | O48: 0.21 | P48: 0.21 | Q48: 0.21 | R48: 0.21 | S48: 0.21 | T48: 0.21 | U48: 0.21 | V48: 0.21 | W48: 0.21 | X48: 0.21 | Y48: 0.21 | Z48: 0.21 | AA48: 0.21 | AB48: 0.21 | AC48: 0.21 | AD48: 0.21 | AE48: 0.21 | AF48: 0.21 | AG48: 0.21 | AH48: 0.21
B49: Target 5y Average | H49: =AVERAGE(D48:H48) -> 0.24587699 | R49: 0.21 | W49: =AVERAGE(S48:W48) -> 0.21 | AB49: =AVERAGE(X48:AB48) -> 0.21 | AG49: =AVERAGE(AC48:AG48) -> 0.21
B52: NOPLAT | C52: =C35-C47 -> 2798 | D52: =D35-D47 -> 3263 | E52: =E35-E47 -> 3676 | F52: =F35-F47 -> 4127 | G52: =G35-G47 -> 5107 | H52: =H35-H47 -> 5868 | I52: =I35-I47 -> 4787.927 | J52: =J35-J47 -> 5177.0545 | ... AH52: =AH35-AH47 -> -93290.614
C55: Last 5 Years | I55: Short Term Forecast
C56: 2017 | D56: 2018 | E56: 2019 | F56: 2020 | G56: 2021 | H56: 2022 | I56: 2023 | J56: =I56+1 -> 2024 | K56: =J56+1 -> 2025 | L56: =K56+1 -> 2026 | M56: =L56+1 -> 2027 | N56: =M56+1 -> 2028 | O56: =N56+1 -> 2029 | P56: =O56+1 -> 2030 | Q56: =P56+1 -> 2031 | ... AH56: =AG56+1 -> 2048
B57: Dep & Amort | C57: =Inputs!G61 -> 1370 | D57: =Inputs!F61 -> 1437 | E57: =Inputs!E61 -> 1492 | F57: =Inputs!D61 -> 1645 | G57: =Inputs!C61 -> 1781 | H57: =Inputs!B61 -> 1900 | I57: =I58*I$23 -> 2277.5339 | J57: =J58*J$23 -> 2391.4106 | K57: =K58*K$23 -> 2559.2369 | L57: =L58*L$23 -> 2687.4275 | M57: =M58*M$23 -> 2768.0503 | N57: =M57*(1+N58) -> 2793.2234 | O57: =N57*(1+O58) -> 2818.6254 | P57: =O57*(1+P58) -> 2844.2584 | Q57: =P57*(1+Q58) -> 2870.1245 | R57: =Q57*(1+R58) -> 2896.2258 | S57: =R57*(1+S58) -> 2921.5744 | T57: =S57*(1+T58) -> 2947.1449 | U57: =T57*(1+U58) -> 2972.9391 | ... AH57: =AG57*(1+AH58) -> 3310.3729
B58: % of Sales | C58: =C57/C$23 -> 0.010618097 | D58: =D57/D$23 -> 0.010150025 | E58: =E57/E$23 -> 0.0097706004 | F58: =F57/F$23 -> 0.0098644167 | G58: =G57/G$23 -> 0.0090900275 | H58: =H57/H$23 -> 0.0083717405 | I58: =$H$59 -> 0.0094493621 | J58: =$H$59 -> 0.0094493621 | K58: =$H$59 -> 0.0094493621 | L58: =$H$59 -> 0.0094493621 | M58: =$H$59 -> 0.0094493621 | N58: =$H$59*(1-(-$H$60)) -> 0.0090941475 | O58: =N58 -> 0.0090941475 | P58: =O58 -> 0.0090941475 | Q58: =P58 -> 0.0090941475 | R58: =Q58 -> 0.0090941475 | S58: =$N$58*(1-(-$H$60)) -> 0.0087522859 | T58: =S58 -> 0.0087522859 | U58: =T58 -> 0.0087522859 | V58: =U58 -> 0.0087522859 | W58: =V58 -> 0.0087522859 | X58: =S58*(1-(-$H$60)) -> 0.0084232754 | Y58: =X58 -> 0.0084232754 | Z58: =Y58 -> 0.0084232754 | AA58: =Z58 -> 0.0084232754 | AB58: =AA58 -> 0.0084232754 | AC58: =X58*(1-(-$H$60)) -> 0.0081066328 | AD58: =AC58 -> 0.0081066328 | AE58: =AD58 -> 0.0081066328 | AF58: =AE58 -> 0.0081066328 | AG58: =AF58 -> 0.0081066328 | AH58: =AC58*(1-(-$H$60)) -> 0.0078018933
B59: Target 5y Average | H59: =AVERAGE(D58:H58) -> 0.0094493621 | R59: =AVERAGE(N58:R58) -> 0.0090941475 | W59: =AVERAGE(S58:W58) -> 0.0087522859 | AB59: =AVERAGE(X58:AB58) -> 0.0084232754 | AG59: =AVERAGE(AC58:AG58) -> 0.0081066328
B60: Average Growth % Sales | D60: =D58/C58-1 -> -0.044082459 | E60: =E58/D58-1 -> -0.037381678 | F60: =F58/E58-1 -> 0.0096018964 | G60: =G58/F58-1 -> -0.078503296 | H60: =AVERAGE(D60:G60) -> -0.037591384 | R60: =AVERAGE(N59:R59) -> 0.0090941475 | W60: =AVERAGE(S59:W59) -> 0.0087522859 | AB60: =AVERAGE(X59:AB59) -> 0.0084232754 | AG60: =AVERAGE(AC59:AG59) -> 0.0081066328
C63: Last 5 Years | I63: Short Term Forecast
C64: 2017 | D64: 2018 | E64: 2019 | F64: 2020 | G64: 2021 | H64: 2022 | I64: 2023 | J64: =I64+1 -> 2024 | K64: =J64+1 -> 2025 | L64: =K64+1 -> 2026 | M64: =L64+1 -> 2027 | N64: =M64+1 -> 2028 | O64: =N64+1 -> 2029 | P64: =O64+1 -> 2030 | Q64: =P64+1 -> 2031 | ... AH64: =AG64+1 -> 2048
B65: CAPEX | C65: =Inputs!G65 -> -2502 | D65: =Inputs!F65 -> -2969 | E65: =Inputs!E65 -> -2998 | F65: =Inputs!D65 -> -2810 | G65: =Inputs!C65 -> -3588 | H65: =Inputs!B65 -> -3891 | I65: =I66*I$23 -> -4478.807 | J65: =J66*J$23 -> -4702.7474 | K65: =K66*K$23 -> -5032.7805 | L65: =L66*L$23 -> -5284.8694 | M65: =M66*M$23 -> -5443.4155 | N65: =M65*(1+N66) -> -5342.2642 | O65: =N65*(1+O66) -> -5242.9925 | P65: =O65*(1+P66) -> -5145.5655 | Q65: =P65*(1+Q66) -> -5049.949 | R65: =Q65*(1+R66) -> -4956.1092 | S65: =R65*(1+S66) -> -4864.0132 | T65: =S65*(1+T66) -> -4773.6285 | U65: =T65*(1+U66) -> -4684.9234 | ... AH65: =AG65*(1+AH66) -> -3671.1564
B66: % of Sales | C66: =C65/C$23 -> -0.019391591 | D66: =D65/D$23 -> -0.020971069 | E66: =E65/E$23 -> -0.019632882 | F66: =F65/F$23 -> -0.016850463 | G66: =G65/G$23 -> -0.018312756 | H66: =H65/H$23 -> -0.017144443 | I66: =$H$67 -> -0.018582323 | J66: =$H$67 -> -0.018582323 | K66: =$H$67 -> -0.018582323 | L66: =$H$67 -> -0.018582323 | M66: =$H$67 -> -0.018582323 | N66: =H67 -> -0.018582323 | O66: =N66 -> -0.018582323 | P66: =O66 -> -0.018582323 | Q66: =P66 -> -0.018582323 | R66: =Q66 -> -0.018582323 | S66: =R66 -> -0.018582323 | T66: =S66 -> -0.018582323 | U66: =T66 -> -0.018582323 | V66: =U66 -> -0.018582323 | ... AH66: =AG66 -> -0.018582323
B67: Target 5y Average | H67: =AVERAGE(D66:H66) -> -0.018582323 | R67: =AVERAGE(N66:R66) -> -0.018582323 | W67: =AVERAGE(S66:W66) -> -0.018582323 | AB67: =AVERAGE(X66:AB66) -> -0.018582323 | AG67: =AVERAGE(AC66:AG66) -> -0.018582323
C70: Last 5 Years | I70: Short Term Forecast
C71: 2017 | D71: 2018 | E71: 2019 | F71: 2020 | G71: 2021 | H71: 2022 | I71: 2023 | J71: =I71+1 -> 2024 | K71: =J71+1 -> 2025 | L71: =K71+1 -> 2026 | M71: =L71+1 -> 2027 | N71: =M71+1 -> 2028 | O71: =N71+1 -> 2029 | P71: =O71+1 -> 2030 | Q71: =P71+1 -> 2031 | ... AH71: =AG71+1 -> 2048
B72: Change in NWC | C72: =Inputs!G22 -> -1885 | D72: =Inputs!F22 -> -935 | E72: =Inputs!E22 -> -681 | F72: =Inputs!D22 -> -2447 | G72: =Inputs!C22 -> -1378 | H72: =Inputs!B22 -> 1034 | I72: =I73*I$23 -> -1360.0919 | J72: =J73*J$23 -> -1428.0965 | K72: =K73*K$23 -> -1528.3185 | L72: =L73*L$23 -> -1604.8711 | M72: =M73*M$23 -> -1653.0172 | N72: =M72*(1+N73) -> -1643.6893 | O72: =N72*(1+O73) -> -1634.4141 | P72: =O72*(1+P73) -> -1625.1912 | Q72: =P72*(1+Q73) -> -1616.0203 | R72: =Q72*(1+R73) -> -1606.9012 | S72: =R72*(1+S73) -> -1597.8335 | T72: =S72*(1+T73) -> -1588.817 | U72: =T72*(1+U73) -> -1579.8514 | ... AH72: =AG72*(1+AH73) -> -1467.8001
B73: % of Sales | C73: =C72/C$23 -> -0.014609572 | D73: =D72/D$23 -> -0.0066042267 | E73: =E72/E$23 -> -0.0044596373 | F73: =F72/F$23 -> -0.014673695 | G73: =G72/G$23 -> -0.00703316 | H73: =H72/H$23 -> 0.0045559893 | I73: =$H$74 -> -0.0056429459 | J73: =$H$74 -> -0.0056429459 | K73: =$H$74 -> -0.0056429459 | L73: =$H$74 -> -0.0056429459 | M73: =$H$74 -> -0.0056429459 | N73: =H74 -> -0.0056429459 | O73: =N73 -> -0.0056429459 | P73: =O73 -> -0.0056429459 | Q73: =P73 -> -0.0056429459 | R73: =Q73 -> -0.0056429459 | S73: =R73 -> -0.0056429459 | T73: =S73 -> -0.0056429459 | U73: =T73 -> -0.0056429459 | V73: =U73 -> -0.0056429459 | ... AH73: =AG73 -> -0.0056429459
B74: Target 5y Average | H74: =AVERAGE(D73:H73) -> -0.0056429459 | R74: =AVERAGE(N73:R73) -> -0.0056429459 | W74: =AVERAGE(S73:W73) -> -0.0056429459 | AB74: =AVERAGE(X73:AB73) -> -0.0056429459 | AG74: =AVERAGE(AC73:AG73) -> -0.0056429459
B77: Unlevered FCF | C77: =C57-C72 -> 3255 | D77: =D57-D72 -> 2372 | E77: =E57-E72 -> 2173 | F77: =F57-F72 -> 4092 | G77: =G57-G72 -> 3159 | H77: =H57-H72 -> 866 | I77: =I57-I72 -> 3637.6258 | J77: =J57-J72 -> 3819.5071 | ... AH77: =AH57-AH72 -> 4778.173
C80: Last 5 Years | I80: Short Term Forecast
C81: 2017 | D81: 2018 | E81: 2019 | F81: 2020 | G81: 2021 | H81: 2022 | I81: 2023 | J81: =I81+1 -> 2024 | K81: =J81+1 -> 2025 | L81: =K81+1 -> 2026 | M81: =L81+1 -> 2027 | N81: =M81+1 -> 2028 | O81: =N81+1 -> 2029 | P81: =O81+1 -> 2030 | Q81: =P81+1 -> 2031 | ... AH81: =AG81+1 -> 2048
B82: Stock-based Compensation | C82: 514 | D82: 544 | E82: 595 | F82: 619 | G82: 665 | H82: 724 | I82: =I83*I$23 -> 869.37632 | J82: =J83*J$23 -> 912.84514 | K82: =K83*K$23 -> 976.9075 | L82: =L83*L$23 -> 1025.8402 | M82: =M83*M$23 -> 1056.6154 | N82: =M82*(1+N83) -> 1060.4266 | O82: =N82*(1+O83) -> 1064.2516 | P82: =O82*(1+P83) -> 1068.0903 | Q82: =P82*(1+Q83) -> 1071.9429 | R82: =Q82*(1+R83) -> 1075.8094 | S82: =R82*(1+S83) -> 1079.6898 | T82: =S82*(1+T83) -> 1083.5843 | U82: =T82*(1+U83) -> 1087.4928 | ... AH82: =AG82*(1+AH83) -> 1139.6046
B83: % of Sales | C83: =C82/C$23 -> 0.0039837241 | D83: =D82/D$23 -> 0.0038424592 | E83: =E82/E$23 -> 0.0038964526 | F83: =F82/F$23 -> 0.0037118991 | G83: =G82/G$23 -> 0.0033940866 | H83: =H82/H$23 -> 0.0031900738 | I83: =$H$84 -> 0.0036069942 | J83: =$H$84 -> 0.0036069942 | K83: =$H$84 -> 0.0036069942 | L83: =$H$84 -> 0.0036069942 | M83: =$H$84 -> 0.0036069942 | N83: =$H$84 -> 0.0036069942 | O83: =N83 -> 0.0036069942 | P83: =O83 -> 0.0036069942 | Q83: =P83 -> 0.0036069942 | R83: =Q83 -> 0.0036069942 | S83: =R83 -> 0.0036069942 | T83: =S83 -> 0.0036069942 | U83: =T83 -> 0.0036069942 | V83: =U83 -> 0.0036069942 | ... AH83: =AG83 -> 0.0036069942
B84: Target 5y Average | H84: =AVERAGE(D83:H83) -> 0.0036069942 | R84: =AVERAGE(N83:R83) -> 0.0036069942 | W84: =AVERAGE(S83:W83) -> 0.0036069942 | AB84: =AVERAGE(X83:AB83) -> 0.0036069942 | AG84: =AVERAGE(AC83:AG83) -> 0.0036069942
B87: Weighted-average interest rate on debt and finance leases
C89: Interest rate | D89: Debt Amount
B90: Senior Notes due May 2024 | C90: 0.0275 | D90: 1000 | E90: =C90*D90 -> 27.5
B91: Senior Notes due May 2027 | C91: 0.03 | D91: 1000 | E91: =C91*D91 -> 30
B92: Senior Notes due June 2027 | C92: 0.0138 | D92: 1250 | E92: =C92*D92 -> 17.25 | F92: =SUM(E90:E92)/(SUM(D90:D92)) -> 0.023
B93: Senior Notes due April 2030 | C93: 0.016 | D93: 1750 | E93: =C93*D93 -> 28
B94: Senior Notes due April 2032 | C94: 0.0175 | D94: 1000 | E94: =C94*D94 -> 17.5
B95: Finance Lease | C95: 0.0397 | D95: 1620 | E95: =C95*D95 -> 64.314
D96: =SUM(D90:D95) -> 7620 | E96: =SUM(E90:E95) -> 184.564 | F96: =SUM(E93:E95)/SUM(D93:D95) -> 0.025129062
C99: Last 5 Years | I99: Short Term Forecast
C100: 2017 | D100: 2018 | E100: 2019 | F100: 2020 | G100: 2021 | H100: 2022 | I100: 2023 | J100: =I100+1 -> 2024 | K100: =J100+1 -> 2025 | L100: =K100+1 -> 2026 | M100: =L100+1 -> 2027 | N100: =M100+1 -> 2028 | O100: =N100+1 -> 2029 | P100: =O100+1 -> 2030 | Q100: =P100+1 -> 2031 | ... AH100: =AG100+1 -> 2048
B101: Dividends | C101: ='Fin. Data'!G27 -> -804 | D101: ='Fin. Data'!F27 -> -689 | E101: ='Fin. Data'!E27 -> -1038 | F101: ='Fin. Data'!D27 -> -1479 | G101: ='Fin. Data'!C27 -> -1318 | H101: ='Fin. Data'!B27 -> -1498 | I101: =-I102*I77 -> -1179.4033 | J101: =-J102*J77 -> -1238.3735 | K101: =-K102*K77 -> -1325.2811 | L101: =-L102*L77 -> -1391.6636 | M101: =-M102*M77 -> -1433.4135 | N101: =M101*(1+N102) -> -1898.1597 | O101: =N101*(1+O102) -> -2513.5874 | P101: =O101*(1+P102) -> -3328.5512 | Q101: =P101*(1+Q102) -> -4407.7454 | R101: =Q101*(1+R102) -> -5836.8395 | S101: =R101*(1+S102) -> -7729.2793 | T101: =S101*(1+T102) -> -10235.292 | U101: =T101*(1+U102) -> -13553.814 | ... AH101: =AG101*(1+AH102) -> -521864.55
B102: Payout Ratio | C102: =-C101/'Fin. Data'!H23 -> 0.34212766 | D102: =-D101/'Fin. Data'!G23 -> 0.25718552 | E102: =-E101/'Fin. Data'!F23 -> 0.33120613 | F102: =-F101/'Fin. Data'!E23 -> 0.4042088 | G102: =-G101/'Fin. Data'!D23 -> 0.32933533 | H102: =-H101/'Fin. Data'!C23 -> 0.29918115 | I102: =$H$103 -> 0.32422338 | J102: =$H$103 -> 0.32422338 | K102: =$H$103 -> 0.32422338 | L102: =$H$103 -> 0.32422338 | M102: =$H$103 -> 0.32422338 | N102: =$H$103 -> 0.32422338 | O102: =$H$103 -> 0.32422338 | P102: =$H$103 -> 0.32422338 | ... AH102: =$H$103 -> 0.32422338
B103: Target 5y Average | H103: =AVERAGE(D102:H102) -> 0.32422338 | R103: =AVERAGE(N102:R102) -> 0.32422338 | W103: =AVERAGE(S102:W102) -> 0.32422338 | AB103: =AVERAGE(X102:AB102) -> 0.32422338 | AG103: =AVERAGE(AC102:AG102) -> 0.32422338
C106: Last 5 Years | I106: Short Term Forecast
C107: 2017 | D107: 2018 | E107: 2019 | F107: 2020 | G107: 2021 | H107: 2022 | I107: 2023 | J107: =I107+1 -> 2024 | K107: =J107+1 -> 2025 | L107: =K107+1 -> 2026 | M107: =L107+1 -> 2027 | N107: =M107+1 -> 2028 | O107: =N107+1 -> 2029 | P107: =O107+1 -> 2030 | Q107: =P107+1 -> 2031 | ... AH107: =AG107+1 -> 2048
B108: Repurchases | C108: ='Fin. Data'!G28 -> -671 | D108: ='Fin. Data'!F28 -> -545 | E108: ='Fin. Data'!E28 -> -519 | F108: ='Fin. Data'!D28 -> -526 | G108: ='Fin. Data'!C28 -> -808 | H108: ='Fin. Data'!B28 -> -802 | I108: =-I109*H77 -> -151.52698 | J108: =-J109*I77 -> -636.48783 | K108: =-K109*J77 -> -668.31222 | L108: =-L109*K77 -> -715.21356 | M108: =-M109*L77 -> -751.03817 | N108: =M108*(1+N109) -> -863.6939 | O108: =N108*(1+O109) -> -993.24798 | P108: =O108*(1+P109) -> -1142.2352 | Q108: =P108*(1+Q109) -> -1313.5705 | R108: =Q108*(1+R109) -> -1510.606 | S108: =R108*(1+S109) -> -1737.1969 | T108: =S108*(1+T109) -> -1997.7765 | U108: =T108*(1+U109) -> -2297.4429 | ... AH108: =AG108*(1+AH109) -> -14135.678
B109: Repurchase rate % Net Income (N-1) | C109: =-C108/'Fin. Data'!H23 -> 0.28553191 | D109: =-D108/'Fin. Data'!G23 -> 0.20343412 | E109: =-E108/'Fin. Data'!F23 -> 0.16560306 | F109: =-F108/'Fin. Data'!E23 -> 0.14375512 | G109: =-G108/'Fin. Data'!D23 -> 0.20189905 | H109: =-H108/'Fin. Data'!C23 -> 0.16017575 | I109: =$H$110 -> 0.17497342 | J109: =$H$110 -> 0.17497342 | K109: =$H$110 -> 0.17497342 | L109: =$H$110 -> 0.17497342 | M109: =$H$110 -> 0.17497342 | N109: 0.15 | O109: 0.15 | P109: 0.15 | Q109: 0.15 | R109: 0.15 | S109: 0.15 | T109: 0.15 | U109: 0.15 | V109: 0.15 | W109: 0.15 | X109: 0.15 | Y109: 0.15 | Z109: 0.15 | AA109: 0.15 | AB109: 0.15 | AC109: 0.15 | AD109: 0.15 | AE109: 0.15 | AF109: 0.15 | AG109: 0.15 | AH109: 0.15
B110: Target 5y Average | H110: =AVERAGE(D109:H109) -> 0.17497342 | R110: =AVERAGE(N109:R109) -> 0.15 | W110: =AVERAGE(S109:W109) -> 0.15 | AB110: =AVERAGE(X109:AB109) -> 0.15 | AG110: =AVERAGE(AC109:AG109) -> 0.15
B114: Segments | C114: Weight | D114: Country Risk Premium | E114: Country Equity Risk Premium
B115: US | C115: =Segments!B5 -> 0.86788072 | D115: 0 | E115: 0.05 | H115: Source: | I115: https://pages.stern.nyu.edu/~adamodar/New_Home_Page/datafile/ctryprem.html
B116: Other Markets | C116: =Segments!B6 -> 0.13211928 | D116: =0.32*0+(1-0.32)*(AVERAGE(0.0075,0.0289,0.0107,0.0091,0.0091,0.0243,0)) -> 0.008704 | E116: =0.32*0.05+(1-0.32)*(AVERAGE(0.0591,0.0743,0.062,0.0607,0.05)) -> 0.0576296
B117: Total | C117: 1 | D117: =D115*$C$115+D116*$C$116 -> 0.0011499662 | E117: =E115*$C$115+E116*$C$116 -> 0.051008017
B119: Firm premium | C119: =C121+C120*(C122-C121) -> 0.048726414
B120: Beta | C120: 0.8
B121: Rf | C121: =3.96% -> 0.0396
B122: Rm | C122: =E117 -> 0.051008017
C127: Last 5 Years | I127: Short Term Forecast
C128: 2017 | D128: 2018 | E128: 2019 | F128: 2020 | G128: 2021 | H128: 2022 | I128: 2023 | J128: =I128+1 -> 2024 | K128: =J128+1 -> 2025 | L128: =K128+1 -> 2026 | M128: =L128+1 -> 2027 | N128: =M128+1 -> 2028 | O128: =N128+1 -> 2029 | P128: =O128+1 -> 2030 | Q128: =P128+1 -> 2031 | ... AH128: =AG128+1 -> 2048
B129: Debt/EBITDA | C129: ='Fin. Data'!G58/'Fin. Data'!G19 -> 0.42217714 | D129: ='Fin. Data'!F58/'Fin. Data'!F19 -> 0.38717843 | E129: ='Fin. Data'!E58/'Fin. Data'!E19 -> 0.39643189 | F129: ='Fin. Data'!D58/'Fin. Data'!D19 -> 0.54951918 | G129: ='Fin. Data'!C58/'Fin. Data'!C19 -> 0.48827155 | H129: ='Fin. Data'!B58/'Fin. Data'!B19 -> 0.42691615 | I129: =$H$130 -> 0.44966344 | J129: =$H$130 -> 0.44966344 | K129: =$H$130 -> 0.44966344 | L129: =$H$130 -> 0.44966344 | M129: =$H$130 -> 0.44966344 | N129: =H130 -> 0.44966344 | O129: =N129 -> 0.44966344 | P129: =O129 -> 0.44966344 | Q129: =P129 -> 0.44966344 | R129: =Q129 -> 0.44966344 | S129: =R129 -> 0.44966344 | T129: =S129 -> 0.44966344 | U129: =T129 -> 0.44966344 | V129: =U129 -> 0.44966344 | ... AH129: =AG129 -> 0.44966344
B130: Target 5y Average | H130: =AVERAGE(D129:H129) -> 0.44966344 | R130: =AVERAGE(#REF!) -> #REF! | W130: =AVERAGE(#REF!) -> #REF! | AB130: =AVERAGE(#REF!) -> #REF! | AG130: =AVERAGE(#REF!) -> #REF!
B134: Modelling Factors
C136: Last 5 Years
C137: 2018 | D137: 2019 | E137: 2020 | F137: 2021 | G137: 2022 | H137: Short Term Forecast | I137: Long Term Forecast
B138: Depreciation factor | C138: =D58 -> 0.010150025 | D138: =E58 -> 0.0097706004 | E138: =F58 -> 0.0098644167 | F138: =G58 -> 0.0090900275 | G138: =H58 -> 0.0083717405 | H138: =AVERAGE(C138:G138) -> 0.0094493621 | I138: =AVERAGE(N58,S58,X58,AC58,AH58) -> 0.008435647
B139: Amortization factor | C139: =C138 -> 0.010150025 | D139: =D138 -> 0.0097706004 | E139: =E138 -> 0.0098644167 | F139: =F138 -> 0.0090900275 | G139: =G138 -> 0.0083717405 | H139: =AVERAGE(C139:G139) -> 0.0094493621 | I139: =AVERAGE(D139:H139) -> 0.0093092295
B140: Stock-based comp | C140: =D83 -> 0.0038424592 | D140: =E83 -> 0.0038964526 | E140: =F83 -> 0.0037118991 | F140: =G83 -> 0.0033940866 | G140: =H83 -> 0.0031900738 | H140: =AVERAGE(C140:G140) -> 0.0036069942 | I140: =AVERAGE(D140:H140) -> 0.0035599013
B141: Tax Rate | C141: =D48 -> 0.27905435 | D141: =E48 -> 0.22398142 | E141: =F48 -> 0.24066237 | F141: =G48 -> 0.23867024 | G141: =H48 -> 0.24701655 | H141: =AVERAGE(C141:G141) -> 0.24587699 | I141: =AVERAGE(D141:H141) -> 0.23924152
B142: Interest Rate on debt | H142: =F92 -> 0.023 | I142: =F96 -> 0.025129062
B143: Interest Rate on cash | H143: =H147 -> -0.018582323 | I143: =I147 -> -0.018104573
...

Sheet Fin. Data
A1: =Inputs!H3 -> #VALUE!
A2: =Inputs!G2 -> Figures in Millions of USD
A3: Results
B4: =OP!J20 -> 2022 | C4: =B4-1 -> 2021 | D4: =C4-1 -> 2020 | E4: =D4-1 -> 2019 | F4: =E4-1 -> 2018 | G4: =F4-1 -> 2017 | H4: =G4-1 -> 2016 | I4: =H4-1 -> 2015 | J4: =I4-1 -> 2014 | ... M4: =L4-1 -> 2011
A5: Net Sales | B5: =_xlfn.XLOOKUP($A5,Inputs!$A:$A,Inputs!B:B,,0) -> 226954 | C5: =_xlfn.XLOOKUP($A5,Inputs!$A:$A,Inputs!C:C,,0) -> 195929 | D5: =_xlfn.XLOOKUP($A5,Inputs!$A:$A,Inputs!D:D,,0) -> 166761 | E5: =_xlfn.XLOOKUP($A5,Inputs!$A:$A,Inputs!E:E,,0) -> 152703 | F5: =_xlfn.XLOOKUP($A5,Inputs!$A:$A,Inputs!F:F,,0) -> 141576 | G5: =_xlfn.XLOOKUP($A5,Inputs!$A:$A,Inputs!G:G,,0) -> 129025 | H5: =_xlfn.XLOOKUP($A5,Inputs!$A:$A,Inputs!H:H,,0) -> 118719 | I5: =_xlfn.XLOOKUP($A5,Inputs!$A:$A,Inputs!I:I,,0) -> 116199 | J5: =_xlfn.XLOOKUP($A5,Inputs!$A:$A,Inputs!J:J,,0) -> 112640 | K5: =_xlfn.XLOOKUP($A5,Inputs!$A:$A,Inputs!K:K,,0) -> 105156 | L5: =_xlfn.XLOOKUP($A5,Inputs!$A:$A,Inputs!L:L,,0) -> 0 | M5: =_xlfn.XLOOKUP($A5,Inputs!$A:$A,Inputs!M:M,,0) -> 0
A6: Growth vs. Previous year | B6: =IFERROR(B5/C5-1,"-") -> 0.15834818 | C6: =IFERROR(C5/D5-1,"-") -> 0.174909 | D6: =IFERROR(D5/E5-1,"-") -> 0.09206106 | E6: =IFERROR(E5/F5-1,"-") -> 0.078593829 | F6: =IFERROR(F5/G5-1,"-") -> 0.097275722 | G6: =IFERROR(G5/H5-1,"-") -> 0.08681003 | H6: =IFERROR(H5/I5-1,"-") -> 0.021686934 | I6: =IFERROR(I5/J5-1,"-") -> 0.031596236 | ... L6: =IFERROR(L5/M5-1,"-") -> - | M6: =IFERROR(M5/#REF!-1,"-") -> -
A7: Gross Profit | B7: =_xlfn.XLOOKUP($A7,Inputs!$A:$A,Inputs!B:B,,0) -> 27572 | C7: =_xlfn.XLOOKUP($A7,Inputs!$A:$A,Inputs!C:C,,0) -> 25245 | D7: =_xlfn.XLOOKUP($A7,Inputs!$A:$A,Inputs!D:D,,0) -> 21822 | E7: =_xlfn.XLOOKUP($A7,Inputs!$A:$A,Inputs!E:E,,0) -> 19817 | F7: =_xlfn.XLOOKUP($A7,Inputs!$A:$A,Inputs!F:F,,0) -> 18424 | G7: =_xlfn.XLOOKUP($A7,Inputs!$A:$A,Inputs!G:G,,0) -> 17143 | H7: =_xlfn.XLOOKUP($A7,Inputs!$A:$A,Inputs!H:H,,0) -> 15818 | I7: =_xlfn.XLOOKUP($A7,Inputs!$A:$A,Inputs!I:I,,0) -> 15134 | J7: =_xlfn.XLOOKUP($A7,Inputs!$A:$A,Inputs!J:J,,0) -> 14182 | K7: =_xlfn.XLOOKUP($A7,Inputs!$A:$A,Inputs!K:K,,0) -> 13208 | L7: =_xlfn.XLOOKUP($A7,Inputs!$A:$A,Inputs!L:L,,0) -> 0 | M7: =_xlfn.XLOOKUP($A7,Inputs!$A:$A,Inputs!M:M,,0) -> 0
A8: % over sales | B8: =IFERROR(B7/B$5,"-") -> 0.12148717 | C8: =IFERROR(C7/C$5,"-") -> 0.12884769 | D8: =IFERROR(D7/D$5,"-") -> 0.13085793 | E8: =IFERROR(E7/E$5,"-") -> 0.12977479 | F8: =IFERROR(F7/F$5,"-") -> 0.13013505 | G8: =IFERROR(G7/G$5,"-") -> 0.13286572 | H8: =IFERROR(H7/H$5,"-") -> 0.13323899 | I8: =IFERROR(I7/I$5,"-") -> 0.13024208 | ... M8: =IFERROR(M7/M$5,"-") -> -
A9: Operating expenses | B9: =B5-B11 -> 219161 | C9: =C5-C11 -> 189221 | D9: =D5-D11 -> 161326 | E9: =E5-E11 -> 147966 | F9: =F5-F11 -> 137050 | G9: =G5-G11 -> 124902 | H9: =H5-H11 -> 115008 | I9: =I5-I11 -> 112521 | ... M9: =M5-M11 -> 0
A10: % over sales | B10: =IFERROR(B9/B$5,"-") -> 0.96566265 | C10: =IFERROR(C9/C$5,"-") -> 0.96576311 | D10: =IFERROR(D9/D$5,"-") -> 0.96740845 | E10: =IFERROR(E9/E$5,"-") -> 0.968979 | F10: =IFERROR(F9/F$5,"-") -> 0.9680313 | G10: =IFERROR(G9/G$5,"-") -> 0.96804495 | H10: =IFERROR(H9/H$5,"-") -> 0.96874131 | I10: =IFERROR(I9/I$5,"-") -> 0.9683474 | ... M10: =IFERROR(M9/M$5,"-") -> -
A11: Operating Income | B11: =_xlfn.XLOOKUP($A11,Inputs!$A:$A,Inputs!B:B,,0) -> 7793 | C11: =_xlfn.XLOOKUP($A11,Inputs!$A:$A,Inputs!C:C,,0) -> 6708 | D11: =_xlfn.XLOOKUP($A11,Inputs!$A:$A,Inputs!D:D,,0) -> 5435 | E11: =_xlfn.XLOOKUP($A11,Inputs!$A:$A,Inputs!E:E,,0) -> 4737 | F11: =_xlfn.XLOOKUP($A11,Inputs!$A:$A,Inputs!F:F,,0) -> 4526 | G11: =_xlfn.XLOOKUP($A11,Inputs!$A:$A,Inputs!G:G,,0) -> 4123 | H11: =_xlfn.XLOOKUP($A11,Inputs!$A:$A,Inputs!H:H,,0) -> 3711 | I11: =_xlfn.XLOOKUP($A11,Inputs!$A:$A,Inputs!I:I,,0) -> 3678 | J11: =_xlfn.XLOOKUP($A11,Inputs!$A:$A,Inputs!J:J,,0) -> 3258 | K11: =_xlfn.XLOOKUP($A11,Inputs!$A:$A,Inputs!K:K,,0) -> 3106 | L11: =_xlfn.XLOOKUP($A11,Inputs!$A:$A,Inputs!L:L,,0) -> 0 | M11: =_xlfn.XLOOKUP($A11,Inputs!$A:$A,Inputs!M:M,,0) -> 0
A12: Operating Margin | B12: =IFERROR(B11/B$5,"-") -> 0.034337355 | C12: =IFERROR(C11/C$5,"-") -> 0.034236892 | D12: =IFERROR(D11/D$5,"-") -> 0.032591553 | E12: =IFERROR(E11/E$5,"-") -> 0.031021002 | F12: =IFERROR(F11/F$5,"-") -> 0.031968695 | G12: =IFERROR(G11/G$5,"-") -> 0.031955047 | H12: =IFERROR(H11/H$5,"-") -> 0.031258686 | I12: =IFERROR(I11/I$5,"-") -> 0.031652596 | ... M12: =IFERROR(M11/M$5,"-") -> -
A13: Growth vs. Previous year | B13: =IFERROR(B12/C12-1,"-") -> 0.0029343426 | C13: =IFERROR(C12/D12-1,"-") -> 0.050483594 | D13: =IFERROR(D12/E12-1,"-") -> 0.050628656 | E13: =IFERROR(E12/F12-1,"-") -> -0.029644429 | F13: =IFERROR(F12/G12-1,"-") -> 0.00042709333 | G13: =IFERROR(G12/H12-1,"-") -> 0.022277359 | H13: =IFERROR(H12/I12-1,"-") -> -0.012444777 | I13: =IFERROR(I12/J12-1,"-") -> 0.094336529 | ... L13: =IFERROR(L12/M12-1,"-") -> - | M13: =IFERROR(M12/#REF!-1,"-") -> -
A14: Net Financial Cost | B14: =_xlfn.XLOOKUP($A14,Inputs!$A:$A,Inputs!B:B,,0) -> 97 | C14: =_xlfn.XLOOKUP($A14,Inputs!$A:$A,Inputs!C:C,,0) -> 130 | D14: =_xlfn.XLOOKUP($A14,Inputs!$A:$A,Inputs!D:D,,0) -> 71 | E14: =_xlfn.XLOOKUP($A14,Inputs!$A:$A,Inputs!E:E,,0) -> 24 | F14: =_xlfn.XLOOKUP($A14,Inputs!$A:$A,Inputs!F:F,,0) -> 84 | G14: =_xlfn.XLOOKUP($A14,Inputs!$A:$A,Inputs!G:G,,0) -> 84 | H14: =_xlfn.XLOOKUP($A14,Inputs!$A:$A,Inputs!H:H,,0) -> 92 | I14: =_xlfn.XLOOKUP($A14,Inputs!$A:$A,Inputs!I:I,,0) -> 74 | J14: =_xlfn.XLOOKUP($A14,Inputs!$A:$A,Inputs!J:J,,0) -> 61 | K14: =_xlfn.XLOOKUP($A14,Inputs!$A:$A,Inputs!K:K,,0) -> 55 | L14: =_xlfn.XLOOKUP($A14,Inputs!$A:$A,Inputs!L:L,,0) -> 0 | M14: =_xlfn.XLOOKUP($A14,Inputs!$A:$A,Inputs!M:M,,0) -> 0
A15: Other Expenses (Revenues) | B15: =_xlfn.XLOOKUP($A15,Inputs!$A:$A,Inputs!B:B,,0) -> 19653 | C15: =_xlfn.XLOOKUP($A15,Inputs!$A:$A,Inputs!C:C,,0) -> 18435 | D15: =_xlfn.XLOOKUP($A15,Inputs!$A:$A,Inputs!D:D,,0) -> 16384 | E15: =_xlfn.XLOOKUP($A15,Inputs!$A:$A,Inputs!E:E,,0) -> 15028 | F15: =_xlfn.XLOOKUP($A15,Inputs!$A:$A,Inputs!F:F,,0) -> 13898 | G15: =_xlfn.XLOOKUP($A15,Inputs!$A:$A,Inputs!G:G,,0) -> 13020 | H15: =_xlfn.XLOOKUP($A15,Inputs!$A:$A,Inputs!H:H,,0) -> 12107 | I15: =_xlfn.XLOOKUP($A15,Inputs!$A:$A,Inputs!I:I,,0) -> 11456 | J15: =_xlfn.XLOOKUP($A15,Inputs!$A:$A,Inputs!J:J,,0) -> 10924 | K15: =_xlfn.XLOOKUP($A15,Inputs!$A:$A,Inputs!K:K,,0) -> 10102 | L15: =_xlfn.XLOOKUP($A15,Inputs!$A:$A,Inputs!L:L,,0) -> 0 | M15: =_xlfn.XLOOKUP($A15,Inputs!$A:$A,Inputs!M:M,,0) -> 0
A16: EBIT | B16: =B7-B15 -> 7919 | C16: =C7-C15 -> 6810 | D16: =D7-D15 -> 5438 | E16: =E7-E15 -> 4789 | F16: =F7-F15 -> 4526 | G16: =G7-G15 -> 4123 | H16: =H7-H15 -> 3711 | I16: =I7-I15 -> 3678 | ... K16: =K7-K15 -> 3106 | L16: =L11-L15 -> 0 | M16: =M11-M15 -> 0
A17: Depreciation & Amortization | B17: =_xlfn.XLOOKUP($A17,Inputs!$A:$A,Inputs!B:B,,0) -> 1900 | C17: =_xlfn.XLOOKUP($A17,Inputs!$A:$A,Inputs!C:C,,0) -> 1781 | D17: =_xlfn.XLOOKUP($A17,Inputs!$A:$A,Inputs!D:D,,0) -> 1645 | E17: =_xlfn.XLOOKUP($A17,Inputs!$A:$A,Inputs!E:E,,0) -> 1492 | F17: =_xlfn.XLOOKUP($A17,Inputs!$A:$A,Inputs!F:F,,0) -> 1437 | G17: =_xlfn.XLOOKUP($A17,Inputs!$A:$A,Inputs!G:G,,0) -> 1370 | H17: =_xlfn.XLOOKUP($A17,Inputs!$A:$A,Inputs!H:H,,0) -> 1255 | I17: =_xlfn.XLOOKUP($A17,Inputs!$A:$A,Inputs!I:I,,0) -> 1127 | J17: =_xlfn.XLOOKUP($A17,Inputs!$A:$A,Inputs!J:J,,0) -> 1029 | K17: =_xlfn.XLOOKUP($A17,Inputs!$A:$A,Inputs!K:K,,0) -> 946 | L17: =_xlfn.XLOOKUP($A17,Inputs!$A:$A,Inputs!L:L,,0) -> 0 | M17: =_xlfn.XLOOKUP($A17,Inputs!$A:$A,Inputs!M:M,,0) -> 0
A18: Changes Net Working Capital | B18: =_xlfn.XLOOKUP($A18,Inputs!$A:$A,Inputs!B:B,,0) -> 1034 | C18: =_xlfn.XLOOKUP($A18,Inputs!$A:$A,Inputs!C:C,,0) -> -1378 | D18: =_xlfn.XLOOKUP($A18,Inputs!$A:$A,Inputs!D:D,,0) -> -2447 | E18: =_xlfn.XLOOKUP($A18,Inputs!$A:$A,Inputs!E:E,,0) -> -681 | F18: =_xlfn.XLOOKUP($A18,Inputs!$A:$A,Inputs!F:F,,0) -> -935 | G18: =_xlfn.XLOOKUP($A18,Inputs!$A:$A,Inputs!G:G,,0) -> -1885 | H18: =_xlfn.XLOOKUP($A18,Inputs!$A:$A,Inputs!H:H,,0) -> 910 | I18: =_xlfn.XLOOKUP($A18,Inputs!$A:$A,Inputs!I:I,,0) -> -727 | J18: =_xlfn.XLOOKUP($A18,Inputs!$A:$A,Inputs!J:J,,0) -> -628 | K18: =_xlfn.XLOOKUP($A18,Inputs!$A:$A,Inputs!K:K,,0) -> -3541 | L18: =_xlfn.XLOOKUP($A18,Inputs!$A:$A,Inputs!L:L,,0) -> 0 | M18: =_xlfn.XLOOKUP($A18,Inputs!$A:$A,Inputs!M:M,,0) -> 0
A19: EBITDA | B19: =B11+B15-B17 -> 25546 | C19: =C11+C15-C17 -> 23362 | D19: =D11+D15-D17 -> 20174 | E19: =E11+E15-E17 -> 18273 | F19: =F11+F15-F17 -> 16987 | G19: =G11+G15-G17 -> 15773 | H19: =H11+H15-H17 -> 14563 | I19: =I11+I15-I17 -> 14007 | ... K19: =K11+K15-K17 -> 12262 | L19: =L11-L15+L17 -> 0 | M19: =M11-M15+M17 -> 0
A20: EBITDA Margin | B20: =IFERROR(B19/B$5,"-") -> 0.11256025 | C20: =IFERROR(C19/C$5,"-") -> 0.11923707 | D20: =IFERROR(D19/D$5,"-") -> 0.12097553 | E20: =IFERROR(E19/E$5,"-") -> 0.11966366 | F20: =IFERROR(F19/F$5,"-") -> 0.11998503 | G20: =IFERROR(G19/G$5,"-") -> 0.12224763 | H20: =IFERROR(H19/H$5,"-") -> 0.12266781 | I20: =IFERROR(I19/I$5,"-") -> 0.12054321 | ... M20: =IFERROR(M19/M$5,"-") -> -
A21: Taxes | B21: =_xlfn.XLOOKUP($A21,Inputs!$A:$A,Inputs!B:B,,0) -> 1925 | C21: =_xlfn.XLOOKUP($A21,Inputs!$A:$A,Inputs!C:C,,0) -> 1601 | D21: =_xlfn.XLOOKUP($A21,Inputs!$A:$A,Inputs!D:D,,0) -> 1308 | E21: =_xlfn.XLOOKUP($A21,Inputs!$A:$A,Inputs!E:E,,0) -> 1061 | F21: =_xlfn.XLOOKUP($A21,Inputs!$A:$A,Inputs!F:F,,0) -> 1263 | G21: =_xlfn.XLOOKUP($A21,Inputs!$A:$A,Inputs!G:G,,0) -> 1325 | H21: =_xlfn.XLOOKUP($A21,Inputs!$A:$A,Inputs!H:H,,0) -> 1243 | I21: =_xlfn.XLOOKUP($A21,Inputs!$A:$A,Inputs!I:I,,0) -> 1195 | J21: =_xlfn.XLOOKUP($A21,Inputs!$A:$A,Inputs!J:J,,0) -> 1109 | K21: =_xlfn.XLOOKUP($A21,Inputs!$A:$A,Inputs!K:K,,0) -> 990 | L21: =_xlfn.XLOOKUP($A21,Inputs!$A:$A,Inputs!L:L,,0) -> 0 | M21: =_xlfn.XLOOKUP($A21,Inputs!$A:$A,Inputs!M:M,,0) -> 0
A22: % Tax | B22: =IFERROR(B21/B$5,"-") -> 0.008481895 | C22: =IFERROR(C21/C$5,"-") -> 0.0081713274 | D22: =IFERROR(D21/D$5,"-") -> 0.0078435605 | E22: =IFERROR(E21/E$5,"-") -> 0.0069481281 | F22: =IFERROR(F21/F$5,"-") -> 0.0089210036 | G22: =IFERROR(G21/G$5,"-") -> 0.010269328 | H22: =IFERROR(H21/H$5,"-") -> 0.010470102 | I22: =IFERROR(I21/I$5,"-") -> 0.010284082 | ... M22: =IFERROR(M21/M$5,"-") -> -
A23: Net Income | B23: =_xlfn.XLOOKUP($A23,Inputs!$A:$A,Inputs!B:B,,0) -> 5844 | C23: =_xlfn.XLOOKUP($A23,Inputs!$A:$A,Inputs!C:C,,0) -> 5007 | D23: =_xlfn.XLOOKUP($A23,Inputs!$A:$A,Inputs!D:D,,0) -> 4002 | E23: =_xlfn.XLOOKUP($A23,Inputs!$A:$A,Inputs!E:E,,0) -> 3659 | F23: =_xlfn.XLOOKUP($A23,Inputs!$A:$A,Inputs!F:F,,0) -> 3134 | G23: =_xlfn.XLOOKUP($A23,Inputs!$A:$A,Inputs!G:G,,0) -> 2679 | H23: =_xlfn.XLOOKUP($A23,Inputs!$A:$A,Inputs!H:H,,0) -> 2350 | I23: =_xlfn.XLOOKUP($A23,Inputs!$A:$A,Inputs!I:I,,0) -> 2377 | J23: =_xlfn.XLOOKUP($A23,Inputs!$A:$A,Inputs!J:J,,0) -> 2058 | K23: =_xlfn.XLOOKUP($A23,Inputs!$A:$A,Inputs!K:K,,0) -> 2039 | L23: =_xlfn.XLOOKUP($A23,Inputs!$A:$A,Inputs!L:L,,0) -> 0 | M23: =_xlfn.XLOOKUP($A23,Inputs!$A:$A,Inputs!M:M,,0) -> 0
A24: Net Income Margin | B24: =IFERROR(B23/B$5,"-") -> 0.025749711 | C24: =IFERROR(C23/C$5,"-") -> 0.025555176 | D24: =IFERROR(D23/D$5,"-") -> 0.023998417 | E24: =IFERROR(E23/E$5,"-") -> 0.023961546 | F24: =IFERROR(F23/F$5,"-") -> 0.02213652 | G24: =IFERROR(G23/G$5,"-") -> 0.020763418 | H24: =IFERROR(H23/H$5,"-") -> 0.019794641 | I24: =IFERROR(I23/I$5,"-") -> 0.020456286 | ... M24: =IFERROR(M23/M$5,"-") -> -
A25: Growth vs. Previous year | B25: =IFERROR(B24/C24-1,"-") -> 0.0076123835 | C25: =IFERROR(C24/D24-1,"-") -> 0.064869225 | D25: =IFERROR(D24/E24-1,"-") -> 0.0015387415 | E25: =IFERROR(E24/F24-1,"-") -> 0.082444121 | F25: =IFERROR(F24/G24-1,"-") -> 0.066130845 | G25: =IFERROR(G24/H24-1,"-") -> 0.048941368 | H25: =IFERROR(H24/I24-1,"-") -> -0.03234434 | I25: =IFERROR(I24/J24-1,"-") -> 0.1196288 | ... L25: =IFERROR(L24/M24-1,"-") -> - | M25: =IFERROR(M24/#REF!-1,"-") -> -
A26: Cash Generated | B26: =B39-C39 -> -1126 | C26: =C39-D39 -> -1130 | D26: =D39-E39 -> 3861 | E26: =E39-F39 -> 2185 | F26: =F39-G39 -> 1480 | G26: =G39-H39 -> 1050 | H26: =H39-I39 -> -1690 | I26: =I39-J39 -> -896 | ... M26: =M39-N39 -> 0
A27: Dividends | B27: =_xlfn.XLOOKUP($A27,Inputs!$A:$A,Inputs!B:B,,0) -> -1498 | C27: =_xlfn.XLOOKUP($A27,Inputs!$A:$A,Inputs!C:C,,0) -> -1318 | D27: =_xlfn.XLOOKUP($A27,Inputs!$A:$A,Inputs!D:D,,0) -> -1479 | E27: =_xlfn.XLOOKUP($A27,Inputs!$A:$A,Inputs!E:E,,0) -> -1038 | F27: =_xlfn.XLOOKUP($A27,Inputs!$A:$A,Inputs!F:F,,0) -> -689 | G27: =_xlfn.XLOOKUP($A27,Inputs!$A:$A,Inputs!G:G,,0) -> -804 | H27: =_xlfn.XLOOKUP($A27,Inputs!$A:$A,Inputs!H:H,,0) -> -736 | I27: =_xlfn.XLOOKUP($A27,Inputs!$A:$A,Inputs!I:I,,0) -> -664 | J27: =_xlfn.XLOOKUP($A27,Inputs!$A:$A,Inputs!J:J,,0) -> -584 | K27: =_xlfn.XLOOKUP($A27,Inputs!$A:$A,Inputs!K:K,,0) -> -511 | L27: =_xlfn.XLOOKUP($A27,Inputs!$A:$A,Inputs!L:L,,0) -> 0 | M27: =_xlfn.XLOOKUP($A27,Inputs!$A:$A,Inputs!M:M,,0) -> 0
A28: Share buyback | B28: =_xlfn.XLOOKUP($A28,Inputs!$A:$A,Inputs!B:B,,0) -> -802 | C28: =_xlfn.XLOOKUP($A28,Inputs!$A:$A,Inputs!C:C,,0) -> -808 | D28: =_xlfn.XLOOKUP($A28,Inputs!$A:$A,Inputs!D:D,,0) -> -526 | E28: =_xlfn.XLOOKUP($A28,Inputs!$A:$A,Inputs!E:E,,0) -> -519 | F28: =_xlfn.XLOOKUP($A28,Inputs!$A:$A,Inputs!F:F,,0) -> -545 | G28: =_xlfn.XLOOKUP($A28,Inputs!$A:$A,Inputs!G:G,,0) -> -671 | H28: =_xlfn.XLOOKUP($A28,Inputs!$A:$A,Inputs!H:H,,0) -> -706 | I28: =_xlfn.XLOOKUP($A28,Inputs!$A:$A,Inputs!I:I,,0) -> -659 | J28: =_xlfn.XLOOKUP($A28,Inputs!$A:$A,Inputs!J:J,,0) -> -498 | K28: =_xlfn.XLOOKUP($A28,Inputs!$A:$A,Inputs!K:K,,0) -> -157 | L28: =_xlfn.XLOOKUP($A28,Inputs!$A:$A,Inputs!L:L,,0) -> 0 | M28: =_xlfn.XLOOKUP($A28,Inputs!$A:$A,Inputs!M:M,,0) -> 0
A29: Net Cash Flow | B29: =SUM(B26:B28) -> -3426 | C29: =SUM(C26:C28) -> -3256 | D29: =SUM(D26:D28) -> 1856 | E29: =SUM(E26:E28) -> 628 | F29: =SUM(F26:F28) -> 246 | G29: =SUM(G26:G28) -> -425 | H29: =SUM(H26:H28) -> -3132 | I29: =SUM(I26:I28) -> -2219 | ... M29: =SUM(M26:M28) -> 0
A30: FNP'' | B30: =+B29-(B58-C29) -> -17588 | C30: =+C29-(C58-D29) -> -12807 | D30: =+D29-(D58-E29) -> -8602 | E30: =+E29-(E58-F29) -> -6370 | F30: =+F29-(F58-G29) -> -6756 | G30: =+G29-(G58-H29) -> -10216 | H30: =+H29-(H58-I29) -> -10512 | I30: =+I29-(I58-J29) -> -8245 | ... M30: =+M29-(M58-N29) -> 0
A31: FNP' | B31: =+B30+B33 -> -17585 | C31: =+C30+C33 -> -12706 | D31: =+D30+D33 -> -9621 | E31: =+E30+E33 -> -6207 | F31: =+F30+F33 -> -6730 | G31: =+G30+G33 -> -10084 | H31: =+H30+H33 -> -10238 | I31: =+I30+I33 -> -8359 | ... M31: =+M30+M33 -> 0
A32: Net Capex | B32: =_xlfn.XLOOKUP($A32,Inputs!$A:$A,Inputs!B:B,,0) -> -3891 | C32: =_xlfn.XLOOKUP($A32,Inputs!$A:$A,Inputs!C:C,,0) -> -3588 | D32: =_xlfn.XLOOKUP($A32,Inputs!$A:$A,Inputs!D:D,,0) -> -2810 | E32: =_xlfn.XLOOKUP($A32,Inputs!$A:$A,Inputs!E:E,,0) -> -2998 | F32: =_xlfn.XLOOKUP($A32,Inputs!$A:$A,Inputs!F:F,,0) -> -2969 | G32: =_xlfn.XLOOKUP($A32,Inputs!$A:$A,Inputs!G:G,,0) -> -2502 | H32: =_xlfn.XLOOKUP($A32,Inputs!$A:$A,Inputs!H:H,,0) -> -2649 | I32: =_xlfn.XLOOKUP($A32,Inputs!$A:$A,Inputs!I:I,,0) -> -2393 | J32: =_xlfn.XLOOKUP($A32,Inputs!$A:$A,Inputs!J:J,,0) -> -1993 | K32: =_xlfn.XLOOKUP($A32,Inputs!$A:$A,Inputs!K:K,,0) -> -2083 | L32: =_xlfn.XLOOKUP($A32,Inputs!$A:$A,Inputs!L:L,,0) -> 0 | M32: =_xlfn.XLOOKUP($A32,Inputs!$A:$A,Inputs!M:M,,0) -> 0
A33: Investments & Acquisitions | B33: =_xlfn.XLOOKUP($A33,Inputs!$A:$A,Inputs!B:B,,0) -> 3 | C33: =_xlfn.XLOOKUP($A33,Inputs!$A:$A,Inputs!C:C,,0) -> 101 | D33: =_xlfn.XLOOKUP($A33,Inputs!$A:$A,Inputs!D:D,,0) -> -1019 | E33: =_xlfn.XLOOKUP($A33,Inputs!$A:$A,Inputs!E:E,,0) -> 163 | F33: =_xlfn.XLOOKUP($A33,Inputs!$A:$A,Inputs!F:F,,0) -> 26 | G33: =_xlfn.XLOOKUP($A33,Inputs!$A:$A,Inputs!G:G,,0) -> 132 | H33: =_xlfn.XLOOKUP($A33,Inputs!$A:$A,Inputs!H:H,,0) -> 274 | I33: =_xlfn.XLOOKUP($A33,Inputs!$A:$A,Inputs!I:I,,0) -> -114 | J33: =_xlfn.XLOOKUP($A33,Inputs!$A:$A,Inputs!J:J,,0) -> -80 | K33: =_xlfn.XLOOKUP($A33,Inputs!$A:$A,Inputs!K:K,,0) -> -165 | L33: =_xlfn.XLOOKUP($A33,Inputs!$A:$A,Inputs!L:L,,0) -> 0 | M33: =_xlfn.XLOOKUP($A33,Inputs!$A:$A,Inputs!M:M,,0) -> 0
A34: Capex + Investments | B34: =+B32+B33 -> -3888 | C34: =+C32+C33 -> -3487 | D34: =+D32+D33 -> -3829 | E34: =+E32+E33 -> -2835 | F34: =+F32+F33 -> -2943 | G34: =+G32+G33 -> -2370 | H34: =+H32+H33 -> -2375 | I34: =+I32+I33 -> -2507 | ... M34: =+M32+M33 -> 0
A35: Dividends + Share Buyback | B35: =+B27+B28 -> -2300 | C35: =+C27+C28 -> -2126 | D35: =+D27+D28 -> -2005 | E35: =+E27+E28 -> -1557 | F35: =+F27+F28 -> -1234 | G35: =+G27+G28 -> -1475 | H35: =+H27+H28 -> -1442 | I35: =+I27+I28 -> -1323 | ... M35: =+M27+M28 -> 0
A36: Payout Ratio | B36: =-IFERROR(B35/B23,"-") -> 0.39356605 | C36: =-IFERROR(C35/C23,"-") -> 0.42460555 | D36: =-IFERROR(D35/D23,"-") -> 0.5009995 | E36: =-IFERROR(E35/E23,"-") -> 0.4255261 | F36: =-IFERROR(F35/F23,"-") -> 0.39374601 | G36: =-IFERROR(G35/G23,"-") -> 0.55057857 | H36: =-IFERROR(H35/H23,"-") -> 0.61361702 | I36: =-IFERROR(I35/I23,"-") -> 0.55658393 | ... K36: =-IFERROR(K35/K23,"-") -> 0.32761157 | L36: =IFERROR(L35/L23,"-") -> - | M36: =IFERROR(M35/M23,"-") -> -
A38: Assets
A39: Cash & Eq. | B39: =_xlfn.XLOOKUP($A39,Inputs!$A:$A,Inputs!B:B,,0) -> 11049 | C39: =_xlfn.XLOOKUP($A39,Inputs!$A:$A,Inputs!C:C,,0) -> 12175 | D39: =_xlfn.XLOOKUP($A39,Inputs!$A:$A,Inputs!D:D,,0) -> 13305 | E39: =_xlfn.XLOOKUP($A39,Inputs!$A:$A,Inputs!E:E,,0) -> 9444 | F39: =_xlfn.XLOOKUP($A39,Inputs!$A:$A,Inputs!F:F,,0) -> 7259 | G39: =_xlfn.XLOOKUP($A39,Inputs!$A:$A,Inputs!G:G,,0) -> 5779 | H39: =_xlfn.XLOOKUP($A39,Inputs!$A:$A,Inputs!H:H,,0) -> 4729 | I39: =_xlfn.XLOOKUP($A39,Inputs!$A:$A,Inputs!I:I,,0) -> 6419 | J39: =_xlfn.XLOOKUP($A39,Inputs!$A:$A,Inputs!J:J,,0) -> 7315 | K39: =_xlfn.XLOOKUP($A39,Inputs!$A:$A,Inputs!K:K,,0) -> 6124 | L39: =_xlfn.XLOOKUP($A39,Inputs!$A:$A,Inputs!L:L,,0) -> 0 | M39: =_xlfn.XLOOKUP($A39,Inputs!$A:$A,Inputs!M:M,,0) -> 0
A40: Accounts Receivable | B40: =_xlfn.XLOOKUP($A40,Inputs!$A:$A,Inputs!B:B,,0) -> 2241 | C40: =_xlfn.XLOOKUP($A40,Inputs!$A:$A,Inputs!C:C,,0) -> 1803 | D40: =_xlfn.XLOOKUP($A40,Inputs!$A:$A,Inputs!D:D,,0) -> 1550 | E40: =_xlfn.XLOOKUP($A40,Inputs!$A:$A,Inputs!E:E,,0) -> 1535 | F40: =_xlfn.XLOOKUP($A40,Inputs!$A:$A,Inputs!F:F,,0) -> 1669 | G40: =_xlfn.XLOOKUP($A40,Inputs!$A:$A,Inputs!G:G,,0) -> 1432 | H40: =_xlfn.XLOOKUP($A40,Inputs!$A:$A,Inputs!H:H,,0) -> 1252 | I40: =_xlfn.XLOOKUP($A40,Inputs!$A:$A,Inputs!I:I,,0) -> 1224 | J40: =_xlfn.XLOOKUP($A40,Inputs!$A:$A,Inputs!J:J,,0) -> 1148 | K40: =_xlfn.XLOOKUP($A40,Inputs!$A:$A,Inputs!K:K,,0) -> 1201 | L40: =_xlfn.XLOOKUP($A40,Inputs!$A:$A,Inputs!L:L,,0) -> 0 | M40: =_xlfn.XLOOKUP($A40,Inputs!$A:$A,Inputs!M:M,,0) -> 0
A41: Inventory | B41: =_xlfn.XLOOKUP($A41,Inputs!$A:$A,Inputs!B:B,,0) -> 17907 | C41: =_xlfn.XLOOKUP($A41,Inputs!$A:$A,Inputs!C:C,,0) -> 14215 | D41: =_xlfn.XLOOKUP($A41,Inputs!$A:$A,Inputs!D:D,,0) -> 12242 | E41: =_xlfn.XLOOKUP($A41,Inputs!$A:$A,Inputs!E:E,,0) -> 11395 | F41: =_xlfn.XLOOKUP($A41,Inputs!$A:$A,Inputs!F:F,,0) -> 11040 | G41: =_xlfn.XLOOKUP($A41,Inputs!$A:$A,Inputs!G:G,,0) -> 9834 | H41: =_xlfn.XLOOKUP($A41,Inputs!$A:$A,Inputs!H:H,,0) -> 8969 | I41: =_xlfn.XLOOKUP($A41,Inputs!$A:$A,Inputs!I:I,,0) -> 8908 | J41: =_xlfn.XLOOKUP($A41,Inputs!$A:$A,Inputs!J:J,,0) -> 8456 | K41: =_xlfn.XLOOKUP($A41,Inputs!$A:$A,Inputs!K:K,,0) -> 7894 | L41: =_xlfn.XLOOKUP($A41,Inputs!$A:$A,Inputs!L:L,,0) -> 0 | M41: =_xlfn.XLOOKUP($A41,Inputs!$A:$A,Inputs!M:M,,0) -> 0
A42: Property, Plant and Equipment | B42: =_xlfn.XLOOKUP($A42,Inputs!$A:$A,Inputs!B:B,,0) -> 44326 | C42: =_xlfn.XLOOKUP($A42,Inputs!$A:$A,Inputs!C:C,,0) -> 41258 | D42: =_xlfn.XLOOKUP($A42,Inputs!$A:$A,Inputs!D:D,,0) -> 38083 | E42: =_xlfn.XLOOKUP($A42,Inputs!$A:$A,Inputs!E:E,,0) -> 32626 | F42: =_xlfn.XLOOKUP($A42,Inputs!$A:$A,Inputs!F:F,,0) -> 30714 | G42: =_xlfn.XLOOKUP($A42,Inputs!$A:$A,Inputs!G:G,,0) -> 28341 | H42: =_xlfn.XLOOKUP($A42,Inputs!$A:$A,Inputs!H:H,,0) -> 26167 | I42: =_xlfn.XLOOKUP($A42,Inputs!$A:$A,Inputs!I:I,,0) -> 23664 | J42: =_xlfn.XLOOKUP($A42,Inputs!$A:$A,Inputs!J:J,,0) -> 22675 | K42: =_xlfn.XLOOKUP($A42,Inputs!$A:$A,Inputs!K:K,,0) -> 21022 | L42: =_xlfn.XLOOKUP($A42,Inputs!$A:$A,Inputs!L:L,,0) -> 0 | M42: =_xlfn.XLOOKUP($A42,Inputs!$A:$A,Inputs!M:M,,0) -> 0
A43: Other Assets | B43: =_xlfn.XLOOKUP($A43,Inputs!$A:$A,Inputs!B:B,,0) -> 2491 | C43: =_xlfn.XLOOKUP($A43,Inputs!$A:$A,Inputs!C:C,,0) -> 2253 | D43: =_xlfn.XLOOKUP($A43,Inputs!$A:$A,Inputs!D:D,,0) -> 1878 | E43: =_xlfn.XLOOKUP($A43,Inputs!$A:$A,Inputs!E:E,,0) -> 1695 | F43: =_xlfn.XLOOKUP($A43,Inputs!$A:$A,Inputs!F:F,,0) -> 865 | G43: =_xlfn.XLOOKUP($A43,Inputs!$A:$A,Inputs!G:G,,0) -> 887 | H43: =_xlfn.XLOOKUP($A43,Inputs!$A:$A,Inputs!H:H,,0) -> 968 | I43: =_xlfn.XLOOKUP($A43,Inputs!$A:$A,Inputs!I:I,,0) -> 846 | J43: =_xlfn.XLOOKUP($A43,Inputs!$A:$A,Inputs!J:J,,0) -> 1177 | K43: =_xlfn.XLOOKUP($A43,Inputs!$A:$A,Inputs!K:K,,0) -> 1121 | L43: =_xlfn.XLOOKUP($A43,Inputs!$A:$A,Inputs!L:L,,0) -> 0 | M43: =_xlfn.XLOOKUP($A43,Inputs!$A:$A,Inputs!M:M,,0) -> 0
A44: Total Assets | B44: =_xlfn.XLOOKUP($A44,Inputs!$A:$A,Inputs!B:B,,0) -> 64166 | C44: =_xlfn.XLOOKUP($A44,Inputs!$A:$A,Inputs!C:C,,0) -> 59268 | D44: =_xlfn.XLOOKUP($A44,Inputs!$A:$A,Inputs!D:D,,0) -> 55556 | E44: =_xlfn.XLOOKUP($A44,Inputs!$A:$A,Inputs!E:E,,0) -> 45400 | F44: =_xlfn.XLOOKUP($A44,Inputs!$A:$A,Inputs!F:F,,0) -> 40830 | G44: =_xlfn.XLOOKUP($A44,Inputs!$A:$A,Inputs!G:G,,0) -> 36347 | H44: =_xlfn.XLOOKUP($A44,Inputs!$A:$A,Inputs!H:H,,0) -> 33163 | I44: =_xlfn.XLOOKUP($A44,Inputs!$A:$A,Inputs!I:I,,0) -> 33017 | J44: =_xlfn.XLOOKUP($A44,Inputs!$A:$A,Inputs!J:J,,0) -> 33024 | K44: =_xlfn.XLOOKUP($A44,Inputs!$A:$A,Inputs!K:K,,0) -> 30283 | L44: =_xlfn.XLOOKUP($A44,Inputs!$A:$A,Inputs!L:L,,0) -> 0 | M44: =_xlfn.XLOOKUP($A44,Inputs!$A:$A,Inputs!M:M,,0) -> 0
A47: Liabilities
A48: Current Liabilities | B48: =_xlfn.XLOOKUP($A48,Inputs!$A:$A,Inputs!B:B,,0) -> 31998 | C48: =_xlfn.XLOOKUP($A48,Inputs!$A:$A,Inputs!C:C,,0) -> 29441 | D48: =_xlfn.XLOOKUP($A48,Inputs!$A:$A,Inputs!D:D,,0) -> 24844 | E48: =_xlfn.XLOOKUP($A48,Inputs!$A:$A,Inputs!E:E,,0) -> 23237 | F48: =_xlfn.XLOOKUP($A48,Inputs!$A:$A,Inputs!F:F,,0) -> 19926 | G48: =_xlfn.XLOOKUP($A48,Inputs!$A:$A,Inputs!G:G,,0) -> 17495 | H48: =_xlfn.XLOOKUP($A48,Inputs!$A:$A,Inputs!H:H,,0) -> 15575 | I48: =_xlfn.XLOOKUP($A48,Inputs!$A:$A,Inputs!I:I,,0) -> 16539 | J48: =_xlfn.XLOOKUP($A48,Inputs!$A:$A,Inputs!J:J,,0) -> 14412 | K48: =_xlfn.XLOOKUP($A48,Inputs!$A:$A,Inputs!K:K,,0) -> 13257 | L48: =_xlfn.XLOOKUP($A48,Inputs!$A:$A,Inputs!L:L,,0) -> 0 | M48: =_xlfn.XLOOKUP($A48,Inputs!$A:$A,Inputs!M:M,,0) -> 0
A49: Short-Term Debt | B49: =_xlfn.XLOOKUP($A49,Inputs!$A:$A,Inputs!B:B,,0) -> 73 | C49: =_xlfn.XLOOKUP($A49,Inputs!$A:$A,Inputs!C:C,,0) -> 799 | D49: =_xlfn.XLOOKUP($A49,Inputs!$A:$A,Inputs!D:D,,0) -> 95 | E49: =_xlfn.XLOOKUP($A49,Inputs!$A:$A,Inputs!E:E,,0) -> 1699 | F49: =_xlfn.XLOOKUP($A49,Inputs!$A:$A,Inputs!F:F,,0) -> 90 | G49: =_xlfn.XLOOKUP($A49,Inputs!$A:$A,Inputs!G:G,,0) -> 86 | H49: =_xlfn.XLOOKUP($A49,Inputs!$A:$A,Inputs!H:H,,0) -> 1100 | I49: =_xlfn.XLOOKUP($A49,Inputs!$A:$A,Inputs!I:I,,0) -> 1283 | J49: =_xlfn.XLOOKUP($A49,Inputs!$A:$A,Inputs!J:J,,0) -> 0 | K49: =_xlfn.XLOOKUP($A49,Inputs!$A:$A,Inputs!K:K,,0) -> 0 | L49: =_xlfn.XLOOKUP($A49,Inputs!$A:$A,Inputs!L:L,,0) -> 0 | M49: =_xlfn.XLOOKUP($A49,Inputs!$A:$A,Inputs!M:M,,0) -> 0
A50: Short-Term Leases | B50: =_xlfn.XLOOKUP($A50,Inputs!$A:$A,Inputs!B:B,,0) -> 484 | C50: =_xlfn.XLOOKUP($A50,Inputs!$A:$A,Inputs!C:C,,0) -> 294 | D50: =_xlfn.XLOOKUP($A50,Inputs!$A:$A,Inputs!D:D,,0) -> 262 | E50: =_xlfn.XLOOKUP($A50,Inputs!$A:$A,Inputs!E:E,,0) -> 51 | F50: 0 | G50: 0 | H50: 0 | I50: 0 | J50: 0 | K50: 0 | L50: =_xlfn.XLOOKUP($A50,Inputs!$A:$A,Inputs!L:L,,0) -> 0 | M50: =_xlfn.XLOOKUP($A50,Inputs!$A:$A,Inputs!M:M,,0) -> 0
A51: Other current liabilities | B51: =_xlfn.XLOOKUP($A51,Inputs!$A:$A,Inputs!B:B,,0) -> 13593 | C51: =_xlfn.XLOOKUP($A51,Inputs!$A:$A,Inputs!C:C,,0) -> 12070 | D51: =_xlfn.XLOOKUP($A51,Inputs!$A:$A,Inputs!D:D,,0) -> 10315 | E51: =_xlfn.XLOOKUP($A51,Inputs!$A:$A,Inputs!E:E,,0) -> 9808 | F51: =_xlfn.XLOOKUP($A51,Inputs!$A:$A,Inputs!F:F,,0) -> 8599 | G51: =_xlfn.XLOOKUP($A51,Inputs!$A:$A,Inputs!G:G,,0) -> 7801 | H51: =_xlfn.XLOOKUP($A51,Inputs!$A:$A,Inputs!H:H,,0) -> 6863 | I51: =_xlfn.XLOOKUP($A51,Inputs!$A:$A,Inputs!I:I,,0) -> 6245 | J51: =_xlfn.XLOOKUP($A51,Inputs!$A:$A,Inputs!J:J,,0) -> 5921 | K51: =_xlfn.XLOOKUP($A51,Inputs!$A:$A,Inputs!K:K,,0) -> 5385 | L51: =_xlfn.XLOOKUP($A51,Inputs!$A:$A,Inputs!L:L,,0) -> 0 | M51: =_xlfn.XLOOKUP($A51,Inputs!$A:$A,Inputs!M:M,,0) -> 0
A52: Non-current Liabilities | B52: =_xlfn.XLOOKUP($A52,Inputs!$A:$A,Inputs!B:B,,0) -> 11521 | C52: =_xlfn.XLOOKUP($A52,Inputs!$A:$A,Inputs!C:C,,0) -> 11749 | D52: =_xlfn.XLOOKUP($A52,Inputs!$A:$A,Inputs!D:D,,0) -> 12007 | E52: =_xlfn.XLOOKUP($A52,Inputs!$A:$A,Inputs!E:E,,0) -> 6579 | F52: =_xlfn.XLOOKUP($A52,Inputs!$A:$A,Inputs!F:F,,0) -> 7801 | G52: =_xlfn.XLOOKUP($A52,Inputs!$A:$A,Inputs!G:G,,0) -> 7773 | H52: =_xlfn.XLOOKUP($A52,Inputs!$A:$A,Inputs!H:H,,0) -> 5256 | I52: =_xlfn.XLOOKUP($A52,Inputs!$A:$A,Inputs!I:I,,0) -> 5635 | J52: =_xlfn.XLOOKUP($A52,Inputs!$A:$A,Inputs!J:J,,0) -> 6097 | K52: =_xlfn.XLOOKUP($A52,Inputs!$A:$A,Inputs!K:K,,0) -> 6014 | L52: =_xlfn.XLOOKUP($A52,Inputs!$A:$A,Inputs!L:L,,0) -> 0 | M52: =_xlfn.XLOOKUP($A52,Inputs!$A:$A,Inputs!M:M,,0) -> 0
A53: Long-Term Debt | B53: =_xlfn.XLOOKUP($A53,Inputs!$A:$A,Inputs!B:B,,0) -> 6484 | C53: =_xlfn.XLOOKUP($A53,Inputs!$A:$A,Inputs!C:C,,0) -> 6692 | D53: =_xlfn.XLOOKUP($A53,Inputs!$A:$A,Inputs!D:D,,0) -> 7514 | E53: =_xlfn.XLOOKUP($A53,Inputs!$A:$A,Inputs!E:E,,0) -> 5124 | F53: =_xlfn.XLOOKUP($A53,Inputs!$A:$A,Inputs!F:F,,0) -> 6487 | G53: =_xlfn.XLOOKUP($A53,Inputs!$A:$A,Inputs!G:G,,0) -> 6573 | H53: =_xlfn.XLOOKUP($A53,Inputs!$A:$A,Inputs!H:H,,0) -> 4061 | I53: =_xlfn.XLOOKUP($A53,Inputs!$A:$A,Inputs!I:I,,0) -> 4852 | J53: =_xlfn.XLOOKUP($A53,Inputs!$A:$A,Inputs!J:J,,0) -> 5093 | K53: =_xlfn.XLOOKUP($A53,Inputs!$A:$A,Inputs!K:K,,0) -> 4998 | L53: =_xlfn.XLOOKUP($A53,Inputs!$A:$A,Inputs!L:L,,0) -> 0 | M53: =_xlfn.XLOOKUP($A53,Inputs!$A:$A,Inputs!M:M,,0) -> 0
A54: Long-Term Leases | B54: =_xlfn.XLOOKUP($A54,Inputs!$A:$A,Inputs!B:B,,0) -> 3865 | C54: =_xlfn.XLOOKUP($A54,Inputs!$A:$A,Inputs!C:C,,0) -> 3622 | D54: =_xlfn.XLOOKUP($A54,Inputs!$A:$A,Inputs!D:D,,0) -> 3215 | E54: =_xlfn.XLOOKUP($A54,Inputs!$A:$A,Inputs!E:E,,0) -> 370 | F54: 0 | G54: 0 | H54: 0 | I54: 0 | J54: 0 | K54: 0 | L54: =_xlfn.XLOOKUP($A54,Inputs!$A:$A,Inputs!L:L,,0) -> 0 | M54: =_xlfn.XLOOKUP($A54,Inputs!$A:$A,Inputs!M:M,,0) -> 0
A55: Other non-current liabilities | B55: =_xlfn.XLOOKUP($A55,Inputs!$A:$A,Inputs!B:B,,0) -> 1172 | C55: =_xlfn.XLOOKUP($A55,Inputs!$A:$A,Inputs!C:C,,0) -> 1435 | D55: =_xlfn.XLOOKUP($A55,Inputs!$A:$A,Inputs!D:D,,0) -> 1278 | E55: =_xlfn.XLOOKUP($A55,Inputs!$A:$A,Inputs!E:E,,0) -> 1085 | F55: =_xlfn.XLOOKUP($A55,Inputs!$A:$A,Inputs!F:F,,0) -> 1314 | G55: =_xlfn.XLOOKUP($A55,Inputs!$A:$A,Inputs!G:G,,0) -> 1200 | H55: =_xlfn.XLOOKUP($A55,Inputs!$A:$A,Inputs!H:H,,0) -> 1195 | I55: =_xlfn.XLOOKUP($A55,Inputs!$A:$A,Inputs!I:I,,0) -> 783 | J55: =_xlfn.XLOOKUP($A55,Inputs!$A:$A,Inputs!J:J,,0) -> 1004 | K55: =_xlfn.XLOOKUP($A55,Inputs!$A:$A,Inputs!K:K,,0) -> 1016 | L55: =_xlfn.XLOOKUP($A55,Inputs!$A:$A,Inputs!L:L,,0) -> 0 | M55: =_xlfn.XLOOKUP($A55,Inputs!$A:$A,Inputs!M:M,,0) -> 0
A56: Total Liabilities | B56: =_xlfn.XLOOKUP($A56,Inputs!$A:$A,Inputs!B:B,,0) -> 43519 | C56: =_xlfn.XLOOKUP($A56,Inputs!$A:$A,Inputs!C:C,,0) -> 41190 | D56: =_xlfn.XLOOKUP($A56,Inputs!$A:$A,Inputs!D:D,,0) -> 36851 | E56: =_xlfn.XLOOKUP($A56,Inputs!$A:$A,Inputs!E:E,,0) -> 29816 | F56: =_xlfn.XLOOKUP($A56,Inputs!$A:$A,Inputs!F:F,,0) -> 27727 | G56: =_xlfn.XLOOKUP($A56,Inputs!$A:$A,Inputs!G:G,,0) -> 25268 | H56: =_xlfn.XLOOKUP($A56,Inputs!$A:$A,Inputs!H:H,,0) -> 20831 | I56: =_xlfn.XLOOKUP($A56,Inputs!$A:$A,Inputs!I:I,,0) -> 22174 | J56: =_xlfn.XLOOKUP($A56,Inputs!$A:$A,Inputs!J:J,,0) -> 20509 | K56: =_xlfn.XLOOKUP($A56,Inputs!$A:$A,Inputs!K:K,,0) -> 19271 | L56: =_xlfn.XLOOKUP($A56,Inputs!$A:$A,Inputs!L:L,,0) -> 0 | M56: =_xlfn.XLOOKUP($A56,Inputs!$A:$A,Inputs!M:M,,0) -> 0
A58: Total Debt | B58: =B49+B53+B50+B54 -> 10906 | C58: =C49+C53+C50+C54 -> 11407 | D58: =D49+D53+D50+D54 -> 11086 | E58: =E49+E53+E50+E54 -> 7244 | F58: =F49+F53+F50+F54 -> 6577 | G58: =G49+G53+G50+G54 -> 6659 | H58: =H49+H53+H50+H54 -> 5161 | I58: =I49+I53+I50+I54 -> 6135 | ... M58: =M49+M53+M50+M54 -> 0
A59: Debt/Assets | B59: =IFERROR(B58/B44,"-") -> 0.1699654 | C59: =IFERROR(C58/C44,"-") -> 0.19246474 | D59: =IFERROR(D58/D44,"-") -> 0.1995464 | E59: =IFERROR(E58/E44,"-") -> 0.15955947 | F59: =IFERROR(F58/F44,"-") -> 0.16108254 | G59: =IFERROR(G58/G44,"-") -> 0.18320632 | H59: =IFERROR(H58/H44,"-") -> 0.15562525 | I59: =IFERROR(I58/I44,"-") -> 0.18581337 | ... M59: =IFERROR(M58/M44,"-") -> -
A60: Net Debt | B60: =B58-B39 -> -143 | C60: =C58-C39 -> -768 | D60: =D58-D39 -> -2219 | E60: =E58-E39 -> -2200 | F60: =F58-F39 -> -682 | G60: =G58-G39 -> 880 | H60: =H58-H39 -> 432 | I60: =I58-I39 -> -284 | ... M60: =M58-M39 -> 0
A62: Minority Interest | B62: =_xlfn.XLOOKUP($A62,Inputs!$A:$A,Inputs!B:B,,0) -> 5 | C62: =_xlfn.XLOOKUP($A62,Inputs!$A:$A,Inputs!C:C,,0) -> 514 | D62: =_xlfn.XLOOKUP($A62,Inputs!$A:$A,Inputs!D:D,,0) -> 421 | E62: =_xlfn.XLOOKUP($A62,Inputs!$A:$A,Inputs!E:E,,0) -> 341 | F62: =_xlfn.XLOOKUP($A62,Inputs!$A:$A,Inputs!F:F,,0) -> 304 | G62: =_xlfn.XLOOKUP($A62,Inputs!$A:$A,Inputs!G:G,,0) -> 301 | H62: =_xlfn.XLOOKUP($A62,Inputs!$A:$A,Inputs!H:H,,0) -> 253 | I62: =_xlfn.XLOOKUP($A62,Inputs!$A:$A,Inputs!I:I,,0) -> 226 | J62: =_xlfn.XLOOKUP($A62,Inputs!$A:$A,Inputs!J:J,,0) -> 212 | K62: =_xlfn.XLOOKUP($A62,Inputs!$A:$A,Inputs!K:K,,0) -> 179 | L62: =_xlfn.XLOOKUP($A62,Inputs!$A:$A,Inputs!L:L,,0) -> 0 | M62: =_xlfn.XLOOKUP($A62,Inputs!$A:$A,Inputs!M:M,,0) -> 0
A64: Shareholder's Equity | B64: =_xlfn.XLOOKUP($A64,Inputs!$A:$A,Inputs!B:B,,0) -> 20642 | C64: =_xlfn.XLOOKUP($A64,Inputs!$A:$A,Inputs!C:C,,0) -> 17564 | D64: =_xlfn.XLOOKUP($A64,Inputs!$A:$A,Inputs!D:D,,0) -> 18284 | E64: =_xlfn.XLOOKUP($A64,Inputs!$A:$A,Inputs!E:E,,0) -> 15243 | F64: =_xlfn.XLOOKUP($A64,Inputs!$A:$A,Inputs!F:F,,0) -> 12799 | G64: =_xlfn.XLOOKUP($A64,Inputs!$A:$A,Inputs!G:G,,0) -> 10778 | H64: =_xlfn.XLOOKUP($A64,Inputs!$A:$A,Inputs!H:H,,0) -> 12079 | I64: =_xlfn.XLOOKUP($A64,Inputs!$A:$A,Inputs!I:I,,0) -> 10617 | J64: =_xlfn.XLOOKUP($A64,Inputs!$A:$A,Inputs!J:J,,0) -> 12303 | K64: =_xlfn.XLOOKUP($A64,Inputs!$A:$A,Inputs!K:K,,0) -> 10833 | L64: =_xlfn.XLOOKUP($A64,Inputs!$A:$A,Inputs!L:L,,0) -> 0 | M64: =_xlfn.XLOOKUP($A64,Inputs!$A:$A,Inputs!M:M,,0) -> 0
A66: Cash Flow
A67: Operating CF | B67: =_xlfn.XLOOKUP($A67,Inputs!$A:$A,Inputs!B:B,,0) -> 7392 | C67: =_xlfn.XLOOKUP($A67,Inputs!$A:$A,Inputs!C:C,,0) -> 8958 | D67: =_xlfn.XLOOKUP($A67,Inputs!$A:$A,Inputs!D:D,,0) -> 8861 | E67: =_xlfn.XLOOKUP($A67,Inputs!$A:$A,Inputs!E:E,,0) -> 6356 | F67: =_xlfn.XLOOKUP($A67,Inputs!$A:$A,Inputs!F:F,,0) -> 5774 | G67: =_xlfn.XLOOKUP($A67,Inputs!$A:$A,Inputs!G:G,,0) -> 6726 | H67: =_xlfn.XLOOKUP($A67,Inputs!$A:$A,Inputs!H:H,,0) -> 3292 | I67: =_xlfn.XLOOKUP($A67,Inputs!$A:$A,Inputs!I:I,,0) -> 4285 | J67: =_xlfn.XLOOKUP($A67,Inputs!$A:$A,Inputs!J:J,,0) -> 3984 | K67: =_xlfn.XLOOKUP($A67,Inputs!$A:$A,Inputs!K:K,,0) -> 3437 | L67: =_xlfn.XLOOKUP($A67,Inputs!$A:$A,Inputs!L:L,,0) -> 0 | M67: =_xlfn.XLOOKUP($A67,Inputs!$A:$A,Inputs!M:M,,0) -> 0
A68: Investing CF | B68: =_xlfn.XLOOKUP($A68,Inputs!$A:$A,Inputs!B:B,,0) -> -3915 | C68: =_xlfn.XLOOKUP($A68,Inputs!$A:$A,Inputs!C:C,,0) -> -3535 | D68: =_xlfn.XLOOKUP($A68,Inputs!$A:$A,Inputs!D:D,,0) -> -3891 | E68: =_xlfn.XLOOKUP($A68,Inputs!$A:$A,Inputs!E:E,,0) -> -2865 | F68: =_xlfn.XLOOKUP($A68,Inputs!$A:$A,Inputs!F:F,,0) -> -2947 | G68: =_xlfn.XLOOKUP($A68,Inputs!$A:$A,Inputs!G:G,,0) -> -2366 | H68: =_xlfn.XLOOKUP($A68,Inputs!$A:$A,Inputs!H:H,,0) -> -2345 | I68: =_xlfn.XLOOKUP($A68,Inputs!$A:$A,Inputs!I:I,,0) -> -2480 | J68: =_xlfn.XLOOKUP($A68,Inputs!$A:$A,Inputs!J:J,,0) -> -2093 | K68: =_xlfn.XLOOKUP($A68,Inputs!$A:$A,Inputs!K:K,,0) -> -2251 | L68: =_xlfn.XLOOKUP($A68,Inputs!$A:$A,Inputs!L:L,,0) -> 0 | M68: =_xlfn.XLOOKUP($A68,Inputs!$A:$A,Inputs!M:M,,0) -> 0
A69: Net Capex | B69: =_xlfn.XLOOKUP($A69,Inputs!$A:$A,Inputs!B:B,,0) -> -3891 | C69: =_xlfn.XLOOKUP($A69,Inputs!$A:$A,Inputs!C:C,,0) -> -3588 | D69: =_xlfn.XLOOKUP($A69,Inputs!$A:$A,Inputs!D:D,,0) -> -2810 | E69: =_xlfn.XLOOKUP($A69,Inputs!$A:$A,Inputs!E:E,,0) -> -2998 | F69: =_xlfn.XLOOKUP($A69,Inputs!$A:$A,Inputs!F:F,,0) -> -2969 | G69: =_xlfn.XLOOKUP($A69,Inputs!$A:$A,Inputs!G:G,,0) -> -2502 | H69: =_xlfn.XLOOKUP($A69,Inputs!$A:$A,Inputs!H:H,,0) -> -2649 | I69: =_xlfn.XLOOKUP($A69,Inputs!$A:$A,Inputs!I:I,,0) -> -2393 | J69: =_xlfn.XLOOKUP($A69,Inputs!$A:$A,Inputs!J:J,,0) -> -1993 | K69: =_xlfn.XLOOKUP($A69,Inputs!$A:$A,Inputs!K:K,,0) -> -2083 | L69: =_xlfn.XLOOKUP($A69,Inputs!$A:$A,Inputs!L:L,,0) -> 0 | M69: =_xlfn.XLOOKUP($A69,Inputs!$A:$A,Inputs!M:M,,0) -> 0
A70: Investments & Acquisitions | B70: =_xlfn.XLOOKUP($A70,Inputs!$A:$A,Inputs!B:B,,0) -> 3 | C70: =_xlfn.XLOOKUP($A70,Inputs!$A:$A,Inputs!C:C,,0) -> 101 | D70: =_xlfn.XLOOKUP($A70,Inputs!$A:$A,Inputs!D:D,,0) -> -1019 | E70: =_xlfn.XLOOKUP($A70,Inputs!$A:$A,Inputs!E:E,,0) -> 163 | F70: =_xlfn.XLOOKUP($A70,Inputs!$A:$A,Inputs!F:F,,0) -> 26 | G70: =_xlfn.XLOOKUP($A70,Inputs!$A:$A,Inputs!G:G,,0) -> 132 | H70: =_xlfn.XLOOKUP($A70,Inputs!$A:$A,Inputs!H:H,,0) -> 274 | I70: =_xlfn.XLOOKUP($A70,Inputs!$A:$A,Inputs!I:I,,0) -> -114 | J70: =_xlfn.XLOOKUP($A70,Inputs!$A:$A,Inputs!J:J,,0) -> -80 | K70: =_xlfn.XLOOKUP($A70,Inputs!$A:$A,Inputs!K:K,,0) -> -165 | L70: =_xlfn.XLOOKUP($A70,Inputs!$A:$A,Inputs!L:L,,0) -> 0 | M70: =_xlfn.XLOOKUP($A70,Inputs!$A:$A,Inputs!M:M,,0) -> 0
A71: Financing CF | B71: =_xlfn.XLOOKUP($A71,Inputs!$A:$A,Inputs!B:B,,0) -> -3890 | C71: =_xlfn.XLOOKUP($A71,Inputs!$A:$A,Inputs!C:C,,0) -> -4283 | D71: =_xlfn.XLOOKUP($A71,Inputs!$A:$A,Inputs!D:D,,0) -> -6488 | E71: =_xlfn.XLOOKUP($A71,Inputs!$A:$A,Inputs!E:E,,0) -> -1147 | F71: =_xlfn.XLOOKUP($A71,Inputs!$A:$A,Inputs!F:F,,0) -> -1147 | G71: =_xlfn.XLOOKUP($A71,Inputs!$A:$A,Inputs!G:G,,0) -> -1281 | H71: =_xlfn.XLOOKUP($A71,Inputs!$A:$A,Inputs!H:H,,0) -> -3218 | I71: =_xlfn.XLOOKUP($A71,Inputs!$A:$A,Inputs!I:I,,0) -> -2419 | J71: =_xlfn.XLOOKUP($A71,Inputs!$A:$A,Inputs!J:J,,0) -> -2324 | K71: =_xlfn.XLOOKUP($A71,Inputs!$A:$A,Inputs!K:K,,0) -> -786 | L71: =_xlfn.XLOOKUP($A71,Inputs!$A:$A,Inputs!L:L,,0) -> 0 | M71: =_xlfn.XLOOKUP($A71,Inputs!$A:$A,Inputs!M:M,,0) -> 0
A72: Dividends | B72: =_xlfn.XLOOKUP($A72,Inputs!$A:$A,Inputs!B:B,,0) -> -1498 | C72: =_xlfn.XLOOKUP($A72,Inputs!$A:$A,Inputs!C:C,,0) -> -1318 | D72: =_xlfn.XLOOKUP($A72,Inputs!$A:$A,Inputs!D:D,,0) -> -1479 | E72: =_xlfn.XLOOKUP($A72,Inputs!$A:$A,Inputs!E:E,,0) -> -1038 | F72: =_xlfn.XLOOKUP($A72,Inputs!$A:$A,Inputs!F:F,,0) -> -689 | G72: =_xlfn.XLOOKUP($A72,Inputs!$A:$A,Inputs!G:G,,0) -> -804 | H72: =_xlfn.XLOOKUP($A72,Inputs!$A:$A,Inputs!H:H,,0) -> -736 | I72: =_xlfn.XLOOKUP($A72,Inputs!$A:$A,Inputs!I:I,,0) -> -664 | J72: =_xlfn.XLOOKUP($A72,Inputs!$A:$A,Inputs!J:J,,0) -> -584 | K72: =_xlfn.XLOOKUP($A72,Inputs!$A:$A,Inputs!K:K,,0) -> -511 | L72: =_xlfn.XLOOKUP($A72,Inputs!$A:$A,Inputs!L:L,,0) -> 0 | M72: =_xlfn.XLOOKUP($A72,Inputs!$A:$A,Inputs!M:M,,0) -> 0
A73: Share buyback | B73: =_xlfn.XLOOKUP($A73,Inputs!$A:$A,Inputs!B:B,,0) -> -802 | C73: =_xlfn.XLOOKUP($A73,Inputs!$A:$A,Inputs!C:C,,0) -> -808 | D73: =_xlfn.XLOOKUP($A73,Inputs!$A:$A,Inputs!D:D,,0) -> -526 | E73: =_xlfn.XLOOKUP($A73,Inputs!$A:$A,Inputs!E:E,,0) -> -519 | F73: =_xlfn.XLOOKUP($A73,Inputs!$A:$A,Inputs!F:F,,0) -> -545 | G73: =_xlfn.XLOOKUP($A73,Inputs!$A:$A,Inputs!G:G,,0) -> -671 | H73: =_xlfn.XLOOKUP($A73,Inputs!$A:$A,Inputs!H:H,,0) -> -706 | I73: =_xlfn.XLOOKUP($A73,Inputs!$A:$A,Inputs!I:I,,0) -> -659 | J73: =_xlfn.XLOOKUP($A73,Inputs!$A:$A,Inputs!J:J,,0) -> -498 | K73: =_xlfn.XLOOKUP($A73,Inputs!$A:$A,Inputs!K:K,,0) -> -157 | L73: =_xlfn.XLOOKUP($A73,Inputs!$A:$A,Inputs!L:L,,0) -> 0 | M73: =_xlfn.XLOOKUP($A73,Inputs!$A:$A,Inputs!M:M,,0) -> 0
A74: FX | B74: =_xlfn.XLOOKUP($A74,Inputs!$A:$A,Inputs!B:B,,0) -> -249 | C74: =_xlfn.XLOOKUP($A74,Inputs!$A:$A,Inputs!C:C,,0) -> 46 | D74: =_xlfn.XLOOKUP($A74,Inputs!$A:$A,Inputs!D:D,,0) -> 70 | E74: =_xlfn.XLOOKUP($A74,Inputs!$A:$A,Inputs!E:E,,0) -> -15 | F74: =_xlfn.XLOOKUP($A74,Inputs!$A:$A,Inputs!F:F,,0) -> -37 | G74: =_xlfn.XLOOKUP($A74,Inputs!$A:$A,Inputs!G:G,,0) -> 25 | H74: =_xlfn.XLOOKUP($A74,Inputs!$A:$A,Inputs!H:H,,0) -> 50 | I74: =_xlfn.XLOOKUP($A74,Inputs!$A:$A,Inputs!I:I,,0) -> -418 | J74: =_xlfn.XLOOKUP($A74,Inputs!$A:$A,Inputs!J:J,,0) -> -11 | K74: =_xlfn.XLOOKUP($A74,Inputs!$A:$A,Inputs!K:K,,0) -> -114 | L74: =_xlfn.XLOOKUP($A74,Inputs!$A:$A,Inputs!L:L,,0) -> 0 | M74: =_xlfn.XLOOKUP($A74,Inputs!$A:$A,Inputs!M:M,,0) -> 0
A75: Changes in cash | B75: =_xlfn.XLOOKUP($A75,Inputs!$A:$A,Inputs!B:B,,0) -> -662 | C75: =_xlfn.XLOOKUP($A75,Inputs!$A:$A,Inputs!C:C,,0) -> 1186 | D75: =_xlfn.XLOOKUP($A75,Inputs!$A:$A,Inputs!D:D,,0) -> -1448 | E75: =_xlfn.XLOOKUP($A75,Inputs!$A:$A,Inputs!E:E,,0) -> 2329 | F75: =_xlfn.XLOOKUP($A75,Inputs!$A:$A,Inputs!F:F,,0) -> 1643 | G75: =_xlfn.XLOOKUP($A75,Inputs!$A:$A,Inputs!G:G,,0) -> 3104 | H75: =_xlfn.XLOOKUP($A75,Inputs!$A:$A,Inputs!H:H,,0) -> -2221 | I75: =_xlfn.XLOOKUP($A75,Inputs!$A:$A,Inputs!I:I,,0) -> -1032 | J75: =_xlfn.XLOOKUP($A75,Inputs!$A:$A,Inputs!J:J,,0) -> -444 | K75: =_xlfn.XLOOKUP($A75,Inputs!$A:$A,Inputs!K:K,,0) -> 286 | L75: =_xlfn.XLOOKUP($A75,Inputs!$A:$A,Inputs!L:L,,0) -> 0 | M75: =_xlfn.XLOOKUP($A75,Inputs!$A:$A,Inputs!M:M,,0) -> 0
A77: Other Data
A78: Number of employees | B78: =_xlfn.XLOOKUP($A78,Inputs!$A:$A,Inputs!B:B,,0) -> 304000 | C78: =_xlfn.XLOOKUP($A78,Inputs!$A:$A,Inputs!C:C,,0) -> 10-K | D78: =_xlfn.XLOOKUP($A78,Inputs!$A:$A,Inputs!D:D,,0) -> 0 | E78: =_xlfn.XLOOKUP($A78,Inputs!$A:$A,Inputs!E:E,,0) -> 0 | F78: =_xlfn.XLOOKUP($A78,Inputs!$A:$A,Inputs!F:F,,0) -> 0 | G78: =_xlfn.XLOOKUP($A78,Inputs!$A:$A,Inputs!G:G,,0) -> 0 | H78: =_xlfn.XLOOKUP($A78,Inputs!$A:$A,Inputs!H:H,,0) -> 0 | I78: =_xlfn.XLOOKUP($A78,Inputs!$A:$A,Inputs!I:I,,0) -> 0 | J78: =_xlfn.XLOOKUP($A78,Inputs!$A:$A,Inputs!J:J,,0) -> 0 | K78: =_xlfn.XLOOKUP($A78,Inputs!$A:$A,Inputs!K:K,,0) -> 0 | L78: =_xlfn.XLOOKUP($A78,Inputs!$A:$A,Inputs!L:L,,0) -> 0 | M78: =_xlfn.XLOOKUP($A78,Inputs!$A:$A,Inputs!M:M,,0) -> 0
A79: Shares Outstanding | B79: =_xlfn.XLOOKUP($A79,Inputs!$A:$A,Inputs!B:B,,0) -> #N/A | C79: =_xlfn.XLOOKUP($A79,Inputs!$A:$A,Inputs!C:C,,0) -> #N/A | D79: =_xlfn.XLOOKUP($A79,Inputs!$A:$A,Inputs!D:D,,0) -> #N/A | E79: =_xlfn.XLOOKUP($A79,Inputs!$A:$A,Inputs!E:E,,0) -> #N/A | F79: =_xlfn.XLOOKUP($A79,Inputs!$A:$A,Inputs!F:F,,0) -> #N/A | G79: =_xlfn.XLOOKUP($A79,Inputs!$A:$A,Inputs!G:G,,0) -> #N/A | H79: =_xlfn.XLOOKUP($A79,Inputs!$A:$A,Inputs!H:H,,0) -> #N/A | I79: =_xlfn.XLOOKUP($A79,Inputs!$A:$A,Inputs!I:I,,0) -> #N/A | J79: =_xlfn.XLOOKUP($A79,Inputs!$A:$A,Inputs!J:J,,0) -> #N/A | K79: =_xlfn.XLOOKUP($A79,Inputs!$A:$A,Inputs!K:K,,0) -> #N/A | L79: =_xlfn.XLOOKUP($A79,Inputs!$A:$A,Inputs!L:L,,0) -> #N/A | M79: =_xlfn.XLOOKUP($A79,Inputs!$A:$A,Inputs!M:M,,0) -> #N/A
A80: Float | B80: =_xlfn.XLOOKUP($A80,Inputs!$A:$A,Inputs!B:B,,0) -> 0.99738238 | C80: =_xlfn.XLOOKUP($A80,Inputs!$A:$A,Inputs!C:C,,0) -> Yahoo finance | D80: =_xlfn.XLOOKUP($A80,Inputs!$A:$A,Inputs!D:D,,0) -> 0 | E80: =_xlfn.XLOOKUP($A80,Inputs!$A:$A,Inputs!E:E,,0) -> 0 | F80: =_xlfn.XLOOKUP($A80,Inputs!$A:$A,Inputs!F:F,,0) -> 0 | G80: =_xlfn.XLOOKUP($A80,Inputs!$A:$A,Inputs!G:G,,0) -> 0 | H80: =_xlfn.XLOOKUP($A80,Inputs!$A:$A,Inputs!H:H,,0) -> 0 | I80: =_xlfn.XLOOKUP($A80,Inputs!$A:$A,Inputs!I:I,,0) -> 0 | J80: =_xlfn.XLOOKUP($A80,Inputs!$A:$A,Inputs!J:J,,0) -> 0 | K80: =_xlfn.XLOOKUP($A80,Inputs!$A:$A,Inputs!K:K,,0) -> 0 | L80: =_xlfn.XLOOKUP($A80,Inputs!$A:$A,Inputs!L:L,,0) -> 0 | M80: =_xlfn.XLOOKUP($A80,Inputs!$A:$A,Inputs!M:M,,0) -> 0
A81: Insiders Own | B81: =_xlfn.XLOOKUP($A81,Inputs!$A:$A,Inputs!B:B,,0) -> 0.002 | C81: =_xlfn.XLOOKUP($A81,Inputs!$A:$A,Inputs!C:C,,0) -> Yahoo finance | D81: =_xlfn.XLOOKUP($A81,Inputs!$A:$A,Inputs!D:D,,0) -> 0 | E81: =_xlfn.XLOOKUP($A81,Inputs!$A:$A,Inputs!E:E,,0) -> 0 | F81: =_xlfn.XLOOKUP($A81,Inputs!$A:$A,Inputs!F:F,,0) -> 0 | G81: =_xlfn.XLOOKUP($A81,Inputs!$A:$A,Inputs!G:G,,0) -> 0 | H81: =_xlfn.XLOOKUP($A81,Inputs!$A:$A,Inputs!H:H,,0) -> 0 | I81: =_xlfn.XLOOKUP($A81,Inputs!$A:$A,Inputs!I:I,,0) -> 0 | J81: =_xlfn.XLOOKUP($A81,Inputs!$A:$A,Inputs!J:J,,0) -> 0 | K81: =_xlfn.XLOOKUP($A81,Inputs!$A:$A,Inputs!K:K,,0) -> 0 | L81: =_xlfn.XLOOKUP($A81,Inputs!$A:$A,Inputs!L:L,,0) -> 0 | M81: =_xlfn.XLOOKUP($A81,Inputs!$A:$A,Inputs!M:M,,0) -> 0
A82: Fitch/ S&P Rating | B82: =_xlfn.XLOOKUP($A82,Inputs!$A:$A,Inputs!B:B,,0) -> 0.79 | C82: =_xlfn.XLOOKUP($A82,Inputs!$A:$A,Inputs!C:C,,0) -> 10-K | D82: =_xlfn.XLOOKUP($A82,Inputs!$A:$A,Inputs!D:D,,0) -> 0 | E82: =_xlfn.XLOOKUP($A82,Inputs!$A:$A,Inputs!E:E,,0) -> 0 | F82: =_xlfn.XLOOKUP($A82,Inputs!$A:$A,Inputs!F:F,,0) -> 0 | G82: =_xlfn.XLOOKUP($A82,Inputs!$A:$A,Inputs!G:G,,0) -> 0 | H82: =_xlfn.XLOOKUP($A82,Inputs!$A:$A,Inputs!H:H,,0) -> 0 | I82: =_xlfn.XLOOKUP($A82,Inputs!$A:$A,Inputs!I:I,,0) -> 0 | J82: =_xlfn.XLOOKUP($A82,Inputs!$A:$A,Inputs!J:J,,0) -> 0 | K82: =_xlfn.XLOOKUP($A82,Inputs!$A:$A,Inputs!K:K,,0) -> 0 | L82: =_xlfn.XLOOKUP($A82,Inputs!$A:$A,Inputs!L:L,,0) -> 0 | M82: =_xlfn.XLOOKUP($A82,Inputs!$A:$A,Inputs!M:M,,0) -> 0
A83: Dividend Yield | B83: =_xlfn.XLOOKUP($A83,Inputs!$A:$A,Inputs!B:B,,0) -> #N/A | C83: =_xlfn.XLOOKUP($A83,Inputs!$A:$A,Inputs!C:C,,0) -> #N/A | D83: =_xlfn.XLOOKUP($A83,Inputs!$A:$A,Inputs!D:D,,0) -> #N/A | E83: =_xlfn.XLOOKUP($A83,Inputs!$A:$A,Inputs!E:E,,0) -> #N/A | F83: =_xlfn.XLOOKUP($A83,Inputs!$A:$A,Inputs!F:F,,0) -> #N/A | G83: =_xlfn.XLOOKUP($A83,Inputs!$A:$A,Inputs!G:G,,0) -> #N/A | H83: =_xlfn.XLOOKUP($A83,Inputs!$A:$A,Inputs!H:H,,0) -> #N/A | I83: =_xlfn.XLOOKUP($A83,Inputs!$A:$A,Inputs!I:I,,0) -> #N/A | J83: =_xlfn.XLOOKUP($A83,Inputs!$A:$A,Inputs!J:J,,0) -> #N/A | K83: =_xlfn.XLOOKUP($A83,Inputs!$A:$A,Inputs!K:K,,0) -> #N/A | L83: =_xlfn.XLOOKUP($A83,Inputs!$A:$A,Inputs!L:L,,0) -> #N/A | M83: =_xlfn.XLOOKUP($A83,Inputs!$A:$A,Inputs!M:M,,0) -> #N/A
A84: Daily Volume in Millions of USD | B84: =_xlfn.XLOOKUP($A84,Inputs!$A:$A,Inputs!B:B,,0) -> 0 | C84: =_xlfn.XLOOKUP($A84,Inputs!$A:$A,Inputs!C:C,,0) -> Yahoo Finance | D84: =_xlfn.XLOOKUP($A84,Inputs!$A:$A,Inputs!D:D,,0) -> 0 | E84: =_xlfn.XLOOKUP($A84,Inputs!$A:$A,Inputs!E:E,,0) -> 0 | F84: =_xlfn.XLOOKUP($A84,Inputs!$A:$A,Inputs!F:F,,0) -> 0 | G84: =_xlfn.XLOOKUP($A84,Inputs!$A:$A,Inputs!G:G,,0) -> 0 | H84: =_xlfn.XLOOKUP($A84,Inputs!$A:$A,Inputs!H:H,,0) -> 0 | I84: =_xlfn.XLOOKUP($A84,Inputs!$A:$A,Inputs!I:I,,0) -> 0 | J84: =_xlfn.XLOOKUP($A84,Inputs!$A:$A,Inputs!J:J,,0) -> 0 | K84: =_xlfn.XLOOKUP($A84,Inputs!$A:$A,Inputs!K:K,,0) -> 0 | L84: =_xlfn.XLOOKUP($A84,Inputs!$A:$A,Inputs!L:L,,0) -> 0 | M84: =_xlfn.XLOOKUP($A84,Inputs!$A:$A,Inputs!M:M,,0) -> 0
B86: 2020 | C86: 2021 | D86: 2022
A87: Short % of Float | B87: 0 | C87: 0 | D87: 0
A88: EPS | B88: 0 | C88: 0 | D88: 0
A90: Corporate Bonds 3, 5 Y 10 | B90: Average Price | C90: Moody's | D90: YTM | E90: DIVISA
B91: =VLOOKUP($A91,Inputs!$A$5:$M$98,MATCH(B$4,Inputs!$B$5:$M$5,0)+1,FALSE) -> #N/A | C91: =VLOOKUP($A91,Inputs!$A$5:$M$98,MATCH(C$4,Inputs!$B$5:$M$5,0)+1,FALSE) -> #N/A | D91: =VLOOKUP($A91,Inputs!$A$5:$M$98,MATCH(D$4,Inputs!$B$5:$M$5,0)+1,FALSE) -> #N/A | E91: =VLOOKUP($A91,Inputs!$A$5:$M$98,MATCH(E$4,Inputs!$B$5:$M$5,0)+1,FALSE) -> #N/A

Sheet Fin. Data (Common Size)
A2: =Inputs!G2 -> Figures in Millions of USD
A3: Results
B4: =OP!J20 -> 2022 | C4: =B4-1 -> 2021 | D4: =C4-1 -> 2020 | E4: =D4-1 -> 2019 | F4: =E4-1 -> 2018 | G4: =F4-1 -> 2017 | H4: =G4-1 -> 2016 | I4: =H4-1 -> 2015 | J4: =I4-1 -> 2014 | ... M4: =L4-1 -> 2011
A5: Net Sales | B5: =_xlfn.XLOOKUP($A5,Inputs!$A:$A,Inputs!B:B,,0) -> 226954 | C5: =_xlfn.XLOOKUP($A5,Inputs!$A:$A,Inputs!C:C,,0) -> 195929 | D5: =_xlfn.XLOOKUP($A5,Inputs!$A:$A,Inputs!D:D,,0) -> 166761 | E5: =_xlfn.XLOOKUP($A5,Inputs!$A:$A,Inputs!E:E,,0) -> 152703 | F5: =_xlfn.XLOOKUP($A5,Inputs!$A:$A,Inputs!F:F,,0) -> 141576 | G5: =_xlfn.XLOOKUP($A5,Inputs!$A:$A,Inputs!G:G,,0) -> 129025 | H5: =_xlfn.XLOOKUP($A5,Inputs!$A:$A,Inputs!H:H,,0) -> 118719 | I5: =_xlfn.XLOOKUP($A5,Inputs!$A:$A,Inputs!I:I,,0) -> 116199 | J5: =_xlfn.XLOOKUP($A5,Inputs!$A:$A,Inputs!J:J,,0) -> 112640 | K5: =_xlfn.XLOOKUP($A5,Inputs!$A:$A,Inputs!K:K,,0) -> 105156 | L5: =_xlfn.XLOOKUP($A5,Inputs!$A:$A,Inputs!L:L,,0) -> 0 | M5: =_xlfn.XLOOKUP($A5,Inputs!$A:$A,Inputs!M:M,,0) -> 0
A6: Growth vs. Previous year | B6: =IFERROR(B5/C5-1,"-") -> 0.15834818 | C6: =IFERROR(C5/D5-1,"-") -> 0.174909 | D6: =IFERROR(D5/E5-1,"-") -> 0.09206106 | E6: =IFERROR(E5/F5-1,"-") -> 0.078593829 | F6: =IFERROR(F5/G5-1,"-") -> 0.097275722 | G6: =IFERROR(G5/H5-1,"-") -> 0.08681003 | H6: =IFERROR(H5/I5-1,"-") -> 0.021686934 | I6: =IFERROR(I5/J5-1,"-") -> 0.031596236 | ... M6: =IFERROR(M5/N5-1,"-") -> -
A7: Gross Profit | B7: =_xlfn.XLOOKUP($A7,Inputs!$A:$A,Inputs!B:B,,0) -> 27572 | C7: =_xlfn.XLOOKUP($A7,Inputs!$A:$A,Inputs!C:C,,0) -> 25245 | D7: =_xlfn.XLOOKUP($A7,Inputs!$A:$A,Inputs!D:D,,0) -> 21822 | E7: =_xlfn.XLOOKUP($A7,Inputs!$A:$A,Inputs!E:E,,0) -> 19817 | F7: =_xlfn.XLOOKUP($A7,Inputs!$A:$A,Inputs!F:F,,0) -> 18424 | G7: =_xlfn.XLOOKUP($A7,Inputs!$A:$A,Inputs!G:G,,0) -> 17143 | H7: =_xlfn.XLOOKUP($A7,Inputs!$A:$A,Inputs!H:H,,0) -> 15818 | I7: =_xlfn.XLOOKUP($A7,Inputs!$A:$A,Inputs!I:I,,0) -> 15134 | J7: =_xlfn.XLOOKUP($A7,Inputs!$A:$A,Inputs!J:J,,0) -> 14182 | K7: =_xlfn.XLOOKUP($A7,Inputs!$A:$A,Inputs!K:K,,0) -> 13208 | L7: =_xlfn.XLOOKUP($A7,Inputs!$A:$A,Inputs!L:L,,0) -> 0 | M7: =_xlfn.XLOOKUP($A7,Inputs!$A:$A,Inputs!M:M,,0) -> 0
A8: % over sales | B8: =IFERROR(B7/B$5,"-") -> 0.12148717 | C8: =IFERROR(C7/C$5,"-") -> 0.12884769 | D8: =IFERROR(D7/D$5,"-") -> 0.13085793 | E8: =IFERROR(E7/E$5,"-") -> 0.12977479 | F8: =IFERROR(F7/F$5,"-") -> 0.13013505 | G8: =IFERROR(G7/G$5,"-") -> 0.13286572 | H8: =IFERROR(H7/H$5,"-") -> 0.13323899 | I8: =IFERROR(I7/I$5,"-") -> 0.13024208 | ... M8: =IFERROR(M7/M$5,"-") -> -
A9: Operating expenses | B9: =B5-B11 -> 219161 | C9: =C5-C11 -> 189221 | D9: =D5-D11 -> 161326 | E9: =E5-E11 -> 147966 | F9: =F5-F11 -> 137050 | G9: =G5-G11 -> 124902 | H9: =H5-H11 -> 115008 | I9: =I5-I11 -> 112521 | ... M9: =M5-M11 -> 0
A10: % over sales | B10: =IFERROR(B9/B$5,"-") -> 0.96566265 | C10: =IFERROR(C9/C$5,"-") -> 0.96576311 | D10: =IFERROR(D9/D$5,"-") -> 0.96740845 | E10: =IFERROR(E9/E$5,"-") -> 0.968979 | F10: =IFERROR(F9/F$5,"-") -> 0.9680313 | G10: =IFERROR(G9/G$5,"-") -> 0.96804495 | H10: =IFERROR(H9/H$5,"-") -> 0.96874131 | I10: =IFERROR(I9/I$5,"-") -> 0.9683474 | ... M10: =IFERROR(M9/M$5,"-") -> -
A11: Operating Income | B11: =_xlfn.XLOOKUP($A11,Inputs!$A:$A,Inputs!B:B,,0) -> 7793 | C11: =_xlfn.XLOOKUP($A11,Inputs!$A:$A,Inputs!C:C,,0) -> 6708 | D11: =_xlfn.XLOOKUP($A11,Inputs!$A:$A,Inputs!D:D,,0) -> 5435 | E11: =_xlfn.XLOOKUP($A11,Inputs!$A:$A,Inputs!E:E,,0) -> 4737 | F11: =_xlfn.XLOOKUP($A11,Inputs!$A:$A,Inputs!F:F,,0) -> 4526 | G11: =_xlfn.XLOOKUP($A11,Inputs!$A:$A,Inputs!G:G,,0) -> 4123 | H11: =_xlfn.XLOOKUP($A11,Inputs!$A:$A,Inputs!H:H,,0) -> 3711 | I11: =_xlfn.XLOOKUP($A11,Inputs!$A:$A,Inputs!I:I,,0) -> 3678 | J11: =_xlfn.XLOOKUP($A11,Inputs!$A:$A,Inputs!J:J,,0) -> 3258 | K11: =_xlfn.XLOOKUP($A11,Inputs!$A:$A,Inputs!K:K,,0) -> 3106 | L11: =_xlfn.XLOOKUP($A11,Inputs!$A:$A,Inputs!L:L,,0) -> 0 | M11: =_xlfn.XLOOKUP($A11,Inputs!$A:$A,Inputs!M:M,,0) -> 0
A12: % over sales | B12: =IFERROR(B11/B$5,"-") -> 0.034337355 | C12: =IFERROR(C11/C$5,"-") -> 0.034236892 | D12: =IFERROR(D11/D$5,"-") -> 0.032591553 | E12: =IFERROR(E11/E$5,"-") -> 0.031021002 | F12: =IFERROR(F11/F$5,"-") -> 0.031968695 | G12: =IFERROR(G11/G$5,"-") -> 0.031955047 | H12: =IFERROR(H11/H$5,"-") -> 0.031258686 | I12: =IFERROR(I11/I$5,"-") -> 0.031652596 | ... M12: =IFERROR(M11/M$5,"-") -> -
A13: Growth vs. Previous year | B13: =IFERROR(B12/C12-1,"-") -> 0.0029343426 | C13: =IFERROR(C12/D12-1,"-") -> 0.050483594 | D13: =IFERROR(D12/E12-1,"-") -> 0.050628656 | E13: =IFERROR(E12/F12-1,"-") -> -0.029644429 | F13: =IFERROR(F12/G12-1,"-") -> 0.00042709333 | G13: =IFERROR(G12/H12-1,"-") -> 0.022277359 | H13: =IFERROR(H12/I12-1,"-") -> -0.012444777 | I13: =IFERROR(I12/J12-1,"-") -> 0.094336529 | ... M13: =IFERROR(M12/N12-1,"-") -> -
A14: Net Financial Cost | B14: =_xlfn.XLOOKUP($A14,Inputs!$A:$A,Inputs!B:B,,0) -> 97 | C14: =_xlfn.XLOOKUP($A14,Inputs!$A:$A,Inputs!C:C,,0) -> 130 | D14: =_xlfn.XLOOKUP($A14,Inputs!$A:$A,Inputs!D:D,,0) -> 71 | E14: =_xlfn.XLOOKUP($A14,Inputs!$A:$A,Inputs!E:E,,0) -> 24 | F14: =_xlfn.XLOOKUP($A14,Inputs!$A:$A,Inputs!F:F,,0) -> 84 | G14: =_xlfn.XLOOKUP($A14,Inputs!$A:$A,Inputs!G:G,,0) -> 84 | H14: =_xlfn.XLOOKUP($A14,Inputs!$A:$A,Inputs!H:H,,0) -> 92 | I14: =_xlfn.XLOOKUP($A14,Inputs!$A:$A,Inputs!I:I,,0) -> 74 | J14: =_xlfn.XLOOKUP($A14,Inputs!$A:$A,Inputs!J:J,,0) -> 61 | K14: =_xlfn.XLOOKUP($A14,Inputs!$A:$A,Inputs!K:K,,0) -> 55 | L14: =_xlfn.XLOOKUP($A14,Inputs!$A:$A,Inputs!L:L,,0) -> 0 | M14: =_xlfn.XLOOKUP($A14,Inputs!$A:$A,Inputs!M:M,,0) -> 0
A15: Other Expenses (Revenues) | B15: =_xlfn.XLOOKUP($A15,Inputs!$A:$A,Inputs!B:B,,0) -> 19653 | C15: =_xlfn.XLOOKUP($A15,Inputs!$A:$A,Inputs!C:C,,0) -> 18435 | D15: =_xlfn.XLOOKUP($A15,Inputs!$A:$A,Inputs!D:D,,0) -> 16384 | E15: =_xlfn.XLOOKUP($A15,Inputs!$A:$A,Inputs!E:E,,0) -> 15028 | F15: =_xlfn.XLOOKUP($A15,Inputs!$A:$A,Inputs!F:F,,0) -> 13898 | G15: =_xlfn.XLOOKUP($A15,Inputs!$A:$A,Inputs!G:G,,0) -> 13020 | H15: =_xlfn.XLOOKUP($A15,Inputs!$A:$A,Inputs!H:H,,0) -> 12107 | I15: =_xlfn.XLOOKUP($A15,Inputs!$A:$A,Inputs!I:I,,0) -> 11456 | J15: =_xlfn.XLOOKUP($A15,Inputs!$A:$A,Inputs!J:J,,0) -> 10924 | K15: =_xlfn.XLOOKUP($A15,Inputs!$A:$A,Inputs!K:K,,0) -> 10102 | L15: =_xlfn.XLOOKUP($A15,Inputs!$A:$A,Inputs!L:L,,0) -> 0 | M15: =_xlfn.XLOOKUP($A15,Inputs!$A:$A,Inputs!M:M,,0) -> 0
A16: EBIT | B16: =B11-B15 -> -11860 | C16: =C11-C15 -> -11727 | D16: =D11-D15 -> -10949 | E16: =E11-E15 -> -10291 | F16: =F11-F15 -> -9372 | G16: =G11-G15 -> -8897 | H16: =H11-H15 -> -8396 | I16: =I11-I15 -> -7778 | ... M16: =M11-M15 -> 0
A17: Depreciation and Amortization | B17: ='Fin. Data'!B17 -> 1900 | C17: ='Fin. Data'!C17 -> 1781 | D17: ='Fin. Data'!D17 -> 1645 | E17: ='Fin. Data'!E17 -> 1492 | F17: ='Fin. Data'!F17 -> 1437 | G17: ='Fin. Data'!G17 -> 1370 | H17: ='Fin. Data'!H17 -> 1255 | I17: ='Fin. Data'!I17 -> 1127 | ... M17: ='Fin. Data'!M17 -> 0
A18: Changes Net Working Capital | B18: =_xlfn.XLOOKUP($A18,Inputs!$A:$A,Inputs!B:B,,0) -> 1034 | C18: =_xlfn.XLOOKUP($A18,Inputs!$A:$A,Inputs!C:C,,0) -> -1378 | D18: =_xlfn.XLOOKUP($A18,Inputs!$A:$A,Inputs!D:D,,0) -> -2447 | E18: =_xlfn.XLOOKUP($A18,Inputs!$A:$A,Inputs!E:E,,0) -> -681 | F18: =_xlfn.XLOOKUP($A18,Inputs!$A:$A,Inputs!F:F,,0) -> -935 | G18: =_xlfn.XLOOKUP($A18,Inputs!$A:$A,Inputs!G:G,,0) -> -1885 | H18: =_xlfn.XLOOKUP($A18,Inputs!$A:$A,Inputs!H:H,,0) -> 910 | I18: =_xlfn.XLOOKUP($A18,Inputs!$A:$A,Inputs!I:I,,0) -> -727 | J18: =_xlfn.XLOOKUP($A18,Inputs!$A:$A,Inputs!J:J,,0) -> -628 | K18: =_xlfn.XLOOKUP($A18,Inputs!$A:$A,Inputs!K:K,,0) -> -3541 | L18: =_xlfn.XLOOKUP($A18,Inputs!$A:$A,Inputs!L:L,,0) -> 0 | M18: =_xlfn.XLOOKUP($A18,Inputs!$A:$A,Inputs!M:M,,0) -> 0
A19: EBITDA | B19: =B11-B15+B17 -> -9960 | C19: =C11-C15+C17 -> -9946 | D19: =D11-D15+D17 -> -9304 | E19: =E11-E15+E17 -> -8799 | F19: =F11-F15+F17 -> -7935 | G19: =G11-G15+G17 -> -7527 | H19: =H11-H15+H17 -> -7141 | I19: =I11-I15+I17 -> -6651 | ... M19: =M11-M15+M17 -> 0
A20: % over sales | B20: =IFERROR(B19/B$5,"-") -> -0.043885545 | C20: =IFERROR(C19/C$5,"-") -> -0.050763287 | D20: =IFERROR(D19/D$5,"-") -> -0.055792421 | E20: =IFERROR(E19/E$5,"-") -> -0.057621658 | F20: =IFERROR(F19/F$5,"-") -> -0.056047635 | G20: =IFERROR(G19/G$5,"-") -> -0.058337531 | H20: =IFERROR(H19/H$5,"-") -> -0.060150439 | I20: =IFERROR(I19/I$5,"-") -> -0.057238014 | ... M20: =IFERROR(M19/M$5,"-") -> -
A21: Taxes | B21: =_xlfn.XLOOKUP($A21,Inputs!$A:$A,Inputs!B:B,,0) -> 1925 | C21: =_xlfn.XLOOKUP($A21,Inputs!$A:$A,Inputs!C:C,,0) -> 1601 | D21: =_xlfn.XLOOKUP($A21,Inputs!$A:$A,Inputs!D:D,,0) -> 1308 | E21: =_xlfn.XLOOKUP($A21,Inputs!$A:$A,Inputs!E:E,,0) -> 1061 | F21: =_xlfn.XLOOKUP($A21,Inputs!$A:$A,Inputs!F:F,,0) -> 1263 | G21: =_xlfn.XLOOKUP($A21,Inputs!$A:$A,Inputs!G:G,,0) -> 1325 | H21: =_xlfn.XLOOKUP($A21,Inputs!$A:$A,Inputs!H:H,,0) -> 1243 | I21: =_xlfn.XLOOKUP($A21,Inputs!$A:$A,Inputs!I:I,,0) -> 1195 | J21: =_xlfn.XLOOKUP($A21,Inputs!$A:$A,Inputs!J:J,,0) -> 1109 | K21: =_xlfn.XLOOKUP($A21,Inputs!$A:$A,Inputs!K:K,,0) -> 990 | L21: =_xlfn.XLOOKUP($A21,Inputs!$A:$A,Inputs!L:L,,0) -> 0 | M21: =_xlfn.XLOOKUP($A21,Inputs!$A:$A,Inputs!M:M,,0) -> 0
A22: % Tax | B22: =IFERROR(B21/B$5,"-") -> 0.008481895 | C22: =IFERROR(C21/C$5,"-") -> 0.0081713274 | D22: =IFERROR(D21/D$5,"-") -> 0.0078435605 | E22: =IFERROR(E21/E$5,"-") -> 0.0069481281 | F22: =IFERROR(F21/F$5,"-") -> 0.0089210036 | G22: =IFERROR(G21/G$5,"-") -> 0.010269328 | H22: =IFERROR(H21/H$5,"-") -> 0.010470102 | I22: =IFERROR(I21/I$5,"-") -> 0.010284082 | ... M22: =IFERROR(M21/M$5,"-") -> -
A23: Net income | B23: =_xlfn.XLOOKUP($A23,Inputs!$A:$A,Inputs!B:B,,0) -> 5844 | C23: =_xlfn.XLOOKUP($A23,Inputs!$A:$A,Inputs!C:C,,0) -> 5007 | D23: =_xlfn.XLOOKUP($A23,Inputs!$A:$A,Inputs!D:D,,0) -> 4002 | E23: =_xlfn.XLOOKUP($A23,Inputs!$A:$A,Inputs!E:E,,0) -> 3659 | F23: =_xlfn.XLOOKUP($A23,Inputs!$A:$A,Inputs!F:F,,0) -> 3134 | G23: =_xlfn.XLOOKUP($A23,Inputs!$A:$A,Inputs!G:G,,0) -> 2679 | H23: =_xlfn.XLOOKUP($A23,Inputs!$A:$A,Inputs!H:H,,0) -> 2350 | I23: =_xlfn.XLOOKUP($A23,Inputs!$A:$A,Inputs!I:I,,0) -> 2377 | J23: =_xlfn.XLOOKUP($A23,Inputs!$A:$A,Inputs!J:J,,0) -> 2058 | K23: =_xlfn.XLOOKUP($A23,Inputs!$A:$A,Inputs!K:K,,0) -> 2039 | L23: =_xlfn.XLOOKUP($A23,Inputs!$A:$A,Inputs!L:L,,0) -> 0 | M23: =_xlfn.XLOOKUP($A23,Inputs!$A:$A,Inputs!M:M,,0) -> 0
A24: % over sales | B24: =IFERROR(B23/B$5,"-") -> 0.025749711 | C24: =IFERROR(C23/C$5,"-") -> 0.025555176 | D24: =IFERROR(D23/D$5,"-") -> 0.023998417 | E24: =IFERROR(E23/E$5,"-") -> 0.023961546 | F24: =IFERROR(F23/F$5,"-") -> 0.02213652 | G24: =IFERROR(G23/G$5,"-") -> 0.020763418 | H24: =IFERROR(H23/H$5,"-") -> 0.019794641 | I24: =IFERROR(I23/I$5,"-") -> 0.020456286 | ... M24: =IFERROR(M23/M$5,"-") -> -
A25: Growth vs. Previous year | B25: =IFERROR(B24/C24-1,"-") -> 0.0076123835 | C25: =IFERROR(C24/D24-1,"-") -> 0.064869225 | D25: =IFERROR(D24/E24-1,"-") -> 0.0015387415 | E25: =IFERROR(E24/F24-1,"-") -> 0.082444121 | F25: =IFERROR(F24/G24-1,"-") -> 0.066130845 | G25: =IFERROR(G24/H24-1,"-") -> 0.048941368 | H25: =IFERROR(H24/I24-1,"-") -> -0.03234434 | I25: =IFERROR(I24/J24-1,"-") -> 0.1196288 | ... M25: =IFERROR(M24/N24-1,"-") -> -
A26: Cash Generated | B26: =B39-C39 -> -1126 | C26: =C39-D39 -> -1130 | D26: =D39-E39 -> 3861 | E26: =E39-F39 -> 2185 | F26: =F39-G39 -> 1480 | G26: =G39-H39 -> 1050 | H26: =H39-I39 -> -1690 | I26: =I39-J39 -> -896 | ... M26: =M39-N39 -> 0
A27: Dividends | B27: =_xlfn.XLOOKUP($A27,Inputs!$A:$A,Inputs!B:B,,0) -> -1498 | C27: =_xlfn.XLOOKUP($A27,Inputs!$A:$A,Inputs!C:C,,0) -> -1318 | D27: =_xlfn.XLOOKUP($A27,Inputs!$A:$A,Inputs!D:D,,0) -> -1479 | E27: =_xlfn.XLOOKUP($A27,Inputs!$A:$A,Inputs!E:E,,0) -> -1038 | F27: =_xlfn.XLOOKUP($A27,Inputs!$A:$A,Inputs!F:F,,0) -> -689 | G27: =_xlfn.XLOOKUP($A27,Inputs!$A:$A,Inputs!G:G,,0) -> -804 | H27: =_xlfn.XLOOKUP($A27,Inputs!$A:$A,Inputs!H:H,,0) -> -736 | I27: =_xlfn.XLOOKUP($A27,Inputs!$A:$A,Inputs!I:I,,0) -> -664 | J27: =_xlfn.XLOOKUP($A27,Inputs!$A:$A,Inputs!J:J,,0) -> -584 | K27: =_xlfn.XLOOKUP($A27,Inputs!$A:$A,Inputs!K:K,,0) -> -511 | L27: =_xlfn.XLOOKUP($A27,Inputs!$A:$A,Inputs!L:L,,0) -> 0 | M27: =_xlfn.XLOOKUP($A27,Inputs!$A:$A,Inputs!M:M,,0) -> 0
A28: Share buyback | B28: =_xlfn.XLOOKUP($A28,Inputs!$A:$A,Inputs!B:B,,0) -> -802 | C28: =_xlfn.XLOOKUP($A28,Inputs!$A:$A,Inputs!C:C,,0) -> -808 | D28: =_xlfn.XLOOKUP($A28,Inputs!$A:$A,Inputs!D:D,,0) -> -526 | E28: =_xlfn.XLOOKUP($A28,Inputs!$A:$A,Inputs!E:E,,0) -> -519 | F28: =_xlfn.XLOOKUP($A28,Inputs!$A:$A,Inputs!F:F,,0) -> -545 | G28: =_xlfn.XLOOKUP($A28,Inputs!$A:$A,Inputs!G:G,,0) -> -671 | H28: =_xlfn.XLOOKUP($A28,Inputs!$A:$A,Inputs!H:H,,0) -> -706 | I28: =_xlfn.XLOOKUP($A28,Inputs!$A:$A,Inputs!I:I,,0) -> -659 | J28: =_xlfn.XLOOKUP($A28,Inputs!$A:$A,Inputs!J:J,,0) -> -498 | K28: =_xlfn.XLOOKUP($A28,Inputs!$A:$A,Inputs!K:K,,0) -> -157 | L28: =_xlfn.XLOOKUP($A28,Inputs!$A:$A,Inputs!L:L,,0) -> 0 | M28: =_xlfn.XLOOKUP($A28,Inputs!$A:$A,Inputs!M:M,,0) -> 0
A29: FNP | B29: =SUM(B26:B28) -> -3426 | C29: =SUM(C26:C28) -> -3256 | D29: =SUM(D26:D28) -> 1856 | E29: =SUM(E26:E28) -> 628 | F29: =SUM(F26:F28) -> 246 | G29: =SUM(G26:G28) -> -425 | H29: =SUM(H26:H28) -> -3132 | I29: =SUM(I26:I28) -> -2219 | ... M29: =SUM(M26:M28) -> 0
A30: FNP'' | B30: =+B29-(B58-C29) -> -13239 | C30: =+C29-(C58-D29) -> -8891 | D30: =+D29-(D58-E29) -> -5125 | E30: =+E29-(E58-F29) -> -5949 | F30: =+F29-(F58-G29) -> -6756 | G30: =+G29-(G58-H29) -> -10216 | H30: =+H29-(H58-I29) -> -10512 | I30: =+I29-(I58-J29) -> -8245 | ... M30: =+M29-(M58-N29) -> 0
A31: FNP' | B31: =+B30+B33 -> -13236 | C31: =+C30+C33 -> -8790 | D31: =+D30+D33 -> -6144 | E31: =+E30+E33 -> -5786 | F31: =+F30+F33 -> -6730 | G31: =+G30+G33 -> -10084 | H31: =+H30+H33 -> -10238 | I31: =+I30+I33 -> -8359 | ... M31: =+M30+M33 -> 0
A32: Net Capex | B32: =_xlfn.XLOOKUP($A32,Inputs!$A:$A,Inputs!B:B,,0) -> -3891 | C32: =_xlfn.XLOOKUP($A32,Inputs!$A:$A,Inputs!C:C,,0) -> -3588 | D32: =_xlfn.XLOOKUP($A32,Inputs!$A:$A,Inputs!D:D,,0) -> -2810 | E32: =_xlfn.XLOOKUP($A32,Inputs!$A:$A,Inputs!E:E,,0) -> -2998 | F32: =_xlfn.XLOOKUP($A32,Inputs!$A:$A,Inputs!F:F,,0) -> -2969 | G32: =_xlfn.XLOOKUP($A32,Inputs!$A:$A,Inputs!G:G,,0) -> -2502 | H32: =_xlfn.XLOOKUP($A32,Inputs!$A:$A,Inputs!H:H,,0) -> -2649 | I32: =_xlfn.XLOOKUP($A32,Inputs!$A:$A,Inputs!I:I,,0) -> -2393 | J32: =_xlfn.XLOOKUP($A32,Inputs!$A:$A,Inputs!J:J,,0) -> -1993 | K32: =_xlfn.XLOOKUP($A32,Inputs!$A:$A,Inputs!K:K,,0) -> -2083 | L32: =_xlfn.XLOOKUP($A32,Inputs!$A:$A,Inputs!L:L,,0) -> 0 | M32: =_xlfn.XLOOKUP($A32,Inputs!$A:$A,Inputs!M:M,,0) -> 0
A33: Investments & Acquisitions | B33: =_xlfn.XLOOKUP($A33,Inputs!$A:$A,Inputs!B:B,,0) -> 3 | C33: =_xlfn.XLOOKUP($A33,Inputs!$A:$A,Inputs!C:C,,0) -> 101 | D33: =_xlfn.XLOOKUP($A33,Inputs!$A:$A,Inputs!D:D,,0) -> -1019 | E33: =_xlfn.XLOOKUP($A33,Inputs!$A:$A,Inputs!E:E,,0) -> 163 | F33: =_xlfn.XLOOKUP($A33,Inputs!$A:$A,Inputs!F:F,,0) -> 26 | G33: =_xlfn.XLOOKUP($A33,Inputs!$A:$A,Inputs!G:G,,0) -> 132 | H33: =_xlfn.XLOOKUP($A33,Inputs!$A:$A,Inputs!H:H,,0) -> 274 | I33: =_xlfn.XLOOKUP($A33,Inputs!$A:$A,Inputs!I:I,,0) -> -114 | J33: =_xlfn.XLOOKUP($A33,Inputs!$A:$A,Inputs!J:J,,0) -> -80 | K33: =_xlfn.XLOOKUP($A33,Inputs!$A:$A,Inputs!K:K,,0) -> -165 | L33: =_xlfn.XLOOKUP($A33,Inputs!$A:$A,Inputs!L:L,,0) -> 0 | M33: =_xlfn.XLOOKUP($A33,Inputs!$A:$A,Inputs!M:M,,0) -> 0
A34: Capex + Investments | B34: =+B32+B33 -> -3888 | C34: =+C32+C33 -> -3487 | D34: =+D32+D33 -> -3829 | E34: =+E32+E33 -> -2835 | F34: =+F32+F33 -> -2943 | G34: =+G32+G33 -> -2370 | H34: =+H32+H33 -> -2375 | I34: =+I32+I33 -> -2507 | ... M34: =+M32+M33 -> 0
A35: Dividends + Share Buyback | B35: =+B27+B28 -> -2300 | C35: =+C27+C28 -> -2126 | D35: =+D27+D28 -> -2005 | E35: =+E27+E28 -> -1557 | F35: =+F27+F28 -> -1234 | G35: =+G27+G28 -> -1475 | H35: =+H27+H28 -> -1442 | I35: =+I27+I28 -> -1323 | ... M35: =+M27+M28 -> 0
A36: Payout Ratio | B36: =IFERROR(B35/B23,"-") -> -0.39356605 | C36: =IFERROR(C35/C23,"-") -> -0.42460555 | D36: =IFERROR(D35/D23,"-") -> -0.5009995 | E36: =IFERROR(E35/E23,"-") -> -0.4255261 | F36: =IFERROR(F35/F23,"-") -> -0.39374601 | G36: =IFERROR(G35/G23,"-") -> -0.55057857 | H36: =IFERROR(H35/H23,"-") -> -0.61361702 | I36: =IFERROR(I35/I23,"-") -> -0.55658393 | ... M36: =IFERROR(M35/M23,"-") -> -
A38: Assets
A39: Cash & Eq. | B39: =_xlfn.XLOOKUP($A39,Inputs!$A:$A,Inputs!B:B,,0) -> 11049 | C39: =_xlfn.XLOOKUP($A39,Inputs!$A:$A,Inputs!C:C,,0) -> 12175 | D39: =_xlfn.XLOOKUP($A39,Inputs!$A:$A,Inputs!D:D,,0) -> 13305 | E39: =_xlfn.XLOOKUP($A39,Inputs!$A:$A,Inputs!E:E,,0) -> 9444 | F39: =_xlfn.XLOOKUP($A39,Inputs!$A:$A,Inputs!F:F,,0) -> 7259 | G39: =_xlfn.XLOOKUP($A39,Inputs!$A:$A,Inputs!G:G,,0) -> 5779 | H39: =_xlfn.XLOOKUP($A39,Inputs!$A:$A,Inputs!H:H,,0) -> 4729 | I39: =_xlfn.XLOOKUP($A39,Inputs!$A:$A,Inputs!I:I,,0) -> 6419 | J39: =_xlfn.XLOOKUP($A39,Inputs!$A:$A,Inputs!J:J,,0) -> 7315 | K39: =_xlfn.XLOOKUP($A39,Inputs!$A:$A,Inputs!K:K,,0) -> 6124 | L39: =_xlfn.XLOOKUP($A39,Inputs!$A:$A,Inputs!L:L,,0) -> 0 | M39: =_xlfn.XLOOKUP($A39,Inputs!$A:$A,Inputs!M:M,,0) -> 0
A40: Accounts Receivable | B40: =_xlfn.XLOOKUP($A40,Inputs!$A:$A,Inputs!B:B,,0) -> 2241 | C40: =_xlfn.XLOOKUP($A40,Inputs!$A:$A,Inputs!C:C,,0) -> 1803 | D40: =_xlfn.XLOOKUP($A40,Inputs!$A:$A,Inputs!D:D,,0) -> 1550 | E40: =_xlfn.XLOOKUP($A40,Inputs!$A:$A,Inputs!E:E,,0) -> 1535 | F40: =_xlfn.XLOOKUP($A40,Inputs!$A:$A,Inputs!F:F,,0) -> 1669 | G40: =_xlfn.XLOOKUP($A40,Inputs!$A:$A,Inputs!G:G,,0) -> 1432 | H40: =_xlfn.XLOOKUP($A40,Inputs!$A:$A,Inputs!H:H,,0) -> 1252 | I40: =_xlfn.XLOOKUP($A40,Inputs!$A:$A,Inputs!I:I,,0) -> 1224 | J40: =_xlfn.XLOOKUP($A40,Inputs!$A:$A,Inputs!J:J,,0) -> 1148 | K40: =_xlfn.XLOOKUP($A40,Inputs!$A:$A,Inputs!K:K,,0) -> 1201 | L40: =_xlfn.XLOOKUP($A40,Inputs!$A:$A,Inputs!L:L,,0) -> 0 | M40: =_xlfn.XLOOKUP($A40,Inputs!$A:$A,Inputs!M:M,,0) -> 0
A41: Inventory | B41: =_xlfn.XLOOKUP($A41,Inputs!$A:$A,Inputs!B:B,,0) -> 17907 | C41: =_xlfn.XLOOKUP($A41,Inputs!$A:$A,Inputs!C:C,,0) -> 14215 | D41: =_xlfn.XLOOKUP($A41,Inputs!$A:$A,Inputs!D:D,,0) -> 12242 | E41: =_xlfn.XLOOKUP($A41,Inputs!$A:$A,Inputs!E:E,,0) -> 11395 | F41: =_xlfn.XLOOKUP($A41,Inputs!$A:$A,Inputs!F:F,,0) -> 11040 | G41: =_xlfn.XLOOKUP($A41,Inputs!$A:$A,Inputs!G:G,,0) -> 9834 | H41: =_xlfn.XLOOKUP($A41,Inputs!$A:$A,Inputs!H:H,,0) -> 8969 | I41: =_xlfn.XLOOKUP($A41,Inputs!$A:$A,Inputs!I:I,,0) -> 8908 | J41: =_xlfn.XLOOKUP($A41,Inputs!$A:$A,Inputs!J:J,,0) -> 8456 | K41: =_xlfn.XLOOKUP($A41,Inputs!$A:$A,Inputs!K:K,,0) -> 7894 | L41: =_xlfn.XLOOKUP($A41,Inputs!$A:$A,Inputs!L:L,,0) -> 0 | M41: =_xlfn.XLOOKUP($A41,Inputs!$A:$A,Inputs!M:M,,0) -> 0
A42: Property, Plant and Equipment | B42: =_xlfn.XLOOKUP($A42,Inputs!$A:$A,Inputs!B:B,,0) -> 44326 | C42: =_xlfn.XLOOKUP($A42,Inputs!$A:$A,Inputs!C:C,,0) -> 41258 | D42: =_xlfn.XLOOKUP($A42,Inputs!$A:$A,Inputs!D:D,,0) -> 38083 | E42: =_xlfn.XLOOKUP($A42,Inputs!$A:$A,Inputs!E:E,,0) -> 32626 | F42: =_xlfn.XLOOKUP($A42,Inputs!$A:$A,Inputs!F:F,,0) -> 30714 | G42: =_xlfn.XLOOKUP($A42,Inputs!$A:$A,Inputs!G:G,,0) -> 28341 | H42: =_xlfn.XLOOKUP($A42,Inputs!$A:$A,Inputs!H:H,,0) -> 26167 | I42: =_xlfn.XLOOKUP($A42,Inputs!$A:$A,Inputs!I:I,,0) -> 23664 | J42: =_xlfn.XLOOKUP($A42,Inputs!$A:$A,Inputs!J:J,,0) -> 22675 | K42: =_xlfn.XLOOKUP($A42,Inputs!$A:$A,Inputs!K:K,,0) -> 21022 | L42: =_xlfn.XLOOKUP($A42,Inputs!$A:$A,Inputs!L:L,,0) -> 0 | M42: =_xlfn.XLOOKUP($A42,Inputs!$A:$A,Inputs!M:M,,0) -> 0
A43: Other Assets | B43: =_xlfn.XLOOKUP($A43,Inputs!$A:$A,Inputs!B:B,,0) -> 2491 | C43: =_xlfn.XLOOKUP($A43,Inputs!$A:$A,Inputs!C:C,,0) -> 2253 | D43: =_xlfn.XLOOKUP($A43,Inputs!$A:$A,Inputs!D:D,,0) -> 1878 | E43: =_xlfn.XLOOKUP($A43,Inputs!$A:$A,Inputs!E:E,,0) -> 1695 | F43: =_xlfn.XLOOKUP($A43,Inputs!$A:$A,Inputs!F:F,,0) -> 865 | G43: =_xlfn.XLOOKUP($A43,Inputs!$A:$A,Inputs!G:G,,0) -> 887 | H43: =_xlfn.XLOOKUP($A43,Inputs!$A:$A,Inputs!H:H,,0) -> 968 | I43: =_xlfn.XLOOKUP($A43,Inputs!$A:$A,Inputs!I:I,,0) -> 846 | J43: =_xlfn.XLOOKUP($A43,Inputs!$A:$A,Inputs!J:J,,0) -> 1177 | K43: =_xlfn.XLOOKUP($A43,Inputs!$A:$A,Inputs!K:K,,0) -> 1121 | L43: =_xlfn.XLOOKUP($A43,Inputs!$A:$A,Inputs!L:L,,0) -> 0 | M43: =_xlfn.XLOOKUP($A43,Inputs!$A:$A,Inputs!M:M,,0) -> 0
A44: Total Assets | B44: =_xlfn.XLOOKUP($A44,Inputs!$A:$A,Inputs!B:B,,0) -> 64166 | C44: =_xlfn.XLOOKUP($A44,Inputs!$A:$A,Inputs!C:C,,0) -> 59268 | D44: =_xlfn.XLOOKUP($A44,Inputs!$A:$A,Inputs!D:D,,0) -> 55556 | E44: =_xlfn.XLOOKUP($A44,Inputs!$A:$A,Inputs!E:E,,0) -> 45400 | F44: =_xlfn.XLOOKUP($A44,Inputs!$A:$A,Inputs!F:F,,0) -> 40830 | G44: =_xlfn.XLOOKUP($A44,Inputs!$A:$A,Inputs!G:G,,0) -> 36347 | H44: =_xlfn.XLOOKUP($A44,Inputs!$A:$A,Inputs!H:H,,0) -> 33163 | I44: =_xlfn.XLOOKUP($A44,Inputs!$A:$A,Inputs!I:I,,0) -> 33017 | J44: =_xlfn.XLOOKUP($A44,Inputs!$A:$A,Inputs!J:J,,0) -> 33024 | K44: =_xlfn.XLOOKUP($A44,Inputs!$A:$A,Inputs!K:K,,0) -> 30283 | L44: =_xlfn.XLOOKUP($A44,Inputs!$A:$A,Inputs!L:L,,0) -> 0 | M44: =_xlfn.XLOOKUP($A44,Inputs!$A:$A,Inputs!M:M,,0) -> 0
A47: Liabilities
A48: Current Liabilities | B48: =_xlfn.XLOOKUP($A48,Inputs!$A:$A,Inputs!B:B,,0) -> 31998 | C48: =_xlfn.XLOOKUP($A48,Inputs!$A:$A,Inputs!C:C,,0) -> 29441 | D48: =_xlfn.XLOOKUP($A48,Inputs!$A:$A,Inputs!D:D,,0) -> 24844 | E48: =_xlfn.XLOOKUP($A48,Inputs!$A:$A,Inputs!E:E,,0) -> 23237 | F48: =_xlfn.XLOOKUP($A48,Inputs!$A:$A,Inputs!F:F,,0) -> 19926 | G48: =_xlfn.XLOOKUP($A48,Inputs!$A:$A,Inputs!G:G,,0) -> 17495 | H48: =_xlfn.XLOOKUP($A48,Inputs!$A:$A,Inputs!H:H,,0) -> 15575 | I48: =_xlfn.XLOOKUP($A48,Inputs!$A:$A,Inputs!I:I,,0) -> 16539 | J48: =_xlfn.XLOOKUP($A48,Inputs!$A:$A,Inputs!J:J,,0) -> 14412 | K48: =_xlfn.XLOOKUP($A48,Inputs!$A:$A,Inputs!K:K,,0) -> 13257 | L48: =_xlfn.XLOOKUP($A48,Inputs!$A:$A,Inputs!L:L,,0) -> 0 | M48: =_xlfn.XLOOKUP($A48,Inputs!$A:$A,Inputs!M:M,,0) -> 0
A49: Short-Term Debt | B49: =_xlfn.XLOOKUP($A49,Inputs!$A:$A,Inputs!B:B,,0) -> 73 | C49: =_xlfn.XLOOKUP($A49,Inputs!$A:$A,Inputs!C:C,,0) -> 799 | D49: =_xlfn.XLOOKUP($A49,Inputs!$A:$A,Inputs!D:D,,0) -> 95 | E49: =_xlfn.XLOOKUP($A49,Inputs!$A:$A,Inputs!E:E,,0) -> 1699 | F49: =_xlfn.XLOOKUP($A49,Inputs!$A:$A,Inputs!F:F,,0) -> 90 | G49: =_xlfn.XLOOKUP($A49,Inputs!$A:$A,Inputs!G:G,,0) -> 86 | H49: =_xlfn.XLOOKUP($A49,Inputs!$A:$A,Inputs!H:H,,0) -> 1100 | I49: =_xlfn.XLOOKUP($A49,Inputs!$A:$A,Inputs!I:I,,0) -> 1283 | J49: =_xlfn.XLOOKUP($A49,Inputs!$A:$A,Inputs!J:J,,0) -> 0 | K49: =_xlfn.XLOOKUP($A49,Inputs!$A:$A,Inputs!K:K,,0) -> 0 | L49: =_xlfn.XLOOKUP($A49,Inputs!$A:$A,Inputs!L:L,,0) -> 0 | M49: =_xlfn.XLOOKUP($A49,Inputs!$A:$A,Inputs!M:M,,0) -> 0
A50: Short-Term Leases | B50: =_xlfn.XLOOKUP($A50,Inputs!$A:$A,Inputs!B:B,,0) -> 484 | C50: =_xlfn.XLOOKUP($A50,Inputs!$A:$A,Inputs!C:C,,0) -> 294 | D50: =_xlfn.XLOOKUP($A50,Inputs!$A:$A,Inputs!D:D,,0) -> 262 | E50: =_xlfn.XLOOKUP($A50,Inputs!$A:$A,Inputs!E:E,,0) -> 51 | F50: =_xlfn.XLOOKUP($A50,Inputs!$A:$A,Inputs!F:F,,0) -> - | G50: =_xlfn.XLOOKUP($A50,Inputs!$A:$A,Inputs!G:G,,0) -> - | H50: =_xlfn.XLOOKUP($A50,Inputs!$A:$A,Inputs!H:H,,0) -> - | I50: =_xlfn.XLOOKUP($A50,Inputs!$A:$A,Inputs!I:I,,0) -> - | J50: =_xlfn.XLOOKUP($A50,Inputs!$A:$A,Inputs!J:J,,0) -> - | K50: =_xlfn.XLOOKUP($A50,Inputs!$A:$A,Inputs!K:K,,0) -> - | L50: =_xlfn.XLOOKUP($A50,Inputs!$A:$A,Inputs!L:L,,0) -> 0 | M50: =_xlfn.XLOOKUP($A50,Inputs!$A:$A,Inputs!M:M,,0) -> 0
A51: Other current liabilities | B51: =_xlfn.XLOOKUP($A51,Inputs!$A:$A,Inputs!B:B,,0) -> 13593 | C51: =_xlfn.XLOOKUP($A51,Inputs!$A:$A,Inputs!C:C,,0) -> 12070 | D51: =_xlfn.XLOOKUP($A51,Inputs!$A:$A,Inputs!D:D,,0) -> 10315 | E51: =_xlfn.XLOOKUP($A51,Inputs!$A:$A,Inputs!E:E,,0) -> 9808 | F51: =_xlfn.XLOOKUP($A51,Inputs!$A:$A,Inputs!F:F,,0) -> 8599 | G51: =_xlfn.XLOOKUP($A51,Inputs!$A:$A,Inputs!G:G,,0) -> 7801 | H51: =_xlfn.XLOOKUP($A51,Inputs!$A:$A,Inputs!H:H,,0) -> 6863 | I51: =_xlfn.XLOOKUP($A51,Inputs!$A:$A,Inputs!I:I,,0) -> 6245 | J51: =_xlfn.XLOOKUP($A51,Inputs!$A:$A,Inputs!J:J,,0) -> 5921 | K51: =_xlfn.XLOOKUP($A51,Inputs!$A:$A,Inputs!K:K,,0) -> 5385 | L51: =_xlfn.XLOOKUP($A51,Inputs!$A:$A,Inputs!L:L,,0) -> 0 | M51: =_xlfn.XLOOKUP($A51,Inputs!$A:$A,Inputs!M:M,,0) -> 0
A52: Non-current Liabilities | B52: =_xlfn.XLOOKUP($A52,Inputs!$A:$A,Inputs!B:B,,0) -> 11521 | C52: =_xlfn.XLOOKUP($A52,Inputs!$A:$A,Inputs!C:C,,0) -> 11749 | D52: =_xlfn.XLOOKUP($A52,Inputs!$A:$A,Inputs!D:D,,0) -> 12007 | E52: =_xlfn.XLOOKUP($A52,Inputs!$A:$A,Inputs!E:E,,0) -> 6579 | F52: =_xlfn.XLOOKUP($A52,Inputs!$A:$A,Inputs!F:F,,0) -> 7801 | G52: =_xlfn.XLOOKUP($A52,Inputs!$A:$A,Inputs!G:G,,0) -> 7773 | H52: =_xlfn.XLOOKUP($A52,Inputs!$A:$A,Inputs!H:H,,0) -> 5256 | I52: =_xlfn.XLOOKUP($A52,Inputs!$A:$A,Inputs!I:I,,0) -> 5635 | J52: =_xlfn.XLOOKUP($A52,Inputs!$A:$A,Inputs!J:J,,0) -> 6097 | K52: =_xlfn.XLOOKUP($A52,Inputs!$A:$A,Inputs!K:K,,0) -> 6014 | L52: =_xlfn.XLOOKUP($A52,Inputs!$A:$A,Inputs!L:L,,0) -> 0 | M52: =_xlfn.XLOOKUP($A52,Inputs!$A:$A,Inputs!M:M,,0) -> 0
A53: Long-Term Debt | B53: =_xlfn.XLOOKUP($A53,Inputs!$A:$A,Inputs!B:B,,0) -> 6484 | C53: =_xlfn.XLOOKUP($A53,Inputs!$A:$A,Inputs!C:C,,0) -> 6692 | D53: =_xlfn.XLOOKUP($A53,Inputs!$A:$A,Inputs!D:D,,0) -> 7514 | E53: =_xlfn.XLOOKUP($A53,Inputs!$A:$A,Inputs!E:E,,0) -> 5124 | F53: =_xlfn.XLOOKUP($A53,Inputs!$A:$A,Inputs!F:F,,0) -> 6487 | G53: =_xlfn.XLOOKUP($A53,Inputs!$A:$A,Inputs!G:G,,0) -> 6573 | H53: =_xlfn.XLOOKUP($A53,Inputs!$A:$A,Inputs!H:H,,0) -> 4061 | I53: =_xlfn.XLOOKUP($A53,Inputs!$A:$A,Inputs!I:I,,0) -> 4852 | J53: =_xlfn.XLOOKUP($A53,Inputs!$A:$A,Inputs!J:J,,0) -> 5093 | K53: =_xlfn.XLOOKUP($A53,Inputs!$A:$A,Inputs!K:K,,0) -> 4998 | L53: =_xlfn.XLOOKUP($A53,Inputs!$A:$A,Inputs!L:L,,0) -> 0 | M53: =_xlfn.XLOOKUP($A53,Inputs!$A:$A,Inputs!M:M,,0) -> 0
A54: Long-Term Leases | B54: =_xlfn.XLOOKUP($A54,Inputs!$A:$A,Inputs!B:B,,0) -> 3865 | C54: =_xlfn.XLOOKUP($A54,Inputs!$A:$A,Inputs!C:C,,0) -> 3622 | D54: =_xlfn.XLOOKUP($A54,Inputs!$A:$A,Inputs!D:D,,0) -> 3215 | E54: =_xlfn.XLOOKUP($A54,Inputs!$A:$A,Inputs!E:E,,0) -> 370 | F54: =_xlfn.XLOOKUP($A54,Inputs!$A:$A,Inputs!F:F,,0) -> - | G54: =_xlfn.XLOOKUP($A54,Inputs!$A:$A,Inputs!G:G,,0) -> - | H54: =_xlfn.XLOOKUP($A54,Inputs!$A:$A,Inputs!H:H,,0) -> - | I54: =_xlfn.XLOOKUP($A54,Inputs!$A:$A,Inputs!I:I,,0) -> - | J54: =_xlfn.XLOOKUP($A54,Inputs!$A:$A,Inputs!J:J,,0) -> - | K54: =_xlfn.XLOOKUP($A54,Inputs!$A:$A,Inputs!K:K,,0) -> - | L54: =_xlfn.XLOOKUP($A54,Inputs!$A:$A,Inputs!L:L,,0) -> 0 | M54: =_xlfn.XLOOKUP($A54,Inputs!$A:$A,Inputs!M:M,,0) -> 0
A55: Other non-current liabilities | B55: =_xlfn.XLOOKUP($A55,Inputs!$A:$A,Inputs!B:B,,0) -> 1172 | C55: =_xlfn.XLOOKUP($A55,Inputs!$A:$A,Inputs!C:C,,0) -> 1435 | D55: =_xlfn.XLOOKUP($A55,Inputs!$A:$A,Inputs!D:D,,0) -> 1278 | E55: =_xlfn.XLOOKUP($A55,Inputs!$A:$A,Inputs!E:E,,0) -> 1085 | F55: =_xlfn.XLOOKUP($A55,Inputs!$A:$A,Inputs!F:F,,0) -> 1314 | G55: =_xlfn.XLOOKUP($A55,Inputs!$A:$A,Inputs!G:G,,0) -> 1200 | H55: =_xlfn.XLOOKUP($A55,Inputs!$A:$A,Inputs!H:H,,0) -> 1195 | I55: =_xlfn.XLOOKUP($A55,Inputs!$A:$A,Inputs!I:I,,0) -> 783 | J55: =_xlfn.XLOOKUP($A55,Inputs!$A:$A,Inputs!J:J,,0) -> 1004 | K55: =_xlfn.XLOOKUP($A55,Inputs!$A:$A,Inputs!K:K,,0) -> 1016 | L55: =_xlfn.XLOOKUP($A55,Inputs!$A:$A,Inputs!L:L,,0) -> 0 | M55: =_xlfn.XLOOKUP($A55,Inputs!$A:$A,Inputs!M:M,,0) -> 0
A56: Total Liabilities | B56: =_xlfn.XLOOKUP($A56,Inputs!$A:$A,Inputs!B:B,,0) -> 43519 | C56: =_xlfn.XLOOKUP($A56,Inputs!$A:$A,Inputs!C:C,,0) -> 41190 | D56: =_xlfn.XLOOKUP($A56,Inputs!$A:$A,Inputs!D:D,,0) -> 36851 | E56: =_xlfn.XLOOKUP($A56,Inputs!$A:$A,Inputs!E:E,,0) -> 29816 | F56: =_xlfn.XLOOKUP($A56,Inputs!$A:$A,Inputs!F:F,,0) -> 27727 | G56: =_xlfn.XLOOKUP($A56,Inputs!$A:$A,Inputs!G:G,,0) -> 25268 | H56: =_xlfn.XLOOKUP($A56,Inputs!$A:$A,Inputs!H:H,,0) -> 20831 | I56: =_xlfn.XLOOKUP($A56,Inputs!$A:$A,Inputs!I:I,,0) -> 22174 | J56: =_xlfn.XLOOKUP($A56,Inputs!$A:$A,Inputs!J:J,,0) -> 20509 | K56: =_xlfn.XLOOKUP($A56,Inputs!$A:$A,Inputs!K:K,,0) -> 19271 | L56: =_xlfn.XLOOKUP($A56,Inputs!$A:$A,Inputs!L:L,,0) -> 0 | M56: =_xlfn.XLOOKUP($A56,Inputs!$A:$A,Inputs!M:M,,0) -> 0
A58: Debt | B58: =B49+B53 -> 6557 | C58: =C49+C53 -> 7491 | D58: =D49+D53 -> 7609 | E58: =E49+E53 -> 6823 | F58: =F49+F53 -> 6577 | G58: =G49+G53 -> 6659 | H58: =H49+H53 -> 5161 | I58: =I49+I53 -> 6135 | ... M58: =M49+M53 -> 0
A59: Debt/Assets | B59: =IFERROR(B58/B44,"-") -> 0.10218807 | C59: =IFERROR(C58/C44,"-") -> 0.12639198 | D59: =IFERROR(D58/D44,"-") -> 0.1369609 | E59: =IFERROR(E58/E44,"-") -> 0.15028634 | F59: =IFERROR(F58/F44,"-") -> 0.16108254 | G59: =IFERROR(G58/G44,"-") -> 0.18320632 | H59: =IFERROR(H58/H44,"-") -> 0.15562525 | I59: =IFERROR(I58/I44,"-") -> 0.18581337 | ... M59: =IFERROR(M58/M44,"-") -> -
A61: Minority Interest | B61: =_xlfn.XLOOKUP($A61,Inputs!$A:$A,Inputs!B:B,,0) -> 5 | C61: =_xlfn.XLOOKUP($A61,Inputs!$A:$A,Inputs!C:C,,0) -> 514 | D61: =_xlfn.XLOOKUP($A61,Inputs!$A:$A,Inputs!D:D,,0) -> 421 | E61: =_xlfn.XLOOKUP($A61,Inputs!$A:$A,Inputs!E:E,,0) -> 341 | F61: =_xlfn.XLOOKUP($A61,Inputs!$A:$A,Inputs!F:F,,0) -> 304 | G61: =_xlfn.XLOOKUP($A61,Inputs!$A:$A,Inputs!G:G,,0) -> 301 | H61: =_xlfn.XLOOKUP($A61,Inputs!$A:$A,Inputs!H:H,,0) -> 253 | I61: =_xlfn.XLOOKUP($A61,Inputs!$A:$A,Inputs!I:I,,0) -> 226 | J61: =_xlfn.XLOOKUP($A61,Inputs!$A:$A,Inputs!J:J,,0) -> 212 | K61: =_xlfn.XLOOKUP($A61,Inputs!$A:$A,Inputs!K:K,,0) -> 179 | L61: =_xlfn.XLOOKUP($A61,Inputs!$A:$A,Inputs!L:L,,0) -> 0 | M61: =_xlfn.XLOOKUP($A61,Inputs!$A:$A,Inputs!M:M,,0) -> 0
A63: Shareholder's Equity | B63: =_xlfn.XLOOKUP($A63,Inputs!$A:$A,Inputs!B:B,,0) -> 20642 | C63: =_xlfn.XLOOKUP($A63,Inputs!$A:$A,Inputs!C:C,,0) -> 17564 | D63: =_xlfn.XLOOKUP($A63,Inputs!$A:$A,Inputs!D:D,,0) -> 18284 | E63: =_xlfn.XLOOKUP($A63,Inputs!$A:$A,Inputs!E:E,,0) -> 15243 | F63: =_xlfn.XLOOKUP($A63,Inputs!$A:$A,Inputs!F:F,,0) -> 12799 | G63: =_xlfn.XLOOKUP($A63,Inputs!$A:$A,Inputs!G:G,,0) -> 10778 | H63: =_xlfn.XLOOKUP($A63,Inputs!$A:$A,Inputs!H:H,,0) -> 12079 | I63: =_xlfn.XLOOKUP($A63,Inputs!$A:$A,Inputs!I:I,,0) -> 10617 | J63: =_xlfn.XLOOKUP($A63,Inputs!$A:$A,Inputs!J:J,,0) -> 12303 | K63: =_xlfn.XLOOKUP($A63,Inputs!$A:$A,Inputs!K:K,,0) -> 10833 | L63: =_xlfn.XLOOKUP($A63,Inputs!$A:$A,Inputs!L:L,,0) -> 0 | M63: =_xlfn.XLOOKUP($A63,Inputs!$A:$A,Inputs!M:M,,0) -> 0
A66: Other Data
A67: Number of employees | B67: =_xlfn.XLOOKUP($A67,Inputs!$A:$A,Inputs!B:B,,0) -> 304000 | C67: 0 | D67: =_xlfn.XLOOKUP($A67,Inputs!$A:$A,Inputs!D:D,,0) -> 0 | E67: =_xlfn.XLOOKUP($A67,Inputs!$A:$A,Inputs!E:E,,0) -> 0 | F67: =_xlfn.XLOOKUP($A67,Inputs!$A:$A,Inputs!F:F,,0) -> 0 | G67: =_xlfn.XLOOKUP($A67,Inputs!$A:$A,Inputs!G:G,,0) -> 0 | H67: =_xlfn.XLOOKUP($A67,Inputs!$A:$A,Inputs!H:H,,0) -> 0 | I67: =_xlfn.XLOOKUP($A67,Inputs!$A:$A,Inputs!I:I,,0) -> 0 | J67: =_xlfn.XLOOKUP($A67,Inputs!$A:$A,Inputs!J:J,,0) -> 0 | K67: =_xlfn.XLOOKUP($A67,Inputs!$A:$A,Inputs!K:K,,0) -> 0 | L67: =_xlfn.XLOOKUP($A67,Inputs!$A:$A,Inputs!L:L,,0) -> 0 | M67: =_xlfn.XLOOKUP($A67,Inputs!$A:$A,Inputs!M:M,,0) -> 0
A68: Shares Outstanding | B68: =_xlfn.XLOOKUP($A68,Inputs!$A:$A,Inputs!B:B,,0) -> #N/A | C68: =_xlfn.XLOOKUP($A68,Inputs!$A:$A,Inputs!C:C,,0) -> #N/A | D68: =_xlfn.XLOOKUP($A68,Inputs!$A:$A,Inputs!D:D,,0) -> #N/A | E68: =_xlfn.XLOOKUP($A68,Inputs!$A:$A,Inputs!E:E,,0) -> #N/A | F68: =_xlfn.XLOOKUP($A68,Inputs!$A:$A,Inputs!F:F,,0) -> #N/A | G68: =_xlfn.XLOOKUP($A68,Inputs!$A:$A,Inputs!G:G,,0) -> #N/A | H68: =_xlfn.XLOOKUP($A68,Inputs!$A:$A,Inputs!H:H,,0) -> #N/A | I68: =_xlfn.XLOOKUP($A68,Inputs!$A:$A,Inputs!I:I,,0) -> #N/A | J68: =_xlfn.XLOOKUP($A68,Inputs!$A:$A,Inputs!J:J,,0) -> #N/A | K68: =_xlfn.XLOOKUP($A68,Inputs!$A:$A,Inputs!K:K,,0) -> #N/A | L68: =_xlfn.XLOOKUP($A68,Inputs!$A:$A,Inputs!L:L,,0) -> #N/A | M68: =_xlfn.XLOOKUP($A68,Inputs!$A:$A,Inputs!M:M,,0) -> #N/A
A69: Float | B69: =_xlfn.XLOOKUP($A69,Inputs!$A:$A,Inputs!B:B,,0) -> 0.99738238 | C69: =_xlfn.XLOOKUP($A69,Inputs!$A:$A,Inputs!C:C,,0) -> Yahoo finance | D69: =_xlfn.XLOOKUP($A69,Inputs!$A:$A,Inputs!D:D,,0) -> 0 | E69: =_xlfn.XLOOKUP($A69,Inputs!$A:$A,Inputs!E:E,,0) -> 0 | F69: =_xlfn.XLOOKUP($A69,Inputs!$A:$A,Inputs!F:F,,0) -> 0 | G69: =_xlfn.XLOOKUP($A69,Inputs!$A:$A,Inputs!G:G,,0) -> 0 | H69: =_xlfn.XLOOKUP($A69,Inputs!$A:$A,Inputs!H:H,,0) -> 0 | I69: =_xlfn.XLOOKUP($A69,Inputs!$A:$A,Inputs!I:I,,0) -> 0 | J69: =_xlfn.XLOOKUP($A69,Inputs!$A:$A,Inputs!J:J,,0) -> 0 | K69: =_xlfn.XLOOKUP($A69,Inputs!$A:$A,Inputs!K:K,,0) -> 0 | L69: =_xlfn.XLOOKUP($A69,Inputs!$A:$A,Inputs!L:L,,0) -> 0 | M69: =_xlfn.XLOOKUP($A69,Inputs!$A:$A,Inputs!M:M,,0) -> 0
A70: Insiders Own | B70: =_xlfn.XLOOKUP($A70,Inputs!$A:$A,Inputs!B:B,,0) -> 0.002 | C70: =_xlfn.XLOOKUP($A70,Inputs!$A:$A,Inputs!C:C,,0) -> Yahoo finance | D70: =_xlfn.XLOOKUP($A70,Inputs!$A:$A,Inputs!D:D,,0) -> 0 | E70: =_xlfn.XLOOKUP($A70,Inputs!$A:$A,Inputs!E:E,,0) -> 0 | F70: =_xlfn.XLOOKUP($A70,Inputs!$A:$A,Inputs!F:F,,0) -> 0 | G70: =_xlfn.XLOOKUP($A70,Inputs!$A:$A,Inputs!G:G,,0) -> 0 | H70: =_xlfn.XLOOKUP($A70,Inputs!$A:$A,Inputs!H:H,,0) -> 0 | I70: =_xlfn.XLOOKUP($A70,Inputs!$A:$A,Inputs!I:I,,0) -> 0 | J70: =_xlfn.XLOOKUP($A70,Inputs!$A:$A,Inputs!J:J,,0) -> 0 | K70: =_xlfn.XLOOKUP($A70,Inputs!$A:$A,Inputs!K:K,,0) -> 0 | L70: =_xlfn.XLOOKUP($A70,Inputs!$A:$A,Inputs!L:L,,0) -> 0 | M70: =_xlfn.XLOOKUP($A70,Inputs!$A:$A,Inputs!M:M,,0) -> 0
A71: Fitch/ S&P Rating | B71: =_xlfn.XLOOKUP($A71,Inputs!$A:$A,Inputs!B:B,,0) -> 0.79 | C71: =_xlfn.XLOOKUP($A71,Inputs!$A:$A,Inputs!C:C,,0) -> 10-K | D71: =_xlfn.XLOOKUP($A71,Inputs!$A:$A,Inputs!D:D,,0) -> 0 | E71: =_xlfn.XLOOKUP($A71,Inputs!$A:$A,Inputs!E:E,,0) -> 0 | F71: =_xlfn.XLOOKUP($A71,Inputs!$A:$A,Inputs!F:F,,0) -> 0 | G71: =_xlfn.XLOOKUP($A71,Inputs!$A:$A,Inputs!G:G,,0) -> 0 | H71: =_xlfn.XLOOKUP($A71,Inputs!$A:$A,Inputs!H:H,,0) -> 0 | I71: =_xlfn.XLOOKUP($A71,Inputs!$A:$A,Inputs!I:I,,0) -> 0 | J71: =_xlfn.XLOOKUP($A71,Inputs!$A:$A,Inputs!J:J,,0) -> 0 | K71: =_xlfn.XLOOKUP($A71,Inputs!$A:$A,Inputs!K:K,,0) -> 0 | L71: =_xlfn.XLOOKUP($A71,Inputs!$A:$A,Inputs!L:L,,0) -> 0 | M71: =_xlfn.XLOOKUP($A71,Inputs!$A:$A,Inputs!M:M,,0) -> 0
A72: Dividend Yield | B72: =_xlfn.XLOOKUP($A72,Inputs!$A:$A,Inputs!B:B,,0) -> #N/A | C72: =_xlfn.XLOOKUP($A72,Inputs!$A:$A,Inputs!C:C,,0) -> #N/A | D72: =_xlfn.XLOOKUP($A72,Inputs!$A:$A,Inputs!D:D,,0) -> #N/A | E72: =_xlfn.XLOOKUP($A72,Inputs!$A:$A,Inputs!E:E,,0) -> #N/A | F72: =_xlfn.XLOOKUP($A72,Inputs!$A:$A,Inputs!F:F,,0) -> #N/A | G72: =_xlfn.XLOOKUP($A72,Inputs!$A:$A,Inputs!G:G,,0) -> #N/A | H72: =_xlfn.XLOOKUP($A72,Inputs!$A:$A,Inputs!H:H,,0) -> #N/A | I72: =_xlfn.XLOOKUP($A72,Inputs!$A:$A,Inputs!I:I,,0) -> #N/A | J72: =_xlfn.XLOOKUP($A72,Inputs!$A:$A,Inputs!J:J,,0) -> #N/A | K72: =_xlfn.XLOOKUP($A72,Inputs!$A:$A,Inputs!K:K,,0) -> #N/A | L72: =_xlfn.XLOOKUP($A72,Inputs!$A:$A,Inputs!L:L,,0) -> #N/A | M72: =_xlfn.XLOOKUP($A72,Inputs!$A:$A,Inputs!M:M,,0) -> #N/A
A73: Daily Volume in Millions of USD | B73: =_xlfn.XLOOKUP($A73,Inputs!$A:$A,Inputs!B:B,,0) -> 0 | C73: =_xlfn.XLOOKUP($A73,Inputs!$A:$A,Inputs!C:C,,0) -> Yahoo Finance | D73: =_xlfn.XLOOKUP($A73,Inputs!$A:$A,Inputs!D:D,,0) -> 0 | E73: =_xlfn.XLOOKUP($A73,Inputs!$A:$A,Inputs!E:E,,0) -> 0 | F73: =_xlfn.XLOOKUP($A73,Inputs!$A:$A,Inputs!F:F,,0) -> 0 | G73: =_xlfn.XLOOKUP($A73,Inputs!$A:$A,Inputs!G:G,,0) -> 0 | H73: =_xlfn.XLOOKUP($A73,Inputs!$A:$A,Inputs!H:H,,0) -> 0 | I73: =_xlfn.XLOOKUP($A73,Inputs!$A:$A,Inputs!I:I,,0) -> 0 | J73: =_xlfn.XLOOKUP($A73,Inputs!$A:$A,Inputs!J:J,,0) -> 0 | K73: =_xlfn.XLOOKUP($A73,Inputs!$A:$A,Inputs!K:K,,0) -> 0 | L73: =_xlfn.XLOOKUP($A73,Inputs!$A:$A,Inputs!L:L,,0) -> 0 | M73: =_xlfn.XLOOKUP($A73,Inputs!$A:$A,Inputs!M:M,,0) -> 0
B75: 2020 | C75: 2021 | D75: 2022
A76: Short % of Float | B76: 0 | C76: 0 | D76: 0
A77: EPS | B77: 0 | C77: 0 | D77: 0
A79: Corporate Bonds 3, 5 Y 10 | B79: Average Price | C79: Moody's | D79: YTM | E79: DIVISA
B80: =VLOOKUP($A80,Inputs!$A$5:$M$98,MATCH(B$4,Inputs!$B$5:$M$5,0)+1,FALSE) -> #N/A | C80: =VLOOKUP($A80,Inputs!$A$5:$M$98,MATCH(C$4,Inputs!$B$5:$M$5,0)+1,FALSE) -> #N/A | D80: =VLOOKUP($A80,Inputs!$A$5:$M$98,MATCH(D$4,Inputs!$B$5:$M$5,0)+1,FALSE) -> #N/A | E80: =VLOOKUP($A80,Inputs!$A$5:$M$98,MATCH(E$4,Inputs!$B$5:$M$5,0)+1,FALSE) -> #N/A

Sheet Inputs
G2: Figures in Millions of USD
G3: Company | H3: #VALUE!
D4: Report in millions
A5: RESULTS | B5: =OP!J20 -> 2022 | C5: =B5-1 -> 2021 | D5: =C5-1 -> 2020 | E5: =D5-1 -> 2019 | F5: =E5-1 -> 2018 | G5: =F5-1 -> 2017 | H5: =G5-1 -> 2016 | I5: =H5-1 -> 2015 | J5: =I5-1 -> 2014 | ... M5: =L5-1 -> 2011 | Q5: Hoja | R5: Nombre campo Bloomberg | T5: Cambio de signo | Z5: 2016 | AA5: 2015 | AB5: 2014 | AC5: 2013 | AD5: 2012 | AE5: 2011 | AF5: 2010 | AG5: 2009
A6: Net Sales | B6: 226954 | C6: 195929 | D6: 166761 | E6: 152703 | F6: 141576 | G6: 129025 | H6: 118719 | I6: 116199 | J6: 112640 | K6: 105156 | N6: Income Statement | O6: Sales | Q6: Ingreso | R6: Ingreso | Z6: 38537 | AA6: 47011 | AB6: 55184 | AC6: 55656 | AD6: 65875 | AE6: 60138 | AF6: 42588 | AG6: 32396
A7: Gross Profit | B7: 27572 | C7: 25245 | D7: 21822 | E7: 19817 | F7: 18424 | G7: 17143 | H7: 15818 | I7: 15134 | J7: 14182 | K7: 13208 | N7: Income Statement | O7: =+A7 -> Gross Profit | Q7: Ingreso | R7: + Coste de bienes y servicios | Z7: =Z6-28044 -> 10493 | AA7: =AA6-33546 -> 13465 | AB7: =AB6-40718 -> 14466 | AC7: =AC6-40727 -> 14929 | AD7: =+AD6-47055 -> 18820 | AE7: =+AE6-43578 -> 16560 | AF7: =+AF6-30367 -> 12221 | AG7: =+AG6-23886 -> 8510
A8: Operating Income | B8: 7793 | C8: 6708 | D8: 5435 | E8: 4737 | F8: 4526 | G8: 4123 | H8: 3711 | I8: 3678 | J8: 3258 | K8: 3106 | N8: Income Statement | O8: Operating Income | Q8: Ingreso | R8: + Ventas, generales y admin | Z8: =Z7-4383 -> 6110 | AA8: =AA7-4951 -> 8514 | AB8: =AB7-6529 -> 7937 | AC8: =AC7-5547 -> 9382 | AD8: =AD7-5919-2466-797-580-485 -> 8573 | AE8: =+AE7-5203-2297-826-1081 -> 7153 | AF8: =+AF7-4248-1905-914-1191 -> 3963 | AG8: =+AG7-3645-1421-1045-1822 -> 577
A9: Other Expenses (Revenues) | B9: 19653 | C9: 18435 | D9: 16384 | E9: 15028 | F9: 13898 | G9: 13020 | H9: 12107 | I9: 11456 | J9: 10924 | K9: 10102 | N9: Income Statement | O9: investment income+other income expense+income loss+minority interest+non controlling interest+share onf net profit+gain8losses) on equity investments+share of result from associates nd joint ventures+non operating profit+ | Q9: Ingreso | R9: + Investigación y desarrollo | S9: + Coste de financiación de beneficio | T9: + Otro gasto operativo | U9: - Beneficio (pérdida) de filiales | V9: - Minoritarios | Z9: =1853+596+595+1904+6+8 -> 4962 | AA9: =2119+587+2023+11 -> 4740 | AB9: =2380+624+1619-8+16 -> 4631 | AC9: =2046+727+981+6+14 -> 3774 | AD9: =-14+41 -> 27 | AE9: 53 | AF9: =58+24 -> 82 | AG9: =12-68 -> -56
A10: Net Financial Cost | B10: 97 | C10: 130 | D10: 71 | E10: 24 | F10: 84 | G10: 84 | H10: 92 | I10: 74 | J10: 61 | K10: 55 | N10: Income Statement | O10: interest expense+financial income and expenses+other financial expense-income+interest and other net+ | Q10: Ingreso | R10: - Ingreso (pérdida) no operacional | Z10: =505+518 -> 1023 | AA10: =507-161 -> 346 | AB10: =484-322 -> 162 | AC10: =465+35 -> 500 | AD10: =467-130 -> 337 | AE10: =396+32 -> 428 | AF10: =343-130 -> 213 | AG10: =389-381 -> 8
A11: Taxes | B11: 1925 | C11: 1601 | D11: 1308 | E11: 1061 | F11: 1263 | G11: 1325 | H11: 1243 | I11: 1195 | J11: 1109 | K11: 990 | N11: Income Statement | O11: Taxes | Q11: Ingreso | R11: - Gasto de impuesto a la renta (Beneficio) | Z11: 192 | AA11: 916 | AB11: 692 | AC11: 1319 | AD11: =2528 -> 2528 | AE11: =1720 -> 1720 | AF11: =968 -> 968 | AG11: =-270 -> -270
A12: Net Income | B12: 5844 | C12: 5007 | D12: 4002 | E12: 3659 | F12: 3134 | G12: 2679 | H12: 2350 | I12: 2377 | J12: 2058 | K12: 2039 | N12: Income Statement | O12: Net Income | Q12: Flujo de caja | R12: + Ingreso neto | Z12: -67 | AA12: 2512 | AB12: 2452 | AC12: 3789 | AD12: 5681 | AE12: =4928+24 -> 4952 | AF12: 2700 | AG12: 895
B13: =SUM(B8:B11) -> 29468 | C13: =SUM(C8:C11) -> 26874 | D13: =SUM(D8:D11) -> 23198 | E13: =SUM(E8:E11) -> 20850 | F13: =SUM(F8:F11) -> 19771 | G13: =SUM(G8:G11) -> 18552 | H13: =SUM(H8:H11) -> 17153 | I13: =SUM(I8:I11) -> 16403 | ... M13: =SUM(M8:M11) -> 0 | Z13: =Z8-Z10-Z9-Z11 -> -67 | AA13: =AA8-AA10-AA9-AA11 -> 2512 | AB13: =AB8-AB10-AB9-AB11 -> 2452 | AC13: =AC8-AC10-AC9-AC11 -> 3789 | AD13: =AD8-AD10-AD9-AD11 -> 5681 | AE13: =AE8-AE10-AE9-AE11 -> 4952 | AF13: =AF8-AF10-AF9-AF11 -> 2700 | AG13: =AG8-AG10-AG9-AG11 -> 895
A14: FINANCIAL POSITION | B14: =B12-B13 -> -23624 | C14: =C12-C13 -> -21867 | D14: =D12-D13 -> -19196 | E14: =E12-E13 -> -17191 | F14: =F12-F13 -> -16637 | G14: =G12-G13 -> -15873 | H14: =H12-H13 -> -14803 | I14: =I12-I13 -> -14026 | ... M14: =M12-M13 -> 0 | Z14: =Z12-Z13 -> 0 | AA14: =AA12-AA13 -> 0 | AB14: =AB12-AB13 -> 0 | AC14: =AC12-AC13 -> 0 | AD14: =AD12-AD13 -> 0 | AE14: =AE12-AE13 -> 0 | AF14: =AF12-AF13 -> 0 | AG14: =AG12-AG13 -> 0
A16: Weighted Average Shares (Basic NI) | B16: 443.9 | C16: 443.7 | D16: 443.1 | E16: 442.3 | F16: 439.8 | G16: 438.5 | H16: 438.4 | I16: 438.6 | J16: 439.5 | K16: 438.7
A17: Weighted Average Shares (Diluted NI) | B17: 444.5 | C17: 444.8 | D17: 444.3 | E17: 443.9 | F17: 442.9 | G17: 441.8 | H17: 440.9 | I17: 441.3 | J17: 442.7 | K17: 442.5
A19: Net gains (losses) from ForEx | B19: 106 | C19: 56 | D19: 7 | E19: 27 | F19: 23 | G19: -5 | H19: 28 | I19: 47 | J19: 26 | K19: 39
A20: Total Comprehensive Income | B20: =B12+B19 -> 5950 | C20: =C12+C19 -> 5063 | D20: =D12+D19 -> 4009 | E20: =E12+E19 -> 3686 | F20: =F12+F19 -> 3157 | G20: =G12+G19 -> 2674 | H20: =H12+H19 -> 2378 | I20: =I12+I19 -> 2424 | ... K20: =K12+K19 -> 2078
A22: Changes Net Working Capital | B22: =B23-C23 -> 1034 | C22: =C23-D23 -> -1378 | D22: =D23-E23 -> -2447 | E22: =E23-F23 -> -681 | F22: =F23-G23 -> -935 | G22: =G23-H23 -> -1885 | H22: =H23-I23 -> 910 | I22: =I23-J23 -> -727 | ... M22: =M23-N23 -> 0 | N22: cash flows | O22: NWC | Q22: Flujo de caja
A23: Net Working Capital | B23: =(B27-B28)-(B42-B44) -> -10278 | C23: =(C27-C28)-(C42-C44) -> -11312 | D23: =(D27-D28)-(D42-D44) -> -9934 | E23: =(E27-E28)-(E42-E44) -> -7487 | F23: =(F27-F28)-(F42-F44) -> -6806 | G23: =(G27-G28)-(G42-G44) -> -5871 | H23: =(H27-H28)-(H42-H44) -> -3986 | I23: =(I27-I28)-(I42-I44) -> -4896 | ... K23: =(K27-K28)-(K42-K44) -> -3541 | L23: =L27-L42-L28 -> 0 | M23: =M27-M42-M28 -> 0
A24: 2625 | C24: 2625 | D24: 2625 | E24: 2625 | F24: 2625 | G24: 2625 | H24: 2625 | I24: 2625 | J24: 2625 | K24: 2625 | L24: 2625 | M24: 2625 | N24: 2625 | Q24: Flujo de caja | R24: + Dividendos pagados | T24: Cambiar signo | Z24: 1799 | AA24: 1757 | AB24: 1620 | AC24: 1111 | AD24: 1617 | AE24: 1159 | AF24: 1084 | AG24: 1029
A25: BALANCE SHEET | D25: 2625 | E25: 2625 | F25: 2625 | G25: 2625 | H25: 2625 | I25: 2625 | J25: 2625 | K25: 2625 | L25: 2625 | M25: 2625 | N25: 2625 | Q25: Flujo de caja | R25: + Aumento en capital | S25: + Baja en capital | T25: Cambiar signo y hacer suma | Z25: 23 | AA25: =-33+2025 -> 1992 | AB25: 3817 | AC25: 1776 | AD25: -244 | AE25: -312 | AF25: -449 | AG25: -110
A26: ASSETS | N26: 1922 | O26: 2625
A27: Current | B27: 32696 | C27: 29505 | D27: 28120 | E27: 23495 | F27: 20289 | G27: 17317 | H27: 15218 | I27: 16779 | J27: 17558 | K27: 15840
A28: Cash & Eq. | B28: 11049 | C28: 12175 | D28: 13305 | E28: 9444 | F28: 7259 | G28: 5779 | H28: 4729 | I28: 6419 | J28: 7315 | K28: 6124 | N28: Balance Sheet | O28: Cash & Eq.
A29: Accounts Receivable | B29: 2241 | C29: 1803 | D29: 1550 | E29: 1535 | F29: 1669 | G29: 1432 | H29: 1252 | I29: 1224 | J29: 1148 | K29: 1201 | N29: Balance Sheet | O29: Accounts Receivable
A30: Inventory | B30: 17907 | C30: 14215 | D30: 12242 | E30: 11395 | F30: 11040 | G30: 9834 | H30: 8969 | I30: 8908 | J30: 8456 | K30: 7894 | N30: Balance Sheet | O30: Inventory | Q30: Balance | R30: + Efectivo, equivalentes y STI | Z30: 7168 | AA30: 6460 | AB30: 7341 | AC30: 6081 | AD30: 5490 | AE30: 3057 | AF30: 3592 | AG30: 4867
A31: Other Current Assets | B31: =B27-SUM(B28:B30) -> 1499 | C31: =C27-SUM(C28:C30) -> 1312 | D31: =D27-SUM(D28:D30) -> 1023 | E31: =E27-SUM(E28:E30) -> 1121 | F31: =F27-SUM(F28:F30) -> 321 | G31: =G27-SUM(G28:G30) -> 272 | H31: =H27-SUM(H28:H30) -> 268 | I31: =I27-SUM(I28:I30) -> 228 | ... M31: =M27-SUM(M28:M30) -> 0 | N31: Balance Sheet | O31: Inventory | Q31: Balance | R31: + Cuentas y notas por cobrar | S31: + Activos derivados y de cobertura | T31: + Inversiones y cuentas por cobrar a LP | Z31: =5981+8522+1029+13556 -> 29088 | AA31: =6695+8991+1170+13651 -> 30507 | AB31: =7737+9027+1364+14644 -> 32772 | AC31: 33499 | AD31: 33911 | AE31: 31031 | AF31: 28849 | AG31: 27162
A32: Non-current | B32: =B38-B27 -> 31470 | C32: =C38-C27 -> 29763 | D32: =D38-D27 -> 27436 | E32: =E38-E27 -> 21905 | F32: =F38-F27 -> 20541 | G32: =G38-G27 -> 19030 | H32: =H38-H27 -> 17945 | I32: =I38-I27 -> 16238 | ... M32: =M38-M27 -> 0
A33: Property, Plant and Equipment | B33: 44326 | C33: 41258 | D33: 38083 | E33: 32626 | F33: 30714 | G33: 28341 | H33: 26167 | I33: 23664 | J33: 22675 | K33: 21022 | Q33: Balance | R33: + Inventarios | Z33: 8614 | AA33: 9700 | AB33: 12205 | AC33: 12625 | AD33: 15547 | AE33: 14544 | AF33: 9587 | AG33: 6360
A34: Operating leases | B34: =B32-B33-B35-B36 -> -13848 | C34: =C32-C33-C35-C36 -> -12436 | D34: =D32-D33-D35-D36 -> -11502 | E34: =E32-E33-E35-E36 -> -11295 | F34: =F32-F33-F35-F36 -> -10717 | G34: =G32-G33-G35-G36 -> -9926 | H34: =H32-H33-H35-H36 -> -8922 | I34: =I32-I33-I35-I36 -> -8044 | ... K34: =K32-K33-K35-K36 -> -7079
A35: Equity Method Investments
A36: Other Non-Current Assets | B36: 992 | C36: 941 | D36: 855 | E36: 574 | F36: 544 | G36: 615 | H36: 700 | I36: 618 | J36: 538 | K36: 500 | L36: =L32-SUM(L33:L35) -> 0 | M36: =M32-SUM(M33:M35) -> 0 | N36: Balance Sheet | O36: Property, Plant and Equipment
A37: Other Assets | B37: =B31+B36 -> 2491 | C37: =C31+C36 -> 2253 | D37: =D31+D36 -> 1878 | E37: =E31+E36 -> 1695 | F37: =F31+F36 -> 865 | G37: =G31+G36 -> 887 | H37: =H31+H36 -> 968 | I37: =I31+I36 -> 846 | ... M37: =M31+M36 -> 0 | N37: Balance Sheet
A38: Total Assets | B38: 64166 | C38: 59268 | D38: 55556 | E38: 45400 | F38: 40830 | G38: 36347 | H38: 33163 | I38: 33017 | J38: 33024 | K38: 30283 | N38: Balance Sheet | O38: Total Assets | Q38: Balance | R38: + Propiedad, planta y equipo; neto | Z38: 15322 | AA38: 16090 | AB38: =16577 -> 16577 | AC38: 17075 | AD38: 16461 | AE38: 14395 | AF38: 12539 | AG38: 12386
N39: Balance Sheet | Z39: =Z40-SUM(Z30:Z38) -> 14512 | AA39: =AA40-SUM(AA30:AA38) -> 15585 | AB39: =AB40-SUM(AB30:AB38) -> 15786 | AC39: =AC40-SUM(AC30:AC38) -> 15616 | AD39: =AD40-SUM(AD30:AD38) -> 17947 | AE39: =AE40-SUM(AE30:AE38) -> 18419 | AF39: =AF40-SUM(AF30:AF38) -> 9453 | AG39: =AG40-SUM(AG30:AG38) -> 9263
N40: Balance Sheet | Q40: Balance | R40: Activos totales | Z40: 74704 | AA40: 78342 | AB40: 84681 | AC40: 84896 | AD40: 89356 | AE40: 81446 | AF40: 64020 | AG40: 60038
A41: LIABILITIES | N41: Balance Sheet
A42: Current Liabilities | B42: 31998 | C42: 29441 | D42: 24844 | E42: 23237 | F42: 19926 | G42: 17495 | H42: 15575 | I42: 16539 | J42: 14412 | K42: 13257 | N42: Balance Sheet | O42: Current Liabilities
A43: Payables | B43: 17848 | C43: 16278 | D43: 14172 | E43: 11679 | F43: 11237 | G43: 9608 | H43: 7612 | I43: 9011 | J43: 8491 | K43: 7872
A44: Short-Term Debt | B44: 73 | C44: 799 | D44: 95 | E44: 1699 | F44: 90 | G44: 86 | H44: 1100 | I44: 1283 | J44: 0 | K44: 0 | N44: Balance Sheet | O44: Short term Debt | Q44: Balance | R44: Pasivos totales corrientes | Z44: 26132 | AA44: 26242 | AB44: 27877 | AC44: 27297 | AD44: 29415 | AE44: =93+3895+8161+3386+2410+2691+298+1967+558+5102 -> 28561 | AF44: =204+3852+5856+2880+1670+1831+281+1521+495+3430 -> 22020 | AG44: =433+3650+2993+3351+797+1217+262+888+302+5399 -> 19292
A45: Short-Term Leases | B45: 484 | C45: 294 | D45: 262 | E45: 51 | F45: - | G45: - | H45: - | I45: - | J45: - | K45: -
A46: Other current liabilities | B46: =B42-SUM(B43:B45) -> 13593 | C46: =C42-SUM(C43:C45) -> 12070 | D46: =D42-SUM(D43:D45) -> 10315 | E46: =E42-SUM(E43:E45) -> 9808 | F46: =F42-SUM(F43:F45) -> 8599 | G46: =G42-SUM(G43:G45) -> 7801 | H46: =H42-SUM(H43:H45) -> 6863 | I46: =I42-SUM(I43:I45) -> 6245 | ... M46: =M42-SUM(M43:M45) -> 0 | N46: Balance Sheet | R46: + Préstamos CP | Z46: 7303 | AA46: 6967 | AB46: 4708 | AC46: 3679 | AD46: 5287 | AE46: 5660 | AF46: 3925 | AG46: 5701
A47: Non-current Liabilities | B47: =B51-B42 -> 11521 | C47: =C51-C42 -> 11749 | D47: =D51-D42 -> 12007 | E47: =E51-E42 -> 6579 | F47: =F51-F42 -> 7801 | G47: =G51-G42 -> 7773 | H47: =H51-H42 -> 5256 | I47: =I51-I42 -> 5635 | ... K47: =K51-K42 -> 6014 | N47: Balance Sheet | O47: Total non current liabilities
A48: Long-Term Debt | B48: 6484 | C48: 6692 | D48: 7514 | E48: 5124 | F48: 6487 | G48: 6573 | H48: 4061 | I48: 4852 | J48: 5093 | K48: 4998 | N48: Balance Sheet | O48: Long term debt | Z48: =Z44-Z46 -> 18829 | AA48: =AA44-AA46 -> 19275 | AB48: =AB44-AB46 -> 23169 | AC48: =AC44-AC46 -> 23618 | AD48: =AD44-AD46 -> 24128 | AE48: =AE44-AE46 -> 22901 | AF48: =AF44-AF46 -> 18095 | AG48: =AG44-AG46 -> 13591
A49: Long-Term Leases | B49: 3865 | C49: 3622 | D49: 3215 | E49: 370 | F49: - | G49: - | H49: - | I49: - | J49: - | K49: - | Q49: Balance | R49: Pasivos totales no corrientes | Z49: =61491-Z44 -> 35359 | AA49: =63457-AA44 -> 37215 | AB49: =67855-AB44 -> 39978 | AC49: 36721 | AD49: 41973 | AE49: =8415+16529+10956+3583 -> 39483 | AF49: =4505+15932+7584+2654 -> 30675 | AG49: =5652+16195+7420+2179 -> 31446
A50: Other non-current liabilities | B50: =B47-SUM(B48:B49) -> 1172 | C50: =C47-SUM(C48:C49) -> 1435 | D50: =D47-SUM(D48:D49) -> 1278 | E50: =E47-SUM(E48:E49) -> 1085 | F50: =F47-SUM(F48:F49) -> 1314 | G50: =G47-SUM(G48:G49) -> 1200 | H50: =H47-SUM(H48:H49) -> 1195 | I50: =I47-SUM(I48:I49) -> 783 | ... M50: =M47-SUM(M48:M49) -> 0 | N50: Balance Sheet | O50: Other non current Liabilities | R50: + Préstamos a largo plazo | Z50: 22818 | AA50: 25169 | AB50: 27784 | AC50: 26719 | AD50: 27752 | AE50: 24944 | AF50: 20437 | AG50: 21847
A51: Total Liabilities | B51: 43519 | C51: 41190 | D51: 36851 | E51: 29816 | F51: 27727 | G51: 25268 | H51: 20831 | I51: 22174 | J51: 20509 | K51: 19271 | N51: Balance Sheet | O51: Total Liabilities
N52: Balance Sheet | Z52: =Z49-Z50 -> 12541 | AA52: =AA49-AA50 -> 12046 | AB52: =AB49-AB50 -> 12194 | AC52: =AC49-AC50 -> 10002 | AD52: =AD49-AD50 -> 14221 | AE52: =AE49-AE50 -> 14539 | AF52: =AF49-AF50 -> 10238 | AG52: =AG49-AG50 -> 9599
N53: Balance Sheet | Z53: =+Z49+Z44 -> 61491 | AA53: =+AA49+AA44 -> 63457 | AB53: =+AB49+AB44 -> 67855 | AC53: =AC44+AC49 -> 64018 | AD53: =AD49+AD44 -> 71388 | AE53: =AE49+AE44 -> 68044 | AF53: =AF49+AF44 -> 52695 | AG53: =AG49+AG44 -> 50738
A54: Minority Interest | B54: 5 | C54: 514 | D54: 421 | E54: 341 | F54: 304 | G54: 301 | H54: 253 | I54: 226 | J54: 212 | K54: 179 | N54: Balance Sheet | O54: Minority Interest
N55: Balance Sheet
A56: Shareholder's Equity | B56: =B38-B51-B54 -> 20642 | C56: =C38-C51-C54 -> 17564 | D56: =D38-D51-D54 -> 18284 | E56: =E38-E51-E54 -> 15243 | F56: =F38-F51-F54 -> 12799 | G56: =G38-G51-G54 -> 10778 | H56: =H38-H51-H54 -> 12079 | I56: =I38-I51-I54 -> 10617 | ... M56: =M38-M51-M54 -> 0 | N56: Balance Sheet | Q56: Balance | R56: + Participación minoritaria/no dominante
A58: CASH FLOW
A59: Operating CF | B59: 7392 | C59: 8958 | D59: 8861 | E59: 6356 | F59: 5774 | G59: 6726 | H59: 3292 | I59: 4285 | J59: 3984 | K59: 3437
A60: Net Income | B60: 5844 | C60: 5007 | D60: 4002 | E60: 3659 | F60: 3134 | G60: 2679 | H60: 2350 | I60: 2377 | J60: 2058 | K60: 2039
A61: Depreciation & Amortization | B61: 1900 | C61: 1781 | D61: 1645 | E61: 1492 | F61: 1437 | G61: 1370 | H61: 1255 | I61: 1127 | J61: 1029 | K61: 946
A62: Changes in assets and liabilities | B62: =B59-B60-B61-B63 -> -952 | C62: =C59-C60-C61-C63 -> 1683 | D62: =D59-D60-D61-D63 -> 2712 | E62: =E59-E60-E61-E63 -> 808 | F62: =F59-F60-F61-F63 -> 1002 | G62: =G59-G60-G61-G63 -> 2687 | H62: =H59-H60-H61-H63 -> -305 | I62: =I59-I60-I61-I63 -> 543 | ... K62: =K59-K60-K61-K63 -> 463
A63: Other Adjustments | B63: 600 | C63: 487 | D63: 502 | E63: 397 | F63: 201 | G63: -10 | H63: -8 | I63: 238 | J63: -74 | K63: -11 | L63: =L59-L60-L61-L62 -> 0 | M63: =M59-M60-M61-M62 -> 0
A64: Investing CF | B64: -3915 | C64: -3535 | D64: -3891 | E64: -2865 | F64: -2947 | G64: -2366 | H64: -2345 | I64: -2480 | J64: -2093 | K64: -2251
A65: Net Capex | B65: -3891 | C65: -3588 | D65: -2810 | E65: -2998 | F65: -2969 | G65: -2502 | H65: -2649 | I65: -2393 | J65: -1993 | K65: -2083
A66: Investments & Acquisitions | B66: =B64-B65-B67 -> 3 | C66: =C64-C65-C67 -> 101 | D66: =D64-D65-D67 -> -1019 | E66: =E64-E65-E67 -> 163 | F66: =F64-F65-F67 -> 26 | G66: =G64-G65-G67 -> 132 | H66: =H64-H65-H67 -> 274 | I66: =I64-I65-I67 -> -114 | ... K66: =K64-K65-K67 -> -165
A67: Other Inflows (Outflows) | B67: -27 | C67: -48 | D67: -62 | E67: -30 | F67: -4 | G67: 4 | H67: 30 | I67: 27 | J67: -20 | K67: -3 | L67: 41 | M67: 28
A68: Financing CF | B68: -3890 | C68: -4283 | D68: -6488 | E68: -1147 | F68: -1147 | G68: -1281 | H68: -3218 | I68: -2419 | J68: -2324 | K68: -786
A69: Debt Borrowing | B69: 0 | C69: 0 | D69: 3992 | E69: 508 | F69: 80 | G69: 3782 | H69: 372 | I69: 1176 | J69: 281 | K69: 4043
A70: Debt Repayment | B70: -800 | C70: -94 | D70: -3200 | E70: -89 | F70: -86 | G70: -2436 | H70: -1394 | I70: -97 | J70: -103 | K70: -357
A71: Lease Increases
A72: Lease Payments
A73: Dividends | B73: -1498 | C73: -1318 | D73: -1479 | E73: -1038 | F73: -689 | G73: -804 | H73: -736 | I73: -664 | J73: -584 | K73: -511 | N73: cash flows FINANCING | O73: Dividends paid
A74: Share buyback | B74: -802 | C74: -808 | D74: -526 | E74: -519 | F74: -545 | G74: -671 | H74: -706 | I74: -659 | J74: -498 | K74: -157 | N74: cash flows FINANCING | O74: =+A74 -> Share buyback
A75: Other Inflows (Outflows) | B75: =B68-B69-B70-B71-B72-B73-B74 -> -790 | C75: =C68-C69-C70-C71-C72-C73-C74 -> -2063 | D75: =D68-D69-D70-D71-D72-D73-D74 -> -5275 | E75: =E68-E69-E70-E71-E72-E73-E74 -> -9 | F75: =F68-F69-F70-F71-F72-F73-F74 -> 93 | G75: =G68-G69-G70-G71-G72-G73-G74 -> -1152 | H75: =H68-H69-H70-H71-H72-H73-H74 -> -754 | I75: =I68-I69-I70-I71-I72-I73-I74 -> -2175 | ... M75: =M68-M69-M70-M71-M72-M73-M74 -> 0
A76: FX | B76: -249 | C76: 46 | D76: 70 | E76: -15 | F76: -37 | G76: 25 | H76: 50 | I76: -418 | J76: -11 | K76: -114
A77: Changes in cash | B77: =B59+B64+B68+B76 -> -662 | C77: =C59+C64+C68+C76 -> 1186 | D77: =D59+D64+D68+D76 -> -1448 | E77: =E59+E64+E68+E76 -> 2329 | F77: =F59+F64+F68+F76 -> 1643 | G77: =G59+G64+G68+G76 -> 3104 | H77: =H59+H64+H68+H76 -> -2221 | I77: =I59+I64+I68+I76 -> -1032 | ... M77: =M59+M64+M68+M76 -> 0
O78: (Vitalis will later fill this info)
A79: Other Data | E79: Corporate Bonds 3, 5 Y 10 | H79: Average Price | J79: Moody's | K79: YTM | L79: DIVISA
A80: Number of employees | B80: 304000 | C80: 10-K | N80: bloomberg
A81: Shares Outstanding (Thousands) | B81: 442604 | C81: Yahoo finance | N81: bloomberg
A82: Float | B82: =OP!M20 -> 0.99738238 | C82: Yahoo finance | N82: bloomberg
A83: Insiders Own | B83: =OP!M21 -> 0.002 | C83: Yahoo finance | N83: bloomberg
A84: Fitch/ S&P Rating | B84: =OP!M22 -> 0.79 | C84: 10-K | N84: bloomberg
A85: Dividend Yield(Yahoo Finance) | B85: =Peers!C35 -> 18.103241 | C85: Yahoo finance | N85: bloomberg
A86: Daily Volume in Millions of USD | C86: Yahoo Finance | N86: bloomberg
B87: 2020 | C87: =B87+1 -> 2021 | D87: =C87+1 -> 2022
A88: Short % of Float | E88: Yahoo Finance
A89: EPS | E89: Yahoo Finance

Sheet Inflation Projections
B4: Projected annual inflation rate in the United States 2010-2028
B5: Projected annual inflation rate in the United States from 2010 to 2028
B7: 2010 | C7: 1.64 | D7: in %
B8: 2011 | C8: 3.14 | D8: in %
B9: 2012 | C9: 2.07 | D9: in %
B10: 2013 | C10: 1.47 | D10: in %
B11: 2014 | C11: 1.62 | D11: in %
B12: 2015 | C12: 0.12 | D12: in %
B13: 2016 | C13: 1.26 | D13: in %
B14: 2017 | C14: 2.13 | D14: in %
B15: 2018 | C15: 2.44 | D15: in %
B16: 2019 | C16: 1.81 | D16: in %
B17: 2020 | C17: 1.25 | D17: in %
B18: 2021 | C18: 4.69 | D18: in %
B19: 2022 | C19: 8 | D19: in %
B20: 2023* | C20: 4.5 | D20: in % | E20: =C20/100 -> 0.045
B21: 2024* | C21: 2.3 | D21: in % | E21: =C21/100 -> 0.023
B22: 2025* | C22: 2.1 | D22: in % | E22: =C22/100 -> 0.021
B23: 2026* | C23: 2 | D23: in % | E23: =C23/100 -> 0.02
B24: 2027* | C24: 2 | D24: in % | E24: =C24/100 -> 0.02
B25: 2028* | C25: 2.1 | D25: in % | E25: =C25/100 -> 0.021
A31: Source: | B31: https://www.statista.com/statistics/244983/projected-inflation-rate-in-the-united-states/

Sheet CPI Projections
B4: U.S. projected Consumer Price Index 2010-2028
B5: Projected Consumer Price Index in the United States from 2010 to 2028
B7: 2010 | C7: 218.08
B8: 2011 | C8: 224.92
B9: 2012 | C9: 229.59
B10: 2013 | C10: 232.95
B11: 2014 | C11: 236.72
B12: 2015 | C12: 237
B13: 2016 | C13: 240.01
B14: 2017 | C14: 245.12
B15: 2018 | C15: 251.1
B16: 2019 | C16: 255.65
B17: 2020 | C17: 258.84
B18: 2021 | C18: 270.97
... B25: 2028* | C25: 339.39

Sheet Sector Impact
E2: Sector | F2: Sub-Industry | H2: Low | K2: Sector | L2: Environment | Q2: Social
E3: Communication Services | F3: Interactive Home Entertainment | H3: Medium | L3: CO2 | M3: Water | N3: Energy | O3: Waste | P3: Degradation | Q3: Turnover | R3: Compensation | S3: Reputation | T3: Discrimination | U3: Security | V3: Damage | W3: Pension | X3: Supply | Y3: Community | Z3: Public | AA3: Litigation
E4: Communication Services | F4: Interactive Media & Services | H4: High | K4: Communication Services | L4: Low | M4: Low | N4: Medium | O4: Low | P4: Low | Q4: Medium | R4: Medium | S4: Low | T4: Low | U4: High | V4: Low | W4: Low | X4: Low | Y4: Low | Z4: Low | AA4: Medium
B5: Environmental | E5: Communication Services | F5: Integrated Telecommunication Services | H5: Very High | K5: Consumer Discretionary | L5: Low | M5: Low | N5: Medium | O5: Medium | P5: Low | Q5: Medium | R5: Medium | S5: Low | T5: Low | U5: Medium | V5: Medium | W5: Medium | X5: High | Y5: Low | Z5: High | AA5: Low
B6: Direct CO2 emissions | E6: Communication Services | F6: Cable & Satellite | K6: Consumer Staples | L6: High | M6: Very High | N6: High | O6: High | P6: High | Q6: Medium | R6: High | S6: High | T6: Low | U6: Medium | V6: Medium | W6: Low | X6: High | Y6: Low | Z6: Very High | AA6: Low
B7: Total Water Use | E7: Communication Services | F7: Broadcasting | K7: Energy | L7: Very High | M7: Very High | N7: Medium | O7: Very High | P7: High | Q7: High | R7: Medium | S7: Medium | T7: Medium | U7: Medium | V7: High | W7: Medium | X7: Medium | Y7: High | Z7: High | AA7: Low
K8: Renewable Energy | L8: Low | M8: Low | N8: Low | O8: Medium | P8: Medium | Q8: Low | R8: Medium | S8: Medium | T8: High | U8: Medium | V8: Low | W8: Low | X8: Medium | Y8: Medium | Z8: High | AA8: Low
B9: Total Energy Consumption | E9: Communication Services | F9: Movies & Entertainment | K9: Financials | L9: Low | M9: Low | N9: Low | O9: Low | P9: Low | Q9: Low | R9: Low | S9: Medium | T9: High | U9: Medium | V9: Low | W9: Low | X9: Low | Y9: Low | Z9: Medium | AA9: Low
K10: Forestry | L10: Low | M10: Medium | N10: Low | O10: Medium | P10: High | Q10: Low | R10: Low | S10: Low | T10: Low | U10: Low | V10: Low | W10: Low | X10: Low | Y10: Medium | Z10: Low | AA10: Low
B11: Waste Management | E11: Communication Services | F11: Advertising | K11: Health Care | L11: Low | M11: Medium | N11: Low | O11: Low | P11: Low | Q11: Low | R11: Low | S11: Medium | T11: Low | U11: High | V11: Low | W11: Low | X11: Low | Y11: Low | Z11: Low | AA11: Low
B12: Land Degradation/Deforestation/Biodiversity loss/Animal sufering/... | E12: Communication Services | F12: Alternative Carriers | K12: Industrials | L12: Very High | M12: Very High | N12: Very High | O12: High | P12: High | Q12: Low | R12: Medium | S12: High | T12: Very High | U12: Medium | V12: Very High | W12: Medium | X12: Very High | Y12: Very High | Z12: Very High | AA12: High
B13: Social | E13: Communication Services | F13: Publishing | K13: Information Technology | L13: Medium | M13: Low | N13: High | O13: Low | P13: Low | Q13: Low | R13: Low | S13: Low | T13: Low | U13: High | V13: Low | W13: Low | X13: Low | Y13: Low | Z13: Medium | AA13: Very High
B14: Employee turnover | E14: Communication Services | F14: Wireless Telecommunication Services | K14: Materials | L14: Very High | M14: Very High | N14: Very High | O14: Very High | P14: High | Q14: High | R14: High | S14: Medium | T14: High | U14: Low | V14: Very High | W14: Medium | X14: Medium | Y14: Very High | Z14: High | AA14: Medium
