Workbook
Name Sectors: '[1]Sector Impact'!$K$4:$K$16
Name Sectors: 'Sector Impact'!$K$4:$K$16

Sheet OP
B2: 45410 | C2: Team 12 | D2: 30th April 2024 | E2: =Inputs!H3 -> #VALUE! | L2: {=_FV(E2,"Bolsa")} -> Nasdaq Stock Market | M2: SIC:
B3: #VALUE! | D3: COMPANY DESCRIPTION | H3: CEO & BOARD OF DIRECTORS
D4: PACCAR Inc. represents a hallmark of American innovation and industrial might, focusing on the specialized design and manufacturing of heavy commercial vehicles. This enterprise orchestrates its global operations through a trio of distinguished subsidiaries: DAF, Kenworth, and Peterbilt. Each of these brands has carved out a significant presence in the trucking industry, offering a wide range of products that cater to various markets worldwide. The essence of PACCAR's operation lies in its ability to combine cutting-edge technology with rigorous quality standards, ensuring that each vehicle that rolls off the production line is a marvel of engineering and a tool designed to withstand the demands of heavy-duty transportation. | H4: Name (Gender;Age) | I4: Tenure | J4: Executive? | K4: Other roles
H5: R. Preston Feight (M;56) | I5: 5 years | J5: Yes | K5: CEO (since 2019); Was an enginner at Ford for six years
H6: Franklin L. Feder (M;72) | I6: 6 years | J6: Yes | K6: Director of Minerals Technologies (since 2017) ; Former CEO of Alcoa Latin Mareica & Caribbean (2004-2014)
H7: Dame Alison J. Carnwath (F;71) | I7: 19 years | J7: Yes | K7: Senior advisor to Evercore Partners (since 2005); Director of Coller Capital (since 2015) and EG Group Ltd. And ASDA Group Ltd. (since 2021)
H8: Kirk S. Hachigian (M;64) | I8: 16 years | J8: Yes | K8: Chairman of Allegion PLC (since 2023); Director of NextEra Energy (since 2013); Former Chairman of JELD-WEN Holding (2016-2019)
H9: Barbara B. Hulit (F;57) | I9: 1 year | J9: No | K9: Former CEO of Advanced Healthcare Solutions (2019-2022); Director of Envista Holdings (since 2021) and Novanta Corporation (since 2022)
H10: Roderick C. Mcgeary (M;73) | I10: 12 years | J10: Yes | K10: Director of Raymond James Financial (since 2015); Former chairman of BearingPoint (2004-2009)
H11: Cynthia A. Niekamp (F;64) | I11: 1 year | J11: No | K11: Vice-President of Automotive Coating at PPG Industries; Former President of BorgWarner's TorqTransfer Systems (2004-2008); Director of Ball Corporation (since 2016)
H12: John M. Pigott (M;60) | I12: 15 years | J12: No | K12: Borther of Mark C. Pigott; Partner in Beta Business Ventures
H13: Mark C. Pigott (M;70) | I13: 30 years | J13: No | K13: Executive Chairman; Former director of Franklin Resources Inc.
H14: Ganesh Ramaswamy (M;55) | I14: 3 years | J14: Yes | K14: Executive Vice President of Industrial & Energy Technology at Baker Hughes; Former President of Global Services for Johnson Controls (2019-2022)
H15: Mark A. Schulz (M;71) | I15: 4 years | J15: Yes | K15: President and CEO of M.A. Schulz and Associates; Founding partner of Fontinalis Partners LLC
B16: {=_FV(E2,"Moeda")&" MILLIONS"} -> USD MILLIONS | H16: Gregory M. E. Spierkel (M;67) | I16: 16 years | J16: Yes | K16: Former CEO of Ingram Micro (2005-2012); Director of sChneider Electric SE (Paris) (since 2014)
B17: COMPANY OVERVIEW
B18: Stock | D18: Liquidity and Solvency | F18: Segments | I18: ="Profitability ("&J19&")" -> Profitability (2023) | L18: Multiples
B19: Last Price | C19: 105.92 | D19: Total Assets | E19: =_xlfn.XLOOKUP(D19,'Fin. Data'!A:A,'Fin. Data'!B:B,,0) -> 40823 | F19: Regions | H19: % Sales | I19: Reporting Year | J19: 2023 | L19: Float | M19: =Inputs!B82 -> 0.9814
B20: Outstanding Shares | C20: {=_FV(E2,"Ações em circulação",TRUE)} -> 524010700 | D20: Total Liabilities | E20: =_xlfn.XLOOKUP(D20,'Fin. Data'!A:A,'Fin. Data'!B:B,,0) -> 24945 | F20: =Segments!C5 -> United States and Canada | H20: =Segments!B5 -> 0.53637901 | I20: End of Year | J20: 45291 | L20: Insiders Own | M20: =Inputs!B83 -> 0.0186
B21: Market Cap. | C21: =C19*C20/1000000 -> 55503.213 | D21: Cash/Share | E21: =_xlfn.XLOOKUP("Cash & Eq.",'Fin. Data'!A:A,'Fin. Data'!B:B,,0)*1000000/C20 -> 13.705827 | F21: =Segments!C6 -> Europe | H21: =Segments!B6 -> 0.24884848 | I21: EBITDA | K21: =_xlfn.XLOOKUP(I21,'Fin. Data'!A:A,'Fin. Data'!B:B,,0) -> 6770.9 | L21: b (Yahoo) | M21: {=_FV(E2,"Beta")} -> 0.9418
B22: +Total Debt | C22: ='Fin. Data'!B58 -> 14238 | D22: EBITDA/Net Financial Cost (NFC) | E22: =_xlfn.XLOOKUP("EBITDA",'Fin. Data'!A:A,'Fin. Data'!B:B,,0)/_xlfn.XLOOKUP("Net Financial Cost",'Fin. Data'!A:A,'Fin. Data'!B:B,,0) -> -52.487597 | F22: =Segments!C7 -> Other | H22: =Segments!B7 -> 0.21477251 | I22: Depreciation & Amortization | K22: =_xlfn.XLOOKUP(I22,'Fin. Data'!A:A,'Fin. Data'!B:B,,0) -> #N/A | L22: Credit Score | M22: =Inputs!B84 -> A+/A1
B23: -Cash | C23: ='Fin. Data'!B39 -> 7182 | D23: Debt/EBITDA | E23: =_xlfn.XLOOKUP("Total Debt",'Fin. Data'!A:A,'Fin. Data'!B:B,,0)/_xlfn.XLOOKUP("EBITDA",'Fin. Data'!A:A,'Fin. Data'!B:B,,0) -> 2.1028224 | I23: EBIT | K23: =_xlfn.XLOOKUP(I23,'Fin. Data'!A:A,'Fin. Data'!B:B,,0) -> 5847 | L23: Price/Book Value | M23: =IFERROR((C19*C20/(E19-E20))/1000000,"") -> 3.4956048
B24: =Enterprise Value | C24: =C21+C22-C23 -> 62559.213 | D24: "Others Assets"/Asset | E24: =_xlfn.XLOOKUP("Other Assets",'Fin. Data'!A:A,'Fin. Data'!B:B,,0)/_xlfn.XLOOKUP("Total Assets",'Fin. Data'!A:A,'Fin. Data'!B:B,,0) -> 0.48125811 | I24: Net Income | K24: =_xlfn.XLOOKUP(I24,'Fin. Data'!A:A,'Fin. Data'!B:B,,0) -> 4601 | L24: NCF(3y avg)/Asset | M24: =IFERROR(K30/E19,"") -> -0.0019433489
B25: Holdings (nac/int'l) | C25: - | D25: Debt/Assets | E25: =_xlfn.XLOOKUP(D25,'Fin. Data'!A:A,'Fin. Data'!B:B,,0) -> 0.34877398 | F25: Categories | H25: % Sales | I25: EPS | K25: =1000000*K24/C20 -> 8.7803551 | L25: Price/Net Inc. (3y avg) | M25: =IFERROR(C21/K29,"") -> 17.592144
B26: t liq. (Holdings/Vol.) | C26: - | D26: EBITDA Margin (average) | E26: =AVERAGE(_xlfn.XLOOKUP("EBITDA Margin",'Fin. Data'!A:A,'Fin. Data'!B:D,,0)) -> 0.16583335 | F26: =Segments!C13 -> Trucks | H26: =Segments!B13 -> 0.7642581 | I26: ROA | K26: =K24/E19 -> 0.11270607 | L26: EV/Asset | M26: =IFERROR(C24/E19,"") -> 1.5324502
B27: % Short | C27: =Inputs!B88 -> 0.0165 | D27: Operating Margin (average) | E27: =AVERAGE(_xlfn.XLOOKUP("Operating Margin",'Fin. Data'!A:A,'Fin. Data'!B:D,,0)) -> 0.13512585 | F27: =Segments!C14 -> Parts | H27: =Segments!B14 -> 0.18260389 | I27: ROIC | K27: =K24/(E19-(E20-C22)) -> 0.15277593 | L27: EV/Ebitda (3y average) | M27: =IFERROR(C24/K28,"") -> 12.680579
B28: Traffic ESG | D28: Net Income Margin (average) | E28: =AVERAGE(_xlfn.XLOOKUP("Net Income Margin",'Fin. Data'!A:A,'Fin. Data'!B:D,,0)) -> 0.10474247 | F28: =Segments!C15 -> Financial Services | H28: =Segments!B15 -> 0.051580817 | I28: EBITDA (3y average) | K28: =AVERAGE(_xlfn.XLOOKUP("EBITDA",'Fin. Data'!A:A,'Fin. Data'!B:D,,0)) -> 4933.4667 | L28: Price/NCF (3y average) | M28: =IFERROR(C21/K30,"") -> -699.62034
B29: E | F29: =Segments!C16 -> Other | H29: =Segments!B16 -> 0.001557189 | I29: Net Income (3y average) | K29: =AVERAGE(_xlfn.XLOOKUP("Net Income",'Fin. Data'!A:A,'Fin. Data'!B:D,,0)) -> 3155 | L29: Bonds 1,3,5a (USD) | M29: -
B30: S | D30: Net Financial Cost/Avg Net Debt | E30: =-_xlfn.XLOOKUP("Net Financial Cost",'Fin. Data'!A:A,'Fin. Data'!B:B,,0)/AVERAGE(_xlfn.XLOOKUP("Net Debt",'Fin. Data'!A:A,'Fin. Data'!B:D,,0)) -> 0.018565603 | I30: NCF (3y average) | K30: =AVERAGE(_xlfn.XLOOKUP("Net Financial Cost",'Fin. Data'!A:A,'Fin. Data'!B:D,,0)) -> -79.333333 | L30: Div+Rep.(3y avg)/Price | M30: =-IFERROR(SUM(E51:E53)/(3*C21),"") -> 0.019448724
B31: G | L31: Div. Yield | M31: =-IFERROR(L52/C21,"") -> 0.027360578
B32: INVESTMENT THESIS
B33: Pillars of Recommendation | H33: Recommendation | I33: Valuation Assumptions
B34: Pillar | C34: Explanation | H34: HOLD | I34: Check DCF
B35: Industry | C35: The industry it's in is very stable and PACCAR seems it be performing well amidst the industry.
B36: Diversification of Products | C36: Their expansion into the EV market could increase overall revenue and diversify it's source.
B37: Increase of Global Commerce | C37: The increase of international commerce entails a need for transportation, which boosts the industry's activity.
B38: Risks of Investment | H38: Price Target | I38: Valuation
B39: Risk | C39: Explanation | H39: =DCF!D75 -> 98.051639 | I39: Discount Rate | J39: =DCF!F50 -> 0.0925 | L39: Price M. Upside | M39: =SARD!AJ14 -> 0.11047345
B40: Cyclical | C40: The company is very dependant on economic cycles, so if international shipment decreases, it'll affect the company a lot.
B41: Dependancy on other Industries | C41: The transportation industry is heavily dependant on other industries, a decrease of activity on other industries will decrease the activity of the transportation industry. | I41: Upside | J41: =DCF!D74 -> -0.07428589 | L41: EV M. Upside | M41: =SARD!AM14 -> 0.010642162
B42: Production Costs, Capacity and Inflation | C42: The Company’s products are exposed to variability in material and commodity costs. Commodity or component price increases, cost pressures due to inflation, significant shortages of component products and labor availability may adversely impact the Company’s financial results or use of its production capacity.
B43: FINANCIAL PERFORMANCE
B44: Year | C44: Net Sales | D44: Operating Margin | E44: Dividends + Share Buyback | F44: Net Cash Flow | G44: Debt/Assets | H44: Depreciation | I44: Capex + Investments | J44: Cash Flow
B45: =B46-1 -> 2015 | C45: {=_xlfn.SORTBY(TRANSPOSE(_xlfn.XLOOKUP(C$44,'Fin. Data'!$A:$A,'Fin. Data'!$B:$J,,0)),$B$45:$B$53,-1)} -> 19115 | D45: {=_xlfn.SORTBY(TRANSPOSE(_xlfn.XLOOKUP(D$44,'Fin. Data'!$A:$A,'Fin. Data'!$B:$J,,0)),$B$45:$B$53,-1)} -> 0.12780539 | E45: {=_xlfn.SORTBY(TRANSPOSE(_xlfn.XLOOKUP(E$44,'Fin. Data'!$A:$A,'Fin. Data'!$B:$J,,0)),$B$45:$B$53,-1)} -> -882.1 | F45: =Inputs!K77 -> -12.5 | G45: {=_xlfn.SORTBY(TRANSPOSE(_xlfn.XLOOKUP(G$44,'Fin. Data'!$A:$A,'Fin. Data'!$B:$J,,0)),$B$45:$B$53,-1)} -> 0.4070109 | H45: {=_xlfn.SORTBY(TRANSPOSE(_xlfn.XLOOKUP(H$44,'Fin. Data'!$A:$A,'Fin. Data'!$B:$J,,0)),$B$45:$B$53,-1)} -> 907.1 | I45: {=_xlfn.SORTBY(TRANSPOSE(_xlfn.XLOOKUP(I$44,'Fin. Data'!$A:$A,'Fin. Data'!$B:$J,,0)),$B$45:$B$53,-1)} -> -2019.5 | L45: =J19 -> 2023 | M45: =L45-1 -> 2022
B46: =B47-1 -> 2016 | C46: 17033 | D46: 0.072975988 | E46: -899.8 | F46: =Inputs!J77 -> 278.8 | G46: 0.41063036 | H46: 993.1 | I46: -1692 | J46: Net Income | L46: =_xlfn.XLOOKUP($J46,'Fin. Data'!$A:$A,'Fin. Data'!B:B,,0) -> 4601 | M46: =_xlfn.XLOOKUP($J46,'Fin. Data'!$A:$A,'Fin. Data'!C:C,,0) -> 3012 | N46: =(C46/C45)-1 -> -0.1089197 | O46: =(D46/D45)-1 -> -0.42900696
B47: =B48-1 -> 2017 | C47: 19456 | D47: 0.11790707 | E47: -558.3 | F47: =Inputs!I77 -> -100.7 | G47: 0.37879693 | H47: 1107.5 | I47: -2037.4 | J47: Operating CF | L47: =_xlfn.XLOOKUP($J47,'Fin. Data'!$A:$A,'Fin. Data'!B:B,,0) -> 4190 | M47: =_xlfn.XLOOKUP($J47,'Fin. Data'!$A:$A,'Fin. Data'!C:C,,0) -> 3027 | N47: =(C47/C46)-1 -> 0.14225327 | O47: =(D47/D46)-1 -> 0.61569683 | Q47: =F47/F46-1 -> -1.3611908 | R47: =H47/H46-1 -> 0.11519484 | S47: =I47/I46-1 -> 0.20413712
B48: =B49-1 -> 2018 | C48: 23496 | D48: 0.12244637 | E48: -1158.7 | F48: =Inputs!H77 -> 449 | G48: 0.39051095 | H48: 1054.1 | I48: -1636.7 | J48: Investing CF | L48: =_xlfn.XLOOKUP($J48,'Fin. Data'!$A:$A,'Fin. Data'!B:B,,0) -> -2871 | M48: =_xlfn.XLOOKUP($J48,'Fin. Data'!$A:$A,'Fin. Data'!C:C,,0) -> -2033 | N48: =(C48/C47)-1 -> 0.20764803 | O48: =(D48/D47)-1 -> 0.038498975 | Q48: =F48/F47-1 -> -5.4587885 | R48: =H48/H47-1 -> -0.048216704 | S48: =I48/I47-1 -> -0.19667223
B49: =B50-1 -> 2019 | C49: 25600 | D49: 0.12523438 | E49: -1248.8 | F49: =Inputs!G77 -> 1071.2 | G49: 0.39575473 | H49: 1077.3 | I49: -2105.9 | J49: Net Capex | L49: =_xlfn.XLOOKUP($J49,'Fin. Data'!$A:$A,'Fin. Data'!B:B,,0) -> -695 | M49: =_xlfn.XLOOKUP($J49,'Fin. Data'!$A:$A,'Fin. Data'!C:C,,0) -> -525 | N49: =(C49/C48)-1 -> 0.089547157 | O49: =(D49/D48)-1 -> 0.022769161 | Q49: =F49/F48-1 -> 1.3857461 | R49: =H49/H48-1 -> 0.022009297 | S49: =I49/I48-1 -> 0.28667441
B50: =B51-1 -> 2020 | C50: 18729 | D50: 0.093971915 | E50: -1281.9 | F50: =Inputs!F77 -> 739.2 | G50: 0.3841472 | H50: 1049 | I50: -1883 | J50: Investments & Acquisitions | L50: =_xlfn.XLOOKUP($J50,'Fin. Data'!$A:$A,'Fin. Data'!B:B,,0) -> -731.1 | M50: =_xlfn.XLOOKUP($J50,'Fin. Data'!$A:$A,'Fin. Data'!C:C,,0) -> -1035.8 | N50: =(C50/C49)-1 -> -0.26839844 | O50: =(D50/D49)-1 -> -0.24963162 | Q50: =F50/F49-1 -> -0.30993279 | R50: =H50/H49-1 -> -0.026269377 | S50: =I50/I49-1 -> -0.10584548
B51: =B52-1 -> 2021 | C51: 23522 | D51: 0.10377519 | E51: -709.5 | F51: =Inputs!E77 -> -635.5 | G51: 0.35605078 | H51: 903.3 | I51: -1808.9 | J51: Financing CF | L51: =_xlfn.XLOOKUP($J51,'Fin. Data'!$A:$A,'Fin. Data'!B:B,,0) -> 1102.2 | M51: =_xlfn.XLOOKUP($J51,'Fin. Data'!$A:$A,'Fin. Data'!C:C,,0) -> 304.9 | N51: =(C51/C50)-1 -> 0.25591329 | O51: =(D51/D50)-1 -> 0.10432132 | Q51: =F51/F50-1 -> -1.8597132 | R51: =H51/H50-1 -> -0.13889418 | S51: =I51/I50-1 -> -0.039352098
B52: =B53-1 -> 2022 | C52: 28820 | D52: 0.1351492 | E52: -1006.8 | F52: =Inputs!D$77 -> -111.3 | G52: 0.34484313 | H52: 790.2 | I52: -1560.8 | J52: Dividends | L52: =_xlfn.XLOOKUP($J52,'Fin. Data'!$A:$A,'Fin. Data'!B:B,,0) -> -1518.6 | M52: =_xlfn.XLOOKUP($J52,'Fin. Data'!$A:$A,'Fin. Data'!C:C,,0) -> -1004.7 | N52: =(C52/C51)-1 -> 0.22523595 | O52: =(D52/D51)-1 -> 0.30232672 | Q52: =F52/F51-1 -> -0.82486231 | R52: =H52/H51-1 -> -0.12520757 | S52: =I52/I51-1 -> -0.13715518
B53: =J19 -> 2023 | C53: 35127 | D53: 0.16645316 | E53: -1522.1 | F53: =Inputs!C77 -> 1262.6 | G53: 0.34877398 | H53: 923.9 | I53: -1426.1 | J53: Share Buyback | L53: =_xlfn.XLOOKUP($J53,'Fin. Data'!$A:$A,'Fin. Data'!B:B,,0) -> -3.5 | M53: =_xlfn.XLOOKUP($J53,'Fin. Data'!$A:$A,'Fin. Data'!C:C,,0) -> -2.1 | N53: =(C53/C52)-1 -> 0.21884108 | O53: =(D53/D52)-1 -> 0.23162515 | Q53: =F53/F52-1 -> -12.344115 | R53: =H53/H52-1 -> 0.16919767 | S53: =I53/I52-1 -> -0.086301896
B54: Annual Growth Rate | C54: =IFERROR((C53/C45)^(1/8)-1,"") -> 0.079029566 | D54: =IFERROR((D53/D45)^(1/8)-1,"") -> 0.033577053 | F54: =IFERROR((F53/F45)^(1/8)-1,"") | H54: =IFERROR((H53/H45)^(1/8)-1,"") -> 0.0022965259 | J54: FX | L54: =_xlfn.XLOOKUP($J54,'Fin. Data'!$A:$A,'Fin. Data'!B:B,,0) -> 69.6 | M54: =_xlfn.XLOOKUP($J54,'Fin. Data'!$A:$A,'Fin. Data'!C:C,,0) -> -36.3 | N54: =(C54/C53)-1 -> -0.99999775 | O54: =(D54/D53)-1 -> -0.79827927
B55: Average Growth Rate | C55: =IFERROR(AVERAGE(N46:N53),"") -> 0.09526508 | D55: =IFERROR(AVERAGE(O46:O53),"") -> 0.079574948 | F55: =IFERROR(AVERAGE(Q46:Q53),"") -> -2.9675509 | H55: =IFERROR(AVERAGE(S46:S53),"") -> -0.010645052 | J55: Changes in Cash | L55: =L47-L48+L51-L52-L53 -> 9685.3 | M55: =M47-M48+M51-M52-M53 -> 6371.7
B56: CVAR | C56: =IFERROR(STDEV(C46:C53)/AVERAGE(C46:C53),"") -> 0.24781235 | D56: =IFERROR(STDEV(D45:D53)/AVERAGE(D45:D53),"") -> 0.22374053 | F56: =IFERROR(STDEV(F45:F53)/AVERAGE(F45:F53),"") -> 1.884378 | H56: =IFERROR(STDEV(H45:H53)/AVERAGE(H45:H53),"") -> 0.10627518 | J56: Inventory/D Revenues | L56: =IFERROR(SUM(I50:I53)/(C53-C49),"") -> -0.70103915 | M56: =IFERROR((SUM(I50:I53)-SUM(H50:H53))/(C53-C49),"") -> -1.0858822
B57: Last Year | C57: =IFERROR(C53/C52-1,"") -> 0.21884108 | D57: =IFERROR(D53/D52-1,"") -> 0.23162515 | F57: =IFERROR(1-(F53/F52),"") -> 12.344115 | H57: =IFERROR(1-(H53/H52),"") -> -0.16919767 | J57: t inversiones; t adq. neto dep. | L57: =IFERROR(L56/E26,"") -> -4.2273713 | M57: =IFERROR(M56/E26,"") -> -6.5480328
B58: QUALITATIVE ANALYSIS
B59: SWOT ANALYSIS | J59: HOLDERS
B60: Strenghts | E60: Weaknesses | J60: Name | M60: % Stake
B61: Strong Brand Portfolio: PACCAR's brand portfolio, including Kenworth, Peterbilt, and DAF, caters to diverse market needs, enhancing global market penetration and ensuring sustained presence across different demographics. Diversification: Spanning truck manufacturing, financial services, and aftermarket parts, PACCAR's diversified business model mitigates risks and stabilizes revenue, supporting long-term profitability and customer engagement. Innovation and Technology: PACCAR's leadership in electric and autonomous truck technologies positions it at the forefront of industry advancements, aligning with sustainability goals and securing a competitive edge. | E61: Complex Regulations: Adhering to stringent global regulations, like Euro VI standards, imposes continuous technological updates and R&D investments, increasing operational costs and complicating production processes. Production Complexity and Flexibility: The complexity of PACCAR's production processes limits operational flexibility, hindering quick adaptation to market shifts, such as the transition to electric vehicles, and potentially increasing costs during transitions. High Dependence on the North American Market: PACCAR's significant reliance on North America for revenue exposes it to regional economic fluctuations, which can threaten its overall financial performance. | J61: Vanguard Fiduciary Ttrust Co | M61: 11,87%
J62: The Vanguard Group | M62: 11,87%
J63: BlackRock Advisors LLC | M63: 5,58
J64: STATE STREET CORPORATION | M64: 4,13%
J65: GEODE CAPITAL MANAGEMENT LLC | M65: 2,4%
J66: FIDELITY MANAGEMENT | M66: 2,3%
J67: MERRYL LYNCH INTERNATIONAL | M67: 2,12%
J68: MASSACHUSETTS FINANCIAL SERVICES | M68: 1,49%
J69: BLACKROCK LIFE LTD | M69: 1,26%
J70: EATON VANCE MANAGEMENT | M70: 1,23%
B71: Opportunities | E71: Threats
B72: Government synergy: Partnering with governments in emerging markets, such as Canada and Brazil, on transportation initiatives can open avenues for growth and collaboration. Expand to emerging markets: Increasing infrastructure development in Asia, Africa, and South America offers growth opportunities for PACCAR to expand its market presence and capitalize on rising demand for transportation solutions. Electric and Autonomous Vehicles: With rising interest in eco-friendly and autonomous vehicles, PACCAR can leverage its R&D to accelerate developments in these areas, aligning with market trends and future demand. | E72: Raw material prices: Volatility in raw material prices, such as steel and aluminum, can impact production costs and profitability, affecting PACCAR's bottom line. Dependency on crucial suppliers: Reliance on key suppliers for critical components poses risks of supply chain disruptions, potentially impacting production and sales. Economic Fluctuations: Downturns in crucial markets like North America and Europe can reduce truck sales, adversely affecting PACCAR's revenue and profitability.
J81: TOTAL | M81: =SUM(M61:M80) -> 0
B82: NOTES | G82: STOCK PERFORMANCE (5 years)
B83: In addition to its core business of truck manufacturing, PACCAR has diversified its operations to encompass a broad spectrum of related services and products. The company boasts an efficient parts division, ensuring that customers have access to high-quality components and replacements, thereby enhancing the longevity and performance of their vehicles. The financial services segment of PACCAR offers tailored financing options, insurance, and leasing solutions, facilitating the acquisition and maintenance of its vehicles by businesses of all sizes. Furthermore, PACCAR's foray into the manufacture and marketing of industrial winches complements its primary offerings, providing robust solutions for cargo handling and logistics challenges. | G83: #VALUE!
G107: =Inputs!H3 -> #VALUE! | I107: =Peers!C2 -> #VALUE! | J107: =Peers!C3 -> #VALUE! | L107: =Peers!C4 -> #VALUE! | M107: =Peers!C5 -> #VALUE!

Sheet Acuerdo
A1: Invertir
A2: NO invertir
A3: Mantener sin elevar posición
A4: Mantener (y seguir comprando)
A5: Liquidar
A6: PENDIENTE

Sheet Segments
B2: ="Regions "&"("&OP!$J$19&")" -> Regions (2023) | Q2: Products
D3: Nominal value | K3: YoY Growth
B4: Weight | C4: Region (Plant) | D4: =OP!J19 -> 2023 | E4: =D4-1 -> 2022 | F4: =E4-1 -> 2021 | G4: =F4-1 -> 2020 | H4: =G4-1 -> 2019 | I4: =H4-1 -> 2018 | K4: =OP!J19 -> 2023 | L4: =K4-1 -> 2022 | M4: =L4-1 -> 2021 | N4: =M4-1 -> 2020 | O4: =N4-1 -> 2019 | P4: =O4-1 -> 2018
B5: =IFERROR(D5/$D$8,"") -> 0.53637901 | C5: United States and Canada | D5: 18841.6 | E5: 15379.2 | F5: 12388.8 | G5: 10526.6 | H5: 15119.3 | I5: 13165.7 | K5: =IFERROR((D5-E5)/E5,"-") -> 0.22513525 | L5: =IFERROR((E5-F5)/F5,"-") -> 0.24137931 | M5: =IFERROR((F5-G5)/G5,"-") -> 0.17690422 | N5: =IFERROR((G5-H5)/H5,"-") -> -0.30376406 | O5: =IFERROR((H5-I5)/I5,"-") -> 0.14838558 | P5: =IFERROR((I5-J5)/J5,"-") -> -
B6: =IFERROR(D6/$D$8,"") -> 0.24884848 | C6: Europe | D6: 8741.4 | E6: 7486.5 | F6: 6325.4 | G6: 4871.2 | H6: 6104.7 | I6: 6071.9 | K6: =IFERROR((D6-E6)/E6,"-") -> 0.16762172 | L6: =IFERROR((E6-F6)/F6,"-") -> 0.18356151 | M6: =IFERROR((F6-G6)/G6,"-") -> 0.29853014 | N6: =IFERROR((G6-H6)/H6,"-") -> -0.20205743 | O6: =IFERROR((H6-I6)/I6,"-") -> 0.0054019335 | P6: =IFERROR((I6-J6)/J6,"-") -> -
B7: =IFERROR(D7/$D$8,"") -> 0.21477251 | C7: Other | D7: 7544.4 | E7: 5954 | F7: 4808.1 | G7: 3330.7 | H7: 4375.7 | I7: 4258.1 | K7: =IFERROR((D7-E7)/E7,"-") -> 0.26711454 | L7: =IFERROR((E7-F7)/F7,"-") -> 0.23832699 | M7: =IFERROR((F7-G7)/G7,"-") -> 0.44357042 | N7: =IFERROR((G7-H7)/H7,"-") -> -0.23881893 | O7: =IFERROR((H7-I7)/I7,"-") -> 0.027617952 | P7: =IFERROR((I7-J7)/J7,"-") -> -
B8: =SUM(B5:B7) -> 1 | C8: TOTAL | D8: =SUM(D5:D7) -> 35127.4 | E8: =SUM(E5:E7) -> 28819.7 | F8: =SUM(F5:F7) -> 23522.3 | G8: =SUM(G5:G7) -> 18728.5 | H8: =SUM(H5:H7) -> 25599.7 | I8: =SUM(I5:I7) -> 23495.7 | K8: =(D8-E8)/E8 -> 0.21886765 | L8: =(E8-F8)/F8 -> 0.22520757 | M8: =(F8-G8)/G8 -> 0.25596284 | N8: =(G8-H8)/H8 -> -0.2684094 | O8: =(H8-I8)/I8 -> 0.0895483 | P8: -
B10: ="Categories "&"("&OP!$J$19&")" -> Categories (2023)
D11: Nominal value | K11: YoY Growth
B12: Weight | C12: Category | D12: =OP!J19 -> 2023 | E12: =D12-1 -> 2022 | F12: =E12-1 -> 2021 | G12: =F12-1 -> 2020 | H12: =G12-1 -> 2019 | I12: =H12-1 -> 2018 | K12: =OP!J19 -> 2023 | L12: =K12-1 -> 2022 | M12: =L12-1 -> 2021 | N12: =M12-1 -> 2020 | O12: =N12-1 -> 2019 | P12: =O12-1 -> 2018
B13: =IFERROR(D13/$D$17,"") -> 0.7642581 | C13: Trucks | D13: 26846.4 | E13: 21486.2 | F13: 16799.7 | G13: 13164.8 | H13: 19989.5 | I13: 18187 | K13: =IFERROR((D13-E13)/E13,"-") -> 0.24947175 | L13: =IFERROR((E13-F13)/F13,"-") -> 0.27896331 | M13: =IFERROR((F13-G13)/G13,"-") -> 0.2761075 | N13: =IFERROR((G13-H13)/H13,"-") -> -0.34141424 | O13: =IFERROR((H13-I13)/I13,"-") -> 0.099109254 | P13: =IFERROR((I13-J13)/J13,"-") -> -
B14: =IFERROR(D14/$D$17,"") -> 0.18260389 | C14: Parts | D14: 6414.4 | E14: 5764.3 | F14: 4944.3 | G14: 3912.9 | H14: 4024.9 | I14: 3838.9 | K14: =IFERROR((D14-E14)/E14,"-") -> 0.11278039 | L14: =IFERROR((E14-F14)/F14,"-") -> 0.16584754 | M14: =IFERROR((F14-G14)/G14,"-") -> 0.26358966 | N14: =IFERROR((G14-H14)/H14,"-") -> -0.027826778 | O14: =IFERROR((H14-I14)/I14,"-") -> 0.048451379 | P14: =IFERROR((I14-J14)/J14,"-") -> -
B15: =IFERROR(D15/$D$17,"") -> 0.051580817 | C15: Financial Services | D15: 1811.9 | E15: 1505.4 | F15: 1687.8 | G15: 1574.2 | H15: 1480 | I15: 1357.1 | K15: =IFERROR((D15-E15)/E15,"-") -> 0.20360037 | L15: =IFERROR((E15-F15)/F15,"-") -> -0.10806968 | M15: =IFERROR((F15-G15)/G15,"-") -> 0.072163639 | N15: =IFERROR((G15-H15)/H15,"-") -> 0.063648649 | O15: =IFERROR((H15-I15)/I15,"-") -> 0.090560755 | P15: =IFERROR((I15-J15)/J15,"-") -> -
B16: =IFERROR(D16/$D$17,"") -> 0.001557189 | C16: Other | D16: 54.7 | E16: 63.8 | F16: 90.5 | G16: 76.6 | H16: 105.3 | I16: 112.7 | K16: =IFERROR((D16-E16)/E16,"-") -> -0.14263323 | L16: =IFERROR((E16-F16)/F16,"-") -> -0.29502762 | M16: =IFERROR((F16-G16)/G16,"-") -> 0.18146214 | N16: =IFERROR((G16-H16)/H16,"-") -> -0.27255461 | O16: =IFERROR((H16-I16)/I16,"-") -> -0.065661047 | P16: =IFERROR((I16-J16)/J16,"-") -> -
B17: =SUM(B13:B16) -> 1 | C17: TOTAL | D17: =SUM(D13:D16) -> 35127.4 | E17: =SUM(E13:E16) -> 28819.7 | F17: =SUM(F13:F16) -> 23522.3 | G17: =SUM(G13:G16) -> 18728.5 | H17: =SUM(H13:H16) -> 25599.7 | I17: =SUM(I13:I16) -> 23495.7 | K17: =(D17-E17)/E17 -> 0.21886765 | L17: =(E17-F17)/F17 -> 0.22520757 | M17: =(F17-G17)/G17 -> 0.25596284 | N17: =(G17-H17)/H17 -> -0.2684094 | O17: =(H17-I17)/I17 -> 0.0895483 | P17: -
B19: Categories | D19: Description | I19: Graphs
B20: =C13 -> Trucks | D20: The Truck segment includes the design and manufacture of high-quality, light-, medium- and heavyduty commercial trucks
B21: =C14 -> Parts | D21: Parts segment includes the distribution of aftermarket parts for trucks and related commercial vehicles, both of which are sold through the same network of independent dealers
B22: =C15 -> Financial Services | D22: Financing or leasing of PACCAR products and services provided to truck customers and dealers
B23: =C16 -> Other | D23: Other includes the winch business as well as sales, income and expenses not attributable to a reportable segment
B24: Industry | J24: Graphs (Industry Forecasts)
B25: Drivers | D25: Description
B26: Economy's strenght | D26: Economic factors such as GDP growth, consumer spending, industrial production, and construction activity play a significant role for Paccar business. If there is a strong economic growth that will, most likely, lead to an increase in freight transportation needs. | E26: Economic Conditions: Economic factors such as GDP growth, consumer spending, industrial production, and construction activity play a significant role in driving demand for trucks. Strong economic growth typically leads to increased freight transportation needs, boosting demand for new trucks.
B27: Dependent sectors | D27: This industry is interconnected with other sectors such as manufacturing, agriculture, retail, and logistics. Changes in supply chain dynamics and shifts in trade patterns will impact demand for trucks. (e.g.: e-commerce)
B28: Environmental adaptability | D28: The recent environmental issues and sustainability concerns are increasing demand for cleaner, more fuel-efficient trucks with lower carbon emissions. Regulatory initiatives and efforts are influencing manufacturers to develop eco-friendly solutions.
B29: Sales forecast
B30: Source | D30: Market Growth CAGR | G30: Period
B31: The Brainy Insights | D31: 0.0683 | G31: 2023 - 2032
B32: Mordor Intelligence | D32: 0.074 | G32: 2019 - 2029
B33: Zion | D33: 0.039 | G33: 2020 - 2026
B34: AVERAGE | D34: =AVERAGE(D31:F33) -> 0.060433333 | G34: {=SMALL(_xlfn.NUMBERVALUE(LEFT(G31:G33,4)),1)&" - "&LARGE(_xlfn.NUMBERVALUE(RIGHT(G31:G33,4)),1)} -> 2019 - 2032
B35: Company's Strategy / Extra Notes
B36: >The company has a differentiated approach to research and development, partnering with suppliers and technology companies in early stages of technology development, and scaling direct investments closer to the time of commercialization >Conservative approach to financial management and a long-term business perspective >Customer loyalty: strong emphasis on building high-quality and reliable trucks. Its brands, including Peterbilt, Kenworth, and DAF, are known for their durability, performance, and long-term value, attracting loyal customers worldwide.
S40: The Company evaluates the performance of its Truck and Parts segments based on operating profits, which excludes investment income, other income and expense, and income taxes

Sheet Peers
B1: Peer Logo | C1: Peer Name | D1: Description | G1: Currency | H1: End of Fiscal Year | I1: Next Earnings Date
B2: #VALUE! | C2: #VALUE! | D2: {=_FV(C2,"Description")} -> Volvo Car AB is a Sweden-based automotive brand. Volvo Car Group is focused on the design, engineering, manufacturing, distribution and sale of passenger cars, with particular focus on sustainability, fully electric cars and direct consumer relations, including subscription and other new mobility services. Volvo Car Group’s addressable market is the global premium passenger car market. Moreover, the Company’s intention is to be a pure electric car company and as a result it is undergoing a shift in its business model to a direct sales model in most of its markets. Volvo Cars’ commitment to electrification also results in the launch of Polestar, a progressive stand-alone electric performance car brand, in which Volvo Cars owns shares. Volvo Cars also holds shares in the automotive brand LYNK&CO, which focuses on young open-minded urban people through a flexible customer offering. | G2: {=_FV(C2,"Currency")} -> SEK | H2: 45291 | I2: 45399
B3: #VALUE! | C3: #VALUE! | D3: {=_FV(C3,"Description")} -> Tesla, Inc. designs, develops, manufactures, sells and leases high-performance fully electric vehicles and energy generation and storage systems, and offer services related to its products. The Company's segments include automotive, and energy generation and storage. The automotive segment includes the design, development, manufacturing, sales and leasing of high-performance fully electric vehicles, and sales of automotive regulatory credits. This segment also includes sales of used vehicles, non-warranty after-sales vehicle services, body shop and parts, paid supercharging, vehicle insurance and retail merchandise. Its consumer vehicles include the Model 3, Y, S, X and Cybertruck. The energy generation and storage segment includes the design, manufacture, installation, sales and leasing of solar energy generation and energy storage products and related services and sales of solar energy systems incentives. Its lithium-ion battery energy storage products include Powerwall and Megapack. | G3: {=_FV(C3,"Currency")} -> USD | H3: 45291 | I3: 45405
B4: #VALUE! | C4: #VALUE! | D4: {=_FV(C4,"Description")} -> Daimler Truck Holding AG is a Germany-based company, which is now operating as an independent entity. It manufactures commercial vehicles, develops new solutions, and invents new technologies. The Company is engaged in the manufacturing of Medium Duty Truck (MDT) and Heavy-Duty Trucks (HDT). The Company produces buses and trucks under brands, such as Bharat Benz, Freightliner, FUSO, Mercedes-Benz, Setra, Thomas Built Buses, and Western Star. The Company also offers tailored financial services to support the purchase and use of its trucks and buses. The Company has operations in France, Germany, India, Mexico, Brazil, and the United States of America, The Company's truck product range includes light, medium, and heavy trucks for long-distance distribution and construction site haulage, special vehicles which are used in municipal application as well as industrial engines. | G4: {=_FV(C4,"Currency")} -> EUR | H4: 45291 | I4: 45415
B5: #VALUE! | C5: #VALUE! | D5: {=_FV(C5,"Description")} -> Renault SA is a France-based company that designs, manufactures and sells passenger cars and light commercial vehicles and related services. Its brand portfolio consists of Renault, Dacia (both operating globally), Alpine (active in Europe, Japan and Australia), Renault Samsung Motors (operates only in South Korea) and Lada (operates only in Russia). The Group operating segments are three: Automotive excluding AVTOVAZ, Sales Financing and AVTOVAZ. Automotive excluding AVTOVAZ consists of the Group’s automotive activities comprising the production, sales, and distribution of passenger and light commercial vehicles, automobile service for the Renault, Dacia and Samsung brands and investments in Nissan, among others. Sales Financing, carried out by RCI Banque, covers the financing operations for sales of vehicles to dealers and end-users. AVTOVAZ, consists of the Russian automotive group AVTOVAZ and its parent company, the joint venture lliance Rostec Auto b.v. | G5: {=_FV(C5,"Currency")} -> EUR | H5: 45291 | I5: 45404
D6: {=_FV(C6,"Descrição")} -> #VALUE! | G6: {=_FV(C6,"Moeda")} -> #VALUE!
B8: {="In Millions "&_FV(OP!E2,"Moeda")} -> In Millions USD | C8: =OP!E2 -> #VALUE! | D8: =C2 -> #VALUE! | E8: =C3 -> #VALUE! | F8: =C4 -> #VALUE! | G8: =C5 -> #VALUE! | H8: AVERAGE | I8: Deviation from Average
B9: Company Info | H9: =IFERROR(AVERAGE(C9:F9),"") | L9: TRAFFIC
B10: Market Cap | C10: {=_FV(C8,"Capitalização de mercado",TRUE)/1000000} -> 59359.932 | D10: {=_FV(D8,"Market cap",TRUE)/1000000*0.099334} -> 11818.004 | E10: {=_FV(E8,"Market cap",TRUE)/1000000} -> 549790.47 | F10: {=_FV(F8,"Market cap",TRUE)/1000000*1.103594} -> 42740.121 | G10: {=_FV(G8,"Market cap",TRUE)/1000000*1.103594} -> 14828.043 | H10: =IFERROR(AVERAGE(C10:G10),"") -> 135707.31 | I10: =SQRT((C10-H10)^2) -> 76347.382 | M10: Best Value
B11: Net Sales (current) | C11: =C60 -> 35127 | D11: =D60 -> 60424 | E11: =E60 -> 96773 | F11: =F60 -> 60424 | G11: =G60 -> 56625 | H11: =IFERROR(AVERAGE(C11:G11),"") -> 61874.6 | I11: =SQRT((C11-H11)^2) -> 26747.6
B12: Profitability | H12: =IFERROR(AVERAGE(C12:F12),"") | M12: Important Value
B13: Sales Growth (ttm) | C13: =C60/C59-1 -> 0.21884108 | D13: =D60/D59-1 -> 0.12836601 | E13: =E60/E59-1 -> 0.79798599 | F13: =F60/F59-1 -> 0.12836601 | G13: =G60/G59-1 -> 0.16120499 | H13: =IFERROR(AVERAGE(C13:G13),"") -> 0.28695282 | I13: =SQRT((C13-H13)^2) -> 0.068111735
B14: Sales Growth (36m) | C14: =C60/C58-1 -> 0.87554061 | D14: =D60/D58-1 -> 0.47210447 | E14: =E60/E58-1 -> 2.0686517 | F14: =F60/F58-1 -> 0.47210447 | G14: =G60/G58-1 -> 0.14280813 | H14: =IFERROR(AVERAGE(C14:G14),"") -> 0.80624187 | I14: =SQRT((C14-H14)^2) -> 0.069298731 | M14: Worst Value
B15: Operating Margin | C15: =C63/C60 -> 0.16645316 | D15: =D63/D60 -> 0.09706408 | E15: =E63/E60 -> 0.0918748 | F15: =F63/F60 -> 0.09706408 | G15: =G63/G60 -> 0.038463576 | H15: =IFERROR(AVERAGE(C15:G15),"") -> 0.098183939 | I15: =SQRT((C15-H15)^2) -> 0.068269217
B16: Net Income Margin | C16: =C66/C60 -> 0.13098187 | D16: =D66/D60 -> 0.067555938 | E16: =E66/E60 -> 0.15499158 | F16: =F66/F60 -> 0.067555938 | G16: =G66/G60 -> 0.041960265 | H16: =IFERROR(AVERAGE(C16:G16),"") -> 0.092609117 | I16: =SQRT((C16-H16)^2) -> 0.038372749
B17: Return on Equity (RoE) | C17: =C66/C79 -> 0.28977201 | D17: =D66/D79 -> 0.32518123 | E17: =E66/E79 -> 0.23947058 | F17: =F66/F79 -> 0.17121047 | G17: =G66/G79 -> 0.072364013 | H17: =IFERROR(AVERAGE(C17:G17),"") -> 0.21959966 | I17: =SQRT((C17-H17)^2) -> 0.070172352
B18: Return on Invested Capital (ROIC) | C18: =(C66+C65)/(C78+C79) -> 0.11568601 | D18: =(D66+D65)/(D78+D79) -> 0.29231912 | E18: =(E66+E65)/(E78+E79) -> 0.14732406 | F18: =(F66+F65)/(F78+F79) -> 0.11085575 | G18: =(G66+G65)/(G78+G79) -> 0.02791276 | H18: =IFERROR(AVERAGE(C18:G18),"") -> 0.13881954 | I18: =SQRT((C18-H18)^2) -> 0.023133526
B19: Solvency | H19: =IFERROR(AVERAGE(C19:F19),"")
B20: Debt/Assets | C20: =C78/C74 -> 0.34877398 | D20: =D78/D74 -> 0.10181079 | E20: =E78/E74 -> 0.049053631 | F20: =F78/F74 -> 0.33332909 | G20: =G78/G74 -> 0.53908817 | H20: =IFERROR(AVERAGE(C20:G20),"") -> 0.27441113 | I20: =SQRT((C20-H20)^2) -> 0.074362846
B21: Net Debt/EBITDA | C21: =(C78-C69)/C62 -> 1.0421067 | D21: =(D78-D69)/D62 -> 0.69337733 | E21: =(E78-E69)/E62 -> -0.54012391 | F21: =(F78-F69)/F62 -> 2.4067242 | G21: =(G78-G69)/G62 -> 7.9151254 | H21: =IFERROR(AVERAGE(C21:G21),"") -> 2.3034419 | I21: =SQRT((C21-H21)^2) -> 1.2613353
B22: Debt/Assets (Leases Free Debt) | C22: =(C78-C77)/C74 -> 0.3443157 | D22: =(D78-D77)/D74 -> 0.10181079 | E22: =(E78-E77)/E74 -> 0.049053631 | F22: =(F78-F77)/F74 -> 0.33332909 | G22: =(G78-G77)/G74 -> 0.53908817 | H22: =IFERROR(AVERAGE(C22:G22),"") -> 0.27351948 | I22: =SQRT((C22-H22)^2) -> 0.070796229
B23: Net Debt/EBIT (Leases Free Debt) | C23: =((C78-C77)-C69)/C62 -> 1.0152269 | D23: =((D78-D77)-D69)/D62 -> 0.69337733 | E23: =((E78-E77)-E69)/E64 -> -8.0472527 | F23: =((F78-F77)-F69)/F62 -> 2.4067242 | G23: =((G78-G77)-G69)/G62 -> 7.9151254 | H23: =IFERROR(AVERAGE(C23:G23),"") -> 0.79664023 | I23: =SQRT((C23-H23)^2) -> 0.2185867
B24: Leasing Debt/Total Debt | C24: =C77/C78 -> 0.012782694 | D24: =D77/D78 -> 0 | E24: =E77/E78 -> 0 | F24: =F77/F78 -> 0 | G24: =G77/G78 -> 0 | H24: =IFERROR(AVERAGE(C24:G24),"") -> 0.0025565388 | I24: =SQRT((C24-H24)^2) -> 0.010226155
B25: Interest Coverage Ratio | C25: =-C62/C64 -> 52.487597 | D25: =-D62/D64 -> -23.971751 | E25: =-E62/E64 -> -14.898901 | F25: =-F62/F64 -> -35.719626 | G25: =-G62/G64 -> -82.229167 | H25: =IFERROR(AVERAGE(C25:G25),"") -> -20.86637 | I25: =SQRT((C25-H25)^2) -> 73.353967
B26: Liquidity
B27: Current Ratio | C27: =C72/C76 -> 0.9077795 | D27: =D72/D76 -> 0.97492496 | E27: =E72/E76 -> 1.725894 | F27: =F72/F76 -> 1.6458441 | G27: =G72/G76 -> 1.1077948 | H27: =IFERROR(AVERAGE(C27:G27),"") -> 1.2724475 | I27: =SQRT((C27-H27)^2) -> 0.36466797
B28: Quick Ratio | C28: =(C69+C70)/C76 -> 0.96651211 | D28: =(D69+D70)/D76 -> 0.1612056 | E28: =(E69+E70)/E76 -> 0.55868234 | F28: =(F69+F70)/F76 -> 0.53957349 | G28: =(G69+G70)/G76 -> 0.76405135 | H28: =IFERROR(AVERAGE(C28:G28),"") -> 0.59800498 | I28: =SQRT((C28-H28)^2) -> 0.36850713
B29: Activity | H29: =IFERROR(AVERAGE(C29:F29),"")
B30: Inventory Turnover | C30: =C61/C71 -> 10.436166 | D30: =D61/D71 -> 8.3865561 | E30: =E61/E71 -> 5.8060326 | F30: =F61/F71 -> 4.7050381 | G30: =G61/G71 -> 8.2396025 | H30: =IFERROR(AVERAGE(C30:G30),"") -> 7.5146791 | I30: =SQRT((C30-H30)^2) -> 2.921487
B31: Acc. Receivable Turnover | C31: =C60/C70 -> 15.981347 | D31: =D60/D70 -> 31.536534 | E31: =E60/E70 -> 27.586374 | F31: =F60/F70 -> 10.43953 | G31: =G60/G70 -> 1.017246 | H31: =IFERROR(AVERAGE(C31:G31),"") -> 17.312206 | I31: =SQRT((C31-H31)^2) -> 1.3308596
A32: Price/Sales | B32: Payables Turnover | C32: =C61/C75 -> 16.152553 | D32: =D61/D75 -> 7.6805623 | E32: =E61/E75 -> 5.4821565 | F32: =F61/F75 -> 8.5142397 | G32: =G61/G75 -> 5.0937429 | H32: =IFERROR(AVERAGE(C32:G32),"") -> 8.5846508 | I32: =SQRT((C32-H32)^2) -> 7.5679018
B33: Fixed Asset Turnover | C33: =C60/C73 -> 9.1153726 | D33: =D60/D74 -> 1.7069409 | E33: =E59/E72 -> 1.0847912 | F33: =F60/F73 -> 4.3769649 | G33: =G60/G73 -> 4.1882396 | H33: =IFERROR(AVERAGE(C33:G33),"") -> 4.0944618 | I33: =SQRT((C33-H33)^2) -> 5.0209108
B34: Total Asset Turnover | C34: =C60/C74 -> 0.86047081 | D34: =D60/D74 -> 1.7069409 | E34: =E60/E74 -> 0.907661 | F34: =F60/F74 -> 0.76886078 | G34: =G60/G74 -> 0.42087229 | H34: =IFERROR(AVERAGE(C34:G34),"") -> 0.93296115 | I34: =SQRT((C34-H34)^2) -> 0.072490338
B35: Valuation | H35: =IFERROR(AVERAGE(C35:F35),"")
B36: Price/Earnings | C36: =C10/C66 -> 12.901528 | D36: =D10/D66 -> 2.8951505 | E36: =E10/E66 -> 36.655142 | F36: =F10/F66 -> 10.470387 | G36: =G10/G66 -> 6.240759 | H36: =IFERROR(AVERAGE(C36:G36),"") -> 13.832593 | I36: =SQRT((C36-H36)^2) -> 0.931065
B37: Price/Sales | C37: =C10/C60 -> 1.6898663 | D37: =D10/D60 -> 0.19558461 | E37: =E10/E60 -> 5.6812383 | F37: =F10/F60 -> 0.70733683 | G37: =G10/G60 -> 0.2618639 | H37: =IFERROR(AVERAGE(C37:G37),"") -> 1.707178 | I37: =SQRT((C37-H37)^2) -> 0.017311714
B38: Price/Book | C38: =C10/C79 -> 3.7385018 | D38: =D10/D79 -> 0.94144861 | E38: =E10/E79 -> 8.7778279 | F38: =F10/F79 -> 1.7926399 | G38: =G10/G79 -> 0.45160637 | H38: =IFERROR(AVERAGE(C38:G38),"") -> 3.1404049 | I38: =SQRT((C38-H38)^2) -> 0.59809692
B39: EV/Sales | C39: =(C78+C10-C69)/C60 -> 1.8907374 | D39: =(D78+D10-D69)/D60 -> 0.24427387 | E39: =(E78+E10-E69)/E60 -> 5.6055663 | F39: =(F78+F10-F69)/F60 -> 1.0118019 | G39: =(G78+G10-G69)/G60 -> 1.3652988 | H39: =IFERROR(AVERAGE(C39:G39),"") -> 2.0235357 | I39: =SQRT((C39-H39)^2) -> 0.13279828
B40: EV/EBITDA | C40: =(C78+C10-C69-C77)/C62 -> 9.782146 | D40: =(D78+D10-D69-D77)/D62 -> 3.4786718 | E40: =(E78+E10-E69-E77)/E62 -> 40.010877 | F40: =(F78+F10-F69-F77)/F62 -> 7.9980535 | G40: =(G78+G10-G69-G77)/G62 -> 9.7935196 | H40: =IFERROR(AVERAGE(C40:G40),"") -> 14.212654 | I40: =SQRT((C40-H40)^2) -> 4.4305076
B41: Stock Info | H41: =IFERROR(AVERAGE(C41:F41),"")
B42: Float | C42: =OP!M19 -> 0.9814 | D42: =1.73/2.03 -> 0.85221675 | E42: =2.77/3.18 -> 0.87106918 | F42: =864.32/1070 -> 0.8077757 | G42: =187.53/295.72 -> 0.63414717 | H42: =IFERROR(AVERAGE(C42:G42),"") -> 0.82932176 | I42: =SQRT((C42-H42)^2) -> 0.15207824
B43: b (Yahoo) | C43: =OP!M21 -> 0.9418 | D43: {=_FV(D8,"Beta")} -> 1.24 | E43: {=_FV(E8,"Beta")} -> 2.3988 | F43: 1.17 | G43: {=_FV(G8,"Beta")} -> 1.9101 | H43: =IFERROR(AVERAGE(C43:G43),"") -> 1.53214 | I43: =SQRT((C43-H43)^2) -> 0.59034
B44: Dividend Yield (yahoo finance) | C44: =OP!M31 -> 0.027360578 | D44: 0 | E44: 0 | F44: 0.0408 | G44: 0.0399 | H44: =IFERROR(AVERAGE(C44:G44),"") -> 0.021612116 | I44: =SQRT((C44-H44)^2) -> 0.0057484624
B45: Stock Performance
B46: 1y | C46: 0.6368 | D46: 0.3462 | E46: -0.0526 | F46: 0.5116 | G46: 0.3548 | H46: =IFERROR(AVERAGE(C46:G46),"") -> 0.35936 | I46: =SQRT((C46-H46)^2) -> 0.27744
B47: 3y | C47: 0.8995 | D47: 0.3407 | E47: -0.242 | F47: 0.484 | G47: 0.3866 | H47: =IFERROR(AVERAGE(C47:G47),"") -> 0.37376 | I47: =SQRT((C47-H47)^2) -> 0.52574
B48: Current Price | C48: =OP!C19 -> 105.92 | D48: 26.89 | E48: {=_FV(E8,"Price")} -> 172.63 | F48: {=_FV(F8,"Price")*1.103594} -> 51.449552 | G48: {=_FV(G8,"Price")*1.103594} -> 50.31285 | H48: -- | I48: --
B49: Average Target Price | C49: 116.5 | D49: 27.51 | E49: 196.72 | F49: 54.22 | G49: 47.92 | H49: -- | I49: --
B50: Upside/Downside | C50: =C49/C48-1 -> 0.099886707 | D50: =D49/D48-1 -> 0.023056898 | E50: =E49/E48-1 -> 0.13954701 | F50: =F49/F48-1 -> 0.053847849 | G50: =G49/G48-1 -> -0.047559429 | H50: =IFERROR(AVERAGE(C50:G50),"") -> 0.053755807 | I50: =SQRT((C50-H50)^2) -> 0.0461309
B51: Extra | H51: =IFERROR(AVERAGE(C51:F51),"")
B52: 3y Operating Cash Flow | C52: =(Inputs!B59/Inputs!E59)-1 -> 0.40265131 | D52: =26.6/30.61-1 -> -0.13100294 | E52: =(13256/2405)-1 -> 4.5118503 | F52: =(386/1270)-1 -> -0.69606299 | G52: =4.46/5.75-1 -> -0.22434783 | H52: =IFERROR(AVERAGE(C52:G52),"") -> 0.77261757 | I52: =SQRT((C52-H52)^2) -> 0.36996626
B53: R&D/Net Sales | C53: =C67/C60 -> 0.011700401 | D53: =D67/D60 -> 0.031444459 | E53: =E67/E60 -> 0.041013506 | F53: =F67/F60 -> 0.031444459 | G53: =G67/G60 -> 0.0241766 | H53: =IFERROR(AVERAGE(C53:G53),"") -> 0.027955885 | I53: =SQRT((C53-H53)^2) -> 0.016255484
B56: Financial Data | C56: =OP!E2 -> #VALUE! | D56: =D8 -> #VALUE! | E56: =E8 -> #VALUE! | F56: =F8 -> #VALUE! | G56: =G8 -> #VALUE!
B57: IS
B58: ="Net Sales ("&OP!J19-3&")" -> Net Sales (2020) | C58: ='Fin. Data'!E5 -> 18729 | D58: 41046 | E58: 31536 | F58: 41046 | G58: 49549
B59: ="Net Sales ("&OP!J19-1&")" -> Net Sales (2022) | C59: ='Fin. Data'!C5 -> 28820 | D59: 53550 | E59: 53823 | F59: 53550 | G59: 48764
B60: ="Net Sales ("&OP!J19&")" -> Net Sales (2023) | C60: ='Fin. Data'!B5 -> 35127 | D60: 60424 | E60: 96773 | F60: 60424 | G60: 56625
B61: COGS | C61: ='Fin. Data'!B5-'Fin. Data'!B7 -> 26894 | D61: 47535 | E61: 79113 | F61: 47535 | G61: 44774
B62: EBITDA | C62: ='Fin. Data'!B19 -> 6770.9 | D62: 4243 | E62: 13558 | F62: 7644 | G62: 7894
B63: Operating Income | C63: ='Fin. Data'!B11 -> 5847 | D63: 5865 | E63: 8891 | F63: 5865 | G63: 2178
B64: Net Financial Cost | C64: ='Fin. Data'!B14 -> -129 | D64: =263-86 -> 177 | E64: =1066-156 -> 910 | F64: =415-201 -> 214 | G64: =448-352 -> 96
B65: Taxes | C65: ='Fin. Data'!B21 -> -1117 | D65: 641 | E65: -5001 | F65: 1465 | G65: 565
B66: Net Income | C66: ='Fin. Data'!B23 -> 4601 | D66: 4082 | E66: 14999 | F66: 4082 | G66: 2376
B67: R&D | C67: 411 | D67: 1900 | E67: 3969 | F67: 1900 | G67: 1369
B68: BS
B69: Cash & Eq. | C69: ='Fin. Data'!B39 -> 7182 | D69: 662 | E69: 12553 | F69: 7799 | G69: 10048
B70: Acc. Receivables | C70: ='Fin. Data'!B40 -> 2198 | D70: 1916 | E70: 3508 | F70: 5788 | G70: 55665
B71: Inventory | C71: ='Fin. Data'!B41 -> 2577 | D71: 5668 | E71: 13626 | F71: 10103 | G71: 5434
B72: Current Assets | C72: =Inputs!C27 -> 8810 | D72: 15591 | E72: 49616 | F72: 41444 | G72: 95277
B73: Fixed Assets | C73: ='Fin. Data'!B42 -> 3853.6 | D73: 8355 | E73: 45123 | F73: 13805 | G73: 13520
B74: Total Assets | C74: ='Fin. Data'!B44 -> 40823 | D74: 35399 | E74: 106618 | F74: 78589 | G74: 134542
B75: Acc. Payable | C75: =Inputs!C43 -> 1665 | D75: 6189 | E75: 14431 | F75: 5583 | G75: 8790
B76: Current Liabilities | C76: =Inputs!C42 -> 9705 | D76: 15992 | E76: 28748 | F76: 25181 | G76: 86006
B77: Leasing Debt | C77: ='Fin. Data'!B50+'Fin. Data'!B54 -> 182
B78: Total Debt | C78: ='Fin. Data'!B58 -> 14238 | D78: 3604 | E78: 5230 | F78: 26196 | G78: 72530
B79: Total Equity | C79: ='Fin. Data'!B64 -> 15878 | D79: 12553 | E79: 62634 | F79: 23842 | G79: 32834

Sheet SARD
C1: in AUD | F1: Variables | K1: Rankings | P1: Difference | U1: Results | Y1: Additional Information | AD1: =#REF! -> #REF! | AE1: Selected Peers | AJ1: Price Multiples (TTM) | AM1: Enterprise Value Multiples (TTM)
B2: Ticker | C2: Company Name | D2: TRBC Industry | E2: Country | F2: ROE | G2: DEBT/EBIT | H2: Market Cap | I2: EPS Growth (2022-2023) (Refinitiv Smart Estimate) | J2: EBIT Margin | K2: ROE | L2: DEBT/EBIT | M2: Market Cap | N2: EPS Growth | O2: EBIT Margin | P2: ROE | Q2: DEBT/EBIT | R2: Market Cap | S2: EPS Growth | T2: EBIT Margin | U2: SARD Result | V2: SARD Peers | W2: SARD Peers adjusted Rank | Y2: Suitability | Z2: Relevant Information Missing | AA2: Author's Override | AB2: Observations | AE2: SARD Peers adjusted Rank | AF2: SARD Result | AG2: Ticker | AH2: Company Name | AI2: Country | AJ2: P / E | AK2: P / B | AL2: Price / Sales | AM2: EV / Sales | AN2: EV / EBITDA | AS2: Net Income After Taxes | AT2: Total Equity | AU2: Total Debt | AV2: Operating Income | AW2: Revenue | AX2: Company Market Cap | AY2: Earnings per Share (FY1) | AZ2: Earnings per Share (FY0)
A3: Benchmark | B3: PCAR.OQ | C3: Paccar Inc | E3: United States of America | F3: =AS3/AT3 -> 0.28974482 | G3: =AU3/AV3 -> 2.4349068 | H3: =AX3 -> 6.4458564e+10 | I3: =(AY3/AZ3)-1 -> -0.097023153 | J3: =AV3/AX3 -> 0.090709437 | K3: =IFERROR(_xlfn.RANK.EQ(F3,F$3:F$62),"N/A") -> 8 | L3: =IFERROR(_xlfn.RANK.EQ(G3,G$3:G$62),"N/A") -> 33 | M3: =IFERROR(_xlfn.RANK.EQ(H3,H$3:H$62),"N/A") -> 3 | N3: =IFERROR(_xlfn.RANK.EQ(I3,I$3:I$326),"N/A") -> 76 | O3: =IFERROR(_xlfn.RANK.EQ(J3,J$3:J$62),"N/A") -> 35 | P3: - | Q3: - | R3: - | S3: - | T3: - | U3: - | V3: - | W3: - | Y3: =IF(OR(Z3="Y",AA3="Y"),"Not suitable","") | AE3: 1 | AF3: =_xlfn.XLOOKUP(AE3,$W$4:$W$102,$U$4:$U$102,"N/A",0,1) -> 16 | AG3: =_xlfn.XLOOKUP(AE3,$W$4:$W$102,$B$4:$B$102,"N/A",0,1) -> DE.N | AH3: =_xlfn.XLOOKUP(AE3,$W$4:$W$102,$C$4:$C$102,"N/A",0,1) -> Deere & Co | AI3: =_xlfn.XLOOKUP(AE3,$W$4:$W$102,$E$4:$E$102,"N/A",0,1) -> United States of America | AJ3: 12.978082 | AK3: 3.6370669 | AL3: 1.1698261 | AM3: 1.4478308 | AN3: 7.9540112 | AS3: 4600800000 | AT3: 15878800000 | AU3: 14236900000 | AV3: 5847000000 | AW3: 35127400000 | AX3: 6.4458564e+10 | AY3: 8.19 | AZ3: 9.07
A4: Comparison | B4: BAWJ.J | C4: Barloworld Ltd | E4: South Africa | F4: =AS4/AT4 -> 0.12272755 | G4: =AU4/AV4 -> 2.6998633 | H4: =AX4 -> 6.0342132e+08 | I4: =IFERROR((AY4/AZ4)-1,"-") -> -0.16285865 | J4: =AV4/AX4 -> 0.38444572 | K4: =IFERROR(_xlfn.RANK.EQ(F4,F$3:F$102),"N/A") -> 58 | L4: =IFERROR(_xlfn.RANK.EQ(G4,G$3:G$102),"N/A") -> 49 | M4: =IFERROR(_xlfn.RANK.EQ(H4,H$3:H$102),"N/A") -> 78 | N4: =IFERROR(_xlfn.RANK.EQ(I4,I$3:I$102),"N/A") -> 80 | O4: =IFERROR(_xlfn.RANK.EQ(J4,J$3:J$102),"N/A") -> 2 | P4: =IFERROR(ABS(K$3-K4),"N/A") -> 50 | Q4: =IFERROR(ABS(L$3-L4),"N/A") -> 16 | R4: =IFERROR(ABS(M$3-M4),"N/A") -> 75 | S4: =IFERROR(ABS(N$3-N4),"N/A") -> 4 | T4: =IFERROR(ABS(O$3-O4),"N/A") -> 33 | U4: =SUM(P4:T4) -> 178 | V4: =_xlfn.RANK.EQ(U4,$U$4:$U$102,1) -> 54 | W4: =IF(Y4="Not suitable","-",V4) -> 54 | Y4: =IF(OR(Z4="Y",AA4="Y"),"Not suitable","") | Z4: =IF(OR(N4="N/A",O4="N/A"),"Y","") | AE4: 2 | AF4: =_xlfn.XLOOKUP(AE4,$W$4:$W$102,$U$4:$U$102,"N/A",0,1) -> 34 | AG4: =_xlfn.XLOOKUP(AE4,$W$4:$W$102,$B$4:$B$102,"N/A",0,1) -> VOLVb.ST | AH4: =_xlfn.XLOOKUP(AE4,$W$4:$W$102,$C$4:$C$102,"N/A",0,1) -> Volvo AB | AI4: =_xlfn.XLOOKUP(AE4,$W$4:$W$102,$E$4:$E$102,"N/A",0,1) -> Sweden | AJ4: 17.695393 | AK4: 9.129633 | AL4: 2.6539377 | AM4: 3.1148533 | AN4: 12.345276 | AS4: 1.0742683e+08 | AT4: 8.7532778e+08 | AU4: 6.2632169e+08 | AV4: 2.3198274e+08 | AW4: 2.3805194e+09 | AX4: 6.0342132e+08 | AY4: 0.4985384 | AZ4: 0.59552476
B5: FSS.N | C5: Federal Signal Corp | E5: United States of America | F5: =AS5/AT5 -> 0.15710151 | G5: =AU5/AV5 -> 1.3318486 | H5: =AX5 -> 5.0276069e+09 | I5: =IFERROR((AY5/AZ5)-1,"-") -> 0.20904073 | J5: =AV5/AX5 -> 0.044653452 | K5: =IFERROR(_xlfn.RANK.EQ(F5,F$3:F$102),"N/A") -> 45 | L5: =IFERROR(_xlfn.RANK.EQ(G5,G$3:G$102),"N/A") -> 70 | M5: =IFERROR(_xlfn.RANK.EQ(H5,H$3:H$102),"N/A") -> 30 | N5: =IFERROR(_xlfn.RANK.EQ(I5,I$3:I$102),"N/A") -> 36 | O5: =IFERROR(_xlfn.RANK.EQ(J5,J$3:J$102),"N/A") -> 82 | P5: =IFERROR(ABS(K$3-K5),"N/A") -> 37 | Q5: =IFERROR(ABS(L$3-L5),"N/A") -> 37 | R5: =IFERROR(ABS(M$3-M5),"N/A") -> 27 | S5: =IFERROR(ABS(N$3-N5),"N/A") -> 40 | T5: =IFERROR(ABS(O$3-O5),"N/A") -> 47 | U5: =SUM(P5:T5) -> 188 | V5: =_xlfn.RANK.EQ(U5,$U$4:$U$102,1) -> 63 | W5: =IF(Y5="Not suitable","-",V5) -> 63 | Y5: =IF(OR(Z5="Y",AA5="Y"),"Not suitable","") | Z5: =IF(OR(N5="N/A",O5="N/A"),"Y","") | AE5: 3 | AF5: =_xlfn.XLOOKUP(AE5,$W$4:$W$102,$U$4:$U$102,"N/A",0,1) -> 53 | AG5: =_xlfn.XLOOKUP(AE5,$W$4:$W$102,$B$4:$B$102,"N/A",0,1) -> DTGGe.DE | AH5: =_xlfn.XLOOKUP(AE5,$W$4:$W$102,$C$4:$C$102,"N/A",0,1) -> Daimler Truck Holding AG | AI5: =_xlfn.XLOOKUP(AE5,$W$4:$W$102,$E$4:$E$102,"N/A",0,1) -> Germany | AJ5: 11.607458 | AK5: 5.0834413 | AL5: 1.8249784 | AM5: 2.7813492 | AN5: 9.6343922 | AS5: 157400000 | AT5: 1001900000 | AU5: 299000000 | AV5: 224500000 | AW5: 1722700000 | AX5: 5.0276069e+09 | AY5: 3.01166 | AZ5: 2.49095
B6: VOLVb.ST | C6: Volvo AB | E6: Sweden | F6: =AS6/AT6 -> 0.28084661 | G6: =AU6/AV6 -> 3.496571 | H6: =AX6 -> 6.1121149e+10 | I6: =IFERROR((AY6/AZ6)-1,"-") -> -0.19102138 | J6: =AV6/AX6 -> 0.10853776 | K6: =IFERROR(_xlfn.RANK.EQ(F6,F$3:F$102),"N/A") -> 13 | L6: =IFERROR(_xlfn.RANK.EQ(G6,G$3:G$102),"N/A") -> 42 | M6: =IFERROR(_xlfn.RANK.EQ(H6,H$3:H$102),"N/A") -> 4 | N6: =IFERROR(_xlfn.RANK.EQ(I6,I$3:I$102),"N/A") -> 84 | O6: =IFERROR(_xlfn.RANK.EQ(J6,J$3:J$102),"N/A") -> 46 | P6: =IFERROR(ABS(K$3-K6),"N/A") -> 5 | Q6: =IFERROR(ABS(L$3-L6),"N/A") -> 9 | R6: =IFERROR(ABS(M$3-M6),"N/A") -> 1 | S6: =IFERROR(ABS(N$3-N6),"N/A") -> 8 | T6: =IFERROR(ABS(O$3-O6),"N/A") -> 11 | U6: =SUM(P6:T6) -> 34 | V6: =_xlfn.RANK.EQ(U6,$U$4:$U$102,1) -> 2 | W6: =IF(Y6="Not suitable","-",V6) -> 2 | Y6: =IF(OR(Z6="Y",AA6="Y"),"Not suitable","") | Z6: =IF(OR(N6="N/A",O6="N/A"),"Y","") | AE6: 4 | AF6: =_xlfn.XLOOKUP(AE6,$W$4:$W$102,$U$4:$U$102,"N/A",0,1) -> 61 | AG6: =_xlfn.XLOOKUP(AE6,$W$4:$W$102,$B$4:$B$102,"N/A",0,1) -> CNHI.N | AH6: =_xlfn.XLOOKUP(AE6,$W$4:$W$102,$C$4:$C$102,"N/A",0,1) -> CNH Industrial NV | AI6: =_xlfn.XLOOKUP(AE6,$W$4:$W$102,$E$4:$E$102,"N/A",0,1) -> United Kingdom | AJ6: 32.628737 | AK6: 5.9932603 | AL6: 2.1133665 | AM6: 2.3376157 | AN6: 15.586887 | AS6: 4.9599682e+09 | AT6: 1.7660773e+10 | AU6: 2.3196086e+10 | AV6: 6.6339525e+09 | AW6: 5.4908513e+10 | AX6: 6.1121149e+10 | AY6: 2.223804 | AZ6: 2.7489033
B7: FTT.TO | C7: Finning International Inc | E7: Canada | F7: =AS7/AT7 -> 0.20723946 | G7: =AU7/AV7 -> 2.9626374 | H7: =AX7 -> 4.0309796e+09 | I7: =IFERROR((AY7/AZ7)-1,"-") -> 0.0079973492 | J7: =AV7/AX7 -> 0.17044287 | K7: =IFERROR(_xlfn.RANK.EQ(F7,F$3:F$102),"N/A") -> 22 | L7: =IFERROR(_xlfn.RANK.EQ(G7,G$3:G$102),"N/A") -> 45 | M7: =IFERROR(_xlfn.RANK.EQ(H7,H$3:H$102),"N/A") -> 35 | N7: =IFERROR(_xlfn.RANK.EQ(I7,I$3:I$102),"N/A") -> 64 | O7: =IFERROR(_xlfn.RANK.EQ(J7,J$3:J$102),"N/A") -> 25 | P7: =IFERROR(ABS(K$3-K7),"N/A") -> 14 | Q7: =IFERROR(ABS(L$3-L7),"N/A") -> 12 | R7: =IFERROR(ABS(M$3-M7),"N/A") -> 32 | S7: =IFERROR(ABS(N$3-N7),"N/A") -> 12 | T7: =IFERROR(ABS(O$3-O7),"N/A") -> 10 | U7: =SUM(P7:T7) -> 80 | V7: =_xlfn.RANK.EQ(U7,$U$4:$U$102,1) -> 7 | W7: =IF(Y7="Not suitable","-",V7) -> 7 | Y7: =IF(OR(Z7="Y",AA7="Y"),"Not suitable","") | Z7: =IF(OR(N7="N/A",O7="N/A"),"Y","") | AE7: 5 | AF7: =_xlfn.XLOOKUP(AE7,$W$4:$W$102,$U$4:$U$102,"N/A",0,1) -> 68 | AG7: =_xlfn.XLOOKUP(AE7,$W$4:$W$102,$B$4:$B$102,"N/A",0,1) -> CAT.N | AH7: =_xlfn.XLOOKUP(AE7,$W$4:$W$102,$C$4:$C$102,"N/A",0,1) -> Caterpillar Inc | AI7: =_xlfn.XLOOKUP(AE7,$W$4:$W$102,$E$4:$E$102,"N/A",0,1) -> United States of America | AJ7: 10.182114 | AK7: 1.754149 | AL7: 0.69293461 | AM7: 0.95883191 | AN7: 7.5926772 | AS7: 3.9335598e+08 | AT7: 1.8980747e+09 | AU7: 2.0354851e+09 | AV7: 6.8705172e+08 | AW7: 7.9479049e+09 | AX7: 4.0309796e+09 | AY7: 2.9298186 | AZ7: 2.9065737
B8: DEZG.DE | C8: DEUTZ AG | E8: Germany | F8: =AS8/AT8 -> 0.14383746 | G8: =AU8/AV8 -> 2.0526316 | H8: =AX8 -> 8.0990641e+08 | I8: =IFERROR((AY8/AZ8)-1,"-") -> 0.12527417 | J8: =AV8/AX8 -> 0.16828353 | K8: =IFERROR(_xlfn.RANK.EQ(F8,F$3:F$102),"N/A") -> 50 | L8: =IFERROR(_xlfn.RANK.EQ(G8,G$3:G$102),"N/A") -> 60 | M8: =IFERROR(_xlfn.RANK.EQ(H8,H$3:H$102),"N/A") -> 72 | N8: =IFERROR(_xlfn.RANK.EQ(I8,I$3:I$102),"N/A") -> 46 | O8: =IFERROR(_xlfn.RANK.EQ(J8,J$3:J$102),"N/A") -> 26 | P8: =IFERROR(ABS(K$3-K8),"N/A") -> 42 | Q8: =IFERROR(ABS(L$3-L8),"N/A") -> 27 | R8: =IFERROR(ABS(M$3-M8),"N/A") -> 69 | S8: =IFERROR(ABS(N$3-N8),"N/A") -> 30 | T8: =IFERROR(ABS(O$3-O8),"N/A") -> 9 | U8: =SUM(P8:T8) -> 177 | V8: =_xlfn.RANK.EQ(U8,$U$4:$U$102,1) -> 52 | W8: =IF(Y8="Not suitable","-",V8) -> 52 | Y8: =IF(OR(Z8="Y",AA8="Y"),"Not suitable","") | Z8: =IF(OR(N8="N/A",O8="N/A"),"Y","") | AE8: 6 | AF8: =_xlfn.XLOOKUP(AE8,$W$4:$W$102,$U$4:$U$102,"N/A",0,1) -> 71 | AG8: =_xlfn.XLOOKUP(AE8,$W$4:$W$102,$B$4:$B$102,"N/A",0,1) -> ALSN.N | AH8: =_xlfn.XLOOKUP(AE8,$W$4:$W$102,$C$4:$C$102,"N/A",0,1) -> Allison Transmission Holdings Inc | AI8: =_xlfn.XLOOKUP(AE8,$W$4:$W$102,$E$4:$E$102,"N/A",0,1) -> United States of America | AJ8: 14.439075 | AK8: 2.4781742 | AL8: 0.99669039 | AM8: 1.0836228 | AN8: 8.0335946 | AS8: 1.1797424e+08 | AT8: 8.2019136e+08 | AU8: 2.7976118e+08 | AV8: 1.3629391e+08 | AW8: 2.276936e+09 | AX8: 8.0990641e+08 | AY8: 0.85331832 | AZ8: 0.75832036
B9: FSTR.OQ | C9: L B Foster Co | E9: United States of America | F9: =AS9/AT9 -> 0.0091407421 | G9: =AU9/AV9 -> 58.551907 | H9: =AX9 -> 2.971543e+08 | I9: =IFERROR((AY9/AZ9)-1,"-") -> 5.2665065 | J9: =AV9/AX9 -> 0.0031768008 | K9: =IFERROR(_xlfn.RANK.EQ(F9,F$3:F$102),"N/A") -> 92 | L9: =IFERROR(_xlfn.RANK.EQ(G9,G$3:G$102),"N/A") -> 1 | M9: =IFERROR(_xlfn.RANK.EQ(H9,H$3:H$102),"N/A") -> 89 | N9: =IFERROR(_xlfn.RANK.EQ(I9,I$3:I$102),"N/A") -> 1 | O9: =IFERROR(_xlfn.RANK.EQ(J9,J$3:J$102),"N/A") -> 93 | P9: =IFERROR(ABS(K$3-K9),"N/A") -> 84 | Q9: =IFERROR(ABS(L$3-L9),"N/A") -> 32 | R9: =IFERROR(ABS(M$3-M9),"N/A") -> 86 | S9: =IFERROR(ABS(N$3-N9),"N/A") -> 75 | T9: =IFERROR(ABS(O$3-O9),"N/A") -> 58 | U9: =SUM(P9:T9) -> 335 | V9: =_xlfn.RANK.EQ(U9,$U$4:$U$102,1) -> 97 | W9: =IF(Y9="Not suitable","-",V9) -> 97 | Y9: =IF(OR(Z9="Y",AA9="Y"),"Not suitable","") | Z9: =IF(OR(N9="N/A",O9="N/A"),"Y","") | AE9: Median | AJ9: =MEDIAN(AJ3:AJ8) -> 13.708579 | AK9: =MEDIAN(AK3:AK8) -> 4.3602541 | AL9: =MEDIAN(AL3:AL8) -> 1.4974023 | AM9: =MEDIAN(AM3:AM8) -> 1.8927232 | AN9: =MEDIAN(AN3:AN8) -> 8.8339934 | AS9: 1299000 | AT9: 142111000 | AU9: 55273000 | AV9: 944000 | AW9: 543744000 | AX9: 2.971543e+08 | AY9: 1.09526 | AZ9: 0.17478
B10: MANP.PA | C10: Manitou BF SA | E10: France | F10: =AS10/AT10 -> 0.16038357 | G10: =AU10/AV10 -> 2.287254 | H10: =AX10 -> 1.0853628e+09 | I10: =IFERROR((AY10/AZ10)-1,"-") -> 0.22217785 | J10: =AV10/AX10 -> 0.21113702 | K10: =IFERROR(_xlfn.RANK.EQ(F10,F$3:F$102),"N/A") -> 42 | L10: =IFERROR(_xlfn.RANK.EQ(G10,G$3:G$102),"N/A") -> 57 | M10: =IFERROR(_xlfn.RANK.EQ(H10,H$3:H$102),"N/A") -> 66 | N10: =IFERROR(_xlfn.RANK.EQ(I10,I$3:I$102),"N/A") -> 33 | O10: =IFERROR(_xlfn.RANK.EQ(J10,J$3:J$102),"N/A") -> 15 | P10: =IFERROR(ABS(K$3-K10),"N/A") -> 34 | Q10: =IFERROR(ABS(L$3-L10),"N/A") -> 24 | R10: =IFERROR(ABS(M$3-M10),"N/A") -> 63 | S10: =IFERROR(ABS(N$3-N10),"N/A") -> 43 | T10: =IFERROR(ABS(O$3-O10),"N/A") -> 20 | U10: =SUM(P10:T10) -> 184 | V10: =_xlfn.RANK.EQ(U10,$U$4:$U$102,1) -> 59 | W10: =IF(Y10="Not suitable","-",V10) -> 59 | Y10: =IF(OR(Z10="Y",AA10="Y"),"Not suitable","") | Z10: =IF(OR(N10="N/A",O10="N/A"),"Y","") | AE10: Benchmark Data | AJ10: Price / Share | AS10: 1.5837021e+08 | AT10: 9.8744661e+08 | AU10: 5.2414775e+08 | AV10: 2.2916028e+08 | AW10: 3.1687639e+09 | AX10: 1.0853628e+09 | AY10: 3.8197986 | AZ10: 3.1254032
B11: ASTE.OQ | C11: Astec Industries Inc | E11: United States of America | F11: =AS11/AT11 -> 0.05157637 | G11: =AU11/AV11 -> 1.7098765 | H11: =AX11 -> 9.6136263e+08 | I11: =IFERROR((AY11/AZ11)-1,"-") -> 0.14694792 | J11: =AV11/AX11 -> 0.050553244 | K11: =IFERROR(_xlfn.RANK.EQ(F11,F$3:F$102),"N/A") -> 85 | L11: =IFERROR(_xlfn.RANK.EQ(G11,G$3:G$102),"N/A") -> 68 | M11: =IFERROR(_xlfn.RANK.EQ(H11,H$3:H$102),"N/A") -> 69 | N11: =IFERROR(_xlfn.RANK.EQ(I11,I$3:I$102),"N/A") -> 42 | O11: =IFERROR(_xlfn.RANK.EQ(J11,J$3:J$102),"N/A") -> 76 | P11: =IFERROR(ABS(K$3-K11),"N/A") -> 77 | Q11: =IFERROR(ABS(L$3-L11),"N/A") -> 35 | R11: =IFERROR(ABS(M$3-M11),"N/A") -> 66 | S11: =IFERROR(ABS(N$3-N11),"N/A") -> 34 | T11: =IFERROR(ABS(O$3-O11),"N/A") -> 41 | U11: =SUM(P11:T11) -> 253 | V11: =_xlfn.RANK.EQ(U11,$U$4:$U$102,1) -> 84 | W11: =IF(Y11="Not suitable","-",V11) -> 84 | Y11: =IF(OR(Z11="Y",AA11="Y"),"Not suitable","") | Z11: =IF(OR(N11="N/A",O11="N/A"),"Y","") | AE11: Benchmark | AF11: Multiplier | AG11: # Shares | AH11: -Debt + Cash | AJ11: P / E | AK11: P / B | AL11: Price / Sales | AM11: EV / Sales | AN11: EV / EBITDA | AS11: 33700000 | AT11: 653400000 | AU11: 83100000 | AV11: 48600000 | AW11: 1338200000 | AX11: 9.6136263e+08 | AY11: 2.73445 | AZ11: 2.38411
B12: LNN.N | C12: Lindsay Corp | E12: United States of America | F12: =AS12/AT12 -> 0.1586214 | G12: =AU12/AV12 -> 1.1292375 | H12: =AX12 -> 1.2945906e+09 | I12: =IFERROR((AY12/AZ12)-1,"-") -> 0.0018217496 | J12: =AV12/AX12 -> 0.078931514 | K12: =IFERROR(_xlfn.RANK.EQ(F12,F$3:F$102),"N/A") -> 44 | L12: =IFERROR(_xlfn.RANK.EQ(G12,G$3:G$102),"N/A") -> 73 | M12: =IFERROR(_xlfn.RANK.EQ(H12,H$3:H$102),"N/A") -> 58 | N12: =IFERROR(_xlfn.RANK.EQ(I12,I$3:I$102),"N/A") -> 66 | O12: =IFERROR(_xlfn.RANK.EQ(J12,J$3:J$102),"N/A") -> 60 | P12: =IFERROR(ABS(K$3-K12),"N/A") -> 36 | Q12: =IFERROR(ABS(L$3-L12),"N/A") -> 40 | R12: =IFERROR(ABS(M$3-M12),"N/A") -> 55 | S12: =IFERROR(ABS(N$3-N12),"N/A") -> 10 | T12: =IFERROR(ABS(O$3-O12),"N/A") -> 25 | U12: =SUM(P12:T12) -> 166 | V12: =_xlfn.RANK.EQ(U12,$U$4:$U$102,1) -> 44 | W12: =IF(Y12="Not suitable","-",V12) -> 44 | Y12: =IF(OR(Z12="Y",AA12="Y"),"Not suitable","") | Z12: =IF(OR(N12="N/A",O12="N/A"),"Y","") | AE12: =C3 -> Paccar Inc | AF12: 1000000 | AG12: =OP!C20 -> 524010700 | AH12: =-'Fin. Data'!B58*SARD!AF12+'Fin. Data'!B39*SARD!AF12 -> -7056000000 | AJ12: =AJ9*'Fin. Data'!B23*AF$12/AG$12 -> 120.36619 | AK12: =AK9*'Fin. Data'!B64*AF$12/AG$12 -> 132.11966 | AL12: =AL9*'Fin. Data'!B5*AF$12/AG$12 -> 100.3782 | AM12: =(AM9*'Fin. Data'!B5*$AF12+$AH12)/$AG12 -> 113.41312 | AN12: =(AN9*'Fin. Data'!B19*$AF12+$AH12)/$AG12 -> 100.68131 | AS12: 72276000 | AT12: 455651000 | AU12: 115390000 | AV12: 102184000 | AW12: 674084000 | AX12: 1.2945906e+09 | AY12: 5.91717 | AZ12: 5.90641
B13: KEPL3.SA | C13: Kepler Weber SA | E13: Brazil | F13: =AS13/AT13 -> 0.33766591 | G13: =AU13/AV13 -> 0.65205102 | H13: =AX13 -> 3.7019596e+08 | I13: =IFERROR((AY13/AZ13)-1,"-") -> -0.25032692 | J13: =AV13/AX13 -> 0.16800597 | K13: =IFERROR(_xlfn.RANK.EQ(F13,F$3:F$102),"N/A") -> 7 | L13: =IFERROR(_xlfn.RANK.EQ(G13,G$3:G$102),"N/A") -> 82 | M13: =IFERROR(_xlfn.RANK.EQ(H13,H$3:H$102),"N/A") -> 87 | N13: =IFERROR(_xlfn.RANK.EQ(I13,I$3:I$102),"N/A") -> 89 | O13: =IFERROR(_xlfn.RANK.EQ(J13,J$3:J$102),"N/A") -> 27 | P13: =IFERROR(ABS(K$3-K13),"N/A") -> 1 | Q13: =IFERROR(ABS(L$3-L13),"N/A") -> 49 | R13: =IFERROR(ABS(M$3-M13),"N/A") -> 84 | S13: =IFERROR(ABS(N$3-N13),"N/A") -> 13 | T13: =IFERROR(ABS(O$3-O13),"N/A") -> 8 | U13: =SUM(P13:T13) -> 155 | V13: =_xlfn.RANK.EQ(U13,$U$4:$U$102,1) -> 41 | W13: =IF(Y13="Not suitable","-",V13) -> 41 | Y13: =IF(OR(Z13="Y",AA13="Y"),"Not suitable","") | Z13: =IF(OR(N13="N/A",O13="N/A"),"Y","") | AE13: By Consolidated Average | AJ13: =AVERAGE(AJ12:AL12) -> 117.62135 | AM13: =AVERAGE(AM12:AN12) -> 107.04722 | AS13: 50537705 | AT13: 1.4966777e+08 | AU13: 40554399 | AV13: 62195132 | AW13: 3.1164527e+08 | AX13: 3.7019596e+08 | AY13: 0.28088985 | AZ13: 0.37468313
B14: MTW.N | C14: Manitowoc Company Inc | E14: United States of America | F14: =AS14/AT14 -> 0.064975966 | G14: =AU14/AV14 -> 4.0270563 | H14: =AX14 -> 4.7973697e+08 | I14: =IFERROR((AY14/AZ14)-1,"-") -> -0.24282759 | J14: =AV14/AX14 -> 0.19260554 | K14: =IFERROR(_xlfn.RANK.EQ(F14,F$3:F$102),"N/A") -> 79 | L14: =IFERROR(_xlfn.RANK.EQ(G14,G$3:G$102),"N/A") -> 35 | M14: =IFERROR(_xlfn.RANK.EQ(H14,H$3:H$102),"N/A") -> 85 | N14: =IFERROR(_xlfn.RANK.EQ(I14,I$3:I$102),"N/A") -> 88 | O14: =IFERROR(_xlfn.RANK.EQ(J14,J$3:J$102),"N/A") -> 23 | P14: =IFERROR(ABS(K$3-K14),"N/A") -> 71 | Q14: =IFERROR(ABS(L$3-L14),"N/A") -> 2 | R14: =IFERROR(ABS(M$3-M14),"N/A") -> 82 | S14: =IFERROR(ABS(N$3-N14),"N/A") -> 12 | T14: =IFERROR(ABS(O$3-O14),"N/A") -> 12 | U14: =SUM(P14:T14) -> 179 | V14: =_xlfn.RANK.EQ(U14,$U$4:$U$102,1) -> 56 | W14: =IF(Y14="Not suitable","-",V14) -> 56 | Y14: =IF(OR(Z14="Y",AA14="Y"),"Not suitable","") | Z14: =IF(OR(N14="N/A",O14="N/A"),"Y","") | AE14: Upside | AJ14: =AJ13/OP!C19-1 -> 0.11047345 | AM14: =AM13/OP!C19-1 -> 0.010642162 | AS14: 39200000 | AT14: 603300000 | AU14: 372100000 | AV14: 92400000 | AW14: 2227800000 | AX14: 4.7973697e+08 | AY14: 1.26285 | AZ14: 1.66785
B15: CAT.N | C15: Caterpillar Inc | E15: United States of America | F15: =AS15/AT15 -> 0.52677747 | G15: =AU15/AV15 -> 2.9213327 | H15: =AX15 -> 1.7797306e+11 | I15: =IFERROR((AY15/AZ15)-1,"-") -> 0.026531404 | J15: =AV15/AX15 -> 0.072853721 | K15: =IFERROR(_xlfn.RANK.EQ(F15,F$3:F$102),"N/A") -> 3 | L15: =IFERROR(_xlfn.RANK.EQ(G15,G$3:G$102),"N/A") -> 46 | M15: =IFERROR(_xlfn.RANK.EQ(H15,H$3:H$102),"N/A") -> 1 | N15: =IFERROR(_xlfn.RANK.EQ(I15,I$3:I$102),"N/A") -> 59 | O15: =IFERROR(_xlfn.RANK.EQ(J15,J$3:J$102),"N/A") -> 66 | P15: =IFERROR(ABS(K$3-K15),"N/A") -> 5 | Q15: =IFERROR(ABS(L$3-L15),"N/A") -> 13 | R15: =IFERROR(ABS(M$3-M15),"N/A") -> 2 | S15: =IFERROR(ABS(N$3-N15),"N/A") -> 17 | T15: =IFERROR(ABS(O$3-O15),"N/A") -> 31 | U15: =SUM(P15:T15) -> 68 | V15: =_xlfn.RANK.EQ(U15,$U$4:$U$102,1) -> 5 | W15: =IF(Y15="Not suitable","-",V15) -> 5 | Y15: =IF(OR(Z15="Y",AA15="Y"),"Not suitable","") | Z15: =IF(OR(N15="N/A",O15="N/A"),"Y","") | AS15: 10269000000 | AT15: 19494000000 | AU15: 37878000000 | AV15: 12966000000 | AW15: 67060000000 | AX15: 1.7797306e+11 | AY15: 21.28402 | AZ15: 20.73392
B16: 6305.T | C16: Hitachi Construction Machinery Co Ltd | E16: Japan | F16: =AS16/AT16 -> 0.11473169 | G16: =AU16/AV16 -> 4.3452479 | H16: =AX16 -> 6.6159762e+09 | I16: =IFERROR((AY16/AZ16)-1,"-") -> 0.25087742 | J16: =AV16/AX16 -> 0.15174117 | K16: =IFERROR(_xlfn.RANK.EQ(F16,F$3:F$102),"N/A") -> 60 | L16: =IFERROR(_xlfn.RANK.EQ(G16,G$3:G$102),"N/A") -> 30 | M16: =IFERROR(_xlfn.RANK.EQ(H16,H$3:H$102),"N/A") -> 27 | N16: =IFERROR(_xlfn.RANK.EQ(I16,I$3:I$102),"N/A") -> 30 | O16: =IFERROR(_xlfn.RANK.EQ(J16,J$3:J$102),"N/A") -> 30 | P16: =IFERROR(ABS(K$3-K16),"N/A") -> 52 | Q16: =IFERROR(ABS(L$3-L16),"N/A") -> 3 | R16: =IFERROR(ABS(M$3-M16),"N/A") -> 24 | S16: =IFERROR(ABS(N$3-N16),"N/A") -> 46 | T16: =IFERROR(ABS(O$3-O16),"N/A") -> 5 | U16: =SUM(P16:T16) -> 130 | V16: =_xlfn.RANK.EQ(U16,$U$4:$U$102,1) -> 26 | W16: =IF(Y16="Not suitable","-",V16) -> 26 | Y16: =IF(OR(Z16="Y",AA16="Y"),"Not suitable","") | Z16: =IF(OR(N16="N/A",O16="N/A"),"Y","") | AS16: 5.7023872e+08 | AT16: 4.9701935e+09 | AU16: 4.3622637e+09 | AV16: 1.003916e+09 | AW16: 9.6352737e+09 | AX16: 6.6159762e+09 | AY16: 2.9053742 | AZ16: 2.322669
B17: 6301.T | C17: Komatsu Ltd | E17: Japan | F17: =AS17/AT17 -> 0.13422645 | G17: =AU17/AV17 -> 2.1466051 | H17: =AX17 -> 2.8954079e+10 | I17: =IFERROR((AY17/AZ17)-1,"-") -> 0.11032005 | J17: =AV17/AX17 -> 0.12767776 | K17: =IFERROR(_xlfn.RANK.EQ(F17,F$3:F$102),"N/A") -> 52 | L17: =IFERROR(_xlfn.RANK.EQ(G17,G$3:G$102),"N/A") -> 58 | M17: =IFERROR(_xlfn.RANK.EQ(H17,H$3:H$102),"N/A") -> 7 | N17: =IFERROR(_xlfn.RANK.EQ(I17,I$3:I$102),"N/A") -> 49 | O17: =IFERROR(_xlfn.RANK.EQ(J17,J$3:J$102),"N/A") -> 40 | P17: =IFERROR(ABS(K$3-K17),"N/A") -> 44 | Q17: =IFERROR(ABS(L$3-L17),"N/A") -> 25 | R17: =IFERROR(ABS(M$3-M17),"N/A") -> 4 | S17: =IFERROR(ABS(N$3-N17),"N/A") -> 27 | T17: =IFERROR(ABS(O$3-O17),"N/A") -> 5 | U17: =SUM(P17:T17) -> 105 | V17: =_xlfn.RANK.EQ(U17,$U$4:$U$102,1) -> 15 | W17: =IF(Y17="Not suitable","-",V17) -> 15 | Y17: =IF(OR(Z17="Y",AA17="Y"),"Not suitable","") | Z17: =IF(OR(N17="N/A",O17="N/A"),"Y","") | AS17: 2.5671135e+09 | AT17: 1.9125243e+10 | AU17: 7.9355524e+09 | AV17: 3.6967919e+09 | AW17: 2.6684803e+10 | AX17: 2.8954079e+10 | AY17: 2.735151 | AZ17: 2.4633897
B18: DE.N | C18: Deere & Co | E18: United States of America | F18: =AS18/AT18 -> 0.46582511 | G18: =AU18/AV18 -> 4.0749952 | H18: =AX18 -> 1.1093131e+11 | I18: =IFERROR((AY18/AZ18)-1,"-") -> -0.19491144 | J18: =AV18/AX18 -> 0.14027599 | K18: =IFERROR(_xlfn.RANK.EQ(F18,F$3:F$102),"N/A") -> 4 | L18: =IFERROR(_xlfn.RANK.EQ(G18,G$3:G$102),"N/A") -> 33 | M18: =IFERROR(_xlfn.RANK.EQ(H18,H$3:H$102),"N/A") -> 2 | N18: =IFERROR(_xlfn.RANK.EQ(I18,I$3:I$102),"N/A") -> 85 | O18: =IFERROR(_xlfn.RANK.EQ(J18,J$3:J$102),"N/A") -> 33 | P18: =IFERROR(ABS(K$3-K18),"N/A") -> 4 | Q18: =IFERROR(ABS(L$3-L18),"N/A") -> 0 | R18: =IFERROR(ABS(M$3-M18),"N/A") -> 1 | S18: =IFERROR(ABS(N$3-N18),"N/A") -> 9 | T18: =IFERROR(ABS(O$3-O18),"N/A") -> 2 | U18: =SUM(P18:T18) -> 16 | V18: =_xlfn.RANK.EQ(U18,$U$4:$U$102,1) -> 1 | W18: =IF(Y18="Not suitable","-",V18) -> 1 | Y18: =IF(OR(Z18="Y",AA18="Y"),"Not suitable","") | Z18: =IF(OR(N18="N/A",O18="N/A"),"Y","") | AS18: 10148000000 | AT18: 21785000000 | AU18: 63411000000 | AV18: 15561000000 | AW18: 61218000000 | AX18: 1.1093131e+11 | AY18: 27.34819 | AZ18: 33.96917
B19: OSK.N | C19: Oshkosh Corp | E19: United States of America | F19: =AS19/AT19 -> 0.16398132 | G19: =AU19/AV19 -> 0.99307545 | H19: =AX19 -> 7.8939627e+09 | I19: =IFERROR((AY19/AZ19)-1,"-") -> 0.083763981 | J19: =AV19/AX19 -> 0.1061064 | K19: =IFERROR(_xlfn.RANK.EQ(F19,F$3:F$102),"N/A") -> 40 | L19: =IFERROR(_xlfn.RANK.EQ(G19,G$3:G$102),"N/A") -> 76 | M19: =IFERROR(_xlfn.RANK.EQ(H19,H$3:H$102),"N/A") -> 22 | N19: =IFERROR(_xlfn.RANK.EQ(I19,I$3:I$102),"N/A") -> 53 | O19: =IFERROR(_xlfn.RANK.EQ(J19,J$3:J$102),"N/A") -> 47 | P19: =IFERROR(ABS(K$3-K19),"N/A") -> 32 | Q19: =IFERROR(ABS(L$3-L19),"N/A") -> 43 | R19: =IFERROR(ABS(M$3-M19),"N/A") -> 19 | S19: =IFERROR(ABS(N$3-N19),"N/A") -> 23 | T19: =IFERROR(ABS(O$3-O19),"N/A") -> 12 | U19: =SUM(P19:T19) -> 129 | V19: =_xlfn.RANK.EQ(U19,$U$4:$U$102,1) -> 24 | W19: =IF(Y19="Not suitable","-",V19) -> 24 | Y19: =IF(OR(Z19="Y",AA19="Y"),"Not suitable","") | Z19: =IF(OR(N19="N/A",O19="N/A"),"Y","") | AS19: 607600000 | AT19: 3705300000 | AU19: 831800000 | AV19: 837600000 | AW19: 9657900000 | AX19: 7.8939627e+09 | AY19: 10.39981 | AZ19: 9.59601
B20: 6294.T | C20: Okada Aiyon Corp | E20: Japan | F20: =AS20/AT20 -> 0.1013061 | G20: =AU20/AV20 -> 4.9067575 | H20: =AX20 -> 1.7498242e+08 | I20: =IFERROR((AY20/AZ20)-1,"-") -> 0.40887707 | J20: =AV20/AX20 -> 0.083981886 | K20: =IFERROR(_xlfn.RANK.EQ(F20,F$3:F$102),"N/A") -> 65 | L20: =IFERROR(_xlfn.RANK.EQ(G20,G$3:G$102),"N/A") -> 25 | M20: =IFERROR(_xlfn.RANK.EQ(H20,H$3:H$102),"N/A") -> 97 | N20: =IFERROR(_xlfn.RANK.EQ(I20,I$3:I$102),"N/A") -> 18 | O20: =IFERROR(_xlfn.RANK.EQ(J20,J$3:J$102),"N/A") -> 57 | P20: =IFERROR(ABS(K$3-K20),"N/A") -> 57 | Q20: =IFERROR(ABS(L$3-L20),"N/A") -> 8 | R20: =IFERROR(ABS(M$3-M20),"N/A") -> 94 | S20: =IFERROR(ABS(N$3-N20),"N/A") -> 58 | T20: =IFERROR(ABS(O$3-O20),"N/A") -> 22 | U20: =SUM(P20:T20) -> 239 | V20: =_xlfn.RANK.EQ(U20,$U$4:$U$102,1) -> 79 | W20: =IF(Y20="Not suitable","-",V20) -> 79 | Y20: =IF(OR(Z20="Y",AA20="Y"),"Not suitable","") | Z20: =IF(OR(N20="N/A",O20="N/A"),"Y","") | AS20: 10650990 | AT20: 1.0513671e+08 | AU20: 72106537 | AV20: 14695354 | AW20: 1.7754116e+08 | AX20: 1.7498242e+08 | AY20: 1.8202837 | AZ20: 1.2920103
B21: TEX.N | C21: Terex Corp | E21: United States of America | F21: =AS21/AT21 -> 0.30897566 | G21: =AU21/AV21 -> 0.97910448 | H21: =AX21 -> 3015000000 | I21: =IFERROR((AY21/AZ21)-1,"-") -> -0.01649684 | J21: =AV21/AX21 -> 0.21111111 | K21: =IFERROR(_xlfn.RANK.EQ(F21,F$3:F$102),"N/A") -> 10 | L21: =IFERROR(_xlfn.RANK.EQ(G21,G$3:G$102),"N/A") -> 77 | M21: =IFERROR(_xlfn.RANK.EQ(H21,H$3:H$102),"N/A") -> 41 | N21: =IFERROR(_xlfn.RANK.EQ(I21,I$3:I$102),"N/A") -> 69 | O21: =IFERROR(_xlfn.RANK.EQ(J21,J$3:J$102),"N/A") -> 16 | P21: =IFERROR(ABS(K$3-K21),"N/A") -> 2 | Q21: =IFERROR(ABS(L$3-L21),"N/A") -> 44 | R21: =IFERROR(ABS(M$3-M21),"N/A") -> 38 | S21: =IFERROR(ABS(N$3-N21),"N/A") -> 7 | T21: =IFERROR(ABS(O$3-O21),"N/A") -> 19 | U21: =SUM(P21:T21) -> 110 | V21: =_xlfn.RANK.EQ(U21,$U$4:$U$102,1) -> 18 | W21: =IF(Y21="Not suitable","-",V21) -> 18 | Y21: =IF(OR(Z21="Y",AA21="Y"),"Not suitable","") | Z21: =IF(OR(N21="N/A",O21="N/A"),"Y","") | AS21: 516700000 | AT21: 1672300000 | AU21: 623200000 | AV21: 636500000 | AW21: 5151500000 | AX21: 3015000000 | AY21: 6.96394 | AZ21: 7.08075
B22: TTC.N | C22: Toro Co | E22: United States of America | F22: =AS22/AT22 -> 0.21821431 | G22: =AU22/AV22 -> 2.3949385 | H22: =AX22 -> 9312042492 | I22: =IFERROR((AY22/AZ22)-1,"-") -> 0.05104826 | J22: =AV22/AX22 -> 0.046251937 | K22: =IFERROR(_xlfn.RANK.EQ(F22,F$3:F$102),"N/A") -> 21 | L22: =IFERROR(_xlfn.RANK.EQ(G22,G$3:G$102),"N/A") -> 54 | M22: =IFERROR(_xlfn.RANK.EQ(H22,H$3:H$102),"N/A") -> 19 | N22: =IFERROR(_xlfn.RANK.EQ(I22,I$3:I$102),"N/A") -> 56 | O22: =IFERROR(_xlfn.RANK.EQ(J22,J$3:J$102),"N/A") -> 80 | P22: =IFERROR(ABS(K$3-K22),"N/A") -> 13 | Q22: =IFERROR(ABS(L$3-L22),"N/A") -> 21 | R22: =IFERROR(ABS(M$3-M22),"N/A") -> 16 | S22: =IFERROR(ABS(N$3-N22),"N/A") -> 20 | T22: =IFERROR(ABS(O$3-O22),"N/A") -> 45 | U22: =SUM(P22:T22) -> 115 | V22: =_xlfn.RANK.EQ(U22,$U$4:$U$102,1) -> 21 | W22: =IF(Y22="Not suitable","-",V22) -> 21 | Y22: =IF(OR(Z22="Y",AA22="Y"),"Not suitable","") | Z22: =IF(OR(N22="N/A",O22="N/A"),"Y","") | AS22: 329700000 | AT22: 1510900000 | AU22: 1031500000 | AV22: 430700000 | AW22: 4553200000 | AX22: 9312042492 | AY22: 4.28587 | AZ22: 4.07771
B23: TIH.TO | C23: Toromont Industries Ltd | E23: Canada | F23: =AS23/AT23 -> 0.19714463 | G23: =AU23/AV23 -> 0.9685244 | H23: =AX23 -> 7.7876213e+09 | I23: =IFERROR((AY23/AZ23)-1,"-") -> 0.028357979 | J23: =AV23/AX23 -> 0.068274182 | K23: =IFERROR(_xlfn.RANK.EQ(F23,F$3:F$102),"N/A") -> 27 | L23: =IFERROR(_xlfn.RANK.EQ(G23,G$3:G$102),"N/A") -> 78 | M23: =IFERROR(_xlfn.RANK.EQ(H23,H$3:H$102),"N/A") -> 23 | N23: =IFERROR(_xlfn.RANK.EQ(I23,I$3:I$102),"N/A") -> 58 | O23: =IFERROR(_xlfn.RANK.EQ(J23,J$3:J$102),"N/A") -> 69 | P23: =IFERROR(ABS(K$3-K23),"N/A") -> 19 | Q23: =IFERROR(ABS(L$3-L23),"N/A") -> 45 | R23: =IFERROR(ABS(M$3-M23),"N/A") -> 20 | S23: =IFERROR(ABS(N$3-N23),"N/A") -> 18 | T23: =IFERROR(ABS(O$3-O23),"N/A") -> 34 | U23: =SUM(P23:T23) -> 136 | V23: =_xlfn.RANK.EQ(U23,$U$4:$U$102,1) -> 28 | W23: =IF(Y23="Not suitable","-",V23) -> 28 | Y23: =IF(OR(Z23="Y",AA23="Y"),"Not suitable","") | Z23: =IF(OR(N23="N/A",O23="N/A"),"Y","") | AS23: 3.9947678e+08 | AT23: 2.0263133e+09 | AU23: 5.149581e+08 | AV23: 5.3169347e+08 | AW23: 3.489846e+09 | AX23: 7.7876213e+09 | AY23: 4.7987224 | AZ23: 4.666393
B24: TRN.N | C24: Trinity Industries Inc | E24: United States of America | F24: =AS24/AT24 -> 0.1349918 | G24: =AU24/AV24 -> 13.799041 | H24: =AX24 -> 2.2462071e+09 | I24: =IFERROR((AY24/AZ24)-1,"-") -> 0.16952113 | J24: =AV24/AX24 -> 0.18564629 | K24: =IFERROR(_xlfn.RANK.EQ(F24,F$3:F$102),"N/A") -> 51 | L24: =IFERROR(_xlfn.RANK.EQ(G24,G$3:G$102),"N/A") -> 4 | M24: =IFERROR(_xlfn.RANK.EQ(H24,H$3:H$102),"N/A") -> 47 | N24: =IFERROR(_xlfn.RANK.EQ(I24,I$3:I$102),"N/A") -> 39 | O24: =IFERROR(_xlfn.RANK.EQ(J24,J$3:J$102),"N/A") -> 24 | P24: =IFERROR(ABS(K$3-K24),"N/A") -> 43 | Q24: =IFERROR(ABS(L$3-L24),"N/A") -> 29 | R24: =IFERROR(ABS(M$3-M24),"N/A") -> 44 | S24: =IFERROR(ABS(N$3-N24),"N/A") -> 37 | T24: =IFERROR(ABS(O$3-O24),"N/A") -> 11 | U24: =SUM(P24:T24) -> 164 | V24: =_xlfn.RANK.EQ(U24,$U$4:$U$102,1) -> 43 | W24: =IF(Y24="Not suitable","-",V24) -> 43 | Y24: =IF(OR(Z24="Y",AA24="Y"),"Not suitable","") | Z24: =IF(OR(N24="N/A",O24="N/A"),"Y","") | AS24: 140000000 | AT24: 1037100000 | AU24: 5754200000 | AV24: 417000000 | AW24: 2983300000 | AX24: 2.2462071e+09 | AY24: 1.40601 | AZ24: 1.20221
B25: 000425.SZ | C25: XCMG Construction Machinery Co Ltd | E25: China | F25: =AS25/AT25 -> 0.080644995 | G25: =AU25/AV25 -> 15.951746 | H25: =AX25 -> 1.0133849e+10 | I25: =IFERROR((AY25/AZ25)-1,"-") -> -0.13201458 | J25: =AV25/AX25 -> 0.07144149 | K25: =IFERROR(_xlfn.RANK.EQ(F25,F$3:F$102),"N/A") -> 73 | L25: =IFERROR(_xlfn.RANK.EQ(G25,G$3:G$102),"N/A") -> 3 | M25: =IFERROR(_xlfn.RANK.EQ(H25,H$3:H$102),"N/A") -> 16 | N25: =IFERROR(_xlfn.RANK.EQ(I25,I$3:I$102),"N/A") -> 78 | O25: =IFERROR(_xlfn.RANK.EQ(J25,J$3:J$102),"N/A") -> 67 | P25: =IFERROR(ABS(K$3-K25),"N/A") -> 65 | Q25: =IFERROR(ABS(L$3-L25),"N/A") -> 30 | R25: =IFERROR(ABS(M$3-M25),"N/A") -> 13 | S25: =IFERROR(ABS(N$3-N25),"N/A") -> 2 | T25: =IFERROR(ABS(O$3-O25),"N/A") -> 32 | U25: =SUM(P25:T25) -> 142 | V25: =_xlfn.RANK.EQ(U25,$U$4:$U$102,1) -> 33 | W25: =IF(Y25="Not suitable","-",V25) -> 33 | Y25: =IF(OR(Z25="Y",AA25="Y"),"Not suitable","") | Z25: =IF(OR(N25="N/A",O25="N/A"),"Y","") | AS25: 6.2266803e+08 | AT25: 7.7210996e+09 | AU25: 1.1548701e+10 | AV25: 7.2397726e+08 | AW25: 1.3602204e+10 | AX25: 1.0133849e+10 | AY25: 0.071923729 | AZ25: 0.082862831
B26: WNC.N | C26: Wabash National Corp | E26: United States of America | F26: =AS26/AT26 -> 0.4219412 | G26: =AU26/AV26 -> 1.2709289 | H26: =AX26 -> 1.2808873e+09 | I26: =IFERROR((AY26/AZ26)-1,"-") -> -0.52120622 | J26: =AV26/AX26 -> 0.24354133 | K26: =IFERROR(_xlfn.RANK.EQ(F26,F$3:F$102),"N/A") -> 5 | L26: =IFERROR(_xlfn.RANK.EQ(G26,G$3:G$102),"N/A") -> 71 | M26: =IFERROR(_xlfn.RANK.EQ(H26,H$3:H$102),"N/A") -> 59 | N26: =IFERROR(_xlfn.RANK.EQ(I26,I$3:I$102),"N/A") -> 97 | O26: =IFERROR(_xlfn.RANK.EQ(J26,J$3:J$102),"N/A") -> 9 | P26: =IFERROR(ABS(K$3-K26),"N/A") -> 3 | Q26: =IFERROR(ABS(L$3-L26),"N/A") -> 38 | R26: =IFERROR(ABS(M$3-M26),"N/A") -> 56 | S26: =IFERROR(ABS(N$3-N26),"N/A") -> 21 | T26: =IFERROR(ABS(O$3-O26),"N/A") -> 26 | U26: =SUM(P26:T26) -> 144 | V26: =_xlfn.RANK.EQ(U26,$U$4:$U$102,1) -> 35 | W26: =IF(Y26="Not suitable","-",V26) -> 35 | Y26: =IF(OR(Z26="Y",AA26="Y"),"Not suitable","") | Z26: =IF(OR(N26="N/A",O26="N/A"),"Y","") | AS26: 231855000 | AT26: 549496000 | AU26: 396465000 | AV26: 311949000 | AW26: 2536500000 | AX26: 1.2808873e+09 | AY26: 2.23127 | AZ26: 4.66019
... B41: RAPT4.SA | C41: Randon SA Implementos e Participacoes | E41: Brazil | F41: =AS41/AT41 -> 0.23876124 | G41: =AU41/AV41 -> 3.8478164 | H41: =AX41 -> 7.9077111e+08 | I41: =IFERROR((AY41/AZ41)-1,"-") -> 0.10740565 | J41: =AV41/AX41 -> 0.38052564 | K41: =IFERROR(_xlfn.RANK.EQ(F41,F$3:F$102),"N/A") -> 17 | L41: =IFERROR(_xlfn.RANK.EQ(G41,G$3:G$102),"N/A") -> 36 | M41: =IFERROR(_xlfn.RANK.EQ(H41,H$3:H$102),"N/A") -> 74 | N41: =IFERROR(_xlfn.RANK.EQ(I41,I$3:I$102),"N/A") -> 50 | O41: =IFERROR(_xlfn.RANK.EQ(J41,J$3:J$102),"N/A") -> 3 | P41: =IFERROR(ABS(K$3-K41),"N/A") -> 9 | Q41: =IFERROR(ABS(L$3-L41),"N/A") -> 3 | R41: =IFERROR(ABS(M$3-M41),"N/A") -> 71 | S41: =IFERROR(ABS(N$3-N41),"N/A") -> 26 | T41: =IFERROR(ABS(O$3-O41),"N/A") -> 32 | U41: =SUM(P41:T41) -> 141 | V41: =_xlfn.RANK.EQ(U41,$U$4:$U$102,1) -> 31 | W41: =IF(Y41="Not suitable","-",V41) -> 31 | Y41: =IF(OR(Z41="Y",AA41="Y"),"Not suitable","") | Z41: =IF(OR(N41="N/A",O41="N/A"),"Y","") | AS41: 1.3668824e+08 | AT41: 5.7248923e+08 | AU41: 1.1578413e+09 | AV41: 3.0090868e+08 | AW41: 2.2439445e+09 | AX41: 7.9077111e+08 | AY41: 0.32435084 | AZ41: 0.29289253
B42: 000490.KS | C42: Daedong Corp | E42: Korea; Republic (S. Korea) | F42: =AS42/AT42 -> 0.026261459 | G42: =AU42/AV42 -> 12.446952 | H42: =AX42 -> 2.6234794e+08 | I42: =IFERROR((AY42/AZ42)-1,"-") -> 0.40632319 | J42: =AV42/AX42 -> 0.19657255 | K42: =IFERROR(_xlfn.RANK.EQ(F42,F$3:F$102),"N/A") -> 90 | L42: =IFERROR(_xlfn.RANK.EQ(G42,G$3:G$102),"N/A") -> 6 | M42: =IFERROR(_xlfn.RANK.EQ(H42,H$3:H$102),"N/A") -> 90 | N42: =IFERROR(_xlfn.RANK.EQ(I42,I$3:I$102),"N/A") -> 19 | O42: =IFERROR(_xlfn.RANK.EQ(J42,J$3:J$102),"N/A") -> 21 | P42: =IFERROR(ABS(K$3-K42),"N/A") -> 82 | Q42: =IFERROR(ABS(L$3-L42),"N/A") -> 27 | R42: =IFERROR(ABS(M$3-M42),"N/A") -> 87 | S42: =IFERROR(ABS(N$3-N42),"N/A") -> 57 | T42: =IFERROR(ABS(O$3-O42),"N/A") -> 14 | U42: =SUM(P42:T42) -> 267 | V42: =_xlfn.RANK.EQ(U42,$U$4:$U$102,1) -> 86 | W42: =IF(Y42="Not suitable","-",V42) -> - | Y42: Not Suitable | Z42: =IF(OR(N42="N/A",O42="N/A"),"Y","") | AS42: 9208521.1 | AT42: 3.5064773e+08 | AU42: 6.4189435e+08 | AV42: 51570403 | AW42: 1.1073785e+09 | AX42: 2.6234794e+08 | AY42: 1.7968955 | AZ42: 1.2777258
B43: OTKAR.IS | C43: Otokar Otomotiv ve Savunma Sanayi AS | E43: Turkey | F43: =AS43/AT43 -> 0.2370141 | G43: =AU43/AV43 -> 6.4735962 | H43: =AX43 -> 1.6515853e+09 | I43: =IFERROR((AY43/AZ43)-1,"-") -> 1.9780839 | J43: =AV43/AX43 -> 0.0511891 | K43: =IFERROR(_xlfn.RANK.EQ(F43,F$3:F$102),"N/A") -> 18 | L43: =IFERROR(_xlfn.RANK.EQ(G43,G$3:G$102),"N/A") -> 16 | M43: =IFERROR(_xlfn.RANK.EQ(H43,H$3:H$102),"N/A") -> 54 | N43: =IFERROR(_xlfn.RANK.EQ(I43,I$3:I$102),"N/A") -> 3 | O43: =IFERROR(_xlfn.RANK.EQ(J43,J$3:J$102),"N/A") -> 75 | P43: =IFERROR(ABS(K$3-K43),"N/A") -> 10 | Q43: =IFERROR(ABS(L$3-L43),"N/A") -> 17 | R43: =IFERROR(ABS(M$3-M43),"N/A") -> 51 | S43: =IFERROR(ABS(N$3-N43),"N/A") -> 73 | T43: =IFERROR(ABS(O$3-O43),"N/A") -> 40 | U43: =SUM(P43:T43) -> 191 | V43: =_xlfn.RANK.EQ(U43,$U$4:$U$102,1) -> 64 | W43: =IF(Y43="Not suitable","-",V43) -> - | Y43: Not Suitable | Z43: =IF(OR(N43="N/A",O43="N/A"),"Y","") | AS43: 66763534 | AT43: 2.8168591e+08 | AU43: 5.472983e+08 | AV43: 84543163 | AW43: 9.240849e+08 | AX43: 1.6515853e+09 | AY43: 1.5305646 | AZ43: 0.51394275
B44: 002900.KS | C44: TYM Corp | E44: Korea; Republic (S. Korea) | F44: =AS44/AT44 -> 0.29266245 | G44: =AU44/AV44 -> 1.7269515 | H44: =AX44 -> 1.8619009e+08 | I44: =IFERROR((AY44/AZ44)-1,"-") -> 0.25965661 | J44: =AV44/AX44 -> 0.51972239 | K44: =IFERROR(_xlfn.RANK.EQ(F44,F$3:F$102),"N/A") -> 11 | L44: =IFERROR(_xlfn.RANK.EQ(G44,G$3:G$102),"N/A") -> 67 | M44: =IFERROR(_xlfn.RANK.EQ(H44,H$3:H$102),"N/A") -> 95 | N44: =IFERROR(_xlfn.RANK.EQ(I44,I$3:I$102),"N/A") -> 29 | O44: =IFERROR(_xlfn.RANK.EQ(J44,J$3:J$102),"N/A") -> 1 | P44: =IFERROR(ABS(K$3-K44),"N/A") -> 3 | Q44: =IFERROR(ABS(L$3-L44),"N/A") -> 34 | R44: =IFERROR(ABS(M$3-M44),"N/A") -> 92 | S44: =IFERROR(ABS(N$3-N44),"N/A") -> 47 | T44: =IFERROR(ABS(O$3-O44),"N/A") -> 34 | U44: =SUM(P44:T44) -> 210 | V44: =_xlfn.RANK.EQ(U44,$U$4:$U$102,1) -> 72 | W44: =IF(Y44="Not suitable","-",V44) -> - | Y44: Not Suitable | Z44: =IF(OR(N44="N/A",O44="N/A"),"Y","") | AS44: 77868628 | AT44: 2.6606976e+08 | AU44: 1.6711219e+08 | AV44: 96767157 | AW44: 9.2483168e+08 | AX44: 1.8619009e+08 | AY44: 1.4293758 | AZ44: 1.1347345
B45: PON1V.HE | C45: Ponsse Oyj | E45: Finland | F45: =AS45/AT45 -> 0.093303584 | G45: =AU45/AV45 -> 2.5333065 | H45: =AX45 -> 6.9935526e+08 | I45: =IFERROR((AY45/AZ45)-1,"-") -> 0.34366498 | J45: =AV45/AX45 -> 0.07440823 | K45: =IFERROR(_xlfn.RANK.EQ(F45,F$3:F$102),"N/A") -> 69 | L45: =IFERROR(_xlfn.RANK.EQ(G45,G$3:G$102),"N/A") -> 52 | M45: =IFERROR(_xlfn.RANK.EQ(H45,H$3:H$102),"N/A") -> 76 | N45: =IFERROR(_xlfn.RANK.EQ(I45,I$3:I$102),"N/A") -> 23 | O45: =IFERROR(_xlfn.RANK.EQ(J45,J$3:J$102),"N/A") -> 64 | P45: =IFERROR(ABS(K$3-K45),"N/A") -> 61 | Q45: =IFERROR(ABS(L$3-L45),"N/A") -> 19 | R45: =IFERROR(ABS(M$3-M45),"N/A") -> 73 | S45: =IFERROR(ABS(N$3-N45),"N/A") -> 53 | T45: =IFERROR(ABS(O$3-O45),"N/A") -> 29 | U45: =SUM(P45:T45) -> 235 | V45: =_xlfn.RANK.EQ(U45,$U$4:$U$102,1) -> 76 | W45: =IF(Y45="Not suitable","-",V45) -> 76 | Y45: =IF(OR(Z45="Y",AA45="Y"),"Not suitable","") | Z45: =IF(OR(N45="N/A",O45="N/A"),"Y","") | AS45: 33135422 | AT45: 3.5513558e+08 | AU45: 1.3182766e+08 | AV45: 52037787 | AW45: 9.0693388e+08 | AX45: 6.9935526e+08 | AY45: 1.3394347 | AZ45: 0.99685165
B46: 600817.SS | C46: Yutong Heavy Industries Co Ltd | E46: China | F46: =AS46/AT46 -> 0.17190174 | G46: =AU46/AV46 -> 0.72237882 | H46: =AX46 -> 6.2046588e+08 | I46: =IFERROR((AY46/AZ46)-1,"-") -> -0.48821516 | J46: =AV46/AX46 -> 0.11244909 | K46: =IFERROR(_xlfn.RANK.EQ(F46,F$3:F$102),"N/A") -> 35 | L46: =IFERROR(_xlfn.RANK.EQ(G46,G$3:G$102),"N/A") -> 81 | M46: =IFERROR(_xlfn.RANK.EQ(H46,H$3:H$102),"N/A") -> 77 | N46: =IFERROR(_xlfn.RANK.EQ(I46,I$3:I$102),"N/A") -> 96 | O46: =IFERROR(_xlfn.RANK.EQ(J46,J$3:J$102),"N/A") -> 42 | P46: =IFERROR(ABS(K$3-K46),"N/A") -> 27 | Q46: =IFERROR(ABS(L$3-L46),"N/A") -> 48 | R46: =IFERROR(ABS(M$3-M46),"N/A") -> 74 | S46: =IFERROR(ABS(N$3-N46),"N/A") -> 20 | T46: =IFERROR(ABS(O$3-O46),"N/A") -> 7 | U46: =SUM(P46:T46) -> 176 | V46: =_xlfn.RANK.EQ(U46,$U$4:$U$102,1) -> 51 | W46: =IF(Y46="Not suitable","-",V46) -> 51 | Y46: =IF(OR(Z46="Y",AA46="Y"),"Not suitable","") | Z46: =IF(OR(N46="N/A",O46="N/A"),"Y","") | AS46: 60559192 | AT46: 3.5228959e+08 | AU46: 50400966 | AV46: 69770824 | AW46: 5.1981684e+08 | AX46: 6.2046588e+08 | AY46: 0.061815985 | AZ46: 0.1207851
B47: ASOK.NS | C47: Ashok Leyland Ltd | E47: India | F47: =AS47/AT47 -> 0.15918531 | G47: =AU47/AV47 -> 7.4638746 | H47: =AX47 -> 5.956611e+09 | I47: =IFERROR((AY47/AZ47)-1,"-") -> 1.1102108 | J47: =AV47/AX47 -> 0.085307341 | K47: =IFERROR(_xlfn.RANK.EQ(F47,F$3:F$102),"N/A") -> 43 | L47: =IFERROR(_xlfn.RANK.EQ(G47,G$3:G$102),"N/A") -> 11 | M47: =IFERROR(_xlfn.RANK.EQ(H47,H$3:H$102),"N/A") -> 28 | N47: =IFERROR(_xlfn.RANK.EQ(I47,I$3:I$102),"N/A") -> 6 | O47: =IFERROR(_xlfn.RANK.EQ(J47,J$3:J$102),"N/A") -> 55 | P47: =IFERROR(ABS(K$3-K47),"N/A") -> 35 | Q47: =IFERROR(ABS(L$3-L47),"N/A") -> 22 | R47: =IFERROR(ABS(M$3-M47),"N/A") -> 25 | S47: =IFERROR(ABS(N$3-N47),"N/A") -> 70 | T47: =IFERROR(ABS(O$3-O47),"N/A") -> 20 | U47: =SUM(P47:T47) -> 172 | V47: =_xlfn.RANK.EQ(U47,$U$4:$U$102,1) -> 49 | W47: =IF(Y47="Not suitable","-",V47) -> 49 | Y47: =IF(OR(Z47="Y",AA47="Y"),"Not suitable","") | Z47: =IF(OR(N47="N/A",O47="N/A"),"Y","") | AS47: 1.6573272e+08 | AT47: 1.0411307e+09 | AU47: 3.792713e+09 | AV47: 5.0814265e+08 | AW47: 5.0721276e+09 | AX47: 5.956611e+09 | AY47: 0.10218839 | AZ47: 0.048425678
B48: ESCO.NS | C48: Escorts Kubota Ltd | E48: India | F48: =AS48/AT48 -> 0.077766282 | G48: =AU48/AV48 -> 0.089444601 | H48: =AX48 -> 3.6417377e+09 | I48: =IFERROR((AY48/AZ48)-1,"-") -> 0.56086658 | J48: =AV48/AX48 -> 0.021410727 | K48: =IFERROR(_xlfn.RANK.EQ(F48,F$3:F$102),"N/A") -> 75 | L48: =IFERROR(_xlfn.RANK.EQ(G48,G$3:G$102),"N/A") -> 87 | M48: =IFERROR(_xlfn.RANK.EQ(H48,H$3:H$102),"N/A") -> 38 | N48: =IFERROR(_xlfn.RANK.EQ(I48,I$3:I$102),"N/A") -> 12 | O48: =IFERROR(_xlfn.RANK.EQ(J48,J$3:J$102),"N/A") -> 90 | P48: =IFERROR(ABS(K$3-K48),"N/A") -> 67 | Q48: =IFERROR(ABS(L$3-L48),"N/A") -> 54 | R48: =IFERROR(ABS(M$3-M48),"N/A") -> 35 | S48: =IFERROR(ABS(N$3-N48),"N/A") -> 64 | T48: =IFERROR(ABS(O$3-O48),"N/A") -> 55 | U48: =SUM(P48:T48) -> 275 | V48: =_xlfn.RANK.EQ(U48,$U$4:$U$102,1) -> 87 | W48: =IF(Y48="Not suitable","-",V48) -> 87 | Y48: =IF(OR(Z48="Y",AA48="Y"),"Not suitable","") | Z48: =IF(OR(N48="N/A",O48="N/A"),"Y","") | AS48: 77489046 | AT48: 9.96435e+08 | AU48: 6974196.7 | AV48: 77972249 | AW48: 1.0258873e+09 | AX48: 3.6417377e+09 | AY48: 1.0780087 | AZ48: 0.69064759
B49: GBX.N | C49: Greenbrier Companies Inc | E49: United States of America | F49: =AS49/AT49 -> 0.052925235 | G49: =AU49/AV49 -> 9.1201814 | H49: =AX49 -> 1.5868741e+09 | I49: =IFERROR((AY49/AZ49)-1,"-") -> 0.31013127 | J49: =AV49/AX49 -> 0.11116194 | K49: =IFERROR(_xlfn.RANK.EQ(F49,F$3:F$102),"N/A") -> 83 | L49: =IFERROR(_xlfn.RANK.EQ(G49,G$3:G$102),"N/A") -> 10 | M49: =IFERROR(_xlfn.RANK.EQ(H49,H$3:H$102),"N/A") -> 55 | N49: =IFERROR(_xlfn.RANK.EQ(I49,I$3:I$102),"N/A") -> 28 | O49: =IFERROR(_xlfn.RANK.EQ(J49,J$3:J$102),"N/A") -> 44 | P49: =IFERROR(ABS(K$3-K49),"N/A") -> 75 | Q49: =IFERROR(ABS(L$3-L49),"N/A") -> 23 | R49: =IFERROR(ABS(M$3-M49),"N/A") -> 52 | S49: =IFERROR(ABS(N$3-N49),"N/A") -> 48 | T49: =IFERROR(ABS(O$3-O49),"N/A") -> 9 | U49: =SUM(P49:T49) -> 207 | V49: =_xlfn.RANK.EQ(U49,$U$4:$U$102,1) -> 71 | W49: =IF(Y49="Not suitable","-",V49) -> 71 | Y49: =IF(OR(Z49="Y",AA49="Y"),"Not suitable","") | Z49: =IF(OR(N49="N/A",O49="N/A"),"Y","") | AS49: 66400000 | AT49: 1254600000 | AU49: 1608800000 | AV49: 176400000 | AW49: 3944000000 | AX49: 1.5868741e+09 | AY49: 4.00025 | AZ49: 3.05332
B50: KCRA.HE | C50: Konecranes Abp | E50: Finland | F50: =AS50/AT50 -> 0.17281164 | G50: =AU50/AV50 -> 2.3724224 | H50: =AX50 -> 4.2836573e+09 | I50: =IFERROR((AY50/AZ50)-1,"-") -> 0.069867125 | J50: =AV50/AX50 -> 0.10369568 | K50: =IFERROR(_xlfn.RANK.EQ(F50,F$3:F$102),"N/A") -> 34 | L50: =IFERROR(_xlfn.RANK.EQ(G50,G$3:G$102),"N/A") -> 55 | M50: =IFERROR(_xlfn.RANK.EQ(H50,H$3:H$102),"N/A") -> 32 | N50: =IFERROR(_xlfn.RANK.EQ(I50,I$3:I$102),"N/A") -> 54 | O50: =IFERROR(_xlfn.RANK.EQ(J50,J$3:J$102),"N/A") -> 49 | P50: =IFERROR(ABS(K$3-K50),"N/A") -> 26 | Q50: =IFERROR(ABS(L$3-L50),"N/A") -> 22 | R50: =IFERROR(ABS(M$3-M50),"N/A") -> 29 | S50: =IFERROR(ABS(N$3-N50),"N/A") -> 22 | T50: =IFERROR(ABS(O$3-O50),"N/A") -> 14 | U50: =SUM(P50:T50) -> 113 | V50: =_xlfn.RANK.EQ(U50,$U$4:$U$102,1) -> 20 | W50: =IF(Y50="Not suitable","-",V50) -> 20 | Y50: =IF(OR(Z50="Y",AA50="Y"),"Not suitable","") | Z50: =IF(OR(N50="N/A",O50="N/A"),"Y","") | AS50: 3.0415062e+08 | AT50: 1.7600124e+09 | AU50: 1.0538223e+09 | AV50: 4.4419675e+08 | AW50: 4.3771865e+09 | AX50: 4.2836573e+09 | AY50: 4.0945477 | AZ50: 3.8271554
B51: ALSO.PA | C51: Alstom SA | E51: France | F51: =AS51/AT51 -> -0.024008003 | G51: =AU51/AV51 -> -46.810127 | H51: =AX51 -> 5.6632806e+09 | I51: =IFERROR((AY51/AZ51)-1,"-") -> -0.058142946 | J51: =AV51/AX51 -> -0.015119947 | K51: =IFERROR(_xlfn.RANK.EQ(F51,F$3:F$102),"N/A") -> 94 | L51: =IFERROR(_xlfn.RANK.EQ(G51,G$3:G$102),"N/A") -> 99 | M51: =IFERROR(_xlfn.RANK.EQ(H51,H$3:H$102),"N/A") -> 29 | N51: =IFERROR(_xlfn.RANK.EQ(I51,I$3:I$102),"N/A") -> 71 | O51: =IFERROR(_xlfn.RANK.EQ(J51,J$3:J$102),"N/A") -> 95 | P51: =IFERROR(ABS(K$3-K51),"N/A") -> 86 | Q51: =IFERROR(ABS(L$3-L51),"N/A") -> 66 | R51: =IFERROR(ABS(M$3-M51),"N/A") -> 26 | S51: =IFERROR(ABS(N$3-N51),"N/A") -> 5 | T51: =IFERROR(ABS(O$3-O51),"N/A") -> 60 | U51: =SUM(P51:T51) -> 243 | V51: =_xlfn.RANK.EQ(U51,$U$4:$U$102,1) -> 80 | W51: =IF(Y51="Not suitable","-",V51) -> 80 | Y51: =IF(OR(Z51="Y",AA51="Y"),"Not suitable","") | Z51: =IF(OR(N51="N/A",O51="N/A"),"Y","") | AS51: -2.341235e+08 | AT51: 9.7518941e+09 | AU51: 4.008281e+09 | AV51: -85628502 | AW51: 1.7892021e+10 | AX51: 5.6632806e+09 | AY51: 1.4250772 | AZ51: 1.5130504
B52: PALF.VI | C52: Palfinger AG | E52: Austria | F52: =AS52/AT52 -> 0.19216287 | G52: =AU52/AV52 -> 3.59074 | H52: =AX52 -> 9.4507622e+08 | I52: =IFERROR((AY52/AZ52)-1,"-") -> -0.34469719 | J52: =AV52/AX52 -> 0.24550134 | K52: =IFERROR(_xlfn.RANK.EQ(F52,F$3:F$102),"N/A") -> 28 | L52: =IFERROR(_xlfn.RANK.EQ(G52,G$3:G$102),"N/A") -> 41 | M52: =IFERROR(_xlfn.RANK.EQ(H52,H$3:H$102),"N/A") -> 70 | N52: =IFERROR(_xlfn.RANK.EQ(I52,I$3:I$102),"N/A") -> 91 | O52: =IFERROR(_xlfn.RANK.EQ(J52,J$3:J$102),"N/A") -> 8 | P52: =IFERROR(ABS(K$3-K52),"N/A") -> 20 | Q52: =IFERROR(ABS(L$3-L52),"N/A") -> 8 | R52: =IFERROR(ABS(M$3-M52),"N/A") -> 67 | S52: =IFERROR(ABS(N$3-N52),"N/A") -> 15 | T52: =IFERROR(ABS(O$3-O52),"N/A") -> 27 | U52: =SUM(P52:T52) -> 137 | V52: =_xlfn.RANK.EQ(U52,$U$4:$U$102,1) -> 29 | W52: =IF(Y52="Not suitable","-",V52) -> 29 | Y52: =IF(OR(Z52="Y",AA52="Y"),"Not suitable","") | Z52: =IF(OR(N52="N/A",O52="N/A"),"Y","") | AS52: 1.3899992e+08 | AT52: 7.2334433e+08 | AU52: 8.3311445e+08 | AV52: 2.3201748e+08 | AW52: 2.6992286e+09 | AX52: 9.4507622e+08 | AY52: 2.4713401 | AZ52: 3.7712948
B53: 000951.SZ | C53: Sinotruk Jinan Truck Co Ltd | E53: China | F53: =AS53/AT53 -> 0.097190587 | G53: =AU53/AV53 -> 4.0359128 | H53: =AX53 -> 2.5344596e+09 | I53: =IFERROR((AY53/AZ53)-1,"-") -> 0.40922118 | J53: =AV53/AX53 -> 0.098696587 | K53: =IFERROR(_xlfn.RANK.EQ(F53,F$3:F$102),"N/A") -> 67 | L53: =IFERROR(_xlfn.RANK.EQ(G53,G$3:G$102),"N/A") -> 34 | M53: =IFERROR(_xlfn.RANK.EQ(H53,H$3:H$102),"N/A") -> 46 | N53: =IFERROR(_xlfn.RANK.EQ(I53,I$3:I$102),"N/A") -> 17 | O53: =IFERROR(_xlfn.RANK.EQ(J53,J$3:J$102),"N/A") -> 51 | P53: =IFERROR(ABS(K$3-K53),"N/A") -> 59 | Q53: =IFERROR(ABS(L$3-L53),"N/A") -> 1 | R53: =IFERROR(ABS(M$3-M53),"N/A") -> 43 | S53: =IFERROR(ABS(N$3-N53),"N/A") -> 59 | T53: =IFERROR(ABS(O$3-O53),"N/A") -> 16 | U53: =SUM(P53:T53) -> 178 | V53: =_xlfn.RANK.EQ(U53,$U$4:$U$102,1) -> 54 | W53: =IF(Y53="Not suitable","-",V53) -> 54 | Y53: =IF(OR(Z53="Y",AA53="Y"),"Not suitable","") | Z53: =IF(OR(N53="N/A",O53="N/A"),"Y","") | AS53: 2.0163107e+08 | AT53: 2.0745946e+09 | AU53: 1.0095534e+09 | AV53: 2.5014252e+08 | AW53: 5.9271821e+09 | AX53: 2.5344596e+09 | AY53: 0.17006346 | AZ53: 0.12067904
B54: 000157.SZ | C54: Zoomlion Heavy Industry Science and Technology Co Ltd | E54: China | F54: =AS54/AT54 -> 0.043562116 | G54: =AU54/AV54 -> 13.074569 | H54: =AX54 -> 8.7551422e+09 | I54: =IFERROR((AY54/AZ54)-1,"-") -> 0.31421264 | J54: =AV54/AX54 -> 0.039517583 | K54: =IFERROR(_xlfn.RANK.EQ(F54,F$3:F$102),"N/A") -> 88 | L54: =IFERROR(_xlfn.RANK.EQ(G54,G$3:G$102),"N/A") -> 5 | M54: =IFERROR(_xlfn.RANK.EQ(H54,H$3:H$102),"N/A") -> 21 | N54: =IFERROR(_xlfn.RANK.EQ(I54,I$3:I$102),"N/A") -> 27 | O54: =IFERROR(_xlfn.RANK.EQ(J54,J$3:J$102),"N/A") -> 85 | P54: =IFERROR(ABS(K$3-K54),"N/A") -> 80 | Q54: =IFERROR(ABS(L$3-L54),"N/A") -> 28 | R54: =IFERROR(ABS(M$3-M54),"N/A") -> 18 | S54: =IFERROR(ABS(N$3-N54),"N/A") -> 49 | T54: =IFERROR(ABS(O$3-O54),"N/A") -> 50 | U54: =SUM(P54:T54) -> 225 | V54: =_xlfn.RANK.EQ(U54,$U$4:$U$102,1) -> 75 | W54: =IF(Y54="Not suitable","-",V54) -> 75 | Y54: =IF(OR(Z54="Y",AA54="Y"),"Not suitable","") | Z54: =IF(OR(N54="N/A",O54="N/A"),"Y","") | AS54: 3.4574002e+08 | AT54: 7.9367131e+09 | AU54: 4.5235661e+09 | AV54: 3.4598206e+08 | AW54: 6.0359998e+09 | AX54: 8.7551422e+09 | AY54: 0.057758609 | AZ54: 0.043949211
B55: 042670.KS | C55: HD Hyundai Infracore Co Ltd | E55: Korea; Republic (S. Korea) | F55: =AS55/AT55 -> 0.12710384 | G55: =AU55/AV55 -> 1.5652702 | H55: =AX55 -> 1.2544982e+09 | I55: =IFERROR((AY55/AZ55)-1,"-") -> -0.1736361 | J55: =AV55/AX55 -> 0.25803951 | K55: =IFERROR(_xlfn.RANK.EQ(F55,F$3:F$102),"N/A") -> 55 | L55: =IFERROR(_xlfn.RANK.EQ(G55,G$3:G$102),"N/A") -> 69 | M55: =IFERROR(_xlfn.RANK.EQ(H55,H$3:H$102),"N/A") -> 61 | N55: =IFERROR(_xlfn.RANK.EQ(I55,I$3:I$102),"N/A") -> 83 | O55: =IFERROR(_xlfn.RANK.EQ(J55,J$3:J$102),"N/A") -> 6 | P55: =IFERROR(ABS(K$3-K55),"N/A") -> 47 | Q55: =IFERROR(ABS(L$3-L55),"N/A") -> 36 | R55: =IFERROR(ABS(M$3-M55),"N/A") -> 58 | S55: =IFERROR(ABS(N$3-N55),"N/A") -> 7 | T55: =IFERROR(ABS(O$3-O55),"N/A") -> 29 | U55: =SUM(P55:T55) -> 177 | V55: =_xlfn.RANK.EQ(U55,$U$4:$U$102,1) -> 52 | W55: =IF(Y55="Not suitable","-",V55) -> 52 | Y55: =IF(OR(Z55="Y",AA55="Y"),"Not suitable","") | Z55: =IF(OR(N55="N/A",O55="N/A"),"Y","") | AS55: 1.7823891e+08 | AT55: 1.4023094e+09 | AU55: 5.0669378e+08 | AV55: 3.2371011e+08 | AW55: 3.5998181e+09 | AX55: 1.2544982e+09 | AY55: 0.99669348 | AZ55: 1.2061193
B56: BUCN.S | C56: Bucher Industries AG | E56: Switzerland | F56: =AS56/AT56 -> 0.19800713 | G56: =AU56/AV56 -> 0.31503299 | H56: =AX56 -> 4.5299711e+09 | I56: =IFERROR((AY56/AZ56)-1,"-") -> -0.17003663 | J56: =AV56/AX56 -> 0.11133349 | K56: =IFERROR(_xlfn.RANK.EQ(F56,F$3:F$102),"N/A") -> 26 | L56: =IFERROR(_xlfn.RANK.EQ(G56,G$3:G$102),"N/A") -> 86 | M56: =IFERROR(_xlfn.RANK.EQ(H56,H$3:H$102),"N/A") -> 31 | N56: =IFERROR(_xlfn.RANK.EQ(I56,I$3:I$102),"N/A") -> 81 | O56: =IFERROR(_xlfn.RANK.EQ(J56,J$3:J$102),"N/A") -> 43 | P56: =IFERROR(ABS(K$3-K56),"N/A") -> 18 | Q56: =IFERROR(ABS(L$3-L56),"N/A") -> 53 | R56: =IFERROR(ABS(M$3-M56),"N/A") -> 28 | S56: =IFERROR(ABS(N$3-N56),"N/A") -> 5 | T56: =IFERROR(ABS(O$3-O56),"N/A") -> 8 | U56: =SUM(P56:T56) -> 112 | V56: =_xlfn.RANK.EQ(U56,$U$4:$U$102,1) -> 19 | W56: =IF(Y56="Not suitable","-",V56) -> - | Y56: Not Suitable | Z56: =IF(OR(N56="N/A",O56="N/A"),"Y","") | AS56: 4.2269756e+08 | AT56: 2.1347594e+09 | AU56: 1.5888295e+08 | AV56: 5.0433749e+08 | AW56: 4.2481283e+09 | AX56: 4.5299711e+09 | AY56: 29.504234 | AZ56: 35.548839
B57: 6432.T | C57: Takeuchi Mfg Co Ltd | E57: Japan | F57: =AS57/AT57 -> 0.13119653 | G57: =AU57/AV57 -> 0.0019118631 | H57: =AX57 -> 1.9140487e+09 | I57: =IFERROR((AY57/AZ57)-1,"-") -> 0.47877685 | J57: =AV57/AX57 -> 0.080255186 | K57: =IFERROR(_xlfn.RANK.EQ(F57,F$3:F$102),"N/A") -> 54 | L57: =IFERROR(_xlfn.RANK.EQ(G57,G$3:G$102),"N/A") -> 93 | M57: =IFERROR(_xlfn.RANK.EQ(H57,H$3:H$102),"N/A") -> 51 | N57: =IFERROR(_xlfn.RANK.EQ(I57,I$3:I$102),"N/A") -> 16 | O57: =IFERROR(_xlfn.RANK.EQ(J57,J$3:J$102),"N/A") -> 59 | P57: =IFERROR(ABS(K$3-K57),"N/A") -> 46 | Q57: =IFERROR(ABS(L$3-L57),"N/A") -> 60 | R57: =IFERROR(ABS(M$3-M57),"N/A") -> 48 | S57: =IFERROR(ABS(N$3-N57),"N/A") -> 60 | T57: =IFERROR(ABS(O$3-O57),"N/A") -> 24 | U57: =SUM(P57:T57) -> 238 | V57: =_xlfn.RANK.EQ(U57,$U$4:$U$102,1) -> 78 | W57: =IF(Y57="Not suitable","-",V57) -> - | Y57: Not Suitable | Z57: =IF(OR(N57="N/A",O57="N/A"),"Y","") | AS57: 1.1732746e+08 | AT57: 8.9428781e+08 | AU57: 293685.76 | AV57: 1.5361233e+08 | AW57: 1.3139941e+09 | AX57: 1.9140487e+09 | AY57: 3.4788037 | AZ57: 2.3524873
B58: 600031.SS | C58: Sany Heavy Industry Co Ltd | E58: China | F58: =AS58/AT58 -> 0.067798663 | G58: =AU58/AV58 -> 10.683806 | H58: =AX58 -> 1.7141722e+10 | I58: =IFERROR((AY58/AZ58)-1,"-") -> 0.116027 | J58: =AV58/AX58 -> 0.041434422 | K58: =IFERROR(_xlfn.RANK.EQ(F58,F$3:F$102),"N/A") -> 78 | L58: =IFERROR(_xlfn.RANK.EQ(G58,G$3:G$102),"N/A") -> 7 | M58: =IFERROR(_xlfn.RANK.EQ(H58,H$3:H$102),"N/A") -> 13 | N58: =IFERROR(_xlfn.RANK.EQ(I58,I$3:I$102),"N/A") -> 47 | O58: =IFERROR(_xlfn.RANK.EQ(J58,J$3:J$102),"N/A") -> 84 | P58: =IFERROR(ABS(K$3-K58),"N/A") -> 70 | Q58: =IFERROR(ABS(L$3-L58),"N/A") -> 26 | R58: =IFERROR(ABS(M$3-M58),"N/A") -> 10 | S58: =IFERROR(ABS(N$3-N58),"N/A") -> 29 | T58: =IFERROR(ABS(O$3-O58),"N/A") -> 49 | U58: =SUM(P58:T58) -> 184 | V58: =_xlfn.RANK.EQ(U58,$U$4:$U$102,1) -> 59 | W58: =IF(Y58="Not suitable","-",V58) -> 59 | Y58: =IF(OR(Z58="Y",AA58="Y"),"Not suitable","") | Z58: =IF(OR(N58="N/A",O58="N/A"),"Y","") | AS58: 6.386048e+08 | AT58: 9.4191356e+09 | AU58: 7.5882519e+09 | AV58: 7.1025735e+08 | AW58: 1.1718108e+10 | AX58: 1.7141722e+10 | AY58: 0.082126081 | AZ58: 0.073587897
B59: ANG.AX | C59: Austin Engineering Ltd | E59: Australia | F59: =AS59/AT59 -> 0.062304068 | G59: =AU59/AV59 -> 4.1485598 | H59: =AX59 -> 1.8960424e+08 | I59: =IFERROR((AY59/AZ59)-1,"-") -> 0.81165987 | J59: =AV59/AX59 -> 0.046502747 | K59: =IFERROR(_xlfn.RANK.EQ(F59,F$3:F$102),"N/A") -> 80 | L59: =IFERROR(_xlfn.RANK.EQ(G59,G$3:G$102),"N/A") -> 31 | M59: =IFERROR(_xlfn.RANK.EQ(H59,H$3:H$102),"N/A") -> 94 | N59: =IFERROR(_xlfn.RANK.EQ(I59,I$3:I$102),"N/A") -> 8 | O59: =IFERROR(_xlfn.RANK.EQ(J59,J$3:J$102),"N/A") -> 79 | P59: =IFERROR(ABS(K$3-K59),"N/A") -> 72 | Q59: =IFERROR(ABS(L$3-L59),"N/A") -> 2 | R59: =IFERROR(ABS(M$3-M59),"N/A") -> 91 | S59: =IFERROR(ABS(N$3-N59),"N/A") -> 68 | T59: =IFERROR(ABS(O$3-O59),"N/A") -> 44 | U59: =SUM(P59:T59) -> 277 | V59: =_xlfn.RANK.EQ(U59,$U$4:$U$102,1) -> 89 | W59: =IF(Y59="Not suitable","-",V59) -> - | Y59: Not Suitable | Z59: =IF(OR(N59="N/A",O59="N/A"),"Y","") | AS59: 4742859 | AT59: 76124388 | AU59: 36578342 | AV59: 8817118.3 | AW59: 1.7218145e+08 | AX59: 1.8960424e+08 | AY59: 0.036376277 | AZ59: 0.020078977
B60: TTRAK.IS | C60: Turk Traktor ve Ziraat Makineleri AS | E60: Turkey | F60: =AS60/AT60 -> 0.60669988 | G60: =AU60/AV60 -> 0.5119725 | H60: =AX60 -> 2.8354971e+09 | I60: =IFERROR((AY60/AZ60)-1,"-") -> 0.13094867 | J60: =AV60/AX60 -> 0.13528468 | K60: =IFERROR(_xlfn.RANK.EQ(F60,F$3:F$102),"N/A") -> 1 | L60: =IFERROR(_xlfn.RANK.EQ(G60,G$3:G$102),"N/A") -> 85 | M60: =IFERROR(_xlfn.RANK.EQ(H60,H$3:H$102),"N/A") -> 42 | N60: =IFERROR(_xlfn.RANK.EQ(I60,I$3:I$102),"N/A") -> 45 | O60: =IFERROR(_xlfn.RANK.EQ(J60,J$3:J$102),"N/A") -> 35 | P60: =IFERROR(ABS(K$3-K60),"N/A") -> 7 | Q60: =IFERROR(ABS(L$3-L60),"N/A") -> 52 | R60: =IFERROR(ABS(M$3-M60),"N/A") -> 39 | S60: =IFERROR(ABS(N$3-N60),"N/A") -> 31 | T60: =IFERROR(ABS(O$3-O60),"N/A") -> 0 | U60: =SUM(P60:T60) -> 129 | V60: =_xlfn.RANK.EQ(U60,$U$4:$U$102,1) -> 24 | W60: =IF(Y60="Not suitable","-",V60) -> 24 | Y60: =IF(OR(Z60="Y",AA60="Y"),"Not suitable","") | Z60: =IF(OR(N60="N/A",O60="N/A"),"Y","") | AS60: 3.1692797e+08 | AT60: 5.2238014e+08 | AU60: 1.963923e+08 | AV60: 3.8359932e+08 | AW60: 1.9824415e+09 | AX60: 2.8354971e+09 | AY60: 3.2360171 | AZ60: 2.8613298
B61: NEX.BK | C61: Nex Point PCL | E61: Thailand | F61: =AS61/AT61 -> 0.18446565 | G61: =AU61/AV61 -> 0.069077009 | H61: =AX61 -> 5.3718707e+08 | I61: =IFERROR((AY61/AZ61)-1,"-") -> 0.22058824 | J61: =AV61/AX61 -> 0.031323196 | K61: =IFERROR(_xlfn.RANK.EQ(F61,F$3:F$102),"N/A") -> 30 | L61: =IFERROR(_xlfn.RANK.EQ(G61,G$3:G$102),"N/A") -> 88 | M61: =IFERROR(_xlfn.RANK.EQ(H61,H$3:H$102),"N/A") -> 82 | N61: =IFERROR(_xlfn.RANK.EQ(I61,I$3:I$102),"N/A") -> 34 | O61: =IFERROR(_xlfn.RANK.EQ(J61,J$3:J$102),"N/A") -> 88 | P61: =IFERROR(ABS(K$3-K61),"N/A") -> 22 | Q61: =IFERROR(ABS(L$3-L61),"N/A") -> 55 | R61: =IFERROR(ABS(M$3-M61),"N/A") -> 79 | S61: =IFERROR(ABS(N$3-N61),"N/A") -> 42 | T61: =IFERROR(ABS(O$3-O61),"N/A") -> 53 | U61: =SUM(P61:T61) -> 251 | V61: =_xlfn.RANK.EQ(U61,$U$4:$U$102,1) -> 82 | W61: =IF(Y61="Not suitable","-",V61) -> - | Y61: Not Suitable | Z61: =IF(OR(N61="N/A",O61="N/A"),"Y","") | AS61: 22225693 | AT61: 1.2048689e+08 | AU61: 1162318.5 | AV61: 16826416 | AW61: 2.707233e+08 | AX61: 5.3718707e+08 | AY61: 0.023314607 | AZ61: 0.019101124
B62: CGCBV.HE | C62: Cargotec Corp | E62: Finland | F62: =AS62/AT62 -> 0.19899561 | G62: =AU62/AV62 -> 1.7914427 | H62: =AX62 -> 3.868755e+09 | I62: =IFERROR((AY62/AZ62)-1,"-") -> -0.22968317 | J62: =AV62/AX62 -> 0.13800796 | K62: =IFERROR(_xlfn.RANK.EQ(F62,F$3:F$102),"N/A") -> 25 | L62: =IFERROR(_xlfn.RANK.EQ(G62,G$3:G$102),"N/A") -> 65 | M62: =IFERROR(_xlfn.RANK.EQ(H62,H$3:H$102),"N/A") -> 37 | N62: =IFERROR(_xlfn.RANK.EQ(I62,I$3:I$102),"N/A") -> 87 | O62: =IFERROR(_xlfn.RANK.EQ(J62,J$3:J$102),"N/A") -> 34 | P62: =IFERROR(ABS(K$3-K62),"N/A") -> 17 | Q62: =IFERROR(ABS(L$3-L62),"N/A") -> 32 | R62: =IFERROR(ABS(M$3-M62),"N/A") -> 34 | S62: =IFERROR(ABS(N$3-N62),"N/A") -> 11 | T62: =IFERROR(ABS(O$3-O62),"N/A") -> 1 | U62: =SUM(P62:T62) -> 95 | V62: =_xlfn.RANK.EQ(U62,$U$4:$U$102,1) -> 11 | W62: =IF(Y62="Not suitable","-",V62) -> 11 | Y62: =IF(OR(Z62="Y",AA62="Y"),"Not suitable","") | Z62: =IF(OR(N62="N/A",O62="N/A"),"Y","") | AS62: 3.8482337e+08 | AT62: 1.9338285e+09 | AU62: 9.5648527e+08 | AV62: 5.3391897e+08 | AW62: 5.0421021e+09 | AX62: 3.868755e+09 | AY62: 4.9195165 | AZ62: 6.3863547
B63: RAIL.OQ | C63: FreightCar America Inc | E63: United States of America | F63: =AS63/AT63 -> -0.63322775 | G63: =AU63/AV63 -> -17.684908 | H63: =AX63 -> 71363948 | I63: =IFERROR((AY63/AZ63)-1,"-") -> -1.3125 | J63: =AV63/AX63 -> -0.057101661 | K63: =IFERROR(_xlfn.RANK.EQ(F63,F$3:F$102),"N/A") -> 98 | L63: =IFERROR(_xlfn.RANK.EQ(G63,G$3:G$102),"N/A") -> 98 | M63: =IFERROR(_xlfn.RANK.EQ(H63,H$3:H$102),"N/A") -> 98 | N63: =IFERROR(_xlfn.RANK.EQ(I63,I$3:I$102),"N/A") -> 100 | O63: =IFERROR(_xlfn.RANK.EQ(J63,J$3:J$102),"N/A") -> 96 | P63: =IFERROR(ABS(K$3-K63),"N/A") -> 90 | Q63: =IFERROR(ABS(L$3-L63),"N/A") -> 65 | R63: =IFERROR(ABS(M$3-M63),"N/A") -> 95 | S63: =IFERROR(ABS(N$3-N63),"N/A") -> 24 | T63: =IFERROR(ABS(O$3-O63),"N/A") -> 61 | U63: =SUM(P63:T63) -> 335 | V63: =_xlfn.RANK.EQ(U63,$U$4:$U$102,1) -> 97 | W63: =IF(Y63="Not suitable","-",V63) -> 97 | Y63: =IF(OR(Z63="Y",AA63="Y"),"Not suitable","") | Z63: =IF(OR(N63="N/A",O63="N/A"),"Y","") | AS63: -23589000 | AT63: 37252000 | AU63: 72066000 | AV63: -4075000 | AW63: 358093000 | AX63: 71363948 | AY63: 0.1 | AZ63: -0.32
B64: 3339.HK | C64: Lonking Holdings Ltd | E64: China | F64: =AS64/AT64 -> 0.041065799 | G64: =AU64/AV64 -> 2.0771388 | H64: =AX64 -> 7.9324936e+08 | I64: =IFERROR((AY64/AZ64)-1,"-") -> 0.53331746 | J64: =AV64/AX64 -> 0.062313758 | K64: =IFERROR(_xlfn.RANK.EQ(F64,F$3:F$102),"N/A") -> 89 | L64: =IFERROR(_xlfn.RANK.EQ(G64,G$3:G$102),"N/A") -> 59 | M64: =IFERROR(_xlfn.RANK.EQ(H64,H$3:H$102),"N/A") -> 73 | N64: =IFERROR(_xlfn.RANK.EQ(I64,I$3:I$102),"N/A") -> 13 | O64: =IFERROR(_xlfn.RANK.EQ(J64,J$3:J$102),"N/A") -> 70 | P64: =IFERROR(ABS(K$3-K64),"N/A") -> 81 | Q64: =IFERROR(ABS(L$3-L64),"N/A") -> 26 | R64: =IFERROR(ABS(M$3-M64),"N/A") -> 70 | S64: =IFERROR(ABS(N$3-N64),"N/A") -> 63 | T64: =IFERROR(ABS(O$3-O64),"N/A") -> 35 | U64: =SUM(P64:T64) -> 275 | V64: =_xlfn.RANK.EQ(U64,$U$4:$U$102,1) -> 87 | W64: =IF(Y64="Not suitable","-",V64) -> 87 | Y64: =IF(OR(Z64="Y",AA64="Y"),"Not suitable","") | Z64: =IF(OR(N64="N/A",O64="N/A"),"Y","") | AS64: 58043844 | AT64: 1.4134352e+09 | AU64: 1.0267369e+08 | AV64: 49430349 | AW64: 1.616632e+09 | AX64: 7.9324936e+08 | AY64: 0.019595018 | AZ64: 0.012779492
B65: WACGn.DE | C65: Wacker Neuson SE | E65: Germany | F65: =AS65/AT65 -> 0.12395812 | G65: =AU65/AV65 -> 1.8729868 | H65: =AX65 -> 1.319424e+09 | I65: =IFERROR((AY65/AZ65)-1,"-") -> -0.26049776 | J65: =AV65/AX65 -> 0.22851032 | K65: =IFERROR(_xlfn.RANK.EQ(F65,F$3:F$102),"N/A") -> 56 | L65: =IFERROR(_xlfn.RANK.EQ(G65,G$3:G$102),"N/A") -> 63 | M65: =IFERROR(_xlfn.RANK.EQ(H65,H$3:H$102),"N/A") -> 57 | N65: =IFERROR(_xlfn.RANK.EQ(I65,I$3:I$102),"N/A") -> 90 | O65: =IFERROR(_xlfn.RANK.EQ(J65,J$3:J$102),"N/A") -> 11 | P65: =IFERROR(ABS(K$3-K65),"N/A") -> 48 | Q65: =IFERROR(ABS(L$3-L65),"N/A") -> 30 | R65: =IFERROR(ABS(M$3-M65),"N/A") -> 54 | S65: =IFERROR(ABS(N$3-N65),"N/A") -> 14 | T65: =IFERROR(ABS(O$3-O65),"N/A") -> 24 | U65: =SUM(P65:T65) -> 170 | V65: =_xlfn.RANK.EQ(U65,$U$4:$U$102,1) -> 45 | W65: =IF(Y65="Not suitable","-",V65) -> 45 | Y65: =IF(OR(Z65="Y",AA65="Y"),"Not suitable","") | Z65: =IF(OR(N65="N/A",O65="N/A"),"Y","") | AS65: 2.051582e+08 | AT65: 1.6550605e+09 | AU65: 5.6470926e+08 | AV65: 3.0150199e+08 | AW65: 2.9299328e+09 | AX65: 1.319424e+09 | AY65: 2.1984774 | AZ65: 2.9729152
B66: METSO.HE | C66: Metso Oyj | E66: Finland | F66: =AS66/AT66 -> 0.20590491 | G66: =AU66/AV66 -> 1.8981366 | H66: =AX66 -> 9.8181381e+09 | I66: =IFERROR((AY66/AZ66)-1,"-") -> 0.0053064849 | J66: =AV66/AX66 -> 0.090484926 | K66: =IFERROR(_xlfn.RANK.EQ(F66,F$3:F$102),"N/A") -> 23 | L66: =IFERROR(_xlfn.RANK.EQ(G66,G$3:G$102),"N/A") -> 62 | M66: =IFERROR(_xlfn.RANK.EQ(H66,H$3:H$102),"N/A") -> 17 | N66: =IFERROR(_xlfn.RANK.EQ(I66,I$3:I$102),"N/A") -> 65 | O66: =IFERROR(_xlfn.RANK.EQ(J66,J$3:J$102),"N/A") -> 54 | P66: =IFERROR(ABS(K$3-K66),"N/A") -> 15 | Q66: =IFERROR(ABS(L$3-L66),"N/A") -> 29 | R66: =IFERROR(ABS(M$3-M66),"N/A") -> 14 | S66: =IFERROR(ABS(N$3-N66),"N/A") -> 11 | T66: =IFERROR(ABS(O$3-O66),"N/A") -> 19 | U66: =SUM(P66:T66) -> 88 | V66: =_xlfn.RANK.EQ(U66,$U$4:$U$102,1) -> 8 | W66: =IF(Y66="Not suitable","-",V66) -> 8 | Y66: =IF(OR(Z66="Y",AA66="Y"),"Not suitable","") | Z66: =IF(OR(N66="N/A",O66="N/A"),"Y","") | AS66: 5.926302e+08 | AT66: 2.8781742e+09 | AU66: 1.6862923e+09 | AV66: 8.883935e+08 | AW66: 5.9483739e+09 | AX66: 9.8181381e+09 | AY66: 0.75294578 | AZ66: 0.74897137
B67: ACEL.NS | C67: Action Construction Equipment Ltd | E67: India | F67: =AS67/AT67 -> 0.1883201 | G67: =AU67/AV67 -> 0.035954355 | H67: =AX67 -> 2.012728e+09 | I67: =IFERROR((AY67/AZ67)-1,"-") -> 0.66776416 | J67: =AV67/AX67 -> 0.012527209 | K67: =IFERROR(_xlfn.RANK.EQ(F67,F$3:F$102),"N/A") -> 29 | L67: =IFERROR(_xlfn.RANK.EQ(G67,G$3:G$102),"N/A") -> 89 | M67: =IFERROR(_xlfn.RANK.EQ(H67,H$3:H$102),"N/A") -> 49 | N67: =IFERROR(_xlfn.RANK.EQ(I67,I$3:I$102),"N/A") -> 9 | O67: =IFERROR(_xlfn.RANK.EQ(J67,J$3:J$102),"N/A") -> 91 | P67: =IFERROR(ABS(K$3-K67),"N/A") -> 21 | Q67: =IFERROR(ABS(L$3-L67),"N/A") -> 56 | R67: =IFERROR(ABS(M$3-M67),"N/A") -> 46 | S67: =IFERROR(ABS(N$3-N67),"N/A") -> 67 | T67: =IFERROR(ABS(O$3-O67),"N/A") -> 56 | U67: =SUM(P67:T67) -> 246 | V67: =_xlfn.RANK.EQ(U67,$U$4:$U$102,1) -> 81 | W67: =IF(Y67="Not suitable","-",V67) -> 81 | Y67: =IF(OR(Z67="Y",AA67="Y"),"Not suitable","") | Z67: =IF(OR(N67="N/A",O67="N/A"),"Y","") | AS67: 21054418 | AT67: 1.1180123e+08 | AU67: 906548.2 | AV67: 25213863 | AW67: 2.6286213e+08 | AX67: 2.012728e+09 | AY67: 0.31231159 | AZ67: 0.18726364
B68: SOM.L | C68: Somero Enterprises Inc | E68: United States of America | F68: =AS68/AT68 -> 0.33613264 | G68: =AU68/AV68 -> 0.0091977973 | H68: =AX68 -> 2.3256976e+08 | I68: =IFERROR((AY68/AZ68)-1,"-") -> -0.085106383 | J68: =AV68/AX68 -> 0.14445128 | K68: =IFERROR(_xlfn.RANK.EQ(F68,F$3:F$102),"N/A") -> 8 | L68: =IFERROR(_xlfn.RANK.EQ(G68,G$3:G$102),"N/A") -> 92 | M68: =IFERROR(_xlfn.RANK.EQ(H68,H$3:H$102),"N/A") -> 91 | N68: =IFERROR(_xlfn.RANK.EQ(I68,I$3:I$102),"N/A") -> 74 | O68: =IFERROR(_xlfn.RANK.EQ(J68,J$3:J$102),"N/A") -> 31 | P68: =IFERROR(ABS(K$3-K68),"N/A") -> 0 | Q68: =IFERROR(ABS(L$3-L68),"N/A") -> 59 | R68: =IFERROR(ABS(M$3-M68),"N/A") -> 88 | S68: =IFERROR(ABS(N$3-N68),"N/A") -> 2 | T68: =IFERROR(ABS(O$3-O68),"N/A") -> 4 | U68: =SUM(P68:T68) -> 153 | V68: =_xlfn.RANK.EQ(U68,$U$4:$U$102,1) -> 39 | W68: =IF(Y68="Not suitable","-",V68) -> 39 | Y68: =IF(OR(Z68="Y",AA68="Y"),"Not suitable","") | Z68: =IF(OR(N68="N/A",O68="N/A"),"Y","") | AS68: 27978000 | AT68: 83235000 | AU68: 309000 | AV68: 33595000 | AW68: 120699000 | AX68: 2.3256976e+08 | AY68: 0.43 | AZ68: 0.47
B69: 002111.SZ | C69: Weihai Guangtai Airport Equipment Co Ltd | E69: China | F69: =AS69/AT69 -> 0.077740675 | G69: =AU69/AV69 -> 4.8909444 | H69: =AX69 -> 7.5215096e+08 | I69: =IFERROR((AY69/AZ69)-1,"-") -> 1.0678058 | J69: =AV69/AX69 -> 0.051784894 | K69: =IFERROR(_xlfn.RANK.EQ(F69,F$3:F$102),"N/A") -> 76 | L69: =IFERROR(_xlfn.RANK.EQ(G69,G$3:G$102),"N/A") -> 26 | M69: =IFERROR(_xlfn.RANK.EQ(H69,H$3:H$102),"N/A") -> 75 | N69: =IFERROR(_xlfn.RANK.EQ(I69,I$3:I$102),"N/A") -> 7 | O69: =IFERROR(_xlfn.RANK.EQ(J69,J$3:J$102),"N/A") -> 74 | P69: =IFERROR(ABS(K$3-K69),"N/A") -> 68 | Q69: =IFERROR(ABS(L$3-L69),"N/A") -> 7 | R69: =IFERROR(ABS(M$3-M69),"N/A") -> 72 | S69: =IFERROR(ABS(N$3-N69),"N/A") -> 69 | T69: =IFERROR(ABS(O$3-O69),"N/A") -> 39 | U69: =SUM(P69:T69) -> 255 | V69: =_xlfn.RANK.EQ(U69,$U$4:$U$102,1) -> 85 | W69: =IF(Y69="Not suitable","-",V69) -> 85 | Y69: =IF(OR(Z69="Y",AA69="Y"),"Not suitable","") | Z69: =IF(OR(N69="N/A",O69="N/A"),"Y","") | AS69: 34074275 | AT69: 4.3830691e+08 | AU69: 1.9050257e+08 | AV69: 38950058 | AW69: 3.4012298e+08 | AX69: 7.5215096e+08 | AY69: 0.084765267 | AZ69: 0.040992857
B70: TITN.OQ | C70: Titan Machinery Inc | E70: United States of America | F70: =AS70/AT70 -> 0.170976 | G70: =AU70/AV70 -> 6.0052652 | H70: =AX70 -> 5.3467566e+08 | I70: =IFERROR((AY70/AZ70)-1,"-") -> -0.34863865 | J70: =AV70/AX70 -> 0.31578958 | K70: =IFERROR(_xlfn.RANK.EQ(F70,F$3:F$102),"N/A") -> 37 | L70: =IFERROR(_xlfn.RANK.EQ(G70,G$3:G$102),"N/A") -> 18 | M70: =IFERROR(_xlfn.RANK.EQ(H70,H$3:H$102),"N/A") -> 83 | N70: =IFERROR(_xlfn.RANK.EQ(I70,I$3:I$102),"N/A") -> 92 | O70: =IFERROR(_xlfn.RANK.EQ(J70,J$3:J$102),"N/A") -> 4 | P70: =IFERROR(ABS(K$3-K70),"N/A") -> 29 | Q70: =IFERROR(ABS(L$3-L70),"N/A") -> 15 | R70: =IFERROR(ABS(M$3-M70),"N/A") -> 80 | S70: =IFERROR(ABS(N$3-N70),"N/A") -> 16 | T70: =IFERROR(ABS(O$3-O70),"N/A") -> 31 | U70: =SUM(P70:T70) -> 171 | V70: =_xlfn.RANK.EQ(U70,$U$4:$U$102,1) -> 48 | W70: =IF(Y70="Not suitable","-",V70) -> 48 | Y70: =IF(OR(Z70="Y",AA70="Y"),"Not suitable","") | Z70: =IF(OR(N70="N/A",O70="N/A"),"Y","") | AS70: 112441000 | AT70: 657642000 | AU70: 1013959000 | AV70: 168845000 | AW70: 2758445000 | AX70: 5.3467566e+08 | AY70: 3.21553 | AZ70: 4.93663
B71: 3808.HK | C71: Sinotruk Hong Kong Ltd | E71: China | F71: =AS71/AT71 -> 0.14468682 | G71: =AU71/AV71 -> 0.77871009 | H71: =AX71 -> 6.89569e+09 | I71: =IFERROR((AY71/AZ71)-1,"-") -> 0.15016392 | J71: =AV71/AX71 -> 0.13254067 | K71: =IFERROR(_xlfn.RANK.EQ(F71,F$3:F$102),"N/A") -> 49 | L71: =IFERROR(_xlfn.RANK.EQ(G71,G$3:G$102),"N/A") -> 80 | M71: =IFERROR(_xlfn.RANK.EQ(H71,H$3:H$102),"N/A") -> 26 | N71: =IFERROR(_xlfn.RANK.EQ(I71,I$3:I$102),"N/A") -> 40 | O71: =IFERROR(_xlfn.RANK.EQ(J71,J$3:J$102),"N/A") -> 37 | P71: =IFERROR(ABS(K$3-K71),"N/A") -> 41 | Q71: =IFERROR(ABS(L$3-L71),"N/A") -> 47 | R71: =IFERROR(ABS(M$3-M71),"N/A") -> 23 | S71: =IFERROR(ABS(N$3-N71),"N/A") -> 36 | T71: =IFERROR(ABS(O$3-O71),"N/A") -> 2 | U71: =SUM(P71:T71) -> 149 | V71: =_xlfn.RANK.EQ(U71,$U$4:$U$102,1) -> 38 | W71: =IF(Y71="Not suitable","-",V71) -> 38 | Y71: =IF(OR(Z71="Y",AA71="Y"),"Not suitable","") | Z71: =IF(OR(N71="N/A",O71="N/A"),"Y","") | AS71: 8.2093761e+08 | AT71: 5.6738935e+09 | AU71: 7.117094e+08 | AV71: 9.139594e+08 | AW71: 1.2045709e+10 | AX71: 6.89569e+09 | AY71: 0.30268649 | AZ71: 0.26316813
B72: 601766.SS | C72: Crrc Corp Ltd | E72: China | F72: =AS72/AT72 -> 0.092569999 | G72: =AU72/AV72 -> 3.6461151 | H72: =AX72 -> 2.4435266e+10 | I72: =IFERROR((AY72/AZ72)-1,"-") -> 0.18121589 | J72: =AV72/AX72 -> 0.095375607 | K72: =IFERROR(_xlfn.RANK.EQ(F72,F$3:F$102),"N/A") -> 70 | L72: =IFERROR(_xlfn.RANK.EQ(G72,G$3:G$102),"N/A") -> 40 | M72: =IFERROR(_xlfn.RANK.EQ(H72,H$3:H$102),"N/A") -> 9 | N72: =IFERROR(_xlfn.RANK.EQ(I72,I$3:I$102),"N/A") -> 37 | O72: =IFERROR(_xlfn.RANK.EQ(J72,J$3:J$102),"N/A") -> 52 | P72: =IFERROR(ABS(K$3-K72),"N/A") -> 62 | Q72: =IFERROR(ABS(L$3-L72),"N/A") -> 7 | R72: =IFERROR(ABS(M$3-M72),"N/A") -> 6 | S72: =IFERROR(ABS(N$3-N72),"N/A") -> 39 | T72: =IFERROR(ABS(O$3-O72),"N/A") -> 17 | U72: =SUM(P72:T72) -> 131 | V72: =_xlfn.RANK.EQ(U72,$U$4:$U$102,1) -> 27 | W72: =IF(Y72="Not suitable","-",V72) -> 27 | Y72: =IF(OR(Z72="Y",AA72="Y"),"Not suitable","") | Z72: =IF(OR(N72="N/A",O72="N/A"),"Y","") | AS72: 2.0808698e+09 | AT72: 2.2478879e+10 | AU72: 8.4973744e+09 | AV72: 2.3305283e+09 | AW72: 3.2323064e+10 | AX72: 2.4435266e+10 | AY72: 0.059995555 | AZ72: 0.050791354
B73: PLOW.N | C73: Douglas Dynamics Inc | E73: United States of America | F73: =AS73/AT73 -> 0.1024464 | G73: =AU73/AV73 -> 5.2384377 | H73: =AX73 -> 5.4058286e+08 | I73: =IFERROR((AY73/AZ73)-1,"-") -> 0.11439238 | J73: =AV73/AX73 -> 0.083075146 | K73: =IFERROR(_xlfn.RANK.EQ(F73,F$3:F$102),"N/A") -> 64 | L73: =IFERROR(_xlfn.RANK.EQ(G73,G$3:G$102),"N/A") -> 22 | M73: =IFERROR(_xlfn.RANK.EQ(H73,H$3:H$102),"N/A") -> 81 | N73: =IFERROR(_xlfn.RANK.EQ(I73,I$3:I$102),"N/A") -> 48 | O73: =IFERROR(_xlfn.RANK.EQ(J73,J$3:J$102),"N/A") -> 58 | P73: =IFERROR(ABS(K$3-K73),"N/A") -> 56 | Q73: =IFERROR(ABS(L$3-L73),"N/A") -> 11 | R73: =IFERROR(ABS(M$3-M73),"N/A") -> 78 | S73: =IFERROR(ABS(N$3-N73),"N/A") -> 28 | T73: =IFERROR(ABS(O$3-O73),"N/A") -> 23 | U73: =SUM(P73:T73) -> 196 | V73: =_xlfn.RANK.EQ(U73,$U$4:$U$102,1) -> 66 | W73: =IF(Y73="Not suitable","-",V73) -> 66 | Y73: =IF(OR(Z73="Y",AA73="Y"),"Not suitable","") | Z73: =IF(OR(N73="N/A",O73="N/A"),"Y","") | AS73: 23723000 | AT73: 231565000 | AU73: 235253000 | AV73: 44909000 | AW73: 568178000 | AX73: 5.4058286e+08 | AY73: 1.56717 | AZ73: 1.4063
... B102: IVG.MI | C102: Iveco Group NV | E102: Italy | F102: =AS102/AT102 -> 0.099405268 | G102: =AU102/AV102 -> 7.2879331 | H102: =AX102 -> 4.1239216e+09 | I102: =IFERROR((AY102/AZ102)-1,"-") -> -0.0099879206 | J102: =AV102/AX102 -> 0.2239879 | K102: =IFERROR(_xlfn.RANK.EQ(F102,F$3:F$102),"N/A") -> 66 | L102: =IFERROR(_xlfn.RANK.EQ(G102,G$3:G$102),"N/A") -> 12 | M102: =IFERROR(_xlfn.RANK.EQ(H102,H$3:H$102),"N/A") -> 34 | N102: =IFERROR(_xlfn.RANK.EQ(I102,I$3:I$102),"N/A") -> 68 | O102: =IFERROR(_xlfn.RANK.EQ(J102,J$3:J$102),"N/A") -> 12 | P102: =IFERROR(ABS(K$3-K102),"N/A") -> 58 | Q102: =IFERROR(ABS(L$3-L102),"N/A") -> 21 | R102: =IFERROR(ABS(M$3-M102),"N/A") -> 31 | S102: =IFERROR(ABS(N$3-N102),"N/A") -> 8 | T102: =IFERROR(ABS(O$3-O102),"N/A") -> 23 | U102: =SUM(P102:T102) -> 141 | V102: =_xlfn.RANK.EQ(U102,$U$4:$U$102,1) -> 31 | W102: =IF(Y102="Not suitable","-",V102) -> 31 | Y102: =IF(OR(Z102="Y",AA102="Y"),"Not suitable","") | Z102: =IF(OR(N102="N/A",O102="N/A"),"Y","") | AS102: 2.5824109e+08 | AT102: 2.5978612e+09 | AU102: 6.7319259e+09 | AV102: 9.2370852e+08 | AW102: 1.7892576e+10 | AX102: 4.1239216e+09 | AY102: 1.5543342 | AZ102: 1.5700154

Sheet ESG
B1: Company GICS Sector:
B2: Industrials | C2: <- Select Industry
B3: ESG Analysis | K3: Relative ESG Analysis
B4: Parameters | C4: Impact | D4: Do they report? | E4: Ranking | F4: Mitigation Plan | G4: Traffic Lights | H4: Improvement over time? | I4: Targets / Goals? | J4: Comments | K4: Parameters | L4: =Peers!C8 -> #VALUE! | M4: =Peers!D8 -> #VALUE! | N4: =Peers!E8 -> #VALUE! | O4: =Peers!F8 -> #VALUE! | P4: =Peers!G8 -> #VALUE! | Q4: =Peers!#REF! -> #REF! | R4: =Peers!#REF! -> #REF! | S4: =Peers!#REF! -> #REF! | T4: AVERAGE
B5: Environmental | K5: Ratios
A6: 1 | B6: CO2 Direct Emissions | C6: =VLOOKUP($B$2,'[2]Sector Impact'!$K$4:$AA$16,A6+1,FALSE) -> Very High | D6: Yes | E6: Medium High | F6: Yes | H6: regarding scope 1&2 emissions yes (from 293 in 2018 to 271 in 2022) but regarding scope 3 emissions no (from 1006 in 2018 to 1059 in 2022) | I6: 2030 target for scope 1&2 emissions is 190 and for scope 3 emissions 754 | J6: Scope 1&2 measured in tonnes CO2e and scope 3 Category 11 measured in g CO2e/vkm WTW. If scope 3 also measured in tonnes then 114542. | K6: CO2 Emissions/$MSales | L6: =IFERROR(L12/L$11,"N/A") -> 3.2684742 | M6: =IFERROR(M12/M$11,"N/A") -> 0.71261419 | N6: =IFERROR(N12/N$11,"N/A") -> 6.3034111 | O6: =IFERROR(O12/O$11,"N/A") -> 10.906262 | P6: =IFERROR(P12/P$11,"N/A") -> 16.778896 | Q6: =IFERROR(Q12/Q$11,"N/A") -> N/A | R6: =R12/R$11 -> #DIV/0! | S6: =S12/S$11 -> #DIV/0! | T6: =IFERROR(AVERAGE(L6:Q6),"") -> 7.5939316
A7: 2 | B7: Total Water Consumption | C7: =VLOOKUP($B$2,'[2]Sector Impact'!$K$4:$AA$16,A7+1,FALSE) -> Very High | D7: No | E7: Medium | F7: Yes | H7: No | I7: No target | J7: They have a water consumption and discharge monitoring and reporting system in place and 100% of the sites are meeting the water standarts (ISO 14001). However no reporting of actual water consumption | K7: Water Consumption/$MSales | L7: =IFERROR(L13/L$11,"N/A") -> N/A | M7: =IFERROR(M13/M$11,"N/A") -> 35.617189 | N7: =IFERROR(N13/N$11,"N/A") -> 34.755541 | O7: =IFERROR(O13/O$11,"N/A") -> 81.937641 | P7: =IFERROR(P13/P$11,"N/A") -> N/A | Q7: =IFERROR(Q13/Q$11,"N/A") -> N/A | R7: =R13/R$11 -> #DIV/0! | S7: =S13/S$11 -> #DIV/0! | T7: =IFERROR(AVERAGE(L7:Q7),"") -> 50.770124
A8: 3 | B8: Total Energy Consumption | C8: =VLOOKUP($B$2,'[2]Sector Impact'!$K$4:$AA$16,A8+1,FALSE) -> Very High | D8: Yes | E8: Medium | F8: No | H8: No, from 877708MWh in 2020 to 975978MWh in 2022 | I8: No target | J8: Sites measure and monitory energy usage (electricity, natural gas, etc.) including access to renewable power options. | K8: Energy Consumption/$MSales | L8: =IFERROR(L14/L$11,"N/A") -> 100.02223 | M8: =IFERROR(M14/M$11,"N/A") -> 79.359195 | N8: =IFERROR(N14/N$11,"N/A") -> N/A | O8: =IFERROR(O14/O$11,"N/A") -> 84.9934 | P8: =IFERROR(P14/P$11,"N/A") -> N/A | Q8: =IFERROR(Q14/Q$11,"N/A") -> N/A | R8: =R14/R$11 -> #DIV/0! | S8: =S14/S$11 -> #DIV/0! | T8: =IFERROR(AVERAGE(L8:Q8),"N/A") -> 88.124941
A9: 4 | B9: Waste Management | C9: =VLOOKUP($B$2,'[2]Sector Impact'!$K$4:$AA$16,A9+1,FALSE) -> High | D9: Yes | E9: Medium | F9: Yes | H9: Yes, from 87% in 2020 to 93% in 2022 | I9: Sites annually target achieving zero waste-to-landfill. | J9: Does not report actual amount of waste | K9: Waste Production/$MSales | L9: =IFERROR(L15/L$11,"N/A") -> N/A | M9: =IFERROR(M15/M$11,"N/A") -> 5.237505 | N9: =IFERROR(N15/N$11,"N/A") -> 3.2827028 | O9: =IFERROR(O15/O$11,"N/A") -> 8.1590097 | P9: =IFERROR(P15/P$11,"N/A") -> N/A | Q9: =IFERROR(Q15/Q$11,"N/A") -> N/A | R9: =R15/R$11 -> #DIV/0! | S9: =S15/S$11 -> #DIV/0! | T9: =IFERROR(AVERAGE(L9:Q9),"") -> 5.5597391
A10: 5 | B10: Land Degradation/Deforestation/Biodiversity loss/Animal sufering/… | C10: =VLOOKUP($B$2,'[2]Sector Impact'!$K$4:$AA$16,A10+1,FALSE) -> High | D10: No | E10: "Best in class" | F10: No | H10: NA | I10: NA | J10: Does not destroy any land | K10: Inputs
B11: Social | K11: Million Net Sales | L11: 35127.4 | M11: 60424 | N11: 96773 | O11: 60424 | P11: 56625 | Q11: =Peers!H60 -> 0 | R11: =Peers!I60 -> 0 | S11: =Peers!J60 -> 0
A12: 6 | B12: Employee Turnover % | C12: =VLOOKUP($B$2,'Sector Impact'!$K$4:$AA$16,A12+1,FALSE) -> Low | H12: No data, but iincreased overall employees over the oast three years | I12: No target | K12: CO2 Emissions Total (Tonnes) | L12: =271+114542 -> 114813 | M12: 43059 | N12: =202000+408000 -> 610000 | O12: 659000 | P12: 950105
A13: 7 | B13: Salaries & Compensation | C13: =VLOOKUP($B$2,'[2]Sector Impact'!$K$4:$AA$16,A13+1,FALSE) -> Medium | D13: No | E13: Medium High | F13: Yes | H13: No data | I13: No target | J13: 3.7 out of 5 on Glassdoor. 3.5 out of 5 on Indeed. "The average PACCAR salary ranges from approximately $58,149 per year for Dealer to $133,114 per year for Performance Manager" from Indeed. PACCAR provides robust benefits packages that support physical, emotional and financial well-being. Employee satisfaction and engagement are measured through periodic surveys that result in quantitative metrics leading to workplace enhancements. | K13: Water Consumption Total (Cubic Meters) | L13: NA | M13: 2152133 | N13: 3363398 | O13: 4951000 | P13: NA
A14: 8 | B14: Reputation | C14: =VLOOKUP($B$2,'[2]Sector Impact'!$K$4:$AA$16,A14+1,FALSE) -> High | D14: No | E14: Medium High | F14: Yes | H14: No data | I14: No target | J14: No bad reputation. | K14: Energy Consumption Total (Gigajoules) | L14: 3513520.8 | M14: 4795200 | N14: NA | O14: 5135641.2 | P14: NA
A15: 9 | B15: Discrimination Events | C15: =VLOOKUP($B$2,'[2]Sector Impact'!$K$4:$AA$16,A15+1,FALSE) -> Very High | D15: No | E15: "Best in class" | F15: Yes | H15: No data | I15: No target | J15: No discrimination events | K15: Waste Production Total (Tonnes) | L15: NA | M15: 316471 | N15: 317677 | O15: 493000 | P15: NA
A16: 10 | B16: Work Safety | C16: =VLOOKUP($B$2,'[2]Sector Impact'!$K$4:$AA$16,A16+1,FALSE) -> Medium | D16: Yes | E16: Medium High | F16: Yes | H16: No, from 1.4 injury/illness per 200000 hrs worked in 2020 to 1.9 in 2022 | I16: No numerical target | J16: "PACCAR's consistent focus on workplace safety has resulted in a fatality rate of zero, and a recordable injury/illness rate lower than the U.S. industry average as seen in the table above." | K16: ESG Scores
A17: 11 | B17: Damage to consumer health | C17: =VLOOKUP($B$2,'[2]Sector Impact'!$K$4:$AA$16,A17+1,FALSE) -> Very High | D17: No | E17: "Best in class" | F17: No | H17: No data | I17: No target | J17: No damage to consumer health, doesnt produce consumer goods | K17: Refinitiv | L17: 66 | M17: 72 | N17: 70 | O17: 84 | P17: 88
A18: 12 | B18: PXP? | C18: =VLOOKUP($B$2,'[2]Sector Impact'!$K$4:$AA$16,A18+1,FALSE) -> Medium | D18: Yes | E18: Medium High | F18: No | H18: No data | I18: No target | J18: Retirement & Pension 401(k) match (1:1 up to 5%) AND a fully-funded defined benefit pension | K18: Sustainalytics | L18: 24.4 | M18: 18.6 | N18: 25.3 | O18: 19.9 | P18: 22.4
A19: 13 | B19: Supply chain | C19: =VLOOKUP($B$2,'[2]Sector Impact'!$K$4:$AA$16,A19+1,FALSE) -> Very High | D19: No | E19: Medium High | F19: Yes | H19: No data | I19: No target | J19: PACCAR selects suppliers after detailed reviews of their operations. PACCAR conducts periodic on-site supplier visits, announced and unannounced, for various reasons, including verification and auditing of contract compliance. PACCAR is committed to ensuring that its suppliers do not use slave labor or engage in human trafficking. PACCAR’s Supplier Code of Conduct prohibits suppliers from using forced labor of any kind. PACCAR suppliers certify that they comply with laws regarding minimum employment age, working conditions and compensation, and do not engage in slavery or human trafficking. Noncompliance is grounds for termination and elimination from the PACCAR supply base. | K19: ISS | L19: C | M19: C | N19: C+ | O19: B- | P19: C+
A20: 14 | B20: Community involvement | C20: =VLOOKUP($B$2,'[2]Sector Impact'!$K$4:$AA$16,A20+1,FALSE) -> Very High | D20: Yes | E20: Medium High | F20: Yes | H20: Yes, gave 10.3 million to charity in 2023 vs. 6.4 in 2021 | I20: No target | J20: PACCAR makes these grants in locations in which its employees work and live worldwide. | K20: CDP | L20: A- | M20: A | N20: F | O20: B | P20: A-
A21: 15 | B21: Public Sector | C21: =VLOOKUP($B$2,'[2]Sector Impact'!$K$4:$AA$16,A21+1,FALSE) -> Very High | D21: Yes | E21: Medium High | F21: Yes | H21: Constant 0 company contributions to politcs | I21: No target | J21: Paccar is also member of certain trade associations
A22: 16 | B22: Litigation | C22: =VLOOKUP($B$2,'[2]Sector Impact'!$K$4:$AA$16,A22+1,FALSE) -> High | D22: Yes | E22: Medium | F22: No | H22: No data | I22: No target | J22: One lawsuit in 2023 regarding price fixing, were found guilty
B23: Corporate Governance | K23: PARAMETERS
A24: 17 | B24: Diversity (Gender, Age, Industry, Region) | E24: Medium | F24: Yes | H24: No data | I24: No target | J24: 3 of 12 directors are women. 17% of directors are racially/ethnically diverse | K24: IMPACT | L24: RANKING | M24: MITIGATION PLAN | P24: TRAFFIC
A25: 18 | B25: % Independence | E25: Medium High | F25: Yes | H25: No data | I25: No target | J25: 75% of PACCAR’s directors are independent. | K25: Low | L25: "Best in class" | M25: Is there evidence of a plan/program ?
A26: 19 | B26: average time as independent directors | E26: Medium | F26: No | H26: No data | I26: No target | J26: 11.7 years average tenure | K26: Medium | L26: Medium High
A27: 20 | B27: Recent departures of directors / C-level executives? | E27: "Best in class" | F27: No | H27: No data | I27: No target | J27: Senior Vice President and Controller retired in 2023 | K27: High | L27: Medium
A28: 21 | B28: CEO/Chairman duality | E28: "Best in class" | F28: No | H28: No data | I28: No target | J28: Have different chairman and CEO | K28: Very high | L28: "Villain"
A29: 22 | B29: Transparency (ESG, segments, acquisitions, other) | E29: "Best in class" | F29: No | H29: No data | I29: No target | J29: All information regarding the board and esg mesueares in available
A30: 23 | B30: Time taken to report after the end of the quarter / year | E30: Medium | F30: No | H30: No data | I30: No target | J30: No information available
A31: 24 | B31: Additional participation of the CEO in other boards or excessive participation of Ch. | E31: "Best in class" | F31: No | H31: No data | I31: No target | J31: Cannot find any information regarding positions in other boards so it is assumed there are non
A32: 25 | B32: Audit / Consulting | D32: No | E32: Medium | F32: No | H32: No data | I32: No target | J32: Non-audit fees represented 11.3% of total auditor fees in 2022.
A33: 26 | B33: ESG-compensation related | D33: No | E33: "Villain" | F33: No | H33: No data | I33: No target | J33: Only performance based and not ESG based
A34: 27 | B34: Management compensation schemes | D34: No | E34: Medium | F34: No | H34: No data | I34: No target | J34: It is only saying that compensation is performance based, nothing else.

Sheet DCF
A1: VALUATION MODEL
G3: Short Term | K3: Long Term
A4: Section | B4: Line # | C4: ITEM | D4: =OP!J19-2&" (Real)" -> 2021 (Real) | E4: =OP!J19-1&" (Real)" -> 2022 (Real) | F4: =OP!J19&" (Real)" -> 2023 (Real) | G4: =OP!J19+1 -> 2024 | H4: =G4+1 -> 2025 | I4: =H4+1 -> 2026 | J4: =I4+1 -> 2027 | K4: =J4+1 -> 2028 | L4: =K4+1 -> 2029 | M4: =L4+1 -> 2030 | N4: =M4+1 -> 2031 | O4: =N4+1 -> 2032 | ... AF4: =AE4+1 -> 2049
A5: INCOME STATEMENT | B5: 1 | C5: Growth | D5: ='Fin. Data'!D6 -> 0.25591329 | E5: =+E6/D6-1 -> 0.22523595 | F5: 0.21884108 | G5: =G6/F6-1 -> 0.02046644 | H5: =H6/G6-1 -> 0.076419971 | I5: =I6/H6-1 -> 0.051025579 | J5: =J6/I6-1 -> 0.04966317 | K5: =K6/J6-1 -> 0.037366757 | L5: =L6/K6-1 -> 0.044108117 | M5: =M6/L6-1 -> 0.023122733 | N5: =N6/M6-1 -> 0.022777014 | ... AE5: =AE6/AD6-1 -> 0.081218713 | AF5: 0.02
B6: 2 | C6: Revenues/Sales | D6: =Inputs!D6 -> 23522 | E6: =Inputs!C6 -> 28820 | F6: =Inputs!B6 -> 35127 | G6: =Assumptions!M259 -> 35845.925 | H6: =Assumptions!N259 -> 38585.269 | I6: =Assumptions!O259 -> 40554.105 | J6: =Assumptions!P259 -> 42568.15 | K6: =Assumptions!Q259 -> 44158.784 | L6: =Assumptions!R259 -> 46106.545 | M6: =Assumptions!S259 -> 47172.654 | N6: =Assumptions!T259 -> 48247.106 | ... AE6: =Assumptions!AK259 -> 137918.32 | AF6: =AE6*(1+AF5) -> 140676.69
B7: 3 | C7: EBIT Margin | D7: =D8/D6 -> 0.10377519 | E7: =E8/E6 -> 0.1351492 | F7: =F8/F6 -> 0.16645316 | G7: 0.185 | H7: 0.18 | I7: 0.17 | J7: 0.16 | K7: 0.15 | L7: =$K$7 -> 0.15 | M7: =$K$7 -> 0.15 | N7: =$K$7 -> 0.15 | O7: =$K$7 -> 0.15 | P7: =$K$7 -> 0.15 | Q7: =$K$7 -> 0.15 | R7: =$K$7 -> 0.15 | S7: =$K$7 -> 0.15 | ... AF7: =$K$7 -> 0.15
B8: 4 | C8: EBIT | D8: ='Fin. Data'!D16 -> 2441 | E8: ='Fin. Data'!C16 -> 3895 | F8: ='Fin. Data'!B16 -> 5847 | G8: =G7*G6 -> 6631.4961 | H8: =H7*H6 -> 6945.3484 | I8: =I7*I6 -> 6894.1978 | J8: =J7*J6 -> 6810.904 | K8: =K7*K6 -> 6623.8176 | L8: =L7*L6 -> 6915.9817 | M8: =M7*M6 -> 7075.8981 | N8: =N7*N6 -> 7237.066 | ... AF8: =AF7*AF6 -> 21101.503
B9: 5a | C9: (Depreciation) | D9: =-Inputs!D129 -> -969 | E9: =-Inputs!C129 -> -561 | F9: =-Inputs!B129 -> -591 | G9: =-$D$53*DCF!F40 -> -530.01972 | H9: =-$D$53*DCF!G40 -> -576.8327 | I9: =-$D$53*DCF!H40 -> -627.22313 | J9: =-$D$53*DCF!I40 -> -680.18475 | K9: =-$E$53*DCF!J40 -> -674.67946 | L9: =-$E$53*DCF!K40 -> -740.78001 | M9: =-$E$53*DCF!L40 -> -809.79614 | N9: =-$E$53*DCF!M40 -> -880.4081 | O9: =-$E$53*DCF!N40 -> -952.6284 | P9: =-$E$53*DCF!O40 -> -1026.7614 | Q9: =-$E$53*DCF!P40 -> -1105.2224 | R9: =-$E$53*DCF!Q40 -> -1192.7633 | ... AF9: =-$E$53*DCF!AE40 -> -3266.5845 | AG9: =SUM(D9:AF9) -> -42760.885
B10: 5b | C10: Amortization | D10: 0 | E10: 0 | F10: 0 | G10: =F38*0 -> 0 | H10: =G38*0 -> 0 | I10: =H38*0 -> 0 | J10: =I38*0 -> 0 | K10: =J38*0 -> 0 | L10: =K38*0 -> 0 | M10: =L38*0 -> 0 | N10: =M38*0 -> 0 | ... AF10: =AE38*0 -> 0
B11: 5c | C11: (Stock based compensation) | D11: =D20 -> -15 | E11: =E20 -> -17 | F11: =F20 -> -21 | G11: =-G6*$D$55 -> -25.092147 | H11: =-H6*$D$55 -> -27.009688 | I11: =-I6*$D$55 -> -28.387873 | J11: =-J6*$D$55 -> -29.797705 | K11: =-K6*$E$55 -> -30.911149 | L11: =-L6*$E$55 -> -32.274581 | M11: =-M6*$E$55 -> -33.020858 | N11: =-N6*$E$55 -> -33.772974 | O11: =-O6*$E$55 -> -34.667441 | P11: =-P6*$E$55 -> -36.691355 | Q11: =-Q6*$E$55 -> -40.937487 | R11: =-R6*$E$55 -> -45.174091 | ... AF11: =-AF6*$E$55 -> -98.473681
B12: 6 | C12: EBITDA | D12: =D8-D9-D10 -> 3410 | E12: =E8-E9-E10 -> 4456 | F12: =F8-F9-F10 -> 6438 | G12: =G8-G9-G10 -> 7161.5158 | H12: =H8-H9-H10 -> 7522.1812 | I12: =I8-I9-I10 -> 7521.421 | J12: =J8-J9-J10 -> 7491.0888 | K12: =K8-K9-K10 -> 7298.4971 | ... AF12: =AF8-AF9-AF10 -> 24368.088
B13: 7 | C13: (Net financing cost) | D13: ='Fin. Data'!D14 -> -63 | E13: ='Fin. Data'!C14 -> -46 | F13: ='Fin. Data'!B14 -> -129 | G13: =F43*($D$58)-F44*$D$57 -> -421.21292 | H13: =G43*($D$58)-G44*$D$57 -> -339.38236 | I13: =H43*($D$58)-H44*$D$57 -> -260.15799 | J13: =I43*($D$58)-I44*$D$57 -> -173.74363 | K13: =J43*($E$58)-J44*$E$57 -> -267.86409 | L13: =K43*($E$58)-K44*$E$57 -> -245.29273 | M13: =L43*($E$58)-L44*$E$57 -> -244.4421 | N13: =M43*($E$58)-M44*$E$57 -> -232.24963 | O13: =N43*($E$58)-N44*$E$57 -> -218.1526 | P13: =O43*($E$58)-O44*$E$57 -> -203.02009 | Q13: =P43*($E$58)-P44*$E$57 -> -198.22576 | R13: =Q43*($E$58)-Q44*$E$57 -> -215.97994 | ... AF13: =AE43*($E$58)-AE44*$E$57 -> 234.47973
B14: 8 | C14: Other income/(cost) | D14: ='Fin. Data'!D15 -> 0 | E14: ='Fin. Data'!C15 -> 0 | F14: ='Fin. Data'!B15 -> 0 | G14: =AVERAGE(D14:F14)*(1+G5) -> 0 | H14: =AVERAGE(E14:G14)*(1+H5) -> 0 | I14: =AVERAGE(F14:H14)*(1+I5) -> 0 | J14: =AVERAGE(G14:I14)*(1+J5) -> 0 | K14: =AVERAGE(H14:J14)*(1+K5) -> 0 | L14: =AVERAGE(I14:K14)*(1+L5) -> 0 | M14: =AVERAGE(J14:L14)*(1+M5) -> 0 | N14: =AVERAGE(K14:M14)*(1+N5) -> 0 | ... AF14: =AVERAGE(AC14:AE14)*(1+AF5) -> 0
B15: 9 | C15: Earnings before taxes | D15: =D8+D13+D14 -> 2378 | E15: =E8+E13+E14 -> 3849 | F15: =F8+F13+F14 -> 5718 | G15: =G8+G13+G14 -> 6210.2831 | H15: =H8+H13+H14 -> 6605.9661 | I15: =I8+I13+I14 -> 6634.0398 | J15: =J8+J13+J14 -> 6637.1604 | K15: =K8+K13+K14 -> 6355.9535 | ... AF15: =AF8+AF13+AF14 -> 21335.983
B16: 10 | C16: (Income tax) | D16: ='Fin. Data'!D21 -> -527 | E16: ='Fin. Data'!C21 -> -837 | F16: ='Fin. Data'!B21 -> -1117 | G16: =-(1*$D$56)*G15 -> -1304.1595 | H16: =-(1*$D$56)*H15 -> -1387.2529 | I16: =-(1*$D$56)*I15 -> -1393.1484 | J16: =-(1*$D$56)*J15 -> -1393.8037 | K16: =-(1*$E$56)*K15 -> -1716.1074 | L16: =-(1*$E$56)*L15 -> -1801.086 | M16: =-(1*$E$56)*M15 -> -1844.4931 | N16: =-(1*$E$56)*N15 -> -1891.3004 | O16: =-(1*$E$56)*O15 -> -1946.8579 | P16: =-(1*$E$56)*P15 -> -2068.0415 | Q16: =-(1*$E$56)*Q15 -> -2315.0051 | R16: =-(1*$E$56)*R15 -> -2555.3292 | ... AF16: =-(1*$E$56)*AF15 -> -5760.7153
B17: 11 | C17: Net income | D17: ='Fin. Data'!D23 -> 1852 | E17: ='Fin. Data'!C23 -> 3012 | F17: ='Fin. Data'!B23 -> 4601 | G17: =G16+G15 -> 4906.1237 | H17: =H16+H15 -> 5218.7132 | I17: =I16+I15 -> 5240.8915 | J17: =J16+J15 -> 5243.3567 | K17: =K16+K15 -> 4639.8461 | L17: =L16+L15 -> 4869.603 | M17: =M16+M15 -> 4986.9629 | N17: =N16+N15 -> 5113.5159 | ... AF17: =AF16+AF15 -> 15575.267
A19: CASH FLOW STATEMENT | B19: 12 | C19: Operating cash flows before WK | D19: =Inputs!D59-Inputs!D62 -> 2538.2 | E19: =Inputs!C59-Inputs!C62 -> 3574.1 | F19: =Inputs!B59-Inputs!B62 -> 5271.5 | G19: =G17-G10-G9-G11 -> 5461.2355 | H19: =H17-H10-H9-H11 -> 5822.5556 | I19: =I17-I10-I9-I11 -> 5896.5025 | J19: =J17-J10-J9-J11 -> 5953.3392 | K19: =K17-K10-K9-K11 -> 5345.4367 | L19: =L17-L10-L9-L11 -> 5642.6576 | M19: =M17-M10-M9-M11 -> 5829.7799 | N19: =N17-N10-N9-N11 -> 6027.697 | ... AF19: =AF17-AF10-AF9-AF11 -> 18940.326
B20: 13 | C20: (Stock-based compensation) | D20: =-Inputs!D103 -> -15 | E20: =-Inputs!C103 -> -17 | F20: =-Inputs!B103 -> -21 | G20: =G11 -> -25.092147 | H20: =H11 -> -27.009688 | I20: =I11 -> -28.387873 | J20: =J11 -> -29.797705 | K20: =K11 -> -30.911149 | L20: =L11 -> -32.274581 | M20: =M11 -> -33.020858 | N20: =N11 -> -33.772974 | ... AF20: =AF11 -> -98.473681
B21: 14 | C21: (Working Capital Flows) | D21: =Inputs!D62 -> -351.5 | E21: =Inputs!C62 -> -547.1 | F21: =Inputs!B62 -> -1081.5 | G21: =-$D$60*(G6-F6) -> -71.892464 | H21: =-$D$60*(H6-G6) -> -273.93445 | I21: =-$D$60*(I6-H6) -> -196.88357 | J21: =-$D$60*(J6-I6) -> -201.40454 | K21: =-$E$60*(K6-J6) -> -127.2507 | L21: =-$E$60*(L6-K6) -> -155.82086 | M21: =-$E$60*(M6-L6) -> -85.288747 | N21: =-$E$60*(N6-M6) -> -85.956178 | O21: =-$E$60*(O6-N6) -> -102.2248 | P21: =-$E$60*(P6-O6) -> -231.30436 | Q21: =-$E$60*(Q6-P6) -> -485.2723 | R21: =-$E$60*(R6-Q6) -> -484.18324 | ... AF21: =-$E$60*(AF6-AE6) -> -220.66931
B22: 15 | C22: -Total Operating Cash Flow | D22: =D19+D20+D21 -> 2171.7 | E22: =E19+E20+E21 -> 3010 | F22: =F19+F20+F21 -> 4169 | G22: =G19+G20+G21 -> 5364.2509 | H22: =H19+H20+H21 -> 5521.6115 | I22: =I19+I20+I21 -> 5671.231 | J22: =J19+J20+J21 -> 5722.1369 | K22: =K19+K20+K21 -> 5187.2748 | ... AF22: =AF19+AF20+AF21 -> 18621.183
B23: 16 | C23: (CAPEX) | D23: ='Fin. Data'!D32 -> -559.1 | E23: ='Fin. Data'!C32 -> -525 | F23: ='Fin. Data'!B32 -> -695 | G23: =-G6*$D$62 -> -716.91849 | H23: =-H6*$D$62 -> -771.70538 | I23: =-I6*$D$62 -> -811.0821 | J23: =-J6*$D$62 -> -851.36301 | K23: =-K6*$E$62 -> -1103.9696 | L23: =-L6*$E$62 -> -1152.6636 | M23: =-M6*$E$62 -> -1179.3164 | N23: =-N6*$E$62 -> -1206.1777 | O23: =-O6*$E$62 -> -1238.1229 | P23: =-P6*$E$62 -> -1310.4055 | Q23: =-Q6*$E$62 -> -1462.0531 | R23: =-R6*$E$62 -> -1613.3604 | ... AF23: =-AF6*$E$62 -> -3516.9172 | AG23: =SUM(D23:AF23) -> -51735.442
B24: 17 | C24: Aquisitions | D24: ='Fin. Data'!D33 -> -1249.8 | E24: ='Fin. Data'!C33 -> -1035.8 | F24: ='Fin. Data'!B33 -> -731.1 | G24: =G6*$D$63 -> 0 | H24: =H6*$D$63 -> 0 | I24: =I6*$D$63 -> 0 | J24: =J6*$D$63 -> 0 | K24: =-K6*$E$63 -> -441.58784 | L24: =-L6*$E$63 -> -461.06545 | M24: =-M6*$E$63 -> -471.72654 | N24: =-N6*$E$63 -> -482.47106 | O24: =-O6*$E$63 -> -495.24916 | P24: =-P6*$E$63 -> -524.16221 | Q24: =-Q6*$E$63 -> -584.82125 | R24: =-R6*$E$63 -> -645.34415 | ... AF24: =-AF6*$E$63 -> -1406.7669 | AH24: =AG9-AG23 -> 8974.5569
B25: 18 | C25: (Other investing flows) | D25: =Inputs!D67 -> 446.2 | E25: =Inputs!C67 -> -472.2 | F25: =Inputs!B67 -> -1444.9 | G25: =(1+G5)*AVERAGE(D25:F25) -> -500.3347 | H25: =(1+H5)*AVERAGE(E25:G25) -> -867.39166 | I25: =(1+I5)*AVERAGE(F25:H25) -> -985.38075 | J25: =(1+J5)*AVERAGE(G25:I25) -> -823.32329 | K25: =(1+K5)*AVERAGE(H25:J25) -> -925.36424 | L25: =(1+L5)*AVERAGE(I25:K25) -> -951.55429 | M25: =(1+M5)*AVERAGE(J25:L25) -> -920.89293 | N25: =(1+N5)*AVERAGE(K25:M25) -> -953.84575 | ... AF25: =(1+AF5)*AVERAGE(AC25:AE25) -> -1616.7997
B26: 19 | C26: -Total Investing Flows | D26: =D23+D24+D25 -> -1362.7 | E26: =E23+E24+E25 -> -2033 | F26: =F23+F24+F25 -> -2871 | G26: =G23+G24+G25 -> -1217.2532 | H26: =H23+H24+H25 -> -1639.097 | I26: =I23+I24+I25 -> -1796.4628 | J26: =J23+J24+J25 -> -1674.6863 | K26: =K23+K24+K25 -> -2470.9217 | ... AF26: =AF23+AF24+AF25 -> -6540.4838
B27: 20 | C27: (Flows related to leases) | D27: =Inputs!D71+Inputs!D72 -> 0 | E27: =Inputs!C71+Inputs!C72 -> 0 | F27: =Inputs!B71+Inputs!B72 -> 0 | G27: =-G6*$D$66 -> 0 | H27: =-H6*$D$66 -> 0 | I27: =-I6*$D$66 -> 0 | J27: =-J6*$D$66 -> 0 | K27: =-K6*$E$66 -> -82.791687 | L27: =-L6*$E$66 -> -86.443472 | M27: =-M6*$E$66 -> -88.442281 | N27: =-N6*$E$66 -> -90.456733 | O27: =-O6*$E$66 -> -92.852452 | P27: =-P6*$E$66 -> -98.273253 | Q27: =-Q6*$E$66 -> -109.64599 | R27: =-R6*$E$66 -> -120.99321 | ... AF27: =-AF6*$E$66 -> -263.74957
B28: 21 | C28: Flows related to debt | D28: =+SUM(Inputs!D69:D70) -> -210.9 | E28: =+SUM(Inputs!C69:C70) -> 1276 | F28: =+SUM(Inputs!B69:B70) -> 2572.8 | G28: =G44-F44 -> 1812.7557 | H28: =H44-G44 -> 539.70127 | I28: =I44-H44 -> -266.0097 | J28: =J44-I44 -> -324.90479 | K28: =K44-J44 -> -659.72878 | L28: =L44-K44 -> 496.56249 | M28: =M44-L44 -> 213.60918 | N28: =N44-M44 -> 208.48353 | ... AF28: =AF44-AE44 -> 353.49869
B29: 22 | C29: (Repurchases)/Issuance of stock | D29: ='Fin. Data'!D28 -> -1.5 | E29: ='Fin. Data'!C28 -> -2.1 | F29: ='Fin. Data'!B28 -> -3.5 | G29: =-G17*$D$65 -> 0 | H29: =-H17*$D$65 -> 0 | I29: =-I17*$D$65 -> 0 | J29: =-J17*$D$65 -> 0 | K29: =-K17*$E$65 -> -75.026096 | L29: =-L17*$E$65 -> -78.741255 | M29: =-M17*$E$65 -> -80.638959 | N29: =-N17*$E$65 -> -82.685316 | O29: =-O17*$E$65 -> -85.114221 | P29: =-P17*$E$65 -> -90.412219 | Q29: =-Q17*$E$65 -> -101.20916 | R29: =-R17*$E$65 -> -111.71584 | ... AF29: =-AF17*$E$65 -> -251.85135
B30: 23 | C30: (Dividends) | D30: ='Fin. Data'!D27 -> -708 | E30: ='Fin. Data'!C27 -> -1004.7 | F30: ='Fin. Data'!B27 -> -1518.6 | G30: =-$D$64*G17 -> -1710.4609 | H30: =-$D$64*H17 -> -1819.4415 | I30: =-$D$64*I17 -> -1827.1736 | J30: =-$D$64*J17 -> -1828.0331 | K30: =-$E$64*K17 -> -2299.3929 | L30: =-$E$64*L17 -> -2413.2548 | M30: =-$E$64*M17 -> -2471.4154 | N30: =-$E$64*N17 -> -2534.132 | O30: =-$E$64*O17 -> -2608.5728 | P30: =-$E$64*P17 -> -2770.9454 | Q30: =-$E$64*Q17 -> -3101.8491 | R30: =-$E$64*R17 -> -3423.8567 | ... AF30: =-$E$64*AF17 -> -7718.7172
B31: 24 | C31: Other financing flows | D31: =Inputs!D75 -> 37.5 | E31: =Inputs!C75 -> 35.7 | F31: =Inputs!B75 -> 51.5 | G31: =(1+G5)*AVERAGE(D31:F31) -> 42.417388 | H31: =(1+H5)*AVERAGE(E31:G31) -> 46.507582 | I31: =(1+I5)*AVERAGE(F31:H31) -> 49.196745 | J31: =(1+J5)*AVERAGE(G31:I31) -> 48.327093 | K31: =(1+K5)*AVERAGE(H31:J31) -> 49.804469 | L31: =(1+L5)*AVERAGE(I31:K31) -> 51.27556 | M31: =(1+M5)*AVERAGE(J31:L31) -> 50.953941 | N31: =(1+N5)*AVERAGE(K31:M31) -> 51.832283 | ... AF31: =(1+AF5)*AVERAGE(AC31:AE31) -> 88.255037
B32: 25 | C32: -Total Financing flows | D32: =D27+D28+D29+D30+D31 -> -882.9 | E32: =E27+E28+E29+E30+E31 -> 304.9 | F32: =F27+F28+F29+F30+F31 -> 1102.2 | G32: =G27+G28+G29+G30+G31 -> 144.71221 | H32: =H27+H28+H29+H30+H31 -> -1233.2326 | I32: =I27+I28+I29+I30+I31 -> -2043.9866 | J32: =J27+J28+J29+J30+J31 -> -2104.6108 | K32: =K27+K28+K29+K30+K31 -> -3067.135 | ... AF32: =AF27+AF28+AF29+AF30+AF31 -> -7792.5644
A34: SUMMARY | B34: 26 | C34: Cash before shareholder returns | D34: =D22+D26+D27+D28+D31 -> 635.6 | E34: =E22+E26+E27+E28+E31 -> 2288.7 | F34: =F22+F26+F27+F28+F31 -> 3922.3 | G34: =G22+G26+G27+G28+G31 -> 6002.1708 | H34: =H22+H26+H27+H28+H31 -> 4468.7233 | I34: =I22+I26+I27+I28+I31 -> 3657.9552 | J34: =J22+J26+J27+J28+J31 -> 3770.873 | K34: =K22+K26+K27+K28+K31 -> 2023.6371 | ... AF34: =AF22+AF26+AF27+AF28+AF31 -> 12258.703
B35: 27 | C35: Returns to shareholders | D35: =-1*(D29+D30) -> 709.5 | E35: =-1*(E29+E30) -> 1006.8 | F35: =-1*(F29+F30) -> 1522.1 | G35: =-1*(G29+G30) -> 1710.4609 | H35: =-1*(H29+H30) -> 1819.4415 | I35: =-1*(I29+I30) -> 1827.1736 | J35: =-1*(J29+J30) -> 1828.0331 | K35: =-1*(K29+K30) -> 2374.419 | ... AF35: =-1*(AF29+AF30) -> 7970.5685
B36: 28 | C36: Excess cash acumulation | D36: =D34-D35 -> -73.9 | E36: =E34-E35 -> 1281.9 | F36: =F34-F35 -> 2400.2 | G36: =G34-G35 -> 4291.71 | H36: =H34-H35 -> 2649.2818 | I36: =I34-I35 -> 1830.7816 | J36: =J34-J35 -> 1942.8398 | K36: =K34-K35 -> -350.78186 | ... AF36: =AF34-AF35 -> 4288.1344
A38: BALANCE SHEET | B38: 29 | C38: Intangible assets (Just Goodwill) | D38: =Inputs!D91 -> 110.6 | E38: =Inputs!C91 -> 104.1 | F38: =Inputs!B91 -> 107.4 | G38: =+F38+(-G10) -> 107.4 | H38: =+G38+(-H10) -> 107.4 | I38: =+H38+(-I10) -> 107.4 | J38: =+I38+(-J10) -> 107.4 | K38: =+J38+(-K10) -> 107.4 | L38: =+K38+(-L10) -> 107.4 | M38: =+L38+(-M10) -> 107.4 | N38: =+M38+(-N10) -> 107.4 | ... AF38: =+AE38+(-AF10) -> 107.4 | AG38: =SUM(G38:AF38) -> 2792.4
B39: 30 | C39: Accumulated amortization | D39: 0 | E39: 0 | F39: 0 | G39: =F39-G10 -> 0 | H39: =G39-H10 -> 0 | I39: =H39-I10 -> 0 | J39: =I39-J10 -> 0 | K39: =J39-K10 -> 0 | L39: =K39-L10 -> 0 | M39: =L39-M10 -> 0 | N39: =M39-N10 -> 0 | ... AF39: =AE39-AF10 -> 0 | AG39: =SUM(G39:AF39) -> 0
B40: 31 | C40: Property Plant and Equipment | D40: =Assumptions!E392 -> 7302 | E40: =Assumptions!D392 -> 7436 | F40: =Assumptions!C392 -> 8117 | G40: =F40+(-G23) -> 8833.9185 | H40: =G40+(-H23) -> 9605.6239 | I40: =H40+(-I23) -> 10416.706 | J40: =I40+(-J23) -> 11268.069 | K40: =J40+(-K23) -> 12372.039 | L40: =K40+(-L23) -> 13524.702 | M40: =L40+(-M23) -> 14704.019 | N40: =M40+(-N23) -> 15910.196 | ... AF40: =AE40+(-AF23) -> 58073.342 | AG40: =SUM(G40:AF40) -> 725349.77
B41: 32 | C41: Accumulated depreciation | D41: =-Inputs!D113 -> 3866.2 | E41: =-Inputs!C113 -> 3920.8 | F41: =-Inputs!B113 -> 4263.4 | G41: =F41-G9 -> 4793.4197 | H41: =G41-H9 -> 5370.2524 | I41: =H41-I9 -> 5997.4755 | J41: =I41-J9 -> 6677.6603 | K41: =J41-K9 -> 7352.3398 | L41: =K41-L9 -> 8093.1198 | M41: =L41-M9 -> 8902.9159 | N41: =M41-N9 -> 9783.324 | ... AF41: =AE41-AF9 -> 44903.285 | AG41: =SUM(G41:AF41) -> 500327.66
A43: CASH & DEBT & DISCOUNTING | B43: 33 | C43: Ending cash balance | D43: ='Fin. Data'!D39 -> 3428 | E43: =E36+D43 -> 4709.9 | F43: =F36+E43 -> 7110.1 | G43: =G36+F43 -> 11401.81 | H43: =H36+G43 -> 14051.092 | I43: =I36+H43 -> 15881.873 | J43: =J36+I43 -> 17824.713 | K43: =K36+J43 -> 17473.931 | L43: =L36+K43 -> 18332.609 | ... AF43: =AF36+AE43 -> 72633.4
B44: 34 | C44: Total Debt | D44: ='Fin. Data'!D58 -> 10433 | E44: ='Fin. Data'!C58 -> 11475 | F44: ='Fin. Data'!B58 -> 14238 | G44: =G67*G12 -> 16050.756 | H44: =H67*H12 -> 16590.457 | I44: =I67*I12 -> 16324.447 | J44: =J67*J12 -> 15999.542 | K44: =K67*K12 -> 15339.814 | L44: =L67*L12 -> 15836.376 | M44: =M67*M12 -> 16049.985 | N44: =N67*N12 -> 16258.469 | ... AF44: =AF67*AF12 -> 36552.131
B45: 35 | C45: Discount factor | F45: =1/((1+$F$50)^G50) -> 1 | G45: =1/((1+$F$50)^G49) -> 0.91533181 | H45: =1/((1+$F$50)^H49) -> 0.83783232 | I45: =1/((1+$F$50)^I49) -> 0.76689457 | J45: =1/((1+$F$50)^J49) -> 0.70196299 | K45: =1/((1+$F$50)^K49) -> 0.64252906 | L45: =1/((1+$F$50)^L49) -> 0.58812728 | M45: =1/((1+$F$50)^M49) -> 0.53833161 | N45: =1/((1+$F$50)^N49) -> 0.49275204 | ... AF45: =1/((1+$F$50)^AF49) -> 0.10024031
B46: 36 | C46: DF + 0.1% | E46: +0.1% | F46: =1/((1+$F$50+0.001)^G50) -> 1 | G46: =1/((1+$F$50+0.001)^G49) -> 0.91449474 | H46: =1/((1+$F$50+0.001)^H49) -> 0.83630063 | I46: =1/((1+$F$50+0.001)^I49) -> 0.76479253 | J46: =1/((1+$F$50+0.001)^J49) -> 0.69939875 | K46: =1/((1+$F$50+0.001)^K49) -> 0.63959648 | L46: =1/((1+$F$50+0.001)^L49) -> 0.58490762 | M46: =1/((1+$F$50+0.001)^M49) -> 0.53489494 | N46: =1/((1+$F$50+0.001)^N49) -> 0.48915861 | ... AF46: =1/((1+$F$50+0.001)^AF49) -> 0.097883959
B47: 37 | C47: DF+0.5% | E47: +0.5% | F47: =1/((1+$F$50+0.005)^G50) -> 1 | G47: =1/((1+$F$50+0.005)^G49) -> 0.91116173 | H47: =1/((1+$F$50+0.005)^H49) -> 0.8302157 | I47: =1/((1+$F$50+0.005)^I49) -> 0.75646077 | J47: =1/((1+$F$50+0.005)^J49) -> 0.68925811 | K47: =1/((1+$F$50+0.005)^K49) -> 0.62802561 | L47: =1/((1+$F$50+0.005)^L49) -> 0.5722329 | M47: =1/((1+$F$50+0.005)^M49) -> 0.52139672 | N47: =1/((1+$F$50+0.005)^N49) -> 0.47507674 | ... AF47: =1/((1+$F$50+0.005)^AF49) -> 0.089018905
A49: Discount Rate | C49: Risk free rate | D49: Equity premium | E49: Firm premium | F49: Total | G49: 1 | H49: 2 | I49: 3 | J49: 4 | K49: 5 | L49: 6 | M49: 7 | N49: 8 | O49: 9 | P49: 10 | Q49: 11 | R49: 12 | S49: 13 | T49: 14 | U49: 15 | V49: 16 | W49: 17 | X49: 18 | Y49: 19 | Z49: 20 | AA49: 21 | AB49: 22 | AC49: 23 | AD49: 24 | AE49: 25 | AF49: 26
C50: 0.04 | D50: 0.045 | E50: 0.0075 | F50: =E50+D50+C50 -> 0.0925
A52: Modelling factors | D52: Short Term | E52: Long Term | F52: Reference (line)
C53: Depreciation factor | D53: =Assumptions!S16 -> 0.06529749 | E53: =Assumptions!T16 -> 0.05987534 | F53: % PPE
C54: Amortization factor | D54: =Assumptions!S17 -> 0 | E54: =Assumptions!T17 -> 0 | F54: % IA
C55: Stock-based comp | D55: =Assumptions!S18 -> 0.0007 | E55: =Assumptions!T18 -> 0.0007 | F55: % Revenue
C56: Tax Rate | D56: =Assumptions!S19 -> 0.21 | E56: =Assumptions!T19 -> 0.27 | F56: % Earnings before tax
C57: Interest Rate on debt | D57: =Assumptions!S20 -> 0.049558711 | E57: =Assumptions!T20 -> 0.050164277 | F57: % Debt (l29)
C58: Interest Rate on cash | D58: =C50 -> 0.04 | E58: 0.03 | F58: % of Cash (l28)
C59: PPE+ROA | D59: =Assumptions!S22 -> 0 | E59: =Assumptions!T22 -> 0 | F59: Growing with capex
C60: Working capital flows | D60: =-Assumptions!S23 -> 0.1 | E60: =-Assumptions!T23 -> 0.08 | F60: % of Change Revenues (l2)
C61: Intangible Assets | D61: =Assumptions!S24 -> 0 | E61: =Assumptions!T24 -> 0 | F61: Growing with amortization
C62: Capex | D62: =Assumptions!S25 -> 0.02 | E62: =Assumptions!T25 -> 0.025 | F62: % Revenue
C63: Acquisition factor | D63: =-Assumptions!S26 -> 0 | E63: =Assumptions!T26 -> 0.01 | F63: % Revenue
C64: Dividends | D64: =Assumptions!S27 -> 0.34863795 | E64: =Assumptions!T27 -> 0.49557526 | F64: % Net Income (11)
C65: Repurchases | D65: =Assumptions!S28 -> 0 | E65: =Assumptions!T28 -> 0.016169954 | F65: % Net Income (11)
C66: Leases | D66: =Assumptions!S29 -> 0 | E66: =Assumptions!T29 -> 0.0018748634 | F66: % Revenue
C67: Total Debt | F67: % EBITDA | G67: 2.2412512 | H67: 2.2055381 | I67: 2.170394 | J67: 2.13581 | K67: 2.1017771 | L67: 2.0682864 | M67: 2.0353294 | N67: 2.0028975 | O67: 1.9709825 | P67: 1.939576 | Q67: 1.9086699 | R67: 1.8782563 | S67: 1.8483273 | T67: 1.8188752 | U67: 1.7898925 | V67: 1.7613715 | W67: 1.733305 | X67: 1.7056858 | Y67: 1.6785066 | Z67: 1.6517605 | AA67: 1.6254406 | AB67: 1.5995401 | AC67: 1.5740523 | AD67: 1.5489707 | AE67: 1.5242887 | AF67: 1.5
D69: $ millions
A70: Valuation | C70: Value of flows | D70: =SUMPRODUCT(G35:AF35,G45:AF45)+((AF43-AF44)*AF45) -> 34430.918 | E70: =D70/D72 -> 0.67012157
C71: Value of perpetuity | D71: =(AF34/(F50-AF5))*AF45 -> 16949.189 | E71: =D71/D72 -> 0.32987843
C72: Total Value | D72: =D70+D71 -> 51380.108
C73: Actual share price | D73: =OP!C19 -> 105.92
C74: Total value vs Mkt Cap | D74: =D75/D73-1 -> -0.07428589
C75: Estimated NPV per share | D75: =D72*1000000/OP!C20 -> 98.051639
A77: Sensibility | C77: Sensitivity +0.1% | D77: =(SUMPRODUCT(G35:AF35,G45:AF45)+((AF43-AF44)*AF45)+(AF34/(F50+0.001-AF5))*AF45)*1000000/OP!C20 -> 97.611569 | E77: =D77/D75-1 -> -0.0044881419
C78: Sensitivity +0.5% | D78: =(SUMPRODUCT(G35:AF35,G45:AF45)+((AF43-AF44)*AF45)+(AF34/(F50+0.005-AF5))*AF45)*1000000/OP!C20 -> 95.964857 | E78: =D78/D75-1 -> -0.021282479
A80: Notes | C80: Price where it'd be a "BUY" | D80: =IF(D74<15%,D75/1.15,D73) -> 85.262294

Sheet Assumptions
B2: Assumptions
B4: Prospects:
B5: Links:
C7: =OP!J19 -> 2023 | D7: =C7-1 -> 2022 | E7: =D7-1 -> 2021 | F7: =E7-1 -> 2020 | G7: =F7-1 -> 2019 | H7: =G7-1 -> 2018 | I7: =H7-1 -> 2017 | J7: =I7-1 -> 2016 | K7: =J7-1 -> 2015 | L7: =K7-1 -> 2014 | N7: Average (3y) | O7: Average (5y) | P7: Average (10y) | Q7: Average (w/o covid) | S7: Short Term Forecast | T7: Long Term Forecast
B8: Revenue growth | C8: =(Inputs!B6-Inputs!C6)/Inputs!C6 -> 0.21884108 | D8: =(Inputs!C6-Inputs!D6)/Inputs!D6 -> 0.22523595 | E8: =(Inputs!D6-Inputs!E6)/Inputs!E6 -> 0.25591329 | F8: =(Inputs!E6-Inputs!F6)/Inputs!F6 -> -0.26839844 | G8: =(Inputs!F6-Inputs!G6)/Inputs!G6 -> 0.089547157 | H8: =(Inputs!G6-Inputs!H6)/Inputs!H6 -> 0.20764803 | I8: =(Inputs!H6-Inputs!I6)/Inputs!I6 -> 0.14225327 | J8: =(Inputs!I6-Inputs!J6)/Inputs!J6 -> -0.1089197 | ... L8: =(Inputs!K6-Inputs!L6)/Inputs!L6 -> 2.8896396 | N8: =AVERAGE(C8:E8) -> 0.23333011 | O8: =AVERAGE(C8:G8) -> 0.10422781 | P8: =AVERAGE(C8:L8) -> 0.36579718 | Q8: =AVERAGE(C8,F8:L8) -> 0.39710282 | X8: 0.16
B9: Operating Margin | C9: =Inputs!B8/Inputs!B6 -> 0.16645316 | D9: =Inputs!C8/Inputs!C6 -> 0.1351492 | E9: =Inputs!D8/Inputs!D6 -> 0.10377519 | F9: =Inputs!E8/Inputs!E6 -> 0.093971915 | G9: =Inputs!F8/Inputs!F6 -> 0.12523438 | H9: =Inputs!G8/Inputs!G6 -> 0.12244637 | I9: =Inputs!H8/Inputs!H6 -> 0.11790707 | J9: =Inputs!I8/Inputs!I6 -> 0.072975988 | ... L9: =Inputs!K8/Inputs!K6 -> 0.11233353 | N9: =AVERAGE(C9:E9) -> 0.13512585 | O9: =AVERAGE(C9:G9) -> 0.12491677 | P9: =AVERAGE(C9:L9) -> 0.11780522 | Q9: =AVERAGE(C9,F9:L9) -> 0.11739097 | S9: 0.15 | T9: 0.12
Q10: =AVERAGE(C10,F10:L10) -> #DIV/0!
B12: Modelling Factors
C14: Last 10 Years
C15: =OP!J19 -> 2023 | D15: =D7 -> 2022 | E15: =E7 -> 2021 | F15: =F7 -> 2020 | G15: =G7 -> 2019 | H15: =H7 -> 2018 | I15: =I7 -> 2017 | J15: =J7 -> 2016 | K15: =K7 -> 2015 | L15: =L7 -> 2014 | N15: Average (3y) | O15: Average (5y) | P15: Average (10y) | Q15: Average (w/o covid) | S15: Short Term Forecast | T15: Long Term Forecast
B16: Depreciation factor | C16: =Inputs!B129/Inputs!B95 -> 0.050686106 | D16: =Inputs!C129/Inputs!C95 -> 0.048109082 | E16: =Inputs!D129/Inputs!D95 -> 0.080830831 | F16: =Inputs!E129/Inputs!E95 -> 0.082697514 | G16: =Inputs!F129/Inputs!F95 -> 0.069463788 | H16: =Inputs!G129/Inputs!G95 -> 0.067195865 | I16: =Inputs!H129/Inputs!H95 -> 0.064447592 | J16: =Inputs!I129/Inputs!I95 -> 0.064037919 | ... L16: =Inputs!K129/Inputs!K95 -> 0.063292499 | N16: =AVERAGE(C16:E16) -> 0.05987534 | O16: =AVERAGE(C16:F16) -> 0.065580883 | P16: =AVERAGE(C16:L16) -> 0.06529749 | Q16: =AVERAGE(C16,F16:L16) -> 0.065504373 | S16: =P16 -> 0.06529749 | T16: =N16 -> 0.05987534
B17: Amortization factor | C17: - - | D17: - - | E17: - - | F17: - - | G17: - - | H17: - - | I17: - - | J17: - - | K17: - - | L17: - - | N17: =AVERAGE(C17:E17) -> #DIV/0! | O17: - - | P17: =AVERAGE(C17:L17) -> #DIV/0! | Q17: =AVERAGE(C17,F17:L17) -> #DIV/0!
B18: Stock-based comp | C18: =-Inputs!B103/'Fin. Data'!B5 -> -0.00059783073 | D18: =-Inputs!C103/'Fin. Data'!C5 -> -0.00058986815 | E18: =-Inputs!D103/'Fin. Data'!D5 -> -0.00063770088 | F18: =-Inputs!E103/'Fin. Data'!E5 -> -0.00069411074 | G18: =-Inputs!F103/'Fin. Data'!F5 -> -0.0005859375 | H18: =-Inputs!G103/'Fin. Data'!G5 -> -0.00055328567 | I18: =-Inputs!H103/'Fin. Data'!H5 -> -0.00066817434 | J18: =-Inputs!I103/'Fin. Data'!I5 -> -0.00076322433 | ... L18: =-Inputs!K103/'Fin. Data'!K5 -> -0.00084223825 | N18: =AVERAGE(C18:E18) -> -0.00060846658 | O18: =AVERAGE(C18:G18) -> -0.0006210896 | P18: =AVERAGE(C18:L18) -> -0.00067170946 | Q18: =AVERAGE(C18,F18:L18) -> -0.0006861907 | S18: 0.0007 | T18: 0.0007
B19: Tax Rate | C19: =-'Fin. Data'!B21/('Fin. Data'!B11+'Fin. Data'!B14+'Fin. Data'!B15) -> 0.19534802 | D19: =-'Fin. Data'!C21/('Fin. Data'!C11+'Fin. Data'!C14+'Fin. Data'!C15) -> 0.21745908 | E19: =-'Fin. Data'!D21/('Fin. Data'!D11+'Fin. Data'!D14+'Fin. Data'!D15) -> 0.2216148 | F19: =-'Fin. Data'!E21/('Fin. Data'!E11+'Fin. Data'!E14+'Fin. Data'!E15) -> 0.21712907 | G19: =-'Fin. Data'!F21/('Fin. Data'!F11+'Fin. Data'!F14+'Fin. Data'!F15) -> 0.22935484 | H19: =-'Fin. Data'!G21/('Fin. Data'!G11+'Fin. Data'!G14+'Fin. Data'!G15) -> 0.21893912 | I19: =-'Fin. Data'!H21/('Fin. Data'!H11+'Fin. Data'!H14+'Fin. Data'!H15) -> 0.30896552 | J19: =-'Fin. Data'!I21/('Fin. Data'!I11+'Fin. Data'!I14+'Fin. Data'!I15) -> 0.53798587 | ... L19: =-'Fin. Data'!K21/('Fin. Data'!K11+'Fin. Data'!K14+'Fin. Data'!K15) -> 0.32639921 | N19: =AVERAGE(C19:E19) -> 0.21147397 | O19: =AVERAGE(C19:G19) -> 0.21618116 | P19: =AVERAGE(C19:L19) -> 0.27868455 | Q19: =AVERAGE(C19,F19:L19) -> 0.29347145 | S19: 0.21 | T19: 0.27
B20: Interest Rate on debt | C20: =0/'Fin. Data'!B58 -> 0 | D20: - - | E20: - - | F20: - - | G20: - - | H20: - - | I20: - - | J20: - - | K20: - - | L20: - - | N20: =AVERAGE(C20:E20) -> 0 | O20: - - | P20: =AVERAGE(C20:L20) -> 0 | Q20: =AVERAGE(C20,F20:L20) -> 0 | S20: =+C346+C349 -> 0.049558711 | T20: =+C346+C352 -> 0.050164277
B21: Interest Rate on cash | C21: =0/Inputs!B28 -> 0 | D21: - - | E21: - - | F21: - - | G21: - - | H21: - - | I21: - - | J21: - - | K21: - - | L21: - - | N21: =AVERAGE(C21:E21) -> 0 | O21: - - | P21: =AVERAGE(C21:L21) -> 0 | Q21: =AVERAGE(C21,F21:L21) -> 0 | S21: 0.04 | T21: 0.04
B22: PPE+ROA | C22: =Inputs!B33/Inputs!C33-1 -> 0.096267638 | D22: =Inputs!C33/Inputs!D33-1 -> 0.023109611 | E22: =Inputs!D33/Inputs!E33-1 -> 0.03753586 | F22: =Inputs!E33/Inputs!F33-1 -> 0.13326033 | G22: =Inputs!F33/Inputs!G33-1 -> 0.17793365 | H22: =Inputs!G33/Inputs!H33-1 -> 0.0066958851 | I22: =Inputs!H33/Inputs!I33-1 -> 0.09040223 | J22: =Inputs!I33/Inputs!J33-1 -> 0.038461538 | ... L22: =Inputs!K33/Inputs!L33-1 -> #VALUE! | N22: =AVERAGE(C22:E22) -> 0.052304369 | O22: =AVERAGE(C22:G22) -> 0.093621416 | P22: =AVERAGE(C22:L22) -> #VALUE! | Q22: =AVERAGE(C22,F22:L22) -> #VALUE!
B23: Working capital flows | C23: =Inputs!B62/(Inputs!B6-Inputs!C6) -> -0.17147614 | D23: =Inputs!C62/(Inputs!C6-Inputs!D6) -> -0.10326538 | E23: =Inputs!D62/(Inputs!D6-Inputs!E6) -> -0.073336115 | F23: =Inputs!E62/(Inputs!E6-Inputs!F6) -> -0.11293844 | G23: =Inputs!F62/(Inputs!F6-Inputs!G6) -> -0.32414449 | H23: =Inputs!G62/(Inputs!G6-Inputs!H6) -> -0.058688119 | I23: =Inputs!H62/(Inputs!H6-Inputs!I6) -> 0.046099876 | J23: =Inputs!I62/(Inputs!I6-Inputs!J6) -> -0.42848223 | ... L23: =Inputs!K62/(Inputs!K6-Inputs!L6) -> -0.002097357 | N23: =AVERAGE(C23:E23) -> -0.11602588 | O23: =AVERAGE(C23:G23) -> -0.15703211 | P23: =AVERAGE(C23:L23) -> -0.034697246 | Q23: =AVERAGE(C23,F23:L23) -> -0.02129637 | S23: -0.1 | T23: -0.08
B24: Intangible Assets | C24: - - | D24: - - | E24: - - | F24: - - | G24: - - | H24: - - | I24: - - | J24: - - | K24: - - | L24: - - | N24: =AVERAGE(C24:E24) -> #DIV/0! | O24: - - | P24: =AVERAGE(C24:L24) -> #DIV/0! | Q24: =AVERAGE(C24,F24:L24) -> #DIV/0!
B25: CAPEX | C25: =-'Fin. Data'!B32/'Fin. Data'!B5 -> 0.01978535 | D25: =-'Fin. Data'!C32/'Fin. Data'!C5 -> 0.018216516 | E25: =-'Fin. Data'!D32/'Fin. Data'!D5 -> 0.023769237 | F25: =-'Fin. Data'!E32/'Fin. Data'!E5 -> 0.029387581 | G25: =-'Fin. Data'!F32/'Fin. Data'!F5 -> 0.022421875 | H25: =-'Fin. Data'!G32/'Fin. Data'!G5 -> 0.019475655 | I25: =-'Fin. Data'!H32/'Fin. Data'!H5 -> 0.021761924 | J25: =-'Fin. Data'!I32/'Fin. Data'!I5 -> 0.022027828 | ... L25: =-'Fin. Data'!K32/'Fin. Data'!K5 -> 0.015223456 | N25: =AVERAGE(C25:E25) -> 0.020590368 | O25: =AVERAGE(C25:G25) -> 0.022716112 | P25: =AVERAGE(C25:L25) -> 0.020706812 | Q25: =AVERAGE(C25,F25:L25) -> 0.020635295 | S25: 0.02 | T25: 0.025
B26: Acquisition factor | C26: ='Fin. Data'!B33/'Fin. Data'!B5 -> -0.02081305 | D26: ='Fin. Data'!C33/'Fin. Data'!C5 -> -0.035940319 | E26: ='Fin. Data'!D33/'Fin. Data'!D5 -> -0.053133237 | F26: ='Fin. Data'!E33/'Fin. Data'!E5 -> -0.07115169 | G26: ='Fin. Data'!F33/'Fin. Data'!F5 -> -0.059839844 | H26: ='Fin. Data'!G33/'Fin. Data'!G5 -> -0.05018301 | I26: ='Fin. Data'!H33/'Fin. Data'!H5 -> -0.082956414 | J26: ='Fin. Data'!I33/'Fin. Data'!I5 -> -0.077308754 | ... L26: ='Fin. Data'!K33/'Fin. Data'!K5 -> -0.071785019 | N26: =AVERAGE(C26:E26) -> -0.036628869 | O26: =AVERAGE(C26:G26) -> -0.048175628 | P26: =AVERAGE(C26:L26) -> -0.061376266 | Q26: =AVERAGE(C26,F26:L26) -> -0.065586138 | T26: 0.01
B27: Dividends | C27: =-'Fin. Data'!B27/'Fin. Data'!B23 -> 0.33005868 | D27: =-'Fin. Data'!C27/'Fin. Data'!C23 -> 0.33356574 | E27: =-'Fin. Data'!D27/'Fin. Data'!D23 -> 0.38228942 | F27: =-'Fin. Data'!E27/'Fin. Data'!E23 -> 0.95516179 | G27: =-'Fin. Data'!F27/'Fin. Data'!F23 -> 0.47680067 | H27: =-'Fin. Data'!G27/'Fin. Data'!G23 -> 0.36642369 | I27: =-'Fin. Data'!H27/'Fin. Data'!H23 -> 0.37170439 | J27: =-'Fin. Data'!I27/'Fin. Data'!I23 -> 1.5886973 | ... L27: =-'Fin. Data'!K27/'Fin. Data'!K23 -> 0.45901398 | N27: =AVERAGE(C27:E27) -> 0.34863795 | O27: =AVERAGE(C27:G27) -> 0.49557526 | P27: =AVERAGE(C27:L27) -> 0.56879675 | Q27: =AVERAGE(C27,F27:L27) -> 0.62151405 | S27: =+N27 -> 0.34863795 | T27: =O27 -> 0.49557526
B28: Repurchases | C28: =-'Fin. Data'!B28/'Fin. Data'!B23 -> 0.00076070419 | D28: =-'Fin. Data'!C28/'Fin. Data'!C23 -> 0.00069721116 | E28: =-'Fin. Data'!D28/'Fin. Data'!D23 -> 0.00080993521 | F28: =-'Fin. Data'!E28/'Fin. Data'!E23 -> 0.032434515 | G28: =-'Fin. Data'!F28/'Fin. Data'!F23 -> 0.046147404 | H28: =-'Fin. Data'!G28/'Fin. Data'!G23 -> 0.16145786 | I28: =-'Fin. Data'!H28/'Fin. Data'!H23 -> 0 | J28: =-'Fin. Data'!I28/'Fin. Data'!I23 -> 0.13505747 | ... L28: =-'Fin. Data'!K28/'Fin. Data'!K23 -> 0.031420162 | N28: =AVERAGE(C28:E28) -> 0.00075595019 | O28: =AVERAGE(C28:G28) -> 0.016169954 | P28: =AVERAGE(C28:L28) -> 0.053447105 | Q28: =AVERAGE(C28,F28:L28) -> 0.066620487 | T28: =O28 -> 0.016169954
B29: Leases | C29: =('Fin. Data'!B50+'Fin. Data'!B54)/'Fin. Data'!B5 -> 0.0051811996 | D29: =('Fin. Data'!C50+'Fin. Data'!C54)/'Fin. Data'!C5 -> 0.0034351145 | E29: =('Fin. Data'!D50+'Fin. Data'!D54)/'Fin. Data'!D5 -> 0.0033585579 | F29: =('Fin. Data'!E50+'Fin. Data'!E54)/'Fin. Data'!E5 -> 0.0022425116 | G29: =('Fin. Data'!F50+'Fin. Data'!F54)/'Fin. Data'!F5 -> 0.00453125 | H29: =('Fin. Data'!G50+'Fin. Data'!G54)/'Fin. Data'!G5 -> 0 | I29: =('Fin. Data'!H50+'Fin. Data'!H54)/'Fin. Data'!H5 -> 0 | J29: =('Fin. Data'!I50+'Fin. Data'!I54)/'Fin. Data'!I5 -> 0 | ... L29: =('Fin. Data'!K50+'Fin. Data'!K54)/'Fin. Data'!K5 -> 0 | N29: =AVERAGE(C29:E29) -> 0.003991624 | O29: =AVERAGE(C29:G29) -> 0.0037497267 | P29: =AVERAGE(C29:L29) -> 0.0018748634 | Q29: =AVERAGE(C29,F29:L29) -> 0.0014943702 | S29: 0 | T29: =P29 -> 0.0018748634
B30: Cash Costs for EBIT | C30: - - | D30: - - | E30: - - | F30: - - | G30: - - | H30: - - | I30: - - | J30: - - | K30: - - | L30: - - | N30: =AVERAGE(C30:E30) -> #DIV/0! | O30: - - | P30: =AVERAGE(C30:L30) -> #DIV/0! | Q30: =AVERAGE(C30,F30:L30) -> #DIV/0!
B31: Total Debt | C31: ='Fin. Data'!B58/'Fin. Data'!B19 -> 2.1028224 | D31: ='Fin. Data'!C58/'Fin. Data'!C19 -> 2.4492017 | E31: ='Fin. Data'!D58/'Fin. Data'!D19 -> 3.1196364 | F31: ='Fin. Data'!E58/'Fin. Data'!E19 -> 3.8647205 | G31: ='Fin. Data'!F58/'Fin. Data'!F19 -> 2.6210214 | H31: ='Fin. Data'!G58/'Fin. Data'!G19 -> 2.5307088 | I31: ='Fin. Data'!H58/'Fin. Data'!H19 -> 2.6118547 | J31: ='Fin. Data'!I58/'Fin. Data'!I19 -> 3.7934739 | ... L31: ='Fin. Data'!K58/'Fin. Data'!K19 -> 2.698954 | N31: =AVERAGE(C31:E31) -> 2.5572202 | O31: =AVERAGE(C31:G31) -> 2.8314805 | P31: =AVERAGE(C31:L31) -> 2.8357093 | Q31: =AVERAGE(C31,F31:L31) -> 2.8485319
B34: Forecasts
R38: TRUCK
B39: Sectors | U39: 2023 | V39: 2022 | W39: 2021 | X39: 2020 | Y39: 2019 | Z39: 2018 | AA39: 2017 | AB39: 2016 | AC39: 2015 | AD39: 2014
B40: Trucks: | K40: Parts: | S40: Truck NAICS: 333924 | U40: 0.78 | V40: 0.76 | W40: 0.74 | X40: 0.73 | Y40: 0.8 | Z40: 0.8 | AA40: 0.8 | AB40: 0.8 | AC40: 0.81 | AD40: 0.77
S41: External Revenue | U41: 26846 | V41: 21486 | W41: 16800 | X41: 13165 | Y41: 19990 | Z41: 18187 | AA41: 14775 | AB41: 12767 | AC41: 14783 | AD41: 14594
S42: Depreciation | U42: 404 | V42: 325 | W42: 278 | X42: 292 | Y42: 382 | Z42: 406 | AA42: 468 | AB42: 433 | AC42: 400 | AD42: 415
S43: Income Before Tax | U43: 3800 | V43: 1753 | W43: 796 | X43: 581 | Y43: 1905 | Z43: 1672 | AA43: 1297 | AB43: 1126 | AC43: 1440 | AD43: 1160
S44: Pre-Tax Margin (%) | U44: 0.1394 | V44: 0.0797 | W44: 0.0458 | X44: 0.0426 | Y44: 0.0934 | Z44: 0.0886 | AA44: 0.0834 | AB44: 0.0825 | AC44: 0.0925 | AD44: 0.0757
S45: Long Lived Assets | U45: 585 | V45: 466 | W45: 547 | X45: 556 | Y45: 665 | Z45: 779 | AA45: 770 | AB45: 736 | AC45: 660 | AD45: --
J46: Financials | S46: Total Assets | U46: 8039 | V46: 7218 | W46: 6912 | X46: 5972 | Y46: 5609 | Z46: 5347 | AA46: 5160 | AB46: 4429 | AC46: 4472 | AD46: 4871
S47: Purchase of Fixed Assets | U47: -- | V47: -- | W47: -- | X47: -- | Y47: -- | Z47: -- | AA47: -- | AB47: -- | AC47: -- | AD47: 505
Z60: l
B78: Revenue
P79: #VALUE!
B80: Quarterly Revenue per Segment (Used 2024)
B82: Quarterly Revenue (Trucks) | C82: Units | D82: Q1 | E82: Q2 | F82: Q3 | G82: Q4 | H82: FY201X | J82: Quarterly Revenue (Parts) | K82: Units | L82: Q1 | M82: Q2 | N82: Q3 | O82: Q4 | P82: FY201X | R82: Quarterly Revenue (Financial) | S82: Units | T82: Q1 | U82: Q2 | V82: Q3 | W82: Q4 | X82: FY201X | Z82: Quarterly Revenue (Others) | AA82: Units | AB82: Q1 | AC82: Q2 | AD82: Q3 | AE82: Q4 | AF82: FY201X
B83: 2014 | C83: USD | D83: 3329.2 | E83: 3455 | F83: 3810.6 | G83: 3999.2 | H83: =IFERROR(SUM(D83:G83),"-") -> 14594 | J83: 2014 | K83: USD | L83: 726.6 | M83: 778 | N83: 784.2 | O83: 788.7 | P83: =IFERROR(SUM(L83:O83),"-") -> 3077.5 | R83: 2014 | S83: USD | T83: =293.7 -> 293.7 | U83: =302.6 -> 302.6 | V83: =305.9 -> 305.9 | W83: =302 -> 302 | X83: =IFERROR(SUM(T83:W83),"-") -> 1204.2 | Z83: 2014 | AA83: USD | AB83: 30.4 | AC83: 34 | AD83: 27.7 | AE83: 29.2 | AF83: =IFERROR(SUM(AB83:AE83),"-") -> 121.3
B84: Percentage of Year | C84: (%) | D84: =IFERROR(D83/SUM($D83:$G83),"-") -> 0.22812115 | E84: =IFERROR(E83/SUM($D83:$G83),"-") -> 0.23674113 | F84: =IFERROR(F83/SUM($D83:$G83),"-") -> 0.2611073 | G84: =IFERROR(G83/SUM($D83:$G83),"-") -> 0.27403042 | H84: =IFERROR(H83/SUM($D83:$G83),"-") -> 1 | J84: Percentage of Year | K84: (%) | L84: =IFERROR(L83/SUM($L83:$O83),"-") -> 0.23610073 | M84: =IFERROR(M83/SUM($L83:$O83),"-") -> 0.2528026 | N84: =IFERROR(N83/SUM($L83:$O83),"-") -> 0.25481722 | O84: =IFERROR(O83/SUM($L83:$O83),"-") -> 0.25627945 | P84: =IFERROR(P83/SUM($L83:$O83),"-") -> 1 | R84: Percentage of Year | S84: (%) | T84: =IFERROR(T83/SUM($T83:$W83),"-") -> 0.24389636 | U84: =IFERROR(U83/SUM($T83:$W83),"-") -> 0.25128716 | V84: =IFERROR(V83/SUM($T83:$W83),"-") -> 0.25402757 | W84: =IFERROR(W83/SUM($T83:$W83),"-") -> 0.25078891 | X84: =IFERROR(X83/SUM($T83:$W83),"-") -> 1 | Z84: Percentage of Year | AA84: (%) | AB84: =IFERROR(AB83/SUM($AB83:$AE83),"-") -> 0.2506183 | AC84: =IFERROR(AC83/SUM($AB83:$AE83),"-") -> 0.28029678 | AD84: =IFERROR(AD83/SUM($AB83:$AE83),"-") -> 0.22835944 | AE84: =IFERROR(AE83/SUM($AB83:$AE83),"-") -> 0.24072547 | AF84: =IFERROR(AF83/SUM($AB83:$AE83),"-") -> 1
B85: 2015 | C85: USD | D85: 3769.1 | E85: 3983.4 | F85: 3744.7 | G85: 3285.3 | H85: =IFERROR(SUM(D85:G85),"-") -> 14782.5 | J85: 2015 | K85: USD | L85: 752.7 | M85: 776.5 | N85: 778 | O85: 752.9 | P85: =IFERROR(SUM(L85:O85),"-") -> 3060.1 | R85: 2015 | S85: USD | T85: =284.7 -> 284.7 | U85: =293.8 -> 293.8 | V85: =301 -> 301 | W85: =292.8 -> 292.8 | X85: =IFERROR(SUM(T85:W85),"-") -> 1172.3 | Z85: 2015 | AA85: USD | AB85: 26.2 | AC85: 26.2 | AD85: 23.5 | AE85: 24.3 | AF85: =IFERROR(SUM(AB85:AE85),"-") -> 100.2
B86: Percentage of Year | C86: (%) | D86: =IFERROR(D85/SUM($D85:$G85),"-") -> 0.2549704 | E86: =IFERROR(E85/SUM($D85:$G85),"-") -> 0.26946728 | F86: =IFERROR(F85/SUM($D85:$G85),"-") -> 0.2533198 | G86: =IFERROR(G85/SUM($D85:$G85),"-") -> 0.22224252 | H86: =IFERROR(H85/SUM($D85:$G85),"-") -> 1 | J86: Percentage of Year | K86: (%) | L86: =IFERROR(L85/SUM($L85:$O85),"-") -> 0.24597235 | M86: =IFERROR(M85/SUM($L85:$O85),"-") -> 0.25374988 | N86: =IFERROR(N85/SUM($L85:$O85),"-") -> 0.25424006 | O86: =IFERROR(O85/SUM($L85:$O85),"-") -> 0.24603771 | P86: =IFERROR(P85/SUM($L85:$O85),"-") -> 1 | R86: Percentage of Year | S86: (%) | T86: =IFERROR(T85/SUM($T85:$W85),"-") -> 0.24285592 | U86: =IFERROR(U85/SUM($T85:$W85),"-") -> 0.25061844 | V86: =IFERROR(V85/SUM($T85:$W85),"-") -> 0.25676021 | W86: =IFERROR(W85/SUM($T85:$W85),"-") -> 0.24976542 | X86: =IFERROR(X85/SUM($T85:$W85),"-") -> 1 | Z86: Percentage of Year | AA86: (%) | AB86: =IFERROR(AB85/SUM($AB85:$AE85),"-") -> 0.26147705 | AC86: =IFERROR(AC85/SUM($AB85:$AE85),"-") -> 0.26147705 | AD86: =IFERROR(AD85/SUM($AB85:$AE85),"-") -> 0.23453094 | AE86: =IFERROR(AE85/SUM($AB85:$AE85),"-") -> 0.24251497 | AF86: =IFERROR(AF85/SUM($AB85:$AE85),"-") -> 1
B87: 2016 | C87: USD | D87: 3270.5 | E87: 3341.2 | F87: 3170.7 | G87: 2984.9 | H87: =IFERROR(SUM(D87:G87),"-") -> 12767.3 | J87: 2016 | K87: USD | L87: 719.5 | M87: 756.4 | N87: 764.8 | O87: 765 | P87: =IFERROR(SUM(L87:O87),"-") -> 3005.7 | R87: 2016 | S87: USD | T87: =289.4 -> 289.4 | U87: 297.4 | V87: 296.2 | W87: 303.7 | X87: =IFERROR(SUM(T87:W87),"-") -> 1186.7 | Z87: 2016 | AA87: USD | AB87: 20.6 | AC87: 18.2 | AD87: 17.7 | AE87: 17.1 | AF87: =IFERROR(SUM(AB87:AE87),"-") -> 73.6
B88: Percentage of Year | C88: (%) | D88: =IFERROR(D87/SUM($D87:$G87),"-") -> 0.25616223 | E88: =IFERROR(E87/SUM($D87:$G87),"-") -> 0.26169981 | F88: =IFERROR(F87/SUM($D87:$G87),"-") -> 0.24834538 | G88: =IFERROR(G87/SUM($D87:$G87),"-") -> 0.23379258 | H88: =IFERROR(H87/SUM($D87:$G87),"-") -> 1 | J88: Percentage of Year | K88: (%) | L88: =IFERROR(L87/SUM($L87:$O87),"-") -> 0.23937851 | M88: =IFERROR(M87/SUM($L87:$O87),"-") -> 0.25165519 | N88: =IFERROR(N87/SUM($L87:$O87),"-") -> 0.25444988 | O88: =IFERROR(O87/SUM($L87:$O87),"-") -> 0.25451642 | P88: =IFERROR(P87/SUM($L87:$O87),"-") -> 1 | R88: Percentage of Year | S88: (%) | T88: =IFERROR(T87/SUM($T87:$W87),"-") -> 0.24386955 | U88: =IFERROR(U87/SUM($T87:$W87),"-") -> 0.25061094 | V88: =IFERROR(V87/SUM($T87:$W87),"-") -> 0.24959973 | W88: =IFERROR(W87/SUM($T87:$W87),"-") -> 0.25591978 | X88: =IFERROR(X87/SUM($T87:$W87),"-") -> 1 | Z88: Percentage of Year | AA88: (%) | AB88: =IFERROR(AB87/SUM($AB87:$AE87),"-") -> 0.2798913 | AC88: =IFERROR(AC87/SUM($AB87:$AE87),"-") -> 0.24728261 | AD88: =IFERROR(AD87/SUM($AB87:$AE87),"-") -> 0.24048913 | AE88: =IFERROR(AE87/SUM($AB87:$AE87),"-") -> 0.23233696 | AF88: =IFERROR(AF87/SUM($AB87:$AE87),"-") -> 1
B89: 2017 | C89: USD | D89: 3130.1 | E89: 3553.6 | F89: 3867.4 | G89: 4223.7 | H89: =IFERROR(SUM(D89:G89),"-") -> 14774.8 | J89: 2017 | K89: USD | L89: 786.7 | M89: 823.1 | N89: 840 | O89: 877.2 | P89: =IFERROR(SUM(L89:O89),"-") -> 3327 | R89: 2017 | S89: USD | T89: 302.2 | U89: 306.3 | V89: 328.2 | W89: 332.2 | X89: =IFERROR(SUM(T89:W89),"-") -> 1268.9 | Z89: 2017 | AA89: USD | AB89: 18.9 | AC89: 21.2 | AD89: 24.1 | AE89: 21.5 | AF89: =IFERROR(SUM(AB89:AE89),"-") -> 85.7
B90: Percentage of Year | C90: (%) | D90: =IFERROR(D89/SUM($D89:$G89),"-") -> 0.21185397 | E90: =IFERROR(E89/SUM($D89:$G89),"-") -> 0.24051764 | F90: =IFERROR(F89/SUM($D89:$G89),"-") -> 0.2617565 | G90: =IFERROR(G89/SUM($D89:$G89),"-") -> 0.28587189 | H90: =IFERROR(H89/SUM($D89:$G89),"-") -> 1 | J90: Percentage of Year | K90: (%) | L90: =IFERROR(L89/SUM($L89:$O89),"-") -> 0.23645927 | M90: =IFERROR(M89/SUM($L89:$O89),"-") -> 0.24740006 | N90: =IFERROR(N89/SUM($L89:$O89),"-") -> 0.25247971 | O90: =IFERROR(O89/SUM($L89:$O89),"-") -> 0.26366096 | P90: =IFERROR(P89/SUM($L89:$O89),"-") -> 1 | R90: Percentage of Year | S90: (%) | T90: =IFERROR(T89/SUM($T89:$W89),"-") -> 0.23815904 | U90: =IFERROR(U89/SUM($T89:$W89),"-") -> 0.24139018 | V90: =IFERROR(V89/SUM($T89:$W89),"-") -> 0.25864922 | W90: =IFERROR(W89/SUM($T89:$W89),"-") -> 0.26180156 | X90: =IFERROR(X89/SUM($T89:$W89),"-") -> 1 | Z90: Percentage of Year | AA90: (%) | AB90: =IFERROR(AB89/SUM($AB89:$AE89),"-") -> 0.22053676 | AC90: =IFERROR(AC89/SUM($AB89:$AE89),"-") -> 0.24737456 | AD90: =IFERROR(AD89/SUM($AB89:$AE89),"-") -> 0.28121354 | AE90: =IFERROR(AE89/SUM($AB89:$AE89),"-") -> 0.25087515 | AF90: =IFERROR(AF89/SUM($AB89:$AE89),"-") -> 1
B91: 2018 | C91: USD | D91: 4353 | E91: 4467.8 | F91: 4429.4 | G91: 4936.8 | H91: =IFERROR(SUM(D91:G91),"-") -> 18187 | J91: 2018 | K91: USD | L91: 939.9 | M91: 968 | N91: 960.1 | O91: 970.9 | P91: =IFERROR(SUM(L91:O91),"-") -> 3838.9 | R91: 2018 | S91: USD | T91: 332.2 | U91: 338 | V91: 339.9 | W91: 347 | X91: =IFERROR(SUM(T91:W91),"-") -> 1357.1 | Z91: 2018 | AA91: USD | AB91: 28.9 | AC91: 31.4 | AD91: 27.4 | AE91: 25 | AF91: =IFERROR(SUM(AB91:AE91),"-") -> 112.7
B92: Percentage of Year | C92: (%) | D92: =IFERROR(D91/SUM($D91:$G91),"-") -> 0.23934679 | E92: =IFERROR(E91/SUM($D91:$G91),"-") -> 0.24565899 | F92: =IFERROR(F91/SUM($D91:$G91),"-") -> 0.24354759 | G92: =IFERROR(G91/SUM($D91:$G91),"-") -> 0.27144664 | H92: =IFERROR(H91/SUM($D91:$G91),"-") -> 1 | J92: Percentage of Year | K92: (%) | L92: =IFERROR(L91/SUM($L91:$O91),"-") -> 0.24483576 | M92: =IFERROR(M91/SUM($L91:$O91),"-") -> 0.25215557 | N92: =IFERROR(N91/SUM($L91:$O91),"-") -> 0.25009768 | O92: =IFERROR(O91/SUM($L91:$O91),"-") -> 0.25291099 | P92: =IFERROR(P91/SUM($L91:$O91),"-") -> 1 | R92: Percentage of Year | S92: (%) | T92: =IFERROR(T91/SUM($T91:$W91),"-") -> 0.24478668 | U92: =IFERROR(U91/SUM($T91:$W91),"-") -> 0.2490605 | V92: =IFERROR(V91/SUM($T91:$W91),"-") -> 0.25046054 | W92: =IFERROR(W91/SUM($T91:$W91),"-") -> 0.25569229 | X92: =IFERROR(X91/SUM($T91:$W91),"-") -> 1 | Z92: Percentage of Year | AA92: (%) | AB92: =IFERROR(AB91/SUM($AB91:$AE91),"-") -> 0.25643301 | AC92: =IFERROR(AC91/SUM($AB91:$AE91),"-") -> 0.27861579 | AD92: =IFERROR(AD91/SUM($AB91:$AE91),"-") -> 0.24312334 | AE92: =IFERROR(AE91/SUM($AB91:$AE91),"-") -> 0.22182786 | AF92: =IFERROR(AF91/SUM($AB91:$AE91),"-") -> 1
B93: 2019 | C93: USD | D93: 5107.3 | E93: 5211.9 | F93: 4977.4 | G93: 4692.9 | H93: =IFERROR(SUM(D93:G93),"-") -> 19989.5 | J93: 2019 | K93: USD | L93: 1004.7 | M93: 1025.4 | N93: 1000.9 | O93: 993.9 | P93: =IFERROR(SUM(L93:O93),"-") -> 4024.9 | R93: 2019 | S93: USD | T93: 349.5 | U93: 361.4 | V93: 362.8 | W93: 406.3 | X93: =IFERROR(SUM(T93:W93),"-") -> 1480 | Z93: 2019 | AA93: USD | AB93: 26.1 | AC93: 29.2 | AD93: 25.9 | AE93: 24.1 | AF93: =IFERROR(SUM(AB93:AE93),"-") -> 105.3
B94: Percentage of Year | C94: (%) | D94: =IFERROR(D93/SUM($D93:$G93),"-") -> 0.25549914 | E94: =IFERROR(E93/SUM($D93:$G93),"-") -> 0.26073188 | F94: =IFERROR(F93/SUM($D93:$G93),"-") -> 0.24900073 | G94: =IFERROR(G93/SUM($D93:$G93),"-") -> 0.23476825 | H94: =IFERROR(H93/SUM($D93:$G93),"-") -> 1 | J94: Percentage of Year | K94: (%) | L94: =IFERROR(L93/SUM($L93:$O93),"-") -> 0.24962111 | M94: =IFERROR(M93/SUM($L93:$O93),"-") -> 0.25476409 | N94: =IFERROR(N93/SUM($L93:$O93),"-") -> 0.24867699 | O94: =IFERROR(O93/SUM($L93:$O93),"-") -> 0.24693781 | P94: =IFERROR(P93/SUM($L93:$O93),"-") -> 1 | R94: Percentage of Year | S94: (%) | T94: =IFERROR(T93/SUM($T93:$W93),"-") -> 0.23614865 | U94: =IFERROR(U93/SUM($T93:$W93),"-") -> 0.24418919 | V94: =IFERROR(V93/SUM($T93:$W93),"-") -> 0.24513514 | W94: =IFERROR(W93/SUM($T93:$W93),"-") -> 0.27452703 | X94: =IFERROR(X93/SUM($T93:$W93),"-") -> 1 | Z94: Percentage of Year | AA94: (%) | AB94: =IFERROR(AB93/SUM($AB93:$AE93),"-") -> 0.24786325 | AC94: =IFERROR(AC93/SUM($AB93:$AE93),"-") -> 0.27730294 | AD94: =IFERROR(AD93/SUM($AB93:$AE93),"-") -> 0.24596391 | AE94: =IFERROR(AE93/SUM($AB93:$AE93),"-") -> 0.2288699 | AF94: =IFERROR(AF93/SUM($AB93:$AE93),"-") -> 1
B95: 2020 | C95: USD | D95: 3757.6 | E95: 1858.4 | F95: 3504 | G95: 4044.8 | H95: =IFERROR(SUM(D95:G95),"-") -> 13164.8 | J95: 2020 | K95: USD | L95: 998.6 | M95: 823.7 | N95: 1016.2 | O95: 1074.4 | P95: =IFERROR(SUM(L95:O95),"-") -> 3912.9 | R95: 2020 | S95: USD | T95: 383.7 | U95: 360.3 | V95: 397.6 | W95: 432.6 | X95: =IFERROR(SUM(T95:W95),"-") -> 1574.2 | Z95: 2020 | AA95: USD | AB95: 21.8 | AC95: 19.8 | AD95: 18.2 | AE95: 16.8 | AF95: =IFERROR(SUM(AB95:AE95),"-") -> 76.6
B96: Percentage of Year | C96: (%) | D96: =IFERROR(D95/SUM($D95:$G95),"-") -> 0.28542781 | E96: =IFERROR(E95/SUM($D95:$G95),"-") -> 0.14116432 | F96: =IFERROR(F95/SUM($D95:$G95),"-") -> 0.26616432 | G96: =IFERROR(G95/SUM($D95:$G95),"-") -> 0.30724356 | H96: =IFERROR(H95/SUM($D95:$G95),"-") -> 1 | J96: Percentage of Year | K96: (%) | L96: =IFERROR(L95/SUM($L95:$O95),"-") -> 0.25520714 | M96: =IFERROR(M95/SUM($L95:$O95),"-") -> 0.21050883 | N96: =IFERROR(N95/SUM($L95:$O95),"-") -> 0.25970508 | O96: =IFERROR(O95/SUM($L95:$O95),"-") -> 0.27457896 | P96: =IFERROR(P95/SUM($L95:$O95),"-") -> 1 | R96: Percentage of Year | S96: (%) | T96: =IFERROR(T95/SUM($T95:$W95),"-") -> 0.24374285 | U96: =IFERROR(U95/SUM($T95:$W95),"-") -> 0.22887816 | V96: =IFERROR(V95/SUM($T95:$W95),"-") -> 0.25257274 | W96: =IFERROR(W95/SUM($T95:$W95),"-") -> 0.27480625 | X96: =IFERROR(X95/SUM($T95:$W95),"-") -> 1 | Z96: Percentage of Year | AA96: (%) | AB96: =IFERROR(AB95/SUM($AB95:$AE95),"-") -> 0.2845953 | AC96: =IFERROR(AC95/SUM($AB95:$AE95),"-") -> 0.25848564 | AD96: =IFERROR(AD95/SUM($AB95:$AE95),"-") -> 0.23759791 | AE96: =IFERROR(AE95/SUM($AB95:$AE95),"-") -> 0.21932115 | AF96: =IFERROR(AF95/SUM($AB95:$AE95),"-") -> 1
B97: 2021 | C97: USD | D97: 4233 | E97: 4152.2 | F97: 3452.5 | G97: 4961.9 | H97: =IFERROR(SUM(D97:G97),"-") -> 16799.6 | J97: 2021 | K97: USD | L97: 1160.7 | M97: 1211.3 | N97: 1260.2 | O97: 1312.1 | P97: =IFERROR(SUM(L97:O97),"-") -> 4944.3 | R97: 2021 | S97: USD | T97: 432 | U97: 456.3 | V97: 409.1 | W97: 390.4 | X97: =IFERROR(SUM(T97:W97),"-") -> 1687.8 | Z97: 2021 | AA97: USD | AB97: 19.8 | AC97: 24.1 | AD97: 24.9 | AE97: 21.7 | AF97: =IFERROR(SUM(AB97:AE97),"-") -> 90.5
B98: Percentage of Year | C98: (%) | D98: =IFERROR(D97/SUM($D97:$G97),"-") -> 0.25197029 | E98: =IFERROR(E97/SUM($D97:$G97),"-") -> 0.24716065 | F98: =IFERROR(F97/SUM($D97:$G97),"-") -> 0.20551085 | G98: =IFERROR(G97/SUM($D97:$G97),"-") -> 0.29535822 | H98: =IFERROR(H97/SUM($D97:$G97),"-") -> 1 | J98: Percentage of Year | K98: (%) | L98: =IFERROR(L97/SUM($L97:$O97),"-") -> 0.23475517 | M98: =IFERROR(M97/SUM($L97:$O97),"-") -> 0.24498918 | N98: =IFERROR(N97/SUM($L97:$O97),"-") -> 0.25487936 | O98: =IFERROR(O97/SUM($L97:$O97),"-") -> 0.26537629 | P98: =IFERROR(P97/SUM($L97:$O97),"-") -> 1 | R98: Percentage of Year | S98: (%) | T98: =IFERROR(T97/SUM($T97:$W97),"-") -> 0.2559545 | U98: =IFERROR(U97/SUM($T97:$W97),"-") -> 0.27035194 | V98: =IFERROR(V97/SUM($T97:$W97),"-") -> 0.24238654 | W98: =IFERROR(W97/SUM($T97:$W97),"-") -> 0.23130703 | X98: =IFERROR(X97/SUM($T97:$W97),"-") -> 1 | Z98: Percentage of Year | AA98: (%) | AB98: =IFERROR(AB97/SUM($AB97:$AE97),"-") -> 0.21878453 | AC98: =IFERROR(AC97/SUM($AB97:$AE97),"-") -> 0.26629834 | AD98: =IFERROR(AD97/SUM($AB97:$AE97),"-") -> 0.27513812 | AE98: =IFERROR(AE97/SUM($AB97:$AE97),"-") -> 0.23977901 | AF98: =IFERROR(AF97/SUM($AB97:$AE97),"-") -> 1
B99: 2022 | C99: USD | D99: 4697.1 | E99: 5336.4 | F99: 5198.4 | G99: 6254.5 | H99: =IFERROR(SUM(D99:G99),"-") -> 21486.4 | J99: 2022 | K99: USD | L99: 1388.9 | M99: 1434.7 | N99: 1471.5 | O99: 1469.2 | P99: =IFERROR(SUM(L99:O99),"-") -> 5764.3 | R99: 2022 | S99: USD | T99: 366.2 | U99: 372.5 | V99: 371.9 | W99: 394.8 | X99: =IFERROR(SUM(T99:W99),"-") -> 1505.4 | Z99: 2022 | AA99: USD | AB99: 20.4 | AC99: 15.1 | AD99: 17.3 | AE99: 11 | AF99: =IFERROR(SUM(AB99:AE99),"-") -> 63.8
B100: Percentage of Year | C100: (%) | D100: =IFERROR(D99/SUM($D99:$G99),"-") -> 0.21860805 | E100: =IFERROR(E99/SUM($D99:$G99),"-") -> 0.24836175 | F100: =IFERROR(F99/SUM($D99:$G99),"-") -> 0.24193909 | G100: =IFERROR(G99/SUM($D99:$G99),"-") -> 0.29109111 | H100: =IFERROR(H99/SUM($D99:$G99),"-") -> 1 | J100: Percentage of Year | K100: (%) | L100: =IFERROR(L99/SUM($L99:$O99),"-") -> 0.2409486 | M100: =IFERROR(M99/SUM($L99:$O99),"-") -> 0.24889405 | N100: =IFERROR(N99/SUM($L99:$O99),"-") -> 0.25527818 | O100: =IFERROR(O99/SUM($L99:$O99),"-") -> 0.25487917 | P100: =IFERROR(P99/SUM($L99:$O99),"-") -> 1 | R100: Percentage of Year | S100: (%) | T100: =IFERROR(T99/SUM($T99:$W99),"-") -> 0.24325761 | U100: =IFERROR(U99/SUM($T99:$W99),"-") -> 0.24744254 | V100: =IFERROR(V99/SUM($T99:$W99),"-") -> 0.24704398 | W100: =IFERROR(W99/SUM($T99:$W99),"-") -> 0.26225588 | X100: =IFERROR(X99/SUM($T99:$W99),"-") -> 1 | Z100: Percentage of Year | AA100: (%) | AB100: =IFERROR(AB99/SUM($AB99:$AE99),"-") -> 0.31974922 | AC100: =IFERROR(AC99/SUM($AB99:$AE99),"-") -> 0.23667712 | AD100: =IFERROR(AD99/SUM($AB99:$AE99),"-") -> 0.27115987 | AE100: =IFERROR(AE99/SUM($AB99:$AE99),"-") -> 0.17241379 | AF100: =IFERROR(AF99/SUM($AB99:$AE99),"-") -> 1
B101: 2023 | C101: USD | D101: 6413.8 | E101: 6827.5 | F101: 6636.4 | G101: 6968.7 | H101: =IFERROR(SUM(D101:G101),"-") -> 26846.4 | J101: 2023 | K101: USD | L101: 1623 | M101: 1598.9 | N101: 1582.2 | O101: 1610.3 | P101: =IFERROR(SUM(L101:O101),"-") -> 6414.4 | R101: 2023 | S101: USD | T101: 423.2 | U101: 439.8 | V101: 464.1 | W101: 484.8 | X101: =IFERROR(SUM(T101:W101),"-") -> 1811.9 | Z101: 2023 | AA101: USD | AB101: 13.3 | AC101: 14.9 | AD101: 13.7 | AE101: 12.8 | AF101: =IFERROR(SUM(AB101:AE101),"-") -> 54.7
B102: Percentage of Year | C102: (%) | D102: =IFERROR(D101/SUM($D101:$G101),"-") -> 0.23890727 | E102: =IFERROR(E101/SUM($D101:$G101),"-") -> 0.25431715 | F102: =IFERROR(F101/SUM($D101:$G101),"-") -> 0.24719888 | G102: =IFERROR(G101/SUM($D101:$G101),"-") -> 0.2595767 | H102: =IFERROR(H101/SUM($D101:$G101),"-") -> 1 | J102: Percentage of Year | K102: (%) | L102: =IFERROR(L101/SUM($L101:$O101),"-") -> 0.25302444 | M102: =IFERROR(M101/SUM($L101:$O101),"-") -> 0.24926727 | N102: =IFERROR(N101/SUM($L101:$O101),"-") -> 0.24666376 | O102: =IFERROR(O101/SUM($L101:$O101),"-") -> 0.25104452 | P102: =IFERROR(P101/SUM($L101:$O101),"-") -> 1 | R102: Percentage of Year | S102: (%) | T102: =IFERROR(T101/SUM($T101:$W101),"-") -> 0.23356697 | U102: =IFERROR(U101/SUM($T101:$W101),"-") -> 0.24272863 | V102: =IFERROR(V101/SUM($T101:$W101),"-") -> 0.25613996 | W102: =IFERROR(W101/SUM($T101:$W101),"-") -> 0.26756444 | X102: =IFERROR(X101/SUM($T101:$W101),"-") -> 1 | Z102: Percentage of Year | AA102: (%) | AB102: =IFERROR(AB101/SUM($AB101:$AE101),"-") -> 0.24314442 | AC102: =IFERROR(AC101/SUM($AB101:$AE101),"-") -> 0.27239488 | AD102: =IFERROR(AD101/SUM($AB101:$AE101),"-") -> 0.25045704 | AE102: =IFERROR(AE101/SUM($AB101:$AE101),"-") -> 0.23400366 | AF102: =IFERROR(AF101/SUM($AB101:$AE101),"-") -> 1
B103: 2024 | C103: USD | D103: 6541 | E103: =D103*E105/D105 -> 6447.0829 | F103: =D103*F105/D105 -> 6640.2147 | G103: =D103*G105/D105 -> 7169.5566 | H103: =IFERROR(D103/D105,"-") -> 26797.854 | J103: 2024 | K103: USD | L103: 1675.9 | M103: =L103*M105/L105 -> 1696.4565 | N103: =L103*N105/L105 -> 1741.2388 | O103: =L103*O105/L105 -> 1765.2697 | P103: =IFERROR(L103/L105,"-") -> 6878.865 | R103: 2024 | S103: USD | T103: 509.3 | U103: =T103*U105/T105 -> 519.86275 | V103: =T103*V105/T105 -> 527.46538 | W103: =T103*W105/T105 -> 542.5063 | X103: =IFERROR(T103/T105,"-") -> 2099.1344 | Z103: 2024 | AA103: USD | AB103: 18.1 | AC103: =AB103*AC105/AB105 -> 18.402094 | AD103: =AB103*AD105/AB105 -> 17.574048 | AE103: =AB103*AE105/AB105 -> 15.994889 | AF103: =IFERROR(AB103/AB105,"-") -> 70.071031
B104: Percentage of Year | C104: (%) | D104: =IFERROR(D103/SUM(D103:G103),"-") -> 0.24408671 | E104: =IFERROR(E103/SUM(D103:G103),"-") -> 0.24058206 | F104: =IFERROR(F103/SUM(D103:G103),"-") -> 0.24778904 | G104: =IFERROR(G103/SUM(D103:G103),"-") -> 0.26754219 | H104: =IFERROR(D104,"-") -> 0.24408671 | J104: Percentage of Year | K104: (%) | L104: =IFERROR(L103/SUM($L103:$O103),"-") -> 0.24363031 | M104: =IFERROR(M103/SUM(L103:O103),"-") -> 0.24661867 | N104: =IFERROR(N103/SUM(L103:O103),"-") -> 0.25312879 | O104: =IFERROR(O103/SUM(L103:O103),"-") -> 0.25662223 | P104: =IFERROR(L104,"-") -> 0.24363031 | R104: Percentage of Year | S104: (%) | T104: =IFERROR(T103/SUM($T103:$W103),"-") -> 0.24262381 | U104: =IFERROR(U103/SUM(T103:W103),"-") -> 0.24765577 | V104: =IFERROR(V103/SUM(T103:W103),"-") -> 0.25127756 | W104: =IFERROR(W103/SUM(T103:W103),"-") -> 0.25844286 | X104: =IFERROR(T104,"-") -> 0.24262381 | Z104: Percentage of Year | AA104: (%) | AB104: =IFERROR(AB103/SUM($AB103:$AE103),"-") -> 0.25830931 | AC104: =IFERROR(AC103/SUM(AB103:AE103),"-") -> 0.26262057 | AD104: =IFERROR(AD103/SUM(AB103:AE103),"-") -> 0.25080332 | AE104: =IFERROR(AE103/SUM(AB103:AE103),"-") -> 0.22826679 | AF104: =IFERROR(AB104,"-") -> 0.25830931
B105: AVERAGE | C105: USD | D105: =IFERROR(AVERAGE(D84,D86,D88,D90,D92,D94,D96,D98,D100,D102),"-") -> 0.24408671 | E105: =IFERROR(AVERAGE(E84,E86,E88,E90,E92,E94,E96,E98,E100,E102),"-") -> 0.24058206 | F105: =IFERROR(AVERAGE(F84,F86,F88,F90,F92,F94,F96,F98,F100,F102),"-") -> 0.24778904 | G105: =IFERROR(AVERAGE(G84,G86,G88,G90,G92,G94,G96,G98,G100,G102),"-") -> 0.26754219 | H105: =IFERROR(SUM(D105:G105),"-") -> 1 | J105: AVERAGE | K105: USD | L105: =IFERROR(AVERAGE(L84,L86,L88,L90,L92,L94,L96,L98,L100,L102),"-") -> 0.24363031 | M105: =IFERROR(AVERAGE(M84,M86,M88,M90,M92,M94,M96,M98,M100,M102),"-") -> 0.24661867 | N105: =IFERROR(AVERAGE(N84,N86,N88,N90,N92,N94,N96,N98,N100,N102),"-") -> 0.25312879 | O105: =IFERROR(AVERAGE(O84,O86,O88,O90,O92,O94,O96,O98,O100,O102),"-") -> 0.25662223 | P105: =IFERROR(SUM(L105:O105),"-") -> 1 | R105: AVERAGE | S105: USD | T105: =IFERROR(AVERAGE(T84,T86,T88,T90,T92,T94,T96,T98,T100,T102),"-") -> 0.24262381 | U105: =IFERROR(AVERAGE(U84,U86,U88,U90,U92,U94,U96,U98,U100,U102),"-") -> 0.24765577 | V105: =IFERROR(AVERAGE(V84,V86,V88,V90,V92,V94,V96,V98,V100,V102),"-") -> 0.25127756 | W105: =IFERROR(AVERAGE(W84,W86,W88,W90,W92,W94,W96,W98,W100,W102),"-") -> 0.25844286 | X105: =IFERROR(SUM(T105:W105),"-") -> 1 | Z105: AVERAGE | AA105: USD | AB105: =IFERROR(AVERAGE(AB84,AB86,AB88,AB90,AB92,AB94,AB96,AB98,AB100,AB102),"-") -> 0.25830931 | AC105: =IFERROR(AVERAGE(AC84,AC86,AC88,AC90,AC92,AC94,AC96,AC98,AC100,AC102),"-") -> 0.26262057 | AD105: =IFERROR(AVERAGE(AD84,AD86,AD88,AD90,AD92,AD94,AD96,AD98,AD100,AD102),"-") -> 0.25080332 | AE105: =IFERROR(AVERAGE(AE84,AE86,AE88,AE90,AE92,AE94,AE96,AE98,AE100,AE102),"-") -> 0.22826679 | AF105: =IFERROR(SUM(AB105:AE105),"-") -> 1
B107: Segment 1: Trucks (77% of Revenue)
B109: Trucks: | C109: =+L15 -> 2014 | D109: =+K15 -> 2015 | E109: =+J15 -> 2016 | F109: =+I15 -> 2017 | G109: =+H15 -> 2018 | H109: =+G15 -> 2019 | I109: =+F15 -> 2020 | J109: =+E15 -> 2021 | K109: =+D15 -> 2022 | L109: =+C15 -> 2023 | M109: Average All | N109: Average 5 Yrs
B110: % revenue | C110: 0.77 | D110: 0.77 | E110: 0.75 | F110: 0.76 | G110: 0.77 | H110: 0.78 | I110: 0.78 | J110: 0.7 | K110: 0.75 | L110: 0.77 | M110: =AVERAGE(C110:L110) -> 0.76 | N110: =AVERAGE(H110:L110) -> 0.756
B111: %growth | D111: =+D112/C112-1 -> 0.0062115071 | E111: =+E112/D112-1 -> -0.13206464 | F111: =+F112/E112-1 -> 0.15748332 | G111: =+G112/F112-1 -> 0.22353813 | H111: =+H112/G112-1 -> 0.10369712 | I111: =+I112/H112-1 -> -0.26839844 | J111: =+J112/I112-1 -> 0.12710167 | K111: =+K112/J112-1 -> 0.3127528 | L111: =+L112/K112-1 -> 0.25134351 | M111: =AVERAGE(C111:L111) -> 0.086851665 | N111: =AVERAGE(H111:L111) -> 0.10529933
B112: Value | C112: =+C110*'Fin. Data'!K5 -> 14627.69 | D112: =+D110*'Fin. Data'!J5 -> 14718.55 | E112: =+E110*'Fin. Data'!I5 -> 12774.75 | F112: =+F110*'Fin. Data'!H5 -> 14786.56 | G112: =+G110*'Fin. Data'!G5 -> 18091.92 | H112: =+H110*'Fin. Data'!F5 -> 19968 | I112: =+I110*'Fin. Data'!E5 -> 14608.62 | J112: =+J110*'Fin. Data'!D5 -> 16465.4 | K112: =+K110*'Fin. Data'!C5 -> 21615 | L112: =+L110*'Fin. Data'!B5 -> 27047.79
B113: Parts:
B114: =+B110 -> % revenue | C114: 0.16 | D114: 0.16 | E114: 0.18 | F114: 0.17 | G114: 0.16 | H114: 0.16 | I114: 0.16 | J114: 0.21 | K114: 0.2 | L114: 0.18 | M114: =AVERAGE(C114:K114) -> 0.17333333 | N114: =AVERAGE(H114:L114) -> 0.182
B115: =+B111 -> %growth | D115: =+D116/C116-1 -> 0.0062115071 | E115: =+E116/D116-1 -> 0.0024653414 | F115: =+F116/E116-1 -> 0.078794758 | G115: =+G116/F116-1 -> 0.13660991 | H115: =+H116/G116-1 -> 0.089547157 | I115: =+I116/H116-1 -> -0.26839844 | J115: =+J116/I116-1 -> 0.64838619 | K115: =+K116/J116-1 -> 0.16689138 | L115: =+L116/K116-1 -> 0.096956974 | M115: =AVERAGE(C115:L115) -> 0.10638498 | N115: =AVERAGE(H115:L115) -> 0.14667665
B116: =+B112 -> Value | C116: =+C114*'Fin. Data'!K5 -> 3039.52 | D116: =+D114*'Fin. Data'!J5 -> 3058.4 | E116: =+E114*'Fin. Data'!I5 -> 3065.94 | F116: =+F114*'Fin. Data'!H5 -> 3307.52 | G116: =+G114*'Fin. Data'!G5 -> 3759.36 | H116: =+H114*'Fin. Data'!F5 -> 4096 | I116: =+I114*'Fin. Data'!E5 -> 2996.64 | J116: =+J114*'Fin. Data'!D5 -> 4939.62 | K116: =+K114*'Fin. Data'!C5 -> 5764 | L116: =+L114*'Fin. Data'!B5 -> 6322.86
B117: Financials:
B118: =+B114 -> % revenue | C118: 0.06 | D118: 0.06 | E118: 0.07 | F118: 0.07 | G118: 0.06 | H118: 0.06 | I118: 0.06 | J118: 0.08 | K118: 0.05 | L118: 0.05 | M118: =AVERAGE(C118:K118) -> 0.063333333 | N118: =+AVERAGE(H118:L118) -> 0.06
B119: =+B115 -> %growth | D119: =+D120/C120-1 -> 0.0062115071 | E119: =+E120/D120-1 -> 0.039593687 | F119: =+F120/E120-1 -> 0.14225327 | G119: =+G120/F120-1 -> 0.03512688 | H119: =+H120/G120-1 -> 0.089547157 | I119: =+I120/H120-1 -> -0.26839844 | J119: =+J120/I120-1 -> 0.67455105 | K119: =+K120/J120-1 -> -0.23422753 | L119: =+L120/K120-1 -> 0.21884108 | M119: =AVERAGE(C119:L119) -> 0.078166519 | N119: =+AVERAGE(H119:L119) -> 0.096062665
B120: =+B116 -> Value | C120: =+C118*'Fin. Data'!K5 -> 1139.82 | D120: =+D118*'Fin. Data'!J5 -> 1146.9 | E120: =+E118*'Fin. Data'!I5 -> 1192.31 | F120: =+F118*'Fin. Data'!H5 -> 1361.92 | G120: =+G118*'Fin. Data'!G5 -> 1409.76 | H120: =+H118*'Fin. Data'!F5 -> 1536 | I120: =+I118*'Fin. Data'!E5 -> 1123.74 | J120: =+J118*'Fin. Data'!D5 -> 1881.76 | K120: =+K118*'Fin. Data'!C5 -> 1441 | L120: =+L118*'Fin. Data'!B5 -> 1756.35
B122: Truck activity
D123: =D125/C125-1 -> 0.037339896 | E123: =E125/D125-1 -> 0.026864196 | F123: =F125/E125-1 -> 0.041841191 | G123: =G125/F125-1 -> 0.054202522 | H123: =H125/G125-1 -> 0.041295302 | I123: =I125/H125-1 -> -0.014990078 | J123: =J125/I125-1 -> 0.10705395 | K123: =K125/J125-1 -> 0.091126404 | L123: =L125/K125-1 -> -1
C124: 2014 | D124: 2015 | E124: 2016 | F124: 2017 | G124: 2018 | H124: 2019 | I124: 2020 | J124: 2021 | K124: 2022 | L124: 2023
B125: US GDP (Millions) | C125: =17550680174000/10^6 -> 17550680 | D125: =18206020741000/10^6 -> 18206021 | E125: =18695110842000/10^6 -> 18695111 | F125: =19477336549000/10^6 -> 19477337 | G125: =20533057312000/10^6 -> 20533057 | H125: =21380976119000/10^6 -> 21380976 | I125: =21060473613000/10^6 -> 21060474 | J125: =23315080560000/10^6 -> 23315081 | K125: =25439700000000/10^6 -> 25439700 | N125: Correl GDP Selected/Truck sales | O125: =CORREL(C128:K128,C127:K127) -> 0.72871298 | P125: United States | Q125: =Segments!B5/(Segments!B5+Segments!B6) -> 0.68308741
B126: EU GDP (Millions) | C126: =12215765.1 -> 12215765 | D126: 12548314 | E126: 13075680 | F126: 13534336 | G126: 14019674 | H126: 13471033 | I126: 14639398 | J126: 15919177 | K126: 16962391 | N126: Average | O126: =+AVERAGE(D129:L129) -> -0.06818405 | P126: Europe | Q126: =Segments!B6/(Segments!B5+Segments!B6) -> 0.31691259
B127: Truck Sales | C127: =+C112 -> 14627.69 | D127: =+D112 -> 14718.55 | E127: =+E112 -> 12774.75 | F127: =+F112 -> 14786.56 | G127: =+G112 -> 18091.92 | H127: =+H112 -> 19968 | I127: =+I112 -> 14608.62 | J127: =+J112 -> 16465.4 | ... L127: =+L112 -> 27047.79 | N127: Average Pre-covid | O127: =+AVERAGE(D129:I129,K129:L129) -> -0.090788776
B128: Weighted GDP | C128: =C125*$Q$125+(C126*1)*$Q$126 -> 15859978 | D128: =D125*$Q$125+(D126*1)*$Q$126 -> 16413022 | E128: =E125*$Q$125+(E126*1)*$Q$126 -> 16914242 | F128: =F125*$Q$125+(F126*1)*$Q$126 -> 17593925 | G128: =G125*$Q$125+(G126*1.179468)*$Q$126 -> 19266262 | H128: =H125*$Q$125+(H126*1.11914)*$Q$126 -> 19382841 | I128: =I125*$Q$125+(I126*1.139744)*$Q$126 -> 19673884 | J128: =J125*$Q$125+(J126*1.18216)*$Q$126 -> 21890220 | K128: =K125*$Q$125+(K126*1.051142)*$Q$126 -> 23028053 | L128: =L125*$Q$125+(L126*1.081121)*$Q$126 -> 0
B129: %Growth | D129: =D128/C128-1 -> 0.03487041 | E129: =E128/D128-1 -> 0.030537942 | F129: =F128/E128-1 -> 0.040184038 | G129: =G128/F128-1 -> 0.095051984 | H129: =H128/G128-1 -> 0.0060509159 | I129: =I128/H128-1 -> 0.015015484 | J129: =J128/I128-1 -> 0.11265375 | K129: =K128/J128-1 -> 0.051979018 | L129: =L128/K128-1 -> -1
D131: =D140 -> 104691.82 | E131: =E140 -> 102522.26 | F131: =F140 -> 102160.86 | G131: =G140 -> 99730.673 | H131: =H140 -> 98409.922 | I131: =I140 -> 95754.808 | J131: =J140 -> 95043.147 | K131: =K140 -> 92805.085 | ... AU131: =AU140 -> 148438.02 | AV131: =$U$201*AV133+$V$201 -> 128240.9 | AW131: =$U$201*AW133+$V$201 -> 129221.52 | AX131: =$U$201*AX133+$V$201 -> 130202.14 | AY131: =$U$201*AY133+$V$201 -> 131182.76 | AZ131: =$U$201*AZ133+$V$201 -> 132163.38 | BA131: =$U$201*BA133+$V$201 -> 133144 | BB131: =$U$201*BB133+$V$201 -> 134124.62 | BC131: =$U$201*BC133+$V$201 -> 135105.24 | ... EQ131: =$U$201*EQ133+$V$201 -> 225322.28
AS132: 1 | AT132: 2 | AU132: 3 | AV132: 4 | AW132: 5 | AX132: 6 | AY132: 7 | AZ132: 8 | BA132: 9 | BB132: 10 | BC132: 11 | BD132: 12 | BE132: 1 | BF132: 2 | BG132: 3 | BH132: 4 | BI132: 5 | BJ132: 6 | BK132: 7 | BL132: 8 | BM132: 9 | BN132: 10 | BO132: 11 | BP132: 12 | BQ132: 1 | BR132: 2 | BS132: 3 | BT132: 4 | BU132: 5 | BV132: 6 | BW132: 7 | BX132: 8 | BY132: 9 | BZ132: 10 | CA132: 11 | CB132: 12 | CC132: 1 | CD132: 2 | CE132: 3 | CF132: 4 | CG132: 5 | CH132: 6 | CI132: 7 | CJ132: 8 | CK132: 9 | CL132: 10 | CM132: 11 | CN132: 12 | CO132: 1 | CP132: 2 | CQ132: 3 | CR132: 4 | CS132: 5 | CT132: 6 | CU132: 7 | CV132: 8 | CW132: 9 | CX132: 10 | CY132: 11 | CZ132: 12 | DA132: 1 | DB132: 2 | DC132: 3 | DD132: 4 | DE132: 5 | DF132: 6 | DG132: 7 | DH132: 8 | DI132: 9 | DJ132: 10 | DK132: 11 | DL132: 12 | DM132: 1 | DN132: 2 | DO132: 3 | DP132: 4 | DQ132: 5 | DR132: 6 | DS132: 7 | DT132: 8 | DU132: 9 | DV132: 10 | DW132: 11 | DX132: 12 | DY132: 1 | DZ132: 2 | EA132: 3 | EB132: 4 | EC132: 5 | ED132: 6 | EE132: 7 | EF132: 8 | EG132: 9 | EH132: 10 | EI132: 11 | EJ132: 12 | EK132: 1 | EL132: 2 | EM132: 3 | EN132: 4 | EO132: 5 | EP132: 6 | EQ132: 7
D133: 1 | E133: 2 | F133: 3 | G133: 4 | H133: 5 | I133: 6 | J133: 7 | K133: 8 | L133: 9 | M133: 10 | N133: 11 | O133: 12 | P133: 13 | Q133: 14 | R133: 15 | S133: 16 | T133: 17 | U133: 18 | V133: 19 | W133: 20 | X133: 21 | Y133: 22 | Z133: 23 | AA133: 24 | AB133: 25 | AC133: 26 | AD133: 27 | AE133: 28 | AF133: 29 | AG133: 30 | AH133: 31 | AI133: 32 | AJ133: 33 | AK133: 34 | AL133: 35 | AM133: 36 | AN133: 37 | AO133: 38 | AP133: 39 | AQ133: 40 | AR133: 41 | AS133: 42 | AT133: 43 | AU133: 44 | AV133: 45 | AW133: 46 | AX133: 47 | AY133: 48 | AZ133: 49 | BA133: 50 | BB133: 51 | BC133: 52 | BD133: 53 | BE133: 54 | BF133: 55 | BG133: 56 | BH133: 57 | BI133: 58 | BJ133: 59 | BK133: 60 | BL133: 61 | BM133: 62 | BN133: 63 | BO133: 64 | BP133: 65 | BQ133: 66 | BR133: 67 | BS133: 68 | BT133: 69 | BU133: 70 | BV133: 71 | BW133: 72 | BX133: 73 | BY133: 74 | BZ133: 75 | CA133: 76 | CB133: 77 | CC133: 78 | CD133: 79 | CE133: 80 | CF133: 81 | CG133: 82 | CH133: 83 | CI133: 84 | CJ133: 85 | CK133: 86 | CL133: 87 | CM133: 88 | CN133: 89 | CO133: 90 | CP133: 91 | CQ133: 92 | CR133: 93 | CS133: 94 | CT133: 95 | CU133: 96 | CV133: 97 | CW133: 98 | CX133: 99 | CY133: 100 | CZ133: 101 | DA133: 102 | DB133: 103 | DC133: 104 | DD133: 105 | DE133: 106 | DF133: 107 | DG133: 108 | DH133: 109 | DI133: 110 | DJ133: 111 | DK133: 112 | DL133: 113 | DM133: 114 | DN133: 115 | DO133: 116 | DP133: 117 | DQ133: 118 | DR133: 119 | DS133: 120 | DT133: 121 | DU133: 122 | DV133: 123 | DW133: 124 | DX133: 125 | DY133: 126 | DZ133: 127 | EA133: 128 | EB133: 129 | EC133: 130 | ED133: 131 | EE133: 132 | EF133: 133 | EG133: 134 | EH133: 135 | EI133: 136 | EJ133: 137 | EK133: 138 | EL133: 139 | EM133: 140 | EN133: 141 | EO133: 142 | EP133: 143 | EQ133: 144
B134: New Truck Deliveries | C134: Units | D134: Q1 2014 | E134: Q2 2014 | F134: Q3 2014 | G134: Q4 2014 | H134: Q1 2015 | I134: Q2 2015 | J134: Q3 2015 | K134: Q4 2015 | L134: Q1 2016 | M134: Q2 2016 | N134: Q3 2016 | O134: Q4 2016 | P134: Q1 2017 | Q134: Q2 2017 | R134: Q3 2017 | S134: Q4 2017 | T134: Q1 2018 | U134: Q2 2018 | V134: Q3 2018 | W134: Q4 2018 | X134: Q1 2019 | Y134: Q2 2019 | Z134: Q3 2019 | AA134: Q4 2019 | AB134: Q1 2020 | AC134: Q2 2020 | AD134: Q3 2020 | AE134: Q4 2020 | AF134: Q1 2021 | AG134: Q2 2021 | AH134: Q3 2021 | AI134: Q4 2021 | AJ134: Q1 2022 | AK134: Q2 2022 | AL134: Q3 2022 | AM134: Q4 2022 | AN134: Q1 2023 | AO134: Q2 2023 | AP134: Q3 2023 | AQ134: Q4 2023 | AR134: Q1 2024 | AS134: Q2 2024 | AT134: Q3 2024 | AU134: Q4 2024 | AV134: Q1 2025 | AW134: Q2 2025 | AX134: Q3 2025 | AY134: Q4 2025 | AZ134: Q1 2026 | BA134: Q2 2026 | BB134: Q3 2026 | BC134: Q4 2026 | BD134: Q1 2027 | BE134: Q2 2027 | BF134: Q3 2027 | BG134: Q4 2027 | BH134: Q1 2028 | BI134: Q2 2028 | BJ134: Q3 2028 | BK134: Q4 2028 | BL134: Q1 2029 | BM134: Q2 2029 | BN134: Q3 2029 | BO134: Q4 2029 | BP134: Q1 2030 | BQ134: Q2 2030 | BR134: Q3 2030 | BS134: Q4 2030 | BT134: Q1 2031 | BU134: Q2 2031 | BV134: Q3 2031 | BW134: Q4 2031 | BX134: Q1 2032 | BY134: Q2 2032 | BZ134: Q3 2032 | CA134: Q4 2032 | CB134: Q1 2033 | CC134: Q2 2033 | CD134: Q3 2033 | CE134: Q4 2033 | CF134: Q1 2034 | CG134: Q2 2034 | CH134: Q3 2034 | CI134: Q4 2034 | CJ134: Q1 2035 | CK134: Q2 2035 | CL134: Q3 2035 | CM134: Q4 2035 | CN134: Q1 2036 | CO134: Q2 2036 | CP134: Q3 2036 | CQ134: Q4 2036 | CR134: Q1 2037 | CS134: Q2 2037 | CT134: Q3 2037 | CU134: Q4 2037 | CV134: Q1 2038 | CW134: Q2 2038 | CX134: Q3 2038 | CY134: Q4 2038 | CZ134: Q1 2039 | DA134: Q2 2039 | DB134: Q3 2039 | DC134: Q4 2039 | DD134: Q1 2040 | DE134: Q2 2040 | DF134: Q3 2040 | DG134: Q4 2040 | DH134: Q1 2041 | DI134: Q2 2041 | DJ134: Q3 2041 | DK134: Q4 2041 | DL134: Q1 2042 | DM134: Q2 2042 | DN134: Q3 2042 | DO134: Q4 2042 | DP134: Q1 2043 | DQ134: Q2 2043 | DR134: Q3 2043 | DS134: Q4 2043 | DT134: Q1 2044 | DU134: Q2 2044 | DV134: Q3 2044 | DW134: Q4 2044 | DX134: Q1 2045 | DY134: Q2 2045 | DZ134: Q3 2045 | EA134: Q4 2045 | EB134: Q1 2046 | EC134: Q2 2046 | ED134: Q3 2046 | EE134: Q4 2046 | EF134: Q1 2047 | EG134: Q2 2047 | EH134: Q3 2047 | EI134: Q4 2047 | EJ134: Q1 2048 | EK134: Q2 2048 | EL134: Q3 2048 | EM134: Q4 2048 | EN134: Q1 2049 | EO134: Q2 2049 | EP134: Q3 2049 | EQ134: Q4 2049
B135: United States and Canada | C135: units | D135: =39100-E135 -> 18600 | E135: 20500 | F135: 23500 | G135: 22200 | H135: 24400 | I135: 26800 | J135: 24200 | K135: 15900 | L135: 18500 | M135: 19800 | N135: 18800 | O135: 14400 | P135: 17000 | Q135: 21200 | R135: 23300 | S135: 22700 | T135: 24200 | U135: 25900 | V135: 28400 | W135: 26800 | X135: 28900 | Y135: 30000 | Z135: 31700 | AA135: 26600 | AB135: 22200 | AC135: 9300 | AD135: 20700 | AE135: 21100 | AF135: 23000 | AG135: 22600 | AH135: 17200 | AI135: 23500 | AJ135: 20700 | AK135: 24400 | AL135: 24400 | AM135: 26100 | AN135: 26000 | AO135: 27500 | AP135: 27500 | AQ135: 28100 | AR135: 29500
B136: Europe | C136: units | D136: =18200-E136 -> 9300 | E136: 8900 | F136: 9200 | G136: 12100 | H136: 10100 | I136: 11200 | J136: 11100 | K136: 15000 | L136: 13500 | M136: 13100 | N136: 11600 | O136: 14800 | P136: 14300 | Q136: 13800 | R136: 12400 | S136: 16600 | T136: 15700 | U136: 15800 | V136: 14300 | W136: 18000 | X136: 16900 | Y136: 15700 | Z136: 12700 | AA136: 14600 | AB136: 11600 | AC136: 6400 | AD136: 10500 | AE136: 14400 | AF136: 13700 | AG136: 11800 | AH136: 9700 | AI136: 18000 | AJ136: 16100 | AK136: 15400 | AL136: 13300 | AM136: 14900 | AN136: 17400 | AO136: 16400 | AP136: 14500 | AQ136: 14900 | AR136: 11600
B137: Other | C137: units | D137: =8200-E137 -> 3900 | E137: 4300 | F137: 4600 | G137: 5800 | H137: 3800 | I137: 3600 | J137: 4100 | K137: 4500 | L137: 3300 | M137: 3900 | N137: 4500 | O137: 4700 | P137: 3700 | Q137: 4400 | R137: 4500 | S137: 5000 | T137: 4600 | U137: 4700 | V137: 5100 | W137: 5600 | X137: 5700 | Y137: 6600 | Z137: 4900 | AA137: 4500 | AB137: 4600 | AC137: 2400 | AD137: 4800 | AE137: 5300 | AF137: 5500 | AG137: 5700 | AH137: 5900 | AI137: 6100 | AJ137: 6200 | AK137: 7100 | AL137: 6700 | AM137: 8100 | AN137: 7700 | AO137: 8000 | AP137: 8100 | AQ137: 8100 | AR137: 7000
B138: TOTAL TRUCK DELIVERIES | C138: units | D138: =SUM(D135:D137) -> 31800 | E138: =SUM(E135:E137) -> 33700 | F138: =SUM(F135:F137) -> 37300 | G138: =SUM(G135:G137) -> 40100 | H138: =SUM(H135:H137) -> 38300 | I138: =SUM(I135:I137) -> 41600 | J138: =SUM(J135:J137) -> 39400 | K138: =SUM(K135:K137) -> 35400 | ... AR138: =SUM(AR135:AR137) -> 48100 | AS138: 48000 | AT138: 48300 | AU138: 48300 | AV138: =AU138*(1+AV144) -> 47194.115 | AW138: =AV138*(1+AW144) -> 49443.378 | AX138: =AW138*(1+AX144) -> 48871.308 | AY138: =AX138*(1+AY144) -> 50431.939 | AZ138: =AY138*(1+AZ144) -> 49277.24 | BA138: =AZ138*(1+BA144) -> 51625.784 | BB138: =BA138*(1+BB144) -> 51028.464 | BC138: =BB138*(1+BC144) -> 52657.98 | ... EQ138: =EP138*(1+EQ144) -> 127118.63
B139: Trucks Revenue (Millions) | C139: USD | D139: 3329.2 | E139: 3455 | F139: 3810.6 | G139: 3999.2 | H139: 3769.1 | I139: 3983.4 | J139: 3744.7 | K139: 3285.3 | L139: 3270.5 | M139: 3341.2 | N139: 3170.7 | O139: 2984.9 | P139: 3130.1 | Q139: 3553.6 | R139: 3867.4 | S139: 4223.7 | T139: 4353 | U139: 4467.8 | V139: 4429.4 | W139: 4936.8 | X139: 5107.3 | Y139: 5211.9 | Z139: 4977.4 | AA139: 4692.9 | AB139: 3757.6 | AC139: 1858.4 | AD139: 3504 | AE139: 4044.8 | AF139: 4233 | AG139: 4152.2 | AH139: 3452.6 | AI139: 4961.9 | AJ139: 4697.1 | AK139: 5336.4 | AL139: 5198.2 | AM139: 6254.5 | AN139: 6413.8 | AO139: 6827.5 | AP139: 6636.4 | AQ139: 6968.7 | AR139: 6541 | AS139: =E103 -> 6447.0829 | AT139: =F103 -> 6640.2147 | AU139: =G103 -> 7169.5566 | AV139: =AV138*AV140/10^6 -> 7138.1099 | AW139: =AW138*AW140/10^6 -> 7490.6717 | AX139: =AX138*AX140/10^6 -> 7416.221 | AY139: =AY138*AY140/10^6 -> 7665.6547 | AZ139: =AZ138*AZ140/10^6 -> 7502.4598 | BA139: =BA138*BA140/10^6 -> 7872.9321 | BB139: =BB138*BB140/10^6 -> 7794.5979 | BC139: =BC138*BC140/10^6 -> 8056.6709 | ... EQ139: =EQ138*EQ140/10^6 -> 28642.66
B140: Average Price Per Truck | C140: USD | D140: =D139*10^6/D138 -> 104691.82 | E140: =E139*10^6/E138 -> 102522.26 | F140: =F139*10^6/F138 -> 102160.86 | G140: =G139*10^6/G138 -> 99730.673 | H140: =H139*10^6/H138 -> 98409.922 | I140: =I139*10^6/I138 -> 95754.808 | J140: =J139*10^6/J138 -> 95043.147 | K140: =K139*10^6/K138 -> 92805.085 | ... AU140: =AU139*10^6/AU138 -> 148438.02 | AV140: =$U$202*AV133+$V$202 -> 151250 | AW140: =$U$202*AW133+$V$202 -> 151500 | AX140: =$U$202*AX133+$V$202 -> 151750 | AY140: =$U$202*AY133+$V$202 -> 152000 | AZ140: =$U$202*AZ133+$V$202 -> 152250 | BA140: =$U$202*BA133+$V$202 -> 152500 | BB140: =$U$202*BB133+$V$202 -> 152750 | BC140: =$U$202*BC133+$V$202 -> 153000 | BD140: =$U$202*BD133+$V$202 -> 153250 | BE140: =$U$203*BE133+$V$203 -> 153800 | BF140: =$U$203*BF133+$V$203 -> 153500 | BG140: =$U$203*BG133+$V$203 -> 153200 | BH140: =$U$203*BH133+$V$203 -> 152900 | BI140: =$U$203*BI133+$V$203 -> 152600 | BJ140: =$U$203*BJ133+$V$203 -> 152300 | BK140: =$U$203*BK133+$V$203 -> 152000 | BL140: =$U$203*BL133+$V$203 -> 151700 | ... BP140: =$U$203*BP133+$V$203 -> 150500 | BQ140: =$U$204*BQ133+$V$204 -> 147200 | BR140: =$U$204*BR133+$V$204 -> 146400 | BS140: =$U$204*BS133+$V$204 -> 145600 | BT140: =$U$204*BT133+$V$204 -> 144800 | BU140: =$U$204*BU133+$V$204 -> 144000 | BV140: =$U$204*BV133+$V$204 -> 143200 | BW140: =$U$204*BW133+$V$204 -> 142400 | BX140: =$U$204*BX133+$V$204 -> 141600 | ... CB140: =$U$204*CB133+$V$204 -> 138400 | CC140: =$U$205*CC133+$V$205 -> 140000 | CD140: =$U$205*CD133+$V$205 -> 142500 | CE140: =$U$205*CE133+$V$205 -> 145000 | CF140: =$U$205*CF133+$V$205 -> 147500 | CG140: =$U$205*CG133+$V$205 -> 150000 | CH140: =$U$205*CH133+$V$205 -> 152500 | CI140: =$U$205*CI133+$V$205 -> 155000 | CJ140: =$U$205*CJ133+$V$205 -> 157500 | ... CN140: =$U$205*CN133+$V$205 -> 167500 | CO140: =$U$206*CO133+$V$206 -> 170000 | CP140: =$U$206*CP133+$V$206 -> 175000 | CQ140: =$U$206*CQ133+$V$206 -> 180000 | CR140: =$U$206*CR133+$V$206 -> 185000 | CS140: =$U$206*CS133+$V$206 -> 190000 | CT140: =$U$206*CT133+$V$206 -> 195000 | CU140: =$U$206*CU133+$V$206 -> 200000 | CV140: =$U$206*CV133+$V$206 -> 205000 | ... CZ140: =$U$206*CZ133+$V$206 -> 225000 | DA140: =$U$207*DA133+$V$207 -> 224000 | DB140: =$U$207*DB133+$V$207 -> 221000 | DC140: =$U$207*DC133+$V$207 -> 218000 | DD140: =$U$207*DD133+$V$207 -> 215000 | DE140: =$U$207*DE133+$V$207 -> 212000 | DF140: =$U$207*DF133+$V$207 -> 209000 | DG140: =$U$207*DG133+$V$207 -> 206000 | DH140: =$U$207*DH133+$V$207 -> 203000 | ... DL140: =$U$207*DL133+$V$207 -> 191000 | DM140: =$U$208*DM133+$V$208 -> 188200 | DN140: =$U$208*DN133+$V$208 -> 187000 | DO140: =$U$208*DO133+$V$208 -> 185800 | DP140: =$U$208*DP133+$V$208 -> 184600 | DQ140: =$U$208*DQ133+$V$208 -> 183400 | DR140: =$U$208*DR133+$V$208 -> 182200 | DS140: =$U$208*DS133+$V$208 -> 181000 | DT140: =$U$208*DT133+$V$208 -> 179800 | ... DX140: =$U$208*DX133+$V$208 -> 175000 | DY140: =$U$209*DY133+$V$209 -> 181000 | DZ140: =$U$209*DZ133+$V$209 -> 184500 | EA140: =$U$209*EA133+$V$209 -> 188000 | EB140: =$U$209*EB133+$V$209 -> 191500 | EC140: =$U$209*EC133+$V$209 -> 195000 | ED140: =$U$209*ED133+$V$209 -> 198500 | EE140: =$U$209*EE133+$V$209 -> 202000 | EF140: =$U$209*EF133+$V$209 -> 205500 | ... EJ140: =$U$209*EJ133+$V$209 -> 219500 | EK140: =$U$210*EK133+$V$210 -> 219438.56 | EL140: =$U$210*EL133+$V$210 -> 220419.18 | EM140: =$U$210*EM133+$V$210 -> 221399.8 | EN140: =$U$210*EN133+$V$210 -> 222380.42 | EO140: =$U$210*EO133+$V$210 -> 223361.04 | EP140: =$U$210*EP133+$V$210 -> 224341.66 | EQ140: =$U$210*EQ133+$V$210 -> 225322.28
D143: 2014 | H143: 2015 | L143: 2016 | P143: 2017 | T143: 2018 | X143: 2019 | AB143: 2020 | AF143: 2021 | AJ143: 2022 | AN143: 2023 | AR143: 2024 | AV143: 2025 | AZ143: 2026 | BD143: 2027 | BH143: 2028 | BL143: 2029 | BP143: 2030 | BT143: 2031 | BX143: 2032 | CB143: 2033 | CF143: 2034 | CJ143: 2035 | CN143: 2036 | CR143: 2037 | CV143: 2038 | CZ143: 2039 | DD143: 2040 | DH143: 2041 | DL143: 2042 | DP143: 2043 | DT143: 2044 | DX143: 2045 | EB143: 2046 | EF143: 2047 | EJ143: 2048 | EN143: 2049
