Workbook
Name Sectors: '[1]Sector Impact'!$K$4:$K$16
Name Sectors: 'Sector Impact'!$K$4:$K$16

Sheet OP
B2: 45390 | C2: Team 12 | D2: 26th April, 2024 | E2: ='Inputs (AUD)'!H3 -> #VALUE! | L2: {=_FV(E2,"Exchange abbreviation",TRUE)} -> XASX | M2: SIC:
D3: COMPANY DESCRIPTION | H3: CEO & BOARD OF DIRECTORS
D4: Pilbara Minerals Limited is an Australia-based lithium company, The Company is primarily engaged in the exploration, development, and mining of minerals in Australia, Its 100% owned Pilgangoora hard-rock lithium operation consists of two processing plants: the Pilgan Plant, located on the northern side and produces spodumene and tantalite concentrates, and the Ngungaju Plant is located to the south produces spodumene concentrate, It owns 70% of the Mt Francisco project, and hosts the large occurrence of outcropping pegmatites, It is also pursuing a proposed downstream joint venture (JV) for the development of an approximately 43,000 tons per annum (tpa) lithium carbonate equivalent (LCE) lithium chemical conversion facility in South Korea, | H4: Name (Sex;Age) | I4: Tenure | J4: Executive? | K4: Other roles
H5: Dale Henderson (M;?) | I5: 2 years | J5: YES | K5: Chief Executive Officer of Pilbara Minerals
H6: Kathleen Conlon (F;?) | I6: 2 months | J6: NO | K6: Non-Executive Director of Aristocrat Leisure Limited and BlueScope Steel Limited, and Chairs the Corporate Governance Committee of the Australian Institute of Company Directors | P6: {=_FV(E2,"Description")} -> Pilbara Minerals Limited is an Australia-based lithium company. The Company is primarily engaged in the exploration, development, and mining of minerals in Australia. Its 100% owned Pilgangoora hard-rock lithium operation is located approximately 120 kilometers (kms) from Port Hedland in Western Australia’s resource-rich Pilbara region. The operation consists of two processing plants: the Pilgan Plant, located on the northern side of the Pilgangoora area and produces spodumene and tantalite concentrates, and the Ngungaju Plant is located to the south produces spodumene concentrate. It owns 70% of the Mt Francisco project, which is located 50 km south-west of the Pilgangoora Project and hosts the large occurrence of outcropping pegmatites located nearby to Port Hedland. It is also pursuing a proposed downstream joint venture (JV) for the development of an approximately 43,000 tons per annum (tpa) lithium carbonate equivalent (LCE) lithium chemical conversion facility in South Korea.
H7: Sally-Anne Layman (F;?) | I7: 6 years | J7: NO | K7: Non-Executive Director of IMDEX Ltd, Beach Energy Ltd and Newmount Corporation.
H8: Nick Cernotta (M;?) | I8: 7 years | J8: NO | K8: Non-Executive Chair of Panoramic Resources Limited and a Non-Executive Director of Northern Star Resources Limited and New Century Resources. Limited
H9: Steve Scudamore (M;?) | I9: 8 years | J9: NO | K9: Vice Chair of the Western Australian Museum and WA Committee Chair of the Australian British Chamber of Commerce and member of the National Board
H10: Miriam Stanborough (F;?) | I10: 2 years | J10: NO | K10: Chair of the Minerals Research Institute of Western Australia (MRIWA), Deputy Chair of the Northern Agricultural Catchments Council (NACC), and Deputy Chair of Scouts | O10: https://www,marketscreener,com/quote/stock/PILBARA-MINERALS-LIMITED-10354122/company/
H11: EXECUTIVE LEADERSHIP TEAM
H12: =H5 -> Dale Henderson (M;?) | I12: =I5 -> 2 years | J12: =J5 -> YES | K12: =K5 -> Chief Executive Officer of Pilbara Minerals
H13: Vince De Carolis (M;?) | I13: 1 year | J13: YES | K13: Chief Operating Officer
H14: Luke Bortoli (M;?) | I14: 1 year | J14: YES | K14: Chief Financial Officer
H15: Sandra McInnes (F;?) | I15: 1 year | J15: YES | K15: Chief Sustainability Officer
H16: John Stanning (M;?) | I16: 1 year | J16: YES | K16: Chief Development Officer
H17: Paul Laybourne (M;?) | I17: 1 year | J17: YES | K17: Project Director
B18: {=_FV(E2,"Currency")&" MILLIONS"} -> AUD MILLIONS | H18: Jen Mintz (F;?) | I18: 1 month | J18: YES | K18: General Counsel
B19: COMPANY OVERVIEW
B20: Stock | D20: Liquidity and Solvency | F20: Segments | I20: Profitability (2023) | L20: Multiples
B21: Last Price | C21: {=_FV(E2,"Price")} -> 3.13 | D21: Total Assets | E21: =_xlfn.XLOOKUP(D21,'Fin. Data'!A:A,'Fin. Data'!B:B,,0) -> 5198.8 | F21: Regions | H21: % Sales | I21: Reporting Year | J21: 2023 | L21: Float | M21: ='Inputs (AUD)'!B82 -> 0.9037
B22: Outstanding Shares | C22: {=_FV(E2,"Shares outstanding",TRUE)} -> 3011485000 | D22: Total Liabilities | E22: =_xlfn.XLOOKUP(D22,'Fin. Data'!A:A,'Fin. Data'!B:B,,0) -> 1808.8 | F22: =Segments!C5 -> Pilgan | H22: =Segments!B5 -> 0.69622735 | I22: End of Year | J22: 45107 | L22: Insiders Own | M22: ='Inputs (AUD)'!B83 -> 0.0963
B23: Market Cap. | C23: =C21*C22/1000000 -> 9425.9481 | D23: Cash/Share | E23: =_xlfn.XLOOKUP("Cash & Eq.",'Fin. Data'!A:A,'Fin. Data'!B:B,,0)*1000000/C22 -> 1.1086225 | F23: =Segments!C6 -> Ngungaju | H23: =Segments!B6 -> 0.36616828 | I23: EBITDA | K23: =_xlfn.XLOOKUP(I23,'Fin. Data'!A:A,'Fin. Data'!B:B,,0) -> 3098.7 | L23: b (Yahoo) | M23: {=_FV(E2,"Beta")} -> 2.0207
B24: +Total Debt | C24: ='Fin. Data'!B58 -> 472 | D24: EBITDA/Net Financial Cost (NFC) | E24: =_xlfn.XLOOKUP("EBITDA",'Fin. Data'!A:A,'Fin. Data'!B:B,,0)/_xlfn.XLOOKUP("Net Financial Cost",'Fin. Data'!A:A,'Fin. Data'!B:B,,0) -> 69.013363 | F24: =Segments!C7 -> (elimination of by-product) | H24: =Segments!B7 -> -0.00050762558 | I24: Depreciation & Amortization | K24: =_xlfn.XLOOKUP(I24,'Fin. Data'!A:A,'Fin. Data'!B:B,,0) -> 1.5 | L24: Score (S&P) | M24: ='Inputs (AUD)'!B84 -> None
B25: -Cash | C25: ='Fin. Data'!B39 -> 3338.6 | D25: Debt/EBITDA | E25: =_xlfn.XLOOKUP("Total Debt",'Fin. Data'!A:A,'Fin. Data'!B:B,,0)/_xlfn.XLOOKUP("EBITDA",'Fin. Data'!A:A,'Fin. Data'!B:B,,0) -> 0.15232194 | F25: =Segments!C8 -> (provisional price adjustment) | H25: =Segments!B8 -> -0.061659653 | I25: EBIT | K25: =_xlfn.XLOOKUP(I25,'Fin. Data'!A:A,'Fin. Data'!B:B,,0) -> 3097.2 | L25: Price/Book Value | M25: =IFERROR((C21*C22/(E21-E22))/1000000,"") -> 2.7805156
B26: =Enterprise Value | C26: =C23+C24-C25 -> 6559.3481 | D26: "Others Assets"/Asset | E26: =_xlfn.XLOOKUP("Other Assets",'Fin. Data'!A:A,'Fin. Data'!B:B,,0)/_xlfn.XLOOKUP("Total Assets",'Fin. Data'!A:A,'Fin. Data'!B:B,,0) -> 0.01521505 | F26: =Segments!C9 -> (hedge close-outs) | H26: =Segments!B9 -> -0.00022834539 | I26: Net Income | K26: =_xlfn.XLOOKUP(I26,'Fin. Data'!A:A,'Fin. Data'!B:B,,0) -> 2391.1 | L26: NCF(3y avg)/Asset | M26: =IFERROR(K32/E21,"") -> 0.20305968
B27: Holdings (nac/int'l) | C27: - | D27: Debt/Assets | E27: =_xlfn.XLOOKUP(D27,'Fin. Data'!A:A,'Fin. Data'!B:B,,0) -> 0.090790182 | F27: Categories | H27: % Sales | I27: EPS | K27: =1000000*K26/C22 -> 0.79399366 | L27: Price/Net Inc. (3y avg) | M27: =IFERROR(C23/K31,"") -> 9.7459397
B28: t liq. (Holdings/Vol.) | C28: - | D28: EBITDA Margin (average) | E28: =AVERAGE(_xlfn.XLOOKUP("EBITDA Margin",'Fin. Data'!A:A,'Fin. Data'!B:D,,0)) -> 0.39491807 | F28: =Segments!C15 -> Spodumene | H28: =Segments!B15 -> 1.061888 | I28: ROA | K28: =K26/E21 -> 0.45993306 | L28: EV/Asset | M28: =IFERROR(C26/E21,"") -> 1.2617042
B29: % Short | C29: N/A | D29: Operating Margin (average) | E29: =AVERAGE(_xlfn.XLOOKUP("Operating Margin",'Fin. Data'!A:A,'Fin. Data'!B:D,,0)) -> 0.40216289 | F29: =Segments!C16 -> Tantalite | H29: =Segments!B16 -> 0.00050762558 | I29: ROIC | K29: =K26/(E21-(E22-C24)) -> 0.61913516 | L29: EV/Ebitda (3y average) | M29: =IFERROR(C26/K30,"") -> 5.1886735
B30: Traffic ESG | D30: Net Income Margin (average) | E30: =AVERAGE(_xlfn.XLOOKUP("Net Income Margin",'Fin. Data'!A:A,'Fin. Data'!B:D,,0)) -> 0.25608103 | F30: =Segments!C17 -> (elimination of by-product) | H30: =Segments!B17 -> -0.00050762558 | I30: EBITDA (3y average) | K30: =AVERAGE(_xlfn.XLOOKUP("EBITDA",'Fin. Data'!A:A,'Fin. Data'!B:D,,0)) -> 1264.1667 | L30: Price/NCF (3y average) | M30: =IFERROR(C23/K32,"") -> 8.9289056
B31: E | F31: =Segments!C18 -> (provisional price adjustment) | H31: =Segments!B18 -> -0.061659653 | I31: Net Income (3y average) | K31: =AVERAGE(_xlfn.XLOOKUP("Net Income",'Fin. Data'!A:A,'Fin. Data'!B:D,,0)) -> 967.16667 | L31: Bonds 1,3,5a (USD) | M31: -
B32: S | D32: Net Financial Cost/Avg Net Debt | E32: =-_xlfn.XLOOKUP("Net Financial Cost",'Fin. Data'!A:A,'Fin. Data'!B:B,,0)/AVERAGE(_xlfn.XLOOKUP("Net Debt",'Fin. Data'!A:A,'Fin. Data'!B:D,,0)) -> 0.043464232 | F32: =Segments!C19 -> (hedge close-outs) | H32: =Segments!B19 -> -0.00022834539 | I32: NCF (3y average) | K32: =AVERAGE(_xlfn.XLOOKUP("Net Cash Flow",'Fin. Data'!A:A,'Fin. Data'!B:D,,0)) -> 1055.6667 | L32: Div+Rep.(3y avg)/Price | M32: =-IFERROR(SUM(E53:E55)/(3*C23),"") -> 0.0030164959
B33: G | L33: Div. Yield | M33: =-IFERROR(L54/C23,"") -> 0.034988523
B34: INVESTMENT THESIS
B35: Pillars of Recommendation | H35: Recommendation | I35: Valuation Assumptions
B36: Pillar | C36: Explanation | H36: HOLD | I36: Check DCF
B37: Growing Company | C37: In general mining companies have a higher than average profit margins when compared with other companies publicly traded companies. Pilbara's financials have been growing exponentially in the last years and they have been able to maintain a very health balance sheet.
B38: Government Incentives and Support | C38: Governments around the world are focused on reaching a greener atmosphere by 2030, therefore they are investing heavily and incentivesing the purchase of EV's and consequently their compontents. This government support and fiscal incentives to produce more, will come with a positive side for Pilbara and the whole market.
B39: Lithium Demand | C39: Currently the supply chain has caught up to the demand, sending the current price per ton down and lowering profit margins for all market players; However, forecasts of demand point to an increase in 2025 signaling a possible increase in revenues and subsequent growth of the companies.
B40: Risks of Investment | H40: Price Target | I40: Valuation
B41: Risk | C41: Explanation | H41: =DCF!D76 -> 4.1785239 | I41: Discount Rate | J41: =DCF!F50 -> 0.091 | L41: Price M. Upside | M41: =SARD!AJ14 -> 0.85939456
B42: Lithium Price Volatility | C42: This is a recent growing concern, where we have seen lithium prices growing as suppliers saturate the market and catch-up with demand, sending the prices plumetting; Never the less, apart from this drop in price, Pilbara has still increased their sells even though the price per ton has decreased, proving their ability to navigate the market and still find buyers.
B43: Economic Cycles | C43: There has been growing concern around the renewable energies and eletrefication of automotives, however sales of eletric vehicles have been exponentially growing for the past 10 years and more and more demand is being brought for lithium batteries. Despite all of this, recently big automotive groups like Mercedes and Ford have halted their investment for the time being in EV R&D, claming it's not opportune to explore this market yet. This return on decisions from big market players might hinder the lithium sector. | I43: Upside | J43: =DCF!D75 -> 0.33499165 | L43: EV M. Upside | M43: =SARD!AM14 -> 0.87720096
B44: Finite Mineral | C44: Altough predictions point to only having 4/5 years of mineral left, some predictions are pointing all the way to 70 years of lithium available still. This is also the case due to inovation and the possibility to recycle batteries, expanding the life cycle of the sector.
B45: FINANCIAL PERFORMANCE
B46: Year | C46: Net Sales | D46: Operating Margin | E46: Dividends + Share Buyback | F46: Net Cash Flow | G46: Debt/Assets | H46: Depreciation & Amortization | I46: Capex + Investments | J46: Cash Flow
B47: =B48-1 -> 2015 | C47: {=_xlfn.SORTBY(TRANSPOSE(_xlfn.XLOOKUP(C$46,'Fin. Data'!$A:$A,'Fin. Data'!$B:$J,,0)),$B$47:$B$55,-1)} -> 0.1 | D47: {=_xlfn.SORTBY(TRANSPOSE(_xlfn.XLOOKUP(D$46,'Fin. Data'!$A:$A,'Fin. Data'!$B:$J,,0)),$B$47:$B$55,-1)} -> -52 | E47: {=_xlfn.SORTBY(TRANSPOSE(_xlfn.XLOOKUP(E$46,'Fin. Data'!$A:$A,'Fin. Data'!$B:$J,,0)),$B$47:$B$55,-1)} -> 5.2 | F47: ='Inputs (AUD)'!K77 -> 0.9 | G47: {=_xlfn.SORTBY(TRANSPOSE(_xlfn.XLOOKUP(G$46,'Fin. Data'!$A:$A,'Fin. Data'!$B:$J,,0)),$B$47:$B$55,-1)} -> - | H47: {=_xlfn.SORTBY(TRANSPOSE(_xlfn.XLOOKUP(H$46,'Fin. Data'!$A:$A,'Fin. Data'!$B:$J,,0)),$B$47:$B$55,-1)} -> 0 | I47: {=_xlfn.SORTBY(TRANSPOSE(_xlfn.XLOOKUP(I$46,'Fin. Data'!$A:$A,'Fin. Data'!$B:$J,,0)),$B$47:$B$55,-1)} -> -1.6 | L47: =J21 -> 2023 | M47: =L47-1 -> 2022
B48: =B49-1 -> 2016 | C48: 0 | D48: - | E48: 122.7 | F48: ='Inputs (AUD)'!J77 -> 2.1 | G48: - | H48: 0.1 | I48: -6.6 | J48: Net Income | L48: =_xlfn.XLOOKUP($J48,'Fin. Data'!$A:$A,'Fin. Data'!B:B,,0) -> 2391.1 | M48: =_xlfn.XLOOKUP($J48,'Fin. Data'!$A:$A,'Fin. Data'!C:C,,0) -> 561.8 | N48: =(C48/C47)-1 -> -1 | O48: =(D48/D47)-1 -> #VALUE!
B49: =B50-1 -> 2017 | C49: 0 | D49: - | E49: 68.4 | F49: ='Inputs (AUD)'!I77 -> 96.8 | G49: 0.36968796 | H49: 0.1 | I49: -52.8 | J49: Operating CF | L49: =_xlfn.XLOOKUP($J49,'Fin. Data'!$A:$A,'Fin. Data'!B:B,,0) -> 3456.7 | M49: =_xlfn.XLOOKUP($J49,'Fin. Data'!$A:$A,'Fin. Data'!C:C,,0) -> 647.6 | N49: =(C49/C48)-1 -> #DIV/0! | O49: =(D49/D48)-1 -> #VALUE! | Q49: =F49/F48-1 -> 45.095238 | R49: =H49/H48-1 -> 0 | S49: =I49/I48-1 -> 7
B50: =B51-1 -> 2018 | C50: 10.2 | D50: -1.6568627 | E50: 156.4 | F50: ='Inputs (AUD)'!H77 -> -12.9 | G50: 0.24661654 | H50: 0.2 | I50: -214.8 | J50: Investing CF | L50: =_xlfn.XLOOKUP($J50,'Fin. Data'!$A:$A,'Fin. Data'!B:B,,0) -> -408 | M50: =_xlfn.XLOOKUP($J50,'Fin. Data'!$A:$A,'Fin. Data'!C:C,,0) -> -204.5 | N50: =(C50/C49)-1 -> #DIV/0! | O50: =(D50/D49)-1 -> #VALUE! | Q50: =F50/F49-1 -> -1.1332645 | R50: =H50/H49-1 -> 1 | S50: =I50/I49-1 -> 3.0681818
B51: =B52-1 -> 2019 | C51: 42.8 | D51: -0.43224299 | E51: 60.7 | F51: ='Inputs (AUD)'!G77 -> 32.7 | G51: 0.23870857 | H51: 0.2 | I51: -178.3 | J51: Net Capex | L51: =_xlfn.XLOOKUP($J51,'Fin. Data'!$A:$A,'Fin. Data'!B:B,,0) -> -385.5 | M51: =_xlfn.XLOOKUP($J51,'Fin. Data'!$A:$A,'Fin. Data'!C:C,,0) -> -128.3 | N51: =(C51/C50)-1 -> 3.1960784 | O51: =(D51/D50)-1 -> -0.73911962 | Q51: =F51/F50-1 -> -3.5348837 | R51: =H51/H50-1 -> 0 | S51: =I51/I50-1 -> -0.16992551
B52: =B53-1 -> 2020 | C52: 84.1 | D52: -0.85136742 | E52: 111.5 | F52: ='Inputs (AUD)'!F77 -> -56.3 | G52: 0.29278008 | H52: 0.6 | I52: -22.6 | J52: Investments & Acquisitions | L52: =_xlfn.XLOOKUP($J52,'Fin. Data'!$A:$A,'Fin. Data'!B:B,,0) -> -22.4 | M52: =_xlfn.XLOOKUP($J52,'Fin. Data'!$A:$A,'Fin. Data'!C:C,,0) -> -76.2 | N52: =(C52/C51)-1 -> 0.96495327 | O52: =(D52/D51)-1 -> 0.96965003 | Q52: =F52/F51-1 -> -2.7217125 | R52: =H52/H51-1 -> 2 | S52: =I52/I51-1 -> -0.87324734
B53: =B54-1 -> 2021 | C53: 175.8 | D53: -0.19908987 | E53: 239.7 | F53: ='Inputs (AUD)'!E77 -> 22.6 | G53: 0.17573971 | H53: 0.5 | I53: -230.8 | J53: Financing CF | L53: =_xlfn.XLOOKUP($J53,'Fin. Data'!$A:$A,'Fin. Data'!B:B,,0) -> -315.1 | M53: =_xlfn.XLOOKUP($J53,'Fin. Data'!$A:$A,'Fin. Data'!C:C,,0) -> 45.5 | N53: =(C53/C52)-1 -> 1.0903686 | O53: =(D53/D52)-1 -> -0.76615281 | Q53: =F53/F52-1 -> -1.401421 | R53: =H53/H52-1 -> -0.16666667 | S53: =I53/I52-1 -> 9.2123894
B54: =B55-1 -> 2022 | C54: 1189.6 | D54: 0.61524882 | E54: 3.6 | F54: ='Inputs (AUD)'!D$77 -> 13.5 | G54: 0.14759402 | H54: 0.7 | I54: -204.5 | J54: Dividends | L54: =_xlfn.XLOOKUP($J54,'Fin. Data'!$A:$A,'Fin. Data'!B:B,,0) -> -329.8 | M54: =_xlfn.XLOOKUP($J54,'Fin. Data'!$A:$A,'Fin. Data'!C:C,,0) -> 0 | N54: =(C54/C53)-1 -> 5.7667804 | O54: =(D54/D53)-1 -> -4.0903069 | Q54: =F54/F53-1 -> -0.40265487 | R54: =H54/H53-1 -> 0.4 | S54: =I54/I53-1 -> -0.11395147
B55: =J21 -> 2023 | C55: 4064 | D55: 0.79032972 | E55: -328.6 | F55: ='Inputs (AUD)'!C77 -> 492 | G55: 0.090790182 | H55: 1.5 | I55: -407.9 | J55: Share Buyback | L55: =_xlfn.XLOOKUP($J55,'Fin. Data'!$A:$A,'Fin. Data'!B:B,,0) -> 1.2 | M55: =_xlfn.XLOOKUP($J55,'Fin. Data'!$A:$A,'Fin. Data'!C:C,,0) -> 3.6 | N55: =(C55/C54)-1 -> 2.4162744 | O55: =(D55/D54)-1 -> 0.28456926 | Q55: =F55/F54-1 -> 35.444444 | R55: =H55/H54-1 -> 1.1428571 | S55: =I55/I54-1 -> 0.99462103
B56: Annual Growth Rate | C56: =IFERROR((C55/C47)^(1/8)-1,"") -> 2.7680722 | D56: =IFERROR((D55/D47)^(1/8)-1,"") | F56: =IFERROR((F55/F47)^(1/8)-1,"") -> 1.1989498 | H56: =IFERROR((H55/H47)^(1/8)-1,"") | J56: FX | L56: =_xlfn.XLOOKUP($J56,'Fin. Data'!$A:$A,'Fin. Data'!B:B,,0) -> 13.2 | M56: =_xlfn.XLOOKUP($J56,'Fin. Data'!$A:$A,'Fin. Data'!C:C,,0) -> 3.4 | N56: =(C56/C55)-1 -> -0.99931888 | O56: =(D56/D55)-1 -> #VALUE!
B57: Average Growth Rate | C57: =IFERROR(AVERAGE(N48:N55),"") | D57: =IFERROR(AVERAGE(O48:O55),"") | F57: =IFERROR(AVERAGE(Q48:Q55),"") -> 10.192249 | H57: =IFERROR(AVERAGE(S48:S55),"") -> 2.7311526 | J57: Changes in Cash | L57: =L49-L50+L53-L54-L55 -> 3878.2 | M57: =M49-M50+M53-M54-M55 -> 894
B58: CVAR | C58: =IFERROR(STDEV(C48:C55)/AVERAGE(C48:C55),"") -> 2.0395589 | D58: =IFERROR(STDEV(D47:D55)/AVERAGE(D47:D55),"") -> -2.5484748 | F58: =IFERROR(STDEV(F47:F55)/AVERAGE(F47:F55),"") -> 2.5102778 | H58: =IFERROR(STDEV(H47:H55)/AVERAGE(H47:H55),"") -> 1.0824036 | J58: Inventory/D Revenues | L58: =IFERROR(SUM(I52:I55)/(C55-C51),"") -> -0.21530886 | M58: =IFERROR((SUM(I52:I55)-SUM(H52:H55))/(C55-C51),"") -> -0.21612951
B59: Last Year | C59: =IFERROR(C55/C54-1,"") -> 2.4162744 | D59: =IFERROR(D55/D54-1,"") -> 0.28456926 | F59: =IFERROR(1-(F55/F54),"") -> -35.444444 | H59: =IFERROR(1-(H55/H54),"") -> -1.1428571 | J59: t inversiones; t adq. neto dep. | L59: =IFERROR(L58/E28,"") -> -0.54519881 | M59: =IFERROR(M58/E28,"") -> -0.54727684
B60: QUALITATIVE ANALYSIS
B61: SWOT ANALYSIS | J61: HOLDERS
B62: Strenghts | E62: Weaknesses | J62: Name | M62: % Stake
B63: Strategic position: The Pilgangoora Operation, (their biggest operation) is positioned within a source-rich region. Joint venture with POSCO: construction of a lithium chemical hydroxide facility in South Korea which will enable both companies to participate in the chemical conversion industry. | E63: Low diversity of products: they mostly only export a product to be processed into lithium chemicals for the lithium-ion battery industry, so they will be threaten by any changes in the lithium market. Lithium price decrease: Recently the lithium price dropped, and it’s being predicted that it will drop more due to a future lithium surplus production in 2024. | J63: HSBC CUSTODY NOMINEES (AUSTRALIA) LIMITED | M63: 0.257
J64: JP MORGAN NOMINEES AUSTRALIA PTY LIMITED | M64: 0.1403
J65: CITICORP NOMINEES PTY LIMITED | M65: 0.0887
J66: GFL INTERNATIONAL CO LTD | M66: 0.0574
J67: POS-LT PTY LTD | M67: 0.0273
J68: NATIONAL NOMINEES LIMITED | M68: 0.0259
J69: BNP PARIBAS NOMS PTY LTD | M69: 0.0257
J70: BNP PARIBAS NOMINEES PTY LTD ACF CLEARSTREAM | M70: 0.0152
J71: BNP PARIBAS NOMINEES PTY LTD <AGENCY LENDING A/C> | M71: 0.0101
J72: HSBC CUSTODY NOMINEES (AUSTRALIA) LIMITED <NT-COMNWLTH SUPER CORP A/C> | M72: 0.0058
B73: Opportunities | E73: Threats | J73: BNP PARIBAS NOMINEES PTY LTD <IB AU NOMS RETAILCLIENT> | M73: 0.0042
B74: Green energy search: Rising market demand due to search for green alternatives of energetic sources to fight the climate changes (long term point of view). Free trade agreements: Government free trade agreement allows for opportunities to enter new market. Key Expansion Projects: P1000 expansion project will increase the production capacity. | E74: Geopolitical Risk: significant dependence on the Chinese market, could be affected by their policies Climate Change: operations could be impacted by changes to local or international regulations, taxation, and/or penalties. Limited mining life of their lithium exploration: the Pilgangoora Operation (independent hard-rock lithium operation) has an estimated mine life of approximately 34 years and there is no expansion in sight for them (regarding mineral products diversity). | J74: CITICORP NOMINEES PTY LIMITED | M74: 0.0037
J75: WASHINGTON H SOUL PATTISON AND COMPANY LIMITED | M75: 0.0036
J76: PALM BEACH NOMINEES PTY LTD | M76: 0.003
J77: NETWEALTH INVESTMENTS LTD | M77: 0.0026
J78: BNPP NOMS PTY LTD HUB24 CUSTODIAL | M78: 0.25%
J79: USB NOMINEES PTY LTD | M79: 0.0022
J80: MR PETER BARRETT CAPP | M80: 0.0017
J81: BRINSDEN HOLDINGS PTY LTD | M81: 0.17%
J82: BNP PARIBAS NOMS | M82: 0.0014
J83: TOTAL | M83: =SUM(M63:M82) -> 0.6758
B84: NOTES | G84: STOCK PERFORMANCE (5 years)
B85: Output in top producers Australia and Latin America will rise 22% and 29% respectively, while that in Africa is expected to double, driven by projects in Zimbabwe, the bank said. Chinese production will also jump 40% in the next two years. This supply surge will lead to a global lithium surplus of 12% (2024).
G109: ='Inputs (AUD)'!H3 -> #VALUE! | I109: =Peers!C2 -> #VALUE! | J109: =Peers!C3 -> #VALUE! | L109: =Peers!C4 -> #VALUE! | M109: =Peers!C5 -> #VALUE!
B112: global supply surplus: https://www.reuters.com/markets/commodities/china-lithium-price-poised-further-decline-2024-analysts-2023-12-01/

Sheet Acuerdo
A1: Invertir
A2: NO invertir
A3: Mantener sin elevar posición
A4: Mantener (y seguir comprando)
A5: Liquidar
A6: PENDIENTE

Sheet Segments
B2: ="Regions "&"("&OP!$J$21&")" -> Regions (2023) | Q2: Products
D3: Nominal value | K3: YoY Growth
B4: Weight | C4: Region (Plant) | D4: =OP!J21 -> 2023 | E4: =D4-1 -> 2022 | F4: =E4-1 -> 2021 | G4: =F4-1 -> 2020 | H4: =G4-1 -> 2019 | I4: =H4-1 -> 2018 | K4: =OP!J21 -> 2023 | L4: =K4-1 -> 2022 | M4: =L4-1 -> 2021 | N4: =M4-1 -> 2020 | O4: =N4-1 -> 2019 | P4: =O4-1 -> 2018
B5: =IFERROR(D5/$D$10,"") -> 0.69622735 | C5: Pilgan | D5: =+(D15*38/58+D16) -> 2829.4812 | E5: =+E15*38/58+E16 -> 766.81931 | F5: =+F15+F16 -> 170.45 | G5: =+G15+G16 -> 92.854 | H5: =+H15+H16 -> 44.498 | I5: =+I15+I16 -> 9.88 | K5: =IFERROR((D5-E5)/E5,"-") -> 2.689893 | L5: =IFERROR((E5-F5)/F5,"-") -> 3.4987933 | M5: =IFERROR((F5-G5)/G5,"-") -> 0.83567752 | N5: =IFERROR((G5-H5)/H5,"-") -> 1.0867005 | O5: =IFERROR((H5-I5)/I5,"-") -> 3.5038462 | P5: =IFERROR((I5-J5)/J5,"-") -> -
B6: =IFERROR(D6/$D$10,"") -> 0.36616828 | C6: Ngungaju | D6: =+D15*20/58 -> 1488.1148 | E6: =+E15*20/58 -> 400.77069 | F6: - | G6: - | H6: - | I6: - | K6: =IFERROR((D6-E6)/E6,"-") -> 2.7131329 | L6: =IFERROR((E6-F6)/F6,"-") -> - | M6: =IFERROR((F6-G6)/G6,"-") -> - | N6: =IFERROR((G6-H6)/H6,"-") -> - | O6: =IFERROR((H6-I6)/I6,"-") -> - | P6: =IFERROR((I6-J6)/J6,"-") -> -
B7: =IFERROR(D7/$D$10,"") -> -0.00050762558 | C7: =+C17 -> (elimination of by-product) | D7: =+D17 -> -2.063 | E7: =+E17 -> -5.355 | F7: =+F17 -> -5.982 | G7: =+G17 -> -7.463 | H7: =+H17 -> -2.293 | I7: =+I17 -> - | K7: =IFERROR((D7-E7)/E7,"-") -> -0.61475257 | L7: =IFERROR((E7-F7)/F7,"-") -> -0.10481444 | M7: =IFERROR((F7-G7)/G7,"-") -> -0.19844567 | N7: =IFERROR((G7-H7)/H7,"-") -> 2.2546882 | O7: =IFERROR((H7-I7)/I7,"-") -> - | P7: =IFERROR((I7-J7)/J7,"-") -> -
B8: =IFERROR(D8/$D$10,"") -> -0.061659653 | C8: =+C18 -> (provisional price adjustment) | D8: =+D18 -> -250.586 | E8: =+E18 -> 27.356 | F8: =+F18 -> 11.356 | G8: =+G18 -> -1.194 | H8: =+H18 -> - | I8: =+I18 -> - | K8: =IFERROR((D8-E8)/E8,"-") -> -10.160184 | L8: =IFERROR((E8-F8)/F8,"-") -> 1.4089468 | M8: =IFERROR((F8-G8)/G8,"-") -> -10.510888 | N8: =IFERROR((G8-H8)/H8,"-") -> - | O8: =IFERROR((H8-I8)/I8,"-") -> - | P8: =IFERROR((I8-J8)/J8,"-") -> -
B9: =IFERROR(D9/$D$10,"") -> -0.00022834539 | C9: =+C19 -> (hedge close-outs) | D9: =+D19 -> -0.928 | E9: =+E19 -> - | F9: =+F19 -> - | G9: =+G19 -> -0.05 | H9: =+H19 -> 0.58 | I9: =+I19 -> 0.308 | K9: =IFERROR((D9-E9)/E9,"-") -> - | L9: =IFERROR((E9-F9)/F9,"-") -> - | M9: =IFERROR((F9-G9)/G9,"-") -> - | N9: =IFERROR((G9-H9)/H9,"-") -> -1.0862069 | O9: =IFERROR((H9-I9)/I9,"-") -> 0.88311688 | P9: =IFERROR((I9-J9)/J9,"-") -> -
B10: =SUM(B5:B9) -> 1 | C10: TOTAL | D10: =SUM(D5:D9) -> 4064.019 | E10: =SUM(E5:E9) -> 1189.591 | F10: =SUM(F5:F9) -> 175.824 | G10: =SUM(G5:G9) -> 84.147 | H10: =SUM(H5:H9) -> 42.785 | I10: =SUM(I5:I9) -> 10.188 | K10: =(D10-E10)/E10 -> 2.4163162 | L10: =(E10-F10)/F10 -> 5.7658056 | M10: =(F10-G10)/G10 -> 1.0894863 | N10: =(G10-H10)/H10 -> 0.96674068 | O10: =(H10-I10)/I10 -> 3.1995485 | P10: -
B12: ="Categories "&"("&OP!$J$21&")" -> Categories (2023)
D13: Nominal value | K13: YoY Growth
B14: Weight | C14: Category | D14: =OP!J21 -> 2023 | E14: =D14-1 -> 2022 | F14: =E14-1 -> 2021 | G14: =F14-1 -> 2020 | H14: =G14-1 -> 2019 | I14: =H14-1 -> 2018 | K14: =OP!J21 -> 2023 | L14: =K14-1 -> 2022 | M14: =L14-1 -> 2021 | N14: =M14-1 -> 2020 | O14: =N14-1 -> 2019 | P14: =O14-1 -> 2018
B15: =IFERROR(D15/$D$20,"") -> 1.061888 | C15: Spodumene | D15: =4315533000/1000000 -> 4315.533 | E15: =1162235000/1000000 -> 1162.235 | F15: =164468000/1000000 -> 164.468 | G15: =85391000/1000000 -> 85.391 | H15: =42205000/1000000 -> 42.205 | I15: =9880000/1000000 -> 9.88 | K15: =IFERROR((D15-E15)/E15,"-") -> 2.7131329 | L15: =IFERROR((E15-F15)/F15,"-") -> 6.066633 | M15: =IFERROR((F15-G15)/G15,"-") -> 0.92605778 | N15: =IFERROR((G15-H15)/H15,"-") -> 1.0232437 | O15: =IFERROR((H15-I15)/I15,"-") -> 3.2717611 | P15: =IFERROR((I15-J15)/J15,"-") -> -
B16: =IFERROR(D16/$D$20,"") -> 0.00050762558 | C16: Tantalite | D16: =2063000/1000000 -> 2.063 | E16: =5355000/1000000 -> 5.355 | F16: =5982000/1000000 -> 5.982 | G16: =7463000/1000000 -> 7.463 | H16: =2293000/1000000 -> 2.293 | I16: 0 | K16: =IFERROR((D16-E16)/E16,"-") -> -0.61475257 | L16: =IFERROR((E16-F16)/F16,"-") -> -0.10481444 | M16: =IFERROR((F16-G16)/G16,"-") -> -0.19844567 | N16: =IFERROR((G16-H16)/H16,"-") -> 2.2546882 | O16: =IFERROR((H16-I16)/I16,"-") -> - | P16: =IFERROR((I16-J16)/J16,"-") -> -
B17: =IFERROR(D17/$D$20,"") -> -0.00050762558 | C17: (elimination of by-product) | D17: =-D16 -> -2.063 | E17: =-E16 -> -5.355 | F17: =-F16 -> -5.982 | G17: =-G16 -> -7.463 | H17: =-H16 -> -2.293 | I17: - | K17: =IFERROR((D17-E17)/E17,"-") -> -0.61475257 | L17: =IFERROR((E17-F17)/F17,"-") -> -0.10481444 | M17: =IFERROR((F17-G17)/G17,"-") -> -0.19844567 | N17: =IFERROR((G17-H17)/H17,"-") -> 2.2546882 | O17: =IFERROR((H17-I17)/I17,"-") -> - | P17: =IFERROR((I17-J17)/J17,"-") -> -
B18: =IFERROR(D18/$D$20,"") -> -0.061659653 | C18: (provisional price adjustment) | D18: =-250586000/1000000 -> -250.586 | E18: =27356000/1000000 -> 27.356 | F18: =11356000/1000000 -> 11.356 | G18: =-1194000/1000000 -> -1.194 | H18: - | I18: - | K18: =IFERROR((D18-E18)/E18,"-") -> -10.160184 | L18: =IFERROR((E18-F18)/F18,"-") -> 1.4089468 | M18: =IFERROR((F18-G18)/G18,"-") -> -10.510888 | N18: =IFERROR((G18-H18)/H18,"-") -> - | O18: =IFERROR((H18-I18)/I18,"-") -> - | P18: =IFERROR((I18-J18)/J18,"-") -> -
B19: =IFERROR(D19/$D$20,"") -> -0.00022834539 | C19: (hedge close-outs) | D19: =-928000/1000000 -> -0.928 | E19: - | F19: - | G19: =-50000/1000000 -> -0.05 | H19: =580000/1000000 -> 0.58 | I19: =308000/1000000 -> 0.308 | K19: =IFERROR((D19-E19)/E19,"-") -> - | L19: =IFERROR((E19-F19)/F19,"-") -> - | M19: =IFERROR((F19-G19)/G19,"-") -> - | N19: =IFERROR((G19-H19)/H19,"-") -> -1.0862069 | O19: =IFERROR((H19-I19)/I19,"-") -> 0.88311688 | P19: =IFERROR((I19-J19)/J19,"-") -> -
B20: =SUM(B15:B19) -> 1 | C20: TOTAL | D20: =SUM(D15:D19) -> 4064.019 | E20: =SUM(E15:E19) -> 1189.591 | F20: =SUM(F15:F19) -> 175.824 | G20: =SUM(G15:G19) -> 84.147 | H20: =SUM(H15:H19) -> 42.785 | I20: =SUM(I15:I19) -> 10.188 | K20: =(D20-E20)/E20 -> 2.4163162 | L20: =(E20-F20)/F20 -> 5.7658056 | M20: =(F20-G20)/G20 -> 1.0894863 | N20: =(G20-H20)/H20 -> 0.96674068 | O20: =(H20-I20)/I20 -> 3.1995485 | P20: -
B22: Categories | D22: Description | I22: Graphs
B23: Spodumene | D23: Spodumene is one of the sources of lithium. Spodumene is first mined and crushed into powder, then is heated to high temperatures in a kiln, then is mixed with chemicals to form a lithium compound, which is then separated and purified into a concentrated lithium product.
B24: Tantalite | D24: Tantalite is the primary source of the chemical element tantalum, a corrosion (heat and acid) resistant metal. It's mainly used in alloys and glass.
B27: Industry | J27: Graphs (Industry Forecasts)
B28: Drivers | D28: Description
B29: Consumer Electronics | D29: According to the Grand View Research, the consumer electronics segment is the one with the highest CAGR (more than 17.2% from 2024 to 2030). It's composed of electronic devices such as mobile phones, laptops, cameras and speakers, which use lithiom-ion batteries.
B30: EVs | D30: The demand for electric vehicles is also a great driver for Pilbara Mineral's revenues, since they also use a great deal of lithium batteries.
B31: Lithium Prices | D31: Every company in this industry is affected by the prices of lithium since its volatility is one of the main drivers for their revenue, specially Pilbara Minerals since the almost deal solely with lithium. The prices have also decreased with an increase of supply these last few years which could turn into a rebound opportunity, since many professionals forecast prices increasing again.
B32: China | D32: The company's exposure to China's economic policies is significant and could impact commodity prices, capital flows and general confidence and sentiment. This happens because China is the biggest importer of lithium and is the responsible for a large part of total lithium processing. In recent times, China has also imposed restrictions to commodities coming from australia.
B33: Sales forecast
B34: Source | D34: Market Growth CAGR | G34: Period
B35: Acumen | D35: 0.234 | G35: 2022 - 2030
B36: Mordor Intelligence | D36: 0.1957 | G36: 2024 - 2029
B37: Grand View Research | D37: 0.128 | G37: 2024 - 2030
B38: Straits Research | D38: 0.221 | G38: 2023 - 2031
B39: AVERAGE | D39: =AVERAGE(D35:F38) -> 0.194675 | G39: 2022 - 2031
B40: Company's Strategy / Extra Notes
B41: Their strategy is 1) Delivering their performance operative commitments; 2) Achieve full potential of the Pilgangoora asset; 3) Extract greater value along the batteries materials chain and 4) Diversify revenue beyond the Pilgangoora asset. To do so they are implementing a number of iniciatives, namely: Downstream Lithium Chemical Facility In joint venture with POSCO, a 43 ktpa Lithium Hydroxide Chemical Facility was commissioned in Gwangyang, South Korea. This would diversify their assets beyond the Pilgangoora operation and diversifying beyond China by estabilishing a link with another country. The first of 2 trains is already open with a nameplate capacity of 21,5 ktpa of lithium hydroxide. There's also a joint feasibility study with Ganfeng, a chinese lithium company, for a 32 ktpa lithium conversion plant. The feasibility study is expected to be completed in March Quarter 2025 with an option to progress to a final investment decision and formation of a joint venture following that. This would fortify their links with China which is the main buyer of lithium, besides their collaboration with South Korea. Mid-stream Demonstration Plant The development of a Mid-stream Demonstration Plant on site at the Pilgangoora Operation was approved by our Board in August 2023. The facility is aimed at demonstrating the potential to enhance the battery materials supply chain by decarbonising spodumene processing, decreasing transport volumes and improving value-add processing at the mine site. Expansion The P680 and the P1000 projects aims to increase total spodumene concentrate production capacity at the Pilgangoora Operation to up to 1 Mtpa. Pilbara Minerals prefers to expand it's mining operation rather than expanding through M&A.

Sheet Peers
B1: Peer Logo | C1: Peer Name | D1: Description | G1: Next Earnings Date | H1: Lithium Revenues | I1: Currency | J1: End of Fiscal Year
B2: #VALUE! | C2: #VALUE! | D2: Albemarle Corporation is a global developer, manufacturer, and marketer of advanced engineering materials. The company produces a variety of specialty chemicals, primarily focusing on lithium and advanced materials as well as bromine and refining catalyst segments. Its lithium and advanced materials segment consist of two product categories: battery-grade lithium compounds and other specialty chemical products. These are used in a range of applications such as fire safety and soundproofing, energy storage, automotive applications, lubricants, pharmaceuticals, crop protection, and customized chemical services. The company has partnerships and joint ventures in various parts of the world and as of December 31, 2016, had 31 office and production sites globally. | G2: Q1 (1st May 2024) | H2: 0.89 | I2: {=_FV(C2,"Moeda")} -> USD | J2: 31st December 2023
B3: #VALUE! | C3: #VALUE! | D3: Sociedad Química y Minera de Chile, or SQM, is a producer and distributor of potassium nitrate and iodine. The company produces plant nutrients and industrial chemicals derived from solar evaporation ponds in the Atacama Desert. Its segments include plant nutrients (such as potassium nitrate), iodine derivatives, lithium, and industrial chemicals. The company's products are used in fertilizers to improve agricultural yield, industrial applications such as glass manufacturing and industrial nitrates, and they produce and sell iodine and its derivatives which have applications in x-ray contrast media and other uses. Lithium and its derivatives, including lithium carbonate, are used in batteries, greases, and air treatment systems and are sold globally. | G3: FY23 (25th April 2024) | H3: 0.72 | I3: {=_FV(C3,"Moeda")} -> USD | J3: 31st December 2023
B4: #VALUE! | C4: #VALUE! | D4: Mineral Resources is an Australian-based mining services company operating through six segments: Mining Services, Iron Ore, Lithium, Energy, Other Commodities, and Central. Their mining services division provides end-to-end solutions, including their subsidiary Crushing Mining Services (CSI) that offers crushing, screening, and processing solutions for mining operations. The company has three iron ore hubs in Western Australia and lithium operations in the Pilbara and Goldfields regions. The Mt Marion lithium project is located 40 kilometers southwest of Kalgoorlie, and the Wodgina lithium project is 120 kilometers south of Port Hedland, in the Pilbara region near the iron ore hubs. It includes two wells in the Perth Basin. | G4: Q3 (26th April 2024) | H4: 0.3958 | I4: {=_FV(C4,"Moeda")} -> AUD | J4: 30th June 2023
B5: #VALUE! | C5: #VALUE! | D5: Arcadium Lithium PLC is an international lithium chemicals producer with a diversified product range. They produce lithium hydroxide, carbonate, spodumene, and other specialties. The company offers various lithium products such as specialty lithium, hydroxide, carbonate, battery-grade lithium hydroxide, and other lithium-ion battery grade carbonate, among others. They focus on direct lithium extraction from hard rock mining, chemical processing, and conventional brine extraction, which is said to be more efficient and less environmentally impactful than traditional methods. The company's operations span across different geographies, including the South American Lithium Triangle, Western Australia, and Canada. | G5: Q1 (2nd May 2024) | H5: =511/883 -> 0.57870895 | I5: {=_FV(C5,"Moeda")} -> AUD | J5: 31st December 2023
D6: {=_FV(C6,"Descrição")} -> #VALUE! | G6: {=_FV(C6,"Moeda")} -> #VALUE!
B8: {=_FV(OP!E2,"Currency")&" MILLIONS"} -> AUD MILLIONS | C8: =OP!E2 -> #VALUE! | D8: =C2 -> #VALUE! | E8: =C3 -> #VALUE! | F8: =C4 -> #VALUE! | G8: =C5 -> #VALUE! | H8: AVERAGE | I8: Deviation from Average
B9: Company Info | H9: =IFERROR(AVERAGE(C9:F9),"") | K9: TRAFFIC
B10: Market Cap | C10: {=_FV(C8,"Market cap",TRUE)/1000000} -> 8913.995 | D10: {=(_FV(D8,"Capitalização de mercado",TRUE)*_FV($D$55,"Preço"))/1000000} -> 18547.685 | E10: {=(_FV(E8,"Capitalização de mercado",TRUE)*_FV($D$55,"Preço"))/1000000} -> 15963.254 | F10: {=_FV(F8,"Capitalização de mercado",TRUE)/1000000} -> 7560.071 | G10: {=_FV(G8,"Capitalização de mercado",TRUE)/1000000} -> 5764.135 | H10: =IFERROR(AVERAGE(C10:G10),"") -> 11349.828 | I10: =SQRT((C10-H10)^2) -> 2435.8329 | L10: Best Value
B11: Net Sales (current) | C11: =C61 -> 4064 | D11: =D61 -> 14490 | E11: =E60 -> 15450 | F11: =F61 -> 4779.1 | G11: =G61 -> 1795.8 | H11: =IFERROR(AVERAGE(C11:G11),"") -> 8115.78 | I11: =SQRT((C11-H11)^2) -> 4051.78
B12: Profitability | H12: =IFERROR(AVERAGE(C12:F12),"") | L12: Important Value
B13: Sales Growth (ttm) | C13: =C61/C60-1 -> 2.4162744 | D13: =D61/D60-1 -> 0.37228904 | E13: =E60/E61-1 -> 0.37321127 | F13: =F61/F60-1 -> 0.39821533 | G13: =G61/G60-1 -> 0.74858812 | H13: =IFERROR(AVERAGE(C13:G13),"") -> 0.86171563 | I13: =SQRT((C13-H13)^2) -> 1.5545587
B14: Sales Growth (36m) | C14: =C61/C59-1 -> 47.323424 | D14: =D61/D59-1 -> 2.1860158 | E14: =E61/E59-1 -> 3.2601287 | F14: =F61/F59-1 -> 1.2493058 | G14: =G61/G59-1 -> 19.736721 | H14: =IFERROR(AVERAGE(C14:G14),"") -> 14.751119 | I14: =SQRT((C14-H14)^2) -> 32.572305 | L14: Worst Value
B15: Operating Margin | C15: =C64/C61 -> 0.79032972 | D15: =D64/D61 -> 0.026501035 | E15: =E64/E61 -> 0.38094392 | F15: =F64/F61 -> 0.10809567 | G15: =G64/G61 -> 0.64717675 | H15: =IFERROR(AVERAGE(C15:G15),"") -> 0.39060942 | I15: =SQRT((C15-H15)^2) -> 0.39972031
B16: EBITDA Margin | C16: =C63/C61 -> 0.76247539 | D16: =D63/D61 -> 0.091649413 | E16: =E63/E61 -> 0.4226291 | F16: =F63/F61 -> 0.3673495 | G16: =G63/G61 -> 0.75398151 | H16: =IFERROR(AVERAGE(C16:G16),"") -> 0.47961698 | I16: =SQRT((C16-H16)^2) -> 0.28285841
B17: Net Income Margin | C17: =C67/C61 -> 0.58836122 | D17: =D67/D61 -> 0.16363009 | E17: =E67/E60 -> 0.19624595 | F17: =F67/F61 -> 0.050909167 | G17: =G67/G61 -> 0.36574229 | H17: =IFERROR(AVERAGE(C17:G17),"") -> 0.27297774 | I17: =SQRT((C17-H17)^2) -> 0.31538348
B18: Return on Equity (RoE) | C18: =C67/C80 -> 0.70533923 | D18: =D67/D80 -> 0.17155054 | E18: =E67/E80 -> 0.37335304 | F18: =F67/F80 -> 0.070012374 | G18: =G67/G80 -> 0.12865062 | H18: =IFERROR(AVERAGE(C18:G18),"") -> 0.28978116 | I18: =SQRT((C18-H18)^2) -> 0.41555807
B19: Return on Invested Capital (ROIC) | C19: =(C67+C66)/(C79+C80) -> 0.36527706 | D19: =(D67+D66)/(D79+D80) -> 0.086409228 | E19: =(E67+E66)/(E79+E80) -> 0.1254417 | F19: =(F67+F66)/(F79+F80) -> 0.018959041 | G19: =(G67+G66)/(G79+G80) -> 0.036236286 | H19: =IFERROR(AVERAGE(C19:G19),"") -> 0.12646466 | I19: =SQRT((C19-H19)^2) -> 0.2388124
B20: Solvency | H20: =IFERROR(AVERAGE(C20:F20),"")
B21: Debt/Assets | C21: =C79/C75 -> 0.090790182 | D21: =D79/D75 -> 0.2280741 | E21: =E79/E75 -> 0.38367561 | F21: =F79/F75 -> 0.38523204 | G21: =G79/G75 -> 0.062773107 | H21: =IFERROR(AVERAGE(C21:G21),"") -> 0.23010901 | I21: =SQRT((C21-H21)^2) -> 0.13931882
B22: Net Debt/EBITDA | C22: =(C79-C70)/C63 -> -0.92509762 | D22: =(D79-D70)/D63 -> 3.623494 | E22: =(E79-E70)/E63 -> 1.177918 | F22: =(F79-F70)/F63 -> 1.0566758 | G22: =(G79-G70)/G63 -> -0.54726736 | H22: =IFERROR(AVERAGE(C22:G22),"") -> 0.87714455 | I22: =SQRT((C22-H22)^2) -> 1.8022422
B23: Debt/Assets (Leases Free Debt) | C23: =(C79-C78)/C75 -> 0.052415942 | D23: =(D79-D78)/D75 -> 0.2280741 | E23: =(E79-E78)/E75 -> 0.38367561 | F23: =(F79-F78)/F75 -> 0.38523204 | G23: =(G79-G78)/G75 -> 0.062773107 | H23: =IFERROR(AVERAGE(C23:G23),"") -> 0.22243416 | I23: =SQRT((C23-H23)^2) -> 0.17001822
B24: Net Debt/EBIT (Leases Free Debt) | C24: =((C79-C78)-C70)/C63 -> -0.98947946 | D24: =((D79-D78)-D70)/D63 -> 3.623494 | E24: =((E79-E78)-E70)/E63 -> 1.177918 | F24: =((F79-F78)-F70)/F63 -> 1.0566758 | G24: =((G79-G78)-G70)/G63 -> -0.54726736 | H24: =IFERROR(AVERAGE(C24:G24),"") -> 0.86426818 | I24: =SQRT((C24-H24)^2) -> 1.8537476
B25: Leasing Debt/Total Debt | C25: =C78/C79 -> 0.42266949 | D25: =D78/D79 -> 0 | E25: =E78/E79 -> 0 | F25: =F78/F79 -> 0 | G25: =G78/G79 -> 0 | H25: =IFERROR(AVERAGE(C25:G25),"") -> 0.084533898 | I25: =SQRT((C25-H25)^2) -> 0.33813559
B26: Interest Coverage Ratio | C26: =-C63/C65 -> -69.013363 | D26: =-D63/D65 -> 7.5885714 | E26: =-E63/E65 -> 63.4 | F26: =-F63/F65 -> -44.785714 | G26: =-G63/G65 -> -47.013889 | H26: =IFERROR(AVERAGE(C26:G26),"") -> -17.964879 | I26: =SQRT((C26-H26)^2) -> 51.048484
B27: Liquidity
B28: Current Ratio | C28: =C73/C77 -> 2.7570512 | D28: =D73/D77 -> 1.4653787 | E28: =E73/E77 -> 2.495365 | F28: =F73/F77 -> 2.7698501 | G28: =G73/G77 -> 2.5159988 | H28: =IFERROR(AVERAGE(C28:G28),"") -> 2.4007288 | I28: =SQRT((C28-H28)^2) -> 0.35632245
B29: Quick Ratio | C29: =(C70+C71)/C77 -> 2.6433042 | D29: =(D70+D71)/D77 -> 0.59066565 | E29: =(E70+E71)/E77 -> 0.6216686 | F29: =(F70+F71)/F77 -> 1.6237245 | G29: =(G70+G71)/G77 -> 2.0626495 | H29: =IFERROR(AVERAGE(C29:G29),"") -> 1.5084025 | I29: =SQRT((C29-H29)^2) -> 1.1349017
B30: Activity | H30: =IFERROR(AVERAGE(C30:F30),"")
B31: Inventory Turnover | C31: =C62/C72 -> 7.9773895 | D31: =D62/D72 -> 3.9971645 | E31: =E62/E72 -> 2.5395242 | F31: =F62/F72 -> 2.5966359 | G31: =G62/G72 -> 1.1128097 | H31: =IFERROR(AVERAGE(C31:G31),"") -> 3.6447047 | I31: =SQRT((C31-H31)^2) -> 4.3326848
B32: Acc. Receivable Turnover | C32: =C61/C71 -> 49.500609 | D32: =D61/D71 -> 8.1358787 | E32: =E61/E71 -> 9.7664931 | F32: =F61/F71 -> 7.2652782 | G32: =G61/G71 -> 12.199728 | H32: =IFERROR(AVERAGE(C32:G32),"") -> 17.373597 | I32: =SQRT((C32-H32)^2) -> 32.127012
A33: Price/Sales | B33: Payables Turnover | C33: =C62/C76 -> 0.81379744 | D33: =D62/D76 -> 4.1379648 | E33: =E62/E76 -> 10.197227 | F33: =F62/F76 -> 1.8281667 | G33: =G62/G76 -> 1.1035024 | H33: =IFERROR(AVERAGE(C33:G33),"") -> 3.6161316 | I33: =SQRT((C33-H33)^2) -> 2.8023341
B34: Fixed Asset Turnover | C34: =C61/C74 -> 2.9353557 | D34: =D61/D75 -> 0.54008722 | E34: =E60/E73 -> 1.7935918 | F34: =F61/F74 -> 1.0558514 | G34: =G61/G74 -> 0.35094782 | H34: =IFERROR(AVERAGE(C34:G34),"") -> 1.3351668 | I34: =SQRT((C34-H34)^2) -> 1.6001889
B35: Total Asset Turnover | C35: =C61/C75 -> 0.78171886 | D35: =D61/D75 -> 0.54008722 | E35: =E61/E75 -> 0.65454651 | F35: =F61/F75 -> 0.56926577 | G35: =G61/G75 -> 0.22944829 | H35: =IFERROR(AVERAGE(C35:G35),"") -> 0.55501333 | I35: =SQRT((C35-H35)^2) -> 0.22670553
B36: Valuation | H36: =IFERROR(AVERAGE(C36:F36),"")
B37: Price/Earnings | C37: =C10/C67 -> 3.7279892 | D37: =D10/D67 -> 7.8227266 | E37: =E10/E67 -> 5.2649254 | F37: =F10/F67 -> 31.073042 | G37: =G10/G67 -> 8.7760886 | H37: =IFERROR(AVERAGE(C37:G37),"") -> 11.332954 | I37: =SQRT((C37-H37)^2) -> 7.6049651
B38: Price/Sales | C38: =C10/C61 -> 2.1934043 | D38: =D10/D61 -> 1.2800335 | E38: =E10/E61 -> 1.4188298 | F38: =F10/F61 -> 1.5819027 | G38: =G10/G61 -> 3.2097867 | H38: =IFERROR(AVERAGE(C38:G38),"") -> 1.9367914 | I38: =SQRT((C38-H38)^2) -> 0.2566129
B39: Price/Book | C39: =C10/C80 -> 2.6294971 | D39: =D10/D80 -> 1.341993 | E39: =E10/E80 -> 1.9656759 | F39: =F10/F80 -> 2.1754974 | G39: =G10/G80 -> 1.1290492 | H39: =IFERROR(AVERAGE(C39:G39),"") -> 1.8483425 | I39: =SQRT((C39-H39)^2) -> 0.78115455
B40: EV/Sales | C40: =(C79+C10-C70)/C61 -> 1.4880401 | D40: =(D79+D10-D70)/D61 -> 1.6121246 | E40: =(E79+E10-E70)/E61 -> 1.9166522 | F40: =(F79+F10-F70)/F61 -> 1.970072 | G40: =(G79+G10-G70)/G61 -> 2.7971573 | H40: =IFERROR(AVERAGE(C40:G40),"") -> 1.9568092 | I40: =SQRT((C40-H40)^2) -> 0.46876911
B41: EV/EBITDA | C41: =(C79+C10-C70)/C63 -> 1.951591 | D41: =(D79+D10-D70)/D63 -> 17.590124 | E41: =(E79+E10-E70)/E63 -> 4.5350692 | F41: =(F79+F10-F70)/F63 -> 5.3629363 | G41: =(G79+G10-G70)/G63 -> 3.7098486 | H41: =IFERROR(AVERAGE(C41:G41),"") -> 6.6299138 | I41: =SQRT((C41-H41)^2) -> 4.6783228
B42: Stock Info | H42: =IFERROR(AVERAGE(C42:F42),"")
B43: Float | C43: =OP!M21 -> 0.9037 | D43: =1-0.29% -> 0.9971 | E43: =1-0.53% -> 0.9947 | F43: =1-15.06% -> 0.8494 | G43: =100% -> 1 | H43: =IFERROR(AVERAGE(C43:G43),"") -> 0.94898 | I43: =SQRT((C43-H43)^2) -> 0.04528
B44: b (Yahoo) | C44: =OP!M23 -> 2.0207 | D44: 1.63 | E44: 1.09 | F44: 1.28 | G44: 1.85 | H44: =IFERROR(AVERAGE(C44:G44),"") -> 1.57414 | I44: =SQRT((C44-H44)^2) -> 0.44656
B45: Dividend Yield (yahoo finance) | C45: =OP!M33 -> 0.034988523 | D45: 0.0135 | E45: 0.1091 | F45: 0.0134 | G45: N/A | H45: =IFERROR(AVERAGE(C45:G45),"") -> 0.042747131 | I45: =SQRT((C45-H45)^2) -> 0.0077586078
B46: Stock Performance
B47: 1y | C47: 0.0334 | D47: -0.4693 | E47: -0.408 | F47: -0.192 | G47: -0.2465 | H47: =IFERROR(AVERAGE(C47:G47),"") -> -0.25648 | I47: =SQRT((C47-H47)^2) -> 0.28988
B48: 3y | C48: =C49/1.04-1 -> 2.0096154 | D48: =D49/(157.28*1.453491)-1 -> -0.30973307 | E48: =E49/(57*1.453491)-1 -> -0.31637806 | F48: =F49/40.15-1 -> -0.062017435 | G48: =G49/10.1-1 -> -0.19405941 | H48: =IFERROR(AVERAGE(C48:G48),"") -> 0.22548548 | I48: =SQRT((C48-H48)^2) -> 1.7841299
B49: Current Price | C49: =OP!C21 -> 3.13 | D49: {=_FV(D8,"Preço")*_FV(D55,"Preço")} -> 157.79852 | E49: {=_FV(E8,"Preço")*_FV(D55,"Preço")} -> 56.637385 | F49: {=_FV(F8,"Preço")} -> 37.66 | G49: {=_FV(G8,"Preço")} -> 8.14 | H49: -- | I49: --
B50: Average Target Price | C50: 3.75 | D50: {=147.87*_FV(D55,"Preço")} -> 226.16717 | E50: {=72.09*_FV(D55,"Preço")} -> 110.26166 | F50: 68.13 | G50: 10.47 | H50: -- | I50: --
B51: Upside/Downside | C51: =C50/C49-1 -> 0.19808307 | D51: =D50/D49-1 -> 0.43326548 | E51: =E50/E49-1 -> 0.94679989 | F51: =F50/F49-1 -> 0.80908125 | G51: =G50/G49-1 -> 0.28624079 | H51: =IFERROR(AVERAGE(C51:G51),"") -> 0.5346941 | I51: =SQRT((C51-H51)^2) -> 0.33661103
B52: Extra | H52: =IFERROR(AVERAGE(C52:F52),"")
B53: 3y Operating Cash Flow | C53: =('Inputs (AUD)'!B59/'Inputs (AUD)'!E59)-1 -> -182.93158 | D53: =(1907849000*1.506672)/(719374000*1.453491)-1 -> 1.7491322 | E53: =(4077595000*1.506672)/(426971000*1.453491)-1 -> 8.8994731 | F53: =1353700000/594600000-1 -> 1.2766566 | G53: =297300000/-11090000-1 -> -27.807935 | H53: =IFERROR(AVERAGE(C53:G53),"") -> -39.76285 | I53: =SQRT((C53-H53)^2) -> 143.16873
B54: R&D/Net Sales | C54: =C68/C61 -> 0.0048474409 | D54: =D68/D61 -> 0.0089026915 | E54: =E68/E61 -> 0 | F54: =F68/F61 -> 0 | G54: =G68/G61 -> 0 | H54: =IFERROR(AVERAGE(C54:G54),"") -> 0.0027500265 | I54: =SQRT((C54-H54)^2) -> 0.0020974145
D55: #VALUE!
B57: Financial Data | C57: =OP!E2 -> #VALUE! | D57: =D8 -> #VALUE! | E57: =E8 -> #VALUE! | F57: =F8 -> #VALUE! | G57: =G8 -> #VALUE!
B58: IS
B59: Net Sales (36m ago) | C59: ='Fin. Data'!E5 -> 84.1 | D59: 4548 | E59: 2641 | F59: 2124.7 | G59: 86.6
B60: Net Sales (12m ago) | C60: ='Fin. Data'!C5 -> 1189.6 | D60: 10559 | E60: 15450 | F60: 3418 | G60: 1027
B61: Net Sales (current) | C61: ='Fin. Data'!B5 -> 4064 | D61: 14490 | E61: 11251 | F61: 4779.1 | G61: 1795.8
B62: COGS | C62: ='Fin. Data'!B5-'Fin. Data'!B7 -> 776.2 | D62: 12687 | E62: 6618 | F62: 1574.6 | G62: 211.1
B63: EBITDA | C63: ='Fin. Data'!B19 -> 3098.7 | D63: 1328 | E63: 4755 | F63: 1755.6 | G63: 1354
B64: Operating Income | C64: ='Fin. Data'!B11 -> 3211.9 | D64: 384 | E64: 4286 | F64: 516.6 | G64: 1162.2
B65: Net Financial Cost | C65: ='Fin. Data'!B14 -> 44.9 | D65: -175 | E65: =179-254 -> -75 | F65: =39.2 -> 39.2 | G65: ='[2]Arcadium Lithium PLC | Income S'!$B$38 -> 28.8
B66: Taxes | C66: ='Fin. Data'!B21 -> -980.4 | D66: -648 | E66: -1186 | F66: -116.1 | G66: -454
B67: Net Income | C67: ='Fin. Data'!B23 -> 2391.1 | D67: 2371 | E67: 3032 | F67: 243.3 | G67: 656.8
B68: R&D | C68: 19.7 | D68: 129 | E68: 0 | F68: 0 | G68: 0
B69: BS
B70: Cash & Eq. | C70: ='Fin. Data'!B39 -> 3338.6 | D70: 1307 | E70: 994 | F70: 1379 | G70: 1232.3
B71: Acc. Receivables | C71: ='Fin. Data'!B40 -> 82.1 | D71: 1781 | E71: 1152 | F71: 657.8 | G71: 147.2
B72: Inventory | C72: ='Fin. Data'!B41 -> 97.3 | D72: 3174 | E72: 2606 | F72: 606.4 | G72: 189.7
B73: Current Assets | C73: ='Inputs (AUD)'!B27 -> 3567.9 | D73: 7661 | E73: 8614 | F73: 3474.5 | G73: 1682.7
B74: Fixed Assets | C74: ='Fin. Data'!B42 -> 1384.5 | D74: 14145 | E74: 5408 | F74: 4526.3 | G74: 5117
B75: Total Assets | C75: ='Fin. Data'!B44 -> 5198.8 | D75: 26829 | E75: 17189 | F75: 8395.2 | G75: 7826.6
B76: Acc. Payable | C76: ='Inputs (AUD)'!B43 -> 953.8 | D76: 3066 | E76: 649 | F76: 861.3 | G76: 191.3
B77: Current Liabilities | C77: ='Inputs (AUD)'!B42 -> 1294.1 | D77: 5228 | E77: 3452 | F77: 1254.4 | G77: 668.8
B78: Leasing Debt | C78: ='Fin. Data'!B50+'Fin. Data'!B54 -> 199.5
B79: Total Debt | C79: ='Fin. Data'!B58 -> 472 | D79: 6119 | E79: 6595 | F79: 3234.1 | G79: 491.3
B80: Total Equity | C80: ='Fin. Data'!B64 -> 3390 | D80: 13821 | E80: 8121 | F80: 3475.1 | G80: 5105.3
B82: Net Income After Taxes | C82: 2391.1 | D82: -277 | E82: 3043 | F82: 244.3 | G82: 780
B83: Difference | C83: =C82-C67 -> 0 | D83: =D82-D67 -> -2648 | E83: =E82-E67 -> 11 | F83: =F82-F67 -> 1 | G83: =G82-G67 -> 123.2

Sheet Peers (TTM)
B1: Peer Logo | C1: Peer Name | D1: Description | G1: Next Earnings Date | H1: Lithium Revenues | I1: Currency | J1: End of Fiscal Year | AC1: PLS.AX | Statement App | Income Statement
B2: #VALUE! | C2: #VALUE! | D2: Albemarle Corporation is a global developer, manufacturer, and marketer of advanced engineering materials. The company produces a variety of specialty chemicals, primarily focusing on lithium and advanced materials as well as bromine and refining catalyst segments. Its lithium and advanced materials segment consist of two product categories: battery-grade lithium compounds and other specialty chemical products. These are used in a range of applications such as fire safety and soundproofing, energy storage, automotive applications, lubricants, pharmaceuticals, crop protection, and customized chemical services. The company has partnerships and joint ventures in various parts of the world and as of December 31, 2016, had 31 office and production sites globally. | G2: Q1 (1st May 2024) | H2: 0.89 | I2: {=_FV(C2,"Moeda")} -> USD | J2: 31st December 2023 | AC2: Mean | Annual & Interim
B3: #VALUE! | C3: #VALUE! | D3: Sociedad Química y Minera de Chile, or SQM, is a producer and distributor of potassium nitrate and iodine. The company produces plant nutrients and industrial chemicals derived from solar evaporation ponds in the Atacama Desert. Its segments include plant nutrients (such as potassium nitrate), iodine derivatives, lithium, and industrial chemicals. The company's products are used in fertilizers to improve agricultural yield, industrial applications such as glass manufacturing and industrial nitrates, and they produce and sell iodine and its derivatives which have applications in x-ray contrast media and other uses. Lithium and its derivatives, including lithium carbonate, are used in batteries, greases, and air treatment systems and are sold globally. | G3: FY23 (25th April 2024) | H3: 0.72 | I3: {=_FV(C3,"Moeda")} -> USD | J3: 31st December 2023 | AC3: Consolidated | AUD
B4: #VALUE! | C4: #VALUE! | D4: Mineral Resources is an Australian-based mining services company operating through six segments: Mining Services, Iron Ore, Lithium, Energy, Other Commodities, and Central. Their mining services division provides end-to-end solutions, including their subsidiary Crushing Mining Services (CSI) that offers crushing, screening, and processing solutions for mining operations. The company has three iron ore hubs in Western Australia and lithium operations in the Pilbara and Goldfields regions. The Mt Marion lithium project is located 40 kilometers southwest of Kalgoorlie, and the Wodgina lithium project is 120 kilometers south of Port Hedland, in the Pilbara region near the iron ore hubs. It includes two wells in the Perth Basin. | G4: Q3 (26th April 2024) | H4: 0.3958 | I4: {=_FV(C4,"Moeda")} -> AUD | J4: 30th June 2023
B5: #VALUE! | C5: #VALUE! | D5: Arcadium Lithium PLC is an international lithium chemicals producer with a diversified product range. They produce lithium hydroxide, carbonate, spodumene, and other specialties. The company offers various lithium products such as specialty lithium, hydroxide, carbonate, battery-grade lithium hydroxide, and other lithium-ion battery grade carbonate, among others. They focus on direct lithium extraction from hard rock mining, chemical processing, and conventional brine extraction, which is said to be more efficient and less environmentally impactful than traditional methods. The company's operations span across different geographies, including the South American Lithium Triangle, Western Australia, and Canada. | G5: Q1 (2nd May 2024) | H5: =511/883 -> 0.57870895 | I5: {=_FV(C5,"Moeda")} -> AUD | J5: 31st December 2023 | AC5: Next Earning Report
D6: {=_FV(C6,"Descrição")} -> #VALUE! | G6: {=_FV(C6,"Moeda")} -> #VALUE!
AE7: HISTORICAL (ACTUALS)
B8: {=_FV(OP!E2,"Currency")&" MILLIONS"} -> AUD MILLIONS | C8: =OP!E2 -> #VALUE! | D8: =C2 -> #VALUE! | E8: =C3 -> #VALUE! | F8: =C4 -> #VALUE! | G8: =C5 -> #VALUE! | H8: AVERAGE | I8: Deviation from Average | AE8: FY 2024
B9: Company Info | H9: =IFERROR(AVERAGE(C9:F9),"") | K9: TRAFFIC | AD9: SAN2 Jun-23 | AE9: SAN1 Dec-23
B10: Market Cap | C10: {=_FV(C8,"Market cap",TRUE)/1000000} -> 8913.995 | D10: {=(_FV(D8,"Capitalização de mercado",TRUE)*_FV($D$55,"Preço"))/1000000} -> 18547.685 | E10: {=(_FV(E8,"Capitalização de mercado",TRUE)*_FV($D$55,"Preço"))/1000000} -> 15963.254 | F10: {=_FV(F8,"Capitalização de mercado",TRUE)/1000000} -> 7560.071 | G10: {=_FV(G8,"Capitalização de mercado",TRUE)/1000000} -> 5764.135 | H10: =IFERROR(AVERAGE(C10:G10),"") -> 11349.828 | I10: =SQRT((C10-H10)^2) -> 2435.8329 | L10: Best Value | AC10: REVENUE | AD10: 1883.892 | AE10: 757.231
B11: Net Sales (current) | C11: =C61 -> 2641.123 | D11: =D61 -> 14490 | E11: =E60 -> 15450 | F11: =F61 -> 4943.7 | G11: =G61 -> 1795.8 | H11: =IFERROR(AVERAGE(C11:G11),"") -> 7864.1246 | I11: =SQRT((C11-H11)^2) -> 5223.0016 | AC11: YoY Growth % | AD11: 1.0981884 | AE11: -0.65266656
B12: Profitability | H12: =IFERROR(AVERAGE(C12:F12),"") | L12: Important Value | AC12: Actual/Predicted Surprise % | AD12: -0.03271 | AE12: -0.00717
B13: Sales Growth (ttm) | C13: =C61/C60-1 -> -0.1419334 | D13: =D61/D60-1 -> 0.37228904 | E13: =E60/E61-1 -> 0.37321127 | F13: =F61/F60-1 -> 0.11985231 | G13: =G61/G60-1 -> 0.74858812 | H13: =IFERROR(AVERAGE(C13:G13),"") -> 0.29440147 | I13: =SQRT((C13-H13)^2) -> 0.43633487 | AC13: Mean at time of Report | AD13: 1947.6 | AE13: 762.69833
B14: Sales Growth (36m) | C14: =C61/C59-1 -> 5.6510944 | D14: =D61/D59-1 -> 2.1860158 | E14: =E61/E59-1 -> 3.2601287 | F14: =F61/F59-1 -> 0.85254441 | G14: =G61/G59-1 -> 19.736721 | H14: =IFERROR(AVERAGE(C14:G14),"") -> 6.3373008 | I14: =SQRT((C14-H14)^2) -> 0.68620635 | L14: Worst Value | AC14: COST OF GOODS SOLD | AD14: 396.516 | AE14: 340.953
B15: Operating Margin | C15: =C64/C61 -> 0.68330782 | D15: =D64/D61 -> 0.026501035 | E15: =E64/E61 -> 0.38094392 | F15: =F64/F61 -> 0.10117928 | G15: =G64/G61 -> 0.64717675 | H15: =IFERROR(AVERAGE(C15:G15),"") -> 0.36782176 | I15: =SQRT((C15-H15)^2) -> 0.31548606 | AC15: YoY Growth % | AD15: 0.60526944 | AE15: -0.10440504
B16: EBITDA Margin | C16: =C63/C61 -> 0.73006823 | D16: =D63/D61 -> 0.091649413 | E16: =E63/E61 -> 0.4226291 | F16: =F63/F61 -> 0.27730243 | G16: =G63/G61 -> 0.75398151 | H16: =IFERROR(AVERAGE(C16:G16),"") -> 0.45512614 | I16: =SQRT((C16-H16)^2) -> 0.2749421 | AC16: Actual/Predicted Surprise % | AD16: 0.01932 | AE16: -0.00014
B17: Net Income Margin | C17: =C67/C61 -> 0.51849157 | D17: =D67/D61 -> 0.16363009 | E17: =E67/E60 -> 0.19624595 | F17: =F67/F61 -> 0.079292837 | G17: =G67/G61 -> 0.36574229 | H17: =IFERROR(AVERAGE(C17:G17),"") -> 0.26468055 | I17: =SQRT((C17-H17)^2) -> 0.25381102 | AC17: Mean at time of Report | AD17: 389 | AE17: 341
B18: Return on Equity (RoE) | C18: =C67/C80 -> 0.42724323 | D18: =D67/D80 -> 0.17155054 | E18: =E67/E80 -> 0.37335304 | F18: =F67/F80 -> 0.099115044 | G18: =G67/G80 -> 0.12865062 | H18: =IFERROR(AVERAGE(C18:G18),"") -> 0.23998249 | I18: =SQRT((C18-H18)^2) -> 0.18726074 | AC18: Guidance | AD18: - | AE18: -
B19: Return on Invested Capital (ROIC) | C19: =(C67+C66)/(C79+C80) -> 0.21161573 | D19: =(D67+D66)/(D79+D80) -> 0.086409228 | E19: =(E67+E66)/(E79+E80) -> 0.1254417 | F19: =(F67+F66)/(F79+F80) -> 0.032436691 | G19: =(G67+G66)/(G79+G80) -> 0.036236286 | H19: =IFERROR(AVERAGE(C19:G19),"") -> 0.098427927 | I19: =SQRT((C19-H19)^2) -> 0.11318781 | AC19: GROSS INCOME | AD19: 1488.331 | AE19: -
B20: Solvency | H20: =IFERROR(AVERAGE(C20:F20),"") | AC20: YoY Growth % | AD20: - | AE20: -
B21: Debt/Assets | C21: =C79/C75 -> 0.13135333 | D21: =D79/D75 -> 0.2280741 | E21: =E79/E75 -> 0.38367561 | F21: =F79/F75 -> 0.4500639 | G21: =G79/G75 -> 0.062773107 | H21: =IFERROR(AVERAGE(C21:G21),"") -> 0.25118801 | I21: =SQRT((C21-H21)^2) -> 0.11983468 | AC21: Margin % | AD21: 79.00299 | AE21: -
B22: Net Debt/EBITDA | C22: =(C79-C70)/C63 -> -0.81506068 | D22: =(D79-D70)/D63 -> 3.623494 | E22: =(E79-E70)/E63 -> 1.177918 | F22: =(F79-F70)/F63 -> 2.5873514 | G22: =(G79-G70)/G63 -> -0.54726736 | H22: =IFERROR(AVERAGE(C22:G22),"") -> 1.2052871 | I22: =SQRT((C22-H22)^2) -> 2.0203477 | AC22: Actual/Predicted Surprise % | AD22: - | AE22: -
B23: Debt/Assets (Leases Free Debt) | C23: =(C79-C78)/C75 -> 0.13135333 | D23: =(D79-D78)/D75 -> 0.2280741 | E23: =(E79-E78)/E75 -> 0.38367561 | F23: =(F79-F78)/F75 -> 0.4500639 | G23: =(G79-G78)/G75 -> 0.062773107 | H23: =IFERROR(AVERAGE(C23:G23),"") -> 0.25118801 | I23: =SQRT((C23-H23)^2) -> 0.11983468 | AC23: Mean at time of Report | AD23: - | AE23: -
B24: Net Debt/EBIT (Leases Free Debt) | C24: =((C79-C78)-C70)/C63 -> -0.81506068 | D24: =((D79-D78)-D70)/D63 -> 3.623494 | E24: =((E79-E78)-E70)/E63 -> 1.177918 | F24: =((F79-F78)-F70)/F63 -> 2.5873514 | G24: =((G79-G78)-G70)/G63 -> -0.54726736 | H24: =IFERROR(AVERAGE(C24:G24),"") -> 1.2052871 | I24: =SQRT((C24-H24)^2) -> 2.0203477 | AC24: GROSS PROFIT MARGIN | AD24: - | AE24: -
B25: Leasing Debt/Total Debt | C25: =C78/C79 -> 0 | D25: =D78/D79 -> 0 | E25: =E78/E79 -> 0 | F25: =F78/F79 -> 0 | G25: =G78/G79 -> 0 | H25: =IFERROR(AVERAGE(C25:G25),"") -> 0 | I25: =SQRT((C25-H25)^2) -> 0 | AC25: YoY Growth | AD25: - | AE25: -
B26: Interest Coverage Ratio | C26: =-C63/C65 -> -21.568233 | D26: =-D63/D65 -> 7.5885714 | E26: =-E63/E65 -> 63.4 | F26: =-F63/F65 -> -27.472946 | G26: =-G63/G65 -> -47.013889 | H26: =IFERROR(AVERAGE(C26:G26),"") -> -5.0132992 | I26: =SQRT((C26-H26)^2) -> 16.554933 | AC26: Actual/Predicted Surprise % | AD26: - | AE26: -
B27: Liquidity | AC27: Mean at time of Report | AD27: - | AE27: -
B28: Current Ratio | C28: =C73/C77 -> 4.355966 | D28: =D73/D77 -> 1.4653787 | E28: =E73/E77 -> 2.495365 | F28: =F73/F77 -> 1.5483693 | G28: =G73/G77 -> 2.5159988 | H28: =IFERROR(AVERAGE(C28:G28),"") -> 2.4762156 | I28: =SQRT((C28-H28)^2) -> 1.8797504
B29: Quick Ratio | C29: =(C70+C71)/C77 -> 3.9619772 | D29: =(D70+D71)/D77 -> 0.59066565 | E29: =(E70+E71)/E77 -> 0.6216686 | F29: =(F70+F71)/F77 -> 1.1514649 | G29: =(G70+G71)/G77 -> 2.0626495 | H29: =IFERROR(AVERAGE(C29:G29),"") -> 1.6776852 | I29: =SQRT((C29-H29)^2) -> 2.284292 | AC29: R&D EXPENSE | AD29: - | AE29: -
B30: Activity | H30: =IFERROR(AVERAGE(C30:F30),"") | AC30: YoY Growth % | AD30: - | AE30: -
B31: Inventory Turnover | C31: =C62/C72 -> 6.0349345 | D31: =D62/D72 -> 3.9971645 | E31: =E62/E72 -> 2.5395242 | F31: =F62/F72 -> 2.9389831 | G31: =G62/G72 -> 1.1128097 | H31: =IFERROR(AVERAGE(C31:G31),"") -> 3.3246832 | I31: =SQRT((C31-H31)^2) -> 2.7102513 | AC31: Actual/Predicted Surprise % | AD31: - | AE31: -
B32: Acc. Receivable Turnover | C32: =C61/C71 -> 67.721103 | D32: =D61/D71 -> 8.1358787 | E32: =E61/E71 -> 9.7664931 | F32: =F61/F71 -> 7.0624286 | G32: =G61/G71 -> 12.199728 | H32: =IFERROR(AVERAGE(C32:G32),"") -> 20.977126 | I32: =SQRT((C32-H32)^2) -> 46.743976 | AC32: Mean at time of Report | AD32: - | AE32: -
A33: Price/Sales | B33: Payables Turnover | C33: =C62/C76 -> 2.7162762 | D33: =D62/D76 -> 4.1379648 | E33: =E62/E76 -> 10.197227 | F33: =F62/F76 -> 1.7574324 | G33: =G62/G76 -> 1.1035024 | H33: =IFERROR(AVERAGE(C33:G33),"") -> 3.9824805 | I33: =SQRT((C33-H33)^2) -> 1.2662042 | AC33: GENERAL & ADMIN EXPENSE | AD33: - | AE33: -
B34: Fixed Asset Turnover | C34: =C61/C74 -> 1.5415415 | D34: =D61/D75 -> 0.54008722 | E34: =E60/E73 -> 1.7935918 | F34: =F61/F74 -> 0.68930563 | G34: =G61/G74 -> 0.35094782 | H34: =IFERROR(AVERAGE(C34:G34),"") -> 0.98309479 | I34: =SQRT((C34-H34)^2) -> 0.55844668 | AC34: YoY Growth % | AD34: - | AE34: -
B35: Total Asset Turnover | C35: =C61/C75 -> 0.60062379 | D35: =D61/D75 -> 0.54008722 | E35: =E61/E75 -> 0.65454651 | F35: =F61/F75 -> 0.45131459 | G35: =G61/G75 -> 0.22944829 | H35: =IFERROR(AVERAGE(C35:G35),"") -> 0.49520408 | I35: =SQRT((C35-H35)^2) -> 0.10541971 | AC35: Actual/Predicted Surprise % | AD35: - | AE35: -
B36: Valuation | H36: =IFERROR(AVERAGE(C36:F36),"") | AC36: Mean at time of Report | AD36: - | AE36: -
B37: Price/Earnings | C37: =C10/C67 -> 6.5094165 | D37: =D10/D67 -> 7.8227266 | E37: =E10/E67 -> 5.2649254 | F37: =F10/F67 -> 19.285895 | G37: =G10/G67 -> 8.7760886 | H37: =IFERROR(AVERAGE(C37:G37),"") -> 9.5318105 | I37: =SQRT((C37-H37)^2) -> 3.022394 | AC37: SG&A EXPENSE | AD37: - | AE37: -
B38: Price/Sales | C38: =C10/C61 -> 3.3750776 | D38: =D10/D61 -> 1.2800335 | E38: =E10/E61 -> 1.4188298 | F38: =F10/F61 -> 1.5292334 | G38: =G10/G61 -> 3.2097867 | H38: =IFERROR(AVERAGE(C38:G38),"") -> 2.1625922 | I38: =SQRT((C38-H38)^2) -> 1.2124854 | AC38: YoY Growth % | AD38: - | AE38: -
B39: Price/Book | C39: =C10/C80 -> 2.7811041 | D39: =D10/D80 -> 1.341993 | E39: =E10/E80 -> 1.9656759 | F39: =F10/F80 -> 1.9115224 | G39: =G10/G80 -> 1.1290492 | H39: =IFERROR(AVERAGE(C39:G39),"") -> 1.8258689 | I39: =SQRT((C39-H39)^2) -> 0.95523522 | AC39: Actual/Predicted Surprise % | AD39: - | AE39: -
B40: EV/Sales | C40: =(C79+C10-C70)/C61 -> 2.7800277 | D40: =(D79+D10-D70)/D61 -> 1.6121246 | E40: =(E79+E10-E70)/E61 -> 1.9166522 | F40: =(F79+F10-F70)/F61 -> 2.2467122 | G40: =(G79+G10-G70)/G61 -> 2.7971573 | H40: =IFERROR(AVERAGE(C40:G40),"") -> 2.2705348 | I40: =SQRT((C40-H40)^2) -> 0.50949289 | AC40: Mean at time of Report | AD40: - | AE40: -
B41: EV/EBITDA | C41: =(C79+C10-C70)/C63 -> 3.8079012 | D41: =(D79+D10-D70)/D63 -> 17.590124 | E41: =(E79+E10-E70)/E63 -> 4.5350692 | F41: =(F79+F10-F70)/F63 -> 8.1020286 | G41: =(G79+G10-G70)/G63 -> 3.7098486 | H41: =IFERROR(AVERAGE(C41:G41),"") -> 7.5489943 | I41: =SQRT((C41-H41)^2) -> 3.7410932 | AC41: OPERATING EXPENSE | AD41: 362.063 | AE41: 59.051
B42: Stock Info | H42: =IFERROR(AVERAGE(C42:F42),"") | AC42: YoY Growth % | AD42: 0.40147633 | AE42: -0.85743292
B43: Float | C43: =OP!M21 -> 0.9037 | D43: =1-0.29% -> 0.9971 | E43: =1-0.53% -> 0.9947 | F43: =1-15.06% -> 0.8494 | G43: =100% -> 1 | H43: =IFERROR(AVERAGE(C43:G43),"") -> 0.94898 | I43: =SQRT((C43-H43)^2) -> 0.04528 | AC43: Actual/Predicted Surprise % | AD43: 0.00573 | AE43: -0.78605
B44: b (Yahoo) | C44: =OP!M23 -> 2.0207 | D44: 1.63 | E44: 1.09 | F44: 1.28 | G44: 1.85 | H44: =IFERROR(AVERAGE(C44:G44),"") -> 1.57414 | I44: =SQRT((C44-H44)^2) -> 0.44656 | AC44: Mean at time of Report | AD44: 360 | AE44: 276
B45: Dividend Yield (yahoo finance) | C45: =OP!M33 -> 0.034988523 | D45: 0.0135 | E45: 0.1091 | F45: 0.0134 | G45: N/A | H45: =IFERROR(AVERAGE(C45:G45),"") -> 0.042747131 | I45: =SQRT((C45-H45)^2) -> 0.0077586078
B46: Stock Performance | AC46: EBITDA | AD46: 1550.71 | AE46: 359.833
B47: 1y | C47: 0.0334 | D47: -0.4693 | E47: -0.408 | F47: -0.192 | G47: -0.2465 | H47: =IFERROR(AVERAGE(C47:G47),"") -> -0.25648 | I47: =SQRT((C47-H47)^2) -> 0.28988 | AC47: YoY Growth % | AD47: 1.3375188 | AE47: -0.79630057
B48: 3y | C48: =C49/1.04-1 -> 2.0096154 | D48: =D49/(157.28*1.453491)-1 -> -0.30973307 | E48: =E49/(57*1.453491)-1 -> -0.31637806 | F48: =F49/40.15-1 -> -0.062017435 | G48: =G49/10.1-1 -> -0.19405941 | H48: =IFERROR(AVERAGE(C48:G48),"") -> 0.22548548 | I48: =SQRT((C48-H48)^2) -> 1.7841299 | AC48: Margin % | AD48: 82.314167 | AE48: 47.519581
B49: Current Price | C49: =OP!C21 -> 3.13 | D49: {=_FV(D8,"Preço")*_FV(D55,"Preço")} -> 157.79852 | E49: {=_FV(E8,"Preço")*_FV(D55,"Preço")} -> 56.637385 | F49: {=_FV(F8,"Preço")} -> 37.66 | G49: {=_FV(G8,"Preço")} -> 8.14 | H49: -- | I49: -- | AC49: Actual/Predicted Surprise % | AD49: 0.02651 | AE49: -0.1944
B50: Average Target Price | C50: 3.75 | D50: {=147.87*_FV(D55,"Preço")} -> 226.16717 | E50: {=72.09*_FV(D55,"Preço")} -> 110.26166 | F50: 68.13 | G50: 10.47 | H50: -- | I50: -- | AC50: Mean at time of Report | AD50: 1510.6667 | AE50: 446.66667
B51: Upside/Downside | C51: =C50/C49-1 -> 0.19808307 | D51: =D50/D49-1 -> 0.43326548 | E51: =E50/E49-1 -> 0.94679989 | F51: =F50/F49-1 -> 0.80908125 | G51: =G50/G49-1 -> 0.28624079 | H51: =IFERROR(AVERAGE(C51:G51),"") -> 0.5346941 | I51: =SQRT((C51-H51)^2) -> 0.33661103 | AC51: EBITDA PER SHARE | AD51: - | AE51: -
B52: Extra | H52: =IFERROR(AVERAGE(C52:F52),"") | AC52: YoY Growth % | AD52: - | AE52: -
B53: 3y Operating Cash Flow | C53: =('Inputs (AUD)'!B59/'Inputs (AUD)'!E59)-1 -> -182.93158 | D53: =(1907849000*1.506672)/(719374000*1.453491)-1 -> 1.7491322 | E53: =(4077595000*1.506672)/(426971000*1.453491)-1 -> 8.8994731 | F53: =1353700000/594600000-1 -> 1.2766566 | G53: =297300000/-11090000-1 -> -27.807935 | H53: =IFERROR(AVERAGE(C53:G53),"") -> -39.76285 | I53: =SQRT((C53-H53)^2) -> 143.16873 | AC53: Actual/Predicted Surprise % | AD53: - | AE53: -
B54: R&D/Net Sales | C54: =C68/C61 -> 0.0096171212 | D54: =D68/D61 -> 0.0089026915 | E54: =E68/E61 -> 0 | F54: =F68/F61 -> 0 | G54: =G68/G61 -> 0 | H54: =IFERROR(AVERAGE(C54:G54),"") -> 0.0037039625 | I54: =SQRT((C54-H54)^2) -> 0.0059131587 | AC54: Mean at time of Report | AD54: - | AE54: -
D55: #VALUE! | AC55: EXPLORATION EXPENSE | AD55: 7.213 | AE55: 18.147
AC56: YoY Growth % | AD56: 1.1582885 | AE56: 0.44863096
B57: Financial Data | C57: =OP!E2 -> #VALUE! | D57: =D8 -> #VALUE! | E57: =E8 -> #VALUE! | F57: =F8 -> #VALUE! | G57: =G8 -> #VALUE! | AC57: Actual/Predicted Surprise % | AD57: -0.98904 | AE57: -0.97682
B58: IS | AC58: Mean at time of Report | AD58: 658 | AE58: 783
B59: Net Sales (36m ago) | C59: 397.096 | D59: 4548 | E59: 2641 | F59: 2668.6 | G59: 86.6 | AC59: DEPRECIATION & AMORTIZATION | AD59: 58.185 | AE59: 65.344
B60: Net Sales (12m ago) | C60: 3077.993 | D60: 10559 | E60: 15450 | F60: 4414.6 | G60: 1027 | AC60: YoY Growth % | AD60: 1.0234038 | AE60: 115.47772
B61: Net Sales (current) | C61: 2641.123 | D61: 14490 | E61: 11251 | F61: 4943.7 | G61: 1795.8 | AC61: Actual/Predicted Surprise % | AD61: 0.10829 | AE61: 1.37615
B62: COGS | C62: 737.469 | D62: 12687 | E62: 6618 | F62: 2080.8 | G62: 211.1 | AC62: Mean at time of Report | AD62: 52.5 | AE62: 27.5
B63: EBITDA | C63: 1928.2 | D63: 1328 | E63: 4755 | F63: 1370.9 | G63: 1354 | AC63: DEPRECIATION | AD63: - | AE63: -
B64: Operating Income | C64: 1804.7 | D64: 384 | E64: 4286 | F64: 500.2 | G64: 1162.2 | AC64: YoY Growth % | AD64: - | AE64: -
B65: Net Financial Cost | C65: 89.4 | D65: -175 | E65: =179-254 -> -75 | F65: 49.9 | G65: ='[2]Arcadium Lithium PLC | Income S'!$B$38 -> 28.8 | AC65: Actual/Predicted Surprise % | AD65: - | AE65: -
B66: Taxes | C66: -568.9 | D66: -648 | E66: -1186 | F66: -103.8 | G66: -454 | AC66: Mean at time of Report | AD66: - | AE66: -
B67: Net Income After Taxes Before Extra Items | C67: 1369.4 | D67: 2371 | E67: 3032 | F67: 392 | G67: 656.8
B68: R&D | C68: 25.4 | D68: 129 | E68: 0 | F68: 0 | G68: 0 | AC68: EBIT | AD68: 1445.371 | AE68: 358.53
B69: BS | AC69: YoY Growth % | AD69: 1.2794055 | AE69: -0.79697372
B70: Cash & Eq. | C70: 2149.2 | D70: 1307 | E70: 994 | F70: 1383 | G70: 1232.3 | AC70: Margin % | AD70: 76.722604 | AE70: 47.347507
B71: Acc. Receivables | C71: 39 | D71: 1781 | E71: 1152 | F71: 700 | G71: 147.2 | AC71: Actual/Predicted Surprise % | AD71: -0.05613 | AE71: -0.13936
B72: Inventory | C72: 122.2 | D72: 3174 | E72: 2606 | F72: 708 | G72: 189.7 | AC72: Mean at time of Report | AD72: 1531.317 | AE72: 416.58467
B73: Current Assets | C73: 2405.8 | D73: 7661 | E73: 8614 | F73: 2801 | G73: 1682.7 | AC73: INTEREST EXPENSE | AD73: 13.371 | AE73: 16.257
B74: Fixed Assets | C74: 1713.3 | D74: 14145 | E74: 5408 | F74: 7172 | G74: 5117 | AC74: YoY Growth % | AD74: 2.165483 | AE74: -0.26502102
B75: Total Assets | C75: 4397.3 | D75: 26829 | E75: 17189 | F75: 10954 | G75: 7826.6 | AC75: Actual/Predicted Surprise % | AD75: -0.21347 | AE75: -0.53551
B76: Acc. Payable | C76: 271.5 | D76: 3066 | E76: 649 | F76: 1184 | G76: 191.3 | AC76: Mean at time of Report | AD76: 17 | AE76: 35
B77: Current Liabilities | C77: 552.3 | D77: 5228 | E77: 3452 | F77: 1809 | G77: 668.8
B78: Leasing Debt | AC78: PRE-TAX PROFIT | AD78: 1481.87 | AE78: 341.57
B79: Total Debt | C79: 577.6 | D79: 6119 | E79: 6595 | F79: 4930 | G79: 491.3 | AC79: YoY Growth % | AD79: 1.3120513 | AE79: -0.80755243
B80: Total Equity | C80: 3205.2 | D80: 13821 | E80: 8121 | F80: 3955 | G80: 5105.3 | AC80: Margin % | AD80: 78.660029 | AE80: 45.107768
AC81: Actual/Predicted Surprise % | AD81: 0.00808 | AE81: -0.24096
B82: Net Income After Taxes | C82: 1369.4 | D82: -277 | E82: 3043 | F82: 372.2 | G82: 780 | AC82: Mean at time of Report | AD82: 1470 | AE82: 450
B83: Difference | C83: =C82-C67 -> 0 | D83: =D82-D67 -> -2648 | E83: =E82-E67 -> 11 | F83: =F82-F67 -> -19.8 | G83: =G82-G67 -> 123.2 | AC83: TAX PROVISION | AD83: 447.463 | AE83: 121.416
AC84: YoY Growth % | AD84: 1.3240847 | AE84: -0.77218938
AC85: Actual/Predicted Surprise % | AD85: 0.01466 | AE85: -0.1265
AC86: Mean at time of Report | AD86: 441 | AE86: 139
AC87: TAX RATE | AD87: 0.2802436 | AE87: 0.3554645
AC88: YoY Growth | AD88: -0.020421 | AE88: 0.0551745
AC89: Actual/Predicted Surprise % | AD89: -0.06586 | AE89: 0.18488
AC90: Mean at time of Report | AD90: 30 | AE90: 30
AC92: NET INCOME | AD92: 1034.407 | AE92: 220.154
AC93: YoY Growth % | AD93: 1.3068845 | AE93: -0.82272879
AC94: Margin % | AD94: 54.907978 | AE94: 29.073559
AC95: Actual/Predicted Surprise % | AD95: 0.00526 | AE95: -0.3226
AC96: Mean at time of Report | AD96: 1029 | AE96: 325
... AC101: Mean at time of Report | AD101: 0.363 | AE101: 0.107
AC102: CASH EPS | AD102: - | AE102: -
AC103: YoY Growth % | AD103: - | AE103: -
AC104: Actual/Predicted Surprise % | AD104: - | AE104: -
AC105: Mean at time of Report | AD105: - | AE105: -
...

Sheet Peers (NTM)
B1: Peer Logo | C1: Peer Name | D1: Description | G1: Next Earnings Date | H1: Lithium Revenues | I1: Currency | J1: End of Fiscal Year | AC1: PLS.AX | Statement App | Income Statement
B2: #VALUE! | C2: #VALUE! | D2: Albemarle Corporation is a global developer, manufacturer, and marketer of advanced engineering materials. The company produces a variety of specialty chemicals, primarily focusing on lithium and advanced materials as well as bromine and refining catalyst segments. Its lithium and advanced materials segment consist of two product categories: battery-grade lithium compounds and other specialty chemical products. These are used in a range of applications such as fire safety and soundproofing, energy storage, automotive applications, lubricants, pharmaceuticals, crop protection, and customized chemical services. The company has partnerships and joint ventures in various parts of the world and as of December 31, 2016, had 31 office and production sites globally. | G2: Q1 (1st May 2024) | H2: 0.89 | I2: {=_FV(C2,"Moeda")} -> USD | J2: 31st December 2023 | AC2: Mean | Annual & Interim
B3: #VALUE! | C3: #VALUE! | D3: Sociedad Química y Minera de Chile, or SQM, is a producer and distributor of potassium nitrate and iodine. The company produces plant nutrients and industrial chemicals derived from solar evaporation ponds in the Atacama Desert. Its segments include plant nutrients (such as potassium nitrate), iodine derivatives, lithium, and industrial chemicals. The company's products are used in fertilizers to improve agricultural yield, industrial applications such as glass manufacturing and industrial nitrates, and they produce and sell iodine and its derivatives which have applications in x-ray contrast media and other uses. Lithium and its derivatives, including lithium carbonate, are used in batteries, greases, and air treatment systems and are sold globally. | G3: FY23 (25th April 2024) | H3: 0.72 | I3: {=_FV(C3,"Moeda")} -> USD | J3: 31st December 2023 | AC3: Consolidated | AUD
B4: #VALUE! | C4: #VALUE! | D4: Mineral Resources is an Australian-based mining services company operating through six segments: Mining Services, Iron Ore, Lithium, Energy, Other Commodities, and Central. Their mining services division provides end-to-end solutions, including their subsidiary Crushing Mining Services (CSI) that offers crushing, screening, and processing solutions for mining operations. The company has three iron ore hubs in Western Australia and lithium operations in the Pilbara and Goldfields regions. The Mt Marion lithium project is located 40 kilometers southwest of Kalgoorlie, and the Wodgina lithium project is 120 kilometers south of Port Hedland, in the Pilbara region near the iron ore hubs. It includes two wells in the Perth Basin. | G4: Q3 (26th April 2024) | H4: 0.3958 | I4: {=_FV(C4,"Moeda")} -> AUD | J4: 30th June 2023
B5: #VALUE! | C5: #VALUE! | D5: Arcadium Lithium PLC is an international lithium chemicals producer with a diversified product range. They produce lithium hydroxide, carbonate, spodumene, and other specialties. The company offers various lithium products such as specialty lithium, hydroxide, carbonate, battery-grade lithium hydroxide, and other lithium-ion battery grade carbonate, among others. They focus on direct lithium extraction from hard rock mining, chemical processing, and conventional brine extraction, which is said to be more efficient and less environmentally impactful than traditional methods. The company's operations span across different geographies, including the South American Lithium Triangle, Western Australia, and Canada. | G5: Q1 (2nd May 2024) | H5: =511/883 -> 0.57870895 | I5: {=_FV(C5,"Moeda")} -> AUD | J5: 31st December 2023 | AC5: Next Earning Report
D6: {=_FV(C6,"Descrição")} -> #VALUE! | G6: {=_FV(C6,"Moeda")} -> #VALUE!
AE7: HISTORICAL (ACTUALS)
B8: {=_FV(OP!E2,"Currency")&" MILLIONS"} -> AUD MILLIONS | C8: =OP!E2 -> #VALUE! | D8: =C2 -> #VALUE! | E8: =C3 -> #VALUE! | F8: =C4 -> #VALUE! | G8: =C5 -> #VALUE! | H8: AVERAGE | I8: Deviation from Average | AE8: FY 2024
B9: Company Info | H9: =IFERROR(AVERAGE(C9:F9),"") | K9: TRAFFIC | AD9: SAN2 Jun-23 | AE9: SAN1 Dec-23
B10: Market Cap | C10: {=_FV(C8,"Market cap",TRUE)/1000000} -> 8913.995 | D10: {=(_FV(D8,"Capitalização de mercado",TRUE)*_FV($D$54,"Preço"))/1000000} -> 18547.685 | E10: {=(_FV(E8,"Capitalização de mercado",TRUE)*_FV($D$54,"Preço"))/1000000} -> 15963.254 | F10: {=_FV(F8,"Capitalização de mercado",TRUE)/1000000} -> 7560.071 | G10: {=_FV(G8,"Capitalização de mercado",TRUE)/1000000} -> 5764.135 | H10: =IFERROR(AVERAGE(C10:G10),"") -> 11349.828 | I10: =SQRT((C10-H10)^2) -> 2435.8329 | L10: Best Value | AC10: REVENUE | AD10: 1883.892 | AE10: 757.231
B11: Net Sales (current) | C11: =C59 -> 1040.469 | D11: =D59 -> 8901.0109 | E11: =E58 -> 11251 | F11: =F59 -> 4903.149 | G11: =G59 -> 1918.1916 | H11: =IFERROR(AVERAGE(C11:G11),"") -> 5602.7641 | I11: =SQRT((C11-H11)^2) -> 4562.2951 | AC11: YoY Growth % | AD11: 1.0981884 | AE11: -0.65266656
B12: Profitability | H12: =IFERROR(AVERAGE(C12:F12),"") | L12: Important Value | AC12: Actual/Predicted Surprise % | AD12: -0.03271 | AE12: -0.00717
B13: Sales Growth (ntm) | C13: =C59/C58-1 -> -0.74397908 | D13: =D59/D58-1 -> -0.38571353 | E13: =E58/E59-1 -> 0.37705603 | F13: =F59/F58-1 -> 0.025956561 | G13: =G59/G58-1 -> 0.068154339 | H13: =IFERROR(AVERAGE(C13:G13),"") -> -0.13170514 | I13: =SQRT((C13-H13)^2) -> 0.61227395 | AC13: Mean at time of Report | AD13: 1947.6 | AE13: 762.69833
B14: Operating Margin | C14: =C62/C59 -> 0.43441948 | D14: =D62/D59 -> 0.079625113 | E14: =E62/E59 -> 0.51041008 | F14: =F62/F59 -> 0.13358762 | G14: =G62/G59 -> 0.2746656 | H14: =IFERROR(AVERAGE(C14:G14),"") -> 0.28654158 | I14: =SQRT((C14-H14)^2) -> 0.1478779 | L14: Worst Value | AC14: COST OF GOODS SOLD | AD14: 396.516 | AE14: 340.953
B15: EBITDA Margin | C15: =C61/C59 -> 0.31187859 | D15: =D61/D59 -> 0.207246 | E15: =E61/E59 -> 0.41090646 | F15: =F61/F59 -> 0.22254412 | G15: =G61/G59 -> 0.37284998 | H15: =IFERROR(AVERAGE(C15:G15),"") -> 0.30508503 | I15: =SQRT((C15-H15)^2) -> 0.0067935556 | AC15: YoY Growth % | AD15: 0.60526944 | AE15: -0.10440504
B16: Net Income Margin | C16: =C65/C59 -> 0.20855979 | D16: =D65/D59 -> 0.075845192 | E16: =E65/E58 -> 0.17355737 | F16: =F65/F59 -> 0.051347817 | G16: =G65/G59 -> 0.17652499 | H16: =IFERROR(AVERAGE(C16:G16),"") -> 0.13716703 | I16: =SQRT((C16-H16)^2) -> 0.071392762 | AC16: Actual/Predicted Surprise % | AD16: 0.01932 | AE16: -0.00014
B17: Return on Equity (RoE) | C17: =C65/C77 -> 0.07309294 | D17: =D65/D77 -> 0.040842501 | E17: =E65/E77 -> 0.21497431 | F17: =F65/F77 -> 0.059952191 | G17: =G65/G77 -> 0.033919562 | H17: =IFERROR(AVERAGE(C17:G17),"") -> 0.0845563 | I17: =SQRT((C17-H17)^2) -> 0.01146336 | AC17: Mean at time of Report | AD17: 389 | AE17: 341
B18: Return on Invested Capital (ROIC) | C18: =(C65+C64)/(C76+C77) -> -0.026621857 | D18: =(D65+D64)/(D76+D77) -> 0.020348551 | E18: =(E65+E64)/(E76+E77) -> 0.067194797 | F18: =(F65+F64)/(F76+F77) -> 0.016279893 | G18: =(G65+G64)/(G76+G77) -> 0.017106616 | H18: =IFERROR(AVERAGE(C18:G18),"") -> 0.0188616 | I18: =SQRT((C18-H18)^2) -> 0.045483457 | AC18: Guidance | AD18: - | AE18: -
B19: Solvency | H19: =IFERROR(AVERAGE(C19:F19),"") | AC19: GROSS INCOME | AD19: 1488.331 | AE19: -
B20: Debt/Assets | C20: =C76/C73 -> 0.091886923 | D20: =D76/D73 -> 0.23897892 | E20: =E76/E73 -> 0.27579915 | F20: =F76/F73 -> 0.45102134 | G20: =G76/G73 -> 0.044657996 | H20: =IFERROR(AVERAGE(C20:G20),"") -> 0.22046887 | I20: =SQRT((C20-H20)^2) -> 0.12858194 | AC20: YoY Growth % | AD20: - | AE20: -
B21: Net Debt/EBITDA | C21: =(C76-C68)/C61 -> -4.3803544 | D21: =(D76-D68)/D61 -> 2.887248 | E21: =(E76-E68)/E61 -> 0.034857924 | F21: =(F76-F68)/F61 -> 4.1898376 | G21: =(G76-G68)/G61 -> -0.72611131 | H21: =IFERROR(AVERAGE(C21:G21),"") -> 0.40109556 | I21: =SQRT((C21-H21)^2) -> 4.78145 | AC21: Margin % | AD21: 79.00299 | AE21: -
B22: Debt/Assets | C22: =(C76-#REF!)/C73 -> #REF! | D22: =(D76-#REF!)/D73 -> #REF! | E22: =(E76-#REF!)/E73 -> #REF! | F22: =(F76-#REF!)/F73 -> #REF! | G22: =(G76-#REF!)/G73 -> #REF! | H22: =IFERROR(AVERAGE(C22:G22),"") | I22: =SQRT((C22-H22)^2) -> #REF! | AC22: Actual/Predicted Surprise % | AD22: - | AE22: -
B23: Net Debt/EBIT (Leases Free Debt) | C23: =((C76-#REF!)-C68)/C61 -> #REF! | D23: =((D76-#REF!)-D68)/D61 -> #REF! | E23: =((E76-#REF!)-E68)/E61 -> #REF! | F23: =((F76-#REF!)-F68)/F61 -> #REF! | G23: =((G76-#REF!)-G68)/G61 -> #REF! | H23: =IFERROR(AVERAGE(C23:G23),"") | I23: =SQRT((C23-H23)^2) -> #REF! | AC23: Mean at time of Report | AD23: - | AE23: -
B24: Leasing Debt/Total Debt | C24: =#REF!/C76 -> #REF! | D24: =#REF!/D76 -> #REF! | E24: =#REF!/E76 -> #REF! | F24: =#REF!/F76 -> #REF! | G24: =#REF!/G76 -> #REF! | H24: =IFERROR(AVERAGE(C24:G24),"") | I24: =SQRT((C24-H24)^2) -> #REF! | AC24: GROSS PROFIT MARGIN | AD24: - | AE24: -
B25: Interest Coverage Ratio | C25: =-C61/C63 -> #DIV/0! | D25: =-D61/D63 -> 7.0758144 | E25: =-E61/E63 -> 26.379507 | F25: =-F61/F63 -> 3.3503353 | G25: =-G61/G63 -> 30.538401 | H25: =IFERROR(AVERAGE(C25:G25),"") | I25: =SQRT((C25-H25)^2) -> #DIV/0! | AC25: YoY Growth | AD25: - | AE25: -
B26: Liquidity | AC26: Actual/Predicted Surprise % | AD26: - | AE26: -
B27: Current Ratio | C27: =C71/C75 -> 3.7487031 | D27: =D71/D75 -> 0.48987931 | E27: =E71/E75 -> 2.2734514 | F27: =F71/F75 -> 1.1693881 | G27: =G71/G75 -> 3.2514713 | H27: =IFERROR(AVERAGE(C27:G27),"") -> 2.1865786 | I27: =SQRT((C27-H27)^2) -> 1.5621245 | AC27: Mean at time of Report | AD27: - | AE27: -
B28: Quick Ratio | C28: =(C68+C69)/C75 -> #VALUE! | D28: =(D68+D69)/D75 -> #VALUE! | E28: =(E68+E69)/E75 -> #VALUE! | F28: =(F68+F69)/F75 -> #VALUE! | G28: =(G68+G69)/G75 -> #VALUE! | H28: =IFERROR(AVERAGE(C28:G28),"") | I28: =SQRT((C28-H28)^2) -> #VALUE!
B29: Activity | H29: =IFERROR(AVERAGE(C29:F29),"") | AC29: R&D EXPENSE | AD29: - | AE29: -
B30: Inventory Turnover | C30: =C60/C70 -> 6.0183486 | D30: =D60/D70 -> 2.6281013 | E30: =E60/E70 -> 3.4551437 | F30: =F60/F70 -> 3.7592408 | G30: =G60/G70 -> 2.1756915 | H30: =IFERROR(AVERAGE(C30:G30),"") -> 3.6073052 | I30: =SQRT((C30-H30)^2) -> 2.4110434 | AC30: YoY Growth % | AD30: - | AE30: -
B31: Acc. Receivable Turnover | C31: =C59/C69 -> #VALUE! | D31: =D59/D69 -> #VALUE! | E31: =E59/E69 -> #VALUE! | F31: =F59/F69 -> #VALUE! | G31: =G59/G69 -> #VALUE! | H31: =IFERROR(AVERAGE(C31:G31),"") | I31: =SQRT((C31-H31)^2) -> #VALUE! | AC31: Actual/Predicted Surprise % | AD31: - | AE31: -
B32: Payables Turnover | C32: =C60/C74 -> #VALUE! | D32: =D60/D74 -> #VALUE! | E32: =E60/E74 -> #VALUE! | F32: =F60/F74 -> #VALUE! | G32: =G60/G74 -> #VALUE! | H32: =IFERROR(AVERAGE(C32:G32),"") | I32: =SQRT((C32-H32)^2) -> #VALUE! | AC32: Mean at time of Report | AD32: - | AE32: -
A33: Price/Sales | B33: Fixed Asset Turnover | C33: =C59/C72 -> #VALUE! | D33: =D59/D73 -> 0.32058231 | E33: =E58/E71 -> 1.049495 | F33: =F59/F72 -> #VALUE! | G33: =G59/G72 -> #VALUE! | H33: =IFERROR(AVERAGE(C33:G33),"") | I33: =SQRT((C33-H33)^2) -> #VALUE! | AC33: GENERAL & ADMIN EXPENSE | AD33: - | AE33: -
B34: Total Asset Turnover | C34: =C59/C73 -> 0.2391333 | D34: =D59/D73 -> 0.32058231 | E34: =E59/E73 -> 0.41655014 | F34: =F59/F73 -> 0.44228496 | G34: =G59/G73 -> 0.14769879 | H34: =IFERROR(AVERAGE(C34:G34),"") -> 0.3132499 | I34: =SQRT((C34-H34)^2) -> 0.074116599 | AC34: YoY Growth % | AD34: - | AE34: -
B35: Valuation | H35: =IFERROR(AVERAGE(C35:F35),"") | AC35: Actual/Predicted Surprise % | AD35: - | AE35: -
B36: Price/Earnings | C36: =C10/C65 -> 41.078318 | D36: =D10/D65 -> 27.474027 | E36: =E10/E65 -> 8.17499 | F36: =F10/F65 -> 30.028165 | G36: =G10/G65 -> 17.022995 | H36: =IFERROR(AVERAGE(C36:G36),"") -> 24.755699 | I36: =SQRT((C36-H36)^2) -> 16.322619 | AC36: Mean at time of Report | AD36: - | AE36: -
B37: Price/Sales | C37: =C10/C59 -> 8.5672855 | D37: =D10/D59 -> 2.0837728 | E37: =E10/E59 -> 1.9538081 | F37: =F10/F59 -> 1.5418807 | G37: =G10/G59 -> 3.004984 | H37: =IFERROR(AVERAGE(C37:G37),"") -> 3.4303462 | I37: =SQRT((C37-H37)^2) -> 5.1369393 | AC37: SG&A EXPENSE | AD37: - | AE37: -
B38: Price/Book | C38: =C10/C77 -> 3.002535 | D38: =D10/D77 -> 1.122108 | E38: =E10/E77 -> 1.7574128 | F38: =F10/F77 -> 1.8002543 | G38: =G10/G77 -> 0.57741254 | H38: =IFERROR(AVERAGE(C38:G38),"") -> 1.6519445 | I38: =SQRT((C38-H38)^2) -> 1.3505905 | AC38: YoY Growth % | AD38: - | AE38: -
B39: EV/Sales | C39: =(C76+C10-C68)/C59 -> 7.2011468 | D39: =(D76+D10-D68)/D59 -> 2.6821435 | E39: =(E76+E10-E68)/E59 -> 1.9681315 | F39: =(F76+F10-F68)/F59 -> 2.4743045 | G39: =(G76+G10-G68)/G59 -> 2.7342534 | H39: =IFERROR(AVERAGE(C39:G39),"") -> 3.4119959 | I39: =SQRT((C39-H39)^2) -> 3.7891509 | AC39: Actual/Predicted Surprise % | AD39: - | AE39: -
B40: EV/EBITDA | C40: =(C76+C10-C68)/C61 -> 23.089584 | D40: =(D76+D10-D68)/D61 -> 12.941834 | E40: =(E76+E10-E68)/E61 -> 4.7897311 | F40: =(F76+F10-F68)/F61 -> 11.118265 | G40: =(G76+G10-G68)/G61 -> 7.3333877 | H40: =IFERROR(AVERAGE(C40:G40),"") -> 11.85456 | I40: =SQRT((C40-H40)^2) -> 11.235024 | AC40: Mean at time of Report | AD40: - | AE40: -
B41: Stock Info | H41: =IFERROR(AVERAGE(C41:F41),"") | AC41: OPERATING EXPENSE | AD41: 362.063 | AE41: 59.051
B42: Float | C42: =OP!M21 -> 0.9037 | D42: =1-0.29% -> 0.9971 | E42: =1-0.53% -> 0.9947 | F42: =1-15.06% -> 0.8494 | G42: =100% -> 1 | H42: =IFERROR(AVERAGE(C42:G42),"") -> 0.94898 | I42: =SQRT((C42-H42)^2) -> 0.04528 | AC42: YoY Growth % | AD42: 0.40147633 | AE42: -0.85743292
B43: b (Yahoo) | C43: =OP!M23 -> 2.0207 | D43: 1.63 | E43: 1.09 | F43: 1.28 | G43: 1.85 | H43: =IFERROR(AVERAGE(C43:G43),"") -> 1.57414 | I43: =SQRT((C43-H43)^2) -> 0.44656 | AC43: Actual/Predicted Surprise % | AD43: 0.00573 | AE43: -0.78605
B44: Dividend Yield (yahoo finance) | C44: =OP!M33 -> 0.034988523 | D44: 0.0135 | E44: 0.1091 | F44: 0.0134 | G44: N/A | H44: =IFERROR(AVERAGE(C44:G44),"") -> 0.042747131 | I44: =SQRT((C44-H44)^2) -> 0.0077586078 | AC44: Mean at time of Report | AD44: 360 | AE44: 276
B45: Stock Performance
B46: 1y | C46: 0.0334 | D46: -0.4693 | E46: -0.408 | F46: -0.192 | G46: -0.2465 | H46: =IFERROR(AVERAGE(C46:G46),"") -> -0.25648 | I46: =SQRT((C46-H46)^2) -> 0.28988 | AC46: EBITDA | AD46: 1550.71 | AE46: 359.833
B47: 3y | C47: =C48/1.04-1 -> 2.0096154 | D47: =D48/(157.28*1.453491)-1 -> -0.30973307 | E47: =E48/(57*1.453491)-1 -> -0.31637806 | F47: =F48/40.15-1 -> -0.062017435 | G47: =G48/10.1-1 -> -0.19405941 | H47: =IFERROR(AVERAGE(C47:G47),"") -> 0.22548548 | I47: =SQRT((C47-H47)^2) -> 1.7841299 | AC47: YoY Growth % | AD47: 1.3375188 | AE47: -0.79630057
B48: Current Price | C48: =OP!C21 -> 3.13 | D48: {=_FV(D8,"Preço")*_FV(D54,"Preço")} -> 157.79852 | E48: {=_FV(E8,"Preço")*_FV(D54,"Preço")} -> 56.637385 | F48: {=_FV(F8,"Preço")} -> 37.66 | G48: {=_FV(G8,"Preço")} -> 8.14 | H48: -- | I48: -- | AC48: Margin % | AD48: 82.314167 | AE48: 47.519581
B49: Average Target Price | C49: 3.75 | D49: {=147.87*_FV(D54,"Preço")} -> 226.16717 | E49: {=72.09*_FV(D54,"Preço")} -> 110.26166 | F49: 68.13 | G49: 10.47 | H49: -- | I49: -- | AC49: Actual/Predicted Surprise % | AD49: 0.02651 | AE49: -0.1944
B50: Upside/Downside | C50: =C49/C48-1 -> 0.19808307 | D50: =D49/D48-1 -> 0.43326548 | E50: =E49/E48-1 -> 0.94679989 | F50: =F49/F48-1 -> 0.80908125 | G50: =G49/G48-1 -> 0.28624079 | H50: =IFERROR(AVERAGE(C50:G50),"") -> 0.5346941 | I50: =SQRT((C50-H50)^2) -> 0.33661103 | AC50: Mean at time of Report | AD50: 1510.6667 | AE50: 446.66667
B51: Extra | H51: =IFERROR(AVERAGE(C51:F51),"") | AC51: EBITDA PER SHARE | AD51: - | AE51: -
B52: 3y Operating Cash Flow | C52: =('Inputs (AUD)'!B59/'Inputs (AUD)'!E59)-1 -> -182.93158 | D52: =(1907849000*1.506672)/(719374000*1.453491)-1 -> 1.7491322 | E52: =(4077595000*1.506672)/(426971000*1.453491)-1 -> 8.8994731 | F52: =1353700000/594600000-1 -> 1.2766566 | G52: =297300000/-11090000-1 -> -27.807935 | H52: =IFERROR(AVERAGE(C52:G52),"") -> -39.76285 | I52: =SQRT((C52-H52)^2) -> 143.16873 | AC52: YoY Growth % | AD52: - | AE52: -
B53: R&D/Net Sales | C53: =C66/C59 -> 0 | D53: =D66/D59 -> 0.01259638 | E53: =E66/E59 -> 0 | F53: =F66/F59 -> 0 | G53: =G66/G59 -> -0.0031208716 | H53: =IFERROR(AVERAGE(C53:G53),"") -> 0.0018951017 | I53: =SQRT((C53-H53)^2) -> 0.0018951017 | AC53: Actual/Predicted Surprise % | AD53: - | AE53: -
D54: #VALUE! | AC54: Mean at time of Report | AD54: - | AE54: -
AC55: EXPLORATION EXPENSE | AD55: 7.213 | AE55: 18.147
B56: Financial Data | C56: =OP!E2 -> #VALUE! | D56: =D8 -> #VALUE! | E56: =E8 -> #VALUE! | F56: =F8 -> #VALUE! | G56: =G8 -> #VALUE! | AC56: YoY Growth % | AD56: 1.1582885 | AE56: 0.44863096
B57: IS | AC57: Actual/Predicted Surprise % | AD57: -0.98904 | AE57: -0.97682
B58: Net Sales (current) | C58: =Peers!C61 -> 4064 | D58: =Peers!D61 -> 14490 | E58: =Peers!E61 -> 11251 | F58: =Peers!F61 -> 4779.1 | G58: =Peers!G61 -> 1795.8 | AC58: Mean at time of Report | AD58: 658 | AE58: 783
B59: Net Sales (next 12 months) | C59: 1040.469 | D59: 8901.0109 | E59: 8170.3284 | F59: 4903.149 | G59: 1918.1916 | AC59: DEPRECIATION & AMORTIZATION | AD59: 58.185 | AE59: 65.344
B60: COGS | C60: 656 | D60: 7699.7285 | E60: 5011.1687 | F60: 2357.7958 | G60: 1155.1141 | AC60: YoY Growth % | AD60: 1.0234038 | AE60: 115.47772
B61: EBITDA | C61: 324.5 | D61: 1844.699 | E61: 3357.2407 | F61: 1091.167 | G61: 715.19768 | AC61: Actual/Predicted Surprise % | AD61: 0.10829 | AE61: 1.37615
B62: Operating Income | C62: 452 | D62: 708.744 | E62: 4170.218 | F62: 655 | G62: 526.86123 | AC62: Mean at time of Report | AD62: 52.5 | AE62: 27.5
B63: Net Financial Cost | C63: 0 | D63: -260.70482 | E63: -127.267 | F63: -325.68889 | G63: -23.419618 | AC63: DEPRECIATION | AD63: - | AE63: -
B64: Taxes | C64: -306.679 | D64: -203.73273 | E64: -978.84092 | F64: -102 | G64: -157.91703 | AC64: YoY Growth % | AD64: - | AE64: -
B65: Net Income | C65: 217 | D65: 675.09888 | E65: 1952.694 | F65: 251.766 | G65: 338.60874 | AC65: Actual/Predicted Surprise % | AD65: - | AE65: -
B66: R&D | C66: 0 | D66: 112.12052 | E66: 0 | F66: 0 | G66: -5.9864295 | AC66: Mean at time of Report | AD66: - | AE66: -
B67: BS
B68: Cash & Eq. | C68: 1821.225 | D68: 1309.1785 | E68: 5292.5736 | F68: 428.1875 | G68: 1099.2948 | AC68: EBIT | AD68: 1445.371 | AE68: 358.53
B69: Acc. Receivables | C69: Not found | D69: Not Found | E69: Not Found | F69: Not Found | G69: Not Found | AC69: YoY Growth % | AD69: 1.2794055 | AE69: -0.79697372
B70: Inventory | C70: 109 | D70: 2929.7685 | E70: 1450.3503 | F70: 627.2 | G70: 530.91813 | AC70: Margin % | AD70: 76.722604 | AE70: 47.347507
B71: Current Assets | C71: 2071.5333 | D71: 6941.8935 | E71: 10720.394 | F71: 1915.75 | G71: 1594.7671 | AC71: Actual/Predicted Surprise % | AD71: -0.05613 | AE71: -0.13936
B72: Fixed Assets | C72: Not Found | D72: Not Found | E72: Not Found | F72: Not Found | G72: Not Found | AC72: Mean at time of Report | AD72: 1531.317 | AE72: 416.58467
B73: Total Assets | C73: 4351 | D73: 27765.134 | E73: 19614.274 | F73: 11085.95 | G73: 12987.185 | AC73: INTEREST EXPENSE | AD73: 13.371 | AE73: 16.257
B74: Acc. Payable | C74: Not Found | D74: Not Found | E74: Not Found | F74: Not Found | G74: Not Found | AC74: YoY Growth % | AD74: 2.165483 | AE74: -0.26502102
B75: Current Liabilities | C75: 552.6 | D75: 14170.62 | E75: 4715.4709 | F75: 1638.25 | G75: 490.47554 | AC75: Actual/Predicted Surprise % | AD75: -0.21347 | AE75: -0.53551
B76: Total Debt | C76: 399.8 | D76: 6635.2819 | E76: 5409.6 | F76: 5000 | G76: 579.98166
B77: Total Equity | C77: 2968.823 | D77: 16529.323 | E77: 9083.3831 | F77: 4199.4462 | G77: 9982.6979 | AC77: PRE-TAX PROFIT | AD77: 1481.87 | AE77: 341.57
AC78: YoY Growth % | AD78: 1.3120513 | AE78: -0.80755243
AC79: Mean at time of Report | AD79: 1470 | AE79: 450
AC80: TAX PROVISION | AD80: 447.463 | AE80: 121.416
AC81: YoY Growth % | AD81: 1.3240847 | AE81: -0.77218938
AC82: Actual/Predicted Surprise % | AD82: 0.01466 | AE82: -0.1265
AC83: Mean at time of Report | AD83: 441 | AE83: 139
AC84: TAX RATE | AD84: 0.2802436 | AE84: 0.3554645
AC85: YoY Growth | AD85: -0.020421 | AE85: 0.0551745
AC86: Actual/Predicted Surprise % | AD86: -0.06586 | AE86: 0.18488
AC87: Mean at time of Report | AD87: 30 | AE87: 30
AC89: NET INCOME | AD89: 1034.407 | AE89: 220.154
AC90: YoY Growth % | AD90: 1.3068845 | AE90: -0.82272879
... AC98: Mean at time of Report | AD98: 0.363 | AE98: 0.107
AC99: CASH EPS | AD99: - | AE99: -
AC100: YoY Growth % | AD100: - | AE100: -
AC101: Actual/Predicted Surprise % | AD101: - | AE101: -
AC102: Mean at time of Report | AD102: - | AE102: -
AC103: EBITDA REPORTED | AD103: 1504.328 | AE103: 423.874
AC104: YoY Growth % | AD104: 1.2720281 | AE104: -0.76004733
AC105: Margin % | AD105: 79.852136 | AE105: 55.976842
AC106: Actual/Predicted Surprise % | AD106: 0.00355 | AE106: -0.02781
AC107: Mean at time of Report | AD107: 1499 | AE107: 436
AC108: PRE-TAX PROFIT REPORTED | AD108: 1596.693 | AE108: 341.57
...

Sheet SARD
C1: in AUD | F1: Variables | K1: Rankings | P1: Difference | U1: Results | Y1: Additional Information | AD1: =B3 -> PLS.AX | AE1: Selected Peers | AJ1: Price Multiples (TTM) | AM1: Enterprise Value Multiples (TTM)
B2: Ticker | C2: Company Name | D2: TRBC Industry | E2: Country | F2: ROE | G2: DEBT/EBIT | H2: Market Cap | I2: EPS Growth (2022-2023) (Refinitiv Smart Estimate) | J2: EBIT Margin | K2: ROE | L2: DEBT/EBIT | M2: Market Cap | N2: EPS Growth | O2: EBIT Margin | P2: ROE | Q2: DEBT/EBIT | R2: Market Cap | S2: EPS Growth | T2: EBIT Margin | U2: SARD Result | V2: SARD Peers | W2: SARD Peers adjusted Rank | Y2: Suitability | Z2: Relevant Information Missing | AA2: Author's Override | AB2: Observations | AE2: SARD Peers adjusted Rank | AF2: SARD Result | AG2: Ticker | AH2: Company Name | AI2: Country | AJ2: P / E | AK2: P / B | AL2: Price / Sales | AM2: EV / Sales | AN2: EV / EBITDA | AS2: Net Income After Taxes | AT2: Total Equity | AU2: Total Debt | AV2: Operating Income | AW2: Revenue | AX2: Company Market Cap | AY2: Earnings per Share (FY1) | AZ2: Earnings per Share (FY0)
A3: Benchmark | B3: PLS.AX | C3: Pilbara Minerals Ltd | D3: Diversified Mining | E3: Australia | F3: =AS3/AT3 -> 0.70534498 | G3: =AU3/AV3 -> 0.14693659 | H3: =AX3 -> 1.3271754e+10 | I3: =(AY3/AZ3)-1 -> -0.85219897 | J3: =AV3/AW3 -> 0.79033169 | K3: =IFERROR(_xlfn.RANK.EQ(F3,F$3:F$64),"N/A") -> 2 | L3: =IFERROR(_xlfn.RANK.EQ(G3,G$3:G$64),"N/A") -> 27 | M3: =IFERROR(_xlfn.RANK.EQ(H3,H$3:H$64),"N/A") -> 11 | N3: =IFERROR(_xlfn.RANK.EQ(I3,I$3:I$64),"N/A") -> 45 | O3: =IFERROR(_xlfn.RANK.EQ(J3,J$3:J$64),"N/A") -> 2 | P3: - | Q3: - | R3: - | S3: - | T3: - | U3: - | V3: - | W3: - | Y3: =IF(OR(Z3="Y",AA3="Y"),"Not suitable","") | Z3: =IF(OR(N3="N/A",O3="N/A"),"Y","") | AE3: 1 | AF3: =_xlfn.XLOOKUP(AE3,$W$4:$W$64,$U$4:$U$64,"N/A",0,1) -> 24 | AG3: =_xlfn.XLOOKUP(AE3,$W$4:$W$64,$B$4:$B$64,"N/A",0,1) -> HZNC.NS | AH3: =_xlfn.XLOOKUP(AE3,$W$4:$W$64,$C$4:$C$64,"N/A",0,1) -> Hindustan Zinc Ltd | AI3: =_xlfn.XLOOKUP(AE3,$W$4:$W$64,$E$4:$E$64,"N/A",0,1) -> India | AJ3: 16.403313 | AK3: 9.6729016 | AL3: 4.4130356 | AM3: 4.4209976 | AN3: 9.2660538 | AS3: 2391135000 | AT3: 3390022000 | AU3: 471949000 | AV3: 3211923000 | AW3: 4064019000 | AX3: 1.3271754e+10 | AY3: 0.11181 | AZ3: 0.75649
A4: Comparison | B4: AIS.AX | C4: Aeris Resources Ltd | D4: Diversified Mining | E4: Australia | F4: =AS4/AT4 -> -0.52466316 | G4: =AU4/AV4 -> -0.18904627 | H4: =AX4 -> 1.1126544e+08 | I4: =(AY4/AZ4)-1 -> -0.78780178 | J4: =AV4/AW4 -> -0.21427778 | K4: =IFERROR(_xlfn.RANK.EQ(F4,F$3:F$64),"N/A") -> 53 | L4: =IFERROR(_xlfn.RANK.EQ(G4,G$3:G$64),"N/A") -> 43 | M4: =IFERROR(_xlfn.RANK.EQ(H4,H$3:H$64),"N/A") -> 42 | N4: =IFERROR(_xlfn.RANK.EQ(I4,I$3:I$64),"N/A") -> 44 | O4: =IFERROR(_xlfn.RANK.EQ(J4,J$3:J$64),"N/A") -> 40 | P4: =IFERROR(ABS(K$3-K4),"N/A") -> 51 | Q4: =IFERROR(ABS(L$3-L4),"N/A") -> 16 | R4: =IFERROR(ABS(M$3-M4),"N/A") -> 31 | S4: =IFERROR(ABS(N$3-N4),"N/A") -> 1 | T4: =IFERROR(ABS(O$3-O4),"N/A") -> 38 | U4: =SUM(P4:T4) -> 137 | V4: =_xlfn.RANK.EQ(U4,$U$4:$U$64,1) -> 36 | W4: =IF(Y4="Not suitable","-",V4) -> 36 | Y4: =IF(OR(Z4="Y",AA4="Y"),"Not suitable","") | Z4: =IF(OR(N4="N/A",O4="N/A"),"Y","") | AE4: 3 | AF4: =_xlfn.XLOOKUP(AE4,$W$4:$W$64,$U$4:$U$64,"N/A",0,1) -> 42 | AG4: =_xlfn.XLOOKUP(AE4,$W$4:$W$64,$B$4:$B$64,"N/A",0,1) -> DPM.TO | AH4: =_xlfn.XLOOKUP(AE4,$W$4:$W$64,$C$4:$C$64,"N/A",0,1) -> Dundee Precious Metals Inc | AI4: =_xlfn.XLOOKUP(AE4,$W$4:$W$64,$E$4:$E$64,"N/A",0,1) -> Canada | AJ4: 6.9517221 | AK4: 1.1274434 | AL4: 2.4291069 | AM4: 1.308628 | AN4: 2.4998279 | AS4: -139754000 | AT4: 266369000 | AU4: 24811000 | AV4: -131243000 | AW4: 612490000 | AX4: 1.1126544e+08 | AY4: -0.0334 | AZ4: -0.1574
B5: ATY.V | C5: Atico Mining Corp | D5: Diversified Mining | E5: Canada | F5: =AS5/AT5 -> -0.053334092 | G5: =AU5/AV5 -> 2.5020665 | H5: =AX5 -> 16458205 | I5: =(AY5/AZ5)-1 -> -2.0162852 | J5: =AV5/AW5 -> 0.14057106 | K5: =IFERROR(_xlfn.RANK.EQ(F5,F$3:F$64),"N/A") -> 34 | L5: =IFERROR(_xlfn.RANK.EQ(G5,G$3:G$64),"N/A") -> 12 | M5: =IFERROR(_xlfn.RANK.EQ(H5,H$3:H$64),"N/A") -> 60 | N5: =IFERROR(_xlfn.RANK.EQ(I5,I$3:I$64),"N/A") -> 61 | O5: =IFERROR(_xlfn.RANK.EQ(J5,J$3:J$64),"N/A") -> 20 | P5: =IFERROR(ABS(K$3-K5),"N/A") -> 32 | Q5: =IFERROR(ABS(L$3-L5),"N/A") -> 15 | R5: =IFERROR(ABS(M$3-M5),"N/A") -> 49 | S5: =IFERROR(ABS(N$3-N5),"N/A") -> 16 | T5: =IFERROR(ABS(O$3-O5),"N/A") -> 18 | U5: =SUM(P5:T5) -> 130 | V5: =_xlfn.RANK.EQ(U5,$U$4:$U$64,1) -> 32 | W5: =IF(Y5="Not suitable","-",V5) -> 32 | Y5: =IF(OR(Z5="Y",AA5="Y"),"Not suitable","") | Z5: =IF(OR(N5="N/A",O5="N/A"),"Y","") | AE5: 4 | AF5: =_xlfn.XLOOKUP(AE5,$W$4:$W$64,$U$4:$U$64,"N/A",0,1) -> 44 | AG5: =_xlfn.XLOOKUP(AE5,$W$4:$W$64,$B$4:$B$64,"N/A",0,1) -> ALS.TO | AH5: =_xlfn.XLOOKUP(AE5,$W$4:$W$64,$C$4:$C$64,"N/A",0,1) -> Altius Minerals Corp | AI5: =_xlfn.XLOOKUP(AE5,$W$4:$W$64,$E$4:$E$64,"N/A",0,1) -> Canada | AJ5: 47.935592 | AK5: 1.6986928 | AL5: 11.104905 | AM5: 13.326728 | AN5: 18.741649 | AS5: -4922787.3 | AT5: 92300949 | AU5: 33641855 | AV5: 13445628 | AW5: 95650041 | AX5: 16458205 | AY5: -0.0152207 | AZ5: 0.0149768
B6: GORO.A | C6: Gold Resource Corp | D6: Diversified Mining | E6: United States of America | F6: =AS6/AT6 -> -0.056556673 | G6: =AU6/AV6 -> 0 | H6: =AX6 -> 35338995 | I6: =(AY6/AZ6)-1 -> 3.0178865 | J6: =AV6/AW6 -> 0.042083562 | K6: =IFERROR(_xlfn.RANK.EQ(F6,F$3:F$64),"N/A") -> 36 | L6: =IFERROR(_xlfn.RANK.EQ(G6,G$3:G$64),"N/A") -> 31 | M6: =IFERROR(_xlfn.RANK.EQ(H6,H$3:H$64),"N/A") -> 55 | N6: =IFERROR(_xlfn.RANK.EQ(I6,I$3:I$64),"N/A") -> 5 | O6: =IFERROR(_xlfn.RANK.EQ(J6,J$3:J$64),"N/A") -> 28 | P6: =IFERROR(ABS(K$3-K6),"N/A") -> 34 | Q6: =IFERROR(ABS(L$3-L6),"N/A") -> 4 | R6: =IFERROR(ABS(M$3-M6),"N/A") -> 44 | S6: =IFERROR(ABS(N$3-N6),"N/A") -> 40 | T6: =IFERROR(ABS(O$3-O6),"N/A") -> 26 | U6: =SUM(P6:T6) -> 148 | V6: =_xlfn.RANK.EQ(U6,$U$4:$U$64,1) -> 42 | W6: =IF(Y6="Not suitable","-",V6) -> 42 | Y6: =IF(OR(Z6="Y",AA6="Y"),"Not suitable","") | Z6: =IF(OR(N6="N/A",O6="N/A"),"Y","") | AE6: 5 | AF6: =_xlfn.XLOOKUP(AE6,$W$4:$W$64,$U$4:$U$64,"N/A",0,1) -> 45 | AG6: =_xlfn.XLOOKUP(AE6,$W$4:$W$64,$B$4:$B$64,"N/A",0,1) -> VDAN.NS | AH6: =_xlfn.XLOOKUP(AE6,$W$4:$W$64,$C$4:$C$64,"N/A",0,1) -> Vedanta Ltd | AI6: =_xlfn.XLOOKUP(AE6,$W$4:$W$64,$E$4:$E$64,"N/A",0,1) -> India | AJ6: 9.1279843 | AK6: 3.2111772 | AL6: 0.70243227 | AM6: 1.0843165 | AN6: 4.4156085 | AS6: -9277837.4 | AT6: 1.6404496e+08 | AU6: 0 | AV6: 8568899.6 | AW6: 2.0361631e+08 | AX6: 35338995 | AY6: -0.2968294 | AZ6: -0.073877
B7: 5711.T | C7: Mitsubishi Materials Corp | D7: Diversified Mining | E7: Japan | F7: =AS7/AT7 -> 0.043106223 | G7: =AU7/AV7 -> 28.205249 | H7: =AX7 -> 3.5156424e+09 | I7: =(AY7/AZ7)-1 -> 4.7127466 | J7: =AV7/AW7 -> 0.012303705 | K7: =IFERROR(_xlfn.RANK.EQ(F7,F$3:F$64),"N/A") -> 25 | L7: =IFERROR(_xlfn.RANK.EQ(G7,G$3:G$64),"N/A") -> 1 | M7: =IFERROR(_xlfn.RANK.EQ(H7,H$3:H$64),"N/A") -> 17 | N7: =IFERROR(_xlfn.RANK.EQ(I7,I$3:I$64),"N/A") -> 3 | O7: =IFERROR(_xlfn.RANK.EQ(J7,J$3:J$64),"N/A") -> 31 | P7: =IFERROR(ABS(K$3-K7),"N/A") -> 23 | Q7: =IFERROR(ABS(L$3-L7),"N/A") -> 26 | R7: =IFERROR(ABS(M$3-M7),"N/A") -> 6 | S7: =IFERROR(ABS(N$3-N7),"N/A") -> 42 | T7: =IFERROR(ABS(O$3-O7),"N/A") -> 29 | U7: =SUM(P7:T7) -> 126 | V7: =_xlfn.RANK.EQ(U7,$U$4:$U$64,1) -> 30 | W7: =IF(Y7="Not suitable","-",V7) -> 30 | Y7: =IF(OR(Z7="Y",AA7="Y"),"Not suitable","") | Z7: =IF(OR(N7="N/A",O7="N/A"),"Y","") | AE7: 6 | AF7: =_xlfn.XLOOKUP(AE7,$W$4:$W$64,$U$4:$U$64,"N/A",0,1) -> 49 | AG7: =_xlfn.XLOOKUP(AE7,$W$4:$W$64,$B$4:$B$64,"N/A",0,1) -> BHP.AX | AH7: =_xlfn.XLOOKUP(AE7,$W$4:$W$64,$C$4:$C$64,"N/A",0,1) -> BHP Group Ltd | AI7: =_xlfn.XLOOKUP(AE7,$W$4:$W$64,$E$4:$E$64,"N/A",0,1) -> Australia | AJ7: 19.805163 | AK7: 3.5871445 | AL7: 2.6427476 | AM7: 2.9260532 | AN7: 5.2801592 | AS7: 2.8811569e+08 | AT7: 6.6838537e+09 | AU7: 6.3562764e+09 | AV7: 2.2535793e+08 | AW7: 1.8316266e+10 | AX7: 3.5156424e+09 | AY7: 2.8906603 | AZ7: 0.50600185
B8: GLEN.L | C8: Glencore PLC | D8: Diversified Mining | E8: Switzerland | F8: =AS8/AT8 -> 0.073657641 | G8: =AU8/AV8 -> 5.9518183 | H8: =AX8 -> 9.0491119e+10 | I8: =(AY8/AZ8)-1 -> -0.21937301 | J8: =AV8/AW8 -> 0.024868131 | K8: =IFERROR(_xlfn.RANK.EQ(F8,F$3:F$64),"N/A") -> 20 | L8: =IFERROR(_xlfn.RANK.EQ(G8,G$3:G$64),"N/A") -> 5 | M8: =IFERROR(_xlfn.RANK.EQ(H8,H$3:H$64),"N/A") -> 4 | N8: =IFERROR(_xlfn.RANK.EQ(I8,I$3:I$64),"N/A") -> 29 | O8: =IFERROR(_xlfn.RANK.EQ(J8,J$3:J$64),"N/A") -> 30 | P8: =IFERROR(ABS(K$3-K8),"N/A") -> 18 | Q8: =IFERROR(ABS(L$3-L8),"N/A") -> 22 | R8: =IFERROR(ABS(M$3-M8),"N/A") -> 7 | S8: =IFERROR(ABS(N$3-N8),"N/A") -> 16 | T8: =IFERROR(ABS(O$3-O8),"N/A") -> 28 | U8: =SUM(P8:T8) -> 91 | V8: =_xlfn.RANK.EQ(U8,$U$4:$U$64,1) -> 24 | W8: =IF(Y8="Not suitable","-",V8) -> 24 | Y8: =IF(OR(Z8="Y",AA8="Y"),"Not suitable","") | Z8: =IF(OR(N8="N/A",O8="N/A"),"Y","") | AE8: 7 | AF8: 49 | AG8: GMEXICOB.MX | AH8: Grupo Mexico SAB de CV | AI8: Mexico | AJ8: 11.199677 | AK8: 2.0000184 | AL8: 2.6456077 | AM8: 3.0065953 | AN8: 6.0797373 | AS8: 4713660300 | AT8: 63994179400 | AU8: 47343651630 | AV8: 7954485310 | AW8: 319866638470 | AX8: 9.0491119e+10 | AY8: 0.61596778 | AZ8: 0.78906799
B9: BCM.V | C9: Bear Creek Mining Corp | D9: Diversified Mining | E9: Canada | F9: =AS9/AT9 -> -0.19798537 | G9: =AU9/AV9 -> -1.1148915 | H9: =AX9 -> 46322122 | I9: =(AY9/AZ9)-1 -> 2.0574454 | J9: =AV9/AW9 -> -0.3028769 | K9: =IFERROR(_xlfn.RANK.EQ(F9,F$3:F$64),"N/A") -> 47 | L9: =IFERROR(_xlfn.RANK.EQ(G9,G$3:G$64),"N/A") -> 50 | M9: =IFERROR(_xlfn.RANK.EQ(H9,H$3:H$64),"N/A") -> 53 | N9: =IFERROR(_xlfn.RANK.EQ(I9,I$3:I$64),"N/A") -> 6 | O9: =IFERROR(_xlfn.RANK.EQ(J9,J$3:J$64),"N/A") -> 42 | P9: =IFERROR(ABS(K$3-K9),"N/A") -> 45 | Q9: =IFERROR(ABS(L$3-L9),"N/A") -> 23 | R9: =IFERROR(ABS(M$3-M9),"N/A") -> 42 | S9: =IFERROR(ABS(N$3-N9),"N/A") -> 39 | T9: =IFERROR(ABS(O$3-O9),"N/A") -> 40 | U9: =SUM(P9:T9) -> 189 | V9: =_xlfn.RANK.EQ(U9,$U$4:$U$64,1) -> 58 | W9: =IF(Y9="Not suitable","-",V9) -> 58 | Y9: =IF(OR(Z9="Y",AA9="Y"),"Not suitable","") | Z9: =IF(OR(N9="N/A",O9="N/A"),"Y","") | AE9: Median | AJ9: =MEDIAN(AJ3:AJ8) -> 13.801495 | AK9: =MEDIAN(AK3:AK8) -> 2.6055978 | AL9: =MEDIAN(AL3:AL8) -> 2.6441777 | AM9: =MEDIAN(AM3:AM8) -> 2.9663243 | AN9: =MEDIAN(AN3:AN8) -> 5.6799482 | AS9: -33176231 | AT9: 1.675691e+08 | AU9: 30252414 | AV9: -27134849 | AW9: 89590356 | AX9: 46322122 | AY9: -0.3191013 | AZ9: -0.1043686
B10: IMA.AX | C10: Image Resources NL | D10: Diversified Mining | E10: Australia | F10: =AS10/AT10 -> 0.13053693 | G10: =AU10/AV10 -> 0.0081939938 | H10: =AX10 -> 63147962 | I10: =(AY10/AZ10)-1 -> -1 | J10: =AV10/AW10 -> 0.14015635 | K10: =IFERROR(_xlfn.RANK.EQ(F10,F$3:F$64),"N/A") -> 12 | L10: =IFERROR(_xlfn.RANK.EQ(G10,G$3:G$64),"N/A") -> 30 | M10: =IFERROR(_xlfn.RANK.EQ(H10,H$3:H$64),"N/A") -> 49 | N10: =IFERROR(_xlfn.RANK.EQ(I10,I$3:I$64),"N/A") -> 47 | O10: =IFERROR(_xlfn.RANK.EQ(J10,J$3:J$64),"N/A") -> 21 | P10: =IFERROR(ABS(K$3-K10),"N/A") -> 10 | Q10: =IFERROR(ABS(L$3-L10),"N/A") -> 3 | R10: =IFERROR(ABS(M$3-M10),"N/A") -> 38 | S10: =IFERROR(ABS(N$3-N10),"N/A") -> 2 | T10: =IFERROR(ABS(O$3-O10),"N/A") -> 19 | U10: =SUM(P10:T10) -> 72 | V10: =_xlfn.RANK.EQ(U10,$U$4:$U$64,1) -> 15 | W10: =IF(Y10="Not suitable","-",V10) -> 15 | Y10: =IF(OR(Z10="Y",AA10="Y"),"Not suitable","") | Z10: =IF(OR(N10="N/A",O10="N/A"),"Y","") | AE10: Benchmark Data | AJ10: Price / Share | AS10: 15168000 | AT10: 116197000 | AU10: 197000 | AV10: 24042000 | AW10: 171537000 | AX10: 63147962 | AZ10: 0.058
B11: S.TO | C11: Sherritt International Corp | D11: Diversified Mining | E11: Canada | F11: =AS11/AT11 -> -0.1047914 | G11: =AU11/AV11 -> -8.9122807 | H11: =AX11 -> 1.2579232e+08 | I11: =(AY11/AZ11)-1 -> 0.33359291 | J11: =AV11/AW11 -> -0.17868339 | K11: =IFERROR(_xlfn.RANK.EQ(F11,F$3:F$64),"N/A") -> 41 | L11: =IFERROR(_xlfn.RANK.EQ(G11,G$3:G$64),"N/A") -> 60 | M11: =IFERROR(_xlfn.RANK.EQ(H11,H$3:H$64),"N/A") -> 41 | N11: =IFERROR(_xlfn.RANK.EQ(I11,I$3:I$64),"N/A") -> 12 | O11: =IFERROR(_xlfn.RANK.EQ(J11,J$3:J$64),"N/A") -> 37 | P11: =IFERROR(ABS(K$3-K11),"N/A") -> 39 | Q11: =IFERROR(ABS(L$3-L11),"N/A") -> 33 | R11: =IFERROR(ABS(M$3-M11),"N/A") -> 30 | S11: =IFERROR(ABS(N$3-N11),"N/A") -> 33 | T11: =IFERROR(ABS(O$3-O11),"N/A") -> 35 | U11: =SUM(P11:T11) -> 170 | V11: =_xlfn.RANK.EQ(U11,$U$4:$U$64,1) -> 54 | W11: =IF(Y11="Not suitable","-",V11) -> 54 | Y11: =IF(OR(Z11="Y",AA11="Y"),"Not suitable","") | Z11: =IF(OR(N11="N/A",O11="N/A"),"Y","") | AE11: Benchmark | AF11: Multiplier | AG11: # Shares | AH11: -Debt + Cash | AJ11: P / E | AK11: P / B | AL11: Price / Sales | AM11: EV / Sales | AN11: EV / EBITDA | AS11: -71287315 | AT11: 6.8027833e+08 | AU11: 3.9424214e+08 | AV11: -44235830 | AW11: 2.4756544e+08 | AX11: 1.2579232e+08 | AY11: -0.16810808 | AZ11: -0.12605652
B12: SOSIL.NGM | C12: Sotkamo Silver AB | D12: Diversified Mining | E12: Sweden | F12: =AS12/AT12 -> 0.091798853 | G12: =AU12/AV12 -> 4.161919 | H12: =AX12 -> 32538544 | I12: =(AY12/AZ12)-1 -> 1.5725809 | J12: =AV12/AW12 -> 0.16197183 | K12: =IFERROR(_xlfn.RANK.EQ(F12,F$3:F$64),"N/A") -> 15 | L12: =IFERROR(_xlfn.RANK.EQ(G12,G$3:G$64),"N/A") -> 8 | M12: =IFERROR(_xlfn.RANK.EQ(H12,H$3:H$64),"N/A") -> 57 | N12: =IFERROR(_xlfn.RANK.EQ(I12,I$3:I$64),"N/A") -> 8 | O12: =IFERROR(_xlfn.RANK.EQ(J12,J$3:J$64),"N/A") -> 19 | P12: =IFERROR(ABS(K$3-K12),"N/A") -> 13 | Q12: =IFERROR(ABS(L$3-L12),"N/A") -> 19 | R12: =IFERROR(ABS(M$3-M12),"N/A") -> 46 | S12: =IFERROR(ABS(N$3-N12),"N/A") -> 37 | T12: =IFERROR(ABS(O$3-O12),"N/A") -> 17 | U12: =SUM(P12:T12) -> 132 | V12: =_xlfn.RANK.EQ(U12,$U$4:$U$64,1) -> 33 | W12: =IF(Y12="Not suitable","-",V12) -> 33 | Y12: =IF(OR(Z12="Y",AA12="Y"),"Not suitable","") | Z12: =IF(OR(N12="N/A",O12="N/A"),"Y","") | AE12: =C3 -> Pilbara Minerals Ltd | AF12: 1000000 | AG12: =OP!C22 -> 3011485000 | AH12: =-'Fin. Data'!B58*SARD!AF12+'Fin. Data'!B39*SARD!AF12 -> 2866600000 | AJ12: =AJ9*'Fin. Data'!B23*AF$12/AG$12 -> 10.9583 | AK12: =AK9*'Fin. Data'!B64*AF$12/AG$12 -> 2.9330966 | AL12: =AL9*'Fin. Data'!B5*AF$12/AG$12 -> 3.5683186 | AM12: =(AM9*'Fin. Data'!B5*$AF12+$AH12)/$AG12 -> 4.9549447 | AN12: =(AN9*'Fin. Data'!B19*$AF12+$AH12)/$AG12 -> 6.7963332 | AS12: 3967547 | AT12: 43220007 | AU12: 40492318 | AV12: 9729242.2 | AW12: 60067495 | AX12: 32538544 | AY12: 0.021951647 | AZ12: 0.0085329278
B13: 29M.AX | C13: 29Metals Ltd | D13: Diversified Mining | E13: Australia | F13: =AS13/AT13 -> -1.042901 | G13: =AU13/AV13 -> -0.76254834 | H13: =AX13 -> 2.4896694e+08 | I13: =(AY13/AZ13)-1 -> -0.76524996 | J13: =AV13/AW13 -> -0.79116305 | K13: =IFERROR(_xlfn.RANK.EQ(F13,F$3:F$64),"N/A") -> 59 | L13: =IFERROR(_xlfn.RANK.EQ(G13,G$3:G$64),"N/A") -> 47 | M13: =IFERROR(_xlfn.RANK.EQ(H13,H$3:H$64),"N/A") -> 33 | N13: =IFERROR(_xlfn.RANK.EQ(I13,I$3:I$64),"N/A") -> 43 | O13: =IFERROR(_xlfn.RANK.EQ(J13,J$3:J$64),"N/A") -> 47 | P13: =IFERROR(ABS(K$3-K13),"N/A") -> 57 | Q13: =IFERROR(ABS(L$3-L13),"N/A") -> 20 | R13: =IFERROR(ABS(M$3-M13),"N/A") -> 22 | S13: =IFERROR(ABS(N$3-N13),"N/A") -> 2 | T13: =IFERROR(ABS(O$3-O13),"N/A") -> 45 | U13: =SUM(P13:T13) -> 146 | V13: =_xlfn.RANK.EQ(U13,$U$4:$U$64,1) -> 40 | W13: =IF(Y13="Not suitable","-",V13) -> 40 | Y13: =IF(OR(Z13="Y",AA13="Y"),"Not suitable","") | Z13: =IF(OR(N13="N/A",O13="N/A"),"Y","") | AE13: By Consolidated Average | AJ13: =AVERAGE(AJ12:AL12) -> 5.819905 | AM13: =AVERAGE(AM12:AN12) -> 5.875639 | AS13: -440463000 | AT13: 422344000 | AU13: 271333000 | AV13: -355824000 | AW13: 449748000 | AX13: 2.4896694e+08 | AY13: -0.11345 | AZ13: -0.48328
B14: USA.TO | C14: Americas Gold and Silver Corporation | D14: Diversified Mining | E14: Canada | F14: =AS14/AT14 -> -0.55630517 | G14: =AU14/AV14 -> -0.43411831 | H14: =AX14 -> 72364913 | I14: =(AY14/AZ14)-1 -> -0.29834755 | J14: =AV14/AW14 -> -0.41956808 | K14: =IFERROR(_xlfn.RANK.EQ(F14,F$3:F$64),"N/A") -> 54 | L14: =IFERROR(_xlfn.RANK.EQ(G14,G$3:G$64),"N/A") -> 46 | M14: =IFERROR(_xlfn.RANK.EQ(H14,H$3:H$64),"N/A") -> 47 | N14: =IFERROR(_xlfn.RANK.EQ(I14,I$3:I$64),"N/A") -> 33 | O14: =IFERROR(_xlfn.RANK.EQ(J14,J$3:J$64),"N/A") -> 44 | P14: =IFERROR(ABS(K$3-K14),"N/A") -> 52 | Q14: =IFERROR(ABS(L$3-L14),"N/A") -> 19 | R14: =IFERROR(ABS(M$3-M14),"N/A") -> 36 | S14: =IFERROR(ABS(N$3-N14),"N/A") -> 12 | T14: =IFERROR(ABS(O$3-O14),"N/A") -> 42 | U14: =SUM(P14:T14) -> 161 | V14: =_xlfn.RANK.EQ(U14,$U$4:$U$64,1) -> 49 | W14: =IF(Y14="Not suitable","-",V14) -> 49 | Y14: =IF(OR(Z14="Y",AA14="Y"),"Not suitable","") | Z14: =IF(OR(N14="N/A",O14="N/A"),"Y","") | AE14: Upside | AJ14: =AJ13/OP!C21-1 -> 0.85939456 | AM14: =AM13/OP!C21-1 -> 0.87720096 | AS14: -66324575 | AT14: 1.1922337e+08 | AU14: 22728573 | AV14: -52355713 | AW14: 1.2478478e+08 | AX14: 72364913 | AY14: -0.23335445 | AZ14: -0.3325784
B15: SMT.TO | C15: Sierra Metals Inc | D15: Diversified Mining | E15: Canada | F15: =AS15/AT15 -> -1.0819957 | G15: =AU15/AV15 -> -1.2420035 | H15: =AX15 -> 1.9204638e+08 | I15: =(AY15/AZ15)-1 -> -1.2972789 | J15: =AV15/AW15 -> -0.39396936 | K15: =IFERROR(_xlfn.RANK.EQ(F15,F$3:F$64),"N/A") -> 60 | L15: =IFERROR(_xlfn.RANK.EQ(G15,G$3:G$64),"N/A") -> 53 | M15: =IFERROR(_xlfn.RANK.EQ(H15,H$3:H$64),"N/A") -> 36 | N15: =IFERROR(_xlfn.RANK.EQ(I15,I$3:I$64),"N/A") -> 58 | O15: =IFERROR(_xlfn.RANK.EQ(J15,J$3:J$64),"N/A") -> 43 | P15: =IFERROR(ABS(K$3-K15),"N/A") -> 58 | Q15: =IFERROR(ABS(L$3-L15),"N/A") -> 26 | R15: =IFERROR(ABS(M$3-M15),"N/A") -> 25 | S15: =IFERROR(ABS(N$3-N15),"N/A") -> 13 | T15: =IFERROR(ABS(O$3-O15),"N/A") -> 41 | U15: =SUM(P15:T15) -> 163 | V15: =_xlfn.RANK.EQ(U15,$U$4:$U$64,1) -> 50 | W15: =IF(Y15="Not suitable","-",V15) -> 50 | Y15: =IF(OR(Z15="Y",AA15="Y"),"Not suitable","") | Z15: =IF(OR(N15="N/A",O15="N/A"),"Y","") | AS15: -1.2961378e+08 | AT15: 1.197914e+08 | AU15: 1.3798013e+08 | AV15: -1.110948e+08 | AW15: 2.8198843e+08 | AX15: 1.9204638e+08 | AY15: 0.0767815 | AZ15: -0.258281
B16: LUCA.V | C16: Luca Mining Corp | D16: Diversified Mining | E16: Canada | F16: =AS16/AT16 -> -0.40923034 | G16: =AU16/AV16 -> -4.5051262 | H16: =AX16 -> 45950630 | I16: =(AY16/AZ16)-1 -> 4.7391051 | J16: =AV16/AW16 -> -0.1960377 | K16: =IFERROR(_xlfn.RANK.EQ(F16,F$3:F$64),"N/A") -> 52 | L16: =IFERROR(_xlfn.RANK.EQ(G16,G$3:G$64),"N/A") -> 59 | M16: =IFERROR(_xlfn.RANK.EQ(H16,H$3:H$64),"N/A") -> 54 | N16: =IFERROR(_xlfn.RANK.EQ(I16,I$3:I$64),"N/A") -> 2 | O16: =IFERROR(_xlfn.RANK.EQ(J16,J$3:J$64),"N/A") -> 39 | P16: =IFERROR(ABS(K$3-K16),"N/A") -> 50 | Q16: =IFERROR(ABS(L$3-L16),"N/A") -> 32 | R16: =IFERROR(ABS(M$3-M16),"N/A") -> 43 | S16: =IFERROR(ABS(N$3-N16),"N/A") -> 43 | T16: =IFERROR(ABS(O$3-O16),"N/A") -> 37 | U16: =SUM(P16:T16) -> 205 | V16: =_xlfn.RANK.EQ(U16,$U$4:$U$64,1) -> 61 | W16: =IF(Y16="Not suitable","-",V16) -> 61 | Y16: =IF(OR(Z16="Y",AA16="Y"),"Not suitable","") | Z16: =IF(OR(N16="N/A",O16="N/A"),"Y","") | AS16: -12574007 | AT16: 30725990 | AU16: 56647490 | AV16: -12574007 | AW16: 64140762 | AX16: 45950630 | AY16: -0.12416357 | AZ16: -0.021634657
B17: MND.TO | C17: Mandalay Resources Corp | D17: Diversified Mining | E17: Canada | F17: =AS17/AT17 -> 0.039917332 | G17: =AU17/AV17 -> 1.2211354 | H17: =AX17 -> 1.6077143e+08 | I17: =(AY17/AZ17)-1 -> 1.7688616 | J17: =AV17/AW17 -> 0.11147199 | K17: =IFERROR(_xlfn.RANK.EQ(F17,F$3:F$64),"N/A") -> 26 | L17: =IFERROR(_xlfn.RANK.EQ(G17,G$3:G$64),"N/A") -> 18 | M17: =IFERROR(_xlfn.RANK.EQ(H17,H$3:H$64),"N/A") -> 37 | N17: =IFERROR(_xlfn.RANK.EQ(I17,I$3:I$64),"N/A") -> 7 | O17: =IFERROR(_xlfn.RANK.EQ(J17,J$3:J$64),"N/A") -> 25 | P17: =IFERROR(ABS(K$3-K17),"N/A") -> 24 | Q17: =IFERROR(ABS(L$3-L17),"N/A") -> 9 | R17: =IFERROR(ABS(M$3-M17),"N/A") -> 26 | S17: =IFERROR(ABS(N$3-N17),"N/A") -> 38 | T17: =IFERROR(ABS(O$3-O17),"N/A") -> 23 | U17: =SUM(P17:T17) -> 120 | V17: =_xlfn.RANK.EQ(U17,$U$4:$U$64,1) -> 27 | W17: =IF(Y17="Not suitable","-",V17) -> 27 | Y17: =IF(OR(Z17="Y",AA17="Y"),"Not suitable","") | Z17: =IF(OR(N17="N/A",O17="N/A"),"Y","") | AS17: 11543328 | AT17: 2.8918086e+08 | AU17: 34649074 | AV17: 28374473 | AW17: 2.5454353e+08 | AX17: 1.6077143e+08 | AY17: 0.3423642 | AZ17: 0.123648
B18: GSVR.V | C18: Guanajuato Silver Company Ltd | D18: Diversified Mining | E18: Canada | F18: =AS18/AT18 -> -0.82344251 | G18: =AU18/AV18 -> -0.88894473 | H18: =AX18 -> 62032415 | I18: =(AY18/AZ18)-1 -> 0.15617613 | J18: =AV18/AW18 -> -0.62312542 | K18: =IFERROR(_xlfn.RANK.EQ(F18,F$3:F$64),"N/A") -> 57 | L18: =IFERROR(_xlfn.RANK.EQ(G18,G$3:G$64),"N/A") -> 49 | M18: =IFERROR(_xlfn.RANK.EQ(H18,H$3:H$64),"N/A") -> 50 | N18: =IFERROR(_xlfn.RANK.EQ(I18,I$3:I$64),"N/A") -> 13 | O18: =IFERROR(_xlfn.RANK.EQ(J18,J$3:J$64),"N/A") -> 46 | P18: =IFERROR(ABS(K$3-K18),"N/A") -> 55 | Q18: =IFERROR(ABS(L$3-L18),"N/A") -> 22 | R18: =IFERROR(ABS(M$3-M18),"N/A") -> 39 | S18: =IFERROR(ABS(N$3-N18),"N/A") -> 32 | T18: =IFERROR(ABS(O$3-O18),"N/A") -> 44 | U18: =SUM(P18:T18) -> 192 | V18: =_xlfn.RANK.EQ(U18,$U$4:$U$64,1) -> 59 | W18: =IF(Y18="Not suitable","-",V18) -> 59 | Y18: =IF(OR(Z18="Y",AA18="Y"),"Not suitable","") | Z18: =IF(OR(N18="N/A",O18="N/A"),"Y","") | AS18: -39294804 | AT18: 47720155 | AU18: 29985028 | AV18: -33731038 | AW18: 54132020 | AX18: 62032415 | AY18: -0.1194384 | AZ18: -0.10330468
B19: AMI.AX | C19: Aurelia Metals Ltd | D19: Diversified Mining | E19: Australia | F19: =AS19/AT19 -> -0.16854999 | G19: =AU19/AV19 -> -0.18348199 | H19: =AX19 -> 2.3656744e+08 | I19: =(AY19/AZ19)-1 -> -1.0032833 | J19: =AV19/AW19 -> -0.18735814 | K19: =IFERROR(_xlfn.RANK.EQ(F19,F$3:F$64),"N/A") -> 46 | L19: =IFERROR(_xlfn.RANK.EQ(G19,G$3:G$64),"N/A") -> 42 | M19: =IFERROR(_xlfn.RANK.EQ(H19,H$3:H$64),"N/A") -> 34 | N19: =IFERROR(_xlfn.RANK.EQ(I19,I$3:I$64),"N/A") -> 56 | O19: =IFERROR(_xlfn.RANK.EQ(J19,J$3:J$64),"N/A") -> 38 | P19: =IFERROR(ABS(K$3-K19),"N/A") -> 44 | Q19: =IFERROR(ABS(L$3-L19),"N/A") -> 15 | R19: =IFERROR(ABS(M$3-M19),"N/A") -> 23 | S19: =IFERROR(ABS(N$3-N19),"N/A") -> 11 | T19: =IFERROR(ABS(O$3-O19),"N/A") -> 36 | U19: =SUM(P19:T19) -> 129 | V19: =_xlfn.RANK.EQ(U19,$U$4:$U$64,1) -> 31 | W19: =IF(Y19="Not suitable","-",V19) -> 31 | Y19: =IF(OR(Z19="Y",AA19="Y"),"Not suitable","") | Z19: =IF(OR(N19="N/A",O19="N/A"),"Y","") | AS19: -52221000 | AT19: 309825000 | AU19: 12692000 | AV19: -69173000 | AW19: 369202000 | AX19: 2.3656744e+08 | AY19: 7e-05 | AZ19: -0.02132
B20: VDAN.NS | C20: Vedanta Ltd | D20: Diversified Mining | E20: India | F20: =AS20/AT20 -> 0.36795779 | G20: =AU20/AV20 -> 2.7517449 | H20: =AX20 -> 1.8998025e+10 | I20: =(AY20/AZ20)-1 -> -0.48843879 | J20: =AV20/AW20 -> 0.16436989 | K20: =IFERROR(_xlfn.RANK.EQ(F20,F$3:F$64),"N/A") -> 4 | L20: =IFERROR(_xlfn.RANK.EQ(G20,G$3:G$64),"N/A") -> 10 | M20: =IFERROR(_xlfn.RANK.EQ(H20,H$3:H$64),"N/A") -> 9 | N20: =IFERROR(_xlfn.RANK.EQ(I20,I$3:I$64),"N/A") -> 37 | O20: =IFERROR(_xlfn.RANK.EQ(J20,J$3:J$64),"N/A") -> 18 | P20: =IFERROR(ABS(K$3-K20),"N/A") -> 2 | Q20: =IFERROR(ABS(L$3-L20),"N/A") -> 17 | R20: =IFERROR(ABS(M$3-M20),"N/A") -> 2 | S20: =IFERROR(ABS(N$3-N20),"N/A") -> 8 | T20: =IFERROR(ABS(O$3-O20),"N/A") -> 16 | U20: =SUM(P20:T20) -> 45 | V20: =_xlfn.RANK.EQ(U20,$U$4:$U$64,1) -> 5 | W20: =IF(Y20="Not suitable","-",V20) -> 5 | Y20: =IF(OR(Z20="Y",AA20="Y"),"Not suitable","") | Z20: =IF(OR(N20="N/A",O20="N/A"),"Y","") | AS20: 2.6411125e+09 | AT20: 7.1777594e+09 | AU20: 1.2130983e+10 | AV20: 4.4084694e+09 | AW20: 2.6820419e+10 | AX20: 1.8998025e+10 | AY20: 0.27362083 | AZ20: 0.53487409
B21: PEOLES.MX | C21: Industrias Penoles SAB de CV | D21: Diversified Mining | E21: Mexico | F21: =AS21/AT21 -> 0.079909452 | G21: =AU21/AV21 -> 7.9476189 | H21: =AX21 -> 7.7914558e+09 | I21: =(AY21/AZ21)-1 -> -0.30565796 | J21: =AV21/AW21 -> 0.06870603 | K21: =IFERROR(_xlfn.RANK.EQ(F21,F$3:F$64),"N/A") -> 19 | L21: =IFERROR(_xlfn.RANK.EQ(G21,G$3:G$64),"N/A") -> 4 | M21: =IFERROR(_xlfn.RANK.EQ(H21,H$3:H$64),"N/A") -> 14 | N21: =IFERROR(_xlfn.RANK.EQ(I21,I$3:I$64),"N/A") -> 34 | O21: =IFERROR(_xlfn.RANK.EQ(J21,J$3:J$64),"N/A") -> 26 | P21: =IFERROR(ABS(K$3-K21),"N/A") -> 17 | Q21: =IFERROR(ABS(L$3-L21),"N/A") -> 23 | R21: =IFERROR(ABS(M$3-M21),"N/A") -> 3 | S21: =IFERROR(ABS(N$3-N21),"N/A") -> 11 | T21: =IFERROR(ABS(O$3-O21),"N/A") -> 24 | U21: =SUM(P21:T21) -> 78 | V21: =_xlfn.RANK.EQ(U21,$U$4:$U$64,1) -> 16 | W21: =IF(Y21="Not suitable","-",V21) -> 16 | Y21: =IF(OR(Z21="Y",AA21="Y"),"Not suitable","") | Z21: =IF(OR(N21="N/A",O21="N/A"),"Y","") | AS21: 4.7787247e+08 | AT21: 5.9801746e+09 | AU21: 4.4268626e+09 | AV21: 5.570049e+08 | AW21: 8.1070744e+09 | AX21: 7.7914558e+09 | AY21: 0.2309115 | AZ21: 0.3325616
B22: DR0G.DE | C22: Deutsche Rohstoff AG | D22: Diversified Mining | E22: Germany | F22: =AS22/AT22 -> 0.51322015 | G22: =AU22/AV22 -> 1.1338421 | H22: =AX22 -> 2.6475409e+08 | I22: =(AY22/AZ22)-1 -> 0.012673817 | J22: =AV22/AW22 -> 0.58583497 | K22: =IFERROR(_xlfn.RANK.EQ(F22,F$3:F$64),"N/A") -> 3 | L22: =IFERROR(_xlfn.RANK.EQ(G22,G$3:G$64),"N/A") -> 19 | M22: =IFERROR(_xlfn.RANK.EQ(H22,H$3:H$64),"N/A") -> 32 | N22: =IFERROR(_xlfn.RANK.EQ(I22,I$3:I$64),"N/A") -> 21 | O22: =IFERROR(_xlfn.RANK.EQ(J22,J$3:J$64),"N/A") -> 3 | P22: =IFERROR(ABS(K$3-K22),"N/A") -> 1 | Q22: =IFERROR(ABS(L$3-L22),"N/A") -> 8 | R22: =IFERROR(ABS(M$3-M22),"N/A") -> 21 | S22: =IFERROR(ABS(N$3-N22),"N/A") -> 24 | T22: =IFERROR(ABS(O$3-O22),"N/A") -> 1 | U22: =SUM(P22:T22) -> 55 | V22: =_xlfn.RANK.EQ(U22,$U$4:$U$64,1) -> 8 | W22: =IF(Y22="Not suitable","-",V22) -> 8 | Y22: =IF(OR(Z22="Y",AA22="Y"),"Not suitable","") | Z22: =IF(OR(N22="N/A",O22="N/A"),"Y","") | AS22: 1.0396609e+08 | AT22: 2.0257601e+08 | AU22: 1.7262139e+08 | AV22: 1.5224465e+08 | AW22: 2.5987634e+08 | AX22: 2.6475409e+08 | AY22: 21.884575 | AZ22: 21.610685
B23: A1M.AX | C23: AIC Mines Ltd | D23: Diversified Mining | E23: Australia | F23: =AS23/AT23 -> -0.037688768 | G23: =AU23/AV23 -> -0.39186384 | H23: =AX23 -> 1.433659e+08 | I23: =(AY23/AZ23)-1 -> -1.7399001 | J23: =AV23/AW23 -> -0.057523779 | K23: =IFERROR(_xlfn.RANK.EQ(F23,F$3:F$64),"N/A") -> 33 | L23: =IFERROR(_xlfn.RANK.EQ(G23,G$3:G$64),"N/A") -> 44 | M23: =IFERROR(_xlfn.RANK.EQ(H23,H$3:H$64),"N/A") -> 39 | N23: =IFERROR(_xlfn.RANK.EQ(I23,I$3:I$64),"N/A") -> 60 | O23: =IFERROR(_xlfn.RANK.EQ(J23,J$3:J$64),"N/A") -> 32 | P23: =IFERROR(ABS(K$3-K23),"N/A") -> 31 | Q23: =IFERROR(ABS(L$3-L23),"N/A") -> 17 | R23: =IFERROR(ABS(M$3-M23),"N/A") -> 28 | S23: =IFERROR(ABS(N$3-N23),"N/A") -> 15 | T23: =IFERROR(ABS(O$3-O23),"N/A") -> 30 | U23: =SUM(P23:T23) -> 121 | V23: =_xlfn.RANK.EQ(U23,$U$4:$U$64,1) -> 28 | W23: =IF(Y23="Not suitable","-",V23) -> 28 | Y23: =IF(OR(Z23="Y",AA23="Y"),"Not suitable","") | Z23: =IF(OR(N23="N/A",O23="N/A"),"Y","") | AS23: -5815000 | AT23: 154290000 | AU23: 2832000 | AV23: -7227000 | AW23: 125635000 | AX23: 1.433659e+08 | AY23: 0.0163 | AZ23: -0.02203
B24: AAL.L | C24: Anglo American PLC | D24: Diversified Mining | E24: United Kingdom | F24: =AS24/AT24 -> 0.053637706 | G24: =AU24/AV24 -> 4.4823748 | H24: =AX24 -> 4.5674651e+10 | I24: =(AY24/AZ24)-1 -> -0.072794502 | J24: =AV24/AW24 -> 0.12309148 | K24: =IFERROR(_xlfn.RANK.EQ(F24,F$3:F$64),"N/A") -> 24 | L24: =IFERROR(_xlfn.RANK.EQ(G24,G$3:G$64),"N/A") -> 7 | M24: =IFERROR(_xlfn.RANK.EQ(H24,H$3:H$64),"N/A") -> 6 | N24: =IFERROR(_xlfn.RANK.EQ(I24,I$3:I$64),"N/A") -> 25 | O24: =IFERROR(_xlfn.RANK.EQ(J24,J$3:J$64),"N/A") -> 23 | P24: =IFERROR(ABS(K$3-K24),"N/A") -> 22 | Q24: =IFERROR(ABS(L$3-L24),"N/A") -> 20 | R24: =IFERROR(ABS(M$3-M24),"N/A") -> 5 | S24: =IFERROR(ABS(N$3-N24),"N/A") -> 20 | T24: =IFERROR(ABS(O$3-O24),"N/A") -> 21 | U24: =SUM(P24:T24) -> 88 | V24: =_xlfn.RANK.EQ(U24,$U$4:$U$64,1) -> 21 | W24: =IF(Y24="Not suitable","-",V24) -> 21 | Y24: =IF(OR(Z24="Y",AA24="Y"),"Not suitable","") | Z24: =IF(OR(N24="N/A",O24="N/A"),"Y","") | AS24: 1973569920 | AT24: 36794450510 | AU24: 24834088160 | AV24: 5540386390 | AW24: 45010316360 | AX24: 4.5674651e+10 | AY24: 3.2940196 | AZ24: 3.5526316
B25: VAST.L | C25: Vast Resources PLC | D25: Diversified Mining | E25: United Kingdom | F25: =AS25/AT25 -> -4.1313409 | G25: =AU25/AV25 -> -1.1269666 | H25: =AX25 -> 5852771.9 | I25: =(AY25/AZ25)-1 -> -1 | J25: =AV25/AW25 -> -2.1870968 | K25: =IFERROR(_xlfn.RANK.EQ(F25,F$3:F$64),"N/A") -> 62 | L25: =IFERROR(_xlfn.RANK.EQ(G25,G$3:G$64),"N/A") -> 52 | M25: =IFERROR(_xlfn.RANK.EQ(H25,H$3:H$64),"N/A") -> 62 | N25: =IFERROR(_xlfn.RANK.EQ(I25,I$3:I$64),"N/A") -> 47 | O25: =IFERROR(_xlfn.RANK.EQ(J25,J$3:J$64),"N/A") -> 50 | P25: =IFERROR(ABS(K$3-K25),"N/A") -> 60 | Q25: =IFERROR(ABS(L$3-L25),"N/A") -> 25 | R25: =IFERROR(ABS(M$3-M25),"N/A") -> 51 | S25: =IFERROR(ABS(N$3-N25),"N/A") -> 2 | T25: =IFERROR(ABS(O$3-O25),"N/A") -> 48 | U25: =SUM(P25:T25) -> 186 | V25: =_xlfn.RANK.EQ(U25,$U$4:$U$64,1) -> 57 | W25: =IF(Y25="Not suitable","-",V25) -> 57 | Y25: =IF(OR(Z25="Y",AA25="Y"),"Not suitable","") | Z25: =IF(OR(N25="N/A",O25="N/A"),"Y","") | AS25: -15901356 | AT25: 3848957.6 | AU25: 13877740 | AV25: -12314243 | AW25: 5630406 | AX25: 5852771.9 | AZ25: -0.12590752
B26: FVI.TO | C26: Fortuna Silver Mines Inc | D26: Diversified Mining | E26: Canada | F26: =AS26/AT26 -> -0.10918284 | G26: =AU26/AV26 -> -2.1181573 | H26: =AX26 -> 1.3659687e+09 | I26: =(AY26/AZ26)-1 -> 0.69984486 | J26: =AV26/AW26 -> -0.16662289 | K26: =IFERROR(_xlfn.RANK.EQ(F26,F$3:F$64),"N/A") -> 43 | L26: =IFERROR(_xlfn.RANK.EQ(G26,G$3:G$64),"N/A") -> 54 | M26: =IFERROR(_xlfn.RANK.EQ(H26,H$3:H$64),"N/A") -> 21 | N26: =IFERROR(_xlfn.RANK.EQ(I26,I$3:I$64),"N/A") -> 10 | O26: =IFERROR(_xlfn.RANK.EQ(J26,J$3:J$64),"N/A") -> 34 | P26: =IFERROR(ABS(K$3-K26),"N/A") -> 41 | Q26: =IFERROR(ABS(L$3-L26),"N/A") -> 27 | R26: =IFERROR(ABS(M$3-M26),"N/A") -> 10 | S26: =IFERROR(ABS(N$3-N26),"N/A") -> 35 | T26: =IFERROR(ABS(O$3-O26),"N/A") -> 32 | U26: =SUM(P26:T26) -> 145 | V26: =_xlfn.RANK.EQ(U26,$U$4:$U$64,1) -> 39 | W26: =IF(Y26="Not suitable","-",V26) -> 39 | Y26: =IF(OR(Z26="Y",AA26="Y"),"Not suitable","") | Z26: =IF(OR(N26="N/A",O26="N/A"),"Y","") | AS26: -1.9948011e+08 | AT26: 1.827028e+09 | AU26: 3.5303191e+08 | AV26: -1.6666935e+08 | AW26: 1.0002789e+09 | AX26: 1.3659687e+09 | AY26: 0.39154383 | AZ26: 0.23034092
B27: S32.AX | C27: South32 Ltd | D27: Diversified Mining | E27: Australia | F27: =AS27/AT27 -> -0.018451365 | G27: =AU27/AV27 -> 8.7929293 | H27: =AX27 -> 1.3361313e+10 | I27: =(AY27/AZ27)-1 -> -0.53175068 | J27: =AV27/AW27 -> 0.026652309 | K27: =IFERROR(_xlfn.RANK.EQ(F27,F$3:F$64),"N/A") -> 31 | L27: =IFERROR(_xlfn.RANK.EQ(G27,G$3:G$64),"N/A") -> 3 | M27: =IFERROR(_xlfn.RANK.EQ(H27,H$3:H$64),"N/A") -> 10 | N27: =IFERROR(_xlfn.RANK.EQ(I27,I$3:I$64),"N/A") -> 38 | O27: =IFERROR(_xlfn.RANK.EQ(J27,J$3:J$64),"N/A") -> 29 | P27: =IFERROR(ABS(K$3-K27),"N/A") -> 29 | Q27: =IFERROR(ABS(L$3-L27),"N/A") -> 24 | R27: =IFERROR(ABS(M$3-M27),"N/A") -> 1 | S27: =IFERROR(ABS(N$3-N27),"N/A") -> 7 | T27: =IFERROR(ABS(O$3-O27),"N/A") -> 27 | U27: =SUM(P27:T27) -> 88 | V27: =_xlfn.RANK.EQ(U27,$U$4:$U$64,1) -> 21 | W27: =IF(Y27="Not suitable","-",V27) -> 21 | Y27: =IF(OR(Z27="Y",AA27="Y"),"Not suitable","") | Z27: =IF(OR(N27="N/A",O27="N/A"),"Y","") | AS27: -259525950 | AT27: 14065406400 | AU27: 2611761150 | AV27: 297029700 | AW27: 11144614350 | AX27: 1.3361313e+10 | AY27: 0.1363822 | AZ27: 0.29125978
B28: ASM.TO | C28: Avino Silver & Gold Mines Ltd | D28: Diversified Mining | E28: Canada | F28: =AS28/AT28 -> 0.031585069 | G28: =AU28/AV28 -> 0.84267952 | H28: =AX28 -> 93867703 | I28: =(AY28/AZ28)-1 -> -0.61143312 | J28: =AV28/AW28 -> 0.17837826 | K28: =IFERROR(_xlfn.RANK.EQ(F28,F$3:F$64),"N/A") -> 27 | L28: =IFERROR(_xlfn.RANK.EQ(G28,G$3:G$64),"N/A") -> 23 | M28: =IFERROR(_xlfn.RANK.EQ(H28,H$3:H$64),"N/A") -> 44 | N28: =IFERROR(_xlfn.RANK.EQ(I28,I$3:I$64),"N/A") -> 40 | O28: =IFERROR(_xlfn.RANK.EQ(J28,J$3:J$64),"N/A") -> 16 | P28: =IFERROR(ABS(K$3-K28),"N/A") -> 25 | Q28: =IFERROR(ABS(L$3-L28),"N/A") -> 4 | R28: =IFERROR(ABS(M$3-M28),"N/A") -> 33 | S28: =IFERROR(ABS(N$3-N28),"N/A") -> 5 | T28: =IFERROR(ABS(O$3-O28),"N/A") -> 14 | U28: =SUM(P28:T28) -> 81 | V28: =_xlfn.RANK.EQ(U28,$U$4:$U$64,1) -> 19 | W28: =IF(Y28="Not suitable","-",V28) -> 19 | Y28: =IF(OR(Z28="Y",AA28="Y"),"Not suitable","") | Z28: =IF(OR(N28="N/A",O28="N/A"),"Y","") | AS28: 4544246.9 | AT28: 1.4387326e+08 | AU28: 9748994.8 | AV28: 11569042 | AW28: 64856795 | AX28: 93867703 | AY28: 0.016648814 | AZ28: 0.042846715
B29: FRES.L | C29: Fresnillo PLC | D29: Diversified Mining | E29: Mexico | F29: =AS29/AT29 -> 0.083644466 | G29: =AU29/AV29 -> 4.5087432 | H29: =AX29 -> 6.6251288e+09 | I29: =(AY29/AZ29)-1 -> 0.065260737 | J29: =AV29/AW29 -> 0.11656151 | K29: =IFERROR(_xlfn.RANK.EQ(F29,F$3:F$64),"N/A") -> 17 | L29: =IFERROR(_xlfn.RANK.EQ(G29,G$3:G$64),"N/A") -> 6 | M29: =IFERROR(_xlfn.RANK.EQ(H29,H$3:H$64),"N/A") -> 15 | N29: =IFERROR(_xlfn.RANK.EQ(I29,I$3:I$64),"N/A") -> 17 | O29: =IFERROR(_xlfn.RANK.EQ(J29,J$3:J$64),"N/A") -> 24 | P29: =IFERROR(ABS(K$3-K29),"N/A") -> 15 | Q29: =IFERROR(ABS(L$3-L29),"N/A") -> 21 | R29: =IFERROR(ABS(M$3-M29),"N/A") -> 4 | S29: =IFERROR(ABS(N$3-N29),"N/A") -> 28 | T29: =IFERROR(ABS(O$3-O29),"N/A") -> 22 | U29: =SUM(P29:T29) -> 90 | V29: =_xlfn.RANK.EQ(U29,$U$4:$U$64,1) -> 23 | W29: =IF(Y29="Not suitable","-",V29) -> 23 | Y29: =IF(OR(Z29="Y",AA29="Y"),"Not suitable","") | Z29: =IF(OR(N29="N/A",O29="N/A"),"Y","") | AS29: 4.5250336e+08 | AT29: 5.4098422e+09 | AU29: 1.876774e+09 | AV29: 4.1625213e+08 | AW29: 3.5710941e+09 | AX29: 6.6251288e+09 | AY29: 0.20869781 | AZ29: 0.19591242
B30: GFM.L | C30: Griffin Mining Ltd | D30: Diversified Mining | E30: United Kingdom | F30: =AS30/AT30 -> 0.03138533 | G30: =AU30/AV30 -> 0.054528 | H30: =AX30 -> 3.5263374e+08 | I30: =(AY30/AZ30)-1 -> -0.23488534 | J30: =AV30/AW30 -> 0.16552433 | K30: =IFERROR(_xlfn.RANK.EQ(F30,F$3:F$64),"N/A") -> 28 | L30: =IFERROR(_xlfn.RANK.EQ(G30,G$3:G$64),"N/A") -> 29 | M30: =IFERROR(_xlfn.RANK.EQ(H30,H$3:H$64),"N/A") -> 31 | N30: =IFERROR(_xlfn.RANK.EQ(I30,I$3:I$64),"N/A") -> 30 | O30: =IFERROR(_xlfn.RANK.EQ(J30,J$3:J$64),"N/A") -> 17 | P30: =IFERROR(ABS(K$3-K30),"N/A") -> 26 | Q30: =IFERROR(ABS(L$3-L30),"N/A") -> 2 | R30: =IFERROR(ABS(M$3-M30),"N/A") -> 20 | S30: =IFERROR(ABS(N$3-N30),"N/A") -> 15 | T30: =IFERROR(ABS(O$3-O30),"N/A") -> 15 | U30: =SUM(P30:T30) -> 78 | V30: =_xlfn.RANK.EQ(U30,$U$4:$U$64,1) -> 16 | W30: =IF(Y30="Not suitable","-",V30) -> 16 | Y30: =IF(OR(Z30="Y",AA30="Y"),"Not suitable","") | Z30: =IF(OR(N30="N/A",O30="N/A"),"Y","") | AS30: 11307777 | AT30: 3.6028862e+08 | AU30: 1250548.6 | AV30: 22934062 | AW30: 1.3855403e+08 | AX30: 3.5263374e+08 | AY30: 0.1374048 | AZ30: 0.1795872
B31: LUN.TO | C31: Lundin Mining Corp | D31: Diversified Mining | E31: Canada | F31: =AS31/AT31 -> 0.063541394 | G31: =AU31/AV31 -> 2.3415255 | H31: =AX31 -> 9.4601023e+09 | I31: =(AY31/AZ31)-1 -> 0.011027128 | J31: =AV31/AW31 -> 0.18706739 | K31: =IFERROR(_xlfn.RANK.EQ(F31,F$3:F$64),"N/A") -> 22 | L31: =IFERROR(_xlfn.RANK.EQ(G31,G$3:G$64),"N/A") -> 14 | M31: =IFERROR(_xlfn.RANK.EQ(H31,H$3:H$64),"N/A") -> 12 | N31: =IFERROR(_xlfn.RANK.EQ(I31,I$3:I$64),"N/A") -> 22 | O31: =IFERROR(_xlfn.RANK.EQ(J31,J$3:J$64),"N/A") -> 14 | P31: =IFERROR(ABS(K$3-K31),"N/A") -> 20 | Q31: =IFERROR(ABS(L$3-L31),"N/A") -> 13 | R31: =IFERROR(ABS(M$3-M31),"N/A") -> 1 | S31: =IFERROR(ABS(N$3-N31),"N/A") -> 23 | T31: =IFERROR(ABS(O$3-O31),"N/A") -> 12 | U31: =SUM(P31:T31) -> 69 | V31: =_xlfn.RANK.EQ(U31,$U$4:$U$64,1) -> 14 | W31: =IF(Y31="Not suitable","-",V31) -> 14 | Y31: =IF(OR(Z31="Y",AA31="Y"),"Not suitable","") | Z31: =IF(OR(N31="N/A",O31="N/A"),"Y","") | AS31: 4.6292109e+08 | AT31: 7.2853467e+09 | AU31: 2.181805e+09 | AV31: 9.3178785e+08 | AW31: 4.9810276e+09 | AX31: 9.4601023e+09 | AY31: 0.69291875 | AZ31: 0.68536118
B32: TECK.N | C32: Teck Resources Ltd | D32: Diversified Mining | E32: Canada | F32: =AS32/AT32 -> 0.086482881 | G32: =AU32/AV32 -> 2.5382151 | H32: =AX32 -> 3.109027e+10 | I32: =(AY32/AZ32)-1 -> -0.12085815 | J32: =AV32/AW32 -> 0.29111985 | K32: =IFERROR(_xlfn.RANK.EQ(F32,F$3:F$64),"N/A") -> 16 | L32: =IFERROR(_xlfn.RANK.EQ(G32,G$3:G$64),"N/A") -> 11 | M32: =IFERROR(_xlfn.RANK.EQ(H32,H$3:H$64),"N/A") -> 7 | N32: =IFERROR(_xlfn.RANK.EQ(I32,I$3:I$64),"N/A") -> 27 | O32: =IFERROR(_xlfn.RANK.EQ(J32,J$3:J$64),"N/A") -> 9 | P32: =IFERROR(ABS(K$3-K32),"N/A") -> 14 | Q32: =IFERROR(ABS(L$3-L32),"N/A") -> 16 | R32: =IFERROR(ABS(M$3-M32),"N/A") -> 4 | S32: =IFERROR(ABS(N$3-N32),"N/A") -> 18 | T32: =IFERROR(ABS(O$3-O32),"N/A") -> 7 | U32: =SUM(P32:T32) -> 59 | V32: =_xlfn.RANK.EQ(U32,$U$4:$U$64,1) -> 9 | W32: =IF(Y32="Not suitable","-",V32) -> 9 | Y32: =IF(OR(Z32="Y",AA32="Y"),"Not suitable","") | Z32: =IF(OR(N32="N/A",O32="N/A"),"Y","") | AS32: 2.5876298e+09 | AT32: 2.9920716e+10 | AU32: 1.2297339e+10 | AV32: 4.8448766e+09 | AW32: 1.6642207e+10 | AX32: 3.109027e+10 | AY32: 5.2905202 | AZ32: 6.0178233
B33: RIO.L | C33: Rio Tinto PLC | D33: Diversified Mining | E33: United Kingdom | F33: =AS33/AT33 -> 0.18233613 | G33: =AU33/AV33 -> 0.96822506 | H33: =AX33 -> 1.7034585e+11 | I33: =(AY33/AZ33)-1 -> 0.094519941 | J33: =AV33/AW33 -> 0.27429174 | K33: =IFERROR(_xlfn.RANK.EQ(F33,F$3:F$64),"N/A") -> 9 | L33: =IFERROR(_xlfn.RANK.EQ(G33,G$3:G$64),"N/A") -> 21 | M33: =IFERROR(_xlfn.RANK.EQ(H33,H$3:H$64),"N/A") -> 2 | N33: =IFERROR(_xlfn.RANK.EQ(I33,I$3:I$64),"N/A") -> 16 | O33: =IFERROR(_xlfn.RANK.EQ(J33,J$3:J$64),"N/A") -> 10 | P33: =IFERROR(ABS(K$3-K33),"N/A") -> 7 | Q33: =IFERROR(ABS(L$3-L33),"N/A") -> 6 | R33: =IFERROR(ABS(M$3-M33),"N/A") -> 9 | S33: =IFERROR(ABS(N$3-N33),"N/A") -> 29 | T33: =IFERROR(ABS(O$3-O33),"N/A") -> 8 | U33: =SUM(P33:T33) -> 59 | V33: =_xlfn.RANK.EQ(U33,$U$4:$U$64,1) -> 9 | W33: =IF(Y33="Not suitable","-",V33) -> 9 | Y33: =IF(OR(Z33="Y",AA33="Y"),"Not suitable","") | Z33: =IF(OR(N33="N/A",O33="N/A"),"Y","") | AS33: 14615283790 | AT33: 80155719980 | AU33: 21074907360 | AV33: 21766537890 | AW33: 79355425630 | AX33: 1.7034585e+11 | AY33: 12.140034 | AZ33: 11.091651
B34: PX.PS | C34: Philex Mining Corp | D34: Diversified Mining | E34: Philippines | F34: =AS34/AT34 -> 0.058164536 | G34: =AU34/AV34 -> 3.5132474 | H34: =AX34 -> 4.5824389e+08 | I34: =(AY34/AZ34)-1 -> 0.045454545 | J34: =AV34/AW34 -> 0.23126215 | K34: =IFERROR(_xlfn.RANK.EQ(F34,F$3:F$64),"N/A") -> 23 | L34: =IFERROR(_xlfn.RANK.EQ(G34,G$3:G$64),"N/A") -> 9 | M34: =IFERROR(_xlfn.RANK.EQ(H34,H$3:H$64),"N/A") -> 27 | N34: =IFERROR(_xlfn.RANK.EQ(I34,I$3:I$64),"N/A") -> 19 | O34: =IFERROR(_xlfn.RANK.EQ(J34,J$3:J$64),"N/A") -> 12 | P34: =IFERROR(ABS(K$3-K34),"N/A") -> 21 | Q34: =IFERROR(ABS(L$3-L34),"N/A") -> 18 | R34: =IFERROR(ABS(M$3-M34),"N/A") -> 16 | S34: =IFERROR(ABS(N$3-N34),"N/A") -> 26 | T34: =IFERROR(ABS(O$3-O34),"N/A") -> 10 | U34: =SUM(P34:T34) -> 91 | V34: =_xlfn.RANK.EQ(U34,$U$4:$U$64,1) -> 24 | W34: =IF(Y34="Not suitable","-",V34) -> 24 | Y34: =IF(OR(Z34="Y",AA34="Y"),"Not suitable","") | Z34: =IF(OR(N34="N/A",O34="N/A"),"Y","") | AS34: 47340005 | AT34: 8.1389809e+08 | AU34: 1.983983e+08 | AV34: 56471484 | AW34: 2.4418818e+08 | AX34: 4.5824389e+08 | AY34: 0.0049725784 | AZ34: 0.0047563794
B35: RIO.AX | C35: Rio Tinto Ltd | D35: Diversified Mining | E35: Australia | F35: =AS35/AT35 -> 0.18233613 | G35: =AU35/AV35 -> 0.96822506 | H35: =AX35 -> 1.7034585e+11 | I35: =(AY35/AZ35)-1 -> 0.11449035 | J35: =AV35/AW35 -> 0.27429174 | K35: =IFERROR(_xlfn.RANK.EQ(F35,F$3:F$64),"N/A") -> 9 | L35: =IFERROR(_xlfn.RANK.EQ(G35,G$3:G$64),"N/A") -> 21 | M35: =IFERROR(_xlfn.RANK.EQ(H35,H$3:H$64),"N/A") -> 2 | N35: =IFERROR(_xlfn.RANK.EQ(I35,I$3:I$64),"N/A") -> 15 | O35: =IFERROR(_xlfn.RANK.EQ(J35,J$3:J$64),"N/A") -> 10 | P35: =IFERROR(ABS(K$3-K35),"N/A") -> 7 | Q35: =IFERROR(ABS(L$3-L35),"N/A") -> 6 | R35: =IFERROR(ABS(M$3-M35),"N/A") -> 9 | S35: =IFERROR(ABS(N$3-N35),"N/A") -> 30 | T35: =IFERROR(ABS(O$3-O35),"N/A") -> 8 | U35: =SUM(P35:T35) -> 60 | V35: =_xlfn.RANK.EQ(U35,$U$4:$U$64,1) -> 11 | W35: =IF(Y35="Not suitable","-",V35) -> 11 | Y35: =IF(OR(Z35="Y",AA35="Y"),"Not suitable","") | Z35: =IF(OR(N35="N/A",O35="N/A"),"Y","") | AS35: 14615283790 | AT35: 80155719980 | AU35: 21074907360 | AV35: 21766537890 | AW35: 79355425630 | AX35: 1.7034585e+11 | AY35: 12.42844 | AZ35: 11.15168
B36: DPM.TO | C36: Dundee Precious Metals Inc | D36: Diversified Mining | E36: Canada | F36: =AS36/AT36 -> 0.16239882 | G36: =AU36/AV36 -> 0.067138036 | H36: =AX36 -> 1.9367763e+09 | I36: =(AY36/AZ36)-1 -> -0.087244598 | J36: =AV36/AW36 -> 0.35895641 | K36: =IFERROR(_xlfn.RANK.EQ(F36,F$3:F$64),"N/A") -> 11 | L36: =IFERROR(_xlfn.RANK.EQ(G36,G$3:G$64),"N/A") -> 28 | M36: =IFERROR(_xlfn.RANK.EQ(H36,H$3:H$64),"N/A") -> 18 | N36: =IFERROR(_xlfn.RANK.EQ(I36,I$3:I$64),"N/A") -> 26 | O36: =IFERROR(_xlfn.RANK.EQ(J36,J$3:J$64),"N/A") -> 8 | P36: =IFERROR(ABS(K$3-K36),"N/A") -> 9 | Q36: =IFERROR(ABS(L$3-L36),"N/A") -> 1 | R36: =IFERROR(ABS(M$3-M36),"N/A") -> 7 | S36: =IFERROR(ABS(N$3-N36),"N/A") -> 19 | T36: =IFERROR(ABS(O$3-O36),"N/A") -> 6 | U36: =SUM(P36:T36) -> 42 | V36: =_xlfn.RANK.EQ(U36,$U$4:$U$64,1) -> 3 | W36: =IF(Y36="Not suitable","-",V36) -> 3 | Y36: =IF(OR(Z36="Y",AA36="Y"),"Not suitable","") | Z36: =IF(OR(N36="N/A",O36="N/A"),"Y","") | AS36: 2.6721902e+08 | AT36: 1.6454492e+09 | AU36: 18405302 | AV36: 2.741412e+08 | AW36: 7.6371723e+08 | AX36: 1.9367763e+09 | AY36: 1.442381 | AZ36: 1.5802492
B37: MDKA.JK | C37: Merdeka Copper Gold Tbk PT | D37: Diversified Mining | E37: Indonesia | F37: =AS37/AT37 -> 0.064638626 | G37: =AU37/AV37 -> 12.727928 | H37: =AX37 -> 5.3695705e+09 | I37: =(AY37/AZ37)-1 -> -1.1155456 | J37: =AV37/AW37 -> 0.1275169 | K37: =IFERROR(_xlfn.RANK.EQ(F37,F$3:F$64),"N/A") -> 21 | L37: =IFERROR(_xlfn.RANK.EQ(G37,G$3:G$64),"N/A") -> 2 | M37: =IFERROR(_xlfn.RANK.EQ(H37,H$3:H$64),"N/A") -> 16 | N37: =IFERROR(_xlfn.RANK.EQ(I37,I$3:I$64),"N/A") -> 57 | O37: =IFERROR(_xlfn.RANK.EQ(J37,J$3:J$64),"N/A") -> 22 | P37: =IFERROR(ABS(K$3-K37),"N/A") -> 19 | Q37: =IFERROR(ABS(L$3-L37),"N/A") -> 25 | R37: =IFERROR(ABS(M$3-M37),"N/A") -> 5 | S37: =IFERROR(ABS(N$3-N37),"N/A") -> 12 | T37: =IFERROR(ABS(O$3-O37),"N/A") -> 20 | U37: =SUM(P37:T37) -> 81 | V37: =_xlfn.RANK.EQ(U37,$U$4:$U$64,1) -> 19 | W37: =IF(Y37="Not suitable","-",V37) -> 19 | Y37: =IF(OR(Z37="Y",AA37="Y"),"Not suitable","") | Z37: =IF(OR(N37="N/A",O37="N/A"),"Y","") | AS37: 95177915 | AT37: 1.4724619e+09 | AU37: 2.0722648e+09 | AV37: 1.6281243e+08 | AW37: 1.276791e+09 | AX37: 5.3695705e+09 | AY37: -0.0007012194 | AZ37: 0.0060687662
... B39: GMEXICOB.MX | C39: Grupo Mexico SAB de CV | D39: Diversified Mining | E39: Mexico | F39: =AS39/AT39 -> 0.210438 | G39: =AU39/AV39 -> 1.5662498 | H39: =AX39 -> 5.8344758e+10 | I39: =(AY39/AZ39)-1 -> -0.057117464 | J39: =AV39/AW39 -> 0.40855999 | K39: =IFERROR(_xlfn.RANK.EQ(F39,F$3:F$64),"N/A") -> 7 | L39: =IFERROR(_xlfn.RANK.EQ(G39,G$3:G$64),"N/A") -> 16 | M39: =IFERROR(_xlfn.RANK.EQ(H39,H$3:H$64),"N/A") -> 5 | N39: =IFERROR(_xlfn.RANK.EQ(I39,I$3:I$64),"N/A") -> 23 | O39: =IFERROR(_xlfn.RANK.EQ(J39,J$3:J$64),"N/A") -> 7 | P39: =IFERROR(ABS(K$3-K39),"N/A") -> 5 | Q39: =IFERROR(ABS(L$3-L39),"N/A") -> 11 | R39: =IFERROR(ABS(M$3-M39),"N/A") -> 6 | S39: =IFERROR(ABS(N$3-N39),"N/A") -> 22 | T39: =IFERROR(ABS(O$3-O39),"N/A") -> 5 | U39: =SUM(P39:T39) -> 49 | V39: =_xlfn.RANK.EQ(U39,$U$4:$U$64,1) -> 6 | W39: =IF(Y39="Not suitable","-",V39) -> 6 | Y39: =IF(OR(Z39="Y",AA39="Y"),"Not suitable","") | Z39: =IF(OR(N39="N/A",O39="N/A"),"Y","") | AS39: 5.8801958e+09 | AT39: 2.7942652e+10 | AU39: 1.3517396e+10 | AV39: 8.6304213e+09 | AW39: 2.1124e+10 | AX39: 5.8344758e+10 | AY39: 0.60256585 | AZ39: 0.63906778
B40: ECORE.L | C40: Ecora Resources PLC | D40: Diversified Mining | E40: United Kingdom | F40: =AS40/AT40 -> 0.18791948 | G40: =AU40/AV40 -> 0.37920263 | H40: =AX40 -> 3.7431478e+08 | I40: =(AY40/AZ40)-1 -> -0.67302021 | J40: =AV40/AW40 -> 0.79877353 | K40: =IFERROR(_xlfn.RANK.EQ(F40,F$3:F$64),"N/A") -> 8 | L40: =IFERROR(_xlfn.RANK.EQ(G40,G$3:G$64),"N/A") -> 25 | M40: =IFERROR(_xlfn.RANK.EQ(H40,H$3:H$64),"N/A") -> 29 | N40: =IFERROR(_xlfn.RANK.EQ(I40,I$3:I$64),"N/A") -> 41 | O40: =IFERROR(_xlfn.RANK.EQ(J40,J$3:J$64),"N/A") -> 1 | P40: =IFERROR(ABS(K$3-K40),"N/A") -> 6 | Q40: =IFERROR(ABS(L$3-L40),"N/A") -> 2 | R40: =IFERROR(ABS(M$3-M40),"N/A") -> 18 | S40: =IFERROR(ABS(N$3-N40),"N/A") -> 4 | T40: =IFERROR(ABS(O$3-O40),"N/A") -> 1 | U40: =SUM(P40:T40) -> 31 | V40: =_xlfn.RANK.EQ(U40,$U$4:$U$64,1) -> 2 | W40: =IF(Y40="Not suitable","-",V40) -> 2 | Y40: =IF(OR(Z40="Y",AA40="Y"),"Not suitable","") | Z40: =IF(OR(N40="N/A",O40="N/A"),"Y","") | AB40: No P/E | AS40: 1.389063e+08 | AT40: 7.3917988e+08 | AU40: 63073442 | AV40: 1.6633177e+08 | AW40: 2.0823395e+08 | AX40: 3.7431478e+08 | AY40: 0.18805058 | AZ40: 0.57511378
B41: SYR.AX | C41: Syrah Resources Ltd | D41: Diversified Mining | E41: Australia | F41: =AS41/AT41 -> -0.061595824 | G41: =AU41/AV41 -> -3.241156 | H41: =AX41 -> 4.6832907e+08 | I41: =(AY41/AZ41)-1 -> 1.3799491 | J41: =AV41/AW41 -> -0.24865323 | K41: =IFERROR(_xlfn.RANK.EQ(F41,F$3:F$64),"N/A") -> 37 | L41: =IFERROR(_xlfn.RANK.EQ(G41,G$3:G$64),"N/A") -> 58 | M41: =IFERROR(_xlfn.RANK.EQ(H41,H$3:H$64),"N/A") -> 26 | N41: =IFERROR(_xlfn.RANK.EQ(I41,I$3:I$64),"N/A") -> 9 | O41: =IFERROR(_xlfn.RANK.EQ(J41,J$3:J$64),"N/A") -> 41 | P41: =IFERROR(ABS(K$3-K41),"N/A") -> 35 | Q41: =IFERROR(ABS(L$3-L41),"N/A") -> 31 | R41: =IFERROR(ABS(M$3-M41),"N/A") -> 15 | S41: =IFERROR(ABS(N$3-N41),"N/A") -> 36 | T41: =IFERROR(ABS(O$3-O41),"N/A") -> 39 | U41: =SUM(P41:T41) -> 156 | V41: =_xlfn.RANK.EQ(U41,$U$4:$U$64,1) -> 48 | W41: =IF(Y41="Not suitable","-",V41) -> 48 | Y41: =IF(OR(Z41="Y",AA41="Y"),"Not suitable","") | Z41: =IF(OR(N41="N/A",O41="N/A"),"Y","") | AS41: -39402554 | AT41: 6.3969522e+08 | AU41: 1.2560234e+08 | AV41: -38752328 | AW41: 1.5584888e+08 | AX41: 4.6832907e+08 | AY41: -0.1396809 | AZ41: -0.05869071
B42: HZNC.NS | C42: Hindustan Zinc Ltd | D42: Diversified Mining | E42: India | F42: =AS42/AT42 -> 0.79322611 | G42: =AU42/AV42 -> 0.83276092 | H42: =AX42 -> 2.4411842e+10 | I42: =(AY42/AZ42)-1 -> -0.25640387 | J42: =AV42/AW42 -> 0.41841164 | K42: =IFERROR(_xlfn.RANK.EQ(F42,F$3:F$64),"N/A") -> 1 | L42: =IFERROR(_xlfn.RANK.EQ(G42,G$3:G$64),"N/A") -> 24 | M42: =IFERROR(_xlfn.RANK.EQ(H42,H$3:H$64),"N/A") -> 8 | N42: =IFERROR(_xlfn.RANK.EQ(I42,I$3:I$64),"N/A") -> 32 | O42: =IFERROR(_xlfn.RANK.EQ(J42,J$3:J$64),"N/A") -> 6 | P42: =IFERROR(ABS(K$3-K42),"N/A") -> 1 | Q42: =IFERROR(ABS(L$3-L42),"N/A") -> 3 | R42: =IFERROR(ABS(M$3-M42),"N/A") -> 3 | S42: =IFERROR(ABS(N$3-N42),"N/A") -> 13 | T42: =IFERROR(ABS(O$3-O42),"N/A") -> 4 | U42: =SUM(P42:T42) -> 24 | V42: =_xlfn.RANK.EQ(U42,$U$4:$U$64,1) -> 1 | W42: =IF(Y42="Not suitable","-",V42) -> 1 | Y42: =IF(OR(Z42="Y",AA42="Y"),"Not suitable","") | Z42: =IF(OR(N42="N/A",O42="N/A"),"Y","") | AS42: 1.8676777e+09 | AT42: 2.3545338e+09 | AU42: 2.1631778e+09 | AV42: 2.5975977e+09 | AW42: 6.2082348e+09 | AX42: 2.4411842e+10 | AY42: 0.3434156 | AZ42: 0.4618308
B43: 000975.SZ | C43: Yintai Gold Co Ltd | D43: Diversified Mining | E43: China | F43: =AS43/AT43 -> 0.1140176 | G43: =AU43/AV43 -> 1.4145771 | H43: =AX43 -> 9.1395173e+09 | I43: =(AY43/AZ43)-1 -> 0.15545733 | J43: =AV43/AW43 -> 0.1925961 | K43: =IFERROR(_xlfn.RANK.EQ(F43,F$3:F$64),"N/A") -> 14 | L43: =IFERROR(_xlfn.RANK.EQ(G43,G$3:G$64),"N/A") -> 17 | M43: =IFERROR(_xlfn.RANK.EQ(H43,H$3:H$64),"N/A") -> 13 | N43: =IFERROR(_xlfn.RANK.EQ(I43,I$3:I$64),"N/A") -> 14 | O43: =IFERROR(_xlfn.RANK.EQ(J43,J$3:J$64),"N/A") -> 13 | P43: =IFERROR(ABS(K$3-K43),"N/A") -> 12 | Q43: =IFERROR(ABS(L$3-L43),"N/A") -> 10 | R43: =IFERROR(ABS(M$3-M43),"N/A") -> 2 | S43: =IFERROR(ABS(N$3-N43),"N/A") -> 31 | T43: =IFERROR(ABS(O$3-O43),"N/A") -> 11 | U43: =SUM(P43:T43) -> 66 | V43: =_xlfn.RANK.EQ(U43,$U$4:$U$64,1) -> 12 | W43: =IF(Y43="Not suitable","-",V43) -> 12 | Y43: =IF(OR(Z43="Y",AA43="Y"),"Not suitable","") | Z43: =IF(OR(N43="N/A",O43="N/A"),"Y","") | AS43: 2.6478625e+08 | AT43: 2.3223279e+09 | AU43: 4.8594407e+08 | AV43: 3.4352604e+08 | AW43: 1.7836604e+09 | AX43: 9.1395173e+09 | AY43: 0.11860813 | AZ43: 0.10265038
B44: NYR.BR | C44: Nyrstar NV | D44: Diversified Mining | E44: Belgium | F44: =AS44/AT44 -> 0.33967742 | G44: =AU44/AV44 -> -12.329851 | H44: =AX44 -> 12737562 | I44: =(AY44/AZ44)-1 -> -1 | J44: =AV44/AW44 -> -1.5858238 | K44: =IFERROR(_xlfn.RANK.EQ(F44,F$3:F$64),"N/A") -> 5 | L44: =IFERROR(_xlfn.RANK.EQ(G44,G$3:G$64),"N/A") -> 61 | M44: =IFERROR(_xlfn.RANK.EQ(H44,H$3:H$64),"N/A") -> 61 | N44: =IFERROR(_xlfn.RANK.EQ(I44,I$3:I$64),"N/A") -> 47 | O44: =IFERROR(_xlfn.RANK.EQ(J44,J$3:J$64),"N/A") -> 49 | P44: =IFERROR(ABS(K$3-K44),"N/A") -> 3 | Q44: =IFERROR(ABS(L$3-L44),"N/A") -> 34 | R44: =IFERROR(ABS(M$3-M44),"N/A") -> 50 | S44: =IFERROR(ABS(N$3-N44),"N/A") -> 2 | T44: =IFERROR(ABS(O$3-O44),"N/A") -> 47 | U44: =SUM(P44:T44) -> 136 | V44: =_xlfn.RANK.EQ(U44,$U$4:$U$64,1) -> 35 | W44: =IF(Y44="Not suitable","-",V44) -> - | Y44: Not Suitable | AS44: -1332516.2 | AT44: -3922887.1 | AU44: 15426267 | AV44: -1251131.7 | AW44: 788947.46 | AX44: 12737562 | AZ44: -2.2552791
B45: BSX.AX | C45: Blackstone Minerals Ltd | D45: Diversified Mining | E45: Australia | F45: =AS45/AT45 -> -1.0941848 | G45: =AU45/AV45 -> -0.014668867 | H45: =AX45 -> 29877754 | I45: =(AY45/AZ45)-1 -> -1 | J45: =AV45/AW45 -> -7.0645502 | K45: =IFERROR(_xlfn.RANK.EQ(F45,F$3:F$64),"N/A") -> 61 | L45: =IFERROR(_xlfn.RANK.EQ(G45,G$3:G$64),"N/A") -> 36 | M45: =IFERROR(_xlfn.RANK.EQ(H45,H$3:H$64),"N/A") -> 58 | N45: =IFERROR(_xlfn.RANK.EQ(I45,I$3:I$64),"N/A") -> 47 | O45: =IFERROR(_xlfn.RANK.EQ(J45,J$3:J$64),"N/A") -> 53 | P45: =IFERROR(ABS(K$3-K45),"N/A") -> 59 | Q45: =IFERROR(ABS(L$3-L45),"N/A") -> 9 | R45: =IFERROR(ABS(M$3-M45),"N/A") -> 47 | S45: =IFERROR(ABS(N$3-N45),"N/A") -> 2 | T45: =IFERROR(ABS(O$3-O45),"N/A") -> 51 | U45: =SUM(P45:T45) -> 168 | V45: =_xlfn.RANK.EQ(U45,$U$4:$U$64,1) -> 52 | W45: =IF(Y45="Not suitable","-",V45) -> - | Y45: Not Suitable | AS45: -34483660 | AT45: 31515390 | AU45: 436910 | AV45: -29784850 | AW45: 4216100 | AX45: 29877754 | AZ45: -0.01908
B46: DVP.AX | C46: Develop Global Ltd | D46: Diversified Mining | E46: Australia | F46: =AS46/AT46 -> -0.11952959 | G46: =AU46/AV46 -> -2.3935377 | H46: =AX46 -> 6.0906049e+08 | I46: =(AY46/AZ46)-1 -> -1 | J46: =AV46/AW46 -> -0.17206725 | K46: =IFERROR(_xlfn.RANK.EQ(F46,F$3:F$64),"N/A") -> 44 | L46: =IFERROR(_xlfn.RANK.EQ(G46,G$3:G$64),"N/A") -> 55 | M46: =IFERROR(_xlfn.RANK.EQ(H46,H$3:H$64),"N/A") -> 23 | N46: =IFERROR(_xlfn.RANK.EQ(I46,I$3:I$64),"N/A") -> 47 | O46: =IFERROR(_xlfn.RANK.EQ(J46,J$3:J$64),"N/A") -> 36 | P46: =IFERROR(ABS(K$3-K46),"N/A") -> 42 | Q46: =IFERROR(ABS(L$3-L46),"N/A") -> 28 | R46: =IFERROR(ABS(M$3-M46),"N/A") -> 12 | S46: =IFERROR(ABS(N$3-N46),"N/A") -> 2 | T46: =IFERROR(ABS(O$3-O46),"N/A") -> 34 | U46: =SUM(P46:T46) -> 118 | V46: =_xlfn.RANK.EQ(U46,$U$4:$U$64,1) -> 26 | W46: =IF(Y46="Not suitable","-",V46) -> - | Y46: Not Suitable | AS46: -17888910 | AT46: 149660930 | AU46: 27913150 | AV46: -11661880 | AW46: 67775130 | AX46: 6.0906049e+08 | AZ46: -0.04988
B47: GGD.TO | C47: GoGold Resources Inc | D47: Diversified Mining | E47: Canada | F47: =AS47/AT47 -> -0.028022745 | G47: =AU47/AV47 -> -0.1159919 | H47: =AX47 -> 4.0456167e+08 | I47: =(AY47/AZ47)-1 -> -2.1903449 | J47: =AV47/AW47 -> -0.48975545 | K47: =IFERROR(_xlfn.RANK.EQ(F47,F$3:F$64),"N/A") -> 32 | L47: =IFERROR(_xlfn.RANK.EQ(G47,G$3:G$64),"N/A") -> 41 | M47: =IFERROR(_xlfn.RANK.EQ(H47,H$3:H$64),"N/A") -> 28 | N47: =IFERROR(_xlfn.RANK.EQ(I47,I$3:I$64),"N/A") -> 62 | O47: =IFERROR(_xlfn.RANK.EQ(J47,J$3:J$64),"N/A") -> 45 | P47: =IFERROR(ABS(K$3-K47),"N/A") -> 30 | Q47: =IFERROR(ABS(L$3-L47),"N/A") -> 14 | R47: =IFERROR(ABS(M$3-M47),"N/A") -> 17 | S47: =IFERROR(ABS(N$3-N47),"N/A") -> 17 | T47: =IFERROR(ABS(O$3-O47),"N/A") -> 43 | U47: =SUM(P47:T47) -> 121 | V47: =_xlfn.RANK.EQ(U47,$U$4:$U$64,1) -> 28 | W47: =IF(Y47="Not suitable","-",V47) -> 28 | Y47: =IF(OR(Z47="Y",AA47="Y"),"Not suitable","") | Z47: =IF(OR(N47="N/A",O47="N/A"),"Y","") | AS47: -12262954 | AT47: 4.3760715e+08 | AU47: 2671738.6 | AV47: -23033837 | AW47: 47031302 | AX47: 4.0456167e+08 | AY47: 0.0097996788 | AZ47: -0.0082326384
B48: CXO.AX | C48: Core Lithium Ltd | D48: Diversified Mining | E48: Australia | F48: =AS48/AT48 -> 0.030457396 | G48: =AU48/AV48 -> 2.4863459 | H48: =AX48 -> 5.2354921e+08 | I48: =(AY48/AZ48)-1 -> -0.91279621 | J48: =AV48/AW48 -> 0.18237875 | K48: =IFERROR(_xlfn.RANK.EQ(F48,F$3:F$64),"N/A") -> 29 | L48: =IFERROR(_xlfn.RANK.EQ(G48,G$3:G$64),"N/A") -> 13 | M48: =IFERROR(_xlfn.RANK.EQ(H48,H$3:H$64),"N/A") -> 24 | N48: =IFERROR(_xlfn.RANK.EQ(I48,I$3:I$64),"N/A") -> 46 | O48: =IFERROR(_xlfn.RANK.EQ(J48,J$3:J$64),"N/A") -> 15 | P48: =IFERROR(ABS(K$3-K48),"N/A") -> 27 | Q48: =IFERROR(ABS(L$3-L48),"N/A") -> 14 | R48: =IFERROR(ABS(M$3-M48),"N/A") -> 13 | S48: =IFERROR(ABS(N$3-N48),"N/A") -> 1 | T48: =IFERROR(ABS(O$3-O48),"N/A") -> 13 | U48: =SUM(P48:T48) -> 68 | V48: =_xlfn.RANK.EQ(U48,$U$4:$U$64,1) -> 13 | W48: =IF(Y48="Not suitable","-",V48) -> 13 | Y48: =IF(OR(Z48="Y",AA48="Y"),"Not suitable","") | Z48: =IF(OR(N48="N/A",O48="N/A"),"Y","") | AS48: 10810000 | AT48: 354922000 | AU48: 22944000 | AV48: 9228000 | AW48: 50598000 | AX48: 5.2354921e+08 | AY48: 0.00092 | AZ48: 0.01055
B49: ALS.TO | C49: Altius Minerals Corp | D49: Diversified Mining | E49: Canada | F49: =AS49/AT49 -> 0.081206434 | G49: =AU49/AV49 -> 2.0956517 | H49: =AX49 -> 9.6453243e+08 | I49: =(AY49/AZ49)-1 -> -0.70000658 | J49: =AV49/AW49 -> 0.56521015 | K49: =IFERROR(_xlfn.RANK.EQ(F49,F$3:F$64),"N/A") -> 18 | L49: =IFERROR(_xlfn.RANK.EQ(G49,G$3:G$64),"N/A") -> 15 | M49: =IFERROR(_xlfn.RANK.EQ(H49,H$3:H$64),"N/A") -> 22 | N49: =IFERROR(_xlfn.RANK.EQ(I49,I$3:I$64),"N/A") -> 42 | O49: =IFERROR(_xlfn.RANK.EQ(J49,J$3:J$64),"N/A") -> 4 | P49: =IFERROR(ABS(K$3-K49),"N/A") -> 16 | Q49: =IFERROR(ABS(L$3-L49),"N/A") -> 12 | R49: =IFERROR(ABS(M$3-M49),"N/A") -> 11 | S49: =IFERROR(ABS(N$3-N49),"N/A") -> 3 | T49: =IFERROR(ABS(O$3-O49),"N/A") -> 2 | U49: =SUM(P49:T49) -> 44 | V49: =_xlfn.RANK.EQ(U49,$U$4:$U$64,1) -> 4 | W49: =IF(Y49="Not suitable","-",V49) -> 4 | Y49: =IF(OR(Z49="Y",AA49="Y"),"Not suitable","") | Z49: =IF(OR(N49="N/A",O49="N/A"),"Y","") | AS49: 42771341 | AT49: 5.2669892e+08 | AU49: 1.3094322e+08 | AV49: 62483294 | AW49: 1.1054878e+08 | AX49: 9.6453243e+08 | AY49: 0.26900811 | AZ49: 0.89671334
B50: MAI.V | C50: Minera Alamos Inc | D50: Diversified Mining | E50: Canada | F50: =AS50/AT50 -> 0.1298274 | G50: =AU50/AV50 -> 0.31065585 | H50: =AX50 -> 1.5459893e+08 | I50: =(AY50/AZ50)-1 -> -1.3880565 | J50: =AV50/AW50 -> 0.055111775 | K50: =IFERROR(_xlfn.RANK.EQ(F50,F$3:F$64),"N/A") -> 13 | L50: =IFERROR(_xlfn.RANK.EQ(G50,G$3:G$64),"N/A") -> 26 | M50: =IFERROR(_xlfn.RANK.EQ(H50,H$3:H$64),"N/A") -> 38 | N50: =IFERROR(_xlfn.RANK.EQ(I50,I$3:I$64),"N/A") -> 59 | O50: =IFERROR(_xlfn.RANK.EQ(J50,J$3:J$64),"N/A") -> 27 | P50: =IFERROR(ABS(K$3-K50),"N/A") -> 11 | Q50: =IFERROR(ABS(L$3-L50),"N/A") -> 1 | R50: =IFERROR(ABS(M$3-M50),"N/A") -> 27 | S50: =IFERROR(ABS(N$3-N50),"N/A") -> 14 | T50: =IFERROR(ABS(O$3-O50),"N/A") -> 25 | U50: =SUM(P50:T50) -> 78 | V50: =_xlfn.RANK.EQ(U50,$U$4:$U$64,1) -> 16 | W50: =IF(Y50="Not suitable","-",V50) -> 16 | Y50: =IF(OR(Z50="Y",AA50="Y"),"Not suitable","") | Z50: =IF(OR(N50="N/A",O50="N/A"),"Y","") | AS50: 6076721.9 | AT50: 46806160 | AU50: 402959.72 | AV50: 1297125.8 | AW50: 23536273 | AX50: 1.5459893e+08 | AY50: -0.0122799 | AZ50: 0.031644615
B51: ELE.V | C51: Elemental Altus Royalties Corp | D51: Diversified Mining | E51: Canada | F51: =AS51/AT51 -> -0.12436914 | G51: =AU51/AV51 -> -2.4379515 | H51: =AX51 -> 2.2827686e+08 | I51: =(AY51/AZ51)-1 -> -0.53638305 | J51: =AV51/AW51 -> -1.2782446 | K51: =IFERROR(_xlfn.RANK.EQ(F51,F$3:F$64),"N/A") -> 45 | L51: =IFERROR(_xlfn.RANK.EQ(G51,G$3:G$64),"N/A") -> 56 | M51: =IFERROR(_xlfn.RANK.EQ(H51,H$3:H$64),"N/A") -> 35 | N51: =IFERROR(_xlfn.RANK.EQ(I51,I$3:I$64),"N/A") -> 39 | O51: =IFERROR(_xlfn.RANK.EQ(J51,J$3:J$64),"N/A") -> 48 | P51: =IFERROR(ABS(K$3-K51),"N/A") -> 43 | Q51: =IFERROR(ABS(L$3-L51),"N/A") -> 29 | R51: =IFERROR(ABS(M$3-M51),"N/A") -> 24 | S51: =IFERROR(ABS(N$3-N51),"N/A") -> 6 | T51: =IFERROR(ABS(O$3-O51),"N/A") -> 46 | U51: =SUM(P51:T51) -> 148 | V51: =_xlfn.RANK.EQ(U51,$U$4:$U$64,1) -> 42 | W51: =IF(Y51="Not suitable","-",V51) -> 42 | Y51: =IF(OR(Z51="Y",AA51="Y"),"Not suitable","") | Z51: =IF(OR(N51="N/A",O51="N/A"),"Y","") | AS51: -26729742 | AT51: 2.1492262e+08 | AU51: 44089176 | AV51: -18084517 | AW51: 14147931 | AX51: 2.2827686e+08 | AY51: -0.063441575 | AZ51: -0.1368405
B52: SRL.AX | C52: Sunrise Energy Metals Ltd | D52: Diversified Mining | E52: Australia | F52: =AS52/AT52 -> -0.56512579 | G52: =AU52/AV52 -> -0.010206321 | H52: =AX52 -> 33835312 | I52: =(AY52/AZ52)-1 -> 6.1276596 | J52: =AV52/AW52 -> -6.1609195 | K52: =IFERROR(_xlfn.RANK.EQ(F52,F$3:F$64),"N/A") -> 55 | L52: =IFERROR(_xlfn.RANK.EQ(G52,G$3:G$64),"N/A") -> 35 | M52: =IFERROR(_xlfn.RANK.EQ(H52,H$3:H$64),"N/A") -> 56 | N52: =IFERROR(_xlfn.RANK.EQ(I52,I$3:I$64),"N/A") -> 1 | O52: =IFERROR(_xlfn.RANK.EQ(J52,J$3:J$64),"N/A") -> 52 | P52: =IFERROR(ABS(K$3-K52),"N/A") -> 53 | Q52: =IFERROR(ABS(L$3-L52),"N/A") -> 8 | R52: =IFERROR(ABS(M$3-M52),"N/A") -> 45 | S52: =IFERROR(ABS(N$3-N52),"N/A") -> 44 | T52: =IFERROR(ABS(O$3-O52),"N/A") -> 50 | U52: =SUM(P52:T52) -> 200 | V52: =_xlfn.RANK.EQ(U52,$U$4:$U$64,1) -> 60 | W52: =IF(Y52="Not suitable","-",V52) -> 60 | Y52: =IF(OR(Z52="Y",AA52="Y"),"Not suitable","") | Z52: =IF(OR(N52="N/A",O52="N/A"),"Y","") | AS52: -9120000 | AT52: 16138000 | AU52: 93000 | AV52: -9112000 | AW52: 1479000 | AX52: 33835312 | AY52: -0.67 | AZ52: -0.094
B53: LODE.A | C53: Comstock Inc | D53: Diversified Mining | E53: United States of America | F53: =AS53/AT53 -> 0 | G53: =AU53/AV53 -> -0.84806624 | H53: =AX53 -> 75533256 | I53: =(AY53/AZ53)-1 -> 3.9807518 | J53: =AV53/AW53 -> -9.8901016 | K53: =IFERROR(_xlfn.RANK.EQ(F53,F$3:F$64),"N/A") -> 30 | L53: =IFERROR(_xlfn.RANK.EQ(G53,G$3:G$64),"N/A") -> 48 | M53: =IFERROR(_xlfn.RANK.EQ(H53,H$3:H$64),"N/A") -> 46 | N53: =IFERROR(_xlfn.RANK.EQ(I53,I$3:I$64),"N/A") -> 4 | O53: =IFERROR(_xlfn.RANK.EQ(J53,J$3:J$64),"N/A") -> 54 | P53: =IFERROR(ABS(K$3-K53),"N/A") -> 28 | Q53: =IFERROR(ABS(L$3-L53),"N/A") -> 21 | R53: =IFERROR(ABS(M$3-M53),"N/A") -> 35 | S53: =IFERROR(ABS(N$3-N53),"N/A") -> 41 | T53: =IFERROR(ABS(O$3-O53),"N/A") -> 52 | U53: =SUM(P53:T53) -> 177 | V53: =_xlfn.RANK.EQ(U53,$U$4:$U$64,1) -> 56 | W53: =IF(Y53="Not suitable","-",V53) -> 56 | Y53: =IF(OR(Z53="Y",AA53="Y"),"Not suitable","") | Z53: =IF(OR(N53="N/A",O53="N/A"),"Y","") | AT53: 1.1494454e+08 | AU53: 15696636 | AV53: -18508738 | AW53: 1871440.6 | AX53: 75533256 | AY53: -0.2309475 | AZ53: -0.046368
B54: MTA.V | C54: Metalla Royalty & Streaming Ltd | D54: Diversified Mining | E54: Canada | F54: =AS54/AT54 -> -0.092174621 | G54: =AU54/AV54 -> -1.1172124 | H54: =AX54 -> 3.5293182e+08 | I54: =(AY54/AZ54)-1 -> -0.24775651 | J54: =AV54/AW54 -> -3.9257447 | K54: =IFERROR(_xlfn.RANK.EQ(F54,F$3:F$64),"N/A") -> 39 | L54: =IFERROR(_xlfn.RANK.EQ(G54,G$3:G$64),"N/A") -> 51 | M54: =IFERROR(_xlfn.RANK.EQ(H54,H$3:H$64),"N/A") -> 30 | N54: =IFERROR(_xlfn.RANK.EQ(I54,I$3:I$64),"N/A") -> 31 | O54: =IFERROR(_xlfn.RANK.EQ(J54,J$3:J$64),"N/A") -> 51 | P54: =IFERROR(ABS(K$3-K54),"N/A") -> 37 | Q54: =IFERROR(ABS(L$3-L54),"N/A") -> 24 | R54: =IFERROR(ABS(M$3-M54),"N/A") -> 19 | S54: =IFERROR(ABS(N$3-N54),"N/A") -> 14 | T54: =IFERROR(ABS(O$3-O54),"N/A") -> 49 | U54: =SUM(P54:T54) -> 143 | V54: =_xlfn.RANK.EQ(U54,$U$4:$U$64,1) -> 38 | W54: =IF(Y54="Not suitable","-",V54) -> 38 | Y54: =IF(OR(Z54="Y",AA54="Y"),"Not suitable","") | Z54: =IF(OR(N54="N/A",O54="N/A"),"Y","") | AS54: -16040384 | AT54: 1.740217e+08 | AU54: 15536510 | AV54: -13906496 | AW54: 3542384.3 | AX54: 3.5293182e+08 | AY54: -0.1794528 | AZ54: -0.2385568
B55: LM8.AX | C55: Lunnon Metals Ltd | D55: Diversified Mining | E55: Australia | F55: =AS55/AT55 -> -0.34198138 | G55: =AU55/AV55 -> -0.0070672115 | H55: =AX55 -> 59904965 | I55: =(AY55/AZ55)-1 -> -0.12359551 | J55: =AV55/AW55 -> -23.309338 | K55: =IFERROR(_xlfn.RANK.EQ(F55,F$3:F$64),"N/A") -> 49 | L55: =IFERROR(_xlfn.RANK.EQ(G55,G$3:G$64),"N/A") -> 33 | M55: =IFERROR(_xlfn.RANK.EQ(H55,H$3:H$64),"N/A") -> 51 | N55: =IFERROR(_xlfn.RANK.EQ(I55,I$3:I$64),"N/A") -> 28 | O55: =IFERROR(_xlfn.RANK.EQ(J55,J$3:J$64),"N/A") -> 57 | P55: =IFERROR(ABS(K$3-K55),"N/A") -> 47 | Q55: =IFERROR(ABS(L$3-L55),"N/A") -> 6 | R55: =IFERROR(ABS(M$3-M55),"N/A") -> 40 | S55: =IFERROR(ABS(N$3-N55),"N/A") -> 17 | T55: =IFERROR(ABS(O$3-O55),"N/A") -> 55 | U55: =SUM(P55:T55) -> 165 | V55: =_xlfn.RANK.EQ(U55,$U$4:$U$64,1) -> 51 | W55: =IF(Y55="Not suitable","-",V55) -> 51 | Y55: =IF(OR(Z55="Y",AA55="Y"),"Not suitable","") | Z55: =IF(OR(N55="N/A",O55="N/A"),"Y","") | AS55: -17735110 | AT55: 51859870 | AU55: 125310 | AV55: -17731180 | AW55: 760690 | AX55: 59904965 | AY55: -0.078 | AZ55: -0.089
B56: CNB.AX | C56: Carnaby Resources Ltd | D56: Diversified Mining | E56: Australia | F56: =AS56/AT56 -> -0.38705013 | G56: =AU56/AV56 -> -0.0015305405 | H56: =AX56 -> 87122790 | I56: =(AY56/AZ56)-1 -> 0.65151515 | J56: =AV56/AW56 -> -23.01461 | K56: =IFERROR(_xlfn.RANK.EQ(F56,F$3:F$64),"N/A") -> 51 | L56: =IFERROR(_xlfn.RANK.EQ(G56,G$3:G$64),"N/A") -> 32 | M56: =IFERROR(_xlfn.RANK.EQ(H56,H$3:H$64),"N/A") -> 45 | N56: =IFERROR(_xlfn.RANK.EQ(I56,I$3:I$64),"N/A") -> 11 | O56: =IFERROR(_xlfn.RANK.EQ(J56,J$3:J$64),"N/A") -> 56 | P56: =IFERROR(ABS(K$3-K56),"N/A") -> 49 | Q56: =IFERROR(ABS(L$3-L56),"N/A") -> 5 | R56: =IFERROR(ABS(M$3-M56),"N/A") -> 34 | S56: =IFERROR(ABS(N$3-N56),"N/A") -> 34 | T56: =IFERROR(ABS(O$3-O56),"N/A") -> 54 | U56: =SUM(P56:T56) -> 176 | V56: =_xlfn.RANK.EQ(U56,$U$4:$U$64,1) -> 55 | W56: =IF(Y56="Not suitable","-",V56) -> 55 | Y56: =IF(OR(Z56="Y",AA56="Y"),"Not suitable","") | Z56: =IF(OR(N56="N/A",O56="N/A"),"Y","") | AS56: -12233780 | AT56: 31607740 | AU56: 18710 | AV56: -12224440 | AW56: 531160 | AX56: 87122790 | AY56: -0.109 | AZ56: -0.066
B57: IE.A | C57: Ivanhoe Electric Inc | D57: Diversified Mining | E57: Canada | F57: =AS57/AT57 -> -0.57735317 | G57: =AU57/AV57 -> -0.42842097 | H57: =AX57 -> 1.4090799e+09 | I57: =(AY57/AZ57)-1 -> -0.41336577 | J57: =AV57/AW57 -> -46.221368 | K57: =IFERROR(_xlfn.RANK.EQ(F57,F$3:F$64),"N/A") -> 56 | L57: =IFERROR(_xlfn.RANK.EQ(G57,G$3:G$64),"N/A") -> 45 | M57: =IFERROR(_xlfn.RANK.EQ(H57,H$3:H$64),"N/A") -> 20 | N57: =IFERROR(_xlfn.RANK.EQ(I57,I$3:I$64),"N/A") -> 36 | O57: =IFERROR(_xlfn.RANK.EQ(J57,J$3:J$64),"N/A") -> 58 | P57: =IFERROR(ABS(K$3-K57),"N/A") -> 54 | Q57: =IFERROR(ABS(L$3-L57),"N/A") -> 18 | R57: =IFERROR(ABS(M$3-M57),"N/A") -> 9 | S57: =IFERROR(ABS(N$3-N57),"N/A") -> 9 | T57: =IFERROR(ABS(O$3-O57),"N/A") -> 56 | U57: =SUM(P57:T57) -> 146 | V57: =_xlfn.RANK.EQ(U57,$U$4:$U$64,1) -> 40 | W57: =IF(Y57="Not suitable","-",V57) -> 40 | Y57: =IF(OR(Z57="Y",AA57="Y"),"Not suitable","") | Z57: =IF(OR(N57="N/A",O57="N/A"),"Y","") | AS57: -3.1729101e+08 | AT57: 5.495614e+08 | AU57: 1.1349202e+08 | AV57: -2.6490771e+08 | AW57: 5731282.3 | AX57: 1.4090799e+09 | AY57: -1.5359459 | AZ57: -2.6182344
B58: PNX.AX | C58: PNX Metals Ltd | D58: Diversified Mining | E58: Australia | F58: =AS58/AT58 -> -0.055744824 | G58: =AU58/AV58 -> -0.084974907 | H58: =AX58 -> 26903124 | I58: =(AY58/AZ58)-1 -> -1 | J58: =AV58/AW58 -> -19.767175 | K58: =IFERROR(_xlfn.RANK.EQ(F58,F$3:F$64),"N/A") -> 35 | L58: =IFERROR(_xlfn.RANK.EQ(G58,G$3:G$64),"N/A") -> 40 | M58: =IFERROR(_xlfn.RANK.EQ(H58,H$3:H$64),"N/A") -> 59 | N58: =IFERROR(_xlfn.RANK.EQ(I58,I$3:I$64),"N/A") -> 47 | O58: =IFERROR(_xlfn.RANK.EQ(J58,J$3:J$64),"N/A") -> 55 | P58: =IFERROR(ABS(K$3-K58),"N/A") -> 33 | Q58: =IFERROR(ABS(L$3-L58),"N/A") -> 13 | R58: =IFERROR(ABS(M$3-M58),"N/A") -> 48 | S58: =IFERROR(ABS(N$3-N58),"N/A") -> 2 | T58: =IFERROR(ABS(O$3-O58),"N/A") -> 53 | U58: =SUM(P58:T58) -> 149 | V58: =_xlfn.RANK.EQ(U58,$U$4:$U$64,1) -> 45 | W58: =IF(Y58="Not suitable","-",V58) -> - | Y58: Not Suitable | AS58: -1472970 | AT58: 26423440 | AU58: 124450 | AV58: -1464550 | AW58: 74090 | AX58: 26903124 | AZ58: 0.00091
B59: DRE.AX | C59: Dreadnought Resources Ltd | D59: Diversified Mining | E59: Australia | F59: =AS59/AT59 -> -0.10861203 | G59: =AU59/AV59 -> -0.030703658 | H59: =AX59 -> 66149886 | I59: =(AY59/AZ59)-1 -> -1 | J59: =AV59/AW59 -> -97.691723 | K59: =IFERROR(_xlfn.RANK.EQ(F59,F$3:F$64),"N/A") -> 42 | L59: =IFERROR(_xlfn.RANK.EQ(G59,G$3:G$64),"N/A") -> 39 | M59: =IFERROR(_xlfn.RANK.EQ(H59,H$3:H$64),"N/A") -> 48 | N59: =IFERROR(_xlfn.RANK.EQ(I59,I$3:I$64),"N/A") -> 47 | O59: =IFERROR(_xlfn.RANK.EQ(J59,J$3:J$64),"N/A") -> 61 | P59: =IFERROR(ABS(K$3-K59),"N/A") -> 40 | Q59: =IFERROR(ABS(L$3-L59),"N/A") -> 12 | R59: =IFERROR(ABS(M$3-M59),"N/A") -> 37 | S59: =IFERROR(ABS(N$3-N59),"N/A") -> 2 | T59: =IFERROR(ABS(O$3-O59),"N/A") -> 59 | U59: =SUM(P59:T59) -> 150 | V59: =_xlfn.RANK.EQ(U59,$U$4:$U$64,1) -> 46 | W59: =IF(Y59="Not suitable","-",V59) -> - | Y59: Not Suitable | AS59: -5521990 | AT59: 50841420 | AU59: 177570 | AV59: -5783350 | AW59: 59200 | AX59: 66149886 | AZ59: -0.001
B60: CHN.AX | C60: Chalice Mining Ltd | D60: Diversified Mining | E60: Australia | F60: =AS60/AT60 -> -0.35071906 | G60: =AU60/AV60 -> -0.024714149 | H60: =AX60 -> 4.7453523e+08 | I60: =(AY60/AZ60)-1 -> -0.30784235 | J60: =AV60/AW60 -> -76.537788 | K60: =IFERROR(_xlfn.RANK.EQ(F60,F$3:F$64),"N/A") -> 50 | L60: =IFERROR(_xlfn.RANK.EQ(G60,G$3:G$64),"N/A") -> 38 | M60: =IFERROR(_xlfn.RANK.EQ(H60,H$3:H$64),"N/A") -> 25 | N60: =IFERROR(_xlfn.RANK.EQ(I60,I$3:I$64),"N/A") -> 35 | O60: =IFERROR(_xlfn.RANK.EQ(J60,J$3:J$64),"N/A") -> 60 | P60: =IFERROR(ABS(K$3-K60),"N/A") -> 48 | Q60: =IFERROR(ABS(L$3-L60),"N/A") -> 11 | R60: =IFERROR(ABS(M$3-M60),"N/A") -> 14 | S60: =IFERROR(ABS(N$3-N60),"N/A") -> 10 | T60: =IFERROR(ABS(O$3-O60),"N/A") -> 58 | U60: =SUM(P60:T60) -> 141 | V60: =_xlfn.RANK.EQ(U60,$U$4:$U$64,1) -> 37 | W60: =IF(Y60="Not suitable","-",V60) -> 37 | Y60: =IF(OR(Z60="Y",AA60="Y"),"Not suitable","") | AS60: -65602000 | AT60: 187050000 | AU60: 1727000 | AV60: -69879000 | AW60: 913000 | AX60: 4.7453523e+08 | AY60: -0.12065 | AZ60: -0.17431
B61: RTR.AX | C61: Rumble Resources Ltd | D61: Diversified Mining | E61: Australia | F61: =AS61/AT61 -> -0.0987213 | G61: =AU61/AV61 -> -0.019379266 | H61: =AX61 -> 53946292 | I61: =(AY61/AZ61)-1 -> -1 | J61: =AV61/AW61 -> -66.729201 | K61: =IFERROR(_xlfn.RANK.EQ(F61,F$3:F$64),"N/A") -> 40 | L61: =IFERROR(_xlfn.RANK.EQ(G61,G$3:G$64),"N/A") -> 37 | M61: =IFERROR(_xlfn.RANK.EQ(H61,H$3:H$64),"N/A") -> 52 | N61: =IFERROR(_xlfn.RANK.EQ(I61,I$3:I$64),"N/A") -> 47 | O61: =IFERROR(_xlfn.RANK.EQ(J61,J$3:J$64),"N/A") -> 59 | P61: =IFERROR(ABS(K$3-K61),"N/A") -> 38 | Q61: =IFERROR(ABS(L$3-L61),"N/A") -> 10 | R61: =IFERROR(ABS(M$3-M61),"N/A") -> 41 | S61: =IFERROR(ABS(N$3-N61),"N/A") -> 2 | T61: =IFERROR(ABS(O$3-O61),"N/A") -> 57 | U61: =SUM(P61:T61) -> 148 | V61: =_xlfn.RANK.EQ(U61,$U$4:$U$64,1) -> 42 | W61: =IF(Y61="Not suitable","-",V61) -> - | Y61: Not Suitable | AS61: -5012420 | AT61: 50773440 | AU61: 101190 | AV61: -5221560 | AW61: 78250 | AX61: 53946292 | AZ61: -0.00547
B62: AZS.AX | C62: Azure Minerals Ltd | D62: Diversified Mining | E62: Australia | F62: =AS62/AT62 -> -0.9381764 | G62: =AU62/AV62 -> -0.0092008797 | H62: =AX62 -> 1651246470 | I62: =(AY62/AZ62)-1 -> -0.057142857 | J62: =AV62/AW62 -> -418.12853 | K62: =IFERROR(_xlfn.RANK.EQ(F62,F$3:F$64),"N/A") -> 58 | L62: =IFERROR(_xlfn.RANK.EQ(G62,G$3:G$64),"N/A") -> 34 | M62: =IFERROR(_xlfn.RANK.EQ(H62,H$3:H$64),"N/A") -> 19 | N62: =IFERROR(_xlfn.RANK.EQ(I62,I$3:I$64),"N/A") -> 24 | O62: =IFERROR(_xlfn.RANK.EQ(J62,J$3:J$64),"N/A") -> 62 | P62: =IFERROR(ABS(K$3-K62),"N/A") -> 56 | Q62: =IFERROR(ABS(L$3-L62),"N/A") -> 7 | R62: =IFERROR(ABS(M$3-M62),"N/A") -> 8 | S62: =IFERROR(ABS(N$3-N62),"N/A") -> 21 | T62: =IFERROR(ABS(O$3-O62),"N/A") -> 60 | U62: =SUM(P62:T62) -> 152 | V62: =_xlfn.RANK.EQ(U62,$U$4:$U$64,1) -> 47 | W62: =IF(Y62="Not suitable","-",V62) -> 47 | Y62: =IF(OR(Z62="Y",AA62="Y"),"Not suitable","") | AS62: -29081470 | AT62: 30997870 | AU62: 267300 | AV62: -29051570 | AW62: 69480 | AX62: 1651246470 | AY62: -0.033 | AZ62: -0.035
B63: STA.AX | C63: Strandline Resources Ltd | D63: Diversified Mining | E63: Australia | F63: =AS63/AT63 -> -0.068907005 | G63: =AU63/AV63 -> -25.221914 | H63: =AX63 -> 1.389436e+08 | I63: =(AY63/AZ63)-1 -> -1 | J63: =AV63/AW63 -> -0.1497672 | K63: =IFERROR(_xlfn.RANK.EQ(F63,F$3:F$64),"N/A") -> 38 | L63: =IFERROR(_xlfn.RANK.EQ(G63,G$3:G$64),"N/A") -> 62 | M63: =IFERROR(_xlfn.RANK.EQ(H63,H$3:H$64),"N/A") -> 40 | N63: =IFERROR(_xlfn.RANK.EQ(I63,I$3:I$64),"N/A") -> 47 | O63: =IFERROR(_xlfn.RANK.EQ(J63,J$3:J$64),"N/A") -> 33 | P63: =IFERROR(ABS(K$3-K63),"N/A") -> 36 | Q63: =IFERROR(ABS(L$3-L63),"N/A") -> 35 | R63: =IFERROR(ABS(M$3-M63),"N/A") -> 29 | S63: =IFERROR(ABS(N$3-N63),"N/A") -> 2 | T63: =IFERROR(ABS(O$3-O63),"N/A") -> 31 | U63: =SUM(P63:T63) -> 133 | V63: =_xlfn.RANK.EQ(U63,$U$4:$U$64,1) -> 34 | W63: =IF(Y63="Not suitable","-",V63) -> - | Y63: Not Suitable | AS63: -11540570 | AT63: 167480360 | AU63: 229551200 | AV63: -9101260 | AW63: 60769380 | AX63: 1.389436e+08 | AZ63: -0.01
B64: PAN.AX | C64: Panoramic Resources Ltd | D64: Diversified Mining | E64: Australia | F64: =AS64/AT64 -> -0.23443772 | G64: =AU64/AV64 -> -2.7180453 | H64: =AX64 -> 1.0393799e+08 | I64: =(AY64/AZ64)-1 -> 0.058201058 | J64: =AV64/AW64 -> -0.16966733 | K64: =IFERROR(_xlfn.RANK.EQ(F64,F$3:F$64),"N/A") -> 48 | L64: =IFERROR(_xlfn.RANK.EQ(G64,G$3:G$64),"N/A") -> 57 | M64: =IFERROR(_xlfn.RANK.EQ(H64,H$3:H$64),"N/A") -> 43 | N64: =IFERROR(_xlfn.RANK.EQ(I64,I$3:I$64),"N/A") -> 18 | O64: =IFERROR(_xlfn.RANK.EQ(J64,J$3:J$64),"N/A") -> 35 | P64: =IFERROR(ABS(K$3-K64),"N/A") -> 46 | Q64: =IFERROR(ABS(L$3-L64),"N/A") -> 30 | R64: =IFERROR(ABS(M$3-M64),"N/A") -> 32 | S64: =IFERROR(ABS(N$3-N64),"N/A") -> 27 | T64: =IFERROR(ABS(O$3-O64),"N/A") -> 33 | U64: =SUM(P64:T64) -> 168 | V64: =_xlfn.RANK.EQ(U64,$U$4:$U$64,1) -> 52 | W64: =IF(Y64="Not suitable","-",V64) -> 52 | Y64: =IF(OR(Z64="Y",AA64="Y"),"Not suitable","") | Z64: =IF(OR(N64="N/A",O64="N/A"),"Y","") | AS64: -33172000 | AT64: 141496000 | AU64: 90163000 | AV64: -33172000 | AW64: 195512000 | AX64: 1.0393799e+08 | AY64: -0.01 | AZ64: -0.00945

Sheet ESG
B1: Company GICS Sector:
B2: Materials | C2: <- Select Industry
B3: ESG Analysis | K3: Relative ESG Analysis
B4: Parameters | C4: Impact | D4: Do they report? | E4: Ranking | F4: Mitigation Plan | G4: Traffic Lights | H4: Improvement over time? | I4: Targets / Goals? | J4: Comments | K4: Parameters | L4: =Peers!C8 -> #VALUE! | M4: =Peers!D8 -> #VALUE! | N4: =Peers!E8 -> #VALUE! | O4: =Peers!F8 -> #VALUE! | P4: =Peers!G8 -> #VALUE! | Q4: =Peers!#REF! -> #REF! | R4: =Peers!#REF! -> #REF! | S4: =Peers!#REF! -> #REF! | T4: AVERAGE
B5: Environmental | K5: Ratios
A6: 1 | B6: CO2 Direct Emissions | C6: =VLOOKUP($B$2,'Sector Impact'!$K$4:$AA$16,A6+1,FALSE) -> Very High | D6: Yes | E6: "Villain" | F6: Yes | H6: Yes | I6: - Continue to develop decarbonisation plan and improve energy efficiency. - Embed climate analysis and internal carbon price to inform decision-making. | J6: The increase in total year emissions in FY23 from the previous can be primarily attributed to the increase in diesel consumption as Pilbara Minerals increased overall activity across operations and construction works for the P680 Project. | K6: CO2 Emissions/$MSales | L6: =IFERROR(L12/L$11,"N/A") -> 36.699803 | M6: =IFERROR(M12/M$11,"N/A") -> 200.41408 | N6: =IFERROR(N12/N$11,"N/A") -> 131.67523 | O6: =IFERROR(O12/O$11,"N/A") -> N/A | P6: =IFERROR(P12/P$11,"N/A") -> N/A | Q6: =IFERROR(Q12/Q$11,"N/A") -> N/A | R6: =R12/R$11 -> #DIV/0! | S6: =S12/S$11 -> #DIV/0! | T6: =IFERROR(AVERAGE(L6:Q6),"") -> 122.9297
A7: 2 | B7: Total Water Consumption | C7: =VLOOKUP($B$2,'Sector Impact'!$K$4:$AA$16,A7+1,FALSE) -> Very High | D7: No | E7: N/A | F7: N/A | H7: N/A | I7: N/A | J7: To effectively monitor changes in water quantity and quality, Pilbara Minerals monitors groundwater abstraction monthly, as well as reviewing groundwater levels and water quality, and vegetation health. A reporting platform stores the historical water record which enables the Company to analyse trends and address any instances of exceeding established benchmarks and operating permits. | K7: Water Consumption/$MSales | L7: =IFERROR(L13/L$11,"N/A") -> 1072.8346 | M7: =IFERROR(M13/M$11,"N/A") -> 786.74948 | N7: =IFERROR(N13/N$11,"N/A") -> 2611.1141 | O7: =IFERROR(O13/O$11,"N/A") -> N/A | P7: =IFERROR(P13/P$11,"N/A") -> N/A | Q7: =IFERROR(Q13/Q$11,"N/A") -> N/A | R7: =R13/R$11 -> #DIV/0! | S7: =S13/S$11 -> #DIV/0! | T7: =IFERROR(AVERAGE(L7:Q7),"") -> 1490.2328
A8: 3 | B8: Total Energy Consumption | C8: =VLOOKUP($B$2,'Sector Impact'!$K$4:$AA$16,A8+1,FALSE) -> Very High | D8: No | E8: N/A | F8: Yes | H8: N/A | I8: Net zero operation in the decade commencing 2040 | J8: Updated high-level climate scenario analysis and completed risk assessment in line with the Taskforce on Climate-related Financial Disclosure. | K8: Energy Consumption/$MSales | L8: =IFERROR(L14/L$11,"N/A") -> 370.91634 | M8: =IFERROR(M14/M$11,"N/A") -> 959.28226 | N8: =IFERROR(N14/N$11,"N/A") -> 665.0863 | O8: =IFERROR(O14/O$11,"N/A") -> N/A | P8: =IFERROR(P14/P$11,"N/A") -> N/A | Q8: =IFERROR(Q14/Q$11,"N/A") -> N/A | R8: =R14/R$11 -> #DIV/0! | S8: =S14/S$11 -> #DIV/0! | T8: =IFERROR(AVERAGE(L8:Q8),"N/A") -> 665.09497
A9: 4 | B9: Waste Management | C9: =VLOOKUP($B$2,'Sector Impact'!$K$4:$AA$16,A9+1,FALSE) -> Very High | D9: Yes | E9: Medium High | F9: No | H9: Yes | I9: N/A | J9: In FY23, significant progress was made in waste management including the upgrade to landfill, recycling, and BioFarm operations. The facility is designed to segregate and responsibly dispose, reuse, or recycle various waste streams including metals, aerosols, plastics, batteries, wood, oils, and hydrocarbons. | K9: Waste Production/$MSales | L9: =IFERROR(L15/L$11,"N/A") -> 2.4279035 | M9: =IFERROR(M15/M$11,"N/A") -> 0.62111801 | N9: =IFERROR(N15/N$11,"N/A") -> 1.7933517 | O9: =IFERROR(O15/O$11,"N/A") -> N/A | P9: =IFERROR(P15/P$11,"N/A") -> N/A | Q9: =IFERROR(Q15/Q$11,"N/A") -> N/A | R9: =R15/R$11 -> #DIV/0! | S9: =S15/S$11 -> #DIV/0! | T9: =IFERROR(AVERAGE(L9:Q9),"") -> 1.6141244
A10: 5 | B10: Land Degradation/Deforestation/Biodiversity loss/Animal sufering/… | C10: =VLOOKUP($B$2,'Sector Impact'!$K$4:$AA$16,A10+1,FALSE) -> High | D10: No | H10: N/A | I10: "Zero environmental issues" | J10: To safeguard biodiversity and minimise adverse impacts on the ecosystem, Pilbara Minerals has formulated various management plans and procedures. These include a corporate EMP which outlines the overarching strategies and processes. Additionally, there is a specialised Fauna Management Procedure to protect fauna within and around the operational areas. | K10: Inputs
B11: Social | K11: Net Sales | L11: =Peers!C61 -> 4064 | M11: =Peers!D61 -> 14490 | N11: =Peers!E61 -> 11251 | O11: =Peers!F61 -> 4779.1 | P11: =Peers!G61 -> 1795.8
A12: 6 | B12: Employee Turnover % | C12: =VLOOKUP($B$2,'Sector Impact'!$K$4:$AA$16,A12+1,FALSE) -> High | H12: N/A | I12: N/A | J12: N/A | K12: CO2 Emissions Total (Tonnes) | L12: 149148 | M12: 2904000 | N12: 1481478 | O12: N/A | P12: N/A
A13: 7 | B13: Salaries & Compensation | C13: =VLOOKUP($B$2,'Sector Impact'!$K$4:$AA$16,A13+1,FALSE) -> High | D13: Yes | E13: Medium | F13: No | H13: Kind of | I13: N/A | J13: Incentive and bonus schemes. | K13: Water Consumption Total (Cubic Meters) | L13: 4360000 | M13: 11400000 | N13: 29377645 | O13: N/A | P13: N/A
A14: 8 | B14: Reputation | C14: =VLOOKUP($B$2,'Sector Impact'!$K$4:$AA$16,A14+1,FALSE) -> Medium | D14: No | E14: Medium | F14: No | H14: Yes | I14: N/A | J14: N/A | K14: Energy Consumption Total (Gigajoules) | L14: 1507404 | M14: 13900000 | N14: 7482886 | O14: N/A | P14: N/A
A15: 9 | B15: Discrimination Events | C15: =VLOOKUP($B$2,'Sector Impact'!$K$4:$AA$16,A15+1,FALSE) -> High | D15: No | E15: Medium High | F15: Yes | H15: No | I15: N/A | J15: Increased spend with over $5M in procurement and contracts awarded to Aboriginal and Torres Strait Islander businesses. | K15: Waste Production Total (Tonnes) | L15: 9867 | M15: 9000 | N15: 20177 | O15: N/A | P15: N/A
A16: 10 | B16: Work Safety | C16: =VLOOKUP($B$2,'Sector Impact'!$K$4:$AA$16,A16+1,FALSE) -> Low | D16: Yes | E16: Medium High | F16: Yes | H16: Yes | J16: Recorded zero fatalities and permanent injuries among employees and contractors. | K16: ESG Scores
A17: 11 | B17: Damage to consumer health | C17: =VLOOKUP($B$2,'Sector Impact'!$K$4:$AA$16,A17+1,FALSE) -> Very High | D17: Yes | E17: "Best in class" | F17: Yes | H17: Yes | J17: N/A | K17: Refinitiv | L17: 44 | M17: 72 | N17: 81 | O17: N/A | P17: N/A
A18: 12 | B18: PXP? | C18: =VLOOKUP($B$2,'Sector Impact'!$K$4:$AA$16,A18+1,FALSE) -> Medium | D18: Yes | E18: Medium | F18: Yes | H18: Yes | I18: N/A | J18: - A team of trained Mental Health First Aiders on site and in Perth who can be accessed by employees at any time - A Lithium Bonus scheme connected to the price of spodumene | K18: Sustainalytics | L18: 40,2 (Severe Risk) | M18: 23,7 (Medium Risk) | N18: 30,8 (Medium Risk) | O18: 21,8 Medium Risk) | P18: 20,8 (Medium Risk)
A19: 13 | B19: Supply chain | C19: =VLOOKUP($B$2,'Sector Impact'!$K$4:$AA$16,A19+1,FALSE) -> Medium | D19: Yes | E19: Medium | F19: No | H19: No | J19: Commence construction of the Mid-stream Demonstration Plant, in joint venture with Calix, with the aim of validating Calix’s patented electric-kiln technology in calcining spodumene concentrate at a lower cost and reduced carbon emissions intensity, thereby further enhancing the sustainability of the battery materials supply chain. | K19: ISS | L19: C | M19: C- | N19: C | O19: C | P19: C
A20: 14 | B20: Community involvement | C20: =VLOOKUP($B$2,'Sector Impact'!$K$4:$AA$16,A20+1,FALSE) -> Very High | D20: Yes | E20: Medium | F20: No | H20: Yes | I20: N/A | J20: Cultural Awareness Training sessions held for 292 employees and organization of two on-country cultural awareness overnight camps. | K20: CDP | L20: F | M20: B | N20: B/B- | O20: N/A | P20: N/A
A21: 15 | B21: Public Sector | C21: =VLOOKUP($B$2,'Sector Impact'!$K$4:$AA$16,A21+1,FALSE) -> High | D21: Yes | E21: Medium | F21: No | H21: No | J21: N/A
A22: 16 | B22: Litigation | C22: =VLOOKUP($B$2,'Sector Impact'!$K$4:$AA$16,A22+1,FALSE) -> Medium | D22: Yes | E22: Medium | F22: No | H22: No | I22: N/A | J22: No relevant Litigations
B23: Corporate Governance | K23: PARAMETERS
A24: 17 | B24: Diversity (Gender, Age, Industry, Region) | E24: Medium High | F24: Yes | H24: No | J24: Improve female representation at senior manager and executive manager level during the period 2019 to 2023 (33%), and promotion of six female candidates to key senior leadership positions. | K24: IMPACT | L24: RANKING | M24: MITIGATION PLAN | P24: TRAFFIC
A25: 18 | B25: % Independence | E25: "Best in class" | F25: No | H25: No | J25: 5/6 Directors were independent (100% of Non-Executive Directors were independent) | K25: Low | L25: "Best in class" | M25: Is there evidence of a plan/program ?
A26: 19 | B26: average time as independent directors | E26: Medium | F26: Yes | H26: Yes | J26: ="Approximately "&ROUND(AVERAGE(2,1/6,6,7,8,2),1)&" years" -> Approximately 4,2 years | K26: Medium | L26: Medium High
A27: 20 | B27: Recent departures of directors / C-level executives? | E27: "Best in class" | F27: Yes | H27: Yes | J27: Recent departure of the Managing Director/CEO (2022) | K27: High | L27: Medium
A28: 21 | B28: CEO/Chairman duality | E28: Medium High | F28: No | H28: No | J28: They are both the same | K28: Very high | L28: "Villain"
A29: 22 | B29: Transparency (ESG, segments, acquisitions, other) | E29: Medium | F29: Yes | H29: No | J29: No problems to be reported
A30: 23 | B30: Time taken to report after the end of the quarter / year | E30: Medium | F30: No | H30: No | J30: Q3: 24 January (24 days) FY23: 25 August (56 days)
A31: 24 | B31: Additional participation of CEO in other boards / excessive participation of Ch. | E31: Medium High | F31: No | H31: No | J31: No evidence of it happening.
A32: 25 | B32: Audit / Consulting | D32: Yes | E32: Medium High | F32: No | H32: Yes | J32: The company's auditor is KPMG, having paid 323 644$ for audit services in 2023.
A33: 26 | B33: ESG-compensation related | D33: Yes | E33: "Best in class" | F33: Yes | H33: No | J33: The Company’s Audit and Risk Committee Charter is disclosed on the Company’s website but the information is not clear enough
A34: 27 | B34: Management compensation schemes | D34: Yes | E34: Medium High | F34: Yes | H34: No | J34: (See image on the right)

Sheet DCF
A1: VALUATION MODEL
G3: Short Term | K3: Long Term
A4: Section | B4: Line # | C4: ITEM | D4: =OP!J21-2&" (Real)" -> 2021 (Real) | E4: =OP!J21-1&" (Real)" -> 2022 (Real) | F4: =OP!J21&" (Real)" -> 2023 (Real) | G4: =OP!J21+1 -> 2024 | H4: =G4+1 -> 2025 | I4: =H4+1 -> 2026 | J4: =I4+1 -> 2027 | K4: =J4+1 -> 2028 | L4: =K4+1 -> 2029 | M4: =L4+1 -> 2030 | N4: =M4+1 -> 2031 | O4: =N4+1 -> 2032 | ... AF4: =AE4+1 -> 2049
A5: INCOME STATEMENT | B5: 1 | C5: Growth | D5: ='Fin. Data'!D6 -> 1.0903686 | E5: =+E6/D6-1 -> 5.7667804 | F5: =+F6/E6-1 -> 2.4162744 | G5: -0.6 | H5: =D136 -> -0.010784296 | I5: =Assumptions!Q153 -> 0.40692169 | J5: =Assumptions!R153 -> 0.19813857 | K5: =Assumptions!S153 -> 0.1222007 | L5: =Assumptions!T153 -> -0.086028585 | M5: =Assumptions!U153 -> 0.20099174 | N5: =Assumptions!V153 -> 0.11512578 | O5: =Assumptions!W153 -> 0.085566695 | P5: =Assumptions!X153 -> 0.16578895 | ... AE5: =Assumptions!AM153 -> 0.062341234 | AF5: 0.03
B6: 2 | C6: Revenues/Sales | D6: ='Inputs (AUD)'!D6 -> 175.8 | E6: ='Inputs (AUD)'!C6 -> 1189.6 | F6: ='Inputs (AUD)'!B6 -> 4064 | G6: =F6*(1+G5) -> 1625.6 | H6: =G6*(1+H5) -> 1608.069 | I6: =H6*(1+I5) -> 2262.4272 | J6: =I6*(1+J5) -> 2710.7013 | K6: =J6*(1+K5) -> 3041.9509 | L6: =K6*(1+L5) -> 2780.2562 | M6: =L6*(1+M5) -> 3339.0647 | N6: =M6*(1+N5) -> 3723.4771 | ... AF6: =AE6*(1+AF5) -> 15689.545
B7: 3 | C7: Operating Margin | D7: =D8/D6 -> -0.19169511 | E7: =E8/E6 -> 0.61054136 | F7: =F8/F6 -> 0.7621063 | G7: 0.55 | H7: 0.65 | I7: 0.65 | J7: 0.6 | K7: 0.58 | L7: =M7+1.75% -> 0.6 | M7: =N7+1.75% -> 0.5825 | N7: =O7+1.75% -> 0.565 | O7: =P7+1.75% -> 0.5475 | P7: =Q7+1.75% -> 0.53 | Q7: =R7+1.75% -> 0.5125 | R7: =S7+1.75% -> 0.495 | S7: =T7+1.75% -> 0.4775 | ... AE7: =AF7+1.75% -> 0.2675 | AF7: 0.25
B8: 4 | C8: EBIT | D8: ='Fin. Data'!D16 -> -33.7 | E8: ='Fin. Data'!C16 -> 726.3 | F8: ='Fin. Data'!B16 -> 3097.2 | G8: =G7*G6 -> 894.08 | H8: =H7*H6 -> 1045.2449 | I8: =I7*I6 -> 1470.5777 | J8: =J7*J6 -> 1626.4208 | K8: =K7*K6 -> 1764.3315 | L8: =L7*L6 -> 1668.1537 | M8: =M7*M6 -> 1945.0052 | N8: =N7*N6 -> 2103.7646 | ... AF8: =AF7*AF6 -> 3922.3863
B9: 5a | C9: (Depreciation) | D9: =-'Fin. Data'!D17 -> -0.5 | E9: =-'Fin. Data'!C17 -> -0.7 | F9: =-'Fin. Data'!B17 -> -1.5 | G9: =$D$53*DCF!F40 -> -46.179 | H9: =$D$53*DCF!G40 -> -49.59276 | I9: =$D$53*DCF!H40 -> -52.969705 | J9: =$D$53*DCF!I40 -> -57.720802 | K9: =$E$53*DCF!J40 -> -84.551033 | L9: =$E$53*DCF!K40 -> -95.502057 | M9: =$E$53*DCF!L40 -> -105.51098 | N9: =$E$53*DCF!M40 -> -117.53161 | O9: =$E$53*DCF!N40 -> -130.93613 | P9: =$E$53*DCF!O40 -> -145.48763 | Q9: =$E$53*DCF!P40 -> -162.4516 | R9: =$E$53*DCF!Q40 -> -181.24579 | ... AF9: =$E$53*DCF!AE40 -> -692.14832 | AG9: =SUM(D9:AF9) -> -7004.5882
B10: 5b | C10: Amortization | D10: 0 | E10: 0 | F10: 0 | G10: =F38*0 -> 0 | H10: =G38*0 -> 0 | I10: =H38*0 -> 0 | J10: =I38*0 -> 0 | K10: =J38*0 -> 0 | L10: =K38*0 -> 0 | M10: =L38*0 -> 0 | N10: =M38*0 -> 0 | ... AF10: =AE38*0 -> 0
B11: 5c | C11: (Stock based compensation) | D11: =D20 -> 0 | E11: =E20 -> 0 | F11: =F20 -> -12.8 | G11: =G6*$D$55 -> 0 | H11: =H6*$D$55 -> 0 | I11: =I6*$D$55 -> 0 | J11: =J6*$D$55 -> 0 | K11: =K6*$E$55 -> -60.839019 | L11: =L6*$E$55 -> -55.605124 | M11: =M6*$E$55 -> -66.781294 | N11: =N6*$E$55 -> -74.469543 | O11: =O6*$E$55 -> -80.841656 | P11: =P6*$E$55 -> -94.244309 | Q11: =Q6*$E$55 -> -104.41215 | R11: =R6*$E$55 -> -115.13344 | ... AF11: =AF6*$E$55 -> -313.79091
B12: 6 | C12: EBITDA | D12: =D8-D9-D10 -> -33.2 | E12: =E8-E9-E10 -> 727 | F12: =F8-F9-F10 -> 3098.7 | G12: =G8-G9-G10 -> 940.259 | H12: =H8-H9-H10 -> 1094.8376 | I12: =I8-I9-I10 -> 1523.5474 | J12: =J8-J9-J10 -> 1684.1416 | K12: =K8-K9-K10 -> 1848.8826 | ... AF12: =AF8-AF9-AF10 -> 4614.5346
B13: 7 | C13: (Net financing cost) | D13: ='Fin. Data'!D14 -> -15.1 | E13: ='Fin. Data'!C14 -> -12.5 | F13: ='Fin. Data'!B14 -> 44.9 | G13: =F43*$D$58-F44*$D$57 -> -9.44 | H13: =G43*$D$58-G44*$D$57 -> -1.880518 | I13: =H43*$D$58-H44*$D$57 -> -2.1896753 | J13: =I43*$D$58-I44*$D$57 -> -3.0470948 | K13: =J43*$E$58-J44*$E$57 -> -3.3682832 | L13: =K43*$E$58-K44*$E$57 -> -5.1768712 | M13: =L43*$E$58-L44*$E$57 -> -4.9382362 | N13: =M43*$E$58-M44*$E$57 -> -5.7414453 | O13: =N43*$E$58-N44*$E$57 -> -6.2196294 | P13: =O43*$E$58-O44*$E$57 -> -6.5631341 | Q13: =P43*$E$58-P44*$E$57 -> -7.4002931 | R13: =Q43*$E$58-Q44*$E$57 -> -7.9464365 | ... AF13: =AE43*$E$58-AE44*$E$57 -> -13.193665
B14: 8 | C14: Other income/(cost) | D14: ='Fin. Data'!D15 -> -1.3 | E14: ='Fin. Data'!C15 -> 5.6 | F14: ='Fin. Data'!B15 -> 114.7 | G14: =AVERAGE(D14:F14)*(1+G5) -> 15.866667 | H14: =AVERAGE(E14:G14)*(1+H5) -> 44.899402 | I14: =AVERAGE(F14:H14)*(1+I5) -> 82.289006 | J14: =AVERAGE(G14:I14)*(1+J5) -> 57.133267 | K14: =AVERAGE(H14:J14)*(1+K5) -> 68.948638 | L14: =AVERAGE(I14:K14)*(1+L5) -> 63.481686 | M14: =AVERAGE(J14:L14)*(1+M5) -> 75.888102 | N14: =AVERAGE(K14:M14)*(1+N5) -> 77.433749 | ... AF14: =AVERAGE(AC14:AE14)*(1+AF5) -> 154.66729
B15: 9 | C15: Earnings before taxes | D15: =D8+D13+D14 -> -50.1 | E15: =E8+E13+E14 -> 719.4 | F15: =F8+F13+F14 -> 3256.8 | G15: =G8+G13+G14 -> 900.50667 | H15: =H8+H13+H14 -> 1088.2638 | I15: =I8+I13+I14 -> 1550.677 | J15: =J8+J13+J14 -> 1680.507 | K15: =K8+K13+K14 -> 1829.9119 | ... AF15: =AF8+AF13+AF14 -> 4063.8599
B16: 10 | C16: (Income tax) | D16: ='Fin. Data'!D21 -> 0 | E16: ='Fin. Data'!C21 -> -163.2 | F16: ='Fin. Data'!B21 -> -980.4 | G16: =-(1*$D$56)*G15 -> -225.12667 | H16: =-(1*$D$56)*H15 -> -272.06594 | I16: =-(1*$D$56)*I15 -> -387.66926 | J16: =-(1*$D$56)*J15 -> -420.12674 | K16: =-(1*$E$56)*K15 -> -548.97357 | L16: =-(1*$E$56)*L15 -> -517.93756 | M16: =-(1*$E$56)*M15 -> -604.78652 | N16: =-(1*$E$56)*N15 -> -652.63707 | O16: =-(1*$E$56)*O15 -> -685.58168 | P16: =-(1*$E$56)*P15 -> -774.2932 | Q16: =-(1*$E$56)*Q15 -> -827.69703 | R16: =-(1*$E$56)*R15 -> -881.07959 | ... AF16: =-(1*$E$56)*AF15 -> -1219.158
B17: 11 | C17: Net income | D17: ='Fin. Data'!D23 -> -51.4 | E17: ='Fin. Data'!C23 -> 561.8 | F17: ='Fin. Data'!B23 -> 2391.1 | G17: =G16+G15 -> 675.38 | H17: =H16+H15 -> 816.19782 | I17: =I16+I15 -> 1163.0078 | J17: =J16+J15 -> 1260.3802 | K17: =K16+K15 -> 1280.9383 | L17: =L16+L15 -> 1208.521 | M17: =M16+M15 -> 1411.1685 | N17: =N16+N15 -> 1522.8198 | ... AF17: =AF16+AF15 -> 2844.702
A19: CASH FLOW STATEMENT | B19: 12 | C19: Operating cash flows before WK | D19: ='Inputs (AUD)'!D59-'Inputs (AUD)'!D62 -> 24 | E19: ='Inputs (AUD)'!C59-'Inputs (AUD)'!C62 -> 657.2 | F19: ='Inputs (AUD)'!B59-'Inputs (AUD)'!B62 -> 3414.9 | G19: =G17-G10-G9-G11 -> 721.559 | H19: =H17-H10-H9-H11 -> 865.79058 | I19: =I17-I10-I9-I11 -> 1215.9775 | J19: =J17-J10-J9-J11 -> 1318.101 | K19: =K17-K10-K9-K11 -> 1426.3284 | L19: =L17-L10-L9-L11 -> 1359.6282 | M19: =M17-M10-M9-M11 -> 1583.4608 | N19: =N17-N10-N9-N11 -> 1714.821 | ... AF19: =AF17-AF10-AF9-AF11 -> 3850.6412
B20: 13 | C20: (Stock-based compensation) | D20: =-'Inputs (AUD)'!D103 -> 0 | E20: =-'Inputs (AUD)'!C103 -> 0 | F20: =-'Inputs (AUD)'!B103 -> -12.8 | G20: =G11 -> 0 | H20: =H11 -> 0 | I20: =I11 -> 0 | J20: =J11 -> 0 | K20: =K11 -> -60.839019 | L20: =L11 -> -55.605124 | M20: =M11 -> -66.781294 | N20: =N11 -> -74.469543 | ... AF20: =AF11 -> -313.79091
B21: 14 | C21: (Working Capital Flows) | D21: ='Inputs (AUD)'!D62 -> -5.2 | E21: ='Inputs (AUD)'!C62 -> -9.6 | F21: ='Inputs (AUD)'!B62 -> 41.8 | G21: =$D$60*(G6-F6) -> 60.96 | H21: =$D$60*(H6-G6) -> 0.43827377 | I21: =$D$60*(I6-H6) -> -16.358954 | J21: =$D$60*(J6-I6) -> -11.206852 | K21: =$E$60*(K6-J6) -> -14.906232 | L21: =$E$60*(L6-K6) -> 11.776263 | M21: =$E$60*(M6-L6) -> -25.146384 | N21: =$E$60*(N6-M6) -> -17.298559 | O21: =$E$60*(O6-N6) -> -14.337254 | P21: =$E$60*(P6-O6) -> -30.15597 | Q21: =$E$60*(Q6-P6) -> -22.877651 | R21: =$E$60*(R6-Q6) -> -24.122899 | ... AF21: =$E$60*(AF6-AE6) -> -20.563967
B22: 15 | C22: -Total Operating Cash Flow | D22: =D19+D20+D21 -> 18.8 | E22: =E19+E20+E21 -> 647.6 | F22: =F19+F20+F21 -> 3443.9 | G22: =G19+G20+G21 -> 782.519 | H22: =H19+H20+H21 -> 866.22886 | I22: =I19+I20+I21 -> 1199.6185 | J22: =J19+J20+J21 -> 1306.8942 | K22: =K19+K20+K21 -> 1350.5831 | ... AF22: =AF19+AF20+AF21 -> 3516.2863
B23: 16 | C23: (CAPEX) | D23: ='Fin. Data'!D32 -> -20.5 | E23: ='Fin. Data'!C32 -> -128.3 | F23: ='Fin. Data'!B32 -> -385.5 | G23: =G6*$D$62 -> -113.792 | H23: =H6*$D$62 -> -112.56483 | I23: =I6*$D$62 -> -158.36991 | J23: =J6*$D$62 -> -189.74909 | K23: =K6*$E$62 -> -273.77558 | L23: =L6*$E$62 -> -250.22306 | M23: =M6*$E$62 -> -300.51583 | N23: =N6*$E$62 -> -335.11294 | O23: =O6*$E$62 -> -363.78745 | P23: =P6*$E$62 -> -424.09939 | Q23: =Q6*$E$62 -> -469.85469 | R23: =R6*$E$62 -> -518.10049 | ... AF23: =AF6*$E$62 -> -1412.0591 | AG23: =SUM(D23:AF23) -> -17710.767
B24: 17 | C24: Aquisitions | D24: ='Fin. Data'!D33 -> -210.3 | E24: ='Fin. Data'!C33 -> -76.2 | F24: ='Fin. Data'!B33 -> -22.4 | G24: =-G6*2% -> -32.512 | H24: =-H6*2% -> -32.161381 | I24: =-I6*2% -> -45.248545 | J24: =J6*$D$63 -> 0 | K24: =K6*$E$63 -> 0 | L24: =L6*$E$63 -> 0 | M24: =M6*$E$63 -> 0 | N24: =-N6*1% -> -37.234771 | O24: =-O6*2% -> -80.841656 | P24: =-P6*3% -> -141.36646 | Q24: =-Q6*4% -> -208.82431 | R24: =-R6*4.5% -> -259.05024 | S24: =S6*$E$63 -> 0 | T24: =T6*$E$63 -> 0 | U24: =U6*$E$63 -> 0 | V24: =V6*$E$63 -> 0 | W24: =W6*$E$63 -> 0 | X24: =-X6*1% -> -95.523852 | Y24: =-Y6*2% -> -205.62747 | Z24: =-Z6*3% -> -331.13587 | AA24: =-AA6*3.5% -> -413.76452 | AB24: =-AB6*3.5% -> -442.16586 | AC24: =-AC6*3.5% -> -471.52898 | AD24: =-AD6*3.5% -> -501.85371 | AE24: =-AE6*3.5% -> -533.13989 | AF24: =-AF6*3.5% -> -549.13408 | AH24: =AG9-AG23 -> 10706.179
B25: 18 | C25: (Other investing flows) | D25: ='Inputs (AUD)'!D67 -> 0 | E25: ='Inputs (AUD)'!C67 -> 0 | F25: ='Inputs (AUD)'!B67 -> -0.1 | G25: =(1+G5)*AVERAGE(D25:F25) -> -0.013333333 | H25: =(1+H5)*AVERAGE(E25:G25) -> -0.037370371 | I25: =(1+I5)*AVERAGE(F25:H25) -> -0.070676104 | J25: =(1+J5)*AVERAGE(G25:I25) -> -0.04847661 | K25: =(1+K5)*AVERAGE(H25:J25) -> -0.058550105 | L25: =(1+L5)*AVERAGE(I25:K25) -> -0.054138432 | M25: =(1+M5)*AVERAGE(J25:L25) -> -0.064519337 | N25: =(1+N5)*AVERAGE(K25:M25) -> -0.065869689 | ... AF25: =(1+AF5)*AVERAGE(AC25:AE25) -> -0.13159227
B26: 19 | C26: -Total Investing Flows | D26: =D23+D24+D25 -> -230.8 | E26: =E23+E24+E25 -> -204.5 | F26: =F23+F24+F25 -> -408 | G26: =G23+G24+G25 -> -146.31733 | H26: =H23+H24+H25 -> -144.76358 | I26: =I23+I24+I25 -> -203.68913 | J26: =J23+J24+J25 -> -189.79757 | K26: =K23+K24+K25 -> -273.83413 | ... AF26: =AF23+AF24+AF25 -> -1961.3247
B27: 20 | C27: (Flows related to leases) | D27: ='Inputs (AUD)'!D71+'Inputs (AUD)'!D72 -> -20.048 | E27: ='Inputs (AUD)'!C71+'Inputs (AUD)'!C72 -> -26.864 | F27: ='Inputs (AUD)'!B71+'Inputs (AUD)'!B72 -> -54.631 | G27: 0 | H27: 0 | I27: 0 | J27: 0 | K27: 0 | L27: 0 | M27: 0 | N27: 0 | O27: 0 | P27: 0 | Q27: 0 | R27: 0 | S27: 0 | T27: 0 | U27: 0 | V27: 0 | W27: 0 | X27: 0 | Y27: 0 | Z27: 0 | AA27: 0 | AB27: 0 | AC27: 0 | AD27: 0 | AE27: 0 | AF27: 0
B28: 21 | C28: Flows related to debt | D28: =+SUM('Inputs (AUD)'!D69:D70) -> 6.2 | E28: =+SUM('Inputs (AUD)'!C69:C70) -> 57.5 | F28: =+SUM('Inputs (AUD)'!B69:B70) -> 51.3 | G28: =G44-F44 -> -377.9741 | H28: =H44-G44 -> 15.457864 | I28: =I44-H44 -> 42.870976 | J28: =J44-I44 -> 16.05942 | K28: =K44-J44 -> 90.429401 | L28: =L44-K44 -> -11.931752 | M28: =M44-L44 -> 40.160457 | N28: =N44-M44 -> 23.909202 | ... AF28: =AF44-AE44 -> -13.648381
B29: 22 | C29: (Repurchases)/Issuance of stock | D29: ='Fin. Data'!D28 -> 239.7 | E29: ='Fin. Data'!C28 -> 3.6 | F29: ='Fin. Data'!B28 -> 1.2 | G29: =-$D$65*(G22-G26) -> -111.46036 | H29: =-$D$65*(H22-H26) -> -121.31909 | I29: =-$D$65*(I22-I26) -> -168.39692 | J29: =-$D$65*(J22-J26) -> -179.60301 | K29: =-$E$65*(K22-K26) -> -243.66259 | L29: =-$E$65*(L22-L26) -> -234.91147 | M29: =-$E$65*(M22-M26) -> -268.81702 | N29: =-$E$65*(N22-N26) -> -299.31997 | O29: =-$E$65*(O22-O26) -> -324.1478 | P29: =-$E$65*(P22-P26) -> -373.13374 | Q29: =-$E$65*(Q22-Q26) -> -412.4435 | R29: =-$E$65*(R22-R26) -> -448.53107 | ... AF29: =-$E$65*(AF22-AF26) -> -821.64166
B30: 23 | C30: (Dividends) | D30: ='Fin. Data'!D27 -> 0 | E30: ='Fin. Data'!C27 -> 0 | F30: ='Fin. Data'!B27 -> -329.8 | G30: =-$D$64*(G22-G26) -> -185.76727 | H30: =-$D$64*(H22-H26) -> -202.19849 | I30: =-$D$64*(I22-I26) -> -280.66153 | J30: =-$D$64*(J22-J26) -> -299.33835 | K30: =-$E$64*(K22-K26) -> -406.10432 | L30: =-$E$64*(L22-L26) -> -391.51912 | M30: =-$E$64*(M22-M26) -> -448.02837 | N30: =-$E$64*(N22-N26) -> -498.86661 | O30: =-$E$64*(O22-O26) -> -540.24633 | P30: =-$E$64*(P22-P26) -> -621.88957 | Q30: =-$E$64*(Q22-Q26) -> -687.40583 | R30: =-$E$64*(R22-R26) -> -747.55178 | ... AF30: =-$E$64*(AF22-AF26) -> -1369.4028
B31: 24 | C31: Other financing flows | D31: ='Inputs (AUD)'!D75 -> 6.848 | E31: ='Inputs (AUD)'!C75 -> 11.264 | F31: ='Inputs (AUD)'!B75 -> 16.831 | G31: =(1+G5)*AVERAGE(D31:F31) -> 4.6590667 | H31: =(1+H5)*AVERAGE(E31:G31) -> 10.800279 | I31: =(1+I5)*AVERAGE(F31:H31) -> 15.143329 | J31: =(1+J5)*AVERAGE(G31:I31) -> 12.222082 | K31: =(1+K5)*AVERAGE(H31:J31) -> 14.276521 | L31: =(1+L5)*AVERAGE(I31:K31) -> 12.686512 | M31: =(1+M5)*AVERAGE(J31:L31) -> 15.687 | N31: =(1+N5)*AVERAGE(K31:M31) -> 15.853384 | ... AF31: =(1+AF5)*AVERAGE(AC31:AE31) -> 31.66224
B32: 25 | C32: -Total Financing flows | D32: =D27+D28+D29+D30+D31 -> 232.7 | E32: =E27+E28+E29+E30+E31 -> 45.5 | F32: =F27+F28+F29+F30+F31 -> -315.1 | G32: =G27+G28+G29+G30+G31 -> -670.54266 | H32: =H27+H28+H29+H30+H31 -> -297.25944 | I32: =I27+I28+I29+I30+I31 -> -391.04414 | J32: =J27+J28+J29+J30+J31 -> -450.65986 | K32: =K27+K28+K29+K30+K31 -> -545.06098 | ... AF32: =AF27+AF28+AF29+AF30+AF31 -> -2173.0306
A34: SUMMARY | B34: 26 | C34: Cash before shareholder returns | D34: =D22+D26+D27+D28+D31 -> -219 | E34: =E22+E26+E27+E28+E31 -> 485 | F34: =F22+F26+F27+F28+F31 -> 3049.4 | G34: =G22+G26+G27+G28+G31 -> 262.88663 | H34: =H22+H26+H27+H28+H31 -> 747.72342 | I34: =I22+I26+I27+I28+I31 -> 1053.9437 | J34: =J22+J26+J27+J28+J31 -> 1145.3781 | K34: =K22+K26+K27+K28+K31 -> 1181.4549 | ... AF34: =AF22+AF26+AF27+AF28+AF31 -> 1572.9754
B35: 27 | C35: Returns to shareholders | D35: =-1*(D29+D30) -> -239.7 | E35: =-1*(E29+E30) -> -3.6 | F35: =-1*(F29+F30) -> 328.6 | G35: =-1*(G29+G30) -> 297.22763 | H35: =-1*(H29+H30) -> 323.51758 | I35: =-1*(I29+I30) -> 449.05845 | J35: =-1*(J29+J30) -> 478.94136 | K35: =-1*(K29+K30) -> 649.7669 | ... AF35: =-1*(AF29+AF30) -> 2191.0444
B36: 28 | C36: Excess cash acumulation | D36: =D34-D35 -> 20.7 | E36: =E34-E35 -> 488.6 | F36: =F34-F35 -> 2720.8 | G36: =G34-G35 -> -34.340993 | H36: =H34-H35 -> 424.20583 | I36: =I34-I35 -> 604.88525 | J36: =J34-J35 -> 666.43675 | K36: =K34-K35 -> 531.68801 | ... AF36: =AF34-AF35 -> -618.06901
A38: BALANCE SHEET | B38: 29 | C38: Intangible assets | D38: ='Inputs (AUD)'!D91 -> 0 | E38: ='Inputs (AUD)'!C91 -> 0 | F38: ='Inputs (AUD)'!B91 -> 0 | G38: =+F38+(-G10) -> 0 | H38: =+G38+(-H10) -> 0 | I38: =+H38+(-I10) -> 0 | J38: =+I38+(-J10) -> 0 | K38: =+J38+(-K10) -> 0 | L38: =+K38+(-L10) -> 0 | M38: =+L38+(-M10) -> 0 | N38: =+M38+(-N10) -> 0 | ... AF38: =+AE38+(-AF10) -> 0 | AG38: =SUM(G38:AF38) -> 0
B39: 30 | C39: Accumulated amortization | D39: 0 | E39: 0 | F39: 0 | G39: =F39-G10 -> 0 | H39: =G39-H10 -> 0 | I39: =H39-I10 -> 0 | J39: =I39-J10 -> 0 | K39: =J39-K10 -> 0 | L39: =K39-L10 -> 0 | M39: =L39-M10 -> 0 | N39: =M39-N10 -> 0 | ... AF39: =AE39-AF10 -> 0 | AG39: =SUM(G39:AF39) -> 0
B40: 31 | C40: PPE+Right of use Assets | D40: ='Inputs (AUD)'!D95 -> 0 | E40: ='Inputs (AUD)'!C95 -> 1003.7 | F40: ='Inputs (AUD)'!B95 -> 1539.3 | G40: =F40+(-G23) -> 1653.092 | H40: =G40+(-H23) -> 1765.6568 | I40: =H40+(-I23) -> 1924.0267 | J40: =I40+(-J23) -> 2113.7758 | K40: =J40+(-K23) -> 2387.5514 | L40: =K40+(-L23) -> 2637.7745 | M40: =L40+(-M23) -> 2938.2903 | N40: =M40+(-N23) -> 3273.4032 | ... AF40: =AE40+(-AF23) -> 18715.767 | AG40: =SUM(G40:AF40) -> 193944.19
B41: 32 | C41: Accumulated depreciation | D41: ='Inputs (AUD)'!D93 -> 0 | E41: =-'Inputs (AUD)'!C93 -> 74.3 | F41: =-'Inputs (AUD)'!B93 -> 163.8 | G41: =F41-G9 -> 209.979 | H41: =G41-H9 -> 259.57176 | I41: =H41-I9 -> 312.54147 | J41: =I41-J9 -> 370.26227 | K41: =J41-K9 -> 454.8133 | L41: =K41-L9 -> 550.31536 | M41: =L41-M9 -> 655.82634 | N41: =M41-N9 -> 773.35795 | ... AF41: =AE41-AF9 -> 7165.6882 | AG41: =SUM(G41:AF41) -> 62418.166
A43: CASH & DEBT & DISCOUNTING | B43: 33 | C43: Ending cash balance | D43: ='Fin. Data'!D39 -> 99.7 | E43: =E36+D43 -> 588.3 | F43: =F36+E43 -> 3309.1 | G43: =G36+F43 -> 3274.759 | H43: =H36+G43 -> 3698.9648 | I43: =I36+H43 -> 4303.8501 | J43: =J36+I43 -> 4970.2868 | K43: =K36+J43 -> 5501.9749 | L43: =L36+K43 -> 5941.8211 | ... AF43: =AF36+AE43 -> 10793.002
B44: 34 | C44: Total Debt | D44: ='Fin. Data'!D58 -> 166.9 | E44: ='Fin. Data'!C58 -> 292 | F44: ='Fin. Data'!B58 -> 472 | G44: =G12*$D$68 -> 94.0259 | H44: =H12*$D$68 -> 109.48376 | I44: =I12*$D$68 -> 152.35474 | J44: =J12*$D$68 -> 168.41416 | K44: =K12*$E$68 -> 258.84356 | L44: =L12*$E$68 -> 246.91181 | M44: =M12*$E$68 -> 287.07227 | N44: =N12*$E$68 -> 310.98147 | O44: =O12*$E$68 -> 328.1567 | P44: =P12*$E$68 -> 370.01465 | Q44: =Q12*$E$68 -> 397.32183 | R44: =R12*$E$68 -> 424.31179 | ... AF44: =AF12*$E$68 -> 646.03485
B45: 35 | C45: Discount factor | F45: =1/((1+$F$50)^G50) -> 1 | G45: =1/((1+$F$50)^G49) -> 1 | H45: =1/((1+$F$50)^H49) -> 0.84013775 | I45: =1/((1+$F$50)^I49) -> 0.7700621 | J45: =1/((1+$F$50)^J49) -> 0.70583144 | K45: =1/((1+$F$50)^K49) -> 0.64695824 | L45: =1/((1+$F$50)^L49) -> 0.59299563 | M45: =1/((1+$F$50)^M49) -> 0.54353404 | N45: =1/((1+$F$50)^N49) -> 0.49819802 | ... AF45: =1/((1+$F$50)^AF49) -> 0.10388587
B46: 36 | C46: DF + 0.1% | E46: +0.1% | F46: =1/((1+$F$50+0.001)^G50) -> 1 | G46: =1/((1+$F$50+0.001)^G49) -> 1 | H46: =1/((1+$F$50+0.001)^H49) -> 0.83859974 | I46: =1/((1+$F$50+0.001)^I49) -> 0.76794848 | J46: =1/((1+$F$50+0.001)^J49) -> 0.70324952 | K46: =1/((1+$F$50+0.001)^K49) -> 0.6440014 | L46: =1/((1+$F$50+0.001)^L49) -> 0.58974487 | M46: =1/((1+$F$50+0.001)^M49) -> 0.5400594 | N46: =1/((1+$F$50+0.001)^N49) -> 0.49455989 | ... AF46: =1/((1+$F$50+0.001)^AF49) -> 0.1014405
B47: 37 | C47: DF+0.5% | E47: +0.5% | F47: =1/((1+$F$50+0.005)^G50) -> 1 | G47: =1/((1+$F$50+0.005)^G49) -> 1 | H47: =1/((1+$F$50+0.005)^H49) -> 0.83248974 | I47: =1/((1+$F$50+0.005)^I49) -> 0.75957093 | J47: =1/((1+$F$50+0.005)^J49) -> 0.69303917 | K47: =1/((1+$F$50+0.005)^K49) -> 0.63233501 | L47: =1/((1+$F$50+0.005)^L49) -> 0.576948 | M47: =1/((1+$F$50+0.005)^M49) -> 0.52641241 | N47: =1/((1+$F$50+0.005)^N49) -> 0.4803033 | ... AF47: =1/((1+$F$50+0.005)^AF49) -> 0.092241338
A49: Discount Rate | C49: Risk free rate | D49: Equity premium | E49: Firm premium | F49: Total | H49: 2 | I49: 3 | J49: 4 | K49: 5 | L49: 6 | M49: 7 | N49: 8 | O49: 9 | P49: 10 | Q49: 11 | R49: 12 | S49: 13 | T49: 14 | U49: 15 | V49: 16 | W49: 17 | X49: 18 | Y49: 19 | Z49: 20 | AA49: 21 | AB49: 22 | AC49: 23 | AD49: 24 | AE49: 25 | AF49: 26
C50: 0.03 | D50: 0.046 | E50: 0.015 | F50: =E50+D50+C50 -> 0.091
A52: Modelling factors | D52: Short Term | E52: Long Term | F52: Reference (line)
C53: Depreciation factor | D53: =-Assumptions!S16 -> -0.03 | E53: =-Assumptions!T16 -> -0.04 | F53: % PPE | H53: =D44/D12 -> -5.0271084 | I53: =E44/E12 -> 0.40165062 | J53: =F44/F12 -> 0.15232194
C54: Amortization factor | D54: =Assumptions!S17 -> 0 | E54: =Assumptions!T17 -> 0 | F54: % IA
C55: Stock-based comp | D55: =-Assumptions!S18 -> 0 | E55: =-Assumptions!T18 -> -0.02 | F55: % Revenue
C56: Tax Rate | D56: =Assumptions!S19 -> 0.25 | E56: =Assumptions!T19 -> 0.3 | F56: % Earnings before tax | G56: =G43/G44 -> 34.828265 | H56: =H43/H44 -> 33.78551 | I56: =I43/I44 -> 28.248876 | J56: =J43/J44 -> 29.512286 | K56: =K43/K44 -> 21.255985 | L56: =L43/L44 -> 24.064548 | M56: =M43/M44 -> 22.544066 | N56: =N43/N44 -> 22.393589 | ... AF56: =AF43/AF44 -> 16.706533
C57: Interest Rate on debt | D57: 0.02 | E57: 0.02 | F57: % Debt (l29)
C58: Interest Rate on cash | D58: =-Assumptions!S21 -> 0 | E58: =-Assumptions!T21 -> 0 | F58: % of Cash (l28)
C59: PPE+ROA | D59: =-Assumptions!S22 -> 0 | E59: =Assumptions!T22 -> 0 | F59: Growing with capex
C60: Working capital flows | D60: =-Assumptions!S23 -> -0.025 | E60: =-Assumptions!T23 -> -0.045 | F60: % of Change Revenues (l2)
C61: Intangible Assets | D61: =Assumptions!S24 -> 0 | E61: =Assumptions!T24 -> 0 | F61: Growing with amortization
C62: Capex | D62: =-Assumptions!S25 -> -0.07 | E62: =-Assumptions!T25 -> -0.09 | F62: % Revenue
C63: Acquisition factor | D63: =Assumptions!S26 -> 0 | E63: =Assumptions!T26 -> 0 | F63: % Revenue
C64: Dividends | D64: 0.2 | E64: 0.25 | F64: % Free Cash Flow
C65: Repurchases | D65: 0.12 | E65: 0.15 | F65: % Free Cash Flow
C66: Leases | D66: =Assumptions!S29 -> 0.09 | E66: 0.11 | F66: % Revenue
C67: Cash Costs for EBIT | D67: =Assumptions!S30 -> 0 | E67: =Assumptions!T30 -> 0 | F67: % Revenue
C68: Total Debt | D68: 0.1 | E68: 0.14 | F68: % EBITDA
A70: Valuation | D70: $ millions
C71: Value of flows | D71: =SUMPRODUCT(G35:AF35,G45:AF45)+((AF43-AF44)*AF45) -> 9904.7108 | E71: =D71/D73 -> 0.78711503
C72: Value of perpetuity | D72: =(AF34/(F50-AF5))*AF45 -> 2678.8512 | E72: =D72/D73 -> 0.21288497
C73: Total Value | D73: =D71+D72 -> 12583.562
C74: Actual share price | D74: =OP!C21 -> 3.13
C75: Total value vs Mkt Cap | D75: =D76/D74-1 -> 0.33499165 | U75: Pilbara
C76: Estimated NPV per share | D76: =D73*1000000/OP!C22 -> 4.1785239 | M76: Acumen | O76: 0.234 | R76: 2022 - 2030 | U76: =(M6/E6)^(1/COUNT(E4:M4))-1 -> 0.1588627
M77: Mordor Intelligence | O77: 0.1957 | R77: 2024 - 2029 | U77: =(L6/G6)^(1/COUNT(G5:L5))-1 -> 0.093566475
A78: Sensibility | C78: Sensitivity +0.1% | D78: =(SUMPRODUCT(G35:AF35,G45:AF45)+((AF43-AF44)*AF45)+(AF34/(F50+0.001-AF5))*AF45)*1000000/OP!C22 -> 4.1641764 | E78: =D78/D76-1 -> -0.0034336285 | M78: Grand View Research | O78: 0.128 | R78: 2024 - 2030 | U78: =(M6/G6)^(1/COUNT(G6:M6))-1 -> 0.10830358
C79: Sensitivity +0.5% | D79: =(SUMPRODUCT(G35:AF35,G45:AF45)+((AF43-AF44)*AF45)+(AF34/(F50+0.005-AF5))*AF45)*1000000/OP!C22 -> 4.1111341 | E79: =D79/D76-1 -> -0.016127649 | M79: Straits Research | O79: 0.221 | R79: 2023 - 2031 | U79: =(N6/F6)^(1/COUNT(F7:N7))-1 -> -0.0096761885
M80: AVERAGE | O80: =AVERAGE(O76:Q79) -> 0.194675 | R80: 2023 - 2031 | U80: =(N6/F6)^(1/COUNT(F7:N7))-1 -> -0.0096761885
A81: Notes | C81: Price where it'd be a "BUY" | D81: =IF(D75<15%,D76/1.15,D74) -> 3.13
A86: Links
A87: https://www.fool.com.au/2023/12/07/pilbara-minerals-shares-have-dropped-34-in-4-months-heres-what-to-focus-on/
A88: https://www.nasdaq.com/articles/lithium-market-forecast%3A-top-trends-that-will-affect-lithium-in-2024
A90: https://www.statista.com/statistics/208725/net-profit-margin-of-the-top-mining-companies/
A92: Net profit margin of the top mining companies worldwide from 2002 to 2022, with a forecast for 2023 | B92: Study done by PwC (June 2023)
A94: 2002 | B94: 6 | C94: in %
A95: 2003 | B95: 11 | C95: in %
A96: 2004 | B96: 15 | C96: in %
A97: 2005 | B97: 20 | C97: in %
A98: 2006 | B98: 27 | C98: in %
A99: 2007 | B99: 26 | C99: in %
A100: 2008 | B100: 16 | C100: in %
A101: 2009 | B101: 15 | C101: in %
A102: 2010 | B102: 25 | C102: in %
A103: 2011 | B103: 24 | C103: in %
A104: 2012 | B104: 13 | C104: in %
A105: 2013 | B105: 4 | C105: in %
... A115: 2023* | B115: 14 | C115: in %
A116: Average for the past 21 years | B116: =AVERAGE(B94:B115) -> 13.454545
A123: Percentage | B123: Sensitivity Analysis | C123: 2024 | D123: 2025 | E123: 2026 | F123: 2027 | G123: 2028 | H123: 2029 | I123: 2030 | J123: 2031 | K123: 2032 | L123: 2033 | M123: 2034 | N123: 2035 | O123: 2036 | P123: 2037 | Q123: 2038 | R123: 2039 | S123: 2040 | T123: 2041 | U123: 2042 | V123: 2043 | W123: 2044 | X123: 2045 | Y123: 2046 | Z123: 2047 | AA123: 2048 | AB123: 2049
A124: 0.375 | B124: Ore Growth
A125: 0.05 | B125: Good Market | C125: =C126+$A$125 -> 0.25220134 | D125: =D126+$A$125 -> 0.25779661 | E125: =E126+$A$125 -> 0.258363 | F125: =F126+$A$125 -> 0.20802233 | G125: =G126+$A$125 -> 0.19145903 | H125: =H126+$A$125 -> 0.084340432 | I125: =I126+$A$125 -> 0.18586943 | J125: =J126+$A$125 -> 0.1869217 | ... AB125: =AB126+$A$125 -> 0.11245589
A126: 0 | B126: Current Market | C126: =Assumptions!O148 -> 0.20220134 | D126: =Assumptions!P148 -> 0.20779661 | E126: =Assumptions!Q148 -> 0.208363 | F126: =Assumptions!R148 -> 0.15802233 | G126: =Assumptions!S148 -> 0.14145903 | H126: =Assumptions!T148 -> 0.034340432 | I126: =Assumptions!U148 -> 0.13586943 | J126: =Assumptions!V148 -> 0.1369217 | ... AB126: =Assumptions!AN148 -> 0.062455886
A127: -0.075 | B127: Bad Market | C127: =C126+$A$127 -> 0.12720134 | D127: =D126+$A$127 -> 0.13279661 | E127: =E126+$A$127 -> 0.133363 | F127: =F126+$A$127 -> 0.083022335 | G127: =G126+$A$127 -> 0.066459027 | H127: =H126+$A$127 -> -0.040659568 | I127: =I126+$A$127 -> 0.060869428 | J127: =J126+$A$127 -> 0.061921696 | ... AB127: =AB126+$A$127 -> -0.012544114
A129: =1-A124 -> 0.625 | B129: Lithium Price
A130: 0.1 | B130: Good Market | C130: =C131+$A$130 -> -0.41223543 | D130: =D131+$A$130 -> -0.041932838 | E130: =E131+$A$130 -> 0.50692169 | F130: =F131+$A$130 -> 0.14011624 | G130: =G131+$A$130 -> 0.080741676 | H130: =H131+$A$130 -> -0.020369016 | I130: =I131+$A$130 -> 0.16512231 | J130: =J131+$A$130 -> 0.07820408 | ... AB130: =AB131+$A$130 -> 0.098030112
A131: 0 | B131: Current Market | C131: =Assumptions!O151 -> -0.51223543 | D131: =Assumptions!P151 -> -0.14193284 | E131: =Assumptions!Q151 -> 0.40692169 | F131: =Assumptions!R151 -> 0.040116237 | G131: =Assumptions!S151 -> -0.019258324 | H131: =Assumptions!T151 -> -0.12036902 | I131: =Assumptions!U151 -> 0.06512231 | J131: =Assumptions!V151 -> -0.02179592 | ... AB131: =Assumptions!AN151 -> -0.0019698881
...

Sheet Assumptions
B2: Assumptions
B4: Prospects:
B5: Links:
C7: =OP!J21 -> 2023 | D7: =C7-1 -> 2022 | E7: =D7-1 -> 2021 | F7: =E7-1 -> 2020 | G7: =F7-1 -> 2019 | H7: =G7-1 -> 2018 | I7: =H7-1 -> 2017 | J7: =I7-1 -> 2016 | K7: =J7-1 -> 2015 | L7: =K7-1 -> 2014 | N7: Average (3y) | O7: Average (5y) | P7: Average (10y) | Q7: Average (w/o covid) | S7: Short Term Forecast | T7: Long Term Forecast | U7: Production Increase, Sales Increase however lower price per tonne dropped the revenue (H1 2024)
B8: Revenue growth | C8: =('Inputs (AUD)'!B6-'Inputs (AUD)'!C6)/'Inputs (AUD)'!C6 -> 2.4162744 | D8: =('Inputs (AUD)'!C6-'Inputs (AUD)'!D6)/'Inputs (AUD)'!D6 -> 5.7667804 | E8: =('Inputs (AUD)'!D6-'Inputs (AUD)'!E6)/'Inputs (AUD)'!E6 -> 1.0903686 | F8: =('Inputs (AUD)'!E6-'Inputs (AUD)'!F6)/'Inputs (AUD)'!F6 -> 0.96495327 | G8: =('Inputs (AUD)'!F6-'Inputs (AUD)'!G6)/'Inputs (AUD)'!G6 -> 3.1960784 | H8: =('Inputs (AUD)'!G6-'Inputs (AUD)'!H6)/'Inputs (AUD)'!H6 -> #DIV/0! | I8: =('Inputs (AUD)'!H6-'Inputs (AUD)'!I6)/'Inputs (AUD)'!I6 -> #DIV/0! | J8: =('Inputs (AUD)'!I6-'Inputs (AUD)'!J6)/'Inputs (AUD)'!J6 -> -1 | ... L8: =('Inputs (AUD)'!K6-'Inputs (AUD)'!L6)/'Inputs (AUD)'!L6 -> -0.99993857 | N8: =AVERAGE(C8:E8) -> 3.0911411 | O8: =AVERAGE(C8:G8) -> 2.686891 | P8: =AVERAGE(C8:L8) -> #DIV/0! | Q8: =AVERAGE(C8,F8:L8) -> #DIV/0! | S8: =N8/3 -> 1.0303804 | T8: =O8/10 -> 0.2686891
B9: Operating Margin | C9: ='Inputs (AUD)'!B8/'Inputs (AUD)'!B6 -> 0.79032972 | D9: ='Inputs (AUD)'!C8/'Inputs (AUD)'!C6 -> 0.61524882 | E9: ='Inputs (AUD)'!D8/'Inputs (AUD)'!D6 -> -0.19908987 | F9: ='Inputs (AUD)'!E8/'Inputs (AUD)'!E6 -> -0.85136742 | G9: ='Inputs (AUD)'!F8/'Inputs (AUD)'!F6 -> -0.43224299 | H9: ='Inputs (AUD)'!G8/'Inputs (AUD)'!G6 -> -1.6568627 | I9: ='Inputs (AUD)'!H8/'Inputs (AUD)'!H6 -> #DIV/0! | J9: ='Inputs (AUD)'!I8/'Inputs (AUD)'!I6 -> #DIV/0! | ... L9: ='Inputs (AUD)'!K8/'Inputs (AUD)'!K6 -> -10 | N9: =AVERAGE(C9:E9) -> 0.40216289 | O9: =AVERAGE(C9:G9) -> -0.015424348 | P9: =AVERAGE(C9:L9) -> #DIV/0! | Q9: =AVERAGE(C9,F9:L9) -> #DIV/0! | S9: =N9/2 -> 0.20108145 | T9: 0.15
Q10: =AVERAGE(C10,F10:L10) -> #DIV/0!
B12: Modelling Factors
C14: Last 10 Years
C15: =OP!J21 -> 2023 | D15: =D7 -> 2022 | E15: =E7 -> 2021 | F15: =F7 -> 2020 | G15: =G7 -> 2019 | H15: =H7 -> 2018 | I15: =I7 -> 2017 | J15: =J7 -> 2016 | K15: =K7 -> 2015 | L15: =L7 -> 2014 | N15: Average (3y) | O15: Average (5y) | P15: Average (10y) | Q15: Average (w/o covid) | S15: Short Term Forecast | T15: Long Term Forecast
