Workbook
Name Sectors: '[1]Sector Impact'!$K$4:$K$16
Name Sectors: 'Sector Impact'!$K$4:$K$16

Sheet OP
B2: 45382 | C2: Team 12 | D2: 24th April, 2024 | E2: ='Inputs (AUD)'!H3 -> #VALUE! | L2: {=_FV(E2,"Exchange abbreviation",TRUE)} -> XASX | M2: SIC:
D3: COMPANY DESCRIPTION | H3: CEO & BOARD OF DIRECTORS
D4: Pilbara Minerals Limited is an Australia-based lithium company, The Company is primarily engaged in the exploration, development, and mining of minerals in Australia, Its 100% owned Pilgangoora hard-rock lithium operation consists of two processing plants: the Pilgan Plant, located on the northern side and produces spodumene and tantalite concentrates, and the Ngungaju Plant is located to the south produces spodumene concentrate, It owns 70% of the Mt Francisco project, and hosts the large occurrence of outcropping pegmatites, It is also pursuing a proposed downstream joint venture (JV) for the development of an approximately 43,000 tons per annum (tpa) lithium carbonate equivalent (LCE) lithium chemical conversion facility in South Korea, | H4: Name (Sex;Age) | I4: Tenure | J4: Executive? | K4: Other roles
H5: Dale Henderson (M;) | I5: 2 years | J5: YES | K5: Chief Executive Officer of Pilbara Minerals
H6: Kathleen Conlon (F;) | I6: 2 months | J6: NO | K6: Non-Executive Director of Aristocrat Leisure Limited and BlueScope Steel Limited, and Chairs the Corporate Governance Committee of the Australian Institute of Company Directors
H7: Sally-Anne Layman (F;) | I7: 6 years | J7: NO | K7: Non-Executive Director of IMDEX Ltd, Beach Energy Ltd and Newmount Corporation.
H8: Nick Cernotta (M;) | I8: 7 years | J8: NO | K8: Non-Executive Chair of Panoramic Resources Limited and a Non-Executive Director of Northern Star Resources Limited and New Century Resources. Limited
H9: Steve Scudamore (M;) | I9: 8 years | J9: NO | K9: Vice Chair of the Western Australian Museum and WA Committee Chair of the Australian British Chamber of Commerce and member of the National Board
H10: Miriam Stanborough (F;) | I10: 2 years | J10: NO | K10: Chair of the Minerals Research Institute of Western Australia (MRIWA), Deputy Chair of the Northern Agricultural Catchments Council (NACC), and Deputy Chair of Scouts | O10: https://www,marketscreener,com/quote/stock/PILBARA-MINERALS-LIMITED-10354122/company/
H11: EXECUTIVE LEADERSHIP TEAM
H12: =H5 -> Dale Henderson (M;) | I12: =I5 -> 2 years | J12: =J5 -> YES | K12: =K5 -> Chief Executive Officer of Pilbara Minerals
H13: Vince De Carolis (M;) | I13: 1 year | J13: YES | K13: Chief Operating Officer
H14: Luke Bortoli (M;) | I14: 1 year | J14: YES | K14: Chief Financial Officer
H15: Sandra McInnes (F;) | I15: 1 year | J15: YES | K15: Chief Sustainability Officer
H16: John Stanning (M;) | I16: 1 year | J16: YES | K16: Chief Development Officer
H17: Paul Laybourne (M;) | I17: 1 year | J17: YES | K17: Project Director
B18: {=_FV(E2,"Currency")&" MILLIONS"} -> AUD MILLIONS | H18: Jen Mintz (F;) | I18: 1 month | J18: YES | K18: General Counsel
B19: COMPANY OVERVIEW
B20: Stock | D20: Liquidity and Solvency | F20: Segments | I20: Profitability (2023) | L20: Multiples
B21: Last Price | C21: {=_FV(E2,"Price")} -> 3.83 | D21: Total Assets | E21: =_xlfn.XLOOKUP(D21,'Fin. Data'!A:A,'Fin. Data'!B:B,,0) -> 5198.8 | F21: Regions | H21: % Sales | I21: Reporting Year | J21: 2023 | L21: Float | M21: ='Inputs (AUD)'!B82 -> 0.9037
B22: Outstanding Shares | C22: {=_FV(E2,"Shares outstanding",TRUE)} -> 3009468000 | D22: Total Liabilities | E22: =_xlfn.XLOOKUP(D22,'Fin. Data'!A:A,'Fin. Data'!B:B,,0) -> 1808.8 | F22: =Segments!C5 -> Pilgan | H22: =Segments!B5 -> 0.69622735 | I22: End of Year | J22: 45107 | L22: Insiders Own | M22: ='Inputs (AUD)'!B83 -> 0.0963
B23: Market Cap. | C23: =C21*C22/1000000 -> 11526.262 | D23: Cash/Share | E23: =_xlfn.XLOOKUP("Cash & Eq.",'Fin. Data'!A:A,'Fin. Data'!B:B,,0)*1000000/C22 -> 1.0004094 | F23: =Segments!C6 -> Ngungaju | H23: =Segments!B6 -> 0.36616828 | I23: EBITDA | K23: =_xlfn.XLOOKUP(I23,'Fin. Data'!A:A,'Fin. Data'!B:B,,0) -> 3098.7 | L23: b (Yahoo) | M23: {=_FV(E2,"Beta")} -> 1.9343
B24: +Total Debt | C24: ='Fin. Data'!B58 -> 472 | D24: EBITDA/Net Financial Cost (NFC) | E24: =_xlfn.XLOOKUP("EBITDA",'Fin. Data'!A:A,'Fin. Data'!B:B,,0)/_xlfn.XLOOKUP("Net Financial Cost",'Fin. Data'!A:A,'Fin. Data'!B:B,,0) -> 69.013363 | F24: =Segments!C7 -> (elimination of by-product) | H24: =Segments!B7 -> -0.00050762558 | I24: Depreciation & Amortization | K24: =_xlfn.XLOOKUP(I24,'Fin. Data'!A:A,'Fin. Data'!B:B,,0) -> 1.5 | L24: Score (S&P) | M24: ='Inputs (AUD)'!B84 -> None
B25: -Cash | C25: ='Fin. Data'!B39 -> 3010.7 | D25: Debt/EBITDA | E25: =_xlfn.XLOOKUP("Total Debt",'Fin. Data'!A:A,'Fin. Data'!B:B,,0)/_xlfn.XLOOKUP("EBITDA",'Fin. Data'!A:A,'Fin. Data'!B:B,,0) -> 0.15232194 | F25: =Segments!C8 -> (provisional price adjustment) | H25: =Segments!B8 -> -0.061659653 | I25: EBIT | K25: =_xlfn.XLOOKUP(I25,'Fin. Data'!A:A,'Fin. Data'!B:B,,0) -> 3097.2 | L25: Price/Book Value | M25: =IFERROR((C21*C22/(E21-E22))/1000000,"") -> 3.4000774
B26: =Enterprise Value | C26: =C23+C24-C25 -> 8987.5624 | D26: "Others Assets"/Asset | E26: =_xlfn.XLOOKUP("Other Assets",'Fin. Data'!A:A,'Fin. Data'!B:B,,0)/_xlfn.XLOOKUP("Total Assets",'Fin. Data'!A:A,'Fin. Data'!B:B,,0) -> 0.078287297 | F26: =Segments!C9 -> (hedge close-outs) | H26: =Segments!B9 -> -0.00022834539 | I26: Net Income | K26: =_xlfn.XLOOKUP(I26,'Fin. Data'!A:A,'Fin. Data'!B:B,,0) -> 2391.1 | L26: NCF(3y avg)/Asset | M26: =IFERROR(K32/E21,"") -> 0.18521582
B27: Holdings (nac/int'l) | C27: - | D27: Debt/Assets | E27: =_xlfn.XLOOKUP(D27,'Fin. Data'!A:A,'Fin. Data'!B:B,,0) -> 0.090790182 | F27: Categories | H27: % Sales | I27: EPS | K27: =1000000*K26/C22 -> 0.79452581 | L27: Price/Net Inc. (3y avg) | M27: =IFERROR(C23/K31,"") -> 11.917556
B28: t liq. (Holdings/Vol.) | C28: - | D28: EBITDA Margin (average) | E28: =AVERAGE(_xlfn.XLOOKUP("EBITDA Margin",'Fin. Data'!A:A,'Fin. Data'!B:D,,0)) -> 0.39491807 | F28: =Segments!C15 -> Spodumene | H28: =Segments!B15 -> 1.061888 | I28: ROA | K28: =K26/E21 -> 0.45993306 | L28: EV/Asset | M28: =IFERROR(C26/E21,"") -> 1.7287763
B29: % Short | C29: N/A | D29: Operating Margin (average) | E29: =AVERAGE(_xlfn.XLOOKUP("Operating Margin",'Fin. Data'!A:A,'Fin. Data'!B:D,,0)) -> 0.40216289 | F29: =Segments!C16 -> Tantalite | H29: =Segments!B16 -> 0.00050762558 | I29: ROIC | K29: =K26/(E21-(E22-C24)) -> 0.61913516 | L29: EV/Ebitda (3y average) | M29: =IFERROR(C26/K30,"") -> 7.1094759
B30: Traffic ESG | D30: Net Income Margin (average) | E30: =AVERAGE(_xlfn.XLOOKUP("Net Income Margin",'Fin. Data'!A:A,'Fin. Data'!B:D,,0)) -> 0.25608103 | F30: =Segments!C17 -> (elimination of by-product) | H30: =Segments!B17 -> -0.00050762558 | I30: EBITDA (3y average) | K30: =AVERAGE(_xlfn.XLOOKUP("EBITDA",'Fin. Data'!A:A,'Fin. Data'!B:D,,0)) -> 1264.1667 | L30: Price/NCF (3y average) | M30: =IFERROR(C23/K32,"") -> 11.970363
B31: E | F31: =Segments!C18 -> (provisional price adjustment) | H31: =Segments!B18 -> -0.061659653 | I31: Net Income (3y average) | K31: =AVERAGE(_xlfn.XLOOKUP("Net Income",'Fin. Data'!A:A,'Fin. Data'!B:D,,0)) -> 967.16667 | L31: Bonds 1,3,5a (USD) | M31: -
B32: S | D32: Net Financial Cost/Avg Net Debt | E32: =-_xlfn.XLOOKUP("Net Financial Cost",'Fin. Data'!A:A,'Fin. Data'!B:B,,0)/AVERAGE(_xlfn.XLOOKUP("Net Debt",'Fin. Data'!A:A,'Fin. Data'!B:D,,0)) -> 0.050530817 | F32: =Segments!C19 -> (hedge close-outs) | H32: =Segments!B19 -> -0.00022834539 | I32: NCF (3y average) | K32: =AVERAGE(_xlfn.XLOOKUP("Net Cash Flow",'Fin. Data'!A:A,'Fin. Data'!B:D,,0)) -> 962.9 | L32: Div+Rep.(3y avg)/Price | M32: =-IFERROR(SUM(E53:E55)/(3*C23),"") -> 0.0024668303
B33: G | L33: Div. Yield | M33: =-IFERROR(L54/C23,"") -> 0.028612918
B34: INVESTMENT THESIS
B35: Pillars of Recommendation | H35: Recommendation | I35: Valuation Assumptions
B36: Pillar | C36: Explanation | H36: BUY | I36: Check DCF
B37: Growing Company | C37: In general mining companies have a higher than average profit margins when compared with other companies publicly traded companies. Pilbara's financials have been growing exponentially in the last years and they have been able to maintain a very health balance sheet.
B38: Government Incentives and Support | C38: Governments around the world are focused on reaching a greener atmosphere by 2030, therefore they are investing heavily and incentivesing the purchase of EV's and consequently their compontents. This government support and fiscal incentives to produce more, will come with a positive side for Pilbara and the whole market.
B39: Lithium Demand | C39: Currently the supply chain has caught up to the demand, sending the current price per ton down and lowering profit margins for all market players; However, forecasts of demand point to an increase in 2025 signaling a possible increase in revenues and subsequent growth of the companies.
B40: Risks of Investment | H40: Price Target | I40: Valuation
B41: Risk | C41: Explanation | H41: =DCF!D76 -> 4.2230708 | I41: Discount Rate | J41: =DCF!F50 -> 0.095 | L41: Price M. Upside | M41: =SARD!AJ14 -> 0.52057587
B42: Lithium Price Volatility | C42: This is a recent growing concern, where we have seen lithium prices growing as suppliers saturate the market and catch-up with demand, sending the prices plumetting; Never the less, apart from this drop in price, Pilbara has still increased their sells even though the price per ton has decreased, proving their ability to navigate the market and still find buyers.
B43: Economic Cycles | C43: There has been growing concern around the renewable energies and eletrefication of automotives, however sales of eletric vehicles have been exponentially growing for the past 10 years and more and more demand is being brought for lithium batteries. Despite all of this, recently big automotive groups like Mercedes and Ford have halted their investment for the time being in EV R&D, claming it's not opportune to explore this market yet. This return on decisions from big market players might hinder the lithium sector. | I43: Upside | J43: =DCF!D75 -> 0.10262944 | L43: EV M. Upside | M43: =SARD!AM14 -> 0.50668951
B44: Finite Mineral | C44: Altough predictions point to only having 4/5 years of mineral left, some predictions are pointing all the way to 70 years of lithium available still. This is also the case due to inovation and the possibility to recycle batteries, expanding the life cycle of the sector.
B45: FINANCIAL PERFORMANCE
B46: Year | C46: Net Sales | D46: Operating Margin | E46: Dividends + Share Buyback | F46: Net Cash Flow | G46: Debt/Assets | H46: Depreciation & Amortization | I46: Capex + Investments | J46: Cash Flow
B47: =B48-1 -> 2015 | C47: {=_xlfn.SORTBY(TRANSPOSE(_xlfn.XLOOKUP(C$46,'Fin. Data'!$A:$A,'Fin. Data'!$B:$J,,0)),$B$47:$B$55,-1)} -> 0.1 | D47: {=_xlfn.SORTBY(TRANSPOSE(_xlfn.XLOOKUP(D$46,'Fin. Data'!$A:$A,'Fin. Data'!$B:$J,,0)),$B$47:$B$55,-1)} -> -52 | E47: {=_xlfn.SORTBY(TRANSPOSE(_xlfn.XLOOKUP(E$46,'Fin. Data'!$A:$A,'Fin. Data'!$B:$J,,0)),$B$47:$B$55,-1)} -> 5.2 | F47: ='Inputs (AUD)'!K77 -> 0.9 | G47: {=_xlfn.SORTBY(TRANSPOSE(_xlfn.XLOOKUP(G$46,'Fin. Data'!$A:$A,'Fin. Data'!$B:$J,,0)),$B$47:$B$55,-1)} -> - | H47: {=_xlfn.SORTBY(TRANSPOSE(_xlfn.XLOOKUP(H$46,'Fin. Data'!$A:$A,'Fin. Data'!$B:$J,,0)),$B$47:$B$55,-1)} -> 0 | I47: {=_xlfn.SORTBY(TRANSPOSE(_xlfn.XLOOKUP(I$46,'Fin. Data'!$A:$A,'Fin. Data'!$B:$J,,0)),$B$47:$B$55,-1)} -> -1.6 | L47: =J21 -> 2023 | M47: =L47-1 -> 2022
B48: =B49-1 -> 2016 | C48: 0 | D48: - | E48: 122.7 | F48: ='Inputs (AUD)'!J77 -> 2.1 | G48: - | H48: 0.1 | I48: -6.6 | J48: Net Income | L48: =_xlfn.XLOOKUP($J48,'Fin. Data'!$A:$A,'Fin. Data'!B:B,,0) -> 2391.1 | M48: =_xlfn.XLOOKUP($J48,'Fin. Data'!$A:$A,'Fin. Data'!C:C,,0) -> 561.8 | N48: =(C48/C47)-1 -> -1 | O48: =(D48/D47)-1 -> #VALUE!
B49: =B50-1 -> 2017 | C49: 0 | D49: - | E49: 68.4 | F49: ='Inputs (AUD)'!I77 -> 96.8 | G49: 0.36968796 | H49: 0.1 | I49: -52.8 | J49: Operating CF | L49: =_xlfn.XLOOKUP($J49,'Fin. Data'!$A:$A,'Fin. Data'!B:B,,0) -> 3456.7 | M49: =_xlfn.XLOOKUP($J49,'Fin. Data'!$A:$A,'Fin. Data'!C:C,,0) -> 647.6 | N49: =(C49/C48)-1 -> #DIV/0! | O49: =(D49/D48)-1 -> #VALUE! | Q49: =F49/F48-1 -> 45.095238 | R49: =H49/H48-1 -> 0 | S49: =I49/I48-1 -> 7
B50: =B51-1 -> 2018 | C50: 10.2 | D50: -1.6568627 | E50: 156.4 | F50: ='Inputs (AUD)'!H77 -> -12.9 | G50: 0.24661654 | H50: 0.2 | I50: -214.8 | J50: Investing CF | L50: =_xlfn.XLOOKUP($J50,'Fin. Data'!$A:$A,'Fin. Data'!B:B,,0) -> -408 | M50: =_xlfn.XLOOKUP($J50,'Fin. Data'!$A:$A,'Fin. Data'!C:C,,0) -> -204.5 | N50: =(C50/C49)-1 -> #DIV/0! | O50: =(D50/D49)-1 -> #VALUE! | Q50: =F50/F49-1 -> -1.1332645 | R50: =H50/H49-1 -> 1 | S50: =I50/I49-1 -> 3.0681818
B51: =B52-1 -> 2019 | C51: 42.8 | D51: -0.43224299 | E51: 60.7 | F51: ='Inputs (AUD)'!G77 -> 32.7 | G51: 0.23870857 | H51: 0.2 | I51: -178.3 | J51: Net Capex | L51: =_xlfn.XLOOKUP($J51,'Fin. Data'!$A:$A,'Fin. Data'!B:B,,0) -> -385.5 | M51: =_xlfn.XLOOKUP($J51,'Fin. Data'!$A:$A,'Fin. Data'!C:C,,0) -> -128.3 | N51: =(C51/C50)-1 -> 3.1960784 | O51: =(D51/D50)-1 -> -0.73911962 | Q51: =F51/F50-1 -> -3.5348837 | R51: =H51/H50-1 -> 0 | S51: =I51/I50-1 -> -0.16992551
B52: =B53-1 -> 2020 | C52: 84.1 | D52: -0.85136742 | E52: 111.5 | F52: ='Inputs (AUD)'!F77 -> -56.3 | G52: 0.29278008 | H52: 0.6 | I52: -22.6 | J52: Investments & Acquisitions | L52: =_xlfn.XLOOKUP($J52,'Fin. Data'!$A:$A,'Fin. Data'!B:B,,0) -> -22.4 | M52: =_xlfn.XLOOKUP($J52,'Fin. Data'!$A:$A,'Fin. Data'!C:C,,0) -> -76.2 | N52: =(C52/C51)-1 -> 0.96495327 | O52: =(D52/D51)-1 -> 0.96965003 | Q52: =F52/F51-1 -> -2.7217125 | R52: =H52/H51-1 -> 2 | S52: =I52/I51-1 -> -0.87324734
B53: =B54-1 -> 2021 | C53: 175.8 | D53: -0.19908987 | E53: 239.7 | F53: ='Inputs (AUD)'!E77 -> 22.6 | G53: 0.17573971 | H53: 0.5 | I53: -230.8 | J53: Financing CF | L53: =_xlfn.XLOOKUP($J53,'Fin. Data'!$A:$A,'Fin. Data'!B:B,,0) -> -315.1 | M53: =_xlfn.XLOOKUP($J53,'Fin. Data'!$A:$A,'Fin. Data'!C:C,,0) -> 45.5 | N53: =(C53/C52)-1 -> 1.0903686 | O53: =(D53/D52)-1 -> -0.76615281 | Q53: =F53/F52-1 -> -1.401421 | R53: =H53/H52-1 -> -0.16666667 | S53: =I53/I52-1 -> 9.2123894
B54: =B55-1 -> 2022 | C54: 1189.6 | D54: 0.61524882 | E54: 3.6 | F54: ='Inputs (AUD)'!D$77 -> 13.5 | G54: 0.14759402 | H54: 0.7 | I54: -204.5 | J54: Dividends | L54: =_xlfn.XLOOKUP($J54,'Fin. Data'!$A:$A,'Fin. Data'!B:B,,0) -> -329.8 | M54: =_xlfn.XLOOKUP($J54,'Fin. Data'!$A:$A,'Fin. Data'!C:C,,0) -> 0 | N54: =(C54/C53)-1 -> 5.7667804 | O54: =(D54/D53)-1 -> -4.0903069 | Q54: =F54/F53-1 -> -0.40265487 | R54: =H54/H53-1 -> 0.4 | S54: =I54/I53-1 -> -0.11395147
B55: =J21 -> 2023 | C55: 4064 | D55: 0.79032972 | E55: -328.6 | F55: ='Inputs (AUD)'!C77 -> 492 | G55: 0.090790182 | H55: 1.5 | I55: -407.9 | J55: Share Buyback | L55: =_xlfn.XLOOKUP($J55,'Fin. Data'!$A:$A,'Fin. Data'!B:B,,0) -> 1.2 | M55: =_xlfn.XLOOKUP($J55,'Fin. Data'!$A:$A,'Fin. Data'!C:C,,0) -> 3.6 | N55: =(C55/C54)-1 -> 2.4162744 | O55: =(D55/D54)-1 -> 0.28456926 | Q55: =F55/F54-1 -> 35.444444 | R55: =H55/H54-1 -> 1.1428571 | S55: =I55/I54-1 -> 0.99462103
B56: Annual Growth Rate | C56: =IFERROR((C55/C47)^(1/8)-1,"") -> 2.7680722 | D56: =IFERROR((D55/D47)^(1/8)-1,"") | F56: =IFERROR((F55/F47)^(1/8)-1,"") -> 1.1989498 | H56: =IFERROR((H55/H47)^(1/8)-1,"") | J56: FX | L56: =_xlfn.XLOOKUP($J56,'Fin. Data'!$A:$A,'Fin. Data'!B:B,,0) -> 13.2 | M56: =_xlfn.XLOOKUP($J56,'Fin. Data'!$A:$A,'Fin. Data'!C:C,,0) -> 3.4 | N56: =(C56/C55)-1 -> -0.99931888 | O56: =(D56/D55)-1 -> #VALUE!
B57: Average Growth Rate | C57: =IFERROR(AVERAGE(N48:N55),"") | D57: =IFERROR(AVERAGE(O48:O55),"") | F57: =IFERROR(AVERAGE(Q48:Q55),"") -> 10.192249 | H57: =IFERROR(AVERAGE(S48:S55),"") -> 2.7311526 | J57: Changes in Cash | L57: =L49-L50+L53-L54-L55 -> 3878.2 | M57: =M49-M50+M53-M54-M55 -> 894
B58: CVAR | C58: =IFERROR(STDEV(C48:C55)/AVERAGE(C48:C55),"") -> 2.0395589 | D58: =IFERROR(STDEV(D47:D55)/AVERAGE(D47:D55),"") -> -2.5484748 | F58: =IFERROR(STDEV(F47:F55)/AVERAGE(F47:F55),"") -> 2.5102778 | H58: =IFERROR(STDEV(H47:H55)/AVERAGE(H47:H55),"") -> 1.0824036 | J58: Inventory/D Revenues | L58: =IFERROR(SUM(I52:I55)/(C55-C51),"") -> -0.21530886 | M58: =IFERROR((SUM(I52:I55)-SUM(H52:H55))/(C55-C51),"") -> -0.21612951
B59: Last Year | C59: =IFERROR(C55/C54-1,"") -> 2.4162744 | D59: =IFERROR(D55/D54-1,"") -> 0.28456926 | F59: =IFERROR(1-(F55/F54),"") -> -35.444444 | H59: =IFERROR(1-(H55/H54),"") -> -1.1428571 | J59: t inversiones; t adq. neto dep. | L59: =IFERROR(L58/E28,"") -> -0.54519881 | M59: =IFERROR(M58/E28,"") -> -0.54727684
B60: QUALITATIVE ANALYSIS
B61: SWOT ANALYSIS | J61: HOLDERS
B62: Strenghts | E62: Weaknesses | J62: Name | M62: % Stake
B63: Strategic position: The Pilgangoora Operation, (their biggest operation) is positioned within a source-rich region. Joint venture with POSCO: construction of a lithium chemical hydroxide facility in South Korea which will enable both companies to participate in the chemical conversion industry. | E63: Low diversity of products: they mostly only export a product to be processed into lithium chemicals for the lithium-ion battery industry, so they will be threaten by any changes in the lithium market. Lithium price decrease: Recently the lithium price dropped, and it’s being predicted that it will drop more due to a future lithium surplus production in 2024. | J63: HSBC CUSTODY NOMINEES (AUSTRALIA) LIMITED | M63: 0.257
J64: JP MORGAN NOMINEES AUSTRALIA PTY LIMITED | M64: 0.1403
J65: CITICORP NOMINEES PTY LIMITED | M65: 0.0887
J66: GFL INTERNATIONAL CO LTD | M66: 0.0574
J67: POS-LT PTY LTD | M67: 0.0273
J68: NATIONAL NOMINEES LIMITED | M68: 0.0259
J69: BNP PARIBAS NOMS PTY LTD | M69: 0.0257
J70: BNP PARIBAS NOMINEES PTY LTD ACF CLEARSTREAM | M70: 0.0152
J71: BNP PARIBAS NOMINEES PTY LTD <AGENCY LENDING A/C> | M71: 0.0101
J72: HSBC CUSTODY NOMINEES (AUSTRALIA) LIMITED <NT-COMNWLTH SUPER CORP A/C> | M72: 0.0058
B73: Opportunities | E73: Threats | J73: BNP PARIBAS NOMINEES PTY LTD <IB AU NOMS RETAILCLIENT> | M73: 0.0042
B74: Green energy search: Rising market demand due to search for green alternatives of energetic sources to fight the climate changes (long term point of view). Free trade agreements: Government free trade agreement allows for opportunities to enter new market. Key Expansion Projects: P1000 expansion project will increase the production capacity. | E74: Geopolitical Risk: significant dependence on the Chinese market, could be affected by their policies Climate Change: operations could be impacted by changes to local or international regulations, taxation, and/or penalties. Limited mining life of their lithium exploration: the Pilgangoora Operation (independent hard-rock lithium operation) has an estimated mine life of approximately 34 years and there is no expansion in sight for them (regarding mineral products diversity). | J74: CITICORP NOMINEES PTY LIMITED | M74: 0.0037
J75: WASHINGTON H SOUL PATTISON AND COMPANY LIMITED | M75: 0.0036
J76: PALM BEACH NOMINEES PTY LTD | M76: 0.003
J77: NETWEALTH INVESTMENTS LTD | M77: 0.0026
J78: BNPP NOMS PTY LTD HUB24 CUSTODIAL | M78: 0.25%
J79: USB NOMINEES PTY LTD | M79: 0.0022
J80: MR PETER BARRETT CAPP | M80: 0.0017
J81: BRINSDEN HOLDINGS PTY LTD | M81: 0.17%
J82: BNP PARIBAS NOMS | M82: 0.0014
J83: TOTAL | M83: =SUM(M63:M82) -> 0.6758
B84: NOTES | G84: STOCK PERFORMANCE (5 years)
B85: Output in top producers Australia and Latin America will rise 22% and 29% respectively, while that in Africa is expected to double, driven by projects in Zimbabwe, the bank said. Chinese production will also jump 40% in the next two years. This supply surge will lead to a global lithium surplus of 12% (2024).
G109: ='Inputs (AUD)'!H3 -> #VALUE! | I109: =Peers!C2 -> #VALUE! | J109: =Peers!C3 -> #VALUE! | L109: =Peers!C4 -> #VALUE! | M109: =Peers!C5 -> #VALUE!
B112: global supply surplus: https://www.reuters.com/markets/commodities/china-lithium-price-poised-further-decline-2024-analysts-2023-12-01/

Sheet Acuerdo
A1: Invertir
A2: NO invertir
A3: Mantener sin elevar posición
A4: Mantener (y seguir comprando)
A5: Liquidar
A6: PENDIENTE

Sheet Segments
B2: ="Regions "&"("&OP!$J$21&")" -> Regions (2023) | Q2: Products
D3: Nominal value | K3: YoY Growth
B4: Weight | C4: Region (Plant) | D4: =OP!J21 -> 2023 | E4: =D4-1 -> 2022 | F4: =E4-1 -> 2021 | G4: =F4-1 -> 2020 | H4: =G4-1 -> 2019 | I4: =H4-1 -> 2018 | K4: =OP!J21 -> 2023 | L4: =K4-1 -> 2022 | M4: =L4-1 -> 2021 | N4: =M4-1 -> 2020 | O4: =N4-1 -> 2019 | P4: =O4-1 -> 2018
B5: =IFERROR(D5/$D$10,"") -> 0.69622735 | C5: Pilgan | D5: =+(D15*38/58+D16) -> 2829.4812 | E5: =+E15*38/58+E16 -> 766.81931 | F5: =+F15+F16 -> 170.45 | G5: =+G15+G16 -> 92.854 | H5: =+H15+H16 -> 44.498 | I5: =+I15+I16 -> 9.88 | K5: =IFERROR((D5-E5)/E5,"-") -> 2.689893 | L5: =IFERROR((E5-F5)/F5,"-") -> 3.4987933 | M5: =IFERROR((F5-G5)/G5,"-") -> 0.83567752 | N5: =IFERROR((G5-H5)/H5,"-") -> 1.0867005 | O5: =IFERROR((H5-I5)/I5,"-") -> 3.5038462 | P5: =IFERROR((I5-J5)/J5,"-") -> -
B6: =IFERROR(D6/$D$10,"") -> 0.36616828 | C6: Ngungaju | D6: =+D15*20/58 -> 1488.1148 | E6: =+E15*20/58 -> 400.77069 | F6: - | G6: - | H6: - | I6: - | K6: =IFERROR((D6-E6)/E6,"-") -> 2.7131329 | L6: =IFERROR((E6-F6)/F6,"-") -> - | M6: =IFERROR((F6-G6)/G6,"-") -> - | N6: =IFERROR((G6-H6)/H6,"-") -> - | O6: =IFERROR((H6-I6)/I6,"-") -> - | P6: =IFERROR((I6-J6)/J6,"-") -> -
B7: =IFERROR(D7/$D$10,"") -> -0.00050762558 | C7: =+C17 -> (elimination of by-product) | D7: =+D17 -> -2.063 | E7: =+E17 -> -5.355 | F7: =+F17 -> -5.982 | G7: =+G17 -> -7.463 | H7: =+H17 -> -2.293 | I7: =+I17 -> - | K7: =IFERROR((D7-E7)/E7,"-") -> -0.61475257 | L7: =IFERROR((E7-F7)/F7,"-") -> -0.10481444 | M7: =IFERROR((F7-G7)/G7,"-") -> -0.19844567 | N7: =IFERROR((G7-H7)/H7,"-") -> 2.2546882 | O7: =IFERROR((H7-I7)/I7,"-") -> - | P7: =IFERROR((I7-J7)/J7,"-") -> -
B8: =IFERROR(D8/$D$10,"") -> -0.061659653 | C8: =+C18 -> (provisional price adjustment) | D8: =+D18 -> -250.586 | E8: =+E18 -> 27.356 | F8: =+F18 -> 11.356 | G8: =+G18 -> -1.194 | H8: =+H18 -> - | I8: =+I18 -> - | K8: =IFERROR((D8-E8)/E8,"-") -> -10.160184 | L8: =IFERROR((E8-F8)/F8,"-") -> 1.4089468 | M8: =IFERROR((F8-G8)/G8,"-") -> -10.510888 | N8: =IFERROR((G8-H8)/H8,"-") -> - | O8: =IFERROR((H8-I8)/I8,"-") -> - | P8: =IFERROR((I8-J8)/J8,"-") -> -
B9: =IFERROR(D9/$D$10,"") -> -0.00022834539 | C9: =+C19 -> (hedge close-outs) | D9: =+D19 -> -0.928 | E9: =+E19 -> - | F9: =+F19 -> - | G9: =+G19 -> -0.05 | H9: =+H19 -> 0.58 | I9: =+I19 -> 0.308 | K9: =IFERROR((D9-E9)/E9,"-") -> - | L9: =IFERROR((E9-F9)/F9,"-") -> - | M9: =IFERROR((F9-G9)/G9,"-") -> - | N9: =IFERROR((G9-H9)/H9,"-") -> -1.0862069 | O9: =IFERROR((H9-I9)/I9,"-") -> 0.88311688 | P9: =IFERROR((I9-J9)/J9,"-") -> -
B10: =SUM(B5:B9) -> 1 | C10: TOTAL | D10: =SUM(D5:D9) -> 4064.019 | E10: =SUM(E5:E9) -> 1189.591 | F10: =SUM(F5:F9) -> 175.824 | G10: =SUM(G5:G9) -> 84.147 | H10: =SUM(H5:H9) -> 42.785 | I10: =SUM(I5:I9) -> 10.188 | K10: =(D10-E10)/E10 -> 2.4163162 | L10: =(E10-F10)/F10 -> 5.7658056 | M10: =(F10-G10)/G10 -> 1.0894863 | N10: =(G10-H10)/H10 -> 0.96674068 | O10: =(H10-I10)/I10 -> 3.1995485 | P10: -
B12: ="Categories "&"("&OP!$J$21&")" -> Categories (2023)
D13: Nominal value | K13: YoY Growth
B14: Weight | C14: Category | D14: =OP!J21 -> 2023 | E14: =D14-1 -> 2022 | F14: =E14-1 -> 2021 | G14: =F14-1 -> 2020 | H14: =G14-1 -> 2019 | I14: =H14-1 -> 2018 | K14: =OP!J21 -> 2023 | L14: =K14-1 -> 2022 | M14: =L14-1 -> 2021 | N14: =M14-1 -> 2020 | O14: =N14-1 -> 2019 | P14: =O14-1 -> 2018
B15: =IFERROR(D15/$D$20,"") -> 1.061888 | C15: Spodumene | D15: =4315533000/1000000 -> 4315.533 | E15: =1162235000/1000000 -> 1162.235 | F15: =164468000/1000000 -> 164.468 | G15: =85391000/1000000 -> 85.391 | H15: =42205000/1000000 -> 42.205 | I15: =9880000/1000000 -> 9.88 | K15: =IFERROR((D15-E15)/E15,"-") -> 2.7131329 | L15: =IFERROR((E15-F15)/F15,"-") -> 6.066633 | M15: =IFERROR((F15-G15)/G15,"-") -> 0.92605778 | N15: =IFERROR((G15-H15)/H15,"-") -> 1.0232437 | O15: =IFERROR((H15-I15)/I15,"-") -> 3.2717611 | P15: =IFERROR((I15-J15)/J15,"-") -> -
B16: =IFERROR(D16/$D$20,"") -> 0.00050762558 | C16: Tantalite | D16: =2063000/1000000 -> 2.063 | E16: =5355000/1000000 -> 5.355 | F16: =5982000/1000000 -> 5.982 | G16: =7463000/1000000 -> 7.463 | H16: =2293000/1000000 -> 2.293 | I16: 0 | K16: =IFERROR((D16-E16)/E16,"-") -> -0.61475257 | L16: =IFERROR((E16-F16)/F16,"-") -> -0.10481444 | M16: =IFERROR((F16-G16)/G16,"-") -> -0.19844567 | N16: =IFERROR((G16-H16)/H16,"-") -> 2.2546882 | O16: =IFERROR((H16-I16)/I16,"-") -> - | P16: =IFERROR((I16-J16)/J16,"-") -> -
B17: =IFERROR(D17/$D$20,"") -> -0.00050762558 | C17: (elimination of by-product) | D17: =-D16 -> -2.063 | E17: =-E16 -> -5.355 | F17: =-F16 -> -5.982 | G17: =-G16 -> -7.463 | H17: =-H16 -> -2.293 | I17: - | K17: =IFERROR((D17-E17)/E17,"-") -> -0.61475257 | L17: =IFERROR((E17-F17)/F17,"-") -> -0.10481444 | M17: =IFERROR((F17-G17)/G17,"-") -> -0.19844567 | N17: =IFERROR((G17-H17)/H17,"-") -> 2.2546882 | O17: =IFERROR((H17-I17)/I17,"-") -> - | P17: =IFERROR((I17-J17)/J17,"-") -> -
B18: =IFERROR(D18/$D$20,"") -> -0.061659653 | C18: (provisional price adjustment) | D18: =-250586000/1000000 -> -250.586 | E18: =27356000/1000000 -> 27.356 | F18: =11356000/1000000 -> 11.356 | G18: =-1194000/1000000 -> -1.194 | H18: - | I18: - | K18: =IFERROR((D18-E18)/E18,"-") -> -10.160184 | L18: =IFERROR((E18-F18)/F18,"-") -> 1.4089468 | M18: =IFERROR((F18-G18)/G18,"-") -> -10.510888 | N18: =IFERROR((G18-H18)/H18,"-") -> - | O18: =IFERROR((H18-I18)/I18,"-") -> - | P18: =IFERROR((I18-J18)/J18,"-") -> -
B19: =IFERROR(D19/$D$20,"") -> -0.00022834539 | C19: (hedge close-outs) | D19: =-928000/1000000 -> -0.928 | E19: - | F19: - | G19: =-50000/1000000 -> -0.05 | H19: =580000/1000000 -> 0.58 | I19: =308000/1000000 -> 0.308 | K19: =IFERROR((D19-E19)/E19,"-") -> - | L19: =IFERROR((E19-F19)/F19,"-") -> - | M19: =IFERROR((F19-G19)/G19,"-") -> - | N19: =IFERROR((G19-H19)/H19,"-") -> -1.0862069 | O19: =IFERROR((H19-I19)/I19,"-") -> 0.88311688 | P19: =IFERROR((I19-J19)/J19,"-") -> -
B20: =SUM(B15:B19) -> 1 | C20: TOTAL | D20: =SUM(D15:D19) -> 4064.019 | E20: =SUM(E15:E19) -> 1189.591 | F20: =SUM(F15:F19) -> 175.824 | G20: =SUM(G15:G19) -> 84.147 | H20: =SUM(H15:H19) -> 42.785 | I20: =SUM(I15:I19) -> 10.188 | K20: =(D20-E20)/E20 -> 2.4163162 | L20: =(E20-F20)/F20 -> 5.7658056 | M20: =(F20-G20)/G20 -> 1.0894863 | N20: =(G20-H20)/H20 -> 0.96674068 | O20: =(H20-I20)/I20 -> 3.1995485 | P20: -
B22: Categories | D22: Description | I22: Graphs
B23: Spodumene | D23: Spodumene is one of the sources of lithium. Spodumene is first mined and crushed into powder, then is heated to high temperatures in a kiln, then is mixed with chemicals to form a lithium compound, which is then separated and purified into a concentrated lithium product.
B24: Tantalite | D24: Tantalite is the primary source of the chemical element tantalum, a corrosion (heat and acid) resistant metal. It's mainly used in alloys and glass.
B27: Industry | J27: Graphs (Industry Forecasts)
B28: Drivers | D28: Description
B29: Consumer Electronics | D29: According to the Grand View Research, the consumer electronics segment is the one with the highest CAGR (more than 17.2% from 2024 to 2030). It's composed of electronic devices such as mobile phones, laptops, cameras and speakers, which use lithiom-ion batteries.
B30: EVs | D30: The demand for electric vehicles is also a great driver for Pilbara Mineral's revenues, since they also use a great deal of lithium batteries.
B31: Lithium Prices | D31: Every company in this industry is affected by the prices of lithium since its volatility is one of the main drivers for their revenue, specially Pilbara Minerals since the almost deal solely with lithium. The prices have also decreased with an increase of supply these last few years which could turn into a rebound opportunity, since many professionals forecast prices increasing again.
B32: China | D32: The company's exposure to China's economic policies is significant and could impact commodity prices, capital flows and general confidence and sentiment. This happens because China is the biggest importer of lithium and is the responsible for a large part of total lithium processing. In recent times, China has also imposed restrictions to commodities coming from australia.
B33: Sales forecast
B34: Source | D34: Market Growth CAGR | G34: Period
B35: Acumen | D35: 0.234 | G35: 2022 - 2030
B36: Mordor Intelligence | D36: 0.1957 | G36: 2024 - 2029
B37: Grand View Research | D37: 0.128 | G37: 2024 - 2030
B38: Straits Research | D38: 0.221 | G38: 2023 - 2031
B39: AVERAGE | D39: =AVERAGE(D35:F38) -> 0.194675 | G39: 2023 - 2031
B40: Company's Strategy / Extra Notes
B41: Their strategy is 1) Delivering their performance operative commitments; 2) Achieve full potential of the Pilgangoora asset; 3) Extract greater value along the batteries materials chain and 4) Diversify revenue beyond the Pilgangoora asset. To do so they are implementing a number of iniciatives, namely: Downstream Lithium Chemical Facility In joint venture with POSCO, a 43 ktpa Lithium Hydroxide Chemical Facility was commissioned in Gwangyang, South Korea. This would diversify their assets beyond the Pilgangoora operation and diversifying beyond China by estabilishing a link with another country. The first of 2 trains is already open with a nameplate capacity of 21,5 ktpa of lithium hydroxide. There's also a joint feasibility study with Ganfeng, a chinese lithium company, for a 32 ktpa lithium conversion plant. The feasibility study is expected to be completed in March Quarter 2025 with an option to progress to a final investment decision and formation of a joint venture following that. This would fortify their links with China which is the main buyer of lithium, besides their collaboration with South Korea. Mid-stream Demonstration Plant The development of a Mid-stream Demonstration Plant on site at the Pilgangoora Operation was approved by our Board in August 2023. The facility is aimed at demonstrating the potential to enhance the battery materials supply chain by decarbonising spodumene processing, decreasing transport volumes and improving value-add processing at the mine site. Expansion The P680 and the P1000 projects aims to increase total spodumene concentrate production capacity at the Pilgangoora Operation to up to 1 Mtpa. Pilbara Minerals prefers to expand it's mining operation rather than expanding through M&A.

Sheet Peers
B1: Peer Logo | C1: Peer Name | D1: Description | G1: Currency | H1: End of Fiscal Year | I1: Next Earnings Date
B2: #VALUE! | C2: #VALUE! | D2: Albemarle Corporation is a global developer, manufacturer, and marketer of advanced engineering materials. The company produces a variety of specialty chemicals, primarily focusing on lithium and advanced materials as well as bromine and refining catalyst segments. Its lithium and advanced materials segment consist of two product categories: battery-grade lithium compounds and other specialty chemical products. These are used in a range of applications such as fire safety and soundproofing, energy storage, automotive applications, lubricants, pharmaceuticals, crop protection, and customized chemical services. The company has partnerships and joint ventures in various parts of the world and as of December 31, 2016, had 31 office and production sites globally. | G2: {=_FV(C2,"Moeda")} -> USD | H2: 31st December 2023 | I2: Q1 (1st May 2024)
B3: #VALUE! | C3: #VALUE! | D3: Sociedad Química y Minera de Chile, or SQM, is a producer and distributor of potassium nitrate and iodine. The company produces plant nutrients and industrial chemicals derived from solar evaporation ponds in the Atacama Desert. Its segments include plant nutrients (such as potassium nitrate), iodine derivatives, lithium, and industrial chemicals. The company's products are used in fertilizers to improve agricultural yield, industrial applications such as glass manufacturing and industrial nitrates, and they produce and sell iodine and its derivatives which have applications in x-ray contrast media and other uses. Lithium and its derivatives, including lithium carbonate, are used in batteries, greases, and air treatment systems and are sold globally. | G3: {=_FV(C3,"Moeda")} -> USD | H3: 31st December 2023 | I3: Q1 (22th May 2024)
B4: #VALUE! | C4: #VALUE! | D4: Mineral Resources is an Australian-based mining services company operating through six segments: Mining Services, Iron Ore, Lithium, Energy, Other Commodities, and Central. Their mining services division provides end-to-end solutions, including their subsidiary Crushing Mining Services (CSI) that offers crushing, screening, and processing solutions for mining operations. The company has three iron ore hubs in Western Australia and lithium operations in the Pilbara and Goldfields regions. The Mt Marion lithium project is located 40 kilometers southwest of Kalgoorlie, and the Wodgina lithium project is 120 kilometers south of Port Hedland, in the Pilbara region near the iron ore hubs. It includes two wells in the Perth Basin. | G4: {=_FV(C4,"Moeda")} -> AUD | H4: 30th June 2023 | I4: Q3 (26th April 2024)
B5: #VALUE! | C5: #VALUE! | D5: Arcadium Lithium PLC is an international lithium chemicals producer with a diversified product range. They produce lithium hydroxide, carbonate, spodumene, and other specialties. The company offers various lithium products such as specialty lithium, hydroxide, carbonate, battery-grade lithium hydroxide, and other lithium-ion battery grade carbonate, among others. They focus on direct lithium extraction from hard rock mining, chemical processing, and conventional brine extraction, which is said to be more efficient and less environmentally impactful than traditional methods. The company's operations span across different geographies, including the South American Lithium Triangle, Western Australia, and Canada. | G5: {=_FV(C5,"Moeda")} -> AUD | H5: 31st December 2023 | I5: Q1 (2nd May 2024)
D6: {=_FV(C6,"Descrição")} -> #VALUE! | G6: {=_FV(C6,"Moeda")} -> #VALUE!
B8: {=_FV(OP!E2,"Currency")&" MILLIONS"} -> AUD MILLIONS | C8: =OP!E2 -> #VALUE! | D8: =C2 -> #VALUE! | E8: =C3 -> #VALUE! | F8: =C4 -> #VALUE! | G8: =C5 -> #VALUE! | H8: AVERAGE | I8: Deviation from Average
B9: Company Info | H9: =IFERROR(AVERAGE(C9:F9),"") | K9: TRAFFIC
B10: Market Cap | C10: {=_FV(C8,"Market cap",TRUE)/1000000} -> 11526.26 | D10: {=(_FV(D8,"Capitalização de mercado",TRUE)*_FV($K$64,"Preço"))/1000000} -> 23385.868 | E10: {=(_FV(E8,"Capitalização de mercado",TRUE)*_FV($K$64,"Preço"))/1000000} -> 20785.91 | F10: {=_FV(F8,"Capitalização de mercado",TRUE)/1000000} -> 13832.86 | G10: {=_FV(G8,"Capitalização de mercado",TRUE)/1000000} -> 4630.654 | H10: =IFERROR(AVERAGE(C10:G10),"") -> 14832.31 | I10: =SQRT((C10-H10)^2) -> 3306.0503 | L10: Best Value
B11: Net Sales (current) | C11: =C60 -> 4064 | D11: =D60 -> 14490 | E11: =E59 -> 15450 | F11: =F60 -> 4779.1 | G11: =G60 -> 1795.8 | H11: =IFERROR(AVERAGE(C11:G11),"") -> 8115.78 | I11: =SQRT((C11-H11)^2) -> 4051.78
B12: Profitability | H12: =IFERROR(AVERAGE(C12:F12),"") | L12: Important Value
B13: Sales Growth (ttm) | C13: =C60/C59-1 -> 2.4162744 | D13: =D60/D59-1 -> 0.37228904 | E13: =E59/E60-1 -> 0.37321127 | F13: =F60/F59-1 -> 0.39821533 | G13: =G60/G59-1 -> 0.74858812 | H13: =IFERROR(AVERAGE(C13:G13),"") -> 0.86171563 | I13: =SQRT((C13-H13)^2) -> 1.5545587
B14: Sales Growth (36m) | C14: =C60/C58-1 -> 47.323424 | D14: =D60/D58-1 -> 2.1860158 | E14: =E60/E58-1 -> 3.2601287 | F14: =F60/F58-1 -> 1.2493058 | G14: =G60/G58-1 -> 19.736721 | H14: =IFERROR(AVERAGE(C14:G14),"") -> 14.751119 | I14: =SQRT((C14-H14)^2) -> 32.572305 | L14: Worst Value
B15: Operating Margin | C15: =C63/C60 -> 0.79032972 | D15: =D63/D60 -> 0.026501035 | E15: =E63/E60 -> 0.38094392 | F15: =F63/F60 -> 0.10809567 | G15: =G63/G60 -> 0.64717675 | H15: =IFERROR(AVERAGE(C15:G15),"") -> 0.39060942 | I15: =SQRT((C15-H15)^2) -> 0.39972031
B16: Net Income Margin | C16: =C66/C60 -> 0.58836122 | D16: =D66/D60 -> -0.019116632 | E16: =E66/E59 -> 0.19695793 | F16: =F66/F60 -> 0.051118411 | G16: =G66/G60 -> 0.43434681 | H16: =IFERROR(AVERAGE(C16:G16),"") -> 0.25033355 | I16: =SQRT((C16-H16)^2) -> 0.33802767
B17: Return on Equity (RoE) | C17: =C66/C79 -> 0.70533923 | D17: =D66/D79 -> -0.020041965 | E17: =E66/E79 -> 0.37470755 | F17: =F66/F79 -> 0.070300135 | G17: =G66/G79 -> 0.1527824 | H17: =IFERROR(AVERAGE(C17:G17),"") -> 0.25661747 | I17: =SQRT((C17-H17)^2) -> 0.44872176
B18: Return on Invested Capital (ROIC) | C18: =(C66+C65)/(C78+C79) -> 0.36527706 | D18: =(D66+D65)/(D78+D79) -> -0.046389168 | E18: =(E66+E65)/(E78+E79) -> 0.12618918 | F18: =(F66+F65)/(F78+F79) -> 0.01910809 | G18: =(G66+G65)/(G78+G79) -> 0.058249652 | H18: =IFERROR(AVERAGE(C18:G18),"") -> 0.10448696 | I18: =SQRT((C18-H18)^2) -> 0.2607901
B19: Solvency | H19: =IFERROR(AVERAGE(C19:F19),"")
B20: Debt/Assets | C20: =C78/C74 -> 0.090790182 | D20: =D78/D74 -> 0.2280741 | E20: =E78/E74 -> 0.38367561 | F20: =F78/F74 -> 0.38523204 | G20: =G78/G74 -> 0.062773107 | H20: =IFERROR(AVERAGE(C20:G20),"") -> 0.23010901 | I20: =SQRT((C20-H20)^2) -> 0.13931882
B21: Net Debt/EBITDA | C21: =(C78-C69)/C62 -> -0.81927905 | D21: =(D78-D69)/D62 -> 3.623494 | E21: =(E78-E69)/E62 -> 1.177918 | F21: =(F78-F69)/F62 -> 1.0799157 | G21: =(G78-G69)/G62 -> -0.54726736 | H21: =IFERROR(AVERAGE(C21:G21),"") -> 0.90295625 | I21: =SQRT((C21-H21)^2) -> 1.7222353
B22: Debt/Assets (Leases Free Debt) | C22: =(C78-C77)/C74 -> 0.052415942 | D22: =(D78-D77)/D74 -> 0.2280741 | E22: =(E78-E77)/E74 -> 0.38367561 | F22: =(F78-F77)/F74 -> 0.38523204 | G22: =(G78-G77)/G74 -> 0.062773107 | H22: =IFERROR(AVERAGE(C22:G22),"") -> 0.22243416 | I22: =SQRT((C22-H22)^2) -> 0.17001822
B23: Net Debt/EBIT (Leases Free Debt) | C23: =((C78-C77)-C69)/C62 -> -0.88366089 | D23: =((D78-D77)-D69)/D62 -> 3.623494 | E23: =((E78-E77)-E69)/E62 -> 1.177918 | F23: =((F78-F77)-F69)/F62 -> 1.0799157 | G23: =((G78-G77)-G69)/G62 -> -0.54726736 | H23: =IFERROR(AVERAGE(C23:G23),"") -> 0.89007988 | I23: =SQRT((C23-H23)^2) -> 1.7737408
B24: Leasing Debt/Total Debt | C24: =C77/C78 -> 0.42266949 | D24: =D77/D78 -> 0 | E24: =E77/E78 -> 0 | F24: =F77/F78 -> 0 | G24: =G77/G78 -> 0 | H24: =IFERROR(AVERAGE(C24:G24),"") -> 0.084533898 | I24: =SQRT((C24-H24)^2) -> 0.33813559
B25: Interest Coverage Ratio | C25: =-C62/C64 -> -69.013363 | D25: =-D62/D64 -> 7.5885714 | E25: =-E62/E64 -> 63.4 | F25: =-F62/F64 -> 7.6496732 | G25: =-G62/G64 -> -47.013889 | H25: =IFERROR(AVERAGE(C25:G25),"") -> -7.4778015 | I25: =SQRT((C25-H25)^2) -> 61.535562
B26: Liquidity
B27: Current Ratio | C27: =C72/C76 -> 2.846724 | D27: =D72/D76 -> 1.4653787 | E27: =E72/E76 -> 2.495365 | F27: =F72/F76 -> 2.7698501 | G27: =G72/G76 -> 2.5159988 | H27: =IFERROR(AVERAGE(C27:G27),"") -> 2.4186633 | I27: =SQRT((C27-H27)^2) -> 0.42806065
B28: Quick Ratio | C28: =(C69+C70)/C76 -> 9.1692855 | D28: =(D69+D70)/D76 -> 0.59066565 | E28: =(E69+E70)/E76 -> 0.6216686 | F28: =(F69+F70)/F76 -> 1.591199 | G28: =(G69+G70)/G76 -> 2.0626495 | H28: =IFERROR(AVERAGE(C28:G28),"") -> 2.8070936 | I28: =SQRT((C28-H28)^2) -> 6.3621919
B29: Activity | H29: =IFERROR(AVERAGE(C29:F29),"")
B30: Inventory Turnover | C30: =C61/C71 -> 7.9773895 | D30: =D61/D71 -> 3.9971645 | E30: =E61/E71 -> 2.5395242 | F30: =F61/F71 -> 2.5966359 | G30: =G61/G71 -> 1.1128097 | H30: =IFERROR(AVERAGE(C30:G30),"") -> 3.6447047 | I30: =SQRT((C30-H30)^2) -> 4.3326848
B31: Acc. Receivable Turnover | C31: =C60/C70 -> 49.500609 | D31: =D60/D70 -> 8.1358787 | E31: =E60/E70 -> 9.7664931 | F31: =F60/F70 -> 7.2652782 | G31: =G60/G70 -> 12.199728 | H31: =IFERROR(AVERAGE(C31:G31),"") -> 17.373597 | I31: =SQRT((C31-H31)^2) -> 32.127012
A32: Price/Sales | B32: Payables Turnover | C32: =C61/C75 -> 5.7538918 | D32: =D61/D75 -> 4.1379648 | E32: =E61/E75 -> 10.197227 | F32: =F61/F75 -> 1.8281667 | G32: =G61/G75 -> 1.1035024 | H32: =IFERROR(AVERAGE(C32:G32),"") -> 4.6041504 | I32: =SQRT((C32-H32)^2) -> 1.1497413
B33: Fixed Asset Turnover | C33: =C60/C73 -> 2.9353557 | D33: =D60/D74 -> 0.54008722 | E33: =E59/E72 -> 1.7935918 | F33: =F60/F73 -> 1.0558514 | G33: =G60/G73 -> 0.35094782 | H33: =IFERROR(AVERAGE(C33:G33),"") -> 1.3351668 | I33: =SQRT((C33-H33)^2) -> 1.6001889
B34: Total Asset Turnover | C34: =C60/C74 -> 0.78171886 | D34: =D60/D74 -> 0.54008722 | E34: =E60/E74 -> 0.65454651 | F34: =F60/F74 -> 0.56926577 | G34: =G60/G74 -> 0.22944829 | H34: =IFERROR(AVERAGE(C34:G34),"") -> 0.55501333 | I34: =SQRT((C34-H34)^2) -> 0.22670553
B35: Valuation | H35: =IFERROR(AVERAGE(C35:F35),"")
B36: Price/Earnings | C36: =C10/C66 -> 4.8204843 | D36: =D10/D66 -> -84.425515 | E36: =E10/E66 -> 6.8307295 | F36: =F10/F66 -> 56.622431 | G36: =G10/G66 -> 5.9367359 | H36: =IFERROR(AVERAGE(C36:G36),"") -> -2.0430268 | I36: =SQRT((C36-H36)^2) -> 6.8635111
B37: Price/Sales | C37: =C10/C60 -> 2.836186 | D37: =D10/D60 -> 1.6139315 | E37: =E10/E60 -> 1.8474722 | F37: =F10/F60 -> 2.8944487 | G37: =G10/G60 -> 2.5786023 | H37: =IFERROR(AVERAGE(C37:G37),"") -> 2.3541282 | I37: =SQRT((C37-H37)^2) -> 0.48205786
B38: Price/Book | C38: =C10/C79 -> 3.4000767 | D38: =D10/D79 -> 1.6920532 | E38: =E10/E79 -> 2.5595259 | F38: =F10/F79 -> 3.9805646 | G38: =G10/G79 -> 0.90702877 | H38: =IFERROR(AVERAGE(C38:G38),"") -> 2.5078498 | I38: =SQRT((C38-H38)^2) -> 0.89222686
B39: EV/Sales | C39: =(C78+C10-C69)/C60 -> 2.2115059 | D39: =(D78+D10-D69)/D60 -> 1.9460226 | E39: =(E78+E10-E69)/E60 -> 2.3452946 | F39: =(F78+F10-F69)/F60 -> 3.2911552 | G39: =(G78+G10-G69)/G60 -> 2.1659728 | H39: =IFERROR(AVERAGE(C39:G39),"") -> 2.3919902 | I39: =SQRT((C39-H39)^2) -> 0.18048434
B40: EV/EBITDA | C40: =(C78+C10-C69-C77)/C62 -> 2.8360474 | D40: =(D78+D10-D69-D77)/D62 -> 21.233334 | E40: =(E78+E10-E69-E77)/E62 -> 5.5492976 | F40: =(F78+F10-F69-F77)/F62 -> 8.9591934 | G40: =(G78+G10-G69-G77)/G62 -> 2.8727134 | H40: =IFERROR(AVERAGE(C40:G40),"") -> 8.2901172 | I40: =SQRT((C40-H40)^2) -> 5.4540698
B41: Stock Info | H41: =IFERROR(AVERAGE(C41:F41),"")
B42: Float | C42: =OP!M21 -> 0.9037 | D42: =1-0.29% -> 0.9971 | E42: =1-0.53% -> 0.9947 | F42: =1-15.06% -> 0.8494 | G42: =100% -> 1 | H42: =IFERROR(AVERAGE(C42:G42),"") -> 0.94898 | I42: =SQRT((C42-H42)^2) -> 0.04528
B43: b (Yahoo) | C43: =OP!M23 -> 1.9343 | D43: 1.63 | E43: 1.09 | F43: 1.28 | G43: 1.85 | H43: =IFERROR(AVERAGE(C43:G43),"") -> 1.55686 | I43: =SQRT((C43-H43)^2) -> 0.37744
B44: Dividend Yield (yahoo finance) | C44: =OP!M33 -> 0.028612918 | D44: 0.0135 | E44: 0.1091 | F44: 0.0134 | G44: N/A | H44: =IFERROR(AVERAGE(C44:G44),"") -> 0.041153229 | I44: =SQRT((C44-H44)^2) -> 0.012540312
B45: Stock Performance
B46: 1y | C46: 0.0334 | D46: -0.4693 | E46: -0.408 | F46: -0.192 | G46: -0.2465 | H46: =IFERROR(AVERAGE(C46:G46),"") -> -0.25648 | I46: =SQRT((C46-H46)^2) -> 0.28988
B47: 3y | C47: =C48/1.04-1 -> 2.6826923 | D47: =D48/(157.28*1.453491)-1 -> -0.1295607 | E47: =E48/(57*1.453491)-1 -> -0.088907653 | F47: =F48/40.15-1 -> 0.76513076 | G47: =G48/10.1-1 -> -0.32871287 | H47: =IFERROR(AVERAGE(C47:G47),"") -> 0.58012837 | I47: =SQRT((C47-H47)^2) -> 2.1025639
B48: Current Price | C48: =OP!C21 -> 3.83 | D48: {=_FV(D8,"Preço")*_FV(K64,"Preço")} -> 198.98683 | E48: {=_FV(E8,"Preço")*_FV(K64,"Preço")} -> 75.483078 | F48: {=_FV(F8,"Preço")} -> 70.87 | G48: {=_FV(G8,"Preço")} -> 6.78 | H48: -- | I48: --
B49: Average Target Price | C49: 3.75 | D49: {=147.87*_FV(K64,"Preço")} -> 227.88246 | E49: {=72.09*_FV(K64,"Preço")} -> 111.0979 | F49: 68.13 | G49: 10.47 | H49: -- | I49: --
B50: Upside/Downside | C50: =C49/C48-1 -> -0.020887728 | D50: =D49/D48-1 -> 0.14521375 | E50: =E49/E48-1 -> 0.47182523 | F50: =F49/F48-1 -> -0.038662339 | G50: =G49/G48-1 -> 0.54424779 | H50: =IFERROR(AVERAGE(C50:G50),"") -> 0.22034734 | I50: =SQRT((C50-H50)^2) -> 0.24123507
B51: Extra | H51: =IFERROR(AVERAGE(C51:F51),"")
B52: 3y Operating Cash Flow | C52: =('Inputs (AUD)'!B59/'Inputs (AUD)'!E59)-1 -> -182.93158 | D52: =(1907849000*1.506672)/(719374000*1.453491)-1 -> 1.7491322 | E52: =(4077595000*1.506672)/(426971000*1.453491)-1 -> 8.8994731 | F52: =1353700000/594600000-1 -> 1.2766566 | G52: =297300000/-11090000-1 -> -27.807935 | H52: =IFERROR(AVERAGE(C52:G52),"") -> -39.76285 | I52: =SQRT((C52-H52)^2) -> 143.16873
B53: R&D/Net Sales | C53: =C67/C60 -> 0.0048474409 | D53: =D67/D60 -> 0.0089026915 | E53: =E67/E60 -> 0 | F53: =F67/F60 -> 0 | G53: =G67/G60 -> 0 | H53: =IFERROR(AVERAGE(C53:G53),"") -> 0.0027500265 | I53: =SQRT((C53-H53)^2) -> 0.0020974145
B56: Financial Data | C56: =OP!E2 -> #VALUE! | D56: =D8 -> #VALUE! | E56: =E8 -> #VALUE! | F56: =F8 -> #VALUE! | G56: =G8 -> #VALUE!
B57: IS
B58: Net Sales (36m ago) | C58: ='Fin. Data'!E5 -> 84.1 | D58: 4548 | E58: 2641 | F58: 2124.7 | G58: 86.6
B59: Net Sales (12m ago) | C59: ='Fin. Data'!C5 -> 1189.6 | D59: 10559 | E59: 15450 | F59: 3418 | G59: 1027
B60: Net Sales (current) | C60: ='Fin. Data'!B5 -> 4064 | D60: 14490 | E60: 11251 | F60: 4779.1 | G60: 1795.8
B61: COGS | C61: ='Fin. Data'!B5-'Fin. Data'!B7 -> 776.2 | D61: 12687 | E61: 6618 | F61: 1574.6 | G61: 211.1
B62: EBITDA | C62: ='Fin. Data'!B19 -> 3098.7 | D62: 1328 | E62: 4755 | F62: 1755.6 | G62: 1354
B63: Operating Income | C63: ='Fin. Data'!B11 -> 3211.9 | D63: 384 | E63: 4286 | F63: 516.6 | G63: 1162.2
B64: Net Financial Cost | C64: ='Fin. Data'!B14 -> 44.9 | D64: -175 | E64: =179-254 -> -75 | F64: =39.2-268.7 -> -229.5 | G64: ='[2]Arcadium Lithium PLC | Income S'!$B$38 -> 28.8 | K64: #VALUE! | L64: {=_FV(K64,"Preço")} -> 1.5411
B65: Taxes | C65: ='Fin. Data'!B21 -> -980.4 | D65: -648 | E65: -1186 | F65: -116.1 | G65: -454
B66: Net Income | C66: ='Fin. Data'!B23 -> 2391.1 | D66: -277 | E66: 3043 | F66: 244.3 | G66: 780
B67: R&D | C67: 19.7 | D67: 129 | E67: 0 | F67: 0 | G67: 0
B68: BS
B69: Cash & Eq. | C69: ='Fin. Data'!B39 -> 3010.7 | D69: 1307 | E69: 994 | F69: 1338.2 | G69: 1232.3
B70: Acc. Receivables | C70: ='Fin. Data'!B40 -> 82.1 | D70: 1781 | E70: 1152 | F70: 657.8 | G70: 147.2
B71: Inventory | C71: ='Fin. Data'!B41 -> 97.3 | D71: 3174 | E71: 2606 | F71: 606.4 | G71: 189.7
B72: Current Assets | C72: ='Inputs (AUD)'!C27 -> 960.2 | D72: 7661 | E72: 8614 | F72: 3474.5 | G72: 1682.7
B73: Fixed Assets | C73: ='Fin. Data'!B42 -> 1384.5 | D73: 14145 | E73: 5408 | F73: 4526.3 | G73: 5117
B74: Total Assets | C74: ='Fin. Data'!B44 -> 5198.8 | D74: 26829 | E74: 17189 | F74: 8395.2 | G74: 7826.6
B75: Acc. Payable | C75: ='Inputs (AUD)'!C43 -> 134.9 | D75: 3066 | E75: 649 | F75: 861.3 | G75: 191.3
B76: Current Liabilities | C76: ='Inputs (AUD)'!C42 -> 337.3 | D76: 5228 | E76: 3452 | F76: 1254.4 | G76: 668.8
B77: Leasing Debt | C77: ='Fin. Data'!B50+'Fin. Data'!B54 -> 199.5
B78: Total Debt | C78: ='Fin. Data'!B58 -> 472 | D78: 6119 | E78: 6595 | F78: 3234.1 | G78: 491.3
B79: Total Equity | C79: ='Fin. Data'!B64 -> 3390 | D79: 13821 | E79: 8121 | F79: 3475.1 | G79: 5105.3
C82: Lithium developer Liontown backs Albemarle's $4.3 billion bid | Reuters
C83: 61171202-1.pdf (ltresources.com.au)
C84: ASX Lithium Stocks: 5 Biggest Companies in 2023 (investingnews.com)
C85: 3 Top Lithium Stocks to Watch for the Coming Quarter | Nasdaq
C86: 2023-Annual-Report.pdf (amazonaws.com)
C87: 8 Best Lithium Stocks of March 2024 – Forbes Advisor
C88: Lithium Stocks List: 5 Biggest Lithium Stocks - Insider Monkey
C89: 2023-Annual-Report-incorporating-Appendix-4E.pdf (irmau.com)
H91: Industry peers average
B92: EBITDA margin | C92: =C62/C60 -> 0.76247539 | D92: =D62/D60 -> 0.091649413 | E92: =E62/E60 -> 0.4226291 | F92: =F62/F60 -> 0.3673495 | G92: =G62/G60 -> 0.75398151 | H92: =AVERAGE(C92:G92) -> 0.47961698
B93: Debt/Assets | C93: =C78/C74 -> 0.090790182 | D93: =D78/D74 -> 0.2280741 | E93: =E78/E74 -> 0.38367561 | F93: =F78/F74 -> 0.38523204 | G93: =G78/G74 -> 0.062773107 | H93: =AVERAGE(C93:G93) -> 0.23010901
B94: Debt/EBITDA | C94: =C78/C62 -> 0.15232194 | D94: =D78/D62 -> 4.6076807 | E94: =E78/E62 -> 1.3869611 | F94: =F78/F62 -> 1.8421622 | G94: =G78/G62 -> 0.36285081 | H94: =AVERAGE(C94:G94) -> 1.6703954

Sheet SARD
C1: in AUD | F1: Variables | K1: Rankings | P1: Difference | U1: Results | Y1: Additional Information | AD1: =B3 -> PLS.AX | AE1: Selected Peers | AJ1: Price Multiples (TTM) | AM1: Enterprise Value Multiples (TTM)
B2: Ticker | C2: Company Name | D2: TRBC Industry | E2: Country | F2: ROE | G2: DEBT/EBIT | H2: Market Cap | I2: EPS Growth (2022-2023) (Refinitiv Smart Estimate) | J2: EBIT Margin | K2: ROE | L2: DEBT/EBIT | M2: Market Cap | N2: EPS Growth | O2: EBIT Margin | P2: ROE | Q2: DEBT/EBIT | R2: Market Cap | S2: EPS Growth | T2: EBIT Margin | U2: SARD Result | V2: SARD Peers | W2: SARD Peers adjusted Rank | Y2: Suitability | Z2: Relevant Information Missing | AA2: Author's Override | AB2: Observations | AE2: SARD Peers adjusted Rank | AF2: SARD Result | AG2: Ticker | AH2: Company Name | AI2: Country | AJ2: P / E | AK2: P / B | AL2: Price / Sales | AM2: EV / Sales | AN2: EV / EBITDA | AS2: Net Income After Taxes | AT2: Total Equity | AU2: Total Debt | AV2: Operating Income | AW2: Revenue | AX2: Company Market Cap | AY2: Earnings per Share (FY1) | AZ2: Earnings per Share (FY0)
A3: Benchmark | B3: PLS.AX | C3: Pilbara Minerals Ltd | D3: Diversified Mining | E3: Australia | F3: =AS3/AT3 -> 0.70534498 | G3: =AU3/AV3 -> 0.14693659 | H3: =AX3 -> 1.3271754e+10 | I3: =(AY3/AZ3)-1 -> -0.85219897 | J3: =AV3/AW3 -> 0.79033169 | K3: =IFERROR(_xlfn.RANK.EQ(F3,F$3:F$64),"N/A") -> 2 | L3: =IFERROR(_xlfn.RANK.EQ(G3,G$3:G$64),"N/A") -> 27 | M3: =IFERROR(_xlfn.RANK.EQ(H3,H$3:H$64),"N/A") -> 11 | N3: =IFERROR(_xlfn.RANK.EQ(I3,I$3:I$64),"N/A") -> 45 | O3: =IFERROR(_xlfn.RANK.EQ(J3,J$3:J$64),"N/A") -> 2 | P3: - | Q3: - | R3: - | S3: - | T3: - | U3: - | V3: - | W3: - | Y3: =IF(OR(Z3="Y",AA3="Y"),"Not suitable","") | Z3: =IF(OR(N3="N/A",O3="N/A"),"Y","") | AE3: 1 | AF3: =_xlfn.XLOOKUP(AE3,$W$4:$W$64,$U$4:$U$64,"N/A",0,1) -> 24 | AG3: =_xlfn.XLOOKUP(AE3,$W$4:$W$64,$B$4:$B$64,"N/A",0,1) -> HZNC.NS | AH3: =_xlfn.XLOOKUP(AE3,$W$4:$W$64,$C$4:$C$64,"N/A",0,1) -> Hindustan Zinc Ltd | AI3: =_xlfn.XLOOKUP(AE3,$W$4:$W$64,$E$4:$E$64,"N/A",0,1) -> India | AJ3: 16.403313 | AK3: 9.6729016 | AL3: 4.4130356 | AM3: 4.4209976 | AN3: 9.2660538 | AS3: 2391135000 | AT3: 3390022000 | AU3: 471949000 | AV3: 3211923000 | AW3: 4064019000 | AX3: 1.3271754e+10 | AY3: 0.11181 | AZ3: 0.75649
A4: Comparison | B4: AIS.AX | C4: Aeris Resources Ltd | D4: Diversified Mining | E4: Australia | F4: =AS4/AT4 -> -0.52466316 | G4: =AU4/AV4 -> -0.18904627 | H4: =AX4 -> 1.1126544e+08 | I4: =(AY4/AZ4)-1 -> -0.78780178 | J4: =AV4/AW4 -> -0.21427778 | K4: =IFERROR(_xlfn.RANK.EQ(F4,F$3:F$64),"N/A") -> 53 | L4: =IFERROR(_xlfn.RANK.EQ(G4,G$3:G$64),"N/A") -> 43 | M4: =IFERROR(_xlfn.RANK.EQ(H4,H$3:H$64),"N/A") -> 42 | N4: =IFERROR(_xlfn.RANK.EQ(I4,I$3:I$64),"N/A") -> 44 | O4: =IFERROR(_xlfn.RANK.EQ(J4,J$3:J$64),"N/A") -> 40 | P4: =IFERROR(ABS(K$3-K4),"N/A") -> 51 | Q4: =IFERROR(ABS(L$3-L4),"N/A") -> 16 | R4: =IFERROR(ABS(M$3-M4),"N/A") -> 31 | S4: =IFERROR(ABS(N$3-N4),"N/A") -> 1 | T4: =IFERROR(ABS(O$3-O4),"N/A") -> 38 | U4: =SUM(P4:T4) -> 137 | V4: =_xlfn.RANK.EQ(U4,$U$4:$U$64,1) -> 36 | W4: =IF(Y4="Not suitable","-",V4) -> 36 | Y4: =IF(OR(Z4="Y",AA4="Y"),"Not suitable","") | Z4: =IF(OR(N4="N/A",O4="N/A"),"Y","") | AE4: 3 | AF4: =_xlfn.XLOOKUP(AE4,$W$4:$W$64,$U$4:$U$64,"N/A",0,1) -> 42 | AG4: =_xlfn.XLOOKUP(AE4,$W$4:$W$64,$B$4:$B$64,"N/A",0,1) -> DPM.TO | AH4: =_xlfn.XLOOKUP(AE4,$W$4:$W$64,$C$4:$C$64,"N/A",0,1) -> Dundee Precious Metals Inc | AI4: =_xlfn.XLOOKUP(AE4,$W$4:$W$64,$E$4:$E$64,"N/A",0,1) -> Canada | AJ4: 6.9517221 | AK4: 1.1274434 | AL4: 2.4291069 | AM4: 1.308628 | AN4: 2.4998279 | AS4: -139754000 | AT4: 266369000 | AU4: 24811000 | AV4: -131243000 | AW4: 612490000 | AX4: 1.1126544e+08 | AY4: -0.0334 | AZ4: -0.1574
B5: ATY.V | C5: Atico Mining Corp | D5: Diversified Mining | E5: Canada | F5: =AS5/AT5 -> -0.053334092 | G5: =AU5/AV5 -> 2.5020665 | H5: =AX5 -> 16458205 | I5: =(AY5/AZ5)-1 -> -2.0162852 | J5: =AV5/AW5 -> 0.14057106 | K5: =IFERROR(_xlfn.RANK.EQ(F5,F$3:F$64),"N/A") -> 34 | L5: =IFERROR(_xlfn.RANK.EQ(G5,G$3:G$64),"N/A") -> 12 | M5: =IFERROR(_xlfn.RANK.EQ(H5,H$3:H$64),"N/A") -> 60 | N5: =IFERROR(_xlfn.RANK.EQ(I5,I$3:I$64),"N/A") -> 61 | O5: =IFERROR(_xlfn.RANK.EQ(J5,J$3:J$64),"N/A") -> 20 | P5: =IFERROR(ABS(K$3-K5),"N/A") -> 32 | Q5: =IFERROR(ABS(L$3-L5),"N/A") -> 15 | R5: =IFERROR(ABS(M$3-M5),"N/A") -> 49 | S5: =IFERROR(ABS(N$3-N5),"N/A") -> 16 | T5: =IFERROR(ABS(O$3-O5),"N/A") -> 18 | U5: =SUM(P5:T5) -> 130 | V5: =_xlfn.RANK.EQ(U5,$U$4:$U$64,1) -> 32 | W5: =IF(Y5="Not suitable","-",V5) -> 32 | Y5: =IF(OR(Z5="Y",AA5="Y"),"Not suitable","") | Z5: =IF(OR(N5="N/A",O5="N/A"),"Y","") | AE5: 4 | AF5: =_xlfn.XLOOKUP(AE5,$W$4:$W$64,$U$4:$U$64,"N/A",0,1) -> 44 | AG5: =_xlfn.XLOOKUP(AE5,$W$4:$W$64,$B$4:$B$64,"N/A",0,1) -> ALS.TO | AH5: =_xlfn.XLOOKUP(AE5,$W$4:$W$64,$C$4:$C$64,"N/A",0,1) -> Altius Minerals Corp | AI5: =_xlfn.XLOOKUP(AE5,$W$4:$W$64,$E$4:$E$64,"N/A",0,1) -> Canada | AJ5: 47.935592 | AK5: 1.6986928 | AL5: 11.104905 | AM5: 13.326728 | AN5: 18.741649 | AS5: -4922787.3 | AT5: 92300949 | AU5: 33641855 | AV5: 13445628 | AW5: 95650041 | AX5: 16458205 | AY5: -0.0152207 | AZ5: 0.0149768
B6: GORO.A | C6: Gold Resource Corp | D6: Diversified Mining | E6: United States of America | F6: =AS6/AT6 -> -0.056556673 | G6: =AU6/AV6 -> 0 | H6: =AX6 -> 35338995 | I6: =(AY6/AZ6)-1 -> 3.0178865 | J6: =AV6/AW6 -> 0.042083562 | K6: =IFERROR(_xlfn.RANK.EQ(F6,F$3:F$64),"N/A") -> 36 | L6: =IFERROR(_xlfn.RANK.EQ(G6,G$3:G$64),"N/A") -> 31 | M6: =IFERROR(_xlfn.RANK.EQ(H6,H$3:H$64),"N/A") -> 55 | N6: =IFERROR(_xlfn.RANK.EQ(I6,I$3:I$64),"N/A") -> 5 | O6: =IFERROR(_xlfn.RANK.EQ(J6,J$3:J$64),"N/A") -> 28 | P6: =IFERROR(ABS(K$3-K6),"N/A") -> 34 | Q6: =IFERROR(ABS(L$3-L6),"N/A") -> 4 | R6: =IFERROR(ABS(M$3-M6),"N/A") -> 44 | S6: =IFERROR(ABS(N$3-N6),"N/A") -> 40 | T6: =IFERROR(ABS(O$3-O6),"N/A") -> 26 | U6: =SUM(P6:T6) -> 148 | V6: =_xlfn.RANK.EQ(U6,$U$4:$U$64,1) -> 42 | W6: =IF(Y6="Not suitable","-",V6) -> 42 | Y6: =IF(OR(Z6="Y",AA6="Y"),"Not suitable","") | Z6: =IF(OR(N6="N/A",O6="N/A"),"Y","") | AE6: 5 | AF6: =_xlfn.XLOOKUP(AE6,$W$4:$W$64,$U$4:$U$64,"N/A",0,1) -> 45 | AG6: =_xlfn.XLOOKUP(AE6,$W$4:$W$64,$B$4:$B$64,"N/A",0,1) -> VDAN.NS | AH6: =_xlfn.XLOOKUP(AE6,$W$4:$W$64,$C$4:$C$64,"N/A",0,1) -> Vedanta Ltd | AI6: =_xlfn.XLOOKUP(AE6,$W$4:$W$64,$E$4:$E$64,"N/A",0,1) -> India | AJ6: 9.1279843 | AK6: 3.2111772 | AL6: 0.70243227 | AM6: 1.0843165 | AN6: 4.4156085 | AS6: -9277837.4 | AT6: 1.6404496e+08 | AU6: 0 | AV6: 8568899.6 | AW6: 2.0361631e+08 | AX6: 35338995 | AY6: -0.2968294 | AZ6: -0.073877
B7: 5711.T | C7: Mitsubishi Materials Corp | D7: Diversified Mining | E7: Japan | F7: =AS7/AT7 -> 0.043106223 | G7: =AU7/AV7 -> 28.205249 | H7: =AX7 -> 3.5156424e+09 | I7: =(AY7/AZ7)-1 -> 4.7127466 | J7: =AV7/AW7 -> 0.012303705 | K7: =IFERROR(_xlfn.RANK.EQ(F7,F$3:F$64),"N/A") -> 25 | L7: =IFERROR(_xlfn.RANK.EQ(G7,G$3:G$64),"N/A") -> 1 | M7: =IFERROR(_xlfn.RANK.EQ(H7,H$3:H$64),"N/A") -> 17 | N7: =IFERROR(_xlfn.RANK.EQ(I7,I$3:I$64),"N/A") -> 3 | O7: =IFERROR(_xlfn.RANK.EQ(J7,J$3:J$64),"N/A") -> 31 | P7: =IFERROR(ABS(K$3-K7),"N/A") -> 23 | Q7: =IFERROR(ABS(L$3-L7),"N/A") -> 26 | R7: =IFERROR(ABS(M$3-M7),"N/A") -> 6 | S7: =IFERROR(ABS(N$3-N7),"N/A") -> 42 | T7: =IFERROR(ABS(O$3-O7),"N/A") -> 29 | U7: =SUM(P7:T7) -> 126 | V7: =_xlfn.RANK.EQ(U7,$U$4:$U$64,1) -> 30 | W7: =IF(Y7="Not suitable","-",V7) -> 30 | Y7: =IF(OR(Z7="Y",AA7="Y"),"Not suitable","") | Z7: =IF(OR(N7="N/A",O7="N/A"),"Y","") | AE7: 6 | AF7: =_xlfn.XLOOKUP(AE7,$W$4:$W$64,$U$4:$U$64,"N/A",0,1) -> 49 | AG7: =_xlfn.XLOOKUP(AE7,$W$4:$W$64,$B$4:$B$64,"N/A",0,1) -> BHP.AX | AH7: =_xlfn.XLOOKUP(AE7,$W$4:$W$64,$C$4:$C$64,"N/A",0,1) -> BHP Group Ltd | AI7: =_xlfn.XLOOKUP(AE7,$W$4:$W$64,$E$4:$E$64,"N/A",0,1) -> Australia | AJ7: 19.805163 | AK7: 3.5871445 | AL7: 2.6427476 | AM7: 2.9260532 | AN7: 5.2801592 | AS7: 2.8811569e+08 | AT7: 6.6838537e+09 | AU7: 6.3562764e+09 | AV7: 2.2535793e+08 | AW7: 1.8316266e+10 | AX7: 3.5156424e+09 | AY7: 2.8906603 | AZ7: 0.50600185
B8: GLEN.L | C8: Glencore PLC | D8: Diversified Mining | E8: Switzerland | F8: =AS8/AT8 -> 0.073657641 | G8: =AU8/AV8 -> 5.9518183 | H8: =AX8 -> 9.0491119e+10 | I8: =(AY8/AZ8)-1 -> -0.21937301 | J8: =AV8/AW8 -> 0.024868131 | K8: =IFERROR(_xlfn.RANK.EQ(F8,F$3:F$64),"N/A") -> 20 | L8: =IFERROR(_xlfn.RANK.EQ(G8,G$3:G$64),"N/A") -> 5 | M8: =IFERROR(_xlfn.RANK.EQ(H8,H$3:H$64),"N/A") -> 4 | N8: =IFERROR(_xlfn.RANK.EQ(I8,I$3:I$64),"N/A") -> 29 | O8: =IFERROR(_xlfn.RANK.EQ(J8,J$3:J$64),"N/A") -> 30 | P8: =IFERROR(ABS(K$3-K8),"N/A") -> 18 | Q8: =IFERROR(ABS(L$3-L8),"N/A") -> 22 | R8: =IFERROR(ABS(M$3-M8),"N/A") -> 7 | S8: =IFERROR(ABS(N$3-N8),"N/A") -> 16 | T8: =IFERROR(ABS(O$3-O8),"N/A") -> 28 | U8: =SUM(P8:T8) -> 91 | V8: =_xlfn.RANK.EQ(U8,$U$4:$U$64,1) -> 24 | W8: =IF(Y8="Not suitable","-",V8) -> 24 | Y8: =IF(OR(Z8="Y",AA8="Y"),"Not suitable","") | Z8: =IF(OR(N8="N/A",O8="N/A"),"Y","") | AE8: 7 | AF8: 49 | AG8: GMEXICOB.MX | AH8: Grupo Mexico SAB de CV | AI8: Mexico | AJ8: 11.199677 | AK8: 2.0000184 | AL8: 2.6456077 | AM8: 3.0065953 | AN8: 6.0797373 | AS8: 4713660300 | AT8: 63994179400 | AU8: 47343651630 | AV8: 7954485310 | AW8: 319866638470 | AX8: 9.0491119e+10 | AY8: 0.61596778 | AZ8: 0.78906799
B9: BCM.V | C9: Bear Creek Mining Corp | D9: Diversified Mining | E9: Canada | F9: =AS9/AT9 -> -0.19798537 | G9: =AU9/AV9 -> -1.1148915 | H9: =AX9 -> 46322122 | I9: =(AY9/AZ9)-1 -> 2.0574454 | J9: =AV9/AW9 -> -0.3028769 | K9: =IFERROR(_xlfn.RANK.EQ(F9,F$3:F$64),"N/A") -> 47 | L9: =IFERROR(_xlfn.RANK.EQ(G9,G$3:G$64),"N/A") -> 50 | M9: =IFERROR(_xlfn.RANK.EQ(H9,H$3:H$64),"N/A") -> 53 | N9: =IFERROR(_xlfn.RANK.EQ(I9,I$3:I$64),"N/A") -> 6 | O9: =IFERROR(_xlfn.RANK.EQ(J9,J$3:J$64),"N/A") -> 42 | P9: =IFERROR(ABS(K$3-K9),"N/A") -> 45 | Q9: =IFERROR(ABS(L$3-L9),"N/A") -> 23 | R9: =IFERROR(ABS(M$3-M9),"N/A") -> 42 | S9: =IFERROR(ABS(N$3-N9),"N/A") -> 39 | T9: =IFERROR(ABS(O$3-O9),"N/A") -> 40 | U9: =SUM(P9:T9) -> 189 | V9: =_xlfn.RANK.EQ(U9,$U$4:$U$64,1) -> 58 | W9: =IF(Y9="Not suitable","-",V9) -> 58 | Y9: =IF(OR(Z9="Y",AA9="Y"),"Not suitable","") | Z9: =IF(OR(N9="N/A",O9="N/A"),"Y","") | AE9: Median | AJ9: =MEDIAN(AJ3:AJ8) -> 13.801495 | AK9: =MEDIAN(AK3:AK8) -> 2.6055978 | AL9: =MEDIAN(AL3:AL8) -> 2.6441777 | AM9: =MEDIAN(AM3:AM8) -> 2.9663243 | AN9: =MEDIAN(AN3:AN8) -> 5.6799482 | AS9: -33176231 | AT9: 1.675691e+08 | AU9: 30252414 | AV9: -27134849 | AW9: 89590356 | AX9: 46322122 | AY9: -0.3191013 | AZ9: -0.1043686
B10: IMA.AX | C10: Image Resources NL | D10: Diversified Mining | E10: Australia | F10: =AS10/AT10 -> 0.13053693 | G10: =AU10/AV10 -> 0.0081939938 | H10: =AX10 -> 63147962 | I10: =(AY10/AZ10)-1 -> -1 | J10: =AV10/AW10 -> 0.14015635 | K10: =IFERROR(_xlfn.RANK.EQ(F10,F$3:F$64),"N/A") -> 12 | L10: =IFERROR(_xlfn.RANK.EQ(G10,G$3:G$64),"N/A") -> 30 | M10: =IFERROR(_xlfn.RANK.EQ(H10,H$3:H$64),"N/A") -> 49 | N10: =IFERROR(_xlfn.RANK.EQ(I10,I$3:I$64),"N/A") -> 47 | O10: =IFERROR(_xlfn.RANK.EQ(J10,J$3:J$64),"N/A") -> 21 | P10: =IFERROR(ABS(K$3-K10),"N/A") -> 10 | Q10: =IFERROR(ABS(L$3-L10),"N/A") -> 3 | R10: =IFERROR(ABS(M$3-M10),"N/A") -> 38 | S10: =IFERROR(ABS(N$3-N10),"N/A") -> 2 | T10: =IFERROR(ABS(O$3-O10),"N/A") -> 19 | U10: =SUM(P10:T10) -> 72 | V10: =_xlfn.RANK.EQ(U10,$U$4:$U$64,1) -> 15 | W10: =IF(Y10="Not suitable","-",V10) -> 15 | Y10: =IF(OR(Z10="Y",AA10="Y"),"Not suitable","") | Z10: =IF(OR(N10="N/A",O10="N/A"),"Y","") | AE10: Benchmark Data | AJ10: Price / Share | AS10: 15168000 | AT10: 116197000 | AU10: 197000 | AV10: 24042000 | AW10: 171537000 | AX10: 63147962 | AZ10: 0.058
B11: S.TO | C11: Sherritt International Corp | D11: Diversified Mining | E11: Canada | F11: =AS11/AT11 -> -0.1047914 | G11: =AU11/AV11 -> -8.9122807 | H11: =AX11 -> 1.2579232e+08 | I11: =(AY11/AZ11)-1 -> 0.33359291 | J11: =AV11/AW11 -> -0.17868339 | K11: =IFERROR(_xlfn.RANK.EQ(F11,F$3:F$64),"N/A") -> 41 | L11: =IFERROR(_xlfn.RANK.EQ(G11,G$3:G$64),"N/A") -> 60 | M11: =IFERROR(_xlfn.RANK.EQ(H11,H$3:H$64),"N/A") -> 41 | N11: =IFERROR(_xlfn.RANK.EQ(I11,I$3:I$64),"N/A") -> 12 | O11: =IFERROR(_xlfn.RANK.EQ(J11,J$3:J$64),"N/A") -> 37 | P11: =IFERROR(ABS(K$3-K11),"N/A") -> 39 | Q11: =IFERROR(ABS(L$3-L11),"N/A") -> 33 | R11: =IFERROR(ABS(M$3-M11),"N/A") -> 30 | S11: =IFERROR(ABS(N$3-N11),"N/A") -> 33 | T11: =IFERROR(ABS(O$3-O11),"N/A") -> 35 | U11: =SUM(P11:T11) -> 170 | V11: =_xlfn.RANK.EQ(U11,$U$4:$U$64,1) -> 54 | W11: =IF(Y11="Not suitable","-",V11) -> 54 | Y11: =IF(OR(Z11="Y",AA11="Y"),"Not suitable","") | Z11: =IF(OR(N11="N/A",O11="N/A"),"Y","") | AE11: Benchmark | AF11: Multiplier | AG11: # Shares | AH11: -Debt + Cash | AJ11: P / E | AK11: P / B | AL11: Price / Sales | AM11: EV / Sales | AN11: EV / EBITDA | AS11: -71287315 | AT11: 6.8027833e+08 | AU11: 3.9424214e+08 | AV11: -44235830 | AW11: 2.4756544e+08 | AX11: 1.2579232e+08 | AY11: -0.16810808 | AZ11: -0.12605652
B12: SOSIL.NGM | C12: Sotkamo Silver AB | D12: Diversified Mining | E12: Sweden | F12: =AS12/AT12 -> 0.091798853 | G12: =AU12/AV12 -> 4.161919 | H12: =AX12 -> 32538544 | I12: =(AY12/AZ12)-1 -> 1.5725809 | J12: =AV12/AW12 -> 0.16197183 | K12: =IFERROR(_xlfn.RANK.EQ(F12,F$3:F$64),"N/A") -> 15 | L12: =IFERROR(_xlfn.RANK.EQ(G12,G$3:G$64),"N/A") -> 8 | M12: =IFERROR(_xlfn.RANK.EQ(H12,H$3:H$64),"N/A") -> 57 | N12: =IFERROR(_xlfn.RANK.EQ(I12,I$3:I$64),"N/A") -> 8 | O12: =IFERROR(_xlfn.RANK.EQ(J12,J$3:J$64),"N/A") -> 19 | P12: =IFERROR(ABS(K$3-K12),"N/A") -> 13 | Q12: =IFERROR(ABS(L$3-L12),"N/A") -> 19 | R12: =IFERROR(ABS(M$3-M12),"N/A") -> 46 | S12: =IFERROR(ABS(N$3-N12),"N/A") -> 37 | T12: =IFERROR(ABS(O$3-O12),"N/A") -> 17 | U12: =SUM(P12:T12) -> 132 | V12: =_xlfn.RANK.EQ(U12,$U$4:$U$64,1) -> 33 | W12: =IF(Y12="Not suitable","-",V12) -> 33 | Y12: =IF(OR(Z12="Y",AA12="Y"),"Not suitable","") | Z12: =IF(OR(N12="N/A",O12="N/A"),"Y","") | AE12: =C3 -> Pilbara Minerals Ltd | AF12: 1000000 | AG12: =OP!C22 -> 3009468000 | AH12: =-'Fin. Data'!B58*SARD!AF12+'Fin. Data'!B39*SARD!AF12 -> 2538700000 | AJ12: =AJ9*'Fin. Data'!B23*AF$12/AG$12 -> 10.965644 | AK12: =AK9*'Fin. Data'!B64*AF$12/AG$12 -> 2.9350624 | AL12: =AL9*'Fin. Data'!B5*AF$12/AG$12 -> 3.5707102 | AM12: =(AM9*'Fin. Data'!B5*$AF12+$AH12)/$AG12 -> 4.8493095 | AN12: =(AN9*'Fin. Data'!B19*$AF12+$AH12)/$AG12 -> 6.6919321 | AS12: 3967547 | AT12: 43220007 | AU12: 40492318 | AV12: 9729242.2 | AW12: 60067495 | AX12: 32538544 | AY12: 0.021951647 | AZ12: 0.0085329278
B13: 29M.AX | C13: 29Metals Ltd | D13: Diversified Mining | E13: Australia | F13: =AS13/AT13 -> -1.042901 | G13: =AU13/AV13 -> -0.76254834 | H13: =AX13 -> 2.4896694e+08 | I13: =(AY13/AZ13)-1 -> -0.76524996 | J13: =AV13/AW13 -> -0.79116305 | K13: =IFERROR(_xlfn.RANK.EQ(F13,F$3:F$64),"N/A") -> 59 | L13: =IFERROR(_xlfn.RANK.EQ(G13,G$3:G$64),"N/A") -> 47 | M13: =IFERROR(_xlfn.RANK.EQ(H13,H$3:H$64),"N/A") -> 33 | N13: =IFERROR(_xlfn.RANK.EQ(I13,I$3:I$64),"N/A") -> 43 | O13: =IFERROR(_xlfn.RANK.EQ(J13,J$3:J$64),"N/A") -> 47 | P13: =IFERROR(ABS(K$3-K13),"N/A") -> 57 | Q13: =IFERROR(ABS(L$3-L13),"N/A") -> 20 | R13: =IFERROR(ABS(M$3-M13),"N/A") -> 22 | S13: =IFERROR(ABS(N$3-N13),"N/A") -> 2 | T13: =IFERROR(ABS(O$3-O13),"N/A") -> 45 | U13: =SUM(P13:T13) -> 146 | V13: =_xlfn.RANK.EQ(U13,$U$4:$U$64,1) -> 40 | W13: =IF(Y13="Not suitable","-",V13) -> 40 | Y13: =IF(OR(Z13="Y",AA13="Y"),"Not suitable","") | Z13: =IF(OR(N13="N/A",O13="N/A"),"Y","") | AE13: By Consolidated Average | AJ13: =AVERAGE(AJ12:AL12) -> 5.8238056 | AM13: =AVERAGE(AM12:AN12) -> 5.7706208 | AS13: -440463000 | AT13: 422344000 | AU13: 271333000 | AV13: -355824000 | AW13: 449748000 | AX13: 2.4896694e+08 | AY13: -0.11345 | AZ13: -0.48328
B14: USA.TO | C14: Americas Gold and Silver Corporation | D14: Diversified Mining | E14: Canada | F14: =AS14/AT14 -> -0.55630517 | G14: =AU14/AV14 -> -0.43411831 | H14: =AX14 -> 72364913 | I14: =(AY14/AZ14)-1 -> -0.29834755 | J14: =AV14/AW14 -> -0.41956808 | K14: =IFERROR(_xlfn.RANK.EQ(F14,F$3:F$64),"N/A") -> 54 | L14: =IFERROR(_xlfn.RANK.EQ(G14,G$3:G$64),"N/A") -> 46 | M14: =IFERROR(_xlfn.RANK.EQ(H14,H$3:H$64),"N/A") -> 47 | N14: =IFERROR(_xlfn.RANK.EQ(I14,I$3:I$64),"N/A") -> 33 | O14: =IFERROR(_xlfn.RANK.EQ(J14,J$3:J$64),"N/A") -> 44 | P14: =IFERROR(ABS(K$3-K14),"N/A") -> 52 | Q14: =IFERROR(ABS(L$3-L14),"N/A") -> 19 | R14: =IFERROR(ABS(M$3-M14),"N/A") -> 36 | S14: =IFERROR(ABS(N$3-N14),"N/A") -> 12 | T14: =IFERROR(ABS(O$3-O14),"N/A") -> 42 | U14: =SUM(P14:T14) -> 161 | V14: =_xlfn.RANK.EQ(U14,$U$4:$U$64,1) -> 49 | W14: =IF(Y14="Not suitable","-",V14) -> 49 | Y14: =IF(OR(Z14="Y",AA14="Y"),"Not suitable","") | Z14: =IF(OR(N14="N/A",O14="N/A"),"Y","") | AE14: Upside | AJ14: =AJ13/OP!C21-1 -> 0.52057587 | AM14: =AM13/OP!C21-1 -> 0.50668951 | AS14: -66324575 | AT14: 1.1922337e+08 | AU14: 22728573 | AV14: -52355713 | AW14: 1.2478478e+08 | AX14: 72364913 | AY14: -0.23335445 | AZ14: -0.3325784
B15: SMT.TO | C15: Sierra Metals Inc | D15: Diversified Mining | E15: Canada | F15: =AS15/AT15 -> -1.0819957 | G15: =AU15/AV15 -> -1.2420035 | H15: =AX15 -> 1.9204638e+08 | I15: =(AY15/AZ15)-1 -> -1.2972789 | J15: =AV15/AW15 -> -0.39396936 | K15: =IFERROR(_xlfn.RANK.EQ(F15,F$3:F$64),"N/A") -> 60 | L15: =IFERROR(_xlfn.RANK.EQ(G15,G$3:G$64),"N/A") -> 53 | M15: =IFERROR(_xlfn.RANK.EQ(H15,H$3:H$64),"N/A") -> 36 | N15: =IFERROR(_xlfn.RANK.EQ(I15,I$3:I$64),"N/A") -> 58 | O15: =IFERROR(_xlfn.RANK.EQ(J15,J$3:J$64),"N/A") -> 43 | P15: =IFERROR(ABS(K$3-K15),"N/A") -> 58 | Q15: =IFERROR(ABS(L$3-L15),"N/A") -> 26 | R15: =IFERROR(ABS(M$3-M15),"N/A") -> 25 | S15: =IFERROR(ABS(N$3-N15),"N/A") -> 13 | T15: =IFERROR(ABS(O$3-O15),"N/A") -> 41 | U15: =SUM(P15:T15) -> 163 | V15: =_xlfn.RANK.EQ(U15,$U$4:$U$64,1) -> 50 | W15: =IF(Y15="Not suitable","-",V15) -> 50 | Y15: =IF(OR(Z15="Y",AA15="Y"),"Not suitable","") | Z15: =IF(OR(N15="N/A",O15="N/A"),"Y","") | AS15: -1.2961378e+08 | AT15: 1.197914e+08 | AU15: 1.3798013e+08 | AV15: -1.110948e+08 | AW15: 2.8198843e+08 | AX15: 1.9204638e+08 | AY15: 0.0767815 | AZ15: -0.258281
B16: LUCA.V | C16: Luca Mining Corp | D16: Diversified Mining | E16: Canada | F16: =AS16/AT16 -> -0.40923034 | G16: =AU16/AV16 -> -4.5051262 | H16: =AX16 -> 45950630 | I16: =(AY16/AZ16)-1 -> 4.7391051 | J16: =AV16/AW16 -> -0.1960377 | K16: =IFERROR(_xlfn.RANK.EQ(F16,F$3:F$64),"N/A") -> 52 | L16: =IFERROR(_xlfn.RANK.EQ(G16,G$3:G$64),"N/A") -> 59 | M16: =IFERROR(_xlfn.RANK.EQ(H16,H$3:H$64),"N/A") -> 54 | N16: =IFERROR(_xlfn.RANK.EQ(I16,I$3:I$64),"N/A") -> 2 | O16: =IFERROR(_xlfn.RANK.EQ(J16,J$3:J$64),"N/A") -> 39 | P16: =IFERROR(ABS(K$3-K16),"N/A") -> 50 | Q16: =IFERROR(ABS(L$3-L16),"N/A") -> 32 | R16: =IFERROR(ABS(M$3-M16),"N/A") -> 43 | S16: =IFERROR(ABS(N$3-N16),"N/A") -> 43 | T16: =IFERROR(ABS(O$3-O16),"N/A") -> 37 | U16: =SUM(P16:T16) -> 205 | V16: =_xlfn.RANK.EQ(U16,$U$4:$U$64,1) -> 61 | W16: =IF(Y16="Not suitable","-",V16) -> 61 | Y16: =IF(OR(Z16="Y",AA16="Y"),"Not suitable","") | Z16: =IF(OR(N16="N/A",O16="N/A"),"Y","") | AS16: -12574007 | AT16: 30725990 | AU16: 56647490 | AV16: -12574007 | AW16: 64140762 | AX16: 45950630 | AY16: -0.12416357 | AZ16: -0.021634657
B17: MND.TO | C17: Mandalay Resources Corp | D17: Diversified Mining | E17: Canada | F17: =AS17/AT17 -> 0.039917332 | G17: =AU17/AV17 -> 1.2211354 | H17: =AX17 -> 1.6077143e+08 | I17: =(AY17/AZ17)-1 -> 1.7688616 | J17: =AV17/AW17 -> 0.11147199 | K17: =IFERROR(_xlfn.RANK.EQ(F17,F$3:F$64),"N/A") -> 26 | L17: =IFERROR(_xlfn.RANK.EQ(G17,G$3:G$64),"N/A") -> 18 | M17: =IFERROR(_xlfn.RANK.EQ(H17,H$3:H$64),"N/A") -> 37 | N17: =IFERROR(_xlfn.RANK.EQ(I17,I$3:I$64),"N/A") -> 7 | O17: =IFERROR(_xlfn.RANK.EQ(J17,J$3:J$64),"N/A") -> 25 | P17: =IFERROR(ABS(K$3-K17),"N/A") -> 24 | Q17: =IFERROR(ABS(L$3-L17),"N/A") -> 9 | R17: =IFERROR(ABS(M$3-M17),"N/A") -> 26 | S17: =IFERROR(ABS(N$3-N17),"N/A") -> 38 | T17: =IFERROR(ABS(O$3-O17),"N/A") -> 23 | U17: =SUM(P17:T17) -> 120 | V17: =_xlfn.RANK.EQ(U17,$U$4:$U$64,1) -> 27 | W17: =IF(Y17="Not suitable","-",V17) -> 27 | Y17: =IF(OR(Z17="Y",AA17="Y"),"Not suitable","") | Z17: =IF(OR(N17="N/A",O17="N/A"),"Y","") | AS17: 11543328 | AT17: 2.8918086e+08 | AU17: 34649074 | AV17: 28374473 | AW17: 2.5454353e+08 | AX17: 1.6077143e+08 | AY17: 0.3423642 | AZ17: 0.123648
B18: GSVR.V | C18: Guanajuato Silver Company Ltd | D18: Diversified Mining | E18: Canada | F18: =AS18/AT18 -> -0.82344251 | G18: =AU18/AV18 -> -0.88894473 | H18: =AX18 -> 62032415 | I18: =(AY18/AZ18)-1 -> 0.15617613 | J18: =AV18/AW18 -> -0.62312542 | K18: =IFERROR(_xlfn.RANK.EQ(F18,F$3:F$64),"N/A") -> 57 | L18: =IFERROR(_xlfn.RANK.EQ(G18,G$3:G$64),"N/A") -> 49 | M18: =IFERROR(_xlfn.RANK.EQ(H18,H$3:H$64),"N/A") -> 50 | N18: =IFERROR(_xlfn.RANK.EQ(I18,I$3:I$64),"N/A") -> 13 | O18: =IFERROR(_xlfn.RANK.EQ(J18,J$3:J$64),"N/A") -> 46 | P18: =IFERROR(ABS(K$3-K18),"N/A") -> 55 | Q18: =IFERROR(ABS(L$3-L18),"N/A") -> 22 | R18: =IFERROR(ABS(M$3-M18),"N/A") -> 39 | S18: =IFERROR(ABS(N$3-N18),"N/A") -> 32 | T18: =IFERROR(ABS(O$3-O18),"N/A") -> 44 | U18: =SUM(P18:T18) -> 192 | V18: =_xlfn.RANK.EQ(U18,$U$4:$U$64,1) -> 59 | W18: =IF(Y18="Not suitable","-",V18) -> 59 | Y18: =IF(OR(Z18="Y",AA18="Y"),"Not suitable","") | Z18: =IF(OR(N18="N/A",O18="N/A"),"Y","") | AS18: -39294804 | AT18: 47720155 | AU18: 29985028 | AV18: -33731038 | AW18: 54132020 | AX18: 62032415 | AY18: -0.1194384 | AZ18: -0.10330468
B19: AMI.AX | C19: Aurelia Metals Ltd | D19: Diversified Mining | E19: Australia | F19: =AS19/AT19 -> -0.16854999 | G19: =AU19/AV19 -> -0.18348199 | H19: =AX19 -> 2.3656744e+08 | I19: =(AY19/AZ19)-1 -> -1.0032833 | J19: =AV19/AW19 -> -0.18735814 | K19: =IFERROR(_xlfn.RANK.EQ(F19,F$3:F$64),"N/A") -> 46 | L19: =IFERROR(_xlfn.RANK.EQ(G19,G$3:G$64),"N/A") -> 42 | M19: =IFERROR(_xlfn.RANK.EQ(H19,H$3:H$64),"N/A") -> 34 | N19: =IFERROR(_xlfn.RANK.EQ(I19,I$3:I$64),"N/A") -> 56 | O19: =IFERROR(_xlfn.RANK.EQ(J19,J$3:J$64),"N/A") -> 38 | P19: =IFERROR(ABS(K$3-K19),"N/A") -> 44 | Q19: =IFERROR(ABS(L$3-L19),"N/A") -> 15 | R19: =IFERROR(ABS(M$3-M19),"N/A") -> 23 | S19: =IFERROR(ABS(N$3-N19),"N/A") -> 11 | T19: =IFERROR(ABS(O$3-O19),"N/A") -> 36 | U19: =SUM(P19:T19) -> 129 | V19: =_xlfn.RANK.EQ(U19,$U$4:$U$64,1) -> 31 | W19: =IF(Y19="Not suitable","-",V19) -> 31 | Y19: =IF(OR(Z19="Y",AA19="Y"),"Not suitable","") | Z19: =IF(OR(N19="N/A",O19="N/A"),"Y","") | AS19: -52221000 | AT19: 309825000 | AU19: 12692000 | AV19: -69173000 | AW19: 369202000 | AX19: 2.3656744e+08 | AY19: 7e-05 | AZ19: -0.02132
B20: VDAN.NS | C20: Vedanta Ltd | D20: Diversified Mining | E20: India | F20: =AS20/AT20 -> 0.36795779 | G20: =AU20/AV20 -> 2.7517449 | H20: =AX20 -> 1.8998025e+10 | I20: =(AY20/AZ20)-1 -> -0.48843879 | J20: =AV20/AW20 -> 0.16436989 | K20: =IFERROR(_xlfn.RANK.EQ(F20,F$3:F$64),"N/A") -> 4 | L20: =IFERROR(_xlfn.RANK.EQ(G20,G$3:G$64),"N/A") -> 10 | M20: =IFERROR(_xlfn.RANK.EQ(H20,H$3:H$64),"N/A") -> 9 | N20: =IFERROR(_xlfn.RANK.EQ(I20,I$3:I$64),"N/A") -> 37 | O20: =IFERROR(_xlfn.RANK.EQ(J20,J$3:J$64),"N/A") -> 18 | P20: =IFERROR(ABS(K$3-K20),"N/A") -> 2 | Q20: =IFERROR(ABS(L$3-L20),"N/A") -> 17 | R20: =IFERROR(ABS(M$3-M20),"N/A") -> 2 | S20: =IFERROR(ABS(N$3-N20),"N/A") -> 8 | T20: =IFERROR(ABS(O$3-O20),"N/A") -> 16 | U20: =SUM(P20:T20) -> 45 | V20: =_xlfn.RANK.EQ(U20,$U$4:$U$64,1) -> 5 | W20: =IF(Y20="Not suitable","-",V20) -> 5 | Y20: =IF(OR(Z20="Y",AA20="Y"),"Not suitable","") | Z20: =IF(OR(N20="N/A",O20="N/A"),"Y","") | AS20: 2.6411125e+09 | AT20: 7.1777594e+09 | AU20: 1.2130983e+10 | AV20: 4.4084694e+09 | AW20: 2.6820419e+10 | AX20: 1.8998025e+10 | AY20: 0.27362083 | AZ20: 0.53487409
B21: PEOLES.MX | C21: Industrias Penoles SAB de CV | D21: Diversified Mining | E21: Mexico | F21: =AS21/AT21 -> 0.079909452 | G21: =AU21/AV21 -> 7.9476189 | H21: =AX21 -> 7.7914558e+09 | I21: =(AY21/AZ21)-1 -> -0.30565796 | J21: =AV21/AW21 -> 0.06870603 | K21: =IFERROR(_xlfn.RANK.EQ(F21,F$3:F$64),"N/A") -> 19 | L21: =IFERROR(_xlfn.RANK.EQ(G21,G$3:G$64),"N/A") -> 4 | M21: =IFERROR(_xlfn.RANK.EQ(H21,H$3:H$64),"N/A") -> 14 | N21: =IFERROR(_xlfn.RANK.EQ(I21,I$3:I$64),"N/A") -> 34 | O21: =IFERROR(_xlfn.RANK.EQ(J21,J$3:J$64),"N/A") -> 26 | P21: =IFERROR(ABS(K$3-K21),"N/A") -> 17 | Q21: =IFERROR(ABS(L$3-L21),"N/A") -> 23 | R21: =IFERROR(ABS(M$3-M21),"N/A") -> 3 | S21: =IFERROR(ABS(N$3-N21),"N/A") -> 11 | T21: =IFERROR(ABS(O$3-O21),"N/A") -> 24 | U21: =SUM(P21:T21) -> 78 | V21: =_xlfn.RANK.EQ(U21,$U$4:$U$64,1) -> 16 | W21: =IF(Y21="Not suitable","-",V21) -> 16 | Y21: =IF(OR(Z21="Y",AA21="Y"),"Not suitable","") | Z21: =IF(OR(N21="N/A",O21="N/A"),"Y","") | AS21: 4.7787247e+08 | AT21: 5.9801746e+09 | AU21: 4.4268626e+09 | AV21: 5.570049e+08 | AW21: 8.1070744e+09 | AX21: 7.7914558e+09 | AY21: 0.2309115 | AZ21: 0.3325616
B22: DR0G.DE | C22: Deutsche Rohstoff AG | D22: Diversified Mining | E22: Germany | F22: =AS22/AT22 -> 0.51322015 | G22: =AU22/AV22 -> 1.1338421 | H22: =AX22 -> 2.6475409e+08 | I22: =(AY22/AZ22)-1 -> 0.012673817 | J22: =AV22/AW22 -> 0.58583497 | K22: =IFERROR(_xlfn.RANK.EQ(F22,F$3:F$64),"N/A") -> 3 | L22: =IFERROR(_xlfn.RANK.EQ(G22,G$3:G$64),"N/A") -> 19 | M22: =IFERROR(_xlfn.RANK.EQ(H22,H$3:H$64),"N/A") -> 32 | N22: =IFERROR(_xlfn.RANK.EQ(I22,I$3:I$64),"N/A") -> 21 | O22: =IFERROR(_xlfn.RANK.EQ(J22,J$3:J$64),"N/A") -> 3 | P22: =IFERROR(ABS(K$3-K22),"N/A") -> 1 | Q22: =IFERROR(ABS(L$3-L22),"N/A") -> 8 | R22: =IFERROR(ABS(M$3-M22),"N/A") -> 21 | S22: =IFERROR(ABS(N$3-N22),"N/A") -> 24 | T22: =IFERROR(ABS(O$3-O22),"N/A") -> 1 | U22: =SUM(P22:T22) -> 55 | V22: =_xlfn.RANK.EQ(U22,$U$4:$U$64,1) -> 8 | W22: =IF(Y22="Not suitable","-",V22) -> 8 | Y22: =IF(OR(Z22="Y",AA22="Y"),"Not suitable","") | Z22: =IF(OR(N22="N/A",O22="N/A"),"Y","") | AS22: 1.0396609e+08 | AT22: 2.0257601e+08 | AU22: 1.7262139e+08 | AV22: 1.5224465e+08 | AW22: 2.5987634e+08 | AX22: 2.6475409e+08 | AY22: 21.884575 | AZ22: 21.610685
B23: A1M.AX | C23: AIC Mines Ltd | D23: Diversified Mining | E23: Australia | F23: =AS23/AT23 -> -0.037688768 | G23: =AU23/AV23 -> -0.39186384 | H23: =AX23 -> 1.433659e+08 | I23: =(AY23/AZ23)-1 -> -1.7399001 | J23: =AV23/AW23 -> -0.057523779 | K23: =IFERROR(_xlfn.RANK.EQ(F23,F$3:F$64),"N/A") -> 33 | L23: =IFERROR(_xlfn.RANK.EQ(G23,G$3:G$64),"N/A") -> 44 | M23: =IFERROR(_xlfn.RANK.EQ(H23,H$3:H$64),"N/A") -> 39 | N23: =IFERROR(_xlfn.RANK.EQ(I23,I$3:I$64),"N/A") -> 60 | O23: =IFERROR(_xlfn.RANK.EQ(J23,J$3:J$64),"N/A") -> 32 | P23: =IFERROR(ABS(K$3-K23),"N/A") -> 31 | Q23: =IFERROR(ABS(L$3-L23),"N/A") -> 17 | R23: =IFERROR(ABS(M$3-M23),"N/A") -> 28 | S23: =IFERROR(ABS(N$3-N23),"N/A") -> 15 | T23: =IFERROR(ABS(O$3-O23),"N/A") -> 30 | U23: =SUM(P23:T23) -> 121 | V23: =_xlfn.RANK.EQ(U23,$U$4:$U$64,1) -> 28 | W23: =IF(Y23="Not suitable","-",V23) -> 28 | Y23: =IF(OR(Z23="Y",AA23="Y"),"Not suitable","") | Z23: =IF(OR(N23="N/A",O23="N/A"),"Y","") | AS23: -5815000 | AT23: 154290000 | AU23: 2832000 | AV23: -7227000 | AW23: 125635000 | AX23: 1.433659e+08 | AY23: 0.0163 | AZ23: -0.02203
B24: AAL.L | C24: Anglo American PLC | D24: Diversified Mining | E24: United Kingdom | F24: =AS24/AT24 -> 0.053637706 | G24: =AU24/AV24 -> 4.4823748 | H24: =AX24 -> 4.5674651e+10 | I24: =(AY24/AZ24)-1 -> -0.072794502 | J24: =AV24/AW24 -> 0.12309148 | K24: =IFERROR(_xlfn.RANK.EQ(F24,F$3:F$64),"N/A") -> 24 | L24: =IFERROR(_xlfn.RANK.EQ(G24,G$3:G$64),"N/A") -> 7 | M24: =IFERROR(_xlfn.RANK.EQ(H24,H$3:H$64),"N/A") -> 6 | N24: =IFERROR(_xlfn.RANK.EQ(I24,I$3:I$64),"N/A") -> 25 | O24: =IFERROR(_xlfn.RANK.EQ(J24,J$3:J$64),"N/A") -> 23 | P24: =IFERROR(ABS(K$3-K24),"N/A") -> 22 | Q24: =IFERROR(ABS(L$3-L24),"N/A") -> 20 | R24: =IFERROR(ABS(M$3-M24),"N/A") -> 5 | S24: =IFERROR(ABS(N$3-N24),"N/A") -> 20 | T24: =IFERROR(ABS(O$3-O24),"N/A") -> 21 | U24: =SUM(P24:T24) -> 88 | V24: =_xlfn.RANK.EQ(U24,$U$4:$U$64,1) -> 21 | W24: =IF(Y24="Not suitable","-",V24) -> 21 | Y24: =IF(OR(Z24="Y",AA24="Y"),"Not suitable","") | Z24: =IF(OR(N24="N/A",O24="N/A"),"Y","") | AS24: 1973569920 | AT24: 36794450510 | AU24: 24834088160 | AV24: 5540386390 | AW24: 45010316360 | AX24: 4.5674651e+10 | AY24: 3.2940196 | AZ24: 3.5526316
B25: VAST.L | C25: Vast Resources PLC | D25: Diversified Mining | E25: United Kingdom | F25: =AS25/AT25 -> -4.1313409 | G25: =AU25/AV25 -> -1.1269666 | H25: =AX25 -> 5852771.9 | I25: =(AY25/AZ25)-1 -> -1 | J25: =AV25/AW25 -> -2.1870968 | K25: =IFERROR(_xlfn.RANK.EQ(F25,F$3:F$64),"N/A") -> 62 | L25: =IFERROR(_xlfn.RANK.EQ(G25,G$3:G$64),"N/A") -> 52 | M25: =IFERROR(_xlfn.RANK.EQ(H25,H$3:H$64),"N/A") -> 62 | N25: =IFERROR(_xlfn.RANK.EQ(I25,I$3:I$64),"N/A") -> 47 | O25: =IFERROR(_xlfn.RANK.EQ(J25,J$3:J$64),"N/A") -> 50 | P25: =IFERROR(ABS(K$3-K25),"N/A") -> 60 | Q25: =IFERROR(ABS(L$3-L25),"N/A") -> 25 | R25: =IFERROR(ABS(M$3-M25),"N/A") -> 51 | S25: =IFERROR(ABS(N$3-N25),"N/A") -> 2 | T25: =IFERROR(ABS(O$3-O25),"N/A") -> 48 | U25: =SUM(P25:T25) -> 186 | V25: =_xlfn.RANK.EQ(U25,$U$4:$U$64,1) -> 57 | W25: =IF(Y25="Not suitable","-",V25) -> 57 | Y25: =IF(OR(Z25="Y",AA25="Y"),"Not suitable","") | Z25: =IF(OR(N25="N/A",O25="N/A"),"Y","") | AS25: -15901356 | AT25: 3848957.6 | AU25: 13877740 | AV25: -12314243 | AW25: 5630406 | AX25: 5852771.9 | AZ25: -0.12590752
B26: FVI.TO | C26: Fortuna Silver Mines Inc | D26: Diversified Mining | E26: Canada | F26: =AS26/AT26 -> -0.10918284 | G26: =AU26/AV26 -> -2.1181573 | H26: =AX26 -> 1.3659687e+09 | I26: =(AY26/AZ26)-1 -> 0.69984486 | J26: =AV26/AW26 -> -0.16662289 | K26: =IFERROR(_xlfn.RANK.EQ(F26,F$3:F$64),"N/A") -> 43 | L26: =IFERROR(_xlfn.RANK.EQ(G26,G$3:G$64),"N/A") -> 54 | M26: =IFERROR(_xlfn.RANK.EQ(H26,H$3:H$64),"N/A") -> 21 | N26: =IFERROR(_xlfn.RANK.EQ(I26,I$3:I$64),"N/A") -> 10 | O26: =IFERROR(_xlfn.RANK.EQ(J26,J$3:J$64),"N/A") -> 34 | P26: =IFERROR(ABS(K$3-K26),"N/A") -> 41 | Q26: =IFERROR(ABS(L$3-L26),"N/A") -> 27 | R26: =IFERROR(ABS(M$3-M26),"N/A") -> 10 | S26: =IFERROR(ABS(N$3-N26),"N/A") -> 35 | T26: =IFERROR(ABS(O$3-O26),"N/A") -> 32 | U26: =SUM(P26:T26) -> 145 | V26: =_xlfn.RANK.EQ(U26,$U$4:$U$64,1) -> 39 | W26: =IF(Y26="Not suitable","-",V26) -> 39 | Y26: =IF(OR(Z26="Y",AA26="Y"),"Not suitable","") | Z26: =IF(OR(N26="N/A",O26="N/A"),"Y","") | AS26: -1.9948011e+08 | AT26: 1.827028e+09 | AU26: 3.5303191e+08 | AV26: -1.6666935e+08 | AW26: 1.0002789e+09 | AX26: 1.3659687e+09 | AY26: 0.39154383 | AZ26: 0.23034092
B27: S32.AX | C27: South32 Ltd | D27: Diversified Mining | E27: Australia | F27: =AS27/AT27 -> -0.018451365 | G27: =AU27/AV27 -> 8.7929293 | H27: =AX27 -> 1.3361313e+10 | I27: =(AY27/AZ27)-1 -> -0.53175068 | J27: =AV27/AW27 -> 0.026652309 | K27: =IFERROR(_xlfn.RANK.EQ(F27,F$3:F$64),"N/A") -> 31 | L27: =IFERROR(_xlfn.RANK.EQ(G27,G$3:G$64),"N/A") -> 3 | M27: =IFERROR(_xlfn.RANK.EQ(H27,H$3:H$64),"N/A") -> 10 | N27: =IFERROR(_xlfn.RANK.EQ(I27,I$3:I$64),"N/A") -> 38 | O27: =IFERROR(_xlfn.RANK.EQ(J27,J$3:J$64),"N/A") -> 29 | P27: =IFERROR(ABS(K$3-K27),"N/A") -> 29 | Q27: =IFERROR(ABS(L$3-L27),"N/A") -> 24 | R27: =IFERROR(ABS(M$3-M27),"N/A") -> 1 | S27: =IFERROR(ABS(N$3-N27),"N/A") -> 7 | T27: =IFERROR(ABS(O$3-O27),"N/A") -> 27 | U27: =SUM(P27:T27) -> 88 | V27: =_xlfn.RANK.EQ(U27,$U$4:$U$64,1) -> 21 | W27: =IF(Y27="Not suitable","-",V27) -> 21 | Y27: =IF(OR(Z27="Y",AA27="Y"),"Not suitable","") | Z27: =IF(OR(N27="N/A",O27="N/A"),"Y","") | AS27: -259525950 | AT27: 14065406400 | AU27: 2611761150 | AV27: 297029700 | AW27: 11144614350 | AX27: 1.3361313e+10 | AY27: 0.1363822 | AZ27: 0.29125978
B28: ASM.TO | C28: Avino Silver & Gold Mines Ltd | D28: Diversified Mining | E28: Canada | F28: =AS28/AT28 -> 0.031585069 | G28: =AU28/AV28 -> 0.84267952 | H28: =AX28 -> 93867703 | I28: =(AY28/AZ28)-1 -> -0.61143312 | J28: =AV28/AW28 -> 0.17837826 | K28: =IFERROR(_xlfn.RANK.EQ(F28,F$3:F$64),"N/A") -> 27 | L28: =IFERROR(_xlfn.RANK.EQ(G28,G$3:G$64),"N/A") -> 23 | M28: =IFERROR(_xlfn.RANK.EQ(H28,H$3:H$64),"N/A") -> 44 | N28: =IFERROR(_xlfn.RANK.EQ(I28,I$3:I$64),"N/A") -> 40 | O28: =IFERROR(_xlfn.RANK.EQ(J28,J$3:J$64),"N/A") -> 16 | P28: =IFERROR(ABS(K$3-K28),"N/A") -> 25 | Q28: =IFERROR(ABS(L$3-L28),"N/A") -> 4 | R28: =IFERROR(ABS(M$3-M28),"N/A") -> 33 | S28: =IFERROR(ABS(N$3-N28),"N/A") -> 5 | T28: =IFERROR(ABS(O$3-O28),"N/A") -> 14 | U28: =SUM(P28:T28) -> 81 | V28: =_xlfn.RANK.EQ(U28,$U$4:$U$64,1) -> 19 | W28: =IF(Y28="Not suitable","-",V28) -> 19 | Y28: =IF(OR(Z28="Y",AA28="Y"),"Not suitable","") | Z28: =IF(OR(N28="N/A",O28="N/A"),"Y","") | AS28: 4544246.9 | AT28: 1.4387326e+08 | AU28: 9748994.8 | AV28: 11569042 | AW28: 64856795 | AX28: 93867703 | AY28: 0.016648814 | AZ28: 0.042846715
B29: FRES.L | C29: Fresnillo PLC | D29: Diversified Mining | E29: Mexico | F29: =AS29/AT29 -> 0.083644466 | G29: =AU29/AV29 -> 4.5087432 | H29: =AX29 -> 6.6251288e+09 | I29: =(AY29/AZ29)-1 -> 0.065260737 | J29: =AV29/AW29 -> 0.11656151 | K29: =IFERROR(_xlfn.RANK.EQ(F29,F$3:F$64),"N/A") -> 17 | L29: =IFERROR(_xlfn.RANK.EQ(G29,G$3:G$64),"N/A") -> 6 | M29: =IFERROR(_xlfn.RANK.EQ(H29,H$3:H$64),"N/A") -> 15 | N29: =IFERROR(_xlfn.RANK.EQ(I29,I$3:I$64),"N/A") -> 17 | O29: =IFERROR(_xlfn.RANK.EQ(J29,J$3:J$64),"N/A") -> 24 | P29: =IFERROR(ABS(K$3-K29),"N/A") -> 15 | Q29: =IFERROR(ABS(L$3-L29),"N/A") -> 21 | R29: =IFERROR(ABS(M$3-M29),"N/A") -> 4 | S29: =IFERROR(ABS(N$3-N29),"N/A") -> 28 | T29: =IFERROR(ABS(O$3-O29),"N/A") -> 22 | U29: =SUM(P29:T29) -> 90 | V29: =_xlfn.RANK.EQ(U29,$U$4:$U$64,1) -> 23 | W29: =IF(Y29="Not suitable","-",V29) -> 23 | Y29: =IF(OR(Z29="Y",AA29="Y"),"Not suitable","") | Z29: =IF(OR(N29="N/A",O29="N/A"),"Y","") | AS29: 4.5250336e+08 | AT29: 5.4098422e+09 | AU29: 1.876774e+09 | AV29: 4.1625213e+08 | AW29: 3.5710941e+09 | AX29: 6.6251288e+09 | AY29: 0.20869781 | AZ29: 0.19591242
B30: GFM.L | C30: Griffin Mining Ltd | D30: Diversified Mining | E30: United Kingdom | F30: =AS30/AT30 -> 0.03138533 | G30: =AU30/AV30 -> 0.054528 | H30: =AX30 -> 3.5263374e+08 | I30: =(AY30/AZ30)-1 -> -0.23488534 | J30: =AV30/AW30 -> 0.16552433 | K30: =IFERROR(_xlfn.RANK.EQ(F30,F$3:F$64),"N/A") -> 28 | L30: =IFERROR(_xlfn.RANK.EQ(G30,G$3:G$64),"N/A") -> 29 | M30: =IFERROR(_xlfn.RANK.EQ(H30,H$3:H$64),"N/A") -> 31 | N30: =IFERROR(_xlfn.RANK.EQ(I30,I$3:I$64),"N/A") -> 30 | O30: =IFERROR(_xlfn.RANK.EQ(J30,J$3:J$64),"N/A") -> 17 | P30: =IFERROR(ABS(K$3-K30),"N/A") -> 26 | Q30: =IFERROR(ABS(L$3-L30),"N/A") -> 2 | R30: =IFERROR(ABS(M$3-M30),"N/A") -> 20 | S30: =IFERROR(ABS(N$3-N30),"N/A") -> 15 | T30: =IFERROR(ABS(O$3-O30),"N/A") -> 15 | U30: =SUM(P30:T30) -> 78 | V30: =_xlfn.RANK.EQ(U30,$U$4:$U$64,1) -> 16 | W30: =IF(Y30="Not suitable","-",V30) -> 16 | Y30: =IF(OR(Z30="Y",AA30="Y"),"Not suitable","") | Z30: =IF(OR(N30="N/A",O30="N/A"),"Y","") | AS30: 11307777 | AT30: 3.6028862e+08 | AU30: 1250548.6 | AV30: 22934062 | AW30: 1.3855403e+08 | AX30: 3.5263374e+08 | AY30: 0.1374048 | AZ30: 0.1795872
B31: LUN.TO | C31: Lundin Mining Corp | D31: Diversified Mining | E31: Canada | F31: =AS31/AT31 -> 0.063541394 | G31: =AU31/AV31 -> 2.3415255 | H31: =AX31 -> 9.4601023e+09 | I31: =(AY31/AZ31)-1 -> 0.011027128 | J31: =AV31/AW31 -> 0.18706739 | K31: =IFERROR(_xlfn.RANK.EQ(F31,F$3:F$64),"N/A") -> 22 | L31: =IFERROR(_xlfn.RANK.EQ(G31,G$3:G$64),"N/A") -> 14 | M31: =IFERROR(_xlfn.RANK.EQ(H31,H$3:H$64),"N/A") -> 12 | N31: =IFERROR(_xlfn.RANK.EQ(I31,I$3:I$64),"N/A") -> 22 | O31: =IFERROR(_xlfn.RANK.EQ(J31,J$3:J$64),"N/A") -> 14 | P31: =IFERROR(ABS(K$3-K31),"N/A") -> 20 | Q31: =IFERROR(ABS(L$3-L31),"N/A") -> 13 | R31: =IFERROR(ABS(M$3-M31),"N/A") -> 1 | S31: =IFERROR(ABS(N$3-N31),"N/A") -> 23 | T31: =IFERROR(ABS(O$3-O31),"N/A") -> 12 | U31: =SUM(P31:T31) -> 69 | V31: =_xlfn.RANK.EQ(U31,$U$4:$U$64,1) -> 14 | W31: =IF(Y31="Not suitable","-",V31) -> 14 | Y31: =IF(OR(Z31="Y",AA31="Y"),"Not suitable","") | Z31: =IF(OR(N31="N/A",O31="N/A"),"Y","") | AS31: 4.6292109e+08 | AT31: 7.2853467e+09 | AU31: 2.181805e+09 | AV31: 9.3178785e+08 | AW31: 4.9810276e+09 | AX31: 9.4601023e+09 | AY31: 0.69291875 | AZ31: 0.68536118
B32: TECK.N | C32: Teck Resources Ltd | D32: Diversified Mining | E32: Canada | F32: =AS32/AT32 -> 0.086482881 | G32: =AU32/AV32 -> 2.5382151 | H32: =AX32 -> 3.109027e+10 | I32: =(AY32/AZ32)-1 -> -0.12085815 | J32: =AV32/AW32 -> 0.29111985 | K32: =IFERROR(_xlfn.RANK.EQ(F32,F$3:F$64),"N/A") -> 16 | L32: =IFERROR(_xlfn.RANK.EQ(G32,G$3:G$64),"N/A") -> 11 | M32: =IFERROR(_xlfn.RANK.EQ(H32,H$3:H$64),"N/A") -> 7 | N32: =IFERROR(_xlfn.RANK.EQ(I32,I$3:I$64),"N/A") -> 27 | O32: =IFERROR(_xlfn.RANK.EQ(J32,J$3:J$64),"N/A") -> 9 | P32: =IFERROR(ABS(K$3-K32),"N/A") -> 14 | Q32: =IFERROR(ABS(L$3-L32),"N/A") -> 16 | R32: =IFERROR(ABS(M$3-M32),"N/A") -> 4 | S32: =IFERROR(ABS(N$3-N32),"N/A") -> 18 | T32: =IFERROR(ABS(O$3-O32),"N/A") -> 7 | U32: =SUM(P32:T32) -> 59 | V32: =_xlfn.RANK.EQ(U32,$U$4:$U$64,1) -> 9 | W32: =IF(Y32="Not suitable","-",V32) -> 9 | Y32: =IF(OR(Z32="Y",AA32="Y"),"Not suitable","") | Z32: =IF(OR(N32="N/A",O32="N/A"),"Y","") | AS32: 2.5876298e+09 | AT32: 2.9920716e+10 | AU32: 1.2297339e+10 | AV32: 4.8448766e+09 | AW32: 1.6642207e+10 | AX32: 3.109027e+10 | AY32: 5.2905202 | AZ32: 6.0178233
B33: RIO.L | C33: Rio Tinto PLC | D33: Diversified Mining | E33: United Kingdom | F33: =AS33/AT33 -> 0.18233613 | G33: =AU33/AV33 -> 0.96822506 | H33: =AX33 -> 1.7034585e+11 | I33: =(AY33/AZ33)-1 -> 0.094519941 | J33: =AV33/AW33 -> 0.27429174 | K33: =IFERROR(_xlfn.RANK.EQ(F33,F$3:F$64),"N/A") -> 9 | L33: =IFERROR(_xlfn.RANK.EQ(G33,G$3:G$64),"N/A") -> 21 | M33: =IFERROR(_xlfn.RANK.EQ(H33,H$3:H$64),"N/A") -> 2 | N33: =IFERROR(_xlfn.RANK.EQ(I33,I$3:I$64),"N/A") -> 16 | O33: =IFERROR(_xlfn.RANK.EQ(J33,J$3:J$64),"N/A") -> 10 | P33: =IFERROR(ABS(K$3-K33),"N/A") -> 7 | Q33: =IFERROR(ABS(L$3-L33),"N/A") -> 6 | R33: =IFERROR(ABS(M$3-M33),"N/A") -> 9 | S33: =IFERROR(ABS(N$3-N33),"N/A") -> 29 | T33: =IFERROR(ABS(O$3-O33),"N/A") -> 8 | U33: =SUM(P33:T33) -> 59 | V33: =_xlfn.RANK.EQ(U33,$U$4:$U$64,1) -> 9 | W33: =IF(Y33="Not suitable","-",V33) -> 9 | Y33: =IF(OR(Z33="Y",AA33="Y"),"Not suitable","") | Z33: =IF(OR(N33="N/A",O33="N/A"),"Y","") | AS33: 14615283790 | AT33: 80155719980 | AU33: 21074907360 | AV33: 21766537890 | AW33: 79355425630 | AX33: 1.7034585e+11 | AY33: 12.140034 | AZ33: 11.091651
B34: PX.PS | C34: Philex Mining Corp | D34: Diversified Mining | E34: Philippines | F34: =AS34/AT34 -> 0.058164536 | G34: =AU34/AV34 -> 3.5132474 | H34: =AX34 -> 4.5824389e+08 | I34: =(AY34/AZ34)-1 -> 0.045454545 | J34: =AV34/AW34 -> 0.23126215 | K34: =IFERROR(_xlfn.RANK.EQ(F34,F$3:F$64),"N/A") -> 23 | L34: =IFERROR(_xlfn.RANK.EQ(G34,G$3:G$64),"N/A") -> 9 | M34: =IFERROR(_xlfn.RANK.EQ(H34,H$3:H$64),"N/A") -> 27 | N34: =IFERROR(_xlfn.RANK.EQ(I34,I$3:I$64),"N/A") -> 19 | O34: =IFERROR(_xlfn.RANK.EQ(J34,J$3:J$64),"N/A") -> 12 | P34: =IFERROR(ABS(K$3-K34),"N/A") -> 21 | Q34: =IFERROR(ABS(L$3-L34),"N/A") -> 18 | R34: =IFERROR(ABS(M$3-M34),"N/A") -> 16 | S34: =IFERROR(ABS(N$3-N34),"N/A") -> 26 | T34: =IFERROR(ABS(O$3-O34),"N/A") -> 10 | U34: =SUM(P34:T34) -> 91 | V34: =_xlfn.RANK.EQ(U34,$U$4:$U$64,1) -> 24 | W34: =IF(Y34="Not suitable","-",V34) -> 24 | Y34: =IF(OR(Z34="Y",AA34="Y"),"Not suitable","") | Z34: =IF(OR(N34="N/A",O34="N/A"),"Y","") | AS34: 47340005 | AT34: 8.1389809e+08 | AU34: 1.983983e+08 | AV34: 56471484 | AW34: 2.4418818e+08 | AX34: 4.5824389e+08 | AY34: 0.0049725784 | AZ34: 0.0047563794
B35: RIO.AX | C35: Rio Tinto Ltd | D35: Diversified Mining | E35: Australia | F35: =AS35/AT35 -> 0.18233613 | G35: =AU35/AV35 -> 0.96822506 | H35: =AX35 -> 1.7034585e+11 | I35: =(AY35/AZ35)-1 -> 0.11449035 | J35: =AV35/AW35 -> 0.27429174 | K35: =IFERROR(_xlfn.RANK.EQ(F35,F$3:F$64),"N/A") -> 9 | L35: =IFERROR(_xlfn.RANK.EQ(G35,G$3:G$64),"N/A") -> 21 | M35: =IFERROR(_xlfn.RANK.EQ(H35,H$3:H$64),"N/A") -> 2 | N35: =IFERROR(_xlfn.RANK.EQ(I35,I$3:I$64),"N/A") -> 15 | O35: =IFERROR(_xlfn.RANK.EQ(J35,J$3:J$64),"N/A") -> 10 | P35: =IFERROR(ABS(K$3-K35),"N/A") -> 7 | Q35: =IFERROR(ABS(L$3-L35),"N/A") -> 6 | R35: =IFERROR(ABS(M$3-M35),"N/A") -> 9 | S35: =IFERROR(ABS(N$3-N35),"N/A") -> 30 | T35: =IFERROR(ABS(O$3-O35),"N/A") -> 8 | U35: =SUM(P35:T35) -> 60 | V35: =_xlfn.RANK.EQ(U35,$U$4:$U$64,1) -> 11 | W35: =IF(Y35="Not suitable","-",V35) -> 11 | Y35: =IF(OR(Z35="Y",AA35="Y"),"Not suitable","") | Z35: =IF(OR(N35="N/A",O35="N/A"),"Y","") | AS35: 14615283790 | AT35: 80155719980 | AU35: 21074907360 | AV35: 21766537890 | AW35: 79355425630 | AX35: 1.7034585e+11 | AY35: 12.42844 | AZ35: 11.15168
B36: DPM.TO | C36: Dundee Precious Metals Inc | D36: Diversified Mining | E36: Canada | F36: =AS36/AT36 -> 0.16239882 | G36: =AU36/AV36 -> 0.067138036 | H36: =AX36 -> 1.9367763e+09 | I36: =(AY36/AZ36)-1 -> -0.087244598 | J36: =AV36/AW36 -> 0.35895641 | K36: =IFERROR(_xlfn.RANK.EQ(F36,F$3:F$64),"N/A") -> 11 | L36: =IFERROR(_xlfn.RANK.EQ(G36,G$3:G$64),"N/A") -> 28 | M36: =IFERROR(_xlfn.RANK.EQ(H36,H$3:H$64),"N/A") -> 18 | N36: =IFERROR(_xlfn.RANK.EQ(I36,I$3:I$64),"N/A") -> 26 | O36: =IFERROR(_xlfn.RANK.EQ(J36,J$3:J$64),"N/A") -> 8 | P36: =IFERROR(ABS(K$3-K36),"N/A") -> 9 | Q36: =IFERROR(ABS(L$3-L36),"N/A") -> 1 | R36: =IFERROR(ABS(M$3-M36),"N/A") -> 7 | S36: =IFERROR(ABS(N$3-N36),"N/A") -> 19 | T36: =IFERROR(ABS(O$3-O36),"N/A") -> 6 | U36: =SUM(P36:T36) -> 42 | V36: =_xlfn.RANK.EQ(U36,$U$4:$U$64,1) -> 3 | W36: =IF(Y36="Not suitable","-",V36) -> 3 | Y36: =IF(OR(Z36="Y",AA36="Y"),"Not suitable","") | Z36: =IF(OR(N36="N/A",O36="N/A"),"Y","") | AS36: 2.6721902e+08 | AT36: 1.6454492e+09 | AU36: 18405302 | AV36: 2.741412e+08 | AW36: 7.6371723e+08 | AX36: 1.9367763e+09 | AY36: 1.442381 | AZ36: 1.5802492
B37: MDKA.JK | C37: Merdeka Copper Gold Tbk PT | D37: Diversified Mining | E37: Indonesia | F37: =AS37/AT37 -> 0.064638626 | G37: =AU37/AV37 -> 12.727928 | H37: =AX37 -> 5.3695705e+09 | I37: =(AY37/AZ37)-1 -> -1.1155456 | J37: =AV37/AW37 -> 0.1275169 | K37: =IFERROR(_xlfn.RANK.EQ(F37,F$3:F$64),"N/A") -> 21 | L37: =IFERROR(_xlfn.RANK.EQ(G37,G$3:G$64),"N/A") -> 2 | M37: =IFERROR(_xlfn.RANK.EQ(H37,H$3:H$64),"N/A") -> 16 | N37: =IFERROR(_xlfn.RANK.EQ(I37,I$3:I$64),"N/A") -> 57 | O37: =IFERROR(_xlfn.RANK.EQ(J37,J$3:J$64),"N/A") -> 22 | P37: =IFERROR(ABS(K$3-K37),"N/A") -> 19 | Q37: =IFERROR(ABS(L$3-L37),"N/A") -> 25 | R37: =IFERROR(ABS(M$3-M37),"N/A") -> 5 | S37: =IFERROR(ABS(N$3-N37),"N/A") -> 12 | T37: =IFERROR(ABS(O$3-O37),"N/A") -> 20 | U37: =SUM(P37:T37) -> 81 | V37: =_xlfn.RANK.EQ(U37,$U$4:$U$64,1) -> 19 | W37: =IF(Y37="Not suitable","-",V37) -> 19 | Y37: =IF(OR(Z37="Y",AA37="Y"),"Not suitable","") | Z37: =IF(OR(N37="N/A",O37="N/A"),"Y","") | AS37: 95177915 | AT37: 1.4724619e+09 | AU37: 2.0722648e+09 | AV37: 1.6281243e+08 | AW37: 1.276791e+09 | AX37: 5.3695705e+09 | AY37: -0.0007012194 | AZ37: 0.0060687662
... B39: GMEXICOB.MX | C39: Grupo Mexico SAB de CV | D39: Diversified Mining | E39: Mexico | F39: =AS39/AT39 -> 0.210438 | G39: =AU39/AV39 -> 1.5662498 | H39: =AX39 -> 5.8344758e+10 | I39: =(AY39/AZ39)-1 -> -0.057117464 | J39: =AV39/AW39 -> 0.40855999 | K39: =IFERROR(_xlfn.RANK.EQ(F39,F$3:F$64),"N/A") -> 7 | L39: =IFERROR(_xlfn.RANK.EQ(G39,G$3:G$64),"N/A") -> 16 | M39: =IFERROR(_xlfn.RANK.EQ(H39,H$3:H$64),"N/A") -> 5 | N39: =IFERROR(_xlfn.RANK.EQ(I39,I$3:I$64),"N/A") -> 23 | O39: =IFERROR(_xlfn.RANK.EQ(J39,J$3:J$64),"N/A") -> 7 | P39: =IFERROR(ABS(K$3-K39),"N/A") -> 5 | Q39: =IFERROR(ABS(L$3-L39),"N/A") -> 11 | R39: =IFERROR(ABS(M$3-M39),"N/A") -> 6 | S39: =IFERROR(ABS(N$3-N39),"N/A") -> 22 | T39: =IFERROR(ABS(O$3-O39),"N/A") -> 5 | U39: =SUM(P39:T39) -> 49 | V39: =_xlfn.RANK.EQ(U39,$U$4:$U$64,1) -> 6 | W39: =IF(Y39="Not suitable","-",V39) -> 6 | Y39: =IF(OR(Z39="Y",AA39="Y"),"Not suitable","") | Z39: =IF(OR(N39="N/A",O39="N/A"),"Y","") | AS39: 5.8801958e+09 | AT39: 2.7942652e+10 | AU39: 1.3517396e+10 | AV39: 8.6304213e+09 | AW39: 2.1124e+10 | AX39: 5.8344758e+10 | AY39: 0.60256585 | AZ39: 0.63906778
B40: ECORE.L | C40: Ecora Resources PLC | D40: Diversified Mining | E40: United Kingdom | F40: =AS40/AT40 -> 0.18791948 | G40: =AU40/AV40 -> 0.37920263 | H40: =AX40 -> 3.7431478e+08 | I40: =(AY40/AZ40)-1 -> -0.67302021 | J40: =AV40/AW40 -> 0.79877353 | K40: =IFERROR(_xlfn.RANK.EQ(F40,F$3:F$64),"N/A") -> 8 | L40: =IFERROR(_xlfn.RANK.EQ(G40,G$3:G$64),"N/A") -> 25 | M40: =IFERROR(_xlfn.RANK.EQ(H40,H$3:H$64),"N/A") -> 29 | N40: =IFERROR(_xlfn.RANK.EQ(I40,I$3:I$64),"N/A") -> 41 | O40: =IFERROR(_xlfn.RANK.EQ(J40,J$3:J$64),"N/A") -> 1 | P40: =IFERROR(ABS(K$3-K40),"N/A") -> 6 | Q40: =IFERROR(ABS(L$3-L40),"N/A") -> 2 | R40: =IFERROR(ABS(M$3-M40),"N/A") -> 18 | S40: =IFERROR(ABS(N$3-N40),"N/A") -> 4 | T40: =IFERROR(ABS(O$3-O40),"N/A") -> 1 | U40: =SUM(P40:T40) -> 31 | V40: =_xlfn.RANK.EQ(U40,$U$4:$U$64,1) -> 2 | W40: =IF(Y40="Not suitable","-",V40) -> 2 | Y40: =IF(OR(Z40="Y",AA40="Y"),"Not suitable","") | Z40: =IF(OR(N40="N/A",O40="N/A"),"Y","") | AB40: No P/E | AS40: 1.389063e+08 | AT40: 7.3917988e+08 | AU40: 63073442 | AV40: 1.6633177e+08 | AW40: 2.0823395e+08 | AX40: 3.7431478e+08 | AY40: 0.18805058 | AZ40: 0.57511378
B41: SYR.AX | C41: Syrah Resources Ltd | D41: Diversified Mining | E41: Australia | F41: =AS41/AT41 -> -0.061595824 | G41: =AU41/AV41 -> -3.241156 | H41: =AX41 -> 4.6832907e+08 | I41: =(AY41/AZ41)-1 -> 1.3799491 | J41: =AV41/AW41 -> -0.24865323 | K41: =IFERROR(_xlfn.RANK.EQ(F41,F$3:F$64),"N/A") -> 37 | L41: =IFERROR(_xlfn.RANK.EQ(G41,G$3:G$64),"N/A") -> 58 | M41: =IFERROR(_xlfn.RANK.EQ(H41,H$3:H$64),"N/A") -> 26 | N41: =IFERROR(_xlfn.RANK.EQ(I41,I$3:I$64),"N/A") -> 9 | O41: =IFERROR(_xlfn.RANK.EQ(J41,J$3:J$64),"N/A") -> 41 | P41: =IFERROR(ABS(K$3-K41),"N/A") -> 35 | Q41: =IFERROR(ABS(L$3-L41),"N/A") -> 31 | R41: =IFERROR(ABS(M$3-M41),"N/A") -> 15 | S41: =IFERROR(ABS(N$3-N41),"N/A") -> 36 | T41: =IFERROR(ABS(O$3-O41),"N/A") -> 39 | U41: =SUM(P41:T41) -> 156 | V41: =_xlfn.RANK.EQ(U41,$U$4:$U$64,1) -> 48 | W41: =IF(Y41="Not suitable","-",V41) -> 48 | Y41: =IF(OR(Z41="Y",AA41="Y"),"Not suitable","") | Z41: =IF(OR(N41="N/A",O41="N/A"),"Y","") | AS41: -39402554 | AT41: 6.3969522e+08 | AU41: 1.2560234e+08 | AV41: -38752328 | AW41: 1.5584888e+08 | AX41: 4.6832907e+08 | AY41: -0.1396809 | AZ41: -0.05869071
B42: HZNC.NS | C42: Hindustan Zinc Ltd | D42: Diversified Mining | E42: India | F42: =AS42/AT42 -> 0.79322611 | G42: =AU42/AV42 -> 0.83276092 | H42: =AX42 -> 2.4411842e+10 | I42: =(AY42/AZ42)-1 -> -0.25640387 | J42: =AV42/AW42 -> 0.41841164 | K42: =IFERROR(_xlfn.RANK.EQ(F42,F$3:F$64),"N/A") -> 1 | L42: =IFERROR(_xlfn.RANK.EQ(G42,G$3:G$64),"N/A") -> 24 | M42: =IFERROR(_xlfn.RANK.EQ(H42,H$3:H$64),"N/A") -> 8 | N42: =IFERROR(_xlfn.RANK.EQ(I42,I$3:I$64),"N/A") -> 32 | O42: =IFERROR(_xlfn.RANK.EQ(J42,J$3:J$64),"N/A") -> 6 | P42: =IFERROR(ABS(K$3-K42),"N/A") -> 1 | Q42: =IFERROR(ABS(L$3-L42),"N/A") -> 3 | R42: =IFERROR(ABS(M$3-M42),"N/A") -> 3 | S42: =IFERROR(ABS(N$3-N42),"N/A") -> 13 | T42: =IFERROR(ABS(O$3-O42),"N/A") -> 4 | U42: =SUM(P42:T42) -> 24 | V42: =_xlfn.RANK.EQ(U42,$U$4:$U$64,1) -> 1 | W42: =IF(Y42="Not suitable","-",V42) -> 1 | Y42: =IF(OR(Z42="Y",AA42="Y"),"Not suitable","") | Z42: =IF(OR(N42="N/A",O42="N/A"),"Y","") | AS42: 1.8676777e+09 | AT42: 2.3545338e+09 | AU42: 2.1631778e+09 | AV42: 2.5975977e+09 | AW42: 6.2082348e+09 | AX42: 2.4411842e+10 | AY42: 0.3434156 | AZ42: 0.4618308
B43: 000975.SZ | C43: Yintai Gold Co Ltd | D43: Diversified Mining | E43: China | F43: =AS43/AT43 -> 0.1140176 | G43: =AU43/AV43 -> 1.4145771 | H43: =AX43 -> 9.1395173e+09 | I43: =(AY43/AZ43)-1 -> 0.15545733 | J43: =AV43/AW43 -> 0.1925961 | K43: =IFERROR(_xlfn.RANK.EQ(F43,F$3:F$64),"N/A") -> 14 | L43: =IFERROR(_xlfn.RANK.EQ(G43,G$3:G$64),"N/A") -> 17 | M43: =IFERROR(_xlfn.RANK.EQ(H43,H$3:H$64),"N/A") -> 13 | N43: =IFERROR(_xlfn.RANK.EQ(I43,I$3:I$64),"N/A") -> 14 | O43: =IFERROR(_xlfn.RANK.EQ(J43,J$3:J$64),"N/A") -> 13 | P43: =IFERROR(ABS(K$3-K43),"N/A") -> 12 | Q43: =IFERROR(ABS(L$3-L43),"N/A") -> 10 | R43: =IFERROR(ABS(M$3-M43),"N/A") -> 2 | S43: =IFERROR(ABS(N$3-N43),"N/A") -> 31 | T43: =IFERROR(ABS(O$3-O43),"N/A") -> 11 | U43: =SUM(P43:T43) -> 66 | V43: =_xlfn.RANK.EQ(U43,$U$4:$U$64,1) -> 12 | W43: =IF(Y43="Not suitable","-",V43) -> 12 | Y43: =IF(OR(Z43="Y",AA43="Y"),"Not suitable","") | Z43: =IF(OR(N43="N/A",O43="N/A"),"Y","") | AS43: 2.6478625e+08 | AT43: 2.3223279e+09 | AU43: 4.8594407e+08 | AV43: 3.4352604e+08 | AW43: 1.7836604e+09 | AX43: 9.1395173e+09 | AY43: 0.11860813 | AZ43: 0.10265038
B44: NYR.BR | C44: Nyrstar NV | D44: Diversified Mining | E44: Belgium | F44: =AS44/AT44 -> 0.33967742 | G44: =AU44/AV44 -> -12.329851 | H44: =AX44 -> 12737562 | I44: =(AY44/AZ44)-1 -> -1 | J44: =AV44/AW44 -> -1.5858238 | K44: =IFERROR(_xlfn.RANK.EQ(F44,F$3:F$64),"N/A") -> 5 | L44: =IFERROR(_xlfn.RANK.EQ(G44,G$3:G$64),"N/A") -> 61 | M44: =IFERROR(_xlfn.RANK.EQ(H44,H$3:H$64),"N/A") -> 61 | N44: =IFERROR(_xlfn.RANK.EQ(I44,I$3:I$64),"N/A") -> 47 | O44: =IFERROR(_xlfn.RANK.EQ(J44,J$3:J$64),"N/A") -> 49 | P44: =IFERROR(ABS(K$3-K44),"N/A") -> 3 | Q44: =IFERROR(ABS(L$3-L44),"N/A") -> 34 | R44: =IFERROR(ABS(M$3-M44),"N/A") -> 50 | S44: =IFERROR(ABS(N$3-N44),"N/A") -> 2 | T44: =IFERROR(ABS(O$3-O44),"N/A") -> 47 | U44: =SUM(P44:T44) -> 136 | V44: =_xlfn.RANK.EQ(U44,$U$4:$U$64,1) -> 35 | W44: =IF(Y44="Not suitable","-",V44) -> - | Y44: Not Suitable | AS44: -1332516.2 | AT44: -3922887.1 | AU44: 15426267 | AV44: -1251131.7 | AW44: 788947.46 | AX44: 12737562 | AZ44: -2.2552791
B45: BSX.AX | C45: Blackstone Minerals Ltd | D45: Diversified Mining | E45: Australia | F45: =AS45/AT45 -> -1.0941848 | G45: =AU45/AV45 -> -0.014668867 | H45: =AX45 -> 29877754 | I45: =(AY45/AZ45)-1 -> -1 | J45: =AV45/AW45 -> -7.0645502 | K45: =IFERROR(_xlfn.RANK.EQ(F45,F$3:F$64),"N/A") -> 61 | L45: =IFERROR(_xlfn.RANK.EQ(G45,G$3:G$64),"N/A") -> 36 | M45: =IFERROR(_xlfn.RANK.EQ(H45,H$3:H$64),"N/A") -> 58 | N45: =IFERROR(_xlfn.RANK.EQ(I45,I$3:I$64),"N/A") -> 47 | O45: =IFERROR(_xlfn.RANK.EQ(J45,J$3:J$64),"N/A") -> 53 | P45: =IFERROR(ABS(K$3-K45),"N/A") -> 59 | Q45: =IFERROR(ABS(L$3-L45),"N/A") -> 9 | R45: =IFERROR(ABS(M$3-M45),"N/A") -> 47 | S45: =IFERROR(ABS(N$3-N45),"N/A") -> 2 | T45: =IFERROR(ABS(O$3-O45),"N/A") -> 51 | U45: =SUM(P45:T45) -> 168 | V45: =_xlfn.RANK.EQ(U45,$U$4:$U$64,1) -> 52 | W45: =IF(Y45="Not suitable","-",V45) -> - | Y45: Not Suitable | AS45: -34483660 | AT45: 31515390 | AU45: 436910 | AV45: -29784850 | AW45: 4216100 | AX45: 29877754 | AZ45: -0.01908
B46: DVP.AX | C46: Develop Global Ltd | D46: Diversified Mining | E46: Australia | F46: =AS46/AT46 -> -0.11952959 | G46: =AU46/AV46 -> -2.3935377 | H46: =AX46 -> 6.0906049e+08 | I46: =(AY46/AZ46)-1 -> -1 | J46: =AV46/AW46 -> -0.17206725 | K46: =IFERROR(_xlfn.RANK.EQ(F46,F$3:F$64),"N/A") -> 44 | L46: =IFERROR(_xlfn.RANK.EQ(G46,G$3:G$64),"N/A") -> 55 | M46: =IFERROR(_xlfn.RANK.EQ(H46,H$3:H$64),"N/A") -> 23 | N46: =IFERROR(_xlfn.RANK.EQ(I46,I$3:I$64),"N/A") -> 47 | O46: =IFERROR(_xlfn.RANK.EQ(J46,J$3:J$64),"N/A") -> 36 | P46: =IFERROR(ABS(K$3-K46),"N/A") -> 42 | Q46: =IFERROR(ABS(L$3-L46),"N/A") -> 28 | R46: =IFERROR(ABS(M$3-M46),"N/A") -> 12 | S46: =IFERROR(ABS(N$3-N46),"N/A") -> 2 | T46: =IFERROR(ABS(O$3-O46),"N/A") -> 34 | U46: =SUM(P46:T46) -> 118 | V46: =_xlfn.RANK.EQ(U46,$U$4:$U$64,1) -> 26 | W46: =IF(Y46="Not suitable","-",V46) -> - | Y46: Not Suitable | AS46: -17888910 | AT46: 149660930 | AU46: 27913150 | AV46: -11661880 | AW46: 67775130 | AX46: 6.0906049e+08 | AZ46: -0.04988
B47: GGD.TO | C47: GoGold Resources Inc | D47: Diversified Mining | E47: Canada | F47: =AS47/AT47 -> -0.028022745 | G47: =AU47/AV47 -> -0.1159919 | H47: =AX47 -> 4.0456167e+08 | I47: =(AY47/AZ47)-1 -> -2.1903449 | J47: =AV47/AW47 -> -0.48975545 | K47: =IFERROR(_xlfn.RANK.EQ(F47,F$3:F$64),"N/A") -> 32 | L47: =IFERROR(_xlfn.RANK.EQ(G47,G$3:G$64),"N/A") -> 41 | M47: =IFERROR(_xlfn.RANK.EQ(H47,H$3:H$64),"N/A") -> 28 | N47: =IFERROR(_xlfn.RANK.EQ(I47,I$3:I$64),"N/A") -> 62 | O47: =IFERROR(_xlfn.RANK.EQ(J47,J$3:J$64),"N/A") -> 45 | P47: =IFERROR(ABS(K$3-K47),"N/A") -> 30 | Q47: =IFERROR(ABS(L$3-L47),"N/A") -> 14 | R47: =IFERROR(ABS(M$3-M47),"N/A") -> 17 | S47: =IFERROR(ABS(N$3-N47),"N/A") -> 17 | T47: =IFERROR(ABS(O$3-O47),"N/A") -> 43 | U47: =SUM(P47:T47) -> 121 | V47: =_xlfn.RANK.EQ(U47,$U$4:$U$64,1) -> 28 | W47: =IF(Y47="Not suitable","-",V47) -> 28 | Y47: =IF(OR(Z47="Y",AA47="Y"),"Not suitable","") | Z47: =IF(OR(N47="N/A",O47="N/A"),"Y","") | AS47: -12262954 | AT47: 4.3760715e+08 | AU47: 2671738.6 | AV47: -23033837 | AW47: 47031302 | AX47: 4.0456167e+08 | AY47: 0.0097996788 | AZ47: -0.0082326384
B48: CXO.AX | C48: Core Lithium Ltd | D48: Diversified Mining | E48: Australia | F48: =AS48/AT48 -> 0.030457396 | G48: =AU48/AV48 -> 2.4863459 | H48: =AX48 -> 5.2354921e+08 | I48: =(AY48/AZ48)-1 -> -0.91279621 | J48: =AV48/AW48 -> 0.18237875 | K48: =IFERROR(_xlfn.RANK.EQ(F48,F$3:F$64),"N/A") -> 29 | L48: =IFERROR(_xlfn.RANK.EQ(G48,G$3:G$64),"N/A") -> 13 | M48: =IFERROR(_xlfn.RANK.EQ(H48,H$3:H$64),"N/A") -> 24 | N48: =IFERROR(_xlfn.RANK.EQ(I48,I$3:I$64),"N/A") -> 46 | O48: =IFERROR(_xlfn.RANK.EQ(J48,J$3:J$64),"N/A") -> 15 | P48: =IFERROR(ABS(K$3-K48),"N/A") -> 27 | Q48: =IFERROR(ABS(L$3-L48),"N/A") -> 14 | R48: =IFERROR(ABS(M$3-M48),"N/A") -> 13 | S48: =IFERROR(ABS(N$3-N48),"N/A") -> 1 | T48: =IFERROR(ABS(O$3-O48),"N/A") -> 13 | U48: =SUM(P48:T48) -> 68 | V48: =_xlfn.RANK.EQ(U48,$U$4:$U$64,1) -> 13 | W48: =IF(Y48="Not suitable","-",V48) -> 13 | Y48: =IF(OR(Z48="Y",AA48="Y"),"Not suitable","") | Z48: =IF(OR(N48="N/A",O48="N/A"),"Y","") | AS48: 10810000 | AT48: 354922000 | AU48: 22944000 | AV48: 9228000 | AW48: 50598000 | AX48: 5.2354921e+08 | AY48: 0.00092 | AZ48: 0.01055
B49: ALS.TO | C49: Altius Minerals Corp | D49: Diversified Mining | E49: Canada | F49: =AS49/AT49 -> 0.081206434 | G49: =AU49/AV49 -> 2.0956517 | H49: =AX49 -> 9.6453243e+08 | I49: =(AY49/AZ49)-1 -> -0.70000658 | J49: =AV49/AW49 -> 0.56521015 | K49: =IFERROR(_xlfn.RANK.EQ(F49,F$3:F$64),"N/A") -> 18 | L49: =IFERROR(_xlfn.RANK.EQ(G49,G$3:G$64),"N/A") -> 15 | M49: =IFERROR(_xlfn.RANK.EQ(H49,H$3:H$64),"N/A") -> 22 | N49: =IFERROR(_xlfn.RANK.EQ(I49,I$3:I$64),"N/A") -> 42 | O49: =IFERROR(_xlfn.RANK.EQ(J49,J$3:J$64),"N/A") -> 4 | P49: =IFERROR(ABS(K$3-K49),"N/A") -> 16 | Q49: =IFERROR(ABS(L$3-L49),"N/A") -> 12 | R49: =IFERROR(ABS(M$3-M49),"N/A") -> 11 | S49: =IFERROR(ABS(N$3-N49),"N/A") -> 3 | T49: =IFERROR(ABS(O$3-O49),"N/A") -> 2 | U49: =SUM(P49:T49) -> 44 | V49: =_xlfn.RANK.EQ(U49,$U$4:$U$64,1) -> 4 | W49: =IF(Y49="Not suitable","-",V49) -> 4 | Y49: =IF(OR(Z49="Y",AA49="Y"),"Not suitable","") | Z49: =IF(OR(N49="N/A",O49="N/A"),"Y","") | AS49: 42771341 | AT49: 5.2669892e+08 | AU49: 1.3094322e+08 | AV49: 62483294 | AW49: 1.1054878e+08 | AX49: 9.6453243e+08 | AY49: 0.26900811 | AZ49: 0.89671334
B50: MAI.V | C50: Minera Alamos Inc | D50: Diversified Mining | E50: Canada | F50: =AS50/AT50 -> 0.1298274 | G50: =AU50/AV50 -> 0.31065585 | H50: =AX50 -> 1.5459893e+08 | I50: =(AY50/AZ50)-1 -> -1.3880565 | J50: =AV50/AW50 -> 0.055111775 | K50: =IFERROR(_xlfn.RANK.EQ(F50,F$3:F$64),"N/A") -> 13 | L50: =IFERROR(_xlfn.RANK.EQ(G50,G$3:G$64),"N/A") -> 26 | M50: =IFERROR(_xlfn.RANK.EQ(H50,H$3:H$64),"N/A") -> 38 | N50: =IFERROR(_xlfn.RANK.EQ(I50,I$3:I$64),"N/A") -> 59 | O50: =IFERROR(_xlfn.RANK.EQ(J50,J$3:J$64),"N/A") -> 27 | P50: =IFERROR(ABS(K$3-K50),"N/A") -> 11 | Q50: =IFERROR(ABS(L$3-L50),"N/A") -> 1 | R50: =IFERROR(ABS(M$3-M50),"N/A") -> 27 | S50: =IFERROR(ABS(N$3-N50),"N/A") -> 14 | T50: =IFERROR(ABS(O$3-O50),"N/A") -> 25 | U50: =SUM(P50:T50) -> 78 | V50: =_xlfn.RANK.EQ(U50,$U$4:$U$64,1) -> 16 | W50: =IF(Y50="Not suitable","-",V50) -> 16 | Y50: =IF(OR(Z50="Y",AA50="Y"),"Not suitable","") | Z50: =IF(OR(N50="N/A",O50="N/A"),"Y","") | AS50: 6076721.9 | AT50: 46806160 | AU50: 402959.72 | AV50: 1297125.8 | AW50: 23536273 | AX50: 1.5459893e+08 | AY50: -0.0122799 | AZ50: 0.031644615
B51: ELE.V | C51: Elemental Altus Royalties Corp | D51: Diversified Mining | E51: Canada | F51: =AS51/AT51 -> -0.12436914 | G51: =AU51/AV51 -> -2.4379515 | H51: =AX51 -> 2.2827686e+08 | I51: =(AY51/AZ51)-1 -> -0.53638305 | J51: =AV51/AW51 -> -1.2782446 | K51: =IFERROR(_xlfn.RANK.EQ(F51,F$3:F$64),"N/A") -> 45 | L51: =IFERROR(_xlfn.RANK.EQ(G51,G$3:G$64),"N/A") -> 56 | M51: =IFERROR(_xlfn.RANK.EQ(H51,H$3:H$64),"N/A") -> 35 | N51: =IFERROR(_xlfn.RANK.EQ(I51,I$3:I$64),"N/A") -> 39 | O51: =IFERROR(_xlfn.RANK.EQ(J51,J$3:J$64),"N/A") -> 48 | P51: =IFERROR(ABS(K$3-K51),"N/A") -> 43 | Q51: =IFERROR(ABS(L$3-L51),"N/A") -> 29 | R51: =IFERROR(ABS(M$3-M51),"N/A") -> 24 | S51: =IFERROR(ABS(N$3-N51),"N/A") -> 6 | T51: =IFERROR(ABS(O$3-O51),"N/A") -> 46 | U51: =SUM(P51:T51) -> 148 | V51: =_xlfn.RANK.EQ(U51,$U$4:$U$64,1) -> 42 | W51: =IF(Y51="Not suitable","-",V51) -> 42 | Y51: =IF(OR(Z51="Y",AA51="Y"),"Not suitable","") | Z51: =IF(OR(N51="N/A",O51="N/A"),"Y","") | AS51: -26729742 | AT51: 2.1492262e+08 | AU51: 44089176 | AV51: -18084517 | AW51: 14147931 | AX51: 2.2827686e+08 | AY51: -0.063441575 | AZ51: -0.1368405
B52: SRL.AX | C52: Sunrise Energy Metals Ltd | D52: Diversified Mining | E52: Australia | F52: =AS52/AT52 -> -0.56512579 | G52: =AU52/AV52 -> -0.010206321 | H52: =AX52 -> 33835312 | I52: =(AY52/AZ52)-1 -> 6.1276596 | J52: =AV52/AW52 -> -6.1609195 | K52: =IFERROR(_xlfn.RANK.EQ(F52,F$3:F$64),"N/A") -> 55 | L52: =IFERROR(_xlfn.RANK.EQ(G52,G$3:G$64),"N/A") -> 35 | M52: =IFERROR(_xlfn.RANK.EQ(H52,H$3:H$64),"N/A") -> 56 | N52: =IFERROR(_xlfn.RANK.EQ(I52,I$3:I$64),"N/A") -> 1 | O52: =IFERROR(_xlfn.RANK.EQ(J52,J$3:J$64),"N/A") -> 52 | P52: =IFERROR(ABS(K$3-K52),"N/A") -> 53 | Q52: =IFERROR(ABS(L$3-L52),"N/A") -> 8 | R52: =IFERROR(ABS(M$3-M52),"N/A") -> 45 | S52: =IFERROR(ABS(N$3-N52),"N/A") -> 44 | T52: =IFERROR(ABS(O$3-O52),"N/A") -> 50 | U52: =SUM(P52:T52) -> 200 | V52: =_xlfn.RANK.EQ(U52,$U$4:$U$64,1) -> 60 | W52: =IF(Y52="Not suitable","-",V52) -> 60 | Y52: =IF(OR(Z52="Y",AA52="Y"),"Not suitable","") | Z52: =IF(OR(N52="N/A",O52="N/A"),"Y","") | AS52: -9120000 | AT52: 16138000 | AU52: 93000 | AV52: -9112000 | AW52: 1479000 | AX52: 33835312 | AY52: -0.67 | AZ52: -0.094
B53: LODE.A | C53: Comstock Inc | D53: Diversified Mining | E53: United States of America | F53: =AS53/AT53 -> 0 | G53: =AU53/AV53 -> -0.84806624 | H53: =AX53 -> 75533256 | I53: =(AY53/AZ53)-1 -> 3.9807518 | J53: =AV53/AW53 -> -9.8901016 | K53: =IFERROR(_xlfn.RANK.EQ(F53,F$3:F$64),"N/A") -> 30 | L53: =IFERROR(_xlfn.RANK.EQ(G53,G$3:G$64),"N/A") -> 48 | M53: =IFERROR(_xlfn.RANK.EQ(H53,H$3:H$64),"N/A") -> 46 | N53: =IFERROR(_xlfn.RANK.EQ(I53,I$3:I$64),"N/A") -> 4 | O53: =IFERROR(_xlfn.RANK.EQ(J53,J$3:J$64),"N/A") -> 54 | P53: =IFERROR(ABS(K$3-K53),"N/A") -> 28 | Q53: =IFERROR(ABS(L$3-L53),"N/A") -> 21 | R53: =IFERROR(ABS(M$3-M53),"N/A") -> 35 | S53: =IFERROR(ABS(N$3-N53),"N/A") -> 41 | T53: =IFERROR(ABS(O$3-O53),"N/A") -> 52 | U53: =SUM(P53:T53) -> 177 | V53: =_xlfn.RANK.EQ(U53,$U$4:$U$64,1) -> 56 | W53: =IF(Y53="Not suitable","-",V53) -> 56 | Y53: =IF(OR(Z53="Y",AA53="Y"),"Not suitable","") | Z53: =IF(OR(N53="N/A",O53="N/A"),"Y","") | AT53: 1.1494454e+08 | AU53: 15696636 | AV53: -18508738 | AW53: 1871440.6 | AX53: 75533256 | AY53: -0.2309475 | AZ53: -0.046368
B54: MTA.V | C54: Metalla Royalty & Streaming Ltd | D54: Diversified Mining | E54: Canada | F54: =AS54/AT54 -> -0.092174621 | G54: =AU54/AV54 -> -1.1172124 | H54: =AX54 -> 3.5293182e+08 | I54: =(AY54/AZ54)-1 -> -0.24775651 | J54: =AV54/AW54 -> -3.9257447 | K54: =IFERROR(_xlfn.RANK.EQ(F54,F$3:F$64),"N/A") -> 39 | L54: =IFERROR(_xlfn.RANK.EQ(G54,G$3:G$64),"N/A") -> 51 | M54: =IFERROR(_xlfn.RANK.EQ(H54,H$3:H$64),"N/A") -> 30 | N54: =IFERROR(_xlfn.RANK.EQ(I54,I$3:I$64),"N/A") -> 31 | O54: =IFERROR(_xlfn.RANK.EQ(J54,J$3:J$64),"N/A") -> 51 | P54: =IFERROR(ABS(K$3-K54),"N/A") -> 37 | Q54: =IFERROR(ABS(L$3-L54),"N/A") -> 24 | R54: =IFERROR(ABS(M$3-M54),"N/A") -> 19 | S54: =IFERROR(ABS(N$3-N54),"N/A") -> 14 | T54: =IFERROR(ABS(O$3-O54),"N/A") -> 49 | U54: =SUM(P54:T54) -> 143 | V54: =_xlfn.RANK.EQ(U54,$U$4:$U$64,1) -> 38 | W54: =IF(Y54="Not suitable","-",V54) -> 38 | Y54: =IF(OR(Z54="Y",AA54="Y"),"Not suitable","") | Z54: =IF(OR(N54="N/A",O54="N/A"),"Y","") | AS54: -16040384 | AT54: 1.740217e+08 | AU54: 15536510 | AV54: -13906496 | AW54: 3542384.3 | AX54: 3.5293182e+08 | AY54: -0.1794528 | AZ54: -0.2385568
B55: LM8.AX | C55: Lunnon Metals Ltd | D55: Diversified Mining | E55: Australia | F55: =AS55/AT55 -> -0.34198138 | G55: =AU55/AV55 -> -0.0070672115 | H55: =AX55 -> 59904965 | I55: =(AY55/AZ55)-1 -> -0.12359551 | J55: =AV55/AW55 -> -23.309338 | K55: =IFERROR(_xlfn.RANK.EQ(F55,F$3:F$64),"N/A") -> 49 | L55: =IFERROR(_xlfn.RANK.EQ(G55,G$3:G$64),"N/A") -> 33 | M55: =IFERROR(_xlfn.RANK.EQ(H55,H$3:H$64),"N/A") -> 51 | N55: =IFERROR(_xlfn.RANK.EQ(I55,I$3:I$64),"N/A") -> 28 | O55: =IFERROR(_xlfn.RANK.EQ(J55,J$3:J$64),"N/A") -> 57 | P55: =IFERROR(ABS(K$3-K55),"N/A") -> 47 | Q55: =IFERROR(ABS(L$3-L55),"N/A") -> 6 | R55: =IFERROR(ABS(M$3-M55),"N/A") -> 40 | S55: =IFERROR(ABS(N$3-N55),"N/A") -> 17 | T55: =IFERROR(ABS(O$3-O55),"N/A") -> 55 | U55: =SUM(P55:T55) -> 165 | V55: =_xlfn.RANK.EQ(U55,$U$4:$U$64,1) -> 51 | W55: =IF(Y55="Not suitable","-",V55) -> 51 | Y55: =IF(OR(Z55="Y",AA55="Y"),"Not suitable","") | Z55: =IF(OR(N55="N/A",O55="N/A"),"Y","") | AS55: -17735110 | AT55: 51859870 | AU55: 125310 | AV55: -17731180 | AW55: 760690 | AX55: 59904965 | AY55: -0.078 | AZ55: -0.089
B56: CNB.AX | C56: Carnaby Resources Ltd | D56: Diversified Mining | E56: Australia | F56: =AS56/AT56 -> -0.38705013 | G56: =AU56/AV56 -> -0.0015305405 | H56: =AX56 -> 87122790 | I56: =(AY56/AZ56)-1 -> 0.65151515 | J56: =AV56/AW56 -> -23.01461 | K56: =IFERROR(_xlfn.RANK.EQ(F56,F$3:F$64),"N/A") -> 51 | L56: =IFERROR(_xlfn.RANK.EQ(G56,G$3:G$64),"N/A") -> 32 | M56: =IFERROR(_xlfn.RANK.EQ(H56,H$3:H$64),"N/A") -> 45 | N56: =IFERROR(_xlfn.RANK.EQ(I56,I$3:I$64),"N/A") -> 11 | O56: =IFERROR(_xlfn.RANK.EQ(J56,J$3:J$64),"N/A") -> 56 | P56: =IFERROR(ABS(K$3-K56),"N/A") -> 49 | Q56: =IFERROR(ABS(L$3-L56),"N/A") -> 5 | R56: =IFERROR(ABS(M$3-M56),"N/A") -> 34 | S56: =IFERROR(ABS(N$3-N56),"N/A") -> 34 | T56: =IFERROR(ABS(O$3-O56),"N/A") -> 54 | U56: =SUM(P56:T56) -> 176 | V56: =_xlfn.RANK.EQ(U56,$U$4:$U$64,1) -> 55 | W56: =IF(Y56="Not suitable","-",V56) -> 55 | Y56: =IF(OR(Z56="Y",AA56="Y"),"Not suitable","") | Z56: =IF(OR(N56="N/A",O56="N/A"),"Y","") | AS56: -12233780 | AT56: 31607740 | AU56: 18710 | AV56: -12224440 | AW56: 531160 | AX56: 87122790 | AY56: -0.109 | AZ56: -0.066
B57: IE.A | C57: Ivanhoe Electric Inc | D57: Diversified Mining | E57: Canada | F57: =AS57/AT57 -> -0.57735317 | G57: =AU57/AV57 -> -0.42842097 | H57: =AX57 -> 1.4090799e+09 | I57: =(AY57/AZ57)-1 -> -0.41336577 | J57: =AV57/AW57 -> -46.221368 | K57: =IFERROR(_xlfn.RANK.EQ(F57,F$3:F$64),"N/A") -> 56 | L57: =IFERROR(_xlfn.RANK.EQ(G57,G$3:G$64),"N/A") -> 45 | M57: =IFERROR(_xlfn.RANK.EQ(H57,H$3:H$64),"N/A") -> 20 | N57: =IFERROR(_xlfn.RANK.EQ(I57,I$3:I$64),"N/A") -> 36 | O57: =IFERROR(_xlfn.RANK.EQ(J57,J$3:J$64),"N/A") -> 58 | P57: =IFERROR(ABS(K$3-K57),"N/A") -> 54 | Q57: =IFERROR(ABS(L$3-L57),"N/A") -> 18 | R57: =IFERROR(ABS(M$3-M57),"N/A") -> 9 | S57: =IFERROR(ABS(N$3-N57),"N/A") -> 9 | T57: =IFERROR(ABS(O$3-O57),"N/A") -> 56 | U57: =SUM(P57:T57) -> 146 | V57: =_xlfn.RANK.EQ(U57,$U$4:$U$64,1) -> 40 | W57: =IF(Y57="Not suitable","-",V57) -> 40 | Y57: =IF(OR(Z57="Y",AA57="Y"),"Not suitable","") | Z57: =IF(OR(N57="N/A",O57="N/A"),"Y","") | AS57: -3.1729101e+08 | AT57: 5.495614e+08 | AU57: 1.1349202e+08 | AV57: -2.6490771e+08 | AW57: 5731282.3 | AX57: 1.4090799e+09 | AY57: -1.5359459 | AZ57: -2.6182344
B58: PNX.AX | C58: PNX Metals Ltd | D58: Diversified Mining | E58: Australia | F58: =AS58/AT58 -> -0.055744824 | G58: =AU58/AV58 -> -0.084974907 | H58: =AX58 -> 26903124 | I58: =(AY58/AZ58)-1 -> -1 | J58: =AV58/AW58 -> -19.767175 | K58: =IFERROR(_xlfn.RANK.EQ(F58,F$3:F$64),"N/A") -> 35 | L58: =IFERROR(_xlfn.RANK.EQ(G58,G$3:G$64),"N/A") -> 40 | M58: =IFERROR(_xlfn.RANK.EQ(H58,H$3:H$64),"N/A") -> 59 | N58: =IFERROR(_xlfn.RANK.EQ(I58,I$3:I$64),"N/A") -> 47 | O58: =IFERROR(_xlfn.RANK.EQ(J58,J$3:J$64),"N/A") -> 55 | P58: =IFERROR(ABS(K$3-K58),"N/A") -> 33 | Q58: =IFERROR(ABS(L$3-L58),"N/A") -> 13 | R58: =IFERROR(ABS(M$3-M58),"N/A") -> 48 | S58: =IFERROR(ABS(N$3-N58),"N/A") -> 2 | T58: =IFERROR(ABS(O$3-O58),"N/A") -> 53 | U58: =SUM(P58:T58) -> 149 | V58: =_xlfn.RANK.EQ(U58,$U$4:$U$64,1) -> 45 | W58: =IF(Y58="Not suitable","-",V58) -> - | Y58: Not Suitable | AS58: -1472970 | AT58: 26423440 | AU58: 124450 | AV58: -1464550 | AW58: 74090 | AX58: 26903124 | AZ58: 0.00091
B59: DRE.AX | C59: Dreadnought Resources Ltd | D59: Diversified Mining | E59: Australia | F59: =AS59/AT59 -> -0.10861203 | G59: =AU59/AV59 -> -0.030703658 | H59: =AX59 -> 66149886 | I59: =(AY59/AZ59)-1 -> -1 | J59: =AV59/AW59 -> -97.691723 | K59: =IFERROR(_xlfn.RANK.EQ(F59,F$3:F$64),"N/A") -> 42 | L59: =IFERROR(_xlfn.RANK.EQ(G59,G$3:G$64),"N/A") -> 39 | M59: =IFERROR(_xlfn.RANK.EQ(H59,H$3:H$64),"N/A") -> 48 | N59: =IFERROR(_xlfn.RANK.EQ(I59,I$3:I$64),"N/A") -> 47 | O59: =IFERROR(_xlfn.RANK.EQ(J59,J$3:J$64),"N/A") -> 61 | P59: =IFERROR(ABS(K$3-K59),"N/A") -> 40 | Q59: =IFERROR(ABS(L$3-L59),"N/A") -> 12 | R59: =IFERROR(ABS(M$3-M59),"N/A") -> 37 | S59: =IFERROR(ABS(N$3-N59),"N/A") -> 2 | T59: =IFERROR(ABS(O$3-O59),"N/A") -> 59 | U59: =SUM(P59:T59) -> 150 | V59: =_xlfn.RANK.EQ(U59,$U$4:$U$64,1) -> 46 | W59: =IF(Y59="Not suitable","-",V59) -> - | Y59: Not Suitable | AS59: -5521990 | AT59: 50841420 | AU59: 177570 | AV59: -5783350 | AW59: 59200 | AX59: 66149886 | AZ59: -0.001
B60: CHN.AX | C60: Chalice Mining Ltd | D60: Diversified Mining | E60: Australia | F60: =AS60/AT60 -> -0.35071906 | G60: =AU60/AV60 -> -0.024714149 | H60: =AX60 -> 4.7453523e+08 | I60: =(AY60/AZ60)-1 -> -0.30784235 | J60: =AV60/AW60 -> -76.537788 | K60: =IFERROR(_xlfn.RANK.EQ(F60,F$3:F$64),"N/A") -> 50 | L60: =IFERROR(_xlfn.RANK.EQ(G60,G$3:G$64),"N/A") -> 38 | M60: =IFERROR(_xlfn.RANK.EQ(H60,H$3:H$64),"N/A") -> 25 | N60: =IFERROR(_xlfn.RANK.EQ(I60,I$3:I$64),"N/A") -> 35 | O60: =IFERROR(_xlfn.RANK.EQ(J60,J$3:J$64),"N/A") -> 60 | P60: =IFERROR(ABS(K$3-K60),"N/A") -> 48 | Q60: =IFERROR(ABS(L$3-L60),"N/A") -> 11 | R60: =IFERROR(ABS(M$3-M60),"N/A") -> 14 | S60: =IFERROR(ABS(N$3-N60),"N/A") -> 10 | T60: =IFERROR(ABS(O$3-O60),"N/A") -> 58 | U60: =SUM(P60:T60) -> 141 | V60: =_xlfn.RANK.EQ(U60,$U$4:$U$64,1) -> 37 | W60: =IF(Y60="Not suitable","-",V60) -> 37 | Y60: =IF(OR(Z60="Y",AA60="Y"),"Not suitable","") | AS60: -65602000 | AT60: 187050000 | AU60: 1727000 | AV60: -69879000 | AW60: 913000 | AX60: 4.7453523e+08 | AY60: -0.12065 | AZ60: -0.17431
B61: RTR.AX | C61: Rumble Resources Ltd | D61: Diversified Mining | E61: Australia | F61: =AS61/AT61 -> -0.0987213 | G61: =AU61/AV61 -> -0.019379266 | H61: =AX61 -> 53946292 | I61: =(AY61/AZ61)-1 -> -1 | J61: =AV61/AW61 -> -66.729201 | K61: =IFERROR(_xlfn.RANK.EQ(F61,F$3:F$64),"N/A") -> 40 | L61: =IFERROR(_xlfn.RANK.EQ(G61,G$3:G$64),"N/A") -> 37 | M61: =IFERROR(_xlfn.RANK.EQ(H61,H$3:H$64),"N/A") -> 52 | N61: =IFERROR(_xlfn.RANK.EQ(I61,I$3:I$64),"N/A") -> 47 | O61: =IFERROR(_xlfn.RANK.EQ(J61,J$3:J$64),"N/A") -> 59 | P61: =IFERROR(ABS(K$3-K61),"N/A") -> 38 | Q61: =IFERROR(ABS(L$3-L61),"N/A") -> 10 | R61: =IFERROR(ABS(M$3-M61),"N/A") -> 41 | S61: =IFERROR(ABS(N$3-N61),"N/A") -> 2 | T61: =IFERROR(ABS(O$3-O61),"N/A") -> 57 | U61: =SUM(P61:T61) -> 148 | V61: =_xlfn.RANK.EQ(U61,$U$4:$U$64,1) -> 42 | W61: =IF(Y61="Not suitable","-",V61) -> - | Y61: Not Suitable | AS61: -5012420 | AT61: 50773440 | AU61: 101190 | AV61: -5221560 | AW61: 78250 | AX61: 53946292 | AZ61: -0.00547
B62: AZS.AX | C62: Azure Minerals Ltd | D62: Diversified Mining | E62: Australia | F62: =AS62/AT62 -> -0.9381764 | G62: =AU62/AV62 -> -0.0092008797 | H62: =AX62 -> 1651246470 | I62: =(AY62/AZ62)-1 -> -0.057142857 | J62: =AV62/AW62 -> -418.12853 | K62: =IFERROR(_xlfn.RANK.EQ(F62,F$3:F$64),"N/A") -> 58 | L62: =IFERROR(_xlfn.RANK.EQ(G62,G$3:G$64),"N/A") -> 34 | M62: =IFERROR(_xlfn.RANK.EQ(H62,H$3:H$64),"N/A") -> 19 | N62: =IFERROR(_xlfn.RANK.EQ(I62,I$3:I$64),"N/A") -> 24 | O62: =IFERROR(_xlfn.RANK.EQ(J62,J$3:J$64),"N/A") -> 62 | P62: =IFERROR(ABS(K$3-K62),"N/A") -> 56 | Q62: =IFERROR(ABS(L$3-L62),"N/A") -> 7 | R62: =IFERROR(ABS(M$3-M62),"N/A") -> 8 | S62: =IFERROR(ABS(N$3-N62),"N/A") -> 21 | T62: =IFERROR(ABS(O$3-O62),"N/A") -> 60 | U62: =SUM(P62:T62) -> 152 | V62: =_xlfn.RANK.EQ(U62,$U$4:$U$64,1) -> 47 | W62: =IF(Y62="Not suitable","-",V62) -> 47 | Y62: =IF(OR(Z62="Y",AA62="Y"),"Not suitable","") | AS62: -29081470 | AT62: 30997870 | AU62: 267300 | AV62: -29051570 | AW62: 69480 | AX62: 1651246470 | AY62: -0.033 | AZ62: -0.035
B63: STA.AX | C63: Strandline Resources Ltd | D63: Diversified Mining | E63: Australia | F63: =AS63/AT63 -> -0.068907005 | G63: =AU63/AV63 -> -25.221914 | H63: =AX63 -> 1.389436e+08 | I63: =(AY63/AZ63)-1 -> -1 | J63: =AV63/AW63 -> -0.1497672 | K63: =IFERROR(_xlfn.RANK.EQ(F63,F$3:F$64),"N/A") -> 38 | L63: =IFERROR(_xlfn.RANK.EQ(G63,G$3:G$64),"N/A") -> 62 | M63: =IFERROR(_xlfn.RANK.EQ(H63,H$3:H$64),"N/A") -> 40 | N63: =IFERROR(_xlfn.RANK.EQ(I63,I$3:I$64),"N/A") -> 47 | O63: =IFERROR(_xlfn.RANK.EQ(J63,J$3:J$64),"N/A") -> 33 | P63: =IFERROR(ABS(K$3-K63),"N/A") -> 36 | Q63: =IFERROR(ABS(L$3-L63),"N/A") -> 35 | R63: =IFERROR(ABS(M$3-M63),"N/A") -> 29 | S63: =IFERROR(ABS(N$3-N63),"N/A") -> 2 | T63: =IFERROR(ABS(O$3-O63),"N/A") -> 31 | U63: =SUM(P63:T63) -> 133 | V63: =_xlfn.RANK.EQ(U63,$U$4:$U$64,1) -> 34 | W63: =IF(Y63="Not suitable","-",V63) -> - | Y63: Not Suitable | AS63: -11540570 | AT63: 167480360 | AU63: 229551200 | AV63: -9101260 | AW63: 60769380 | AX63: 1.389436e+08 | AZ63: -0.01
B64: PAN.AX | C64: Panoramic Resources Ltd | D64: Diversified Mining | E64: Australia | F64: =AS64/AT64 -> -0.23443772 | G64: =AU64/AV64 -> -2.7180453 | H64: =AX64 -> 1.0393799e+08 | I64: =(AY64/AZ64)-1 -> 0.058201058 | J64: =AV64/AW64 -> -0.16966733 | K64: =IFERROR(_xlfn.RANK.EQ(F64,F$3:F$64),"N/A") -> 48 | L64: =IFERROR(_xlfn.RANK.EQ(G64,G$3:G$64),"N/A") -> 57 | M64: =IFERROR(_xlfn.RANK.EQ(H64,H$3:H$64),"N/A") -> 43 | N64: =IFERROR(_xlfn.RANK.EQ(I64,I$3:I$64),"N/A") -> 18 | O64: =IFERROR(_xlfn.RANK.EQ(J64,J$3:J$64),"N/A") -> 35 | P64: =IFERROR(ABS(K$3-K64),"N/A") -> 46 | Q64: =IFERROR(ABS(L$3-L64),"N/A") -> 30 | R64: =IFERROR(ABS(M$3-M64),"N/A") -> 32 | S64: =IFERROR(ABS(N$3-N64),"N/A") -> 27 | T64: =IFERROR(ABS(O$3-O64),"N/A") -> 33 | U64: =SUM(P64:T64) -> 168 | V64: =_xlfn.RANK.EQ(U64,$U$4:$U$64,1) -> 52 | W64: =IF(Y64="Not suitable","-",V64) -> 52 | Y64: =IF(OR(Z64="Y",AA64="Y"),"Not suitable","") | Z64: =IF(OR(N64="N/A",O64="N/A"),"Y","") | AS64: -33172000 | AT64: 141496000 | AU64: 90163000 | AV64: -33172000 | AW64: 195512000 | AX64: 1.0393799e+08 | AY64: -0.01 | AZ64: -0.00945

Sheet ESG
B1: Company GICS Sector:
B2: Materials | C2: <- Select Industry
B3: ESG Analysis | K3: Relative ESG Analysis
B4: Parameters | C4: Impact | D4: Do they report? | E4: Ranking | F4: Mitigation Plan | G4: Traffic Lights | H4: Improvement over time? | I4: Targets / Goals? | J4: Comments | K4: Parameters | L4: =Peers!C8 -> #VALUE! | M4: =Peers!D8 -> #VALUE! | N4: =Peers!E8 -> #VALUE! | O4: =Peers!F8 -> #VALUE! | P4: =Peers!G8 -> #VALUE! | Q4: =Peers!#REF! -> #REF! | R4: =Peers!#REF! -> #REF! | S4: =Peers!#REF! -> #REF! | T4: AVERAGE
B5: Environmental | K5: Ratios
A6: 1 | B6: CO2 Direct Emissions | C6: =VLOOKUP($B$2,'Sector Impact'!$K$4:$AA$16,A6+1,FALSE) -> Very High | D6: Yes | E6: "Villain" | F6: Yes | H6: Yes | I6: Continue to develop decarbonisation plan and improve energy efficiency. • Embed climate analysis and internal carbon price to inform decision-making. | J6: The increase in total year emissions in FY23 from the previous can be primarily attributed to the increase in diesel consumption as Pilbara Minerals increased overall activity across operations and construction works for the P680 Project. | K6: CO2 Emissions/$Sales | L6: =IFERROR(L12/L$11,"N/A") -> 36.699803 | M6: =IFERROR(M12/M$11,"N/A") -> 200.41408 | N6: =IFERROR(N12/N$11,"N/A") -> 131.67523 | O6: =IFERROR(O12/O$11,"N/A") -> N/A | P6: =IFERROR(P12/P$11,"N/A") -> N/A | Q6: =IFERROR(Q12/Q$11,"N/A") -> N/A | R6: =R12/R$11 -> #DIV/0! | S6: =S12/S$11 -> #DIV/0! | T6: =IFERROR(AVERAGE(L6:Q6),"") -> 122.9297
A7: 2 | B7: Total Water Consumption | C7: =VLOOKUP($B$2,'Sector Impact'!$K$4:$AA$16,A7+1,FALSE) -> Very High | D7: No | E7: N/A | F7: N/A | H7: N/A | J7: Advanced a holistic water balance at the Pilgangoora Operation in 2023 | K7: Water Consumption/$Sales | L7: =IFERROR(L13/L$11,"N/A") -> 1072.8346 | M7: =IFERROR(M13/M$11,"N/A") -> 786.74948 | N7: =IFERROR(N13/N$11,"N/A") -> 2611.1141 | O7: =IFERROR(O13/O$11,"N/A") -> N/A | P7: =IFERROR(P13/P$11,"N/A") -> N/A | Q7: =IFERROR(Q13/Q$11,"N/A") -> N/A | R7: =R13/R$11 -> #DIV/0! | S7: =S13/S$11 -> #DIV/0! | T7: =IFERROR(AVERAGE(L7:Q7),"") -> 1490.2328
A8: 3 | B8: Total Energy Consumption | C8: =VLOOKUP($B$2,'Sector Impact'!$K$4:$AA$16,A8+1,FALSE) -> Very High | D8: No | E8: N/A | F8: Yes | H8: N/A | I8: Net zero operation in the decade commencing 2040 | J8: Updated high-level climate scenario analysis and completed risk assessment in line with the Taskforce on Climate-related Financial Disclosure. | K8: Energy Consumption/$Sales | L8: =IFERROR(L14/L$11,"N/A") -> 370.91634 | M8: =IFERROR(M14/M$11,"N/A") -> 959.28226 | N8: =IFERROR(N14/N$11,"N/A") -> 665.0863 | O8: =IFERROR(O14/O$11,"N/A") -> N/A | P8: =IFERROR(P14/P$11,"N/A") -> N/A | Q8: =IFERROR(Q14/Q$11,"N/A") -> N/A | R8: =R14/R$11 -> #DIV/0! | S8: =S14/S$11 -> #DIV/0! | T8: =IFERROR(AVERAGE(L8:Q8),"N/A") -> 665.09497
A9: 4 | B9: Waste Management | C9: =VLOOKUP($B$2,'Sector Impact'!$K$4:$AA$16,A9+1,FALSE) -> Very High | D9: Yes | E9: Medium High | F9: No | H9: Yes | I9: N/A | J9: In FY23, significant progress was made in waste management including the upgrade to landfill, recycling, and BioFarm operations. The facility is designed to segregate and responsibly dispose, reuse, or recycle various waste streams including metals, aerosols, plastics, batteries, wood, oils, and hydrocarbons. | K9: Waste Production/$Sales | L9: =IFERROR(L15/L$11,"N/A") -> 2.4279035 | M9: =IFERROR(M15/M$11,"N/A") -> 0.62111801 | N9: =IFERROR(N15/N$11,"N/A") -> 1.7933517 | O9: =IFERROR(O15/O$11,"N/A") -> N/A | P9: =IFERROR(P15/P$11,"N/A") -> N/A | Q9: =IFERROR(Q15/Q$11,"N/A") -> N/A | R9: =R15/R$11 -> #DIV/0! | S9: =S15/S$11 -> #DIV/0! | T9: =IFERROR(AVERAGE(L9:Q9),"") -> 1.6141244
A10: 5 | B10: Land Degradation/Deforestation/Biodiversity loss/Animal sufering/… | C10: =VLOOKUP($B$2,'Sector Impact'!$K$4:$AA$16,A10+1,FALSE) -> High | D10: No | H10: N/A | I10: "Zero environmental issues" | J10: To safeguard biodiversity and minimise adverse impacts on the ecosystem, Pilbara Minerals has formulated various management plans and procedures. These include a corporate EMP which outlines the overarching strategies and processes. Additionally, there is a specialised Fauna Management Procedure to protect fauna within and around the operational areas. | K10: Inputs
B11: Social | K11: Net Sales | L11: 4064 | M11: 14490 | N11: 11251 | O11: 4779.1 | P11: 1795.8
A12: 6 | B12: Employee Turnover % | C12: =VLOOKUP($B$2,'Sector Impact'!$K$4:$AA$16,A12+1,FALSE) -> High | H12: N/A | I12: N/A | J12: N/A | K12: CO2 Emissions Total (Tonnes) | L12: 149148 | M12: 2904000 | N12: 1481478 | O12: N/A | P12: N/A
A13: 7 | B13: Salaries & Compensation | C13: =VLOOKUP($B$2,'Sector Impact'!$K$4:$AA$16,A13+1,FALSE) -> High | D13: Yes | E13: Medium | F13: No | H13: Kind of | I13: N/A | J13: Incentive and bonus schemes. | K13: Water Consumption Total (Cubic Meters) | L13: 4360000 | M13: 11400000 | N13: 29377645 | O13: N/A | P13: N/A
A14: 8 | B14: Reputation | C14: =VLOOKUP($B$2,'Sector Impact'!$K$4:$AA$16,A14+1,FALSE) -> Medium | D14: No | E14: Medium | F14: No | H14: Yes | I14: N/A | J14: N/A | K14: Energy Consumption Total (Gigajoules) | L14: 1507404 | M14: 13900000 | N14: 7482886 | O14: N/A | P14: N/A
A15: 9 | B15: Discrimination Events | C15: =VLOOKUP($B$2,'Sector Impact'!$K$4:$AA$16,A15+1,FALSE) -> High | D15: No | E15: Medium High | F15: Yes | H15: No | I15: N/A | J15: Increased spend with over $5M in procurement and contracts awarded to Aboriginal and Torres Strait Islander businesses. | K15: Waste Production Total (Tonnes) | L15: 9867 | M15: 9000 | N15: 20177 | O15: N/A | P15: N/A
A16: 10 | B16: Work Safety | C16: =VLOOKUP($B$2,'Sector Impact'!$K$4:$AA$16,A16+1,FALSE) -> Low | D16: Yes | E16: Medium High | F16: Yes | H16: Yes | J16: Recorded zero fatalities and permanent injuries among employees and contractors. | K16: ESG Scores
A17: 11 | B17: Damage to consumer health | C17: =VLOOKUP($B$2,'Sector Impact'!$K$4:$AA$16,A17+1,FALSE) -> Very High | D17: Yes | E17: "Best in class" | F17: Yes | H17: Yes | J17: N/A | K17: Refinitiv | L17: 44 | M17: 72 | N17: 81 | O17: N/A | P17: N/A
A18: 12 | B18: PXP? | C18: =VLOOKUP($B$2,'Sector Impact'!$K$4:$AA$16,A18+1,FALSE) -> Medium | D18: Yes | E18: Medium | F18: Yes | H18: Yes | I18: N/A | J18: A team of trained Mental Health First Aiders on site and in Perth who can be accessed by employees at any time A Lithium Bonus scheme connected to the price of spodumene | K18: Sustainalytics | L18: 40.2 (severe risk) | M18: 23.7 (medium risk) | N18: 30.8 (medium risk) | O18: 21.8 (medium risk) | P18: 20.8 (medium risk)
A19: 13 | B19: Supply chain | C19: =VLOOKUP($B$2,'Sector Impact'!$K$4:$AA$16,A19+1,FALSE) -> Medium | D19: Yes | E19: Medium | F19: No | H19: No | J19: Commence construction of the Mid-stream Demonstration Plant, in joint venture with Calix, with the aim of validating Calix’s patented electric-kiln technology in calcining spodumene concentrate at a lower cost and reduced carbon emissions intensity, thereby further enhancing the sustainability of the battery materials supply chain. | K19: ISS | L19: C | M19: C- | N19: C | O19: C | P19: C
A20: 14 | B20: Community involvement | C20: =VLOOKUP($B$2,'Sector Impact'!$K$4:$AA$16,A20+1,FALSE) -> Very High | D20: Yes | E20: Medium | F20: No | H20: Yes | I20: N/A | J20: Cultural Awareness Training sessions held for 292 employees and organization of two on-country cultural awareness overnight camps. | K20: CDP | L20: F | M20: B | N20: B/B- | O20: N/A | P20: N/A
A21: 15 | B21: Public Sector | C21: =VLOOKUP($B$2,'Sector Impact'!$K$4:$AA$16,A21+1,FALSE) -> High | D21: Yes | E21: Medium | F21: No | H21: No | J21: N/A
A22: 16 | B22: Litigation | C22: =VLOOKUP($B$2,'Sector Impact'!$K$4:$AA$16,A22+1,FALSE) -> Medium | D22: Yes | E22: Medium | F22: No | H22: No | I22: N/A | J22: No relevant Litigations
B23: Corporate Governance | K23: PARAMETERS
A24: 17 | B24: Diversity (Gender, Age, Industry, Region) | E24: Medium High | F24: Yes | H24: No | J24: Improve female representation at senior manager and executive manager level during the period 2019 to 2023 (33%), and promotion of six female candidates to key senior leadership positions. | K24: IMPACT | L24: RANKING | M24: MITIGATION PLAN | P24: TRAFFIC
A25: 18 | B25: % Independence | E25: "Best in class" | F25: No | H25: No | J25: 5/6 Directors were independent (100% of Non-Executive Directors were independent) | K25: Low | L25: "Best in class" | M25: Is there evidence of a plan/program ?
A26: 19 | B26: average time as independent directors | E26: Medium | F26: Yes | H26: Yes | J26: similar to the industry average | K26: Medium | L26: Medium High
A27: 20 | B27: Recent departures of directors / C-level executives? | E27: "Best in class" | F27: Yes | H27: Yes | J27: Recent departure of the Managing Director/CEO (2022) | K27: High | L27: Medium
A28: 21 | B28: CEO/Chairman duality | E28: Medium High | F28: No | H28: No | J28: They are both the same | K28: Very high | L28: "Villain"
A29: 22 | B29: Transparency (ESG, segments, acquisitions, other) | E29: Medium | F29: Yes | H29: No | J29: N/A
A30: 23 | B30: Time taken to report after the end of the quarter / year | E30: Medium | F30: No | H30: No | J30: N/A
A31: 24 | B31: Additional participation of the CEO in other boards or excessive participation of Ch. | E31: Medium High | F31: No | H31: No | J31: No evidence of it happening.
A32: 25 | B32: Audit / Consulting | D32: Yes | E32: Medium High | F32: No | H32: Yes | J32: N/A
A33: 26 | B33: ESG-compensation related | D33: Yes | E33: "Best in class" | F33: Yes | H33: No | J33: The Company’s Audit and Risk Committee Charter is disclosed on the Company’s website but the information is not clear enough
A34: 27 | B34: Management compensation schemes | D34: Yes | E34: Medium High | F34: Yes | H34: No | J34: Above average base salary compared to its peers.

Sheet DCF
A1: VALUATION MODEL
G3: Short Term | K3: Long Term
A4: Section | B4: Line # | C4: ITEM | D4: =OP!J21-2&" (Real)" -> 2021 (Real) | E4: =OP!J21-1&" (Real)" -> 2022 (Real) | F4: =OP!J21&" (Real)" -> 2023 (Real) | G4: =OP!J21+1 -> 2024 | H4: =G4+1 -> 2025 | I4: =H4+1 -> 2026 | J4: =I4+1 -> 2027 | K4: =J4+1 -> 2028 | L4: =K4+1 -> 2029 | M4: =L4+1 -> 2030 | N4: =M4+1 -> 2031 | O4: =N4+1 -> 2032 | ... AF4: =AE4+1 -> 2049
A5: INCOME STATEMENT | B5: 1 | C5: Growth | D5: ='Fin. Data'!D6 -> 1.0903686 | E5: =+E6/D6-1 -> 5.7667804 | F5: =+F6/E6-1 -> 2.4162744 | G5: =Assumptions!S182 -> -0.41902793 | H5: =D136 -> 0.10854151 | I5: =[3]Assumptions!U182 -> 0.40692169 | J5: =[3]Assumptions!V182 -> 0.19813857 | K5: =[3]Assumptions!W182 -> 0.1222007 | L5: =[3]Assumptions!X182 -> -0.086028585 | M5: =[3]Assumptions!Y182 -> 0.20099174 | N5: =[3]Assumptions!Z182 -> 0.11512578 | O5: =[3]Assumptions!AA182 -> 0.085566695 | P5: =[3]Assumptions!AB182 -> 0.16578895 | ... AE5: =[3]Assumptions!AQ182 -> 0.062341234 | AF5: 0.02
B6: 2 | C6: Revenues/Sales | D6: ='Inputs (AUD)'!D6 -> 175.8 | E6: ='Inputs (AUD)'!C6 -> 1189.6 | F6: ='Inputs (AUD)'!B6 -> 4064 | G6: =F6*(1+G5) -> 2361.0705 | H6: =G6*(1+H5) -> 2617.3447 | I6: =H6*(1+I5) -> 3682.399 | J6: =I6*(1+J5) -> 4412.0242 | K6: =J6*(1+K5) -> 4951.1767 | L6: =K6*(1+L5) -> 4525.234 | M6: =L6*(1+M5) -> 5434.7686 | N6: =M6*(1+N5) -> 6060.4506 | ... AF6: =AE6*(1+AF5) -> 25288.876
B7: 3 | C7: Operating Margin | D7: =D8/D6 -> -0.19169511 | E7: =E8/E6 -> 0.61054136 | F7: =F8/F6 -> 0.7621063 | G7: 0.55 | H7: 0.65 | I7: 0.65 | J7: 0.6 | K7: 0.58 | L7: =M7+1.75% -> 0.6 | M7: =N7+1.75% -> 0.5825 | N7: =O7+1.75% -> 0.565 | O7: =P7+1.75% -> 0.5475 | P7: =Q7+1.75% -> 0.53 | Q7: =R7+1.75% -> 0.5125 | R7: =S7+1.75% -> 0.495 | S7: =T7+1.75% -> 0.4775 | ... AE7: =AF7+1.75% -> 0.2675 | AF7: 0.25
B8: 4 | C8: EBIT | D8: ='Fin. Data'!D16 -> -33.7 | E8: ='Fin. Data'!C16 -> 726.3 | F8: ='Fin. Data'!B16 -> 3097.2 | G8: =G7*G6 -> 1298.5888 | H8: =H7*H6 -> 1701.274 | I8: =I7*I6 -> 2393.5593 | J8: =J7*J6 -> 2647.2145 | K8: =K7*K6 -> 2871.6825 | L8: =L7*L6 -> 2715.1404 | M8: =M7*M6 -> 3165.7527 | N8: =N7*N6 -> 3424.1546 | ... AF8: =AF7*AF6 -> 6322.219
B9: 5a | C9: (Depreciation) | D9: =-'Fin. Data'!D17 -> -0.5 | E9: =-'Fin. Data'!C17 -> -0.7 | F9: =-'Fin. Data'!B17 -> -1.5 | G9: =$D$53*DCF!F40 -> -46.179 | H9: =$D$53*DCF!G40 -> -51.137248 | I9: =$D$53*DCF!H40 -> -56.633672 | J9: =$D$53*DCF!I40 -> -64.36671 | K9: =$E$53*DCF!J40 -> -98.175947 | L9: =$E$53*DCF!K40 -> -116.00018 | M9: =$E$53*DCF!L40 -> -132.29103 | N9: =$E$53*DCF!M40 -> -151.85619 | O9: =$E$53*DCF!N40 -> -173.67381 | P9: =$E$53*DCF!O40 -> -197.3583 | Q9: =$E$53*DCF!P40 -> -224.96941 | R9: =$E$53*DCF!Q40 -> -255.55943 | ... AF9: =$E$53*DCF!AE40 -> -1087.1207 | AG9: =SUM(D9:AF9) -> -10413.745
B10: 5b | C10: Amortization | D10: 0 | E10: 0 | F10: 0 | G10: =F38*0 -> 0 | H10: =G38*0 -> 0 | I10: =H38*0 -> 0 | J10: =I38*0 -> 0 | K10: =J38*0 -> 0 | L10: =K38*0 -> 0 | M10: =L38*0 -> 0 | N10: =M38*0 -> 0 | ... AF10: =AE38*0 -> 0
B11: 5c | C11: (Stock based compensation) | D11: =D20 -> 0 | E11: =E20 -> 0 | F11: =F20 -> -12.8 | G11: =G6*$D$55 -> 0 | H11: =H6*$D$55 -> 0 | I11: =I6*$D$55 -> 0 | J11: =J6*$D$55 -> 0 | K11: =K6*$E$55 -> -99.023534 | L11: =L6*$E$55 -> -90.50468 | M11: =M6*$E$55 -> -108.69537 | N11: =N6*$E$55 -> -121.20901 | O11: =O6*$E$55 -> -131.58047 | P11: =P6*$E$55 -> -153.39505 | Q11: =Q6*$E$55 -> -169.94456 | R11: =R6*$E$55 -> -187.39488 | ... AF11: =AF6*$E$55 -> -505.77752
B12: 6 | C12: EBITDA | D12: =D8-D9-D10 -> -33.2 | E12: =E8-E9-E10 -> 727 | F12: =F8-F9-F10 -> 3098.7 | G12: =G8-G9-G10 -> 1344.7678 | H12: =H8-H9-H10 -> 1752.4113 | I12: =I8-I9-I10 -> 2450.193 | J12: =J8-J9-J10 -> 2711.5813 | K12: =K8-K9-K10 -> 2969.8584 | ... AF12: =AF8-AF9-AF10 -> 7409.3397
B13: 7 | C13: (Net financing cost) | D13: ='Fin. Data'!D14 -> -15.1 | E13: ='Fin. Data'!C14 -> -12.5 | F13: ='Fin. Data'!B14 -> 44.9 | G13: =F43*$D$58-F44*$D$57 -> -9.44 | H13: =G43*$D$58-G44*$D$57 -> -2.6895356 | I13: =H43*$D$58-H44*$D$57 -> -3.5048225 | J13: =I43*$D$58-I44*$D$57 -> -4.900386 | K13: =J43*$E$58-J44*$E$57 -> -5.4231625 | L13: =K43*$E$58-K44*$E$57 -> -8.3156036 | M13: =L43*$E$58-L44*$E$57 -> -7.9271936 | N13: =M43*$E$58-M44*$E$57 -> -9.2345225 | O13: =N43*$E$58-N44*$E$57 -> -10.01283 | P13: =O43*$E$58-O44*$E$57 -> -10.571929 | Q13: =P43*$E$58-P44*$E$57 -> -11.934516 | R13: =Q43*$E$58-Q44*$E$57 -> -12.823437 | ... AF13: =AE43*$E$58-AE44*$E$57 -> -21.363993
B14: 8 | C14: Other income/(cost) | D14: ='Fin. Data'!D15 -> -1.3 | E14: ='Fin. Data'!C15 -> 5.6 | F14: ='Fin. Data'!B15 -> 114.7 | G14: =AVERAGE(D14:F14)*(1+G5) -> 23.045226 | H14: =AVERAGE(E14:G14)*(1+H5) -> 52.968044 | I14: =AVERAGE(F14:H14)*(1+I5) -> 89.439545 | J14: =AVERAGE(G14:I14)*(1+J5) -> 66.078466 | K14: =AVERAGE(H14:J14)*(1+K5) -> 77.987733 | L14: =AVERAGE(I14:K14)*(1+L5) -> 71.139192 | M14: =AVERAGE(J14:L14)*(1+M5) -> 86.153299 | N14: =AVERAGE(K14:M14)*(1+N5) -> 87.455681 | ... AF14: =AVERAGE(AC14:AE14)*(1+AF5) -> 173.10354
B15: 9 | C15: Earnings before taxes | D15: =D8+D13+D14 -> -50.1 | E15: =E8+E13+E14 -> 719.4 | F15: =F8+F13+F14 -> 3256.8 | G15: =G8+G13+G14 -> 1312.194 | H15: =H8+H13+H14 -> 1751.5525 | I15: =I8+I13+I14 -> 2479.4941 | J15: =J8+J13+J14 -> 2708.3926 | K15: =K8+K13+K14 -> 2944.2471 | ... AF15: =AF8+AF13+AF14 -> 6473.9585
B16: 10 | C16: (Income tax) | D16: ='Fin. Data'!D21 -> 0 | E16: ='Fin. Data'!C21 -> -163.2 | F16: ='Fin. Data'!B21 -> -980.4 | G16: =-(1*$D$56)*G15 -> -328.0485 | H16: =-(1*$D$56)*H15 -> -437.88813 | I16: =-(1*$D$56)*I15 -> -619.87351 | J16: =-(1*$D$56)*J15 -> -677.09816 | K16: =-(1*$E$56)*K15 -> -883.27412 | L16: =-(1*$E$56)*L15 -> -833.38919 | M16: =-(1*$E$56)*M15 -> -973.19365 | N16: =-(1*$E$56)*N15 -> -1050.7127 | O16: =-(1*$E$56)*O15 -> -1104.1698 | P16: =-(1*$E$56)*P15 -> -1246.8829 | Q16: =-(1*$E$56)*Q15 -> -1333.6565 | R16: =-(1*$E$56)*R15 -> -1419.8762 | ... AF16: =-(1*$E$56)*AF15 -> -1942.1876
B17: 11 | C17: Net income | D17: ='Fin. Data'!D23 -> -51.4 | E17: ='Fin. Data'!C23 -> 561.8 | F17: ='Fin. Data'!B23 -> 2391.1 | G17: =G16+G15 -> 984.1455 | H17: =H16+H15 -> 1313.6644 | I17: =I16+I15 -> 1859.6205 | J17: =J16+J15 -> 2031.2945 | K17: =K16+K15 -> 2060.9729 | L17: =L16+L15 -> 1944.5748 | M17: =M16+M15 -> 2270.7852 | N17: =N16+N15 -> 2451.663 | ... AF17: =AF16+AF15 -> 4531.771
A19: CASH FLOW STATEMENT | B19: 12 | C19: Operating cash flows before WK | D19: ='Inputs (AUD)'!D59-'Inputs (AUD)'!D62 -> 24 | E19: ='Inputs (AUD)'!C59-'Inputs (AUD)'!C62 -> 657.2 | F19: ='Inputs (AUD)'!B59-'Inputs (AUD)'!B62 -> 3414.9 | G19: =G17-G10-G9-G11 -> 1030.3245 | H19: =H17-H10-H9-H11 -> 1364.8016 | I19: =I17-I10-I9-I11 -> 1916.2542 | J19: =J17-J10-J9-J11 -> 2095.6612 | K19: =K17-K10-K9-K11 -> 2258.1724 | L19: =L17-L10-L9-L11 -> 2151.0796 | M19: =M17-M10-M9-M11 -> 2511.7716 | N19: =N17-N10-N9-N11 -> 2724.7282 | ... AF19: =AF17-AF10-AF9-AF11 -> 6124.6692
B20: 13 | C20: (Stock-based compensation) | D20: =-'Inputs (AUD)'!D103 -> 0 | E20: =-'Inputs (AUD)'!C103 -> 0 | F20: =-'Inputs (AUD)'!B103 -> -12.8 | G20: =G11 -> 0 | H20: =H11 -> 0 | I20: =I11 -> 0 | J20: =J11 -> 0 | K20: =K11 -> -99.023534 | L20: =L11 -> -90.50468 | M20: =M11 -> -108.69537 | N20: =N11 -> -121.20901 | ... AF20: =AF11 -> -505.77752
B21: 14 | C21: (Working Capital Flows) | D21: ='Inputs (AUD)'!D62 -> -5.2 | E21: ='Inputs (AUD)'!C62 -> -9.6 | F21: ='Inputs (AUD)'!B62 -> 41.8 | G21: =$D$60*(G6-F6) -> 42.573237 | H21: =$D$60*(H6-G6) -> -6.4068538 | I21: =$D$60*(I6-H6) -> -26.626358 | J21: =$D$60*(J6-I6) -> -18.240632 | K21: =$E$60*(K6-J6) -> -24.261861 | L21: =$E$60*(L6-K6) -> 19.167423 | M21: =$E$60*(M6-L6) -> -40.929059 | N21: =$E$60*(N6-M6) -> -28.155688 | O21: =$E$60*(O6-N6) -> -23.335773 | P21: =$E$60*(P6-O6) -> -49.082822 | Q21: =$E$60*(Q6-P6) -> -37.236397 | R21: =$E$60*(R6-Q6) -> -39.263202 | ... AF21: =$E$60*(AF6-AE6) -> -22.313714
B22: 15 | C22: -Total Operating Cash Flow | D22: =D19+D20+D21 -> 18.8 | E22: =E19+E20+E21 -> 647.6 | F22: =F19+F20+F21 -> 3443.9 | G22: =G19+G20+G21 -> 1072.8977 | H22: =H19+H20+H21 -> 1358.3948 | I22: =I19+I20+I21 -> 1889.6279 | J22: =J19+J20+J21 -> 2077.4205 | K22: =K19+K20+K21 -> 2134.887 | ... AF22: =AF19+AF20+AF21 -> 5596.578
B23: 16 | C23: (CAPEX) | D23: ='Fin. Data'!D32 -> -20.5 | E23: ='Fin. Data'!C32 -> -128.3 | F23: ='Fin. Data'!B32 -> -385.5 | G23: =G6*$D$62 -> -165.27494 | H23: =H6*$D$62 -> -183.21413 | I23: =I6*$D$62 -> -257.76793 | J23: =J6*$D$62 -> -308.8417 | K23: =K6*$E$62 -> -445.6059 | L23: =L6*$E$62 -> -407.27106 | M23: =M6*$E$62 -> -489.12918 | N23: =N6*$E$62 -> -545.44055 | O23: =O6*$E$62 -> -592.1121 | P23: =P6*$E$62 -> -690.27774 | Q23: =Q6*$E$62 -> -764.75054 | R23: =R6*$E$62 -> -843.27694 | ... AF23: =AF6*$E$62 -> -2275.9988 | AG23: =SUM(D23:AF23) -> -28449.017
B24: 17 | C24: Aquisitions | D24: ='Fin. Data'!D33 -> -210.3 | E24: ='Fin. Data'!C33 -> -76.2 | F24: ='Fin. Data'!B33 -> -22.4 | G24: =-G6*2% -> -47.22141 | H24: =-H6*2% -> -52.346893 | I24: =-I6*2% -> -73.647979 | J24: =J6*$D$63 -> 0 | K24: =K6*$E$63 -> 0 | L24: =L6*$E$63 -> 0 | M24: =M6*$E$63 -> 0 | N24: =-N6*1% -> -60.604506 | O24: =-O6*2% -> -131.58047 | P24: =-P6*3% -> -230.09258 | Q24: =-Q6*4% -> -339.88913 | R24: =-R6*4.5% -> -421.63847 | S24: =S6*$E$63 -> 0 | T24: =T6*$E$63 -> 0 | U24: =U6*$E$63 -> 0 | V24: =V6*$E$63 -> 0 | W24: =W6*$E$63 -> 0 | X24: =-X6*1% -> -155.47768 | Y24: =-Y6*2% -> -334.68585 | Z24: =-Z6*3% -> -538.96734 | AA24: =-AA6*3.5% -> -673.45638 | AB24: =-AB6*3.5% -> -719.68331 | AC24: =-AC6*3.5% -> -767.47566 | AD24: =-AD6*3.5% -> -816.83316 | AE24: =-AE6*3.5% -> -867.75555 | AF24: =-AF6*3.5% -> -885.11066 | AH24: =AG9-AG23 -> 18035.272
B25: 18 | C25: (Other investing flows) | D25: ='Inputs (AUD)'!D67 -> 0 | E25: ='Inputs (AUD)'!C67 -> 0 | F25: ='Inputs (AUD)'!B67 -> -0.1 | G25: =(1+G5)*AVERAGE(D25:F25) -> -0.019365736 | H25: =(1+H5)*AVERAGE(E25:G25) -> -0.044107291 | I25: =(1+I5)*AVERAGE(F25:H25) -> -0.076664582 | J25: =(1+J5)*AVERAGE(G25:I25) -> -0.055968092 | K25: =(1+K5)*AVERAGE(H25:J25) -> -0.066112571 | L25: =(1+L5)*AVERAGE(I25:K25) -> -0.060549158 | M25: =(1+M5)*AVERAGE(J25:L25) -> -0.073112302 | N25: =(1+N5)*AVERAGE(K25:M25) -> -0.074257723 | ... AF25: =(1+AF5)*AVERAGE(AC25:AE25) -> -0.14700353
B26: 19 | C26: -Total Investing Flows | D26: =D23+D24+D25 -> -230.8 | E26: =E23+E24+E25 -> -204.5 | F26: =F23+F24+F25 -> -408 | G26: =G23+G24+G25 -> -212.51571 | H26: =H23+H24+H25 -> -235.60513 | I26: =I23+I24+I25 -> -331.49257 | J26: =J23+J24+J25 -> -308.89766 | K26: =K23+K24+K25 -> -445.67202 | ... AF26: =AF23+AF24+AF25 -> -3161.2565
B27: 20 | C27: (Flows related to leases) | D27: ='Inputs (AUD)'!D71+'Inputs (AUD)'!D72 -> -20.048 | E27: ='Inputs (AUD)'!C71+'Inputs (AUD)'!C72 -> -26.864 | F27: ='Inputs (AUD)'!B71+'Inputs (AUD)'!B72 -> -54.631 | G27: 0 | H27: 0 | I27: 0 | J27: 0 | K27: 0 | L27: 0 | M27: 0 | N27: 0 | O27: 0 | P27: 0 | Q27: 0 | R27: 0 | S27: 0 | T27: 0 | U27: 0 | V27: 0 | W27: 0 | X27: 0 | Y27: 0 | Z27: 0 | AA27: 0 | AB27: 0 | AC27: 0 | AD27: 0 | AE27: 0 | AF27: 0
B28: 21 | C28: Flows related to debt | D28: =+SUM('Inputs (AUD)'!D69:D70) -> 6.2 | E28: =+SUM('Inputs (AUD)'!C69:C70) -> 57.5 | F28: =+SUM('Inputs (AUD)'!B69:B70) -> 51.3 | G28: =G44-F44 -> -337.52322 | H28: =H44-G44 -> 40.76435 | I28: =I44-H44 -> 69.778173 | J28: =J44-I44 -> 26.138825 | K28: =K44-J44 -> 144.62206 | L28: =L44-K44 -> -19.420501 | M28: =M44-L44 -> 65.366445 | N28: =N44-M44 -> 38.915383 | ... AF28: =AF44-AE44 -> -30.892097
B29: 22 | C29: (Repurchases)/Issuance of stock | D29: ='Fin. Data'!D28 -> 239.7 | E29: ='Fin. Data'!C28 -> 3.6 | F29: ='Fin. Data'!B28 -> 1.2 | G29: =-G17*$D$65 -> -39.36582 | H29: =-H17*$D$65 -> -52.546576 | I29: =-I17*$D$65 -> -74.384822 | J29: =-J17*$D$65 -> -81.251779 | K29: =-K17*$E$65 -> -103.04865 | L29: =-L17*$E$65 -> -97.228739 | M29: =-M17*$E$65 -> -113.53926 | N29: =-N17*$E$65 -> -122.58315 | O29: =-O17*$E$65 -> -128.81981 | P29: =-P17*$E$65 -> -145.46967 | Q29: =-Q17*$E$65 -> -155.59326 | R29: =-R17*$E$65 -> -165.65222 | ... AF29: =-AF17*$E$65 -> -226.58855
B30: 23 | C30: (Dividends) | D30: ='Fin. Data'!D27 -> 0 | E30: ='Fin. Data'!C27 -> 0 | F30: ='Fin. Data'!B27 -> -329.8 | G30: =-$D$64*G17 -> -98.41455 | H30: =-$D$64*H17 -> -131.36644 | I30: =-$D$64*I17 -> -185.96205 | J30: =-$D$64*J17 -> -203.12945 | K30: =-$E$64*K17 -> -370.97513 | L30: =-$E$64*L17 -> -350.02346 | M30: =-$E$64*M17 -> -408.74133 | N30: =-$E$64*N17 -> -441.29934 | O30: =-$E$64*O17 -> -463.75131 | P30: =-$E$64*P17 -> -523.69081 | Q30: =-$E$64*Q17 -> -560.13574 | R30: =-$E$64*R17 -> -596.348 | ... AF30: =-$E$64*AF17 -> -815.71877
B31: 24 | C31: Other financing flows | D31: ='Inputs (AUD)'!D75 -> 6.848 | E31: ='Inputs (AUD)'!C75 -> 11.264 | F31: ='Inputs (AUD)'!B75 -> 16.831 | G31: =(1+G5)*AVERAGE(D31:F31) -> 6.766969 | H31: =(1+H5)*AVERAGE(E31:G31) -> 12.88198 | I31: =(1+I5)*AVERAGE(F31:H31) -> 17.108144 | J31: =(1+J5)*AVERAGE(G31:I31) -> 14.68003 | K31: =(1+K5)*AVERAGE(H31:J31) -> 16.709626 | L31: =(1+L5)*AVERAGE(I31:K31) -> 14.775201 | M31: =(1+M5)*AVERAGE(J31:L31) -> 18.481204 | N31: =(1+N5)*AVERAGE(K31:M31) -> 18.572803 | ... AF31: =(1+AF5)*AVERAGE(AC31:AE31) -> 36.774801
B32: 25 | C32: -Total Financing flows | D32: =D27+D28+D29+D30+D31 -> 232.7 | E32: =E27+E28+E29+E30+E31 -> 45.5 | F32: =F27+F28+F29+F30+F31 -> -315.1 | G32: =G27+G28+G29+G30+G31 -> -468.53662 | H32: =H27+H28+H29+H30+H31 -> -130.26669 | I32: =I27+I28+I29+I30+I31 -> -173.46056 | J32: =J27+J28+J29+J30+J31 -> -243.56237 | K32: =K27+K28+K29+K30+K31 -> -312.69209 | ... AF32: =AF27+AF28+AF29+AF30+AF31 -> -1036.4246
A34: SUMMARY | B34: 26 | C34: Cash before shareholder returns | D34: =D22+D26+D27+D28+D31 -> -219 | E34: =E22+E26+E27+E28+E31 -> 485 | F34: =F22+F26+F27+F28+F31 -> 3049.4 | G34: =G22+G26+G27+G28+G31 -> 529.62577 | H34: =H22+H26+H27+H28+H31 -> 1176.436 | I34: =I22+I26+I27+I28+I31 -> 1645.0216 | J34: =J22+J26+J27+J28+J31 -> 1809.3417 | K34: =K22+K26+K27+K28+K31 -> 1850.5467 | ... AF34: =AF22+AF26+AF27+AF28+AF31 -> 2441.2042
B35: 27 | C35: Returns to shareholders | D35: =-1*(D29+D30) -> -239.7 | E35: =-1*(E29+E30) -> -3.6 | F35: =-1*(F29+F30) -> 328.6 | G35: =-1*(G29+G30) -> 137.78037 | H35: =-1*(H29+H30) -> 183.91302 | I35: =-1*(I29+I30) -> 260.34688 | J35: =-1*(J29+J30) -> 284.38123 | K35: =-1*(K29+K30) -> 474.02378 | ... AF35: =-1*(AF29+AF30) -> 1042.3073
B36: 28 | C36: Excess cash acumulation | D36: =D34-D35 -> 20.7 | E36: =E34-E35 -> 488.6 | F36: =F34-F35 -> 2720.8 | G36: =G34-G35 -> 391.8454 | H36: =H34-H35 -> 992.52298 | I36: =I34-I35 -> 1384.6747 | J36: =J34-J35 -> 1524.9605 | K36: =K34-K35 -> 1376.5229 | ... AF36: =AF34-AF35 -> 1398.8969
A38: BALANCE SHEET | B38: 29 | C38: Intangible assets | D38: ='Inputs (AUD)'!D91 -> 0 | E38: ='Inputs (AUD)'!C91 -> 0 | F38: ='Inputs (AUD)'!B91 -> 0 | G38: =+F38+(-G10) -> 0 | H38: =+G38+(-H10) -> 0 | I38: =+H38+(-I10) -> 0 | J38: =+I38+(-J10) -> 0 | K38: =+J38+(-K10) -> 0 | L38: =+K38+(-L10) -> 0 | M38: =+L38+(-M10) -> 0 | N38: =+M38+(-N10) -> 0 | ... AF38: =+AE38+(-AF10) -> 0 | AG38: =SUM(G38:AF38) -> 0
B39: 30 | C39: Accumulated amortization | D39: 0 | E39: 0 | F39: 0 | G39: =F39-G10 -> 0 | H39: =G39-H10 -> 0 | I39: =H39-I10 -> 0 | J39: =I39-J10 -> 0 | K39: =J39-K10 -> 0 | L39: =K39-L10 -> 0 | M39: =L39-M10 -> 0 | N39: =M39-N10 -> 0 | ... AF39: =AE39-AF10 -> 0 | AG39: =SUM(G39:AF39) -> 0
B40: 31 | C40: PPE+Right of use Assets | D40: ='Inputs (AUD)'!D95 -> 0 | E40: ='Inputs (AUD)'!C95 -> 1003.7 | F40: ='Inputs (AUD)'!B95 -> 1539.3 | G40: =F40+(-G23) -> 1704.5749 | H40: =G40+(-H23) -> 1887.7891 | I40: =H40+(-I23) -> 2145.557 | J40: =I40+(-J23) -> 2454.3987 | K40: =J40+(-K23) -> 2900.0046 | L40: =K40+(-L23) -> 3307.2756 | M40: =L40+(-M23) -> 3796.4048 | N40: =M40+(-N23) -> 4341.8454 | ... AF40: =AE40+(-AF23) -> 29454.017 | AG40: =SUM(G40:AF40) -> 290010.15
B41: 32 | C41: Accumulated depreciation | D41: ='Inputs (AUD)'!D93 -> 0 | E41: ='Inputs (AUD)'!C93 -> -74.3 | F41: ='Inputs (AUD)'!B93 -> -163.8 | G41: =F41-G9 -> -117.621 | H41: =G41-H9 -> -66.483752 | I41: =H41-I9 -> -9.8500801 | J41: =I41-J9 -> 54.51663 | K41: =J41-K9 -> 152.69258 | L41: =K41-L9 -> 268.69276 | M41: =L41-M9 -> 400.98379 | N41: =M41-N9 -> 552.83998 | ... AF41: =AE41-AF9 -> 10247.245 | AG41: =SUM(G41:AF41) -> 77540.977
A43: CASH & DEBT & DISCOUNTING | B43: 33 | C43: Ending cash balance | D43: ='Fin. Data'!D39 -> 79 | E43: =E36+D43 -> 567.6 | F43: =F36+E43 -> 3288.4 | G43: =G36+F43 -> 3680.2454 | H43: =H36+G43 -> 4672.7684 | I43: =I36+H43 -> 6057.4431 | J43: =J36+I43 -> 7582.4036 | K43: =K36+J43 -> 8958.9265 | L43: =L36+K43 -> 10179.44 | ... AF43: =AF36+AE43 -> 46931.208
B44: 34 | C44: Total Debt | D44: ='Fin. Data'!D58 -> 166.9 | E44: ='Fin. Data'!C58 -> 292 | F44: ='Fin. Data'!B58 -> 472 | G44: =G12*$D$68 -> 134.47678 | H44: =H12*$D$68 -> 175.24113 | I44: =I12*$D$68 -> 245.0193 | J44: =J12*$D$68 -> 271.15813 | K44: =K12*$E$68 -> 415.78018 | L44: =L12*$E$68 -> 396.35968 | M44: =M12*$E$68 -> 461.72612 | N44: =N12*$E$68 -> 500.64151 | O44: =O12*$E$68 -> 528.59647 | P44: =P12*$E$68 -> 596.72581 | Q44: =Q12*$E$68 -> 641.17184 | R44: =R12*$E$68 -> 685.10156 | ... AF44: =AF12*$E$68 -> 1037.3076
B45: 35 | C45: Discount factor | F45: =1/((1+$F$50)^G50) -> 1 | G45: =1/((1+$F$50)^G49) -> 0.91324201 | H45: =1/((1+$F$50)^H49) -> 0.83401097 | I45: =1/((1+$F$50)^I49) -> 0.76165385 | J45: =1/((1+$F$50)^J49) -> 0.69557429 | K45: =1/((1+$F$50)^K49) -> 0.63522767 | L45: =1/((1+$F$50)^L49) -> 0.58011659 | M45: =1/((1+$F$50)^M49) -> 0.52978684 | N45: =1/((1+$F$50)^N49) -> 0.4838236 | ... AF45: =1/((1+$F$50)^AF49) -> 0.094456729
B46: 36 | C46: DF + 0.1% | E46: +0.1% | F46: =1/((1+$F$50+0.001)^G50) -> 1 | G46: =1/((1+$F$50+0.001)^G49) -> 0.91240876 | H46: =1/((1+$F$50+0.001)^H49) -> 0.83248974 | I46: =1/((1+$F$50+0.001)^I49) -> 0.75957093 | J46: =1/((1+$F$50+0.001)^J49) -> 0.69303917 | K46: =1/((1+$F$50+0.001)^K49) -> 0.63233501 | L46: =1/((1+$F$50+0.001)^L49) -> 0.576948 | M46: =1/((1+$F$50+0.001)^M49) -> 0.52641241 | N46: =1/((1+$F$50+0.001)^N49) -> 0.4803033 | ... AF46: =1/((1+$F$50+0.001)^AF49) -> 0.092241338
B47: 37 | C47: DF+0.5% | E47: +0.5% | F47: =1/((1+$F$50+0.005)^G50) -> 1 | G47: =1/((1+$F$50+0.005)^G49) -> 0.90909091 | H47: =1/((1+$F$50+0.005)^H49) -> 0.82644628 | I47: =1/((1+$F$50+0.005)^I49) -> 0.7513148 | J47: =1/((1+$F$50+0.005)^J49) -> 0.68301346 | K47: =1/((1+$F$50+0.005)^K49) -> 0.62092132 | L47: =1/((1+$F$50+0.005)^L49) -> 0.56447393 | M47: =1/((1+$F$50+0.005)^M49) -> 0.51315812 | N47: =1/((1+$F$50+0.005)^N49) -> 0.46650738 | ... AF47: =1/((1+$F$50+0.005)^AF49) -> 0.083905453
A49: Discount Rate | C49: Risk free rate | D49: Equity premium | E49: Firm premium | F49: Total | G49: 1 | H49: 2 | I49: 3 | J49: 4 | K49: 5 | L49: 6 | M49: 7 | N49: 8 | O49: 9 | P49: 10 | Q49: 11 | R49: 12 | S49: 13 | T49: 14 | U49: 15 | V49: 16 | W49: 17 | X49: 18 | Y49: 19 | Z49: 20 | AA49: 21 | AB49: 22 | AC49: 23 | AD49: 24 | AE49: 25 | AF49: 26
C50: 0.04 | D50: 0.045 | E50: 0.01 | F50: =E50+D50+C50 -> 0.095
G51: =G17/G6 -> 0.41682173 | H51: =H17/H6 -> 0.5019073 | I51: =I17/I6 -> 0.50500246 | J51: =J17/J6 -> 0.46039966 | K51: =K17/K6 -> 0.41625922 | L51: =L17/L6 -> 0.42971806 | M51: =M17/M6 -> 0.41782555 | N51: =N17/N6 -> 0.40453478 | ... AF51: =AF17/AF6 -> 0.17920017
A52: Modelling factors | D52: Short Term | E52: Long Term | F52: Reference (line)
C53: Depreciation factor | D53: =-Assumptions!S16 -> -0.03 | E53: =-Assumptions!T16 -> -0.04 | F53: % PPE | H53: =D44/D12 -> -5.0271084 | I53: =E44/E12 -> 0.40165062 | J53: =F44/F12 -> 0.15232194
C54: Amortization factor | D54: =Assumptions!S17 -> 0 | E54: =Assumptions!T17 -> 0 | F54: % IA
C55: Stock-based comp | D55: =-Assumptions!S18 -> 0 | E55: =-Assumptions!T18 -> -0.02 | F55: % Revenue
C56: Tax Rate | D56: =Assumptions!S19 -> 0.25 | E56: =Assumptions!T19 -> 0.3 | F56: % Earnings before tax | G56: =G43/G44 -> 27.367144 | H56: =H43/H44 -> 26.664793 | I56: =I43/I44 -> 24.72231 | J56: =J43/J44 -> 27.963033 | K56: =K43/K44 -> 21.547267 | L56: =L43/L44 -> 25.682329 | M56: =M43/M44 -> 25.153335 | N56: =N43/N44 -> 26.120091 | ... AF56: =AF43/AF44 -> 45.243291
C57: Interest Rate on debt | D57: 0.02 | E57: 0.02 | F57: % Debt (l29)
C58: Interest Rate on cash | D58: =-Assumptions!S21 -> 0 | E58: =-Assumptions!T21 -> 0 | F58: % of Cash (l28)
C59: PPE+ROA | D59: =-Assumptions!S22 -> 0 | E59: =Assumptions!T22 -> 0 | F59: Growing with capex
C60: Working capital flows | D60: =-Assumptions!S23 -> -0.025 | E60: =-Assumptions!T23 -> -0.045 | F60: % of Change Revenues (l2)
C61: Intangible Assets | D61: =Assumptions!S24 -> 0 | E61: =Assumptions!T24 -> 0 | F61: Growing with amortization
C62: Capex | D62: =-Assumptions!S25 -> -0.07 | E62: =-Assumptions!T25 -> -0.09 | F62: % Revenue
C63: Acquisition factor | D63: =Assumptions!S26 -> 0 | E63: =Assumptions!T26 -> 0 | F63: % Revenue
C64: Dividends | D64: 0.1 | E64: 0.18 | F64: % Net Income (11)
C65: Repurchases | D65: =Assumptions!S28 -> 0.04 | E65: =Assumptions!T28 -> 0.05 | F65: % Net Income (11) | G65: =D43/D44 -> 0.47333733 | H65: =E43/E44 -> 1.9438356 | I65: =F43/F44 -> 6.9669492
C66: Leases | D66: =Assumptions!S29 -> 0.09 | E66: 0.11 | F66: % Revenue
C67: Cash Costs for EBIT | D67: =Assumptions!S30 -> 0 | E67: =Assumptions!T30 -> 0 | F67: % Revenue
C68: Total Debt | D68: 0.1 | E68: 0.14 | F68: % EBITDA
A70: Valuation | D70: $ millions
C71: Value of flows | D71: =SUMPRODUCT(G35:AF35,G45:AF45)+((AF43-AF44)*AF45) -> 9634.6875 | E71: =D71/D73 -> 0.75808786
C72: Value of perpetuity | D72: =(AF34/(F50-AF5))*AF45 -> 3074.5088 | E72: =D72/D73 -> 0.24191214
C73: Total Value | D73: =D71+D72 -> 12709.196
C74: Actual share price | D74: =OP!C21 -> 3.83
C75: Total value vs Mkt Cap | D75: =D76/D74-1 -> 0.10262944
C76: Estimated NPV per share | D76: =D73*1000000/OP!C22 -> 4.2230708
A78: Sensibility | C78: Sensitivity +0.1% | D78: =(SUMPRODUCT(G35:AF35,G45:AF45)+((AF43-AF44)*AF45)+(AF34/(F50+0.001-AF5))*AF45)*1000000/OP!C22 -> 4.2096285 | E78: =D78/D76-1 -> -0.0031830544
C79: Sensitivity +0.5% | D79: =(SUMPRODUCT(G35:AF35,G45:AF45)+((AF43-AF44)*AF45)+(AF34/(F50+0.005-AF5))*AF45)*1000000/OP!C22 -> 4.15922 | E79: =D79/D76-1 -> -0.015119509
A81: Notes | C81: Price where it'd be a "BUY" | D81: =IF(D75<15%,D76/1.15,"") -> 3.6722355
A86: Links
A87: https://www.fool.com.au/2023/12/07/pilbara-minerals-shares-have-dropped-34-in-4-months-heres-what-to-focus-on/
A88: https://www.nasdaq.com/articles/lithium-market-forecast%3A-top-trends-that-will-affect-lithium-in-2024
A90: https://www.statista.com/statistics/208725/net-profit-margin-of-the-top-mining-companies/
A92: Net profit margin of the top mining companies worldwide from 2002 to 2022, with a forecast for 2023 | B92: Study done by PwC (June 2023)
A94: 2002 | B94: 6 | C94: in %
A95: 2003 | B95: 11 | C95: in %
A96: 2004 | B96: 15 | C96: in %
A97: 2005 | B97: 20 | C97: in %
A98: 2006 | B98: 27 | C98: in %
A99: 2007 | B99: 26 | C99: in %
A100: 2008 | B100: 16 | C100: in %
A101: 2009 | B101: 15 | C101: in %
A102: 2010 | B102: 25 | C102: in %
A103: 2011 | B103: 24 | C103: in %
A104: 2012 | B104: 13 | C104: in %
A105: 2013 | B105: 4 | C105: in %
... A115: 2023* | B115: 14 | C115: in %
A116: Average for the past 21 years | B116: =AVERAGE(B94:B115) -> 13.454545
A123: Percentage | B123: Sensitivity Analysis | C123: 2024 | D123: 2025 | E123: 2026 | F123: 2027 | G123: 2028 | H123: 2029 | I123: 2030 | J123: 2031 | K123: 2032 | L123: 2033 | M123: 2034 | N123: 2035 | O123: 2036 | P123: 2037 | Q123: 2038 | R123: 2039 | S123: 2040 | T123: 2041 | U123: 2042 | V123: 2043 | W123: 2044 | X123: 2045 | Y123: 2046 | Z123: 2047 | AA123: 2048 | AB123: 2049
A124: =1-A129 -> 0.2 | B124: Ore Growth
A125: 0.025 | B125: Good Market | C125: =C126+$A$125 -> 0.25100481 | D125: =D126+$A$125 -> 0.21004378 | E125: =E126+$A$125 -> 0.19532588 | F125: =F126+$A$125 -> 0.18264256 | G125: =G126+$A$125 -> 0.17162753 | H125: =H126+$A$125 -> 0.16198946 | I125: =I126+$A$125 -> 0.15349663 | J125: =J126+$A$125 -> 0.15490263 | ... AB125: =AB126+$A$125 -> 0.085982906
A126: 0 | B126: Current Market | C126: =Assumptions!S177 -> 0.22600481 | D126: =Assumptions!T177 -> 0.18504378 | E126: =Assumptions!U177 -> 0.17032588 | F126: =Assumptions!V177 -> 0.15764256 | G126: =Assumptions!W177 -> 0.14662753 | H126: =Assumptions!X177 -> 0.13698946 | I126: =Assumptions!Y177 -> 0.12849663 | J126: =Assumptions!Z177 -> 0.12990263 | ... AB126: =Assumptions!AR177 -> 0.060982906
A127: -0.025 | B127: Bad Market | C127: =C126+$A$127 -> 0.20100481 | D127: =D126+$A$127 -> 0.16004378 | E127: =E126+$A$127 -> 0.14532588 | F127: =F126+$A$127 -> 0.13264256 | G127: =G126+$A$127 -> 0.12162753 | H127: =H126+$A$127 -> 0.11198946 | I127: =I126+$A$127 -> 0.10349663 | J127: =J126+$A$127 -> 0.10490263 | ... AB127: =AB126+$A$127 -> 0.035982906
A129: 0.8 | B129: Lithium Price
A130: 0.05 | B130: Good Market | C130: =C131+$A$130 -> -0.36902793 | D130: =D131+$A$130 -> 0.13941594 | E130: =E131+$A$130 -> 0.13517825 | F130: =F131+$A$130 -> 0.11840823 | G130: =G131+$A$130 -> 0.1061185 | H130: =H131+$A$130 -> 0.096849025 | I130: =I131+$A$130 -> 0.089688458 | J130: =J131+$A$130 -> 0.079391705 | ... AB130: =AB131+$A$130 -> 0.053498756
A131: 0 | B131: Current Market | C131: =Assumptions!S180 -> -0.41902793 | D131: =Assumptions!T180 -> 0.08941594 | E131: =Assumptions!U180 -> 0.085178248 | F131: =Assumptions!V180 -> 0.068408227 | G131: =Assumptions!W180 -> 0.056118504 | H131: =Assumptions!X180 -> 0.046849025 | I131: =Assumptions!Y180 -> 0.039688458 | J131: =Assumptions!Z180 -> 0.029391705 | ... AB131: =Assumptions!AR180 -> 0.0034987558
A132: -0.05 | B132: Bad Market | C132: =C131+$A$132 -> -0.46902793 | D132: =D131+$A$132 -> 0.03941594 | E132: =E131+$A$132 -> 0.035178248 | F132: =F131+$A$132 -> 0.018408227 | G132: =G131+$A$132 -> 0.0061185043 | H132: =H131+$A$132 -> -0.0031509746 | I132: =I131+$A$132 -> -0.010311542 | J132: =J131+$A$132 -> -0.020608295 | ... AB132: =AB131+$A$132 -> -0.046501244
...

Sheet Assumptions
B2: Assumptions
B4: Prospects:
B5: Links:
C7: =OP!J21 -> 2023 | D7: =C7-1 -> 2022 | E7: =D7-1 -> 2021 | F7: =E7-1 -> 2020 | G7: =F7-1 -> 2019 | H7: =G7-1 -> 2018 | I7: =H7-1 -> 2017 | J7: =I7-1 -> 2016 | K7: =J7-1 -> 2015 | L7: =K7-1 -> 2014 | N7: Average (3y) | O7: Average (5y) | P7: Average (10y) | Q7: Average (w/o covid) | S7: Short Term Forecast | T7: Long Term Forecast | U7: Production Increase, Sales Increase however lower price per tonne dropped the revenue (H1 2024)
B8: Revenue growth | C8: =('Inputs (AUD)'!B6-'Inputs (AUD)'!C6)/'Inputs (AUD)'!C6 -> 2.4162744 | D8: =('Inputs (AUD)'!C6-'Inputs (AUD)'!D6)/'Inputs (AUD)'!D6 -> 5.7667804 | E8: =('Inputs (AUD)'!D6-'Inputs (AUD)'!E6)/'Inputs (AUD)'!E6 -> 1.0903686 | F8: =('Inputs (AUD)'!E6-'Inputs (AUD)'!F6)/'Inputs (AUD)'!F6 -> 0.96495327 | G8: =('Inputs (AUD)'!F6-'Inputs (AUD)'!G6)/'Inputs (AUD)'!G6 -> 3.1960784 | H8: =('Inputs (AUD)'!G6-'Inputs (AUD)'!H6)/'Inputs (AUD)'!H6 -> #DIV/0! | I8: =('Inputs (AUD)'!H6-'Inputs (AUD)'!I6)/'Inputs (AUD)'!I6 -> #DIV/0! | J8: =('Inputs (AUD)'!I6-'Inputs (AUD)'!J6)/'Inputs (AUD)'!J6 -> -1 | ... L8: =('Inputs (AUD)'!K6-'Inputs (AUD)'!L6)/'Inputs (AUD)'!L6 -> -0.99993857 | N8: =AVERAGE(C8:E8) -> 3.0911411 | O8: =AVERAGE(C8:G8) -> 2.686891 | P8: =AVERAGE(C8:L8) -> #DIV/0! | Q8: =AVERAGE(C8,F8:L8) -> #DIV/0! | S8: =N8/3 -> 1.0303804 | T8: =O8/10 -> 0.2686891
B9: Operating Margin | C9: ='Inputs (AUD)'!B8/'Inputs (AUD)'!B6 -> 0.79032972 | D9: ='Inputs (AUD)'!C8/'Inputs (AUD)'!C6 -> 0.61524882 | E9: ='Inputs (AUD)'!D8/'Inputs (AUD)'!D6 -> -0.19908987 | F9: ='Inputs (AUD)'!E8/'Inputs (AUD)'!E6 -> -0.85136742 | G9: ='Inputs (AUD)'!F8/'Inputs (AUD)'!F6 -> -0.43224299 | H9: ='Inputs (AUD)'!G8/'Inputs (AUD)'!G6 -> -1.6568627 | I9: ='Inputs (AUD)'!H8/'Inputs (AUD)'!H6 -> #DIV/0! | J9: ='Inputs (AUD)'!I8/'Inputs (AUD)'!I6 -> #DIV/0! | ... L9: ='Inputs (AUD)'!K8/'Inputs (AUD)'!K6 -> -10 | N9: =AVERAGE(C9:E9) -> 0.40216289 | O9: =AVERAGE(C9:G9) -> -0.015424348 | P9: =AVERAGE(C9:L9) -> #DIV/0! | Q9: =AVERAGE(C9,F9:L9) -> #DIV/0! | S9: =N9/2 -> 0.20108145 | T9: 0.15
Q10: =AVERAGE(C10,F10:L10) -> #DIV/0!
B12: Modelling Factors
C14: Last 10 Years
C15: =OP!J21 -> 2023 | D15: =D7 -> 2022 | E15: =E7 -> 2021 | F15: =F7 -> 2020 | G15: =G7 -> 2019 | H15: =H7 -> 2018 | I15: =I7 -> 2017 | J15: =J7 -> 2016 | K15: =K7 -> 2015 | L15: =L7 -> 2014 | N15: Average (3y) | O15: Average (5y) | P15: Average (10y) | Q15: Average (w/o covid) | S15: Short Term Forecast | T15: Long Term Forecast
B16: Depreciation factor | C16: ='Inputs (AUD)'!B61/'Inputs (AUD)'!B95 -> 0.00097446891 | D16: ='Inputs (AUD)'!C61/'Inputs (AUD)'!C95 -> 0.00069741955 | E16: ='Inputs (AUD)'!D61/'Inputs (AUD)'!D95 -> #DIV/0! | F16: ='Inputs (AUD)'!E61/'Inputs (AUD)'!E95 -> #DIV/0! | G16: -- | H16: ='Inputs (AUD)'!G61/'Inputs (AUD)'!G95 -> #DIV/0! | I16: ='Inputs (AUD)'!H61/'Inputs (AUD)'!H95 -> #DIV/0! | J16: ='Inputs (AUD)'!I61/'Inputs (AUD)'!I95 -> 0.0076923077 | K16: ='Inputs (AUD)'!J61/'Inputs (AUD)'!J95 -> #DIV/0! | L16: ='Inputs (AUD)'!K61/'Inputs (AUD)'!K95 -> #DIV/0! | N16: =AVERAGE(C16:E16) -> #DIV/0! | O16: =AVERAGE(C16:F16) -> #DIV/0! | P16: =AVERAGE(C16:L16) -> #DIV/0! | Q16: =AVERAGE(C16,F16:L16) -> #DIV/0! | S16: 0.03 | T16: 0.04 | U16: Mining Equipement, similar to construction equipment (excavators, Bulldozers, etc) have an average lifespan of about 10-12 years
B17: Amortization factor | C17: - - | D17: - - | E17: - - | F17: - - | G17: - - | H17: - - | I17: - - | J17: - - | K17: - - | L17: - - | N17: =AVERAGE(C17:E17) -> #DIV/0! | O17: - - | P17: =AVERAGE(C17:L17) -> #DIV/0! | Q17: =AVERAGE(C17,F17:L17) -> #DIV/0!
B18: Stock-based comp | C18: =-'Inputs (AUD)'!B103/'Fin. Data'!B5 -> -0.0031496063 | D18: =-'Inputs (AUD)'!C103/'Fin. Data'!C5 -> 0 | E18: =-'Inputs (AUD)'!D103/'Fin. Data'!D5 -> 0 | F18: =-'Inputs (AUD)'!E103/'Fin. Data'!E5 -> 0 | G18: =-'Inputs (AUD)'!F103/'Fin. Data'!F5 -> 0 | H18: =-'Inputs (AUD)'!G103/'Fin. Data'!G5 -> 0 | I18: =-'Inputs (AUD)'!H103/'Fin. Data'!H5 -> #DIV/0! | J18: =-'Inputs (AUD)'!I103/'Fin. Data'!I5 -> #DIV/0! | ... L18: =-'Inputs (AUD)'!K103/'Fin. Data'!K5 -> 0 | N18: =AVERAGE(C18:E18) -> -0.0010498688 | O18: =AVERAGE(C18:G18) -> -0.00062992126 | P18: =AVERAGE(C18:L18) -> #DIV/0! | Q18: =AVERAGE(C18,F18:L18) -> #DIV/0! | S18: 0 | T18: 0.02 | U18: No Compensation has been paid out in the previous years.
B19: Tax Rate | C19: =-'Fin. Data'!B21/('Fin. Data'!B11+'Fin. Data'!B14+'Fin. Data'!B15) -> 0.29079045 | D19: =-'Fin. Data'!C21/('Fin. Data'!C11+'Fin. Data'!C14+'Fin. Data'!C15) -> 0.22510345 | E19: =-'Fin. Data'!D21/('Fin. Data'!D11+'Fin. Data'!D14+'Fin. Data'!D15) -> 0 | F19: =-'Fin. Data'!E21/('Fin. Data'!E11+'Fin. Data'!E14+'Fin. Data'!E15) -> 0 | G19: =-'Fin. Data'!F21/('Fin. Data'!F11+'Fin. Data'!F14+'Fin. Data'!F15) -> 0 | H19: =-'Fin. Data'!G21/('Fin. Data'!G11+'Fin. Data'!G14+'Fin. Data'!G15) -> 0 | I19: =-'Fin. Data'!H21/('Fin. Data'!H11+'Fin. Data'!H14+'Fin. Data'!H15) -> 0 | J19: =-'Fin. Data'!I21/('Fin. Data'!I11+'Fin. Data'!I14+'Fin. Data'!I15) -> -0.0036101083 | ... L19: =-'Fin. Data'!K21/('Fin. Data'!K11+'Fin. Data'!K14+'Fin. Data'!K15) -> 0 | N19: =AVERAGE(C19:E19) -> 0.17196463 | O19: =AVERAGE(C19:G19) -> 0.10317878 | P19: =AVERAGE(C19:L19) -> 0.053014093 | Q19: =AVERAGE(C19,F19:L19) -> 0.038129685 | S19: 0.25 | T19: 0.3 | U19: * According to MINERALS RESOURCE RENT TAX (MRRT) of Australia
B20: Interest Rate on debt | C20: =0/'Fin. Data'!B58 -> 0 | D20: - - | E20: - - | F20: - - | G20: - - | H20: - - | I20: - - | J20: - - | K20: - - | L20: - - | N20: =AVERAGE(C20:E20) -> 0 | O20: - - | P20: =AVERAGE(C20:L20) -> 0 | Q20: =AVERAGE(C20,F20:L20) -> 0
B21: Interest Rate on cash | C21: =0/'Inputs (AUD)'!B28 -> 0 | D21: - - | E21: - - | F21: - - | G21: - - | H21: - - | I21: - - | J21: - - | K21: - - | L21: - - | N21: =AVERAGE(C21:E21) -> 0 | O21: - - | P21: =AVERAGE(C21:L21) -> 0 | Q21: =AVERAGE(C21,F21:L21) -> 0
B22: PPE+ROA | C22: ='Inputs (AUD)'!B33/'Inputs (AUD)'!C33-1 -> 0.47491211 | D22: ='Inputs (AUD)'!C33/'Inputs (AUD)'!D33-1 -> 0.19473081 | E22: ='Inputs (AUD)'!D33/'Inputs (AUD)'!E33-1 -> 0.60740589 | F22: ='Inputs (AUD)'!E33/'Inputs (AUD)'!F33-1 -> 0.11015217 | G22: ='Inputs (AUD)'!F33/'Inputs (AUD)'!G33-1 -> 0.16082257 | H22: ='Inputs (AUD)'!G33/'Inputs (AUD)'!H33-1 -> 2.4263776 | I22: ='Inputs (AUD)'!H33/'Inputs (AUD)'!I33-1 -> 99.636364 | J22: ='Inputs (AUD)'!I33/'Inputs (AUD)'!J33-1 -> -0.42105263 | ... L22: ='Inputs (AUD)'!K33/'Inputs (AUD)'!L33-1 -> 0.068965517 | N22: =AVERAGE(C22:E22) -> 0.42568294 | O22: =AVERAGE(C22:G22) -> 0.30960471 | P22: =AVERAGE(C22:L22) -> 10.287158 | Q22: =AVERAGE(C22,F22:L22) -> 12.758681
B23: Working capital flows | C23: ='Inputs (AUD)'!B62/('Inputs (AUD)'!B6-'Inputs (AUD)'!C6) -> 0.014542165 | D23: ='Inputs (AUD)'!C62/('Inputs (AUD)'!C6-'Inputs (AUD)'!D6) -> -0.0094693233 | E23: ='Inputs (AUD)'!D62/('Inputs (AUD)'!D6-'Inputs (AUD)'!E6) -> -0.056706652 | F23: ='Inputs (AUD)'!E62/('Inputs (AUD)'!E6-'Inputs (AUD)'!F6) -> -0.14043584 | G23: ='Inputs (AUD)'!F62/('Inputs (AUD)'!F6-'Inputs (AUD)'!G6) -> -0.12269939 | H23: ='Inputs (AUD)'!G62/('Inputs (AUD)'!G6-'Inputs (AUD)'!H6) -> -0.19607843 | I23: ='Inputs (AUD)'!H62/('Inputs (AUD)'!H6-'Inputs (AUD)'!I6) -> #DIV/0! | J23: ='Inputs (AUD)'!I62/('Inputs (AUD)'!I6-'Inputs (AUD)'!J6) -> 96 | ... L23: ='Inputs (AUD)'!K62/('Inputs (AUD)'!K6-'Inputs (AUD)'!L6) -> 0 | N23: =AVERAGE(C23:E23) -> -0.01721127 | O23: =AVERAGE(C23:G23) -> -0.062953806 | P23: =AVERAGE(C23:L23) -> #DIV/0! | Q23: =AVERAGE(C23,F23:L23) -> #DIV/0! | S23: 0.025 | T23: 0.045
B24: Intangible Assets | C24: - - | D24: - - | E24: - - | F24: - - | G24: - - | H24: - - | I24: - - | J24: - - | K24: - - | L24: - - | N24: =AVERAGE(C24:E24) -> #DIV/0! | O24: - - | P24: =AVERAGE(C24:L24) -> #DIV/0! | Q24: =AVERAGE(C24,F24:L24) -> #DIV/0!
B25: CAPEX | C25: =-'Fin. Data'!B32/'Fin. Data'!B5 -> 0.094857283 | D25: =-'Fin. Data'!C32/'Fin. Data'!C5 -> 0.10785138 | E25: =-'Fin. Data'!D32/'Fin. Data'!D5 -> 0.11660978 | F25: =-'Fin. Data'!E32/'Fin. Data'!E5 -> 0.26872771 | G25: =-'Fin. Data'!F32/'Fin. Data'!F5 -> 4.1658879 | H25: =-'Fin. Data'!G32/'Fin. Data'!G5 -> 21.480392 | I25: =-'Fin. Data'!H32/'Fin. Data'!H5 -> #DIV/0! | J25: =-'Fin. Data'!I32/'Fin. Data'!I5 -> #DIV/0! | ... L25: =-'Fin. Data'!K32/'Fin. Data'!K5 -> 5.3333333 | N25: =AVERAGE(C25:E25) -> 0.10643948 | O25: =AVERAGE(C25:G25) -> 0.9507868 | P25: =AVERAGE(C25:L25) -> #DIV/0! | Q25: =AVERAGE(C25,F25:L25) -> #DIV/0! | S25: 0.07 | T25: 0.09
B26: Acquisition factor | C26: ='Fin. Data'!B33/'Fin. Data'!B5 -> -0.005511811 | D26: ='Fin. Data'!C33/'Fin. Data'!C5 -> -0.064055145 | E26: ='Fin. Data'!D33/'Fin. Data'!D5 -> -1.1962457 | F26: ='Fin. Data'!E33/'Fin. Data'!E5 -> 0 | G26: ='Fin. Data'!F33/'Fin. Data'!F5 -> 0 | H26: ='Fin. Data'!G33/'Fin. Data'!G5 -> 0.42156863 | I26: ='Fin. Data'!H33/'Fin. Data'!H5 -> #DIV/0! | J26: ='Fin. Data'!I33/'Fin. Data'!I5 -> #DIV/0! | ... L26: ='Fin. Data'!K33/'Fin. Data'!K5 -> 0 | N26: =AVERAGE(C26:E26) -> -0.42193756 | O26: =AVERAGE(C26:G26) -> -0.25316254 | P26: =AVERAGE(C26:L26) -> #DIV/0! | Q26: =AVERAGE(C26,F26:L26) -> #DIV/0!
B27: Dividends | C27: =-'Fin. Data'!B27/'Fin. Data'!B23 -> 0.13792815 | D27: =-'Fin. Data'!C27/'Fin. Data'!C23 -> 0 | E27: =-'Fin. Data'!D27/'Fin. Data'!D23 -> 0 | F27: =-'Fin. Data'!E27/'Fin. Data'!E23 -> 0 | G27: =-'Fin. Data'!F27/'Fin. Data'!F23 -> 0 | H27: =-'Fin. Data'!G27/'Fin. Data'!G23 -> 0 | I27: =-'Fin. Data'!H27/'Fin. Data'!H23 -> 0 | J27: =-'Fin. Data'!I27/'Fin. Data'!I23 -> 0 | ... L27: =-'Fin. Data'!K27/'Fin. Data'!K23 -> 0 | N27: =AVERAGE(C27:E27) -> 0.04597605 | O27: =AVERAGE(C27:G27) -> 0.02758563 | P27: =AVERAGE(C27:L27) -> 0.013792815 | Q27: =AVERAGE(C27,F27:L27) -> 0.017241019 | S27: 0.075 | T27: 0.175 | U27: *Paying a sustainable dividend to shareholders, with a target dividend payout ratio of between 20-30% of free cash flow ( https://pilbaraminerals.com.au/investors/dividend-information/)
B28: Repurchases | C28: =-'Fin. Data'!B28/'Fin. Data'!B23 -> -0.00050186107 | D28: =-'Fin. Data'!C28/'Fin. Data'!C23 -> -0.0064079744 | E28: =-'Fin. Data'!D28/'Fin. Data'!D23 -> 4.6634241 | F28: =-'Fin. Data'!E28/'Fin. Data'!E23 -> 1.12286 | G28: =-'Fin. Data'!F28/'Fin. Data'!F23 -> 2.100346 | H28: =-'Fin. Data'!G28/'Fin. Data'!G23 -> 8.0618557 | I28: =-'Fin. Data'!H28/'Fin. Data'!H23 -> 2.6307692 | J28: =-'Fin. Data'!I28/'Fin. Data'!I23 -> 2.2068345 | ... L28: =-'Fin. Data'!K28/'Fin. Data'!K23 -> 0.375 | N28: =AVERAGE(C28:E28) -> 1.5521714 | O28: =AVERAGE(C28:G28) -> 1.5759441 | P28: =AVERAGE(C28:L28) -> 2.2099634 | Q28: =AVERAGE(C28,F28:L28) -> 2.1803273 | S28: 0.04 | T28: 0.05
B29: Leases | C29: =('Fin. Data'!B50+'Fin. Data'!B54)/'Fin. Data'!B5 -> 0.049089567 | D29: =('Fin. Data'!C50+'Fin. Data'!C54)/'Fin. Data'!C5 -> 0.073806321 | E29: =('Fin. Data'!D50+'Fin. Data'!D54)/'Fin. Data'!D5 -> 0.14618885 | F29: =('Fin. Data'!E50+'Fin. Data'!E54)/'Fin. Data'!E5 -> 0.93460166 | G29: =('Fin. Data'!F50+'Fin. Data'!F54)/'Fin. Data'!F5 -> 0.20794393 | H29: =('Fin. Data'!G50+'Fin. Data'!G54)/'Fin. Data'!G5 -> 0.068627451 | I29: =('Fin. Data'!H50+'Fin. Data'!H54)/'Fin. Data'!H5 -> #DIV/0! | J29: =('Fin. Data'!I50+'Fin. Data'!I54)/'Fin. Data'!I5 -> #DIV/0! | ... L29: =('Fin. Data'!K50+'Fin. Data'!K54)/'Fin. Data'!K5 -> #VALUE! | N29: =AVERAGE(C29:E29) -> 0.089694913 | O29: =AVERAGE(C29:G29) -> 0.28232607 | P29: =AVERAGE(C29:L29) -> #DIV/0! | Q29: =AVERAGE(C29,F29:L29) -> #DIV/0! | S29: 0.09 | T29: 0.12
B30: Cash Costs for EBIT | C30: - - | D30: - - | E30: - - | F30: - - | G30: - - | H30: - - | I30: - - | J30: - - | K30: - - | L30: - - | N30: =AVERAGE(C30:E30) -> #DIV/0! | O30: - - | P30: =AVERAGE(C30:L30) -> #DIV/0! | Q30: =AVERAGE(C30,F30:L30) -> #DIV/0!
B31: Total Debt | C31: ='Fin. Data'!B58/'Fin. Data'!B19 -> 0.15232194 | D31: ='Fin. Data'!C58/'Fin. Data'!C19 -> 0.40165062 | E31: ='Fin. Data'!D58/'Fin. Data'!D19 -> -5.0271084 | F31: ='Fin. Data'!E58/'Fin. Data'!E19 -> -2.6808511 | G31: ='Fin. Data'!F58/'Fin. Data'!F19 -> -11.779661 | H31: ='Fin. Data'!G58/'Fin. Data'!G19 -> -10.330709 | I31: ='Fin. Data'!H58/'Fin. Data'!H19 -> -4.4748201 | J31: ='Fin. Data'!I58/'Fin. Data'!I19 -> #VALUE! | ... L31: ='Fin. Data'!K58/'Fin. Data'!K19 -> #VALUE! | N31: =AVERAGE(C31:E31) -> -1.4910453 | O31: =AVERAGE(C31:G31) -> -3.7867296 | P31: =AVERAGE(C31:L31) -> #VALUE! | Q31: =AVERAGE(C31,F31:L31) -> #VALUE! | S31: 0.12 | T31: 0.15
B34: Forecasts
B37: https://www.statista.com/statistics/452025/projected-total-demand-for-lithium-globally/
H48: Year | I48: Demand | J48: Demand Growth YoY | K48: Average Price per ton | L48: Price Growth YoY | M48: Revenue Growth
H49: 2020 | I49: 310 | J49: -- | K49: 8400 | L49: -- | M49: =F8 -> 0.96495327
H50: 2021 | I50: 508 | J50: =I50/I49-1 -> 0.63870968 | K50: 12600 | L50: =K50/K49-1 -> 0.5 | M50: =E8 -> 1.0903686
H51: 2022 | I51: 690 | J51: =I51/I50-1 -> 0.35826772 | K51: 68100 | L51: =K51/K50-1 -> 4.4047619 | M51: =D8 -> 5.7667804
H52: 2023 | I52: 917 | J52: =I52/I51-1 -> 0.32898551 | K52: 46000 | L52: =K52/K51-1 -> -0.32452276 | M52: =C8 -> 2.4162744
H53: 2024 | I53: 1072 | J53: =I53/I52-1 -> 0.16902944
H54: 2025 | I54: 1257 | J54: =I54/I53-1 -> 0.17257463
H55: 2026 | I55: 1433 | J55: =I55/I54-1 -> 0.14001591
H56: 2027 | I56: 1628 | J56: =I56/I55-1 -> 0.13607816
H57: 2028 | I57: 1861 | J57: =I57/I56-1 -> 0.14312039
H58: 2029 | I58: 2123 | J58: =I58/I57-1 -> 0.14078452
H59: 2030 | I59: 2453 | J59: =I59/I58-1 -> 0.15544041
H60: 2031 | I60: 2688 | J60: =I60/I59-1 -> 0.09580106
H61: 2032 | I61: 2933 | J61: =I61/I60-1 -> 0.091145833
H62: 2033 | I62: 3182 | J62: =I62/I61-1 -> 0.084896011
H63: 2034 | I63: 3477 | J63: =I63/I62-1 -> 0.092708988
H64: 2035 | I64: 3829 | J64: =I64/I63-1 -> 0.1012367
A95: Regression Forecast
B97: Year (Quarterly) | C97: Units | D97: April Q FY17 | E97: September Q FY17 | F97: December Q FY17 | G97: April Q FY18 | H97: September Q FY18 | I97: December Q FY18 | J97: April Q FY19 | K97: September Q FY19 | L97: December Q FY19 | M97: April Q FY20 | N97: September Q FY20 | O97: December Q FY20 | P97: April Q FY21 | Q97: September Q FY21 | R97: December Q FY21 | S97: April Q FY22 | T97: September Q FY22 | U97: December Q FY22 | V97: April Q FY23 | W97: September Q FY23 | X97: December Q FY23 | Y97: April Q FY24 | Z97: September Q FY24 | AA97: December Q FY24 | AB97: Average
B98: Sales | C98: kt | T98: 1037 | U98: 851.1 | V98: 138.2 | W98: 144.3 | X98: 176.3 | Y98: 146.4 | Z98: 146.4 | AA98: 159.9 | AB98: =AVERAGE(Table2[[#This Row],[April Q FY17]]:Table2[[#This Row],[December Q FY24]]) -> 349.95
B99: Production | C99: kt | R99: 83.476 | S99: 81.431 | T99: 147.105 | U99: 162.151 | V99: 147.1 | W99: 148.1 | X99: 162.8 | Y99: 144.2 | Z99: 144.2 | AA99: 176 | AB99: =AVERAGE(Table2[[#This Row],[April Q FY17]]:Table2[[#This Row],[December Q FY24]]) -> 139.6563
B100: Revenue | C100: A$M | S100: 169.2 | V100: 868 | W100: 1000 | X100: 800 | Y100: 493 | Z100: 493 | AA100: 264 | AB100: =AVERAGE(Table2[[#This Row],[April Q FY17]]:Table2[[#This Row],[December Q FY24]]) -> 583.88571
B101: Realised Price | C101: US$/T | S101: 6250 | T101: 4266 | V101: 4266 | W101: 4840 | X101: 3256 | Y101: 2240 | Z101: 2240 | AA101: 1113 | AB101: =AVERAGE(Table2[[#This Row],[April Q FY17]]:Table2[[#This Row],[December Q FY24]]) -> 3558.875
B103: Exploration (Quarter Basis) | C103: Units | D103: Sparkline | E103: Q1 FY17 | F103: Q2 FY17 | G103: Q3 FY17 | H103: Q4 FY17 | I103: Q1 FY18 | J103: Q2 FY18 | K103: Q3 FY18 | L103: Q4 FY18 | M103: Q1 FY19 | N103: Q2 FY19 | O103: Q3 FY19 | P103: Q4 FY19 | Q103: Q1 FY20 | R103: Q2 FY20 | S103: Q3 FY20 | T103: Q4 FY20 | U103: Q1 FY21 | V103: Q2 FY21 | W103: Q3 FY21 | X103: Q4 FY21 | Y103: Q1 FY22 | Z103: Q2 FY22 | AA103: Q3 FY22 | AB103: Q4 FY22 | AC103: Q1 FY23 | AD103: Q2 FY23 | AE103: Q3 FY23 | AF103: Q4 FY23 | AG103: Q1 FY24 | AH103: Q2 FY24 | AI103: Total
B104: Ore Mined | C104: wmt | E104: - | F104: - | G104: - | H104: - | I104: - | J104: 0 | K104: 0 | L104: 344549 | M104: 487978 | N104: 762531 | O104: 540426 | P104: 640173 | Q104: 303177 | R104: 65941 | S104: 4954 | T104: 438070 | U104: 372468 | V104: 466121 | W104: 85068 | X104: 672020 | Y104: 639188 | Z104: 779638 | AA104: 815387 | AB104: 1172450 | AC104: 1442545 | AD104: 1095739 | AE104: 1225563 | AF104: 1271150 | AG104: 1411017 | AH104: 1618748 | AI104: =SUM(Table1[[#This Row],[Q1 FY17]]:Table1[[#This Row],[Q2 FY24]]) -> 16654901
B105: QoQ Growth | C105: QoQ (%) | E105: =IFERROR(E104/C104-1,"-") -> - | F105: =IFERROR(F104/E104-1,"-") -> - | G105: =IFERROR(G104/F104-1,"-") -> - | H105: =IFERROR(H104/G104-1,"-") -> - | I105: =IFERROR(I104/H104-1,"-") -> - | J105: =IFERROR(J104/I104-1,"-") -> - | K105: =IFERROR(K104/J104-1,"-") -> - | L105: =IFERROR(L104/K104-1,"-") -> - | M105: =IFERROR(M104/L104-1,"-") -> 0.41628041 | ... AH105: =IFERROR(AH104/AG104-1,"-") -> 0.14722076
B106: Waste Mined | C106: wmt | E106: - | F106: - | G106: - | H106: - | I106: - | J106: 151812 | K106: 1823205 | L106: 2851161 | M106: 1921907 | N106: 2154690 | O106: 2445917 | P106: 1900027 | Q106: 868441 | R106: 26046 | S106: 21775 | T106: 213621 | U106: 338461 | V106: 612147 | W106: 1639128 | X106: 1976039 | Y106: 2929647 | Z106: 3829865 | AA106: 5261012 | AB106: 6120903 | AC106: 6540334 | AD106: 6360951 | AE106: 6572687 | AF106: 7311878 | AG106: 7741062 | AH106: 7965907 | AI106: =SUM(Table1[[#This Row],[Q1 FY17]]:Table1[[#This Row],[Q2 FY24]]) -> 79578623
B107: QoQ Growth | C107: QoQ (%) | E107: =IFERROR(E106/C106-1,"-") -> - | F107: =IFERROR(F106/E106-1,"-") -> - | G107: =IFERROR(G106/F106-1,"-") -> - | H107: =IFERROR(H106/G106-1,"-") -> - | I107: =IFERROR(I106/H106-1,"-") -> - | J107: =IFERROR(J106/I106-1,"-") -> - | K107: =IFERROR(K106/J106-1,"-") -> 11.009624 | L107: =IFERROR(L106/K106-1,"-") -> 0.56381811 | M107: =IFERROR(M106/L106-1,"-") -> -0.32592127 | ... AH107: =IFERROR(AH106/AG106-1,"-") -> 0.029045756
B108: Total Mineral Mined | C108: wmt | E108: - | F108: - | G108: - | H108: - | I108: - | J108: =J106 -> 151812 | K108: =K106 -> 1823205 | L108: 3195710 | M108: 2409894 | N108: 2917220 | O108: 2986342 | P108: 2540200 | Q108: 1171618 | R108: 91987 | S108: 26729 | T108: 651691 | U108: 710930 | V108: 1078268 | W108: 2224196 | X108: 2648059 | Y108: 3568836 | Z108: 4672233 | AA108: 6076398 | AB108: 7292353 | AC108: 7982879 | AD108: 7456690 | AE108: 7798250 | AF108: 8583028 | AG108: 9152078 | AH108: 9584655 | AI108: =SUM(Table1[[#This Row],[Q1 FY17]]:Table1[[#This Row],[Q2 FY24]]) -> 96795261
B109: QoQ Growth | C109: QoQ (%) | E109: =IFERROR(E108/C108-1,"-") -> - | F109: =IFERROR(F108/E108-1,"-") -> - | G109: =IFERROR(G108/F108-1,"-") -> - | H109: =IFERROR(H108/G108-1,"-") -> - | I109: =IFERROR(I108/H108-1,"-") -> - | J109: =IFERROR(J108/I108-1,"-") -> - | K109: =IFERROR(K108/J108-1,"-") -> 11.009624 | L109: =IFERROR(L108/K108-1,"-") -> 0.75279796 | M109: =IFERROR(M108/L108-1,"-") -> -0.24589716 | ... AH109: =IFERROR(AH108/AG108-1,"-") -> 0.047265441
B110: Ore Processed | C110: dmt | E110: - | F110: - | G110: - | H110: - | I110: - | J110: - | K110: - | L110: - | M110: 173667 | N110: 420221 | O110: 414223 | P110: 456541 | Q110: 202596 | R110: 102251 | S110: 137407 | T110: 199961 | U110: 360227 | V110: 381973 | W110: 415277 | X110: 422111 | Y110: 443691 | Z110: 566027 | AA110: 613202 | AB110: 792428 | AC110: 801968 | AD110: 902924 | AE110: 846949 | AF110: 893500 | AG110: 852148 | AH110: 982028 | AI110: =SUM(Table1[[#This Row],[Q1 FY17]]:Table1[[#This Row],[Q2 FY24]]) -> 11381320
B111: QoQ Growth | C111: QoQ (%) | E111: =IFERROR(E110/C110-1,"-") -> - | F111: =IFERROR(F110/E110-1,"-") -> - | G111: =IFERROR(G110/F110-1,"-") -> - | H111: =IFERROR(H110/G110-1,"-") -> - | I111: =IFERROR(I110/H110-1,"-") -> - | J111: =IFERROR(J110/I110-1,"-") -> - | K111: =IFERROR(K110/J110-1,"-") -> - | L111: =IFERROR(L110/K110-1,"-") -> - | M111: =IFERROR(M110/L110-1,"-") -> - | ... AH111: =IFERROR(AH110/AG110-1,"-") -> 0.15241484
B112: Lithium Market price | C112: AUD $ | E112: 16000 | F112: 19000 | G112: 23084.6 | H112: 25704 | I112: 24460.15 | J112: 21795.2 | K112: 14406 | L112: 11466.78 | M112: 11441.04 | N112: 11068.3 | O112: 9262.5 | P112: 7810 | Q112: 6873.6 | R112: 6095.52 | S112: 5675.55 | T112: 6266.5 | U112: 10177.2 | V112: 13699.8 | W112: 18540 | X112: 33313.2 | Y112: 62960 | Z112: 71366.4 | AA112: 71540 | AB112: 78173.6 | AC112: 56979 | AD112: 37102 | AE112: 32477 | AF112: 18379.4
B113: QoQ Growth | C113: QoQ (%) | E113: =IFERROR(E112/C112-1,"-") -> - | F113: =IFERROR(F112/E112-1,"-") -> 0.1875 | G113: =IFERROR(G112/F112-1,"-") -> 0.21497895 | H113: =IFERROR(H112/G112-1,"-") -> 0.11346959 | I113: =IFERROR(I112/H112-1,"-") -> -0.048391301 | J113: =IFERROR(J112/I112-1,"-") -> -0.10895068 | K113: =IFERROR(K112/J112-1,"-") -> -0.33902878 | L113: =IFERROR(L112/K112-1,"-") -> -0.20402749 | M113: =IFERROR(M112/L112-1,"-") -> -0.0022447453 | ... AF113: =IFERROR(AF112/AE112-1,"-") -> -0.4340795
B116: Exploration (Quarter Basis) | C116: Units | D116: Sparkline | E116: Q1 FY17 | F116: Q2 FY17 | G116: Q3 FY17 | H116: Q4 FY17 | I116: Q1 FY18 | J116: Q2 FY18 | K116: Q3 FY18 | L116: Q4 FY18 | M116: Q1 FY19 | N116: Q2 FY19 | O116: Q3 FY19 | P116: Q4 FY19 | Q116: Q1 FY20 | R116: Q2 FY20 | S116: Q3 FY20 | T116: Q4 FY20 | U116: Q1 FY21 | V116: Q2 FY21 | W116: Q3 FY21 | X116: Q4 FY21 | Y116: Q1 FY22 | Z116: Q2 FY22 | AA116: Q3 FY22 | AB116: Q4 FY22 | AC116: Q1 FY23 | AD116: Q2 FY23 | AE116: Q3 FY23 | AF116: Q4 FY23 | AG116: Q1 FY24 | AH116: Q2 FY24 | AI116: Total
B117: Waste Margin | C117: (%) | E117: =IFERROR(E106/E108,"-") -> - | F117: =IFERROR(F106/F108,"-") -> - | G117: =IFERROR(G106/G108,"-") -> - | H117: =IFERROR(H106/H108,"-") -> - | I117: =IFERROR(I106/I108,"-") -> - | J117: =IFERROR(J106/J108,"-") -> 1 | K117: =IFERROR(K106/K108,"-") -> 1 | L117: =IFERROR(L106/L108,"-") -> 0.8921839 | ... AH117: =IFERROR(AH106/AH108,"-") -> 0.83111046
B118: Processed Eficiency | C118: (%) | E118: =IFERROR(E110/E104,"-") -> - | F118: =IFERROR(F110/F104,"-") -> - | G118: =IFERROR(G110/G104,"-") -> - | H118: =IFERROR(H110/H104,"-") -> - | I118: =IFERROR(I110/I104,"-") -> - | J118: =IFERROR(J110/J104,"-") -> - | K118: =IFERROR(K110/K104,"-") -> - | L118: =IFERROR(L110/L104,"-") -> - | ... AH118: =IFERROR(AH110/AH104,"-") -> 0.60665897
B119: Mining Efficiency | E119: =IFERROR(E104/E108,"-") -> - | F119: =IFERROR(F104/F108,"-") -> - | G119: =IFERROR(G104/G108,"-") -> - | H119: =IFERROR(H104/H108,"-") -> - | I119: =IFERROR(I104/I108,"-") -> - | J119: =IFERROR(J104/J108,"-") -> 0 | K119: =IFERROR(K104/K108,"-") -> 0 | L119: =IFERROR(L104/L108,"-") -> 0.1078161 | ... AH119: =IFERROR(AH104/AH108,"-") -> 0.16888954
B121: Exploration (Yearly Basis) | C121: Units | D121: Sparkline | E121: 2017 | F121: 2018 | G121: 2019 | H121: 2020 | I121: 2021 | J121: 2022 | K121: 2023 | L121: 2024 (Q1+Q2) | M121: Total | N121: 2024 (Q3+Q4) | O121: 2025 | P121: 2026 | Q121: 2027 | R121: 2028 | S121: 2029 | T121: 2030 | U121: 2031 | V121: 2032 | W121: 2033 | X121: 2034 | Y121: 2035 | Z121: 2036 | AA121: 2037 | AB121: 2038 | AC121: 2039 | AD121: 2040 | AE121: 2041 | AF121: 2042 | AG121: 2043 | AH121: 2044 | AI121: 2045 | AJ121: 2046 | AK121: 2047 | AL121: 2048 | AM121: 2049 | AN121: CAGR
B122: Ore Mined | C122: wmt | E122: =SUM(E104:H104) -> 0 | F122: =SUM(I104:L104) -> 344549 | G122: =SUM(M104:P104) -> 2431108 | H122: =SUM(Q104:T104) -> 812142 | I122: =SUM(U104:X104) -> 1595677 | J122: =SUM(Y104:AB104) -> 3406663 | K122: =SUM(AC104:AF104) -> 5034997 | L122: =SUM(AG104:AH104) -> 3029765 | M122: =SUM(E122:L122) -> 16654901 | N122: =N128/M134 -> 3530444.9 | O122: =O128/N134 -> 2012078.5 | P122: =P128/O134 -> 2369806.6 | Q122: =Q128/P134 -> 2755725.1 | R122: =R128/Q134 -> 3169163.3 | S122: =S128/R134 -> 3609471.5 | T122: =T128/S134 -> 4076020.3 | U122: =U128/T134 -> 4588749.6 | ... AM122: =AM128/AL134 -> 19088156 | AN122: =(AM122/O122)^(1/(2049-2025)-1) -> 0.11576952
B123: YoY Growth | C123: (%) | E123: =IFERROR(E122/C122-1,"-") -> - | F123: =IFERROR(F122/E122-1,"-") -> - | G123: =IFERROR(G122/F122-1,"-") -> 6.0559137 | H123: =IFERROR(H122/G122-1,"-") -> -0.66593751 | I123: =IFERROR(I122/H122-1,"-") -> 0.96477586 | J123: =IFERROR(J122/I122-1,"-") -> 1.1349327 | K123: =IFERROR(K122/J122-1,"-") -> 0.47798505 | L123: =IFERROR(L122/K122-1,"-") -> -0.39825883 | M123: =IFERROR(M122/L122-1,"-") -> 4.4970933 | N123: =IFERROR(N122/L122-1,"-") -> 0.16525372 | O123: =IFERROR(O122/(L122+N122)-1,"-") -> -0.69329053 | P123: =IFERROR(P122/O122-1,"-") -> 0.17779029 | Q123: =IFERROR(Q122/P122-1,"-") -> 0.16284811 | R123: =IFERROR(R122/Q122-1,"-") -> 0.15002883 | S123: =IFERROR(S122/R122-1,"-") -> 0.13893516 | T123: =IFERROR(T122/S122-1,"-") -> 0.12925683 | U123: =IFERROR(U122/T122-1,"-") -> 0.12579164 | V123: =IFERROR(V122/U122-1,"-") -> 0.12540093 | W123: =IFERROR(W122/V122-1,"-") -> 0.11730936 | ... AM123: =IFERROR(AM122/AL122-1,"-") -> 0.055892462
B124: Waste Mined | C124: wmt | E124: =SUM(E106:H106) -> 0 | F124: =SUM(I106:L106) -> 4826178 | G124: =SUM(M106:P106) -> 8422541 | H124: =SUM(Q106:T106) -> 1129883 | I124: =SUM(U106:X106) -> 4565775 | J124: =SUM(Y106:AB106) -> 18141427 | K124: =SUM(AC106:AF106) -> 26785850 | L124: =SUM(AG106:AH106) -> 15706969 | M124: =SUM(E124:L124) -> 79578623 | N124: =N126-N122 -> 17647750 | O124: =O126-O122 -> 9706363.4 | P124: =P126-P122 -> 11041520 | Q124: =Q126-Q122 -> 12410464 | R124: =R126-R122 -> 13805295 | S124: =S126-S122 -> 15219094 | T124: =T126-T122 -> 16645796 | U124: =U126-U122 -> 18161408 | ... AM124: =AM126-AM122 -> 46349050 | AN124: =(AM124/O124)^(1/(2049-2025)-1) -> 0.22351502
B125: YoY Growth | C125: (%) | E125: =IFERROR(E124/C124-1,"-") -> - | F125: =IFERROR(F124/E124-1,"-") -> - | G125: =IFERROR(G124/F124-1,"-") -> 0.74517828 | H125: =IFERROR(H124/G124-1,"-") -> -0.8658501 | I125: =IFERROR(I124/H124-1,"-") -> 3.0409272 | J125: =IFERROR(J124/I124-1,"-") -> 2.9733511 | K125: =IFERROR(K124/J124-1,"-") -> 0.47650182 | L125: =IFERROR(L124/K124-1,"-") -> -0.41360946 | M125: =IFERROR(M124/L124-1,"-") -> 4.0664532 | N125: =IFERROR(N124/L124-1,"-") -> 0.12356176 | O125: =IFERROR(O124/(L124+N124)-1,"-") -> -0.7089958 | P125: =IFERROR(P124/O124-1,"-") -> 0.13755473 | Q125: =IFERROR(Q124/P124-1,"-") -> 0.12398152 | R125: =IFERROR(R124/Q124-1,"-") -> 0.11239153 | S125: =IFERROR(S124/R124-1,"-") -> 0.10240994 | T125: =IFERROR(T124/S124-1,"-") -> 0.093744215 | U125: =IFERROR(U124/T124-1,"-") -> 0.091050718 | V125: =IFERROR(V124/U124-1,"-") -> 0.091299885 | W125: =IFERROR(W124/V124-1,"-") -> 0.084044763 | ... AM125: =IFERROR(AM124/AL124-1,"-") -> 0.03051902
B126: Total Mineral Mined | C126: wmt | E126: =SUM(E108:H108) -> 0 | F126: =SUM(I108:L108) -> 5170727 | G126: =SUM(M108:P108) -> 10853656 | H126: =SUM(Q108:T108) -> 1942025 | I126: =SUM(U108:X108) -> 6661453 | J126: =SUM(Y108:AB108) -> 21609820 | K126: =SUM(AC108:AF108) -> 31820847 | L126: =SUM(AG108:AH108) -> 18736733 | M126: =SUM(E126:L126) -> 96795261 | N126: =N122/M135 -> 21178195 | O126: =O122/N135 -> 11718442 | P126: =P122/O135 -> 13411326 | Q126: =Q122/P135 -> 15166189 | R126: =R122/Q135 -> 16974458 | S126: =S122/R135 -> 18828566 | T126: =T122/S135 -> 20721817 | U126: =U122/T135 -> 22750158 | ... AM126: =AM122/AL135 -> 65437206 | AN126: =(AM126/O126)^(1/(2049-2025)-1) -> 0.19238369
B127: YoY Growth | C127: (%) | E127: =IFERROR(E126/C126-1,"-") -> - | F127: =IFERROR(F126/E126-1,"-") -> - | G127: =IFERROR(G126/F126-1,"-") -> 1.099058 | H127: =IFERROR(H126/G126-1,"-") -> -0.82107181 | I127: =IFERROR(I126/H126-1,"-") -> 2.4301582 | J127: =IFERROR(J126/I126-1,"-") -> 2.24401 | K127: =IFERROR(K126/J126-1,"-") -> 0.47251791 | L127: =IFERROR(L126/K126-1,"-") -> -0.41118057 | M127: =IFERROR(M126/L126-1,"-") -> 4.1660693 | N127: =IFERROR(N126/L126-1,"-") -> 0.13030349 | O127: =IFERROR(O126/(L126+N126)-1,"-") -> -0.70641455 | P127: =IFERROR(P126/O126-1,"-") -> 0.14446325 | Q127: =IFERROR(Q126/P126-1,"-") -> 0.13084932 | R127: =IFERROR(R126/Q126-1,"-") -> 0.11923029 | S127: =IFERROR(S126/R126-1,"-") -> 0.10922927 | T127: =IFERROR(T126/S126-1,"-") -> 0.10055205 | U127: =IFERROR(U126/T126-1,"-") -> 0.097884322 | V127: =IFERROR(V126/U126-1,"-") -> 0.098178131 | W127: =IFERROR(W126/V126-1,"-") -> 0.090920618 | ... AM127: =IFERROR(AM126/AL126-1,"-") -> 0.037793634
B128: Ore Processed | C128: dmt | E128: =SUM(E110:H110) -> 0 | F128: =SUM(I110:L110) -> 0 | G128: =SUM(M110:P110) -> 1464652 | H128: =SUM(Q110:T110) -> 642215 | I128: =SUM(U110:X110) -> 1579588 | J128: =SUM(Y110:AB110) -> 2415348 | K128: =SUM(AC110:AF110) -> 3445341 | L128: =SUM(AG110:AH110) -> 1834176 | M128: =SUM(E128:L128) -> 11381320 | N128: =SUM(U169:V169) -> 2154932.6 | O128: =T178 -> 1238204.1 | P128: =U178 -> 1470193.8 | Q128: =V178 -> 1723390.7 | R128: =W178 -> 1997794.8 | S128: =X178 -> 2293406.1 | T128: =Y178 -> 2610224.6 | U128: =Z178 -> 2961512.8 | V128: =AA178 -> 3358710.1 | ... AM128: =AR178 -> 14037155 | AN128: =(AM128/O128)^(1/(2049-2025)-1) -> 0.097600064
B129: YoY Growth | C129: (%) | E129: =IFERROR(E128/C128-1,"-") -> - | F129: =IFERROR(F128/E128-1,"-") -> - | G129: =IFERROR(G128/F128-1,"-") -> - | H129: =IFERROR(H128/G128-1,"-") -> -0.56152383 | I129: =IFERROR(I128/H128-1,"-") -> 1.4595937 | J129: =IFERROR(J128/I128-1,"-") -> 0.52909999 | K129: =IFERROR(K128/J128-1,"-") -> 0.42643669 | L129: =IFERROR(L128/K128-1,"-") -> -0.46763586 | M129: =IFERROR(M128/L128-1,"-") -> 5.2051406 | N129: =IFERROR(N128/L128-1,"-") -> 0.17487778 | O129: =IFERROR(O128/(L128+N128)-1,"-") -> -0.68960382 | P129: =IFERROR(P128/O128-1,"-") -> 0.18735982 | Q129: =IFERROR(Q128/P128-1,"-") -> 0.17222009 | R129: =IFERROR(R128/Q128-1,"-") -> 0.15922339 | S129: =IFERROR(S128/R128-1,"-") -> 0.1479688 | T129: =IFERROR(T128/S128-1,"-") -> 0.13814322 | U129: =IFERROR(U128/T128-1,"-") -> 0.13458159 | V129: =IFERROR(V128/U128-1,"-") -> 0.13411976 | W129: =IFERROR(W128/V128-1,"-") -> 0.12589895 | ... AM129: =IFERROR(AM128/AL128-1,"-") -> 0.063120784
B132: Exploration (Yearly Basis) | C132: Units | D132: Sparkline | E132: 2017 | F132: 2018 | G132: 2019 | H132: 2020 | I132: 2021 | J132: 2022 | K132: 2023 | L132: 2024 (Q1+Q2) | M132: 2024 Q3+Q4) | N132: 2025 | O132: 2026 | P132: 2027 | Q132: 2028 | R132: 2029 | S132: 2030 | T132: 2031 | U132: 2032 | V132: 2033 | W132: 2034 | X132: 2035 | Y132: 2036 | Z132: 2037 | AA132: 2038 | AB132: 2039 | AC132: 2040 | AD132: 2041 | AE132: 2042 | AF132: 2043 | AG132: 2044 | AH132: 2045 | AI132: 2046 | AJ132: 2047 | AK132: 2048 | AL132: 2049
B133: Waste Margin | C133: (%) | E133: =IFERROR(E124/E126,"-") -> - | F133: =IFERROR(F124/F126,"-") -> 0.93336546 | G133: =IFERROR(G124/G126,"-") -> 0.77600958 | H133: =IFERROR(H124/H126,"-") -> 0.58180662 | I133: =IFERROR(I124/I126,"-") -> 0.68540227 | J133: =IFERROR(J124/J126,"-") -> 0.83949922 | K133: =IFERROR(K124/K126,"-") -> 0.84177049 | L133: =IFERROR(L124/L126,"-") -> 0.83829817 | M133: =Table6[[#This Row],[2024 (Q1+Q2)]]-0.5% -> 0.83329817 | N133: =N124/N126 -> 0.83329812 | O133: =O124/O126 -> 0.82829812 | P133: =P124/P126 -> 0.82329812 | Q133: =Q124/Q126 -> 0.81829812 | R133: =R124/R126 -> 0.81329812 | S133: =S124/S126 -> 0.80829812 | T133: =T124/T126 -> 0.80329812 | U133: =U124/U126 -> 0.79829812 | ... AL133: =AL124/AL126 -> 0.71329812
B134: Processed Eficiency | C134: (%) | E134: =IFERROR(E128/E122,"-") -> - | F134: =IFERROR(F128/F122,"-") -> 0 | G134: =IFERROR(G128/G122,"-") -> 0.60246275 | H134: =IFERROR(H128/H122,"-") -> 0.79076689 | I134: =IFERROR(I128/I122,"-") -> 0.98991713 | J134: =IFERROR(J128/J122,"-") -> 0.70900703 | K134: =IFERROR(K128/K122,"-") -> 0.68427866 | L134: =IFERROR(L128/L122,"-") -> 0.60538557 | M134: =Table6[[#This Row],[2024 (Q1+Q2)]]+0.5% -> 0.61038557 | N134: =Table6[[#This Row],[2024 Q3+Q4)]]+0.5% -> 0.61538557 | O134: =Table6[[#This Row],[2025]]+0.5% -> 0.62038557 | P134: =Table6[[#This Row],[2026]]+0.5% -> 0.62538557 | Q134: =Table6[[#This Row],[2027]]+0.5% -> 0.63038557 | R134: =Table6[[#This Row],[2028]]+0.5% -> 0.63538557 | S134: =Table6[[#This Row],[2029]]+0.5% -> 0.64038557 | T134: =Table6[[#This Row],[2030]]+0.5% -> 0.64538557 | U134: =Table6[[#This Row],[2031]]+0.5% -> 0.65038557 | V134: =Table6[[#This Row],[2032]]+0.5% -> 0.65538557 | W134: =Table6[[#This Row],[2033]]+0.5% -> 0.66038557 | X134: =Table6[[#This Row],[2034]]+0.5% -> 0.66538557 | Y134: =Table6[[#This Row],[2035]]+0.5% -> 0.67038557 | Z134: =Table6[[#This Row],[2036]]+0.5% -> 0.67538557 | AA134: =Table6[[#This Row],[2037]]+0.5% -> 0.68038557 | AB134: =Table6[[#This Row],[2038]]+0.5% -> 0.68538557 | AC134: =Table6[[#This Row],[2039]]+0.5% -> 0.69038557 | AD134: =Table6[[#This Row],[2040]]+0.5% -> 0.69538557 | AE134: =Table6[[#This Row],[2041]]+0.5% -> 0.70038557 | AF134: =Table6[[#This Row],[2042]]+0.5% -> 0.70538557 | AG134: =Table6[[#This Row],[2043]]+0.5% -> 0.71038557 | AH134: =Table6[[#This Row],[2044]]+0.5% -> 0.71538557 | AI134: =Table6[[#This Row],[2045]]+0.5% -> 0.72038557 | AJ134: =Table6[[#This Row],[2046]]+0.5% -> 0.72538557 | AK134: =Table6[[#This Row],[2047]]+0.5% -> 0.73038557 | AL134: =Table6[[#This Row],[2048]]+0.5% -> 0.73538557
B135: Mining Efficiency | E135: =IFERROR(E122/E126,"-") -> - | F135: =IFERROR(F122/F126,"-") -> 0.066634537 | G135: =IFERROR(G122/G126,"-") -> 0.22398978 | H135: =IFERROR(H122/H126,"-") -> 0.41819338 | I135: =IFERROR(I122/I126,"-") -> 0.23953888 | J135: =IFERROR(J122/J126,"-") -> 0.15764421 | K135: =IFERROR(K122/K126,"-") -> 0.15822951 | L135: =IFERROR(L122/L126,"-") -> 0.16170188 | M135: =Table6[[#This Row],[2024 (Q1+Q2)]]+0.5% -> 0.16670188 | N135: =Table6[[#This Row],[2024 Q3+Q4)]]+0.5% -> 0.17170188 | O135: =Table6[[#This Row],[2025]]+0.5% -> 0.17670188 | P135: =Table6[[#This Row],[2026]]+0.5% -> 0.18170188 | Q135: =Table6[[#This Row],[2027]]+0.5% -> 0.18670188 | R135: =Table6[[#This Row],[2028]]+0.5% -> 0.19170188 | S135: =Table6[[#This Row],[2029]]+0.5% -> 0.19670188 | T135: =Table6[[#This Row],[2030]]+0.5% -> 0.20170188 | U135: =Table6[[#This Row],[2031]]+0.5% -> 0.20670188 | V135: =Table6[[#This Row],[2032]]+0.5% -> 0.21170188 | W135: =Table6[[#This Row],[2033]]+0.5% -> 0.21670188 | X135: =Table6[[#This Row],[2034]]+0.5% -> 0.22170188 | Y135: =Table6[[#This Row],[2035]]+0.5% -> 0.22670188 | Z135: =Table6[[#This Row],[2036]]+0.5% -> 0.23170188 | AA135: =Table6[[#This Row],[2037]]+0.5% -> 0.23670188 | AB135: =Table6[[#This Row],[2038]]+0.5% -> 0.24170188 | AC135: =Table6[[#This Row],[2039]]+0.5% -> 0.24670188 | AD135: =Table6[[#This Row],[2040]]+0.5% -> 0.25170188 | AE135: =Table6[[#This Row],[2041]]+0.5% -> 0.25670188 | AF135: =Table6[[#This Row],[2042]]+0.5% -> 0.26170188 | AG135: =Table6[[#This Row],[2043]]+0.5% -> 0.26670188 | AH135: =Table6[[#This Row],[2044]]+0.5% -> 0.27170188 | AI135: =Table6[[#This Row],[2045]]+0.5% -> 0.27670188 | AJ135: =Table6[[#This Row],[2046]]+0.5% -> 0.28170188 | AK135: =Table6[[#This Row],[2047]]+0.5% -> 0.28670188 | AL135: =Table6[[#This Row],[2048]]+0.5% -> 0.29170188
B138: FY QoQ (Previous Quarter Comparison) | C138: Q1 | D138: Q2 | E138: Q3 | F138: Q4
B139: 2017/2018 | C139: =IFERROR(I104/E104-1,"-") -> - | D139: =IFERROR(J104/F104-1,"-") -> - | E139: =IFERROR(K104/G104-1,"-") -> - | F139: =IFERROR(L104/H104-1,"-") -> -
B140: 2018/2019 | C140: =IFERROR(M104/I104-1,"-") -> - | D140: =IFERROR(N104/J104-1,"-") -> - | E140: =IFERROR(O104/K104-1,"-") -> - | F140: =IFERROR(P104/L104-1,"-") -> 0.85800278 | H140: Green >50% Growth QoQ
B141: 2019/2020 | C141: =IFERROR(Q104/M104-1,"-") -> -0.37870765 | D141: =IFERROR(R104/N104-1,"-") -> -0.91352352 | E141: =IFERROR(S104/O104-1,"-") -> -0.99083316 | F141: =IFERROR(T104/P104-1,"-") -> -0.3157006 | H141: Yellow 0>X>50 Growth QoQ
B142: 2020/2021 | C142: =U104/Q104-1 -> 0.22854966 | D142: =V104/R104-1 -> 6.0687584 | E142: =W104/S104-1 -> 16.171579 | F142: =X104/T104-1 -> 0.53404707 | H142: Red <0% Growth QoQ
B143: 2021/2022 | C143: =Y104/U104-1 -> 0.71608836 | D143: =Z104/V104-1 -> 0.67260861 | E143: =AA104/W104-1 -> 8.5851201 | F143: =AB104/X104-1 -> 0.74466534
B144: 2022/2023 | C144: =AC104/Y104-1 -> 1.2568399 | D144: =AD104/Z104-1 -> 0.40544586 | E144: =AE104/AA104-1 -> 0.50304457 | F144: =AF104/AB104-1 -> 0.084182694
B145: 2023/2024 | C145: =AG104/AC104-1 -> -0.021855817 | D145: =AH104/AD104-1 -> 0.47731166 | E145: -- | F145: --
B148: Quarter on Quarter Basis | C148: Q1 2017 /Q3 2017 (Pilbara) | D148: Q2 2017 | E148: Q3 2017 | F148: Q4 2017 | G148: Q1 2018 | H148: Q2 2018 | I148: Q3 2018 | J148: Q4 2018 | K148: Q1 2019 | L148: Q2 2019 | M148: Q3 2019 | N148: Q4 2019 | O148: Q1 2020 | P148: Q2 2020 | Q148: Q3 2020 | R148: Q4 2020 | S148: Q1 2021 | T148: Q2 2021 | U148: Q3 2021 | V148: Q4 2021 | W148: Q1 2022 | X148: Q2 2022 | Y148: Q3 2022 | Z148: Q4 2022 | AA148: Q1 2023 | AB148: Q2 2023 | AC148: Q3 2023
B149: Real GDP Australia (Domestic Currency, Quarterly, Adjusted for Seasonality) | C149: 524315 | D149: 527584 | E149: 532395 | F149: 534702 | G149: 540338 | H149: 544406 | I149: 546654 | J149: 547965 | K149: 551170 | L149: 552985 | M149: 556078 | N149: 558708 | O149: 557692 | P149: 518939 | Q149: 538204 | R149: 556770 | S149: 568917 | T149: 573804 | U149: 562864 | V149: 586759 | W149: 589562 | X149: 594037 | Y149: 595251 | Z149: 600340 | AA149: 603542 | AB149: 606190 | AC149: 607475
B151: Correlation Analysis | C151: 2015 | D151: 2016 | E151: 2017 | F151: 2018 | G151: 2019 | H151: 2020 | I151: 2021 | J151: 2022 | K151: 2023
B152: Net Sales | C152: ='Fin. Data'!J5 -> 0.1 | D152: ='Fin. Data'!I5 -> 0 | E152: ='Fin. Data'!H5 -> 0 | F152: ='Fin. Data'!G5 -> 10.2 | G152: ='Fin. Data'!F5 -> 42.8 | H152: ='Fin. Data'!E5 -> 84.1 | I152: ='Fin. Data'!D5 -> 175.8 | J152: ='Fin. Data'!C5 -> 1189.6 | K152: ='Fin. Data'!B5 -> 4064
B153: Ore Processed | C153: 0 | D153: 0 | E153: 0 | F153: =F128 -> 0 | G153: =G128 -> 1464652 | H153: =H128 -> 642215 | I153: =I128 -> 1579588 | J153: =J128 -> 2415348 | K153: =K128 -> 3445341
B154: GDP Australia Mining | C154: 272540 | D154: 289829 | E154: 292523 | F154: 306743 | G154: 320937 | H154: 333814 | I154: 323912 | J154: 316846 | K154: 320905
B155: GDP Australia (millions) (Total) | C155: 1988419 | D155: 2043680 | E155: 2091067 | F155: 2151841 | G155: 2198775 | H155: 2191416 | I155: 2237695 | J155: 2333221 | K155: 2406521
B156: Average Price | E156: =AVERAGE(E112:H112) -> 20947.15 | F156: =AVERAGE(I112:L112) -> 18032.033 | G156: =AVERAGE(M112:P112) -> 9895.46 | H156: =AVERAGE(Q112:T112) -> 6227.7925 | I156: =AVERAGE(U112:X112) -> 18932.55 | J156: =AVERAGE(Y112:AB112) -> 71010 | K156: =AVERAGE(AC112:AF112) -> 36234.35
C158: =B159 -> GDP Australia (millions) (Total) | D158: Net Sales | G158: BEV | H158: Ore Processed
B159: =B155 -> GDP Australia (millions) (Total) | C159: 1 | F159: BEV | G159: 1 | J159: Correlation between the sales of BEV and Ore Processed by Pilbara | N159: GDP Australia | O159: Average Lithium Price
B160: Net Sales | C160: 0.76473491 | D160: 1 | F160: Ore Processed | G160: 0.97033825 | H160: 1 | M160: GDP Australia | N160: 1
C161: Net Sales | D161: =B163 -> GDP Australia Mining | M161: Average Lithium Price | N161: 0.62987403 | O161: 1 | R161: Modelling Factor | S161: BEV | T161: 0
B162: Net Sales | C162: 1 | G162: Net Sales | H162: Ore Processed | J162: Correlation between Net Sales Values and Ore Processed by Pilbara | S162: Ore | T162: 0
...

Sheet Fin. Data
A1: ='Inputs (AUD)'!H3 -> #VALUE!
A2: ='Inputs (AUD)'!G2 -> Figures in Millions of AUD
A3: Results
B4: =OP!J21 -> 2023 | C4: =B4-1 -> 2022 | D4: =C4-1 -> 2021 | E4: =D4-1 -> 2020 | F4: =E4-1 -> 2019 | G4: =F4-1 -> 2018 | H4: =G4-1 -> 2017 | I4: =H4-1 -> 2016 | J4: =I4-1 -> 2015 | ... M4: =L4-1 -> 2012
A5: Net Sales | B5: =_xlfn.XLOOKUP($A5,'Inputs (AUD)'!$A:$A,'Inputs (AUD)'!B:B,,0) -> 4064 | C5: =_xlfn.XLOOKUP($A5,'Inputs (AUD)'!$A:$A,'Inputs (AUD)'!C:C,,0) -> 1189.6 | D5: =_xlfn.XLOOKUP($A5,'Inputs (AUD)'!$A:$A,'Inputs (AUD)'!D:D,,0) -> 175.8 | E5: =_xlfn.XLOOKUP($A5,'Inputs (AUD)'!$A:$A,'Inputs (AUD)'!E:E,,0) -> 84.1 | F5: =_xlfn.XLOOKUP($A5,'Inputs (AUD)'!$A:$A,'Inputs (AUD)'!F:F,,0) -> 42.8 | G5: =_xlfn.XLOOKUP($A5,'Inputs (AUD)'!$A:$A,'Inputs (AUD)'!G:G,,0) -> 10.2 | H5: =_xlfn.XLOOKUP($A5,'Inputs (AUD)'!$A:$A,'Inputs (AUD)'!H:H,,0) -> 0 | I5: =_xlfn.XLOOKUP($A5,'Inputs (AUD)'!$A:$A,'Inputs (AUD)'!I:I,,0) -> 0 | J5: =_xlfn.XLOOKUP($A5,'Inputs (AUD)'!$A:$A,'Inputs (AUD)'!J:J,,0) -> 0.1 | K5: =_xlfn.XLOOKUP($A5,'Inputs (AUD)'!$A:$A,'Inputs (AUD)'!K:K,,0) -> 0.3 | L5: =_xlfn.XLOOKUP($A5,'Inputs (AUD)'!$A:$A,'Inputs (AUD)'!L:L,,0) -> 4884 | M5: =_xlfn.XLOOKUP($A5,'Inputs (AUD)'!$A:$A,'Inputs (AUD)'!M:M,,0) -> 0
A6: Growth vs. Previous year | B6: =IFERROR(B5/C5-1,"-") -> 2.4162744 | C6: =IFERROR(C5/D5-1,"-") -> 5.7667804 | D6: =IFERROR(D5/E5-1,"-") -> 1.0903686 | E6: =IFERROR(E5/F5-1,"-") -> 0.96495327 | F6: =IFERROR(F5/G5-1,"-") -> 3.1960784 | G6: =IFERROR(G5/H5-1,"-") -> - | H6: =IFERROR(H5/I5-1,"-") -> - | I6: =IFERROR(I5/J5-1,"-") -> -1 | ... L6: =IFERROR(L5/M5-1,"-") -> - | M6: =IFERROR(M5/#REF!-1,"-") -> -
A7: Gross Profit | B7: =_xlfn.XLOOKUP($A7,'Inputs (AUD)'!$A:$A,'Inputs (AUD)'!B:B,,0) -> 3287.8 | C7: =_xlfn.XLOOKUP($A7,'Inputs (AUD)'!$A:$A,'Inputs (AUD)'!C:C,,0) -> 811.2 | D7: =_xlfn.XLOOKUP($A7,'Inputs (AUD)'!$A:$A,'Inputs (AUD)'!D:D,,0) -> 20.1 | E7: =_xlfn.XLOOKUP($A7,'Inputs (AUD)'!$A:$A,'Inputs (AUD)'!E:E,,0) -> -27.9 | F7: =_xlfn.XLOOKUP($A7,'Inputs (AUD)'!$A:$A,'Inputs (AUD)'!F:F,,0) -> 6.2 | G7: =_xlfn.XLOOKUP($A7,'Inputs (AUD)'!$A:$A,'Inputs (AUD)'!G:G,,0) -> 4 | H7: =_xlfn.XLOOKUP($A7,'Inputs (AUD)'!$A:$A,'Inputs (AUD)'!H:H,,0) -> 0 | I7: =_xlfn.XLOOKUP($A7,'Inputs (AUD)'!$A:$A,'Inputs (AUD)'!I:I,,0) -> 0 | J7: =_xlfn.XLOOKUP($A7,'Inputs (AUD)'!$A:$A,'Inputs (AUD)'!J:J,,0) -> 0 | K7: =_xlfn.XLOOKUP($A7,'Inputs (AUD)'!$A:$A,'Inputs (AUD)'!K:K,,0) -> 0 | L7: =_xlfn.XLOOKUP($A7,'Inputs (AUD)'!$A:$A,'Inputs (AUD)'!L:L,,0) -> 1681 | M7: =_xlfn.XLOOKUP($A7,'Inputs (AUD)'!$A:$A,'Inputs (AUD)'!M:M,,0) -> 0
A8: % over sales | B8: =IFERROR(B7/B$5,"-") -> 0.80900591 | C8: =IFERROR(C7/C$5,"-") -> 0.68190989 | D8: =IFERROR(D7/D$5,"-") -> 0.11433447 | E8: =IFERROR(E7/E$5,"-") -> -0.33174792 | F8: =IFERROR(F7/F$5,"-") -> 0.14485981 | G8: =IFERROR(G7/G$5,"-") -> 0.39215686 | H8: =IFERROR(H7/H$5,"-") -> - | I8: =IFERROR(I7/I$5,"-") -> - | ... M8: =IFERROR(M7/M$5,"-") -> -
A9: Operating expenses | B9: =B5-B11 -> 852.1 | C9: =C5-C11 -> 457.7 | D9: =D5-D11 -> 210.8 | E9: =E5-E11 -> 155.7 | F9: =F5-F11 -> 61.3 | G9: =G5-G11 -> 27.1 | H9: =H5-H11 -> 28 | I9: =I5-I11 -> 53.2 | ... M9: =M5-M11 -> 0
A10: % over sales | B10: =IFERROR(B9/B$5,"-") -> 0.20967028 | C10: =IFERROR(C9/C$5,"-") -> 0.38475118 | D10: =IFERROR(D9/D$5,"-") -> 1.1990899 | E10: =IFERROR(E9/E$5,"-") -> 1.8513674 | F10: =IFERROR(F9/F$5,"-") -> 1.432243 | G10: =IFERROR(G9/G$5,"-") -> 2.6568627 | H10: =IFERROR(H9/H$5,"-") -> - | I10: =IFERROR(I9/I$5,"-") -> - | ... M10: =IFERROR(M9/M$5,"-") -> -
A11: Operating Income | B11: =_xlfn.XLOOKUP($A11,'Inputs (AUD)'!$A:$A,'Inputs (AUD)'!B:B,,0) -> 3211.9 | C11: =_xlfn.XLOOKUP($A11,'Inputs (AUD)'!$A:$A,'Inputs (AUD)'!C:C,,0) -> 731.9 | D11: =_xlfn.XLOOKUP($A11,'Inputs (AUD)'!$A:$A,'Inputs (AUD)'!D:D,,0) -> -35 | E11: =_xlfn.XLOOKUP($A11,'Inputs (AUD)'!$A:$A,'Inputs (AUD)'!E:E,,0) -> -71.6 | F11: =_xlfn.XLOOKUP($A11,'Inputs (AUD)'!$A:$A,'Inputs (AUD)'!F:F,,0) -> -18.5 | G11: =_xlfn.XLOOKUP($A11,'Inputs (AUD)'!$A:$A,'Inputs (AUD)'!G:G,,0) -> -16.9 | H11: =_xlfn.XLOOKUP($A11,'Inputs (AUD)'!$A:$A,'Inputs (AUD)'!H:H,,0) -> -28 | I11: =_xlfn.XLOOKUP($A11,'Inputs (AUD)'!$A:$A,'Inputs (AUD)'!I:I,,0) -> -53.2 | J11: =_xlfn.XLOOKUP($A11,'Inputs (AUD)'!$A:$A,'Inputs (AUD)'!J:J,,0) -> -5.2 | K11: =_xlfn.XLOOKUP($A11,'Inputs (AUD)'!$A:$A,'Inputs (AUD)'!K:K,,0) -> -3 | L11: =_xlfn.XLOOKUP($A11,'Inputs (AUD)'!$A:$A,'Inputs (AUD)'!L:L,,0) -> 718 | M11: =_xlfn.XLOOKUP($A11,'Inputs (AUD)'!$A:$A,'Inputs (AUD)'!M:M,,0) -> 0
A12: Operating Margin | B12: =IFERROR(B11/B$5,"-") -> 0.79032972 | C12: =IFERROR(C11/C$5,"-") -> 0.61524882 | D12: =IFERROR(D11/D$5,"-") -> -0.19908987 | E12: =IFERROR(E11/E$5,"-") -> -0.85136742 | F12: =IFERROR(F11/F$5,"-") -> -0.43224299 | G12: =IFERROR(G11/G$5,"-") -> -1.6568627 | H12: =IFERROR(H11/H$5,"-") -> - | I12: =IFERROR(I11/I$5,"-") -> - | ... M12: =IFERROR(M11/M$5,"-") -> -
A13: Growth vs. Previous year | B13: =IFERROR(B12/C12-1,"-") -> 0.28456926 | C13: =IFERROR(C12/D12-1,"-") -> -4.0903069 | D13: =IFERROR(D12/E12-1,"-") -> -0.76615281 | E13: =IFERROR(E12/F12-1,"-") -> 0.96965003 | F13: =IFERROR(F12/G12-1,"-") -> -0.73911962 | G13: =IFERROR(G12/H12-1,"-") -> - | H13: =IFERROR(H12/I12-1,"-") -> - | I13: =IFERROR(I12/J12-1,"-") -> - | ... L13: =IFERROR(L12/M12-1,"-") -> - | M13: =IFERROR(M12/#REF!-1,"-") -> -
A14: Net Financial Cost | B14: =_xlfn.XLOOKUP($A14,'Inputs (AUD)'!$A:$A,'Inputs (AUD)'!B:B,,0) -> 44.9 | C14: =_xlfn.XLOOKUP($A14,'Inputs (AUD)'!$A:$A,'Inputs (AUD)'!C:C,,0) -> -12.5 | D14: =_xlfn.XLOOKUP($A14,'Inputs (AUD)'!$A:$A,'Inputs (AUD)'!D:D,,0) -> -15.1 | E14: =_xlfn.XLOOKUP($A14,'Inputs (AUD)'!$A:$A,'Inputs (AUD)'!E:E,,0) -> -22.5 | F14: =_xlfn.XLOOKUP($A14,'Inputs (AUD)'!$A:$A,'Inputs (AUD)'!F:F,,0) -> -3.9 | G14: =_xlfn.XLOOKUP($A14,'Inputs (AUD)'!$A:$A,'Inputs (AUD)'!G:G,,0) -> 1.5 | H14: =_xlfn.XLOOKUP($A14,'Inputs (AUD)'!$A:$A,'Inputs (AUD)'!H:H,,0) -> 2.1 | I14: =_xlfn.XLOOKUP($A14,'Inputs (AUD)'!$A:$A,'Inputs (AUD)'!I:I,,0) -> -2.2 | J14: =_xlfn.XLOOKUP($A14,'Inputs (AUD)'!$A:$A,'Inputs (AUD)'!J:J,,0) -> -0.2 | K14: =_xlfn.XLOOKUP($A14,'Inputs (AUD)'!$A:$A,'Inputs (AUD)'!K:K,,0) -> -0.2 | L14: =_xlfn.XLOOKUP($A14,'Inputs (AUD)'!$A:$A,'Inputs (AUD)'!L:L,,0) -> -67 | M14: =_xlfn.XLOOKUP($A14,'Inputs (AUD)'!$A:$A,'Inputs (AUD)'!M:M,,0) -> 0
