Workbook
Name Sectors: '[1]Sector Impact'!$K$4:$K$16
Name Sectors: 'Sector Impact'!$K$4:$K$16

Sheet OP
B2: 45039 | C2: Team 1 | D2: 45303 | E2: UNITEDHEALTH GROUP INCORPORATED (XNYS:UNH) | L2: NYSE | M2: SIC: 6321
D3: COMPANY DESCRIPTION | H3: CEO & BOARD OF DIRECTORS
D4: {=_FV(Inputs!H3,"Description")} -> UnitedHealth Group Incorporated is a healthcare company. The Company has two businesses, Optum and UnitedHealthcare. Optum serves the health care marketplace, including patients and consumers, payers, care providers, employers, governments and life sciences companies. UnitedHealthcare offers a full range of health benefits designed to simplify the health care experience and make it more affordable for consumers to access care. UnitedHealthcare Employer & Individual serves consumers and employers, ranging from sole proprietorships to large, multi-site and national employers and public sector employers. UnitedHealthcare Medicare & Retirement delivers health and well-being benefits to seniors and other Medicare eligible consumers. The Company’s segments include Optum Health, Optum Insight, Optum Rx and UnitedHealthcare. UnitedHealthcare segment includes UnitedHealthcare Employer & Individual, UnitedHealthcare Medicare & Retirement and UnitedHealthcare Community & State. | H4: Name (Gender;Age) | I4: Tenure | J4: Executive? | K4: Other roles
H5: Charles Baker (M; 67) | I5: 0 | J5: No | K5: Current President of NCAA
H6: Timothy Flynn (M; 65) | I6: 6 | J6: No | K6: Chairman and CEO of KPMG International
H7: Paul Garcia (M; 69) | I7: 2 | J7: No | K7: Retired Chair & Chief Executive Officer Global Payments Inc.
H8: Kristen Gil (W; 50) | I8: 1 | J8: No | K8: Vice President of Business and Operations at Google
H9: Stephen Hemsley (M; 71) | I9: 23 | J9: Yes | K9: Executive Chairman of the Board UnitedHealth Group
H10: Michele Hooper (W; 72) | I10: 16 | J10: No | K10: Board Member of Black Directors Health Equity Agenda
H11: F. William McNabb III (M; 66) | I11: 5 | J11: No | K11: None
H12: Valerie Montgomery Rice, M.D. (W; 62) | I12: 6 | J12: No | K12: President and CEO, Morehouse School of Medicine
H13: John Noseworthy, M.D. (M; 72) | I13: 4 | J13: No | K13: Board Member at: Mitre an AlixPartners, Executive Chair at Caire and Chairman at Aegis Ventures
H14: Sir Andrew Witty (M; 59) | I14: 2 | J14: Yes | K14: CEO of UnitedHealth Group
B17: USD MILLIONS
B18: COMPANY OVERVIEW
B19: Stock | D19: Liquidity and Solvency | F19: Segments | I19: Profitability (2022) | L19: Multiples
B20: Last Price | C20: 523.28 | D20: Total Assets | E20: =_xlfn.XLOOKUP(D20,'[2]Fin. Data1'!A:A,'[2]Fin. Data1'!B:B,,0) -> 245705 | F20: Regions | H20: % Sales | I20: Reporting Year | J20: 2022 | L20: Float | M20: 0.996
B21: Outstanding Shares | C21: 924925300 | D21: Total Liabilities | E21: =_xlfn.XLOOKUP(D21,'[2]Fin. Data1'!A:A,'[2]Fin. Data1'!B:B,,0) -> 159358 | F21: =Segments!C5 -> USA | H21: =[2]Segments1!B5 -> 0.89631492 | I21: End of Year | J21: 1 October 2022 | L21: Insiders Own | M21: 0.0025
B22: Market Cap. | C22: =C20*C21/1000000 -> 483994.91 | D22: Cash/Share | E22: =_xlfn.XLOOKUP("Cash & Eq.",'[2]Fin. Data1'!A:A,'[2]Fin. Data1'!B:B,,0)*1000000/C21 -> 30.176491 | F22: =Segments!C6 -> Global | H22: =[2]Segments1!B6 -> 0.10368508 | I22: EBITDA | K22: =_xlfn.XLOOKUP(I22,'[2]Fin. Data1'!A:A,'[2]Fin. Data1'!B:B,,0) -> 31835 | L22: b (Yahoo) | M22: 0.55
B23: +Total Debt | C23: ='[2]Fin. Data1'!B58 -> 63467 | D23: EBITDA/Net Financial Cost (NFC) | E23: =_xlfn.XLOOKUP("EBITDA",'[2]Fin. Data1'!A:A,'[2]Fin. Data1'!B:B,,0)/_xlfn.XLOOKUP("Net Financial Cost",'[2]Fin. Data1'!A:A,'[2]Fin. Data1'!B:B,,0) -> -15.217495 | I23: Depreciation & Amortization | K23: =_xlfn.XLOOKUP(I23,'[2]Fin. Data1'!A:A,'[2]Fin. Data1'!B:B,,0) -> 3400 | L23: Score (S&P)
B24: -Cash | C24: ='[2]Fin. Data1'!B39 -> 27911 | D24: Debt/EBITDA | E24: =_xlfn.XLOOKUP("Total Debt",'[2]Fin. Data1'!A:A,'[2]Fin. Data1'!B:B,,0)/_xlfn.XLOOKUP("EBITDA",'[2]Fin. Data1'!A:A,'[2]Fin. Data1'!B:B,,0) -> 1.9936234 | I24: EBIT | K24: =_xlfn.XLOOKUP(I24,'[2]Fin. Data1'!A:A,'[2]Fin. Data1'!B:B,,0) -> 28435 | L24: Price/Book Value | M24: =IFERROR((C20*C21/(E20-E21))/1000000,"") -> 5.6052313
B25: =Enterprise Value | C25: =C22+C23-C24 -> 519550.91 | D25: "Others Assets"/Asset | E25: =_xlfn.XLOOKUP("Other Assets",'[2]Fin. Data1'!A:A,'[2]Fin. Data1'!B:B,,0)/_xlfn.XLOOKUP("Total Assets",'[2]Fin. Data1'!A:A,'[2]Fin. Data1'!B:B,,0) -> 0.52904092 | I25: Net Income | K25: =_xlfn.XLOOKUP(I25,'[2]Fin. Data1'!A:A,'[2]Fin. Data1'!B:B,,0) -> 20639 | L25: NCF(3y avg)/Asset | M25: =IFERROR(K31/E20,"") -> 0.073448512
B26: Holdings (nac/int'l) | C26: - | D26: Debt/Assets | E26: =_xlfn.XLOOKUP(D26,'[2]Fin. Data1'!A:A,'[2]Fin. Data1'!B:B,,0) -> 0.25830569 | F26: Categories | H26: % Sales | I26: EPS | K26: =1000000*K25/C21 -> 22.314234 | L26: Price/Net Inc. (3y avg) | M26: =IFERROR(C22/K30,"") -> 26.819075
B27: t liq. (Holdings/Vol.) | C27: - | D27: EBITDA Margin (average) | E27: =AVERAGE(_xlfn.XLOOKUP("EBITDA Margin",'[2]Fin. Data1'!A:A,'[2]Fin. Data1'!B:D,,0)) -> 0.096905436 | F27: =[2]Segments1!C14 -> UnitedHealthcare | H27: =[2]Segments1!B14 -> 0.45708633 | I27: ROA | K27: =K25/E20 -> 0.083999105 | L27: EV/Asset | M27: =IFERROR(C25/E20,"") -> 2.1145313
B28: % Short | C28: 0.0065 | D28: Operating Margin (average) | E28: =AVERAGE(_xlfn.XLOOKUP("Operating Margin",'[2]Fin. Data1'!A:A,'[2]Fin. Data1'!B:D,,0)) -> 0.086065155 | F28: =[2]Segments1!C16 -> Optum Insight | H28: =[2]Segments1!B16 -> 0.043686033 | I28: ROIC | K28: =K25/(E20-(E21-C23)) -> 0.13776416 | L28: EV/Ebitda (3y average) | M28: =IFERROR(C25/K29,"") -> 18.510436
B29: Traffic ESG | D29: Net Income Margin (average) | E29: =AVERAGE(_xlfn.XLOOKUP("Net Income Margin",'[2]Fin. Data1'!A:A,'[2]Fin. Data1'!B:D,,0)) -> 0.062216278 | F29: =[2]Segments1!C17 -> Optum Rx | H29: =[2]Segments1!B17 -> 0.29413627 | I29: EBITDA (3y average) | K29: =AVERAGE(_xlfn.XLOOKUP("EBITDA",'[2]Fin. Data1'!A:A,'[2]Fin. Data1'!B:D,,0)) -> 28068 | L29: Price/NCF (3y average) | M29: =IFERROR(C22/K31,"") -> 26.819075
B30: E | F30: =Segments!C15 -> Optum Health | H30: =Segments!B15 -> 0.20509137 | I30: Net Income (3y average) | K30: =AVERAGE(_xlfn.XLOOKUP("Net Income",'[2]Fin. Data1'!A:A,'[2]Fin. Data1'!B:D,,0)) -> 18046.667 | L30: Bonds 1,3,5a (USD) | M30: -
B31: S | D31: Net Financial Cost/Avg Net Debt | E31: =-_xlfn.XLOOKUP("Net Financial Cost",'[2]Fin. Data1'!A:A,'[2]Fin. Data1'!B:B,,0)/AVERAGE(_xlfn.XLOOKUP("Net Debt",'[2]Fin. Data1'!A:A,'[2]Fin. Data1'!B:D,,0)) -> 0.067207093 | I31: NCF (3y average) | K31: =AVERAGE(_xlfn.XLOOKUP("Net Income",'[2]Fin. Data1'!A:A,'[2]Fin. Data1'!B:D,,0)) -> 18046.667 | L31: Div+Rep.(3y avg)/Price | M31: =-IFERROR(SUM(E52:E54)/(3*C22),"") -> 0.019323206
B32: G | L32: Div. Yield | M32: =-IFERROR(L53/C22,"") -> 0.012378229
B33: INVESTMENT THESIS
B34: Pillars of Recommendation | H34: Recommendation | I34: Valuation Assumptions
B35: Pillar | C35: Explanation | H35: Sell | I35: CHECK DCF
B36: Inorganic Growth | C36: UNH has high anticipation of acquisition as a growth strategy.
B37: Backed Investment | C37: Although UNH is considered overvalued and its stock price is inflated, it would not be reasonable to sell for mulitple reasons. Company and stock are considered safe bets as default and bankruptcy risk is low, company is able to sell off assets and companies in the case of emergency ('too big to fail'). High speculation of price increase by other investors/institutions. Majority shareholders (institutional) are Vanguard and Fidelity, which have high investing and political influence, and can therefore lobby for favourable conditions for UNH in the case of emergency.
B38: Safe Industry to Invest in | C38: Healthcare in general is typically a more stable industry to invest in. Even in times of economic/social/catastrophic/other distresses, individuals need to go to the doctor, buy medicine and other medical aids, and especially need insurance. This causes the industry to sometimes profit during times of distress (ie. Covid) as well.
B39: Risks of Investment | H39: Price Target | I39: Valuation
B40: Risk | C40: Explanation | H40: $550 | I40: Discount Rate | J40: =DCF!F50 -> 0.0805 | L40: Price M. Upside | M40: =SARD!AJ14 -> -0.3625604
B41: Regulatory risk | C41: Healthcare and Insurance industries in the US is highly subject to regulations, which are highly dependant upon political motives of the countries leaders. (Thinking ahead to 2024 presidential election and onwards)
B42: Political risk | C42: UNH is closely related to (and even employs) current or former politicians with certain ideologies. Possible cause for negative perception due to political preference of customers. | I42: Upside | J42: =DCF!D76 -> -0.068100445 | L42: EV M. Upside | M42: =SARD!AM14 -> -0.53244397
B43: Exchange Rate risk | C43: Around 10% of UNH's revenue is from out of the US and this portion is subject to exchance rate risk.
B44: FINANCIAL PERFORMANCE
B45: Year | C45: Net Sales | D45: Operating Margin | E45: Dividends + Share Buyback | F45: Net Cash Flow | G45: Debt/Assets | H45: Depreciation & Amortization | I45: Capex + Investments | J45: Cash Flow
B46: =B47-1 -> 2014 | C46: {=_xlfn.SORTBY(TRANSPOSE(_xlfn.XLOOKUP(C$45,'[2]Fin. Data1'!$A:$A,'[2]Fin. Data1'!$B:$J,,0)),$B$46:$B$54,-1)} -> 130474 | D46: {=_xlfn.SORTBY(TRANSPOSE(_xlfn.XLOOKUP(D$45,'[2]Fin. Data1'!$A:$A,'[2]Fin. Data1'!$B:$J,,0)),$B$46:$B$54,-1)} -> 0.078743658 | E46: {=_xlfn.SORTBY(TRANSPOSE(_xlfn.XLOOKUP(E$45,'[2]Fin. Data1'!$A:$A,'[2]Fin. Data1'!$B:$J,,0)),$B$46:$B$54,-1)} -> -4908 | F46: =[2]Inputs1!J77 -> 219 | G46: {=_xlfn.SORTBY(TRANSPOSE(_xlfn.XLOOKUP(G$45,'[2]Fin. Data1'!$A:$A,'[2]Fin. Data1'!$B:$J,,0)),$B$46:$B$54,-1)} -> 0.27703688 | H46: {=_xlfn.SORTBY(TRANSPOSE(_xlfn.XLOOKUP(H$45,'[2]Fin. Data1'!$A:$A,'[2]Fin. Data1'!$B:$J,,0)),$B$46:$B$54,-1)} -> 1478 | I46: {=_xlfn.SORTBY(TRANSPOSE(_xlfn.XLOOKUP(I$45,'[2]Fin. Data1'!$A:$A,'[2]Fin. Data1'!$B:$J,,0)),$B$46:$B$54,-1)} -> -2534 | L46: =J20 -> 2022 | M46: =L46-1 -> 2021
B47: =B48-1 -> 2015 | C47: 157107 | D47: 0.070149643 | E47: -2584 | F47: =[2]Inputs1!I77 -> 3428 | G47: 0.36124544 | H47: 1693 | I47: -18395 | J47: Net Income | L47: =_xlfn.XLOOKUP($J47,'[2]Fin. Data1'!$A:$A,'[2]Fin. Data1'!B:B,,0) -> 20639 | M47: =_xlfn.XLOOKUP($J47,'[2]Fin. Data1'!$A:$A,'[2]Fin. Data1'!C:C,,0) -> 17732 | N47: =(C47/C46)-1 -> 0.20412496 | O47: =(D47/D46)-1 -> -0.10913913
B48: =B49-1 -> 2016 | C48: 184840 | D48: 0.069952391 | E48: -3112 | F48: =[2]Inputs1!H77 -> -493 | G48: 0.32752219 | H48: 2055 | I48: -9355 | J48: Operating CF | L48: =_xlfn.XLOOKUP($J48,'[2]Fin. Data1'!$A:$A,'[2]Fin. Data1'!B:B,,0) -> 26206 | M48: =_xlfn.XLOOKUP($J48,'[2]Fin. Data1'!$A:$A,'[2]Fin. Data1'!C:C,,0) -> 22343 | N48: =(C48/C47)-1 -> 0.17652301 | O48: =(D48/D47)-1 -> -0.0028118743 | Q48: =F48/F47-1 -> -1.1438156 | R48: =H48/H47-1 -> 0.21382162 | S48: =I48/I47-1 -> -0.49143789
B49: =B50-1 -> 2017 | C49: 201159 | D49: 0.075606858 | E49: -3585 | F49: =[2]Inputs1!G77 -> 1551 | G49: 0.25991313 | H49: 2245 | I49: -8599 | J49: Investing CF | L49: =_xlfn.XLOOKUP($J49,'[2]Fin. Data1'!$A:$A,'[2]Fin. Data1'!B:B,,0) -> -28476 | M49: =_xlfn.XLOOKUP($J49,'[2]Fin. Data1'!$A:$A,'[2]Fin. Data1'!C:C,,0) -> -10372 | N49: =(C49/C48)-1 -> 0.088287167 | O49: =(D49/D48)-1 -> 0.080833077 | Q49: =F49/F48-1 -> -4.1460446 | R49: =H49/H48-1 -> 0.092457421 | S49: =I49/I48-1 -> -0.0808124
B50: =B51-1 -> 2018 | C50: 226247 | D50: 0.07665958 | E50: -6982 | F50: =[2]Inputs1!F77 -> -1115 | G50: 0.27213065 | H50: 2428 | I50: -12385 | J50: Net Capex | L50: =_xlfn.XLOOKUP($J50,'[2]Fin. Data1'!$A:$A,'[2]Fin. Data1'!B:B,,0) -> -2802 | M50: =_xlfn.XLOOKUP($J50,'[2]Fin. Data1'!$A:$A,'[2]Fin. Data1'!C:C,,0) -> -2454 | N50: =(C50/C49)-1 -> 0.12471726 | O50: =(D50/D49)-1 -> 0.013923628 | Q50: =F50/F49-1 -> -1.718891 | R50: =H50/H49-1 -> 0.081514477 | S50: =I50/I49-1 -> 0.44028375
B51: =B52-1 -> 2019 | C51: 242155 | D51: 0.081290909 | E51: -8395 | F51: =[2]Inputs1!E77 -> 119 | G51: 0.26622156 | H51: 2720 | I51: -12699 | J51: Investments & Acquisitions | L51: =_xlfn.XLOOKUP($J51,'[2]Fin. Data1'!$A:$A,'[2]Fin. Data1'!B:B,,0) -> -25674 | M51: =_xlfn.XLOOKUP($J51,'[2]Fin. Data1'!$A:$A,'[2]Fin. Data1'!C:C,,0) -> -7918 | N51: =(C51/C50)-1 -> 0.070312535 | O51: =(D51/D50)-1 -> 0.06041422 | Q51: =F51/F50-1 -> -1.1067265 | R51: =H51/H50-1 -> 0.12026359 | S51: =I51/I50-1 -> 0.02535325
B52: =B53-1 -> 2020 | C52: 257141 | D52: 0.087131185 | E52: -7394 | F52: =[2]Inputs1!D77 -> 5936 | G52: 0.25179305 | H52: 2891 | I52: -12532 | J52: Financing CF | L52: =_xlfn.XLOOKUP($J52,'[2]Fin. Data1'!$A:$A,'[2]Fin. Data1'!B:B,,0) -> 4226 | M52: =_xlfn.XLOOKUP($J52,'[2]Fin. Data1'!$A:$A,'[2]Fin. Data1'!C:C,,0) -> -7455 | N52: =(C52/C51)-1 -> 0.061885982 | O52: =(D52/D51)-1 -> 0.071844149 | Q52: =F52/F51-1 -> 48.882353 | R52: =H52/H51-1 -> 0.062867647 | S52: =I52/I51-1 -> -0.013150642
B53: =B54-1 -> 2021 | C53: 287597 | D53: 0.083345793 | E53: -8925 | F53: =[2]Inputs1!C$77 -> 4454 | G53: 0.24428621 | H53: 3103 | I53: -10372 | J53: Dividends | L53: =_xlfn.XLOOKUP($J53,'[2]Fin. Data1'!$A:$A,'[2]Fin. Data1'!B:B,,0) -> -5991 | M53: =_xlfn.XLOOKUP($J53,'[2]Fin. Data1'!$A:$A,'[2]Fin. Data1'!C:C,,0) -> -5280 | N53: =(C53/C52)-1 -> 0.11844086 | O53: =(D53/D52)-1 -> -0.043444743 | Q53: =F53/F52-1 -> -0.24966307 | R53: =H53/H52-1 -> 0.073331027 | S53: =I53/I52-1 -> -0.17235876
B54: =J20 -> 2022 | C54: 324162 | D54: 0.087718486 | E54: -11738 | F54: =[2]Inputs1!B77 -> 1990 | G54: 0.25830569 | H54: 3400 | I54: -28476 | J54: Share Buyback | L54: =_xlfn.XLOOKUP($J54,'[2]Fin. Data1'!$A:$A,'[2]Fin. Data1'!B:B,,0) -> -5747 | M54: =_xlfn.XLOOKUP($J54,'[2]Fin. Data1'!$A:$A,'[2]Fin. Data1'!C:C,,0) -> -3645 | N54: =(C54/C53)-1 -> 0.12713971 | O54: =(D54/D53)-1 -> 0.052464478 | Q54: =F54/F53-1 -> -0.5532106 | R54: =H54/H53-1 -> 0.095713825 | S54: =I54/I53-1 -> 1.7454686
B55: Annual Growth Rate | C55: =IFERROR((C54/C46)^(1/8)-1,"") -> 0.12048169 | D55: =IFERROR((D54/D46)^(1/8)-1,"") -> 0.013583292 | F55: =IFERROR((F54/F46)^(1/8)-1,"") -> 0.3176532 | H55: =IFERROR((H54/H46)^(1/8)-1,"") -> 0.10975104 | J55: FX | L55: =_xlfn.XLOOKUP($J55,'[2]Fin. Data1'!$A:$A,'[2]Fin. Data1'!B:B,,0) -> 34 | M55: =_xlfn.XLOOKUP($J55,'[2]Fin. Data1'!$A:$A,'[2]Fin. Data1'!C:C,,0) -> -62 | N55: =(C55/C54)-1 -> -0.99999963 | O55: =(D55/D54)-1 -> -0.84514903
B56: Average Growth Rate | C56: =IFERROR(AVERAGE(N47:N54),"") -> 0.12142894 | D56: =IFERROR(AVERAGE(O47:O54),"") -> 0.015510475 | F56: =IFERROR(AVERAGE(Q47:Q54),"") -> 5.7091431 | H56: =IFERROR(AVERAGE(S47:S54),"") -> 0.20762084 | J56: Changes in Cash | L56: =L48-L49+L52-L53-L54 -> 70646 | M56: =M48-M49+M52-M53-M54 -> 34185
B57: CVAR | C57: =IFERROR(STDEV(C47:C54)/AVERAGE(C47:C54),"") -> 0.23337145 | D57: =IFERROR(STDEV(D46:D54)/AVERAGE(D46:D54),"") -> 0.082990762 | F57: =IFERROR(STDEV(F46:F54)/AVERAGE(F46:F54),"") -> 1.3410414 | H57: =IFERROR(STDEV(H46:H54)/AVERAGE(H46:H54),"") -> 0.26308528 | J57: Inventory/D Revenues | L57: =IFERROR(SUM(I51:I54)/(C54-C50),"") -> -0.65443497 | M57: =IFERROR((SUM(I51:I54)-SUM(H51:H54))/(C54-C50),"") -> -0.77815452
B58: Last Year | C58: =IFERROR(C54/C53-1,"") -> 0.12713971 | D58: =IFERROR(D54/D53-1,"") -> 0.052464478 | F58: =IFERROR(1-(F54/F53),"") -> 0.5532106 | H58: =IFERROR(1-(H54/H53),"") -> -0.095713825 | J58: t inversiones; t adq. neto dep. | L58: =IFERROR(L57/E27,"") -> -6.753336 | M58: =IFERROR(M57/E27,"") -> -8.0300399
B59: QUALITATIVE ANALYSIS
B60: SWOT ANALYSIS | J60: HOLDERS
B61: Pros | E61: Cons | J61: Name | M61: % Stake
B62: Market Leader - UHG is the largest health insurer in the United States. The company had 2X the revenues of the secound largest healht insurance (in the USA), in 2021. Investment in healthcare technology - UHG has a technological and innovation-oriented growth. The company has invested heavily in developing and using technology to improve its operations, evident through its Optum brand, and provide better care to its members. Diversified business model - UHG operates in four main segments: Unitedhealthcare, OptumInsight, OptumRx, and OptumHealth. Strong brand reputation - UHG is a well-respected brand in the healthcare industry. The company has a strong reputation for customer service and innovation. | E62: Reliance on premiums - UHG is heavily reliant on premiums for its revenue. This makes the company sensitive to changes in medical/healthcare costs and benefit designs. Legal challenges - UHG has faced a number of legal challenges in recent years, including lawsuits related to its business practices, and its focus on profits over patient care. Dependency on technology - UHG heavily relies on technology to manage its operations and provide services to customers. UHG should be carefull about how they use those technologies ans AI Algorithms or they could significantly impact the company's operations, reputation, and financial performance. | J62: Insiders
J63: Mr. Stephen J. Hemsley | M63: 6.8711672e-07
J64: Mr. John F. Rex | M64: 1.6596354e-07
J65: Sir Andrew P. Witty | M65: 8.4657051e-08
J66: Mr. Dirk C. McMahon | M66: 6.8965965e-08
J67: Ms. Michele J. Hooper | M67: 4.1664144e-08
J68: Total Insiders | M68: 0.0025
J70: Institutional Holders
J71: Vanguard Group Inc | M71: 0.0904
B72: Opportunities | E72: Risks | J72: Blackrock Inc. | M72: 0.0788
B73: Technological Advancements and additions to healthcare services value chain - UHG can use technology to improve the care it provides to its members, as well as to improve efficiency, and personalize care. Expanding into new markets - UHG has the opportunity to expand into new markets, such as international markets and new segments of the healthcare industry. Partnering with other organizations - UHG can partner with other organizations to improve the care it provides to its members, and reduce costs. | E73: Politics & Regulation - The healthcare industry is subject to frequent changes in laws, regulations, and reimbursement rates. UnitedHealth Group needs to closely monitor these changes and adapt its business strategies accordingly to maintain its competitive edge. Increasing competition in the healthcare industry - The healthcare industry is becoming increasingly competitive, with new entrants and new technologies. UHG faces competition from various players, including other health insurance providers, hospitals, clinics, and technology companies. | J73: State Street Corporation | M73: 0.048
J74: FMR, LLC | M74: 0.047
J75: Capital World Investors | M75: 0.0312
J76: Price (T.Rowe) Associates Inc | M76: 0.0289
J77: Wellington Management Group, LLP | M77: 0.0273
J78: JP Morgan Chase & Company | M78: 0.0252
J79: Geode Capital Management, LLC | M79: 0.0193
J80: Morgan Stanley | M80: 0.017
J81: Total Institutional Holders | M81: 0.8945
B82: NOTES | G82: STOCK PERFORMANCE (5 years)
B83: UNH is highly backed by Vanguard Group and also hired F. William McNabb III, their former CEO, as one of its directors. Further investigation into the relationship between these 2 organizations and analysis of Vanguard Group's investment strategy (and how they choose to influence their investments) could give good insight into how UNH decides to conduct its business.
G107: =E2 -> UNITEDHEALTH GROUP INCORPORATED (XNYS:UNH) | I107: =Peers!D50 -> #VALUE! | J107: =Peers!E50 -> #VALUE! | L107: =Peers!F50 -> #VALUE!

Sheet Segments
B2: ="Regions "&"("&[2]OP1!$J$20&")" -> Regions (2022) | Q2: Products
D3: Nominal value ($ Million) | K3: YoY Growth | Q3: Neither United Health Group nor Optum manufacture any products, they are a services company. Althought they do sell some medicines and pharmaceutical products, even direct-to-consumer, they sell it as retailers rather than manufacturers. Additionally, they specialize in different management and logisitics services regarding healthcare and pharamceuticals, again however, they do not actually manufacture any products
B4: Weight | C4: Region | D4: =[2]OP1!J20 -> 2022 | E4: =D4-1 -> 2021 | F4: =E4-1 -> 2020 | G4: =F4-1 -> 2019 | H4: =G4-1 -> 2018 | I4: =H4-1 -> 2017 | K4: =[2]OP1!J20 -> 2022 | L4: =K4-1 -> 2021 | M4: =L4-1 -> 2020 | N4: =M4-1 -> 2019 | O4: =N4-1 -> 2018 | P4: =O4-1 -> 2017
B5: =IFERROR(D5/$D$9,"") -> 0.89631492 | C5: USA | D5: =D21*(46335000/51695000) -> 290551.24 | E5: =E21*(45120000/50630000) -> 256298.18 | F5: =F21*(43010000/48435000) -> 228339.72 | G5: =G21*(43430000/49150000) -> 213973.38 | H5: =H21*(42855000/49075000) -> 197571.37 | I5: =I21*(42595000/46675000) -> 183575.1 | K5: =(D5-E5)/E5 -> 0.13364536 | L5: =(E5-F5)/F5 -> 0.12244236 | M5: =(F5-G5)/G5 -> 0.067140786 | N5: =(G5-H5)/H5 -> 0.083018132 | O5: =(H5-I5)/I5 -> 0.076242794 | P5: -
B6: =IFERROR(D6/$D$9,"") -> 0.10368508 | C6: Global | D6: =D21*(5360000/51695000) -> 33610.762 | E6: =E21*(5510000/50630000) -> 31298.824 | F6: =F21*(5425000/48435000) -> 28801.279 | G6: =G21*(5720000/49150000) -> 28181.62 | H6: =H21*(6220000/49075000) -> 28675.626 | I6: =I21*(4080000/46675000) -> 17583.904 | K6: =(D6-E6)/E6 -> 0.073866588 | L6: =(E6-F6)/F6 -> 0.086716487 | M6: =(F6-G6)/G6 -> 0.021988054 | N6: =(G6-H6)/H6 -> -0.017227395 | O6: =(H6-I6)/I6 -> 0.63078835 | P6: -
B7: =IFERROR(D7/$D$9,"") -> 0
B8: =IFERROR(D8/$D$9,"") -> 0
B9: =SUM(B5:B8) -> 1 | C9: TOTAL | D9: =SUM(D5:D8) -> 324162 | E9: =SUM(E5:E8) -> 287597 | F9: =SUM(F5:F8) -> 257141 | G9: =SUM(G5:G8) -> 242155 | H9: =SUM(H5:H8) -> 226247 | I9: =SUM(I5:I8) -> 201159 | K9: =(D9-E9)/E9 -> 0.12713971 | L9: =(E9-F9)/F9 -> 0.11844086 | M9: =(F9-G9)/G9 -> 0.061885982 | N9: =(G9-H9)/H9 -> 0.070312535 | O9: =(H9-I9)/I9 -> 0.12471726 | P9: -
B11: ="Categories "&"("&[2]OP1!$J$20&")" -> Categories (2022)
D12: Nominal value ($ Million) | K12: YoY Growth
B13: Weight | C13: Category | D13: =[2]OP1!J20 -> 2022 | E13: =D13-1 -> 2021 | F13: =E13-1 -> 2020 | G13: =F13-1 -> 2019 | H13: =G13-1 -> 2018 | I13: =H13-1 -> 2017 | K13: =[2]OP1!J20 -> 2022 | L13: =K13-1 -> 2021 | M13: =L13-1 -> 2020 | N13: =M13-1 -> 2019 | O13: =N13-1 -> 2018 | P13: =O13-1 -> 2017
B14: =IFERROR(D14/$D$18,"") -> 0.45708633 | C14: UnitedHealthcare | D14: 249741 | E14: 222899 | F14: 200875 | G14: 193842 | H14: 183476 | I14: 163257 | K14: =(D14-E14)/E14 -> 0.12042225 | L14: =(E14-F14)/F14 -> 0.10964032 | M14: =(F14-G14)/G14 -> 0.036282127 | N14: =(G14-H14)/H14 -> 0.056497853 | O14: =(H14-I14)/I14 -> 0.12384768 | P14: -
B15: =IFERROR(D15/$D$18,"") -> 0.20509137 | C15: Optum Health | D15: 112057 | E15: 83299 | F15: 62289 | G15: 48283 | H15: 39027 | I15: 32999 | K15: =(D15-E15)/E15 -> 0.34523824 | L15: =(E15-F15)/F15 -> 0.33729872 | M15: =(F15-G15)/G15 -> 0.2900814 | N15: =(G15-H15)/H15 -> 0.23716914 | O15: =(H15-I15)/I15 -> 0.1826722 | P15: -
B16: =IFERROR(D16/$D$18,"") -> 0.043686033 | C16: Optum Insight | D16: 23869 | E16: 20066 | F16: 17743 | G16: 16245 | H16: 14604 | I16: 13214 | K16: =(D16-E16)/E16 -> 0.18952457 | L16: =(E16-F16)/F16 -> 0.13092487 | M16: =(F16-G16)/G16 -> 0.092212989 | N16: =(G16-H16)/H16 -> 0.11236647 | O16: =(H16-I16)/I16 -> 0.10519146 | P16: -
B17: =IFERROR(D17/$D$18,"") -> 0.29413627 | C17: Optum Rx | D17: 160709 | E17: 147093 | F17: 139918 | G17: 116381 | H17: 108976 | I17: 100709 | K17: =(D17-E17)/E17 -> 0.092567287 | L17: =(E17-F17)/F17 -> 0.051280035 | M17: =(F17-G17)/G17 -> 0.20224092 | N17: =(G17-H17)/H17 -> 0.067950741 | O17: =(H17-I17)/I17 -> 0.082087996 | P17: -
B18: =SUM(B14:B17) -> 1 | C18: TOTAL | D18: =SUM(D14:D17) -> 546376 | E18: =SUM(E14:E17) -> 473357 | F18: =SUM(F14:F17) -> 420825 | G18: =SUM(G14:G17) -> 374751 | H18: =SUM(H14:H17) -> 346083 | I18: =SUM(I14:I17) -> 310179 | K18: =(D18-E18)/E18 -> 0.15425778 | L18: =(E18-F18)/F18 -> 0.12483099 | M18: =(F18-G18)/G18 -> 0.12294564 | N18: =(G18-H18)/H18 -> 0.08283562 | O18: =(H18-I18)/I18 -> 0.11575252 | P18: -
C19: Intersegment Reconcilliation | D19: =111107*2 -> 222214 | E19: =92880*2 -> 185760 | F19: =81842*2 -> 163684 | G19: =129274+3322 -> 132596 | H19: =117018+2818 -> 119836 | I19: =54510*2 -> 109020
C20: as a % of total Revenue | D20: =D19/D18 -> 0.40670527 | E20: =E19/E18 -> 0.39243108 | F20: =F19/F18 -> 0.38895978 | G20: =G19/G18 -> 0.35382427 | H20: =H19/H18 -> 0.34626376 | I20: =I19/I18 -> 0.35147447
B21: =B18 -> 1 | C21: TOTAL (Net of Intersegment Revenue) | D21: =D18-D19 -> 324162 | E21: =E18-E19 -> 287597 | F21: =F18-F19 -> 257141 | G21: =G18-G19 -> 242155 | H21: =H18-H19 -> 226247 | I21: =I18-I19 -> 201159 | K21: =(D21-E21)/E21 -> 0.12713971 | L21: =(E21-F21)/F21 -> 0.11844086 | M21: =(F21-G21)/G21 -> 0.061885982 | N21: =(G21-H21)/H21 -> 0.070312535 | O21: =(H21-I21)/I21 -> 0.12471726 | P21: -
B23: Categories | D23: Description | I23: Graphs
B24: UnitedHealthcare | D24: variety of health insurance products and services to individuals, employers, and government programs; this includes health plans, dental plans, vision plans, and other related products
B25: Optum Health | D25: broad range of health management services, including care delivery and management, wellness programs, and behavioral health services; aims to improve the overall health and well-being of individuals
B26: Optum Insight | D26: services such as data analytics, technology solutions, and consulting services to help health care organizations optimize their operations and improve efficiency
B27: Optum Rx | D27: management of prescription benefits, including pharmacy benefit management, mail order pharmacy services, specialty pharmacy services, and more. aims to help individuals access their medications in a cost-effective and efficient manner
B31: Industry | J31: Graphs (Industry Forecasts)
B32: Drivers | D32: Description
B33: Perscription Drug Costs | D33: Typically drives the cost of UHG's revenues, because they act as a retailer for pharmaceutical products and other healthcare products (ie. wrist brace, first-aid kit, etc.)
B34: Healthcare Spending | D34: Within UHG's main market (US), the healthcare insurance system is privatized rather than public, which results in many regulatory precedents in place, to mitigate monopolies and other potential business malpractices in the economy. In the US Healthcare spending accounts for around 18% (2022) of the country's GDP, making it one of the largest contributing factors.
B35: Healthcare Software Development | D35: Drives the markets within which UHG's Optum arm operates in, as they provide majority of their services related to software and data analytics. The increased demand within this industry drives the competitive edge companies may get by being innovative and creating the most efficient, comprehensive and user-friendly solutions.
B36: Sales forecast
B37: Source | D37: Market Growth CAGR | G37: Period
B38: Grand View Research | D38: 0.0608 | G38: 2023-2030
B39: IMARC Group | D39: 0.062 | G39: 2023-2032
B40: Mordor Intelligence | D40: 0.0795 | G40: 2023-2028
B41: Mordor Intelligence | D41: 0.129 | H41: 2022-2027
B42: IMARC Group | D42: 0.118 | G42: 2024-2032
B43: Grand View Research | D43: 0.1125 | G43: 2023-2030
B44: Company's Strategy / Extra Notes
B45: – One of UnitedHealth growth strategies encompasses inorganic growth through acquisitions. These acquisitions aim at increasing UHG's cover of the healthcare value chain and markets as well as diversifying their operations. – Most recently UHG acquired Healthcare Associates of Texas for $300mn and Optum acquired Refresh Mental Health. In addition to this, when considering the increasing YoY intersegment revenue (45% most recently), it is evident that UHG is employing a conservative strategy, where they try to rely as little as possible on outside suppliers and products in order to conduct their core business activities. – Although UHG does conduct business internationally (UK, Ireland, India, Brazil, Philippines, Colombia, Puerto Rico), their major revenue source (accounting for 90% of revenue) comes from the US. UHG has an effort to expand, however mainly within the US which is further supported with the most recent acquisitions (specifically Healthcare Associates of Texas). As the US has the largest and most lucrative healthcare market, this motivate UHG to concentrate majority of their efforts within the region. – UHG claims that they have 5 strategic growth priorities: Value-Based Comprehensive Care Delivery, Health Benefits, Health Technology, Health Financial Services, and Pharmacy Care Services. – UHG also embraces a very technological and innovation-oriented growth, evident through its Optum brand, which it created in 2011 by merging its existing pharmacy and care delivery services. In summary, UHG channels growth through innovation-oriented business activities as well as acquisitions, aimed at diversifying the company's market reach as well as optimizing the overall healthcare experience.
C58: https://www2.deloitte.com/us/en/blog/health-care-blog/2022/will-digital-players-reinvent-health-insurance.html
C59: https://www2.deloitte.com/content/dam/insights/articles/us164819_chs-hospitals-and-drivers-of-health/US164819_Addressing-the-DOH.pdf
C60: https://www.bain.com/insights/payers-global-healthcare-private-equity-and-ma-report-2023/
C61: https://www.unitedhealthgroup.com/content/dam/UHG/PDF/investors/2022/conference/IC_22_Group_Highlights.pdf

Sheet Acuerdo
A1: Invertir
A2: NO invertir
A3: Mantener sin elevar posición
A4: Mantener (y seguir comprando)
A5: Liquidar
A6: PENDIENTE

Sheet SARD
F1: Variables | K1: Rankings | P1: Difference | U1: Results | Y1: Additional Information | AD1: =B3 -> UNH.N | AE1: Selected Peers | AJ1: Price Multiples (TTM) | AM1: Enterprise Value Multiples (TTM)
B2: Ticker | C2: Company Name | D2: TRBC Industry | E2: Country | F2: ROE | G2: DEBT/EBIT | H2: Market Cap | I2: EPS Growth (2019-2023) (Refinitiv Smart Estimate) | J2: EBIT Margin | K2: ROE | L2: DEBT/EBIT | M2: Market Cap | N2: EPS Growth | O2: EBIT Margin | P2: ROE | Q2: DEBT/EBIT | R2: Market Cap | S2: EPS Growth | T2: EBIT Margin | U2: SARD Result | V2: SARD Peers | W2: SARD Peers adjusted Rank | Y2: Suitability | Z2: Relevant Information Missing | AA2: Author's Override | AB2: Observations | AE2: SARD Peers adjusted Rank | AF2: SARD Result | AG2: Ticker | AH2: Company Name | AI2: Country | AJ2: P / E | AK2: P / B | AL2: Price / Sales | AM2: EV / Sales | AN2: EV / EBITDA
A3: Benchmark | B3: UNH.N | C3: UnitedHealth Group Inc | D3: Managed Healthcare | E3: United States of America | F3: 0.26537828 | G3: 2.0264814 | H3: 5.0894939e+11 | I3: 24.95 | J3: 0.087718486 | K3: =IFERROR(_xlfn.RANK.EQ(F3,F$3:F$14),"N/A") -> 3 | L3: =IFERROR(_xlfn.RANK.EQ(G3,G$3:G$14),"N/A") -> 7 | M3: =IFERROR(_xlfn.RANK.EQ(H3,H$3:H$15),"N/A") -> 1 | N3: =IFERROR(_xlfn.RANK.EQ(I3,I$3:I$15),"N/A") -> 3 | O3: =IFERROR(_xlfn.RANK.EQ(J3,J$3:J$15),"N/A") -> 3 | P3: - | Q3: - | R3: - | S3: - | T3: - | U3: - | V3: - | W3: - | Y3: =IF(OR(Z3="Y",AA3="Y"),"Not suitable","") | Z3: =IF(N3="N/A","Y","") | AE3: {=_xlfn._xlws.SORT(_xlfn._xlws.FILTER(SARD!W3:W14,SARD!W3:W14<=SMALL(W4:W14,6)),,1)} -> 1 | AF3: =_xlfn.XLOOKUP($AE3,$W:$W,U:U,,0) -> 10 | AG3: =_xlfn.XLOOKUP($AE3,$W:$W,B:B,,0) -> ELV.N | AH3: =_xlfn.XLOOKUP($AE3,$W:$W,C:C,,0) -> Elevance Health Inc | AI3: =_xlfn.XLOOKUP($AE3,$W:$W,E:E,,0) -> United States of America | AJ3: 18.923728 | AK3: 2.95 | AL3: 0.67169202 | AM3: 0.75 | AN3: 11.1
A4: Comparison | B4: HUM.N | C4: Humana Inc | D4: Managed Healthcare | E4: United States of America | F4: 0.18326693 | G4: 2.8298241 | H4: 61598448752 | I4: 28.3 | J4: 0.043648906 | K4: =IFERROR(_xlfn.RANK.EQ(F4,F$3:F$14),"N/A") -> 4 | L4: =IFERROR(_xlfn.RANK.EQ(G4,G$3:G$14),"N/A") -> 3 | M4: =IFERROR(_xlfn.RANK.EQ(H4,H$3:H$14),"N/A") -> 4 | N4: =IFERROR(_xlfn.RANK.EQ(I4,I$3:I$14),"N/A") -> 2 | O4: =IFERROR(_xlfn.RANK.EQ(J4,J$3:J$14),"N/A") -> 6 | P4: =IFERROR(ABS(K$3-K4),"N/A") -> 1 | Q4: =IFERROR(ABS(L$3-L4),"N/A") -> 4 | R4: =IFERROR(ABS(M$3-M4),"N/A") -> 3 | S4: =IFERROR(ABS(N$3-N4),"N/A") -> 1 | T4: =IFERROR(ABS(O$3-O4),"N/A") -> 3 | U4: =SUM(P4:T4) -> 12 | V4: =_xlfn.RANK.EQ(U4,$U$4:$U$14,1) -> 2 | W4: =IF(Y4="Not suitable","-",V4) -> 2 | Y4: =IF(OR(Z4="Y",AA4="Y"),"Not suitable","") | Z4: =IF(N4="N/A","Y","") | AE4: 2 | AF4: =_xlfn.XLOOKUP($AE4,$W:$W,U:U,,0) -> 12 | AG4: =_xlfn.XLOOKUP($AE4,$W:$W,B:B,,0) -> HUM.N | AH4: =_xlfn.XLOOKUP($AE4,$W:$W,C:C,,0) -> Humana Inc | AI4: =_xlfn.XLOOKUP($AE4,$W:$W,E:E,,0) -> United States of America | AJ4: 20.740747 | AK4: 3.6343412 | AL4: 0.60183534 | AM4: 0.57 | AN4: 10.69
B5: CI.N | C5: Cigna Group | D5: Managed Healthcare | E5: United States of America | F5: 0.15100168 | G5: 3.0858476 | H5: 7.5431575e+10 | I5: 24.85 | J5: 0.055817767 | K5: =IFERROR(_xlfn.RANK.EQ(F5,F$3:F$14),"N/A") -> 6 | L5: =IFERROR(_xlfn.RANK.EQ(G5,G$3:G$14),"N/A") -> 2 | M5: =IFERROR(_xlfn.RANK.EQ(H5,H$3:H$14),"N/A") -> 3 | N5: =IFERROR(_xlfn.RANK.EQ(I5,I$3:I$14),"N/A") -> 4 | O5: =IFERROR(_xlfn.RANK.EQ(J5,J$3:J$14),"N/A") -> 4 | P5: =IFERROR(ABS(K$3-K5),"N/A") -> 3 | Q5: =IFERROR(ABS(L$3-L5),"N/A") -> 5 | R5: =IFERROR(ABS(M$3-M5),"N/A") -> 2 | S5: =IFERROR(ABS(N$3-N5),"N/A") -> 1 | T5: =IFERROR(ABS(O$3-O5),"N/A") -> 1 | U5: =SUM(P5:T5) -> 12 | V5: =_xlfn.RANK.EQ(U5,$U$4:$U$14,1) -> 2 | W5: 3 | Y5: =IF(OR(Z5="Y",AA5="Y"),"Not suitable","") | Z5: =IF(N5="N/A","Y","") | AE5: 3 | AF5: =_xlfn.XLOOKUP($AE5,$W:$W,U:U,,0) -> 12 | AG5: =_xlfn.XLOOKUP($AE5,$W:$W,B:B,,0) -> CI.N | AH5: =_xlfn.XLOOKUP($AE5,$W:$W,C:C,,0) -> Cigna Group | AI5: =_xlfn.XLOOKUP($AE5,$W:$W,E:E,,0) -> United States of America | AJ5: 14.545081 | AK5: 1.6547433 | AL5: 0.39721317 | AM5: 0.51 | AN5: 8.65
B6: ELV.N | C6: Elevance Health Inc | D6: Managed Healthcare | E6: United States of America | F6: 0.16607345 | G6: 2.7974478 | H6: 1.1326205e+11 | I6: 33.06 | J6: 0.055377104 | K6: =IFERROR(_xlfn.RANK.EQ(F6,F$3:F$14),"N/A") -> 5 | L6: =IFERROR(_xlfn.RANK.EQ(G6,G$3:G$14),"N/A") -> 4 | M6: =IFERROR(_xlfn.RANK.EQ(H6,H$3:H$14),"N/A") -> 2 | N6: =IFERROR(_xlfn.RANK.EQ(I6,I$3:I$14),"N/A") -> 1 | O6: =IFERROR(_xlfn.RANK.EQ(J6,J$3:J$14),"N/A") -> 5 | P6: =IFERROR(ABS(K$3-K6),"N/A") -> 2 | Q6: =IFERROR(ABS(L$3-L6),"N/A") -> 3 | R6: =IFERROR(ABS(M$3-M6),"N/A") -> 1 | S6: =IFERROR(ABS(N$3-N6),"N/A") -> 2 | T6: =IFERROR(ABS(O$3-O6),"N/A") -> 2 | U6: =SUM(P6:T6) -> 10 | V6: =_xlfn.RANK.EQ(U6,$U$4:$U$14,1) -> 1 | W6: =IF(Y6="Not suitable","-",V6) -> 1 | Y6: =IF(OR(Z6="Y",AA6="Y"),"Not suitable","") | Z6: =IF(N6="N/A","Y","") | AE6: 4 | AF6: =_xlfn.XLOOKUP($AE6,$W:$W,U:U,,0) -> 13 | AG6: =_xlfn.XLOOKUP($AE6,$W:$W,B:B,,0) -> MOH.N | AH6: =_xlfn.XLOOKUP($AE6,$W:$W,C:C,,0) -> Molina Healthcare Inc | AI6: =_xlfn.XLOOKUP($AE6,$W:$W,E:E,,0) -> Brazil | AJ6: 20.87184 | AK6: 5.4874968 | AL6: 0.64354979 | AM6: 0.42 | AN6: 7.62
B7: CNC.N | C7: Centene Corp | D7: Managed Healthcare | E7: United States of America | F7: 0.049964667 | G7: 13.367953 | H7: 40070417010 | I7: 6.65 | J7: 0.009325686 | K7: =IFERROR(_xlfn.RANK.EQ(F7,F$3:F$14),"N/A") -> 9 | L7: =IFERROR(_xlfn.RANK.EQ(G7,G$3:G$14),"N/A") -> 1 | M7: =IFERROR(_xlfn.RANK.EQ(H7,H$3:H$14),"N/A") -> 5 | N7: =IFERROR(_xlfn.RANK.EQ(I7,I$3:I$14),"N/A") -> 6 | O7: =IFERROR(_xlfn.RANK.EQ(J7,J$3:J$14),"N/A") -> 9 | P7: =IFERROR(ABS(K$3-K7),"N/A") -> 6 | Q7: =IFERROR(ABS(L$3-L7),"N/A") -> 6 | R7: =IFERROR(ABS(M$3-M7),"N/A") -> 4 | S7: =IFERROR(ABS(N$3-N7),"N/A") -> 3 | T7: =IFERROR(ABS(O$3-O7),"N/A") -> 6 | U7: =SUM(P7:T7) -> 25 | V7: =_xlfn.RANK.EQ(U7,$U$4:$U$14,1) -> 8 | W7: =IF(Y7="Not suitable","-",V7) -> 8 | Y7: =IF(OR(Z7="Y",AA7="Y"),"Not suitable","") | Z7: =IF(N7="N/A","Y","") | AE7: 5 | AF7: =_xlfn.XLOOKUP($AE7,$W:$W,U:U,,0) -> 20 | AG7: =_xlfn.XLOOKUP($AE7,$W:$W,B:B,,0) -> ODPV3.SA | AH7: =_xlfn.XLOOKUP($AE7,$W:$W,C:C,,0) -> Odontoprev SA | AI7: =_xlfn.XLOOKUP($AE7,$W:$W,E:E,,0) -> Italy | AJ7: 12.416288 | AK7: 4.1591911 | AL7: 2.9462169 | AM7: 2.7 | AN7: 8.77
B8: MOH.N | C8: Molina Healthcare Inc | D8: Managed Healthcare | E8: Brazil | F8: 0.26720648 | G8: 2.0571185 | H8: 21396100000 | I8: 20.87 | J8: 0.036686057 | K8: =IFERROR(_xlfn.RANK.EQ(F8,F$3:F$14),"N/A") -> 2 | L8: =IFERROR(_xlfn.RANK.EQ(G8,G$3:G$14),"N/A") -> 6 | M8: =IFERROR(_xlfn.RANK.EQ(H8,H$3:H$14),"N/A") -> 6 | N8: =IFERROR(_xlfn.RANK.EQ(I8,I$3:I$14),"N/A") -> 5 | O8: =IFERROR(_xlfn.RANK.EQ(J8,J$3:J$14),"N/A") -> 7 | P8: =IFERROR(ABS(K$3-K8),"N/A") -> 1 | Q8: =IFERROR(ABS(L$3-L8),"N/A") -> 1 | R8: =IFERROR(ABS(M$3-M8),"N/A") -> 5 | S8: =IFERROR(ABS(N$3-N8),"N/A") -> 2 | T8: =IFERROR(ABS(O$3-O8),"N/A") -> 4 | U8: =SUM(P8:T8) -> 13 | V8: =_xlfn.RANK.EQ(U8,$U$4:$U$14,1) -> 4 | W8: =IF(Y8="Not suitable","-",V8) -> 4 | Y8: =IF(OR(Z8="Y",AA8="Y"),"Not suitable","") | Z8: =IF(N8="N/A","Y","") | AE8: 6 | AF8: =_xlfn.XLOOKUP($AE8,$W:$W,U:U,,0) -> 22 | AG8: =_xlfn.XLOOKUP($AE8,$W:$W,B:B,,0) -> PGNY.OQ | AH8: =_xlfn.XLOOKUP($AE8,$W:$W,C:C,,0) -> Progyny Inc | AI8: =_xlfn.XLOOKUP($AE8,$W:$W,E:E,,0) -> United States of America | AJ8: 68.365985 | AK8: 6.5683503 | AL8: 3.279651 | AM8: 2.95 | AN8: 56.75
B9: ODPV3.SA | C9: Odontoprev SA | D9: Managed Healthcare | E9: Italy | F9: 0.38116587 | G9: 0.045917736 | H9: 1.2382017e+09 | I9: 0.18 | J9: 0.30150566 | K9: =IFERROR(_xlfn.RANK.EQ(F9,F$3:F$14),"N/A") -> 1 | L9: =IFERROR(_xlfn.RANK.EQ(G9,G$3:G$14),"N/A") -> 9 | M9: =IFERROR(_xlfn.RANK.EQ(H9,H$3:H$14),"N/A") -> 10 | N9: =IFERROR(_xlfn.RANK.EQ(I9,I$3:I$14),"N/A") -> 8 | O9: =IFERROR(_xlfn.RANK.EQ(J9,J$3:J$14),"N/A") -> 1 | P9: =IFERROR(ABS(K$3-K9),"N/A") -> 2 | Q9: =IFERROR(ABS(L$3-L9),"N/A") -> 2 | R9: =IFERROR(ABS(M$3-M9),"N/A") -> 9 | S9: =IFERROR(ABS(N$3-N9),"N/A") -> 5 | T9: =IFERROR(ABS(O$3-O9),"N/A") -> 2 | U9: =SUM(P9:T9) -> 20 | V9: =_xlfn.RANK.EQ(U9,$U$4:$U$14,1) -> 5 | W9: =IF(Y9="Not suitable","-",V9) -> 5 | Y9: =IF(OR(Z9="Y",AA9="Y"),"Not suitable","") | Z9: =IF(N9="N/A","Y","") | AE9: Median | AJ9: =MEDIAN(AJ3:AJ8) -> 19.832238 | AK9: =MEDIAN(AK3:AK8) -> 3.8967662 | AL9: =MEDIAN(AL3:AL8) -> 0.6576209 | AM9: =MEDIAN(AM3:AM8) -> 0.66 | AN9: =MEDIAN(AN3:AN8) -> 9.73
B10: HIA.MI | C10: Health Italia SpA | D10: Managed Healthcare | E10: Brazil | F10: 0.1167753 | G10: 2.6976918 | H10: 27967938 | I10: 0.17 | J10: 0.15918176 | K10: =IFERROR(_xlfn.RANK.EQ(F10,F$3:F$14),"N/A") -> 7 | L10: =IFERROR(_xlfn.RANK.EQ(G10,G$3:G$14),"N/A") -> 5 | M10: =IFERROR(_xlfn.RANK.EQ(H10,H$3:H$14),"N/A") -> 12 | N10: =IFERROR(_xlfn.RANK.EQ(I10,I$3:I$14),"N/A") -> 9 | O10: =IFERROR(_xlfn.RANK.EQ(J10,J$3:J$14),"N/A") -> 2 | P10: =IFERROR(ABS(K$3-K10),"N/A") -> 4 | Q10: =IFERROR(ABS(L$3-L10),"N/A") -> 2 | R10: =IFERROR(ABS(M$3-M10),"N/A") -> 11 | S10: =IFERROR(ABS(N$3-N10),"N/A") -> 6 | T10: =IFERROR(ABS(O$3-O10),"N/A") -> 1 | U10: =SUM(P10:T10) -> 24 | V10: =_xlfn.RANK.EQ(U10,$U$4:$U$14,1) -> 7 | W10: =IF(Y10="Not suitable","-",V10) -> 7 | Y10: =IF(OR(Z10="Y",AA10="Y"),"Not suitable","") | Z10: =IF(N10="N/A","Y","") | AE10: Benchmark Data | AJ10: Price / Share
B11: HAPV3.SA | C11: Hapvida Participacoes e Investimentos SA | D11: Managed Healthcare | E11: United States of America | F11: -0.01591483 | G11: -90.254672 | H11: 6.6975316e+09 | I11: 0 | J11: -0.006563152 | K11: =IFERROR(_xlfn.RANK.EQ(F11,F$3:F$14),"N/A") -> 10 | L11: =IFERROR(_xlfn.RANK.EQ(G11,G$3:G$14),"N/A") -> 12 | M11: =IFERROR(_xlfn.RANK.EQ(H11,H$3:H$14),"N/A") -> 7 | N11: =IFERROR(_xlfn.RANK.EQ(I11,I$3:I$14),"N/A") -> 10 | O11: =IFERROR(_xlfn.RANK.EQ(J11,J$3:J$14),"N/A") -> 10 | P11: =IFERROR(ABS(K$3-K11),"N/A") -> 7 | Q11: =IFERROR(ABS(L$3-L11),"N/A") -> 5 | R11: =IFERROR(ABS(M$3-M11),"N/A") -> 6 | S11: =IFERROR(ABS(N$3-N11),"N/A") -> 7 | T11: =IFERROR(ABS(O$3-O11),"N/A") -> 7 | U11: =SUM(P11:T11) -> 32 | V11: =_xlfn.RANK.EQ(U11,$U$4:$U$14,1) -> 9 | W11: =IF(Y11="Not suitable","-",V11) -> 9 | Y11: =IF(OR(Z11="Y",AA11="Y"),"Not suitable","") | Z11: =IF(N11="N/A","Y","") | AE11: Benchmark | AF11: Multiplier | AG11: # Shares | AH11: -Debt + Cash | AJ11: P / E | AK11: P / B | AL11: Price / Sales | AM11: EV / Sales | AN11: EV / EBITDA
B12: PGNY.OQ | C12: Progyny Inc | D12: Managed Healthcare | E12: United States of America | F12: 0.080532035 | G12: 0.27770875 | H12: 3.3878107e+09 | I12: 0.58 | J12: 0.029661475 | K12: =IFERROR(_xlfn.RANK.EQ(F12,F$3:F$14),"N/A") -> 8 | L12: =IFERROR(_xlfn.RANK.EQ(G12,G$3:G$14),"N/A") -> 8 | M12: =IFERROR(_xlfn.RANK.EQ(H12,H$3:H$14),"N/A") -> 8 | N12: =IFERROR(_xlfn.RANK.EQ(I12,I$3:I$14),"N/A") -> 7 | O12: =IFERROR(_xlfn.RANK.EQ(J12,J$3:J$14),"N/A") -> 8 | P12: =IFERROR(ABS(K$3-K12),"N/A") -> 5 | Q12: =IFERROR(ABS(L$3-L12),"N/A") -> 1 | R12: =IFERROR(ABS(M$3-M12),"N/A") -> 7 | S12: =IFERROR(ABS(N$3-N12),"N/A") -> 4 | T12: =IFERROR(ABS(O$3-O12),"N/A") -> 5 | U12: =SUM(P12:T12) -> 22 | V12: =_xlfn.RANK.EQ(U12,$U$4:$U$14,1) -> 6 | W12: =IF(Y12="Not suitable","-",V12) -> 6 | Y12: =IF(OR(Z12="Y",AA12="Y"),"Not suitable","") | Z12: =IF(N12="N/A","Y","") | AE12: =C3 -> UnitedHealth Group Inc | AF12: 1000000 | AG12: 924925293 | AH12: =-'Fin. Data'!B58*SARD!AF12+'Fin. Data'!B39*SARD!AF12 -> -35556000000 | AJ12: =AJ9*'Fin. Data'!B23*AF$12/AG$12 -> 442.54121 | AK12: =AK9*'Fin. Data'!B64*AF$12/AG$12 -> 327.65814 | AL12: =AL9*'Fin. Data'!B5*AF$12/AG$12 -> 230.47884 | AM12: =(AM9*'Fin. Data'!B5*$AF12+$AH12)/$AG12 -> 192.87063 | AN12: =(AN9*'Fin. Data'!B19*$AF12+$AH12)/$AG12 -> 296.45481
B13: CLOV.OQ | C13: Clover Health Investments Corp | D13: Managed Healthcare | E13: United States of America | F13: -0.94944338 | G13: -0.016858555 | H13: 4.6087228e+08 | I13: -0.41 | J13: -0.099979665 | K13: =IFERROR(_xlfn.RANK.EQ(F13,F$3:F$14),"N/A") -> 12 | L13: =IFERROR(_xlfn.RANK.EQ(G13,G$3:G$14),"N/A") -> 10 | M13: =IFERROR(_xlfn.RANK.EQ(H13,H$3:H$14),"N/A") -> 11 | N13: =IFERROR(_xlfn.RANK.EQ(I13,I$3:I$14),"N/A") -> 11 | O13: =IFERROR(_xlfn.RANK.EQ(J13,J$3:J$14),"N/A") -> 12 | P13: =IFERROR(ABS(K$3-K13),"N/A") -> 9 | Q13: =IFERROR(ABS(L$3-L13),"N/A") -> 3 | R13: =IFERROR(ABS(M$3-M13),"N/A") -> 10 | S13: =IFERROR(ABS(N$3-N13),"N/A") -> 8 | T13: =IFERROR(ABS(O$3-O13),"N/A") -> 9 | U13: =SUM(P13:T13) -> 39 | V13: =_xlfn.RANK.EQ(U13,$U$4:$U$14,1) -> 11 | W13: =IF(Y13="Not suitable","-",V13) -> 11 | Y13: =IF(OR(Z13="Y",AA13="Y"),"Not suitable","") | Z13: =IF(N13="N/A","Y","") | AE13: By Consolidated Average | AJ13: =AVERAGE(AJ12:AL12) -> 333.5594 | AM13: =AVERAGE(AM12:AN12) -> 244.66272
B14: ALHC.OQ | C14: Alignment Healthcare Inc | D14: Managed Healthcare | E14: United States of America | F14: -0.62840261 | G14: -1.2318875 | H14: 1.4674143e+09 | I14: -0.77 | J14: -0.091227681 | K14: =IFERROR(_xlfn.RANK.EQ(F14,F$3:F$14),"N/A") -> 11 | L14: =IFERROR(_xlfn.RANK.EQ(G14,G$3:G$14),"N/A") -> 11 | M14: =IFERROR(_xlfn.RANK.EQ(H14,H$3:H$14),"N/A") -> 9 | N14: =IFERROR(_xlfn.RANK.EQ(I14,I$3:I$14),"N/A") -> 12 | O14: =IFERROR(_xlfn.RANK.EQ(J14,J$3:J$14),"N/A") -> 11 | P14: =IFERROR(ABS(K$3-K14),"N/A") -> 8 | Q14: =IFERROR(ABS(L$3-L14),"N/A") -> 4 | R14: =IFERROR(ABS(M$3-M14),"N/A") -> 8 | S14: =IFERROR(ABS(N$3-N14),"N/A") -> 9 | T14: =IFERROR(ABS(O$3-O14),"N/A") -> 8 | U14: =SUM(P14:T14) -> 37 | V14: =_xlfn.RANK.EQ(U14,$U$4:$U$14,1) -> 10 | W14: =IF(Y14="Not suitable","-",V14) -> 10 | Y14: =IF(OR(Z14="Y",AA14="Y"),"Not suitable","") | Z14: =IF(N14="N/A","Y","") | AE14: Upside | AJ14: =AJ13/OP!C20-1 -> -0.3625604 | AM14: =AM13 /OP!C20-1 -> -0.53244397
Y15: =IF(OR(Z15="Y",AA15="Y"),"Not suitable","") | Z15: =IF(N15="N/A","Y","")

Sheet Peers
B1: Peer Logo | C1: Peer Name | D1: Description
C2: #VALUE! | D2: {=_FV(C2,"Description")} -> Elevance Health, Inc. is a health company. It operates as a health insurer in the United States. The Company operates through four segments: Health Benefit, CarelonRx, Carelon Services, and Corporate & Other. The Health Benefits segment offers a comprehensive suite of health plans and services to Individual, employer group risk-based, employer group fee-based, BlueCard, Medicare, Medicaid and federal employees health benefits (FEHB) program members. The CarelonRx segment includes its pharmacy business. CarelonRx markets and offers pharmacy services to affiliated health plan customers, as well as to external customers outside of the health plans. It also offers infusible and injectable therapies. Carelon Services offers healthcare-related services and capabilities to internal and external customers including integrated care delivery, behavioral health, palliative care, utilization management, payment integrity services and subrogation services, as well as health and wellness programs.
C3: #VALUE! | D3: {=_FV(C3,"Description")} -> CVS Health Corporation is a health solutions company. The Company operates in four segments: Health Care Benefits, Health Services, Pharmacy & Consumer Wellness, and Corporate/Other. Its Health Care Benefits segment offer a range of traditional, voluntary and consumer-directed health insurance products and related services, including medical, pharmacy, dental and behavioral health plans, medical management capabilities, Medicare Advantage and Medicare supplement plans, and Medicaid health care management services. Its Health Services segment provides a full range of pharmacy benefit management solutions, delivers health care services in its medical clinics, virtually, and in the home, and offers provider enablement solutions. The Pharmacy & Consumer Wellness segment dispenses prescriptions in its retail pharmacies and through its infusion operations, provides ancillary pharmacy services, including pharmacy patient care programs, diagnostic testing and vaccination administration.
C4: #VALUE! | D4: {=_FV(C4,"Description")} -> Humana Inc. is a healthcare company. It operates through two segments: Insurance and CenterWell. The Insurance segment consists of Medicare benefits, marketed to individuals or directly through group Medicare accounts. It also includes its contract with the Centers for Medicare and Medicaid Services (CMS) to administer the Limited Income Newly Eligible Transition (LI-NET), a prescription drug plan program and contracts with various states to provide Medicaid, dual eligible demonstration, and Long-Term Support Services benefits. It also includes products consisting of employer group commercial fully insured medical and specialty health insurance benefits. The CenterWell segment includes pharmacy solutions, primary care, and home solutions operations. It also includes its strategic partnerships with Welsh, Carson, Anderson & Stowe (WCAS) to develop and operate senior-focused, payor-agnostic, primary care centers, as well as a minority ownership interest in Gentiva Hospice operations.
B6: In Millions USD | C6: =OP!E2 -> UNITEDHEALTH GROUP INCORPORATED (XNYS:UNH) | D6: =C2 -> #VALUE! | E6: =C3 -> #VALUE! | F6: =C4 -> #VALUE! | G6: AVERAGE | H6: Deviation from Average
B7: Company Info | G7: =IFERROR(AVERAGE(A7:F7),"") | L7: TRAFFIC
B8: Market Cap | C8: =OP!C22 -> 483994.91 | D8: {=_FV(D6,"Market cap",TRUE)/1000000} -> 127732 | E8: {=_FV(E6,"Market cap",TRUE)/1000000} -> 72937.64 | F8: {=_FV(F6,"Market cap",TRUE)/1000000} -> 38716.36 | G8: =IFERROR(AVERAGE($C$8:$F$8),"") -> 180845.23 | H8: =SQRT(($C$8-$G$8)^2) -> 303149.68 | M8: Best Value
B9: Net Sales (current) | C9: =C54 -> 324162 | D9: =D54 -> 155660 | E9: =E54 -> 321629 | F9: =F54 -> 92488 | G9: =IFERROR(AVERAGE($C$9:$F$9),"") -> 223484.75 | H9: =SQRT(($C$9-$G$9)^2) -> 100677.25
B10: Profitability | G10: =IFERROR(AVERAGE(A10:F10),"") | M10: Important Value
B11: Sales Growth (ttm) | C11: =C54/C53-1 -> 0.12713971 | D11: =D54/D53-1 -> 0.1366773 | E11: =E54/E53-1 -> 0.10558863 | F11: =F54/F53-1 -> 0.11596704 | G11: =IFERROR(AVERAGE($C$11:$F$11),"") -> 0.12134317 | H11: =SQRT(($C$11-$G$11)^2) -> 0.0057965419
B12: Sales Growth (36m) | C12: =C54/C52-1 -> 0.33865499 | D12: =D54/D52-1 -> 0.50919615 | E12: =E54/E52-1 -> 0.25751764 | F12: =F54/F52-1 -> 0.43643903 | G12: =IFERROR(AVERAGE($C$12:$F$12),"") -> 0.38545195 | H12: =SQRT(($C$12-$G$12)^2) -> 0.046796961 | M12: Worst Value
B13: Operating Margin | C13: =C57/C54 -> 0.087718486 | D13: =D57/D54 -> 0.055377104 | E13: =E57/E54 -> 0.024083649 | F13: =F57/F54 -> 0.041086411 | G13: =IFERROR(AVERAGE($C$13:$F$13),"") -> 0.052066413 | H13: =SQRT(($C$13-$G$13)^2) -> 0.035652074
B14: Net Income Margin | C14: =C60/C54 -> 0.063668783 | D14: =D60/D54 -> 0.038667609 | E14: =E60/E54 -> 0.012949703 | F14: =F60/F54 -> 0.030295822 | G14: =IFERROR(AVERAGE($C$14:$F$14),"") -> 0.036395479 | H14: =SQRT(($C$14-$G$14)^2) -> 0.027273304
B15: Return on Equity (RoE) | C15: =C60/C72 -> 0.26537829 | D15: =D60/D72 -> 0.1657807 | E15: =E60/E72 -> 0.058402861 | F15: =F60/F72 -> 0.18230319 | G15: =IFERROR(AVERAGE($C$15:$F$15),"") -> 0.16796626 | H15: =SQRT(($C$15-$G$15)^2) -> 0.097412026
B16: Return on Invested Capital (ROIC) | C16: =(C60+C59)/(C71+C72) -> 0.10574275 | D16: =(D60+D59)/(D71+D72) -> 0.070654243 | E16: =(E60+E59)/(E71+E72) -> 0.019021873 | F16: =(F60+F59)/(F71+F72) -> 0.13449564 | G16: =IFERROR(AVERAGE($C$16:$F$16),"") -> 0.082478626 | H16: =SQRT(($C$16-$G$16)^2) -> 0.023264122
B17: Solvency | G17: =IFERROR(AVERAGE(A17:F17),"")
B18: Debt/Assets | C18: =C71/C68 -> 0.25830569 | D18: =D71/D68 -> 0.23463589 | E18: =E71/E68 -> 0.30985434 | F18: =F71/F68 -> 0.25848334 | G18: =IFERROR(AVERAGE($C$18:$F$18),"") -> 0.26531982 | H18: =SQRT(($C$18-$G$18)^2) -> 0.0070141238
B19: Net Debt/EBITDA | C19: =(C71-C63)/C56 -> 1.1168839 | D19: =(D71-D63)/D56 -> 1.7819325 | E19: =(E71-E63)/E56 -> 4.7514389 | F19: =(F71-F63)/F56 -> 1.3457529 | G19: =IFERROR(AVERAGE($C$19:$F$19),"") -> 2.2490021 | H19: =SQRT(($C$19-$G$19)^2) -> 1.1321181
B20: Interest Coverage Ratio | C20: =-C56/C58 -> 15.217495 | D20: =-D56/D58 -> 11.030552 | E20: =-E56/E58 -> 5.3178837 | F20: =-F56/F58 -> 11.244389 | G20: =IFERROR(AVERAGE($C$20:$F$20),"") -> 10.70258 | H20: =SQRT(($C$20-$G$20)^2) -> 4.5149152
B21: Liquidity
B22: Current Ratio | C22: =C66/C70 -> 0.77399509 | D22: =D66/D70 -> 1.4010732 | E22: =E66/E70 -> 0.94186647 | F22: =F66/F70 -> 1.524217 | G22: =IFERROR(AVERAGE($C$22:$F$22),"") -> 1.1602879 | H22: =SQRT(($C$22-$G$22)^2) -> 0.38629284
B23: Quick Ratio | C23: =(C63+C64)/C70 -> 0.65400002 | D23: =(D63+D64)/D70 -> 0.59026098 | E23: =(E63+E64)/E70 -> 0.57676093 | F23: =(F63+F64)/F70 -> 0.39207125 | G23: =IFERROR(AVERAGE($C$23:$F$23),"") -> 0.5532733 | H23: =SQRT(($C$23-$G$23)^2) -> 0.10072673
B24: Activity | G24: =IFERROR(AVERAGE(A24:F24),"")
B25: Inventory Turnover | C25: =C55/C65 -> 1.3743425 | D25: 0 | E25: =E55/E65 -> 10.313882 | F25: 0 | G25: =IFERROR(AVERAGE($C$25:$F$25),"") -> 2.922056 | H25: =SQRT(($C$25-$G$25)^2) -> 1.5477136
B26: Acc. Receivable Turnover | C26: =C54/C64 -> 10.645714 | D26: =D54/D64 -> 9.7020693 | E26: =E54/E64 -> 11.791648 | F26: =F54/F64 -> 55.249701 | G26: =IFERROR(AVERAGE($C$26:$F$26),"") -> 21.847283 | H26: =SQRT(($C$26-$G$26)^2) -> 11.201569
A27: Price/Sales | B27: Payables Turnover | C27: =C55/C69 -> 0.59366578 | D27: =D55/D70 -> 0.32837062 | E27: =E55/E70 -> 2.8233911 | F27: =F55/F70 -> 0 | G27: =IFERROR(AVERAGE($C$27:$F$27),"") -> 0.93635687 | H27: =SQRT(($C$27-$G$27)^2) -> 0.34269109
B28: Fixed Asset Turnover | C28: =C54/C67 -> 32.006517 | D28: =D54/D67 -> 36.065802 | E28: =E54/E67 -> 24.984774 | F28: =F54/F67 -> 28.714064 | G28: =IFERROR(AVERAGE($C$28:$F$28),"") -> 30.442789 | H28: =SQRT(($C$28-$G$28)^2) -> 1.5637275
B29: Total Asset Turnover | C29: =C54/C68 -> 1.3193138 | D29: =D54/D68 -> 1.5146149 | E29: =E54/E68 -> 1.4089541 | F29: =F54/F68 -> 2.1481361 | G29: =IFERROR(AVERAGE($C$29:$F$29),"") -> 1.5977547 | H29: =SQRT(($C$29-$G$29)^2) -> 0.27844091
B30: Valuation | G30: =IFERROR(AVERAGE(A30:F30),"")
B31: Price/Earnings | C31: =C8/C60 -> 23.450502 | D31: =D8/D60 -> 21.221465 | E31: =E8/E60 -> 17.512038 | F31: =F8/F60 -> 13.817402 | G31: =IFERROR(AVERAGE($C$31:$F$31),"") -> 19.000352 | H31: =SQRT(($C$31-$G$31)^2) -> 4.4501501
B32: Price/Sales | C32: =C8/C54 -> 1.4930649 | D32: =D8/D54 -> 0.82058332 | E32: =E8/E54 -> 0.22677569 | F32: =F8/F54 -> 0.41860955 | G32: =IFERROR(AVERAGE($C$32:$F$32),"") -> 0.73975837 | H32: =SQRT(($C$32-$G$32)^2) -> 0.75330655
B33: Price/Book | C33: =C8/C72 -> 6.223254 | D33: =D8/D72 -> 3.5181095 | E33: =E8/E72 -> 1.0227531 | F33: =F8/F72 -> 2.5189564 | G33: =IFERROR(AVERAGE($C$33:$F$33),"") -> 3.3207683 | H33: =SQRT(($C$33-$G$33)^2) -> 2.9024858
B34: EV/Sales | C34: =(C71+C8-C63)/C54 -> 1.6027508 | D34: =(D71+D8-D63)/D54 -> 0.92804189 | E34: =(E71+E8-E63)/E54 -> 0.40644544 | F34: =(F71+F8-F63)/F54 -> 0.48421806 | G34: =IFERROR(AVERAGE($C$34:$F$34),"") -> 0.85536405 | H34: =SQRT(($C$34-$G$34)^2) -> 0.74738677
B35: EV/EBITDA | C35: =(C71+C8-C63)/C56 -> 16.320117 | D35: =(D71+D8-D63)/D56 -> 15.389262 | E35: =(E71+E8-E63)/E56 -> 10.748614 | F35: =(F71+F8-F63)/F56 -> 9.9322156 | G35: =IFERROR(AVERAGE($C$35:$F$35),"") -> 13.097552 | H35: =SQRT(($C$35-$G$35)^2) -> 3.2225647
B36: Stock Info | G36: =IFERROR(AVERAGE(A36:F36),"")
B37: Float | C37: =OP!M20 -> 0.996 | D37: 0.995 | E37: 0.9924 | F37: 0.9967 | G37: =IFERROR(AVERAGE($C$37:$F$37),"") -> 0.995025 | H37: =SQRT(($C$37-$G$37)^2) -> 0.000975
B38: b (Yahoo) | C38: =OP!M22 -> 0.55 | D38: 0.78 | E38: 0.49 | F38: 0.47 | G38: =IFERROR(AVERAGE($C$38:$F$38),"") -> 0.5725 | H38: =SQRT(($C$38-$G$38)^2) -> 0.0225
B39: Dividend Yield (yahoo finance) | C39: =[2]OP1!M32 -> 0.011818344 | D39: 0.0128 | E39: 3.49% | F39: 0.0096 | G39: =IFERROR(AVERAGE($C$39:$F$39),"") -> 0.011406115 | H39: =SQRT(($C$39-$G$39)^2) -> 0.00041222939
B40: Stock Performance
B41: 1y | C41: 0.0658 | D41: 0.0519 | E41: -0.125 | F41: -0.271 | G41: =IFERROR(AVERAGE($C$41:$F$41),"") -> -0.069575 | H41: =SQRT(($C$41-$G$41)^2) -> 0.135375
B42: 3y | C42: 1.59 | D42: =(D43/285.43) -1 -> 0.92986021 | E42: =(E43/70.48)-1 -> -0.17735528 | F42: =(F43/372.11)-1 -> -0.13584693 | G42: =IFERROR(AVERAGE($C$42:$F$42),"") -> 0.5516645 | H42: =SQRT(($C$42-$G$42)^2) -> 1.0383355
B43: Current Price | C43: =OP!C20 -> 523.28 | D43: {=_FV(D6,"Price")} -> 550.84 | E43: {=_FV(E6,"Price")} -> 57.98 | F43: {=_FV(F6,"Price")} -> 321.56 | G43: =IFERROR(AVERAGE($C$43:$F$43),"") -> 363.415 | H43: =SQRT(($C$43-$G$43)^2) -> 159.865
B44: Average Target Price | C44: 599.98 | D44: 572.87 | E44: 88.57 | F44: 411.53 | G44: =IFERROR(AVERAGE($C$44:$F$44),"") -> 418.2375 | H44: =SQRT(($C$44-$G$44)^2) -> 181.7425
B45: Upside/Downside | C45: =C44/C43-1 -> 0.14657545 | D45: =(D44/D43)-1 -> 0.039993465 | E45: =E44/E43-1 -> 0.52759572 | F45: =F44/F43-1 -> 0.27979226 | G45: =IFERROR(AVERAGE($C$45:$F$45),"") -> 0.24848922 | H45: =SQRT(($C$45-$G$45)^2) -> 0.10191378
B46: Extra | G46: =IFERROR(AVERAGE(A46:F46),"")
B47: 3y Operating Cash Flow | C47: =([2]Inputs1!B59-[2]Inputs1!E59)/[2]Inputs1!E59 -> 0.4193793 | D47: =(8399-6061)/6061 -> 0.38574493 | E47: =(16177-12848)/12848 -> 0.25910648 | F47: =(4587-5284)/5284 -> -0.13190765 | G47: =IFERROR(AVERAGE($C$47:$F$47),"") -> 0.23308076 | H47: =SQRT(($C$47-$G$47)^2) -> 0.18629854
B48: R&D/Net Sales | C48: =C61/C9 -> 0 | D48: =D61/D9 -> 0 | E48: =E61/E9 -> 0 | F48: =F61/F9 -> 0 | G48: =IFERROR(AVERAGE($C$48:$F$48),"") -> 0 | H48: =SQRT(($C$48-$G$48)^2) -> 0
B50: Financial Data | C50: =OP!E2 -> UNITEDHEALTH GROUP INCORPORATED (XNYS:UNH) | D50: =D6 -> #VALUE! | E50: =E6 -> #VALUE! | F50: =F6 -> #VALUE!
B51: IS
B52: Net Sales (36m ago) | C52: ='[2]Fin. Data1'!E5 -> 242155 | D52: 103141 | E52: 255765 | F52: 64387
B53: Net Sales (12m ago) | C53: ='[2]Fin. Data1'!C5 -> 287597 | D53: 136943 | E53: 290912 | F53: 82877
B54: Net Sales (current) | C54: ='[2]Fin. Data1'!B5 -> 324162 | D54: 155660 | E54: 321629 | F54: 92488
B55: COGS | C55: ='[2]Fin. Data1'!B5-'[2]Fin. Data1'!B7 -> 33703 | D55: 13035 | E55: 196892 | F55: 0
B56: EBITDA | C56: ='[2]Fin. Data1'!B19 -> 31835 | D56: 9387 | E56: 12162 | F56: 4509
B57: Operating Income | C57: ='[2]Fin. Data1'!B11 -> 28435 | D57: 8620 | E57: 7746 | F57: 3800
B58: Net Financial Cost | C58: ='[2]Fin. Data1'!B14 -> -2092 | D58: -851 | E58: -2287 | F58: -401
B59: Taxes | C59: ='[2]Fin. Data1'!B21 -> -5704 | D59: -1750 | E59: -1463 | F59: 762
B60: Net Income | C60: ='[2]Fin. Data1'!B23 -> 20639 | D60: 6019 | E60: 4165 | F60: 2802
B61: R&D | C61: 0 | D61: 0 | E61: 0 | F61: 0
B62: BS
B63: Cash & Eq. | C63: ='[2]Fin. Data1'!B39 -> 27911 | D63: 7387 | E63: 12945 | F63: 5061
B64: Acc. Receivables | C64: ='[2]Fin. Data1'!B40 -> 30450 | D64: 16044 | E64: 27276 | F64: 1674
B65: Inventory | C65: ='[2]Fin. Data1'!B41 -> 24523 | D65: 0 | E65: 19090 | F65: 0
B66: Current Assets | C66: =[2]Inputs1!B27 -> 69069 | D66: 55617 | E66: 65682 | F66: 26183
B67: Fixed Assets | C67: ='[2]Fin. Data1'!B42 -> 10128 | D67: 4316 | E67: 12873 | F67: 3221
B68: Total Assets | C68: ='[2]Fin. Data1'!B44 -> 245705 | D68: 102772 | E68: 228275 | F68: 43055
B69: Acc. Payable | C69: =[2]Inputs1!B43 -> 56771 | D69: 21203 | E69: 14838 | F69: 14502
B70: Current Liabilities | C70: =[2]Inputs1!B42 -> 89237 | D70: 39696 | E70: 69736 | F70: 17178
B71: Total Debt | C71: ='[2]Fin. Data1'!B58 -> 63467 | D71: 24114 | E71: 70732 | F71: 11129
B72: Total Equity | C72: ='[2]Fin. Data1'!B64 -> 77772 | D72: 36307 | E72: 71315 | F72: 15370

Sheet ESG
B1: Company GICS Sector: | T1: Yes
B2: Health Care | T2: No
B3: ESG Analysis | K3: Relative ESG Analysis
B4: Parameters | C4: Impact | D4: Do they report? | E4: Ranking | F4: Mitigation Plan | G4: Traffic Lights | H4: Improvement over time? | I4: Targets / Goals? | J4: Comments | K4: Parameters | L4: UNITEDHEALTH GROUP INCORPORATED (XNYS:UNH) | M4: ELEVANCE HEALTH, INC. (XNYS:ELV) | N4: CVS HEALTH CORPORATION (XNYS:CVS) | O4: HUMANA INC. (XNYS:HUM) | P4: AVERAGE | Q4: Deviation from Average | R4: AVERAGE
B5: Environmental | K5: Ratios
A6: 1 | B6: CO2 Direct Emissions | C6: =VLOOKUP($B$2,'Sector Impact'!$K$4:$AA$16,A6+1,FALSE) -> Low | D6: Yes | E6: Medium | F6: Yes | H6: No | I6: Operational net-zero by 2035 | J6: Operational net-zero by 2035, with 60% scope 1 and 2 reduction and 100% renewable energy by 2030 | K6: CO2 Emissions/$M Sales | L6: =L12/L$11 -> 0.00037758898 | M6: =M12/M$11 -> 0.00010086085 | N6: =N12/N$11 -> 0.00077729309 | O6: =O12/O$11 -> 0.00051249892 | P6: =P12/P$11 -> 0.00048716971 | Q6: =Q12/Q$11 -> 0.00013434018 | R6: =IFERROR(AVERAGE(L6:Q6),"") -> 0.00039829196
A7: 2 | B7: Total Water Consumption | C7: =VLOOKUP($B$2,'Sector Impact'!$K$4:$AA$16,A7+1,FALSE) -> Medium | D7: Yes | E7: Medium High | F7: Yes | H7: Yes | I7: UnitedHealth Group plan to create a holistic approach to water conservation across the enterprise, including creating design guidelines for water efficiency and water quality. | J7: UNH have plumbing and irrigation projects, as well as sustainable landscape projects to reduce their water usage. In 2021 they implemented a holistic water-tracking program, that showed that 47% of total water usage is currently treated/recycled water instead of fresh water. In 2022 they expanded this effort. | K7: Water Consumption/$M Sales | L7: =L13/L$11 -> 0.0013184766 | M7: =M13/M$11 -> 0.0010381601 | N7: =N13/N$11 -> 0.0054876892 | O7: =O13/O$11 -> 0.0081556526 | P7: =P13/P$11 -> 0.0034770829 | Q7: =Q13/Q$11 -> 0.0034732276 | R7: =IFERROR(AVERAGE(L7:Q7),"") -> 0.0038250482
A8: 3 | B8: Total Energy Consumption | C8: =VLOOKUP($B$2,'Sector Impact'!$K$4:$AA$16,A8+1,FALSE) -> Low | E8: Medium | F8: Yes | H8: No | K8: Energy Consumption/$M Sales | L8: =L14/L$11 -> 0.0048876796 | M8: =M14/M$11 -> 0.0015810099 | N8: =N14/N$11 -> 0.0096468291 | O8: =O14/O$11 -> 0.0038859095 | P8: =P14/P$11 -> 0.0059205382 | Q8: =Q14/Q$11 -> 0.0025949259 | R8: =IFERROR(AVERAGE(L8:Q8),"") -> 0.0047528154
A9: 4 | B9: Waste Management | C9: =VLOOKUP($B$2,'Sector Impact'!$K$4:$AA$16,A9+1,FALSE) -> Low | D9: Yes | E9: "Villain" | F9: Yes | H9: No | K9: Waste Production/$M Sales | L9: =L15/L$11 -> 0.00030848773 | M9: =M15/M$11 -> 7.7091096e-06 | N9: =N15/N$11 -> 2.9848055e-05 | O9: =O15/O$11 -> 9.62287e-05 | P9: =P15/P$11 -> 0.00013390175 | Q9: =Q15/Q$11 -> 0.0006960361 | R9: =IFERROR(AVERAGE(L9:Q9),"") -> 0.00021203524
A10: 5 | B10: Land Degradation/Deforestation/Biodiversity loss/Animal sufering/… | C10: =VLOOKUP($B$2,'Sector Impact'!$K$4:$AA$16,A10+1,FALSE) -> Low | D10: No | K10: Inputs
B11: Social | K11: Net Sales ($M) | L11: 324162 | M11: 155660 | N11: 321629 | O11: 92488 | P11: =IFERROR(AVERAGE($L$11:$O$11),"") -> 223484.75 | Q11: =SQRT(($L$11-$P$11)^2) -> 100677.25
A12: 6 | B12: Employee Turnover % | C12: =VLOOKUP($B$2,'Sector Impact'!$K$4:$AA$16,A12+1,FALSE) -> Low | D12: Yes | F12: No | H12: No | I12: None | J12: UNH had an employee turnover of 20% in 2022. | K12: CO2 Emissions Total (Tonnes) | L12: 122.4 | M12: 15.7 | N12: 250 | O12: 47.4 | P12: =IFERROR(AVERAGE($L$12:$O$12),"") -> 108.875 | Q12: =SQRT(($L$12-$P$12)^2) -> 13.525
A13: 7 | B13: Salaries & Compensation | C13: =VLOOKUP($B$2,'Sector Impact'!$K$4:$AA$16,A13+1,FALSE) -> Low | J13: Diference between highest and lowest paid: $180k. Highest paid sector: Legal, with over 182k. Lowest paid sector: Administration, with barely 59k. Workers say they are being paid fairly and are also satisfied with UNH perks and benefits. | K13: Water Consumption Total (Cubic Meters) | L13: =1810-1382.6 -> 427.4 | M13: 161.6 | N13: 1765 | O13: 754.3 | P13: =IFERROR(AVERAGE($L$13:$O$13),"") -> 777.075 | Q13: =SQRT(($L$13-$P$13)^2) -> 349.675
A14: 8 | B14: Reputation | C14: =VLOOKUP($B$2,'Sector Impact'!$K$4:$AA$16,A14+1,FALSE) -> Medium | D14: Yes | E14: Medium | F14: No | I14: None | J14: UNH is facing a class action lawsuit by KKR-owned doctors group for breache the contract between the two companies by unilaterally reducing reimbursement rates for its physician’s services and not paid its bills. UNH is also facing a action lawsuit for following an algorithm that overrode physicians recommendations, and denied eldery pations claims for stays extended care facilities. Also, back in 2019, it was discovered that an algorithm sold by Optum significantly underestimated the amount of care black patients need compared with white patients | K14: Energy Consumption Total (Gigajoules) | L14: 1584.4 | M14: 246.1 | N14: 3102.7 | O14: 359.4 | P14: =IFERROR(AVERAGE($L$14:$O$14),"") -> 1323.15 | Q14: =SQRT(($L$14-$P$14)^2) -> 261.25
A15: 9 | B15: Discrimination Events | C15: =VLOOKUP($B$2,'Sector Impact'!$K$4:$AA$16,A15+1,FALSE) -> Low | F15: Yes | K15: Waste Production Total (Tonnes) | L15: 100 | M15: 1.2 | N15: 9.6 | O15: 8.9 | P15: =IFERROR(AVERAGE($L$15:$O$15),"") -> 29.925 | Q15: =SQRT(($L$15-$P$15)^2) -> 70.075
A16: 10 | B16: Work Safety | C16: =VLOOKUP($B$2,'Sector Impact'!$K$4:$AA$16,A16+1,FALSE) -> High | D16: No | E16: "Best in class" | F16: No | I16: None | J16: UNH did not state any accident | K16: ESG Scores
A17: 11 | B17: Damage to consumer health | C17: =VLOOKUP($B$2,'Sector Impact'!$K$4:$AA$16,A17+1,FALSE) -> Low | D17: Yes | F17: Yes | H17: Yes | I17: None | J17: It's a health company. | K17: Refinitiv | L17: 80 | M17: 83 | N17: 91 | O17: 88 | P17: 85.5 | Q17: 5.5
A18: 12 | B18: PXP? | C18: =VLOOKUP($B$2,'Sector Impact'!$K$4:$AA$16,A18+1,FALSE) -> Low | K18: Sustainalytics | L18: 15.3 | M18: 10.6 | N18: 22 | O18: 22.5 | P18: 17.6 | Q18: 2.3
A19: 13 | B19: Supply chain | C19: =VLOOKUP($B$2,'Sector Impact'!$K$4:$AA$16,A19+1,FALSE) -> Low | D19: Yes | H19: None | I19: UNH plan to improve their emissions calculation and assess supplier performance with the help of some select suppliers, as well as update supplier trainings. | K19: ISS | L19: C+ | M19: B- | N19: C | O19: C+ | P19: C | Q19: -
A20: 14 | B20: Community involvement | C20: =VLOOKUP($B$2,'Sector Impact'!$K$4:$AA$16,A20+1,FALSE) -> Low | I20: h | K20: CDP | L20: B | M20: B | N20: B | O20: B | P20: B | Q20: -
A21: 15 | B21: Public Sector | C21: =VLOOKUP($B$2,'Sector Impact'!$K$4:$AA$16,A21+1,FALSE) -> Low | D21: Yes | I21: None | J21: UnitedHealthcare is subject to extensive government regulation. During the 2022 election cycle, UNH contributed at least $360,000 to members of congress who opposed federal voting rights legislation, and key UNH staff have made large contributions totaling $37,300 to anti-democracy federal legislators. UNH has released statements in support of democracy
A22: 16 | B22: Litigation | C22: =VLOOKUP($B$2,'Sector Impact'!$K$4:$AA$16,A22+1,FALSE) -> Low | D22: Yes
B23: Corporate Governance | K23: PARAMETERS
A24: 17 | B24: Diversity (Gender, Age, Industry, Region) | E24: Medium High | F24: No | I24: There are not any especific goals regarding diversity | J24: 1/3 of the directors nominees are ethically diverse, 1/3 are women and 2/9 are African American | K24: IMPACT | L24: RANKING | M24: MITIGATION PLAN | O24: TRAFFIC
A25: 17 | B25: % Independence | E25: Medium High | F25: No | I25: Nothing is stated | J25: 78% of the Board members are independent | K25: Low | L25: "Best in class" | M25: Is there evidence of a plan/program ?
A26: 17 | B26: average time as independent directors | E26: Medium High | F26: No | I26: Nothing is stated | J26: All board members apart from the CEO and the Chairman are independent | K26: Medium | L26: Medium High
A27: 17 | B27: Recent departures of directors / C-level executives? | E27: Medium High | F27: No | I27: UNH target´s is to keep the average tenue of the board below 7 years | J27: UNH strives to maintain a balance of tenure on the Board. Long-serving directors bring experience while newer directors contribute fresh perspective | K27: High | L27: Medium
A28: 17 | B28: CEO/Chairman duality | E28: "Best in class" | F28: No | I28: Nothing is stated | J28: UHN separates CEO and Chair of the Board | K28: Very high | L28: "Villain"
A29: 17 | B29: Transparency (ESG, segments, acquisitions, other) | E29: "Best in class" | F29: No | I29: Nothing is stated | J29: UNH does a ful disclosure of corporate governance policies and pratices
A30: 17 | B30: Time taken to report after the end of the quarter / year | E30: "Best in class" | F30: No | I30: Nothing is stated | J30: The audit is done by an independant consulting firm and is completely independent from the UHN
A31: 17 | B31: Additional participation of the CEO in other boards or excessive participation of Ch. | E31: Medium High | F31: No | I31: Nothing is stated | J31: The CEO and the Chairman are the only board members who are not independent, therefore they participate in other boards
A32: 17 | B32: Audit / Consulting | D32: Yes | E32: "Best in class" | F32: No | I32: Nothing is stated | J32: The company uses an independent consultant (Delloitte & Touche LLP) to assure transparency. Delloite & Touche LLP is responsible for consolidated financinal statements, internal control over financial reporting, quarterly reviews, other statutory and legal entity audtis and consultations on techinal matters
A33: 17 | B33: ESG-compensation related | D33: No | E33: Medium | F33: No | I33: Nothing is stated | J33: They don't state nothing about it.
A34: 17 | B34: Management compensation schemes | D34: Yes | E34: Medium High | F34: No | I34: Nothing is stated | J34: The company as a compensation scheme in two ways: Cash and stocks
U48: GHG Scope 1 Emissions (tonnes) | AC48: Net Sales ($M) | AK48: GHG Scope 1 Emissions / Net Sales ($M)
U49: UNH | V49: ELV | W49: CVS | X49: HUM | AC49: UNH | AD49: ELV | AE49: CVS | AF49: HUM | AK49: UNH | AL49: ELV | AM49: CVS | AN49: HUM
T50: 2011 | U50: X | V50: X | W50: 234.1 | X50: X | AB50: 2011 | AC50: 101862 | AD50: 60710.7 | AE50: 107100 | AF50: =36832 -> 36832 | AJ50: 2011 | AM50: =W50/AE50 -> 0.0021858077
T51: 2012 | U51: X | V51: X | W51: 156.1 | X51: 12.7 | AB51: 2012 | AC51: 110618 | AD51: 61497.2 | AE51: 123133 | AF51: =39126 -> 39126 | AJ51: 2012 | AM51: =W51/AE51 -> 0.0012677349 | AN51: =X51/AF51 -> 0.00032459234
T52: 2013 | U52: X | V52: X | W52: 245.6 | X52: 17.5 | AB52: 2013 | AC52: 122489 | AD52: 71023.5 | AE52: 126761 | AF52: =41313 -> 41313 | AJ52: 2013 | AM52: =W52/AE52 -> 0.0019375044 | AN52: =X52/AF52 -> 0.00042359548
T53: 2014 | U53: X | V53: X | W53: 188.5 | X53: 16.9 | AB53: 2014 | AC53: 130474 | AD53: 73874.1 | AE53: 139367 | AF53: =48500 -> 48500 | AJ53: 2014 | AM53: =W53/AE53 -> 0.001352544 | AN53: =X53/AF53 -> 0.00034845361
T54: 2015 | U54: 16.6 | V54: X | W54: 214.2 | X54: 15.7 | AB54: 2015 | AC54: 157107 | AD54: 79156.5 | AE54: 153290 | AF54: =54289 -> 54289 | AJ54: 2015 | AK54: =U54/AC54 -> 0.00010566047 | AM54: =W54/AE54 -> 0.0013973514 | AN54: =X54/AF54 -> 0.00028919302
T55: 2016 | U55: 15.8 | V55: X | W55: 220.6 | X55: 16.1 | AB55: 2016 | AC55: 184840 | AD55: 84863 | AE55: 177526 | AF55: =54379 -> 54379 | AJ55: 2016 | AK55: =U55/AC55 -> 8.5479333e-05 | AM55: =W55/AE55 -> 0.0012426349 | AN55: =X55/AF55 -> 0.00029607017
T56: 2017 | U56: 16.6 | V56: 6 | W56: 206.1 | X56: 16.4 | AB56: 2017 | AC56: 201159 | AD56: 90040 | AE56: =184786 -> 184786 | AF56: =53767 -> 53767 | AJ56: 2017 | AK56: =U56/AC56 -> 8.2521786e-05 | AL56: =V56/AD56 -> 6.663705e-05 | AM56: =W56/AE56 -> 0.0011153442 | AN56: =X56/AF56 -> 0.00030501981
T57: 2018 | U57: 13.9 | V57: 11.2 | W57: 177.3 | X57: 16.4 | AB57: 2018 | AC57: 226247 | AD57: 92105 | AE57: =194579 -> 194579 | AF57: =56912 -> 56912 | AJ57: 2018 | AK57: =U57/AC57 -> 6.1437279e-05 | AL57: =V57/AD57 -> 0.00012160035 | AM57: =W57/AE57 -> 0.00091119802 | AN57: =X57/AF57 -> 0.00028816418
T58: 2019 | U58: 17.7 | V58: 17.1 | W58: 157.2 | X58: 15 | AB58: 2019 | AC58: 242155 | AD58: 104213 | AE58: =256776 -> 256776 | AF58: =64888 -> 64888 | AJ58: 2019 | AK58: =U58/AC58 -> 7.309368e-05 | AL58: =V58/AD58 -> 0.00016408701 | AM58: =W58/AE58 -> 0.00061220675 | AN58: =X58/AF58 -> 0.00023116755
T59: 2020 | U59: 24.5 | V59: 12.2 | W59: 165.4 | X59: 10.8 | AB59: 2020 | AC59: 257141 | AD59: 121867 | AE59: =268706 -> 268706 | AF59: =77155 -> 77155 | AJ59: 2020 | AK59: =U59/AC59 -> 9.5278466e-05 | AL59: =V59/AD59 -> 0.00010010914 | AM59: =W59/AE59 -> 0.00061554264 | AN59: =X59/AF59 -> 0.00013997797
T60: 2021 | U60: 121.6 | V60: 11.8 | W60: 188.3 | X60: 15.7 | AB60: 2021 | AC60: 287597 | AD60: 138639 | AE60: =292111 -> 292111 | AF60: =83064 -> 83064 | AJ60: 2021 | AK60: =U60/AC60 -> 0.00042281387 | AL60: =V60/AD60 -> 8.5113136e-05 | AM60: =W60/AE60 -> 0.00064461797 | AN60: =X60/AF60 -> 0.00018901088
T61: 2022 | U61: 122.4 | V61: 15.7 | W61: 250 | X61: 47.4 | AB61: 2022 | AC61: 324162 | AD61: 156595 | AE61: 322467 | AF61: 92870 | AJ61: 2022 | AK61: =U61/AC61 -> 0.00037758898 | AL61: =V61/AD61 -> 0.00010025863 | AM61: =W61/AE61 -> 0.00077527313 | AN61: =X61/AF61 -> 0.00051039087
U63: Total Water Consumption (cubic meters) | AK63: Total Water Consumption / Net Sales ($M)
U64: UNH | V64: ELV | W64: CVS | X64: HUM | AK64: UNH | AL64: ELV | AM64: CVS | AN64: HUM
T65: 2013 | U65: X | V65: X | W65: X | X65: X | AJ65: 2013
T66: 2014 | U66: X | V66: X | W66: X | X66: 404.5 | AJ66: 2014 | AN66: =X66/AF53 -> 0.0083402062
T67: 2015 | U67: 690 | V67: 658.7 | W67: X | X67: 358.2 | AJ67: 2015 | AK67: =U67/AC54 -> 0.0043919112 | AL67: =V67/AD54 -> 0.0083214897 | AN67: =X67/AF54 -> 0.0065980217
T68: 2016 | U68: 942.9 | V68: 534.8 | W68: X | X68: 421.6 | AJ68: 2016 | AK68: =U68/AC55 -> 0.0051011686 | AL68: =V68/AD55 -> 0.0063019219 | AN68: =X68/AF55 -> 0.0077529929
T69: 2017 | U69: 816.2 | V69: 489.4 | W69: X | X69: 397.1 | AJ69: 2017 | AK69: =U69/AC56 -> 0.0040574869 | AL69: =V69/AD56 -> 0.0054353621 | AN69: =X69/AF56 -> 0.0073855711
T70: 2018 | U70: 736.8 | V70: 492.9 | W70: X | X70: 337.1 | AJ70: 2018 | AK70: =U70/AC57 -> 0.0032566178 | AL70: =V70/AD57 -> 0.005351501 | AN70: =X70/AF57 -> 0.0059231796
T71: 2019 | U71: 648.6 | V71: 539.4 | W71: X | X71: 300.1 | AJ71: 2019 | AK71: =U71/AC58 -> 0.0026784498 | AL71: =V71/AD58 -> 0.0051759377 | AN71: =X71/AF58 -> 0.0046248921
T72: 2020 | U72: =557.2-18 -> 539.2 | V72: 302.8 | W72: 1194 | X72: 703.8 | AJ72: 2020 | AK72: =U72/AC59 -> 0.002096904 | AL72: =V72/AD59 -> 0.0024846759 | AM72: =W72/AE59 -> 0.0044435182 | AN72: =X72/AF59 -> 0.0091218975
T73: 2021 | U73: =1250-1040.8 -> 209.2 | V73: 228.3 | W73: 1179 | X73: 677.5 | AJ73: 2021 | AK73: =U73/AC60 -> 0.00072740675 | AL73: =V73/AD60 -> 0.0016467228 | AM73: =W73/AE60 -> 0.0040361369 | AN73: =X73/AF60 -> 0.0081563614
T74: 2022 | U74: =1810-1382.6 -> 427.4 | V74: 161.6 | W74: 1765 | X74: 754.3 | AJ74: 2022 | AK74: =U74/AC61 -> 0.0013184766 | AL74: =V74/AD61 -> 0.0010319614 | AM74: =W74/AE61 -> 0.0054734283 | AN74: =X74/AF61 -> 0.0081221062
U76: Energy Consumption (gigajoules) | AK76: Total Energy Consumption / Net Sales ($M)
U77: UNH | V77: ELV | W77: CVS | X77: HUM | AK77: UNH | AL77: ELV | AM77: CVS | AN77: HUM
T78: 2011 | U78: X | V78: X | W78: X | X78: 195.6 | AJ78: 2011 | AN78: =X78/AF50 -> 0.0053105995
T79: 2012 | U79: X | V79: X | W79: X | X79: 56.6 | AJ79: 2012 | AN79: =X79/AF51 -> 0.0014466084
T80: 2013 | U80: X | V80: X | W80: X | X80: 82.3 | AJ80: 2013 | AN80: =X80/AF52 -> 0.001992109
T81: 2014 | U81: X | V81: X | W81: X | X81: 259.7 | AJ81: 2014 | AN81: =X81/AF53 -> 0.0053546392
T82: 2015 | U82: 372.2 | V82: X | W82: 3716.3 | X82: 251.9 | AJ82: 2015 | AK82: =U82/AC54 -> 0.002369086 | AM82: =W82/AE54 -> 0.024243591 | AN82: =X82/AF54 -> 0.0046399823
T83: 2016 | U83: 372.9 | V83: X | W83: 3655.6 | X83: 254.1 | AJ83: 2016 | AK83: =U83/AC55 -> 0.0020174205 | AM83: =W83/AE55 -> 0.020591913 | AN83: =X83/AF55 -> 0.0046727597
T84: 2017 | U84: 366.5 | V84: X | W84: 3523.3 | X84: 261.6 | AJ84: 2017 | AK84: =U84/AC56 -> 0.0018219418 | AM84: =W84/AE56 -> 0.019066921 | AN84: =X84/AF56 -> 0.0048654379
T85: 2018 | U85: 364.7 | V85: 282.5 | W85: 3221.4 | X85: 239.9 | AJ85: 2018 | AK85: =U85/AC57 -> 0.0016119551 | AL85: =V85/AD57 -> 0.0030671516 | AM85: =W85/AE57 -> 0.016555743 | AN85: =X85/AF57 -> 0.0042152797
T86: 2019 | U86: 375.7 | V86: 292.5 | W86: 3234.2 | X86: 215 | AJ86: 2019 | AK86: =U86/AC58 -> 0.0015514856 | AL86: =V86/AD58 -> 0.0028067516 | AM86: =W86/AE58 -> 0.012595414 | AN86: =X86/AF58 -> 0.0033134016
T87: 2020 | U87: 381.7 | V87: 275.1 | W87: 3042.3 | X87: 198.6 | AJ87: 2020 | AK87: =U87/AC59 -> 0.0014843996 | AL87: =V87/AD59 -> 0.0022573789 | AM87: =W87/AE59 -> 0.01132204 | AN87: =X87/AF59 -> 0.0025740393
T88: 2021 | U88: 1436.8 | V88: 213.1 | W88: 3020.6 | X88: 258.2 | AJ88: 2021 | AK88: =U88/AC60 -> 0.0049958797 | AL88: =V88/AD60 -> 0.0015370855 | AM88: =W88/AE60 -> 0.01034059 | AN88: =X88/AF60 -> 0.0031084465
T89: 2022 | U89: 1584.4 | V89: 246.1 | W89: 3102.7 | X89: 359.4 | AJ89: 2022 | AK89: =U89/AC61 -> 0.0048876796 | AL89: =V89/AD61 -> 0.00157157 | AM89: =W89/AE61 -> 0.0096217597 | AN89: =X89/AF61 -> 0.0038699257
U91: Total Waste Production (tonnes) | AK91: Total Waste Production / Net Sales ($M)
U92: UNH | V92: ELV | W92: CVS | X92: HUM | AK92: UNH | AL92: ELV | AM92: CVS | AN92: HUM
T93: 2012 | U93: X | V93: X | W93: X | X93: 5.4 | AJ93: 2012 | AN93: =X93/AF51 -> 0.00013801564
T94: 2013 | U94: X | V94: X | W94: X | X94: 8.3 | AJ94: 2013 | AN94: =X94/AF52 -> 0.00020090528
T95: 2014 | U95: 13.4 | V95: X | W95: X | X95: 8.6 | AJ95: 2014 | AK95: =U95/AC53 -> 0.00010270245 | AN95: =X95/AF53 -> 0.00017731959
T96: 2015 | U96: 12.9 | V96: X | W96: 3.4 | X96: 9.2 | AJ96: 2015 | AK96: =U96/AC54 -> 8.2109645e-05 | AM96: =W96/AE54 -> 2.2180181e-05 | AN96: =X96/AF54 -> 0.00016946343
T97: 2016 | U97: 13.5 | V97: X | W97: 3.4 | X97: 8.7 | AJ97: 2016 | AK97: =U97/AC55 -> 7.3036139e-05 | AM97: =W97/AE55 -> 1.9152124e-05 | AN97: =X97/AF55 -> 0.00015998823
T98: 2017 | U98: 15.9 | V98: 4 | W98: 4.7 | X98: 9.1 | AJ98: 2017 | AK98: =U98/AC56 -> 7.9041952e-05 | AL98: =V98/AD56 -> 4.44247e-05 | AM98: =W98/AE56 -> 2.5434827e-05 | AN98: =X98/AF56 -> 0.0001692488
T99: 2018 | U99: 15.5 | V99: 4.1 | W99: 5.1 | X99: 6.8 | AJ99: 2018 | AK99: =U99/AC57 -> 6.8509196e-05 | AL99: =V99/AD57 -> 4.4514413e-05 | AM99: =W99/AE57 -> 2.6210434e-05 | AN99: =X99/AF57 -> 0.00011948271
T100: 2019 | U100: 15.4 | V100: 4.1 | W100: 4.4 | X100: 6.6 | AJ100: 2019 | AK100: =U100/AC58 -> 6.3595631e-05 | AL100: =V100/AD58 -> 3.93425e-05 | AM100: =W100/AE58 -> 1.7135558e-05 | AN100: =X100/AF58 -> 0.00010171372
T101: 2020 | U101: 14.4 | V101: 1.8 | W101: 4.3 | X101: 4.2 | AJ101: 2020 | AK101: =U101/AC59 -> 5.6000404e-05 | AL101: =V101/AD59 -> 1.47702e-05 | AM101: =W101/AE59 -> 1.600262e-05 | AN101: =X101/AF59 -> 5.4435876e-05
T102: 2021 | U102: 17.6 | V102: 1.1 | W102: 5.6 | X102: 7.3 | AJ102: 2021 | AK102: =U102/AC60 -> 6.1196744e-05 | AL102: =V102/AD60 -> 7.9342753e-06 | AM102: =W102/AE60 -> 1.9170795e-05 | AN102: =X102/AF60 -> 8.7884041e-05
T103: 2022 | U103: 100 | V103: 1.2 | W103: 9.6 | X103: 8.9 | AJ103: 2022 | AK103: =U103/AC61 -> 0.00030848773 | AL103: =V103/AD61 -> 7.6630799e-06 | AM103: =W103/AE61 -> 2.9770488e-05 | AN103: =X103/AF61 -> 9.5832885e-05

Sheet DCF
A1: VALUATION MODEL
G3: Short Term | K3: Long Term
A4: Section | B4: Line # | C4: ITEM | D4: 2020 (Real) | E4: 2021 (Real) | F4: 2022 (Real) | G4: 2023 | H4: =G4+1 -> 2024 | I4: =H4+1 -> 2025 | J4: =I4+1 -> 2026 | K4: =J4+1 -> 2027 | L4: =K4+1 -> 2028 | M4: =L4+1 -> 2029 | N4: =M4+1 -> 2030 | O4: =N4+1 -> 2031 | ... AF4: =AE4+1 -> 2048
A5: INCOME STATEMENT | B5: 1 | C5: Growth | D5: ='Fin. Data'!D6 -> 0.061885982 | E5: =+E6/D6-1 -> 0.11844086 | F5: =+F6/E6-1 -> 0.12713971 | G5: =+G6/F6-1 -> 0.14809822 | H5: =+H6/G6-1 -> 0.087109583 | I5: =+I6/H6-1 -> 0.095035682 | J5: =+J6/I6-1 -> 0.11791771 | K5: =+K6/J6-1 -> 0.11791771 | L5: =+L6/K6-1 -> 0.093633333 | ... AF5: =+AF6/AE6-1 -> 0.02
B6: 2 | C6: Revenues/Sales | D6: =Inputs!D6 -> 257141 | E6: =Inputs!C6 -> 287597 | F6: =Inputs!B6 -> 324162 | G6: =Assumptions!G43 -> 372169.82 | H6: =Assumptions!H43 -> 404589.37 | I6: =Assumptions!I43 -> 443039.8 | J6: =Assumptions!J43 -> 495282.04 | K6: =Assumptions!K43 -> 553684.57 | L6: =Assumptions!L43 -> 605527.9 | M6: =Assumptions!M43 -> 662225.49 | N6: =Assumptions!N43 -> 724231.87 | ... AF6: =Assumptions!AF43 -> 1274956.7
B7: 3 | C7: EBIT/Operating Margin | D7: =D8/D6 -> 0.087131185 | E7: =E8/E6 -> 0.083345793 | F7: =F8/F6 -> 0.087718486 | G7: 0.0885 | H7: 0.087 | I7: 0.086 | J7: 0.082 | K7: =Assumptions!$L$15 -> 0.079659229 | L7: =7.97% -> 0.0797 | M7: =7.97% -> 0.0797 | N7: =7.97% -> 0.0797 | O7: =7.97% -> 0.0797 | P7: =7.97% -> 0.0797 | Q7: =7.97% -> 0.0797 | R7: =7.97% -> 0.0797 | S7: =7.97% -> 0.0797 | ... AE7: =7.97% -> 0.0797 | AF7: 0.0797
B8: 4 | C8: EBIT | D8: ='Fin. Data'!D11 -> 22405 | E8: ='Fin. Data'!C11 -> 23970 | F8: ='Fin. Data'!B11 -> 28435 | G8: =G7*G6 -> 32937.029 | H8: =H7*H6 -> 35199.276 | I8: =I7*I6 -> 38101.423 | J8: =J7*J6 -> 40613.127 | K8: =K7*K6 -> 44106.085 | L8: =L7*L6 -> 48260.573 | M8: =M7*M6 -> 52779.372 | N8: =N7*N6 -> 57721.28 | ... AF8: =AF7*AF6 -> 101614.05
B9: 5a | C9: (Dep) | D9: -1450 | E9: -1560 | F9: -1700 | G9: =$D$53*DCF!F40 -> -1754.5796 | H9: =$D$53*DCF!G40 -> -2060.8296 | I9: =$D$53*DCF!H40 -> -2393.7569 | J9: =$D$53*DCF!I40 -> -2758.3242 | K9: =$E$53*DCF!J40 -> -3505.223 | L9: =$E$53*DCF!K40 -> -4009.6735 | M9: =$E$53*DCF!L40 -> -4561.3573 | N9: =$E$53*DCF!M40 -> -5164.6971 | O9: =$E$53*DCF!N40 -> -5824.5297 | P9: =$E$53*DCF!O40 -> -6546.1446 | Q9: =$E$53*DCF!P40 -> -7335.3266 | R9: =$E$53*DCF!Q40 -> -8198.4025 | ... AF9: =$E$53*DCF!AE40 -> -22260.857 | AG9: =SUM(D9:AF9) -> -274549.51
B10: 5b | C10: Amort | D10: -1441 | E10: -1543 | F10: -1700 | G10: =F38*$D$54 -> -1831.1782 | H10: =G38*$D$54 -> -1860.6208 | I10: =H38*$D$54 -> -1890.5367 | J10: =I38*$D$54 -> -1920.9337 | K10: =J38*$E$54 -> -1712.3955 | L10: =K38*$E$54 -> -1736.5509 | M10: =L38*$E$54 -> -1761.047 | N10: =M38*$E$54 -> -1785.8886 | O10: =N38*$E$54 -> -1811.0807 | P10: =O38*$E$54 -> -1836.6282 | Q10: =P38*$E$54 -> -1862.536 | R10: =Q38*$E$54 -> -1888.8092 | ... AF10: =AE38*$E$54 -> -2298.0322
B11: 5c | C11: (Stock based compensation) | D11: -647 | E11: -729 | F11: -875 | G11: =G6*$D$55 -> -987.72182 | H11: =H6*$D$55 -> -1073.7619 | I11: =I6*$D$55 -> -1175.8076 | J11: =J6*$D$55 -> -1314.4561 | K11: =K6*$D$55 -> -1469.4537 | L11: =L6*$D$55 -> -1607.0436 | M11: =M6*$D$55 -> -1757.5164 | N11: =N6*$D$55 -> -1922.0786 | ... AF11: =AF6*$D$55 -> -3383.6772
B12: 6 | C12: EBITDA | D12: =D8-D9-D10 -> 25296 | E12: =E8-E9-E10 -> 27073 | F12: =F8-F9-F10 -> 31835 | G12: =G8-G9-G10 -> 36522.787 | H12: =H8-H9-H10 -> 39120.726 | I12: =I8-I9-I10 -> 42385.717 | J12: =J8-J9-J10 -> 45292.385 | K12: =K8-K9-K10 -> 49323.704 | ... AF12: =AF8-AF9-AF10 -> 126172.94
B13: 7 | C13: (Net financing cost) | D13: ='Fin. Data'!D14 -> -1663 | E13: ='Fin. Data'!C14 -> -1660 | F13: ='Fin. Data'!B14 -> -2092 | G13: =F43*$D$58-F44*$D$57 -> -1059.1611 | H13: =G43*$D$58-G44*$D$57 -> -1013.7534 | I13: =H43*$D$58-H44*$D$57 -> -1074.1282 | J13: =I43*$D$58-I44*$D$57 -> -1097.8406 | K13: =J43*$E$58-J44*$E$57 -> -1685.2453 | L13: =K43*$E$58-K44*$E$57 -> -1789.9198 | M13: =L43*$E$58-L44*$E$57 -> -1930.4154 | N13: =M43*$E$58-M44*$E$57 -> -2088.9274 | O13: =N43*$E$58-N44*$E$57 -> -2263.2042 | P13: =O43*$E$58-O44*$E$57 -> -2455.6338 | Q13: =P43*$E$58-P44*$E$57 -> -2669.1916 | R13: =Q43*$E$58-Q44*$E$57 -> -2905.147 | ... AF13: =AE43*$E$58-AE44*$E$57 -> -6180.7069
B14: 8 | C14: Other income/(cost) | D14: ='Fin. Data'!D15 -> 0 | E14: ='Fin. Data'!C15 -> 0 | F14: ='Fin. Data'!B15 -> 0 | G14: =AVERAGE(D14:F14)*(1+G5) -> 0 | H14: =AVERAGE(E14:G14)*(1+H5) -> 0 | I14: =AVERAGE(F14:H14)*(1+I5) -> 0 | J14: =AVERAGE(G14:I14)*(1+J5) -> 0 | K14: =AVERAGE(H14:J14)*(1+K5) -> 0 | L14: =AVERAGE(I14:K14)*(1+L5) -> 0 | M14: =AVERAGE(J14:L14)*(1+M5) -> 0 | N14: =AVERAGE(K14:M14)*(1+N5) -> 0 | ... AF14: =AVERAGE(AC14:AE14)*(1+AF5) -> 0
B15: 9 | C15: Earnings before taxes | D15: =D8+D13+D14 -> 20742 | E15: =E8+E13+E14 -> 22310 | F15: =F8+F13+F14 -> 26343 | G15: =G8+G13+G14 -> 31877.868 | H15: =H8+H13+H14 -> 34185.522 | I15: =I8+I13+I14 -> 37027.295 | J15: =J8+J13+J14 -> 39515.287 | K15: =K8+K13+K14 -> 42420.84 | ... AF15: =AF8+AF13+AF14 -> 95433.34
B16: 10 | C16: (Income tax) | D16: ='Fin. Data'!D21 -> -4973 | E16: ='Fin. Data'!C21 -> -4578 | F16: ='Fin. Data'!B21 -> -5704 | G16: =-(1*$D$56)*G15 -> -6968.49 | H16: =-(1*$D$56)*H15 -> -7472.9424 | I16: =-(1*$D$56)*I15 -> -8094.1529 | J16: =-(1*$D$56)*J15 -> -8638.027 | K16: =-(1*$E$56)*K15 -> -9273.1799 | L16: =-(1*$E$56)*L15 -> -10158.468 | M16: =-(1*$E$56)*M15 -> -11115.563 | N16: =-(1*$E$56)*N15 -> -12161.212 | O16: =-(1*$E$56)*O15 -> -13304.566 | P16: =-(1*$E$56)*P15 -> -14554.576 | Q16: =-(1*$E$56)*Q15 -> -15920.948 | R16: =-(1*$E$56)*R15 -> -16199.457 | ... AF16: =-(1*$E$56)*AF15 -> -20861.693
B17: 11 | C17: Net income | D17: ='Fin. Data'!D23 -> 15769 | E17: ='Fin. Data'!C23 -> 17732 | F17: ='Fin. Data'!B23 -> 20639 | G17: =G16+G15 -> 24909.378 | H17: =H16+H15 -> 26712.58 | I17: =I16+I15 -> 28933.142 | J17: =J16+J15 -> 30877.26 | K17: =K16+K15 -> 33147.66 | L17: =L16+L15 -> 36312.186 | M17: =M16+M15 -> 39733.393 | N17: =N16+N15 -> 43471.141 | ... AF17: =AF16+AF15 -> 74571.647
A19: CASH FLOW STATEMENT | B19: 12 | C19: Operating cash flows before WK | D19: =D22-D21 -> 19279 | E19: =E22-E21 -> 20821 | F19: =F22-F21 -> 23960 | G19: =G17-G10-G9-G11 -> 29482.857 | H19: =H17-H10-H9-H11 -> 31707.792 | I19: =I17-I10-I9-I11 -> 34393.243 | J19: =J17-J10-J9-J11 -> 36870.974 | K19: =K17-K10-K9-K11 -> 39834.732 | L19: =L17-L10-L9-L11 -> 43665.454 | M19: =M17-M10-M9-M11 -> 47813.314 | N19: =N17-N10-N9-N11 -> 52343.806 | ... AF19: =AF17-AF10-AF9-AF11 -> 102514.21
B20: 13 | C20: (Stock-based compensation) | D20: =D11 -> -647 | E20: =E11 -> -729 | F20: =F11 -> -875 | G20: =G11 -> -987.72182 | H20: =H11 -> -1073.7619 | I20: =I11 -> -1175.8076 | J20: =J11 -> -1314.4561 | K20: =K11 -> -1469.4537 | ... AF20: =AF11 -> -3383.6772
B21: 14 | C21: (Working Capital Flows) | D21: =Inputs!D62 -> 2895 | E21: =Inputs!C62 -> 1522 | F21: =Inputs!B62 -> 2246 | G21: =$D$60*(G6-F6) -> 3449.1889 | H21: =$D$60*(H6-G6) -> 2329.2286 | I21: =$D$60*(I6-H6) -> 2762.5249 | J21: =$D$60*(J6-I6) -> 3753.417 | K21: =$E$60*(K6-J6) -> 4196.0114 | L21: =$E$60*(L6-K6) -> 3724.7569 | M21: =$E$60*(M6-L6) -> 4073.5183 | N21: =$E$60*(N6-M6) -> 4454.9354 | O21: =$E$60*(O6-N6) -> 4872.0659 | P21: =$E$60*(P6-O6) -> 5328.2536 | Q21: =$E$60*(Q6-P6) -> 5827.1558 | R21: =$E$60*(R6-Q6) -> 1361.2186 | ... AF21: =$E$60*(AF6-AE6) -> 1796.099
B22: 15 | C22: -Total Operating Cash Flow | D22: =Inputs!D59 -> 22174 | E22: =Inputs!C59 -> 22343 | F22: =Inputs!B59 -> 26206 | G22: =G19+G20+G21 -> 31944.324 | H22: =H19+H20+H21 -> 32963.259 | I22: =I19+I20+I21 -> 35979.96 | J22: =J19+J20+J21 -> 39309.935 | K22: =K19+K20+K21 -> 42561.29 | L22: =L19+L20+L21 -> 45783.167 | M22: =M19+M20+M21 -> 50129.316 | N22: =N19+N20+N21 -> 54876.662 | ... AF22: =AF19+AF20+AF21 -> 100926.64
B23: 16 | C23: (CAPEX) | D23: ='Fin. Data'!D32 -> -2051 | E23: ='Fin. Data'!C32 -> -2454 | F23: ='Fin. Data'!B32 -> -2802 | G23: =G6*$D$62 -> -2977.3585 | H23: =H6*$D$62 -> -3236.715 | I23: =I6*$D$62 -> -3544.3184 | J23: =J6*$D$62 -> -3962.2563 | K23: =K6*$E$62 -> -4429.4765 | L23: =L6*$E$62 -> -4844.2232 | M23: =M6*$E$62 -> -5297.8039 | N23: =N6*$E$62 -> -5793.855 | O23: =O6*$E$62 -> -6336.3529 | P23: =P6*$E$62 -> -6929.6468 | Q23: =Q6*$E$62 -> -7578.4927 | R23: =R6*$E$62 -> -7730.0626 | ... AF23: =AF6*$E$62 -> -10199.653 | AG23: =SUM(D23:AF23) -> -195916.69
B24: 17 | C24: Adq | D24: =Inputs!D66 -> -10481 | E24: ='Fin. Data'!C33 -> -7918 | F24: ='Fin. Data'!B33 -> -25674 | G24: =G6*$D$63 -> -12778.889 | H24: =H6*$D$63 -> -13892.052 | I24: =I6*$D$63 -> -15212.293 | J24: =J6*$D$63 -> -17006.092 | K24: =K6*$E$63 -> -19011.411 | L24: =L6*$E$63 -> -20791.513 | M24: =M6*$E$63 -> -22738.292 | N24: =N6*$E$63 -> -24867.354 | O24: =O6*$E$63 -> -27195.767 | P24: =P6*$E$63 -> -29742.197 | Q24: =Q6*$E$63 -> -32527.058 | R24: =R6*$E$63 -> -33177.599 | ... AF24: =AF6*$E$63 -> -43777.138 | AH24: =AG9-AG23 -> -78632.812
B25: 18 | C25: (Other investing flows) | D25: =Inputs!D67 -> 0 | E25: =Inputs!C67 -> 0 | F25: =Inputs!B67 -> 0 | G25: =(1+G5)*AVERAGE(D25:F25) -> 0 | H25: =(1+H5)*AVERAGE(E25:G25) -> 0 | I25: =(1+I5)*AVERAGE(F25:H25) -> 0 | J25: =(1+J5)*AVERAGE(G25:I25) -> 0 | K25: =(1+K5)*AVERAGE(H25:J25) -> 0 | L25: =(1+L5)*AVERAGE(I25:K25) -> 0 | M25: =(1+M5)*AVERAGE(J25:L25) -> 0 | N25: =(1+N5)*AVERAGE(K25:M25) -> 0 | ... AF25: =(1+AF5)*AVERAGE(AC25:AE25) -> 0
B26: 19 | C26: -Total Investing Flows | D26: =D23+D24+D25 -> -12532 | E26: =E23+E24+E25 -> -10372 | F26: =F23+F24+F25 -> -28476 | G26: =G23+G24+G25 -> -15756.247 | H26: =H23+H24+H25 -> -17128.767 | I26: =I23+I24+I25 -> -18756.611 | J26: =J23+J24+J25 -> -20968.348 | K26: =K23+K24+K25 -> -23440.888 | ... AF26: =AF23+AF24+AF25 -> -53976.791
B27: 20 | C27: (Flows related to leases) | D27: =Inputs!D71+Inputs!D72 -> 0 | E27: =Inputs!C71+Inputs!C72 -> 0 | F27: =Inputs!B71+Inputs!B72 -> 0 | G27: 0 | H27: 0 | I27: 0 | J27: 0 | K27: 0 | L27: 0 | M27: 0 | N27: 0 | O27: 0 | P27: 0 | Q27: 0 | R27: 0 | S27: 0 | T27: 0 | U27: 0 | V27: 0 | W27: 0 | X27: 0 | Y27: 0 | Z27: 0 | AA27: 0 | AB27: 0 | AC27: 0 | AD27: 0 | AE27: 0 | AF27: 0
B28: 21 | C28: Flows related to debt | D28: =+SUM(Inputs!D69:D70) -> 2586 | E28: =+SUM(Inputs!C69:C70) -> 2481 | F28: =+SUM(Inputs!B69:B70) -> 12536 | G28: =G44-F44 -> 9943.801 | H28: =H44-G44 -> 5221.8581 | I28: =I44-H44 -> 6562.6312 | J28: =J44-I44 -> 5842.4041 | K28: =K44-J44 -> 8102.9506 | L28: =L44-K44 -> 9413.0186 | M28: =M44-L44 -> 10240.906 | N28: =N44-M44 -> 11195.881 | ... AF28: =AF44-AE44 -> 6358.0482
B29: 22 | C29: (Repurchases)/Issuance of stock | D29: ='Fin. Data'!D28 -> -2810 | E29: ='Fin. Data'!C28 -> -3645 | F29: ='Fin. Data'!B28 -> -5747 | G29: =-G17*$D$66 -> -10672.364 | H29: =-H17*$D$66 -> -11444.942 | I29: =-I17*$D$66 -> -12396.337 | J29: =-J17*$D$66 -> -13229.289 | K29: =-K17*$E$66 -> -14202.037 | L29: =-L17*$E$66 -> -15557.871 | M29: =-M17*$E$66 -> -17023.679 | N29: =-N17*$E$66 -> -18625.108 | O29: =-O17*$E$66 -> -20376.176 | P29: =-P17*$E$66 -> -22290.587 | Q29: =-Q17*$E$66 -> -24383.21 | R29: =-R17*$E$66 -> -24809.751 | ... AF29: =-AF17*$E$66 -> -31950.047
B30: 23 | C30: (Dividends) | D30: ='Fin. Data'!D27 -> -4584 | E30: ='Fin. Data'!C27 -> -5280 | F30: ='Fin. Data'!B27 -> -5991 | G30: =-$D$64*G17 -> -7632.2333 | H30: =-$D$64*H17 -> -8184.7344 | I30: =-$D$64*I17 -> -8865.1147 | J30: =-$D$64*J17 -> -9460.7924 | K30: =-$E$64*K17 -> -9433.9137 | L30: =-$E$64*L17 -> -10334.546 | M30: =-$E$64*M17 -> -11308.231 | N30: =-$E$64*N17 -> -12372.004 | O30: =-$E$64*O17 -> -13535.177 | P30: =-$E$64*P17 -> -14806.853 | Q30: =-$E$64*Q17 -> -16196.909 | R30: =-$E$64*R17 -> -16480.245 | ... AF30: =-$E$64*AF17 -> -21223.293
B31: 24 | C31: Other financing flows | D31: =Inputs!D75 -> 1218 | E31: =Inputs!C75 -> -1011 | F31: =Inputs!B75 -> 3428 | G31: =(1+G5)*AVERAGE(D31:F31) -> 1391.1123 | H31: =(1+H5)*AVERAGE(E31:G31) -> 1379.9451 | I31: =(1+I5)*AVERAGE(F31:H31) -> 2262.7297 | J31: =(1+J5)*AVERAGE(G31:I31) -> 1875.7866 | K31: =(1+K5)*AVERAGE(H31:J31) -> 2056.3953 | L31: =(1+L5)*AVERAGE(I31:K31) -> 2258.3206 | M31: =(1+M5)*AVERAGE(J31:L31) -> 2256.7133 | N31: =(1+N5)*AVERAGE(K31:M31) -> 2395.578 | ... AF31: =(1+AF5)*AVERAGE(AC31:AE31) -> 3111.0542
B32: 25 | C32: -Total Financing flows | D32: =D27+D28+D29+D30+D31 -> -3590 | E32: =E27+E28+E29+E30+E31 -> -7455 | F32: =F27+F28+F29+F30+F31 -> 4226 | G32: =G27+G28+G29+G30+G31 -> -6969.6842 | H32: =H27+H28+H29+H30+H31 -> -13027.873 | I32: =I27+I28+I29+I30+I31 -> -12436.09 | J32: =J27+J28+J29+J30+J31 -> -14971.891 | K32: =K27+K28+K29+K30+K31 -> -13476.605 | ... AF32: =AF27+AF28+AF29+AF30+AF31 -> -43704.237
A34: SUMMARY | B34: 26 | C34: Cash before shareholder returns | D34: =D22+D26+D27+D28+D31 -> 13446 | E34: =E22+E26+E27+E28+E31 -> 13441 | F34: =F22+F26+F27+F28+F31 -> 13694 | G34: =G22+G26+G27+G28+G31 -> 27522.991 | H34: =H22+H26+H27+H28+H31 -> 22436.295 | I34: =I22+I26+I27+I28+I31 -> 26048.71 | J34: =J22+J26+J27+J28+J31 -> 26059.777 | K34: =K22+K26+K27+K28+K31 -> 29279.748 | ... AF34: =AF22+AF26+AF27+AF28+AF31 -> 56418.947
B35: 27 | C35: Returns to shareholders | D35: =-1*(D29+D30) -> 7394 | E35: =-1*(E29+E30) -> 8925 | F35: =-1*(F29+F30) -> 11738 | G35: =-1*(G29+G30) -> 18304.598 | H35: =-1*(H29+H30) -> 19629.676 | I35: =-1*(I29+I30) -> 21261.451 | J35: =-1*(J29+J30) -> 22690.082 | K35: =-1*(K29+K30) -> 23635.951 | ... AF35: =-1*(AF29+AF30) -> 53173.34
B36: 28 | C36: Excess cash acumulation | D36: =D34-D35 -> 6052 | E36: =E34-E35 -> 4516 | F36: =F34-F35 -> 1956 | G36: =G34-G35 -> 9218.393 | H36: =H34-H35 -> 2806.6182 | I36: =I34-I35 -> 4787.2587 | J36: =J34-J35 -> 3369.6957 | K36: =K34-K35 -> 5643.7976 | ... AF36: =AF34-AF35 -> 3245.6071
A38: BALANCE SHEET | B38: 29 | C38: Intangible assets | D38: =71337+16311 -> 87648 | E38: =75795+15680 -> 91475 | F38: =93352+20538 -> 113890 | G38: =+F38+(-G10) -> 115721.18 | H38: =+G38+(-H10) -> 117581.8 | I38: =+H38+(-I10) -> 119472.34 | J38: =+I38+(-J10) -> 121393.27 | K38: =+J38+(-K10) -> 123105.66 | L38: =+K38+(-L10) -> 124842.22 | M38: =+L38+(-M10) -> 126603.26 | N38: =+M38+(-N10) -> 128389.15 | ... AF38: =+AE38+(-AF10) -> 165207.62 | AG38: =SUM(G38:AF38) -> 3624021.8
B39: 30 | C39: Accumulated amortization | D39: 5455 | E39: 5636 | F39: 6137 | G39: =F39-G10 -> 7968.1782 | H39: =G39-H10 -> 9828.799 | I39: =H39-I10 -> 11719.336 | J39: =I39-J10 -> 13640.269 | K39: =J39-K10 -> 15352.665 | L39: =K39-L10 -> 17089.216 | M39: =L39-M10 -> 18850.263 | N39: =M39-N10 -> 20636.152 | ... AF39: =AE39-AF10 -> 57454.619 | AG39: =SUM(G39:AF39) -> 822443.8
B40: 31 | C40: PPE+Right of use Assets | D40: 13856 | E40: 14961 | F40: 17058 | G40: =F40+(-G23) -> 20035.359 | H40: =G40+(-H23) -> 23272.074 | I40: =H40+(-I23) -> 26816.392 | J40: =I40+(-J23) -> 30778.648 | K40: =J40+(-K23) -> 35208.125 | L40: =K40+(-L23) -> 40052.348 | M40: =L40+(-M23) -> 45350.152 | N40: =M40+(-N23) -> 51144.007 | ... AF40: =AE40+(-AF23) -> 205667.69 | AG40: =SUM(G40:AF40) -> 2566455.5
B41: 32 | C41: Accumulated depreciation | D41: 5230 | E41: 5992 | F41: 6930 | G41: =F41-G9 -> 8684.5796 | H41: =G41-H9 -> 10745.409 | I41: =H41-I9 -> 13139.166 | J41: =I41-J9 -> 15897.49 | K41: =J41-K9 -> 19402.713 | L41: =K41-L9 -> 23412.387 | M41: =L41-M9 -> 27973.744 | N41: =M41-N9 -> 33138.441 | ... AF41: =AE41-AF9 -> 276769.51 | AG41: =SUM(G41:AF41) -> 2592814.7
A43: CASH & DEBT & DISCOUNTING | B43: 33 | C43: Ending cash balance | D43: ='Fin. Data'!D39 -> 19781 | E43: =E36+D43 -> 24297 | F43: =F36+E43 -> 26253 | G43: =G36+F43 -> 35471.393 | H43: =H36+G43 -> 38278.011 | I43: =I36+H43 -> 43065.27 | J43: =J36+I43 -> 46434.966 | K43: =K36+J43 -> 52078.763 | L43: =L36+K43 -> 58005.117 | ... AF43: =AF36+AE43 -> 75900.343
B44: 34 | C44: Total Debt | D44: ='Fin. Data'!D58 -> 49676 | E44: ='Fin. Data'!C58 -> 51839 | F44: ='Fin. Data'!B58 -> 63467 | G44: =G12*$D$69 -> 73410.801 | H44: =H12*$D$69 -> 78632.659 | I44: =I12*$D$69 -> 85195.29 | J44: =J12*$D$69 -> 91037.694 | K44: =K12*$E$69 -> 99140.645 | L44: =L12*$E$69 -> 108553.66 | M44: =M12*$E$69 -> 118794.57 | N44: =N12*$E$69 -> 129990.45 | O44: =O12*$E$69 -> 142230.67 | P44: =P12*$E$69 -> 155612.95 | Q44: =Q12*$E$69 -> 170244.18 | R44: =R12*$E$69 -> 175066.9 | ... AF44: =AF12*$E$69 -> 253607.6
B45: 35 | C45: Discount factor | F45: =1/((1+$F$50)^G50) -> 1 | G45: =1/((1+$F$50)^G49) -> 0.92549745 | H45: =1/((1+$F$50)^H49) -> 0.85654554 | I45: =1/((1+$F$50)^I49) -> 0.79273072 | J45: =1/((1+$F$50)^J49) -> 0.73367026 | K45: =1/((1+$F$50)^K49) -> 0.67900996 | L45: =1/((1+$F$50)^L49) -> 0.62842199 | M45: =1/((1+$F$50)^M49) -> 0.58160295 | N45: =1/((1+$F$50)^N49) -> 0.53827205 | ... AF45: =1/((1+$F$50)^AF49) -> 0.13358446
B46: 36 | C46: DF + 0.1% | E46: +0.1% | F46: =1/((1+$F$50+0.001)^G50) -> 1 | G46: =1/((1+$F$50+0.001)^G49) -> 0.9246417 | H46: =1/((1+$F$50+0.001)^H49) -> 0.85496228 | I46: =1/((1+$F$50+0.001)^I49) -> 0.79053377 | J46: =1/((1+$F$50+0.001)^J49) -> 0.73096049 | K46: =1/((1+$F$50+0.001)^K49) -> 0.67587655 | L46: =1/((1+$F$50+0.001)^L49) -> 0.62494365 | M46: =1/((1+$F$50+0.001)^M49) -> 0.57784896 | N46: =1/((1+$F$50+0.001)^N49) -> 0.53430324 | ... AF46: =1/((1+$F$50+0.001)^AF49) -> 0.13040985
B47: 37 | C47: DF+0.5% | E47: +0.5% | F47: =1/((1+$F$50+0.005)^G50) -> 1 | G47: =1/((1+$F$50+0.005)^G49) -> 0.92123445 | H47: =1/((1+$F$50+0.005)^H49) -> 0.84867292 | I47: =1/((1+$F$50+0.005)^I49) -> 0.78182673 | J47: =1/((1+$F$50+0.005)^J49) -> 0.72024572 | K47: =1/((1+$F$50+0.005)^K49) -> 0.66351518 | L47: =1/((1+$F$50+0.005)^L49) -> 0.61125304 | M47: =1/((1+$F$50+0.005)^M49) -> 0.56310736 | N47: =1/((1+$F$50+0.005)^N49) -> 0.5187539 | ... AF47: =1/((1+$F$50+0.005)^AF49) -> 0.11847439
A49: Discount Rate | C49: Risk free rate | D49: Equity premium | E49: Firm premium | F49: Total | G49: 1 | H49: 2 | I49: 3 | J49: 4 | K49: 5 | L49: 6 | M49: 7 | N49: 8 | O49: 9 | P49: 10 | Q49: 11 | R49: 12 | S49: 13 | T49: 14 | U49: 15 | V49: 16 | W49: 17 | X49: 18 | Y49: 19 | Z49: 20 | AA49: 21 | AB49: 22 | AC49: 23 | AD49: 24 | AE49: 25 | AF49: 26
C50: 0.04 | D50: 0.0375 | E50: 0.003 | F50: =E50+D50+C50 -> 0.0805 | G50: 0
A52: Modelling factors | D52: Short Term | E52: Long Term | F52: Reference (line)
C53: Depreciation factor | D53: =Assumptions!K22 -> -0.10285963 | E53: =Assumptions!L22 -> -0.11388489 | F53: % PPE
C54: Amortization factor | D54: =Assumptions!K23 -> -0.016078481 | E54: =Assumptions!L23 -> -0.014106182 | F54: % IA
C55: Stock-based comp | D55: =Assumptions!K24 -> -0.0026539547 | E55: =Assumptions!L24 -> -0.0026539547 | F55: % revenue
C56: Tax Rate | D56: =Assumptions!K25 -> 0.21859963 | E56: =Assumptions!L25 -> 0.21859963 | F56: % (line 9)
C57: Interest Rate on debt | D57: =Assumptions!K26 -> 0.033813404 | E57: =Assumptions!L26 -> 0.033813404 | F57: % debt (l29)
C58: Interest Rate on cash | D58: =Assumptions!K27 -> 0.0414 | E58: =Assumptions!L27 -> 0.03 | F58: % of cash (l28)
C59: PPE+ROA | D59: -- | E59: -- | F59: Growing with capex
C60: Working capital flows | D60: =Assumptions!K29 -> 0.071846403 | E60: =Assumptions!L29 -> 0.071846403 | F60: % of change revenues (l2)
C61: Intangible Assets | D61: =Assumptions!K30 -> 0.11313467 | E61: =Assumptions!L30 -> 0.11332098 | F61: Growing with amortization
C62: Capex | D62: =-Assumptions!K31 -> -0.008 | E62: =-Assumptions!L31 -> -0.008 | F62: % revenue (l2)
C63: Acquisition factor | D63: =-Assumptions!K32 -> -0.034336177 | E63: =-Assumptions!L32 -> -0.034336177 | F63: % revenue (l2)
C64: Dividends | D64: =Assumptions!K33 -> 0.3064 | E64: =Assumptions!L33 -> 0.2846027 | F64: % net income (11)
C65: Repurchases | D65: =Assumptions!K34 -> 0.32806996 | E65: =Assumptions!L34 -> 0.32806996 | F65: % net income (11)
C66: Repurchases | D66: =Assumptions!I425 -> 0.42844765 | E66: =Assumptions!I425 -> 0.42844765 | F66: % retained earnings
C67: Leases | D67: -- | E67: -- | F67: % revenue (l2)
C68: Cash Costs for EBIT | D68: -- | E68: -- | F68: % revenue (l2)
C69: Total Debt | D69: =Assumptions!K37 -> 2.01 | E69: =Assumptions!L37 -> 2.01 | F69: multiple of EBITDA
A71: Valuation | D71: $ millions
C72: Value of flows | D72: =SUMPRODUCT(G35:AF35,G45:AF45)+((AF43-AF44)*AF45) -> 326461.18 | E72: =D72/D74 -> 0.7238051
C73: Value of perpetuity | D73: =(AF34/(F50-AF5))*AF45 -> 124573.47 | E73: =D73/D74 -> 0.2761949
C74: Total Value | D74: =D72+D73 -> 451034.64
C75: Actual share price | D75: =OP!C20 -> 523.28
C76: Total value vs Mkt Cap | D76: =D77/D75-1 -> -0.068100445
C77: Estimated NPV per share | D77: =D74*1000000/OP!C21 -> 487.6444
A79: Sensibility | C79: Sensitivity +0.1% | D79: =(SUMPRODUCT(G35:AF35,G45:AF45)+((AF43-AF44)*AF45)+(AF34/(F50+0.001-AF5))*AF45)*1000000/OP!C21 -> 485.4544 | E79: =D79/D77-1 -> -0.0044909739
C80: Sensitivity +0.5% | D80: =(SUMPRODUCT(G35:AF35,G45:AF45)+((AF43-AF44)*AF45)+(AF34/(F50+0.005-AF5))*AF45)*1000000/OP!C21 -> 477.36311 | E80: =D80/D77-1 -> -0.02108358
A82: Notes

Sheet Assumptions
B2: Assumptions
B4: Prospects: | C4: OECD (GDP Quarterly Data)
B6: Links:
B8: Industry Assumptions
C13: 2022 | D13: =C13-1 -> 2021 | E13: =D13-1 -> 2020 | F13: =E13-1 -> 2019 | G13: =F13-1 -> 2018 | I13: Average | K13: Short Term Forecast | L13: Long Term Forecast | M13: Perpetual Term Forecast
B14: Revenue growth | C14: =(Inputs!B6-Inputs!C6)/Inputs!C6 -> 0.12713971 | D14: =(Inputs!C6-Inputs!D6)/Inputs!D6 -> 0.11844086 | E14: =(Inputs!D6-Inputs!E6)/Inputs!E6 -> 0.061885982 | F14: =(Inputs!E6-Inputs!F6)/Inputs!F6 -> 0.070312535 | G14: =(Inputs!F6-Inputs!G6)/Inputs!G6 -> 0.12471726 | I14: =AVERAGE(C14:G14) -> 0.10049927 | K14: =AVERAGE(G44:J44) -> 0.1120403 | L14: =AVERAGE([2]Segments1!D38:F43) -> 0.093633333 | M14: 0.02
B15: Operating Margin | C15: =Inputs!B8/Inputs!B6 -> 0.087718486 | D15: =Inputs!C8/Inputs!C6 -> 0.083345793 | E15: =Inputs!D8/Inputs!D6 -> 0.087131185 | F15: =Inputs!E8/Inputs!E6 -> 0.081290909 | G15: =Inputs!F8/Inputs!F6 -> 0.07665958 | I15: =AVERAGE(C15:G15) -> 0.083229191 | K15: =AVERAGE(C15:E15) -> 0.086065155 | L15: =AVERAGE('Fin. Data'!B12:M12) -> 0.079659229 | M15: 0.079659229
B18: Modelling Factors
C20: Last 5 Years
C21: =C13 -> 2022 | D21: =D13 -> 2021 | E21: =E13 -> 2020 | F21: =F13 -> 2019 | G21: =G13 -> 2018 | I21: Average | K21: Short Term Forecast | L21: Long Term Forecast
B22: Depreciation factor | C22: =G326 -> -0.099659984 | D22: =F326 -> -0.1042711 | E22: =E326 -> -0.10464781 | F22: =D326 -> -0.13236976 | G22: =C326 -> -0.1284758 | I22: =AVERAGE(C22:G22) -> -0.11388489 | K22: =AVERAGE(C22:E22) -> -0.10285963 | L22: =AVERAGE(C22:G22) -> -0.11388489
B23: Amortization factor | C23: =G329 -> -0.014926684 | D23: =F329 -> -0.016867997 | E23: =E329 -> -0.016440763 | F23: =D329 -> -0.011182371 | G23: =C329 -> -0.011113095 | I23: =AVERAGE(C23:G23) -> -0.014106182 | K23: =AVERAGE(C23:E23) -> -0.016078481 | L23: =AVERAGE(C23:G23) -> -0.014106182
B24: Stock-based comp | C24: =DCF!F11/DCF!F6 -> -0.0026992677 | D24: =DCF!E11/DCF!E6 -> -0.002534797 | E24: =DCF!D11/DCF!D6 -> -0.0025161293 | F24: =673/C43*-1 -> -0.0027792117 | G24: =620/Inputs!F6*-1 -> -0.0027403678 | I24: =AVERAGE(C24:G24) -> -0.0026539547 | K24: =I24 -> -0.0026539547 | L24: =I24 -> -0.0026539547
B25: Tax Rate | C25: =G339 -> 0.21652811 | D25: =F339 -> 0.20519946 | E25: =E339 -> 0.23975509 | F25: =D339 -> 0.20810856 | G25: =C339 -> 0.22340692 | I25: =AVERAGE(C25:G25) -> 0.21859963 | K25: =I25 -> 0.21859963 | L25: =I25 -> 0.21859963
B26: Interest Rate on debt | C26: =G336 -> 0.032962012 | D26: =F336 -> 0.032022223 | E26: =E336 -> 0.033476931 | F26: =D336 -> 0.036809021 | G26: =C336 -> 0.033796833 | I26: =AVERAGE(C26:G26) -> 0.033813404 | K26: =I26 -> 0.033813404 | L26: =I26 -> 0.033813404
B27: Interest Rate on cash | C27: - | D27: - | E27: - | F27: - | G27: - | I27: - | K27: =C346 -> 0.0414 | L27: =3% -> 0.03
B28: PPE+ROA | C28: =(Inputs!B33/Inputs!C33)-1 -> 0.12922288 | D28: =(Inputs!C33/Inputs!D33)-1 -> 0.039763506 | E28: =(Inputs!D33/Inputs!E33)-1 -> -0.0089613971 | F28: =(Inputs!E33/Inputs!F33)-1 -> 0.02908489 | G28: =(Inputs!F33/Inputs!G33)-1 -> 0.20604591 | I28: =AVERAGE(C28:G28) -> 0.079031158 | L28: -0.06
B29: Working capital flows | C29: =Inputs!B62/(Inputs!B6-Inputs!C6) -> 0.06142486 | D29: =Inputs!C62/(Inputs!C6-Inputs!D6) -> 0.049973733 | E29: =Inputs!D62/(Inputs!D6-Inputs!E6) -> 0.1931803 | F29: =Inputs!E62/(Inputs!E6-Inputs!F6) -> 0.042934373 | G29: =Inputs!F62/(Inputs!F6-Inputs!G6) -> 0.01171875 | I29: =AVERAGE(C29:G29) -> 0.071846403 | K29: =I29 -> 0.071846403 | L29: =I29 -> 0.071846403
B30: Intangible Assets | C30: =G365*G364+G368*G367 -> 0.24573694 | D30: =F365*F364+F368*F367 -> 0.045148953 | E30: =E368*E367+E365*E364 -> 0.081124293 | F30: =D368*D367+D365*D364 -> 0.11332921 | G30: =C368*C367+C365*C364 -> 0.081265519 | I30: =AVERAGE(C30:G30) -> 0.11332098 | K30: =I362 -> 0.11313467 | L30: =I30 -> 0.11332098
B31: CAPEX | C31: =G319 -> 0.0086438262 | D31: =F319 -> 0.0085327733 | E31: =E319 -> 0.0079761687 | F31: =D319 -> 0.0085523735 | G31: =C319 -> 0.009118353 | I31: =AVERAGE(C31:G31) -> 0.0085646989 | K31: 0.008 | L31: 0.008
B32: Acquisition factor | C32: =G374 -> 0.066195297 | D32: =F374 -> 0.01676304 | E32: =E374 -> 0.027762978 | F32: =D374 -> 0.03445314 | G32: =C374 -> 0.026506429 | I32: =AVERAGE(C32:G32) -> 0.034336177 | K32: =I32 -> 0.034336177 | L32: =I32 -> 0.034336177
B33: Dividends | C33: =G418 -> 0.29027569 | D33: =F418 -> 0.29776675 | E33: =E418 -> 0.29069694 | F33: =D418 -> 0.27614299 | G33: =C418 -> 0.26813116 | I33: =AVERAGE(C33:G33) -> 0.2846027 | K33: 0.3064 | L33: =I33 -> 0.2846027
B34: Repurchases | C34: =G426 -> 0.33916372 | D34: =F426 -> 0.28197609 | E34: =E426 -> 0.26951614 | F34: =D426 -> 0.38626308 | G34: =C426 -> 0.36343079 | I34: =AVERAGE(C34:G34) -> 0.32806996 | K34: =I34 -> 0.32806996 | L34: =I34 -> 0.32806996
B35: Leases | C35: -- | D35: -- | E35: -- | F35: -- | G35: -- | I35: - | K35: -- | L35: --
B36: Cash Costs for EBIT | C36: -- | D36: -- | E36: -- | F36: -- | G36: -- | I36: - | K36: -- | L36: --
B37: Total Debt | C37: =G432 -> 1.9936234 | D37: =F432 -> 1.9147859 | E37: =E432 -> 1.9637887 | F37: =D432 -> 2.0661906 | G37: =C432 -> 2.095084 | I37: 2.01 | K37: 2.01 | L37: 2.01
B40: Forecasts
A41: Revenues
B42: (Mn) | C42: 2019 (Real) | D42: 2020 (Real) | E42: 2021 (Real) | F42: 2022 (Real) | G42: 2023 | H42: =G42+1 -> 2024 | I42: =H42+1 -> 2025 | J42: =I42+1 -> 2026 | K42: =J42+1 -> 2027 | L42: =K42+1 -> 2028 | M42: =L42+1 -> 2029 | N42: =M42+1 -> 2030 | O42: =N42+1 -> 2031 | ... AF42: =AE42+1 -> 2048
B43: Sales Revenue | C43: =Inputs!E6 -> 242155 | D43: =Inputs!D6 -> 257141 | E43: =Inputs!C6 -> 287597 | F43: =Inputs!B6 -> 324162 | G43: =D301 -> 372169.82 | H43: =E301 -> 404589.37 | I43: =F301 -> 443039.8 | J43: =G301 -> 495282.04 | K43: =H301 -> 553684.57 | L43: =K43*(1+$L$14) -> 605527.9 | M43: =L43*(1+$L$14) -> 662225.49 | N43: =M43*(1+$L$14) -> 724231.87 | O43: =N43*(1+$L$14) -> 792044.12 | P43: =O43*(1+$L$14) -> 866205.85 | Q43: =P43*(1+$L$14) -> 947311.59 | R43: =Q43*(1+$M$14) -> 966257.82 | S43: =R43*(1+$M$14) -> 985582.98 | T43: =S43*(1+$M$14) -> 1005294.6 | U43: =T43*(1+$M$14) -> 1025400.5 | V43: =U43*(1+$M$14) -> 1045908.5 | W43: =V43*(1+$M$14) -> 1066826.7 | X43: =W43*(1+$M$14) -> 1088163.2 | Y43: =X43*(1+$M$14) -> 1109926.5 | ... AF43: =AE43*(1+$M$14) -> 1274956.7
B44: Growth % | C44: =G86 -> 0.070312535 | D44: =G90 -> 0.061885982 | E44: =G94 -> 0.11844086 | F44: =G98 -> 0.12713971 | G44: =(G43/F43)-1 -> 0.14809822 | H44: =(H43/G43)-1 -> 0.087109583 | I44: =(I43/H43)-1 -> 0.095035682 | J44: =(J43/I43)-1 -> 0.11791771 | K44: =(K43/J43)-1 -> 0.11791771 | L44: =(L43/K43)-1 -> 0.093633333 | M44: =(M43/L43)-1 -> 0.093633333 | N44: =(N43/M43)-1 -> 0.093633333 | ... Q44: =(Q43/P43)-1 -> 0.093633333 | R44: 0.02 | S44: 0.02 | T44: 0.02 | U44: 0.02 | V44: 0.02 | W44: 0.02 | X44: 0.02 | Y44: 0.02 | Z44: 0.02 | AA44: 0.02 | AB44: 0.02 | AC44: 0.02 | AD44: 0.02 | AE44: 0.02 | AF44: 0.02
B54: Quarter | C54: Revenues (mn) | D54: Growth | E54: Year | F54: Revenues (Annual, mn) | G54: Growth | H54: Weighting of Quarter
B55: Q1 | C55: 27282 | D55: - - | E55: 2012 | F55: - - | H55: =C55/(SUM($C$55:$C$58)) -> 0.24663256 | AB55: (Millions $) | AC55: - | AD55: - | AE55: - | AF55: - | AG55: - | AH55: - | AI55: - | AJ55: -
B56: Q2 | C56: 27265 | D56: =(C56/C55)-1 -> -0.00062312147 | E56: 2012 | F56: - - | H56: =C56/(SUM($C$55:$C$58)) -> 0.24647887 | V56: National Health Expenditures (bn) | X56: Net Cost of Insurance (bn) | Z56: Year | AB56: Year | AC56: Quarter | AD56: US Quarterly Real GDP | AE56: Growth | AF56: Brazilian Quarterly Real GDP | AG56: UK & Ireland (EU) Quarterly Real GDP | AH56: India Quarterly Real GDP | AI56: Colombia Quarterly Real GDP | AJ56: Global Average Quarterly Real GDP (Excluding Philippenes & Puerto Rico, data n/a) | AK56: Average Global Growth
B57: Q3 | C57: 27302 | D57: =(C57/C56)-1 -> 0.0013570512 | E57: 2012 | F57: - - | H57: =C57/(SUM($C$55:$C$58)) -> 0.24681336 | AB57: 2012 | AC57: Q1 | AD57: 4279816 | AE57: - | AF57: 72007.08 | AG57: 3474035.4 | AH57: 331164.4 | AI57: 44559.643 | AJ57: =AVERAGE(AF57:AI57) -> 980441.63 | AK57: - | AU57: Weigthed Average Quarterly GDP of Segments (US:89.08, Global:10.92) | AV57: Quarter | AW57: Year | AX57: Average Global Growth
B58: Q4 | C58: 28769 | D58: =(C58/C57)-1 -> 0.053732327 | E58: 2012 | F58: =SUM(C55:C58) -> 110618 | G58: -- | H58: =C58/(SUM($C$55:$C$58)) -> 0.26007521 | V58: 2783.3 | W58: - | X58: 162.4 | Y58: - | Z58: 2012 | AB58: 2012 | AC58: Q2 | AD58: 4345706 | AE58: =(AD58/AD57)-1 -> 0.015395522 | AF58: 74116.33 | AG58: 3470677.4 | AH58: 308730.8 | AI58: 44751.764 | AJ58: =AVERAGE(AF58:AI58) -> 974569.07 | AK58: =(AJ58/AJ57)-1 -> -0.005989706 | AU58: =($L$101*AD57)+($L$102*AJ57) -> 3919524.3 | AV58: Q1 | AW58: 2012 | AX58: -
B59: Q1 | C59: 30340 | D59: =(C59/C58)-1 -> 0.05460739 | E59: 2013 | F59: - - | H59: =C59/(SUM($C$59:$C$62)) -> 0.24769571 | V59: 2856.6 | W59: =(V59/V58)-1 -> 0.026335645 | X59: 169.3 | Y59: =(X59/X58)-1 -> 0.042487685 | Z59: 2013 | AB59: 2012 | AC59: Q3 | AD59: 4376682 | AE59: =(AD59/AD58)-1 -> 0.0071279557 | AF59: 76611.38 | AG59: 3569453.9 | AH59: 307433 | AI59: 44536.521 | AJ59: =AVERAGE(AF59:AI59) -> 999508.7 | AK59: =(AJ59/AJ58)-1 -> 0.025590415 | AU59: =($L$101*AD58)+($L$102*AJ58) -> 3977577.8 | AV59: Q2 | AW59: 2012 | AX59: =(AU59/AU58)-1 -> 0.014811371 | AZ59: 0.014811371 | BA59: =SUM(AX59:AX61) -> 0.035513584
B60: Q2 | C60: 30408 | D60: =(C60/C59)-1 -> 0.0022412657 | E60: 2013 | F60: - - | H60: =C60/(SUM($C$59:$C$62)) -> 0.24825086 | V60: 3002.6 | W60: =(V60/V59)-1 -> 0.051109711 | X60: 189.7 | Y60: =(X60/X59)-1 -> 0.12049616 | Z60: 2014 | AB60: 2012 | AC60: Q4 | AD60: 4440555 | AE60: =(AD60/AD59)-1 -> 0.014593932 | AF60: 75856.05 | AG60: 3384928.6 | AH60: 328267.8 | AI60: 45111.344 | AJ60: =AVERAGE(AF60:AI60) -> 958540.95 | AK60: =(AJ60/AJ59)-1 -> -0.040987889 | AU60: =($L$101*AD59)+($L$102*AJ59) -> 4007894.7 | AV60: Q3 | AW60: 2012 | AX60: =(AU60/AU59)-1 -> 0.007621932 | AZ60: 0.007621932
B61: Q3 | C61: 30624 | D61: =(C61/C60)-1 -> 0.0071033938 | E61: 2013 | F61: - - | H61: =C61/(SUM($C$59:$C$62)) -> 0.25001429 | V61: 3165.4 | W61: =(V61/V60)-1 -> 0.054219676 | X61: 200.7 | Y61: =(X61/X60)-1 -> 0.057986294 | Z61: 2015 | AB61: 2013 | AC61: Q1 | AD61: 4320262 | AE61: =(AD61/AD60)-1 -> -0.027089632 | AF61: 73966.45 | AG61: 3488132.9 | AH61: 345391.2 | AI61: 45671.279 | AJ61: =AVERAGE(AF61:AI61) -> 988290.46 | AK61: =(AJ61/AJ60)-1 -> 0.031036242 | AU61: =($L$101*AD60)+($L$102*AJ60) -> 4060319.1 | AV61: Q4 | AW61: 2012 | AX61: =(AU61/AU60)-1 -> 0.013080281 | AZ61: 0.013080281
B62: Q4 | C62: 31117 | D62: =(C62/C61)-1 -> 0.016098485 | E62: 2013 | F62: =SUM(C59:C62) -> 122489 | H62: =C62/(SUM($C$59:$C$62)) -> 0.25403914 | V62: 3307.4 | W62: =(V62/V61)-1 -> 0.044860049 | X62: 211.5 | Y62: =(X62/X61)-1 -> 0.053811659 | Z62: 2016 | AB62: 2013 | AC62: Q2 | AD62: 4419140 | AE62: =(AD62/AD61)-1 -> 0.022887038 | AF62: 77097.18 | AG62: 3495505.3 | AH62: 328636 | AI62: 47178.985 | AJ62: =AVERAGE(AF62:AI62) -> 987104.37 | AK62: =(AJ62/AJ61)-1 -> -0.001200144 | AU62: =($L$101*AD61)+($L$102*AJ61) -> 3956410.7 | AV62: Q1 | AW62: 2013 | AX62: =(AU62/AU61)-1 -> -0.02559118 | AZ62: -0.02559118 | BA62: =SUM(AX62:AX65) -> 0.033009893
B63: Q1 | C63: 31708 | D63: =(C63/C62)-1 -> 0.018992833 | E63: 2014 | F63: - - | G63: =(F62/F58)-1 -> 0.10731527 | H63: =C63/(SUM($C$63:$C$66)) -> 0.2430216 | V63: 3446.5 | W63: =(V63/V62)-1 -> 0.042057205 | X63: 222.6 | Y63: =(X63/X62)-1 -> 0.05248227 | Z63: 2017 | AB63: 2013 | AC63: Q3 | AD63: 4486445 | AE63: =(AD63/AD62)-1 -> 0.015230339 | AF63: 78725.05 | AG63: 3608387.5 | AH63: 329991.2 | AI63: 47301.253 | AJ63: =AVERAGE(AF63:AI63) -> 1016101.3 | AK63: =(AJ63/AJ62)-1 -> 0.029375703 | AU63: =($L$101*AD62)+($L$102*AJ62) -> 4044361.7 | AV63: Q2 | AW63: 2013 | AX63: =(AU63/AU62)-1 -> 0.022229998 | AZ63: 0.022229998
B64: Q2 | C64: 32574 | D64: =(C64/C63)-1 -> 0.027311719 | E64: 2014 | F64: - - | H64: =C64/(SUM($C$63:$C$66)) -> 0.24965894 | V64: 3604.4 | W64: =(V64/V63)-1 -> 0.045814595 | X64: 249 | Y64: =(X64/X63)-1 -> 0.11859838 | Z64: 2018 | AB64: 2013 | AC64: Q4 | AD64: 4586321 | AE64: =(AD64/AD63)-1 -> 0.022261724 | AF64: 77774.28 | AG64: 3454011.7 | AH64: 349720 | AI64: 47995.512 | AJ64: =AVERAGE(AF64:AI64) -> 982375.37 | AK64: =(AJ64/AJ63)-1 -> -0.033191454 | AU64: =($L$101*AD63)+($L$102*AJ63) -> 4107483.5 | AV64: Q3 | AW64: 2013 | AX64: =(AU64/AU63)-1 -> 0.015607346 | AZ64: 0.015607346
B65: Q3 | C65: 32759 | D65: =(C65/C64)-1 -> 0.0056793762 | E65: 2014 | F65: - - | H65: =C65/(SUM($C$63:$C$66)) -> 0.25107684 | V65: 3757.4 | W65: =(V65/V64)-1 -> 0.042448119 | X65: 235.6 | Y65: =(X65/X64)-1 -> -0.053815261 | Z65: 2019 | AB65: 2014 | AC65: Q1 | AD65: 4403178 | AE65: =(AD65/AD64)-1 -> -0.039932443 | AF65: 76532.63 | AG65: 3541094.8 | AH65: 363846 | AI65: 48704.112 | AJ65: =AVERAGE(AF65:AI65) -> 1007544.4 | AK65: =(AJ65/AJ64)-1 -> 0.025620565 | AU65: =($L$101*AD64)+($L$102*AJ64) -> 4192770.1 | AV65: Q4 | AW65: 2013 | AX65: =(AU65/AU64)-1 -> 0.020763729 | AZ65: 0.020763729
B66: Q4 | C66: 33433 | D66: =(C66/C65)-1 -> 0.020574499 | E66: 2014 | F66: =SUM(C63:C66) -> 130474 | G66: =(F66/F62)-1 -> 0.065189527 | H66: =C66/(SUM($C$63:$C$66)) -> 0.25624262 | V66: 4144.1 | W66: =(V66/V65)-1 -> 0.10291691 | X66: 296.8 | Y66: =(X66/X65)-1 -> 0.25976231 | Z66: 2020 | AB66: 2014 | AC66: Q2 | AD66: 4532342 | AE66: =(AD66/AD65)-1 -> 0.029334267 | AF66: 76761.6 | AG66: 3558174.6 | AH66: 355005 | AI66: 48802.995 | AJ66: =AVERAGE(AF66:AI66) -> 1009686 | AK66: =(AJ66/AJ65)-1 -> 0.0021256268 | AU66: =($L$101*AD65)+($L$102*AJ65) -> 4032374.8 | AV66: Q1 | AW66: 2014 | AX66: =(AU66/AU65)-1 -> -0.038255216 | AZ66: -0.038255216 | BA66: =SUM(AX66:AX69) -> 0.027936546
B67: Q1 | C67: 35756 | D67: =(C67/C66)-1 -> 0.069482248 | E67: 2015 | F67: - - | H67: =C67/(SUM($C$67:$C$70)) -> 0.22759011 | V67: 4255.1 | W67: =(V67/V66)-1 -> 0.026785068 | X67: 255.7 | Y67: =(X67/X66)-1 -> -0.13847709 | Z67: 2021 | AB67: 2014 | AC67: Q3 | AD67: 4616610 | AE67: =(AD67/AD66)-1 -> 0.018592595 | AF67: 78222.18 | AG67: 3673472.3 | AH67: 358713.6 | AI67: 49295.443 | AJ67: =AVERAGE(AF67:AI67) -> 1039925.9 | AK67: =(AJ67/AJ66)-1 -> 0.029949737 | AU67: =($L$101*AD66)+($L$102*AJ66) -> 4147668 | AV67: Q2 | AW67: 2014 | AX67: =(AU67/AU66)-1 -> 0.028591876 | AZ67: 0.028591876
B68: Q2 | C68: 36263 | D68: =(C68/C67)-1 -> 0.014179438 | E68: 2015 | F68: - - | H68: =C68/(SUM($C$67:$C$70)) -> 0.23081721 | V68: 4400 | W68: =(V68/V67)-1 -> 0.034053254 | X68: 264 | Y68: =(X68/X67)-1 -> 0.032459914 | Z68: 2022 | AB68: 2014 | AC68: Q4 | AD68: 4709584 | AE68: =(AD68/AD67)-1 -> 0.02013902 | AF68: 77596.55 | AG68: 3523710.3 | AH68: 370433 | AI68: 49809.269 | AJ68: =AVERAGE(AF68:AI68) -> 1005387.3 | AK68: =(AJ68/AJ67)-1 -> -0.03321256 | AU68: =($L$101*AD67)+($L$102*AJ67) -> 4226036.1 | AV68: Q3 | AW68: 2014 | AX68: =(AU68/AU67)-1 -> 0.018894503 | AZ68: 0.018894503
B69: Q3 | C69: 41489 | D69: =(C69/C68)-1 -> 0.14411384 | E69: 2015 | F69: - - | H69: =C69/(SUM($C$67:$C$70)) -> 0.26408117 | AB69: 2015 | AC69: Q1 | AD69: 4562381 | AE69: =(AD69/AD68)-1 -> -0.031256051 | AF69: 75293.25 | AG69: 3619153.8 | AH69: 389722.2 | AI69: 50120.382 | AJ69: =AVERAGE(AF69:AI69) -> 1033572.4 | AK69: =(AJ69/AJ68)-1 -> 0.028034101 | AU69: =($L$101*AD68)+($L$102*AJ68) -> 4305085.7 | AV69: Q4 | AW69: 2014 | AX69: =(AU69/AU68)-1 -> 0.018705383 | AZ69: 0.018705383
B70: Q4 | C70: 43599 | D70: =(C70/C69)-1 -> 0.050856854 | E70: 2015 | F70: =SUM(C67:C70) -> 157107 | G70: =(F70/F66)-1 -> 0.20412496 | H70: =C70/(SUM($C$67:$C$70)) -> 0.2775115 | AB70: 2015 | AC70: Q2 | AD70: 4696817 | AE70: =(AD70/AD69)-1 -> 0.029466193 | AF70: 74658.03 | AG70: 3641859.1 | AH70: 381959.2 | AI70: 50481.394 | AJ70: =AVERAGE(AF70:AI70) -> 1037239.4 | AK70: =(AJ70/AJ69)-1 -> 0.0035479112 | AU70: =($L$101*AD69)+($L$102*AJ69) -> 4177035.1 | AV70: Q1 | AW70: 2015 | AX70: =(AU70/AU69)-1 -> -0.029744034 | AZ70: -0.029744034 | BA70: =SUM(AX70:AX73) -> 0.019966092
B71: Q1 | C71: 44527 | D71: =(C71/C70)-1 -> 0.021284892 | E71: 2016 | F71: - - | H71: =C71/(SUM($C$71:$C$74)) -> 0.24089483 | AB71: 2015 | AC71: Q3 | AD71: 4741070 | AE71: =(AD71/AD70)-1 -> 0.0094219128 | AF71: 74887.68 | AG71: 3769025.8 | AH71: 387532.6 | AI71: 50989.19 | AJ71: =AVERAGE(AF71:AI71) -> 1070608.8 | AK71: =(AJ71/AJ70)-1 -> 0.032171344 | AU71: =($L$101*AD70)+($L$102*AJ70) -> 4297191.1 | AV71: Q2 | AW71: 2015 | AX71: =(AU71/AU70)-1 -> 0.028765865 | AZ71: 0.028765865
B72: Q2 | C72: 46485 | D72: =(C72/C71)-1 -> 0.04397332 | E72: 2016 | F72: - - | H72: =C72/(SUM($C$71:$C$74)) -> 0.25148777 | AB72: 2015 | AC72: Q4 | AD72: 4799354 | AE72: =(AD72/AD71)-1 -> 0.012293427 | AF72: 73313.6 | AG72: 3595919 | AH72: 397094.6 | AI72: 50832.506 | AJ72: =AVERAGE(AF72:AI72) -> 1029289.9 | AK72: =(AJ72/AJ71)-1 -> -0.038593827 | AU72: =($L$101*AD71)+($L$102*AJ71) -> 4340255.6 | AV72: Q3 | AW72: 2015 | AX72: =(AU72/AU71)-1 -> 0.010021549 | AZ72: 0.010021549
B73: Q3 | C73: 46305 | D73: =(C73/C72)-1 -> -0.0038722168 | E73: 2016 | F73: - - | H73: =C73/(SUM($C$71:$C$74)) -> 0.25051396 | AB73: 2016 | AC73: Q1 | AD73: 4641851 | AE73: =(AD73/AD72)-1 -> -0.032817542 | AF73: 71424.55 | AG73: 3709024.2 | AH73: 425143.6 | AI73: 51329.98 | AJ73: =AVERAGE(AF73:AI73) -> 1064230.6 | AK73: =(AJ73/AJ72)-1 -> 0.03394637 | AU73: =($L$101*AD72)+($L$102*AJ72) -> 4387663 | AV73: Q4 | AW73: 2015 | AX73: =(AU73/AU72)-1 -> 0.010922712 | AZ73: 0.010922712
B74: Q4 | C74: 47523 | D74: =(C74/C73)-1 -> 0.026303855 | E74: 2016 | F74: =SUM(C71:C74) -> 184840 | G74: =(F74/F70)-1 -> 0.17652301 | H74: =C74/(SUM($C$71:$C$74)) -> 0.25710344 | AB74: 2016 | AC74: Q2 | AD74: 4768308 | AE74: =(AD74/AD73)-1 -> 0.027242796 | AF74: 72255.23 | AG74: 3695643.3 | AH74: 415112.6 | AI74: 51589.542 | AJ74: =AVERAGE(AF74:AI74) -> 1058650.2 | AK74: =(AJ74/AJ73)-1 -> -0.0052436142 | AU74: =($L$101*AD73)+($L$102*AJ73) -> 4251174.9 | AV74: Q1 | AW74: 2016 | AX74: =(AU74/AU73)-1 -> -0.031107255 | AZ74: -0.031107255 | BA74: =SUM(AX74:AX77) -> 0.024561598
B75: Q1 | C75: 48723 | D75: =(C75/C74)-1 -> 0.025250931 | E75: 2017 | F75: - - | H75: =C75/(SUM($C$75:$C$78)) -> 0.24221139 | AB75: 2016 | AC75: Q3 | AD75: 4819182 | AE75: =(AD75/AD74)-1 -> 0.010669193 | AF75: 73049.8 | AG75: 3833686.4 | AH75: 425006.4 | AI75: 51722.152 | AJ75: =AVERAGE(AF75:AI75) -> 1095866.2 | AK75: =(AJ75/AJ74)-1 -> 0.035154219 | AU75: =($L$101*AD74)+($L$102*AJ74) -> 4363213.4 | AV75: Q2 | AW75: 2016 | AX75: =(AU75/AU74)-1 -> 0.026354718 | AZ75: 0.026354718
B76: Q2 | C76: 50053 | D76: =(C76/C75)-1 -> 0.02729717 | E76: 2017 | F76: - - | H76: =C76/(SUM($C$75:$C$78)) -> 0.24882307 | AB76: 2016 | AC76: Q4 | AD76: 4912331 | AE76: =(AD76/AD75)-1 -> 0.019328799 | AF76: 71655.73 | AG76: 3697990.2 | AH76: 431146.8 | AI76: 52007.148 | AJ76: =AVERAGE(AF76:AI76) -> 1063200 | AK76: =(AJ76/AJ75)-1 -> -0.029808583 | AU76: =($L$101*AD75)+($L$102*AJ75) -> 4412595.9 | AV76: Q3 | AW76: 2016 | AX76: =(AU76/AU75)-1 -> 0.011317931 | AZ76: 0.011317931
B77: Q3 | C77: 50322 | D77: =(C77/C76)-1 -> 0.0053743032 | E77: 2017 | F77: - - | H77: =C77/(SUM($C$75:$C$78)) -> 0.25016032 | AB77: 2017 | AC77: Q1 | AD77: 4698367 | AE77: =(AD77/AD76)-1 -> -0.043556511 | AF77: 71625.83 | AG77: 3790648.6 | AH77: 451882.2 | AI77: 51997.746 | AJ77: =AVERAGE(AF77:AI77) -> 1091538.6 | AK77: =(AJ77/AJ76)-1 -> 0.026654087 | AU77: =($L$101*AD76)+($L$102*AJ76) -> 4492005.9 | AV77: Q4 | AW77: 2016 | AX77: =(AU77/AU76)-1 -> 0.017996204 | AZ77: 0.017996204
B78: Q4 | C78: 52061 | D78: =(C78/C77)-1 -> 0.03455745 | E78: 2017 | F78: =SUM(C75:C78) -> 201159 | G78: =(F78/F74)-1 -> 0.088287167 | H78: =C78/(SUM($C$75:$C$78)) -> 0.25880522 | AB78: 2017 | AC78: Q2 | AD78: 4893234 | AE78: =(AD78/AD77)-1 -> 0.041475474 | AF78: 72824 | AG78: 3803930.3 | AH78: 440487.6 | AI78: 52220.641 | AJ78: =AVERAGE(AF78:AI78) -> 1092365.6 | AK78: =(AJ78/AJ77)-1 -> 0.00075768392 | AU78: =($L$101*AD77)+($L$102*AJ77) -> 4304501.3 | AV78: Q1 | AW78: 2017 | AX78: =(AU78/AU77)-1 -> -0.041741832 | AZ78: -0.041741832 | BA78: =SUM(AX78:AX81) -> 0.033366003
B79: Q1 | C79: 55188 | D79: =(C79/C78)-1 -> 0.060064156 | E79: 2018 | F79: - - | H79: =C79/(SUM($C$79:$C$82)) -> 0.2439281 | AB79: 2017 | AC79: Q3 | AD79: 4950878 | AE79: =(AD79/AD78)-1 -> 0.011780348 | AF79: 74248.25 | AG79: 3936631.7 | AH79: 447608 | AI79: 52554.201 | AJ79: =AVERAGE(AF79:AI79) -> 1127760.5 | AK79: =(AJ79/AJ78)-1 -> 0.032402065 | AU79: =($L$101*AD78)+($L$102*AJ78) -> 4478179.2 | AV79: Q2 | AW79: 2017 | AX79: =(AU79/AU78)-1 -> 0.040347957 | AZ79: 0.040347957
B80: Q2 | C80: 56086 | D80: =(C80/C79)-1 -> 0.016271653 | E80: 2018 | F80: - - | H80: =C80/(SUM($C$79:$C$82)) -> 0.24789721 | AB80: 2017 | AC80: Q4 | AD80: 5069624 | AE80: =(AD80/AD79)-1 -> 0.023984837 | AF80: 73502.18 | AG80: 3774996.1 | AH80: 459898.6 | AI80: 52685.338 | AJ80: =AVERAGE(AF80:AI80) -> 1090270.6 | AK80: =(AJ80/AJ79)-1 -> -0.033242858 | AU80: =($L$101*AD79)+($L$102*AJ79) -> 4533393.6 | AV80: Q3 | AW80: 2017 | AX80: =(AU80/AU79)-1 -> 0.012329654 | AZ80: 0.012329654
B81: Q3 | C81: 56556 | D81: =(C81/C80)-1 -> 0.0083799879 | E81: 2018 | F81: - - | H81: =C81/(SUM($C$79:$C$82)) -> 0.24997459 | AB81: 2018 | AC81: Q1 | AD81: 4890817 | AE81: =(AD81/AD80)-1 -> -0.035270269 | AF81: 72990.7 | AG81: 3874277.4 | AH81: 492248.4 | AI81: 52886.835 | AJ81: =AVERAGE(AF81:AI81) -> 1123100.8 | AK81: =(AJ81/AJ80)-1 -> 0.030112048 | AU81: =($L$101*AD80)+($L$102*AJ80) -> 4635078.6 | AV81: Q4 | AW81: 2017 | AX81: =(AU81/AU80)-1 -> 0.022430223 | AZ81: 0.022430223
B82: Q4 | C82: 58417 | D82: =(C82/C81)-1 -> 0.032905439 | E82: 2018 | F82: =SUM(C79:C82) -> 226247 | G82: =(F82/F78)-1 -> 0.12471726 | H82: =C82/(SUM($C$79:$C$82)) -> 0.25820011 | AB82: 2018 | AC82: Q2 | AD82: 5039983 | AE82: =(AD82/AD81)-1 -> 0.030499199 | AF82: 74002.4 | AG82: 3867699 | AH82: 473522 | AI82: 53656.592 | AJ82: =AVERAGE(AF82:AI82) -> 1117220 | AK82: =(AJ82/AJ81)-1 -> -0.0052362492 | AU82: =($L$101*AD81)+($L$102*AJ81) -> 4479382.4 | AV82: Q1 | AW82: 2018 | AX82: =(AU82/AU81)-1 -> -0.033590845 | AZ82: -0.033590845 | BA82: =SUM(AX82:AX85) -> 0.020946439
B83: Q1 | C83: 60308 | D83: =(C83/C82)-1 -> 0.032370714 | E83: 2019 | F83: - - | H83: =C83/(SUM($C$83:$C$86)) -> 0.2490471 | AB83: 2018 | AC83: Q3 | AD83: 5092532 | AE83: =(AD83/AD82)-1 -> 0.010426424 | AF83: 75775.75 | AG83: 4007868 | AH83: 476509.6 | AI83: 54108.75 | AJ83: =AVERAGE(AF83:AI83) -> 1153565.5 | AK83: =(AJ83/AJ82)-1 -> 0.032532113 | AU83: =($L$101*AD82)+($L$102*AJ82) -> 4611617.3 | AV83: Q2 | AW83: 2018 | AX83: =(AU83/AU82)-1 -> 0.029520785 | AZ83: 0.029520785
B84: Q2 | C84: 60595 | D84: =(C84/C83)-1 -> 0.0047589043 | E84: 2019 | F84: - - | H84: =C84/(SUM($C$83:$C$86)) -> 0.25023229 | AB84: 2018 | AC84: Q4 | AD84: 5170563 | AE84: =(AD84/AD83)-1 -> 0.015322633 | AF84: 74643.3 | AG84: 3842593.6 | AH84: 488566.4 | AI84: 54176.93 | AJ84: =AVERAGE(AF84:AI84) -> 1114995.1 | AK84: =(AJ84/AJ83)-1 -> -0.03343587 | AU84: =($L$101*AD83)+($L$102*AJ83) -> 4662396.9 | AV84: Q3 | AW84: 2018 | AX84: =(AU84/AU83)-1 -> 0.01101123 | AZ84: 0.01101123
B85: Q3 | C85: 60351 | D85: =(C85/C84)-1 -> -0.0040267349 | E85: 2019 | F85: - - | H85: =C85/(SUM($C$83:$C$86)) -> 0.24922467 | AB85: 2019 | AC85: Q1 | AD85: 4968926 | AE85: =(AD85/AD84)-1 -> -0.038997107 | AF85: 73646.8 | AG85: 3932205.5 | AH85: 520409.4 | AI85: 54770.95 | AJ85: =AVERAGE(AF85:AI85) -> 1145258.2 | AK85: =(AJ85/AJ84)-1 -> 0.027141919 | AU85: =($L$101*AD84)+($L$102*AJ84) -> 4727695 | AV85: Q4 | AW85: 2018 | AX85: =(AU85/AU84)-1 -> 0.014005268 | AZ85: 0.014005268
B86: Q4 | C86: 60901 | D86: =(C86/C85)-1 -> 0.0091133535 | E86: 2019 | F86: =SUM(C83:C86) -> 242155 | G86: =(F86/F82)-1 -> 0.070312535 | H86: =C86/(SUM($C$83:$C$86)) -> 0.25149594 | AB86: 2019 | AC86: Q2 | AD86: 5157365 | AE86: =(AD86/AD85)-1 -> 0.037923487 | AF86: 74866.5 | AG86: 3950557 | AH86: 497649.6 | AI86: 55310.41 | AJ86: =AVERAGE(AF86:AI86) -> 1144595.9 | AK86: =(AJ86/AJ85)-1 -> -0.00057828461 | AU86: =($L$101*AD85)+($L$102*AJ85) -> 4551381.5 | AV86: Q1 | AW86: 2019 | AX86: =(AU86/AU85)-1 -> -0.037293757 | AZ86: -0.037293757 | BA86: =SUM(AX86:AX89) -> 0.034896753
B87: Q1 | C87: 64421 | D87: =(C87/C86)-1 -> 0.057798723 | E87: 2020 | F87: - - | H87: =C87/(SUM($C$87:$C$90)) -> 0.25052792 | AB87: 2019 | AC87: Q3 | AD87: 5223895 | AE87: =(AD87/AD86)-1 -> 0.012899998 | AF87: 76614.98 | AG87: 4069664.3 | AH87: 496993 | AI87: 55852.67 | AJ87: =AVERAGE(AF87:AI87) -> 1174781.2 | AK87: =(AJ87/AJ86)-1 -> 0.026372068 | AU87: =($L$101*AD86)+($L$102*AJ86) -> 4719170.6 | AV87: Q2 | AW87: 2019 | AX87: =(AU87/AU86)-1 -> 0.036865541 | AZ87: 0.036865541
B88: Q2 | C88: 62138 | D88: =(C88/C87)-1 -> -0.035438754 | E88: 2020 | F88: - - | H88: =C88/(SUM($C$87:$C$90)) -> 0.24164952 | AB88: 2019 | AC88: Q4 | AD88: 5341901 | AE88: =(AD88/AD87)-1 -> 0.022589658 | AF88: 75914.63 | AG88: 4077803.7 | AH88: 504473.2 | AI88: 55741.369 | AJ88: =AVERAGE(AF88:AI88) -> 1178483.2 | AK88: =(AJ88/AJ87)-1 -> 0.0031512141 | AU88: =($L$101*AD87)+($L$102*AJ87) -> 4781731.8 | AV88: Q3 | AW88: 2019 | AX88: =(AU88/AU87)-1 -> 0.013256814 | AZ88: 0.013256814
B89: Q3 | C89: 65115 | D89: =(C89/C88)-1 -> 0.047909492 | E89: 2020 | F89: - - | H89: =C89/(SUM($C$87:$C$90)) -> 0.25322683 | AB89: 2020 | AC89: Q1 | AD89: 5044763 | AE89: =(AD89/AD88)-1 -> -0.055624018 | AF89: 73955.58 | AG89: 3967703 | AH89: 535735.2 | AI89: 54980.053 | AJ89: =AVERAGE(AF89:AI89) -> 1158093.5 | AK89: =(AJ89/AJ88)-1 -> -0.017301703 | AU89: =($L$101*AD88)+($L$102*AJ88) -> 4887255.8 | AV89: Q4 | AW89: 2019 | AX89: =(AU89/AU88)-1 -> 0.022068156 | AZ89: 0.022068156
B90: Q4 | C90: 65467 | D90: =(C90/C89)-1 -> 0.0054058205 | E90: 2020 | F90: =SUM(C87:C90) -> 257141 | G90: =(F90/F86)-1 -> 0.061885982 | H90: =C90/(SUM($C$87:$C$90)) -> 0.25459573 | AB90: 2020 | AC90: Q2 | AD90: 4773286 | AE90: =(AD90/AD89)-1 -> -0.053813628 | AF90: 67285.25 | AG90: 3491578.6 | AH90: 381362.8 | AI90: 46017.596 | AJ90: =AVERAGE(AF90:AI90) -> 996561.06 | AK90: =(AJ90/AJ89)-1 -> -0.13948131 | AU90: =($L$101*AD89)+($L$102*AJ89) -> 4620338.7 | AV90: Q1 | AW90: 2020 | AX90: =(AU90/AU89)-1 -> -0.054614922 | AZ90: -0.054614922 | BA90: =SUM(AX90:AX93) -> -0.0044731528
B91: Q1 | C91: 70196 | D91: =(C91/C90)-1 -> 0.072234866 | E91: 2021 | F91: - - | H91: =C91/(SUM($C$91:$C$94)) -> 0.24407765 | AB91: 2020 | AC91: Q3 | AD91: 5129120 | AE91: =(AD91/AD90)-1 -> 0.074546968 | AF91: 74297.95 | AG91: 3917551.2 | AH91: 468542.2 | AI91: 50796.6 | AJ91: =AVERAGE(AF91:AI91) -> 1127797 | AK91: =(AJ91/AJ90)-1 -> 0.1316888 | AU91: =($L$101*AD90)+($L$102*AJ90) -> 4360867.6 | AV91: Q2 | AW91: 2020 | AX91: =(AU91/AU90)-1 -> -0.056158448 | AZ91: -0.056158448
B92: Q2 | C92: 71321 | D92: =(C92/C91)-1 -> 0.016026554 | E92: 2021 | F92: - - | H92: =C92/(SUM($C$91:$C$94)) -> 0.24798937 | AB92: 2020 | AC92: Q4 | AD92: 5286905 | AE92: =(AD92/AD91)-1 -> 0.030762587 | AF92: 75639.65 | AG92: 3933221.4 | AH92: 512481.2 | AI92: 53804.587 | AJ92: =AVERAGE(AF92:AI92) -> 1143786.7 | AK92: =(AJ92/AJ91)-1 -> 0.014177837 | AU92: =($L$101*AD91)+($L$102*AJ91) -> 4692175.5 | AV92: Q3 | AW92: 2020 | AX92: =(AU92/AU91)-1 -> 0.07597293 | AZ92: 0.07597293
B93: Q3 | C93: 72337 | D93: =(C93/C92)-1 -> 0.014245454 | E93: 2021 | F93: - - | H93: =C93/(SUM($C$91:$C$94)) -> 0.2515221 | AB93: 2021 | AC93: Q1 | AD93: 5116102 | AE93: =(AD93/AD92)-1 -> -0.032306803 | AF93: 75223.38 | AG93: 3952887.5 | AH93: 553809.2 | AI93: 55979.664 | AJ93: =AVERAGE(AF93:AI93) -> 1159474.9 | AK93: =(AJ93/AJ92)-1 -> 0.013716042 | AU93: =($L$101*AD92)+($L$102*AJ92) -> 4834476.5 | AV93: Q4 | AW93: 2020 | AX93: =(AU93/AU92)-1 -> 0.030327287 | AZ93: 0.030327287
B94: Q4 | C94: 73743 | D94: =(C94/C93)-1 -> 0.019436803 | E94: 2021 | F94: =SUM(C91:C94) -> 287597 | G94: =(F94/F90)-1 -> 0.11844086 | H94: =C94/(SUM($C$91:$C$94)) -> 0.25641088 | AB94: 2021 | AC94: Q2 | AD94: 5337036 | AE94: =(AD94/AD93)-1 -> 0.043184049 | AF94: 75638.98 | AG94: 4059615.5 | AH94: 463547 | AI94: 54779.483 | AJ94: =AVERAGE(AF94:AI94) -> 1163395.2 | AK94: =(AJ94/AJ93)-1 -> 0.0033811035 | AU94: =($L$101*AD93)+($L$102*AJ93) -> 4684038.3 | AV94: Q1 | AW94: 2021 | AX94: =(AU94/AU93)-1 -> -0.031117776 | AZ94: -0.031117776 | BA94: =SUM(AX94:AX97) -> 0.054044818
B95: Q1 | C95: 80149 | D95: =(C95/C94)-1 -> 0.086869262 | E95: 2022 | F95: - - | H95: =C95/(SUM($C$95:$C$98)) -> 0.24724983 | AB95: 2021 | AC95: Q3 | AD95: 5386212 | AE95: =(AD95/AD94)-1 -> 0.0092141031 | AF95: 77590.03 | AG95: 4148927 | AH95: 511232.4 | AI95: 57731.2 | AJ95: =AVERAGE(AF95:AI95) -> 1198870.2 | AK95: =(AJ95/AJ94)-1 -> 0.030492575 | AU95: =($L$101*AD94)+($L$102*AJ94) -> 4881274.4 | AV95: Q2 | AW95: 2021 | AX95: =(AU95/AU94)-1 -> 0.042108132 | AZ95: 0.042108132
B96: Q2 | C96: 80332 | D96: =(C96/C95)-1 -> 0.0022832475 | E96: 2022 | F96: - - | H96: =C96/(SUM($C$95:$C$98)) -> 0.24781436 | AB96: 2021 | AC96: Q4 | AD96: 5568342 | AE96: =(AD96/AD95)-1 -> 0.033814116 | AF96: 77252.53 | AG96: 4186267.3 | AH96: 539107.8 | AI96: 59757.655 | AJ96: =AVERAGE(AF96:AI96) -> 1215596.3 | AK96: =(AJ96/AJ95)-1 -> 0.013951606 | AU96: =($L$101*AD95)+($L$102*AJ95) -> 4928954.3 | AV96: Q3 | AW96: 2021 | AX96: =(AU96/AU95)-1 -> 0.0097679084 | AZ96: 0.0097679084
B97: Q3 | C97: 80894 | D97: =(C97/C96)-1 -> 0.0069959667 | E97: 2022 | F97: - - | H97: =C97/(SUM($C$95:$C$98)) -> 0.24954807 | AB97: 2022 | AC97: Q1 | AD97: 5303774 | AE97: =(AD97/AD96)-1 -> -0.047512886 | AF97: 77049.03 | AG97: 4215571.2 | AH97: 575730.4 | AI97: 60475.56 | AJ97: =AVERAGE(AF97:AI97) -> 1232206.5 | AK97: =(AJ97/AJ96)-1 -> 0.013664262 | AU97: =($L$101*AD96)+($L$102*AJ96) -> 5093022.2 | AV97: Q4 | AW97: 2021 | AX97: =(AU97/AU96)-1 -> 0.033286554 | AZ97: 0.033286554
B98: Q4 | C98: 82787 | D98: =(C98/C97)-1 -> 0.023400994 | E98: 2022 | F98: =SUM(C95:C98) -> 324162 | G98: =(F98/F94)-1 -> 0.12713971 | H98: =C98/(SUM($C$95:$C$98)) -> 0.25538774 | AB98: 2022 | AC98: Q2 | AD98: 5434749 | AE98: =(AD98/AD97)-1 -> 0.02469468 | AF98: 78426.45 | AG98: 4245080.2 | AH98: 524200.6 | AI98: 61436.152 | AJ98: =AVERAGE(AF98:AI98) -> 1227285.9 | AK98: =(AJ98/AJ97)-1 -> -0.0039934027 | AU98: =($L$101*AD97)+($L$102*AJ97) -> 4859158.8 | AV98: Q1 | AW98: 2022 | AX98: =(AU98/AU97)-1 -> -0.045918382 | AZ98: -0.045918382 | BA98: =SUM(AX98:AX101) -> 0.0070603335
B99: Q1 | C99: 91931 | D99: =(C99/C98)-1 -> 0.11045212 | E99: 2023 | F99: - - | H99: - | AB99: 2022 | AC99: Q3 | AD99: 5487022 | AE99: =(AD99/AD98)-1 -> 0.0096182915 | AF99: 80367.1 | AG99: 4262060.5 | AH99: 542920 | AI99: 61964.113 | AJ99: =AVERAGE(AF99:AI99) -> 1236827.9 | AK99: =(AJ99/AJ98)-1 -> 0.0077749431 | AU99: =($L$101*AD98)+($L$102*AJ98) -> 4975294 | AV99: Q2 | AW99: 2022 | AX99: =(AU99/AU98)-1 -> 0.023900266 | AZ99: 0.023900266
B100: Q2 | C100: 92903 | D100: =(C100/C99)-1 -> 0.010573147 | E100: 2023 | F100: - - | H100: - | I100: Geographic segments 6Y average weight on Revenues | AB100: 2022 | AC100: Q4 | AD100: 5596492 | AE100: =(AD100/AD99)-1 -> 0.019950713 | AF100: 78729.38 | AG100: 4262060.5 | AH100: 563168.2 | AI100: 60935.136 | AJ100: =AVERAGE(AF100:AI100) -> 1241223.3 | AK100: =(AJ100/AJ99)-1 -> 0.0035537489 | AU100: =($L$101*AD99)+($L$102*AJ99) -> 5022900.8 | AV100: Q3 | AW100: 2022 | AX100: =(AU100/AU99)-1 -> 0.0095686372 | AZ100: 0.0095686372
B101: Q3 | C101: 92361 | D101: =(C101/C100)-1 -> -0.005834042 | E101: 2023 | F101: - - | H101: - | I101: United States | L101: 0.8908 | AU101: =($L$101*AD100)+($L$102*AJ100) -> 5120896.7 | AV101: Q4 | AW101: 2022 | AX101: =(AU101/AU100)-1 -> 0.019509812 | AZ101: 0.019509812
G102: =AVERAGE(G98,G94,G90,G86,G82,G78,G74,G70,G66,G63) -> 0.11439363 | I102: Global | L102: 0.1092
M106: WA Growth | N106: Revenue Growth | P106: Year | Q106: National Health Expenditures (mn) | R106: Net Cost of Insurance (bn)
M107: 0.014811371 | N107: -0.00062312147 | S107: Annual Revenues (bn) | V107: Growth (National Health Expenditure) | W107: Growth (Net Insurance Cost) | X107: Growth (Annual Revenues) | Y107: LN Rev. | Z107: LN Exp. | AA107: LN Cost
M108: 0.007621932 | N108: 0.0013570512 | P108: 2012 | Q108: 2783.3 | R108: 162.4 | S108: 110.618 | T108: =SUM(Q108:R108) -> 2945.7 | Y108: =LN(S108) -> 4.7060828 | Z108: {=LN(Q108:Q118)} -> 7.9313926 | AA108: {=LN(R108:R118)} -> 5.0900624
M109: 0.013080281 | N109: 0.053732327 | P109: 2013 | Q109: 2856.6 | R109: 169.3 | S109: 122.489 | T109: =SUM(Q109:R109) -> 3025.9 | V109: 0.026335645 | W109: 0.042487685 | X109: 0.10731527 | Y109: =LN(S109) -> 4.8080212 | Z109: 7.9573874 | AA109: 5.1316723
M110: -0.02559118 | N110: 0.05460739 | P110: 2014 | Q110: 3002.6 | R110: 189.7 | S110: 130.474 | T110: =SUM(Q110:R110) -> 3192.3 | V110: 0.051109711 | W110: 0.12049616 | X110: 0.065189527 | Y110: =LN(S110) -> 4.871174 | Z110: 8.0072339 | AA110: 5.2454439
M111: 0.022229998 | N111: 0.0022412657 | P111: 2015 | Q111: 3165.4 | R111: 200.7 | S111: 157.107 | T111: =SUM(Q111:R111) -> 3366.1 | V111: 0.054219676 | W111: 0.057986294 | X111: 0.20412496 | Y111: =LN(S111) -> 5.0569271 | Z111: 8.0600347 | AA111: 5.3018113
M112: 0.015607346 | N112: 0.0071033938 | P112: 2016 | Q112: 3307.4 | R112: 211.5 | S112: 184.84 | T112: =SUM(Q112:R112) -> 3518.9 | V112: 0.044860049 | W112: 0.053811659 | X112: 0.17652301 | Y112: =LN(S112) -> 5.2194906 | Z112: 8.1039177 | AA112: 5.354225
M113: 0.020763729 | N113: 0.016098485 | P113: 2017 | Q113: 3446.5 | R113: 222.6 | S113: 201.159 | T113: =SUM(Q113:R113) -> 3669.1 | V113: 0.042057205 | W113: 0.05248227 | X113: 0.088287167 | Y113: =LN(S113) -> 5.3040956 | Z113: 8.1451145 | AA113: 5.4053764
M114: -0.038255216 | N114: 0.018992833 | P114: 2018 | Q114: 3604.4 | R114: 249 | S114: 226.247 | T114: =SUM(Q114:R114) -> 3853.4 | V114: 0.045814595 | W114: 0.11859838 | X114: 0.12471726 | Y114: =LN(S114) -> 5.4216273 | Z114: 8.1899106 | AA114: 5.5174529
M115: 0.028591876 | N115: 0.027311719 | P115: 2019 | Q115: 3757.4 | R115: 235.6 | S115: 242.155 | T115: =SUM(Q115:R115) -> 3993 | V115: 0.042448119 | W115: -0.053815261 | X115: 0.070312535 | Y115: =LN(S115) -> 5.489578 | Z115: 8.2314825 | AA115: 5.4621355
M116: 0.018894503 | N116: 0.0056793762 | P116: 2020 | Q116: 4144.1 | R116: 296.8 | S116: 257.141 | T116: =SUM(Q116:R116) -> 4440.9 | V116: 0.10291691 | W116: 0.25976231 | X116: 0.061885982 | Y116: =LN(S116) -> 5.5496246 | Z116: 8.3294409 | AA116: 5.6930585
M117: 0.018705383 | N117: 0.020574499 | P117: 2021 | Q117: 4255.1 | R117: 255.7 | S117: 287.597 | T117: =SUM(Q117:R117) -> 4510.8 | V117: 0.026785068 | W117: -0.13847709 | X117: 0.11844086 | Y117: =LN(S117) -> 5.6615602 | Z117: 8.3558735 | AA117: 5.5440049
M118: -0.029744034 | N118: 0.069482248 | P118: 2022 | Q118: 4400 | R118: 264 | S118: 324.162 | T118: =SUM(Q118:R118) -> 4664 | V118: 0.034053254 | W118: 0.032459914 | X118: 0.12713971 | Y118: =LN(S118) -> 5.7812434 | Z118: 8.3893598 | AA118: 5.5759491
M119: 0.028765865 | N119: 0.014179438
M120: 0.010021549 | N120: 0.14411384
M121: 0.010922712 | N121: 0.050856854
M122: -0.031107255 | N122: 0.021284892
M123: 0.026354718 | N123: 0.04397332
M124: 0.011317931 | N124: -0.0038722168
M125: 0.017996204 | N125: 0.026303855
...

Sheet Fin. Data
A1: =Inputs!H3 -> #VALUE!
A2: =Inputs!G2 -> Figures in Millions of USD
A3: Results
B4: =[2]OP1!J20 -> 2022 | C4: =B4-1 -> 2021 | D4: =C4-1 -> 2020 | E4: =D4-1 -> 2019 | F4: =E4-1 -> 2018 | G4: =F4-1 -> 2017 | H4: =G4-1 -> 2016 | I4: =H4-1 -> 2015 | J4: =I4-1 -> 2014 | ... M4: =L4-1 -> 2011
A5: Net Sales | B5: =_xlfn.XLOOKUP($A5,Inputs!$A:$A,Inputs!B:B,,0) -> 324162 | C5: =_xlfn.XLOOKUP($A5,Inputs!$A:$A,Inputs!C:C,,0) -> 287597 | D5: =_xlfn.XLOOKUP($A5,Inputs!$A:$A,Inputs!D:D,,0) -> 257141 | E5: =_xlfn.XLOOKUP($A5,Inputs!$A:$A,Inputs!E:E,,0) -> 242155 | F5: =_xlfn.XLOOKUP($A5,Inputs!$A:$A,Inputs!F:F,,0) -> 226247 | G5: =_xlfn.XLOOKUP($A5,Inputs!$A:$A,Inputs!G:G,,0) -> 201159 | H5: =_xlfn.XLOOKUP($A5,Inputs!$A:$A,Inputs!H:H,,0) -> 184840 | I5: =_xlfn.XLOOKUP($A5,Inputs!$A:$A,Inputs!I:I,,0) -> 157107 | J5: =_xlfn.XLOOKUP($A5,Inputs!$A:$A,Inputs!J:J,,0) -> 130474 | K5: =_xlfn.XLOOKUP($A5,Inputs!$A:$A,Inputs!K:K,,0) -> 122489 | L5: =_xlfn.XLOOKUP($A5,Inputs!$A:$A,Inputs!L:L,,0) -> 110618 | M5: =_xlfn.XLOOKUP($A5,Inputs!$A:$A,Inputs!M:M,,0) -> 101862
A6: Growth vs. Previous year | B6: =IFERROR(B5/C5-1,"-") -> 0.12713971 | C6: =IFERROR(C5/D5-1,"-") -> 0.11844086 | D6: =IFERROR(D5/E5-1,"-") -> 0.061885982 | E6: =IFERROR(E5/F5-1,"-") -> 0.070312535 | F6: =IFERROR(F5/G5-1,"-") -> 0.12471726 | G6: =IFERROR(G5/H5-1,"-") -> 0.088287167 | H6: =IFERROR(H5/I5-1,"-") -> 0.17652301 | I6: =IFERROR(I5/J5-1,"-") -> 0.20412496 | ... L6: =IFERROR(L5/M5-1,"-") -> 0.085959435 | M6: =IFERROR(M5/#REF!-1,"-") -> - | AJ6: 2022 | AK6: =AJ6-1 -> 2021 | AL6: =AK6-1 -> 2020 | AM6: =AL6-1 -> 2019 | AN6: =AM6-1 -> 2018 | AO6: =AN6-1 -> 2017 | AP6: =AO6-1 -> 2016 | AQ6: =AP6-1 -> 2015 | AR6: =AQ6-1 -> 2014 | ... AU6: =AT6-1 -> 2011
A7: Gross Profit | B7: =_xlfn.XLOOKUP($A7,Inputs!$A:$A,Inputs!B:B,,0) -> 290459 | C7: =_xlfn.XLOOKUP($A7,Inputs!$A:$A,Inputs!C:C,,0) -> 256563 | D7: =_xlfn.XLOOKUP($A7,Inputs!$A:$A,Inputs!D:D,,0) -> 226396 | E7: =_xlfn.XLOOKUP($A7,Inputs!$A:$A,Inputs!E:E,,0) -> 214038 | F7: =_xlfn.XLOOKUP($A7,Inputs!$A:$A,Inputs!F:F,,0) -> 199249 | G7: =_xlfn.XLOOKUP($A7,Inputs!$A:$A,Inputs!G:G,,0) -> 177047 | H7: =_xlfn.XLOOKUP($A7,Inputs!$A:$A,Inputs!H:H,,0) -> 160424 | I7: =_xlfn.XLOOKUP($A7,Inputs!$A:$A,Inputs!I:I,,0) -> 140901 | J7: =_xlfn.XLOOKUP($A7,Inputs!$A:$A,Inputs!J:J,,0) -> 126690 | K7: =_xlfn.XLOOKUP($A7,Inputs!$A:$A,Inputs!K:K,,0) -> 119650 | L7: =_xlfn.XLOOKUP($A7,Inputs!$A:$A,Inputs!L:L,,0) -> 108095 | M7: =_xlfn.XLOOKUP($A7,Inputs!$A:$A,Inputs!M:M,,0) -> 99477 | AI7: Operating Margin | AJ7: 0.087718486 | AK7: 0.083345793 | AL7: 0.087131185 | AM7: 0.081290909 | AN7: 0.07665958 | AO7: 0.075606858 | AP7: 0.069952391 | AQ7: 0.070149643 | AR7: 0.078743658 | AS7: 0.078562157 | AT7: 0.083657271 | AU7: 0.083092812
A8: % over sales | B8: =IFERROR(B7/B$5,"-") -> 0.89603038 | C8: =IFERROR(C7/C$5,"-") -> 0.89209206 | D8: =IFERROR(D7/D$5,"-") -> 0.88043525 | E8: =IFERROR(E7/E$5,"-") -> 0.88388842 | F8: =IFERROR(F7/F$5,"-") -> 0.88067024 | G8: =IFERROR(G7/G$5,"-") -> 0.88013462 | H8: =IFERROR(H7/H$5,"-") -> 0.86790738 | I8: =IFERROR(I7/I$5,"-") -> 0.89684737 | ... M8: =IFERROR(M7/M$5,"-") -> 0.97658597 | AI8: Net Income Margin | AJ8: 0.063668783 | AK8: 0.06165572 | AL8: 0.061324332 | AM8: 0.058801181 | AN8: 0.054727797 | AO8: 0.04783778 | AP8: 0.038265527 | AQ8: 0.037350341 | AR8: 0.043066051 | AS8: 0.046314363 | AT8: 0.049955703 | AU8: 0.050480061
A9: Operating expenses | B9: =B5-B11 -> 295727 | C9: =C5-C11 -> 263627 | D9: =D5-D11 -> 234736 | E9: =E5-E11 -> 222470 | F9: =F5-F11 -> 208903 | G9: =G5-G11 -> 185950 | H9: =H5-H11 -> 171910 | I9: =I5-I11 -> 146086 | ... M9: =M5-M11 -> 93398
A10: % over sales | B10: =IFERROR(B9/B$5,"-") -> 0.91228151 | C10: =IFERROR(C9/C$5,"-") -> 0.91665421 | D10: =IFERROR(D9/D$5,"-") -> 0.91286882 | E10: =IFERROR(E9/E$5,"-") -> 0.91870909 | F10: =IFERROR(F9/F$5,"-") -> 0.92334042 | G10: =IFERROR(G9/G$5,"-") -> 0.92439314 | H10: =IFERROR(H9/H$5,"-") -> 0.93004761 | I10: =IFERROR(I9/I$5,"-") -> 0.92985036 | ... M10: =IFERROR(M9/M$5,"-") -> 0.91690719
A11: Operating Income | B11: =_xlfn.XLOOKUP($A11,Inputs!$A:$A,Inputs!B:B,,0) -> 28435 | C11: =_xlfn.XLOOKUP($A11,Inputs!$A:$A,Inputs!C:C,,0) -> 23970 | D11: =_xlfn.XLOOKUP($A11,Inputs!$A:$A,Inputs!D:D,,0) -> 22405 | E11: =_xlfn.XLOOKUP($A11,Inputs!$A:$A,Inputs!E:E,,0) -> 19685 | F11: =_xlfn.XLOOKUP($A11,Inputs!$A:$A,Inputs!F:F,,0) -> 17344 | G11: =_xlfn.XLOOKUP($A11,Inputs!$A:$A,Inputs!G:G,,0) -> 15209 | H11: =_xlfn.XLOOKUP($A11,Inputs!$A:$A,Inputs!H:H,,0) -> 12930 | I11: =_xlfn.XLOOKUP($A11,Inputs!$A:$A,Inputs!I:I,,0) -> 11021 | J11: =_xlfn.XLOOKUP($A11,Inputs!$A:$A,Inputs!J:J,,0) -> 10274 | K11: =_xlfn.XLOOKUP($A11,Inputs!$A:$A,Inputs!K:K,,0) -> 9623 | L11: =_xlfn.XLOOKUP($A11,Inputs!$A:$A,Inputs!L:L,,0) -> 9254 | M11: =_xlfn.XLOOKUP($A11,Inputs!$A:$A,Inputs!M:M,,0) -> 8464
A12: Operating Margin | B12: =IFERROR(B11/B$5,"-") -> 0.087718486 | C12: =IFERROR(C11/C$5,"-") -> 0.083345793 | D12: =IFERROR(D11/D$5,"-") -> 0.087131185 | E12: =IFERROR(E11/E$5,"-") -> 0.081290909 | F12: =IFERROR(F11/F$5,"-") -> 0.07665958 | G12: =IFERROR(G11/G$5,"-") -> 0.075606858 | H12: =IFERROR(H11/H$5,"-") -> 0.069952391 | I12: =IFERROR(I11/I$5,"-") -> 0.070149643 | ... M12: =IFERROR(M11/M$5,"-") -> 0.083092812
A13: Growth vs. Previous year | B13: =IFERROR(B12/C12-1,"-") -> 0.052464478 | C13: =IFERROR(C12/D12-1,"-") -> -0.043444743 | D13: =IFERROR(D12/E12-1,"-") -> 0.071844149 | E13: =IFERROR(E12/F12-1,"-") -> 0.06041422 | F13: =IFERROR(F12/G12-1,"-") -> 0.013923628 | G13: =IFERROR(G12/H12-1,"-") -> 0.080833077 | H13: =IFERROR(H12/I12-1,"-") -> -0.0028118743 | I13: =IFERROR(I12/J12-1,"-") -> -0.10913913 | ... L13: =IFERROR(L12/M12-1,"-") -> 0.0067931162 | M13: =IFERROR(M12/#REF!-1,"-") -> -
A14: Net Financial Cost | B14: =_xlfn.XLOOKUP($A14,Inputs!$A:$A,Inputs!B:B,,0) -> -2092 | C14: =_xlfn.XLOOKUP($A14,Inputs!$A:$A,Inputs!C:C,,0) -> -1660 | D14: =_xlfn.XLOOKUP($A14,Inputs!$A:$A,Inputs!D:D,,0) -> -1663 | E14: =_xlfn.XLOOKUP($A14,Inputs!$A:$A,Inputs!E:E,,0) -> -1704 | F14: =_xlfn.XLOOKUP($A14,Inputs!$A:$A,Inputs!F:F,,0) -> -1400 | G14: =_xlfn.XLOOKUP($A14,Inputs!$A:$A,Inputs!G:G,,0) -> -1186 | H14: =_xlfn.XLOOKUP($A14,Inputs!$A:$A,Inputs!H:H,,0) -> -1067 | I14: =_xlfn.XLOOKUP($A14,Inputs!$A:$A,Inputs!I:I,,0) -> -790 | J14: =_xlfn.XLOOKUP($A14,Inputs!$A:$A,Inputs!J:J,,0) -> -618 | K14: =_xlfn.XLOOKUP($A14,Inputs!$A:$A,Inputs!K:K,,0) -> -708 | L14: =_xlfn.XLOOKUP($A14,Inputs!$A:$A,Inputs!L:L,,0) -> -632 | M14: =_xlfn.XLOOKUP($A14,Inputs!$A:$A,Inputs!M:M,,0) -> -505
A15: Other Expenses (Revenues) | B15: =_xlfn.XLOOKUP($A15,Inputs!$A:$A,Inputs!B:B,,0) -> 0 | C15: =_xlfn.XLOOKUP($A15,Inputs!$A:$A,Inputs!C:C,,0) -> 0 | D15: =_xlfn.XLOOKUP($A15,Inputs!$A:$A,Inputs!D:D,,0) -> 0 | E15: =_xlfn.XLOOKUP($A15,Inputs!$A:$A,Inputs!E:E,,0) -> 0 | F15: =_xlfn.XLOOKUP($A15,Inputs!$A:$A,Inputs!F:F,,0) -> 0 | G15: =_xlfn.XLOOKUP($A15,Inputs!$A:$A,Inputs!G:G,,0) -> 0 | H15: =_xlfn.XLOOKUP($A15,Inputs!$A:$A,Inputs!H:H,,0) -> 0 | I15: =_xlfn.XLOOKUP($A15,Inputs!$A:$A,Inputs!I:I,,0) -> 0 | J15: =_xlfn.XLOOKUP($A15,Inputs!$A:$A,Inputs!J:J,,0) -> 0 | K15: =_xlfn.XLOOKUP($A15,Inputs!$A:$A,Inputs!K:K,,0) -> 0 | L15: =_xlfn.XLOOKUP($A15,Inputs!$A:$A,Inputs!L:L,,0) -> 0 | M15: =_xlfn.XLOOKUP($A15,Inputs!$A:$A,Inputs!M:M,,0) -> 0
A16: EBIT | B16: =B11-B15 -> 28435 | C16: =C11-C15 -> 23970 | D16: =D11-D15 -> 22405 | E16: =E11-E15 -> 19685 | F16: =F11-F15 -> 17344 | G16: =G11-G15 -> 15209 | H16: =H11-H15 -> 12930 | I16: =I11-I15 -> 11021 | ... M16: =M11-M15 -> 8464
A17: Depreciation & Amortization | B17: =_xlfn.XLOOKUP($A17,Inputs!$A:$A,Inputs!B:B,,0) -> 3400 | C17: =_xlfn.XLOOKUP($A17,Inputs!$A:$A,Inputs!C:C,,0) -> 3103 | D17: =_xlfn.XLOOKUP($A17,Inputs!$A:$A,Inputs!D:D,,0) -> 2891 | E17: =_xlfn.XLOOKUP($A17,Inputs!$A:$A,Inputs!E:E,,0) -> 2720 | F17: =_xlfn.XLOOKUP($A17,Inputs!$A:$A,Inputs!F:F,,0) -> 2428 | G17: =_xlfn.XLOOKUP($A17,Inputs!$A:$A,Inputs!G:G,,0) -> 2245 | H17: =_xlfn.XLOOKUP($A17,Inputs!$A:$A,Inputs!H:H,,0) -> 2055 | I17: =_xlfn.XLOOKUP($A17,Inputs!$A:$A,Inputs!I:I,,0) -> 1693 | J17: =_xlfn.XLOOKUP($A17,Inputs!$A:$A,Inputs!J:J,,0) -> 1478 | K17: =_xlfn.XLOOKUP($A17,Inputs!$A:$A,Inputs!K:K,,0) -> 1375 | L17: =_xlfn.XLOOKUP($A17,Inputs!$A:$A,Inputs!L:L,,0) -> 1309 | M17: =_xlfn.XLOOKUP($A17,Inputs!$A:$A,Inputs!M:M,,0) -> 1124
A18: Changes Net Working Capital | B18: =_xlfn.XLOOKUP($A18,Inputs!$A:$A,Inputs!B:B,,0) -> -7638 | C18: =_xlfn.XLOOKUP($A18,Inputs!$A:$A,Inputs!C:C,,0) -> -1958 | D18: =_xlfn.XLOOKUP($A18,Inputs!$A:$A,Inputs!D:D,,0) -> -5090 | E18: =_xlfn.XLOOKUP($A18,Inputs!$A:$A,Inputs!E:E,,0) -> -4552 | F18: =_xlfn.XLOOKUP($A18,Inputs!$A:$A,Inputs!F:F,,0) -> 28 | G18: =_xlfn.XLOOKUP($A18,Inputs!$A:$A,Inputs!G:G,,0) -> -221 | H18: =_xlfn.XLOOKUP($A18,Inputs!$A:$A,Inputs!H:H,,0) -> -4468 | I18: =_xlfn.XLOOKUP($A18,Inputs!$A:$A,Inputs!I:I,,0) -> -7877 | J18: =_xlfn.XLOOKUP($A18,Inputs!$A:$A,Inputs!J:J,,0) -> 411 | K18: =_xlfn.XLOOKUP($A18,Inputs!$A:$A,Inputs!K:K,,0) -> 787 | L18: =_xlfn.XLOOKUP($A18,Inputs!$A:$A,Inputs!L:L,,0) -> -1923 | M18: =_xlfn.XLOOKUP($A18,Inputs!$A:$A,Inputs!M:M,,0) -> 0
A19: EBITDA | B19: =B11-B15+B17 -> 31835 | C19: =C11-C15+C17 -> 27073 | D19: =D11-D15+D17 -> 25296 | E19: =E11-E15+E17 -> 22405 | F19: =F11-F15+F17 -> 19772 | G19: =G11-G15+G17 -> 17454 | H19: =H11-H15+H17 -> 14985 | I19: =I11-I15+I17 -> 12714 | ... M19: =M11-M15+M17 -> 9588
A20: EBITDA Margin | B20: =IFERROR(B19/B$5,"-") -> 0.098207069 | C20: =IFERROR(C19/C$5,"-") -> 0.094135196 | D20: =IFERROR(D19/D$5,"-") -> 0.098374044 | E20: =IFERROR(E19/E$5,"-") -> 0.092523384 | F20: =IFERROR(F19/F$5,"-") -> 0.087391214 | G20: =IFERROR(G19/G$5,"-") -> 0.086767184 | H20: =IFERROR(H19/H$5,"-") -> 0.081070115 | I20: =IFERROR(I19/I$5,"-") -> 0.080925739 | ... M20: =IFERROR(M19/M$5,"-") -> 0.094127349
A21: Taxes | B21: =_xlfn.XLOOKUP($A21,Inputs!$A:$A,Inputs!B:B,,0) -> -5704 | C21: =_xlfn.XLOOKUP($A21,Inputs!$A:$A,Inputs!C:C,,0) -> -4578 | D21: =_xlfn.XLOOKUP($A21,Inputs!$A:$A,Inputs!D:D,,0) -> -4973 | E21: =_xlfn.XLOOKUP($A21,Inputs!$A:$A,Inputs!E:E,,0) -> -3742 | F21: =_xlfn.XLOOKUP($A21,Inputs!$A:$A,Inputs!F:F,,0) -> -3562 | G21: =_xlfn.XLOOKUP($A21,Inputs!$A:$A,Inputs!G:G,,0) -> -4400 | H21: =_xlfn.XLOOKUP($A21,Inputs!$A:$A,Inputs!H:H,,0) -> -4790 | I21: =_xlfn.XLOOKUP($A21,Inputs!$A:$A,Inputs!I:I,,0) -> -4363 | J21: =_xlfn.XLOOKUP($A21,Inputs!$A:$A,Inputs!J:J,,0) -> -4037 | K21: =_xlfn.XLOOKUP($A21,Inputs!$A:$A,Inputs!K:K,,0) -> -3242 | L21: =_xlfn.XLOOKUP($A21,Inputs!$A:$A,Inputs!L:L,,0) -> -3096 | M21: =_xlfn.XLOOKUP($A21,Inputs!$A:$A,Inputs!M:M,,0) -> -2817
A22: % Tax | B22: =IFERROR(B21/B$5,"-") -> -0.01759614 | C22: =IFERROR(C21/C$5,"-") -> -0.015918108 | D22: =IFERROR(D21/D$5,"-") -> -0.019339584 | E22: =IFERROR(E21/E$5,"-") -> -0.015452912 | F22: =IFERROR(F21/F$5,"-") -> -0.015743855 | G22: =IFERROR(G21/G$5,"-") -> -0.021873245 | H22: =IFERROR(H21/H$5,"-") -> -0.025914304 | I22: =IFERROR(I21/I$5,"-") -> -0.027770882 | ... M22: =IFERROR(M21/M$5,"-") -> -0.027655063
A23: Net Income | B23: =_xlfn.XLOOKUP($A23,Inputs!$A:$A,Inputs!B:B,,0) -> 20639 | C23: =_xlfn.XLOOKUP($A23,Inputs!$A:$A,Inputs!C:C,,0) -> 17732 | D23: =_xlfn.XLOOKUP($A23,Inputs!$A:$A,Inputs!D:D,,0) -> 15769 | E23: =_xlfn.XLOOKUP($A23,Inputs!$A:$A,Inputs!E:E,,0) -> 14239 | F23: =_xlfn.XLOOKUP($A23,Inputs!$A:$A,Inputs!F:F,,0) -> 12382 | G23: =_xlfn.XLOOKUP($A23,Inputs!$A:$A,Inputs!G:G,,0) -> 9623 | H23: =_xlfn.XLOOKUP($A23,Inputs!$A:$A,Inputs!H:H,,0) -> 7073 | I23: =_xlfn.XLOOKUP($A23,Inputs!$A:$A,Inputs!I:I,,0) -> 5868 | J23: =_xlfn.XLOOKUP($A23,Inputs!$A:$A,Inputs!J:J,,0) -> 5619 | K23: =_xlfn.XLOOKUP($A23,Inputs!$A:$A,Inputs!K:K,,0) -> 5673 | L23: =_xlfn.XLOOKUP($A23,Inputs!$A:$A,Inputs!L:L,,0) -> 5526 | M23: =_xlfn.XLOOKUP($A23,Inputs!$A:$A,Inputs!M:M,,0) -> 5142
A24: Net Income Margin | B24: =IFERROR(B23/B$5,"-") -> 0.063668783 | C24: =IFERROR(C23/C$5,"-") -> 0.06165572 | D24: =IFERROR(D23/D$5,"-") -> 0.061324332 | E24: =IFERROR(E23/E$5,"-") -> 0.058801181 | F24: =IFERROR(F23/F$5,"-") -> 0.054727797 | G24: =IFERROR(G23/G$5,"-") -> 0.04783778 | H24: =IFERROR(H23/H$5,"-") -> 0.038265527 | I24: =IFERROR(I23/I$5,"-") -> 0.037350341 | ... M24: =IFERROR(M23/M$5,"-") -> 0.050480061
A25: Growth vs. Previous year | B25: =IFERROR(B24/C24-1,"-") -> 0.032650065 | C25: =IFERROR(C24/D24-1,"-") -> 0.0054038558 | D25: =IFERROR(D24/E24-1,"-") -> 0.042909865 | E25: =IFERROR(E24/F24-1,"-") -> 0.074429883 | F25: =IFERROR(F24/G24-1,"-") -> 0.14402879 | G25: =IFERROR(G24/H24-1,"-") -> 0.25015344 | H25: =IFERROR(H24/I24-1,"-") -> 0.024502751 | I25: =IFERROR(I24/J24-1,"-") -> -0.13271963 | ... L25: =IFERROR(L24/M24-1,"-") -> -0.010387425 | M25: =IFERROR(M24/#REF!-1,"-") -> -
A26: Cash Generated | B26: =B39-C39 -> 4004 | C26: =C39-D39 -> 4126 | D26: =D39-E39 -> 5536 | E26: =E39-F39 -> -79 | F26: =F39-G39 -> -1166 | G26: =G39-H39 -> 2215 | H26: =H39-I39 -> 364 | I26: =I39-J39 -> 3675 | ... M26: =M39-N39 -> 12006
A27: Dividends | B27: =_xlfn.XLOOKUP($A27,Inputs!$A:$A,Inputs!B:B,,0) -> -5991 | C27: =_xlfn.XLOOKUP($A27,Inputs!$A:$A,Inputs!C:C,,0) -> -5280 | D27: =_xlfn.XLOOKUP($A27,Inputs!$A:$A,Inputs!D:D,,0) -> -4584 | E27: =_xlfn.XLOOKUP($A27,Inputs!$A:$A,Inputs!E:E,,0) -> -3932 | F27: =_xlfn.XLOOKUP($A27,Inputs!$A:$A,Inputs!F:F,,0) -> -3320 | G27: =_xlfn.XLOOKUP($A27,Inputs!$A:$A,Inputs!G:G,,0) -> -2773 | H27: =_xlfn.XLOOKUP($A27,Inputs!$A:$A,Inputs!H:H,,0) -> -2261 | I27: =_xlfn.XLOOKUP($A27,Inputs!$A:$A,Inputs!I:I,,0) -> -1786 | J27: =_xlfn.XLOOKUP($A27,Inputs!$A:$A,Inputs!J:J,,0) -> -1362 | K27: =_xlfn.XLOOKUP($A27,Inputs!$A:$A,Inputs!K:K,,0) -> -1056 | L27: =_xlfn.XLOOKUP($A27,Inputs!$A:$A,Inputs!L:L,,0) -> -820 | M27: =_xlfn.XLOOKUP($A27,Inputs!$A:$A,Inputs!M:M,,0) -> -651
A28: Share buyback | B28: =_xlfn.XLOOKUP($A28,Inputs!$A:$A,Inputs!B:B,,0) -> -5747 | C28: =_xlfn.XLOOKUP($A28,Inputs!$A:$A,Inputs!C:C,,0) -> -3645 | D28: =_xlfn.XLOOKUP($A28,Inputs!$A:$A,Inputs!D:D,,0) -> -2810 | E28: =_xlfn.XLOOKUP($A28,Inputs!$A:$A,Inputs!E:E,,0) -> -4463 | F28: =_xlfn.XLOOKUP($A28,Inputs!$A:$A,Inputs!F:F,,0) -> -3662 | G28: =_xlfn.XLOOKUP($A28,Inputs!$A:$A,Inputs!G:G,,0) -> -812 | H28: =_xlfn.XLOOKUP($A28,Inputs!$A:$A,Inputs!H:H,,0) -> -851 | I28: =_xlfn.XLOOKUP($A28,Inputs!$A:$A,Inputs!I:I,,0) -> -798 | J28: =_xlfn.XLOOKUP($A28,Inputs!$A:$A,Inputs!J:J,,0) -> -3546 | K28: =_xlfn.XLOOKUP($A28,Inputs!$A:$A,Inputs!K:K,,0) -> -2572 | L28: =_xlfn.XLOOKUP($A28,Inputs!$A:$A,Inputs!L:L,,0) -> -2006 | M28: =_xlfn.XLOOKUP($A28,Inputs!$A:$A,Inputs!M:M,,0) -> -2613
A29: Net Cash Flow | B29: =SUM(B26:B28) -> -7734 | C29: =SUM(C26:C28) -> -4799 | D29: =SUM(D26:D28) -> -1858 | E29: =SUM(E26:E28) -> -8474 | F29: =SUM(F26:F28) -> -8148 | G29: =SUM(G26:G28) -> -1370 | H29: =SUM(H26:H28) -> -2748 | I29: =SUM(I26:I28) -> 1091 | ... M29: =SUM(M26:M28) -> 8742
A30: FNP'' | B30: =+B29-(B58-C29) -> -76000 | C30: =+C29-(C58-D29) -> -58496 | D30: =+D29-(D58-E29) -> -60008 | E30: =+E29-(E58-F29) -> -62915 | F30: =+F29-(F58-G29) -> -50942 | G30: =+G29-(G58-H29) -> -40261 | H30: =+H29-(H58-I29) -> -41880 | I30: =+I29-(I58-J29) -> -43984 | ... M30: =+M29-(M58-N29) -> -7917
A31: FNP' | B31: =+B30+B33 -> -101674 | C31: =+C30+C33 -> -66414 | D31: =+D30+D33 -> -70489 | E31: =+E30+E33 -> -73543 | F31: =+F30+F33 -> -61264 | G31: =+G30+G33 -> -46837 | H31: =+H30+H33 -> -49530 | I31: =+I30+I33 -> -60823 | ... M31: =+M30+M33 -> -11022
A32: Net Capex | B32: =_xlfn.XLOOKUP($A32,Inputs!$A:$A,Inputs!B:B,,0) -> -2802 | C32: =_xlfn.XLOOKUP($A32,Inputs!$A:$A,Inputs!C:C,,0) -> -2454 | D32: =_xlfn.XLOOKUP($A32,Inputs!$A:$A,Inputs!D:D,,0) -> -2051 | E32: =_xlfn.XLOOKUP($A32,Inputs!$A:$A,Inputs!E:E,,0) -> -2071 | F32: =_xlfn.XLOOKUP($A32,Inputs!$A:$A,Inputs!F:F,,0) -> -2063 | G32: =_xlfn.XLOOKUP($A32,Inputs!$A:$A,Inputs!G:G,,0) -> -2023 | H32: =_xlfn.XLOOKUP($A32,Inputs!$A:$A,Inputs!H:H,,0) -> -1705 | I32: =_xlfn.XLOOKUP($A32,Inputs!$A:$A,Inputs!I:I,,0) -> -1556 | J32: =_xlfn.XLOOKUP($A32,Inputs!$A:$A,Inputs!J:J,,0) -> -1525 | K32: =_xlfn.XLOOKUP($A32,Inputs!$A:$A,Inputs!K:K,,0) -> -1307 | L32: =_xlfn.XLOOKUP($A32,Inputs!$A:$A,Inputs!L:L,,0) -> -1070 | M32: =_xlfn.XLOOKUP($A32,Inputs!$A:$A,Inputs!M:M,,0) -> -1067
A33: Investments & Acquisitions | B33: =_xlfn.XLOOKUP($A33,Inputs!$A:$A,Inputs!B:B,,0) -> -25674 | C33: =_xlfn.XLOOKUP($A33,Inputs!$A:$A,Inputs!C:C,,0) -> -7918 | D33: =_xlfn.XLOOKUP($A33,Inputs!$A:$A,Inputs!D:D,,0) -> -10481 | E33: =_xlfn.XLOOKUP($A33,Inputs!$A:$A,Inputs!E:E,,0) -> -10628 | F33: =_xlfn.XLOOKUP($A33,Inputs!$A:$A,Inputs!F:F,,0) -> -10322 | G33: =_xlfn.XLOOKUP($A33,Inputs!$A:$A,Inputs!G:G,,0) -> -6576 | H33: =_xlfn.XLOOKUP($A33,Inputs!$A:$A,Inputs!H:H,,0) -> -7650 | I33: =_xlfn.XLOOKUP($A33,Inputs!$A:$A,Inputs!I:I,,0) -> -16839 | J33: =_xlfn.XLOOKUP($A33,Inputs!$A:$A,Inputs!J:J,,0) -> -1009 | K33: =_xlfn.XLOOKUP($A33,Inputs!$A:$A,Inputs!K:K,,0) -> -1782 | L33: =_xlfn.XLOOKUP($A33,Inputs!$A:$A,Inputs!L:L,,0) -> -7579 | M33: =_xlfn.XLOOKUP($A33,Inputs!$A:$A,Inputs!M:M,,0) -> -3105
A34: Capex + Investments | B34: =+B32+B33 -> -28476 | C34: =+C32+C33 -> -10372 | D34: =+D32+D33 -> -12532 | E34: =+E32+E33 -> -12699 | F34: =+F32+F33 -> -12385 | G34: =+G32+G33 -> -8599 | H34: =+H32+H33 -> -9355 | I34: =+I32+I33 -> -18395 | ... M34: =+M32+M33 -> -4172
A35: Dividends + Share Buyback | B35: =+B27+B28 -> -11738 | C35: =+C27+C28 -> -8925 | D35: =+D27+D28 -> -7394 | E35: =+E27+E28 -> -8395 | F35: =+F27+F28 -> -6982 | G35: =+G27+G28 -> -3585 | H35: =+H27+H28 -> -3112 | I35: =+I27+I28 -> -2584 | ... M35: =+M27+M28 -> -3264
A36: Payout Ratio | B36: =-IFERROR(B35/B23,"-") -> 0.56872911 | C36: =-IFERROR(C35/C23,"-") -> 0.50332732 | D36: =-IFERROR(D35/D23,"-") -> 0.46889467 | E36: =-IFERROR(E35/E23,"-") -> 0.58957792 | F36: =-IFERROR(F35/F23,"-") -> 0.56388306 | G36: =-IFERROR(G35/G23,"-") -> 0.37254494 | H36: =-IFERROR(H35/H23,"-") -> 0.43998303 | I36: =-IFERROR(I35/I23,"-") -> 0.44035446 | ... L36: =-IFERROR(L35/L23,"-") -> 0.51140065 | M36: =IFERROR(M35/M23,"-") -> -0.63477246
A38: Assets
A39: Cash & Eq. | B39: =_xlfn.XLOOKUP($A39,Inputs!$A:$A,Inputs!B:B,,0) -> 27911 | C39: =_xlfn.XLOOKUP($A39,Inputs!$A:$A,Inputs!C:C,,0) -> 23907 | D39: =_xlfn.XLOOKUP($A39,Inputs!$A:$A,Inputs!D:D,,0) -> 19781 | E39: =_xlfn.XLOOKUP($A39,Inputs!$A:$A,Inputs!E:E,,0) -> 14245 | F39: =_xlfn.XLOOKUP($A39,Inputs!$A:$A,Inputs!F:F,,0) -> 14324 | G39: =_xlfn.XLOOKUP($A39,Inputs!$A:$A,Inputs!G:G,,0) -> 15490 | H39: =_xlfn.XLOOKUP($A39,Inputs!$A:$A,Inputs!H:H,,0) -> 13275 | I39: =_xlfn.XLOOKUP($A39,Inputs!$A:$A,Inputs!I:I,,0) -> 12911 | J39: =_xlfn.XLOOKUP($A39,Inputs!$A:$A,Inputs!J:J,,0) -> 9236 | K39: =_xlfn.XLOOKUP($A39,Inputs!$A:$A,Inputs!K:K,,0) -> 9213 | L39: =_xlfn.XLOOKUP($A39,Inputs!$A:$A,Inputs!L:L,,0) -> 11437 | M39: =_xlfn.XLOOKUP($A39,Inputs!$A:$A,Inputs!M:M,,0) -> 12006
A40: Accounts Receivable | B40: =_xlfn.XLOOKUP($A40,Inputs!$A:$A,Inputs!B:B,,0) -> 30450 | C40: =_xlfn.XLOOKUP($A40,Inputs!$A:$A,Inputs!C:C,,0) -> 28082 | D40: =_xlfn.XLOOKUP($A40,Inputs!$A:$A,Inputs!D:D,,0) -> 25404 | E40: =_xlfn.XLOOKUP($A40,Inputs!$A:$A,Inputs!E:E,,0) -> 21462 | F40: =_xlfn.XLOOKUP($A40,Inputs!$A:$A,Inputs!F:F,,0) -> 18250 | G40: =_xlfn.XLOOKUP($A40,Inputs!$A:$A,Inputs!G:G,,0) -> 15830 | H40: =_xlfn.XLOOKUP($A40,Inputs!$A:$A,Inputs!H:H,,0) -> 15651 | I40: =_xlfn.XLOOKUP($A40,Inputs!$A:$A,Inputs!I:I,,0) -> 13324 | J40: =_xlfn.XLOOKUP($A40,Inputs!$A:$A,Inputs!J:J,,0) -> 9750 | K40: =_xlfn.XLOOKUP($A40,Inputs!$A:$A,Inputs!K:K,,0) -> 7050 | L40: =_xlfn.XLOOKUP($A40,Inputs!$A:$A,Inputs!L:L,,0) -> 5598 | M40: =_xlfn.XLOOKUP($A40,Inputs!$A:$A,Inputs!M:M,,0) -> 4549
A41: Inventory (2021-2022) | B41: 24523 | C41: 23267 | D41: 23927 | E41: 19827 | F41: 16438 | G41: 15535 | H41: 15297 | I41: 14183 | J41: 11809 | K41: 10052 | L41: -26749 | M41: -27485
A42: Property, Plant and Equipment | B42: =_xlfn.XLOOKUP($A42,Inputs!$A:$A,Inputs!B:B,,0) -> 10128 | C42: =_xlfn.XLOOKUP($A42,Inputs!$A:$A,Inputs!C:C,,0) -> 8969 | D42: =_xlfn.XLOOKUP($A42,Inputs!$A:$A,Inputs!D:D,,0) -> 8626 | E42: =_xlfn.XLOOKUP($A42,Inputs!$A:$A,Inputs!E:E,,0) -> 8704 | F42: =_xlfn.XLOOKUP($A42,Inputs!$A:$A,Inputs!F:F,,0) -> 8458 | G42: =_xlfn.XLOOKUP($A42,Inputs!$A:$A,Inputs!G:G,,0) -> 7013 | H42: =_xlfn.XLOOKUP($A42,Inputs!$A:$A,Inputs!H:H,,0) -> 5901 | I42: =_xlfn.XLOOKUP($A42,Inputs!$A:$A,Inputs!I:I,,0) -> 4861 | J42: =_xlfn.XLOOKUP($A42,Inputs!$A:$A,Inputs!J:J,,0) -> 4418 | K42: =_xlfn.XLOOKUP($A42,Inputs!$A:$A,Inputs!K:K,,0) -> 4010 | L42: =_xlfn.XLOOKUP($A42,Inputs!$A:$A,Inputs!L:L,,0) -> 3939 | M42: =_xlfn.XLOOKUP($A42,Inputs!$A:$A,Inputs!M:M,,0) -> 2515
A43: Other Assets | B43: =_xlfn.XLOOKUP($A43,Inputs!$A:$A,Inputs!B:B,,0) -> 129988 | C43: =_xlfn.XLOOKUP($A43,Inputs!$A:$A,Inputs!C:C,,0) -> 105234 | D43: =_xlfn.XLOOKUP($A43,Inputs!$A:$A,Inputs!D:D,,0) -> 102236 | E43: =_xlfn.XLOOKUP($A43,Inputs!$A:$A,Inputs!E:E,,0) -> 92269 | F43: =_xlfn.XLOOKUP($A43,Inputs!$A:$A,Inputs!F:F,,0) -> 78679 | G43: =_xlfn.XLOOKUP($A43,Inputs!$A:$A,Inputs!G:G,,0) -> 72384 | H43: =_xlfn.XLOOKUP($A43,Inputs!$A:$A,Inputs!H:H,,0) -> 64115 | I43: =_xlfn.XLOOKUP($A43,Inputs!$A:$A,Inputs!I:I,,0) -> 61366 | J43: =_xlfn.XLOOKUP($A43,Inputs!$A:$A,Inputs!J:J,,0) -> 44151 | K43: =_xlfn.XLOOKUP($A43,Inputs!$A:$A,Inputs!K:K,,0) -> 42004 | L43: =_xlfn.XLOOKUP($A43,Inputs!$A:$A,Inputs!L:L,,0) -> 42200 | M43: =_xlfn.XLOOKUP($A43,Inputs!$A:$A,Inputs!M:M,,0) -> 32653
A44: Total Assets | B44: =_xlfn.XLOOKUP($A44,Inputs!$A:$A,Inputs!B:B,,0) -> 245705 | C44: =_xlfn.XLOOKUP($A44,Inputs!$A:$A,Inputs!C:C,,0) -> 212206 | D44: =_xlfn.XLOOKUP($A44,Inputs!$A:$A,Inputs!D:D,,0) -> 197289 | E44: =_xlfn.XLOOKUP($A44,Inputs!$A:$A,Inputs!E:E,,0) -> 173889 | F44: =_xlfn.XLOOKUP($A44,Inputs!$A:$A,Inputs!F:F,,0) -> 152221 | G44: =_xlfn.XLOOKUP($A44,Inputs!$A:$A,Inputs!G:G,,0) -> 139058 | H44: =_xlfn.XLOOKUP($A44,Inputs!$A:$A,Inputs!H:H,,0) -> 122810 | I44: =_xlfn.XLOOKUP($A44,Inputs!$A:$A,Inputs!I:I,,0) -> 111254 | J44: =_xlfn.XLOOKUP($A44,Inputs!$A:$A,Inputs!J:J,,0) -> 86382 | K44: =_xlfn.XLOOKUP($A44,Inputs!$A:$A,Inputs!K:K,,0) -> 81882 | L44: =_xlfn.XLOOKUP($A44,Inputs!$A:$A,Inputs!L:L,,0) -> 80885 | M44: =_xlfn.XLOOKUP($A44,Inputs!$A:$A,Inputs!M:M,,0) -> 67889
A47: Liabilities
A48: Current Liabilities | B48: =_xlfn.XLOOKUP($A48,Inputs!$A:$A,Inputs!B:B,,0) -> 89237 | C48: =_xlfn.XLOOKUP($A48,Inputs!$A:$A,Inputs!C:C,,0) -> 78292 | D48: =_xlfn.XLOOKUP($A48,Inputs!$A:$A,Inputs!D:D,,0) -> 72420 | E48: =_xlfn.XLOOKUP($A48,Inputs!$A:$A,Inputs!E:E,,0) -> 61782 | F48: =_xlfn.XLOOKUP($A48,Inputs!$A:$A,Inputs!F:F,,0) -> 53209 | G48: =_xlfn.XLOOKUP($A48,Inputs!$A:$A,Inputs!G:G,,0) -> 50463 | H48: =_xlfn.XLOOKUP($A48,Inputs!$A:$A,Inputs!H:H,,0) -> 49252 | I48: =_xlfn.XLOOKUP($A48,Inputs!$A:$A,Inputs!I:I,,0) -> 42898 | J48: =_xlfn.XLOOKUP($A48,Inputs!$A:$A,Inputs!J:J,,0) -> 30623 | K48: =_xlfn.XLOOKUP($A48,Inputs!$A:$A,Inputs!K:K,,0) -> 27881 | L48: =_xlfn.XLOOKUP($A48,Inputs!$A:$A,Inputs!L:L,,0) -> 27116 | M48: =_xlfn.XLOOKUP($A48,Inputs!$A:$A,Inputs!M:M,,0) -> 23922
A49: Short-Term Debt | B49: =_xlfn.XLOOKUP($A49,Inputs!$A:$A,Inputs!B:B,,0) -> 6185 | C49: =_xlfn.XLOOKUP($A49,Inputs!$A:$A,Inputs!C:C,,0) -> 6191 | D49: =_xlfn.XLOOKUP($A49,Inputs!$A:$A,Inputs!D:D,,0) -> 7661 | E49: =_xlfn.XLOOKUP($A49,Inputs!$A:$A,Inputs!E:E,,0) -> 6492 | F49: =_xlfn.XLOOKUP($A49,Inputs!$A:$A,Inputs!F:F,,0) -> 4369 | G49: =_xlfn.XLOOKUP($A49,Inputs!$A:$A,Inputs!G:G,,0) -> 5126 | H49: =_xlfn.XLOOKUP($A49,Inputs!$A:$A,Inputs!H:H,,0) -> 9161 | I49: =_xlfn.XLOOKUP($A49,Inputs!$A:$A,Inputs!I:I,,0) -> 8776 | J49: =_xlfn.XLOOKUP($A49,Inputs!$A:$A,Inputs!J:J,,0) -> 3371 | K49: =_xlfn.XLOOKUP($A49,Inputs!$A:$A,Inputs!K:K,,0) -> 3569 | L49: =_xlfn.XLOOKUP($A49,Inputs!$A:$A,Inputs!L:L,,0) -> 4218 | M49: =_xlfn.XLOOKUP($A49,Inputs!$A:$A,Inputs!M:M,,0) -> 2207
A50: Short-Term Leases | B50: =_xlfn.XLOOKUP($A50,Inputs!$A:$A,Inputs!B:B,,0) -> 0 | C50: =_xlfn.XLOOKUP($A50,Inputs!$A:$A,Inputs!C:C,,0) -> 0 | D50: =_xlfn.XLOOKUP($A50,Inputs!$A:$A,Inputs!D:D,,0) -> 0 | E50: =_xlfn.XLOOKUP($A50,Inputs!$A:$A,Inputs!E:E,,0) -> 0 | F50: =_xlfn.XLOOKUP($A50,Inputs!$A:$A,Inputs!F:F,,0) -> 0 | G50: =_xlfn.XLOOKUP($A50,Inputs!$A:$A,Inputs!G:G,,0) -> 0 | H50: =_xlfn.XLOOKUP($A50,Inputs!$A:$A,Inputs!H:H,,0) -> 0 | I50: =_xlfn.XLOOKUP($A50,Inputs!$A:$A,Inputs!I:I,,0) -> 0 | J50: =_xlfn.XLOOKUP($A50,Inputs!$A:$A,Inputs!J:J,,0) -> 0 | K50: =_xlfn.XLOOKUP($A50,Inputs!$A:$A,Inputs!K:K,,0) -> 0 | L50: =_xlfn.XLOOKUP($A50,Inputs!$A:$A,Inputs!L:L,,0) -> 0 | M50: =_xlfn.XLOOKUP($A50,Inputs!$A:$A,Inputs!M:M,,0) -> 0
A51: Other current liabilities | B51: =_xlfn.XLOOKUP($A51,Inputs!$A:$A,Inputs!B:B,,0) -> 26281 | C51: =_xlfn.XLOOKUP($A51,Inputs!$A:$A,Inputs!C:C,,0) -> 22975 | D51: =_xlfn.XLOOKUP($A51,Inputs!$A:$A,Inputs!D:D,,0) -> 20392 | E51: =_xlfn.XLOOKUP($A51,Inputs!$A:$A,Inputs!E:E,,0) -> 14595 | F51: =_xlfn.XLOOKUP($A51,Inputs!$A:$A,Inputs!F:F,,0) -> 12244 | G51: =_xlfn.XLOOKUP($A51,Inputs!$A:$A,Inputs!G:G,,0) -> 12286 | H51: =_xlfn.XLOOKUP($A51,Inputs!$A:$A,Inputs!H:H,,0) -> 10339 | I51: =_xlfn.XLOOKUP($A51,Inputs!$A:$A,Inputs!I:I,,0) -> 7798 | J51: =_xlfn.XLOOKUP($A51,Inputs!$A:$A,Inputs!J:J,,0) -> 5965 | K51: =_xlfn.XLOOKUP($A51,Inputs!$A:$A,Inputs!K:K,,0) -> 5279 | L51: =_xlfn.XLOOKUP($A51,Inputs!$A:$A,Inputs!L:L,,0) -> 4910 | M51: =_xlfn.XLOOKUP($A51,Inputs!$A:$A,Inputs!M:M,,0) -> 5063
A52: Non-current Liabilities | B52: =_xlfn.XLOOKUP($A52,Inputs!$A:$A,Inputs!B:B,,0) -> 70121 | C52: =_xlfn.XLOOKUP($A52,Inputs!$A:$A,Inputs!C:C,,0) -> 57435 | D52: =_xlfn.XLOOKUP($A52,Inputs!$A:$A,Inputs!D:D,,0) -> 54330 | E52: =_xlfn.XLOOKUP($A52,Inputs!$A:$A,Inputs!E:E,,0) -> 49945 | F52: =_xlfn.XLOOKUP($A52,Inputs!$A:$A,Inputs!F:F,,0) -> 42785 | G52: =_xlfn.XLOOKUP($A52,Inputs!$A:$A,Inputs!G:G,,0) -> 36573 | H52: =_xlfn.XLOOKUP($A52,Inputs!$A:$A,Inputs!H:H,,0) -> 33369 | I52: =_xlfn.XLOOKUP($A52,Inputs!$A:$A,Inputs!I:I,,0) -> 32895 | J52: =_xlfn.XLOOKUP($A52,Inputs!$A:$A,Inputs!J:J,,0) -> 21917 | K52: =_xlfn.XLOOKUP($A52,Inputs!$A:$A,Inputs!K:K,,0) -> 20677 | L52: =_xlfn.XLOOKUP($A52,Inputs!$A:$A,Inputs!L:L,,0) -> 20470 | M52: =_xlfn.XLOOKUP($A52,Inputs!$A:$A,Inputs!M:M,,0) -> 15675
A53: Long-Term Debt | B53: =_xlfn.XLOOKUP($A53,Inputs!$A:$A,Inputs!B:B,,0) -> 57282 | C53: =_xlfn.XLOOKUP($A53,Inputs!$A:$A,Inputs!C:C,,0) -> 45648 | D53: =_xlfn.XLOOKUP($A53,Inputs!$A:$A,Inputs!D:D,,0) -> 42015 | E53: =_xlfn.XLOOKUP($A53,Inputs!$A:$A,Inputs!E:E,,0) -> 39801 | F53: =_xlfn.XLOOKUP($A53,Inputs!$A:$A,Inputs!F:F,,0) -> 37055 | G53: =_xlfn.XLOOKUP($A53,Inputs!$A:$A,Inputs!G:G,,0) -> 31017 | H53: =_xlfn.XLOOKUP($A53,Inputs!$A:$A,Inputs!H:H,,0) -> 31062 | I53: =_xlfn.XLOOKUP($A53,Inputs!$A:$A,Inputs!I:I,,0) -> 31414 | J53: =_xlfn.XLOOKUP($A53,Inputs!$A:$A,Inputs!J:J,,0) -> 20560 | K53: =_xlfn.XLOOKUP($A53,Inputs!$A:$A,Inputs!K:K,,0) -> 19152 | L53: =_xlfn.XLOOKUP($A53,Inputs!$A:$A,Inputs!L:L,,0) -> 18935 | M53: =_xlfn.XLOOKUP($A53,Inputs!$A:$A,Inputs!M:M,,0) -> 14452
A54: Long-Term Leases | B54: =_xlfn.XLOOKUP($A54,Inputs!$A:$A,Inputs!B:B,,0) -> 0 | C54: =_xlfn.XLOOKUP($A54,Inputs!$A:$A,Inputs!C:C,,0) -> 0 | D54: =_xlfn.XLOOKUP($A54,Inputs!$A:$A,Inputs!D:D,,0) -> 0 | E54: =_xlfn.XLOOKUP($A54,Inputs!$A:$A,Inputs!E:E,,0) -> 0 | F54: =_xlfn.XLOOKUP($A54,Inputs!$A:$A,Inputs!F:F,,0) -> 0 | G54: =_xlfn.XLOOKUP($A54,Inputs!$A:$A,Inputs!G:G,,0) -> 0 | H54: =_xlfn.XLOOKUP($A54,Inputs!$A:$A,Inputs!H:H,,0) -> 0 | I54: =_xlfn.XLOOKUP($A54,Inputs!$A:$A,Inputs!I:I,,0) -> 0 | J54: =_xlfn.XLOOKUP($A54,Inputs!$A:$A,Inputs!J:J,,0) -> 0 | K54: =_xlfn.XLOOKUP($A54,Inputs!$A:$A,Inputs!K:K,,0) -> 0 | L54: =_xlfn.XLOOKUP($A54,Inputs!$A:$A,Inputs!L:L,,0) -> 0 | M54: =_xlfn.XLOOKUP($A54,Inputs!$A:$A,Inputs!M:M,,0) -> 0
A55: Other non-current liabilities | B55: =_xlfn.XLOOKUP($A55,Inputs!$A:$A,Inputs!B:B,,0) -> 12839 | C55: =_xlfn.XLOOKUP($A55,Inputs!$A:$A,Inputs!C:C,,0) -> 11787 | D55: =_xlfn.XLOOKUP($A55,Inputs!$A:$A,Inputs!D:D,,0) -> 12315 | E55: =_xlfn.XLOOKUP($A55,Inputs!$A:$A,Inputs!E:E,,0) -> 10144 | F55: =_xlfn.XLOOKUP($A55,Inputs!$A:$A,Inputs!F:F,,0) -> 5730 | G55: =_xlfn.XLOOKUP($A55,Inputs!$A:$A,Inputs!G:G,,0) -> 5556 | H55: =_xlfn.XLOOKUP($A55,Inputs!$A:$A,Inputs!H:H,,0) -> 2307 | I55: =_xlfn.XLOOKUP($A55,Inputs!$A:$A,Inputs!I:I,,0) -> 1481 | J55: =_xlfn.XLOOKUP($A55,Inputs!$A:$A,Inputs!J:J,,0) -> 1357 | K55: =_xlfn.XLOOKUP($A55,Inputs!$A:$A,Inputs!K:K,,0) -> 1525 | L55: =_xlfn.XLOOKUP($A55,Inputs!$A:$A,Inputs!L:L,,0) -> 1535 | M55: =_xlfn.XLOOKUP($A55,Inputs!$A:$A,Inputs!M:M,,0) -> 1223
A56: Total Liabilities | B56: =_xlfn.XLOOKUP($A56,Inputs!$A:$A,Inputs!B:B,,0) -> 159358 | C56: =_xlfn.XLOOKUP($A56,Inputs!$A:$A,Inputs!C:C,,0) -> 135727 | D56: =_xlfn.XLOOKUP($A56,Inputs!$A:$A,Inputs!D:D,,0) -> 126750 | E56: =_xlfn.XLOOKUP($A56,Inputs!$A:$A,Inputs!E:E,,0) -> 111727 | F56: =_xlfn.XLOOKUP($A56,Inputs!$A:$A,Inputs!F:F,,0) -> 95994 | G56: =_xlfn.XLOOKUP($A56,Inputs!$A:$A,Inputs!G:G,,0) -> 87036 | H56: =_xlfn.XLOOKUP($A56,Inputs!$A:$A,Inputs!H:H,,0) -> 82621 | I56: =_xlfn.XLOOKUP($A56,Inputs!$A:$A,Inputs!I:I,,0) -> 75793 | J56: =_xlfn.XLOOKUP($A56,Inputs!$A:$A,Inputs!J:J,,0) -> 52540 | K56: =_xlfn.XLOOKUP($A56,Inputs!$A:$A,Inputs!K:K,,0) -> 48558 | L56: =_xlfn.XLOOKUP($A56,Inputs!$A:$A,Inputs!L:L,,0) -> 47586 | M56: =_xlfn.XLOOKUP($A56,Inputs!$A:$A,Inputs!M:M,,0) -> 39597
A58: Total Debt | B58: =B49+B53+B50+B54 -> 63467 | C58: =C49+C53+C50+C54 -> 51839 | D58: =D49+D53+D50+D54 -> 49676 | E58: =E49+E53+E50+E54 -> 46293 | F58: =F49+F53+F50+F54 -> 41424 | G58: =G49+G53+G50+G54 -> 36143 | H58: =H49+H53+H50+H54 -> 40223 | I58: =I49+I53+I50+I54 -> 40190 | ... M58: =M49+M53+M50+M54 -> 16659
A59: Debt/Assets | B59: =IFERROR(B58/B44,"-") -> 0.25830569 | C59: =IFERROR(C58/C44,"-") -> 0.24428621 | D59: =IFERROR(D58/D44,"-") -> 0.25179305 | E59: =IFERROR(E58/E44,"-") -> 0.26622156 | F59: =IFERROR(F58/F44,"-") -> 0.27213065 | G59: =IFERROR(G58/G44,"-") -> 0.25991313 | H59: =IFERROR(H58/H44,"-") -> 0.32752219 | I59: =IFERROR(I58/I44,"-") -> 0.36124544 | ... M59: =IFERROR(M58/M44,"-") -> 0.24538585
A60: Net Debt | B60: =B58-B39 -> 35556 | C60: =C58-C39 -> 27932 | D60: =D58-D39 -> 29895 | E60: =E58-E39 -> 32048 | F60: =F58-F39 -> 27100 | G60: =G58-G39 -> 20653 | H60: =H58-H39 -> 26948 | I60: =I58-I39 -> 27279 | ... M60: =M58-M39 -> 4653
A62: Minority Interest | B62: =_xlfn.XLOOKUP($A62,Inputs!$A:$A,Inputs!B:B,,0) -> 8575 | C62: =_xlfn.XLOOKUP($A62,Inputs!$A:$A,Inputs!C:C,,0) -> 4719 | D62: =_xlfn.XLOOKUP($A62,Inputs!$A:$A,Inputs!D:D,,0) -> 5048 | E62: =_xlfn.XLOOKUP($A62,Inputs!$A:$A,Inputs!E:E,,0) -> 4546 | F62: =_xlfn.XLOOKUP($A62,Inputs!$A:$A,Inputs!F:F,,0) -> 4531 | G62: =_xlfn.XLOOKUP($A62,Inputs!$A:$A,Inputs!G:G,,0) -> 4246 | H62: =_xlfn.XLOOKUP($A62,Inputs!$A:$A,Inputs!H:H,,0) -> 1915 | I62: =_xlfn.XLOOKUP($A62,Inputs!$A:$A,Inputs!I:I,,0) -> 1631 | J62: =_xlfn.XLOOKUP($A62,Inputs!$A:$A,Inputs!J:J,,0) -> 1388 | K62: =_xlfn.XLOOKUP($A62,Inputs!$A:$A,Inputs!K:K,,0) -> 1175 | L62: =_xlfn.XLOOKUP($A62,Inputs!$A:$A,Inputs!L:L,,0) -> 2121 | M62: =_xlfn.XLOOKUP($A62,Inputs!$A:$A,Inputs!M:M,,0) -> 0
A64: Shareholder's Equity | B64: =_xlfn.XLOOKUP($A64,Inputs!$A:$A,Inputs!B:B,,0) -> 77772 | C64: =_xlfn.XLOOKUP($A64,Inputs!$A:$A,Inputs!C:C,,0) -> 71760 | D64: =_xlfn.XLOOKUP($A64,Inputs!$A:$A,Inputs!D:D,,0) -> 65491 | E64: =_xlfn.XLOOKUP($A64,Inputs!$A:$A,Inputs!E:E,,0) -> 57616 | F64: =_xlfn.XLOOKUP($A64,Inputs!$A:$A,Inputs!F:F,,0) -> 51696 | G64: =_xlfn.XLOOKUP($A64,Inputs!$A:$A,Inputs!G:G,,0) -> 47776 | H64: =_xlfn.XLOOKUP($A64,Inputs!$A:$A,Inputs!H:H,,0) -> 38274 | I64: =_xlfn.XLOOKUP($A64,Inputs!$A:$A,Inputs!I:I,,0) -> 33830 | J64: =_xlfn.XLOOKUP($A64,Inputs!$A:$A,Inputs!J:J,,0) -> 32454 | K64: =_xlfn.XLOOKUP($A64,Inputs!$A:$A,Inputs!K:K,,0) -> 32149 | L64: =_xlfn.XLOOKUP($A64,Inputs!$A:$A,Inputs!L:L,,0) -> 31178 | M64: =_xlfn.XLOOKUP($A64,Inputs!$A:$A,Inputs!M:M,,0) -> 28292
A66: Cash Flow
A67: Operating CF | B67: =_xlfn.XLOOKUP($A67,Inputs!$A:$A,Inputs!B:B,,0) -> 26206 | C67: =_xlfn.XLOOKUP($A67,Inputs!$A:$A,Inputs!C:C,,0) -> 22343 | D67: =_xlfn.XLOOKUP($A67,Inputs!$A:$A,Inputs!D:D,,0) -> 22174 | E67: =_xlfn.XLOOKUP($A67,Inputs!$A:$A,Inputs!E:E,,0) -> 18463 | F67: =_xlfn.XLOOKUP($A67,Inputs!$A:$A,Inputs!F:F,,0) -> 15713 | G67: =_xlfn.XLOOKUP($A67,Inputs!$A:$A,Inputs!G:G,,0) -> 13596 | H67: =_xlfn.XLOOKUP($A67,Inputs!$A:$A,Inputs!H:H,,0) -> 9795 | I67: =_xlfn.XLOOKUP($A67,Inputs!$A:$A,Inputs!I:I,,0) -> 9740 | J67: =_xlfn.XLOOKUP($A67,Inputs!$A:$A,Inputs!J:J,,0) -> 8051 | K67: =_xlfn.XLOOKUP($A67,Inputs!$A:$A,Inputs!K:K,,0) -> 6991 | L67: =_xlfn.XLOOKUP($A67,Inputs!$A:$A,Inputs!L:L,,0) -> 7155 | M67: =_xlfn.XLOOKUP($A67,Inputs!$A:$A,Inputs!M:M,,0) -> 6968
A68: Investing CF | B68: =_xlfn.XLOOKUP($A68,Inputs!$A:$A,Inputs!B:B,,0) -> -28476 | C68: =_xlfn.XLOOKUP($A68,Inputs!$A:$A,Inputs!C:C,,0) -> -10372 | D68: =_xlfn.XLOOKUP($A68,Inputs!$A:$A,Inputs!D:D,,0) -> -12532 | E68: =_xlfn.XLOOKUP($A68,Inputs!$A:$A,Inputs!E:E,,0) -> -12699 | F68: =_xlfn.XLOOKUP($A68,Inputs!$A:$A,Inputs!F:F,,0) -> -12385 | G68: =_xlfn.XLOOKUP($A68,Inputs!$A:$A,Inputs!G:G,,0) -> -8599 | H68: =_xlfn.XLOOKUP($A68,Inputs!$A:$A,Inputs!H:H,,0) -> -9355 | I68: =_xlfn.XLOOKUP($A68,Inputs!$A:$A,Inputs!I:I,,0) -> -18395 | J68: =_xlfn.XLOOKUP($A68,Inputs!$A:$A,Inputs!J:J,,0) -> -2534 | K68: =_xlfn.XLOOKUP($A68,Inputs!$A:$A,Inputs!K:K,,0) -> -3089 | L68: =_xlfn.XLOOKUP($A68,Inputs!$A:$A,Inputs!L:L,,0) -> -8649 | M68: =_xlfn.XLOOKUP($A68,Inputs!$A:$A,Inputs!M:M,,0) -> -4172
A69: Net Capex | B69: =_xlfn.XLOOKUP($A69,Inputs!$A:$A,Inputs!B:B,,0) -> -2802 | C69: =_xlfn.XLOOKUP($A69,Inputs!$A:$A,Inputs!C:C,,0) -> -2454 | D69: =_xlfn.XLOOKUP($A69,Inputs!$A:$A,Inputs!D:D,,0) -> -2051 | E69: =_xlfn.XLOOKUP($A69,Inputs!$A:$A,Inputs!E:E,,0) -> -2071 | F69: =_xlfn.XLOOKUP($A69,Inputs!$A:$A,Inputs!F:F,,0) -> -2063 | G69: =_xlfn.XLOOKUP($A69,Inputs!$A:$A,Inputs!G:G,,0) -> -2023 | H69: =_xlfn.XLOOKUP($A69,Inputs!$A:$A,Inputs!H:H,,0) -> -1705 | I69: =_xlfn.XLOOKUP($A69,Inputs!$A:$A,Inputs!I:I,,0) -> -1556 | J69: =_xlfn.XLOOKUP($A69,Inputs!$A:$A,Inputs!J:J,,0) -> -1525 | K69: =_xlfn.XLOOKUP($A69,Inputs!$A:$A,Inputs!K:K,,0) -> -1307 | L69: =_xlfn.XLOOKUP($A69,Inputs!$A:$A,Inputs!L:L,,0) -> -1070 | M69: =_xlfn.XLOOKUP($A69,Inputs!$A:$A,Inputs!M:M,,0) -> -1067
A70: Investments & Acquisitions | B70: =_xlfn.XLOOKUP($A70,Inputs!$A:$A,Inputs!B:B,,0) -> -25674 | C70: =_xlfn.XLOOKUP($A70,Inputs!$A:$A,Inputs!C:C,,0) -> -7918 | D70: =_xlfn.XLOOKUP($A70,Inputs!$A:$A,Inputs!D:D,,0) -> -10481 | E70: =_xlfn.XLOOKUP($A70,Inputs!$A:$A,Inputs!E:E,,0) -> -10628 | F70: =_xlfn.XLOOKUP($A70,Inputs!$A:$A,Inputs!F:F,,0) -> -10322 | G70: =_xlfn.XLOOKUP($A70,Inputs!$A:$A,Inputs!G:G,,0) -> -6576 | H70: =_xlfn.XLOOKUP($A70,Inputs!$A:$A,Inputs!H:H,,0) -> -7650 | I70: =_xlfn.XLOOKUP($A70,Inputs!$A:$A,Inputs!I:I,,0) -> -16839 | J70: =_xlfn.XLOOKUP($A70,Inputs!$A:$A,Inputs!J:J,,0) -> -1009 | K70: =_xlfn.XLOOKUP($A70,Inputs!$A:$A,Inputs!K:K,,0) -> -1782 | L70: =_xlfn.XLOOKUP($A70,Inputs!$A:$A,Inputs!L:L,,0) -> -7579 | M70: =_xlfn.XLOOKUP($A70,Inputs!$A:$A,Inputs!M:M,,0) -> -3105
A71: Financing CF | B71: =_xlfn.XLOOKUP($A71,Inputs!$A:$A,Inputs!B:B,,0) -> 4226 | C71: =_xlfn.XLOOKUP($A71,Inputs!$A:$A,Inputs!C:C,,0) -> -7455 | D71: =_xlfn.XLOOKUP($A71,Inputs!$A:$A,Inputs!D:D,,0) -> -3590 | E71: =_xlfn.XLOOKUP($A71,Inputs!$A:$A,Inputs!E:E,,0) -> -5625 | F71: =_xlfn.XLOOKUP($A71,Inputs!$A:$A,Inputs!F:F,,0) -> -4365 | G71: =_xlfn.XLOOKUP($A71,Inputs!$A:$A,Inputs!G:G,,0) -> -3441 | H71: =_xlfn.XLOOKUP($A71,Inputs!$A:$A,Inputs!H:H,,0) -> -1011 | I71: =_xlfn.XLOOKUP($A71,Inputs!$A:$A,Inputs!I:I,,0) -> 12239 | J71: =_xlfn.XLOOKUP($A71,Inputs!$A:$A,Inputs!J:J,,0) -> -5293 | K71: =_xlfn.XLOOKUP($A71,Inputs!$A:$A,Inputs!K:K,,0) -> -4946 | L71: =_xlfn.XLOOKUP($A71,Inputs!$A:$A,Inputs!L:L,,0) -> 471 | M71: =_xlfn.XLOOKUP($A71,Inputs!$A:$A,Inputs!M:M,,0) -> -2490
A72: Dividends | B72: =_xlfn.XLOOKUP($A72,Inputs!$A:$A,Inputs!B:B,,0) -> -5991 | C72: =_xlfn.XLOOKUP($A72,Inputs!$A:$A,Inputs!C:C,,0) -> -5280 | D72: =_xlfn.XLOOKUP($A72,Inputs!$A:$A,Inputs!D:D,,0) -> -4584 | E72: =_xlfn.XLOOKUP($A72,Inputs!$A:$A,Inputs!E:E,,0) -> -3932 | F72: =_xlfn.XLOOKUP($A72,Inputs!$A:$A,Inputs!F:F,,0) -> -3320 | G72: =_xlfn.XLOOKUP($A72,Inputs!$A:$A,Inputs!G:G,,0) -> -2773 | H72: =_xlfn.XLOOKUP($A72,Inputs!$A:$A,Inputs!H:H,,0) -> -2261 | I72: =_xlfn.XLOOKUP($A72,Inputs!$A:$A,Inputs!I:I,,0) -> -1786 | J72: =_xlfn.XLOOKUP($A72,Inputs!$A:$A,Inputs!J:J,,0) -> -1362 | K72: =_xlfn.XLOOKUP($A72,Inputs!$A:$A,Inputs!K:K,,0) -> -1056 | L72: =_xlfn.XLOOKUP($A72,Inputs!$A:$A,Inputs!L:L,,0) -> -820 | M72: =_xlfn.XLOOKUP($A72,Inputs!$A:$A,Inputs!M:M,,0) -> -651
A73: Share buyback | B73: =_xlfn.XLOOKUP($A73,Inputs!$A:$A,Inputs!B:B,,0) -> -5747 | C73: =_xlfn.XLOOKUP($A73,Inputs!$A:$A,Inputs!C:C,,0) -> -3645 | D73: =_xlfn.XLOOKUP($A73,Inputs!$A:$A,Inputs!D:D,,0) -> -2810 | E73: =_xlfn.XLOOKUP($A73,Inputs!$A:$A,Inputs!E:E,,0) -> -4463 | F73: =_xlfn.XLOOKUP($A73,Inputs!$A:$A,Inputs!F:F,,0) -> -3662 | G73: =_xlfn.XLOOKUP($A73,Inputs!$A:$A,Inputs!G:G,,0) -> -812 | H73: =_xlfn.XLOOKUP($A73,Inputs!$A:$A,Inputs!H:H,,0) -> -851 | I73: =_xlfn.XLOOKUP($A73,Inputs!$A:$A,Inputs!I:I,,0) -> -798 | J73: =_xlfn.XLOOKUP($A73,Inputs!$A:$A,Inputs!J:J,,0) -> -3546 | K73: =_xlfn.XLOOKUP($A73,Inputs!$A:$A,Inputs!K:K,,0) -> -2572 | L73: =_xlfn.XLOOKUP($A73,Inputs!$A:$A,Inputs!L:L,,0) -> -2006 | M73: =_xlfn.XLOOKUP($A73,Inputs!$A:$A,Inputs!M:M,,0) -> -2613
A74: FX | B74: =_xlfn.XLOOKUP($A74,Inputs!$A:$A,Inputs!B:B,,0) -> 34 | C74: =_xlfn.XLOOKUP($A74,Inputs!$A:$A,Inputs!C:C,,0) -> -62 | D74: =_xlfn.XLOOKUP($A74,Inputs!$A:$A,Inputs!D:D,,0) -> -116 | E74: =_xlfn.XLOOKUP($A74,Inputs!$A:$A,Inputs!E:E,,0) -> -20 | F74: =_xlfn.XLOOKUP($A74,Inputs!$A:$A,Inputs!F:F,,0) -> -78 | G74: =_xlfn.XLOOKUP($A74,Inputs!$A:$A,Inputs!G:G,,0) -> -5 | H74: =_xlfn.XLOOKUP($A74,Inputs!$A:$A,Inputs!H:H,,0) -> 78 | I74: =_xlfn.XLOOKUP($A74,Inputs!$A:$A,Inputs!I:I,,0) -> -156 | J74: =_xlfn.XLOOKUP($A74,Inputs!$A:$A,Inputs!J:J,,0) -> -5 | K74: =_xlfn.XLOOKUP($A74,Inputs!$A:$A,Inputs!K:K,,0) -> -86 | L74: =_xlfn.XLOOKUP($A74,Inputs!$A:$A,Inputs!L:L,,0) -> 0 | M74: =_xlfn.XLOOKUP($A74,Inputs!$A:$A,Inputs!M:M,,0) -> 0
A75: Changes in cash | B75: =_xlfn.XLOOKUP($A75,Inputs!$A:$A,Inputs!B:B,,0) -> 1990 | C75: =_xlfn.XLOOKUP($A75,Inputs!$A:$A,Inputs!C:C,,0) -> 4454 | D75: =_xlfn.XLOOKUP($A75,Inputs!$A:$A,Inputs!D:D,,0) -> 5936 | E75: =_xlfn.XLOOKUP($A75,Inputs!$A:$A,Inputs!E:E,,0) -> 119 | F75: =_xlfn.XLOOKUP($A75,Inputs!$A:$A,Inputs!F:F,,0) -> -1115 | G75: =_xlfn.XLOOKUP($A75,Inputs!$A:$A,Inputs!G:G,,0) -> 1551 | H75: =_xlfn.XLOOKUP($A75,Inputs!$A:$A,Inputs!H:H,,0) -> -493 | I75: =_xlfn.XLOOKUP($A75,Inputs!$A:$A,Inputs!I:I,,0) -> 3428 | J75: =_xlfn.XLOOKUP($A75,Inputs!$A:$A,Inputs!J:J,,0) -> 219 | K75: =_xlfn.XLOOKUP($A75,Inputs!$A:$A,Inputs!K:K,,0) -> -1130 | L75: =_xlfn.XLOOKUP($A75,Inputs!$A:$A,Inputs!L:L,,0) -> -1023 | M75: =_xlfn.XLOOKUP($A75,Inputs!$A:$A,Inputs!M:M,,0) -> 306
A77: Other Data
A78: Number of employees | B78: 400000 | C78: =_xlfn.XLOOKUP($A78,Inputs!$A:$A,Inputs!C:C,,0) -> #N/A | D78: =_xlfn.XLOOKUP($A78,Inputs!$A:$A,Inputs!D:D,,0) -> #N/A | E78: =_xlfn.XLOOKUP($A78,Inputs!$A:$A,Inputs!E:E,,0) -> #N/A | F78: =_xlfn.XLOOKUP($A78,Inputs!$A:$A,Inputs!F:F,,0) -> #N/A | G78: =_xlfn.XLOOKUP($A78,Inputs!$A:$A,Inputs!G:G,,0) -> #N/A | H78: =_xlfn.XLOOKUP($A78,Inputs!$A:$A,Inputs!H:H,,0) -> #N/A | I78: =_xlfn.XLOOKUP($A78,Inputs!$A:$A,Inputs!I:I,,0) -> #N/A | J78: =_xlfn.XLOOKUP($A78,Inputs!$A:$A,Inputs!J:J,,0) -> #N/A | K78: =_xlfn.XLOOKUP($A78,Inputs!$A:$A,Inputs!K:K,,0) -> #N/A | L78: =_xlfn.XLOOKUP($A78,Inputs!$A:$A,Inputs!L:L,,0) -> #N/A | M78: =_xlfn.XLOOKUP($A78,Inputs!$A:$A,Inputs!M:M,,0) -> #N/A
A79: Shares Outstanding | B79: 924920 | C79: =_xlfn.XLOOKUP($A79,Inputs!$A:$A,Inputs!C:C,,0) -> #N/A | D79: =_xlfn.XLOOKUP($A79,Inputs!$A:$A,Inputs!D:D,,0) -> #N/A | E79: =_xlfn.XLOOKUP($A79,Inputs!$A:$A,Inputs!E:E,,0) -> #N/A | F79: =_xlfn.XLOOKUP($A79,Inputs!$A:$A,Inputs!F:F,,0) -> #N/A | G79: =_xlfn.XLOOKUP($A79,Inputs!$A:$A,Inputs!G:G,,0) -> #N/A | H79: =_xlfn.XLOOKUP($A79,Inputs!$A:$A,Inputs!H:H,,0) -> #N/A | I79: =_xlfn.XLOOKUP($A79,Inputs!$A:$A,Inputs!I:I,,0) -> #N/A | J79: =_xlfn.XLOOKUP($A79,Inputs!$A:$A,Inputs!J:J,,0) -> #N/A | K79: =_xlfn.XLOOKUP($A79,Inputs!$A:$A,Inputs!K:K,,0) -> #N/A | L79: =_xlfn.XLOOKUP($A79,Inputs!$A:$A,Inputs!L:L,,0) -> #N/A | M79: =_xlfn.XLOOKUP($A79,Inputs!$A:$A,Inputs!M:M,,0) -> #N/A
A80: Float | B80: =_xlfn.XLOOKUP($A80,Inputs!$A:$A,Inputs!B:B,,0) -> 0.9962 | C80: =_xlfn.XLOOKUP($A80,Inputs!$A:$A,Inputs!C:C,,0) -> Yahoo finance | D80: =_xlfn.XLOOKUP($A80,Inputs!$A:$A,Inputs!D:D,,0) -> 0 | E80: =_xlfn.XLOOKUP($A80,Inputs!$A:$A,Inputs!E:E,,0) -> 0 | F80: =_xlfn.XLOOKUP($A80,Inputs!$A:$A,Inputs!F:F,,0) -> 0 | G80: =_xlfn.XLOOKUP($A80,Inputs!$A:$A,Inputs!G:G,,0) -> 0 | H80: =_xlfn.XLOOKUP($A80,Inputs!$A:$A,Inputs!H:H,,0) -> 0 | I80: =_xlfn.XLOOKUP($A80,Inputs!$A:$A,Inputs!I:I,,0) -> 0 | J80: =_xlfn.XLOOKUP($A80,Inputs!$A:$A,Inputs!J:J,,0) -> 0 | K80: =_xlfn.XLOOKUP($A80,Inputs!$A:$A,Inputs!K:K,,0) -> 0 | L80: =_xlfn.XLOOKUP($A80,Inputs!$A:$A,Inputs!L:L,,0) -> 0 | M80: =_xlfn.XLOOKUP($A80,Inputs!$A:$A,Inputs!M:M,,0) -> 0
A81: Insiders Own | B81: =_xlfn.XLOOKUP($A81,Inputs!$A:$A,Inputs!B:B,,0) -> 0.0027 | C81: =_xlfn.XLOOKUP($A81,Inputs!$A:$A,Inputs!C:C,,0) -> Yahoo finance | D81: =_xlfn.XLOOKUP($A81,Inputs!$A:$A,Inputs!D:D,,0) -> 0 | E81: =_xlfn.XLOOKUP($A81,Inputs!$A:$A,Inputs!E:E,,0) -> 0 | F81: =_xlfn.XLOOKUP($A81,Inputs!$A:$A,Inputs!F:F,,0) -> 0 | G81: =_xlfn.XLOOKUP($A81,Inputs!$A:$A,Inputs!G:G,,0) -> 0 | H81: =_xlfn.XLOOKUP($A81,Inputs!$A:$A,Inputs!H:H,,0) -> 0 | I81: =_xlfn.XLOOKUP($A81,Inputs!$A:$A,Inputs!I:I,,0) -> 0 | J81: =_xlfn.XLOOKUP($A81,Inputs!$A:$A,Inputs!J:J,,0) -> 0 | K81: =_xlfn.XLOOKUP($A81,Inputs!$A:$A,Inputs!K:K,,0) -> 0 | L81: =_xlfn.XLOOKUP($A81,Inputs!$A:$A,Inputs!L:L,,0) -> 0 | M81: =_xlfn.XLOOKUP($A81,Inputs!$A:$A,Inputs!M:M,,0) -> 0
A82: Fitch/ S&P Rating | B82: =_xlfn.XLOOKUP($A82,Inputs!$A:$A,Inputs!B:B,,0) -> A/A+ | C82: =_xlfn.XLOOKUP($A82,Inputs!$A:$A,Inputs!C:C,,0) -> 10-K | D82: =_xlfn.XLOOKUP($A82,Inputs!$A:$A,Inputs!D:D,,0) -> 0 | E82: =_xlfn.XLOOKUP($A82,Inputs!$A:$A,Inputs!E:E,,0) -> 0 | F82: =_xlfn.XLOOKUP($A82,Inputs!$A:$A,Inputs!F:F,,0) -> 0 | G82: =_xlfn.XLOOKUP($A82,Inputs!$A:$A,Inputs!G:G,,0) -> 0 | H82: =_xlfn.XLOOKUP($A82,Inputs!$A:$A,Inputs!H:H,,0) -> 0 | I82: =_xlfn.XLOOKUP($A82,Inputs!$A:$A,Inputs!I:I,,0) -> 0 | J82: =_xlfn.XLOOKUP($A82,Inputs!$A:$A,Inputs!J:J,,0) -> 0 | K82: =_xlfn.XLOOKUP($A82,Inputs!$A:$A,Inputs!K:K,,0) -> 0 | L82: =_xlfn.XLOOKUP($A82,Inputs!$A:$A,Inputs!L:L,,0) -> 0 | M82: =_xlfn.XLOOKUP($A82,Inputs!$A:$A,Inputs!M:M,,0) -> 0
A83: Dividend Yield | B83: 0.0139 | C83: =_xlfn.XLOOKUP($A83,Inputs!$A:$A,Inputs!C:C,,0) -> #N/A | D83: =_xlfn.XLOOKUP($A83,Inputs!$A:$A,Inputs!D:D,,0) -> #N/A | E83: =_xlfn.XLOOKUP($A83,Inputs!$A:$A,Inputs!E:E,,0) -> #N/A | F83: =_xlfn.XLOOKUP($A83,Inputs!$A:$A,Inputs!F:F,,0) -> #N/A | G83: =_xlfn.XLOOKUP($A83,Inputs!$A:$A,Inputs!G:G,,0) -> #N/A | H83: =_xlfn.XLOOKUP($A83,Inputs!$A:$A,Inputs!H:H,,0) -> #N/A | I83: =_xlfn.XLOOKUP($A83,Inputs!$A:$A,Inputs!I:I,,0) -> #N/A | J83: =_xlfn.XLOOKUP($A83,Inputs!$A:$A,Inputs!J:J,,0) -> #N/A | K83: =_xlfn.XLOOKUP($A83,Inputs!$A:$A,Inputs!K:K,,0) -> #N/A | L83: =_xlfn.XLOOKUP($A83,Inputs!$A:$A,Inputs!L:L,,0) -> #N/A | M83: =_xlfn.XLOOKUP($A83,Inputs!$A:$A,Inputs!M:M,,0) -> #N/A
A84: Daily Volume in Millions of USD | B84: =_xlfn.XLOOKUP($A84,Inputs!$A:$A,Inputs!B:B,,0) -> 3098388 | C84: =_xlfn.XLOOKUP($A84,Inputs!$A:$A,Inputs!C:C,,0) -> Yahoo Finance | D84: =_xlfn.XLOOKUP($A84,Inputs!$A:$A,Inputs!D:D,,0) -> 0 | E84: =_xlfn.XLOOKUP($A84,Inputs!$A:$A,Inputs!E:E,,0) -> 0 | F84: =_xlfn.XLOOKUP($A84,Inputs!$A:$A,Inputs!F:F,,0) -> 0 | G84: =_xlfn.XLOOKUP($A84,Inputs!$A:$A,Inputs!G:G,,0) -> 0 | H84: =_xlfn.XLOOKUP($A84,Inputs!$A:$A,Inputs!H:H,,0) -> 0 | I84: =_xlfn.XLOOKUP($A84,Inputs!$A:$A,Inputs!I:I,,0) -> 0 | J84: =_xlfn.XLOOKUP($A84,Inputs!$A:$A,Inputs!J:J,,0) -> 0 | K84: =_xlfn.XLOOKUP($A84,Inputs!$A:$A,Inputs!K:K,,0) -> 0 | L84: =_xlfn.XLOOKUP($A84,Inputs!$A:$A,Inputs!L:L,,0) -> 0 | M84: =_xlfn.XLOOKUP($A84,Inputs!$A:$A,Inputs!M:M,,0) -> 0
B86: 2020 | C86: 2021 | D86: 2022
A87: Short % of Float | B87: 0.0068 | C87: 0.0057 | D87: 0.0112
A88: EPS | B88: 21.47 | C88: 18.33 | D88: 16.23
A90: Corporate Bonds 3, 5 Y 10 | B90: Average Price | C90: Moody's | D90: YTM | E90: DIVISA
B91: =VLOOKUP($A91,Inputs!$A$5:$M$98,MATCH(B$4,Inputs!$B$5:$M$5,0)+1,FALSE) -> #N/A | C91: =VLOOKUP($A91,Inputs!$A$5:$M$98,MATCH(C$4,Inputs!$B$5:$M$5,0)+1,FALSE) -> #N/A | D91: =VLOOKUP($A91,Inputs!$A$5:$M$98,MATCH(D$4,Inputs!$B$5:$M$5,0)+1,FALSE) -> #N/A | E91: =VLOOKUP($A91,Inputs!$A$5:$M$98,MATCH(E$4,Inputs!$B$5:$M$5,0)+1,FALSE) -> #N/A

Sheet Inputs
G2: Figures in Millions of USD
G3: Company | H3: #VALUE!
D4: Report in millions
A5: RESULTS | B5: 2022 | C5: =B5-1 -> 2021 | D5: =C5-1 -> 2020 | E5: =D5-1 -> 2019 | F5: =E5-1 -> 2018 | G5: =F5-1 -> 2017 | H5: =G5-1 -> 2016 | I5: =H5-1 -> 2015 | J5: =I5-1 -> 2014 | ... M5: =L5-1 -> 2011 | Q5: Hoja | R5: Nombre campo Bloomberg | T5: Cambio de signo | Z5: 2016 | AA5: 2015 | AB5: 2014 | AC5: 2013 | AD5: 2012 | AE5: 2011 | AF5: 2010 | AG5: 2009
A6: Net Sales | B6: 324162 | C6: 287597 | D6: 257141 | E6: 242155 | F6: 226247 | G6: 201159 | H6: 184840 | I6: 157107 | J6: 130474 | K6: 122489 | L6: 110618 | M6: 101862 | N6: Income Statement | O6: Sales | Q6: Ingreso | R6: Ingreso | Z6: 38537 | AA6: 47011 | AB6: 55184 | AC6: 55656 | AD6: 65875 | AE6: 60138 | AF6: 42588 | AG6: 32396
A7: Gross Profit | B7: =B6-33703 -> 290459 | C7: =C6-31034 -> 256563 | D7: 226396 | E7: 214038 | F7: 199249 | G7: 177047 | H7: 160424 | I7: 140901 | J7: 126690 | K7: 119650 | L7: 108095 | M7: 99477 | N7: Income Statement | O7: =+A7 -> Gross Profit | Q7: Ingreso | R7: + Coste de bienes y servicios | Z7: =Z6-28044 -> 10493 | AA7: =AA6-33546 -> 13465 | AB7: =AB6-40718 -> 14466 | AC7: =AC6-40727 -> 14929 | AD7: =+AD6-47055 -> 18820 | AE7: =+AE6-43578 -> 16560 | AF7: =+AF6-30367 -> 12221 | AG7: =+AG6-23886 -> 8510
A8: Operating Income | B8: 28435 | C8: 23970 | D8: 22405 | E8: 19685 | F8: 17344 | G8: 15209 | H8: 12930 | I8: 11021 | J8: 10274 | K8: 9623 | L8: 9254 | M8: 8464 | N8: Income Statement | O8: Operating Income | Q8: Ingreso | R8: + Ventas, generales y admin | Z8: =Z7-4383 -> 6110 | AA8: =AA7-4951 -> 8514 | AB8: =AB7-6529 -> 7937 | AC8: =AC7-5547 -> 9382 | AD8: =AD7-5919-2466-797-580-485 -> 8573 | AE8: =+AE7-5203-2297-826-1081 -> 7153 | AF8: =+AF7-4248-1905-914-1191 -> 3963 | AG8: =+AG7-3645-1421-1045-1822 -> 577
A9: Other Expenses (Revenues) | N9: Income Statement | O9: investment income+other income expense+income loss+minority interest+non controlling interest+share onf net profit+gain8losses) on equity investments+share of result from associates nd joint ventures+non operating profit+ | Q9: Ingreso | R9: + Investigación y desarrollo | S9: + Coste de financiación de beneficio | T9: + Otro gasto operativo | U9: - Beneficio (pérdida) de filiales | V9: - Minoritarios | Z9: =1853+596+595+1904+6+8 -> 4962 | AA9: =2119+587+2023+11 -> 4740 | AB9: =2380+624+1619-8+16 -> 4631 | AC9: =2046+727+981+6+14 -> 3774 | AD9: =-14+41 -> 27 | AE9: 53 | AF9: =58+24 -> 82 | AG9: =12-68 -> -56
A10: Net Financial Cost | B10: -2092 | C10: -1660 | D10: -1663 | E10: -1704 | F10: -1400 | G10: -1186 | H10: -1067 | I10: -790 | J10: -618 | K10: -708 | L10: -632 | M10: -505 | N10: Income Statement | O10: interest expense+financial income and expenses+other financial expense-income+interest and other net+ | Q10: Ingreso | R10: - Ingreso (pérdida) no operacional | Z10: =505+518 -> 1023 | AA10: =507-161 -> 346 | AB10: =484-322 -> 162 | AC10: =465+35 -> 500 | AD10: =467-130 -> 337 | AE10: =396+32 -> 428 | AF10: =343-130 -> 213 | AG10: =389-381 -> 8
A11: Taxes | B11: -5704 | C11: -4578 | D11: -4973 | E11: -3742 | F11: -3562 | G11: -4400 | H11: -4790 | I11: -4363 | J11: -4037 | K11: -3242 | L11: -3096 | M11: -2817 | N11: Income Statement | O11: Taxes | Q11: Ingreso | R11: - Gasto de impuesto a la renta (Beneficio) | Z11: 192 | AA11: 916 | AB11: 692 | AC11: 1319 | AD11: =2528 -> 2528 | AE11: =1720 -> 1720 | AF11: =968 -> 968 | AG11: =-270 -> -270
A12: Net Income | B12: 20639 | C12: 17732 | D12: 15769 | E12: 14239 | F12: 12382 | G12: 9623 | H12: 7073 | I12: 5868 | J12: 5619 | K12: 5673 | L12: 5526 | M12: 5142 | N12: Income Statement | O12: Net Income | Q12: Flujo de caja | R12: + Ingreso neto | Z12: -67 | AA12: 2512 | AB12: 2452 | AC12: 3789 | AD12: 5681 | AE12: =4928+24 -> 4952 | AF12: 2700 | AG12: 895
B13: =SUM(B8:B11) -> 20639 | C13: =SUM(C8:C11) -> 17732 | D13: =SUM(D8:D11) -> 15769 | E13: =SUM(E8:E11) -> 14239 | F13: =SUM(F8:F11) -> 12382 | G13: =SUM(G8:G11) -> 9623 | H13: =SUM(H8:H11) -> 7073 | I13: =SUM(I8:I11) -> 5868 | ... M13: =SUM(M8:M11) -> 5142 | Z13: =Z8-Z10-Z9-Z11 -> -67 | AA13: =AA8-AA10-AA9-AA11 -> 2512 | AB13: =AB8-AB10-AB9-AB11 -> 2452 | AC13: =AC8-AC10-AC9-AC11 -> 3789 | AD13: =AD8-AD10-AD9-AD11 -> 5681 | AE13: =AE8-AE10-AE9-AE11 -> 4952 | AF13: =AF8-AF10-AF9-AF11 -> 2700 | AG13: =AG8-AG10-AG9-AG11 -> 895
A14: FINANCIAL POSITION | B14: =B12-B13 -> 0 | C14: =C12-C13 -> 0 | D14: =D12-D13 -> 0 | E14: =E12-E13 -> 0 | F14: =F12-F13 -> 0 | G14: =G12-G13 -> 0 | H14: =H12-H13 -> 0 | I14: =I12-I13 -> 0 | ... M14: =M12-M13 -> 0 | Z14: =Z12-Z13 -> 0 | AA14: =AA12-AA13 -> 0 | AB14: =AB12-AB13 -> 0 | AC14: =AC12-AC13 -> 0 | AD14: =AD12-AD13 -> 0 | AE14: =AE12-AE13 -> 0 | AF14: =AF12-AF13 -> 0 | AG14: =AG12-AG13 -> 0
A16: Weighted Average Shares (Basic NI) | B16: 937 | C16: 943 | D16: 949 | E16: 951 | F16: 963 | G16: 964 | H16: 952 | I16: 953 | J16: 986 | K16: 1006 | L16: 1027 | M16: 1070
A17: Weighted Average Shares (Diluted NI) | B17: 950 | C17: 956 | D17: 961 | E17: 966 | F17: 983 | G17: 985 | H17: 968 | I17: 967 | J17: 986 | K17: 1023 | L17: 1046 | M17: 1087
A19: Net gains (losses) from ForEx | B19: 192 | C19: -657 | D19: -983 | E19: -271 | F19: -1242 | G19: -70 | H19: 806 | I19: -1775 | J19: -653 | K19: -884 | L19: -63 | M19: 13
A20: Total Comprehensive Income | B20: 17630 | C20: 16162 | D20: 15533 | E20: 14821 | F20: 10865 | G20: 10837 | H20: 7726 | I20: 3926 | J20: 5135 | K20: 4327 | L20: 5503 | M20: 5351
A22: Changes Net Working Capital | B22: =B23-C23 -> -7638 | C22: =C23-D23 -> -1958 | D22: =D23-E23 -> -5090 | E22: =E23-F23 -> -4552 | F22: =F23-G23 -> 28 | G22: =G23-H23 -> -221 | H22: =H23-I23 -> -4468 | I22: =I23-J23 -> -7877 | ... L22: =L23-M23 -> -1923 | N22: cash flows | O22: NWC | Q22: Flujo de caja
A23: Net Working Capital | B23: =B27-B42-B28 -> -48079 | C23: =C27-C42-C28 -> -40441 | D23: =D27-D42-D28 -> -38483 | E23: =E27-E42-E28 -> -33393 | F23: =F27-F42-F28 -> -28841 | G23: =G27-G42-G28 -> -28869 | H23: =H27-H42-H28 -> -28648 | I23: =I27-I42-I28 -> -24180 | ... M23: =M27-M42-M28 -> -15578
A24: 2625 | B24: 2246 | C24: 1522 | D24: 2895 | E24: 683 | F24: 294 | G24: 679 | H24: 183 | I24: 2081 | J24: 1005 | K24: -306 | L24: -178 | M24: 309 | N24: 2625 | Q24: Flujo de caja | R24: + Dividendos pagados | T24: Cambiar signo | Z24: 1799 | AA24: 1757 | AB24: 1620 | AC24: 1111 | AD24: 1617 | AE24: 1159 | AF24: 1084 | AG24: 1029
A25: BALANCE SHEET | B25: 2625 | C25: 2625 | D25: 2625 | E25: 2625 | F25: 2625 | G25: 2625 | H25: 2625 | I25: 2625 | J25: 2625 | K25: 2625 | L25: 2625 | M25: 2625 | N25: 2625 | Q25: Flujo de caja | R25: + Aumento en capital | S25: + Baja en capital | T25: Cambiar signo y hacer suma | Z25: 23 | AA25: =-33+2025 -> 1992 | AB25: 3817 | AC25: 1776 | AD25: -244 | AE25: -312 | AF25: -449 | AG25: -110
A26: ASSETS | N26: 1922 | O26: 2625
A27: Current | B27: 69069 | C27: 61758 | D27: 53718 | E27: 42634 | F27: 38692 | G27: 37084 | H27: 33879 | I27: 31629 | J27: 23556 | K27: 20380 | L27: 21052 | M27: 20350
A28: Cash & Eq. | B28: 27911 | C28: 23907 | D28: 19781 | E28: 14245 | F28: 14324 | G28: 15490 | H28: 13275 | I28: 12911 | J28: 9236 | K28: 9213 | L28: 11437 | M28: 12006 | N28: Balance Sheet | O28: Cash & Eq.
A29: Accounts Receivable | B29: 30450 | C29: 28082 | D29: 25404 | E29: 21462 | F29: 18250 | G29: 15830 | H29: 15651 | I29: 13324 | J29: 9750 | K29: 7050 | L29: 5598 | M29: 4549 | N29: Balance Sheet | O29: Accounts Receivable
A30: Inventory | B30: 3500 | C30: 2900 | N30: Balance Sheet | O30: Inventory | Q30: Balance | R30: + Efectivo, equivalentes y STI | Z30: 7168 | AA30: 6460 | AB30: 7341 | AC30: 6081 | AD30: 5490 | AE30: 3057 | AF30: 3592 | AG30: 4867
A31: Other Current Assets | B31: =B27-SUM(B28:B30) -> 7208 | C31: =C27-SUM(C28:C30) -> 6869 | D31: =D27-SUM(D28:D30) -> 8533 | E31: =E27-SUM(E28:E30) -> 6927 | F31: =F27-SUM(F28:F30) -> 6118 | G31: =G27-SUM(G28:G30) -> 5764 | H31: =H27-SUM(H28:H30) -> 4953 | I31: =I27-SUM(I28:I30) -> 5394 | ... K31: =K27-SUM(K28:K30) -> 4117 | L31: 4017 | M31: 3795 | N31: Balance Sheet | O31: Inventory | Q31: Balance | R31: + Cuentas y notas por cobrar | S31: + Activos derivados y de cobertura | T31: + Inversiones y cuentas por cobrar a LP | Z31: =5981+8522+1029+13556 -> 29088 | AA31: =6695+8991+1170+13651 -> 30507 | AB31: =7737+9027+1364+14644 -> 32772 | AC31: 33499 | AD31: 33911 | AE31: 31031 | AF31: 28849 | AG31: 27162
A32: Non-current | B32: =B38-B27 -> 176636 | C32: =C38-C27 -> 150448 | D32: =D38-D27 -> 143571 | E32: =E38-E27 -> 131255 | F32: =F38-F27 -> 113529 | G32: =G38-G27 -> 101974 | H32: =H38-H27 -> 88931 | I32: =I38-I27 -> 79625 | ... M32: =M38-M27 -> 47539
A33: Property, Plant and Equipment | B33: 10128 | C33: 8969 | D33: 8626 | E33: 8704 | F33: 8458 | G33: 7013 | H33: 5901 | I33: 4861 | J33: 4418 | K33: 4010 | L33: 3939 | M33: 2515 | Q33: Balance | R33: + Inventarios | Z33: 8614 | AA33: 9700 | AB33: 12205 | AC33: 12625 | AD33: 15547 | AE33: 14544 | AF33: 9587 | AG33: 6360
A34: Operating leases
A35: Equity Method Investments | B35: 43728 | C35: 43114 | D35: 41242 | E35: 37209 | F35: 32510 | G35: 28341 | H35: 23868 | I35: 18792 | J35: 18827 | K35: 19605 | L35: 17711 | M35: 16166
A36: Other Non-Current Assets | B36: =B32-SUM(B33:B35) -> 122780 | C36: =C32-SUM(C33:C35) -> 98365 | D36: =D32-SUM(D33:D35) -> 93703 | E36: =E32-SUM(E33:E35) -> 85342 | F36: =F32-SUM(F33:F35) -> 72561 | G36: =G32-SUM(G33:G35) -> 66620 | H36: =H32-SUM(H33:H35) -> 59162 | I36: =I32-SUM(I33:I35) -> 55972 | ... M36: =M32-SUM(M33:M35) -> 28858 | N36: Balance Sheet | O36: Property, Plant and Equipment
A37: Other Assets | B37: =B31+B36 -> 129988 | C37: =C31+C36 -> 105234 | D37: =D31+D36 -> 102236 | E37: =E31+E36 -> 92269 | F37: =F31+F36 -> 78679 | G37: =G31+G36 -> 72384 | H37: =H31+H36 -> 64115 | I37: =I31+I36 -> 61366 | ... M37: =M31+M36 -> 32653 | N37: Balance Sheet
A38: Total Assets | B38: 245705 | C38: 212206 | D38: 197289 | E38: 173889 | F38: 152221 | G38: 139058 | H38: 122810 | I38: 111254 | J38: 86382 | K38: 81882 | L38: 80885 | M38: 67889 | N38: Balance Sheet | O38: Total Assets | Q38: Balance | R38: + Propiedad, planta y equipo; neto | Z38: 15322 | AA38: 16090 | AB38: =16577 -> 16577 | AC38: 17075 | AD38: 16461 | AE38: 14395 | AF38: 12539 | AG38: 12386
N39: Balance Sheet | Z39: =Z40-SUM(Z30:Z38) -> 14512 | AA39: =AA40-SUM(AA30:AA38) -> 15585 | AB39: =AB40-SUM(AB30:AB38) -> 15786 | AC39: =AC40-SUM(AC30:AC38) -> 15616 | AD39: =AD40-SUM(AD30:AD38) -> 17947 | AE39: =AE40-SUM(AE30:AE38) -> 18419 | AF39: =AF40-SUM(AF30:AF38) -> 9453 | AG39: =AG40-SUM(AG30:AG38) -> 9263
N40: Balance Sheet | Q40: Balance | R40: Activos totales | Z40: 74704 | AA40: 78342 | AB40: 84681 | AC40: 84896 | AD40: 89356 | AE40: 81446 | AF40: 64020 | AG40: 60038
A41: LIABILITIES | N41: Balance Sheet
A42: Current Liabilities | B42: 89237 | C42: 78292 | D42: 72420 | E42: 61782 | F42: 53209 | G42: 50463 | H42: 49252 | I42: 42898 | J42: 30623 | K42: 27881 | L42: 27116 | M42: 23922 | N42: Balance Sheet | O42: Current Liabilities
A43: Payables | B43: 56771 | C43: 49126 | D43: 44367 | E43: 40695 | F43: 36596 | G43: 33051 | H43: 29752 | I43: 26324 | J43: 21287 | K43: 19033 | L43: 17988 | M43: 16652
A44: Short-Term Debt | B44: 6185 | C44: 6191 | D44: 7661 | E44: 6492 | F44: 4369 | G44: 5126 | H44: 9161 | I44: 8776 | J44: 3371 | K44: 3569 | L44: 4218 | M44: 2207 | N44: Balance Sheet | O44: Short term Debt | Q44: Balance | R44: Pasivos totales corrientes | Z44: 26132 | AA44: 26242 | AB44: 27877 | AC44: 27297 | AD44: 29415 | AE44: =93+3895+8161+3386+2410+2691+298+1967+558+5102 -> 28561 | AF44: =204+3852+5856+2880+1670+1831+281+1521+495+3430 -> 22020 | AG44: =433+3650+2993+3351+797+1217+262+888+302+5399 -> 19292
A45: Short-Term Leases
A46: Other current liabilities | B46: =B42-SUM(B43:B45) -> 26281 | C46: =C42-SUM(C43:C45) -> 22975 | D46: =D42-SUM(D43:D45) -> 20392 | E46: =E42-SUM(E43:E45) -> 14595 | F46: =F42-SUM(F43:F45) -> 12244 | G46: =G42-SUM(G43:G45) -> 12286 | H46: =H42-SUM(H43:H45) -> 10339 | I46: =I42-SUM(I43:I45) -> 7798 | ... M46: =M42-SUM(M43:M45) -> 5063 | N46: Balance Sheet | R46: + Préstamos CP | Z46: 7303 | AA46: 6967 | AB46: 4708 | AC46: 3679 | AD46: 5287 | AE46: 5660 | AF46: 3925 | AG46: 5701
A47: Non-current Liabilities | B47: =B51-B42 -> 70121 | C47: =C51-C42 -> 57435 | D47: =D51-D42 -> 54330 | E47: =E51-E42 -> 49945 | F47: =F51-F42 -> 42785 | G47: =G51-G42 -> 36573 | H47: =H51-H42 -> 33369 | I47: =I51-I42 -> 32895 | ... M47: =M51-M42 -> 15675 | N47: Balance Sheet | O47: Total non current liabilities
A48: Long-Term Debt | B48: 57282 | C48: 45648 | D48: 42015 | E48: 39801 | F48: 37055 | G48: 31017 | H48: 31062 | I48: 31414 | J48: 20560 | K48: 19152 | L48: 18935 | M48: 14452 | N48: Balance Sheet | O48: Long term debt | Z48: =Z44-Z46 -> 18829 | AA48: =AA44-AA46 -> 19275 | AB48: =AB44-AB46 -> 23169 | AC48: =AC44-AC46 -> 23618 | AD48: =AD44-AD46 -> 24128 | AE48: =AE44-AE46 -> 22901 | AF48: =AF44-AF46 -> 18095 | AG48: =AG44-AG46 -> 13591
A49: Long-Term Leases | Q49: Balance | R49: Pasivos totales no corrientes | Z49: =61491-Z44 -> 35359 | AA49: =63457-AA44 -> 37215 | AB49: =67855-AB44 -> 39978 | AC49: 36721 | AD49: 41973 | AE49: =8415+16529+10956+3583 -> 39483 | AF49: =4505+15932+7584+2654 -> 30675 | AG49: =5652+16195+7420+2179 -> 31446
A50: Other non-current liabilities | B50: =B47-SUM(B48:B49) -> 12839 | C50: =C47-SUM(C48:C49) -> 11787 | D50: =D47-SUM(D48:D49) -> 12315 | E50: =E47-SUM(E48:E49) -> 10144 | F50: =F47-SUM(F48:F49) -> 5730 | G50: =G47-SUM(G48:G49) -> 5556 | H50: =H47-SUM(H48:H49) -> 2307 | I50: =I47-SUM(I48:I49) -> 1481 | ... M50: =M47-SUM(M48:M49) -> 1223 | N50: Balance Sheet | O50: Other non current Liabilities | R50: + Préstamos a largo plazo | Z50: 22818 | AA50: 25169 | AB50: 27784 | AC50: 26719 | AD50: 27752 | AE50: 24944 | AF50: 20437 | AG50: 21847
A51: Total Liabilities | B51: 159358 | C51: 135727 | D51: 126750 | E51: 111727 | F51: 95994 | G51: 87036 | H51: 82621 | I51: 75793 | J51: 52540 | K51: 48558 | L51: 47586 | M51: 39597 | N51: Balance Sheet | O51: Total Liabilities
N52: Balance Sheet | Z52: =Z49-Z50 -> 12541 | AA52: =AA49-AA50 -> 12046 | AB52: =AB49-AB50 -> 12194 | AC52: =AC49-AC50 -> 10002 | AD52: =AD49-AD50 -> 14221 | AE52: =AE49-AE50 -> 14539 | AF52: =AF49-AF50 -> 10238 | AG52: =AG49-AG50 -> 9599
N53: Balance Sheet | Z53: =+Z49+Z44 -> 61491 | AA53: =+AA49+AA44 -> 63457 | AB53: =+AB49+AB44 -> 67855 | AC53: =AC44+AC49 -> 64018 | AD53: =AD49+AD44 -> 71388 | AE53: =AE49+AE44 -> 68044 | AF53: =AF49+AF44 -> 52695 | AG53: =AG49+AG44 -> 50738
A54: Minority Interest | B54: 8575 | C54: 4719 | D54: 5048 | E54: 4546 | F54: 4531 | G54: 4246 | H54: 1915 | I54: 1631 | J54: 1388 | K54: 1175 | L54: 2121 | M54: 0 | N54: Balance Sheet | O54: Minority Interest
N55: Balance Sheet
A56: Shareholder's Equity | B56: =B38-B51-B54 -> 77772 | C56: =C38-C51-C54 -> 71760 | D56: =D38-D51-D54 -> 65491 | E56: =E38-E51-E54 -> 57616 | F56: =F38-F51-F54 -> 51696 | G56: =G38-G51-G54 -> 47776 | H56: =H38-H51-H54 -> 38274 | I56: =I38-I51-I54 -> 33830 | ... M56: =M38-M51-M54 -> 28292 | N56: Balance Sheet | Q56: Balance | R56: + Participación minoritaria/no dominante
A58: CASH FLOW | D58: exp CGAR
A59: Operating CF | B59: 26206 | C59: 22343 | D59: 22174 | E59: 18463 | F59: 15713 | G59: 13596 | H59: 9795 | I59: 9740 | J59: 8051 | K59: 6991 | L59: 7155 | M59: 6968
A60: Net Income | B60: =B12 -> 20639 | C60: =C12 -> 17732 | D60: =D12 -> 15769 | E60: =E12 -> 14239 | F60: =F12 -> 12382 | G60: =G12 -> 9623 | H60: =H12 -> 7073 | I60: =I12 -> 5868 | ... M60: =M12 -> 5142
A61: Depreciation & Amortization | B61: 3400 | C61: 3103 | D61: 2891 | E61: 2720 | F61: 2428 | G61: 2245 | H61: 2055 | I61: 1693 | J61: 1478 | K61: 1375 | L61: 1309 | M61: 1124
A62: Changes in assets and liabilities | B62: 2246 | C62: 1522 | D62: 2895 | E62: 683 | F62: 294 | G62: 679 | H62: 183 | I62: 2081 | J62: 1005 | K62: -306 | L62: -178 | M62: 309
A63: Other Adjustments | B63: =B59-B60-B61-B62 -> -79 | C63: =C59-C60-C61-C62 -> -14 | D63: =D59-D60-D61-D62 -> 619 | E63: =E59-E60-E61-E62 -> 821 | F63: =F59-F60-F61-F62 -> 609 | G63: =G59-G60-G61-G62 -> 1049 | H63: =H59-H60-H61-H62 -> 484 | I63: =I59-I60-I61-I62 -> 98 | ... M63: =M59-M60-M61-M62 -> 393
A64: Investing CF | B64: -28476 | C64: -10372 | D64: -12532 | E64: -12699 | F64: -12385 | G64: -8599 | H64: -9355 | I64: -18395 | J64: -2534 | K64: -3089 | L64: -8649 | M64: -4172
A65: Net Capex | B65: -2802 | C65: -2454 | D65: -2051 | E65: -2071 | F65: -2063 | G65: -2023 | H65: -1705 | I65: -1556 | J65: -1525 | K65: -1307 | L65: -1070 | M65: -1067
A66: Investments & Acquisitions | B66: -25674 | C66: -7918 | D66: -10481 | E66: -10628 | F66: -10322 | G66: -6576 | H66: -7650 | I66: -16839 | J66: -1009 | K66: -1782 | L66: -7579 | M66: -3105
A67: Other Inflows (Outflows) | B67: =B64-B65-B66 -> 0 | C67: =C64-C65-C66 -> 0 | D67: =D64-D65-D66 -> 0 | E67: =E64-E65-E66 -> 0 | F67: =F64-F65-F66 -> 0 | G67: =G64-G65-G66 -> 0 | H67: =H64-H65-H66 -> 0 | I67: =I64-I65-I66 -> 0 | ... M67: =M64-M65-M66 -> 0
A68: Financing CF | B68: 4226 | C68: -7455 | D68: -3590 | E68: -5625 | F68: -4365 | G68: -3441 | H68: -1011 | I68: 12239 | J68: -5293 | K68: -4946 | L68: 471 | M68: -2490
A69: Debt Borrowing | B69: 15551 | C69: 6933 | D69: 5736 | E69: 5744 | F69: 6935 | G69: 5291 | H69: 3968 | I69: 15648 | J69: 1997 | K69: 2235 | L69: 5553 | M69: 2234
A70: Debt Repayment | B70: -3015 | C70: -4452 | D70: -3150 | E70: -1750 | F70: -2801 | G70: -7906 | H70: -2978 | I70: -1041 | J70: -1606 | K70: -2083 | L70: -986 | M70: -1888
A71: Lease Increases
A72: Lease Payments
A73: Dividends | B73: -5991 | C73: -5280 | D73: -4584 | E73: -3932 | F73: -3320 | G73: -2773 | H73: -2261 | I73: -1786 | J73: -1362 | K73: -1056 | L73: -820 | M73: -651 | N73: cash flows FINANCING | O73: Dividends paid
A74: Share buyback | B74: -5747 | C74: -3645 | D74: -2810 | E74: -4463 | F74: -3662 | G74: -812 | H74: -851 | I74: -798 | J74: -3546 | K74: -2572 | L74: -2006 | M74: -2613 | N74: cash flows FINANCING | O74: =+A74 -> Share buyback
A75: Other Inflows (Outflows) | B75: =B68-B69-B70-B71-B72-B73-B74 -> 3428 | C75: =C68-C69-C70-C71-C72-C73-C74 -> -1011 | D75: =D68-D69-D70-D71-D72-D73-D74 -> 1218 | E75: =E68-E69-E70-E71-E72-E73-E74 -> -1224 | F75: =F68-F69-F70-F71-F72-F73-F74 -> -1517 | G75: =G68-G69-G70-G71-G72-G73-G74 -> 2759 | H75: =H68-H69-H70-H71-H72-H73-H74 -> 1111 | I75: =I68-I69-I70-I71-I72-I73-I74 -> 216 | ... M75: =M68-M69-M70-M71-M72-M73-M74 -> 428
A76: FX | B76: 34 | C76: -62 | D76: -116 | E76: -20 | F76: -78 | G76: -5 | H76: 78 | I76: -156 | J76: -5 | K76: -86 | L76: 0 | M76: 0
A77: Changes in cash | B77: =B59+B64+B68+B76 -> 1990 | C77: =C59+C64+C68+C76 -> 4454 | D77: =D59+D64+D68+D76 -> 5936 | E77: =E59+E64+E68+E76 -> 119 | F77: =F59+F64+F68+F76 -> -1115 | G77: =G59+G64+G68+G76 -> 1551 | H77: =H59+H64+H68+H76 -> -493 | I77: =I59+I64+I68+I76 -> 3428 | ... M77: =M59+M64+M68+M76 -> 306
O78: (Vitalis will later fill this info)
A79: Other Data | E79: Corporate Bonds 3, 5 Y 10 | H79: Average Price | J79: Moody's | K79: YTM | L79: DIVISA
A80: Number of employees | B80: 400000 | C80: 10-K | N80: bloomberg
A81: Shares Outstanding (Thousands) | B81: 924920 | C81: Yahoo finance | N81: bloomberg
A82: Float | B82: 0.9962 | C82: Yahoo finance | N82: bloomberg
A83: Insiders Own | B83: 0.0027 | C83: Yahoo finance | N83: bloomberg
A84: Fitch/ S&P Rating | B84: A/A+ | C84: 10-K | N84: bloomberg
A85: Dividend Yield(Yahoo Finance) | B85: 0.0139 | C85: Yahoo finance | N85: bloomberg
A86: Daily Volume in Millions of USD | B86: 3098388 | C86: Yahoo Finance | N86: bloomberg
B87: =B5 -> 2022 | C87: =C5 -> 2021 | D87: =D5 -> 2020
A88: Short % of Float | B88: 0.0068 | C88: 0.0057 | D88: 0.0112 | E88: Yahoo Finance
A89: EPS | B89: 21.47 | C89: 18.33 | D89: 16.23 | E89: Yahoo Finance

Sheet Sector Impact
E2: Sector | F2: Sub-Industry | H2: Low | K2: Sector | L2: Environment | Q2: Social
E3: Communication Services | F3: Interactive Home Entertainment | H3: Medium | L3: CO2 | M3: Water | N3: Energy | O3: Waste | P3: Degradation | Q3: Turnover | R3: Compensation | S3: Reputation | T3: Discrimination | U3: Security | V3: Damage | W3: Pension | X3: Supply | Y3: Community | Z3: Public | AA3: Litigation
E4: Communication Services | F4: Interactive Media & Services | H4: High | K4: Communication Services | L4: Low | M4: Low | N4: Medium | O4: Low | P4: Low | Q4: Medium | R4: Medium | S4: Low | T4: Low | U4: High | V4: Low | W4: Low | X4: Low | Y4: Low | Z4: Low | AA4: Medium
B5: Environmental | E5: Communication Services | F5: Integrated Telecommunication Services | H5: Very High | K5: Consumer Discretionary | L5: Low | M5: Low | N5: Medium | O5: Medium | P5: Low | Q5: Medium | R5: Medium | S5: Low | T5: Low | U5: Medium | V5: Medium | W5: Medium | X5: High | Y5: Low | Z5: High | AA5: Low
B6: Direct CO2 emissions | E6: Communication Services | F6: Cable & Satellite | K6: Consumer Staples | L6: High | M6: Very High | N6: High | O6: High | P6: High | Q6: Medium | R6: High | S6: High | T6: Low | U6: Medium | V6: Medium | W6: Low | X6: High | Y6: Low | Z6: Very High | AA6: Low
B7: Total Water Use | E7: Communication Services | F7: Broadcasting | K7: Energy | L7: Very High | M7: Very High | N7: Medium | O7: Very High | P7: High | Q7: High | R7: Medium | S7: Medium | T7: Medium | U7: Medium | V7: High | W7: Medium | X7: Medium | Y7: High | Z7: High | AA7: Low
K8: Renewable Energy | L8: Low | M8: Low | N8: Low | O8: Medium | P8: Medium | Q8: Low | R8: Medium | S8: Medium | T8: High | U8: Medium | V8: Low | W8: Low | X8: Medium | Y8: Medium | Z8: High | AA8: Low
B9: Total Energy Consumption | E9: Communication Services | F9: Movies & Entertainment | K9: Financials | L9: Low | M9: Low | N9: Low | O9: Low | P9: Low | Q9: Low | R9: Low | S9: Medium | T9: High | U9: Medium | V9: Low | W9: Low | X9: Low | Y9: Low | Z9: Medium | AA9: Low
K10: Forestry | L10: Low | M10: Medium | N10: Low | O10: Medium | P10: High | Q10: Low | R10: Low | S10: Low | T10: Low | U10: Low | V10: Low | W10: Low | X10: Low | Y10: Medium | Z10: Low | AA10: Low
B11: Waste Management | E11: Communication Services | F11: Advertising | K11: Health Care | L11: Low | M11: Medium | N11: Low | O11: Low | P11: Low | Q11: Low | R11: Low | S11: Medium | T11: Low | U11: High | V11: Low | W11: Low | X11: Low | Y11: Low | Z11: Low | AA11: Low
B12: Land Degradation/Deforestation/Biodiversity loss/Animal sufering/... | E12: Communication Services | F12: Alternative Carriers | K12: Industrials | L12: Very High | M12: Very High | N12: Very High | O12: High | P12: High | Q12: Low | R12: Medium | S12: High | T12: Very High | U12: Medium | V12: Very High | W12: Medium | X12: Very High | Y12: Very High | Z12: Very High | AA12: High
B13: Social | E13: Communication Services | F13: Publishing | K13: Information Technology | L13: Medium | M13: Low | N13: High | O13: Low | P13: Low | Q13: Low | R13: Low | S13: Low | T13: Low | U13: High | V13: Low | W13: Low | X13: Low | Y13: Low | Z13: Medium | AA13: Very High
B14: Employee turnover | E14: Communication Services | F14: Wireless Telecommunication Services | K14: Materials | L14: Very High | M14: Very High | N14: Very High | O14: Very High | P14: High | Q14: High | R14: High | S14: Medium | T14: High | U14: Low | V14: Very High | W14: Medium | X14: Medium | Y14: Very High | Z14: High | AA14: Medium
B15: Salaries and compensation | E15: Consumer Discretionary | F15: Automotive Retail | K15: Real Estate | L15: Low | M15: Low | N15: Medium | O15: Low | P15: Low | Q15: Medium | R15: Low | S15: Low | T15: Low | U15: High | V15: Low | W15: Medium | X15: Low | Y15: Medium | Z15: Low | AA15: Low
