Workbook
Name businessresearchinsights: '[1]Segments- LR'!$D$38,'[1]Segments- LR'!$B$38
Name Sectors: '[2]Sector Impact'!$K$4:$K$16
Name Sectors: 'Sector Impact'!$K$4:$K$16

Sheet OP
B2: 45252 | C2: Team 4 | D2: 44949 | E2: =Inputs!H3 -> #VALUE! | L2: NYSE | M2: SIC:
D3: COMPANY DESCRIPTION | H3: CEO & BOARD OF DIRECTORS
D4: {=_FV(Inputs!H3,"Description")} -> Verizon Communications Inc. is a holding company. The Company, through its subsidiaries, provides communications, information and entertainment products and services to consumers, businesses and governmental agencies. Its reportable segments are Verizon Consumer Group and Verizon Business Group. Its Consumer segment provides wireless and wireline communications services. Its wireless services are provided across wireless networks in the United States (U.S.) under the Verizon brands. Its wireline services are provided in nine states in the Mid-Atlantic and Northeastern U.S., as well as Washington D.C., over its fiber-optic network under the Fios brand and over a traditional copper-based network. Its Business segment provides wireless and wireline communications services and products, including data, video and conferencing services, security and managed network services, local and long-distance voice services and network access to deliver various Internet of Things services and products. | H4: Name | I4: Gender | J4: Age | K4: Tenure | L4: Executive? | M4: Other roles
H5: Hans Vestberg | I5: M | J5: 57 | K5: 5 | L5: Yes | M5: Chairman and Chief Executive Officer of verizon Communications Inc.
H6: Clarence Otis, Jr. | I6: M | J6: 67 | K6: 17 | L6: No | M6: Former Chairmanand Chief executive Officer of Darden Restaurents, Inc.
H7: Shellye L. Archambeau | I7: F | J7: 61 | K7: 10 | L7: No | M7: Former Chief Execituve Officer of MetricStream, Inc.
H8: Roxanne S. Austin | I8: F | J8: 61 | K8: 3 | L8: No | M8: President and Chief Executive Officer of Austin Investement Advisors
H9: Mark T. Bertolini | I9: M | J9: 67 | K9: 8 | L9: No | M9: Chief Executive Officer of Oscar Health, Inc.
H10: Vittorio Colao | I10: M | J10: 61 | K10: 1 | L10: No | M10: Former Italian Minister for Innovation, Digital Transition and Space and Former Chief Executive of Vodafine Group Plc
H11: Melanie L. Healey | I11: F | J11: 62 | K11: 12 | L11: No | M11: Former Group President of The Procter & Gamble Company
H12: Laxman Narasimhan | I12: M | J12: 56 | K12: 2 | L12: No | M12: Chief Executive Officer of Starbucks Corporation
H13: Daniel H. Schulman | I13: M | J13: 65 | K13: 5 | L13: No | M13: Presindet and Chied Executive Officer of PayPal Holdings, Inc.
H14: Rodney E. Slater | I14: M | J14: 68 | K14: 13 | L14: No | M14: Partner at Squire Patton Boggs LLP
H15: Carol B. Tomé | I15: F | J15: 66 | K15: 2 | L15: No | M15: Chief Executive officer, United Parcel Service, Inc.
B16: USD MILLIONS | H16: Gregory G. Weaver | I16: M | J16: 70 | K16: 8 | L16: No | M16: Former Chairman and Chief Executive Officer of Delotte & Touche LLP
B17: COMPANY OVERVIEW
B18: Stock | D18: Liquidity and Solvency | F18: Segments | I18: Profitability (2022) | L18: Multiples
B19: Last Price | C19: {=_FV(E2,"Price")} -> 40.335 | D19: Total Assets | E19: =_xlfn.XLOOKUP(D19,'Fin. Data'!A:A,'Fin. Data'!B:B,,0) -> 379680 | F19: Regions | H19: % Sales | I19: Reporting Year | J19: 2022 | L19: Float | M19: =100%-M20 -> 0.9997
B20: Outstanding Shares | C20: {=_FV(E2,"Shares outstanding",TRUE)} -> 4204272000 | D20: Total Liabilities | E20: =_xlfn.XLOOKUP(D20,'Fin. Data'!A:A,'Fin. Data'!B:B,,0) -> 288536 | F20: =Segments!C5 -> United States (U.S.) | H20: =Segments!B5 -> 1 | I20: End of Year | J20: 1 October 2022 | L20: Insiders Own | M20: 0.0003
B21: Market Cap. | C21: =C19*C20/1000000 -> 169579.31 | D21: Cash/Share | E21: =_xlfn.XLOOKUP("Cash & Eq.",'Fin. Data'!A:A,'Fin. Data'!B:B,,0)*1000000/C20 -> 0.61960787 | I21: EBITDA | K21: =_xlfn.XLOOKUP(I21,'Fin. Data'!A:A,'Fin. Data'!B:B,,0) -> 46193 | L21: b (Yahoo) | M21: 0.33
B22: +Total Debt | C22: ='Fin. Data'!B58 -> 150639 | D22: EBIDTA/Net Financial Cost (NFC) | E22: ='Fin. Data (Common Size)'!B19/(-'Fin. Data (Common Size)'!B14) -> 12.942841 | I22: Depreciation & Amortization | K22: =_xlfn.XLOOKUP(I22,'Fin. Data'!A:A,'Fin. Data'!B:B,,0) -> 17099 | L22: Score (S&P) | M22: BBB+
B23: -Cash | C23: ='Fin. Data'!B39 -> 2605 | D23: Debt/EBITDA | E23: =_xlfn.XLOOKUP("Total Debt",'Fin. Data'!A:A,'Fin. Data'!B:B,,0)/_xlfn.XLOOKUP("EBITDA",'Fin. Data'!A:A,'Fin. Data'!B:B,,0) -> 3.2610785 | I23: EBIT | K23: =_xlfn.XLOOKUP(I23,'Fin. Data'!A:A,'Fin. Data'!B:B,,0) -> 29094 | L23: Price/Book Value | M23: =IFERROR((C19*C20/(E19-E20))/1000000,"") -> 1.8605647
B24: =Enterprise Value | C24: =C21+C22-C23 -> 317613.31 | D24: "Others Assets"/Asset | E24: =_xlfn.XLOOKUP("Other Assets",'Fin. Data'!A:A,'Fin. Data'!B:B,,0)/_xlfn.XLOOKUP("Total Assets",'Fin. Data'!A:A,'Fin. Data'!B:B,,0) -> 0.49888327 | I24: Net Income | K24: =_xlfn.XLOOKUP(I24,'Fin. Data'!A:A,'Fin. Data'!B:B,,0) -> 21748 | L24: NCF(3y avg)/Asset | M24: =IFERROR(K30/E19,"") -> 0.055058646
B25: Holdings (nac/int'l) | C25: - | D25: Debt/Assets | E25: =_xlfn.XLOOKUP(D25,'Fin. Data'!A:A,'Fin. Data'!B:B,,0) -> 0.39675253 | F25: Categories | H25: % Sales | I25: EPS | K25: =1000000*K24/C20 -> 5.1728337 | L25: Price/Net Inc. (3y avg) | M25: =IFERROR(C21/K29,"") -> 8.1120313
B26: t liq. (Holdings/Vol.) | C26: - | D26: EBITDA Margin (average) | E26: =AVERAGE(_xlfn.XLOOKUP("EBITDA Margin",'Fin. Data'!A:A,'Fin. Data'!B:D,,0)) -> 0.35291332 | F26: =Segments!C11 -> Verizon Consumer Group | H26: =Segments!B11 -> 0.75499689 | I26: ROA | K26: =K24/E19 -> 0.057279815 | L26: EV/Asset | M26: =IFERROR(C24/E19,"") -> 0.83652895
B27: % Short | C27: 0.0098 | D27: Operating Margin (average) | E27: =AVERAGE(_xlfn.XLOOKUP("Operating Margin",'Fin. Data'!A:A,'Fin. Data'!B:D,,0)) -> 0.22999265 | F27: =Segments!C12 -> Verizon Business Group | H27: =Segments!B12 -> 0.22700333 | I27: ROIC | K27: =K24/(E19-(E20-C22)) -> 0.089948425 | L27: EV/Ebidta (3y average) | M27: =IFERROR(C24/K28,"") -> 6.7751725
B28: Traffic ESG | D28: Net Income Margin (average) | E28: =AVERAGE(_xlfn.XLOOKUP("Net Income Margin",'Fin. Data'!A:A,'Fin. Data'!B:D,,0)) -> 0.15707779 | F28: =Segments!C13 -> Corporate and other | H28: =Segments!B13 -> 0.017999781 | I28: EBITDA (3y average) | K28: =AVERAGE(_xlfn.XLOOKUP("EBITDA",'Fin. Data'!A:A,'Fin. Data'!B:D,,0)) -> 46879 | L28: Price/NCF (3y average) | M28: =IFERROR(C21/K30,"") -> 8.1120313
B29: E | I29: Net Income (3y average) | K29: =AVERAGE(_xlfn.XLOOKUP("Net Income",'Fin. Data'!A:A,'Fin. Data'!B:D,,0)) -> 20904.667 | L29: Bonds 1,3,5a (USD) | M29: -
B30: S | D30: Net Financial Cost/Avg Net Debt | E30: =-_xlfn.XLOOKUP("Net Financial Cost",'Fin. Data'!A:A,'Fin. Data'!B:B,,0)/AVERAGE(_xlfn.XLOOKUP("Net Debt",'Fin. Data'!A:A,'Fin. Data'!B:D,,0)) -> 0.026576679 | I30: NCF (3y average) | K30: =AVERAGE(_xlfn.XLOOKUP("Net Income",'Fin. Data'!A:A,'Fin. Data'!B:D,,0)) -> 20904.667 | L30: Div+Rep.(3y avg)/Price | M30: =-IFERROR(SUM(E51:E53)/(3*C21),"") -> 0.061882549
B31: G | L31: Div. Yield | M31: =IFERROR(L52/C21,"") -> 0.063716499
B32: INVESTMENT THESIS
B33: Pillars of Recommendation | H33: Recommendation | I33: Valuation Assumptions
B34: Pillar | C34: Explanation | H34: BUY | I34: Check DCF
B35: 5G | C35: Verizon has been leading the development of 5G wireless technology industry standards and the ecosystems for fixed and mobile 5G wireless services.
B36: Steady Demand | C36: It's anticipate that demand will continue to increase over time, driven by growth in customer connections and the increased usage of wireless broadband services that use more bandwidth and require faster rates of speed, providing a reliable source of revenue.
B37: Network quality | C37: Their network differentiation will be the cornerstone of their service revenue growth and that will allow the attraction the highest quality customer base in the industry and maintain a market-leading share of the B2B market.
B38: Risks of Investment | H38: Price Target | I38: Valuation
B39: Risk | C39: Explanation | H39: =DCF!D74 -> 46.729073 | I39: Discount Rate | J39: =DCF!F50 -> 0.1041 | L39: Upside | M39: =DCF!D73 -> 0.15852419
B40: Competitive market | C40: Many other companies have strong market presence, brand recognition and existing customer relationships, all of which contribute to intensifying competition that may affect future revenue growth.
B41: Cybersecurity | C41: The inability to operate or use the networks and systems or those of suppliers, vendors and other service providers as a result of cyber attacks, even for a limited period of time, may result in significant expenses to Verizon and/or a loss of marketshare to our competitors.
B42: Regulatory and Political Changes | C42: Data privacy regulations can affect how telecommunications companies collect, store, and use customer data and changes in spectrum allocation policies can affect the availability and cost of spectrum for telecommunications companies, impacting their ability to provide services and innovate.
B43: FINANCIAL PERFORMANCE
B44: Year | C44: Net Sales | D44: Operating Margin | E44: Dividends + Share Buyback | F44: Net Cash Flow | G44: Debt/Assets | H44: Depreciation & Amortization | I44: Capex + Investments | J44: Cash Flow
B45: =B46-1 -> 2014 | C45: {=_xlfn.SORTBY(TRANSPOSE(_xlfn.XLOOKUP(C$44,'Fin. Data'!$A:$A,'Fin. Data'!$B:$J,,0)),$B$45:$B$53,-1)} -> 127079 | D45: {=_xlfn.SORTBY(TRANSPOSE(_xlfn.XLOOKUP(D$44,'Fin. Data'!$A:$A,'Fin. Data'!$B:$J,,0)),$B$45:$B$53,-1)} -> 0.1542269 | E45: {=_xlfn.SORTBY(TRANSPOSE(_xlfn.XLOOKUP(E$44,'Fin. Data'!$A:$A,'Fin. Data'!$B:$J,,0)),$B$45:$B$53,-1)} -> -7803 | F45: =Inputs!J77 -> -42930 | G45: {=_xlfn.SORTBY(TRANSPOSE(_xlfn.XLOOKUP(G$44,'Fin. Data'!$A:$A,'Fin. Data'!$B:$J,,0)),$B$45:$B$53,-1)} -> 0.48694415 | H45: {=_xlfn.SORTBY(TRANSPOSE(_xlfn.XLOOKUP(H$44,'Fin. Data'!$A:$A,'Fin. Data'!$B:$J,,0)),$B$45:$B$53,-1)} -> 16533 | I45: {=_xlfn.SORTBY(TRANSPOSE(_xlfn.XLOOKUP(I$44,'Fin. Data'!$A:$A,'Fin. Data'!$B:$J,,0)),$B$45:$B$53,-1)} -> -17730 | L45: =J19 -> 2022 | M45: =L45-1 -> 2021
B46: =B47-1 -> 2015 | C46: 131620 | D46: 0.25117763 | E46: -13672 | F46: =Inputs!I77 -> -6128 | G46: 0.44938671 | H46: 16017 | I46: -31262 | J46: Net Income | L46: =_xlfn.XLOOKUP($J46,'Fin. Data'!$A:$A,'Fin. Data'!B:B,,0) -> 21748 | M46: =_xlfn.XLOOKUP($J46,'Fin. Data'!$A:$A,'Fin. Data'!C:C,,0) -> 22618 | N46: =(C46/C45)-1 -> 0.035733677 | O46: =(D46/D45)-1 -> 0.62862403
B47: =B48-1 -> 2016 | C47: 125980 | D47: 0.21478806 | E47: -9262 | F47: =Inputs!H77 -> -1561 | G47: 0.4426161 | H47: 15928 | I47: -21358 | J47: Operating CF | L47: =_xlfn.XLOOKUP($J47,'Fin. Data'!$A:$A,'Fin. Data'!B:B,,0) -> 37141 | M47: =_xlfn.XLOOKUP($J47,'Fin. Data'!$A:$A,'Fin. Data'!C:C,,0) -> 39539 | N47: =(C47/C46)-1 -> -0.042850631 | O47: =(D47/D46)-1 -> -0.14487584 | Q47: =F47/F46-1 -> -0.74526762 | R47: =H47/H46-1 -> -0.0055565961 | S47: =I47/I46-1 -> -0.31680635
B48: =B49-1 -> 2017 | C48: 126034 | D48: 0.21760001 | E48: -9472 | F48: =Inputs!G77 -> -289 | G48: 0.45536919 | H48: 16954 | I48: -23710 | J48: Investing CF | L48: =-_xlfn.XLOOKUP($J48,'Fin. Data'!$A:$A,'Fin. Data'!B:B,,0) -> 28662 | M48: =-_xlfn.XLOOKUP($J48,'Fin. Data'!$A:$A,'Fin. Data'!C:C,,0) -> 67153 | N48: =(C48/C47)-1 -> 0.00042863947 | O48: =(D48/D47)-1 -> 0.013091748 | Q48: =F48/F47-1 -> -0.81486227 | R48: =H48/H47-1 -> 0.064414867 | S48: =I48/I47-1 -> 0.11012267
B49: =B50-1 -> 2018 | C49: 130863 | D49: 0.17023911 | E49: -9772 | F49: =Inputs!F77 -> 1028 | G49: 0.42692832 | H49: 17403 | I49: -18317 | J49: Net Capex | L49: =-_xlfn.XLOOKUP($J49,'Fin. Data'!$A:$A,'Fin. Data'!B:B,,0) -> 26740 | M49: =_xlfn.XLOOKUP($J49,'Fin. Data'!$A:$A,'Fin. Data'!C:C,,0) -> -67882 | N49: =(C49/C48)-1 -> 0.038315058 | O49: =(D49/D48)-1 -> -0.21765122 | Q49: =F49/F48-1 -> -4.5570934 | R49: =H49/H48-1 -> 0.026483426 | S49: =I49/I48-1 -> -0.22745677
B50: =B51-1 -> 2019 | C50: 131868 | D50: 0.23036673 | E50: -10016 | F50: =Inputs!E77 -> 1 | G50: 0.38216895 | H50: 16682 | I50: -18866 | J50: Investments & Acquisitions | L50: =-_xlfn.XLOOKUP($J50,'Fin. Data'!$A:$A,'Fin. Data'!B:B,,0) -> -248 | M50: =_xlfn.XLOOKUP($J50,'Fin. Data'!$A:$A,'Fin. Data'!C:C,,0) -> -4065 | N50: =(C50/C49)-1 -> 0.0076797873 | O50: =(D50/D49)-1 -> 0.35319514 | Q50: =F50/F49-1 -> -0.99902724 | R50: =H50/H49-1 -> -0.041429639 | S50: =I50/I49-1 -> 0.029972157
B51: =B52-1 -> 2020 | C51: 128292 | D51: 0.2244723 | E51: -10232 | F51: =Inputs!D77 -> 19581 | G51: 0.40780331 | H51: 16720 | I51: -20838 | J51: Financing CF | L51: =_xlfn.XLOOKUP($J51,'Fin. Data'!$A:$A,'Fin. Data'!B:B,,0) -> -8529 | M51: =_xlfn.XLOOKUP($J51,'Fin. Data'!$A:$A,'Fin. Data'!C:C,,0) -> 8277 | N51: =(C51/C50)-1 -> -0.027118027 | O51: =(D51/D50)-1 -> -0.02558717 | Q51: =F51/F50-1 -> 19580 | R51: =H51/H50-1 -> 0.0022779043 | S51: =I51/I50-1 -> 0.10452666
B52: =B53-1 -> 2021 | C52: 133613 | D52: 0.24285062 | E52: -10445 | F52: =Inputs!C$77 -> -19337 | G52: 0.4115375 | H52: 16206 | I52: -71947 | J52: Dividends | L52: =-_xlfn.XLOOKUP($J52,'Fin. Data'!$A:$A,'Fin. Data'!B:B,,0) -> 10805 | M52: =_xlfn.XLOOKUP($J52,'Fin. Data'!$A:$A,'Fin. Data'!C:C,,0) -> -10445 | N52: =(C52/C51)-1 -> 0.041475696 | O52: =(D52/D51)-1 -> 0.081873458 | Q52: =F52/F51-1 -> -1.9875389 | R52: =H52/H51-1 -> -0.030741627 | S52: =I52/I51-1 -> 2.4526826
B53: =J19 -> 2022 | C53: 136835 | D53: 0.22265502 | E53: -10805 | F53: =Inputs!B77 -> -50 | G53: 0.39675253 | H53: 17099 | I53: -26492 | J53: Share Buyback | L53: =_xlfn.XLOOKUP($J53,'Fin. Data'!$A:$A,'Fin. Data'!B:B,,0) -> 0 | M53: =_xlfn.XLOOKUP($J53,'Fin. Data'!$A:$A,'Fin. Data'!C:C,,0) -> 0 | N53: =(C53/C52)-1 -> 0.02411442 | O53: =(D53/D52)-1 -> -0.083160579 | Q53: =F53/F52-1 -> -0.99741428 | R53: =H53/H52-1 -> 0.055103048 | S53: =I53/I52-1 -> -0.63178451
B54: Annual Growth Rate | C54: =IFERROR((C53/C45)^(1/8)-1,"") -> 0.009288735 | D54: =IFERROR((D53/D45)^(1/8)-1,"") -> 0.046969539 | F54: =IFERROR((F53/F45)^(1/8)-1,"") -> -0.57019037 | H54: =IFERROR((H53/H45)^(1/8)-1,"") -> 0.0042165646 | J54: FX | L54: =_xlfn.XLOOKUP($J54,'Fin. Data'!$A:$A,'Fin. Data'!B:B,,0) -> 0 | M54: =_xlfn.XLOOKUP($J54,'Fin. Data'!$A:$A,'Fin. Data'!C:C,,0) -> 0 | N54: =(C54/C53)-1 -> -0.99999993 | O54: =(D54/D53)-1 -> -0.78904792
B55: Average Growth Rate | C55: =IFERROR(AVERAGE(N46:N53),"") -> 0.0097223275 | D55: =IFERROR(AVERAGE(O46:O53),"") -> 0.075688696 | F55: =IFERROR(AVERAGE(Q46:Q53),"") -> 2795.6998 | H55: =IFERROR(AVERAGE(S46:S53),"") -> 0.21732235 | J55: Changes in Cash | L55: =L47-L48+L51-L52-L53 -> -10855 | M55: =M47-M48+M51-M52-M53 -> -8892
B56: CVAR | C56: =IFERROR(STDEV(C46:C53)/AVERAGE(C46:C53),"") -> 0.028667502 | D56: =IFERROR(STDEV(D45:D53)/AVERAGE(D45:D53),"") -> 0.14912746 | F56: =IFERROR(STDEV(F45:F53)/AVERAGE(F45:F53),"") -> -3.1159201 | H56: =IFERROR(STDEV(H45:H53)/AVERAGE(H45:H53),"") -> 0.030010579 | J56: Inventory/D Revenues | L56: =IFERROR(SUM(I50:I53)/(C53-C49),"") -> -23.131782 | M56: =IFERROR((SUM(I50:I53)-SUM(H50:H53))/(C53-C49),"") -> -34.301741
B57: Last Year | C57: =IFERROR(C53/C52-1,"") -> 0.02411442 | D57: =IFERROR(1-(D53/D52),"") -> 0.083160579 | F57: =IFERROR(1-(F53/F52),"") -> 0.99741428 | H57: =IFERROR(1-(H53/H52),"") -> -0.055103048 | J57: t inversiones; t adq. neto dep. | L57: =IFERROR(L56/E26,"") -> -65.54522 | M57: =IFERROR(M56/E26,"") -> -97.195938
B58: QUALITATIVE ANALYSIS
B59: SWOT ANALYSIS | J59: HOLDERS
B60: Pros | E60: Cons | J60: Name | M60: % Stake
B61: Market Leader; Strong Network Infraestructure; Diverse Service Portfolio; Strong brand Presence (reputation for reliability and quality) | E61: High Operating Costs; Competetive Pricing Pressure; Regulatory Challenges
B71: Opportunities | E71: Risks
B72: 5G Expansion; Diversification; Global expansion | E72: Highly competitive market; Low diversity of supliers; Technological Disruption; Economic Downturn
B81: NOTES | G81: STOCK PERFORMANCE (5 years)
B82: Verizon's mobile network is the largest wireless carrier in the United States, with 143.3 million subscribers as of the end of Q2 2023. Verizon currently owns the 8.5% market share of the entire global telecommunication services industry
G106: =Peers!C8 -> #VALUE! | H106: =Peers!D8 -> #VALUE! | I106: =Peers!E8 -> #VALUE! | J106: =Peers!F8 -> #VALUE! | L106: =Peers!G8 -> #VALUE! | M106: =Peers!H8 -> #VALUE!

Sheet Segments
B2: ="Regions "&"("&OP!$J$19&")" -> Regions (2022) | Q2: Products
D3: Nominal value | K3: YoY Growth | AH3: Consumer Segment
B4: Weight | C4: Region | D4: =OP!J19 -> 2022 | E4: =D4-1 -> 2021 | F4: =E4-1 -> 2020 | G4: =F4-1 -> 2019 | H4: =G4-1 -> 2018 | I4: =H4-1 -> 2017 | K4: =OP!J19 -> 2022 | L4: =K4-1 -> 2021 | M4: =L4-1 -> 2020 | N4: =M4-1 -> 2019 | O4: =N4-1 -> 2018 | P4: =O4-1 -> 2017 | Q4: Verizon Consumer Group
B5: =IFERROR(D5/$D$6,"") -> 1 | C5: United States (U.S.) | D5: 136835 | E5: 133613 | F5: 128292 | G5: 131868 | H5: 130863 | I5: 126034 | K5: =(D5-E5)/E5 -> 0.02411442 | L5: =(E5-F5)/F5 -> 0.041475696 | M5: =(F5-G5)/G5 -> -0.027118027 | N5: =(G5-H5)/H5 -> 0.0076797873 | O5: =(H5-I5)/I5 -> 0.038315058 | Q5: Services | R5: 73139
B6: =SUM(B5:B5) -> 1 | C6: TOTAL | D6: =SUM(D5:D5) -> 136835 | E6: =SUM(E5:E5) -> 133613 | F6: =SUM(F5:F5) -> 128292 | G6: =SUM(G5:G5) -> 131868 | H6: =SUM(H5:H5) -> 130863 | I6: =SUM(I5:I5) -> 126034 | K6: =(D6-E6)/E6 -> 0.02411442 | L6: =(E6-F6)/F6 -> 0.041475696 | M6: =(F6-G6)/G6 -> -0.027118027 | N6: =(G6-H6)/H6 -> 0.0076797873 | O6: =(H6-I6)/I6 -> 0.038315058 | P6: 0.037 | Q6: Wireless equipment | R6: 23168
Q7: Other | R7: 7199
B8: ="Categories "&"("&OP!$J$19&")" -> Categories (2022) | Q8: Total Operating Revenues | R8: 103506
D9: Nominal value | K9: YoY Growth
B10: Weight | C10: Category | D10: =OP!J19 -> 2022 | E10: =D10-1 -> 2021 | F10: =E10-1 -> 2020 | G10: =F10-1 -> 2019 | H10: =G10-1 -> 2018 | I10: =H10-1 -> 2017 | K10: =OP!J19 -> 2022 | L10: =K10-1 -> 2021 | M10: =L10-1 -> 2020 | N10: =M10-1 -> 2019 | O10: =N10-1 -> 2018 | P10: =O10-1 -> 2017 | Q10: Verizon Business Group
B11: =IFERROR(D11/$D$14,"") -> 0.75499689 | C11: Verizon Consumer Group | D11: =103310 -> 103310 | E11: 94999 | F11: 88137 | G11: 90725 | H11: 89510 | K11: =(D11-E11)/E11 -> 0.087485131 | L11: =(E11-F11)/F11 -> 0.077856065 | M11: =(F11-G11)/G11 -> -0.028525765 | N11: =(G11-H11)/H11 -> 0.013573902 | O11: =(H11-I11)/I11 -> #DIV/0!
B12: =IFERROR(D12/$D$14,"") -> 0.22700333 | C12: Verizon Business Group | D12: 31062 | E12: 30998 | F12: 30790 | G12: 31385 | H12: 31407 | K12: =(D12-E12)/E12 -> 0.0020646493 | L12: =(E12-F12)/F12 -> 0.0067554401 | M12: =(F12-G12)/G12 -> -0.018958101 | N12: =(G12-H12)/H12 -> -0.00070048078 | O12: =(H12-I12)/I12 -> #DIV/0! | Q12: Small and Medium Business | R12: 12595
B13: =IFERROR(D13/$D$14,"") -> 0.017999781 | C13: Corporate and other | D13: 2463 | E13: 7616 | F13: 9365 | G13: 9758 | H13: 9946 | K13: =(D13-E13)/E13 -> -0.67660189 | L13: =(E13-F13)/F13 -> -0.18675921 | M13: =(F13-G13)/G13 -> -0.040274646 | N13: =(G13-H13)/H13 -> -0.018902071 | O13: =(H13-I13)/I13 -> #DIV/0! | Q13: Global Enterprise | R13: 9733
B14: =SUM(B11:B13) -> 1 | C14: TOTAL | D14: =SUM(D11:D13) -> 136835 | E14: =SUM(E11:E13) -> 133613 | F14: =SUM(F11:F13) -> 128292 | G14: =SUM(G11:G13) -> 131868 | H14: =SUM(H11:H13) -> 130863 | I14: =SUM(I11:I13) -> 0 | K14: =(D14-E14)/E14 -> 0.02411442 | L14: =(E14-F14)/F14 -> 0.041475696 | M14: =(F14-G14)/G14 -> -0.027118027 | N14: =(G14-H14)/H14 -> 0.0076797873 | O14: =(H14-I14)/I14 -> #DIV/0! | P14: 0.037 | Q14: Public Sector and Other | R14: 6117 | AH14: Business Segment
Q15: Wholesale | R15: 2584
B16: Categories | D16: Description | I16: Graphs | Q16: Total Operating Revenues | R16: 31072
B17: Verizon Consumer Group | D17: Provides consumer-focused wireless and wireline communications services and products.
B18: Verizon Business Group | D18: Provides wireless and wireline communications services and products to businesses, government customers and wireless and wireline carriers across the U.S. and select products and services to customers around the world.
B19: Corporate and other | D19: Primarily includes insurance captives, investments in unconsolidated businesses and development stage businesses.
B21: Industry | J21: Graphs (Industry Forecasts)
B22: Drivers | D22: Description
B23: Consumer Satisfaction | D23: Growth based on delivering what customers want and need in the digital world.
B24: 5G Technology Advancements | D24: Deploying new network architecture and technologies to secure leadership in both fourth-generation (4G) and fifth-generation (5G) wireless networks creates new opportunities in the business market in a cost efficient manner.
B25: Cybersecurity | D25: Regulatory changes in this area are important to the development of tecnology and security and managed network services.
B26: Sales forecast
B27: Source | D27: Market Growth CGAR | G27: Period
B28: Grand View Research | D28: 0.062 | G28: 2023-2030
B29: Statista | D29: 0.0202 | G29: 2023-2028
B30: Analysys Mason | D30: 0.0204 | G30: 2021-2026
B31: Transparency Market Research | D31: 0.05 | G31: 2020-2030
B32: Company's Strategy / Extra Notes
B35: To compete effectively in today’s dynamic marketplace, we are focused on the capabilities of our high-performing networks to drive growth based on delivering what customers want and need in the digital world. In 2022, we focused on maintaining our network leadership, including by rapidly deploying C-Band spectrum; retaining and growing our high-quality customer base while balancing profitability in challenging market conditions; and driving monetization of our networks, platforms and solutions. We are creating business value by earning the trust of our stakeholders, limiting our environmental impact and supporting our customer base growth while creating social benefit through our products and services.

Sheet Acuerdo
A1: Invertir
A2: NO invertir
A3: Mantener sin elevar posición
A4: Mantener (y seguir comprando)
A5: Liquidar
A6: PENDIENTE

Sheet Peers
B1: Peer Logo | C1: Peer Name | D1: Description
C2: =D8 -> #VALUE! | D2: AT&T Inc. is a holding company. The Company is a provider of telecommunications and technology services globally. The Company operates through two segments, namely Communications and Latin America. The Communications segment provides wireless and wireline telecom and broadband services to consumers located in the United States and globally. The business units of the Communication segment include Mobility, Business Wireline, and Consumer Wireline.
C3: =E8 -> #VALUE! | D3: T-Mobile US, Inc. is a provider of mobile communications services, including voice, messaging and data, under its flagship brands, T-Mobile and Metro by T-Mobile, in the United States, Puerto Rico and the United States Virgin Islands. The Company provides mobile communications services primarily using its fourth generation (4G) long term evolution network and its fifth generation (5G) technology network. It also offers a selection of wireless devices, including handsets, tablets and other mobile communication devices, and accessories for sale, as well as financing through equipment installment plans and leasing through JUMP! On Demand.
C4: =F8 -> #VALUE! | D4: Comcast Corporation is a global media and technology company. The Company provides broadband, wireless, and video through Xfinity, Comcast Business, and Sky; produce, distribute, and stream entertainment, sports, and news through brands, including NBC, Telemundo, Universal, Peacock, and Sky; and brings theme parks and attractions to life through Universal Destinations and Experiences. The Company operates through two primary businesses, namely Connectivity & Platforms and Content & Experiences.
C5: =G8 -> #VALUE! | D5: Charter Communications, Inc. is a broadband connectivity company and cable operator serving more than 32 million customers in 41 states through its Spectrum brand. The Company offers a range of residential and business services including Spectrum Internet, television (TV), mobile and voice. The Company also distributes news coverage and sports programming to its customers through Spectrum Networks. Its Spectrum Mobile service is offered to customers subscribing to its Internet service, and runs on Verizon Communications Inc.(Verizon) mobile network, combined with Spectrum WiFi.
C6: =H8 -> #VALUE! | D6: Lumen Technologies, Inc. is an international facilities-based technology and communications company. The Company is engaged primarily in providing a range of integrated services to its business and mass-market customers. It conducts its operations under three brands: Lumen, which is its flagship brand for serving the enterprise and wholesale markets; Quantum Fiber, which provides fiber-based services to residential and small business customers, and CenturyLink, which offers mass-marketed legacy copper-based services. The Company’s segments include Business Segment and Mass Markets Segment.
B8: In Millions USD (exc Market Cap) | C8: #VALUE! | D8: #VALUE! | E8: #VALUE! | F8: #VALUE! | G8: #VALUE! | H8: #VALUE! | I8: AVERAGE | J8: Deviation from Average
B9: Company Info | I9: =IFERROR(AVERAGE(C9:H9),"") | L9: TRAFFIC
B10: Market Cap | C10: =OP!C21 -> 169579.31 | D10: {=_FV(D8,"Capitalização de mercado",TRUE)/1000000} -> 120882.2 | E10: {=_FV(E8,"Capitalização de mercado",TRUE)/1000000} -> 191085.75 | F10: {=_FV(F8,"Capitalização de mercado",TRUE)/1000000} -> 157801.88 | G10: {=_FV(G8,"Capitalização de mercado",TRUE)/1000000} -> 42403.554 | H10: {=_FV(H8,"Capitalização de mercado",TRUE)/1000000} -> 1388.4145 | I10: =IFERROR(AVERAGE(C10:H10),"") -> 113856.85 | J10: =SQRT((C10-I10)^2) -> 55722.46 | M10: Best Value
B11: Net Sales (current) | C11: =C55 -> 136835 | D11: =D55 -> 120741 | E11: =E55 -> 79571 | F11: =F55 -> 121427 | G11: =G55 -> 54022 | H11: =H55 -> 17478 | I11: =IFERROR(AVERAGE(C11:H11),"") -> 88345.667 | J11: =SQRT((C11-I11)^2) -> 48489.333
B12: Profitability | I12: =IFERROR(AVERAGE(C12:H12),"") | M12: Middle Ground
B13: Sales Growth (ttm) | C13: =C55/C54-1 -> 0.02411442 | D13: =D55/D54-1 -> -0.099203211 | E13: =E55/E54-1 -> -0.0068274295 | F13: =F55/F54-1 -> 0.043321734 | G13: =G55/G54-1 -> 0.045276886 | H13: =H55/H54-1 -> -0.11220602 | I13: =IFERROR(AVERAGE(C13:H13),"") -> -0.017587271 | J13: =SQRT((C13-I13)^2) -> 0.041701691
B14: Sales Growth (36m) | C14: =C55/C53-1 -> 0.037666454 | D14: =D55/D53-1 -> -0.3336332 | E14: =E55/E53-1 -> 0.76832304 | F14: =F55/F53-1 -> 0.11460227 | G14: =G55/G53-1 -> 0.12318856 | H14: =H55/H53-1 -> -0.21976697 | I14: =IFERROR(AVERAGE(C14:H14),"") -> 0.081730023 | J14: =SQRT((C14-I14)^2) -> 0.044063569 | M14: Worst Value
B15: Operating Margin | C15: =C58/C55 -> 0.22265502 | D15: =D58/D55 -> 0.18975327 | E15: =E58/E55 -> 0.10188385 | F15: =F58/F55 -> 0.11563326 | G15: =G58/G55 -> 0.22662989 | H15: =H58/H55 -> 0.18840828 | I15: =IFERROR(AVERAGE(C15:H15),"") -> 0.1741606 | J15: =SQRT((C15-I15)^2) -> 0.048494425
B16: Net Income Margin | C16: =C61/C55 -> 0.15893594 | D16: =D61/D55 -> -0.058430856 | E16: =E61/E55 -> 0.032549547 | F16: =F61/F55 -> 0.040559348 | G16: =G61/G55 -> 0.093572989 | H16: =H61/H55 -> -0.088568486 | I16: =IFERROR(AVERAGE(C16:H16),"") -> 0.029769748 | J16: =SQRT((C16-I16)^2) -> 0.1291662
B17: Return on Equity (RoE) | C17: =C61/C72 -> 0.24211522 | D17: =D61/D72 -> -0.066270889 | E17: =E61/E72 -> 0.037182727 | F17: =F61/F72 -> 0.061679691 | G17: =G61/G72 -> 0.40282094 | H17: =H61/H72 -> -0.14831848 | I17: =IFERROR(AVERAGE(C17:H17),"") -> 0.088201535 | J17: =SQRT((C17-I17)^2) -> 0.15391369
B18: Return on Invested Capital (ROIC) | C18: =(C61+C60)/(C71+C72) -> 0.063315091 | D18: =(D61+D60)/(D71+D72) -> -0.012541358 | E18: =(E61+E60)/(E71+E72) -> 0.0096243932 | F18: =(F61+F60)/(F71+F72) -> 0.0030616109 | G18: =(G61+G60)/(G71+G72) -> 0.031314537 | H18: =(H61+H60)/(H71+H72) -> -0.046181523 | I18: =IFERROR(AVERAGE(C18:H18),"") -> 0.0080987919 | J18: =SQRT((C18-I18)^2) -> 0.055216299
B19: Solvency | I19: =IFERROR(AVERAGE(C19:H19),"")
B20: Debt/Assets | C20: =C71/C68 -> 0.39675253 | D20: =D71/D68 -> 0.38395891 | E20: =E71/E68 -> 0.67040475 | F20: =F71/F68 -> 0.40820911 | G20: =G71/G68 -> 0.67371975 | H20: =H71/H68 -> 0.77102301 | I20: =IFERROR(AVERAGE(C20:H20),"") -> 0.55067801 | J20: =SQRT((C20-I20)^2) -> 0.15392548
B21: Net Debt/EBITDA | C21: =(C71-C63)/C57 -> 3.2046847 | D21: =(D71-D63)/D57 -> 7.1774661 | E21: =(E71-E63)/E57 -> 6.803978 | F21: =(F71-F63)/F57 -> 3.4910351 | G21: =(G71-G63)/G57 -> 4.5740566 | H21: =(H71-H63)/H57 -> 9.4673184 | I21: =IFERROR(AVERAGE(C21:H21),"") -> 5.7864231 | J21: =SQRT((C21-I21)^2) -> 2.5817384
B22: Interest Coverage Ratio | C22: =-C57/C59 -> 12.942841 | D22: =-D57/D59 -> -3.4438441 | E22: =-E57/E59 -> 5.9931629 | F22: =-F57/F59 -> 7.3724333 | G22: =-G57/G59 -> 4.6413521 | H22: =-H57/H59 -> 2.6876877 | I22: =IFERROR(AVERAGE(C22:H22),"") -> 5.0322722 | J22: =SQRT((C22-I22)^2) -> 7.910569
B23: Liquidity
B24: Current Ratio | C24: =C66/C70 -> 0.75455941 | D24: =D66/D70 -> 0.58939348 | E24: =E66/E70 -> 0.77063293 | F24: =F66/F70 -> 0.78265859 | G24: =G66/G70 -> 0.33294654 | H24: =H66/H70 -> 1.1284614 | I24: =IFERROR(AVERAGE(C24:H24),"") -> 0.72644205 | J24: =SQRT((C24-I24)^2) -> 0.028117353
B25: Quick Ratio | C25: =(C63+C64)/C70 -> 0.54037193 | D25: =(D63+D64)/D70 -> 0.27000516 | E25: =(E63+E64)/E70 -> 0.36181392 | F25: =(F63+F64)/F70 -> 0.62466382 | G25: =(G63+G64)/G70 -> 0.29556569 | H25: =(H63+H64)/H70 -> 0.56797835 | I25: =IFERROR(AVERAGE(C25:H25),"") -> 0.44339981 | J25: =SQRT((C25-I25)^2) -> 0.096972117
B26: Activity | I26: =IFERROR(AVERAGE(C26:H26),"")
B27: Inventory Turnover | C27: =C56/C65 -> 24.762563 | D27: =D56/D65 -> 34.385207 | E27: =E56/E65 -> 19.217622 | F27: - | G27: - | H27: =H56/H65 -> 46.381356 | I27: =IFERROR(AVERAGE(C27:H27),"") -> 31.186687 | J27: =SQRT((C27-I27)^2) -> 6.424124
B28: Acc. Receivable Turnover | C28: =C55/C64 -> 5.5837346 | D28: =D55/D64 -> 10.530351 | E28: =E55/E64 -> 17.901237 | F28: =F55/F64 -> 9.5830637 | G28: =G55/G64 -> 18.494351 | H28: =H55/H64 -> 11.833446 | I28: =IFERROR(AVERAGE(C28:H28),"") -> 12.321031 | J28: =SQRT((C28-I28)^2) -> 6.737296
A29: Price/Sales | B29: Payables Turnover | C29: =C56/C69 -> 6.7580571 | D29: =D56/D69 -> 2.5181737 | E29: =E56/E69 -> 5.019548 | F29: =F56/F69 -> 6.774713 | G29: =G56/G69 -> 3.1147324 | H29: =H56/H69 -> 11.522105 | I29: =IFERROR(AVERAGE(C29:H29),"") -> 5.9512216 | J29: =SQRT((C29-I29)^2) -> 0.80683556
B30: Fixed Asset Turnover | C30: =C55/C67 -> 1.0244901 | D30: =D55/D67 -> 0.94739692 | E30: =E55/E67 -> 1.8906762 | F30: =F55/F67 -> 2.1884654 | G30: =G55/G67 -> 1.4989872 | H30: =H55/H67 -> 0.91192737 | I30: =IFERROR(AVERAGE(C30:H30),"") -> 1.4103239 | J30: =SQRT((C30-I30)^2) -> 0.38583374 | U30: 1000000
B31: Total Asset Turnover | C31: =C55/C68 -> 0.3603956 | D31: =D55/D68 -> 0.29971478 | E31: =E55/E68 -> 0.37651061 | F31: =F55/F68 -> 0.47197357 | G31: =G55/G68 -> 0.37379517 | H31: =H55/H68 -> 0.38344924 | I31: =IFERROR(AVERAGE(C31:H31),"") -> 0.37763983 | J31: =SQRT((C31-I31)^2) -> 0.017244234
B32: Valuation | I32: =IFERROR(AVERAGE(C32:H32),"")
B33: Price/Earnings | C33: =C10/C61 -> 7.7974669 | D33: =D10/D61 -> -17.134259 | E33: =E10/E61 -> 73.778281 | F33: =F10/F61 -> 32.040991 | G33: =G10/G61 -> 8.3884379 | H33: =H10/H61 -> -0.89690859 | I33: =IFERROR(AVERAGE(C33:H33),"") -> 17.329001 | J33: =SQRT((C33-I33)^2) -> 9.5315345
B34: Price/Sales | C34: =C10/C55 -> 1.2392978 | D34: =D10/D55 -> 1.0011694 | E34: =E10/E55 -> 2.4014496 | F34: =F10/F55 -> 1.2995617 | G34: =G10/G55 -> 0.7849312 | H34: =H10/H55 -> 0.079437836 | I34: =IFERROR(AVERAGE(C34:H34),"") -> 1.1343079 | J34: =SQRT((C34-I34)^2) -> 0.10498984
B35: Price/Book | C35: =C10/C72 -> 1.8878855 | D35: =D10/D72 -> 1.1355026 | E35: =E10/E72 -> 2.7432777 | F35: =F10/F72 -> 1.9762784 | G35: =G10/G72 -> 3.3790385 | H35: =H10/H72 -> 0.13302812 | I35: =IFERROR(AVERAGE(C35:H35),"") -> 1.8758351 | J35: =SQRT((C35-I35)^2) -> 0.012050341
B36: EV/Sales | C36: =(C71+(C10/1000000)-C63)/C55 -> 1.0818443 | D36: =(D71+(D10/1000000)-D63)/D55 -> 1.2504296 | E36: =(E71+(E10/1000000)-E63)/E55 -> 1.7239345 | F36: =(F71+(F10/1000000)-F63)/F55 -> 0.82578963 | G36: =(G71+(G10/1000000)-G63)/G55 -> 1.790438 | H36: =(H71+(H10/1000000)-H63)/H55 -> 1.9391808 | I36: =IFERROR(AVERAGE(C36:H36),"") -> 1.4352695 | J36: =SQRT((C36-I36)^2) -> 0.35342514
B37: EV/EBITDA | C37: =(C71+(C10/1000000)-C63)/C57 -> 3.2046884 | D37: =(D71+(D10/1000000)-D63)/D57 -> 7.1774719 | E37: =(E71+(E10/1000000)-E63)/E57 -> 6.8039875 | F37: =(F71+(F10/1000000)-F63)/F57 -> 3.4910406 | G37: =(G71+(G10/1000000)-G63)/G57 -> 4.5740586 | H37: =(H71+(H10/1000000)-H63)/H57 -> 9.4673188 | I37: =IFERROR(AVERAGE(C37:H37),"") -> 5.7864276 | J37: =SQRT((C37-I37)^2) -> 2.5817392
B38: Stock Info | I38: =IFERROR(AVERAGE(C38:H38),"")
B39: Float | C39: 0.99 | D39: 0.991 | E39: 0.9964 | F39: 0.99 | G39: 0.66 | H39: 0.99 | I39: =IFERROR(AVERAGE(C39:H39),"") -> 0.93623333 | J39: =SQRT((C39-I39)^2) -> 0.053766667
B40: b (Yahoo) | C40: 0.33 | D40: 0.66 | E40: 0.79 | F40: 0.99 | G40: 1.12 | H40: 1.01 | I40: =IFERROR(AVERAGE(C40:H40),"") -> 0.81666667 | J40: =SQRT((C40-I40)^2) -> 0.48666667
B41: Dividend Yield (yahoo finance) | C41: 0.078 | D41: 0.0252 | E41: 0.0197 | F41: 0.02546917 | G41: 0 | H41: 0.1534 | I41: =IFERROR(AVERAGE(C41:H41),"") -> 0.050294862 | J41: =SQRT((C41-I41)^2) -> 0.027705138
B42: Stock Performance
B43: 1y | C43: -0.2063 | D43: -0.1625 | E43: -0.0326 | F43: 0.87176653 | G43: 0.2456 | H43: -0.8084 | I43: =IFERROR(AVERAGE(C43:H43),"") -> -0.015405579 | J43: =SQRT((C43-I43)^2) -> 0.19089442
B44: 3y | C44: -0.4373 | D44: -0.2792 | E44: 0.2842 | F44: 0.79969047 | G44: -0.2637 | H44: -0.8402 | I44: =IFERROR(AVERAGE(C44:H44),"") -> -0.12275159 | J44: =SQRT((C44-I44)^2) -> 0.31454841
B45: Current Price | C45: {=_FV(C8,"Preço")} -> 40.335 | D45: {=_FV(D8,"Preço")} -> 19.97 | E45: {=_FV(E8,"Preço")} -> 161 | F45: {=_FV(F8,"Preço")} -> 39.73 | G45: {=_FV(G8,"Preço")} -> 262.92 | H45: {=_FV(H8,"Preço")} -> 1.375 | I45: =IFERROR(AVERAGE(C45:H45),"") -> 87.555 | J45: =SQRT((C45-I45)^2) -> 47.22
B46: Average Target Price | C46: 40.19 | D46: 18.58 | E46: 177.13 | F46: 48.88 | G46: 478.1 | H46: 2.45 | I46: =IFERROR(AVERAGE(C46:H46),"") -> 127.555 | J46: =SQRT((C46-I46)^2) -> 87.365
B47: Upside/Downside | C47: =C46/C45-1 -> -0.0035948928 | D47: =D46/D45-1 -> -0.069604407 | E47: =E46/E45-1 -> 0.10018634 | F47: =F46/F45-1 -> 0.23030456 | G47: =G46/G45-1 -> 0.81842386 | H47: =H46/H45-1 -> 0.78181818 | I47: =IFERROR(AVERAGE(C47:H47),"") -> 0.30958894 | J47: =SQRT((C47-I47)^2) -> 0.31318383
B48: Extra
B49: 3y Operating Cash Flow | C49: =(Inputs!B59-Inputs!E59)/Inputs!E59 -> 0.039025345 | D49: -0.26 | E49: 1.46 | F49: 0.03 | G49: 0.27 | H49: -0.29 | J49: =SQRT((C49-I49)^2) -> 0.039025345
B51: Financial Data | C51: =OP!E2 -> #VALUE! | D51: =D8 -> #VALUE! | E51: =E8 -> #VALUE! | F51: =F8 -> #VALUE! | G51: #VALUE! | H51: #VALUE!
B52: IS
B53: Net Sales (36m ago) | C53: ='Fin. Data'!E5 -> 131868 | D53: 181193 | E53: 44998 | F53: 108942 | G53: 48097 | H53: 22401
B54: Net Sales (12m ago) | C54: ='Fin. Data'!C5 -> 133613 | D54: 134038 | E54: 80118 | F54: 116385 | G54: 51682 | H54: 19687
B55: Net Sales (current) | C55: ='Fin. Data'!B5 -> 136835 | D55: 120741 | E55: 79571 | F55: 121427 | G55: 54022 | H55: 17478
B56: COGS | C56: ='Fin. Data'!B5-'Fin. Data'!B7 -> 59133 | D56: 107385 | E56: 36206 | F56: 84982 | G56: 32876 | H56: 10946
B57: EBITDA | C57: ='Fin. Data'!B19 -> 46193 | D57: 21035 | E57: 20161 | F57: 28723 | G57: 21146 | H57: 3580
B58: Operating Income | C58: ='Fin. Data'!B11 -> 30467 | D58: 22911 | E58: 8107 | F58: 14041 | G58: 12243 | H58: 3293
B59: Net Financial Cost | C59: ='Fin. Data'!B14 -> -3569 | D59: 6108 | E59: -3364 | F59: -3896 | G59: -4556 | H59: -1332
B60: Taxes | C60: ='Fin. Data'!B21 -> -6523 | D60: 3780 | E60: -556 | F60: -4359 | G60: -1613 | H60: -557
B61: Net Income | C61: ='Fin. Data'!B23 -> 21748 | D61: -7055 | E61: 2590 | F61: 4925 | G61: 5055 | H61: -1548
B62: BS
B63: Cash & Eq. | C63: ='Fin. Data'!B39 -> 2605 | D63: 3701 | E63: 4507 | F63: 4749 | G63: 645 | H63: 1251
B64: Acc. Receivables | C64: ='Fin. Data'!B40 -> 24506 | D64: 11466 | E64: 4445 | F64: 12671 | G64: 2921 | H64: 1477
B65: Inventory | C65: ='Fin. Data'!B41 -> 2388 | D65: 3123 | E65: 1884 | F65: 0 | G65: 0 | H65: 236
B66: Current Assets | C66: =Inputs!B27 -> 37857 | D66: 33108 | E66: 19067 | F66: 21826 | G66: 4017 | H66: 5420
B67: Fixed Assets | C67: ='Fin. Data'!B42 -> 133564 | D67: 127445 | E67: 42086 | F67: 55485 | G67: 36039 | H67: 19166
B68: Total Assets | C68: ='Fin. Data'!B44 -> 379680 | D68: 402853 | E68: 211338 | F68: 257275 | G68: 144523 | H68: 45581
B69: Acc. Payable | C69: =Inputs!B43 -> 8750 | D69: 42644 | E69: 7213 | F69: 12544 | G69: 10555 | H69: 950
B70: Current Liabilities | C70: =Inputs!B42 -> 50171 | D70: 56173 | E70: 24742 | F70: 27887 | G70: 12065 | H70: 4803
B71: Total Debt | C71: ='Fin. Data'!B58 -> 150639 | D71: 154679 | E71: 141682 | F71: 105022 | G71: 97368 | H71: 35144
B72: Total Equity | C72: ='Fin. Data'!B64 -> 89825 | D72: 106457 | E72: 69656 | F72: 79848 | G72: 12549 | H72: 10437

Sheet ESG
B1: Company GICS Sector: | T1: Yes
B2: Communication Services | C2: <- Select Industry | T2: No
B3: ESG Analysis | K3: Relative ESG Analysis
B4: Parameters | C4: Impact | D4: Do they report? | E4: Ranking | F4: Mitigation Plan | G4: Traffic Lights | H4: Improvement over time? | I4: Targets / Goals? | J4: Comments | K4: Parameters | L4: =Peers!C8 -> #VALUE! | M4: =Peers!D8 -> #VALUE! | N4: =Peers!E8 -> #VALUE! | O4: =Peers!F8 -> #VALUE! | P4: =Peers!G8 -> #VALUE! | Q4: =Peers!H8 -> #VALUE!
B5: Environmental | K5: Ratios
A6: 1 | B6: CO2 Direct Emissions | C6: =VLOOKUP($B$2,'Sector Impact'!$K$4:$AA$16,A6+1,FALSE) -> Low | K6: CO2 Emissions/$M Sales | L6: =L12/L$11 -> 0.11157373 | M6: =M12/M$11 -> 0.16867154 | N6: =N12/N$11 -> 0.092170401 | O6: =O12/O$11 -> 0.14856416 | P6: =P12/P$11 -> 0.017211229 | Q6: =Q12/Q$11 -> 0.10190811
A7: 2 | B7: Total Water Consumption | C7: =VLOOKUP($B$2,'Sector Impact'!$K$4:$AA$16,A7+1,FALSE) -> Low | K7: Water Consumption/$M Sales | L7: =L13/L$11 -> 1.4762305e-05 | M7: =M13/M$11 -> 8.4064237e-05 | N7: =N13/N$11 -> 0.013253359 | O7: =O13/O$11 -> 0 | P7: =P13/P$11 -> 0 | Q7: =Q13/Q$11 -> 0.024660736
A8: 3 | B8: Total Energy Consumption | C8: =VLOOKUP($B$2,'Sector Impact'!$K$4:$AA$16,A8+1,FALSE) -> Medium | D8: Yes | E8: "Best in class" | F8: Yes | J8: For the 10th consecutive year, the EPA named Verizon an ENERGY STAR Partner of the Year and was again recognized with a Sustained Excellence designation. | K8: Energy Consumption/$M Sales | L8: =L14/M$11 -> 0.054401984 | M8: =M14/M$11 -> 0.14079724 | N8: =N14/N$11 -> 0.100896 | O8: =O14/O$11 -> 0.18079613 | P8: =P14/P$11 -> 0 | Q8: =Q14/Q$11 -> 0.29882864
A9: 4 | B9: Waste Management | C9: =VLOOKUP($B$2,'Sector Impact'!$K$4:$AA$16,A9+1,FALSE) -> Low | K9: Waste Production/$M Sales | L9: =L15/M$11 -> 0.00035944708 | M9: =M15/M$11 -> 0.0015754632 | N9: =N15/N$11 -> 0.00014578175 | O9: =O15/O$11 -> 0 | P9: =P15/P$11 -> 0.00051493836 | Q9: =Q15/Q$11 -> 0.0022404165
A10: 5 | B10: Land Degradation/Deforestation/Biodiversity loss/Animal sufering/… | C10: =VLOOKUP($B$2,'Sector Impact'!$K$4:$AA$16,A10+1,FALSE) -> Low | K10: Inputs
B11: Social | K11: Net Sales ($M) | L11: =Peers!C55 -> 136835 | M11: =Peers!D55 -> 120741 | N11: =Peers!E55 -> 79571 | O11: =Peers!F55 -> 121427 | P11: =Peers!G55 -> 54022 | Q11: =Peers!H55 -> 17478
A12: 6 | B12: Employee Turnover % | C12: =VLOOKUP($B$2,'Sector Impact'!$K$4:$AA$16,A12+1,FALSE) -> Medium | D12: No | E12: "Best in class" | F12: No | J12: Employee’s turnover sits below 5% | K12: CO2 Emissions Total (Tonnes) | L12: 15267.192 | M12: 20365.571 | N12: 7334.091 | O12: 18039.7 | P12: 929.785 | Q12: 1781.15
A13: 7 | B13: Salaries & Compensation | C13: =VLOOKUP($B$2,'Sector Impact'!$K$4:$AA$16,A13+1,FALSE) -> Medium | D13: Yes | E13: Medium High | F13: No | J13: In 2022, Verizon invested $2.5 billion to provide healthcare benefits and services to approximately 460,000 employees, eligible retirees and their dependents. | K13: Water Consumption Total (Cubic Meters) | L13: 2.02 | M13: 10.15 | N13: 1054.583 | O13: 0 | Q13: 431.02034
A14: 8 | B14: Reputation | C14: =VLOOKUP($B$2,'Sector Impact'!$K$4:$AA$16,A14+1,FALSE) -> Low | K14: Energy Consumption Total (Gigajoules) | L14: 6568.55 | M14: 17000 | N14: 8028.396 | O14: 21953.532 | Q14: 5222.927
A15: 9 | B15: Discrimination Events | C15: =VLOOKUP($B$2,'Sector Impact'!$K$4:$AA$16,A15+1,FALSE) -> Low | F15: Yes | K15: Waste Production Total (Tonnes) | L15: 43.4 | M15: 190.223 | N15: 11.6 | O15: 0 | P15: 27.818 | Q15: 39.158
A16: 10 | B16: Work Safety | C16: =VLOOKUP($B$2,'Sector Impact'!$K$4:$AA$16,A16+1,FALSE) -> High | D16: Yes | E16: "Best in class" | F16: Yes | I16: None | J16: In 2022, occupational injuries and illnesses rate was 1.1 per 100 employees, well below the Bureau of Labor Statistics telecommunications industry average of 1.7 | K16: ESG Scores
A17: 11 | B17: Damage to consumer health | C17: =VLOOKUP($B$2,'Sector Impact'!$K$4:$AA$16,A17+1,FALSE) -> Low | I17: None | K17: Refinitiv | L17: 72/100 | M17: 76/100 | N17: 64/100 | O17: 66/100 | P17: 43/100 | Q17: Not scored
A18: 12 | B18: PXP? | C18: =VLOOKUP($B$2,'Sector Impact'!$K$4:$AA$16,A18+1,FALSE) -> Low | K18: Sustainalytics | L18: 18,6 (Low Risk) | M18: 23,9 (Medium Risk) | N18: 24,7 (Medium Risk) | O18: 23,1 (Medium risk) | P18: 24,2 (Medium Risk) | Q18: 26,1 (Medium Risk)
A19: 13 | B19: Supply chain | C19: Medium | D19: Yes | E19: Medium High | F19: Yes | I19: supplier diversity for over 15 years | K19: ISS
A20: 14 | B20: Community involvement | C20: =VLOOKUP($B$2,'Sector Impact'!$K$4:$AA$16,A20+1,FALSE) -> Low | K20: CDP | L20: B | M20: A | N20: A- | O20: B | P20: Not Scored | Q20: B
A21: 15 | B21: Public Sector | C21: =VLOOKUP($B$2,'Sector Impact'!$K$4:$AA$16,A21+1,FALSE) -> Low | I21: None
A22: 16 | B22: Litigation | C22: =VLOOKUP($B$2,'Sector Impact'!$K$4:$AA$16,A22+1,FALSE) -> Medium | D22: Yes | E22: Medium | F22: Yes | H22: None | I22: None | J22: Verizon is involved in various litigation and regulatory proceedings at the state and federal level but they don't believe that any pending legal proceedings to which they're subject are required to be disclosed as material legal proceedings in the report.
B23: Corporate Governance | K23: PARAMETERS
A24: 17 | B24: Diversity (Gender, Age, Industry, Region) | E24: Medium High | F24: Yes | I24: None | J24: As of December 31, 2022, the 12-member Board included four women and five Directors who self-identify as racially or ethnically diverse. | K24: IMPACT | L24: RANKING | M24: MITIGATION PLAN | O24: TRAFFIC
A25: 18 | B25: % Independence | E25: Medium High | F25: No | I25: None | J25: 91.67% of board members are independent. | K25: Low | L25: "Best in class" | M25: Is there evidence of a plan/program ?
A26: 19 | B26: average time as independent directors | E26: "Best in class" | F26: No | I26: None | J26: 6.98 Yrs average board tenure. | K26: Medium | L26: Medium High
A27: 20 | B27: Recent departures of directors / C-level executives? | E27: Medium High | F27: No | I27: None | J27: Mr. Colao was elected to the Board in November 2022 as an independent Director. | K27: High | L27: Medium
A28: 21 | B28: CEO/Chairman duality | E28: "Villain" | F28: No | I28: None | J28: Hans Vestberg is the CEO and Chairman since 2019. | K28: Very high | L28: "Villain"
A29: 22 | B29: Transparency (ESG, segments, acquisitions, other) | E29: "Best in class" | F29: No | I29: None | J29: The information of the board about their public profile is available and accurately disclosed.
A30: 23 | B30: Time taken to report after the end of the quarter / year | E30: Medium High | F30: No | I30: None | J30: 1Q was released on 27/04/2023 and the Annual Report was released on 10/02/2023.
A31: 24 | B31: Additional participation of the CEO in other boards or excessive participation of Ch. | E31: Medium High | F31: No | I31: None | J31: None
A32: 25 | B32: Audit / Consulting | D32: Yes | E32: Medium High | F32: No | I32: None | J32: The company hasn't paid for any extra services.
A33: 26 | B33: ESG-compensation related | D33: Yes | E33: Medium High | F33: No | I33: None | J33: For over 20 years, our short-term incentive program has included an ESG metric.
A34: 27 | B34: Management compensation schemes | D34: Yes | E34: "Best in class" | F34: No | I34: None | J34: Directors and executive officers have interests in other stock-based units under Verizon deferred compensation plans and stock-based long-term incentive awards. There is alignment with shareholders' interests and the same incentives to drive the company's success.

Sheet DCF
A1: VALUATION MODEL
G3: Short Term | K3: Long Term
A4: Section | B4: Line # | C4: ITEM | D4: 2020 (Real) | E4: 2021 (Real) | F4: 2022 (Real) | G4: 2023 | H4: =G4+1 -> 2024 | I4: =H4+1 -> 2025 | J4: =I4+1 -> 2026 | K4: =J4+1 -> 2027 | L4: =K4+1 -> 2028 | M4: =L4+1 -> 2029 | N4: =M4+1 -> 2030 | O4: =N4+1 -> 2031 | ... AF4: =AE4+1 -> 2048
A5: INCOME STATEMENT | B5: 1 | C5: Growth | D5: ='Fin. Data'!D6 -> -0.027118027 | E5: =+E6/D6-1 -> 0.041475696 | F5: =+F6/E6-1 -> 0.02411442 | G5: 0.03 | H5: =+G5+($K$5-$G$5)/4 -> 0.025 | I5: =+H5+($K$5-$G$5)/4 -> 0.02 | J5: =+I5+($K$5-$G$5)/4 -> 0.015 | K5: =+Assumptions!$M$6 -> 0.01 | L5: =+Assumptions!$M$6 -> 0.01 | M5: =+Assumptions!$M$6 -> 0.01 | N5: =+Assumptions!$M$6 -> 0.01 | O5: =+Assumptions!$M$6 -> 0.01 | P5: =+Assumptions!$M$6 -> 0.01 | Q5: =+Assumptions!$M$6 -> 0.01 | R5: =+Assumptions!$M$6 -> 0.01 | ... AF5: =+Assumptions!$M$6 -> 0.01
B6: 2 | C6: Revenues/Sales | D6: 128292 | E6: 133613 | F6: 136835 | G6: =F6*(1+G5) -> 140940.05 | H6: =G6*(1+H5) -> 144463.55 | I6: =H6*(1+I5) -> 147352.82 | J6: =I6*(1+J5) -> 149563.11 | K6: =J6*(1+K5) -> 151058.75 | L6: =K6*(1+L5) -> 152569.33 | M6: =L6*(1+M5) -> 154095.03 | N6: =M6*(1+N5) -> 155635.98 | ... AF6: =AE6*(1+AF5) -> 186163.58
B7: 3 | C7: EBIT/Operating Margin | D7: =D8/D6 -> 0.2244723 | E7: =E8/E6 -> 0.24285062 | F7: =F8/F6 -> 0.22265502 | G7: 0.23 | H7: =$G$7 -> 0.23 | I7: =$G$7 -> 0.23 | J7: =$G$7 -> 0.23 | K7: 0.22 | L7: =$K$7 -> 0.22 | M7: =$K$7 -> 0.22 | N7: =$K$7 -> 0.22 | O7: =$K$7 -> 0.22 | P7: =$K$7 -> 0.22 | Q7: =$K$7 -> 0.22 | R7: =$K$7 -> 0.22 | S7: =$K$7 -> 0.22 | ... AE7: =$K$7 -> 0.22 | AF7: 0.22
B8: 4 | C8: EBIT | D8: ='Fin. Data'!D11 -> 28798 | E8: ='Fin. Data'!C11 -> 32448 | F8: ='Fin. Data'!B11 -> 30467 | G8: =G7*G6 -> 32416.212 | H8: =H7*H6 -> 33226.617 | I8: =I7*I6 -> 33891.149 | J8: =J7*J6 -> 34399.516 | K8: =K7*K6 -> 33232.924 | L8: =L7*L6 -> 33565.253 | M8: =M7*M6 -> 33900.906 | N8: =N7*N6 -> 34239.915 | ... AF8: =AF7*AF6 -> 40955.988
B9: 5a | C9: (Dep) | D9: -14275 | E9: -14119 | F9: -14592 | G9: =$D$53*DCF!F40 -> -15092.975 | H9: =$D$53*DCF!G40 -> -15975.924 | I9: =$D$53*DCF!H40 -> -16968.009 | J9: =$D$53*DCF!I40 -> -17979.937 | K9: =$E$53*DCF!J40 -> -17436.696 | L9: =$E$53*DCF!K40 -> -18252.413 | M9: =$E$53*DCF!L40 -> -19076.287 | N9: =$E$53*DCF!M40 -> -19908.401 | O9: =$E$53*DCF!N40 -> -20748.835 | P9: =$E$53*DCF!O40 -> -21597.673 | Q9: =$E$53*DCF!P40 -> -22455 | R9: =$E$53*DCF!Q40 -> -23320.901 | ... AF9: =$E$53*DCF!AE40 -> -36393.307 | AG9: =SUM(D9:AF9) -> -694221.68
B10: 5b | C10: Amort | D10: -2445 | E10: -2087 | F10: -2507 | G10: =F38*$D$54 -> -2444.96 | H10: =G38*$D$54 -> -2640.5568 | I10: =H38*$D$54 -> -2851.8013 | J10: =I38*$D$54 -> -3079.9455 | K10: =J38*$E$54 -> -2910.5485 | L10: =K38*$E$54 -> -3114.2868 | M10: =L38*$E$54 -> -3332.2869 | N10: =M38*$E$54 -> -3565.547 | O10: =N38*$E$54 -> -3815.1353 | P10: =O38*$E$54 -> -4082.1948 | Q10: =P38*$E$54 -> -4367.9484 | R10: =Q38*$E$54 -> -4673.7048 | ... AF10: =AE38*$E$54 -> -12051.307
B11: 5c | C11: (Stock based compensation) | D11: -780 | E11: -625 | F11: -609 | G11: =G6*$D$55 -> -714.48076 | H11: =H6*$D$55 -> -732.34278 | I11: =I6*$D$55 -> -746.98964 | J11: =J6*$D$55 -> -758.19448 | K11: =K6*$D$55 -> -765.77643 | L11: =L6*$D$55 -> -773.43419 | M11: =M6*$D$55 -> -781.16853 | N11: =N6*$D$55 -> -788.98022 | ... AF11: =AF6*$D$55 -> -943.7367
B12: 6 | C12: EBIDTA | D12: =D8-D9-D10 -> 45518 | E12: =E8-E9-E10 -> 48654 | F12: =F8-F9-F10 -> 47566 | G12: =G8-G9-G10 -> 49954.147 | H12: =H8-H9-H10 -> 51843.097 | I12: =I8-I9-I10 -> 53710.96 | J12: =J8-J9-J10 -> 55459.399 | K12: =K8-K9-K10 -> 53580.168 | ... AF12: =AF8-AF9-AF10 -> 89400.602
B13: 7 | C13: (Net financing cost) | D13: ='Fin. Data'!D14 -> -4247 | E13: ='Fin. Data'!C14 -> -3340 | F13: ='Fin. Data'!B14 -> -3569 | G13: =F43*$D$58-F44*$D$57 -> -8913.06 | H13: =G43*$D$58-G44*$D$57 -> -8869.6826 | I13: =H43*$D$58-H44*$D$57 -> -8870.5033 | J13: =I43*$D$58-I44*$D$57 -> -8896.6603 | K13: =J43*$E$58-J44*$E$57 -> -5251.5397 | L13: =K43*$E$58-K44*$E$57 -> -5134.5037 | M13: =L43*$E$58-L44*$E$57 -> -5142.547 | N13: =M43*$E$58-M44*$E$57 -> -5131.6922 | O13: =N43*$E$58-N44*$E$57 -> -4759.0034 | P13: =O43*$E$58-O44*$E$57 -> -4705.962 | Q13: =P43*$E$58-P44*$E$57 -> -4361.8887 | R13: =Q43*$E$58-Q44*$E$57 -> -4264.9652 | ... AF13: =AE43*$E$58-AE44*$E$57 -> -600.14201
B14: 8 | C14: Other income/(cost) | D14: ='Fin. Data'!D15 -> -584 | E14: ='Fin. Data'!C15 -> 312 | F14: ='Fin. Data'!B15 -> 1373 | G14: =AVERAGE(D14:F14)*(1+G5) -> 378.01 | H14: =AVERAGE(E14:G14)*(1+H5) -> 704.86175 | I14: =AVERAGE(F14:H14)*(1+I5) -> 834.9964 | J14: =AVERAGE(G14:I14)*(1+J5) -> 648.87872 | K14: =AVERAGE(H14:J14)*(1+K5) -> 736.87475 | L14: =AVERAGE(I14:K14)*(1+L5) -> 747.65245 | M14: =AVERAGE(J14:L14)*(1+M5) -> 718.24666 | N14: =AVERAGE(K14:M14)*(1+N5) -> 741.60053 | ... AF14: =AVERAGE(AC14:AE14)*(1+AF5) -> 806.39601
B15: 9 | C15: Earnings before taxes | D15: =D8+D13+D14 -> 23967 | E15: =E8+E13+E14 -> 29420 | F15: =F8+F13+F14 -> 28271 | G15: =G8+G13+G14 -> 23881.162 | H15: =H8+H13+H14 -> 25061.796 | I15: =I8+I13+I14 -> 25855.642 | J15: =J8+J13+J14 -> 26151.735 | K15: =K8+K13+K14 -> 28718.259 | ... AF15: =AF8+AF13+AF14 -> 41162.242
B16: 10 | C16: (Income tax) | D16: ='Fin. Data'!D21 -> -5619 | E16: ='Fin. Data'!C21 -> -6802 | F16: ='Fin. Data'!B21 -> -6523 | G16: =-(1*24%)*G15 -> -5731.4788 | H16: =-(1*$D$56)*H15 -> -5817.5259 | I16: =-(1*$D$56)*I15 -> -6001.7993 | J16: =-(1*$D$56)*J15 -> -6070.5304 | K16: =-(1*$E$56)*K15 -> -7753.93 | L16: =-(1*$E$56)*L15 -> -7878.1686 | M16: =-(1*$E$56)*M15 -> -7958.6835 | N16: =-(1*$E$56)*N15 -> -8059.4523 | O16: =-(1*$E$56)*O15 -> -8252.9556 | P16: =-(1*$E$56)*P15 -> -8360.2435 | Q16: =-(1*$E$56)*Q15 -> -8549.5803 | R16: =-(1*$E$56)*R15 -> -8671.7242 | ... AF16: =-(1*$E$56)*AF15 -> -11113.805
B17: 11 | C17: Net income | D17: =Inputs!D12 -> 18348 | E17: =Inputs!C12 -> 22618 | F17: =Inputs!B12 -> 21748 | G17: =G16+G15 -> 18149.683 | H17: =H16+H15 -> 19244.27 | I17: =I16+I15 -> 19853.843 | J17: =J16+J15 -> 20081.204 | K17: =K16+K15 -> 20964.329 | L17: =L16+L15 -> 21300.234 | M17: =M16+M15 -> 21517.922 | N17: =N16+N15 -> 21790.371 | ... AF17: =AF16+AF15 -> 30048.436
A19: CASH FLOW STATEMENT | B19: 12 | C19: Operating cash flows before WK | D19: =+D22-D20-D21 -> 39712 | E19: =+E22-E20-E21 -> 41147 | F19: =+F22-F20-F21 -> 41984 | G19: =G17-G10-G9-G11 -> 36402.099 | H19: =H17-H10-H9-H11 -> 38593.093 | I19: =I17-I10-I9-I11 -> 40420.643 | J19: =J17-J10-J9-J11 -> 41899.281 | K19: =K17-K10-K9-K11 -> 42077.35 | L19: =L17-L10-L9-L11 -> 43440.368 | M19: =M17-M10-M9-M11 -> 44707.665 | N19: =N17-N10-N9-N11 -> 46053.299 | ... AF19: =AF17-AF10-AF9-AF11 -> 79436.787
B20: 13 | C20: (Stock-based compensation) | D20: -780 | E20: -625 | F20: -609 | G20: =G11 -> -714.48076 | H20: =H11 -> -732.34278 | I20: =I11 -> -746.98964 | J20: =J11 -> -758.19448 | K20: =K11 -> -765.77643 | L20: =L11 -> -773.43419 | M20: =M11 -> -781.16853 | N20: =N11 -> -788.98022 | ... AF20: =AF11 -> -943.7367
B21: 14 | C21: (Working Capital Flows) | D21: =Inputs!D62 -> 2836 | E21: =Inputs!C62 -> -983 | F21: =Inputs!B62 -> -4234 | G21: =$D$60*(G6-F6) -> -5282.3709 | H21: =$D$60*(H6-G6) -> -4534.035 | I21: =$D$60*(I6-H6) -> -3717.9087 | J21: =$D$60*(J6-I6) -> -2844.2002 | K21: =$E$60*(K6-J6) -> -1924.5754 | L21: =$E$60*(L6-K6) -> -1943.8212 | M21: =$E$60*(M6-L6) -> -1963.2594 | N21: =$E$60*(N6-M6) -> -1982.892 | O21: =$E$60*(O6-N6) -> -2002.7209 | P21: =$E$60*(P6-O6) -> -2022.7481 | Q21: =$E$60*(Q6-P6) -> -2042.9756 | R21: =$E$60*(R6-Q6) -> -2063.4054 | ... AF21: =$E$60*(AF6-AE6) -> -2371.8313
B22: 15 | C22: -Total Operating Cash Flow | D22: 41768 | E22: 39539 | F22: 37141 | G22: =G19+G20+G21 -> 30405.247 | H22: =H19+H20+H21 -> 33326.716 | I22: =I19+I20+I21 -> 35955.745 | J22: =J19+J20+J21 -> 38296.887 | K22: =K19+K20+K21 -> 39386.998 | L22: =L19+L20+L21 -> 40723.112 | M22: =M19+M20+M21 -> 41963.237 | N22: =N19+N20+N21 -> 43281.427 | ... AF22: =AF19+AF20+AF21 -> 76121.219
B23: 16 | C23: (CAPEX) | D23: ='Fin. Data'!D32 -> -20318 | E23: ='Fin. Data'!C32 -> -67882 | F23: ='Fin. Data'!B32 -> -26740 | G23: -18000 | H23: =H6*$D$62 -> -20224.897 | I23: =I6*$D$62 -> -20629.395 | J23: =J6*$D$62 -> -20938.836 | K23: =K6*$E$62 -> -18127.049 | L23: =L6*$E$62 -> -18308.32 | M23: =M6*$E$62 -> -18491.403 | N23: =N6*$E$62 -> -18676.317 | O23: =O6*$E$62 -> -18863.08 | P23: =P6*$E$62 -> -19051.711 | Q23: =Q6*$E$62 -> -19242.228 | R23: =R6*$E$62 -> -19434.651 | ... AF23: =AF6*$E$62 -> -22339.63 | AG23: =SUM(D23:AF23) -> -638330.78
B24: 17 | C24: Adq | D24: =Inputs!D66 -> -520 | E24: ='Fin. Data'!C33 -> -4065 | F24: ='Fin. Data'!B33 -> 248 | G24: =G6*$D$63 -> -976.48955 | H24: =H6*$D$63 -> -1000.9018 | I24: =I6*$D$63 -> -1020.9198 | J24: =J6*$D$63 -> -1036.2336 | K24: =K6*$E$63 -> -1046.596 | L24: =L6*$E$63 -> -1057.0619 | M24: =M6*$E$63 -> -1067.6325 | N24: =N6*$E$63 -> -1078.3089 | O24: =O6*$E$63 -> -1089.092 | P24: =P6*$E$63 -> -1099.9829 | Q24: =Q6*$E$63 -> -1110.9827 | R24: =R6*$E$63 -> -1122.0925 | ... AF24: =AF6*$E$63 -> -1289.8164 | AH24: =AG9-AG23 -> -55890.9
B25: 18 | C25: (Other investing flows) | D25: =Inputs!D67 -> -2674 | E25: =Inputs!C67 -> 4794 | F25: =Inputs!B67 -> -2170 | G25: =(1+G5)*AVERAGE(Inputs!B67:M67) -> 2216.8175 | H25: =(1+H5)*AVERAGE(E25:G25) -> 1653.946 | I25: =(1+I5)*AVERAGE(F25:H25) -> 578.25958 | J25: =(1+J5)*AVERAGE(G25:I25) -> 1505.2528 | K25: =(1+K5)*AVERAGE(H25:J25) -> 1258.2776 | L25: =(1+L5)*AVERAGE(I25:K25) -> 1125.0693 | M25: =(1+M5)*AVERAGE(J25:L25) -> 1309.1619 | N25: =(1+N5)*AVERAGE(K25:M25) -> 1243.1447 | O25: =(1+O5)*AVERAGE(L25:N25) -> 1238.0499 | ... AF25: =(1+AF5)*AVERAGE(AC25:AE25) -> 1366.7305
B26: 19 | C26: -Total Investing Flows | D26: =D23+D24+D25 -> -23512 | E26: =E23+E24+E25 -> -67153 | F26: =F23+F24+F25 -> -28662 | G26: =G23+G24+G25 -> -16759.672 | H26: =H23+H24+H25 -> -19571.853 | I26: =I23+I24+I25 -> -21072.055 | J26: =J23+J24+J25 -> -20469.817 | K26: =K23+K24+K25 -> -17915.368 | ... AF26: =AF23+AF24+AF25 -> -22262.716
B27: 20 | C27: (Flows related to leases) | D27: =Inputs!D71+Inputs!D72 -> 0 | E27: =Inputs!C71+Inputs!C72 -> 0 | F27: =Inputs!B71+Inputs!B72 -> 0 | G27: =AVERAGE(D27:F27) -> 0 | H27: =AVERAGE(E27:G27) -> 0 | I27: =AVERAGE(F27:H27) -> 0 | J27: =AVERAGE(G27:I27) -> 0 | K27: =AVERAGE(H27:J27) -> 0 | L27: =AVERAGE(I27:K27) -> 0 | M27: =AVERAGE(J27:L27) -> 0 | N27: =AVERAGE(K27:M27) -> 0 | ... AF27: =AVERAGE(AC27:AE27) -> 0
B28: 21 | C28: Flows related to debt | D28: =+SUM(Inputs!D69:D70) -> 14269 | E28: =+SUM(Inputs!C69:C70) -> 22554 | F28: =+SUM(Inputs!B69:B70) -> 4348 | G28: =G44-F44 -> -776.56009 | H28: =H44-G44 -> 482.54215 | I28: =I44-H44 -> 5416.8016 | J28: =J44-I44 -> 5070.4725 | K28: =K44-J44 -> -5449.7681 | L28: =L44-K44 -> 3920.1761 | M28: =M44-L44 -> 3994.8283 | N28: =N44-M44 -> -19012.836 | ... AF28: =AF44-AE44 -> 4816.3239
B29: 22 | C29: (Respurchases)/Issuance of stock | D29: ='Fin. Data'!D28 -> 0 | E29: ='Fin. Data'!C28 -> 0 | F29: ='Fin. Data'!B28 -> 0 | G29: =-G17*$D$65 -> 0 | H29: =-H17*$D$65 -> 0 | I29: =-I17*$D$65 -> 0 | J29: =-J17*$D$65 -> 0 | K29: =K17*$E$65 -> -2096.4329 | L29: =L17*$E$65 -> -2130.0234 | M29: =M17*$E$65 -> -2151.7922 | N29: =N17*$E$65 -> -2179.0371 | O29: =O17*$E$65 -> -2231.3547 | P29: =P17*$E$65 -> -2260.3621 | Q29: =Q17*$E$65 -> -2311.5532 | R29: =R17*$E$65 -> -2344.5773 | ... AF29: =AF17*$E$65 -> -3004.8436
B30: 23 | C30: (Dividends) | D30: ='Fin. Data'!D27 -> -10232 | E30: ='Fin. Data'!C27 -> -10445 | F30: ='Fin. Data'!B27 -> -10805 | G30: =-$D$64*G17 -> -9982.3255 | H30: =-$D$64*H17 -> -10584.349 | I30: =-$D$64*I17 -> -10919.614 | J30: =-$D$64*J17 -> -11044.662 | K30: =-$E$64*K17 -> -14675.03 | L30: =-$E$64*L17 -> -14910.163 | M30: =-$E$64*M17 -> -15062.545 | N30: =-$E$64*N17 -> -15253.26 | O30: =-$E$64*O17 -> -15619.483 | P30: =-$E$64*P17 -> -15822.535 | Q30: =-$E$64*Q17 -> -16180.872 | R30: =-$E$64*R17 -> -16412.041 | ... AF30: =-$E$64*AF17 -> -21033.906
B31: 24 | C31: Other financing flows | D31: =Inputs!D75 -> -2712 | E31: =Inputs!C75 -> -3832 | F31: =Inputs!B75 -> -2072 | G31: =(1+G5)*AVERAGE(D31:F31) -> -2958.16 | H31: =(1+H5)*AVERAGE(E31:G31) -> -3027.9047 | I31: =(1+I5)*AVERAGE(F31:H31) -> -2739.742 | J31: =(1+J5)*AVERAGE(G31:I31) -> -2952.2313 | K31: =(1+K5)*AVERAGE(H31:J31) -> -2935.6922 | L31: =(1+L5)*AVERAGE(I31:K31) -> -2904.6474 | M31: =(1+M5)*AVERAGE(J31:L31) -> -2960.1655 | N31: =(1+N5)*AVERAGE(K31:M31) -> -2962.8367 | ... AF31: =(1+AF5)*AVERAGE(AC31:AE31) -> -3239.7706
B32: 25 | C32: -Total Financing flows | D32: =D27+D28+D29+D30+D31 -> 1325 | E32: =E27+E28+E29+E30+E31 -> 8277 | F32: =F27+F28+F29+F30+F31 -> -8529 | G32: =G27+G28+G29+G30+G31 -> -13717.046 | H32: =H27+H28+H29+H30+H31 -> -13129.711 | I32: =I27+I28+I29+I30+I31 -> -8242.554 | J32: =J27+J28+J29+J30+J31 -> -8926.4211 | K32: =K27+K28+K29+K30+K31 -> -25156.924 | ... AF32: =AF27+AF28+AF29+AF30+AF31 -> -22462.196
A34: SUMMARY | B34: 26 | C34: Cash before shareholder returns | D34: =D22+D26+D27+D28+D31 -> 29813 | E34: =E22+E26+E27+E28+E31 -> -8892 | F34: =F22+F26+F27+F28+F31 -> 10755 | G34: =G22+G26+G27+G28+G31 -> 9910.8549 | H34: =H22+H26+H27+H28+H31 -> 11209.5 | I34: =I22+I26+I27+I28+I31 -> 17560.749 | J34: =J22+J26+J27+J28+J31 -> 19945.311 | K34: =K22+K26+K27+K28+K31 -> 13086.17 | ... AF34: =AF22+AF26+AF27+AF28+AF31 -> 55435.057
B35: 27 | C35: Returns to shareholders | D35: =-1*(D29+D30) -> 10232 | E35: =-1*(E29+E30) -> 10445 | F35: =-1*(F29+F30) -> 10805 | G35: =-1*(G29+G30) -> 9982.3255 | H35: =-1*(H29+H30) -> 10584.349 | I35: =-1*(I29+I30) -> 10919.614 | J35: =-1*(J29+J30) -> 11044.662 | K35: =-1*(K29+K30) -> 16771.463 | ... AF35: =-1*(AF29+AF30) -> 24038.749
B36: 28 | C36: Excess cash acumulation | D36: =D34-D35 -> 19581 | E36: =E34-E35 -> -19337 | F36: =F34-F35 -> -50 | G36: =G34-G35 -> -71.470651 | H36: =H34-H35 -> 625.15149 | I36: =I34-I35 -> 6641.1356 | J36: =J34-J35 -> 8900.6485 | K36: =K34-K35 -> -3685.2935 | ... AF36: =AF34-AF35 -> 31396.308
A38: BALANCE SHEET | B38: 29 | C38: Intangible assets | D38: 27477 | E38: 28485 | F38: 30562 | G38: =+F38+(-G10) -> 33006.96 | H38: =+G38+(-H10) -> 35647.517 | I38: =+H38+(-I10) -> 38499.318 | J38: =+I38+(-J10) -> 41579.264 | K38: =+J38+(-K10) -> 44489.812 | L38: =+K38+(-L10) -> 47604.099 | M38: =+L38+(-M10) -> 50936.386 | N38: =+M38+(-N10) -> 54501.933 | ... AF38: =+AE38+(-AF10) -> 184212.84 | AG38: =SUM(G38:AF38) -> 2328989.2
B39: 30 | C39: Accumulated amorization | D39: 18064 | E39: 16808 | F39: 19101 | G39: =F39-G10 -> 21545.96 | H39: =G39-H10 -> 24186.517 | I39: =H39-I10 -> 27038.318 | J39: =I39-J10 -> 30118.264 | K39: =J39-K10 -> 33028.812 | L39: =K39-L10 -> 36143.099 | M39: =L39-M10 -> 39475.386 | N39: =M39-N10 -> 43040.933 | ... AF39: =AE39-AF10 -> 172751.84 | AG39: =SUM(G39:AF39) -> 2031003.2
B40: 31 | C40: PPE+Right of use Assets | D40: 279737 | E40: 289897 | F40: 307689 | G40: =F40+(-G23) -> 325689 | H40: =G40+(-H23) -> 345913.9 | I40: =H40+(-I23) -> 366543.29 | J40: =I40+(-J23) -> 387482.13 | K40: =J40+(-K23) -> 405609.18 | L40: =K40+(-L23) -> 423917.5 | M40: =L40+(-M23) -> 442408.9 | N40: =M40+(-N23) -> 461085.22 | ... AF40: =AE40+(-AF23) -> 831079.78 | AG40: x
B41: 32 | C41: Accumulated depreciation | D41: 184904 | E41: 190201 | F41: 200225 | G41: =F41-G9 -> 215317.98 | H41: =G41-H9 -> 231293.9 | I41: =H41-I9 -> 248261.91 | J41: =I41-J9 -> 266241.85 | K41: =J41-K9 -> 283678.54 | L41: =K41-L9 -> 301930.95 | M41: =L41-M9 -> 321007.24 | N41: =M41-N9 -> 340915.64 | ... AF41: =AE41-AF9 -> 851460.68 | AG41: =SUM(G41:AF41) -> 12749616
A43: CASH & DEBT & DISCOUNTING | B43: 33 | C43: Ending cash balance | D43: ='Fin. Data'!D39 -> 22171 | E43: =E36+D43 -> 2834 | F43: =F36+E43 -> 2784 | G43: =G36+F43 -> 2712.5293 | H43: =H36+G43 -> 3337.6808 | I43: =I36+H43 -> 9978.8165 | J43: =J36+I43 -> 18879.465 | K43: =K36+J43 -> 15194.171 | L43: =L36+K43 -> 21652.313 | ... AF43: =AF36+AE43 -> 337152.96
B44: 34 | C44: Total Debt | D44: ='Fin. Data'!D58 -> 129062 | E44: ='Fin. Data'!C58 -> 150868 | F44: ='Fin. Data'!B58 -> 150639 | G44: =G12*3 -> 149862.44 | H44: =H12*Assumptions!$O$41 -> 150344.98 | I44: =I12*Assumptions!$O$41 -> 155761.78 | J44: =J12*Assumptions!$O$41 -> 160832.26 | K44: =K12*Assumptions!$O$41 -> 155382.49 | L44: =L12*Assumptions!$O$41 -> 159302.66 | M44: =M12*Assumptions!$O$41 -> 163297.49 | N44: =N12*Assumptions!$O$42 -> 144284.66 | O44: =O12*Assumptions!$O$42 -> 147865.71 | P44: =P12*Assumptions!$O$43 -> 133337.61 | Q44: =Q12*Assumptions!$O$43 -> 136620.81 | R44: =R12*Assumptions!$O$43 -> 139974.56 | S44: =S12*Assumptions!$O$43 -> 143402.2 | T44: =T12*Assumptions!$O$43 -> 146907.31 | U44: =U12*Assumptions!$O$43 -> 150493.67 | V44: =V12*Assumptions!$O$43 -> 154165.35 | W44: =W12*Assumptions!$O$43 -> 157926.64 | ... AF44: =AF12*Assumptions!$O$43 -> 196681.32
B45: 35 | C45: Discount factor | F45: =1/((1+$F$50)^G50) -> 1 | G45: =1/((1+$F$50)^G49) -> 0.90571506 | H45: =1/((1+$F$50)^H49) -> 0.82031977 | I45: =1/((1+$F$50)^I49) -> 0.74297597 | J45: =1/((1+$F$50)^J49) -> 0.67292453 | K45: =1/((1+$F$50)^K49) -> 0.60947788 | L45: =1/((1+$F$50)^L49) -> 0.5520133 | M45: =1/((1+$F$50)^M49) -> 0.49996676 | N45: =1/((1+$F$50)^N49) -> 0.45282742 | ... AF45: =1/((1+$F$50)^AF49) -> 0.076169542
B46: 36 | C46: DF + 0.1% | E46: +0.1% | F46: =1/((1+$F$50+0.001)^G50) -> 1 | G46: =1/((1+$F$50+0.001)^G49) -> 0.90489548 | H46: =1/((1+$F$50+0.001)^H49) -> 0.81883584 | I46: =1/((1+$F$50+0.001)^I49) -> 0.74096085 | J46: =1/((1+$F$50+0.001)^J49) -> 0.67049213 | K46: =1/((1+$F$50+0.001)^K49) -> 0.6067253 | L46: =1/((1+$F$50+0.001)^L49) -> 0.54902298 | M46: =1/((1+$F$50+0.001)^M49) -> 0.49680842 | N46: =1/((1+$F$50+0.001)^N49) -> 0.4495597 | ... AF46: =1/((1+$F$50+0.001)^AF49) -> 0.074397604
B47: 37 | C47: DF+0.5% | E47: +0.5% | F47: =1/((1+$F$50+0.005)^G50) -> 1 | G47: =1/((1+$F$50+0.005)^G49) -> 0.90163195 | H47: =1/((1+$F$50+0.005)^H49) -> 0.81294018 | I47: =1/((1+$F$50+0.005)^I49) -> 0.73297284 | J47: =1/((1+$F$50+0.005)^J49) -> 0.66087174 | K47: =1/((1+$F$50+0.005)^K49) -> 0.59586308 | L47: =1/((1+$F$50+0.005)^L49) -> 0.53724919 | M47: =1/((1+$F$50+0.005)^M49) -> 0.48440104 | N47: =1/((1+$F$50+0.005)^N49) -> 0.43675145 | ... AF47: =1/((1+$F$50+0.005)^AF49) -> 0.067726972
A49: Discount Rate | C49: Risk free rate | D49: Equity premium | E49: Firm premium | F49: Total | G49: 1 | H49: 2 | I49: 3 | J49: 4 | K49: 5 | L49: 6 | M49: 7 | N49: 8 | O49: 9 | P49: 10 | Q49: 11 | R49: 12 | S49: 13 | T49: 14 | U49: 15 | V49: 16 | W49: 17 | X49: 18 | Y49: 19 | Z49: 20 | AA49: 21 | AB49: 22 | AC49: 23 | AD49: 24 | AE49: 25 | AF49: 26
C50: 0.0466 | D50: 0.05 | E50: 0.0075 | F50: =E50+D50+C50 -> 0.1041 | G50: 0
A52: Modelling factors | D52: Short Term | E52: Long Term | F52: Reference (line)
C53: Depreciation factor | D53: =Assumptions!L14 -> -0.049052697 | E53: -0.045 | F53: % PPE
C54: Amortization factor | D54: -0.08 | E54: -0.07 | F54: % IA
C55: Stock-based comp | D55: =Assumptions!L16 -> -0.0050693948 | E55: =-0.0025 -> -0.0025 | F55: % revenue
C56: Tax Rate | D56: =-Assumptions!L17 -> 0.23212726 | E56: 0.27 | F56: % (line 9)
C57: Interest Rate on debt | D57: 0.06 | E57: 0.035 | F57: % debt (l29)
C58: Interest Rate on cash | D58: 0.045 | E58: 0.02 | F58: % of cash (l28)
C59: PPE+ROA | D59: =Assumptions!L20 -> 0 | E59: =Assumptions!M20 -> 0 | F59: Growing with capex
C60: Working capital flows | D60: =Assumptions!L21 -> -1.2867982 | E60: =Assumptions!M21 -> -1.2867982 | F60: % of change revenues (l2)
C61: Intangible Assets | D61: =Assumptions!L22 -> 0 | E61: =Assumptions!M22 -> 0 | F61: Growing with amortization
C62: Capex | D62: -0.14 | E62: -0.12 | F62: % revenue (l2)
C63: Acquisition factor | D63: =Assumptions!L24 -> -0.0069284036 | E63: =D63 -> -0.0069284036 | F63: % revenue (l2)
C64: Dividends | D64: 0.55 | E64: 0.7 | F64: % net income (11)
C65: Repurchases | D65: 0 | E65: -0.1 | F65: % net income (11)
C66: Leases | D66: - | E66: - | F66: % revenue (l2)
A68: Valuation | D68: $ millions
C69: Value of flows | D69: =SUMPRODUCT(G35:AF35,G45:AF45)+((AF43-AF44)*AF45) -> 151589.65 | E69: =D69/D71 -> 0.77159887
C70: Value of perpetuity | D70: =(AF34/(F50-AF5))*AF45 -> 44872.082 | E70: =D70/D71 -> 0.22840113
C71: Total Value | D71: =D69+D70 -> 196461.73
C72: Actual share price | D72: =OP!C19 -> 40.335
C73: Total value vs Mkt Cap | D73: =D74/D72-1 -> 0.15852419
C74: Estimated NPV per share | D74: =D71*1000000/OP!C20 -> 46.729073
A76: Sensibility | C76: Sensitivity +0.1% | D76: =(SUMPRODUCT(G35:AF35,G45:AF45)+((AF43-AF44)*AF45)+(AF34/(F50+0.001-AF5))*AF45)*1000000/OP!C20 -> 46.616844 | E76: =D76/D74-1 -> -0.0024016943
C77: Sensitivity +0.5% | D77: =(SUMPRODUCT(G35:AF35,G45:AF45)+((AF43-AF44)*AF45)+(AF34/(F50+0.005-AF5))*AF45)*1000000/OP!C20 -> 46.190578 | E77: =D77/D74-1 -> -0.01152377
A79: Notes
A81: EPS 2023 Model | B81: =(G17*1000000)/OP!C20 -> 4.3169621
A82: EPS 2023 Guidance | B82: 4.55 - 4.85

Sheet Debt
B1: Amount outstanding (at maturity) | C1: Coupon rate | D1: Maturity date | E1: Company totals | F1: Total
A2: Dollars in millions
A4: Debt maturing within one year
A6: Commericail Paper | B6: 500 | E6: 500
A8: Verizon Communications Inc. | B8: €685(a) | C8: 0.01625 | D8: 45352
A9: Verizon Communications Inc. | B9: 999 | C9: 0.0075 | D9: 45373
A10: Verizon Communications Inc. | B10: 95 | C10: SOFR+0.50% | D10: 45373
A11: Verizon Communications Inc. | B11: £413(a) | C11: 0.04073 | D11: 45461 | E11: 2453
A13: Private placements | B13: 9487 | E13: 9487
A15: Total debt maturing within one year | F15: 12440
A17: Long-term debt
A18: Verizon Pennsylvania LLC | B18: 44 | C18: 0.06 | D18: 47088
A19: Verizon Pennsylvania LLC | B19: 31 | C19: 0.0835 | D19: 11307
A20: Verizon Pennsylvania LLC | B20: 35 | C20: 0.0875 | D20: 11550 | E20: 110
A22: Verizon Maryland LLC | B22: 20 | C22: 0.08 | D22: 47406
A23: Verizon Maryland LLC | B23: 21 | C23: 0.083 | D23: 11536
A24: Verizon Maryland LLC | B24: 139 | C24: 0.05125 | D24: 12220 | E24: 180
A26: Verizon Virginia LLC | B26: 9 | C26: 0.08375 | D26: 47392 | E26: 9
A28: Verizon Delaware LLC | B28: 2 | C28: 0.08625 | D28: 11611 | E28: 2
A30: Verizon New Jersey Inc. | B30: 45 | C30: 0.0785 | D30: 47437 | E30: 45
A32: Verizon New England Inc. | B32: 133 | C32: 0.07875 | D32: 47437 | E32: 133
A34: Verizon New York Inc. | B34: 35 | C34: 0.065 | D34: 46858
A35: Verizon New York Inc. | B35: 99 | C35: 0.07375 | D35: 11780 | E35: 134
A37: Alltel Corporation | B37: 38 | C37: 0.068 | D37: 47239
A38: Alltel Corporation | B38: 56 | C38: 0.07875 | D38: 11871 | E38: 94
A40: Verizon Communications Inc. | B40: 1161 | C40: 0.035 | D40: 45597
A41: Verizon Communications Inc. | B41: 1340 | C41: 0.03376 | D41: 45703
A42: Verizon Communications Inc. | B42: €1,000(a) | C42: 0.00875 | D42: 45749
A43: Verizon Communications Inc. | B43: 889 | C43: LIBOR+1.10% | D43: 45792
A44: Verizon Communications Inc. | B44: 1404 | C44: 0.0085 | D44: 45981
A45: Verizon Communications Inc. | B45: €1,250(a) | C45: 0.0325 | D45: 46070
A46: Verizon Communications Inc. | B46: 1916 | C46: 0.0145 | D46: 46101
A47: Verizon Communications Inc. | B47: 526 | C47: SOFR+0.79% | D47: 46101
A48: Verizon Communications Inc. | B48: 4 | C48: 0.011 | D48: 46188
A49: Verizon Communications Inc. | B49: 2 | C49: 0.0105 | D49: 46188
A50: Verizon Communications Inc. | B50: 1869 | C50: 0.02625 | D50: 46249
A51: Verizon Communications Inc. | B51: €1,250(a) | C51: 0.01375 | D51: 46322
A52: Verizon Communications Inc. | B52: 3250 | C52: 0.04125 | D52: 46462
A53: Verizon Communications Inc. | B53: 750 | C53: 0.03 | D53: 46468
A54: Verizon Communications Inc. | B54: €1,250(a) | C54: 0.00875 | D54: 46485
A55: Verizon Communications Inc. | B55: CHF400(a) | C55: 0.01 | D55: 46721
A56: Verizon Communications Inc. | B56: 2830 | C56: 0.021 | D56: 46834
A57: Verizon Communications Inc. | B57: CAD$1,000(a) | C57: 0.02375 | D57: 46834
A58: Verizon Communications Inc. | B58: CHF375(a) | C58: 0.00193 | D58: 46836
A59: Verizon Communications Inc. | B59: 250 | C59: 0.0694 | D59: 46858
A60: Verizon Communications Inc. | B60: 4200 | C60: 0.04329 | D60: 47017
A61: Verizon Communications Inc. | B61: €1,250(a) | C61: 0.01375 | D61: 47059
A62: Verizon Communications Inc. | B62: £600(a) | C62: 0.01125 | D62: 47060
A63: Verizon Communications Inc. | B63: 1000 | C63: 0.03875 | D63: 47157
A64: Verizon Communications Inc. | B64: €1,000(a) | C64: 0.00375 | D64: 47199
A65: Verizon Communications Inc. | B65: 3 | C65: 0.035 | D65: 47223
A66: Verizon Communications Inc. | B66: 105 | C66: 0.068 | D66: 47239
A67: Verizon Communications Inc. | B67: 1 | C67: 0.04 | D67: 47253
A68: Verizon Communications Inc. | B68: 3 | C68: 0.0415 | D68: 47253
A69: Verizon Communications Inc. | B69: 2 | C69: 0.0395 | D69: 47284
A70: Verizon Communications Inc. | B70: 1 | C70: 0.038 | D70: 47284
A71: Verizon Communications Inc. | B71: 1 | C71: 0.04 | D71: 47345
A72: Verizon Communications Inc. | B72: 1 | C72: 0.041 | D72: 47376
A73: Verizon Communications Inc. | B73: 1 | C73: 0.045 | D73: 47376
A74: Verizon Communications Inc. | B74: 1 | C74: 0.048 | D74: 47376
A75: Verizon Communications Inc. | B75: €750(a) | C75: 0.01875 | D75: 47417
A76: Verizon Communications Inc. | B76: 1 | C76: 0.0555 | D76: 47437
A77: Verizon Communications Inc. | B77: 3 | C77: 0.056 | D77: 47437
A78: Verizon Communications Inc. | B78: 3 | C78: 0.0515 | D78: 47437
A79: Verizon Communications Inc. | B79: 4000 | C79: 0.04016 | D79: 47455
A80: Verizon Communications Inc. | B80: 3 | C80: 0.05 | D80: 47467
A81: Verizon Communications Inc. | B81: 1 | C81: 0.047 | D81: 47467
A82: Verizon Communications Inc. | B82: 1 | C82: 0.048 | D82: 11004
A83: Verizon Communications Inc. | B83: 1 | C83: 0.0505 | D83: 11032
A84: Verizon Communications Inc. | B84: 1 | C84: 0.0515 | D84: 11032
A85: Verizon Communications Inc. | B85: 1 | C85: 0.0515 | D85: 11032
A86: Verizon Communications Inc. | B86: 1500 | C86: 0.0315 | D86: 11039
A87: Verizon Communications Inc. | B87: €1,250(a) | C87: 0.0125 | D87: 11056
A88: Verizon Communications Inc. | B88: 1 | C88: 0.019 | D88: 11093
A89: Verizon Communications Inc. | B89: 1 | C89: 0.0205 | D89: 11093
A90: Verizon Communications Inc. | B90: 1 | C90: 0.0465 | D90: 11093
A91: Verizon Communications Inc. | B91: 1 | C91: 0.047 | D91: 11093
A92: Verizon Communications Inc. | B92: CAD$1,000(a) | C92: 0.025 | D92: 11094
A93: Verizon Communications Inc. | B93: 1 | C93: 0.05 | D93: 11124
A94: Verizon Communications Inc. | B94: 1 | C94: 0.0505 | D94: 11124
A95: Verizon Communications Inc. | B95: 1 | C95: 0.05 | D95: 11154
A96: Verizon Communications Inc. | B96: 1 | C96: 0.0525 | D96: 11185
A97: Verizon Communications Inc. | B97: 1 | C97: 0.054 | D97: 11216
A98: Verizon Communications Inc. | B98: 1 | C98: 0.0545 | D98: 11216
A99: Verizon Communications Inc. | B99: 1 | C99: 0.055 | D99: 11216
A100: Verizon Communications Inc. | B100: 1000 | C100: 0.015 | D100: 11219
A101: Verizon Communications Inc. | B101: £550(a) | C101: 0.01875 | D101: 11220
A102: Verizon Communications Inc. | B102: 1147 | C102: 0.0168 | D102: 11261
A103: Verizon Communications Inc. | B103: €1,250(a) | C103: 0.0425 | D103: 11262
A104: Verizon Communications Inc. | B104: 2 | C104: 0.0165 | D104: 11277
A105: Verizon Communications Inc. | B105: 563 | C105: 0.0775 | D105: 11293
A106: Verizon Communications Inc. | B106: 2250 | C106: 0.0175 | D106: 11343
A107: Verizon Communications Inc. | B107: 3707 | C107: 0.0255 | D107: 11403
A108: Verizon Communications Inc. | B108: CHF325(a) | C108: 0.00555 | D108: 11406
A109: Verizon Communications Inc. | B109: £500(a) | C109: 0.025 | D109: 11421
A110: Verizon Communications Inc. | B110: 6 | C110: 0.0235 | D110: 11458
A111: Verizon Communications Inc. | B111: 4 | C111: 0.0235 | D111: 11489
A112: Verizon Communications Inc. | B112: 3 | C112: 0.022 | D112: 11489
A113: Verizon Communications Inc. | B113: 1 | C113: 0.0265 | D113: 11550
A114: Verizon Communications Inc. | B114: 2 | C114: 0.02 | D114: 11550
...

Sheet Assumptions
C2: Assumptions
D5: 2022 | E5: =D5-1 -> 2021 | F5: =E5-1 -> 2020 | G5: =F5-1 -> 2019 | H5: =G5-1 -> 2018 | J5: Average | L5: Short Term Forecast | M5: Long Term Forecast
C6: Revenue growth | D6: =(Inputs!B6-Inputs!C6)/Inputs!C6 -> 0.02411442 | E6: =(Inputs!C6-Inputs!D6)/Inputs!D6 -> 0.041475696 | F6: =(Inputs!D6-Inputs!E6)/Inputs!E6 -> -0.027118027 | G6: =(Inputs!E6-Inputs!F6)/Inputs!F6 -> 0.0076797873 | H6: =(Inputs!F6-Inputs!G6)/Inputs!G6 -> 0.038315058 | J6: =AVERAGE(D6:H6) -> 0.016893387 | L6: 0.03 | M6: 0.01
C7: Operating Margin | D7: =Inputs!B8/Inputs!B6 -> 0.22265502 | E7: =Inputs!C8/Inputs!C6 -> 0.24285062 | F7: =Inputs!D8/Inputs!D6 -> 0.2244723 | G7: =Inputs!E8/Inputs!E6 -> 0.23036673 | H7: =Inputs!F8/Inputs!F6 -> 0.17023911 | J7: =AVERAGE(D7:H7) -> 0.21811676 | L7: 0.224 | M7: =J7 -> 0.21811676
C10: Modelling Factors
D12: Last 5 Years
D13: 2018 | E13: 2019 | F13: 2020 | G13: 2021 | H13: 2022 | J13: Average | L13: Short Term Forecast | M13: Long Term Forecast | O13: Reference
C14: Depreciation factor | F14: =DCF!D9/DCF!D40 -> -0.051030075 | G14: =DCF!E9/DCF!E40 -> -0.048703505 | H14: =DCF!F9/DCF!F40 -> -0.04742451 | J14: =AVERAGE(D14:H14) -> -0.049052697 | L14: =J14 -> -0.049052697 | M14: =L14 -> -0.049052697
C15: Amortization factor | F15: =DCF!D10/DCF!D38 -> -0.088983513 | G15: =DCF!E10/DCF!E38 -> -0.073266632 | H15: =DCF!F10/DCF!F38 -> -0.082029972 | J15: =AVERAGE(D15:H15) -> -0.081426706 | L15: =J15 -> -0.081426706 | M15: =L15 -> -0.081426706
C16: Stock-based comp | F16: =+DCF!D11/DCF!D6 -> -0.0060798803 | G16: =+DCF!E11/DCF!E6 -> -0.0046776885 | H16: =+DCF!F11/DCF!F6 -> -0.0044506157 | J16: =AVERAGE(D16:H16) -> -0.0050693948 | L16: =J16 -> -0.0050693948 | M16: =L16 -> -0.0050693948
C17: Tax Rate | F17: =DCF!D16/DCF!D15 -> -0.23444737 | G17: =DCF!E16/DCF!E15 -> -0.23120326 | H17: =DCF!F16/DCF!F15 -> -0.23073114 | J17: =AVERAGE(D17:H17) -> -0.23212726 | L17: =J17 -> -0.23212726 | M17: =L17 -> -0.23212726
C18: Interest Rate on debt | D18: =H36 -> 0.04274608 | E18: =G36 -> 0.04242571 | F18: =F36 -> 0.033115867 | G18: =E36 -> 0.023099663 | H18: =D36 -> 0.023984493 | J18: =AVERAGE(D18:H18) -> 0.033074363 | L18: =J18 -> 0.033074363 | M18: {=-AVERAGE('Fin. Data'!B14:M14/'Fin. Data'!B58:M58)} -> 0.038521455
C19: Interest Rate on cash | L19: =J19 -> 0 | M19: =L19 -> 0
C20: PPE+ROA | L20: =J20 -> 0 | M20: =L20 -> 0
C21: Working capital flows | D21: =+Inputs!F62/(Inputs!F6-Inputs!G6) -> -0.54607579 | E21: =+Inputs!E62/(Inputs!E6-Inputs!F6) -> -3.5960199 | F21: =+Inputs!D62/(Inputs!D6-Inputs!E6) -> -0.79306488 | G21: =+Inputs!C62/(Inputs!C6-Inputs!D6) -> -0.18473971 | H21: =+Inputs!B62/(Inputs!B6-Inputs!C6) -> -1.3140906 | J21: =AVERAGE(D21:H21) -> -1.2867982 | L21: =J21 -> -1.2867982 | M21: =L21 -> -1.2867982
C22: Intangible Assets | L22: =J22 -> 0 | M22: =L22 -> 0
C23: CAPEX | D23: =+'Fin. Data'!F32/'Fin. Data'!F5 -> -0.13821325 | E23: =+'Fin. Data'!E32/'Fin. Data'!E5 -> -0.14284739 | F23: =+'Fin. Data'!D32/'Fin. Data'!D5 -> -0.15837309 | G23: =+'Fin. Data'!C32/'Fin. Data'!C5 -> -0.50804937 | H23: =+'Fin. Data'!B32/'Fin. Data'!B5 -> -0.19541784 | J23: =AVERAGE(D23:H23) -> -0.22858019 | L23: =J23 -> -0.22858019 | M23: {=AVERAGE('Fin. Data'!B32:M32/'Fin. Data'!B5:M5)} -> -0.18627613
C24: Acquisition factor | D24: ='Fin. Data'!F33/'Fin. Data'!F5 -> -0.0017575633 | E24: ='Fin. Data'!E33/'Fin. Data'!E5 -> -0.00021991689 | F24: ='Fin. Data'!D33/'Fin. Data'!D5 -> -0.0040532535 | G24: ='Fin. Data'!C33/'Fin. Data'!C5 -> -0.030423686 | H24: ='Fin. Data'!B33/'Fin. Data'!B5 -> 0.0018124018 | J24: =AVERAGE(D24:H24) -> -0.0069284036 | L24: =J24 -> -0.0069284036 | M24: {=AVERAGE('Fin. Data'!B33:M33/'Fin. Data'!B5:M5)} -> -0.014145907
C25: Dividends | D25: =-'Fin. Data'!F27/'Fin. Data'!F23 -> 0.60926492 | E25: =-'Fin. Data'!E27/'Fin. Data'!E23 -> 0.50616535 | F25: =-'Fin. Data'!D27/'Fin. Data'!D23 -> 0.55766296 | G25: =-'Fin. Data'!C27/'Fin. Data'!C23 -> 0.46180034 | H25: =-'Fin. Data'!B27/'Fin. Data'!B23 -> 0.49682729 | J25: =AVERAGE(D25:H25) -> 0.52634417 | L25: =J25 -> 0.52634417 | M25: {=-AVERAGE('Fin. Data'!B27:M27/'Fin. Data'!B23:M23)} -> 0.50265893
C26: Repurchases | D26: =-'Fin. Data'!F28/'Fin. Data'!F23 -> 0 | E26: =-'Fin. Data'!E28/'Fin. Data'!E23 -> 0 | F26: =-'Fin. Data'!D28/'Fin. Data'!D23 -> 0 | G26: =-'Fin. Data'!C28/'Fin. Data'!C23 -> 0 | H26: =-'Fin. Data'!B28/'Fin. Data'!B23 -> 0 | J26: =AVERAGE(D26:H26) -> 0 | L26: =J26 -> 0 | M26: =L26 -> 0
C29: Forecasts
B32: Interest Rate on Debt
D33: 2022 | E33: 2021 | F33: 2020 | G33: 2019 | H33: 2018 | I33: 2017 | J33: 2016 | K33: 2015 | L33: 2014 | M33: 2013 | N33: Average 10Y
B34: Interest Expense | D34: -3613 | E34: -3485 | F34: -4274 | G34: -4730 | H34: -4833 | I34: -4733 | J34: -4376 | K34: -4920 | L34: -4915 | M34: -2667
B35: Debt | D35: ='Fin. Data'!B58 -> 150639 | E35: ='Fin. Data'!C58 -> 150868 | F35: ='Fin. Data'!D58 -> 129062 | G35: ='Fin. Data'!E58 -> 111489 | H35: ='Fin. Data'!F58 -> 113063 | I35: ='Fin. Data'!G58 -> 117095 | J35: ='Fin. Data'!H58 -> 108078 | K35: ='Fin. Data'!I58 -> 109729 | ... M35: ='Fin. Data'!K58 -> 93591
D36: =-D34/D35 -> 0.023984493 | E36: =-E34/E35 -> 0.023099663 | F36: =-F34/F35 -> 0.033115867 | G36: =-G34/G35 -> 0.04242571 | H36: =-H34/H35 -> 0.04274608 | I36: =-I34/I35 -> 0.040420172 | J36: =-J34/J35 -> 0.040489276 | K36: =-K34/K35 -> 0.044837737 | ... M36: =-M34/M35 -> 0.02849633
B39: Debt/Ebitda | D39: ='Fin. Data'!B58/'Fin. Data'!B19 -> 3.2610785 | E39: ='Fin. Data'!C58/'Fin. Data'!C19 -> 3.1208473 | F39: ='Fin. Data'!D58/'Fin. Data'!D19 -> 2.7994881 | G39: ='Fin. Data'!E58/'Fin. Data'!E19 -> 2.2308954 | H39: ='Fin. Data'!F58/'Fin. Data'!F19 -> 3.0147722 | I39: ='Fin. Data'!G58/'Fin. Data'!G19 -> 2.5194182 | J39: ='Fin. Data'!H58/'Fin. Data'!H19 -> 2.4187181 | K39: ='Fin. Data'!I58/'Fin. Data'!I19 -> 2.240419 | ... M39: ='Fin. Data'!K58/'Fin. Data'!K19 -> 1.92582 | N39: =AVERAGE(D39:M39) -> 2.671806
O41: 2.9 | P41: Short term
B42: A3/A-(current level) | O42: 2.5 | P42: Medium term
B43: Default spread | I43: 0.02 | O43: 2.2 | P43: Long term
B44: 30Y US Bond Yield | I44: 0.0487
B45: 5Y US Bond Yield | I45: 0.0472
B46: Country default spread (US) | I46: 0
B47: Short-term cost debt | I47: =I43+I45+I46 -> 0.0672
B48: Long-term cost of debt | I48: =I46+I44+I43 -> 0.0687

Sheet Fin. Data
A1: =Inputs!H3 -> #VALUE!
A2: =Inputs!G2 -> Figures in Millions of USD
A3: Results
B4: =OP!J19 -> 2022 | C4: =B4-1 -> 2021 | D4: =C4-1 -> 2020 | E4: =D4-1 -> 2019 | F4: =E4-1 -> 2018 | G4: =F4-1 -> 2017 | H4: =G4-1 -> 2016 | I4: =H4-1 -> 2015 | J4: =I4-1 -> 2014 | ... M4: =L4-1 -> 2011
A5: Net Sales | B5: =_xlfn.XLOOKUP($A5,Inputs!$A:$A,Inputs!B:B,,0) -> 136835 | C5: =_xlfn.XLOOKUP($A5,Inputs!$A:$A,Inputs!C:C,,0) -> 133613 | D5: =_xlfn.XLOOKUP($A5,Inputs!$A:$A,Inputs!D:D,,0) -> 128292 | E5: =_xlfn.XLOOKUP($A5,Inputs!$A:$A,Inputs!E:E,,0) -> 131868 | F5: =_xlfn.XLOOKUP($A5,Inputs!$A:$A,Inputs!F:F,,0) -> 130863 | G5: =_xlfn.XLOOKUP($A5,Inputs!$A:$A,Inputs!G:G,,0) -> 126034 | H5: =_xlfn.XLOOKUP($A5,Inputs!$A:$A,Inputs!H:H,,0) -> 125980 | I5: =_xlfn.XLOOKUP($A5,Inputs!$A:$A,Inputs!I:I,,0) -> 131620 | J5: =_xlfn.XLOOKUP($A5,Inputs!$A:$A,Inputs!J:J,,0) -> 127079 | K5: =_xlfn.XLOOKUP($A5,Inputs!$A:$A,Inputs!K:K,,0) -> 120550 | L5: =_xlfn.XLOOKUP($A5,Inputs!$A:$A,Inputs!L:L,,0) -> 115846 | M5: =_xlfn.XLOOKUP($A5,Inputs!$A:$A,Inputs!M:M,,0) -> 110875
A6: Growth vs. Previous year | B6: =IFERROR(B5/C5-1,"-") -> 0.02411442 | C6: =IFERROR(C5/D5-1,"-") -> 0.041475696 | D6: =IFERROR(D5/E5-1,"-") -> -0.027118027 | E6: =IFERROR(E5/F5-1,"-") -> 0.0076797873 | F6: =IFERROR(F5/G5-1,"-") -> 0.038315058 | G6: =IFERROR(G5/H5-1,"-") -> 0.00042863947 | H6: =IFERROR(H5/I5-1,"-") -> -0.042850631 | I6: =IFERROR(I5/J5-1,"-") -> 0.035733677 | ... L6: =IFERROR(L5/M5-1,"-") -> 0.044834273 | M6: =IFERROR(M5/#REF!-1,"-") -> -
A7: Gross Profit | B7: =_xlfn.XLOOKUP($A7,Inputs!$A:$A,Inputs!B:B,,0) -> 77702 | C7: =_xlfn.XLOOKUP($A7,Inputs!$A:$A,Inputs!C:C,,0) -> 77312 | D7: =_xlfn.XLOOKUP($A7,Inputs!$A:$A,Inputs!D:D,,0) -> 77091 | E7: =_xlfn.XLOOKUP($A7,Inputs!$A:$A,Inputs!E:E,,0) -> 77142 | F7: =_xlfn.XLOOKUP($A7,Inputs!$A:$A,Inputs!F:F,,0) -> 75658 | G7: =_xlfn.XLOOKUP($A7,Inputs!$A:$A,Inputs!G:G,,0) -> 73142 | H7: =_xlfn.XLOOKUP($A7,Inputs!$A:$A,Inputs!H:H,,0) -> 73279 | I7: =_xlfn.XLOOKUP($A7,Inputs!$A:$A,Inputs!I:I,,0) -> 79063 | J7: =_xlfn.XLOOKUP($A7,Inputs!$A:$A,Inputs!J:J,,0) -> 77175 | K7: =_xlfn.XLOOKUP($A7,Inputs!$A:$A,Inputs!K:K,,0) -> 75663 | L7: =_xlfn.XLOOKUP($A7,Inputs!$A:$A,Inputs!L:L,,0) -> 69611 | M7: =_xlfn.XLOOKUP($A7,Inputs!$A:$A,Inputs!M:M,,0) -> 65000
A8: % over sales | B8: =IFERROR(B7/B$5,"-") -> 0.56785179 | C8: =IFERROR(C7/C$5,"-") -> 0.57862633 | D8: =IFERROR(D7/D$5,"-") -> 0.60090263 | E8: =IFERROR(E7/E$5,"-") -> 0.58499408 | F8: =IFERROR(F7/F$5,"-") -> 0.57814661 | G8: =IFERROR(G7/G$5,"-") -> 0.58033547 | H8: =IFERROR(H7/H$5,"-") -> 0.58167169 | I8: =IFERROR(I7/I$5,"-") -> 0.60069138 | ... M8: =IFERROR(M7/M$5,"-") -> 0.58624577
A9: Operating expenses | B9: =B5-B11 -> 106368 | C9: =C5-C11 -> 101165 | D9: =D5-D11 -> 99494 | E9: =E5-E11 -> 101490 | F9: =F5-F11 -> 108585 | G9: =G5-G11 -> 98609 | H9: =H5-H11 -> 98921 | I9: =I5-I11 -> 98560 | ... M9: =M5-M11 -> 97995
A10: % over sales | B10: =IFERROR(B9/B$5,"-") -> 0.77734498 | C10: =IFERROR(C9/C$5,"-") -> 0.75714938 | D10: =IFERROR(D9/D$5,"-") -> 0.7755277 | E10: =IFERROR(E9/E$5,"-") -> 0.76963327 | F10: =IFERROR(F9/F$5,"-") -> 0.82976089 | G10: =IFERROR(G9/G$5,"-") -> 0.78239999 | H10: =IFERROR(H9/H$5,"-") -> 0.78521194 | I10: =IFERROR(I9/I$5,"-") -> 0.74882237 | ... M10: =IFERROR(M9/M$5,"-") -> 0.88383315
A11: Operating Income | B11: =_xlfn.XLOOKUP($A11,Inputs!$A:$A,Inputs!B:B,,0) -> 30467 | C11: =_xlfn.XLOOKUP($A11,Inputs!$A:$A,Inputs!C:C,,0) -> 32448 | D11: =_xlfn.XLOOKUP($A11,Inputs!$A:$A,Inputs!D:D,,0) -> 28798 | E11: =_xlfn.XLOOKUP($A11,Inputs!$A:$A,Inputs!E:E,,0) -> 30378 | F11: =_xlfn.XLOOKUP($A11,Inputs!$A:$A,Inputs!F:F,,0) -> 22278 | G11: =_xlfn.XLOOKUP($A11,Inputs!$A:$A,Inputs!G:G,,0) -> 27425 | H11: =_xlfn.XLOOKUP($A11,Inputs!$A:$A,Inputs!H:H,,0) -> 27059 | I11: =_xlfn.XLOOKUP($A11,Inputs!$A:$A,Inputs!I:I,,0) -> 33060 | J11: =_xlfn.XLOOKUP($A11,Inputs!$A:$A,Inputs!J:J,,0) -> 19599 | K11: =_xlfn.XLOOKUP($A11,Inputs!$A:$A,Inputs!K:K,,0) -> 31968 | L11: =_xlfn.XLOOKUP($A11,Inputs!$A:$A,Inputs!L:L,,0) -> 13160 | M11: =_xlfn.XLOOKUP($A11,Inputs!$A:$A,Inputs!M:M,,0) -> 12880
A12: Operating Margin | B12: =IFERROR(B11/B$5,"-") -> 0.22265502 | C12: =IFERROR(C11/C$5,"-") -> 0.24285062 | D12: =IFERROR(D11/D$5,"-") -> 0.2244723 | E12: =IFERROR(E11/E$5,"-") -> 0.23036673 | F12: =IFERROR(F11/F$5,"-") -> 0.17023911 | G12: =IFERROR(G11/G$5,"-") -> 0.21760001 | H12: =IFERROR(H11/H$5,"-") -> 0.21478806 | I12: =IFERROR(I11/I$5,"-") -> 0.25117763 | ... M12: =IFERROR(M11/M$5,"-") -> 0.11616685
A13: Growth vs. Previous year | B13: =IFERROR(B12/C12-1,"-") -> -0.083160579 | C13: =IFERROR(C12/D12-1,"-") -> 0.081873458 | D13: =IFERROR(D12/E12-1,"-") -> -0.02558717 | E13: =IFERROR(E12/F12-1,"-") -> 0.35319514 | F13: =IFERROR(F12/G12-1,"-") -> -0.21765122 | G13: =IFERROR(G12/H12-1,"-") -> 0.013091748 | H13: =IFERROR(H12/I12-1,"-") -> -0.14487584 | I13: =IFERROR(I12/J12-1,"-") -> 0.62862403 | ... L13: =IFERROR(L12/M12-1,"-") -> -0.02210412 | M13: =IFERROR(M12/#REF!-1,"-") -> -
A14: Net Financial Cost | B14: =_xlfn.XLOOKUP($A14,Inputs!$A:$A,Inputs!B:B,,0) -> -3569 | C14: =_xlfn.XLOOKUP($A14,Inputs!$A:$A,Inputs!C:C,,0) -> -3340 | D14: =_xlfn.XLOOKUP($A14,Inputs!$A:$A,Inputs!D:D,,0) -> -4247 | E14: =_xlfn.XLOOKUP($A14,Inputs!$A:$A,Inputs!E:E,,0) -> -4730 | F14: =_xlfn.XLOOKUP($A14,Inputs!$A:$A,Inputs!F:F,,0) -> -4833 | G14: =_xlfn.XLOOKUP($A14,Inputs!$A:$A,Inputs!G:G,,0) -> -4733 | H14: =_xlfn.XLOOKUP($A14,Inputs!$A:$A,Inputs!H:H,,0) -> -4376 | I14: =_xlfn.XLOOKUP($A14,Inputs!$A:$A,Inputs!I:I,,0) -> -4920 | J14: =_xlfn.XLOOKUP($A14,Inputs!$A:$A,Inputs!J:J,,0) -> -4915 | K14: =_xlfn.XLOOKUP($A14,Inputs!$A:$A,Inputs!K:K,,0) -> -2667 | L14: =_xlfn.XLOOKUP($A14,Inputs!$A:$A,Inputs!L:L,,0) -> -2571 | M14: =_xlfn.XLOOKUP($A14,Inputs!$A:$A,Inputs!M:M,,0) -> -2827
A15: Other Expenses (Revenues) | B15: =_xlfn.XLOOKUP($A15,Inputs!$A:$A,Inputs!B:B,,0) -> 1373 | C15: =_xlfn.XLOOKUP($A15,Inputs!$A:$A,Inputs!C:C,,0) -> 312 | D15: =_xlfn.XLOOKUP($A15,Inputs!$A:$A,Inputs!D:D,,0) -> -584 | E15: =_xlfn.XLOOKUP($A15,Inputs!$A:$A,Inputs!E:E,,0) -> -2915 | F15: =_xlfn.XLOOKUP($A15,Inputs!$A:$A,Inputs!F:F,,0) -> 2178 | G15: =_xlfn.XLOOKUP($A15,Inputs!$A:$A,Inputs!G:G,,0) -> -2098 | H15: =_xlfn.XLOOKUP($A15,Inputs!$A:$A,Inputs!H:H,,0) -> -1697 | I15: =_xlfn.XLOOKUP($A15,Inputs!$A:$A,Inputs!I:I,,0) -> 100 | J15: =_xlfn.XLOOKUP($A15,Inputs!$A:$A,Inputs!J:J,,0) -> 586 | K15: =_xlfn.XLOOKUP($A15,Inputs!$A:$A,Inputs!K:K,,0) -> -24 | L15: =_xlfn.XLOOKUP($A15,Inputs!$A:$A,Inputs!L:L,,0) -> -692 | M15: =_xlfn.XLOOKUP($A15,Inputs!$A:$A,Inputs!M:M,,0) -> 430
A16: EBIT | B16: =B11-B15 -> 29094 | C16: =C11-C15 -> 32136 | D16: =D11-D15 -> 29382 | E16: =E11-E15 -> 33293 | F16: =F11-F15 -> 20100 | G16: =G11-G15 -> 29523 | H16: =H11-H15 -> 28756 | I16: =I11-I15 -> 32960 | ... M16: =M11-M15 -> 12450
A17: Depreciation & Amortization | B17: =_xlfn.XLOOKUP($A17,Inputs!$A:$A,Inputs!B:B,,0) -> 17099 | C17: =_xlfn.XLOOKUP($A17,Inputs!$A:$A,Inputs!C:C,,0) -> 16206 | D17: =_xlfn.XLOOKUP($A17,Inputs!$A:$A,Inputs!D:D,,0) -> 16720 | E17: =_xlfn.XLOOKUP($A17,Inputs!$A:$A,Inputs!E:E,,0) -> 16682 | F17: =_xlfn.XLOOKUP($A17,Inputs!$A:$A,Inputs!F:F,,0) -> 17403 | G17: =_xlfn.XLOOKUP($A17,Inputs!$A:$A,Inputs!G:G,,0) -> 16954 | H17: =_xlfn.XLOOKUP($A17,Inputs!$A:$A,Inputs!H:H,,0) -> 15928 | I17: =_xlfn.XLOOKUP($A17,Inputs!$A:$A,Inputs!I:I,,0) -> 16017 | J17: =_xlfn.XLOOKUP($A17,Inputs!$A:$A,Inputs!J:J,,0) -> 16533 | K17: =_xlfn.XLOOKUP($A17,Inputs!$A:$A,Inputs!K:K,,0) -> 16606 | L17: =_xlfn.XLOOKUP($A17,Inputs!$A:$A,Inputs!L:L,,0) -> 16460 | M17: =_xlfn.XLOOKUP($A17,Inputs!$A:$A,Inputs!M:M,,0) -> 16496
A18: Changes Net Working Capital | B18: =_xlfn.XLOOKUP($A18,Inputs!$A:$A,Inputs!B:B,,0) -> -1566 | C18: =_xlfn.XLOOKUP($A18,Inputs!$A:$A,Inputs!C:C,,0) -> -6116 | D18: =_xlfn.XLOOKUP($A18,Inputs!$A:$A,Inputs!D:D,,0) -> 2752 | E18: =_xlfn.XLOOKUP($A18,Inputs!$A:$A,Inputs!E:E,,0) -> -3950 | F18: =_xlfn.XLOOKUP($A18,Inputs!$A:$A,Inputs!F:F,,0) -> -836 | G18: =_xlfn.XLOOKUP($A18,Inputs!$A:$A,Inputs!G:G,,0) -> 1622 | H18: =_xlfn.XLOOKUP($A18,Inputs!$A:$A,Inputs!H:H,,0) -> 10417 | I18: =_xlfn.XLOOKUP($A18,Inputs!$A:$A,Inputs!I:I,,0) -> -8156 | J18: =_xlfn.XLOOKUP($A18,Inputs!$A:$A,Inputs!J:J,,0) -> 498 | K18: =_xlfn.XLOOKUP($A18,Inputs!$A:$A,Inputs!K:K,,0) -> -770 | L18: =_xlfn.XLOOKUP($A18,Inputs!$A:$A,Inputs!L:L,,0) -> 4370 | M18: =_xlfn.XLOOKUP($A18,Inputs!$A:$A,Inputs!M:M,,0) -> 0
A19: EBITDA | B19: =B11-B15+B17 -> 46193 | C19: =C11-C15+C17 -> 48342 | D19: =D11-D15+D17 -> 46102 | E19: =E11-E15+E17 -> 49975 | F19: =F11-F15+F17 -> 37503 | G19: =G11-G15+G17 -> 46477 | H19: =H11-H15+H17 -> 44684 | I19: =I11-I15+I17 -> 48977 | ... M19: =M11-M15+M17 -> 28946
A20: EBITDA Margin | B20: =IFERROR(B19/B$5,"-") -> 0.33758176 | C20: =IFERROR(C19/C$5,"-") -> 0.36180611 | D20: =IFERROR(D19/D$5,"-") -> 0.3593521 | E20: =IFERROR(E19/E$5,"-") -> 0.37897746 | F20: =IFERROR(F19/F$5,"-") -> 0.28658215 | G20: =IFERROR(G19/G$5,"-") -> 0.36876557 | H20: =IFERROR(H19/H$5,"-") -> 0.35469122 | I20: =IFERROR(I19/I$5,"-") -> 0.3721091 | ... M20: =IFERROR(M19/M$5,"-") -> 0.26106877
A21: Taxes | B21: =_xlfn.XLOOKUP($A21,Inputs!$A:$A,Inputs!B:B,,0) -> -6523 | C21: =_xlfn.XLOOKUP($A21,Inputs!$A:$A,Inputs!C:C,,0) -> -6802 | D21: =_xlfn.XLOOKUP($A21,Inputs!$A:$A,Inputs!D:D,,0) -> -5619 | E21: =_xlfn.XLOOKUP($A21,Inputs!$A:$A,Inputs!E:E,,0) -> -2945 | F21: =_xlfn.XLOOKUP($A21,Inputs!$A:$A,Inputs!F:F,,0) -> -3584 | G21: =_xlfn.XLOOKUP($A21,Inputs!$A:$A,Inputs!G:G,,0) -> 9956 | H21: =_xlfn.XLOOKUP($A21,Inputs!$A:$A,Inputs!H:H,,0) -> -7378 | I21: =_xlfn.XLOOKUP($A21,Inputs!$A:$A,Inputs!I:I,,0) -> -9865 | J21: =_xlfn.XLOOKUP($A21,Inputs!$A:$A,Inputs!J:J,,0) -> -3314 | K21: =_xlfn.XLOOKUP($A21,Inputs!$A:$A,Inputs!K:K,,0) -> -5730 | L21: =_xlfn.XLOOKUP($A21,Inputs!$A:$A,Inputs!L:L,,0) -> 660 | M21: =_xlfn.XLOOKUP($A21,Inputs!$A:$A,Inputs!M:M,,0) -> -285
A22: % Tax | B22: =IFERROR(B21/B$5,"-") -> -0.047670552 | C22: =IFERROR(C21/C$5,"-") -> -0.05090822 | D22: =IFERROR(D21/D$5,"-") -> -0.043798522 | E22: =IFERROR(E21/E$5,"-") -> -0.022332939 | F22: =IFERROR(F21/F$5,"-") -> -0.02738742 | G22: =IFERROR(G21/G$5,"-") -> 0.078994557 | H22: =IFERROR(H21/H$5,"-") -> -0.058564852 | I22: =IFERROR(I21/I$5,"-") -> -0.074950615 | ... M22: =IFERROR(M21/M$5,"-") -> -0.0025704622
A23: Net Income | B23: =_xlfn.XLOOKUP($A23,Inputs!$A:$A,Inputs!B:B,,0) -> 21748 | C23: =_xlfn.XLOOKUP($A23,Inputs!$A:$A,Inputs!C:C,,0) -> 22618 | D23: =_xlfn.XLOOKUP($A23,Inputs!$A:$A,Inputs!D:D,,0) -> 18348 | E23: =_xlfn.XLOOKUP($A23,Inputs!$A:$A,Inputs!E:E,,0) -> 19788 | F23: =_xlfn.XLOOKUP($A23,Inputs!$A:$A,Inputs!F:F,,0) -> 16039 | G23: =_xlfn.XLOOKUP($A23,Inputs!$A:$A,Inputs!G:G,,0) -> 30550 | H23: =_xlfn.XLOOKUP($A23,Inputs!$A:$A,Inputs!H:H,,0) -> 13608 | I23: =_xlfn.XLOOKUP($A23,Inputs!$A:$A,Inputs!I:I,,0) -> 18375 | J23: =_xlfn.XLOOKUP($A23,Inputs!$A:$A,Inputs!J:J,,0) -> 11956 | K23: =_xlfn.XLOOKUP($A23,Inputs!$A:$A,Inputs!K:K,,0) -> 23547 | L23: =_xlfn.XLOOKUP($A23,Inputs!$A:$A,Inputs!L:L,,0) -> 10557 | M23: =_xlfn.XLOOKUP($A23,Inputs!$A:$A,Inputs!M:M,,0) -> 10198
A24: Net Income Margin | B24: =IFERROR(B23/B$5,"-") -> 0.15893594 | C24: =IFERROR(C23/C$5,"-") -> 0.16927994 | D24: =IFERROR(D23/D$5,"-") -> 0.14301749 | E24: =IFERROR(E23/E$5,"-") -> 0.15005915 | F24: =IFERROR(F23/F$5,"-") -> 0.12256329 | G24: =IFERROR(G23/G$5,"-") -> 0.24239491 | H24: =IFERROR(H23/H$5,"-") -> 0.10801715 | I24: =IFERROR(I23/I$5,"-") -> 0.13960644 | ... M24: =IFERROR(M23/M$5,"-") -> 0.091977452
A25: Growth vs. Previous year | B25: =IFERROR(B24/C24-1,"-") -> -0.061105828 | C25: =IFERROR(C24/D24-1,"-") -> 0.18363099 | D25: =IFERROR(D24/E24-1,"-") -> -0.046925887 | E25: =IFERROR(E24/F24-1,"-") -> 0.22434008 | F25: =IFERROR(F24/G24-1,"-") -> -0.49436524 | G25: =IFERROR(G24/H24-1,"-") -> 1.2440411 | H25: =IFERROR(H24/I24-1,"-") -> -0.22627392 | I25: =IFERROR(I24/J24-1,"-") -> 0.48386142 | ... L25: =IFERROR(L24/M24-1,"-") -> -0.0092180091 | M25: =IFERROR(M24/#REF!-1,"-") -> -
A26: Cash Generated | B26: =B39-C39 -> -316 | C26: =C39-D39 -> -19250 | D26: =D39-E39 -> 19577 | E26: =E39-F39 -> -151 | F26: =F39-G39 -> 666 | G26: =G39-H39 -> -801 | H26: =H39-I39 -> -1590 | I26: =I39-J39 -> -6128 | ... M26: =M39-N39 -> 13362
A27: Dividends | B27: =_xlfn.XLOOKUP($A27,Inputs!$A:$A,Inputs!B:B,,0) -> -10805 | C27: =_xlfn.XLOOKUP($A27,Inputs!$A:$A,Inputs!C:C,,0) -> -10445 | D27: =_xlfn.XLOOKUP($A27,Inputs!$A:$A,Inputs!D:D,,0) -> -10232 | E27: =_xlfn.XLOOKUP($A27,Inputs!$A:$A,Inputs!E:E,,0) -> -10016 | F27: =_xlfn.XLOOKUP($A27,Inputs!$A:$A,Inputs!F:F,,0) -> -9772 | G27: =_xlfn.XLOOKUP($A27,Inputs!$A:$A,Inputs!G:G,,0) -> -9472 | H27: =_xlfn.XLOOKUP($A27,Inputs!$A:$A,Inputs!H:H,,0) -> -9262 | I27: =_xlfn.XLOOKUP($A27,Inputs!$A:$A,Inputs!I:I,,0) -> -8538 | J27: =_xlfn.XLOOKUP($A27,Inputs!$A:$A,Inputs!J:J,,0) -> -7803 | K27: =_xlfn.XLOOKUP($A27,Inputs!$A:$A,Inputs!K:K,,0) -> -5936 | L27: =_xlfn.XLOOKUP($A27,Inputs!$A:$A,Inputs!L:L,,0) -> -5230 | M27: =_xlfn.XLOOKUP($A27,Inputs!$A:$A,Inputs!M:M,,0) -> -5555
A28: Share buyback | B28: =_xlfn.XLOOKUP($A28,Inputs!$A:$A,Inputs!B:B,,0) -> 0 | C28: =_xlfn.XLOOKUP($A28,Inputs!$A:$A,Inputs!C:C,,0) -> 0 | D28: =_xlfn.XLOOKUP($A28,Inputs!$A:$A,Inputs!D:D,,0) -> 0 | E28: =_xlfn.XLOOKUP($A28,Inputs!$A:$A,Inputs!E:E,,0) -> 0 | F28: =_xlfn.XLOOKUP($A28,Inputs!$A:$A,Inputs!F:F,,0) -> 0 | G28: =_xlfn.XLOOKUP($A28,Inputs!$A:$A,Inputs!G:G,,0) -> 0 | H28: =_xlfn.XLOOKUP($A28,Inputs!$A:$A,Inputs!H:H,,0) -> 0 | I28: =_xlfn.XLOOKUP($A28,Inputs!$A:$A,Inputs!I:I,,0) -> -5134 | J28: =_xlfn.XLOOKUP($A28,Inputs!$A:$A,Inputs!J:J,,0) -> 0 | K28: =_xlfn.XLOOKUP($A28,Inputs!$A:$A,Inputs!K:K,,0) -> -153 | L28: =_xlfn.XLOOKUP($A28,Inputs!$A:$A,Inputs!L:L,,0) -> 0 | M28: =_xlfn.XLOOKUP($A28,Inputs!$A:$A,Inputs!M:M,,0) -> 0
A29: Net Cash Flow | B29: =SUM(B26:B28) -> -11121 | C29: =SUM(C26:C28) -> -29695 | D29: =SUM(D26:D28) -> 9345 | E29: =SUM(E26:E28) -> -10167 | F29: =SUM(F26:F28) -> -9106 | G29: =SUM(G26:G28) -> -10273 | H29: =SUM(H26:H28) -> -10852 | I29: =SUM(I26:I28) -> -19800 | ... M29: =SUM(M26:M28) -> 7807
A30: FNP'' | B30: =+B29-(B58-C29) -> -191455 | C30: =+C29-(C58-D29) -> -171218 | D30: =+D29-(D58-E29) -> -129884 | E30: =+E29-(E58-F29) -> -130762 | F30: =+F29-(F58-G29) -> -132442 | G30: =+G29-(G58-H29) -> -138220 | H30: =+H29-(H58-I29) -> -138730 | I30: =+I29-(I58-J29) -> -180262 | ... M30: =+M29-(M58-N29) -> -47345
A31: FNP' | B31: =+B30+B33 -> -191207 | C31: =+C30+C33 -> -175283 | D31: =+D30+D33 -> -130404 | E31: =+E30+E33 -> -130791 | F31: =+F30+F33 -> -132672 | G31: =+G30+G33 -> -144100 | H31: =+H30+H33 -> -142495 | I31: =+I30+I33 -> -183807 | ... M31: =+M30+M33 -> -49363
A32: Net Capex | B32: =_xlfn.XLOOKUP($A32,Inputs!$A:$A,Inputs!B:B,,0) -> -26740 | C32: =_xlfn.XLOOKUP($A32,Inputs!$A:$A,Inputs!C:C,,0) -> -67882 | D32: =_xlfn.XLOOKUP($A32,Inputs!$A:$A,Inputs!D:D,,0) -> -20318 | E32: =_xlfn.XLOOKUP($A32,Inputs!$A:$A,Inputs!E:E,,0) -> -18837 | F32: =_xlfn.XLOOKUP($A32,Inputs!$A:$A,Inputs!F:F,,0) -> -18087 | G32: =_xlfn.XLOOKUP($A32,Inputs!$A:$A,Inputs!G:G,,0) -> -17830 | H32: =_xlfn.XLOOKUP($A32,Inputs!$A:$A,Inputs!H:H,,0) -> -17593 | I32: =_xlfn.XLOOKUP($A32,Inputs!$A:$A,Inputs!I:I,,0) -> -27717 | J32: =_xlfn.XLOOKUP($A32,Inputs!$A:$A,Inputs!J:J,,0) -> -17545 | K32: =_xlfn.XLOOKUP($A32,Inputs!$A:$A,Inputs!K:K,,0) -> -17184 | L32: =_xlfn.XLOOKUP($A32,Inputs!$A:$A,Inputs!L:L,,0) -> -20110 | M32: =_xlfn.XLOOKUP($A32,Inputs!$A:$A,Inputs!M:M,,0) -> -16244
A33: Investments & Acquisitions | B33: =_xlfn.XLOOKUP($A33,Inputs!$A:$A,Inputs!B:B,,0) -> 248 | C33: =_xlfn.XLOOKUP($A33,Inputs!$A:$A,Inputs!C:C,,0) -> -4065 | D33: =_xlfn.XLOOKUP($A33,Inputs!$A:$A,Inputs!D:D,,0) -> -520 | E33: =_xlfn.XLOOKUP($A33,Inputs!$A:$A,Inputs!E:E,,0) -> -29 | F33: =_xlfn.XLOOKUP($A33,Inputs!$A:$A,Inputs!F:F,,0) -> -230 | G33: =_xlfn.XLOOKUP($A33,Inputs!$A:$A,Inputs!G:G,,0) -> -5880 | H33: =_xlfn.XLOOKUP($A33,Inputs!$A:$A,Inputs!H:H,,0) -> -3765 | I33: =_xlfn.XLOOKUP($A33,Inputs!$A:$A,Inputs!I:I,,0) -> -3545 | J33: =_xlfn.XLOOKUP($A33,Inputs!$A:$A,Inputs!J:J,,0) -> -185 | K33: =_xlfn.XLOOKUP($A33,Inputs!$A:$A,Inputs!K:K,,0) -> -494 | L33: =_xlfn.XLOOKUP($A33,Inputs!$A:$A,Inputs!L:L,,0) -> -913 | M33: =_xlfn.XLOOKUP($A33,Inputs!$A:$A,Inputs!M:M,,0) -> -2018
A34: Capex + Investments | B34: =+B32+B33 -> -26492 | C34: =+C32+C33 -> -71947 | D34: =+D32+D33 -> -20838 | E34: =+E32+E33 -> -18866 | F34: =+F32+F33 -> -18317 | G34: =+G32+G33 -> -23710 | H34: =+H32+H33 -> -21358 | I34: =+I32+I33 -> -31262 | ... M34: =+M32+M33 -> -18262
A35: Dividends + Share Buyback | B35: =+B27+B28 -> -10805 | C35: =+C27+C28 -> -10445 | D35: =+D27+D28 -> -10232 | E35: =+E27+E28 -> -10016 | F35: =+F27+F28 -> -9772 | G35: =+G27+G28 -> -9472 | H35: =+H27+H28 -> -9262 | I35: =+I27+I28 -> -13672 | ... M35: =+M27+M28 -> -5555
A36: Payout Ratio | B36: =IFERROR(B35/B23,"-") -> -0.49682729 | C36: =IFERROR(C35/C23,"-") -> -0.46180034 | D36: =IFERROR(D35/D23,"-") -> -0.55766296 | E36: =IFERROR(E35/E23,"-") -> -0.50616535 | F36: =IFERROR(F35/F23,"-") -> -0.60926492 | G36: =IFERROR(G35/G23,"-") -> -0.3100491 | H36: =IFERROR(H35/H23,"-") -> -0.68062904 | I36: =IFERROR(I35/I23,"-") -> -0.74405442 | ... M36: =IFERROR(M35/M23,"-") -> -0.54471465
A38: Assets
A39: Cash & Eq. | B39: =_xlfn.XLOOKUP($A39,Inputs!$A:$A,Inputs!B:B,,0) -> 2605 | C39: =_xlfn.XLOOKUP($A39,Inputs!$A:$A,Inputs!C:C,,0) -> 2921 | D39: =_xlfn.XLOOKUP($A39,Inputs!$A:$A,Inputs!D:D,,0) -> 22171 | E39: =_xlfn.XLOOKUP($A39,Inputs!$A:$A,Inputs!E:E,,0) -> 2594 | F39: =_xlfn.XLOOKUP($A39,Inputs!$A:$A,Inputs!F:F,,0) -> 2745 | G39: =_xlfn.XLOOKUP($A39,Inputs!$A:$A,Inputs!G:G,,0) -> 2079 | H39: =_xlfn.XLOOKUP($A39,Inputs!$A:$A,Inputs!H:H,,0) -> 2880 | I39: =_xlfn.XLOOKUP($A39,Inputs!$A:$A,Inputs!I:I,,0) -> 4470 | J39: =_xlfn.XLOOKUP($A39,Inputs!$A:$A,Inputs!J:J,,0) -> 10598 | K39: =_xlfn.XLOOKUP($A39,Inputs!$A:$A,Inputs!K:K,,0) -> 53528 | L39: =_xlfn.XLOOKUP($A39,Inputs!$A:$A,Inputs!L:L,,0) -> 3093 | M39: =_xlfn.XLOOKUP($A39,Inputs!$A:$A,Inputs!M:M,,0) -> 13362
A40: Accounts Receivable | B40: =_xlfn.XLOOKUP($A40,Inputs!$A:$A,Inputs!B:B,,0) -> 24506 | C40: =_xlfn.XLOOKUP($A40,Inputs!$A:$A,Inputs!C:C,,0) -> 24585 | D40: =_xlfn.XLOOKUP($A40,Inputs!$A:$A,Inputs!D:D,,0) -> 24650 | E40: =_xlfn.XLOOKUP($A40,Inputs!$A:$A,Inputs!E:E,,0) -> 26277 | F40: =_xlfn.XLOOKUP($A40,Inputs!$A:$A,Inputs!F:F,,0) -> 25859 | G40: =_xlfn.XLOOKUP($A40,Inputs!$A:$A,Inputs!G:G,,0) -> 23493 | H40: =_xlfn.XLOOKUP($A40,Inputs!$A:$A,Inputs!H:H,,0) -> 17513 | I40: =_xlfn.XLOOKUP($A40,Inputs!$A:$A,Inputs!I:I,,0) -> 13457 | J40: =_xlfn.XLOOKUP($A40,Inputs!$A:$A,Inputs!J:J,,0) -> 13993 | K40: =_xlfn.XLOOKUP($A40,Inputs!$A:$A,Inputs!K:K,,0) -> 12439 | L40: =_xlfn.XLOOKUP($A40,Inputs!$A:$A,Inputs!L:L,,0) -> 12576 | M40: =_xlfn.XLOOKUP($A40,Inputs!$A:$A,Inputs!M:M,,0) -> 11776
A41: Inventory | B41: =_xlfn.XLOOKUP($A41,Inputs!$A:$A,Inputs!B:B,,0) -> 2388 | C41: =_xlfn.XLOOKUP($A41,Inputs!$A:$A,Inputs!C:C,,0) -> 3055 | D41: =_xlfn.XLOOKUP($A41,Inputs!$A:$A,Inputs!D:D,,0) -> 1796 | E41: =_xlfn.XLOOKUP($A41,Inputs!$A:$A,Inputs!E:E,,0) -> 1422 | F41: =_xlfn.XLOOKUP($A41,Inputs!$A:$A,Inputs!F:F,,0) -> 1336 | G41: =_xlfn.XLOOKUP($A41,Inputs!$A:$A,Inputs!G:G,,0) -> 1034 | H41: =_xlfn.XLOOKUP($A41,Inputs!$A:$A,Inputs!H:H,,0) -> 1202 | I41: =_xlfn.XLOOKUP($A41,Inputs!$A:$A,Inputs!I:I,,0) -> 1252 | J41: =_xlfn.XLOOKUP($A41,Inputs!$A:$A,Inputs!J:J,,0) -> 1153 | K41: =_xlfn.XLOOKUP($A41,Inputs!$A:$A,Inputs!K:K,,0) -> 1020 | L41: =_xlfn.XLOOKUP($A41,Inputs!$A:$A,Inputs!L:L,,0) -> 1075 | M41: =_xlfn.XLOOKUP($A41,Inputs!$A:$A,Inputs!M:M,,0) -> 940
A42: Property, Plant and Equipment | B42: =_xlfn.XLOOKUP($A42,Inputs!$A:$A,Inputs!B:B,,0) -> 133564 | C42: =_xlfn.XLOOKUP($A42,Inputs!$A:$A,Inputs!C:C,,0) -> 127579 | D42: =_xlfn.XLOOKUP($A42,Inputs!$A:$A,Inputs!D:D,,0) -> 117364 | E42: =_xlfn.XLOOKUP($A42,Inputs!$A:$A,Inputs!E:E,,0) -> 114609 | F42: =_xlfn.XLOOKUP($A42,Inputs!$A:$A,Inputs!F:F,,0) -> 89286 | G42: =_xlfn.XLOOKUP($A42,Inputs!$A:$A,Inputs!G:G,,0) -> 88568 | H42: =_xlfn.XLOOKUP($A42,Inputs!$A:$A,Inputs!H:H,,0) -> 84751 | I42: =_xlfn.XLOOKUP($A42,Inputs!$A:$A,Inputs!I:I,,0) -> 83541 | J42: =_xlfn.XLOOKUP($A42,Inputs!$A:$A,Inputs!J:J,,0) -> 89947 | K42: =_xlfn.XLOOKUP($A42,Inputs!$A:$A,Inputs!K:K,,0) -> 88956 | L42: =_xlfn.XLOOKUP($A42,Inputs!$A:$A,Inputs!L:L,,0) -> 88642 | M42: =_xlfn.XLOOKUP($A42,Inputs!$A:$A,Inputs!M:M,,0) -> 88434
A43: Other Assets | B43: =_xlfn.XLOOKUP($A43,Inputs!$A:$A,Inputs!B:B,,0) -> 189416 | C43: =_xlfn.XLOOKUP($A43,Inputs!$A:$A,Inputs!C:C,,0) -> 179512 | D43: =_xlfn.XLOOKUP($A43,Inputs!$A:$A,Inputs!D:D,,0) -> 127380 | E43: =_xlfn.XLOOKUP($A43,Inputs!$A:$A,Inputs!E:E,,0) -> 123573 | F43: =_xlfn.XLOOKUP($A43,Inputs!$A:$A,Inputs!F:F,,0) -> 144932 | G43: =_xlfn.XLOOKUP($A43,Inputs!$A:$A,Inputs!G:G,,0) -> 140930 | H43: =_xlfn.XLOOKUP($A43,Inputs!$A:$A,Inputs!H:H,,0) -> 136724 | I43: =_xlfn.XLOOKUP($A43,Inputs!$A:$A,Inputs!I:I,,0) -> 140659 | J43: =_xlfn.XLOOKUP($A43,Inputs!$A:$A,Inputs!J:J,,0) -> 116123 | K43: =_xlfn.XLOOKUP($A43,Inputs!$A:$A,Inputs!K:K,,0) -> 114723 | L43: =_xlfn.XLOOKUP($A43,Inputs!$A:$A,Inputs!L:L,,0) -> 116435 | M43: =_xlfn.XLOOKUP($A43,Inputs!$A:$A,Inputs!M:M,,0) -> 112501
A44: Total Assets | B44: =_xlfn.XLOOKUP($A44,Inputs!$A:$A,Inputs!B:B,,0) -> 379680 | C44: =_xlfn.XLOOKUP($A44,Inputs!$A:$A,Inputs!C:C,,0) -> 366596 | D44: =_xlfn.XLOOKUP($A44,Inputs!$A:$A,Inputs!D:D,,0) -> 316481 | E44: =_xlfn.XLOOKUP($A44,Inputs!$A:$A,Inputs!E:E,,0) -> 291727 | F44: =_xlfn.XLOOKUP($A44,Inputs!$A:$A,Inputs!F:F,,0) -> 264829 | G44: =_xlfn.XLOOKUP($A44,Inputs!$A:$A,Inputs!G:G,,0) -> 257143 | H44: =_xlfn.XLOOKUP($A44,Inputs!$A:$A,Inputs!H:H,,0) -> 244180 | I44: =_xlfn.XLOOKUP($A44,Inputs!$A:$A,Inputs!I:I,,0) -> 244175 | J44: =_xlfn.XLOOKUP($A44,Inputs!$A:$A,Inputs!J:J,,0) -> 232616 | K44: =_xlfn.XLOOKUP($A44,Inputs!$A:$A,Inputs!K:K,,0) -> 274098 | L44: =_xlfn.XLOOKUP($A44,Inputs!$A:$A,Inputs!L:L,,0) -> 225222 | M44: =_xlfn.XLOOKUP($A44,Inputs!$A:$A,Inputs!M:M,,0) -> 230461
A47: Liabilities
A48: Current Liabilities | B48: =_xlfn.XLOOKUP($A48,Inputs!$A:$A,Inputs!B:B,,0) -> 50171 | C48: =_xlfn.XLOOKUP($A48,Inputs!$A:$A,Inputs!C:C,,0) -> 47160 | D48: =_xlfn.XLOOKUP($A48,Inputs!$A:$A,Inputs!D:D,,0) -> 39660 | E48: =_xlfn.XLOOKUP($A48,Inputs!$A:$A,Inputs!E:E,,0) -> 44868 | F48: =_xlfn.XLOOKUP($A48,Inputs!$A:$A,Inputs!F:F,,0) -> 37930 | G48: =_xlfn.XLOOKUP($A48,Inputs!$A:$A,Inputs!G:G,,0) -> 33037 | H48: =_xlfn.XLOOKUP($A48,Inputs!$A:$A,Inputs!H:H,,0) -> 30340 | I48: =_xlfn.XLOOKUP($A48,Inputs!$A:$A,Inputs!I:I,,0) -> 35052 | J48: =_xlfn.XLOOKUP($A48,Inputs!$A:$A,Inputs!J:J,,0) -> 27987 | K48: =_xlfn.XLOOKUP($A48,Inputs!$A:$A,Inputs!K:K,,0) -> 27050 | L48: =_xlfn.XLOOKUP($A48,Inputs!$A:$A,Inputs!L:L,,0) -> 26956 | M48: =_xlfn.XLOOKUP($A48,Inputs!$A:$A,Inputs!M:M,,0) -> 30761
A49: Short-Term Debt | B49: =_xlfn.XLOOKUP($A49,Inputs!$A:$A,Inputs!B:B,,0) -> 150 | C49: =_xlfn.XLOOKUP($A49,Inputs!$A:$A,Inputs!C:C,,0) -> 0 | D49: =_xlfn.XLOOKUP($A49,Inputs!$A:$A,Inputs!D:D,,0) -> 320 | E49: =_xlfn.XLOOKUP($A49,Inputs!$A:$A,Inputs!E:E,,0) -> 0 | F49: =_xlfn.XLOOKUP($A49,Inputs!$A:$A,Inputs!F:F,,0) -> 150 | G49: =_xlfn.XLOOKUP($A49,Inputs!$A:$A,Inputs!G:G,,0) -> 150 | H49: =_xlfn.XLOOKUP($A49,Inputs!$A:$A,Inputs!H:H,,0) -> 168 | I49: =_xlfn.XLOOKUP($A49,Inputs!$A:$A,Inputs!I:I,,0) -> 0 | J49: =_xlfn.XLOOKUP($A49,Inputs!$A:$A,Inputs!J:J,,0) -> 338 | K49: =_xlfn.XLOOKUP($A49,Inputs!$A:$A,Inputs!K:K,,0) -> 447 | L49: =_xlfn.XLOOKUP($A49,Inputs!$A:$A,Inputs!L:L,,0) -> 500 | M49: =_xlfn.XLOOKUP($A49,Inputs!$A:$A,Inputs!M:M,,0) -> 1934
A50: Short-Term Leases | B50: =_xlfn.XLOOKUP($A50,Inputs!$A:$A,Inputs!B:B,,0) -> 9813 | C50: =_xlfn.XLOOKUP($A50,Inputs!$A:$A,Inputs!C:C,,0) -> 7443 | D50: =_xlfn.XLOOKUP($A50,Inputs!$A:$A,Inputs!D:D,,0) -> 5569 | E50: =_xlfn.XLOOKUP($A50,Inputs!$A:$A,Inputs!E:E,,0) -> 10777 | F50: =_xlfn.XLOOKUP($A50,Inputs!$A:$A,Inputs!F:F,,0) -> 7040 | G50: =_xlfn.XLOOKUP($A50,Inputs!$A:$A,Inputs!G:G,,0) -> 3303 | H50: =_xlfn.XLOOKUP($A50,Inputs!$A:$A,Inputs!H:H,,0) -> 2477 | I50: =_xlfn.XLOOKUP($A50,Inputs!$A:$A,Inputs!I:I,,0) -> 6489 | J50: =_xlfn.XLOOKUP($A50,Inputs!$A:$A,Inputs!J:J,,0) -> 2397 | K50: =_xlfn.XLOOKUP($A50,Inputs!$A:$A,Inputs!K:K,,0) -> 3486 | L50: =_xlfn.XLOOKUP($A50,Inputs!$A:$A,Inputs!L:L,,0) -> 3869 | M50: =_xlfn.XLOOKUP($A50,Inputs!$A:$A,Inputs!M:M,,0) -> 2915
A51: Other current liabilities | B51: =_xlfn.XLOOKUP($A51,Inputs!$A:$A,Inputs!B:B,,0) -> 31458 | C51: =_xlfn.XLOOKUP($A51,Inputs!$A:$A,Inputs!C:C,,0) -> 31677 | D51: =_xlfn.XLOOKUP($A51,Inputs!$A:$A,Inputs!D:D,,0) -> 27104 | E51: =_xlfn.XLOOKUP($A51,Inputs!$A:$A,Inputs!E:E,,0) -> 26366 | F51: =_xlfn.XLOOKUP($A51,Inputs!$A:$A,Inputs!F:F,,0) -> 23508 | G51: =_xlfn.XLOOKUP($A51,Inputs!$A:$A,Inputs!G:G,,0) -> 22521 | H51: =_xlfn.XLOOKUP($A51,Inputs!$A:$A,Inputs!H:H,,0) -> 20611 | I51: =_xlfn.XLOOKUP($A51,Inputs!$A:$A,Inputs!I:I,,0) -> 28563 | J51: =_xlfn.XLOOKUP($A51,Inputs!$A:$A,Inputs!J:J,,0) -> 19654 | K51: =_xlfn.XLOOKUP($A51,Inputs!$A:$A,Inputs!K:K,,0) -> 18163 | L51: =_xlfn.XLOOKUP($A51,Inputs!$A:$A,Inputs!L:L,,0) -> 18133 | M51: =_xlfn.XLOOKUP($A51,Inputs!$A:$A,Inputs!M:M,,0) -> 21718
A52: Non-current Liabilities | B52: =_xlfn.XLOOKUP($A52,Inputs!$A:$A,Inputs!B:B,,0) -> 238365 | C52: =_xlfn.XLOOKUP($A52,Inputs!$A:$A,Inputs!C:C,,0) -> 237646 | D52: =_xlfn.XLOOKUP($A52,Inputs!$A:$A,Inputs!D:D,,0) -> 208979 | E52: =_xlfn.XLOOKUP($A52,Inputs!$A:$A,Inputs!E:E,,0) -> 185464 | F52: =_xlfn.XLOOKUP($A52,Inputs!$A:$A,Inputs!F:F,,0) -> 173754 | G52: =_xlfn.XLOOKUP($A52,Inputs!$A:$A,Inputs!G:G,,0) -> 181010 | H52: =_xlfn.XLOOKUP($A52,Inputs!$A:$A,Inputs!H:H,,0) -> 191316 | I52: =_xlfn.XLOOKUP($A52,Inputs!$A:$A,Inputs!I:I,,0) -> 192695 | J52: =_xlfn.XLOOKUP($A52,Inputs!$A:$A,Inputs!J:J,,0) -> 192331 | K52: =_xlfn.XLOOKUP($A52,Inputs!$A:$A,Inputs!K:K,,0) -> 208212 | L52: =_xlfn.XLOOKUP($A52,Inputs!$A:$A,Inputs!L:L,,0) -> 165109 | M52: =_xlfn.XLOOKUP($A52,Inputs!$A:$A,Inputs!M:M,,0) -> 163730
A53: Long-Term Debt | B53: =_xlfn.XLOOKUP($A53,Inputs!$A:$A,Inputs!B:B,,0) -> 139509 | C53: =_xlfn.XLOOKUP($A53,Inputs!$A:$A,Inputs!C:C,,0) -> 142500 | D53: =_xlfn.XLOOKUP($A53,Inputs!$A:$A,Inputs!D:D,,0) -> 122257 | E53: =_xlfn.XLOOKUP($A53,Inputs!$A:$A,Inputs!E:E,,0) -> 99932 | F53: =_xlfn.XLOOKUP($A53,Inputs!$A:$A,Inputs!F:F,,0) -> 105284 | G53: =_xlfn.XLOOKUP($A53,Inputs!$A:$A,Inputs!G:G,,0) -> 113004 | H53: =_xlfn.XLOOKUP($A53,Inputs!$A:$A,Inputs!H:H,,0) -> 104818 | I53: =_xlfn.XLOOKUP($A53,Inputs!$A:$A,Inputs!I:I,,0) -> 103240 | J53: =_xlfn.XLOOKUP($A53,Inputs!$A:$A,Inputs!J:J,,0) -> 110536 | K53: =_xlfn.XLOOKUP($A53,Inputs!$A:$A,Inputs!K:K,,0) -> 89547 | L53: =_xlfn.XLOOKUP($A53,Inputs!$A:$A,Inputs!L:L,,0) -> 47618 | M53: =_xlfn.XLOOKUP($A53,Inputs!$A:$A,Inputs!M:M,,0) -> 50303
A54: Long-Term Leases | B54: =_xlfn.XLOOKUP($A54,Inputs!$A:$A,Inputs!B:B,,0) -> 1167 | C54: =_xlfn.XLOOKUP($A54,Inputs!$A:$A,Inputs!C:C,,0) -> 925 | D54: =_xlfn.XLOOKUP($A54,Inputs!$A:$A,Inputs!D:D,,0) -> 916 | E54: =_xlfn.XLOOKUP($A54,Inputs!$A:$A,Inputs!E:E,,0) -> 780 | F54: =_xlfn.XLOOKUP($A54,Inputs!$A:$A,Inputs!F:F,,0) -> 589 | G54: =_xlfn.XLOOKUP($A54,Inputs!$A:$A,Inputs!G:G,,0) -> 638 | H54: =_xlfn.XLOOKUP($A54,Inputs!$A:$A,Inputs!H:H,,0) -> 615 | I54: =_xlfn.XLOOKUP($A54,Inputs!$A:$A,Inputs!I:I,,0) -> 0 | J54: =_xlfn.XLOOKUP($A54,Inputs!$A:$A,Inputs!J:J,,0) -> 0 | K54: =_xlfn.XLOOKUP($A54,Inputs!$A:$A,Inputs!K:K,,0) -> 111 | L54: =_xlfn.XLOOKUP($A54,Inputs!$A:$A,Inputs!L:L,,0) -> 0 | M54: =_xlfn.XLOOKUP($A54,Inputs!$A:$A,Inputs!M:M,,0) -> 0
A55: Other non-current liabilities | B55: =_xlfn.XLOOKUP($A55,Inputs!$A:$A,Inputs!B:B,,0) -> 97689 | C55: =_xlfn.XLOOKUP($A55,Inputs!$A:$A,Inputs!C:C,,0) -> 94221 | D55: =_xlfn.XLOOKUP($A55,Inputs!$A:$A,Inputs!D:D,,0) -> 85806 | E55: =_xlfn.XLOOKUP($A55,Inputs!$A:$A,Inputs!E:E,,0) -> 84752 | F55: =_xlfn.XLOOKUP($A55,Inputs!$A:$A,Inputs!F:F,,0) -> 67881 | G55: =_xlfn.XLOOKUP($A55,Inputs!$A:$A,Inputs!G:G,,0) -> 67368 | H55: =_xlfn.XLOOKUP($A55,Inputs!$A:$A,Inputs!H:H,,0) -> 85883 | I55: =_xlfn.XLOOKUP($A55,Inputs!$A:$A,Inputs!I:I,,0) -> 89455 | J55: =_xlfn.XLOOKUP($A55,Inputs!$A:$A,Inputs!J:J,,0) -> 81795 | K55: =_xlfn.XLOOKUP($A55,Inputs!$A:$A,Inputs!K:K,,0) -> 118554 | L55: =_xlfn.XLOOKUP($A55,Inputs!$A:$A,Inputs!L:L,,0) -> 117491 | M55: =_xlfn.XLOOKUP($A55,Inputs!$A:$A,Inputs!M:M,,0) -> 113427
A56: Total Liabilities | B56: =_xlfn.XLOOKUP($A56,Inputs!$A:$A,Inputs!B:B,,0) -> 288536 | C56: =_xlfn.XLOOKUP($A56,Inputs!$A:$A,Inputs!C:C,,0) -> 284806 | D56: =_xlfn.XLOOKUP($A56,Inputs!$A:$A,Inputs!D:D,,0) -> 248639 | E56: =_xlfn.XLOOKUP($A56,Inputs!$A:$A,Inputs!E:E,,0) -> 230332 | F56: =_xlfn.XLOOKUP($A56,Inputs!$A:$A,Inputs!F:F,,0) -> 211684 | G56: =_xlfn.XLOOKUP($A56,Inputs!$A:$A,Inputs!G:G,,0) -> 214047 | H56: =_xlfn.XLOOKUP($A56,Inputs!$A:$A,Inputs!H:H,,0) -> 221656 | I56: =_xlfn.XLOOKUP($A56,Inputs!$A:$A,Inputs!I:I,,0) -> 227747 | J56: =_xlfn.XLOOKUP($A56,Inputs!$A:$A,Inputs!J:J,,0) -> 220318 | K56: =_xlfn.XLOOKUP($A56,Inputs!$A:$A,Inputs!K:K,,0) -> 235262 | L56: =_xlfn.XLOOKUP($A56,Inputs!$A:$A,Inputs!L:L,,0) -> 192065 | M56: =_xlfn.XLOOKUP($A56,Inputs!$A:$A,Inputs!M:M,,0) -> 194491
A58: Total Debt | B58: =B49+B53+B50+B54 -> 150639 | C58: =C49+C53+C50+C54 -> 150868 | D58: =D49+D53+D50+D54 -> 129062 | E58: =E49+E53+E50+E54 -> 111489 | F58: =F49+F53+F50+F54 -> 113063 | G58: =G49+G53+G50+G54 -> 117095 | H58: =H49+H53+H50+H54 -> 108078 | I58: =I49+I53+I50+I54 -> 109729 | ... M58: =M49+M53+M50+M54 -> 55152
A59: Debt/Assets | B59: =IFERROR(B58/B44,"-") -> 0.39675253 | C59: =IFERROR(C58/C44,"-") -> 0.4115375 | D59: =IFERROR(D58/D44,"-") -> 0.40780331 | E59: =IFERROR(E58/E44,"-") -> 0.38216895 | F59: =IFERROR(F58/F44,"-") -> 0.42692832 | G59: =IFERROR(G58/G44,"-") -> 0.45536919 | H59: =IFERROR(H58/H44,"-") -> 0.4426161 | I59: =IFERROR(I58/I44,"-") -> 0.44938671 | ... M59: =IFERROR(M58/M44,"-") -> 0.23931164
A60: Net Debt | B60: =B58-B39 -> 148034 | C60: =C58-C39 -> 147947 | D60: =D58-D39 -> 106891 | E60: =E58-E39 -> 108895 | F60: =F58-F39 -> 110318 | G60: =G58-G39 -> 115016 | H60: =H58-H39 -> 105198 | I60: =I58-I39 -> 105259 | ... M60: =M58-M39 -> 41790
A62: Minority Interest | B62: =_xlfn.XLOOKUP($A62,Inputs!$A:$A,Inputs!B:B,,0) -> 1319 | C62: =_xlfn.XLOOKUP($A62,Inputs!$A:$A,Inputs!C:C,,0) -> 1410 | D62: =_xlfn.XLOOKUP($A62,Inputs!$A:$A,Inputs!D:D,,0) -> 1430 | E62: =_xlfn.XLOOKUP($A62,Inputs!$A:$A,Inputs!E:E,,0) -> 1440 | F62: =_xlfn.XLOOKUP($A62,Inputs!$A:$A,Inputs!F:F,,0) -> 1565 | G62: =_xlfn.XLOOKUP($A62,Inputs!$A:$A,Inputs!G:G,,0) -> 1591 | H62: =_xlfn.XLOOKUP($A62,Inputs!$A:$A,Inputs!H:H,,0) -> 1508 | I62: =_xlfn.XLOOKUP($A62,Inputs!$A:$A,Inputs!I:I,,0) -> 1414 | J62: =_xlfn.XLOOKUP($A62,Inputs!$A:$A,Inputs!J:J,,0) -> 1378 | K62: =_xlfn.XLOOKUP($A62,Inputs!$A:$A,Inputs!K:K,,0) -> 56580 | L62: =_xlfn.XLOOKUP($A62,Inputs!$A:$A,Inputs!L:L,,0) -> 52375 | M62: =_xlfn.XLOOKUP($A62,Inputs!$A:$A,Inputs!M:M,,0) -> 49938
A64: Shareholder's Equity | B64: =_xlfn.XLOOKUP($A64,Inputs!$A:$A,Inputs!B:B,,0) -> 89825 | C64: =_xlfn.XLOOKUP($A64,Inputs!$A:$A,Inputs!C:C,,0) -> 80380 | D64: =_xlfn.XLOOKUP($A64,Inputs!$A:$A,Inputs!D:D,,0) -> 66412 | E64: =_xlfn.XLOOKUP($A64,Inputs!$A:$A,Inputs!E:E,,0) -> 59955 | F64: =_xlfn.XLOOKUP($A64,Inputs!$A:$A,Inputs!F:F,,0) -> 51580 | G64: =_xlfn.XLOOKUP($A64,Inputs!$A:$A,Inputs!G:G,,0) -> 41505 | H64: =_xlfn.XLOOKUP($A64,Inputs!$A:$A,Inputs!H:H,,0) -> 21016 | I64: =_xlfn.XLOOKUP($A64,Inputs!$A:$A,Inputs!I:I,,0) -> 15014 | J64: =_xlfn.XLOOKUP($A64,Inputs!$A:$A,Inputs!J:J,,0) -> 10920 | K64: =_xlfn.XLOOKUP($A64,Inputs!$A:$A,Inputs!K:K,,0) -> -17744 | L64: =_xlfn.XLOOKUP($A64,Inputs!$A:$A,Inputs!L:L,,0) -> -19218 | M64: =_xlfn.XLOOKUP($A64,Inputs!$A:$A,Inputs!M:M,,0) -> -13968
A66: Cash Flow
A67: Operating CF | B67: =_xlfn.XLOOKUP($A67,Inputs!$A:$A,Inputs!B:B,,0) -> 37141 | C67: =_xlfn.XLOOKUP($A67,Inputs!$A:$A,Inputs!C:C,,0) -> 39539 | D67: =_xlfn.XLOOKUP($A67,Inputs!$A:$A,Inputs!D:D,,0) -> 41768 | E67: =_xlfn.XLOOKUP($A67,Inputs!$A:$A,Inputs!E:E,,0) -> 35746 | F67: =_xlfn.XLOOKUP($A67,Inputs!$A:$A,Inputs!F:F,,0) -> 34339 | G67: =_xlfn.XLOOKUP($A67,Inputs!$A:$A,Inputs!G:G,,0) -> 24318 | H67: =_xlfn.XLOOKUP($A67,Inputs!$A:$A,Inputs!H:H,,0) -> 21689 | I67: =_xlfn.XLOOKUP($A67,Inputs!$A:$A,Inputs!I:I,,0) -> 39027 | J67: =_xlfn.XLOOKUP($A67,Inputs!$A:$A,Inputs!J:J,,0) -> 30631 | K67: =_xlfn.XLOOKUP($A67,Inputs!$A:$A,Inputs!K:K,,0) -> 38818 | L67: =_xlfn.XLOOKUP($A67,Inputs!$A:$A,Inputs!L:L,,0) -> 31486 | M67: =_xlfn.XLOOKUP($A67,Inputs!$A:$A,Inputs!M:M,,0) -> 29780
A68: Investing CF | B68: =_xlfn.XLOOKUP($A68,Inputs!$A:$A,Inputs!B:B,,0) -> -28662 | C68: =_xlfn.XLOOKUP($A68,Inputs!$A:$A,Inputs!C:C,,0) -> -67153 | D68: =_xlfn.XLOOKUP($A68,Inputs!$A:$A,Inputs!D:D,,0) -> -23512 | E68: =_xlfn.XLOOKUP($A68,Inputs!$A:$A,Inputs!E:E,,0) -> -17581 | F68: =_xlfn.XLOOKUP($A68,Inputs!$A:$A,Inputs!F:F,,0) -> -17934 | G68: =_xlfn.XLOOKUP($A68,Inputs!$A:$A,Inputs!G:G,,0) -> -18456 | H68: =_xlfn.XLOOKUP($A68,Inputs!$A:$A,Inputs!H:H,,0) -> -9874 | I68: =_xlfn.XLOOKUP($A68,Inputs!$A:$A,Inputs!I:I,,0) -> -30043 | J68: =_xlfn.XLOOKUP($A68,Inputs!$A:$A,Inputs!J:J,,0) -> -15856 | K68: =_xlfn.XLOOKUP($A68,Inputs!$A:$A,Inputs!K:K,,0) -> -14833 | L68: =_xlfn.XLOOKUP($A68,Inputs!$A:$A,Inputs!L:L,,0) -> -20502 | M68: =_xlfn.XLOOKUP($A68,Inputs!$A:$A,Inputs!M:M,,0) -> -17250
A69: Net Capex | B69: =_xlfn.XLOOKUP($A69,Inputs!$A:$A,Inputs!B:B,,0) -> -26740 | C69: =_xlfn.XLOOKUP($A69,Inputs!$A:$A,Inputs!C:C,,0) -> -67882 | D69: =_xlfn.XLOOKUP($A69,Inputs!$A:$A,Inputs!D:D,,0) -> -20318 | E69: =_xlfn.XLOOKUP($A69,Inputs!$A:$A,Inputs!E:E,,0) -> -18837 | F69: =_xlfn.XLOOKUP($A69,Inputs!$A:$A,Inputs!F:F,,0) -> -18087 | G69: =_xlfn.XLOOKUP($A69,Inputs!$A:$A,Inputs!G:G,,0) -> -17830 | H69: =_xlfn.XLOOKUP($A69,Inputs!$A:$A,Inputs!H:H,,0) -> -17593 | I69: =_xlfn.XLOOKUP($A69,Inputs!$A:$A,Inputs!I:I,,0) -> -27717 | J69: =_xlfn.XLOOKUP($A69,Inputs!$A:$A,Inputs!J:J,,0) -> -17545 | K69: =_xlfn.XLOOKUP($A69,Inputs!$A:$A,Inputs!K:K,,0) -> -17184 | L69: =_xlfn.XLOOKUP($A69,Inputs!$A:$A,Inputs!L:L,,0) -> -20110 | M69: =_xlfn.XLOOKUP($A69,Inputs!$A:$A,Inputs!M:M,,0) -> -16244
A70: Investments & Acquisitions | B70: =_xlfn.XLOOKUP($A70,Inputs!$A:$A,Inputs!B:B,,0) -> 248 | C70: =_xlfn.XLOOKUP($A70,Inputs!$A:$A,Inputs!C:C,,0) -> -4065 | D70: =_xlfn.XLOOKUP($A70,Inputs!$A:$A,Inputs!D:D,,0) -> -520 | E70: =_xlfn.XLOOKUP($A70,Inputs!$A:$A,Inputs!E:E,,0) -> -29 | F70: =_xlfn.XLOOKUP($A70,Inputs!$A:$A,Inputs!F:F,,0) -> -230 | G70: =_xlfn.XLOOKUP($A70,Inputs!$A:$A,Inputs!G:G,,0) -> -5880 | H70: =_xlfn.XLOOKUP($A70,Inputs!$A:$A,Inputs!H:H,,0) -> -3765 | I70: =_xlfn.XLOOKUP($A70,Inputs!$A:$A,Inputs!I:I,,0) -> -3545 | J70: =_xlfn.XLOOKUP($A70,Inputs!$A:$A,Inputs!J:J,,0) -> -185 | K70: =_xlfn.XLOOKUP($A70,Inputs!$A:$A,Inputs!K:K,,0) -> -494 | L70: =_xlfn.XLOOKUP($A70,Inputs!$A:$A,Inputs!L:L,,0) -> -913 | M70: =_xlfn.XLOOKUP($A70,Inputs!$A:$A,Inputs!M:M,,0) -> -2018
A71: Financing CF | B71: =_xlfn.XLOOKUP($A71,Inputs!$A:$A,Inputs!B:B,,0) -> -8529 | C71: =_xlfn.XLOOKUP($A71,Inputs!$A:$A,Inputs!C:C,,0) -> 8277 | D71: =_xlfn.XLOOKUP($A71,Inputs!$A:$A,Inputs!D:D,,0) -> 1325 | E71: =_xlfn.XLOOKUP($A71,Inputs!$A:$A,Inputs!E:E,,0) -> -18164 | F71: =_xlfn.XLOOKUP($A71,Inputs!$A:$A,Inputs!F:F,,0) -> -15377 | G71: =_xlfn.XLOOKUP($A71,Inputs!$A:$A,Inputs!G:G,,0) -> -6151 | H71: =_xlfn.XLOOKUP($A71,Inputs!$A:$A,Inputs!H:H,,0) -> -13376 | I71: =_xlfn.XLOOKUP($A71,Inputs!$A:$A,Inputs!I:I,,0) -> -15112 | J71: =_xlfn.XLOOKUP($A71,Inputs!$A:$A,Inputs!J:J,,0) -> -57705 | K71: =_xlfn.XLOOKUP($A71,Inputs!$A:$A,Inputs!K:K,,0) -> 26450 | L71: =_xlfn.XLOOKUP($A71,Inputs!$A:$A,Inputs!L:L,,0) -> -21253 | M71: =_xlfn.XLOOKUP($A71,Inputs!$A:$A,Inputs!M:M,,0) -> -5836
A72: Dividends | B72: =_xlfn.XLOOKUP($A72,Inputs!$A:$A,Inputs!B:B,,0) -> -10805 | C72: =_xlfn.XLOOKUP($A72,Inputs!$A:$A,Inputs!C:C,,0) -> -10445 | D72: =_xlfn.XLOOKUP($A72,Inputs!$A:$A,Inputs!D:D,,0) -> -10232 | E72: =_xlfn.XLOOKUP($A72,Inputs!$A:$A,Inputs!E:E,,0) -> -10016 | F72: =_xlfn.XLOOKUP($A72,Inputs!$A:$A,Inputs!F:F,,0) -> -9772 | G72: =_xlfn.XLOOKUP($A72,Inputs!$A:$A,Inputs!G:G,,0) -> -9472 | H72: =_xlfn.XLOOKUP($A72,Inputs!$A:$A,Inputs!H:H,,0) -> -9262 | I72: =_xlfn.XLOOKUP($A72,Inputs!$A:$A,Inputs!I:I,,0) -> -8538 | J72: =_xlfn.XLOOKUP($A72,Inputs!$A:$A,Inputs!J:J,,0) -> -7803 | K72: =_xlfn.XLOOKUP($A72,Inputs!$A:$A,Inputs!K:K,,0) -> -5936 | L72: =_xlfn.XLOOKUP($A72,Inputs!$A:$A,Inputs!L:L,,0) -> -5230 | M72: =_xlfn.XLOOKUP($A72,Inputs!$A:$A,Inputs!M:M,,0) -> -5555
A73: Share buyback | B73: =_xlfn.XLOOKUP($A73,Inputs!$A:$A,Inputs!B:B,,0) -> 0 | C73: =_xlfn.XLOOKUP($A73,Inputs!$A:$A,Inputs!C:C,,0) -> 0 | D73: =_xlfn.XLOOKUP($A73,Inputs!$A:$A,Inputs!D:D,,0) -> 0 | E73: =_xlfn.XLOOKUP($A73,Inputs!$A:$A,Inputs!E:E,,0) -> 0 | F73: =_xlfn.XLOOKUP($A73,Inputs!$A:$A,Inputs!F:F,,0) -> 0 | G73: =_xlfn.XLOOKUP($A73,Inputs!$A:$A,Inputs!G:G,,0) -> 0 | H73: =_xlfn.XLOOKUP($A73,Inputs!$A:$A,Inputs!H:H,,0) -> 0 | I73: =_xlfn.XLOOKUP($A73,Inputs!$A:$A,Inputs!I:I,,0) -> -5134 | J73: =_xlfn.XLOOKUP($A73,Inputs!$A:$A,Inputs!J:J,,0) -> 0 | K73: =_xlfn.XLOOKUP($A73,Inputs!$A:$A,Inputs!K:K,,0) -> -153 | L73: =_xlfn.XLOOKUP($A73,Inputs!$A:$A,Inputs!L:L,,0) -> 0 | M73: =_xlfn.XLOOKUP($A73,Inputs!$A:$A,Inputs!M:M,,0) -> 0
A74: FX | B74: =_xlfn.XLOOKUP($A74,Inputs!$A:$A,Inputs!B:B,,0) -> 0 | C74: =_xlfn.XLOOKUP($A74,Inputs!$A:$A,Inputs!C:C,,0) -> 0 | D74: =_xlfn.XLOOKUP($A74,Inputs!$A:$A,Inputs!D:D,,0) -> 0 | E74: =_xlfn.XLOOKUP($A74,Inputs!$A:$A,Inputs!E:E,,0) -> 0 | F74: =_xlfn.XLOOKUP($A74,Inputs!$A:$A,Inputs!F:F,,0) -> 0 | G74: =_xlfn.XLOOKUP($A74,Inputs!$A:$A,Inputs!G:G,,0) -> 0 | H74: =_xlfn.XLOOKUP($A74,Inputs!$A:$A,Inputs!H:H,,0) -> 0 | I74: =_xlfn.XLOOKUP($A74,Inputs!$A:$A,Inputs!I:I,,0) -> 0 | J74: =_xlfn.XLOOKUP($A74,Inputs!$A:$A,Inputs!J:J,,0) -> 0 | K74: =_xlfn.XLOOKUP($A74,Inputs!$A:$A,Inputs!K:K,,0) -> 0 | L74: =_xlfn.XLOOKUP($A74,Inputs!$A:$A,Inputs!L:L,,0) -> 0 | M74: =_xlfn.XLOOKUP($A74,Inputs!$A:$A,Inputs!M:M,,0) -> 0
A75: Changes in cash | B75: =_xlfn.XLOOKUP($A75,Inputs!$A:$A,Inputs!B:B,,0) -> -50 | C75: =_xlfn.XLOOKUP($A75,Inputs!$A:$A,Inputs!C:C,,0) -> -19337 | D75: =_xlfn.XLOOKUP($A75,Inputs!$A:$A,Inputs!D:D,,0) -> 19581 | E75: =_xlfn.XLOOKUP($A75,Inputs!$A:$A,Inputs!E:E,,0) -> 1 | F75: =_xlfn.XLOOKUP($A75,Inputs!$A:$A,Inputs!F:F,,0) -> 1028 | G75: =_xlfn.XLOOKUP($A75,Inputs!$A:$A,Inputs!G:G,,0) -> -289 | H75: =_xlfn.XLOOKUP($A75,Inputs!$A:$A,Inputs!H:H,,0) -> -1561 | I75: =_xlfn.XLOOKUP($A75,Inputs!$A:$A,Inputs!I:I,,0) -> -6128 | J75: =_xlfn.XLOOKUP($A75,Inputs!$A:$A,Inputs!J:J,,0) -> -42930 | K75: =_xlfn.XLOOKUP($A75,Inputs!$A:$A,Inputs!K:K,,0) -> 50435 | L75: =_xlfn.XLOOKUP($A75,Inputs!$A:$A,Inputs!L:L,,0) -> -10269 | M75: =_xlfn.XLOOKUP($A75,Inputs!$A:$A,Inputs!M:M,,0) -> 6694
A77: Other Data
A78: Number of employees | B78: =_xlfn.XLOOKUP($A78,Inputs!$A:$A,Inputs!B:B,,0) -> #N/A | C78: =_xlfn.XLOOKUP($A78,Inputs!$A:$A,Inputs!C:C,,0) -> #N/A | D78: =_xlfn.XLOOKUP($A78,Inputs!$A:$A,Inputs!D:D,,0) -> #N/A | E78: =_xlfn.XLOOKUP($A78,Inputs!$A:$A,Inputs!E:E,,0) -> #N/A | F78: =_xlfn.XLOOKUP($A78,Inputs!$A:$A,Inputs!F:F,,0) -> #N/A | G78: =_xlfn.XLOOKUP($A78,Inputs!$A:$A,Inputs!G:G,,0) -> #N/A | H78: =_xlfn.XLOOKUP($A78,Inputs!$A:$A,Inputs!H:H,,0) -> #N/A | I78: =_xlfn.XLOOKUP($A78,Inputs!$A:$A,Inputs!I:I,,0) -> #N/A | J78: =_xlfn.XLOOKUP($A78,Inputs!$A:$A,Inputs!J:J,,0) -> #N/A | K78: =_xlfn.XLOOKUP($A78,Inputs!$A:$A,Inputs!K:K,,0) -> #N/A | L78: =_xlfn.XLOOKUP($A78,Inputs!$A:$A,Inputs!L:L,,0) -> #N/A | M78: =_xlfn.XLOOKUP($A78,Inputs!$A:$A,Inputs!M:M,,0) -> #N/A
A79: Shares Outstanding | B79: =_xlfn.XLOOKUP($A79,Inputs!$A:$A,Inputs!B:B,,0) -> #N/A | C79: =_xlfn.XLOOKUP($A79,Inputs!$A:$A,Inputs!C:C,,0) -> #N/A | D79: =_xlfn.XLOOKUP($A79,Inputs!$A:$A,Inputs!D:D,,0) -> #N/A | E79: =_xlfn.XLOOKUP($A79,Inputs!$A:$A,Inputs!E:E,,0) -> #N/A | F79: =_xlfn.XLOOKUP($A79,Inputs!$A:$A,Inputs!F:F,,0) -> #N/A | G79: =_xlfn.XLOOKUP($A79,Inputs!$A:$A,Inputs!G:G,,0) -> #N/A | H79: =_xlfn.XLOOKUP($A79,Inputs!$A:$A,Inputs!H:H,,0) -> #N/A | I79: =_xlfn.XLOOKUP($A79,Inputs!$A:$A,Inputs!I:I,,0) -> #N/A | J79: =_xlfn.XLOOKUP($A79,Inputs!$A:$A,Inputs!J:J,,0) -> #N/A | K79: =_xlfn.XLOOKUP($A79,Inputs!$A:$A,Inputs!K:K,,0) -> #N/A | L79: =_xlfn.XLOOKUP($A79,Inputs!$A:$A,Inputs!L:L,,0) -> #N/A | M79: =_xlfn.XLOOKUP($A79,Inputs!$A:$A,Inputs!M:M,,0) -> #N/A
A80: Float | B80: =_xlfn.XLOOKUP($A80,Inputs!$A:$A,Inputs!B:B,,0) -> 0.9997 | C80: =_xlfn.XLOOKUP($A80,Inputs!$A:$A,Inputs!C:C,,0) -> Yahoo finance | D80: =_xlfn.XLOOKUP($A80,Inputs!$A:$A,Inputs!D:D,,0) -> 0 | E80: =_xlfn.XLOOKUP($A80,Inputs!$A:$A,Inputs!E:E,,0) -> 0 | F80: =_xlfn.XLOOKUP($A80,Inputs!$A:$A,Inputs!F:F,,0) -> 0 | G80: =_xlfn.XLOOKUP($A80,Inputs!$A:$A,Inputs!G:G,,0) -> 0 | H80: =_xlfn.XLOOKUP($A80,Inputs!$A:$A,Inputs!H:H,,0) -> 0 | I80: =_xlfn.XLOOKUP($A80,Inputs!$A:$A,Inputs!I:I,,0) -> 0 | J80: =_xlfn.XLOOKUP($A80,Inputs!$A:$A,Inputs!J:J,,0) -> 0 | K80: =_xlfn.XLOOKUP($A80,Inputs!$A:$A,Inputs!K:K,,0) -> 0 | L80: =_xlfn.XLOOKUP($A80,Inputs!$A:$A,Inputs!L:L,,0) -> 0 | M80: =_xlfn.XLOOKUP($A80,Inputs!$A:$A,Inputs!M:M,,0) -> 0
A81: Insiders Own | B81: =_xlfn.XLOOKUP($A81,Inputs!$A:$A,Inputs!B:B,,0) -> 0.0003 | C81: =_xlfn.XLOOKUP($A81,Inputs!$A:$A,Inputs!C:C,,0) -> Yahoo finance | D81: =_xlfn.XLOOKUP($A81,Inputs!$A:$A,Inputs!D:D,,0) -> 0 | E81: =_xlfn.XLOOKUP($A81,Inputs!$A:$A,Inputs!E:E,,0) -> 0 | F81: =_xlfn.XLOOKUP($A81,Inputs!$A:$A,Inputs!F:F,,0) -> 0 | G81: =_xlfn.XLOOKUP($A81,Inputs!$A:$A,Inputs!G:G,,0) -> 0 | H81: =_xlfn.XLOOKUP($A81,Inputs!$A:$A,Inputs!H:H,,0) -> 0 | I81: =_xlfn.XLOOKUP($A81,Inputs!$A:$A,Inputs!I:I,,0) -> 0 | J81: =_xlfn.XLOOKUP($A81,Inputs!$A:$A,Inputs!J:J,,0) -> 0 | K81: =_xlfn.XLOOKUP($A81,Inputs!$A:$A,Inputs!K:K,,0) -> 0 | L81: =_xlfn.XLOOKUP($A81,Inputs!$A:$A,Inputs!L:L,,0) -> 0 | M81: =_xlfn.XLOOKUP($A81,Inputs!$A:$A,Inputs!M:M,,0) -> 0
A82: Fitch/ S&P Rating | B82: =_xlfn.XLOOKUP($A82,Inputs!$A:$A,Inputs!B:B,,0) -> BBB+ | C82: =_xlfn.XLOOKUP($A82,Inputs!$A:$A,Inputs!C:C,,0) -> 10-K | D82: =_xlfn.XLOOKUP($A82,Inputs!$A:$A,Inputs!D:D,,0) -> 0 | E82: =_xlfn.XLOOKUP($A82,Inputs!$A:$A,Inputs!E:E,,0) -> 0 | F82: =_xlfn.XLOOKUP($A82,Inputs!$A:$A,Inputs!F:F,,0) -> 0 | G82: =_xlfn.XLOOKUP($A82,Inputs!$A:$A,Inputs!G:G,,0) -> 0 | H82: =_xlfn.XLOOKUP($A82,Inputs!$A:$A,Inputs!H:H,,0) -> 0 | I82: =_xlfn.XLOOKUP($A82,Inputs!$A:$A,Inputs!I:I,,0) -> 0 | J82: =_xlfn.XLOOKUP($A82,Inputs!$A:$A,Inputs!J:J,,0) -> 0 | K82: =_xlfn.XLOOKUP($A82,Inputs!$A:$A,Inputs!K:K,,0) -> 0 | L82: =_xlfn.XLOOKUP($A82,Inputs!$A:$A,Inputs!L:L,,0) -> 0 | M82: =_xlfn.XLOOKUP($A82,Inputs!$A:$A,Inputs!M:M,,0) -> 0
A83: Dividend Yield | B83: =_xlfn.XLOOKUP($A83,Inputs!$A:$A,Inputs!B:B,,0) -> #N/A | C83: =_xlfn.XLOOKUP($A83,Inputs!$A:$A,Inputs!C:C,,0) -> #N/A | D83: =_xlfn.XLOOKUP($A83,Inputs!$A:$A,Inputs!D:D,,0) -> #N/A | E83: =_xlfn.XLOOKUP($A83,Inputs!$A:$A,Inputs!E:E,,0) -> #N/A | F83: =_xlfn.XLOOKUP($A83,Inputs!$A:$A,Inputs!F:F,,0) -> #N/A | G83: =_xlfn.XLOOKUP($A83,Inputs!$A:$A,Inputs!G:G,,0) -> #N/A | H83: =_xlfn.XLOOKUP($A83,Inputs!$A:$A,Inputs!H:H,,0) -> #N/A | I83: =_xlfn.XLOOKUP($A83,Inputs!$A:$A,Inputs!I:I,,0) -> #N/A | J83: =_xlfn.XLOOKUP($A83,Inputs!$A:$A,Inputs!J:J,,0) -> #N/A | K83: =_xlfn.XLOOKUP($A83,Inputs!$A:$A,Inputs!K:K,,0) -> #N/A | L83: =_xlfn.XLOOKUP($A83,Inputs!$A:$A,Inputs!L:L,,0) -> #N/A | M83: =_xlfn.XLOOKUP($A83,Inputs!$A:$A,Inputs!M:M,,0) -> #N/A
A84: Daily Volume in Millions of USD | B84: =_xlfn.XLOOKUP($A84,Inputs!$A:$A,Inputs!B:B,,0) -> 0 | C84: =_xlfn.XLOOKUP($A84,Inputs!$A:$A,Inputs!C:C,,0) -> Yahoo Finance | D84: =_xlfn.XLOOKUP($A84,Inputs!$A:$A,Inputs!D:D,,0) -> 0 | E84: =_xlfn.XLOOKUP($A84,Inputs!$A:$A,Inputs!E:E,,0) -> 0 | F84: =_xlfn.XLOOKUP($A84,Inputs!$A:$A,Inputs!F:F,,0) -> 0 | G84: =_xlfn.XLOOKUP($A84,Inputs!$A:$A,Inputs!G:G,,0) -> 0 | H84: =_xlfn.XLOOKUP($A84,Inputs!$A:$A,Inputs!H:H,,0) -> 0 | I84: =_xlfn.XLOOKUP($A84,Inputs!$A:$A,Inputs!I:I,,0) -> 0 | J84: =_xlfn.XLOOKUP($A84,Inputs!$A:$A,Inputs!J:J,,0) -> 0 | K84: =_xlfn.XLOOKUP($A84,Inputs!$A:$A,Inputs!K:K,,0) -> 0 | L84: =_xlfn.XLOOKUP($A84,Inputs!$A:$A,Inputs!L:L,,0) -> 0 | M84: =_xlfn.XLOOKUP($A84,Inputs!$A:$A,Inputs!M:M,,0) -> 0
B86: 2020 | C86: 2021 | D86: 2022
A87: Short % of Float | B87: 0 | C87: 0 | D87: 0
A88: EPS | B88: 0 | C88: 0 | D88: 0
A90: Corporate Bonds 3, 5 Y 10 | B90: Average Price | C90: Moody's | D90: YTM | E90: DIVISA
B91: =VLOOKUP($A91,Inputs!$A$5:$M$98,MATCH(B$4,Inputs!$B$5:$M$5,0)+1,FALSE) -> #N/A | C91: =VLOOKUP($A91,Inputs!$A$5:$M$98,MATCH(C$4,Inputs!$B$5:$M$5,0)+1,FALSE) -> #N/A | D91: =VLOOKUP($A91,Inputs!$A$5:$M$98,MATCH(D$4,Inputs!$B$5:$M$5,0)+1,FALSE) -> #N/A | E91: =VLOOKUP($A91,Inputs!$A$5:$M$98,MATCH(E$4,Inputs!$B$5:$M$5,0)+1,FALSE) -> #N/A

Sheet Fin. Data (Common Size)
A1: =Inputs!H3 -> #VALUE!
A2: =Inputs!G2 -> Figures in Millions of USD
A3: Results
B4: =OP!J19 -> 2022 | C4: =B4-1 -> 2021 | D4: =C4-1 -> 2020 | E4: =D4-1 -> 2019 | F4: =E4-1 -> 2018 | G4: =F4-1 -> 2017 | H4: =G4-1 -> 2016 | I4: =H4-1 -> 2015 | J4: =I4-1 -> 2014 | ... M4: =L4-1 -> 2011
A5: Net Sales | B5: =_xlfn.XLOOKUP($A5,Inputs!$A:$A,Inputs!B:B,,0) -> 136835 | C5: =_xlfn.XLOOKUP($A5,Inputs!$A:$A,Inputs!C:C,,0) -> 133613 | D5: =_xlfn.XLOOKUP($A5,Inputs!$A:$A,Inputs!D:D,,0) -> 128292 | E5: =_xlfn.XLOOKUP($A5,Inputs!$A:$A,Inputs!E:E,,0) -> 131868 | F5: =_xlfn.XLOOKUP($A5,Inputs!$A:$A,Inputs!F:F,,0) -> 130863 | G5: =_xlfn.XLOOKUP($A5,Inputs!$A:$A,Inputs!G:G,,0) -> 126034 | H5: =_xlfn.XLOOKUP($A5,Inputs!$A:$A,Inputs!H:H,,0) -> 125980 | I5: =_xlfn.XLOOKUP($A5,Inputs!$A:$A,Inputs!I:I,,0) -> 131620 | J5: =_xlfn.XLOOKUP($A5,Inputs!$A:$A,Inputs!J:J,,0) -> 127079 | K5: =_xlfn.XLOOKUP($A5,Inputs!$A:$A,Inputs!K:K,,0) -> 120550 | L5: =_xlfn.XLOOKUP($A5,Inputs!$A:$A,Inputs!L:L,,0) -> 115846 | M5: =_xlfn.XLOOKUP($A5,Inputs!$A:$A,Inputs!M:M,,0) -> 110875
A6: Growth vs. Previous year | B6: =IFERROR(B5/C5-1,"-") -> 0.02411442 | C6: =IFERROR(C5/D5-1,"-") -> 0.041475696 | D6: =IFERROR(D5/E5-1,"-") -> -0.027118027 | E6: =IFERROR(E5/F5-1,"-") -> 0.0076797873 | F6: =IFERROR(F5/G5-1,"-") -> 0.038315058 | G6: =IFERROR(G5/H5-1,"-") -> 0.00042863947 | H6: =IFERROR(H5/I5-1,"-") -> -0.042850631 | I6: =IFERROR(I5/J5-1,"-") -> 0.035733677 | ... M6: =IFERROR(M5/N5-1,"-") -> -
A7: Gross Profit | B7: =_xlfn.XLOOKUP($A7,Inputs!$A:$A,Inputs!B:B,,0) -> 77702 | C7: =_xlfn.XLOOKUP($A7,Inputs!$A:$A,Inputs!C:C,,0) -> 77312 | D7: =_xlfn.XLOOKUP($A7,Inputs!$A:$A,Inputs!D:D,,0) -> 77091 | E7: =_xlfn.XLOOKUP($A7,Inputs!$A:$A,Inputs!E:E,,0) -> 77142 | F7: =_xlfn.XLOOKUP($A7,Inputs!$A:$A,Inputs!F:F,,0) -> 75658 | G7: =_xlfn.XLOOKUP($A7,Inputs!$A:$A,Inputs!G:G,,0) -> 73142 | H7: =_xlfn.XLOOKUP($A7,Inputs!$A:$A,Inputs!H:H,,0) -> 73279 | I7: =_xlfn.XLOOKUP($A7,Inputs!$A:$A,Inputs!I:I,,0) -> 79063 | J7: =_xlfn.XLOOKUP($A7,Inputs!$A:$A,Inputs!J:J,,0) -> 77175 | K7: =_xlfn.XLOOKUP($A7,Inputs!$A:$A,Inputs!K:K,,0) -> 75663 | L7: =_xlfn.XLOOKUP($A7,Inputs!$A:$A,Inputs!L:L,,0) -> 69611 | M7: =_xlfn.XLOOKUP($A7,Inputs!$A:$A,Inputs!M:M,,0) -> 65000
A8: % over sales | B8: =IFERROR(B7/B$5,"-") -> 0.56785179 | C8: =IFERROR(C7/C$5,"-") -> 0.57862633 | D8: =IFERROR(D7/D$5,"-") -> 0.60090263 | E8: =IFERROR(E7/E$5,"-") -> 0.58499408 | F8: =IFERROR(F7/F$5,"-") -> 0.57814661 | G8: =IFERROR(G7/G$5,"-") -> 0.58033547 | H8: =IFERROR(H7/H$5,"-") -> 0.58167169 | I8: =IFERROR(I7/I$5,"-") -> 0.60069138 | ... M8: =IFERROR(M7/M$5,"-") -> 0.58624577
A9: Operating expenses | B9: =B5-B11 -> 106368 | C9: =C5-C11 -> 101165 | D9: =D5-D11 -> 99494 | E9: =E5-E11 -> 101490 | F9: =F5-F11 -> 108585 | G9: =G5-G11 -> 98609 | H9: =H5-H11 -> 98921 | I9: =I5-I11 -> 98560 | ... M9: =M5-M11 -> 97995
A10: % over sales | B10: =IFERROR(B9/B$5,"-") -> 0.77734498 | C10: =IFERROR(C9/C$5,"-") -> 0.75714938 | D10: =IFERROR(D9/D$5,"-") -> 0.7755277 | E10: =IFERROR(E9/E$5,"-") -> 0.76963327 | F10: =IFERROR(F9/F$5,"-") -> 0.82976089 | G10: =IFERROR(G9/G$5,"-") -> 0.78239999 | H10: =IFERROR(H9/H$5,"-") -> 0.78521194 | I10: =IFERROR(I9/I$5,"-") -> 0.74882237 | ... M10: =IFERROR(M9/M$5,"-") -> 0.88383315
A11: Operating Income | B11: =_xlfn.XLOOKUP($A11,Inputs!$A:$A,Inputs!B:B,,0) -> 30467 | C11: =_xlfn.XLOOKUP($A11,Inputs!$A:$A,Inputs!C:C,,0) -> 32448 | D11: =_xlfn.XLOOKUP($A11,Inputs!$A:$A,Inputs!D:D,,0) -> 28798 | E11: =_xlfn.XLOOKUP($A11,Inputs!$A:$A,Inputs!E:E,,0) -> 30378 | F11: =_xlfn.XLOOKUP($A11,Inputs!$A:$A,Inputs!F:F,,0) -> 22278 | G11: =_xlfn.XLOOKUP($A11,Inputs!$A:$A,Inputs!G:G,,0) -> 27425 | H11: =_xlfn.XLOOKUP($A11,Inputs!$A:$A,Inputs!H:H,,0) -> 27059 | I11: =_xlfn.XLOOKUP($A11,Inputs!$A:$A,Inputs!I:I,,0) -> 33060 | J11: =_xlfn.XLOOKUP($A11,Inputs!$A:$A,Inputs!J:J,,0) -> 19599 | K11: =_xlfn.XLOOKUP($A11,Inputs!$A:$A,Inputs!K:K,,0) -> 31968 | L11: =_xlfn.XLOOKUP($A11,Inputs!$A:$A,Inputs!L:L,,0) -> 13160 | M11: =_xlfn.XLOOKUP($A11,Inputs!$A:$A,Inputs!M:M,,0) -> 12880
A12: % over sales | B12: =IFERROR(B11/B$5,"-") -> 0.22265502 | C12: =IFERROR(C11/C$5,"-") -> 0.24285062 | D12: =IFERROR(D11/D$5,"-") -> 0.2244723 | E12: =IFERROR(E11/E$5,"-") -> 0.23036673 | F12: =IFERROR(F11/F$5,"-") -> 0.17023911 | G12: =IFERROR(G11/G$5,"-") -> 0.21760001 | H12: =IFERROR(H11/H$5,"-") -> 0.21478806 | I12: =IFERROR(I11/I$5,"-") -> 0.25117763 | ... M12: =IFERROR(M11/M$5,"-") -> 0.11616685
A13: Growth vs. Previous year | B13: =IFERROR(B12/C12-1,"-") -> -0.083160579 | C13: =IFERROR(C12/D12-1,"-") -> 0.081873458 | D13: =IFERROR(D12/E12-1,"-") -> -0.02558717 | E13: =IFERROR(E12/F12-1,"-") -> 0.35319514 | F13: =IFERROR(F12/G12-1,"-") -> -0.21765122 | G13: =IFERROR(G12/H12-1,"-") -> 0.013091748 | H13: =IFERROR(H12/I12-1,"-") -> -0.14487584 | I13: =IFERROR(I12/J12-1,"-") -> 0.62862403 | ... M13: =IFERROR(M12/N12-1,"-") -> -
A14: Net Financial Cost | B14: =_xlfn.XLOOKUP($A14,Inputs!$A:$A,Inputs!B:B,,0) -> -3569 | C14: =_xlfn.XLOOKUP($A14,Inputs!$A:$A,Inputs!C:C,,0) -> -3340 | D14: =_xlfn.XLOOKUP($A14,Inputs!$A:$A,Inputs!D:D,,0) -> -4247 | E14: =_xlfn.XLOOKUP($A14,Inputs!$A:$A,Inputs!E:E,,0) -> -4730 | F14: =_xlfn.XLOOKUP($A14,Inputs!$A:$A,Inputs!F:F,,0) -> -4833 | G14: =_xlfn.XLOOKUP($A14,Inputs!$A:$A,Inputs!G:G,,0) -> -4733 | H14: =_xlfn.XLOOKUP($A14,Inputs!$A:$A,Inputs!H:H,,0) -> -4376 | I14: =_xlfn.XLOOKUP($A14,Inputs!$A:$A,Inputs!I:I,,0) -> -4920 | J14: =_xlfn.XLOOKUP($A14,Inputs!$A:$A,Inputs!J:J,,0) -> -4915 | K14: =_xlfn.XLOOKUP($A14,Inputs!$A:$A,Inputs!K:K,,0) -> -2667 | L14: =_xlfn.XLOOKUP($A14,Inputs!$A:$A,Inputs!L:L,,0) -> -2571 | M14: =_xlfn.XLOOKUP($A14,Inputs!$A:$A,Inputs!M:M,,0) -> -2827
A15: Other Expenses (Revenues) | B15: =_xlfn.XLOOKUP($A15,Inputs!$A:$A,Inputs!B:B,,0) -> 1373 | C15: =_xlfn.XLOOKUP($A15,Inputs!$A:$A,Inputs!C:C,,0) -> 312 | D15: =_xlfn.XLOOKUP($A15,Inputs!$A:$A,Inputs!D:D,,0) -> -584 | E15: =_xlfn.XLOOKUP($A15,Inputs!$A:$A,Inputs!E:E,,0) -> -2915 | F15: =_xlfn.XLOOKUP($A15,Inputs!$A:$A,Inputs!F:F,,0) -> 2178 | G15: =_xlfn.XLOOKUP($A15,Inputs!$A:$A,Inputs!G:G,,0) -> -2098 | H15: =_xlfn.XLOOKUP($A15,Inputs!$A:$A,Inputs!H:H,,0) -> -1697 | I15: =_xlfn.XLOOKUP($A15,Inputs!$A:$A,Inputs!I:I,,0) -> 100 | J15: =_xlfn.XLOOKUP($A15,Inputs!$A:$A,Inputs!J:J,,0) -> 586 | K15: =_xlfn.XLOOKUP($A15,Inputs!$A:$A,Inputs!K:K,,0) -> -24 | L15: =_xlfn.XLOOKUP($A15,Inputs!$A:$A,Inputs!L:L,,0) -> -692 | M15: =_xlfn.XLOOKUP($A15,Inputs!$A:$A,Inputs!M:M,,0) -> 430
A16: EBIT | B16: =B11-B15 -> 29094 | C16: =C11-C15 -> 32136 | D16: =D11-D15 -> 29382 | E16: =E11-E15 -> 33293 | F16: =F11-F15 -> 20100 | G16: =G11-G15 -> 29523 | H16: =H11-H15 -> 28756 | I16: =I11-I15 -> 32960 | ... M16: =M11-M15 -> 12450
A17: Depreciation and Amortization | B17: ='Fin. Data'!B17 -> 17099 | C17: ='Fin. Data'!C17 -> 16206 | D17: ='Fin. Data'!D17 -> 16720 | E17: ='Fin. Data'!E17 -> 16682 | F17: ='Fin. Data'!F17 -> 17403 | G17: ='Fin. Data'!G17 -> 16954 | H17: ='Fin. Data'!H17 -> 15928 | I17: ='Fin. Data'!I17 -> 16017 | ... M17: ='Fin. Data'!M17 -> 16496
A18: Changes Net Working Capital | B18: =_xlfn.XLOOKUP($A18,Inputs!$A:$A,Inputs!B:B,,0) -> -1566 | C18: =_xlfn.XLOOKUP($A18,Inputs!$A:$A,Inputs!C:C,,0) -> -6116 | D18: =_xlfn.XLOOKUP($A18,Inputs!$A:$A,Inputs!D:D,,0) -> 2752 | E18: =_xlfn.XLOOKUP($A18,Inputs!$A:$A,Inputs!E:E,,0) -> -3950 | F18: =_xlfn.XLOOKUP($A18,Inputs!$A:$A,Inputs!F:F,,0) -> -836 | G18: =_xlfn.XLOOKUP($A18,Inputs!$A:$A,Inputs!G:G,,0) -> 1622 | H18: =_xlfn.XLOOKUP($A18,Inputs!$A:$A,Inputs!H:H,,0) -> 10417 | I18: =_xlfn.XLOOKUP($A18,Inputs!$A:$A,Inputs!I:I,,0) -> -8156 | J18: =_xlfn.XLOOKUP($A18,Inputs!$A:$A,Inputs!J:J,,0) -> 498 | K18: =_xlfn.XLOOKUP($A18,Inputs!$A:$A,Inputs!K:K,,0) -> -770 | L18: =_xlfn.XLOOKUP($A18,Inputs!$A:$A,Inputs!L:L,,0) -> 4370 | M18: =_xlfn.XLOOKUP($A18,Inputs!$A:$A,Inputs!M:M,,0) -> 0
A19: EBITDA | B19: =B11-B15+B17 -> 46193 | C19: =C11-C15+C17 -> 48342 | D19: =D11-D15+D17 -> 46102 | E19: =E11-E15+E17 -> 49975 | F19: =F11-F15+F17 -> 37503 | G19: =G11-G15+G17 -> 46477 | H19: =H11-H15+H17 -> 44684 | I19: =I11-I15+I17 -> 48977 | ... M19: =M11-M15+M17 -> 28946
A20: % over sales | B20: =IFERROR(B19/B$5,"-") -> 0.33758176 | C20: =IFERROR(C19/C$5,"-") -> 0.36180611 | D20: =IFERROR(D19/D$5,"-") -> 0.3593521 | E20: =IFERROR(E19/E$5,"-") -> 0.37897746 | F20: =IFERROR(F19/F$5,"-") -> 0.28658215 | G20: =IFERROR(G19/G$5,"-") -> 0.36876557 | H20: =IFERROR(H19/H$5,"-") -> 0.35469122 | I20: =IFERROR(I19/I$5,"-") -> 0.3721091 | ... M20: =IFERROR(M19/M$5,"-") -> 0.26106877
A21: Taxes | B21: =_xlfn.XLOOKUP($A21,Inputs!$A:$A,Inputs!B:B,,0) -> -6523 | C21: =_xlfn.XLOOKUP($A21,Inputs!$A:$A,Inputs!C:C,,0) -> -6802 | D21: =_xlfn.XLOOKUP($A21,Inputs!$A:$A,Inputs!D:D,,0) -> -5619 | E21: =_xlfn.XLOOKUP($A21,Inputs!$A:$A,Inputs!E:E,,0) -> -2945 | F21: =_xlfn.XLOOKUP($A21,Inputs!$A:$A,Inputs!F:F,,0) -> -3584 | G21: =_xlfn.XLOOKUP($A21,Inputs!$A:$A,Inputs!G:G,,0) -> 9956 | H21: =_xlfn.XLOOKUP($A21,Inputs!$A:$A,Inputs!H:H,,0) -> -7378 | I21: =_xlfn.XLOOKUP($A21,Inputs!$A:$A,Inputs!I:I,,0) -> -9865 | J21: =_xlfn.XLOOKUP($A21,Inputs!$A:$A,Inputs!J:J,,0) -> -3314 | K21: =_xlfn.XLOOKUP($A21,Inputs!$A:$A,Inputs!K:K,,0) -> -5730 | L21: =_xlfn.XLOOKUP($A21,Inputs!$A:$A,Inputs!L:L,,0) -> 660 | M21: =_xlfn.XLOOKUP($A21,Inputs!$A:$A,Inputs!M:M,,0) -> -285
A22: % Tax | B22: =IFERROR(B21/B$5,"-") -> -0.047670552 | C22: =IFERROR(C21/C$5,"-") -> -0.05090822 | D22: =IFERROR(D21/D$5,"-") -> -0.043798522 | E22: =IFERROR(E21/E$5,"-") -> -0.022332939 | F22: =IFERROR(F21/F$5,"-") -> -0.02738742 | G22: =IFERROR(G21/G$5,"-") -> 0.078994557 | H22: =IFERROR(H21/H$5,"-") -> -0.058564852 | I22: =IFERROR(I21/I$5,"-") -> -0.074950615 | ... M22: =IFERROR(M21/M$5,"-") -> -0.0025704622
A23: Net income | B23: =_xlfn.XLOOKUP($A23,Inputs!$A:$A,Inputs!B:B,,0) -> 21748 | C23: =_xlfn.XLOOKUP($A23,Inputs!$A:$A,Inputs!C:C,,0) -> 22618 | D23: =_xlfn.XLOOKUP($A23,Inputs!$A:$A,Inputs!D:D,,0) -> 18348 | E23: =_xlfn.XLOOKUP($A23,Inputs!$A:$A,Inputs!E:E,,0) -> 19788 | F23: =_xlfn.XLOOKUP($A23,Inputs!$A:$A,Inputs!F:F,,0) -> 16039 | G23: =_xlfn.XLOOKUP($A23,Inputs!$A:$A,Inputs!G:G,,0) -> 30550 | H23: =_xlfn.XLOOKUP($A23,Inputs!$A:$A,Inputs!H:H,,0) -> 13608 | I23: =_xlfn.XLOOKUP($A23,Inputs!$A:$A,Inputs!I:I,,0) -> 18375 | J23: =_xlfn.XLOOKUP($A23,Inputs!$A:$A,Inputs!J:J,,0) -> 11956 | K23: =_xlfn.XLOOKUP($A23,Inputs!$A:$A,Inputs!K:K,,0) -> 23547 | L23: =_xlfn.XLOOKUP($A23,Inputs!$A:$A,Inputs!L:L,,0) -> 10557 | M23: =_xlfn.XLOOKUP($A23,Inputs!$A:$A,Inputs!M:M,,0) -> 10198
A24: % over sales | B24: =IFERROR(B23/B$5,"-") -> 0.15893594 | C24: =IFERROR(C23/C$5,"-") -> 0.16927994 | D24: =IFERROR(D23/D$5,"-") -> 0.14301749 | E24: =IFERROR(E23/E$5,"-") -> 0.15005915 | F24: =IFERROR(F23/F$5,"-") -> 0.12256329 | G24: =IFERROR(G23/G$5,"-") -> 0.24239491 | H24: =IFERROR(H23/H$5,"-") -> 0.10801715 | I24: =IFERROR(I23/I$5,"-") -> 0.13960644 | ... M24: =IFERROR(M23/M$5,"-") -> 0.091977452
A25: Growth vs. Previous year | B25: =IFERROR(B24/C24-1,"-") -> -0.061105828 | C25: =IFERROR(C24/D24-1,"-") -> 0.18363099 | D25: =IFERROR(D24/E24-1,"-") -> -0.046925887 | E25: =IFERROR(E24/F24-1,"-") -> 0.22434008 | F25: =IFERROR(F24/G24-1,"-") -> -0.49436524 | G25: =IFERROR(G24/H24-1,"-") -> 1.2440411 | H25: =IFERROR(H24/I24-1,"-") -> -0.22627392 | I25: =IFERROR(I24/J24-1,"-") -> 0.48386142 | ... M25: =IFERROR(M24/N24-1,"-") -> -
A26: Cash Generated | B26: =B39-C39 -> -316 | C26: =C39-D39 -> -19250 | D26: =D39-E39 -> 19577 | E26: =E39-F39 -> -151 | F26: =F39-G39 -> 666 | G26: =G39-H39 -> -801 | H26: =H39-I39 -> -1590 | I26: =I39-J39 -> -6128 | ... M26: =M39-N39 -> 13362
A27: Dividends | B27: =_xlfn.XLOOKUP($A27,Inputs!$A:$A,Inputs!B:B,,0) -> -10805 | C27: =_xlfn.XLOOKUP($A27,Inputs!$A:$A,Inputs!C:C,,0) -> -10445 | D27: =_xlfn.XLOOKUP($A27,Inputs!$A:$A,Inputs!D:D,,0) -> -10232 | E27: =_xlfn.XLOOKUP($A27,Inputs!$A:$A,Inputs!E:E,,0) -> -10016 | F27: =_xlfn.XLOOKUP($A27,Inputs!$A:$A,Inputs!F:F,,0) -> -9772 | G27: =_xlfn.XLOOKUP($A27,Inputs!$A:$A,Inputs!G:G,,0) -> -9472 | H27: =_xlfn.XLOOKUP($A27,Inputs!$A:$A,Inputs!H:H,,0) -> -9262 | I27: =_xlfn.XLOOKUP($A27,Inputs!$A:$A,Inputs!I:I,,0) -> -8538 | J27: =_xlfn.XLOOKUP($A27,Inputs!$A:$A,Inputs!J:J,,0) -> -7803 | K27: =_xlfn.XLOOKUP($A27,Inputs!$A:$A,Inputs!K:K,,0) -> -5936 | L27: =_xlfn.XLOOKUP($A27,Inputs!$A:$A,Inputs!L:L,,0) -> -5230 | M27: =_xlfn.XLOOKUP($A27,Inputs!$A:$A,Inputs!M:M,,0) -> -5555
A28: Share buyback | B28: =_xlfn.XLOOKUP($A28,Inputs!$A:$A,Inputs!B:B,,0) -> 0 | C28: =_xlfn.XLOOKUP($A28,Inputs!$A:$A,Inputs!C:C,,0) -> 0 | D28: =_xlfn.XLOOKUP($A28,Inputs!$A:$A,Inputs!D:D,,0) -> 0 | E28: =_xlfn.XLOOKUP($A28,Inputs!$A:$A,Inputs!E:E,,0) -> 0 | F28: =_xlfn.XLOOKUP($A28,Inputs!$A:$A,Inputs!F:F,,0) -> 0 | G28: =_xlfn.XLOOKUP($A28,Inputs!$A:$A,Inputs!G:G,,0) -> 0 | H28: =_xlfn.XLOOKUP($A28,Inputs!$A:$A,Inputs!H:H,,0) -> 0 | I28: =_xlfn.XLOOKUP($A28,Inputs!$A:$A,Inputs!I:I,,0) -> -5134 | J28: =_xlfn.XLOOKUP($A28,Inputs!$A:$A,Inputs!J:J,,0) -> 0 | K28: =_xlfn.XLOOKUP($A28,Inputs!$A:$A,Inputs!K:K,,0) -> -153 | L28: =_xlfn.XLOOKUP($A28,Inputs!$A:$A,Inputs!L:L,,0) -> 0 | M28: =_xlfn.XLOOKUP($A28,Inputs!$A:$A,Inputs!M:M,,0) -> 0
A29: FNP | B29: =SUM(B26:B28) -> -11121 | C29: =SUM(C26:C28) -> -29695 | D29: =SUM(D26:D28) -> 9345 | E29: =SUM(E26:E28) -> -10167 | F29: =SUM(F26:F28) -> -9106 | G29: =SUM(G26:G28) -> -10273 | H29: =SUM(H26:H28) -> -10852 | I29: =SUM(I26:I28) -> -19800 | ... M29: =SUM(M26:M28) -> 7807
A30: FNP'' | B30: =+B29-(B58-C29) -> -180475 | C30: =+C29-(C58-D29) -> -162850 | D30: =+D29-(D58-E29) -> -123399 | E30: =+E29-(E58-F29) -> -119205 | F30: =+F29-(F58-G29) -> -124813 | G30: =+G29-(G58-H29) -> -134279 | H30: =+H29-(H58-I29) -> -135638 | I30: =+I29-(I58-J29) -> -173773 | ... M30: =+M29-(M58-N29) -> -44430
A31: FNP' | B31: =+B30+B33 -> -180227 | C31: =+C30+C33 -> -166915 | D31: =+D30+D33 -> -123919 | E31: =+E30+E33 -> -119234 | F31: =+F30+F33 -> -125043 | G31: =+G30+G33 -> -140159 | H31: =+H30+H33 -> -139403 | I31: =+I30+I33 -> -177318 | ... M31: =+M30+M33 -> -46448
A32: Net Capex | B32: =_xlfn.XLOOKUP($A32,Inputs!$A:$A,Inputs!B:B,,0) -> -26740 | C32: =_xlfn.XLOOKUP($A32,Inputs!$A:$A,Inputs!C:C,,0) -> -67882 | D32: =_xlfn.XLOOKUP($A32,Inputs!$A:$A,Inputs!D:D,,0) -> -20318 | E32: =_xlfn.XLOOKUP($A32,Inputs!$A:$A,Inputs!E:E,,0) -> -18837 | F32: =_xlfn.XLOOKUP($A32,Inputs!$A:$A,Inputs!F:F,,0) -> -18087 | G32: =_xlfn.XLOOKUP($A32,Inputs!$A:$A,Inputs!G:G,,0) -> -17830 | H32: =_xlfn.XLOOKUP($A32,Inputs!$A:$A,Inputs!H:H,,0) -> -17593 | I32: =_xlfn.XLOOKUP($A32,Inputs!$A:$A,Inputs!I:I,,0) -> -27717 | J32: =_xlfn.XLOOKUP($A32,Inputs!$A:$A,Inputs!J:J,,0) -> -17545 | K32: =_xlfn.XLOOKUP($A32,Inputs!$A:$A,Inputs!K:K,,0) -> -17184 | L32: =_xlfn.XLOOKUP($A32,Inputs!$A:$A,Inputs!L:L,,0) -> -20110 | M32: =_xlfn.XLOOKUP($A32,Inputs!$A:$A,Inputs!M:M,,0) -> -16244
A33: Investments & Acquisitions | B33: =_xlfn.XLOOKUP($A33,Inputs!$A:$A,Inputs!B:B,,0) -> 248 | C33: =_xlfn.XLOOKUP($A33,Inputs!$A:$A,Inputs!C:C,,0) -> -4065 | D33: =_xlfn.XLOOKUP($A33,Inputs!$A:$A,Inputs!D:D,,0) -> -520 | E33: =_xlfn.XLOOKUP($A33,Inputs!$A:$A,Inputs!E:E,,0) -> -29 | F33: =_xlfn.XLOOKUP($A33,Inputs!$A:$A,Inputs!F:F,,0) -> -230 | G33: =_xlfn.XLOOKUP($A33,Inputs!$A:$A,Inputs!G:G,,0) -> -5880 | H33: =_xlfn.XLOOKUP($A33,Inputs!$A:$A,Inputs!H:H,,0) -> -3765 | I33: =_xlfn.XLOOKUP($A33,Inputs!$A:$A,Inputs!I:I,,0) -> -3545 | J33: =_xlfn.XLOOKUP($A33,Inputs!$A:$A,Inputs!J:J,,0) -> -185 | K33: =_xlfn.XLOOKUP($A33,Inputs!$A:$A,Inputs!K:K,,0) -> -494 | L33: =_xlfn.XLOOKUP($A33,Inputs!$A:$A,Inputs!L:L,,0) -> -913 | M33: =_xlfn.XLOOKUP($A33,Inputs!$A:$A,Inputs!M:M,,0) -> -2018
A34: Capex + Investments | B34: =+B32+B33 -> -26492 | C34: =+C32+C33 -> -71947 | D34: =+D32+D33 -> -20838 | E34: =+E32+E33 -> -18866 | F34: =+F32+F33 -> -18317 | G34: =+G32+G33 -> -23710 | H34: =+H32+H33 -> -21358 | I34: =+I32+I33 -> -31262 | ... M34: =+M32+M33 -> -18262
A35: Dividends + Share Buyback | B35: =+B27+B28 -> -10805 | C35: =+C27+C28 -> -10445 | D35: =+D27+D28 -> -10232 | E35: =+E27+E28 -> -10016 | F35: =+F27+F28 -> -9772 | G35: =+G27+G28 -> -9472 | H35: =+H27+H28 -> -9262 | I35: =+I27+I28 -> -13672 | ... M35: =+M27+M28 -> -5555
A36: Payout Ratio | B36: =IFERROR(B35/B23,"-") -> -0.49682729 | C36: =IFERROR(C35/C23,"-") -> -0.46180034 | D36: =IFERROR(D35/D23,"-") -> -0.55766296 | E36: =IFERROR(E35/E23,"-") -> -0.50616535 | F36: =IFERROR(F35/F23,"-") -> -0.60926492 | G36: =IFERROR(G35/G23,"-") -> -0.3100491 | H36: =IFERROR(H35/H23,"-") -> -0.68062904 | I36: =IFERROR(I35/I23,"-") -> -0.74405442 | ... M36: =IFERROR(M35/M23,"-") -> -0.54471465
A38: Assets
A39: Cash & Eq. | B39: =_xlfn.XLOOKUP($A39,Inputs!$A:$A,Inputs!B:B,,0) -> 2605 | C39: =_xlfn.XLOOKUP($A39,Inputs!$A:$A,Inputs!C:C,,0) -> 2921 | D39: =_xlfn.XLOOKUP($A39,Inputs!$A:$A,Inputs!D:D,,0) -> 22171 | E39: =_xlfn.XLOOKUP($A39,Inputs!$A:$A,Inputs!E:E,,0) -> 2594 | F39: =_xlfn.XLOOKUP($A39,Inputs!$A:$A,Inputs!F:F,,0) -> 2745 | G39: =_xlfn.XLOOKUP($A39,Inputs!$A:$A,Inputs!G:G,,0) -> 2079 | H39: =_xlfn.XLOOKUP($A39,Inputs!$A:$A,Inputs!H:H,,0) -> 2880 | I39: =_xlfn.XLOOKUP($A39,Inputs!$A:$A,Inputs!I:I,,0) -> 4470 | J39: =_xlfn.XLOOKUP($A39,Inputs!$A:$A,Inputs!J:J,,0) -> 10598 | K39: =_xlfn.XLOOKUP($A39,Inputs!$A:$A,Inputs!K:K,,0) -> 53528 | L39: =_xlfn.XLOOKUP($A39,Inputs!$A:$A,Inputs!L:L,,0) -> 3093 | M39: =_xlfn.XLOOKUP($A39,Inputs!$A:$A,Inputs!M:M,,0) -> 13362
A40: Accounts Receivable | B40: =_xlfn.XLOOKUP($A40,Inputs!$A:$A,Inputs!B:B,,0) -> 24506 | C40: =_xlfn.XLOOKUP($A40,Inputs!$A:$A,Inputs!C:C,,0) -> 24585 | D40: =_xlfn.XLOOKUP($A40,Inputs!$A:$A,Inputs!D:D,,0) -> 24650 | E40: =_xlfn.XLOOKUP($A40,Inputs!$A:$A,Inputs!E:E,,0) -> 26277 | F40: =_xlfn.XLOOKUP($A40,Inputs!$A:$A,Inputs!F:F,,0) -> 25859 | G40: =_xlfn.XLOOKUP($A40,Inputs!$A:$A,Inputs!G:G,,0) -> 23493 | H40: =_xlfn.XLOOKUP($A40,Inputs!$A:$A,Inputs!H:H,,0) -> 17513 | I40: =_xlfn.XLOOKUP($A40,Inputs!$A:$A,Inputs!I:I,,0) -> 13457 | J40: =_xlfn.XLOOKUP($A40,Inputs!$A:$A,Inputs!J:J,,0) -> 13993 | K40: =_xlfn.XLOOKUP($A40,Inputs!$A:$A,Inputs!K:K,,0) -> 12439 | L40: =_xlfn.XLOOKUP($A40,Inputs!$A:$A,Inputs!L:L,,0) -> 12576 | M40: =_xlfn.XLOOKUP($A40,Inputs!$A:$A,Inputs!M:M,,0) -> 11776
A41: Inventory | B41: =_xlfn.XLOOKUP($A41,Inputs!$A:$A,Inputs!B:B,,0) -> 2388 | C41: =_xlfn.XLOOKUP($A41,Inputs!$A:$A,Inputs!C:C,,0) -> 3055 | D41: =_xlfn.XLOOKUP($A41,Inputs!$A:$A,Inputs!D:D,,0) -> 1796 | E41: =_xlfn.XLOOKUP($A41,Inputs!$A:$A,Inputs!E:E,,0) -> 1422 | F41: =_xlfn.XLOOKUP($A41,Inputs!$A:$A,Inputs!F:F,,0) -> 1336 | G41: =_xlfn.XLOOKUP($A41,Inputs!$A:$A,Inputs!G:G,,0) -> 1034 | H41: =_xlfn.XLOOKUP($A41,Inputs!$A:$A,Inputs!H:H,,0) -> 1202 | I41: =_xlfn.XLOOKUP($A41,Inputs!$A:$A,Inputs!I:I,,0) -> 1252 | J41: =_xlfn.XLOOKUP($A41,Inputs!$A:$A,Inputs!J:J,,0) -> 1153 | K41: =_xlfn.XLOOKUP($A41,Inputs!$A:$A,Inputs!K:K,,0) -> 1020 | L41: =_xlfn.XLOOKUP($A41,Inputs!$A:$A,Inputs!L:L,,0) -> 1075 | M41: =_xlfn.XLOOKUP($A41,Inputs!$A:$A,Inputs!M:M,,0) -> 940
A42: Property, Plant and Equipment | B42: =_xlfn.XLOOKUP($A42,Inputs!$A:$A,Inputs!B:B,,0) -> 133564 | C42: =_xlfn.XLOOKUP($A42,Inputs!$A:$A,Inputs!C:C,,0) -> 127579 | D42: =_xlfn.XLOOKUP($A42,Inputs!$A:$A,Inputs!D:D,,0) -> 117364 | E42: =_xlfn.XLOOKUP($A42,Inputs!$A:$A,Inputs!E:E,,0) -> 114609 | F42: =_xlfn.XLOOKUP($A42,Inputs!$A:$A,Inputs!F:F,,0) -> 89286 | G42: =_xlfn.XLOOKUP($A42,Inputs!$A:$A,Inputs!G:G,,0) -> 88568 | H42: =_xlfn.XLOOKUP($A42,Inputs!$A:$A,Inputs!H:H,,0) -> 84751 | I42: =_xlfn.XLOOKUP($A42,Inputs!$A:$A,Inputs!I:I,,0) -> 83541 | J42: =_xlfn.XLOOKUP($A42,Inputs!$A:$A,Inputs!J:J,,0) -> 89947 | K42: =_xlfn.XLOOKUP($A42,Inputs!$A:$A,Inputs!K:K,,0) -> 88956 | L42: =_xlfn.XLOOKUP($A42,Inputs!$A:$A,Inputs!L:L,,0) -> 88642 | M42: =_xlfn.XLOOKUP($A42,Inputs!$A:$A,Inputs!M:M,,0) -> 88434
A43: Other Assets | B43: =_xlfn.XLOOKUP($A43,Inputs!$A:$A,Inputs!B:B,,0) -> 189416 | C43: =_xlfn.XLOOKUP($A43,Inputs!$A:$A,Inputs!C:C,,0) -> 179512 | D43: =_xlfn.XLOOKUP($A43,Inputs!$A:$A,Inputs!D:D,,0) -> 127380 | E43: =_xlfn.XLOOKUP($A43,Inputs!$A:$A,Inputs!E:E,,0) -> 123573 | F43: =_xlfn.XLOOKUP($A43,Inputs!$A:$A,Inputs!F:F,,0) -> 144932 | G43: =_xlfn.XLOOKUP($A43,Inputs!$A:$A,Inputs!G:G,,0) -> 140930 | H43: =_xlfn.XLOOKUP($A43,Inputs!$A:$A,Inputs!H:H,,0) -> 136724 | I43: =_xlfn.XLOOKUP($A43,Inputs!$A:$A,Inputs!I:I,,0) -> 140659 | J43: =_xlfn.XLOOKUP($A43,Inputs!$A:$A,Inputs!J:J,,0) -> 116123 | K43: =_xlfn.XLOOKUP($A43,Inputs!$A:$A,Inputs!K:K,,0) -> 114723 | L43: =_xlfn.XLOOKUP($A43,Inputs!$A:$A,Inputs!L:L,,0) -> 116435 | M43: =_xlfn.XLOOKUP($A43,Inputs!$A:$A,Inputs!M:M,,0) -> 112501
A44: Total Assets | B44: =_xlfn.XLOOKUP($A44,Inputs!$A:$A,Inputs!B:B,,0) -> 379680 | C44: =_xlfn.XLOOKUP($A44,Inputs!$A:$A,Inputs!C:C,,0) -> 366596 | D44: =_xlfn.XLOOKUP($A44,Inputs!$A:$A,Inputs!D:D,,0) -> 316481 | E44: =_xlfn.XLOOKUP($A44,Inputs!$A:$A,Inputs!E:E,,0) -> 291727 | F44: =_xlfn.XLOOKUP($A44,Inputs!$A:$A,Inputs!F:F,,0) -> 264829 | G44: =_xlfn.XLOOKUP($A44,Inputs!$A:$A,Inputs!G:G,,0) -> 257143 | H44: =_xlfn.XLOOKUP($A44,Inputs!$A:$A,Inputs!H:H,,0) -> 244180 | I44: =_xlfn.XLOOKUP($A44,Inputs!$A:$A,Inputs!I:I,,0) -> 244175 | J44: =_xlfn.XLOOKUP($A44,Inputs!$A:$A,Inputs!J:J,,0) -> 232616 | K44: =_xlfn.XLOOKUP($A44,Inputs!$A:$A,Inputs!K:K,,0) -> 274098 | L44: =_xlfn.XLOOKUP($A44,Inputs!$A:$A,Inputs!L:L,,0) -> 225222 | M44: =_xlfn.XLOOKUP($A44,Inputs!$A:$A,Inputs!M:M,,0) -> 230461
A47: Liabilities
A48: Current Liabilities | B48: =_xlfn.XLOOKUP($A48,Inputs!$A:$A,Inputs!B:B,,0) -> 50171 | C48: =_xlfn.XLOOKUP($A48,Inputs!$A:$A,Inputs!C:C,,0) -> 47160 | D48: =_xlfn.XLOOKUP($A48,Inputs!$A:$A,Inputs!D:D,,0) -> 39660 | E48: =_xlfn.XLOOKUP($A48,Inputs!$A:$A,Inputs!E:E,,0) -> 44868 | F48: =_xlfn.XLOOKUP($A48,Inputs!$A:$A,Inputs!F:F,,0) -> 37930 | G48: =_xlfn.XLOOKUP($A48,Inputs!$A:$A,Inputs!G:G,,0) -> 33037 | H48: =_xlfn.XLOOKUP($A48,Inputs!$A:$A,Inputs!H:H,,0) -> 30340 | I48: =_xlfn.XLOOKUP($A48,Inputs!$A:$A,Inputs!I:I,,0) -> 35052 | J48: =_xlfn.XLOOKUP($A48,Inputs!$A:$A,Inputs!J:J,,0) -> 27987 | K48: =_xlfn.XLOOKUP($A48,Inputs!$A:$A,Inputs!K:K,,0) -> 27050 | L48: =_xlfn.XLOOKUP($A48,Inputs!$A:$A,Inputs!L:L,,0) -> 26956 | M48: =_xlfn.XLOOKUP($A48,Inputs!$A:$A,Inputs!M:M,,0) -> 30761
A49: Short-Term Debt | B49: =_xlfn.XLOOKUP($A49,Inputs!$A:$A,Inputs!B:B,,0) -> 150 | C49: =_xlfn.XLOOKUP($A49,Inputs!$A:$A,Inputs!C:C,,0) -> 0 | D49: =_xlfn.XLOOKUP($A49,Inputs!$A:$A,Inputs!D:D,,0) -> 320 | E49: =_xlfn.XLOOKUP($A49,Inputs!$A:$A,Inputs!E:E,,0) -> 0 | F49: =_xlfn.XLOOKUP($A49,Inputs!$A:$A,Inputs!F:F,,0) -> 150 | G49: =_xlfn.XLOOKUP($A49,Inputs!$A:$A,Inputs!G:G,,0) -> 150 | H49: =_xlfn.XLOOKUP($A49,Inputs!$A:$A,Inputs!H:H,,0) -> 168 | I49: =_xlfn.XLOOKUP($A49,Inputs!$A:$A,Inputs!I:I,,0) -> 0 | J49: =_xlfn.XLOOKUP($A49,Inputs!$A:$A,Inputs!J:J,,0) -> 338 | K49: =_xlfn.XLOOKUP($A49,Inputs!$A:$A,Inputs!K:K,,0) -> 447 | L49: =_xlfn.XLOOKUP($A49,Inputs!$A:$A,Inputs!L:L,,0) -> 500 | M49: =_xlfn.XLOOKUP($A49,Inputs!$A:$A,Inputs!M:M,,0) -> 1934
A50: Short-Term Leases | B50: =_xlfn.XLOOKUP($A50,Inputs!$A:$A,Inputs!B:B,,0) -> 9813 | C50: =_xlfn.XLOOKUP($A50,Inputs!$A:$A,Inputs!C:C,,0) -> 7443 | D50: =_xlfn.XLOOKUP($A50,Inputs!$A:$A,Inputs!D:D,,0) -> 5569 | E50: =_xlfn.XLOOKUP($A50,Inputs!$A:$A,Inputs!E:E,,0) -> 10777 | F50: =_xlfn.XLOOKUP($A50,Inputs!$A:$A,Inputs!F:F,,0) -> 7040 | G50: =_xlfn.XLOOKUP($A50,Inputs!$A:$A,Inputs!G:G,,0) -> 3303 | H50: =_xlfn.XLOOKUP($A50,Inputs!$A:$A,Inputs!H:H,,0) -> 2477 | I50: =_xlfn.XLOOKUP($A50,Inputs!$A:$A,Inputs!I:I,,0) -> 6489 | J50: =_xlfn.XLOOKUP($A50,Inputs!$A:$A,Inputs!J:J,,0) -> 2397 | K50: =_xlfn.XLOOKUP($A50,Inputs!$A:$A,Inputs!K:K,,0) -> 3486 | L50: =_xlfn.XLOOKUP($A50,Inputs!$A:$A,Inputs!L:L,,0) -> 3869 | M50: =_xlfn.XLOOKUP($A50,Inputs!$A:$A,Inputs!M:M,,0) -> 2915
A51: Other current liabilities | B51: =_xlfn.XLOOKUP($A51,Inputs!$A:$A,Inputs!B:B,,0) -> 31458 | C51: =_xlfn.XLOOKUP($A51,Inputs!$A:$A,Inputs!C:C,,0) -> 31677 | D51: =_xlfn.XLOOKUP($A51,Inputs!$A:$A,Inputs!D:D,,0) -> 27104 | E51: =_xlfn.XLOOKUP($A51,Inputs!$A:$A,Inputs!E:E,,0) -> 26366 | F51: =_xlfn.XLOOKUP($A51,Inputs!$A:$A,Inputs!F:F,,0) -> 23508 | G51: =_xlfn.XLOOKUP($A51,Inputs!$A:$A,Inputs!G:G,,0) -> 22521 | H51: =_xlfn.XLOOKUP($A51,Inputs!$A:$A,Inputs!H:H,,0) -> 20611 | I51: =_xlfn.XLOOKUP($A51,Inputs!$A:$A,Inputs!I:I,,0) -> 28563 | J51: =_xlfn.XLOOKUP($A51,Inputs!$A:$A,Inputs!J:J,,0) -> 19654 | K51: =_xlfn.XLOOKUP($A51,Inputs!$A:$A,Inputs!K:K,,0) -> 18163 | L51: =_xlfn.XLOOKUP($A51,Inputs!$A:$A,Inputs!L:L,,0) -> 18133 | M51: =_xlfn.XLOOKUP($A51,Inputs!$A:$A,Inputs!M:M,,0) -> 21718
A52: Non-current Liabilities | B52: =_xlfn.XLOOKUP($A52,Inputs!$A:$A,Inputs!B:B,,0) -> 238365 | C52: =_xlfn.XLOOKUP($A52,Inputs!$A:$A,Inputs!C:C,,0) -> 237646 | D52: =_xlfn.XLOOKUP($A52,Inputs!$A:$A,Inputs!D:D,,0) -> 208979 | E52: =_xlfn.XLOOKUP($A52,Inputs!$A:$A,Inputs!E:E,,0) -> 185464 | F52: =_xlfn.XLOOKUP($A52,Inputs!$A:$A,Inputs!F:F,,0) -> 173754 | G52: =_xlfn.XLOOKUP($A52,Inputs!$A:$A,Inputs!G:G,,0) -> 181010 | H52: =_xlfn.XLOOKUP($A52,Inputs!$A:$A,Inputs!H:H,,0) -> 191316 | I52: =_xlfn.XLOOKUP($A52,Inputs!$A:$A,Inputs!I:I,,0) -> 192695 | J52: =_xlfn.XLOOKUP($A52,Inputs!$A:$A,Inputs!J:J,,0) -> 192331 | K52: =_xlfn.XLOOKUP($A52,Inputs!$A:$A,Inputs!K:K,,0) -> 208212 | L52: =_xlfn.XLOOKUP($A52,Inputs!$A:$A,Inputs!L:L,,0) -> 165109 | M52: =_xlfn.XLOOKUP($A52,Inputs!$A:$A,Inputs!M:M,,0) -> 163730
A53: Long-Term Debt | B53: =_xlfn.XLOOKUP($A53,Inputs!$A:$A,Inputs!B:B,,0) -> 139509 | C53: =_xlfn.XLOOKUP($A53,Inputs!$A:$A,Inputs!C:C,,0) -> 142500 | D53: =_xlfn.XLOOKUP($A53,Inputs!$A:$A,Inputs!D:D,,0) -> 122257 | E53: =_xlfn.XLOOKUP($A53,Inputs!$A:$A,Inputs!E:E,,0) -> 99932 | F53: =_xlfn.XLOOKUP($A53,Inputs!$A:$A,Inputs!F:F,,0) -> 105284 | G53: =_xlfn.XLOOKUP($A53,Inputs!$A:$A,Inputs!G:G,,0) -> 113004 | H53: =_xlfn.XLOOKUP($A53,Inputs!$A:$A,Inputs!H:H,,0) -> 104818 | I53: =_xlfn.XLOOKUP($A53,Inputs!$A:$A,Inputs!I:I,,0) -> 103240 | J53: =_xlfn.XLOOKUP($A53,Inputs!$A:$A,Inputs!J:J,,0) -> 110536 | K53: =_xlfn.XLOOKUP($A53,Inputs!$A:$A,Inputs!K:K,,0) -> 89547 | L53: =_xlfn.XLOOKUP($A53,Inputs!$A:$A,Inputs!L:L,,0) -> 47618 | M53: =_xlfn.XLOOKUP($A53,Inputs!$A:$A,Inputs!M:M,,0) -> 50303
A54: Long-Term Leases | B54: =_xlfn.XLOOKUP($A54,Inputs!$A:$A,Inputs!B:B,,0) -> 1167 | C54: =_xlfn.XLOOKUP($A54,Inputs!$A:$A,Inputs!C:C,,0) -> 925 | D54: =_xlfn.XLOOKUP($A54,Inputs!$A:$A,Inputs!D:D,,0) -> 916 | E54: =_xlfn.XLOOKUP($A54,Inputs!$A:$A,Inputs!E:E,,0) -> 780 | F54: =_xlfn.XLOOKUP($A54,Inputs!$A:$A,Inputs!F:F,,0) -> 589 | G54: =_xlfn.XLOOKUP($A54,Inputs!$A:$A,Inputs!G:G,,0) -> 638 | H54: =_xlfn.XLOOKUP($A54,Inputs!$A:$A,Inputs!H:H,,0) -> 615 | I54: =_xlfn.XLOOKUP($A54,Inputs!$A:$A,Inputs!I:I,,0) -> 0 | J54: =_xlfn.XLOOKUP($A54,Inputs!$A:$A,Inputs!J:J,,0) -> 0 | K54: =_xlfn.XLOOKUP($A54,Inputs!$A:$A,Inputs!K:K,,0) -> 111 | L54: =_xlfn.XLOOKUP($A54,Inputs!$A:$A,Inputs!L:L,,0) -> 0 | M54: =_xlfn.XLOOKUP($A54,Inputs!$A:$A,Inputs!M:M,,0) -> 0
A55: Other non-current liabilities | B55: =_xlfn.XLOOKUP($A55,Inputs!$A:$A,Inputs!B:B,,0) -> 97689 | C55: =_xlfn.XLOOKUP($A55,Inputs!$A:$A,Inputs!C:C,,0) -> 94221 | D55: =_xlfn.XLOOKUP($A55,Inputs!$A:$A,Inputs!D:D,,0) -> 85806 | E55: =_xlfn.XLOOKUP($A55,Inputs!$A:$A,Inputs!E:E,,0) -> 84752 | F55: =_xlfn.XLOOKUP($A55,Inputs!$A:$A,Inputs!F:F,,0) -> 67881 | G55: =_xlfn.XLOOKUP($A55,Inputs!$A:$A,Inputs!G:G,,0) -> 67368 | H55: =_xlfn.XLOOKUP($A55,Inputs!$A:$A,Inputs!H:H,,0) -> 85883 | I55: =_xlfn.XLOOKUP($A55,Inputs!$A:$A,Inputs!I:I,,0) -> 89455 | J55: =_xlfn.XLOOKUP($A55,Inputs!$A:$A,Inputs!J:J,,0) -> 81795 | K55: =_xlfn.XLOOKUP($A55,Inputs!$A:$A,Inputs!K:K,,0) -> 118554 | L55: =_xlfn.XLOOKUP($A55,Inputs!$A:$A,Inputs!L:L,,0) -> 117491 | M55: =_xlfn.XLOOKUP($A55,Inputs!$A:$A,Inputs!M:M,,0) -> 113427
A56: Total Liabilities | B56: =_xlfn.XLOOKUP($A56,Inputs!$A:$A,Inputs!B:B,,0) -> 288536 | C56: =_xlfn.XLOOKUP($A56,Inputs!$A:$A,Inputs!C:C,,0) -> 284806 | D56: =_xlfn.XLOOKUP($A56,Inputs!$A:$A,Inputs!D:D,,0) -> 248639 | E56: =_xlfn.XLOOKUP($A56,Inputs!$A:$A,Inputs!E:E,,0) -> 230332 | F56: =_xlfn.XLOOKUP($A56,Inputs!$A:$A,Inputs!F:F,,0) -> 211684 | G56: =_xlfn.XLOOKUP($A56,Inputs!$A:$A,Inputs!G:G,,0) -> 214047 | H56: =_xlfn.XLOOKUP($A56,Inputs!$A:$A,Inputs!H:H,,0) -> 221656 | I56: =_xlfn.XLOOKUP($A56,Inputs!$A:$A,Inputs!I:I,,0) -> 227747 | J56: =_xlfn.XLOOKUP($A56,Inputs!$A:$A,Inputs!J:J,,0) -> 220318 | K56: =_xlfn.XLOOKUP($A56,Inputs!$A:$A,Inputs!K:K,,0) -> 235262 | L56: =_xlfn.XLOOKUP($A56,Inputs!$A:$A,Inputs!L:L,,0) -> 192065 | M56: =_xlfn.XLOOKUP($A56,Inputs!$A:$A,Inputs!M:M,,0) -> 194491
A58: Debt | B58: =B49+B53 -> 139659 | C58: =C49+C53 -> 142500 | D58: =D49+D53 -> 122577 | E58: =E49+E53 -> 99932 | F58: =F49+F53 -> 105434 | G58: =G49+G53 -> 113154 | H58: =H49+H53 -> 104986 | I58: =I49+I53 -> 103240 | ... M58: =M49+M53 -> 52237
A59: Debt/Assets | B59: =IFERROR(B58/B44,"-") -> 0.36783344 | C59: =IFERROR(C58/C44,"-") -> 0.38871128 | D59: =IFERROR(D58/D44,"-") -> 0.38731235 | E59: =IFERROR(E58/E44,"-") -> 0.34255314 | F59: =IFERROR(F58/F44,"-") -> 0.39812105 | G59: =IFERROR(G58/G44,"-") -> 0.44004309 | H59: =IFERROR(H58/H44,"-") -> 0.42995331 | I59: =IFERROR(I58/I44,"-") -> 0.42281151 | ... M59: =IFERROR(M58/M44,"-") -> 0.22666308
A61: Minority Interest | B61: =_xlfn.XLOOKUP($A61,Inputs!$A:$A,Inputs!B:B,,0) -> 1319 | C61: =_xlfn.XLOOKUP($A61,Inputs!$A:$A,Inputs!C:C,,0) -> 1410 | D61: =_xlfn.XLOOKUP($A61,Inputs!$A:$A,Inputs!D:D,,0) -> 1430 | E61: =_xlfn.XLOOKUP($A61,Inputs!$A:$A,Inputs!E:E,,0) -> 1440 | F61: =_xlfn.XLOOKUP($A61,Inputs!$A:$A,Inputs!F:F,,0) -> 1565 | G61: =_xlfn.XLOOKUP($A61,Inputs!$A:$A,Inputs!G:G,,0) -> 1591 | H61: =_xlfn.XLOOKUP($A61,Inputs!$A:$A,Inputs!H:H,,0) -> 1508 | I61: =_xlfn.XLOOKUP($A61,Inputs!$A:$A,Inputs!I:I,,0) -> 1414 | J61: =_xlfn.XLOOKUP($A61,Inputs!$A:$A,Inputs!J:J,,0) -> 1378 | K61: =_xlfn.XLOOKUP($A61,Inputs!$A:$A,Inputs!K:K,,0) -> 56580 | L61: =_xlfn.XLOOKUP($A61,Inputs!$A:$A,Inputs!L:L,,0) -> 52375 | M61: =_xlfn.XLOOKUP($A61,Inputs!$A:$A,Inputs!M:M,,0) -> 49938
A63: Shareholder's Equity | B63: =_xlfn.XLOOKUP($A63,Inputs!$A:$A,Inputs!B:B,,0) -> 89825 | C63: =_xlfn.XLOOKUP($A63,Inputs!$A:$A,Inputs!C:C,,0) -> 80380 | D63: =_xlfn.XLOOKUP($A63,Inputs!$A:$A,Inputs!D:D,,0) -> 66412 | E63: =_xlfn.XLOOKUP($A63,Inputs!$A:$A,Inputs!E:E,,0) -> 59955 | F63: =_xlfn.XLOOKUP($A63,Inputs!$A:$A,Inputs!F:F,,0) -> 51580 | G63: =_xlfn.XLOOKUP($A63,Inputs!$A:$A,Inputs!G:G,,0) -> 41505 | H63: =_xlfn.XLOOKUP($A63,Inputs!$A:$A,Inputs!H:H,,0) -> 21016 | I63: =_xlfn.XLOOKUP($A63,Inputs!$A:$A,Inputs!I:I,,0) -> 15014 | J63: =_xlfn.XLOOKUP($A63,Inputs!$A:$A,Inputs!J:J,,0) -> 10920 | K63: =_xlfn.XLOOKUP($A63,Inputs!$A:$A,Inputs!K:K,,0) -> -17744 | L63: =_xlfn.XLOOKUP($A63,Inputs!$A:$A,Inputs!L:L,,0) -> -19218 | M63: =_xlfn.XLOOKUP($A63,Inputs!$A:$A,Inputs!M:M,,0) -> -13968
A66: Other Data
A67: Number of employees | B67: =_xlfn.XLOOKUP($A67,Inputs!$A:$A,Inputs!B:B,,0) -> #N/A | C67: =_xlfn.XLOOKUP($A67,Inputs!$A:$A,Inputs!C:C,,0) -> #N/A | D67: =_xlfn.XLOOKUP($A67,Inputs!$A:$A,Inputs!D:D,,0) -> #N/A | E67: =_xlfn.XLOOKUP($A67,Inputs!$A:$A,Inputs!E:E,,0) -> #N/A | F67: =_xlfn.XLOOKUP($A67,Inputs!$A:$A,Inputs!F:F,,0) -> #N/A | G67: =_xlfn.XLOOKUP($A67,Inputs!$A:$A,Inputs!G:G,,0) -> #N/A | H67: =_xlfn.XLOOKUP($A67,Inputs!$A:$A,Inputs!H:H,,0) -> #N/A | I67: =_xlfn.XLOOKUP($A67,Inputs!$A:$A,Inputs!I:I,,0) -> #N/A | J67: =_xlfn.XLOOKUP($A67,Inputs!$A:$A,Inputs!J:J,,0) -> #N/A | K67: =_xlfn.XLOOKUP($A67,Inputs!$A:$A,Inputs!K:K,,0) -> #N/A | L67: =_xlfn.XLOOKUP($A67,Inputs!$A:$A,Inputs!L:L,,0) -> #N/A | M67: =_xlfn.XLOOKUP($A67,Inputs!$A:$A,Inputs!M:M,,0) -> #N/A
A68: Shares Outstanding | B68: =_xlfn.XLOOKUP($A68,Inputs!$A:$A,Inputs!B:B,,0) -> #N/A | C68: =_xlfn.XLOOKUP($A68,Inputs!$A:$A,Inputs!C:C,,0) -> #N/A | D68: =_xlfn.XLOOKUP($A68,Inputs!$A:$A,Inputs!D:D,,0) -> #N/A | E68: =_xlfn.XLOOKUP($A68,Inputs!$A:$A,Inputs!E:E,,0) -> #N/A | F68: =_xlfn.XLOOKUP($A68,Inputs!$A:$A,Inputs!F:F,,0) -> #N/A | G68: =_xlfn.XLOOKUP($A68,Inputs!$A:$A,Inputs!G:G,,0) -> #N/A | H68: =_xlfn.XLOOKUP($A68,Inputs!$A:$A,Inputs!H:H,,0) -> #N/A | I68: =_xlfn.XLOOKUP($A68,Inputs!$A:$A,Inputs!I:I,,0) -> #N/A | J68: =_xlfn.XLOOKUP($A68,Inputs!$A:$A,Inputs!J:J,,0) -> #N/A | K68: =_xlfn.XLOOKUP($A68,Inputs!$A:$A,Inputs!K:K,,0) -> #N/A | L68: =_xlfn.XLOOKUP($A68,Inputs!$A:$A,Inputs!L:L,,0) -> #N/A | M68: =_xlfn.XLOOKUP($A68,Inputs!$A:$A,Inputs!M:M,,0) -> #N/A
A69: Float | B69: =_xlfn.XLOOKUP($A69,Inputs!$A:$A,Inputs!B:B,,0) -> 0.9997 | C69: =_xlfn.XLOOKUP($A69,Inputs!$A:$A,Inputs!C:C,,0) -> Yahoo finance | D69: =_xlfn.XLOOKUP($A69,Inputs!$A:$A,Inputs!D:D,,0) -> 0 | E69: =_xlfn.XLOOKUP($A69,Inputs!$A:$A,Inputs!E:E,,0) -> 0 | F69: =_xlfn.XLOOKUP($A69,Inputs!$A:$A,Inputs!F:F,,0) -> 0 | G69: =_xlfn.XLOOKUP($A69,Inputs!$A:$A,Inputs!G:G,,0) -> 0 | H69: =_xlfn.XLOOKUP($A69,Inputs!$A:$A,Inputs!H:H,,0) -> 0 | I69: =_xlfn.XLOOKUP($A69,Inputs!$A:$A,Inputs!I:I,,0) -> 0 | J69: =_xlfn.XLOOKUP($A69,Inputs!$A:$A,Inputs!J:J,,0) -> 0 | K69: =_xlfn.XLOOKUP($A69,Inputs!$A:$A,Inputs!K:K,,0) -> 0 | L69: =_xlfn.XLOOKUP($A69,Inputs!$A:$A,Inputs!L:L,,0) -> 0 | M69: =_xlfn.XLOOKUP($A69,Inputs!$A:$A,Inputs!M:M,,0) -> 0
A70: Insiders Own | B70: =_xlfn.XLOOKUP($A70,Inputs!$A:$A,Inputs!B:B,,0) -> 0.0003 | C70: =_xlfn.XLOOKUP($A70,Inputs!$A:$A,Inputs!C:C,,0) -> Yahoo finance | D70: =_xlfn.XLOOKUP($A70,Inputs!$A:$A,Inputs!D:D,,0) -> 0 | E70: =_xlfn.XLOOKUP($A70,Inputs!$A:$A,Inputs!E:E,,0) -> 0 | F70: =_xlfn.XLOOKUP($A70,Inputs!$A:$A,Inputs!F:F,,0) -> 0 | G70: =_xlfn.XLOOKUP($A70,Inputs!$A:$A,Inputs!G:G,,0) -> 0 | H70: =_xlfn.XLOOKUP($A70,Inputs!$A:$A,Inputs!H:H,,0) -> 0 | I70: =_xlfn.XLOOKUP($A70,Inputs!$A:$A,Inputs!I:I,,0) -> 0 | J70: =_xlfn.XLOOKUP($A70,Inputs!$A:$A,Inputs!J:J,,0) -> 0 | K70: =_xlfn.XLOOKUP($A70,Inputs!$A:$A,Inputs!K:K,,0) -> 0 | L70: =_xlfn.XLOOKUP($A70,Inputs!$A:$A,Inputs!L:L,,0) -> 0 | M70: =_xlfn.XLOOKUP($A70,Inputs!$A:$A,Inputs!M:M,,0) -> 0
A71: Fitch/ S&P Rating | B71: =_xlfn.XLOOKUP($A71,Inputs!$A:$A,Inputs!B:B,,0) -> BBB+ | C71: =_xlfn.XLOOKUP($A71,Inputs!$A:$A,Inputs!C:C,,0) -> 10-K | D71: =_xlfn.XLOOKUP($A71,Inputs!$A:$A,Inputs!D:D,,0) -> 0 | E71: =_xlfn.XLOOKUP($A71,Inputs!$A:$A,Inputs!E:E,,0) -> 0 | F71: =_xlfn.XLOOKUP($A71,Inputs!$A:$A,Inputs!F:F,,0) -> 0 | G71: =_xlfn.XLOOKUP($A71,Inputs!$A:$A,Inputs!G:G,,0) -> 0 | H71: =_xlfn.XLOOKUP($A71,Inputs!$A:$A,Inputs!H:H,,0) -> 0 | I71: =_xlfn.XLOOKUP($A71,Inputs!$A:$A,Inputs!I:I,,0) -> 0 | J71: =_xlfn.XLOOKUP($A71,Inputs!$A:$A,Inputs!J:J,,0) -> 0 | K71: =_xlfn.XLOOKUP($A71,Inputs!$A:$A,Inputs!K:K,,0) -> 0 | L71: =_xlfn.XLOOKUP($A71,Inputs!$A:$A,Inputs!L:L,,0) -> 0 | M71: =_xlfn.XLOOKUP($A71,Inputs!$A:$A,Inputs!M:M,,0) -> 0
A72: Dividend Yield | B72: =_xlfn.XLOOKUP($A72,Inputs!$A:$A,Inputs!B:B,,0) -> #N/A | C72: =_xlfn.XLOOKUP($A72,Inputs!$A:$A,Inputs!C:C,,0) -> #N/A | D72: =_xlfn.XLOOKUP($A72,Inputs!$A:$A,Inputs!D:D,,0) -> #N/A | E72: =_xlfn.XLOOKUP($A72,Inputs!$A:$A,Inputs!E:E,,0) -> #N/A | F72: =_xlfn.XLOOKUP($A72,Inputs!$A:$A,Inputs!F:F,,0) -> #N/A | G72: =_xlfn.XLOOKUP($A72,Inputs!$A:$A,Inputs!G:G,,0) -> #N/A | H72: =_xlfn.XLOOKUP($A72,Inputs!$A:$A,Inputs!H:H,,0) -> #N/A | I72: =_xlfn.XLOOKUP($A72,Inputs!$A:$A,Inputs!I:I,,0) -> #N/A | J72: =_xlfn.XLOOKUP($A72,Inputs!$A:$A,Inputs!J:J,,0) -> #N/A | K72: =_xlfn.XLOOKUP($A72,Inputs!$A:$A,Inputs!K:K,,0) -> #N/A | L72: =_xlfn.XLOOKUP($A72,Inputs!$A:$A,Inputs!L:L,,0) -> #N/A | M72: =_xlfn.XLOOKUP($A72,Inputs!$A:$A,Inputs!M:M,,0) -> #N/A
A73: Daily Volume in Millions of USD | B73: =_xlfn.XLOOKUP($A73,Inputs!$A:$A,Inputs!B:B,,0) -> 0 | C73: =_xlfn.XLOOKUP($A73,Inputs!$A:$A,Inputs!C:C,,0) -> Yahoo Finance | D73: =_xlfn.XLOOKUP($A73,Inputs!$A:$A,Inputs!D:D,,0) -> 0 | E73: =_xlfn.XLOOKUP($A73,Inputs!$A:$A,Inputs!E:E,,0) -> 0 | F73: =_xlfn.XLOOKUP($A73,Inputs!$A:$A,Inputs!F:F,,0) -> 0 | G73: =_xlfn.XLOOKUP($A73,Inputs!$A:$A,Inputs!G:G,,0) -> 0 | H73: =_xlfn.XLOOKUP($A73,Inputs!$A:$A,Inputs!H:H,,0) -> 0 | I73: =_xlfn.XLOOKUP($A73,Inputs!$A:$A,Inputs!I:I,,0) -> 0 | J73: =_xlfn.XLOOKUP($A73,Inputs!$A:$A,Inputs!J:J,,0) -> 0 | K73: =_xlfn.XLOOKUP($A73,Inputs!$A:$A,Inputs!K:K,,0) -> 0 | L73: =_xlfn.XLOOKUP($A73,Inputs!$A:$A,Inputs!L:L,,0) -> 0 | M73: =_xlfn.XLOOKUP($A73,Inputs!$A:$A,Inputs!M:M,,0) -> 0
B75: 2020 | C75: 2021 | D75: 2022
A76: Short % of Float | B76: 0 | C76: 0 | D76: 0
A77: EPS | B77: 0 | C77: 0 | D77: 0
A79: Corporate Bonds 3, 5 Y 10 | B79: Average Price | C79: Moody's | D79: YTM | E79: DIVISA
B80: =VLOOKUP($A80,Inputs!$A$5:$M$98,MATCH(B$4,Inputs!$B$5:$M$5,0)+1,FALSE) -> #N/A | C80: =VLOOKUP($A80,Inputs!$A$5:$M$98,MATCH(C$4,Inputs!$B$5:$M$5,0)+1,FALSE) -> #N/A | D80: =VLOOKUP($A80,Inputs!$A$5:$M$98,MATCH(D$4,Inputs!$B$5:$M$5,0)+1,FALSE) -> #N/A | E80: =VLOOKUP($A80,Inputs!$A$5:$M$98,MATCH(E$4,Inputs!$B$5:$M$5,0)+1,FALSE) -> #N/A

Sheet Inputs
G2: Figures in Millions of USD
G3: Company | H3: #VALUE!
D4: Report in millions
A5: RESULTS | B5: =OP!J19 -> 2022 | C5: =B5-1 -> 2021 | D5: =C5-1 -> 2020 | E5: =D5-1 -> 2019 | F5: =E5-1 -> 2018 | G5: =F5-1 -> 2017 | H5: =G5-1 -> 2016 | I5: =H5-1 -> 2015 | J5: =I5-1 -> 2014 | ... M5: =L5-1 -> 2011 | Q5: Hoja | R5: Nombre campo Bloomberg | T5: Cambio de signo | Z5: 2016 | AA5: 2015 | AB5: 2014 | AC5: 2013 | AD5: 2012 | AE5: 2011 | AF5: 2010 | AG5: 2009
A6: Net Sales | B6: 136835 | C6: 133613 | D6: 128292 | E6: 131868 | F6: 130863 | G6: 126034 | H6: 125980 | I6: 131620 | J6: 127079 | K6: 120550 | L6: 115846 | M6: 110875 | N6: Income Statement | O6: Sales | Q6: Ingreso | R6: Ingreso | Z6: 38537 | AA6: 47011 | AB6: 55184 | AC6: 55656 | AD6: 65875 | AE6: 60138 | AF6: 42588 | AG6: 32396
A7: Gross Profit | B7: 77702 | C7: 77312 | D7: 77091 | E7: 77142 | F7: 75658 | G7: 73142 | H7: 73279 | I7: 79063 | J7: 77175 | K7: 75663 | L7: 69611 | M7: 65000 | N7: Income Statement | O7: =+A7 -> Gross Profit | Q7: Ingreso | R7: + Coste de bienes y servicios | Z7: =Z6-28044 -> 10493 | AA7: =AA6-33546 -> 13465 | AB7: =AB6-40718 -> 14466 | AC7: =AC6-40727 -> 14929 | AD7: =+AD6-47055 -> 18820 | AE7: =+AE6-43578 -> 16560 | AF7: =+AF6-30367 -> 12221 | AG7: =+AG6-23886 -> 8510
A8: Operating Income | B8: 30467 | C8: 32448 | D8: 28798 | E8: 30378 | F8: 22278 | G8: 27425 | H8: 27059 | I8: 33060 | J8: 19599 | K8: 31968 | L8: 13160 | M8: 12880 | N8: Income Statement | O8: Operating Income | Q8: Ingreso | R8: + Ventas, generales y admin | Z8: =Z7-4383 -> 6110 | AA8: =AA7-4951 -> 8514 | AB8: =AB7-6529 -> 7937 | AC8: =AC7-5547 -> 9382 | AD8: =AD7-5919-2466-797-580-485 -> 8573 | AE8: =+AE7-5203-2297-826-1081 -> 7153 | AF8: =+AF7-4248-1905-914-1191 -> 3963 | AG8: =+AG7-3645-1421-1045-1822 -> 577
A9: Other Expenses (Revenues) | B9: 1373 | C9: 312 | D9: =-539-45 -> -584 | E9: =-2900-15 -> -2915 | F9: =2364-186 -> 2178 | G9: =-2021-77 -> -2098 | H9: =-1599-98 -> -1697 | I9: =186-86 -> 100 | J9: =-1194+1780 -> 586 | K9: =-166+142 -> -24 | L9: =-1016+324 -> -692 | M9: =-14+444 -> 430 | N9: Income Statement | O9: investment income+other income expense+income loss+minority interest+non controlling interest+share onf net profit+gain8losses) on equity investments+share of result from associates nd joint ventures+non operating profit+ | Q9: Ingreso | R9: + Investigación y desarrollo | S9: + Coste de financiación de beneficio | T9: + Otro gasto operativo | U9: - Beneficio (pérdida) de filiales | V9: - Minoritarios | Z9: =1853+596+595+1904+6+8 -> 4962 | AA9: =2119+587+2023+11 -> 4740 | AB9: =2380+624+1619-8+16 -> 4631 | AC9: =2046+727+981+6+14 -> 3774 | AD9: =-14+41 -> 27 | AE9: 53 | AF9: =58+24 -> 82 | AG9: =12-68 -> -56
A10: Net Financial Cost | B10: =-3613+44 -> -3569 | C10: =-3485+145 -> -3340 | D10: -4247 | E10: -4730 | F10: -4833 | G10: -4733 | H10: -4376 | I10: -4920 | J10: -4915 | K10: -2667 | L10: -2571 | M10: -2827 | N10: Income Statement | O10: interest expense+financial income and expenses+other financial expense-income+interest and other net+ | Q10: Ingreso | R10: - Ingreso (pérdida) no operacional | Z10: =505+518 -> 1023 | AA10: =507-161 -> 346 | AB10: =484-322 -> 162 | AC10: =465+35 -> 500 | AD10: =467-130 -> 337 | AE10: =396+32 -> 428 | AF10: =343-130 -> 213 | AG10: =389-381 -> 8 | AJ10: Interest expense
A11: Taxes | B11: -6523 | C11: -6802 | D11: -5619 | E11: -2945 | F11: -3584 | G11: 9956 | H11: -7378 | I11: -9865 | J11: -3314 | K11: -5730 | L11: 660 | M11: -285 | N11: Income Statement | O11: Taxes | P11: Provision for income tax | Q11: Ingreso | R11: - Gasto de impuesto a la renta (Beneficio) | Z11: 192 | AA11: 916 | AB11: 692 | AC11: 1319 | AD11: =2528 -> 2528 | AE11: =1720 -> 1720 | AF11: =968 -> 968 | AG11: =-270 -> -270
A12: Net Income | B12: 21748 | C12: 22618 | D12: 18348 | E12: 19788 | F12: 16039 | G12: 30550 | H12: 13608 | I12: 18375 | J12: 11956 | K12: 23547 | L12: 10557 | M12: 10198 | N12: Income Statement | O12: Net Income | Q12: Flujo de caja | R12: + Ingreso neto | Z12: -67 | AA12: 2512 | AB12: 2452 | AC12: 3789 | AD12: 5681 | AE12: =4928+24 -> 4952 | AF12: 2700 | AG12: 895
B13: =SUM(B8:B11) -> 21748 | C13: =SUM(C8:C11) -> 22618 | D13: =SUM(D8:D11) -> 18348 | E13: =SUM(E8:E11) -> 19788 | F13: =SUM(F8:F11) -> 16039 | G13: =SUM(G8:G11) -> 30550 | H13: =SUM(H8:H11) -> 13608 | I13: =SUM(I8:I11) -> 18375 | ... M13: =SUM(M8:M11) -> 10198 | Z13: =Z8-Z10-Z9-Z11 -> -67 | AA13: =AA8-AA10-AA9-AA11 -> 2512 | AB13: =AB8-AB10-AB9-AB11 -> 2452 | AC13: =AC8-AC10-AC9-AC11 -> 3789 | AD13: =AD8-AD10-AD9-AD11 -> 5681 | AE13: =AE8-AE10-AE9-AE11 -> 4952 | AF13: =AF8-AF10-AF9-AF11 -> 2700 | AG13: =AG8-AG10-AG9-AG11 -> 895
A14: FINANCIAL POSITION | B14: =B12-B13 -> 0 | C14: =C12-C13 -> 0 | D14: =D12-D13 -> 0 | E14: =E12-E13 -> 0 | F14: =F12-F13 -> 0 | G14: =G12-G13 -> 0 | H14: =H12-H13 -> 0 | I14: =I12-I13 -> 0 | ... M14: =M12-M13 -> 0 | Z14: =Z12-Z13 -> 0 | AA14: =AA12-AA13 -> 0 | AB14: =AB12-AB13 -> 0 | AC14: =AC12-AC13 -> 0 | AD14: =AD12-AD13 -> 0 | AE14: =AE12-AE13 -> 0 | AF14: =AF12-AF13 -> 0 | AG14: =AG12-AG13 -> 0
A16: Weighted Average Shares (Basic NI) | B16: 4202 | C16: 4148 | D16: 4140 | E16: 4138 | F16: 4128 | G16: 4084 | H16: 4080 | I16: 4085 | J16: 3974 | K16: 2866 | L16: 2853 | M16: 2833
A17: Weighted Average Shares (Diluted NI) | B17: 4204 | C17: 4150 | D17: 4142 | E17: 4140 | F17: 4132 | G17: 4089 | H17: 4086 | I17: 4093 | J17: 3981 | K17: 2874 | L17: 2862 | M17: 2833
A19: Net gains (losses) from ForEx | B19: -153 | C19: -141 | D19: 180 | E19: 16 | F19: -117 | G19: 245 | H19: -19 | I19: -208 | J19: -1199 | K19: 60 | L19: 69 | M19: -119
A20: Total Comprehensive Income | B20: 20810 | C20: 21762 | D20: 17279 | E20: 18416 | F20: 15120 | G20: 30536 | H20: 15731 | I20: 17814 | J20: 10686 | K20: 23655 | L20: 11533 | M20: 10419
A22: Changes Net Working Capital | B22: =B23-C23 -> -1566 | C22: =C23-D23 -> -6116 | D22: =D23-E23 -> 2752 | E22: =E23-F23 -> -3950 | F22: =F23-G23 -> -836 | G22: =G23-H23 -> 1622 | H22: =H23-I23 -> 10417 | I22: =I23-J23 -> -8156 | ... L22: =L23-M23 -> 4370 | N22: cash flows | O22: NWC | Q22: Flujo de caja
A23: Net Working Capital | B23: =B27-B42-B28 -> -14919 | C23: =C27-C42-C28 -> -13353 | D23: =D27-D42-D28 -> -7237 | E23: =E27-E42-E28 -> -9989 | F23: =F27-F42-F28 -> -6039 | G23: =G27-G42-G28 -> -5203 | H23: =H27-H42-H28 -> -6825 | I23: =I27-I42-I28 -> -17242 | ... M23: =M27-M42-M28 -> -13184
A24: 2625 | B24: 2625 | C24: 2625 | D24: 2625 | E24: 2625 | F24: 2625 | G24: 2625 | H24: 2625 | I24: 2625 | J24: 2625 | K24: 2625 | L24: 2625 | M24: 2625 | N24: 2625 | Q24: Flujo de caja | R24: + Dividendos pagados | T24: Cambiar signo | Z24: 1799 | AA24: 1757 | AB24: 1620 | AC24: 1111 | AD24: 1617 | AE24: 1159 | AF24: 1084 | AG24: 1029
A25: BALANCE SHEET | B25: 2625 | C25: 2625 | D25: 2625 | E25: 2625 | F25: 2625 | G25: 2625 | H25: 2625 | I25: 2625 | J25: 2625 | K25: 2625 | L25: 2625 | M25: 2625 | N25: 2625 | Q25: Flujo de caja | R25: + Aumento en capital | S25: + Baja en capital | T25: Cambiar signo y hacer suma | Z25: 23 | AA25: =-33+2025 -> 1992 | AB25: 3817 | AC25: 1776 | AD25: -244 | AE25: -312 | AF25: -449 | AG25: -110
A26: ASSETS | N26: 1922 | O26: 2625
A27: Current | B27: 37857 | C27: 36728 | D27: 54594 | E27: 37473 | F27: 34636 | G27: 29913 | H27: 26395 | I27: 22280 | J27: 29499 | K27: 70994 | L27: 21235 | M27: 30939
A28: Cash & Eq. | B28: 2605 | C28: 2921 | D28: 22171 | E28: 2594 | F28: 2745 | G28: 2079 | H28: 2880 | I28: 4470 | J28: 10598 | K28: 53528 | L28: 3093 | M28: 13362 | N28: Balance Sheet | O28: Cash & Eq.
A29: Accounts Receivable | B29: 24506 | C29: 24585 | D29: 24650 | E29: 26277 | F29: 25859 | G29: 23493 | H29: 17513 | I29: 13457 | J29: 13993 | K29: 12439 | L29: 12576 | M29: 11776 | N29: Balance Sheet | O29: Accounts Receivable
A30: Inventory | B30: 2388 | C30: 3055 | D30: 1796 | E30: 1422 | F30: 1336 | G30: 1034 | H30: 1202 | I30: 1252 | J30: 1153 | K30: 1020 | L30: 1075 | M30: 940 | N30: Balance Sheet | O30: Inventory | Q30: Balance | R30: + Efectivo, equivalentes y STI | Z30: 7168 | AA30: 6460 | AB30: 7341 | AC30: 6081 | AD30: 5490 | AE30: 3057 | AF30: 3592 | AG30: 4867
A31: Other Current Assets | B31: =B27-SUM(B28:B30) -> 8358 | C31: =C27-SUM(C28:C30) -> 6167 | D31: =D27-SUM(D28:D30) -> 5977 | E31: =E27-SUM(E28:E30) -> 7180 | F31: =F27-SUM(F28:F30) -> 4696 | G31: =G27-SUM(G28:G30) -> 3307 | H31: =H27-SUM(H28:H30) -> 4800 | I31: =I27-SUM(I28:I30) -> 3101 | ... M31: =M27-SUM(M28:M30) -> 4861 | N31: Balance Sheet | O31: Inventory | Q31: Balance | R31: + Cuentas y notas por cobrar | S31: + Activos derivados y de cobertura | T31: + Inversiones y cuentas por cobrar a LP | Z31: =5981+8522+1029+13556 -> 29088 | AA31: =6695+8991+1170+13651 -> 30507 | AB31: =7737+9027+1364+14644 -> 32772 | AC31: 33499 | AD31: 33911 | AE31: 31031 | AF31: 28849 | AG31: 27162
A32: Non-current | B32: =B38-B27 -> 341823 | C32: =C38-C27 -> 329868 | D32: =D$38-D$27 -> 261887 | E32: =E$38-E$27 -> 254254 | F32: =F$38-F$27 -> 230193 | G32: =G$38-G$27 -> 227230 | H32: =H$38-H$27 -> 217785 | I32: =I$38-I$27 -> 221895 | J32: =J$38-J$27 -> 203117 | K32: =K$38-K$27 -> 203104 | ... M32: =M$38-M$27 -> 199522
A33: Property, Plant and Equipment | B33: 133564 | C33: 127579 | D33: 117364 | E33: 114609 | F33: 89286 | G33: 88568 | H33: 84751 | I33: 83541 | J33: 89947 | K33: 88956 | L33: 88642 | M33: 88434 | P33: net | Q33: Balance | R33: + Inventarios | Z33: 8614 | AA33: 9700 | AB33: 12205 | AC33: 12625 | AD33: 15547 | AE33: 14544 | AF33: 9587 | AG33: 6360
A34: Operating leases | B34: 26130 | C34: 27883 | D34: 22531 | E34: 22694
A35: Equity Method Investments | B35: 1071 | C35: 1061 | D35: 589 | E35: 558 | F35: 671 | G35: 1039 | H35: 1110 | I35: 796 | J35: 802 | K35: 3432 | L35: 3401 | M35: 3448
A36: Other Non-Current Assets | B36: =B32-SUM(B33:B35) -> 181058 | C36: =C32-SUM(C33:C35) -> 173345 | D36: =D32-SUM(D33:D35) -> 121403 | E36: =E32-SUM(E33:E35) -> 116393 | F36: =F32-SUM(F33:F35) -> 140236 | G36: =G32-SUM(G33:G35) -> 137623 | H36: =H32-SUM(H33:H35) -> 131924 | I36: =I32-SUM(I33:I35) -> 137558 | ... M36: =M32-SUM(M33:M35) -> 107640 | N36: Balance Sheet | O36: Property, Plant and Equipment
A37: Other Assets | B37: =B31+B36 -> 189416 | C37: =C31+C36 -> 179512 | D37: =D31+D36 -> 127380 | E37: =E31+E36 -> 123573 | F37: =F31+F36 -> 144932 | G37: =G31+G36 -> 140930 | H37: =H31+H36 -> 136724 | I37: =I31+I36 -> 140659 | ... M37: =M31+M36 -> 112501 | N37: Balance Sheet
A38: Total Assets | B38: 379680 | C38: 366596 | D38: 316481 | E38: 291727 | F38: 264829 | G38: 257143 | H38: 244180 | I38: 244175 | J38: 232616 | K38: 274098 | L38: 225222 | M38: 230461 | N38: Balance Sheet | O38: Total Assets | Q38: Balance | R38: + Propiedad, planta y equipo; neto | Z38: 15322 | AA38: 16090 | AB38: =16577 -> 16577 | AC38: 17075 | AD38: 16461 | AE38: 14395 | AF38: 12539 | AG38: 12386
N39: Balance Sheet | Z39: =Z40-SUM(Z30:Z38) -> 14512 | AA39: =AA40-SUM(AA30:AA38) -> 15585 | AB39: =AB40-SUM(AB30:AB38) -> 15786 | AC39: =AC40-SUM(AC30:AC38) -> 15616 | AD39: =AD40-SUM(AD30:AD38) -> 17947 | AE39: =AE40-SUM(AE30:AE38) -> 18419 | AF39: =AF40-SUM(AF30:AF38) -> 9453 | AG39: =AG40-SUM(AG30:AG38) -> 9263
N40: Balance Sheet | Q40: Balance | R40: Activos totales | Z40: 74704 | AA40: 78342 | AB40: 84681 | AC40: 84896 | AD40: 89356 | AE40: 81446 | AF40: 64020 | AG40: 60038
A41: LIABILITIES | N41: Balance Sheet
A42: Current Liabilities | B42: 50171 | C42: 47160 | D42: 39660 | E42: 44868 | F42: 37930 | G42: 33037 | H42: 30340 | I42: 35052 | J42: 27987 | K42: 27050 | L42: 26956 | M42: 30761 | N42: Balance Sheet | O42: Current Liabilities
A43: Payables | B43: 8750 | C43: 8040 | D43: 6667 | E43: 7725 | F43: 7232 | G43: 7063 | H43: 7084 | I43: 0 | J43: 5598 | K43: 4954 | L43: 4454 | M43: 4194 | P43: Accounts Payable
A44: Short-Term Debt | B44: 150 | C44: 0 | D44: 320 | E44: 0 | F44: 150 | G44: 150 | H44: 168 | I44: 0 | J44: 338 | K44: 447 | L44: 500 | M44: 1934 | N44: Balance Sheet | O44: Short term Debt | Q44: Balance | R44: Pasivos totales corrientes | Z44: 26132 | AA44: 26242 | AB44: 27877 | AC44: 27297 | AD44: 29415 | AE44: =93+3895+8161+3386+2410+2691+298+1967+558+5102 -> 28561 | AF44: =204+3852+5856+2880+1670+1831+281+1521+495+3430 -> 22020 | AG44: =433+3650+2993+3351+797+1217+262+888+302+5399 -> 19292
A45: Short-Term Leases | B45: 9813 | C45: 7443 | D45: 5569 | E45: 10777 | F45: 7040 | G45: 3303 | H45: 2477 | I45: 6489 | J45: 2397 | K45: 3486 | L45: 3869 | M45: 2915 | P45: Capital Leases
A46: Other current liabilities | B46: =B42-SUM(B43:B45) -> 31458 | C46: =C42-SUM(C43:C45) -> 31677 | D46: =D42-SUM(D43:D45) -> 27104 | E46: =E42-SUM(E43:E45) -> 26366 | F46: =F42-SUM(F43:F45) -> 23508 | G46: =G42-SUM(G43:G45) -> 22521 | H46: =H42-SUM(H43:H45) -> 20611 | I46: =I42-SUM(I43:I45) -> 28563 | ... M46: =M42-SUM(M43:M45) -> 21718 | N46: Balance Sheet | R46: + Préstamos CP | Z46: 7303 | AA46: 6967 | AB46: 4708 | AC46: 3679 | AD46: 5287 | AE46: 5660 | AF46: 3925 | AG46: 5701
A47: Non-current Liabilities | B47: =B51-B42 -> 238365 | C47: =C51-C42 -> 237646 | D47: =D51-D42 -> 208979 | E47: =E51-E42 -> 185464 | F47: =F51-F42 -> 173754 | G47: =G51-G42 -> 181010 | H47: =H51-H42 -> 191316 | I47: =I51-I42 -> 192695 | ... M47: =M51-M42 -> 163730 | N47: Balance Sheet | O47: Total non current liabilities
A48: Long-Term Debt | B48: 139509 | C48: 142500 | D48: 122257 | E48: 99932 | F48: 105284 | G48: 113004 | H48: 104818 | I48: 103240 | J48: 110536 | K48: 89547 | L48: 47618 | M48: 50303 | N48: Balance Sheet | O48: Long term debt | Z48: =Z44-Z46 -> 18829 | AA48: =AA44-AA46 -> 19275 | AB48: =AB44-AB46 -> 23169 | AC48: =AC44-AC46 -> 23618 | AD48: =AD44-AD46 -> 24128 | AE48: =AE44-AE46 -> 22901 | AF48: =AF44-AF46 -> 18095 | AG48: =AG44-AG46 -> 13591
A49: Long-Term Leases | B49: 1167 | C49: 925 | D49: 916 | E49: 780 | F49: 589 | G49: 638 | H49: 615 | I49: 0 | J49: 0 | K49: 111 | L49: 0 | M49: 0 | P49: Capital Lease Obligations (Total LT debt) | Q49: Balance | R49: Pasivos totales no corrientes | Z49: =61491-Z44 -> 35359 | AA49: =63457-AA44 -> 37215 | AB49: =67855-AB44 -> 39978 | AC49: 36721 | AD49: 41973 | AE49: =8415+16529+10956+3583 -> 39483 | AF49: =4505+15932+7584+2654 -> 30675 | AG49: =5652+16195+7420+2179 -> 31446
A50: Other non-current liabilities | B50: =B47-SUM(B48:B49) -> 97689 | C50: =C47-SUM(C48:C49) -> 94221 | D50: =D47-SUM(D48:D49) -> 85806 | E50: =E47-SUM(E48:E49) -> 84752 | F50: =F47-SUM(F48:F49) -> 67881 | G50: =G47-SUM(G48:G49) -> 67368 | H50: =H47-SUM(H48:H49) -> 85883 | I50: =I47-SUM(I48:I49) -> 89455 | ... M50: =M47-SUM(M48:M49) -> 113427 | N50: Balance Sheet | O50: Other non current Liabilities | R50: + Préstamos a largo plazo | Z50: 22818 | AA50: 25169 | AB50: 27784 | AC50: 26719 | AD50: 27752 | AE50: 24944 | AF50: 20437 | AG50: 21847
A51: Total Liabilities | B51: 288536 | C51: 284806 | D51: 248639 | E51: 230332 | F51: 211684 | G51: 214047 | H51: 221656 | I51: 227747 | J51: 220318 | K51: 235262 | L51: 192065 | M51: 194491 | N51: Balance Sheet | O51: Total Liabilities
N52: Balance Sheet | Z52: =Z49-Z50 -> 12541 | AA52: =AA49-AA50 -> 12046 | AB52: =AB49-AB50 -> 12194 | AC52: =AC49-AC50 -> 10002 | AD52: =AD49-AD50 -> 14221 | AE52: =AE49-AE50 -> 14539 | AF52: =AF49-AF50 -> 10238 | AG52: =AG49-AG50 -> 9599
N53: Balance Sheet | Z53: =+Z49+Z44 -> 61491 | AA53: =+AA49+AA44 -> 63457 | AB53: =+AB49+AB44 -> 67855 | AC53: =AC44+AC49 -> 64018 | AD53: =AD49+AD44 -> 71388 | AE53: =AE49+AE44 -> 68044 | AF53: =AF49+AF44 -> 52695 | AG53: =AG49+AG44 -> 50738
A54: Minority Interest | B54: 1319 | C54: 1410 | D54: 1430 | E54: 1440 | F54: 1565 | G54: 1591 | H54: 1508 | I54: 1414 | J54: 1378 | K54: 56580 | L54: 52375 | M54: 49938 | N54: Balance Sheet | O54: Minority Interest | P54: non Redeemable
N55: Balance Sheet
A56: Shareholder's Equity | B56: =B38-B51-B54 -> 89825 | C56: =C38-C51-C54 -> 80380 | D56: =D38-D51-D54 -> 66412 | E56: =E38-E51-E54 -> 59955 | F56: =F38-F51-F54 -> 51580 | G56: =G38-G51-G54 -> 41505 | H56: =H38-H51-H54 -> 21016 | I56: =I38-I51-I54 -> 15014 | ... M56: =M38-M51-M54 -> -13968 | N56: Balance Sheet | Q56: Balance | R56: + Participación minoritaria/no dominante
A58: CASH FLOW
A59: Operating CF | B59: 37141 | C59: 39539 | D59: 41768 | E59: 35746 | F59: 34339 | G59: 24318 | H59: 21689 | I59: 39027 | J59: 30631 | K59: 38818 | L59: 31486 | M59: 29780
A60: Net Income | B60: 21748 | C60: 22618 | D60: 18348 | E60: 19788 | F60: 16039 | G60: 30550 | H60: 13608 | I60: 18375 | J60: 11956 | K60: 23547 | L60: 10557 | M60: 10198
A61: Depreciation & Amortization | B61: 17099 | C61: 16206 | D61: 16720 | E61: 16682 | F61: 17403 | G61: 16954 | H61: 15928 | I61: 16017 | J61: 16533 | K61: 16606 | L61: 16460 | M61: 16496
A62: Changes in assets and liabilities | B62: -4234 | C62: -983 | D62: 2836 | E62: -3614 | F62: -2637 | G62: -8673 | H62: -10040 | I62: 1129 | J62: -5248 | K62: -2959 | L62: -3826 | M62: -5179 | P62: changes in working Capital
A63: Other Adjustments | B63: =B59-B60-B61-B62 -> 2528 | C63: =C59-C60-C61-C62 -> 1698 | D63: =D59-D60-D61-D62 -> 3864 | E63: =E59-E60-E61-E62 -> 2890 | F63: =F59-F60-F61-F62 -> 3534 | G63: =G59-G60-G61-G62 -> -14513 | H63: =H59-H60-H61-H62 -> 2193 | I63: =I59-I60-I61-I62 -> 3506 | ... M63: =M59-M60-M61-M62 -> 8265
A64: Investing CF | B64: -28662 | C64: -67153 | D64: -23512 | E64: -17581 | F64: -17934 | G64: -18456 | H64: -9874 | I64: -30043 | J64: -15856 | K64: -14833 | L64: -20502 | M64: -17250
A65: Net Capex | B65: -26740 | C65: -67882 | D65: -20318 | E65: -18837 | F65: -18087 | G65: -17830 | H65: -17593 | I65: -27717 | J65: -17545 | K65: -17184 | L65: -20110 | M65: -16244 | P65: Capital Expenditures
A66: Investments & Acquisitions | B66: 248 | C66: -4065 | D66: -520 | E66: -29 | F66: -230 | G66: -5880 | H66: -3765 | I66: -3545 | J66: -185 | K66: -494 | L66: -913 | M66: -2018 | P66: Acquisition of Business
A67: Other Inflows (Outflows) | B67: =B64-B65-B66 -> -2170 | C67: =C64-C65-C66 -> 4794 | D67: =D64-D65-D66 -> -2674 | E67: =E$64-E$65-E$66 -> 1285 | F67: =F$64-F$65-F$66 -> 383 | G67: =G$64-G$65-G$66 -> 5254 | H67: =H$64-H$65-H$66 -> 11484 | I67: =I$64-I$65-I$66 -> 1219 | J67: =J$64-J$65-J$66 -> 1874 | K67: =K$64-K$65-K$66 -> 2845 | L67: =L$64-L$65-L$66 -> 521 | M67: =M$64-M$65-M$66 -> 1012
A68: Financing CF | B68: -8529 | C68: 8277 | D68: 1325 | E68: -18164 | F68: -15377 | G68: -6151 | H68: -13376 | I68: -15112 | J68: -57705 | K68: 26450 | L68: -21253 | M68: -5836
A69: Debt Borrowing | B69: 17912 | C69: 41417 | D69: 31457 | E69: 18655 | F69: 10777 | G69: 31997 | H69: 17950 | I69: 6667 | J69: 30967 | K69: 49166
A70: Debt Repayment | B70: -13564 | C70: -18863 | D70: -17188 | E70: -23886 | F70: -15348 | G70: -24407 | H70: -19308 | I70: -9684 | J70: -18144 | K70: -8305
A71: Lease Increases | B71: 0 | C71: 0 | D71: 0 | E71: 0 | F71: 0 | G71: 0 | H71: 0 | I71: 0 | J71: 0 | K71: 0
A72: Lease Payments | B72: 0 | C72: 0 | D72: 0 | E72: 0 | F72: 0 | G72: 0 | H72: 0 | I72: 0 | J72: 0 | K72: 0
A73: Dividends | B73: -10805 | C73: -10445 | D73: -10232 | E73: -10016 | F73: -9772 | G73: -9472 | H73: -9262 | I73: -8538 | J73: -7803 | K73: -5936 | L73: -5230 | M73: -5555 | N73: cash flows FINANCING | O73: Dividends paid
A74: Share buyback | B74: 0 | C74: 0 | D74: 0 | E74: 0 | F74: 0 | G74: 0 | H74: 0 | I74: -5134 | J74: 0 | K74: -153 | N74: cash flows FINANCING | O74: =+A74 -> Share buyback
A75: Other Inflows (Outflows) | B75: =B68-B69-B70-B71-B72-B73-B74 -> -2072 | C75: =C68-C69-C70-C71-C72-C73-C74 -> -3832 | D75: =D68-D69-D70-D71-D72-D73-D74 -> -2712 | E75: =E68-E69-E70-E71-E72-E73-E74 -> -2917 | F75: =F68-F69-F70-F71-F72-F73-F74 -> -1034 | G75: =G68-G69-G70-G71-G72-G73-G74 -> -4269 | H75: =H68-H69-H70-H71-H72-H73-H74 -> -2756 | I75: =I68-I69-I70-I71-I72-I73-I74 -> 1577 | ... M75: =M68-M69-M70-M71-M72-M73-M74 -> -281 | P75: 0,1B - 2015
A76: FX
A77: Changes in cash | B77: =B59+B64+B68+B76 -> -50 | C77: =C59+C64+C68+C76 -> -19337 | D77: =D59+D64+D68+D76 -> 19581 | E77: =E59+E64+E68+E76 -> 1 | F77: =F59+F64+F68+F76 -> 1028 | G77: =G59+G64+G68+G76 -> -289 | H77: =H59+H64+H68+H76 -> -1561 | I77: =I59+I64+I68+I76 -> -6128 | ... M77: =M59+M64+M68+M76 -> 6694
O78: (Vitalis will later fill this info)
A79: Other Data | E79: Corporate Bonds 3, 5 Y 10 | H79: Average Price | J79: Moody's | K79: YTM | L79: DIVISA
A80: Number of employees | B80: 142000 | C80: 10-K | N80: bloomberg
A81: Shares Outstanding (Thousands) | B81: 285620 | C81: Yahoo finance | N81: bloomberg
A82: Float | B82: =OP!M19 -> 0.9997 | C82: Yahoo finance | N82: bloomberg
A83: Insiders Own | B83: =OP!M20 -> 0.0003 | C83: Yahoo finance | N83: bloomberg
A84: Fitch/ S&P Rating | B84: =OP!M22 -> BBB+ | C84: 10-K | N84: bloomberg
A85: Dividend Yield(Yahoo Finance) | B85: =Peers!C35 -> 1.8878855 | C85: Yahoo finance | N85: bloomberg
A86: Daily Volume in Millions of USD | C86: Yahoo Finance | N86: bloomberg
B87: 2020 | C87: =B87+1 -> 2021 | D87: =C87+1 -> 2022
A88: Short % of Float | E88: Yahoo Finance
A89: EPS | E89: Yahoo Finance

Sheet Sector Impact
E2: Sector | F2: Sub-Industry | H2: Low | K2: Sector | L2: Environment | Q2: Social
E3: Communication Services | F3: Interactive Home Entertainment | H3: Medium | L3: CO2 | M3: Water | N3: Energy | O3: Waste | P3: Degradation | Q3: Turnover | R3: Compensation | S3: Reputation | T3: Discrimination | U3: Security | V3: Damage | W3: Pension | X3: Supply | Y3: Community | Z3: Public | AA3: Litigation
E4: Communication Services | F4: Interactive Media & Services | H4: High | K4: Communication Services | L4: Low | M4: Low | N4: Medium | O4: Low | P4: Low | Q4: Medium | R4: Medium | S4: Low | T4: Low | U4: High | V4: Low | W4: Low | X4: Low | Y4: Low | Z4: Low | AA4: Medium
B5: Environmental | E5: Communication Services | F5: Integrated Telecommunication Services | H5: Very High | K5: Consumer Discretionary | L5: Low | M5: Low | N5: Medium | O5: Medium | P5: Low | Q5: Medium | R5: Medium | S5: Low | T5: Low | U5: Medium | V5: Medium | W5: Medium | X5: High | Y5: Low | Z5: High | AA5: Low
B6: Direct CO2 emissions | E6: Communication Services | F6: Cable & Satellite | K6: Consumer Staples | L6: High | M6: Very High | N6: High | O6: High | P6: High | Q6: Medium | R6: High | S6: High | T6: Low | U6: Medium | V6: Medium | W6: Low | X6: High | Y6: Low | Z6: Very High | AA6: Low
B7: Total Water Use | E7: Communication Services | F7: Broadcasting | K7: Energy | L7: Very High | M7: Very High | N7: Medium | O7: Very High | P7: High | Q7: High | R7: Medium | S7: Medium | T7: Medium | U7: Medium | V7: High | W7: Medium | X7: Medium | Y7: High | Z7: High | AA7: Low
K8: Renewable Energy | L8: Low | M8: Low | N8: Low | O8: Medium | P8: Medium | Q8: Low | R8: Medium | S8: Medium | T8: High | U8: Medium | V8: Low | W8: Low | X8: Medium | Y8: Medium | Z8: High | AA8: Low
B9: Total Energy Consumption | E9: Communication Services | F9: Movies & Entertainment | K9: Financials | L9: Low | M9: Low | N9: Low | O9: Low | P9: Low | Q9: Low | R9: Low | S9: Medium | T9: High | U9: Medium | V9: Low | W9: Low | X9: Low | Y9: Low | Z9: Medium | AA9: Low
K10: Forestry | L10: Low | M10: Medium | N10: Low | O10: Medium | P10: High | Q10: Low | R10: Low | S10: Low | T10: Low | U10: Low | V10: Low | W10: Low | X10: Low | Y10: Medium | Z10: Low | AA10: Low
B11: Waste Management | E11: Communication Services | F11: Advertising | K11: Health Care | L11: Low | M11: Medium | N11: Low | O11: Low | P11: Low | Q11: Low | R11: Low | S11: Medium | T11: Low | U11: High | V11: Low | W11: Low | X11: Low | Y11: Low | Z11: Low | AA11: Low
B12: Land Degradation/Deforestation/Biodiversity loss/Animal sufering/... | E12: Communication Services | F12: Alternative Carriers | K12: Industrials | L12: Very High | M12: Very High | N12: Very High | O12: High | P12: High | Q12: Low | R12: Medium | S12: High | T12: Very High | U12: Medium | V12: Very High | W12: Medium | X12: Very High | Y12: Very High | Z12: Very High | AA12: High
B13: Social | E13: Communication Services | F13: Publishing | K13: Information Technology | L13: Medium | M13: Low | N13: High | O13: Low | P13: Low | Q13: Low | R13: Low | S13: Low | T13: Low | U13: High | V13: Low | W13: Low | X13: Low | Y13: Low | Z13: Medium | AA13: Very High
B14: Employee turnover | E14: Communication Services | F14: Wireless Telecommunication Services | K14: Materials | L14: Very High | M14: Very High | N14: Very High | O14: Very High | P14: High | Q14: High | R14: High | S14: Medium | T14: High | U14: Low | V14: Very High | W14: Medium | X14: Medium | Y14: Very High | Z14: High | AA14: Medium
B15: Salaries and compensation | E15: Consumer Discretionary | F15: Automotive Retail | K15: Real Estate | L15: Low | M15: Low | N15: Medium | O15: Low | P15: Low | Q15: Medium | R15: Low | S15: Low | T15: Low | U15: High | V15: Low | W15: Medium | X15: Low | Y15: Medium | Z15: Low | AA15: Low
B16: Reputational issues | E16: Consumer Discretionary | F16: Internet & Direct Marketing Retail | K16: Utilities | L16: Very High | M16: High | N16: High | O16: Medium | P16: High | Q16: Low | R16: Medium | S16: Medium | T16: Low | U16: Medium | V16: Medium | W16: Medium | X16: Medium | Y16: Low | Z16: Medium | AA16: Low
B17: Discrimination issues | E17: Consumer Discretionary | F17: Auto Parts & Equipment
B18: Job security | E18: Consumer Discretionary | F18: Specialty Stores
B19: Health injuries | E19: Consumer Discretionary | F19: Computer & Electronics Retail | L19: Communication Services | M19: Consumer Discretionary | N19: Consumer Staples | O19: Energy | P19: Financials | Q19: Health Care | R19: Industrials | S19: Information Technology | T19: Materials | U19: Real Estate | V19: Utilities
B20: PXP? | E20: Consumer Discretionary | F20: Hotels, Resorts & Cruise Lines | L20: Interactive Home Entertainment | M20: Automotive Retail | N20: Tobacco | O20: Oil & Gas Exploration & Production | P20: Life & Health Insurance | Q20: Health Care Equipment | R20: Industrial Conglomerates | S20: IT Consulting & Other Services | T20: Industrial Gases | U20: Office REITs | V20: Independent Power Producers & Energy Traders
B21: Supply chain | E21: Consumer Discretionary | F21: Restaurants | L21: Interactive Media & Services | M21: Internet & Direct Marketing Retail | N21: Agricultural Products | O21: Oil & Gas Equipment & Services | P21: Property & Casualty Insurance | Q21: Pharmaceuticals | R21: Airlines | S21: Application Software | T21: Specialty Chemicals | U21: Specialized REITs | V21: Electric Utilities
B22: Community involvement | E22: Consumer Discretionary | F22: Homebuilding | L22: Integrated Telecommunication Services | M22: Auto Parts & Equipment | N22: Distillers & Vintners | O22: Integrated Oil & Gas | P22: Consumer Finance | Q22: Health Care Supplies | R22: Building Products | S22: Semiconductors | T22: Paper Packaging | U22: Residential REITs | V22: Multi-Utilities
B23: Public Sector | E23: Consumer Discretionary | F23: General Merchandise Stores | L23: Cable & Satellite | M23: Specialty Stores | N23: Packaged Foods & Meats | O23: Oil & Gas Refining & Marketing | P23: Asset Management & Custody Banks | Q23: Health Care Distributors | R23: Electrical Components & Equipment | S23: Internet Services & Infrastructure | T23: Metal & Glass Containers | U23: Real Estate Services | V23: Water Utilities
B24: Litigation | E24: Consumer Discretionary | F24: Automobile Manufacturers | L24: Broadcasting | M24: Computer & Electronics Retail | N24: Household Products | O24: Oil & Gas Storage & Transportation | P24: Insurance Brokers | Q24: Biotechnology | R24: Aerospace & Defense | S24: Electronic Components | T24: Fertilizers & Agricultural Chemicals | U24: Industrial REITs | V24: Gas Utilities
E25: Consumer Discretionary | F25: Apparel Retail | L25: Movies & Entertainment | M25: Hotels, Resorts & Cruise Lines | N25: Soft Drinks | P25: Multi-line Insurance | Q25: Managed Health Care | R25: Air Freight & Logistics | S25: Technology Hardware, Storage & Peripherals | T25: Commodity Chemicals | U25: Retail REITs
E26: Consumer Discretionary | F26: Consumer Electronics | L26: Advertising | M26: Restaurants | N26: Hypermarkets & Super Centers | P26: Diversified Banks | Q26: Life Sciences Tools & Services | R26: Construction Machinery & Heavy Trucks | S26: Semiconductor Equipment | T26: Diversified Chemicals | U26: Health Care REITs
E27: Consumer Discretionary | F27: Apparel, Accessories & Luxury Goods | L27: Alternative Carriers | M27: Homebuilding | N27: Personal Products | P27: Multi-Sector Holdings | Q27: Health Care Technology | R27: Diversified Support Services | S27: Communications Equipment | T27: Copper | U27: Hotel & Resort REITs
E28: Consumer Discretionary | F28: Leisure Products | L28: Publishing | M28: General Merchandise Stores | N28: Food Retail | P28: Financial Exchanges & Data | Q28: Health Care Services | R28: Railroads | S28: Data Processing & Outsourced Services | T28: Construction Materials
E29: Consumer Discretionary | F29: Home Improvement Retail | L29: Wireless Telecommunication Services | M29: Automobile Manufacturers | N29: Brewers | P29: Investment Banking & Brokerage | Q29: Health Care Facilities | R29: Industrial Machinery | S29: Technology Distributors | T29: Gold
E30: Consumer Discretionary | F30: Casinos & Gaming | M30: Apparel Retail | N30: Food Distributors | P30: Regional Banks | R30: Agricultural & Farm Machinery | S30: Electronic Equipment & Instruments | T30: Steel
E31: Consumer Discretionary | F31: Home Furnishings | M31: Consumer Electronics | N31: Drug Retail | P31: Reinsurance | R31: Research & Consulting Services | S31: Systems Software
E32: Consumer Discretionary | F32: Distributors | M32: Apparel, Accessories & Luxury Goods | P32: Thrifts & Mortgage Finance | R32: Construction & Engineering | S32: Electronic Manufacturing Services
E33: Consumer Discretionary | F33: Housewares & Specialties | M33: Leisure Products | R33: Trucking
E34: Consumer Discretionary | F34: Household Appliances | M34: Home Improvement Retail | R34: Environmental & Facilities Services
E35: Consumer Staples | F35: Tobacco | M35: Casinos & Gaming | R35: Human Resource & Employment Services
E36: Consumer Staples | F36: Agricultural Products | M36: Home Furnishings | R36: Trading Companies & Distributors
E37: Consumer Staples | F37: Distillers & Vintners | M37: Distributors
E38: Consumer Staples | F38: Packaged Foods & Meats | M38: Housewares & Specialties
E39: Consumer Staples | F39: Household Products | M39: Household Appliances
E40: Consumer Staples | F40: Soft Drinks
E41: Consumer Staples | F41: Hypermarkets & Super Centers
E42: Consumer Staples | F42: Personal Products
E43: Consumer Staples | F43: Food Retail
E44: Consumer Staples | F44: Brewers
E45: Consumer Staples | F45: Food Distributors
E46: Consumer Staples | F46: Drug Retail
E47: Energy | F47: Oil & Gas Exploration & Production
E48: Energy | F48: Oil & Gas Equipment & Services
E49: Energy | F49: Integrated Oil & Gas
E50: Energy | F50: Oil & Gas Refining & Marketing
E51: Energy | F51: Oil & Gas Storage & Transportation
... E128: Utilities | F128: Gas Utilities
