Workbook
Name Benchmark: [1]ControlsH!$B$3
Name BestConsOv: #REF!
Name Broker_Name: OFFSET(#REF!,0,0,[1]ControlsH!$E$5, 1)
Name calCODE: [1]ControlsH!$C$4
Name Chart_Benchmark_100_Size: OFFSET(#REF!, 0, 0, [1]ControlsH!$E$3, 1)
Name Chart_Date_Size: OFFSET(#REF!, 0, 0, [1]ControlsH!$E$3, 1)
Name Chart_Date_VAL1_Size: OFFSET(#REF!, 0, 0, [1]ControlsH!$I$3, 1)
Name Chart_Date_VAL2_Size: OFFSET(#REF!, 0, 0, [1]ControlsH!$I$5, 1)
Name Chart_Peer_100_Size: OFFSET(#REF!, 0, 0, [1]ControlsH!$E$3, 1)
Name Chart_Price_100_Size: OFFSET(#REF!, 0, 0, [1]ControlsH!$E$3, 1)
Name Chart_Price_Size: OFFSET(#REF!, 0, 0, [1]ControlsH!$E$3, 1)
Name Chart_VAL1_FY1_Size: OFFSET(#REF!, 0, 0, [1]ControlsH!$F$3, 1)
Name Chart_VAL1_FY2_Size: OFFSET(#REF!, 0, 0, [1]ControlsH!$G$3, 1)
Name Chart_VAL1_FY3_Size: OFFSET(#REF!, 0, 0, [1]ControlsH!$H$3, 1)
Name Chart_VAL2_FY1_Size: OFFSET(#REF!, 0, 0, [1]ControlsH!$F$5, 1)
Name Chart_VAL2_FY2_Size: OFFSET(#REF!, 0, 0, [1]ControlsH!$G$5, 1)
Name Chart_VAL2_FY3_Size: OFFSET(#REF!, 0, 0, [1]ControlsH!$H$5, 1)
Name Chart_Volume_Size: OFFSET(#REF!, 0, 0, [1]ControlsH!$E$3, 1)
Name compNAME: [1]ControlsH!$B$6
Name CURRENCY: [1]ControlsH!$B$9
Name currPRICE: [1]Overview!$E$19
Name custBenchmark: [1]Overview!$C$9
Name custED: #REF!
Name custSD: #REF!
Name dayCODE: [1]ControlsH!$C$5
Name ED: [1]ControlsH!$B$5
Name ESTBrokersItem: #REF!
Name ESTBrokersPeriod: #REF!
Name ESTDetailBroker: #REF!
Name ESTDetailBroker2: #REF!
Name ESTDetailPeriod: #REF!
Name EstDetPerO: #REF!
Name EstDetPerT: #REF!
Name FinancialsPeriod: #REF!
Name fundTICKER: [1]ControlsH!$B$15
Name GraphValRatio1: #REF!
Name GraphValRatio2: #REF!
Name Index1: #REF!
Name Lang: [1]Overview!$D$11
Name newCrncy: [1]ControlsH!$B$21:$B$199
Name newEstBrokerPeriod: #REF!
Name newEstBrokersItem: #REF!
Name newEstDetailBroker: #REF!
Name newEstDetailBroker2: #REF!
Name newEstDetailPeriod: #REF!
Name newFinancialsPeriod: #REF!
Name newOverviewCon: #REF!
Name newOverviewYear: #REF!
Name newOwners: #REF!
Name newPeersRatio: #REF!
Name newPeriod: #REF!
Name newValRatio1: #REF!
Name newValRatio2: #REF!
Name OverviewValRatioPeriod: [1]Overview!$D$30
Name PeerDate1: [1]Peers!$S$11
Name peerHist1: #REF!
Name PeerIndex: [1]ControlsH!$F$35:$F$36
Name Peers: OFFSET([1]Peers!$C$18,0,0,MAX(COUNTA([1]Peers!$C$18:$C$47),1),1)
Name peersWEIGHT: [1]ControlsH!$B$13
Name PERIODICITY: [1]ControlsH!$C$3

Sheet OP
B2: (date of last modification) | C2: Analista: Research | D2: Report (quarter): (date) | E2: ANSYS Inc. (ANSS) | K2: (stock market) | L2: SIC: Sí
B3: #VALUE! | D3: DESCRIPTION: (write relevant information about the company, 1-2 lines is enough. If you find segments and key products relevant for this part, you can also write it here)
D4: CEO & BOARD: Name (Chairman or not; age; board member since; current board presence; previous jobs); note: *Independent members, green: new members
B5: Millones de USD
B6: Acción | D6: Liquidez y Solvencia | F6: =Segments!B2 -> Regions (2023) | I6: Rentabilidad (2024) | K6: Múltiplos
B7: Último Precio | C7: 334 | D7: Activo: | E7: =Cifras_en_Millones!B45 -> 8051.431 | H7: %Vts; %Op.Mg.; D | I7: Año termina: | J7: 31 December | K7: Float: | L7: =(96.87+0.61)/100 -> 0.9748
B8: Outstanding Shares | C8: 87.45 | D8: Pasivo: | E8: =Cifras_en_Millones!B57 -> 1096 | F8: =Segments!B4 -> US | H8: =+Segments!J4 -> 49%; NA; 18% | K8: Insiders Own: | L8: 0.0061
B9: Market Cap. | C9: =C7*C8 -> 29208.3 | D9: Cash/Precio | E9: =1000000*C11/C8 -> 16543659 | F9: =Segments!B5 -> Germany | H9: =+Segments!J5 -> 8%; NA; 5% | I9: EBIT | K9: b (Bloomberg; Yahoo) | L9: 1.12
B10: +Deuda Total | C10: =Cifras_en_Millones!B60 -> 86.93 | D10: Ebidta/CIF | F10: =Segments!B6 -> Japan | H10: =+Segments!J6 -> 7%; NA; -9% | I10: +Dep&Amort | J10: =Cifras_en_Millones!B17 -> 142.672 | K10: Calificación (S&P)
B11: -Cash | C11: =Cifras_en_Millones!B40 -> 1446.743 | D11: Deuda/Ebidta | E11: =Cifras_en_Millones!B60/Cifras_en_Millones!B19 -> 0.10063626 | F11: =Segments!B7 -> China and Hong Kong | H11: =+Segments!J7 -> 5%; NA; 14% | I11: =EBIDTA | J11: =J9+J10 -> 142.672 | K11: Precio/Valor en libros | L11: =((C7*C8)/1000000)/(E7-E8) -> 4.1993516e-06
B12: =Enterprise Value | C12: =C9+C10-C11 -> 27848.487 | D12: "Otros activos"/Activo | E12: =Cifras_en_Millones!B44/Cifras_en_Millones!B45 -> 0.68213862 | F12: =Segments!B8 -> South Korea | H12: =+Segments!J8 -> 4%; NA; 6% | I12: Utilidad Neta | J12: =Cifras_en_Millones!B23 -> 575.692 | K12: FNP(p)/Activos | L12: =J18/E7 -> 0
B13: Tenencia % (nac/int'l) | D13: Deuda/Activo | E13: =C10/E7 -> 0.010796838 | F13: Company reports only one product segment | I13: UPA | J13: =1000000*J12/C8 -> 6583098.9 | K13: Precio/Utilidad(p) | L13: =C9/J17 -> 54.772683 | N13: =C10/J11 -> 0.60929965
B14: t liq. (Pos prom./Vol.) | D14: Margen de Operación (p) | E14: =Cifras_en_Millones!B12 -> 0.2822327 | G14: NA | H14: NA | I14: ROA | J14: =J12/E7 -> 0.071501824 | K14: EV/Activos | L14: =C12/E7 -> 3.4588245
B15: % Short | C15: 0.019 | D15: Margen neto (p) | E15: =Cifras_en_Millones!B24 -> 0.22629403 | G15: NA | H15: NA | I15: ROIC | J15: =J12/(E7-(E8-C10)) -> 0.081747016 | K15: EV/Ebidta (p) | L15: =C12/J16 -> 35.088333
B16: Semáforo ESG | D16: Ebidta/Ingresos(p) | E16: =Cifras_en_Millones!B19/Cifras_en_Millones!B5 -> 0.3395456 | I16: Ebidta(p) | J16: =AVERAGE(Cifras_en_Millones!B19:D19) -> 793.668 | K16: Precio/FNP (p) | L16: =C9/J18 -> #DIV/0!
B17: E | D17: CIF/Deuda Neta Promedio | I17: Utilidad Neta (p) | J17: =AVERAGE(Cifras_en_Millones!B23:D23) -> 533.264 | K17: Bonos 1;5;40a (USD) | L17: 4.0%; 4.4%; 5% | N17: 12
B18: S | I18: FNP (p) | J18: =SUM(F35:F37)/3 -> 0 | K18: TDY(p)/Precio | L18: =SUM(E35:E37)/(3*C9) -> 0
B19: G | I19: Tax (p) últ. 5a | J19: 0.16 | K19: Div. Yield: | L19: =K33/C9 -> 0
B20: Tesis de inversión | H20: Acuerdo | I20: Supuestos de valuación | L20: DCF Value
B21: (Investment thesis) | H21: Mantener sin elevar posición | I21: VER DCF | L21: =DCFF!D66 -> 379.47843
B23: KSF | H23: PO / Precio Stand By | L23: =DCFF!D65 -> 0.13616296
H24: =DCFF!D71 -> -0.086599655 | I24: Tasa de descuento: | J24: =DCFF!D47 -> 0.0806
B25: Año | C25: Ingresos | D25: Margen Operativo | E25: Div.+Recompra | F25: FNP | G25: Deuda/Activo | H25: Depreciación | I25: Capex + Adq | J25: Cash Flow
B26: =B27-1 -> 2013 | C26: 861.3 | D26: 0.37373737 | K26: 2022 | L26: =K26-1 -> 2021
B27: =B28-1 -> 2014 | C27: 936 | D27: 0.37126068 | J27: Profit | N27: =C27/C26-1 -> 0.086729363 | O27: =D27/D26-1 -> -0.0066268191
B28: =B29-1 -> 2015 | C28: 942.8 | D28: 0.3751591 | J28: Cash Flow from Operations (BWC) | N28: =C28/C27-1 -> 0.0072649573 | O28: =D28/D27-1 -> 0.010500484 | P28: =E28/E27-1 -> #DIV/0! | Q28: =F28/F27-1 -> #DIV/0! | R28: =H28/H27-1 -> #DIV/0! | S28: =I28/I27-1 -> #DIV/0! | BT28: 4303
B29: =B30-1 -> 2016 | C29: 988.5 | D29: 0.38057663 | J29: Working Capital | N29: =C29/C28-1 -> 0.048472635 | O29: =D29/D28-1 -> 0.014440622 | P29: =E29/E28-1 -> #DIV/0! | Q29: =F29/F28-1 -> #DIV/0! | R29: =H29/H28-1 -> #DIV/0! | S29: =I29/I28-1 -> #DIV/0! | BT29: 3066
B30: =B31-1 -> 2017 | C30: 1095.3 | D30: 0.35670593 | J30: Investing Activities | N30: =C30/C29-1 -> 0.10804249 | O30: =D30/D29-1 -> -0.062722469 | P30: =E30/E29-1 -> #DIV/0! | Q30: =F30/F29-1 -> #DIV/0! | R30: =H30/H29-1 -> #DIV/0! | S30: =I30/I29-1 -> #DIV/0! | BT30: 3283
B31: =B32-1 -> 2018 | C31: 1293.6 | D31: 0.36842919 | J31: Capex | N31: =C31/C30-1 -> 0.18104629 | O31: =D31/D30-1 -> 0.032865348 | P31: =E31/E30-1 -> #DIV/0! | Q31: =F31/F30-1 -> #DIV/0! | R31: =H31/H30-1 -> #DIV/0! | S31: =I31/I30-1 -> #DIV/0!
B32: =B33-1 -> 2019 | C32: 1515.9 | D32: 0.33973217 | J32: Adquisiones | N32: =C32/C31-1 -> 0.17184601 | O32: =D32/D31-1 -> -0.077890184 | P32: =E32/E31-1 -> #DIV/0! | Q32: =F32/F31-1 -> #DIV/0! | R32: =H32/H31-1 -> #DIV/0! | S32: =I32/I31-1 -> #DIV/0!
B33: =B34-1 -> 2020 | C33: 1681.3 | D33: 0.29524772 | J33: Dividends | N33: =C33/C32-1 -> 0.1091101 | O33: =D33/D32-1 -> -0.13093975 | P33: =E33/E32-1 -> #DIV/0! | Q33: =F33/F32-1 -> #DIV/0! | R33: =H33/H32-1 -> #DIV/0! | S33: =I33/I32-1 -> #DIV/0!
B34: =B35-1 -> 2021 | C34: 1906.7 | D34: 0.26920858 | J34: Stock Repurchases | N34: =C34/C33-1 -> 0.13406293 | O34: =D34/D33-1 -> -0.088194226 | P34: =E34/E33-1 -> #DIV/0! | Q34: =F34/F33-1 -> #DIV/0! | R34: =H34/H33-1 -> #DIV/0! | S34: =I34/I33-1 -> #DIV/0!
B35: =B36-1 -> 2022 | C35: 2065.6 | D35: 0.28693842 | J35: Endeudamiento Neto | N35: =C35/C34-1 -> 0.083337704 | O35: =D35/D34-1 -> 0.065859118 | P35: =E35/E34-1 -> #DIV/0! | Q35: =F35/F34-1 -> #DIV/0! | R35: =H35/H34-1 -> #DIV/0! | S35: =I35/I34-1 -> #DIV/0!
B36: =B37-1 -> 2023 | C36: 2269.9 | D36: 0.27582713 | J36: Otros Financiemientos | N36: =C36/C35-1 -> 0.098905887 | O36: =D36/D35-1 -> -0.038723608
B37: 2024 | C37: 2544 | D37: 0.2822327 | N37: =C37/C36-1 -> 0.12075422 | O37: =D37/D36-1 -> 0.023223152
B38: 2024 Est. | C38: =DCFF!H6 -> 2509 | D38: =DCFF!H7 -> 0.23595058
B39: CAGR | C39: =(C37/C32)^(1/5)-1 -> 0.10909644 | D39: =(D37/D26)^(1/11)-1 -> -0.025206105 | J39: FX | K39: 0 | L39: 0
B40: AAG | C40: =AVERAGE(N27:N37) -> 0.1045066 | D40: =AVERAGE(O27:O37) -> -0.023473485 | J40: D Cash and Equivalents | K40: =K28+K29+K30+K33+K34+K35+K36+K39 -> 0 | L40: =L28+L29+L30+L33+L34+L35+L36+L39 -> 0
B41: CVAR | C41: =STDEV(C26:C37)/AVERAGE(C26:C37) -> 0.38473903 | D41: =STDEV(D26:D37)/AVERAGE(D26:D37) -> 0.13638766 | J41: Inv/D Vts | K41: =SUM(I33:I37)/(C37-C32) -> 0 | L41: =(SUM(I33:I37)-SUM(H33:H37))/(C37-C32) -> 0
B42: Último Año | C42: =C37/C36-1 -> 0.12075422 | D42: =D37/D36-1 -> 0.023223152 | J42: t inversiones; t adq. neto dep. | K42: =K41/E14 -> 0 | L42: =L41/E14 -> 0
B43: Pros y Cons | I43: (historical stock price of the company and its peers; source: Bloomberg)
B44: （write a text explaining pros and cons of the company)
B45: Riesgos
B46: (risks)
B47: Oportunidades
B48: (opportunities)
B49: CHECKLIST
B50: Crecimiento | C50: Riesgos claros | D50: ESG | E50: Peer Analysis | F50: Consenso | G50: KSF | H50: PO/Stand By | I50: (write the peers' names here)
B51: (p) = Promedio de últimos 3 años
B52: NOTES:

Sheet COVID-19 impact
A1: https://www.apple.com/newsroom/2020/03/apples-covid-19-response/ | G1: https://glg.it/articles/how-might-the-wuhan-coronavirus-impact-apples-supply-chain/ | N1: https://www.cnbc.com/2020/02/18/the-significance-of-apples-coronavirus-warning.html
A2: March 13 | G2: January 29 | N2: Ferbuary 18
A23: Otros:
A24: https://www.macrumors.com/guide/covid-19-coronavirus/

Sheet Cifras_en_Millones
A1: =Cifras_Originales!G5 -> (Company name) ((ticker))
A2: =Cifras_Originales!C4 -> Cifras en Millones de USD
A4: Resultados | B4: 2024 | C4: =Cifras_Originales!B7 -> 2023 | D4: =Cifras_Originales!C7 -> 2022 | E4: =Cifras_Originales!D7 -> 2021 | F4: =Cifras_Originales!E7 -> 2020 | G4: =Cifras_Originales!F7 -> 2019 | H4: =Cifras_Originales!G7 -> 2018 | I4: =Cifras_Originales!H7 -> 2017 | J4: =Cifras_Originales!I7 -> 2016 | ... M4: =Cifras_Originales!L7 -> 2013
A5: Ventas Netas | B5: =Cifras_Originales!N8 -> 2544 | C5: =Cifras_Originales!B8 -> 2269.9 | D5: =Cifras_Originales!C8 -> 2065.6 | E5: =Cifras_Originales!D8 -> 1906.7 | F5: =Cifras_Originales!E8 -> 1681.3 | G5: =Cifras_Originales!F8 -> 1515.9 | H5: =Cifras_Originales!G8 -> 1293.6 | I5: =Cifras_Originales!H8 -> 1095.3 | J5: =Cifras_Originales!I8 -> 988.5 | ... M5: =Cifras_Originales!L8 -> 861.3
A6: Crecimiento vs. Año pasado | B6: =B5/C5-1 -> 0.12075422 | C6: =C5/D5-1 -> 0.098905887 | D6: =D5/E5-1 -> 0.083337704 | E6: =E5/F5-1 -> 0.13406293 | F6: =F5/G5-1 -> 0.1091101 | G6: =G5/H5-1 -> 0.17184601 | H6: =H5/I5-1 -> 0.18104629 | I6: =I5/J5-1 -> 0.10804249 | ... L6: =L5/M5-1 -> 0.086729363
A7: Utilidad Bruta | B7: =Cifras_Originales!N9 -> 2264 | C7: =Cifras_Originales!B9 -> 1998.7 | D7: =Cifras_Originales!C9 -> 1814.9 | E7: =Cifras_Originales!D9 -> 1648.7 | F7: =Cifras_Originales!E9 -> 1456 | G7: =Cifras_Originales!F9 -> 1349.6 | H7: =Cifras_Originales!G9 -> 1137.8 | I7: =Cifras_Originales!H9 -> 945.1 | J7: =Cifras_Originales!I9 -> 841.6 | ... M7: =Cifras_Originales!L9 -> 714.6
A8: porcentaje sobre ventas | B8: =B7/B5 -> 0.88993711 | C8: =C7/C5 -> 0.88052337 | D8: =D7/D5 -> 0.87863091 | E8: =E7/E5 -> 0.86468768 | F8: =F7/F5 -> 0.86599655 | G8: =G7/G5 -> 0.89029619 | H8: =H7/H5 -> 0.87956092 | I8: =I7/I5 -> 0.86286862 | ... M8: =M7/M5 -> 0.82967607
A9: Gastos de Operación | B9: =B5-B11 -> 1826 | C9: =C5-C11 -> 1643.8 | D9: =D5-D11 -> 1472.9 | E9: =E5-E11 -> 1393.4 | F9: =F5-F11 -> 1184.9 | G9: =G5-G11 -> 1000.9 | H9: =H5-H11 -> 817 | I9: =I5-I11 -> 704.6 | ... M9: =M5-M11 -> 539.4
A10: porcentaje sobre ventas | B10: =B9/B5 -> 0.7177673 | C10: =C9/C5 -> 0.72417287 | D10: =D9/D5 -> 0.71306158 | E10: =E9/E5 -> 0.73079142 | F10: =F9/F5 -> 0.70475228 | G10: =G9/G5 -> 0.66026783 | H10: =H9/H5 -> 0.63157081 | I10: =I9/I5 -> 0.64329407 | ... M10: =M9/M5 -> 0.62626263
A11: Utilidad de Operación | B11: =Cifras_Originales!N10 -> 718 | C11: =Cifras_Originales!B10 -> 626.1 | D11: =Cifras_Originales!C10 -> 592.7 | E11: =Cifras_Originales!D10 -> 513.3 | F11: =Cifras_Originales!E10 -> 496.4 | G11: =Cifras_Originales!F10 -> 515 | H11: =Cifras_Originales!G10 -> 476.6 | I11: =Cifras_Originales!H10 -> 390.7 | J11: =Cifras_Originales!I10 -> 376.2 | ... M11: =Cifras_Originales!L10 -> 321.9
A12: porcentaje sobre ventas | B12: =B11/B5 -> 0.2822327 | C12: =C11/C5 -> 0.27582713 | D12: =D11/D5 -> 0.28693842 | E12: =E11/E5 -> 0.26920858 | F12: =F11/F5 -> 0.29524772 | G12: =G11/G5 -> 0.33973217 | H12: =H11/H5 -> 0.36842919 | I12: =I11/I5 -> 0.35670593 | ... M12: =M11/M5 -> 0.37373737
A13: Crecimiento vs año anterior | B13: =B11/C11-1 -> 0.14678166 | C13: =C11/D11-1 -> 0.056352286 | D13: =D11/E11-1 -> 0.15468537 | E13: =E11/F11-1 -> 0.034045125 | F13: =F11/G11-1 -> -0.036116505 | G13: =G11/H11-1 -> 0.080570709 | H13: =H11/I11-1 -> 0.21986179 | I13: =I11/J11-1 -> 0.038543328 | ... L13: =L11/M11-1 -> 0.079527804
A14: CIF (Productos Financieros) | B14: =Cifras_Originales!N11 -> -3.29 | C14: =Cifras_Originales!B11 -> 43.9 | D14: =Cifras_Originales!C11 -> -5.4 | E14: =Cifras_Originales!D11 -> 5 | F14: =Cifras_Originales!E11 -> 4.2 | G14: =Cifras_Originales!F11 -> 56.2 | H14: =Cifras_Originales!G11 -> -13.3 | I14: =Cifras_Originales!H11 -> 55.1 | J14: =Cifras_Originales!I11 -> 38.8 | ... M14: =Cifras_Originales!L11 -> -28.2
A15: Otros Gastos (Productos) | B15: =Cifras_Originales!N12 -> -3.132 | C15: =Cifras_Originales!B12 -> -34 | D15: =Cifras_Originales!C12 -> -17.34 | E15: =Cifras_Originales!D12 -> 2.08 | F15: =Cifras_Originales!E12 -> -2.43 | G15: =Cifras_Originales!F12 -> 7.54 | H15: =Cifras_Originales!G12 -> 10.51 | I15: =Cifras_Originales!H12 -> 4.97 | J15: =Cifras_Originales!I12 -> 4.07 | ... M15: =Cifras_Originales!L12 -> 0.626
A16: Utilidad antes de Impuestos y partidas extra. | B16: =B11-B14-B15 -> 724.422 | C16: =C11-C14-C15 -> 616.2 | D16: =D11-D14-D15 -> 615.44 | E16: =E11-E14-E15 -> 506.22 | F16: =F11-F14-F15 -> 494.63 | G16: =G11-G14-G15 -> 451.26 | H16: =H11-H14-H15 -> 479.39 | I16: =I11-I14-I15 -> 330.63 | ... M16: =M11-M14-M15 -> 349.474
A17: Depreciación y amortización del ejercicio | B17: =Cifras_Originales!N13 -> 142.672 | C17: =Cifras_Originales!B13 -> 132.5 | D17: =Cifras_Originales!C13 -> 114.56 | E17: =Cifras_Originales!D13 -> 106.87 | F17: =Cifras_Originales!E13 -> 106.25 | G17: =Cifras_Originales!F13 -> 78.97 | H17: =Cifras_Originales!G13 -> 59.26 | I17: =Cifras_Originales!H13 -> 67.68 | J17: =Cifras_Originales!I13 -> 69.59 | ... M17: =Cifras_Originales!L13 -> 80.7
A18: Capital de Trabajo | B18: =Cifras_Originales!N14 -> 189 | C18: =Cifras_Originales!B14 -> 1160.3 | D18: =Cifras_Originales!C14 -> 869.3 | E18: =Cifras_Originales!D14 -> 860.1 | F18: =Cifras_Originales!E14 -> 990.4 | G18: =Cifras_Originales!F14 -> 860.4 | H18: =Cifras_Originales!G14 -> 786.4 | I18: =Cifras_Originales!H14 -> 661.7 | J18: =Cifras_Originales!I14 -> 630.3 | ... M18: =Cifras_Originales!L14 -> 627.2
A19: EBITDA (flujo operativo) | B19: =B11-B15+B17 -> 863.804 | C19: =C11-C15+C17 -> 792.6 | D19: =D11-D15+D17 -> 724.6 | E19: =E11-E15+E17 -> 618.09 | F19: =F11-F15+F17 -> 605.08 | G19: =G11-G15+G17 -> 586.43 | H19: =H11-H15+H17 -> 525.35 | I19: =I11-I15+I17 -> 453.41 | ... M19: =M11-M15+M17 -> 401.974
A20: porcentaje sobre ventas | B20: =B19/B5 -> 0.3395456 | C20: =C19/C5 -> 0.34917838 | D20: =D19/D5 -> 0.35079396 | E20: =E19/E5 -> 0.32416741 | F20: =F19/F5 -> 0.35988818 | G20: =G19/G5 -> 0.38685269 | H20: =H19/H5 -> 0.40611472 | I20: =I19/I5 -> 0.41395965 | ... M20: =M19/M5 -> 0.46670614
A21: I.S.R Y P.T.U. | B21: 142.346 | C21: =Cifras_Originales!B17 -> 115.8 | D21: =Cifras_Originales!C17 -> 91.7 | E21: =Cifras_Originales!D17 -> 51.6 | F21: =Cifras_Originales!E17 -> 60.7 | G21: =Cifras_Originales!F17 -> 0 | H21: =Cifras_Originales!G17 -> 60 | I21: =Cifras_Originales!H17 -> 71.3 | J21: =Cifras_Originales!I17 -> 67.7 | ... M21: =Cifras_Originales!L17 -> 104.2
A22: % Tax | B22: =+B21/B16 -> 0.19649597 | C22: =+C21/C16 -> 0.187926 | D22: =+D21/D16 -> 0.14899909 | E22: =+E21/E16 -> 0.10193197 | F22: =+F21/F16 -> 0.12271799 | G22: =+G21/G16 -> 0 | H22: =+H21/H16 -> 0.12515906 | I22: =+I21/I16 -> 0.21564891 | ... M22: =+M21/M16 -> 0.29816238
A23: Utilidad Neta | B23: =Cifras_Originales!N18 -> 575.692 | C23: =Cifras_Originales!B18 -> 500.4 | D23: =Cifras_Originales!C18 -> 523.7 | E23: =Cifras_Originales!D18 -> 454.6 | F23: =Cifras_Originales!E18 -> 433.9 | G23: =Cifras_Originales!F18 -> 451.3 | H23: =Cifras_Originales!G18 -> 419.4 | I23: =Cifras_Originales!H18 -> 259.3 | J23: =Cifras_Originales!I18 -> 265.6 | ... M23: =Cifras_Originales!L18 -> 245.3
A24: porcentaje sobre ventas | B24: =B23/B5 -> 0.22629403 | C24: =C23/C5 -> 0.22045024 | D24: =D23/D5 -> 0.25353408 | E24: =E23/E5 -> 0.23842241 | F24: =F23/F5 -> 0.25807411 | G24: =G23/G5 -> 0.29771093 | H24: =H23/H5 -> 0.3242115 | I24: =I23/I5 -> 0.23673879 | ... M24: =M23/M5 -> 0.28480204
A25: Crecimiento vs año anterior | B25: =B23/C23-1 -> 0.15046363 | C25: =C23/D23-1 -> -0.044491121 | D25: =D23/E23-1 -> 0.15200176 | E25: =E23/F23-1 -> 0.047706845 | F25: =F23/G23-1 -> -0.038555285 | G25: =G23/H23-1 -> 0.07606104 | H25: =H23/I23-1 -> 0.61743155 | I25: =I23/J23-1 -> -0.02371988 | ... L25: =L23/M23-1 -> 0.038320424
A26: Efectivo Generado | B26: =B40-C40 -> 586.543 | C26: =C40-D40 -> 245.8 | D26: =D40-E40 -> -53.3 | E26: =E40-F40 -> -245 | F26: =F40-G40 -> 40.6 | G26: =G40-H40 -> 95 | H26: =H40-I40 -> -104.4 | I26: =I40-J40 -> 59 | ... M26: =M40-N40 -> 742.5
A27: Dividendos | B27: 0 | C27: =Cifras_Originales!B19 -> 0 | D27: =Cifras_Originales!C19 -> 0 | E27: =Cifras_Originales!D19 -> 0 | F27: =Cifras_Originales!E19 -> 0 | G27: =Cifras_Originales!F19 -> 0 | H27: =Cifras_Originales!G19 -> 0 | I27: =Cifras_Originales!H19 -> 0 | J27: =Cifras_Originales!I19 -> 0 | ... M27: =Cifras_Originales!L19 -> 0
A29: Recompra de Acciones | B29: 0 | C29: =Cifras_Originales!B20 -> -47.2 | D29: =Cifras_Originales!C20 -> -69.2 | E29: =Cifras_Originales!D20 -> -175.9 | F29: =Cifras_Originales!E20 -> -294.3 | G29: =Cifras_Originales!F20 -> -282.5 | H29: =Cifras_Originales!G20 -> -294.7 | I29: =Cifras_Originales!H20 -> -257.7 | J29: =Cifras_Originales!I20 -> -67.5 | ... M29: =Cifras_Originales!L20 -> -244.2
A30: FNP | B30: =SUM(B26:B29) -> 586.543 | C30: =SUM(C26:C29) -> 198.6 | D30: =SUM(D26:D29) -> -122.5 | E30: =SUM(E26:E29) -> -420.9 | F30: =SUM(F26:F29) -> -253.7 | G30: =SUM(G26:G29) -> -187.5 | H30: =SUM(H26:H29) -> -399.1 | I30: =SUM(I26:I29) -> -198.7 | ... M30: =SUM(M26:M29) -> 498.3
A31: FNP (ajustado por deuda) | B31: =B30-(B60-C60) -> 552.713 | C31: =C30-(C60-D60) -> 145.5 | D31: =D30-(D60-E60) -> -122.5 | E31: =E30-(E60-F60) -> -420.9 | F31: =F30-(F60-G60) -> -253.7 | G31: =G30-(G60-H60) -> -187.5 | H31: =H30-(H60-I60) -> -399.1 | I31: =I30-(I60-J60) -> 519.8 | ... M31: =M30-(M60-N60) -> -526.5
A32: FNP (ajustado por inversiones) | B32: =B31+B34 -> 552.713 | C32: =C31+C34 -> 145.5 | D32: =D31+D34 -> -122.5 | E32: =E31+E34 -> -420.9 | F32: =F31+F34 -> -253.7 | G32: =G31+G34 -> -187.5 | H32: =H31+H34 -> -399.1 | I32: =I31+I34 -> 519.8 | ... M32: =M31+M34 -> -526.761
A33: Capex | B33: -44 | C33: =Cifras_Originales!B15 -> -25.3 | D33: =Cifras_Originales!C15 -> -24.37 | E33: =Cifras_Originales!D15 -> -23.02 | F33: =Cifras_Originales!E15 -> -35.37 | G33: =Cifras_Originales!F15 -> -44.94 | H33: =Cifras_Originales!G15 -> -21.76 | I33: =Cifras_Originales!H15 -> -19.15 | J33: =Cifras_Originales!I15 -> -12.44 | ... M33: =Cifras_Originales!L15 -> -28.85
A34: Inversiones | B34: 0 | C34: =Cifras_Originales!B16 -> 0 | D34: =Cifras_Originales!C16 -> 0 | E34: =Cifras_Originales!D16 -> 0 | F34: =Cifras_Originales!E16 -> 0 | G34: =Cifras_Originales!F16 -> 0 | H34: =Cifras_Originales!G16 -> 0 | I34: =Cifras_Originales!H16 -> 0 | J34: =Cifras_Originales!I16 -> 0 | ... M34: =Cifras_Originales!L16 -> -0.261
A35: Capex + Inversiones | B35: =B33+C34 -> -44 | C35: =+C34+C33 -> -25.3 | D35: =+D34+D33 -> -24.37 | E35: =+E34+E33 -> -23.02 | F35: =+F34+F33 -> -35.37 | G35: =+G34+G33 -> -44.94 | H35: =+H34+H33 -> -21.76 | I35: =+I34+I33 -> -19.15 | J35: =+J34+J33 -> -12.44 | ... M35: =+M34+M33 -> -29.111
B36: =+B35/B5 -> -0.017295597 | C36: =+C35/C5 -> -0.011145865 | D36: =+D35/D5 -> -0.011798025 | E36: =+E35/E5 -> -0.012073216 | F36: =+F35/F5 -> -0.021037293 | G36: =+G35/G5 -> -0.029645755 | H36: =+H35/H5 -> -0.016821274 | I36: =+I35/I5 -> -0.017483794 | ... M36: =+M35/M5 -> -0.033798909
A37: Dividendos + Recompra de Acciones | B37: =SUM(B27:B29) -> 0 | C37: =SUM(C27:C29) -> -47.2 | D37: =SUM(D27:D29) -> -69.2 | E37: =SUM(E27:E29) -> -175.9 | F37: =SUM(F27:F29) -> -294.3 | G37: =SUM(G27:G29) -> -282.5 | H37: =SUM(H27:H29) -> -294.7 | I37: =SUM(I27:I29) -> -257.7 | ... M37: =SUM(M27:M29) -> -244.2
A39: Activo
A40: Caja | B40: 1446.743 | C40: =Cifras_Originales!B24 -> 860.2 | D40: =Cifras_Originales!C24 -> 614.4 | E40: =Cifras_Originales!D24 -> 667.7 | F40: =Cifras_Originales!E24 -> 912.7 | G40: =Cifras_Originales!F24 -> 872.1 | H40: =Cifras_Originales!G24 -> 777.1 | I40: =Cifras_Originales!H24 -> 881.5 | J40: =Cifras_Originales!I24 -> 822.5 | ... M40: =Cifras_Originales!L24 -> 742.5
A41: Cuentas y documentos por cobrar | B41: 1022.85 | C41: =Cifras_Originales!B25 -> 864.5 | D41: =Cifras_Originales!C25 -> 760.3 | E41: =Cifras_Originales!D25 -> 645.9 | F41: =Cifras_Originales!E25 -> 537.6 | G41: =Cifras_Originales!F25 -> 433.5 | H41: =Cifras_Originales!G25 -> 317.7 | I41: =Cifras_Originales!H25 -> 124.7 | J41: =Cifras_Originales!I25 -> 107.2 | ... M41: =Cifras_Originales!L25 -> 97.8
A42: Inventarios | B42: 0 | C42: =Cifras_Originales!B26 -> 0 | D42: =Cifras_Originales!C26 -> 0 | E42: =Cifras_Originales!D26 -> 0 | F42: =Cifras_Originales!E26 -> 0 | G42: =Cifras_Originales!F26 -> 0 | H42: =Cifras_Originales!G26 -> 0 | I42: =Cifras_Originales!H26 -> 0 | J42: =Cifras_Originales!I26 -> 0 | ... M42: =Cifras_Originales!L26 -> 0
A43: Activos Fijos (Net Plant) | B43: 89.646 | C43: =Cifras_Originales!B27 -> 194.8 | D43: =Cifras_Originales!C27 -> 210 | E43: =Cifras_Originales!D27 -> 208.8 | F43: =Cifras_Originales!E27 -> 234.2 | G43: =Cifras_Originales!F27 -> 189.3 | H43: =Cifras_Originales!G27 -> 61.7 | I43: =Cifras_Originales!H27 -> 57.1 | J43: =Cifras_Originales!I27 -> 54.7 | ... M43: =Cifras_Originales!L27 -> 60.5 | P43: 24 | Q43: =P43-1 -> 23 | R43: =Q43-1 -> 22 | S43: =R43-1 -> 21 | T43: =S43-1 -> 20 | U43: =T43-1 -> 19 | V43: =U43-1 -> 18 | W43: =V43-1 -> 17 | X43: =W43-1 -> 16 | ... AA43: =Z43-1 -> 13
A44: Otros Activos | B44: =B45-SUM(B40:B43) -> 5492.192 | C44: =Cifras_Originales!B28 -> 5403.4 | D44: =Cifras_Originales!C28 -> 5103.2 | E44: =Cifras_Originales!D28 -> 4801.9 | F44: =Cifras_Originales!E28 -> 4256.1 | G44: =Cifras_Originales!F28 -> 3344 | H44: =Cifras_Originales!G28 -> 2109.5 | I44: =Cifras_Originales!H28 -> 1878.3 | J44: =Cifras_Originales!I28 -> 1816.1 | ... M44: =Cifras_Originales!L28 -> 1821.6 | O44: Assets | Q44: 7322.9 | R44: 6687.9 | S44: 6324.3 | T44: 5940.6 | U44: 4838.9 | V44: 3266 | W44: 2941.6 | X44: 2800.5 | Y44: 2729.9 | Z44: 2752.9 | AA44: 2722.4
A45: Total Activo | B45: 8051.431 | C45: =Cifras_Originales!B29 -> 7322.9 | D45: =Cifras_Originales!C29 -> 6687.9 | E45: =Cifras_Originales!D29 -> 6324.3 | F45: =Cifras_Originales!E29 -> 5940.6 | G45: =Cifras_Originales!F29 -> 4838.9 | H45: =Cifras_Originales!G29 -> 3266 | I45: =Cifras_Originales!H29 -> 2941.6 | J45: =Cifras_Originales!I29 -> 2800.5 | ... M45: =Cifras_Originales!L29 -> 2722.4 | O45: Debt | P45: 0 | Q45: 53.1 | R45: 0 | S45: 0 | T45: 0 | U45: 0 | V45: 0 | W45: 0 | X45: 718.5 | Y45: 1087.2 | Z45: 1008 | AA45: 1024.8
P47: =P45/P44 -> #DIV/0! | Q47: =Q45/Q44 -> 0.0072512256 | R47: =R45/R44 -> 0 | S47: =S45/S44 -> 0 | T47: =T45/T44 -> 0 | U47: =U45/U44 -> 0 | V47: =V45/V44 -> 0 | W47: =W45/W44 -> 0 | ... AA47: =AA45/AA44 -> 0.37643256
A48: Pasivo
A49: Pasivo Corto Plazo | B49: 941.184 | C49: =Cifras_Originales!B33 -> 477.4 | D49: =Cifras_Originales!C33 -> 440.4 | E49: =Cifras_Originales!D33 -> 465.1 | F49: =Cifras_Originales!E33 -> 484.1 | G49: =Cifras_Originales!F33 -> 539.1 | H49: =Cifras_Originales!G33 -> 608.6 | I49: =Cifras_Originales!H33 -> 524.8 | J49: =Cifras_Originales!I33 -> 695.1 | ... M49: =Cifras_Originales!L33 -> 794.8 | P49: 13 | Q49: =P49+1 -> 14 | R49: =Q49+1 -> 15 | S49: =R49+1 -> 16 | T49: =S49+1 -> 17 | U49: =T49+1 -> 18 | V49: =U49+1 -> 19 | W49: =V49+1 -> 20 | X49: =W49+1 -> 21 | ... AA49: =Z49+1 -> 24
A50: Deuda a corto plazo | B50: 0 | C50: =Cifras_Originales!B34 -> 53.1 | D50: =Cifras_Originales!C34 -> 0 | E50: =Cifras_Originales!D34 -> 0 | F50: =Cifras_Originales!E34 -> 0 | G50: =Cifras_Originales!F34 -> 0 | H50: =Cifras_Originales!G34 -> 0 | I50: =Cifras_Originales!H34 -> 0 | J50: =Cifras_Originales!I34 -> 93.2 | ... M50: =Cifras_Originales!L34 -> 22.8 | P50: {=_xlfn.SORTBY(P47:AA47, _xlfn.SEQUENCE(1, COLUMNS(P47:AA47), COLUMNS(P47:AA47), -1))} -> 0.37643256 | Q50: 0.36615932 | R50: 0.39825635 | S50: 0.25656133 | T50: 0 | U50: 0 | V50: 0 | W50: 0 | X50: 0 | Y50: 0 | Z50: 0.0072512256 | AA50: #DIV/0!
A51: Short-Term Leases | B51: 0 | C51: =Cifras_Originales!B35 -> 0 | D51: =Cifras_Originales!C35 -> 0 | E51: =Cifras_Originales!D35 -> 0 | F51: =Cifras_Originales!E35 -> 0 | G51: =Cifras_Originales!F35 -> 0 | H51: =Cifras_Originales!G35 -> 0 | I51: =Cifras_Originales!H35 -> 0 | J51: =Cifras_Originales!I35 -> 18.2 | ... M51: =Cifras_Originales!L35 -> 22.8
A52: Otros Pasivos a Corto Plazo | B52: 204.969 | C52: =Cifras_Originales!B36 -> 424.3 | D52: =Cifras_Originales!C36 -> 440.4 | E52: =Cifras_Originales!D36 -> 465.1 | F52: =Cifras_Originales!E36 -> 484.1 | G52: =Cifras_Originales!F36 -> 539.1 | H52: =Cifras_Originales!G36 -> 608.6 | I52: =Cifras_Originales!H36 -> 524.8 | J52: =Cifras_Originales!I36 -> 583.7 | ... M52: =Cifras_Originales!L36 -> 749.2
A53: Pasivo Largo Plazo | B53: 754.208 | C53: =Cifras_Originales!B37 -> 255.2 | D53: =Cifras_Originales!C37 -> 189.7 | E53: =Cifras_Originales!D37 -> 145.7 | F53: =Cifras_Originales!E37 -> 70.3 | G53: =Cifras_Originales!F37 -> 51.3 | H53: =Cifras_Originales!G37 -> 53 | I53: =Cifras_Originales!H37 -> 87.2 | J53: =Cifras_Originales!I37 -> 91.7 | ... M53: =Cifras_Originales!L37 -> 1061.8
A54: Deuda a largo plazo | B54: 0 | C54: =Cifras_Originales!B38 -> 0 | D54: =Cifras_Originales!C38 -> 0 | E54: =Cifras_Originales!D38 -> 0 | F54: =Cifras_Originales!E38 -> 0 | G54: =Cifras_Originales!F38 -> 0 | H54: =Cifras_Originales!G38 -> 0 | I54: =Cifras_Originales!H38 -> 0 | J54: =Cifras_Originales!I38 -> 515.3 | ... M54: =Cifras_Originales!L38 -> 866.4
A55: Long-Term Leases | B55: 86.93 | C55: =Cifras_Originales!B39 -> 0 | D55: =Cifras_Originales!C39 -> 0 | E55: =Cifras_Originales!D39 -> 0 | F55: =Cifras_Originales!E39 -> 0 | G55: =Cifras_Originales!F39 -> 0 | H55: =Cifras_Originales!G39 -> 0 | I55: =Cifras_Originales!H39 -> 0 | J55: =Cifras_Originales!I39 -> 91.8 | ... M55: =Cifras_Originales!L39 -> 112.8 | P55: {=TRANSPOSE(_xlfn.ANCHORARRAY(P50))} -> 0.37643256 | Q55: 13
A56: Otros Pasivos a Largo Plazo | B56: =B53-SUM(B54:B55) -> 667.278 | C56: =Cifras_Originales!B40 -> 255.2 | D56: =Cifras_Originales!C40 -> 189.7 | E56: =Cifras_Originales!D40 -> 145.7 | F56: =Cifras_Originales!E40 -> 70.3 | G56: =Cifras_Originales!F40 -> 51.3 | H56: =Cifras_Originales!G40 -> 53 | I56: =Cifras_Originales!H40 -> 87.2 | J56: =Cifras_Originales!I40 -> -515.4 | ... M56: =Cifras_Originales!L40 -> 82.6 | P56: 0.36615932 | Q56: =Q55+1 -> 14
A57: Total pasivos | B57: 1096 | C57: =Cifras_Originales!B41 -> 732.6 | D57: =Cifras_Originales!C41 -> 630.1 | E57: =Cifras_Originales!D41 -> 610.8 | F57: =Cifras_Originales!E41 -> 554.4 | G57: =Cifras_Originales!F41 -> 590.4 | H57: =Cifras_Originales!G41 -> 661.6 | I57: =Cifras_Originales!H41 -> 612 | J57: =Cifras_Originales!I41 -> 786.8 | ... M57: =Cifras_Originales!L41 -> 1856.6 | P57: 0.39825635 | Q57: =Q56+1 -> 15
P58: 0.25656133 | Q58: =Q57+1 -> 16
A59: Deuda Neta | B59: =B60-B40 -> -1359.813 | C59: =C60-C40 -> -807.1 | D59: =D60-D40 -> -614.4 | E59: =E60-E40 -> -667.7 | F59: =F60-F40 -> -912.7 | G59: =G60-G40 -> -872.1 | H59: =H60-H40 -> -777.1 | I59: =I60-I40 -> -881.5 | ... M59: =M60-M40 -> 282.3 | P59: 0 | Q59: =Q58+1 -> 17
A60: Deuda | B60: =B50+B51+B54+B55 -> 86.93 | C60: =C50+C51+C54+C55 -> 53.1 | D60: =D50+D51+D54+D55 -> 0 | E60: =E50+E51+E54+E55 -> 0 | F60: =F50+F51+F54+F55 -> 0 | G60: =G50+G51+G54+G55 -> 0 | H60: =H50+H51+H54+H55 -> 0 | I60: =I50+I51+I54+I55 -> 0 | ... M60: =M50+M51+M54+M55 -> 1024.8 | P60: 0 | Q60: =Q59+1 -> 18
B61: =B60/B45 -> 0.010796838 | C61: =C60/C45 -> 0.0072512256 | D61: =D60/D45 -> 0 | E61: =E60/E45 -> 0 | F61: =F60/F45 -> 0 | G61: =G60/G45 -> 0 | H61: =H60/H45 -> 0 | I61: =I60/I45 -> 0 | ... M61: =M60/M45 -> 0.37643256 | P61: 0 | Q61: =Q60+1 -> 19
P62: 0 | Q62: =Q61+1 -> 20
A63: Interés Minoritario | B63: 0 | C63: =Cifras_Originales!B44 -> 0 | D63: =Cifras_Originales!C44 -> 0 | E63: =Cifras_Originales!D44 -> 0 | F63: =Cifras_Originales!E44 -> 0 | G63: =Cifras_Originales!F44 -> 0 | H63: =Cifras_Originales!G44 -> 0 | I63: =Cifras_Originales!H44 -> 0 | J63: =Cifras_Originales!I44 -> 0 | ... M63: =Cifras_Originales!L44 -> 0 | P63: 0 | Q63: =Q62+1 -> 21
P64: 0 | Q64: =Q63+1 -> 22
P65: 0.0072512256 | Q65: =Q64+1 -> 23
A66: Capital Contable | B66: =B45-B57-B63 -> 6955.431 | C66: =C45-C57-C63 -> 6590.3 | D66: =D45-D57-D63 -> 6057.8 | E66: =E45-E57-E63 -> 5713.5 | F66: =F45-F57-F63 -> 5386.2 | G66: =G45-G57-G63 -> 4248.5 | H66: =H45-H57-H63 -> 2604.4 | I66: =I45-I57-I63 -> 2329.6 | ... M66: =M45-M57-M63 -> 865.8 | P66: #DIV/0! | Q66: =Q65+1 -> 24
A69: OTROS DATOS AL FIN DE AÑO
A70: Numero deEmpleados | B70: 6500 | C70: =Cifras_Originales!B49 -> 6200 | D70: =Cifras_Originales!C49 -> 5600 | E70: =Cifras_Originales!D49 -> 5100 | F70: =Cifras_Originales!E49 -> 4800 | G70: =Cifras_Originales!F49 -> 2100 | H70: =Cifras_Originales!G49 -> 1700 | I70: =Cifras_Originales!H49 -> 2900 | J70: =Cifras_Originales!I49 -> 2800 | ... M70: =Cifras_Originales!L49 -> 2600
A71: Acciones en circulación (millones) | B71: 86.9 | C71: =+Cifras_Originales!B50 -> 92.7 | D71: =+Cifras_Originales!C50 -> 92.3 | E71: =+Cifras_Originales!D50 -> 90.8 | F71: =+Cifras_Originales!E50 -> 88.1 | G71: =+Cifras_Originales!F50 -> 85.7 | H71: =+Cifras_Originales!G50 -> 84.2 | I71: =+Cifras_Originales!H50 -> 83.6 | J71: =+Cifras_Originales!I50 -> 85.7 | ... M71: =+Cifras_Originales!L50 -> 86.9
A72: Float | B72: 0 | C72: =Cifras_Originales!B51 -> 0 | D72: =Cifras_Originales!C51 -> 0 | E72: =Cifras_Originales!D51 -> 0 | F72: =Cifras_Originales!E51 -> 0 | G72: =Cifras_Originales!F51 -> 0 | H72: =Cifras_Originales!G51 -> 0 | I72: =Cifras_Originales!H51 -> 0 | J72: =Cifras_Originales!I51 -> 0 | ... M72: =Cifras_Originales!L51 -> 0
A73: Insiders Own | B73: 0.61% | C73: =Cifras_Originales!B52 -> 0.0239 | D73: =Cifras_Originales!C52 -> 0.0231 | E73: =Cifras_Originales!D52 -> 0.022 | F73: =Cifras_Originales!E52 -> 0.0229 | G73: =Cifras_Originales!F52 -> 0.022 | H73: =Cifras_Originales!G52 -> 0.0219 | I73: =Cifras_Originales!H52 -> 0.021 | J73: =Cifras_Originales!I52 -> 0.0206 | ... M73: =Cifras_Originales!L52 -> 0.0154
A74: S&P | B74: 0 | C74: =+Cifras_Originales!B53 -> 0 | D74: =+Cifras_Originales!C53 -> 0 | E74: =+Cifras_Originales!D53 -> 0 | F74: =+Cifras_Originales!E53 -> 0 | G74: =+Cifras_Originales!F53 -> 0 | H74: =+Cifras_Originales!G53 -> 0 | I74: =+Cifras_Originales!H53 -> 0 | J74: =+Cifras_Originales!I53 -> 0 | ... M74: =+Cifras_Originales!L53 -> 0
A75: =Cifras_Originales!A54 -> Vol. Diario en Millones USD | B75: 0 | C75: =Cifras_Originales!B54 -> 0 | D75: =Cifras_Originales!C54 -> 0 | E75: =Cifras_Originales!D54 -> 0 | F75: =Cifras_Originales!E54 -> 0 | G75: =Cifras_Originales!F54 -> 0 | H75: =Cifras_Originales!G54 -> 0 | I75: =Cifras_Originales!H54 -> 0 | J75: =Cifras_Originales!I54 -> 0 | ... M75: =Cifras_Originales!L54 -> 0 | IH75: =Cifras_Originales!GM54 -> 0
B77: =+Cifras_Originales!B55 -> 2021 | C77: =+Cifras_Originales!C55 -> 2022 | D77: =+Cifras_Originales!D55 -> 2023
A78: =Cifras_Originales!A56 -> Posicion en Corto (%) | B78: =Cifras_Originales!B56 -> 0
A79: =Cifras_Originales!A57 -> EPS | B79: =Cifras_Originales!B57 -> 5.22 | C79: =Cifras_Originales!C57 -> 6.01 | D79: =Cifras_Originales!D57 -> 5.56
A81: =+Cifras_Originales!A59 -> BONOS DE LA EMISORA A 3, 5 Y 10 | B81: Precio Medio | C81: Moody's | D81: YTM | E81: DIVISA
A82: =+Cifras_Originales!A60 -> 0 | B82: =+Cifras_Originales!B60 -> 0 | C82: =+Cifras_Originales!C60 -> 0 | D82: =+Cifras_Originales!D60 -> 0 | E82: =+Cifras_Originales!E60 -> 0
A83: =+Cifras_Originales!A61 -> 0 | B83: =+Cifras_Originales!B61 -> 0 | C83: =+Cifras_Originales!C61 -> 0 | D83: =+Cifras_Originales!D61 -> 0 | E83: =+Cifras_Originales!E61 -> 0
A84: =+Cifras_Originales!A62 -> 0 | B84: =+Cifras_Originales!B62 -> 0 | C84: =+Cifras_Originales!C62 -> 0 | D84: =+Cifras_Originales!D62 -> 0 | E84: =+Cifras_Originales!E62 -> 0
A85: =+Cifras_Originales!A63 -> 0 | B85: =+Cifras_Originales!B63 -> 0 | C85: =+Cifras_Originales!C63 -> 0 | D85: =+Cifras_Originales!D63 -> 0 | E85: =+Cifras_Originales!E63 -> 0

Sheet Segments
B2: Regions (2023) | L2: Proyectado | N2: Escenario de estrés | X2: Escenario de estrés
C3: 2024 | D3: =C3-1 -> 2023 | E3: Ut. Operativa | F3: % Vts | G3: Margen | H3: Crec | L3: Crecimiento | M3: 2022 (Real) | N3: 2023 (Real) | O3: 2024 (Real) | P3: 2025 | Q3: 2026 | R3: 2027 | S3: 2028 | T3: 2029 | V3: Márgenes (regional) | W3: 2022 (Real) | X3: 2023 (Real) | Y3: 2024 (Real) | Z3: 2025 | AA3: 2026 | AB3: 2027 | AC3: 2028 | AD3: 2029
B4: US | C4: 1251892 | D4: 1058293 | E4: NA | F4: =C4/$C$14 -> 0.49193947 | G4: NA | H4: =C4/D4-1 -> 0.18293516 | J4: =IF(C4="","",IF(F4=0,"NA",TEXT(F4,"0%"))&"; "&IF(G4=0,"NA",TEXT(G4,"0.0%"))&"; "&IF(H4=0,"NA",TEXT(H4,"0%"))) -> 49%; NA; 18% | L4: =B17 -> 0 | V4: =B4 -> US | W4: 932587
B5: Germany | C5: 209714 | D5: 199068 | E5: NA | F5: =C5/$C$14 -> 0.082408542 | G5: NA | H5: =C5/D5-1 -> 0.053479213 | J5: =IF(C5="","",IF(F5=0,"NA",TEXT(F5,"0%"))&"; "&IF(G5=0,"NA",TEXT(G5,"0.0%"))&"; "&IF(H5=0,"NA",TEXT(H5,"0%"))) -> 8%; NA; 5% | L5: =B18 -> 0 | V5: =B5 -> Germany | W5: 198612
B6: Japan | C6: 184547 | D6: 203013 | E6: NA | F6: =C6/$C$14 -> 0.072518998 | G6: NA | H6: =C6/D6-1 -> -0.090959692 | J6: =IF(C6="","",IF(F6=0,"NA",TEXT(F6,"0%"))&"; "&IF(G6=0,"NA",TEXT(G6,"0.0%"))&"; "&IF(H6=0,"NA",TEXT(H6,"0%"))) -> 7%; NA; -9% | L6: =B19 -> 0 | V6: =B6 -> Japan | W6: 186199
B7: China and Hong Kong | C7: 126628 | D7: 111467 | E7: NA | F7: =C7/$C$14 -> 0.049759334 | G7: NA | H7: =C7/D7-1 -> 0.13601335 | J7: =IF(C7="","",IF(F7=0,"NA",TEXT(F7,"0%"))&"; "&IF(G7=0,"NA",TEXT(G7,"0.0%"))&"; "&IF(H7=0,"NA",TEXT(H7,"0%"))) -> 5%; NA; 14% | L7: =B20 -> 0 | V7: =B7 -> China and Hong Kong | W7: 105101
B8: South Korea | C8: 112895 | D8: 106261 | E8: NA | F8: =C8/$C$14 -> 0.044362858 | G8: NA | H8: =C8/D8-1 -> 0.062431184 | J8: =IF(C8="","",IF(F8=0,"NA",TEXT(F8,"0%"))&"; "&IF(G8=0,"NA",TEXT(G8,"0.0%"))&"; "&IF(H8=0,"NA",TEXT(H8,"0%"))) -> 4%; NA; 6% | L8: =B21 -> 0 | V8: =B8 -> South Korea
B9: Other EMEA | C9: 445791 | D9: 406719 | E9: NA | F9: =C9/$C$14 -> 0.1751766 | G9: NA | H9: =C9/D9-1 -> 0.096066326 | J9: =IF(C9="","",IF(F9=0,"NA",TEXT(F9,"0%"))&"; "&IF(G9=0,"NA",TEXT(G9,"0.0%"))&"; "&IF(H9=0,"NA",TEXT(H9,"0%"))) -> 18%; NA; 10% | L9: % vts. | V9: Margen Operativp | W9: =(#REF!*W12+#REF!*W13+#REF!*W14+#REF!*W15+W8*W16)/SUM(W12:W16)+W10 -> #REF! | X9: =(X4*X12+X5*X13+X6*X14+X7*X15+X8*X16)/SUM(X12:X16)+X10 -> #DIV/0! | Y9: =(Y4*Y12+Y5*Y13+Y6*Y14+Y7*Y15+Y8*Y16)/SUM(Y12:Y16)+Y10 -> #DIV/0! | Z9: =(Z4*Z12+Z5*Z13+Z6*Z14+Z7*Z15+Z8*Z16)/SUM(Z12:Z16)+Z10 -> #DIV/0! | AA9: =(AA4*AA12+AA5*AA13+AA6*AA14+AA7*AA15+AA8*AA16)/SUM(AA12:AA16)+AA10 -> #DIV/0! | AB9: =(AB4*AB12+AB5*AB13+AB6*AB14+AB7*AB15+AB8*AB16)/SUM(AB12:AB16)+AB10 -> #DIV/0! | AC9: =(AC4*AC12+AC5*AC13+AC6*AC14+AC7*AC15+AC8*AC16)/SUM(AC12:AC16)+AC10 -> #DIV/0! | AD9: =(AD4*AD12+AD5*AD13+AD6*AD14+AD7*AD15+AD8*AD16)/SUM(AD12:AD16)+AD10 -> #DIV/0!
B10: Other International | C10: 213342 | D10: 185128 | E10: NA | F10: =C10/$C$14 -> 0.08383419 | G10: NA | H10: =C10/D10-1 -> 0.15240266 | J10: =IF(C10="","",IF(F10=0,"NA",TEXT(F10,"0%"))&"; "&IF(G10=0,"NA",TEXT(G10,"0.0%"))&"; "&IF(H10=0,"NA",TEXT(H10,"0%"))) -> 8%; NA; 15% | L10: =B17 -> 0 | V10: Ajuste R&D | W10: =(-6200-18752)/274515 -> -0.090894851 | X10: =(-6143-21914)/365817 -> -0.076696818 | Y10: =(-7207-26251)/394328 -> -0.084848147 | Z10: -0.1 | AA10: -0.1 | AB10: -0.1 | AC10: -0.1 | AD10: -0.1
J11: =IF(C11="","",IF(F11=0,"NA",TEXT(F11,"0%"))&"; "&IF(G11=0,"NA",TEXT(G11,"0.0%"))&"; "&IF(H11=0,"NA",TEXT(H11,"0%"))) | L11: =B18 -> 0 | V11: % vts.
J12: =IF(C12="","",IF(F12=0,"NA",TEXT(F12,"0%"))&"; "&IF(G12=0,"NA",TEXT(G12,"0.0%"))&"; "&IF(H12=0,"NA",TEXT(H12,"0%"))) | L12: =B19 -> 0 | V12: =V4 -> US
J13: =IF(C13="","",IF(F13=0,"NA",TEXT(F13,"0%"))&"; "&IF(G13=0,"NA",TEXT(G13,"0.0%"))&"; "&IF(H13=0,"NA",TEXT(H13,"0%"))) | L13: =B20 -> 0 | V13: =V5 -> Germany
B14: TOTAL | C14: =SUM(C4:C12) -> 2544809 | D14: =SUM(D4:D12) -> 2269949 | E14: NA | F14: =C14/SUM($C$4:$C$13) -> 1 | G14: NA | H14: =C14/D14-1 -> 0.12108642 | L14: =B21 -> 0 | V14: =V6 -> Japan
M15: =SUM(M10:M14) -> 0 | N15: =SUM(N10:N14) -> 0 | O15: =SUM(O10:O14) -> 0 | P15: =SUM(P10:P14) -> 0 | Q15: =SUM(Q10:Q14) -> 0 | R15: =SUM(R10:R14) -> 0 | S15: =SUM(S10:S14) -> 0 | T15: =SUM(T10:T14) -> 0 | V15: =V7 -> China and Hong Kong
N16: =N15/M15-1 -> #DIV/0! | O16: =O15/N15-1 -> #DIV/0! | P16: =P15/O15-1 -> #DIV/0! | Q16: =Q15/P15-1 -> #DIV/0! | R16: =R15/Q15-1 -> #DIV/0! | S16: =S15/R15-1 -> #DIV/0! | T16: =T15/S15-1 -> #DIV/0! | V16: =V8 -> South Korea
W17: =SUM(W12:W16) -> 0 | X17: =SUM(X12:X16) -> 0 | Y17: =SUM(Y12:Y16) -> 0 | Z17: =SUM(Z12:Z16) -> 0 | AA17: =SUM(AA12:AA16) -> 0 | AB17: =SUM(AB12:AB16) -> 0 | AC17: =SUM(AC12:AC16) -> 0 | AD17: =SUM(AD12:AD16) -> 0

Sheet Peers
A2: Multiplos (USD) | B2: ANSS | C2: DSY.PA | D2: ALTR | E2: PTC
B3: Ansys | C3: Dassault Systèmes | D3: Altair Engineering | E3: PTC
A4: Ventas | B4: =Cifras_en_Millones!B5 -> 2544 | C4: 6213 | D4: 665.788 | E4: 2298.472 | G4: Averages
A5: Crecimiento (1S23/1S22) | B5: 9.89% | C5: 5.05% | D5: 5.04% | E5: 8.47% | G5: =AVERAGE(B5:E5) -> #DIV/0!
A6: Crecimiento (1S23/1S19) | B6: 45.7% | C6: 48.1% | D6: 30.9% | E6: 0.67 | G6: =AVERAGE(B6:E6) -> 0.67
A7: Deuda | B7: 122278 | C7: 82110 | D7: 26772 | E7: 100504 | G7: =AVERAGE(B7:E7) -> 82916
A8: Activos | B8: 323888 | C8: 301311 | D8: 319616 | E8: 321195 | G8: =AVERAGE(B8:E8) -> 316502.5
A9: Deuda/Activos | B9: =Cifras_Originales!$B$41/Cifras_Originales!$B$29 -> 0.10004233 | C9: =14622/14622 -> 1 | D9: =652162/1363493 -> 0.47830242 | E9: =3611552/6288842 -> 0.57427933 | G9: =AVERAGE(B9:E9) -> 0.53815602
A10: Deuda/EBITDA | B10: =733/793 -> 0.92433796 | C10: =(14622.5/1241.9) -> 11.774297 | D10: =652.162/31.09 -> 20.976584 | E10: =6288.842/498.5 -> 12.615531 | G10: =AVERAGE(B10:E10) -> 11.572688
A11: (Capex + Adq.)/Revenue | B11: =-DCFF!G22/DCFF!G6 -> 0.011013701 | C11: 3.19% | D11: 6.86% | E11: 9.53% | G11: =AVERAGE(B11:E11) -> 0.011013701
A12: ROA (p) | B12: 7.18% | C12: 7.18% | D12: -0.0065 | E12: 3.9% | G12: =AVERAGE(B12:E12) -> -0.0065
A13: ROIC (p) | B13: 6.34% | C13: 12.08% | D13: =-0.0192%% -> -1.92e-06 | E13: 10.15% | G13: =AVERAGE(B13:E13) -> -1.92e-06
A14: Margen Operativo 2024 | B14: 24.27% | C14: 20.86% | D14: 0.02656 | E14: 21.86% | G14: =AVERAGE(B14:E14) -> 0.02656
A15: Margen Operativo 2023 | B15: 26.31% | C15: 22.99% | D15: 0.0003966 | E15: 23.14% | G15: =AVERAGE(B15:E15) -> 0.0003966
A16: Float | B16: 87.26 | C16: 668.54 | D16: 46.51 | E16: 113.92 | G16: =AVERAGE(B16:E16) -> #DIV/0!
A17: b | B17: 1.12 | C17: 0.62 | D17: 1.42 | E17: 1.19 | G17: =AVERAGE(B17:E17) -> 1.42
A18: Precio/Utilidad | B18: 51.02 | C18: 44.13 | D18: 698.62 | E18: 49.74 | G18: =AVERAGE(B18:E18) -> 210.8775
A19: Precio/Ventas | B19: 11.99 | C19: 7.34 | D19: 14.61 | E19: 9.66 | G19: =AVERAGE(B19:E19) -> 10.9
A20: EV/Activos | B20: 3.6082474 | C20: 2.7491961 | D20: 6.2377632 | E20: 3.7241379 | G20: =AVERAGE(B20:E20) -> 4.0798362
A21: EV/Ebitda | B21: 33.24 | C21: 22.21 | D21: 91.2 | E21: 32.59 | G21: =AVERAGE(B21:E21) -> 44.81
A22: Div. Yield: | B22: 0 | C22: 0.58% | D22: 0 | E22: 0
B24: *Nota: Estos múltiplos no consideran el promedio de los últimos 3 años, únicamente valores del último año reportado
B25: **Cifras en USD
A27: (You can make up a table with different indicators in order to link them to the multiples/ratios. At the end, put the table unvisible with white color)

Sheet Acuerdo
A1: Invertir
A2: NO invertir
A3: Mantener sin elevar posición
A4: Mantener (y seguir comprando)
A5: Liquidar
A6: PENDIENTE

Sheet ESG
B2: Análisis ESG | J2: PARÁMETROS
C3: Impacto | D3: ¿Reporta? | E3: Ranking | F3: Mitigación | G3: Semáforo | H3: Comentarios | J3: IMPACTO | L3: RANKING | M3: MITIGACIÓN
B4: Ambiental | J4: NONE | K4: 0 | L4: "Best in class" | M4: Is there evidence of progam/plan/etc…
B5: Emisiones directas CO2 | C5: 0 | D5: Si | E5: "Best in class" | J5: LOW | K5: 1 | L5: Medium high
B6: Uso total de agua | D6: No | J6: MEDIUM | K6: 2 | L6: Medium
B7: Total Energy Consumption | C7: 1 | D7: Si | E7: "Best in class" | J7: HIGH | K7: 3 | L7: "Villain"
B8: Waste Management | D8: No
B9: Land Degradation/Deforestation/Biodiversity loss/Animal sufering/… | D9: No | J9: TRAFFIC LIGHTS
B10: Social
B11: % Rotación de empleados | C11: 0 | D11: Si | E11: "Best in class"
B12: Sueldos y compensaciones | C12: 1 | D12: Si | E12: Medium high
B13: Temas de reputación | C13: 0 | D13: Si | E13: "Best in class"
B14: Temas de discriminación | D14: No
B15: Seguridad laboral | D15: No
B16: Daños a la salud | D16: No
B17: PXP?
B18: Supply chain | D18: No
B19: Community involvement | C19: Medium | D19: Si
B20: Public Sector | D20: No
B21: Litigios | D21: No
B22: Gobierno
B23: Diversidad (Género, edad, industria, región)
B24: % independientes
B25: tiempo promedio como consejeros independientes
B26: Salidas recientes de consejeros/C-level executives?
B27: CEO/Chairman
B28: Transparencia (segmentos, fuente de riqueza, adquisiciones, otros)
B29: Tiempo que tardan en reportar luego del final del trimestre/año
B30: Participación adicional del CEO en otros consejos o excesiva del Ch.
B31: Auditoría/Consultoría | D31: Si
B32: Esquemas de compensación al management | D32: Si

Sheet DCF
A1: Discounted Cash Flow
A3: Ventas | E3: Margen Operativo
A16: Inversiones | E16: Utilidad Neta
D31: 0.001 | E31: =1/((1+$B$59+$D31)^(E35-2021)) -> 0.92250923 | F31: =1/((1+$B$59+$D31)^(F35-2021)) -> 0.85102327 | G31: =1/((1+$B$59+$D31)^(G35-2021)) -> 0.78507682 | H31: =1/((1+$B$59+$D31)^(H35-2021)) -> 0.72424061 | I31: =1/((1+$B$59+$D31)^(I35-2021)) -> 0.66811864 | J31: =1/((1+$B$59+$D31)^(J35-2021)) -> 0.61634561 | K31: =1/((1+$B$59+$D31)^(K35-2021)) -> 0.56858451 | L31: =1/((1+$B$59+$D31)^(L35-2021)) -> 0.52452446 | ... AC31: =1/((1+$B$59+$D31)^(AC35-2021)) -> 0.13312755
D32: 0.005 | E32: =1/((1+$B$59+$D32)^(E35-2021)) -> 0.91911765 | F32: =1/((1+$B$59+$D32)^(F35-2021)) -> 0.84477725 | G32: =1/((1+$B$59+$D32)^(G35-2021)) -> 0.77644968 | H32: =1/((1+$B$59+$D32)^(H35-2021)) -> 0.7136486 | I32: =1/((1+$B$59+$D32)^(I35-2021)) -> 0.65592702 | J32: =1/((1+$B$59+$D32)^(J35-2021)) -> 0.6028741 | K32: =1/((1+$B$59+$D32)^(K35-2021)) -> 0.55411223 | L32: =1/((1+$B$59+$D32)^(L35-2021)) -> 0.50929433 | ... AC32: =1/((1+$B$59+$D32)^(AC35-2021)) -> 0.12141647
D33: Normal | E33: =1/((1+$B$59)^(E35-2021)) -> 0.92336103 | F33: =1/((1+$B$59)^(F35-2021)) -> 0.8525956 | G33: =1/((1+$B$59)^(G35-2021)) -> 0.78725355 | H33: =1/((1+$B$59)^(H35-2021)) -> 0.72691926 | I33: =1/((1+$B$59)^(I35-2021)) -> 0.67120892 | J33: =1/((1+$B$59)^(J35-2021)) -> 0.61976816 | K33: =1/((1+$B$59)^(K35-2021)) -> 0.57226977 | L33: =1/((1+$B$59)^(L35-2021)) -> 0.5284116 | ... AC33: =1/((1+$B$59)^(AC35-2021)) -> 0.13623496
B35: 2019 (Real) | C35: 2020 (Real) | D35: 2021 | E35: =D35+1 -> 2022 | F35: =E35+1 -> 2023 | G35: =F35+1 -> 2024 | H35: =G35+1 -> 2025 | I35: =H35+1 -> 2026 | J35: =I35+1 -> 2027 | K35: =J35+1 -> 2028 | L35: =K35+1 -> 2029 | ... AC35: =AB35+1 -> 2046
A36: Crecimiento | B36: =OP!N34 -> 0.13406293 | C36: =OP!N35 -> 0.083337704 | D36: 0.35 | E36: 0.034 | F36: 0.095 | G36: 0.095 | H36: 0.095 | I36: 0.095 | J36: 0.095 | K36: 0.08 | L36: 0.06 | M36: 0.05 | N36: 0.04 | O36: 0.035 | P36: 0.035 | Q36: 0.035 | R36: 0.035 | S36: 0.035 | T36: 0.035 | U36: 0.035 | V36: 0.035 | W36: 0.035 | X36: 0.035 | Y36: 0.035 | Z36: 0.035 | AA36: 0.035 | AB36: 0.035 | AC36: 0.035
A37: Ventas | B37: =OP!C34 -> 1906.7 | C37: =OP!C35 -> 2065.6 | D37: =OP!C34*(1+D36) -> 2574.045 | E37: =D37*(1+E36) -> 2661.5625 | F37: =E37*(1+F36) -> 2914.411 | G37: =F37*(1+G36) -> 3191.28 | H37: =G37*(1+H36) -> 3494.4516 | I37: =H37*(1+I36) -> 3826.4245 | J37: =I37*(1+J36) -> 4189.9348 | K37: =J37*(1+K36) -> 4525.1296 | L37: =K37*(1+L36) -> 4796.6374 | ... AC37: =AB37*(1+AC36) -> 8775.3566
A38: Margen Operativo | B38: =+OP!D34 -> 0.26920858 | C38: =+OP!D35 -> 0.28693842 | D38: =108166.4/365513.2 -> 0.29593022 | E38: =108162.8/377959.8 -> 0.28617541 | F38: 0.27 | G38: 0.275 | H38: 0.26 | I38: 0.255 | J38: 0.25 | K38: 0.25 | L38: 0.25 | M38: 0.25 | N38: 0.25 | O38: 0.25 | P38: 0.25 | Q38: 0.25 | R38: 0.25 | S38: 0.25 | T38: 0.25 | U38: 0.25 | V38: 0.25 | W38: 0.25 | X38: 0.25 | Y38: 0.25 | Z38: 0.25 | AA38: 0.25 | AB38: 0.25 | AC38: 0.25
A39: EBIT | B39: 63930 | C39: 66288 | D39: =D37*D38 -> 761.73769 | E39: =E37*E38 -> 761.67374 | F39: =F37*F38 -> 786.89096 | G39: =G37*G38 -> 877.602 | H39: =H37*H38 -> 908.55742 | I39: =I37*I38 -> 975.73825 | J39: =J37*J38 -> 1047.4837 | K39: =K37*K38 -> 1131.2824 | ... AC39: =AC37*AC38 -> 2193.8392
A40: Dep&Amort | B40: =OP!H34 -> 0 | C40: =OP!H35 -> 0 | D40: 11000 | E40: =D40*(1+E36*$H$59) -> 11374 | F40: =E40*(1+F36*$H$59) -> 12454.53 | G40: =F40*(1+G36*$H$59) -> 13637.71 | H40: =G40*(1+H36*$H$59) -> 14933.293 | I40: =H40*(1+I36*$I$59) -> 16351.956 | J40: =I40*(1+J36*$I$59) -> 17905.391 | K40: =J40*(1+K36*$I$59) -> 19337.823 | L40: =K40*(1+L36*$I$59) -> 20498.092 | M40: =L40*(1+M36*$I$59) -> 21522.997 | N40: =M40*(1+N36*$I$59) -> 22383.917 | O40: =N40*(1+O36*$I$59) -> 23167.354 | P40: =O40*(1+P36*$I$59) -> 23978.211 | ... AC40: =AB40*(1+AC36*$I$59) -> 37500.868
A41: EBIDTA | B41: =+B39+B40 -> 63930 | C41: =+C39+C40 -> 66288 | D41: =D39+D40 -> 11761.738 | E41: =E39+E40 -> 12135.674 | F41: =F39+F40 -> 13241.421 | G41: =G39+G40 -> 14515.312 | H41: =H39+H40 -> 15841.85 | I41: =I39+I40 -> 17327.694 | J41: =J39+J40 -> 18952.875 | K41: =K39+K40 -> 20469.105 | ... AC41: =AC39+AC40 -> 39694.708
A42: CIF | B42: -1385 | C42: -890 | D42: =(C48)*$H$60 -> -1124.36 | E42: =(D48)*$H$60 -> -1113.1164 | F42: =(E48)*$H$60 -> -1113.1164 | G42: =(F48)*$H$60 -> -1113.1164 | H42: =(G48)*$H$60 -> -1113.1164 | I42: =(H48)*$H$60 -> -1113.1164 | J42: =(I48)*$H$60 -> -1113.1164 | K42: =(J48)*$H$60 -> -1113.1164 | ... AC42: =(AB48)*$H$60 -> -1113.1164
A43: Otros Gastos | B43: =-422-2817 -> -3239 | C43: =87-3634 -> -3547 | D43: =-C43*(1+D36) -> 4788.45 | E43: =D43*(1+E36*0.5) -> 4869.8537 | F43: =E43*(1+F36*0.5) -> 5101.1717 | G43: =F43*(1+G36*0.5) -> 5343.4774 | H43: =G43*(1+H36*0.5) -> 5597.2925 | I43: =H43*(1+I36*0.5) -> 5863.1639 | J43: =I43*(1+J36*0.5) -> 6141.6642 | K43: =J43*(1+K36*0.5) -> 6387.3308 | L43: =K43*(1+L36*0.5) -> 6578.9507 | ... AC43: =AB43*(1+AC36*0.5) -> 8922.7133
A44: Utilidad antes de Impuestos | B44: =B39-B42-B43 -> 68554 | C44: =C39-C42-C43 -> 70725 | D44: =D39-D42-D43 -> -2902.3523 | E44: =E39-E42-E43 -> -2995.0635 | F44: =F39-F42-F43 -> -3201.1643 | G44: =G39-G42-G43 -> -3352.759 | H44: =H39-H42-H43 -> -3575.6187 | I44: =I39-I42-I43 -> -3774.3093 | ... AC44: =AC39-AC42-AC43 -> -5615.7577
A45: ISR & PTU | B45: 10481 | C45: 9680 | D45: =$H$61*D44 -> -609.49398 | E45: =$H$61*E44 -> -628.96334 | F45: =$H$61*F44 -> -672.24451 | G45: =$I$61*G44 -> -771.13456 | H45: =$I$61*H44 -> -822.3923 | I45: =$I$61*I44 -> -868.09113 | J45: =$I$61*J44 -> -915.64474 | K45: =$I$61*K44 -> -952.87435 | L45: =$I$61*L44 -> -981.33524 | M45: =$I$61*M44 -> -1005.3739 | N45: =$I$61*N44 -> -1024.8097 | ... AC45: =$I$61*AC44 -> -1291.6243
A46: Utilidad Neta | B46: =B44-B45 -> 58073 | C46: =C44-C45 -> 61045 | D46: =D44-D45 -> -2292.8583 | E46: =E44-E45 -> -2366.1002 | F46: =F44-F45 -> -2528.9198 | G46: =G44-G45 -> -2581.6244 | H46: =H44-H45 -> -2753.2264 | I46: =I44-I45 -> -2906.2181 | ... AC46: =AC44-AC45 -> -4324.1334
A47: Inversiones y Capex | B47: =OP!I34 -> 0 | C47: =OP!I35 -> 0 | D47: 10000 | E47: =D47*(1+E36*$H$62) -> 10408 | F47: =E47*(1+F36*$H$62) -> 11594.512 | G47: =F47*(1+G36*$H$62) -> 12916.286 | H47: =G47*(1+H36*$H$62) -> 14388.743 | I47: =H47*(1+I36*$H$62) -> 16029.06 | J47: =I47*(1+J36*$H$62) -> 17856.373 | K47: =J47*(1+K36*$H$62) -> 19570.584 | L47: =K47*(1+L36*$H$62) -> 20979.666 | ... AC47: =AB47*(1+AC36*$H$62) -> 43199.777
A48: Deuda + Lease Liabilities | B48: 108047 | C48: 112436 | D48: =C48*0.99 -> 111311.64 | E48: =D48 -> 111311.64 | F48: =E48 -> 111311.64 | G48: =F48 -> 111311.64 | H48: =G48 -> 111311.64 | I48: =H48 -> 111311.64 | J48: =I48 -> 111311.64 | K48: =J48 -> 111311.64 | L48: =K48 -> 111311.64 | ... AC48: =AB48 -> 111311.64
A49: Deuda/EBITDA | B49: =B48/B41 -> 1.6900829 | C49: =C48/C41 -> 1.6961743 | D49: =D48/D41 -> 9.4638771 | E49: =E48/E41 -> 9.172267
A50: FNP | B50: =OP!F34 -> 0 | C50: =OP!F35 -> 0 | D50: =D41-D42-D43-D45-D47+D48-C48 -> -2417.2183 | E50: =E41-E42-E43-E45-E47+E48-D48 -> -1400.1002 | F50: =F41-F42-F43-F45-F47+F48-E48 -> -1668.9018 | G50: =G41-G42-G43-G45-G47+G48-F48 -> -1860.2004 | H50: =H41-H42-H43-H45-H47+H48-G48 -> -2208.6766 | I50: =I41-I42-I43-I45-I47+I48-H48 -> -2583.3222 | J50: =J41-J42-J43-J45-J47+J48-I48 -> -3016.4004 | K50: =K41-K42-K43-K45-K47+K48-J48 -> -3422.8191 | ... AC50: =AC41-AC42-AC43-AC45-AC47+AC48-AB48 -> -10023.042
A51: F(t) | B51: 0 | C51: 0 | D51: =C51*(1+$B$59)+D50 -> -2417.2183 | E51: =D51*(1+$B$59)+E50 -> -4017.9476 | F51: =E51*(1+$B$59)+F50 -> -6020.3391 | G51: =F51*(1+$B$59)+G50 -> -8380.2276 | H51: =G51*(1+$B$59)+H50 -> -11284.463 | I51: =H51*(1+$B$59)+I50 -> -14804.396 | J51: =I51*(1+$B$59)+J50 -> -19049.561 | K51: =J51*(1+$B$59)+K50 -> -24053.494 | ... AC51: =AB51*(1+$B$59)+AC50 -> -324050.68
AB52: =AB51-AB48 -> -401272.53 | AC52: =AC50/(B59-AC36) -> -208813.38
A53: EPS | C53: =1000000*C46/OP!$C$8 -> 6.9805603e+08 | D53: =1000000*D46/OP!$C$8 -> -26219077 | E53: =1000000*E46/OP!$C$8 -> -27056606 | F53: =1000000*F46/OP!$C$8 -> -28918466
A54: Consenso EPS | C54: 3.3 | D54: 5.6 | E54: 5.6
A55: E$/UN | D55: =$B$61/D46 -> 36.249528 | E55: =$B$61/E46 -> 35.127436 | F55: =$B$61/F46 -> 32.865824
A56: EEV/EBIDA | D56: =($B$61+D48-D51)/D41 -> 2.6028318 | E56: =($B$61+E48-E51)/E41 -> 2.6545337 | F56: =($B$61+F48-F51)/F41 -> 2.5840842
C58: "TELP" | D58: CER | E58: D Analista | H58: CP | I58: LP
A59: Tasa de descuento: | B59: =SUM(C59:E59) -> 0.083 | C59: 0.0307 | D59: 0.0523 | E59: 0 | G59: Factor D&A | H59: 1 | I59: 1
G60: Factor CIF | H60: -0.01
A61: VPN*@i% | B61: =C62+C63 -> -83115.033 | C61: Normal | D61: =D31 -> 0.001 | E61: =D32 -> 0.005 | G61: Factor ISR | H61: 0.21 | I61: 0.23
A62: DCF 25Y | B62: =C62/B61 -> 0.65773118 | C62: =AB52/(1+B59)^25 -> -54667.349 | D62: =SUMPRODUCT(E50:AB50,E31:AB31) -> -39909.169 | E62: =SUMPRODUCT(E50:AB50,E32:AB32) -> -38157.285 | G62: Factor inv | H62: 1.2
A63: Perpetuidad | B63: =1-B62 -> 0.34226882 | C63: =AC52/(1+B59)^25 -> -28447.684 | D63: =(AC50/($B$59+D31-$AC$36))*AC31 -> -27231.492 | E63: =(AC50/($B$59+D32-$AC$36))*AC32 -> -22961.556 | G63: Suma D&A | H63: =SUM(40:40) -> 628429.57
A64: VPN/Acción | B64: =1000000*B61/OP!C8 -> -9.5042919e+08 | D64: =1000000*SUM(D62:D63)/OP!C8 -> -7.6776056e+08 | E64: =1000000*SUM(E62:E63)/OP!C8 -> -6.9890041e+08 | G64: Suma Inv. | H64: =SUM(47:47) -> 672845.39
B65: =B64/OP!C7-1 -> -2845597.4 | D65: =D64/B64-1 -> -0.19219594 | E65: =E64/B64-1 -> -0.26464757 | G65: Inv.+Goodwill | H65: =SUM(47:47)+(OP!E12*OP!E7) -> 678337.59
A67: Duración | B67: =B62*D68+B63*D69 -> 21.117542 | E67: 1 | F67: 2 | G67: 3 | H67: 4 | I67: 5 | J67: 6 | K67: 7 | L67: 8 | M67: 9 | N67: 10 | O67: 11 | P67: 12 | Q67: 13 | R67: 14 | S67: 15 | T67: 16 | U67: 17 | V67: 18 | W67: 19 | X67: 20 | Y67: 21 | Z67: 22 | AA67: 23 | AB67: 24 | AC67: 25
A68: 0.001 | B68: =-$B$67*A68 -> -0.021117542 | D68: =SUM(E68:AB68)/SUMPRODUCT(E50:AB50,E33:AB33) -> 12.307204 | E68: =E67*E50*E33 -> -1292.7979 | F68: =F67*F50*F33 -> -2845.7967 | G68: =G67*G50*G33 -> -4393.3482 | H68: =H67*H50*H33 -> -6422.1182 | I68: =I67*I50*I33 -> -8669.7445 | J68: =J67*J50*J33 -> -11216.814 | K68: =K67*K50*K33 -> -13711.431 | L68: =L67*L50*L33 -> -15923.848 | ... AC68: =AC67*AC50*AC33 -> -34137.221
A69: 0.005 | B69: =-$B$67*A69 -> -0.10558771 | D69: =(1+B59)/B59+AC67 -> 38.048193

Sheet DCFF
C1: VALUATION MODEL
C2: Año fiscal de Apple cierra en septiembre
D3: =D19/D6 -> -0.086599655 | E3: =E19/E6 -> -0.087061415 | F3: =F19/F6 -> -0.081380713 | G3: 0 | H3: 0.25 | I3: =H3+1 -> 1.25 | J3: =I3+1 -> 2.25 | K3: =J3+1 -> 3.25 | L3: =K3+1 -> 4.25 | M3: =L3+1 -> 5.25 | N3: =M3+1 -> 6.25 | O3: =N3+1 -> 7.25 | P3: =O3+1 -> 8.25 | ... AF3: =AE3+1 -> 24.25
A4: Section | B4: Line # | C4: ITEM | D4: 2020 (Real) | E4: 2021 (Real) | F4: 2022 (Real) | G4: 2023 (Real) | H4: 2024 | I4: =+H4+1 -> 2025 | J4: =+I4+1 -> 2026 | K4: =+J4+1 -> 2027 | L4: =+K4+1 -> 2028 | M4: =+L4+1 -> 2029 | N4: =+M4+1 -> 2030 | O4: =+N4+1 -> 2031 | P4: =+O4+1 -> 2032 | ... AF4: =+AE4+1 -> 2048 | AG4: Notes
A5: INCOME STATEMENT | B5: 1 | C5: Growth | D5: 0.08 | E5: =Cifras_en_Millones!E6 -> 0.13406293 | F5: =Cifras_en_Millones!D6 -> 0.083337704 | G5: =Cifras_en_Millones!C6 -> 0.098905887 | H5: =H6/G6-1 -> 0.10533504 | I5: =I6/H6-1 -> 0.092865684 | J5: =J6/I6-1 -> 0.134 | K5: =K6/J6-1 -> 0.134 | L5: =L6/K6-1 -> 0.134 | M5: =M6/L6-1 -> 0.134 | N5: =N6/M6-1 -> 0.134 | O5: =O6/N6-1 -> 0.07 | ... AE5: =AE6/AD6-1 -> 0.07 | AF5: 0.02
B6: 2 | C6: Revenues/Sales | D6: 1681.3 | E6: 1906.7 | F6: 2065.6 | G6: 2269.9 | H6: 2509 | I6: 2742 | J6: =I6*(1.134) -> 3109.428 | K6: =J6*(1.134) -> 3526.0914 | L6: =K6*(1.134) -> 3998.5876 | M6: =L6*(1.134) -> 4534.3983 | N6: =M6*(1.134) -> 5142.0077 | O6: =N6*1.07 -> 5501.9482 | P6: =O6*1.07 -> 5887.0846 | Q6: =P6*1.07 -> 6299.1805 | R6: =Q6*1.07 -> 6740.1232 | S6: =R6*1.07 -> 7211.9318 | T6: =S6*1.07 -> 7716.767 | U6: =T6*1.07 -> 8256.9407 | V6: =U6*1.07 -> 8834.9266 | ... AF6: =AE6*1.07 -> 17379.638
B7: 3 | C7: EBIT/Operating Margin | D7: =523/DCFF!D6 -> 0.31106882 | E7: =494/E6 -> 0.25908638 | F7: =515/F6 -> 0.24932223 | G7: =757/G6 -> 0.33349487 | H7: =H8/H6 -> 0.23595058 | I7: =AVERAGE(D7:H7) -> 0.27778457 | J7: =AVERAGE(E7:I7) -> 0.27112773 | K7: =AVERAGE(F7:J7) -> 0.273536 | L7: =AVERAGE(G7:K7) -> 0.27837875 | M7: =L7*1.02 -> 0.28394632 | N7: =M7*1.02 -> 0.28962525 | O7: =N7*1.02 -> 0.29541775 | P7: =O7*1.02 -> 0.30132611 | Q7: =P7*1.02 -> 0.30735263 | R7: =Q7*1.02 -> 0.31349968 | S7: =R7*1.02 -> 0.31976968 | T7: =S7*1.02 -> 0.32616507 | ... AF7: =AE7*1.02 -> 0.41365618
B8: 4 | C8: EBIT | D8: 496 | E8: 513 | F8: 593 | G8: 626 | H8: 592 | I8: =I7*I6 -> 761.6853 | J8: =J7*J6 -> 843.05214 | K8: =K7*K6 -> 964.51291 | L8: =L7*L6 -> 1113.1218 | M8: =M7*M6 -> 1287.5257 | N8: =N7*N6 -> 1489.2553 | O8: =O7*O6 -> 1625.3732 | P8: =P7*P6 -> 1773.9323 | ... AF8: =AF7*AF6 -> 7189.1945
B9: 5a | C9: (Dep&Amort) | D9: -85.3 | E9: -106.9 | F9: -114.6 | G9: -132.5 | H9: {=G9*0.7+0.3*(-$D$50*AVERAGE(-1*(D22:G22)))} -> -94.306077 | I9: {=H9*0.7+0.3*(-$D$50*AVERAGE(-1*(E22:H22)))} -> -67.567717 | J9: {=I9*0.7+0.3*(-$D$50*AVERAGE(-1*(F22:I22)))} -> -49.06979 | K9: {=J9*0.7+0.3*(-$D$50*AVERAGE(-1*(G22:J22)))} -> -36.39978 | L9: {=K9*0.7+0.3*(-$D$50*AVERAGE(-1*(H22:K22)))} -> -27.878863 | M9: {=L9*0.7+0.3*(-$D$50*AVERAGE(-1*(I22:L22)))} -> -22.426805 | N9: {=M9*0.7+0.3*(-$D$50*AVERAGE(-1*(J22:M22)))} -> -19.212465 | O9: {=N9*0.7+0.3*(-$D$50*AVERAGE(-1*(K22:N22)))} -> -17.645209 | ... AF9: {=AE9*0.7+0.3*(-$D$50*AVERAGE(-1*(AB22:AE22)))} -> -43.391047
B10: 5b | C10: (Stock based compensation) | D10: -145.6 | E10: -166.3 | F10: -168.1 | G10: -221.9 | H10: =($D$51*H6)*-1 -> -221.39211 | I10: =($D$51*I6)*-1 -> -241.95184 | J10: =($D$51*J6)*-1 -> -274.37339 | K10: =($D$51*K6)*-1 -> -311.13942 | L10: =($D$51*L6)*-1 -> -352.8321 | M10: =($D$51*M6)*-1 -> -400.11161 | N10: =($D$51*N6)*-1 -> -453.72656 | O10: =($D$51*O6)*-1 -> -485.48742 | ... AF10: =($D$51*AF6)*-1 -> -1533.565
B11: 6 | C11: EBIDTA | D11: =-D9+D8 -> 581.3 | E11: =-E9+E8 -> 619.9 | F11: =-F9+F8 -> 707.6 | G11: =-G9+G8 -> 758.5 | H11: =-H9+H8 -> 686.30608 | I11: =-I9+I8 -> 829.25302 | J11: =-J9+J8 -> 892.12193 | K11: =-K9+K8 -> 1000.9127 | ... AF11: =-AF9+AF8 -> 7232.5856
B12: 7 | C12: (Net financing cost) | D12: =Cifras_Originales!E11 -> 4.2 | E12: =Cifras_Originales!D11 -> 5 | F12: =Cifras_Originales!C11 -> -5.4 | G12: =Cifras_Originales!B11 -> 43.9 | H12: =-$D$53*G37+G36*$D$54 -> 38.59592 | I12: =-$D$53*H37+H36*$D$54 -> 57.678667 | J12: =-$D$53*I37+I36*$D$54 -> 79.622607 | K12: =-$D$53*J37+J36*$D$54 -> 103.9971 | L12: =-$D$53*K37+K36*$D$54 -> 131.08106 | M12: =-$D$53*L37+L36*$D$54 -> 161.27488 | N12: =-$D$53*M37+M36*$D$54 -> 195.55392 | O12: =-$D$53*N37+N36*$D$54 -> 234.36027 | ... AF12: =-$D$53*AE37+AE36*$D$54 -> 1721.9618
B13: 8 | C13: Other income/(cost) | D13: =Cifras_Originales!E12 -> -2.43 | E13: =Cifras_Originales!D12 -> 2.08 | F13: =Cifras_Originales!C12 -> -17.34 | G13: =Cifras_Originales!B12 -> -34 | H13: -21 | I13: =H13*(1+I5) -> -22.950179 | J13: =I13*(1+J5) -> -26.025503 | K13: =J13*(1+K5) -> -29.512921 | L13: =K13*(1+L5) -> -33.467652 | M13: =L13*(1+M5) -> -37.952318 | N13: =M13*(1+N5) -> -43.037928 | O13: =N13*(1+O5) -> -46.050583 | P13: =O13*(1+P5) -> -49.274124 | ... AF13: =AE13*(1+AF5) -> -138.66784
B14: 9 | C14: Earnings before taxes | D14: =D8+D12+D13 -> 497.77 | E14: =E8+E12+E13 -> 520.08 | F14: =F8+F12+F13 -> 570.26 | G14: =G8+G12+G13 -> 635.9 | H14: =H8+H12+H13 -> 609.59592 | I14: =I8+I12+I13 -> 796.41379 | J14: =J8+J12+J13 -> 896.64925 | K14: =K8+K12+K13 -> 1038.9971 | ... AF14: =AF8+AF12+AF13 -> 8772.4885
B15: 10 | C15: (Income tax) | D15: =-Cifras_Originales!E17 -> -60.7 | E15: =-Cifras_Originales!D17 -> -51.6 | F15: =-Cifras_Originales!C17 -> -91.7 | G15: =-Cifras_Originales!B17 -> -115.8 | H15: =(-1*$D$52)*H14 -> -115.82322 | I15: =(-1*$D$52)*I14 -> -151.31862 | J15: =(-1*$D$52)*J14 -> -170.36336 | K15: =(-1*$D$52)*K14 -> -197.40945 | L15: =(-1*$D$52)*L14 -> -230.03969 | M15: =(-1*$D$52)*M14 -> -268.06118 | N15: =(-1*$E$52)*N14 -> -322.75617 | O15: =(-1*$E$52)*O14 -> -356.55232 | P15: =(-1*$E$52)*P14 -> -393.21239 | Q15: =(-1*$E$52)*Q14 -> -433.20026 | R15: =(-1*$E$52)*R14 -> -476.8233 | S15: =(-1*$E$52)*S14 -> -524.41186 | T15: =(-1*$E$52)*T14 -> -576.32582 | U15: =(-1*$E$52)*U14 -> -632.95962 | ... AF15: =(-1*$E$52)*AF14 -> -1724.5854
B16: 11 | C16: Net income | D16: =D14+D15 -> 437.07 | E16: =E14+E15 -> 468.48 | F16: =F14+F15 -> 478.56 | G16: =G14+G15 -> 520.1 | H16: =H14+H15 -> 493.7727 | I16: =I14+I15 -> 645.09517 | J16: =J14+J15 -> 726.28589 | K16: =K14+K15 -> 841.58764 | ... AF16: =AF14+AF15 -> 7047.903
A18: CASH FLOW STATEMENT | B18: 12 | C18: Operating cash flows before WK | D18: 663 | E18: 774 | F18: 710 | G18: 692 | H18: =H11+H12+H13+H15 -> 588.07877 | I18: =I11+I12+I13+I15 -> 712.66289 | J18: =J11+J12+J13+J15 -> 775.35568 | K18: =K11+K12+K13+K15 -> 877.98742 | L18: =L11+L12+L13+L15 -> 1008.5744 | M18: =M11+M12+M13+M15 -> 1165.2139 | N18: =N11+N12+N13+N15 -> 1338.2275 | O18: =O11+O12+O13+O15 -> 1474.7758 | ... AF18: =AF11+AF12+AF13+AF15 -> 7091.2941
B19: 13 | C19: (Stock-based compensation) | D19: -145.6 | E19: -166 | F19: -168.1 | G19: -221.9 | H19: =$D$55*H6 -> 208.62313 | I19: =$D$55*I6 -> 227.99706 | J19: =$D$55*J6 -> 258.54867 | K19: =$D$55*K6 -> 293.19419 | L19: =$D$55*L6 -> 332.48221 | M19: =$D$55*M6 -> 377.03483 | N19: =$D$55*N6 -> 427.5575 | O19: =$D$55*O6 -> 457.48652 | ... AF19: =$D$55*AF6 -> 1445.1154
B20: 14 | C20: (Working Capital Flows) | D20: =T94 -> 130 | E20: =U94 -> -130 | F20: =V94 -> 9 | G20: =W94 -> 331 | H20: =$D$56*(H6-G6) -> 40.755691 | I20: =$D$56*(I6-H6) -> 39.715918 | J20: =$D$56*(J6-I6) -> 62.629786 | K20: =$D$56*(K6-J6) -> 71.022178 | L20: =$E$56*(L6-K6) -> 80.539149 | M20: =$E$56*(M6-L6) -> 91.331395 | N20: =$E$56*(N6-M6) -> 103.5698 | O20: =$E$56*(O6-N6) -> 61.353514 | P20: =$E$56*(P6-O6) -> 65.64826 | Q20: =$E$56*(Q6-P6) -> 70.243639 | R20: =$E$56*(R6-Q6) -> 75.160693 | S20: =$E$56*(S6-R6) -> 80.421942 | ... AF20: =$E$56*(AF6-AE6) -> 193.80441
B21: 15 | C21: -Total Operating Cash Flow | D21: =D18+D19+D20 -> 647.4 | E21: =E18+E19+E20 -> 478 | F21: =F18+F19+F20 -> 550.9 | G21: =G18+G19+G20 -> 801.1 | H21: =H18+H19+H20 -> 837.4576 | I21: =I18+I19+I20 -> 980.37587 | J21: =J18+J19+J20 -> 1096.5341 | K21: =K18+K19+K20 -> 1242.2038 | ... AF21: =AF18+AF19+AF20 -> 8730.2139
B22: 16 | C22: (CAPEX and Acquisitions) | D22: -35 | E22: -23 | F22: -24 | G22: -25 | H22: =-$D$57*H6 -> -34.820248 | I22: =-$D$57*I6 -> -38.053854 | J22: =-$D$57*J6 -> -43.153071 | K22: =-$D$57*K6 -> -48.935582 | L22: =-$E$57*L6 -> -70.066913 | M22: =-$E$57*M6 -> -79.455879 | N22: =-$E$57*N6 -> -90.102967 | O22: =-$E$57*O6 -> -96.410174 | P22: =-$E$57*P6 -> -103.15889 | Q22: =-$E$57*Q6 -> -110.38001 | R22: =-$E$57*R6 -> -118.10661 | S22: =-$E$57*S6 -> -126.37407 | ... AF22: =-$E$57*AF6 -> -304.54192
B23: 17 | C23: (Other investing flows) | D23: -7 | E23: -3 | F23: -0.7 | G23: -5.8 | H23: 0 | I23: 0 | J23: 0 | K23: 0 | L23: 0 | M23: 0 | N23: 0 | O23: 0 | P23: 0 | Q23: 0 | R23: 0 | S23: 0 | T23: 0 | U23: 0 | V23: 0 | W23: 0 | X23: 0 | Y23: 0 | Z23: 0 | AA23: 0 | AB23: 0 | AC23: 0 | AD23: 0 | AE23: 0 | AF23: 0
B24: 18 | C24: -Total Investing Flows | D24: =D22+D23 -> -42 | E24: =E22+E23 -> -26 | F24: =F22+F23 -> -24.7 | G24: =G22+G23 -> -30.8 | H24: =H22+H23 -> -34.820248 | I24: =I22+I23 -> -38.053854 | J24: =J22+J23 -> -43.153071 | K24: =K22+K23 -> -48.935582 | ... AF24: =AF22+AF23 -> -304.54192
B25: 19 | C25: (Flows related to leases) | D25: -23 | E25: -22 | F25: -23 | G25: -24 | H25: =AVERAGE(D25:G25) -> -23 | I25: =AVERAGE(E25:H25) -> -23 | J25: =AVERAGE(F25:I25) -> -23.25 | K25: =AVERAGE(G25:J25) -> -23.3125 | L25: =AVERAGE(H25:K25) -> -23.140625 | M25: =AVERAGE(I25:L25) -> -23.175781 | N25: =AVERAGE(J25:M25) -> -23.219727 | O25: =AVERAGE(K25:N25) -> -23.212158 | ... AF25: =AVERAGE(AB25:AE25) -> -23.199998
B26: 20 | C26: Flows related to debt | D26: 300 | E26: -45 | F26: 0 | G26: 0 | H26: =(H37-G37) -> 0 | I26: =(I37-H37) -> 0 | J26: =(J37-I37) -> 0 | K26: =(K37-J37) -> 0 | L26: =(L37-K37) -> 0 | M26: =(M37-L37) -> 0 | N26: =(N37-M37) -> 0 | O26: =(O37-N37) -> 0 | ... AF26: =(AF37-AE37) -> 0
B27: 21 | C27: (Respurchases)/Issuance of stock | D27: -161 | E27: -135 | F27: -206 | G27: -196 | H27: =AVERAGE(D27:G27) -> -174.5 | I27: =AVERAGE(E27:H27) -> -177.875 | J27: =AVERAGE(F27:I27) -> -188.59375 | K27: =AVERAGE(G27:J27) -> -184.24219 | L27: =AVERAGE(H27:K27) -> -181.30273 | M27: =AVERAGE(I27:L27) -> -183.00342 | N27: =AVERAGE(J27:M27) -> -184.28552 | O27: =AVERAGE(K27:N27) -> -183.20847 | ... AF27: =AVERAGE(AB27:AE27) -> -183.30014
B28: 22 | C28: (Dividends) | D28: =Cifras_Originales!E19 -> 0 | E28: =Cifras_Originales!D19 -> 0 | F28: =Cifras_Originales!C19 -> 0 | G28: =Cifras_Originales!B19 -> 0 | H28: =(1+$D$58)*G28 -> 0 | I28: =(1+$D$58)*H28 -> 0 | J28: =(1+$D$58)*I28 -> 0 | K28: =(1+$D$58)*J28 -> 0 | L28: =(1+$E$58)*K28 -> 0 | M28: =(1+$E$58)*L28 -> 0 | N28: =(1+$E$58)*M28 -> 0 | O28: =(1+$E$58)*N28 -> 0 | P28: =(1+$E$58)*O28 -> 0 | Q28: =(1+$E$58)*P28 -> 0 | R28: =(1+$E$58)*Q28 -> 0 | S28: =(1+$E$58)*R28 -> 0 | ... AF28: =(1+$E$58)*AE28 -> 0
B29: 23 | C29: Other financing flows | D29: -0.9 | E29: -0.5 | F29: -1.3 | G29: -1.3 | H29: 0 | I29: 0 | J29: 0 | K29: 0 | L29: 0 | M29: 0 | N29: 0 | O29: 0 | P29: 0 | Q29: 0 | R29: 0 | S29: 0 | T29: 0 | U29: 0 | V29: 0 | W29: 0 | X29: 0 | Y29: 0 | Z29: 0 | AA29: 0 | AB29: 0 | AC29: 0 | AD29: 0 | AE29: 0 | AF29: 0
B30: 24 | C30: -Total Financing flows | D30: =SUM(D25:D29) -> 115.1 | E30: =SUM(E25:E29) -> -202.5 | F30: =SUM(F25:F29) -> -230.3 | G30: =SUM(G25:G29) -> -221.3 | H30: =SUM(H25:H29) -> -197.5 | I30: =SUM(I25:I29) -> -200.875 | J30: =SUM(J25:J29) -> -211.84375 | K30: =SUM(K25:K29) -> -207.55469 | ... AF30: =SUM(AF25:AF29) -> -206.50014
A32: SUMMARY | B32: 25 | C32: Cash before shareholder returns | D32: =D21+D24+D25+D26+D29 -> 881.5 | E32: =E21+E24+E25+E26+E29 -> 384.5 | F32: =F21+F24+F25+F26+F29 -> 501.9 | G32: =G21+G24+G25+G26+G29 -> 745 | H32: =H21+H24+H25+H26+H29 -> 779.63735 | I32: =I21+I24+I25+I26+I29 -> 919.32201 | J32: =J21+J24+J25+J26+J29 -> 1030.1311 | K32: =K21+K24+K25+K26+K29 -> 1169.9557 | ... AF32: =AF21+AF24+AF25+AF26+AF29 -> 8402.472
B33: 26 | C33: Returns to shareholders | D33: =(D27+D28) -> -161 | E33: =(E27+E28) -> -135 | F33: =(F27+F28) -> -206 | G33: =(G27+G28) -> -196 | H33: =(H27+H28) -> -174.5 | I33: =(I27+I28) -> -177.875 | J33: =(J27+J28) -> -188.59375 | K33: =(K27+K28) -> -184.24219 | ... AF33: =(AF27+AF28) -> -183.30014
B34: 27 | C34: Excess cash acumulation | D34: =D32-D33 -> 1042.5 | E34: =E32-E33 -> 519.5 | F34: =F32-F33 -> 707.9 | G34: =G32-G33 -> 941 | H34: =H32-H33 -> 954.13735 | I34: =I32-I33 -> 1097.197 | J34: =J32-J33 -> 1218.7248 | K34: =K32-K33 -> 1354.1979 | ... AF34: =AF32-AF33 -> 8585.7721
A36: CASH & DEBT & DISCOUNTING | B36: 28 | C36: Ending cash balance | D36: 912.7 | E36: =D36+E34 -> 1432.2 | F36: =E36+F34 -> 2140.1 | G36: =F36+G34 -> 3081.1 | H36: =G36+H34 -> 4035.2373 | I36: =H36+I34 -> 5132.4344 | J36: =I36+J34 -> 6351.1592 | K36: =J36+K34 -> 7705.3571 | L36: =K36+L34 -> 9215.048 | ... AF36: =AE36+AF34 -> 95835.166
B37: 29 | C37: Total Debt | D37: 942.7 | E37: 880.8 | F37: 889.2 | G37: 877.7 | H37: =G37 -> 877.7 | I37: =H37 -> 877.7 | J37: =I37 -> 877.7 | K37: =J37 -> 877.7 | L37: =K37 -> 877.7 | M37: =L37 -> 877.7 | N37: =M37 -> 877.7 | O37: =N37 -> 877.7 | ... AF37: =AE37 -> 877.7
B38: 30 | C38: Discount factor | G38: =1/((1+$D$47)^G3) -> 1 | H38: =1/((1+$D$47)^H3) -> 0.98080746 | I38: =1/((1+$D$47)^I3) -> 0.9076508 | J38: =1/((1+$D$47)^J3) -> 0.83995077 | K38: =1/((1+$D$47)^K3) -> 0.77730036 | L38: =1/((1+$D$47)^L3) -> 0.71932293 | M38: =1/((1+$D$47)^M3) -> 0.66566994 | N38: =1/((1+$D$47)^N3) -> 0.61601882 | ... AF38: =1/((1+$D$47)^AF3) -> 0.15262464
F39: =1/((1+$D$48+0.001)^F$3) -> 1.0000813 | G39: =1/((1+$D$47+0.001)^G$3) -> 1 | H39: =1/((1+$D$47+0.001)^H$3) -> 0.98058068 | I39: =1/((1+$D$47+0.001)^I$3) -> 0.90660196 | J39: =1/((1+$D$47+0.001)^J$3) -> 0.83820447 | K39: =1/((1+$D$47+0.001)^K$3) -> 0.77496715 | L39: =1/((1+$D$47+0.001)^L$3) -> 0.71650069 | M39: =1/((1+$D$47+0.001)^M$3) -> 0.66244517 | N39: =1/((1+$D$47+0.001)^N$3) -> 0.6124678 | ... AE39: =1/((1+$D$47+0.001)^AE$3) -> 0.16141717
F40: =1/((1+$D$48+0.005)^F$3) -> 1.000406 | G40: =1/((1+$D$47+0.005)^G$3) -> 1 | H40: =1/((1+$D$47+0.005)^H$3) -> 0.97967616 | I40: =1/((1+$D$47+0.005)^I$3) -> 0.9024283 | J40: =1/((1+$D$47+0.005)^J$3) -> 0.83127146 | K40: =1/((1+$D$47+0.005)^K$3) -> 0.76572537 | L40: =1/((1+$D$47+0.005)^L$3) -> 0.70534762 | M40: =1/((1+$D$47+0.005)^M$3) -> 0.64973067 | N40: =1/((1+$D$47+0.005)^N$3) -> 0.59849914 | ... AE40: =1/((1+$D$47+0.005)^AE$3) -> 0.14814137
C42: EPS | H42: =1000000*H16/OP!C8 -> 5646343 | I42: =1000000*I16/OP!$C8 -> 7376731.5 | J42: =1000000*J16/OP!$C8 -> 8305156
C43: Consenso EPS
C44: E$/UN | H44: =$D$64/H16 -> 67.207824 | I44: =$D$64/I16 -> 51.442624
A46: Discount rate | D46: Total | E46: Risk free rate | F46: Equity premium | G46: Firm premium
C47: Discount Rate | D47: =SUM(E47:G47) -> 0.0806 | E47: 0.04 | F47: 0.0406
D49: Short Term | E49: Long Term | F49: Reference (line)
A50: Modelling factors | C50: Depreciation factor | D50: 0.19390371 | E50: 0.19390371 | F50: % Capex/Adq (l16) | G50: =SUM(G22:AF22)/SUM(G9:AF9) -> 3.9931898
C51: Stock-based comp | D51: =H71 -> 0.088239183 | E51: 0.09 | F51: % revenue (l2) | G51: =-SUM(D10:F10)/SUM(D6:F6) -> 0.084901656
C52: Tax Rate | D52: 0.19 | E52: =N82 -> 0.19659022 | F52: % (line 9)
C53: Interest Rate on debt | D53: =H74 -> 0.026234568 | E53: 0.04 | F53: % debt (l29)
C54: Interest Rate on cash | D54: 0.02 | E54: =N83 -> 0.021225515 | F54: % of cash (l28)
C55: Net SBC | D55: =H78 -> 0.083149914 | E55: =N88 -> 0.060030242 | F55: % revenue (l2)
C56: Working capital flows | D56: =Y97 -> 0.17045458 | E56: =D56 -> 0.17045458 | F56: % of change revenues (l2)
C57: Capex / Adq | D57: =H75 -> 0.013878138 | E57: =N85 -> 0.017522915 | F57: % revenue (l2)
C58: Dividends | D58: 0 | E58: 0 | F58: Growth rate
C59: Other financing flows | D59: =H76 -> -0.0011163756 | E59: =N86 -> -0.0030276904 | F59: % of debt (l29)
A61: Valuation | D61: $ millions | E61: % | F61: Notes | AE61: =((AE36-AE37)*AE38) -> 14244.954
C62: Value of flows | D62: =SUMPRODUCT(G33:AE33,G38:AE38)+((AE36-AE37)*AE38) -> 12023.273 | E62: =D62/D64 -> 0.36230622 | F62: Present value of flows (l27), plus cash minus debt | AE62: =AE54+AE61 -> 14244.954
C63: Value of perpetuity | D63: =(AF32/(D47-AF5))*AF38 -> 21162.116 | E63: =D63/D64 -> 0.63769378 | F63: Present value of perpetuity (column AF flow, dividend by growth minus discount rate)
C64: Total Value | D64: =D62+D63 -> 33185.389 | F64: Final market value of firm's equity, compare to its mkt cap
C65: Total value vs Mkt Cap | D65: =D66/D67-1 -> 0.13616296 | F65: Gives degree of undervaluation (if positive, meaning it's worth more than what the market thinks) or overvaluation (negative, worth less than what the market thinks)
C66: Estimated NPV per share | D66: =D64/OP!C8 -> 379.47843 | F66: If we divide total value by # of shares, we get the estimated share value
C67: Actual share price | D67: =OP!C7 -> 334 | F67: Actual share price
C70: calculations for ST ratios (4y) | D70: 2020 | E70: 2021 | F70: 2022 | G70: 2023 | H70: ST average
C71: Stock-based comp | D71: =D10/D6 -> -0.086599655 | E71: =E10/E6 -> -0.087218755 | F71: =F10/F6 -> -0.081380713 | G71: =G10/G6 -> -0.09775761 | H71: =(AVERAGE(D71:G71))*-1 -> 0.088239183
C72: Tax rate | D72: =D15/D14 -> -0.12194387 | E72: =E15/E14 -> -0.099215505 | F72: =F15/F14 -> -0.16080384 | G72: =G15/G14 -> -0.1821041 | H72: =AVERAGE(D72:G72) -> -0.14101683
C73: Interest Rate on cash | D73: =11/D34 -> 0.010551559 | E73: =12.4/E34 -> 0.023869105 | F73: =22.7/F34 -> 0.032066676 | G73: =47.1/G34 -> 0.050053135 | H73: =AVERAGE(D73:G73) -> 0.029135119
C74: Interest Rate on debt | D74: =11/D37 -> 0.011668611 | E74: =12.4/E37 -> 0.014078111 | F74: =22.7/F37 -> 0.025528565 | G74: =47.1/G37 -> 0.053662983 | H74: =AVERAGE(D74:G74) -> 0.026234568
C75: Capex/adq | D75: =J85 -> 0.020817225 | E75: =K85 -> 0.012062726 | F75: =L85 -> 0.0116189 | G75: =M85 -> 0.011013701 | H75: =AVERAGE(D75:G75) -> 0.013878138
C76: other financing flows | D76: =D29/D37 -> -0.00095470457 | E76: =E29/E37 -> -0.00056766576 | F76: =F29/F37 -> -0.0014619883 | G76: =G29/G37 -> -0.0014811439 | H76: =AVERAGE(D76:G76) -> -0.0011163756
C77: Working capital flows | D77: -0.57 | E77: 0.0006 | F77: 0.0162 | G77: -0.42 | H77: 0.17
C78: Net SBC | D78: 0.086599655 | E78: 0.078 | F78: 0.076 | G78: 0.092 | H78: =AVERAGE(Table1[[#This Row],[2020]:[2023]]) -> 0.083149914 | I78: (no tax benefit from stock options)
C80: calculations for LT ratios (10y) | D80: 2014 | E80: 2015 | F80: 2016 | G80: 2017 | H80: 2018 | I80: 2019 | J80: 2020 | K80: 2021 | L80: 2022 | M80: 2023 | N80: LT average | V80: Fix/Left
C81: Stock-based comp | D81: 0.023824786 | E81: 0.036062792 | F81: 0.033687405 | G81: 0.048571168 | H81: 0.064393939 | I81: 0.076654133 | J81: =D10/D6 -> -0.086599655 | K81: =E10/E6 -> -0.087218755 | L81: =F10/F6 -> -0.081380713 | M81: =G10/G6 -> -0.09775761 | N81: =AVERAGE(Table2[[#This Row],[2020]:[2023]]) -> -0.088239183 | S81: Sales | U81: Nice | V81: Explain
C82: Tax rate | D82: 0.2683137 | E82: 0.29204036 | F82: 0.301604 | G82: 0.34470558 | H82: 0.13898584 | I82: 0.13643322 | J82: 0.12148208 | K82: 0.1177726 | L82: 0.089692334 | M82: 0.15487249 | N82: =AVERAGE(Table2[[#This Row],[2014]:[2023]]) -> 0.19659022 | S82: Margins | U82: Nice | V82: Explain
C83: Interest Rate on cash | D83: 0.0010151 | E83: 0 | F83: 0 | G83: 0 | H83: 0 | I83: 0.004013301 | J83: 0.012052153 | K83: 0.018571215 | L83: 0.036946615 | M83: 0.054754708 | N83: =(Table2[[#This Row],[2014]]+Table2[[#This Row],[2019]]+Table2[[#This Row],[2020]]+Table2[[#This Row],[2021]]+Table2[[#This Row],[2022]]+Table2[[#This Row],[2023]])/6 -> 0.021225515 | S83: D&A | V83: Why the odd numbers?
C84: Interest Rate on debt | D84: 0 | E84: 0 | F84: 0 | G84: 0 | H84: 0 | I84: 0.005120702 | J84: 0.011668611 | K84: 0.014078111 | L84: 0.025528565 | M84: 0.053662983 | N84: =AVERAGE(Table2[[#This Row],[2019]:[2022]]) -> 0.014098997
C85: Capex/adq | D85: 0.028 | E85: 0.016970725 | F85: 0.012139605 | G85: 0.017346846 | H85: 0.016233766 | I85: 0.029025661 | J85: 0.020817225 | K85: 0.012062726 | L85: 0.0116189 | M85: 0.011013701 | N85: =AVERAGE(Table2[[#This Row],[2014]:[2023]]) -> 0.017522915 | S85: NWC | U85: Explain
C86: other financing flows | D86: -0.01025641 | E86: -0.005939754 | F86: -0.006170966 | G86: 0 | H86: -0.003865182 | I86: -0.00204499 | J86: -0.0005353 | K86: -0.000262233 | L86: -0.000629357 | M86: -0.000572712 | N86: =AVERAGE(Table2[[#This Row],[2014]:[2023]]) -> -0.0030276904 | S86: CapEx | V86: Why the odd numbers?
C87: Working capital flows | D87: 0.66131191 | E87: 4.0735294 | F87: 0.22757112 | G87: 0.14981273 | H87: -0.13867877 | I87: -0.55870445 | J87: -0.7019347 | K87: -0.67169477 | L87: -0.37696665 | M87: -0.27704356 | N87: 0.23872023
C88: Net SBC | D88: 0.008333333 | E88: 0.036062792 | F88: 0.033687405 | G88: 0.048571168 | H88: 0.064393939 | I88: 0.076654133 | J88: 0.086599655 | K88: 0.078 | L88: 0.076 | M88: 0.092 | N88: =AVERAGE(Table2[[#This Row],[2014]:[2023]]) -> 0.060030242 | T88: Debt schedule???
D92: 2023 | E92: =D92-1 -> 2022 | F92: =E92-1 -> 2021 | G92: =F92-1 -> 2020 | H92: =G92-1 -> 2019 | I92: =H92-1 -> 2018 | N92: 2014 | O92: 2015 | P92: 2016 | Q92: 2017 | R92: 2018 | S92: 2019 | T92: 2020 | U92: 2021 | V92: 2022 | W92: 2023 | X92: 2024
C93: D&A | D93: 132.5 | E93: 114.6 | F93: 106.9 | G93: 85.3 | H93: 60.5 | I93: 59.2 | M93: NWC | N93: 662 | O93: 662 | P93: 662 | Q93: 662 | R93: 786 | S93: 860 | T93: 990 | U93: 860 | V93: 869 | W93: 1200 | X93: 1100
C94: Amort. | D94: 81 | E94: 69.3 | F94: 60.8 | G94: 40.6 | H94: 21.7 | I94: 27 | M94: change | O94: =O93-N93 -> 0 | P94: =P93-O93 -> 0 | Q94: =Q93-P93 -> 0 | R94: =R93-Q93 -> 124 | S94: =S93-R93 -> 74 | T94: =T93-S93 -> 130 | U94: =U93-T93 -> -130 | V94: =V93-U93 -> 9 | ... X94: =X93-W93 -> -100 | Y94: =AVERAGE(T94:X94) -> 48
C95: Dep | D95: =D93-D94 -> 51.5 | E95: =E93-E94 -> 45.3 | F95: =F93-F94 -> 46.1 | G95: =G93-G94 -> 44.7 | H95: =H93-H94 -> 38.8 | I95: =I93-I94 -> 32.2 | M95: revenue | T95: 1681.3 | U95: 1906.7 | V95: 2065.6 | W95: 2269.9 | X95: 2509
M96: change in revenue | U96: =U95-T95 -> 225.4 | V96: =V95-U95 -> 158.9 | W96: =W95-V95 -> 204.3 | X96: =X95-W95 -> 239.1
C97: Net PPE | D97: 77.8 | E97: 80.8 | F97: 87.9 | G97: 96.5 | H97: 83.6 | I97: 61.7 | M97: change in NWC / Change in revenue | U97: =U94/U96 -> -0.57675244 | V97: =V94/V96 -> 0.056639396 | W97: =W94/W96 -> 1.6201664 | X97: =X94/X96 -> -0.41823505 | Y97: =AVERAGE(U97:X97) -> 0.17045458
C98: Accumulated Dep | D98: 175.5 | E98: 158.3 | F98: 156.1 | G98: 142.3 | H98: 129.1 | I98: 121.5
C99: Gross tangibles | D99: =D97+D98 -> 253.3 | E99: =E97+E98 -> 239.1 | F99: =F97+F98 -> 244 | G99: =G97+G98 -> 238.8 | H99: =H97+H98 -> 212.7 | I99: =I97+I98 -> 183.2
J100: 3Y average
C101: Dep as % of Gross PPE | D101: =D95/D99 -> 0.20331623 | E101: =E95/E99 -> 0.18946048 | F101: =F95/F99 -> 0.18893443 | G101: =G95/G99 -> 0.18718593 | H101: =H95/H99 -> 0.18241655 | I101: =I95/I99 -> 0.17576419 | J101: =AVERAGE(D101:F101) -> 0.19390371
C102: Amort. As % of Gross Intangibles | D102: =D94/D99 -> 0.31977892 | E102: =E94/E99 -> 0.28983689 | F102: =F94/F99 -> 0.24918033 | G102: =G94/G99 -> 0.17001675 | H102: =H94/H99 -> 0.10202163 | I102: =I94/I99 -> 0.14737991
C104: Goodwill | D104: 3805.9 | E104: 3658.3 | F104: 3409.3 | G104: 3038.3 | H104: 2413.3 | I104: 1572.5
C105: other intangible assets | D105: 835.4 | E105: 809.2 | F105: 763.1 | G105: 694.9 | H105: 476.7 | I105: 211.3
C106: total intangible assets | D106: =D104+D105 -> 4641.3 | E106: =E104+E105 -> 4467.5 | F106: =F104+F105 -> 4172.4 | G106: =G104+G105 -> 3733.2 | H106: =H104+H105 -> 2890 | I106: =I104+I105 -> 1783.8
C107: other long term assets (tangible) | D107: 273 | E107: 261.9 | F107: 279.8 | G107: 225.1 | H107: 180 | I107: 82.8
C108: total tangible assets | D108: =D107+D97 -> 350.8 | E108: =E107+E97 -> 342.7 | F108: =F107+F97 -> 367.7 | G108: =G107+G97 -> 321.6 | H108: =H107+H97 -> 263.6 | I108: =I107+I97 -> 144.5
C109: intangible assets as % of total assets | D109: =D106/(D106+D108) -> 0.92972897 | E109: =E106/(E106+E108) -> 0.92875556 | F109: =F106/(F106+F108) -> 0.91901059 | G109: =G106/(G106+G108) -> 0.92068659 | H109: =H106/(H106+H108) -> 0.91641299 | I109: =I106/(I106+I108) -> 0.92506353
C110: tangible assets as % of total assets | D110: =D108/(D108+D106) -> 0.070271028 | E110: =E108/(E108+E106) -> 0.071244439 | F110: =F108/(F108+F106) -> 0.080989406 | G110: =G108/(G108+G106) -> 0.079313406 | H110: =H108/(H108+H106) -> 0.083587012 | I110: =I108/(I108+I106) -> 0.074936473
C111: weighted dep. & amor. Percentage | D111: =D109*D102+D110*D101 -> 0.31159497 | E111: =E109*E102+E110*E101 -> 0.28268563 | F111: =F109*F102+F110*F101 -> 0.24430105 | G111: =G109*G102+G110*G101 -> 0.1713785 | H111: =H109*H102+H110*H101 -> 0.1087416 | I111: =I109*I102+I110*I101 -> 0.14950693 | J111: =AVERAGE(D111:I111) -> 0.21136811 | K111: =AVERAGE(D111:J111) -> 0.21136811
C113: (excludes operating leases, do net get depreciated by lessee)

Sheet Cifras_Originales
B1: 936 | C1: 942.8 | D1: 988.5 | E1: 1095.3 | F1: 1293.6 | G1: 1515.9 | H1: 1681.3 | I1: 1906.7 | J1: 2065.6 | K1: 2269.9
B2: {=_xlfn.SORTBY(B1:K1, _xlfn.SEQUENCE(1, COLUMNS(B1:K1), COLUMNS(B1:K1), -1))} -> 2269.9 | C2: 2065.6 | D2: 1906.7 | E2: 1681.3 | F2: 1515.9 | G2: 1293.6 | H2: 1095.3 | I2: 988.5 | J2: 942.8 | K2: 936 | L2: 861.3 | M2: 798
A3: USD
A4: Millones | C4: ="Cifras en "&A4&" de "&A3 -> Cifras en Millones de USD
A5: (Company name) | G5: =A5&" ("&A6&")" -> (Company name) ((ticker))
A6: (ticker)
A7: RESULTADOS | B7: 2023 | C7: =B7-1 -> 2022 | D7: =C7-1 -> 2021 | E7: =D7-1 -> 2020 | F7: =E7-1 -> 2019 | G7: =F7-1 -> 2018 | H7: =G7-1 -> 2017 | I7: =H7-1 -> 2016 | J7: =I7-1 -> 2015 | ... M7: =L7-1 -> 2012 | N7: 2024
A8: Ventas Netas | B8: 2269.9 | C8: 2065.6 | D8: 1906.7 | E8: 1681.3 | F8: 1515.9 | G8: 1293.6 | H8: 1095.3 | I8: 988.5 | J8: 942.8 | K8: 936 | L8: 861.3 | M8: 798 | N8: 2544
A9: Utilidad Bruta | B9: 1998.7 | C9: 1814.9 | D9: 1648.7 | E9: 1456 | F9: 1349.6 | G9: 1137.8 | H9: 945.1 | I9: 841.6 | J9: 795.5 | K9: 782.2 | L9: 714.6 | M9: 658.5 | N9: 2264
A10: Utilidad de Operación | B10: 626.1 | C10: 592.7 | D10: 513.3 | E10: 496.4 | F10: 515 | G10: 476.6 | H10: 390.7 | I10: 376.2 | J10: 353.7 | K10: 347.5 | L10: 321.9 | M10: 294.3 | N10: 718
A11: CIF (Poductos) | B11: 43.9 | C11: -5.4 | D11: 5 | E11: 4.2 | F11: 56.2 | G11: -13.3 | H11: 55.1 | I11: 38.8 | J11: -38.3 | K11: -22.6 | L11: -28.2 | M11: -1.9 | N11: -3.29 | S11: =C7 -> 2022 | T11: =D7 -> 2021 | U11: =E7 -> 2020 | V11: =F7 -> 2019 | W11: =G7 -> 2018 | X11: =H7 -> 2017 | Y11: =I7 -> 2016 | Z11: =J7 -> 2015 | ... AB11: =L7 -> 2013
A12: Otros Gastos (Ingresos) | B12: -34 | C12: -17.34 | D12: 2.08 | E12: -2.43 | F12: 7.54 | G12: 10.51 | H12: 4.97 | I12: 4.07 | J12: 3.09 | K12: 0.689 | L12: 0.626 | M12: -0.706 | N12: -3.132 | R12: Inventories | S12: =C26 -> 0 | T12: =D26 -> 0 | U12: =E26 -> 0 | V12: =F26 -> 0 | W12: =G26 -> 0 | X12: =H26 -> 0 | Y12: =I26 -> 0 | Z12: =J26 -> 0 | ... AC12: =M26 -> 0
A13: Depreciación y amortización | B13: 132.5 | C13: 114.56 | D13: 106.87 | E13: 106.25 | F13: 78.97 | G13: 59.26 | H13: 67.68 | I13: 69.59 | J13: 77.67 | K13: 81.92 | L13: 80.7 | M13: 85.42 | N13: 142.672 | R13: Por cobrar | S13: =C25 -> 760.3 | T13: =D25 -> 645.9 | U13: =E25 -> 537.6 | V13: =F25 -> 433.5 | W13: =G25 -> 317.7 | X13: =H25 -> 124.7 | Y13: =I25 -> 107.2 | Z13: =J25 -> 91.6 | ... AC13: =M25 -> 96.6
A14: Capital de Trabajo | B14: 1160.3 | C14: 869.3 | D14: 860.1 | E14: 990.4 | F14: 860.4 | G14: 786.4 | H14: 661.7 | I14: 630.3 | J14: 592.3 | K14: 617.2 | L14: 627.2 | M14: 436 | N14: 189 | R14: Por pagar
A15: Capex | B15: -25.3 | C15: -24.37 | D15: =-23.02 -> -23.02 | E15: -35.37 | F15: -44.94 | G15: -21.76 | H15: -19.15 | I15: -12.44 | J15: -16.14 | K15: -26.02 | L15: -28.85 | N15: -44
A16: Inversiones | B16: 0 | C16: 0 | D16: 0 | E16: 0 | F16: 0 | G16: 0 | H16: 0 | J16: 0 | K16: -0.335 | L16: -0.261 | M16: -0.288 | N16: 0 | S16: =(S12-T12) -> 0 | T16: =(T12-U12) -> 0 | U16: =(U12-V12) -> 0 | V16: =(V12-W12) -> 0 | W16: =(W12-X12) -> 0 | X16: =(X12-Y12) -> 0 | Y16: =(Y12-Z12) -> 0 | Z16: =(Z12-AA12) -> 0 | ... AB16: =(AB12-AC12) -> 0
A17: I.S.R Y P.T.U. | B17: 115.8 | C17: 91.7 | D17: 51.6 | E17: 60.7 | G17: 60 | H17: 71.3 | I17: 67.7 | J17: 136.4 | K17: 114.7 | L17: 104.2 | M17: 93.4 | S17: =(S13-T13) -> 114.4 | T17: =(T13-U13) -> 108.3 | U17: =(U13-V13) -> 104.1 | V17: =(V13-W13) -> 115.8 | W17: =(W13-X13) -> 193 | X17: =(X13-Y13) -> 17.5 | Y17: =(Y13-Z13) -> 15.6 | Z17: =(Z13-AA13) -> -9.6 | ... AB17: =(AB13-AC13) -> 1.2
A18: Utilidad Neta | B18: 500.4 | C18: 523.7 | D18: 454.6 | E18: 433.9 | F18: 451.3 | G18: 419.4 | H18: 259.3 | I18: 265.6 | J18: 252.5 | K18: 254.7 | L18: 245.3 | M18: 203.5 | N18: 575.692 | S18: =(S14-T14) -> 0 | T18: =(T14-U14) -> 0 | U18: =(U14-V14) -> 0 | V18: =(V14-W14) -> 0 | W18: =(W14-X14) -> 0 | X18: =(X14-Y14) -> 0 | Y18: =(Y14-Z14) -> 0 | Z18: =(Z14-AA14) -> 0 | ... AB18: =(AB14-AC14) -> 0
A19: Dividendos | B19: 0 | C19: 0 | D19: 0 | E19: 0 | F19: 0 | G19: 0 | H19: 0 | I19: 0 | J19: 0 | K19: 0 | L19: 0 | M19: 0 | N19: 0 | R19: Capital de trabajo | S19: =SUM(S16:S18) -> 114.4 | T19: =SUM(T16:T18) -> 108.3 | U19: =SUM(U16:U18) -> 104.1 | V19: =SUM(V16:V18) -> 115.8 | W19: =SUM(W16:W18) -> 193 | X19: =SUM(X16:X18) -> 17.5 | Y19: =SUM(Y16:Y18) -> 15.6 | Z19: =SUM(Z16:Z18) -> -9.6 | ... AB19: =SUM(AB16:AB18) -> 1.2
A20: Compra de Acciones | B20: -47.2 | C20: -69.2 | D20: -175.9 | E20: -294.3 | F20: -282.5 | G20: -294.7 | H20: -257.7 | I20: -67.5 | J20: -202.5 | K20: -200.3 | L20: -244.2 | M20: -230 | N20: 0
B21: =B10-B11-B12-B17 -> 500.4 | C21: =C10-C11-C12-C17 -> 523.74 | D21: =D10-D11-D12-D17 -> 454.62 | E21: =E10-E11-E12-E17 -> 433.93 | F21: =F10-F11-F12-F17 -> 451.26 | G21: =G10-G11-G12-G17 -> 419.39 | H21: =H10-H11-H12-H17 -> 259.33 | I21: =I10-I11-I12-I17 -> 265.63 | ... N21: =N10-N11-N12-N17 -> 724.422
A22: POSICIÓN FINANCIERA | B22: =B18-B21 -> 0 | C22: =C18-C21 -> -0.04 | D22: =D18-D21 -> -0.02 | E22: =E18-E21 -> -0.03 | F22: =F18-F21 -> 0.04 | G22: =G18-G21 -> 0.01 | H22: =H18-H21 -> -0.03 | I22: =I18-I21 -> -0.03 | ... N22: =N18-N21 -> -148.73
A23: Activo
A24: Caja | B24: 860.2 | C24: 614.4 | D24: 667.7 | E24: 912.7 | F24: 872.1 | G24: 777.1 | H24: 881.5 | I24: 822.5 | J24: 784.6 | K24: 788.1 | L24: 742.5 | M24: 576.7
A25: Cuentas y documentos por cobrar | B25: 864.5 | C25: 760.3 | D25: 645.9 | E25: 537.6 | F25: 433.5 | G25: 317.7 | H25: 124.7 | I25: 107.2 | J25: 91.6 | K25: 101.2 | L25: 97.8 | M25: 96.6 | P25: =B14-C14 -> 291 | Q25: =C14-D14 -> 9.2 | R25: =D14-E14 -> -130.3 | S25: =E14-F14 -> 130
A26: Inventarios | B26: 0 | C26: 0 | D26: 0 | E26: 0 | F26: 0 | G26: 0 | H26: 0 | I26: 0 | J26: 0 | K26: 0 | L26: 0 | M26: 0
A27: Activos Fijos (Net Plant) | B27: 194.8 | C27: 210 | D27: 208.8 | E27: 234.2 | F27: 189.3 | G27: 61.7 | H27: 57.1 | I27: 54.7 | J27: 61.9 | K27: 64.2 | L27: 60.5 | M27: 52.3
A28: Otros Activos | B28: =B29-SUM(B24:B27) -> 5403.4 | C28: =C29-SUM(C24:C27) -> 5103.2 | D28: =D29-SUM(D24:D27) -> 4801.9 | E28: =E29-SUM(E24:E27) -> 4256.1 | F28: =F29-SUM(F24:F27) -> 3344 | G28: =G29-SUM(G24:G27) -> 2109.5 | H28: =H29-SUM(H24:H27) -> 1878.3 | I28: =I29-SUM(I24:I27) -> 1816.1 | ... M28: =M29-SUM(M24:M27) -> 1881.8
A29: Total Activo | B29: 7322.9 | C29: 6687.9 | D29: 6324.3 | E29: 5940.6 | F29: 4838.9 | G29: 3266 | H29: 2941.6 | I29: 2800.5 | J29: 2729.9 | K29: 2752.9 | L29: 2722.4 | M29: 2607.4 | Q29: SORTBY(Q33:S33; SEQUENCE(1; COLUMNS(Q33:S33); COLUMNS(Q33:S33); -1))
A32: Pasivo
A33: Pasivo Corto Plazo | B33: 477.4 | C33: 440.4 | D33: 465.1 | E33: 484.1 | F33: 539.1 | G33: 608.6 | H33: 524.8 | I33: 695.1 | J33: 728.8 | K33: 778.5 | L33: 794.8 | M33: 889.3
A34: Deuda a corto plazo | B34: 53.1 | C34: 0 | D34: 0 | E34: 0 | F34: 0 | G34: 0 | H34: 0 | I34: 93.2 | J34: 23.6 | K34: 22.8 | L34: 22.8 | M34: 23.3
A35: Short-Term Leases | B35: 0 | C35: 0 | D35: 0 | E35: 0 | F35: 0 | G35: 0 | H35: 0 | I35: 18.2 | J35: 23.6 | K35: 22.8 | L35: 22.8 | M35: 23.3
A36: Otros Pasivos a Corto Plazo | B36: =B33-B34-B35 -> 424.3 | C36: =C33-C34-C35 -> 440.4 | D36: =D33-D34-D35 -> 465.1 | E36: =E33-E34-E35 -> 484.1 | F36: =F33-F34-F35 -> 539.1 | G36: =G33-G34-G35 -> 608.6 | H36: =H33-H34-H35 -> 524.8 | I36: =I33-I34-I35 -> 583.7 | ... M36: =M33-M34-M35 -> 842.7
A37: Pasivo Largo Plazo | B37: 255.2 | C37: 189.7 | D37: 145.7 | E37: 70.3 | F37: 51.3 | G37: 53 | H37: 87.2 | I37: 91.7 | J37: 690.4 | K37: 1113.9 | L37: 1061.8 | M37: 1027.3
A38: Deuda a largo plazo | B38: 0 | C38: 0 | D38: 0 | E38: 0 | F38: 0 | G38: 0 | H38: 0 | I38: 515.3 | J38: 919.1 | K38: 858 | L38: 866.4 | M38: 854.4
A39: Long-Term Leases | B39: 0 | C39: 0 | D39: 0 | E39: 0 | F39: 0 | G39: 0 | H39: 0 | I39: 91.8 | J39: 120.9 | K39: 104.4 | L39: 112.8 | M39: 100.5
A40: Otros Pasivos a Largo Plazo | B40: =B37-B38-B39 -> 255.2 | C40: =C37-C38-C39 -> 189.7 | D40: =D37-D38-D39 -> 145.7 | E40: =E37-E38-E39 -> 70.3 | F40: =F37-F38-F39 -> 51.3 | G40: =G37-G38-G39 -> 53 | H40: =H37-H38-H39 -> 87.2 | I40: =I37-I38-I39 -> -515.4 | ... M40: =M37-M38-M39 -> 72.4
A41: Total pasivos | B41: =B33+B37 -> 732.6 | C41: =C33+C37 -> 630.1 | D41: =+D37+D33 -> 610.8 | E41: =+E37+E33 -> 554.4 | F41: =+F37+F33 -> 590.4 | G41: =+G37+G33 -> 661.6 | H41: =+H37+H33 -> 612 | I41: =I33+I37 -> 786.8 | J41: =J37+J33 -> 1419.2 | K41: =K37+K33 -> 1892.4 | L41: =L37+L33 -> 1856.6 | M41: =M37+M33 -> 1916.6
A44: Interés Minoritario | B44: 0 | C44: 0 | D44: 0 | E44: 0 | F44: 0 | G44: 0 | H44: 0 | I44: 0 | J44: 0 | K44: 0 | L44: 0 | M44: 0
A46: Capital Contable | B46: =B29-B41-B44 -> 6590.3 | C46: =C29-C41-C44 -> 6057.8 | D46: =D29-D41-D44 -> 5713.5 | E46: =E29-E41-E44 -> 5386.2 | F46: =F29-F41-F44 -> 4248.5 | G46: =G29-G41-G44 -> 2604.4 | H46: =H29-H41-H44 -> 2329.6 | I46: =I29-I41-I44 -> 2013.7 | ... L46: =L29-L41-L44 -> 865.8 | M46: 47791
A48: OTROS DATOS AL FIN DE AÑO
A49: Numero de Empleados | B49: 6200 | C49: 5600 | D49: 5100 | E49: 4800 | F49: 2100 | G49: 1700 | H49: 2900 | I49: 2800 | J49: 2800 | K49: 2700 | L49: 2600 | M49: 2400
A50: Acciones en circulación (millones) | B50: 92.7 | C50: 92.3 | D50: 90.8 | E50: 88.1 | F50: 85.7 | G50: 84.2 | H50: 83.6 | I50: 85.7 | J50: 86.6 | K50: 87.1 | L50: 86.9 | M50: 86.9
A51: Float
A52: Insiders Own | B52: 0.0239 | C52: 0.0231 | D52: 0.022 | E52: 0.0229 | F52: 0.022 | G52: 0.0219 | H52: 0.021 | I52: 0.0206 | J52: 0.019 | K52: 0.0155 | L52: 0.0154 | M52: 0.0146
A53: S&P
A54: ="Vol. Diario en Millones "&A3 -> Vol. Diario en Millones USD
B55: 2021 | C55: =B55+1 -> 2022 | D55: =C55+1 -> 2023
A56: Posicion en Corto (%)
A57: EPS | B57: 5.22 | C57: 6.01 | D57: 5.56
A59: BONOS DE LA EMISORA A 3, 5 Y 10 | B59: Precio Medio | C59: S&P | D59: YTM (%) | E59: DIVISA

Sheet Q
B2: 3Q17 | C2: 3Q18 | D2: 4Q18 | E2: 1Q19 | F2: 2Q19 | G2: 3Q19 | H2: 4Q19 | I2: 1Q20 | J2: 2Q20 | K2: 3Q20 | L2: 4Q20 | M2: 1Q21 | N2: 2Q21 | O2: 3Q21 | P2: 4Q21 | Q2: 1Q22 | R2: 2Q22 | S2: 3Q22 | T2: 4Q22 | U2: 1Q23 | V2: 2Q23 | W2: 3Q23 | X2: 4Q23e | Z2: 2019 | AA2: 2020 | AB2: 2021 | AC2: 2022 | AD2: 2023 | AE2: 2024 | AF2: 2025 | AG2: 2026 | AH2: 2027 | AI2: 2028 | AJ2: 2029 | AK2: 2030 | AL2: 2031 | AM2: 2032 | AN2: 2033 | AO2: 2034 | AP2: 2035 | AQ2: 2036 | AR2: 2037 | AS2: 2038 | AT2: 2039 | AU2: 2040 | AV2: 2041 | AW2: 2042 | AX2: 2043 | AY2: 2044 | AZ2: 2045 | BA2: 2046 | BB2: 2047
A3: Shares
A4: Growth
A5: Prods | AE5: 0.045 | AF5: =0.987*AE5 -> 0.044415 | AG5: =0.987*AF5 -> 0.043837605 | AH5: =0.987*AG5 -> 0.043267716 | AI5: =0.987*AH5 -> 0.042705236 | AJ5: =0.987*AI5 -> 0.042150068 | AK5: =0.987*AJ5 -> 0.041602117 | AL5: =0.987*AK5 -> 0.041061289 | AM5: =0.987*AL5 -> 0.040527493 | ... BB5: =0.987*BA5 -> 0.033304815
A6: Serv | AE6: 0.09 | AF6: =AE6*0.975 -> 0.08775 | AG6: =AF6*0.975 -> 0.08555625 | AH6: =AG6*0.975 -> 0.083417344 | AI6: =AH6*0.975 -> 0.08133191 | AJ6: =AI6*0.975 -> 0.079298612 | AK6: =AJ6*0.975 -> 0.077316147 | AL6: =AK6*0.975 -> 0.075383243 | AM6: =AL6*0.975 -> 0.073498662 | ... BB6: =BA6*0.975 -> 0.050274605
A8: COGS
A9: Prods | Z9: =Z30/Z26 -> 0.67792204 | AA9: =AA30/AA26 -> 0.68533661 | AB9: =AB30/AB26 -> 0.64650697 | AC9: =AC30/AC26 -> 0.6371652 | AD9: =AD30/AD26 -> 0.6358648 | AE9: =AD9*1.001 -> 0.63650067 | AF9: =AE9*1.001 -> 0.63713717 | AG9: =AF9*1.001 -> 0.6377743 | AH9: =AG9*1.001 -> 0.63841208 | AI9: =AH9*1.001 -> 0.63905049 | AJ9: =AI9*1.001 -> 0.63968954 | AK9: =AJ9*1.001 -> 0.64032923 | AL9: =AK9*1.001 -> 0.64096956 | ... BB9: =BA9*1.001 -> 0.65130235
A10: Serv | Z10: =Z31/Z27 -> 0.36261908 | AA10: =AA31/AA27 -> 0.33984898 | AB10: =AB31/AB27 -> 0.30274023 | AC10: =AC31/AC27 -> 0.28254553 | AD10: =AD31/AD27 -> 0.29105249 | AE10: =AD10*1.001 -> 0.29134354 | AF10: =AE10*1.001 -> 0.29163488 | AG10: =AF10*1.001 -> 0.29192652 | AH10: =AG10*1.001 -> 0.29221845 | AI10: =AH10*1.001 -> 0.29251066 | AJ10: =AI10*1.001 -> 0.29280317 | AK10: =AJ10*1.001 -> 0.29309598 | AL10: =AK10*1.001 -> 0.29338907 | ... BB10: =BA10*1.001 -> 0.29811867
A12: R&D | Z12: =Z33/Z25 -> 0.062331363 | AA12: =AA33/AA25 -> 0.068309564 | AB12: =AB33/AB25 -> 0.059904269 | AC12: =AC33/AC25 -> 0.066571484 | AD12: =AD33/AD25 -> 0.078317483 | AE12: =1.01*AD12 -> 0.079100658 | AF12: =1.01*AE12 -> 0.079891665 | AG12: =1.01*AF12 -> 0.080690581 | AH12: =1.01*AG12 -> 0.081497487 | AI12: =1.01*AH12 -> 0.082312462 | AJ12: =1.01*AI12 -> 0.083135587 | AK12: =1.01*AJ12 -> 0.083966943 | AL12: =1.01*AK12 -> 0.084806612 | ... BB12: =1.01*BA12 -> 0.099442422
A13: SGA | Z13: =Z34/Z25 -> 0.070126146 | AA13: =AA34/AA25 -> 0.07254977 | AB13: =AB34/AB25 -> 0.060065552 | AC13: =AC34/AC25 -> 0.063637378 | AD13: =AD34/AD25 -> 0.065265004 | AE13: =AD13*1.001 -> 0.065330269 | AF13: =AE13*1.001 -> 0.0653956 | AG13: =AF13*1.001 -> 0.065460995 | AH13: =AG13*1.001 -> 0.065526456 | AI13: =AH13*1.001 -> 0.065591983 | AJ13: =AI13*1.001 -> 0.065657575 | AK13: =AJ13*1.001 -> 0.065723232 | AL13: =AK13*1.001 -> 0.065788956 | ... BB13: =BA13*1.001 -> 0.066849511
A15: Utiilidad oP
A17: Tax Rate | Z17: =Z41/Z40 -> 0.15943837 | AA17: =AA41/AA40 -> 0.14428165 | AB17: =AB41/AB40 -> 0.13302261 | AC17: =AC41/AC40 -> 0.16204462
A19: DA | Z19: =Z52/Z25 -> 0.048225418 | AA19: =AA52/AA25 -> 0.040274666 | AB19: =AB52/AB25 -> 0.030846024 | AC19: =AC52/AC25 -> 0.028159299
A20: SBC | Z20: =Z53/Z25 -> 0.023322853 | AA20: =AA53/AA25 -> 0.024876601 | AB20: =AB53/AB25 -> 0.021611899 | AC20: =AC53/AC25 -> 0.022920006
A21: Net SBC | U21: =((W25+V25)/(R25+S25))-1 -> -0.019995894 | Z21: =(Z53+Z54)/Z25 -> 0.031148385 | AA21: =(AA53+AA54)/AA25 -> 0.034908839 | AB21: =(AB53+AB54)/AB25 -> 0.039533428 | AC21: =(AC53+AC54)/AC25 -> 0.038701284
A22: Capex | U22: =((W25+V25)/(F25+G25))-1 -> 0.57956253 | Z22: =Z55/Z25 -> 0.040338389 | AA22: =AA55/AA25 -> 0.026625139 | AB22: =AB55/AB25 -> 0.030302036 | AC22: =AC55/AC25 -> 0.027155059
A23: Net SBC Factor | Z23: =Z21/Z20 -> 1.3355307 | AA23: =AA21/AA20 -> 1.4032801 | AB23: =AB21/AB20 -> 1.8292436 | AC23: =AC21/AC20 -> 1.6885373
A25: Revenue | C25: =C26+C27 -> 53265 | D25: =D26+D27 -> 64040 | E25: =E26+E27 -> 84310 | F25: =F26+F27 -> 58015 | G25: =G26+G27 -> 53809 | H25: =H26+H27 -> 64040 | I25: =I26+I27 -> 91819 | J25: =J26+J27 -> 58313 | ... X25: =X26+X27 -> 89282 | Z25: =Z26+Z27 -> 260174 | AA25: =AA26+AA27 -> 274515 | AB25: =AB26+AB27 -> 365817 | AC25: =AC26+AC27 -> 394328 | AD25: =AD26+AD27 -> 383069 | AE25: =AE26+AE27 -> 404095.7 | AF25: =AF26+AF27 -> 426020.39 | AG25: =AG26+AG27 -> 448860.49 | ... BB25: =BB26+BB27 -> 1156800
A26: -Products | C26: 43095 | D26: 51529 | E26: 73435 | F26: 46565 | G26: 42354 | H26: 51529 | I26: 79104 | J26: 44965 | K26: 46529 | L26: 50149 | M26: 95678 | N26: 72683 | O26: 63948 | P26: 65083 | Q26: 104429 | R26: 77457 | S26: 63355 | T26: 70958 | U26: 96388 | V26: 73929 | W26: 60584 | X26: 67977 | Z26: =SUM(E26:H26) -> 213883 | AA26: =SUM(I26:L26) -> 220747 | AB26: =SUM(M26:P26) -> 297392 | AC26: =SUM(Q26:T26) -> 316199 | AD26: =SUM(U26:X26) -> 298878 | AE26: =(1+AE5)*AD26 -> 312327.51 | AF26: =(1+AF5)*AE26 -> 326199.54 | AG26: =(1+AG5)*AF26 -> 340499.34 | AH26: =(1+AH5)*AG26 -> 355231.97 | AI26: =(1+AI5)*AH26 -> 370402.24 | AJ26: =(1+AJ5)*AI26 -> 386014.72 | AK26: =(1+AK5)*AJ26 -> 402073.75 | AL26: =(1+AL5)*AK26 -> 418583.41 | ... BB26: =(1+BB5)*BA26 -> 746321.37
A27: -Services | C27: 10170 | D27: 12511 | E27: 10875 | F27: 11450 | G27: 11455 | H27: 12511 | I27: 12715 | J27: 13348 | K27: 13156 | L27: 14549 | M27: 15761 | N27: 16901 | O27: 17486 | P27: 18277 | Q27: 19516 | R27: 19821 | S27: 19604 | T27: 19188 | U27: 20766 | V27: 20907 | W27: 21213 | X27: 21305 | Z27: =SUM(E27:H27) -> 46291 | AA27: =SUM(I27:L27) -> 53768 | AB27: =SUM(M27:P27) -> 68425 | AC27: =SUM(Q27:T27) -> 78129 | AD27: =SUM(U27:X27) -> 84191 | AE27: =(1+AE6)*AD27 -> 91768.19 | AF27: =(1+AF6)*AE27 -> 99820.849 | AG27: =(1+AG6)*AF27 -> 108361.15 | AH27: =(1+AH6)*AG27 -> 117400.35 | AI27: =(1+AI6)*AH27 -> 126948.74 | AJ27: =(1+AJ6)*AI27 -> 137015.6 | AK27: =(1+AK6)*AJ27 -> 147609.12 | AL27: =(1+AL6)*AK27 -> 158736.37 | ... BB27: =(1+BB6)*BA27 -> 410478.6
A29: COGS
A30: -Products | C30: 28956 | D30: 35238 | E30: 48238 | F30: 32047 | G30: 29473 | H30: 35238 | I30: 52075 | J30: 31321 | K30: 32693 | L30: 35197 | M30: 62130 | N30: 46447 | O30: 40899 | P30: 42790 | Q30: 64309 | R30: 49290 | S30: 41485 | T30: 46387 | U30: 60765 | V30: 46795 | W30: 39136 | X30: 43350 | Z30: =SUM(E30:H30) -> 144996 | AA30: =SUM(I30:L30) -> 151286 | AB30: =SUM(M30:P30) -> 192266 | AC30: =SUM(Q30:T30) -> 201471 | AD30: =SUM(U30:X30) -> 190046 | AE30: =AE9*AE26 -> 198796.67 | AF30: =AF9*AF26 -> 207833.85 | AG30: =AG9*AG26 -> 217161.73 | AH30: =AH9*AH26 -> 226784.38 | AI30: =AI9*AI26 -> 236705.73 | AJ30: =AJ9*AJ26 -> 246929.58 | AK30: =AK9*AK26 -> 257459.57 | AL30: =AL9*AL26 -> 268299.23 | ... BB30: =BB9*BB26 -> 486080.86
A31: -Services | C31: 3888 | D31: 4489 | E31: 4041 | F31: 4147 | G31: 4109 | H31: 4489 | I31: 4527 | J31: 4622 | K31: 4312 | L31: 4812 | M31: 4981 | N31: 5058 | O31: 5280 | P31: 5396 | Q31: 5393 | R31: 5429 | S31: 5589 | T31: 5664 | U31: 6057 | V31: 6065 | W31: 6248 | X31: 6134 | Z31: =SUM(E31:H31) -> 16786 | AA31: =SUM(I31:L31) -> 18273 | AB31: =SUM(M31:P31) -> 20715 | AC31: =SUM(Q31:T31) -> 22075 | AD31: =SUM(U31:X31) -> 24504 | AE31: =AE10*AE27 -> 26736.069 | AF31: =AF10*AF27 -> 29111.242 | AG31: =AG10*AG27 -> 31633.492 | AH31: =AH10*AH27 -> 34306.546 | AI31: =AI10*AI27 -> 37133.86 | AJ31: =AJ10*AJ27 -> 40118.602 | AK31: =AK10*AK27 -> 43263.638 | AL31: =AL10*AL27 -> 46571.517 | ... BB31: =BB10*BB27 -> 122371.34
A33: R&D | C33: 3701 | D33: 4110 | E33: 3902 | F33: 3948 | G33: 4257 | H33: 4110 | I33: 4451 | J33: 4565 | K33: 4758 | L33: 4978 | M33: 5163 | N33: 5262 | O33: 5717 | P33: 5772 | Q33: 6306 | R33: 6387 | S33: 6797 | T33: 6761 | U33: 7709 | V33: 7457 | W33: 7442 | X33: 7393 | Z33: =SUM(E33:H33) -> 16217 | AA33: =SUM(I33:L33) -> 18752 | AB33: =SUM(M33:P33) -> 21914 | AC33: =SUM(Q33:T33) -> 26251 | AD33: =SUM(U33:X33) -> 30001 | AE33: =AE12*AE$25 -> 31964.236 | AF33: =AF12*AF$25 -> 34035.478 | AG33: =AG12*AG$25 -> 36218.814 | AH33: =AH12*AH$25 -> 38518.346 | AI33: =AI12*AI$25 -> 40938.183 | AJ33: =AJ12*AJ$25 -> 43482.432 | AK33: =AK12*AK$25 -> 46155.189 | AL33: =AL12*AL$25 -> 48960.535 | ... BB33: =BB12*BB$25 -> 115034.99
A34: SGA | C34: 4108 | D34: 4578 | E34: 4783 | F34: 4458 | G34: 4426 | H34: 4578 | I34: 5197 | J34: 4952 | K34: 4831 | L34: 4936 | M34: 5631 | N34: 5314 | O34: 5412 | P34: 5616 | Q34: 6449 | R34: 6193 | S34: 6012 | T34: 6440 | U34: 6607 | V34: 6201 | W34: 5973 | X34: 6220 | Z34: =SUM(E34:H34) -> 18245 | AA34: =SUM(I34:L34) -> 19916 | AB34: =SUM(M34:P34) -> 21973 | AC34: =SUM(Q34:T34) -> 25094 | AD34: =SUM(U34:X34) -> 25001 | AE34: =AE13*AE$25 -> 26399.681 | AF34: =AF13*AF$25 -> 27859.859 | AG34: =AG13*AG$25 -> 29382.854 | AH34: =AH13*AH$25 -> 30969.921 | AI34: =AI13*AI$25 -> 32622.237 | AJ34: =AJ13*AJ$25 -> 34340.902 | AK34: =AK13*AK$25 -> 36126.934 | AL34: =AL13*AL$25 -> 37981.266 | ... BB34: =BB13*BB$25 -> 77331.512
A36: Ut OP | C36: =C25-C30-C31-C33-C34 -> 12612 | D36: =D25-D30-D31-D33-D34 -> 15625 | E36: =E25-E30-E31-E33-E34 -> 23346 | F36: =F25-F30-F31-F33-F34 -> 13415 | G36: =G25-G30-G31-G33-G34 -> 11544 | H36: =H25-H30-H31-H33-H34 -> 15625 | I36: =I25-I30-I31-I33-I34 -> 25569 | J36: =J25-J30-J31-J33-J34 -> 12853 | ... X36: =X25-X30-X31-X33-X34 -> 26185 | Z36: =Z25-Z30-Z31-Z33-Z34 -> 63930 | AA36: =AA25-AA30-AA31-AA33-AA34 -> 66288 | AB36: =AB25-AB30-AB31-AB33-AB34 -> 108949 | AC36: =AC25-AC30-AC31-AC33-AC34 -> 119437 | AD36: =AD25-AD30-AD31-AD33-AD34 -> 113517 | AE36: =AE25-AE30-AE31-AE33-AE34 -> 120199.05 | AF36: =AF25-AF30-AF31-AF33-AF34 -> 127179.96 | AG36: =AG25-AG30-AG31-AG33-AG34 -> 134463.6 | ... BB36: =BB25-BB30-BB31-BB33-BB34 -> 355981.27
A38: Other | C38: 672 | D38: 502 | E38: 560 | F38: 378 | G38: 367 | H38: 502 | I38: 349 | J38: 282 | K38: 46 | L38: 126 | M38: 45 | N38: 508 | O38: 243 | P38: -538 | Q38: -247 | R38: 160 | S38: -10 | T38: -237 | U38: -393 | V38: 64 | W38: -265 | Z38: =SUM(E38:H38) -> 1807 | AA38: =SUM(I38:L38) -> 803 | AB38: =SUM(M38:P38) -> 258 | AC38: =SUM(Q38:T38) -> -334
A40: efore tax | C40: =C26+C27-C30-C31-C33-C34+C38 -> 13284 | D40: =D26+D27-D30-D31-D33-D34+D38 -> 16127 | E40: =E26+E27-E30-E31-E33-E34+E38 -> 23906 | F40: =F26+F27-F30-F31-F33-F34+F38 -> 13793 | G40: =G26+G27-G30-G31-G33-G34+G38 -> 11911 | H40: =H26+H27-H30-H31-H33-H34+H38 -> 16127 | I40: =I26+I27-I30-I31-I33-I34+I38 -> 25918 | J40: =J26+J27-J30-J31-J33-J34+J38 -> 13135 | ... W40: =W26+W27-W30-W31-W33-W34+W38 -> 22733 | Z40: =SUM(E40:H40) -> 65737 | AA40: =SUM(I40:L40) -> 67091 | AB40: =SUM(M40:P40) -> 109207 | AC40: =SUM(Q40:T40) -> 119103
A41: Tax | C41: 1765 | D41: 2441 | E41: 3941 | F41: 2232 | G41: 1867 | H41: 2441 | I41: 3682 | J41: 1886 | K41: 1884 | L41: 2228 | M41: 4824 | N41: 4381 | O41: 2625 | P41: 2697 | Q41: 6611 | R41: 5129 | S41: 3624 | T41: 3936 | U41: 5625 | V41: 4222 | W41: 2852 | Z41: =SUM(E41:H41) -> 10481 | AA41: =SUM(I41:L41) -> 9680 | AB41: =SUM(M41:P41) -> 14527 | AC41: =SUM(Q41:T41) -> 19300
A42: NI | C42: =C40-C41 -> 11519 | D42: =D40-D41 -> 13686 | E42: =E40-E41 -> 19965 | F42: =F40-F41 -> 11561 | G42: =G40-G41 -> 10044 | H42: =H40-H41 -> 13686 | I42: =I40-I41 -> 22236 | J42: =J40-J41 -> 11249 | ... W42: =W40-W41 -> 19881
A45: DA | E45: 3395 | F45: 6435 | G45: 9368 | H45: 12547 | I45: 2816 | J45: 5602 | K45: 8354 | L45: 11056 | M45: 2666 | N45: 5463 | O45: 8295 | P45: 11284 | Q45: 2697 | R45: 5434 | S45: 8239 | T45: 11104 | U45: 2916 | V45: 5814 | W45: 8866
A46: SBC | E46: 1559 | F46: 3073 | G46: 4569 | H46: 6068 | I46: 1710 | J46: 3407 | K46: 5105 | L46: 6829 | M46: 2020 | N46: 4001 | O46: 5961 | P46: 7906 | Q46: 2265 | R46: 4517 | S46: 6760 | T46: 9038 | U46: 2905 | V46: 5591 | W46: 8208
A47: Other SBC | E47: 1318 | F47: 1037 | G47: 2325 | H47: 2036 | I47: 1377 | J47: 1136 | K47: 2804 | L47: 2754 | M47: 2861 | N47: 3160 | O47: 5855 | P47: 6556 | Q47: 2888 | R47: 3218 | S47: 5915 | T47: 6223 | U47: 2316 | V47: 2734 | W47: 5119
A48: Capex | E48: 3355 | F48: 5718 | G48: 7718 | H48: 10495 | I48: 2107 | J48: 3960 | K48: 5525 | L48: 7309 | M48: 3500 | N48: 5769 | O48: 7862 | P48: 11085 | Q48: 2803 | R48: 5317 | S48: 7419 | T48: 10708 | U48: 3787 | V48: 6703 | W48: 8796
A49: Divs | E49: 3568 | F49: 7011 | G49: 10640 | H49: 14119 | I49: 3539 | J49: 6914 | K49: 10570 | L49: 14081 | M49: 3613 | N49: 7060 | O49: 10827 | P49: 14467 | Q49: 3732 | R49: 7327 | S49: 11138 | T49: 14841 | U49: 3768 | V49: 7418 | W49: 11267
A50: Repurch | E50: 8796 | F50: 32498 | G50: 49463 | H50: 66897 | I50: 20706 | J50: 39280 | K50: 55171 | L50: 72358 | M50: 24775 | N50: 43323 | O50: 66223 | P50: 85971 | Q50: 20478 | R50: 43109 | S50: 64974 | T50: 89402 | U50: 19475 | V50: 39069 | W50: 56547
A52: DA | E52: =E45 -> 3395 | F52: =F45-E45 -> 3040 | G52: =G45-F45 -> 2933 | H52: =H45-G45 -> 3179 | I52: =I45 -> 2816 | J52: =J45-I45 -> 2786 | K52: =K45-J45 -> 2752 | L52: =L45-K45 -> 2702 | M52: =M45 -> 2666 | N52: =N45-M45 -> 2797 | O52: =O45-N45 -> 2832 | P52: =P45-O45 -> 2989 | Q52: =Q45 -> 2697 | R52: =R45-Q45 -> 2737 | S52: =S45-R45 -> 2805 | T52: =T45-S45 -> 2865 | U52: =U45 -> 2916 | V52: =V45-U45 -> 2898 | W52: =W45-V45 -> 3052 | X52: 3262 | Z52: =SUM(E52:H52) -> 12547 | AA52: =SUM(I52:L52) -> 11056 | AB52: =SUM(M52:P52) -> 11284 | AC52: =SUM(Q52:T52) -> 11104
A53: SBC | E53: =E46 -> 1559 | F53: =F46-E46 -> 1514 | G53: =G46-F46 -> 1496 | H53: =H46-G46 -> 1499 | I53: =I46 -> 1710 | J53: =J46-I46 -> 1697 | K53: =K46-J46 -> 1698 | L53: =L46-K46 -> 1724 | M53: =M46 -> 2020 | N53: =N46-M46 -> 1981 | O53: =O46-N46 -> 1960 | P53: =P46-O46 -> 1945 | Q53: =Q46 -> 2265 | R53: =R46-Q46 -> 2252 | S53: =S46-R46 -> 2243 | T53: =T46-S46 -> 2278 | U53: =U46 -> 2905 | V53: =V46-U46 -> 2686 | W53: =W46-V46 -> 2617 | Z53: =SUM(E53:H53) -> 6068 | AA53: =SUM(I53:L53) -> 6829 | AB53: =SUM(M53:P53) -> 7906 | AC53: =SUM(Q53:T53) -> 9038
A54: Other SBC | E54: =E47 -> 1318 | F54: =F47-E47 -> -281 | G54: =G47-F47 -> 1288 | H54: =H47-G47 -> -289 | I54: =I47 -> 1377 | J54: =J47-I47 -> -241 | K54: =K47-J47 -> 1668 | L54: =L47-K47 -> -50 | M54: =M47 -> 2861 | N54: =N47-M47 -> 299 | O54: =O47-N47 -> 2695 | P54: =P47-O47 -> 701 | Q54: =Q47 -> 2888 | R54: =R47-Q47 -> 330 | S54: =S47-R47 -> 2697 | T54: =T47-S47 -> 308 | U54: =U47 -> 2316 | V54: =V47-U47 -> 418 | W54: =W47-V47 -> 2385 | Z54: =SUM(E54:H54) -> 2036 | AA54: =SUM(I54:L54) -> 2754 | AB54: =SUM(M54:P54) -> 6556 | AC54: =SUM(Q54:T54) -> 6223
A55: Capex | E55: =E48 -> 3355 | F55: =F48-E48 -> 2363 | G55: =G48-F48 -> 2000 | H55: =H48-G48 -> 2777 | I55: =I48 -> 2107 | J55: =J48-I48 -> 1853 | K55: =K48-J48 -> 1565 | L55: =L48-K48 -> 1784 | M55: =M48 -> 3500 | N55: =N48-M48 -> 2269 | O55: =O48-N48 -> 2093 | P55: =P48-O48 -> 3223 | Q55: =Q48 -> 2803 | R55: =R48-Q48 -> 2514 | S55: =S48-R48 -> 2102 | T55: =T48-S48 -> 3289 | U55: =U48 -> 3787 | V55: =V48-U48 -> 2916 | W55: =W48-V48 -> 2093 | Z55: =SUM(E55:H55) -> 10495 | AA55: =SUM(I55:L55) -> 7309 | AB55: =SUM(M55:P55) -> 11085 | AC55: =SUM(Q55:T55) -> 10708
A56: Divs | E56: =E49 -> 3568 | F56: =F49-E49 -> 3443 | G56: =G49-F49 -> 3629 | H56: =H49-G49 -> 3479 | I56: =I49 -> 3539 | J56: =J49-I49 -> 3375 | K56: =K49-J49 -> 3656 | L56: =L49-K49 -> 3511 | M56: =M49 -> 3613 | N56: =N49-M49 -> 3447 | O56: =O49-N49 -> 3767 | P56: =P49-O49 -> 3640 | Q56: =Q49 -> 3732 | R56: =R49-Q49 -> 3595 | S56: =S49-R49 -> 3811 | T56: =T49-S49 -> 3703 | U56: =U49 -> 3768 | V56: =V49-U49 -> 3650 | W56: =W49-V49 -> 3849 | Z56: =SUM(E56:H56) -> 14119 | AA56: =SUM(I56:L56) -> 14081 | AB56: =SUM(M56:P56) -> 14467 | AC56: =SUM(Q56:T56) -> 14841
A57: Repurch | E57: =E50 -> 8796 | F57: =F50-E50 -> 23702 | G57: =G50-F50 -> 16965 | H57: =H50-G50 -> 17434 | I57: =I50 -> 20706 | J57: =J50-I50 -> 18574 | K57: =K50-J50 -> 15891 | L57: =L50-K50 -> 17187 | M57: =M50 -> 24775 | N57: =N50-M50 -> 18548 | O57: =O50-N50 -> 22900 | P57: =P50-O50 -> 19748 | Q57: =Q50 -> 20478 | R57: =R50-Q50 -> 22631 | S57: =S50-R50 -> 21865 | T57: =T50-S50 -> 24428 | U57: =U50 -> 19475 | V57: =V50-U50 -> 19594 | W57: =W50-V50 -> 17478 | Z57: =SUM(E57:H57) -> 66897 | AA57: =SUM(I57:L57) -> 72358 | AB57: =SUM(M57:P57) -> 85971 | AC57: =SUM(Q57:T57) -> 89402
J63: -1
