Workbook
Name Sectors: '[1]Sector Impact'!$K$4:$K$16
Name Sectors: 'Sector Impact'!$K$4:$K$16

Sheet OP
B2: (Date of last update) | C2: Team 1 | D2: (Date of next Quarter/Annual Report) | E2: =Inputs!I3 -> #VALUE! | L2: {=_FV(E2,"Exchange")} -> New York Stock Exchange | M2: SIC:
D3: COMPANY DESCRIPTION | H3: CEO & BOARD OF DIRECTORS
D4: {=_FV(Inputs!I3,"Description")} -> Constellation Brands, Inc. is a producer and marketer of beer, wine, and spirits with operations in the United States, Mexico, New Zealand, and Italy with brands, such as Corona Extra, Modelo Especial, Robert Mondavi Winery, Kim Crawford, Meiomi, The Prisoner Wine Company, High West, Casa Noble, and Mi CAMPO. Its segments include Beer, Wine and Spirits, and Corporate Operations and Other. In the Beer segment, its portfolio consists of high-end imported beer brands and ABAs. It has a perpetual brand license to produce its Mexican beer portfolio and to import, market, and sell such portfolio in the United States. In the Wine and Spirits segment, it sells a portfolio that includes higher-end wine brands complemented by certain higher-end spirits brands. Its Corporate Operations and Other segment consist of costs of corporate development, corporate finance, corporate strategy, executive management, growth, human resources, internal audit, investor relations, IT, legal and public relations. | H4: Name, Age and Tenure | I4: Gender | J4: Executive? | L4: Other roles
H5: Bill Newlands (-,6) | I5: M | J5: President and CEO (yes) | L5: Lead Director of Hormel Foods Corporation;
H6: Jim Bourdeau (-,7 ) | I6: M | J6: Chief Legal Officer (yes) | L6: N/A
H7: Christy Clark (58,5 ) | I7: F | J7: No | L7: Senior Advisor at Bennett Jones LLP
H8: Jennifer Daniels (-,6) | I8: F | J8: No | L8: Chief Legal Officer and Secretary of Colgate-Palmolive Company
H9: Nicholas Fink (-, 4) | I9: M | J9: No | L9: Chief Executive Officer, Fortune Brands Innovations, Inc.
H10: William T. Giles | I10: M | J10: No | L10: Former Chief Financial Officer and Executive Vice President of AutoZone, Inc
H11: Richar Sands (74, ) | I11: M | J11: No | L11: Non-Management Director
H12: Rob Sands ( 66, ) | I12: M | J12: No | L12: Non-Management Director
H13: Luca Zaramella (, 1) | I13: M | J13: No | L13: Executive Vice President, Chief Financial Officer of Mondelēz International
H14: Ernesto M. Hernández | I14: M | J14: No | L14: Former President and Managing Director of General Motors de Mexico, S. de R.L. de C.V.
B15: {=_FV(E2,"Currency")&" MILLIONS"} -> USD MILLIONS | H15: Daniel J. McCarthy | I15: M | J15: No | L15: Former President and Chief Executive Officer of Frontier Communications Corporation
B18: COMPANY OVERVIEW
B19: Stock | D19: Liquidity and Solvency | F19: Segments | I19: ="Profitability ("&J20&")" -> Profitability (2024) | L19: Multiples
B20: Last Price | C20: {=_FV(E2,"Price")} -> 248.17 | D20: Total Assets | E20: =_xlfn.XLOOKUP(D20,'Fin. Data'!A:A,'Fin. Data'!B:B,,0) -> 25691.7 | F20: Regions | H20: % Sales | I20: Reporting Year | J20: 2024 | L20: Float | M20: =164.92/181.54 -> 0.90844993
B21: Outstanding Shares | C21: {=_FV(E2,"Shares outstanding",TRUE)} -> 182192400 | D21: Total Liabilities | E21: =_xlfn.XLOOKUP(D21,'Fin. Data'!A:A,'Fin. Data'!B:B,,0) -> 15627.1 | F21: =Segments!C5 -> U.S. | H21: =Segments!B5 -> 0.97854805 | I21: End of Year | J21: 45291 | L21: Insiders Own | M21: 0.1194
B22: Market Cap. | C22: =C20*C21/1000000 -> 45214.688 | D22: Cash/Share | E22: =_xlfn.XLOOKUP("Cash & Eq.",'Fin. Data'!A:A,'Fin. Data'!B:B,,0)*1000000/C21 -> 0.83647836 | I22: EBITDA | K22: =_xlfn.XLOOKUP(I22,'Fin. Data'!A:A,'Fin. Data'!B:B,,0) -> 4111.4 | L22: b (Yahoo) | M22: {=IF(_FV(E2,"Beta") <> "",_FV(E2,"Beta"),"")} -> 0.8734
B23: +Total Debt | C23: ='Fin. Data'!B58 -> 12575.4 | D23: EBITDA/Net Financial Cost (NFC) | E23: =IFERROR(_xlfn.XLOOKUP("EBITDA",'Fin. Data'!A:A,'Fin. Data'!B:B,,0)/_xlfn.XLOOKUP("Net Financial Cost",'Fin. Data'!A:A,'Fin. Data'!B:B,,0),"") -> -9.4428112 | I23: Depreciation & Amortization | K23: =_xlfn.XLOOKUP(I23,'Fin. Data'!A:A,'Fin. Data'!B:B,,0) -> 429.2 | L23: Score (S&P) | M23: BBB+
B24: -Cash | C24: ='Fin. Data'!B39 -> 152.4 | D24: Debt/EBITDA | E24: =IFERROR(_xlfn.XLOOKUP("Total Debt",'Fin. Data'!A:A,'Fin. Data'!B:B,,0)/_xlfn.XLOOKUP("EBITDA",'Fin. Data'!A:A,'Fin. Data'!B:B,,0),"") -> 3.0586661 | F24: =Segments!C6 -> Non-U.S. | H24: =Segments!B6 -> 0.021451946 | I24: EBIT | K24: =_xlfn.XLOOKUP(I24,'Fin. Data'!A:A,'Fin. Data'!B:B,,0) -> 3682.2 | L24: Price/Book Value | M24: =IFERROR((C20*C21/(E20-E21))/1000000,"") -> 4.4924476
B25: =Enterprise Value | C25: =C22+C23-C24 -> 57637.688 | D25: "Others Assets"/Asset | E25: =IFERROR(_xlfn.XLOOKUP("Other Assets",'Fin. Data'!A:A,'Fin. Data'!B:B,,0)/_xlfn.XLOOKUP("Total Assets",'Fin. Data'!A:A,'Fin. Data'!B:B,,0),"") -> 0.53663635 | I25: Net Income | K25: =_xlfn.XLOOKUP(I25,'Fin. Data'!A:A,'Fin. Data'!B:B,,0) -> 1765.2 | L25: NCF(3y avg)/Asset | M25: =IFERROR(K31/E20,"") -> -0.015445974
B26: Holdings (nac/int'l) | C26: - | D26: Debt/Assets | E26: =_xlfn.XLOOKUP(D26,'Fin. Data'!A:A,'Fin. Data'!B:B,,0) -> 0.48947325 | F26: Categories | H26: % Sales | I26: EPS | K26: =1000000*K25/C21 -> 9.6886588 | L26: Price/Net Inc. (3y avg) | M26: =IFERROR(C22/K30,"") -> 78.511353
B27: t liq. (Holdings/Vol.) | C27: - | D27: EBITDA Margin (average) | E27: =IFERROR(AVERAGE(_xlfn.XLOOKUP("EBITDA Margin",'Fin. Data'!A:A,'Fin. Data'!B:D,,0)),"") -> 0.4885634 | F27: =Segments!C18 -> Beer | H27: =Segments!B18 -> 0.81939007 | I27: ROA | K27: =IFERROR(K25/E20,"") -> 0.068707014 | L27: EV/Asset | M27: =IFERROR(C25/E20,"") -> 2.2434361
B28: % Short | C28: 0.01274 | D28: Operating Margin (average) | E28: =IFERROR(AVERAGE(_xlfn.XLOOKUP("Operating Margin",'Fin. Data'!A:A,'Fin. Data'!B:D,,0)),"") -> 0.2944276 | I28: ROIC | K28: =IFERROR(Peers!C18,"") -> 0.12488643 | L28: EV/Ebitda (3y average) | M28: =IFERROR(C25/K29,"") -> 12.57193
B29: Traffic ESG | D29: Net Income Margin (average) | E29: =IFERROR(AVERAGE(_xlfn.XLOOKUP("Net Income Margin",'Fin. Data'!A:A,'Fin. Data'!B:D,,0)),"") -> 0.057745769 | F29: =Segments!C19 -> Wine | H29: =Segments!B19 -> 0.15580518 | I29: EBITDA (3y average) | K29: =AVERAGE(_xlfn.XLOOKUP("EBITDA",'Fin. Data'!A:A,'Fin. Data'!B:D,,0)) -> 4584.6333 | L29: Price/NCF (3y average) | M29: =IFERROR(C22/K31,"") -> -113.93873
B30: E | I30: Net Income (3y average) | K30: =AVERAGE(_xlfn.XLOOKUP("Net Income",'Fin. Data'!A:A,'Fin. Data'!B:D,,0)) -> 575.9 | L30: Bonds 1,3,5a (USD) | M30: -
B31: S | D31: Net Financial Cost/Avg Net Debt | E31: =IFERROR(-_xlfn.XLOOKUP("Net Financial Cost",'Fin. Data'!A:A,'Fin. Data'!B:B,,0)/AVERAGE(_xlfn.XLOOKUP("Net Debt",'Fin. Data'!A:A,'Fin. Data'!B:D,,0)),"") -> 0.036222058 | F31: =Segments!C20 -> Spirits | H31: =Segments!B20 -> 0.024804754 | I31: NCF (3y average) | K31: =AVERAGE(_xlfn.XLOOKUP("Net Financial Cost",'Fin. Data'!A:A,'Fin. Data'!B:D,,0)) -> -396.83333 | L31: Div+Rep.(3y avg)/Price | M31: =-IFERROR(SUM(E53:E55)/(3*C22),"") -> 0.038003137
B32: G | L32: Div. Yield | M32: =-IFERROR(L54/C22,"") -> 0.014459903
B33: INVESTMENT THESIS
B34: Pillars of Recommendation | H34: Recommendation | I34: Valuation Assumptions
B35: Pillar | C35: Explanation | H35: Hold | I35: Check DCF
B36: Strong Brand Portfolio | C36: Constellation Brands Inc. possesses numerous renowned brands that are recognized globally that follows the trend of "premiumization" (focus on premium products).
B37: Adaptive strategic oversight from the board | C37: Constellation's board is effectively shifting focus from lower-profit segments like wine and spirits, prioritizing higher-growth, high-margin investments instead.
B38: Leader in the U.S. imported beer market | C38: Constellation is a leader in the U.S. imported beer market, with a strong presence in the high-end beer.
B39: Risks of Investment | H39: Price Target | I39: Valuation
B40: Risk | C40: Explanation | H40: =DCF!D75 -> 188.41005 | I40: Discount Rate | J40: =DCF!F50 -> 0.0875 | L40: Price M. Upside | M40: -
B41: Competition | C41: The intense competition may impact its market position and profitability.
B42: Project cancellations | C42: Constellation Brands Inc. has a high incidence of project cancellations, like the Mexicali brewery, the project of craft beer | I42: Upside | J42: =IFERROR(DCF!D74,"") -> -0.24080247 | L42: EV M. Upside | M42: -
B43: Changing Consumer Preferences | C43: Shifts in consumer tastes toward healthier options or non-alcoholic beverages could affect sales in traditional alcohol categories.
B44: Regulatory Challenges | C44: Changes in laws or regulations can heavily impact operations and profitability.
B45: FINANCIAL PERFORMANCE
B46: Year | C46: Net Sales | D46: Operating Margin | E46: Dividends + Share Buyback | F46: Net Cash Flow | G46: Debt/Assets | H46: Depreciation & Amortization | I46: Capex + Investments | J46: Cash Flow
B47: =B48-1 -> 2016 | C47: {=_xlfn.SORTBY(TRANSPOSE(_xlfn.XLOOKUP(C$46,'Fin. Data'!$A:$A,'Fin. Data'!$B:$J,,0)),$B$47:$B$55,-1)} -> 6548.4 | D47: {=_xlfn.SORTBY(TRANSPOSE(_xlfn.XLOOKUP(D$46,'Fin. Data'!$A:$A,'Fin. Data'!$B:$J,,0)),$B$47:$B$55,-1)} -> 0.26954676 | E47: {=_xlfn.SORTBY(TRANSPOSE(_xlfn.XLOOKUP(E$46,'Fin. Data'!$A:$A,'Fin. Data'!$B:$J,,0)),$B$47:$B$55,-1)} -> -572.1 | F47: =Inputs!K77 -> 46.2 | G47: {=_xlfn.SORTBY(TRANSPOSE(_xlfn.XLOOKUP(G$46,'Fin. Data'!$A:$A,'Fin. Data'!$B:$J,,0)),$B$47:$B$55,-1)} -> 0.47634542 | H47: {=_xlfn.SORTBY(TRANSPOSE(_xlfn.XLOOKUP(H$46,'Fin. Data'!$A:$A,'Fin. Data'!$B:$J,,0)),$B$47:$B$55,-1)} -> 221 | I47: {=_xlfn.SORTBY(TRANSPOSE(_xlfn.XLOOKUP(I$46,'Fin. Data'!$A:$A,'Fin. Data'!$B:$J,,0)),$B$47:$B$55,-1)} -> -2207.7 | L47: =J20 -> 2024 | M47: =L47-1 -> 2023
B48: =B49-1 -> 2017 | C48: 7331.5 | D48: 0.32727273 | E48: -768.2 | F48: =Inputs!J77 -> -27 | G48: 0.49660796 | H48: 293.9 | I48: -1443.1 | J48: Net Income | L48: =_xlfn.XLOOKUP($J48,'Fin. Data'!$A:$A,'Fin. Data'!B:B,,0) -> 1765.2 | M48: =_xlfn.XLOOKUP($J48,'Fin. Data'!$A:$A,'Fin. Data'!C:C,,0) -> -38.5 | N48: =(C48/C47)-1 -> 0.11958646 | O48: =(D48/D47)-1 -> 0.21415938
B49: =B50-1 -> 2018 | C49: 7585 | D49: 0.30118655 | E49: -912.9 | F49: =Inputs!I77 -> 94.3 | G49: 0.49597589 | H49: 386.5 | I49: -1413.1 | J49: Operating CF | L49: =_xlfn.XLOOKUP($J49,'Fin. Data'!$A:$A,'Fin. Data'!B:B,,0) -> 2780 | M49: =_xlfn.XLOOKUP($J49,'Fin. Data'!$A:$A,'Fin. Data'!C:C,,0) -> 2756.9 | N49: =(C49/C48)-1 -> 0.034576826 | O49: =(D49/D48)-1 -> -0.079707757 | Q49: =F49/F48-1 -> -4.4925926 | R49: =H49/H48-1 -> 0.31507315 | S49: =I49/I48-1 -> -0.02078858
B50: =B51-1 -> 2019 | C50: 8116 | D50: 0.29721538 | E50: -1553.6 | F50: =Inputs!H77 -> -87.1 | G50: 0.46581599 | H50: 447.1 | I50: -4830.9 | J50: Investing CF | L50: =_xlfn.XLOOKUP($J50,'Fin. Data'!$A:$A,'Fin. Data'!B:B,,0) -> -1285.9 | M50: =_xlfn.XLOOKUP($J50,'Fin. Data'!$A:$A,'Fin. Data'!C:C,,0) -> -999.4 | N50: =(C50/C49)-1 -> 0.070006592 | O50: =(D50/D49)-1 -> -0.013185102 | Q50: =F50/F49-1 -> -1.9236479 | R50: =H50/H49-1 -> 0.15679172 | S50: =I50/I49-1 -> 2.418654
B51: =B52-1 -> 2020 | C51: 8343.5 | D51: 0.25822497 | E51: -1615.1 | F51: =Inputs!G77 -> 3.3 | G51: 0.46735009 | H51: 343.2 | I51: -531.4 | J51: Net Capex | L51: =_xlfn.XLOOKUP($J51,'Fin. Data'!$A:$A,'Fin. Data'!B:B,,0) -> -1269.1 | M51: =_xlfn.XLOOKUP($J51,'Fin. Data'!$A:$A,'Fin. Data'!C:C,,0) -> -1028.7 | N51: =(C51/C50)-1 -> 0.02803105 | O51: =(D51/D50)-1 -> -0.13118571 | Q51: =F51/F50-1 -> -1.0378875 | R51: =H51/H50-1 -> -0.23238649 | S51: =I51/I50-1 -> -0.88999979
B52: =B53-1 -> 2021 | C52: 8614.9 | D52: 0.32398519 | E52: -1620.9 | F52: =Inputs!F77 -> -12.2 | G52: 0.40574732 | H52: 305.1 | I52: -88.5 | J52: Investments & Acquisitions | L52: =_xlfn.XLOOKUP($J52,'Fin. Data'!$A:$A,'Fin. Data'!B:B,,0) -> 47.8 | M52: =_xlfn.XLOOKUP($J52,'Fin. Data'!$A:$A,'Fin. Data'!C:C,,0) -> 28.8 | N52: =(C52/C51)-1 -> 0.032528315 | O52: =(D52/D51)-1 -> 0.25466253 | Q52: =F52/F51-1 -> -4.6969697 | R52: =H52/H51-1 -> -0.11101399 | S52: =I52/I51-1 -> -0.83345879
B53: =B54-1 -> 2022 | C53: 8820.7 | D53: 0.2643441 | E53: -1963.5 | F53: =Inputs!E77 -> 379.2 | G53: 0.42443475 | H53: 342.4 | I53: -1033.8 | J53: Financing CF | L53: =_xlfn.XLOOKUP($J53,'Fin. Data'!$A:$A,'Fin. Data'!B:B,,0) -> -1474.6 | M53: =_xlfn.XLOOKUP($J53,'Fin. Data'!$A:$A,'Fin. Data'!C:C,,0) -> -1819.9 | N53: =(C53/C52)-1 -> 0.023888844 | O53: =(D53/D52)-1 -> -0.18408585 | Q53: =F53/F52-1 -> -32.081967 | R53: =H53/H52-1 -> 0.122255 | S53: =I53/I52-1 -> 10.681356
B54: =B55-1 -> 2023 | C54: 9452.6 | D54: 0.30075323 | E54: -2287.9 | F54: =Inputs!D$77 -> -261.2 | G54: 0.52698653 | H54: 400 | I54: -999.9 | J54: Dividends | L54: =_xlfn.XLOOKUP($J54,'Fin. Data'!$A:$A,'Fin. Data'!B:B,,0) -> -653.8 | M54: =_xlfn.XLOOKUP($J54,'Fin. Data'!$A:$A,'Fin. Data'!C:C,,0) -> -587.7 | N54: =(C54/C53)-1 -> 0.071638305 | O54: =(D54/D53)-1 -> 0.13773386 | Q54: =F54/F53-1 -> -1.6888186 | R54: =H54/H53-1 -> 0.1682243 | S54: =I54/I53-1 -> -0.032791642
B55: 2024 | C55: 9961.8 | D55: 0.31818547 | E55: -903.5 | F55: =Inputs!C77 -> -65.9 | G55: 0.48947325 | H55: 429.2 | I55: -1221.3 | J55: Share Buyback | L55: =_xlfn.XLOOKUP($J55,'Fin. Data'!$A:$A,'Fin. Data'!B:B,,0) -> -249.7 | M55: =_xlfn.XLOOKUP($J55,'Fin. Data'!$A:$A,'Fin. Data'!C:C,,0) -> -1700.2 | N55: =(C55/C54)-1 -> 0.053868777 | O55: =(D55/D54)-1 -> 0.057961926 | Q55: =F55/F54-1 -> -0.74770291 | R55: =H55/H54-1 -> 0.073 | S55: =I55/I54-1 -> 0.22142214
B56: Annual Growth Rate | C56: =IFERROR((C55/C47)^(1/8)-1,"") -> 0.053841574 | D56: =IFERROR((D55/D47)^(1/8)-1,"") -> 0.020953067 | F56: =IFERROR((F55/F47)^(1/8)-1,"") | H56: =IFERROR((H55/H47)^(1/8)-1,"") -> 0.086509255 | J56: FX | L56: =_xlfn.XLOOKUP($J56,'Fin. Data'!$A:$A,'Fin. Data'!B:B,,0) -> -0.6 | M56: =_xlfn.XLOOKUP($J56,'Fin. Data'!$A:$A,'Fin. Data'!C:C,,0) -> -3.5 | N56: =(C56/C55)-1 -> -0.9999946 | O56: =(D56/D55)-1 -> -0.93414826
B57: Average Growth Rate | C57: =IFERROR(AVERAGE(N48:N55),"") -> 0.054265647 | D57: =IFERROR(AVERAGE(O48:O55),"") -> 0.032044159 | F57: =IFERROR(AVERAGE(Q48:Q55),"") -> -6.6670838 | H57: =IFERROR(AVERAGE(S48:S55),"") -> 1.649199 | J57: Changes in Cash | L57: =L49-L50+L53-L54-L55 -> 3494.8 | M57: =M49-M50+M53-M54-M55 -> 4224.3
B58: CVAR | C58: =IFERROR(STDEV(C48:C55)/AVERAGE(C48:C55),"") -> 0.10420683 | D58: =IFERROR(STDEV(D47:D55)/AVERAGE(D47:D55),"") -> 0.08814078 | F58: =IFERROR(STDEV(F47:F55)/AVERAGE(F47:F55),"") -> 22.177983 | H58: =IFERROR(STDEV(H47:H55)/AVERAGE(H47:H55),"") -> 0.20435165 | J58: Inventory/D Revenues | L58: =IFERROR(SUM(I52:I55)/(C55-C51),"") -> -2.066057 | M58: =IFERROR((SUM(I52:I55)-SUM(H52:H55))/(C55-C51),"") -> -2.9785577
B59: Last Year | C59: =IFERROR(C55/C54-1,"") -> 0.053868777 | D59: =IFERROR(D55/D54-1,"") -> 0.057961926 | F59: =IFERROR(1-(F55/F54),"") -> 0.74770291 | H59: =IFERROR(1-(H55/H54),"") -> -0.073 | J59: t inversiones; t adq. neto dep. | L59: =IFERROR(L58/E27,"") -> -4.228841 | M59: =IFERROR(M58/E27,"") -> -6.0965633
B60: QUALITATIVE ANALYSIS
B61: SWOT ANALYSIS | J61: HOLDERS
B62: Pros | E62: Cons | J62: Name | M62: % Stake
J63: Vanguard Group Inc | M63: 0.0755
B64: Diversified Business Model | E64: High levels of dead stock | J64: Capital International Investors | M64: 0.0602
J65: Blackrock Inc. | M65: 0.0571
J66: Capital World Investors | M66: 0.0543
B67: Leadership position in the U.S. beer market | E67: High Debt levels | J67: Morgan Stanley | M67: 0.0442
J68: State Street Corporation | M68: 0.037
J69: JP Morgan Chase & Company | M69: 0.0175
B70: A solid approach to distributing and selling products through online channels. | E70: Dependence on limited facilities for production of their Mexican beer brands | J70: Geode Capital Management, LLC | M70: 0.0174
J71: Aristotle Capital Management, LLC | M71: 0.0169
J72: Alliancebernstein L.P. | M72: 0.0162
B73: Opportunities | E73: Risks | J73: Washington Mutual Investors Fund | M73: 0.0349
J74: American Balanced Fund | M74: 0.0295
B75: Expansion into emerging markets with rising demand for alcoholic beverages. | E75: Highly competitive industry | J75: Vanguard Total Stock Market Index Fund | M75: 0.0285
J76: Vanguard 500 Index Fund | M76: 0.0227
J77: American Mutual Fund Inc | M77: 0.0176
B78: Development of new product lines | E78: Significant reliance on agricultural goods | J78: Fidelity 500 Index Fund | M78: 0.0108
J79: SPDR S&P 500 ETF Trust | M79: 0.0105
B80: Expanding digital sales platforms to capitalize on shifting consumer purchasing behaviors. | E80: Reliance on complex information systems and third‐party global networks | J80: iShares Core S&P 500 ETF | M80: 0.0097
J81: Investment Company Of America | M81: 0.0095
J82: TOTAL | M82: =SUM(M63:M81) -> 0.57
B83: NOTES | G83: STOCK PERFORMANCE (5 years)
G108: =E2 -> #VALUE! | I108: =Peers!C2 -> #VALUE! | J108: =Peers!C3 -> #VALUE! | K108: =Peers!C5 -> #VALUE! | L108: =Peers!C4 -> #VALUE! | M108: =Peers!C6 -> #VALUE!

Sheet Segments
B2: ="Regions "&"("&OP!$J$20&")" -> Regions (2024) | Q2: Products
D3: Nominal value | K3: YoY Growth
B4: Weight | C4: Region | D4: 2024 | E4: =D4-1 -> 2023 | F4: =E4-1 -> 2022 | G4: =F4-1 -> 2021 | H4: =G4-1 -> 2020 | I4: =H4-1 -> 2019 | K4: 2024 | L4: =K4-1 -> 2023 | M4: =L4-1 -> 2022 | N4: =M4-1 -> 2021 | O4: =N4-1 -> 2020 | P4: =O4-1 -> 2019
B5: =IFERROR(D5/$D$13,"") -> 0.97854805 | C5: U.S. | D5: 9748.1 | E5: 9194.5 | F5: 8585.8 | G5: 8396.5 | H5: 8116.2 | I5: 7894.8 | K5: =(D5-E5)/E5 -> 0.060209908 | L5: =(E5-F5)/F5 -> 0.070896131 | M5: =(F5-G5)/G5 -> 0.022545108 | N5: =(G5-H5)/H5 -> 0.034535867 | O5: =(H5-I5)/I5 -> 0.028043776 | P5: -
B6: =IFERROR(D6/$D$13,"") -> 0.021451946 | C6: Non-U.S. | D6: 213.7 | E6: 258.1 | F6: 234.9 | G6: 218.4 | H6: 227.3 | I6: 221.2 | K6: =(D6-E6)/E6 -> -0.17202635 | L6: =(E6-F6)/F6 -> 0.098765432 | M6: =(F6-G6)/G6 -> 0.075549451 | N6: =(G6-H6)/H6 -> -0.039155301 | O6: =(H6-I6)/I6 -> 0.027576854 | P6: -
B7: =IFERROR(D7/$D$13,"") -> 0 | K7: =(D7-E7)/E7 -> #DIV/0! | L7: =(E7-F7)/F7 -> #DIV/0! | M7: =(F7-G7)/G7 -> #DIV/0! | N7: =(G7-H7)/H7 -> #DIV/0! | O7: =(H7-I7)/I7 -> #DIV/0! | P7: -
B8: =IFERROR(D8/$D$13,"") -> 0 | K8: =(D8-E8)/E8 -> #DIV/0! | L8: =(E8-F8)/F8 -> #DIV/0! | M8: =(F8-G8)/G8 -> #DIV/0! | N8: =(G8-H8)/H8 -> #DIV/0! | O8: =(H8-I8)/I8 -> #DIV/0! | P8: -
B9: =IFERROR(D9/$D$13,"") -> 0 | K9: =(D9-E9)/E9 -> #DIV/0! | L9: =(E9-F9)/F9 -> #DIV/0! | M9: =(F9-G9)/G9 -> #DIV/0! | N9: =(G9-H9)/H9 -> #DIV/0! | O9: =(H9-I9)/I9 -> #DIV/0! | P9: -
B10: =IFERROR(D10/$D$13,"") -> 0 | K10: =(D10-E10)/E10 -> #DIV/0! | L10: =(E10-F10)/F10 -> #DIV/0! | M10: =(F10-G10)/G10 -> #DIV/0! | N10: =(G10-H10)/H10 -> #DIV/0! | O10: =(H10-I10)/I10 -> #DIV/0! | P10: -
B11: =IFERROR(D11/$D$13,"") -> 0
B12: =IFERROR(D12/$D$13,"") -> 0
B13: =SUM(B5:B12) -> 1 | C13: TOTAL | D13: =SUM(D5:D12) -> 9961.8 | E13: =SUM(E5:E12) -> 9452.6 | F13: =SUM(F5:F12) -> 8820.7 | G13: =SUM(G5:G12) -> 8614.9 | H13: =SUM(H5:H12) -> 8343.5 | I13: =SUM(I5:I12) -> 8116 | K13: =(D13-E13)/E13 -> 0.053868777 | L13: =(E13-F13)/F13 -> 0.071638305 | M13: =(F13-G13)/G13 -> 0.023888844 | N13: =(G13-H13)/H13 -> 0.032528315 | O13: =(H13-I13)/I13 -> 0.02803105 | P13: -
B15: ="Categories "&"("&OP!$J$20&")" -> Categories (2024)
D16: Nominal value | K16: YoY Growth
B17: Weight | C17: Category | D17: 2024 | E17: =D17-1 -> 2023 | F17: =E17-1 -> 2022 | G17: =F17-1 -> 2021 | H17: =G17-1 -> 2020 | I17: =H17-1 -> 2019 | K17: 2024 | L17: =K17-1 -> 2023 | M17: =L17-1 -> 2022 | N17: =M17-1 -> 2021 | O17: =N17-1 -> 2020 | P17: =O17-1 -> 2019
B18: =IFERROR(D18/$D$24,"") -> 0.81939007 | C18: Beer | D18: 8162.6 | E18: 7465 | F18: 6751.6 | G18: 6074.6 | H18: 5615.9 | I18: 5202.1 | K18: =(D18-E18)/E18 -> 0.093449431 | L18: =(E18-F18)/F18 -> 0.10566384 | M18: =(F18-G18)/G18 -> 0.11144767 | N18: =(G18-H18)/H18 -> 0.081678805 | O18: =(H18-I18)/I18 -> 0.079544799 | P18: -
B19: =IFERROR(D19/$D$24,"") -> 0.15580518 | C19: Wine | D19: 1552.1 | E19: 1722.7 | F19: 1819.3 | G19: 2208.4 | H19: 2367.5 | I19: 2532.5 | K19: =(D19-E19)/E19 -> -0.099030592 | L19: =(E19-F19)/F19 -> -0.053097345 | M19: =(F19-G19)/G19 -> -0.17619091 | N19: =(G19-H19)/H19 -> -0.06720169 | O19: =(H19-I19)/I19 -> -0.065153011 | P19: -
B20: =IFERROR(D20/$D$24,"") -> 0.024804754 | C20: Spirits | D20: 247.1 | E20: 264.9 | F20: 249.8 | G20: 331.9 | H20: 360.1 | I20: 381.4 | K20: =(D20-E20)/E20 -> -0.067195168 | L20: =(E20-F20)/F20 -> 0.060448359 | M20: =(F20-G20)/G20 -> -0.24736366 | N20: =(G20-H20)/H20 -> -0.07831158 | O20: =(H20-I20)/I20 -> -0.05584688 | P20: -
B21: =IFERROR(D21/$D$24,"") -> 0 | K21: =(D21-E21)/E21 -> #DIV/0! | L21: =(E21-F21)/F21 -> #DIV/0! | M21: =(F21-G21)/G21 -> #DIV/0! | N21: =(G21-H21)/H21 -> #DIV/0! | O21: =(H21-I21)/I21 -> #DIV/0! | P21: -
B22: =IFERROR(D22/$D$24,"") -> 0 | K22: =(D22-E22)/E22 -> #DIV/0! | L22: =(E22-F22)/F22 -> #DIV/0! | M22: =(F22-G22)/G22 -> #DIV/0! | N22: =(G22-H22)/H22 -> #DIV/0! | O22: =(H22-I22)/I22 -> #DIV/0! | P22: -
B23: =IFERROR(D23/$D$24,"") -> 0 | K23: =(D23-E23)/E23 -> #DIV/0! | L23: =(E23-F23)/F23 -> #DIV/0! | M23: =(F23-G23)/G23 -> #DIV/0! | N23: =(G23-H23)/H23 -> #DIV/0! | O23: =(H23-I23)/I23 -> #DIV/0! | P23: -
B24: =SUM(B18:B23) -> 1 | C24: TOTAL | D24: =SUM(D18:D23) -> 9961.8 | E24: =SUM(E18:E23) -> 9452.6 | F24: =SUM(F18:F23) -> 8820.7 | G24: =SUM(G18:G23) -> 8614.9 | H24: =SUM(H18:H23) -> 8343.5 | I24: =SUM(I18:I23) -> 8116 | K24: =(D24-E24)/E24 -> 0.053868777 | L24: =(E24-F24)/F24 -> 0.071638305 | M24: =(F24-G24)/G24 -> 0.023888844 | N24: =(G24-H24)/H24 -> 0.032528315 | O24: =(H24-I24)/I24 -> 0.02803105 | P24: -
B26: Categories' operating margin
D27: Nominal value | K27: YoY Growth
B28: Category | D28: 2024 | E28: =D28-1 -> 2023 | F28: =E28-1 -> 2022 | G28: =F28-1 -> 2021 | H28: =G28-1 -> 2020 | I28: =H28-1 -> 2019 | K28: 2024 | L28: =K28-1 -> 2023 | M28: =L28-1 -> 2022 | N28: =M28-1 -> 2021 | O28: =N28-1 -> 2020 | P28: =O28-1 -> 2019
B29: Beer | D29: 0.379 | E29: 0.383 | F29: 0.4 | G29: 0.411 | H29: 0.4 | I29: 0.393 | K29: =(D29-E29)/E29 -> -0.010443864 | L29: =(E29-F29)/F29 -> -0.0425 | M29: =(F29-G29)/G29 -> -0.02676399 | N29: =(G29-H29)/H29 -> 0.0275 | O29: =(H29-I29)/I29 -> 0.017811705 | P29: -
B30: Wine and Spirits | D30: 0.222 | E30: 0.228 | F30: 0.227 | G30: 0.245 | H30: 0.26 | I30: 0.265 | K30: =(D30-E30)/E30 -> -0.026315789 | L30: =(E30-F30)/F30 -> 0.0044052863 | M30: =(F30-G30)/G30 -> -0.073469388 | N30: =(G30-H30)/H30 -> -0.057692308 | O30: =(H30-I30)/I30 -> -0.018867925 | P30: -
C31: Spirits | K31: =(D31-E31)/E31 -> #DIV/0! | L31: =(E31-F31)/F31 -> #DIV/0! | M31: =(F31-G31)/G31 -> #DIV/0! | N31: =(G31-H31)/H31 -> #DIV/0! | O31: =(H31-I31)/I31 -> #DIV/0! | P31: -
K32: =(D32-E32)/E32 -> #DIV/0! | L32: =(E32-F32)/F32 -> #DIV/0! | M32: =(F32-G32)/G32 -> #DIV/0! | N32: =(G32-H32)/H32 -> #DIV/0! | O32: =(H32-I32)/I32 -> #DIV/0! | P32: -
K33: =(D33-E33)/E33 -> #DIV/0! | L33: =(E33-F33)/F33 -> #DIV/0! | M33: =(F33-G33)/G33 -> #DIV/0! | N33: =(G33-H33)/H33 -> #DIV/0! | O33: =(H33-I33)/I33 -> #DIV/0! | P33: -
K34: =(D34-E34)/E34 -> #DIV/0! | L34: =(E34-F34)/F34 -> #DIV/0! | M34: =(F34-G34)/G34 -> #DIV/0! | N34: =(G34-H34)/H34 -> #DIV/0! | O34: =(H34-I34)/I34 -> #DIV/0! | P34: -
B35: TOTAL | D35: =SUM(D29:D34) -> 0.601 | E35: =SUM(E29:E34) -> 0.611 | F35: =SUM(F29:F34) -> 0.627 | G35: =SUM(G29:G34) -> 0.656 | H35: =SUM(H29:H34) -> 0.66 | I35: =SUM(I29:I34) -> 0.658 | K35: =(D35-E35)/E35 -> -0.016366612 | L35: =(E35-F35)/F35 -> -0.025518341 | M35: =(F35-G35)/G35 -> -0.044207317 | N35: =(G35-H35)/H35 -> -0.0060606061 | O35: =(H35-I35)/I35 -> 0.0030395137 | P35: -
B37: Number of units shipped (in million)
D38: Nominal value | K38: YoY Growth
B39: Category | D39: 2024 | E39: =D39-1 -> 2023 | F39: =E39-1 -> 2022 | G39: =F39-1 -> 2021 | H39: =G39-1 -> 2020 | I39: =H39-1 -> 2019 | K39: 2024 | L39: =K39-1 -> 2023 | M39: =L39-1 -> 2022 | N39: =M39-1 -> 2021 | O39: =N39-1 -> 2020 | P39: =O39-1 -> 2019
B40: Beer | D40: 4181 | E40: 3892 | F40: 3642 | G40: 3346 | H40: 3119 | I40: 2941 | K40: =(D40-E40)/E40 -> 0.074254882 | L40: =(E40-F40)/F40 -> 0.068643602 | M40: =(F40-G40)/G40 -> 0.088463837 | N40: =(G40-H40)/H40 -> 0.072779737 | O40: =(H40-I40)/I40 -> 0.060523631 | P40: -
B41: Wine and Spirits | D41: 238 | E41: 271 | F41: 299 | G41: 450 | H41: 536 | I41: 585 | K41: =(D41-E41)/E41 -> -0.12177122 | L41: =(E41-F41)/F41 -> -0.093645485 | M41: =(F41-G41)/G41 -> -0.33555556 | N41: =(G41-H41)/H41 -> -0.16044776 | O41: =(H41-I41)/I41 -> -0.083760684 | P41: -
B44: Categories | D44: Description | J44: Graphs
B45: Beer | D45: This segment positions Constellation as a leader in the U.S. imported beer market, with a strong presence in the high-end beer segment, featuring well-known names like Corona, Modelo, and Pacifico.
B46: Wine and Spirits | D46: This segment features a diverse portfolio, focusing on premium and luxury wines such as Robert Mondavi and The Prisoner Wine Company, as well as popular spirits like High West Whiskey and SVEDKA Vodka. It emphasizes premiumization to cater to evolving consumer preferences.
B50: Main costumers
B51: Company | D51: % of Constellation Revenue | F51: Short description
B52: Reyes Holdings LLC | D52: 0.251 | F52: Reyes Holdings, L.L.C. operates as a holding company. Through its subsidiaries, provides food and beverage products to restaurants, sporting venues, schools, nursing homes, hospitals, and hotels. Reyes Holdings serves customers globally.
B53: Southern Glazer's Wine and Spirits LLC | D53: 0.117 | F53: Southern Glazer's Wine and Spirits, LLC produces and supplies alcoholic beverages. The Company offers wines and spirits. Southern Glazer's Wine and Spirits serves customers in the United States.
B55: Industry | J55: Graphs (Industry Forecasts)
B56: Drivers | D56: Description
B57: Premiumization and Sustainability | D57: Constellation Brands will continue leveraging the premiumization trend by focusing on high-margin beverages. Simultaneously, investment in sustainability initiatives will appeal to the growing number of environmentally conscious consumers, boosting brand value and loyalty.
B58: Digital Innovation and E-Commerce | D58: Improved digital strategies, such as direct-to-consumer sales and collaborations with online delivery platforms, will drive future revenue growth. As the shift toward online alcohol purchases accelerates, expanding e-commerce capabilities will be key to reaching new customer segments and boosting sales.
B59: Expansion into New Markets and Cannabis Beverages | D59: The company is set to explore international markets beyond North America, targeting regions with rising demand for imported and premium alcoholic beverages. Additionally, as cannabis legalization expands, Constellation’s partnership with Canopy Growth positions it to capitalize on emerging opportunities in cannabis-infused beverages, offering a new revenue stream and gain an early market share into a new market.
B60: Margin improvement | D60: Constellation Brands may improve margins by focusing on premium products, divesting underperforming assets, and driving innovation in high-growth categories like RTDs and hard seltzers. Additionally, operational efficiency improvements and cost management strategies further optimize profitability.
B61: Sales forecast
B62: Source | D62: Market Growth CAGR | G62: Period
B63: Grande view research | D63: 0.093 | G63: 2025-2030
B64: Markets & Data | D64: 0.0495 | G64: 2023-2030
B65: Straits research | D65: 0.0615 | G65: 2024-2032
B66: Average | D66: =AVERAGE(D63:F65) -> 0.068
B67: Company's Strategy / Extra Notes
B68: Constellation Brands is shifting its strategy from acquisitions to expanding beer production capacity. This change aims to meet rising demand and support long-term growth through organic expansion. Unlike the acquisition-heavy 2015-2019 period, current investments prioritize scaling infrastructure, enhancing supply chain efficiency, and capturing a larger market share in the premium beer segment. The company is divesting its lower-end wine and spirits brands, like Black Box and Clos du Bois, to focus on premium offerings and streamline its portfolio.
B69: The company is committed on growing sales, expanding margins, and increasing cash flow in order to continue to achieve comparable earnings per share growth as well as their target net leverage ratio on a comparable basis and dividend payout ratio; investing to support the growth of the business; delivering additional returns to stockholders through periodic share repurchases.
B70: The results of operations and financial condition have been affected by macroeconomic headwinds, including rising unemployment, inflation, changing prices, other unfavorable global and regional economic conditions, global supply chain disruptions and constraints, and geopolitical events, as well as reductions in the discretionary income of consumers available to purchase the products and shifting consumer behaviors.
B71: Additionally, ongoing macroeconomic headwinds, particularly rising unemployment, have led to a recent deceleration in the rate of growth of consumer demand for the company' products. We expect some or all of these impacts to continue during the remainder of Fiscal 2025 which could have a material impact on the results of operations. The company intends to continue to monitor the economic environment, the shifting behavior of consumers, and their impacts on the business.
B72: The company is continuing the commodity and foreign exchange hedging programs while also seeking to identify additional cost savings and efficiency initiatives.
B73: The company’s stock-based compensation plan focuses on shorter vesting periods (typically 1-3 years) for nonqualified stock options, RSUs, and PSUs, with a continued emphasis on aligning awards with financial and operational performance metrics to incentivize long-term value creation.

Sheet Acuerdo
A1: Invertir
A2: NO invertir
A3: Mantener sin elevar posición
A4: Mantener (y seguir comprando)
A5: Liquidar
A6: PENDIENTE

Sheet Peers
B1: Peer Logo | C1: Peer Name | D1: Description
C2: #VALUE! | D2: Established in 2005 throught the merger of Molson, a canadian brewerie, and Coors, na american beer producer, Molson Coors Beverage Company is a leading multinational beverage and brewing company, that primarily produces beer, along with various hard seltzers and ready-to-drink cocktails. It operates worldwide, with a strong presence in North America and Europe.
C3: #VALUE! | D3: Diageo plc is a British alcoholic incorporated in 1886 and it specializes in the production, marketing and sales of various alcoholic beverages. It has a portfolios of iconic brands ranging form spirits to beers, and including gin, vodka, cider, liquer, wine, etc.
C4: #VALUE! | D4: Anheuser-Busch Inbev SA is a multinational beverage and brewing company, headquartered in Belgium, that produces, distributes, exports, markets, and sells beer and beverages.
C5: #VALUE! | D5: Pernod Ricard is a wine and spirits producers and seller. The company operates worldwine and is know for its diverse portfolio that includes whiskey, vodka, gin, rum, liqueur and bitters, champagne, tequila and mezcal, and aperitif.
C6: #VALUE! | D6: Brown-Forman is a well-known multinacional beverage company that manufactures, exports, markets, and sells various alcoholic beverages. It provides wines, whiskey spirits, whiskey-based flavored liqueurs, ready-to-drink cocktails, ready-to-pour products, vodkas, tequilas, gin, brandy, rum, bourbons, and liqueurs.
B8: In Millions USD | C8: =OP!E2 -> #VALUE! | D8: =C2 -> #VALUE! | E8: =C3 -> #VALUE! | F8: =C4 -> #VALUE! | G8: =C5 -> #VALUE! | H8: =C6 -> #VALUE! | I8: AVERAGE | J8: Deviation from Average
B9: Company Info | I9: =IFERROR(AVERAGE(C9:H9),"") | L9: TRAFFIC
B10: Market Cap | C10: {=_FV(C8,"Market cap",TRUE)/1000000} -> 45214.688 | D10: 11728 | E10: 78614 | F10: 126627 | G10: 35107 | H10: 22706 | I10: =IFERROR(AVERAGE(C10:H10),"") -> 53332.781 | J10: =SQRT((C10-I10)^2) -> 8118.0934 | M10: Best Value
B11: Net Sales (current) | C11: =C56 -> 9961.8 | D11: =D56 -> 11702 | E11: =E56 -> 20269 | F11: =F56 -> 59380 | G11: =G56 -> 13753 | H11: =H56 -> 4178 | I11: =IFERROR(AVERAGE(C11:H11),"") -> 19873.967 | J11: =SQRT((C11-I11)^2) -> 9912.1667
B12: Profitability | I12: =IFERROR(AVERAGE(C12:H12),"") | M12: Important Value
B13: Sales Growth (ttm) | C13: =C56/C55-1 -> 0.053868777 | D13: =D56/D55-1 -> 0.09354266 | E13: =E56/E55-1 -> -0.01391389 | F13: =F56/F55-1 -> 0.027584536 | G13: =G56/G55-1 -> 0.038040607 | H13: =H56/H55-1 -> -0.011825922 | I13: =IFERROR(AVERAGE(C13:H13),"") -> 0.031216128 | J13: =SQRT((C13-I13)^2) -> 0.022652649
B14: Sales Growth (36m) | C14: =C56/C54-1 -> 0.1563454 | D14: =D56/D54-1 -> -0.0018764927 | E14: =E56/E54-1 -> 0.15073237 | F14: =F56/F54-1 -> 0.26661121 | G14: =G56/G54-1 -> 0.31431575 | H14: =H56/H54-1 -> 0.22521994 | I14: =IFERROR(AVERAGE(C14:H14),"") -> 0.1852247 | J14: =SQRT((C14-I14)^2) -> 0.028879295 | M14: Worst Value
B15: Operating Margin | C15: =C59/C56 -> 0.31818547 | D15: =D59/D56 -> 0.12288498 | E15: =E59/E56 -> 0.29606789 | F15: =F59/F56 -> 0.2401482 | G15: =G59/G56 -> 0.21209918 | H15: =H59/H56 -> 0.26352322 | I15: =IFERROR(AVERAGE(C15:H15),"") -> 0.24215149 | J15: =SQRT((C15-I15)^2) -> 0.076033981
B16: Net Income Margin | C16: =C62/C56 -> 0.17719689 | D16: =D62/D56 -> 0.099897453 | E16: =E62/E56 -> 0.19093197 | F16: =F62/F56 -> 0.08994611 | G16: =G62/G56 -> 0.11422962 | H16: =H62/H56 -> 0.23647678 | I16: =IFERROR(AVERAGE(C16:H16),"") -> 0.15144647 | J16: =SQRT((C16-I16)^2) -> 0.025750421
B17: Return on Equity (RoE) | C17: =C62/C74 -> 0.18117437 | D17: =D62/D74 -> 0.087193257 | E17: =E62/E74 -> 0.38576555 | F17: =F62/F74 -> 0.065255107 | G17: =G62/G74 -> 0.093157021 | H17: =H62/H74 -> 0.28092124 | I17: =IFERROR(AVERAGE(C17:H17),"") -> 0.18224442 | J17: =SQRT((C17-I17)^2) -> 0.0010700546
B18: Return on Invested Capital (ROIC) | C18: =(1+C61/(C59+C60))*C59/(C73+C74-C65) -> 0.12488643 | D18: =(1+D61/(D59+D60))*D59/(D73+D74-D65) -> 0.062712614 | E18: =(1+E61/(E59+E60))*E59/(E73+E74-E65) -> 0.1624451 | F18: =(1+F61/(F59+F60))*F59/(F73+F74-F65) -> 0.083735629 | G18: =(1+G61/(G59+G60))*G59/(G73+G74-G65) -> 0.080745074 | H18: =(1+H61/(H59+H60))*H59/(H73+H74-H65) -> 0.13814683 | I18: =IFERROR(AVERAGE(C18:H18),"") -> 0.10877861 | J18: =SQRT((C18-I18)^2) -> 0.016107817
B19: Solvency | I19: =IFERROR(AVERAGE(C19:H19),"")
B20: Debt/Assets | C20: =C73/C70 -> 0.48947325 | D20: =D73/D70 -> 0.23772512 | E20: =E73/E70 -> 0.47281963 | F20: =F73/F70 -> 0.35637823 | G20: =G73/G70 -> 0.34752973 | H20: =H73/H70 -> 0.37962283 | I20: =IFERROR(AVERAGE(C20:H20),"") -> 0.38059146 | J20: =SQRT((C20-I20)^2) -> 0.10888179
B21: Net Debt/EBITDA | C21: =(C73-C65)/C58 -> 3.0215985 | D21: =(D73-D65)/D58 -> 2.4900876 | E21: =(E73-E65)/E58 -> 2.8243262 | F21: =(F73-F65)/F58 -> 3.5427362 | G21: =(G73-G65)/G58 -> 3.4297012 | H21: =(H73-H65)/H58 -> 1.8054422 | I21: =IFERROR(AVERAGE(C21:H21),"") -> 2.8523153 | J21: =SQRT((C21-I21)^2) -> 0.16928317
B22: Interest Coverage Ratio | C22: =-C58/C60 -> -9.4428112 | D22: =-D58/D60 -> -10.397891 | E22: =-E58/E60 -> -8.0079096 | F22: =-F58/F60 -> -4.625 | G22: =-G58/G60 -> -7.5032967 | H22: =-H58/H60 -> -13.00885 | I22: =IFERROR(AVERAGE(C22:H22),"") -> -8.8309596 | J22: =SQRT((C22-I22)^2) -> 0.61185158
B23: Liquidity
B24: Current Ratio | C24: =C68/C72 -> 1.1778122 | D24: =D68/D72 -> 0.69606645 | E24: =E68/E72 -> 1.5328334 | F24: =F68/F72 -> 0.62888901 | G24: =G68/G72 -> 1.6583699 | H24: =H68/H72 -> 2.588839 | I24: =IFERROR(AVERAGE(C24:H24),"") -> 1.3804683 | J24: =SQRT((C24-I24)^2) -> 0.20265611
B25: Quick Ratio | C25: =(C65+C66)/C72 -> 0.33190715 | D25: =(D65+D66)/D72 -> 0.39750794 | E25: =(E65+E66)/E72 -> 0.50385083 | F25: =(F65+F66)/F72 -> 0.39686726 | G25: =(G65+G66)/G72 -> 0.60446221 | H25: =(H65+H66)/H72 -> 0.77934573 | I25: =IFERROR(AVERAGE(C25:H25),"") -> 0.50232352 | J25: =SQRT((C25-I25)^2) -> 0.17041637
B26: Activity | I26: =IFERROR(AVERAGE(C26:H26),"")
B27: Inventory Turnover | C27: =C57/C67 -> 2.3790117 | D27: =D57/D67 -> 9.1433915 | E27: =E57/E67 -> 0.83034979 | F27: =F57/F67 -> 5.014827 | G27: =G57/G67 -> 0.5600181 | H27: =H57/H67 -> 0.64593114 | I27: =IFERROR(AVERAGE(C27:H27),"") -> 3.0955882 | J27: =SQRT((C27-I27)^2) -> 0.71657652
B28: Acc. Receivable Turnover | C28: =C56/C66 -> 11.961816 | D28: =D56/D66 -> 15.437995 | E28: =E56/E66 -> 5.812733 | F28: =F56/F66 -> 13.659995 | G28: =G56/G66 -> 7.5815877 | H28: =H56/H66 -> 5.4330299 | I28: =IFERROR(AVERAGE(C28:D28,F28,H28),"") -> 11.623209 | J28: =SQRT((C28-I28)^2) -> 0.33860666
A29: Price/Sales | B29: Payables Turnover | C29: =C57/C71 -> 5.2515135 | D29: =D57/D71 -> 3.0490644 | E29: =E57/E71 -> 1.2122259 | F29: =F57/F71 -> 1.5452648 | G29: =G57/G71 -> 0.96491228 | H29: =H57/H71 -> 6.1835206 | I29: =IFERROR(AVERAGE(C29:D29,F29,H29),"") -> 4.0073409 | J29: =SQRT((C29-I29)^2) -> 1.2441727
B30: Fixed Asset Turnover | C30: =C56/C69 -> 1.2366918 | D30: =D56/D69 -> 0.49738598 | E30: =E56/E69 -> 0.66788586 | F30: =F56/F69 -> 0.30300092 | G30: =G56/G69 -> 0.49927394 | H30: =H56/H69 -> 1.0116223 | I30: =IFERROR(AVERAGE(C30:H30),"") -> 0.70264347 | J30: =SQRT((C30-I30)^2) -> 0.53404836
B31: Total Asset Turnover | C31: =C56/C70 -> 0.3877439 | D31: =D56/D70 -> 0.44367773 | E31: =E56/E70 -> 0.44572723 | F31: =F56/F70 -> 0.27072125 | G31: =G56/G70 -> 0.32777235 | H31: =H56/H70 -> 0.5116336 | I31: =IFERROR(AVERAGE(C31:H31),"") -> 0.39787934 | J31: =SQRT((C31-I31)^2) -> 0.010135442
B32: Valuation | I32: =IFERROR(AVERAGE(C32:H32),"")
B33: Price/Earnings | C33: =C10/C62 -> 25.614484 | D33: =D10/D62 -> 10.032506 | E33: =E10/E62 -> 20.313695 | F33: =F10/F62 -> 23.708482 | G33: =G10/G62 -> 22.346913 | H33: =H10/H62 -> 22.981781 | I33: =IFERROR(AVERAGE(C33:H33),"") -> 20.832977 | J33: =SQRT((C33-I33)^2) -> 4.7815075
B34: Price/Sales | C34: =C10/C56 -> 4.538807 | D34: =D10/D56 -> 1.0022218 | E34: =E10/E56 -> 3.8785337 | F34: =F10/F56 -> 2.1324857 | G34: =G10/G56 -> 2.5526794 | H34: =H10/H56 -> 5.4346577 | I34: =IFERROR(AVERAGE(C34:H34),"") -> 3.2565642 | J34: =SQRT((C34-I34)^2) -> 1.2822428
B35: Price/Book | C35: =C10/C74 -> 4.6406881 | D35: =D10/D74 -> 0.87476691 | E35: =E10/E74 -> 7.8363238 | F35: =F10/F74 -> 1.5470995 | G35: =G10/G74 -> 2.0817718 | H35: =H10/H74 -> 6.4560705 | I35: =IFERROR(AVERAGE(C35:H35),"") -> 3.9061201 | J35: =SQRT((C35-I35)^2) -> 0.73456797
B36: EV/Sales | C36: =(C73+C10-C65)/C56 -> 5.7858708 | D36: =(D73+D10-D65)/D56 -> 1.4637669 | E36: =(E73+E10-E65)/E56 -> 4.8660516 | F36: =(F73+F10-F65)/F56 -> 3.2737622 | G36: =(G73+G10-G65)/G56 -> 3.4040573 | H36: =(H73+H10-H65)/H56 -> 6.0698899 | I36: =IFERROR(AVERAGE(C36:H36),"") -> 4.1438998 | J36: =SQRT((C36-I36)^2) -> 1.641971
B37: EV/EBITDA | C37: =(C73+C10-C65)/C58 -> 14.018993 | D37: =(D73+D10-D65)/D58 -> 7.8971876 | E37: =(E73+E10-E65)/E58 -> 13.917031 | F37: =(F73+F10-F65)/F58 -> 10.162371 | G37: =(G73+G10-G65)/G58 -> 13.712947 | H37: =(H73+H10-H65)/H58 -> 17.251701 | I37: =IFERROR(AVERAGE(C37:H37),"") -> 12.826705 | J37: =SQRT((C37-I37)^2) -> 1.1922879
B38: Stock Info | I38: =IFERROR(AVERAGE(C38:H38),"")
B39: Float | C39: =OP!M20 -> 0.90844993 | D39: 0.893 | E39: 1 | F39: 0.3988 | G39: 0.7639 | H39: 0.6902 | I39: =IFERROR(AVERAGE(C39:H39),"") -> 0.77572499 | J39: =SQRT((C39-I39)^2) -> 0.13272494
B40: b (Yahoo) | C40: =OP!M22 -> 0.8734 | D40: 0.81 | E40: 0.36 | F40: 0.98 | G40: 0.5 | H40: 0.75 | I40: =IFERROR(AVERAGE(C40:H40),"") -> 0.71223333 | J40: =SQRT((C40-I40)^2) -> 0.16116667
B41: Dividend Yield (yahoo finance) | C41: =OP!M32 -> 0.014459903 | D41: 0.031 | E41: 0.0074 | F41: 0.0132 | G41: 0.0357 | H41: 0.018 | I41: =IFERROR(AVERAGE(C41:H41),"") -> 0.019959984 | J41: =SQRT((C41-I41)^2) -> 0.0055000809
B42: Stock Performance
B43: 1y | C43: =234.38/241.5-1 -> -0.029482402 | D43: =59.56/58.99-1 -> 0.0096626547 | E43: =120.43/159.71-1 -> -0.24594578 | F43: =57.28/59.32-1 -> -0.034389751 | G43: =112.65/172.2-1 -> -0.34581882 | H43: =40.77/58.72-1 -> -0.30568801 | I43: =IFERROR(AVERAGE(C43:H43),"") -> -0.15861035 | J43: =SQRT((C43-I43)^2) -> 0.12912795
B44: 3y | C44: =234.38/221.78-1 -> 0.056813058 | D44: =59.56/46.09-1 -> 0.29225429 | E44: =120.43/204.39-1 -> -0.41078331 | F44: =57.28/60.29-1 -> -0.049925361 | G44: =112.65/204.4-1 -> -0.44887476 | H44: =40.77/73.53-1 -> -0.44553244 | I44: =IFERROR(AVERAGE(C44:H44),"") -> -0.16767475 | J44: =SQRT((C44-I44)^2) -> 0.22448781
B45: Current Price | C45: 234.38 | D45: 59.56 | E45: =120.43 -> 120.43 | F45: 57.28 | G45: 113 | H45: 40.77 | I45: =IFERROR(AVERAGE(C45:H45),"") -> 104.23667 | J45: =SQRT((C45-I45)^2) -> 130.14333
B46: Average Target Price | C46: 291.47 | D46: 59.4 | E46: 136.67 | F46: 73 | G46: =138.6*1.07 -> 148.302 | H46: 48.71 | I46: =IFERROR(AVERAGE(C46:H46),"") -> 126.25867 | J46: =SQRT((C46-I46)^2) -> 165.21133
B47: Upside/Downside | C47: =C46/C45-1 -> 0.2435788 | D47: =D46/D45-1 -> -0.0026863667 | E47: =E46/E45-1 -> 0.13485012 | F47: =F46/F45-1 -> 0.27444134 | G47: =G46/G45-1 -> 0.31240708 | H47: =H46/H45-1 -> 0.19475104 | I47: =IFERROR(AVERAGE(C47:H47),"") -> 0.19289034 | J47: =SQRT((C47-I47)^2) -> 0.050688467
B48: Extra | I48: =IFERROR(AVERAGE(C48:H48),"")
B49: 3y Operating Cash Flow | C49: =(Inputs!C59-Inputs!F59)/Inputs!F59 -> 0.080671083 | D49: =2079/1695-1 -> 0.22654867 | E49: =4105/5057.15947-1 -> -0.1882795 | F49: =13265/10891-1 -> 0.21797815 | G49: =1727/1999-1 -> -0.13606803 | H49: =647/817-1 -> -0.20807834 | I49: =IFERROR(AVERAGE(C49:H49),"") -> -0.0012046616 | J49: =SQRT((C49-I49)^2) -> 0.081875745
B50: R&D/Net Sales | C50: =C63/C11 -> 0 | D50: =D63/D11 -> 0 | E50: =E63/E11 -> 0 | F50: =F63/F11 -> 0 | G50: =G63/G11 -> 0 | H50: =H63/H11 -> 0 | I50: =IFERROR(AVERAGE(C50:H50),"") -> 0 | J50: =SQRT((C50-I50)^2) -> 0
B52: Financial Data | C52: =OP!E2 -> #VALUE! | D52: =D8 -> #VALUE! | E52: =E8 -> #VALUE! | F52: =F8 -> #VALUE! | G52: =G8 -> #VALUE! | H52: =H8 -> #VALUE!
B53: IS
B54: Net Sales (36m ago) | C54: ='Fin. Data'!E5 -> 8614.9 | D54: 11724 | E54: 17614 | F54: 46881 | G54: 10464 | H54: 3410
B55: Net Sales (12m ago) | C55: ='Fin. Data'!C5 -> 9452.6 | D55: 10701 | E55: 20555 | F55: 57786 | G55: 13249 | H55: 4228
B56: Net Sales (current) | C56: ='Fin. Data'!B5 -> 9961.8 | D56: 11702 | E56: 20269 | F56: 59380 | G56: 13753 | H56: 4178
B57: COGS | C57: ='Fin. Data'!B5-'Fin. Data'!B7 -> 4944.3 | D57: 7333 | E57: 8071 | F57: 27396 | G57: 4950 | H57: 1651
B58: EBITDA | C58: ='Fin. Data'!B19 -> 4111.4 | D58: 2169 | E58: 7087 | F58: 19129 | G58: 3414 | H58: 1470
B59: Operating Income | C59: ='Fin. Data'!B11 -> 3169.7 | D59: 1438 | E59: 6001 | F59: 14260 | G59: 2917 | H59: 1101
B60: Net Financial Cost | C60: =-'Fin. Data'!B14 -> 435.4 | D60: 208.6 | E60: 885 | F60: 4136 | G60: 455 | H60: 113
B61: Taxes | C61: ='Fin. Data'!B21 -> -456.6 | D61: -296 | E61: -1285 | F61: -2234 | G61: -705 | H61: -274
B62: Net Income | C62: ='Fin. Data'!B23 -> 1765.2 | D62: 1169 | E62: 3870 | F62: 5341 | G62: 1571 | H62: 988
B63: R&D
B64: BS
B65: Cash & Eq. | C65: ='Fin. Data'!B39 -> 152.4 | D65: 869 | E65: 1485 | F65: 10399 | G65: 2873 | H65: 446
B66: Acc. Receivables | C66: ='Fin. Data'!B40 -> 832.8 | D66: 758 | E66: 3487 | F66: 4347 | G66: 1814 | H66: 769
B67: Inventory | C67: ='Fin. Data'!B41 -> 2078.3 | D67: 802 | E67: 9720 | F67: 5463 | G67: 8839 | H67: 2556
B68: Current Assets | C68: =Inputs!C27 -> 3496.1 | D68: 2849 | E68: 15126 | F68: 23367 | G68: 12859 | H68: 4036
B69: Fixed Assets | C69: ='Fin. Data'!B42 -> 8055.2 | D69: 23527 | E69: 30348 | F69: 195973 | G69: 27546 | H69: 4130
B70: Total Assets | C70: ='Fin. Data'!B44 -> 25691.7 | D70: 26375 | E70: 45474 | F70: 219340 | G70: 41959 | H70: 8166
B71: Acc. Payable | C71: =Inputs!C43 -> 941.5 | D71: 2405 | E71: =6354+304 -> 6658 | F71: 17729 | G71: =3461+1556+113 -> 5130 | H71: 267
B72: Current Liabilities | C72: =Inputs!C42 -> 2968.3 | D72: 4093 | E72: 9868 | F72: 37156 | G72: 7754 | H72: 1559
B73: Total Debt | C73: ='Fin. Data'!B58 -> 12575.4 | D73: 6270 | E73: 21501 | F73: 78168 | G73: 14582 | H73: 3100
B74: Total Equity | C74: ='Fin. Data'!B64 -> 9743.1 | D74: 13407 | E74: 10032 | F74: 81848 | G74: 16864 | H74: 3517

Sheet ESG
B1: Company GICS Sector: | T1: Yes
B2: Consumer Staples | C2: <- Select Industry | T2: No
B3: ESG Analysis | K3: Relative ESG Analysis
B4: Parameters | C4: Impact | D4: Do they report? | E4: Ranking | F4: Mitigation Plan | G4: Traffic Lights | H4: Improvement over time? | I4: Targets / Goals? | J4: Comments | K4: Parameters | L4: =Peers!C8 -> #VALUE! | M4: =Peers!D8 -> #VALUE! | N4: =Peers!E8 -> #VALUE! | O4: =Peers!F8 -> #VALUE! | P4: =Peers!G8 -> #VALUE! | Q4: =Peers!H8 -> #VALUE! | R4: AVERAGE
B5: Environmental | K5: Ratios
A6: 1 | B6: CO2 Direct Emissions | C6: =VLOOKUP($B$2,'Sector Impact'!$K$4:$AA$16,A6+1,FALSE) -> High | D6: Yes | E6: Medium High | F6: Yes | H6: Co2 emissions have increased in the last five years, but slower every year | I6: reducing scope 1 and 2 emissions by 15% by 2025 | J6: no info about 2024 | K6: CO2 Emissions/$M Sales | L6: =L12/L$11 -> #DIV/0! | M6: =#REF!/M$11 -> #REF! | N6: =N12/N$11 -> #DIV/0! | O6: =O12/O$11 -> 61.986123 | P6: =P12/P$11 -> #DIV/0! | Q6: =Q12/Q$11 -> #DIV/0! | R6: =IFERROR(AVERAGE(L6:Q6),"")
A7: 2 | B7: Total Water Consumption | C7: =VLOOKUP($B$2,'Sector Impact'!$K$4:$AA$16,A7+1,FALSE) -> Very High | D7: Yes | E7: Medium High | F7: Yes | H7: inconsistent | I7: nothing especific | J7: vague goals and strategies | K7: Water Consumption/$M Sales | L7: =L13/L$11 -> #DIV/0! | M7: =M12/M$11 -> 81.04495 | N7: =N13/N$11 -> #DIV/0! | O7: =O13/O$11 -> #VALUE! | P7: =P13/P$11 -> #DIV/0! | Q7: =Q13/Q$11 -> #DIV/0! | R7: =IFERROR(AVERAGE(L7:Q7),"")
A8: 3 | B8: Total Energy Consumption | C8: =VLOOKUP($B$2,'Sector Impact'!$K$4:$AA$16,A8+1,FALSE) -> High | D8: No | E8: "Villain" | F8: No | H8: - | I8: no | J8: 6/10 years unreported, including 2023. Increase in consumption in the years reported, implementation of renewable energy sources. | K8: Energy Consumption/$M Sales | L8: =L14/L$11 -> #DIV/0! | M8: =M14/M$11 -> 2040.0252 | N8: =N14/N$11 -> #DIV/0! | O8: =O14/O$11 -> 933.8161 | P8: =P14/P$11 -> #DIV/0! | Q8: =Q14/Q$11 -> #DIV/0! | R8: =IFERROR(AVERAGE(L8:Q8),"")
A9: 4 | B9: Waste Management | C9: =VLOOKUP($B$2,'Sector Impact'!$K$4:$AA$16,A9+1,FALSE) -> High | D9: No | E9: Medium | F9: Yes | H9: - | I9: reducing packaging, increase percentage of recicled materials used in packaging to 80% | J9: only reported up to 2016 | K9: Waste Production/$M Sales | L9: =L15/L$11 -> #DIV/0! | M9: =M15/M$11 -> 70.383951 | N9: =N15/N$11 -> #DIV/0! | O9: =O15/O$11 -> #VALUE! | P9: =P15/P$11 -> #DIV/0! | Q9: =Q15/Q$11 -> #DIV/0! | R9: =IFERROR(AVERAGE(L9:Q9),"")
A10: 5 | B10: Land Degradation/Deforestation/Biodiversity loss/Animal sufering/… | C10: =VLOOKUP($B$2,'Sector Impact'!$K$4:$AA$16,A10+1,FALSE) -> High | D10: Yes | E10: Medium High | F10: Yes | H10: - | I10: environmental partnerships, donations and restoration iniciatives | J10: - | K10: Inputs
B11: Social | K11: Net Sales ($M) | M11: 11702 | O11: 59380
A12: 6 | B12: Employee Turnover % | C12: =VLOOKUP($B$2,'Sector Impact'!$K$4:$AA$16,A12+1,FALSE) -> Medium | D12: No | E12: Medium | F12: No | H12: - | I12: - | J12: - | K12: CO2 Emissions Total (Tonnes) | M12: 948388 | O12: 3680736
A13: 7 | B13: Salaries & Compensation | C13: =VLOOKUP($B$2,'Sector Impact'!$K$4:$AA$16,A13+1,FALSE) -> High | D13: No | E13: Medium | F13: No | H13: - | I13: - | J13: - | K13: Water Consumption Total (Cubic Meters) | M13: - | O13: -
A14: 8 | B14: Reputation | C14: =VLOOKUP($B$2,'Sector Impact'!$K$4:$AA$16,A14+1,FALSE) -> High | D14: No | E14: Medium High | F14: No | H14: - | I14: - | J14: nothing relevant found | K14: Energy Consumption Total (Gigajoules) | M14: 23872375 | O14: 55450000
A15: 9 | B15: Discrimination Events | C15: =VLOOKUP($B$2,'Sector Impact'!$K$4:$AA$16,A15+1,FALSE) -> Low | F15: Yes | K15: Waste Production Total (Tonnes) | M15: 823633 | O15: -
A16: 10 | B16: Work Safety | C16: =VLOOKUP($B$2,'Sector Impact'!$K$4:$AA$16,A16+1,FALSE) -> Medium | D16: No | E16: "Best in class" | F16: No | H16: - | I16: - | J16: no incidents found | K16: ESG Scores
A17: 11 | B17: Damage to consumer health | C17: =VLOOKUP($B$2,'Sector Impact'!$K$4:$AA$16,A17+1,FALSE) -> Medium | D17: No | E17: Medium High | F17: No | H17: - | I17: - | J17: promotion of responsible alcohol consumption, member of Responsability.org | K17: Refinitiv | L17: 37 | M17: 65 | O17: -
A18: 12 | B18: PXP? | C18: =VLOOKUP($B$2,'Sector Impact'!$K$4:$AA$16,A18+1,FALSE) -> Low | K18: Sustainalytics | L18: 26.4 | M18: 25.5 | O18: 22.1
A19: 13 | B19: Supply chain | C19: =VLOOKUP($B$2,'Sector Impact'!$K$4:$AA$16,A19+1,FALSE) -> High | D19: No | E19: Medium | F19: No | H19: - | I19: - | J19: suppliers are not disclosed, but a code of conduct has been published | K19: ISS | L19: C+ | M19: C | O19: C
A20: 14 | B20: Community involvement | C20: =VLOOKUP($B$2,'Sector Impact'!$K$4:$AA$16,A20+1,FALSE) -> Low | K20: CDP | L20: A-,A- | M20: - | O20: A,A
A21: 15 | B21: Public Sector | C21: =VLOOKUP($B$2,'Sector Impact'!$K$4:$AA$16,A21+1,FALSE) -> Very High | D21: No | E21: Medium High | F21: No | H21: - | I21: - | J21: -
A22: 16 | B22: Litigation | C22: =VLOOKUP($B$2,'Sector Impact'!$K$4:$AA$16,A22+1,FALSE) -> Low | D22: Yes
B23: Corporate Governance | K23: PARAMETERS
A24: 17 | B24: Diversity (Gender, Age, Industry, Region) | E24: Medium | F24: No | H24: - | I24: - | J24: barelly any diversity in age, gender and ethnicity, however quite diverse regarding backrounds | K24: IMPACT | L24: RANKING | M24: MITIGATION PLAN | O24: TRAFFIC
A25: 18 | B25: % Independence | E25: Medium High | F25: Yes | H25: Yes | I25: - | J25: 10 out of 13 independent board members, seven of which have been added in the last 5 years | K25: Low | L25: "Best in class" | M25: Is there evidence of a plan/program ?
A26: 19 | B26: average time as independent directors | E26: "Best in class" | F26: No | H26: - | I26: - | J26: average 5.3 years. | K26: Medium | L26: Medium High
A27: 20 | B27: Recent departures of directors / C-level executives? | E27: Medium High | F27: Yes | H27: - | I27: to increase nr of independent directors | J27: executive vice-president and president of the company’s wine and spirits division has stepped down in february | K27: High | L27: Medium
A28: 21 | B28: CEO/Chairman duality | E28: "Best in class" | F28: No | H28: - | I28: - | J28: CEO and chairman are independent | K28: Very high | L28: "Villain"
A29: 22 | B29: Transparency (ESG, segments, acquisitions, other) | E29: Medium | F29: No | H29: - | I29: - | J29: the data found for this company regarding environment, and social measures is mainly taken from 2023 documents, since 2024 sustainability report has not yet been published.
A30: 23 | B30: Time taken to report after the end of the quarter / year | E30: Medium High | F30: No | H30: - | I30: - | J30: 3 months
A31: 24 | B31: Additional participation of the CEO in other boards or excessive participation of Ch. | E31: "Best in class" | F31: No | H31: - | I31: - | J31: -
A32: 25 | B32: Audit / Consulting | D32: Yes | E32: "Villain" | F32: No | H32: no, on the contrary | I32: - | J32: "other fees" where reported in the proxy statement in the value of $13,000
A33: 26 | B33: ESG-compensation related | D33: No | E33: Medium | F33: No | H33: - | I33: - | J33: -
A34: 27 | B34: Management compensation schemes | D34: Yes | E34: "Best in class" | F34: No | H34: - | I34: - | J34: -
B37: the data found for this company regarding environment, and social measures is mainly taken from 2023 documents, since 2024 sustainability report has not yet been published.

Sheet DCF
A1: VALUATION MODEL
G3: Short Term | K3: Long Term
A4: Section | B4: Line # | C4: ITEM | D4: 2022 (Real) | E4: 2023 (Real) | F4: 2024 (Real) | G4: 2025 | H4: =G4+1 -> 2026 | I4: =H4+1 -> 2027 | J4: =I4+1 -> 2028 | K4: =J4+1 -> 2029 | L4: =K4+1 -> 2030 | M4: =L4+1 -> 2031 | N4: =M4+1 -> 2032 | O4: =N4+1 -> 2033 | ... AF4: =AE4+1 -> 2050
A5: INCOME STATEMENT | B5: 1 | C5: Growth | D5: ='Fin. Data'!D6 -> 0.023888844 | E5: =+E6/D6-1 -> 0.071638305 | F5: =+F6/E6-1 -> 0.053868777 | G5: =Assumptions!D39 -> 0.05 | H5: =Assumptions!E39 -> 0.045 | I5: =Assumptions!F39 -> 0.04 | J5: =Assumptions!G39 -> 0.04 | K5: =Assumptions!H39 -> 0.03 | L5: =Assumptions!I39 -> 0.03 | M5: =Assumptions!J39 -> 0.03 | N5: =Assumptions!K39 -> 0.03 | ... AE5: =Assumptions!AB39 -> 0.03 | AF5: =Assumptions!AD39 -> 0.03
B6: 2 | C6: Revenues/Sales | D6: =Inputs!D6 -> 8820.7 | E6: =Inputs!C6 -> 9452.6 | F6: =Inputs!B6 -> 9961.8 | G6: =F6*(1+G5) -> 10459.89 | H6: =G6*(1+H5) -> 10930.585 | I6: =H6*(1+I5) -> 11367.808 | J6: =I6*(1+J5) -> 11822.521 | K6: =J6*(1+K5) -> 12177.196 | L6: =K6*(1+L5) -> 12542.512 | M6: =L6*(1+M5) -> 12918.788 | N6: =M6*(1+N5) -> 13306.351 | ... AF6: =AE6*(1+AF5) -> 22653.172
B7: 3 | C7: EBIT/Operating Margin | D7: =D8/D6 -> 0.2643441 | E7: =E8/E6 -> 0.30075323 | F7: =F8/F6 -> 0.31818547 | G7: =Assumptions!D40 -> 0.33 | H7: =Assumptions!E40 -> 0.33 | I7: =Assumptions!F40 -> 0.33 | J7: =Assumptions!G40 -> 0.33 | K7: =Assumptions!H40 -> 0.345 | L7: =Assumptions!I40 -> 0.345 | M7: =Assumptions!J40 -> 0.345 | N7: =Assumptions!K40 -> 0.345 | ... AE7: =Assumptions!AB40 -> 0.345 | AF7: =Assumptions!AD40 -> 0.345
B8: 4 | C8: EBIT | D8: ='Fin. Data'!D11 -> 2331.7 | E8: ='Fin. Data'!C11 -> 2842.9 | F8: ='Fin. Data'!B11 -> 3169.7 | G8: =G7*G6 -> 3451.7637 | H8: =H7*H6 -> 3607.0931 | I8: =I7*I6 -> 3751.3768 | J8: =J7*J6 -> 3901.4319 | K8: =K7*K6 -> 4201.1328 | L8: =L7*L6 -> 4327.1667 | M8: =M7*M6 -> 4456.9817 | N8: =N7*N6 -> 4590.6912 | ... AF8: =AF7*AF6 -> 7815.3445
B9: 5a | C9: (Dep) | D9: -218.1 | E9: -439.6 | F9: -341.2 | G9: =$D$53*DCF!F40 -> -479.7156 | H9: =$D$53*DCF!G40 -> -540.6156 | I9: =$D$53*DCF!H40 -> -604.88744 | J9: =$D$53*DCF!I40 -> -671.73015 | K9: =$E$53*DCF!J40 -> -705.94912 | L9: =$E$53*DCF!K40 -> -769.27054 | M9: =$E$53*DCF!L40 -> -834.49161 | N9: =$E$53*DCF!M40 -> -901.6693 | O9: =$E$53*DCF!N40 -> -970.86233 | P9: =$E$53*DCF!O40 -> -1042.1311 | Q9: =$E$53*DCF!P40 -> -1115.538 | R9: =$E$53*DCF!Q40 -> -1191.1471 | ... AF9: =$E$53*DCF!AE40 -> -2521.785 | AG9: =SUM(D9:AF9) -> -36845.432
B10: 5b | C10: (Amort) | D10: -5.1 | E10: =-3.2 -> -3.2 | F10: -1.3 | G10: =F38*$D$54 -> -1.36585 | H10: =G38*$D$54 -> -1.3665329 | I10: =H38*$D$54 -> -1.3672162 | J10: =I38*$D$54 -> -1.3678998 | K10: =J38*$E$54 -> -2.189734 | L10: =K38*$E$54 -> -2.1914858 | M10: =L38*$E$54 -> -2.193239 | N10: =M38*$E$54 -> -2.1949936 | O10: =N38*$E$54 -> -2.1967496 | P10: =O38*$E$54 -> -2.198507 | Q10: =P38*$E$54 -> -2.2002658 | R10: =Q38*$E$54 -> -2.202026 | ... AF10: =AE38*$E$54 -> -2.2268173
B11: 5c | C11: (Stock based compensation) | D11: -44.9 | E11: -68.5 | F11: -63.6 | G11: =G6*$D$55 -> -83.67912 | H11: =H6*$D$55 -> -87.44468 | I11: =I6*$D$55 -> -90.942468 | J11: =J6*$D$55 -> -94.580166 | K11: =K6*$D$55 -> -97.417571 | L11: =L6*$D$55 -> -100.3401 | M11: =M6*$D$55 -> -103.3503 | N11: =N6*$D$55 -> -106.45081 | ... AF11: =AF6*$D$55 -> -181.22538
B12: 6 | C12: EBITDA | D12: =D8-D9-D10 -> 2554.9 | E12: =E8-E9-E10 -> 3285.7 | F12: =F8-F9-F10 -> 3512.2 | G12: =G8-G9-G10 -> 3932.8452 | H12: =H8-H9-H10 -> 4149.0752 | I12: =I8-I9-I10 -> 4357.6314 | J12: =J8-J9-J10 -> 4574.5299 | K12: =K8-K9-K10 -> 4909.2716 | ... AF12: =AF8-AF9-AF10 -> 10339.356
B13: 7 | C13: (Net financing cost) | D13: ='Fin. Data'!D14 -> -356.4 | E13: ='Fin. Data'!C14 -> -398.7 | F13: ='Fin. Data'!B14 -> -435.4 | G13: =F43*$D$58-F44*$D$57 -> -377.262 | H13: =G43*$D$58-G44*$D$57 -> -360.783 | I13: =H43*$D$58-H44*$D$57 -> -339.918 | J13: =I43*$D$58-I44*$D$57 -> -321.969 | K13: =J43*$E$58-J44*$E$57 -> -346.32675 | L13: =K43*$E$58-K44*$E$57 -> -350.12075 | M13: =L43*$E$58-L44*$E$57 -> -369.50725 | N13: =M43*$E$58-M44*$E$57 -> -384.55725 | O13: =N43*$E$58-N44*$E$57 -> -402.38975 | P13: =O43*$E$58-O44*$E$57 -> -399.08575 | Q13: =P43*$E$58-P44*$E$57 -> -408.16125 | R13: =Q43*$E$58-Q44*$E$57 -> -427.41125 | ... AF13: =AE43*$E$58-AE44*$E$57 -> -410.57975
B14: 8 | C14: Other income/(cost) | D14: ='Fin. Data'!D15 -> -1664.9 | E14: ='Fin. Data'!C15 -> -2060.6 | F14: ='Fin. Data'!B15 -> -512.5 | G14: -1600 | H14: =AVERAGE(F14)*(1+H5)*1.2 -> -642.675 | I14: =AVERAGE(F14,H14)*(1+I5)*1.2 -> -720.8292 | J14: =AVERAGE(F14,H14:I14)*(1+J5)*1.2 -> -780.41775 | K14: =AVERAGE(H14:J14)*(1+K5) -> -736.07987 | L14: =AVERAGE(I14:K14)*(1+L5) -> -768.14887 | M14: =AVERAGE(J14:L14)*(1+M5) -> -784.39529 | N14: =AVERAGE(K14:M14)*(1+N5) -> -785.76092 | O14: =AVERAGE(L14:N14)*(1+O5) -> -802.81808 | P14: =AVERAGE(M14:O14)*(1+P5) -> -814.72117 | Q14: =AVERAGE(N14:P14)*(1+Q5) -> -825.13306 | R14: =AVERAGE(O14:Q14)*(1+R5) -> -838.65083 | ... AF14: =AVERAGE(AC14:AE14)*(1+AF5) -> -1031.5879
B15: 9 | C15: Earnings before taxes | D15: =D8+D13+D14 -> 310.4 | E15: =E8+E13+E14 -> 383.6 | F15: =F8+F13+F14 -> 2221.8 | G15: =G8+G13+G14 -> 1474.5017 | H15: =H8+H13+H14 -> 2603.6351 | I15: =I8+I13+I14 -> 2690.6296 | J15: =J8+J13+J14 -> 2799.0451 | K15: =K8+K13+K14 -> 3118.7261 | ... AF15: =AF8+AF13+AF14 -> 6373.1768
B16: 10 | C16: (Income tax) | D16: ='Fin. Data'!D21 -> -309.4 | E16: ='Fin. Data'!C21 -> -422.1 | F16: ='Fin. Data'!B21 -> -456.6 | G16: =-11%*G15 -> -162.19519 | H16: =-$D$56*H15 -> -520.72701 | I16: =-$D$56*I15 -> -538.12592 | J16: =-$D$56*J15 -> -559.80902 | K16: =-$E$56*K15 -> -623.74523 | L16: =-$E$56*L15 -> -641.77942 | M16: =-$E$56*M15 -> -660.61584 | N16: =-$E$56*N15 -> -684.07461 | O16: =-$E$56*O15 -> -704.64082 | P16: =-$E$56*P15 -> -731.29147 | Q16: =-$E$56*Q15 -> -756.61558 | R16: =-$E$56*R15 -> -780.16026 | ... AF16: =-$E$56*AF15 -> -1274.6354
B17: 11 | C17: Net income | D17: ='Fin. Data'!D23 -> 1 | E17: ='Fin. Data'!C23 -> -38.5 | F17: ='Fin. Data'!B23 -> 1765.2 | G17: =G16+G15 -> 1312.3065 | H17: =H16+H15 -> 2082.9081 | I17: =I16+I15 -> 2152.5037 | J17: =J16+J15 -> 2239.2361 | K17: =K16+K15 -> 2494.9809 | L17: =L16+L15 -> 2567.1177 | M17: =M16+M15 -> 2642.4634 | N17: =N16+N15 -> 2736.2984 | ... AF17: =AF16+AF15 -> 5098.5414
A19: CASH FLOW STATEMENT | B19: 12 | C19: Operating cash flows before WK | D19: =Inputs!D59-DCF!D20-DCF!D21 -> 1901.3 | E19: =Inputs!C59-DCF!E20-DCF!E21 -> 1894.8 | F19: =Inputs!B59-DCF!F20-DCF!F21 -> 2364.9 | G19: =G17-G10-G9-G11 -> 1877.0671 | H19: =H17-H10-H9-H11 -> 2712.3349 | I19: =I17-I10-I9-I11 -> 2849.7008 | J19: =J17-J10-J9-J11 -> 3006.9143 | K19: =K17-K10-K9-K11 -> 3300.5373 | L19: =L17-L10-L9-L11 -> 3438.9198 | M19: =M17-M10-M9-M11 -> 3582.4985 | N19: =N17-N10-N9-N11 -> 3746.6135 | ... AF19: =AF17-AF10-AF9-AF11 -> 7803.7786
B20: 13 | C20: (Stock-based compensation) | D20: -44.9 | E20: -63.6 | F20: -68.5 | G20: =G11 -> -83.67912 | H20: =H11 -> -87.44468 | I20: =I11 -> -90.942468 | J20: =J11 -> -94.580166 | K20: =K11 -> -97.417571 | L20: =L11 -> -100.3401 | M20: =M11 -> -103.3503 | N20: =N11 -> -106.45081 | ... AF20: =AF11 -> -181.22538
B21: 14 | C21: (Working Capital Flows) | D21: =Inputs!D62 -> 849 | E21: =Inputs!C62 -> 925.7 | F21: =Inputs!B62 -> 483.6 | G21: =D60*(G6-F6) -> 597.708 | H21: =$D$60*(H6-G6) -> 564.83406 | I21: =$D$60*(I6-H6) -> 524.66808 | J21: =$D$60*(J6-I6) -> 545.65481 | K21: =$E$60*(K6-J6) -> 638.41612 | L21: =$E$60*(L6-K6) -> 657.56861 | M21: =$E$60*(M6-L6) -> 677.29566 | N21: =$E$60*(N6-M6) -> 697.61453 | O21: =$E$60*(O6-N6) -> 718.54297 | P21: =$E$60*(P6-O6) -> 740.09926 | Q21: =$E$60*(Q6-P6) -> 762.30224 | R21: =$E$60*(R6-Q6) -> 785.1713 | ... AF21: =$E$60*(AF6-AE6) -> 1187.642
B22: 15 | C22: -Total Operating Cash Flow | D22: =D19+D20+D21 -> 2705.4 | E22: =E19+E20+E21 -> 2756.9 | F22: =F19+F20+F21 -> 2780 | G22: =G19+G20+G21 -> 2391.096 | H22: =H19+H20+H21 -> 3189.7242 | I22: =I19+I20+I21 -> 3283.4264 | J22: =J19+J20+J21 -> 3457.989 | K22: =K19+K20+K21 -> 3841.5359 | ... AF22: =AF19+AF20+AF21 -> 8810.1953
B23: 16 | C23: (CAPEX) | D23: ='Fin. Data'!D32 -> -1022.7 | E23: ='Fin. Data'!C32 -> -1028.7 | F23: ='Fin. Data'!B32 -> -1269.1 | G23: -1450 | H23: =H6*$D$62 -> -1530.2819 | I23: =I6*$D$62 -> -1591.4932 | J23: =J6*$D$62 -> -1655.1529 | K23: =K6*$E$62 -> -1583.0355 | L23: =L6*$E$62 -> -1630.5266 | M23: =M6*$E$62 -> -1679.4424 | N23: =N6*$E$62 -> -1729.8257 | O23: =O6*$E$62 -> -1781.7204 | P23: =P6*$E$62 -> -1835.1721 | Q23: =Q6*$E$62 -> -1890.2272 | R23: =R6*$E$62 -> -1946.934 | ... AF23: =AF6*$E$62 -> -2944.9124 | AG23: =SUM(D23:AF23) -> -57888.236
B24: 17 | C24: Adq | D24: =Inputs!E66 -> 757.2 | E24: ='Fin. Data'!C33 -> 28.8 | F24: ='Fin. Data'!B33 -> 47.8 | G24: =G6*$D$63 -> 52.29945 | H24: =H6*$D$63 -> 54.652925 | I24: =I6*$D$63 -> 56.839042 | J24: =J6*$D$63 -> 59.112604 | K24: =K6*$E$63 -> -365.31589 | L24: =L6*$E$63 -> -376.27537 | M24: =M6*$E$63 -> -387.56363 | N24: =N6*$E$63 -> -399.19054 | O24: =O6*$E$63 -> -411.16626 | P24: =P6*$E$63 -> -423.50124 | Q24: =Q6*$E$63 -> -436.20628 | R24: =R6*$E$63 -> -449.29247 | ... AF24: =AF6*$E$63 -> -679.59517 | AH24: =AG9-AG23 -> 21042.805
B25: 18 | C25: (Other investing flows) | D25: =Inputs!D67 -> -2 | E25: =Inputs!C67 -> 0.5 | F25: =Inputs!B67 -> -64.6 | G25: =(1+G5)*AVERAGE(D25:F25) -> -23.135 | H25: =(1+H5)*AVERAGE(E25:G25) -> -30.386858 | I25: =(1+I5)*AVERAGE(F25:H25) -> -40.948911 | J25: =(1+J5)*AVERAGE(G25:I25) -> -32.749867 | K25: =(1+K5)*AVERAGE(H25:J25) -> -35.736068 | L25: =(1+L5)*AVERAGE(I25:K25) -> -37.57263 | M25: =(1+M5)*AVERAGE(J25:L25) -> -36.413441 | N25: =(1+N5)*AVERAGE(K25:M25) -> -37.671268 | ... AF25: =(1+AF5)*AVERAGE(AC25:AE25) -> -49.096977
B26: 19 | C26: -Total Investing Flows | D26: =D23+D24+D25 -> -267.5 | E26: =E23+E24+E25 -> -999.4 | F26: =F23+F24+F25 -> -1285.9 | G26: =G23+G24+G25 -> -1420.8356 | H26: =H23+H24+H25 -> -1506.0158 | I26: =I23+I24+I25 -> -1575.6031 | J26: =J23+J24+J25 -> -1628.7902 | K26: =K23+K24+K25 -> -1984.0875 | ... AF26: =AF23+AF24+AF25 -> -3673.6046
B27: 20 | C27: (Flows related to leases) | D27: =Inputs!D71+Inputs!D72 -> -5.9 | E27: =Inputs!C71+Inputs!C72 -> -8.8 | F27: =Inputs!B71+Inputs!B72 -> -9.7 | G27: =G6*$D$66 -> -10.45989 | H27: =H6*$D$66 -> -10.930585 | I27: =I6*$D$66 -> -11.367808 | J27: =J6*$D$66 -> -11.822521 | K27: =$E$66*K6 -> -12.177196 | L27: =$E$66*L6 -> -12.542512 | M27: =$E$66*M6 -> -12.918788 | N27: =$E$66*N6 -> -13.306351 | O27: =$E$66*O6 -> -13.705542 | P27: =$E$66*P6 -> -14.116708 | Q27: =$E$66*Q6 -> -14.540209 | R27: =$E$66*R6 -> -14.976416 | ... AF27: =$E$66*AF6 -> -22.653172
B28: 21 | C28: Flows related to debt | D28: =+SUM(Inputs!D69:D70) -> -727.3 | E28: =+SUM(Inputs!C69:C70) -> 306.7 | F28: =+SUM(Inputs!B69:B70) -> -596.9 | G28: =G44-F44 -> -549.3 | H28: =H44-G44 -> -695.5 | I28: =I44-H44 -> -598.3 | J28: =J44-I44 -> -837.25 | K28: =K44-J44 -> 108.4 | L28: =L44-K44 -> 553.9 | M28: =M44-L44 -> 430 | N28: =N44-M44 -> 509.5 | ... AF28: =AF44-AE44 -> -350
B29: 22 | C29: (Repurchases)/Issuance of stock | D29: ='Fin. Data'!D28 -> -1390.5 | E29: ='Fin. Data'!C28 -> -1700.2 | F29: ='Fin. Data'!B28 -> -249.7 | G29: =-G17*$D$65 -> -183.72291 | H29: =-H17*$D$65 -> -291.60713 | I29: =-I17*$D$65 -> -301.35051 | J29: =-J17*$D$65 -> -313.49305 | K29: =-K17*$E$65 -> -1247.4905 | L29: =-L17*$E$65 -> -1283.5588 | M29: =-M17*$E$65 -> -1321.2317 | N29: =-N17*$E$65 -> -1368.1492 | O29: =-O17*$E$65 -> -1409.2816 | P29: =-P17*$E$65 -> -1462.5829 | Q29: =-Q17*$E$65 -> -1513.2312 | R29: =-R17*$E$65 -> -1560.3205 | ... AF29: =-AF17*$E$65 -> -2549.2707
B30: 23 | C30: (Dividends) | D30: ='Fin. Data'!D27 -> -573 | E30: ='Fin. Data'!C27 -> -587.7 | F30: ='Fin. Data'!B27 -> -653.8 | G30: =$D$64*G17 -> -524.92261 | H30: =$D$64*H17 -> -833.16322 | I30: =$D$64*I17 -> -861.00147 | J30: =$D$64*J17 -> -895.69444 | K30: =$E$64*K17 -> -1247.4905 | L30: =$E$64*L17 -> -1283.5588 | M30: =$E$64*M17 -> -1321.2317 | N30: =$E$64*N17 -> -1368.1492 | O30: =$E$64*O17 -> -1409.2816 | P30: =$E$64*P17 -> -1462.5829 | Q30: =$E$64*Q17 -> -1513.2312 | R30: =$E$64*R17 -> -1560.3205 | ... AF30: =$E$64*AF17 -> -2549.2707
B31: 24 | C31: Other financing flows | D31: =Inputs!D75 -> 767.2 | E31: =Inputs!C75 -> 170.1 | F31: =Inputs!B75 -> 35.5 | G31: =(1+G5)*AVERAGE(D31:F31) -> 340.48 | H31: =(1+H5)*AVERAGE(E31:G31) -> 190.21787 | I31: =(1+I5)*AVERAGE(F31:H31) -> 196.28193 | J31: =(1+J5)*AVERAGE(G31:I31) -> 252.01966 | K31: =(1+K5)*AVERAGE(H31:J31) -> 219.22501 | L31: =(1+L5)*AVERAGE(I31:K31) -> 229.18413 | M31: =(1+M5)*AVERAGE(J31:L31) -> 240.48056 | N31: =(1+N5)*AVERAGE(K31:M31) -> 236.5188 | ... AF31: =(1+AF5)*AVERAGE(AC31:AE31) -> 311.98955
B32: 25 | C32: -Total Financing flows | D32: =D27+D28+D29+D30+D31 -> -1929.5 | E32: =E27+E28+E29+E30+E31 -> -1819.9 | F32: =F27+F28+F29+F30+F31 -> -1474.6 | G32: =G27+G28+G29+G30+G31 -> -927.92541 | H32: =H27+H28+H29+H30+H31 -> -1640.9831 | I32: =I27+I28+I29+I30+I31 -> -1575.7379 | J32: =J27+J28+J29+J30+J31 -> -1806.2403 | K32: =K27+K28+K29+K30+K31 -> -2179.5331 | ... AF32: =AF27+AF28+AF29+AF30+AF31 -> -5159.2051
A34: SUMMARY | B34: 26 | C34: Cash before shareholder returns | D34: =D22+D26+D27+D28+D31 -> 2471.9 | E34: =E22+E26+E27+E28+E31 -> 2225.5 | F34: =F22+F26+F27+F28+F31 -> 923 | G34: =G22+G26+G27+G28+G31 -> 750.98052 | H34: =H22+H26+H27+H28+H31 -> 1167.4957 | I34: =I22+I26+I27+I28+I31 -> 1294.4375 | J34: =J22+J26+J27+J28+J31 -> 1232.1459 | K34: =K22+K26+K27+K28+K31 -> 2172.8962 | ... AF34: =AF22+AF26+AF27+AF28+AF31 -> 5075.9271
B35: 27 | C35: Returns to shareholders | D35: =-1*(D29+D30) -> 1963.5 | E35: =-1*(E29+E30) -> 2287.9 | F35: =-1*(F29+F30) -> 903.5 | G35: =-1*(G29+G30) -> 708.64552 | H35: =-1*(H29+H30) -> 1124.7703 | I35: =-1*(I29+I30) -> 1162.352 | J35: =-1*(J29+J30) -> 1209.1875 | K35: =-1*(K29+K30) -> 2494.9809 | ... AF35: =-1*(AF29+AF30) -> 5098.5414
B36: 28 | C36: Excess cash acumulation | D36: =D34-D35 -> 508.4 | E36: =E34-E35 -> -62.4 | F36: =F34-F35 -> 19.5 | G36: =G34-G35 -> 42.335006 | H36: =H34-H35 -> 42.725339 | I36: =I34-I35 -> 132.08549 | J36: =J34-J35 -> 22.958429 | K36: =K34-K35 -> -322.0847 | ... AF36: =AF34-AF35 -> -22.614366
A38: BALANCE SHEET | B38: 29 | C38: Intangible assets | D38: 2755.2 | E38: 2728.1 | F38: 2731.7 | G38: =+F38+(-G10) -> 2733.0658 | H38: =+G38+(-H10) -> 2734.4324 | I38: =+H38+(-I10) -> 2735.7996 | J38: =+I38+(-J10) -> 2737.1675 | K38: =+J38+(-K10) -> 2739.3572 | L38: =+K38+(-L10) -> 2741.5487 | M38: =+L38+(-M10) -> 2743.742 | N38: =+M38+(-N10) -> 2745.937 | ... AF38: =+AE38+(-AF10) -> 2785.7485 | AG38: =SUM(G38:AF38) -> 71715.268
B39: 30 | C39: Accumulated amortization | D39: 86.3 | E39: 88.8 | F39: 89.6 | G39: =F39-G10 -> 90.96585 | H39: =G39-H10 -> 92.332383 | I39: =H39-I10 -> 93.699599 | J39: =I39-J10 -> 95.067499 | K39: =J39-K10 -> 97.257233 | L39: =K39-L10 -> 99.448719 | M39: =L39-M10 -> 101.64196 | N39: =M39-N10 -> 103.83695 | ... AF39: =AE39-AF10 -> 143.64848 | AG39: =SUM(G39:AF39) -> 3020.6679
B40: 31 | C40: PPE+Right of use Assets | D40: =Assumptions!AC19 -> 8512.6 | E40: =Assumptions!AB19 -> 9726.5 | F40: =Assumptions!AA19 -> 11421.8 | G40: =F40+(-G23) -> 12871.8 | H40: =G40+(-H23) -> 14402.082 | I40: =H40+(-I23) -> 15993.575 | J40: =I40+(-J23) -> 17648.728 | K40: =J40+(-K23) -> 19231.764 | L40: =K40+(-L23) -> 20862.29 | M40: =L40+(-M23) -> 22541.733 | N40: =M40+(-N23) -> 24271.558 | ... AF40: =AE40+(-AF23) -> 65989.536 | AG40: =SUM(G40:AF40) -> 947996.56
B41: 32 | C41: Accumulated depreciation | D41: =Assumptions!AC16 -> 1952.3 | E41: =Assumptions!AB16 -> 2391.9 | F41: =Assumptions!AA16 -> 2733.1 | G41: =F41-G9 -> 3212.8156 | H41: =G41-H9 -> 3753.4312 | I41: =H41-I9 -> 4358.3186 | J41: =I41-J9 -> 5030.0488 | K41: =J41-K9 -> 5735.9979 | L41: =K41-L9 -> 6505.2685 | M41: =L41-M9 -> 7339.7601 | N41: =M41-N9 -> 8241.4294 | ... AF41: =AE41-AF9 -> 38579.632 | AG41: =SUM(G41:AF41) -> 436687.98
A43: CASH & DEBT & DISCOUNTING | B43: 33 | C43: Ending cash balance | D43: ='Fin. Data'!D39 -> 199.4 | E43: =E36+D43 -> 137 | F43: =F36+E43 -> 156.5 | G43: =G36+F43 -> 198.83501 | H43: =H36+G43 -> 241.56034 | I43: =I36+H43 -> 373.64584 | J43: =J36+I43 -> 396.60427 | K43: =K36+J43 -> 74.519567 | L43: =L36+K43 -> 229.71722 | ... AF43: =AF36+AE43 -> 70.293292
B44: 34 | C44: Total Debt | D44: ='Fin. Data'!D58 -> 10974.1 | E44: ='Fin. Data'!C58 -> 12996.7 | F44: ='Fin. Data'!B58 -> 12575.4 | G44: =Assumptions!C84 -> 12026.1 | H44: =Assumptions!D84 -> 11330.6 | I44: =Assumptions!E84 -> 10732.3 | J44: =Assumptions!F84 -> 9895.05 | K44: =Assumptions!G84 -> 10003.45 | L44: =Assumptions!H84 -> 10557.35 | M44: =Assumptions!I84 -> 10987.35 | N44: =Assumptions!J84 -> 11496.85 | ... AF44: =Assumptions!AB84 -> 11380.85
B45: 35 | C45: Discount factor | F45: =1/((1+$F$50)^G50) -> 1 | G45: =1/((1+$F$50)^G49) -> 0.91954023 | H45: =1/((1+$F$50)^H49) -> 0.84555423 | I45: =1/((1+$F$50)^I49) -> 0.77752114 | J45: =1/((1+$F$50)^J49) -> 0.71496196 | K45: =1/((1+$F$50)^K49) -> 0.65743629 | L45: =1/((1+$F$50)^L49) -> 0.60453912 | M45: =1/((1+$F$50)^M49) -> 0.55589804 | N45: =1/((1+$F$50)^N49) -> 0.51117061 | ... AF45: =1/((1+$F$50)^AF49) -> 0.11293774
B46: 36 | C46: DF + 0.1% | E46: +0.1% | F46: =1/((1+$F$50+0.001)^G50) -> 1 | G46: =1/((1+$F$50+0.001)^G49) -> 0.91869545 | H46: =1/((1+$F$50+0.001)^H49) -> 0.84400133 | I46: =1/((1+$F$50+0.001)^I49) -> 0.77538019 | J46: =1/((1+$F$50+0.001)^J49) -> 0.71233825 | K46: =1/((1+$F$50+0.001)^K49) -> 0.65442191 | L46: =1/((1+$F$50+0.001)^L49) -> 0.60121444 | M46: =1/((1+$F$50+0.001)^M49) -> 0.55233297 | N46: =1/((1+$F$50+0.001)^N49) -> 0.50742579 | ... AF46: =1/((1+$F$50+0.001)^AF49) -> 0.11027085
B47: 37 | C47: DF+0.5% | E47: +0.5% | F47: =1/((1+$F$50+0.005)^G50) -> 1 | G47: =1/((1+$F$50+0.005)^G49) -> 0.91533181 | H47: =1/((1+$F$50+0.005)^H49) -> 0.83783232 | I47: =1/((1+$F$50+0.005)^I49) -> 0.76689457 | J47: =1/((1+$F$50+0.005)^J49) -> 0.70196299 | K47: =1/((1+$F$50+0.005)^K49) -> 0.64252906 | L47: =1/((1+$F$50+0.005)^L49) -> 0.58812728 | M47: =1/((1+$F$50+0.005)^M49) -> 0.53833161 | N47: =1/((1+$F$50+0.005)^N49) -> 0.49275204 | ... AF47: =1/((1+$F$50+0.005)^AF49) -> 0.10024031
A49: Discount Rate | C49: Risk free rate | D49: Equity premium | E49: Firm premium | F49: Total | G49: 1 | H49: 2 | I49: 3 | J49: 4 | K49: 5 | L49: 6 | M49: 7 | N49: 8 | O49: 9 | P49: 10 | Q49: 11 | R49: 12 | S49: 13 | T49: 14 | U49: 15 | V49: 16 | W49: 17 | X49: 18 | Y49: 19 | Z49: 20 | AA49: 21 | AB49: 22 | AC49: 23 | AD49: 24 | AE49: 25 | AF49: 26
C50: 0.04 | D50: 0.04 | E50: 0.0075 | F50: =E50+D50+C50 -> 0.0875 | G50: 0
A52: Modelling factors | D52: Short Term | E52: Long Term | F52: Reference (line)
C53: Depreciation factor | D53: =-Assumptions!S17 -> -0.042 | E53: =-Assumptions!T17 -> -0.04 | F53: =Assumptions!V17 -> % PPE
C54: Amortization factor | D54: =-Assumptions!S18 -> -0.0005 | E54: =-Assumptions!T18 -> -0.0008 | F54: =Assumptions!V18 -> % IA
C55: Stock-based comp | D55: =-Assumptions!S19 -> -0.008 | E55: =-Assumptions!T19 -> -0.01 | F55: =Assumptions!V19 -> % Revenue
C56: Tax Rate | D56: =Assumptions!S20 -> 0.2 | E56: =Assumptions!T20 -> 0.2 | F56: =Assumptions!V20 -> % EBT
C57: Interest Rate on debt | D57: =Assumptions!S21 -> 0.03 | E57: =Assumptions!T21 -> 0.035 | F57: =Assumptions!V21 -> % Debt
C58: Interest Rate on cash | D58: =Assumptions!S22 -> 0 | E58: =Assumptions!T22 -> 0 | F58: =Assumptions!V22 -> % Cash
C59: PPE+ROA | D59: =Assumptions!S23 -> - - | E59: =Assumptions!T23 -> - - | F59: =Assumptions!V23 -> Growing with CAPEX
C60: Working capital flows | D60: =Assumptions!S24 -> 1.2 | E60: =Assumptions!T24 -> 1.8 | F60: =Assumptions!V24 -> % Change in Revenues
C61: Intangible Assets | D61: =Assumptions!S25 -> - - | E61: =Assumptions!T25 -> - - | F61: =Assumptions!V25 -> Growing with Amortization
C62: Capex | D62: =-Assumptions!S26 -> -0.14 | E62: =-Assumptions!T26 -> -0.13 | F62: =Assumptions!V26 -> % Revenue
C63: Acquisition factor | D63: =Assumptions!S27 -> 0.005 | E63: =Assumptions!T27 -> -0.03 | F63: =Assumptions!V27 -> % Revenue
C64: Dividends | D64: =Assumptions!S28 -> -0.4 | E64: =Assumptions!T28 -> -0.5 | F64: =Assumptions!V28 -> % Net Income
C65: Repurchases | D65: =Assumptions!S29 -> 0.14 | E65: =Assumptions!T29 -> 0.5 | F65: =Assumptions!V29 -> % Net Income
C66: Leases | D66: =-Assumptions!S30 -> -0.001 | E66: =-Assumptions!T30 -> -0.001 | F66: =Assumptions!V30 -> % Revenue
C67: Total Debt | D67: =Assumptions!S31 -> - | E67: =Assumptions!T31 -> - | F67: Check assumptions
A69: Valuation | D69: $ millions
C70: Value of flows | D70: =SUMPRODUCT(G35:AF35,G45:AF45)+((AF43-AF44)*AF45) -> 24357.075 | E70: =D70/D72 -> 0.70956276
C71: Value of perpetuity | D71: =(AF34/(F50-AF5))*AF45 -> 9969.8041 | E71: =D71/D72 -> 0.29043724
C72: Total Value | D72: =D70+D71 -> 34326.879
C73: Actual share price | D73: =OP!C20 -> 248.17
C74: Total value vs Mkt Cap | D74: =D75/D73-1 -> -0.24080247
C75: Estimated NPV per share | D75: =D72*1000000/OP!C21 -> 188.41005
A77: Sensibility | C77: Sensitivity +0.1% | D77: =(SUMPRODUCT(G35:AF35,G45:AF45)+((AF43-AF44)*AF45)+(AF34/(F50+0.001-AF5))*AF45)*1000000/OP!C21 -> 187.47464 | E77: =D77/D75-1 -> -0.0049647391
C78: Sensitivity +0.5% | D78: =(SUMPRODUCT(G35:AF35,G45:AF45)+((AF43-AF44)*AF45)+(AF34/(F50+0.005-AF5))*AF45)*1000000/OP!C21 -> 184.03235 | E78: =D78/D75-1 -> -0.023234979
A80: Notes | C80: Price where it'd be a "BUY" | D80: =D75/1.15 -> 163.83483
BX9853: 2025 | BY9853: =BX9853+1 -> 2026 | BZ9853: =BY9853+1 -> 2027 | CA9853: =BZ9853+1 -> 2028
BX9854: =((2/3)*F14+((D14+E14)/2)*(1/3))*(1+G5) -> -1010.7125 | BY9854: =((2/3)*F14+((E14+G14)/2)*(1/3))*(1+H5) -> -994.59617 | BZ9854: =((2/3)*F14+((H14+G14)/2)*(1/3))*(1+I5) -> -744.06367 | CA9854: =((2/3)*F14+((H14+I14)/2)*(1/3))*(1+J5) -> -591.67406

Sheet Assumptions
B2: Assumptions
B4: Prospects: | C4: =HYPERLINK("#Assumptions!DA1035","Guidance") -> Guidance
B6: Links: | C6: https://www.cbrands.com/blogs/news/constellation-brands-updates-fiscal-2025-outlook
C8: 2024 | D8: =C8-1 -> 2023 | E8: =D8-1 -> 2022 | F8: =E8-1 -> 2021 | G8: =F8-1 -> 2020 | H8: =G8-1 -> 2019 | I8: =H8-1 -> 2018 | J8: =I8-1 -> 2017 | K8: =J8-1 -> 2016 | ... M8: =L8-1 -> 2014 | O8: 10Y Average | P8: 5Y Average | Q8: 3Y Average | S8: Short Term Forecast | T8: Long Term Forecast
B9: Revenue growth | C9: =(Inputs!C6-Inputs!D6)/Inputs!D6 -> 0.071638305 | D9: =(Inputs!D6-Inputs!E6)/Inputs!E6 -> 0.023888844 | E9: =(Inputs!E6-Inputs!F6)/Inputs!F6 -> 0.032528315 | F9: =(Inputs!F6-Inputs!G6)/Inputs!G6 -> 0.02803105 | G9: =(Inputs!G6-Inputs!H6)/Inputs!H6 -> 0.070006592 | H9: =(Inputs!H6-Inputs!I6)/Inputs!I6 -> 0.034576826 | I9: =(Inputs!I6-Inputs!J6)/Inputs!J6 -> 0.11958646 | J9: =(Inputs!J6-Inputs!K6)/Inputs!K6 -> 0.086330458 | ... M9: =(Inputs!M6-Inputs!N6)/Inputs!N6 -> 0.053422748 | O9: =AVERAGE(C9:M9) -> 0.1362969 | P9: =AVERAGE(C9:G9) -> 0.045218621 | Q9: =AVERAGE(C9:E9) -> 0.042685155 | S9: 0.04 | T9: 0.03
B10: Operating Margin | C10: =Inputs!C8/Inputs!C6 -> 0.30075323 | D10: =Inputs!D8/Inputs!D6 -> 0.2643441 | E10: =Inputs!E8/Inputs!E6 -> 0.32398519 | F10: =Inputs!F8/Inputs!F6 -> 0.25822497 | G10: =Inputs!G8/Inputs!G6 -> 0.29721538 | H10: =Inputs!H8/Inputs!H6 -> 0.30118655 | I10: =Inputs!I8/Inputs!I6 -> 0.32727273 | J10: =Inputs!J8/Inputs!J6 -> 0.26954676 | ... M10: =Inputs!M8/Inputs!M6 -> 0.18701048 | O10: =AVERAGE(C10:M10) -> 0.26744333 | P10: =AVERAGE(C10:G10) -> 0.28890457 | Q10: =AVERAGE(C10:E10) -> 0.29636084 | S10: 0.33 | T10: 0.345
B13: Modelling Factors
C15: Last 10 Years | Z15: Values in M. | AA15: 2024 | AB15: =AA15-1 -> 2023 | AC15: =AB15-1 -> 2022 | AD15: =AC15-1 -> 2021 | AE15: =AD15-1 -> 2020 | AF15: =AE15-1 -> 2019 | AG15: =AF15-1 -> 2018 | AH15: =AG15-1 -> 2017 | AI15: =AH15-1 -> 2016 | ... AK15: =AJ15-1 -> 2014 | AL15: 2013
C16: =C8 -> 2024 | D16: =D8 -> 2023 | E16: =E8 -> 2022 | F16: =F8 -> 2021 | G16: =G8 -> 2020 | H16: =H8 -> 2019 | I16: =I8 -> 2018 | J16: =J8 -> 2017 | ... M16: =M8 -> 2014 | O16: =O8 -> 10Y Average | P16: =P8 -> 5Y Average | Q16: =Q8 -> 3Y Average | S16: Short Term Forecast | T16: Long Term Forecast | V16: Reference | Z16: Accumulated Depreciation | AA16: 2733.1 | AB16: 2391.9 | AC16: 1952.3 | AD16: 1734.2 | AE16: 1458.2 | AF16: 1705.2 | AG16: 1484 | AH16: 1277 | AI16: 1179.3 | AJ16: 1050.2 | AK16: 924.7
B17: Depreciation factor | C17: =AA29/AA24 -> 0.039663339 | D17: =AB29/AB24 -> 0.041460068 | E17: =AC29/AC24 -> 0.042099876 | F17: =AD29/AD24 -> 0.038884036 | G17: =AE29/AE24 -> 0.048076923 | H17: =AF29/AF24 -> 0.047773395 | I17: =AG29/AG24 -> 0.046830419 | J17: =AH29/AH24 -> 0.045587163 | ... M17: =AK29/AK24 -> 0.0475672 | O17: =AVERAGE(C17:M17) -> 0.043755183 | P17: =AVERAGE(C17:G17) -> 0.042036849 | Q17: =AVERAGE(C17:E17) -> 0.041074428 | S17: 0.042 | T17: 0.04 | V17: % PPE | Z17: Accumulated Amortization | AA17: =AA18-AA26 -> 89.6 | AB17: =AB18-AB26 -> 88.8 | AC17: =AC18-AC26 -> 86.3 | AD17: =AD18-AD26 -> 81.8 | AE17: =AE18-AE26 -> 75.5 | AF17: =AF18-AF26 -> 70.4 | AG17: =AG18-AG26 -> 64.5 | AH17: =AH18-AH26 -> 58.7 | ... AK17: =AK18-AK26 -> 186.6
B18: Amortization factor | C18: =AA30/AA18 -> 0.00046078049 | D18: =AB30/AB18 -> 0.0011360006 | E18: =AC30/AC18 -> 0.0017948267 | F18: =AD30/AD18 -> 0.0018835069 | G18: =AE30/AE18 -> 0.0020397939 | H18: =AF30/AF18 -> 0.0018357045 | I18: =AG30/AG18 -> 0.0017511056 | J18: =AH30/AH18 -> 0.003026423 | ... M18: =AK30/AK18 -> 0.0045352137 | O18: =AVERAGE(C18:M18) -> 0.0038388968 | P18: =AVERAGE(C18:G18) -> 0.0014629817 | Q18: =AVERAGE(C18:E18) -> 0.0011305359 | S18: 0.0005 | T18: 0.0008 | V18: % IA | Z18: Intangible Assets (Gross) | AA18: =2715.2+106.1 -> 2821.3 | AB18: =2710.4+106.5 -> 2816.9 | AC18: =108+2733.5 -> 2841.5 | AD18: =108.3+2705.6 -> 2813.9 | AE18: =107.6+2686.8 -> 2794.4 | AF18: =110.4+3158.1 -> 3268.5 | AG18: =110.1+3259.2 -> 3369.3 | AH18: =109+3327.4 -> 3436.4 | AI18: =193.1+3337.9 -> 3531 | AJ18: =190.2+3078.3 -> 3268.5 | AK18: =186.6+3231.1 -> 3417.7
B19: Stock-based comp | C19: =AA20/Inputs!B6 -> 0.0063843884 | D19: =AB20/Inputs!C6 -> 0.0072466835 | E19: =AC20/Inputs!D6 -> 0.005090299 | F19: =AD20/Inputs!E6 -> 0.0073129114 | G19: =AE20/Inputs!F6 -> 0.0072391682 | H19: =AF20/Inputs!G6 -> 0.0078979793 | I19: =AG20/Inputs!H6 -> 0.0080290046 | J19: =AH20/Inputs!I6 -> 0.007651913 | ... M19: =AK20/Inputs!L6 -> 0.010251248 | O19: =AVERAGE(C19:M19) -> 0.007679452 | P19: =AVERAGE(C19:G19) -> 0.0066546901 | Q19: =AVERAGE(C19:E19) -> 0.0062404569 | S19: 0.008 | T19: 0.01 | V19: % Revenue | Z19: PPE+ROA | AA19: =AA24+AA25 -> 11421.8 | AB19: =AB24+AB25 -> 9726.5 | AC19: =AC24+AC25 -> 8512.6 | AD19: =AD24+AD25 -> 8050.7 | AE19: =AE24+AE25 -> 7299.2 | AF19: =AF24+AF25 -> 6972.5 | AG19: =AG24+AG25 -> 6273.7 | AH19: =AH24+AH25 -> 5209.8 | ... AK19: =AK24+AK25 -> 2939
B20: Tax Rate | C20: ='Fin. Data'!B21/('Fin. Data'!B21-'Fin. Data'!B23) -> 0.20550905 | D20: ='Fin. Data'!C21/('Fin. Data'!C21-'Fin. Data'!C23) -> 1.100365 | E20: ='Fin. Data'!D21/('Fin. Data'!D21-'Fin. Data'!D23) -> 0.99677835 | F20: ='Fin. Data'!E21/('Fin. Data'!E21-'Fin. Data'!E23) -> 0.20099099 | G20: ='Fin. Data'!F21/('Fin. Data'!F21-'Fin. Data'!F23) -> 1.0226407 | H20: ='Fin. Data'!G21/('Fin. Data'!G21-'Fin. Data'!G23) -> 0.16547648 | I20: ='Fin. Data'!H21/('Fin. Data'!H21-'Fin. Data'!H23) -> 0.005079609 | J20: ='Fin. Data'!I21/('Fin. Data'!I21-'Fin. Data'!I23) -> 0.26473679 | ... M20: ='Fin. Data'!L21/('Fin. Data'!L21-'Fin. Data'!L23) -> 0.11769514 | O20: =AVERAGE(C20:M20) -> 0.42398966 | P20: =AVERAGE(C20:G20) -> 0.70525681 | Q20: =AVERAGE(C20:E20) -> 0.76755079 | S20: 0.2 | T20: 0.2 | V20: % EBT | Z20: Stock Based Compensation | AA20: 63.6 | AB20: 68.5 | AC20: 44.9 | AD20: 63 | AE20: 60.4 | AF20: 64.1 | AG20: 60.9 | AH20: 56.1 | AI20: 54 | AJ20: 55 | AK20: 49.9
B21: Interest Rate on debt | C21: =AA21/AA23 -> 0.034623153 | D21: =AB21/AB23 -> 0.030677018 | E21: =AC21/AC23 -> 0.032476467 | F21: =AD21/AD23 -> 0.035070969 | G21: =AE21/AE23 -> 0.033572184 | H21: =AF21/AF23 -> 0.027841222 | I21: =AG21/AG23 -> 0.032817301 | J21: =AH21/AH23 -> 0.036273693 | ... M21: =AK21/AK23 -> 0.047520572 | O21: =AVERAGE(C21:M21) -> 0.036026287 | P21: =AVERAGE(C21:G21) -> 0.033283958 | Q21: =AVERAGE(C21:E21) -> 0.032592213 | S21: 0.03 | T21: 0.035 | V21: % Debt | Z21: Interest expenses | AA21: 435.4 | AB21: 398.7 | AC21: 356.4 | AD21: 385.7 | AE21: 428.7 | AF21: 379.1 | AG21: 334.3 | AH21: 335.1 | AI21: 314.7 | AJ21: 339.1 | AK21: 330.9
B22: Interest Rate on cash | C22: =AA22/Inputs!B28 -> 0 | D22: =AB22/Inputs!C28 -> 0 | E22: =AC22/Inputs!D28 -> 0 | F22: =AD22/Inputs!E28 -> 0 | G22: =AE22/Inputs!F28 -> 0 | H22: =AF22/Inputs!G28 -> 0.12820513 | I22: =AG22/Inputs!H28 -> 0.025470653 | J22: =AH22/Inputs!I28 -> 0.010146561 | ... M22: =AK22/Inputs!L28 -> 0.12050078 | O22: =AVERAGE(C22:M22) -> 0.027878709 | P22: =AVERAGE(C22:G22) -> 0 | Q22: =AVERAGE(C22:E22) -> 0 | S22: 0 | T22: 0 | V22: % Cash | Z22: Interest income | AA22: 0 | AB22: 0 | AC22: 0 | AD22: 0 | AE22: 0 | AF22: 12 | AG22: 2.3 | AH22: 1.8 | AI22: 0.8 | AJ22: 1.4 | AK22: 7.7
B23: PPE+ROA | C23: =Inputs!B33/Inputs!C33-1 -> 0.17333799 | D23: =Inputs!C33/Inputs!D33-1 -> 0.13294607 | E23: =Inputs!D33/Inputs!E33-1 -> 0.040882232 | F23: =Inputs!E33/Inputs!F33-1 -> 0.091618226 | G23: =Inputs!F33/Inputs!G33-1 -> 0.012473184 | H23: =Inputs!G33/Inputs!H33-1 -> 0.09971397 | I23: =Inputs!H33/Inputs!I33-1 -> 0.21788548 | J23: =Inputs!I33/Inputs!J33-1 -> 0.1798164 | ... M23: =Inputs!L33/Inputs!M33-1 -> 0.63897478 | O23: =AVERAGE(C23:M23) -> 0.19654486 | P23: =AVERAGE(C23:G23) -> 0.090251541 | Q23: =AVERAGE(C23:E23) -> 0.1157221 | S23: - - | T23: - - | V23: Growing with CAPEX | Z23: Total Debt | AA23: ='Fin. Data'!B58 -> 12575.4 | AB23: ='Fin. Data'!C58 -> 12996.7 | AC23: ='Fin. Data'!D58 -> 10974.1 | AD23: ='Fin. Data'!E58 -> 10997.7 | AE23: ='Fin. Data'!F58 -> 12769.5 | AF23: ='Fin. Data'!G58 -> 13616.5 | AG23: ='Fin. Data'!H58 -> 10186.7 | AH23: ='Fin. Data'!I58 -> 9238.1 | ... AK23: ='Fin. Data'!L58 -> 6963.3
B24: Working capital flows | C24: =Inputs!B62/(Inputs!B6-Inputs!C6) -> 0.94972506 | D24: =Inputs!C62/(Inputs!C6-Inputs!D6) -> 1.464947 | E24: =Inputs!D62/(Inputs!D6-Inputs!E6) -> 4.1253644 | F24: =Inputs!E62/(Inputs!E6-Inputs!F6) -> 1.8043478 | G24: =Inputs!F62/(Inputs!F6-Inputs!G6) -> 0.59296703 | H24: =Inputs!G62/(Inputs!G6-Inputs!H6) -> 0.52787194 | I24: =Inputs!H62/(Inputs!H6-Inputs!I6) -> 1.3956607 | J24: =Inputs!I62/(Inputs!I6-Inputs!J6) -> 0.65138552 | ... M24: =Inputs!L62/(Inputs!L6-Inputs!M6) -> -0.00086889361 | O24: =AVERAGE(C24:M24) -> 1.1236879 | P24: =AVERAGE(C24:G24) -> 1.7874703 | Q24: =AVERAGE(C24:E24) -> 2.1800122 | S24: 1.2 | T24: 1.8 | V24: % Change in Revenues | Z24: PPE (Gross) | AA24: 10788.3 | AB24: 9257.1 | AC24: 8011.9 | AD24: 7555.8 | AE24: 6791.2 | AF24: 6972.5 | AG24: 6273.7 | AH24: 5209.8 | AI24: 4512.7 | AJ24: 3731.8 | AK24: 2939
B25: Intangible Assets | C25: =AA26/AB26-1 -> 0.0013195997 | D25: =AB26/AC26-1 -> -0.0098359466 | E25: =AC26/AD26-1 -> 0.0084550346 | F25: =AD26/AE26-1 -> 0.0048549046 | G25: =AE26/AF26-1 -> -0.14983897 | H25: =AF26/AG26-1 -> -0.032286371 | I25: =AG26/AH26-1 -> -0.021582734 | J25: =AH26/AI26-1 -> -0.0076679006 | ... M25: =AK26/AL26-1 -> 2.7079412 | O25: =AVERAGE(C25:M25) -> 0.23235402 | P25: =AVERAGE(C25:G25) -> -0.029009075 | Q25: =AVERAGE(C25:E25) -> -2.0437421e-05 | S25: - - | T25: - - | V25: Growing with Amortization | Z25: Right of use assets | AA25: 633.5 | AB25: 469.4 | AC25: 500.7 | AD25: 494.9 | AE25: 508 | AF25: 0 | AG25: 0 | AH25: 0 | AI25: 0 | AJ25: 0 | AK25: 0
B26: CAPEX | C26: =Inputs!C65/Inputs!C6 -> -0.1088272 | D26: =Inputs!D65/Inputs!D6 -> -0.11594318 | E26: =Inputs!E65/Inputs!E6 -> -0.098167129 | F26: =Inputs!F65/Inputs!F6 -> -0.086078984 | G26: =Inputs!G65/Inputs!G6 -> -0.10029571 | H26: =Inputs!H65/Inputs!H6 -> -0.13870798 | I26: =Inputs!I65/Inputs!I6 -> -0.12376731 | J26: =Inputs!J65/Inputs!J6 -> -0.13610958 | ... M26: =Inputs!M65/Inputs!M6 -> -0.022209506 | O26: =AVERAGE(C26:M26) -> -0.099578596 | P26: =AVERAGE(C26:G26) -> -0.10186244 | Q26: =AVERAGE(C26:E26) -> -0.10764584 | S26: 0.14 | T26: 0.13 | V26: % Revenue | Z26: Intangible assets (Net) | AA26: 2731.7 | AB26: 2728.1 | AC26: 2755.2 | AD26: 2732.1 | AE26: 2718.9 | AF26: 3198.1 | AG26: 3304.8 | AH26: 3377.7 | AI26: 3403.8 | AJ26: 3181 | AK26: 3231.1 | AL26: 871.4
B27: Acquisition factor | C27: =Inputs!B66/Inputs!B6 -> 0.0047983296 | D27: =Inputs!C66/Inputs!C6 -> 0.0030467808 | E27: =Inputs!D66/Inputs!D6 -> -0.0012584035 | F27: =Inputs!E66/Inputs!E6 -> 0.08789423 | G27: =Inputs!F66/Inputs!F6 -> 0.022388686 | H27: =Inputs!G66/Inputs!G6 -> -0.49493593 | I27: =Inputs!H66/Inputs!H6 -> -0.047593935 | J27: =Inputs!I66/Inputs!I6 -> -0.073068267 | ... M27: =Inputs!L66/Inputs!L6 -> -0.96170676 | O27: =AVERAGE(C27:M27) -> -0.15572163 | P27: =AVERAGE(C27:G27) -> 0.023373924 | Q27: =AVERAGE(C27:E27) -> 0.002195569 | S27: 0.005 | T27: -0.03 | V27: % Revenue | Z27: Total Depreciation & amortization expense | AA27: 429.2 | AB27: 387 | AC27: 342.4 | AD27: 299.1 | AE27: 332.2 | AF27: 339.1 | AG27: 299.7 | AH27: 247.9 | AI27: 221 | AJ27: 202 | AK27: 155.3
B28: Dividends | C28: =Inputs!B73/Inputs!B12 -> -0.37038296 | D28: =Inputs!C73/Inputs!C12 -> 15.264935 | E28: =Inputs!D73/Inputs!D12 -> -573 | F28: =Inputs!E73/Inputs!E12 -> -0.2830003 | G28: =Inputs!F73/Inputs!F12 -> -26.598131 | H28: =Inputs!G73/Inputs!G12 -> -0.16122691 | I28: =Inputs!H73/Inputs!H12 -> -0.1716578 | J28: =Inputs!I73/Inputs!I12 -> -0.20471674 | ... M28: =Inputs!L73/Inputs!L12 -> 0 | O28: =AVERAGE(C28,F28,H28:K28) -> -0.23646338 | P28: =AVERAGE(C28,F28) -> -0.32669163 | Q28: - | S28: -0.4 | T28: -0.5 | V28: % Net Income
B29: Repurchases | C29: =Inputs!B74/Inputs!B12 -> -0.14145706 | D29: =Inputs!C74/Inputs!C12 -> 44.161039 | E29: =Inputs!D74/Inputs!D12 -> -1390.5 | F29: =Inputs!E74/Inputs!E12 -> -0.51476523 | G29: =Inputs!F74/Inputs!F12 -> -48.873832 | H29: =Inputs!G74/Inputs!G12 -> -0.28790726 | I29: =Inputs!H74/Inputs!H12 -> -0.2200103 | J29: =Inputs!I74/Inputs!I12 -> -0.2943737 | ... M29: =Inputs!L74/Inputs!L12 -> 0 | O29: =AVERAGE(C29,F29,H29:L29) -> -0.38898459 | P29: =AVERAGE(C29,F29) -> -0.32811115 | Q29: - | S29: 0.14 | T29: 0.5 | V29: % Net Income | Z29: Depreciation expense | AA29: =AA27-AA30 -> 427.9 | AB29: =AB27-AB30 -> 383.8 | AC29: =AC27-AC30 -> 337.3 | AD29: =AD27-AD30 -> 293.8 | AE29: =AE27-AE30 -> 326.5 | AF29: =AF27-AF30 -> 333.1 | AG29: =AG27-AG30 -> 293.8 | AH29: =AH27-AH30 -> 237.5 | ... AK29: =AK27-AK30 -> 139.8
B30: Leases | C30: =Inputs!B72/Inputs!B6 -> -0.00097371961 | D30: =Inputs!C72/Inputs!C6 -> -0.00093096079 | E30: =Inputs!D72/Inputs!D6 -> -0.00066888115 | F30: =Inputs!E72/Inputs!E6 -> -0.0012188186 | G30: =Inputs!F72/Inputs!F6 -> -0.0016539821 | H30: =Inputs!G72/Inputs!G6 -> 0 | I30: =Inputs!H72/Inputs!H6 -> 0 | J30: =Inputs!I72/Inputs!I6 -> 0 | ... M30: =Inputs!L72/Inputs!L6 -> 0 | O30: =AVERAGE(C30:M30) -> -0.00049512384 | P30: =AVERAGE(C30:G30) -> -0.0010892725 | Q30: =AVERAGE(C30:E30) -> -0.00085785385 | S30: 0.001 | T30: 0.001 | V30: % Revenue | Z30: Amortization expense | AA30: 1.3 | AB30: 3.2 | AC30: 5.1 | AD30: 5.3 | AE30: 5.7 | AF30: 6 | AG30: 5.9 | AH30: 10.4 | AI30: 40.7 | AJ30: 40 | AK30: 15.5
B31: Total Debt | C31: ='Fin. Data'!B58/'Fin. Data'!B19 -> 3.0586661 | D31: ='Fin. Data'!C58/'Fin. Data'!C19 -> 2.4505892 | E31: ='Fin. Data'!D58/'Fin. Data'!D19 -> 2.5291772 | F31: ='Fin. Data'!E58/'Fin. Data'!E19 -> 3.7170717 | G31: ='Fin. Data'!F58/'Fin. Data'!F19 -> 2.4716915 | H31: ='Fin. Data'!G58/'Fin. Data'!G19 -> 17.930603 | I31: ='Fin. Data'!H58/'Fin. Data'!H19 -> 4.6646671 | J31: ='Fin. Data'!I58/'Fin. Data'!I19 -> 3.4651538 | ... M31: ='Fin. Data'!L58/'Fin. Data'!L19 -> -9.0762513 | O31: =AVERAGE(C31:M31) -> 3.6117314 | P31: =AVERAGE(C31:G31) -> 2.8454392 | Q31: =AVERAGE(C31:E31) -> 2.6794775 | S31: - | T31: - | V31: Check assumptions
B34: Forecasts
D36: Short-term | H36: Long-term
B37: Base Scenario | C37: Time Period (Years) | D37: 2025 | E37: =D37+1 -> 2026 | F37: =E37+1 -> 2027 | G37: =F37+1 -> 2028 | H37: =G37+1 -> 2029 | I37: =H37+1 -> 2030 | J37: =I37+1 -> 2031 | K37: =J37+1 -> 2032 | L37: =K37+1 -> 2033 | ... AD37: =AC37+1 -> 2051
C38: Forecasted Yearly Revenues | D38: =Inputs!B6*(1+Assumptions!D39) -> 10459.89 | E38: =D38*(1+E39) -> 10930.585 | F38: =E38*(1+F39) -> 11367.808 | G38: =F38*(1+G39) -> 11822.521 | H38: =G38*(1+H39) -> 12177.196 | I38: =H38*(1+I39) -> 12542.512 | J38: =I38*(1+J39) -> 12918.788 | K38: =J38*(1+K39) -> 13306.351 | L38: =K38*(1+L39) -> 13705.542 | ... AD38: =AC38*(1+AD39) -> 23332.768
C39: Forecasted Revenues Growth | D39: 0.05 | E39: 0.045 | F39: =$S$9 -> 0.04 | G39: =$S$9 -> 0.04 | H39: =T9 -> 0.03 | I39: =T9 -> 0.03 | J39: =$T$9 -> 0.03 | K39: =$T$9 -> 0.03 | L39: =$T$9 -> 0.03 | M39: =$T$9 -> 0.03 | N39: =$T$9 -> 0.03 | O39: =$T$9 -> 0.03 | P39: =$T$9 -> 0.03 | Q39: =$T$9 -> 0.03 | ... AC39: =$T$9 -> 0.03 | AD39: =T9 -> 0.03
C40: Operating Margin | D40: =S10 -> 0.33 | E40: =S10 -> 0.33 | F40: =S10 -> 0.33 | G40: =S10 -> 0.33 | H40: =T10 -> 0.345 | I40: =T10 -> 0.345 | J40: =$T$10 -> 0.345 | K40: =$T$10 -> 0.345 | L40: =$T$10 -> 0.345 | M40: =$T$10 -> 0.345 | N40: =$T$10 -> 0.345 | O40: =$T$10 -> 0.345 | P40: =$T$10 -> 0.345 | Q40: =$T$10 -> 0.345 | ... AC40: =$T$10 -> 0.345 | AD40: =T10 -> 0.345
B42: Bullish Scenario | C42: Time Period (Years) | D42: 2025 | E42: =D42+1 -> 2026 | F42: =E42+1 -> 2027 | G42: =F42+1 -> 2028 | H42: =G42+1 -> 2029 | I42: =H42+1 -> 2030 | J42: =I42+1 -> 2031 | K42: =J42+1 -> 2032 | L42: =K42+1 -> 2033 | ... AD42: =AC42+1 -> 2051
C43: Forecasted Yearly Revenues | D43: =Inputs!B6*(1+Assumptions!D44) -> 10559.508 | E43: =D43*(1+E44) -> 11140.281 | F43: =E43*(1+F44) -> 11697.295 | G43: =F43*(1+G44) -> 12223.673 | H43: =G43*(1+H44) -> 12590.383 | I43: =H43*(1+I44) -> 12968.095 | J43: =I43*(1+J44) -> 13357.138 | K43: =J43*(1+K44) -> 13757.852 | L43: =K43*(1+L44) -> 14170.588 | ... AD43: =AC43*(1+AD44) -> 24124.477
C44: Forecasted Revenues Growth | D44: 0.06 | E44: 0.055 | F44: 0.05 | G44: 0.045 | H44: 0.03 | I44: 0.03 | J44: 0.03 | K44: 0.03 | L44: 0.03 | M44: 0.03 | N44: 0.03 | O44: 0.03 | P44: 0.03 | Q44: 0.03 | R44: 0.03 | S44: 0.03 | T44: 0.03 | U44: 0.03 | V44: 0.03 | W44: 0.03 | X44: 0.03 | Y44: 0.03 | Z44: 0.03 | AA44: 0.03 | AB44: 0.03 | AC44: 0.03 | AD44: 0.03
C45: Operating Margin | D45: 0.325 | E45: 0.34 | F45: 0.34 | G45: 0.34 | H45: 0.35 | I45: 0.35 | J45: 0.35 | K45: 0.35 | L45: 0.35 | M45: 0.35 | N45: 0.35 | O45: 0.35 | P45: 0.35 | Q45: 0.35 | R45: 0.35 | S45: 0.35 | T45: 0.35 | U45: 0.35 | V45: 0.35 | W45: 0.35 | X45: 0.35 | Y45: 0.35 | Z45: 0.35 | AA45: 0.35 | AB45: 0.35 | AC45: 0.35 | AD45: 0.35
B47: Bearish Scenario | C47: Time Period (Years) | D47: 2025 | E47: =D47+1 -> 2026 | F47: =E47+1 -> 2027 | G47: =F47+1 -> 2028 | H47: =G47+1 -> 2029 | I47: =H47+1 -> 2030 | J47: =I47+1 -> 2031 | K47: =J47+1 -> 2032 | L47: =K47+1 -> 2033 | ... AD47: =AC47+1 -> 2051
C48: Forecasted Yearly Revenues | D48: =Inputs!B6*(1+Assumptions!D49) -> 10335.368 | E48: =D48*(1+E49) -> 10722.944 | F48: =E48*(1+F49) -> 11098.247 | G48: =F48*(1+G49) -> 11431.194 | H48: =G48*(1+H49) -> 11659.818 | I48: =H48*(1+I49) -> 11893.014 | J48: =I48*(1+J49) -> 12130.875 | K48: =J48*(1+K49) -> 12373.492 | L48: =K48*(1+L49) -> 12620.962 | ... AD48: =AC48*(1+AD49) -> 18025.842
C49: Forecasted Revenues Growth | D49: 0.0375 | E49: 0.0375 | F49: 0.035 | G49: 0.03 | H49: 0.02 | I49: 0.02 | J49: 0.02 | K49: 0.02 | L49: 0.02 | M49: 0.02 | N49: 0.02 | O49: 0.02 | P49: 0.02 | Q49: 0.02 | R49: 0.02 | S49: 0.02 | T49: 0.02 | U49: 0.02 | V49: 0.02 | W49: 0.02 | X49: 0.02 | Y49: 0.02 | Z49: 0.02 | AA49: 0.02 | AB49: 0.02 | AC49: 0.02 | AD49: 0.02
C50: Operating Margin | D50: 0.29 | E50: 0.28 | F50: 0.275 | G50: 0.275 | H50: 0.265 | I50: 0.265 | J50: 0.265 | K50: 0.265 | L50: 0.265 | M50: 0.265 | N50: 0.265 | O50: 0.265 | P50: 0.265 | Q50: 0.265 | R50: 0.265 | S50: 0.265 | T50: 0.265 | U50: 0.265 | V50: 0.265 | W50: 0.265 | X50: 0.265 | Y50: 0.265 | Z50: 0.265 | AA50: 0.265 | AB50: 0.265 | AC50: 0.265 | AD50: 0.265
B53: Debt
G56: Bonds (Only in USA/Canada and in Million $) | W56: Loans (Only in USA and in Million $)
G57: Issuance date | H57: Maturity Date | I57: Amount Outstanding | K57: Issued Amount | N57: Interest Rate (%) | P57: Interest Expense | R57: Maturity by fiscal year | T57: Interest payments | W57: Loan type | Y57: Issued date | Z57: Amount (in M of $) | AA57: Maturity date | AB57: Maturity by fiscal year
G58: Nov 2014 | H58: Nov 2024 | I58: 399.5 | K58: 400 | N58: 0.0475 | P58: =K58*N58 -> 19 | R58: 2025 | T58: May/Nov | W58: Other Loan | Y58: Dez 2020 | Z58: 20 | AA58: Dez 2030 | AB58: 2031
G59: Dec 2015 | H59: Dec 2025 | I59: 398.8 | K59: 400 | N59: 0.0475 | P59: =K59*N59 -> 19 | R59: 2026 | T59: Jun/Dec | W59: Term Loan | Y59: Mar 2021 | Z59: 750 | AA59: Mar 2026 | AB59: 2027
G60: Dec 2016 | H60: Dec 2026 | I60: 598.3 | K60: 600 | N60: 0.037 | P60: =K60*N60 -> 22.2 | R60: 2027 | T60: Jun/Dec | W60: Revolver/Line >= 1 Yr. | Y60: Abr 2022 | Z60: 2250 | AA60: Abr 2027 | AB60: 2028
G61: May 2017 | H61: May 2027 | I61: 498.2 | K61: 500 | N61: 0.035 | P61: =K61*N61 -> 17.5 | R61: 2028 | T61: May/Nov | W61: Term Loan A | Y61: Abr 2022 | Z61: 491.25 | AA61: Abr 2027 | AB61: 2028
G62: May 2017 | H62: May 2047 | I62: 493.9 | K62: 500 | N62: 0.045 | P62: =K62*N62 -> 22.5 | R62: 2048 | T62: May/Nov | W62: Delay Draw Term Loan | Y62: Ago 2022 | Z62: 1000 | AA62: Dez 2025 | AB62: 2026
G63: Feb 2018 | H63: Feb 2028 | I63: 697.1 | K63: 700 | N63: 0.036 | P63: =K63*N63 -> 25.2 | R63: 2029 | T63: Feb/Aug | W63: Total | Y63: - | Z63: =SUM(Z58:Z62) -> 4511.25 | AA63: - | AB63: -
G64: Feb 2018 | H64: Feb 2048 | I64: 593.2 | K64: 600 | N64: 0.041 | P64: =K64*N64 -> 24.6 | R64: 2048 | T64: Feb/Aug
G65: Oct 2018 | H65: Nov 2025 | I65: 498.8 | K65: 500 | N65: 0.044 | P65: =K65*N65 -> 22 | R65: 2026 | T65: May/Nov
G66: Oct 2018 | H66: Nov 2028 | I66: 497.3 | K66: 500 | N66: 0.0465 | P66: =K66*N66 -> 23.25 | R66: 2029 | T66: May/Nov
G67: Oct 2018 | H67: Nov 2048 | I67: 493.8 | K67: 500 | N67: 0.0525 | P67: =K67*N67 -> 26.25 | R67: 2049 | T67: May/Nov | W67: Annual report guidance for bonds repayment
G68: Jul 2019 | H68: Aug 2029 | I68: 796.1 | K68: 800 | N68: 0.0315 | P68: =K68*N68 -> 25.2 | R68: 2030 | T68: Feb/Aug
G69: Apr 2020 | H69: May 2030 | I69: 596.2 | K69: 600 | N69: 0.02875 | P69: =K69*N69 -> 17.25 | R69: 2051 | T69: May/Nov | W69: Fiscal 2025 | Y69: 957.5
G70: Apr 2020 | H70: May 2050 | I70: 590.6 | K70: 600 | N70: 0.0375 | P70: =K70*N70 -> 22.5 | R70: 2051 | T70: May/Nov | W70: Fiscal 2026 | Y70: 1404.9
G71: Jul 2021 | H71: Aug 2031 | I71: 990.5 | K71: 1000 | N71: 0.0225 | P71: =K71*N71 -> 22.5 | R71: 2032 | T71: Feb/Aug | W71: Fiscal 2027 | Y71: 603.8
G72: May 2022 | H72: May 2024 | I72: 549.8 | K72: 550 | N72: 0.036 | P72: =K72*N72 -> 19.8 | R72: 2025 | T72: May/Nov | W72: Fiscal 2028 | Y72: 1801.5
G73: May 2022 | H73: May 2027 | I73: 597.8 | K73: 600 | N73: 0.0435 | P73: =K73*N73 -> 26.1 | R73: 2028 | T73: May/Nov | W73: Fiscal 2029 | Y73: 900
G74: May 2022 | H74: May 2032 | I74: 694.4 | K74: 700 | N74: 0.0475 | P74: =K74*N74 -> 33.25 | R74: 2033 | T74: May/Nov
G75: Feb 2023 | H75: Feb 2026 | I75: 497.9 | K75: 500 | N75: 0.05 | P75: =K75*N75 -> 25 | R75: 2026 | T75: Feb/Aug
G76: May 2023 | H76: May 2033 | I76: 740.7 | K76: 750 | N76: 0.049 | P76: =K76*N76 -> 36.75 | R76: 2034 | T76: May/Nov
G77: Jan 2024 | H77: Jan 2029 | I77: 397.2 | K77: 400 | N77: 0.048 | P77: =K77*N77 -> 19.2 | R77: 2029 | T77: Jan/Jul
G78: Total | H78: - | I78: =SUM(I58:J77) -> 11620.1 | K78: =SUM(K59:M76) -> 10900 | N78: =AVERAGE(N58:O77) -> 0.0413125 | P78: =SUM(P58:Q77) -> 469.05 | R78: - | T78: -
B80: Maturity Year | C80: 2025 | D80: 2026 | E80: 2027 | F80: 2028 | G80: 2029 | H80: 2030 | I80: 2031 | J80: 2032 | K80: 2033 | L80: 2034 | M80: 2035 | N80: 2036 | O80: 2037 | P80: 2038 | Q80: 2039 | R80: 2040 | S80: 2041 | T80: 2042 | U80: 2043 | V80: 2044 | W80: 2045 | X80: 2046 | Y80: 2047 | Z80: 2048 | AA80: 2049 | AB80: 2050 | AC80: 2051
B81: Bonds Repayment | C81: =I58+I72 -> 949.3 | D81: =I59+I75+I65 -> 1395.5 | E81: =I60 -> 598.3 | F81: =I61+I73 -> 1096 | G81: =I77+I66+I63 -> 1591.6 | H81: =I68 -> 796.1 | J81: =I71 -> 990.5 | K81: =I74 -> 694.4 | L81: =I76 -> 740.7 | M81: =+C83 -> 400 | N81: =+D83 -> 1700 | O81: =+E83 -> 750 | P81: =F83-K82 -> 1000 | Q81: =G83 -> 1700 | R81: =H83 -> 1350 | S81: =I83 -> 450 | T81: =J83 -> 1500 | U81: =K83 -> 2600 | V81: =L83 -> 1000 | W81: =M83 -> 950 | X81: =N83 -> 1650 | Y81: =O83 -> 1000 | Z81: =I62+I64+P83 -> 2337.1 | AA81: =+I67+Q83 -> 2193.8 | AB81: =R83 -> 1350 | AC81: =I70+I69+S83 -> 2136.8
B82: Loans Repayment | D82: =Z62 -> 1000 | E82: =Z59 -> 750 | F82: =Z60+Z61 -> 2741.25 | I82: =Z58 -> 20 | K82: 2000
B83: Forecasted debt | C83: 400 | D83: 1700 | E83: 750 | F83: 3000 | G83: 1700 | H83: 1350 | I83: 450 | J83: 1500 | K83: 2600 | L83: 1000 | M83: 950 | N83: 1650 | O83: 1000 | P83: 1250 | Q83: 1700 | R83: 1350 | S83: 950 | T83: 1550 | U83: 2100 | V83: 900 | W83: 1000 | X83: 1400 | Y83: 1250 | Z83: 1650 | AA83: 1950 | AB83: 1000
B84: Total Debt | C84: =DCF!F44-C81-C82+C83 -> 12026.1 | D84: =C84-D81-D82+D83 -> 11330.6 | E84: =D84-E81-E82+E83 -> 10732.3 | F84: =E84-F81-F82+F83 -> 9895.05 | G84: =F84-G81-G82+G83 -> 10003.45 | H84: =G84-H81-H82+H83 -> 10557.35 | I84: =H84-I81-I82+I83 -> 10987.35 | J84: =I84-J81-J82+J83 -> 11496.85 | K84: =J84-K81-K82+K83 -> 11402.45 | ... AB84: =AA84-AB81-AB82+AB83 -> 11380.85
B87: Bloomberg and other data
B89: Average excise taxes (% of sales) | E89: Average gross revenues annual growth
B90: 10y | C90: -0.10966448 | E90: 3y | F90: =AVERAGE(D105:F105)/3 -> 0.015444161
B91: 5y | C91: -0.089469184 | E91: 5y | F91: =AVERAGE(D105:H105)/5 -> 0.0076548709
B92: 3y | C92: -0.083889252 | E92: 9y | F92: =AVERAGE(D105:O105)/9 -> 0.013830415
B94: bloomberg forecast | C94: 2025 | D94: 2026 | E94: 2027 | F94: 2028 | G94: 2029 | H94: 2030 | I94: 2031 | J94: 2032 | K94: 2033 | L94: 2034
B95: Operating profit | C95: 3527.2632 | D95: 3836.3 | E95: 4140.4667 | F95: 4413.375 | G95: 4620.3333 | H95: 4917.8 | I95: 4981 | J95: 5224.6667 | K95: 5471 | L95: 5725.3333
B96: Revenues | C96: 10387.333 | D96: 11040.286 | E96: 11761.6 | F96: 12449.25 | G96: 13066.333 | H96: 13948.4 | I96: 14386.667 | J96: 15045.333 | K96: 15717.667 | L96: 16407.333
B97: Operating margin | C97: =C95/C96 -> 0.3395735 | D97: =D95/D96 -> 0.34748195 | E97: =E95/E96 -> 0.3520326 | F97: =F95/F96 -> 0.35450931 | G97: =G95/G96 -> 0.35360596 | H97: =H95/H96 -> 0.3525709 | I97: =I95/I96 -> 0.34622335 | J97: =J95/J96 -> 0.34726161 | ... L97: =L95/L96 -> 0.34894966
B98: rev growth in % | C98: =(C96/Inputs!C6)*0.01 -> 0.010988864 | D98: =D95/C95-1 -> 0.087613775 | E98: =E95/D95-1 -> 0.079286465 | F98: =F95/E95-1 -> 0.065912457 | G98: =G95/F95-1 -> 0.046893439 | H98: =H95/G95-1 -> 0.064382079 | I98: =I95/H95-1 -> 0.012851275 | J98: =J95/I95-1 -> 0.048919226 | K98: =K95/J95-1 -> 0.047148143 | L98: =L95/K95-1 -> 0.04648754
D101: 2024 | E101: =D101-1 -> 2023 | F101: =E101-1 -> 2022 | G101: =F101-1 -> 2021 | H101: =G101-1 -> 2020 | I101: =H101-1 -> 2019 | J101: =I101-1 -> 2018 | K101: =J101-1 -> 2017 | L101: =K101-1 -> 2016 | ... P101: =O101-1 -> 2012
B102: Excise taxes (as % of total sales [not net]) | D102: -0.081323405 | E102: -0.083020165 | F102: -0.087324187 | G102: -0.094080593 | H102: -0.10159757 | I102: -0.10456333 | J102: -0.10839958 | K102: -0.11059775 | L102: -0.11500085 | M102: -0.11963447 | N102: -0.12563593 | O102: -0.15503139 | P102: -0.13942906
B103: Excise taxes (M of $) | D103: -749.2 | E103: -724.6 | F103: -708.4 | G103: -740.8 | H103: -769.5 | I103: -768.3 | J103: -741.8 | K103: -730.1 | L103: -675.4 | M103: -644.1 | N103: -543.3 | O103: -375.3 | P103: -324.8
B104: Gross sales value | D104: 10711 | E104: 10177.2 | F104: 9529.1 | G104: 9355.7 | H104: 9113 | I104: 8884.3 | J104: 8326.8 | K104: 8061.6 | L104: 7223.8 | M104: 6672.1 | N104: 5411 | O104: 3171.4 | P104: 2979.1
D105: =D104/E104-1 -> 0.052450576 | E105: =E104/F104-1 -> 0.068012719 | F105: =F104/G104-1 -> 0.018534156 | G105: =G104/H104-1 -> 0.026632284 | H105: =H104/I104-1 -> 0.025742039 | I105: =I104/J104-1 -> 0.066952491 | J105: =J104/K104-1 -> 0.032896695 | K105: =K104/L104-1 -> 0.11597774 | ... O105: =O104/P104-1 -> 0.064549696 | P105: =P104/#REF!-1 -> #REF!
C106: bloomberg Dividends estimates | K106: bloomberg Multiples estimates
B124: SG&A
C126: 2013 | D126: =C126+1 -> 2014 | E126: =D126+1 -> 2015 | F126: =E126+1 -> 2016 | G126: =F126+1 -> 2017 | H126: =G126+1 -> 2018 | I126: =H126+1 -> 2019 | J126: =I126+1 -> 2020 | K126: =J126+1 -> 2021 | ... N126: =M126+1 -> 2024
B127: Operating margin | C127: 522.9 | D127: 795.7 | E127: 1500.2 | F127: 1765.1 | G127: 2399.4 | H127: 2284.5 | I127: 2412.2 | J127: 2154.5 | K127: 2791.1 | L127: 2331.7 | M127: 2842.9 | N127: 3169.7
B128: Net revenues | C128: 2796.1 | D128: 4867.7 | E128: 6028 | F128: 6548.4 | G128: 7331.5 | H128: 7585 | I128: 8116 | J128: 8343.5 | K128: 8614.9 | L128: 8820.7 | M128: 9452.6 | N128: 9961.8
B129: Operating margin as % of net sales | C129: =C127/C128 -> 0.18701048 | D129: =D127/D128 -> 0.16346529 | E129: =E127/E128 -> 0.24887193 | F129: =F127/F128 -> 0.26954676 | G129: =G127/G128 -> 0.32727273 | H129: =H127/H128 -> 0.30118655 | I129: =I127/I128 -> 0.29721538 | J129: =J127/J128 -> 0.25822497 | ... N129: =N127/N128 -> 0.31818547
B131: COGS | C131: 1687.8 | D131: 2876 | E131: 3357.2 | F131: 3606.1 | G131: 3802.1 | H131: 3767.8 | I131: 4037.5 | J131: 4191.6 | K131: 4148.9 | L131: 4121.9 | M131: 4682.6 | N131: 4944.3
B132: COGS as % of net sales | C132: =C131/C128 -> 0.60362648 | D132: =D131/D128 -> 0.59083345 | E132: =E131/E128 -> 0.55693431 | F132: =F131/F128 -> 0.55068414 | G132: =G131/G128 -> 0.51859783 | H132: =H131/H128 -> 0.49674357 | I132: =I131/I128 -> 0.49747413 | J132: =J131/J128 -> 0.5023791 | ... N132: =N131/N128 -> 0.49632597
B133: COGS growth | C133: =Inputs!M7/Inputs!N7-1 -> 0.043498729 | D133: =D127/C127-1 -> 0.52170587 | E133: =E127/D127-1 -> 0.88538394 | F133: =F127/E127-1 -> 0.17657646 | G133: =G127/F127-1 -> 0.35935641 | H133: =H127/G127-1 -> -0.047886972 | I133: =I127/H127-1 -> 0.055898446 | J133: =J127/I127-1 -> -0.10683194 | K133: =K127/J127-1 -> 0.29547459 | ... N133: =N127/M127-1 -> 0.11495304
B134: Revenues growth | C134: =C128/Inputs!N6-1 -> 0.053422748 | D134: =D128/C128-1 -> 0.7408891 | E134: =E128/D128-1 -> 0.2383672 | F134: =F128/E128-1 -> 0.086330458 | G134: =G128/F128-1 -> 0.11958646 | H134: =H128/G128-1 -> 0.034576826 | I134: =I128/H128-1 -> 0.070006592 | J134: =J128/I128-1 -> 0.02803105 | K134: =K128/J128-1 -> 0.032528315 | ... N134: =N128/M128-1 -> 0.053868777
B135: Correlation between growths (11y) | C135: =CORREL(C133:N133,C134:N134) -> 0.58470256
C137: 2013 | D137: =C137+1 -> 2014 | E137: =D137+1 -> 2015 | F137: =E137+1 -> 2016 | G137: =F137+1 -> 2017 | H137: =G137+1 -> 2018 | I137: =H137+1 -> 2019 | J137: =I137+1 -> 2020 | K137: =J137+1 -> 2021 | ... N137: =M137+1 -> 2024
B138: SG&A expenses | C138: 585.4 | D138: 895.1 | E138: 1078.4 | F138: 1177.2 | G138: 1392.4 | H138: 1532.7 | I138: 1668.1 | J138: 1621.8 | K138: 1665.1 | L138: 1709.7 | M138: 1926.1 | N138: 1847.8
B139: SG&A expenses as % of net sales | C139: =C138/C128 -> 0.20936304 | D139: =D138/D128 -> 0.18388561 | E139: =E138/E128 -> 0.17889847 | F139: =F138/F128 -> 0.1797691 | G139: =G138/G128 -> 0.18992021 | H139: =H138/H128 -> 0.20206987 | I139: =I138/I128 -> 0.20553228 | J139: =J138/J128 -> 0.19437886 | ... N139: =N138/N128 -> 0.18548857
B140: Marketing expenses | C140: 121.9 | D140: 278.5 | E140: 406.1 | F140: 468.3 | G140: 555.8 | H140: 615.7 | I140: 700.8 | J140: 769.5 | K140: 805 | L140: 824.6 | M140: 860.8 | N140: 853.5
B141: Marketing expenses as % of net sales | C141: =C140/C128 -> 0.043596438 | D141: =D140/D128 -> 0.057213879 | E141: =E140/E128 -> 0.067368945 | F141: =F140/F128 -> 0.071513652 | G141: =G140/G128 -> 0.075809862 | H141: =H140/H128 -> 0.081173368 | I141: =I140/I128 -> 0.086347955 | J141: =J140/J128 -> 0.092227482 | ... N141: =N140/N128 -> 0.085677287
B142: Marketing expenses as % of SG&A | C142: =C140/C138 -> 0.20823369 | D142: =D140/D138 -> 0.31113842 | E142: =E140/E138 -> 0.37657641 | F142: =F140/F138 -> 0.39780836 | G142: =G140/G138 -> 0.39916691 | H142: =H140/H138 -> 0.4017094 | I142: =I140/I138 -> 0.4201187 | J142: =J140/J138 -> 0.47447281 | ... N142: =N140/N138 -> 0.46190064
B143: SG&A expenses growth | C143: - | D143: =D138/C138-1 -> 0.52903997 | E143: =E138/D138-1 -> 0.20478159 | F143: =F138/E138-1 -> 0.091617211 | G143: =G138/F138-1 -> 0.18280666 | H143: =H138/G138-1 -> 0.10076128 | I143: =I138/H138-1 -> 0.088340836 | J143: =J138/I138-1 -> -0.02775613 | K143: =K138/J138-1 -> 0.02669873 | ... N143: =N138/M138-1 -> -0.040652095
...

Sheet Fin. Data
A1: =Inputs!I3 -> #VALUE!
A2: =Inputs!H2 -> Figures in Millions of USD
A3: Results
B4: =OP!J20 -> 2024 | C4: =B4-1 -> 2023 | D4: =C4-1 -> 2022 | E4: =D4-1 -> 2021 | F4: =E4-1 -> 2020 | G4: =F4-1 -> 2019 | H4: =G4-1 -> 2018 | I4: =H4-1 -> 2017 | J4: =I4-1 -> 2016 | ... M4: =L4-1 -> 2013
A5: Net Sales | B5: =_xlfn.XLOOKUP($A5,Inputs!$A:$A,Inputs!B:B,,0) -> 9961.8 | C5: =_xlfn.XLOOKUP($A5,Inputs!$A:$A,Inputs!C:C,,0) -> 9452.6 | D5: =_xlfn.XLOOKUP($A5,Inputs!$A:$A,Inputs!D:D,,0) -> 8820.7 | E5: =_xlfn.XLOOKUP($A5,Inputs!$A:$A,Inputs!E:E,,0) -> 8614.9 | F5: =_xlfn.XLOOKUP($A5,Inputs!$A:$A,Inputs!F:F,,0) -> 8343.5 | G5: =_xlfn.XLOOKUP($A5,Inputs!$A:$A,Inputs!G:G,,0) -> 8116 | H5: =_xlfn.XLOOKUP($A5,Inputs!$A:$A,Inputs!H:H,,0) -> 7585 | I5: =_xlfn.XLOOKUP($A5,Inputs!$A:$A,Inputs!I:I,,0) -> 7331.5 | J5: =_xlfn.XLOOKUP($A5,Inputs!$A:$A,Inputs!J:J,,0) -> 6548.4 | K5: =_xlfn.XLOOKUP($A5,Inputs!$A:$A,Inputs!K:K,,0) -> 6028 | L5: =_xlfn.XLOOKUP($A5,Inputs!$A:$A,Inputs!L:L,,0) -> 4867.7 | M5: =_xlfn.XLOOKUP($A5,Inputs!$A:$A,Inputs!M:M,,0) -> 2796.1
A6: Growth vs. Previous year | B6: =IFERROR(B5/C5-1,"-") -> 0.053868777 | C6: =IFERROR(C5/D5-1,"-") -> 0.071638305 | D6: =IFERROR(D5/E5-1,"-") -> 0.023888844 | E6: =IFERROR(E5/F5-1,"-") -> 0.032528315 | F6: =IFERROR(F5/G5-1,"-") -> 0.02803105 | G6: =IFERROR(G5/H5-1,"-") -> 0.070006592 | H6: =IFERROR(H5/I5-1,"-") -> 0.034576826 | I6: =IFERROR(I5/J5-1,"-") -> 0.11958646 | ... L6: =IFERROR(L5/M5-1,"-") -> 0.7408891 | M6: =IFERROR(M5/#REF!-1,"-") -> -
A7: Gross Profit | B7: =_xlfn.XLOOKUP($A7,Inputs!$A:$A,Inputs!B:B,,0) -> 5017.5 | C7: =_xlfn.XLOOKUP($A7,Inputs!$A:$A,Inputs!C:C,,0) -> 4770 | D7: =_xlfn.XLOOKUP($A7,Inputs!$A:$A,Inputs!D:D,,0) -> 4698.8 | E7: =_xlfn.XLOOKUP($A7,Inputs!$A:$A,Inputs!E:E,,0) -> 4466 | F7: =_xlfn.XLOOKUP($A7,Inputs!$A:$A,Inputs!F:F,,0) -> 4151.9 | G7: =_xlfn.XLOOKUP($A7,Inputs!$A:$A,Inputs!G:G,,0) -> 4078.5 | H7: =_xlfn.XLOOKUP($A7,Inputs!$A:$A,Inputs!H:H,,0) -> 3817.2 | I7: =_xlfn.XLOOKUP($A7,Inputs!$A:$A,Inputs!I:I,,0) -> 3529.4 | J7: =_xlfn.XLOOKUP($A7,Inputs!$A:$A,Inputs!J:J,,0) -> 2942.3 | K7: =_xlfn.XLOOKUP($A7,Inputs!$A:$A,Inputs!K:K,,0) -> 2670.8 | L7: =_xlfn.XLOOKUP($A7,Inputs!$A:$A,Inputs!L:L,,0) -> 1991.7 | M7: =_xlfn.XLOOKUP($A7,Inputs!$A:$A,Inputs!M:M,,0) -> 1108.3
A8: % over sales | B8: =IFERROR(B7/B$5,"-") -> 0.50367403 | C8: =IFERROR(C7/C$5,"-") -> 0.50462307 | D8: =IFERROR(D7/D$5,"-") -> 0.53270149 | E8: =IFERROR(E7/E$5,"-") -> 0.51840416 | F8: =IFERROR(F7/F$5,"-") -> 0.4976209 | G8: =IFERROR(G7/G$5,"-") -> 0.50252587 | H8: =IFERROR(H7/H$5,"-") -> 0.50325643 | I8: =IFERROR(I7/I$5,"-") -> 0.48140217 | ... M8: =IFERROR(M7/M$5,"-") -> 0.39637352
A9: Operating expenses | B9: =B5-B11 -> 6792.1 | C9: =C5-C11 -> 6609.7 | D9: =D5-D11 -> 6489 | E9: =E5-E11 -> 5823.8 | F9: =F5-F11 -> 6189 | G9: =G5-G11 -> 5703.8 | H9: =H5-H11 -> 5300.5 | I9: =I5-I11 -> 4932.1 | ... M9: =M5-M11 -> 2273.2
A10: % over sales | B10: =IFERROR(B9/B$5,"-") -> 0.68181453 | C10: =IFERROR(C9/C$5,"-") -> 0.69924677 | D10: =IFERROR(D9/D$5,"-") -> 0.7356559 | E10: =IFERROR(E9/E$5,"-") -> 0.67601481 | F10: =IFERROR(F9/F$5,"-") -> 0.74177503 | G10: =IFERROR(G9/G$5,"-") -> 0.70278462 | H10: =IFERROR(H9/H$5,"-") -> 0.69881345 | I10: =IFERROR(I9/I$5,"-") -> 0.67272727 | ... M10: =IFERROR(M9/M$5,"-") -> 0.81298952
A11: Operating Income | B11: =_xlfn.XLOOKUP($A11,Inputs!$A:$A,Inputs!B:B,,0) -> 3169.7 | C11: =_xlfn.XLOOKUP($A11,Inputs!$A:$A,Inputs!C:C,,0) -> 2842.9 | D11: =_xlfn.XLOOKUP($A11,Inputs!$A:$A,Inputs!D:D,,0) -> 2331.7 | E11: =_xlfn.XLOOKUP($A11,Inputs!$A:$A,Inputs!E:E,,0) -> 2791.1 | F11: =_xlfn.XLOOKUP($A11,Inputs!$A:$A,Inputs!F:F,,0) -> 2154.5 | G11: =_xlfn.XLOOKUP($A11,Inputs!$A:$A,Inputs!G:G,,0) -> 2412.2 | H11: =_xlfn.XLOOKUP($A11,Inputs!$A:$A,Inputs!H:H,,0) -> 2284.5 | I11: =_xlfn.XLOOKUP($A11,Inputs!$A:$A,Inputs!I:I,,0) -> 2399.4 | J11: =_xlfn.XLOOKUP($A11,Inputs!$A:$A,Inputs!J:J,,0) -> 1765.1 | K11: =_xlfn.XLOOKUP($A11,Inputs!$A:$A,Inputs!K:K,,0) -> 1500.2 | L11: =_xlfn.XLOOKUP($A11,Inputs!$A:$A,Inputs!L:L,,0) -> 795.7 | M11: =_xlfn.XLOOKUP($A11,Inputs!$A:$A,Inputs!M:M,,0) -> 522.9
A12: Operating Margin | B12: =IFERROR(B11/B$5,"-") -> 0.31818547 | C12: =IFERROR(C11/C$5,"-") -> 0.30075323 | D12: =IFERROR(D11/D$5,"-") -> 0.2643441 | E12: =IFERROR(E11/E$5,"-") -> 0.32398519 | F12: =IFERROR(F11/F$5,"-") -> 0.25822497 | G12: =IFERROR(G11/G$5,"-") -> 0.29721538 | H12: =IFERROR(H11/H$5,"-") -> 0.30118655 | I12: =IFERROR(I11/I$5,"-") -> 0.32727273 | ... M12: =IFERROR(M11/M$5,"-") -> 0.18701048
A13: Growth vs. Previous year | B13: =IFERROR(B12/C12-1,"-") -> 0.057961926 | C13: =IFERROR(C12/D12-1,"-") -> 0.13773386 | D13: =IFERROR(D12/E12-1,"-") -> -0.18408585 | E13: =IFERROR(E12/F12-1,"-") -> 0.25466253 | F13: =IFERROR(F12/G12-1,"-") -> -0.13118571 | G13: =IFERROR(G12/H12-1,"-") -> -0.013185102 | H13: =IFERROR(H12/I12-1,"-") -> -0.079707757 | I13: =IFERROR(I12/J12-1,"-") -> 0.21415938 | ... L13: =IFERROR(L12/M12-1,"-") -> -0.12590304 | M13: =IFERROR(M12/#REF!-1,"-") -> -
A14: Net Financial Cost | B14: =_xlfn.XLOOKUP($A14,Inputs!$A:$A,Inputs!B:B,,0) -> -435.4 | C14: =_xlfn.XLOOKUP($A14,Inputs!$A:$A,Inputs!C:C,,0) -> -398.7 | D14: =_xlfn.XLOOKUP($A14,Inputs!$A:$A,Inputs!D:D,,0) -> -356.4 | E14: =_xlfn.XLOOKUP($A14,Inputs!$A:$A,Inputs!E:E,,0) -> -385.7 | F14: =_xlfn.XLOOKUP($A14,Inputs!$A:$A,Inputs!F:F,,0) -> -431.1 | G14: =_xlfn.XLOOKUP($A14,Inputs!$A:$A,Inputs!G:G,,0) -> -367.1 | H14: =_xlfn.XLOOKUP($A14,Inputs!$A:$A,Inputs!H:H,,0) -> -429 | I14: =_xlfn.XLOOKUP($A14,Inputs!$A:$A,Inputs!I:I,,0) -> -333.3 | J14: =_xlfn.XLOOKUP($A14,Inputs!$A:$A,Inputs!J:J,,0) -> -315 | K14: =_xlfn.XLOOKUP($A14,Inputs!$A:$A,Inputs!K:K,,0) -> -342.1 | L14: =_xlfn.XLOOKUP($A14,Inputs!$A:$A,Inputs!L:L,,0) -> -323.2 | M14: =_xlfn.XLOOKUP($A14,Inputs!$A:$A,Inputs!M:M,,0) -> -239.6
A15: Other Expenses (Revenues) | B15: =_xlfn.XLOOKUP($A15,Inputs!$A:$A,Inputs!B:B,,0) -> -512.5 | C15: =_xlfn.XLOOKUP($A15,Inputs!$A:$A,Inputs!C:C,,0) -> -2060.6 | D15: =_xlfn.XLOOKUP($A15,Inputs!$A:$A,Inputs!D:D,,0) -> -1664.9 | E15: =_xlfn.XLOOKUP($A15,Inputs!$A:$A,Inputs!E:E,,0) -> 137.5 | F15: =_xlfn.XLOOKUP($A15,Inputs!$A:$A,Inputs!F:F,,0) -> -2668.6 | G15: =_xlfn.XLOOKUP($A15,Inputs!$A:$A,Inputs!G:G,,0) -> 2099.9 | H15: =_xlfn.XLOOKUP($A15,Inputs!$A:$A,Inputs!H:H,,0) -> 487.2 | I15: =_xlfn.XLOOKUP($A15,Inputs!$A:$A,Inputs!I:I,,0) -> 27.3 | J15: =_xlfn.XLOOKUP($A15,Inputs!$A:$A,Inputs!J:J,,0) -> 51.1 | K15: =_xlfn.XLOOKUP($A15,Inputs!$A:$A,Inputs!K:K,,0) -> 21.5 | L15: =_xlfn.XLOOKUP($A15,Inputs!$A:$A,Inputs!L:L,,0) -> 1729.8 | M15: =_xlfn.XLOOKUP($A15,Inputs!$A:$A,Inputs!M:M,,0) -> 233.1
A16: EBIT | B16: =B11-B15 -> 3682.2 | C16: =C11-C15 -> 4903.5 | D16: =D11-D15 -> 3996.6 | E16: =E11-E15 -> 2653.6 | F16: =F11-F15 -> 4823.1 | G16: =G11-G15 -> 312.3 | H16: =H11-H15 -> 1797.3 | I16: =I11-I15 -> 2372.1 | ... M16: =M11-M15 -> 289.8
A17: Depreciation & Amortization | B17: =_xlfn.XLOOKUP($A17,Inputs!$A:$A,Inputs!B:B,,0) -> 429.2 | C17: =_xlfn.XLOOKUP($A17,Inputs!$A:$A,Inputs!C:C,,0) -> 400 | D17: =_xlfn.XLOOKUP($A17,Inputs!$A:$A,Inputs!D:D,,0) -> 342.4 | E17: =_xlfn.XLOOKUP($A17,Inputs!$A:$A,Inputs!E:E,,0) -> 305.1 | F17: =_xlfn.XLOOKUP($A17,Inputs!$A:$A,Inputs!F:F,,0) -> 343.2 | G17: =_xlfn.XLOOKUP($A17,Inputs!$A:$A,Inputs!G:G,,0) -> 447.1 | H17: =_xlfn.XLOOKUP($A17,Inputs!$A:$A,Inputs!H:H,,0) -> 386.5 | I17: =_xlfn.XLOOKUP($A17,Inputs!$A:$A,Inputs!I:I,,0) -> 293.9 | J17: =_xlfn.XLOOKUP($A17,Inputs!$A:$A,Inputs!J:J,,0) -> 221 | K17: =_xlfn.XLOOKUP($A17,Inputs!$A:$A,Inputs!K:K,,0) -> 202 | L17: =_xlfn.XLOOKUP($A17,Inputs!$A:$A,Inputs!L:L,,0) -> 166.9 | M17: =_xlfn.XLOOKUP($A17,Inputs!$A:$A,Inputs!M:M,,0) -> 120.2
A18: Changes Net Working Capital | B18: =_xlfn.XLOOKUP($A18,Inputs!$A:$A,Inputs!B:B,,0) -> 41.1 | C18: =_xlfn.XLOOKUP($A18,Inputs!$A:$A,Inputs!C:C,,0) -> -37.2 | D18: =_xlfn.XLOOKUP($A18,Inputs!$A:$A,Inputs!D:D,,0) -> -883.3 | E18: =_xlfn.XLOOKUP($A18,Inputs!$A:$A,Inputs!E:E,,0) -> 223.9 | F18: =_xlfn.XLOOKUP($A18,Inputs!$A:$A,Inputs!F:F,,0) -> 664.3 | G18: =_xlfn.XLOOKUP($A18,Inputs!$A:$A,Inputs!G:G,,0) -> -917.5 | H18: =_xlfn.XLOOKUP($A18,Inputs!$A:$A,Inputs!H:H,,0) -> 989.1 | I18: =_xlfn.XLOOKUP($A18,Inputs!$A:$A,Inputs!I:I,,0) -> -267.2 | J18: =_xlfn.XLOOKUP($A18,Inputs!$A:$A,Inputs!J:J,,0) -> -1047.8 | K18: =_xlfn.XLOOKUP($A18,Inputs!$A:$A,Inputs!K:K,,0) -> 1012.4 | L18: =_xlfn.XLOOKUP($A18,Inputs!$A:$A,Inputs!L:L,,0) -> -804.2 | M18: =_xlfn.XLOOKUP($A18,Inputs!$A:$A,Inputs!M:M,,0) -> 704
A19: EBITDA | B19: =B11-B15+B17 -> 4111.4 | C19: =C11-C15+C17 -> 5303.5 | D19: =D11-D15+D17 -> 4339 | E19: =E11-E15+E17 -> 2958.7 | F19: =F11-F15+F17 -> 5166.3 | G19: =G11-G15+G17 -> 759.4 | H19: =H11-H15+H17 -> 2183.8 | I19: =I11-I15+I17 -> 2666 | ... M19: =M11-M15+M17 -> 410
A20: EBITDA Margin | B20: =IFERROR(B19/B$5,"-") -> 0.41271658 | C20: =IFERROR(C19/C$5,"-") -> 0.56106256 | D20: =IFERROR(D19/D$5,"-") -> 0.49191107 | E20: =IFERROR(E19/E$5,"-") -> 0.34343985 | F20: =IFERROR(F19/F$5,"-") -> 0.61920058 | G20: =IFERROR(G19/G$5,"-") -> 0.09356826 | H20: =IFERROR(H19/H$5,"-") -> 0.28791035 | I20: =IFERROR(I19/I$5,"-") -> 0.36363636 | ... M20: =IFERROR(M19/M$5,"-") -> 0.14663281
A21: Taxes | B21: =_xlfn.XLOOKUP($A21,Inputs!$A:$A,Inputs!B:B,,0) -> -456.6 | C21: =_xlfn.XLOOKUP($A21,Inputs!$A:$A,Inputs!C:C,,0) -> -422.1 | D21: =_xlfn.XLOOKUP($A21,Inputs!$A:$A,Inputs!D:D,,0) -> -309.4 | E21: =_xlfn.XLOOKUP($A21,Inputs!$A:$A,Inputs!E:E,,0) -> -511.1 | F21: =_xlfn.XLOOKUP($A21,Inputs!$A:$A,Inputs!F:F,,0) -> 966.6 | G21: =_xlfn.XLOOKUP($A21,Inputs!$A:$A,Inputs!G:G,,0) -> -685.9 | H21: =_xlfn.XLOOKUP($A21,Inputs!$A:$A,Inputs!H:H,,0) -> -11.9 | I21: =_xlfn.XLOOKUP($A21,Inputs!$A:$A,Inputs!I:I,,0) -> -554.2 | J21: =_xlfn.XLOOKUP($A21,Inputs!$A:$A,Inputs!J:J,,0) -> -440.6 | K21: =_xlfn.XLOOKUP($A21,Inputs!$A:$A,Inputs!K:K,,0) -> -343.4 | L21: =_xlfn.XLOOKUP($A21,Inputs!$A:$A,Inputs!L:L,,0) -> -259.2 | M21: =_xlfn.XLOOKUP($A21,Inputs!$A:$A,Inputs!M:M,,0) -> -128.6
A22: % Tax | B22: =IFERROR(B21/B$5,"-") -> -0.04583509 | C22: =IFERROR(C21/C$5,"-") -> -0.044654381 | D22: =IFERROR(D21/D$5,"-") -> -0.035076581 | E22: =IFERROR(E21/E$5,"-") -> -0.059327444 | F22: =IFERROR(F21/F$5,"-") -> 0.11585066 | G22: =IFERROR(G21/G$5,"-") -> -0.084512075 | H22: =IFERROR(H21/H$5,"-") -> -0.001568886 | I22: =IFERROR(I21/I$5,"-") -> -0.075591625 | ... M22: =IFERROR(M21/M$5,"-") -> -0.045992633
A23: Net Income | B23: =_xlfn.XLOOKUP($A23,Inputs!$A:$A,Inputs!B:B,,0) -> 1765.2 | C23: =_xlfn.XLOOKUP($A23,Inputs!$A:$A,Inputs!C:C,,0) -> -38.5 | D23: =_xlfn.XLOOKUP($A23,Inputs!$A:$A,Inputs!D:D,,0) -> 1 | E23: =_xlfn.XLOOKUP($A23,Inputs!$A:$A,Inputs!E:E,,0) -> 2031.8 | F23: =_xlfn.XLOOKUP($A23,Inputs!$A:$A,Inputs!F:F,,0) -> 21.4 | G23: =_xlfn.XLOOKUP($A23,Inputs!$A:$A,Inputs!G:G,,0) -> 3459.1 | H23: =_xlfn.XLOOKUP($A23,Inputs!$A:$A,Inputs!H:H,,0) -> 2330.8 | I23: =_xlfn.XLOOKUP($A23,Inputs!$A:$A,Inputs!I:I,,0) -> 1539.2 | J23: =_xlfn.XLOOKUP($A23,Inputs!$A:$A,Inputs!J:J,,0) -> 1060.6 | K23: =_xlfn.XLOOKUP($A23,Inputs!$A:$A,Inputs!K:K,,0) -> 836.2 | L23: =_xlfn.XLOOKUP($A23,Inputs!$A:$A,Inputs!L:L,,0) -> 1943.1 | M23: =_xlfn.XLOOKUP($A23,Inputs!$A:$A,Inputs!M:M,,0) -> 387.8
A24: Net Income Margin | B24: =IFERROR(B23/B$5,"-") -> 0.17719689 | C24: =IFERROR(C23/C$5,"-") -> -0.0040729535 | D24: =IFERROR(D23/D$5,"-") -> 0.00011336969 | E24: =IFERROR(E23/E$5,"-") -> 0.23584719 | F24: =IFERROR(F23/F$5,"-") -> 0.0025648709 | G24: =IFERROR(G23/G$5,"-") -> 0.42620749 | H24: =IFERROR(H23/H$5,"-") -> 0.30729071 | I24: =IFERROR(I23/I$5,"-") -> 0.20994339 | ... M24: =IFERROR(M23/M$5,"-") -> 0.13869318
A25: Growth vs. Previous year | B25: =IFERROR(B24/C24-1,"-") -> -44.505749 | C25: =IFERROR(C24/D24-1,"-") -> -36.926301 | D25: =IFERROR(D24/E24-1,"-") -> -0.99951931 | E25: =IFERROR(E24/F24-1,"-") -> 90.952854 | F25: =IFERROR(F24/G24-1,"-") -> -0.99398211 | G25: =IFERROR(G24/H24-1,"-") -> 0.38698465 | H25: =IFERROR(H24/I24-1,"-") -> 0.46368361 | I25: =IFERROR(I24/J24-1,"-") -> 0.29624112 | ... L25: =IFERROR(L24/M24-1,"-") -> 1.8781687 | M25: =IFERROR(M24/#REF!-1,"-") -> -
A26: Cash Generated | B26: =B39-C39 -> 18.9 | C26: =C39-D39 -> -65.9 | D26: =D39-E39 -> -261.2 | E26: =E39-F39 -> 379.2 | F26: =F39-G39 -> -12.2 | G26: =G39-H39 -> 3.3 | H26: =H39-I39 -> -87.1 | I26: =I39-J39 -> 94.3 | ... M26: =M39-N39 -> 331.5
A27: Dividends | B27: =_xlfn.XLOOKUP($A27,Inputs!$A:$A,Inputs!B:B,,0) -> -653.8 | C27: =_xlfn.XLOOKUP($A27,Inputs!$A:$A,Inputs!C:C,,0) -> -587.7 | D27: =_xlfn.XLOOKUP($A27,Inputs!$A:$A,Inputs!D:D,,0) -> -573 | E27: =_xlfn.XLOOKUP($A27,Inputs!$A:$A,Inputs!E:E,,0) -> -575 | F27: =_xlfn.XLOOKUP($A27,Inputs!$A:$A,Inputs!F:F,,0) -> -569.2 | G27: =_xlfn.XLOOKUP($A27,Inputs!$A:$A,Inputs!G:G,,0) -> -557.7 | H27: =_xlfn.XLOOKUP($A27,Inputs!$A:$A,Inputs!H:H,,0) -> -400.1 | I27: =_xlfn.XLOOKUP($A27,Inputs!$A:$A,Inputs!I:I,,0) -> -315.1 | J27: =_xlfn.XLOOKUP($A27,Inputs!$A:$A,Inputs!J:J,,0) -> -241.6 | K27: =_xlfn.XLOOKUP($A27,Inputs!$A:$A,Inputs!K:K,,0) -> 0 | L27: =_xlfn.XLOOKUP($A27,Inputs!$A:$A,Inputs!L:L,,0) -> 0 | M27: =_xlfn.XLOOKUP($A27,Inputs!$A:$A,Inputs!M:M,,0) -> 0
A28: Share buyback | B28: =_xlfn.XLOOKUP($A28,Inputs!$A:$A,Inputs!B:B,,0) -> -249.7 | C28: =_xlfn.XLOOKUP($A28,Inputs!$A:$A,Inputs!C:C,,0) -> -1700.2 | D28: =_xlfn.XLOOKUP($A28,Inputs!$A:$A,Inputs!D:D,,0) -> -1390.5 | E28: =_xlfn.XLOOKUP($A28,Inputs!$A:$A,Inputs!E:E,,0) -> -1045.9 | F28: =_xlfn.XLOOKUP($A28,Inputs!$A:$A,Inputs!F:F,,0) -> -1045.9 | G28: =_xlfn.XLOOKUP($A28,Inputs!$A:$A,Inputs!G:G,,0) -> -995.9 | H28: =_xlfn.XLOOKUP($A28,Inputs!$A:$A,Inputs!H:H,,0) -> -512.8 | I28: =_xlfn.XLOOKUP($A28,Inputs!$A:$A,Inputs!I:I,,0) -> -453.1 | J28: =_xlfn.XLOOKUP($A28,Inputs!$A:$A,Inputs!J:J,,0) -> -330.5 | K28: =_xlfn.XLOOKUP($A28,Inputs!$A:$A,Inputs!K:K,,0) -> -796.7 | L28: =_xlfn.XLOOKUP($A28,Inputs!$A:$A,Inputs!L:L,,0) -> 0 | M28: =_xlfn.XLOOKUP($A28,Inputs!$A:$A,Inputs!M:M,,0) -> -383
A29: Net Cash Flow | B29: =SUM(B26:B28) -> -884.6 | C29: =SUM(C26:C28) -> -2353.8 | D29: =SUM(D26:D28) -> -2224.7 | E29: =SUM(E26:E28) -> -1241.7 | F29: =SUM(F26:F28) -> -1627.3 | G29: =SUM(G26:G28) -> -1550.3 | H29: =SUM(H26:H28) -> -1000 | I29: =SUM(I26:I28) -> -673.9 | ... M29: =SUM(M26:M28) -> -51.5
A30: FNP'' | B30: =+B29-(B58-C29) -> -15813.8 | C30: =+C29-(C58-D29) -> -17575.2 | D30: =+D29-(D58-E29) -> -14440.5 | E30: =+E29-(E58-F29) -> -13866.7 | F30: =+F29-(F58-G29) -> -15947.1 | G30: =+G29-(G58-H29) -> -16166.8 | H30: =+H29-(H58-I29) -> -11860.6 | I30: =+I29-(I58-J29) -> -10511.1 | ... M30: =+M29-(M58-N29) -> -3356.9
A31: FNP' | B31: =+B30+B33 -> -15766 | C31: =+C30+C33 -> -17546.4 | D31: =+D30+D33 -> -14451.6 | E31: =+E30+E33 -> -13109.5 | F31: =+F30+F33 -> -15760.3 | G31: =+G30+G33 -> -20183.7 | H31: =+H30+H33 -> -12221.6 | I31: =+I30+I33 -> -11046.8 | ... M31: =+M30+M33 -> -3516.2
A32: Net Capex | B32: =_xlfn.XLOOKUP($A32,Inputs!$A:$A,Inputs!B:B,,0) -> -1269.1 | C32: =_xlfn.XLOOKUP($A32,Inputs!$A:$A,Inputs!C:C,,0) -> -1028.7 | D32: =_xlfn.XLOOKUP($A32,Inputs!$A:$A,Inputs!D:D,,0) -> -1022.7 | E32: =_xlfn.XLOOKUP($A32,Inputs!$A:$A,Inputs!E:E,,0) -> -845.7 | F32: =_xlfn.XLOOKUP($A32,Inputs!$A:$A,Inputs!F:F,,0) -> -718.2 | G32: =_xlfn.XLOOKUP($A32,Inputs!$A:$A,Inputs!G:G,,0) -> -814 | H32: =_xlfn.XLOOKUP($A32,Inputs!$A:$A,Inputs!H:H,,0) -> -1052.1 | I32: =_xlfn.XLOOKUP($A32,Inputs!$A:$A,Inputs!I:I,,0) -> -907.4 | J32: =_xlfn.XLOOKUP($A32,Inputs!$A:$A,Inputs!J:J,,0) -> -891.3 | K32: =_xlfn.XLOOKUP($A32,Inputs!$A:$A,Inputs!K:K,,0) -> -719.4 | L32: =_xlfn.XLOOKUP($A32,Inputs!$A:$A,Inputs!L:L,,0) -> -223.5 | M32: =_xlfn.XLOOKUP($A32,Inputs!$A:$A,Inputs!M:M,,0) -> -62.1
A33: Investments & Acquisitions | B33: =_xlfn.XLOOKUP($A33,Inputs!$A:$A,Inputs!B:B,,0) -> 47.8 | C33: =_xlfn.XLOOKUP($A33,Inputs!$A:$A,Inputs!C:C,,0) -> 28.8 | D33: =_xlfn.XLOOKUP($A33,Inputs!$A:$A,Inputs!D:D,,0) -> -11.1 | E33: =_xlfn.XLOOKUP($A33,Inputs!$A:$A,Inputs!E:E,,0) -> 757.2 | F33: =_xlfn.XLOOKUP($A33,Inputs!$A:$A,Inputs!F:F,,0) -> 186.8 | G33: =_xlfn.XLOOKUP($A33,Inputs!$A:$A,Inputs!G:G,,0) -> -4016.9 | H33: =_xlfn.XLOOKUP($A33,Inputs!$A:$A,Inputs!H:H,,0) -> -361 | I33: =_xlfn.XLOOKUP($A33,Inputs!$A:$A,Inputs!I:I,,0) -> -535.7 | J33: =_xlfn.XLOOKUP($A33,Inputs!$A:$A,Inputs!J:J,,0) -> -1316.4 | K33: =_xlfn.XLOOKUP($A33,Inputs!$A:$A,Inputs!K:K,,0) -> -310.3 | L33: =_xlfn.XLOOKUP($A33,Inputs!$A:$A,Inputs!L:L,,0) -> -4681.3 | M33: =_xlfn.XLOOKUP($A33,Inputs!$A:$A,Inputs!M:M,,0) -> -159.3
A34: Capex + Investments | B34: =+B32+B33 -> -1221.3 | C34: =+C32+C33 -> -999.9 | D34: =+D32+D33 -> -1033.8 | E34: =+E32+E33 -> -88.5 | F34: =+F32+F33 -> -531.4 | G34: =+G32+G33 -> -4830.9 | H34: =+H32+H33 -> -1413.1 | I34: =+I32+I33 -> -1443.1 | ... M34: =+M32+M33 -> -221.4
A35: Dividends + Share Buyback | B35: =+B27+B28 -> -903.5 | C35: =+C27+C28 -> -2287.9 | D35: =+D27+D28 -> -1963.5 | E35: =+E27+E28 -> -1620.9 | F35: =+F27+F28 -> -1615.1 | G35: =+G27+G28 -> -1553.6 | H35: =+H27+H28 -> -912.9 | I35: =+I27+I28 -> -768.2 | ... M35: =+M27+M28 -> -383
A36: Payout Ratio | B36: =IFERROR(B35/B23,"-") -> -0.51184002 | C36: =IFERROR(C35/C23,"-") -> 59.425974 | D36: =IFERROR(D35/D23,"-") -> -1963.5 | E36: =IFERROR(E35/E23,"-") -> -0.79776553 | F36: =IFERROR(F35/F23,"-") -> -75.471963 | G36: =IFERROR(G35/G23,"-") -> -0.44913417 | H36: =IFERROR(H35/H23,"-") -> -0.3916681 | I36: =IFERROR(I35/I23,"-") -> -0.49909044 | ... M36: =IFERROR(M35/M23,"-") -> -0.98762249
A38: Assets
A39: Cash & Eq. | B39: =_xlfn.XLOOKUP($A39,Inputs!$A:$A,Inputs!B:B,,0) -> 152.4 | C39: =_xlfn.XLOOKUP($A39,Inputs!$A:$A,Inputs!C:C,,0) -> 133.5 | D39: =_xlfn.XLOOKUP($A39,Inputs!$A:$A,Inputs!D:D,,0) -> 199.4 | E39: =_xlfn.XLOOKUP($A39,Inputs!$A:$A,Inputs!E:E,,0) -> 460.6 | F39: =_xlfn.XLOOKUP($A39,Inputs!$A:$A,Inputs!F:F,,0) -> 81.4 | G39: =_xlfn.XLOOKUP($A39,Inputs!$A:$A,Inputs!G:G,,0) -> 93.6 | H39: =_xlfn.XLOOKUP($A39,Inputs!$A:$A,Inputs!H:H,,0) -> 90.3 | I39: =_xlfn.XLOOKUP($A39,Inputs!$A:$A,Inputs!I:I,,0) -> 177.4 | J39: =_xlfn.XLOOKUP($A39,Inputs!$A:$A,Inputs!J:J,,0) -> 83.1 | K39: =_xlfn.XLOOKUP($A39,Inputs!$A:$A,Inputs!K:K,,0) -> 110.1 | L39: =_xlfn.XLOOKUP($A39,Inputs!$A:$A,Inputs!L:L,,0) -> 63.9 | M39: =_xlfn.XLOOKUP($A39,Inputs!$A:$A,Inputs!M:M,,0) -> 331.5
A40: Accounts Receivable | B40: =_xlfn.XLOOKUP($A40,Inputs!$A:$A,Inputs!B:B,,0) -> 832.8 | C40: =_xlfn.XLOOKUP($A40,Inputs!$A:$A,Inputs!C:C,,0) -> 901.6 | D40: =_xlfn.XLOOKUP($A40,Inputs!$A:$A,Inputs!D:D,,0) -> 899 | E40: =_xlfn.XLOOKUP($A40,Inputs!$A:$A,Inputs!E:E,,0) -> 785.3 | F40: =_xlfn.XLOOKUP($A40,Inputs!$A:$A,Inputs!F:F,,0) -> 864.8 | G40: =_xlfn.XLOOKUP($A40,Inputs!$A:$A,Inputs!G:G,,0) -> 846.9 | H40: =_xlfn.XLOOKUP($A40,Inputs!$A:$A,Inputs!H:H,,0) -> 776.2 | I40: =_xlfn.XLOOKUP($A40,Inputs!$A:$A,Inputs!I:I,,0) -> 737 | J40: =_xlfn.XLOOKUP($A40,Inputs!$A:$A,Inputs!J:J,,0) -> 732.5 | K40: =_xlfn.XLOOKUP($A40,Inputs!$A:$A,Inputs!K:K,,0) -> 598.9 | L40: =_xlfn.XLOOKUP($A40,Inputs!$A:$A,Inputs!L:L,,0) -> 626.2 | M40: =_xlfn.XLOOKUP($A40,Inputs!$A:$A,Inputs!M:M,,0) -> 471.9
A41: Inventory | B41: =_xlfn.XLOOKUP($A41,Inputs!$A:$A,Inputs!B:B,,0) -> 2078.3 | C41: =_xlfn.XLOOKUP($A41,Inputs!$A:$A,Inputs!C:C,,0) -> 1898.7 | D41: =_xlfn.XLOOKUP($A41,Inputs!$A:$A,Inputs!D:D,,0) -> 1573.2 | E41: =_xlfn.XLOOKUP($A41,Inputs!$A:$A,Inputs!E:E,,0) -> 1291.1 | F41: =_xlfn.XLOOKUP($A41,Inputs!$A:$A,Inputs!F:F,,0) -> 1373.6 | G41: =_xlfn.XLOOKUP($A41,Inputs!$A:$A,Inputs!G:G,,0) -> 2130.4 | H41: =_xlfn.XLOOKUP($A41,Inputs!$A:$A,Inputs!H:H,,0) -> 2084 | I41: =_xlfn.XLOOKUP($A41,Inputs!$A:$A,Inputs!I:I,,0) -> 1955.1 | J41: =_xlfn.XLOOKUP($A41,Inputs!$A:$A,Inputs!J:J,,0) -> 1851.6 | K41: =_xlfn.XLOOKUP($A41,Inputs!$A:$A,Inputs!K:K,,0) -> 1827.2 | L41: =_xlfn.XLOOKUP($A41,Inputs!$A:$A,Inputs!L:L,,0) -> 1743.8 | M41: =_xlfn.XLOOKUP($A41,Inputs!$A:$A,Inputs!M:M,,0) -> 1480.9
A42: Property, Plant and Equipment | B42: =_xlfn.XLOOKUP($A42,Inputs!$A:$A,Inputs!B:B,,0) -> 8055.2 | C42: =_xlfn.XLOOKUP($A42,Inputs!$A:$A,Inputs!C:C,,0) -> 6865.2 | D42: =_xlfn.XLOOKUP($A42,Inputs!$A:$A,Inputs!D:D,,0) -> 6059.6 | E42: =_xlfn.XLOOKUP($A42,Inputs!$A:$A,Inputs!E:E,,0) -> 5821.6 | F42: =_xlfn.XLOOKUP($A42,Inputs!$A:$A,Inputs!F:F,,0) -> 5333 | G42: =_xlfn.XLOOKUP($A42,Inputs!$A:$A,Inputs!G:G,,0) -> 5267.3 | H42: =_xlfn.XLOOKUP($A42,Inputs!$A:$A,Inputs!H:H,,0) -> 4789.7 | I42: =_xlfn.XLOOKUP($A42,Inputs!$A:$A,Inputs!I:I,,0) -> 3932.8 | J42: =_xlfn.XLOOKUP($A42,Inputs!$A:$A,Inputs!J:J,,0) -> 3333.4 | K42: =_xlfn.XLOOKUP($A42,Inputs!$A:$A,Inputs!K:K,,0) -> 2681.6 | L42: =_xlfn.XLOOKUP($A42,Inputs!$A:$A,Inputs!L:L,,0) -> 2014.3 | M42: =_xlfn.XLOOKUP($A42,Inputs!$A:$A,Inputs!M:M,,0) -> 1229
A43: Other Assets | B43: =_xlfn.XLOOKUP($A43,Inputs!$A:$A,Inputs!B:B,,0) -> 13787.1 | C43: =_xlfn.XLOOKUP($A43,Inputs!$A:$A,Inputs!C:C,,0) -> 13757.5 | D43: =_xlfn.XLOOKUP($A43,Inputs!$A:$A,Inputs!D:D,,0) -> 13957 | E43: =_xlfn.XLOOKUP($A43,Inputs!$A:$A,Inputs!E:E,,0) -> 15479.9 | F43: =_xlfn.XLOOKUP($A43,Inputs!$A:$A,Inputs!F:F,,0) -> 16095.1 | G43: =_xlfn.XLOOKUP($A43,Inputs!$A:$A,Inputs!G:G,,0) -> 16868.2 | H43: =_xlfn.XLOOKUP($A43,Inputs!$A:$A,Inputs!H:H,,0) -> 12117.8 | I43: =_xlfn.XLOOKUP($A43,Inputs!$A:$A,Inputs!I:I,,0) -> 11224.8 | J43: =_xlfn.XLOOKUP($A43,Inputs!$A:$A,Inputs!J:J,,0) -> 10532.9 | K43: =_xlfn.XLOOKUP($A43,Inputs!$A:$A,Inputs!K:K,,0) -> 9409.2 | L43: =_xlfn.XLOOKUP($A43,Inputs!$A:$A,Inputs!L:L,,0) -> 9374.6 | M43: =_xlfn.XLOOKUP($A43,Inputs!$A:$A,Inputs!M:M,,0) -> 3537.8
A44: Total Assets | B44: =_xlfn.XLOOKUP($A44,Inputs!$A:$A,Inputs!B:B,,0) -> 25691.7 | C44: =_xlfn.XLOOKUP($A44,Inputs!$A:$A,Inputs!C:C,,0) -> 24662.3 | D44: =_xlfn.XLOOKUP($A44,Inputs!$A:$A,Inputs!D:D,,0) -> 25855.8 | E44: =_xlfn.XLOOKUP($A44,Inputs!$A:$A,Inputs!E:E,,0) -> 27104.8 | F44: =_xlfn.XLOOKUP($A44,Inputs!$A:$A,Inputs!F:F,,0) -> 27323.2 | G44: =_xlfn.XLOOKUP($A44,Inputs!$A:$A,Inputs!G:G,,0) -> 29231.5 | H44: =_xlfn.XLOOKUP($A44,Inputs!$A:$A,Inputs!H:H,,0) -> 20538.7 | I44: =_xlfn.XLOOKUP($A44,Inputs!$A:$A,Inputs!I:I,,0) -> 18602.4 | J44: =_xlfn.XLOOKUP($A44,Inputs!$A:$A,Inputs!J:J,,0) -> 16965 | K44: =_xlfn.XLOOKUP($A44,Inputs!$A:$A,Inputs!K:K,,0) -> 15093 | L44: =_xlfn.XLOOKUP($A44,Inputs!$A:$A,Inputs!L:L,,0) -> 14302.1 | M44: =_xlfn.XLOOKUP($A44,Inputs!$A:$A,Inputs!M:M,,0) -> 7638.1
A47: Liabilities
A48: Current Liabilities | B48: =_xlfn.XLOOKUP($A48,Inputs!$A:$A,Inputs!B:B,,0) -> 3141.7 | C48: =_xlfn.XLOOKUP($A48,Inputs!$A:$A,Inputs!C:C,,0) -> 2968.3 | D48: =_xlfn.XLOOKUP($A48,Inputs!$A:$A,Inputs!D:D,,0) -> 2698.8 | E48: =_xlfn.XLOOKUP($A48,Inputs!$A:$A,Inputs!E:E,,0) -> 1269.1 | F48: =_xlfn.XLOOKUP($A48,Inputs!$A:$A,Inputs!F:F,,0) -> 2311.8 | G48: =_xlfn.XLOOKUP($A48,Inputs!$A:$A,Inputs!G:G,,0) -> 3163.8 | H48: =_xlfn.XLOOKUP($A48,Inputs!$A:$A,Inputs!H:H,,0) -> 2039.6 | I48: =_xlfn.XLOOKUP($A48,Inputs!$A:$A,Inputs!I:I,,0) -> 2697.6 | J48: =_xlfn.XLOOKUP($A48,Inputs!$A:$A,Inputs!J:J,,0) -> 2272.3 | K48: =_xlfn.XLOOKUP($A48,Inputs!$A:$A,Inputs!K:K,,0) -> 1130.7 | L48: =_xlfn.XLOOKUP($A48,Inputs!$A:$A,Inputs!L:L,,0) -> 2025.7 | M48: =_xlfn.XLOOKUP($A48,Inputs!$A:$A,Inputs!M:M,,0) -> 677.9
A49: Short-Term Debt | B49: =_xlfn.XLOOKUP($A49,Inputs!$A:$A,Inputs!B:B,,0) -> 1198.2 | C49: =_xlfn.XLOOKUP($A49,Inputs!$A:$A,Inputs!C:C,,0) -> 1185.2 | D49: =_xlfn.XLOOKUP($A49,Inputs!$A:$A,Inputs!D:D,,0) -> 928.3 | E49: =_xlfn.XLOOKUP($A49,Inputs!$A:$A,Inputs!E:E,,0) -> 29.2 | F49: =_xlfn.XLOOKUP($A49,Inputs!$A:$A,Inputs!F:F,,0) -> 973.8 | G49: =_xlfn.XLOOKUP($A49,Inputs!$A:$A,Inputs!G:G,,0) -> 1856.7 | H49: =_xlfn.XLOOKUP($A49,Inputs!$A:$A,Inputs!H:H,,0) -> 769.1 | I49: =_xlfn.XLOOKUP($A49,Inputs!$A:$A,Inputs!I:I,,0) -> 1517.4 | J49: =_xlfn.XLOOKUP($A49,Inputs!$A:$A,Inputs!J:J,,0) -> 1265 | K49: =_xlfn.XLOOKUP($A49,Inputs!$A:$A,Inputs!K:K,,0) -> 210.5 | L49: =_xlfn.XLOOKUP($A49,Inputs!$A:$A,Inputs!L:L,,0) -> 590 | M49: =_xlfn.XLOOKUP($A49,Inputs!$A:$A,Inputs!M:M,,0) -> 27.6
A50: Short-Term Leases | B50: =_xlfn.XLOOKUP($A50,Inputs!$A:$A,Inputs!B:B,,0) -> 97.1 | C50: =_xlfn.XLOOKUP($A50,Inputs!$A:$A,Inputs!C:C,,0) -> 90.9 | D50: =_xlfn.XLOOKUP($A50,Inputs!$A:$A,Inputs!D:D,,0) -> 86.7 | E50: =_xlfn.XLOOKUP($A50,Inputs!$A:$A,Inputs!E:E,,0) -> 73.4 | F50: =_xlfn.XLOOKUP($A50,Inputs!$A:$A,Inputs!F:F,,0) -> 88.3 | G50: =_xlfn.XLOOKUP($A50,Inputs!$A:$A,Inputs!G:G,,0) -> 0 | H50: =_xlfn.XLOOKUP($A50,Inputs!$A:$A,Inputs!H:H,,0) -> 0 | I50: =_xlfn.XLOOKUP($A50,Inputs!$A:$A,Inputs!I:I,,0) -> 0 | J50: =_xlfn.XLOOKUP($A50,Inputs!$A:$A,Inputs!J:J,,0) -> 0 | K50: =_xlfn.XLOOKUP($A50,Inputs!$A:$A,Inputs!K:K,,0) -> 0 | L50: =_xlfn.XLOOKUP($A50,Inputs!$A:$A,Inputs!L:L,,0) -> 0 | M50: =_xlfn.XLOOKUP($A50,Inputs!$A:$A,Inputs!M:M,,0) -> 0
A51: Other current liabilities | B51: =_xlfn.XLOOKUP($A51,Inputs!$A:$A,Inputs!B:B,,0) -> 739.3 | C51: =_xlfn.XLOOKUP($A51,Inputs!$A:$A,Inputs!C:C,,0) -> 750.7 | D51: =_xlfn.XLOOKUP($A51,Inputs!$A:$A,Inputs!D:D,,0) -> 784.6 | E51: =_xlfn.XLOOKUP($A51,Inputs!$A:$A,Inputs!E:E,,0) -> 706.5 | F51: =_xlfn.XLOOKUP($A51,Inputs!$A:$A,Inputs!F:F,,0) -> 692.1 | G51: =_xlfn.XLOOKUP($A51,Inputs!$A:$A,Inputs!G:G,,0) -> 690.4 | H51: =_xlfn.XLOOKUP($A51,Inputs!$A:$A,Inputs!H:H,,0) -> 678.3 | I51: =_xlfn.XLOOKUP($A51,Inputs!$A:$A,Inputs!I:I,,0) -> 620.4 | J51: =_xlfn.XLOOKUP($A51,Inputs!$A:$A,Inputs!J:J,,0) -> 578 | K51: =_xlfn.XLOOKUP($A51,Inputs!$A:$A,Inputs!K:K,,0) -> 634.4 | L51: =_xlfn.XLOOKUP($A51,Inputs!$A:$A,Inputs!L:L,,0) -> 1140.5 | M51: =_xlfn.XLOOKUP($A51,Inputs!$A:$A,Inputs!M:M,,0) -> 441.3
A52: Non-current Liabilities | B52: =_xlfn.XLOOKUP($A52,Inputs!$A:$A,Inputs!B:B,,0) -> 12485.4 | C52: =_xlfn.XLOOKUP($A52,Inputs!$A:$A,Inputs!C:C,,0) -> 12960.1 | D52: =_xlfn.XLOOKUP($A52,Inputs!$A:$A,Inputs!D:D,,0) -> 11109.2 | E52: =_xlfn.XLOOKUP($A52,Inputs!$A:$A,Inputs!E:E,,0) -> 11906.6 | F52: =_xlfn.XLOOKUP($A52,Inputs!$A:$A,Inputs!F:F,,0) -> 12537.1 | G52: =_xlfn.XLOOKUP($A52,Inputs!$A:$A,Inputs!G:G,,0) -> 13230.5 | H52: =_xlfn.XLOOKUP($A52,Inputs!$A:$A,Inputs!H:H,,0) -> 10507.4 | I52: =_xlfn.XLOOKUP($A52,Inputs!$A:$A,Inputs!I:I,,0) -> 9020 | J52: =_xlfn.XLOOKUP($A52,Inputs!$A:$A,Inputs!J:J,,0) -> 8000.9 | K52: =_xlfn.XLOOKUP($A52,Inputs!$A:$A,Inputs!K:K,,0) -> 8081 | L52: =_xlfn.XLOOKUP($A52,Inputs!$A:$A,Inputs!L:L,,0) -> 7295.1 | M52: =_xlfn.XLOOKUP($A52,Inputs!$A:$A,Inputs!M:M,,0) -> 4099.9
A53: Long-Term Debt | B53: =_xlfn.XLOOKUP($A53,Inputs!$A:$A,Inputs!B:B,,0) -> 10681.1 | C53: =_xlfn.XLOOKUP($A53,Inputs!$A:$A,Inputs!C:C,,0) -> 11286.5 | D53: =_xlfn.XLOOKUP($A53,Inputs!$A:$A,Inputs!D:D,,0) -> 9488.2 | E53: =_xlfn.XLOOKUP($A53,Inputs!$A:$A,Inputs!E:E,,0) -> 10413.1 | F53: =_xlfn.XLOOKUP($A53,Inputs!$A:$A,Inputs!F:F,,0) -> 11210.8 | G53: =_xlfn.XLOOKUP($A53,Inputs!$A:$A,Inputs!G:G,,0) -> 11759.8 | H53: =_xlfn.XLOOKUP($A53,Inputs!$A:$A,Inputs!H:H,,0) -> 9417.6 | I53: =_xlfn.XLOOKUP($A53,Inputs!$A:$A,Inputs!I:I,,0) -> 7720.7 | J53: =_xlfn.XLOOKUP($A53,Inputs!$A:$A,Inputs!J:J,,0) -> 6816.2 | K53: =_xlfn.XLOOKUP($A53,Inputs!$A:$A,Inputs!K:K,,0) -> 7086 | L53: =_xlfn.XLOOKUP($A53,Inputs!$A:$A,Inputs!L:L,,0) -> 6373.3 | M53: =_xlfn.XLOOKUP($A53,Inputs!$A:$A,Inputs!M:M,,0) -> 3277.8
A54: Long-Term Leases | B54: =_xlfn.XLOOKUP($A54,Inputs!$A:$A,Inputs!B:B,,0) -> 599 | C54: =_xlfn.XLOOKUP($A54,Inputs!$A:$A,Inputs!C:C,,0) -> 434.1 | D54: =_xlfn.XLOOKUP($A54,Inputs!$A:$A,Inputs!D:D,,0) -> 470.9 | E54: =_xlfn.XLOOKUP($A54,Inputs!$A:$A,Inputs!E:E,,0) -> 482 | F54: =_xlfn.XLOOKUP($A54,Inputs!$A:$A,Inputs!F:F,,0) -> 496.6 | G54: =_xlfn.XLOOKUP($A54,Inputs!$A:$A,Inputs!G:G,,0) -> 0 | H54: =_xlfn.XLOOKUP($A54,Inputs!$A:$A,Inputs!H:H,,0) -> 0 | I54: =_xlfn.XLOOKUP($A54,Inputs!$A:$A,Inputs!I:I,,0) -> 0 | J54: =_xlfn.XLOOKUP($A54,Inputs!$A:$A,Inputs!J:J,,0) -> 0 | K54: =_xlfn.XLOOKUP($A54,Inputs!$A:$A,Inputs!K:K,,0) -> 0 | L54: =_xlfn.XLOOKUP($A54,Inputs!$A:$A,Inputs!L:L,,0) -> 0 | M54: =_xlfn.XLOOKUP($A54,Inputs!$A:$A,Inputs!M:M,,0) -> 0
A55: Other non-current liabilities | B55: =_xlfn.XLOOKUP($A55,Inputs!$A:$A,Inputs!B:B,,0) -> 1205.3 | C55: =_xlfn.XLOOKUP($A55,Inputs!$A:$A,Inputs!C:C,,0) -> 1239.5 | D55: =_xlfn.XLOOKUP($A55,Inputs!$A:$A,Inputs!D:D,,0) -> 1150.1 | E55: =_xlfn.XLOOKUP($A55,Inputs!$A:$A,Inputs!E:E,,0) -> 1011.5 | F55: =_xlfn.XLOOKUP($A55,Inputs!$A:$A,Inputs!F:F,,0) -> 829.7 | G55: =_xlfn.XLOOKUP($A55,Inputs!$A:$A,Inputs!G:G,,0) -> 1470.7 | H55: =_xlfn.XLOOKUP($A55,Inputs!$A:$A,Inputs!H:H,,0) -> 1089.8 | I55: =_xlfn.XLOOKUP($A55,Inputs!$A:$A,Inputs!I:I,,0) -> 1299.3 | J55: =_xlfn.XLOOKUP($A55,Inputs!$A:$A,Inputs!J:J,,0) -> 1184.7 | K55: =_xlfn.XLOOKUP($A55,Inputs!$A:$A,Inputs!K:K,,0) -> 995 | L55: =_xlfn.XLOOKUP($A55,Inputs!$A:$A,Inputs!L:L,,0) -> 921.8 | M55: =_xlfn.XLOOKUP($A55,Inputs!$A:$A,Inputs!M:M,,0) -> 822.1
A56: Total Liabilities | B56: =_xlfn.XLOOKUP($A56,Inputs!$A:$A,Inputs!B:B,,0) -> 15627.1 | C56: =_xlfn.XLOOKUP($A56,Inputs!$A:$A,Inputs!C:C,,0) -> 15928.4 | D56: =_xlfn.XLOOKUP($A56,Inputs!$A:$A,Inputs!D:D,,0) -> 13808 | E56: =_xlfn.XLOOKUP($A56,Inputs!$A:$A,Inputs!E:E,,0) -> 13175.7 | F56: =_xlfn.XLOOKUP($A56,Inputs!$A:$A,Inputs!F:F,,0) -> 14848.9 | G56: =_xlfn.XLOOKUP($A56,Inputs!$A:$A,Inputs!G:G,,0) -> 16394.3 | H56: =_xlfn.XLOOKUP($A56,Inputs!$A:$A,Inputs!H:H,,0) -> 12547 | I56: =_xlfn.XLOOKUP($A56,Inputs!$A:$A,Inputs!I:I,,0) -> 11717.6 | J56: =_xlfn.XLOOKUP($A56,Inputs!$A:$A,Inputs!J:J,,0) -> 10273.2 | K56: =_xlfn.XLOOKUP($A56,Inputs!$A:$A,Inputs!K:K,,0) -> 9211.7 | L56: =_xlfn.XLOOKUP($A56,Inputs!$A:$A,Inputs!L:L,,0) -> 9320.8 | M56: =_xlfn.XLOOKUP($A56,Inputs!$A:$A,Inputs!M:M,,0) -> 4777.8
A58: Total Debt | B58: =B49+B53+B50+B54 -> 12575.4 | C58: =C49+C53+C50+C54 -> 12996.7 | D58: =D49+D53+D50+D54 -> 10974.1 | E58: =E49+E53+E50+E54 -> 10997.7 | F58: =F49+F53+F50+F54 -> 12769.5 | G58: =G49+G53+G50+G54 -> 13616.5 | H58: =H49+H53+H50+H54 -> 10186.7 | I58: =I49+I53+I50+I54 -> 9238.1 | ... M58: =M49+M53+M50+M54 -> 3305.4
A59: Debt/Assets | B59: =IFERROR(B58/B44,"-") -> 0.48947325 | C59: =IFERROR(C58/C44,"-") -> 0.52698653 | D59: =IFERROR(D58/D44,"-") -> 0.42443475 | E59: =IFERROR(E58/E44,"-") -> 0.40574732 | F59: =IFERROR(F58/F44,"-") -> 0.46735009 | G59: =IFERROR(G58/G44,"-") -> 0.46581599 | H59: =IFERROR(H58/H44,"-") -> 0.49597589 | I59: =IFERROR(I58/I44,"-") -> 0.49660796 | ... M59: =IFERROR(M58/M44,"-") -> 0.4327516
A60: Net Debt | B60: =B58-B39 -> 12423 | C60: =C58-C39 -> 12863.2 | D60: =D58-D39 -> 10774.7 | E60: =E58-E39 -> 10537.1 | F60: =F58-F39 -> 12688.1 | G60: =G58-G39 -> 13522.9 | H60: =H58-H39 -> 10096.4 | I60: =I58-I39 -> 9060.7 | ... M60: =M58-M39 -> 2973.9
A62: Minority Interest | B62: =_xlfn.XLOOKUP($A62,Inputs!$A:$A,Inputs!B:B,,0) -> 321.5 | C62: =_xlfn.XLOOKUP($A62,Inputs!$A:$A,Inputs!C:C,,0) -> 320.3 | D62: =_xlfn.XLOOKUP($A62,Inputs!$A:$A,Inputs!D:D,,0) -> 315.9 | E62: =_xlfn.XLOOKUP($A62,Inputs!$A:$A,Inputs!E:E,,0) -> 330.2 | F62: =_xlfn.XLOOKUP($A62,Inputs!$A:$A,Inputs!F:F,,0) -> 342.5 | G62: =_xlfn.XLOOKUP($A62,Inputs!$A:$A,Inputs!G:G,,0) -> 286.2 | H62: =_xlfn.XLOOKUP($A62,Inputs!$A:$A,Inputs!H:H,,0) -> 16.6 | I62: =_xlfn.XLOOKUP($A62,Inputs!$A:$A,Inputs!I:I,,0) -> -6.4 | J62: =_xlfn.XLOOKUP($A62,Inputs!$A:$A,Inputs!J:J,,0) -> 132.2 | K62: =_xlfn.XLOOKUP($A62,Inputs!$A:$A,Inputs!K:K,,0) -> 110.6 | L62: =_xlfn.XLOOKUP($A62,Inputs!$A:$A,Inputs!L:L,,0) -> 0 | M62: =_xlfn.XLOOKUP($A62,Inputs!$A:$A,Inputs!M:M,,0) -> 0
A64: Shareholder's Equity | B64: =_xlfn.XLOOKUP($A64,Inputs!$A:$A,Inputs!B:B,,0) -> 9743.1 | C64: =_xlfn.XLOOKUP($A64,Inputs!$A:$A,Inputs!C:C,,0) -> 8413.6 | D64: =_xlfn.XLOOKUP($A64,Inputs!$A:$A,Inputs!D:D,,0) -> 11731.9 | E64: =_xlfn.XLOOKUP($A64,Inputs!$A:$A,Inputs!E:E,,0) -> 13598.9 | F64: =_xlfn.XLOOKUP($A64,Inputs!$A:$A,Inputs!F:F,,0) -> 12131.8 | G64: =_xlfn.XLOOKUP($A64,Inputs!$A:$A,Inputs!G:G,,0) -> 12551 | H64: =_xlfn.XLOOKUP($A64,Inputs!$A:$A,Inputs!H:H,,0) -> 7975.1 | I64: =_xlfn.XLOOKUP($A64,Inputs!$A:$A,Inputs!I:I,,0) -> 6891.2 | J64: =_xlfn.XLOOKUP($A64,Inputs!$A:$A,Inputs!J:J,,0) -> 6559.6 | K64: =_xlfn.XLOOKUP($A64,Inputs!$A:$A,Inputs!K:K,,0) -> 5770.7 | L64: =_xlfn.XLOOKUP($A64,Inputs!$A:$A,Inputs!L:L,,0) -> 4981.3 | M64: =_xlfn.XLOOKUP($A64,Inputs!$A:$A,Inputs!M:M,,0) -> 2860.3
A66: Cash Flow
A67: Operating CF | B67: =_xlfn.XLOOKUP($A67,Inputs!$A:$A,Inputs!B:B,,0) -> 2780 | C67: =_xlfn.XLOOKUP($A67,Inputs!$A:$A,Inputs!C:C,,0) -> 2756.9 | D67: =_xlfn.XLOOKUP($A67,Inputs!$A:$A,Inputs!D:D,,0) -> 2705.4 | E67: =_xlfn.XLOOKUP($A67,Inputs!$A:$A,Inputs!E:E,,0) -> 2806.5 | F67: =_xlfn.XLOOKUP($A67,Inputs!$A:$A,Inputs!F:F,,0) -> 2551.1 | G67: =_xlfn.XLOOKUP($A67,Inputs!$A:$A,Inputs!G:G,,0) -> 2246.3 | H67: =_xlfn.XLOOKUP($A67,Inputs!$A:$A,Inputs!H:H,,0) -> 1931.4 | I67: =_xlfn.XLOOKUP($A67,Inputs!$A:$A,Inputs!I:I,,0) -> 1696 | J67: =_xlfn.XLOOKUP($A67,Inputs!$A:$A,Inputs!J:J,,0) -> 1413.7 | K67: =_xlfn.XLOOKUP($A67,Inputs!$A:$A,Inputs!K:K,,0) -> 1081 | L67: =_xlfn.XLOOKUP($A67,Inputs!$A:$A,Inputs!L:L,,0) -> 826.2 | M67: =_xlfn.XLOOKUP($A67,Inputs!$A:$A,Inputs!M:M,,0) -> 556.3
A68: Investing CF | B68: =_xlfn.XLOOKUP($A68,Inputs!$A:$A,Inputs!B:B,,0) -> -1285.9 | C68: =_xlfn.XLOOKUP($A68,Inputs!$A:$A,Inputs!C:C,,0) -> -999.4 | D68: =_xlfn.XLOOKUP($A68,Inputs!$A:$A,Inputs!D:D,,0) -> -1035.8 | E68: =_xlfn.XLOOKUP($A68,Inputs!$A:$A,Inputs!E:E,,0) -> -87.9 | F68: =_xlfn.XLOOKUP($A68,Inputs!$A:$A,Inputs!F:F,,0) -> -531 | G68: =_xlfn.XLOOKUP($A68,Inputs!$A:$A,Inputs!G:G,,0) -> -4831.8 | H68: =_xlfn.XLOOKUP($A68,Inputs!$A:$A,Inputs!H:H,,0) -> -1423.1 | I68: =_xlfn.XLOOKUP($A68,Inputs!$A:$A,Inputs!I:I,,0) -> -1461.8 | J68: =_xlfn.XLOOKUP($A68,Inputs!$A:$A,Inputs!J:J,,0) -> -2207.4 | K68: =_xlfn.XLOOKUP($A68,Inputs!$A:$A,Inputs!K:K,,0) -> -1015.9 | L68: =_xlfn.XLOOKUP($A68,Inputs!$A:$A,Inputs!L:L,,0) -> -4863.8 | M68: =_xlfn.XLOOKUP($A68,Inputs!$A:$A,Inputs!M:M,,0) -> -206.8
A69: Net Capex | B69: =_xlfn.XLOOKUP($A69,Inputs!$A:$A,Inputs!B:B,,0) -> -1269.1 | C69: =_xlfn.XLOOKUP($A69,Inputs!$A:$A,Inputs!C:C,,0) -> -1028.7 | D69: =_xlfn.XLOOKUP($A69,Inputs!$A:$A,Inputs!D:D,,0) -> -1022.7 | E69: =_xlfn.XLOOKUP($A69,Inputs!$A:$A,Inputs!E:E,,0) -> -845.7 | F69: =_xlfn.XLOOKUP($A69,Inputs!$A:$A,Inputs!F:F,,0) -> -718.2 | G69: =_xlfn.XLOOKUP($A69,Inputs!$A:$A,Inputs!G:G,,0) -> -814 | H69: =_xlfn.XLOOKUP($A69,Inputs!$A:$A,Inputs!H:H,,0) -> -1052.1 | I69: =_xlfn.XLOOKUP($A69,Inputs!$A:$A,Inputs!I:I,,0) -> -907.4 | J69: =_xlfn.XLOOKUP($A69,Inputs!$A:$A,Inputs!J:J,,0) -> -891.3 | K69: =_xlfn.XLOOKUP($A69,Inputs!$A:$A,Inputs!K:K,,0) -> -719.4 | L69: =_xlfn.XLOOKUP($A69,Inputs!$A:$A,Inputs!L:L,,0) -> -223.5 | M69: =_xlfn.XLOOKUP($A69,Inputs!$A:$A,Inputs!M:M,,0) -> -62.1
A70: Investments & Acquisitions | B70: =_xlfn.XLOOKUP($A70,Inputs!$A:$A,Inputs!B:B,,0) -> 47.8 | C70: =_xlfn.XLOOKUP($A70,Inputs!$A:$A,Inputs!C:C,,0) -> 28.8 | D70: =_xlfn.XLOOKUP($A70,Inputs!$A:$A,Inputs!D:D,,0) -> -11.1 | E70: =_xlfn.XLOOKUP($A70,Inputs!$A:$A,Inputs!E:E,,0) -> 757.2 | F70: =_xlfn.XLOOKUP($A70,Inputs!$A:$A,Inputs!F:F,,0) -> 186.8 | G70: =_xlfn.XLOOKUP($A70,Inputs!$A:$A,Inputs!G:G,,0) -> -4016.9 | H70: =_xlfn.XLOOKUP($A70,Inputs!$A:$A,Inputs!H:H,,0) -> -361 | I70: =_xlfn.XLOOKUP($A70,Inputs!$A:$A,Inputs!I:I,,0) -> -535.7 | J70: =_xlfn.XLOOKUP($A70,Inputs!$A:$A,Inputs!J:J,,0) -> -1316.4 | K70: =_xlfn.XLOOKUP($A70,Inputs!$A:$A,Inputs!K:K,,0) -> -310.3 | L70: =_xlfn.XLOOKUP($A70,Inputs!$A:$A,Inputs!L:L,,0) -> -4681.3 | M70: =_xlfn.XLOOKUP($A70,Inputs!$A:$A,Inputs!M:M,,0) -> -159.3
A71: Financing CF | B71: =_xlfn.XLOOKUP($A71,Inputs!$A:$A,Inputs!B:B,,0) -> -1474.6 | C71: =_xlfn.XLOOKUP($A71,Inputs!$A:$A,Inputs!C:C,,0) -> -1819.9 | D71: =_xlfn.XLOOKUP($A71,Inputs!$A:$A,Inputs!D:D,,0) -> -1929.5 | E71: =_xlfn.XLOOKUP($A71,Inputs!$A:$A,Inputs!E:E,,0) -> -2346.6 | F71: =_xlfn.XLOOKUP($A71,Inputs!$A:$A,Inputs!F:F,,0) -> -2031.4 | G71: =_xlfn.XLOOKUP($A71,Inputs!$A:$A,Inputs!G:G,,0) -> 2593.3 | H71: =_xlfn.XLOOKUP($A71,Inputs!$A:$A,Inputs!H:H,,0) -> -601.2 | I71: =_xlfn.XLOOKUP($A71,Inputs!$A:$A,Inputs!I:I,,0) -> -134.8 | J71: =_xlfn.XLOOKUP($A71,Inputs!$A:$A,Inputs!J:J,,0) -> 776 | K71: =_xlfn.XLOOKUP($A71,Inputs!$A:$A,Inputs!K:K,,0) -> -16.4 | L71: =_xlfn.XLOOKUP($A71,Inputs!$A:$A,Inputs!L:L,,0) -> 3777 | M71: =_xlfn.XLOOKUP($A71,Inputs!$A:$A,Inputs!M:M,,0) -> -98.7
A72: Dividends | B72: =_xlfn.XLOOKUP($A72,Inputs!$A:$A,Inputs!B:B,,0) -> -653.8 | C72: =_xlfn.XLOOKUP($A72,Inputs!$A:$A,Inputs!C:C,,0) -> -587.7 | D72: =_xlfn.XLOOKUP($A72,Inputs!$A:$A,Inputs!D:D,,0) -> -573 | E72: =_xlfn.XLOOKUP($A72,Inputs!$A:$A,Inputs!E:E,,0) -> -575 | F72: =_xlfn.XLOOKUP($A72,Inputs!$A:$A,Inputs!F:F,,0) -> -569.2 | G72: =_xlfn.XLOOKUP($A72,Inputs!$A:$A,Inputs!G:G,,0) -> -557.7 | H72: =_xlfn.XLOOKUP($A72,Inputs!$A:$A,Inputs!H:H,,0) -> -400.1 | I72: =_xlfn.XLOOKUP($A72,Inputs!$A:$A,Inputs!I:I,,0) -> -315.1 | J72: =_xlfn.XLOOKUP($A72,Inputs!$A:$A,Inputs!J:J,,0) -> -241.6 | K72: =_xlfn.XLOOKUP($A72,Inputs!$A:$A,Inputs!K:K,,0) -> 0 | L72: =_xlfn.XLOOKUP($A72,Inputs!$A:$A,Inputs!L:L,,0) -> 0 | M72: =_xlfn.XLOOKUP($A72,Inputs!$A:$A,Inputs!M:M,,0) -> 0
A73: Share buyback | B73: =_xlfn.XLOOKUP($A73,Inputs!$A:$A,Inputs!B:B,,0) -> -249.7 | C73: =_xlfn.XLOOKUP($A73,Inputs!$A:$A,Inputs!C:C,,0) -> -1700.2 | D73: =_xlfn.XLOOKUP($A73,Inputs!$A:$A,Inputs!D:D,,0) -> -1390.5 | E73: =_xlfn.XLOOKUP($A73,Inputs!$A:$A,Inputs!E:E,,0) -> -1045.9 | F73: =_xlfn.XLOOKUP($A73,Inputs!$A:$A,Inputs!F:F,,0) -> -1045.9 | G73: =_xlfn.XLOOKUP($A73,Inputs!$A:$A,Inputs!G:G,,0) -> -995.9 | H73: =_xlfn.XLOOKUP($A73,Inputs!$A:$A,Inputs!H:H,,0) -> -512.8 | I73: =_xlfn.XLOOKUP($A73,Inputs!$A:$A,Inputs!I:I,,0) -> -453.1 | J73: =_xlfn.XLOOKUP($A73,Inputs!$A:$A,Inputs!J:J,,0) -> -330.5 | K73: =_xlfn.XLOOKUP($A73,Inputs!$A:$A,Inputs!K:K,,0) -> -796.7 | L73: =_xlfn.XLOOKUP($A73,Inputs!$A:$A,Inputs!L:L,,0) -> 0 | M73: =_xlfn.XLOOKUP($A73,Inputs!$A:$A,Inputs!M:M,,0) -> -383
A74: FX | B74: =_xlfn.XLOOKUP($A74,Inputs!$A:$A,Inputs!B:B,,0) -> -0.6 | C74: =_xlfn.XLOOKUP($A74,Inputs!$A:$A,Inputs!C:C,,0) -> -3.5 | D74: =_xlfn.XLOOKUP($A74,Inputs!$A:$A,Inputs!D:D,,0) -> -1.3 | E74: =_xlfn.XLOOKUP($A74,Inputs!$A:$A,Inputs!E:E,,0) -> 7.2 | F74: =_xlfn.XLOOKUP($A74,Inputs!$A:$A,Inputs!F:F,,0) -> -0.9 | G74: =_xlfn.XLOOKUP($A74,Inputs!$A:$A,Inputs!G:G,,0) -> -4.5 | H74: =_xlfn.XLOOKUP($A74,Inputs!$A:$A,Inputs!H:H,,0) -> 5.8 | I74: =_xlfn.XLOOKUP($A74,Inputs!$A:$A,Inputs!I:I,,0) -> -5.1 | J74: =_xlfn.XLOOKUP($A74,Inputs!$A:$A,Inputs!J:J,,0) -> -9.3 | K74: =_xlfn.XLOOKUP($A74,Inputs!$A:$A,Inputs!K:K,,0) -> -2.5 | L74: =_xlfn.XLOOKUP($A74,Inputs!$A:$A,Inputs!L:L,,0) -> -7 | M74: =_xlfn.XLOOKUP($A74,Inputs!$A:$A,Inputs!M:M,,0) -> -5.1
A75: Changes in cash | B75: =_xlfn.XLOOKUP($A75,Inputs!$A:$A,Inputs!B:B,,0) -> 18.9 | C75: =_xlfn.XLOOKUP($A75,Inputs!$A:$A,Inputs!C:C,,0) -> -65.9 | D75: =_xlfn.XLOOKUP($A75,Inputs!$A:$A,Inputs!D:D,,0) -> -261.2 | E75: =_xlfn.XLOOKUP($A75,Inputs!$A:$A,Inputs!E:E,,0) -> 379.2 | F75: =_xlfn.XLOOKUP($A75,Inputs!$A:$A,Inputs!F:F,,0) -> -12.2 | G75: =_xlfn.XLOOKUP($A75,Inputs!$A:$A,Inputs!G:G,,0) -> 3.3 | H75: =_xlfn.XLOOKUP($A75,Inputs!$A:$A,Inputs!H:H,,0) -> -87.1 | I75: =_xlfn.XLOOKUP($A75,Inputs!$A:$A,Inputs!I:I,,0) -> 94.3 | J75: =_xlfn.XLOOKUP($A75,Inputs!$A:$A,Inputs!J:J,,0) -> -27 | K75: =_xlfn.XLOOKUP($A75,Inputs!$A:$A,Inputs!K:K,,0) -> 46.2 | L75: =_xlfn.XLOOKUP($A75,Inputs!$A:$A,Inputs!L:L,,0) -> -267.6 | M75: =_xlfn.XLOOKUP($A75,Inputs!$A:$A,Inputs!M:M,,0) -> 245.7
A77: Other Data
A78: Number of employees | B78: =_xlfn.XLOOKUP($A78,Inputs!$A:$A,Inputs!C:C,,0) -> #N/A | C78: =_xlfn.XLOOKUP($A78,Inputs!$A:$A,Inputs!D:D,,0) -> #N/A | D78: =_xlfn.XLOOKUP($A78,Inputs!$A:$A,Inputs!E:E,,0) -> #N/A | E78: =_xlfn.XLOOKUP($A78,Inputs!$A:$A,Inputs!F:F,,0) -> #N/A | F78: =_xlfn.XLOOKUP($A78,Inputs!$A:$A,Inputs!G:G,,0) -> #N/A | G78: =_xlfn.XLOOKUP($A78,Inputs!$A:$A,Inputs!H:H,,0) -> #N/A | H78: =_xlfn.XLOOKUP($A78,Inputs!$A:$A,Inputs!I:I,,0) -> #N/A | I78: =_xlfn.XLOOKUP($A78,Inputs!$A:$A,Inputs!J:J,,0) -> #N/A | J78: =_xlfn.XLOOKUP($A78,Inputs!$A:$A,Inputs!K:K,,0) -> #N/A | K78: =_xlfn.XLOOKUP($A78,Inputs!$A:$A,Inputs!L:L,,0) -> #N/A | L78: =_xlfn.XLOOKUP($A78,Inputs!$A:$A,Inputs!M:M,,0) -> #N/A | M78: =_xlfn.XLOOKUP($A78,Inputs!$A:$A,Inputs!N:N,,0) -> #N/A
A79: Shares Outstanding | B79: =_xlfn.XLOOKUP($A79,Inputs!$A:$A,Inputs!C:C,,0) -> #N/A | C79: =_xlfn.XLOOKUP($A79,Inputs!$A:$A,Inputs!D:D,,0) -> #N/A | D79: =_xlfn.XLOOKUP($A79,Inputs!$A:$A,Inputs!E:E,,0) -> #N/A | E79: =_xlfn.XLOOKUP($A79,Inputs!$A:$A,Inputs!F:F,,0) -> #N/A | F79: =_xlfn.XLOOKUP($A79,Inputs!$A:$A,Inputs!G:G,,0) -> #N/A | G79: =_xlfn.XLOOKUP($A79,Inputs!$A:$A,Inputs!H:H,,0) -> #N/A | H79: =_xlfn.XLOOKUP($A79,Inputs!$A:$A,Inputs!I:I,,0) -> #N/A | I79: =_xlfn.XLOOKUP($A79,Inputs!$A:$A,Inputs!J:J,,0) -> #N/A | J79: =_xlfn.XLOOKUP($A79,Inputs!$A:$A,Inputs!K:K,,0) -> #N/A | K79: =_xlfn.XLOOKUP($A79,Inputs!$A:$A,Inputs!L:L,,0) -> #N/A | L79: =_xlfn.XLOOKUP($A79,Inputs!$A:$A,Inputs!M:M,,0) -> #N/A | M79: =_xlfn.XLOOKUP($A79,Inputs!$A:$A,Inputs!N:N,,0) -> #N/A
A80: Float | B80: =_xlfn.XLOOKUP($A80,Inputs!$A:$A,Inputs!C:C,,0) -> 0 | C80: =_xlfn.XLOOKUP($A80,Inputs!$A:$A,Inputs!D:D,,0) -> Yahoo finance | D80: =_xlfn.XLOOKUP($A80,Inputs!$A:$A,Inputs!E:E,,0) -> 0 | E80: =_xlfn.XLOOKUP($A80,Inputs!$A:$A,Inputs!F:F,,0) -> 0 | F80: =_xlfn.XLOOKUP($A80,Inputs!$A:$A,Inputs!G:G,,0) -> 0 | G80: =_xlfn.XLOOKUP($A80,Inputs!$A:$A,Inputs!H:H,,0) -> 0 | H80: =_xlfn.XLOOKUP($A80,Inputs!$A:$A,Inputs!I:I,,0) -> 0 | I80: =_xlfn.XLOOKUP($A80,Inputs!$A:$A,Inputs!J:J,,0) -> 0 | J80: =_xlfn.XLOOKUP($A80,Inputs!$A:$A,Inputs!K:K,,0) -> 0 | K80: =_xlfn.XLOOKUP($A80,Inputs!$A:$A,Inputs!L:L,,0) -> 0 | L80: =_xlfn.XLOOKUP($A80,Inputs!$A:$A,Inputs!M:M,,0) -> 0 | M80: =_xlfn.XLOOKUP($A80,Inputs!$A:$A,Inputs!N:N,,0) -> 0
A81: Insiders Own | B81: =_xlfn.XLOOKUP($A81,Inputs!$A:$A,Inputs!C:C,,0) -> 0 | C81: =_xlfn.XLOOKUP($A81,Inputs!$A:$A,Inputs!D:D,,0) -> Yahoo finance | D81: =_xlfn.XLOOKUP($A81,Inputs!$A:$A,Inputs!E:E,,0) -> 0 | E81: =_xlfn.XLOOKUP($A81,Inputs!$A:$A,Inputs!F:F,,0) -> 0 | F81: =_xlfn.XLOOKUP($A81,Inputs!$A:$A,Inputs!G:G,,0) -> 0 | G81: =_xlfn.XLOOKUP($A81,Inputs!$A:$A,Inputs!H:H,,0) -> 0 | H81: =_xlfn.XLOOKUP($A81,Inputs!$A:$A,Inputs!I:I,,0) -> 0 | I81: =_xlfn.XLOOKUP($A81,Inputs!$A:$A,Inputs!J:J,,0) -> 0 | J81: =_xlfn.XLOOKUP($A81,Inputs!$A:$A,Inputs!K:K,,0) -> 0 | K81: =_xlfn.XLOOKUP($A81,Inputs!$A:$A,Inputs!L:L,,0) -> 0 | L81: =_xlfn.XLOOKUP($A81,Inputs!$A:$A,Inputs!M:M,,0) -> 0 | M81: =_xlfn.XLOOKUP($A81,Inputs!$A:$A,Inputs!N:N,,0) -> 0
A82: Fitch/ S&P Rating | B82: =_xlfn.XLOOKUP($A82,Inputs!$A:$A,Inputs!C:C,,0) -> 0 | C82: =_xlfn.XLOOKUP($A82,Inputs!$A:$A,Inputs!D:D,,0) -> 10-K | D82: =_xlfn.XLOOKUP($A82,Inputs!$A:$A,Inputs!E:E,,0) -> 0 | E82: =_xlfn.XLOOKUP($A82,Inputs!$A:$A,Inputs!F:F,,0) -> 0 | F82: =_xlfn.XLOOKUP($A82,Inputs!$A:$A,Inputs!G:G,,0) -> 0 | G82: =_xlfn.XLOOKUP($A82,Inputs!$A:$A,Inputs!H:H,,0) -> 0 | H82: =_xlfn.XLOOKUP($A82,Inputs!$A:$A,Inputs!I:I,,0) -> 0 | I82: =_xlfn.XLOOKUP($A82,Inputs!$A:$A,Inputs!J:J,,0) -> 0 | J82: =_xlfn.XLOOKUP($A82,Inputs!$A:$A,Inputs!K:K,,0) -> 0 | K82: =_xlfn.XLOOKUP($A82,Inputs!$A:$A,Inputs!L:L,,0) -> 0 | L82: =_xlfn.XLOOKUP($A82,Inputs!$A:$A,Inputs!M:M,,0) -> 0 | M82: =_xlfn.XLOOKUP($A82,Inputs!$A:$A,Inputs!N:N,,0) -> 0
A83: Dividend Yield | B83: =_xlfn.XLOOKUP($A83,Inputs!$A:$A,Inputs!C:C,,0) -> #N/A | C83: =_xlfn.XLOOKUP($A83,Inputs!$A:$A,Inputs!D:D,,0) -> #N/A | D83: =_xlfn.XLOOKUP($A83,Inputs!$A:$A,Inputs!E:E,,0) -> #N/A | E83: =_xlfn.XLOOKUP($A83,Inputs!$A:$A,Inputs!F:F,,0) -> #N/A | F83: =_xlfn.XLOOKUP($A83,Inputs!$A:$A,Inputs!G:G,,0) -> #N/A | G83: =_xlfn.XLOOKUP($A83,Inputs!$A:$A,Inputs!H:H,,0) -> #N/A | H83: =_xlfn.XLOOKUP($A83,Inputs!$A:$A,Inputs!I:I,,0) -> #N/A | I83: =_xlfn.XLOOKUP($A83,Inputs!$A:$A,Inputs!J:J,,0) -> #N/A | J83: =_xlfn.XLOOKUP($A83,Inputs!$A:$A,Inputs!K:K,,0) -> #N/A | K83: =_xlfn.XLOOKUP($A83,Inputs!$A:$A,Inputs!L:L,,0) -> #N/A | L83: =_xlfn.XLOOKUP($A83,Inputs!$A:$A,Inputs!M:M,,0) -> #N/A | M83: =_xlfn.XLOOKUP($A83,Inputs!$A:$A,Inputs!N:N,,0) -> #N/A
A84: Daily Volume in Millions of USD | B84: =_xlfn.XLOOKUP($A84,Inputs!$A:$A,Inputs!C:C,,0) -> 0 | C84: =_xlfn.XLOOKUP($A84,Inputs!$A:$A,Inputs!D:D,,0) -> Yahoo Finance | D84: =_xlfn.XLOOKUP($A84,Inputs!$A:$A,Inputs!E:E,,0) -> 0 | E84: =_xlfn.XLOOKUP($A84,Inputs!$A:$A,Inputs!F:F,,0) -> 0 | F84: =_xlfn.XLOOKUP($A84,Inputs!$A:$A,Inputs!G:G,,0) -> 0 | G84: =_xlfn.XLOOKUP($A84,Inputs!$A:$A,Inputs!H:H,,0) -> 0 | H84: =_xlfn.XLOOKUP($A84,Inputs!$A:$A,Inputs!I:I,,0) -> 0 | I84: =_xlfn.XLOOKUP($A84,Inputs!$A:$A,Inputs!J:J,,0) -> 0 | J84: =_xlfn.XLOOKUP($A84,Inputs!$A:$A,Inputs!K:K,,0) -> 0 | K84: =_xlfn.XLOOKUP($A84,Inputs!$A:$A,Inputs!L:L,,0) -> 0 | L84: =_xlfn.XLOOKUP($A84,Inputs!$A:$A,Inputs!M:M,,0) -> 0 | M84: =_xlfn.XLOOKUP($A84,Inputs!$A:$A,Inputs!N:N,,0) -> 0
B86: 2020 | C86: 2021 | D86: 2022
A87: Short % of Float | B87: 0 | C87: 0 | D87: 0
A88: EPS | B88: 0 | C88: 0 | D88: 0
A90: Corporate Bonds 3, 5 Y 10 | B90: Average Price | C90: Moody's | D90: YTM | E90: DIVISA
B91: =VLOOKUP($A91,Inputs!$A$5:$N$98,MATCH(B$4,Inputs!$C$5:$N$5,0)+1,FALSE) -> #N/A | C91: =VLOOKUP($A91,Inputs!$A$5:$N$98,MATCH(C$4,Inputs!$C$5:$N$5,0)+1,FALSE) -> #N/A | D91: =VLOOKUP($A91,Inputs!$A$5:$N$98,MATCH(D$4,Inputs!$C$5:$N$5,0)+1,FALSE) -> #N/A | E91: =VLOOKUP($A91,Inputs!$A$5:$N$98,MATCH(E$4,Inputs!$C$5:$N$5,0)+1,FALSE) -> #N/A

Sheet Inputs
H2: Figures in Millions of USD
H3: Company | I3: #VALUE!
E4: Report in millions
A5: RESULTS | B5: 2024 | C5: =B5-1 -> 2023 | D5: =C5-1 -> 2022 | E5: =D5-1 -> 2021 | F5: =E5-1 -> 2020 | G5: =F5-1 -> 2019 | H5: =G5-1 -> 2018 | I5: =H5-1 -> 2017 | J5: =I5-1 -> 2016 | ... N5: =M5-1 -> 2012 | R5: Hoja | S5: Nombre campo Bloomberg | U5: Cambio de signo | AA5: 2016 | AB5: 2015 | AC5: 2014 | AD5: 2013 | AE5: 2012 | AF5: 2011 | AG5: 2010 | AH5: 2009
A6: Net Sales | B6: 9961.8 | C6: 9452.6 | D6: 8820.7 | E6: 8614.9 | F6: 8343.5 | G6: 8116 | H6: 7585 | I6: 7331.5 | J6: =6548.4 -> 6548.4 | K6: 6028 | L6: =4867.7 -> 4867.7 | M6: =2796.1 -> 2796.1 | N6: =2654.3 -> 2654.3 | O6: Income Statement | P6: Sales | R6: Ingreso | S6: Ingreso | AA6: 38537 | AB6: 47011 | AC6: 55184 | AD6: 55656 | AE6: 65875 | AF6: 60138 | AG6: 42588 | AH6: 32396
A7: Gross Profit | B7: 5017.5 | C7: 4770 | D7: 4698.8 | E7: 4466 | F7: 4151.9 | G7: =4078.5 -> 4078.5 | H7: 3817.2 | I7: 3529.4 | J7: 2942.3 | K7: 2670.8 | L7: =1991.7 -> 1991.7 | M7: =1108.3 -> 1108.3 | N7: =1062.1 -> 1062.1 | O7: Income Statement | P7: =+A7 -> Gross Profit | R7: Ingreso | S7: + Coste de bienes y servicios | AA7: =AA6-28044 -> 10493 | AB7: =AB6-33546 -> 13465 | AC7: =AC6-40718 -> 14466 | AD7: =AD6-40727 -> 14929 | AE7: =+AE6-47055 -> 18820 | AF7: =+AF6-43578 -> 16560 | AG7: =+AG6-30367 -> 12221 | AH7: =+AH6-23886 -> 8510
A8: Operating Income | B8: 3169.7 | C8: 2842.9 | D8: 2331.7 | E8: 2791.1 | F8: 2154.5 | G8: 2412.2 | H8: =2284.5 -> 2284.5 | I8: =2399.4 -> 2399.4 | J8: 1765.1 | K8: 1500.2 | L8: =2437.7-1642 -> 795.7 | M8: =522.9 -> 522.9 | N8: =486.5 -> 486.5 | O8: Income Statement | P8: Operating Income | R8: Ingreso | S8: + Ventas, generales y admin | AA8: =AA7-4383 -> 6110 | AB8: =AB7-4951 -> 8514 | AC8: =AC7-6529 -> 7937 | AD8: =AD7-5547 -> 9382 | AE8: =AE7-5919-2466-797-580-485 -> 8573 | AF8: =+AF7-5203-2297-826-1081 -> 7153 | AG8: =+AG7-4248-1905-914-1191 -> 3963 | AH8: =+AH7-3645-1421-1045-1822 -> 577
A9: Other Expenses (Revenues) | B9: =-511.8-0.7 -> -512.5 | C9: -2060.6 | D9: -1664.9 | E9: 137.5 | F9: -2668.6 | G9: 2099.9 | H9: 487.2 | I9: =27.3 -> 27.3 | J9: 51.1 | K9: 21.5 | L9: =87.8+1642 -> 1729.8 | M9: =233.1 -> 233.1 | N9: 228.5 | O9: Income Statement | P9: investment income+other income expense+income loss+minority interest+non controlling interest+share onf net profit+gain8losses) on equity investments+share of result from associates nd joint ventures+non operating profit+ | R9: Ingreso | S9: + Investigación y desarrollo | T9: + Coste de financiación de beneficio | U9: + Otro gasto operativo | V9: - Beneficio (pérdida) de filiales | W9: - Minoritarios | AA9: =1853+596+595+1904+6+8 -> 4962 | AB9: =2119+587+2023+11 -> 4740 | AC9: =2380+624+1619-8+16 -> 4631 | AD9: =2046+727+981+6+14 -> 3774 | AE9: =-14+41 -> 27 | AF9: 53 | AG9: =58+24 -> 82 | AH9: =12-68 -> -56
A10: Net Financial Cost | B10: -435.4 | C10: -398.7 | D10: -356.4 | E10: -385.7 | F10: =-428.7-2.4 -> -431.1 | G10: -367.1 | H10: =-332-97 -> -429 | I10: -333.3 | J10: -315 | K10: -342.1 | L10: =-323.2 -> -323.2 | M10: =-227.1-12.5 -> -239.6 | N10: =-181 -> -181 | O10: Income Statement | P10: interest expense+financial income and expenses+other financial expense-income+interest and other net+ | R10: Ingreso | S10: - Ingreso (pérdida) no operacional | AA10: =505+518 -> 1023 | AB10: =507-161 -> 346 | AC10: =484-322 -> 162 | AD10: =465+35 -> 500 | AE10: =467-130 -> 337 | AF10: =396+32 -> 428 | AG10: =343-130 -> 213 | AH10: =389-381 -> 8
A11: Taxes | B11: -456.6 | C11: -422.1 | D11: -309.4 | E11: -511.1 | F11: 966.6 | G11: -685.9 | H11: -11.9 | I11: -554.2 | J11: -440.6 | K11: -343.4 | L11: =-259.2 -> -259.2 | M11: =-128.6 -> -128.6 | N11: =-89 -> -89 | O11: Income Statement | P11: Taxes | R11: Ingreso | S11: - Gasto de impuesto a la renta (Beneficio) | AA11: 192 | AB11: 916 | AC11: 692 | AD11: 1319 | AE11: =2528 -> 2528 | AF11: =1720 -> 1720 | AG11: =968 -> 968 | AH11: =-270 -> -270
A12: Net Income | B12: 1765.2 | C12: -38.5 | D12: 1 | E12: 2031.8 | F12: 21.4 | G12: =3459.1 -> 3459.1 | H12: 2330.8 | I12: 1539.2 | J12: 1060.6 | K12: 836.2 | L12: =1943.1 -> 1943.1 | M12: =387.8 -> 387.8 | N12: =445 -> 445 | O12: Income Statement | P12: Net Income | R12: Flujo de caja | S12: + Ingreso neto | AA12: -67 | AB12: 2512 | AC12: 2452 | AD12: 3789 | AE12: 5681 | AF12: =4928+24 -> 4952 | AG12: 2700 | AH12: 895
B13: =SUM(B8:B11) -> 1765.2 | C13: =SUM(C8:C11) -> -38.5 | D13: =SUM(D8:D11) -> 1 | E13: =SUM(E8:E11) -> 2031.8 | F13: =SUM(F8:F11) -> 21.4 | G13: =SUM(G8:G11) -> 3459.1 | H13: =SUM(H8:H11) -> 2330.8 | I13: =SUM(I8:I11) -> 1539.2 | ... N13: =SUM(N8:N11) -> 445 | AA13: =AA8-AA10-AA9-AA11 -> -67 | AB13: =AB8-AB10-AB9-AB11 -> 2512 | AC13: =AC8-AC10-AC9-AC11 -> 2452 | AD13: =AD8-AD10-AD9-AD11 -> 3789 | AE13: =AE8-AE10-AE9-AE11 -> 5681 | AF13: =AF8-AF10-AF9-AF11 -> 4952 | AG13: =AG8-AG10-AG9-AG11 -> 2700 | AH13: =AH8-AH10-AH9-AH11 -> 895
A14: FINANCIAL POSITION | B14: =B12-B13 -> 0 | C14: =C12-C13 -> -1.7053026e-13 | D14: =D12-D13 -> 2.2737368e-13 | E14: =E12-E13 -> 0 | F14: =F12-F13 -> -2.0605739e-13 | G14: =G12-G13 -> 0 | H14: =H12-H13 -> 0 | I14: =I12-I13 -> 0 | ... N14: =N12-N13 -> 0 | AA14: =AA12-AA13 -> 0 | AB14: =AB12-AB13 -> 0 | AC14: =AC12-AC13 -> 0 | AD14: =AD12-AD13 -> 0 | AE14: =AE12-AE13 -> 0 | AF14: =AF12-AF13 -> 0 | AG14: =AG12-AG13 -> 0 | AH14: =AH12-AH13 -> 0
A16: Weighted Average Shares (Basic NI) | B16: 183.307 | C16: 169.337 | D16: 167.431 | E16: 170.239 | F16: =168.329 -> 168.329 | G16: 167.249 | H16: 171.457 | I16: 175.934 | J16: 173.383 | K16: 169.325 | L16: 164.69 | M16: 158.658 | N16: 180.724
A17: Weighted Average Shares (Diluted NI) | B17: 183.959 | C17: 169.337 | D17: 167.431 | E17: =195.308 -> 195.308 | F17: =168.329 -> 168.329 | G17: =195.532 -> 195.532 | H17: 200.745 | I17: 204.099 | J17: 203.821 | K17: 201.224 | L17: 197.57 | M17: 190.307 | N17: 208.655 | R17: 208655 | S17: 208655
A19: Net gains (losses) from ForEx | B19: 293.1 | C19: 274.6 | D19: -40.4 | E19: -56 | F19: 60.8 | G19: -196.8 | H19: 153.8 | I19: 22.1 | J19: 323.3 | K19: 191 | L19: -66.8 | M19: -37.4 | N19: 14.6
A20: Total Comprehensive Income | B20: 2075.7 | C20: 370.2 | D20: 117.6 | E20: 1928.8 | F20: 75.8 | G20: 3284.9 | H20: 2515.8 | I20: 1587.8 | J20: 733.3 | K20: 622.4 | L20: 1897 | M20: 346.2 | N20: 429.9
A22: Changes Net Working Capital | B22: =B23-C23 -> 41.1 | C22: =C23-D23 -> -37.2 | D22: =D23-E23 -> -883.3 | E22: =E23-F23 -> 223.9 | F22: =F23-G23 -> 664.3 | G22: =G23-H23 -> -917.5 | H22: =H23-I23 -> 989.1 | I22: =I23-J23 -> -267.2 | ... M22: =M23-N23 -> 704 | N22: - | O22: cash flows | P22: NWC | R22: Flujo de caja
A23: Net Working Capital | B23: =B27-B42-B28 -> 435.4 | C23: =C27-C42-C28 -> 394.3 | D23: =D27-D42-D28 -> 431.5 | E23: =E27-E42-E28 -> 1314.8 | F23: =F27-F42-F28 -> 1090.9 | G23: =G27-G42-G28 -> 426.6 | H23: =H27-H42-H28 -> 1344.1 | I23: =I27-I42-I28 -> 355 | ... N23: =N27-N42-N28 -> 757.8
A24: 2625 | C24: 2625 | D24: 2625 | E24: 2625 | F24: 2625 | G24: 2625 | H24: 2625 | I24: 2625 | J24: 2625 | K24: 2625 | L24: 2625 | M24: 2625 | N24: 2625 | O24: 2625 | R24: Flujo de caja | S24: + Dividendos pagados | U24: Cambiar signo | AA24: 1799 | AB24: 1757 | AC24: 1620 | AD24: 1111 | AE24: 1617 | AF24: 1159 | AG24: 1084 | AH24: 1029
A25: BALANCE SHEET | C25: 2625 | D25: 2625 | E25: 2625 | F25: 2625 | G25: 2625 | H25: 2625 | J25: 2625 | K25: 2625 | L25: 2625 | M25: 2625 | N25: 2625 | O25: 2625 | R25: Flujo de caja | S25: + Aumento en capital | T25: + Baja en capital | U25: Cambiar signo y hacer suma | AA25: 23 | AB25: =-33+2025 -> 1992 | AC25: 3817 | AD25: 1776 | AE25: -244 | AF25: -312 | AG25: -449 | AH25: -110
A26: ASSETS | O26: 1922 | P26: 2625
A27: Current | B27: =3729.5 -> 3729.5 | C27: =3496.1 -> 3496.1 | D27: =3329.7 -> 3329.7 | E27: =3044.5 -> 3044.5 | F27: =3484.1 -> 3484.1 | G27: =3684 -> 3684 | H27: =3474 -> 3474 | I27: =3230 -> 3230 | J27: =2977.6 -> 2977.6 | K27: =2910.8 -> 2910.8 | L27: =2747.2 -> 2747.2 | M27: =2471.2 -> 2471.2 | N27: =2034.2 -> 2034.2
A28: Cash & Eq. | B28: 152.4 | C28: 133.5 | D28: 199.4 | E28: 460.6 | F28: 81.4 | G28: 93.6 | H28: 90.3 | I28: 177.4 | J28: 83.1 | K28: 110.1 | L28: =63.9 -> 63.9 | M28: =331.5 -> 331.5 | N28: =85.8 -> 85.8 | O28: Balance Sheet | P28: Cash & Eq.
A29: Accounts Receivable | B29: 832.8 | C29: 901.6 | D29: =899 -> 899 | E29: =785.3 -> 785.3 | F29: =864.8 -> 864.8 | G29: =846.9 -> 846.9 | H29: 776.2 | I29: =737 -> 737 | J29: 732.5 | K29: 598.9 | L29: =626.2 -> 626.2 | M29: =471.9 -> 471.9 | N29: =437.6 -> 437.6 | O29: Balance Sheet | P29: Accounts Receivable
A30: Inventory | B30: 2078.3 | C30: 1898.7 | D30: 1573.2 | E30: 1291.1 | F30: 1373.6 | G30: 2130.4 | H30: 2084 | I30: 1955.1 | J30: 1851.6 | K30: 1827.2 | L30: =1743.8 -> 1743.8 | M30: =1480.9 -> 1480.9 | N30: =1374.5 -> 1374.5 | O30: Balance Sheet | P30: Inventory | R30: Balance | S30: + Efectivo, equivalentes y STI | AA30: 7168 | AB30: 6460 | AC30: 7341 | AD30: 6081 | AE30: 5490 | AF30: 3057 | AG30: 3592 | AH30: 4867
A31: Other Current Assets | B31: =B27-SUM(B28:B30) -> 666 | C31: =C27-SUM(C28:C30) -> 562.3 | D31: =D27-SUM(D28:D30) -> 658.1 | E31: =E27-SUM(E28:E30) -> 507.5 | F31: =F27-SUM(F28:F30) -> 1164.3 | G31: =G27-SUM(G28:G30) -> 613.1 | H31: =H27-SUM(H28:H30) -> 523.5 | I31: =I27-SUM(I28:I30) -> 360.5 | ... N31: =N27-SUM(N28:N30) -> 136.3 | O31: Balance Sheet | P31: Inventory | R31: Balance | S31: + Cuentas y notas por cobrar | T31: + Activos derivados y de cobertura | U31: + Inversiones y cuentas por cobrar a LP | AA31: =5981+8522+1029+13556 -> 29088 | AB31: =6695+8991+1170+13651 -> 30507 | AC31: =7737+9027+1364+14644 -> 32772 | AD31: 33499 | AE31: 33911 | AF31: 31031 | AG31: 28849 | AH31: 27162
A32: Non-current | B32: =B38-B27 -> 21962.2 | C32: =C38-C27 -> 21166.2 | D32: =D38-D27 -> 22526.1 | E32: =E38-E27 -> 24060.3 | F32: =F38-F27 -> 23839.1 | G32: =G38-G27 -> 25547.5 | H32: =H38-H27 -> 17064.7 | I32: =I38-I27 -> 15372.4 | ... N32: =N38-N27 -> 5075.7
A33: Property, Plant and Equipment | B33: =8055.2 -> 8055.2 | C33: =6865.2 -> 6865.2 | D33: =6059.6 -> 6059.6 | E33: =5821.6 -> 5821.6 | F33: =5333 -> 5333 | G33: =5267.3 -> 5267.3 | H33: =4789.7 -> 4789.7 | I33: =3932.8 -> 3932.8 | J33: =3333.4 -> 3333.4 | K33: =2681.6 -> 2681.6 | L33: =2014.3 -> 2014.3 | M33: =1229 -> 1229 | N33: =1255.8 -> 1255.8 | R33: Balance | S33: + Inventarios | AA33: 8614 | AB33: 9700 | AC33: 12205 | AD33: 12625 | AE33: 15547 | AF33: 14544 | AG33: 9587 | AH33: 6360
A34: Operating leases | B34: 615.3 | C34: 442.5 | D34: 478.9 | E34: =477.9 -> 477.9 | F34: =481.4 -> 481.4 | G34: 559.5 | H34: 559.2 | I34: 497.7 | J34: 355.3 | K34: 392.5 | L34: =406 -> 406 | M34: =343.4 -> 343.4 | N34: =374.6 -> 374.6
A35: Equity Method Investments | B35: 170.6 | C35: 663.3 | D35: 2688.7 | E35: 2788.4 | F35: 3093.9 | G35: 3465.6 | H35: 121.5 | I35: 77.6 | J35: 76.2 | K35: 73.5 | L35: =73.3 -> 73.3 | M35: =243.6 -> 243.6 | N35: =248.3 -> 248.3
A36: Other Non-Current Assets | B36: =B32-SUM(B33:B35) -> 13121.1 | C36: =C32-SUM(C33:C35) -> 13195.2 | D36: =D32-SUM(D33:D35) -> 13298.9 | E36: =E32-SUM(E33:E35) -> 14972.4 | F36: =F32-SUM(F33:F35) -> 14930.8 | G36: =G32-SUM(G33:G35) -> 16255.1 | H36: =H32-SUM(H33:H35) -> 11594.3 | I36: =I32-SUM(I33:I35) -> 10864.3 | ... N36: =N32-SUM(N33:N35) -> 3197 | O36: Balance Sheet | P36: Property, Plant and Equipment
A37: Other Assets | B37: =B31+B36 -> 13787.1 | C37: =C31+C36 -> 13757.5 | D37: =D31+D36 -> 13957 | E37: =E31+E36 -> 15479.9 | F37: =F31+F36 -> 16095.1 | G37: =G31+G36 -> 16868.2 | H37: =H31+H36 -> 12117.8 | I37: =I31+I36 -> 11224.8 | ... N37: =N31+N36 -> 3333.3 | O37: Balance Sheet
A38: Total Assets | B38: 25691.7 | C38: 24662.3 | D38: 25855.8 | E38: 27104.8 | F38: 27323.2 | G38: 29231.5 | H38: 20538.7 | I38: 18602.4 | J38: 16965 | K38: 15093 | L38: =14302.1 -> 14302.1 | M38: =7638.1 -> 7638.1 | N38: =7109.9 -> 7109.9 | O38: Balance Sheet | P38: Total Assets | R38: Balance | S38: + Propiedad, planta y equipo; neto | AA38: 15322 | AB38: 16090 | AC38: =16577 -> 16577 | AD38: 17075 | AE38: 16461 | AF38: 14395 | AG38: 12539 | AH38: 12386
O39: Balance Sheet | AA39: =AA40-SUM(AA30:AA38) -> 14512 | AB39: =AB40-SUM(AB30:AB38) -> 15585 | AC39: =AC40-SUM(AC30:AC38) -> 15786 | AD39: =AD40-SUM(AD30:AD38) -> 15616 | AE39: =AE40-SUM(AE30:AE38) -> 17947 | AF39: =AF40-SUM(AF30:AF38) -> 18419 | AG39: =AG40-SUM(AG30:AG38) -> 9453 | AH39: =AH40-SUM(AH30:AH38) -> 9263
O40: Balance Sheet | R40: Balance | S40: Activos totales | AA40: 74704 | AB40: 78342 | AC40: 84681 | AD40: 84896 | AE40: 89356 | AF40: 81446 | AG40: 64020 | AH40: 60038
A41: LIABILITIES | O41: Balance Sheet
A42: Current Liabilities | B42: 3141.7 | C42: 2968.3 | D42: 2698.8 | E42: 1269.1 | F42: 2311.8 | G42: 3163.8 | H42: 2039.6 | I42: 2697.6 | J42: 2272.3 | K42: 1130.7 | L42: =2025.7 -> 2025.7 | M42: =677.9 -> 677.9 | N42: =1190.6 -> 1190.6 | O42: Balance Sheet | P42: Current Liabilities
A43: Payables | B43: 1107.1 | C43: 941.5 | D43: 899.2 | E43: 460 | F43: 557.6 | G43: =616.7 -> 616.7 | H43: 592.2 | I43: =559.8 -> 559.8 | J43: =429.3 -> 429.3 | K43: 285.8 | L43: =295.2 -> 295.2 | M43: =209 -> 209 | N43: =130.5 -> 130.5
A44: Short-Term Debt | B44: 1198.2 | C44: 1185.2 | D44: 928.3 | E44: 29.2 | F44: 973.8 | G44: 1856.7 | H44: 769.1 | I44: 1517.4 | J44: 1265 | K44: 210.5 | L44: =590 -> 590 | M44: =27.6 -> 27.6 | N44: =330.2 -> 330.2 | O44: Balance Sheet | P44: Short term Debt | R44: Balance | S44: Pasivos totales corrientes | AA44: 26132 | AB44: 26242 | AC44: 27877 | AD44: 27297 | AE44: 29415 | AF44: =93+3895+8161+3386+2410+2691+298+1967+558+5102 -> 28561 | AG44: =204+3852+5856+2880+1670+1831+281+1521+495+3430 -> 22020 | AH44: =433+3650+2993+3351+797+1217+262+888+302+5399 -> 19292
A45: Short-Term Leases | B45: =89.6+7.5 -> 97.1 | C45: 90.9 | D45: 86.7 | E45: 73.4 | F45: 88.3 | G45: 0 | H45: 0 | I45: 0 | J45: 0 | K45: 0 | L45: =0 -> 0 | M45: =0 -> 0 | N45: =0 -> 0
A46: Other current liabilities | B46: =B42-SUM(B43:B45) -> 739.3 | C46: =C42-SUM(C43:C45) -> 750.7 | D46: =D42-SUM(D43:D45) -> 784.6 | E46: =E42-SUM(E43:E45) -> 706.5 | F46: =F42-SUM(F43:F45) -> 692.1 | G46: =G42-SUM(G43:G45) -> 690.4 | H46: =H42-SUM(H43:H45) -> 678.3 | I46: =I42-SUM(I43:I45) -> 620.4 | ... N46: =N42-SUM(N43:N45) -> 729.9 | O46: Balance Sheet | S46: + Préstamos CP | AA46: 7303 | AB46: 6967 | AC46: 4708 | AD46: 3679 | AE46: 5287 | AF46: 5660 | AG46: 3925 | AH46: 5701
A47: Non-current Liabilities | B47: 12485.4 | C47: =C51-C42 -> 12960.1 | D47: =D51-D42 -> 11109.2 | E47: =E51-E42 -> 11906.6 | F47: =F51-F42 -> 12537.1 | G47: =G51-G42 -> 13230.5 | H47: =H51-H42 -> 10507.4 | I47: =I51-I42 -> 9020 | J47: =J51-J42 -> 8000.9 | ... N47: =N51-N42 -> 3243.3 | O47: Balance Sheet | P47: Total non current liabilities
A48: Long-Term Debt | B48: 10681.1 | C48: 11286.5 | D48: 9488.2 | E48: 10413.1 | F48: 11210.8 | G48: 11759.8 | H48: 9417.6 | I48: 7720.7 | J48: 6816.2 | K48: 7086 | L48: =6373.3 -> 6373.3 | M48: =3277.8 -> 3277.8 | N48: =2421.4 -> 2421.4 | O48: Balance Sheet | P48: Long term debt | AA48: =AA44-AA46 -> 18829 | AB48: =AB44-AB46 -> 19275 | AC48: =AC44-AC46 -> 23169 | AD48: =AD44-AD46 -> 23618 | AE48: =AE44-AE46 -> 24128 | AF48: =AF44-AF46 -> 22901 | AG48: =AG44-AG46 -> 18095 | AH48: =AH44-AH46 -> 13591
A49: Long-Term Leases | B49: =588.7+10.3 -> 599 | C49: 434.1 | D49: 470.9 | E49: 482 | F49: 496.6 | G49: 0 | H49: 0 | I49: 0 | J49: 0 | K49: 0 | L49: =0 -> 0 | M49: =0 -> 0 | N49: =0 -> 0 | R49: Balance | S49: Pasivos totales no corrientes | AA49: =61491-AA44 -> 35359 | AB49: =63457-AB44 -> 37215 | AC49: =67855-AC44 -> 39978 | AD49: 36721 | AE49: 41973 | AF49: =8415+16529+10956+3583 -> 39483 | AG49: =4505+15932+7584+2654 -> 30675 | AH49: =5652+16195+7420+2179 -> 31446
A50: Other non-current liabilities | B50: =B47-SUM(B48:B49) -> 1205.3 | C50: =C47-SUM(C48:C49) -> 1239.5 | D50: =D47-SUM(D48:D49) -> 1150.1 | E50: =E47-SUM(E48:E49) -> 1011.5 | F50: =F47-SUM(F48:F49) -> 829.7 | G50: =G47-SUM(G48:G49) -> 1470.7 | H50: =H47-SUM(H48:H49) -> 1089.8 | I50: =I47-SUM(I48:I49) -> 1299.3 | ... N50: =N47-SUM(N48:N49) -> 821.9 | O50: Balance Sheet | P50: Other non current Liabilities | S50: + Préstamos a largo plazo | AA50: 22818 | AB50: 25169 | AC50: 27784 | AD50: 26719 | AE50: 27752 | AF50: 24944 | AG50: 20437 | AH50: 21847
A51: Total Liabilities | B51: 15627.1 | C51: 15928.4 | D51: 13808 | E51: 13175.7 | F51: 14848.9 | G51: 16394.3 | H51: 12547 | I51: 11717.6 | J51: 10273.2 | K51: 9211.7 | L51: =L38-4981.3 -> 9320.8 | M51: =M38-2860.3 -> 4777.8 | N51: =N38-2676 -> 4433.9 | O51: Balance Sheet | P51: Total Liabilities
O52: Balance Sheet | AA52: =AA49-AA50 -> 12541 | AB52: =AB49-AB50 -> 12046 | AC52: =AC49-AC50 -> 12194 | AD52: =AD49-AD50 -> 10002 | AE52: =AE49-AE50 -> 14221 | AF52: =AF49-AF50 -> 14539 | AG52: =AG49-AG50 -> 10238 | AH52: =AH49-AH50 -> 9599
O53: Balance Sheet | AA53: =+AA49+AA44 -> 61491 | AB53: =+AB49+AB44 -> 63457 | AC53: =+AC49+AC44 -> 67855 | AD53: =AD44+AD49 -> 64018 | AE53: =AE49+AE44 -> 71388 | AF53: =AF49+AF44 -> 68044 | AG53: =AG49+AG44 -> 52695 | AH53: =AH49+AH44 -> 50738
A54: Minority Interest | B54: 321.5 | C54: 320.3 | D54: 315.9 | E54: 330.2 | F54: 342.5 | G54: 286.2 | H54: 16.6 | I54: -6.4 | J54: 132.2 | K54: 110.6 | L54: 0 | M54: 0 | N54: 0 | O54: Balance Sheet | P54: Minority Interest
O55: Balance Sheet
A56: Shareholder's Equity | B56: =B38-B51-B54 -> 9743.1 | C56: =C38-C51-C54 -> 8413.6 | D56: =D38-D51-D54 -> 11731.9 | E56: =E38-E51-E54 -> 13598.9 | F56: =F38-F51-F54 -> 12131.8 | G56: =G38-G51-G54 -> 12551 | H56: =H38-H51-H54 -> 7975.1 | I56: =I38-I51-I54 -> 6891.2 | ... N56: =N38-N51-N54 -> 2676 | O56: Balance Sheet | R56: Balance | S56: + Participación minoritaria/no dominante
A58: CASH FLOW
A59: Operating CF | B59: 2780 | C59: 2756.9 | D59: 2705.4 | E59: 2806.5 | F59: 2551.1 | G59: 2246.3 | H59: 1931.4 | I59: 1696 | J59: 1413.7 | K59: 1081 | L59: 826.2 | M59: 556.3 | N59: 784.1
A60: Net Income | B60: =B12 -> 1765.2 | C60: =C12 -> -38.5 | D60: =D12 -> 1 | E60: =E12 -> 2031.8 | F60: =F12 -> 21.4 | G60: =G12 -> 3459.1 | H60: =H12 -> 2330.8 | I60: =I12 -> 1539.2 | ... N60: =N12 -> 445
A61: Depreciation & Amortization | B61: 429.2 | C61: 400 | D61: 342.4 | E61: 305.1 | F61: 343.2 | G61: 447.1 | H61: 386.5 | I61: 293.9 | J61: 221 | K61: 202 | L61: 166.9 | M61: 120.2 | N61: 110.3
A62: Changes in assets and liabilities | B62: 483.6 | C62: 925.7 | D62: 849 | E62: 489.7 | F62: 134.9 | G62: 280.3 | H62: 353.8 | I62: 510.1 | J62: 322.2 | K62: 266.9 | L62: =36.5-41.4-0.2-49.3-5.5+58.1 -> -1.8 | M62: =-38.9-90-9.6+76.9-5.8-0.3 -> -67.7 | N62: =-5.6+51.5+6.5-6+10.6+44.6 -> 101.6
A63: Other Adjustments | B63: =B59-B60-B61-B62 -> 102 | C63: =C59-C60-C61-C62 -> 1469.7 | D63: =D59-D60-D61-D62 -> 1513 | E63: =E59-E60-E61-E62 -> -20.1 | F63: =F59-F60-F61-F62 -> 2051.6 | G63: =G59-G60-G61-G62 -> -1940.2 | H63: =H59-H60-H61-H62 -> -1139.7 | I63: =I59-I60-I61-I62 -> -647.2 | ... N63: =N59-N60-N61-N62 -> 127.2
A64: Investing CF | B64: -1285.9 | C64: -999.4 | D64: -1035.8 | E64: -87.9 | F64: -531 | G64: -4831.8 | H64: -1423.1 | I64: -1461.8 | J64: -2207.4 | K64: -1015.9 | L64: -4863.8 | M64: -206.8 | N64: -135.1
A65: Net Capex | B65: -1269.1 | C65: =-1035.4+6.7 -> -1028.7 | D65: =-1026.8+4.1 -> -1022.7 | E65: =-864.6+18.9 -> -845.7 | F65: =-726.5+8.3 -> -718.2 | G65: =-886.3+72.3 -> -814 | H65: =-1058+5.9 -> -1052.1 | I65: -907.4 | J65: -891.3 | K65: -719.4 | L65: -223.5 | M65: -62.1 | N65: -64.8
A66: Investments & Acquisitions | B66: 47.8 | C66: =-37.1-30.8+96.7 -> 28.8 | D66: =-53.5-36.6+74.4+4.6 -> -11.1 | E66: =-19.9-222.4+999.5 -> 757.2 | F66: =269.7+1.5-36.2-48.2 -> 186.8 | G66: =-4081.5-45.6+110.2 -> -4016.9 | H66: =-210.9-150.1 -> -361 | I66: =575.3-1111 -> -535.7 | J66: -1316.4 | K66: -310.3 | L66: -4681.3 | M66: -159.3 | N66: -51.5
A67: Other Inflows (Outflows) | B67: =B64-B65-B66 -> -64.6 | C67: =C64-C65-C66 -> 0.5 | D67: =D64-D65-D66 -> -2 | E67: =E64-E65-E66 -> 0.6 | F67: =F64-F65-F66 -> 0.4 | G67: =G64-G65-G66 -> -0.9 | H67: =H64-H65-H66 -> -10 | I67: =I64-I65-I66 -> -18.7 | ... N67: =N64-N65-N66 -> -18.8
A68: Financing CF | B68: -1474.6 | C68: -1819.9 | D68: -1929.5 | E68: -2346.6 | F68: -2031.4 | G68: 2593.3 | H68: -601.2 | I68: -134.8 | J68: 776 | K68: -16.4 | L68: 3777 | M68: -98.7 | N68: -575.1
A69: Debt Borrowing | B69: 1144.4 | C69: 3344.9 | D69: 995.6 | E69: 1194.7 | F69: 1291.3 | G69: 3657.6 | H69: 7933.4 | I69: 1965.6 | J69: 610 | K69: 905 | L69: 3725 | M69: 2050 | N69: 0
A70: Debt Repayment | B70: -1741.3 | C70: -3038.2 | D70: -1722.9 | E70: -2982.5 | F70: -2756.1 | G70: -142.9 | H70: -7388.1 | I70: -1183 | J70: -582.6 | K70: -632.6 | L70: =-96.4-82.2 -> -178.6 | M70: =-1537.2-35.8 -> -1573 | N70: -475.9
A71: Lease Increases | B71: 0 | C71: 0 | D71: 0 | E71: 0 | F71: 0 | G71: 0 | H71: 0 | I71: 0 | J71: 0 | K71: 0 | L71: 0 | M71: 0 | N71: 0
A72: Lease Payments | B72: -9.7 | C72: -8.8 | D72: -5.9 | E72: -10.5 | F72: =-13.8 -> -13.8 | G72: 0 | H72: 0 | I72: 0 | J72: 0 | K72: 0 | L72: 0 | M72: 0 | N72: 0
A73: Dividends | B73: -653.8 | C73: -587.7 | D73: -573 | E73: -575 | F73: -569.2 | G73: -557.7 | H73: -400.1 | I73: -315.1 | J73: -241.6 | K73: 0 | L73: 0 | M73: 0 | N73: 0 | O73: cash flows FINANCING | P73: Dividends paid
A74: Share buyback | B74: -249.7 | C74: -1700.2 | D74: -1390.5 | E74: -1045.9 | F74: -1045.9 | G74: -995.9 | H74: -512.8 | I74: -453.1 | J74: -330.5 | K74: -796.7 | L74: 0 | M74: -383 | N74: -413.7 | O74: cash flows FINANCING | P74: =+A74 -> Share buyback
A75: Other Inflows (Outflows) | B75: =B68-B69-B70-B71-B72-B73-B74 -> 35.5 | C75: =C68-C69-C70-C71-C72-C73-C74 -> 170.1 | D75: =D68-D69-D70-D71-D72-D73-D74 -> 767.2 | E75: =E68-E69-E70-E71-E72-E73-E74 -> 1072.6 | F75: =F68-F69-F70-F71-F72-F73-F74 -> 1062.3 | G75: =G68-G69-G70-G71-G72-G73-G74 -> 632.2 | H75: =H68-H69-H70-H71-H72-H73-H74 -> -233.6 | I75: =I68-I69-I70-I71-I72-I73-I74 -> -149.2 | ... N75: =N68-N69-N70-N71-N72-N73-N74 -> 314.5
A76: FX | B76: -0.6 | C76: -3.5 | D76: -1.3 | E76: 7.2 | F76: -0.9 | G76: -4.5 | H76: 5.8 | I76: -5.1 | J76: -9.3 | K76: -2.5 | L76: -7 | M76: -5.1 | N76: 2.7
A77: Changes in cash | B77: 18.9 | C77: =C59+C64+C68+C76 -> -65.9 | D77: =D59+D64+D68+D76 -> -261.2 | E77: =E59+E64+E68+E76 -> 379.2 | F77: =F59+F64+F68+F76 -> -12.2 | G77: =G59+G64+G68+G76 -> 3.3 | H77: =H59+H64+H68+H76 -> -87.1 | I77: =I59+I64+I68+I76 -> 94.3 | J77: =J59+J64+J68+J76 -> -27 | ... N77: =N59+N64+N68+N76 -> 76.6
P78: (Vitalis will later fill this info)
A79: Other Data | F79: Corporate Bonds 3, 5 Y 10 | I79: Average Price | K79: Moody's | L79: YTM | M79: DIVISA
A80: Number of employees | B80: 10600 | D80: 10-K | O80: bloomberg
A81: Shares Outstanding (Thousands) | B81: 182190 | D81: Yahoo finance | O81: bloomberg
A82: Float | B82: =73.53*(100) -> 7353 | D82: Yahoo finance | O82: bloomberg
A83: Insiders Own | B83: 0.1194 | D83: Yahoo finance | O83: bloomberg
A84: Fitch/ S&P Rating | B84: BBB+ | D84: 10-K | O84: bloomberg
A85: Dividend Yield(Yahoo Finance) | B85: 0.0174 | D85: Yahoo finance | O85: bloomberg
A86: Daily Volume in Millions of USD | D86: Yahoo Finance | O86: bloomberg
B87: =B5 -> 2024 | C87: =C5 -> 2023 | D87: =D5 -> 2022 | E87: =E5 -> 2021
A88: Short % of Float | B88: =OP!C28 -> 0.01274 | F88: Yahoo Finance
A89: EPS | B89: 3.17 | C89: 9.05 | D89: 0.56 | E89: 4.25 | F89: Yahoo Finance
A92: Excise taxes (as % of total sales) | B92: =B93/(B93+B6) -> -0.081323405 | C92: =C93/(C93+C6) -> -0.083020165 | D92: =D93/(D93+D6) -> -0.087324187 | E92: =E93/(E93+E6) -> -0.094080593 | F92: =F93/(F93+F6) -> -0.10159757 | G92: =G93/(G93+G6) -> -0.10456333 | H92: =H93/(H93+H6) -> -0.10839958 | I92: =I93/(I93+I6) -> -0.11059775 | ... N92: =N93/(N93+N6) -> -0.13942906
A93: Excise taxes (M of $) | B93: -749.2 | C93: -724.6 | D93: -708.4 | E93: -740.8 | F93: -769.5 | G93: -768.3 | H93: -741.8 | I93: -730.1 | J93: -675.4 | K93: -644.1 | L93: -543.3 | M93: -375.3 | N93: -324.8
AO135: =Assumptions!#REF!+1 -> #REF!
AO136: =DCF!AF43 -> 70.293292
AO137: =Assumptions!#REF!*1.15 -> #REF!
AO138: =Assumptions!#REF!*0.85 -> #REF!

Sheet Sector Impact
E2: Sector | F2: Sub-Industry | H2: Low | K2: Sector | L2: Environment | Q2: Social
E3: Communication Services | F3: Interactive Home Entertainment | H3: Medium | L3: CO2 | M3: Water | N3: Energy | O3: Waste | P3: Degradation | Q3: Turnover | R3: Compensation | S3: Reputation | T3: Discrimination | U3: Security | V3: Damage | W3: Pension | X3: Supply | Y3: Community | Z3: Public | AA3: Litigation
E4: Communication Services | F4: Interactive Media & Services | H4: High | K4: Communication Services | L4: Low | M4: Low | N4: Medium | O4: Low | P4: Low | Q4: Medium | R4: Medium | S4: Low | T4: Low | U4: High | V4: Low | W4: Low | X4: Low | Y4: Low | Z4: Low | AA4: Medium
B5: Environmental | E5: Communication Services | F5: Integrated Telecommunication Services | H5: Very High | K5: Consumer Discretionary | L5: Low | M5: Low | N5: Medium | O5: Medium | P5: Low | Q5: Medium | R5: Medium | S5: Low | T5: Low | U5: Medium | V5: Medium | W5: Medium | X5: High | Y5: Low | Z5: High | AA5: Low
B6: Direct CO2 emissions | E6: Communication Services | F6: Cable & Satellite | K6: Consumer Staples | L6: High | M6: Very High | N6: High | O6: High | P6: High | Q6: Medium | R6: High | S6: High | T6: Low | U6: Medium | V6: Medium | W6: Low | X6: High | Y6: Low | Z6: Very High | AA6: Low
B7: Total Water Use | E7: Communication Services | F7: Broadcasting | K7: Energy | L7: Very High | M7: Very High | N7: Medium | O7: Very High | P7: High | Q7: High | R7: Medium | S7: Medium | T7: Medium | U7: Medium | V7: High | W7: Medium | X7: Medium | Y7: High | Z7: High | AA7: Low
K8: Renewable Energy | L8: Low | M8: Low | N8: Low | O8: Medium | P8: Medium | Q8: Low | R8: Medium | S8: Medium | T8: High | U8: Medium | V8: Low | W8: Low | X8: Medium | Y8: Medium | Z8: High | AA8: Low
B9: Total Energy Consumption | E9: Communication Services | F9: Movies & Entertainment | K9: Financials | L9: Low | M9: Low | N9: Low | O9: Low | P9: Low | Q9: Low | R9: Low | S9: Medium | T9: High | U9: Medium | V9: Low | W9: Low | X9: Low | Y9: Low | Z9: Medium | AA9: Low
K10: Forestry | L10: Low | M10: Medium | N10: Low | O10: Medium | P10: High | Q10: Low | R10: Low | S10: Low | T10: Low | U10: Low | V10: Low | W10: Low | X10: Low | Y10: Medium | Z10: Low | AA10: Low
B11: Waste Management | E11: Communication Services | F11: Advertising | K11: Health Care | L11: Low | M11: Medium | N11: Low | O11: Low | P11: Low | Q11: Low | R11: Low | S11: Medium | T11: Low | U11: High | V11: Low | W11: Low | X11: Low | Y11: Low | Z11: Low | AA11: Low
B12: Land Degradation/Deforestation/Biodiversity loss/Animal sufering/... | E12: Communication Services | F12: Alternative Carriers | K12: Industrials | L12: Very High | M12: Very High | N12: Very High | O12: High | P12: High | Q12: Low | R12: Medium | S12: High | T12: Very High | U12: Medium | V12: Very High | W12: Medium | X12: Very High | Y12: Very High | Z12: Very High | AA12: High
B13: Social | E13: Communication Services | F13: Publishing | K13: Information Technology | L13: Medium | M13: Low | N13: High | O13: Low | P13: Low | Q13: Low | R13: Low | S13: Low | T13: Low | U13: High | V13: Low | W13: Low | X13: Low | Y13: Low | Z13: Medium | AA13: Very High
B14: Employee turnover | E14: Communication Services | F14: Wireless Telecommunication Services | K14: Materials | L14: Very High | M14: Very High | N14: Very High | O14: Very High | P14: High | Q14: High | R14: High | S14: Medium | T14: High | U14: Low | V14: Very High | W14: Medium | X14: Medium | Y14: Very High | Z14: High | AA14: Medium
B15: Salaries and compensation | E15: Consumer Discretionary | F15: Automotive Retail | K15: Real Estate | L15: Low | M15: Low | N15: Medium | O15: Low | P15: Low | Q15: Medium | R15: Low | S15: Low | T15: Low | U15: High | V15: Low | W15: Medium | X15: Low | Y15: Medium | Z15: Low | AA15: Low
B16: Reputational issues | E16: Consumer Discretionary | F16: Internet & Direct Marketing Retail | K16: Utilities | L16: Very High | M16: High | N16: High | O16: Medium | P16: High | Q16: Low | R16: Medium | S16: Medium | T16: Low | U16: Medium | V16: Medium | W16: Medium | X16: Medium | Y16: Low | Z16: Medium | AA16: Low
B17: Discrimination issues | E17: Consumer Discretionary | F17: Auto Parts & Equipment
B18: Job security | E18: Consumer Discretionary | F18: Specialty Stores
B19: Health injuries | E19: Consumer Discretionary | F19: Computer & Electronics Retail | L19: Communication Services | M19: Consumer Discretionary | N19: Consumer Staples | O19: Energy | P19: Financials | Q19: Health Care | R19: Industrials | S19: Information Technology | T19: Materials | U19: Real Estate | V19: Utilities
B20: PXP? | E20: Consumer Discretionary | F20: Hotels, Resorts & Cruise Lines | L20: Interactive Home Entertainment | M20: Automotive Retail | N20: Tobacco | O20: Oil & Gas Exploration & Production | P20: Life & Health Insurance | Q20: Health Care Equipment | R20: Industrial Conglomerates | S20: IT Consulting & Other Services | T20: Industrial Gases | U20: Office REITs | V20: Independent Power Producers & Energy Traders
B21: Supply chain | E21: Consumer Discretionary | F21: Restaurants | L21: Interactive Media & Services | M21: Internet & Direct Marketing Retail | N21: Agricultural Products | O21: Oil & Gas Equipment & Services | P21: Property & Casualty Insurance | Q21: Pharmaceuticals | R21: Airlines | S21: Application Software | T21: Specialty Chemicals | U21: Specialized REITs | V21: Electric Utilities
B22: Community involvement | E22: Consumer Discretionary | F22: Homebuilding | L22: Integrated Telecommunication Services | M22: Auto Parts & Equipment | N22: Distillers & Vintners | O22: Integrated Oil & Gas | P22: Consumer Finance | Q22: Health Care Supplies | R22: Building Products | S22: Semiconductors | T22: Paper Packaging | U22: Residential REITs | V22: Multi-Utilities
B23: Public Sector | E23: Consumer Discretionary | F23: General Merchandise Stores | L23: Cable & Satellite | M23: Specialty Stores | N23: Packaged Foods & Meats | O23: Oil & Gas Refining & Marketing | P23: Asset Management & Custody Banks | Q23: Health Care Distributors | R23: Electrical Components & Equipment | S23: Internet Services & Infrastructure | T23: Metal & Glass Containers | U23: Real Estate Services | V23: Water Utilities
B24: Litigation | E24: Consumer Discretionary | F24: Automobile Manufacturers | L24: Broadcasting | M24: Computer & Electronics Retail | N24: Household Products | O24: Oil & Gas Storage & Transportation | P24: Insurance Brokers | Q24: Biotechnology | R24: Aerospace & Defense | S24: Electronic Components | T24: Fertilizers & Agricultural Chemicals | U24: Industrial REITs | V24: Gas Utilities
E25: Consumer Discretionary | F25: Apparel Retail | L25: Movies & Entertainment | M25: Hotels, Resorts & Cruise Lines | N25: Soft Drinks | P25: Multi-line Insurance | Q25: Managed Health Care | R25: Air Freight & Logistics | S25: Technology Hardware, Storage & Peripherals | T25: Commodity Chemicals | U25: Retail REITs
E26: Consumer Discretionary | F26: Consumer Electronics | L26: Advertising | M26: Restaurants | N26: Hypermarkets & Super Centers | P26: Diversified Banks | Q26: Life Sciences Tools & Services | R26: Construction Machinery & Heavy Trucks | S26: Semiconductor Equipment | T26: Diversified Chemicals | U26: Health Care REITs
E27: Consumer Discretionary | F27: Apparel, Accessories & Luxury Goods | L27: Alternative Carriers | M27: Homebuilding | N27: Personal Products | P27: Multi-Sector Holdings | Q27: Health Care Technology | R27: Diversified Support Services | S27: Communications Equipment | T27: Copper | U27: Hotel & Resort REITs
E28: Consumer Discretionary | F28: Leisure Products | L28: Publishing | M28: General Merchandise Stores | N28: Food Retail | P28: Financial Exchanges & Data | Q28: Health Care Services | R28: Railroads | S28: Data Processing & Outsourced Services | T28: Construction Materials
E29: Consumer Discretionary | F29: Home Improvement Retail | L29: Wireless Telecommunication Services | M29: Automobile Manufacturers | N29: Brewers | P29: Investment Banking & Brokerage | Q29: Health Care Facilities | R29: Industrial Machinery | S29: Technology Distributors | T29: Gold
E30: Consumer Discretionary | F30: Casinos & Gaming | M30: Apparel Retail | N30: Food Distributors | P30: Regional Banks | R30: Agricultural & Farm Machinery | S30: Electronic Equipment & Instruments | T30: Steel
E31: Consumer Discretionary | F31: Home Furnishings | M31: Consumer Electronics | N31: Drug Retail | P31: Reinsurance | R31: Research & Consulting Services | S31: Systems Software
E32: Consumer Discretionary | F32: Distributors | M32: Apparel, Accessories & Luxury Goods | P32: Thrifts & Mortgage Finance | R32: Construction & Engineering | S32: Electronic Manufacturing Services
E33: Consumer Discretionary | F33: Housewares & Specialties | M33: Leisure Products | R33: Trucking
E34: Consumer Discretionary | F34: Household Appliances | M34: Home Improvement Retail | R34: Environmental & Facilities Services
E35: Consumer Staples | F35: Tobacco | M35: Casinos & Gaming | R35: Human Resource & Employment Services
E36: Consumer Staples | F36: Agricultural Products | M36: Home Furnishings | R36: Trading Companies & Distributors
E37: Consumer Staples | F37: Distillers & Vintners | M37: Distributors
E38: Consumer Staples | F38: Packaged Foods & Meats | M38: Housewares & Specialties
E39: Consumer Staples | F39: Household Products | M39: Household Appliances
E40: Consumer Staples | F40: Soft Drinks
E41: Consumer Staples | F41: Hypermarkets & Super Centers
E42: Consumer Staples | F42: Personal Products
E43: Consumer Staples | F43: Food Retail
E44: Consumer Staples | F44: Brewers
E45: Consumer Staples | F45: Food Distributors
E46: Consumer Staples | F46: Drug Retail
E47: Energy | F47: Oil & Gas Exploration & Production
E48: Energy | F48: Oil & Gas Equipment & Services
E49: Energy | F49: Integrated Oil & Gas
E50: Energy | F50: Oil & Gas Refining & Marketing
E51: Energy | F51: Oil & Gas Storage & Transportation
... E128: Utilities | F128: Gas Utilities
