Workbook
Name Benchmark: [1]ControlsH!$B$3
Name BestConsOv: #REF!
Name BestConsOv: #REF!
Name Broker_Name: OFFSET(#REF!,0,0,[1]ControlsH!$E$5, 1)
Name Broker_Name: OFFSET(#REF!,0,0,[1]ControlsH!$E$5, 1)
Name calCODE: [1]ControlsH!$C$4
Name Chart_Benchmark_100_Size: OFFSET(#REF!, 0, 0, [1]ControlsH!$E$3, 1)
Name Chart_Date_Size: OFFSET(#REF!, 0, 0, [1]ControlsH!$E$3, 1)
Name Chart_Date_Size: OFFSET(#REF!, 0, 0, [1]ControlsH!$E$3, 1)
Name Chart_Date_VAL1_Size: OFFSET(#REF!, 0, 0, [1]ControlsH!$I$3, 1)
Name Chart_Date_VAL1_Size: OFFSET(#REF!, 0, 0, [1]ControlsH!$I$3, 1)
Name Chart_Date_VAL2_Size: OFFSET(#REF!, 0, 0, [1]ControlsH!$I$5, 1)
Name Chart_Date_VAL2_Size: OFFSET(#REF!, 0, 0, [1]ControlsH!$I$5, 1)
Name Chart_Peer_100_Size: OFFSET(#REF!, 0, 0, [1]ControlsH!$E$3, 1)
Name Chart_Peer_100_Size: OFFSET(#REF!, 0, 0, [1]ControlsH!$E$3, 1)
Name Chart_Price_100_Size: OFFSET(#REF!, 0, 0, [1]ControlsH!$E$3, 1)
Name Chart_Price_100_Size: OFFSET(#REF!, 0, 0, [1]ControlsH!$E$3, 1)
Name Chart_Price_Size: OFFSET(#REF!, 0, 0, [1]ControlsH!$E$3, 1)
Name Chart_Price_Size: OFFSET(#REF!, 0, 0, [1]ControlsH!$E$3, 1)
Name Chart_VAL1_FY1_Size: OFFSET(#REF!, 0, 0, [1]ControlsH!$F$3, 1)
Name Chart_VAL1_FY1_Size: OFFSET(#REF!, 0, 0, [1]ControlsH!$F$3, 1)
Name Chart_VAL1_FY2_Size: OFFSET(#REF!, 0, 0, [1]ControlsH!$G$3, 1)
Name Chart_VAL1_FY2_Size: OFFSET(#REF!, 0, 0, [1]ControlsH!$G$3, 1)
Name Chart_VAL1_FY3_Size: OFFSET(#REF!, 0, 0, [1]ControlsH!$H$3, 1)
Name Chart_VAL1_FY3_Size: OFFSET(#REF!, 0, 0, [1]ControlsH!$H$3, 1)
Name Chart_VAL2_FY1_Size: OFFSET(#REF!, 0, 0, [1]ControlsH!$F$5, 1)
Name Chart_VAL2_FY1_Size: OFFSET(#REF!, 0, 0, [1]ControlsH!$F$5, 1)
Name Chart_VAL2_FY2_Size: OFFSET(#REF!, 0, 0, [1]ControlsH!$G$5, 1)
Name Chart_VAL2_FY2_Size: OFFSET(#REF!, 0, 0, [1]ControlsH!$G$5, 1)
Name Chart_VAL2_FY3_Size: OFFSET(#REF!, 0, 0, [1]ControlsH!$H$5, 1)
Name Chart_VAL2_FY3_Size: OFFSET(#REF!, 0, 0, [1]ControlsH!$H$5, 1)
Name Chart_Volume_Size: OFFSET(#REF!, 0, 0, [1]ControlsH!$E$3, 1)
Name Chart_Volume_Size: OFFSET(#REF!, 0, 0, [1]ControlsH!$E$3, 1)
Name compNAME: [1]ControlsH!$B$6
Name CURRENCY: [1]ControlsH!$B$9
Name currPRICE: [1]Overview!$E$19
Name custBenchmark: [1]Overview!$C$9
Name custED: #REF!
Name custED: #REF!
Name custSD: #REF!
Name custSD: #REF!
Name dayCODE: [1]ControlsH!$C$5
Name ED: [1]ControlsH!$B$5
Name ESTBrokersItem: #REF!
Name ESTBrokersItem: #REF!
Name ESTBrokersPeriod: #REF!
Name ESTBrokersPeriod: #REF!
Name ESTDetailBroker: #REF!
Name ESTDetailBroker: #REF!
Name ESTDetailBroker2: #REF!
Name ESTDetailBroker2: #REF!
Name ESTDetailPeriod: #REF!
Name ESTDetailPeriod: #REF!
Name EstDetPerO: #REF!
Name EstDetPerO: #REF!
Name EstDetPerT: #REF!
Name EstDetPerT: #REF!
Name FinancialsPeriod: #REF!
Name FinancialsPeriod: #REF!
Name fundTICKER: [1]ControlsH!$B$15

Sheet OP
B2: (26/02/2025) | C2: Analista: LIS | D2: Annual Report 2024 | E2: {=_FV(N2,"Name")} -> Dassault Systemes SE | K2: Euronext Paris | L2: SIC: sí | N2: #VALUE!
D3: DESCRIPTION: Dassault Systèmes SE is a French company that provides software solutions for 3D design, simulation, data management, and product lifecycle management across various industries. Its key offerings include SOLIDWORKS, CATIA, SIMULIA, and the 3DEXPERIENCE platform
D4: CEO & BOARD: Pascal Daloz (CEO s.2024; 54;dir.s. 2020); Bernard Charlès (67; dir.s. 1993; Ex. Chairman of the Board of Directors, CEO from 1995 to 2022); Charles Edelstenne (86, , dir.s. 1993, Founder & Honorary Chairman); *Geneviève Berger(69, ,dir.s.2023, Indep. dir & Lead director of Sustainable Development); *Xavier Cauchois(66, , dir.s. 2018, Indep. dir); Catherine Dassault(56, ,dir.s. 2016, dir); *Laurence Daures(50, ,dir.s.2016, Indep. dir. & Lead indep. dir); *Odile Desforges(74, , dir.s.2013, indep. dir); *Soumitra Dutta(60, , dir.s.2017, indep. dir); Olivier Costa de Beauregard(65; , dir.) Anne-Laure Chevalier( , emp. repre); Christine Defert( emp.repre)
B5: Milliones de USD
B6: Acción | D6: Liquidez y Solvencia | F6: Regiones (2023) | I6: Rentabilidad (2024) | K6: Múltiplos
B7: Último Precio | C7: {=_FV(N2,"Previous close",TRUE)} -> 26.21 | D7: Activo: | E7: =Cifras_en_Millones!C45 -> 15545.9 | H7: %Vts; %Op.Mg.; Change | I7: Año termina: | J7: 31/12/2024 | K7: Float: | L7: 0.5104
B8: Outstanding Shares | C8: {=_FV(N2,"Shares outstanding",TRUE)} -> 1341456000 | D8: Pasivo: | E8: =Cifras_en_Millones!C57 -> 6465.2 | F8: =+Segments!B4 -> Americas | H8: =+Segments!F4 -> 0.39962687 | K8: Insiders Own: | L8: 0.4812
B9: Market Cap. | C9: =C7*C8/1000000 -> 35159.562 | D9: Cash/Precio | E9: =+C11/C8*1000000 -> 2.9464999 | F9: =+Segments!B5 -> Europe | H9: =+Segments!F5 -> 0.37817164 | I9: EBIT | J9: =Cifras_en_Millones!C11 -> 1359.6 | K9: b (Bloomberg; Yahoo) | L9: 0,82
B10: +Deuda Total | C10: =Cifras_en_Millones!C60 -> 2493.6 | D10: Ebidta/CIF | E10: =Cifras_en_Millones!C19/Cifras_en_Millones!C14 -> -6.7449324 | F10: =+Segments!B6 -> Asia | H10: =+Segments!F6 -> 0.22220149 | I10: +Dep&Amort | J10: =Cifras_en_Millones!C17 -> -561 | K10: Calificación (S&P) | L10: A
B11: -Cash | C11: =Cifras_en_Millones!C40 -> 3952.6 | D11: Deuda/Ebidta | E11: =Cifras_en_Millones!C60/Cifras_en_Millones!C19 -> 3.1224643 | I11: =EBIDTA | J11: =+J9+J10 -> 798.6 | K11: Precio/Valor en libros | L11: =((C7*C8)/1000000)/(E7-E8) -> 3.8718999
B12: =Enterprise Value | C12: =C9+C10-C11 -> 33700.562 | D12: "Otros activos"/Activo | E12: =Cifras_en_Millones!C44/Cifras_en_Millones!C45 -> 0.54654282 | I12: Utilidad Neta | J12: =Cifras_en_Millones!C23 -> 1198.1 | K12: FNP(p)/Activos | L12: =J18/E7 -> 0.042463501
B13: Tenencia % (nac/int'l) | D13: Deuda/Activo | E13: =Cifras_en_Millones!C60/Cifras_en_Millones!C45 -> 0.16040242 | F13: Productos (2023) | I13: UPA | J13: =+J12/C8*1000000 -> 0.89313403 | K13: Precio/Utilidad(p) | L13: =C9/J17 -> 31.276575
B14: t liq. (Pos prom./Vol.) | D14: Margen de Operación (p) | E14: =AVERAGE(Cifras_en_Millones!C12:E12) -> 0.21915431 | H14: %Vts; %Op.Mg.; Change | I14: ROA | J14: =+J12/E7 -> 0.077068552 | K14: EV/Activos | L14: =C12/E7 -> 2.1678103
B15: % Short | D15: Margen neto (p) | E15: =AVERAGE(Cifras_en_Millones!C24:E24) -> 0.17782473 | F15: =+Segments!B17 -> Industrial Innovation | H15: =+Segments!F17 -> 0.54253731 | I15: ROIC | J15: =J12/(E7-(E8-C10)) -> 0.10351382 | K15: EV/Ebidta (p) | L15: =C12/J16 -> 66.941459
B16: Semáforo ESG | D16: Ebidta/Ingresos(p) | E16: =AVERAGE(Cifras_en_Millones!C20:E20) -> 0.12490169 | F16: =+Segments!B18 -> Life Sciences | H16: =+Segments!F18 -> 0.21623134 | I16: Ebidta(p) | J16: =AVERAGE(Cifras_en_Millones!B19:D19) -> 503.43333 | K16: Precio/FNP (p) | L16: =C9/J18 -> 53.261303
B17: E | D17: CIF/Deuda Neta Promedio | E17: =Cifras_en_Millones!C14/AVERAGE(Cifras_en_Millones!C59:D59) -> 0.16601234 | F17: =+Segments!B19 -> Mainstream Innovation | H17: =+Segments!F19 -> 0.24123134 | I17: Utilidad Neta (p) | J17: =AVERAGE(Cifras_en_Millones!B23:D23) -> 1124.15 | K17: Bonos 1;5;40a (USD)
B18: S | I18: FNP (p) | J18: =SUM(F36:F37)/3 -> 660.13333 | K18: TDY(p)/Precio | L18: =SUM(E34:E36)/(3*C9) -> -0.010787013
B19: G | I19: Tax (p) últ. 5a | J19: =AVERAGE(Cifras_en_Millones!C22:G22) -> -0.22648854 | K19: Div. Yield: | L19: =-K33/C9 -> 0.0086093223
B20: Tese de Inversión
B21: The decision to sell is based on a negative DCF valuation, which sets a price target of $23.3, implying a -43% downside compared to the current share price of $37.98. While the software market has strong growth potential, risks related to geopolitical uncertainty, raw material price volatility, and a potential slowdown in demand add further concerns. It is also important to note that the valuation model used was the Dividend Discount Model, which only considers dividends paid and share buybacks, potentially undervaluing the company. If a valuation approach based on Free Cash Flow to the Firm had been used, the price target might have been higher, better reflecting the company's growth potential. | H21: SELL | I21: VER DCF | L21: =DCFF!D66 -> 29.300464
B23: KSF | L23: =DCFF!D65 -> 0.14053967
H24: =+DCFF!D66 -> 29.300464 | I24: Tasa de descuento | J24: =DCFF!D47 -> 0.08
B25: Año | C25: Ingresos | D25: Margen Operativo | E25: Div.+Recompra | F25: FNP | G25: Deuda/Activo | H25: Depreciación | I25: Capex + Adq | J25: Cash Flow
B26: 2012 | C26: =Cifras_Originales!N6 -> 2028.342 | D26: =Cifras_Originales!N8/C26 -> 0.24698054 | E26: =Cifras_Originales!N17+Cifras_Originales!N18 -> -64.2 | F26: =Cifras_Originales!$N$16 -> 338.829 | G26: =Cifras_Originales!$N$39/Cifras_Originales!$N$27 -> 0.34860481 | H26: =Cifras_Originales!$N$11 -> -132.1 | I26: =Cifras_Originales!$N$13+Cifras_Originales!$N$14 -> -218.8 | K26: 2024 | L26: 2023
B27: =B26+1 -> 2013 | C27: =Cifras_Originales!M6 -> 2066.1 | D27: =Cifras_Originales!M8/C27 -> 0.24345385 | E27: =Cifras_Originales!M17+Cifras_Originales!M18 -> -51.5 | F27: =Cifras_Originales!$M$16 -> 355.2 | G27: =Cifras_Originales!$M$39/Cifras_Originales!$M$27 -> 0.37338523 | H27: =Cifras_Originales!$M$11 -> -141.3 | I27: =Cifras_Originales!$M$13+Cifras_Originales!$M$14 -> -168.6 | J27: Utilidad Neta | K27: =Cifras_Originales!B16 -> 1198.1 | L27: =Cifras_Originales!C16 -> 1050.2 | N27: =C27/C26-1 -> 0.018615204 | O27: =D27/D26-1 -> -0.014279216
B28: =B27+1 -> 2014 | C28: =Cifras_Originales!L6 -> 2294.3 | D28: =Cifras_Originales!L8/C28 -> 0.18776969 | E28: =Cifras_Originales!L17+Cifras_Originales!L18 -> -149.6 | F28: =Cifras_Originales!$L$16 -> 292.5 | G28: =Cifras_Originales!$L$39/Cifras_Originales!$L$27 -> 0.40361519 | H28: =Cifras_Originales!$L$11 -> -176.3 | I28: =Cifras_Originales!$L$13+Cifras_Originales!$L$14 -> -1000.9 | J28: Cash Flow from Operations (BWC) | K28: =+K29+1660 -> 1373.7 | L28: =1565+L29 -> 1325.5 | N28: =C28/C27-1 -> 0.11044964 | O28: =D28/D27-1 -> -0.22872573 | P28: =E28/E27-1 -> 1.9048544 | Q28: =F28/F27-1 -> -0.17652027 | R28: =H28/H27-1 -> 0.24769993 | S28: =I28/I27-1 -> 4.9365362
B29: =B28+1 -> 2015 | C29: =Cifras_Originales!K6 -> 2839.5 | D29: =Cifras_Originales!K8/C29 -> 0.22299701 | E29: =Cifras_Originales!K17+Cifras_Originales!K18 -> -90.8 | F29: =Cifras_Originales!$K$16 -> 406 | G29: =Cifras_Originales!$K$39/Cifras_Originales!$K$27 -> 0.44739677 | H29: =Cifras_Originales!$K$11 -> -211.4 | I29: =Cifras_Originales!$K$13+Cifras_Originales!$K$14 -> -60.5 | J29: Working Capital | K29: =Cifras_Originales!B12 -> -286.3 | L29: =Cifras_Originales!C12 -> -239.5 | N29: =C29/C28-1 -> 0.23763239 | O29: =D29/D28-1 -> 0.18760917 | P29: =E29/E28-1 -> -0.39304813 | Q29: =F29/F28-1 -> 0.38803419 | R29: =H29/H28-1 -> 0.19909246 | S29: =I29/I28-1 -> -0.9395544
B30: =B29+1 -> 2016 | C30: =Cifras_Originales!J6 -> 3055.6 | D30: =Cifras_Originales!J8/C30 -> 0.21992407 | E30: =Cifras_Originales!J17+Cifras_Originales!J18 -> -202.3 | F30: =Cifras_Originales!$J$16 -> 452.2 | G30: =Cifras_Originales!$J$39/Cifras_Originales!$J$27 -> 0.44075413 | H30: =Cifras_Originales!$J$11 -> -206.4 | I30: =Cifras_Originales!$J$13+Cifras_Originales!$J$14 -> -299 | J30: Investing Activities | K30: -191.7 | L30: -161.6 | N30: =C30/C29-1 -> 0.076104948 | O30: =D30/D29-1 -> -0.013780152 | P30: =E30/E29-1 -> 1.2279736 | Q30: =F31/F29-1 -> 0.28103448 | R30: =H30/H29-1 -> -0.023651845 | S30: =I30/I29-1 -> 3.9421488
B31: =B30+1 -> 2017 | C31: =Cifras_Originales!I6 -> 3228 | D31: =Cifras_Originales!I8/C31 -> 0.22583643 | E31: =Cifras_Originales!I17+Cifras_Originales!I18 -> -121.9 | F31: =Cifras_Originales!$I$16 -> 520.1 | G31: =Cifras_Originales!$I$39/Cifras_Originales!$I$27 -> 0.43156278 | H31: =Cifras_Originales!$I$11 -> -217.7 | I31: =Cifras_Originales!$I$13+Cifras_Originales!$I$14 -> -367.4 | J31: Capex | K31: =Cifras_Originales!B13 -> -193.4 | L31: =Cifras_Originales!C13 -> -145.3 | N31: =C31/C30-1 -> 0.056420998 | O31: =D31/D30-1 -> 0.02688363 | P31: =#REF!/E30-1 -> #REF! | Q31: =F32/F31-1 -> 0.083253221 | R31: =H31/H30-1 -> 0.054748062 | S31: =I31/I30-1 -> 0.22876254
B32: =B31+1 -> 2018 | C32: =Cifras_Originales!H6 -> 3477.4 | D32: =Cifras_Originales!H8/C32 -> 0.22091218 | E32: =Cifras_Originales!H17+Cifras_Originales!H18 -> -174.4 | F32: =Cifras_Originales!$H$16 -> 563.4 | G32: =Cifras_Originales!$H$39/Cifras_Originales!$H$27 -> 0.4198771 | H32: =Cifras_Originales!$H$11 -> -237.7 | I32: =Cifras_Originales!$H$13+Cifras_Originales!$H$14 -> -323.2 | J32: Adquisiones | K32: =Cifras_en_Millones!C34 -> 1.6 | L32: =+Cifras_Originales!C33 -> 66.5 | N32: =C32/C31-1 -> 0.077261462 | O32: =D32/D31-1 -> -0.021804522 | P32: =E31/#REF!-1 -> #REF! | Q32: =F33/F32-1 -> 0.076144835 | R32: =H32/H31-1 -> 0.091869545 | S32: =I32/I31-1 -> -0.12030484
B33: =B32+1 -> 2019 | C33: =Cifras_Originales!G6 -> 4018.2 | D33: =Cifras_Originales!G8/C33 -> 0.20227963 | E33: =Cifras_Originales!G17+Cifras_Originales!G18 -> -212.2 | F33: =Cifras_Originales!$G$16 -> 606.3 | G33: =Cifras_Originales!$G$39/Cifras_Originales!$G$27 -> 0.6206551 | H33: =Cifras_Originales!$G$11 -> -396 | I33: =Cifras_Originales!$G$13+Cifras_Originales!$G$14 -> -5334.8 | J33: Dividends | K33: =Cifras_Originales!B17 -> -302.7 | L33: =Cifras_Originales!C17 -> -276.2 | N33: =C33/C32-1 -> 0.15551849 | O33: =D33/D32-1 -> -0.08434369 | P33: =E32/E31-1 -> 0.43068089 | Q33: =F34/F33-1 -> -0.1992413 | R33: =H33/H32-1 -> 0.6659655 | S33: =I33/I32-1 -> 15.506188
B34: =B33+1 -> 2020 | C34: =Cifras_Originales!F6 -> 4452.3 | D34: =Cifras_Originales!F8/C34 -> 0.15041664 | E34: =Cifras_Originales!F17+Cifras_Originales!F18 -> -261 | F34: =Cifras_Originales!$F$16 -> 485.5 | G34: =Cifras_Originales!$F$39/Cifras_Originales!$F$27 -> 0.60613844 | H34: =Cifras_Originales!$F$11 -> -604.5 | I34: =Cifras_Originales!$F$13+Cifras_Originales!$F$14 -> -208 | J34: Stock Repurchases | K34: =Cifras_Originales!B18 -> -325.6 | L34: =Cifras_Originales!C18 -> -162.3 | N34: =C34/C33-1 -> 0.10803345 | O34: =D34/D33-1 -> -0.25639255 | P34: =E33/E32-1 -> 0.21674312 | Q34: =F35/F34-1 -> 0.59402678 | R34: =H34/H33-1 -> 0.52651515 | S34: =I34/I33-1 -> -0.96101072
B35: =B34+1 -> 2021 | C35: =Cifras_Originales!E6 -> 4860 | D35: =Cifras_Originales!E8/C35 -> 0.20975309 | E35: =Cifras_Originales!E17+Cifras_Originales!E18 -> -274.3 | F35: =Cifras_Originales!$E$16 -> 773.9 | G35: =Cifras_Originales!$E$39/Cifras_Originales!$E$27 -> 0.56318088 | H35: =Cifras_Originales!$E$11 -> -574.6 | I35: =Cifras_Originales!$E$13+Cifras_Originales!$E$14 -> -160.4 | J35: Endeudamiento Neto | K35: =(Cifras_en_Millones!$C$54+Cifras_en_Millones!$C$50)-(Cifras_en_Millones!$D$50+Cifras_en_Millones!$D$54) -> -497.1 | L35: =(Cifras_en_Millones!$D$54+Cifras_en_Millones!$D$50)-(Cifras_en_Millones!$E$50+Cifras_en_Millones!$E54) -> -5.3 | N35: =C35/C34-1 -> 0.091570649 | O35: =D35/D34-1 -> 0.39448061 | P35: =E34/E33-1 -> 0.22997172 | Q35: =F36/F35-1 -> 0.20196408 | R35: =H35/H34-1 -> -0.049462366 | S35: =I35/I34-1 -> -0.22884615
B36: =B35+1 -> 2022 | C36: =Cifras_Originales!D6 -> 5665.3 | D36: =Cifras_Originales!D8/C36 -> 0.22997899 | E36: =Cifras_Originales!D17+Cifras_Originales!D18 -> -602.5 | F36: =Cifras_Originales!$D$16 -> 930.2 | G36: =Cifras_Originales!$D$39/Cifras_Originales!$D$27 -> 0.48637202 | H36: =Cifras_Originales!$D$11 -> -596.8 | I36: =Cifras_Originales!$D$13+Cifras_Originales!$D$14 -> -213.9 | J36: Otros Financiemientos | K36: =1211.9-OP!$K$33-OP!$K$35 -> 2011.7 | L36: =537-OP!$L$33-OP!$L$35 -> 818.5 | N36: =C36/C35-1 -> 0.16569959 | O36: =D36/D35-1 -> 0.096427227
B37: =B36+1 -> 2023 | C37: =Cifras_Originales!C6 -> 5951.4 | D37: =Cifras_Originales!C8/C37 -> 0.20867359 | E37: =Cifras_Originales!C17+Cifras_Originales!C18 -> -438.5 | F37: =Cifras_Originales!$C16 -> 1050.2 | G37: =Cifras_Originales!$C$39/Cifras_Originales!$C$27 -> 0.46342598 | H37: =Cifras_Originales!$C$11 -> -569.5 | I37: =Cifras_Originales!$C$13+Cifras_Originales!$C$14 -> -161.7 | N37: =C37/C36-1 -> 0.050500415 | O37: =D37/D36-1 -> -0.092640658
B38: 2024 | C38: =Cifras_Originales!B6 -> 6213.6 | D38: =Cifras_Originales!B8/Cifras_Originales!B6 -> 0.21881035 | E38: =Cifras_Originales!B17+Cifras_Originales!B18 -> -628.3 | F38: =Cifras_Originales!B16 -> 1198.1 | G38: =Cifras_Originales!$B$39/Cifras_Originales!$B$27 -> 0.41587814 | H38: =Cifras_Originales!$B$11 -> -561 | I38: =Cifras_Originales!$B$13+Cifras_Originales!$B$14 -> -191.8
B39: CAGR | C39: =(C38/C26)^(1/($B$38-$B$26))-1 -> 0.097783863 | D39: =(D38/D26)^(1/($B$38-$B$26))-1 -> -0.01004126 | E39: =(E38/E26)^(1/($B$38-$B$26))-1 -> 0.20935184 | F39: =(F38/F26)^(1/($B$38-$B$26))-1 -> 0.11098802 | G39: =(G38/G26)^(1/($B$38-$B$26))-1 -> 0.01481309 | H39: =(H38/H26)^(1/($B$38-$B$26))-1 -> 0.12807594 | I39: =(I38/I26)^(1/($B$38-$B$26))-1 -> -0.010915399 | J39: FX | K39: -67.5 | L39: 128.2
B40: AAG | C40: =AVERAGE(N27:N37) -> 0.10434611 | D40: =AVERAGE(O27:O37) -> -0.00059689773 | E40: =(E38-E26)/13 -> -43.392308 | F40: =AVERAGE(Q27:Q37) -> 0.156087 | G40: =AVERAGE(R27:R37) -> 0.21409705 | H40: =AVERAGE(S27:S37) -> 2.7954899 | J40: Change in Cash and Eq. | K40: =Cifras_en_Millones!C40-Cifras_en_Millones!D40 -> 384.3 | L40: =Cifras_en_Millones!D40-Cifras_en_Millones!E40 -> 799.3
B41: CVAR | C41: =+STDEV(C26:C37)/AVERAGE(C26:C37) -> 0.3663778 | D41: =+STDEV(D26:D37)/AVERAGE(D26:D37) -> 0.12139251 | E41: =+STDEV(E26:E36)/AVERAGE(E26:E36) -> -0.76177535 | F41: =+STDEV(F26:F37)/AVERAGE(F26:F37) -> 0.42389175 | G41: =+STDEV(G26:G37)/AVERAGE(G26:G37) -> 0.18704179 | H41: =+STDEV(H26:H37)/AVERAGE(H26:H37) -> -0.57420508 | I41: =+STDEV(I26:I37)/AVERAGE(I26:I37) -> -2.0796445 | J41: Inv/Change in Vts | K41: =K31/(Cifras_en_Millones!C5-Cifras_en_Millones!D5) -> -0.73760488 | L41: =L31/(Cifras_en_Millones!D5-Cifras_en_Millones!E5) -> -0.50786438
B42: Último Año | C42: =C37/C36-1 -> 0.050500415 | D42: =D37/D36-1 -> -0.092640658 | E42: =E36/E35-1 -> 1.1965002 | F42: =F37/F36-1 -> 0.12900452 | G42: =G37/G36-1 -> -0.047177966 | H42: =H37/H36-1 -> -0.045743968 | I42: =I37/I36-1 -> -0.24403927 | J42: t inversiones; t adq. neto dep. | K42: =K32-Cifras_en_Millones!C17 -> 562.6 | L42: =L32-Cifras_en_Millones!D17 -> 636
B43: Pros
B44: Strategic partnerships across various industries to strengthen its market position (Volkswagen; Kupa); Strong international presence and market reach; Strong financial performance; Diversified Industry Presence
B45: Cons
B46: Complexity of the software (low trustpilot ratings)
B47: Riesgos
B48: Uncertain global geopolitical, economic and health conditions may cause some customers to reduce their investments; Continued pressure or volatility on raw materials and energy prices; Sales cycle of Dassault Systèmes’ products;
B49: Oportunidades
B50: Software engineering market is expected to grow for the next decade wtith a CAGR=10,2%; The rise of generative AI and LLMs will allow to cut costs (jobs decreasing) and expansion opportunities | I50: Dassault, Autodesk, Siemens, Parametric
B51: CHECKLIST
B52: Crescimiento | C52: Riesgos Claros | D52: ESG | E52: Peer Analysis | F52: Consenso | G52: KSF | H52: PO/Stand By | I52: (write the peers' names here)
B54: NOTES:

Sheet COVID-19 impact
A1: https://www.apple.com/newsroom/2020/03/apples-covid-19-response/ | G1: https://glg.it/articles/how-might-the-wuhan-coronavirus-impact-apples-supply-chain/ | N1: https://www.cnbc.com/2020/02/18/the-significance-of-apples-coronavirus-warning.html
A2: March 13 | G2: January 29 | N2: Ferbuary 18
A23: Otros:
A24: https://www.macrumors.com/guide/covid-19-coronavirus/

Sheet Segments
B2: Regions (2024)
C3: 2024 | D3: =C3-1 -> 2023 | E3: Ut. Operativa | F3: % Vts | G3: Margen | H3: Crec
B4: Americas | C4: 2214.7 | D4: 2142 | F4: =D4/SUM($D$4:$D$6) -> 0.39962687 | H4: =+C4/D4-1 -> 0.033940243 | J4: =IF(D4="","",IF(F4=0,"NA",TEXT(F4,"0%"))&"; "&IF(G4=0,"NA",TEXT(G4,"0.0%"))&"; "&IF(H4=0,"NA",TEXT(H4,"0%"))) -> 40%; NA; 3% | M4: 40% USD
B5: Europe | C5: 2150.4 | D5: 2027 | F5: =D5/SUM($D$4:$D$6) -> 0.37817164 | H5: =+C5/D5-1 -> 0.060878145 | J5: =IF(D5="","",IF(F5=0,"NA",TEXT(F5,"0%"))&"; "&IF(G5=0,"NA",TEXT(G5,"0.0%"))&"; "&IF(H5=0,"NA",TEXT(H5,"0%"))) -> 38%; NA; 6% | M5: 38% EUR
B6: Asia | C6: 1248.1 | D6: 1191 | F6: =D6/SUM($D$4:$D$6) -> 0.22220149 | H6: =+C6/D6-1 -> 0.047942905 | J6: =IF(D6="","",IF(F6=0,"NA",TEXT(F6,"0%"))&"; "&IF(G6=0,"NA",TEXT(G6,"0.0%"))&"; "&IF(H6=0,"NA",TEXT(H6,"0%"))) -> 22%; NA; 5% | M6: 22% YEN
J7: =IF(C7="","",IF(F7=0,"NA",TEXT(F7,"0%"))&"; "&IF(G7=0,"NA",TEXT(G7,"0.0%"))&"; "&IF(H7=0,"NA",TEXT(H7,"0%")))
J8: =IF(C8="","",IF(F8=0,"NA",TEXT(F8,"0%"))&"; "&IF(G8=0,"NA",TEXT(G8,"0.0%"))&"; "&IF(H8=0,"NA",TEXT(H8,"0%")))
J9: =IF(C9="","",IF(F9=0,"NA",TEXT(F9,"0%"))&"; "&IF(G9=0,"NA",TEXT(G9,"0.0%"))&"; "&IF(H9=0,"NA",TEXT(H9,"0%")))
J10: =IF(C10="","",IF(F10=0,"NA",TEXT(F10,"0%"))&"; "&IF(G10=0,"NA",TEXT(G10,"0.0%"))&"; "&IF(H10=0,"NA",TEXT(H10,"0%")))
J11: =IF(C11="","",IF(F11=0,"NA",TEXT(F11,"0%"))&"; "&IF(G11=0,"NA",TEXT(G11,"0.0%"))&"; "&IF(H11=0,"NA",TEXT(H11,"0%")))
J12: =IF(C12="","",IF(F12=0,"NA",TEXT(F12,"0%"))&"; "&IF(G12=0,"NA",TEXT(G12,"0.0%"))&"; "&IF(H12=0,"NA",TEXT(H12,"0%")))
J13: =IF(C13="","",IF(F13=0,"NA",TEXT(F13,"0%"))&"; "&IF(G13=0,"NA",TEXT(G13,"0.0%"))&"; "&IF(H13=0,"NA",TEXT(H13,"0%")))
B14: TOTAL | C14: =SUM(C4:C12) -> 5613.2 | D14: =SUM(D4:D12) -> 5360 | E14: =SUM(E4:E13) -> 0 | F14: =C14/SUM($C$4:$C$13) -> 1 | G14: =E14/C14 -> 0 | H14: =C14/D14-1 -> 0.047238806
B15: Segments (2024)
C16: =2024 -> 2024 | D16: =C16-1 -> 2023 | E16: Ut. Op. | F16: % Vts | G16: Margen | H16: Crec
B17: Industrial Innovation | C17: 3019.6 | D17: 2908 | F17: =D17/SUM($D$17:$D$19) -> 0.54253731 | H17: =+C17/D17-1 -> 0.038376891 | J17: =IF(D17="","",IF(F17=0,"NA",TEXT(F17,"0%"))&"; "&IF(G17=0,"NA",TEXT(G17,"0.0%"))&"; "&IF(H17=0,"NA",TEXT(H17,"0%"))) -> 54%; NA; 4%
B18: Life Sciences | C18: 1144.2 | D18: 1159 | F18: =D18/SUM($D$17:$D$19) -> 0.21623134 | H18: =+C18/D18-1 -> -0.012769629 | J18: =IF(D18="","",IF(F18=0,"NA",TEXT(F18,"0%"))&"; "&IF(G18=0,"NA",TEXT(G18,"0.0%"))&"; "&IF(H18=0,"NA",TEXT(H18,"0%"))) -> 22%; NA; -1%
B19: Mainstream Innovation | C19: 1449.4 | D19: 1293 | F19: =D19/SUM($D$17:$D$19) -> 0.24123134 | H19: =+C19/D19-1 -> 0.12095901 | J19: =IF(D19="","",IF(F19=0,"NA",TEXT(F19,"0%"))&"; "&IF(G19=0,"NA",TEXT(G19,"0.0%"))&"; "&IF(H19=0,"NA",TEXT(H19,"0%"))) -> 24%; NA; 12%
J20: =IF(C20="","",IF(F20=0,"NA",TEXT(F20,"0%"))&"; "&IF(G20=0,"NA",TEXT(G20,"0.0%"))&"; "&IF(H20=0,"NA",TEXT(H20,"0%")))
J21: =IF(C21="","",IF(F21=0,"NA",TEXT(F21,"0%"))&"; "&IF(G21=0,"NA",TEXT(G21,"0.0%"))&"; "&IF(H21=0,"NA",TEXT(H21,"0%")))
J22: =IF(C22="","",IF(F22=0,"NA",TEXT(F22,"0%"))&"; "&IF(G22=0,"NA",TEXT(G22,"0.0%"))&"; "&IF(H22=0,"NA",TEXT(H22,"0%")))
J23: =IF(C23="","",IF(F23=0,"NA",TEXT(F23,"0%"))&"; "&IF(G23=0,"NA",TEXT(G23,"0.0%"))&"; "&IF(H23=0,"NA",TEXT(H23,"0%")))
J24: =IF(C24="","",IF(F24=0,"NA",TEXT(F24,"0%"))&"; "&IF(G24=0,"NA",TEXT(G24,"0.0%"))&"; "&IF(H24=0,"NA",TEXT(H24,"0%")))
J25: =IF(C25="","",IF(F25=0,"NA",TEXT(F25,"0%"))&"; "&IF(G25=0,"NA",TEXT(G25,"0.0%"))&"; "&IF(H25=0,"NA",TEXT(H25,"0%")))
J26: =IF(C26="","",IF(F26=0,"NA",TEXT(F26,"0%"))&"; "&IF(G26=0,"NA",TEXT(G26,"0.0%"))&"; "&IF(H26=0,"NA",TEXT(H26,"0%")))
B27: TOTAL | C27: =SUM(C17:C26) -> 5613.2 | D27: =SUM(D17:D26) -> 5360 | E27: =SUM(E17:E26) -> 0 | F27: =C27/SUM(C17:C26) -> 1 | G27: =E27/C27 -> 0 | H27: =C27/D27-1 -> 0.047238806

Sheet Peers
B1: #VALUE! | C1: #VALUE! | D1: #VALUE! | E1: #VALUE!
A2: Multiplos (USD) | B2: {=+_FV(B1,"Ticker symbol",TRUE)} -> DSY | C2: {=+_FV(C1,"Ticker symbol",TRUE)} -> PTC | D2: {=+_FV(D1,"Ticker symbol",TRUE)} -> SIE | E2: {=+_FV(E1,"Ticker symbol",TRUE)} -> ADSK
B3: {=+_FV(B1,"Name")} -> Dassault Systemes SE | C3: {=+_FV(C1,"Name")} -> PTC INC. | D3: {=+_FV(D1,"Name")} -> Siemens AG | E3: {=+_FV(E1,"Name")} -> AUTODESK, INC.
A4: Ventas | B4: 5951.4 | C4: 2097.1 | D4: 74882 | E4: 5005
A5: Crecimiento (1S23/1S22) | B5: =(B4-5665.3)/5665.3 -> 0.050500415 | C5: =(C4-1933.3)/1933.3 -> 0.084725599 | D5: =(D4-71977)/71977 -> 0.040360115 | E5: =(E4-4386)/4386 -> 0.14113087
A6: Crecimiento (1S23/1S19) | B6: =(5951-4018)/4018 -> 0.48108512 | C6: =(C4-1255.6)/1255.6 -> 0.67019752 | D6: =(D4-58483)/58483 -> 0.28040627 | E6: =(E4-2569.8)/2569.8 -> 0.94762238
A7: Deuda | B7: 3600.9 | C7: 1889 | D7: 46596 | E7: 2666
A8: Activos | B8: 14622.5 | C8: 6288.8 | D8: 145071 | E8: 9438
A9: Deuda/Activos | B9: =B7/B8 -> 0.24625748 | C9: =C7/C8 -> 0.30037527 | D9: =D7/D8 -> 0.32119445 | E9: =E7/E8 -> 0.2824751
A10: Deuda/EBITDA | B10: 2.3 | C10: 3 | D10: 3.6 | E10: 2.2
A11: (Capex + Adq.)/Revenue | B11: =(-145.3-16.1)/B4 -> -0.027119669 | C11: =(-23.8-828.3)/C4 -> -0.40632302 | D11: =(-2146-407)/D4 -> -0.034093641 | E11: =(-36.8-88.3)/E4 -> -0.024995005
A12: ROA (p) | B12: 0.0562 | C12: 0.0544 | D12: 0.0396 | E12: 0.0713
A13: ROIC (p) | B13: 0.0943 | C13: 0.0859 | D13: 0.0683 | E13: 0.2224
A14: Margen Operativo | B14: =1298/B4 -> 0.21809994 | C14: =477.9/C4 -> 0.22788613 | D14: =9401/D4 -> 0.12554419 | E14: =1170/E4 -> 0.23376623
A15: Margen Operativo 2022 | B15: =1319.1/5665.3 -> 0.23283851 | C15: =498.6/1933.3 -> 0.257901 | D15: =7276/71977 -> 0.10108785 | E15: =618/4386 -> 0.14090287
A16: Float | B16: =668.54/1310 -> 0.51033588 | C16: =113.92/120.32 -> 0.94680851 | D16: =785.88/783.22 -> 1.0033962 | E16: =213.5/215.51 -> 0.99067329
A17: b | B17: 0.62 | C17: 1.19 | D17: 1.22 | E17: 1.43
A18: Precio/Utilidad | B18: 54.7 | C18: 91.2 | D18: 14.8 | E18: 60
A19: Precio/Ventas | B19: 9.6 | C19: 7.9 | D19: 1.5 | E19: 9.8
A20: EV/Activos | B20: =56285.4/B8 -> 3.8492323 | C20: =18105.6/C8 -> 2.879023 | D20: =157667.5/D8 -> 1.0868299 | E20: =45482.4/E8 -> 4.8190718
A21: EV/Ebitda | B21: 35.8 | C21: 28.9 | D21: 11.5 | E21: 41.3
A22: Div. Yield: | B22: {=+(-B28*1000000/_FV(B1,"Shares outstanding",TRUE))/_xlfn.STOCKHISTORY(B2,B29-2,B29-2,0,0,1)} -> 0.0046545876 | C22: {=+(-C28*1000000/_FV(C1,"Shares outstanding",TRUE))/_xlfn.STOCKHISTORY(C2,C29-2,C29-2,0,0,1)} -> 0 | D22: {=+(-D28*1000000/_FV(D1,"Shares outstanding",TRUE))/_xlfn.STOCKHISTORY(D2,D29-2,D29-2,0,0,1)} -> 0.024732227 | E22: {=+(-E28*1000000/_FV(E1,"Shares outstanding",TRUE))/_xlfn.STOCKHISTORY(E2,E29-2,E29-2,0,0,1)} -> 0
B24: *Nota: Estos múltiplos no consideran el promedio de los últimos 3 años, únicamente valores del último año reportado
B25: **Cifras en USD
A27: (You can make up a table with different indicators in order to link them to the multiples/ratios. At the end, put the table unvisible with white color)
A28: Dividends | B28: -276.2 | C28: 0 | D28: -3362 | E28: 0
A29: Year end | B29: 45291 | C29: 45291 | D29: 45291 | E29: 45291

Sheet Acuerdo
A1: Invertir
A2: NO invertir
A3: Mantener sin elevar posición
A4: Mantener (y seguir comprando)
A5: Liquidar
A6: PENDIENTE

Sheet ESG
B2: Análisis ESG | J2: PARÁMETROS
C3: Impacto | D3: ¿Reporta? | E3: Ranking | F3: Mitigación | G3: Semáforo | H3: Comentarios | J3: IMPACTO | L3: RANKING | M3: MITIGACIÓN
B4: Ambiental | J4: NONE | K4: 0 | L4: "Best in class" | M4: Is there evidence of progam/plan/etc…
B5: Emisiones directas CO2 | C5: LOW | D5: Yes | E5: Best in Class | F5: Yes | H5: A pesar del impacto que otras empresas tienen en la reducción de emisiones con sus softwares (como Virtual Twin), también está comprometida con los objetivos de reucción aprovador por la SBTi | J5: LOW | K5: 1 | L5: Medium high
B6: Uso total de agua | C6: NONE | D6: Yes | E6: Best in Class | F6: Yes | H6: El agua no es esnecial para sus operaciones, por lo que tienes niveles de consumo muy bajos. | J6: MEDIUM | K6: 2 | L6: Medium
B7: Total Energy Consumption | C7: MEDIUM | D7: Yes | E7: Medium High | F7: Yes | H7: Apoyan fuentes de energía descentralizadas y con bajas emisiones de carbono, como las micro centrales nucleares. También ayudan en la construcción de infraestructuras para reducir los costes energéticos, por ejemplo manipulando dos flujos de calor. | J7: HIGH | K7: 3 | L7: "Villain"
B8: Waste Management | C8: NONE | D8: Yes | E8: Best in Class | F8: Yes | H8: Colabora con la iniciativa EECONE, que tiene como objetivo reducir los residuos electrónicos. 3DEXPERIENCE Lab apoya a startups como Atacama Biomaterials, que desarrolló Woodpack, una alternativa biodegradable a los envases plásticos.
B9: Land Degradation/Deforestation/Biodiversity loss/Animal sufering/… | C9: NONE | D9: Yes | E9: Best in Class | F9: N/A | J9: TRAFFIC LIGHTS
B10: Social
B11: % Rotación de empleados | C11: MEDIUM | D11: No | E11: Villain | F11: No | H11: El 'Comparably' menciona que están en el 5% inferior entre más de 4000 empresas de tamaño similar, y es el segundo peor entre 5 competidores.
B12: Sueldos y compensaciones | C12: NONE | D12: No | E12: Medium High | F12: No | H12: Tienen salarios promedio altos, generalmente más de 100,000 USD.
B13: Temas de reputación | C13: MEDIUM | D13: Yes | E13: Villain | F13: No | H13: La evaluación promédia en Glassdoor es 2/5, con más de 4800 reviews. Familia Dassault tuve problemas de reputación, como corrupción.
B14: Temas de discriminación | C14: LOW | D14: Yes | E14: Best in Class | F14: Yes | H14: Tienen iniciativas para mujeres en STEM. La proporción de mujeres entre los directivos ejecutivos es del 31,9 %. No tienes litigios de discriminacións.
B15: Seguridad laboral | C15: LOW | D15: No | E15: Best in Class | F15: No | H15: Como una empresa de softwares, no tienen riesgos claros de seguridad laboral.
B16: Daños a la salud | C16: LOW | D16: No | E16: Best in Class | F16: No | H16: Tampoco hay riesgos directos a la salúd.
B17: PXP? | D17: Yes | E17: Best in Class | F17: Yes | H17: Hay violaciones de derechos de autor y de capital humano. Pierden algunos de sus empleados para otras empresas competidoras.
B18: Supply chain | C18: NONE | D18: Yes | E18: Best in Class | F18: Yes | H18: La empresa no tiene inventarios, pero sus proveedores de energía fueron mencionados anteriormente.
B19: Community involvement | H19: Más de 147 nacionalidades. Tienen iniciativas comunitárias para minorias. Ofrecen programas de capacitación para ayudar a los empleados y a las comunidades externas a adaptarse a los cambios tecnológicos.
B20: Public Sector | C20: HIGH | D20: Yes | E20: Best in Class | F20: Yes | H20: Recibe ayuda financiera del gobierno francés. Ofrece servicios a los gobiernos.
B21: Litigios | C21: HIGH | D21: Yes | E21: Best in Class | F21: Yes | H21: Han presentado múltiples demandas por violación de derechos de autor, la mayoría de las cuales ganaron.
B22: Gobierno
B23: Diversidad (Género, edad, industria, región) | E23: Medium High | F23: Yes | H23: Diversidad en género y edad, pero el board és en su mayoria de nacionalidad francesa.
B24: % independientes | E24: Medium High | F24: Yes | H24: 80%. Two members are part of the Dassault family.
B25: tiempo promedio como consejeros independientes | E25: Medium High | F25: No | H25: Solo 2 de 10 tienen mandatos que excedan 12 años.
B26: Salidas recientes de consejeros/C-level executives? | E26: Best in Class | F26: N/A | H26: Bernard Charles fue director general durante casi 30 años, renunció en 2024 y fue reemplazado por su sucesor Pascal Daloz.
B27: CEO/Chairman | E27: Best in Class | F27: N/A | H27: Pascal Daloz se unió a Dassault en 2001, desempeñando funciones como VP de R&D, COO and CFO, preparándose para convertirse en CEO.
B28: Transparencia (segmentos, fuente de riqueza, adquisiciones, otros) | E28: Best in Class | F28: N/A
B29: Tiempo que tardan en reportar luego del final del trimestre/año | E29: Best in Class | F29: N/A | H29: Compartieron los resultados del cuarto trimestre en el 4 de Febrero.
B30: Participación adicional del CEO en otros consejos o excesiva del Ch. | E30: Medium | F30: No | H30: Se desempeña como miembro independiente de la board de Sopra-Steria y STMicroelectronics, ambas empresas que cotizan en bolsa.
B31: Auditoría/Consultoría | H31: Cofrac Inspection Accreditation
B32: Esquemas de compensación al management | C32: LOW | D32: Yes | E32: Medium High | F32: Yes | H32: 450.000 acciones para el CEO, el crecimiento en EPS es el 80% de los criterios, la evaluación ESG es el 20%

Sheet DCF
A1: Discounted Cash Flow
A3: Ventas | E3: Margen Operativo
A16: Inversiones | E16: Utilidad Neta
D31: 0.001 | E31: =1/((1+$B$59+$D31)^(E35-2021)) -> 0.92250923 | F31: =1/((1+$B$59+$D31)^(F35-2021)) -> 0.85102327 | G31: =1/((1+$B$59+$D31)^(G35-2021)) -> 0.78507682 | H31: =1/((1+$B$59+$D31)^(H35-2021)) -> 0.72424061 | I31: =1/((1+$B$59+$D31)^(I35-2021)) -> 0.66811864 | J31: =1/((1+$B$59+$D31)^(J35-2021)) -> 0.61634561 | K31: =1/((1+$B$59+$D31)^(K35-2021)) -> 0.56858451 | L31: =1/((1+$B$59+$D31)^(L35-2021)) -> 0.52452446 | ... AC31: =1/((1+$B$59+$D31)^(AC35-2021)) -> 0.13312755
D32: 0.005 | E32: =1/((1+$B$59+$D32)^(E35-2021)) -> 0.91911765 | F32: =1/((1+$B$59+$D32)^(F35-2021)) -> 0.84477725 | G32: =1/((1+$B$59+$D32)^(G35-2021)) -> 0.77644968 | H32: =1/((1+$B$59+$D32)^(H35-2021)) -> 0.7136486 | I32: =1/((1+$B$59+$D32)^(I35-2021)) -> 0.65592702 | J32: =1/((1+$B$59+$D32)^(J35-2021)) -> 0.6028741 | K32: =1/((1+$B$59+$D32)^(K35-2021)) -> 0.55411223 | L32: =1/((1+$B$59+$D32)^(L35-2021)) -> 0.50929433 | ... AC32: =1/((1+$B$59+$D32)^(AC35-2021)) -> 0.12141647
D33: Normal | E33: =1/((1+$B$59)^(E35-2021)) -> 0.92336103 | F33: =1/((1+$B$59)^(F35-2021)) -> 0.8525956 | G33: =1/((1+$B$59)^(G35-2021)) -> 0.78725355 | H33: =1/((1+$B$59)^(H35-2021)) -> 0.72691926 | I33: =1/((1+$B$59)^(I35-2021)) -> 0.67120892 | J33: =1/((1+$B$59)^(J35-2021)) -> 0.61976816 | K33: =1/((1+$B$59)^(K35-2021)) -> 0.57226977 | L33: =1/((1+$B$59)^(L35-2021)) -> 0.5284116 | ... AC33: =1/((1+$B$59)^(AC35-2021)) -> 0.13623496
B35: 2019 (Real) | C35: 2020 (Real) | D35: 2021 | E35: =D35+1 -> 2022 | F35: =E35+1 -> 2023 | G35: =F35+1 -> 2024 | H35: =G35+1 -> 2025 | I35: =H35+1 -> 2026 | J35: =I35+1 -> 2027 | K35: =J35+1 -> 2028 | L35: =K35+1 -> 2029 | ... AC35: =AB35+1 -> 2046
A36: Crecimiento | B36: =#REF! -> #REF! | C36: =#REF! -> #REF! | D36: 0.35 | E36: 0.034 | F36: 0.095 | G36: 0.095 | H36: 0.095 | I36: 0.095 | J36: 0.095 | K36: 0.08 | L36: 0.06 | M36: 0.05 | N36: 0.04 | O36: 0.035 | P36: 0.035 | Q36: 0.035 | R36: 0.035 | S36: 0.035 | T36: 0.035 | U36: 0.035 | V36: 0.035 | W36: 0.035 | X36: 0.035 | Y36: 0.035 | Z36: 0.035 | AA36: 0.035 | AB36: 0.035 | AC36: 0.035
A37: Ventas | B37: =#REF! -> #REF! | C37: =#REF! -> #REF! | D37: =#REF!*(1+D36) -> #REF! | E37: =D37*(1+E36) -> #REF! | F37: =E37*(1+F36) -> #REF! | G37: =F37*(1+G36) -> #REF! | H37: =G37*(1+H36) -> #REF! | I37: =H37*(1+I36) -> #REF! | J37: =I37*(1+J36) -> #REF! | K37: =J37*(1+K36) -> #REF! | L37: =K37*(1+L36) -> #REF! | ... AC37: =AB37*(1+AC36) -> #REF!
A38: Margen Operativo | B38: =+#REF! -> #REF! | C38: =+#REF! -> #REF! | D38: =108166.4/365513.2 -> 0.29593022 | E38: =108162.8/377959.8 -> 0.28617541 | F38: 0.27 | G38: 0.275 | H38: 0.26 | I38: 0.255 | J38: 0.25 | K38: 0.25 | L38: 0.25 | M38: 0.25 | N38: 0.25 | O38: 0.25 | P38: 0.25 | Q38: 0.25 | R38: 0.25 | S38: 0.25 | T38: 0.25 | U38: 0.25 | V38: 0.25 | W38: 0.25 | X38: 0.25 | Y38: 0.25 | Z38: 0.25 | AA38: 0.25 | AB38: 0.25 | AC38: 0.25
A39: EBIT | B39: 63930 | C39: 66288 | D39: =D37*D38 -> #REF! | E39: =E37*E38 -> #REF! | F39: =F37*F38 -> #REF! | G39: =G37*G38 -> #REF! | H39: =H37*H38 -> #REF! | I39: =I37*I38 -> #REF! | J39: =J37*J38 -> #REF! | K39: =K37*K38 -> #REF! | ... AC39: =AC37*AC38 -> #REF!
A40: Dep&Amort | B40: =#REF! -> #REF! | C40: =#REF! -> #REF! | D40: 11000 | E40: =D40*(1+E36*$H$59) -> 11374 | F40: =E40*(1+F36*$H$59) -> 12454.53 | G40: =F40*(1+G36*$H$59) -> 13637.71 | H40: =G40*(1+H36*$H$59) -> 14933.293 | I40: =H40*(1+I36*$I$59) -> 16351.956 | J40: =I40*(1+J36*$I$59) -> 17905.391 | K40: =J40*(1+K36*$I$59) -> 19337.823 | L40: =K40*(1+L36*$I$59) -> 20498.092 | M40: =L40*(1+M36*$I$59) -> 21522.997 | N40: =M40*(1+N36*$I$59) -> 22383.917 | O40: =N40*(1+O36*$I$59) -> 23167.354 | P40: =O40*(1+P36*$I$59) -> 23978.211 | ... AC40: =AB40*(1+AC36*$I$59) -> 37500.868
A41: EBIDTA | B41: =+B39+B40 -> #REF! | C41: =+C39+C40 -> #REF! | D41: =D39+D40 -> #REF! | E41: =E39+E40 -> #REF! | F41: =F39+F40 -> #REF! | G41: =G39+G40 -> #REF! | H41: =H39+H40 -> #REF! | I41: =I39+I40 -> #REF! | J41: =J39+J40 -> #REF! | K41: =K39+K40 -> #REF! | ... AC41: =AC39+AC40 -> #REF!
A42: CIF | B42: -1385 | C42: -890 | D42: =(C48)*$H$60 -> -1124.36 | E42: =(D48)*$H$60 -> -1113.1164 | F42: =(E48)*$H$60 -> -1113.1164 | G42: =(F48)*$H$60 -> -1113.1164 | H42: =(G48)*$H$60 -> -1113.1164 | I42: =(H48)*$H$60 -> -1113.1164 | J42: =(I48)*$H$60 -> -1113.1164 | K42: =(J48)*$H$60 -> -1113.1164 | ... AC42: =(AB48)*$H$60 -> -1113.1164
A43: Otros Gastos | B43: =-422-2817 -> -3239 | C43: =87-3634 -> -3547 | D43: =-C43*(1+D36) -> 4788.45 | E43: =D43*(1+E36*0.5) -> 4869.8537 | F43: =E43*(1+F36*0.5) -> 5101.1717 | G43: =F43*(1+G36*0.5) -> 5343.4774 | H43: =G43*(1+H36*0.5) -> 5597.2925 | I43: =H43*(1+I36*0.5) -> 5863.1639 | J43: =I43*(1+J36*0.5) -> 6141.6642 | K43: =J43*(1+K36*0.5) -> 6387.3308 | L43: =K43*(1+L36*0.5) -> 6578.9507 | ... AC43: =AB43*(1+AC36*0.5) -> 8922.7133
A44: Utilidad antes de Impuestos | B44: =B39-B42-B43 -> 68554 | C44: =C39-C42-C43 -> 70725 | D44: =D39-D42-D43 -> #REF! | E44: =E39-E42-E43 -> #REF! | F44: =F39-F42-F43 -> #REF! | G44: =G39-G42-G43 -> #REF! | H44: =H39-H42-H43 -> #REF! | I44: =I39-I42-I43 -> #REF! | ... AC44: =AC39-AC42-AC43 -> #REF!
A45: ISR & PTU | B45: 10481 | C45: 9680 | D45: =$H$61*D44 -> #REF! | E45: =$H$61*E44 -> #REF! | F45: =$H$61*F44 -> #REF! | G45: =$I$61*G44 -> #REF! | H45: =$I$61*H44 -> #REF! | I45: =$I$61*I44 -> #REF! | J45: =$I$61*J44 -> #REF! | K45: =$I$61*K44 -> #REF! | L45: =$I$61*L44 -> #REF! | M45: =$I$61*M44 -> #REF! | N45: =$I$61*N44 -> #REF! | ... AC45: =$I$61*AC44 -> #REF!
A46: Utilidad Neta | B46: =B44-B45 -> 58073 | C46: =C44-C45 -> 61045 | D46: =D44-D45 -> #REF! | E46: =E44-E45 -> #REF! | F46: =F44-F45 -> #REF! | G46: =G44-G45 -> #REF! | H46: =H44-H45 -> #REF! | I46: =I44-I45 -> #REF! | ... AC46: =AC44-AC45 -> #REF!
A47: Inversiones y Capex | B47: =#REF! -> #REF! | C47: =#REF! -> #REF! | D47: 10000 | E47: =D47*(1+E36*$H$62) -> 10408 | F47: =E47*(1+F36*$H$62) -> 11594.512 | G47: =F47*(1+G36*$H$62) -> 12916.286 | H47: =G47*(1+H36*$H$62) -> 14388.743 | I47: =H47*(1+I36*$H$62) -> 16029.06 | J47: =I47*(1+J36*$H$62) -> 17856.373 | K47: =J47*(1+K36*$H$62) -> 19570.584 | L47: =K47*(1+L36*$H$62) -> 20979.666 | ... AC47: =AB47*(1+AC36*$H$62) -> 43199.777
A48: Deuda + Lease Liabilities | B48: 108047 | C48: 112436 | D48: =C48*0.99 -> 111311.64 | E48: =D48 -> 111311.64 | F48: =E48 -> 111311.64 | G48: =F48 -> 111311.64 | H48: =G48 -> 111311.64 | I48: =H48 -> 111311.64 | J48: =I48 -> 111311.64 | K48: =J48 -> 111311.64 | L48: =K48 -> 111311.64 | ... AC48: =AB48 -> 111311.64
A49: Deuda/EBITDA | B49: =B48/B41 -> #REF! | C49: =C48/C41 -> #REF! | D49: =D48/D41 -> #REF! | E49: =E48/E41 -> #REF!
A50: FNP | B50: =#REF! -> #REF! | C50: =#REF! -> #REF! | D50: =D41-D42-D43-D45-D47+D48-C48 -> #REF! | E50: =E41-E42-E43-E45-E47+E48-D48 -> #REF! | F50: =F41-F42-F43-F45-F47+F48-E48 -> #REF! | G50: =G41-G42-G43-G45-G47+G48-F48 -> #REF! | H50: =H41-H42-H43-H45-H47+H48-G48 -> #REF! | I50: =I41-I42-I43-I45-I47+I48-H48 -> #REF! | J50: =J41-J42-J43-J45-J47+J48-I48 -> #REF! | K50: =K41-K42-K43-K45-K47+K48-J48 -> #REF! | ... AC50: =AC41-AC42-AC43-AC45-AC47+AC48-AB48 -> #REF!
A51: F(t) | B51: 0 | C51: 0 | D51: =C51*(1+$B$59)+D50 -> #REF! | E51: =D51*(1+$B$59)+E50 -> #REF! | F51: =E51*(1+$B$59)+F50 -> #REF! | G51: =F51*(1+$B$59)+G50 -> #REF! | H51: =G51*(1+$B$59)+H50 -> #REF! | I51: =H51*(1+$B$59)+I50 -> #REF! | J51: =I51*(1+$B$59)+J50 -> #REF! | K51: =J51*(1+$B$59)+K50 -> #REF! | ... AC51: =AB51*(1+$B$59)+AC50 -> #REF!
AB52: =AB51-AB48 -> #REF! | AC52: =AC50/(B59-AC36) -> #REF!
A53: EPS | C53: =1000000*C46/#REF! -> #REF! | D53: =1000000*D46/#REF! -> #REF! | E53: =1000000*E46/#REF! -> #REF! | F53: =1000000*F46/#REF! -> #REF!
A54: Consenso EPS | C54: 3.3 | D54: 5.6 | E54: 5.6
A55: E$/UN | D55: =$B$61/D46 -> #REF! | E55: =$B$61/E46 -> #REF! | F55: =$B$61/F46 -> #REF!
A56: EEV/EBIDA | D56: =($B$61+D48-D51)/D41 -> #REF! | E56: =($B$61+E48-E51)/E41 -> #REF! | F56: =($B$61+F48-F51)/F41 -> #REF!
C58: "TELP" | D58: CER | E58: D Analista | H58: CP | I58: LP
A59: Tasa de descuento: | B59: =SUM(C59:E59) -> 0.083 | C59: 0.0307 | D59: 0.0523 | E59: 0 | G59: Factor D&A | H59: 1 | I59: 1
G60: Factor CIF | H60: -0.01
A61: VPN*@i% | B61: =C62+C63 -> #REF! | C61: Normal | D61: =D31 -> 0.001 | E61: =D32 -> 0.005 | G61: Factor ISR | H61: 0.21 | I61: 0.23
A62: DCF 25Y | B62: =C62/B61 -> #REF! | C62: =AB52/(1+B59)^25 -> #REF! | D62: =SUMPRODUCT(E50:AB50,E31:AB31) -> #REF! | E62: =SUMPRODUCT(E50:AB50,E32:AB32) -> #REF! | G62: Factor inv | H62: 1.2
A63: Perpetuidad | B63: =1-B62 -> #REF! | C63: =AC52/(1+B59)^25 -> #REF! | D63: =(AC50/($B$59+D31-$AC$36))*AC31 -> #REF! | E63: =(AC50/($B$59+D32-$AC$36))*AC32 -> #REF! | G63: Suma D&A | H63: =SUM(40:40) -> #REF!
A64: VPN/Acción | B64: =1000000*B61/#REF! -> #REF! | D64: =1000000*SUM(D62:D63)/#REF! -> #REF! | E64: =1000000*SUM(E62:E63)/#REF! -> #REF! | G64: Suma Inv. | H64: =SUM(47:47) -> #REF!
B65: =B64/#REF!-1 -> #REF! | D65: =D64/B64-1 -> #REF! | E65: =E64/B64-1 -> #REF! | G65: Inv.+Goodwill | H65: =SUM(47:47)+(#REF!*#REF!) -> #REF!
A67: Duración | B67: =B62*D68+B63*D69 -> #REF! | E67: 1 | F67: 2 | G67: 3 | H67: 4 | I67: 5 | J67: 6 | K67: 7 | L67: 8 | M67: 9 | N67: 10 | O67: 11 | P67: 12 | Q67: 13 | R67: 14 | S67: 15 | T67: 16 | U67: 17 | V67: 18 | W67: 19 | X67: 20 | Y67: 21 | Z67: 22 | AA67: 23 | AB67: 24 | AC67: 25
A68: 0.001 | B68: =-$B$67*A68 -> #REF! | D68: =SUM(E68:AB68)/SUMPRODUCT(E50:AB50,E33:AB33) -> #REF! | E68: =E67*E50*E33 -> #REF! | F68: =F67*F50*F33 -> #REF! | G68: =G67*G50*G33 -> #REF! | H68: =H67*H50*H33 -> #REF! | I68: =I67*I50*I33 -> #REF! | J68: =J67*J50*J33 -> #REF! | K68: =K67*K50*K33 -> #REF! | L68: =L67*L50*L33 -> #REF! | ... AC68: =AC67*AC50*AC33 -> #REF!
A69: 0.005 | B69: =-$B$67*A69 -> #REF! | D69: =(1+B59)/B59+AC67 -> 38.048193

Sheet DCFF
C1: VALUATION MODEL
C2: Año fiscal de Apple cierra en septiembre
D3: =D19/D6 -> 0.035308642 | E3: =E19/E6 -> 0.029424744 | F3: =F19/F6 -> 0.030917095 | G3: 0 | H3: 0.25 | I3: =H3+1 -> 1.25 | J3: =I3+1 -> 2.25 | K3: =J3+1 -> 3.25 | L3: =K3+1 -> 4.25 | M3: =L3+1 -> 5.25 | N3: =M3+1 -> 6.25 | O3: =N3+1 -> 7.25 | P3: =O3+1 -> 8.25 | ... AF3: =AE3+1 -> 24.25
A4: Section | B4: Line # | C4: ITEM | D4: 2021 | E4: =+D4+1 -> 2022 | F4: =+E4+1 -> 2023 | G4: =+F4+1 -> 2024 | H4: 2025 | I4: =+H4+1 -> 2026 | J4: =+I4+1 -> 2027 | K4: =+J4+1 -> 2028 | L4: =+K4+1 -> 2029 | M4: =+L4+1 -> 2030 | N4: =+M4+1 -> 2031 | O4: =+N4+1 -> 2032 | P4: =+O4+1 -> 2033 | ... AF4: =+AE4+1 -> 2049 | AG4: Notes
A5: INCOME STATEMENT | B5: 1 | C5: Growth | D5: =Cifras_en_Millones!F6 -> 0.091570649 | E5: =Cifras_en_Millones!E6 -> 0.16569959 | F5: =Cifras_en_Millones!D6 -> 0.050500415 | G5: =Cifras_en_Millones!C6 -> 0.044056861 | H5: =H6/G6-1 -> 0.080050212 | I5: =I6/H6-1 -> 0.079272836 | J5: 0.057 | K5: 0.057 | L5: 0.057 | M5: 0.057 | N5: =+M5-($M$5-$AF$5)/($AF$4-$M$4) -> 0.055315789 | O5: =+N5-($M$5-$AF$5)/($AF$4-$M$4) -> 0.053631579 | P5: =+O5-($M$5-$AF$5)/($AF$4-$M$4) -> 0.051947368 | Q5: =+P5-($M$5-$AF$5)/($AF$4-$M$4) -> 0.050263158 | R5: =+Q5-($M$5-$AF$5)/($AF$4-$M$4) -> 0.048578947 | S5: =+R5-($M$5-$AF$5)/($AF$4-$M$4) -> 0.046894737 | T5: =+S5-($M$5-$AF$5)/($AF$4-$M$4) -> 0.045210526 | U5: =+T5-($M$5-$AF$5)/($AF$4-$M$4) -> 0.043526316 | ... AE5: =+AD5-($M$5-$AF$5)/($AF$4-$M$4) -> 0.026684211 | AF5: 0.025
B6: 2 | C6: Revenues/Sales | D6: =Cifras_en_Millones!F5 -> 4860 | E6: =Cifras_en_Millones!E5 -> 5665.3 | F6: =Cifras_en_Millones!D5 -> 5951.4 | G6: =Cifras_en_Millones!C5 -> 6213.6 | H6: 6711 | I6: 7243 | J6: =+I6*(1+J5) -> 7655.851 | K6: =+J6*(1+K5) -> 8092.2345 | L6: =+K6*(1+L5) -> 8553.4919 | M6: =+L6*(1+M5) -> 9041.0409 | N6: =+M6*(1+N5) -> 9541.1532 | O6: =+N6*(1+O5) -> 10052.86 | P6: =+O6*(1+P5) -> 10575.08 | Q6: =+P6*(1+Q5) -> 11106.617 | ... AF6: =+AE6*(1+AF5) -> 19088.862
B7: 3 | C7: EBIT/Operating Margin | D7: =Cifras_en_Millones!F12 -> 0.20975309 | E7: =Cifras_en_Millones!E12 -> 0.22997899 | F7: =Cifras_en_Millones!D12 -> 0.20867359 | G7: =Cifras_en_Millones!C12 -> 0.21881035 | H7: 0.21 | I7: 0.215 | J7: 0.22 | K7: 0.225 | L7: 0.23 | M7: =+L7 -> 0.23 | N7: =+M7 -> 0.23 | O7: =+N7 -> 0.23 | P7: =+O7 -> 0.23 | Q7: =+P7 -> 0.23 | R7: =+Q7 -> 0.23 | S7: =+R7 -> 0.23 | T7: =+S7 -> 0.23 | ... AF7: =+AE7 -> 0.23
B8: 4 | C8: EBIT | D8: =D6*D7 -> 1019.4 | E8: =E6*E7 -> 1302.9 | F8: =F6*F7 -> 1241.9 | G8: =G7*G6 -> 1359.6 | H8: =+H6*H7 -> 1409.31 | I8: =+I6*I7 -> 1557.245 | J8: =J7*J6 -> 1684.2872 | K8: =K7*K6 -> 1820.7528 | L8: =L7*L6 -> 1967.3031 | M8: =M7*M6 -> 2079.4394 | N8: =N7*N6 -> 2194.4652 | O8: =O7*O6 -> 2312.1579 | P8: =P7*P6 -> 2432.2684 | Q8: =Q7*Q6 -> 2554.5219 | ... AF8: =AF7*AF6 -> 4390.4382
B9: 5a | C9: (Dep&Amort) | D9: =Cifras_en_Millones!F17 -> -574.6 | E9: =Cifras_en_Millones!E17 -> -596.8 | F9: =Cifras_en_Millones!D17 -> -569.5 | G9: =Cifras_en_Millones!C17 -> -561 | H9: =-H95 -> -548.2555 | I9: =-I95 -> -554.39633 | J9: =-J95 -> -565.17415 | K9: =-K95 -> -579.54657 | L9: =-L95 -> -597.29191 | M9: =-M95 -> -618.23696 | N9: =-N95 -> -642.13844 | O9: =-O95 -> -668.7171 | ... AF9: =-AF95 -> -1334.5234
B10: 5b | C10: (Stock based compensation) | D10: =D19 -> 171.6 | E10: =E19 -> 166.7 | F10: =F19 -> 184 | G10: =G19 -> 185 | H10: =-$D$51*H6 -> -210.7254 | I10: =-$D$51*I6 -> -227.4302 | J10: =-$D$51*J6 -> -240.39372 | K10: =-$D$51*K6 -> -254.09616 | L10: =-$E$51*L6 -> -268.57964 | M10: =-$E$51*M6 -> -283.88868 | N10: =-$E$51*N6 -> -299.59221 | O10: =-$E$51*O6 -> -315.65981 | P10: =-$E$51*P6 -> -332.05751 | Q10: =-$E$51*Q6 -> -348.74777 | R10: =-$E$51*R6 -> -365.68957 | S10: =-$E$51*S6 -> -382.83849 | ... AF10: =-$E$51*AF6 -> -599.39025
B11: 6 | C11: EBIDTA | D11: =-D9+D8 -> 1594 | E11: =-E9+E8 -> 1899.7 | F11: =-F9+F8 -> 1811.4 | G11: =-G9+G8 -> 1920.6 | H11: =-H9+H8 -> 1957.5655 | I11: =-I9+I8 -> 2111.6413 | J11: =-J9+J8 -> 2249.4614 | K11: =-K9+K8 -> 2400.2993 | ... AF11: =-AF9+AF8 -> 5724.9615
B12: 7 | C12: (Net financing cost) | D12: =Cifras_Originales!E9 -> 16.8 | E12: =Cifras_Originales!D9 -> -13.8 | F12: =Cifras_Originales!C9 -> -98.3 | G12: =Cifras_Originales!B9 -> -118.4 | H12: =-$D$53*G37+G36*$D$54 -> 103.0109 | I12: =-$D$53*H37+H36*$D$54 -> 128.38183 | J12: =-$D$53*I37+I36*$D$54 -> 137.9474 | K12: =-$D$53*J37+J36*$D$54 -> 168.85875 | L12: =-$D$53*K37+K36*$D$54 -> 201.00796 | M12: =-$D$53*L37+L36*$D$54 -> 210.35868 | N12: =-$D$53*M37+M36*$D$54 -> 234.21901 | O12: =-$D$53*N37+N36*$D$54 -> 268.07102 | ... AF12: =-$D$53*AE37+AE36*$D$54 -> 844.49227
B13: 8 | C13: Other income/(cost) | D13: =Cifras_Originales!E10 -> 1.7 | E13: =Cifras_Originales!D10 -> -11.1 | F13: =Cifras_Originales!C10 -> -39.3 | G13: =Cifras_Originales!B10 -> 0 | H13: =AVERAGE(D13:G13)*(1+H5) -> -13.149611 | I13: =AVERAGE(E13:H13)*(1+I5) -> -17.146842 | J13: =AVERAGE(F13:I13)*(1+J5) -> -18.390863 | K13: =AVERAGE(G13:J13)*(1+K5) -> -12.865623 | L13: =AVERAGE(H13:K13)*(1+L5) -> -16.265364 | M13: =AVERAGE(I13:L13)*(1+M5) -> -17.088702 | N13: =AVERAGE(J13:M13)*(1+N5) -> -17.046134 | O13: =AVERAGE(K13:N13)*(1+O5) -> -16.664718 | ... AF13: =AVERAGE(AB13:AE13)*(1+AF5) -> -21.976897
B14: 9 | C14: Earnings before taxes | D14: =D8-D12+D13 -> 1004.3 | E14: =E8-E12+E13 -> 1305.6 | F14: =F8-F12+F13 -> 1300.9 | G14: =G8-G12+G13 -> 1478 | H14: =H8+H12+H13 -> 1499.1713 | I14: =I8+I12+I13 -> 1668.48 | J14: =J8+J12+J13 -> 1803.8438 | K14: =K8+K12+K13 -> 1976.7459 | L14: =L8+L12+L13 -> 2152.0457 | M14: =M8+M12+M13 -> 2272.7094 | N14: =N8+N12+N13 -> 2411.6381 | O14: =O8+O12+O13 -> 2563.5642 | ... AF14: =AF8+AF12+AF13 -> 5212.9535
B15: 10 | C15: (Income tax) | D15: =Cifras_en_Millones!F21 -> -230.4 | E15: =Cifras_en_Millones!E21 -> -375.4 | F15: =Cifras_en_Millones!D21 -> -250.7 | G15: =Cifras_en_Millones!C21 -> -279.9 | H15: =(-1*$D$52)*H14 -> -337.01371 | I15: =(-1*$D$52)*I14 -> -375.0743 | J15: =(-1*$D$52)*J14 -> -405.50408 | K15: =(-1*$D$52)*K14 -> -444.37248 | L15: =(-1*$E$52)*L14 -> -483.77988 | M15: =(-1*$E$52)*M14 -> -510.90507 | N15: =(-1*$E$52)*N14 -> -542.13625 | O15: =(-1*$E$52)*O14 -> -576.28923 | P15: =(-1*$E$52)*P14 -> -611.09779 | Q15: =(-1*$E$52)*Q14 -> -646.99483 | R15: =(-1*$E$52)*R14 -> -683.28691 | S15: =(-1*$E$52)*S14 -> -720.37872 | ... AF15: =(-1*$E$52)*AF14 -> -1171.872
B16: 11 | C16: Net income | D16: =D14+D15 -> 773.9 | E16: =E14+E15 -> 930.2 | F16: =F14+F15 -> 1050.2 | G16: =G14+G15 -> 1198.1 | H16: =H14+H15 -> 1162.1576 | I16: =I14+I15 -> 1293.4057 | J16: =J14+J15 -> 1398.3397 | K16: =K14+K15 -> 1532.3734 | ... AF16: =AF14+AF15 -> 4041.0816
A18: CASH FLOW STATEMENT | B18: 12 | C18: Operating cash flows before WK | D18: =+D16-D9 -> 1348.5 | E18: =+E16-E9 -> 1527 | F18: =+F16-F9 -> 1619.7 | G18: =+G16-G9 -> 1759.1 | H18: =H11+H12+H13+H15 -> 1710.4131 | I18: =I11+I12+I13+I15 -> 1847.802 | J18: =J11+J12+J13+J15 -> 1963.5138 | K18: =K11+K12+K13+K15 -> 2111.92 | L18: =L11+L12+L13+L15 -> 2265.5578 | M18: =M11+M12+M13+M15 -> 2380.0413 | N18: =N11+N12+N13+N15 -> 2511.6403 | O18: =O11+O12+O13+O15 -> 2655.992 | ... AF18: =AF11+AF12+AF13+AF15 -> 5375.605
B19: 13 | C19: (Stock-based compensation) | D19: 171.6 | E19: 166.7 | F19: 184 | G19: 185 | H19: =-H10 -> 210.7254 | I19: =-I10 -> 227.4302 | J19: =-J10 -> 240.39372 | K19: =-K10 -> 254.09616 | L19: =-L10 -> 268.57964 | M19: =-M10 -> 283.88868 | N19: =-N10 -> 299.59221 | O19: =-O10 -> 315.65981 | ... AF19: =-AF10 -> 599.39025
B20: 14 | C20: (Working Capital Flows) | D20: =+Cifras_Originales!E12 -> 93.2 | E20: =+Cifras_Originales!D12 -> -169.8 | F20: =+Cifras_Originales!C12 -> -239.5 | G20: =+Cifras_Originales!B12 -> -286.3 | H20: =$D$56*(H6-G6) -> -353.154 | I20: =$D$56*(I6-H6) -> -377.72 | J20: =$D$56*(J6-I6) -> -293.12421 | K20: =$D$56*(K6-J6) -> -309.83229 | L20: =$E$56*(L6-K6) -> -327.49273 | M20: =$E$56*(M6-L6) -> -346.15982 | N20: =$E$56*(N6-M6) -> -355.07974 | O20: =$E$56*(O6-N6) -> -363.31205 | P20: =$E$56*(P6-O6) -> -370.77594 | Q20: =$E$56*(Q6-P6) -> -377.39121 | R20: =$E$56*(R6-Q6) -> -383.07891 | S20: =$E$56*(S6-R6) -> -387.76212 | ... AF20: =$E$56*(AF6-AE6) -> -330.56321
B21: 15 | C21: -Total Operating Cash Flow | D21: =D18+D19+D20 -> 1613.3 | E21: =E18+E19+E20 -> 1523.9 | F21: =F18+F19+F20 -> 1564.2 | G21: =G18+G19+G20 -> 1657.8 | H21: =H18+H19+H20 -> 1567.9845 | I21: =I18+I19+I20 -> 1697.5122 | J21: =J18+J19+J20 -> 1910.7833 | K21: =K18+K19+K20 -> 2056.1839 | ... AF21: =AF18+AF19+AF20 -> 5644.432
B22: 16 | C22: (CAPEX and Acquisitions) | D22: =-103.7-21.4 -> -125.1 | E22: =-132.3-46.4 -> -178.7 | F22: =-145.3-16.1 -> -161.4 | G22: =-193.4-22.5 -> -215.9 | H22: =-$D$57*H6 -> -217.4364 | I22: =-$D$57*I6 -> -234.6732 | J22: =-$D$57*J6 -> -248.04957 | K22: =-$D$57*K6 -> -262.1884 | L22: =-$E$57*L6 -> -277.13314 | M22: =-$E$57*M6 -> -292.92973 | N22: =-$E$57*N6 -> -309.13336 | O22: =-$E$57*O6 -> -325.71267 | P22: =-$E$57*P6 -> -342.63259 | Q22: =-$E$57*Q6 -> -359.85439 | R22: =-$E$57*R6 -> -377.33573 | S22: =-$E$57*S6 -> -395.03079 | ... AF22: =-$E$57*AF6 -> -618.47912
B23: 17 | C23: (Other investing flows) | D23: =-35.3 -> -35.3 | E23: -35.2 | F23: -0.3 | G23: 24 | H23: =+AVERAGE(D23:G23)*(1+H5) -> -12.636587 | I23: =+AVERAGE(E23:H23)*(1+I5) -> -6.5124908 | J23: =+AVERAGE(F23:I23)*(1+J5) -> 1.2025811 | K23: =+AVERAGE(G23:J23)*(1+K5) -> 1.5996381 | L23: =+AVERAGE(H23:K23)*(1+L5) -> -4.3196575 | M23: =+AVERAGE(I23:L23)*(1+M5) -> -2.1219088 | N23: =+AVERAGE(J23:M23)*(1+N5) -> -0.96016512 | O23: =+AVERAGE(K23:N23)*(1+O5) -> -1.5283172 | ... AF23: =+AVERAGE(AB23:AE23)*(1+AF5) -> -2.3025638
B24: 18 | C24: -Total Investing Flows | D24: =D22+D23 -> -160.4 | E24: =E22+E23 -> -213.9 | F24: =F22+F23 -> -161.7 | G24: =G22+G23 -> -191.9 | H24: =H22+H23 -> -230.07299 | I24: =I22+I23 -> -241.18569 | J24: =J22+J23 -> -246.84699 | K24: =K22+K23 -> -260.58876 | ... AF24: =AF22+AF23 -> -620.78168
B25: 19 | C25: (Flows related to leases) | D25: -97.6 | E25: -102 | F25: -89.4 | G25: -79.7 | H25: =AVERAGE(D25:G25)*(1+H5) -> -99.553628 | I25: =AVERAGE(E25:H25)*(1+I5) -> -100.0091 | J25: =AVERAGE(F25:I25)*(1+J5) -> -97.419125 | K25: =AVERAGE(G25:J25)*(1+K5) -> -99.538179 | L25: =AVERAGE(H25:K25)*(1+L5) -> -104.78042 | M25: =AVERAGE(I25:L25)*(1+M5) -> -106.1616 | N25: =AVERAGE(J25:M25)*(1+N5) -> -107.61565 | O25: =AVERAGE(K25:N25)*(1+O5) -> -110.12975 | ... AF25: =AVERAGE(AB25:AE25)*(1+AF5) -> -141.11344
B26: 20 | C26: Flows related to debt | D26: =1.3-341.2 -> -339.9 | E26: =257.8-1143.9 -> -886.1 | F26: =20-28.1 -> -8.1 | G26: =-700.9+200.2 -> -500.7 | H26: =(H37-G37) -> 0 | I26: =(I37-H37) -> -900 | J26: =(J37-I37) -> 0 | K26: =(K37-J37) -> 0 | L26: =(L37-K37) -> -1150 | M26: =(M37-L37) -> -443.6 | N26: =(N37-M37) -> 0 | O26: =(O37-N37) -> 0 | ... AF26: =(AF37-AE37) -> 0
B27: 21 | C27: (Repurchases)/Issuance of stock | D27: -283.2 | E27: -639.6 | F27: -375.4 | G27: -374 | H27: =+H16*$D$55 -> -500.6428 | I27: =+I16*$D$55 -> -557.18283 | J27: =+J16*$D$55 -> -602.38707 | K27: =+K16*$D$55 -> -660.1271 | L27: =+L16*$D$55 -> -718.66785 | M27: =+M16*$D$55 -> -758.96304 | N27: =+N16*$D$55 -> -805.35778 | O27: =+O16*$D$55 -> -856.09294 | P27: =+P16*$D$55 -> -907.80198 | Q27: =+Q16*$E$55 -> -1028.0609 | R27: =+R16*$E$55 -> -1085.7282 | S27: =+S16*($E$55-10%) -> -1393.0816 | T27: =+T16*($E$55-10%) -> -1462.44 | U27: =+U16*($E$55-20%) -> -1806.3881 | V27: =+V16*($E$55-20%) -> -1885.8648 | W27: =+W16*($E$55-20%) -> -1966.1409 | X27: =+X16*($E$55-20%) -> -2047.0447 | Y27: =+Y16*($E$55-25%) -> -2289.458 | Z27: =+Z16*($E$55-25%) -> -2374.1333 | AA27: =+AA16*($E$55-25%) -> -2458.7293 | AB27: =+AB16*($E$55-25%) -> -2543.0191 | AC27: =+AC16*($E$55-25%) -> -2626.7688 | AD27: =+AD16*($E$55-25%) -> -2709.7354 | AE27: =+AE16*($E$55-25%) -> -2791.6767 | AF27: =+AF16*($E$55-25%) -> -2872.3497
B28: 22 | C28: (Dividends) | D28: -147.1 | E28: -223.5 | F28: -276.2 | G28: -302.7 | H28: =+$D$58*H16 -> -290.5394 | I28: =+$D$58*I16 -> -323.35142 | J28: =+$D$58*J16 -> -349.58492 | K28: =+$D$58*K16 -> -383.09335 | L28: =+$E$58*L16 -> -500.47975 | M28: =+$E$58*M16 -> -528.54129 | N28: =+$E$58*N16 -> -560.85056 | O28: =+$E$58*O16 -> -596.18248 | P28: =+$E$58*P16 -> -632.19262 | Q28: =+$E$58*Q16 -> -669.32882 | R28: =+$E$58*R16 -> -706.87369 | S28: =+$E$58*S16 -> -745.24589 | ... AF28: =+$E$58*AF16 -> -1212.3245
B29: 23 | C29: Other financing flows | D29: =156-0.1+90 -> 245.9 | E29: =62+198.6-1.8+71 -> 329.8 | F29: =-0.9+67+146.1+67.5 -> 279.7 | G29: =48.4-3.3+128 -> 173.1 | H29: =(1+H5)*AVERAGE(D29:G29) -> 277.70791 | I29: =(1+I5)*AVERAGE(E29:H29) -> 286.09038 | J29: =(1+J5)*AVERAGE(F29:I29) -> 268.6361 | K29: =(1+K5)*AVERAGE(G29:J29) -> 265.71246 | L29: =(1+L5)*AVERAGE(H29:K29) -> 290.18531 | M29: =(1+M5)*AVERAGE(I29:L29) -> 293.48246 | N29: =(1+N5)*AVERAGE(J29:M29) -> 294.96507 | O29: =(1+O5)*AVERAGE(K29:N29) -> 301.42959 | ... AF29: =(1+AF5)*AVERAGE(AB29:AE29) -> 387.61872
B30: 24 | C30: -Total Financing flows | D30: =SUM(D25:D29) -> -621.9 | E30: =SUM(E25:E29) -> -1521.4 | F30: =SUM(F25:F29) -> -469.4 | G30: =SUM(G25:G29) -> -1084 | H30: =SUM(H25:H29) -> -613.02792 | I30: =SUM(I25:I29) -> -1594.453 | J30: =SUM(J25:J29) -> -780.75501 | K30: =SUM(K25:K29) -> -877.04617 | ... AF30: =SUM(AF25:AF29) -> -3838.1689
A32: SUMMARY | B32: 25 | C32: Cash before shareholder returns | D32: =D21+D24+D25+D26+D29 -> 1261.3 | E32: =E21+E24+E25+E26+E29 -> 651.7 | F32: =F21+F24+F25+F26+F29 -> 1584.7 | G32: =G21+G24+G25+G26+G29 -> 1058.6 | H32: =H21+H24+H25+H26+H29 -> 1516.0658 | I32: =I21+I24+I25+I26+I29 -> 742.4078 | J32: =J21+J24+J25+J26+J29 -> 1835.1533 | K32: =K21+K24+K25+K26+K29 -> 1961.7694 | ... AF32: =AF21+AF24+AF25+AF26+AF29 -> 5270.1556
B33: 26 | C33: Returns to shareholders | D33: =-1*(D27+D28) -> 430.3 | E33: =-1*(E27+E28) -> 863.1 | F33: =-1*(F27+F28) -> 651.6 | G33: =-1*(G27+G28) -> 676.7 | H33: =-1*(H27+H28) -> 791.1822 | I33: =-1*(I27+I28) -> 880.53425 | J33: =-1*(J27+J28) -> 951.97199 | K33: =-1*(K27+K28) -> 1043.2205 | ... AF33: =-1*(AF27+AF28) -> 4084.6742
B34: 27 | C34: Excess cash acumulation | D34: =D32-D33 -> 831 | E34: =E32-E33 -> -211.4 | F34: =F32-F33 -> 933.1 | G34: =G32-G33 -> 381.9 | H34: =H32-H33 -> 724.88358 | I34: =I32-I33 -> -138.12645 | J34: =J32-J33 -> 883.18134 | K34: =K32-K33 -> 918.54892 | ... AF34: =AF32-AF33 -> 1185.4814
A36: CASH & DEBT & DISCOUNTING | B36: 28 | C36: Ending cash balance | D36: =+Cifras_Originales!E22 -> 2979.5 | E36: =D36+E34 -> 2768.1 | F36: =E36+F34 -> 3701.2 | G36: =F36+G34 -> 4083.1 | H36: =G36+H34 -> 4807.9836 | I36: =H36+I34 -> 4669.8571 | J36: =I36+J34 -> 5553.0385 | K36: =J36+K34 -> 6471.5874 | L36: =K36+L34 -> 6213.0366 | ... AF36: =AE36+AF34 -> 25313.832
B37: 29 | C37: Total Debt | D37: =Cifras_en_Millones!F60 -> 4470.7 | E37: =Cifras_en_Millones!E60 -> 3576.7 | F37: =Cifras_en_Millones!D60 -> 3600.9 | G37: =Cifras_en_Millones!C60 -> 2493.6 | H37: =+G37 -> 2493.6 | I37: =+H37-900 -> 1593.6 | J37: =+I37 -> 1593.6 | K37: =+J37 -> 1593.6 | L37: =+K37-1150 -> 443.6 | M37: =L352 -> 0 | N37: =M37 -> 0 | O37: =N37 -> 0 | P37: =O37 -> 0 | Q37: =P37 -> 0 | R37: =Q37 -> 0 | S37: =R37 -> 0 | T37: =S37 -> 0 | U37: =T37 -> 0 | ... AF37: =AE37 -> 0
B38: 30 | C38: Discount factor | G38: =1/((1+$D$47)^G3) -> 1 | H38: =1/((1+$D$47)^H3) -> 0.98094365 | I38: =1/((1+$D$47)^I3) -> 0.90828116 | J38: =1/((1+$D$47)^J3) -> 0.84100107 | K38: =1/((1+$D$47)^K3) -> 0.7787047 | L38: =1/((1+$D$47)^L3) -> 0.72102287 | M38: =1/((1+$D$47)^M3) -> 0.66761377 | N38: =1/((1+$D$47)^N3) -> 0.6181609 | ... AF38: =1/((1+$D$47)^AF3) -> 0.15469416
F39: =1/((1+$D$48+0.001)^F$3) -> 0.9999691 | G39: =1/((1+$D$47+0.001)^G$3) -> 1 | H39: =1/((1+$D$47+0.001)^H$3) -> 0.98071671 | I39: =1/((1+$D$47+0.001)^I$3) -> 0.907231 | J39: =1/((1+$D$47+0.001)^J$3) -> 0.83925162 | K39: =1/((1+$D$47+0.001)^K$3) -> 0.77636598 | L39: =1/((1+$D$47+0.001)^L$3) -> 0.71819239 | M39: =1/((1+$D$47+0.001)^M$3) -> 0.66437779 | N39: =1/((1+$D$47+0.001)^N$3) -> 0.61459555 | ... AE39: =1/((1+$D$47+0.001)^AE$3) -> 0.16351312
F40: =1/((1+$D$48+0.005)^F$3) -> 0.99984581 | G40: =1/((1+$D$47+0.005)^G$3) -> 1 | H40: =1/((1+$D$47+0.005)^H$3) -> 0.97981157 | I40: =1/((1+$D$47+0.005)^I$3) -> 0.90305214 | J40: =1/((1+$D$47+0.005)^J$3) -> 0.83230612 | K40: =1/((1+$D$47+0.005)^K$3) -> 0.76710242 | L40: =1/((1+$D$47+0.005)^L$3) -> 0.70700684 | M40: =1/((1+$D$47+0.005)^M$3) -> 0.6516192 | N40: =1/((1+$D$47+0.005)^N$3) -> 0.60057069 | ... AE40: =1/((1+$D$47+0.005)^AE$3) -> 0.1500578
C42: EPS | H42: {=1000000*H16/_FV(OP!$N$2,"Shares outstanding",TRUE)} -> 0.86634044 | I42: {=1000000*I16/_FV(OP!$N$2,"Shares outstanding",TRUE)} -> 0.96418047 | J42: {=1000000*J16/_FV(OP!$N$2,"Shares outstanding",TRUE)} -> 1.0424044 | M42: =+E28/D28-1 -> 0.51937458 | N42: =+F28/E28-1 -> 0.23579418 | O42: =+G28/F28-1 -> 0.095944967 | P42: =+H28/G28-1 -> -0.040173783
C43: Consenso EPS
C44: E$/UN | H44: =$D$64/H16 -> 33.820958 | I44: =$D$64/I16 -> 30.388983
A46: Discount rate | D46: Total | E46: Risk free rate | F46: Equity premium | G46: Firm premium
C47: Discount Rate | D47: =SUM(E47:G47) -> 0.08 | E47: 0.04 | F47: 0.04 | G47: 0
J48: =1659-G18-G20 -> 186.2
D49: Short Term | E49: Long Term | F49: Reference (line)
A50: Modelling factors | C50: Depreciation factor | F50: % PP&E+Intangibles exc. Goodwill
C51: Stock-based comp | D51: 0.0314 | E51: =+D51 -> 0.0314 | F51: % revenue (l2)
C52: Tax Rate | D52: 0.2248 | E52: =+D52 -> 0.2248 | F52: % (line 9)
C53: Interest Rate on debt | D53: 0.016 | E53: 0.016 | F53: % debt (l29)
C54: Interest Rate on cash | D54: 0.035 | E54: 0.035 | F54: % of cash (l28)
C55: Stock repurchase | D55: =+$H$99 -> -0.43078737 | E55: =+D55-3% -> -0.46078737 | F55: % net income
C56: Working capital flows | D56: -0.71 | E56: =+D56 -> -0.71 | F56: % of change revenues (l2)
C57: Capex / Adq | D57: 0.0324 | E57: =+D57 -> 0.0324 | F57: % revenue (l2)
C58: Dividends | D58: -0.25 | E58: -0.3 | F58: / net income
C59: Other financing flows | F59: MVA, growing with Revenue
A61: Valuation | D61: $ millions | E61: % | F61: Notes | AE61: =((AE36-AE37)*AE38) -> 4031.1162
C62: Value of flows | D62: =SUMPRODUCT(G33:AE33,G38:AE38)+((AE36-AE37)*AE38) -> 24482.332 | E62: =D62/D64 -> 0.62287637 | F62: Present value of flows (l27), plus cash minus debt | AE62: =AE54+AE61 -> 4031.1162
C63: Value of perpetuity | D63: =(AF32/(D47-AF5))*AF38 -> 14822.951 | E63: =D63/D64 -> 0.37712363 | F63: Present value of perpetuity (column AF flow, dividend by growth minus discount rate)
C64: Total Value | D64: =D62+D63 -> 39305.283 | F64: Final market value of firm's equity, compare to its mkt cap
C65: Total value vs Mkt Cap | D65: =D66/D67-1 -> 0.14053967 | F65: Gives degree of undervaluation (if positive, meaning it's worth more than what the market thinks) or overvaluation (negative, worth less than what the market thinks)
C66: Estimated NPV per share | D66: {=1000000*D64/_FV(OP!N2,"Shares outstanding",TRUE)} -> 29.300464 | F66: If we divide total value by # of shares, we get the estimated share value
C67: Actual share price | D67: {=+_FV(OP!N2,"Price")} -> 25.69 | F67: Actual share price
C70: Support | D70: 2024 | E70: =+D70-1 -> 2023 | F70: =+E70-1 -> 2022 | G70: =+F70-1 -> 2021 | H70: AVG
C71: Change in revenue | E71: =+E6-D6 -> 805.3 | F71: =+F6-E6 -> 286.1 | G71: =+G6-F6 -> 262.2
C72: Working capital flows | E72: =+E20 -> -169.8 | F72: =+F20 -> -239.5 | G72: =+G20 -> -286.3
C73: Working Capital flows as %chang in revenue | E73: =+E72/E71 -> -0.2108531 | F73: =+F72/F71 -> -0.83711989 | G73: =+G72/G71 -> -1.0919146 | H73: =+AVERAGE(E73:G73) -> -0.71329585
C74: Revenue | D74: =+D6 -> 4860 | E74: =+E6 -> 5665.3 | F74: =+F6 -> 5951.4 | G74: =+G6 -> 6213.6
C75: Capex+Acq | D75: =+Cifras_en_Millones!C35 -> -191.8 | E75: =+Cifras_en_Millones!D35 -> -161.7 | F75: =+Cifras_en_Millones!E35 -> -213.9 | G75: =+Cifras_en_Millones!F35 -> -160.4
C76: Capex+acq as % of revenue | D76: =+D75/D74 -> -0.039465021 | E76: =+E75/E74 -> -0.028542178 | F76: =+F75/F74 -> -0.035941123 | G76: =+G75/G74 -> -0.025814343 | H76: =+AVERAGE(D76:G76) -> -0.032440666
C79: Support | D79: 2024 | E79: =+D79-1 -> 2023 | F79: =+E79-1 -> 2022 | G79: =+F79-1 -> 2021 | H79: =+G79-1 -> 2020 | I79: AVG
C80: Intangibles excl. Goodwill | D80: =7687.1-4805 -> 2882.1 | E80: 2842.1 | F80: 3302.4 | G80: 3462.6 | H80: 3546.8 | K80: 1) D&A as % of PP&E + Intangibles (excl Goodwill)
C81: PP&E | D81: 945.8 | E81: 882.8 | F81: 819.9 | G81: 817 | H81: 861.1 | K81: 2) PP%E+Intangibles -> growing with capex + % R&D
C82: PP&E + Intangibles excl. Goodwill | D82: =+SUM(D80:D81) -> 3827.9 | E82: =+SUM(E80:E81) -> 3724.9 | F82: =+SUM(F80:F81) -> 4122.3 | G82: =+SUM(G80:G81) -> 4279.6 | H82: =+SUM(H80:H81) -> 4407.9 | K82: Sum PP&E and INtangibles, the difference would be filled by R&D
C83: D&A | D83: 561 | E83: 569.5 | F83: 596.8 | G83: 574.6 | H83: 604.5
C84: D&A as % PP&E + Intangibles excl. Goodwill | D84: =+D83/D82 -> 0.14655555 | E84: =+E83/E82 -> 0.15289001 | F84: =+F83/F82 -> 0.14477355 | G84: =+G83/G82 -> 0.13426488 | H84: =+H83/H82 -> 0.13714013 | I84: =+AVERAGE(D84:H84) -> 0.14312483
C85: Capex | D85: -193.4 | E85: -145.3 | F85: -132.3 | G85: -103.7 | H85: -127
C86: R&D | D86: 1286.2 | E86: 1228.3 | F86: 1087.2 | G86: 949.3 | H86: 935.4
C87: R&D as % revenue | D87: =+D86/G6 -> 0.20699755 | E87: =+E86/F6 -> 0.20638841 | F87: =+F86/E6 -> 0.19190511 | G87: =+G86/D6 -> 0.19532922 | I87: =+AVERAGE(D87:G87) -> 0.20015507
C88: Forecast PP&E+Int (capex and D&A factor) | D88: =+E82-D83-D85 -> 3357.3 | E88: =+F82-E83-E85 -> 3698.1 | F88: =+G82-F83-F85 -> 3815.1 | G88: =+H82-G83-G85 -> 3937
C89: Difference from actual | D89: =+D82-D88 -> 470.6 | E89: =+E82-E88 -> 26.8 | F89: =+F82-F88 -> 307.2 | G89: =+G82-G88 -> 342.6
C90: Difference as % of R&D | D90: =+D89/D86 -> 0.365884 | E90: =+E89/E86 -> 0.021818774 | F90: =+F89/F86 -> 0.28256071 | G90: =+G89/G86 -> 0.3608975 | I90: =+AVERAGE(D90:H90) -> 0.25779025
C92: Forecast | H92: 2025 | I92: =+H92+1 -> 2026 | J92: =+I92+1 -> 2027 | K92: =+J92+1 -> 2028 | L92: =+K92+1 -> 2029 | M92: =+L92+1 -> 2030 | N92: =+M92+1 -> 2031 | O92: =+N92+1 -> 2032 | P92: =+O92+1 -> 2033 | ... AF92: =+AE92+1 -> 2049
C93: R&D | H93: =+H6*$I$87 -> 1343.2407 | I93: =+I6*$I$87 -> 1449.7232 | J93: =+J6*$I$87 -> 1532.3574 | K93: =+K6*$I$87 -> 1619.7018 | L93: =+L6*$I$87 -> 1712.0248 | M93: =+M6*$I$87 -> 1809.6102 | N93: =+N6*$I$87 -> 1909.7102 | O93: =+O6*$I$87 -> 2012.131 | ... AF93: =+AF6*$I$87 -> 3820.7325
C94: PP&E+Intangibles Forecast | H94: =+D82+G9-H22+$I$90*H93 -> 3830.6107 | I94: =+H94-H22-H95+$I$90*I93 -> 3873.5161 | J94: =+I94-I22-I95+$I$90*J93 -> 3948.8198 | K94: =+J94-J22-J95+$I$90*K93 -> 4049.2386 | L94: =+K94-K22-K95+$I$90*L93 -> 4173.2237 | M94: =+L94-L22-L95+$I$90*M93 -> 4319.5648 | N94: =+M94-M22-M95+$I$90*N93 -> 4486.5622 | O94: =+N94-N22-N95+$I$90*O93 -> 4672.2649 | P94: =+O94-O22-O95+$I$90*P93 -> 4874.9137 | ... AF94: =+AE94-AE22-AE95+$I$90*AF93 -> 9324.1921
C95: D&A | H95: =+$I$84*H94 -> 548.2555 | I95: =+$I$84*I94 -> 554.39633 | J95: =+$I$84*J94 -> 565.17415 | K95: =+$I$84*K94 -> 579.54657 | L95: =+$I$84*L94 -> 597.29191 | M95: =+$I$84*M94 -> 618.23696 | N95: =+$I$84*N94 -> 642.13844 | O95: =+$I$84*O94 -> 668.7171 | ... AF95: =+$I$84*AF94 -> 1334.5234
C97: Support | D97: 2021 | E97: =+D97+1 -> 2022 | F97: =+E97+1 -> 2023 | G97: =+F97+1 -> 2024 | H97: AVG
C98: Repurchase (Issuance) of Stock | D98: =+D27 -> -283.2 | E98: =+E27 -> -639.6 | F98: =+F27 -> -375.4 | G98: =+G27 -> -374
C99: % of net income | D99: =+D98/D16 -> -0.36593875 | E99: =+E98/E16 -> -0.68759407 | F99: =+F98/F16 -> -0.35745572 | G99: =+G98/G16 -> -0.31216092 | H99: =+AVERAGE(D99:G99) -> -0.43078737

Sheet Cifras_en_Millones
A1: =Cifras_Originales!G3 -> Dassault Systemes SE (DSY)
A2: =Cifras_Originales!C2 -> Cifras en Millones de USD
A4: Resultados | B4: 2025 | C4: =Cifras_Originales!B5 -> 2024 | D4: =Cifras_Originales!C5 -> 2023 | E4: =Cifras_Originales!D5 -> 2022 | F4: =Cifras_Originales!E5 -> 2021 | G4: =Cifras_Originales!F5 -> 2020 | H4: =Cifras_Originales!G5 -> 2019 | I4: =Cifras_Originales!H5 -> 2018 | J4: =Cifras_Originales!I5 -> 2017 | ... M4: =Cifras_Originales!L5 -> 2014
A5: Ventas Netas | C5: =Cifras_Originales!B6 -> 6213.6 | D5: =Cifras_Originales!C6 -> 5951.4 | E5: =Cifras_Originales!D6 -> 5665.3 | F5: =Cifras_Originales!E6 -> 4860 | G5: =Cifras_Originales!F6 -> 4452.3 | H5: =Cifras_Originales!G6 -> 4018.2 | I5: =Cifras_Originales!H6 -> 3477.4 | J5: =Cifras_Originales!I6 -> 3228 | ... M5: =Cifras_Originales!L6 -> 2294.3
A6: Crecimiento vs. Año pasado | B6: =B5/C5-1 -> -1 | C6: =C5/D5-1 -> 0.044056861 | D6: =D5/E5-1 -> 0.050500415 | E6: =E5/F5-1 -> 0.16569959 | F6: =F5/G5-1 -> 0.091570649 | G6: =G5/H5-1 -> 0.10803345 | H6: =H5/I5-1 -> 0.15551849 | I6: =I5/J5-1 -> 0.077261462 | ... L6: =L5/M5-1 -> 0.23763239
A7: Utilidad Bruta | C7: =Cifras_Originales!B7 -> 5197.3 | D7: =Cifras_Originales!C7 -> 4980.4 | E7: =Cifras_Originales!D7 -> 4746 | F7: =Cifras_Originales!E7 -> 4069.7 | G7: =Cifras_Originales!F7 -> 3702.6 | H7: =Cifras_Originales!G7 -> 3384.6 | I7: =Cifras_Originales!H7 -> 2966.6 | J7: =Cifras_Originales!I7 -> 2754 | ... M7: =Cifras_Originales!L7 -> 1951
A8: porcentaje sobre ventas | B8: =B7/B5 -> #DIV/0! | C8: =C7/C5 -> 0.83643942 | D8: =D7/D5 -> 0.83684511 | E8: =E7/E5 -> 0.83773145 | F8: =F7/F5 -> 0.83738683 | G8: =G7/G5 -> 0.83161512 | H8: =H7/H5 -> 0.84231746 | I8: =I7/I5 -> 0.85310864 | ... M8: =M7/M5 -> 0.8503683
A9: Gastos de Operación | B9: =B5-B11 -> 0 | C9: =C5-C11 -> 4854 | D9: =D5-D11 -> 4709.5 | E9: =E5-E11 -> 4362.4 | F9: =F5-F11 -> 3840.6 | G9: =G5-G11 -> 3782.6 | H9: =H5-H11 -> 3205.4 | I9: =I5-I11 -> 2709.2 | ... M9: =M5-M11 -> 1863.5
A10: porcentaje sobre ventas | B10: =B9/B5 -> #DIV/0! | C10: =C9/C5 -> 0.78118965 | D10: =D9/D5 -> 0.79132641 | E10: =E9/E5 -> 0.77002101 | F10: =F9/F5 -> 0.79024691 | G10: =G9/G5 -> 0.84958336 | H10: =H9/H5 -> 0.79772037 | I10: =I9/I5 -> 0.77908782 | ... M10: =M9/M5 -> 0.81223031
A11: Utilidad de Operación | C11: =Cifras_Originales!B8 -> 1359.6 | D11: =Cifras_Originales!C8 -> 1241.9 | E11: =Cifras_Originales!D8 -> 1302.9 | F11: =Cifras_Originales!E8 -> 1019.4 | G11: =Cifras_Originales!F8 -> 669.7 | H11: =Cifras_Originales!G8 -> 812.8 | I11: =Cifras_Originales!H8 -> 768.2 | J11: =Cifras_Originales!I8 -> 729 | ... M11: =Cifras_Originales!L8 -> 430.8
A12: porcentaje sobre ventas | B12: =B11/B5 -> #DIV/0! | C12: =C11/C5 -> 0.21881035 | D12: =D11/D5 -> 0.20867359 | E12: =E11/E5 -> 0.22997899 | F12: =F11/F5 -> 0.20975309 | G12: =G11/G5 -> 0.15041664 | H12: =H11/H5 -> 0.20227963 | I12: =I11/I5 -> 0.22091218 | ... M12: =M11/M5 -> 0.18776969
A13: Crecimiento vs año anterior | B13: =B11/C11-1 -> -1 | C13: =C11/D11-1 -> 0.094774136 | D13: =D11/E11-1 -> -0.046818635 | E13: =E11/F11-1 -> 0.27810477 | F13: =F11/G11-1 -> 0.52217411 | G13: =G11/H11-1 -> -0.17605807 | H13: =H11/I11-1 -> 0.058057797 | I13: =I11/J11-1 -> 0.053772291 | ... L13: =L11/M11-1 -> 0.46982358
A14: CIF (Productos Financieros) | C14: =Cifras_Originales!B9 -> -118.4 | D14: =Cifras_Originales!C9 -> -98.3 | E14: =Cifras_Originales!D9 -> -13.8 | F14: =Cifras_Originales!E9 -> 16.8 | G14: =Cifras_Originales!F9 -> 22.9 | H14: =Cifras_Originales!G9 -> -8.5 | I14: =Cifras_Originales!H9 -> -21.9 | J14: =Cifras_Originales!I9 -> -13 | ... M14: =Cifras_Originales!L9 -> -17.1
A15: Otros Gastos (Productos) | C15: =Cifras_Originales!B10 -> 0 | D15: =Cifras_Originales!C10 -> -39.3 | E15: =Cifras_Originales!D10 -> -11.1 | F15: =Cifras_Originales!E10 -> 1.7 | G15: =Cifras_Originales!F10 -> -0.5 | H15: =Cifras_Originales!G10 -> -5.4 | I15: =Cifras_Originales!H10 -> -6.3 | J15: =Cifras_Originales!I10 -> 9.4 | ... M15: =Cifras_Originales!L10 -> -2.2
A16: Utilidad antes de Impuestos y partidas extra. | B16: =B11-B14-B15 -> 0 | C16: =C11-C14-C15 -> 1478 | D16: =D11-D14-D15 -> 1379.5 | E16: =E11-E14-E15 -> 1327.8 | F16: =F11-F14-F15 -> 1000.9 | G16: =G11-G14-G15 -> 647.3 | H16: =H11-H14-H15 -> 826.7 | I16: =I11-I14-I15 -> 796.4 | ... M16: =M11-M14-M15 -> 450.1
A17: Depreciación y amortización del ejercicio | C17: =Cifras_Originales!B11 -> -561 | D17: =Cifras_Originales!C11 -> -569.5 | E17: =Cifras_Originales!D11 -> -596.8 | F17: =Cifras_Originales!E11 -> -574.6 | G17: =Cifras_Originales!F11 -> -604.5 | H17: =Cifras_Originales!G11 -> -396 | I17: =Cifras_Originales!H11 -> -237.7 | J17: =Cifras_Originales!I11 -> -217.7 | ... M17: =Cifras_Originales!L11 -> -176.3
A18: Capital de Trabajo | C18: =Cifras_Originales!B12 -> -286.3 | D18: =Cifras_Originales!C12 -> -239.5 | E18: =Cifras_Originales!D12 -> -169.8 | F18: =Cifras_Originales!E12 -> 93.2 | G18: =Cifras_Originales!F12 -> -32.5 | H18: =Cifras_Originales!G12 -> 58.3 | I18: =Cifras_Originales!H12 -> 8.1 | J18: =Cifras_Originales!I12 -> -84.6 | ... M18: =Cifras_Originales!L12 -> 2
A19: EBITDA (flujo operativo) | B19: =B11-B15+B17 -> 0 | C19: =C11-C15+C17 -> 798.6 | D19: =D11-D15+D17 -> 711.7 | E19: =E11-E15+E17 -> 717.2 | F19: =F11-F15+F17 -> 443.1 | G19: =G11-G15+G17 -> 65.7 | H19: =H11-H15+H17 -> 422.2 | I19: =I11-I15+I17 -> 536.8 | ... M19: =M11-M15+M17 -> 256.7
A20: porcentaje sobre ventas | B20: =B19/B5 -> #DIV/0! | C20: =C19/C5 -> 0.12852453 | D20: =D19/D5 -> 0.11958531 | E20: =E19/E5 -> 0.12659524 | F20: =F19/F5 -> 0.09117284 | G20: =G19/G5 -> 0.014756418 | H20: =H19/H5 -> 0.10507192 | I20: =I19/I5 -> 0.15436821 | ... M20: =M19/M5 -> 0.11188598
A21: I.S.R Y P.T.U. | C21: =Cifras_Originales!B15 -> -279.9 | D21: =Cifras_Originales!C15 -> -250.7 | E21: =Cifras_Originales!D15 -> -375.4 | F21: =Cifras_Originales!E15 -> -230.4 | G21: =Cifras_Originales!F15 -> -160.8 | H21: =Cifras_Originales!G15 -> -209.6 | I21: =Cifras_Originales!H15 -> -220.4 | J21: =Cifras_Originales!I15 -> -231.3 | ... M21: =Cifras_Originales!L15 -> -153.3
A22: % Tax | B22: =+B21/B16 -> #DIV/0! | C22: =+C21/C16 -> -0.18937754 | D22: =+D21/D16 -> -0.18173251 | E22: =+E21/E16 -> -0.2827233 | F22: =+F21/F16 -> -0.23019283 | G22: =+G21/G16 -> -0.2484165 | H22: =+H21/H16 -> -0.25353816 | I22: =+I21/I16 -> -0.27674535 | ... M22: =+M21/M16 -> -0.34059098
A23: Utilidad Neta | C23: =Cifras_Originales!B16 -> 1198.1 | D23: =Cifras_Originales!C16 -> 1050.2 | E23: =Cifras_Originales!D16 -> 930.2 | F23: =Cifras_Originales!E16 -> 773.9 | G23: =Cifras_Originales!F16 -> 485.5 | H23: =Cifras_Originales!G16 -> 606.3 | I23: =Cifras_Originales!H16 -> 563.4 | J23: =Cifras_Originales!I16 -> 520.1 | ... M23: =Cifras_Originales!L16 -> 292.5
A24: porcentaje sobre ventas | B24: =B23/B5 -> #DIV/0! | C24: =C23/C5 -> 0.19281898 | D24: =D23/D5 -> 0.17646268 | E24: =E23/E5 -> 0.16419254 | F24: =F23/F5 -> 0.15923868 | G24: =G23/G5 -> 0.10904476 | H24: =H23/H5 -> 0.15088846 | I24: =I23/I5 -> 0.1620176 | ... M24: =M23/M5 -> 0.12748987
A25: Crecimiento vs año anterior | B25: =B23/C23-1 -> -1 | C25: =C23/D23-1 -> 0.14083032 | D25: =D23/E23-1 -> 0.12900452 | E25: =E23/F23-1 -> 0.20196408 | F25: =F23/G23-1 -> 0.59402678 | G25: =G23/H23-1 -> -0.1992413 | H25: =H23/I23-1 -> 0.076144835 | I25: =I23/J23-1 -> 0.083253221 | ... L25: =L23/M23-1 -> 0.38803419
A26: Efectivo Generado | B26: =B40-C40 -> -3952.6 | C26: =C40-D40 -> 384.3 | D26: =D40-E40 -> 799.3 | E26: =E40-F40 -> -210.5 | F26: =F40-G40 -> 830.7 | G26: =G40-H40 -> 203.9 | H26: =H40-I40 -> -865 | I26: =I40-J40 -> 349.2 | ... M26: =M40-N40 -> 1175.5
A27: Dividendos | C27: =Cifras_Originales!B17 -> -302.7 | D27: =Cifras_Originales!C17 -> -276.2 | E27: =Cifras_Originales!D17 -> -223.5 | F27: =Cifras_Originales!E17 -> -147.1 | G27: =Cifras_Originales!F17 -> -182.5 | H27: =Cifras_Originales!G17 -> -168.8 | I27: =Cifras_Originales!H17 -> -38 | J27: =Cifras_Originales!I17 -> -51.3 | ... M27: =Cifras_Originales!L17 -> -35.8
B28: =B27/C27-1 -> -1 | C28: =C27/D27-1 -> 0.095944967 | D28: =D27/E27-1 -> 0.23579418 | E28: =E27/F27-1 -> 0.51937458 | F28: =F27/G27-1 -> -0.1939726 | G28: =G27/H27-1 -> 0.081161137 | H28: =H27/I27-1 -> 3.4421053 | I28: =I27/J27-1 -> -0.25925926 | ... L28: =L27/M27-1 -> 1.7486034
A29: Recompra de Acciones | C29: =Cifras_Originales!B18 -> -325.6 | D29: =Cifras_Originales!C18 -> -162.3 | E29: =Cifras_Originales!D18 -> -379 | F29: =Cifras_Originales!E18 -> -127.2 | G29: =Cifras_Originales!F18 -> -78.5 | H29: =Cifras_Originales!G18 -> -43.4 | I29: =Cifras_Originales!H18 -> -136.4 | J29: =Cifras_Originales!I18 -> -70.6 | ... M29: =Cifras_Originales!L18 -> -113.8
A30: FNP | B30: =+B26+B27+B29 -> -3952.6 | C30: =+C26+C27+C29 -> -244 | D30: =+D26+D27+D29 -> 360.8 | E30: =+E26+E27+E29 -> -813 | F30: =+F26+F27+F29 -> 556.4 | G30: =+G26+G27+G29 -> -57.1 | H30: =+H26+H27+H29 -> -1077.2 | I30: =+I26+I27+I29 -> 174.8 | ... M30: =+M26+M27+M29 -> 1025.9
A31: FNP (ajustado por deuda) | B31: =B30-(B60-C60) -> -1459 | C31: =C30-(C60-D60) -> 863.3 | D31: =D30-(D60-E60) -> 336.6 | E31: =E30-(E60-F60) -> 81 | F31: =F30-(F60-G60) -> 919.3 | G31: =G30-(G60-H60) -> 406.3 | H31: =H30-(H60-I60) -> -5374.2 | I31: =I30-(I60-J60) -> 174.8 | ... M31: =M30-(M60-N60) -> 665.9
A32: FNP (ajustado por inversiones) | B32: =B31+B34 -> -1459 | C32: =C31+C34 -> 864.9 | D32: =D31+D34 -> 320.2 | E32: =E31+E34 -> -0.6 | F32: =F31+F34 -> 862.6 | G32: =G31+G34 -> 325.3 | H32: =H31+H34 -> -10610.7 | I32: =I31+I34 -> -76 | ... M32: =M31+M34 -> -289.6
A33: Capex | C33: =Cifras_Originales!B13 -> -193.4 | D33: =Cifras_Originales!C13 -> -145.3 | E33: =Cifras_Originales!D13 -> -132.3 | F33: =Cifras_Originales!E13 -> -103.7 | G33: =Cifras_Originales!F13 -> -127 | H33: =Cifras_Originales!G13 -> -98.3 | I33: =Cifras_Originales!H13 -> -72.4 | J33: =Cifras_Originales!I13 -> -84.5 | ... O33: =Cifras_Originales!N13 -> -40.6
A34: Inversiones | C34: =Cifras_Originales!B14 -> 1.6 | D34: =Cifras_Originales!C14 -> -16.4 | E34: =Cifras_Originales!D14 -> -81.6 | F34: =Cifras_Originales!E14 -> -56.7 | G34: =Cifras_Originales!F14 -> -81 | H34: =Cifras_Originales!G14 -> -5236.5 | I34: =Cifras_Originales!H14 -> -250.8 | J34: =Cifras_Originales!I14 -> -282.9 | ... O34: =Cifras_Originales!N14 -> -178.2
A35: Capex + Inversiones | B35: =+B34+B33 -> 0 | C35: =+C34+C33 -> -191.8 | D35: =+D34+D33 -> -161.7 | E35: =+E34+E33 -> -213.9 | F35: =+F34+F33 -> -160.4 | G35: =+G34+G33 -> -208 | H35: =+H34+H33 -> -5334.8 | I35: =+I34+I33 -> -323.2 | J35: =+J34+J33 -> -367.4 | L35: =+L34+L33 -> -60.5 | M35: =+M34+M33 -> -1000.9 | N35: =+N34+N33 -> -168.6 | O35: =+O34+O33 -> -218.8
B36: =+B35/B5 -> #DIV/0! | C36: =+C35/C5 -> -0.030867774 | D36: =+D35/D5 -> -0.027170078 | E36: =+E35/E5 -> -0.037756165 | F36: =+F35/F5 -> -0.033004115 | G36: =+G35/G5 -> -0.046717427 | H36: =+H35/H5 -> -1.3276592 | I36: =+I35/I5 -> -0.092943003 | ... M36: =+M35/M5 -> -0.43625507
A37: Dividendos + Recompra de Acciones | B37: =SUM(B27:B29) -> -1 | C37: =SUM(C27:C29) -> -628.20406 | D37: =SUM(D27:D29) -> -438.26421 | E37: =SUM(E27:E29) -> -601.98063 | F37: =SUM(F27:F29) -> -274.49397 | G37: =SUM(G27:G29) -> -260.91884 | H37: =SUM(H27:H29) -> -208.75789 | I37: =SUM(I27:I29) -> -174.65926 | ... M37: =SUM(M27:M29) -> -149.6
A39: Activo
A40: Caja | C40: =Cifras_Originales!B22 -> 3952.6 | D40: =Cifras_Originales!C22 -> 3568.3 | E40: =Cifras_Originales!D22 -> 2769 | F40: =Cifras_Originales!E22 -> 2979.5 | G40: =Cifras_Originales!F22 -> 2148.8 | H40: =Cifras_Originales!G22 -> 1944.9 | I40: =Cifras_Originales!H22 -> 2809.9 | J40: =Cifras_Originales!I22 -> 2460.7 | ... M40: =Cifras_Originales!L22 -> 1175.5
A41: Cuentas y documentos por cobrar | C41: =Cifras_Originales!B23 -> 2151 | D41: =Cifras_Originales!C23 -> 1734.7 | E41: =Cifras_Originales!D23 -> 1681.9 | F41: =Cifras_Originales!E23 -> 1379 | G41: =Cifras_Originales!F23 -> 1256.1 | H41: =Cifras_Originales!G23 -> 1346.1 | I41: =Cifras_Originales!H23 -> 1070.6 | J41: =Cifras_Originales!I23 -> 895.9 | ... M41: =Cifras_Originales!L23 -> 627.7
A42: Inventarios | C42: =Cifras_Originales!B24 -> 0 | D42: =Cifras_Originales!C24 -> 0 | E42: =Cifras_Originales!D24 -> 0 | F42: =Cifras_Originales!E24 -> 0 | G42: =Cifras_Originales!F24 -> 0 | H42: =Cifras_Originales!G24 -> 0 | I42: =Cifras_Originales!H24 -> 0 | J42: =Cifras_Originales!I24 -> 0 | ... M42: =Cifras_Originales!L24 -> 0
A43: Activos Fijos (Net Plant) | C43: =Cifras_Originales!B25 -> 945.8 | D43: =Cifras_Originales!C25 -> 882.8 | E43: =Cifras_Originales!D25 -> 819.9 | F43: =Cifras_Originales!E25 -> 817 | G43: =Cifras_Originales!F25 -> 861.1 | H43: =Cifras_Originales!G25 -> 899.7 | I43: =Cifras_Originales!H25 -> 178.2 | J43: =Cifras_Originales!I25 -> 169 | ... M43: =Cifras_Originales!L25 -> 136.7
A44: Otros Activos | B44: =B45-SUM(B40:B43) -> 0 | C44: =Cifras_Originales!B26 -> 8496.5 | D44: =Cifras_Originales!C26 -> 9011 | E44: =Cifras_Originales!D26 -> 9056 | F44: =Cifras_Originales!E26 -> 8725 | G44: =Cifras_Originales!F26 -> 9709 | H44: =Cifras_Originales!G26 -> 3942 | I44: =Cifras_Originales!H26 -> 3504 | J44: =Cifras_Originales!I26 -> 3495 | ... M44: =Cifras_Originales!L26 -> 1811
A45: Total Activo | C45: =Cifras_Originales!B27 -> 15545.9 | D45: =Cifras_Originales!C27 -> 14622.4 | E45: =Cifras_Originales!D27 -> 14261.1 | F45: =Cifras_Originales!E27 -> 14218.7 | G45: =Cifras_Originales!F27 -> 12964.2 | H45: =Cifras_Originales!G27 -> 13872.6 | I45: =Cifras_Originales!H27 -> 7974 | J45: =Cifras_Originales!I27 -> 7029.8 | ... M45: =Cifras_Originales!L27 -> 4962.4
A48: Pasivo
A49: Pasivo Corto Plazo | C49: =Cifras_Originales!B31 -> 3521.5 | D49: =Cifras_Originales!C31 -> 3561 | E49: =Cifras_Originales!D31 -> 2881 | F49: =Cifras_Originales!E31 -> 3470.3 | G49: =Cifras_Originales!F31 -> 2086.9 | H49: =Cifras_Originales!G31 -> 2133.8 | I49: =Cifras_Originales!H31 -> 2022.7 | J49: =Cifras_Originales!I31 -> 1527.5 | ... M49: =Cifras_Originales!L31 -> 1134.9
A50: Deuda a corto plazo | C50: =Cifras_Originales!B32 -> 450.8 | D50: =Cifras_Originales!C32 -> 950.1 | E50: =Cifras_Originales!D32 -> 258.6 | F50: =Cifras_Originales!E32 -> 903.2 | G50: =Cifras_Originales!F32 -> 16 | H50: =Cifras_Originales!G32 -> 4.4 | I50: =Cifras_Originales!H32 -> 350 | J50: =Cifras_Originales!I32 -> 0 | ... M50: =Cifras_Originales!L32 -> 10
A51: Short-Term Leases | C51: =Cifras_Originales!B33 -> 0 | D51: =Cifras_Originales!C33 -> 66.5 | E51: =Cifras_Originales!D33 -> 83.1 | F51: =Cifras_Originales!E33 -> 83.5 | G51: =Cifras_Originales!F33 -> 78.8 | H51: =Cifras_Originales!G33 -> 83 | I51: =Cifras_Originales!H33 -> 0 | J51: =Cifras_Originales!I33 -> 0 | ... M51: =Cifras_Originales!L33 -> 0
A52: Otros Pasivos a Corto Plazo | C52: =Cifras_Originales!B34 -> 3070.7 | D52: =Cifras_Originales!C34 -> 2456 | E52: =Cifras_Originales!D34 -> 2400 | F52: =Cifras_Originales!E34 -> 1913 | G52: =Cifras_Originales!F34 -> 1963 | H52: =Cifras_Originales!G34 -> 1673 | I52: =Cifras_Originales!H34 -> 1528 | J52: =Cifras_Originales!I34 -> 1466 | ... M52: =Cifras_Originales!L34 -> 868
A53: Pasivo Largo Plazo | C53: =Cifras_Originales!B35 -> 2943.7 | D53: =Cifras_Originales!C35 -> 3215.4 | E53: =Cifras_Originales!D35 -> 4055.2 | F53: =Cifras_Originales!E35 -> 4537.4 | G53: =Cifras_Originales!F35 -> 5771.2 | H53: =Cifras_Originales!G35 -> 6476.3 | I53: =Cifras_Originales!H35 -> 1325.4 | J53: =Cifras_Originales!I35 -> 1506.3 | ... M53: =Cifras_Originales!L35 -> 868
A54: Deuda a largo plazo | C54: =Cifras_Originales!B36 -> 2042.8 | D54: =Cifras_Originales!C36 -> 2040.6 | E54: =Cifras_Originales!D36 -> 2737.4 | F54: =Cifras_Originales!E36 -> 2966.4 | G54: =Cifras_Originales!F36 -> 4174.3 | H54: =Cifras_Originales!G36 -> 4596.8 | I54: =Cifras_Originales!H36 -> 650 | J54: =Cifras_Originales!I36 -> 1000 | ... M54: =Cifras_Originales!L36 -> 350
A55: Long-Term Leases | C55: =Cifras_Originales!B37 -> 0 | D55: =Cifras_Originales!C37 -> 543.7 | E55: =Cifras_Originales!D37 -> 497.6 | F55: =Cifras_Originales!E37 -> 517.6 | G55: =Cifras_Originales!F37 -> 564.5 | H55: =Cifras_Originales!G37 -> 612.8 | I55: =Cifras_Originales!H37 -> 0 | J55: =Cifras_Originales!I37 -> 0 | ... M55: =Cifras_Originales!L37 -> 0
A56: Otros Pasivos a Largo Plazo | B56: =B53-SUM(B54:B55) -> 0 | C56: =Cifras_Originales!B38 -> 900.9 | D56: =Cifras_Originales!C38 -> 323 | E56: =Cifras_Originales!D38 -> 536 | F56: =Cifras_Originales!E38 -> 468 | G56: =Cifras_Originales!F38 -> 654 | H56: =Cifras_Originales!G38 -> 675 | I56: =Cifras_Originales!H38 -> 506 | J56: =Cifras_Originales!I38 -> 595 | ... M56: =Cifras_Originales!L38 -> 316
A57: Total pasivos | C57: =Cifras_Originales!B39 -> 6465.2 | D57: =Cifras_Originales!C39 -> 6776.4 | E57: =Cifras_Originales!D39 -> 6936.2 | F57: =Cifras_Originales!E39 -> 8007.7 | G57: =Cifras_Originales!F39 -> 7858.1 | H57: =Cifras_Originales!G39 -> 8610.1 | I57: =Cifras_Originales!H39 -> 3348.1 | J57: =Cifras_Originales!I39 -> 3033.8 | ... M57: =Cifras_Originales!L39 -> 2002.9
A59: Deuda Neta | B59: =B60-B40 -> 0 | C59: =C60-C40 -> -1459 | D59: =D60-D40 -> 32.6 | E59: =E60-E40 -> 807.7 | F59: =F60-F40 -> 1491.2 | G59: =G60-G40 -> 2684.8 | H59: =H60-H40 -> 3352.1 | I59: =I60-I40 -> -1809.9 | ... M59: =M60-M40 -> -815.5
A60: Deuda | B60: =B50+B51+B54+B55 -> 0 | C60: =C50+C51+C54+C55 -> 2493.6 | D60: =D50+D51+D54+D55 -> 3600.9 | E60: =E50+E51+E54+E55 -> 3576.7 | F60: =F50+F51+F54+F55 -> 4470.7 | G60: =G50+G51+G54+G55 -> 4833.6 | H60: =H50+H51+H54+H55 -> 5297 | I60: =I50+I51+I54+I55 -> 1000 | ... M60: =M50+M51+M54+M55 -> 360
B61: =B60/B45 -> #DIV/0! | C61: =C60/C45 -> 0.16040242 | D61: =D60/D45 -> 0.24625916 | E61: =E60/E45 -> 0.25080113 | F61: =F60/F45 -> 0.31442396 | G61: =G60/G45 -> 0.37284213 | H61: =H60/H45 -> 0.38183181 | I61: =I60/I45 -> 0.12540757 | ... M61: =M60/M45 -> 0.072545542
A63: Interés Minoritario | B63: 0 | C63: =Cifras_Originales!B42 -> 14.1 | D63: =Cifras_Originales!C42 -> 11.9 | E63: =Cifras_Originales!D42 -> 14.2 | F63: =Cifras_Originales!E42 -> 13.7 | G63: =Cifras_Originales!F42 -> 44.8 | H63: =Cifras_Originales!G42 -> 53.9 | I63: =Cifras_Originales!H42 -> 63.9 | J63: =Cifras_Originales!I42 -> 1.9 | ... M63: =Cifras_Originales!L42 -> 16
A66: Capital Contable | B66: =B45-B57-B63 -> 0 | C66: =C45-C57-C63 -> 9066.6 | D66: =D45-D57-D63 -> 7834.1 | E66: =E45-E57-E63 -> 7310.7 | F66: =F45-F57-F63 -> 6197.3 | G66: =G45-G57-G63 -> 5061.3 | H66: =H45-H57-H63 -> 5208.6 | I66: =I45-I57-I63 -> 4562 | ... M66: =M45-M57-M63 -> 2943.5
A69: OTROS DATOS AL FIN DE AÑO
A70: Numero deEmpleados | C70: =Cifras_Originales!B47 -> 24000 | D70: =Cifras_Originales!C47 -> 0 | E70: =Cifras_Originales!D47 -> 0 | F70: =Cifras_Originales!E47 -> 0 | G70: =Cifras_Originales!F47 -> 0 | H70: =Cifras_Originales!G47 -> 0 | I70: =Cifras_Originales!H47 -> 0 | J70: =Cifras_Originales!I47 -> 0 | ... M70: =Cifras_Originales!L47 -> 0
A71: Acciones en circulación (millones) | C71: =+Cifras_Originales!B48 -> 1341.456 | D71: =+Cifras_Originales!C48 -> 0 | E71: =+Cifras_Originales!D48 -> 0 | F71: =+Cifras_Originales!E48 -> 0 | G71: =+Cifras_Originales!F48 -> 0 | H71: =+Cifras_Originales!G48 -> 0 | I71: =+Cifras_Originales!H48 -> 0 | J71: =+Cifras_Originales!I48 -> 0 | ... M71: =+Cifras_Originales!L48 -> 0
A72: Float | C72: =Cifras_Originales!B49 -> 0.49836894 | D72: =Cifras_Originales!C49 -> 0 | E72: =Cifras_Originales!D49 -> 0 | F72: =Cifras_Originales!E49 -> 0 | G72: =Cifras_Originales!F49 -> 0 | H72: =Cifras_Originales!G49 -> 0 | I72: =Cifras_Originales!H49 -> 0 | J72: =Cifras_Originales!I49 -> 0 | ... M72: =Cifras_Originales!L49 -> 0
A73: Insiders Own | C73: =Cifras_Originales!B50 -> 0.4812 | D73: =Cifras_Originales!C50 -> 0 | E73: =Cifras_Originales!D50 -> 0 | F73: =Cifras_Originales!E50 -> 0 | G73: =Cifras_Originales!F50 -> 0 | H73: =Cifras_Originales!G50 -> 0 | I73: =Cifras_Originales!H50 -> 0 | J73: =Cifras_Originales!I50 -> 0 | ... M73: =Cifras_Originales!L50 -> 0
A74: S&P | C74: =+Cifras_Originales!B51 -> 0 | D74: =+Cifras_Originales!C51 -> 0 | E74: =+Cifras_Originales!D51 -> 0 | F74: =+Cifras_Originales!E51 -> 0 | G74: =+Cifras_Originales!F51 -> 0 | H74: =+Cifras_Originales!G51 -> 0 | I74: =+Cifras_Originales!H51 -> 0 | J74: =+Cifras_Originales!I51 -> 0 | ... M74: =+Cifras_Originales!L51 -> 0
A75: =Cifras_Originales!A52 -> Vol. Diario en Millones USD | C75: =Cifras_Originales!B52 -> 0 | D75: =Cifras_Originales!C52 -> 0 | E75: =Cifras_Originales!D52 -> 0 | F75: =Cifras_Originales!E52 -> 0 | G75: =Cifras_Originales!F52 -> 0 | H75: =Cifras_Originales!G52 -> 0 | I75: =Cifras_Originales!H52 -> 0 | J75: =Cifras_Originales!I52 -> 0 | ... M75: =Cifras_Originales!L52 -> 0 | IH75: =Cifras_Originales!GM52 -> 0
B77: =+Cifras_Originales!B53 -> 2022 | C77: =+Cifras_Originales!C53 -> 2023 | D77: =+Cifras_Originales!D53 -> 2024
A78: =Cifras_Originales!A54 -> Posicion en Corto (%) | B78: =Cifras_Originales!B54 -> 0
A79: =Cifras_Originales!A55 -> EPS | B79: =Cifras_Originales!B55 -> 0.71 | C79: =Cifras_Originales!C55 -> 0.8 | D79: =Cifras_Originales!D55 -> 0.91
A81: =+Cifras_Originales!A57 -> BONOS DE LA EMISORA A 3, 5 Y 10 | B81: Precio Medio | C81: Moody's | D81: YTM | E81: DIVISA
A82: =+Cifras_Originales!A58 -> 0 | B82: =+Cifras_Originales!B58 -> 0 | C82: =+Cifras_Originales!C58 -> 0 | D82: =+Cifras_Originales!D58 -> 0 | E82: =+Cifras_Originales!E58 -> 0
A83: =+Cifras_Originales!A59 -> 0 | B83: =+Cifras_Originales!B59 -> 0 | C83: =+Cifras_Originales!C59 -> 0 | D83: =+Cifras_Originales!D59 -> 0 | E83: =+Cifras_Originales!E59 -> 0
A84: =+Cifras_Originales!A60 -> 0 | B84: =+Cifras_Originales!B60 -> 0 | C84: =+Cifras_Originales!C60 -> 0 | D84: =+Cifras_Originales!D60 -> 0 | E84: =+Cifras_Originales!E60 -> 0
A85: =+Cifras_Originales!A61 -> 0 | B85: =+Cifras_Originales!B61 -> 0 | C85: =+Cifras_Originales!C61 -> 0 | D85: =+Cifras_Originales!D61 -> 0 | E85: =+Cifras_Originales!E61 -> 0

Sheet Cifras_Originales
A1: USD
A2: Millones | C2: Cifras en Millones de USD | K2: #VALUE!
A3: {=_FV(K2,"Name")} -> Dassault Systemes SE | G3: =A3&" ("&A4&")" -> Dassault Systemes SE (DSY)
A4: {=_FV(K2,"Ticker symbol",TRUE)} -> DSY
A5: RESULTADOS | B5: 2024 | C5: =+B5-1 -> 2023 | D5: =+C5-1 -> 2022 | E5: =+D5-1 -> 2021 | F5: =+E5-1 -> 2020 | G5: =+F5-1 -> 2019 | H5: =+G5-1 -> 2018 | I5: =+H5-1 -> 2017 | J5: =+I5-1 -> 2016 | ... N5: =+M5-1 -> 2012
A6: Ventas Netas | B6: =_xlfn.XLOOKUP("Revenue",'[2]Income - GAAP'!$A:$A,'[2]Income - GAAP'!E:E) -> 6213.6 | C6: =_xlfn.XLOOKUP("Revenue",'[2]Income - GAAP'!$A:$A,'[2]Income - GAAP'!F:F) -> 5951.4 | D6: =_xlfn.XLOOKUP("Revenue",'[2]Income - GAAP'!$A:$A,'[2]Income - GAAP'!G:G) -> 5665.3 | E6: =_xlfn.XLOOKUP("Revenue",'[2]Income - GAAP'!$A:$A,'[2]Income - GAAP'!H:H) -> 4860 | F6: =_xlfn.XLOOKUP("Revenue",'[2]Income - GAAP'!$A:$A,'[2]Income - GAAP'!I:I) -> 4452.3 | G6: =_xlfn.XLOOKUP("Revenue",'[2]Income - GAAP'!$A:$A,'[2]Income - GAAP'!J:J) -> 4018.2 | H6: =_xlfn.XLOOKUP("Revenue",'[2]Income - GAAP'!$A:$A,'[2]Income - GAAP'!K:K) -> 3477.4 | I6: =_xlfn.XLOOKUP("Revenue",'[2]Income - GAAP'!$A:$A,'[2]Income - GAAP'!L:L) -> 3228 | J6: =_xlfn.XLOOKUP("Revenue",'[2]Income - GAAP'!$A:$A,'[2]Income - GAAP'!M:M) -> 3055.6 | K6: =_xlfn.XLOOKUP("Revenue",'[2]Income - GAAP'!$A:$A,'[2]Income - GAAP'!N:N) -> 2839.5 | L6: =_xlfn.XLOOKUP("Revenue",'[2]Income - GAAP'!$A:$A,'[2]Income - GAAP'!O:O) -> 2294.3 | M6: =_xlfn.XLOOKUP("Revenue",'[2]Income - GAAP'!$A:$A,'[2]Income - GAAP'!P:P) -> 2066.1 | N6: =_xlfn.XLOOKUP("Revenue",'[2]Income - GAAP'!$A:$A,'[2]Income - GAAP'!Q:Q) -> 2028.342
A7: Utilidad Bruta | B7: =_xlfn.XLOOKUP("Gross Profit",'[2]Income - GAAP'!$A:$A,'[2]Income - GAAP'!E:E) -> 5197.3 | C7: =_xlfn.XLOOKUP("Gross Profit",'[2]Income - GAAP'!$A:$A,'[2]Income - GAAP'!F:F) -> 4980.4 | D7: =_xlfn.XLOOKUP("Gross Profit",'[2]Income - GAAP'!$A:$A,'[2]Income - GAAP'!G:G) -> 4746 | E7: =_xlfn.XLOOKUP("Gross Profit",'[2]Income - GAAP'!$A:$A,'[2]Income - GAAP'!H:H) -> 4069.7 | F7: =_xlfn.XLOOKUP("Gross Profit",'[2]Income - GAAP'!$A:$A,'[2]Income - GAAP'!I:I) -> 3702.6 | G7: =_xlfn.XLOOKUP("Gross Profit",'[2]Income - GAAP'!$A:$A,'[2]Income - GAAP'!J:J) -> 3384.6 | H7: =_xlfn.XLOOKUP("Gross Profit",'[2]Income - GAAP'!$A:$A,'[2]Income - GAAP'!K:K) -> 2966.6 | I7: =_xlfn.XLOOKUP("Gross Profit",'[2]Income - GAAP'!$A:$A,'[2]Income - GAAP'!L:L) -> 2754 | J7: =_xlfn.XLOOKUP("Gross Profit",'[2]Income - GAAP'!$A:$A,'[2]Income - GAAP'!M:M) -> 2592 | K7: =_xlfn.XLOOKUP("Gross Profit",'[2]Income - GAAP'!$A:$A,'[2]Income - GAAP'!N:N) -> 2401.5 | L7: =_xlfn.XLOOKUP("Gross Profit",'[2]Income - GAAP'!$A:$A,'[2]Income - GAAP'!O:O) -> 1951 | M7: =_xlfn.XLOOKUP("Gross Profit",'[2]Income - GAAP'!$A:$A,'[2]Income - GAAP'!P:P) -> 1804.8 | N7: =_xlfn.XLOOKUP("Gross Profit",'[2]Income - GAAP'!$A:$A,'[2]Income - GAAP'!Q:Q) -> 1761.308
A8: Utilidad de Operación | B8: =_xlfn.XLOOKUP("Operating Income (Loss)",'[2]Income - GAAP'!$A:$A,'[2]Income - GAAP'!E:E) -> 1359.6 | C8: =_xlfn.XLOOKUP("Operating Income (Loss)",'[2]Income - GAAP'!$A:$A,'[2]Income - GAAP'!F:F) -> 1241.9 | D8: =_xlfn.XLOOKUP("Operating Income (Loss)",'[2]Income - GAAP'!$A:$A,'[2]Income - GAAP'!G:G) -> 1302.9 | E8: =_xlfn.XLOOKUP("Operating Income (Loss)",'[2]Income - GAAP'!$A:$A,'[2]Income - GAAP'!H:H) -> 1019.4 | F8: =_xlfn.XLOOKUP("Operating Income (Loss)",'[2]Income - GAAP'!$A:$A,'[2]Income - GAAP'!I:I) -> 669.7 | G8: =_xlfn.XLOOKUP("Operating Income (Loss)",'[2]Income - GAAP'!$A:$A,'[2]Income - GAAP'!J:J) -> 812.8 | H8: =_xlfn.XLOOKUP("Operating Income (Loss)",'[2]Income - GAAP'!$A:$A,'[2]Income - GAAP'!K:K) -> 768.2 | I8: =_xlfn.XLOOKUP("Operating Income (Loss)",'[2]Income - GAAP'!$A:$A,'[2]Income - GAAP'!L:L) -> 729 | J8: =_xlfn.XLOOKUP("Operating Income (Loss)",'[2]Income - GAAP'!$A:$A,'[2]Income - GAAP'!M:M) -> 672 | K8: =_xlfn.XLOOKUP("Operating Income (Loss)",'[2]Income - GAAP'!$A:$A,'[2]Income - GAAP'!N:N) -> 633.2 | L8: =_xlfn.XLOOKUP("Operating Income (Loss)",'[2]Income - GAAP'!$A:$A,'[2]Income - GAAP'!O:O) -> 430.8 | M8: =_xlfn.XLOOKUP("Operating Income (Loss)",'[2]Income - GAAP'!$A:$A,'[2]Income - GAAP'!P:P) -> 503 | N8: =_xlfn.XLOOKUP("Operating Income (Loss)",'[2]Income - GAAP'!$A:$A,'[2]Income - GAAP'!Q:Q) -> 500.961
A9: CIF (Poductos) | B9: -118.4 | C9: =_xlfn.XLOOKUP(" + Interest Expense, Net",'[2]Income - GAAP'!$A:$A,'[2]Income - GAAP'!F:F) -> -98.3 | D9: =_xlfn.XLOOKUP(" + Interest Expense, Net",'[2]Income - GAAP'!$A:$A,'[2]Income - GAAP'!G:G) -> -13.8 | E9: =_xlfn.XLOOKUP(" + Interest Expense, Net",'[2]Income - GAAP'!$A:$A,'[2]Income - GAAP'!H:H) -> 16.8 | F9: =_xlfn.XLOOKUP(" + Interest Expense, Net",'[2]Income - GAAP'!$A:$A,'[2]Income - GAAP'!I:I) -> 22.9 | G9: =_xlfn.XLOOKUP(" + Interest Expense, Net",'[2]Income - GAAP'!$A:$A,'[2]Income - GAAP'!J:J) -> -8.5 | H9: =_xlfn.XLOOKUP(" + Interest Expense, Net",'[2]Income - GAAP'!$A:$A,'[2]Income - GAAP'!K:K) -> -21.9 | I9: =_xlfn.XLOOKUP(" + Interest Expense, Net",'[2]Income - GAAP'!$A:$A,'[2]Income - GAAP'!L:L) -> -13 | J9: =_xlfn.XLOOKUP(" + Interest Expense, Net",'[2]Income - GAAP'!$A:$A,'[2]Income - GAAP'!M:M) -> 7.9 | K9: =_xlfn.XLOOKUP(" + Interest Expense, Net",'[2]Income - GAAP'!$A:$A,'[2]Income - GAAP'!N:N) -> -11.2 | L9: =_xlfn.XLOOKUP(" + Interest Expense, Net",'[2]Income - GAAP'!$A:$A,'[2]Income - GAAP'!O:O) -> -17.1 | M9: =_xlfn.XLOOKUP(" + Interest Expense, Net",'[2]Income - GAAP'!$A:$A,'[2]Income - GAAP'!P:P) -> -18.2 | N9: =_xlfn.XLOOKUP(" + Interest Expense, Net",'[2]Income - GAAP'!$A:$A,'[2]Income - GAAP'!Q:Q) -> -13.311
A10: Otros Gastos (Ingresos) | B10: 0 | C10: =-_xlfn.XLOOKUP(" + Other Non-Op (Income) Loss",'[2]Income - GAAP'!$A:$A,'[2]Income - GAAP'!F:F)-_xlfn.XLOOKUP(" + Foreign Exch (Gain) Loss",'[2]Income - GAAP'!$A:$A,'[2]Income - GAAP'!F:F)-_xlfn.XLOOKUP(" + (Income) Loss from Affiliates",'[2]Income - GAAP'!$A:$A,'[2]Income - GAAP'!F:F) -> -39.3 | D10: =-_xlfn.XLOOKUP(" + Other Non-Op (Income) Loss",'[2]Income - GAAP'!$A:$A,'[2]Income - GAAP'!G:G)-_xlfn.XLOOKUP(" + Foreign Exch (Gain) Loss",'[2]Income - GAAP'!$A:$A,'[2]Income - GAAP'!G:G)-_xlfn.XLOOKUP(" + (Income) Loss from Affiliates",'[2]Income - GAAP'!$A:$A,'[2]Income - GAAP'!G:G) -> -11.1 | E10: =-_xlfn.XLOOKUP(" + Other Non-Op (Income) Loss",'[2]Income - GAAP'!$A:$A,'[2]Income - GAAP'!H:H)-_xlfn.XLOOKUP(" + Foreign Exch (Gain) Loss",'[2]Income - GAAP'!$A:$A,'[2]Income - GAAP'!H:H)-_xlfn.XLOOKUP(" + (Income) Loss from Affiliates",'[2]Income - GAAP'!$A:$A,'[2]Income - GAAP'!H:H) -> 1.7 | F10: =-_xlfn.XLOOKUP(" + Other Non-Op (Income) Loss",'[2]Income - GAAP'!$A:$A,'[2]Income - GAAP'!I:I)-_xlfn.XLOOKUP(" + Foreign Exch (Gain) Loss",'[2]Income - GAAP'!$A:$A,'[2]Income - GAAP'!I:I)-_xlfn.XLOOKUP(" + (Income) Loss from Affiliates",'[2]Income - GAAP'!$A:$A,'[2]Income - GAAP'!I:I) -> -0.5 | G10: =-_xlfn.XLOOKUP(" + Other Non-Op (Income) Loss",'[2]Income - GAAP'!$A:$A,'[2]Income - GAAP'!J:J)-_xlfn.XLOOKUP(" + Foreign Exch (Gain) Loss",'[2]Income - GAAP'!$A:$A,'[2]Income - GAAP'!J:J)-_xlfn.XLOOKUP(" + (Income) Loss from Affiliates",'[2]Income - GAAP'!$A:$A,'[2]Income - GAAP'!J:J) -> -5.4 | H10: =-_xlfn.XLOOKUP(" + Other Non-Op (Income) Loss",'[2]Income - GAAP'!$A:$A,'[2]Income - GAAP'!K:K)-_xlfn.XLOOKUP(" + Foreign Exch (Gain) Loss",'[2]Income - GAAP'!$A:$A,'[2]Income - GAAP'!K:K)-_xlfn.XLOOKUP(" + (Income) Loss from Affiliates",'[2]Income - GAAP'!$A:$A,'[2]Income - GAAP'!K:K) -> -6.3 | I10: =-_xlfn.XLOOKUP(" + Other Non-Op (Income) Loss",'[2]Income - GAAP'!$A:$A,'[2]Income - GAAP'!L:L)-_xlfn.XLOOKUP(" + Foreign Exch (Gain) Loss",'[2]Income - GAAP'!$A:$A,'[2]Income - GAAP'!L:L)-_xlfn.XLOOKUP(" + (Income) Loss from Affiliates",'[2]Income - GAAP'!$A:$A,'[2]Income - GAAP'!L:L) -> 9.4 | J10: =-_xlfn.XLOOKUP(" + Other Non-Op (Income) Loss",'[2]Income - GAAP'!$A:$A,'[2]Income - GAAP'!M:M)-_xlfn.XLOOKUP(" + Foreign Exch (Gain) Loss",'[2]Income - GAAP'!$A:$A,'[2]Income - GAAP'!M:M)-_xlfn.XLOOKUP(" + (Income) Loss from Affiliates",'[2]Income - GAAP'!$A:$A,'[2]Income - GAAP'!M:M) -> -2.6 | K10: =-_xlfn.XLOOKUP(" + Other Non-Op (Income) Loss",'[2]Income - GAAP'!$A:$A,'[2]Income - GAAP'!N:N)-_xlfn.XLOOKUP(" + Foreign Exch (Gain) Loss",'[2]Income - GAAP'!$A:$A,'[2]Income - GAAP'!N:N)-_xlfn.XLOOKUP(" + (Income) Loss from Affiliates",'[2]Income - GAAP'!$A:$A,'[2]Income - GAAP'!N:N) -> -11.3 | L10: =-_xlfn.XLOOKUP(" + Other Non-Op (Income) Loss",'[2]Income - GAAP'!$A:$A,'[2]Income - GAAP'!O:O)-_xlfn.XLOOKUP(" + Foreign Exch (Gain) Loss",'[2]Income - GAAP'!$A:$A,'[2]Income - GAAP'!O:O)-_xlfn.XLOOKUP(" + (Income) Loss from Affiliates",'[2]Income - GAAP'!$A:$A,'[2]Income - GAAP'!O:O) -> -2.2 | M10: =-_xlfn.XLOOKUP(" + Other Non-Op (Income) Loss",'[2]Income - GAAP'!$A:$A,'[2]Income - GAAP'!P:P)-_xlfn.XLOOKUP(" + Foreign Exch (Gain) Loss",'[2]Income - GAAP'!$A:$A,'[2]Income - GAAP'!P:P)-_xlfn.XLOOKUP(" + (Income) Loss from Affiliates",'[2]Income - GAAP'!$A:$A,'[2]Income - GAAP'!P:P) -> -0.3 | N10: =-_xlfn.XLOOKUP(" + Other Non-Op (Income) Loss",'[2]Income - GAAP'!$A:$A,'[2]Income - GAAP'!Q:Q)-_xlfn.XLOOKUP(" + Foreign Exch (Gain) Loss",'[2]Income - GAAP'!$A:$A,'[2]Income - GAAP'!Q:Q)-_xlfn.XLOOKUP(" + (Income) Loss from Affiliates",'[2]Income - GAAP'!$A:$A,'[2]Income - GAAP'!Q:Q) -> 4.782
A11: Depreciación y amortización | B11: =-_xlfn.XLOOKUP(" + Depreciation & Amortization",'[2]Cash Flow - Standardized'!$A:$A,'[2]Cash Flow - Standardized'!C:C) -> -561 | C11: =-_xlfn.XLOOKUP(" + Depreciation & Amortization",'[2]Cash Flow - Standardized'!$A:$A,'[2]Cash Flow - Standardized'!D:D) -> -569.5 | D11: =-_xlfn.XLOOKUP(" + Depreciation & Amortization",'[2]Cash Flow - Standardized'!$A:$A,'[2]Cash Flow - Standardized'!E:E) -> -596.8 | E11: =-_xlfn.XLOOKUP(" + Depreciation & Amortization",'[2]Cash Flow - Standardized'!$A:$A,'[2]Cash Flow - Standardized'!F:F) -> -574.6 | F11: =-_xlfn.XLOOKUP(" + Depreciation & Amortization",'[2]Cash Flow - Standardized'!$A:$A,'[2]Cash Flow - Standardized'!G:G) -> -604.5 | G11: =-_xlfn.XLOOKUP(" + Depreciation & Amortization",'[2]Cash Flow - Standardized'!$A:$A,'[2]Cash Flow - Standardized'!H:H) -> -396 | H11: =-_xlfn.XLOOKUP(" + Depreciation & Amortization",'[2]Cash Flow - Standardized'!$A:$A,'[2]Cash Flow - Standardized'!I:I) -> -237.7 | I11: =-_xlfn.XLOOKUP(" + Depreciation & Amortization",'[2]Cash Flow - Standardized'!$A:$A,'[2]Cash Flow - Standardized'!J:J) -> -217.7 | J11: =-_xlfn.XLOOKUP(" + Depreciation & Amortization",'[2]Cash Flow - Standardized'!$A:$A,'[2]Cash Flow - Standardized'!K:K) -> -206.4 | K11: =-_xlfn.XLOOKUP(" + Depreciation & Amortization",'[2]Cash Flow - Standardized'!$A:$A,'[2]Cash Flow - Standardized'!L:L) -> -211.4 | L11: =-_xlfn.XLOOKUP(" + Depreciation & Amortization",'[2]Cash Flow - Standardized'!$A:$A,'[2]Cash Flow - Standardized'!M:M) -> -176.3 | M11: =-_xlfn.XLOOKUP(" + Depreciation & Amortization",'[2]Cash Flow - Standardized'!$A:$A,'[2]Cash Flow - Standardized'!N:N) -> -141.3 | N11: =-_xlfn.XLOOKUP(" + Depreciation & Amortization",'[2]Cash Flow - Standardized'!$A:$A,'[2]Cash Flow - Standardized'!O:O) -> -132.1
A12: Capital de Trabajo | B12: =_xlfn.XLOOKUP(" + Chg in Non-Cash Work Cap",'[2]Cash Flow - Standardized'!$A:$A,'[2]Cash Flow - Standardized'!C:C)+_xlfn.XLOOKUP(" + Deferred Income Taxes",'[2]Cash Flow - Standardized'!$A:$A,'[2]Cash Flow - Standardized'!C:C)+_xlfn.XLOOKUP(" + Other Non-Cash Adj",'[2]Cash Flow - Standardized'!$A:$A,'[2]Cash Flow - Standardized'!C:C)-DCFF!G10 -> -286.3 | C12: =_xlfn.XLOOKUP(" + Chg in Non-Cash Work Cap",'[2]Cash Flow - Standardized'!$A:$A,'[2]Cash Flow - Standardized'!D:D)+_xlfn.XLOOKUP(" + Deferred Income Taxes",'[2]Cash Flow - Standardized'!$A:$A,'[2]Cash Flow - Standardized'!D:D)+_xlfn.XLOOKUP(" + Other Non-Cash Adj",'[2]Cash Flow - Standardized'!$A:$A,'[2]Cash Flow - Standardized'!D:D) -> -239.5 | D12: =_xlfn.XLOOKUP(" + Chg in Non-Cash Work Cap",'[2]Cash Flow - Standardized'!$A:$A,'[2]Cash Flow - Standardized'!E:E)+_xlfn.XLOOKUP(" + Deferred Income Taxes",'[2]Cash Flow - Standardized'!$A:$A,'[2]Cash Flow - Standardized'!E:E)+_xlfn.XLOOKUP(" + Other Non-Cash Adj",'[2]Cash Flow - Standardized'!$A:$A,'[2]Cash Flow - Standardized'!E:E) -> -169.8 | E12: =_xlfn.XLOOKUP(" + Chg in Non-Cash Work Cap",'[2]Cash Flow - Standardized'!$A:$A,'[2]Cash Flow - Standardized'!F:F)+_xlfn.XLOOKUP(" + Deferred Income Taxes",'[2]Cash Flow - Standardized'!$A:$A,'[2]Cash Flow - Standardized'!F:F)+_xlfn.XLOOKUP(" + Other Non-Cash Adj",'[2]Cash Flow - Standardized'!$A:$A,'[2]Cash Flow - Standardized'!F:F) -> 93.2 | F12: =_xlfn.XLOOKUP(" + Chg in Non-Cash Work Cap",'[2]Cash Flow - Standardized'!$A:$A,'[2]Cash Flow - Standardized'!G:G)+_xlfn.XLOOKUP(" + Deferred Income Taxes",'[2]Cash Flow - Standardized'!$A:$A,'[2]Cash Flow - Standardized'!G:G)+_xlfn.XLOOKUP(" + Other Non-Cash Adj",'[2]Cash Flow - Standardized'!$A:$A,'[2]Cash Flow - Standardized'!G:G) -> -32.5 | G12: =_xlfn.XLOOKUP(" + Chg in Non-Cash Work Cap",'[2]Cash Flow - Standardized'!$A:$A,'[2]Cash Flow - Standardized'!H:H)+_xlfn.XLOOKUP(" + Deferred Income Taxes",'[2]Cash Flow - Standardized'!$A:$A,'[2]Cash Flow - Standardized'!H:H)+_xlfn.XLOOKUP(" + Other Non-Cash Adj",'[2]Cash Flow - Standardized'!$A:$A,'[2]Cash Flow - Standardized'!H:H) -> 58.3 | H12: =_xlfn.XLOOKUP(" + Chg in Non-Cash Work Cap",'[2]Cash Flow - Standardized'!$A:$A,'[2]Cash Flow - Standardized'!I:I)+_xlfn.XLOOKUP(" + Deferred Income Taxes",'[2]Cash Flow - Standardized'!$A:$A,'[2]Cash Flow - Standardized'!I:I)+_xlfn.XLOOKUP(" + Other Non-Cash Adj",'[2]Cash Flow - Standardized'!$A:$A,'[2]Cash Flow - Standardized'!I:I) -> 8.1 | I12: =_xlfn.XLOOKUP(" + Chg in Non-Cash Work Cap",'[2]Cash Flow - Standardized'!$A:$A,'[2]Cash Flow - Standardized'!J:J)+_xlfn.XLOOKUP(" + Deferred Income Taxes",'[2]Cash Flow - Standardized'!$A:$A,'[2]Cash Flow - Standardized'!J:J)+_xlfn.XLOOKUP(" + Other Non-Cash Adj",'[2]Cash Flow - Standardized'!$A:$A,'[2]Cash Flow - Standardized'!J:J) -> -84.6 | J12: =_xlfn.XLOOKUP(" + Chg in Non-Cash Work Cap",'[2]Cash Flow - Standardized'!$A:$A,'[2]Cash Flow - Standardized'!K:K)+_xlfn.XLOOKUP(" + Deferred Income Taxes",'[2]Cash Flow - Standardized'!$A:$A,'[2]Cash Flow - Standardized'!K:K)+_xlfn.XLOOKUP(" + Other Non-Cash Adj",'[2]Cash Flow - Standardized'!$A:$A,'[2]Cash Flow - Standardized'!K:K) -> -103.7 | K12: =_xlfn.XLOOKUP(" + Chg in Non-Cash Work Cap",'[2]Cash Flow - Standardized'!$A:$A,'[2]Cash Flow - Standardized'!L:L)+_xlfn.XLOOKUP(" + Deferred Income Taxes",'[2]Cash Flow - Standardized'!$A:$A,'[2]Cash Flow - Standardized'!L:L)+_xlfn.XLOOKUP(" + Other Non-Cash Adj",'[2]Cash Flow - Standardized'!$A:$A,'[2]Cash Flow - Standardized'!L:L) -> -20.5 | L12: =_xlfn.XLOOKUP(" + Chg in Non-Cash Work Cap",'[2]Cash Flow - Standardized'!$A:$A,'[2]Cash Flow - Standardized'!M:M)+_xlfn.XLOOKUP(" + Deferred Income Taxes",'[2]Cash Flow - Standardized'!$A:$A,'[2]Cash Flow - Standardized'!M:M)+_xlfn.XLOOKUP(" + Other Non-Cash Adj",'[2]Cash Flow - Standardized'!$A:$A,'[2]Cash Flow - Standardized'!M:M) -> 2 | M12: =_xlfn.XLOOKUP(" + Chg in Non-Cash Work Cap",'[2]Cash Flow - Standardized'!$A:$A,'[2]Cash Flow - Standardized'!N:N)+_xlfn.XLOOKUP(" + Deferred Income Taxes",'[2]Cash Flow - Standardized'!$A:$A,'[2]Cash Flow - Standardized'!N:N)+_xlfn.XLOOKUP(" + Other Non-Cash Adj",'[2]Cash Flow - Standardized'!$A:$A,'[2]Cash Flow - Standardized'!N:N) -> -20.8 | N12: =_xlfn.XLOOKUP(" + Chg in Non-Cash Work Cap",'[2]Cash Flow - Standardized'!$A:$A,'[2]Cash Flow - Standardized'!O:O)+_xlfn.XLOOKUP(" + Deferred Income Taxes",'[2]Cash Flow - Standardized'!$A:$A,'[2]Cash Flow - Standardized'!O:O)+_xlfn.XLOOKUP(" + Other Non-Cash Adj",'[2]Cash Flow - Standardized'!$A:$A,'[2]Cash Flow - Standardized'!O:O) -> 74.3
A13: Capex | B13: =_xlfn.XLOOKUP(" + Change in Fixed & Intang",'[2]Cash Flow - Standardized'!$A:$A,'[2]Cash Flow - Standardized'!C:C) -> -193.4 | C13: =_xlfn.XLOOKUP(" + Change in Fixed & Intang",'[2]Cash Flow - Standardized'!$A:$A,'[2]Cash Flow - Standardized'!D:D) -> -145.3 | D13: =_xlfn.XLOOKUP(" + Change in Fixed & Intang",'[2]Cash Flow - Standardized'!$A:$A,'[2]Cash Flow - Standardized'!E:E) -> -132.3 | E13: =_xlfn.XLOOKUP(" + Change in Fixed & Intang",'[2]Cash Flow - Standardized'!$A:$A,'[2]Cash Flow - Standardized'!F:F) -> -103.7 | F13: =_xlfn.XLOOKUP(" + Change in Fixed & Intang",'[2]Cash Flow - Standardized'!$A:$A,'[2]Cash Flow - Standardized'!G:G) -> -127 | G13: =_xlfn.XLOOKUP(" + Change in Fixed & Intang",'[2]Cash Flow - Standardized'!$A:$A,'[2]Cash Flow - Standardized'!H:H) -> -98.3 | H13: =_xlfn.XLOOKUP(" + Change in Fixed & Intang",'[2]Cash Flow - Standardized'!$A:$A,'[2]Cash Flow - Standardized'!I:I) -> -72.4 | I13: =_xlfn.XLOOKUP(" + Change in Fixed & Intang",'[2]Cash Flow - Standardized'!$A:$A,'[2]Cash Flow - Standardized'!J:J) -> -84.5 | J13: =_xlfn.XLOOKUP(" + Change in Fixed & Intang",'[2]Cash Flow - Standardized'!$A:$A,'[2]Cash Flow - Standardized'!K:K) -> -56.7 | K13: =_xlfn.XLOOKUP(" + Change in Fixed & Intang",'[2]Cash Flow - Standardized'!$A:$A,'[2]Cash Flow - Standardized'!L:L) -> -43.6 | L13: =_xlfn.XLOOKUP(" + Change in Fixed & Intang",'[2]Cash Flow - Standardized'!$A:$A,'[2]Cash Flow - Standardized'!M:M) -> -45.4 | M13: =_xlfn.XLOOKUP(" + Change in Fixed & Intang",'[2]Cash Flow - Standardized'!$A:$A,'[2]Cash Flow - Standardized'!N:N) -> -42.4 | N13: =_xlfn.XLOOKUP(" + Change in Fixed & Intang",'[2]Cash Flow - Standardized'!$A:$A,'[2]Cash Flow - Standardized'!O:O) -> -40.6
A14: Inversiones | B14: =_xlfn.XLOOKUP(" + Net Cash From Acq & Div",'[2]Cash Flow - Standardized'!$A:$A,'[2]Cash Flow - Standardized'!C:C)+_xlfn.XLOOKUP(" + Other Investing Activities",'[2]Cash Flow - Standardized'!$A:$A,'[2]Cash Flow - Standardized'!C:C) -> 1.6 | C14: =_xlfn.XLOOKUP(" + Net Cash From Acq & Div",'[2]Cash Flow - Standardized'!$A:$A,'[2]Cash Flow - Standardized'!D:D)+_xlfn.XLOOKUP(" + Other Investing Activities",'[2]Cash Flow - Standardized'!$A:$A,'[2]Cash Flow - Standardized'!D:D) -> -16.4 | D14: =_xlfn.XLOOKUP(" + Net Cash From Acq & Div",'[2]Cash Flow - Standardized'!$A:$A,'[2]Cash Flow - Standardized'!E:E)+_xlfn.XLOOKUP(" + Other Investing Activities",'[2]Cash Flow - Standardized'!$A:$A,'[2]Cash Flow - Standardized'!E:E) -> -81.6 | E14: =_xlfn.XLOOKUP(" + Net Cash From Acq & Div",'[2]Cash Flow - Standardized'!$A:$A,'[2]Cash Flow - Standardized'!F:F)+_xlfn.XLOOKUP(" + Other Investing Activities",'[2]Cash Flow - Standardized'!$A:$A,'[2]Cash Flow - Standardized'!F:F) -> -56.7 | F14: =_xlfn.XLOOKUP(" + Net Cash From Acq & Div",'[2]Cash Flow - Standardized'!$A:$A,'[2]Cash Flow - Standardized'!G:G)+_xlfn.XLOOKUP(" + Other Investing Activities",'[2]Cash Flow - Standardized'!$A:$A,'[2]Cash Flow - Standardized'!G:G) -> -81 | G14: =_xlfn.XLOOKUP(" + Net Cash From Acq & Div",'[2]Cash Flow - Standardized'!$A:$A,'[2]Cash Flow - Standardized'!H:H)+_xlfn.XLOOKUP(" + Other Investing Activities",'[2]Cash Flow - Standardized'!$A:$A,'[2]Cash Flow - Standardized'!H:H) -> -5236.5 | H14: =_xlfn.XLOOKUP(" + Net Cash From Acq & Div",'[2]Cash Flow - Standardized'!$A:$A,'[2]Cash Flow - Standardized'!I:I)+_xlfn.XLOOKUP(" + Other Investing Activities",'[2]Cash Flow - Standardized'!$A:$A,'[2]Cash Flow - Standardized'!I:I) -> -250.8 | I14: =_xlfn.XLOOKUP(" + Net Cash From Acq & Div",'[2]Cash Flow - Standardized'!$A:$A,'[2]Cash Flow - Standardized'!J:J)+_xlfn.XLOOKUP(" + Other Investing Activities",'[2]Cash Flow - Standardized'!$A:$A,'[2]Cash Flow - Standardized'!J:J) -> -282.9 | J14: =_xlfn.XLOOKUP(" + Net Cash From Acq & Div",'[2]Cash Flow - Standardized'!$A:$A,'[2]Cash Flow - Standardized'!K:K)+_xlfn.XLOOKUP(" + Other Investing Activities",'[2]Cash Flow - Standardized'!$A:$A,'[2]Cash Flow - Standardized'!K:K) -> -242.3 | K14: =_xlfn.XLOOKUP(" + Net Cash From Acq & Div",'[2]Cash Flow - Standardized'!$A:$A,'[2]Cash Flow - Standardized'!L:L)+_xlfn.XLOOKUP(" + Other Investing Activities",'[2]Cash Flow - Standardized'!$A:$A,'[2]Cash Flow - Standardized'!L:L) -> -16.9 | L14: =_xlfn.XLOOKUP(" + Net Cash From Acq & Div",'[2]Cash Flow - Standardized'!$A:$A,'[2]Cash Flow - Standardized'!M:M)+_xlfn.XLOOKUP(" + Other Investing Activities",'[2]Cash Flow - Standardized'!$A:$A,'[2]Cash Flow - Standardized'!M:M) -> -955.5 | M14: =_xlfn.XLOOKUP(" + Net Cash From Acq & Div",'[2]Cash Flow - Standardized'!$A:$A,'[2]Cash Flow - Standardized'!N:N)+_xlfn.XLOOKUP(" + Other Investing Activities",'[2]Cash Flow - Standardized'!$A:$A,'[2]Cash Flow - Standardized'!N:N) -> -126.2 | N14: =_xlfn.XLOOKUP(" + Net Cash From Acq & Div",'[2]Cash Flow - Standardized'!$A:$A,'[2]Cash Flow - Standardized'!O:O)+_xlfn.XLOOKUP(" + Other Investing Activities",'[2]Cash Flow - Standardized'!$A:$A,'[2]Cash Flow - Standardized'!O:O) -> -178.2
A15: I.S.R Y P.T.U. | B15: =-_xlfn.XLOOKUP(" - Income Tax Expense (Benefit)",'[2]Income - GAAP'!$A:$A,'[2]Income - GAAP'!E:E) -> -279.9 | C15: =-_xlfn.XLOOKUP(" - Income Tax Expense (Benefit)",'[2]Income - GAAP'!$A:$A,'[2]Income - GAAP'!F:F) -> -250.7 | D15: =-_xlfn.XLOOKUP(" - Income Tax Expense (Benefit)",'[2]Income - GAAP'!$A:$A,'[2]Income - GAAP'!G:G) -> -375.4 | E15: =-_xlfn.XLOOKUP(" - Income Tax Expense (Benefit)",'[2]Income - GAAP'!$A:$A,'[2]Income - GAAP'!H:H) -> -230.4 | F15: =-_xlfn.XLOOKUP(" - Income Tax Expense (Benefit)",'[2]Income - GAAP'!$A:$A,'[2]Income - GAAP'!I:I) -> -160.8 | G15: =-_xlfn.XLOOKUP(" - Income Tax Expense (Benefit)",'[2]Income - GAAP'!$A:$A,'[2]Income - GAAP'!J:J) -> -209.6 | H15: =-_xlfn.XLOOKUP(" - Income Tax Expense (Benefit)",'[2]Income - GAAP'!$A:$A,'[2]Income - GAAP'!K:K) -> -220.4 | I15: =-_xlfn.XLOOKUP(" - Income Tax Expense (Benefit)",'[2]Income - GAAP'!$A:$A,'[2]Income - GAAP'!L:L) -> -231.3 | J15: =-_xlfn.XLOOKUP(" - Income Tax Expense (Benefit)",'[2]Income - GAAP'!$A:$A,'[2]Income - GAAP'!M:M) -> -209.3 | K15: =-_xlfn.XLOOKUP(" - Income Tax Expense (Benefit)",'[2]Income - GAAP'!$A:$A,'[2]Income - GAAP'!N:N) -> -227.1 | L15: =-_xlfn.XLOOKUP(" - Income Tax Expense (Benefit)",'[2]Income - GAAP'!$A:$A,'[2]Income - GAAP'!O:O) -> -153.3 | M15: =-_xlfn.XLOOKUP(" - Income Tax Expense (Benefit)",'[2]Income - GAAP'!$A:$A,'[2]Income - GAAP'!P:P) -> -165.8 | N15: =-_xlfn.XLOOKUP(" - Income Tax Expense (Benefit)",'[2]Income - GAAP'!$A:$A,'[2]Income - GAAP'!Q:Q) -> -180.225
A16: Utilidad Neta | B16: =_xlfn.XLOOKUP("Income (Loss) Incl. MI",'[2]Income - GAAP'!$A:$A,'[2]Income - GAAP'!E:E) -> 1198.1 | C16: =_xlfn.XLOOKUP("Income (Loss) Incl. MI",'[2]Income - GAAP'!$A:$A,'[2]Income - GAAP'!F:F) -> 1050.2 | D16: =_xlfn.XLOOKUP("Income (Loss) Incl. MI",'[2]Income - GAAP'!$A:$A,'[2]Income - GAAP'!G:G) -> 930.2 | E16: =_xlfn.XLOOKUP("Income (Loss) Incl. MI",'[2]Income - GAAP'!$A:$A,'[2]Income - GAAP'!H:H) -> 773.9 | F16: =_xlfn.XLOOKUP("Income (Loss) Incl. MI",'[2]Income - GAAP'!$A:$A,'[2]Income - GAAP'!I:I) -> 485.5 | G16: =_xlfn.XLOOKUP("Income (Loss) Incl. MI",'[2]Income - GAAP'!$A:$A,'[2]Income - GAAP'!J:J) -> 606.3 | H16: =_xlfn.XLOOKUP("Income (Loss) Incl. MI",'[2]Income - GAAP'!$A:$A,'[2]Income - GAAP'!K:K) -> 563.4 | I16: =_xlfn.XLOOKUP("Income (Loss) Incl. MI",'[2]Income - GAAP'!$A:$A,'[2]Income - GAAP'!L:L) -> 520.1 | J16: =_xlfn.XLOOKUP("Income (Loss) Incl. MI",'[2]Income - GAAP'!$A:$A,'[2]Income - GAAP'!M:M) -> 452.2 | K16: =_xlfn.XLOOKUP("Income (Loss) Incl. MI",'[2]Income - GAAP'!$A:$A,'[2]Income - GAAP'!N:N) -> 406 | L16: =_xlfn.XLOOKUP("Income (Loss) Incl. MI",'[2]Income - GAAP'!$A:$A,'[2]Income - GAAP'!O:O) -> 292.5 | M16: =_xlfn.XLOOKUP("Income (Loss) Incl. MI",'[2]Income - GAAP'!$A:$A,'[2]Income - GAAP'!P:P) -> 355.2 | N16: =_xlfn.XLOOKUP("Income (Loss) Incl. MI",'[2]Income - GAAP'!$A:$A,'[2]Income - GAAP'!Q:Q) -> 338.829
A17: Dividendos | B17: =_xlfn.XLOOKUP(" + Dividends Paid",'[2]Cash Flow - Standardized'!$A:$A,'[2]Cash Flow - Standardized'!C:C) -> -302.7 | C17: =_xlfn.XLOOKUP(" + Dividends Paid",'[2]Cash Flow - Standardized'!$A:$A,'[2]Cash Flow - Standardized'!D:D) -> -276.2 | D17: =_xlfn.XLOOKUP(" + Dividends Paid",'[2]Cash Flow - Standardized'!$A:$A,'[2]Cash Flow - Standardized'!E:E) -> -223.5 | E17: =_xlfn.XLOOKUP(" + Dividends Paid",'[2]Cash Flow - Standardized'!$A:$A,'[2]Cash Flow - Standardized'!F:F) -> -147.1 | F17: =_xlfn.XLOOKUP(" + Dividends Paid",'[2]Cash Flow - Standardized'!$A:$A,'[2]Cash Flow - Standardized'!G:G) -> -182.5 | G17: =_xlfn.XLOOKUP(" + Dividends Paid",'[2]Cash Flow - Standardized'!$A:$A,'[2]Cash Flow - Standardized'!H:H) -> -168.8 | H17: =_xlfn.XLOOKUP(" + Dividends Paid",'[2]Cash Flow - Standardized'!$A:$A,'[2]Cash Flow - Standardized'!I:I) -> -38 | I17: =_xlfn.XLOOKUP(" + Dividends Paid",'[2]Cash Flow - Standardized'!$A:$A,'[2]Cash Flow - Standardized'!J:J) -> -51.3 | J17: =_xlfn.XLOOKUP(" + Dividends Paid",'[2]Cash Flow - Standardized'!$A:$A,'[2]Cash Flow - Standardized'!K:K) -> -101.9 | K17: =_xlfn.XLOOKUP(" + Dividends Paid",'[2]Cash Flow - Standardized'!$A:$A,'[2]Cash Flow - Standardized'!L:L) -> -98.4 | L17: =_xlfn.XLOOKUP(" + Dividends Paid",'[2]Cash Flow - Standardized'!$A:$A,'[2]Cash Flow - Standardized'!M:M) -> -35.8 | M17: =_xlfn.XLOOKUP(" + Dividends Paid",'[2]Cash Flow - Standardized'!$A:$A,'[2]Cash Flow - Standardized'!N:N) -> -34.8 | N17: =_xlfn.XLOOKUP(" + Dividends Paid",'[2]Cash Flow - Standardized'!$A:$A,'[2]Cash Flow - Standardized'!O:O) -> -87.8
A18: Compra de Acciones | B18: =_xlfn.XLOOKUP(" + Cash (Repurchase) of Equity",'[2]Cash Flow - Standardized'!$A:$A,'[2]Cash Flow - Standardized'!C:C) -> -325.6 | C18: =_xlfn.XLOOKUP(" + Cash (Repurchase) of Equity",'[2]Cash Flow - Standardized'!$A:$A,'[2]Cash Flow - Standardized'!D:D) -> -162.3 | D18: =_xlfn.XLOOKUP(" + Cash (Repurchase) of Equity",'[2]Cash Flow - Standardized'!$A:$A,'[2]Cash Flow - Standardized'!E:E) -> -379 | E18: =_xlfn.XLOOKUP(" + Cash (Repurchase) of Equity",'[2]Cash Flow - Standardized'!$A:$A,'[2]Cash Flow - Standardized'!F:F) -> -127.2 | F18: =_xlfn.XLOOKUP(" + Cash (Repurchase) of Equity",'[2]Cash Flow - Standardized'!$A:$A,'[2]Cash Flow - Standardized'!G:G) -> -78.5 | G18: =_xlfn.XLOOKUP(" + Cash (Repurchase) of Equity",'[2]Cash Flow - Standardized'!$A:$A,'[2]Cash Flow - Standardized'!H:H) -> -43.4 | H18: =_xlfn.XLOOKUP(" + Cash (Repurchase) of Equity",'[2]Cash Flow - Standardized'!$A:$A,'[2]Cash Flow - Standardized'!I:I) -> -136.4 | I18: =_xlfn.XLOOKUP(" + Cash (Repurchase) of Equity",'[2]Cash Flow - Standardized'!$A:$A,'[2]Cash Flow - Standardized'!J:J) -> -70.6 | J18: =_xlfn.XLOOKUP(" + Cash (Repurchase) of Equity",'[2]Cash Flow - Standardized'!$A:$A,'[2]Cash Flow - Standardized'!K:K) -> -100.4 | K18: =_xlfn.XLOOKUP(" + Cash (Repurchase) of Equity",'[2]Cash Flow - Standardized'!$A:$A,'[2]Cash Flow - Standardized'!L:L) -> 7.6 | L18: =_xlfn.XLOOKUP(" + Cash (Repurchase) of Equity",'[2]Cash Flow - Standardized'!$A:$A,'[2]Cash Flow - Standardized'!M:M) -> -113.8 | M18: =_xlfn.XLOOKUP(" + Cash (Repurchase) of Equity",'[2]Cash Flow - Standardized'!$A:$A,'[2]Cash Flow - Standardized'!N:N) -> -16.7 | N18: =_xlfn.XLOOKUP(" + Cash (Repurchase) of Equity",'[2]Cash Flow - Standardized'!$A:$A,'[2]Cash Flow - Standardized'!O:O) -> 23.6
A20: POSICIÓN FINANCIERA
A21: Activo
A22: Caja | B22: =+_xlfn.XLOOKUP(" + Cash, Cash Equivalents & STI",'[2]Bal Sheet - Standardized'!$A:$A,'[2]Bal Sheet - Standardized'!C:C) -> 3952.6 | C22: =+_xlfn.XLOOKUP(" + Cash, Cash Equivalents & STI",'[2]Bal Sheet - Standardized'!$A:$A,'[2]Bal Sheet - Standardized'!D:D) -> 3568.3 | D22: =+_xlfn.XLOOKUP(" + Cash, Cash Equivalents & STI",'[2]Bal Sheet - Standardized'!$A:$A,'[2]Bal Sheet - Standardized'!E:E) -> 2769 | E22: =+_xlfn.XLOOKUP(" + Cash, Cash Equivalents & STI",'[2]Bal Sheet - Standardized'!$A:$A,'[2]Bal Sheet - Standardized'!F:F) -> 2979.5 | F22: =+_xlfn.XLOOKUP(" + Cash, Cash Equivalents & STI",'[2]Bal Sheet - Standardized'!$A:$A,'[2]Bal Sheet - Standardized'!G:G) -> 2148.8 | G22: =+_xlfn.XLOOKUP(" + Cash, Cash Equivalents & STI",'[2]Bal Sheet - Standardized'!$A:$A,'[2]Bal Sheet - Standardized'!H:H) -> 1944.9 | H22: =+_xlfn.XLOOKUP(" + Cash, Cash Equivalents & STI",'[2]Bal Sheet - Standardized'!$A:$A,'[2]Bal Sheet - Standardized'!I:I) -> 2809.9 | I22: =+_xlfn.XLOOKUP(" + Cash, Cash Equivalents & STI",'[2]Bal Sheet - Standardized'!$A:$A,'[2]Bal Sheet - Standardized'!J:J) -> 2460.7 | J22: =+_xlfn.XLOOKUP(" + Cash, Cash Equivalents & STI",'[2]Bal Sheet - Standardized'!$A:$A,'[2]Bal Sheet - Standardized'!K:K) -> 2492.8 | K22: =+_xlfn.XLOOKUP(" + Cash, Cash Equivalents & STI",'[2]Bal Sheet - Standardized'!$A:$A,'[2]Bal Sheet - Standardized'!L:L) -> 2351.3 | L22: =+_xlfn.XLOOKUP(" + Cash, Cash Equivalents & STI",'[2]Bal Sheet - Standardized'!$A:$A,'[2]Bal Sheet - Standardized'!M:M) -> 1175.5 | M22: =+_xlfn.XLOOKUP(" + Cash, Cash Equivalents & STI",'[2]Bal Sheet - Standardized'!$A:$A,'[2]Bal Sheet - Standardized'!N:N) -> 1803.6 | N22: =+_xlfn.XLOOKUP(" + Cash, Cash Equivalents & STI",'[2]Bal Sheet - Standardized'!$A:$A,'[2]Bal Sheet - Standardized'!O:O) -> 1319.1
A23: Cuentas y documentos por cobrar | B23: =+_xlfn.XLOOKUP(" + Accounts & Notes Receiv",'[2]Bal Sheet - Standardized'!$A:$A,'[2]Bal Sheet - Standardized'!C:C)+_xlfn.XLOOKUP(" + Unbilled Revenues",'[2]Bal Sheet - Standardized'!$A:$A,'[2]Bal Sheet - Standardized'!C:C) -> 2151 | C23: =+_xlfn.XLOOKUP(" + Accounts & Notes Receiv",'[2]Bal Sheet - Standardized'!$A:$A,'[2]Bal Sheet - Standardized'!D:D)+_xlfn.XLOOKUP(" + Unbilled Revenues",'[2]Bal Sheet - Standardized'!$A:$A,'[2]Bal Sheet - Standardized'!D:D) -> 1734.7 | D23: =+_xlfn.XLOOKUP(" + Accounts & Notes Receiv",'[2]Bal Sheet - Standardized'!$A:$A,'[2]Bal Sheet - Standardized'!E:E)+_xlfn.XLOOKUP(" + Unbilled Revenues",'[2]Bal Sheet - Standardized'!$A:$A,'[2]Bal Sheet - Standardized'!E:E) -> 1681.9 | E23: =+_xlfn.XLOOKUP(" + Accounts & Notes Receiv",'[2]Bal Sheet - Standardized'!$A:$A,'[2]Bal Sheet - Standardized'!F:F)+_xlfn.XLOOKUP(" + Unbilled Revenues",'[2]Bal Sheet - Standardized'!$A:$A,'[2]Bal Sheet - Standardized'!F:F) -> 1379 | F23: =+_xlfn.XLOOKUP(" + Accounts & Notes Receiv",'[2]Bal Sheet - Standardized'!$A:$A,'[2]Bal Sheet - Standardized'!G:G)+_xlfn.XLOOKUP(" + Unbilled Revenues",'[2]Bal Sheet - Standardized'!$A:$A,'[2]Bal Sheet - Standardized'!G:G) -> 1256.1 | G23: =+_xlfn.XLOOKUP(" + Accounts & Notes Receiv",'[2]Bal Sheet - Standardized'!$A:$A,'[2]Bal Sheet - Standardized'!H:H)+_xlfn.XLOOKUP(" + Unbilled Revenues",'[2]Bal Sheet - Standardized'!$A:$A,'[2]Bal Sheet - Standardized'!H:H) -> 1346.1 | H23: =+_xlfn.XLOOKUP(" + Accounts & Notes Receiv",'[2]Bal Sheet - Standardized'!$A:$A,'[2]Bal Sheet - Standardized'!I:I)+_xlfn.XLOOKUP(" + Unbilled Revenues",'[2]Bal Sheet - Standardized'!$A:$A,'[2]Bal Sheet - Standardized'!I:I) -> 1070.6 | I23: =+_xlfn.XLOOKUP(" + Accounts & Notes Receiv",'[2]Bal Sheet - Standardized'!$A:$A,'[2]Bal Sheet - Standardized'!J:J)+_xlfn.XLOOKUP(" + Unbilled Revenues",'[2]Bal Sheet - Standardized'!$A:$A,'[2]Bal Sheet - Standardized'!J:J) -> 895.9 | J23: =+_xlfn.XLOOKUP(" + Accounts & Notes Receiv",'[2]Bal Sheet - Standardized'!$A:$A,'[2]Bal Sheet - Standardized'!K:K)+_xlfn.XLOOKUP(" + Unbilled Revenues",'[2]Bal Sheet - Standardized'!$A:$A,'[2]Bal Sheet - Standardized'!K:K) -> 820.4 | K23: =+_xlfn.XLOOKUP(" + Accounts & Notes Receiv",'[2]Bal Sheet - Standardized'!$A:$A,'[2]Bal Sheet - Standardized'!L:L)+_xlfn.XLOOKUP(" + Unbilled Revenues",'[2]Bal Sheet - Standardized'!$A:$A,'[2]Bal Sheet - Standardized'!L:L) -> 739.1 | L23: =+_xlfn.XLOOKUP(" + Accounts & Notes Receiv",'[2]Bal Sheet - Standardized'!$A:$A,'[2]Bal Sheet - Standardized'!M:M)+_xlfn.XLOOKUP(" + Unbilled Revenues",'[2]Bal Sheet - Standardized'!$A:$A,'[2]Bal Sheet - Standardized'!M:M) -> 627.7 | M23: =+_xlfn.XLOOKUP(" + Accounts & Notes Receiv",'[2]Bal Sheet - Standardized'!$A:$A,'[2]Bal Sheet - Standardized'!N:N)+_xlfn.XLOOKUP(" + Unbilled Revenues",'[2]Bal Sheet - Standardized'!$A:$A,'[2]Bal Sheet - Standardized'!N:N) -> 472.6 | N23: =+_xlfn.XLOOKUP(" + Accounts & Notes Receiv",'[2]Bal Sheet - Standardized'!$A:$A,'[2]Bal Sheet - Standardized'!O:O)+_xlfn.XLOOKUP(" + Unbilled Revenues",'[2]Bal Sheet - Standardized'!$A:$A,'[2]Bal Sheet - Standardized'!O:O) -> 457.8
A24: Inventarios | B24: =+_xlfn.XLOOKUP(" + Inventories",'[2]Bal Sheet - Standardized'!$A:$A,'[2]Bal Sheet - Standardized'!C:C) -> 0 | C24: =+_xlfn.XLOOKUP(" + Inventories",'[2]Bal Sheet - Standardized'!$A:$A,'[2]Bal Sheet - Standardized'!D:D) -> 0 | D24: =+_xlfn.XLOOKUP(" + Inventories",'[2]Bal Sheet - Standardized'!$A:$A,'[2]Bal Sheet - Standardized'!E:E) -> 0 | E24: =+_xlfn.XLOOKUP(" + Inventories",'[2]Bal Sheet - Standardized'!$A:$A,'[2]Bal Sheet - Standardized'!F:F) -> 0 | F24: =+_xlfn.XLOOKUP(" + Inventories",'[2]Bal Sheet - Standardized'!$A:$A,'[2]Bal Sheet - Standardized'!G:G) -> 0 | G24: =+_xlfn.XLOOKUP(" + Inventories",'[2]Bal Sheet - Standardized'!$A:$A,'[2]Bal Sheet - Standardized'!H:H) -> 0 | H24: =+_xlfn.XLOOKUP(" + Inventories",'[2]Bal Sheet - Standardized'!$A:$A,'[2]Bal Sheet - Standardized'!I:I) -> 0 | I24: =+_xlfn.XLOOKUP(" + Inventories",'[2]Bal Sheet - Standardized'!$A:$A,'[2]Bal Sheet - Standardized'!J:J) -> 0 | J24: =+_xlfn.XLOOKUP(" + Inventories",'[2]Bal Sheet - Standardized'!$A:$A,'[2]Bal Sheet - Standardized'!K:K) -> 0 | K24: =+_xlfn.XLOOKUP(" + Inventories",'[2]Bal Sheet - Standardized'!$A:$A,'[2]Bal Sheet - Standardized'!L:L) -> 0 | L24: =+_xlfn.XLOOKUP(" + Inventories",'[2]Bal Sheet - Standardized'!$A:$A,'[2]Bal Sheet - Standardized'!M:M) -> 0 | M24: =+_xlfn.XLOOKUP(" + Inventories",'[2]Bal Sheet - Standardized'!$A:$A,'[2]Bal Sheet - Standardized'!N:N) -> 0 | N24: =+_xlfn.XLOOKUP(" + Inventories",'[2]Bal Sheet - Standardized'!$A:$A,'[2]Bal Sheet - Standardized'!O:O) -> 0
A25: Activos Fijos (Net Plant) | B25: =_xlfn.XLOOKUP(" + Property, Plant & Equip, Net",'[2]Bal Sheet - Standardized'!$A:$A,'[2]Bal Sheet - Standardized'!C:C) -> 945.8 | C25: =_xlfn.XLOOKUP(" + Property, Plant & Equip, Net",'[2]Bal Sheet - Standardized'!$A:$A,'[2]Bal Sheet - Standardized'!D:D) -> 882.8 | D25: =_xlfn.XLOOKUP(" + Property, Plant & Equip, Net",'[2]Bal Sheet - Standardized'!$A:$A,'[2]Bal Sheet - Standardized'!E:E) -> 819.9 | E25: =_xlfn.XLOOKUP(" + Property, Plant & Equip, Net",'[2]Bal Sheet - Standardized'!$A:$A,'[2]Bal Sheet - Standardized'!F:F) -> 817 | F25: =_xlfn.XLOOKUP(" + Property, Plant & Equip, Net",'[2]Bal Sheet - Standardized'!$A:$A,'[2]Bal Sheet - Standardized'!G:G) -> 861.1 | G25: =_xlfn.XLOOKUP(" + Property, Plant & Equip, Net",'[2]Bal Sheet - Standardized'!$A:$A,'[2]Bal Sheet - Standardized'!H:H) -> 899.7 | H25: =_xlfn.XLOOKUP(" + Property, Plant & Equip, Net",'[2]Bal Sheet - Standardized'!$A:$A,'[2]Bal Sheet - Standardized'!I:I) -> 178.2 | I25: =_xlfn.XLOOKUP(" + Property, Plant & Equip, Net",'[2]Bal Sheet - Standardized'!$A:$A,'[2]Bal Sheet - Standardized'!J:J) -> 169 | J25: =_xlfn.XLOOKUP(" + Property, Plant & Equip, Net",'[2]Bal Sheet - Standardized'!$A:$A,'[2]Bal Sheet - Standardized'!K:K) -> 135.4 | K25: =_xlfn.XLOOKUP(" + Property, Plant & Equip, Net",'[2]Bal Sheet - Standardized'!$A:$A,'[2]Bal Sheet - Standardized'!L:L) -> 135.3 | L25: =_xlfn.XLOOKUP(" + Property, Plant & Equip, Net",'[2]Bal Sheet - Standardized'!$A:$A,'[2]Bal Sheet - Standardized'!M:M) -> 136.7 | M25: =_xlfn.XLOOKUP(" + Property, Plant & Equip, Net",'[2]Bal Sheet - Standardized'!$A:$A,'[2]Bal Sheet - Standardized'!N:N) -> 100.4 | N25: =_xlfn.XLOOKUP(" + Property, Plant & Equip, Net",'[2]Bal Sheet - Standardized'!$A:$A,'[2]Bal Sheet - Standardized'!O:O) -> 107.8
A26: Otros Activos | B26: =B27-SUM(B22:B25) -> 8496.5 | C26: 9011 | D26: 9056 | E26: 8725 | F26: 9709 | G26: 3942 | H26: 3504 | I26: 3495 | J26: 3086 | K26: 3023 | L26: 1811 | M26: 1728 | N26: 1728
A27: Total Activo | B27: =_xlfn.XLOOKUP("Total Assets",'[2]Bal Sheet - Standardized'!$A:$A,'[2]Bal Sheet - Standardized'!C:C,,,-1) -> 15545.9 | C27: =_xlfn.XLOOKUP("Total Assets",'[2]Bal Sheet - Standardized'!$A:$A,'[2]Bal Sheet - Standardized'!D:D,,,-1) -> 14622.4 | D27: =_xlfn.XLOOKUP("Total Assets",'[2]Bal Sheet - Standardized'!$A:$A,'[2]Bal Sheet - Standardized'!E:E,,,-1) -> 14261.1 | E27: =_xlfn.XLOOKUP("Total Assets",'[2]Bal Sheet - Standardized'!$A:$A,'[2]Bal Sheet - Standardized'!F:F,,,-1) -> 14218.7 | F27: =_xlfn.XLOOKUP("Total Assets",'[2]Bal Sheet - Standardized'!$A:$A,'[2]Bal Sheet - Standardized'!G:G,,,-1) -> 12964.2 | G27: =_xlfn.XLOOKUP("Total Assets",'[2]Bal Sheet - Standardized'!$A:$A,'[2]Bal Sheet - Standardized'!H:H,,,-1) -> 13872.6 | H27: =_xlfn.XLOOKUP("Total Assets",'[2]Bal Sheet - Standardized'!$A:$A,'[2]Bal Sheet - Standardized'!I:I,,,-1) -> 7974 | I27: =_xlfn.XLOOKUP("Total Assets",'[2]Bal Sheet - Standardized'!$A:$A,'[2]Bal Sheet - Standardized'!J:J,,,-1) -> 7029.8 | J27: =_xlfn.XLOOKUP("Total Assets",'[2]Bal Sheet - Standardized'!$A:$A,'[2]Bal Sheet - Standardized'!K:K,,,-1) -> 6943.1 | K27: =_xlfn.XLOOKUP("Total Assets",'[2]Bal Sheet - Standardized'!$A:$A,'[2]Bal Sheet - Standardized'!L:L,,,-1) -> 6311.4 | L27: =_xlfn.XLOOKUP("Total Assets",'[2]Bal Sheet - Standardized'!$A:$A,'[2]Bal Sheet - Standardized'!M:M,,,-1) -> 4962.4 | M27: =_xlfn.XLOOKUP("Total Assets",'[2]Bal Sheet - Standardized'!$A:$A,'[2]Bal Sheet - Standardized'!N:N,,,-1) -> 4187.9 | N27: =_xlfn.XLOOKUP("Total Assets",'[2]Bal Sheet - Standardized'!$A:$A,'[2]Bal Sheet - Standardized'!O:O,,,-1) -> 3612.4
A30: Pasivo
A31: Pasivo Corto Plazo | B31: =_xlfn.XLOOKUP("Total Current Liabilities",'[2]Bal Sheet - Standardized'!$A:$A,'[2]Bal Sheet - Standardized'!C:C) -> 3521.5 | C31: =_xlfn.XLOOKUP("Total Current Liabilities",'[2]Bal Sheet - Standardized'!$A:$A,'[2]Bal Sheet - Standardized'!D:D) -> 3561 | D31: =_xlfn.XLOOKUP("Total Current Liabilities",'[2]Bal Sheet - Standardized'!$A:$A,'[2]Bal Sheet - Standardized'!E:E) -> 2881 | E31: =_xlfn.XLOOKUP("Total Current Liabilities",'[2]Bal Sheet - Standardized'!$A:$A,'[2]Bal Sheet - Standardized'!F:F) -> 3470.3 | F31: =_xlfn.XLOOKUP("Total Current Liabilities",'[2]Bal Sheet - Standardized'!$A:$A,'[2]Bal Sheet - Standardized'!G:G) -> 2086.9 | G31: =_xlfn.XLOOKUP("Total Current Liabilities",'[2]Bal Sheet - Standardized'!$A:$A,'[2]Bal Sheet - Standardized'!H:H) -> 2133.8 | H31: =_xlfn.XLOOKUP("Total Current Liabilities",'[2]Bal Sheet - Standardized'!$A:$A,'[2]Bal Sheet - Standardized'!I:I) -> 2022.7 | I31: =_xlfn.XLOOKUP("Total Current Liabilities",'[2]Bal Sheet - Standardized'!$A:$A,'[2]Bal Sheet - Standardized'!J:J) -> 1527.5 | J31: =_xlfn.XLOOKUP("Total Current Liabilities",'[2]Bal Sheet - Standardized'!$A:$A,'[2]Bal Sheet - Standardized'!K:K) -> 1465.6 | K31: =_xlfn.XLOOKUP("Total Current Liabilities",'[2]Bal Sheet - Standardized'!$A:$A,'[2]Bal Sheet - Standardized'!L:L) -> 1311.9 | L31: =_xlfn.XLOOKUP("Total Current Liabilities",'[2]Bal Sheet - Standardized'!$A:$A,'[2]Bal Sheet - Standardized'!M:M) -> 1134.9 | M31: =_xlfn.XLOOKUP("Total Current Liabilities",'[2]Bal Sheet - Standardized'!$A:$A,'[2]Bal Sheet - Standardized'!N:N) -> 888.2 | N31: =_xlfn.XLOOKUP("Total Current Liabilities",'[2]Bal Sheet - Standardized'!$A:$A,'[2]Bal Sheet - Standardized'!O:O) -> 928.5
A32: Deuda a corto plazo | B32: =_xlfn.XLOOKUP(" + ST Borrowings",'[2]Bal Sheet - Standardized'!$A:$A,'[2]Bal Sheet - Standardized'!C:C)+_xlfn.XLOOKUP(" + Current Portion of LT Debt",'[2]Bal Sheet - Standardized'!$A:$A,'[2]Bal Sheet - Standardized'!C:C) -> 450.8 | C32: =_xlfn.XLOOKUP(" + ST Borrowings",'[2]Bal Sheet - Standardized'!$A:$A,'[2]Bal Sheet - Standardized'!D:D)+_xlfn.XLOOKUP(" + Current Portion of LT Debt",'[2]Bal Sheet - Standardized'!$A:$A,'[2]Bal Sheet - Standardized'!D:D) -> 950.1 | D32: =_xlfn.XLOOKUP(" + ST Borrowings",'[2]Bal Sheet - Standardized'!$A:$A,'[2]Bal Sheet - Standardized'!E:E)+_xlfn.XLOOKUP(" + Current Portion of LT Debt",'[2]Bal Sheet - Standardized'!$A:$A,'[2]Bal Sheet - Standardized'!E:E) -> 258.6 | E32: =_xlfn.XLOOKUP(" + ST Borrowings",'[2]Bal Sheet - Standardized'!$A:$A,'[2]Bal Sheet - Standardized'!F:F)+_xlfn.XLOOKUP(" + Current Portion of LT Debt",'[2]Bal Sheet - Standardized'!$A:$A,'[2]Bal Sheet - Standardized'!F:F) -> 903.2 | F32: =_xlfn.XLOOKUP(" + ST Borrowings",'[2]Bal Sheet - Standardized'!$A:$A,'[2]Bal Sheet - Standardized'!G:G)+_xlfn.XLOOKUP(" + Current Portion of LT Debt",'[2]Bal Sheet - Standardized'!$A:$A,'[2]Bal Sheet - Standardized'!G:G) -> 16 | G32: =_xlfn.XLOOKUP(" + ST Borrowings",'[2]Bal Sheet - Standardized'!$A:$A,'[2]Bal Sheet - Standardized'!H:H)+_xlfn.XLOOKUP(" + Current Portion of LT Debt",'[2]Bal Sheet - Standardized'!$A:$A,'[2]Bal Sheet - Standardized'!H:H) -> 4.4 | H32: =_xlfn.XLOOKUP(" + ST Borrowings",'[2]Bal Sheet - Standardized'!$A:$A,'[2]Bal Sheet - Standardized'!I:I)+_xlfn.XLOOKUP(" + Current Portion of LT Debt",'[2]Bal Sheet - Standardized'!$A:$A,'[2]Bal Sheet - Standardized'!I:I) -> 350 | I32: =_xlfn.XLOOKUP(" + ST Borrowings",'[2]Bal Sheet - Standardized'!$A:$A,'[2]Bal Sheet - Standardized'!J:J)+_xlfn.XLOOKUP(" + Current Portion of LT Debt",'[2]Bal Sheet - Standardized'!$A:$A,'[2]Bal Sheet - Standardized'!J:J) -> 0 | J32: =_xlfn.XLOOKUP(" + ST Borrowings",'[2]Bal Sheet - Standardized'!$A:$A,'[2]Bal Sheet - Standardized'!K:K)+_xlfn.XLOOKUP(" + Current Portion of LT Debt",'[2]Bal Sheet - Standardized'!$A:$A,'[2]Bal Sheet - Standardized'!K:K) -> 0 | K32: =_xlfn.XLOOKUP(" + ST Borrowings",'[2]Bal Sheet - Standardized'!$A:$A,'[2]Bal Sheet - Standardized'!L:L)+_xlfn.XLOOKUP(" + Current Portion of LT Debt",'[2]Bal Sheet - Standardized'!$A:$A,'[2]Bal Sheet - Standardized'!L:L) -> 0 | L32: =_xlfn.XLOOKUP(" + ST Borrowings",'[2]Bal Sheet - Standardized'!$A:$A,'[2]Bal Sheet - Standardized'!M:M)+_xlfn.XLOOKUP(" + Current Portion of LT Debt",'[2]Bal Sheet - Standardized'!$A:$A,'[2]Bal Sheet - Standardized'!M:M) -> 10 | M32: =_xlfn.XLOOKUP(" + ST Borrowings",'[2]Bal Sheet - Standardized'!$A:$A,'[2]Bal Sheet - Standardized'!N:N)+_xlfn.XLOOKUP(" + Current Portion of LT Debt",'[2]Bal Sheet - Standardized'!$A:$A,'[2]Bal Sheet - Standardized'!N:N) -> 20 | N32: =_xlfn.XLOOKUP(" + ST Borrowings",'[2]Bal Sheet - Standardized'!$A:$A,'[2]Bal Sheet - Standardized'!O:O)+_xlfn.XLOOKUP(" + Current Portion of LT Debt",'[2]Bal Sheet - Standardized'!$A:$A,'[2]Bal Sheet - Standardized'!O:O) -> 25.5
A33: Short-Term Leases | B33: =_xlfn.XLOOKUP(" + ST Lease Liabilities",'[2]Bal Sheet - Standardized'!$A:$A,'[2]Bal Sheet - Standardized'!C:C) -> 0 | C33: =_xlfn.XLOOKUP(" + ST Lease Liabilities",'[2]Bal Sheet - Standardized'!$A:$A,'[2]Bal Sheet - Standardized'!D:D) -> 66.5 | D33: =_xlfn.XLOOKUP(" + ST Lease Liabilities",'[2]Bal Sheet - Standardized'!$A:$A,'[2]Bal Sheet - Standardized'!E:E) -> 83.1 | E33: =_xlfn.XLOOKUP(" + ST Lease Liabilities",'[2]Bal Sheet - Standardized'!$A:$A,'[2]Bal Sheet - Standardized'!F:F) -> 83.5 | F33: =_xlfn.XLOOKUP(" + ST Lease Liabilities",'[2]Bal Sheet - Standardized'!$A:$A,'[2]Bal Sheet - Standardized'!G:G) -> 78.8 | G33: =_xlfn.XLOOKUP(" + ST Lease Liabilities",'[2]Bal Sheet - Standardized'!$A:$A,'[2]Bal Sheet - Standardized'!H:H) -> 83 | H33: =_xlfn.XLOOKUP(" + ST Lease Liabilities",'[2]Bal Sheet - Standardized'!$A:$A,'[2]Bal Sheet - Standardized'!I:I) -> 0 | I33: =_xlfn.XLOOKUP(" + ST Lease Liabilities",'[2]Bal Sheet - Standardized'!$A:$A,'[2]Bal Sheet - Standardized'!J:J) -> 0 | J33: =_xlfn.XLOOKUP(" + ST Lease Liabilities",'[2]Bal Sheet - Standardized'!$A:$A,'[2]Bal Sheet - Standardized'!K:K) -> 0 | K33: =_xlfn.XLOOKUP(" + ST Lease Liabilities",'[2]Bal Sheet - Standardized'!$A:$A,'[2]Bal Sheet - Standardized'!L:L) -> 0 | L33: =_xlfn.XLOOKUP(" + ST Lease Liabilities",'[2]Bal Sheet - Standardized'!$A:$A,'[2]Bal Sheet - Standardized'!M:M) -> 0 | M33: =_xlfn.XLOOKUP(" + ST Lease Liabilities",'[2]Bal Sheet - Standardized'!$A:$A,'[2]Bal Sheet - Standardized'!N:N) -> 0 | N33: =_xlfn.XLOOKUP(" + ST Lease Liabilities",'[2]Bal Sheet - Standardized'!$A:$A,'[2]Bal Sheet - Standardized'!O:O) -> 0
A34: Otros Pasivos a Corto Plazo | B34: =B31-SUM(B32:B33) -> 3070.7 | C34: 2456 | D34: 2400 | E34: 1913 | F34: 1963 | G34: 1673 | H34: 1528 | I34: 1466 | J34: 1312 | K34: 1125 | L34: 868 | M34: 903 | N34: 903
A35: Pasivo Largo Plazo | B35: =_xlfn.XLOOKUP("Total Noncurrent Liabilities",'[2]Bal Sheet - Standardized'!$A:$A,'[2]Bal Sheet - Standardized'!C:C) -> 2943.7 | C35: =_xlfn.XLOOKUP("Total Noncurrent Liabilities",'[2]Bal Sheet - Standardized'!$A:$A,'[2]Bal Sheet - Standardized'!D:D) -> 3215.4 | D35: =_xlfn.XLOOKUP("Total Noncurrent Liabilities",'[2]Bal Sheet - Standardized'!$A:$A,'[2]Bal Sheet - Standardized'!E:E) -> 4055.2 | E35: =_xlfn.XLOOKUP("Total Noncurrent Liabilities",'[2]Bal Sheet - Standardized'!$A:$A,'[2]Bal Sheet - Standardized'!F:F) -> 4537.4 | F35: =_xlfn.XLOOKUP("Total Noncurrent Liabilities",'[2]Bal Sheet - Standardized'!$A:$A,'[2]Bal Sheet - Standardized'!G:G) -> 5771.2 | G35: =_xlfn.XLOOKUP("Total Noncurrent Liabilities",'[2]Bal Sheet - Standardized'!$A:$A,'[2]Bal Sheet - Standardized'!H:H) -> 6476.3 | H35: =_xlfn.XLOOKUP("Total Noncurrent Liabilities",'[2]Bal Sheet - Standardized'!$A:$A,'[2]Bal Sheet - Standardized'!I:I) -> 1325.4 | I35: =_xlfn.XLOOKUP("Total Noncurrent Liabilities",'[2]Bal Sheet - Standardized'!$A:$A,'[2]Bal Sheet - Standardized'!J:J) -> 1506.3 | J35: =_xlfn.XLOOKUP("Total Noncurrent Liabilities",'[2]Bal Sheet - Standardized'!$A:$A,'[2]Bal Sheet - Standardized'!K:K) -> 1594.6 | K35: =_xlfn.XLOOKUP("Total Noncurrent Liabilities",'[2]Bal Sheet - Standardized'!$A:$A,'[2]Bal Sheet - Standardized'!L:L) -> 1511.9 | L35: =_xlfn.XLOOKUP("Total Noncurrent Liabilities",'[2]Bal Sheet - Standardized'!$A:$A,'[2]Bal Sheet - Standardized'!M:M) -> 868 | M35: =_xlfn.XLOOKUP("Total Noncurrent Liabilities",'[2]Bal Sheet - Standardized'!$A:$A,'[2]Bal Sheet - Standardized'!N:N) -> 675.5 | N35: =_xlfn.XLOOKUP("Total Noncurrent Liabilities",'[2]Bal Sheet - Standardized'!$A:$A,'[2]Bal Sheet - Standardized'!O:O) -> 330.8
A36: Deuda a largo plazo | B36: =_xlfn.XLOOKUP(" + LT Borrowings",'[2]Bal Sheet - Standardized'!$A:$A,'[2]Bal Sheet - Standardized'!C:C) -> 2042.8 | C36: =_xlfn.XLOOKUP(" + LT Borrowings",'[2]Bal Sheet - Standardized'!$A:$A,'[2]Bal Sheet - Standardized'!D:D) -> 2040.6 | D36: =_xlfn.XLOOKUP(" + LT Borrowings",'[2]Bal Sheet - Standardized'!$A:$A,'[2]Bal Sheet - Standardized'!E:E) -> 2737.4 | E36: =_xlfn.XLOOKUP(" + LT Borrowings",'[2]Bal Sheet - Standardized'!$A:$A,'[2]Bal Sheet - Standardized'!F:F) -> 2966.4 | F36: =_xlfn.XLOOKUP(" + LT Borrowings",'[2]Bal Sheet - Standardized'!$A:$A,'[2]Bal Sheet - Standardized'!G:G) -> 4174.3 | G36: =_xlfn.XLOOKUP(" + LT Borrowings",'[2]Bal Sheet - Standardized'!$A:$A,'[2]Bal Sheet - Standardized'!H:H) -> 4596.8 | H36: =_xlfn.XLOOKUP(" + LT Borrowings",'[2]Bal Sheet - Standardized'!$A:$A,'[2]Bal Sheet - Standardized'!I:I) -> 650 | I36: =_xlfn.XLOOKUP(" + LT Borrowings",'[2]Bal Sheet - Standardized'!$A:$A,'[2]Bal Sheet - Standardized'!J:J) -> 1000 | J36: =_xlfn.XLOOKUP(" + LT Borrowings",'[2]Bal Sheet - Standardized'!$A:$A,'[2]Bal Sheet - Standardized'!K:K) -> 1000 | K36: =_xlfn.XLOOKUP(" + LT Borrowings",'[2]Bal Sheet - Standardized'!$A:$A,'[2]Bal Sheet - Standardized'!L:L) -> 1000 | L36: =_xlfn.XLOOKUP(" + LT Borrowings",'[2]Bal Sheet - Standardized'!$A:$A,'[2]Bal Sheet - Standardized'!M:M) -> 350 | M36: =_xlfn.XLOOKUP(" + LT Borrowings",'[2]Bal Sheet - Standardized'!$A:$A,'[2]Bal Sheet - Standardized'!N:N) -> 360 | N36: =_xlfn.XLOOKUP(" + LT Borrowings",'[2]Bal Sheet - Standardized'!$A:$A,'[2]Bal Sheet - Standardized'!O:O) -> 38.3
A37: Long-Term Leases | B37: =_xlfn.XLOOKUP(" + LT Lease Liabilities",'[2]Bal Sheet - Standardized'!$A:$A,'[2]Bal Sheet - Standardized'!C:C) -> 0 | C37: =_xlfn.XLOOKUP(" + LT Lease Liabilities",'[2]Bal Sheet - Standardized'!$A:$A,'[2]Bal Sheet - Standardized'!D:D) -> 543.7 | D37: =_xlfn.XLOOKUP(" + LT Lease Liabilities",'[2]Bal Sheet - Standardized'!$A:$A,'[2]Bal Sheet - Standardized'!E:E) -> 497.6 | E37: =_xlfn.XLOOKUP(" + LT Lease Liabilities",'[2]Bal Sheet - Standardized'!$A:$A,'[2]Bal Sheet - Standardized'!F:F) -> 517.6 | F37: =_xlfn.XLOOKUP(" + LT Lease Liabilities",'[2]Bal Sheet - Standardized'!$A:$A,'[2]Bal Sheet - Standardized'!G:G) -> 564.5 | G37: =_xlfn.XLOOKUP(" + LT Lease Liabilities",'[2]Bal Sheet - Standardized'!$A:$A,'[2]Bal Sheet - Standardized'!H:H) -> 612.8 | H37: =_xlfn.XLOOKUP(" + LT Lease Liabilities",'[2]Bal Sheet - Standardized'!$A:$A,'[2]Bal Sheet - Standardized'!I:I) -> 0 | I37: =_xlfn.XLOOKUP(" + LT Lease Liabilities",'[2]Bal Sheet - Standardized'!$A:$A,'[2]Bal Sheet - Standardized'!J:J) -> 0 | J37: =_xlfn.XLOOKUP(" + LT Lease Liabilities",'[2]Bal Sheet - Standardized'!$A:$A,'[2]Bal Sheet - Standardized'!K:K) -> 0 | K37: =_xlfn.XLOOKUP(" + LT Lease Liabilities",'[2]Bal Sheet - Standardized'!$A:$A,'[2]Bal Sheet - Standardized'!L:L) -> 0 | L37: =_xlfn.XLOOKUP(" + LT Lease Liabilities",'[2]Bal Sheet - Standardized'!$A:$A,'[2]Bal Sheet - Standardized'!M:M) -> 0 | M37: =_xlfn.XLOOKUP(" + LT Lease Liabilities",'[2]Bal Sheet - Standardized'!$A:$A,'[2]Bal Sheet - Standardized'!N:N) -> 0 | N37: =_xlfn.XLOOKUP(" + LT Lease Liabilities",'[2]Bal Sheet - Standardized'!$A:$A,'[2]Bal Sheet - Standardized'!O:O) -> 0
A38: Otros Pasivos a Largo Plazo | B38: =B35-SUM(B36:B37) -> 900.9 | C38: 323 | D38: 536 | E38: 468 | F38: 654 | G38: 675 | H38: 506 | I38: 595 | J38: 512 | K38: 518 | L38: 316 | M38: 293 | N38: 293
A39: Total Passivos | B39: =_xlfn.XLOOKUP("Total Liabilities",'[2]Bal Sheet - Standardized'!$A:$A,'[2]Bal Sheet - Standardized'!C:C) -> 6465.2 | C39: =_xlfn.XLOOKUP("Total Liabilities",'[2]Bal Sheet - Standardized'!$A:$A,'[2]Bal Sheet - Standardized'!D:D) -> 6776.4 | D39: =_xlfn.XLOOKUP("Total Liabilities",'[2]Bal Sheet - Standardized'!$A:$A,'[2]Bal Sheet - Standardized'!E:E) -> 6936.2 | E39: =_xlfn.XLOOKUP("Total Liabilities",'[2]Bal Sheet - Standardized'!$A:$A,'[2]Bal Sheet - Standardized'!F:F) -> 8007.7 | F39: =_xlfn.XLOOKUP("Total Liabilities",'[2]Bal Sheet - Standardized'!$A:$A,'[2]Bal Sheet - Standardized'!G:G) -> 7858.1 | G39: =_xlfn.XLOOKUP("Total Liabilities",'[2]Bal Sheet - Standardized'!$A:$A,'[2]Bal Sheet - Standardized'!H:H) -> 8610.1 | H39: =_xlfn.XLOOKUP("Total Liabilities",'[2]Bal Sheet - Standardized'!$A:$A,'[2]Bal Sheet - Standardized'!I:I) -> 3348.1 | I39: =_xlfn.XLOOKUP("Total Liabilities",'[2]Bal Sheet - Standardized'!$A:$A,'[2]Bal Sheet - Standardized'!J:J) -> 3033.8 | J39: =_xlfn.XLOOKUP("Total Liabilities",'[2]Bal Sheet - Standardized'!$A:$A,'[2]Bal Sheet - Standardized'!K:K) -> 3060.2 | K39: =_xlfn.XLOOKUP("Total Liabilities",'[2]Bal Sheet - Standardized'!$A:$A,'[2]Bal Sheet - Standardized'!L:L) -> 2823.7 | L39: =_xlfn.XLOOKUP("Total Liabilities",'[2]Bal Sheet - Standardized'!$A:$A,'[2]Bal Sheet - Standardized'!M:M) -> 2002.9 | M39: =_xlfn.XLOOKUP("Total Liabilities",'[2]Bal Sheet - Standardized'!$A:$A,'[2]Bal Sheet - Standardized'!N:N) -> 1563.7 | N39: =_xlfn.XLOOKUP("Total Liabilities",'[2]Bal Sheet - Standardized'!$A:$A,'[2]Bal Sheet - Standardized'!O:O) -> 1259.3
A42: Interés Minoritario | B42: =_xlfn.XLOOKUP(" + Minority/Non Controlling Interest",'[2]Bal Sheet - Standardized'!$A:$A,'[2]Bal Sheet - Standardized'!C:C) -> 14.1 | C42: =_xlfn.XLOOKUP(" + Minority/Non Controlling Interest",'[2]Bal Sheet - Standardized'!$A:$A,'[2]Bal Sheet - Standardized'!D:D) -> 11.9 | D42: =_xlfn.XLOOKUP(" + Minority/Non Controlling Interest",'[2]Bal Sheet - Standardized'!$A:$A,'[2]Bal Sheet - Standardized'!E:E) -> 14.2 | E42: =_xlfn.XLOOKUP(" + Minority/Non Controlling Interest",'[2]Bal Sheet - Standardized'!$A:$A,'[2]Bal Sheet - Standardized'!F:F) -> 13.7 | F42: =_xlfn.XLOOKUP(" + Minority/Non Controlling Interest",'[2]Bal Sheet - Standardized'!$A:$A,'[2]Bal Sheet - Standardized'!G:G) -> 44.8 | G42: =_xlfn.XLOOKUP(" + Minority/Non Controlling Interest",'[2]Bal Sheet - Standardized'!$A:$A,'[2]Bal Sheet - Standardized'!H:H) -> 53.9 | H42: =_xlfn.XLOOKUP(" + Minority/Non Controlling Interest",'[2]Bal Sheet - Standardized'!$A:$A,'[2]Bal Sheet - Standardized'!I:I) -> 63.9 | I42: =_xlfn.XLOOKUP(" + Minority/Non Controlling Interest",'[2]Bal Sheet - Standardized'!$A:$A,'[2]Bal Sheet - Standardized'!J:J) -> 1.9 | J42: =_xlfn.XLOOKUP(" + Minority/Non Controlling Interest",'[2]Bal Sheet - Standardized'!$A:$A,'[2]Bal Sheet - Standardized'!K:K) -> 22.6 | K42: =_xlfn.XLOOKUP(" + Minority/Non Controlling Interest",'[2]Bal Sheet - Standardized'!$A:$A,'[2]Bal Sheet - Standardized'!L:L) -> 19.2 | L42: =_xlfn.XLOOKUP(" + Minority/Non Controlling Interest",'[2]Bal Sheet - Standardized'!$A:$A,'[2]Bal Sheet - Standardized'!M:M) -> 16 | M42: =_xlfn.XLOOKUP(" + Minority/Non Controlling Interest",'[2]Bal Sheet - Standardized'!$A:$A,'[2]Bal Sheet - Standardized'!N:N) -> 13.6 | N42: =_xlfn.XLOOKUP(" + Minority/Non Controlling Interest",'[2]Bal Sheet - Standardized'!$A:$A,'[2]Bal Sheet - Standardized'!O:O) -> 16.2
A44: Capital Contable | B44: =B27-B39 -> 9080.7 | C44: =C27-C39 -> 7846 | D44: =D27-D39 -> 7324.9 | E44: =E27-E39 -> 6211 | F44: =F27-F39 -> 5106.1 | G44: =G27-G39 -> 5262.5 | H44: =H27-H39 -> 4625.9 | I44: =I27-I39 -> 3996 | ... M44: =M27-M39 -> 2624.2
A46: OTROS DATOS AL FIN DE AÑO
A47: Numero de Empleados | B47: 24000
A48: Acciones en circulación (millones) | B48: {=_FV(K2,"Shares outstanding",TRUE)/1000000} -> 1341.456
A49: Float | B49: =668.54/B48 -> 0.49836894
A50: Insiders Own | B50: 0.4812
A51: S&P
A52: Vol. Diario en Millones USD
B53: 2022 | C53: 2023 | D53: 2024
A54: Posicion en Corto (%)
A55: EPS | B55: 0.71 | C55: 0.8 | D55: 0.91
A57: BONOS DE LA EMISORA A 3, 5 Y 10 | B57: Precio Medio | C57: S&P | D57: YTM (%) | E57: DIVISA
G58: =(Cifras_en_Millones!$C$54+Cifras_en_Millones!$C$50)-(Cifras_en_Millones!$D$50+Cifras_en_Millones!$D$54) -> -497.1
C66: usd | D66: eur | E66: yen | G66: eurusd | H66: 1.05
B67: 10y | C67: 4.43 | D67: 2.48 | E67: 1.44 | G67: eurjpy | H67: 156.78
B68: 30y | C68: 4.68 | D68: 2.79 | E68: 2.33

Sheet Q
B2: 3Q17 | C2: 3Q18 | D2: 4Q18 | E2: 1Q19 | F2: 2Q19 | G2: 3Q19 | H2: 4Q19 | I2: 1Q20 | J2: 2Q20 | K2: 3Q20 | L2: 4Q20 | M2: 1Q21 | N2: 2Q21 | O2: 3Q21 | P2: 4Q21 | Q2: 1Q22 | R2: 2Q22 | S2: 3Q22 | T2: 4Q22 | U2: 1Q23 | V2: 2Q23 | W2: 3Q23 | X2: 4Q23e | Z2: 2019 | AA2: 2020 | AB2: 2021 | AC2: 2022 | AD2: 2023 | AE2: 2024 | AF2: 2025 | AG2: 2026 | AH2: 2027 | AI2: 2028 | AJ2: 2029 | AK2: 2030 | AL2: 2031 | AM2: 2032 | AN2: 2033 | AO2: 2034 | AP2: 2035 | AQ2: 2036 | AR2: 2037 | AS2: 2038 | AT2: 2039 | AU2: 2040 | AV2: 2041 | AW2: 2042 | AX2: 2043 | AY2: 2044 | AZ2: 2045 | BA2: 2046 | BB2: 2047
A3: Shares
A4: Growth
A5: Prods | AE5: 0.045 | AF5: =0.987*AE5 -> 0.044415 | AG5: =0.987*AF5 -> 0.043837605 | AH5: =0.987*AG5 -> 0.043267716 | AI5: =0.987*AH5 -> 0.042705236 | AJ5: =0.987*AI5 -> 0.042150068 | AK5: =0.987*AJ5 -> 0.041602117 | AL5: =0.987*AK5 -> 0.041061289 | AM5: =0.987*AL5 -> 0.040527493 | ... BB5: =0.987*BA5 -> 0.033304815
A6: Serv | AE6: 0.09 | AF6: =AE6*0.975 -> 0.08775 | AG6: =AF6*0.975 -> 0.08555625 | AH6: =AG6*0.975 -> 0.083417344 | AI6: =AH6*0.975 -> 0.08133191 | AJ6: =AI6*0.975 -> 0.079298612 | AK6: =AJ6*0.975 -> 0.077316147 | AL6: =AK6*0.975 -> 0.075383243 | AM6: =AL6*0.975 -> 0.073498662 | ... BB6: =BA6*0.975 -> 0.050274605
A8: COGS
A9: Prods | Z9: =Z30/Z26 -> 0.67792204 | AA9: =AA30/AA26 -> 0.68533661 | AB9: =AB30/AB26 -> 0.64650697 | AC9: =AC30/AC26 -> 0.6371652 | AD9: =AD30/AD26 -> 0.6358648 | AE9: =AD9*1.001 -> 0.63650067 | AF9: =AE9*1.001 -> 0.63713717 | AG9: =AF9*1.001 -> 0.6377743 | AH9: =AG9*1.001 -> 0.63841208 | AI9: =AH9*1.001 -> 0.63905049 | AJ9: =AI9*1.001 -> 0.63968954 | AK9: =AJ9*1.001 -> 0.64032923 | AL9: =AK9*1.001 -> 0.64096956 | ... BB9: =BA9*1.001 -> 0.65130235
A10: Serv | Z10: =Z31/Z27 -> 0.36261908 | AA10: =AA31/AA27 -> 0.33984898 | AB10: =AB31/AB27 -> 0.30274023 | AC10: =AC31/AC27 -> 0.28254553 | AD10: =AD31/AD27 -> 0.29105249 | AE10: =AD10*1.001 -> 0.29134354 | AF10: =AE10*1.001 -> 0.29163488 | AG10: =AF10*1.001 -> 0.29192652 | AH10: =AG10*1.001 -> 0.29221845 | AI10: =AH10*1.001 -> 0.29251066 | AJ10: =AI10*1.001 -> 0.29280317 | AK10: =AJ10*1.001 -> 0.29309598 | AL10: =AK10*1.001 -> 0.29338907 | ... BB10: =BA10*1.001 -> 0.29811867
A12: R&D | Z12: =Z33/Z25 -> 0.062331363 | AA12: =AA33/AA25 -> 0.068309564 | AB12: =AB33/AB25 -> 0.059904269 | AC12: =AC33/AC25 -> 0.066571484 | AD12: =AD33/AD25 -> 0.078317483 | AE12: =1.01*AD12 -> 0.079100658 | AF12: =1.01*AE12 -> 0.079891665 | AG12: =1.01*AF12 -> 0.080690581 | AH12: =1.01*AG12 -> 0.081497487 | AI12: =1.01*AH12 -> 0.082312462 | AJ12: =1.01*AI12 -> 0.083135587 | AK12: =1.01*AJ12 -> 0.083966943 | AL12: =1.01*AK12 -> 0.084806612 | ... BB12: =1.01*BA12 -> 0.099442422
A13: SGA | Z13: =Z34/Z25 -> 0.070126146 | AA13: =AA34/AA25 -> 0.07254977 | AB13: =AB34/AB25 -> 0.060065552 | AC13: =AC34/AC25 -> 0.063637378 | AD13: =AD34/AD25 -> 0.065265004 | AE13: =AD13*1.001 -> 0.065330269 | AF13: =AE13*1.001 -> 0.0653956 | AG13: =AF13*1.001 -> 0.065460995 | AH13: =AG13*1.001 -> 0.065526456 | AI13: =AH13*1.001 -> 0.065591983 | AJ13: =AI13*1.001 -> 0.065657575 | AK13: =AJ13*1.001 -> 0.065723232 | AL13: =AK13*1.001 -> 0.065788956 | ... BB13: =BA13*1.001 -> 0.066849511
A15: Utiilidad oP
A17: Tax Rate | Z17: =Z41/Z40 -> 0.15943837 | AA17: =AA41/AA40 -> 0.14428165 | AB17: =AB41/AB40 -> 0.13302261 | AC17: =AC41/AC40 -> 0.16204462
A19: DA | Z19: =Z52/Z25 -> 0.048225418 | AA19: =AA52/AA25 -> 0.040274666 | AB19: =AB52/AB25 -> 0.030846024 | AC19: =AC52/AC25 -> 0.028159299
A20: SBC | Z20: =Z53/Z25 -> 0.023322853 | AA20: =AA53/AA25 -> 0.024876601 | AB20: =AB53/AB25 -> 0.021611899 | AC20: =AC53/AC25 -> 0.022920006
A21: Net SBC | U21: =((W25+V25)/(R25+S25))-1 -> -0.019995894 | Z21: =(Z53+Z54)/Z25 -> 0.031148385 | AA21: =(AA53+AA54)/AA25 -> 0.034908839 | AB21: =(AB53+AB54)/AB25 -> 0.039533428 | AC21: =(AC53+AC54)/AC25 -> 0.038701284
A22: Capex | U22: =((W25+V25)/(F25+G25))-1 -> 0.57956253 | Z22: =Z55/Z25 -> 0.040338389 | AA22: =AA55/AA25 -> 0.026625139 | AB22: =AB55/AB25 -> 0.030302036 | AC22: =AC55/AC25 -> 0.027155059
A23: Net SBC Factor | Z23: =Z21/Z20 -> 1.3355307 | AA23: =AA21/AA20 -> 1.4032801 | AB23: =AB21/AB20 -> 1.8292436 | AC23: =AC21/AC20 -> 1.6885373
A25: Revenue | C25: =C26+C27 -> 53265 | D25: =D26+D27 -> 64040 | E25: =E26+E27 -> 84310 | F25: =F26+F27 -> 58015 | G25: =G26+G27 -> 53809 | H25: =H26+H27 -> 64040 | I25: =I26+I27 -> 91819 | J25: =J26+J27 -> 58313 | ... X25: =X26+X27 -> 89282 | Z25: =Z26+Z27 -> 260174 | AA25: =AA26+AA27 -> 274515 | AB25: =AB26+AB27 -> 365817 | AC25: =AC26+AC27 -> 394328 | AD25: =AD26+AD27 -> 383069 | AE25: =AE26+AE27 -> 404095.7 | AF25: =AF26+AF27 -> 426020.39 | AG25: =AG26+AG27 -> 448860.49 | ... BB25: =BB26+BB27 -> 1156800
A26: -Products | C26: 43095 | D26: 51529 | E26: 73435 | F26: 46565 | G26: 42354 | H26: 51529 | I26: 79104 | J26: 44965 | K26: 46529 | L26: 50149 | M26: 95678 | N26: 72683 | O26: 63948 | P26: 65083 | Q26: 104429 | R26: 77457 | S26: 63355 | T26: 70958 | U26: 96388 | V26: 73929 | W26: 60584 | X26: 67977 | Z26: =SUM(E26:H26) -> 213883 | AA26: =SUM(I26:L26) -> 220747 | AB26: =SUM(M26:P26) -> 297392 | AC26: =SUM(Q26:T26) -> 316199 | AD26: =SUM(U26:X26) -> 298878 | AE26: =(1+AE5)*AD26 -> 312327.51 | AF26: =(1+AF5)*AE26 -> 326199.54 | AG26: =(1+AG5)*AF26 -> 340499.34 | AH26: =(1+AH5)*AG26 -> 355231.97 | AI26: =(1+AI5)*AH26 -> 370402.24 | AJ26: =(1+AJ5)*AI26 -> 386014.72 | AK26: =(1+AK5)*AJ26 -> 402073.75 | AL26: =(1+AL5)*AK26 -> 418583.41 | ... BB26: =(1+BB5)*BA26 -> 746321.37
A27: -Services | C27: 10170 | D27: 12511 | E27: 10875 | F27: 11450 | G27: 11455 | H27: 12511 | I27: 12715 | J27: 13348 | K27: 13156 | L27: 14549 | M27: 15761 | N27: 16901 | O27: 17486 | P27: 18277 | Q27: 19516 | R27: 19821 | S27: 19604 | T27: 19188 | U27: 20766 | V27: 20907 | W27: 21213 | X27: 21305 | Z27: =SUM(E27:H27) -> 46291 | AA27: =SUM(I27:L27) -> 53768 | AB27: =SUM(M27:P27) -> 68425 | AC27: =SUM(Q27:T27) -> 78129 | AD27: =SUM(U27:X27) -> 84191 | AE27: =(1+AE6)*AD27 -> 91768.19 | AF27: =(1+AF6)*AE27 -> 99820.849 | AG27: =(1+AG6)*AF27 -> 108361.15 | AH27: =(1+AH6)*AG27 -> 117400.35 | AI27: =(1+AI6)*AH27 -> 126948.74 | AJ27: =(1+AJ6)*AI27 -> 137015.6 | AK27: =(1+AK6)*AJ27 -> 147609.12 | AL27: =(1+AL6)*AK27 -> 158736.37 | ... BB27: =(1+BB6)*BA27 -> 410478.6
A29: COGS
A30: -Products | C30: 28956 | D30: 35238 | E30: 48238 | F30: 32047 | G30: 29473 | H30: 35238 | I30: 52075 | J30: 31321 | K30: 32693 | L30: 35197 | M30: 62130 | N30: 46447 | O30: 40899 | P30: 42790 | Q30: 64309 | R30: 49290 | S30: 41485 | T30: 46387 | U30: 60765 | V30: 46795 | W30: 39136 | X30: 43350 | Z30: =SUM(E30:H30) -> 144996 | AA30: =SUM(I30:L30) -> 151286 | AB30: =SUM(M30:P30) -> 192266 | AC30: =SUM(Q30:T30) -> 201471 | AD30: =SUM(U30:X30) -> 190046 | AE30: =AE9*AE26 -> 198796.67 | AF30: =AF9*AF26 -> 207833.85 | AG30: =AG9*AG26 -> 217161.73 | AH30: =AH9*AH26 -> 226784.38 | AI30: =AI9*AI26 -> 236705.73 | AJ30: =AJ9*AJ26 -> 246929.58 | AK30: =AK9*AK26 -> 257459.57 | AL30: =AL9*AL26 -> 268299.23 | ... BB30: =BB9*BB26 -> 486080.86
A31: -Services | C31: 3888 | D31: 4489 | E31: 4041 | F31: 4147 | G31: 4109 | H31: 4489 | I31: 4527 | J31: 4622 | K31: 4312 | L31: 4812 | M31: 4981 | N31: 5058 | O31: 5280 | P31: 5396 | Q31: 5393 | R31: 5429 | S31: 5589 | T31: 5664 | U31: 6057 | V31: 6065 | W31: 6248 | X31: 6134 | Z31: =SUM(E31:H31) -> 16786 | AA31: =SUM(I31:L31) -> 18273 | AB31: =SUM(M31:P31) -> 20715 | AC31: =SUM(Q31:T31) -> 22075 | AD31: =SUM(U31:X31) -> 24504 | AE31: =AE10*AE27 -> 26736.069 | AF31: =AF10*AF27 -> 29111.242 | AG31: =AG10*AG27 -> 31633.492 | AH31: =AH10*AH27 -> 34306.546 | AI31: =AI10*AI27 -> 37133.86 | AJ31: =AJ10*AJ27 -> 40118.602 | AK31: =AK10*AK27 -> 43263.638 | AL31: =AL10*AL27 -> 46571.517 | ... BB31: =BB10*BB27 -> 122371.34
A33: R&D | C33: 3701 | D33: 4110 | E33: 3902 | F33: 3948 | G33: 4257 | H33: 4110 | I33: 4451 | J33: 4565 | K33: 4758 | L33: 4978 | M33: 5163 | N33: 5262 | O33: 5717 | P33: 5772 | Q33: 6306 | R33: 6387 | S33: 6797 | T33: 6761 | U33: 7709 | V33: 7457 | W33: 7442 | X33: 7393 | Z33: =SUM(E33:H33) -> 16217 | AA33: =SUM(I33:L33) -> 18752 | AB33: =SUM(M33:P33) -> 21914 | AC33: =SUM(Q33:T33) -> 26251 | AD33: =SUM(U33:X33) -> 30001 | AE33: =AE12*AE$25 -> 31964.236 | AF33: =AF12*AF$25 -> 34035.478 | AG33: =AG12*AG$25 -> 36218.814 | AH33: =AH12*AH$25 -> 38518.346 | AI33: =AI12*AI$25 -> 40938.183 | AJ33: =AJ12*AJ$25 -> 43482.432 | AK33: =AK12*AK$25 -> 46155.189 | AL33: =AL12*AL$25 -> 48960.535 | ... BB33: =BB12*BB$25 -> 115034.99
A34: SGA | C34: 4108 | D34: 4578 | E34: 4783 | F34: 4458 | G34: 4426 | H34: 4578 | I34: 5197 | J34: 4952 | K34: 4831 | L34: 4936 | M34: 5631 | N34: 5314 | O34: 5412 | P34: 5616 | Q34: 6449 | R34: 6193 | S34: 6012 | T34: 6440 | U34: 6607 | V34: 6201 | W34: 5973 | X34: 6220 | Z34: =SUM(E34:H34) -> 18245 | AA34: =SUM(I34:L34) -> 19916 | AB34: =SUM(M34:P34) -> 21973 | AC34: =SUM(Q34:T34) -> 25094 | AD34: =SUM(U34:X34) -> 25001 | AE34: =AE13*AE$25 -> 26399.681 | AF34: =AF13*AF$25 -> 27859.859 | AG34: =AG13*AG$25 -> 29382.854 | AH34: =AH13*AH$25 -> 30969.921 | AI34: =AI13*AI$25 -> 32622.237 | AJ34: =AJ13*AJ$25 -> 34340.902 | AK34: =AK13*AK$25 -> 36126.934 | AL34: =AL13*AL$25 -> 37981.266 | ... BB34: =BB13*BB$25 -> 77331.512
A36: Ut OP | C36: =C25-C30-C31-C33-C34 -> 12612 | D36: =D25-D30-D31-D33-D34 -> 15625 | E36: =E25-E30-E31-E33-E34 -> 23346 | F36: =F25-F30-F31-F33-F34 -> 13415 | G36: =G25-G30-G31-G33-G34 -> 11544 | H36: =H25-H30-H31-H33-H34 -> 15625 | I36: =I25-I30-I31-I33-I34 -> 25569 | J36: =J25-J30-J31-J33-J34 -> 12853 | ... X36: =X25-X30-X31-X33-X34 -> 26185 | Z36: =Z25-Z30-Z31-Z33-Z34 -> 63930 | AA36: =AA25-AA30-AA31-AA33-AA34 -> 66288 | AB36: =AB25-AB30-AB31-AB33-AB34 -> 108949 | AC36: =AC25-AC30-AC31-AC33-AC34 -> 119437 | AD36: =AD25-AD30-AD31-AD33-AD34 -> 113517 | AE36: =AE25-AE30-AE31-AE33-AE34 -> 120199.05 | AF36: =AF25-AF30-AF31-AF33-AF34 -> 127179.96 | AG36: =AG25-AG30-AG31-AG33-AG34 -> 134463.6 | ... BB36: =BB25-BB30-BB31-BB33-BB34 -> 355981.27
A38: Other | C38: 672 | D38: 502 | E38: 560 | F38: 378 | G38: 367 | H38: 502 | I38: 349 | J38: 282 | K38: 46 | L38: 126 | M38: 45 | N38: 508 | O38: 243 | P38: -538 | Q38: -247 | R38: 160 | S38: -10 | T38: -237 | U38: -393 | V38: 64 | W38: -265 | Z38: =SUM(E38:H38) -> 1807 | AA38: =SUM(I38:L38) -> 803 | AB38: =SUM(M38:P38) -> 258 | AC38: =SUM(Q38:T38) -> -334
A40: efore tax | C40: =C26+C27-C30-C31-C33-C34+C38 -> 13284 | D40: =D26+D27-D30-D31-D33-D34+D38 -> 16127 | E40: =E26+E27-E30-E31-E33-E34+E38 -> 23906 | F40: =F26+F27-F30-F31-F33-F34+F38 -> 13793 | G40: =G26+G27-G30-G31-G33-G34+G38 -> 11911 | H40: =H26+H27-H30-H31-H33-H34+H38 -> 16127 | I40: =I26+I27-I30-I31-I33-I34+I38 -> 25918 | J40: =J26+J27-J30-J31-J33-J34+J38 -> 13135 | ... W40: =W26+W27-W30-W31-W33-W34+W38 -> 22733 | Z40: =SUM(E40:H40) -> 65737 | AA40: =SUM(I40:L40) -> 67091 | AB40: =SUM(M40:P40) -> 109207 | AC40: =SUM(Q40:T40) -> 119103
A41: Tax | C41: 1765 | D41: 2441 | E41: 3941 | F41: 2232 | G41: 1867 | H41: 2441 | I41: 3682 | J41: 1886 | K41: 1884 | L41: 2228 | M41: 4824 | N41: 4381 | O41: 2625 | P41: 2697 | Q41: 6611 | R41: 5129 | S41: 3624 | T41: 3936 | U41: 5625 | V41: 4222 | W41: 2852 | Z41: =SUM(E41:H41) -> 10481 | AA41: =SUM(I41:L41) -> 9680 | AB41: =SUM(M41:P41) -> 14527 | AC41: =SUM(Q41:T41) -> 19300
A42: NI | C42: =C40-C41 -> 11519 | D42: =D40-D41 -> 13686 | E42: =E40-E41 -> 19965 | F42: =F40-F41 -> 11561 | G42: =G40-G41 -> 10044 | H42: =H40-H41 -> 13686 | I42: =I40-I41 -> 22236 | J42: =J40-J41 -> 11249 | ... W42: =W40-W41 -> 19881
A45: DA | E45: 3395 | F45: 6435 | G45: 9368 | H45: 12547 | I45: 2816 | J45: 5602 | K45: 8354 | L45: 11056 | M45: 2666 | N45: 5463 | O45: 8295 | P45: 11284 | Q45: 2697 | R45: 5434 | S45: 8239 | T45: 11104 | U45: 2916 | V45: 5814 | W45: 8866
A46: SBC | E46: 1559 | F46: 3073 | G46: 4569 | H46: 6068 | I46: 1710 | J46: 3407 | K46: 5105 | L46: 6829 | M46: 2020 | N46: 4001 | O46: 5961 | P46: 7906 | Q46: 2265 | R46: 4517 | S46: 6760 | T46: 9038 | U46: 2905 | V46: 5591 | W46: 8208
A47: Other SBC | E47: 1318 | F47: 1037 | G47: 2325 | H47: 2036 | I47: 1377 | J47: 1136 | K47: 2804 | L47: 2754 | M47: 2861 | N47: 3160 | O47: 5855 | P47: 6556 | Q47: 2888 | R47: 3218 | S47: 5915 | T47: 6223 | U47: 2316 | V47: 2734 | W47: 5119
A48: Capex | E48: 3355 | F48: 5718 | G48: 7718 | H48: 10495 | I48: 2107 | J48: 3960 | K48: 5525 | L48: 7309 | M48: 3500 | N48: 5769 | O48: 7862 | P48: 11085 | Q48: 2803 | R48: 5317 | S48: 7419 | T48: 10708 | U48: 3787 | V48: 6703 | W48: 8796
A49: Divs | E49: 3568 | F49: 7011 | G49: 10640 | H49: 14119 | I49: 3539 | J49: 6914 | K49: 10570 | L49: 14081 | M49: 3613 | N49: 7060 | O49: 10827 | P49: 14467 | Q49: 3732 | R49: 7327 | S49: 11138 | T49: 14841 | U49: 3768 | V49: 7418 | W49: 11267
A50: Repurch | E50: 8796 | F50: 32498 | G50: 49463 | H50: 66897 | I50: 20706 | J50: 39280 | K50: 55171 | L50: 72358 | M50: 24775 | N50: 43323 | O50: 66223 | P50: 85971 | Q50: 20478 | R50: 43109 | S50: 64974 | T50: 89402 | U50: 19475 | V50: 39069 | W50: 56547
A52: DA | E52: =E45 -> 3395 | F52: =F45-E45 -> 3040 | G52: =G45-F45 -> 2933 | H52: =H45-G45 -> 3179 | I52: =I45 -> 2816 | J52: =J45-I45 -> 2786 | K52: =K45-J45 -> 2752 | L52: =L45-K45 -> 2702 | M52: =M45 -> 2666 | N52: =N45-M45 -> 2797 | O52: =O45-N45 -> 2832 | P52: =P45-O45 -> 2989 | Q52: =Q45 -> 2697 | R52: =R45-Q45 -> 2737 | S52: =S45-R45 -> 2805 | T52: =T45-S45 -> 2865 | U52: =U45 -> 2916 | V52: =V45-U45 -> 2898 | W52: =W45-V45 -> 3052 | X52: 3262 | Z52: =SUM(E52:H52) -> 12547 | AA52: =SUM(I52:L52) -> 11056 | AB52: =SUM(M52:P52) -> 11284 | AC52: =SUM(Q52:T52) -> 11104
A53: SBC | E53: =E46 -> 1559 | F53: =F46-E46 -> 1514 | G53: =G46-F46 -> 1496 | H53: =H46-G46 -> 1499 | I53: =I46 -> 1710 | J53: =J46-I46 -> 1697 | K53: =K46-J46 -> 1698 | L53: =L46-K46 -> 1724 | M53: =M46 -> 2020 | N53: =N46-M46 -> 1981 | O53: =O46-N46 -> 1960 | P53: =P46-O46 -> 1945 | Q53: =Q46 -> 2265 | R53: =R46-Q46 -> 2252 | S53: =S46-R46 -> 2243 | T53: =T46-S46 -> 2278 | U53: =U46 -> 2905 | V53: =V46-U46 -> 2686 | W53: =W46-V46 -> 2617 | Z53: =SUM(E53:H53) -> 6068 | AA53: =SUM(I53:L53) -> 6829 | AB53: =SUM(M53:P53) -> 7906 | AC53: =SUM(Q53:T53) -> 9038
A54: Other SBC | E54: =E47 -> 1318 | F54: =F47-E47 -> -281 | G54: =G47-F47 -> 1288 | H54: =H47-G47 -> -289 | I54: =I47 -> 1377 | J54: =J47-I47 -> -241 | K54: =K47-J47 -> 1668 | L54: =L47-K47 -> -50 | M54: =M47 -> 2861 | N54: =N47-M47 -> 299 | O54: =O47-N47 -> 2695 | P54: =P47-O47 -> 701 | Q54: =Q47 -> 2888 | R54: =R47-Q47 -> 330 | S54: =S47-R47 -> 2697 | T54: =T47-S47 -> 308 | U54: =U47 -> 2316 | V54: =V47-U47 -> 418 | W54: =W47-V47 -> 2385 | Z54: =SUM(E54:H54) -> 2036 | AA54: =SUM(I54:L54) -> 2754 | AB54: =SUM(M54:P54) -> 6556 | AC54: =SUM(Q54:T54) -> 6223
A55: Capex | E55: =E48 -> 3355 | F55: =F48-E48 -> 2363 | G55: =G48-F48 -> 2000 | H55: =H48-G48 -> 2777 | I55: =I48 -> 2107 | J55: =J48-I48 -> 1853 | K55: =K48-J48 -> 1565 | L55: =L48-K48 -> 1784 | M55: =M48 -> 3500 | N55: =N48-M48 -> 2269 | O55: =O48-N48 -> 2093 | P55: =P48-O48 -> 3223 | Q55: =Q48 -> 2803 | R55: =R48-Q48 -> 2514 | S55: =S48-R48 -> 2102 | T55: =T48-S48 -> 3289 | U55: =U48 -> 3787 | V55: =V48-U48 -> 2916 | W55: =W48-V48 -> 2093 | Z55: =SUM(E55:H55) -> 10495 | AA55: =SUM(I55:L55) -> 7309 | AB55: =SUM(M55:P55) -> 11085 | AC55: =SUM(Q55:T55) -> 10708
A56: Divs | E56: =E49 -> 3568 | F56: =F49-E49 -> 3443 | G56: =G49-F49 -> 3629 | H56: =H49-G49 -> 3479 | I56: =I49 -> 3539 | J56: =J49-I49 -> 3375 | K56: =K49-J49 -> 3656 | L56: =L49-K49 -> 3511 | M56: =M49 -> 3613 | N56: =N49-M49 -> 3447 | O56: =O49-N49 -> 3767 | P56: =P49-O49 -> 3640 | Q56: =Q49 -> 3732 | R56: =R49-Q49 -> 3595 | S56: =S49-R49 -> 3811 | T56: =T49-S49 -> 3703 | U56: =U49 -> 3768 | V56: =V49-U49 -> 3650 | W56: =W49-V49 -> 3849 | Z56: =SUM(E56:H56) -> 14119 | AA56: =SUM(I56:L56) -> 14081 | AB56: =SUM(M56:P56) -> 14467 | AC56: =SUM(Q56:T56) -> 14841
A57: Repurch | E57: =E50 -> 8796 | F57: =F50-E50 -> 23702 | G57: =G50-F50 -> 16965 | H57: =H50-G50 -> 17434 | I57: =I50 -> 20706 | J57: =J50-I50 -> 18574 | K57: =K50-J50 -> 15891 | L57: =L50-K50 -> 17187 | M57: =M50 -> 24775 | N57: =N50-M50 -> 18548 | O57: =O50-N50 -> 22900 | P57: =P50-O50 -> 19748 | Q57: =Q50 -> 20478 | R57: =R50-Q50 -> 22631 | S57: =S50-R50 -> 21865 | T57: =T50-S50 -> 24428 | U57: =U50 -> 19475 | V57: =V50-U50 -> 19594 | W57: =W50-V50 -> 17478 | Z57: =SUM(E57:H57) -> 66897 | AA57: =SUM(I57:L57) -> 72358 | AB57: =SUM(M57:P57) -> 85971 | AC57: =SUM(Q57:T57) -> 89402
J63: -1
