Workbook
Name Benchmark: [1]ControlsH!$B$3
Name BestConsOv: #REF!
Name Broker_Name: OFFSET(#REF!,0,0,[1]ControlsH!$E$5, 1)
Name calCODE: [1]ControlsH!$C$4
Name Chart_Benchmark_100_Size: OFFSET(#REF!, 0, 0, [1]ControlsH!$E$3, 1)
Name Chart_Date_Size: OFFSET(#REF!, 0, 0, [1]ControlsH!$E$3, 1)
Name Chart_Date_VAL1_Size: OFFSET(#REF!, 0, 0, [1]ControlsH!$I$3, 1)
Name Chart_Date_VAL2_Size: OFFSET(#REF!, 0, 0, [1]ControlsH!$I$5, 1)
Name Chart_Peer_100_Size: OFFSET(#REF!, 0, 0, [1]ControlsH!$E$3, 1)
Name Chart_Price_100_Size: OFFSET(#REF!, 0, 0, [1]ControlsH!$E$3, 1)
Name Chart_Price_Size: OFFSET(#REF!, 0, 0, [1]ControlsH!$E$3, 1)
Name Chart_VAL1_FY1_Size: OFFSET(#REF!, 0, 0, [1]ControlsH!$F$3, 1)
Name Chart_VAL1_FY2_Size: OFFSET(#REF!, 0, 0, [1]ControlsH!$G$3, 1)
Name Chart_VAL1_FY3_Size: OFFSET(#REF!, 0, 0, [1]ControlsH!$H$3, 1)
Name Chart_VAL2_FY1_Size: OFFSET(#REF!, 0, 0, [1]ControlsH!$F$5, 1)
Name Chart_VAL2_FY2_Size: OFFSET(#REF!, 0, 0, [1]ControlsH!$G$5, 1)
Name Chart_VAL2_FY3_Size: OFFSET(#REF!, 0, 0, [1]ControlsH!$H$5, 1)
Name Chart_Volume_Size: OFFSET(#REF!, 0, 0, [1]ControlsH!$E$3, 1)
Name compNAME: [1]ControlsH!$B$6
Name CURRENCY: [1]ControlsH!$B$9
Name currPRICE: [1]Overview!$E$19
Name custBenchmark: [1]Overview!$C$9
Name custED: #REF!
Name custSD: #REF!
Name dayCODE: [1]ControlsH!$C$5
Name ED: [1]ControlsH!$B$5
Name ESTBrokersItem: #REF!
Name ESTBrokersPeriod: #REF!
Name ESTDetailBroker: #REF!
Name ESTDetailBroker2: #REF!
Name ESTDetailPeriod: #REF!
Name EstDetPerO: #REF!
Name EstDetPerT: #REF!
Name FinancialsPeriod: #REF!
Name fundTICKER: [1]ControlsH!$B$15
Name GraphValRatio1: #REF!
Name GraphValRatio2: #REF!
Name Index1: #REF!
Name Lang: [1]Overview!$D$11
Name newCrncy: [1]ControlsH!$B$21:$B$199
Name newEstBrokerPeriod: #REF!
Name newEstBrokersItem: #REF!
Name newEstDetailBroker: #REF!
Name newEstDetailBroker2: #REF!
Name newEstDetailPeriod: #REF!
Name newFinancialsPeriod: #REF!
Name newOverviewCon: #REF!
Name newOverviewYear: #REF!
Name newOwners: #REF!
Name newPeersRatio: #REF!
Name newPeriod: #REF!
Name newValRatio1: #REF!
Name newValRatio2: #REF!
Name OverviewValRatioPeriod: [1]Overview!$D$30
Name PeerDate1: [1]Peers!$S$11
Name peerHist1: #REF!
Name PeerIndex: [1]ControlsH!$F$35:$F$36
Name Peers: OFFSET([1]Peers!$C$18,0,0,MAX(COUNTA([1]Peers!$C$18:$C$47),1),1)
Name peersWEIGHT: [1]ControlsH!$B$13
Name PERIODICITY: [1]ControlsH!$C$3

Sheet OP
B2: 45728 | C2: Analista: Research | D2: Report (quarter): 26/11/2024 | E2: DICK'S Sporting Goods, Inc. | K2: NYSE | L2: SIC: Sí
D3: DESCRIPTION: Dick’s Sporting Goods is a leading U.S. retailer offering sports equipment, apparel, and footwear, catering to athletes and outdoor enthusiasts. Founded in 1948, it operates hundreds of stores nationwide.
D4: Lauren R. Hobart (55 yo; dir. s. 2018; Pres. & CEO; ex Senior VP and CMO), Edward W. Stack (69 yo; Ch; dir. s. 1984; ex CEO), William J. Colombo (68 yo; dir. s. 2002; Vice Ch; ex Pres. & COO), Mark J. Barrenechea (59 yo; dir. s. 2014; CEO & CTO OpenText Corp.), Emanuel Chirico (66 yo; dir. s. 2003; ex Ch & CEO PVH Corp.), Robert W. Eddy (51 yo; dir. s. 2023; Ch, Pres & CEO BJ's Wholesale Club Holdings, Inc.), Anne Fink (60 yo; dir. s. 2019; Pres. Global Foodservice PepsiCo, Inc.), Larry Fitzgerald Jr. (40 yo; dir. s. 2020; Pres. Larry Fitzgerald Enterprises), Sandeep Mathrani (61 yo; dir. s. 2020; dir. Sycamore Partners; ex CEO WeWork), Desiree Ralls-Morrison (57 yo; dir. s. 2020; Exec. VP McDonald's Corporation), Lawrence J. Schorr (70 yo; dir. s. 1985; Lead dir. DICK's Sporting Goods, Inc.; Deputy Ch SURTECO North America), Larry D. Stone (72 yo; dir. s. 2007; ex Pres. & COO Lowe's Companies Inc.)
B5: Millones de USD
B6: Acción | D6: Liquidez y Solvencia | F6: =Segments!B2 -> Regions (2023) | I6: Rentabilidad (2022) | K6: Múltiplos
B7: Último Precio | C7: 198.97 | D7: Activo: | E7: =Cifras_en_Millones!C45 -> 9311.752 | H7: %Vts; %Op.Mg.; D | I7: Año termina: | J7: 44954 | K7: Float: | L7: 0.963
B8: Outstanding Shares | C8: 81470000 | D8: Pasivo: | E8: =Cifras_en_Millones!C57 -> 6694.077 | F8: =Segments!B4 -> United States | H8: =+Segments!I4 -> 100%; 1.0%; 5% | K8: Insiders Own: | L8: 0.0379
B9: Market Cap. | C9: =C7*C8/1000000 -> 16210.086 | D9: Cash/Precio | E9: =1000000*C11/C8 -> 22.108997 | I9: EBIT | J9: 1478.968 | K9: b (Bloomberg; Yahoo) | L9: 1.6
B10: +Deuda Total | C10: 4263.83 | D10: Ebidta/CIF | E10: =Cifras_en_Millones!C19/Cifras_en_Millones!C14 -> 12.854742 | I10: +Dep&Amort | J10: =Cifras_en_Millones!D17 -> 375 | K10: Calificación (S&P) | L10: BBB
B11: -Cash | C11: =Cifras_Originales!C22 -> 1801.22 | D11: Deuda/Ebidta | E11: =OP!C10/Cifras_en_Millones!C19 -> 2.4088101 | I11: =EBIDTA | J11: =J9+J10 -> 1853.968 | K11: Precio/Valor en libros | L11: =((C7*C8)/1000000)/(E7-E8) -> 6.192551
B12: =Enterprise Value | C12: =C9+C10-C11 -> 18672.696 | D12: "Otros activos"/Activo | E12: =Cifras_en_Millones!C44/Cifras_en_Millones!C45 -> 0.31236839 | I12: Utilidad Neta | J12: =Cifras_en_Millones!D23 -> 1043 | K12: FNP(p)/Activos | L12: =J18/E7 -> 0.12603397
B13: Tenencia % (nac/int'l) | C13: - | D13: Deuda/Activo | E13: =C10/E7 -> 0.45789772 | F13: =Segments!B15 -> Products (2023) | I13: UPA | J13: =1000000*J12/C8 -> 12.802259 | K13: Precio/Utilidad(p) | L13: =C9/J17 -> 15.515615 | N13: =C10/J11 -> 2.2998401
B14: t liq. (Pos prom./Vol.) | C14: - | D14: Margen de Operación (p) | E14: =AVERAGE(Cifras_en_Millones!C11/Cifras_en_Millones!C5,Cifras_en_Millones!D11/Cifras_en_Millones!D5,Cifras_en_Millones!E11/Cifras_en_Millones!E5) -> 0.12751558 | H14: %Vts; D | I14: ROA | J14: =J12/E7 -> 0.112009 | K14: EV/Activos | L14: =C12/E7 -> 2.0052828
B15: % Short | C15: 0.0565 | D15: Margen neto (p) | E15: =AVERAGE(Cifras_en_Millones!C23/12984.399,Cifras_en_Millones!D23/12368.198,Cifras_en_Millones!E23/12293.368) -> 0.096186925 | F15: =Segments!B17 -> Hardlines | H15: =+Segments!I17 -> 38%; NA; -1% | I15: ROIC | J15: =J12/(E7-(E8-C10)) -> 0.15156568 | K15: EV/Ebidta (p) | L15: =C12/J16 -> 15.457248
B16: Semáforo ESG | D16: Ebidta/Ingresos(p) | E16: =AVERAGE(Cifras_en_Millones!C19/12984.399,Cifras_en_Millones!D19/12368.198,Cifras_en_Millones!E19/12293.368) -> 0.15980005 | F16: =Segments!B18 -> Apparel | H16: =+Segments!I18 -> 33%; NA; 3% | I16: Ebidta(p) | J16: =AVERAGE(Cifras_en_Millones!B19:D19) -> 1208.022 | K16: Precio/FNP (p) | L16: =C9/J18 -> 13.812309
B17: E | D17: CIF/Deuda Neta Promedio | E17: =Cifras_en_Millones!C14/AVERAGE(Cifras_en_Millones!C59:M59) -> 0.058763075 | F17: =Segments!B19 -> Footwear | H17: =+Segments!I19 -> 26%; NA; 14% | I17: Utilidad Neta (p) | J17: =AVERAGE(Cifras_en_Millones!B23:D23) -> 1044.7595 | K17: Bonos 1;5;40a (USD) | L17: 4.0%; 4.4%; 5% | N17: 12
B18: S | F18: =Segments!B20 -> Other | H18: =+Segments!I20 -> 3%; NA; 60% | I18: FNP (p) | J18: =SUM(F35:F37)/3 -> 1173.5971 | K18: TDY(p)/Precio | L18: =SUM(E35:E37)/(3*C9) -> 0.069455488
B19: G | I19: Tax (p) últ. 5a | J19: 0.16 | K19: Div. Yield: | L19: =K33/C9 -> 0.010061637
B20: Tesis de inversión | H20: Acuerdo | I20: Supuestos de valuación | L20: DCF Value
B21: Investment in e-commerce - The company has successfully integrated online and offline sales, with a variety of options for customer shopping. Investments in technology enhance efficiency and position DICK’S well for future retail trends. Growing demand for sporting goods - With the population's increased purchasing power and its growing interest in sporting goods, the company's revenue is expected to grow. | H21: Mantener sin elevar posición | I21: VER DCF | L21: =DCFF!D66 -> 143.81382
B23: KSF | H23: PO / Precio Stand By | L23: =DCFF!D65 -> -0.27720855
B24: Sensitivity to economy downturns - Sportings goods are not an essential good. Therefore, in case of a lower disposable income due to unfortunate economic circumstances, clients will buy less sporting goods. Supply chain problems - Increased protectionist measures by the USA and the continuation of wars and political tensions may impact the company's supply chain, resulting in a decrease in revenues. | H24: =DCFF!D71 -> 0 | I24: Tasa de descuento: | J24: =DCFF!D47 -> 0.09 | K24: HOLD
B25: Año | C25: Ingresos | D25: Margen Operativo | E25: Div.+Recompra | F25: FNP | G25: Deuda/Activo | H25: Depreciación | I25: Capex + Adq | J25: Cash Flow
B26: 2012 | C26: 5836 | D26: =Cifras_Originales!N8/OP!C26 -> 0.089731666 | E26: =Cifras_Originales!N17+Cifras_Originales!N18 -> 307.1934 | F26: 652 | G26: =(Cifras_Originales!N32+Cifras_Originales!N36)/Cifras_Originales!N27 -> 0.29548581 | H26: =Cifras_Originales!N11 -> 125.096 | I26: =Cifras_Originales!N13 -> 258 | K26: 2022 | L26: =K26-1 -> 2021
B27: =B26+1 -> 2013 | C27: 6213 | D27: =Cifras_en_Millones!M11/OP!C27 -> 0.086401416 | E27: =Cifras_en_Millones!M37 -> 214.468 | F27: =Cifras_en_Millones!M30 -> 396.199 | G27: =Cifras_en_Millones!M59/Cifras_en_Millones!M45 -> 0.23166792 | H27: =Cifras_en_Millones!M17 -> 154.928 | I27: =Cifras_en_Millones!M35 -> 285.668 | J27: Profit | K27: =Cifras_en_Millones!D23 -> 1043 | L27: =Cifras_en_Millones!E23 -> 1519.871 | N27: =C27/C26-1 -> 0.06459904 | O27: =D27/D26-1 -> -0.037113422
B28: =B27+1 -> 2014 | C28: 6814 | D28: =Cifras_en_Millones!L11/OP!C28 -> 0.081311858 | E28: =Cifras_en_Millones!L37 -> 61.324063 | F28: =Cifras_en_Millones!L30 -> 101.27206 | G28: =Cifras_en_Millones!L59/Cifras_en_Millones!L45 -> 0.22562786 | H28: =Cifras_en_Millones!L17 -> 179.431 | I28: =Cifras_en_Millones!L35 -> 349.007 | J28: Cash Flow from Operations (BWC) | K28: 921.881 | L28: 1616.872 | N28: =C28/C27-1 -> 0.096732657 | O28: =D28/D27-1 -> -0.058905961 | P28: =E28/E27-1 -> -0.71406427 | Q28: =F28/F27-1 -> -0.74439092 | R28: =H28/H27-1 -> 0.15815734 | S28: =I28/I27-1 -> 0.22172242 | BT28: 4303
B29: =B28+1 -> 2015 | C29: 7271 | D29: =Cifras_en_Millones!K11/OP!C29 -> 0.073606382 | E29: =Cifras_en_Millones!K37 -> 122.08546 | F29: =Cifras_en_Millones!K30 -> 19.342465 | G29: =Cifras_en_Millones!K59/Cifras_en_Millones!K45 -> 0.25289296 | H29: =Cifras_en_Millones!K17 -> 193.594 | I29: =Cifras_en_Millones!K35 -> 370.028 | J29: Working Capital | K29: =Cifras_en_Millones!D18 -> 359.155 | L29: =Cifras_en_Millones!E18 -> -248.731 | N29: =C29/C28-1 -> 0.067067802 | O29: =D29/D28-1 -> -0.094764486 | P29: =E29/E28-1 -> 0.99082478 | Q29: =F29/F28-1 -> -0.80900493 | R29: =H29/H28-1 -> 0.078932849 | S29: =I29/I28-1 -> 0.060230884 | BT29: 3066
B30: =B29+1 -> 2016 | C30: 7922 | D30: =Cifras_en_Millones!J11/OP!C30 -> 0.056785408 | E30: =Cifras_en_Millones!J37 -> 97.931005 | F30: =Cifras_en_Millones!J30 -> 143.772 | G30: =Cifras_en_Millones!J59/Cifras_en_Millones!J45 -> 0.25467068 | H30: =Cifras_en_Millones!J17 -> 233.834 | I30: =Cifras_en_Millones!J35 -> 242 | J30: Investing Activities | K30: -392.894 | L30: -343.979 | N30: =C30/C29-1 -> 0.089533764 | O30: =D30/D29-1 -> -0.22852603 | P30: =E30/E29-1 -> -0.19784878 | Q30: =F30/F29-1 -> 6.4329722 | R30: =H30/H29-1 -> 0.20785768 | S30: =I30/I29-1 -> -0.34599544 | BT30: 3283
B31: =B30+1 -> 2017 | C31: 8590 | D31: =Cifras_en_Millones!I11/OP!C31 -> 0.055596508 | E31: =Cifras_en_Millones!I37 -> 115.705 | F31: =Cifras_en_Millones!I30 -> 52.181 | G31: =Cifras_en_Millones!I59/Cifras_en_Millones!I45 -> 0.28116417 | H31: =Cifras_en_Millones!I17 -> 237.651 | I31: =Cifras_en_Millones!I35 -> 372.6 | J31: Capex | K31: =Cifras_en_Millones!D33 -> 328 | L31: =Cifras_en_Millones!E33 -> 268.1 | N31: =C31/C30-1 -> 0.084322141 | O31: =D31/D30-1 -> -0.02093672 | P31: =E31/E30-1 -> 0.18149508 | Q31: =F31/F30-1 -> -0.6370573 | R31: =H31/H30-1 -> 0.016323546 | S31: =I31/I30-1 -> 0.53966942
B32: =B31+1 -> 2018 | C32: 8437 | D32: =Cifras_en_Millones!H11/OP!C32 -> 0.05271222 | E32: =Cifras_en_Millones!H37 -> 123.41161 | F32: =Cifras_en_Millones!H30 -> 135.81161 | G32: =Cifras_en_Millones!H59/Cifras_en_Millones!H45 -> 0.29445692 | H32: =Cifras_en_Millones!H17 -> 243.83 | I32: =Cifras_en_Millones!H35 -> 170.5 | J32: Adquisiones | K32: 0 | L32: 0 | N32: =C32/C31-1 -> -0.017811409 | O32: =D32/D31-1 -> -0.051878935 | P32: =E32/E31-1 -> 0.066605715 | Q32: =F32/F31-1 -> 1.6027024 | R32: =H32/H31-1 -> 0.026000311 | S32: =I32/I31-1 -> -0.54240472
B33: =B32+1 -> 2019 | C33: 8751 | D33: =Cifras_en_Millones!G11/OP!C33 -> 0.042922295 | E33: =Cifras_en_Millones!G37 -> 500.60078 | F33: =Cifras_en_Millones!G30 -> 456.29178 | G33: =Cifras_en_Millones!G59/Cifras_en_Millones!G45 -> 0.67402332 | H33: =Cifras_en_Millones!G17 -> 335.746 | I33: =Cifras_en_Millones!G35 -> 179.5 | J33: Dividends | K33: =Cifras_en_Millones!D27 -> 163.1 | L33: =Cifras_en_Millones!E27 -> 603 | N33: =C33/C32-1 -> 0.03721702 | O33: =D33/D32-1 -> -0.18572402 | P33: =E33/E32-1 -> 3.0563507 | Q33: =F33/F32-1 -> 2.3597405 | R33: =H33/H32-1 -> 0.37696756 | S33: =I33/I32-1 -> 0.052785924
B34: =B33+1 -> 2020 | C34: 9584.019 | D34: =Cifras_en_Millones!F11/OP!C34 -> 0.077365978 | E34: =Cifras_en_Millones!F37 -> 107.79947 | F34: =Cifras_en_Millones!F30 -> 1696.5225 | G34: =Cifras_en_Millones!F59/Cifras_en_Millones!F45 -> 0.4269029 | H34: =Cifras_en_Millones!F17 -> 326.014 | I34: =Cifras_en_Millones!F35 -> 175.8 | J34: Stock Repurchases | K34: =Cifras_en_Millones!D29 -> 426.7 | L34: =Cifras_en_Millones!E29 -> 1180 | N34: =C34/C33-1 -> 0.095191292 | O34: =D34/D33-1 -> 0.80246602 | P34: =E34/E33-1 -> -0.7846598 | Q34: =F34/F33-1 -> 2.7180649 | R34: =H34/H33-1 -> -0.028986198 | S34: =I34/I33-1 -> -0.020612813
B35: =B34+1 -> 2021 | C35: 12293.368 | D35: =Cifras_en_Millones!E11/OP!C35 -> 0.16549598 | E35: =Cifras_en_Millones!E37 -> 1787.6145 | F35: =Cifras_en_Millones!E30 -> 2772.7525 | G35: =Cifras_en_Millones!E59/Cifras_en_Millones!E45 -> 0.41827621 | H35: =Cifras_en_Millones!E17 -> 322.551 | I35: =Cifras_en_Millones!E35 -> 268.1 | J35: Endeudamiento Neto | K35: =Cifras_en_Millones!D59 -> 4025.142 | L35: =Cifras_en_Millones!E59 -> 3781.918 | N35: =C35/C34-1 -> 0.28269445 | O35: =D35/D34-1 -> 1.1391313 | P35: =E35/E34-1 -> 15.582776 | Q35: =F35/F34-1 -> 0.63437418 | R35: =H35/H34-1 -> -0.010622243 | S35: =I35/I34-1 -> 0.52502844
B36: =B35+1 -> 2022 | C36: 12368.198 | D36: =Cifras_en_Millones!D11/OP!C36 -> 0.11828878 | E36: =Cifras_en_Millones!D37 -> 589.07048 | F36: =Cifras_en_Millones!D30 -> -129.74852 | G36: =Cifras_en_Millones!D59/Cifras_en_Millones!D45 -> 0.44762614 | H36: =Cifras_en_Millones!D17 -> 375 | I36: =Cifras_en_Millones!D35 -> 328 | J36: Otros Financiemientos | K36: 0 | L36: 0 | N36: =C36/C35-1 -> 0.0060870219 | O36: =D36/D35-1 -> -0.28524684
B37: =B36+1 -> 2023 | C37: 12984.399 | D37: =Cifras_en_Millones!C11/OP!C37 -> 0.098761984 | E37: =Cifras_en_Millones!C37 -> 1000.9533 | F37: =Cifras_en_Millones!C30 -> 877.78728 | G37: =Cifras_en_Millones!C59/Cifras_en_Millones!C45 -> 0.46783355 | H37: =Cifras_en_Millones!C17 -> 393.933 | I37: =Cifras_en_Millones!C35 -> 520.4 | N37: =C37/C36-1 -> 0.049821405 | O37: =D37/D36-1 -> -0.1650773
B38: 2024 Est. | C38: =DCFF!H6 -> 13425.869 | D38: =DCFF!H7 -> 0.112
B39: CAGR | C39: =(C37/C32)^(1/5)-1 -> 0.090050857 | D39: =(D37/D26)^(1/11)-1 -> 0.0087552895 | J39: FX | K39: 0 | L39: 0
B40: AAG | C40: =AVERAGE(N27:N37) -> 0.077768653 | D40: =AVERAGE(O27:O37) -> 0.073947597 | J40: D Cash and Equivalents | K40: =K28+K29+K30+K33+K34+K35+K36+K39 -> 5503.084 | L40: =L28+L29+L30+L33+L34+L35+L36+L39 -> 6589.08
B41: CVAR | C41: =STDEV(C26:C37)/AVERAGE(C26:C37) -> 0.27369085 | D41: =STDEV(D26:D37)/AVERAGE(D26:D37) -> 0.40396024 | J41: Inv/D Vts | K41: =SUM(I33:I37)/(C37-C32) -> 0.32365755 | L41: =(SUM(I33:I37)-SUM(H33:H37))/(C37-C32) -> -0.061891204
B42: Último Año | C42: =C37/C36-1 -> 0.049821405 | D42: =D37/D36-1 -> -0.1650773 | J42: t inversiones; t adq. neto dep. | K42: =K41/E14 -> 2.5381804 | L42: =L41/E14 -> -0.4853619
B43: Pros | I43: (historical stock price of the company and its peers; source: Bloomberg)
B44: Strong Brand Recognition – DICK'S is a well-known and trusted brand in the sporting goods industry with a loyal customer base. Diverse Product Range – Offers a wide variety of sports equipment, apparel, and footwear, catering to different customer needs. Flexible Retail Strategy – Strong presence in both physical stores and e-commerce, allowing flexibility in customer shopping experiences.
B45: Cons
B46: High Dependence on U.S. Market – Limited international presence makes the company vulnerable to domestic economic fluctuations. High Operating Costs – Large physical store network leads to significant expenses related to maintenance, staffing, and logistics. Large Dependency on Asia – 89% of the company's factories are in Asia, making it's operations susceptible to economic and political changes in this region.
B47: Oportunidades
B48: Expansion into New Markets – Entering international markets or expanding e-commerce could increase revenue streams. Growing Demand for Athleisure – The rising popularity of athletic apparel as everyday wear presents an opportunity for growth. Technology Integration – Enhanced digital tools, such as AI-driven personalization and augmented reality shopping experiences, could improve customer engagement.
B49: Riesgos
B50: Intense Competition – Faces competition from major retailers like Amazon, Walmart, and other specialty sporting goods stores. Economic Downturns – Inflation or economic recessions may reduce consumer spending on non-essential goods like sporting equipment. Supply Chain Disruptions – Global supply chain challenges, including material shortages and shipping delays, can impact product availability and pricing.
B51: CHECKLIST
B52: Crecimiento | C52: Riesgos claros | D52: ESG | E52: Peer Analysis | F52: Consenso | G52: KSF | H52: PO/Stand By | I52: DICK's Sporting Goods (DKS); Hibbett Sports (HIBB); Academy Sports and Outdoors (ASO); Foot Locker (FL)
B53: (p) = Promedio de últimos 3 años
B54: NOTES:
B55: A class action lawsuit was filed against DICK’s Sporting Goods on February 16th, 2024. The shareholders alleged that they bought DICK’s Sporting Goods’ stock at artificially inflated prices between May 25, 2022, and August 21, 2023
B56: and are now seeking compensation for their financial losses.
B57: The company has also had to face many lawsuits due to wage and working hours violations and workplace safety and health violations.

Sheet Segments
B2: Regions (2023)
C3: 2023 | D3: =C3-1 -> 2022 | E3: Ut. Operativa | F3: % Vts | G3: Margen | H3: Crec
B4: United States | C4: =+Cifras_en_Millones!C5 -> 12984.399 | D4: =+Cifras_en_Millones!D5 -> 12368.198 | E4: 1282.4 | F4: =+C4/$C$27 -> 1 | G4: =+E4/C14 -> 0.098764679 | H4: =+C4/D4-1 -> 0.049821405 | I4: =IF(C4="","",IF(F4=0,"NA",TEXT(F4,"0%"))&"; "&IF(G4=0,"NA",TEXT(G4,"0.0%"))&"; "&IF(H4=0,"NA",TEXT(H4,"0%"))) -> 100%; 1.0%; 5%
I5: =IF(C5="","",IF(F5=0,"NA",TEXT(F5,"0%"))&"; "&IF(G5=0,"NA",TEXT(G5,"0.0%"))&"; "&IF(H5=0,"NA",TEXT(H5,"0%")))
I6: =IF(C6="","",IF(F6=0,"NA",TEXT(F6,"0%"))&"; "&IF(G6=0,"NA",TEXT(G6,"0.0%"))&"; "&IF(H6=0,"NA",TEXT(H6,"0%")))
I7: =IF(C7="","",IF(F7=0,"NA",TEXT(F7,"0%"))&"; "&IF(G7=0,"NA",TEXT(G7,"0.0%"))&"; "&IF(H7=0,"NA",TEXT(H7,"0%")))
I8: =IF(C8="","",IF(F8=0,"NA",TEXT(F8,"0%"))&"; "&IF(G8=0,"NA",TEXT(G8,"0.0%"))&"; "&IF(H8=0,"NA",TEXT(H8,"0%")))
I9: =IF(C9="","",IF(F9=0,"NA",TEXT(F9,"0%"))&"; "&IF(G9=0,"NA",TEXT(G9,"0.0%"))&"; "&IF(H9=0,"NA",TEXT(H9,"0%")))
I10: =IF(C10="","",IF(F10=0,"NA",TEXT(F10,"0%"))&"; "&IF(G10=0,"NA",TEXT(G10,"0.0%"))&"; "&IF(H10=0,"NA",TEXT(H10,"0%")))
I11: =IF(C11="","",IF(F11=0,"NA",TEXT(F11,"0%"))&"; "&IF(G11=0,"NA",TEXT(G11,"0.0%"))&"; "&IF(H11=0,"NA",TEXT(H11,"0%")))
I12: =IF(C12="","",IF(F12=0,"NA",TEXT(F12,"0%"))&"; "&IF(G12=0,"NA",TEXT(G12,"0.0%"))&"; "&IF(H12=0,"NA",TEXT(H12,"0%")))
I13: =IF(C13="","",IF(F13=0,"NA",TEXT(F13,"0%"))&"; "&IF(G13=0,"NA",TEXT(G13,"0.0%"))&"; "&IF(H13=0,"NA",TEXT(H13,"0%")))
B14: TOTAL | C14: =SUM(C4:C12) -> 12984.399 | D14: =SUM(D4:D12) -> 12368.198 | E14: =SUM(E4:E13) -> 1282.4 | F14: =C14/SUM($C$4:$C$13) -> 1 | G14: =E14/C14 -> 0.098764679 | H14: =C14/D14-1 -> 0.049821405
B15: Products (2023)
C16: 2023 | D16: =C16-1 -> 2022 | E16: Ut. Op. | F16: % Vts | G16: Margen | H16: Crec
B17: Hardlines | C17: =+C198 -> 4915.5 | D17: 4952.2 | E17: NA | F17: =+C17/$C$27 -> 0.3785697 | G17: NA | H17: =+C17/D17-1 -> -0.0074108477 | I17: =IF(C17="","",IF(F17=0,"NA",TEXT(F17,"0%"))&"; "&IF(G17=0,"NA",TEXT(G17,"0.0%"))&"; "&IF(H17=0,"NA",TEXT(H17,"0%"))) -> 38%; NA; -1%
B18: Apparel | C18: =+Segments!C200 -> 4329.8 | D18: 4218.1 | E18: NA | F18: =+C18/$C$27 -> 0.33346172 | G18: NA | H18: =+C18/D18-1 -> 0.026481117 | I18: =IF(C18="","",IF(F18=0,"NA",TEXT(F18,"0%"))&"; "&IF(G18=0,"NA",TEXT(G18,"0.0%"))&"; "&IF(H18=0,"NA",TEXT(H18,"0%"))) -> 33%; NA; 3%
B19: Footwear | C19: =+C202 -> 3388.7 | D19: 2979.1 | E19: NA | F19: =+C19/$C$27 -> 0.26098243 | G19: NA | H19: =+C19/D19-1 -> 0.13749119 | I19: =IF(C19="","",IF(F19=0,"NA",TEXT(F19,"0%"))&"; "&IF(G19=0,"NA",TEXT(G19,"0.0%"))&"; "&IF(H19=0,"NA",TEXT(H19,"0%"))) -> 26%; NA; 14%
B20: Other | C20: =+C204 -> 350.4 | D20: 218.8 | E20: NA | F20: =+C20/$C$27 -> 0.026986232 | G20: NA | H20: =+C20/D20-1 -> 0.60146252 | I20: =IF(C20="","",IF(F20=0,"NA",TEXT(F20,"0%"))&"; "&IF(G20=0,"NA",TEXT(G20,"0.0%"))&"; "&IF(H20=0,"NA",TEXT(H20,"0%"))) -> 3%; NA; 60%
E21: =+E4 -> 1282.4 | I21: =IF(C21="","",IF(F21=0,"NA",TEXT(F21,"0%"))&"; "&IF(G21=0,"NA",TEXT(G21,"0.0%"))&"; "&IF(H21=0,"NA",TEXT(H21,"0%")))
I22: =IF(C22="","",IF(F22=0,"NA",TEXT(F22,"0%"))&"; "&IF(G22=0,"NA",TEXT(G22,"0.0%"))&"; "&IF(H22=0,"NA",TEXT(H22,"0%")))
I23: =IF(C23="","",IF(F23=0,"NA",TEXT(F23,"0%"))&"; "&IF(G23=0,"NA",TEXT(G23,"0.0%"))&"; "&IF(H23=0,"NA",TEXT(H23,"0%")))
I24: =IF(C24="","",IF(F24=0,"NA",TEXT(F24,"0%"))&"; "&IF(G24=0,"NA",TEXT(G24,"0.0%"))&"; "&IF(H24=0,"NA",TEXT(H24,"0%")))
I25: =IF(C25="","",IF(F25=0,"NA",TEXT(F25,"0%"))&"; "&IF(G25=0,"NA",TEXT(G25,"0.0%"))&"; "&IF(H25=0,"NA",TEXT(H25,"0%")))
I26: =IF(C26="","",IF(F26=0,"NA",TEXT(F26,"0%"))&"; "&IF(G26=0,"NA",TEXT(G26,"0.0%"))&"; "&IF(H26=0,"NA",TEXT(H26,"0%")))
B27: TOTAL | C27: =+Cifras_en_Millones!C5 -> 12984.399 | D27: =+Cifras_en_Millones!D5 -> 12368.198 | E27: =SUM(E17:E26) -> 1282.4 | F27: =C27/SUM(C17:C26) -> 0.99999992 | G27: =E27/C27 -> 0.098764679 | H27: =C27/D27-1 -> 0.049821405
L29: 45622
B30: Factories By Region: | C30: % | L30: Question by:
B31: Asia | C31: 0.89 | L31: Adrienne Yih, Analyst at Barclays Capital, Inc. :
B32: North America | C32: 0.05 | L32: I guess officially the Tariff Man has come up. So, we had an update
B33: Latin America | C33: 0.04 | L33: yesterday evening, 25% Canada, Mexico and obviously the 10% in China. Historically, you've already told us that
B34: EMEA | C34: 0.02 | L34: you don't have much exposure. But for the private label, so can you just update us? I'm assuming that this doesn't
B35: 9% of factories based on High-risk countries based on BSCI criteria | L35: change the answer that you've given us before, but just remind us now that we have some quazi-official numbers.
B36: % of Factories Doesn't correlate to Production % | L36: How are you thinking about that? Thank you.
L37: Navdeep Gupta, Executive Vice President & Chief Financial Officer, Dick's Sporting Goods, Inc. :
L38: In terms of tariffs, I think so I would
D39: (See Comment) | L39: say does that a slightly more information is known. We still don't know about the timing and likely – the categories
B40: 39 Weeks Ended Nov 2, 2024 | C40: DKS | D40: Specialty Concept Stores | E40: Total | L40: that would be impacted. So, still a lot to be learned more, but like you said, we have navigated the situation back
B41: Beginning Stores | C41: 724 | D41: 131 | E41: 855 | L41: in 2018, 2019 effectively as well. Vertical brands perspective, we have a very small or actually very, very
B42: Q1 New Stores | C42: 1 | D42: 3 | E42: 4 | L42: negligible amount of exposure because we have diversified our supply chain, both from China as well as there's
B43: Q2 New Stores | C43: 2 | D43: 5 | E43: 7 | L43: not much of an exposure, even if you look into Mexico or Canada.
B44: Q3 New Stores | C44: 2 | D44: 1 | E44: 3
B45: Stores Acquired | C45: - | D45: - | E45: -
B46: Closed Stores | C46: 2 | D46: 3 | E46: 5
B47: Total Stores | C47: 727 | D47: 137 | E47: 864
B48: Relocated Stores | C48: 8 | D48: 3 | E48: 11
B53: Specialty Concept / Number of stores
B54: Golf Galaxy | C54: 109 | D54: Specialized Golf Equipment ans Services
B55: Field House | C55: 22 | D55: A next-generation format of the traditional 50,000 sq. ft. DICK's stores, inspired by the House of Sport concept.
B56: Going, Going, Gone! | C56: 20 | D56: Off-price stores offering discounts on footwear and apparel brands.
B57: House of Sports | C57: 17 | D57: 170000 Sq Ft turf Fielf, Rock Climbing Wall, Batting Cages, Golf Hitting Bays, Health and Wellness Destination
B58: Public Lands | C58: 8 | D58: Focuses on outdoor activities and gear, catering to enthusiasts of hiking, camping, and other outdoor sports.
E60: Only cells in blue are considered Specialty Concept Stores, despite that in practice all other mentioned stores are different from the main Dicks Sporting Goods store
B62: Specialty Concept Stores generate higher sales per square foot when compared to regular stores (no numbers are provided)
B75: State | C75: Total Stores | D75: Dick's Stores | E75: Dick's % | F75: Specialty Stores | G75: Specialty %
B76: California | C76: 64 | D76: 57 | E76: 6.67% | F76: 7 | G76: 0.82%
B77: Florida | C77: 57 | D77: 48 | E77: 5.61% | F77: 9 | G77: 1.05%
B78: Texas | C78: 57 | D78: 48 | E78: 5.61% | F78: 9 | G78: 1.05%
B79: Pennsylvania | C79: 49 | D79: 39 | E79: 4.56% | F79: 10 | G79: 1.17%
B80: Ohio | C80: 46 | D80: 36 | E80: 4.21% | F80: 10 | G80: 1.17%
B81: New York | C81: 46 | D81: 43 | E81: 5.03% | F81: 3 | G81: 0.35%
B82: North Carolina | C82: 38 | D82: 31 | E82: 3.63% | F82: 7 | G82: 0.82%
B83: Illinois | C83: 37 | D83: 32 | E83: 3.74% | F83: 5 | G83: 0.58%
B84: Virginia | C84: 33 | D84: 27 | E84: 3.16% | F84: 6 | G84: 0.70%
B85: Michigan | C85: 26 | D85: 21 | E85: 2.46% | F85: 5 | G85: 0.58%
B86: Georgia | C86: 26 | D86: 23 | E86: 2.69% | F86: 3 | G86: 0.35%
B87: New Jersey | C87: 23 | D87: 19 | E87: 2.22% | F87: 4 | G87: 0.47%
... B93: Wisconsin | C93: 17 | D93: 13 | E93: 1.52% | F93: 4 | G93: 0.47%
B94: Washington | C94: 16 | D94: 0 | E94: — | F94: 0 | G94: 0
B95: Missouri | C95: 15 | D95: 13 | E95: 1.52% | F95: 2 | G95: 0.23%
B96: Minnesota | C96: 14 | D96: 10 | E96: 1.17% | F96: 4 | G96: 0.47%
B97: Connecticut | C97: 14 | D97: 11 | E97: 1.29% | F97: 3 | G97: 0.35%
B98: South Carolina | C98: 14 | D98: 11 | E98: 1.29% | F98: 3 | G98: 0.35%
B99: Kentucky | C99: 14 | D99: 12 | E99: 1.40% | F99: 2 | G99: 0.23%
B100: Alabama | C100: 14 | D100: 13 | E100: 1.52% | F100: 1 | G100: 0.12%
B101: Arizona | C101: 12 | D101: 9 | E101: 1.05% | F101: 3 | G101: 0.35%
B102: Kansas | C102: 12 | D102: 10 | E102: 1.17% | F102: 2 | G102: 0.23%
B103: Oregon | C103: 12 | D103: 10 | E103: 1.17% | F103: 2 | G103: 0.23%
B104: Iowa | C104: 9 | D104: 7 | E104: 0.82% | F104: 2 | G104: 0.23%
B105: Oklahoma | C105: 9 | D105: 7 | E105: 0.82% | F105: 2 | G105: 0.23%
B106: Louisiana | C106: 8 | D106: 8 | E106: 0.94% | F106: 0 | G106: 0
B107: New Hampshire | C107: 7 | D107: 0 | E107: — | F107: 0 | G107: 0
B108: Mississippi | C108: 7 | D108: 0 | E108: — | F108: 0 | G108: 0
B109: Utah | C109: 7 | D109: 5 | E109: 0.58% | F109: 2 | G109: 0.23%
B110: Idaho | C110: 7 | D110: 6 | E110: 0.70% | F110: 1 | G110: 0.12%
B111: Nevada | C111: 6 | D111: 4 | E111: 0.47% | F111: 2 | G111: 0.23%
B112: West Virginia | C112: 6 | D112: 6 | E112: 0.70% | F112: 0 | G112: 0
B113: Arkansas | C113: 5 | D113: 4 | E113: 0.47% | F113: 1 | G113: 0.12%
B114: Nebraska | C114: 5 | D114: 4 | E114: 0.47% | F114: 1 | G114: 0.12%
B115: New Mexico | C115: 4 | D115: 0 | E115: — | F115: 0 | G115: 0
B116: Maine | C116: 4 | D116: 0 | E116: — | F116: 0 | G116: 0
B117: Delaware | C117: 4 | D117: 3 | E117: 0.35% | F117: 1 | G117: 0.12%
B118: Rhode Island | C118: 3 | D118: 2 | E118: 0.23% | F118: 1 | G118: 0.12%
B119: Vermont | C119: 2 | D119: 0 | E119: — | F119: 0 | G119: 0
B120: District of Columbia | C120: 1 | D120: 0 | E120: — | F120: 0 | G120: 0
B121: North Dakota | C121: 1 | D121: 0 | E121: — | F121: 0 | G121: 0
B122: Wyoming | C122: 1 | D122: 0 | E122: — | F122: 0 | G122: 0
B123: South Dakota | C123: 1 | D123: 0 | E123: — | F123: 0 | G123: 0
B187: Hardlines | C187: 4915.5 | D187: {=+C17:C20} -> 4915.5 | E187: {=+D17:D20} -> 4952.2 | F187: 4428.5
B188: Apparel | C188: 4329.8 | D188: 4329.8 | E188: 4218.1 | F188: 3180.2
...

Sheet COVID-19 impact
A1: https://www.apple.com/newsroom/2020/03/apples-covid-19-response/ | G1: https://glg.it/articles/how-might-the-wuhan-coronavirus-impact-apples-supply-chain/ | N1: https://www.cnbc.com/2020/02/18/the-significance-of-apples-coronavirus-warning.html
A2: March 13 | G2: January 29 | N2: Ferbuary 18
A23: Otros:
A24: https://www.macrumors.com/guide/covid-19-coronavirus/

Sheet Peers
A2: Multiplos (USD) | B2: (DKS) | C2: (HIBB) | D2: (ASO) | E2: (FL)
B3: (DICK´S Sporting Goods) | C3: (Hibbett Sports) | D3: (Academy Sports and Outdoors) | E3: (Foot Locker)
A4: Ventas | B4: 13,425.4M | C4: 1,703.0M | D4: 6,051.4M | E4: 8,124.0M
A5: Crecimiento (1S23/1S22) | B5: 0.0154 | C5: 0.0101 | D5: 0.0376 | E5: -0.0909
A6: Crecimiento (1S23/1S19) | B6: 0.369 | C6: 0.6927 | D6: 0.3704 | E6: 0.1604
A7: Deuda | B7: 122278 | C7: 82110 | D7: 26772 | E7: 100504
A8: Activos | B8: 323888 | C8: 301311 | D8: 319616 | E8: 321195
A9: Deuda/Activos | B9: =OP!C10/OP!E7 -> 0.45789772 | C9: 0.0513 | D9: 0.3513 | E9: 0.4131
A10: Deuda/EBITDA | B10: =OP!C10/OP!J11 -> 2.2998401 | C10: 0.2511 | D10: 2.5318 | E10: 8.488
A11: (Capex + Adq.)/Revenue | B11: =-DCFF!G22/DCFF!G6 -> 0.045240908 | C11: 0.0334 | D11: 0.0316 | E11: 0.0322
A12: ROA (p) | B12: =OP!J14 -> 0.112009 | C12: 0.1135 | D12: 0.0734 | E12: 0.0114
A13: ROIC (p) | B13: =OP!J15 -> 0.15156568 | C13: 0.1479 | D13: 0.1234 | E13: 0.044
A14: Margen Operativo | B14: =OP!D37 -> 0.098761984 | C14: 0.0792 | D14: 0.0971 | E14: 0.016
A15: Margen Operativo 2022 | B15: =OP!D36 -> 0.11828878 | C15: 0.135 | D15: 0.134 | E15: 0.1169
A16: Float | B16: =OP!L7 -> 0.963 | C16: 0.777 | D16: 0.9855 | E16: 0.679
A17: b | B17: =OP!L9 -> 1.6 | C17: 1.88 | D17: 1.37 | E17: 1.43
A18: Precio/Utilidad | B18: 17.18 | C18: 10.77 | D18: 8.58 | E18: 9.72
A19: Precio/Ventas | B19: 1.48 | C19: 0.63 | D19: 0.64 | E19: 0.22
A20: EV/Activos | B20: =OP!C12/OP!E7 -> 2.0052828 | C20: 2.71 | D20: 0.98 | E20: 0.63
A21: EV/Ebitda | B21: 12.5 | C21: 5.91 | D21: 6.86 | E21: 12.98
A22: Div. Yield: | B22: =OP!L19 -> 0.010061637 | C22: 0.011 | D22: 0.0067 | E22: 0.0385
B24: *Nota: Estos múltiplos no consideran el promedio de los últimos 3 años, únicamente valores del último año reportado
B25: **Cifras en USD
A27: (You can make up a table with different indicators in order to link them to the multiples/ratios. At the end, put the table unvisible with white color)

Sheet Acuerdo
A1: Invertir
A2: NO invertir
A3: Mantener sin elevar posición
A4: Mantener (y seguir comprando)
A5: Liquidar
A6: PENDIENTE

Sheet ESG
B2: Análisis ESG | J2: PARÁMETROS
C3: Impacto | D3: ¿Reporta? | E3: Ranking | F3: Mitigación | G3: Semáforo | H3: Comentarios | J3: IMPACTO | L3: RANKING | M3: MITIGACIÓN
B4: Ambiental | J4: NONE | K4: 0 | L4: "Best in class" | M4: Is there evidence of progam/plan/etc…
B5: Emisiones directas CO2 | C5: 2 | D5: Yes | E5: Medium | F5: Yes | H5: The firm has taken steps to reduce carbon emissions by optimizing its supply chain and investing in more energy-efficient logistics. | J5: LOW | K5: 1 | L5: Medium high
B6: Uso total de agua | C6: 1 | D6: Yes | E6: Best in class | F6: Yes | H6: The firm is one of the best in the industry regarding this metric. | J6: MEDIUM | K6: 2 | L6: Medium
B7: Total Energy Consumption | C7: 2 | D7: Yes | E7: Medium high | F7: No | H7: The company is committed to increasing energy efficiency across its stores, with some locations using LED lighting and other energy-saving technologies. | J7: HIGH | K7: 3 | L7: "Villain"
B8: Waste Management | C8: 1 | D8: Yes | E8: Medium high | F8: Yes | H8: The company has implemented recycling programs and is working to reduce plastic usage in packaging.
B9: Land Degradation/Deforestation/Biodiversity loss/Animal sufering/… | C9: 3 | D9: Yes | E9: Medium | F9: Yes | H9: Dick’s has policies to source sustainable products, including eco-friendly athletic wear and responsibly sourced outdoor gear. | J9: TRAFFIC LIGHTS
B10: Social
B11: % Rotación de empleados | C11: 3 | D11: Yes | E11: Medium High | F11: No | H11: The company does not disclose employee turnover %. Most employees do not stay with the company for more than a year.
B12: Sueldos y compensaciones | C12: 1 | D12: No | E12: Medium | F12: No | H12: The company offers medical, dental, vision, disability and life insurance, flexible paid time off programs covering parental and family leave and hybrid work arrangements.
B13: Temas de reputación | C13: 1 | D13: No | E13: Villain | F13: Yes | H13: The company has faced some lawsuits.
B14: Temas de discriminación | C14: 1 | D14: No | E14: Medium | F14: Yes | H14: Dick’s has been recognized for its diversity, equity, and inclusion (DEI) initiatives, ensuring fair hiring and promotion practices.
B15: Seguridad laboral | C15: 2 | D15: Yes | E15: Medium | F15: Yes | H15: The company applies required employee training and special training in stores that sell firearms. The company has suffered some cases of data breaching, which puts it employees at risk, though there have been investments in the improvement of cybersecurity protocols.
B16: Daños a la salud | C16: 3 | D16: No | E16: Villain | F16: Yes | H16: The company has faced lawsuits regarding this matter.
B17: PXP? | D17: Yes | E17: Medium high | F17: Yes | H17: The company offers a company-matched retirement savings 401K plan that vests immediately and is open for all teammates.
B18: Supply chain | C18: 3 | D18: Yes | E18: Medium high | F18: No | H18: The company had some ethical issues about sourcing policies to ensure suppliers follow labor practices.
B19: Community involvement | C19: 2 | D19: No | E19: Medium | F19: Yes | H19: Dick’s Sporting Goods Foundation supports youth sports through grants and donations.
B20: Public Sector | C20: 3 | D20: No | E20: Medium | F20: Yes | H20: The company rarely engages in advocacy related to sports policies and youth development.
B21: Litigios | C21: 2 | D21: No | E21: Medium | F21: Yes | H21: Dick’s has faced some legal disputes, including employment-related cases, but actively addresses compliance and workplace policies.
B22: Gobierno
B23: Diversidad (Género, edad, industria, región) | E23: Medium high | F23: Yes | H23: The company plans to achieve 50% female employees compared to the total workforce.
B24: % independientes | E24: Medium high | F24: Yes | H24: A portion of the board consists of independent directors to ensure balanced decision-making.
B25: tiempo promedio como consejeros independientes | E25: Medium | F25: No | H25: Board members serve standard terms with periodic reviews to bring fresh perspectives.
B26: Salidas recientes de consejeros/C-level executives? | E26: Medium | F26: No | H26: The company has experienced leadership changes, such as the transition of CEO Lauren Hobart in 2021
B27: CEO/Chairman | E27: Medium high | F27: No | H27: The CEO and Chairman roles are separate, reinforcing independent leadership.
B28: Transparencia (segmentos, fuente de riqueza, adquisiciones, otros) | E28: Medium | F28: No | H28: Dick’s provides clear financial reports and corporate social responsibility (CSR) disclosures.
B29: Tiempo que tardan en reportar luego del final del trimestre/año | E29: Medium | F29: No | H29: The company follows standard reporting timelines in compliance with SEC regulations.
B30: Participación adicional del CEO en otros consejos o excesiva del Ch. | E30: Medium | F30: No | H30: CEO involvement in external boards is balanced to ensure focus on the company.
B31: Auditoría/Consultoría | D31: No | E31: Medium | F31: Yes | H31: The company undergoes independent financial audits to maintain credibility.
B32: Esquemas de compensación al management | D32: No | E32: Villain | F32: Yes | H32: Executive pay is tied to performance metrics, with bonuses based on company success. However its rare that employees get a raise

Sheet DCF
A1: Discounted Cash Flow
A3: Ventas | E3: Margen Operativo
A16: Inversiones | E16: Utilidad Neta
D31: 0.001 | E31: =1/((1+$B$59+$D31)^(E35-2021)) -> 0.92250923 | F31: =1/((1+$B$59+$D31)^(F35-2021)) -> 0.85102327 | G31: =1/((1+$B$59+$D31)^(G35-2021)) -> 0.78507682 | H31: =1/((1+$B$59+$D31)^(H35-2021)) -> 0.72424061 | I31: =1/((1+$B$59+$D31)^(I35-2021)) -> 0.66811864 | J31: =1/((1+$B$59+$D31)^(J35-2021)) -> 0.61634561 | K31: =1/((1+$B$59+$D31)^(K35-2021)) -> 0.56858451 | L31: =1/((1+$B$59+$D31)^(L35-2021)) -> 0.52452446 | ... AC31: =1/((1+$B$59+$D31)^(AC35-2021)) -> 0.13312755
D32: 0.005 | E32: =1/((1+$B$59+$D32)^(E35-2021)) -> 0.91911765 | F32: =1/((1+$B$59+$D32)^(F35-2021)) -> 0.84477725 | G32: =1/((1+$B$59+$D32)^(G35-2021)) -> 0.77644968 | H32: =1/((1+$B$59+$D32)^(H35-2021)) -> 0.7136486 | I32: =1/((1+$B$59+$D32)^(I35-2021)) -> 0.65592702 | J32: =1/((1+$B$59+$D32)^(J35-2021)) -> 0.6028741 | K32: =1/((1+$B$59+$D32)^(K35-2021)) -> 0.55411223 | L32: =1/((1+$B$59+$D32)^(L35-2021)) -> 0.50929433 | ... AC32: =1/((1+$B$59+$D32)^(AC35-2021)) -> 0.12141647
D33: Normal | E33: =1/((1+$B$59)^(E35-2021)) -> 0.92336103 | F33: =1/((1+$B$59)^(F35-2021)) -> 0.8525956 | G33: =1/((1+$B$59)^(G35-2021)) -> 0.78725355 | H33: =1/((1+$B$59)^(H35-2021)) -> 0.72691926 | I33: =1/((1+$B$59)^(I35-2021)) -> 0.67120892 | J33: =1/((1+$B$59)^(J35-2021)) -> 0.61976816 | K33: =1/((1+$B$59)^(K35-2021)) -> 0.57226977 | L33: =1/((1+$B$59)^(L35-2021)) -> 0.5284116 | ... AC33: =1/((1+$B$59)^(AC35-2021)) -> 0.13623496
B35: 2019 (Real) | C35: 2020 (Real) | D35: 2021 | E35: =D35+1 -> 2022 | F35: =E35+1 -> 2023 | G35: =F35+1 -> 2024 | H35: =G35+1 -> 2025 | I35: =H35+1 -> 2026 | J35: =I35+1 -> 2027 | K35: =J35+1 -> 2028 | L35: =K35+1 -> 2029 | ... AC35: =AB35+1 -> 2046
A36: Crecimiento | B36: =OP!N34 -> 0.095191292 | C36: =OP!N35 -> 0.28269445 | D36: 0.35 | E36: 0.034 | F36: 0.095 | G36: 0.095 | H36: 0.095 | I36: 0.095 | J36: 0.095 | K36: 0.08 | L36: 0.06 | M36: 0.05 | N36: 0.04 | O36: 0.035 | P36: 0.035 | Q36: 0.035 | R36: 0.035 | S36: 0.035 | T36: 0.035 | U36: 0.035 | V36: 0.035 | W36: 0.035 | X36: 0.035 | Y36: 0.035 | Z36: 0.035 | AA36: 0.035 | AB36: 0.035 | AC36: 0.035
A37: Ventas | B37: =OP!C34 -> 9584.019 | C37: =OP!C35 -> 12293.368 | D37: =OP!C34*(1+D36) -> 12938.426 | E37: =D37*(1+E36) -> 13378.332 | F37: =E37*(1+F36) -> 14649.274 | G37: =F37*(1+G36) -> 16040.955 | H37: =G37*(1+H36) -> 17564.845 | I37: =H37*(1+I36) -> 19233.506 | J37: =I37*(1+J36) -> 21060.689 | K37: =J37*(1+K36) -> 22745.544 | L37: =K37*(1+L36) -> 24110.276 | ... AC37: =AB37*(1+AC36) -> 44109.291
A38: Margen Operativo | B38: =+OP!D34 -> 0.077365978 | C38: =+OP!D35 -> 0.16549598 | D38: =108166.4/365513.2 -> 0.29593022 | E38: =108162.8/377959.8 -> 0.28617541 | F38: 0.27 | G38: 0.275 | H38: 0.26 | I38: 0.255 | J38: 0.25 | K38: 0.25 | L38: 0.25 | M38: 0.25 | N38: 0.25 | O38: 0.25 | P38: 0.25 | Q38: 0.25 | R38: 0.25 | S38: 0.25 | T38: 0.25 | U38: 0.25 | V38: 0.25 | W38: 0.25 | X38: 0.25 | Y38: 0.25 | Z38: 0.25 | AA38: 0.25 | AB38: 0.25 | AC38: 0.25
A39: EBIT | B39: 63930 | C39: 66288 | D39: =D37*D38 -> 3828.8711 | E39: =E37*E38 -> 3828.5497 | F39: =F37*F38 -> 3955.3039 | G39: =G37*G38 -> 4411.2625 | H39: =H37*H38 -> 4566.8598 | I39: =I37*I38 -> 4904.5439 | J39: =J37*J38 -> 5265.1722 | K39: =K37*K38 -> 5686.386 | ... AC39: =AC37*AC38 -> 11027.323
A40: Dep&Amort | B40: =OP!H34 -> 326.014 | C40: =OP!H35 -> 322.551 | D40: 11000 | E40: =D40*(1+E36*$H$59) -> 11374 | F40: =E40*(1+F36*$H$59) -> 12454.53 | G40: =F40*(1+G36*$H$59) -> 13637.71 | H40: =G40*(1+H36*$H$59) -> 14933.293 | I40: =H40*(1+I36*$I$59) -> 16351.956 | J40: =I40*(1+J36*$I$59) -> 17905.391 | K40: =J40*(1+K36*$I$59) -> 19337.823 | L40: =K40*(1+L36*$I$59) -> 20498.092 | M40: =L40*(1+M36*$I$59) -> 21522.997 | N40: =M40*(1+N36*$I$59) -> 22383.917 | O40: =N40*(1+O36*$I$59) -> 23167.354 | P40: =O40*(1+P36*$I$59) -> 23978.211 | ... AC40: =AB40*(1+AC36*$I$59) -> 37500.868
A41: EBIDTA | B41: =+B39+B40 -> 64256.014 | C41: =+C39+C40 -> 66610.551 | D41: =D39+D40 -> 14828.871 | E41: =E39+E40 -> 15202.55 | F41: =F39+F40 -> 16409.834 | G41: =G39+G40 -> 18048.973 | H41: =H39+H40 -> 19500.153 | I41: =I39+I40 -> 21256.5 | J41: =J39+J40 -> 23170.564 | K41: =K39+K40 -> 25024.209 | ... AC41: =AC39+AC40 -> 48528.191
A42: CIF | B42: -1385 | C42: -890 | D42: =(C48)*$H$60 -> -1124.36 | E42: =(D48)*$H$60 -> -1113.1164 | F42: =(E48)*$H$60 -> -1113.1164 | G42: =(F48)*$H$60 -> -1113.1164 | H42: =(G48)*$H$60 -> -1113.1164 | I42: =(H48)*$H$60 -> -1113.1164 | J42: =(I48)*$H$60 -> -1113.1164 | K42: =(J48)*$H$60 -> -1113.1164 | ... AC42: =(AB48)*$H$60 -> -1113.1164
A43: Otros Gastos | B43: =-422-2817 -> -3239 | C43: =87-3634 -> -3547 | D43: =-C43*(1+D36) -> 4788.45 | E43: =D43*(1+E36*0.5) -> 4869.8537 | F43: =E43*(1+F36*0.5) -> 5101.1717 | G43: =F43*(1+G36*0.5) -> 5343.4774 | H43: =G43*(1+H36*0.5) -> 5597.2925 | I43: =H43*(1+I36*0.5) -> 5863.1639 | J43: =I43*(1+J36*0.5) -> 6141.6642 | K43: =J43*(1+K36*0.5) -> 6387.3308 | L43: =K43*(1+L36*0.5) -> 6578.9507 | ... AC43: =AB43*(1+AC36*0.5) -> 8922.7133
A44: Utilidad antes de Impuestos | B44: =B39-B42-B43 -> 68554 | C44: =C39-C42-C43 -> 70725 | D44: =D39-D42-D43 -> 164.78109 | E44: =E39-E42-E43 -> 71.812404 | F44: =F39-F42-F43 -> -32.751406 | G44: =G39-G42-G43 -> 180.90158 | H44: =H39-H42-H43 -> 82.683667 | I44: =I39-I42-I43 -> 154.49642 | ... AC44: =AC39-AC42-AC43 -> 3217.7258
A45: ISR & PTU | B45: 10481 | C45: 9680 | D45: =$H$61*D44 -> 34.604029 | E45: =$H$61*E44 -> 15.080605 | F45: =$H$61*F44 -> -6.8777954 | G45: =$I$61*G44 -> 41.607364 | H45: =$I$61*H44 -> 19.017243 | I45: =$I$61*I44 -> 35.534178 | J45: =$I$61*J44 -> 54.423605 | K45: =$I$61*K44 -> 94.799462 | L45: =$I$61*L44 -> 129.19901 | M45: =$I$61*M44 -> 160.68708 | N45: =$I$61*N44 -> 187.89365 | ... AC45: =$I$61*AC44 -> 740.07694
A46: Utilidad Neta | B46: =B44-B45 -> 58073 | C46: =C44-C45 -> 61045 | D46: =D44-D45 -> 130.17706 | E46: =E44-E45 -> 56.731799 | F46: =F44-F45 -> -25.873611 | G46: =G44-G45 -> 139.29422 | H46: =H44-H45 -> 63.666424 | I46: =I44-I45 -> 118.96225 | ... AC46: =AC44-AC45 -> 2477.6489
A47: Inversiones y Capex | B47: =OP!I34 -> 175.8 | C47: =OP!I35 -> 268.1 | D47: 10000 | E47: =D47*(1+E36*$H$62) -> 10408 | F47: =E47*(1+F36*$H$62) -> 11594.512 | G47: =F47*(1+G36*$H$62) -> 12916.286 | H47: =G47*(1+H36*$H$62) -> 14388.743 | I47: =H47*(1+I36*$H$62) -> 16029.06 | J47: =I47*(1+J36*$H$62) -> 17856.373 | K47: =J47*(1+K36*$H$62) -> 19570.584 | L47: =K47*(1+L36*$H$62) -> 20979.666 | ... AC47: =AB47*(1+AC36*$H$62) -> 43199.777
A48: Deuda + Lease Liabilities | B48: 108047 | C48: 112436 | D48: =C48*0.99 -> 111311.64 | E48: =D48 -> 111311.64 | F48: =E48 -> 111311.64 | G48: =F48 -> 111311.64 | H48: =G48 -> 111311.64 | I48: =H48 -> 111311.64 | J48: =I48 -> 111311.64 | K48: =J48 -> 111311.64 | L48: =K48 -> 111311.64 | ... AC48: =AB48 -> 111311.64
A49: Deuda/EBITDA | B49: =B48/B41 -> 1.681508 | C49: =C48/C41 -> 1.6879608 | D49: =D48/D41 -> 7.5064136 | E49: =E48/E41 -> 7.321906
A50: FNP | B50: =OP!F34 -> 1696.5225 | C50: =OP!F35 -> 2772.7525 | D50: =D41-D42-D43-D45-D47+D48-C48 -> 5.8170605 | E50: =E41-E42-E43-E45-E47+E48-D48 -> 1022.7318 | F50: =F41-F42-F43-F45-F47+F48-E48 -> 834.14439 | G50: =G41-G42-G43-G45-G47+G48-F48 -> 860.7182 | H50: =H41-H42-H43-H45-H47+H48-G48 -> 608.21624 | I50: =I41-I42-I43-I45-I47+I48-H48 -> 441.85818 | J50: =J41-J42-J43-J45-J47+J48-I48 -> 231.21968 | K50: =K41-K42-K43-K45-K47+K48-J48 -> 84.61058 | ... AC50: =AC41-AC42-AC43-AC45-AC47+AC48-AB48 -> -3221.2601
A51: F(t) | B51: 0 | C51: 0 | D51: =C51*(1+$B$59)+D50 -> 5.8170605 | E51: =D51*(1+$B$59)+E50 -> 1029.0317 | F51: =E51*(1+$B$59)+F50 -> 1948.5857 | G51: =F51*(1+$B$59)+G50 -> 2971.0365 | H51: =G51*(1+$B$59)+H50 -> 3825.8488 | I51: =H51*(1+$B$59)+I50 -> 4585.2524 | J51: =I51*(1+$B$59)+J50 -> 5197.048 | K51: =J51*(1+$B$59)+K50 -> 5713.0136 | ... AC51: =AB51*(1+$B$59)+AC50 -> -14352.673
AB52: =AB51-AB48 -> -121589.95 | AC52: =AC50/(B59-AC36) -> -67109.585
A53: EPS | C53: =1000000*C46/OP!$C$8 -> 749.29422 | D53: =1000000*D46/OP!$C$8 -> 1.5978527 | E53: =1000000*E46/OP!$C$8 -> 0.69635202 | F53: =1000000*F46/OP!$C$8 -> -0.31758452
A54: Consenso EPS | C54: 3.3 | D54: 5.6 | E54: 5.6
A55: E$/UN | D55: =$B$61/D46 -> -197.48084 | E55: =$B$61/E46 -> -453.14048 | F55: =$B$61/F46 -> 993.57894
A56: EEV/EBIDA | D56: =($B$61+D48-D51)/D41 -> 5.7724116 | E56: =($B$61+E48-E51)/E41 -> 5.5632203 | F56: =($B$61+F48-F51)/F41 -> 5.0978931
C58: "TELP" | D58: CER | E58: D Analista | H58: CP | I58: LP
A59: Tasa de descuento: | B59: =SUM(C59:E59) -> 0.083 | C59: 0.0307 | D59: 0.0523 | E59: 0 | G59: Factor D&A | H59: 1 | I59: 1
G60: Factor CIF | H60: -0.01
A61: VPN*@i% | B61: =C62+C63 -> -25707.475 | C61: Normal | D61: =D31 -> 0.001 | E61: =D32 -> 0.005 | G61: Factor ISR | H61: 0.21 | I61: 0.23
A62: DCF 25Y | B62: =C62/B61 -> 0.64435745 | C62: =AB52/(1+B59)^25 -> -16564.803 | D62: =SUMPRODUCT(E50:AB50,E31:AB31) -> -1451.4891 | E62: =SUMPRODUCT(E50:AB50,E32:AB32) -> -1182.0448 | G62: Factor inv | H62: 1.2
A63: Perpetuidad | B63: =1-B62 -> 0.35564255 | C63: =AC52/(1+B59)^25 -> -9142.672 | D63: =(AC50/($B$59+D31-$AC$36))*AC31 -> -8751.8055 | E63: =(AC50/($B$59+D32-$AC$36))*AC32 -> -7379.5102 | G63: Suma D&A | H63: =SUM(40:40) -> 629078.14
A64: VPN/Acción | B64: =1000000*B61/OP!C8 -> -315.54529 | D64: =1000000*SUM(D62:D63)/OP!C8 -> -125.2399 | E64: =1000000*SUM(E62:E63)/OP!C8 -> -105.08844 | G64: Suma Inv. | H64: =SUM(47:47) -> 673289.29
B65: =B64/OP!C7-1 -> -2.5858938 | D65: =D64/B64-1 -> -0.60310009 | E65: =E64/B64-1 -> -0.66696243 | G65: Inv.+Goodwill | H65: =SUM(47:47)+(OP!E12*OP!E7) -> 676197.99
A67: Duración | B67: =B62*D68+B63*D69 -> 46.32178 | E67: 1 | F67: 2 | G67: 3 | H67: 4 | I67: 5 | J67: 6 | K67: 7 | L67: 8 | M67: 9 | N67: 10 | O67: 11 | P67: 12 | Q67: 13 | R67: 14 | S67: 15 | T67: 16 | U67: 17 | V67: 18 | W67: 19 | X67: 20 | Y67: 21 | Z67: 22 | AA67: 23 | AB67: 24 | AC67: 25
A68: 0.001 | B68: =-$B$67*A68 -> -0.04632178 | D68: =SUM(E68:AB68)/SUMPRODUCT(E50:AB50,E33:AB33) -> 50.888251 | E68: =E67*E50*E33 -> 944.35069 | F68: =F67*F50*F33 -> 1422.3757 | G68: =G67*G50*G33 -> 2032.8104 | H68: =H67*H50*H33 -> 1768.4964 | I68: =I67*I50*I33 -> 1482.8958 | J68: =J67*J50*J33 -> 859.81557 | K68: =K67*K50*K33 -> 338.94054 | L68: =L67*L50*L33 -> -207.29982 | ... AC68: =AC67*AC50*AC33 -> -10971.206
A69: 0.005 | B69: =-$B$67*A69 -> -0.2316089 | D69: =(1+B59)/B59+AC67 -> 38.048193

Sheet DCFF
C1: VALUATION MODEL
C2: Año fiscal de DICK'S Sporting Goods cierra en febrero
D3: =D19/D6 -> -0.0052354863 | E3: =E19/E6 -> -0.0042949987 | F3: =F19/F6 -> -0.0040913802 | G3: 0 | H3: 0.25 | I3: =H3+1 -> 1.25 | J3: =I3+1 -> 2.25 | K3: =J3+1 -> 3.25 | L3: =K3+1 -> 4.25 | M3: =L3+1 -> 5.25 | N3: =M3+1 -> 6.25 | O3: =N3+1 -> 7.25 | P3: =O3+1 -> 8.25 | ... AF3: =AE3+1 -> 24.25 | AH3: interest expense as percentage of revenues
A4: Section | B4: Line # | C4: ITEM | D4: 2020 (Real) | E4: 2021 (Real) | F4: 2022 (Real) | G4: 2023 (Real) | H4: 2024 | I4: =+H4+1 -> 2025 | J4: =+I4+1 -> 2026 | K4: =+J4+1 -> 2027 | L4: =+K4+1 -> 2028 | M4: =+L4+1 -> 2029 | N4: =+M4+1 -> 2030 | O4: =+N4+1 -> 2031 | P4: =+O4+1 -> 2032 | ... AF4: =+AE4+1 -> 2048 | AG4: Notes | AH4: interest expense | AI4: -2.929 | AJ4: -3.215 | AK4: -4.012 | AL4: -5.856 | AM4: -8.047 | AN4: -10.248 | AO4: -17.012 | AP4: -48.812 | AQ4: -57.839 | AR4: -95.22 | AS4: -58.023
A5: INCOME STATEMENT | B5: 1 | C5: Growth | D5: =Cifras_en_Millones!F6 -> 0.095223457 | E5: =Cifras_en_Millones!E6 -> 0.28269445 | F5: =Cifras_en_Millones!D6 -> 0.0060870219 | G5: =Cifras_en_Millones!C6 -> 0.049821405 | H5: 0.034 | I5: 0.035 | J5: 0.0429 | K5: 0.048 | L5: 0.042 | M5: 0.04 | N5: 0.04 | O5: 0.038 | P5: 0.038 | Q5: 0.036 | R5: 0.036 | S5: 0.034 | T5: 0.034 | U5: 0.032 | V5: 0.032 | W5: 0.03 | X5: 0.03 | Y5: 0.028 | Z5: 0.028 | AA5: 0.026 | AB5: 0.026 | AC5: 0.024 | AD5: 0.022 | AE5: 0.022 | AF5: 0.02 | AH5: revenues | AI5: 6213.173 | AJ5: 6814.479 | AK5: 7270.965 | AL5: 7921.981 | AM5: 8590.472 | AN5: 8436.57 | AO5: 8750.743 | AP5: 9584.019 | AQ5: 12293.368 | AR5: 12368.198 | AS5: 12984.399
B6: 2 | C6: Revenues/Sales | D6: 9584.019 | E6: 12293.368 | F6: 12368.198 | G6: 12984.399 | H6: =G6*(1+H5) -> 13425.869 | I6: =H6*(1+I5) -> 13895.774 | J6: =I6*(1+J5) -> 14491.903 | K6: =J6*(1+K5) -> 15187.514 | L6: =K6*(1+L5) -> 15825.39 | M6: =L6*(1+M5) -> 16458.405 | N6: =M6*(1+N5) -> 17116.741 | O6: =N6*(1+O5) -> 17767.178 | ... AF6: =AE6*(1+AF5) -> 29019.712 | AH6: interest expense as percentage of revenues | AI6: =AI4/AI5 -> -0.00047141774 | AJ6: =AJ4/AJ5 -> -0.00047178955 | AK6: =AK4/AK5 -> -0.0005517837 | AL6: =AL4/AL5 -> -0.00073920904 | AM6: =AM4/AM5 -> -0.00093673549 | AN6: =AN4/AN5 -> -0.0012147117 | AO6: =AO4/AO5 -> -0.0019440635 | AP6: =AP4/AP5 -> -0.0050930617 | ... AS6: =AS4/AS5 -> -0.0044686704
B7: 3 | C7: EBIT/Operating Margin | D7: =D8/D6 -> 0.077365978 | E7: =E8/E6 -> 0.16549598 | F7: =F8/F6 -> 0.11828878 | G7: =G8/G6 -> 0.098761984 | H7: 0.112 | I7: 0.11 | J7: 0.11 | K7: 0.11 | L7: 0.085 | M7: 0.085 | N7: 0.085 | O7: 0.085 | P7: 0.085 | Q7: 0.085 | R7: 0.085 | S7: 0.085 | T7: 0.085 | U7: 0.085 | V7: 0.085 | W7: 0.085 | X7: 0.085 | Y7: 0.085 | Z7: 0.085 | AA7: 0.085 | AB7: 0.085 | AC7: 0.085 | AD7: 0.085 | AE7: 0.085 | AF7: 0.085 | AH7: short term average | AI7: =AVERAGE(AP6:AS6) -> -0.005491351
B8: 4 | C8: EBIT | D8: 741.477 | E8: 2034.503 | F8: 1463.019 | G8: 1282.365 | H8: =H6*H7 -> 1503.6973 | I8: =I6*I7 -> 1528.5351 | J8: =J6*J7 -> 1594.1093 | K8: =K6*K7 -> 1670.6265 | L8: =L6*L7 -> 1345.1581 | M8: =M6*M7 -> 1398.9644 | N8: =N6*N7 -> 1454.923 | O8: =O6*O7 -> 1510.2101 | ... AF8: =AF6*AF7 -> 2466.6755 | AH8: long term average | AI8: =AVERAGE(AI6:AS6) -> -0.0025722831
B9: 5a | C9: (Dep&Amort) | D9: -326.014 | E9: -322.551 | F9: -365.475 | G9: -393.933 | H9: =H22*$D50 -> -100.69401 | I9: =I22*$D50 -> -104.2183 | J9: =J22*$D50 -> -108.68927 | K9: =K22*$D50 -> -113.90635 | L9: =L22*$E50 -> -118.69042 | M9: =M22*$E50 -> -123.43804 | N9: =N22*$E50 -> -128.37556 | O9: =O22*$E50 -> -133.25383 | P9: =P22*$E50 -> -138.31748 | Q9: =Q22*$E50 -> -143.29691 | R9: =R22*$E50 -> -148.4556 | S9: =S22*$E50 -> -153.50309 | ... AF9: =AF22*$E50 -> -217.64784
B10: 5b | C10: (Stock based compensation) | D10: -50.177 | E10: -52.8 | F10: -50.603 | G10: -57.285 | H10: =H6*$D51 -> -60.416409 | I10: =I6*$D51 -> -62.530983 | J10: =J6*$D51 -> -65.213562 | K10: =K6*$D51 -> -68.343813 | L10: =L6*$D51 -> -71.214253 | M10: =M6*$D51 -> -74.062823 | N10: =N6*$D51 -> -77.025336 | O10: =O6*$D51 -> -79.952299 | ... AF10: =AF6*$D51 -> -130.5887
B11: 6 | C11: EBIDTA | D11: =D8-D9-D10 -> 1117.668 | E11: =E8-E9-E10 -> 2409.854 | F11: =F8-F9-F10 -> 1879.097 | G11: =G8-G9-G10 -> 1733.583 | H11: =H8-H9 -> 1604.3913 | I11: =I8-I9 -> 1632.7534 | J11: =J8-J9 -> 1702.7986 | K11: =K8-K9 -> 1784.5329 | L11: =L8-L9 -> 1463.8485 | M11: =M8-M9 -> 1522.4025 | N11: =N8-N9 -> 1583.2986 | O11: =O8-O9 -> 1643.4639 | ... AF11: =AF8-AF9 -> 2684.3234 | AH11: other income/cost as % of capex
B12: 7 | C12: (Interest Expense) | D12: -48.812 | E12: -57.839 | F12: -95.22 | G12: -58.023 | H12: =H6*$AI7 -> -73.726156 | I12: =I6*$AI7 -> -76.306572 | J12: =J6*$AI7 -> -79.580124 | K12: =K6*$AI7 -> -83.399969 | L12: =L6*$AI8 -> -40.707383 | M12: =M6*$AI8 -> -42.335678 | N12: =N6*$AI8 -> -44.029105 | O12: =O6*$AI8 -> -45.702211 | P12: =P6*$AI8 -> -47.438895 | Q12: =Q6*$AI8 -> -49.146695 | R12: =R6*$AI8 -> -50.915976 | S12: =S6*$AI8 -> -52.64712 | ... AF12: =AF6*$AI8 -> -74.646916 | AH12: other income/cost | AM12: 31.81 | AN12: -2.565 | AO12: 15.324 | AP12: 19.07 | AQ12: 17.774 | AR12: 15.949 | AS12: 93.809
B13: 8 | C13: Other income/(cost) | D13: 19.07 | E13: 17.774 | F13: 15.949 | G13: 93.809 | H13: =H22*$AP16 -> 34.868778 | I13: =I22*$AP16 -> 36.089185 | J13: =J22*$AP16 -> 37.637411 | K13: =K22*$AP16 -> 39.444007 | L13: =L22*$AM17 -> 31.936046 | M13: =M22*$AM17 -> 33.213487 | N13: =N22*$AM17 -> 34.542027 | O13: =O22*$AM17 -> 35.854624 | P13: =P22*$AM17 -> 37.2171 | Q13: =Q22*$AM17 -> 38.556915 | R13: =R22*$AM17 -> 39.944964 | S13: =S22*$AM17 -> 41.303093 | ... AF13: =AF22*$AM17 -> 58.56253 | AH13: Capex | AM13: -474.347 | AN13: -198.219 | AO13: =-(217.461) -> -217.461 | AP13: -224.027 | AQ13: -308.261 | AR13: -364.075 | AS13: -587.426
B14: 9 | C14: Earnings before taxes | D14: =D8+D12+D13 -> 711.735 | E14: =E8+E12+E13 -> 1994.438 | F14: =F8+F12+F13 -> 1383.748 | G14: =G8+G12+G13 -> 1318.151 | H14: =H8+H12+H13 -> 1464.8399 | I14: =I8+I12+I13 -> 1488.3177 | J14: =J8+J12+J13 -> 1552.1666 | K14: =K8+K12+K13 -> 1626.6706 | ... AF14: =AF8+AF12+AF13 -> 2450.5911 | AH14: short term | AP14: =AP12/AP13 -> -0.085123668 | AQ14: =AQ12/AQ13 -> -0.057658932 | AR14: =AR12/AR13 -> -0.043806908 | AS14: =AS12/AS13 -> -0.15969501
B15: 10 | C15: (Income tax) | D15: -181.484 | E15: -474.567 | F15: -340.61 | G15: -271.632 | H15: =-H14*$D52 -> -351.56158 | I15: =-I14*$D52 -> -357.19626 | J15: =-J14*$D52 -> -372.51998 | K15: =-K14*$D52 -> -390.40094 | L15: =-L14*$D52 -> -320.73283 | M15: =-M14*$D52 -> -333.56214 | N15: =-N14*$D52 -> -346.90463 | O15: =-O14*$D52 -> -360.087 | ... AF15: =-AF14*$D52 -> -588.14187 | AH15: long term | AM15: =AM12/AM13 -> -0.067060612 | AN15: =AN12/AN13 -> 0.012940233 | AO15: =AO12/AO13 -> -0.070467808 | AP15: =AP12/AP13 -> -0.085123668 | AQ15: =AQ12/AQ13 -> -0.057658932 | AR15: =AR12/AR13 -> -0.043806908 | AS15: =AS12/AS13 -> -0.15969501
B16: 11 | C16: Net income | D16: =D14+D15 -> 530.251 | E16: =E15+E14 -> 1519.871 | F16: =F14+F15 -> 1043.138 | G16: =G14+G15 -> 1046.519 | H16: =H14+H15 -> 1113.2783 | I16: =I14+I15 -> 1131.1215 | J16: =J14+J15 -> 1179.6466 | K16: =K14+K15 -> 1236.2696 | L16: =L14+L15 -> 1015.654 | M16: =M14+M15 -> 1056.2801 | ... AF16: =AF14+AF15 -> 1862.4493 | AL16: average short | AP16: =SUM(AP14:AS14)/4 -> -0.086571129
AL17: average long | AM17: =SUM(AM15:AS15)/7 -> -0.067267529
A18: CASH FLOW STATEMENT | B18: 12 | C18: Operating cash flows before WK | D18: 831.596 | E18: 1889.667 | F18: 1451.269 | G18: 1455.491 | H18: =H11+H12+H13+H15 -> 1213.9723 | I18: =I11+I12+I13+I15 -> 1235.3398 | J18: =J11+J12+J13+J15 -> 1288.3359 | K18: =K11+K12+K13+K15 -> 1350.176 | L18: =L11+L12+L13+L15 -> 1134.3444 | M18: =M11+M12+M13+M15 -> 1179.7181 | N18: =N11+N12+N13+N15 -> 1226.9069 | O18: =O11+O12+O13+O15 -> 1273.5293 | ... AF18: =AF11+AF12+AF13+AF15 -> 2080.0971
B19: 13 | C19: (Stock-based compensation) | D19: -50.177 | E19: -52.8 | F19: -50.603 | G19: -57.285 | H19: =H10 -> -60.416409 | I19: =I10 -> -62.530983 | J19: =J10 -> -65.213562 | K19: =K10 -> -68.343813 | L19: =L10 -> -71.214253 | M19: =M10 -> -74.062823 | N19: =N10 -> -77.025336 | O19: =O10 -> -79.952299 | ... AF19: =AF10 -> -130.5887
B20: 14 | C20: (Working Capital Flows) | D20: 670.996 | E20: -325.595 | F20: -579.991 | G20: 14.559 | H20: =$D56*(H6-G6) -> -551.83696 | I20: =$D56*(I6-H6) -> -587.38175 | J20: =$D56*(J6-I6) -> -745.16088 | K20: =$D56*(K6-J6) -> -869.51416 | L20: =$E56*(L6-K6) -> -797.34448 | M20: =$E56*(M6-L6) -> -791.26948 | N20: =$E56*(N6-M6) -> -822.92026 | O20: =$E56*(O6-N6) -> -813.04522 | P20: =$E56*(P6-O6) -> -843.94093 | Q20: =$E56*(Q6-P6) -> -829.90486 | R20: =$E56*(R6-Q6) -> -859.78144 | S20: =$E56*(S6-R6) -> -841.24837 | ... AF20: =$E56*(AF6-AE6) -> -711.26745
B21: 15 | C21: -Total Operating Cash Flow | D21: =D18-D19+D20 -> 1552.769 | E21: =E18-E19+E20 -> 1616.872 | F21: =F18-F19+F20 -> 921.881 | G21: =G18-G19+G20 -> 1527.335 | H21: =H18-H19+H20 -> 722.55179 | I21: =I18-I19+I20 -> 710.48903 | J21: =J18-J19+J20 -> 608.38855 | K21: =K18-K19+K20 -> 549.00565 | ... AF21: =AF18-AF19+AF20 -> 1499.4184
B22: 16 | C22: (CAPEX and Acquisitions) | D22: -224.027 | E22: -308.261 | F22: -364.075 | G22: -587.426 | H22: =-$D$57*H6 -> -402.77606 | I22: =-$D$57*I6 -> -416.87322 | J22: =-$D$57*J6 -> -434.75708 | K22: =-$D$57*K6 -> -455.62542 | L22: =-$E$57*L6 -> -474.76169 | M22: =-$E$57*M6 -> -493.75216 | N22: =-$E$57*N6 -> -513.50224 | O22: =-$E$57*O6 -> -533.01533 | P22: =-$E$57*P6 -> -553.26991 | Q22: =-$E$57*Q6 -> -573.18763 | R22: =-$E$57*R6 -> -593.82238 | S22: =-$E$57*S6 -> -614.01234 | ... AF22: =-$E$57*AF6 -> -870.59136
B23: 17 | C23: (Other investing flows) | D23: -0.137 | E23: -35.718 | F23: -28.819 | G23: -27.25 | H23: 0 | I23: 0 | J23: 0 | K23: 0 | L23: 0 | M23: 0 | N23: 0 | O23: 0 | P23: 0 | Q23: 0 | R23: 0 | S23: 0 | T23: 0 | U23: 0 | V23: 0 | W23: 0 | X23: 0 | Y23: 0 | Z23: 0 | AA23: 0 | AB23: 0 | AC23: 0 | AD23: 0 | AE23: 0 | AF23: 0
B24: 18 | C24: -Total Investing Flows | D24: =D22+D23 -> -224.164 | E24: =E22+E23 -> -343.979 | F24: =F22+F23 -> -392.894 | G24: =G22+G23 -> -614.676 | H24: =H22+H23 -> -402.77606 | I24: =I22+I23 -> -416.87322 | J24: =J22+J23 -> -434.75708 | K24: =K22+K23 -> -455.62542 | ... AF24: =AF22+AF23 -> -870.59136
B25: 19 | C25: (Flows related to leases) | D25: -0.826 | E25: -0.726 | F25: -0.74 | G25: -0.823 | H25: 0 | I25: 0 | J25: 0 | K25: 0 | L25: 0 | M25: 0 | N25: 0 | O25: 0 | P25: 0 | Q25: 0 | R25: 0 | S25: 0 | T25: 0 | U25: 0 | V25: 0 | W25: 0 | X25: 0 | Y25: 0 | Z25: 0 | AA25: 0 | AB25: 0 | AC25: 0 | AD25: 0 | AE25: 0 | AF25: 0
B26: 20 | C26: Flows related to debt | D26: 172.447 | E26: 1481.403 | F26: -515.865 | G26: -0.137 | H26: 300 | I26: 500 | J26: 600 | K26: 700 | L26: 700 | M26: 700 | N26: 700 | O26: 600 | P26: 700 | Q26: 700 | R26: 700 | S26: 700 | T26: 700 | U26: 700 | V26: 700 | W26: 700 | X26: 700 | Y26: 700 | Z26: 700 | AA26: 700 | AB26: 700 | AC26: 700 | AD26: 700 | AE26: 700 | AF26: 700
B27: 21 | C27: (Repurchases)/Issuance of stock | D27: 138.631 | E27: -1150.882 | F27: -478.711 | G27: -732.266 | H27: =H16*$D55 -> -445.31133 | I27: =I16*$D55 -> -452.4486 | J27: =J16*$D55 -> -471.85864 | K27: =K16*$D55 -> -494.50786 | L27: =L16*$E55 -> -406.26158 | M27: =M16*$E55 -> -422.51204 | N27: =N16*$E55 -> -439.41253 | O27: =O16*$E55 -> -456.1102 | P27: =P16*$E55 -> -473.44239 | Q27: =Q16*$E55 -> -490.48631 | R27: =R16*$E55 -> -508.14382 | S27: =S16*$E55 -> -525.42071 | ... AF27: =AF16*$E55 -> -744.97971
B28: 22 | C28: (Dividends) | D28: -107.404 | E28: -602.964 | F28: -163.081 | G28: -351.201 | H28: =H16*$D58 -> -300.58515 | I28: =I16*$D58 -> -305.4028 | J28: =J16*$D58 -> -318.50458 | K28: =K16*$D58 -> -333.7928 | L28: =L16*$E58 -> -253.91349 | M28: =M16*$E58 -> -264.07003 | N28: =N16*$E58 -> -274.63283 | O28: =O16*$E58 -> -285.06888 | P28: =P16*$E58 -> -295.90149 | Q28: =Q16*$E58 -> -306.55395 | R28: =R16*$E58 -> -317.58989 | S28: =S16*$E58 -> -328.38795 | ... AF28: =AF16*$E58 -> -465.61232
B29: 23 | C29: Other financing flows | D29: 57.209 | E29: -14.553 | F29: -89.239 | G29: 48.679 | H29: =G29*(1+H5) -> 50.334086 | I29: =H29*(1+I5) -> 52.095779 | J29: =I29*(1+J5) -> 54.330688 | K29: =J29*(1+K5) -> 56.938561 | L29: =K29*(1+L5) -> 59.329981 | M29: =L29*(1+M5) -> 61.70318 | N29: =M29*(1+N5) -> 64.171307 | O29: =N29*(1+O5) -> 66.609817 | ... AF29: =AE29*(1+AF5) -> 108.79599
B30: 24 | C30: -Total Financing flows | D30: 260.057 | E30: =SUM(E25:E29) -> -287.722 | F30: =SUM(F25:F29) -> -1247.636 | G30: =SUM(G25:G29) -> -1035.748 | H30: =SUM(H25:H29) -> -395.56239 | I30: =SUM(I25:I29) -> -205.75562 | J30: =SUM(J25:J29) -> -136.03254 | K30: =SUM(K25:K29) -> -71.362097 | L30: =SUM(L25:L29) -> 99.154912 | ... AF30: =SUM(AF25:AF29) -> -401.79603
A32: SUMMARY | B32: 25 | C32: Cash before shareholder returns | D32: =D21+D24+D25+D26+D29 -> 1557.435 | E32: =E21+E24+E25+E26+E29 -> 2739.017 | F32: =F21+F24+F25+F26+F29 -> -76.857 | G32: =G21+G24+G25+G26+G29 -> 960.378 | H32: =H21+H24+H25+H26+H29 -> 670.10982 | I32: =I21+I24+I25+I26+I29 -> 845.71159 | J32: =J21+J24+J25+J26+J29 -> 827.96216 | K32: =K21+K24+K25+K26+K29 -> 850.31879 | ... AF32: =AF21+AF24+AF25+AF26+AF29 -> 1437.623
B33: 26 | C33: Returns to shareholders | D33: =-1*(D27+D28) -> -31.227 | E33: =-1*(E27+E28) -> 1753.846 | F33: =-1*(F27+F28) -> 641.792 | G33: =-1*(G27+G28) -> 1083.467 | H33: =-1*(H27+H28) -> 745.89648 | I33: =-1*(I27+I28) -> 757.8514 | J33: =-1*(J27+J28) -> 790.36322 | K33: =-1*(K27+K28) -> 828.30066 | ... AF33: =-1*(AF27+AF28) -> 1210.592
B34: 27 | C34: Excess cash acumulation | D34: =D32-D33 -> 1588.662 | E34: =E32-E33 -> 985.171 | F34: =F32-F33 -> -718.649 | G34: =G32-G33 -> -123.089 | H34: =H32-H33 -> -75.786658 | I34: =I32-I33 -> 87.86019 | J34: =J32-J33 -> 37.59894 | K34: =K32-K33 -> 22.01813 | ... AF34: =AF32-AF33 -> 227.03096
A36: CASH & DEBT & DISCOUNTING | B36: 28 | C36: Ending cash balance | D36: 1658.067 | E36: =D36+E34 -> 2643.238 | F36: =E36+F34 -> 1924.589 | G36: =F36+G34 -> 1801.5 | H36: =G36+H34 -> 1725.7133 | I36: =H36+I34 -> 1813.5735 | J36: =I36+J34 -> 1851.1725 | K36: =J36+K34 -> 1873.1906 | L36: =K36+L34 -> 1905.798 | ... AF36: =AE36+AF34 -> 3063.5178
B37: 29 | C37: Total Debt | D37: =Cifras_en_Millones!F60 -> 4967.785 | E37: =Cifras_en_Millones!E60 -> 6425.123 | F37: =Cifras_en_Millones!D60 -> 5949.528 | G37: =Cifras_en_Millones!C60 -> 6157.57 | H37: =G37 -> 6157.57 | I37: =H37 -> 6157.57 | J37: =I37 -> 6157.57 | K37: =J37 -> 6157.57 | L37: =K37 -> 6157.57 | M37: =L37 -> 6157.57 | N37: =M37 -> 6157.57 | O37: =N37 -> 6157.57 | ... AF37: =AE37 -> 6157.57
B38: 30 | C38: Discount factor | G38: =1/((1+$D$47)^G3) -> 1 | H38: =1/((1+$D$47)^H3) -> 0.978686 | I38: =1/((1+$D$47)^I3) -> 0.89787706 | J38: =1/((1+$D$47)^J3) -> 0.82374043 | K38: =1/((1+$D$47)^K3) -> 0.75572516 | L38: =1/((1+$D$47)^L3) -> 0.69332584 | M38: =1/((1+$D$47)^M3) -> 0.63607875 | N38: =1/((1+$D$47)^N3) -> 0.58355848 | ... AF38: =1/((1+$D$47)^AF3) -> 0.12371075
F39: =1/((1+$D$48+0.001)^F$3) -> 1.0000041 | G39: =1/((1+$D$47+0.001)^G$3) -> 1 | H39: =1/((1+$D$47+0.001)^H$3) -> 0.97846166 | I39: =1/((1+$D$47+0.001)^I$3) -> 0.89684845 | J39: =1/((1+$D$47+0.001)^J$3) -> 0.82204258 | K39: =1/((1+$D$47+0.001)^K$3) -> 0.75347624 | L39: =1/((1+$D$47+0.001)^L$3) -> 0.690629 | M39: =1/((1+$D$47+0.001)^M$3) -> 0.63302383 | N39: =1/((1+$D$47+0.001)^N$3) -> 0.58022349 | ... AE39: =1/((1+$D$47+0.001)^AE$3) -> 0.13200019
F40: =1/((1+$D$48+0.005)^F$3) -> 1.0000204 | G40: =1/((1+$D$47+0.005)^G$3) -> 1 | H40: =1/((1+$D$47+0.005)^H$3) -> 0.97756686 | I40: =1/((1+$D$47+0.005)^I$3) -> 0.89275512 | J40: =1/((1+$D$47+0.005)^J$3) -> 0.81530148 | K40: =1/((1+$D$47+0.005)^K$3) -> 0.74456756 | L40: =1/((1+$D$47+0.005)^L$3) -> 0.67997038 | M40: =1/((1+$D$47+0.005)^M$3) -> 0.62097751 | N40: =1/((1+$D$47+0.005)^N$3) -> 0.56710275 | ... AE40: =1/((1+$D$47+0.005)^AE$3) -> 0.12123324
C42: EPS | H42: =1000000*H16/OP!C8 -> 13.664887 | I42: =1000000*I16/OP!$C8 -> 13.883902 | J42: =1000000*J16/OP!$C8 -> 14.479521
C43: Consenso EPS
C44: E$/UN | H44: =$D$64/H16 -> 10.524333 | I44: =$D$64/I16 -> 10.358314
A46: Discount rate | D46: Total | E46: Risk free rate | F46: Equity premium | G46: Firm premium
C47: Discount Rate | D47: =SUM(E47:G47) -> 0.09 | E47: 0.04 | F47: 0.04 | G47: 0.01
D49: Short Term | E49: Long Term | F49: Reference (line)
A50: Modelling factors | C50: Depreciation factor | D50: 0.25 | E50: 0.25 | F50: % PPE
C51: Stock-based comp | D51: -0.0045 | E51: -0.0045 | F51: % revenue (l2)
C52: Tax Rate | D52: 0.24 | E52: 0.24 | F52: % (line 9)
C53: Interest Rate on debt | D53: 0.0475 | E53: 0.0475 | F53: % debt (l29)
C54: Interest Rate on cash | D54: 0.035 | E54: 0.035 | F54: % of cash (l28)
C55: Stock-Repurchase | D55: -0.4 | E55: -0.4 | F55: % of net income
C56: Working capital flows | D56: -1.25 | E56: -1.25 | F56: % of change revenues (l2)
C57: Capex / Adq | D57: 0.03 | E57: 0.03 | F57: % revenue (l2)
C58: Dividends | D58: -0.27 | E58: -0.25 | F58: % net income
C59: Other financing flows | F59: growing with revenue
A61: Valuation | D61: $ millions | E61: % | F61: Notes | AE61: =((AE36-AE37)*AE38) -> -447.8305
C62: Value of flows | D62: =SUMPRODUCT(G33:AE33,G38:AE38)+((AE36-AE37)*AE38) -> 9175.8056 | E62: =D62/D64 -> 0.78315168 | F62: Present value of flows (l27), plus cash minus debt | AE62: =AE54+AE61 -> -447.8305
C63: Value of perpetuity | D63: =(AF32/(D47-AF5))*AF38 -> 2540.7059 | E63: =D63/D64 -> 0.21684832 | F63: Present value of perpetuity (column AF flow, dividend by growth minus discount rate)
C64: Total Value | D64: =D62+D63 -> 11716.512 | F64: Final market value of firm's equity, compare to its mkt cap
C65: Total value vs Mkt Cap | D65: =D66/D67-1 -> -0.27720855 | F65: Gives degree of undervaluation (if positive, meaning it's worth more than what the market thinks) or overvaluation (negative, worth less than what the market thinks)
C66: Estimated NPV per share | D66: =1000000*D64/OP!C8 -> 143.81382 | F66: If we divide total value by # of shares, we get the estimated share value
C67: Actual share price | D67: =OP!C7 -> 198.97 | F67: Actual share price

Sheet Cifras_en_Millones
A1: =Cifras_Originales!H3 -> DICK'S Sporting Goods, Inc. (DKS)
A2: =Cifras_Originales!D2 -> Cifras en Millones de USD
A4: Resultados | B4: 2024 | C4: =Cifras_Originales!C5 -> 2023 | D4: =Cifras_Originales!D5 -> 2022 | E4: =Cifras_Originales!E5 -> 2021 | F4: =Cifras_Originales!F5 -> 2020 | G4: =Cifras_Originales!G5 -> 2019 | H4: =Cifras_Originales!H5 -> 2018 | I4: =Cifras_Originales!I5 -> 2017 | J4: =Cifras_Originales!J5 -> 2016 | ... M4: =Cifras_Originales!M5 -> 2013
A5: Ventas Netas | C5: =Cifras_Originales!C6 -> 12984.399 | D5: =Cifras_Originales!D6 -> 12368.198 | E5: =Cifras_Originales!E6 -> 12293.368 | F5: =Cifras_Originales!F6 -> 9584.019 | G5: =Cifras_Originales!G6 -> 8750.743 | H5: =Cifras_Originales!H6 -> 8436.57 | I5: =Cifras_Originales!I6 -> 8590.472 | J5: =Cifras_Originales!J6 -> 7921.981 | ... M5: =Cifras_Originales!M6 -> 6213.173
A6: Crecimiento vs. Año pasado | B6: =B5/C5-1 -> -1 | C6: =C5/D5-1 -> 0.049821405 | D6: =D5/E5-1 -> 0.0060870219 | E6: =E5/F5-1 -> 0.28269445 | F6: =F5/G5-1 -> 0.095223457 | G6: =G5/H5-1 -> 0.037239423 | H6: =H5/I5-1 -> -0.01791543 | I6: =I5/J5-1 -> 0.084384323 | ... L6: =L5/M5-1 -> 0.096779214
A7: Utilidad Bruta | C7: =Cifras_Originales!C7 -> 4533.375 | D7: =Cifras_Originales!D7 -> 4284.558 | E7: =Cifras_Originales!E7 -> 4711.886 | F7: =Cifras_Originales!F7 -> 3050.707 | G7: =Cifras_Originales!G7 -> 2554.558 | H7: =Cifras_Originales!H7 -> 2437.782 | I7: =Cifras_Originales!I7 -> 2489.06 | J7: =Cifras_Originales!J7 -> 2365.783 | ... M7: =Cifras_Originales!M7 -> 1943.95
A8: porcentaje sobre ventas | B8: =B7/B5 -> #DIV/0! | C8: =C7/C5 -> 0.34914015 | D8: =D7/D5 -> 0.34641732 | E8: =E7/E5 -> 0.38328683 | F8: =F7/F5 -> 0.31831187 | G8: =G7/G5 -> 0.2919247 | H8: =H7/H5 -> 0.28895416 | I8: =I7/I5 -> 0.28974659 | ... M8: =M7/M5 -> 0.31287556
A9: Gastos de Operación | B9: =B5-B11 -> 0 | C9: =C5-C11 -> 11702.034 | D9: =D5-D11 -> 10905.179 | E9: =E5-E11 -> 10258.865 | F9: =F5-F11 -> 8842.542 | G9: =G5-G11 -> 8375.13 | H9: =H5-H11 -> 7991.837 | I9: =I5-I11 -> 8112.898 | ... M9: =M5-M11 -> 5676.361
A10: porcentaje sobre ventas | B10: =B9/B5 -> #DIV/0! | C10: =C9/C5 -> 0.90123802 | D10: =D9/D5 -> 0.88171122 | E10: =E9/E5 -> 0.83450402 | F10: =F9/F5 -> 0.92263402 | G10: =G9/G5 -> 0.95707644 | H10: =H9/H5 -> 0.94728509 | I10: =I9/I5 -> 0.94440655 | ... M10: =M9/M5 -> 0.91360099
A11: Utilidad de Operación | C11: =Cifras_Originales!C8 -> 1282.365 | D11: =Cifras_Originales!D8 -> 1463.019 | E11: =Cifras_Originales!E8 -> 2034.503 | F11: =Cifras_Originales!F8 -> 741.477 | G11: =Cifras_Originales!G8 -> 375.613 | H11: =Cifras_Originales!H8 -> 444.733 | I11: =Cifras_Originales!I8 -> 477.574 | J11: =Cifras_Originales!J8 -> 449.854 | ... M11: =Cifras_Originales!M8 -> 536.812
A12: porcentaje sobre ventas | B12: =B11/B5 -> #DIV/0! | C12: =C11/C5 -> 0.098761984 | D12: =D11/D5 -> 0.11828878 | E12: =E11/E5 -> 0.16549598 | F12: =F11/F5 -> 0.077365978 | G12: =G11/G5 -> 0.042923555 | H12: =H11/H5 -> 0.052714907 | I12: =I11/I5 -> 0.055593453 | ... M12: =M11/M5 -> 0.086399011
A13: Crecimiento vs año anterior | B13: =B11/C11-1 -> -1 | C13: =C11/D11-1 -> -0.12348028 | D13: =D11/E11-1 -> -0.28089612 | E13: =E11/F11-1 -> 1.7438518 | F13: =F11/G11-1 -> 0.97404509 | G13: =G11/H11-1 -> -0.15541909 | H13: =H11/I11-1 -> -0.068766306 | I13: =I11/J11-1 -> 0.061619992 | ... L13: =L11/M11-1 -> 0.032128566
A14: CIF (Productos Financieros) | C14: =Cifras_Originales!C9 -> 137.7 | D14: =Cifras_Originales!D9 -> 95.22 | E14: =Cifras_Originales!E9 -> 57.839 | F14: =Cifras_Originales!F9 -> 48.812 | G14: =Cifras_Originales!G9 -> 17.012 | H14: =Cifras_Originales!H9 -> 11.1 | I14: =Cifras_Originales!I9 -> 8.047 | J14: =Cifras_Originales!J9 -> 5.856 | ... M14: =Cifras_Originales!M9 -> 3.129
A15: Otros Gastos (Productos) | C15: =Cifras_Originales!C10 -> -93.8 | D15: =Cifras_Originales!D10 -> -15.949 | E15: =Cifras_Originales!E10 -> -17.744 | F15: =Cifras_Originales!F10 -> -19.07 | G15: =Cifras_Originales!G10 -> -15.324 | H15: =Cifras_Originales!H10 -> 2.565 | I15: =Cifras_Originales!I10 -> -31.81 | J15: =Cifras_Originales!J10 -> -14.424 | ... M15: =Cifras_Originales!M10 -> -12.224
A16: Utilidad antes de Impuestos y partidas extra. | B16: =B11-B14-B15 -> 0 | C16: =C11-C14-C15 -> 1238.465 | D16: =D11-D14-D15 -> 1383.748 | E16: =E11-E14-E15 -> 1994.408 | F16: =F11-F14-F15 -> 711.735 | G16: =G11-G14-G15 -> 373.925 | H16: =H11-H14-H15 -> 431.068 | I16: =I11-I14-I15 -> 501.337 | ... M16: =M11-M14-M15 -> 545.907
A17: Depreciación y amortización del ejercicio | C17: =Cifras_Originales!C11 -> 393.933 | D17: =Cifras_Originales!D11 -> 375 | E17: =Cifras_Originales!E11 -> 322.551 | F17: =Cifras_Originales!F11 -> 326.014 | G17: =Cifras_Originales!G11 -> 335.746 | H17: =Cifras_Originales!H11 -> 243.83 | I17: =Cifras_Originales!I11 -> 237.651 | J17: =Cifras_Originales!J11 -> 233.834 | ... M17: =Cifras_Originales!M11 -> 154.928
A18: Capital de Trabajo | C18: =Cifras_Originales!C12 -> 536.331 | D18: =Cifras_Originales!D12 -> 359.155 | E18: =Cifras_Originales!E12 -> -248.731 | F18: =Cifras_Originales!F12 -> 392.782 | G18: =Cifras_Originales!G12 -> 333.542 | H18: =Cifras_Originales!H12 -> 617.759 | I18: =Cifras_Originales!I12 -> 581.071 | J18: =Cifras_Originales!J12 -> 598.263 | ... M18: =Cifras_Originales!M12 -> 617.484
A19: EBITDA (flujo operativo) | B19: =B11-B15+B17 -> 0 | C19: =C11-C15+C17 -> 1770.098 | D19: =D11-D15+D17 -> 1853.968 | E19: =E11-E15+E17 -> 2374.798 | F19: =F11-F15+F17 -> 1086.561 | G19: =G11-G15+G17 -> 726.683 | H19: =H11-H15+H17 -> 685.998 | I19: =I11-I15+I17 -> 747.035 | ... M19: =M11-M15+M17 -> 703.964
A20: porcentaje sobre ventas | B20: =B19/B5 -> #DIV/0! | C20: =C19/C5 -> 0.13632499 | D20: =D19/D5 -> 0.14989799 | E20: =E19/E5 -> 0.19317717 | F20: =F19/F5 -> 0.11337217 | G20: =G19/G5 -> 0.083042434 | H20: =H19/H5 -> 0.081312429 | I20: =I19/I5 -> 0.086960879 | ... M20: =M19/M5 -> 0.11330185
A21: I.S.R Y P.T.U. | C21: =Cifras_Originales!C15 -> 191.92 | D21: =Cifras_Originales!D15 -> 340.7 | E21: =Cifras_Originales!E15 -> 474.5 | F21: =Cifras_Originales!F15 -> 181.5 | G21: =Cifras_Originales!G15 -> 76.5 | H21: =Cifras_Originales!H15 -> 111.2 | I21: =Cifras_Originales!I15 -> 177.9 | J21: =Cifras_Originales!J15 -> 171 | ... M21: =Cifras_Originales!M15 -> 208.3
A22: % Tax | B22: =+B21/B16 -> #DIV/0! | C22: =+C21/C16 -> 0.15496603 | D22: =+D21/D16 -> 0.24621535 | E22: =+E21/E16 -> 0.23791521 | F22: =+F21/F16 -> 0.25501064 | G22: =+G21/G16 -> 0.20458648 | H22: =+H21/H16 -> 0.25796394 | I22: =+I21/I16 -> 0.35485113 | ... M22: =+M21/M16 -> 0.38156682
A23: Utilidad Neta | C23: =Cifras_Originales!C16 -> 1046.519 | D23: =Cifras_Originales!D16 -> 1043 | E23: =Cifras_Originales!E16 -> 1519.871 | F23: =Cifras_Originales!F16 -> 530.251 | G23: =Cifras_Originales!G16 -> 297.462 | H23: =Cifras_Originales!H16 -> 319.864 | I23: =Cifras_Originales!I16 -> 323.445 | J23: =Cifras_Originales!J16 -> 287.396 | ... M23: =Cifras_Originales!M16 -> 337.598
A24: porcentaje sobre ventas | B24: =B23/B5 -> #DIV/0! | C24: =C23/C5 -> 0.080598186 | D24: =D23/D5 -> 0.08432918 | E24: =E23/E5 -> 0.12363341 | F24: =F23/F5 -> 0.055326581 | G24: =G23/G5 -> 0.033992771 | H24: =H23/H5 -> 0.037913986 | I24: =I23/I5 -> 0.037651598 | ... M24: =M23/M5 -> 0.054335844
A25: Crecimiento vs año anterior | B25: =B23/C23-1 -> -1 | C25: =C23/D23-1 -> 0.0033739214 | D25: =D23/E23-1 -> -0.31375755 | E25: =E23/F23-1 -> 1.8663237 | F25: =F23/G23-1 -> 0.78258399 | G25: =G23/H23-1 -> -0.070036015 | H25: =H23/I23-1 -> -0.011071434 | I25: =I23/J23-1 -> 0.1254332 | ... L25: =L23/M23-1 -> 0.019549879
A26: Efectivo Generado | B26: =B40-C40 -> -1801.22 | C26: =C40-D40 -> -123.166 | D26: =D40-E40 -> -718.819 | E26: =E40-F40 -> 985.138 | F26: =F40-G40 -> 1588.723 | G26: =G40-H40 -> -44.309 | H26: =H40-I40 -> 12.4 | I26: =I40-J40 -> -63.524 | ... M26: =M40-N40 -> 181.731
A27: Dividendos | C27: =Cifras_Originales!C17 -> 351.2 | D27: =Cifras_Originales!D17 -> 163.1 | E27: =Cifras_Originales!E17 -> 603 | F27: =Cifras_Originales!F17 -> 107.4 | G27: =Cifras_Originales!G17 -> 98.3 | H27: =Cifras_Originales!H17 -> 89.3 | I27: =Cifras_Originales!I17 -> 73.1 | J27: =Cifras_Originales!J17 -> 68 | ... M27: =Cifras_Originales!M17 -> 64.4
B28: =B27/C27-1 -> -1 | C28: =C27/D27-1 -> 1.1532802 | D28: =D27/E27-1 -> -0.72951907 | E28: =E27/F27-1 -> 4.6145251 | F28: =F27/G27-1 -> 0.092573754 | G28: =G27/H27-1 -> 0.10078387 | H28: =H27/I27-1 -> 0.22161423 | I28: =I27/J27-1 -> 0.075 | ... L28: =L27/M27-1 -> -0.048136646
A29: Recompra de Acciones | C29: =Cifras_Originales!C18 -> 648.6 | D29: =Cifras_Originales!D18 -> 426.7 | E29: =Cifras_Originales!E18 -> 1180 | F29: =Cifras_Originales!F18 -> 0.3069 | G29: =Cifras_Originales!G18 -> 402.2 | H29: =Cifras_Originales!H18 -> 33.89 | I29: =Cifras_Originales!I18 -> 42.53 | J29: =Cifras_Originales!J18 -> 29.88 | ... M29: =Cifras_Originales!M18 -> 150.068
A30: FNP | B30: =SUM(B26:B29) -> -1802.22 | C30: =SUM(C26:C29) -> 877.78728 | D30: =SUM(D26:D29) -> -129.74852 | E30: =SUM(E26:E29) -> 2772.7525 | F30: =SUM(F26:F29) -> 1696.5225 | G30: =SUM(G26:G29) -> 456.29178 | H30: =SUM(H26:H29) -> 135.81161 | I30: =SUM(I26:I29) -> 52.181 | ... M30: =SUM(M26:M29) -> 396.199
A31: FNP (ajustado por deuda) | B31: =B30-(B60-C60) -> 4355.35 | C31: =C30-(C60-D60) -> 669.74528 | D31: =D30-(D60-E60) -> 345.84648 | E31: =E30-(E60-F60) -> 1315.4145 | F31: =F30-(F60-G60) -> 1265.8855 | G31: =G30-(G60-H60) -> -2734.2682 | H31: =H30-(H60-I60) -> 72.473614 | I31: =I30-(I60-J60) -> -32.763 | ... M31: =M30-(M60-N60) -> -497.097
A32: FNP (ajustado por inversiones) | B32: =B31+B34 -> 4355.35 | C32: =C31+C34 -> 669.74528 | D32: =D31+D34 -> 345.84648 | E32: =E31+E34 -> 1315.4145 | F32: =F31+F34 -> 1274.3855 | G32: =G31+G34 -> -2734.2682 | H32: =H31+H34 -> 72.473614 | I32: =I31+I34 -> -32.763 | ... M32: =M31+M34 -> -497.097
A33: Capex | C33: =Cifras_Originales!C13 -> 520.4 | D33: =Cifras_Originales!D13 -> 328 | E33: =Cifras_Originales!E13 -> 268.1 | F33: =Cifras_Originales!F13 -> 167.3 | G33: =Cifras_Originales!G13 -> 179.5 | H33: =Cifras_Originales!H13 -> 170.5 | I33: =Cifras_Originales!I13 -> 372.6 | J33: =Cifras_Originales!J13 -> 242 | ... M33: =Cifras_Originales!M13 -> 285.668
A34: Inversiones | C34: =Cifras_Originales!C14 -> 0 | D34: =Cifras_Originales!D14 -> 0 | E34: =Cifras_Originales!E14 -> 0 | F34: =Cifras_Originales!F14 -> 8.5 | G34: =Cifras_Originales!G14 -> 0 | H34: =Cifras_Originales!H14 -> 0 | I34: =Cifras_Originales!I14 -> 0 | J34: =Cifras_Originales!J14 -> 0 | ... M34: =Cifras_Originales!M14 -> 0
A35: Capex + Inversiones | B35: =+B34+B33 -> 0 | C35: =+C34+C33 -> 520.4 | D35: =+D34+D33 -> 328 | E35: =+E34+E33 -> 268.1 | F35: =+F34+F33 -> 175.8 | G35: =+G34+G33 -> 179.5 | H35: =+H34+H33 -> 170.5 | I35: =+I34+I33 -> 372.6 | ... M35: =+M34+M33 -> 285.668
B36: =+B35/B5 -> #DIV/0! | C36: =+C35/C5 -> 0.040078867 | D36: =+D35/D5 -> 0.026519627 | E36: =+E35/E5 -> 0.021808507 | F36: =+F35/F5 -> 0.018343035 | G36: =+G35/G5 -> 0.020512544 | H36: =+H35/H5 -> 0.020209635 | I36: =+I35/I5 -> 0.043373635 | ... M36: =+M35/M5 -> 0.045977796
A37: Dividendos + Recompra de Acciones | B37: =SUM(B27:B29) -> -1 | C37: =SUM(C27:C29) -> 1000.9533 | D37: =SUM(D27:D29) -> 589.07048 | E37: =SUM(E27:E29) -> 1787.6145 | F37: =SUM(F27:F29) -> 107.79947 | G37: =SUM(G27:G29) -> 500.60078 | H37: =SUM(H27:H29) -> 123.41161 | I37: =SUM(I27:I29) -> 115.705 | ... M37: =SUM(M27:M29) -> 214.468
A39: Activo
A40: Caja | C40: =Cifras_Originales!C22 -> 1801.22 | D40: =Cifras_Originales!D22 -> 1924.386 | E40: =Cifras_Originales!E22 -> 2643.205 | F40: =Cifras_Originales!F22 -> 1658.067 | G40: =Cifras_Originales!G22 -> 69.344 | H40: =Cifras_Originales!H22 -> 113.653 | I40: =Cifras_Originales!I22 -> 101.253 | J40: =Cifras_Originales!J22 -> 164.777 | ... M40: =Cifras_Originales!M22 -> 181.731
A41: Cuentas y documentos por cobrar | C41: =Cifras_Originales!C23 -> 114.877 | D41: =Cifras_Originales!D23 -> 71.286 | E41: =Cifras_Originales!E23 -> 68.263 | F41: =Cifras_Originales!F23 -> 53.149 | G41: =Cifras_Originales!G23 -> 53.173 | H41: =Cifras_Originales!H23 -> 37.97 | I41: =Cifras_Originales!I23 -> 60.107 | J41: =Cifras_Originales!J23 -> 75.199 | ... M41: =Cifras_Originales!M23 -> 60.779
A42: Inventarios | C42: =Cifras_Originales!C24 -> 2848.797 | D42: =Cifras_Originales!D24 -> 2830.917 | E42: =Cifras_Originales!E24 -> 2297.609 | F42: =Cifras_Originales!F24 -> 1953.568 | G42: =Cifras_Originales!G24 -> 2202.275 | H42: =Cifras_Originales!H24 -> 1824.696 | I42: =Cifras_Originales!I24 -> 1711.103 | J42: =Cifras_Originales!J24 -> 1638.632 | ... M42: =Cifras_Originales!M24 -> 1232.065
A43: Activos Fijos (Net Plant) | C43: =Cifras_Originales!C25 -> 1638.161 | D43: =Cifras_Originales!D25 -> 1312.988 | E43: =Cifras_Originales!E25 -> 1319.681 | F43: =Cifras_Originales!F25 -> 1300.265 | G43: =Cifras_Originales!G25 -> 1415.728 | H43: =Cifras_Originales!H25 -> 1565.271 | I43: =Cifras_Originales!I25 -> 1677.34 | J43: =Cifras_Originales!J25 -> 1522.574 | ... M43: =Cifras_Originales!M25 -> 1084.529
A44: Otros Activos | B44: =B45-SUM(B40:B43) -> 0 | C44: =Cifras_Originales!C26 -> 2908.697 | D44: =Cifras_Originales!D26 -> 2852.619 | E44: =Cifras_Originales!E26 -> 2712.918 | F44: =Cifras_Originales!F26 -> 2787.81 | G44: =Cifras_Originales!G26 -> 2888.04 | H44: =Cifras_Originales!H26 -> 645.559 | I44: =Cifras_Originales!I26 -> 654.136 | J44: =Cifras_Originales!J26 -> 657.114 | ... M44: =Cifras_Originales!M26 -> 512.383
A45: Total Activo | C45: =Cifras_Originales!C27 -> 9311.752 | D45: =Cifras_Originales!D27 -> 8992.196 | E45: =Cifras_Originales!E27 -> 9041.676 | F45: =Cifras_Originales!F27 -> 7752.859 | G45: =Cifras_Originales!G27 -> 6628.56 | H45: =Cifras_Originales!H27 -> 4187.149 | I45: =Cifras_Originales!I27 -> 4203.939 | J45: =Cifras_Originales!J27 -> 4058.296 | ... M45: =Cifras_Originales!M27 -> 3071.487
A48: Pasivo
A49: Pasivo Corto Plazo | C49: =Cifras_Originales!C31 -> 2752 | D49: =Cifras_Originales!D31 -> 2641.446 | E49: =Cifras_Originales!E31 -> 2712.68 | F49: =Cifras_Originales!F31 -> 2550.198 | G49: =Cifras_Originales!G31 -> 2076.474 | H49: =Cifras_Originales!H31 -> 1504.639 | I49: =Cifras_Originales!I31 -> 1425.014 | J49: =Cifras_Originales!J31 -> 1397.415 | ... M49: =Cifras_Originales!M31 -> 1002.587
A50: Deuda a corto plazo | C50: =Cifras_Originales!C32 -> 1894 | D50: =Cifras_Originales!D32 -> 1745 | E50: =Cifras_Originales!E32 -> 1914.929 | F50: =Cifras_Originales!F32 -> 1817.224 | G50: =Cifras_Originales!G32 -> 1427.545 | H50: =Cifras_Originales!H32 -> 1274.408 | I50: =Cifras_Originales!I32 -> 1207.732 | J50: =Cifras_Originales!J32 -> 1192.981 | ... M50: =Cifras_Originales!M32 -> 847.304
A51: Short-Term Leases | C51: =Cifras_Originales!C33 -> 492.856 | D51: =Cifras_Originales!D33 -> 546.755 | E51: =Cifras_Originales!E33 -> 480.318 | F51: =Cifras_Originales!F33 -> 472.67 | G51: =Cifras_Originales!G33 -> 422.97 | H51: =Cifras_Originales!H33 -> 5.623 | I51: =Cifras_Originales!I33 -> 5.202 | J51: =Cifras_Originales!J33 -> 0.646 | ... M51: =Cifras_Originales!M33 -> 0.899
A52: Otros Pasivos a Corto Plazo | C52: =Cifras_Originales!C34 -> 365.144 | D52: =Cifras_Originales!D34 -> 349.691 | E52: =Cifras_Originales!E34 -> 317.433 | F52: =Cifras_Originales!F34 -> 260.304 | G52: =Cifras_Originales!G34 -> 225.959 | H52: =Cifras_Originales!H34 -> 224.608 | I52: =Cifras_Originales!I34 -> 212.08 | J52: =Cifras_Originales!J34 -> 203.788 | ... M52: =Cifras_Originales!M34 -> 154.384
A53: Pasivo Largo Plazo | C53: =Cifras_Originales!C35 -> 3942.077 | D53: =Cifras_Originales!D35 -> 3826.127 | E53: =Cifras_Originales!E35 -> 4227.41 | F53: =Cifras_Originales!F35 -> 2863.127 | G53: =Cifras_Originales!G35 -> 2820.488 | H53: =Cifras_Originales!H35 -> 778.349 | I53: =Cifras_Originales!I35 -> 837.424 | J53: =Cifras_Originales!J35 -> 731.392 | ... M53: =Cifras_Originales!M35 -> 376.721
A54: Deuda a largo plazo | C54: =Cifras_Originales!C36 -> 1483 | D54: =Cifras_Originales!D36 -> 1540 | E54: =Cifras_Originales!E36 -> 1930.73 | F54: =Cifras_Originales!F36 -> 418.583 | G54: =Cifras_Originales!G36 -> 233.287 | H54: =Cifras_Originales!H36 -> 11.776 | I54: =Cifras_Originales!I36 -> 10.232 | J54: =Cifras_Originales!J36 -> 0 | ... M54: =Cifras_Originales!M36 -> 38.617
A55: Long-Term Leases | C55: =Cifras_Originales!C37 -> 2287.714 | D55: =Cifras_Originales!D37 -> 2117.773 | E55: =Cifras_Originales!E37 -> 2099.146 | F55: =Cifras_Originales!F37 -> 2259.308 | G55: =Cifras_Originales!G37 -> 2453.346 | H55: =Cifras_Originales!H37 -> 54.781 | I55: =Cifras_Originales!I37 -> 60.084 | J55: =Cifras_Originales!J37 -> 4.679 | ... M55: =Cifras_Originales!M37 -> 6.476
A56: Otros Pasivos a Largo Plazo | B56: =B53-SUM(B54:B55) -> 0 | C56: =Cifras_Originales!C38 -> 171.363 | D56: =Cifras_Originales!D38 -> 168.354 | E56: =Cifras_Originales!E38 -> 197.534 | F56: =Cifras_Originales!F38 -> 185.236 | G56: =Cifras_Originales!G38 -> 133.855 | H56: =Cifras_Originales!H38 -> 711.792 | I56: =Cifras_Originales!I38 -> 767.108 | J56: =Cifras_Originales!J38 -> 726.713 | ... M56: =Cifras_Originales!M38 -> 331.628
A57: Total pasivos | C57: =Cifras_Originales!C39 -> 6694.077 | D57: =Cifras_Originales!D39 -> 6467.573 | E57: =Cifras_Originales!E39 -> 6940.09 | F57: =Cifras_Originales!F39 -> 5413.325 | G57: =Cifras_Originales!G39 -> 4896.962 | H57: =Cifras_Originales!H39 -> 2282.988 | I57: =Cifras_Originales!I39 -> 2262.438 | J57: =Cifras_Originales!J39 -> 2128.807 | ... M57: =Cifras_Originales!M39 -> 1379.308
A59: Deuda Neta | B59: =B60-B40 -> 0 | C59: =C60-C40 -> 4356.35 | D59: =D60-D40 -> 4025.142 | E59: =E60-E40 -> 3781.918 | F59: =F60-F40 -> 3309.718 | G59: =G60-G40 -> 4467.804 | H59: =H60-H40 -> 1232.935 | I59: =I60-I40 -> 1181.997 | ... M59: =M60-M40 -> 711.565
A60: Deuda | B60: =B50+B51+B54+B55 -> 0 | C60: =C50+C51+C54+C55 -> 6157.57 | D60: =D50+D51+D54+D55 -> 5949.528 | E60: =E50+E51+E54+E55 -> 6425.123 | F60: =F50+F51+F54+F55 -> 4967.785 | G60: =G50+G51+G54+G55 -> 4537.148 | H60: =H50+H51+H54+H55 -> 1346.588 | I60: =I50+I51+I54+I55 -> 1283.25 | ... M60: =M50+M51+M54+M55 -> 893.296
B61: =B60/B45 -> #DIV/0! | C61: =C60/C45 -> 0.66126868 | D61: =D60/D45 -> 0.66163238 | E61: =E60/E45 -> 0.71061195 | F61: =F60/F45 -> 0.64076813 | G61: =G60/G45 -> 0.68448471 | H61: =H60/H45 -> 0.32160021 | I61: =I60/I45 -> 0.30524943 | ... M61: =M60/M45 -> 0.29083503
A63: Interés Minoritario | B63: 0 | C63: =Cifras_Originales!C42 -> 0 | D63: =Cifras_Originales!D42 -> 0 | E63: =Cifras_Originales!E42 -> 0 | F63: =Cifras_Originales!F42 -> 0 | G63: =Cifras_Originales!G42 -> 0 | H63: =Cifras_Originales!H42 -> 0 | I63: =Cifras_Originales!I42 -> 0 | J63: =Cifras_Originales!J42 -> 0 | ... M63: =Cifras_Originales!M42 -> 0
A66: Capital Contable | B66: =B45-B57-B63 -> 0 | C66: =C45-C57-C63 -> 2617.675 | D66: =D45-D57-D63 -> 2524.623 | E66: =E45-E57-E63 -> 2101.586 | F66: =F45-F57-F63 -> 2339.534 | G66: =G45-G57-G63 -> 1731.598 | H66: =H45-H57-H63 -> 1904.161 | I66: =I45-I57-I63 -> 1941.501 | ... M66: =M45-M57-M63 -> 1692.179
A69: OTROS DATOS AL FIN DE AÑO
A70: Numero deEmpleados | C70: =Cifras_Originales!C47 -> 18900 | D70: =Cifras_Originales!D47 -> 18800 | E70: =Cifras_Originales!E47 -> 17800 | F70: =Cifras_Originales!F47 -> 16800 | G70: =Cifras_Originales!G47 -> 15300 | H70: =Cifras_Originales!H47 -> 15200 | I70: =Cifras_Originales!I47 -> 15400 | J70: =Cifras_Originales!J47 -> 14600 | ... M70: =Cifras_Originales!M47 -> 11200
A71: Acciones en circulación (millones) | C71: =+Cifras_Originales!C48 -> 82.448335 | D71: =+Cifras_Originales!D48 -> 85.618121 | E71: =+Cifras_Originales!E48 -> 79.849731 | F71: =+Cifras_Originales!F48 -> 89.281316 | G71: =+Cifras_Originales!G48 -> 86.938594 | H71: =+Cifras_Originales!H48 -> 96.303132 | I71: =+Cifras_Originales!I48 -> 104.59835 | J71: =+Cifras_Originales!J48 -> 112.79654 | ... M71: =+Cifras_Originales!M48 -> 123.84475
A72: Float | C72: =Cifras_Originales!C49 -> 0.963 | D72: =Cifras_Originales!D49 -> 0 | E72: =Cifras_Originales!E49 -> 0 | F72: =Cifras_Originales!F49 -> 0 | G72: =Cifras_Originales!G49 -> 0 | H72: =Cifras_Originales!H49 -> 0 | I72: =Cifras_Originales!I49 -> 0 | J72: =Cifras_Originales!J49 -> 0 | ... M72: =Cifras_Originales!M49 -> 0
A73: Insiders Own | C73: =Cifras_Originales!C50 -> 0.036 | D73: =Cifras_Originales!D50 -> 0 | E73: =Cifras_Originales!E50 -> 0 | F73: =Cifras_Originales!F50 -> 0 | G73: =Cifras_Originales!G50 -> 0 | H73: =Cifras_Originales!H50 -> 0 | I73: =Cifras_Originales!I50 -> 0 | J73: =Cifras_Originales!J50 -> 0 | ... M73: =Cifras_Originales!M50 -> 0
A74: S&P | C74: =+Cifras_Originales!C51 -> BBB | D74: =+Cifras_Originales!D51 -> 0 | E74: =+Cifras_Originales!E51 -> 0 | F74: =+Cifras_Originales!F51 -> 0 | G74: =+Cifras_Originales!G51 -> 0 | H74: =+Cifras_Originales!H51 -> 0 | I74: =+Cifras_Originales!I51 -> 0 | J74: =+Cifras_Originales!J51 -> 0 | ... M74: =+Cifras_Originales!M51 -> 0
A75: =Cifras_Originales!A52 -> Vol. Diario en Millones USD | C75: =Cifras_Originales!C52 -> 17.3557 | D75: =Cifras_Originales!D52 -> 16.983 | E75: =Cifras_Originales!E52 -> 25.9225 | F75: =Cifras_Originales!F52 -> 29.2232 | G75: =Cifras_Originales!G52 -> 33.8472 | H75: =Cifras_Originales!H52 -> 34.8128 | I75: =Cifras_Originales!I52 -> 53.8201 | J75: =Cifras_Originales!J52 -> 43.5032 | ... M75: =Cifras_Originales!M52 -> 34.8195 | IH75: =Cifras_Originales!GO52 -> 0
B77: =+Cifras_Originales!C53 -> 2021 | C77: =+Cifras_Originales!D53 -> 2022 | D77: =+Cifras_Originales!E53 -> 2023
A78: =Cifras_Originales!A54 -> Posicion en Corto (%) | B78: =Cifras_Originales!C54 -> 0
A79: =Cifras_Originales!A55 -> EPS | B79: =Cifras_Originales!C55 -> 18.27 | C79: =Cifras_Originales!D55 -> 13.43 | D79: =Cifras_Originales!E55 -> 12.72
A81: =+Cifras_Originales!A57 -> BONOS DE LA EMISORA A 3, 5 Y 10 | B81: Precio Medio | C81: Moody's | D81: YTM | E81: DIVISA
A82: =+Cifras_Originales!A58 -> 0 | B82: =+Cifras_Originales!C58 -> 0 | C82: =+Cifras_Originales!D58 -> 0 | D82: =+Cifras_Originales!E58 -> 0 | E82: =+Cifras_Originales!F58 -> 0
A83: =+Cifras_Originales!A59 -> 0 | B83: =+Cifras_Originales!C59 -> 0 | C83: =+Cifras_Originales!D59 -> 0 | D83: =+Cifras_Originales!E59 -> 0 | E83: =+Cifras_Originales!F59 -> 0
A84: =+Cifras_Originales!A60 -> 0 | B84: =+Cifras_Originales!C60 -> 0 | C84: =+Cifras_Originales!D60 -> 0 | D84: =+Cifras_Originales!E60 -> 0 | E84: =+Cifras_Originales!F60 -> 0
A85: =+Cifras_Originales!A61 -> 0 | B85: =+Cifras_Originales!C61 -> 0 | C85: =+Cifras_Originales!D61 -> 0 | D85: =+Cifras_Originales!E61 -> 0 | E85: =+Cifras_Originales!F61 -> 0

Sheet Cifras_Originales
A1: USD
A2: Millones | D2: ="Cifras en "&A2&" de "&A1 -> Cifras en Millones de USD
A3: DICK'S Sporting Goods, Inc. | H3: =A3&" ("&A4&")" -> DICK'S Sporting Goods, Inc. (DKS)
A4: DKS
A5: RESULTADOS | B5: 2024 | C5: 2023 | D5: =C5-1 -> 2022 | E5: =D5-1 -> 2021 | F5: =E5-1 -> 2020 | G5: =F5-1 -> 2019 | H5: =G5-1 -> 2018 | I5: =H5-1 -> 2017 | J5: =I5-1 -> 2016 | K5: =J5-1 -> 2015 | ... N5: =M5-1 -> 2012
A6: Ventas Netas | B6: 13442.849 | C6: 12984.399 | D6: 12368.198 | E6: 12293.368 | F6: 9584.019 | G6: 8750.743 | H6: 8436.57 | I6: 8590.472 | J6: 7921.981 | K6: 7270.695 | L6: 6814.479 | M6: 6213.173 | N6: 5836.119
A7: Utilidad Bruta | B7: 4825.696 | C7: 4533.375 | D7: 4284.558 | E7: 4711.886 | F7: 3050.707 | G7: 2554.558 | H7: 2437.782 | I7: 2489.06 | J7: 2365.783 | K7: 2182.887 | L7: 2086.666 | M7: 1943.95 | N7: 1837.163
A8: Utilidad de Operación | B8: 1473.932 | C8: 1282.365 | D8: 1463.019 | E8: 2034.503 | F8: 741.477 | G8: 375.613 | H8: 444.733 | I8: 477.574 | J8: 449.854 | K8: 535.192 | L8: 554.059 | M8: 536.812 | N8: 523.674
A9: CIF (Poductos) | B9: 52.987 | C9: 137.7 | D9: 95.22 | E9: 57.839 | F9: 48.812 | G9: 17.012 | H9: 11.1 | I9: 8.047 | J9: 5.856 | K9: 4.012 | L9: 3.315 | M9: 3.129 | N9: 7.034 | T9: 2023 | U9: =D5 -> 2022 | V9: =E5 -> 2021 | W9: =F5 -> 2020 | X9: =G5 -> 2019 | Y9: =H5 -> 2018 | Z9: =I5 -> 2017 | AA9: =J5 -> 2016 | AB9: =K5 -> 2015 | ... AD9: =M5 -> 2013
A10: Otros Gastos (Ingresos) | B10: -98.088 | C10: -93.8 | D10: -15.949 | E10: -17.744 | F10: -19.07 | G10: -15.324 | H10: 2.565 | I10: -31.81 | J10: -14.424 | K10: 0.305 | L10: -5.17 | M10: -12.224 | N10: -4.555 | S10: Inventories | T10: =C24 -> 2848.797 | U10: =D24 -> 2830.917 | V10: =E24 -> 2297.609 | W10: =F24 -> 1953.568 | X10: =G24 -> 2202.275 | Y10: =H24 -> 1824.696 | Z10: =I24 -> 1711.103 | AA10: =J24 -> 1638.632 | ... AE10: =N24 -> 1096.186
A11: Depreciación y amortización | B11: 400.409 | C11: 393.933 | D11: 375 | E11: 322.551 | F11: 326.014 | G11: 335.746 | H11: 243.83 | I11: 237.651 | J11: 233.834 | K11: 193.594 | L11: 179.431 | M11: 154.928 | N11: 125.096 | S11: Por cobrar | T11: =C23 -> 114.877 | U11: =D23 -> 71.286 | V11: =E23 -> 68.263 | W11: =F23 -> 53.149 | X11: =G23 -> 53.173 | Y11: =H23 -> 37.97 | Z11: =I23 -> 60.107 | AA11: =J23 -> 75.199 | ... AE11: =N23 -> 34.625
A12: Capital de Trabajo | B12: =T17 -> 61.471 | C12: =U17 -> 536.331 | D12: =V17 -> 359.155 | E12: =W17 -> -248.731 | F12: =X17 -> 392.782 | G12: 333.542 | H12: 617.759 | I12: 581.071 | J12: 598.263 | K12: 621.015 | L12: 731.551 | M12: 617.484 | N12: 595.121 | S12: Por pagar
A13: Capex | B13: 726 | C13: 520.4 | D13: 328 | E13: 268.1 | F13: 167.3 | G13: 179.5 | H13: 170.5 | I13: 372.6 | J13: 242 | K13: 370.028 | L13: 349.007 | M13: 285.668 | N13: 258
A14: Inversiones | B14: 0 | C14: 0 | D14: 0 | E14: 0 | F14: 8.5 | G14: 0 | H14: 0 | I14: 0 | J14: 0 | K14: 0 | L14: 0 | M14: 0 | N14: 0 | T14: =(T10-U10) -> 17.88 | U14: =(U10-V10) -> 533.308 | V14: =(V10-W10) -> 344.041 | W14: =(W10-X10) -> -248.707 | X14: =(X10-Y10) -> 377.579 | Y14: =(Y10-Z10) -> 113.593 | Z14: =(Z10-AA10) -> 72.471 | AA14: =(AA10-AB10) -> 111.445 | ... AD14: =(AD10-AE10) -> 135.879
A15: I.S.R Y P.T.U. | B15: 353.7 | C15: 191.92 | D15: 340.7 | E15: 474.5 | F15: 181.5 | G15: 76.5 | H15: 111.2 | I15: 177.9 | J15: 171 | K15: 200.5 | L15: 211.7 | M15: 208.3 | N15: 230.5 | T15: =T11-U11 -> 43.591 | U15: =(U11-V11) -> 3.023 | V15: =(V11-W11) -> 15.114 | W15: =(W11-X11) -> -0.024 | X15: =(X11-Y11) -> 15.203 | Y15: =(Y11-Z11) -> -22.137 | Z15: =(Z11-AA11) -> -15.092 | AA15: =(AA11-AB11) -> 13.804 | AB15: =(AB11-AC11) -> -18.897 | ... AD15: =(AD11-AE11) -> 26.154
A16: Utilidad Neta | B16: 1165.308 | C16: 1046.519 | D16: 1043 | E16: 1519.871 | F16: 530.251 | G16: 297.462 | H16: 319.864 | I16: 323.445 | J16: 287.396 | K16: 330.391 | L16: 344.198 | M16: 337.598 | N16: 290.709 | T16: =T12-U12 -> 0 | U16: =(U12-V12) -> 0 | V16: =(V12-W12) -> 0 | W16: =(W12-X12) -> 0 | X16: =(X12-Y12) -> 0 | Y16: =(Y12-Z12) -> 0 | Z16: =(Z12-AA12) -> 0 | AA16: =(AA12-AB12) -> 0 | AB16: =(AB12-AC12) -> 0 | ... AD16: =(AD12-AE12) -> 0
A17: Dividendos | B17: 362 | C17: 351.2 | D17: 163.1 | E17: 603 | F17: 107.4 | G17: 98.3 | H17: 89.3 | I17: 73.1 | J17: 68 | K17: 64.7 | L17: 61.3 | M17: 64.4 | N17: 307 | S17: Capital de trabajo | T17: =SUM(T14:T16) -> 61.471 | U17: =SUM(U14:U16) -> 536.331 | V17: =SUM(V14:V16) -> 359.155 | W17: =SUM(W14:W16) -> -248.731 | X17: =SUM(X14:X16) -> 392.782 | Y17: =SUM(Y14:Y16) -> 91.456 | Z17: =SUM(Z14:Z16) -> 57.379 | AA17: =SUM(AA14:AA16) -> 125.249 | ... AD17: =SUM(AD14:AD16) -> 162.033
A18: Compra de Acciones | B18: 268 | C18: 648.6 | D18: 426.7 | E18: 1180 | F18: 0.3069 | G18: 402.2 | H18: 33.89 | I18: 42.53 | J18: 29.88 | K18: 57.33 | L18: 0.0722 | M18: 150.068 | N18: 0.1934
B19: =B8-B9-B10-B15 -> 1165.333 | C19: =C8-C9-C10-C15 -> 1046.545 | D19: =D8-D9-D10-D15 -> 1043.048 | E19: =E8-E9-E10-E15 -> 1519.908 | F19: =F8-F9-F10-F15 -> 530.235 | G19: =G8-G9-G10-G15 -> 297.425 | H19: =H8-H9-H10-H15 -> 319.868 | I19: =I8-I9-I10-I15 -> 323.437 | ... N19: =N8-N9-N10-N15 -> 290.695
A20: POSICIÓN FINANCIERA | B20: =B16-B19 -> -0.025 | C20: =C16-C19 -> -0.026 | D20: =D16-D19 -> -0.048 | E20: =E16-E19 -> -0.037 | F20: =F16-F19 -> 0.016 | G20: =G16-G19 -> 0.037 | H20: =H16-H19 -> -0.004 | I20: =I16-I19 -> 0.008 | ... N20: =N16-N19 -> 0.014
A21: Activo
A22: Caja | B22: 1689.94 | C22: 1801.22 | D22: 1924.386 | E22: 2643.205 | F22: 1658.067 | G22: 69.344 | H22: 113.653 | I22: 101.253 | J22: 164.777 | K22: 118.936 | L22: 221.679 | M22: 181.731 | N22: 345.214
A23: Cuentas y documentos por cobrar | B23: 214.25 | C23: 114.877 | D23: 71.286 | E23: 68.263 | F23: 53.149 | G23: 53.173 | H23: 37.97 | I23: 60.107 | J23: 75.199 | K23: 61.395 | L23: 80.292 | M23: 60.779 | N23: 34.625
A24: Inventarios | B24: 3349.83 | C24: 2848.797 | D24: 2830.917 | E24: 2297.609 | F24: 1953.568 | G24: 2202.275 | H24: 1824.696 | I24: 1711.103 | J24: 1638.632 | K24: 1527.187 | L24: 1390.767 | M24: 1232.065 | N24: 1096.186
A25: Activos Fijos (Net Plant) | B25: 2069.914 | C25: 1638.161 | D25: 1312.988 | E25: 1319.681 | F25: 1300.265 | G25: 1415.728 | H25: 1565.271 | I25: 1677.34 | J25: 1522.574 | K25: 1347.885 | L25: 1203.382 | M25: 1084.529 | N25: 840.135
A26: Otros Activos | B26: =B27-SUM(B22:B25) -> 3134.76 | C26: =C27-SUM(C22:C25) -> 2908.697 | D26: =D27-SUM(D22:D25) -> 2852.619 | E26: =E27-SUM(E22:E25) -> 2712.918 | F26: =F27-SUM(F22:F25) -> 2787.81 | G26: =G27-SUM(G22:G25) -> 2888.04 | H26: =H27-SUM(H22:H25) -> 645.559 | I26: =I27-SUM(I22:I25) -> 654.136 | ... N26: =N27-SUM(N22:N25) -> 571.647
A27: Total Activo | B27: 10458.694 | C27: 9311.752 | D27: 8992.196 | E27: 9041.676 | F27: 7752.859 | G27: 6628.56 | H27: 4187.149 | I27: 4203.939 | J27: 4058.296 | K27: 3559.336 | L27: 3436.198 | M27: 3071.487 | N27: 2887.807
A30: Pasivo
A31: Pasivo Corto Plazo | B31: 3080.062 | C31: 2752 | D31: 2641.446 | E31: 2712.68 | F31: 2550.198 | G31: 2076.474 | H31: 1504.639 | I31: 1425.014 | J31: 1397.415 | K31: 1191.675 | L31: 1118.833 | M31: 1002.587 | N31: 1000.768
A32: Deuda a corto plazo | B32: 2181.785 | C32: 1894 | D32: 1745 | E32: 1914.929 | F32: 1817.224 | G32: 1427.545 | H32: 1274.408 | I32: 1207.732 | J32: 1192.981 | K32: 1006.7 | L32: 946.037 | M32: 847.304 | N32: 845.893
A33: Short-Term Leases | B33: 503.236 | C33: 492.856 | D33: 546.755 | E33: 480.318 | F33: 472.67 | G33: 422.97 | H33: 5.623 | I33: 5.202 | J33: 0.646 | K33: 0.589 | L33: 0.537 | M33: 0.899 | N33: 8.513
A34: Otros Pasivos a Corto Plazo | B34: =B31-B32-B33 -> 395.041 | C34: =C31-C32-C33 -> 365.144 | D34: =D31-D32-D33 -> 349.691 | E34: =E31-E32-E33 -> 317.433 | F34: =F31-F32-F33 -> 260.304 | G34: =G31-G32-G33 -> 225.959 | H34: =H31-H32-H33 -> 224.608 | I34: =I31-I32-I33 -> 212.08 | ... N34: =N31-N32-N33 -> 146.362
A35: Pasivo Largo Plazo | B35: 4180.368 | C35: 3942.077 | D35: 3826.127 | E35: 4227.41 | F35: 2863.127 | G35: 2820.488 | H35: 778.349 | I35: 837.424 | J35: 731.392 | K35: 578.474 | L35: 485.14 | M35: 376.721 | N35: 299.715
A36: Deuda a largo plazo | B36: 1484.217 | C36: 1483 | D36: 1540 | E36: 1930.73 | F36: 418.583 | G36: 233.287 | H36: 11.776 | I36: 10.232 | J36: 0 | K36: 6.454 | L36: 44.494 | M36: 38.617 | N36: 7.413
A37: Long-Term Leases | B37: 2500.307 | C37: 2287.714 | D37: 2117.773 | E37: 2099.146 | F37: 2259.308 | G37: 2453.346 | H37: 54.781 | I37: 60.084 | J37: 4.679 | K37: 5.324 | L37: 5.913 | M37: 6.476 | N37: 7.762
A38: Otros Pasivos a Largo Plazo | B38: =B35-B36-B37 -> 195.844 | C38: =C35-C36-C37 -> 171.363 | D38: =D35-D36-D37 -> 168.354 | E38: =E35-E36-E37 -> 197.534 | F38: =F35-F36-F37 -> 185.236 | G38: =G35-G36-G37 -> 133.855 | H38: =H35-H36-H37 -> 711.792 | I38: =I35-I36-I37 -> 767.108 | ... N38: =N35-N36-N37 -> 284.54
A39: Total pasivos | B39: =B31+B35 -> 7260.43 | C39: =C31+C35 -> 6694.077 | D39: =D31+D35 -> 6467.573 | E39: =+E35+E31 -> 6940.09 | F39: =+F35+F31 -> 5413.325 | G39: =+G35+G31 -> 4896.962 | H39: =+H35+H31 -> 2282.988 | I39: =+I35+I31 -> 2262.438 | J39: =J31+J35 -> 2128.807 | K39: =K35+K31 -> 1770.149 | L39: =L35+L31 -> 1603.973 | M39: =M35+M31 -> 1379.308 | N39: =N35+N31 -> 1300.483
A42: Interés Minoritario | B42: 0 | C42: 0 | D42: 0 | E42: 0 | F42: 0 | G42: 0 | H42: 0 | I42: 0 | J42: 0 | K42: 0 | L42: 0 | M42: 0 | N42: 0
A44: Capital Contable | B44: =B27-B39-B42 -> 3198.264 | C44: =C27-C39-C42 -> 2617.675 | D44: =D27-D39-D42 -> 2524.623 | E44: =E27-E39-E42 -> 2101.586 | F44: =F27-F39-F42 -> 2339.534 | G44: =G27-G39-G42 -> 1731.598 | H44: =H27-H39-H42 -> 1904.161 | I44: =I27-I39-I42 -> 1941.501 | ... N44: =N27-N39-N42 -> 1587.324
A46: OTROS DATOS AL FIN DE AÑO
A47: Numero de Empleados | C47: 18900 | D47: 18800 | E47: 17800 | F47: 16800 | G47: 15300 | H47: 15200 | I47: 15400 | J47: 14600 | K47: 13100 | L47: 12000 | M47: 11200 | N47: 11100
A48: Acciones en circulación (millones) | C48: 82.448335 | D48: 85.618121 | E48: 79.849731 | F48: 89.281316 | G48: 86.938594 | H48: 96.303132 | I48: 104.59835 | J48: 112.79654 | K48: 114.92326 | L48: 118.79312 | M48: 123.84475 | N48: 123.01137
A49: Float | C49: 0.963
A50: Insiders Own | C50: 0.036
A51: S&P | C51: BBB
A52: ="Vol. Diario en Millones "&A1 -> Vol. Diario en Millones USD | C52: 17.3557 | D52: 16.983 | E52: 25.9225 | F52: 29.2232 | G52: 33.8472 | H52: 34.8128 | I52: 53.8201 | J52: 43.5032 | K52: 33.6072 | L52: 18.8319 | M52: 34.8195 | N52: 24.0493
C53: 2021 | D53: =C53+1 -> 2022 | E53: =D53+1 -> 2023
A54: Posicion en Corto (%) | E54: 0.1122
A55: EPS | C55: 18.27 | D55: 13.43 | E55: 12.72
A57: BONOS DE LA EMISORA A 3, 5 Y 10 | C57: Precio Medio | D57: S&P | E57: YTM (%) | F57: DIVISA

Sheet Q
B2: 3Q17 | C2: 3Q18 | D2: 4Q18 | E2: 1Q19 | F2: 2Q19 | G2: 3Q19 | H2: 4Q19 | I2: 1Q20 | J2: 2Q20 | K2: 3Q20 | L2: 4Q20 | M2: 1Q21 | N2: 2Q21 | O2: 3Q21 | P2: 4Q21 | Q2: 1Q22 | R2: 2Q22 | S2: 3Q22 | T2: 4Q22 | U2: 1Q23 | V2: 2Q23 | W2: 3Q23 | X2: 4Q23e | Z2: 2019 | AA2: 2020 | AB2: 2021 | AC2: 2022 | AD2: 2023 | AE2: 2024 | AF2: 2025 | AG2: 2026 | AH2: 2027 | AI2: 2028 | AJ2: 2029 | AK2: 2030 | AL2: 2031 | AM2: 2032 | AN2: 2033 | AO2: 2034 | AP2: 2035 | AQ2: 2036 | AR2: 2037 | AS2: 2038 | AT2: 2039 | AU2: 2040 | AV2: 2041 | AW2: 2042 | AX2: 2043 | AY2: 2044 | AZ2: 2045 | BA2: 2046 | BB2: 2047
A3: Shares
A4: Growth
A5: Prods | AE5: 0.045 | AF5: =0.987*AE5 -> 0.044415 | AG5: =0.987*AF5 -> 0.043837605 | AH5: =0.987*AG5 -> 0.043267716 | AI5: =0.987*AH5 -> 0.042705236 | AJ5: =0.987*AI5 -> 0.042150068 | AK5: =0.987*AJ5 -> 0.041602117 | AL5: =0.987*AK5 -> 0.041061289 | AM5: =0.987*AL5 -> 0.040527493 | ... BB5: =0.987*BA5 -> 0.033304815
A6: Serv | AE6: 0.09 | AF6: =AE6*0.975 -> 0.08775 | AG6: =AF6*0.975 -> 0.08555625 | AH6: =AG6*0.975 -> 0.083417344 | AI6: =AH6*0.975 -> 0.08133191 | AJ6: =AI6*0.975 -> 0.079298612 | AK6: =AJ6*0.975 -> 0.077316147 | AL6: =AK6*0.975 -> 0.075383243 | AM6: =AL6*0.975 -> 0.073498662 | ... BB6: =BA6*0.975 -> 0.050274605
A8: COGS
A9: Prods | Z9: =Z30/Z26 -> 0.67792204 | AA9: =AA30/AA26 -> 0.68533661 | AB9: =AB30/AB26 -> 0.64650697 | AC9: =AC30/AC26 -> 0.6371652 | AD9: =AD30/AD26 -> 0.6358648 | AE9: =AD9*1.001 -> 0.63650067 | AF9: =AE9*1.001 -> 0.63713717 | AG9: =AF9*1.001 -> 0.6377743 | AH9: =AG9*1.001 -> 0.63841208 | AI9: =AH9*1.001 -> 0.63905049 | AJ9: =AI9*1.001 -> 0.63968954 | AK9: =AJ9*1.001 -> 0.64032923 | AL9: =AK9*1.001 -> 0.64096956 | ... BB9: =BA9*1.001 -> 0.65130235
A10: Serv | Z10: =Z31/Z27 -> 0.36261908 | AA10: =AA31/AA27 -> 0.33984898 | AB10: =AB31/AB27 -> 0.30274023 | AC10: =AC31/AC27 -> 0.28254553 | AD10: =AD31/AD27 -> 0.29105249 | AE10: =AD10*1.001 -> 0.29134354 | AF10: =AE10*1.001 -> 0.29163488 | AG10: =AF10*1.001 -> 0.29192652 | AH10: =AG10*1.001 -> 0.29221845 | AI10: =AH10*1.001 -> 0.29251066 | AJ10: =AI10*1.001 -> 0.29280317 | AK10: =AJ10*1.001 -> 0.29309598 | AL10: =AK10*1.001 -> 0.29338907 | ... BB10: =BA10*1.001 -> 0.29811867
A12: R&D | Z12: =Z33/Z25 -> 0.062331363 | AA12: =AA33/AA25 -> 0.068309564 | AB12: =AB33/AB25 -> 0.059904269 | AC12: =AC33/AC25 -> 0.066571484 | AD12: =AD33/AD25 -> 0.078317483 | AE12: =1.01*AD12 -> 0.079100658 | AF12: =1.01*AE12 -> 0.079891665 | AG12: =1.01*AF12 -> 0.080690581 | AH12: =1.01*AG12 -> 0.081497487 | AI12: =1.01*AH12 -> 0.082312462 | AJ12: =1.01*AI12 -> 0.083135587 | AK12: =1.01*AJ12 -> 0.083966943 | AL12: =1.01*AK12 -> 0.084806612 | ... BB12: =1.01*BA12 -> 0.099442422
A13: SGA | Z13: =Z34/Z25 -> 0.070126146 | AA13: =AA34/AA25 -> 0.07254977 | AB13: =AB34/AB25 -> 0.060065552 | AC13: =AC34/AC25 -> 0.063637378 | AD13: =AD34/AD25 -> 0.065265004 | AE13: =AD13*1.001 -> 0.065330269 | AF13: =AE13*1.001 -> 0.0653956 | AG13: =AF13*1.001 -> 0.065460995 | AH13: =AG13*1.001 -> 0.065526456 | AI13: =AH13*1.001 -> 0.065591983 | AJ13: =AI13*1.001 -> 0.065657575 | AK13: =AJ13*1.001 -> 0.065723232 | AL13: =AK13*1.001 -> 0.065788956 | ... BB13: =BA13*1.001 -> 0.066849511
A15: Utiilidad oP
A17: Tax Rate | Z17: =Z41/Z40 -> 0.15943837 | AA17: =AA41/AA40 -> 0.14428165 | AB17: =AB41/AB40 -> 0.13302261 | AC17: =AC41/AC40 -> 0.16204462
A19: DA | Z19: =Z52/Z25 -> 0.048225418 | AA19: =AA52/AA25 -> 0.040274666 | AB19: =AB52/AB25 -> 0.030846024 | AC19: =AC52/AC25 -> 0.028159299
A20: SBC | Z20: =Z53/Z25 -> 0.023322853 | AA20: =AA53/AA25 -> 0.024876601 | AB20: =AB53/AB25 -> 0.021611899 | AC20: =AC53/AC25 -> 0.022920006
A21: Net SBC | U21: =((W25+V25)/(R25+S25))-1 -> -0.019995894 | Z21: =(Z53+Z54)/Z25 -> 0.031148385 | AA21: =(AA53+AA54)/AA25 -> 0.034908839 | AB21: =(AB53+AB54)/AB25 -> 0.039533428 | AC21: =(AC53+AC54)/AC25 -> 0.038701284
A22: Capex | U22: =((W25+V25)/(F25+G25))-1 -> 0.57956253 | Z22: =Z55/Z25 -> 0.040338389 | AA22: =AA55/AA25 -> 0.026625139 | AB22: =AB55/AB25 -> 0.030302036 | AC22: =AC55/AC25 -> 0.027155059
A23: Net SBC Factor | Z23: =Z21/Z20 -> 1.3355307 | AA23: =AA21/AA20 -> 1.4032801 | AB23: =AB21/AB20 -> 1.8292436 | AC23: =AC21/AC20 -> 1.6885373
A25: Revenue | C25: =C26+C27 -> 53265 | D25: =D26+D27 -> 64040 | E25: =E26+E27 -> 84310 | F25: =F26+F27 -> 58015 | G25: =G26+G27 -> 53809 | H25: =H26+H27 -> 64040 | I25: =I26+I27 -> 91819 | J25: =J26+J27 -> 58313 | ... X25: =X26+X27 -> 89282 | Z25: =Z26+Z27 -> 260174 | AA25: =AA26+AA27 -> 274515 | AB25: =AB26+AB27 -> 365817 | AC25: =AC26+AC27 -> 394328 | AD25: =AD26+AD27 -> 383069 | AE25: =AE26+AE27 -> 404095.7 | AF25: =AF26+AF27 -> 426020.39 | AG25: =AG26+AG27 -> 448860.49 | ... BB25: =BB26+BB27 -> 1156800
A26: -Products | C26: 43095 | D26: 51529 | E26: 73435 | F26: 46565 | G26: 42354 | H26: 51529 | I26: 79104 | J26: 44965 | K26: 46529 | L26: 50149 | M26: 95678 | N26: 72683 | O26: 63948 | P26: 65083 | Q26: 104429 | R26: 77457 | S26: 63355 | T26: 70958 | U26: 96388 | V26: 73929 | W26: 60584 | X26: 67977 | Z26: =SUM(E26:H26) -> 213883 | AA26: =SUM(I26:L26) -> 220747 | AB26: =SUM(M26:P26) -> 297392 | AC26: =SUM(Q26:T26) -> 316199 | AD26: =SUM(U26:X26) -> 298878 | AE26: =(1+AE5)*AD26 -> 312327.51 | AF26: =(1+AF5)*AE26 -> 326199.54 | AG26: =(1+AG5)*AF26 -> 340499.34 | AH26: =(1+AH5)*AG26 -> 355231.97 | AI26: =(1+AI5)*AH26 -> 370402.24 | AJ26: =(1+AJ5)*AI26 -> 386014.72 | AK26: =(1+AK5)*AJ26 -> 402073.75 | AL26: =(1+AL5)*AK26 -> 418583.41 | ... BB26: =(1+BB5)*BA26 -> 746321.37
A27: -Services | C27: 10170 | D27: 12511 | E27: 10875 | F27: 11450 | G27: 11455 | H27: 12511 | I27: 12715 | J27: 13348 | K27: 13156 | L27: 14549 | M27: 15761 | N27: 16901 | O27: 17486 | P27: 18277 | Q27: 19516 | R27: 19821 | S27: 19604 | T27: 19188 | U27: 20766 | V27: 20907 | W27: 21213 | X27: 21305 | Z27: =SUM(E27:H27) -> 46291 | AA27: =SUM(I27:L27) -> 53768 | AB27: =SUM(M27:P27) -> 68425 | AC27: =SUM(Q27:T27) -> 78129 | AD27: =SUM(U27:X27) -> 84191 | AE27: =(1+AE6)*AD27 -> 91768.19 | AF27: =(1+AF6)*AE27 -> 99820.849 | AG27: =(1+AG6)*AF27 -> 108361.15 | AH27: =(1+AH6)*AG27 -> 117400.35 | AI27: =(1+AI6)*AH27 -> 126948.74 | AJ27: =(1+AJ6)*AI27 -> 137015.6 | AK27: =(1+AK6)*AJ27 -> 147609.12 | AL27: =(1+AL6)*AK27 -> 158736.37 | ... BB27: =(1+BB6)*BA27 -> 410478.6
A29: COGS
A30: -Products | C30: 28956 | D30: 35238 | E30: 48238 | F30: 32047 | G30: 29473 | H30: 35238 | I30: 52075 | J30: 31321 | K30: 32693 | L30: 35197 | M30: 62130 | N30: 46447 | O30: 40899 | P30: 42790 | Q30: 64309 | R30: 49290 | S30: 41485 | T30: 46387 | U30: 60765 | V30: 46795 | W30: 39136 | X30: 43350 | Z30: =SUM(E30:H30) -> 144996 | AA30: =SUM(I30:L30) -> 151286 | AB30: =SUM(M30:P30) -> 192266 | AC30: =SUM(Q30:T30) -> 201471 | AD30: =SUM(U30:X30) -> 190046 | AE30: =AE9*AE26 -> 198796.67 | AF30: =AF9*AF26 -> 207833.85 | AG30: =AG9*AG26 -> 217161.73 | AH30: =AH9*AH26 -> 226784.38 | AI30: =AI9*AI26 -> 236705.73 | AJ30: =AJ9*AJ26 -> 246929.58 | AK30: =AK9*AK26 -> 257459.57 | AL30: =AL9*AL26 -> 268299.23 | ... BB30: =BB9*BB26 -> 486080.86
A31: -Services | C31: 3888 | D31: 4489 | E31: 4041 | F31: 4147 | G31: 4109 | H31: 4489 | I31: 4527 | J31: 4622 | K31: 4312 | L31: 4812 | M31: 4981 | N31: 5058 | O31: 5280 | P31: 5396 | Q31: 5393 | R31: 5429 | S31: 5589 | T31: 5664 | U31: 6057 | V31: 6065 | W31: 6248 | X31: 6134 | Z31: =SUM(E31:H31) -> 16786 | AA31: =SUM(I31:L31) -> 18273 | AB31: =SUM(M31:P31) -> 20715 | AC31: =SUM(Q31:T31) -> 22075 | AD31: =SUM(U31:X31) -> 24504 | AE31: =AE10*AE27 -> 26736.069 | AF31: =AF10*AF27 -> 29111.242 | AG31: =AG10*AG27 -> 31633.492 | AH31: =AH10*AH27 -> 34306.546 | AI31: =AI10*AI27 -> 37133.86 | AJ31: =AJ10*AJ27 -> 40118.602 | AK31: =AK10*AK27 -> 43263.638 | AL31: =AL10*AL27 -> 46571.517 | ... BB31: =BB10*BB27 -> 122371.34
A33: R&D | C33: 3701 | D33: 4110 | E33: 3902 | F33: 3948 | G33: 4257 | H33: 4110 | I33: 4451 | J33: 4565 | K33: 4758 | L33: 4978 | M33: 5163 | N33: 5262 | O33: 5717 | P33: 5772 | Q33: 6306 | R33: 6387 | S33: 6797 | T33: 6761 | U33: 7709 | V33: 7457 | W33: 7442 | X33: 7393 | Z33: =SUM(E33:H33) -> 16217 | AA33: =SUM(I33:L33) -> 18752 | AB33: =SUM(M33:P33) -> 21914 | AC33: =SUM(Q33:T33) -> 26251 | AD33: =SUM(U33:X33) -> 30001 | AE33: =AE12*AE$25 -> 31964.236 | AF33: =AF12*AF$25 -> 34035.478 | AG33: =AG12*AG$25 -> 36218.814 | AH33: =AH12*AH$25 -> 38518.346 | AI33: =AI12*AI$25 -> 40938.183 | AJ33: =AJ12*AJ$25 -> 43482.432 | AK33: =AK12*AK$25 -> 46155.189 | AL33: =AL12*AL$25 -> 48960.535 | ... BB33: =BB12*BB$25 -> 115034.99
A34: SGA | C34: 4108 | D34: 4578 | E34: 4783 | F34: 4458 | G34: 4426 | H34: 4578 | I34: 5197 | J34: 4952 | K34: 4831 | L34: 4936 | M34: 5631 | N34: 5314 | O34: 5412 | P34: 5616 | Q34: 6449 | R34: 6193 | S34: 6012 | T34: 6440 | U34: 6607 | V34: 6201 | W34: 5973 | X34: 6220 | Z34: =SUM(E34:H34) -> 18245 | AA34: =SUM(I34:L34) -> 19916 | AB34: =SUM(M34:P34) -> 21973 | AC34: =SUM(Q34:T34) -> 25094 | AD34: =SUM(U34:X34) -> 25001 | AE34: =AE13*AE$25 -> 26399.681 | AF34: =AF13*AF$25 -> 27859.859 | AG34: =AG13*AG$25 -> 29382.854 | AH34: =AH13*AH$25 -> 30969.921 | AI34: =AI13*AI$25 -> 32622.237 | AJ34: =AJ13*AJ$25 -> 34340.902 | AK34: =AK13*AK$25 -> 36126.934 | AL34: =AL13*AL$25 -> 37981.266 | ... BB34: =BB13*BB$25 -> 77331.512
A36: Ut OP | C36: =C25-C30-C31-C33-C34 -> 12612 | D36: =D25-D30-D31-D33-D34 -> 15625 | E36: =E25-E30-E31-E33-E34 -> 23346 | F36: =F25-F30-F31-F33-F34 -> 13415 | G36: =G25-G30-G31-G33-G34 -> 11544 | H36: =H25-H30-H31-H33-H34 -> 15625 | I36: =I25-I30-I31-I33-I34 -> 25569 | J36: =J25-J30-J31-J33-J34 -> 12853 | ... X36: =X25-X30-X31-X33-X34 -> 26185 | Z36: =Z25-Z30-Z31-Z33-Z34 -> 63930 | AA36: =AA25-AA30-AA31-AA33-AA34 -> 66288 | AB36: =AB25-AB30-AB31-AB33-AB34 -> 108949 | AC36: =AC25-AC30-AC31-AC33-AC34 -> 119437 | AD36: =AD25-AD30-AD31-AD33-AD34 -> 113517 | AE36: =AE25-AE30-AE31-AE33-AE34 -> 120199.05 | AF36: =AF25-AF30-AF31-AF33-AF34 -> 127179.96 | AG36: =AG25-AG30-AG31-AG33-AG34 -> 134463.6 | ... BB36: =BB25-BB30-BB31-BB33-BB34 -> 355981.27
A38: Other | C38: 672 | D38: 502 | E38: 560 | F38: 378 | G38: 367 | H38: 502 | I38: 349 | J38: 282 | K38: 46 | L38: 126 | M38: 45 | N38: 508 | O38: 243 | P38: -538 | Q38: -247 | R38: 160 | S38: -10 | T38: -237 | U38: -393 | V38: 64 | W38: -265 | Z38: =SUM(E38:H38) -> 1807 | AA38: =SUM(I38:L38) -> 803 | AB38: =SUM(M38:P38) -> 258 | AC38: =SUM(Q38:T38) -> -334
A40: efore tax | C40: =C26+C27-C30-C31-C33-C34+C38 -> 13284 | D40: =D26+D27-D30-D31-D33-D34+D38 -> 16127 | E40: =E26+E27-E30-E31-E33-E34+E38 -> 23906 | F40: =F26+F27-F30-F31-F33-F34+F38 -> 13793 | G40: =G26+G27-G30-G31-G33-G34+G38 -> 11911 | H40: =H26+H27-H30-H31-H33-H34+H38 -> 16127 | I40: =I26+I27-I30-I31-I33-I34+I38 -> 25918 | J40: =J26+J27-J30-J31-J33-J34+J38 -> 13135 | ... W40: =W26+W27-W30-W31-W33-W34+W38 -> 22733 | Z40: =SUM(E40:H40) -> 65737 | AA40: =SUM(I40:L40) -> 67091 | AB40: =SUM(M40:P40) -> 109207 | AC40: =SUM(Q40:T40) -> 119103
A41: Tax | C41: 1765 | D41: 2441 | E41: 3941 | F41: 2232 | G41: 1867 | H41: 2441 | I41: 3682 | J41: 1886 | K41: 1884 | L41: 2228 | M41: 4824 | N41: 4381 | O41: 2625 | P41: 2697 | Q41: 6611 | R41: 5129 | S41: 3624 | T41: 3936 | U41: 5625 | V41: 4222 | W41: 2852 | Z41: =SUM(E41:H41) -> 10481 | AA41: =SUM(I41:L41) -> 9680 | AB41: =SUM(M41:P41) -> 14527 | AC41: =SUM(Q41:T41) -> 19300
A42: NI | C42: =C40-C41 -> 11519 | D42: =D40-D41 -> 13686 | E42: =E40-E41 -> 19965 | F42: =F40-F41 -> 11561 | G42: =G40-G41 -> 10044 | H42: =H40-H41 -> 13686 | I42: =I40-I41 -> 22236 | J42: =J40-J41 -> 11249 | ... W42: =W40-W41 -> 19881
A45: DA | E45: 3395 | F45: 6435 | G45: 9368 | H45: 12547 | I45: 2816 | J45: 5602 | K45: 8354 | L45: 11056 | M45: 2666 | N45: 5463 | O45: 8295 | P45: 11284 | Q45: 2697 | R45: 5434 | S45: 8239 | T45: 11104 | U45: 2916 | V45: 5814 | W45: 8866
A46: SBC | E46: 1559 | F46: 3073 | G46: 4569 | H46: 6068 | I46: 1710 | J46: 3407 | K46: 5105 | L46: 6829 | M46: 2020 | N46: 4001 | O46: 5961 | P46: 7906 | Q46: 2265 | R46: 4517 | S46: 6760 | T46: 9038 | U46: 2905 | V46: 5591 | W46: 8208
A47: Other SBC | E47: 1318 | F47: 1037 | G47: 2325 | H47: 2036 | I47: 1377 | J47: 1136 | K47: 2804 | L47: 2754 | M47: 2861 | N47: 3160 | O47: 5855 | P47: 6556 | Q47: 2888 | R47: 3218 | S47: 5915 | T47: 6223 | U47: 2316 | V47: 2734 | W47: 5119
A48: Capex | E48: 3355 | F48: 5718 | G48: 7718 | H48: 10495 | I48: 2107 | J48: 3960 | K48: 5525 | L48: 7309 | M48: 3500 | N48: 5769 | O48: 7862 | P48: 11085 | Q48: 2803 | R48: 5317 | S48: 7419 | T48: 10708 | U48: 3787 | V48: 6703 | W48: 8796
A49: Divs | E49: 3568 | F49: 7011 | G49: 10640 | H49: 14119 | I49: 3539 | J49: 6914 | K49: 10570 | L49: 14081 | M49: 3613 | N49: 7060 | O49: 10827 | P49: 14467 | Q49: 3732 | R49: 7327 | S49: 11138 | T49: 14841 | U49: 3768 | V49: 7418 | W49: 11267
A50: Repurch | E50: 8796 | F50: 32498 | G50: 49463 | H50: 66897 | I50: 20706 | J50: 39280 | K50: 55171 | L50: 72358 | M50: 24775 | N50: 43323 | O50: 66223 | P50: 85971 | Q50: 20478 | R50: 43109 | S50: 64974 | T50: 89402 | U50: 19475 | V50: 39069 | W50: 56547
A52: DA | E52: =E45 -> 3395 | F52: =F45-E45 -> 3040 | G52: =G45-F45 -> 2933 | H52: =H45-G45 -> 3179 | I52: =I45 -> 2816 | J52: =J45-I45 -> 2786 | K52: =K45-J45 -> 2752 | L52: =L45-K45 -> 2702 | M52: =M45 -> 2666 | N52: =N45-M45 -> 2797 | O52: =O45-N45 -> 2832 | P52: =P45-O45 -> 2989 | Q52: =Q45 -> 2697 | R52: =R45-Q45 -> 2737 | S52: =S45-R45 -> 2805 | T52: =T45-S45 -> 2865 | U52: =U45 -> 2916 | V52: =V45-U45 -> 2898 | W52: =W45-V45 -> 3052 | X52: 3262 | Z52: =SUM(E52:H52) -> 12547 | AA52: =SUM(I52:L52) -> 11056 | AB52: =SUM(M52:P52) -> 11284 | AC52: =SUM(Q52:T52) -> 11104
A53: SBC | E53: =E46 -> 1559 | F53: =F46-E46 -> 1514 | G53: =G46-F46 -> 1496 | H53: =H46-G46 -> 1499 | I53: =I46 -> 1710 | J53: =J46-I46 -> 1697 | K53: =K46-J46 -> 1698 | L53: =L46-K46 -> 1724 | M53: =M46 -> 2020 | N53: =N46-M46 -> 1981 | O53: =O46-N46 -> 1960 | P53: =P46-O46 -> 1945 | Q53: =Q46 -> 2265 | R53: =R46-Q46 -> 2252 | S53: =S46-R46 -> 2243 | T53: =T46-S46 -> 2278 | U53: =U46 -> 2905 | V53: =V46-U46 -> 2686 | W53: =W46-V46 -> 2617 | Z53: =SUM(E53:H53) -> 6068 | AA53: =SUM(I53:L53) -> 6829 | AB53: =SUM(M53:P53) -> 7906 | AC53: =SUM(Q53:T53) -> 9038
A54: Other SBC | E54: =E47 -> 1318 | F54: =F47-E47 -> -281 | G54: =G47-F47 -> 1288 | H54: =H47-G47 -> -289 | I54: =I47 -> 1377 | J54: =J47-I47 -> -241 | K54: =K47-J47 -> 1668 | L54: =L47-K47 -> -50 | M54: =M47 -> 2861 | N54: =N47-M47 -> 299 | O54: =O47-N47 -> 2695 | P54: =P47-O47 -> 701 | Q54: =Q47 -> 2888 | R54: =R47-Q47 -> 330 | S54: =S47-R47 -> 2697 | T54: =T47-S47 -> 308 | U54: =U47 -> 2316 | V54: =V47-U47 -> 418 | W54: =W47-V47 -> 2385 | Z54: =SUM(E54:H54) -> 2036 | AA54: =SUM(I54:L54) -> 2754 | AB54: =SUM(M54:P54) -> 6556 | AC54: =SUM(Q54:T54) -> 6223
A55: Capex | E55: =E48 -> 3355 | F55: =F48-E48 -> 2363 | G55: =G48-F48 -> 2000 | H55: =H48-G48 -> 2777 | I55: =I48 -> 2107 | J55: =J48-I48 -> 1853 | K55: =K48-J48 -> 1565 | L55: =L48-K48 -> 1784 | M55: =M48 -> 3500 | N55: =N48-M48 -> 2269 | O55: =O48-N48 -> 2093 | P55: =P48-O48 -> 3223 | Q55: =Q48 -> 2803 | R55: =R48-Q48 -> 2514 | S55: =S48-R48 -> 2102 | T55: =T48-S48 -> 3289 | U55: =U48 -> 3787 | V55: =V48-U48 -> 2916 | W55: =W48-V48 -> 2093 | Z55: =SUM(E55:H55) -> 10495 | AA55: =SUM(I55:L55) -> 7309 | AB55: =SUM(M55:P55) -> 11085 | AC55: =SUM(Q55:T55) -> 10708
A56: Divs | E56: =E49 -> 3568 | F56: =F49-E49 -> 3443 | G56: =G49-F49 -> 3629 | H56: =H49-G49 -> 3479 | I56: =I49 -> 3539 | J56: =J49-I49 -> 3375 | K56: =K49-J49 -> 3656 | L56: =L49-K49 -> 3511 | M56: =M49 -> 3613 | N56: =N49-M49 -> 3447 | O56: =O49-N49 -> 3767 | P56: =P49-O49 -> 3640 | Q56: =Q49 -> 3732 | R56: =R49-Q49 -> 3595 | S56: =S49-R49 -> 3811 | T56: =T49-S49 -> 3703 | U56: =U49 -> 3768 | V56: =V49-U49 -> 3650 | W56: =W49-V49 -> 3849 | Z56: =SUM(E56:H56) -> 14119 | AA56: =SUM(I56:L56) -> 14081 | AB56: =SUM(M56:P56) -> 14467 | AC56: =SUM(Q56:T56) -> 14841
A57: Repurch | E57: =E50 -> 8796 | F57: =F50-E50 -> 23702 | G57: =G50-F50 -> 16965 | H57: =H50-G50 -> 17434 | I57: =I50 -> 20706 | J57: =J50-I50 -> 18574 | K57: =K50-J50 -> 15891 | L57: =L50-K50 -> 17187 | M57: =M50 -> 24775 | N57: =N50-M50 -> 18548 | O57: =O50-N50 -> 22900 | P57: =P50-O50 -> 19748 | Q57: =Q50 -> 20478 | R57: =R50-Q50 -> 22631 | S57: =S50-R50 -> 21865 | T57: =T50-S50 -> 24428 | U57: =U50 -> 19475 | V57: =V50-U50 -> 19594 | W57: =W50-V50 -> 17478 | Z57: =SUM(E57:H57) -> 66897 | AA57: =SUM(I57:L57) -> 72358 | AB57: =SUM(M57:P57) -> 85971 | AC57: =SUM(Q57:T57) -> 89402
J63: -1
