Workbook
Name Sectors: '[1]Sector Impact'!$K$4:$K$16
Name Sectors: 'Sector Impact'!$K$4:$K$16

Sheet OP
B2: 18/09/2024 | C2: Team 5 | D2: 22/10/2024 | E2: =Inputs!H3 -> #VALUE! | L2: {=_FV(E2,"Exchange")} -> New York Stock Exchange | M2: SIC:
D3: COMPANY DESCRIPTION | H3: CEO & BOARD OF DIRECTORS
D4: {=_FV(Inputs!H3,"Description")} -> Ermenegildo Zegna NV is an Italy-based manufacturer of high-end menswear and accessories. The Company focuses on producing different kinds of apparel, including outerwear such as jackets, suits, blazers, shirts, pants and jeans, as well as shoes, sportswear and accessories. The Company is active worldwide. | H4: Name, Age and Tenure | I4: Gender | J4: Executive? | L4: Other roles
H5: Ermenegildo Zegna, 69, 35 years | I5: Male | J5: Yes | L5: CEO, Chairman
H6: Sergio P. Ermotti, 64, 3 years | I6: Male | J6: No | L6: Lead non-executive director
H7: Andrea C. Bonomi, 59, 3 years | I7: Male | J7: No | L7: -
H8: Angelica Cheung, 58, 3 years | I8: Female | J8: No | L8: -
H9: Domenico de Sole, 80, 19 years | I9: Male | J9: No | L9: -
H10: Ronald B. Johnson, 64, 5 years | I10: Male | J10: No | L10: -
H11: Valerie A. Mars, 65, 3 years | I11: Female | J11: No | L11: Chair of the Audit Comitee
H12: Michele Norsa, 76, 7 years | I12: Male | J12: No | L12: Chair of the Governance & Sustainability Comitee
H13: Henry Peter, 67, 10 years | I13: Male | J13: No | L13: Chair of the Compensation Commitee
H14: Anna Zegna, 67, 6 years | I14: Female | J14: No | L14: -
B15: {=_FV(E2,"Currency")&" MILLIONS"} -> USD MILLIONS | H15: Paolo Zegna, 68, 3 years | I15: Male | J15: No | L15: -
B18: COMPANY OVERVIEW
B19: Stock | D19: Liquidity and Solvency | F19: Segments | I19: ="Profitability ("&J20&")" -> Profitability (2023) | L19: Multiples
B20: Last Price | C20: {=_FV(E2,"Price")} -> 9.44 | D20: Total Assets | E20: =_xlfn.XLOOKUP(D20,'Fin. Data'!A:A,'Fin. Data'!B:B,,0) -> 3053.66 | F20: Regions | H20: % Sales | I20: Reporting Year | J20: 2023 | L20: Float | M20: =IF(Inputs!B82 <> "",Inputs!B82,"") -> 59.07M
B21: Outstanding Shares | C21: {=_FV(E2,"Shares outstanding",TRUE)} -> 254089400 | D21: Total Liabilities | E21: =_xlfn.XLOOKUP(D21,'Fin. Data'!A:A,'Fin. Data'!B:B,,0) -> 2059 | F21: ='Segments '!C5 -> EMEA(excuding Italy and UK) | H21: ='Segments '!B5 -> 0.12490291 | I21: End of Year | J21: 45291 | L21: Insiders Own | M21: =IF(Inputs!B83 <> "",Inputs!B83,"") -> 0.752
B22: Market Cap. | C22: =C20*C21/1000000 -> 2398.6039 | D22: Cash/Share | E22: =_xlfn.XLOOKUP("Cash & Eq.",'Fin. Data'!A:A,'Fin. Data'!B:B,,0)*1000000/C21 -> 1.2869486 | F22: ='Segments '!C6 -> Italy | H22: ='Segments '!B6 -> 0.14791262 | I22: EBITDA | K22: =_xlfn.XLOOKUP(I22,'Fin. Data'!A:A,'Fin. Data'!B:B,,0) -> 491.27 | L22: b (Yahoo) | M22: 0.66
B23: +Total Debt | C23: ='Fin. Data'!B58 -> 1099.57 | D23: EBITDA/Net Financial Cost (NFC) | E23: =IFERROR(_xlfn.XLOOKUP("EBITDA",'Fin. Data'!A:A,'Fin. Data'!B:B,,0)/_xlfn.XLOOKUP("Net Financial Cost",'Fin. Data'!A:A,'Fin. Data'!B:B,,0),"") -> -14.664776 | F23: ='Segments '!C7 -> Japan | H23: ='Segments '!B7 -> 0.044616505 | I23: Depreciation & Amortization | K23: =_xlfn.XLOOKUP(I23,'Fin. Data'!A:A,'Fin. Data'!B:B,,0) -> 211 | L23: Score (S&P) | M23: =IF(Inputs!B84 <> "",Inputs!B84,"")
B24: -Cash | C24: ='Fin. Data'!B39 -> 327 | D24: Debt/EBITDA | E24: =IFERROR(_xlfn.XLOOKUP("Total Debt",'Fin. Data'!A:A,'Fin. Data'!B:B,,0)/_xlfn.XLOOKUP("EBITDA",'Fin. Data'!A:A,'Fin. Data'!B:B,,0),"") -> 2.2382193 | F24: ='Segments '!C8 -> Greater china region | H24: ='Segments '!B8 -> 0.31262136 | I24: EBIT | K24: =_xlfn.XLOOKUP(I24,'Fin. Data'!A:A,'Fin. Data'!B:B,,0) -> 280.27 | L24: Price/Book Value | M24: =IFERROR((C20*C21/(E20-E21))/1000000,"") -> 2.4114812
B25: =Enterprise Value | C25: =C22+C23-C24 -> 3171.1739 | D25: "Others Assets"/Asset | E25: =IFERROR(_xlfn.XLOOKUP("Other Assets",'Fin. Data'!A:A,'Fin. Data'!B:B,,0)/_xlfn.XLOOKUP("Total Assets",'Fin. Data'!A:A,'Fin. Data'!B:B,,0),"") -> 0.16415384 | F25: ='Segments '!C9 -> United States | H25: ='Segments '!B9 -> 0.20184466 | I25: Net Income | K25: =_xlfn.XLOOKUP(I25,'Fin. Data'!A:A,'Fin. Data'!B:B,,0) -> 131.42 | L25: NCF(3y avg)/Asset | M25: =IFERROR(K31/E20,"") -> -0.0073627494
B26: Holdings (nac/int'l) | C26: - | D26: Debt/Assets | E26: =_xlfn.XLOOKUP(D26,'Fin. Data'!A:A,'Fin. Data'!B:B,,0) -> 0.36008265 | F26: Categories | H26: % Sales | I26: EPS | K26: =1000000*K25/C21 -> 0.51721953 | L26: Price/Net Inc. (3y avg) | M26: =IFERROR(C22/K30,"") -> 290.27075
B27: t liq. (Holdings/Vol.) | C27: - | D27: EBITDA Margin (average) | E27: =IFERROR(AVERAGE(_xlfn.XLOOKUP("EBITDA Margin",'Fin. Data'!A:A,'Fin. Data'!B:D,,0)),"") -> 0.2954313 | F27: ='Segments '!C18 -> Zegna branded products | H27: ='Segments '!B18 -> 0.58254553 | I27: ROA | K27: =IFERROR(K25/E20,"") -> 0.04303688 | L27: EV/Asset | M27: =IFERROR(C25/E20,"") -> 1.038483
B28: % Short | D28: Operating Margin (average) | E28: =IFERROR(AVERAGE(_xlfn.XLOOKUP("Operating Margin",'Fin. Data'!A:A,'Fin. Data'!B:D,,0)),"") -> 0.10626811 | F28: ='Segments '!C19 -> Thom Browne | H28: ='Segments '!B19 -> 0.19868611 | I28: ROIC | K28: =IFERROR(#REF!,"") | L28: EV/Ebitda (3y average) | M28: =IFERROR(C25/K29,"") -> 6.3714441
B29: Traffic ESG | D29: Net Income Margin (average) | E29: =IFERROR(AVERAGE(_xlfn.XLOOKUP("Net Income Margin",'Fin. Data'!A:A,'Fin. Data'!B:D,,0)),"") -> -0.0023115197 | F29: ='Segments '!C20 -> Tom Ford Fashion | H29: ='Segments '!B20 -> 0.12366899 | I29: EBITDA (3y average) | K29: =AVERAGE(_xlfn.XLOOKUP("EBITDA",'Fin. Data'!A:A,'Fin. Data'!B:D,,0)) -> 497.71667 | L29: Price/NCF (3y average) | M29: =IFERROR(C22/K31,"") -> -106.68364
B30: E | F30: ='Segments '!C23 -> Textile | H30: ='Segments '!B23 -> 0.079275369 | I30: Net Income (3y average) | K30: =AVERAGE(_xlfn.XLOOKUP("Net Income",'Fin. Data'!A:A,'Fin. Data'!B:D,,0)) -> 8.2633333 | L30: Bonds 1,3,5a (USD) | M30: -
B31: S | D31: Net Financial Cost/Avg Net Debt | E31: =IFERROR(-_xlfn.XLOOKUP("Net Financial Cost",'Fin. Data'!A:A,'Fin. Data'!B:B,,0)/AVERAGE(_xlfn.XLOOKUP("Net Debt",'Fin. Data'!A:A,'Fin. Data'!B:D,,0)),"") -> 0.046328309 | F31: ='Segments '!C22 -> Other | H31: ='Segments '!B22 -> 0.015823999 | I31: NCF (3y average) | K31: =AVERAGE(_xlfn.XLOOKUP("Net Financial Cost",'Fin. Data'!A:A,'Fin. Data'!B:D,,0)) -> -22.483333 | L31: Div+Rep.(3y avg)/Price | M31: =-IFERROR(SUM(E52:E54)/(3*C22),"") -> 0.11617591
B32: G | L32: Div. Yield | M32: =-IFERROR(L53/C22,"") -> 0.011285732
B33: INVESTMENT THESIS
B34: Pillars of Recommendation | H34: Recommendation | I34: Valuation Assumptions
B35: Pillar | C35: Explanation | H35: Hold | I35: Check DCF
B36: Strategic Aqcuisitions | C36: 2023: The acquisition of the Tom Ford brand was set to supercharge the Group's expansion in the luxury business.
B37: Vertical Integration | C37: By owning land and farms, ZEGNA ensures a high level of quality control in its textile development process, strengthening its financial performance.
B39: Risks of Investment | H39: Price Target | I39: Valuation
B40: Risk | C40: Explanation | H40: =IFERROR(DCF!D75,"") -> 6.1422803 | I40: Discount Rate | J40: =DCF!F50 -> 0.085 | L40: Price M. Upside | M40: =IFERROR(#REF!,"")
B41: Changes in consumer's preferences | C41: Luxury market companies are experiencing a slowdown in profits due to shifts in consumer preferences. Zegna's profit in H1 2024 is down by approximately 40% compared to H1 2023.
B42: Dependence on global markets | C42: A global economic recession can reduce disposable incomes, subsequently reducing demand for luxury goods. | I42: Upside | J42: =IFERROR(DCF!D74,"") -> -0.34933472 | L42: EV M. Upside | M42: =IFERROR(#REF!,"")
B43: Declining EPS | C43: Historical data reveals that the company's EPS has declined by 45% annually over the past years.
B44: FINANCIAL PERFORMANCE
B45: Year | C45: Net Sales | D45: Operating Margin | E45: Dividends + Share Buyback | F45: Net Cash Flow | G45: Debt/Assets | H45: Depreciation & Amortization | I45: Capex + Investments | J45: Cash Flow
B46: =B47-1 -> 2015 | C46: {=_xlfn.SORTBY(TRANSPOSE(_xlfn.XLOOKUP(C$45,'Fin. Data'!$A:$A,'Fin. Data'!$B:$J,,0)),$B$46:$B$54,-1)} -> N/A | D46: {=_xlfn.SORTBY(TRANSPOSE(_xlfn.XLOOKUP(D$45,'Fin. Data'!$A:$A,'Fin. Data'!$B:$J,,0)),$B$46:$B$54,-1)} -> - | E46: {=_xlfn.SORTBY(TRANSPOSE(_xlfn.XLOOKUP(E$45,'Fin. Data'!$A:$A,'Fin. Data'!$B:$J,,0)),$B$46:$B$54,-1)} -> #VALUE! | F46: =Inputs!J77 -> 0 | G46: {=_xlfn.SORTBY(TRANSPOSE(_xlfn.XLOOKUP(G$45,'Fin. Data'!$A:$A,'Fin. Data'!$B:$J,,0)),$B$46:$B$54,-1)} -> - | H46: {=_xlfn.SORTBY(TRANSPOSE(_xlfn.XLOOKUP(H$45,'Fin. Data'!$A:$A,'Fin. Data'!$B:$J,,0)),$B$46:$B$54,-1)} -> N/A | I46: {=_xlfn.SORTBY(TRANSPOSE(_xlfn.XLOOKUP(I$45,'Fin. Data'!$A:$A,'Fin. Data'!$B:$J,,0)),$B$46:$B$54,-1)} -> #VALUE! | L46: =J20 -> 2023 | M46: =L46-1 -> 2022
B47: =B48-1 -> 2016 | C47: N/A | D47: - | E47: #VALUE! | F47: =Inputs!I77 -> 0 | G47: - | H47: N/A | I47: #VALUE! | J47: Net Income | L47: =_xlfn.XLOOKUP($J47,'Fin. Data'!$A:$A,'Fin. Data'!B:B,,0) -> 131.42 | M47: =_xlfn.XLOOKUP($J47,'Fin. Data'!$A:$A,'Fin. Data'!C:C,,0) -> 54.24
B48: =B49-1 -> 2017 | C48: N/A | D48: - | E48: #VALUE! | F48: =Inputs!H77 -> 0 | G48: - | H48: N/A | I48: #VALUE! | J48: Operating CF | L48: =_xlfn.XLOOKUP($J48,'Fin. Data'!$A:$A,'Fin. Data'!B:B,,0) -> 298 | M48: =_xlfn.XLOOKUP($J48,'Fin. Data'!$A:$A,'Fin. Data'!C:C,,0) -> 154 | Q48: =F48/F47-1 -> #DIV/0! | R48: =H48/H47-1 -> #VALUE! | S48: =I48/I47-1 -> #VALUE!
B49: =B50-1 -> 2018 | C49: 1396 | D49: 0.089992837 | E49: -3 | F49: =Inputs!G77 -> -11.29 | G49: - | H49: 190 | I49: -394.65 | J49: Investing CF | L49: =_xlfn.XLOOKUP($J49,'Fin. Data'!$A:$A,'Fin. Data'!B:B,,0) -> 23.56 | M49: =_xlfn.XLOOKUP($J49,'Fin. Data'!$A:$A,'Fin. Data'!C:C,,0) -> -60.4 | Q49: =F49/F48-1 -> #DIV/0! | R49: =H49/H48-1 -> #VALUE! | S49: =I49/I48-1 -> #VALUE!
B50: =B51-1 -> 2019 | C50: 1479 | D50: 0.081920216 | E50: 0 | F50: =Inputs!F77 -> -10.42 | G50: 0.42916144 | H50: 198 | I50: 94 | J50: Net Capex | L50: =_xlfn.XLOOKUP($J50,'Fin. Data'!$A:$A,'Fin. Data'!B:B,,0) -> -61.46 | M50: =_xlfn.XLOOKUP($J50,'Fin. Data'!$A:$A,'Fin. Data'!C:C,,0) -> -51.52 | N50: =(C50/C49)-1 -> 0.059455587 | O50: =(D50/D49)-1 -> -0.089702921 | Q50: =F50/F49-1 -> -0.077059345 | R50: =H50/H49-1 -> 0.042105263 | S50: =I50/I49-1 -> -1.2381857
B51: =B52-1 -> 2020 | C51: 1158 | D51: 0.020803109 | E51: 1 | F51: =Inputs!E77 -> 130.68 | G51: 0.4457603 | H51: 212 | I51: 106 | J51: Investments & Acquisitions | L51: =_xlfn.XLOOKUP($J51,'Fin. Data'!$A:$A,'Fin. Data'!B:B,,0) -> 85.46 | M51: =_xlfn.XLOOKUP($J51,'Fin. Data'!$A:$A,'Fin. Data'!C:C,,0) -> -8.48 | N51: =(C51/C50)-1 -> -0.21703854 | O51: =(D51/D50)-1 -> -0.74605647 | Q51: =F51/F50-1 -> -13.541267 | R51: =H51/H50-1 -> 0.070707071 | S51: =I51/I50-1 -> 0.12765957
B52: =B53-1 -> 2021 | C52: 1529 | D52: 0.092851537 | E52: -766.88 | F52: =Inputs!D77 -> 160.17 | G52: 0.43413805 | H52: 193 | I52: -97 | J52: Financing CF | L52: =_xlfn.XLOOKUP($J52,'Fin. Data'!$A:$A,'Fin. Data'!B:B,,0) -> -270.88 | M52: =_xlfn.XLOOKUP($J52,'Fin. Data'!$A:$A,'Fin. Data'!C:C,,0) -> -312.88 | N52: =(C52/C51)-1 -> 0.32037997 | O52: =(D52/D51)-1 -> 3.4633491 | Q52: =F52/F51-1 -> 0.22566575 | R52: =H52/H51-1 -> -0.089622642 | S52: =I52/I51-1 -> -1.9150943
B53: =B54-1 -> 2022 | C53: 1573 | D53: 0.1091227 | E53: -38.03 | F53: =Inputs!C$77 -> -219.28 | G53: 0.37687036 | H53: 183 | I53: -60 | J53: Dividends | L53: =_xlfn.XLOOKUP($J53,'Fin. Data'!$A:$A,'Fin. Data'!B:B,,0) -> -27.07 | M53: =_xlfn.XLOOKUP($J53,'Fin. Data'!$A:$A,'Fin. Data'!C:C,,0) -> -23.03 | N53: =(C53/C52)-1 -> 0.028776978 | O53: =(D53/D52)-1 -> 0.17523844 | Q53: =F53/F52-1 -> -2.3690454 | R53: =H53/H52-1 -> -0.051813472 | S53: =I53/I52-1 -> -0.3814433
B54: =J20 -> 2023 | C54: 2060 | D54: 0.1168301 | E54: -31.07 | F54: =Inputs!B77 -> 50.68 | G54: 0.36008265 | H54: 211 | I54: 24 | J54: Share Buyback | L54: =_xlfn.XLOOKUP($J54,'Fin. Data'!$A:$A,'Fin. Data'!B:B,,0) -> -4 | M54: =_xlfn.XLOOKUP($J54,'Fin. Data'!$A:$A,'Fin. Data'!C:C,,0) -> -15 | N54: =(C54/C53)-1 -> 0.30959949 | O54: =(D54/D53)-1 -> 0.070630601 | Q54: =F54/F53-1 -> -1.23112 | R54: =H54/H53-1 -> 0.15300546 | S54: =I54/I53-1 -> -1.4
B55: Annual Growth Rate | C55: =IFERROR((C54/C49)^(1/5)-1,"") -> 0.080926989 | D55: =IFERROR((D54/D49)^(1/5)-1,"") -> 0.053584467 | F55: =IFERROR((F54/F49)^(1/5)-1,"") -> -2.3502946 | H55: =IFERROR((H54/H49)^(1/5)-1,"") -> 0.02118816 | J55: FX | L55: =_xlfn.XLOOKUP($J55,'Fin. Data'!$A:$A,'Fin. Data'!B:B,,0) -> 0 | M55: =_xlfn.XLOOKUP($J55,'Fin. Data'!$A:$A,'Fin. Data'!C:C,,0) -> 0 | N55: =(C55/C54)-1 -> -0.99996072 | O55: =(D55/D54)-1 -> -0.54134706
B56: Average Growth Rate | C56: =IFERROR(AVERAGE(N47:N54),"") -> 0.1002347 | D56: =IFERROR(AVERAGE(O50:O54),"") -> 0.57469175 | F56: =IFERROR(AVERAGE(Q50:Q54),"") -> -3.3985652 | H56: =IFERROR(AVERAGE(S50:S54),"") -> -0.96141276 | J56: Changes in Cash | L56: =L48-L49+L52-L53-L54 -> 34.63 | M56: =M48-M49+M52-M53-M54 -> -60.45
B57: CVAR | C57: =IFERROR(STDEV(C47:C54)/AVERAGE(C47:C54),"") -> 0.19393462 | D57: =IFERROR(STDEV(D46:D54)/AVERAGE(D46:D54),"") -> 0.3999126 | F57: =IFERROR(STDEV(F46:F54)/AVERAGE(F46:F54),"") -> 9.6254694 | H57: =IFERROR(STDEV(H46:H54)/AVERAGE(H46:H54),"") -> 0.058897534 | J57: Inventory/D Revenues | L57: =IFERROR(SUM(I51:I54)/(C54-C50),"") -> -0.046471601 | M57: =IFERROR((SUM(I51:I54)-SUM(H51:H54))/(C54-C50),"") -> -1.4216867
B58: Last Year | C58: =IFERROR(C54/C53-1,"") -> 0.30959949 | D58: =IFERROR(D54/D53-1,"") -> 0.070630601 | F58: =IFERROR(1-(F54/F53),"") -> 1.23112 | H58: =IFERROR(1-(H54/H53),"") -> -0.15300546 | J58: t inversiones; t adq. neto dep. | L58: =IFERROR(L57/E27,"") -> -0.15730087 | M58: =IFERROR(M57/E27,"") -> -4.8122414
B59: QUALITATIVE ANALYSIS
B60: SWOT ANALYSIS | J60: HOLDERS
B61: Pros | E61: Cons | J61: Name | M61: % Stake
J62: Monterubello SS | M62: 0.5982
B63: Good Reputation: | C63: Ermenegildo Zegna is known for its high quality materials and is considered as one of the top menswear brands. | E63: Specific target audience: | F63: The Group's target audience counts with high-income professionals, executives, and entrepreneurs, meaning that its demand can be limited especially in periods of recession. | J63: Strategic Holding Group SARL | M63: 0.121
J64: T. Rowe Price International Ltd. | M64: 0.052
J65: Capital Research & Management Co. (Global Investors) | M65: 0.0342
B66: Strong customer base: | C66: A loyal customer base contributes to repeat business. | E66: Low Dividend payout ratio: | F66: ZGN Divident payout ratio can be considered as Low when compared to the top 25% dividend payers in the luxury market. | J66: Ermenegildo Zegna di Monte Rubello | M66: 0.0326
J67: Capital Research & Management Co. (World Investors) | M67: 0.0256
J68: Invesco Advisers, Inc. | M68: 0.016
J69: Public Investment Fund (Investment Company) | M69: 0.0148
J70: Artisan Partners Holdings LP | M70: 0.0147
J71: Universal-Investment-Gesellschaft mbH (Invt Mgmt) | M71: 0.007
B72: Opportunities | E72: Risks | J72: FIL LTD | M72: 0.0057
J73: Gam Holding Ag | M73: 0.0032
B74: Expansion to emerging markets: | C74: Potential growth in emerging luxury markets like China and India. | E74: Progressive slowdown in the luxury market: | F74: The luxury market is experiencing a slowdown in profits, mostly due to shifts in consumer preferences. | J74: Tabor Asset Management, LP | M74: 0.0025
J75: Nuveen Asset Management, LLC | M75: 0.0021
J76: American Funds Insurance Ser-Global Small Capitalization Fund | M76: 0.0053
B77: Diversification: | C77: This would allow the brand to appeal to a broader audience. | J77: Smallcap World Fund | M77: 0.0545
E78: Challenging stock performance: | F78: This may lead to concerns among investors. | J78: College Retirement Equities Fund-Stock Account | M78: 0.0021
J79: Old Westbury Small & Mid Cap Strategies Fund | M79: 0.002
J80: TOTAL | M80: =SUM(M61:M79) -> 0.9935
B82: NOTES | G82: STOCK PERFORMANCE (3 years)
G107: =E2 -> #VALUE! | I107: =Peers!D8 -> #VALUE! | J107: =Peers!E8 -> #VALUE! | K107: =Peers!F8 -> #VALUE! | L107: =Peers!G8 -> #VALUE! | M107: =Peers!H8 -> #VALUE!

Sheet Segments 
B2: ="Regions "&"("&[2]OP!$J$20&")" -> Regions (2023) | Q2: Products
D3: Nominal value | K3: YoY Growth
B4: Weight | C4: Region | D4: =[2]OP!J20 -> 2023 | E4: =D4-1 -> 2022 | F4: =E4-1 -> 2021 | G4: =F4-1 -> 2020 | H4: =G4-1 -> 2019 | I4: =H4-1 -> 2018 | K4: =[2]OP!J20 -> 2023 | L4: =K4-1 -> 2022 | M4: =L4-1 -> 2021 | N4: =M4-1 -> 2020 | O4: =N4-1 -> 2019 | P4: =O4-1 -> 2018
B5: =IFERROR(D5/$D$13,"") -> 0.12490291 | C5: EMEA(excuding Italy and UK) | D5: 257.3 | E5: =(182.2*1000)*0.001 -> 182.2 | F5: =(217.6*1000)*0.001 -> 217.6 | G5: =(184.6*1000)*0.001 -> 184.6 | H5: =(260.5*1000)*0.001 -> 260.5 | I5: =(290.5*1000)*0.001 -> 290.5 | K5: =(D5-E5)/E5 -> 0.41218441 | L5: =(E5-F5)/F5 -> -0.16268382 | M5: =(F5-G5)/G5 -> 0.1787649 | N5: =(G5-H5)/H5 -> -0.29136276 | O5: =(H5-I5)/I5 -> -0.10327022 | P5: -
B6: =IFERROR(D6/$D$13,"") -> 0.14791262 | C6: Italy | D6: =(304.7*1000)*0.001 -> 304.7 | E6: =(236.3*1000)*0.001 -> 236.3 | F6: =(187.7*1000)*0.001 -> 187.7 | G6: =(138.4*1000)*0.001 -> 138.4 | H6: =(157.5*1000)*0.001 -> 157.5 | I6: =(113*1000)*0.001 -> 113 | K6: =(D6-E6)/E6 -> 0.28946255 | L6: =(E6-F6)/F6 -> 0.25892381 | M6: =(F6-G6)/G6 -> 0.35621387 | N6: =(G6-H6)/H6 -> -0.12126984 | O6: =(H6-I6)/I6 -> 0.39380531 | P6: -
B7: =IFERROR(D7/$D$13,"") -> 0.044616505 | C7: Japan | D7: =(91.91*1000)*0.001 -> 91.91 | E7: =(68.94*1000)*0.001 -> 68.94 | F7: =(65.62*1000)*0.001 -> 65.62 | G7: =(70.23*1000)*0.001 -> 70.23 | H7: =(101*1000)*0.001 -> 101 | I7: =(84.86*1000)*0.001 -> 84.86 | K7: =(D7-E7)/E7 -> 0.33318828 | L7: =(E7-F7)/F7 -> 0.050594331 | M7: =(F7-G7)/G7 -> -0.065641464 | N7: =(G7-H7)/H7 -> -0.30465347 | O7: =(H7-I7)/I7 -> 0.19019562 | P7: -
B8: =IFERROR(D8/$D$13,"") -> 0.31262136 | C8: Greater china region | D8: =(644*1000)*0.001 -> 644 | E8: =(520.5*1000)*0.001 -> 520.5 | F8: =(696.5*1000)*0.001 -> 696.5 | G8: =(500.2*1000)*0.001 -> 500.2 | H8: =(513.3*1000)*0.001 -> 513.3 | I8: =(477.9*1000)*0.001 -> 477.9 | K8: =(D8-E8)/E8 -> 0.23727185 | L8: =(E8-F8)/F8 -> -0.25269203 | M8: =(F8-G8)/G8 -> 0.39244302 | N8: =(G8-H8)/H8 -> -0.025521138 | O8: =(H8-I8)/I8 -> 0.074074074 | P8: -
B9: =IFERROR(D9/$D$13,"") -> 0.20184466 | C9: United States | D9: =(415.8*1000)*0.001 -> 415.8 | E9: =(284.8*1000)*0.001 -> 284.8 | F9: =(208.3*1000)*0.001 -> 208.3 | G9: =(131.1*1000)*0.001 -> 131.1 | H9: =(230.3*1000)*0.001 -> 230.3 | I9: =(228.6*1000)*0.001 -> 228.6 | K9: =(D9-E9)/E9 -> 0.45997191 | L9: =(E9-F9)/F9 -> 0.36725876 | M9: =(F9-G9)/G9 -> 0.58886346 | N9: =(G9-H9)/H9 -> -0.43074251 | O9: =(H9-I9)/I9 -> 0.0074365704 | P9: -
B10: =IFERROR(D10/$D$13,"") -> 0.16810194 | C10: Other | D10: =(346.29*1000)*0.001 -> 346.29 | E10: =(280.26*1000)*0.001 -> 280.26 | F10: =(153.28*1000)*0.001 -> 153.28 | G10: =(133.47*1000)*0.001 -> 133.47 | H10: =(216.4*1000)*0.001 -> 216.4 | I10: =(201.14*1000)*0.001 -> 201.14 | K10: =(D10-E10)/E10 -> 0.23560265 | L10: =(E10-F10)/F10 -> 0.82841858 | M10: =(F10-G10)/G10 -> 0.14842287 | N10: =(G10-H10)/H10 -> -0.38322551 | O10: =(H10-I10)/I10 -> 0.075867555 | P10: -
B11: =IFERROR(D11/$D$13,"") -> 0
B12: =IFERROR(D12/$D$13,"") -> 0
B13: =SUM(B5:B12) -> 1 | C13: TOTAL | D13: =SUM(D5:D12) -> 2060 | E13: =SUM(E5:E12) -> 1573 | F13: =SUM(F5:F12) -> 1529 | G13: =SUM(G5:G12) -> 1158 | H13: =SUM(H5:H12) -> 1479 | I13: =SUM(I5:I12) -> 1396 | K13: =(D13-E13)/E13 -> 0.30959949 | L13: =(E13-F13)/F13 -> 0.028776978 | M13: =(F13-G13)/G13 -> 0.32037997 | N13: =(G13-H13)/H13 -> -0.21703854 | O13: =(H13-I13)/I13 -> 0.059455587 | P13: -
B15: ="Categories "&"("&[2]OP!$J$20&")" -> Categories (2023)
D16: Nominal value | K16: YoY Growth
B17: Weight | C17: Category | D17: =[2]OP!J20 -> 2023 | E17: =D17-1 -> 2022 | F17: =E17-1 -> 2021 | G17: =F17-1 -> 2020 | H17: =G17-1 -> 2019 | I17: =H17-1 -> 2018 | K17: =[2]OP!J20 -> 2023 | L17: =K17-1 -> 2022 | M17: =L17-1 -> 2021 | N17: =M17-1 -> 2020 | O17: =N17-1 -> 2019 | P17: =O17-1 -> 2018
B18: =IFERROR(D18/$D$24,"") -> 0.58254553 | C18: Zegna branded products | D18: =(1199.77*1000)*0.001 -> 1199.77 | E18: =(973.35*1000)*0.001 -> 973.35 | F18: =(1002.23*1000)*0.001 -> 1002.23 | G18: =(726.52*1000)*0.001 -> 726.52 | H18: =(1029.25*1000)*0.001 -> 1029.25 | I18: =(1097.98*1000)*0.001 -> 1097.98 | K18: =(D18-E18)/E18 -> 0.2326193 | L18: =(E18-F18)/F18 -> -0.028815741 | M18: =(F18-G18)/G18 -> 0.37949403 | N18: =(G18-H18)/H18 -> -0.29412679 | O18: =(H18-I18)/I18 -> -0.062596769 | P18: -
B19: =IFERROR(D19/$D$24,"") -> 0.19868611 | C19: Thom Browne | D19: =(409.2*1000)*0.001 -> 409.2 | E19: =(347.66*1000)*0.001 -> 347.66 | F19: =(311.55*1000)*0.001 -> 311.55 | G19: =(204.88*1000)*0.001 -> 204.88 | H19: =(179.75*1000)*0.001 -> 179.75 | I19: =(22.5*1000)*0.001 -> 22.5 | K19: =(D19-E19)/E19 -> 0.17701202 | L19: =(E19-F19)/F19 -> 0.11590435 | M19: =(F19-G19)/G19 -> 0.52064623 | N19: =(G19-H19)/H19 -> 0.13980529 | O19: =(H19-I19)/I19 -> 6.9888889 | P19: -
B20: =IFERROR(D20/$D$24,"") -> 0.12366899 | C20: Tom Ford Fashion | D20: =(254.7*1000)*0.001 -> 254.7 | E20: N/A | F20: N/A | G20: N/A | H20: N/A | I20: N/A | K20: - | L20: - | M20: - | N20: - | O20: - | P20: -
B21: =IFERROR(D21/$D$24,"") -> 0 | C21: Strategic Alliances | D21: 0 | E21: =(103.02*1000)*0.001 -> 103.02 | F21: =(88.66*1000)*0.001 -> 88.66 | G21: =(93.91*1000)*0.001 -> 93.91 | H21: =(102.66*1000)*0.001 -> 102.66 | I21: =(108.96*1000)*0.001 -> 108.96 | K21: =(D21-E21)/E21 -> -1 | L21: =(E21-F21)/F21 -> 0.16196707 | M21: =(F21-G21)/G21 -> -0.05590459 | N21: =(G21-H21)/H21 -> -0.085232807 | O21: =(H21-I21)/I21 -> -0.057819383 | P21: -
B22: =IFERROR(D22/$D$24,"") -> 0.015823999 | C22: Other | D22: =5.18+27.41 -> 32.59 | E22: =(4.55*1000)*0.001 -> 4.55 | F22: =((3.91+1.41)*1000)*0.001 -> 5.32 | G22: =((18.82+13.86)*1000)*0.001 -> 32.68 | H22: =((26.04+19.84)*1000)*0.001 -> 45.88 | I22: =((29.24+20.71)*1000)*0.001 -> 49.95 | K22: =(D22-E22)/E22 -> 6.1626374 | L22: =(E22-F22)/F22 -> -0.14473684 | M22: =(F22-G22)/G22 -> -0.8372093 | N22: =(G22-H22)/H22 -> -0.28770706 | O22: =(H22-I22)/I22 -> -0.081481481 | P22: -
B23: =IFERROR(D23/$D$24,"") -> 0.079275369 | C23: Textile | D23: =(163.27*1000)*0.001 -> 163.27 | E23: =(144.42*1000)*0.001 -> 144.42 | F23: =(121.24*1000)*0.001 -> 121.24 | G23: =(100.01*1000)*0.001 -> 100.01 | H23: =(121.46*1000)*0.001 -> 121.46 | I23: =(116.61*1000)*0.001 -> 116.61 | K23: =(D23-E23)/E23 -> 0.13052209 | L23: =(E23-F23)/F23 -> 0.19119103 | M23: =(F23-G23)/G23 -> 0.21227877 | N23: =(G23-H23)/H23 -> -0.17660135 | O23: =(H23-I23)/I23 -> 0.04159163 | P23: -
B24: =SUM(B18:B23) -> 1 | C24: TOTAL | D24: =SUM(D18:D23) -> 2059.53 | E24: =SUM(E18:E23) -> 1573 | F24: =SUM(F18:F23) -> 1529 | G24: =SUM(G18:G23) -> 1158 | H24: =SUM(H18:H23) -> 1479 | I24: =SUM(I18:I23) -> 1396 | K24: =(D24-E24)/E24 -> 0.3093007 | L24: =(E24-F24)/F24 -> 0.028776978 | M24: =(F24-G24)/G24 -> 0.32037997 | N24: =(G24-H24)/H24 -> -0.21703854 | O24: =(H24-I24)/I24 -> 0.059455587 | P24: -
B26: Categories | D26: Description | I26: Graphs
B27: Tom ford fashion | D27: Collection of fashion from Tom Ford ranging from glasses to suits
B28: Textile | D28: Sale of raw and transformed material to other luxury companies
B29: Zegna branded products | D29: Products from zegna mainly clothing
B30: Thom Browne | D30: Not so traditional luxury clothing
B31: Strategic Alliances | D31: Alliances mainly to do consultation for other big players in the market
B34: Industry | J34: Graphs (Industry Forecasts)
B35: Drivers | D35: Description
B36: Casualisation | D36: Luxury wear becomes each day more casual and less forma
B37: China | D37: Growing market in China for luxuxry goods
B38: Sales forecast
B39: Source | D39: Market Growth CAGR | G39: Period
B40: https://www.statista.com/outlook/cmo/luxury-goods/luxury-fashion/luxury-apparel/worldwide | D40: 0.0292 | G40: 2024-2029
B41: https://www.grandviewresearch.com/industry-analysis/luxury-goods-market-report | D41: 0.068 | G41: 2024-2030
B42: https://www.cognitivemarketresearch.com/affordable-luxury-fashion-market-report | D42: 0.05 | G42: 2024-2030
B43: Average | D43: =AVERAGE(D40:F42) -> 0.049066667
B44: Company's Strategy / Extra Notes
B47: Group aims for compounded average annual growth of revenues over 10% and of Adjusted EBIT of around 20%, and a strong Cash Surplus. Group sees positive momentum across brands and shares the business strategy for Tom Ford Fashion, where it expects revenues to grow at a compounded average rate1 of over 10% in the medium term.
B56: Zegna branded products will continue to bet on the silent luxury products

Sheet Acuerdo
A1: Invertir
A2: NO invertir
A3: Mantener sin elevar posición
A4: Mantener (y seguir comprando)
A5: Liquidar
A6: PENDIENTE

Sheet Peers
B1: Peer Logo | C1: Peer Name | D1: Description
C2: #VALUE! | D2: Brunello Cucinelli SpA is an Italy-based company engaged in the fashion industry. The Company designs, manufactures and sells clothing for woman and men, cashmere products and accessories collections. The Company markets its products through direct retail channel; wholesale monobrand channel, consisting of franchised monobrand retail stores, and wholesale multibrand channel. The Company is active globally.
C3: #VALUE! | D3: Moncler SpA is an Italy-based company engaged in fashion industry. The Company designs, produces and distributes clothing and accessories through Moncler brand. The Company offers mainly sportswear, outerwear, knitwear and skiwear. Moncler SpA trades its products through approximately 122 stores, as well as through the wholesale distribution channel. Moncler SpA operates in approximately 66 countries.
C4: #VALUE! | D4: Tod's SpA is an Italy-based holding company. The Company, through its subsidiaries, is primarily engaged in creation, production and distribution of shoes, leather goods and accessories, apparel. The Company operates in the luxury sector under brands, such as TOD'S, ROGER VIVIER, HOGAN and FAY. The Company relies on approximately three channels: directly operated stores (DOS), franchised retail outlets, as well as a series of selected, independent multiband stores.
C5: #VALUE! | D5: Prada SpA is an Italy-based company engaged in fashion industry. The Company is a parent of the Prada Group. The Company, along with its subsidiaries, is engaged in the design, production and distribution of leather goods, handbags, clothing, eyewear, fragrances, footwear and accessories. The Company trades its products through several brands, such as Prada, Miu Miu, The Church and The Car Shoe. Prada SpA operates in approximately 70 countries through directly operated stores, franchise operated stores, a network of selected multi-brand stores and department stores.
C6: #VALUE! | D6: Hugo Boss AG is a Germany-based developer and marketer of men's and women's clothing and accessories for the international fashion market. The Company's brand portfolio comprises BOSS, BOSS Orange, Camel, Green, Black, Blue and HUGO and others: BOSS comprises business wear, leisurewear and evening apparel, as well as watches, eyewear and fragrances; BOSS Orange and BOSS Camel focuses on womenswear; BOSS Green comprises sportswear and BOSS Black focuses on modern tailoring, BOSS Blue focuses on denimwear, HUGO provides apparel for both business and leisure, as well as shoes, accessories and licensed fragrances.
B8: In Millions USD | C8: =OP!E2 -> #VALUE! | D8: =C2 -> #VALUE! | E8: =C3 -> #VALUE! | F8: =C4 -> #VALUE! | G8: =C5 -> #VALUE! | H8: =C6 -> #VALUE! | I8: AVERAGE | J8: Deviation from Average
B9: Company Info | I9: =IFERROR(AVERAGE(C9:H9),"") | L9: TRAFFIC
B10: Market Cap | C10: {=_FV(C8,"Market cap",TRUE)/1000000} -> 2398.6039 | D10: {=_FV(D8,"Market cap",TRUE)/1000000} -> 7024.4 | E10: {=_FV(E8,"Market cap",TRUE)/1000000} -> 13877.7 | F10: {=_FV(F8,"Market cap",TRUE)/1000000} -> 1127.166 | G10: {=_FV(G8,"Market cap",TRUE)/1000000} -> 120264.7 | H10: {=_FV(H8,"Market cap",TRUE)/1000000} -> 2923.712 | I10: =IFERROR(AVERAGE(C10:H10),"") -> 24602.714 | J10: =SQRT((C10-I10)^2) -> 22204.11 | M10: Best Value
B11: Net Sales (current) | C11: =C56 -> 2060 | D11: =D56 -> 1257.4575 | E11: =E56 -> 3293.3652 | F11: =F56 -> 1243.4198 | G11: =G56 -> 2816.7493 | H11: =H56 -> 4631.7857 | I11: =IFERROR(AVERAGE(C11:H11),"") -> 2550.4629 | J11: =SQRT((C11-I11)^2) -> 490.46292
B12: Profitability | I12: =IFERROR(AVERAGE(C12:H12),"") | M12: Important Value
B13: Sales Growth (ttm) | C13: =C56/C55-1 -> 0.30959949 | D13: =D56/D55-1 -> 0.27754496 | E13: =E56/E55-1 -> 0.18227064 | F13: =F56/F55-1 -> 0.15377505 | G13: =G56/G55-1 -> 0.048876729 | H13: =H56/H55-1 -> 0.18541238 | I13: =IFERROR(AVERAGE(C13:H13),"") -> 0.19291321 | J13: =SQRT((C13-I13)^2) -> 0.11668628
B14: Sales Growth (36m) | C14: =C56/C54-1 -> 0.77892919 | D14: =D56/D54-1 -> 0.89261329 | E14: =E56/E54-1 -> 0.87211231 | F14: =F56/F54-1 -> 0.59804135 | G14: =G56/G54-1 -> 0.94034996 | H14: =H56/H54-1 -> 0.94887264 | I14: =IFERROR(AVERAGE(C14:H14),"") -> 0.83848646 | J14: =SQRT((C14-I14)^2) -> 0.059557267 | M14: Worst Value
B15: Operating Margin | C15: =C59/C56 -> 0.1168301 | D15: =D59/D56 -> 0.16447491 | E15: =E59/E56 -> 0.29952212 | F15: =F59/F56 -> 0.057292092 | G15: =G59/G56 -> 0.31681856 | H15: =H59/H56 -> 0.097769121 | I15: =IFERROR(AVERAGE(C15:H15),"") -> 0.17545115 | J15: =SQRT((C15-I15)^2) -> 0.058621052
B16: Net Income Margin | C16: =C62/C56 -> 0.071359223 | D16: =D62/D56 -> 0.10865967 | E16: =E62/E56 -> 0.065578341 | F16: =F62/F56 -> 0.044393361 | G16: =G61/G56 -> 0.094771819 | H16: =H62/H56 -> 0.049797474 | I16: =IFERROR(AVERAGE(C16:H16),"") -> 0.072426648 | J16: =SQRT((C16-I16)^2) -> 0.0010674247
B17: Return on Equity (RoE) | C17: =C62/C74 -> 0.15846323 | D17: =D62/D74 -> 0.27293971 | E17: =E62/E74 -> 0.06088173 | F17: =F62/F74 -> 0.030307896 | G17: =G61/G74 -> 0.085095859 | H17: =H62/H74 -> 0.15942029 | I17: =IFERROR(AVERAGE(C17:H17),"") -> 0.12785145 | J17: =SQRT((C17-I17)^2) -> 0.030611778
B18: Return on Invested Capital (ROIC) | C18: =(1+C61/(C59+C60))*C59/(C73+C74-C65) -> 0.17527185 | D18: =(1+D61/(D59+D60))*D59/(D73+D74-D65) -> 0.205748 | E18: =(1+E61/(E59+E60))*E59/(E73+E74-E65) -> 0.3738004 | F18: =(1+F61/(F59+F60))*F59/(F73+F74-F65) -> 0.03334261 | G18: =(1+G61/(G59+G60))*G59/(G73+G74-G65) -> 0.21285129 | H18: =(1+H61/(H59+H60))*H59/(H73+H74-H65) -> 0.20144744 | I18: =IFERROR(AVERAGE(C18:H18),"") -> 0.20041027 | J18: =SQRT((C18-I18)^2) -> 0.025138416
B19: Solvency | I19: =IFERROR(AVERAGE(C19:H19),"")
B20: Debt/Assets | C20: =C73/C70 -> 0.36008265 | D20: =D73/D70 -> 0.57907934 | E20: =E73/E70 -> 0.1705542 | F20: =F73/F70 -> 0.30266499 | G20: =G73/G70 -> 0.48676847 | H20: =H73/H70 -> 0.36578341 | I20: =IFERROR(AVERAGE(C20:H20),"") -> 0.37748884 | J20: =SQRT((C20-I20)^2) -> 0.01740619
B21: Net Debt/EBITDA | C21: =(C73-C65)/C58 -> 0.50330293 | D21: =(D73-D65)/D58 -> 2.1214219 | E21: - | F21: =(F73-F65)/F58 -> 4.4558659 | G21: =(G73-G65)/G58 -> 1.7049336 | H21: =(H73-H65)/H58 -> 1.5318456 | I21: =IFERROR(AVERAGE(C21:H21),"") -> 2.063474 | J21: =SQRT((C21-I21)^2) -> 1.5601711
B22: Interest Coverage Ratio | C22: - | D22: - | E22: - | F22: - | G22: - | H22: - | I22: =IFERROR(AVERAGE(C22:H22),"") | J22: =SQRT((C22-I22)^2) -> #VALUE!
B23: Liquidity
B24: Current Ratio | C24: =C68/C72 -> 1.2722186 | D24: =D68/D72 -> 1.2420418 | E24: =E68/E72 -> 1.8873561 | F24: =F68/F72 -> 1.629666 | G24: =G68/G72 -> 1.4502655 | H24: =H68/H72 -> 1.6429692 | I24: =IFERROR(AVERAGE(C24:H24),"") -> 1.5207529 | J24: =SQRT((C24-I24)^2) -> 0.24853427
B25: Quick Ratio | C25: =(C65+C66)/C72 -> 0.53716752 | D25: =(D65+D66)/D72 -> 0.43681833 | E25: =(E65+E66)/E72 -> 1.3107334 | F25: =(F65+F66)/F72 -> 0.42581608 | G25: =(G65+G66)/G72 -> 0.80764567 | H25: =(H65+H66)/H72 -> 0.45315114 | I25: =IFERROR(AVERAGE(C25:H25),"") -> 0.66188869 | J25: =SQRT((C25-I25)^2) -> 0.12472118
B26: Activity | I26: =IFERROR(AVERAGE(C26:H26),"")
B27: Inventory Turnover | C27: =C57/C67 -> 1.2756846 | D27: =D57/D67 -> 2.7327031 | E27: =E57/E67 -> 1.507988 | F27: =F57/F67 -> 2.1705546 | G27: =G57/G67 -> 2.1642331 | H27: =H57/H67 -> 1.3744955 | I27: =IFERROR(AVERAGE(C27:H27),"") -> 1.8709431 | J27: =SQRT((C27-I27)^2) -> 0.59525857
B28: Acc. Receivable Turnover | C28: =C56/C66 -> 7.5457875 | D28: =D56/D66 -> 14.57618 | E28: =E56/E66 -> 9.1650604 | F28: =F56/F66 -> 10.587594 | G28: =G56/G66 -> 3.5249628 | H28: =H56/H66 -> 11.162234 | I28: =IFERROR(AVERAGE(C28:H28),"") -> 9.4269698 | J28: =SQRT((C28-I28)^2) -> 1.8811823
A29: Price/Sales | B29: Payables Turnover | C29: =C57/C71 -> 2.3002187 | D29: =D57/D71 -> 4.7224622 | E29: =E57/E71 -> 1.268854 | F29: =F57/F71 -> 5.5193572 | G29: =G57/G71 -> 1.3326669 | H29: =H57/H71 -> 2.5615598 | I29: =IFERROR(AVERAGE(C29:H29),"") -> 2.9508531 | J29: =SQRT((C29-I29)^2) -> 0.65063439
B30: Fixed Asset Turnover | C30: =C56/C69 -> 2.691368 | D30: =D56/D69 -> 1.4725298 | E30: =E56/E69 -> 2.7568334 | F30: =F56/F69 -> 1.539582 | G30: =G56/G69 -> 3.1116964 | H30: =H56/H69 -> 7.6744531 | I30: =IFERROR(AVERAGE(C30:H30),"") -> 3.2077438 | J30: =SQRT((C30-I30)^2) -> 0.51637578
B31: Total Asset Turnover | C31: =C56/C70 -> 0.67460032 | D31: =D56/D70 -> 0.82573847 | E31: =E56/E70 -> 0.59779748 | F31: =F56/F70 -> 0.53666973 | G31: =G56/G70 -> 0.53768812 | H31: =H56/H70 -> 1.2088134 | I31: =IFERROR(AVERAGE(C31:H31),"") -> 0.73021792 | J31: =SQRT((C31-I31)^2) -> 0.055617599
B32: Valuation | I32: =IFERROR(AVERAGE(C32:H32),"")
B33: Price/Earnings | C33: =C10/C62 -> 16.317034 | D33: =D10/D62 -> 51.409991 | E33: =E10/E62 -> 64.256517 | F33: =F10/F62 -> 20.419827 | G33: =G10/G61 -> 450.51657 | H33: =H10/H62 -> 12.6759 | I33: =IFERROR(AVERAGE(C33:H33),"") -> 102.59931 | J33: =SQRT((C33-I33)^2) -> 86.282273
B34: Price/Sales | C34: =C10/C56 -> 1.1643708 | D34: =D10/D56 -> 5.5861926 | E34: =E10/E56 -> 4.2138358 | F34: =F10/F56 -> 0.90650477 | G34: =G10/G56 -> 42.696275 | H34: =H10/H56 -> 0.63122782 | I34: =IFERROR(AVERAGE(C34:H34),"") -> 9.1997344 | J34: =SQRT((C34-I34)^2) -> 8.0353636
B35: Price/Book | C35: =C10/C74 -> 2.5856498 | D35: =D10/D74 -> 14.031828 | E35: =E10/E74 -> 3.9120479 | F35: =F10/F74 -> 0.61888201 | G35: =G10/G74 -> 38.337094 | H35: =H10/H74 -> 2.0207957 | I35: =IFERROR(AVERAGE(C35:H35),"") -> 10.25105 | J35: =SQRT((C35-I35)^2) -> 7.6653998
B36: EV/Sales | C36: =(C73+C10-C65)/C56 -> 1.5394048 | D36: =(D73+D10-D65)/D56 -> 6.1936209 | E36: =(E73+E10-E65)/E56 -> 4.1644463 | F36: =(F73+F10-F65)/F56 -> 1.3951945 | G36: =(G73+G10-G65)/G56 -> 43.513408 | H36: =(H73+H10-H65)/H56 -> 0.90570959 | I36: =IFERROR(AVERAGE(C36:H36),"") -> 9.6186307 | J36: =SQRT((C36-I36)^2) -> 8.0792259
B37: EV/EBITDA | C37: =(C73+C10-C65)/C58 -> 2.0659114 | D37: =(D73+D10-D65)/D58 -> 21.631001 | E37: =(E73+E10-E65)/E58 -> 13.328198 | F37: =(F73+F10-F65)/F58 -> 12.721364 | G37: =(G73+G10-G65)/G58 -> 90.789897 | H37: =(H73+H10-H65)/H58 -> 5.0546427 | I37: =IFERROR(AVERAGE(C37:H37),"") -> 24.265169 | J37: =SQRT((C37-I37)^2) -> 22.199257
B38: Stock Info | I38: =IFERROR(AVERAGE(C38:H38),"")
B39: Float | C39: =OP!M20 -> 59.07M | D39: 33.92 | E39: 219.57 | F39: 6.17 | G39: 512.35 | H39: 47.9 | I39: =IFERROR(AVERAGE(C39:H39),"") -> 163.982 | J39: =SQRT((C39-I39)^2) -> #VALUE!
B40: b (Yahoo) | C40: =OP!M22 -> 0.66 | D40: 1.03 | E40: 1.02 | F40: 0.89 | G40: 1.17 | H40: 1.34 | I40: =IFERROR(AVERAGE(C40:H40),"") -> 1.0183333 | J40: =SQRT((C40-I40)^2) -> 0.35833333
B41: Dividend Yield (yahoo finance) | C41: =OP!M32 -> 0.011285732 | D41: 0.0109 | E41: 0.024 | F41: - | G41: 0.0217 | H41: 0.0357 | I41: =IFERROR(AVERAGE(C41:H41),"") -> 0.020717146 | J41: =SQRT((C41-I41)^2) -> 0.0094314148
B42: Stock Performance
B43: 1y | C43: -0.2819 | D43: 0.3579 | E43: 0.0314 | F43: -0.1179 | G43: 0.1942 | H43: -0.3166 | I43: =IFERROR(AVERAGE(C43:H43),"") -> -0.02215 | J43: =SQRT((C43-I43)^2) -> 0.25975
B44: 3y | C44: =7.61/10.45-1 -> -0.27177033 | D44: =91.1/56.1-1 -> 0.62388592 | E44: =50.48/64.68-1 -> -0.21954236 | F44: =37.65/60.49-1 -> -0.37758307 | G44: =14.89/13.09-1 -> 0.13750955 | H44: =43/52.16-1 -> -0.1756135 | I44: =IFERROR(AVERAGE(C44:H44),"") -> -0.047185633 | J44: =SQRT((C44-I44)^2) -> 0.2245847
B45: Current Price | C45: {=_FV(C8,"Price")} -> 9.44 | D45: {=_FV(D8,"Price")} -> 106.45 | E45: {=_FV(E8,"Price")} -> 52.18 | F45: {=_FV(F8,"Price")} -> 37.65 | G45: {=_FV(G8,"Price")} -> 5.78 | H45: {=_FV(H8,"Price")} -> 41.46 | I45: =IFERROR(AVERAGE(C45:H45),"") -> 42.16 | J45: =SQRT((C45-I45)^2) -> 32.72
B46: Average Target Price | C46: 10.68 | D46: 109.2 | E46: 67.8 | F46: - | G46: - | H46: 55 | I46: =IFERROR(AVERAGE(C46:H46),"") -> 60.67 | J46: =SQRT((C46-I46)^2) -> 49.99
B47: Upside/Downside | C47: =C46/C45-1 -> 0.13135593 | D47: =D46/D45-1 -> 0.025833725 | E47: =E46/E45-1 -> 0.29934841 | F47: N/A | G47: N/A | H47: =H46/H45-1 -> 0.32657984 | I47: =IFERROR(AVERAGE(C47:H47),"") -> 0.19577948 | J47: =SQRT((C47-I47)^2) -> 0.064423543
B48: Extra | I48: =IFERROR(AVERAGE(C48:H48),"")
B49: 3y Operating Cash Flow | C49: =(Inputs!B59-Inputs!E59)/Inputs!E59 -> 2.6790123 | D49: =((E76*209.048)-(E78*36.462))/(E78*36.462) -> 4.1807526 | E49: =((E76*804.442)-(E78*242.287 ))/(E78*242.287 ) -> 2.000212 | F49: =((E76*160.316)-(E78*28.935))/(E78*28.935) -> 4.0065748 | G49: =((E76*1092.278)-(E78*133.818))/(E78*133.818) -> 6.3757464 | H49: =((E76*393.643)-(E78*239.912))/(E78*239.912) -> 0.48264742 | I49: =IFERROR(AVERAGE(C49:H49),"") -> 3.2874909 | J49: =SQRT((C49-I49)^2) -> 0.60847859
B50: R&D/Net Sales | C50: N/A | D50: N/A | E50: N/A | F50: N/A | G50: =G63/G11 -> 0.059004655 | H50: =H63/H11 -> 0.032165833 | I50: =IFERROR(AVERAGE(C50:H50),"") -> 0.045585244 | J50: =SQRT((C50-I50)^2) -> #VALUE!
B52: Financial Data | C52: =OP!E2 -> #VALUE! | D52: =D8 -> #VALUE! | E52: =E8 -> #VALUE! | F52: =F8 -> #VALUE! | G52: =G8 -> #VALUE! | H52: =H8 -> #VALUE!
B53: IS
B54: Net Sales (36m ago) | C54: ='Fin. Data'!E5 -> 1158 | D54: =E78*544.013 -> 664.40278 | E54: =E78*1440.409 -> 1759.1707 | F54: =E78*637.1 -> 778.08989 | G54: =E78*1188.628 -> 1451.6707 | H54: =E78*1946 -> 2376.6488
B55: Net Sales (12m ago) | C55: ='Fin. Data'!C5 -> 1573 | D55: =E77*919.708 -> 984.27654 | E55: =E77*2602.89 -> 2785.6271 | F55: =E77*1007 -> 1077.6969 | G55: =E77*2509.323 -> 2685.4912 | H55: =E77*3651 -> 3907.3202
B56: Net Sales (current) | C56: ='Fin. Data'!B5 -> 2060 | D56: =E76*1139.42 -> 1257.4575 | E56: =E76*2984.217 -> 3293.3652 | F56: =E76*1126.7 -> 1243.4198 | G56: =E76*2552.341 -> 2816.7493 | H56: =E76*4197 -> 4631.7857
B57: COGS | C57: =Inputs!B6-Inputs!B7 -> 736.07 | D57: =E76*(114.343+475.769+194.969) -> 866.411 | E57: =E76*683.387 -> 754.18207 | F57: =E76*(265.19+328.445+68.966+254.098) -> 1011.6639 | G57: 819.274 | H57: 1617
B58: EBITDA | C58: 1535 | D58: =E76*326.251 -> 360.04878 | E58: =E76*932.43 -> 1029.0245 | F58: 136.37 | G58: 1350 | H58: =E76*752.034 -> 829.94052
B59: Operating Income | C59: =Inputs!B8 -> 240.67 | D59: =E76*187.406 -> 206.82021 | E59: =E76*893.839 -> 986.43572 | F59: =E76*64.551 -> 71.238123 | G59: =E76*808.629 -> 892.39844 | H59: =E76*410.337 -> 452.84562
B60: Net Financial Cost | C60: 7 | D60: =E76*(5.355-0.676) -> 5.1637182 | E60: =E76*(22.201-0.578) -> 23.863022 | F60: =E76*(7.787-0.779) -> 7.7339896 | G60: =E76*(5.853-0.627) -> 5.7673844 | H60: =E76*(5.603-0) -> 6.1834395
B61: Taxes | C61: 59 | D61: =E76*49.532 -> 54.663238 | E61: =E76*258.733 -> 285.53629 | F61: =E76*9.793 -> 10.8075 | G61: =E76*241.89 -> 266.94845 | H61: =E76*87 -> 96.012713
B62: Net Income | C62: 147 | D62: =E76*123.809 -> 136.63492 | E62: =E76*195.7 -> 215.97343 | F62: =E76*50.018 -> 55.199585 | G62: =E76*566.74 -> 625.45109 | H62: =E76*209 -> 230.65123
B63: R&D | C63: N/A | D63: N/A | E63: N/A | F63: N/A | G63: =E76*150.6 -> 166.20132 | H63: =E76*135 -> 148.98524
B64: BS
B65: Cash & Eq. | C65: ='Fin. Data'!B39 -> 327 | D65: =E76*106.944 -> 118.0228 | E65: =E76*998.799 -> 1102.269 | F65: =E76*84.817 -> 93.603567 | G65: =E76*225.028 -> 248.33964 | H65: =E76*118 -> 130.22414
B66: Acc. Receivables | C66: ='Fin. Data'!B40 -> 273 | D66: =E76*78.17 -> 86.267975 | E66: =E76*325.608 -> 359.33917 | F66: =E76*106.417 -> 117.44121 | G66: =E76*724.076 -> 799.08622 | H66: =E76*376 -> 414.9515
B67: Inventory | C67: ='Fin. Data'!B41 -> 577 | D67: =E76*287.291 -> 317.05274 | E67: =E76*453.178 -> 500.12471 | F67: =E76*422.334 -> 466.08544 | G67: =E76*343.017 -> 378.55164 | H67: =E76*1066 -> 1176.4316
B68: Current Assets | C68: =Inputs!B27 -> 1421.03 | D68: =E76*526.35 -> 580.87692 | E68: =E76*1907.045 -> 2104.6042 | F68: =E76*731.883 -> 807.70199 | G68: =E76*1704.278 -> 1880.8317 | H68: =E76*1791.073 -> 1976.6181
B69: Fixed Assets | C69: ='Fin. Data'!B42 -> 765.41 | D69: =E76*773.784 -> 853.94369 | E69: =E76*1082.48 -> 1194.6189 | F69: =E76*731.822 -> 807.63467 | G69: =E76*820.241 -> 905.21338 | H69: 603.533
B70: Total Assets | C70: ='Fin. Data'!B44 -> 3053.66 | D70: =E76*1379.88 -> 1522.8279 | E70: =E76*4992.02 -> 5509.1654 | F70: =E76*2099.429 -> 2316.9181 | G70: =E76*4746.88 -> 5238.6302 | H70: =E76*3472 -> 3831.6798
B71: Acc. Payable | C71: =Inputs!B43 -> 320 | D71: =E76*166.244 -> 183.46595 | E71: =E76*538.586 -> 594.3805 | F71: =E76*166.088 -> 183.29379 | G71: =E76*557.055 -> 614.76278 | H71: =E76*572 -> 631.256
B72: Current Liabilities | C72: =Inputs!B42 -> 1116.97 | D72: =E76*423.778 -> 467.67903 | E72: =E76*1010.432 -> 1115.1071 | F72: =E76*449.1 -> 495.62425 | G72: =E76*1175.149 -> 1296.8879 | H72: =E76*1090.144 -> 1203.0768
B73: Total Debt | C73: ='Fin. Data'!B58 -> 1099.57 | D73: =E76*799.06 -> 881.83815 | E73: =E76*851.41 -> 939.61131 | F73: 701.25 | G73: 2550 | H73: =E76*1270 -> 1401.5649
B74: Total Equity | C74: ='Fin. Data'!B64 -> 927.66 | D74: =E76*453.613 -> 500.60477 | E74: =E76*3214.429 -> 3547.4259 | F74: =E76*1650.329 -> 1821.2939 | G74: =E76*2842.559 -> 3137.0322 | H74: =E76*1311 -> 1446.8123
D76: Avg. FX Rate EUR/USD - 31/12/2023 | E76: 1.1035944
D77: Avg. FX Rate EUR/USD - 31/12/2022 | E77: 1.0702055
D78: Avg. FX Rate EUR/USD - 31/12/2020 | E78: 1.2212995

Sheet ESG
B1: Company GICS Sector: | T1: Yes
B2: Consumer Discretionary | C2: <- Select Industry | T2: No
B3: ESG Analysis | K3: Relative ESG Analysis
B4: Parameters | C4: Impact | D4: Do they report? | E4: Ranking | F4: Mitigation Plan | G4: Traffic Lights | H4: Improvement over time? | I4: Targets / Goals? | J4: Comments | K4: Parameters | L4: =OP!E2 -> #VALUE! | M4: =Peers!C2 -> #VALUE! | N4: =Peers!C3 -> #VALUE! | O4: =Peers!C4 -> #VALUE! | P4: =Peers!C5 -> #VALUE! | Q4: =Peers!C6 -> #VALUE! | R4: AVERAGE
B5: Environmental | K5: Ratios
A6: 1 | B6: CO2 Direct Emissions | C6: =VLOOKUP($B$2,'Sector Impact'!$K$4:$AA$16,A6+1,FALSE) -> Low | K6: CO2 Emissions/$M Sales | L6: =L12/L$11 -> 217.56699 | M6: =M12/M$11 -> 74.285589 | N6: =N12/N$11 -> 357.75958 | O6: =O12/O$11 -> 128.00893 | P6: =P12/P$11 -> 70.230952 | Q6: =Q12/Q$11 -> 289.70227 | R6: =IFERROR(AVERAGE(L6:Q6),"") -> 189.59239
A7: 2 | B7: Total Water Consumption | C7: =VLOOKUP($B$2,'Sector Impact'!$K$4:$AA$16,A7+1,FALSE) -> Low | K7: Water Consumption/$M Sales | L7: =L13/L$11 -> 217.96117 | M7: =M13/M$11 -> 30.731087 | N7: =N13/N$11 -> 105.79829 | O7: =O13/O$11 -> 128.40237 | P7: =P13/P$11 -> 61.034048 | Q7: =Q13/Q$11 -> 54.431115 | R7: =IFERROR(AVERAGE(L7:Q7),"") -> 99.726345
A8: 3 | B8: Total Energy Consumption | C8: =VLOOKUP($B$2,'Sector Impact'!$K$4:$AA$16,A8+1,FALSE) -> Medium | D8: Yes | E8: Medium | F8: Yes | J8: There was an increase of 50,000 Gj of energy consumption between 2022 and 2023. | K8: Energy Consumption/$M Sales | L8: =L14/L$11 -> 172.61505 | M8: =M14/M$11 -> 71.08917 | N8: =N14/N$11 -> 301.93673 | O8: =O14/O$11 -> 151.30178 | P8: =P14/P$11 -> 91.480476 | Q8: =Q14/Q$11 -> 36.251164 | R8: =IFERROR(AVERAGE(L8:Q8),"") -> 137.44573
A9: 4 | B9: Waste Management | C9: =VLOOKUP($B$2,'Sector Impact'!$K$4:$AA$16,A9+1,FALSE) -> Medium | D9: Yes | E9: Medium | F9: Yes | J9: The company was able to reduce 100 tonnes of waste between 2022 and 2023. | K9: Waste Production/$M Sales | L9: =L15/L$11 -> 0.58980583 | M9: =M15/M$11 -> 0.48058627 | N9: =N15/N$11 -> 2.6938593 | O9: =O15/O$11 -> 2.875532 | P9: =P15/P$11 -> 0.54166667 | Q9: =Q15/Q$11 -> 2.4420707 | R9: =IFERROR(AVERAGE(L9:Q9),"") -> 1.6039201
A10: 5 | B10: Land Degradation/Deforestation/Biodiversity loss/Animal sufering/… | C10: =VLOOKUP($B$2,'Sector Impact'!$K$4:$AA$16,A10+1,FALSE) -> Low | K10: Inputs
B11: Social | K11: Net Sales ($M) | L11: 2060 | M11: 1139.4 | N11: 671.75 | O11: 963.3 | P11: 4200 | Q11: 3651
A12: 6 | B12: Employee Turnover % | C12: =VLOOKUP($B$2,'Sector Impact'!$K$4:$AA$16,A12+1,FALSE) -> Medium | D12: No | J12: Could not find any information. | K12: CO2 Emissions Total (Tonnes) | L12: 448188 | M12: 84641 | N12: 240325 | O12: 123311 | P12: 294970 | Q12: 1057703
A13: 7 | B13: Salaries & Compensation | C13: =VLOOKUP($B$2,'Sector Impact'!$K$4:$AA$16,A13+1,FALSE) -> Medium | D13: Yes | E13: "Villain" | F13: No | J13: The median salarie is 102,715 while the average salarie at Ermenegildo Zegna is 87,694. | K13: Water Consumption Total (Cubic Meters) | L13: 449000 | M13: 35015 | N13: 71070 | O13: 123690 | P13: 256343 | Q13: 198728
A14: 8 | B14: Reputation | C14: =VLOOKUP($B$2,'Sector Impact'!$K$4:$AA$16,A14+1,FALSE) -> Low | K14: Energy Consumption Total (Gigajoules) | L14: 355587 | M14: 80999 | N14: 202826 | O14: 145749 | P14: 384218 | Q14: 132353
A15: 9 | B15: Discrimination Events | C15: =VLOOKUP($B$2,'Sector Impact'!$K$4:$AA$16,A15+1,FALSE) -> Low | F15: Yes | K15: Waste Production Total (Tonnes) | L15: 1215 | M15: 547.58 | N15: 1809.6 | O15: 2770 | P15: 2275 | Q15: 8916
A16: 10 | B16: Work Safety | C16: =VLOOKUP($B$2,'Sector Impact'!$K$4:$AA$16,A16+1,FALSE) -> Medium | D16: No | E16: "Best in class" | F16: No | I16: None | J16: There are no reports of recent accidents at work at the company. | K16: ESG Scores
A17: 11 | B17: Damage to consumer health | C17: =VLOOKUP($B$2,'Sector Impact'!$K$4:$AA$16,A17+1,FALSE) -> Medium | D17: No | E17: "Best in class" | F17: No | I17: None | J17: There are no reports of damages to consumer health made by products of the company. | K17: Refinitiv | L17: 40/100 | M17: 50/100 | N17: 81/100 | P17: 52/100 | Q17: 89/100
A18: 12 | B18: PXP? | C18: =VLOOKUP($B$2,'Sector Impact'!$K$4:$AA$16,A18+1,FALSE) -> Medium | D18: No | E18: "Villain" | F18: No | H18: None | I18: None | J18: Could not find any information about the company pension plan. | K18: Sustainalytics | M18: 18.8(Low Risk) | N18: 8.4(negligible risk) | O18: 14.8(Low Risk) | P18: 15.0(Low Risk) | Q18: 12.5(Low Risk)
A19: 13 | B19: Supply chain | C19: =VLOOKUP($B$2,'Sector Impact'!$K$4:$AA$16,A19+1,FALSE) -> High | D19: Yes | E19: "Best in class" | F19: No | I19: None | J19: The company establishes a great relation with their suppliers being a part of their "filera". | K19: ISS | L19: C | M19: C- | N19: C | O19: C- | P19: C+ | Q19: B-
A20: 14 | B20: Community involvement | C20: =VLOOKUP($B$2,'Sector Impact'!$K$4:$AA$16,A20+1,FALSE) -> Low | K20: CDP | L20: /C | M20: A-/ | N20: A/F | O20: F/F | P20: A-/F/B | Q20: B/
A21: 15 | B21: Public Sector | C21: =VLOOKUP($B$2,'Sector Impact'!$K$4:$AA$16,A21+1,FALSE) -> High | D21: No | I21: None | J21: Could not find any information.
A22: 16 | B22: Litigation | C22: =VLOOKUP($B$2,'Sector Impact'!$K$4:$AA$16,A22+1,FALSE) -> Low | D22: Yes
B23: Corporate Governance | K23: PARAMETERS
A24: 17 | B24: Diversity (Gender, Age, Industry, Region) | E24: Medium | F24: No | I24: None | J24: 3 out of 10 members of the board are women. | K24: IMPACT | L24: RANKING | M24: MITIGATION PLAN | O24: TRAFFIC
A25: 18 | B25: % Independence | E25: Medium | F25: No | I25: None | J25: Half of the members of the board are independent. | K25: Low | L25: "Best in class" | M25: Is there evidence of a plan/program ?
A26: 19 | B26: average time as independent directors | E26: "Best in class" | F26: No | I26: None | J26: The average time as independent director is around 5 years. | K26: Medium | L26: Medium High
A27: 20 | B27: Recent departures of directors / C-level executives? | E27: "Best in class" | F27: No | I27: None | J27: The most recent departure was in 2021. | K27: High | L27: Medium
A28: 21 | B28: CEO/Chairman duality | E28: "Villain" | F28: No | I28: None | J28: Both the chairman and CEO positions are occupied by Ermenegildo Zegna | K28: Very high | L28: "Villain"
A29: 22 | B29: Transparency (ESG, segments, acquisitions, other) | E29: Medium | F29: No | I29: None | J29: It was really hard to find the information about the environmental part.
A30: 23 | B30: Time taken to report after the end of the quarter / year | E30: "Best in class" | F30: No | I30: None | J30: The company took 5 months to publish their report.
A31: 24 | B31: Additional participation of the CEO in other boards or excessive participation of Ch. | E31: "Best in class" | F31: No | I31: None | J31: The CEO and chairman of the company is only present on Ermenegildo Zegna board.
A32: 25 | B32: Audit / Consulting | D32: Yes | E32: Medium | F32: No | I32: None | J32: The company spent 6,483 in audit and non-audit fees.
A33: 26 | B33: ESG-compensation related | D33: No | E33: "Villain" | F33: No | I33: None | J33: The company offers no ESG-compensation related.
A34: 27 | B34: Management compensation schemes | D34: Yes | E34: "Best in class" | F34: No | I34: None | J34: The Company will pay Non-Executive directors an annual base fee of 150,000 euros per annum payable 50% in cash and 50% in Company's ordinary shares ("Equity Awards"), subject to a restricted stock award.

Sheet DCF
A1: VALUATION MODEL
G3: Short Term | K3: Long Term
A4: Section | B4: Line # | C4: ITEM | D4: 2021 (Real) | E4: 2022 (Real) | F4: 2023 (Real) | G4: 2024 | H4: =G4+1 -> 2025 | I4: =H4+1 -> 2026 | J4: =I4+1 -> 2027 | K4: =J4+1 -> 2028 | L4: =K4+1 -> 2029 | M4: =L4+1 -> 2030 | N4: =M4+1 -> 2031 | O4: =N4+1 -> 2032 | ... AF4: =AE4+1 -> 2049
A5: INCOME STATEMENT | B5: 1 | C5: Growth | D5: ='Fin. Data'!D6 -> 0.32037997 | E5: =+E6/D6-1 -> 0.028776978 | F5: =+F6/E6-1 -> 0.30959949 | G5: 0.085 | H5: =Assumptions!L9 -> 0.05 | I5: =Assumptions!L9 -> 0.05 | J5: =Assumptions!L9 -> 0.05 | K5: =Assumptions!M9 -> 0.03 | L5: =Assumptions!M9 -> 0.03 | M5: =Assumptions!M9 -> 0.03 | N5: =Assumptions!M9 -> 0.03 | O5: =Assumptions!M9 -> 0.03 | P5: =Assumptions!M9 -> 0.03 | Q5: =Assumptions!$M$9 -> 0.03 | R5: =Assumptions!$M$9 -> 0.03 | S5: =Assumptions!$M$9 -> 0.03 | T5: =Assumptions!$M$9 -> 0.03 | U5: =Assumptions!$M$9 -> 0.03 | V5: =Assumptions!$M$9 -> 0.03 | W5: =Assumptions!$M$9 -> 0.03 | X5: =Assumptions!$M$9 -> 0.03 | ... AE5: =Assumptions!$M$9 -> 0.03 | AF5: =Assumptions!M9 -> 0.03
B6: 2 | C6: Revenues/Sales | D6: =Inputs!D6 -> 1529 | E6: =Inputs!C6 -> 1573 | F6: =Inputs!B6 -> 2060 | G6: =F6*(1+G5) -> 2235.1 | H6: =G6*(1+H5) -> 2346.855 | I6: =H6*(1+I5) -> 2464.1978 | J6: =I6*(1+J5) -> 2587.4076 | K6: =J6*(1+K5) -> 2665.0299 | L6: =K6*(1+L5) -> 2744.9808 | M6: =L6*(1+M5) -> 2827.3302 | N6: =M6*(1+N5) -> 2912.1501 | ... AF6: =AE6*(1+AF5) -> 4957.7406
B7: 3 | C7: EBIT/Operating Margin | D7: =D8/D6 -> 0.092851537 | E7: =E8/E6 -> 0.1091227 | F7: =F8/F6 -> 0.1168301 | G7: =Assumptions!L10 -> 0.13 | H7: =Assumptions!L10 -> 0.13 | I7: =Assumptions!L10 -> 0.13 | J7: =Assumptions!L10 -> 0.13 | K7: =Assumptions!M10 -> 0.14 | L7: =Assumptions!$M$10 -> 0.14 | M7: =Assumptions!$M$10 -> 0.14 | N7: =Assumptions!$M$10 -> 0.14 | O7: =Assumptions!$M$10 -> 0.14 | P7: =Assumptions!$M$10 -> 0.14 | Q7: =Assumptions!$M$10 -> 0.14 | R7: =Assumptions!$M$10 -> 0.14 | S7: =Assumptions!$M$10 -> 0.14 | ... AE7: =Assumptions!$M$10 -> 0.14 | AF7: =Assumptions!M10 -> 0.14
B8: 4 | C8: EBIT | D8: ='Fin. Data'!D11 -> 141.97 | E8: ='Fin. Data'!C11 -> 171.65 | F8: ='Fin. Data'!B11 -> 240.67 | G8: =G7*G6 -> 290.563 | H8: =H7*H6 -> 305.09115 | I8: =I7*I6 -> 320.34571 | J8: =J7*J6 -> 336.36299 | K8: =K7*K6 -> 373.10418 | L8: =L7*L6 -> 384.29731 | M8: =M7*M6 -> 395.82623 | N8: =N7*N6 -> 407.70101 | ... AF8: =AF7*AF6 -> 694.08368 | AG8: 322.78589
B9: 5a | C9: (Dep) | D9: -15.42 | E9: -14.28 | F9: -17.71 | G9: =-G40*$D$53 -> -21.090713 | H9: =-H40*$D$53 -> -23.144211 | I9: =-I40*$D$53 -> -25.300384 | J9: =-J40*$D$53 -> -27.564365 | K9: =-K40*$E$53 -> -29.563138 | L9: =-L40*$E$53 -> -31.621873 | M9: =-M40*$E$53 -> -33.742371 | N9: =-N40*$E$53 -> -35.926484 | O9: =-O40*$E$53 -> -38.176119 | P9: =-P40*$E$53 -> -40.493244 | Q9: =-Q40*$E$53 -> -42.879883 | R9: =-R40*$E$53 -> -45.338121 | ... AF9: =-AF40*$E$53 -> -88.600439 | AG9: -53.797648
B10: 5b | C10: (Amort) | D10: -10 | E10: -12 | F10: -14 | G10: =F10*(1+$D$54) -> -14.35 | H10: =G10*(1+$D$54) -> -14.70875 | I10: =H10*(1+$D$54) -> -15.076469 | J10: =I10*(1+$D$54) -> -15.45338 | K10: =J10*(1+$E$54) -> -15.839715 | L10: =K10*(1+$E$54) -> -16.235708 | M10: =L10*(1+$E$54) -> -16.641601 | N10: =M10*(1+$E$54) -> -17.057641 | O10: =N10*(1+$E$54) -> -17.484082 | P10: =O10*(1+$E$54) -> -17.921184 | Q10: =P10*(1+$E$54) -> -18.369213 | R10: =Q10*(1+$E$54) -> -18.828444 | ... AF10: =AE10*(1+$E$54) -> -26.604098 | AG10: -35.865099
B11: 5c | C11: (Stock based compensation) | D11: -116.4 | E11: -122.6 | F11: -143.22 | G11: =-G6*$D$55 -> -134.106 | H11: =-H6*$D$55 -> -140.8113 | I11: =-I6*$D$55 -> -147.85187 | J11: =-J6*$D$55 -> -155.24446 | K11: =-K6*$E$55 -> -159.90179 | L11: =-L6*$E$55 -> -164.69885 | M11: =-M6*$E$55 -> -169.63981 | N11: =-N6*$E$55 -> -174.72901 | O11: =-O6*$E$55 -> -179.97088 | P11: =-P6*$E$55 -> -185.37 | Q11: =-Q6*$E$55 -> -190.9311 | R11: =-R6*$E$55 -> -196.65904 | ... AF11: =-AF6*$E$55 -> -297.46444 | AG11: -107.5953
B12: 6 | C12: EBITDA | D12: =D8-D9-D10 -> 167.39 | E12: =E8-E9-E10 -> 197.93 | F12: =F8-F9-F10 -> 272.38 | G12: =G8-G9-G10 -> 326.00371 | H12: =H8-H9-H10 -> 342.94411 | I12: =I8-I9-I10 -> 360.72256 | J12: =J8-J9-J10 -> 379.38074 | K12: =K8-K9-K10 -> 418.50703 | ... AF12: =AF8-AF9-AF10 -> 809.28822 | AG12: 233.12314
B13: 7 | C13: (Net financing cost) | D13: ='Fin. Data'!D14 -> -6.21 | E13: ='Fin. Data'!C14 -> -27.74 | F13: ='Fin. Data'!B14 -> -33.5 | G13: =F43*$D$58-F44*$D$57 -> -15.450161 | H13: =G43*$D$58-G44*$D$57 -> -14.153521 | I13: =H43*$D$58-H44*$D$57 -> -12.062645 | J13: =I43*$D$58-I44*$D$57 -> -11.805994 | K13: =J43*$E$58-J44*$E$57 -> -23.436036 | L13: =K43*$E$58-K44*$E$57 -> -23.355336 | M13: =L43*$E$58-L44*$E$57 -> -24.271525 | N13: =M43*$E$58-M44*$E$57 -> -25.203988 | O13: =N43*$E$58-N44*$E$57 -> -26.136888 | P13: =O43*$E$58-O44*$E$57 -> -27.080848 | Q13: =P43*$E$58-P44*$E$57 -> -28.03411 | R13: =Q43*$E$58-Q44*$E$57 -> -28.994271 | ... AF13: =AE43*$E$58-AE44*$E$57 -> -43.320243
B14: 8 | C14: Other income/(cost) | D14: ='Fin. Data'!D15 -> -260.31 | E14: ='Fin. Data'!C15 -> -51.95 | F14: ='Fin. Data'!B15 -> -39.6 | G14: =AVERAGE(D14:F14)*(1+G5) -> -127.25603 | H14: =AVERAGE(E14:G14)*(1+H5) -> -76.582112 | I14: =AVERAGE(F14:H14)*(1+I5) -> -85.203351 | J14: =AVERAGE(G14:I14)*(1+J5) -> -101.16452 | K14: =AVERAGE(H14:J14)*(1+K5) -> -90.279495 | L14: =AVERAGE(I14:K14)*(1+L5) -> -94.982264 | M14: =AVERAGE(J14:L14)*(1+M5) -> -98.33969 | N14: =AVERAGE(K14:M14)*(1+N5) -> -97.369831 | ... AF14: =AVERAGE(AC14:AE14)*(1+AF5) -> -128.28854
B15: 9 | C15: Earnings before taxes | D15: =D8+D13+D14 -> -124.55 | E15: =E8+E13+E14 -> 91.96 | F15: =F8+F13+F14 -> 167.57 | G15: =G8+G13+G14 -> 147.85681 | H15: =H8+H13+H14 -> 214.35552 | I15: =I8+I13+I14 -> 223.07971 | J15: =J8+J13+J14 -> 223.39248 | K15: =K8+K13+K14 -> 259.38865 | ... AF15: =AF8+AF13+AF14 -> 522.4749
B16: 10 | C16: (Income tax) | D16: ='Fin. Data'!D21 -> -36.32 | E16: ='Fin. Data'!C21 -> -37.72 | F16: ='Fin. Data'!B21 -> -36.15 | G16: =-$D$56*G15 -> -35.485633 | H16: =-$D$56*H15 -> -51.445324 | I16: =-$D$56*I15 -> -53.539131 | J16: =-$D$56*J15 -> -53.614194 | K16: =-$E$56*K15 -> -62.253276 | L16: =-$E$56*L15 -> -63.83033 | M16: =-$E$56*M15 -> -65.571603 | N16: =-$E$56*N15 -> -68.430526 | O16: =-$E$56*O15 -> -70.557834 | P16: =-$E$56*P15 -> -72.957469 | Q16: =-$E$56*Q15 -> -75.585813 | R16: =-$E$56*R15 -> -78.137744 | ... AF16: =-$E$56*AF15 -> -125.39398
B17: 11 | C17: Net income | D17: ='Fin. Data'!D23 -> -160.87 | E17: ='Fin. Data'!C23 -> 54.24 | F17: ='Fin. Data'!B23 -> 131.42 | G17: =G16+G15 -> 112.37117 | H17: =H16+H15 -> 162.91019 | I17: =I16+I15 -> 169.54058 | J17: =J16+J15 -> 169.77828 | K17: =K16+K15 -> 197.13537 | L17: =L16+L15 -> 202.12938 | M17: =M16+M15 -> 207.64341 | N17: =N16+N15 -> 216.69667 | ... AF17: =AF16+AF15 -> 397.08093
A19: CASH FLOW STATEMENT | B19: 12 | C19: Operating cash flows before WK | D19: 318.9 | E19: 282.87 | F19: 443.95 | G19: =G17-G10-G9-G11 -> 281.91788 | H19: =H17-H10-H9-H11 -> 341.57445 | I19: =I17-I10-I9-I11 -> 357.7693 | J19: =J17-J10-J9-J11 -> 368.04049 | K19: =K17-K10-K9-K11 -> 402.44002 | L19: =L17-L10-L9-L11 -> 414.6858 | M19: =M17-M10-M9-M11 -> 427.66719 | N19: =N17-N10-N9-N11 -> 444.4098 | ... AF19: =AF17-AF10-AF9-AF11 -> 809.7499
B20: 13 | C20: (Stock-based compensation) | D20: =D11 -> -116.4 | E20: =E11 -> -122.6 | F20: =F11 -> -143.22 | G20: =G11 -> -134.106 | H20: =H11 -> -140.8113 | I20: =I11 -> -147.85187 | J20: =J11 -> -155.24446 | K20: =K11 -> -159.90179 | ... AF20: =AF11 -> -297.46444
B21: 14 | C21: (Working Capital Flows) | D21: =Inputs!D62 -> 24 | E21: =Inputs!C62 -> -40 | F21: =Inputs!B62 -> -22 | G21: =$D$60*(G6-F6) -> -8.755 | H21: =$D$60*(H6-G6) -> -5.58775 | I21: =$D$60*(I6-H6) -> -5.8671375 | J21: =$D$60*(J6-I6) -> -6.1604944 | K21: =$E$60*(K6-J6) -> 62.097783 | L21: =$E$60*(L6-K6) -> 63.960717 | M21: =$E$60*(M6-L6) -> 65.879538 | N21: =$E$60*(N6-M6) -> 67.855924 | O21: =$E$60*(O6-N6) -> 69.891602 | P21: =$E$60*(P6-O6) -> 71.98835 | Q21: =$E$60*(Q6-P6) -> 74.148001 | R21: =$E$60*(R6-Q6) -> 76.372441 | ... AF21: =$E$60*(AF6-AE6) -> 115.52017
B22: 15 | C22: -Total Operating Cash Flow | D22: =D19+D20+D21 -> 226.5 | E22: =E19+E20+E21 -> 120.27 | F22: =F19+F20+F21 -> 278.73 | G22: =G19+G20+G21 -> 139.05688 | H22: =H19+H20+H21 -> 195.1754 | I22: =I19+I20+I21 -> 204.0503 | J22: =J19+J20+J21 -> 206.63553 | K22: =K19+K20+K21 -> 304.63601 | ... AF22: =AF19+AF20+AF21 -> 627.80563
B23: 16 | C23: (CAPEX) | D23: ='Fin. Data'!D32 -> -89.7 | E23: ='Fin. Data'!C32 -> -51.52 | F23: ='Fin. Data'!B32 -> -61.46 | G23: =G6*$D$62 -> -78.2285 | H23: =H6*$D$62 -> -82.139925 | I23: =I6*$D$62 -> -86.246921 | J23: =J6*$D$62 -> -90.559267 | K23: =K6*$E$62 -> -79.950896 | L23: =L6*$E$62 -> -82.349423 | M23: =M6*$E$62 -> -84.819906 | N23: =N6*$E$62 -> -87.364503 | O23: =O6*$E$62 -> -89.985438 | P23: =P6*$E$62 -> -92.685001 | Q23: =Q6*$E$62 -> -95.465551 | R23: =R6*$E$62 -> -98.329518 | ... AF23: =AF6*$E$62 -> -148.73222 | AG23: =SUM(D23:AF23) -> -2981.2976
B24: 17 | C24: Adq | D24: =Inputs!D66 -> -7.3 | E24: ='Fin. Data'!C33 -> -8.48 | F24: ='Fin. Data'!B33 -> 85.46 | G24: =G6*$D$63 -> -33.5265 | H24: =H6*$D$63 -> -35.202825 | I24: =I6*$D$63 -> -36.962966 | J24: =J6*$D$63 -> -38.811115 | K24: =K6*$E$63 -> -106.60119 | L24: =L6*$E$63 -> -109.79923 | M24: =M6*$E$63 -> -113.09321 | N24: =N6*$E$63 -> -116.486 | O24: =O6*$E$63 -> -119.98058 | P24: =P6*$E$63 -> -123.58 | Q24: =Q6*$E$63 -> -127.2874 | R24: =R6*$E$63 -> -131.10602 | ... AF24: =AF6*$E$63 -> -198.30962 | AH24: =AG9-AG23 -> 2927.4999
B25: 18 | C25: (Other investing flows) | D25: =Inputs!D67 -> 0 | E25: =Inputs!C67 -> -0.4 | F25: =Inputs!B67 -> -0.44 | G25: =(1+G5)*AVERAGE(D25:F25) -> -0.3038 | H25: =(1+H5)*AVERAGE(E25:G25) -> -0.40033 | I25: =(1+I5)*AVERAGE(F25:H25) -> -0.4004455 | J25: =(1+J5)*AVERAGE(G25:I25) -> -0.38660143 | K25: =(1+K5)*AVERAGE(H25:J25) -> -0.40766608 | L25: =(1+L5)*AVERAGE(I25:K25) -> -0.4101848 | M25: =(1+M5)*AVERAGE(J25:L25) -> -0.41352862 | N25: =(1+N5)*AVERAGE(K25:M25) -> -0.42277363 | ... AF25: =(1+AF5)*AVERAGE(AC25:AE25) -> -0.55059886
B26: 19 | C26: -Total Investing Flows | D26: =D23+D24+D25 -> -97 | E26: =E23+E24+E25 -> -60.4 | F26: =F23+F24+F25 -> 23.56 | G26: =G23+G24+G25 -> -112.0588 | H26: =H23+H24+H25 -> -117.74308 | I26: =I23+I24+I25 -> -123.61033 | J26: =J23+J24+J25 -> -129.75698 | K26: =K23+K24+K25 -> -186.95976 | ... AF26: =AF23+AF24+AF25 -> -347.59244
B27: 20 | C27: (Flows related to leases) | D27: =Inputs!D71+Inputs!D72 -> 0 | E27: =Inputs!C71+Inputs!C72 -> 0 | F27: =Inputs!B71+Inputs!B72 -> 0 | G27: =G6*$D$66 -> 145.2815 | H27: =H6*$D$66 -> 152.54558 | I27: =I6*$D$66 -> 160.17285 | J27: =J6*$D$66 -> 168.1815 | K27: =$E$66*K6 -> 79.950896 | L27: =$E$66*L6 -> 82.349423 | M27: =$E$66*M6 -> 84.819906 | N27: =$E$66*N6 -> 87.364503 | O27: =$E$66*O6 -> 89.985438 | P27: =$E$66*P6 -> 92.685001 | Q27: =$E$66*Q6 -> 95.465551 | R27: =$E$66*R6 -> 98.329518 | ... AF27: =$E$66*AF6 -> 148.73222
B28: 21 | C28: Flows related to debt | D28: =+SUM(Inputs!D69:D70) -> -168 | E28: =+SUM(Inputs!C69:C70) -> -301 | F28: =+SUM(Inputs!B69:B70) -> -246 | G28: =G44-F44 -> -186.7596 | H28: =H44-G44 -> 47.433115 | I28: =I44-H44 -> 49.779658 | J28: =J44-I44 -> 52.242901 | K28: =K44-J44 -> -15.998483 | L28: =L44-K44 -> 34.119635 | M28: =M44-L44 -> 35.138274 | N28: =N44-M44 -> 36.187348 | ... AF28: =AF44-AE44 -> 61.458039
B29: 22 | C29: (Repurchases)/Issuance of stock | D29: ='Fin. Data'!D28 -> -767 | E29: ='Fin. Data'!C28 -> -15 | F29: ='Fin. Data'!B28 -> -4 | G29: =-G17*$D$65 -> -4.4948469 | H29: =-H17*$D$65 -> -6.5164077 | I29: =-I17*$D$65 -> -6.7816232 | J29: =-J17*$D$65 -> -6.7911312 | K29: =-K17*$E$65 -> -19.713537 | L29: =-L17*$E$65 -> -20.212938 | M29: =-M17*$E$65 -> -20.764341 | N29: =-N17*$E$65 -> -21.669667 | O29: =-O17*$E$65 -> -22.343314 | P29: =-P17*$E$65 -> -23.103198 | Q29: =-Q17*$E$65 -> -23.935507 | R29: =-R17*$E$65 -> -24.743619 | ... AF29: =-AF17*$E$65 -> -39.708093
B30: 23 | C30: (Dividends) | D30: =-'Fin. Data'!D27 -> -0.12 | E30: ='Fin. Data'!C27 -> -23.03 | F30: ='Fin. Data'!B27 -> -27.07 | G30: =-$D$64*G17 -> -22.474234 | H30: =-$D$64*H17 -> -32.582039 | I30: =-$D$64*I17 -> -33.908116 | J30: =-$D$64*J17 -> -33.955656 | K30: =-$E$64*K17 -> -78.85415 | L30: =-$E$64*L17 -> -80.851751 | M30: =-$E$64*M17 -> -83.057363 | N30: =-$E$64*N17 -> -86.678667 | O30: =-$E$64*O17 -> -89.373257 | P30: =-$E$64*P17 -> -92.412793 | Q30: =-$E$64*Q17 -> -95.742029 | R30: =-$E$64*R17 -> -98.974475 | ... AF30: =-$E$64*AF17 -> -158.83237
B31: 24 | C31: Other financing flows | D31: =Inputs!D75 -> 859.05 | E31: =Inputs!C75 -> 26.15 | F31: =Inputs!B75 -> 6.19 | G31: =(1+G5)*AVERAGE(Inputs!B74:M74) -> -142.49667 | H31: =(1+H5)*AVERAGE(Inputs!B74:L74,G31) -> -139.5745 | I31: =(1+I5)*AVERAGE(Inputs!B74:L74,G31,H31) -> -140.44684 | J31: =(1+J5)*AVERAGE(G31:I31) -> -147.8813 | K31: =(1+K5)*AVERAGE(H31:J31) -> -146.91324 | L31: =(1+L5)*AVERAGE(I31:K31) -> -149.43288 | M31: =(1+M5)*AVERAGE(J31:L31) -> -152.51808 | N31: =(1+N5)*AVERAGE(K31:M31) -> -154.11004 | O31: =(1+O5)*AVERAGE(L31:N31) -> -156.58094 | P31: =(1+P5)*AVERAGE(M31:O31) -> -159.03511 | Q31: =(1+Q5)*AVERAGE(N31:P31) -> -161.27263 | ... AF31: =(1+AF5)*AVERAGE(AC31:AE31) -> -201.46887
B32: 25 | C32: -Total Financing flows | D32: =D27+D28+D29+D30+D31 -> -76.07 | E32: =E27+E28+E29+E30+E31 -> -312.88 | F32: =F27+F28+F29+F30+F31 -> -270.88 | G32: =G27+G28+G29+G30+G31 -> -210.94385 | H32: =H27+H28+H29+H30+H31 -> 21.305743 | I32: =I27+I28+I29+I30+I31 -> 28.815932 | J32: =J27+J28+J29+J30+J31 -> 31.796307 | K32: =K27+K28+K29+K30+K31 -> -181.52851 | ... AF32: =AF27+AF28+AF29+AF30+AF31 -> -189.81908
A34: SUMMARY | B34: 26 | C34: Cash before shareholder returns | D34: =D22+D26+D27+D28+D31 -> 820.55 | E34: =E22+E26+E27+E28+E31 -> -214.98 | F34: =F22+F26+F27+F28+F31 -> 62.48 | G34: =G22+G26+G27+G28+G31 -> -156.97669 | H34: =H22+H26+H27+H28+H31 -> 137.83651 | I34: =I22+I26+I27+I28+I31 -> 149.94563 | J34: =J22+J26+J27+J28+J31 -> 149.42164 | K34: =K22+K26+K27+K28+K31 -> 34.715425 | ... AF34: =AF22+AF26+AF27+AF28+AF31 -> 288.93457
B35: 27 | C35: Returns to shareholders | D35: =-1*(D29+D30) -> 767.12 | E35: =-1*(E29+E30) -> 38.03 | F35: =-1*(F29+F30) -> 31.07 | G35: =-1*(G29+G30) -> 26.969081 | H35: =-1*(H29+H30) -> 39.098446 | I35: =-1*(I29+I30) -> 40.689739 | J35: =-1*(J29+J30) -> 40.746787 | K35: =-1*(K29+K30) -> 98.567687 | ... AF35: =-1*(AF29+AF30) -> 198.54046
B36: 28 | C36: Excess cash acumulation | D36: =D34-D35 -> 53.43 | E36: =E34-E35 -> -253.01 | F36: =F34-F35 -> 31.41 | G36: =G34-G35 -> -183.94577 | H36: =H34-H35 -> 98.738067 | I36: =I34-I35 -> 109.25589 | J36: =J34-J35 -> 108.67486 | K36: =K34-K35 -> -63.852262 | ... AF36: =AF34-AF35 -> 90.394111
A38: BALANCE SHEET | B38: 29 | C38: Intangible assets | D38: 483.4 | E38: 487.9 | F38: 631.6 | G38: =+F38+(-G10) -> 645.95 | H38: =+G38+(-H10) -> 660.65875 | I38: =+H38+(-I10) -> 675.73522 | J38: =+I38+(-J10) -> 691.1886 | K38: =+J38+(-K10) -> 707.02831 | L38: =+K38+(-L10) -> 723.26402 | M38: =+L38+(-M10) -> 739.90562 | N38: =+M38+(-N10) -> 756.96326 | ... AF38: =+AE38+(-AF10) -> 1148.368 | AG38: =SUM(G38:AF38) -> 22685.088
B39: 30 | C39: Accumulated amortization | D39: 146.719 | E39: 143.184 | F39: 160.895 | G39: =F39-G10 -> 175.245 | H39: =G39-H10 -> 189.95375 | I39: =H39-I10 -> 205.03022 | J39: =I39-J10 -> 220.4836 | K39: =J39-K10 -> 236.32331 | L39: =K39-L10 -> 252.55902 | M39: =L39-M10 -> 269.20062 | N39: =M39-N10 -> 286.25826 | ... AF39: =AE39-AF10 -> 677.66301 | AG39: =SUM(G39:AF39) -> 10446.758
B40: 31 | C40: PPE+Right of use Assets | D40: 547.9 | E40: 536.87 | F40: 765.4 | G40: =F40+(-G23) -> 843.6285 | H40: =G40+(-H23) -> 925.76842 | I40: =H40+(-I23) -> 1012.0153 | J40: =I40+(-J23) -> 1102.5746 | K40: =J40+(-K23) -> 1182.5255 | L40: =K40+(-L23) -> 1264.8749 | M40: =L40+(-M23) -> 1349.6948 | N40: =M40+(-N23) -> 1437.0593 | ... AF40: =AE40+(-AF23) -> 3544.0176 | AG40: =SUM(G40:AF40) -> 53332.846
B41: 32 | C41: Accumulated depreciation | D41: 447.475 | E41: 435.16 | F41: 436.648 | G41: =F41-G9 -> 457.73871 | H41: =G41-H9 -> 480.88292 | I41: =H41-I9 -> 506.18331 | J41: =I41-J9 -> 533.74767 | K41: =J41-K9 -> 563.31081 | L41: =K41-L9 -> 594.93268 | M41: =L41-M9 -> 628.67505 | N41: =M41-N9 -> 664.60154 | ... AF41: =AE41-AF9 -> 1769.9691 | AG41: =SUM(G41:AF41) -> 25461.792
A43: CASH & DEBT & DISCOUNTING | B43: 33 | C43: Ending cash balance | D43: ='Fin. Data'!D39 -> 523 | E43: =E36+D43 -> 269.99 | F43: =F36+E43 -> 301.4 | G43: =G36+F43 -> 117.45423 | H43: =H36+G43+190 -> 406.1923 | I43: =I36+H43 -> 515.44819 | J43: =J36+I43 -> 624.12305 | K43: =K36+J43 -> 560.27079 | L43: =L36+K43 -> 547.63112 | M43: =M36+L43 -> 536.82979 | N43: =N36+M43 -> 531.1867 | O43: =O36+N43 -> 528.73336 | P43: =P36+O43 -> 529.98342 | ... AF43: =AF36+AE43 -> 1235.1581
B44: 34 | C44: Total Debt | D44: ='Fin. Data'!D58 -> 1212.96 | E44: ='Fin. Data'!C58 -> 978.77 | F44: ='Fin. Data'!B58 -> 1099.57 | G44: =G12*$D$67 -> 912.81039 | H44: =H12*$D$67 -> 960.24351 | I44: =I12*$D$67 -> 1010.0232 | J44: =J12*$D$67 -> 1062.2661 | K44: =K12*$E$67 -> 1046.2676 | L44: =L12*$E$67 -> 1080.3872 | M44: =M12*$E$67 -> 1115.5255 | N44: =N12*$E$67 -> 1151.7128 | O44: =O12*$E$67 -> 1188.9806 | P44: =P12*$E$67 -> 1227.3611 | Q44: =Q12*$E$67 -> 1266.8875 | R44: =R12*$E$67 -> 1307.5941 | ... AF44: =AF12*$E$67 -> 2023.2205
B45: 35 | C45: Discount factor | F45: =1/((1+$F$50)^G50) -> 1 | G45: =1/((1+$F$50)^G49) -> 0.92165899 | H45: =1/((1+$F$50)^H49) -> 0.84945529 | I45: =1/((1+$F$50)^I49) -> 0.7829081 | J45: =1/((1+$F$50)^J49) -> 0.72157428 | K45: =1/((1+$F$50)^K49) -> 0.66504542 | L45: =1/((1+$F$50)^L49) -> 0.61294509 | M45: =1/((1+$F$50)^M49) -> 0.56492635 | N45: =1/((1+$F$50)^N49) -> 0.52066945 | ... AF45: =1/((1+$F$50)^AF49) -> 0.1199021
B46: 36 | C46: DF + 0.1% | E46: +0.1% | F46: =1/((1+$F$50+0.001)^G50) -> 1 | G46: =1/((1+$F$50+0.001)^G49) -> 0.92081031 | H46: =1/((1+$F$50+0.001)^H49) -> 0.84789163 | I46: =1/((1+$F$50+0.001)^I49) -> 0.78074736 | J46: =1/((1+$F$50+0.001)^J49) -> 0.71892022 | K46: =1/((1+$F$50+0.001)^K49) -> 0.66198915 | L46: =1/((1+$F$50+0.001)^L49) -> 0.60956644 | M46: =1/((1+$F$50+0.001)^M49) -> 0.56129506 | N46: =1/((1+$F$50+0.001)^N49) -> 0.51684628 | ... AF46: =1/((1+$F$50+0.001)^AF49) -> 0.11706432
B47: 37 | C47: DF+0.5% | E47: +0.5% | F47: =1/((1+$F$50+0.005)^G50) -> 1 | G47: =1/((1+$F$50+0.005)^G49) -> 0.91743119 | H47: =1/((1+$F$50+0.005)^H49) -> 0.84167999 | I47: =1/((1+$F$50+0.005)^I49) -> 0.77218348 | J47: =1/((1+$F$50+0.005)^J49) -> 0.70842521 | K47: =1/((1+$F$50+0.005)^K49) -> 0.64993139 | L47: =1/((1+$F$50+0.005)^L49) -> 0.59626733 | M47: =1/((1+$F$50+0.005)^M49) -> 0.54703424 | N47: =1/((1+$F$50+0.005)^N49) -> 0.50186628 | ... AF47: =1/((1+$F$50+0.005)^AF49) -> 0.10639251
A49: Discount Rate | C49: Risk free rate | D49: Equity premium | E49: Firm premium | F49: Total | G49: 1 | H49: 2 | I49: 3 | J49: 4 | K49: 5 | L49: 6 | M49: 7 | N49: 8 | O49: 9 | P49: 10 | Q49: 11 | R49: 12 | S49: 13 | T49: 14 | U49: 15 | V49: 16 | W49: 17 | X49: 18 | Y49: 19 | Z49: 20 | AA49: 21 | AB49: 22 | AC49: 23 | AD49: 24 | AE49: 25 | AF49: 26
C50: 0.04 | D50: 0.04 | E50: 0.005 | F50: =E50+D50+C50 -> 0.085 | G50: 0
A52: Modelling factors | D52: Short Term | E52: Long Term | F52: Reference (line)
C53: Depreciation factor | D53: =Assumptions!L17 -> 0.025 | E53: =Assumptions!M17 -> 0.025 | F53: =Assumptions!O17 -> % PPE
C54: Amortization factor | D54: =Assumptions!L18 -> 0.025 | E54: =Assumptions!M18 -> 0.025 | F54: =Assumptions!O18 -> % IA
C55: Stock-based comp | D55: =Assumptions!L19 -> 0.06 | E55: =Assumptions!M19 -> 0.06 | F55: =Assumptions!O19 -> % Revenue
C56: Tax Rate | D56: =Assumptions!L20 -> 0.24 | E56: =Assumptions!M20 -> 0.24 | F56: =Assumptions!O20 -> % EBT
C57: Interest Rate on debt | D57: =Assumptions!L21 -> 0.016792166 | E57: =Assumptions!M21 -> 0.025 | F57: =Assumptions!O21 -> % Debt
C58: Interest Rate on cash | D58: =Assumptions!L22 -> 0.01 | E58: =Assumptions!M22 -> 0.005 | F58: =Assumptions!O22 -> % Cash
C59: PPE+ROA | D59: =Assumptions!L23 -> -- | E59: =Assumptions!M23 -> -- | F59: =Assumptions!O23 -> Growing with CAPEX
C60: Working capital flows | D60: =Assumptions!L24 -> -0.05 | E60: =Assumptions!M24 -> 0.8 | F60: =Assumptions!O24 -> % Change in Revenues
C61: Intangible Assets | D61: =Assumptions!L25 -> -- | E61: =Assumptions!M25 -> -- | F61: =Assumptions!O25 -> Growing with Amortization
C62: Capex | D62: =Assumptions!L26 -> -0.035 | E62: =Assumptions!M26 -> -0.03 | F62: =Assumptions!O26 -> % Revenue
C63: Acquisition factor | D63: =Assumptions!L27 -> -0.015 | E63: =Assumptions!M27 -> -0.04 | F63: =Assumptions!O27 -> % Revenue
C64: Dividends | D64: =Assumptions!L28 -> 0.2 | E64: =Assumptions!M28 -> 0.4 | F64: =Assumptions!O28 -> % Net Income
... C66: Leases | D66: =Assumptions!L30 -> 0.065 | E66: =Assumptions!M30 -> 0.03 | F66: =Assumptions!O30 -> % Revenue
C67: Total Debt | D67: =Assumptions!L31 -> 2.8 | E67: =Assumptions!M31 -> 2.5 | F67: % EBITDA
A69: Valuation | D69: $ millions
C70: Value of flows | D70: =SUMPRODUCT(G35:AF35,G45:AF45)+((AF43-AF44)*AF45) -> 930.79988 | E70: =D70/D72 -> 0.59640344
C71: Value of perpetuity | D71: =(AF34/(F50-AF5))*AF45 -> 629.88843 | E71: =D71/D72 -> 0.40359656
C72: Total Value | D72: =D70+D71 -> 1560.6883
C73: Actual share price | D73: =OP!C20 -> 9.44
C74: Total value vs Mkt Cap | D74: =D75/D73-1 -> -0.34933472
C75: Estimated NPV per share | D75: =D72*1000000/OP!C21 -> 6.1422803
A77: Sensibility | C77: Sensitivity +0.1% | D77: =(SUMPRODUCT(G35:AF35,G45:AF45)+((AF43-AF44)*AF45)+(AF34/(F50+0.001-AF5))*AF45)*1000000/OP!C21 -> 6.0980124 | E77: =D77/D75-1 -> -0.0072070814
C78: Sensitivity +0.5% | D78: =(SUMPRODUCT(G35:AF35,G45:AF45)+((AF43-AF44)*AF45)+(AF34/(F50+0.005-AF5))*AF45)*1000000/OP!C21 -> 5.9356967 | E78: =D78/D75-1 -> -0.033633046
A80: Notes | C80: Price where it'd be a "BUY" | D80: =D75/1.15 -> 5.3411133

Sheet Assumptions
B2: Assumptions
B4: Prospects:
B6: Links: | C6: Zegna 2023 Annual Report (20-F) | F6: Zegna Q3 2024 earnings call transcript
C8: 2023 | D8: =C8-1 -> 2022 | E8: =D8-1 -> 2021 | F8: =E8-1 -> 2020 | G8: =F8-1 -> 2019 | I8: 5Y Average | L8: Short Term Forecast | M8: Long Term Forecast
B9: Revenue growth | C9: =(Inputs!B6-Inputs!C6)/Inputs!C6 -> 0.30959949 | D9: =(Inputs!C6-Inputs!D6)/Inputs!D6 -> 0.028776978 | E9: =(Inputs!D6-Inputs!E6)/Inputs!E6 -> 0.32037997 | F9: =(Inputs!E6-Inputs!F6)/Inputs!F6 -> -0.21703854 | G9: =(Inputs!F6-Inputs!G6)/Inputs!G6 -> 0.059455587 | I9: =AVERAGE(C9:G9) -> 0.1002347 | L9: 0.05 | M9: 0.03
B10: Operating Margin | C10: =Inputs!B8/Inputs!B6 -> 0.1168301 | D10: =Inputs!C8/Inputs!C6 -> 0.1091227 | E10: =Inputs!D8/Inputs!D6 -> 0.092851537 | F10: =Inputs!E8/Inputs!E6 -> 0.020803109 | G10: =Inputs!F8/Inputs!F6 -> 0.081920216 | I10: =AVERAGE(C10:G10) -> 0.084305531 | L10: 0.13 | M10: 0.14
B13: Modelling Factors
C15: Last 5 Years
C16: =C8 -> 2023 | D16: =D8 -> 2022 | E16: =E8 -> 2021 | F16: =F8 -> 2020 | G16: =G8 -> 2019 | I16: =I8 -> 5Y Average | L16: Short Term Forecast | M16: Long Term Forecast | O16: Reference
B17: Depreciation factor | C17: =DCF!F9/DCF!F40 -> -0.023138228 | D17: =DCF!E9/DCF!E40 -> -0.026598618 | E17: =DCF!D9/DCF!D40 -> -0.028143822 | F17: =-175.8/727.6 -> -0.24161627 | G17: =-173.6/823.9 -> -0.21070518 | I17: =AVERAGE(C17:G17) -> -0.10604042 | L17: 0.025 | M17: 0.025 | O17: % PPE
B18: Amortization factor | C18: =DCF!F10/DCF!F38 -> -0.022165928 | D18: =DCF!E10/DCF!E38 -> -0.024595204 | E18: =DCF!D10/DCF!D38 -> -0.020686802 | F18: =-13.03/473.7 -> -0.027506861 | G18: =-13.73/470.8 -> -0.029163127 | I18: =AVERAGE(C18:G18) -> -0.024823584 | L18: 0.025 | M18: 0.025 | O18: % IA
B19: Stock-based comp | C19: =DCF!F11/DCF!F6 -> -0.069524272 | D19: =DCF!E11/DCF!E6 -> -0.077940242 | E19: =DCF!D11/DCF!D6 -> -0.076128188 | F19: -- | G19: -- | I19: =AVERAGE(C19:E19) -> -0.074530901 | L19: 0.06 | M19: 0.06 | O19: % Revenue
B20: Tax Rate | C20: ='Fin. Data'!B21/('Fin. Data'!B21+'Fin. Data'!B23) -> -0.37944788 | D20: ='Fin. Data'!C21/('Fin. Data'!C21+'Fin. Data'!C23) -> -2.283293 | E20: ='Fin. Data'!D21/('Fin. Data'!D21+'Fin. Data'!D23) -> 0.18418784 | F20: ='Fin. Data'!E21/('Fin. Data'!E21+'Fin. Data'!E23) -> 0.22851797 | G20: ='Fin. Data'!F21/('Fin. Data'!F21+'Fin. Data'!F23) -> 1.9862237 | I20: =AVERAGE(C20:G20) -> -0.052762277 | L20: 0.24 | M20: 0.24 | O20: % EBT
B21: Interest Rate on debt | C21: =32.86/'Fin. Data'!B58 -> 0.029884409 | D21: =15.45/'Fin. Data'!C58 -> 0.015785118 | E21: =13.99/'Fin. Data'!D58 -> 0.011533769 | F21: =16.41/'Fin. Data'!E58 -> 0.01248127 | G21: =18.77/'Fin. Data'!E58 -> 0.014276261 | I21: =AVERAGE(C21:G21) -> 0.016792166 | L21: =I21 -> 0.016792166 | M21: 0.025 | O21: % Debt
B22: Interest Rate on cash | C22: =3.13/'Fin. Data'!B39 -> 0.0095718654 | D22: =1.82/'Fin. Data'!C39 -> 0.0066911765 | E22: =2.91/'Fin. Data'!D39 -> 0.0055640535 | F22: =4.4/'Fin. Data'!E39 -> 0.011340206 | G22: =6.89/'Fin. Data'!F39 -> 0.029194915 | I22: =AVERAGE(C22:G22) -> 0.012472443 | L22: 0.01 | M22: 0.005 | O22: % Cash
B23: PPE+ROA | C23: =Inputs!B33/Inputs!C33-1 -> 0.42568965 | D23: =Inputs!C33/Inputs!D33-1 -> -0.020095641 | E23: =Inputs!D33/Inputs!E33-1 -> -0.24702455 | F23: =Inputs!E33/Inputs!F33-1 -> -0.11686956 | G23: -- | I23: =AVERAGE(C23:F23) -> 0.010424974 | L23: -- | M23: -- | O23: Growing with CAPEX
B24: Working capital flows | C24: =Inputs!B62/(Inputs!B6-Inputs!C6) -> -0.045174538 | D24: =Inputs!C62/(Inputs!C6-Inputs!D6) -> -0.90909091 | E24: =Inputs!D62/(Inputs!D6-Inputs!E6) -> 0.064690027 | F24: =Inputs!E62/(Inputs!E6-Inputs!F6) -> 0.034267913 | G24: =Inputs!F62/(Inputs!F6-Inputs!G6) -> -0.15662651 | I24: =AVERAGE(C24:G24) -> -0.2023868 | L24: -0.05 | M24: 0.8 | O24: % Change in Revenues
B25: Intangible Assets | C25: 0.0002 | D25: 0.0527 | E25: 0.0497 | F25: 0.043 | G25: 0.0519 | I25: =AVERAGE(C25:G25) -> 0.0395 | L25: -- | M25: -- | O25: Growing with Amortization
B26: CAPEX | C26: =Inputs!B65/Inputs!B6 -> -0.029834951 | D26: =Inputs!C65/Inputs!C6 -> -0.032752702 | E26: =Inputs!D65/Inputs!D6 -> -0.058665795 | F26: =Inputs!E65/Inputs!E6 -> -0.025777202 | G26: =Inputs!F65/Inputs!F6 -> -0.035165652 | I26: =AVERAGE(C26:G26) -> -0.03643926 | L26: -0.035 | M26: -0.03 | O26: % Revenue
B27: Acquisition factor | C27: =Inputs!B66/Inputs!B6 -> 0.041485437 | D27: =Inputs!C66/Inputs!C6 -> -0.0053909727 | E27: =Inputs!D66/Inputs!D6 -> -0.0047743623 | F27: =Inputs!E66/Inputs!E6 -> 0.11731434 | G27: =Inputs!F66/Inputs!F6 -> 0.09872211 | I27: =AVERAGE(C27:G27) -> 0.049471309 | L27: -0.015 | M27: -0.04 | O27: % Revenue
B28: Dividends | C28: =Inputs!B73/Inputs!B12 -> -0.20598082 | D28: =Inputs!C73/Inputs!C12 -> -0.4245944 | E28: =Inputs!D73/Inputs!D12 -> -0.00074594393 | F28: =Inputs!E73/Inputs!E12 -> 0 | G28: =Inputs!F73/Inputs!F12 -> 0 | I28: =AVERAGE(C28:G28) -> -0.12626423 | L28: 0.2 | M28: 0.4 | O28: % Net Income
B29: Repurchases | C29: =Inputs!B74/Inputs!B12 -> -0.030436768 | D29: =Inputs!C74/Inputs!C12 -> -0.27654867 | E29: =Inputs!D74/Inputs!D12 -> 4.767825 | F29: =Inputs!E74/Inputs!E12 -> -0.017322016 | G29: =Inputs!F74/Inputs!F12 -> 0 | I29: =AVERAGE(C29:G29) -> 0.8887035 | L29: 0.04 | M29: 0.1 | O29: % Net Income
B30: Leases | C30: =Inputs!B72/Inputs!B6 -> 0.066019417 | D30: =Inputs!C72/Inputs!C6 -> 0.081373172 | E30: =Inputs!D72/Inputs!D6 -> 0.077828646 | F30: =Inputs!E72/Inputs!E6 -> 0.089810017 | G30: =Inputs!F72/Inputs!F6 -> 0.083840433 | I30: =AVERAGE(C30:G30) -> 0.079774337 | L30: 0.065 | M30: 0.03 | O30: % Revenue
B31: Total Debt | C31: ='Fin. Data'!B58/'Fin. Data'!B19 -> 2.2382193 | D31: ='Fin. Data'!C58/'Fin. Data'!C19 -> 2.4072061 | E31: ='Fin. Data'!D58/'Fin. Data'!D19 -> 2.0376294 | F31: ='Fin. Data'!E58/'Fin. Data'!E19 -> 4.2980386 | G31: ='Fin. Data'!F58/'Fin. Data'!F19 -> 3.5266067 | I31: =AVERAGE(C31:G31) -> 2.90154 | L31: 2.8 | M31: 2.5 | O31: % EBITDA
B34: Forecasts

Sheet Fin. Data
A1: =Inputs!H3 -> #VALUE!
A2: =Inputs!G2 -> Figures in Millions of USD
A3: Results
B4: =OP!J20 -> 2023 | C4: =B4-1 -> 2022 | D4: =C4-1 -> 2021 | E4: =D4-1 -> 2020 | F4: =E4-1 -> 2019 | G4: =F4-1 -> 2018 | H4: =G4-1 -> 2017 | I4: =H4-1 -> 2016 | J4: =I4-1 -> 2015 | ... M4: =L4-1 -> 2012
A5: Net Sales | B5: =_xlfn.XLOOKUP($A5,Inputs!$A:$A,Inputs!B:B,,0) -> 2060 | C5: =_xlfn.XLOOKUP($A5,Inputs!$A:$A,Inputs!C:C,,0) -> 1573 | D5: =_xlfn.XLOOKUP($A5,Inputs!$A:$A,Inputs!D:D,,0) -> 1529 | E5: =_xlfn.XLOOKUP($A5,Inputs!$A:$A,Inputs!E:E,,0) -> 1158 | F5: =_xlfn.XLOOKUP($A5,Inputs!$A:$A,Inputs!F:F,,0) -> 1479 | G5: =_xlfn.XLOOKUP($A5,Inputs!$A:$A,Inputs!G:G,,0) -> 1396 | H5: =_xlfn.XLOOKUP($A5,Inputs!$A:$A,Inputs!H:H,,0) -> N/A | I5: =_xlfn.XLOOKUP($A5,Inputs!$A:$A,Inputs!I:I,,0) -> N/A | J5: =_xlfn.XLOOKUP($A5,Inputs!$A:$A,Inputs!J:J,,0) -> N/A | K5: =_xlfn.XLOOKUP($A5,Inputs!$A:$A,Inputs!K:K,,0) -> N/A | L5: =_xlfn.XLOOKUP($A5,Inputs!$A:$A,Inputs!L:L,,0) -> N/A | M5: =_xlfn.XLOOKUP($A5,Inputs!$A:$A,Inputs!M:M,,0) -> N/A
A6: Growth vs. Previous year | B6: =IFERROR(B5/C5-1,"-") -> 0.30959949 | C6: =IFERROR(C5/D5-1,"-") -> 0.028776978 | D6: =IFERROR(D5/E5-1,"-") -> 0.32037997 | E6: =IFERROR(E5/F5-1,"-") -> -0.21703854 | F6: =IFERROR(F5/G5-1,"-") -> 0.059455587 | G6: =IFERROR(G5/H5-1,"-") -> - | H6: =IFERROR(H5/I5-1,"-") -> - | I6: =IFERROR(I5/J5-1,"-") -> - | ... L6: =IFERROR(L5/M5-1,"-") -> - | M6: =IFERROR(M5/#REF!-1,"-") -> -
A7: Gross Profit | B7: =_xlfn.XLOOKUP($A7,Inputs!$A:$A,Inputs!B:B,,0) -> 1323.93 | C7: =_xlfn.XLOOKUP($A7,Inputs!$A:$A,Inputs!C:C,,0) -> 977.64 | D7: =_xlfn.XLOOKUP($A7,Inputs!$A:$A,Inputs!D:D,,0) -> 942.36 | E7: =_xlfn.XLOOKUP($A7,Inputs!$A:$A,Inputs!E:E,,0) -> 611.18 | F7: =_xlfn.XLOOKUP($A7,Inputs!$A:$A,Inputs!F:F,,0) -> 855.62 | G7: =_xlfn.XLOOKUP($A7,Inputs!$A:$A,Inputs!G:G,,0) -> 858.76 | H7: =_xlfn.XLOOKUP($A7,Inputs!$A:$A,Inputs!H:H,,0) -> N/A | I7: =_xlfn.XLOOKUP($A7,Inputs!$A:$A,Inputs!I:I,,0) -> N/A | J7: =_xlfn.XLOOKUP($A7,Inputs!$A:$A,Inputs!J:J,,0) -> N/A | K7: =_xlfn.XLOOKUP($A7,Inputs!$A:$A,Inputs!K:K,,0) -> N/A | L7: =_xlfn.XLOOKUP($A7,Inputs!$A:$A,Inputs!L:L,,0) -> N/A | M7: =_xlfn.XLOOKUP($A7,Inputs!$A:$A,Inputs!M:M,,0) -> N/A
A8: % over sales | B8: =IFERROR(B7/B$5,"-") -> 0.64268447 | C8: =IFERROR(C7/C$5,"-") -> 0.62151303 | D8: =IFERROR(D7/D$5,"-") -> 0.6163244 | E8: =IFERROR(E7/E$5,"-") -> 0.52778929 | F8: =IFERROR(F7/F$5,"-") -> 0.57851251 | G8: =IFERROR(G7/G$5,"-") -> 0.61515759 | H8: =IFERROR(H7/H$5,"-") -> - | I8: =IFERROR(I7/I$5,"-") -> - | ... M8: =IFERROR(M7/M$5,"-") -> -
A9: Operating expenses | B9: =B5-B11 -> 1819.33 | C9: =C5-C11 -> 1401.35 | D9: =D5-D11 -> 1387.03 | E9: =E5-E11 -> 1133.91 | F9: =F5-F11 -> 1357.84 | G9: =G5-G11 -> 1270.37 | H9: =H5-H11 -> #VALUE! | I9: =I5-I11 -> #VALUE! | ... M9: =M5-M11 -> #VALUE!
A10: % over sales | B10: =IFERROR(B9/B$5,"-") -> 0.8831699 | C10: =IFERROR(C9/C$5,"-") -> 0.8908773 | D10: =IFERROR(D9/D$5,"-") -> 0.90714846 | E10: =IFERROR(E9/E$5,"-") -> 0.97919689 | F10: =IFERROR(F9/F$5,"-") -> 0.91807978 | G10: =IFERROR(G9/G$5,"-") -> 0.91000716 | H10: =IFERROR(H9/H$5,"-") -> - | I10: =IFERROR(I9/I$5,"-") -> - | ... M10: =IFERROR(M9/M$5,"-") -> -
A11: Operating Income | B11: =_xlfn.XLOOKUP($A11,Inputs!$A:$A,Inputs!B:B,,0) -> 240.67 | C11: =_xlfn.XLOOKUP($A11,Inputs!$A:$A,Inputs!C:C,,0) -> 171.65 | D11: =_xlfn.XLOOKUP($A11,Inputs!$A:$A,Inputs!D:D,,0) -> 141.97 | E11: =_xlfn.XLOOKUP($A11,Inputs!$A:$A,Inputs!E:E,,0) -> 24.09 | F11: =_xlfn.XLOOKUP($A11,Inputs!$A:$A,Inputs!F:F,,0) -> 121.16 | G11: =_xlfn.XLOOKUP($A11,Inputs!$A:$A,Inputs!G:G,,0) -> 125.63 | H11: =_xlfn.XLOOKUP($A11,Inputs!$A:$A,Inputs!H:H,,0) -> N/A | I11: =_xlfn.XLOOKUP($A11,Inputs!$A:$A,Inputs!I:I,,0) -> N/A | J11: =_xlfn.XLOOKUP($A11,Inputs!$A:$A,Inputs!J:J,,0) -> N/A | K11: =_xlfn.XLOOKUP($A11,Inputs!$A:$A,Inputs!K:K,,0) -> N/A | L11: =_xlfn.XLOOKUP($A11,Inputs!$A:$A,Inputs!L:L,,0) -> N/A | M11: =_xlfn.XLOOKUP($A11,Inputs!$A:$A,Inputs!M:M,,0) -> N/A
A12: Operating Margin | B12: =IFERROR(B11/B$5,"-") -> 0.1168301 | C12: =IFERROR(C11/C$5,"-") -> 0.1091227 | D12: =IFERROR(D11/D$5,"-") -> 0.092851537 | E12: =IFERROR(E11/E$5,"-") -> 0.020803109 | F12: =IFERROR(F11/F$5,"-") -> 0.081920216 | G12: =IFERROR(G11/G$5,"-") -> 0.089992837 | H12: =IFERROR(H11/H$5,"-") -> - | I12: =IFERROR(I11/I$5,"-") -> - | ... M12: =IFERROR(M11/M$5,"-") -> -
A13: Growth vs. Previous year | B13: =IFERROR(B12/C12-1,"-") -> 0.070630601 | C13: =IFERROR(C12/D12-1,"-") -> 0.17523844 | D13: =IFERROR(D12/E12-1,"-") -> 3.4633491 | E13: =IFERROR(E12/F12-1,"-") -> -0.74605647 | F13: =IFERROR(F12/G12-1,"-") -> -0.089702921 | G13: =IFERROR(G12/H12-1,"-") -> - | H13: =IFERROR(H12/I12-1,"-") -> - | I13: =IFERROR(I12/J12-1,"-") -> - | ... L13: =IFERROR(L12/M12-1,"-") -> - | M13: =IFERROR(M12/#REF!-1,"-") -> -
A14: Net Financial Cost | B14: =_xlfn.XLOOKUP($A14,Inputs!$A:$A,Inputs!B:B,,0) -> -33.5 | C14: =_xlfn.XLOOKUP($A14,Inputs!$A:$A,Inputs!C:C,,0) -> -27.74 | D14: =_xlfn.XLOOKUP($A14,Inputs!$A:$A,Inputs!D:D,,0) -> -6.21 | E14: =_xlfn.XLOOKUP($A14,Inputs!$A:$A,Inputs!E:E,,0) -> 5.09 | F14: =_xlfn.XLOOKUP($A14,Inputs!$A:$A,Inputs!F:F,,0) -> -6.9 | G14: =_xlfn.XLOOKUP($A14,Inputs!$A:$A,Inputs!G:G,,0) -> -22.58 | H14: =_xlfn.XLOOKUP($A14,Inputs!$A:$A,Inputs!H:H,,0) -> N/A | I14: =_xlfn.XLOOKUP($A14,Inputs!$A:$A,Inputs!I:I,,0) -> N/A | J14: =_xlfn.XLOOKUP($A14,Inputs!$A:$A,Inputs!J:J,,0) -> N/A | K14: =_xlfn.XLOOKUP($A14,Inputs!$A:$A,Inputs!K:K,,0) -> N/A | L14: =_xlfn.XLOOKUP($A14,Inputs!$A:$A,Inputs!L:L,,0) -> N/A | M14: =_xlfn.XLOOKUP($A14,Inputs!$A:$A,Inputs!M:M,,0) -> N/A
A15: Other Expenses (Revenues) | B15: =_xlfn.XLOOKUP($A15,Inputs!$A:$A,Inputs!B:B,,0) -> -39.6 | C15: =_xlfn.XLOOKUP($A15,Inputs!$A:$A,Inputs!C:C,,0) -> -51.95 | D15: =_xlfn.XLOOKUP($A15,Inputs!$A:$A,Inputs!D:D,,0) -> -260.31 | E15: =_xlfn.XLOOKUP($A15,Inputs!$A:$A,Inputs!E:E,,0) -> -69.81 | F15: =_xlfn.XLOOKUP($A15,Inputs!$A:$A,Inputs!F:F,,0) -> -40.9 | G15: =_xlfn.XLOOKUP($A15,Inputs!$A:$A,Inputs!G:G,,0) -> -23.82 | H15: =_xlfn.XLOOKUP($A15,Inputs!$A:$A,Inputs!H:H,,0) -> N/A | I15: =_xlfn.XLOOKUP($A15,Inputs!$A:$A,Inputs!I:I,,0) -> N/A | J15: =_xlfn.XLOOKUP($A15,Inputs!$A:$A,Inputs!J:J,,0) -> N/A | K15: =_xlfn.XLOOKUP($A15,Inputs!$A:$A,Inputs!K:K,,0) -> N/A | L15: =_xlfn.XLOOKUP($A15,Inputs!$A:$A,Inputs!L:L,,0) -> N/A | M15: =_xlfn.XLOOKUP($A15,Inputs!$A:$A,Inputs!M:M,,0) -> N/A
A16: EBIT | B16: =B11-B15 -> 280.27 | C16: =C11-C15 -> 223.6 | D16: =D11-D15 -> 402.28 | E16: =E11-E15 -> 93.9 | F16: =F11-F15 -> 162.06 | G16: =G11-G15 -> 149.45 | H16: =H11-H15 -> #VALUE! | I16: =I11-I15 -> #VALUE! | ... M16: =M11-M15 -> #VALUE!
A17: Depreciation & Amortization | B17: =_xlfn.XLOOKUP($A17,Inputs!$A:$A,Inputs!B:B,,0) -> 211 | C17: =_xlfn.XLOOKUP($A17,Inputs!$A:$A,Inputs!C:C,,0) -> 183 | D17: =_xlfn.XLOOKUP($A17,Inputs!$A:$A,Inputs!D:D,,0) -> 193 | E17: =_xlfn.XLOOKUP($A17,Inputs!$A:$A,Inputs!E:E,,0) -> 212 | F17: =_xlfn.XLOOKUP($A17,Inputs!$A:$A,Inputs!F:F,,0) -> 198 | G17: =_xlfn.XLOOKUP($A17,Inputs!$A:$A,Inputs!G:G,,0) -> 190 | H17: =_xlfn.XLOOKUP($A17,Inputs!$A:$A,Inputs!H:H,,0) -> N/A | I17: =_xlfn.XLOOKUP($A17,Inputs!$A:$A,Inputs!I:I,,0) -> N/A | J17: =_xlfn.XLOOKUP($A17,Inputs!$A:$A,Inputs!J:J,,0) -> N/A | K17: =_xlfn.XLOOKUP($A17,Inputs!$A:$A,Inputs!K:K,,0) -> N/A | L17: =_xlfn.XLOOKUP($A17,Inputs!$A:$A,Inputs!L:L,,0) -> N/A | M17: =_xlfn.XLOOKUP($A17,Inputs!$A:$A,Inputs!M:M,,0) -> N/A
A18: Changes Net Working Capital | B18: =_xlfn.XLOOKUP($A18,Inputs!$A:$A,Inputs!B:B,,0) -> -199.01 | C18: =_xlfn.XLOOKUP($A18,Inputs!$A:$A,Inputs!C:C,,0) -> -76.48 | D18: =_xlfn.XLOOKUP($A18,Inputs!$A:$A,Inputs!D:D,,0) -> -218.88 | E18: =_xlfn.XLOOKUP($A18,Inputs!$A:$A,Inputs!E:E,,0) -> -9.17 | F18: =_xlfn.XLOOKUP($A18,Inputs!$A:$A,Inputs!F:F,,0) -> N/A | G18: =_xlfn.XLOOKUP($A18,Inputs!$A:$A,Inputs!G:G,,0) -> N/A | H18: =_xlfn.XLOOKUP($A18,Inputs!$A:$A,Inputs!H:H,,0) -> N/A | I18: =_xlfn.XLOOKUP($A18,Inputs!$A:$A,Inputs!I:I,,0) -> N/A | J18: =_xlfn.XLOOKUP($A18,Inputs!$A:$A,Inputs!J:J,,0) -> N/A | K18: =_xlfn.XLOOKUP($A18,Inputs!$A:$A,Inputs!K:K,,0) -> N/A | L18: =_xlfn.XLOOKUP($A18,Inputs!$A:$A,Inputs!L:L,,0) -> N/A | M18: =_xlfn.XLOOKUP($A18,Inputs!$A:$A,Inputs!M:M,,0) -> N/A
A19: EBITDA | B19: =B11-B15+B17 -> 491.27 | C19: =C11-C15+C17 -> 406.6 | D19: =D11-D15+D17 -> 595.28 | E19: =E11-E15+E17 -> 305.9 | F19: =F11-F15+F17 -> 360.06 | G19: =G11-G15+G17 -> 339.45 | H19: =H11-H15+H17 -> #VALUE! | I19: =I11-I15+I17 -> #VALUE! | ... M19: =M11-M15+M17 -> #VALUE!
A20: EBITDA Margin | B20: =IFERROR(B19/B$5,"-") -> 0.23848058 | C20: =IFERROR(C19/C$5,"-") -> 0.25848697 | D20: =IFERROR(D19/D$5,"-") -> 0.38932636 | E20: =IFERROR(E19/E$5,"-") -> 0.26416235 | F20: =IFERROR(F19/F$5,"-") -> 0.24344828 | G20: =IFERROR(G19/G$5,"-") -> 0.24315903 | H20: =IFERROR(H19/H$5,"-") -> - | I20: =IFERROR(I19/I$5,"-") -> - | ... M20: =IFERROR(M19/M$5,"-") -> -
A21: Taxes | B21: =_xlfn.XLOOKUP($A21,Inputs!$A:$A,Inputs!B:B,,0) -> -36.15 | C21: =_xlfn.XLOOKUP($A21,Inputs!$A:$A,Inputs!C:C,,0) -> -37.72 | D21: =_xlfn.XLOOKUP($A21,Inputs!$A:$A,Inputs!D:D,,0) -> -36.32 | E21: =_xlfn.XLOOKUP($A21,Inputs!$A:$A,Inputs!E:E,,0) -> -17.1 | F21: =_xlfn.XLOOKUP($A21,Inputs!$A:$A,Inputs!F:F,,0) -> -49.02 | G21: =_xlfn.XLOOKUP($A21,Inputs!$A:$A,Inputs!G:G,,0) -> -34.7 | H21: =_xlfn.XLOOKUP($A21,Inputs!$A:$A,Inputs!H:H,,0) -> N/A | I21: =_xlfn.XLOOKUP($A21,Inputs!$A:$A,Inputs!I:I,,0) -> N/A | J21: =_xlfn.XLOOKUP($A21,Inputs!$A:$A,Inputs!J:J,,0) -> N/A | K21: =_xlfn.XLOOKUP($A21,Inputs!$A:$A,Inputs!K:K,,0) -> N/A | L21: =_xlfn.XLOOKUP($A21,Inputs!$A:$A,Inputs!L:L,,0) -> N/A | M21: =_xlfn.XLOOKUP($A21,Inputs!$A:$A,Inputs!M:M,,0) -> N/A
A22: % Tax | B22: =IFERROR(B21/B$5,"-") -> -0.017548544 | C22: =IFERROR(C21/C$5,"-") -> -0.023979657 | D22: =IFERROR(D21/D$5,"-") -> -0.023754088 | E22: =IFERROR(E21/E$5,"-") -> -0.014766839 | F22: =IFERROR(F21/F$5,"-") -> -0.033144016 | G22: =IFERROR(G21/G$5,"-") -> -0.024856734 | H22: =IFERROR(H21/H$5,"-") -> - | I22: =IFERROR(I21/I$5,"-") -> - | ... M22: =IFERROR(M21/M$5,"-") -> -
A23: Net Income | B23: =_xlfn.XLOOKUP($A23,Inputs!$A:$A,Inputs!B:B,,0) -> 131.42 | C23: =_xlfn.XLOOKUP($A23,Inputs!$A:$A,Inputs!C:C,,0) -> 54.24 | D23: =_xlfn.XLOOKUP($A23,Inputs!$A:$A,Inputs!D:D,,0) -> -160.87 | E23: =_xlfn.XLOOKUP($A23,Inputs!$A:$A,Inputs!E:E,,0) -> -57.73 | F23: =_xlfn.XLOOKUP($A23,Inputs!$A:$A,Inputs!F:F,,0) -> 24.34 | G23: =_xlfn.XLOOKUP($A23,Inputs!$A:$A,Inputs!G:G,,0) -> 44.53 | H23: =_xlfn.XLOOKUP($A23,Inputs!$A:$A,Inputs!H:H,,0) -> N/A | I23: =_xlfn.XLOOKUP($A23,Inputs!$A:$A,Inputs!I:I,,0) -> N/A | J23: =_xlfn.XLOOKUP($A23,Inputs!$A:$A,Inputs!J:J,,0) -> N/A | K23: =_xlfn.XLOOKUP($A23,Inputs!$A:$A,Inputs!K:K,,0) -> N/A | L23: =_xlfn.XLOOKUP($A23,Inputs!$A:$A,Inputs!L:L,,0) -> N/A | M23: =_xlfn.XLOOKUP($A23,Inputs!$A:$A,Inputs!M:M,,0) -> N/A
A24: Net Income Margin | B24: =IFERROR(B23/B$5,"-") -> 0.063796117 | C24: =IFERROR(C23/C$5,"-") -> 0.034481882 | D24: =IFERROR(D23/D$5,"-") -> -0.10521256 | E24: =IFERROR(E23/E$5,"-") -> -0.049853195 | F24: =IFERROR(F23/F$5,"-") -> 0.016457066 | G24: =IFERROR(G23/G$5,"-") -> 0.031898281 | H24: =IFERROR(H23/H$5,"-") -> - | I24: =IFERROR(I23/I$5,"-") -> - | ... M24: =IFERROR(M23/M$5,"-") -> -
A25: Growth vs. Previous year | B25: =IFERROR(B24/C24-1,"-") -> 0.85013443 | C25: =IFERROR(C24/D24-1,"-") -> -1.3277354 | D25: =IFERROR(D24/E24-1,"-") -> 1.1104476 | E25: =IFERROR(E24/F24-1,"-") -> -4.0292882 | F25: =IFERROR(F24/G24-1,"-") -> -0.48407672 | G25: =IFERROR(G24/H24-1,"-") -> - | H25: =IFERROR(H24/I24-1,"-") -> - | I25: =IFERROR(I24/J24-1,"-") -> - | ... L25: =IFERROR(L24/M24-1,"-") -> - | M25: =IFERROR(M24/#REF!-1,"-") -> -
A26: Cash Generated | B26: =B39-C39 -> 55 | C26: =C39-D39 -> -251 | D26: =D39-E39 -> 135 | E26: =E39-F39 -> 152 | F26: =F39-G39 -> #VALUE! | G26: =G39-H39 -> #VALUE! | H26: =H39-I39 -> #VALUE! | I26: =I39-J39 -> #VALUE! | ... M26: =M39-N39 -> #VALUE!
A27: Dividends | B27: =_xlfn.XLOOKUP($A27,Inputs!$A:$A,Inputs!B:B,,0) -> -27.07 | C27: =_xlfn.XLOOKUP($A27,Inputs!$A:$A,Inputs!C:C,,0) -> -23.03 | D27: =_xlfn.XLOOKUP($A27,Inputs!$A:$A,Inputs!D:D,,0) -> 0.12 | E27: =_xlfn.XLOOKUP($A27,Inputs!$A:$A,Inputs!E:E,,0) -> 0 | F27: =_xlfn.XLOOKUP($A27,Inputs!$A:$A,Inputs!F:F,,0) -> 0 | G27: =_xlfn.XLOOKUP($A27,Inputs!$A:$A,Inputs!G:G,,0) -> 0 | H27: =_xlfn.XLOOKUP($A27,Inputs!$A:$A,Inputs!H:H,,0) -> N/A | I27: =_xlfn.XLOOKUP($A27,Inputs!$A:$A,Inputs!I:I,,0) -> N/A | J27: =_xlfn.XLOOKUP($A27,Inputs!$A:$A,Inputs!J:J,,0) -> N/A | K27: =_xlfn.XLOOKUP($A27,Inputs!$A:$A,Inputs!K:K,,0) -> N/A | L27: =_xlfn.XLOOKUP($A27,Inputs!$A:$A,Inputs!L:L,,0) -> N/A | M27: =_xlfn.XLOOKUP($A27,Inputs!$A:$A,Inputs!M:M,,0) -> N/A
A28: Share buyback | B28: =_xlfn.XLOOKUP($A28,Inputs!$A:$A,Inputs!B:B,,0) -> -4 | C28: =_xlfn.XLOOKUP($A28,Inputs!$A:$A,Inputs!C:C,,0) -> -15 | D28: =_xlfn.XLOOKUP($A28,Inputs!$A:$A,Inputs!D:D,,0) -> -767 | E28: =_xlfn.XLOOKUP($A28,Inputs!$A:$A,Inputs!E:E,,0) -> 1 | F28: =_xlfn.XLOOKUP($A28,Inputs!$A:$A,Inputs!F:F,,0) -> 0 | G28: =_xlfn.XLOOKUP($A28,Inputs!$A:$A,Inputs!G:G,,0) -> -3 | H28: =_xlfn.XLOOKUP($A28,Inputs!$A:$A,Inputs!H:H,,0) -> N/A | I28: =_xlfn.XLOOKUP($A28,Inputs!$A:$A,Inputs!I:I,,0) -> N/A | J28: =_xlfn.XLOOKUP($A28,Inputs!$A:$A,Inputs!J:J,,0) -> N/A | K28: =_xlfn.XLOOKUP($A28,Inputs!$A:$A,Inputs!K:K,,0) -> N/A | L28: =_xlfn.XLOOKUP($A28,Inputs!$A:$A,Inputs!L:L,,0) -> N/A | M28: =_xlfn.XLOOKUP($A28,Inputs!$A:$A,Inputs!M:M,,0) -> N/A
A29: Net Cash Flow | B29: =SUM(B26:B28) -> 23.93 | C29: =SUM(C26:C28) -> -289.03 | D29: =SUM(D26:D28) -> -631.88 | E29: =SUM(E26:E28) -> 153 | F29: =SUM(F26:F28) -> #VALUE! | G29: =SUM(G26:G28) -> #VALUE! | H29: =SUM(H26:H28) -> #VALUE! | I29: =SUM(I26:I28) -> #VALUE! | ... M29: =SUM(M26:M28) -> #VALUE!
A30: FNP'' | B30: =+B29-(B58-C29) -> -1364.67 | C30: =+C29-(C58-D29) -> -1899.68 | D30: =+D29-(D58-E29) -> -1691.84 | E30: =+E29-(E58-F29) -> #VALUE! | F30: =+F29-(F58-G29) -> #VALUE! | G30: =+G29-(G58-H29) -> #VALUE! | H30: =+H29-(H58-I29) -> #VALUE! | I30: =+I29-(I58-J29) -> #VALUE! | ... M30: =+M29-(M58-N29) -> #VALUE!
A31: FNP' | B31: =+B30+B33 -> -1279.21 | C31: =+C30+C33 -> -1908.16 | D31: =+D30+D33 -> -1699.14 | E31: =+E30+E33 -> #VALUE! | F31: =+F30+F33 -> #VALUE! | G31: =+G30+G33 -> #VALUE! | H31: =+H30+H33 -> #VALUE! | I31: =+I30+I33 -> #VALUE! | ... M31: =+M30+M33 -> #VALUE!
A32: Net Capex | B32: =_xlfn.XLOOKUP($A32,Inputs!$A:$A,Inputs!B:B,,0) -> -61.46 | C32: =_xlfn.XLOOKUP($A32,Inputs!$A:$A,Inputs!C:C,,0) -> -51.52 | D32: =_xlfn.XLOOKUP($A32,Inputs!$A:$A,Inputs!D:D,,0) -> -89.7 | E32: =_xlfn.XLOOKUP($A32,Inputs!$A:$A,Inputs!E:E,,0) -> -29.85 | F32: =_xlfn.XLOOKUP($A32,Inputs!$A:$A,Inputs!F:F,,0) -> -52.01 | G32: =_xlfn.XLOOKUP($A32,Inputs!$A:$A,Inputs!G:G,,0) -> -17.85 | H32: =_xlfn.XLOOKUP($A32,Inputs!$A:$A,Inputs!H:H,,0) -> N/A | I32: =_xlfn.XLOOKUP($A32,Inputs!$A:$A,Inputs!I:I,,0) -> N/A | J32: =_xlfn.XLOOKUP($A32,Inputs!$A:$A,Inputs!J:J,,0) -> N/A | K32: =_xlfn.XLOOKUP($A32,Inputs!$A:$A,Inputs!K:K,,0) -> N/A | L32: =_xlfn.XLOOKUP($A32,Inputs!$A:$A,Inputs!L:L,,0) -> N/A | M32: =_xlfn.XLOOKUP($A32,Inputs!$A:$A,Inputs!M:M,,0) -> N/A
A33: Investments & Acquisitions | B33: =_xlfn.XLOOKUP($A33,Inputs!$A:$A,Inputs!B:B,,0) -> 85.46 | C33: =_xlfn.XLOOKUP($A33,Inputs!$A:$A,Inputs!C:C,,0) -> -8.48 | D33: =_xlfn.XLOOKUP($A33,Inputs!$A:$A,Inputs!D:D,,0) -> -7.3 | E33: =_xlfn.XLOOKUP($A33,Inputs!$A:$A,Inputs!E:E,,0) -> 135.85 | F33: =_xlfn.XLOOKUP($A33,Inputs!$A:$A,Inputs!F:F,,0) -> 146.01 | G33: =_xlfn.XLOOKUP($A33,Inputs!$A:$A,Inputs!G:G,,0) -> -376.8 | H33: =_xlfn.XLOOKUP($A33,Inputs!$A:$A,Inputs!H:H,,0) -> N/A | I33: =_xlfn.XLOOKUP($A33,Inputs!$A:$A,Inputs!I:I,,0) -> N/A | J33: =_xlfn.XLOOKUP($A33,Inputs!$A:$A,Inputs!J:J,,0) -> N/A | K33: =_xlfn.XLOOKUP($A33,Inputs!$A:$A,Inputs!K:K,,0) -> N/A | L33: =_xlfn.XLOOKUP($A33,Inputs!$A:$A,Inputs!L:L,,0) -> N/A | M33: =_xlfn.XLOOKUP($A33,Inputs!$A:$A,Inputs!M:M,,0) -> N/A
A34: Capex + Investments | B34: =+B32+B33 -> 24 | C34: =+C32+C33 -> -60 | D34: =+D32+D33 -> -97 | E34: =+E32+E33 -> 106 | F34: =+F32+F33 -> 94 | G34: =+G32+G33 -> -394.65 | H34: =+H32+H33 -> #VALUE! | I34: =+I32+I33 -> #VALUE! | ... M34: =+M32+M33 -> #VALUE!
A35: Dividends + Share Buyback | B35: =+B27+B28 -> -31.07 | C35: =+C27+C28 -> -38.03 | D35: =+D27+D28 -> -766.88 | E35: =+E27+E28 -> 1 | F35: =+F27+F28 -> 0 | G35: =+G27+G28 -> -3 | H35: =+H27+H28 -> #VALUE! | I35: =+I27+I28 -> #VALUE! | ... M35: =+M27+M28 -> #VALUE!
A36: Payout Ratio | B36: =IFERROR(B35/B23,"-") -> -0.23641759 | C36: =IFERROR(C35/C23,"-") -> -0.70114307 | D36: =IFERROR(D35/D23,"-") -> 4.767079 | E36: =IFERROR(E35/E23,"-") -> -0.017322016 | F36: =IFERROR(F35/F23,"-") -> 0 | G36: =IFERROR(G35/G23,"-") -> -0.067370312 | H36: =IFERROR(H35/H23,"-") -> - | I36: =IFERROR(I35/I23,"-") -> - | ... M36: =IFERROR(M35/M23,"-") -> -
A38: Assets
A39: Cash & Eq. | B39: =_xlfn.XLOOKUP($A39,Inputs!$A:$A,Inputs!B:B,,0) -> 327 | C39: =_xlfn.XLOOKUP($A39,Inputs!$A:$A,Inputs!C:C,,0) -> 272 | D39: =_xlfn.XLOOKUP($A39,Inputs!$A:$A,Inputs!D:D,,0) -> 523 | E39: =_xlfn.XLOOKUP($A39,Inputs!$A:$A,Inputs!E:E,,0) -> 388 | F39: =_xlfn.XLOOKUP($A39,Inputs!$A:$A,Inputs!F:F,,0) -> 236 | G39: =_xlfn.XLOOKUP($A39,Inputs!$A:$A,Inputs!G:G,,0) -> N/A | H39: =_xlfn.XLOOKUP($A39,Inputs!$A:$A,Inputs!H:H,,0) -> N/A | I39: =_xlfn.XLOOKUP($A39,Inputs!$A:$A,Inputs!I:I,,0) -> N/A | J39: =_xlfn.XLOOKUP($A39,Inputs!$A:$A,Inputs!J:J,,0) -> N/A | K39: =_xlfn.XLOOKUP($A39,Inputs!$A:$A,Inputs!K:K,,0) -> N/A | L39: =_xlfn.XLOOKUP($A39,Inputs!$A:$A,Inputs!L:L,,0) -> N/A | M39: =_xlfn.XLOOKUP($A39,Inputs!$A:$A,Inputs!M:M,,0) -> N/A
A40: Accounts Receivable | B40: =_xlfn.XLOOKUP($A40,Inputs!$A:$A,Inputs!B:B,,0) -> 273 | C40: =_xlfn.XLOOKUP($A40,Inputs!$A:$A,Inputs!C:C,,0) -> 197 | D40: =_xlfn.XLOOKUP($A40,Inputs!$A:$A,Inputs!D:D,,0) -> 190 | E40: =_xlfn.XLOOKUP($A40,Inputs!$A:$A,Inputs!E:E,,0) -> 180 | F40: =_xlfn.XLOOKUP($A40,Inputs!$A:$A,Inputs!F:F,,0) -> 206 | G40: =_xlfn.XLOOKUP($A40,Inputs!$A:$A,Inputs!G:G,,0) -> N/A | H40: =_xlfn.XLOOKUP($A40,Inputs!$A:$A,Inputs!H:H,,0) -> N/A | I40: =_xlfn.XLOOKUP($A40,Inputs!$A:$A,Inputs!I:I,,0) -> N/A | J40: =_xlfn.XLOOKUP($A40,Inputs!$A:$A,Inputs!J:J,,0) -> N/A | K40: =_xlfn.XLOOKUP($A40,Inputs!$A:$A,Inputs!K:K,,0) -> N/A | L40: =_xlfn.XLOOKUP($A40,Inputs!$A:$A,Inputs!L:L,,0) -> N/A | M40: =_xlfn.XLOOKUP($A40,Inputs!$A:$A,Inputs!M:M,,0) -> N/A
A41: Inventory | B41: =_xlfn.XLOOKUP($A41,Inputs!$A:$A,Inputs!B:B,,0) -> 577 | C41: =_xlfn.XLOOKUP($A41,Inputs!$A:$A,Inputs!C:C,,0) -> 440 | D41: =_xlfn.XLOOKUP($A41,Inputs!$A:$A,Inputs!D:D,,0) -> 385 | E41: =_xlfn.XLOOKUP($A41,Inputs!$A:$A,Inputs!E:E,,0) -> 393 | F41: =_xlfn.XLOOKUP($A41,Inputs!$A:$A,Inputs!F:F,,0) -> 353 | G41: =_xlfn.XLOOKUP($A41,Inputs!$A:$A,Inputs!G:G,,0) -> N/A | H41: =_xlfn.XLOOKUP($A41,Inputs!$A:$A,Inputs!H:H,,0) -> N/A | I41: =_xlfn.XLOOKUP($A41,Inputs!$A:$A,Inputs!I:I,,0) -> N/A | J41: =_xlfn.XLOOKUP($A41,Inputs!$A:$A,Inputs!J:J,,0) -> N/A | K41: =_xlfn.XLOOKUP($A41,Inputs!$A:$A,Inputs!K:K,,0) -> N/A | L41: =_xlfn.XLOOKUP($A41,Inputs!$A:$A,Inputs!L:L,,0) -> N/A | M41: =_xlfn.XLOOKUP($A41,Inputs!$A:$A,Inputs!M:M,,0) -> N/A
A42: Property, Plant and Equipment | B42: =_xlfn.XLOOKUP($A42,Inputs!$A:$A,Inputs!B:B,,0) -> 765.41 | C42: =_xlfn.XLOOKUP($A42,Inputs!$A:$A,Inputs!C:C,,0) -> 536.87 | D42: =_xlfn.XLOOKUP($A42,Inputs!$A:$A,Inputs!D:D,,0) -> 547.88 | E42: =_xlfn.XLOOKUP($A42,Inputs!$A:$A,Inputs!E:E,,0) -> 727.62 | F42: =_xlfn.XLOOKUP($A42,Inputs!$A:$A,Inputs!F:F,,0) -> 823.91 | G42: =_xlfn.XLOOKUP($A42,Inputs!$A:$A,Inputs!G:G,,0) -> N/A | H42: =_xlfn.XLOOKUP($A42,Inputs!$A:$A,Inputs!H:H,,0) -> N/A | I42: =_xlfn.XLOOKUP($A42,Inputs!$A:$A,Inputs!I:I,,0) -> N/A | J42: =_xlfn.XLOOKUP($A42,Inputs!$A:$A,Inputs!J:J,,0) -> N/A | K42: =_xlfn.XLOOKUP($A42,Inputs!$A:$A,Inputs!K:K,,0) -> N/A | L42: =_xlfn.XLOOKUP($A42,Inputs!$A:$A,Inputs!L:L,,0) -> N/A | M42: =_xlfn.XLOOKUP($A42,Inputs!$A:$A,Inputs!M:M,,0) -> N/A
A43: Other Assets | B43: =_xlfn.XLOOKUP($A43,Inputs!$A:$A,Inputs!B:B,,0) -> 501.27 | C43: =_xlfn.XLOOKUP($A43,Inputs!$A:$A,Inputs!C:C,,0) -> 725.12 | D43: =_xlfn.XLOOKUP($A43,Inputs!$A:$A,Inputs!D:D,,0) -> 701.4 | E43: =_xlfn.XLOOKUP($A43,Inputs!$A:$A,Inputs!E:E,,0) -> 784.42 | F43: =_xlfn.XLOOKUP($A43,Inputs!$A:$A,Inputs!F:F,,0) -> 773.08 | G43: =_xlfn.XLOOKUP($A43,Inputs!$A:$A,Inputs!G:G,,0) -> 0 | H43: =_xlfn.XLOOKUP($A43,Inputs!$A:$A,Inputs!H:H,,0) -> 0 | I43: =_xlfn.XLOOKUP($A43,Inputs!$A:$A,Inputs!I:I,,0) -> 0 | J43: =_xlfn.XLOOKUP($A43,Inputs!$A:$A,Inputs!J:J,,0) -> 0 | K43: =_xlfn.XLOOKUP($A43,Inputs!$A:$A,Inputs!K:K,,0) -> 0 | L43: =_xlfn.XLOOKUP($A43,Inputs!$A:$A,Inputs!L:L,,0) -> 0 | M43: =_xlfn.XLOOKUP($A43,Inputs!$A:$A,Inputs!M:M,,0) -> 0
A44: Total Assets | B44: =_xlfn.XLOOKUP($A44,Inputs!$A:$A,Inputs!B:B,,0) -> 3053.66 | C44: =_xlfn.XLOOKUP($A44,Inputs!$A:$A,Inputs!C:C,,0) -> 2597.1 | D44: =_xlfn.XLOOKUP($A44,Inputs!$A:$A,Inputs!D:D,,0) -> 2793.95 | E44: =_xlfn.XLOOKUP($A44,Inputs!$A:$A,Inputs!E:E,,0) -> 2949.5 | F44: =_xlfn.XLOOKUP($A44,Inputs!$A:$A,Inputs!F:F,,0) -> 2958.77 | G44: =_xlfn.XLOOKUP($A44,Inputs!$A:$A,Inputs!G:G,,0) -> 0 | H44: =_xlfn.XLOOKUP($A44,Inputs!$A:$A,Inputs!H:H,,0) -> 0 | I44: =_xlfn.XLOOKUP($A44,Inputs!$A:$A,Inputs!I:I,,0) -> 0 | J44: =_xlfn.XLOOKUP($A44,Inputs!$A:$A,Inputs!J:J,,0) -> 0 | K44: =_xlfn.XLOOKUP($A44,Inputs!$A:$A,Inputs!K:K,,0) -> 0 | L44: =_xlfn.XLOOKUP($A44,Inputs!$A:$A,Inputs!L:L,,0) -> 0 | M44: =_xlfn.XLOOKUP($A44,Inputs!$A:$A,Inputs!M:M,,0) -> 0
A47: Liabilities
A48: Current Liabilities | B48: =_xlfn.XLOOKUP($A48,Inputs!$A:$A,Inputs!B:B,,0) -> 1116.97 | C48: =_xlfn.XLOOKUP($A48,Inputs!$A:$A,Inputs!C:C,,0) -> 927.85 | D48: =_xlfn.XLOOKUP($A48,Inputs!$A:$A,Inputs!D:D,,0) -> 798.39 | E48: =_xlfn.XLOOKUP($A48,Inputs!$A:$A,Inputs!E:E,,0) -> 653.95 | F48: =_xlfn.XLOOKUP($A48,Inputs!$A:$A,Inputs!F:F,,0) -> 680.87 | G48: =_xlfn.XLOOKUP($A48,Inputs!$A:$A,Inputs!G:G,,0) -> 0 | H48: =_xlfn.XLOOKUP($A48,Inputs!$A:$A,Inputs!H:H,,0) -> 0 | I48: =_xlfn.XLOOKUP($A48,Inputs!$A:$A,Inputs!I:I,,0) -> 0 | J48: =_xlfn.XLOOKUP($A48,Inputs!$A:$A,Inputs!J:J,,0) -> 0 | K48: =_xlfn.XLOOKUP($A48,Inputs!$A:$A,Inputs!K:K,,0) -> 0 | L48: =_xlfn.XLOOKUP($A48,Inputs!$A:$A,Inputs!L:L,,0) -> 0 | M48: =_xlfn.XLOOKUP($A48,Inputs!$A:$A,Inputs!M:M,,0) -> 0
A49: Short-Term Debt | B49: =_xlfn.XLOOKUP($A49,Inputs!$A:$A,Inputs!B:B,,0) -> 319.31 | C49: =_xlfn.XLOOKUP($A49,Inputs!$A:$A,Inputs!C:C,,0) -> 306.27 | D49: =_xlfn.XLOOKUP($A49,Inputs!$A:$A,Inputs!D:D,,0) -> 178.81 | E49: =_xlfn.XLOOKUP($A49,Inputs!$A:$A,Inputs!E:E,,0) -> 129.49 | F49: =_xlfn.XLOOKUP($A49,Inputs!$A:$A,Inputs!F:F,,0) -> 118.86 | G49: =_xlfn.XLOOKUP($A49,Inputs!$A:$A,Inputs!G:G,,0) -> N/A | H49: =_xlfn.XLOOKUP($A49,Inputs!$A:$A,Inputs!H:H,,0) -> N/A | I49: =_xlfn.XLOOKUP($A49,Inputs!$A:$A,Inputs!I:I,,0) -> N/A | J49: =_xlfn.XLOOKUP($A49,Inputs!$A:$A,Inputs!J:J,,0) -> N/A | K49: =_xlfn.XLOOKUP($A49,Inputs!$A:$A,Inputs!K:K,,0) -> N/A | L49: =_xlfn.XLOOKUP($A49,Inputs!$A:$A,Inputs!L:L,,0) -> N/A | M49: =_xlfn.XLOOKUP($A49,Inputs!$A:$A,Inputs!M:M,,0) -> N/A
A50: Short-Term Leases | B50: =_xlfn.XLOOKUP($A50,Inputs!$A:$A,Inputs!B:B,,0) -> 135.35 | C50: =_xlfn.XLOOKUP($A50,Inputs!$A:$A,Inputs!C:C,,0) -> 119.28 | D50: =_xlfn.XLOOKUP($A50,Inputs!$A:$A,Inputs!D:D,,0) -> 121.23 | E50: =_xlfn.XLOOKUP($A50,Inputs!$A:$A,Inputs!E:E,,0) -> 113.39 | F50: =_xlfn.XLOOKUP($A50,Inputs!$A:$A,Inputs!F:F,,0) -> 114.92 | G50: =_xlfn.XLOOKUP($A50,Inputs!$A:$A,Inputs!G:G,,0) -> N/A | H50: =_xlfn.XLOOKUP($A50,Inputs!$A:$A,Inputs!H:H,,0) -> N/A | I50: =_xlfn.XLOOKUP($A50,Inputs!$A:$A,Inputs!I:I,,0) -> N/A | J50: =_xlfn.XLOOKUP($A50,Inputs!$A:$A,Inputs!J:J,,0) -> N/A | K50: =_xlfn.XLOOKUP($A50,Inputs!$A:$A,Inputs!K:K,,0) -> N/A | L50: =_xlfn.XLOOKUP($A50,Inputs!$A:$A,Inputs!L:L,,0) -> N/A | M50: =_xlfn.XLOOKUP($A50,Inputs!$A:$A,Inputs!M:M,,0) -> N/A
A51: Other current liabilities | B51: =_xlfn.XLOOKUP($A51,Inputs!$A:$A,Inputs!B:B,,0) -> 342.31 | C51: =_xlfn.XLOOKUP($A51,Inputs!$A:$A,Inputs!C:C,,0) -> 241.3 | D51: =_xlfn.XLOOKUP($A51,Inputs!$A:$A,Inputs!D:D,,0) -> 278.35 | E51: =_xlfn.XLOOKUP($A51,Inputs!$A:$A,Inputs!E:E,,0) -> 179.07 | F51: =_xlfn.XLOOKUP($A51,Inputs!$A:$A,Inputs!F:F,,0) -> 164.09 | G51: =_xlfn.XLOOKUP($A51,Inputs!$A:$A,Inputs!G:G,,0) -> 0 | H51: =_xlfn.XLOOKUP($A51,Inputs!$A:$A,Inputs!H:H,,0) -> 0 | I51: =_xlfn.XLOOKUP($A51,Inputs!$A:$A,Inputs!I:I,,0) -> 0 | J51: =_xlfn.XLOOKUP($A51,Inputs!$A:$A,Inputs!J:J,,0) -> 0 | K51: =_xlfn.XLOOKUP($A51,Inputs!$A:$A,Inputs!K:K,,0) -> 0 | L51: =_xlfn.XLOOKUP($A51,Inputs!$A:$A,Inputs!L:L,,0) -> 0 | M51: =_xlfn.XLOOKUP($A51,Inputs!$A:$A,Inputs!M:M,,0) -> 0
A52: Non-current Liabilities | B52: =_xlfn.XLOOKUP($A52,Inputs!$A:$A,Inputs!B:B,,0) -> 942.03 | C52: =_xlfn.XLOOKUP($A52,Inputs!$A:$A,Inputs!C:C,,0) -> 885.15 | D52: =_xlfn.XLOOKUP($A52,Inputs!$A:$A,Inputs!D:D,,0) -> 1263.61 | E52: =_xlfn.XLOOKUP($A52,Inputs!$A:$A,Inputs!E:E,,0) -> 1508.05 | F52: =_xlfn.XLOOKUP($A52,Inputs!$A:$A,Inputs!F:F,,0) -> 1460.13 | G52: =_xlfn.XLOOKUP($A52,Inputs!$A:$A,Inputs!G:G,,0) -> 0 | H52: =_xlfn.XLOOKUP($A52,Inputs!$A:$A,Inputs!H:H,,0) -> 0 | I52: =_xlfn.XLOOKUP($A52,Inputs!$A:$A,Inputs!I:I,,0) -> 0 | J52: =_xlfn.XLOOKUP($A52,Inputs!$A:$A,Inputs!J:J,,0) -> 0 | K52: =_xlfn.XLOOKUP($A52,Inputs!$A:$A,Inputs!K:K,,0) -> 0 | L52: =_xlfn.XLOOKUP($A52,Inputs!$A:$A,Inputs!L:L,,0) -> 0 | M52: =_xlfn.XLOOKUP($A52,Inputs!$A:$A,Inputs!M:M,,0) -> 0
A53: Long-Term Debt | B53: =_xlfn.XLOOKUP($A53,Inputs!$A:$A,Inputs!B:B,,0) -> 125.02 | C53: =_xlfn.XLOOKUP($A53,Inputs!$A:$A,Inputs!C:C,,0) -> 197.86 | D53: =_xlfn.XLOOKUP($A53,Inputs!$A:$A,Inputs!D:D,,0) -> 536.17 | E53: =_xlfn.XLOOKUP($A53,Inputs!$A:$A,Inputs!E:E,,0) -> 687.37 | F53: =_xlfn.XLOOKUP($A53,Inputs!$A:$A,Inputs!F:F,,0) -> 581.29 | G53: =_xlfn.XLOOKUP($A53,Inputs!$A:$A,Inputs!G:G,,0) -> N/A | H53: =_xlfn.XLOOKUP($A53,Inputs!$A:$A,Inputs!H:H,,0) -> N/A | I53: =_xlfn.XLOOKUP($A53,Inputs!$A:$A,Inputs!I:I,,0) -> N/A | J53: =_xlfn.XLOOKUP($A53,Inputs!$A:$A,Inputs!J:J,,0) -> N/A | K53: =_xlfn.XLOOKUP($A53,Inputs!$A:$A,Inputs!K:K,,0) -> N/A | L53: =_xlfn.XLOOKUP($A53,Inputs!$A:$A,Inputs!L:L,,0) -> N/A | M53: =_xlfn.XLOOKUP($A53,Inputs!$A:$A,Inputs!M:M,,0) -> N/A
A54: Long-Term Leases | B54: =_xlfn.XLOOKUP($A54,Inputs!$A:$A,Inputs!B:B,,0) -> 519.89 | C54: =_xlfn.XLOOKUP($A54,Inputs!$A:$A,Inputs!C:C,,0) -> 355.36 | D54: =_xlfn.XLOOKUP($A54,Inputs!$A:$A,Inputs!D:D,,0) -> 376.75 | E54: =_xlfn.XLOOKUP($A54,Inputs!$A:$A,Inputs!E:E,,0) -> 384.52 | F54: =_xlfn.XLOOKUP($A54,Inputs!$A:$A,Inputs!F:F,,0) -> 454.72 | G54: =_xlfn.XLOOKUP($A54,Inputs!$A:$A,Inputs!G:G,,0) -> N/A | H54: =_xlfn.XLOOKUP($A54,Inputs!$A:$A,Inputs!H:H,,0) -> N/A | I54: =_xlfn.XLOOKUP($A54,Inputs!$A:$A,Inputs!I:I,,0) -> N/A | J54: =_xlfn.XLOOKUP($A54,Inputs!$A:$A,Inputs!J:J,,0) -> N/A | K54: =_xlfn.XLOOKUP($A54,Inputs!$A:$A,Inputs!K:K,,0) -> N/A | L54: =_xlfn.XLOOKUP($A54,Inputs!$A:$A,Inputs!L:L,,0) -> N/A | M54: =_xlfn.XLOOKUP($A54,Inputs!$A:$A,Inputs!M:M,,0) -> N/A
A55: Other non-current liabilities | B55: =_xlfn.XLOOKUP($A55,Inputs!$A:$A,Inputs!B:B,,0) -> 297.12 | C55: =_xlfn.XLOOKUP($A55,Inputs!$A:$A,Inputs!C:C,,0) -> 331.93 | D55: =_xlfn.XLOOKUP($A55,Inputs!$A:$A,Inputs!D:D,,0) -> 350.69 | E55: =_xlfn.XLOOKUP($A55,Inputs!$A:$A,Inputs!E:E,,0) -> 436.16 | F55: =_xlfn.XLOOKUP($A55,Inputs!$A:$A,Inputs!F:F,,0) -> 424.12 | G55: =_xlfn.XLOOKUP($A55,Inputs!$A:$A,Inputs!G:G,,0) -> 0 | H55: =_xlfn.XLOOKUP($A55,Inputs!$A:$A,Inputs!H:H,,0) -> 0 | I55: =_xlfn.XLOOKUP($A55,Inputs!$A:$A,Inputs!I:I,,0) -> 0 | J55: =_xlfn.XLOOKUP($A55,Inputs!$A:$A,Inputs!J:J,,0) -> 0 | K55: =_xlfn.XLOOKUP($A55,Inputs!$A:$A,Inputs!K:K,,0) -> 0 | L55: =_xlfn.XLOOKUP($A55,Inputs!$A:$A,Inputs!L:L,,0) -> 0 | M55: =_xlfn.XLOOKUP($A55,Inputs!$A:$A,Inputs!M:M,,0) -> 0
A56: Total Liabilities | B56: =_xlfn.XLOOKUP($A56,Inputs!$A:$A,Inputs!B:B,,0) -> 2059 | C56: =_xlfn.XLOOKUP($A56,Inputs!$A:$A,Inputs!C:C,,0) -> 1813 | D56: =_xlfn.XLOOKUP($A56,Inputs!$A:$A,Inputs!D:D,,0) -> 2062 | E56: =_xlfn.XLOOKUP($A56,Inputs!$A:$A,Inputs!E:E,,0) -> 2162 | F56: =_xlfn.XLOOKUP($A56,Inputs!$A:$A,Inputs!F:F,,0) -> 2141 | G56: =_xlfn.XLOOKUP($A56,Inputs!$A:$A,Inputs!G:G,,0) -> 0 | H56: =_xlfn.XLOOKUP($A56,Inputs!$A:$A,Inputs!H:H,,0) -> 0 | I56: =_xlfn.XLOOKUP($A56,Inputs!$A:$A,Inputs!I:I,,0) -> 0 | J56: =_xlfn.XLOOKUP($A56,Inputs!$A:$A,Inputs!J:J,,0) -> 0 | K56: =_xlfn.XLOOKUP($A56,Inputs!$A:$A,Inputs!K:K,,0) -> 0 | L56: =_xlfn.XLOOKUP($A56,Inputs!$A:$A,Inputs!L:L,,0) -> 0 | M56: =_xlfn.XLOOKUP($A56,Inputs!$A:$A,Inputs!M:M,,0) -> 0
A58: Total Debt | B58: =B49+B53+B50+B54 -> 1099.57 | C58: =C49+C53+C50+C54 -> 978.77 | D58: =D49+D53+D50+D54 -> 1212.96 | E58: =E49+E53+E50+E54 -> 1314.77 | F58: =F49+F53+F50+F54 -> 1269.79 | G58: =G49+G53+G50+G54 -> #VALUE! | H58: =H49+H53+H50+H54 -> #VALUE! | I58: =I49+I53+I50+I54 -> #VALUE! | ... M58: =M49+M53+M50+M54 -> #VALUE!
A59: Debt/Assets | B59: =IFERROR(B58/B44,"-") -> 0.36008265 | C59: =IFERROR(C58/C44,"-") -> 0.37687036 | D59: =IFERROR(D58/D44,"-") -> 0.43413805 | E59: =IFERROR(E58/E44,"-") -> 0.4457603 | F59: =IFERROR(F58/F44,"-") -> 0.42916144 | G59: =IFERROR(G58/G44,"-") -> - | H59: =IFERROR(H58/H44,"-") -> - | I59: =IFERROR(I58/I44,"-") -> - | ... M59: =IFERROR(M58/M44,"-") -> -
A60: Net Debt | B60: =B58-B39 -> 772.57 | C60: =C58-C39 -> 706.77 | D60: =D58-D39 -> 689.96 | E60: =E58-E39 -> 926.77 | F60: =F58-F39 -> 1033.79 | G60: =G58-G39 -> #VALUE! | H60: =H58-H39 -> #VALUE! | I60: =I58-I39 -> #VALUE! | ... M60: =M58-M39 -> #VALUE!
A62: Minority Interest | B62: =_xlfn.XLOOKUP($A62,Inputs!$A:$A,Inputs!B:B,,0) -> 67 | C62: =_xlfn.XLOOKUP($A62,Inputs!$A:$A,Inputs!C:C,,0) -> 57 | D62: =_xlfn.XLOOKUP($A62,Inputs!$A:$A,Inputs!D:D,,0) -> 49 | E62: =_xlfn.XLOOKUP($A62,Inputs!$A:$A,Inputs!E:E,,0) -> 53 | F62: =_xlfn.XLOOKUP($A62,Inputs!$A:$A,Inputs!F:F,,0) -> 46 | G62: =_xlfn.XLOOKUP($A62,Inputs!$A:$A,Inputs!G:G,,0) -> N/A | H62: =_xlfn.XLOOKUP($A62,Inputs!$A:$A,Inputs!H:H,,0) -> N/A | I62: =_xlfn.XLOOKUP($A62,Inputs!$A:$A,Inputs!I:I,,0) -> N/A | J62: =_xlfn.XLOOKUP($A62,Inputs!$A:$A,Inputs!J:J,,0) -> N/A | K62: =_xlfn.XLOOKUP($A62,Inputs!$A:$A,Inputs!K:K,,0) -> N/A | L62: =_xlfn.XLOOKUP($A62,Inputs!$A:$A,Inputs!L:L,,0) -> N/A | M62: =_xlfn.XLOOKUP($A62,Inputs!$A:$A,Inputs!M:M,,0) -> N/A
A64: Shareholder's Equity | B64: =_xlfn.XLOOKUP($A64,Inputs!$A:$A,Inputs!B:B,,0) -> 927.66 | C64: =_xlfn.XLOOKUP($A64,Inputs!$A:$A,Inputs!C:C,,0) -> 727.1 | D64: =_xlfn.XLOOKUP($A64,Inputs!$A:$A,Inputs!D:D,,0) -> 682.95 | E64: =_xlfn.XLOOKUP($A64,Inputs!$A:$A,Inputs!E:E,,0) -> 734.5 | F64: =_xlfn.XLOOKUP($A64,Inputs!$A:$A,Inputs!F:F,,0) -> 771.77 | G64: =_xlfn.XLOOKUP($A64,Inputs!$A:$A,Inputs!G:G,,0) -> N/A | H64: =_xlfn.XLOOKUP($A64,Inputs!$A:$A,Inputs!H:H,,0) -> N/A | I64: =_xlfn.XLOOKUP($A64,Inputs!$A:$A,Inputs!I:I,,0) -> N/A | J64: =_xlfn.XLOOKUP($A64,Inputs!$A:$A,Inputs!J:J,,0) -> N/A | K64: =_xlfn.XLOOKUP($A64,Inputs!$A:$A,Inputs!K:K,,0) -> N/A | L64: =_xlfn.XLOOKUP($A64,Inputs!$A:$A,Inputs!L:L,,0) -> N/A | M64: =_xlfn.XLOOKUP($A64,Inputs!$A:$A,Inputs!M:M,,0) -> N/A
A66: Cash Flow
A67: Operating CF | B67: =_xlfn.XLOOKUP($A67,Inputs!$A:$A,Inputs!B:B,,0) -> 298 | C67: =_xlfn.XLOOKUP($A67,Inputs!$A:$A,Inputs!C:C,,0) -> 154 | D67: =_xlfn.XLOOKUP($A67,Inputs!$A:$A,Inputs!D:D,,0) -> 333 | E67: =_xlfn.XLOOKUP($A67,Inputs!$A:$A,Inputs!E:E,,0) -> 81 | F67: =_xlfn.XLOOKUP($A67,Inputs!$A:$A,Inputs!F:F,,0) -> 195 | G67: =_xlfn.XLOOKUP($A67,Inputs!$A:$A,Inputs!G:G,,0) -> 228 | H67: =_xlfn.XLOOKUP($A67,Inputs!$A:$A,Inputs!H:H,,0) -> 0 | I67: =_xlfn.XLOOKUP($A67,Inputs!$A:$A,Inputs!I:I,,0) -> 0 | J67: =_xlfn.XLOOKUP($A67,Inputs!$A:$A,Inputs!J:J,,0) -> 0 | K67: =_xlfn.XLOOKUP($A67,Inputs!$A:$A,Inputs!K:K,,0) -> 0 | L67: =_xlfn.XLOOKUP($A67,Inputs!$A:$A,Inputs!L:L,,0) -> 0 | M67: =_xlfn.XLOOKUP($A67,Inputs!$A:$A,Inputs!M:M,,0) -> 0
A68: Investing CF | B68: =_xlfn.XLOOKUP($A68,Inputs!$A:$A,Inputs!B:B,,0) -> 23.56 | C68: =_xlfn.XLOOKUP($A68,Inputs!$A:$A,Inputs!C:C,,0) -> -60.4 | D68: =_xlfn.XLOOKUP($A68,Inputs!$A:$A,Inputs!D:D,,0) -> -97 | E68: =_xlfn.XLOOKUP($A68,Inputs!$A:$A,Inputs!E:E,,0) -> 105.67 | F68: =_xlfn.XLOOKUP($A68,Inputs!$A:$A,Inputs!F:F,,0) -> 93.98 | G68: =_xlfn.XLOOKUP($A68,Inputs!$A:$A,Inputs!G:G,,0) -> -394.97 | H68: =_xlfn.XLOOKUP($A68,Inputs!$A:$A,Inputs!H:H,,0) -> 0 | I68: =_xlfn.XLOOKUP($A68,Inputs!$A:$A,Inputs!I:I,,0) -> 0 | J68: =_xlfn.XLOOKUP($A68,Inputs!$A:$A,Inputs!J:J,,0) -> 0 | K68: =_xlfn.XLOOKUP($A68,Inputs!$A:$A,Inputs!K:K,,0) -> 0 | L68: =_xlfn.XLOOKUP($A68,Inputs!$A:$A,Inputs!L:L,,0) -> 0 | M68: =_xlfn.XLOOKUP($A68,Inputs!$A:$A,Inputs!M:M,,0) -> 0
A69: Net Capex | B69: =_xlfn.XLOOKUP($A69,Inputs!$A:$A,Inputs!B:B,,0) -> -61.46 | C69: =_xlfn.XLOOKUP($A69,Inputs!$A:$A,Inputs!C:C,,0) -> -51.52 | D69: =_xlfn.XLOOKUP($A69,Inputs!$A:$A,Inputs!D:D,,0) -> -89.7 | E69: =_xlfn.XLOOKUP($A69,Inputs!$A:$A,Inputs!E:E,,0) -> -29.85 | F69: =_xlfn.XLOOKUP($A69,Inputs!$A:$A,Inputs!F:F,,0) -> -52.01 | G69: =_xlfn.XLOOKUP($A69,Inputs!$A:$A,Inputs!G:G,,0) -> -17.85 | H69: =_xlfn.XLOOKUP($A69,Inputs!$A:$A,Inputs!H:H,,0) -> N/A | I69: =_xlfn.XLOOKUP($A69,Inputs!$A:$A,Inputs!I:I,,0) -> N/A | J69: =_xlfn.XLOOKUP($A69,Inputs!$A:$A,Inputs!J:J,,0) -> N/A | K69: =_xlfn.XLOOKUP($A69,Inputs!$A:$A,Inputs!K:K,,0) -> N/A | L69: =_xlfn.XLOOKUP($A69,Inputs!$A:$A,Inputs!L:L,,0) -> N/A | M69: =_xlfn.XLOOKUP($A69,Inputs!$A:$A,Inputs!M:M,,0) -> N/A
A70: Investments & Acquisitions | B70: =_xlfn.XLOOKUP($A70,Inputs!$A:$A,Inputs!B:B,,0) -> 85.46 | C70: =_xlfn.XLOOKUP($A70,Inputs!$A:$A,Inputs!C:C,,0) -> -8.48 | D70: =_xlfn.XLOOKUP($A70,Inputs!$A:$A,Inputs!D:D,,0) -> -7.3 | E70: =_xlfn.XLOOKUP($A70,Inputs!$A:$A,Inputs!E:E,,0) -> 135.85 | F70: =_xlfn.XLOOKUP($A70,Inputs!$A:$A,Inputs!F:F,,0) -> 146.01 | G70: =_xlfn.XLOOKUP($A70,Inputs!$A:$A,Inputs!G:G,,0) -> -376.8 | H70: =_xlfn.XLOOKUP($A70,Inputs!$A:$A,Inputs!H:H,,0) -> N/A | I70: =_xlfn.XLOOKUP($A70,Inputs!$A:$A,Inputs!I:I,,0) -> N/A | J70: =_xlfn.XLOOKUP($A70,Inputs!$A:$A,Inputs!J:J,,0) -> N/A | K70: =_xlfn.XLOOKUP($A70,Inputs!$A:$A,Inputs!K:K,,0) -> N/A | L70: =_xlfn.XLOOKUP($A70,Inputs!$A:$A,Inputs!L:L,,0) -> N/A | M70: =_xlfn.XLOOKUP($A70,Inputs!$A:$A,Inputs!M:M,,0) -> N/A
A71: Financing CF | B71: =_xlfn.XLOOKUP($A71,Inputs!$A:$A,Inputs!B:B,,0) -> -270.88 | C71: =_xlfn.XLOOKUP($A71,Inputs!$A:$A,Inputs!C:C,,0) -> -312.88 | D71: =_xlfn.XLOOKUP($A71,Inputs!$A:$A,Inputs!D:D,,0) -> -75.83 | E71: =_xlfn.XLOOKUP($A71,Inputs!$A:$A,Inputs!E:E,,0) -> -55.99 | F71: =_xlfn.XLOOKUP($A71,Inputs!$A:$A,Inputs!F:F,,0) -> -299.4 | G71: =_xlfn.XLOOKUP($A71,Inputs!$A:$A,Inputs!G:G,,0) -> 155.68 | H71: =_xlfn.XLOOKUP($A71,Inputs!$A:$A,Inputs!H:H,,0) -> 0 | I71: =_xlfn.XLOOKUP($A71,Inputs!$A:$A,Inputs!I:I,,0) -> 0 | J71: =_xlfn.XLOOKUP($A71,Inputs!$A:$A,Inputs!J:J,,0) -> 0 | K71: =_xlfn.XLOOKUP($A71,Inputs!$A:$A,Inputs!K:K,,0) -> 0 | L71: =_xlfn.XLOOKUP($A71,Inputs!$A:$A,Inputs!L:L,,0) -> 0 | M71: =_xlfn.XLOOKUP($A71,Inputs!$A:$A,Inputs!M:M,,0) -> 0
A72: Dividends | B72: =_xlfn.XLOOKUP($A72,Inputs!$A:$A,Inputs!B:B,,0) -> -27.07 | C72: =_xlfn.XLOOKUP($A72,Inputs!$A:$A,Inputs!C:C,,0) -> -23.03 | D72: =_xlfn.XLOOKUP($A72,Inputs!$A:$A,Inputs!D:D,,0) -> 0.12 | E72: =_xlfn.XLOOKUP($A72,Inputs!$A:$A,Inputs!E:E,,0) -> 0 | F72: =_xlfn.XLOOKUP($A72,Inputs!$A:$A,Inputs!F:F,,0) -> 0 | G72: =_xlfn.XLOOKUP($A72,Inputs!$A:$A,Inputs!G:G,,0) -> 0 | H72: =_xlfn.XLOOKUP($A72,Inputs!$A:$A,Inputs!H:H,,0) -> N/A | I72: =_xlfn.XLOOKUP($A72,Inputs!$A:$A,Inputs!I:I,,0) -> N/A | J72: =_xlfn.XLOOKUP($A72,Inputs!$A:$A,Inputs!J:J,,0) -> N/A | K72: =_xlfn.XLOOKUP($A72,Inputs!$A:$A,Inputs!K:K,,0) -> N/A | L72: =_xlfn.XLOOKUP($A72,Inputs!$A:$A,Inputs!L:L,,0) -> N/A | M72: =_xlfn.XLOOKUP($A72,Inputs!$A:$A,Inputs!M:M,,0) -> N/A
A73: Share buyback | B73: =_xlfn.XLOOKUP($A73,Inputs!$A:$A,Inputs!B:B,,0) -> -4 | C73: =_xlfn.XLOOKUP($A73,Inputs!$A:$A,Inputs!C:C,,0) -> -15 | D73: =_xlfn.XLOOKUP($A73,Inputs!$A:$A,Inputs!D:D,,0) -> -767 | E73: =_xlfn.XLOOKUP($A73,Inputs!$A:$A,Inputs!E:E,,0) -> 1 | F73: =_xlfn.XLOOKUP($A73,Inputs!$A:$A,Inputs!F:F,,0) -> 0 | G73: =_xlfn.XLOOKUP($A73,Inputs!$A:$A,Inputs!G:G,,0) -> -3 | H73: =_xlfn.XLOOKUP($A73,Inputs!$A:$A,Inputs!H:H,,0) -> N/A | I73: =_xlfn.XLOOKUP($A73,Inputs!$A:$A,Inputs!I:I,,0) -> N/A | J73: =_xlfn.XLOOKUP($A73,Inputs!$A:$A,Inputs!J:J,,0) -> N/A | K73: =_xlfn.XLOOKUP($A73,Inputs!$A:$A,Inputs!K:K,,0) -> N/A | L73: =_xlfn.XLOOKUP($A73,Inputs!$A:$A,Inputs!L:L,,0) -> N/A | M73: =_xlfn.XLOOKUP($A73,Inputs!$A:$A,Inputs!M:M,,0) -> N/A
A74: FX | B74: =_xlfn.XLOOKUP($A74,Inputs!$A:$A,Inputs!B:B,,0) -> 0 | C74: =_xlfn.XLOOKUP($A74,Inputs!$A:$A,Inputs!C:C,,0) -> 0 | D74: =_xlfn.XLOOKUP($A74,Inputs!$A:$A,Inputs!D:D,,0) -> 0 | E74: =_xlfn.XLOOKUP($A74,Inputs!$A:$A,Inputs!E:E,,0) -> 0 | F74: =_xlfn.XLOOKUP($A74,Inputs!$A:$A,Inputs!F:F,,0) -> 0 | G74: =_xlfn.XLOOKUP($A74,Inputs!$A:$A,Inputs!G:G,,0) -> 0 | H74: =_xlfn.XLOOKUP($A74,Inputs!$A:$A,Inputs!H:H,,0) -> 0 | I74: =_xlfn.XLOOKUP($A74,Inputs!$A:$A,Inputs!I:I,,0) -> 0 | J74: =_xlfn.XLOOKUP($A74,Inputs!$A:$A,Inputs!J:J,,0) -> 0 | K74: =_xlfn.XLOOKUP($A74,Inputs!$A:$A,Inputs!K:K,,0) -> 0 | L74: =_xlfn.XLOOKUP($A74,Inputs!$A:$A,Inputs!L:L,,0) -> 0 | M74: =_xlfn.XLOOKUP($A74,Inputs!$A:$A,Inputs!M:M,,0) -> 0
A75: Changes in cash | B75: =_xlfn.XLOOKUP($A75,Inputs!$A:$A,Inputs!B:B,,0) -> 50.68 | C75: =_xlfn.XLOOKUP($A75,Inputs!$A:$A,Inputs!C:C,,0) -> -219.28 | D75: =_xlfn.XLOOKUP($A75,Inputs!$A:$A,Inputs!D:D,,0) -> 160.17 | E75: =_xlfn.XLOOKUP($A75,Inputs!$A:$A,Inputs!E:E,,0) -> 130.68 | F75: =_xlfn.XLOOKUP($A75,Inputs!$A:$A,Inputs!F:F,,0) -> -10.42 | G75: =_xlfn.XLOOKUP($A75,Inputs!$A:$A,Inputs!G:G,,0) -> -11.29 | H75: =_xlfn.XLOOKUP($A75,Inputs!$A:$A,Inputs!H:H,,0) -> 0 | I75: =_xlfn.XLOOKUP($A75,Inputs!$A:$A,Inputs!I:I,,0) -> 0 | J75: =_xlfn.XLOOKUP($A75,Inputs!$A:$A,Inputs!J:J,,0) -> 0 | K75: =_xlfn.XLOOKUP($A75,Inputs!$A:$A,Inputs!K:K,,0) -> 0 | L75: =_xlfn.XLOOKUP($A75,Inputs!$A:$A,Inputs!L:L,,0) -> 0 | M75: =_xlfn.XLOOKUP($A75,Inputs!$A:$A,Inputs!M:M,,0) -> 0
A77: Other Data
A78: Number of employees | B78: =_xlfn.XLOOKUP($A78,Inputs!$A:$A,Inputs!B:B,,0) -> #N/A | C78: =_xlfn.XLOOKUP($A78,Inputs!$A:$A,Inputs!C:C,,0) -> #N/A | D78: =_xlfn.XLOOKUP($A78,Inputs!$A:$A,Inputs!D:D,,0) -> #N/A | E78: =_xlfn.XLOOKUP($A78,Inputs!$A:$A,Inputs!E:E,,0) -> #N/A | F78: =_xlfn.XLOOKUP($A78,Inputs!$A:$A,Inputs!F:F,,0) -> #N/A | G78: =_xlfn.XLOOKUP($A78,Inputs!$A:$A,Inputs!G:G,,0) -> #N/A | H78: =_xlfn.XLOOKUP($A78,Inputs!$A:$A,Inputs!H:H,,0) -> #N/A | I78: =_xlfn.XLOOKUP($A78,Inputs!$A:$A,Inputs!I:I,,0) -> #N/A | J78: =_xlfn.XLOOKUP($A78,Inputs!$A:$A,Inputs!J:J,,0) -> #N/A | K78: =_xlfn.XLOOKUP($A78,Inputs!$A:$A,Inputs!K:K,,0) -> #N/A | L78: =_xlfn.XLOOKUP($A78,Inputs!$A:$A,Inputs!L:L,,0) -> #N/A | M78: =_xlfn.XLOOKUP($A78,Inputs!$A:$A,Inputs!M:M,,0) -> #N/A
A79: Shares Outstanding | B79: =_xlfn.XLOOKUP($A79,Inputs!$A:$A,Inputs!B:B,,0) -> #N/A | C79: =_xlfn.XLOOKUP($A79,Inputs!$A:$A,Inputs!C:C,,0) -> #N/A | D79: =_xlfn.XLOOKUP($A79,Inputs!$A:$A,Inputs!D:D,,0) -> #N/A | E79: =_xlfn.XLOOKUP($A79,Inputs!$A:$A,Inputs!E:E,,0) -> #N/A | F79: =_xlfn.XLOOKUP($A79,Inputs!$A:$A,Inputs!F:F,,0) -> #N/A | G79: =_xlfn.XLOOKUP($A79,Inputs!$A:$A,Inputs!G:G,,0) -> #N/A | H79: =_xlfn.XLOOKUP($A79,Inputs!$A:$A,Inputs!H:H,,0) -> #N/A | I79: =_xlfn.XLOOKUP($A79,Inputs!$A:$A,Inputs!I:I,,0) -> #N/A | J79: =_xlfn.XLOOKUP($A79,Inputs!$A:$A,Inputs!J:J,,0) -> #N/A | K79: =_xlfn.XLOOKUP($A79,Inputs!$A:$A,Inputs!K:K,,0) -> #N/A | L79: =_xlfn.XLOOKUP($A79,Inputs!$A:$A,Inputs!L:L,,0) -> #N/A | M79: =_xlfn.XLOOKUP($A79,Inputs!$A:$A,Inputs!M:M,,0) -> #N/A
A80: Float | B80: =_xlfn.XLOOKUP($A80,Inputs!$A:$A,Inputs!B:B,,0) -> 59.07M | C80: =_xlfn.XLOOKUP($A80,Inputs!$A:$A,Inputs!C:C,,0) -> Yahoo finance | D80: =_xlfn.XLOOKUP($A80,Inputs!$A:$A,Inputs!D:D,,0) -> 0 | E80: =_xlfn.XLOOKUP($A80,Inputs!$A:$A,Inputs!E:E,,0) -> 0 | F80: =_xlfn.XLOOKUP($A80,Inputs!$A:$A,Inputs!F:F,,0) -> 0 | G80: =_xlfn.XLOOKUP($A80,Inputs!$A:$A,Inputs!G:G,,0) -> 0 | H80: =_xlfn.XLOOKUP($A80,Inputs!$A:$A,Inputs!H:H,,0) -> 0 | I80: =_xlfn.XLOOKUP($A80,Inputs!$A:$A,Inputs!I:I,,0) -> 0 | J80: =_xlfn.XLOOKUP($A80,Inputs!$A:$A,Inputs!J:J,,0) -> 0 | K80: =_xlfn.XLOOKUP($A80,Inputs!$A:$A,Inputs!K:K,,0) -> 0 | L80: =_xlfn.XLOOKUP($A80,Inputs!$A:$A,Inputs!L:L,,0) -> 0 | M80: =_xlfn.XLOOKUP($A80,Inputs!$A:$A,Inputs!M:M,,0) -> 0
A81: Insiders Own | B81: =_xlfn.XLOOKUP($A81,Inputs!$A:$A,Inputs!B:B,,0) -> 0.752 | C81: =_xlfn.XLOOKUP($A81,Inputs!$A:$A,Inputs!C:C,,0) -> Yahoo finance | D81: =_xlfn.XLOOKUP($A81,Inputs!$A:$A,Inputs!D:D,,0) -> 0 | E81: =_xlfn.XLOOKUP($A81,Inputs!$A:$A,Inputs!E:E,,0) -> 0 | F81: =_xlfn.XLOOKUP($A81,Inputs!$A:$A,Inputs!F:F,,0) -> 0 | G81: =_xlfn.XLOOKUP($A81,Inputs!$A:$A,Inputs!G:G,,0) -> 0 | H81: =_xlfn.XLOOKUP($A81,Inputs!$A:$A,Inputs!H:H,,0) -> 0 | I81: =_xlfn.XLOOKUP($A81,Inputs!$A:$A,Inputs!I:I,,0) -> 0 | J81: =_xlfn.XLOOKUP($A81,Inputs!$A:$A,Inputs!J:J,,0) -> 0 | K81: =_xlfn.XLOOKUP($A81,Inputs!$A:$A,Inputs!K:K,,0) -> 0 | L81: =_xlfn.XLOOKUP($A81,Inputs!$A:$A,Inputs!L:L,,0) -> 0 | M81: =_xlfn.XLOOKUP($A81,Inputs!$A:$A,Inputs!M:M,,0) -> 0
A82: Fitch/ S&P Rating | B82: =_xlfn.XLOOKUP($A82,Inputs!$A:$A,Inputs!B:B,,0) -> 0 | C82: =_xlfn.XLOOKUP($A82,Inputs!$A:$A,Inputs!C:C,,0) -> 10-K | D82: =_xlfn.XLOOKUP($A82,Inputs!$A:$A,Inputs!D:D,,0) -> 0 | E82: =_xlfn.XLOOKUP($A82,Inputs!$A:$A,Inputs!E:E,,0) -> 0 | F82: =_xlfn.XLOOKUP($A82,Inputs!$A:$A,Inputs!F:F,,0) -> 0 | G82: =_xlfn.XLOOKUP($A82,Inputs!$A:$A,Inputs!G:G,,0) -> 0 | H82: =_xlfn.XLOOKUP($A82,Inputs!$A:$A,Inputs!H:H,,0) -> 0 | I82: =_xlfn.XLOOKUP($A82,Inputs!$A:$A,Inputs!I:I,,0) -> 0 | J82: =_xlfn.XLOOKUP($A82,Inputs!$A:$A,Inputs!J:J,,0) -> 0 | K82: =_xlfn.XLOOKUP($A82,Inputs!$A:$A,Inputs!K:K,,0) -> 0 | L82: =_xlfn.XLOOKUP($A82,Inputs!$A:$A,Inputs!L:L,,0) -> 0 | M82: =_xlfn.XLOOKUP($A82,Inputs!$A:$A,Inputs!M:M,,0) -> 0
A83: Dividend Yield | B83: =_xlfn.XLOOKUP($A83,Inputs!$A:$A,Inputs!B:B,,0) -> #N/A | C83: =_xlfn.XLOOKUP($A83,Inputs!$A:$A,Inputs!C:C,,0) -> #N/A | D83: =_xlfn.XLOOKUP($A83,Inputs!$A:$A,Inputs!D:D,,0) -> #N/A | E83: =_xlfn.XLOOKUP($A83,Inputs!$A:$A,Inputs!E:E,,0) -> #N/A | F83: =_xlfn.XLOOKUP($A83,Inputs!$A:$A,Inputs!F:F,,0) -> #N/A | G83: =_xlfn.XLOOKUP($A83,Inputs!$A:$A,Inputs!G:G,,0) -> #N/A | H83: =_xlfn.XLOOKUP($A83,Inputs!$A:$A,Inputs!H:H,,0) -> #N/A | I83: =_xlfn.XLOOKUP($A83,Inputs!$A:$A,Inputs!I:I,,0) -> #N/A | J83: =_xlfn.XLOOKUP($A83,Inputs!$A:$A,Inputs!J:J,,0) -> #N/A | K83: =_xlfn.XLOOKUP($A83,Inputs!$A:$A,Inputs!K:K,,0) -> #N/A | L83: =_xlfn.XLOOKUP($A83,Inputs!$A:$A,Inputs!L:L,,0) -> #N/A | M83: =_xlfn.XLOOKUP($A83,Inputs!$A:$A,Inputs!M:M,,0) -> #N/A
A84: Daily Volume in Millions of USD | B84: =_xlfn.XLOOKUP($A84,Inputs!$A:$A,Inputs!B:B,,0) -> 0 | C84: =_xlfn.XLOOKUP($A84,Inputs!$A:$A,Inputs!C:C,,0) -> Yahoo Finance | D84: =_xlfn.XLOOKUP($A84,Inputs!$A:$A,Inputs!D:D,,0) -> 0 | E84: =_xlfn.XLOOKUP($A84,Inputs!$A:$A,Inputs!E:E,,0) -> 0 | F84: =_xlfn.XLOOKUP($A84,Inputs!$A:$A,Inputs!F:F,,0) -> 0 | G84: =_xlfn.XLOOKUP($A84,Inputs!$A:$A,Inputs!G:G,,0) -> 0 | H84: =_xlfn.XLOOKUP($A84,Inputs!$A:$A,Inputs!H:H,,0) -> 0 | I84: =_xlfn.XLOOKUP($A84,Inputs!$A:$A,Inputs!I:I,,0) -> 0 | J84: =_xlfn.XLOOKUP($A84,Inputs!$A:$A,Inputs!J:J,,0) -> 0 | K84: =_xlfn.XLOOKUP($A84,Inputs!$A:$A,Inputs!K:K,,0) -> 0 | L84: =_xlfn.XLOOKUP($A84,Inputs!$A:$A,Inputs!L:L,,0) -> 0 | M84: =_xlfn.XLOOKUP($A84,Inputs!$A:$A,Inputs!M:M,,0) -> 0
B86: 2020 | C86: 2021 | D86: 2022
A87: Short % of Float | B87: 0 | C87: 0 | D87: 0
A88: EPS | B88: 0 | C88: 0 | D88: 0
A90: Corporate Bonds 3, 5 Y 10 | B90: Average Price | C90: Moody's | D90: YTM | E90: DIVISA
B91: =VLOOKUP($A91,Inputs!$A$5:$M$98,MATCH(B$4,Inputs!$B$5:$M$5,0)+1,FALSE) -> #N/A | C91: =VLOOKUP($A91,Inputs!$A$5:$M$98,MATCH(C$4,Inputs!$B$5:$M$5,0)+1,FALSE) -> #N/A | D91: =VLOOKUP($A91,Inputs!$A$5:$M$98,MATCH(D$4,Inputs!$B$5:$M$5,0)+1,FALSE) -> #N/A | E91: =VLOOKUP($A91,Inputs!$A$5:$M$98,MATCH(E$4,Inputs!$B$5:$M$5,0)+1,FALSE) -> #N/A

Sheet Sector Impact
E2: Sector | F2: Sub-Industry | H2: Low | K2: Sector | L2: Environment | Q2: Social
E3: Communication Services | F3: Interactive Home Entertainment | H3: Medium | L3: CO2 | M3: Water | N3: Energy | O3: Waste | P3: Degradation | Q3: Turnover | R3: Compensation | S3: Reputation | T3: Discrimination | U3: Security | V3: Damage | W3: Pension | X3: Supply | Y3: Community | Z3: Public | AA3: Litigation
E4: Communication Services | F4: Interactive Media & Services | H4: High | K4: Communication Services | L4: Low | M4: Low | N4: Medium | O4: Low | P4: Low | Q4: Medium | R4: Medium | S4: Low | T4: Low | U4: High | V4: Low | W4: Low | X4: Low | Y4: Low | Z4: Low | AA4: Medium
B5: Environmental | E5: Communication Services | F5: Integrated Telecommunication Services | H5: Very High | K5: Consumer Discretionary | L5: Low | M5: Low | N5: Medium | O5: Medium | P5: Low | Q5: Medium | R5: Medium | S5: Low | T5: Low | U5: Medium | V5: Medium | W5: Medium | X5: High | Y5: Low | Z5: High | AA5: Low
B6: Direct CO2 emissions | E6: Communication Services | F6: Cable & Satellite | K6: Consumer Staples | L6: High | M6: Very High | N6: High | O6: High | P6: High | Q6: Medium | R6: High | S6: High | T6: Low | U6: Medium | V6: Medium | W6: Low | X6: High | Y6: Low | Z6: Very High | AA6: Low
B7: Total Water Use | E7: Communication Services | F7: Broadcasting | K7: Energy | L7: Very High | M7: Very High | N7: Medium | O7: Very High | P7: High | Q7: High | R7: Medium | S7: Medium | T7: Medium | U7: Medium | V7: High | W7: Medium | X7: Medium | Y7: High | Z7: High | AA7: Low
K8: Renewable Energy | L8: Low | M8: Low | N8: Low | O8: Medium | P8: Medium | Q8: Low | R8: Medium | S8: Medium | T8: High | U8: Medium | V8: Low | W8: Low | X8: Medium | Y8: Medium | Z8: High | AA8: Low
B9: Total Energy Consumption | E9: Communication Services | F9: Movies & Entertainment | K9: Financials | L9: Low | M9: Low | N9: Low | O9: Low | P9: Low | Q9: Low | R9: Low | S9: Medium | T9: High | U9: Medium | V9: Low | W9: Low | X9: Low | Y9: Low | Z9: Medium | AA9: Low
K10: Forestry | L10: Low | M10: Medium | N10: Low | O10: Medium | P10: High | Q10: Low | R10: Low | S10: Low | T10: Low | U10: Low | V10: Low | W10: Low | X10: Low | Y10: Medium | Z10: Low | AA10: Low
B11: Waste Management | E11: Communication Services | F11: Advertising | K11: Health Care | L11: Low | M11: Medium | N11: Low | O11: Low | P11: Low | Q11: Low | R11: Low | S11: Medium | T11: Low | U11: High | V11: Low | W11: Low | X11: Low | Y11: Low | Z11: Low | AA11: Low
B12: Land Degradation/Deforestation/Biodiversity loss/Animal sufering/... | E12: Communication Services | F12: Alternative Carriers | K12: Industrials | L12: Very High | M12: Very High | N12: Very High | O12: High | P12: High | Q12: Low | R12: Medium | S12: High | T12: Very High | U12: Medium | V12: Very High | W12: Medium | X12: Very High | Y12: Very High | Z12: Very High | AA12: High
B13: Social | E13: Communication Services | F13: Publishing | K13: Information Technology | L13: Medium | M13: Low | N13: High | O13: Low | P13: Low | Q13: Low | R13: Low | S13: Low | T13: Low | U13: High | V13: Low | W13: Low | X13: Low | Y13: Low | Z13: Medium | AA13: Very High
B14: Employee turnover | E14: Communication Services | F14: Wireless Telecommunication Services | K14: Materials | L14: Very High | M14: Very High | N14: Very High | O14: Very High | P14: High | Q14: High | R14: High | S14: Medium | T14: High | U14: Low | V14: Very High | W14: Medium | X14: Medium | Y14: Very High | Z14: High | AA14: Medium
B15: Salaries and compensation | E15: Consumer Discretionary | F15: Automotive Retail | K15: Real Estate | L15: Low | M15: Low | N15: Medium | O15: Low | P15: Low | Q15: Medium | R15: Low | S15: Low | T15: Low | U15: High | V15: Low | W15: Medium | X15: Low | Y15: Medium | Z15: Low | AA15: Low
B16: Reputational issues | E16: Consumer Discretionary | F16: Internet & Direct Marketing Retail | K16: Utilities | L16: Very High | M16: High | N16: High | O16: Medium | P16: High | Q16: Low | R16: Medium | S16: Medium | T16: Low | U16: Medium | V16: Medium | W16: Medium | X16: Medium | Y16: Low | Z16: Medium | AA16: Low
B17: Discrimination issues | E17: Consumer Discretionary | F17: Auto Parts & Equipment
B18: Job security | E18: Consumer Discretionary | F18: Specialty Stores
B19: Health injuries | E19: Consumer Discretionary | F19: Computer & Electronics Retail | L19: Communication Services | M19: Consumer Discretionary | N19: Consumer Staples | O19: Energy | P19: Financials | Q19: Health Care | R19: Industrials | S19: Information Technology | T19: Materials | U19: Real Estate | V19: Utilities
B20: PXP? | E20: Consumer Discretionary | F20: Hotels, Resorts & Cruise Lines | L20: Interactive Home Entertainment | M20: Automotive Retail | N20: Tobacco | O20: Oil & Gas Exploration & Production | P20: Life & Health Insurance | Q20: Health Care Equipment | R20: Industrial Conglomerates | S20: IT Consulting & Other Services | T20: Industrial Gases | U20: Office REITs | V20: Independent Power Producers & Energy Traders
B21: Supply chain | E21: Consumer Discretionary | F21: Restaurants | L21: Interactive Media & Services | M21: Internet & Direct Marketing Retail | N21: Agricultural Products | O21: Oil & Gas Equipment & Services | P21: Property & Casualty Insurance | Q21: Pharmaceuticals | R21: Airlines | S21: Application Software | T21: Specialty Chemicals | U21: Specialized REITs | V21: Electric Utilities
B22: Community involvement | E22: Consumer Discretionary | F22: Homebuilding | L22: Integrated Telecommunication Services | M22: Auto Parts & Equipment | N22: Distillers & Vintners | O22: Integrated Oil & Gas | P22: Consumer Finance | Q22: Health Care Supplies | R22: Building Products | S22: Semiconductors | T22: Paper Packaging | U22: Residential REITs | V22: Multi-Utilities
B23: Public Sector | E23: Consumer Discretionary | F23: General Merchandise Stores | L23: Cable & Satellite | M23: Specialty Stores | N23: Packaged Foods & Meats | O23: Oil & Gas Refining & Marketing | P23: Asset Management & Custody Banks | Q23: Health Care Distributors | R23: Electrical Components & Equipment | S23: Internet Services & Infrastructure | T23: Metal & Glass Containers | U23: Real Estate Services | V23: Water Utilities
B24: Litigation | E24: Consumer Discretionary | F24: Automobile Manufacturers | L24: Broadcasting | M24: Computer & Electronics Retail | N24: Household Products | O24: Oil & Gas Storage & Transportation | P24: Insurance Brokers | Q24: Biotechnology | R24: Aerospace & Defense | S24: Electronic Components | T24: Fertilizers & Agricultural Chemicals | U24: Industrial REITs | V24: Gas Utilities
E25: Consumer Discretionary | F25: Apparel Retail | L25: Movies & Entertainment | M25: Hotels, Resorts & Cruise Lines | N25: Soft Drinks | P25: Multi-line Insurance | Q25: Managed Health Care | R25: Air Freight & Logistics | S25: Technology Hardware, Storage & Peripherals | T25: Commodity Chemicals | U25: Retail REITs
E26: Consumer Discretionary | F26: Consumer Electronics | L26: Advertising | M26: Restaurants | N26: Hypermarkets & Super Centers | P26: Diversified Banks | Q26: Life Sciences Tools & Services | R26: Construction Machinery & Heavy Trucks | S26: Semiconductor Equipment | T26: Diversified Chemicals | U26: Health Care REITs
E27: Consumer Discretionary | F27: Apparel, Accessories & Luxury Goods | L27: Alternative Carriers | M27: Homebuilding | N27: Personal Products | P27: Multi-Sector Holdings | Q27: Health Care Technology | R27: Diversified Support Services | S27: Communications Equipment | T27: Copper | U27: Hotel & Resort REITs
E28: Consumer Discretionary | F28: Leisure Products | L28: Publishing | M28: General Merchandise Stores | N28: Food Retail | P28: Financial Exchanges & Data | Q28: Health Care Services | R28: Railroads | S28: Data Processing & Outsourced Services | T28: Construction Materials
E29: Consumer Discretionary | F29: Home Improvement Retail | L29: Wireless Telecommunication Services | M29: Automobile Manufacturers | N29: Brewers | P29: Investment Banking & Brokerage | Q29: Health Care Facilities | R29: Industrial Machinery | S29: Technology Distributors | T29: Gold
E30: Consumer Discretionary | F30: Casinos & Gaming | M30: Apparel Retail | N30: Food Distributors | P30: Regional Banks | R30: Agricultural & Farm Machinery | S30: Electronic Equipment & Instruments | T30: Steel
E31: Consumer Discretionary | F31: Home Furnishings | M31: Consumer Electronics | N31: Drug Retail | P31: Reinsurance | R31: Research & Consulting Services | S31: Systems Software
E32: Consumer Discretionary | F32: Distributors | M32: Apparel, Accessories & Luxury Goods | P32: Thrifts & Mortgage Finance | R32: Construction & Engineering | S32: Electronic Manufacturing Services
E33: Consumer Discretionary | F33: Housewares & Specialties | M33: Leisure Products | R33: Trucking
E34: Consumer Discretionary | F34: Household Appliances | M34: Home Improvement Retail | R34: Environmental & Facilities Services
E35: Consumer Staples | F35: Tobacco | M35: Casinos & Gaming | R35: Human Resource & Employment Services
E36: Consumer Staples | F36: Agricultural Products | M36: Home Furnishings | R36: Trading Companies & Distributors
E37: Consumer Staples | F37: Distillers & Vintners | M37: Distributors
E38: Consumer Staples | F38: Packaged Foods & Meats | M38: Housewares & Specialties
E39: Consumer Staples | F39: Household Products | M39: Household Appliances
E40: Consumer Staples | F40: Soft Drinks
E41: Consumer Staples | F41: Hypermarkets & Super Centers
E42: Consumer Staples | F42: Personal Products
E43: Consumer Staples | F43: Food Retail
E44: Consumer Staples | F44: Brewers
E45: Consumer Staples | F45: Food Distributors
E46: Consumer Staples | F46: Drug Retail
E47: Energy | F47: Oil & Gas Exploration & Production
E48: Energy | F48: Oil & Gas Equipment & Services
E49: Energy | F49: Integrated Oil & Gas
E50: Energy | F50: Oil & Gas Refining & Marketing
E51: Energy | F51: Oil & Gas Storage & Transportation
... E128: Utilities | F128: Gas Utilities

Sheet Inputs
G2: Figures in Millions of USD
G3: Company | H3: #VALUE!
D4: Report in millions
A5: RESULTS | B5: 2023 | C5: =B5-1 -> 2022 | D5: =C5-1 -> 2021 | E5: =D5-1 -> 2020 | F5: =E5-1 -> 2019 | G5: =F5-1 -> 2018 | H5: =G5-1 -> 2017 | I5: =H5-1 -> 2016 | J5: =I5-1 -> 2015 | ... M5: =L5-1 -> 2012 | Q5: Hoja | R5: Nombre campo Bloomberg | T5: Cambio de signo | Z5: 2016 | AA5: 2015 | AB5: 2014 | AC5: 2013 | AD5: 2012 | AE5: 2011 | AF5: 2010 | AG5: 2009
A6: Net Sales | B6: 2060 | C6: 1573 | D6: 1529 | E6: 1158 | F6: 1479 | G6: 1396 | H6: N/A | I6: N/A | J6: N/A | K6: N/A | L6: N/A | M6: N/A | N6: Income Statement | O6: Sales | Q6: Ingreso | R6: Ingreso | Z6: 38537 | AA6: 47011 | AB6: 55184 | AC6: 55656 | AD6: 65875 | AE6: 60138 | AF6: 42588 | AG6: 32396
A7: Gross Profit | B7: 1323.93 | C7: 977.64 | D7: 942.36 | E7: 611.18 | F7: 855.62 | G7: 858.76 | H7: N/A | I7: N/A | J7: N/A | K7: N/A | L7: N/A | M7: N/A | N7: Income Statement | O7: =+A7 -> Gross Profit | Q7: Ingreso | R7: + Coste de bienes y servicios | Z7: =Z6-28044 -> 10493 | AA7: =AA6-33546 -> 13465 | AB7: =AB6-40718 -> 14466 | AC7: =AC6-40727 -> 14929 | AD7: =+AD6-47055 -> 18820 | AE7: =+AE6-43578 -> 16560 | AF7: =+AF6-30367 -> 12221 | AG7: =+AG6-23886 -> 8510
A8: Operating Income | B8: 240.67 | C8: 171.65 | D8: 141.97 | E8: 24.09 | F8: 121.16 | G8: 125.63 | H8: N/A | I8: N/A | J8: N/A | K8: N/A | L8: N/A | M8: N/A | N8: Income Statement | O8: Operating Income | Q8: Ingreso | R8: + Ventas, generales y admin | Z8: =Z7-4383 -> 6110 | AA8: =AA7-4951 -> 8514 | AB8: =AB7-6529 -> 7937 | AC8: =AC7-5547 -> 9382 | AD8: =AD7-5919-2466-797-580-485 -> 8573 | AE8: =+AE7-5203-2297-826-1081 -> 7153 | AF8: =+AF7-4248-1905-914-1191 -> 3963 | AG8: =+AG7-3645-1421-1045-1822 -> 577
A9: Other Expenses (Revenues) | B9: -39.6 | C9: -51.95 | D9: -260.31 | E9: -69.81 | F9: -40.9 | G9: -23.82 | H9: N/A | I9: N/A | J9: N/A | K9: N/A | L9: N/A | M9: N/A | N9: Income Statement | O9: investment income+other income expense+income loss+minority interest+non controlling interest+share onf net profit+gain8losses) on equity investments+share of result from associates nd joint ventures+non operating profit+ | Q9: Ingreso | R9: + Investigación y desarrollo | S9: + Coste de financiación de beneficio | T9: + Otro gasto operativo | U9: - Beneficio (pérdida) de filiales | V9: - Minoritarios | Z9: =1853+596+595+1904+6+8 -> 4962 | AA9: =2119+587+2023+11 -> 4740 | AB9: =2380+624+1619-8+16 -> 4631 | AC9: =2046+727+981+6+14 -> 3774 | AD9: =-14+41 -> 27 | AE9: 53 | AF9: =58+24 -> 82 | AG9: =12-68 -> -56
A10: Net Financial Cost | B10: -33.5 | C10: -27.74 | D10: -6.21 | E10: 5.09 | F10: -6.9 | G10: -22.58 | H10: N/A | I10: N/A | J10: N/A | K10: N/A | L10: N/A | M10: N/A | N10: Income Statement | O10: interest expense+financial income and expenses+other financial expense-income+interest and other net+ | Q10: Ingreso | R10: - Ingreso (pérdida) no operacional | Z10: =505+518 -> 1023 | AA10: =507-161 -> 346 | AB10: =484-322 -> 162 | AC10: =465+35 -> 500 | AD10: =467-130 -> 337 | AE10: =396+32 -> 428 | AF10: =343-130 -> 213 | AG10: =389-381 -> 8
A11: Taxes | B11: -36.15 | C11: -37.72 | D11: -36.32 | E11: -17.1 | F11: -49.02 | G11: -34.7 | H11: N/A | I11: N/A | J11: N/A | K11: N/A | L11: N/A | M11: N/A | N11: Income Statement | O11: Taxes | Q11: Ingreso | R11: - Gasto de impuesto a la renta (Beneficio) | Z11: 192 | AA11: 916 | AB11: 692 | AC11: 1319 | AD11: =2528 -> 2528 | AE11: =1720 -> 1720 | AF11: =968 -> 968 | AG11: =-270 -> -270
A12: Net Income | B12: 131.42 | C12: 54.24 | D12: -160.87 | E12: -57.73 | F12: 24.34 | G12: 44.53 | H12: N/A | I12: N/A | J12: N/A | K12: N/A | L12: N/A | M12: N/A | N12: Income Statement | O12: Net Income | Q12: Flujo de caja | R12: + Ingreso neto | Z12: -67 | AA12: 2512 | AB12: 2452 | AC12: 3789 | AD12: 5681 | AE12: =4928+24 -> 4952 | AF12: 2700 | AG12: 895
B13: =SUM(B8:B11) -> 131.42 | C13: =SUM(C8:C11) -> 54.24 | D13: =SUM(D8:D11) -> -160.87 | E13: =SUM(E8:E11) -> -57.73 | F13: =SUM(F8:F11) -> 24.34 | G13: =SUM(G8:G11) -> 44.53 | H13: =SUM(H8:H11) -> 0 | I13: =SUM(I8:I11) -> 0 | ... M13: =SUM(M8:M11) -> 0 | Z13: =Z8-Z10-Z9-Z11 -> -67 | AA13: =AA8-AA10-AA9-AA11 -> 2512 | AB13: =AB8-AB10-AB9-AB11 -> 2452 | AC13: =AC8-AC10-AC9-AC11 -> 3789 | AD13: =AD8-AD10-AD9-AD11 -> 5681 | AE13: =AE8-AE10-AE9-AE11 -> 4952 | AF13: =AF8-AF10-AF9-AF11 -> 2700 | AG13: =AG8-AG10-AG9-AG11 -> 895
A14: FINANCIAL POSITION | B14: =B12-B13 -> 0 | C14: =C12-C13 -> 0 | D14: =D12-D13 -> 0 | E14: =E12-E13 -> 0 | F14: =F12-F13 -> 0 | G14: =G12-G13 -> 0 | H14: N/A | I14: N/A | J14: N/A | K14: N/A | L14: N/A | M14: N/A | Z14: =Z12-Z13 -> 0 | AA14: =AA12-AA13 -> 0 | AB14: =AB12-AB13 -> 0 | AC14: =AC12-AC13 -> 0 | AD14: =AD12-AD13 -> 0 | AE14: =AE12-AE13 -> 0 | AF14: =AF12-AF13 -> 0 | AG14: =AG12-AG13 -> 0
A16: Weighted Average Shares (Basic NI) | B16: 247.02 | C16: 237.55 | D16: 203.5 | E16: 242.34 | F16: 242.34 | G16: 242.34 | H16: N/A | I16: N/A | J16: N/A | K16: N/A | L16: N/A | M16: N/A
A17: Weighted Average Shares (Diluted NI) | B17: 252.36 | C17: 240.65 | D17: 203.5 | E17: 242.34 | F17: 242.34 | G17: 242.34 | H17: N/A | I17: N/A | J17: N/A | K17: N/A | L17: N/A | M17: N/A
A19: Net gains (losses) from ForEx | B19: -17 | C19: 11 | D19: 48 | E19: -42 | F19: 12 | G19: 0 | H19: N/A | I19: N/A | J19: N/A | K19: N/A | L19: N/A | M19: N/A
A20: Total Comprehensive Income | B20: 108.77 | C20: 87.34 | D20: -120.77 | E20: -97.47 | F20: 36.78 | G20: 42.25 | H20: N/A | I20: N/A | J20: N/A | K20: N/A | L20: N/A | M20: N/A
A22: Changes Net Working Capital | B22: =B23-C23 -> -199.01 | C22: =C23-D23 -> -76.48 | D22: =D23-E23 -> -218.88 | E22: =E23-F23 -> -9.17 | F22: N/A | G22: N/A | H22: N/A | I22: N/A | J22: N/A | K22: N/A | L22: N/A | M22: N/A | N22: cash flows | O22: NWC | Q22: Flujo de caja
A23: Net Working Capital | B23: =B27-B42-B28 -> -22.94 | C23: =C27-C42-C28 -> 176.07 | D23: =D27-D42-D28 -> 252.55 | E23: =E27-E42-E28 -> 471.43 | F23: =F27-F42-F28 -> 480.6 | G23: N/A | H23: N/A | I23: N/A | J23: N/A | K23: N/A | L23: N/A | M23: N/A
A24: 2625 | B24: 2625 | C24: 2625 | D24: 2625 | E24: 2625 | F24: 2625 | G24: 2625 | H24: 2625 | I24: 2625 | J24: 2625 | K24: 2625 | L24: 2625 | M24: 2625 | N24: 2625 | Q24: Flujo de caja | R24: + Dividendos pagados | T24: Cambiar signo | Z24: 1799 | AA24: 1757 | AB24: 1620 | AC24: 1111 | AD24: 1617 | AE24: 1159 | AF24: 1084 | AG24: 1029
A25: BALANCE SHEET | B25: 2625 | C25: 2625 | D25: 2625 | E25: 2625 | F25: 2625 | G25: 2625 | H25: 2625 | I25: 2625 | J25: 2625 | K25: 2625 | L25: 2625 | M25: 2625 | N25: 2625 | Q25: Flujo de caja | R25: + Aumento en capital | S25: + Baja en capital | T25: Cambiar signo y hacer suma | Z25: 23 | AA25: =-33+2025 -> 1992 | AB25: 3817 | AC25: 1776 | AD25: -244 | AE25: -312 | AF25: -449 | AG25: -110
A26: ASSETS | N26: 1922 | O26: 2625 | S26: {=Inputs!B65P26} -> #NAME?
A27: Current | B27: 1421.03 | C27: 1375.92 | D27: 1573.94 | E27: 1513.38 | F27: 1397.47
A28: Cash & Eq. | B28: 327 | C28: 272 | D28: 523 | E28: 388 | F28: 236 | G28: N/A | H28: N/A | I28: N/A | J28: N/A | K28: N/A | L28: N/A | M28: N/A | N28: Balance Sheet | O28: Cash & Eq.
A29: Accounts Receivable | B29: 273 | C29: 197 | D29: 190 | E29: 180 | F29: 206 | G29: N/A | H29: N/A | I29: N/A | J29: N/A | K29: N/A | L29: N/A | M29: N/A | N29: Balance Sheet | O29: Accounts Receivable
A30: Inventory | B30: 577 | C30: 440 | D30: 385 | E30: 393 | F30: 353 | G30: N/A | H30: N/A | I30: N/A | J30: N/A | K30: N/A | L30: N/A | M30: N/A | N30: Balance Sheet | O30: Inventory | Q30: Balance | R30: + Efectivo, equivalentes y STI | Z30: 7168 | AA30: 6460 | AB30: 7341 | AC30: 6081 | AD30: 5490 | AE30: 3057 | AF30: 3592 | AG30: 4867
A31: Other Current Assets | B31: =B27-SUM(B28:B30) -> 244.03 | C31: =C27-SUM(C28:C30) -> 466.92 | D31: =D27-SUM(D28:D30) -> 475.94 | E31: =E27-SUM(E28:E30) -> 552.38 | F31: =F27-SUM(F28:F30) -> 602.47 | G31: =G27-SUM(G28:G30) -> 0 | H31: =H27-SUM(H28:H30) -> 0 | I31: =I27-SUM(I28:I30) -> 0 | ... M31: =M27-SUM(M28:M30) -> 0 | N31: Balance Sheet | O31: Inventory | Q31: Balance | R31: + Cuentas y notas por cobrar | S31: + Activos derivados y de cobertura | T31: + Inversiones y cuentas por cobrar a LP | Z31: =5981+8522+1029+13556 -> 29088 | AA31: =6695+8991+1170+13651 -> 30507 | AB31: =7737+9027+1364+14644 -> 32772 | AC31: 33499 | AD31: 33911 | AE31: 31031 | AF31: 28849 | AG31: 27162
A32: Non-current | B32: =B38-B27 -> 1632.63 | C32: =C38-C27 -> 1221.18 | D32: =D38-D27 -> 1220.01 | E32: =E38-E27 -> 1436.12 | F32: =F38-F27 -> 1561.3 | G32: =G38-G27 -> 0 | H32: =H38-H27 -> 0 | I32: =I38-I27 -> 0 | ... M32: =M38-M27 -> 0
A33: Property, Plant and Equipment | B33: 765.41 | C33: 536.87 | D33: 547.88 | E33: 727.62 | F33: 823.91 | G33: N/A | H33: N/A | I33: N/A | J33: N/A | K33: N/A | L33: N/A | M33: N/A | Q33: Balance | R33: + Inventarios | Z33: 8614 | AA33: 9700 | AB33: 12205 | AC33: 12625 | AD33: 15547 | AE33: 14544 | AF33: 9587 | AG33: 6360
A34: Operating leases | B34: 589.27 | C34: 401.87 | D34: 421.15 | E34: 429.47 | F34: 514.92 | G34: N/A | H34: N/A | I34: N/A | J34: N/A | K34: N/A | L34: N/A | M34: N/A
A35: Equity Method Investments | B35: 20.71 | C35: 24.24 | D35: 25.52 | E35: 46.99 | F35: 51.86 | G35: N/A | H35: N/A | I35: N/A | J35: N/A | K35: N/A | L35: N/A | M35: N/A
A36: Other Non-Current Assets | B36: =B32-SUM(B33:B35) -> 257.24 | C36: =C32-SUM(C33:C35) -> 258.2 | D36: =D32-SUM(D33:D35) -> 225.46 | E36: =E32-SUM(E33:E35) -> 232.04 | F36: =F32-SUM(F33:F35) -> 170.61 | G36: =G32-SUM(G33:G35) -> 0 | H36: =H32-SUM(H33:H35) -> 0 | I36: =I32-SUM(I33:I35) -> 0 | ... M36: =M32-SUM(M33:M35) -> 0 | N36: Balance Sheet | O36: Property, Plant and Equipment
A37: Other Assets | B37: =B31+B36 -> 501.27 | C37: =C31+C36 -> 725.12 | D37: =D31+D36 -> 701.4 | E37: =E31+E36 -> 784.42 | F37: =F31+F36 -> 773.08 | G37: =G31+G36 -> 0 | H37: =H31+H36 -> 0 | I37: =I31+I36 -> 0 | ... M37: =M31+M36 -> 0 | N37: Balance Sheet
A38: Total Assets | B38: 3053.66 | C38: 2597.1 | D38: 2793.95 | E38: 2949.5 | F38: 2958.77 | N38: Balance Sheet | O38: Total Assets | Q38: Balance | R38: + Propiedad, planta y equipo; neto | Z38: 15322 | AA38: 16090 | AB38: =16577 -> 16577 | AC38: 17075 | AD38: 16461 | AE38: 14395 | AF38: 12539 | AG38: 12386
N39: Balance Sheet | Z39: =Z40-SUM(Z30:Z38) -> 14512 | AA39: =AA40-SUM(AA30:AA38) -> 15585 | AB39: =AB40-SUM(AB30:AB38) -> 15786 | AC39: =AC40-SUM(AC30:AC38) -> 15616 | AD39: =AD40-SUM(AD30:AD38) -> 17947 | AE39: =AE40-SUM(AE30:AE38) -> 18419 | AF39: =AF40-SUM(AF30:AF38) -> 9453 | AG39: =AG40-SUM(AG30:AG38) -> 9263
N40: Balance Sheet | Q40: Balance | R40: Activos totales | Z40: 74704 | AA40: 78342 | AB40: 84681 | AC40: 84896 | AD40: 89356 | AE40: 81446 | AF40: 64020 | AG40: 60038
A41: LIABILITIES | N41: Balance Sheet
A42: Current Liabilities | B42: 1116.97 | C42: 927.85 | D42: 798.39 | E42: 653.95 | F42: 680.87 | N42: Balance Sheet | O42: Current Liabilities
A43: Payables | B43: 320 | C43: 261 | D43: 220 | E43: 232 | F43: 283 | G43: N/A | H43: N/A | I43: N/A | J43: N/A | K43: N/A | L43: N/A | M43: N/A
A44: Short-Term Debt | B44: 319.31 | C44: 306.27 | D44: 178.81 | E44: 129.49 | F44: 118.86 | G44: N/A | H44: N/A | I44: N/A | J44: N/A | K44: N/A | L44: N/A | M44: N/A | N44: Balance Sheet | O44: Short term Debt | Q44: Balance | R44: Pasivos totales corrientes | Z44: 26132 | AA44: 26242 | AB44: 27877 | AC44: 27297 | AD44: 29415 | AE44: =93+3895+8161+3386+2410+2691+298+1967+558+5102 -> 28561 | AF44: =204+3852+5856+2880+1670+1831+281+1521+495+3430 -> 22020 | AG44: =433+3650+2993+3351+797+1217+262+888+302+5399 -> 19292
A45: Short-Term Leases | B45: 135.35 | C45: 119.28 | D45: 121.23 | E45: 113.39 | F45: 114.92 | G45: N/A | H45: N/A | I45: N/A | J45: N/A | K45: N/A | L45: N/A | M45: N/A
A46: Other current liabilities | B46: =B42-SUM(B43:B45) -> 342.31 | C46: =C42-SUM(C43:C45) -> 241.3 | D46: =D42-SUM(D43:D45) -> 278.35 | E46: =E42-SUM(E43:E45) -> 179.07 | F46: =F42-SUM(F43:F45) -> 164.09 | G46: =G42-SUM(G43:G45) -> 0 | H46: =H42-SUM(H43:H45) -> 0 | I46: =I42-SUM(I43:I45) -> 0 | ... M46: =M42-SUM(M43:M45) -> 0 | N46: Balance Sheet | R46: + Préstamos CP | Z46: 7303 | AA46: 6967 | AB46: 4708 | AC46: 3679 | AD46: 5287 | AE46: 5660 | AF46: 3925 | AG46: 5701
A47: Non-current Liabilities | B47: =B51-B42 -> 942.03 | C47: =C51-C42 -> 885.15 | D47: =D51-D42 -> 1263.61 | E47: =E51-E42 -> 1508.05 | F47: =F51-F42 -> 1460.13 | G47: =G51-G42 -> 0 | H47: =H51-H42 -> 0 | I47: =I51-I42 -> 0 | ... M47: =M51-M42 -> 0 | N47: Balance Sheet | O47: Total non current liabilities
A48: Long-Term Debt | B48: 125.02 | C48: 197.86 | D48: 536.17 | E48: 687.37 | F48: 581.29 | G48: N/A | H48: N/A | I48: N/A | J48: N/A | K48: N/A | L48: N/A | M48: N/A | N48: Balance Sheet | O48: Long term debt | Z48: =Z44-Z46 -> 18829 | AA48: =AA44-AA46 -> 19275 | AB48: =AB44-AB46 -> 23169 | AC48: =AC44-AC46 -> 23618 | AD48: =AD44-AD46 -> 24128 | AE48: =AE44-AE46 -> 22901 | AF48: =AF44-AF46 -> 18095 | AG48: =AG44-AG46 -> 13591
A49: Long-Term Leases | B49: 519.89 | C49: 355.36 | D49: 376.75 | E49: 384.52 | F49: 454.72 | G49: N/A | H49: N/A | I49: N/A | J49: N/A | K49: N/A | L49: N/A | M49: N/A | Q49: Balance | R49: Pasivos totales no corrientes | Z49: =61491-Z44 -> 35359 | AA49: =63457-AA44 -> 37215 | AB49: =67855-AB44 -> 39978 | AC49: 36721 | AD49: 41973 | AE49: =8415+16529+10956+3583 -> 39483 | AF49: =4505+15932+7584+2654 -> 30675 | AG49: =5652+16195+7420+2179 -> 31446
A50: Other non-current liabilities | B50: =B47-SUM(B48:B49) -> 297.12 | C50: =C47-SUM(C48:C49) -> 331.93 | D50: =D47-SUM(D48:D49) -> 350.69 | E50: =E47-SUM(E48:E49) -> 436.16 | F50: =F47-SUM(F48:F49) -> 424.12 | G50: =G47-SUM(G48:G49) -> 0 | H50: =H47-SUM(H48:H49) -> 0 | I50: =I47-SUM(I48:I49) -> 0 | ... M50: =M47-SUM(M48:M49) -> 0 | N50: Balance Sheet | O50: Other non current Liabilities | R50: + Préstamos a largo plazo | Z50: 22818 | AA50: 25169 | AB50: 27784 | AC50: 26719 | AD50: 27752 | AE50: 24944 | AF50: 20437 | AG50: 21847
A51: Total Liabilities | B51: 2059 | C51: 1813 | D51: 2062 | E51: 2162 | F51: 2141 | N51: Balance Sheet | O51: Total Liabilities
N52: Balance Sheet | Z52: =Z49-Z50 -> 12541 | AA52: =AA49-AA50 -> 12046 | AB52: =AB49-AB50 -> 12194 | AC52: =AC49-AC50 -> 10002 | AD52: =AD49-AD50 -> 14221 | AE52: =AE49-AE50 -> 14539 | AF52: =AF49-AF50 -> 10238 | AG52: =AG49-AG50 -> 9599
N53: Balance Sheet | Z53: =+Z49+Z44 -> 61491 | AA53: =+AA49+AA44 -> 63457 | AB53: =+AB49+AB44 -> 67855 | AC53: =AC44+AC49 -> 64018 | AD53: =AD49+AD44 -> 71388 | AE53: =AE49+AE44 -> 68044 | AF53: =AF49+AF44 -> 52695 | AG53: =AG49+AG44 -> 50738
A54: Minority Interest | B54: 67 | C54: 57 | D54: 49 | E54: 53 | F54: 46 | G54: N/A | H54: N/A | I54: N/A | J54: N/A | K54: N/A | L54: N/A | M54: N/A | N54: Balance Sheet | O54: Minority Interest
N55: Balance Sheet
A56: Shareholder's Equity | B56: =B38-B51-B54 -> 927.66 | C56: =C38-C51-C54 -> 727.1 | D56: =D38-D51-D54 -> 682.95 | E56: =E38-E51-E54 -> 734.5 | F56: =F38-F51-F54 -> 771.77 | G56: N/A | H56: N/A | I56: N/A | J56: N/A | K56: N/A | L56: N/A | M56: N/A | N56: Balance Sheet | Q56: Balance | R56: + Participación minoritaria/no dominante
A58: CASH FLOW
A59: Operating CF | B59: 298 | C59: 154 | D59: 333 | E59: 81 | F59: 195 | G59: 228
A60: Net Income | B60: =B12 -> 131.42 | C60: =C12 -> 54.24 | D60: =D12 -> -160.87 | E60: =E12 -> -57.73 | F60: =F12 -> 24.34 | G60: =G12 -> 44.53 | H60: =H12 -> N/A | I60: =I12 -> N/A | ... M60: =M12 -> N/A
A61: Depreciation & Amortization | B61: 211 | C61: 183 | D61: 193 | E61: 212 | F61: 198 | G61: 190 | H61: N/A | I61: N/A | J61: N/A | K61: N/A | L61: N/A | M61: N/A
A62: Changes in assets and liabilities | B62: -22 | C62: -40 | D62: 24 | E62: -11 | F62: -13 | G62: 7 | H62: N/A | I62: N/A | J62: N/A | K62: N/A | L62: N/A | M62: N/A
A63: Other Adjustments | B63: =B59-B60-B61-B62 -> -22.42 | C63: =C59-C60-C61-C62 -> -43.24 | D63: =D59-D60-D61-D62 -> 276.87 | E63: =E59-E60-E61-E62 -> -62.27 | F63: =F59-F60-F61-F62 -> -14.34 | G63: =G59-G60-G61-G62 -> -13.53 | H63: N/A | I63: N/A | J63: N/A | K63: N/A | L63: N/A | M63: N/A
A64: Investing CF | B64: 23.56 | C64: -60.4 | D64: -97 | E64: 105.67 | F64: 93.98 | G64: -394.97
A65: Net Capex | B65: -61.46 | C65: -51.52 | D65: -89.7 | E65: -29.85 | F65: -52.01 | G65: -17.85 | H65: N/A | I65: N/A | J65: N/A | K65: N/A | L65: N/A | M65: N/A
A66: Investments & Acquisitions | B66: 85.46 | C66: -8.48 | D66: -7.3 | E66: 135.85 | F66: 146.01 | G66: -376.8 | H66: N/A | I66: N/A | J66: N/A | K66: N/A | L66: N/A | M66: N/A
A67: Other Inflows (Outflows) | B67: =B64-B65-B66 -> -0.44 | C67: =C64-C65-C66 -> -0.4 | D67: =D64-D65-D66 -> 0 | E67: =E64-E65-E66 -> -0.33 | F67: =F64-F65-F66 -> -0.02 | G67: =G64-G65-G66 -> -0.32 | H67: N/A | I67: N/A | J67: N/A | K67: N/A | L67: N/A | M67: N/A
A68: Financing CF | B68: -270.88 | C68: -312.88 | D68: -75.83 | E68: -55.99 | F68: -299.4 | G68: 155.68
A69: Debt Borrowing | B69: 221 | C69: 0 | D69: 146 | E69: 303 | F69: 146 | G69: 561 | H69: N/A | I69: N/A | J69: N/A | K69: N/A | L69: N/A | M69: N/A
A70: Debt Repayment | B70: -467 | C70: -301 | D70: -314 | E70: -356 | F70: -429 | G70: -391 | H70: N/A | I70: N/A | J70: N/A | K70: N/A | L70: N/A | M70: N/A
A71: Lease Payments | B71: -136 | C71: -128 | D71: -119 | E71: -104 | F71: -124 | G71: -134 | H71: N/A | I71: N/A | J71: N/A | K71: N/A | L71: N/A | M71: N/A
A72: Lease Increases | B72: 136 | C72: 128 | D72: 119 | E72: 104 | F72: 124 | G72: 134 | H72: N/A | I72: N/A | J72: N/A | K72: N/A | L72: N/A | M72: N/A
A73: Dividends | B73: -27.07 | C73: -23.03 | D73: 0.12 | E73: 0 | F73: 0 | G73: 0 | H73: N/A | I73: N/A | J73: N/A | K73: N/A | L73: N/A | M73: N/A | N73: cash flows FINANCING | O73: Dividends paid
A74: Share buyback | B74: -4 | C74: -15 | D74: -767 | E74: 1 | F74: 0 | G74: -3 | H74: N/A | I74: N/A | J74: N/A | K74: N/A | L74: N/A | M74: N/A | N74: cash flows FINANCING | O74: =+A74 -> Share buyback
A75: Other Inflows (Outflows) | B75: =B68-B69-B70-B71-B72-B73-B74 -> 6.19 | C75: =C68-C69-C70-C71-C72-C73-C74 -> 26.15 | D75: =D68-D69-D70-D71-D72-D73-D74 -> 859.05 | E75: =E68-E69-E70-E71-E72-E73-E74 -> -3.99 | F75: =F68-F69-F70-F71-F72-F73-F74 -> -16.4 | G75: =G68-G69-G70-G71-G72-G73-G74 -> -11.32 | H75: N/A | I75: N/A | J75: N/A | K75: N/A | L75: N/A | M75: N/A
A76: FX
A77: Changes in cash | B77: =B59+B64+B68+B76 -> 50.68 | C77: =C59+C64+C68+C76 -> -219.28 | D77: =D59+D64+D68+D76 -> 160.17 | E77: =E59+E64+E68+E76 -> 130.68 | F77: =F59+F64+F68+F76 -> -10.42 | G77: =G59+G64+G68+G76 -> -11.29 | H77: =H59+H64+H68+H76 -> 0 | I77: =I59+I64+I68+I76 -> 0 | ... M77: =M59+M64+M68+M76 -> 0
O78: (Vitalis will later fill this info)
A79: Other Data | E79: Corporate Bonds 3, 5 Y 10 | H79: Average Price | J79: Moody's | K79: YTM | L79: DIVISA
A80: Number of employees | B80: 7201 | C80: 10-K | N80: bloomberg
A81: Shares Outstanding (Thousands) | B81: 250.31M | C81: Yahoo finance | N81: bloomberg
A82: Float | B82: 59.07M | C82: Yahoo finance | N82: bloomberg
A83: Insiders Own | B83: 0.752 | C83: Yahoo finance | N83: bloomberg
A84: Fitch/ S&P Rating | C84: 10-K | N84: bloomberg
A85: Dividend Yield(Yahoo Finance) | B85: 0.0124 | C85: Yahoo finance | N85: bloomberg
A86: Daily Volume in Millions of USD | B86: 0 | C86: Yahoo Finance | N86: bloomberg
B87: =B5 -> 2023 | C87: =C5 -> 2022 | D87: =D5 -> 2021
A88: Short % of Float | E88: Yahoo Finance
A89: EPS | B89: €0.52 | C89: €0.21 | D89: -€0.68 | E89: Yahoo Finance
