Workbook
Name Benchmark: #REF!
Name BestConsOv: #REF!
Name Broker_Name: OFFSET(#REF!,0,0,#REF!, 1)
Name calCODE: #REF!
Name Chart_Benchmark_100_Size: OFFSET(#REF!, 0, 0,#REF!, 1)
Name Chart_Date_Size: OFFSET(#REF!, 0, 0,#REF!, 1)
Name Chart_Date_VAL1_Size: OFFSET(#REF!, 0, 0,#REF!, 1)
Name Chart_Date_VAL2_Size: OFFSET(#REF!, 0, 0,#REF!, 1)
Name Chart_Peer_100_Size: OFFSET(#REF!, 0, 0,#REF!, 1)
Name Chart_Price_100_Size: OFFSET(#REF!, 0, 0,#REF!, 1)
Name Chart_Price_Size: OFFSET(#REF!, 0, 0,#REF!, 1)
Name Chart_VAL1_FY1_Size: OFFSET(#REF!, 0, 0,#REF!, 1)
Name Chart_VAL1_FY2_Size: OFFSET(#REF!, 0, 0,#REF!, 1)
Name Chart_VAL1_FY3_Size: OFFSET(#REF!, 0, 0,#REF!, 1)
Name Chart_VAL2_FY1_Size: OFFSET(#REF!, 0, 0,#REF!, 1)
Name Chart_VAL2_FY2_Size: OFFSET(#REF!, 0, 0,#REF!, 1)
Name Chart_VAL2_FY3_Size: OFFSET(#REF!, 0, 0,#REF!, 1)
Name Chart_Volume_Size: OFFSET(#REF!, 0, 0,#REF!, 1)
Name compNAME: #REF!
Name CURRENCY: #REF!
Name currPRICE: #REF!
Name custBenchmark: #REF!
Name custED: #REF!
Name custSD: #REF!
Name dayCODE: #REF!
Name ED: #REF!
Name ESTBrokersItem: #REF!
Name ESTBrokersPeriod: #REF!
Name ESTDetailBroker: #REF!
Name ESTDetailBroker2: #REF!
Name ESTDetailPeriod: #REF!
Name EstDetPerO: #REF!
Name EstDetPerT: #REF!
Name FinancialsPeriod: #REF!
Name fundTICKER: #REF!
Name GraphValRatio1: #REF!
Name GraphValRatio2: #REF!
Name Index1: #REF!
Name Lang: #REF!
Name newCrncy: #REF!
Name newEstBrokerPeriod: #REF!
Name newEstBrokersItem: #REF!
Name newEstDetailBroker: #REF!
Name newEstDetailBroker2: #REF!
Name newEstDetailPeriod: #REF!
Name newFinancialsPeriod: #REF!
Name newOverviewCon: #REF!
Name newOverviewYear: #REF!
Name newOwners: #REF!
Name newPeersRatio: #REF!
Name newPeriod: #REF!
Name newValRatio1: #REF!
Name newValRatio2: #REF!
Name OverviewValRatioPeriod: #REF!
Name PeerDate1: #REF!
Name peerHist1: #REF!
Name PeerIndex: #REF!
Name Peers: OFFSET(#REF!,0,0,MAX(COUNTA(#REF!),1),1)
Name peersWEIGHT: #REF!
Name PERIODICITY: #REF!

Sheet OP
B2: 45761 | C2: Analista: Research | D2: 31/12/2025 (1st Quarter 2025/05/01) | E2: #VALUE! | K2: {=_FV(E2,"Bolsa")} -> Nasdaq Stock Market | L2: SIC: Sí
B3: #VALUE! | D3: DESCRIPTION: Laureate Education is a company of higher education institutions that focus on offering accesible and quality education to students around the world. The University offers undergraduated and doctoral degrees in business and managment, medical and health sciences, engineering, information and technology, architecture, education, law and communications
D4: Andrew B. Cohen (54yo; Ch; dir. s. 2016; ex Portfolio Manager at S.A.C Capital Advisors); Eilif Serck-Hanssen (58yo; dir. s. 2018; CEO of Laureate Education; ex CFO of XOJET); Leslie Brush (58yo; dir s. 2014: Vice President of Laureate Education; ex Vice President of FIS); Rick Buskirk (57yo; dir. s. 2021; CFO of Laureate Education; ex analyst at Deutsche Bank); Marcelo Cadoso (52yo; dir. s. 2021; COO of Laureate Education; ex CFO of Dell EMC Computer System); Chistian Hearbele (51yo; dir. s. 2022; CEO Peru of Laureate Education; ex Latin America Corporate Audit Director of Pepsi); Adam Smith (59yo; dir s. 2014; Senior Vice President of Laurete Education; ex independent consultant)
B5: Millones de USD
B6: Acción | D6: Liquidez y Solvencia | F6: =Segments!B2 -> Regions (2023) | I6: Rentabilidad (2022) | K6: Múltiplos
B7: Último Precio | C7: {=_FV(E2,"Preço")} -> 30.14 | D7: Activo: | E7: =Cifras_Originales!B27 -> 1972.237 | H7: %Vts; %Op.Mg.; D | I7: Año termina: | J7: 46022 | K7: Float: | L7: 0.91
B8: Outstanding Shares | C8: {=_FV(E2,"Ações em circulação",TRUE)/1000000} -> 147.3631 | D8: Pasivo: | E8: =Cifras_Originales!B39 -> 1196.482 | F8: =Segments!B4 -> Mexico | H8: =+Segments!J4 -> 53%; NA; 27% | K8: Insiders Own: | L8: =Cifras_Originales!B50 -> 0.0232
B9: Market Cap. | C9: {=_FV(E2,"Capitalização de mercado",TRUE)/1000000} -> 4441.5238 | D9: Cash/Precio | E9: =C11/C8 -> 0.5779398 | I9: EBIT | J9: 262.269 | K9: b (Bloomberg; Yahoo) | L9: =0.89 -> 0.89
B10: +Deuda Total | C10: =Cifras_Originales!B39 -> 1196.482 | D10: Ebidta/CIF | E10: =378.3/Cifras_Originales!B9 -> 4.3184932 | F10: =Segments!B5 -> Peru | H10: =+Segments!J5 -> 47%; NA; 12% | I10: +Dep&Amort | J10: =Cifras_Originales!C11 -> 59.132 | K10: Calificación (S&P) | L10: B+
B11: -Cash | C11: =Cifras_Originales!B22 -> 85.167 | D11: Deuda/Ebidta | E11: =E8/378.3 -> 3.1627861 | I11: =EBIDTA | J11: =J9+J10 -> 321.401 | K11: Precio/Valor en libros | L11: 3.02
B12: =Enterprise Value | C12: =C9+C10-C11 -> 5552.8388 | D12: "Otros activos"/Activo | E12: =Cifras_Originales!B26/OP!E7 -> 0.45779234 | F12: =Segments!B6 -> United States | H12: =+Segments!J6 -> 0%; NA; NA | I12: Utilidad Neta | J12: =Cifras_Originales!B16 -> 107.59 | K12: FNP(p)/Activos | L12: =J18/E7 -> -0.01212143
B13: Tenencia % (nac/int'l) | C13: - | D13: Deuda/Activo | E13: =C10/E7 -> 0.60666238 | I13: UPA | J13: =1000000*J12/C8 -> 730101.36 | K13: Precio/Utilidad(p) | L13: =C9/J17 -> 50.140535 | N13: =C10/J11 -> 3.7227078
B14: t liq. (Pos prom./Vol.) | C14: 0.1 | D14: Margen de Operación (p) | E14: 0.231 | F14: =Segments!B7 -> Other Foreign Countries | H14: =+Segments!J7 -> NA; NA; NA | I14: ROA | J14: =J12/E7 -> 0.054552267 | K14: EV/Activos | L14: =C12/E7 -> 2.8155028
B15: % Short | C15: 0.0228 | D15: Margen neto (p) | E15: 0.221 | F15: =Segments!B15 -> Products (2023) | I15: ROIC | J15: =J12/(E7-(E8-C10)) -> 0.054552267 | K15: EV/Ebidta (p) | L15: =C12/J16 -> 22.445265
B16: Semáforo ESG | D16: Ebidta/Ingresos(p) | E16: =140.3/423.4 -> 0.33136514 | F16: Products aren't reported | I16: Ebidta(p) | J16: =AVERAGE(Cifras_en_Millones!B19:D19) -> 247.39467 | K16: Precio/FNP (p) | L16: =C9/J18 -> -185.78858
B17: E | D17: CIF/Deuda Neta Promedio | E17: =Cifras_Originales!B9/(Cifras_Originales!B31+Cifras_Originales!B35) -> 0.073214641 | I17: Utilidad Neta (p) | J17: =AVERAGE(Cifras_en_Millones!B23:D23) -> 88.5815 | K17: Bonos 1;5;40a (USD) | L17: 4.0%; 4.4%; 5% | N17: 12
B18: S | I18: FNP (p) | J18: =SUM(F35:F37)/3 -> -23.906333 | K18: TDY(p)/Precio | L18: =SUM(E35:E37)/(3*C9) -> -0.077174864
B19: G | I19: Tax (p) últ. 5a | J19: 0.16 | K19: Div. Yield: | L19: 0
B20: Tesis de inversión | H20: Acuerdo | I20: Supuestos de valuación | L20: DCF Value
B21: Dividend Payments: Dividend yield = 0.7% (2024). Profitability Margins: 2023 Operating margin = 22.8%; The company is now focusing on maintaining good margins and operational efficiency. Potential Growth: Investments in digital infrastructure could lead to higher enrollments and better margins in the medium-to-long term. | H21: Mantener sin elevar posición | L21: =DCFF!D66 -> 16.276883
B23: KSF | H23: PO / Precio Stand By | L23: =DCFF!D65 -> -0.45995742
B24: Strong Market Presence & Geographic Diversification, Reputation & Accreditation, Scalability & Online Education, Financial Stability & Profitability, Social Impact & ESG Commitment | H24: =L21*0.85 -> 13.835351 | I24: Tasa de descuento: | J24: =DCFF!D47 -> 0.0925
B25: Año | C25: Ingresos | D25: Margen Operativo | E25: Div.+Recompra | F25: FNP | G25: Deuda/Activo | H25: Depreciación y amortización | I25: Capex + Adq | J25: Cash Flow
B26: 2012 | C26: =Cifras_Originales!M6 -> 3567.117 | D26: =Cifras_Originales!M8/Cifras_Originales!M6 -> 0.08648693 | E26: =Cifras_Originales!M17 -> -15.561 | F26: -80.6 | I26: -457.3 | K26: 2024 | L26: 2023
B27: =B26+1 -> 2013 | C27: =Cifras_Originales!L6 -> 3913.881 | D27: =Cifras_en_Millones!M12 -> 0.090507351 | E27: =Cifras_Originales!L17 -> 0 | F27: 132.3 | H27: =Cifras_en_Millones!L17 -> 288.331 | I27: -273.9 | J27: Profit | K27: 39.2 | L27: 26 | N27: =C27/C26-1 -> 0.097211277 | O27: =D27/D26-1 -> 0.046485869
B28: =B27+1 -> 2014 | C28: =Cifras_Originales!K6 -> 4414.682 | D28: =Cifras_en_Millones!L12 -> 0.096334912 | E28: =Cifras_Originales!K17 -> -8.381 | F28: -98.3 | G28: =Cifras_en_Millones!L61 -> 0.4871592 | H28: =Cifras_en_Millones!L17 -> 288.331 | I28: -148.5 | J28: Cash Flow from Operations (BWC) | K28: 90.263 | L28: =117.987-26.87 -> 91.117 | N28: =C28/C27-1 -> 0.12795509 | O28: =D28/D27-1 -> 0.064387709 | P28: =E28/E27-1 -> #DIV/0! | Q28: =F28/F27-1 -> -1.7430083 | R28: =H28/H27-1 -> 0 | S28: =I28/I27-1 -> -0.45783133 | BT28: 4303
B29: =B28+1 -> 2015 | C29: =Cifras_Originales!J6 -> 4291.659 | D29: =Cifras_en_Millones!K12 -> 0.078514393 | E29: =Cifras_Originales!J17 -> -23.054 | F29: -2.9 | G29: =Cifras_en_Millones!K61 -> 0.51542731 | H29: =Cifras_en_Millones!K17 -> 282.946 | I29: -358.9 | J29: Working Capital | K29: -52.2 | L29: -177 | N29: =C29/C28-1 -> -0.027866786 | O29: =D29/D28-1 -> -0.18498505 | P29: =E29/E28-1 -> 1.7507457 | Q29: =F29/F28-1 -> -0.97049847 | R29: =H29/H28-1 -> -0.018676452 | S29: =I29/I28-1 -> 1.416835 | BT29: 3066
B30: =B29+1 -> 2016 | C30: =Cifras_Originales!I6 -> 4244.192 | D30: =Cifras_en_Millones!J12 -> 0.09574449 | E30: =Cifras_Originales!I17 -> -2.159 | F30: 6.3 | G30: =Cifras_en_Millones!J61 -> 0.60642797 | H30: =Cifras_en_Millones!J17 -> 264.879 | I30: -256.7 | J30: Investing Activities | K30: 30.346 | L30: 2044.192 | N30: =C30/C29-1 -> -0.011060292 | O30: =D30/D29-1 -> 0.21945145 | P30: =E30/E29-1 -> -0.90635031 | Q30: =F30/F29-1 -> -3.1724138 | R30: =H30/H29-1 -> -0.063853173 | S30: =I30/I29-1 -> -0.28475899 | BT30: 3283
B31: =B30+1 -> 2017 | C31: =Cifras_Originales!H6 -> 3385.876 | D31: =Cifras_en_Millones!I12 -> 0.10316798 | E31: -19.371 | F31: =2898.836-3038.946 -> -140.11 | G31: =Cifras_en_Millones!I61 -> 0.51612793 | H31: =Cifras_en_Millones!I17 -> 264.742 | I31: -217.6 | J31: Capex | K31: =Cifras_Originales!C13 -> 30.658 | L31: =Cifras_Originales!D13 -> 2100.376 | N31: =C31/C30-1 -> -0.20223308 | O31: =D31/D30-1 -> 0.077534418 | P31: =E32/E30-1 -> 4.1426586 | Q31: =F37/F30-1 -> -15.232698 | R31: =H37/H30-1 -> -0.73717056 | S31: =I31/I30-1 -> -0.15231788
B32: =B31+1 -> 2018 | C32: =Cifras_Originales!G6 -> 3290.213 | D32: =Cifras_en_Millones!H12 -> 0.11843306 | E32: =-11.103 -> -11.103 | F32: =485.47-867.915 -> -382.445 | G32: =Cifras_en_Millones!H61 -> 0.40228404 | H32: =Cifras_en_Millones!H17 -> 239.998 | I32: -168.2 | J32: Adquisiones | K32: 583.493 | L32: 546.795 | N32: =C32/C31-1 -> -0.028253545 | O32: =D32/D31-1 -> 0.14796333 | P32: =#REF!/E32-1 -> #REF! | Q32: =F36/F37-1 -> -1.6975665 | R32: =H36/H37-1 -> -0.15062197 | S32: =#REF!/I31-1 -> #REF!
B33: =B32+1 -> 2019 | C33: =Cifras_Originales!F6 -> 1212.07 | D33: =Cifras_en_Millones!G12 -> -0.51298522 | E33: -99.253 | F33: =1123.179-2507.79 -> -1384.611 | G33: =Cifras_en_Millones!G61 -> 0.38406349 | H33: =Cifras_en_Millones!G17 -> 193.356 | I33: -71.7 | J33: Dividends | K33: =Cifras_Originales!C17 -> 0 | L33: =Cifras_Originales!D17 -> 0 | N33: =C33/C32-1 -> -0.63161352 | O33: =D33/D32-1 -> -5.331436 | P33: =E33/#REF!-1 -> #REF! | Q33: =F33/F36-1 -> -23.136775 | R33: =H35/H36-1 -> 0.71105324 | S33: =#REF!/#REF!-1 -> #REF!
B34: =B33+1 -> 2020 | C34: =Cifras_Originales!E6 -> 1024.917 | D34: =DCFF!D7 -> 0.094481797 | E34: -264.03 | F34: =-74.624+14.538 -> -60.086 | G34: =Cifras_en_Millones!F61 -> 0.25623855 | H34: =Cifras_en_Millones!F17 -> 143.516 | I34: -40.3 | J34: Stock Repurchases | K34: -282.2 | L34: -380.5 | N34: =C34/C33-1 -> -0.15440775 | O34: =D34/D33-1 -> -1.1841803 | P34: =E34/E33-1 -> 1.6601715 | Q34: =F34/F33-1 -> -0.95660442 | R34: =H33/H35-1 -> 0.91104786 | S34: =#REF!/#REF!-1 -> #REF!
B35: =B34+1 -> 2021 | C35: =Cifras_Originales!D6 -> 1086.701 | D35: =DCFF!E7 -> 0.13237588 | E35: -380.505 | F35: =-50.444+5.843 -> -44.601 | G35: =Cifras_en_Millones!E61 -> 0.28656133 | H35: =Cifras_en_Millones!E17 -> 101.178 | I35: -45 | J35: Endeudamiento Neto | K35: 146.946 | L35: -171.131 | N35: =C35/C34-1 -> 0.060281955 | O35: =D35/D34-1 -> 0.40107283 | P35: =E35/E34-1 -> 0.44114305 | Q35: =F35/F34-1 -> -0.25771394 | R35: =H34/H33-1 -> -0.25776288 | S35: =#REF!/#REF!-1 -> #REF!
B36: =B35+1 -> 2022 | C36: =Cifras_Originales!C6 -> 1242.271 | D36: =DCFF!F7 -> 0.21807802 | E36: =-282.151-253.188 -> -535.339 | F36: =496.253-433.705 -> 62.548 | G36: =Cifras_en_Millones!D61 -> 0.2374606 | H36: =Cifras_en_Millones!D17 -> 59.132 | I36: -53.1 | J36: Otros Financiemientos | K36: 0 | L36: 0 | N36: =C36/C35-1 -> 0.14315805 | O36: =D36/D35-1 -> 0.64741509
B37: =B36+1 -> 2023 | C37: =Cifras_Originales!B6 -> 1484.288 | D37: =DCFF!G7 -> 0.23036095 | E37: -112.478 | F37: =153.772-243.438 -> -89.666 | G37: =Cifras_en_Millones!C61 -> 0.30320595 | H37: =Cifras_en_Millones!C17 -> 69.618 | I37: -56.5 | N37: =C37/C36-1 -> 0.1948182 | O37: =D37/D36-1 -> 0.056323577
B38: 2024 Est. | C38: =DCFF!H6 -> 1566.6 | D38: =DCFF!H7 -> 0.225
B39: CAGR | C39: =(C37/C32)^(1/5)-1 -> -0.14717714 | D39: =(D37/D31)^(1/6)-1 -> 0.14325731 | J39: FX | K39: 0 | L39: 0
B40: AAG | C40: =AVERAGE(N27:N37) -> -0.039273671 | D40: =AVERAGE(O32:O37) -> -0.87714025 | J40: D Cash and Equivalents | K40: =K28+K29+K30+K33+K34+K35+K36+K39 -> -66.845 | L40: =L28+L29+L30+L33+L34+L35+L36+L39 -> 1406.678
B41: CVAR | C41: =STDEV(C26:C37)/AVERAGE(C26:C37) -> 0.5127391 | D41: =STDEV(D31:D37)/AVERAGE(D31:D37) -> 4.6714488 | J41: Inv/D Vts | K41: =SUM(H33:H37)/(C37-C32) -> -0.31385578 | L41: =(SUM(H33:H37)-SUM(#REF!))/(C37-C32) -> #REF!
B42: Último Año | C42: =C37/C36-1 -> 0.1948182 | D42: =D37/D36-1 -> 0.056323577 | J42: t inversiones; t adq. neto dep. | K42: =K41/E14 -> -1.358683 | L42: =L41/E14 -> #REF!
B43: Pros | I43: #VALUE!
B44: Increase in net income and adjusted EBITDA; Consolidated market presence; Diversified teaching model (in-person; online hybrid)
B45: Cons
B46: High dependency on Latin America markets; Significant exposure to currency fluctuations; Complex operational structure with multiple segments and academic cycles
B47: Riesgos
B48: Intense competition from private and public institutions; Regulatory and legal uncertainties; Risk associated with legal and tax contingencies
B49: Oportunidades
B50: Continuos growth in demand for higher education in emerging markets; Recovering macroeconomic environment, especially in Peru
B51: CHECKLIST
B52: Crecimiento | C52: Riesgos claros | D52: ESG | E52: Peer Analysis | F52: Consenso | G52: KSF | H52: PO/Stand By
B53: (p) = Promedio de últimos 3 años
B54: NOTES:

Sheet COVID-19 impact
A1: https://www.apple.com/newsroom/2020/03/apples-covid-19-response/ | G1: https://glg.it/articles/how-might-the-wuhan-coronavirus-impact-apples-supply-chain/ | N1: https://www.cnbc.com/2020/02/18/the-significance-of-apples-coronavirus-warning.html
A2: March 13 | G2: January 29 | N2: Ferbuary 18
A23: Otros:
A24: https://www.macrumors.com/guide/covid-19-coronavirus/

Sheet Segments
B2: Regions (2023)
C3: 2023 | D3: =C3-1 -> 2022 | E3: Ut. Operativa | F3: % Vts | G3: Margen | H3: Crec
B4: Mexico | C4: 782 | D4: 613.9 | E4: NA | F4: 0.527 | G4: NA | H4: 0.27 | J4: =IF(C4="","",IF(F4=0,"NA",TEXT(F4,"0%"))&"; "&IF(G4=0,"NA",TEXT(G4,"0.0%"))&"; "&IF(H4=0,"NA",TEXT(H4,"0%"))) -> 53%; NA; 27%
B5: Peru | C5: 701.4 | D5: 624.2 | E5: NA | F5: 0.473 | G5: NA | H5: 0.12 | J5: =IF(C5="","",IF(F5=0,"NA",TEXT(F5,"0%"))&"; "&IF(G5=0,"NA",TEXT(G5,"0.0%"))&"; "&IF(H5=0,"NA",TEXT(H5,"0%"))) -> 47%; NA; 12%
B6: United States | C6: 0.8 | D6: 0 | E6: NA | F6: 0.001 | G6: NA | J6: =IF(C6="","",IF(F6=0,"NA",TEXT(F6,"0%"))&"; "&IF(G6=0,"NA",TEXT(G6,"0.0%"))&"; "&IF(H6=0,"NA",TEXT(H6,"0%"))) -> 0%; NA; NA
B7: Other Foreign Countries | C7: 0 | D7: 4.1 | E7: NA | F7: 0 | G7: NA | J7: =IF(C7="","",IF(F7=0,"NA",TEXT(F7,"0%"))&"; "&IF(G7=0,"NA",TEXT(G7,"0.0%"))&"; "&IF(H7=0,"NA",TEXT(H7,"0%"))) -> NA; NA; NA
J8: =IF(C8="","",IF(F8=0,"NA",TEXT(F8,"0%"))&"; "&IF(G8=0,"NA",TEXT(G8,"0.0%"))&"; "&IF(H8=0,"NA",TEXT(H8,"0%")))
J9: =IF(C9="","",IF(F9=0,"NA",TEXT(F9,"0%"))&"; "&IF(G9=0,"NA",TEXT(G9,"0.0%"))&"; "&IF(H9=0,"NA",TEXT(H9,"0%")))
J10: =IF(C10="","",IF(F10=0,"NA",TEXT(F10,"0%"))&"; "&IF(G10=0,"NA",TEXT(G10,"0.0%"))&"; "&IF(H10=0,"NA",TEXT(H10,"0%")))
J11: =IF(C11="","",IF(F11=0,"NA",TEXT(F11,"0%"))&"; "&IF(G11=0,"NA",TEXT(G11,"0.0%"))&"; "&IF(H11=0,"NA",TEXT(H11,"0%")))
J12: =IF(C12="","",IF(F12=0,"NA",TEXT(F12,"0%"))&"; "&IF(G12=0,"NA",TEXT(G12,"0.0%"))&"; "&IF(H12=0,"NA",TEXT(H12,"0%")))
J13: =IF(C13="","",IF(F13=0,"NA",TEXT(F13,"0%"))&"; "&IF(G13=0,"NA",TEXT(G13,"0.0%"))&"; "&IF(H13=0,"NA",TEXT(H13,"0%")))
B14: TOTAL | C14: =SUM(C4:C12) -> 1484.2 | D14: =SUM(D4:D12) -> 1242.2 | E14: =SUM(E4:E13) -> 0 | F14: =C14/SUM($C$4:$C$13) -> 1 | G14: =E14/C14 -> 0 | H14: =C14/D14-1 -> 0.19481565
B15: Products (2023)
B16: Produts aren't reported since 2020

Sheet Peers
A2: Multiplos (USD) | B2: LAUR | C2: STRA | D2: ATGE | E2: PRDO
B3: Laureate Education | C3: Strategic Education | D3: Adtalem Global Education | E3: Perdoceo Education Corporation
A4: Ventas | B4: =Cifras_Originales!B6 -> 1484.288 | C4: 1130 | D4: 448 | E4: 238.184
A5: Crecimiento Ult. Año fiscal | B5: 0.194 | C5: 0.063 | D5: 11.92% | E5: =710004/695208-1 -> 0.021282839
A6: Crecimiento (vs 2019) | B6: 0.225 | C6: 0.133 | D6: 12.84% | E6: =710004/627704-1 -> 0.13111275
A7: Deuda | B7: 122278 | C7: 82110 | D7: 26772 | E7: 100504
A8: Activos | B8: 323888 | C8: 301311 | D8: 319616 | E8: 321195
A9: Deuda/Activos | B9: =OP!C10/OP!E7 -> 0.60666238 | C9: =213325/2125213 -> 0.10037817 | D9: =847853/2741417 -> 0.30927546 | E9: =131537/1237034 -> 0.10633257
A10: Deuda/EBITDA | B10: =OP!C10/OP!J11 -> 3.7227078 | C10: =213325/217795 -> 0.97947611 | D10: =847853/395099 -> 2.1459255 | E10: =131537/216698 -> 0.60700606
A11: (Capex + Adq.)/Revenue | B11: =DCFF!G22/DCFF!G6 -> -0.034964912 | C11: =36943/1065480 -> 0.034672636 | D11: =50375/1687694 -> 0.02984842 | E11: =4625/710004 -> 0.0065140478
A12: ROA (p) | B12: =107.6/2125.6 -> 0.050621001 | C12: =0.06/2.161 -> 0.027764924 | D12: 0.0748 | E12: 0.0995
A13: ROIC (p) | B13: =(1+B29/(B30+B31))*B30/(B32+B33-B34) -> 0.3258084 | C13: =(1+C29/(C30+C31))*C30/(C32+C33-C34) -> 0.13550156 | D13: =(1+D29/(D30+D31))*D30/(D32+D33-D34) -> 0.18961076 | E13: =(1+E29/(E30+E31))*E30/(E32+E33-E34) -> 0.50996078
A14: Margen Operativo (p) | B14: 0.2283 | C14: 0.1212 | D14: 0.1159 | E14: 0.2119
A15: Margen Operativo | B15: 0.2174 | C15: 0.088 | D15: 0.0555 | E15: 0.1865
A16: Float | B16: =OP!L7 -> 0.91 | C16: =1-3.03% -> 0.9697 | D16: =1-3.39% -> 0.9661 | E16: =1-9.95% -> 0.9005
A17: b | B17: =OP!L9 -> 0.89 | C17: 0.58 | D17: 0.97 | E17: 1.06
A18: Precio/Utilidad | B18: 17.39 | C18: 18.12 | D18: 18.98 | E18: 11.48
A19: Precio/Ventas | B19: 1.97 | C19: 1.99 | D19: 2.39 | E19: 2.68
A20: EV/Activos | B20: =OP!C12/OP!E7 -> 2.8155028 | C20: =2410/2125 -> 1.1341176 | D20: =4310/2741 -> 1.5724188 | E20: =1280/1237 -> 1.0347615
A21: EV/Ebitda | B21: =OP!C12/OP!J11 -> 17.276981 | C21: 10.9 | D21: 11.46 | E21: 6.23
A22: Div. Yield: | B22: N/A | C22: 0.0284 | D22: N/A | E22: 0.0192
A24: *Nota: Estos múltiplos no consideran el promedio de los últimos 3 años, únicamente valores del último año reportado
A25: **Cifras en USD
A29: Taxes | B29: 108750 | C29: 52282 | D29: 48840 | E29: 53850
A30: Op. Income | B30: 361212 | C30: 172330 | D30: 329942 | E30: 212425
A31: Net financial cost
A32: Total debt | B32: 582703 | C32: 213325 | D32: 847853 | E32: 131537
A33: Total Equity | B33: 949138 | C33: 1652518 | D33: 1369135 | E33: 959536
A34: Cash and Equivalents | B34: 89392 | C34: 208209 | D34: 219306 | E34: 568925

Sheet Acuerdo
A1: Invertir
A2: NO invertir
A3: Mantener sin elevar posición
A4: Mantener (y seguir comprando)
A5: Liquidar
A6: PENDIENTE

Sheet DCF
A1: Discounted Cash Flow
A3: Ventas | E3: Margen Operativo
A16: Inversiones | E16: Utilidad Neta
D31: 0.001 | E31: =1/((1+$B$59+$D31)^(E35-2021)) -> 0.92250923 | F31: =1/((1+$B$59+$D31)^(F35-2021)) -> 0.85102327 | G31: =1/((1+$B$59+$D31)^(G35-2021)) -> 0.78507682 | H31: =1/((1+$B$59+$D31)^(H35-2021)) -> 0.72424061 | I31: =1/((1+$B$59+$D31)^(I35-2021)) -> 0.66811864 | J31: =1/((1+$B$59+$D31)^(J35-2021)) -> 0.61634561 | K31: =1/((1+$B$59+$D31)^(K35-2021)) -> 0.56858451 | L31: =1/((1+$B$59+$D31)^(L35-2021)) -> 0.52452446 | ... AC31: =1/((1+$B$59+$D31)^(AC35-2021)) -> 0.13312755
D32: 0.005 | E32: =1/((1+$B$59+$D32)^(E35-2021)) -> 0.91911765 | F32: =1/((1+$B$59+$D32)^(F35-2021)) -> 0.84477725 | G32: =1/((1+$B$59+$D32)^(G35-2021)) -> 0.77644968 | H32: =1/((1+$B$59+$D32)^(H35-2021)) -> 0.7136486 | I32: =1/((1+$B$59+$D32)^(I35-2021)) -> 0.65592702 | J32: =1/((1+$B$59+$D32)^(J35-2021)) -> 0.6028741 | K32: =1/((1+$B$59+$D32)^(K35-2021)) -> 0.55411223 | L32: =1/((1+$B$59+$D32)^(L35-2021)) -> 0.50929433 | ... AC32: =1/((1+$B$59+$D32)^(AC35-2021)) -> 0.12141647
D33: Normal | E33: =1/((1+$B$59)^(E35-2021)) -> 0.92336103 | F33: =1/((1+$B$59)^(F35-2021)) -> 0.8525956 | G33: =1/((1+$B$59)^(G35-2021)) -> 0.78725355 | H33: =1/((1+$B$59)^(H35-2021)) -> 0.72691926 | I33: =1/((1+$B$59)^(I35-2021)) -> 0.67120892 | J33: =1/((1+$B$59)^(J35-2021)) -> 0.61976816 | K33: =1/((1+$B$59)^(K35-2021)) -> 0.57226977 | L33: =1/((1+$B$59)^(L35-2021)) -> 0.5284116 | ... AC33: =1/((1+$B$59)^(AC35-2021)) -> 0.13623496
B35: 2019 (Real) | C35: 2020 (Real) | D35: 2021 | E35: =D35+1 -> 2022 | F35: =E35+1 -> 2023 | G35: =F35+1 -> 2024 | H35: =G35+1 -> 2025 | I35: =H35+1 -> 2026 | J35: =I35+1 -> 2027 | K35: =J35+1 -> 2028 | L35: =K35+1 -> 2029 | ... AC35: =AB35+1 -> 2046
A36: Crecimiento | B36: =OP!N34 -> -0.15440775 | C36: =OP!N35 -> 0.060281955 | D36: 0.35 | E36: 0.034 | F36: 0.095 | G36: 0.095 | H36: 0.095 | I36: 0.095 | J36: 0.095 | K36: 0.08 | L36: 0.06 | M36: 0.05 | N36: 0.04 | O36: 0.035 | P36: 0.035 | Q36: 0.035 | R36: 0.035 | S36: 0.035 | T36: 0.035 | U36: 0.035 | V36: 0.035 | W36: 0.035 | X36: 0.035 | Y36: 0.035 | Z36: 0.035 | AA36: 0.035 | AB36: 0.035 | AC36: 0.035
A37: Ventas | B37: =OP!C34 -> 1024.917 | C37: =OP!C35 -> 1086.701 | D37: =OP!C34*(1+D36) -> 1383.638 | E37: =D37*(1+E36) -> 1430.6816 | F37: =E37*(1+F36) -> 1566.5964 | G37: =F37*(1+G36) -> 1715.4231 | H37: =G37*(1+H36) -> 1878.3882 | I37: =H37*(1+I36) -> 2056.8351 | J37: =I37*(1+J36) -> 2252.2345 | K37: =J37*(1+K36) -> 2432.4132 | L37: =K37*(1+L36) -> 2578.358 | ... AC37: =AB37*(1+AC36) -> 4717.0568
A38: Margen Operativo | B38: =+OP!D34 -> 0.094481797 | C38: =+OP!D35 -> 0.13237588 | D38: =108166.4/365513.2 -> 0.29593022 | E38: =108162.8/377959.8 -> 0.28617541 | F38: 0.27 | G38: 0.275 | H38: 0.26 | I38: 0.255 | J38: 0.25 | K38: 0.25 | L38: 0.25 | M38: 0.25 | N38: 0.25 | O38: 0.25 | P38: 0.25 | Q38: 0.25 | R38: 0.25 | S38: 0.25 | T38: 0.25 | U38: 0.25 | V38: 0.25 | W38: 0.25 | X38: 0.25 | Y38: 0.25 | Z38: 0.25 | AA38: 0.25 | AB38: 0.25 | AC38: 0.25
A39: EBIT | B39: 63930 | C39: 66288 | D39: =D37*D38 -> 409.46028 | E39: =E37*E38 -> 409.4259 | F39: =F37*F38 -> 422.98103 | G39: =G37*G38 -> 471.74134 | H39: =H37*H38 -> 488.38094 | I39: =I37*I38 -> 524.49296 | J39: =J37*J38 -> 563.05862 | K39: =K37*K38 -> 608.10331 | ... AC39: =AC37*AC38 -> 1179.2642
A40: Dep&Amort | B40: =OP!H33 -> 193.356 | C40: =OP!H34 -> 143.516 | D40: 11000 | E40: =D40*(1+E36*$H$59) -> 11374 | F40: =E40*(1+F36*$H$59) -> 12454.53 | G40: =F40*(1+G36*$H$59) -> 13637.71 | H40: =G40*(1+H36*$H$59) -> 14933.293 | I40: =H40*(1+I36*$I$59) -> 16351.956 | J40: =I40*(1+J36*$I$59) -> 17905.391 | K40: =J40*(1+K36*$I$59) -> 19337.823 | L40: =K40*(1+L36*$I$59) -> 20498.092 | M40: =L40*(1+M36*$I$59) -> 21522.997 | N40: =M40*(1+N36*$I$59) -> 22383.917 | O40: =N40*(1+O36*$I$59) -> 23167.354 | P40: =O40*(1+P36*$I$59) -> 23978.211 | ... AC40: =AB40*(1+AC36*$I$59) -> 37500.868
A41: EBIDTA | B41: =+B39+B40 -> 64123.356 | C41: =+C39+C40 -> 66431.516 | D41: =D39+D40 -> 11409.46 | E41: =E39+E40 -> 11783.426 | F41: =F39+F40 -> 12877.511 | G41: =G39+G40 -> 14109.452 | H41: =H39+H40 -> 15421.674 | I41: =I39+I40 -> 16876.449 | J41: =J39+J40 -> 18468.45 | K41: =K39+K40 -> 19945.926 | ... AC41: =AC39+AC40 -> 38680.133
A42: CIF | B42: -1385 | C42: -890 | D42: =(C48)*$H$60 -> -1124.36 | E42: =(D48)*$H$60 -> -1113.1164 | F42: =(E48)*$H$60 -> -1113.1164 | G42: =(F48)*$H$60 -> -1113.1164 | H42: =(G48)*$H$60 -> -1113.1164 | I42: =(H48)*$H$60 -> -1113.1164 | J42: =(I48)*$H$60 -> -1113.1164 | K42: =(J48)*$H$60 -> -1113.1164 | ... AC42: =(AB48)*$H$60 -> -1113.1164
A43: Otros Gastos | B43: =-422-2817 -> -3239 | C43: =87-3634 -> -3547 | D43: =-C43*(1+D36) -> 4788.45 | E43: =D43*(1+E36*0.5) -> 4869.8537 | F43: =E43*(1+F36*0.5) -> 5101.1717 | G43: =F43*(1+G36*0.5) -> 5343.4774 | H43: =G43*(1+H36*0.5) -> 5597.2925 | I43: =H43*(1+I36*0.5) -> 5863.1639 | J43: =I43*(1+J36*0.5) -> 6141.6642 | K43: =J43*(1+K36*0.5) -> 6387.3308 | L43: =K43*(1+L36*0.5) -> 6578.9507 | ... AC43: =AB43*(1+AC36*0.5) -> 8922.7133
A44: Utilidad antes de Impuestos | B44: =B39-B42-B43 -> 68554 | C44: =C39-C42-C43 -> 70725 | D44: =D39-D42-D43 -> -3254.6297 | E44: =E39-E42-E43 -> -3347.3113 | F44: =F39-F42-F43 -> -3565.0743 | G44: =G39-G42-G43 -> -3758.6196 | H44: =H39-H42-H43 -> -3995.7952 | I44: =I39-I42-I43 -> -4225.5546 | ... AC44: =AC39-AC42-AC43 -> -6630.3327
A45: ISR & PTU | B45: 10481 | C45: 9680 | D45: =$H$61*D44 -> -683.47224 | E45: =$H$61*E44 -> -702.93538 | F45: =$H$61*F44 -> -748.6656 | G45: =$I$61*G44 -> -864.48251 | H45: =$I$61*H44 -> -919.03289 | I45: =$I$61*I44 -> -971.87755 | J45: =$I$61*J44 -> -1027.0625 | K45: =$I$61*K44 -> -1073.2055 | L45: =$I$61*L44 -> -1108.8863 | M45: =$I$61*M44 -> -1139.3025 | N45: =$I$61*N44 -> -1164.0955 | ... AC45: =$I$61*AC44 -> -1524.9765
A46: Utilidad Neta | B46: =B44-B45 -> 58073 | C46: =C44-C45 -> 61045 | D46: =D44-D45 -> -2571.1575 | E46: =E44-E45 -> -2644.376 | F46: =F44-F45 -> -2816.4087 | G46: =G44-G45 -> -2894.1371 | H46: =H44-H45 -> -3076.7623 | I46: =I44-I45 -> -3253.677 | ... AC46: =AC44-AC45 -> -5105.3562
A47: Inversiones y Capex | B47: =OP!#REF! -> #REF! | C47: =OP!#REF! -> #REF! | D47: 10000 | E47: =D47*(1+E36*$H$62) -> 10408 | F47: =E47*(1+F36*$H$62) -> 11594.512 | G47: =F47*(1+G36*$H$62) -> 12916.286 | H47: =G47*(1+H36*$H$62) -> 14388.743 | I47: =H47*(1+I36*$H$62) -> 16029.06 | J47: =I47*(1+J36*$H$62) -> 17856.373 | K47: =J47*(1+K36*$H$62) -> 19570.584 | L47: =K47*(1+L36*$H$62) -> 20979.666 | ... AC47: =AB47*(1+AC36*$H$62) -> 43199.777
A48: Deuda + Lease Liabilities | B48: 108047 | C48: 112436 | D48: =C48*0.99 -> 111311.64 | E48: =D48 -> 111311.64 | F48: =E48 -> 111311.64 | G48: =F48 -> 111311.64 | H48: =G48 -> 111311.64 | I48: =H48 -> 111311.64 | J48: =I48 -> 111311.64 | K48: =J48 -> 111311.64 | L48: =K48 -> 111311.64 | ... AC48: =AB48 -> 111311.64
A49: Deuda/EBITDA | B49: =B48/B41 -> 1.6849867 | C49: =C48/C41 -> 1.6925099 | D49: =D48/D41 -> 9.7560829 | E49: =E48/E41 -> 9.4464582
A50: FNP | B50: =OP!F34 -> -60.086 | C50: =OP!F35 -> -44.601 | D50: =D41-D42-D43-D45-D47+D48-C48 -> -2695.5175 | E50: =E41-E42-E43-E45-E47+E48-D48 -> -1678.376 | F50: =F41-F42-F43-F45-F47+F48-E48 -> -1956.3907 | G50: =G41-G42-G43-G45-G47+G48-F48 -> -2172.7131 | H50: =H41-H42-H43-H45-H47+H48-G48 -> -2532.2125 | I50: =I41-I42-I43-I45-I47+I48-H48 -> -2930.7811 | J50: =J41-J42-J43-J45-J47+J48-I48 -> -3389.4078 | K50: =K41-K42-K43-K45-K47+K48-J48 -> -3825.6671 | ... AC50: =AC41-AC42-AC43-AC45-AC47+AC48-AB48 -> -10804.265
A51: F(t) | B51: 0 | C51: 0 | D51: =C51*(1+$B$59)+D50 -> -2695.5175 | E51: =D51*(1+$B$59)+E50 -> -4597.6214 | F51: =E51*(1+$B$59)+F50 -> -6935.6146 | G51: =F51*(1+$B$59)+G50 -> -9683.9838 | H51: =G51*(1+$B$59)+H50 -> -13019.967 | I51: =H51*(1+$B$59)+I50 -> -17031.405 | J51: =I51*(1+$B$59)+J50 -> -21834.42 | K51: =J51*(1+$B$59)+K50 -> -27472.344 | ... AC51: =AB51*(1+$B$59)+AC50 -> -359621.23
AB52: =AB51-AB48 -> -433395.64 | AC52: =AC50/(B59-AC36) -> -225088.86
A53: EPS | C53: =1000000*C46/OP!$C$8 -> 4.1424889e+08 | D53: =1000000*D46/OP!$C$8 -> -17447770 | E53: =1000000*E46/OP!$C$8 -> -17944628 | F53: =1000000*F46/OP!$C$8 -> -19112035
A54: Consenso EPS | C54: 3.3 | D54: 5.6 | E54: 5.6
A55: E$/UN | D55: =$B$61/D46 -> 34.890361 | E55: =$B$61/E46 -> 33.924303 | F55: =$B$61/F46 -> 31.852129
A56: EEV/EBIDA | D56: =($B$61+D48-D51)/D41 -> 2.1296841 | E56: =($B$61+E48-E51)/E41 -> 2.2235172 | F56: =($B$61+F48-F51)/F41 -> 2.2161614
C58: "TELP" | D58: CER | E58: D Analista | H58: CP | I58: LP
A59: Tasa de descuento: | B59: =SUM(C59:E59) -> 0.083 | C59: 0.0307 | D59: 0.0523 | E59: 0 | G59: Factor D&A | H59: 1 | I59: 1
G60: Factor CIF | H60: -0.01
A61: VPN*@i% | B61: =C62+C63 -> -89708.612 | C61: Normal | D61: =D31 -> 0.001 | E61: =D32 -> 0.005 | G61: Factor ISR | H61: 0.21 | I61: 0.23
A62: DCF 25Y | B62: =C62/B61 -> 0.65817136 | C62: =AB52/(1+B59)^25 -> -59043.639 | D62: =SUMPRODUCT(E50:AB50,E31:AB31) -> -44326.249 | E62: =SUMPRODUCT(E50:AB50,E32:AB32) -> -42404.098 | G62: Factor inv | H62: 1.2
A63: Perpetuidad | B63: =1-B62 -> 0.34182864 | C63: =AC52/(1+B59)^25 -> -30664.973 | D63: =(AC50/($B$59+D31-$AC$36))*AC31 -> -29353.987 | E63: =(AC50/($B$59+D32-$AC$36))*AC32 -> -24751.241 | G63: Suma D&A | H63: =SUM(40:40) -> 628766.44
A64: VPN/Acción | B64: =1000000*B61/OP!C8 -> -6.0875899e+08 | D64: =1000000*SUM(D62:D63)/OP!C8 -> -4.9999108e+08 | E64: =1000000*SUM(E62:E63)/OP!C8 -> -4.557134e+08 | G64: Suma Inv. | H64: =SUM(47:47) -> #REF!
B65: =B64/OP!C7-1 -> -20197711 | D65: =D64/B64-1 -> -0.17867154 | E65: =E64/B64-1 -> -0.25140588 | G65: Inv.+Goodwill | H65: =SUM(47:47)+(OP!E12*OP!E7) -> #REF!
A67: Duración | B67: =B62*D68+B63*D69 -> 21.007164 | E67: 1 | F67: 2 | G67: 3 | H67: 4 | I67: 5 | J67: 6 | K67: 7 | L67: 8 | M67: 9 | N67: 10 | O67: 11 | P67: 12 | Q67: 13 | R67: 14 | S67: 15 | T67: 16 | U67: 17 | V67: 18 | W67: 19 | X67: 20 | Y67: 21 | Z67: 22 | AA67: 23 | AB67: 24 | AC67: 25
A68: 0.001 | B68: =-$B$67*A68 -> -0.021007164 | D68: =SUM(E68:AB68)/SUMPRODUCT(E50:AB50,E33:AB33) -> 12.156716 | E68: =E67*E50*E33 -> -1549.747 | F68: =F67*F50*F33 -> -3336.0202 | G68: =G67*G50*G33 -> -5131.4284 | H68: =H67*H50*H33 -> -7362.856 | I68: =I67*I50*I33 -> -9835.832 | J68: =J67*J50*J33 -> -12603.882 | K68: =K67*K50*K33 -> -15325.195 | L68: =L67*L50*L33 -> -17728.982 | ... AC68: =AC67*AC50*AC33 -> -36797.967
A69: 0.005 | B69: =-$B$67*A69 -> -0.10503582 | D69: =(1+B59)/B59+AC67 -> 38.048193

Sheet DCFF
C1: VALUATION MODEL
D3: =D19/D6 -> 0.012974709 | E3: =E19/E6 -> 0.0093604405 | F3: =F19/F6 -> 0.0070644811 | G3: 0 | H3: 0.25 | I3: =H3+1 -> 1.25 | J3: =I3+1 -> 2.25 | K3: =J3+1 -> 3.25 | L3: =K3+1 -> 4.25 | M3: =L3+1 -> 5.25 | N3: =M3+1 -> 6.25 | O3: =N3+1 -> 7.25 | P3: =O3+1 -> 8.25 | ... AF3: =AE3+1 -> 24.25
A4: Section | B4: Line # | C4: ITEM | D4: 2020 (Real) | E4: 2021 (Real) | F4: 2022 (Real) | G4: 2023 (Real) | H4: 2024 | I4: =+H4+1 -> 2025 | J4: =+I4+1 -> 2026 | K4: =+J4+1 -> 2027 | L4: =+K4+1 -> 2028 | M4: =+L4+1 -> 2029 | N4: =+M4+1 -> 2030 | O4: =+N4+1 -> 2031 | P4: =+O4+1 -> 2032 | ... AF4: =+AE4+1 -> 2048 | AG4: Notes
A5: INCOME STATEMENT | B5: 1 | C5: Growth | D5: =Cifras_en_Millones!F6 -> -0.15440775 | E5: =Cifras_en_Millones!E6 -> 0.060281955 | F5: =Cifras_en_Millones!D6 -> 0.14315805 | G5: =Cifras_en_Millones!C6 -> 0.1948182 | H5: =H6/G6-1 -> 0.055455545 | I5: =I6/H6-1 -> 0.056896128 | J5: =J6/I6-1 -> 0.055742409 | K5: =K6/J6-1 -> 0.054479126 | L5: =L6/K6-1 -> 0.055439618 | M5: =M6/L6-1 -> 0.053592005 | N5: =N6/M6-1 -> 0.05179442 | O5: =O6/N6-1 -> 0.050048725 | ... AE5: =AE6/AD6-1 -> 0.024183497 | AF5: 0.02
B6: 2 | C6: Revenues/Sales | D6: =Cifras_en_Millones!F5 -> 1024.917 | E6: =Cifras_en_Millones!E5 -> 1086.701 | F6: =Cifras_en_Millones!D5 -> 1242.271 | G6: =Cifras_en_Millones!C5 -> 1484.288 | H6: =I82 -> 1566.6 | I6: =J82 -> 1655.7335 | J6: =K82 -> 1748.028 | K6: =L82 -> 1843.2591 | L6: =M82 -> 1945.4487 | M6: =N82 -> 2049.7092 | N6: =O82 -> 2155.8727 | O6: =P82 -> 2263.7713 | ... AF6: =AG82 -> 4029.1541
B7: 3 | C7: EBIT/Operating Margin | D7: =Cifras_en_Millones!F11/Cifras_en_Millones!F5 -> 0.094481797 | E7: =Cifras_en_Millones!E11/Cifras_en_Millones!E5 -> 0.13237588 | F7: =Cifras_en_Millones!D11/Cifras_en_Millones!D5 -> 0.21807802 | G7: =Cifras_en_Millones!C11/Cifras_en_Millones!C5 -> 0.23036095 | H7: 0.225 | I7: =H7*0.995 -> 0.223875 | J7: =I7*0.995 -> 0.22275562 | K7: =J7*0.995 -> 0.22164185 | L7: =K7*0.995 -> 0.22053364 | M7: 0.23 | N7: =23%*0.995 -> 0.22885 | O7: =N7*0.995 -> 0.22770575 | P7: =O7*0.995 -> 0.22656722 | Q7: =P7*0.995 -> 0.22543439 | R7: =Q7*0.995 -> 0.22430721 | S7: =R7*0.995 -> 0.22318568 | T7: 0.21 | U7: =T7*0.95 -> 0.1995 | V7: 0.21 | W7: 0.21 | X7: 0.21 | Y7: 0.21 | Z7: 0.21 | AA7: 0.21 | AB7: 0.21 | AC7: 0.21 | AD7: 0.21 | AE7: 0.21 | AF7: 0.21
B8: 4 | C8: EBIT | D8: =D6*D7 -> 96.836 | E8: =E6*E7 -> 143.853 | F8: =F6*F7 -> 270.912 | G8: =G7*G6 -> 341.922 | H8: =H7*H6 -> 352.485 | I8: =I7*I6 -> 370.67733 | J8: =J7*J6 -> 389.38308 | K8: =K7*K6 -> 408.54335 | L8: =L7*L6 -> 429.03687 | M8: =M7*M6 -> 471.43311 | N8: =N7*N6 -> 493.37146 | ... AF8: =AF7*AF6 -> 846.12236
B9: 5a | C9: (Dep&Amort) | D9: =-Cifras_en_Millones!F17 -> -143.516 | E9: =-Cifras_en_Millones!E17 -> -101.178 | F9: =-Cifras_en_Millones!D17 -> -59.132 | G9: =-Cifras_en_Millones!C17 -> -69.618 | H9: {=G9*0.7+0.3*(-$D$50*AVERAGE(-1*(D22:G22)))} -> -40.689357 | I9: {=H9*0.7+0.3*(-$D$50*AVERAGE(-1*(E22:H22)))} -> -22.621126 | J9: {=I9*0.7+0.3*(-$D$50*AVERAGE(-1*(F22:I22)))} -> -16.671868 | K9: {=J9*0.7+0.3*(-$D$50*AVERAGE(-1*(G22:J22)))} -> -13.018888 | L9: {=K9*0.7+0.3*(-$D$50*AVERAGE(-1*(H22:K22)))} -> -10.748491 | M9: {=L9*0.7+0.3*(-$D$50*AVERAGE(-1*(I22:L22)))} -> -9.1334093 | N9: {=M9*0.7+0.3*(-$D$50*AVERAGE(-1*(J22:M22)))} -> -7.9744238 | O9: {=N9*0.7+0.3*(-$D$50*AVERAGE(-1*(K22:N22)))} -> -7.1316644 | ... AF9: {=AE9*0.7+0.3*(-$D$50*AVERAGE(-1*(AB22:AE22)))} -> -8.5455291
B10: 5b | C10: (Stock based compensation) | D10: =-D19 -> -13.298 | E10: =-E19 -> -10.172 | F10: =-F19 -> -8.776 | G10: =-G19 -> -7.114 | H10: =-$D$51*H6 -> -6.0742571 | I10: =-$D$51*I6 -> -6.4198588 | J10: =-$D$51*J6 -> -6.7777172 | K10: =-$D$51*K6 -> -7.1469613 | L10: =-$E$51*L6 -> -19.454487 | M10: =-$E$51*M6 -> -20.497092 | N10: =-$E$51*N6 -> -21.558727 | O10: =-$E$51*O6 -> -22.637713 | P10: =-$E$51*P6 -> -23.732388 | Q10: =-$E$51*Q6 -> -24.841112 | R10: =-$E$51*R6 -> -25.962286 | S10: =-$E$51*S6 -> -27.094353 | ... AF10: =-$E$51*AF6 -> -40.291541
B11: 6 | C11: EBIDTA | D11: =-D9+D8 -> 240.352 | E11: =-E9+E8 -> 245.031 | F11: =-F9+F8 -> 330.044 | G11: =-G9+G8 -> 411.54 | H11: =-H9+H8 -> 393.17436 | I11: =-I9+I8 -> 393.29846 | J11: =-J9+J8 -> 406.05495 | K11: =-K9+K8 -> 421.56224 | ... AF11: =-AF9+AF8 -> 854.66789
B12: 7 | C12: (Net financing cost) | D12: =-Cifras_en_Millones!F14 -> -85.225 | E12: =-Cifras_en_Millones!E14 -> -28.097 | F12: =-Cifras_en_Millones!D14 -> -26.251 | G12: =-Cifras_en_Millones!C14 -> -87.6 | H12: =-$D$53*G37+G36*$D$54 -> -13.68147 | I12: =-$D$53*H37+H36*$D$54 -> -11.487073 | J12: =-$D$53*I37+I36*$D$54 -> -11.108987 | K12: =-$D$53*J37+J36*$D$54 -> -10.277606 | L12: =-$D$53*K37+K36*$D$54 -> -9.3424863 | M12: =-$D$53*L37+L36*$D$54 -> -8.2742336 | N12: =-$D$53*M37+M36*$D$54 -> -6.3449658 | O12: =-$E$53*N37+N36*E54 -> -25.55263 | P12: =-$E$53*O37+O36*$E$54 -> -25.57044 | Q12: =-$E$53*P37+P36*$E$54 -> -25.58527 | R12: =-$E$53*Q37+Q36*$E$54 -> -25.596895 | S12: =-$E$53*R37+R36*$E$54 -> -25.60354 | T12: =-$E$53*S37+S36*$E$54 -> -25.603904 | U12: =-$E$53*T37+T36*$E$54 -> -23.354713 | V12: =-$E$53*U37+U36*$E$54 -> -23.010608 | W12: =-$E$53*V37+V36*$E$54 -> -23.367026 | ... AF12: =-$E$53*AE37+AE36*$E$54 -> -23.831081
B13: 8 | C13: Other income/(cost) | D13: =Cifras_en_Millones!F15 -> 755 | E13: =Cifras_en_Millones!E15 -> -222.3 | F13: =Cifras_en_Millones!D15 -> -9.5 | G13: =Cifras_en_Millones!C15 -> 8.9 | H13: =-0.03*H6 -> -46.998 | I13: =-0.03*I6 -> -49.672004 | J13: =-0.03*J6 -> -52.440841 | K13: =-0.03*K6 -> -55.297773 | L13: =-0.03*L6 -> -58.36346 | M13: =-0.03*M6 -> -61.491275 | N13: =-0.03*N6 -> -64.67618 | O13: =-0.03*O6 -> -67.91314 | ... AF13: =-0.03*AF6 -> -120.87462
B14: 9 | C14: Earnings before taxes | D14: =D8+D12-13 -> -1.389 | E14: =E8+E12-E13 -> 338.056 | F14: =F8+F12-F13 -> 254.161 | G14: =G8+G12-G13 -> 245.422 | H14: =H8+H12+H13 -> 291.80553 | I14: =I8+I12+I13 -> 309.51825 | J14: =J8+J12+J13 -> 325.83325 | K14: =K8+K12+K13 -> 342.96797 | L14: =L8+L12+L13 -> 361.33093 | M14: =M8+M12+M13 -> 401.6676 | N14: =N8+N12+N13 -> 422.35031 | O14: =O8+O12+O13 -> 422.00798 | ... AF14: =AF8+AF12+AF13 -> 701.41666
B15: 10 | C15: (Income tax) | D15: =-Cifras_en_Millones!F21 -> 130.1 | E15: =-Cifras_en_Millones!E21 -> -145.6 | F15: =-Cifras_en_Millones!D21 -> -184.591 | G15: =-Cifras_en_Millones!C21 -> -137.803 | H15: =(-1*$D$52)*H14 -> -87.541659 | I15: =(-1*$D$52)*I14 -> -92.855476 | J15: =(-1*$D$52)*J14 -> -97.749975 | K15: =(-1*$D$52)*K14 -> -102.89039 | L15: =(-1*$E$52)*L14 -> -108.39928 | M15: =(-1*$E$52)*M14 -> -120.50028 | N15: =(-1*$E$52)*N14 -> -126.70509 | O15: =(-1*$E$52)*O14 -> -126.60239 | P15: =(-1*$E$52)*P14 -> -132.27915 | Q15: =(-1*$E$52)*Q14 -> -137.96864 | R15: =(-1*$E$52)*R14 -> -143.66071 | S15: =(-1*$E$52)*S14 -> -149.34617 | ... AF15: =(-1*$E$52)*AF14 -> -210.425
B16: 11 | C16: Net income | D16: =D14+D15 -> 128.711 | E16: =E14+E15 -> 192.456 | F16: =F14+F15 -> 69.57 | G16: =G14+G15 -> 107.619 | H16: =H14+H15 -> 204.26387 | I16: =I14+I15 -> 216.66278 | J16: =J14+J15 -> 228.08328 | K16: =K14+K15 -> 240.07758 | ... AF16: =AF14+AF15 -> 490.99166
A18: CASH FLOW STATEMENT | B18: 12 | C18: Operating cash flows before WK | D18: =259.6-D19-D20 -> 309.584 | E18: =-156.1-E19-E20 -> -285.575 | F18: =178.2-F19-F20 -> -8.592 | G18: =250.78-G20-G19 -> 285.604 | H18: =H11+H12+H13+H15 -> 244.95323 | I18: =I11+I12+I13+I15 -> 239.2839 | J18: =J11+J12+J13+J15 -> 244.75514 | K18: =K11+K12+K13+K15 -> 253.09647 | L18: =L11+L12+L13+L15 -> 263.68014 | M18: =M11+M12+M13+M15 -> 290.30073 | N18: =N11+N12+N13+N15 -> 303.61964 | O18: =O11+O12+O13+O15 -> 302.53725 | ... AF18: =AF11+AF12+AF13+AF15 -> 499.53719
B19: 13 | C19: (Stock-based compensation) | D19: 13.298 | E19: 10.172 | F19: 8.776 | G19: 7.114 | H19: =$D$55*H10 -> -0.023552023 | I19: =$D$55*I10 -> -0.024892042 | J19: =$D$55*J10 -> -0.026279585 | K19: =$D$55*K10 -> -0.027711273 | L19: =$D$55*L10 -> -0.075431861 | M19: =$D$55*M10 -> -0.079474406 | N19: =$D$55*N10 -> -0.083590737 | O19: =$D$55*O10 -> -0.087774347 | ... AF19: =$D$55*AF10 -> -0.15622442
B20: 14 | C20: (Working Capital Flows) | D20: =Cifras_Originales!E12-Cifras_Originales!F12 -> -63.282 | E20: =Cifras_Originales!D12-Cifras_Originales!E12 -> 119.303 | F20: =Cifras_Originales!C12-Cifras_Originales!D12 -> 178.016 | G20: =Cifras_Originales!B12-Cifras_Originales!C12 -> -41.938 | H20: =$D$56*(H6-G6) -> 49.3872 | I20: =$D$56*(I6-H6) -> 53.480084 | J20: =$D$56*(J6-I6) -> 55.376744 | K20: =$D$56*(K6-J6) -> 57.138625 | L20: =$E$56*(L6-K6) -> 30.656874 | M20: =$E$56*(M6-L6) -> 31.278148 | N20: =$E$56*(N6-M6) -> 31.849049 | O20: =$E$56*(O6-N6) -> 32.369603 | P20: =$E$56*(P6-O6) -> 32.840235 | Q20: =$E$56*(Q6-P6) -> 33.261732 | R20: =$E$56*(R6-Q6) -> 33.635198 | S20: =$E$56*(S6-R6) -> 33.962019 | ... AF20: =$E$56*(AF6-AE6) -> 29.220599
B21: 15 | C21: -Total Operating Cash Flow | D21: =D18+D19+D20 -> 259.6 | E21: =E18+E19+E20 -> -156.1 | F21: =F18+F19+F20 -> 178.2 | G21: =G18+G19+G20 -> 250.78 | H21: =H18+H19+H20 -> 294.31688 | I21: =I18+I19+I20 -> 292.7391 | J21: =J18+J19+J20 -> 300.10561 | K21: =K18+K19+K20 -> 310.20738 | ... AF21: =AF18+AF19+AF20 -> 528.60156
B22: 16 | C22: (CAPEX and Acquisitions) | D22: =Cifras_Originales!E13 -> 601.945 | E22: =Cifras_Originales!D13 -> 2100.376 | F22: =Cifras_Originales!C13 -> 30.658 | G22: =Cifras_Originales!B13 -> -51.898 | H22: =-$D$57*H6 -> -125.328 | I22: =-$D$57*I6 -> -132.45868 | J22: =-$D$57*J6 -> -139.84224 | K22: =-$D$57*K6 -> -147.46073 | L22: =-$E$57*L6 -> -116.72692 | M22: =-$E$57*M6 -> -122.98255 | N22: =-$E$57*N6 -> -129.35236 | O22: =-$E$57*O6 -> -135.82628 | P22: =-$E$57*P6 -> -142.39433 | Q22: =-$E$57*Q6 -> -149.04667 | R22: =-$E$57*R6 -> -155.77371 | S22: =-$E$57*S6 -> -162.56612 | ... AF22: =-$E$57*AF6 -> -241.74925
B23: 17 | C23: (Other investing flows) | D23: =587.4-D22 -> -14.545 | E23: =2044.2-E22 -> -56.176 | F23: =30.3-F22 -> -0.358 | G23: =-51.9-G22 -> -0.002 | H23: 0 | I23: 0 | J23: 0 | K23: 0 | L23: 0 | M23: 0 | N23: 0 | O23: 0 | P23: 0 | Q23: 0 | R23: 0 | S23: 0 | T23: 0 | U23: 0 | V23: 0 | W23: 0 | X23: 0 | Y23: 0 | Z23: 0 | AA23: 0 | AB23: 0 | AC23: 0 | AD23: 0 | AE23: 0 | AF23: 0
B24: 18 | C24: -Total Investing Flows | D24: =D22+D23 -> 587.4 | E24: =E22+E23 -> 2044.2 | F24: =F22+F23 -> 30.3 | G24: =G22+G23 -> -51.9 | H24: =H22+H23 -> -125.328 | I24: =I22+I23 -> -132.45868 | J24: =J22+J23 -> -139.84224 | K24: =K22+K23 -> -147.46073 | ... AF24: =AF22+AF23 -> -241.74925
B25: 19 | C25: (Flows related to leases) | H25: 0 | I25: 0 | J25: 0 | K25: 0 | L25: 0 | M25: 0 | N25: 0 | O25: 0 | P25: 0 | Q25: 0 | R25: 0 | S25: 0 | T25: 0 | U25: 0 | V25: 0 | W25: 0 | X25: 0 | Y25: 0 | Z25: 0 | AA25: 0 | AB25: 0 | AC25: 0 | AD25: 0 | AE25: 0 | AF25: 0
B26: 20 | C26: Flows related to debt | D26: =528.382-705.353-0.779 -> -177.75 | E26: =46.493-942.03-32.98 -> -928.517 | F26: =496.253-433.705 -> 62.548 | G26: =153.772-243.438-1.306 -> -90.972 | H26: =(H37-G37) -> 109.71984 | I26: =(I37-H37) -> 0.22338071 | J26: =(J37-I37) -> 22.961684 | K26: =(K37-J37) -> 27.91312 | L26: =(L37-K37) -> 32.801626 | M26: =(M37-L37) -> 73.406078 | N26: =(N37-M37) -> -163.13549 | O26: =(O37-N37) -> 29.763345 | ... AF26: =(AF37-AE37) -> 22.760061
B27: 21 | C27: (Respurchases)/Issuance of stock | D27: -99.523 | E27: -380.505 | F27: -282.151 | G27: 0 | H27: =(H21+H24+H28)*-1 -> -166.98888 | I27: =(I21+I24+I28)*-0.95 -> -141.97492 | J27: =(J21+J24+J28)*-0.95 -> -141.41624 | K27: =(K21+K24+K28)*-0.95 -> -143.20564 | L27: =(L21+L24+L28)*-0.95 -> -156.64367 | M27: =(M21+M24+M28)*-0.95 -> -175.23556 | N27: =(N21+N24+N28)*-0.95 -> -181.68796 | O27: =(O21+O24+O28)*-0.95 -> -132.9161 | P27: =(P21+P24+P28)*-0.95 -> -136.59272 | ... AF27: =(AF21+AF24+AF28)*-0.95 -> -85.932871
B28: 22 | C28: (Dividends) | D28: 0 | E28: 0 | F28: 0 | G28: 0 | H28: -2 | I28: =0.05*I16*(-1) -> -10.833139 | J28: =0.05*J16*(-1) -> -11.404164 | K28: =0.05*K16*(-1) -> -12.003879 | L28: =0.05*L16*(-1) -> -12.646582 | M28: =0.05*M16*(-1) -> -14.058366 | N28: =0.05*N16*(-1) -> -14.782261 | O28: =0.2*O16*(-1) -> -59.081117 | P28: =0.2*P16*(-1) -> -61.730272 | Q28: =0.2*Q16*(-1) -> -64.385367 | R28: =0.2*R16*(-1) -> -67.041666 | S28: =0.2*S16*(-1) -> -69.694877 | T28: =0.2*T16*(-1) -> -67.467998 | U28: =0.2*U16*(-1) -> -66.175182 | V28: =0.3*V16*(-1) -> -109.70654 | W28: =0.3*W16*(-1) -> -113.42776 | X28: =0.3*X16*(-1) -> -117.51653 | Y28: =0.4*Y16*(-1) -> -162.01318 | Z28: =0.4*Z16*(-1) -> -167.19625 | AA28: =0.4*AA16*(-1) -> -172.26438 | AB28: =0.4*AB16*(-1) -> -177.22281 | AC28: =0.4*AC16*(-1) -> -182.07734 | AD28: =0.4*AD16*(-1) -> -186.83411 | AE28: =0.4*AE16*(-1) -> -191.49947 | AF28: =0.4*AF16*(-1) -> -196.39666
B29: 23 | C29: Other financing flows | D29: =-77.5-D25-D26-D27-D28 -> 199.773 | E29: =-2698-E25-E26-E27-E28 -> -1388.978 | F29: =-460.4-F25-F26-F27-F28 -> -240.797 | G29: =-195.7-G25-G26-G27-G28 -> -104.728 | H29: 0 | I29: 0 | J29: 0 | K29: 0 | L29: 0 | M29: 0 | N29: 0 | O29: 0 | P29: 0 | Q29: 0 | R29: 0 | S29: 0 | T29: 0 | U29: 0 | V29: 0 | W29: 0 | X29: 0 | Y29: 0 | Z29: 0 | AA29: 0 | AB29: 0 | AC29: 0 | AD29: 0 | AE29: 0 | AF29: 0
B30: 24 | C30: -Total Financing flows | D30: =SUM(D25:D29) -> -77.5 | E30: =SUM(E25:E29) -> -2698 | F30: =SUM(F25:F29) -> -460.4 | G30: =SUM(G25:G29) -> -195.7 | H30: =SUM(H25:H29) -> -59.269033 | I30: =SUM(I25:I29) -> -152.58467 | J30: =SUM(J25:J29) -> -129.85872 | K30: =SUM(K25:K29) -> -127.2964 | ... AF30: =SUM(AF25:AF29) -> -259.56947
A32: SUMMARY | B32: 25 | C32: Cash before shareholder returns | D32: =D21+D24+D25+D26+D29 -> 869.023 | E32: =E21+E24+E25+E26+E29 -> -429.395 | F32: =F21+F24+F25+F26+F29 -> 30.251 | G32: =G21+G24+G25+G26+G29 -> 3.18 | H32: =H21+H24+H25+H26+H29 -> 278.70872 | I32: =I21+I24+I25+I26+I29 -> 160.5038 | J32: =J21+J24+J25+J26+J29 -> 183.22505 | K32: =K21+K24+K25+K26+K29 -> 190.65977 | ... AF32: =AF21+AF24+AF25+AF26+AF29 -> 309.61238
B33: 26 | C33: Returns to shareholders | D33: =-1*(D27+D28) -> 99.523 | E33: =-1*(E27+E28) -> 380.505 | F33: =-1*(F27+F28) -> 282.151 | G33: =-1*(G27+G28) -> 0 | H33: =-1*(H27+H28) -> 168.98888 | I33: =-1*(I27+I28) -> 152.80805 | J33: =-1*(J27+J28) -> 152.8204 | K33: =-1*(K27+K28) -> 155.20952 | ... AF33: =-1*(AF27+AF28) -> 282.32954
B34: 27 | C34: Excess cash acumulation | D34: =D32-D33 -> 769.5 | E34: =E32-E33 -> -809.9 | F34: =F32-F33 -> -251.9 | G34: =G32-G33 -> 3.18 | H34: =H32-H33 -> 109.71984 | I34: =I32-I33 -> 7.6957447 | J34: =J32-J33 -> 30.404644 | K34: =K32-K33 -> 35.450258 | ... AF34: =AF32-AF33 -> 27.282844
A36: CASH & DEBT & DISCOUNTING | B36: 28 | C36: Ending cash balance | D36: =Cifras_Originales!E22 -> 61.576 | E36: =Cifras_Originales!D22 -> 750.147 | F36: =Cifras_Originales!C22 -> 324.801 | G36: =Cifras_Originales!B22 -> 85.167 | H36: =G36+H34 -> 194.88684 | I36: =H36+I34 -> 202.58259 | J36: =I36+J34 -> 232.98723 | K36: =J36+K34 -> 268.43749 | L36: =K36+L34 -> 309.48352 | M36: =L36+M34 -> 392.11252 | N36: =M36+N34 -> 238.53955 | O36: =N36+O34 -> 275.29848 | ... AF36: =AE36+AF34 -> 578.2241
B37: 29 | C37: Total Debt | D37: =Cifras_en_Millones!F60 -> 1664.634 | E37: =Cifras_en_Millones!E60 -> 1424.466 | F37: =Cifras_en_Millones!D60 -> 525.099 | G37: =Cifras_en_Millones!C60 -> 597.994 | H37: =$D$219*H11 -> 707.71384 | I37: =$D$219*I11 -> 707.93722 | J37: =$D$219*J11 -> 730.89891 | K37: =$D$219*K11 -> 758.81203 | L37: =$D$219*L11 -> 791.61365 | M37: =$D$219*M11 -> 865.01973 | N37: =$E$219*N11 -> 701.88424 | O37: =$E$219*O11 -> 731.64758 | P37: =$E$219*P11 -> 761.88693 | Q37: =$E$219*Q11 -> 792.61075 | R37: =$E$219*R11 -> 823.65523 | S37: =$E$219*S11 -> 854.89171 | T37: =$F$219*T11 -> 657.8932 | U37: =$F$219*U11 -> 648.91654 | V37: =$F$219*V11 -> 706.84115 | W37: =$F$219*W11 -> 730.24884 | X37: =$F$219*X11 -> 755.47547 | Y37: =$F$219*Y11 -> 780.14201 | Z37: =$F$219*Z11 -> 804.2605 | AA37: =$F$219*AA11 -> 827.84894 | ... AF37: =$F$219*AF11 -> 940.13468
B38: 30 | C38: Discount factor | G38: =1/((1+$D$47)^G3) -> 1 | H38: =1/((1+$D$47)^H3) -> 0.97812563 | I38: =1/((1+$D$47)^I3) -> 0.8953095 | J38: =1/((1+$D$47)^J3) -> 0.81950526 | K38: =1/((1+$D$47)^K3) -> 0.75011923 | L38: =1/((1+$D$47)^L3) -> 0.68660799 | M38: =1/((1+$D$47)^M3) -> 0.62847414 | N38: =1/((1+$D$47)^N3) -> 0.57526237 | ... AF38: =1/((1+$D$47)^AF3) -> 0.11702535
F39: =1/((1+$D$48+0.001)^F$3) -> 0.99999294 | G39: =1/((1+$D$47+0.001)^G$3) -> 1 | H39: =1/((1+$D$47+0.001)^H$3) -> 0.97790193 | I39: =1/((1+$D$47+0.001)^I$3) -> 0.89428617 | J39: =1/((1+$D$47+0.001)^J$3) -> 0.81782 | K39: =1/((1+$D$47+0.001)^K$3) -> 0.74789209 | L39: =1/((1+$D$47+0.001)^L$3) -> 0.68394339 | M39: =1/((1+$D$47+0.001)^M$3) -> 0.62546263 | N39: =1/((1+$D$47+0.001)^N$3) -> 0.57198229 | ... AE39: =1/((1+$D$47+0.001)^AE$3) -> 0.12515932
F40: =1/((1+$D$48+0.005)^F$3) -> 0.99996477 | G40: =1/((1+$D$47+0.005)^G$3) -> 1 | H40: =1/((1+$D$47+0.005)^H$3) -> 0.97700968 | I40: =1/((1+$D$47+0.005)^I$3) -> 0.89021383 | J40: =1/((1+$D$47+0.005)^J$3) -> 0.81112878 | K40: =1/((1+$D$47+0.005)^K$3) -> 0.7390695 | L40: =1/((1+$D$47+0.005)^L$3) -> 0.67341185 | M40: =1/((1+$D$47+0.005)^M$3) -> 0.6135871 | N40: =1/((1+$D$47+0.005)^N$3) -> 0.55907709 | ... AE40: =1/((1+$D$47+0.005)^AE$3) -> 0.11497269
C42: EPS | H42: =H16/OP!C8 -> 1.3861263 | I42: =I16/OP!$C8 -> 1.4702648 | J42: =J16/OP!$C8 -> 1.5477638
C43: Consenso EPS
C44: E$/UN | H44: =$D$64/H16 -> 11.742713 | I44: =$D$64/I16 -> 11.070716
A46: Discount rate | D46: Total | E46: Risk free rate | F46: Equity premium | G46: Firm premium
C47: Discount Rate | D47: =SUM(E47:G47) -> 0.0925 | E47: 0.04 | F47: 0.04 | G47: 0.0125
D49: Short Term | E49: Long Term | F49: Reference (line) | I49: CAGR | J49: =(AF6/H6)^(1/26)-1 -> 0.037000743
A50: Modelling factors | C50: Dep. & Amort. factor | D50: =G118 -> 0.04 | E50: =G119 -> 0.06 | F50: % (PPE + Intangible assets) | G50: =SUM(G22:AF22)/SUM(G9:AF9) -> 13.932133
C51: Stock-based comp | D51: =D131 -> 0.0038773504 | E51: =1% -> 0.01 | F51: % revenue (l2) | G51: =-SUM(D10:F10)/SUM(D6:F6) -> 0.0096145102
C52: Tax Rate | D52: 0.3 | E52: 0.3 | F52: % (line 9)
C53: Interest Rate on debt | D53: =G168 -> 0.03 | E53: =G169 -> 0.05 | F53: % debt (l29)
C54: Interest Rate on cash | D54: 0.05 | E54: 0.04 | F54: % of cash (l28)
C55: Net SBC | D55: =D51 -> 0.0038773504 | E55: =E51 -> 0.01 | F55: % revenue (l2)
C56: Working capital flows | D56: 0.6 | E56: 0.3 | F56: % of change revenues (l2)
C57: Capex / Adq | D57: 0.08 | E57: 0.06 | F57: % revenue (l2)
C58: Dividends | D58: 0.01 | E58: 0.03 | F58: Growth rate
C59: Other financing flows | F59: % of debt (l29)
A61: Valuation | D61: $ millions | E61: % | F61: Notes | AE61: =((AE36-AE37)*AE38) -> -46.848576
C62: Value of flows | D62: =SUMPRODUCT(G33:AE33,G38:AE38)+((AE36-AE37)*AE38) -> 1898.8534 | E62: =D62/D64 -> 0.79164676 | F62: Present value of flows (l27), plus cash minus debt | AE62: =AE54+AE61 -> -46.848576
C63: Value of perpetuity | D63: =(AF32/(D47-AF5))*AF38 -> 499.75857 | E63: =D63/D64 -> 0.20835324 | F63: Present value of perpetuity (column AF flow, dividend by growth minus discount rate)
C64: Total Value | D64: =D62+D63 -> 2398.612 | F64: Final market value of firm's equity, compare to its mkt cap
C65: Total value vs Mkt Cap | D65: =D66/D67-1 -> -0.45995742 | F65: Gives degree of undervaluation (if positive, meaning it's worth more than what the market thinks) or overvaluation (negative, worth less than what the market thinks)
C66: Estimated NPV per share | D66: =D64/OP!C8 -> 16.276883 | F66: If we divide total value by # of shares, we get the estimated share value
C67: Actual share price | D67: =OP!C7 -> 30.14 | F67: Actual share price
A71: REVENUE
A73: Revenue per enrollment forecast:
E77: 2020 | F77: =E77+1 -> 2021 | G77: =F77+1 -> 2022 | H77: =G77+1 -> 2023 | I77: =H77+1 -> 2024 | J77: =I77+1 -> 2025 | K77: =J77+1 -> 2026 | L77: =K77+1 -> 2027 | M77: =L77+1 -> 2028 | ... AG77: =AF77+1 -> 2048
B78: Enrollments by country | D78: Mexico | E78: 195170 | F78: 203500 | G78: 222000 | H78: 242000 | I78: 258500 | J78: =I78*(1+J88) -> 275302.5 | K78: =J78*(1+K88) -> 292660.32 | L78: =K78*(1+L88) -> 310558.99 | M78: =L78*(1+M88) -> 329192.53 | N78: =M78*(1+N88) -> 347956.5 | O78: =N78*(1+O88) -> 366798.35 | P78: =O78*(1+P88) -> 385667.37 | Q78: =P78*(1+Q88) -> 404515.08 | ... AG78: =AF78*(1+AG88) -> 607947.14
D79: Peru | E79: 141330 | F79: 185000 | G79: 200000 | H79: 206900 | I79: 213500 | J79: =I79*(1+J89) -> 220972.5 | K79: =J79*(1+K89) -> 228474.52 | L79: =K79*(1+L89) -> 235998.52 | M79: =L79*(1+M89) -> 243314.48 | N79: =M79*(1+N89) -> 250630.95 | O79: =N79*(1+O89) -> 257941.32 | P79: =O79*(1+P89) -> 265239.22 | Q79: =P79*(1+Q89) -> 272518.47 | ... AG79: =AF79*(1+AG89) -> 370073.66
B80: Revenue per enrollment by country | D80: Mexico | E80: 2739.1505 | F80: 2655.5283 | G80: 2765.3153 | H80: 3233.8843 | I80: 3254.1586 | J80: =I80*(1+J90) -> 3276.9377 | K80: =J80*(1+K90) -> 3299.8763 | L80: =K80*(1+L90) -> 3322.9754 | M80: =L80*(1+M90) -> 3356.2052 | N80: =M80*(1+N90) -> 3389.7672 | O80: =N80*(1+O90) -> 3423.6649 | P80: =O80*(1+P90) -> 3457.9015 | Q80: =P80*(1+Q90) -> 3492.4806 | ... AG80: =AF80*(1+AG90) -> 4197.6856
D81: Peru | E81: 3408.6889 | F81: 2903.2432 | G81: 3121 | H81: 3391.4935 | I81: 3396.7213 | J81: =I81*(1+J91) -> 3410.3082 | K81: =J81*(1+K91) -> 3423.9494 | L81: =K81*(1+L91) -> 3437.6452 | M81: =L81*(1+M91) -> 3454.8335 | N81: =M81*(1+N91) -> 3472.1076 | O81: =N81*(1+O91) -> 3489.4682 | P81: =O81*(1+P91) -> 3506.9155 | Q81: =P81*(1+Q91) -> 3524.4501 | ... AG81: =AF81*(1+AG91) -> 3991.5921
B82: Revenue (millions) | D82: Total | E82: 1025 | F82: 1086.7 | G82: 1242.2 | H82: 1484.3 | I82: 1566.6 | J82: =(J78*J80+J79*J81)/10^6 -> 1655.7335 | K82: =(K78*K80+K79*K81)/10^6 -> 1748.028 | L82: =(L78*L80+L79*L81)/10^6 -> 1843.2591 | M82: =(M78*M80+M79*M81)/10^6 -> 1945.4487 | N82: =(N78*N80+N79*N81)/10^6 -> 2049.7092 | O82: =(O78*O80+O79*O81)/10^6 -> 2155.8727 | P82: =(P78*P80+P79*P81)/10^6 -> 2263.7713 | Q82: =(Q78*Q80+Q79*Q81)/10^6 -> 2373.2388 | ... AG82: =(AG78*AG80+AG79*AG81)/10^6 -> 4029.1541
A86: Multiples:
E87: 2020 | F87: =E87+1 -> 2021 | G87: =F87+1 -> 2022 | H87: =G87+1 -> 2023 | I87: =H87+1 -> 2024 | J87: =I87+1 -> 2025 | K87: =J87+1 -> 2026 | L87: =K87+1 -> 2027 | M87: =L87+1 -> 2028 | ... AG87: =AF87+1 -> 2048
B88: %change in enrollments | D88: Mexico | E88: - | F88: 0.04268074 | G88: 0.090909091 | H88: 0.09009009 | I88: 0.068181818 | J88: 0.065 | K88: =J88*0.97 -> 0.06305 | L88: =K88*0.97 -> 0.0611585 | M88: 0.06 | N88: =M88*0.95 -> 0.057 | O88: =N88*0.95 -> 0.05415 | P88: =O88*0.95 -> 0.0514425 | Q88: =P88*0.95 -> 0.048870375 | R88: =Q88*0.95 -> 0.046426856 | S88: =R88*0.95 -> 0.044105513 | T88: =S88*0.95 -> 0.041900238 | U88: =T88*0.9 -> 0.037710214 | V88: =U88*0.9 -> 0.033939193 | W88: =V88*0.9 -> 0.030545273 | X88: =W88*0.9 -> 0.027490746 | Y88: =X88*0.9 -> 0.024741671 | Z88: =Y88*0.9 -> 0.022267504 | AA88: =Z88*0.9 -> 0.020040754 | AB88: =AA88*0.9 -> 0.018036678 | ... AG88: =AF88*0.9 -> 0.010650478
D89: Peru | E89: - | F89: 0.30899314 | G89: 0.081081081 | H89: 0.0345 | I89: 0.031899468 | J89: 0.035 | K89: =J89*0.97 -> 0.03395 | L89: =K89*0.97 -> 0.0329315 | M89: 0.031 | N89: =M89*0.97 -> 0.03007 | O89: =N89*0.97 -> 0.0291679 | P89: =O89*0.97 -> 0.028292863 | Q89: =P89*0.97 -> 0.027444077 | R89: =Q89*0.97 -> 0.026620755 | S89: =R89*0.97 -> 0.025822132 | T89: =S89*0.97 -> 0.025047468 | U89: =T89*0.95 -> 0.023795095 | V89: =U89*0.95 -> 0.02260534 | W89: =V89*0.95 -> 0.021475073 | X89: =W89*0.95 -> 0.020401319 | Y89: =X89*0.95 -> 0.019381253 | Z89: =Y89*0.95 -> 0.018412191 | AA89: =Z89*0.95 -> 0.017491581 | AB89: =AA89*0.95 -> 0.016617002 | ... AG89: =AF89*0.95 -> 0.01285792
B90: %change in revenue per enrollment | D90: Mexico | E90: - | F90: =F80/E80-1 -> -0.030528527 | G90: =G80/F80-1 -> 0.041342832 | H90: =H80/G80-1 -> 0.16944505 | I90: =I80/H80-1 -> 0.0062693368 | J90: 0.007 | K90: 0.007 | L90: 0.007 | M90: 0.01 | N90: 0.01 | O90: 0.01 | P90: 0.01 | Q90: 0.01 | R90: 0.01 | S90: 0.01 | T90: 0.01 | U90: 0.01 | V90: 0.01 | W90: 0.01 | X90: 0.01 | Y90: 0.0125 | Z90: 0.0125 | AA90: 0.0125 | AB90: 0.0125 | AC90: 0.0125 | AD90: 0.0125 | AE90: 0.0125 | AF90: 0.0125 | AG90: 0.015
D91: Peru | E91: - | F91: =F81/E81-1 -> -0.14828154 | G91: =G81/F81-1 -> 0.075004655 | H91: =H81/G81-1 -> 0.086668848 | I91: =I81/H81-1 -> 0.0015414555 | J91: 0.004 | K91: 0.004 | L91: 0.004 | M91: =0.5% -> 0.005 | N91: =0.5% -> 0.005 | O91: =0.5% -> 0.005 | P91: =0.5% -> 0.005 | Q91: =0.5% -> 0.005 | R91: =0.5% -> 0.005 | S91: =0.5% -> 0.005 | T91: =0.5% -> 0.005 | ... X91: =0.5% -> 0.005 | Y91: 0.01 | Z91: 0.01 | AA91: 0.01 | AB91: 0.01 | AC91: 0.01 | AD91: 0.01 | AE91: 0.01 | AF91: 0.01 | AG91: 0.01
B92: Revenue Growth Rate | D92: Total | E92: - | F92: =F82/E82-1 -> 0.060195122 | G92: =G82/F82-1 -> 0.14309377 | H92: =H82/G82-1 -> 0.19489615 | I92: =I82/H82-1 -> 0.055447012 | J92: =J82/I82-1 -> 0.056896128 | K92: =K82/J82-1 -> 0.055742409 | L92: =L82/K82-1 -> 0.054479126 | M92: =M82/L82-1 -> 0.055439618 | ... AF92: =AF82/AE82-1 -> 0.024183497 | AG92: 0.02
A98: EBIT MARGIN
D101: 2023 | E101: =D101-1 -> 2022 | F101: =E101-1 -> 2021 | G101: =F101-1 -> 2020 | H101: =G101-1 -> 2019 | I101: =H101-1 -> 2018 | J101: =I101-1 -> 2017
C102: EBIT | D102: =Cifras_Originales!B8 -> 341.922 | E102: =Cifras_Originales!C8 -> 270.912 | F102: =Cifras_Originales!D8 -> 143.853 | G102: =Cifras_Originales!E8 -> 96.836 | H102: =Cifras_Originales!F8 -> -621.774 | I102: =Cifras_Originales!G8 -> 389.67 | J102: =Cifras_Originales!H8 -> 349.314
C103: EBIT Margin | D103: =Cifras_Originales!B8/Cifras_Originales!B6 -> 0.23036095 | E103: =Cifras_Originales!C8/Cifras_Originales!C6 -> 0.21807802 | F103: =Cifras_Originales!D8/Cifras_Originales!D6 -> 0.13237588 | G103: =Cifras_Originales!E8/Cifras_Originales!E6 -> 0.094481797 | H103: =Cifras_Originales!F8/Cifras_Originales!F6 -> -0.51298522 | I103: =Cifras_Originales!G8/Cifras_Originales!G6 -> 0.11843306 | J103: =Cifras_Originales!H8/Cifras_Originales!H6 -> 0.10316798
C105: Average (3Y) | D105: =AVERAGE(D103:F103) -> 0.19360495 | F105: ST Multiple | G105: 0.22
F106: MT Multiple | G106: 0.23
F107: LT Multiple | G107: 0.21
A109: DEPRECIATION & AMORTIZATION FACTOR
D112: 2017 | E112: =D112+1 -> 2018 | F112: =E112+1 -> 2019 | G112: =F112+1 -> 2020 | H112: =G112+1 -> 2021 | I112: =H112+1 -> 2022 | J112: =I112+1 -> 2023
C113: Depreciation & Amortization | D113: 60.4 | E113: 26.5 | F113: 82 | G113: 83.1 | H113: 101.2 | I113: 59.1 | J113: 69.6
C114: PPE | D114: =Cifras_Originales!H25 -> 2151.633 | E114: =Cifras_Originales!G25 -> 1380.417 | F114: =Cifras_Originales!F25 -> 1278.935 | G114: =Cifras_Originales!E25 -> 1162.394 | H114: =Cifras_Originales!D25 -> 1041.251 | I114: =Cifras_Originales!C25 -> 883.861 | J114: =Cifras_Originales!B25 -> 912.972
C115: Intangible assets | D115: 3033 | E115: 2860.3 | F115: 1170.2 | G115: 802 | H115: 689.6 | I115: 735.1 | J115: 830.7
C116: %(PPE + Intangible assets) | D116: =D113/(D114+D115) -> 0.011649812 | E116: =E113/(E114+E115) -> 0.0062489433 | F116: =F113/(F114+F115) -> 0.033481209 | G116: =G113/(G114+G115) -> 0.042303122 | H116: =H113/(H114+H115) -> 0.058468349 | I116: =I113/(I114+I115) -> 0.036504894 | J116: =J113/(J114+J115) -> 0.039915764
C118: Average (total) | D118: =AVERAGE(D116:J116) -> 0.032653156 | F118: ST Multiple | G118: 0.04
C119: Average (5Y) | D119: =AVERAGE(F116:J116) -> 0.042134668 | F119: LT Multiple | G119: 0.06
C120: Average (3Y) | D120: =AVERAGE(H116:J116) -> 0.044963002
A123: STOCK BASED COMPENSATION
D125: 2023 | E125: =D125-1 -> 2022 | F125: =E125-1 -> 2021 | G125: =F125-1 -> 2020 | H125: =G125-1 -> 2019 | I125: =H125-1 -> 2018 | J125: =I125-1 -> 2017
C126: Stock based compensation | D126: =G10 -> -7.114 | E126: =F19 -> 8.776 | F126: =E19 -> 10.172 | G126: =D19 -> 13.298 | H126: 12.994 | I126: 10.791 | J126: 64.788
C127: %Revenues | D127: =D126/G6 -> -0.0047928704 | E127: =E126/F6 -> 0.0070644811 | F127: =F126/E6 -> 0.0093604405 | G127: =D10/D6 -> -0.012974709 | H127: =H126/Cifras_Originales!F6 -> 0.010720503 | I127: =I126/Cifras_Originales!G6 -> 0.0032797269 | J127: =J126/Cifras_Originales!H6 -> 0.019134782
C129: Average (total) | D129: =AVERAGE(D127:J127) -> 0.0045417649 | F129: ST Multiple | G129: =D131 -> 0.0038773504
C130: Average (5Y) | D130: =AVERAGE(D127:H127) -> 0.001875569 | F130: LT Multiple | G130: 0.01
C131: Average (3Y) | D131: =AVERAGE(D127:F127) -> 0.0038773504
A133: TAX RATE
D135: 2024 | E135: 2023 | F135: =E135-1 -> 2022 | G135: =F135-1 -> 2021 | H135: =G135-1 -> 2020 | I135: =H135-1 -> 2019 | J135: =I135-1 -> 2018 | K135: =J135-1 -> 2017
C136: Pretax Income | D136: 358.7 | E136: 254.5 | F136: =Cifras_Originales!C8 -> 270.912 | G136: =Cifras_Originales!D8 -> 143.853 | H136: =Cifras_Originales!E8 -> 96.836 | I136: =Cifras_Originales!F8 -> -621.774 | J136: =Cifras_Originales!G8 -> 389.67 | K136: =Cifras_Originales!H8 -> 349.314
...

Sheet ESG
B2: Análisis ESG | J2: PARÁMETROS
C3: Impacto | D3: ¿Reporta? | E3: Ranking | F3: Mitigación | G3: Semáforo | H3: Comentarios | J3: IMPACTO | L3: RANKING | M3: MITIGACIÓN
B4: Ambiental | J4: NONE | K4: 0 | L4: "Best in class" | M4: Is there evidence of progam/plan/etc…
B5: Emisiones directas CO2 | C5: Low | D5: Yes | E5: Medium High | F5: Yes | H5: Despite implementing mitigation strategies for the category, the company does not publicly report specific data: To minimize greenhouse gas emissions, UPN has implemented initiatives including waste segregation stations, LED lighting, eco-efficient faucets and urinals, renewable energy sources, parking spaces for sustainable mobility, and the use of solar energy and drip irrigation. | J5: LOW | K5: 1 | L5: Medium high
B6: Uso total de agua | C6: Low | D6: Yes | E6: Medium High | F6: Yes | H6: To further reduce water consumption, Laureate Education has implemented water catchment systems in covered parking lots, allowing for the collection of rainwater, as well as low-flow taps across its campuses | J6: MEDIUM | K6: 2 | L6: Medium
B7: Total Energy Consumption | C7: Medium | D7: Yes | E7: Medium High | F7: Yes | H7: Laureate Education is actively addressing energy consumption by integrating energy-efficient practices across its campuses. Key initiatives include replacing fluorescent and luminescent lights with LED lights, and the implementation of solar systems | J7: HIGH | K7: 3 | L7: "Villain"
B8: Waste Management | C8: Low | D8: Yes | E8: Best in class | F8: Yes | H8: Organic waste is treated through composting, contributing to a circular approach that minimizes waste and enhances sustainability on campus
B9: Land Degradation/Deforestation/Biodiversity loss/Animal sufering/… | C9: Low | D9: No | F9: No | H9: The company promotes biodiversity through audits of campus flora and fauna, as well as the establishment of pollinator and hydroponic gardens | J9: TRAFFIC LIGHTS
B10: Social
B11: % Rotación de empleados | C11: Medium | D11: No | F11: Yes
B12: Sueldos y compensaciones | C12: Medium | D12: No | E12: Medium | F12: Yes
B13: Temas de reputación | C13: Medium | D13: No | F13: Yes | H13: Laureate previously scaled back operations in various regions (e.g., divesting universities in the U.S. and other countries), which raised concerns about long-term commitments to students and communities.
B14: Temas de discriminación | C14: Low | D14: Yes | E14: Best in class | F14: Yes | H14: The report highlights Laureate’s Silver-Level Certification for Labor Equality and Non-Discrimination awarded to UNITEC
B15: Seguridad laboral | C15: Low | D15: No | E15: Best in class | F15: Yes
B16: Daños a la salud | C16: Low | D16: No | E16: Best in class | F16: Yes
B17: PXP?
B18: Supply chain | C18: Medium | D18: No | F18: Yes | H18: No specific details are provided in the report
B19: Community involvement | C19: Low | D19: Yes | E19: Best in class | F19: Yes | H19: Strongly emphasized with over 1.05 million volunteer hours dedicated to social initiatives, making this a high-impact area.
B20: Public Sector | C20: Medium | D20: No | F20: Yes | H20: While the company engages with the public sector through educational and healthcare programs, clearer reporting on government collaborations and regulatory compliance would enhance stakeholder confidence
B21: Litigios | C21: Low | D21: No | F21: Yes | H21: No major legal disputes were mentioned
B22: Gobierno
B23: Diversidad (Género, edad, industria, región) | C23: Low | D23: Yes | E23: Medium High | F23: Yes | H23: The company has made notable progress in gender diversity, with women comprising 47% of employees, 52% of students, and 29% of senior leadership—an increase from the previous year. Additionally, the presence of international teams across multiple countries suggests an emphasis on cultural diversity - Laureate has received notable recognition for its diversity and inclusion efforts—such as UNITEC’s Silver-Level Certification for Labor Equality and Non-Discrimination
B24: % independientes
B25: tiempo promedio como consejeros independientes
B26: Salidas recientes de consejeros/C-level executives?
B27: CEO/Chairman
B28: Transparencia (segmentos, fuente de riqueza, adquisiciones, otros)
B29: Tiempo que tardan en reportar luego del final del trimestre/año
B30: Participación adicional del CEO en otros consejos o excesiva del Ch.
B31: Auditoría/Consultoría | D31: Yes | H31: The audit of Laureate Education is overseen by an independent auditor
B32: Esquemas de compensación al management | D32: Yes | H32: The Compensation Committee, among other things, monitors and assesses the Company’s compensation programs and policies. In consultation with its independent compensation consultant and with management regarding such matters

Sheet Cifras_en_Millones
A1: =Cifras_Originales!G3 -> #VALUE!
A2: =Cifras_Originales!C2 -> Cifras en Millones de USD
A4: Resultados | B4: 2024 | C4: =Cifras_Originales!B5 -> 2023 | D4: =Cifras_Originales!C5 -> 2022 | E4: =Cifras_Originales!D5 -> 2021 | F4: =Cifras_Originales!E5 -> 2020 | G4: =Cifras_Originales!F5 -> 2019 | H4: =Cifras_Originales!G5 -> 2018 | I4: =Cifras_Originales!H5 -> 2017 | J4: =Cifras_Originales!I5 -> 2016 | ... M4: =Cifras_Originales!L5 -> 2013
A5: Ventas Netas | C5: =Cifras_Originales!B6 -> 1484.288 | D5: =Cifras_Originales!C6 -> 1242.271 | E5: =Cifras_Originales!D6 -> 1086.701 | F5: =Cifras_Originales!E6 -> 1024.917 | G5: =Cifras_Originales!F6 -> 1212.07 | H5: =Cifras_Originales!G6 -> 3290.213 | I5: =Cifras_Originales!H6 -> 3385.876 | J5: =Cifras_Originales!I6 -> 4244.192 | ... M5: =Cifras_Originales!L6 -> 3913.881
A6: Crecimiento vs. Año pasado | B6: =B5/C5-1 -> -1 | C6: =C5/D5-1 -> 0.1948182 | D6: =D5/E5-1 -> 0.14315805 | E6: =E5/F5-1 -> 0.060281955 | F6: =F5/G5-1 -> -0.15440775 | G6: =G5/H5-1 -> -0.63161352 | H6: =H5/I5-1 -> -0.028253545 | I6: =I5/J5-1 -> -0.20223308 | ... L6: =L5/M5-1 -> 0.12795509
A7: Utilidad Bruta | C7: =Cifras_Originales!B7 -> 394.507 | D7: =Cifras_Originales!C7 -> 334.906 | E7: =Cifras_Originales!D7 -> 272.211 | F7: =Cifras_Originales!E7 -> 222.459 | G7: =Cifras_Originales!F7 -> 262.599 | H7: =Cifras_Originales!G7 -> 593.164 | I7: =Cifras_Originales!H7 -> 564.585 | J7: =Cifras_Originales!I7 -> 628.854 | ... M7: =Cifras_Originales!L7 -> 495.432
A8: porcentaje sobre ventas | B8: =B7/B5 -> #DIV/0! | C8: =C7/C5 -> 0.26578871 | D8: =D7/D5 -> 0.26959174 | E8: =E7/E5 -> 0.25049301 | F8: =F7/F5 -> 0.21705075 | G8: =G7/G5 -> 0.21665333 | H8: =H7/H5 -> 0.18028134 | I8: =I7/I5 -> 0.1667471 | ... M8: =M7/M5 -> 0.12658331
A9: Gastos de Operación | B9: =B5-B11 -> 0 | C9: =C5-C11 -> 1142.366 | D9: =D5-D11 -> 971.359 | E9: =E5-E11 -> 942.848 | F9: =F5-F11 -> 928.081 | G9: =G5-G11 -> 1833.844 | H9: =H5-H11 -> 2900.543 | I9: =I5-I11 -> 3036.562 | ... M9: =M5-M11 -> 3559.646
A10: porcentaje sobre ventas | B10: =B9/B5 -> #DIV/0! | C10: =C9/C5 -> 0.76963905 | D10: =D9/D5 -> 0.78192198 | E10: =E9/E5 -> 0.86762412 | F10: =F9/F5 -> 0.9055182 | G10: =G9/G5 -> 1.5129852 | H10: =H9/H5 -> 0.88156694 | I10: =I9/I5 -> 0.89683202 | ... M10: =M9/M5 -> 0.90949265
A11: Utilidad de Operación | C11: =Cifras_Originales!B8 -> 341.922 | D11: =Cifras_Originales!C8 -> 270.912 | E11: =Cifras_Originales!D8 -> 143.853 | F11: =Cifras_Originales!E8 -> 96.836 | G11: =Cifras_Originales!F8 -> -621.774 | H11: =Cifras_Originales!G8 -> 389.67 | I11: =Cifras_Originales!H8 -> 349.314 | J11: =Cifras_Originales!I8 -> 406.358 | ... M11: =Cifras_Originales!L8 -> 354.235
A12: porcentaje sobre ventas | B12: =B11/B5 -> #DIV/0! | C12: =C11/C5 -> 0.23036095 | D12: =D11/D5 -> 0.21807802 | E12: =E11/E5 -> 0.13237588 | F12: =F11/F5 -> 0.094481797 | G12: =G11/G5 -> -0.51298522 | H12: =H11/H5 -> 0.11843306 | I12: =I11/I5 -> 0.10316798 | ... M12: =M11/M5 -> 0.090507351
A13: Crecimiento vs año anterior | B13: =B11/C11-1 -> -1 | C13: =C11/D11-1 -> 0.26211464 | D13: =D11/E11-1 -> 0.88325582 | E13: =E11/F11-1 -> 0.48553224 | F13: =F11/G11-1 -> -1.1557415 | G13: =G11/H11-1 -> -2.5956425 | H13: =H11/I11-1 -> 0.11552929 | I13: =I11/J11-1 -> -0.14037868 | ... L13: =L11/M11-1 -> 0.20058153
A14: CIF (Productos Financieros) | C14: =Cifras_Originales!B9 -> 87.6 | D14: =Cifras_Originales!C9 -> 26.251 | E14: =Cifras_Originales!D9 -> 28.097 | F14: =Cifras_Originales!E9 -> 85.225 | G14: =Cifras_Originales!F9 -> 129.848 | H14: =Cifras_Originales!G9 -> 255.958 | I14: =Cifras_Originales!H9 -> 320.536 | J14: =Cifras_Originales!I9 -> 335.766 | ... M14: =Cifras_Originales!L9 -> 331.491
A15: Otros Gastos (Productos) | C15: =Cifras_Originales!B10 -> 8.9 | D15: =Cifras_Originales!C10 -> -9.5 | E15: =Cifras_Originales!D10 -> -222.3 | F15: =Cifras_Originales!E10 -> 755 | G15: =Cifras_Originales!F10 -> -1721.1 | H15: =Cifras_Originales!G10 -> -368.1 | I15: =Cifras_Originales!H10 -> 28.6 | J15: =Cifras_Originales!I10 -> -366.3 | ... M15: =Cifras_Originales!L10 -> 15.7
A16: Utilidad antes de Impuestos y partidas extra. | B16: =B11-B14-B15 -> 0 | C16: =C11-C14-C15 -> 245.422 | D16: =D11-D14-D15 -> 254.161 | E16: =E11-E14-E15 -> 338.056 | F16: =F11-F14-F15 -> -743.389 | G16: =G11-G14-G15 -> 969.478 | H16: =H11-H14-H15 -> 501.812 | I16: =I11-I14-I15 -> 0.178 | ... M16: =M11-M14-M15 -> 7.044
A17: Depreciación y amortización del ejercicio | C17: =Cifras_Originales!B11 -> 69.618 | D17: =Cifras_Originales!C11 -> 59.132 | E17: =Cifras_Originales!D11 -> 101.178 | F17: =Cifras_Originales!E11 -> 143.516 | G17: =Cifras_Originales!F11 -> 193.356 | H17: =Cifras_Originales!G11 -> 239.998 | I17: =Cifras_Originales!H11 -> 264.742 | J17: =Cifras_Originales!I11 -> 264.879 | ... M17: =Cifras_Originales!L11 -> 0
A18: Capital de Trabajo | C18: =Cifras_Originales!B12 -> -43.796 | D18: =Cifras_Originales!C12 -> -1.858 | E18: =Cifras_Originales!D12 -> -179.874 | F18: =Cifras_Originales!E12 -> -299.177 | G18: =Cifras_Originales!F12 -> -235.895 | H18: =Cifras_Originales!G12 -> -81.3 | I18: =Cifras_Originales!H12 -> -230.488 | J18: =Cifras_Originales!I12 -> -172.047 | ... M18: =Cifras_Originales!L12 -> -119.06
A19: EBITDA (flujo operativo) | B19: =B11-B15+B17 -> 0 | C19: =C11-C15+C17 -> 402.64 | D19: =D11-D15+D17 -> 339.544 | E19: =E11-E15+E17 -> 467.331 | F19: =F11-F15+F17 -> -514.648 | G19: =G11-G15+G17 -> 1292.682 | H19: =H11-H15+H17 -> 997.768 | I19: =I11-I15+I17 -> 585.456 | ... M19: =M11-M15+M17 -> 338.535
A20: porcentaje sobre ventas | B20: =B19/B5 -> #DIV/0! | C20: =C19/C5 -> 0.27126811 | D20: =D19/D5 -> 0.27332522 | E20: =E19/E5 -> 0.43004562 | F20: =F19/F5 -> -0.50213627 | G20: =G19/G5 -> 1.0665077 | H20: =H19/H5 -> 0.30325332 | I20: =I19/I5 -> 0.17291123 | ... M20: =M19/M5 -> 0.086495987
A21: I.S.R Y P.T.U. | C21: =Cifras_Originales!B15 -> 137.803 | D21: =Cifras_Originales!C15 -> 184.591 | E21: =Cifras_Originales!D15 -> 145.6 | F21: =Cifras_Originales!E15 -> -130.1 | G21: =Cifras_Originales!F15 -> 31.041 | H21: =Cifras_Originales!G15 -> 131.771 | I21: =Cifras_Originales!H15 -> -91.308 | J21: =Cifras_Originales!I15 -> 65.001 | ... M21: =Cifras_Originales!L15 -> 76.746
A22: % Tax | B22: =+B21/B16 -> #DIV/0! | C22: =+C21/C16 -> 0.56149408 | D22: =+D21/D16 -> 0.72627586 | E22: =+E21/E16 -> 0.43069787 | F22: =+F21/F16 -> 0.17500932 | G22: =+G21/G16 -> 0.032018261 | H22: =+H21/H16 -> 0.26259037 | I22: =+I21/I16 -> -512.96629 | ... M22: =+M21/M16 -> 10.89523
A23: Utilidad Neta | C23: =Cifras_Originales!B16 -> 107.59 | D23: =Cifras_Originales!C16 -> 69.573 | E23: =Cifras_Originales!D16 -> 192.446 | F23: =Cifras_Originales!E16 -> -613.331 | G23: =Cifras_Originales!F16 -> 938.484 | H23: =Cifras_Originales!G16 -> 370.067 | I23: =Cifras_Originales!H16 -> 91.465 | J23: =Cifras_Originales!I16 -> 371.847 | ... M23: =Cifras_Originales!L16 -> -69.7
A24: porcentaje sobre ventas | B24: =B23/B5 -> #DIV/0! | C24: =C23/C5 -> 0.072485933 | D24: =D23/D5 -> 0.056004688 | E24: =E23/E5 -> 0.17709195 | F24: =F23/F5 -> -0.59842016 | G24: =G23/G5 -> 0.77428201 | H24: =H23/H5 -> 0.11247509 | I24: =I23/I5 -> 0.027013689 | ... M24: =M23/M5 -> -0.017808411
A25: Crecimiento vs año anterior | B25: =B23/C23-1 -> -1 | C25: =C23/D23-1 -> 0.54643324 | D25: =D23/E23-1 -> -0.6384804 | E25: =E23/F23-1 -> -1.3137718 | F25: =F23/G23-1 -> -1.6535338 | G25: =G23/H23-1 -> 1.535984 | H25: =H23/I23-1 -> 3.0459957 | I25: =I23/J23-1 -> -0.75402518 | ... L25: =L23/M23-1 -> 1.271033
A26: Efectivo Generado | B26: =B40-C40 -> -85.167 | C26: =C40-D40 -> -239.634 | D26: =D40-E40 -> -425.346 | E26: =E40-F40 -> 688.571 | F26: =F40-G40 -> -326.914 | G26: =G40-H40 -> 67.923 | H26: =H40-I40 -> -144.398 | I26: =I40-J40 -> 6.292 | ... M26: =M40-N40 -> 0
A27: Dividendos | C27: =Cifras_Originales!B17 -> 0 | D27: =Cifras_Originales!C17 -> 0 | E27: =Cifras_Originales!D17 -> 0 | F27: =Cifras_Originales!E17 -> 0 | G27: =Cifras_Originales!F17 -> 0 | H27: =Cifras_Originales!G17 -> -11.103 | I27: =Cifras_Originales!H17 -> -19.371 | J27: =Cifras_Originales!I17 -> -2.159 | ... M27: =Cifras_Originales!L17 -> 0
B28: =B27/C27-1 -> #DIV/0! | C28: =C27/D27-1 -> #DIV/0! | D28: =D27/E27-1 -> #DIV/0! | E28: =E27/F27-1 -> #DIV/0! | F28: =F27/G27-1 -> #DIV/0! | G28: =G27/H27-1 -> -1 | H28: =H27/I27-1 -> -0.4268236 | I28: =I27/J27-1 -> 7.9722094 | ... L28: =L27/M27-1 -> #DIV/0!
A29: Recompra de Acciones | C29: =Cifras_Originales!B18 -> -112.478 | D29: =Cifras_Originales!C18 -> -535.339 | E29: =Cifras_Originales!D18 -> -380.505 | F29: =Cifras_Originales!E18 -> -264.03 | G29: =Cifras_Originales!F18 -> -99.253 | H29: =Cifras_Originales!G18 -> 0 | I29: =Cifras_Originales!H18 -> 0 | J29: =Cifras_Originales!I18 -> 0 | ... M29: =Cifras_Originales!L18 -> 0
A30: FNP | B30: =SUM(B26:B29) -> #DIV/0! | C30: =SUM(C26:C29) -> #DIV/0! | D30: =SUM(D26:D29) -> #DIV/0! | E30: =SUM(E26:E29) -> #DIV/0! | F30: =SUM(F26:F29) -> #DIV/0! | G30: =SUM(G26:G29) -> -32.33 | H30: =SUM(H26:H29) -> -155.92782 | I30: =SUM(I26:I29) -> -5.1067906 | ... M30: =SUM(M26:M29) -> 0
A31: FNP (ajustado por deuda) | B31: =B30-(B60-C60) -> #DIV/0! | C31: =C30-(C60-D60) -> #DIV/0! | D31: =D30-(D60-E60) -> #DIV/0! | E31: =E30-(E60-F60) -> #DIV/0! | F31: =F30-(F60-G60) -> #DIV/0! | G31: =G30-(G60-H60) -> 341.096 | H31: =H30-(H60-I60) -> 515.81418 | I31: =I30-(I60-J60) -> 861.04321 | ... M31: =M30-(M60-N60) -> 0
A32: FNP (ajustado por inversiones) | B32: =B31+B34 -> #DIV/0! | C32: =C31+C34 -> #DIV/0! | D32: =D31+D34 -> #DIV/0! | E32: =E31+E34 -> #DIV/0! | F32: =F31+F34 -> #DIV/0! | G32: =G31+G34 -> 339.891 | H32: =H31+H34 -> 498.79518 | I32: =I31+I34 -> 860.20821 | ... M32: =M31+M34 -> 0
A33: Capex | C33: =Cifras_Originales!B13 -> -51.898 | D33: =Cifras_Originales!C13 -> 30.658 | E33: =Cifras_Originales!D13 -> 2100.376 | F33: =Cifras_Originales!E13 -> 601.945 | G33: =Cifras_Originales!F13 -> 1110.401 | H33: =Cifras_Originales!G13 -> 137.761 | I33: =Cifras_Originales!H13 -> -264.232 | J33: =Cifras_Originales!I13 -> 314.183 | ... M33: =Cifras_Originales!L13 -> 0
A34: Inversiones | C34: =Cifras_Originales!B14 -> 0 | D34: =Cifras_Originales!C14 -> 0 | E34: =Cifras_Originales!D14 -> 0 | F34: =Cifras_Originales!E14 -> 0 | G34: =Cifras_Originales!F14 -> -1.205 | H34: =Cifras_Originales!G14 -> -17.019 | I34: =Cifras_Originales!H14 -> -0.835 | J34: =Cifras_Originales!I14 -> 0 | ... M34: =Cifras_Originales!L14 -> 0
A35: Capex + Inversiones | B35: =+B34+B33 -> 0 | C35: =+C34+C33 -> -51.898 | D35: =+D34+D33 -> 30.658 | E35: =+E34+E33 -> 2100.376 | F35: =+F34+F33 -> 601.945 | G35: =+G34+G33 -> 1109.196 | H35: =+H34+H33 -> 120.742 | I35: =+I34+I33 -> -265.067 | ... M35: =+M34+M33 -> 0
B36: =+B35/B5 -> #DIV/0! | C36: =+C35/C5 -> -0.034964912 | D36: =+D35/D5 -> 0.024678995 | E36: =+E35/E5 -> 1.9328003 | F36: =+F35/F5 -> 0.58731097 | G36: =+G35/G5 -> 0.91512536 | H36: =+H35/H5 -> 0.03669732 | I36: =+I35/I5 -> -0.078286092 | ... M36: =+M35/M5 -> 0
A37: Dividendos + Recompra de Acciones | B37: =SUM(B27:B29) -> #DIV/0! | C37: =SUM(C27:C29) -> #DIV/0! | D37: =SUM(D27:D29) -> #DIV/0! | E37: =SUM(E27:E29) -> #DIV/0! | F37: =SUM(F27:F29) -> #DIV/0! | G37: =SUM(G27:G29) -> -100.253 | H37: =SUM(H27:H29) -> -11.529824 | I37: =SUM(I27:I29) -> -11.398791 | ... M37: =SUM(M27:M29) -> 0
A39: Activo
A40: Caja | C40: =Cifras_Originales!B22 -> 85.167 | D40: =Cifras_Originales!C22 -> 324.801 | E40: =Cifras_Originales!D22 -> 750.147 | F40: =Cifras_Originales!E22 -> 61.576 | G40: =Cifras_Originales!F22 -> 388.49 | H40: =Cifras_Originales!G22 -> 320.567 | I40: =Cifras_Originales!H22 -> 464.965 | J40: =Cifras_Originales!I22 -> 458.673 | ... M40: =Cifras_Originales!L22 -> 0
A41: Cuentas y documentos por cobrar | C41: =Cifras_Originales!B23 -> 71.223 | D41: =Cifras_Originales!C23 -> 55.761 | E41: =Cifras_Originales!D23 -> 62.044 | F41: =Cifras_Originales!E23 -> 62.667 | G41: =Cifras_Originales!F23 -> 237.673 | H41: =Cifras_Originales!G23 -> 295.89 | I41: =Cifras_Originales!H23 -> 304.147 | J41: =Cifras_Originales!I23 -> 283.045 | ... M41: =Cifras_Originales!L23 -> 0
A42: Inventarios | C42: =Cifras_Originales!B24 -> 0 | D42: =Cifras_Originales!C24 -> 0 | E42: =Cifras_Originales!D24 -> 0 | F42: =Cifras_Originales!E24 -> 0 | G42: =Cifras_Originales!F24 -> 0 | H42: =Cifras_Originales!G24 -> 0 | I42: =Cifras_Originales!H24 -> 0 | J42: =Cifras_Originales!I24 -> 0 | ... M42: =Cifras_Originales!L24 -> 0
A43: Activos Fijos (Net Plant) | C43: =Cifras_Originales!B25 -> 912.972 | D43: =Cifras_Originales!C25 -> 883.861 | E43: =Cifras_Originales!D25 -> 1041.251 | F43: =Cifras_Originales!E25 -> 1162.394 | G43: =Cifras_Originales!F25 -> 1278.935 | H43: =Cifras_Originales!G25 -> 1380.417 | I43: =Cifras_Originales!H25 -> 2151.633 | J43: =Cifras_Originales!I25 -> 2290.9 | ... M43: =Cifras_Originales!L25 -> 0
A44: Otros Activos | B44: =B45-SUM(B40:B43) -> 0 | C44: =Cifras_Originales!B26 -> 902.875 | D44: =Cifras_Originales!C26 -> 946.887 | E44: =Cifras_Originales!D26 -> 3117.452 | F44: =Cifras_Originales!E26 -> 5209.786 | G44: =Cifras_Originales!F26 -> 4864.538 | H44: =Cifras_Originales!G26 -> 5394.411 | I44: =Cifras_Originales!H26 -> 4141.725 | J44: =Cifras_Originales!I26 -> 4406.498 | ... M44: =Cifras_Originales!L26 -> 0
A45: Total Activo | C45: =Cifras_Originales!B27 -> 1972.237 | D45: =Cifras_Originales!C27 -> 2211.31 | E45: =Cifras_Originales!D27 -> 4970.894 | F45: =Cifras_Originales!E27 -> 6496.423 | G45: =Cifras_Originales!F27 -> 6769.636 | H45: =Cifras_Originales!G27 -> 7391.285 | I45: =Cifras_Originales!H27 -> 7062.47 | J45: =Cifras_Originales!I27 -> 7439.116 | ... M45: =Cifras_Originales!L27 -> 0
A48: Pasivo
A49: Pasivo Corto Plazo | C49: =Cifras_Originales!B31 -> 381.387 | D49: =Cifras_Originales!C31 -> 371.928 | E49: =Cifras_Originales!D31 -> 804.555 | F49: =Cifras_Originales!E31 -> 1045.055 | G49: =Cifras_Originales!F31 -> 1190.087 | H49: =Cifras_Originales!G31 -> 1374.589 | I49: =Cifras_Originales!H31 -> 1440.232 | J49: =Cifras_Originales!I31 -> 0 | ... M49: =Cifras_Originales!L31 -> 0
A50: Deuda a corto plazo | C50: =Cifras_Originales!B32 -> 0 | D50: =Cifras_Originales!C32 -> 0 | E50: =Cifras_Originales!D32 -> 0 | F50: =Cifras_Originales!E32 -> 0 | G50: =Cifras_Originales!F32 -> 0 | H50: =Cifras_Originales!G32 -> 0 | I50: =Cifras_Originales!H32 -> 0 | J50: =Cifras_Originales!I32 -> 180.851 | ... M50: =Cifras_Originales!L32 -> 0
A51: Short-Term Leases | C51: =Cifras_Originales!B33 -> 45.167 | D51: =Cifras_Originales!C33 -> 43.407 | E51: =Cifras_Originales!D33 -> 50.061 | F51: =Cifras_Originales!E33 -> 44.353 | G51: =Cifras_Originales!F33 -> 6.385 | H51: =Cifras_Originales!G33 -> 0 | I51: =Cifras_Originales!H33 -> 15.763 | J51: =Cifras_Originales!I33 -> 11.503 | ... M51: =Cifras_Originales!L33 -> 0
A52: Otros Pasivos a Corto Plazo | C52: =Cifras_Originales!B34 -> 336.22 | D52: =Cifras_Originales!C34 -> 328.521 | E52: =Cifras_Originales!D34 -> 754.494 | F52: =Cifras_Originales!E34 -> 1000.702 | G52: =Cifras_Originales!F34 -> 1183.702 | H52: =Cifras_Originales!G34 -> 1374.589 | I52: =Cifras_Originales!H34 -> 1424.469 | J52: =Cifras_Originales!I34 -> -192.354 | ... M52: =Cifras_Originales!L34 -> 0
A53: Pasivo Largo Plazo | C53: =Cifras_Originales!B35 -> 815.095 | D53: =Cifras_Originales!C35 -> 698.11 | E53: =Cifras_Originales!D35 -> 1900.681 | F53: =Cifras_Originales!E35 -> 2634.922 | G53: =Cifras_Originales!F35 -> 3514.207 | H53: =Cifras_Originales!G35 -> 4015.417 | I53: =Cifras_Originales!H35 -> 0 | J53: =Cifras_Originales!I35 -> 0 | ... M53: =Cifras_Originales!L35 -> 0
A54: Deuda a largo plazo | C54: =Cifras_Originales!B36 -> 133.916 | D54: =Cifras_Originales!C36 -> 64.722 | E54: =Cifras_Originales!D36 -> 852.689 | F54: =Cifras_Originales!E36 -> 1077.514 | G54: =Cifras_Originales!F36 -> 2480.328 | H54: =Cifras_Originales!G36 -> 2973.396 | I54: =Cifras_Originales!H36 -> 3394.296 | J54: =Cifras_Originales!I36 -> 4083.181 | ... M54: =Cifras_Originales!L36 -> 0
A55: Long-Term Leases | C55: =Cifras_Originales!B37 -> 418.911 | D55: =Cifras_Originales!C37 -> 416.97 | E55: =Cifras_Originales!D37 -> 521.716 | F55: =Cifras_Originales!E37 -> 542.767 | G55: =Cifras_Originales!F37 -> 113.257 | H55: =Cifras_Originales!G37 -> 0 | I55: =Cifras_Originales!H37 -> 235.079 | J55: =Cifras_Originales!I37 -> 235.753 | ... M55: =Cifras_Originales!L37 -> 0
A56: Otros Pasivos a Largo Plazo | B56: =B53-SUM(B54:B55) -> 0 | C56: =Cifras_Originales!B38 -> 262.268 | D56: =Cifras_Originales!C38 -> 216.418 | E56: =Cifras_Originales!D38 -> 526.276 | F56: =Cifras_Originales!E38 -> 1014.641 | G56: =Cifras_Originales!F38 -> 920.622 | H56: =Cifras_Originales!G38 -> 1042.021 | I56: =Cifras_Originales!H38 -> -3629.375 | J56: =Cifras_Originales!I38 -> -4318.934 | ... M56: =Cifras_Originales!L38 -> 0
A57: Total pasivos | C57: =Cifras_Originales!B39 -> 1196.482 | D57: =Cifras_Originales!C39 -> 1070.038 | E57: =Cifras_Originales!D39 -> 2705.236 | F57: =Cifras_Originales!E39 -> 3679.977 | G57: =Cifras_Originales!F39 -> 4704.294 | H57: =Cifras_Originales!G39 -> 5390.006 | I57: =Cifras_Originales!H39 -> 1440.232 | J57: =Cifras_Originales!I39 -> 0 | ... M57: =Cifras_Originales!L39 -> 0
A59: Deuda Neta | B59: =B60-B40 -> 0 | C59: =C60-C40 -> 512.827 | D59: =D60-D40 -> 200.298 | E59: =E60-E40 -> 674.319 | F59: =F60-F40 -> 1603.058 | G59: =G60-G40 -> 2211.48 | H59: =H60-H40 -> 2652.829 | I59: =I60-I40 -> 3180.173 | ... M59: =M60-M40 -> 0
A60: Deuda | B60: =B50+B51+B54+B55 -> 0 | C60: =C50+C51+C54+C55 -> 597.994 | D60: =D50+D51+D54+D55 -> 525.099 | E60: =E50+E51+E54+E55 -> 1424.466 | F60: =F50+F51+F54+F55 -> 1664.634 | G60: =G50+G51+G54+G55 -> 2599.97 | H60: =H50+H51+H54+H55 -> 2973.396 | I60: =I50+I51+I54+I55 -> 3645.138 | ... M60: =M50+M51+M54+M55 -> 0
B61: =B60/B45 -> #DIV/0! | C61: =C60/C45 -> 0.30320595 | D61: =D60/D45 -> 0.2374606 | E61: =E60/E45 -> 0.28656133 | F61: =F60/F45 -> 0.25623855 | G61: =G60/G45 -> 0.38406349 | H61: =H60/H45 -> 0.40228404 | I61: =I60/I45 -> 0.51612793 | ... M61: =M60/M45 -> #DIV/0!
A63: Interés Minoritario | B63: 0 | C63: =Cifras_Originales!B42 -> 0 | D63: =Cifras_Originales!C42 -> 0 | E63: =Cifras_Originales!D42 -> 0 | F63: =Cifras_Originales!E42 -> 0 | G63: =Cifras_Originales!F42 -> 0 | H63: =Cifras_Originales!G42 -> 0 | I63: =Cifras_Originales!H42 -> 0 | J63: =Cifras_Originales!I42 -> 0 | ... M63: =Cifras_Originales!L42 -> 0
A66: Capital Contable | B66: =B45-B57-B63 -> 0 | C66: =C45-C57-C63 -> 775.755 | D66: =D45-D57-D63 -> 1141.272 | E66: =E45-E57-E63 -> 2265.658 | F66: =F45-F57-F63 -> 2816.446 | G66: =G45-G57-G63 -> 2065.342 | H66: =H45-H57-H63 -> 2001.279 | I66: =I45-I57-I63 -> 5622.238 | ... M66: =M45-M57-M63 -> 0
A69: OTROS DATOS AL FIN DE AÑO
A70: Numero deEmpleados | C70: =Cifras_Originales!B47 -> 4400 | D70: =Cifras_Originales!C47 -> 1800 | E70: =Cifras_Originales!D47 -> 3000 | F70: =Cifras_Originales!E47 -> 5000 | G70: =Cifras_Originales!F47 -> 6000 | H70: =Cifras_Originales!G47 -> 9000 | I70: =Cifras_Originales!H47 -> 9000 | J70: =Cifras_Originales!I47 -> 19900 | ... M70: =Cifras_Originales!L47 -> 0
A71: Acciones en circulación (millones) | C71: =+Cifras_Originales!B48 -> 157.37 | D71: =+Cifras_Originales!C48 -> 156 | E71: =+Cifras_Originales!D48 -> 181 | F71: =+Cifras_Originales!E48 -> 119 | G71: =+Cifras_Originales!F48 -> 127 | H71: =+Cifras_Originales!G48 -> 91 | I71: =+Cifras_Originales!H48 -> 55 | J71: =+Cifras_Originales!I48 -> 0 | ... M71: =+Cifras_Originales!L48 -> 0
A72: Float | C72: =Cifras_Originales!B49 -> 0.91439 | D72: =Cifras_Originales!C49 -> 0.9158 | E72: =Cifras_Originales!D49 -> 0.7641 | F72: =Cifras_Originales!E49 -> 0.9053 | G72: =Cifras_Originales!F49 -> 0.8903 | H72: =Cifras_Originales!G49 -> 0.84857 | I72: =Cifras_Originales!H49 -> 0.9307 | J72: =Cifras_Originales!I49 -> 0 | ... M72: =Cifras_Originales!L49 -> 0
A73: Insiders Own | C73: =Cifras_Originales!B50 -> 0.0232 | D73: =Cifras_Originales!C50 -> 0.022 | E73: =Cifras_Originales!D50 -> 0.0078 | F73: =Cifras_Originales!E50 -> 0.013 | G73: =Cifras_Originales!F50 -> 0.029 | H73: =Cifras_Originales!G50 -> 0.019 | I73: =Cifras_Originales!H50 -> 0.026 | J73: =Cifras_Originales!I50 -> 0 | ... M73: =Cifras_Originales!L50 -> 0
A74: S&P | C74: =+Cifras_Originales!B51 -> 0 | D74: =+Cifras_Originales!C51 -> 0 | E74: =+Cifras_Originales!D51 -> 0 | F74: =+Cifras_Originales!E51 -> 0 | G74: =+Cifras_Originales!F51 -> 0 | H74: =+Cifras_Originales!G51 -> 0 | I74: =+Cifras_Originales!H51 -> 0 | J74: =+Cifras_Originales!I51 -> 0 | ... M74: =+Cifras_Originales!L51 -> 0
A75: =Cifras_Originales!A52 -> Vol. Diario en Millones USD | C75: =Cifras_Originales!B52 -> 13203.2 | D75: =Cifras_Originales!C52 -> 27539.6 | E75: =Cifras_Originales!D52 -> 32727.3 | F75: =Cifras_Originales!E52 -> 11364.4 | G75: =Cifras_Originales!F52 -> 29945.9 | H75: =Cifras_Originales!G52 -> 26416.3 | I75: =Cifras_Originales!H52 -> 13758.5 | J75: =Cifras_Originales!I52 -> 0 | ... M75: =Cifras_Originales!L52 -> 0 | IH75: =Cifras_Originales!GM52 -> 0
B77: =+Cifras_Originales!B53 -> 2021 | C77: =+Cifras_Originales!C53 -> 2022 | D77: =+Cifras_Originales!D53 -> 2023
A78: =Cifras_Originales!A54 -> Posicion en Corto (%) | B78: =Cifras_Originales!B54 -> 0.00862
A79: =Cifras_Originales!A55 -> EPS | B79: =Cifras_Originales!B55 -> 1.01 | C79: =Cifras_Originales!C55 -> 0.42 | D79: =Cifras_Originales!D55 -> 0.68
A81: =+Cifras_Originales!A57 -> BONOS DE LA EMISORA A 3, 5 Y 10 | B81: Precio Medio | C81: Moody's | D81: YTM | E81: DIVISA
A82: =+Cifras_Originales!A58 -> 0 | B82: =+Cifras_Originales!B58 -> 0 | C82: =+Cifras_Originales!C58 -> 0 | D82: =+Cifras_Originales!D58 -> 0 | E82: =+Cifras_Originales!E58 -> 0
A83: =+Cifras_Originales!A59 -> 0 | B83: =+Cifras_Originales!B59 -> 0 | C83: =+Cifras_Originales!C59 -> 0 | D83: =+Cifras_Originales!D59 -> 0 | E83: =+Cifras_Originales!E59 -> 0
A84: =+Cifras_Originales!A60 -> 0 | B84: =+Cifras_Originales!B60 -> 0 | C84: =+Cifras_Originales!C60 -> 0 | D84: =+Cifras_Originales!D60 -> 0 | E84: =+Cifras_Originales!E60 -> 0
A85: =+Cifras_Originales!A61 -> 0 | B85: =+Cifras_Originales!B61 -> 0 | C85: =+Cifras_Originales!C61 -> 0 | D85: =+Cifras_Originales!D61 -> 0 | E85: =+Cifras_Originales!E61 -> 0

Sheet Q
B2: 3Q17 | C2: 3Q18 | D2: 4Q18 | E2: 1Q19 | F2: 2Q19 | G2: 3Q19 | H2: 4Q19 | I2: 1Q20 | J2: 2Q20 | K2: 3Q20 | L2: 4Q20 | M2: 1Q21 | N2: 2Q21 | O2: 3Q21 | P2: 4Q21 | Q2: 1Q22 | R2: 2Q22 | S2: 3Q22 | T2: 4Q22 | U2: 1Q23 | V2: 2Q23 | W2: 3Q23 | X2: 4Q23e | Z2: 2019 | AA2: 2020 | AB2: 2021 | AC2: 2022 | AD2: 2023 | AE2: 2024 | AF2: 2025 | AG2: 2026 | AH2: 2027 | AI2: 2028 | AJ2: 2029 | AK2: 2030 | AL2: 2031 | AM2: 2032 | AN2: 2033 | AO2: 2034 | AP2: 2035 | AQ2: 2036 | AR2: 2037 | AS2: 2038 | AT2: 2039 | AU2: 2040 | AV2: 2041 | AW2: 2042 | AX2: 2043 | AY2: 2044 | AZ2: 2045 | BA2: 2046 | BB2: 2047
A3: Shares
A4: Growth
A5: Prods | AE5: 0.045 | AF5: =0.987*AE5 -> 0.044415 | AG5: =0.987*AF5 -> 0.043837605 | AH5: =0.987*AG5 -> 0.043267716 | AI5: =0.987*AH5 -> 0.042705236 | AJ5: =0.987*AI5 -> 0.042150068 | AK5: =0.987*AJ5 -> 0.041602117 | AL5: =0.987*AK5 -> 0.041061289 | AM5: =0.987*AL5 -> 0.040527493 | ... BB5: =0.987*BA5 -> 0.033304815
A6: Serv | AE6: 0.09 | AF6: =AE6*0.975 -> 0.08775 | AG6: =AF6*0.975 -> 0.08555625 | AH6: =AG6*0.975 -> 0.083417344 | AI6: =AH6*0.975 -> 0.08133191 | AJ6: =AI6*0.975 -> 0.079298612 | AK6: =AJ6*0.975 -> 0.077316147 | AL6: =AK6*0.975 -> 0.075383243 | AM6: =AL6*0.975 -> 0.073498662 | ... BB6: =BA6*0.975 -> 0.050274605
A8: COGS
A9: Prods | Z9: =Z30/Z26 -> 0.67792204 | AA9: =AA30/AA26 -> 0.68533661 | AB9: =AB30/AB26 -> 0.64650697 | AC9: =AC30/AC26 -> 0.6371652 | AD9: =AD30/AD26 -> 0.6358648 | AE9: =AD9*1.001 -> 0.63650067 | AF9: =AE9*1.001 -> 0.63713717 | AG9: =AF9*1.001 -> 0.6377743 | AH9: =AG9*1.001 -> 0.63841208 | AI9: =AH9*1.001 -> 0.63905049 | AJ9: =AI9*1.001 -> 0.63968954 | AK9: =AJ9*1.001 -> 0.64032923 | AL9: =AK9*1.001 -> 0.64096956 | ... BB9: =BA9*1.001 -> 0.65130235
A10: Serv | Z10: =Z31/Z27 -> 0.36261908 | AA10: =AA31/AA27 -> 0.33984898 | AB10: =AB31/AB27 -> 0.30274023 | AC10: =AC31/AC27 -> 0.28254553 | AD10: =AD31/AD27 -> 0.29105249 | AE10: =AD10*1.001 -> 0.29134354 | AF10: =AE10*1.001 -> 0.29163488 | AG10: =AF10*1.001 -> 0.29192652 | AH10: =AG10*1.001 -> 0.29221845 | AI10: =AH10*1.001 -> 0.29251066 | AJ10: =AI10*1.001 -> 0.29280317 | AK10: =AJ10*1.001 -> 0.29309598 | AL10: =AK10*1.001 -> 0.29338907 | ... BB10: =BA10*1.001 -> 0.29811867
A12: R&D | Z12: =Z33/Z25 -> 0.062331363 | AA12: =AA33/AA25 -> 0.068309564 | AB12: =AB33/AB25 -> 0.059904269 | AC12: =AC33/AC25 -> 0.066571484 | AD12: =AD33/AD25 -> 0.078317483 | AE12: =1.01*AD12 -> 0.079100658 | AF12: =1.01*AE12 -> 0.079891665 | AG12: =1.01*AF12 -> 0.080690581 | AH12: =1.01*AG12 -> 0.081497487 | AI12: =1.01*AH12 -> 0.082312462 | AJ12: =1.01*AI12 -> 0.083135587 | AK12: =1.01*AJ12 -> 0.083966943 | AL12: =1.01*AK12 -> 0.084806612 | ... BB12: =1.01*BA12 -> 0.099442422
A13: SGA | Z13: =Z34/Z25 -> 0.070126146 | AA13: =AA34/AA25 -> 0.07254977 | AB13: =AB34/AB25 -> 0.060065552 | AC13: =AC34/AC25 -> 0.063637378 | AD13: =AD34/AD25 -> 0.065265004 | AE13: =AD13*1.001 -> 0.065330269 | AF13: =AE13*1.001 -> 0.0653956 | AG13: =AF13*1.001 -> 0.065460995 | AH13: =AG13*1.001 -> 0.065526456 | AI13: =AH13*1.001 -> 0.065591983 | AJ13: =AI13*1.001 -> 0.065657575 | AK13: =AJ13*1.001 -> 0.065723232 | AL13: =AK13*1.001 -> 0.065788956 | ... BB13: =BA13*1.001 -> 0.066849511
A15: Utiilidad oP
A17: Tax Rate | Z17: =Z41/Z40 -> 0.15943837 | AA17: =AA41/AA40 -> 0.14428165 | AB17: =AB41/AB40 -> 0.13302261 | AC17: =AC41/AC40 -> 0.16204462
A19: DA | Z19: =Z52/Z25 -> 0.048225418 | AA19: =AA52/AA25 -> 0.040274666 | AB19: =AB52/AB25 -> 0.030846024 | AC19: =AC52/AC25 -> 0.028159299
A20: SBC | Z20: =Z53/Z25 -> 0.023322853 | AA20: =AA53/AA25 -> 0.024876601 | AB20: =AB53/AB25 -> 0.021611899 | AC20: =AC53/AC25 -> 0.022920006
A21: Net SBC | U21: =((W25+V25)/(R25+S25))-1 -> -0.019995894 | Z21: =(Z53+Z54)/Z25 -> 0.031148385 | AA21: =(AA53+AA54)/AA25 -> 0.034908839 | AB21: =(AB53+AB54)/AB25 -> 0.039533428 | AC21: =(AC53+AC54)/AC25 -> 0.038701284
A22: Capex | U22: =((W25+V25)/(F25+G25))-1 -> 0.57956253 | Z22: =Z55/Z25 -> 0.040338389 | AA22: =AA55/AA25 -> 0.026625139 | AB22: =AB55/AB25 -> 0.030302036 | AC22: =AC55/AC25 -> 0.027155059
A23: Net SBC Factor | Z23: =Z21/Z20 -> 1.3355307 | AA23: =AA21/AA20 -> 1.4032801 | AB23: =AB21/AB20 -> 1.8292436 | AC23: =AC21/AC20 -> 1.6885373
A25: Revenue | C25: =C26+C27 -> 53265 | D25: =D26+D27 -> 64040 | E25: =E26+E27 -> 84310 | F25: =F26+F27 -> 58015 | G25: =G26+G27 -> 53809 | H25: =H26+H27 -> 64040 | I25: =I26+I27 -> 91819 | J25: =J26+J27 -> 58313 | ... X25: =X26+X27 -> 89282 | Z25: =Z26+Z27 -> 260174 | AA25: =AA26+AA27 -> 274515 | AB25: =AB26+AB27 -> 365817 | AC25: =AC26+AC27 -> 394328 | AD25: =AD26+AD27 -> 383069 | AE25: =AE26+AE27 -> 404095.7 | AF25: =AF26+AF27 -> 426020.39 | AG25: =AG26+AG27 -> 448860.49 | ... BB25: =BB26+BB27 -> 1156800
A26: -Products | C26: 43095 | D26: 51529 | E26: 73435 | F26: 46565 | G26: 42354 | H26: 51529 | I26: 79104 | J26: 44965 | K26: 46529 | L26: 50149 | M26: 95678 | N26: 72683 | O26: 63948 | P26: 65083 | Q26: 104429 | R26: 77457 | S26: 63355 | T26: 70958 | U26: 96388 | V26: 73929 | W26: 60584 | X26: 67977 | Z26: =SUM(E26:H26) -> 213883 | AA26: =SUM(I26:L26) -> 220747 | AB26: =SUM(M26:P26) -> 297392 | AC26: =SUM(Q26:T26) -> 316199 | AD26: =SUM(U26:X26) -> 298878 | AE26: =(1+AE5)*AD26 -> 312327.51 | AF26: =(1+AF5)*AE26 -> 326199.54 | AG26: =(1+AG5)*AF26 -> 340499.34 | AH26: =(1+AH5)*AG26 -> 355231.97 | AI26: =(1+AI5)*AH26 -> 370402.24 | AJ26: =(1+AJ5)*AI26 -> 386014.72 | AK26: =(1+AK5)*AJ26 -> 402073.75 | AL26: =(1+AL5)*AK26 -> 418583.41 | ... BB26: =(1+BB5)*BA26 -> 746321.37
A27: -Services | C27: 10170 | D27: 12511 | E27: 10875 | F27: 11450 | G27: 11455 | H27: 12511 | I27: 12715 | J27: 13348 | K27: 13156 | L27: 14549 | M27: 15761 | N27: 16901 | O27: 17486 | P27: 18277 | Q27: 19516 | R27: 19821 | S27: 19604 | T27: 19188 | U27: 20766 | V27: 20907 | W27: 21213 | X27: 21305 | Z27: =SUM(E27:H27) -> 46291 | AA27: =SUM(I27:L27) -> 53768 | AB27: =SUM(M27:P27) -> 68425 | AC27: =SUM(Q27:T27) -> 78129 | AD27: =SUM(U27:X27) -> 84191 | AE27: =(1+AE6)*AD27 -> 91768.19 | AF27: =(1+AF6)*AE27 -> 99820.849 | AG27: =(1+AG6)*AF27 -> 108361.15 | AH27: =(1+AH6)*AG27 -> 117400.35 | AI27: =(1+AI6)*AH27 -> 126948.74 | AJ27: =(1+AJ6)*AI27 -> 137015.6 | AK27: =(1+AK6)*AJ27 -> 147609.12 | AL27: =(1+AL6)*AK27 -> 158736.37 | ... BB27: =(1+BB6)*BA27 -> 410478.6
A29: COGS
A30: -Products | C30: 28956 | D30: 35238 | E30: 48238 | F30: 32047 | G30: 29473 | H30: 35238 | I30: 52075 | J30: 31321 | K30: 32693 | L30: 35197 | M30: 62130 | N30: 46447 | O30: 40899 | P30: 42790 | Q30: 64309 | R30: 49290 | S30: 41485 | T30: 46387 | U30: 60765 | V30: 46795 | W30: 39136 | X30: 43350 | Z30: =SUM(E30:H30) -> 144996 | AA30: =SUM(I30:L30) -> 151286 | AB30: =SUM(M30:P30) -> 192266 | AC30: =SUM(Q30:T30) -> 201471 | AD30: =SUM(U30:X30) -> 190046 | AE30: =AE9*AE26 -> 198796.67 | AF30: =AF9*AF26 -> 207833.85 | AG30: =AG9*AG26 -> 217161.73 | AH30: =AH9*AH26 -> 226784.38 | AI30: =AI9*AI26 -> 236705.73 | AJ30: =AJ9*AJ26 -> 246929.58 | AK30: =AK9*AK26 -> 257459.57 | AL30: =AL9*AL26 -> 268299.23 | ... BB30: =BB9*BB26 -> 486080.86
A31: -Services | C31: 3888 | D31: 4489 | E31: 4041 | F31: 4147 | G31: 4109 | H31: 4489 | I31: 4527 | J31: 4622 | K31: 4312 | L31: 4812 | M31: 4981 | N31: 5058 | O31: 5280 | P31: 5396 | Q31: 5393 | R31: 5429 | S31: 5589 | T31: 5664 | U31: 6057 | V31: 6065 | W31: 6248 | X31: 6134 | Z31: =SUM(E31:H31) -> 16786 | AA31: =SUM(I31:L31) -> 18273 | AB31: =SUM(M31:P31) -> 20715 | AC31: =SUM(Q31:T31) -> 22075 | AD31: =SUM(U31:X31) -> 24504 | AE31: =AE10*AE27 -> 26736.069 | AF31: =AF10*AF27 -> 29111.242 | AG31: =AG10*AG27 -> 31633.492 | AH31: =AH10*AH27 -> 34306.546 | AI31: =AI10*AI27 -> 37133.86 | AJ31: =AJ10*AJ27 -> 40118.602 | AK31: =AK10*AK27 -> 43263.638 | AL31: =AL10*AL27 -> 46571.517 | ... BB31: =BB10*BB27 -> 122371.34
A33: R&D | C33: 3701 | D33: 4110 | E33: 3902 | F33: 3948 | G33: 4257 | H33: 4110 | I33: 4451 | J33: 4565 | K33: 4758 | L33: 4978 | M33: 5163 | N33: 5262 | O33: 5717 | P33: 5772 | Q33: 6306 | R33: 6387 | S33: 6797 | T33: 6761 | U33: 7709 | V33: 7457 | W33: 7442 | X33: 7393 | Z33: =SUM(E33:H33) -> 16217 | AA33: =SUM(I33:L33) -> 18752 | AB33: =SUM(M33:P33) -> 21914 | AC33: =SUM(Q33:T33) -> 26251 | AD33: =SUM(U33:X33) -> 30001 | AE33: =AE12*AE$25 -> 31964.236 | AF33: =AF12*AF$25 -> 34035.478 | AG33: =AG12*AG$25 -> 36218.814 | AH33: =AH12*AH$25 -> 38518.346 | AI33: =AI12*AI$25 -> 40938.183 | AJ33: =AJ12*AJ$25 -> 43482.432 | AK33: =AK12*AK$25 -> 46155.189 | AL33: =AL12*AL$25 -> 48960.535 | ... BB33: =BB12*BB$25 -> 115034.99
A34: SGA | C34: 4108 | D34: 4578 | E34: 4783 | F34: 4458 | G34: 4426 | H34: 4578 | I34: 5197 | J34: 4952 | K34: 4831 | L34: 4936 | M34: 5631 | N34: 5314 | O34: 5412 | P34: 5616 | Q34: 6449 | R34: 6193 | S34: 6012 | T34: 6440 | U34: 6607 | V34: 6201 | W34: 5973 | X34: 6220 | Z34: =SUM(E34:H34) -> 18245 | AA34: =SUM(I34:L34) -> 19916 | AB34: =SUM(M34:P34) -> 21973 | AC34: =SUM(Q34:T34) -> 25094 | AD34: =SUM(U34:X34) -> 25001 | AE34: =AE13*AE$25 -> 26399.681 | AF34: =AF13*AF$25 -> 27859.859 | AG34: =AG13*AG$25 -> 29382.854 | AH34: =AH13*AH$25 -> 30969.921 | AI34: =AI13*AI$25 -> 32622.237 | AJ34: =AJ13*AJ$25 -> 34340.902 | AK34: =AK13*AK$25 -> 36126.934 | AL34: =AL13*AL$25 -> 37981.266 | ... BB34: =BB13*BB$25 -> 77331.512
A36: Ut OP | C36: =C25-C30-C31-C33-C34 -> 12612 | D36: =D25-D30-D31-D33-D34 -> 15625 | E36: =E25-E30-E31-E33-E34 -> 23346 | F36: =F25-F30-F31-F33-F34 -> 13415 | G36: =G25-G30-G31-G33-G34 -> 11544 | H36: =H25-H30-H31-H33-H34 -> 15625 | I36: =I25-I30-I31-I33-I34 -> 25569 | J36: =J25-J30-J31-J33-J34 -> 12853 | ... X36: =X25-X30-X31-X33-X34 -> 26185 | Z36: =Z25-Z30-Z31-Z33-Z34 -> 63930 | AA36: =AA25-AA30-AA31-AA33-AA34 -> 66288 | AB36: =AB25-AB30-AB31-AB33-AB34 -> 108949 | AC36: =AC25-AC30-AC31-AC33-AC34 -> 119437 | AD36: =AD25-AD30-AD31-AD33-AD34 -> 113517 | AE36: =AE25-AE30-AE31-AE33-AE34 -> 120199.05 | AF36: =AF25-AF30-AF31-AF33-AF34 -> 127179.96 | AG36: =AG25-AG30-AG31-AG33-AG34 -> 134463.6 | ... BB36: =BB25-BB30-BB31-BB33-BB34 -> 355981.27
A38: Other | C38: 672 | D38: 502 | E38: 560 | F38: 378 | G38: 367 | H38: 502 | I38: 349 | J38: 282 | K38: 46 | L38: 126 | M38: 45 | N38: 508 | O38: 243 | P38: -538 | Q38: -247 | R38: 160 | S38: -10 | T38: -237 | U38: -393 | V38: 64 | W38: -265 | Z38: =SUM(E38:H38) -> 1807 | AA38: =SUM(I38:L38) -> 803 | AB38: =SUM(M38:P38) -> 258 | AC38: =SUM(Q38:T38) -> -334
A40: efore tax | C40: =C26+C27-C30-C31-C33-C34+C38 -> 13284 | D40: =D26+D27-D30-D31-D33-D34+D38 -> 16127 | E40: =E26+E27-E30-E31-E33-E34+E38 -> 23906 | F40: =F26+F27-F30-F31-F33-F34+F38 -> 13793 | G40: =G26+G27-G30-G31-G33-G34+G38 -> 11911 | H40: =H26+H27-H30-H31-H33-H34+H38 -> 16127 | I40: =I26+I27-I30-I31-I33-I34+I38 -> 25918 | J40: =J26+J27-J30-J31-J33-J34+J38 -> 13135 | ... W40: =W26+W27-W30-W31-W33-W34+W38 -> 22733 | Z40: =SUM(E40:H40) -> 65737 | AA40: =SUM(I40:L40) -> 67091 | AB40: =SUM(M40:P40) -> 109207 | AC40: =SUM(Q40:T40) -> 119103
A41: Tax | C41: 1765 | D41: 2441 | E41: 3941 | F41: 2232 | G41: 1867 | H41: 2441 | I41: 3682 | J41: 1886 | K41: 1884 | L41: 2228 | M41: 4824 | N41: 4381 | O41: 2625 | P41: 2697 | Q41: 6611 | R41: 5129 | S41: 3624 | T41: 3936 | U41: 5625 | V41: 4222 | W41: 2852 | Z41: =SUM(E41:H41) -> 10481 | AA41: =SUM(I41:L41) -> 9680 | AB41: =SUM(M41:P41) -> 14527 | AC41: =SUM(Q41:T41) -> 19300
A42: NI | C42: =C40-C41 -> 11519 | D42: =D40-D41 -> 13686 | E42: =E40-E41 -> 19965 | F42: =F40-F41 -> 11561 | G42: =G40-G41 -> 10044 | H42: =H40-H41 -> 13686 | I42: =I40-I41 -> 22236 | J42: =J40-J41 -> 11249 | ... W42: =W40-W41 -> 19881
A45: DA | E45: 3395 | F45: 6435 | G45: 9368 | H45: 12547 | I45: 2816 | J45: 5602 | K45: 8354 | L45: 11056 | M45: 2666 | N45: 5463 | O45: 8295 | P45: 11284 | Q45: 2697 | R45: 5434 | S45: 8239 | T45: 11104 | U45: 2916 | V45: 5814 | W45: 8866
A46: SBC | E46: 1559 | F46: 3073 | G46: 4569 | H46: 6068 | I46: 1710 | J46: 3407 | K46: 5105 | L46: 6829 | M46: 2020 | N46: 4001 | O46: 5961 | P46: 7906 | Q46: 2265 | R46: 4517 | S46: 6760 | T46: 9038 | U46: 2905 | V46: 5591 | W46: 8208
A47: Other SBC | E47: 1318 | F47: 1037 | G47: 2325 | H47: 2036 | I47: 1377 | J47: 1136 | K47: 2804 | L47: 2754 | M47: 2861 | N47: 3160 | O47: 5855 | P47: 6556 | Q47: 2888 | R47: 3218 | S47: 5915 | T47: 6223 | U47: 2316 | V47: 2734 | W47: 5119
A48: Capex | E48: 3355 | F48: 5718 | G48: 7718 | H48: 10495 | I48: 2107 | J48: 3960 | K48: 5525 | L48: 7309 | M48: 3500 | N48: 5769 | O48: 7862 | P48: 11085 | Q48: 2803 | R48: 5317 | S48: 7419 | T48: 10708 | U48: 3787 | V48: 6703 | W48: 8796
A49: Divs | E49: 3568 | F49: 7011 | G49: 10640 | H49: 14119 | I49: 3539 | J49: 6914 | K49: 10570 | L49: 14081 | M49: 3613 | N49: 7060 | O49: 10827 | P49: 14467 | Q49: 3732 | R49: 7327 | S49: 11138 | T49: 14841 | U49: 3768 | V49: 7418 | W49: 11267
A50: Repurch | E50: 8796 | F50: 32498 | G50: 49463 | H50: 66897 | I50: 20706 | J50: 39280 | K50: 55171 | L50: 72358 | M50: 24775 | N50: 43323 | O50: 66223 | P50: 85971 | Q50: 20478 | R50: 43109 | S50: 64974 | T50: 89402 | U50: 19475 | V50: 39069 | W50: 56547
A52: DA | E52: =E45 -> 3395 | F52: =F45-E45 -> 3040 | G52: =G45-F45 -> 2933 | H52: =H45-G45 -> 3179 | I52: =I45 -> 2816 | J52: =J45-I45 -> 2786 | K52: =K45-J45 -> 2752 | L52: =L45-K45 -> 2702 | M52: =M45 -> 2666 | N52: =N45-M45 -> 2797 | O52: =O45-N45 -> 2832 | P52: =P45-O45 -> 2989 | Q52: =Q45 -> 2697 | R52: =R45-Q45 -> 2737 | S52: =S45-R45 -> 2805 | T52: =T45-S45 -> 2865 | U52: =U45 -> 2916 | V52: =V45-U45 -> 2898 | W52: =W45-V45 -> 3052 | X52: 3262 | Z52: =SUM(E52:H52) -> 12547 | AA52: =SUM(I52:L52) -> 11056 | AB52: =SUM(M52:P52) -> 11284 | AC52: =SUM(Q52:T52) -> 11104
A53: SBC | E53: =E46 -> 1559 | F53: =F46-E46 -> 1514 | G53: =G46-F46 -> 1496 | H53: =H46-G46 -> 1499 | I53: =I46 -> 1710 | J53: =J46-I46 -> 1697 | K53: =K46-J46 -> 1698 | L53: =L46-K46 -> 1724 | M53: =M46 -> 2020 | N53: =N46-M46 -> 1981 | O53: =O46-N46 -> 1960 | P53: =P46-O46 -> 1945 | Q53: =Q46 -> 2265 | R53: =R46-Q46 -> 2252 | S53: =S46-R46 -> 2243 | T53: =T46-S46 -> 2278 | U53: =U46 -> 2905 | V53: =V46-U46 -> 2686 | W53: =W46-V46 -> 2617 | Z53: =SUM(E53:H53) -> 6068 | AA53: =SUM(I53:L53) -> 6829 | AB53: =SUM(M53:P53) -> 7906 | AC53: =SUM(Q53:T53) -> 9038
A54: Other SBC | E54: =E47 -> 1318 | F54: =F47-E47 -> -281 | G54: =G47-F47 -> 1288 | H54: =H47-G47 -> -289 | I54: =I47 -> 1377 | J54: =J47-I47 -> -241 | K54: =K47-J47 -> 1668 | L54: =L47-K47 -> -50 | M54: =M47 -> 2861 | N54: =N47-M47 -> 299 | O54: =O47-N47 -> 2695 | P54: =P47-O47 -> 701 | Q54: =Q47 -> 2888 | R54: =R47-Q47 -> 330 | S54: =S47-R47 -> 2697 | T54: =T47-S47 -> 308 | U54: =U47 -> 2316 | V54: =V47-U47 -> 418 | W54: =W47-V47 -> 2385 | Z54: =SUM(E54:H54) -> 2036 | AA54: =SUM(I54:L54) -> 2754 | AB54: =SUM(M54:P54) -> 6556 | AC54: =SUM(Q54:T54) -> 6223
A55: Capex | E55: =E48 -> 3355 | F55: =F48-E48 -> 2363 | G55: =G48-F48 -> 2000 | H55: =H48-G48 -> 2777 | I55: =I48 -> 2107 | J55: =J48-I48 -> 1853 | K55: =K48-J48 -> 1565 | L55: =L48-K48 -> 1784 | M55: =M48 -> 3500 | N55: =N48-M48 -> 2269 | O55: =O48-N48 -> 2093 | P55: =P48-O48 -> 3223 | Q55: =Q48 -> 2803 | R55: =R48-Q48 -> 2514 | S55: =S48-R48 -> 2102 | T55: =T48-S48 -> 3289 | U55: =U48 -> 3787 | V55: =V48-U48 -> 2916 | W55: =W48-V48 -> 2093 | Z55: =SUM(E55:H55) -> 10495 | AA55: =SUM(I55:L55) -> 7309 | AB55: =SUM(M55:P55) -> 11085 | AC55: =SUM(Q55:T55) -> 10708
A56: Divs | E56: =E49 -> 3568 | F56: =F49-E49 -> 3443 | G56: =G49-F49 -> 3629 | H56: =H49-G49 -> 3479 | I56: =I49 -> 3539 | J56: =J49-I49 -> 3375 | K56: =K49-J49 -> 3656 | L56: =L49-K49 -> 3511 | M56: =M49 -> 3613 | N56: =N49-M49 -> 3447 | O56: =O49-N49 -> 3767 | P56: =P49-O49 -> 3640 | Q56: =Q49 -> 3732 | R56: =R49-Q49 -> 3595 | S56: =S49-R49 -> 3811 | T56: =T49-S49 -> 3703 | U56: =U49 -> 3768 | V56: =V49-U49 -> 3650 | W56: =W49-V49 -> 3849 | Z56: =SUM(E56:H56) -> 14119 | AA56: =SUM(I56:L56) -> 14081 | AB56: =SUM(M56:P56) -> 14467 | AC56: =SUM(Q56:T56) -> 14841
A57: Repurch | E57: =E50 -> 8796 | F57: =F50-E50 -> 23702 | G57: =G50-F50 -> 16965 | H57: =H50-G50 -> 17434 | I57: =I50 -> 20706 | J57: =J50-I50 -> 18574 | K57: =K50-J50 -> 15891 | L57: =L50-K50 -> 17187 | M57: =M50 -> 24775 | N57: =N50-M50 -> 18548 | O57: =O50-N50 -> 22900 | P57: =P50-O50 -> 19748 | Q57: =Q50 -> 20478 | R57: =R50-Q50 -> 22631 | S57: =S50-R50 -> 21865 | T57: =T50-S50 -> 24428 | U57: =U50 -> 19475 | V57: =V50-U50 -> 19594 | W57: =W50-V50 -> 17478 | Z57: =SUM(E57:H57) -> 66897 | AA57: =SUM(I57:L57) -> 72358 | AB57: =SUM(M57:P57) -> 85971 | AC57: =SUM(Q57:T57) -> 89402
J63: -1

Sheet Cifras_Originales
A1: USD
A2: Millones | C2: Cifras en Millones de USD
A3: #VALUE! | G3: #VALUE!
A4: {=_FV(A3,"Símbolo do ticker",TRUE)} -> LAUR
A5: RESULTADOS | B5: 2023 | C5: 2022 | D5: 2021 | E5: 2020 | F5: 2019 | G5: 2018 | H5: 2017 | I5: 2016 | J5: 2015 | K5: 2014 | L5: 2013 | M5: 2012
A6: Ventas Netas | B6: 1484.288 | C6: 1242.271 | D6: 1086.701 | E6: 1024.917 | F6: 1212.07 | G6: 3290.213 | H6: 3385.876 | I6: 4244.192 | J6: 4291.659 | K6: 4414.682 | L6: 3913.881 | M6: 3567.117
A7: Utilidad Bruta | B7: 394.507 | C7: 334.906 | D7: 272.211 | E7: 222.459 | F7: 262.599 | G7: 593.164 | H7: 564.585 | I7: 628.854 | J7: 531.643 | K7: 576.503 | L7: 495.432 | M7: 418.587
A8: Utilidad de Operación | B8: 341.922 | C8: 270.912 | D8: 143.853 | E8: 96.836 | F8: -621.774 | G8: 389.67 | H8: 349.314 | I8: 406.358 | J8: 336.957 | K8: 425.288 | L8: 354.235 | M8: 308.509
A9: CIF (Poductos) | B9: 87.6 | C9: 26.251 | D9: 28.097 | E9: 85.225 | F9: 129.848 | G9: 255.958 | H9: 320.536 | I9: 335.766 | J9: 533.914 | K9: 473.932 | L9: 331.491 | M9: 273.861 | S9: =C5 -> 2022 | T9: =D5 -> 2021 | U9: =E5 -> 2020 | V9: =F5 -> 2019 | W9: =G5 -> 2018 | X9: =H5 -> 2017 | Y9: =I5 -> 2016 | Z9: =J5 -> 2015 | ... AB9: =L5 -> 2013
A10: Otros Gastos (Ingresos) | B10: 8.9 | C10: -9.5 | D10: -222.3 | E10: 755 | F10: -1721.1 | G10: -368.1 | H10: 28.6 | I10: -366.3 | J10: 1.6 | K10: 148.7 | L10: 15.7 | M10: 167.6 | R10: Inventories | S10: =C24 -> 0 | T10: =D24 -> 0 | U10: =E24 -> 0 | V10: =F24 -> 0 | W10: =G24 -> 0 | X10: =H24 -> 0 | Y10: =I24 -> 0 | Z10: =J24 -> 1.828 | ... AC10: =M24 -> -
A11: Depreciación y amortización | B11: 69.618 | C11: 59.132 | D11: 101.178 | E11: 143.516 | F11: 193.356 | G11: 239.998 | H11: 264.742 | I11: 264.879 | J11: 282.946 | K11: 288.331 | L11: 0 | M11: 221.235 | R11: Por cobrar | S11: =C23 -> 55.761 | T11: =D23 -> 62.044 | U11: =E23 -> 62.667 | V11: =F23 -> 237.673 | W11: =G23 -> 295.89 | X11: =H23 -> 304.147 | Y11: =I23 -> 283.045 | Z11: =J23 -> 287.745 | ... AC11: =M23 -> -
A12: Capital de Trabajo | B12: -43.796 | C12: -1.858 | D12: -179.874 | E12: -299.177 | F12: -235.895 | G12: -81.3 | H12: -230.488 | I12: -172.047 | J12: -212.582 | K12: -130.705 | L12: -119.06 | M12: -48.934 | R12: Por pagar
A13: Capex | B13: -51.898 | C13: 30.658 | D13: 2100.376 | E13: 601.945 | F13: 1110.401 | G13: 137.761 | H13: -264.232 | I13: 314.183 | J13: -139.98 | K13: -412.181 | L13: 0 | M13: 0
A14: Inversiones | B14: 0 | C14: 0 | D14: 0 | E14: 0 | F14: -1.205 | G14: -17.019 | H14: -0.835 | I14: 0 | J14: -7.98 | K14: -287.945 | L14: 0 | M14: 0 | S14: =(S10-T10) -> 0 | T14: =(T10-U10) -> 0 | U14: =(U10-V10) -> 0 | V14: =(V10-W10) -> 0 | W14: =(W10-X10) -> 0 | X14: =(X10-Y10) -> 0 | Y14: =(Y10-Z10) -> -1.828 | Z14: =(Z10-AA10) -> -1.532 | ... AB14: =(AB10-AC10) -> #VALUE!
A15: I.S.R Y P.T.U. | B15: 137.803 | C15: 184.591 | D15: 145.6 | E15: -130.1 | F15: 31.041 | G15: 131.771 | H15: -91.308 | I15: 65.001 | J15: 117.73 | K15: -39.06 | L15: 76.746 | M15: 68.1 | S15: =(S11-T11) -> -6.283 | T15: =(T11-U11) -> -0.623 | U15: =(U11-V11) -> -175.006 | V15: =(V11-W11) -> -58.217 | W15: =(W11-X11) -> -8.257 | X15: =(X11-Y11) -> 21.102 | Y15: =(Y11-Z11) -> -4.7 | Z15: =(Z11-AA11) -> 20.777 | ... AB15: =(AB11-AC11) -> #VALUE!
A16: Utilidad Neta | B16: 107.59 | C16: 69.573 | D16: 192.446 | E16: -613.331 | F16: 938.484 | G16: 370.067 | H16: 91.465 | I16: 371.847 | J16: -316.248 | K16: -158.291 | L16: -69.7 | M16: -201.058 | S16: =(S12-T12) -> 0 | T16: =(T12-U12) -> 0 | U16: =(U12-V12) -> 0 | V16: =(V12-W12) -> 0 | W16: =(W12-X12) -> 0 | X16: =(X12-Y12) -> 0 | Y16: =(Y12-Z12) -> 0 | Z16: =(Z12-AA12) -> 0 | ... AB16: =(AB12-AC12) -> 0
A17: Dividendos | B17: 0 | C17: 0 | D17: 0 | E17: 0 | F17: 0 | G17: -11.103 | H17: -19.371 | I17: -2.159 | J17: -23.054 | K17: -8.381 | L17: 0 | M17: -15.561 | R17: Capital de trabajo | S17: =SUM(S14:S16) -> -6.283 | T17: =SUM(T14:T16) -> -0.623 | U17: =SUM(U14:U16) -> -175.006 | V17: =SUM(V14:V16) -> -58.217 | W17: =SUM(W14:W16) -> -8.257 | X17: =SUM(X14:X16) -> 21.102 | Y17: =SUM(Y14:Y16) -> -6.528 | Z17: =SUM(Z14:Z16) -> 19.245 | ... AB17: =SUM(AB14:AB16) -> #VALUE!
A18: Compra de Acciones | B18: -112.478 | C18: -535.339 | D18: -380.505 | E18: -264.03 | F18: -99.253 | G18: 0 | H18: 0 | I18: 0 | J18: 0 | K18: 0 | L18: 0 | M18: 0
B19: =B8-B9-B10-B15 -> 107.619 | C19: =C8-C9-C10-C15 -> 69.57 | D19: =D8-D9-D10-D15 -> 192.456 | E19: =E8-E9-E10-E15 -> -613.289 | F19: =F8-F9-F10-F15 -> 938.437 | G19: =G8-G9-G10-G15 -> 370.041 | H19: =H8-H9-H10-H15 -> 91.486 | I19: =I8-I9-I10-I15 -> 371.891 | ... M19: =M8-M9-M10-M15 -> -201.052
A20: POSICIÓN FINANCIERA | B20: =B16-B19 -> -0.029 | C20: =C16-C19 -> 0.003 | D20: =D16-D19 -> -0.01 | E20: =E16-E19 -> -0.042 | F20: =F16-F19 -> 0.047 | G20: =G16-G19 -> 0.026 | H20: =H16-H19 -> -0.021 | I20: =I16-I19 -> -0.044 | ... M20: =M16-M19 -> -0.006
A21: Activo
A22: Caja | B22: 85.167 | C22: 324.801 | D22: 750.147 | E22: 61.576 | F22: 388.49 | G22: 320.567 | H22: 464.965 | I22: 458.673 | J22: 461.584 | K22: 559.9 | L22: 0 | M22: -
A23: Cuentas y documentos por cobrar | B23: 71.223 | C23: 55.761 | D23: 62.044 | E23: 62.667 | F23: 237.673 | G23: 295.89 | H23: 304.147 | I23: 283.045 | J23: 287.745 | K23: 266.968 | L23: 0 | M23: -
A24: Inventarios | B24: 0 | C24: 0 | D24: 0 | E24: 0 | F24: 0 | G24: 0 | H24: 0 | I24: 0 | J24: 1.828 | K24: 3.36 | L24: 0 | M24: -
A25: Activos Fijos (Net Plant) | B25: 912.972 | C25: 883.861 | D25: 1041.251 | E25: 1162.394 | F25: 1278.935 | G25: 1380.417 | H25: 2151.633 | I25: 2290.9 | J25: 2514.319 | K25: 2656.726 | L25: 0 | M25: -
A26: Otros Activos | B26: 902.875 | C26: 946.887 | D26: 3117.452 | E26: 5209.786 | F26: 4864.538 | G26: 5394.411 | H26: 4141.725 | I26: 4406.498 | J26: 5172.742 | K26: 4968.126 | L26: 0 | M26: 0
A27: Total Activo | B27: 1972.237 | C27: 2211.31 | D27: 4970.894 | E27: 6496.423 | F27: 6769.636 | G27: 7391.285 | H27: 7062.47 | I27: 7439.116 | J27: 8438.218 | K27: 8455.08 | L27: 0
A30: Pasivo
A31: Pasivo Corto Plazo | B31: 381.387 | C31: 371.928 | D31: 804.555 | E31: 1045.055 | F31: 1190.087 | G31: 1374.589 | H31: 1440.232 | I31: 0 | J31: 0 | K31: 1596.404 | L31: 0
A32: Deuda a corto plazo | B32: 0 | C32: 0 | D32: 0 | E32: 0 | F32: 0 | G32: 0 | H32: 0 | I32: 180.851 | J32: 0 | K32: 0 | L32: 0
A33: Short-Term Leases | B33: 45.167 | C33: 43.407 | D33: 50.061 | E33: 44.353 | F33: 6.385 | G33: 0 | H33: 15.763 | I33: 11.503 | J33: 15.707 | K33: 0 | L33: 0
A34: Otros Pasivos a Corto Plazo | B34: 336.22 | C34: 328.521 | D34: 754.494 | E34: 1000.702 | F34: 1183.702 | G34: 1374.589 | H34: 1424.469 | I34: -192.354 | J34: -15.707 | K34: 1596.404 | L34: 0 | M34: 0
A35: Pasivo Largo Plazo | B35: 815.095 | C35: 698.11 | D35: 1900.681 | E35: 2634.922 | F35: 3514.207 | G35: 4015.417 | H35: 0 | I35: 0 | J35: 5668.479 | K35: 5307.374 | L35: 0
A36: Deuda a largo plazo | B36: 133.916 | C36: 64.722 | D36: 852.689 | E36: 1077.514 | F36: 2480.328 | G36: 2973.396 | H36: 3394.296 | I36: 4083.181 | J36: 4045.189 | K36: 4118.97 | L36: 0
A37: Long-Term Leases | B37: 418.911 | C37: 416.97 | D37: 521.716 | E37: 542.767 | F37: 113.257 | G37: 0 | H37: 235.079 | I37: 235.753 | J37: 288.392 | K37: 0 | L37: 0
A38: Otros Pasivos a Largo Plazo | B38: 262.268 | C38: 216.418 | D38: 526.276 | E38: 1014.641 | F38: 920.622 | G38: 1042.021 | H38: -3629.375 | I38: -4318.934 | J38: 1334.898 | K38: 1188.404 | L38: 0 | M38: 0
A39: Total pasivos | B39: 1196.482 | C39: 1070.038 | D39: 2705.236 | E39: 3679.977 | F39: 4704.294 | G39: 5390.006 | H39: 1440.232 | I39: 0 | J39: 5668.479 | K39: 6903.778 | L39: 0 | M39: 0
A42: Interés Minoritario | B42: 0 | C42: 0 | D42: 0 | E42: 0 | F42: 0 | G42: 0 | H42: 0 | I42: 0 | J42: 0 | K42: 0 | L42: 0 | M42: 0
A44: Capital Contable | B44: 775.755 | C44: 1141.272 | D44: 2265.658 | E44: 2816.446 | F44: 2065.342 | G44: 2001.279 | H44: 5622.238 | I44: 7439.116 | J44: 2769.739 | K44: 1551.302 | L44: 0 | M44: 47791
A46: OTROS DATOS AL FIN DE AÑO
A47: Numero de Empleados | B47: 4400 | C47: 1800 | D47: 3000 | E47: 5000 | F47: 6000 | G47: 9000 | H47: 9000 | I47: 19900 | J47: — | K47: — | L47: 0 | M47: 0
A48: Acciones en circulación (millones) | B48: 157.37 | C48: 156 | D48: 181 | E48: 119 | F48: 127 | G48: 91 | H48: 55
A49: Float | B49: 0.91439 | C49: 0.9158 | D49: 0.7641 | E49: 0.9053 | F49: 0.8903 | G49: 0.84857 | H49: 0.9307
A50: Insiders Own | B50: 0.0232 | C50: 0.022 | D50: 0.0078 | E50: 0.013 | F50: 0.029 | G50: 0.019 | H50: 0.026 | N50: DEF 14A
A51: S&P
A52: Vol. Diario en Millones USD | B52: 13203.2 | C52: 27539.6 | D52: 32727.3 | E52: 11364.4 | F52: 29945.9 | G52: 26416.3 | H52: 13758.5
B53: 2021 | C53: 2022 | D53: 2023
A54: Posicion en Corto (%) | B54: 0.00862 | C54: 0.02837 | D54: 0.08039
A55: EPS | B55: =1.01 -> 1.01 | C55: =0.42 -> 0.42 | D55: 0.68
A57: BONOS DE LA EMISORA A 3, 5 Y 10 | B57: Precio Medio | C57: S&P | D57: YTM (%) | E57: DIVISA
