Workbook
Name Benchmark: [1]ControlsH!$B$3
Name BestConsOv: #REF!
Name Broker_Name: OFFSET(#REF!,0,0,[1]ControlsH!$E$5, 1)
Name calCODE: [1]ControlsH!$C$4
Name Chart_Benchmark_100_Size: OFFSET(#REF!, 0, 0, [1]ControlsH!$E$3, 1)
Name Chart_Date_Size: OFFSET(#REF!, 0, 0, [1]ControlsH!$E$3, 1)
Name Chart_Date_VAL1_Size: OFFSET(#REF!, 0, 0, [1]ControlsH!$I$3, 1)
Name Chart_Date_VAL2_Size: OFFSET(#REF!, 0, 0, [1]ControlsH!$I$5, 1)
Name Chart_Peer_100_Size: OFFSET(#REF!, 0, 0, [1]ControlsH!$E$3, 1)
Name Chart_Price_100_Size: OFFSET(#REF!, 0, 0, [1]ControlsH!$E$3, 1)
Name Chart_Price_Size: OFFSET(#REF!, 0, 0, [1]ControlsH!$E$3, 1)
Name Chart_VAL1_FY1_Size: OFFSET(#REF!, 0, 0, [1]ControlsH!$F$3, 1)
Name Chart_VAL1_FY2_Size: OFFSET(#REF!, 0, 0, [1]ControlsH!$G$3, 1)
Name Chart_VAL1_FY3_Size: OFFSET(#REF!, 0, 0, [1]ControlsH!$H$3, 1)
Name Chart_VAL2_FY1_Size: OFFSET(#REF!, 0, 0, [1]ControlsH!$F$5, 1)
Name Chart_VAL2_FY2_Size: OFFSET(#REF!, 0, 0, [1]ControlsH!$G$5, 1)
Name Chart_VAL2_FY3_Size: OFFSET(#REF!, 0, 0, [1]ControlsH!$H$5, 1)
Name Chart_Volume_Size: OFFSET(#REF!, 0, 0, [1]ControlsH!$E$3, 1)
Name compNAME: [1]ControlsH!$B$6
Name CURRENCY: [1]ControlsH!$B$9
Name currPRICE: [1]Overview!$E$19
Name custBenchmark: [1]Overview!$C$9
Name custED: #REF!
Name custSD: #REF!
Name dayCODE: [1]ControlsH!$C$5
Name ED: [1]ControlsH!$B$5
Name ESTBrokersItem: #REF!
Name ESTBrokersPeriod: #REF!
Name ESTDetailBroker: #REF!
Name ESTDetailBroker2: #REF!
Name ESTDetailPeriod: #REF!
Name EstDetPerO: #REF!
Name EstDetPerT: #REF!
Name FinancialsPeriod: #REF!
Name fundTICKER: [1]ControlsH!$B$15
Name GraphValRatio1: #REF!
Name GraphValRatio2: #REF!
Name Index1: #REF!
Name Lang: [1]Overview!$D$11
Name newCrncy: [1]ControlsH!$B$21:$B$199
Name newEstBrokerPeriod: #REF!
Name newEstBrokersItem: #REF!
Name newEstDetailBroker: #REF!
Name newEstDetailBroker2: #REF!
Name newEstDetailPeriod: #REF!
Name newFinancialsPeriod: #REF!
Name newOverviewCon: #REF!
Name newOverviewYear: #REF!
Name newOwners: #REF!
Name newPeersRatio: #REF!
Name newPeriod: #REF!
Name newValRatio1: #REF!
Name newValRatio2: #REF!
Name OverviewValRatioPeriod: [1]Overview!$D$30
Name PeerDate1: [1]Peers!$S$11
Name peerHist1: #REF!
Name PeerIndex: [1]ControlsH!$F$35:$F$36
Name Peers: OFFSET([1]Peers!$C$18,0,0,MAX(COUNTA([1]Peers!$C$18:$C$47),1),1)
Name peersWEIGHT: [1]ControlsH!$B$13
Name PERIODICITY: [1]ControlsH!$C$3

Sheet OP
B2: (date of last modification) | C2: Analista: Research | D2: Report (quarter): (date) | E2: Name of the Company (Ticker) | K2: (stock market) | L2: SIC: Sí
D3: DESCRIPTION: (write relevant information about the company, 1-2 lines is enough. If you find segments and key products relevant for this part, you can also write it here)
D4: CEO & BOARD: Name (Chairman or not; age; board member since; current board presence; previous jobs); note: *Independent members, green: new members
B5: Millones de USD
B6: Acción | D6: Liquidez y Solvencia | F6: =Segments!B2 -> Regions (2023) | I6: Rentabilidad (2022) | K6: Múltiplos
B7: Último Precio | D7: Activo: | H7: %Vts; %Op.Mg.; D | I7: Año termina: | K7: Float:
B8: Outstanding Shares | D8: Pasivo: | F8: =Segments!B4 -> 0 | H8: =+Segments!J4 | K8: Insiders Own:
B9: Market Cap. | C9: =C7*C8/1000000 -> 0 | D9: Cash/Precio | E9: =1000000*C11/C8 -> #DIV/0! | F9: =Segments!B5 -> 0 | H9: =+Segments!J5 | I9: EBIT | K9: b (Bloomberg; Yahoo)
B10: +Deuda Total | D10: Ebidta/CIF | F10: =Segments!B6 -> 0 | H10: =+Segments!J6 | I10: +Dep&Amort | K10: Calificación (S&P)
B11: -Cash | D11: Deuda/Ebidta | F11: =Segments!B7 -> 0 | H11: =+Segments!J7 | I11: =EBIDTA | J11: =J9+J10 -> 0 | K11: Precio/Valor en libros | L11: =((C7*C8)/1000000)/(E7-E8) -> #DIV/0!
B12: =Enterprise Value | C12: =C9+C10-C11 -> 0 | D12: "Otros activos"/Activo | F12: =Segments!B8 -> 0 | H12: =+Segments!J8 | I12: Utilidad Neta | K12: FNP(p)/Activos | L12: =J18/E7 -> #DIV/0!
B13: Tenencia % (nac/int'l) | D13: Deuda/Activo | E13: =C10/E7 -> #DIV/0! | F13: =Segments!B15 -> Products (2023) | I13: UPA | J13: =1000000*J12/C8 -> #DIV/0! | K13: Precio/Utilidad(p) | L13: =C9/J17 -> #DIV/0! | N13: =C10/J11 -> #DIV/0!
B14: t liq. (Pos prom./Vol.) | D14: Margen de Operación (p) | H14: %Vts; D | I14: ROA | J14: =J12/E7 -> #DIV/0! | K14: EV/Activos | L14: =C12/E7 -> #DIV/0!
B15: % Short | D15: Margen neto (p) | F15: =Segments!B17 -> 0 | H15: =+Segments!J17 | I15: ROIC | J15: =J12/(E7-(E8-C10)) -> #DIV/0! | K15: EV/Ebidta (p) | L15: =C12/J16 -> #DIV/0!
B16: Semáforo ESG | D16: Ebidta/Ingresos(p) | F16: =Segments!B18 -> 0 | H16: =+Segments!J18 | I16: Ebidta(p) | J16: =AVERAGE(Cifras_en_Millones!B19:D19) -> 0 | K16: Precio/FNP (p) | L16: =C9/J18 -> #DIV/0!
B17: E | D17: CIF/Deuda Neta Promedio | F17: =Segments!B19 -> 0 | H17: =+Segments!J19 | I17: Utilidad Neta (p) | J17: =AVERAGE(Cifras_en_Millones!B23:D23) -> 0 | K17: Bonos 1;5;40a (USD) | L17: 4.0%; 4.4%; 5% | N17: 12
B18: S | F18: =Segments!B20 -> 0 | H18: =+Segments!J20 | I18: FNP (p) | J18: =SUM(F35:F37)/3 -> 0 | K18: TDY(p)/Precio | L18: =SUM(E35:E37)/(3*C9) -> #DIV/0!
B19: G | F19: =Segments!B21 -> 0 | H19: =+Segments!J21 | I19: Tax (p) últ. 5a | J19: 0.16 | K19: Div. Yield: | L19: =K33/C9 -> #DIV/0!
B20: Tesis de inversión | H20: Acuerdo | I20: Supuestos de valuación | L20: DCF Value
B21: (Investment thesis) | H21: Mantener sin elevar posición | I21: VER DCF | L21: =DCFF!D66 -> #VALUE!
B23: KSF | H23: PO / Precio Stand By | L23: =DCFF!D65 -> #VALUE!
H24: =DCFF!D71 -> 0 | I24: Tasa de descuento: | J24: =DCFF!D47 -> 0
B25: Año | C25: Ingresos | D25: Margen Operativo | E25: Div.+Recompra | F25: FNP | G25: Deuda/Activo | H25: Depreciación | I25: Capex + Adq | J25: Cash Flow
B26: 2012 | K26: 2022 | L26: =K26-1 -> 2021
B27: =B26+1 -> 2013 | J27: Profit | N27: =C27/C26-1 -> #DIV/0! | O27: =D27/D26-1 -> #DIV/0!
B28: =B27+1 -> 2014 | J28: Cash Flow from Operations (BWC) | N28: =C28/C27-1 -> #DIV/0! | O28: =D28/D27-1 -> #DIV/0! | P28: =E28/E27-1 -> #DIV/0! | Q28: =F28/F27-1 -> #DIV/0! | R28: =H28/H27-1 -> #DIV/0! | S28: =I28/I27-1 -> #DIV/0! | BT28: 4303
B29: =B28+1 -> 2015 | J29: Working Capital | N29: =C29/C28-1 -> #DIV/0! | O29: =D29/D28-1 -> #DIV/0! | P29: =E29/E28-1 -> #DIV/0! | Q29: =F29/F28-1 -> #DIV/0! | R29: =H29/H28-1 -> #DIV/0! | S29: =I29/I28-1 -> #DIV/0! | BT29: 3066
B30: =B29+1 -> 2016 | J30: Investing Activities | N30: =C30/C29-1 -> #DIV/0! | O30: =D30/D29-1 -> #DIV/0! | P30: =E30/E29-1 -> #DIV/0! | Q30: =F30/F29-1 -> #DIV/0! | R30: =H30/H29-1 -> #DIV/0! | S30: =I30/I29-1 -> #DIV/0! | BT30: 3283
B31: =B30+1 -> 2017 | J31: Capex | N31: =C31/C30-1 -> #DIV/0! | O31: =D31/D30-1 -> #DIV/0! | P31: =E31/E30-1 -> #DIV/0! | Q31: =F31/F30-1 -> #DIV/0! | R31: =H31/H30-1 -> #DIV/0! | S31: =I31/I30-1 -> #DIV/0!
B32: =B31+1 -> 2018 | J32: Adquisiones | N32: =C32/C31-1 -> #DIV/0! | O32: =D32/D31-1 -> #DIV/0! | P32: =E32/E31-1 -> #DIV/0! | Q32: =F32/F31-1 -> #DIV/0! | R32: =H32/H31-1 -> #DIV/0! | S32: =I32/I31-1 -> #DIV/0!
B33: =B32+1 -> 2019 | J33: Dividends | N33: =C33/C32-1 -> #DIV/0! | O33: =D33/D32-1 -> #DIV/0! | P33: =E33/E32-1 -> #DIV/0! | Q33: =F33/F32-1 -> #DIV/0! | R33: =H33/H32-1 -> #DIV/0! | S33: =I33/I32-1 -> #DIV/0!
B34: =B33+1 -> 2020 | J34: Stock Repurchases | N34: =C34/C33-1 -> #DIV/0! | O34: =D34/D33-1 -> #DIV/0! | P34: =E34/E33-1 -> #DIV/0! | Q34: =F34/F33-1 -> #DIV/0! | R34: =H34/H33-1 -> #DIV/0! | S34: =I34/I33-1 -> #DIV/0!
B35: =B34+1 -> 2021 | J35: Endeudamiento Neto | N35: =C35/C34-1 -> #DIV/0! | O35: =D35/D34-1 -> #DIV/0! | P35: =E35/E34-1 -> #DIV/0! | Q35: =F35/F34-1 -> #DIV/0! | R35: =H35/H34-1 -> #DIV/0! | S35: =I35/I34-1 -> #DIV/0!
B36: =B35+1 -> 2022 | J36: Otros Financiemientos | N36: =C36/C35-1 -> #DIV/0! | O36: =D36/D35-1 -> #DIV/0!
B37: =B36+1 -> 2023 | D37: =119500/C37 -> #DIV/0! | N37: =C37/C36-1 -> #DIV/0! | O37: =D37/D36-1 -> #DIV/0!
B38: 2024 Est. | C38: =DCFF!H6 -> 0 | D38: =DCFF!H7 -> 0
B39: CAGR | C39: =(C37/C32)^(1/5)-1 -> #DIV/0! | D39: =(D37/D26)^(1/11)-1 -> #DIV/0! | J39: FX | K39: 0 | L39: 0
B40: AAG | C40: =AVERAGE(N27:N37) -> #DIV/0! | D40: =AVERAGE(O27:O37) -> #DIV/0! | J40: D Cash and Equivalents | K40: =K28+K29+K30+K33+K34+K35+K36+K39 -> 0 | L40: =L28+L29+L30+L33+L34+L35+L36+L39 -> 0
B41: CVAR | C41: =STDEV(C26:C37)/AVERAGE(C26:C37) -> #DIV/0! | D41: =STDEV(D26:D37)/AVERAGE(D26:D37) -> #DIV/0! | J41: Inv/D Vts | K41: =SUM(I33:I37)/(C37-C32) -> #DIV/0! | L41: =(SUM(I33:I37)-SUM(H33:H37))/(C37-C32) -> #DIV/0!
B42: Último Año | C42: =C37/C36-1 -> #DIV/0! | D42: =D37/D36-1 -> #DIV/0! | J42: t inversiones; t adq. neto dep. | K42: =K41/E14 -> #DIV/0! | L42: =L41/E14 -> #DIV/0!
B43: Pros y Cons | I43: (historical stock price of the company and its peers; source: Bloomberg)
B44: （write a text explaining pros and cons of the company)
B45: Riesgos
B46: (risks)
B47: Oportunidades
B48: (opportunities)
B49: CHECKLIST
B50: Crecimiento | C50: Riesgos claros | D50: ESG | E50: Peer Analysis | F50: Consenso | G50: KSF | H50: PO/Stand By | I50: (write the peers' names here)
B51: (p) = Promedio de últimos 3 años
B52: NOTES:

Sheet COVID-19 impact
A1: https://www.apple.com/newsroom/2020/03/apples-covid-19-response/ | G1: https://glg.it/articles/how-might-the-wuhan-coronavirus-impact-apples-supply-chain/ | N1: https://www.cnbc.com/2020/02/18/the-significance-of-apples-coronavirus-warning.html
A2: March 13 | G2: January 29 | N2: Ferbuary 18
A23: Otros:
A24: https://www.macrumors.com/guide/covid-19-coronavirus/

Sheet Segments
B2: Regions (2023) | L2: Proyectado | N2: Escenario de estrés | X2: Escenario de estrés
C3: 2022 | D3: =C3-1 -> 2021 | E3: Ut. Operativa | F3: % Vts | G3: Margen | H3: Crec | L3: Crecimiento | M3: 2021 (Real) | N3: 2022 (Real) | O3: 2023 (Real) | P3: 2024 (Est) | Q3: 2025 | R3: 2026 | S3: 2027 | T3: 2028 | V3: Márgenes (regional) | W3: 2020 (Real) | X3: 2021 (Real) | Y3: 2022 (Real) | Z3: 2023 (Est) | AA3: 2024 | AB3: 2025 | AC3: 2026 | AD3: 2027
J4: =IF(C4="","",IF(F4=0,"NA",TEXT(F4,"0%"))&"; "&IF(G4=0,"NA",TEXT(G4,"0.0%"))&"; "&IF(H4=0,"NA",TEXT(H4,"0%"))) | L4: =B17 -> 0 | V4: =B4 -> 0
J5: =IF(C5="","",IF(F5=0,"NA",TEXT(F5,"0%"))&"; "&IF(G5=0,"NA",TEXT(G5,"0.0%"))&"; "&IF(H5=0,"NA",TEXT(H5,"0%"))) | L5: =B18 -> 0 | V5: =B5 -> 0
J6: =IF(C6="","",IF(F6=0,"NA",TEXT(F6,"0%"))&"; "&IF(G6=0,"NA",TEXT(G6,"0.0%"))&"; "&IF(H6=0,"NA",TEXT(H6,"0%"))) | L6: =B19 -> 0 | V6: =B6 -> 0
J7: =IF(C7="","",IF(F7=0,"NA",TEXT(F7,"0%"))&"; "&IF(G7=0,"NA",TEXT(G7,"0.0%"))&"; "&IF(H7=0,"NA",TEXT(H7,"0%"))) | L7: =B20 -> 0 | V7: =B7 -> 0
J8: =IF(C8="","",IF(F8=0,"NA",TEXT(F8,"0%"))&"; "&IF(G8=0,"NA",TEXT(G8,"0.0%"))&"; "&IF(H8=0,"NA",TEXT(H8,"0%"))) | L8: =B21 -> 0 | V8: =B8 -> 0
J9: =IF(C9="","",IF(F9=0,"NA",TEXT(F9,"0%"))&"; "&IF(G9=0,"NA",TEXT(G9,"0.0%"))&"; "&IF(H9=0,"NA",TEXT(H9,"0%"))) | L9: % vts. | V9: Margen Operativp | W9: =(W4*W12+W5*W13+W6*W14+W7*W15+W8*W16)/SUM(W12:W16)+W10 -> #DIV/0! | X9: =(X4*X12+X5*X13+X6*X14+X7*X15+X8*X16)/SUM(X12:X16)+X10 -> #DIV/0! | Y9: =(Y4*Y12+Y5*Y13+Y6*Y14+Y7*Y15+Y8*Y16)/SUM(Y12:Y16)+Y10 -> #DIV/0! | Z9: =(Z4*Z12+Z5*Z13+Z6*Z14+Z7*Z15+Z8*Z16)/SUM(Z12:Z16)+Z10 -> #DIV/0! | AA9: =(AA4*AA12+AA5*AA13+AA6*AA14+AA7*AA15+AA8*AA16)/SUM(AA12:AA16)+AA10 -> #DIV/0! | AB9: =(AB4*AB12+AB5*AB13+AB6*AB14+AB7*AB15+AB8*AB16)/SUM(AB12:AB16)+AB10 -> #DIV/0! | AC9: =(AC4*AC12+AC5*AC13+AC6*AC14+AC7*AC15+AC8*AC16)/SUM(AC12:AC16)+AC10 -> #DIV/0! | AD9: =(AD4*AD12+AD5*AD13+AD6*AD14+AD7*AD15+AD8*AD16)/SUM(AD12:AD16)+AD10 -> #DIV/0!
J10: =IF(C10="","",IF(F10=0,"NA",TEXT(F10,"0%"))&"; "&IF(G10=0,"NA",TEXT(G10,"0.0%"))&"; "&IF(H10=0,"NA",TEXT(H10,"0%"))) | L10: =B17 -> 0 | V10: Ajuste R&D | W10: =(-6200-18752)/274515 -> -0.090894851 | X10: =(-6143-21914)/365817 -> -0.076696818 | Y10: =(-7207-26251)/394328 -> -0.084848147 | Z10: -0.1 | AA10: -0.1 | AB10: -0.1 | AC10: -0.1 | AD10: -0.1
J11: =IF(C11="","",IF(F11=0,"NA",TEXT(F11,"0%"))&"; "&IF(G11=0,"NA",TEXT(G11,"0.0%"))&"; "&IF(H11=0,"NA",TEXT(H11,"0%"))) | L11: =B18 -> 0 | V11: % vts.
J12: =IF(C12="","",IF(F12=0,"NA",TEXT(F12,"0%"))&"; "&IF(G12=0,"NA",TEXT(G12,"0.0%"))&"; "&IF(H12=0,"NA",TEXT(H12,"0%"))) | L12: =B19 -> 0 | V12: =V4 -> 0
J13: =IF(C13="","",IF(F13=0,"NA",TEXT(F13,"0%"))&"; "&IF(G13=0,"NA",TEXT(G13,"0.0%"))&"; "&IF(H13=0,"NA",TEXT(H13,"0%"))) | L13: =B20 -> 0 | V13: =V5 -> 0
B14: TOTAL | C14: =SUM(C4:C12) -> 0 | D14: =SUM(D4:D12) -> 0 | E14: =SUM(E4:E13) -> 0 | F14: =C14/SUM($C$4:$C$13) -> #DIV/0! | G14: =E14/C14 -> #DIV/0! | H14: =C14/D14-1 -> #DIV/0! | L14: =B21 -> 0 | V14: =V6 -> 0
B15: Products (2023) | M15: =SUM(M10:M14) -> 0 | N15: =SUM(N10:N14) -> 0 | O15: =SUM(O10:O14) -> 0 | P15: =SUM(P10:P14) -> 0 | Q15: =SUM(Q10:Q14) -> 0 | R15: =SUM(R10:R14) -> 0 | S15: =SUM(S10:S14) -> 0 | T15: =SUM(T10:T14) -> 0 | V15: =V7 -> 0
C16: =C3 -> 2022 | D16: =C16-1 -> 2021 | E16: Ut. Op. | F16: % Vts | G16: Margen | H16: Crec | N16: =N15/M15-1 -> #DIV/0! | O16: =O15/N15-1 -> #DIV/0! | P16: =P15/O15-1 -> #DIV/0! | Q16: =Q15/P15-1 -> #DIV/0! | R16: =R15/Q15-1 -> #DIV/0! | S16: =S15/R15-1 -> #DIV/0! | T16: =T15/S15-1 -> #DIV/0! | V16: =V8 -> 0
J17: =IF(C17="","",IF(F17=0,"NA",TEXT(F17,"0%"))&"; "&IF(G17=0,"NA",TEXT(G17,"0.0%"))&"; "&IF(H17=0,"NA",TEXT(H17,"0%"))) | W17: =SUM(W12:W16) -> 0 | X17: =SUM(X12:X16) -> 0 | Y17: =SUM(Y12:Y16) -> 0 | Z17: =SUM(Z12:Z16) -> 0 | AA17: =SUM(AA12:AA16) -> 0 | AB17: =SUM(AB12:AB16) -> 0 | AC17: =SUM(AC12:AC16) -> 0 | AD17: =SUM(AD12:AD16) -> 0
J18: =IF(C18="","",IF(F18=0,"NA",TEXT(F18,"0%"))&"; "&IF(G18=0,"NA",TEXT(G18,"0.0%"))&"; "&IF(H18=0,"NA",TEXT(H18,"0%")))
J19: =IF(C19="","",IF(F19=0,"NA",TEXT(F19,"0%"))&"; "&IF(G19=0,"NA",TEXT(G19,"0.0%"))&"; "&IF(H19=0,"NA",TEXT(H19,"0%")))
J20: =IF(C20="","",IF(F20=0,"NA",TEXT(F20,"0%"))&"; "&IF(G20=0,"NA",TEXT(G20,"0.0%"))&"; "&IF(H20=0,"NA",TEXT(H20,"0%")))
J21: =IF(C21="","",IF(F21=0,"NA",TEXT(F21,"0%"))&"; "&IF(G21=0,"NA",TEXT(G21,"0.0%"))&"; "&IF(H21=0,"NA",TEXT(H21,"0%")))
J22: =IF(C22="","",IF(F22=0,"NA",TEXT(F22,"0%"))&"; "&IF(G22=0,"NA",TEXT(G22,"0.0%"))&"; "&IF(H22=0,"NA",TEXT(H22,"0%")))
J23: =IF(C23="","",IF(F23=0,"NA",TEXT(F23,"0%"))&"; "&IF(G23=0,"NA",TEXT(G23,"0.0%"))&"; "&IF(H23=0,"NA",TEXT(H23,"0%")))
J24: =IF(C24="","",IF(F24=0,"NA",TEXT(F24,"0%"))&"; "&IF(G24=0,"NA",TEXT(G24,"0.0%"))&"; "&IF(H24=0,"NA",TEXT(H24,"0%")))
J25: =IF(C25="","",IF(F25=0,"NA",TEXT(F25,"0%"))&"; "&IF(G25=0,"NA",TEXT(G25,"0.0%"))&"; "&IF(H25=0,"NA",TEXT(H25,"0%")))
J26: =IF(C26="","",IF(F26=0,"NA",TEXT(F26,"0%"))&"; "&IF(G26=0,"NA",TEXT(G26,"0.0%"))&"; "&IF(H26=0,"NA",TEXT(H26,"0%")))
B27: TOTAL | C27: =SUM(C17:C26) -> 0 | D27: =SUM(D17:D26) -> 0 | E27: =SUM(E17:E26) -> 0 | F27: =C27/SUM(C17:C26) -> #DIV/0! | G27: =E27/C27 -> #DIV/0! | H27: =C27/D27-1 -> #DIV/0!

Sheet Peers
A2: Multiplos (USD) | B2: LAUR | C2: STRA | D2: ATGE | E2: PRDO
B3: Laureate Education | C3: Strategic Education | D3: Adtalem Global Education | E3: Perdoceo Education Corporation
A4: Ventas | B4: 1484.288M
A5: Crecimiento (1S23/1S22) | B5: 19.4%
A6: Crecimiento (1S23/1S19) | B6: 22.5%
A7: Deuda | B7: 122278 | C7: 82110 | D7: 26772 | E7: 100504
A8: Activos | B8: 323888 | C8: 301311 | D8: 319616 | E8: 321195
A9: Deuda/Activos | B9: 55.76%
A10: Deuda/EBITDA | B10: =500060000/430970000 -> 1.1603128
A11: (Capex + Adq.)/Revenue | B11: =-DCFF!G22/DCFF!G6 -> #DIV/0!
A12: ROA (p)
A13: ROIC (p)
A14: Margen Operativo | B14: 19.54%
A15: Margen Operativo 2022
A16: Float | B16: 2.71%
A17: b | B17: 0.87
A18: Precio/Utilidad
A19: Precio/Ventas | B19: 1.97
A20: EV/Activos | B20: =OP!C12/OP!E7 -> #DIV/0!
A21: EV/Ebitda | B21: =OP!C12/OP!J11 -> #DIV/0!
A22: Div. Yield:
B24: *Nota: Estos múltiplos no consideran el promedio de los últimos 3 años, únicamente valores del último año reportado
B25: **Cifras en USD
A27: (You can make up a table with different indicators in order to link them to the multiples/ratios. At the end, put the table unvisible with white color)

Sheet Acuerdo
A1: Invertir
A2: NO invertir
A3: Mantener sin elevar posición
A4: Mantener (y seguir comprando)
A5: Liquidar
A6: PENDIENTE

Sheet ESG
B2: Análisis ESG | J2: PARÁMETROS
C3: Impacto | D3: ¿Reporta? | E3: Ranking | F3: Mitigación | G3: Semáforo | H3: Comentarios | J3: IMPACTO | L3: RANKING | M3: MITIGACIÓN
B4: Ambiental | J4: NONE | K4: 0 | L4: "Best in class" | M4: Is there evidence of progam/plan/etc…
B5: Emisiones directas CO2 | J5: LOW | K5: 1 | L5: Medium high
B6: Uso total de agua | J6: MEDIUM | K6: 2 | L6: Medium
B7: Total Energy Consumption | J7: HIGH | K7: 3 | L7: "Villain"
B8: Waste Management
B9: Land Degradation/Deforestation/Biodiversity loss/Animal sufering/… | J9: TRAFFIC LIGHTS
B10: Social
B11: % Rotación de empleados
B12: Sueldos y compensaciones
B13: Temas de reputación
B14: Temas de discriminación
B15: Seguridad laboral
B16: Daños a la salud
B17: PXP?
B18: Supply chain
B19: Community involvement
B20: Public Sector
B21: Litigios
... B32: Esquemas de compensación al management

Sheet DCF
A1: Discounted Cash Flow
A3: Ventas | E3: Margen Operativo
A16: Inversiones | E16: Utilidad Neta
D31: 0.001 | E31: =1/((1+$B$59+$D31)^(E35-2021)) -> 0.92250923 | F31: =1/((1+$B$59+$D31)^(F35-2021)) -> 0.85102327 | G31: =1/((1+$B$59+$D31)^(G35-2021)) -> 0.78507682 | H31: =1/((1+$B$59+$D31)^(H35-2021)) -> 0.72424061 | I31: =1/((1+$B$59+$D31)^(I35-2021)) -> 0.66811864 | J31: =1/((1+$B$59+$D31)^(J35-2021)) -> 0.61634561 | K31: =1/((1+$B$59+$D31)^(K35-2021)) -> 0.56858451 | L31: =1/((1+$B$59+$D31)^(L35-2021)) -> 0.52452446 | ... AC31: =1/((1+$B$59+$D31)^(AC35-2021)) -> 0.13312755
D32: 0.005 | E32: =1/((1+$B$59+$D32)^(E35-2021)) -> 0.91911765 | F32: =1/((1+$B$59+$D32)^(F35-2021)) -> 0.84477725 | G32: =1/((1+$B$59+$D32)^(G35-2021)) -> 0.77644968 | H32: =1/((1+$B$59+$D32)^(H35-2021)) -> 0.7136486 | I32: =1/((1+$B$59+$D32)^(I35-2021)) -> 0.65592702 | J32: =1/((1+$B$59+$D32)^(J35-2021)) -> 0.6028741 | K32: =1/((1+$B$59+$D32)^(K35-2021)) -> 0.55411223 | L32: =1/((1+$B$59+$D32)^(L35-2021)) -> 0.50929433 | ... AC32: =1/((1+$B$59+$D32)^(AC35-2021)) -> 0.12141647
D33: Normal | E33: =1/((1+$B$59)^(E35-2021)) -> 0.92336103 | F33: =1/((1+$B$59)^(F35-2021)) -> 0.8525956 | G33: =1/((1+$B$59)^(G35-2021)) -> 0.78725355 | H33: =1/((1+$B$59)^(H35-2021)) -> 0.72691926 | I33: =1/((1+$B$59)^(I35-2021)) -> 0.67120892 | J33: =1/((1+$B$59)^(J35-2021)) -> 0.61976816 | K33: =1/((1+$B$59)^(K35-2021)) -> 0.57226977 | L33: =1/((1+$B$59)^(L35-2021)) -> 0.5284116 | ... AC33: =1/((1+$B$59)^(AC35-2021)) -> 0.13623496
B35: 2019 (Real) | C35: 2020 (Real) | D35: 2021 | E35: =D35+1 -> 2022 | F35: =E35+1 -> 2023 | G35: =F35+1 -> 2024 | H35: =G35+1 -> 2025 | I35: =H35+1 -> 2026 | J35: =I35+1 -> 2027 | K35: =J35+1 -> 2028 | L35: =K35+1 -> 2029 | ... AC35: =AB35+1 -> 2046
A36: Crecimiento | B36: =OP!N34 -> #DIV/0! | C36: =OP!N35 -> #DIV/0! | D36: 0.35 | E36: 0.034 | F36: 0.095 | G36: 0.095 | H36: 0.095 | I36: 0.095 | J36: 0.095 | K36: 0.08 | L36: 0.06 | M36: 0.05 | N36: 0.04 | O36: 0.035 | P36: 0.035 | Q36: 0.035 | R36: 0.035 | S36: 0.035 | T36: 0.035 | U36: 0.035 | V36: 0.035 | W36: 0.035 | X36: 0.035 | Y36: 0.035 | Z36: 0.035 | AA36: 0.035 | AB36: 0.035 | AC36: 0.035
A37: Ventas | B37: =OP!C34 -> 0 | C37: =OP!C35 -> 0 | D37: =OP!C34*(1+D36) -> 0 | E37: =D37*(1+E36) -> 0 | F37: =E37*(1+F36) -> 0 | G37: =F37*(1+G36) -> 0 | H37: =G37*(1+H36) -> 0 | I37: =H37*(1+I36) -> 0 | J37: =I37*(1+J36) -> 0 | K37: =J37*(1+K36) -> 0 | L37: =K37*(1+L36) -> 0 | ... AC37: =AB37*(1+AC36) -> 0
A38: Margen Operativo | B38: =+OP!D34 -> 0 | C38: =+OP!D35 -> 0 | D38: =108166.4/365513.2 -> 0.29593022 | E38: =108162.8/377959.8 -> 0.28617541 | F38: 0.27 | G38: 0.275 | H38: 0.26 | I38: 0.255 | J38: 0.25 | K38: 0.25 | L38: 0.25 | M38: 0.25 | N38: 0.25 | O38: 0.25 | P38: 0.25 | Q38: 0.25 | R38: 0.25 | S38: 0.25 | T38: 0.25 | U38: 0.25 | V38: 0.25 | W38: 0.25 | X38: 0.25 | Y38: 0.25 | Z38: 0.25 | AA38: 0.25 | AB38: 0.25 | AC38: 0.25
A39: EBIT | B39: 63930 | C39: 66288 | D39: =D37*D38 -> 0 | E39: =E37*E38 -> 0 | F39: =F37*F38 -> 0 | G39: =G37*G38 -> 0 | H39: =H37*H38 -> 0 | I39: =I37*I38 -> 0 | J39: =J37*J38 -> 0 | K39: =K37*K38 -> 0 | ... AC39: =AC37*AC38 -> 0
A40: Dep&Amort | B40: =OP!H34 -> 0 | C40: =OP!H35 -> 0 | D40: 11000 | E40: =D40*(1+E36*$H$59) -> 11374 | F40: =E40*(1+F36*$H$59) -> 12454.53 | G40: =F40*(1+G36*$H$59) -> 13637.71 | H40: =G40*(1+H36*$H$59) -> 14933.293 | I40: =H40*(1+I36*$I$59) -> 16351.956 | J40: =I40*(1+J36*$I$59) -> 17905.391 | K40: =J40*(1+K36*$I$59) -> 19337.823 | L40: =K40*(1+L36*$I$59) -> 20498.092 | M40: =L40*(1+M36*$I$59) -> 21522.997 | N40: =M40*(1+N36*$I$59) -> 22383.917 | O40: =N40*(1+O36*$I$59) -> 23167.354 | P40: =O40*(1+P36*$I$59) -> 23978.211 | ... AC40: =AB40*(1+AC36*$I$59) -> 37500.868
A41: EBIDTA | B41: =+B39+B40 -> 63930 | C41: =+C39+C40 -> 66288 | D41: =D39+D40 -> 11000 | E41: =E39+E40 -> 11374 | F41: =F39+F40 -> 12454.53 | G41: =G39+G40 -> 13637.71 | H41: =H39+H40 -> 14933.293 | I41: =I39+I40 -> 16351.956 | J41: =J39+J40 -> 17905.391 | K41: =K39+K40 -> 19337.823 | ... AC41: =AC39+AC40 -> 37500.868
A42: CIF | B42: -1385 | C42: -890 | D42: =(C48)*$H$60 -> -1124.36 | E42: =(D48)*$H$60 -> -1113.1164 | F42: =(E48)*$H$60 -> -1113.1164 | G42: =(F48)*$H$60 -> -1113.1164 | H42: =(G48)*$H$60 -> -1113.1164 | I42: =(H48)*$H$60 -> -1113.1164 | J42: =(I48)*$H$60 -> -1113.1164 | K42: =(J48)*$H$60 -> -1113.1164 | ... AC42: =(AB48)*$H$60 -> -1113.1164
A43: Otros Gastos | B43: =-422-2817 -> -3239 | C43: =87-3634 -> -3547 | D43: =-C43*(1+D36) -> 4788.45 | E43: =D43*(1+E36*0.5) -> 4869.8537 | F43: =E43*(1+F36*0.5) -> 5101.1717 | G43: =F43*(1+G36*0.5) -> 5343.4774 | H43: =G43*(1+H36*0.5) -> 5597.2925 | I43: =H43*(1+I36*0.5) -> 5863.1639 | J43: =I43*(1+J36*0.5) -> 6141.6642 | K43: =J43*(1+K36*0.5) -> 6387.3308 | L43: =K43*(1+L36*0.5) -> 6578.9507 | ... AC43: =AB43*(1+AC36*0.5) -> 8922.7133
A44: Utilidad antes de Impuestos | B44: =B39-B42-B43 -> 68554 | C44: =C39-C42-C43 -> 70725 | D44: =D39-D42-D43 -> -3664.09 | E44: =E39-E42-E43 -> -3756.7373 | F44: =F39-F42-F43 -> -3988.0553 | G44: =G39-G42-G43 -> -4230.361 | H44: =H39-H42-H43 -> -4484.1761 | I44: =I39-I42-I43 -> -4750.0475 | ... AC44: =AC39-AC42-AC43 -> -7809.5969
A45: ISR & PTU | B45: 10481 | C45: 9680 | D45: =$H$61*D44 -> -769.4589 | E45: =$H$61*E44 -> -788.91482 | F45: =$H$61*F44 -> -837.49161 | G45: =$I$61*G44 -> -972.98302 | H45: =$I$61*H44 -> -1031.3605 | I45: =$I$61*I44 -> -1092.5109 | J45: =$I$61*J44 -> -1156.566 | K45: =$I$61*K44 -> -1213.0693 | L45: =$I$61*L44 -> -1257.1419 | M45: =$I$61*M44 -> -1294.9709 | N45: =$I$61*N44 -> -1325.9906 | ... AC45: =$I$61*AC44 -> -1796.2073
A46: Utilidad Neta | B46: =B44-B45 -> 58073 | C46: =C44-C45 -> 61045 | D46: =D44-D45 -> -2894.6311 | E46: =E44-E45 -> -2967.8224 | F46: =F44-F45 -> -3150.5637 | G46: =G44-G45 -> -3257.3779 | H46: =H44-H45 -> -3452.8156 | I46: =I44-I45 -> -3657.5366 | ... AC46: =AC44-AC45 -> -6013.3896
A47: Inversiones y Capex | B47: =OP!I34 -> 0 | C47: =OP!I35 -> 0 | D47: 10000 | E47: =D47*(1+E36*$H$62) -> 10408 | F47: =E47*(1+F36*$H$62) -> 11594.512 | G47: =F47*(1+G36*$H$62) -> 12916.286 | H47: =G47*(1+H36*$H$62) -> 14388.743 | I47: =H47*(1+I36*$H$62) -> 16029.06 | J47: =I47*(1+J36*$H$62) -> 17856.373 | K47: =J47*(1+K36*$H$62) -> 19570.584 | L47: =K47*(1+L36*$H$62) -> 20979.666 | ... AC47: =AB47*(1+AC36*$H$62) -> 43199.777
A48: Deuda + Lease Liabilities | B48: 108047 | C48: 112436 | D48: =C48*0.99 -> 111311.64 | E48: =D48 -> 111311.64 | F48: =E48 -> 111311.64 | G48: =F48 -> 111311.64 | H48: =G48 -> 111311.64 | I48: =H48 -> 111311.64 | J48: =I48 -> 111311.64 | K48: =J48 -> 111311.64 | L48: =K48 -> 111311.64 | ... AC48: =AB48 -> 111311.64
A49: Deuda/EBITDA | B49: =B48/B41 -> 1.6900829 | C49: =C48/C41 -> 1.6961743 | D49: =D48/D41 -> 10.11924 | E49: =E48/E41 -> 9.786499
A50: FNP | B50: =OP!F34 -> 0 | C50: =OP!F35 -> 0 | D50: =D41-D42-D43-D45-D47+D48-C48 -> -3018.9911 | E50: =E41-E42-E43-E45-E47+E48-D48 -> -2001.8224 | F50: =F41-F42-F43-F45-F47+F48-E48 -> -2290.5457 | G50: =G41-G42-G43-G45-G47+G48-F48 -> -2535.954 | H50: =H41-H42-H43-H45-H47+H48-G48 -> -2908.2658 | I50: =I41-I42-I43-I45-I47+I48-H48 -> -3334.6407 | J50: =J41-J42-J43-J45-J47+J48-I48 -> -3822.9629 | K50: =K41-K42-K43-K45-K47+K48-J48 -> -4293.9066 | ... AC50: =AC41-AC42-AC43-AC45-AC47+AC48-AB48 -> -11712.299
A51: F(t) | B51: 0 | C51: 0 | D51: =C51*(1+$B$59)+D50 -> -3018.9911 | E51: =D51*(1+$B$59)+E50 -> -5271.3898 | F51: =E51*(1+$B$59)+F50 -> -7999.4608 | G51: =F51*(1+$B$59)+G50 -> -11199.37 | H51: =G51*(1+$B$59)+H50 -> -15037.184 | I51: =H51*(1+$B$59)+I50 -> -19619.91 | J51: =I51*(1+$B$59)+J50 -> -25071.326 | K51: =J51*(1+$B$59)+K50 -> -31446.153 | ... AC51: =AB51*(1+$B$59)+AC50 -> -400965.71
AB52: =AB51-AB48 -> -470733.07 | AC52: =AC50/(B59-AC36) -> -244006.22
A53: EPS | C53: =1000000*C46/OP!$C$8 -> #DIV/0! | D53: =1000000*D46/OP!$C$8 -> #DIV/0! | E53: =1000000*E46/OP!$C$8 -> #DIV/0! | F53: =1000000*F46/OP!$C$8 -> #DIV/0!
A54: Consenso EPS | C54: 3.3 | D54: 5.6 | E54: 5.6
A55: E$/UN | D55: =$B$61/D46 -> 33.638996 | E55: =$B$61/E46 -> 32.809403 | F55: =$B$61/F46 -> 30.906369
A56: EEV/EBIDA | D56: =($B$61+D48-D51)/D41 -> 1.5416499 | E56: =($B$61+E48-E51)/E41 -> 1.6889878 | F56: =($B$61+F48-F51)/F41 -> 1.7614971
C58: "TELP" | D58: CER | E58: D Analista | H58: CP | I58: LP
A59: Tasa de descuento: | B59: =SUM(C59:E59) -> 0.083 | C59: 0.0307 | D59: 0.0523 | E59: 0 | G59: Factor D&A | H59: 1 | I59: 1
G60: Factor CIF | H60: -0.01
A61: VPN*@i% | B61: =C62+C63 -> -97372.483 | C61: Normal | D61: =D31 -> 0.001 | E61: =D32 -> 0.005 | G61: Factor ISR | H61: 0.21 | I61: 0.23
A62: DCF 25Y | B62: =C62/B61 -> 0.65860808 | C62: =AB52/(1+B59)^25 -> -64130.304 | D62: =SUMPRODUCT(E50:AB50,E31:AB31) -> -49460.323 | E62: =SUMPRODUCT(E50:AB50,E32:AB32) -> -47340.268 | G62: Factor inv | H62: 1.2
A63: Perpetuidad | B63: =1-B62 -> 0.34139192 | C63: =AC52/(1+B59)^25 -> -33242.179 | D63: =(AC50/($B$59+D31-$AC$36))*AC31 -> -31821.013 | E63: =(AC50/($B$59+D32-$AC$36))*AC32 -> -26831.434 | G63: Suma D&A | H63: =SUM(40:40) -> 628429.57
A64: VPN/Acción | B64: =1000000*B61/OP!C8 -> #DIV/0! | D64: =1000000*SUM(D62:D63)/OP!C8 -> #DIV/0! | E64: =1000000*SUM(E62:E63)/OP!C8 -> #DIV/0! | G64: Suma Inv. | H64: =SUM(47:47) -> 672845.39
B65: =B64/OP!C7-1 -> #DIV/0! | D65: =D64/B64-1 -> #DIV/0! | E65: =E64/B64-1 -> #DIV/0! | G65: Inv.+Goodwill | H65: =SUM(47:47)+(OP!E12*OP!E7) -> 672845.39
A67: Duración | B67: =B62*D68+B63*D69 -> 20.902877 | E67: 1 | F67: 2 | G67: 3 | H67: 4 | I67: 5 | J67: 6 | K67: 7 | L67: 8 | M67: 9 | N67: 10 | O67: 11 | P67: 12 | Q67: 13 | R67: 14 | S67: 15 | T67: 16 | U67: 17 | V67: 18 | W67: 19 | X67: 20 | Y67: 21 | Z67: 22 | AA67: 23 | AB67: 24 | AC67: 25
A68: 0.001 | B68: =-$B$67*A68 -> -0.020902877 | D68: =SUM(E68:AB68)/SUMPRODUCT(E50:AB50,E33:AB33) -> 12.015539 | E68: =E67*E50*E33 -> -1848.4048 | F68: =F67*F50*F33 -> -3905.8183 | G68: =G67*G50*G33 -> -5989.3163 | H68: =H67*H50*H33 -> -8456.2976 | I68: =I67*I50*I33 -> -11191.203 | J68: =J67*J50*J33 -> -14216.104 | K68: =K67*K50*K33 -> -17200.911 | L68: =L67*L50*L33 -> -19827.131 | ... AC68: =AC67*AC50*AC33 -> -39890.615
A69: 0.005 | B69: =-$B$67*A69 -> -0.10451438 | D69: =(1+B59)/B59+AC67 -> 38.048193

Sheet DCFF
C1: VALUATION MODEL
C2: Año fiscal de Apple cierra en septiembre
D3: =D19/D6 -> #DIV/0! | E3: =E19/E6 -> #DIV/0! | F3: =F19/F6 -> #DIV/0! | G3: 0 | H3: 0.25 | I3: =H3+1 -> 1.25 | J3: =I3+1 -> 2.25 | K3: =J3+1 -> 3.25 | L3: =K3+1 -> 4.25 | M3: =L3+1 -> 5.25 | N3: =M3+1 -> 6.25 | O3: =N3+1 -> 7.25 | P3: =O3+1 -> 8.25 | ... AF3: =AE3+1 -> 24.25
A4: Section | B4: Line # | C4: ITEM | D4: 2020 (Real) | E4: 2021 (Real) | F4: 2022 (Real) | G4: 2023 (Real) | H4: 2024 | I4: =+H4+1 -> 2025 | J4: =+I4+1 -> 2026 | K4: =+J4+1 -> 2027 | L4: =+K4+1 -> 2028 | M4: =+L4+1 -> 2029 | N4: =+M4+1 -> 2030 | O4: =+N4+1 -> 2031 | P4: =+O4+1 -> 2032 | ... AF4: =+AE4+1 -> 2048 | AG4: Notes
A5: INCOME STATEMENT | B5: 1 | C5: Growth | D5: =Cifras_en_Millones!F6 -> #DIV/0! | E5: =Cifras_en_Millones!E6 -> #DIV/0! | F5: =Cifras_en_Millones!D6 -> #DIV/0! | G5: =Cifras_en_Millones!C6 -> #DIV/0! | H5: =H6/G6-1 -> #DIV/0! | I5: =I6/H6-1 -> #DIV/0! | J5: =J6/I6-1 -> #DIV/0! | K5: =K6/J6-1 -> #DIV/0! | L5: =L6/K6-1 -> #DIV/0! | M5: =M6/L6-1 -> #DIV/0! | N5: =N6/M6-1 -> #DIV/0! | O5: =O6/N6-1 -> #DIV/0! | ... AF5: =AF6/AE6-1 -> #DIV/0!
B6: 2 | C6: Revenues/Sales
B7: 3 | C7: EBIT/Operating Margin
B8: 4 | C8: EBIT | D8: =D6*D7 -> 0 | E8: =E6*E7 -> 0 | F8: =F6*F7 -> 0 | G8: =G7*G6 -> 0 | H8: =H7*H6 -> 0 | I8: =I7*I6 -> 0 | J8: =J7*J6 -> 0 | K8: =K7*K6 -> 0 | L8: =L7*L6 -> 0 | M8: =M7*M6 -> 0 | N8: =N7*N6 -> 0 | ... AF8: =AF7*AF6 -> 0
B9: 5a | C9: (Dep&Amort) | H9: {=G9*0.7+0.3*(-$D$50*AVERAGE(-1*(D22:G22)))} -> 0 | I9: {=H9*0.7+0.3*(-$D$50*AVERAGE(-1*(E22:H22)))} -> 0 | J9: {=I9*0.7+0.3*(-$D$50*AVERAGE(-1*(F22:I22)))} -> 0 | K9: {=J9*0.7+0.3*(-$D$50*AVERAGE(-1*(G22:J22)))} -> 0 | L9: {=K9*0.7+0.3*(-$D$50*AVERAGE(-1*(H22:K22)))} -> 0 | M9: {=L9*0.7+0.3*(-$D$50*AVERAGE(-1*(I22:L22)))} -> 0 | N9: {=M9*0.7+0.3*(-$D$50*AVERAGE(-1*(J22:M22)))} -> 0 | O9: {=N9*0.7+0.3*(-$D$50*AVERAGE(-1*(K22:N22)))} -> 0 | ... AF9: {=AE9*0.7+0.3*(-$D$50*AVERAGE(-1*(AB22:AE22)))} -> 0
B10: 5b | C10: (Stock based compensation) | D10: =D19 -> 0 | E10: =E19 -> 0 | F10: =F19 -> 0 | G10: =G19 -> 0 | H10: =-$D$51*H6 -> 0 | I10: =-$D$51*I6 -> 0 | J10: =-$D$51*J6 -> 0 | K10: =-$D$51*K6 -> 0 | L10: =-$E$51*L6 -> 0 | M10: =-$E$51*M6 -> 0 | N10: =-$E$51*N6 -> 0 | O10: =-$E$51*O6 -> 0 | P10: =-$E$51*P6 -> 0 | Q10: =-$E$51*Q6 -> 0 | R10: =-$E$51*R6 -> 0 | S10: =-$E$51*S6 -> 0 | ... AF10: =-$E$51*AF6 -> 0
B11: 6 | C11: EBIDTA | D11: =-D9+D8 -> 0 | E11: =-E9+E8 -> 0 | F11: =-F9+F8 -> 0 | G11: =-G9+G8 -> 0 | H11: =-H9+H8 -> 0 | I11: =-I9+I8 -> 0 | J11: =-J9+J8 -> 0 | K11: =-K9+K8 -> 0 | ... AF11: =-AF9+AF8 -> 0
B12: 7 | C12: (Net financing cost) | H12: =-$D$53*G37+G36*$D$54 -> #VALUE! | I12: =-$D$53*H37+H36*$D$54 -> #VALUE! | J12: =-$D$53*I37+I36*$D$54 -> #VALUE! | K12: =-$D$53*J37+J36*$D$54 -> #VALUE! | L12: =-$D$53*K37+K36*$D$54 -> #VALUE! | M12: =-$D$53*L37+L36*$D$54 -> #VALUE! | N12: =-$D$53*M37+M36*$D$54 -> #VALUE! | O12: =-$D$53*N37+N36*$D$54 -> #VALUE! | ... AF12: =-$D$53*AE37+AE36*$D$54 -> #VALUE!
B13: 8 | C13: Other income/(cost) | H13: 0 | I13: =H13*(1+I5) -> #DIV/0! | J13: =I13*(1+J5) -> #DIV/0! | K13: =J13*(1+K5) -> #DIV/0! | L13: =K13*(1+L5) -> #DIV/0! | M13: =L13*(1+M5) -> #DIV/0! | N13: =M13*(1+N5) -> #DIV/0! | O13: =N13*(1+O5) -> #DIV/0! | P13: =O13*(1+P5) -> #DIV/0! | ... AF13: =AE13*(1+AF5) -> #DIV/0!
B14: 9 | C14: Earnings before taxes | D14: =D8+D12+D13 -> 0 | E14: =E8+E12+E13 -> 0 | F14: =F8+F12+F13 -> 0 | G14: =G8+G12+G13 -> 0 | H14: =H8+H12+H13 -> #VALUE! | I14: =I8+I12+I13 -> #VALUE! | J14: =J8+J12+J13 -> #VALUE! | K14: =K8+K12+K13 -> #VALUE! | ... AF14: =AF8+AF12+AF13 -> #VALUE!
B15: 10 | C15: (Income tax) | H15: =(-1*$D$52)*H14 -> #VALUE! | I15: =(-1*$D$52)*I14 -> #VALUE! | J15: =(-1*$D$52)*J14 -> #VALUE! | K15: =(-1*$D$52)*K14 -> #VALUE! | L15: =(-1*$E$52)*L14 -> #VALUE! | M15: =(-1*$E$52)*M14 -> #VALUE! | N15: =(-1*$E$52)*N14 -> #VALUE! | O15: =(-1*$E$52)*O14 -> #VALUE! | P15: =(-1*$E$52)*P14 -> #VALUE! | Q15: =(-1*$E$52)*Q14 -> #VALUE! | R15: =(-1*$E$52)*R14 -> #VALUE! | S15: =(-1*$E$52)*S14 -> #VALUE! | ... AF15: =(-1*$E$52)*AF14 -> #VALUE!
B16: 11 | C16: Net income | D16: =D14+D15 -> 0 | E16: =E14+E15 -> 0 | F16: =F14+F15 -> 0 | G16: =G14+G15 -> 0 | H16: =H14+H15 -> #VALUE! | I16: =I14+I15 -> #VALUE! | J16: =J14+J15 -> #VALUE! | K16: =K14+K15 -> #VALUE! | ... AF16: =AF14+AF15 -> #VALUE!
A18: CASH FLOW STATEMENT | B18: 12 | C18: Operating cash flows before WK | H18: =H11+H12+H13+H15 -> #VALUE! | I18: =I11+I12+I13+I15 -> #VALUE! | J18: =J11+J12+J13+J15 -> #VALUE! | K18: =K11+K12+K13+K15 -> #VALUE! | L18: =L11+L12+L13+L15 -> #VALUE! | M18: =M11+M12+M13+M15 -> #VALUE! | N18: =N11+N12+N13+N15 -> #VALUE! | O18: =O11+O12+O13+O15 -> #VALUE! | ... AF18: =AF11+AF12+AF13+AF15 -> #VALUE!
B19: 13 | C19: (Stock-based compensation) | H19: =$D$55*H10 -> 0 | I19: =$D$55*I10 -> 0 | J19: =$D$55*J10 -> 0 | K19: =$D$55*K10 -> 0 | L19: =$D$55*L10 -> 0 | M19: =$D$55*M10 -> 0 | N19: =$D$55*N10 -> 0 | O19: =$D$55*O10 -> 0 | ... AF19: =$D$55*AF10 -> 0
B20: 14 | C20: (Working Capital Flows) | H20: =$D$56*(H6-G6) -> 0 | I20: =$D$56*(I6-H6) -> 0 | J20: =$D$56*(J6-I6) -> 0 | K20: =$D$56*(K6-J6) -> 0 | L20: =$E$56*(L6-K6) -> 0 | M20: =$E$56*(M6-L6) -> 0 | N20: =$E$56*(N6-M6) -> 0 | O20: =$E$56*(O6-N6) -> 0 | P20: =$E$56*(P6-O6) -> 0 | Q20: =$E$56*(Q6-P6) -> 0 | R20: =$E$56*(R6-Q6) -> 0 | S20: =$E$56*(S6-R6) -> 0 | ... AF20: =$E$56*(AF6-AE6) -> 0
B21: 15 | C21: -Total Operating Cash Flow | D21: =D18+D19+D20 -> 0 | E21: =E18+E19+E20 -> 0 | F21: =F18+F19+F20 -> 0 | G21: =G18+G19+G20 -> 0 | H21: =H18+H19+H20 -> #VALUE! | I21: =I18+I19+I20 -> #VALUE! | J21: =J18+J19+J20 -> #VALUE! | K21: =K18+K19+K20 -> #VALUE! | ... AF21: =AF18+AF19+AF20 -> #VALUE!
B22: 16 | C22: (CAPEX and Acquisitions) | H22: =-$D$57*H6 -> 0 | I22: =-$D$57*I6 -> 0 | J22: =-$D$57*J6 -> 0 | K22: =-$D$57*K6 -> 0 | L22: =-$E$57*L6 -> 0 | M22: =-$E$57*M6 -> 0 | N22: =-$E$57*N6 -> 0 | O22: =-$E$57*O6 -> 0 | P22: =-$E$57*P6 -> 0 | Q22: =-$E$57*Q6 -> 0 | R22: =-$E$57*R6 -> 0 | S22: =-$E$57*S6 -> 0 | ... AF22: =-$E$57*AF6 -> 0
B23: 17 | C23: (Other investing flows) | H23: 0 | I23: 0 | J23: 0 | K23: 0 | L23: 0 | M23: 0 | N23: 0 | O23: 0 | P23: 0 | Q23: 0 | R23: 0 | S23: 0 | T23: 0 | U23: 0 | V23: 0 | W23: 0 | X23: 0 | Y23: 0 | Z23: 0 | AA23: 0 | AB23: 0 | AC23: 0 | AD23: 0 | AE23: 0 | AF23: 0
B24: 18 | C24: -Total Investing Flows | D24: =D22+D23 -> 0 | E24: =E22+E23 -> 0 | F24: =F22+F23 -> 0 | G24: =G22+G23 -> 0 | H24: =H22+H23 -> 0 | I24: =I22+I23 -> 0 | J24: =J22+J23 -> 0 | K24: =K22+K23 -> 0 | ... AF24: =AF22+AF23 -> 0
B25: 19 | C25: (Flows related to leases) | H25: 0 | I25: 0 | J25: 0 | K25: 0 | L25: 0 | M25: 0 | N25: 0 | O25: 0 | P25: 0 | Q25: 0 | R25: 0 | S25: 0 | T25: 0 | U25: 0 | V25: 0 | W25: 0 | X25: 0 | Y25: 0 | Z25: 0 | AA25: 0 | AB25: 0 | AC25: 0 | AD25: 0 | AE25: 0 | AF25: 0
B26: 20 | C26: Flows related to debt | H26: =(H37-G37) -> 0 | I26: =(I37-H37) -> 0 | J26: =(J37-I37) -> 0 | K26: =(K37-J37) -> 0 | L26: =(L37-K37) -> 0 | M26: =(M37-L37) -> 0 | N26: =(N37-M37) -> 0 | O26: =(O37-N37) -> 0 | ... AF26: =(AF37-AE37) -> 0
B27: 21 | C27: (Respurchases)/Issuance of stock | H27: =(H21+H24+H28)*-1 -> #VALUE! | I27: =(I21+I24+I28)*-0.95 -> #VALUE! | J27: =(J21+J24+J28)*-0.95 -> #VALUE! | K27: =(K21+K24+K28)*-0.95 -> #VALUE! | L27: =(L21+L24+L28)*-0.95 -> #VALUE! | M27: =(M21+M24+M28)*-0.95 -> #VALUE! | N27: =(N21+N24+N28)*-0.95 -> #VALUE! | O27: =(O21+O24+O28)*-0.95 -> #VALUE! | P27: =(P21+P24+P28)*-0.95 -> #VALUE! | ... AF27: =(AF21+AF24+AF28)*-0.95 -> #VALUE!
B28: 22 | C28: (Dividends) | H28: =(1+$D$58)*G28 -> 0 | I28: =(1+$D$58)*H28 -> 0 | J28: =(1+$D$58)*I28 -> 0 | K28: =(1+$D$58)*J28 -> 0 | L28: =(1+$E$58)*K28 -> 0 | M28: =(1+$E$58)*L28 -> 0 | N28: =(1+$E$58)*M28 -> 0 | O28: =(1+$E$58)*N28 -> 0 | P28: =(1+$E$58)*O28 -> 0 | Q28: =(1+$E$58)*P28 -> 0 | R28: =(1+$E$58)*Q28 -> 0 | S28: =(1+$E$58)*R28 -> 0 | ... AF28: =(1+$E$58)*AE28 -> 0
B29: 23 | C29: Other financing flows | H29: 0 | I29: 0 | J29: 0 | K29: 0 | L29: 0 | M29: 0 | N29: 0 | O29: 0 | P29: 0 | Q29: 0 | R29: 0 | S29: 0 | T29: 0 | U29: 0 | V29: 0 | W29: 0 | X29: 0 | Y29: 0 | Z29: 0 | AA29: 0 | AB29: 0 | AC29: 0 | AD29: 0 | AE29: 0 | AF29: 0
B30: 24 | C30: -Total Financing flows | D30: =SUM(D25:D29) -> 0 | E30: =SUM(E25:E29) -> 0 | F30: =SUM(F25:F29) -> 0 | G30: =SUM(G25:G29) -> 0 | H30: =SUM(H25:H29) -> #VALUE! | I30: =SUM(I25:I29) -> #VALUE! | J30: =SUM(J25:J29) -> #VALUE! | K30: =SUM(K25:K29) -> #VALUE! | ... AF30: =SUM(AF25:AF29) -> #VALUE!
A32: SUMMARY | B32: 25 | C32: Cash before shareholder returns | D32: =D21+D24+D25+D26+D29 -> 0 | E32: =E21+E24+E25+E26+E29 -> 0 | F32: =F21+F24+F25+F26+F29 -> 0 | G32: =G21+G24+G25+G26+G29 -> 0 | H32: =H21+H24+H25+H26+H29 -> #VALUE! | I32: =I21+I24+I25+I26+I29 -> #VALUE! | J32: =J21+J24+J25+J26+J29 -> #VALUE! | K32: =K21+K24+K25+K26+K29 -> #VALUE! | ... AF32: =AF21+AF24+AF25+AF26+AF29 -> #VALUE!
B33: 26 | C33: Returns to shareholders | D33: =-1*(D27+D28) -> 0 | E33: =-1*(E27+E28) -> 0 | F33: =-1*(F27+F28) -> 0 | G33: =-1*(G27+G28) -> 0 | H33: =-1*(H27+H28) -> #VALUE! | I33: =-1*(I27+I28) -> #VALUE! | J33: =-1*(J27+J28) -> #VALUE! | K33: =-1*(K27+K28) -> #VALUE! | ... AF33: =-1*(AF27+AF28) -> #VALUE!
B34: 27 | C34: Excess cash acumulation | D34: =D32-D33 -> 0 | E34: =E32-E33 -> 0 | F34: =F32-F33 -> 0 | G34: =G32-G33 -> 0 | H34: =H32-H33 -> #VALUE! | I34: =I32-I33 -> #VALUE! | J34: =J32-J33 -> #VALUE! | K34: =K32-K33 -> #VALUE! | ... AF34: =AF32-AF33 -> #VALUE!
A36: CASH & DEBT & DISCOUNTING | B36: 28 | C36: Ending cash balance | D36: =C36+D34 -> #VALUE! | E36: =D36+E34 -> #VALUE! | F36: =E36+F34 -> #VALUE! | G36: =F36+G34 -> #VALUE! | H36: =G36+H34 -> #VALUE! | I36: =H36+I34 -> #VALUE! | J36: =I36+J34 -> #VALUE! | K36: =J36+K34 -> #VALUE! | ... AF36: =AE36+AF34 -> #VALUE!
B37: 29 | C37: Total Debt | D37: =Cifras_en_Millones!F60 -> 0 | E37: =Cifras_en_Millones!E60 -> 0 | F37: =Cifras_en_Millones!D60 -> 0 | G37: =Cifras_en_Millones!C60 -> 0 | H37: =G37 -> 0 | I37: =H37 -> 0 | J37: =I37 -> 0 | K37: =J37 -> 0 | L37: =K37 -> 0 | M37: =L37 -> 0 | N37: =M37 -> 0 | O37: =N37 -> 0 | ... AF37: =AE37 -> 0
B38: 30 | C38: Discount factor | G38: =1/((1+$D$47)^G3) -> 1 | H38: =1/((1+$D$47)^H3) -> 1 | I38: =1/((1+$D$47)^I3) -> 1 | J38: =1/((1+$D$47)^J3) -> 1 | K38: =1/((1+$D$47)^K3) -> 1 | L38: =1/((1+$D$47)^L3) -> 1 | M38: =1/((1+$D$47)^M3) -> 1 | N38: =1/((1+$D$47)^N3) -> 1 | ... AF38: =1/((1+$D$47)^AF3) -> 1
F39: =1/((1+$D$48+0.001)^F$3) -> #DIV/0! | G39: =1/((1+$D$47+0.001)^G$3) -> 1 | H39: =1/((1+$D$47+0.001)^H$3) -> 0.99975016 | I39: =1/((1+$D$47+0.001)^I$3) -> 0.9987514 | J39: =1/((1+$D$47+0.001)^J$3) -> 0.99775365 | K39: =1/((1+$D$47+0.001)^K$3) -> 0.99675689 | L39: =1/((1+$D$47+0.001)^L$3) -> 0.99576113 | M39: =1/((1+$D$47+0.001)^M$3) -> 0.99476637 | N39: =1/((1+$D$47+0.001)^N$3) -> 0.99377259 | ... AE39: =1/((1+$D$47+0.001)^AE$3) -> 0.97702955
F40: =1/((1+$D$48+0.005)^F$3) -> #DIV/0! | G40: =1/((1+$D$47+0.005)^G$3) -> 1 | H40: =1/((1+$D$47+0.005)^H$3) -> 0.99875389 | I40: =1/((1+$D$47+0.005)^I$3) -> 0.99378497 | J40: =1/((1+$D$47+0.005)^J$3) -> 0.98884076 | K40: =1/((1+$D$47+0.005)^K$3) -> 0.98392116 | L40: =1/((1+$D$47+0.005)^L$3) -> 0.97902603 | M40: =1/((1+$D$47+0.005)^M$3) -> 0.97415525 | N40: =1/((1+$D$47+0.005)^N$3) -> 0.96930871 | ... AE40: =1/((1+$D$47+0.005)^AE$3) -> 0.89051054
C42: EPS | H42: =1000000*H16/OP!C8 -> #VALUE! | I42: =1000000*I16/OP!$C8 -> #VALUE! | J42: =1000000*J16/OP!$C8 -> #VALUE!
C43: Consenso EPS
C44: E$/UN | H44: =$D$64/H16 -> #VALUE! | I44: =$D$64/I16 -> #VALUE!
A46: Discount rate | D46: Total | E46: Risk free rate | F46: Equity premium | G46: Firm premium
C47: Discount Rate | D47: =SUM(E47:G47) -> 0
D49: Short Term | E49: Long Term | F49: Reference (line)
A50: Modelling factors | C50: Depreciation factor | F50: % Capex/Adq (l16) | G50: =SUM(G22:AF22)/SUM(G9:AF9) -> #DIV/0!
C51: Stock-based comp | F51: % revenue (l2) | G51: =-SUM(D10:F10)/SUM(D6:F6) -> #DIV/0!
C52: Tax Rate | F52: % (line 9)
C53: Interest Rate on debt | F53: % debt (l29)
C54: Interest Rate on cash | F54: % of cash (l28)
C55: Net SBC | F55: % revenue (l2)
C56: Working capital flows | F56: % of change revenues (l2)
C57: Capex / Adq | F57: % revenue (l2)
C58: Dividends | F58: Growth rate
C59: Other financing flows | F59: % of debt (l29)
A61: Valuation | D61: $ millions | E61: % | F61: Notes | AE61: =((AE36-AE37)*AE38) -> #VALUE!
C62: Value of flows | D62: =SUMPRODUCT(G33:AE33,G38:AE38)+((AE36-AE37)*AE38) -> #VALUE! | E62: =D62/D64 -> #VALUE! | F62: Present value of flows (l27), plus cash minus debt | AE62: =AE54+AE61 -> #VALUE!
C63: Value of perpetuity | D63: =(AF32/(D47-AF5))*AF38 -> #VALUE! | E63: =D63/D64 -> #VALUE! | F63: Present value of perpetuity (column AF flow, dividend by growth minus discount rate)
C64: Total Value | D64: =D62+D63 -> #VALUE! | F64: Final market value of firm's equity, compare to its mkt cap
C65: Total value vs Mkt Cap | D65: =D66/D67-1 -> #VALUE! | F65: Gives degree of undervaluation (if positive, meaning it's worth more than what the market thinks) or overvaluation (negative, worth less than what the market thinks)
C66: Estimated NPV per share | D66: =1000000*D64/OP!C8 -> #VALUE! | F66: If we divide total value by # of shares, we get the estimated share value
C67: Actual share price | D67: =OP!C7 -> 0 | F67: Actual share price

Sheet Cifras_en_Millones
A1: =Cifras_Originales!G3 -> (Company name) ((ticker))
A2: =Cifras_Originales!C2 -> Cifras en Millones de USD
A4: Resultados | B4: 2024 | C4: =Cifras_Originales!B5 -> 2023 | D4: =Cifras_Originales!C5 -> 2022 | E4: =Cifras_Originales!D5 -> 2021 | F4: =Cifras_Originales!E5 -> 2020 | G4: =Cifras_Originales!F5 -> 2019 | H4: =Cifras_Originales!G5 -> 2018 | I4: =Cifras_Originales!H5 -> 2017 | J4: =Cifras_Originales!I5 -> 2016 | ... M4: =Cifras_Originales!L5 -> 2013
A5: Ventas Netas | C5: =Cifras_Originales!B6 -> 0 | D5: =Cifras_Originales!C6 -> 0 | E5: =Cifras_Originales!D6 -> 0 | F5: =Cifras_Originales!E6 -> 0 | G5: =Cifras_Originales!F6 -> 0 | H5: =Cifras_Originales!G6 -> 0 | I5: =Cifras_Originales!H6 -> 0 | J5: =Cifras_Originales!I6 -> 0 | ... M5: =Cifras_Originales!L6 -> 0
A6: Crecimiento vs. Año pasado | B6: =B5/C5-1 -> #DIV/0! | C6: =C5/D5-1 -> #DIV/0! | D6: =D5/E5-1 -> #DIV/0! | E6: =E5/F5-1 -> #DIV/0! | F6: =F5/G5-1 -> #DIV/0! | G6: =G5/H5-1 -> #DIV/0! | H6: =H5/I5-1 -> #DIV/0! | I6: =I5/J5-1 -> #DIV/0! | ... L6: =L5/M5-1 -> #DIV/0!
A7: Utilidad Bruta | C7: =Cifras_Originales!B7 -> 0 | D7: =Cifras_Originales!C7 -> 0 | E7: =Cifras_Originales!D7 -> 0 | F7: =Cifras_Originales!E7 -> 0 | G7: =Cifras_Originales!F7 -> 0 | H7: =Cifras_Originales!G7 -> 0 | I7: =Cifras_Originales!H7 -> 0 | J7: =Cifras_Originales!I7 -> 0 | ... M7: =Cifras_Originales!L7 -> 0
A8: porcentaje sobre ventas | B8: =B7/B5 -> #DIV/0! | C8: =C7/C5 -> #DIV/0! | D8: =D7/D5 -> #DIV/0! | E8: =E7/E5 -> #DIV/0! | F8: =F7/F5 -> #DIV/0! | G8: =G7/G5 -> #DIV/0! | H8: =H7/H5 -> #DIV/0! | I8: =I7/I5 -> #DIV/0! | ... M8: =M7/M5 -> #DIV/0!
A9: Gastos de Operación | B9: =B5-B11 -> 0 | C9: =C5-C11 -> 0 | D9: =D5-D11 -> 0 | E9: =E5-E11 -> 0 | F9: =F5-F11 -> 0 | G9: =G5-G11 -> 0 | H9: =H5-H11 -> 0 | I9: =I5-I11 -> 0 | ... M9: =M5-M11 -> 0
A10: porcentaje sobre ventas | B10: =B9/B5 -> #DIV/0! | C10: =C9/C5 -> #DIV/0! | D10: =D9/D5 -> #DIV/0! | E10: =E9/E5 -> #DIV/0! | F10: =F9/F5 -> #DIV/0! | G10: =G9/G5 -> #DIV/0! | H10: =H9/H5 -> #DIV/0! | I10: =I9/I5 -> #DIV/0! | ... M10: =M9/M5 -> #DIV/0!
A11: Utilidad de Operación | C11: =Cifras_Originales!B8 -> 0 | D11: =Cifras_Originales!C8 -> 0 | E11: =Cifras_Originales!D8 -> 0 | F11: =Cifras_Originales!E8 -> 0 | G11: =Cifras_Originales!F8 -> 0 | H11: =Cifras_Originales!G8 -> 0 | I11: =Cifras_Originales!H8 -> 0 | J11: =Cifras_Originales!I8 -> 0 | ... M11: =Cifras_Originales!L8 -> 0
A12: porcentaje sobre ventas | B12: =B11/B5 -> #DIV/0! | C12: =C11/C5 -> #DIV/0! | D12: =D11/D5 -> #DIV/0! | E12: =E11/E5 -> #DIV/0! | F12: =F11/F5 -> #DIV/0! | G12: =G11/G5 -> #DIV/0! | H12: =H11/H5 -> #DIV/0! | I12: =I11/I5 -> #DIV/0! | ... M12: =M11/M5 -> #DIV/0!
A13: Crecimiento vs año anterior | B13: =B11/C11-1 -> #DIV/0! | C13: =C11/D11-1 -> #DIV/0! | D13: =D11/E11-1 -> #DIV/0! | E13: =E11/F11-1 -> #DIV/0! | F13: =F11/G11-1 -> #DIV/0! | G13: =G11/H11-1 -> #DIV/0! | H13: =H11/I11-1 -> #DIV/0! | I13: =I11/J11-1 -> #DIV/0! | ... L13: =L11/M11-1 -> #DIV/0!
A14: CIF (Productos Financieros) | C14: =Cifras_Originales!B9 -> 0 | D14: =Cifras_Originales!C9 -> 0 | E14: =Cifras_Originales!D9 -> 0 | F14: =Cifras_Originales!E9 -> 0 | G14: =Cifras_Originales!F9 -> 0 | H14: =Cifras_Originales!G9 -> 0 | I14: =Cifras_Originales!H9 -> 0 | J14: =Cifras_Originales!I9 -> 0 | ... M14: =Cifras_Originales!L9 -> 0
A15: Otros Gastos (Productos) | C15: =Cifras_Originales!B10 -> 0 | D15: =Cifras_Originales!C10 -> 0 | E15: =Cifras_Originales!D10 -> 0 | F15: =Cifras_Originales!E10 -> 0 | G15: =Cifras_Originales!F10 -> 0 | H15: =Cifras_Originales!G10 -> 0 | I15: =Cifras_Originales!H10 -> 0 | J15: =Cifras_Originales!I10 -> 0 | ... M15: =Cifras_Originales!L10 -> 0
A16: Utilidad antes de Impuestos y partidas extra. | B16: =B11-B14-B15 -> 0 | C16: =C11-C14-C15 -> 0 | D16: =D11-D14-D15 -> 0 | E16: =E11-E14-E15 -> 0 | F16: =F11-F14-F15 -> 0 | G16: =G11-G14-G15 -> 0 | H16: =H11-H14-H15 -> 0 | I16: =I11-I14-I15 -> 0 | ... M16: =M11-M14-M15 -> 0
A17: Depreciación y amortización del ejercicio | C17: =Cifras_Originales!B11 -> 0 | D17: =Cifras_Originales!C11 -> 0 | E17: =Cifras_Originales!D11 -> 0 | F17: =Cifras_Originales!E11 -> 0 | G17: =Cifras_Originales!F11 -> 0 | H17: =Cifras_Originales!G11 -> 0 | I17: =Cifras_Originales!H11 -> 0 | J17: =Cifras_Originales!I11 -> 0 | ... M17: =Cifras_Originales!L11 -> 0
A18: Capital de Trabajo | C18: =Cifras_Originales!B12 -> 0 | D18: =Cifras_Originales!C12 -> 0 | E18: =Cifras_Originales!D12 -> 0 | F18: =Cifras_Originales!E12 -> 0 | G18: =Cifras_Originales!F12 -> 0 | H18: =Cifras_Originales!G12 -> 0 | I18: =Cifras_Originales!H12 -> 0 | J18: =Cifras_Originales!I12 -> 0 | ... M18: =Cifras_Originales!L12 -> 0
A19: EBITDA (flujo operativo) | B19: =B11-B15+B17 -> 0 | C19: =C11-C15+C17 -> 0 | D19: =D11-D15+D17 -> 0 | E19: =E11-E15+E17 -> 0 | F19: =F11-F15+F17 -> 0 | G19: =G11-G15+G17 -> 0 | H19: =H11-H15+H17 -> 0 | I19: =I11-I15+I17 -> 0 | ... M19: =M11-M15+M17 -> 0
A20: porcentaje sobre ventas | B20: =B19/B5 -> #DIV/0! | C20: =C19/C5 -> #DIV/0! | D20: =D19/D5 -> #DIV/0! | E20: =E19/E5 -> #DIV/0! | F20: =F19/F5 -> #DIV/0! | G20: =G19/G5 -> #DIV/0! | H20: =H19/H5 -> #DIV/0! | I20: =I19/I5 -> #DIV/0! | ... M20: =M19/M5 -> #DIV/0!
A21: I.S.R Y P.T.U. | C21: =Cifras_Originales!B15 -> 0 | D21: =Cifras_Originales!C15 -> 0 | E21: =Cifras_Originales!D15 -> 0 | F21: =Cifras_Originales!E15 -> 0 | G21: =Cifras_Originales!F15 -> 0 | H21: =Cifras_Originales!G15 -> 0 | I21: =Cifras_Originales!H15 -> 0 | J21: =Cifras_Originales!I15 -> 0 | ... M21: =Cifras_Originales!L15 -> 0
A22: % Tax | B22: =+B21/B16 -> #DIV/0! | C22: =+C21/C16 -> #DIV/0! | D22: =+D21/D16 -> #DIV/0! | E22: =+E21/E16 -> #DIV/0! | F22: =+F21/F16 -> #DIV/0! | G22: =+G21/G16 -> #DIV/0! | H22: =+H21/H16 -> #DIV/0! | I22: =+I21/I16 -> #DIV/0! | ... M22: =+M21/M16 -> #DIV/0!
A23: Utilidad Neta | C23: =Cifras_Originales!B16 -> 0 | D23: =Cifras_Originales!C16 -> 0 | E23: =Cifras_Originales!D16 -> 0 | F23: =Cifras_Originales!E16 -> 0 | G23: =Cifras_Originales!F16 -> 0 | H23: =Cifras_Originales!G16 -> 0 | I23: =Cifras_Originales!H16 -> 0 | J23: =Cifras_Originales!I16 -> 0 | ... M23: =Cifras_Originales!L16 -> 0
A24: porcentaje sobre ventas | B24: =B23/B5 -> #DIV/0! | C24: =C23/C5 -> #DIV/0! | D24: =D23/D5 -> #DIV/0! | E24: =E23/E5 -> #DIV/0! | F24: =F23/F5 -> #DIV/0! | G24: =G23/G5 -> #DIV/0! | H24: =H23/H5 -> #DIV/0! | I24: =I23/I5 -> #DIV/0! | ... M24: =M23/M5 -> #DIV/0!
A25: Crecimiento vs año anterior | B25: =B23/C23-1 -> #DIV/0! | C25: =C23/D23-1 -> #DIV/0! | D25: =D23/E23-1 -> #DIV/0! | E25: =E23/F23-1 -> #DIV/0! | F25: =F23/G23-1 -> #DIV/0! | G25: =G23/H23-1 -> #DIV/0! | H25: =H23/I23-1 -> #DIV/0! | I25: =I23/J23-1 -> #DIV/0! | ... L25: =L23/M23-1 -> #DIV/0!
A26: Efectivo Generado | B26: =B40-C40 -> 0 | C26: =C40-D40 -> 0 | D26: =D40-E40 -> 0 | E26: =E40-F40 -> 0 | F26: =F40-G40 -> 0 | G26: =G40-H40 -> 0 | H26: =H40-I40 -> 0 | I26: =I40-J40 -> 0 | ... M26: =M40-N40 -> 0
A27: Dividendos | C27: =Cifras_Originales!B17 -> 0 | D27: =Cifras_Originales!C17 -> 0 | E27: =Cifras_Originales!D17 -> 0 | F27: =Cifras_Originales!E17 -> 0 | G27: =Cifras_Originales!F17 -> 0 | H27: =Cifras_Originales!G17 -> 0 | I27: =Cifras_Originales!H17 -> 0 | J27: =Cifras_Originales!I17 -> 0 | ... M27: =Cifras_Originales!L17 -> 0
B28: =B27/C27-1 -> #DIV/0! | C28: =C27/D27-1 -> #DIV/0! | D28: =D27/E27-1 -> #DIV/0! | E28: =E27/F27-1 -> #DIV/0! | F28: =F27/G27-1 -> #DIV/0! | G28: =G27/H27-1 -> #DIV/0! | H28: =H27/I27-1 -> #DIV/0! | I28: =I27/J27-1 -> #DIV/0! | ... L28: =L27/M27-1 -> #DIV/0!
A29: Recompra de Acciones | C29: =Cifras_Originales!B18 -> 0 | D29: =Cifras_Originales!C18 -> 0 | E29: =Cifras_Originales!D18 -> 0 | F29: =Cifras_Originales!E18 -> 0 | G29: =Cifras_Originales!F18 -> 0 | H29: =Cifras_Originales!G18 -> 0 | I29: =Cifras_Originales!H18 -> 0 | J29: =Cifras_Originales!I18 -> 0 | ... M29: =Cifras_Originales!L18 -> 0
A30: FNP | B30: =SUM(B26:B29) -> #DIV/0! | C30: =SUM(C26:C29) -> #DIV/0! | D30: =SUM(D26:D29) -> #DIV/0! | E30: =SUM(E26:E29) -> #DIV/0! | F30: =SUM(F26:F29) -> #DIV/0! | G30: =SUM(G26:G29) -> #DIV/0! | H30: =SUM(H26:H29) -> #DIV/0! | I30: =SUM(I26:I29) -> #DIV/0! | ... M30: =SUM(M26:M29) -> 0
A31: FNP (ajustado por deuda) | B31: =B30-(B60-C60) -> #DIV/0! | C31: =C30-(C60-D60) -> #DIV/0! | D31: =D30-(D60-E60) -> #DIV/0! | E31: =E30-(E60-F60) -> #DIV/0! | F31: =F30-(F60-G60) -> #DIV/0! | G31: =G30-(G60-H60) -> #DIV/0! | H31: =H30-(H60-I60) -> #DIV/0! | I31: =I30-(I60-J60) -> #DIV/0! | ... M31: =M30-(M60-N60) -> 0
A32: FNP (ajustado por inversiones) | B32: =B31+B34 -> #DIV/0! | C32: =C31+C34 -> #DIV/0! | D32: =D31+D34 -> #DIV/0! | E32: =E31+E34 -> #DIV/0! | F32: =F31+F34 -> #DIV/0! | G32: =G31+G34 -> #DIV/0! | H32: =H31+H34 -> #DIV/0! | I32: =I31+I34 -> #DIV/0! | ... M32: =M31+M34 -> 0
A33: Capex | C33: =Cifras_Originales!B13 -> 0 | D33: =Cifras_Originales!C13 -> 0 | E33: =Cifras_Originales!D13 -> 0 | F33: =Cifras_Originales!E13 -> 0 | G33: =Cifras_Originales!F13 -> 0 | H33: =Cifras_Originales!G13 -> 0 | I33: =Cifras_Originales!H13 -> 0 | J33: =Cifras_Originales!I13 -> 0 | ... M33: =Cifras_Originales!L13 -> 0
A34: Inversiones | C34: =Cifras_Originales!B14 -> 0 | D34: =Cifras_Originales!C14 -> 0 | E34: =Cifras_Originales!D14 -> 0 | F34: =Cifras_Originales!E14 -> 0 | G34: =Cifras_Originales!F14 -> 0 | H34: =Cifras_Originales!G14 -> 0 | I34: =Cifras_Originales!H14 -> 0 | J34: =Cifras_Originales!I14 -> 0 | ... M34: =Cifras_Originales!L14 -> 0
A35: Capex + Inversiones | B35: =+B34+B33 -> 0 | C35: =+C34+C33 -> 0 | D35: =+D34+D33 -> 0 | E35: =+E34+E33 -> 0 | F35: =+F34+F33 -> 0 | G35: =+G34+G33 -> 0 | H35: =+H34+H33 -> 0 | I35: =+I34+I33 -> 0 | ... M35: =+M34+M33 -> 0
B36: =+B35/B5 -> #DIV/0! | C36: =+C35/C5 -> #DIV/0! | D36: =+D35/D5 -> #DIV/0! | E36: =+E35/E5 -> #DIV/0! | F36: =+F35/F5 -> #DIV/0! | G36: =+G35/G5 -> #DIV/0! | H36: =+H35/H5 -> #DIV/0! | I36: =+I35/I5 -> #DIV/0! | ... M36: =+M35/M5 -> #DIV/0!
A37: Dividendos + Recompra de Acciones | B37: =SUM(B27:B29) -> #DIV/0! | C37: =SUM(C27:C29) -> #DIV/0! | D37: =SUM(D27:D29) -> #DIV/0! | E37: =SUM(E27:E29) -> #DIV/0! | F37: =SUM(F27:F29) -> #DIV/0! | G37: =SUM(G27:G29) -> #DIV/0! | H37: =SUM(H27:H29) -> #DIV/0! | I37: =SUM(I27:I29) -> #DIV/0! | ... M37: =SUM(M27:M29) -> 0
A39: Activo
A40: Caja | C40: =Cifras_Originales!B22 -> 0 | D40: =Cifras_Originales!C22 -> 0 | E40: =Cifras_Originales!D22 -> 0 | F40: =Cifras_Originales!E22 -> 0 | G40: =Cifras_Originales!F22 -> 0 | H40: =Cifras_Originales!G22 -> 0 | I40: =Cifras_Originales!H22 -> 0 | J40: =Cifras_Originales!I22 -> 0 | ... M40: =Cifras_Originales!L22 -> 0
A41: Cuentas y documentos por cobrar | C41: =Cifras_Originales!B23 -> 0 | D41: =Cifras_Originales!C23 -> 0 | E41: =Cifras_Originales!D23 -> 0 | F41: =Cifras_Originales!E23 -> 0 | G41: =Cifras_Originales!F23 -> 0 | H41: =Cifras_Originales!G23 -> 0 | I41: =Cifras_Originales!H23 -> 0 | J41: =Cifras_Originales!I23 -> 0 | ... M41: =Cifras_Originales!L23 -> 0
A42: Inventarios | C42: =Cifras_Originales!B24 -> 0 | D42: =Cifras_Originales!C24 -> 0 | E42: =Cifras_Originales!D24 -> 0 | F42: =Cifras_Originales!E24 -> 0 | G42: =Cifras_Originales!F24 -> 0 | H42: =Cifras_Originales!G24 -> 0 | I42: =Cifras_Originales!H24 -> 0 | J42: =Cifras_Originales!I24 -> 0 | ... M42: =Cifras_Originales!L24 -> 0
A43: Activos Fijos (Net Plant) | C43: =Cifras_Originales!B25 -> 0 | D43: =Cifras_Originales!C25 -> 0 | E43: =Cifras_Originales!D25 -> 0 | F43: =Cifras_Originales!E25 -> 0 | G43: =Cifras_Originales!F25 -> 0 | H43: =Cifras_Originales!G25 -> 0 | I43: =Cifras_Originales!H25 -> 0 | J43: =Cifras_Originales!I25 -> 0 | ... M43: =Cifras_Originales!L25 -> 0
A44: Otros Activos | B44: =B45-SUM(B40:B43) -> 0 | C44: =Cifras_Originales!B26 -> 0 | D44: =Cifras_Originales!C26 -> 0 | E44: =Cifras_Originales!D26 -> 0 | F44: =Cifras_Originales!E26 -> 0 | G44: =Cifras_Originales!F26 -> 0 | H44: =Cifras_Originales!G26 -> 0 | I44: =Cifras_Originales!H26 -> 0 | J44: =Cifras_Originales!I26 -> 0 | ... M44: =Cifras_Originales!L26 -> 0
A45: Total Activo | C45: =Cifras_Originales!B27 -> 0 | D45: =Cifras_Originales!C27 -> 0 | E45: =Cifras_Originales!D27 -> 0 | F45: =Cifras_Originales!E27 -> 0 | G45: =Cifras_Originales!F27 -> 0 | H45: =Cifras_Originales!G27 -> 0 | I45: =Cifras_Originales!H27 -> 0 | J45: =Cifras_Originales!I27 -> 0 | ... M45: =Cifras_Originales!L27 -> 0
A48: Pasivo
A49: Pasivo Corto Plazo | C49: =Cifras_Originales!B31 -> 0 | D49: =Cifras_Originales!C31 -> 0 | E49: =Cifras_Originales!D31 -> 0 | F49: =Cifras_Originales!E31 -> 0 | G49: =Cifras_Originales!F31 -> 0 | H49: =Cifras_Originales!G31 -> 0 | I49: =Cifras_Originales!H31 -> 0 | J49: =Cifras_Originales!I31 -> 0 | ... M49: =Cifras_Originales!L31 -> 0
A50: Deuda a corto plazo | C50: =Cifras_Originales!B32 -> 0 | D50: =Cifras_Originales!C32 -> 0 | E50: =Cifras_Originales!D32 -> 0 | F50: =Cifras_Originales!E32 -> 0 | G50: =Cifras_Originales!F32 -> 0 | H50: =Cifras_Originales!G32 -> 0 | I50: =Cifras_Originales!H32 -> 0 | J50: =Cifras_Originales!I32 -> 0 | ... M50: =Cifras_Originales!L32 -> 0
A51: Short-Term Leases | C51: =Cifras_Originales!B33 -> 0 | D51: =Cifras_Originales!C33 -> 0 | E51: =Cifras_Originales!D33 -> 0 | F51: =Cifras_Originales!E33 -> 0 | G51: =Cifras_Originales!F33 -> 0 | H51: =Cifras_Originales!G33 -> 0 | I51: =Cifras_Originales!H33 -> 0 | J51: =Cifras_Originales!I33 -> 0 | ... M51: =Cifras_Originales!L33 -> 0
A52: Otros Pasivos a Corto Plazo | C52: =Cifras_Originales!B34 -> 0 | D52: =Cifras_Originales!C34 -> 0 | E52: =Cifras_Originales!D34 -> 0 | F52: =Cifras_Originales!E34 -> 0 | G52: =Cifras_Originales!F34 -> 0 | H52: =Cifras_Originales!G34 -> 0 | I52: =Cifras_Originales!H34 -> 0 | J52: =Cifras_Originales!I34 -> 0 | ... M52: =Cifras_Originales!L34 -> 0
A53: Pasivo Largo Plazo | C53: =Cifras_Originales!B35 -> 0 | D53: =Cifras_Originales!C35 -> 0 | E53: =Cifras_Originales!D35 -> 0 | F53: =Cifras_Originales!E35 -> 0 | G53: =Cifras_Originales!F35 -> 0 | H53: =Cifras_Originales!G35 -> 0 | I53: =Cifras_Originales!H35 -> 0 | J53: =Cifras_Originales!I35 -> 0 | ... M53: =Cifras_Originales!L35 -> 0
A54: Deuda a largo plazo | C54: =Cifras_Originales!B36 -> 0 | D54: =Cifras_Originales!C36 -> 0 | E54: =Cifras_Originales!D36 -> 0 | F54: =Cifras_Originales!E36 -> 0 | G54: =Cifras_Originales!F36 -> 0 | H54: =Cifras_Originales!G36 -> 0 | I54: =Cifras_Originales!H36 -> 0 | J54: =Cifras_Originales!I36 -> 0 | ... M54: =Cifras_Originales!L36 -> 0
A55: Long-Term Leases | C55: =Cifras_Originales!B37 -> 0 | D55: =Cifras_Originales!C37 -> 0 | E55: =Cifras_Originales!D37 -> 0 | F55: =Cifras_Originales!E37 -> 0 | G55: =Cifras_Originales!F37 -> 0 | H55: =Cifras_Originales!G37 -> 0 | I55: =Cifras_Originales!H37 -> 0 | J55: =Cifras_Originales!I37 -> 0 | ... M55: =Cifras_Originales!L37 -> 0
A56: Otros Pasivos a Largo Plazo | B56: =B53-SUM(B54:B55) -> 0 | C56: =Cifras_Originales!B38 -> 0 | D56: =Cifras_Originales!C38 -> 0 | E56: =Cifras_Originales!D38 -> 0 | F56: =Cifras_Originales!E38 -> 0 | G56: =Cifras_Originales!F38 -> 0 | H56: =Cifras_Originales!G38 -> 0 | I56: =Cifras_Originales!H38 -> 0 | J56: =Cifras_Originales!I38 -> 0 | ... M56: =Cifras_Originales!L38 -> 0
A57: Total pasivos | C57: =Cifras_Originales!B39 -> 0 | D57: =Cifras_Originales!C39 -> 0 | E57: =Cifras_Originales!D39 -> 0 | F57: =Cifras_Originales!E39 -> 0 | G57: =Cifras_Originales!F39 -> 0 | H57: =Cifras_Originales!G39 -> 0 | I57: =Cifras_Originales!H39 -> 0 | J57: =Cifras_Originales!I39 -> 0 | ... M57: =Cifras_Originales!L39 -> 0
A59: Deuda Neta | B59: =B60-B40 -> 0 | C59: =C60-C40 -> 0 | D59: =D60-D40 -> 0 | E59: =E60-E40 -> 0 | F59: =F60-F40 -> 0 | G59: =G60-G40 -> 0 | H59: =H60-H40 -> 0 | I59: =I60-I40 -> 0 | ... M59: =M60-M40 -> 0
A60: Deuda | B60: =B50+B51+B54+B55 -> 0 | C60: =C50+C51+C54+C55 -> 0 | D60: =D50+D51+D54+D55 -> 0 | E60: =E50+E51+E54+E55 -> 0 | F60: =F50+F51+F54+F55 -> 0 | G60: =G50+G51+G54+G55 -> 0 | H60: =H50+H51+H54+H55 -> 0 | I60: =I50+I51+I54+I55 -> 0 | ... M60: =M50+M51+M54+M55 -> 0
B61: =B60/B45 -> #DIV/0! | C61: =C60/C45 -> #DIV/0! | D61: =D60/D45 -> #DIV/0! | E61: =E60/E45 -> #DIV/0! | F61: =F60/F45 -> #DIV/0! | G61: =G60/G45 -> #DIV/0! | H61: =H60/H45 -> #DIV/0! | I61: =I60/I45 -> #DIV/0! | ... M61: =M60/M45 -> #DIV/0!
A63: Interés Minoritario | B63: 0 | C63: =Cifras_Originales!B42 -> 0 | D63: =Cifras_Originales!C42 -> 0 | E63: =Cifras_Originales!D42 -> 0 | F63: =Cifras_Originales!E42 -> 0 | G63: =Cifras_Originales!F42 -> 0 | H63: =Cifras_Originales!G42 -> 0 | I63: =Cifras_Originales!H42 -> 0 | J63: =Cifras_Originales!I42 -> 0 | ... M63: =Cifras_Originales!L42 -> 0
A66: Capital Contable | B66: =B45-B57-B63 -> 0 | C66: =C45-C57-C63 -> 0 | D66: =D45-D57-D63 -> 0 | E66: =E45-E57-E63 -> 0 | F66: =F45-F57-F63 -> 0 | G66: =G45-G57-G63 -> 0 | H66: =H45-H57-H63 -> 0 | I66: =I45-I57-I63 -> 0 | ... M66: =M45-M57-M63 -> 0
A69: OTROS DATOS AL FIN DE AÑO
A70: Numero deEmpleados | C70: =Cifras_Originales!B47 -> 0 | D70: =Cifras_Originales!C47 -> 0 | E70: =Cifras_Originales!D47 -> 0 | F70: =Cifras_Originales!E47 -> 0 | G70: =Cifras_Originales!F47 -> 0 | H70: =Cifras_Originales!G47 -> 0 | I70: =Cifras_Originales!H47 -> 0 | J70: =Cifras_Originales!I47 -> 0 | ... M70: =Cifras_Originales!L47 -> 0
A71: Acciones en circulación (millones) | C71: =+Cifras_Originales!B48 -> 0 | D71: =+Cifras_Originales!C48 -> 0 | E71: =+Cifras_Originales!D48 -> 0 | F71: =+Cifras_Originales!E48 -> 0 | G71: =+Cifras_Originales!F48 -> 0 | H71: =+Cifras_Originales!G48 -> 0 | I71: =+Cifras_Originales!H48 -> 0 | J71: =+Cifras_Originales!I48 -> 0 | ... M71: =+Cifras_Originales!L48 -> 0
A72: Float | C72: =Cifras_Originales!B49 -> 0 | D72: =Cifras_Originales!C49 -> 0 | E72: =Cifras_Originales!D49 -> 0 | F72: =Cifras_Originales!E49 -> 0 | G72: =Cifras_Originales!F49 -> 0 | H72: =Cifras_Originales!G49 -> 0 | I72: =Cifras_Originales!H49 -> 0 | J72: =Cifras_Originales!I49 -> 0 | ... M72: =Cifras_Originales!L49 -> 0
A73: Insiders Own | C73: =Cifras_Originales!B50 -> 0 | D73: =Cifras_Originales!C50 -> 0 | E73: =Cifras_Originales!D50 -> 0 | F73: =Cifras_Originales!E50 -> 0 | G73: =Cifras_Originales!F50 -> 0 | H73: =Cifras_Originales!G50 -> 0 | I73: =Cifras_Originales!H50 -> 0 | J73: =Cifras_Originales!I50 -> 0 | ... M73: =Cifras_Originales!L50 -> 0
A74: S&P | C74: =+Cifras_Originales!B51 -> 0 | D74: =+Cifras_Originales!C51 -> 0 | E74: =+Cifras_Originales!D51 -> 0 | F74: =+Cifras_Originales!E51 -> 0 | G74: =+Cifras_Originales!F51 -> 0 | H74: =+Cifras_Originales!G51 -> 0 | I74: =+Cifras_Originales!H51 -> 0 | J74: =+Cifras_Originales!I51 -> 0 | ... M74: =+Cifras_Originales!L51 -> 0
A75: =Cifras_Originales!A52 -> Vol. Diario en Millones USD | C75: =Cifras_Originales!B52 -> 0 | D75: =Cifras_Originales!C52 -> 0 | E75: =Cifras_Originales!D52 -> 0 | F75: =Cifras_Originales!E52 -> 0 | G75: =Cifras_Originales!F52 -> 0 | H75: =Cifras_Originales!G52 -> 0 | I75: =Cifras_Originales!H52 -> 0 | J75: =Cifras_Originales!I52 -> 0 | ... M75: =Cifras_Originales!L52 -> 0 | IH75: =Cifras_Originales!GM52 -> 0
B77: =+Cifras_Originales!B53 -> 2021 | C77: =+Cifras_Originales!C53 -> 2022 | D77: =+Cifras_Originales!D53 -> 2023
A78: =Cifras_Originales!A54 -> Posicion en Corto (%) | B78: =Cifras_Originales!B54 -> 0
A79: =Cifras_Originales!A55 -> EPS | B79: =Cifras_Originales!B55 -> 0 | C79: =Cifras_Originales!C55 -> 0 | D79: =Cifras_Originales!D55 -> 0
A81: =+Cifras_Originales!A57 -> BONOS DE LA EMISORA A 3, 5 Y 10 | B81: Precio Medio | C81: Moody's | D81: YTM | E81: DIVISA
A82: =+Cifras_Originales!A58 -> 0 | B82: =+Cifras_Originales!B58 -> 0 | C82: =+Cifras_Originales!C58 -> 0 | D82: =+Cifras_Originales!D58 -> 0 | E82: =+Cifras_Originales!E58 -> 0
A83: =+Cifras_Originales!A59 -> 0 | B83: =+Cifras_Originales!B59 -> 0 | C83: =+Cifras_Originales!C59 -> 0 | D83: =+Cifras_Originales!D59 -> 0 | E83: =+Cifras_Originales!E59 -> 0
A84: =+Cifras_Originales!A60 -> 0 | B84: =+Cifras_Originales!B60 -> 0 | C84: =+Cifras_Originales!C60 -> 0 | D84: =+Cifras_Originales!D60 -> 0 | E84: =+Cifras_Originales!E60 -> 0
A85: =+Cifras_Originales!A61 -> 0 | B85: =+Cifras_Originales!B61 -> 0 | C85: =+Cifras_Originales!C61 -> 0 | D85: =+Cifras_Originales!D61 -> 0 | E85: =+Cifras_Originales!E61 -> 0

Sheet Cifras_Originales
A1: USD
A2: Millones | C2: ="Cifras en "&A2&" de "&A1 -> Cifras en Millones de USD
A3: (Company name) | G3: =A3&" ("&A4&")" -> (Company name) ((ticker))
A4: (ticker)
A5: RESULTADOS | B5: 2023 | C5: =B5-1 -> 2022 | D5: =C5-1 -> 2021 | E5: =D5-1 -> 2020 | F5: =E5-1 -> 2019 | G5: =F5-1 -> 2018 | H5: =G5-1 -> 2017 | I5: =H5-1 -> 2016 | J5: =I5-1 -> 2015 | ... M5: =L5-1 -> 2012
A6: Ventas Netas
A7: Utilidad Bruta
A8: Utilidad de Operación
A9: CIF (Poductos) | S9: =C5 -> 2022 | T9: =D5 -> 2021 | U9: =E5 -> 2020 | V9: =F5 -> 2019 | W9: =G5 -> 2018 | X9: =H5 -> 2017 | Y9: =I5 -> 2016 | Z9: =J5 -> 2015 | ... AB9: =L5 -> 2013
A10: Otros Gastos (Ingresos) | R10: Inventories | S10: =C24 -> 0 | T10: =D24 -> 0 | U10: =E24 -> 0 | V10: =F24 -> 0 | W10: =G24 -> 0 | X10: =H24 -> 0 | Y10: =I24 -> 0 | Z10: =J24 -> 0 | ... AC10: =M24 -> 0
A11: Depreciación y amortización | R11: Por cobrar | S11: =C23 -> 0 | T11: =D23 -> 0 | U11: =E23 -> 0 | V11: =F23 -> 0 | W11: =G23 -> 0 | X11: =H23 -> 0 | Y11: =I23 -> 0 | Z11: =J23 -> 0 | ... AC11: =M23 -> 0
A12: Capital de Trabajo | R12: Por pagar
A13: Capex
A14: Inversiones | S14: =(S10-T10) -> 0 | T14: =(T10-U10) -> 0 | U14: =(U10-V10) -> 0 | V14: =(V10-W10) -> 0 | W14: =(W10-X10) -> 0 | X14: =(X10-Y10) -> 0 | Y14: =(Y10-Z10) -> 0 | Z14: =(Z10-AA10) -> 0 | ... AB14: =(AB10-AC10) -> 0
A15: I.S.R Y P.T.U. | S15: =(S11-T11) -> 0 | T15: =(T11-U11) -> 0 | U15: =(U11-V11) -> 0 | V15: =(V11-W11) -> 0 | W15: =(W11-X11) -> 0 | X15: =(X11-Y11) -> 0 | Y15: =(Y11-Z11) -> 0 | Z15: =(Z11-AA11) -> 0 | ... AB15: =(AB11-AC11) -> 0
A16: Utilidad Neta | S16: =(S12-T12) -> 0 | T16: =(T12-U12) -> 0 | U16: =(U12-V12) -> 0 | V16: =(V12-W12) -> 0 | W16: =(W12-X12) -> 0 | X16: =(X12-Y12) -> 0 | Y16: =(Y12-Z12) -> 0 | Z16: =(Z12-AA12) -> 0 | ... AB16: =(AB12-AC12) -> 0
A17: Dividendos | R17: Capital de trabajo | S17: =SUM(S14:S16) -> 0 | T17: =SUM(T14:T16) -> 0 | U17: =SUM(U14:U16) -> 0 | V17: =SUM(V14:V16) -> 0 | W17: =SUM(W14:W16) -> 0 | X17: =SUM(X14:X16) -> 0 | Y17: =SUM(Y14:Y16) -> 0 | Z17: =SUM(Z14:Z16) -> 0 | ... AB17: =SUM(AB14:AB16) -> 0
A18: Compra de Acciones
B19: =B8-B9-B10-B15 -> 0 | C19: =C8-C9-C10-C15 -> 0 | D19: =D8-D9-D10-D15 -> 0 | E19: =E8-E9-E10-E15 -> 0 | F19: =F8-F9-F10-F15 -> 0 | G19: =G8-G9-G10-G15 -> 0 | H19: =H8-H9-H10-H15 -> 0 | I19: =I8-I9-I10-I15 -> 0 | ... M19: =M8-M9-M10-M15 -> 0
A20: POSICIÓN FINANCIERA | B20: =B16-B19 -> 0 | C20: =C16-C19 -> 0 | D20: =D16-D19 -> 0 | E20: =E16-E19 -> 0 | F20: =F16-F19 -> 0 | G20: =G16-G19 -> 0 | H20: =H16-H19 -> 0 | I20: =I16-I19 -> 0 | ... M20: =M16-M19 -> 0
A21: Activo
A22: Caja
A23: Cuentas y documentos por cobrar
A24: Inventarios
A25: Activos Fijos (Net Plant)
A26: Otros Activos | B26: =B27-SUM(B22:B25) -> 0 | C26: =C27-SUM(C22:C25) -> 0 | D26: =D27-SUM(D22:D25) -> 0 | E26: =E27-SUM(E22:E25) -> 0 | F26: =F27-SUM(F22:F25) -> 0 | G26: =G27-SUM(G22:G25) -> 0 | H26: =H27-SUM(H22:H25) -> 0 | I26: =I27-SUM(I22:I25) -> 0 | ... M26: =M27-SUM(M22:M25) -> 0
A27: Total Activo
A30: Pasivo
A31: Pasivo Corto Plazo
A32: Deuda a corto plazo
A33: Short-Term Leases
A34: Otros Pasivos a Corto Plazo | B34: =B31-B32-B33 -> 0 | C34: =C31-C32-C33 -> 0 | D34: =D31-D32-D33 -> 0 | E34: =E31-E32-E33 -> 0 | F34: =F31-F32-F33 -> 0 | G34: =G31-G32-G33 -> 0 | H34: =H31-H32-H33 -> 0 | I34: =I31-I32-I33 -> 0 | ... M34: =M31-M32-M33 -> 0
A35: Pasivo Largo Plazo
A36: Deuda a largo plazo
A37: Long-Term Leases
A38: Otros Pasivos a Largo Plazo | B38: =B35-B36-B37 -> 0 | C38: =C35-C36-C37 -> 0 | D38: =D35-D36-D37 -> 0 | E38: =E35-E36-E37 -> 0 | F38: =F35-F36-F37 -> 0 | G38: =G35-G36-G37 -> 0 | H38: =H35-H36-H37 -> 0 | I38: =I35-I36-I37 -> 0 | ... M38: =M35-M36-M37 -> 0
A39: Total pasivos | B39: =B31+B35 -> 0 | C39: =C31+C35 -> 0 | D39: =+D35+D31 -> 0 | E39: =+E35+E31 -> 0 | F39: =+F35+F31 -> 0 | G39: =+G35+G31 -> 0 | H39: =+H35+H31 -> 0 | I39: =I31+I35 -> 0 | J39: =J35+J31 -> 0 | K39: =K35+K31 -> 0 | L39: =L35+L31 -> 0 | M39: =M35+M31 -> 0
A42: Interés Minoritario | B42: 0 | C42: 0 | D42: 0 | E42: 0 | F42: 0 | G42: 0 | H42: 0 | I42: 0 | J42: 0 | K42: 0 | L42: 0 | M42: 0
A44: Capital Contable | B44: =B27-B39-B42 -> 0 | C44: =C27-C39-C42 -> 0 | D44: =D27-D39-D42 -> 0 | E44: =E27-E39-E42 -> 0 | F44: =F27-F39-F42 -> 0 | G44: =G27-G39-G42 -> 0 | H44: =H27-H39-H42 -> 0 | I44: =I27-I39-I42 -> 0 | ... L44: =L27-L39-L42 -> 0 | M44: 47791
A46: OTROS DATOS AL FIN DE AÑO
A47: Numero de Empleados
A48: Acciones en circulación (millones)
A49: Float
A50: Insiders Own
A51: S&P
A52: ="Vol. Diario en Millones "&A1 -> Vol. Diario en Millones USD
B53: 2021 | C53: =B53+1 -> 2022 | D53: =C53+1 -> 2023
A54: Posicion en Corto (%)
A55: EPS
A57: BONOS DE LA EMISORA A 3, 5 Y 10 | B57: Precio Medio | C57: S&P | D57: YTM (%) | E57: DIVISA

Sheet Q
B2: 3Q17 | C2: 3Q18 | D2: 4Q18 | E2: 1Q19 | F2: 2Q19 | G2: 3Q19 | H2: 4Q19 | I2: 1Q20 | J2: 2Q20 | K2: 3Q20 | L2: 4Q20 | M2: 1Q21 | N2: 2Q21 | O2: 3Q21 | P2: 4Q21 | Q2: 1Q22 | R2: 2Q22 | S2: 3Q22 | T2: 4Q22 | U2: 1Q23 | V2: 2Q23 | W2: 3Q23 | X2: 4Q23e | Z2: 2019 | AA2: 2020 | AB2: 2021 | AC2: 2022 | AD2: 2023 | AE2: 2024 | AF2: 2025 | AG2: 2026 | AH2: 2027 | AI2: 2028 | AJ2: 2029 | AK2: 2030 | AL2: 2031 | AM2: 2032 | AN2: 2033 | AO2: 2034 | AP2: 2035 | AQ2: 2036 | AR2: 2037 | AS2: 2038 | AT2: 2039 | AU2: 2040 | AV2: 2041 | AW2: 2042 | AX2: 2043 | AY2: 2044 | AZ2: 2045 | BA2: 2046 | BB2: 2047
A3: Shares
A4: Growth
A5: Prods | AE5: 0.045 | AF5: =0.987*AE5 -> 0.044415 | AG5: =0.987*AF5 -> 0.043837605 | AH5: =0.987*AG5 -> 0.043267716 | AI5: =0.987*AH5 -> 0.042705236 | AJ5: =0.987*AI5 -> 0.042150068 | AK5: =0.987*AJ5 -> 0.041602117 | AL5: =0.987*AK5 -> 0.041061289 | AM5: =0.987*AL5 -> 0.040527493 | ... BB5: =0.987*BA5 -> 0.033304815
A6: Serv | AE6: 0.09 | AF6: =AE6*0.975 -> 0.08775 | AG6: =AF6*0.975 -> 0.08555625 | AH6: =AG6*0.975 -> 0.083417344 | AI6: =AH6*0.975 -> 0.08133191 | AJ6: =AI6*0.975 -> 0.079298612 | AK6: =AJ6*0.975 -> 0.077316147 | AL6: =AK6*0.975 -> 0.075383243 | AM6: =AL6*0.975 -> 0.073498662 | ... BB6: =BA6*0.975 -> 0.050274605
A8: COGS
A9: Prods | Z9: =Z30/Z26 -> 0.67792204 | AA9: =AA30/AA26 -> 0.68533661 | AB9: =AB30/AB26 -> 0.64650697 | AC9: =AC30/AC26 -> 0.6371652 | AD9: =AD30/AD26 -> 0.6358648 | AE9: =AD9*1.001 -> 0.63650067 | AF9: =AE9*1.001 -> 0.63713717 | AG9: =AF9*1.001 -> 0.6377743 | AH9: =AG9*1.001 -> 0.63841208 | AI9: =AH9*1.001 -> 0.63905049 | AJ9: =AI9*1.001 -> 0.63968954 | AK9: =AJ9*1.001 -> 0.64032923 | AL9: =AK9*1.001 -> 0.64096956 | ... BB9: =BA9*1.001 -> 0.65130235
A10: Serv | Z10: =Z31/Z27 -> 0.36261908 | AA10: =AA31/AA27 -> 0.33984898 | AB10: =AB31/AB27 -> 0.30274023 | AC10: =AC31/AC27 -> 0.28254553 | AD10: =AD31/AD27 -> 0.29105249 | AE10: =AD10*1.001 -> 0.29134354 | AF10: =AE10*1.001 -> 0.29163488 | AG10: =AF10*1.001 -> 0.29192652 | AH10: =AG10*1.001 -> 0.29221845 | AI10: =AH10*1.001 -> 0.29251066 | AJ10: =AI10*1.001 -> 0.29280317 | AK10: =AJ10*1.001 -> 0.29309598 | AL10: =AK10*1.001 -> 0.29338907 | ... BB10: =BA10*1.001 -> 0.29811867
A12: R&D | Z12: =Z33/Z25 -> 0.062331363 | AA12: =AA33/AA25 -> 0.068309564 | AB12: =AB33/AB25 -> 0.059904269 | AC12: =AC33/AC25 -> 0.066571484 | AD12: =AD33/AD25 -> 0.078317483 | AE12: =1.01*AD12 -> 0.079100658 | AF12: =1.01*AE12 -> 0.079891665 | AG12: =1.01*AF12 -> 0.080690581 | AH12: =1.01*AG12 -> 0.081497487 | AI12: =1.01*AH12 -> 0.082312462 | AJ12: =1.01*AI12 -> 0.083135587 | AK12: =1.01*AJ12 -> 0.083966943 | AL12: =1.01*AK12 -> 0.084806612 | ... BB12: =1.01*BA12 -> 0.099442422
A13: SGA | Z13: =Z34/Z25 -> 0.070126146 | AA13: =AA34/AA25 -> 0.07254977 | AB13: =AB34/AB25 -> 0.060065552 | AC13: =AC34/AC25 -> 0.063637378 | AD13: =AD34/AD25 -> 0.065265004 | AE13: =AD13*1.001 -> 0.065330269 | AF13: =AE13*1.001 -> 0.0653956 | AG13: =AF13*1.001 -> 0.065460995 | AH13: =AG13*1.001 -> 0.065526456 | AI13: =AH13*1.001 -> 0.065591983 | AJ13: =AI13*1.001 -> 0.065657575 | AK13: =AJ13*1.001 -> 0.065723232 | AL13: =AK13*1.001 -> 0.065788956 | ... BB13: =BA13*1.001 -> 0.066849511
A15: Utiilidad oP
A17: Tax Rate | Z17: =Z41/Z40 -> 0.15943837 | AA17: =AA41/AA40 -> 0.14428165 | AB17: =AB41/AB40 -> 0.13302261 | AC17: =AC41/AC40 -> 0.16204462
A19: DA | Z19: =Z52/Z25 -> 0.048225418 | AA19: =AA52/AA25 -> 0.040274666 | AB19: =AB52/AB25 -> 0.030846024 | AC19: =AC52/AC25 -> 0.028159299
A20: SBC | Z20: =Z53/Z25 -> 0.023322853 | AA20: =AA53/AA25 -> 0.024876601 | AB20: =AB53/AB25 -> 0.021611899 | AC20: =AC53/AC25 -> 0.022920006
A21: Net SBC | U21: =((W25+V25)/(R25+S25))-1 -> -0.019995894 | Z21: =(Z53+Z54)/Z25 -> 0.031148385 | AA21: =(AA53+AA54)/AA25 -> 0.034908839 | AB21: =(AB53+AB54)/AB25 -> 0.039533428 | AC21: =(AC53+AC54)/AC25 -> 0.038701284
A22: Capex | U22: =((W25+V25)/(F25+G25))-1 -> 0.57956253 | Z22: =Z55/Z25 -> 0.040338389 | AA22: =AA55/AA25 -> 0.026625139 | AB22: =AB55/AB25 -> 0.030302036 | AC22: =AC55/AC25 -> 0.027155059
A23: Net SBC Factor | Z23: =Z21/Z20 -> 1.3355307 | AA23: =AA21/AA20 -> 1.4032801 | AB23: =AB21/AB20 -> 1.8292436 | AC23: =AC21/AC20 -> 1.6885373
A25: Revenue | C25: =C26+C27 -> 53265 | D25: =D26+D27 -> 64040 | E25: =E26+E27 -> 84310 | F25: =F26+F27 -> 58015 | G25: =G26+G27 -> 53809 | H25: =H26+H27 -> 64040 | I25: =I26+I27 -> 91819 | J25: =J26+J27 -> 58313 | ... X25: =X26+X27 -> 89282 | Z25: =Z26+Z27 -> 260174 | AA25: =AA26+AA27 -> 274515 | AB25: =AB26+AB27 -> 365817 | AC25: =AC26+AC27 -> 394328 | AD25: =AD26+AD27 -> 383069 | AE25: =AE26+AE27 -> 404095.7 | AF25: =AF26+AF27 -> 426020.39 | AG25: =AG26+AG27 -> 448860.49 | ... BB25: =BB26+BB27 -> 1156800
A26: -Products | C26: 43095 | D26: 51529 | E26: 73435 | F26: 46565 | G26: 42354 | H26: 51529 | I26: 79104 | J26: 44965 | K26: 46529 | L26: 50149 | M26: 95678 | N26: 72683 | O26: 63948 | P26: 65083 | Q26: 104429 | R26: 77457 | S26: 63355 | T26: 70958 | U26: 96388 | V26: 73929 | W26: 60584 | X26: 67977 | Z26: =SUM(E26:H26) -> 213883 | AA26: =SUM(I26:L26) -> 220747 | AB26: =SUM(M26:P26) -> 297392 | AC26: =SUM(Q26:T26) -> 316199 | AD26: =SUM(U26:X26) -> 298878 | AE26: =(1+AE5)*AD26 -> 312327.51 | AF26: =(1+AF5)*AE26 -> 326199.54 | AG26: =(1+AG5)*AF26 -> 340499.34 | AH26: =(1+AH5)*AG26 -> 355231.97 | AI26: =(1+AI5)*AH26 -> 370402.24 | AJ26: =(1+AJ5)*AI26 -> 386014.72 | AK26: =(1+AK5)*AJ26 -> 402073.75 | AL26: =(1+AL5)*AK26 -> 418583.41 | ... BB26: =(1+BB5)*BA26 -> 746321.37
A27: -Services | C27: 10170 | D27: 12511 | E27: 10875 | F27: 11450 | G27: 11455 | H27: 12511 | I27: 12715 | J27: 13348 | K27: 13156 | L27: 14549 | M27: 15761 | N27: 16901 | O27: 17486 | P27: 18277 | Q27: 19516 | R27: 19821 | S27: 19604 | T27: 19188 | U27: 20766 | V27: 20907 | W27: 21213 | X27: 21305 | Z27: =SUM(E27:H27) -> 46291 | AA27: =SUM(I27:L27) -> 53768 | AB27: =SUM(M27:P27) -> 68425 | AC27: =SUM(Q27:T27) -> 78129 | AD27: =SUM(U27:X27) -> 84191 | AE27: =(1+AE6)*AD27 -> 91768.19 | AF27: =(1+AF6)*AE27 -> 99820.849 | AG27: =(1+AG6)*AF27 -> 108361.15 | AH27: =(1+AH6)*AG27 -> 117400.35 | AI27: =(1+AI6)*AH27 -> 126948.74 | AJ27: =(1+AJ6)*AI27 -> 137015.6 | AK27: =(1+AK6)*AJ27 -> 147609.12 | AL27: =(1+AL6)*AK27 -> 158736.37 | ... BB27: =(1+BB6)*BA27 -> 410478.6
A29: COGS
A30: -Products | C30: 28956 | D30: 35238 | E30: 48238 | F30: 32047 | G30: 29473 | H30: 35238 | I30: 52075 | J30: 31321 | K30: 32693 | L30: 35197 | M30: 62130 | N30: 46447 | O30: 40899 | P30: 42790 | Q30: 64309 | R30: 49290 | S30: 41485 | T30: 46387 | U30: 60765 | V30: 46795 | W30: 39136 | X30: 43350 | Z30: =SUM(E30:H30) -> 144996 | AA30: =SUM(I30:L30) -> 151286 | AB30: =SUM(M30:P30) -> 192266 | AC30: =SUM(Q30:T30) -> 201471 | AD30: =SUM(U30:X30) -> 190046 | AE30: =AE9*AE26 -> 198796.67 | AF30: =AF9*AF26 -> 207833.85 | AG30: =AG9*AG26 -> 217161.73 | AH30: =AH9*AH26 -> 226784.38 | AI30: =AI9*AI26 -> 236705.73 | AJ30: =AJ9*AJ26 -> 246929.58 | AK30: =AK9*AK26 -> 257459.57 | AL30: =AL9*AL26 -> 268299.23 | ... BB30: =BB9*BB26 -> 486080.86
A31: -Services | C31: 3888 | D31: 4489 | E31: 4041 | F31: 4147 | G31: 4109 | H31: 4489 | I31: 4527 | J31: 4622 | K31: 4312 | L31: 4812 | M31: 4981 | N31: 5058 | O31: 5280 | P31: 5396 | Q31: 5393 | R31: 5429 | S31: 5589 | T31: 5664 | U31: 6057 | V31: 6065 | W31: 6248 | X31: 6134 | Z31: =SUM(E31:H31) -> 16786 | AA31: =SUM(I31:L31) -> 18273 | AB31: =SUM(M31:P31) -> 20715 | AC31: =SUM(Q31:T31) -> 22075 | AD31: =SUM(U31:X31) -> 24504 | AE31: =AE10*AE27 -> 26736.069 | AF31: =AF10*AF27 -> 29111.242 | AG31: =AG10*AG27 -> 31633.492 | AH31: =AH10*AH27 -> 34306.546 | AI31: =AI10*AI27 -> 37133.86 | AJ31: =AJ10*AJ27 -> 40118.602 | AK31: =AK10*AK27 -> 43263.638 | AL31: =AL10*AL27 -> 46571.517 | ... BB31: =BB10*BB27 -> 122371.34
A33: R&D | C33: 3701 | D33: 4110 | E33: 3902 | F33: 3948 | G33: 4257 | H33: 4110 | I33: 4451 | J33: 4565 | K33: 4758 | L33: 4978 | M33: 5163 | N33: 5262 | O33: 5717 | P33: 5772 | Q33: 6306 | R33: 6387 | S33: 6797 | T33: 6761 | U33: 7709 | V33: 7457 | W33: 7442 | X33: 7393 | Z33: =SUM(E33:H33) -> 16217 | AA33: =SUM(I33:L33) -> 18752 | AB33: =SUM(M33:P33) -> 21914 | AC33: =SUM(Q33:T33) -> 26251 | AD33: =SUM(U33:X33) -> 30001 | AE33: =AE12*AE$25 -> 31964.236 | AF33: =AF12*AF$25 -> 34035.478 | AG33: =AG12*AG$25 -> 36218.814 | AH33: =AH12*AH$25 -> 38518.346 | AI33: =AI12*AI$25 -> 40938.183 | AJ33: =AJ12*AJ$25 -> 43482.432 | AK33: =AK12*AK$25 -> 46155.189 | AL33: =AL12*AL$25 -> 48960.535 | ... BB33: =BB12*BB$25 -> 115034.99
A34: SGA | C34: 4108 | D34: 4578 | E34: 4783 | F34: 4458 | G34: 4426 | H34: 4578 | I34: 5197 | J34: 4952 | K34: 4831 | L34: 4936 | M34: 5631 | N34: 5314 | O34: 5412 | P34: 5616 | Q34: 6449 | R34: 6193 | S34: 6012 | T34: 6440 | U34: 6607 | V34: 6201 | W34: 5973 | X34: 6220 | Z34: =SUM(E34:H34) -> 18245 | AA34: =SUM(I34:L34) -> 19916 | AB34: =SUM(M34:P34) -> 21973 | AC34: =SUM(Q34:T34) -> 25094 | AD34: =SUM(U34:X34) -> 25001 | AE34: =AE13*AE$25 -> 26399.681 | AF34: =AF13*AF$25 -> 27859.859 | AG34: =AG13*AG$25 -> 29382.854 | AH34: =AH13*AH$25 -> 30969.921 | AI34: =AI13*AI$25 -> 32622.237 | AJ34: =AJ13*AJ$25 -> 34340.902 | AK34: =AK13*AK$25 -> 36126.934 | AL34: =AL13*AL$25 -> 37981.266 | ... BB34: =BB13*BB$25 -> 77331.512
A36: Ut OP | C36: =C25-C30-C31-C33-C34 -> 12612 | D36: =D25-D30-D31-D33-D34 -> 15625 | E36: =E25-E30-E31-E33-E34 -> 23346 | F36: =F25-F30-F31-F33-F34 -> 13415 | G36: =G25-G30-G31-G33-G34 -> 11544 | H36: =H25-H30-H31-H33-H34 -> 15625 | I36: =I25-I30-I31-I33-I34 -> 25569 | J36: =J25-J30-J31-J33-J34 -> 12853 | ... X36: =X25-X30-X31-X33-X34 -> 26185 | Z36: =Z25-Z30-Z31-Z33-Z34 -> 63930 | AA36: =AA25-AA30-AA31-AA33-AA34 -> 66288 | AB36: =AB25-AB30-AB31-AB33-AB34 -> 108949 | AC36: =AC25-AC30-AC31-AC33-AC34 -> 119437 | AD36: =AD25-AD30-AD31-AD33-AD34 -> 113517 | AE36: =AE25-AE30-AE31-AE33-AE34 -> 120199.05 | AF36: =AF25-AF30-AF31-AF33-AF34 -> 127179.96 | AG36: =AG25-AG30-AG31-AG33-AG34 -> 134463.6 | ... BB36: =BB25-BB30-BB31-BB33-BB34 -> 355981.27
A38: Other | C38: 672 | D38: 502 | E38: 560 | F38: 378 | G38: 367 | H38: 502 | I38: 349 | J38: 282 | K38: 46 | L38: 126 | M38: 45 | N38: 508 | O38: 243 | P38: -538 | Q38: -247 | R38: 160 | S38: -10 | T38: -237 | U38: -393 | V38: 64 | W38: -265 | Z38: =SUM(E38:H38) -> 1807 | AA38: =SUM(I38:L38) -> 803 | AB38: =SUM(M38:P38) -> 258 | AC38: =SUM(Q38:T38) -> -334
A40: efore tax | C40: =C26+C27-C30-C31-C33-C34+C38 -> 13284 | D40: =D26+D27-D30-D31-D33-D34+D38 -> 16127 | E40: =E26+E27-E30-E31-E33-E34+E38 -> 23906 | F40: =F26+F27-F30-F31-F33-F34+F38 -> 13793 | G40: =G26+G27-G30-G31-G33-G34+G38 -> 11911 | H40: =H26+H27-H30-H31-H33-H34+H38 -> 16127 | I40: =I26+I27-I30-I31-I33-I34+I38 -> 25918 | J40: =J26+J27-J30-J31-J33-J34+J38 -> 13135 | ... W40: =W26+W27-W30-W31-W33-W34+W38 -> 22733 | Z40: =SUM(E40:H40) -> 65737 | AA40: =SUM(I40:L40) -> 67091 | AB40: =SUM(M40:P40) -> 109207 | AC40: =SUM(Q40:T40) -> 119103
A41: Tax | C41: 1765 | D41: 2441 | E41: 3941 | F41: 2232 | G41: 1867 | H41: 2441 | I41: 3682 | J41: 1886 | K41: 1884 | L41: 2228 | M41: 4824 | N41: 4381 | O41: 2625 | P41: 2697 | Q41: 6611 | R41: 5129 | S41: 3624 | T41: 3936 | U41: 5625 | V41: 4222 | W41: 2852 | Z41: =SUM(E41:H41) -> 10481 | AA41: =SUM(I41:L41) -> 9680 | AB41: =SUM(M41:P41) -> 14527 | AC41: =SUM(Q41:T41) -> 19300
A42: NI | C42: =C40-C41 -> 11519 | D42: =D40-D41 -> 13686 | E42: =E40-E41 -> 19965 | F42: =F40-F41 -> 11561 | G42: =G40-G41 -> 10044 | H42: =H40-H41 -> 13686 | I42: =I40-I41 -> 22236 | J42: =J40-J41 -> 11249 | ... W42: =W40-W41 -> 19881
A45: DA | E45: 3395 | F45: 6435 | G45: 9368 | H45: 12547 | I45: 2816 | J45: 5602 | K45: 8354 | L45: 11056 | M45: 2666 | N45: 5463 | O45: 8295 | P45: 11284 | Q45: 2697 | R45: 5434 | S45: 8239 | T45: 11104 | U45: 2916 | V45: 5814 | W45: 8866
A46: SBC | E46: 1559 | F46: 3073 | G46: 4569 | H46: 6068 | I46: 1710 | J46: 3407 | K46: 5105 | L46: 6829 | M46: 2020 | N46: 4001 | O46: 5961 | P46: 7906 | Q46: 2265 | R46: 4517 | S46: 6760 | T46: 9038 | U46: 2905 | V46: 5591 | W46: 8208
A47: Other SBC | E47: 1318 | F47: 1037 | G47: 2325 | H47: 2036 | I47: 1377 | J47: 1136 | K47: 2804 | L47: 2754 | M47: 2861 | N47: 3160 | O47: 5855 | P47: 6556 | Q47: 2888 | R47: 3218 | S47: 5915 | T47: 6223 | U47: 2316 | V47: 2734 | W47: 5119
A48: Capex | E48: 3355 | F48: 5718 | G48: 7718 | H48: 10495 | I48: 2107 | J48: 3960 | K48: 5525 | L48: 7309 | M48: 3500 | N48: 5769 | O48: 7862 | P48: 11085 | Q48: 2803 | R48: 5317 | S48: 7419 | T48: 10708 | U48: 3787 | V48: 6703 | W48: 8796
A49: Divs | E49: 3568 | F49: 7011 | G49: 10640 | H49: 14119 | I49: 3539 | J49: 6914 | K49: 10570 | L49: 14081 | M49: 3613 | N49: 7060 | O49: 10827 | P49: 14467 | Q49: 3732 | R49: 7327 | S49: 11138 | T49: 14841 | U49: 3768 | V49: 7418 | W49: 11267
A50: Repurch | E50: 8796 | F50: 32498 | G50: 49463 | H50: 66897 | I50: 20706 | J50: 39280 | K50: 55171 | L50: 72358 | M50: 24775 | N50: 43323 | O50: 66223 | P50: 85971 | Q50: 20478 | R50: 43109 | S50: 64974 | T50: 89402 | U50: 19475 | V50: 39069 | W50: 56547
A52: DA | E52: =E45 -> 3395 | F52: =F45-E45 -> 3040 | G52: =G45-F45 -> 2933 | H52: =H45-G45 -> 3179 | I52: =I45 -> 2816 | J52: =J45-I45 -> 2786 | K52: =K45-J45 -> 2752 | L52: =L45-K45 -> 2702 | M52: =M45 -> 2666 | N52: =N45-M45 -> 2797 | O52: =O45-N45 -> 2832 | P52: =P45-O45 -> 2989 | Q52: =Q45 -> 2697 | R52: =R45-Q45 -> 2737 | S52: =S45-R45 -> 2805 | T52: =T45-S45 -> 2865 | U52: =U45 -> 2916 | V52: =V45-U45 -> 2898 | W52: =W45-V45 -> 3052 | X52: 3262 | Z52: =SUM(E52:H52) -> 12547 | AA52: =SUM(I52:L52) -> 11056 | AB52: =SUM(M52:P52) -> 11284 | AC52: =SUM(Q52:T52) -> 11104
A53: SBC | E53: =E46 -> 1559 | F53: =F46-E46 -> 1514 | G53: =G46-F46 -> 1496 | H53: =H46-G46 -> 1499 | I53: =I46 -> 1710 | J53: =J46-I46 -> 1697 | K53: =K46-J46 -> 1698 | L53: =L46-K46 -> 1724 | M53: =M46 -> 2020 | N53: =N46-M46 -> 1981 | O53: =O46-N46 -> 1960 | P53: =P46-O46 -> 1945 | Q53: =Q46 -> 2265 | R53: =R46-Q46 -> 2252 | S53: =S46-R46 -> 2243 | T53: =T46-S46 -> 2278 | U53: =U46 -> 2905 | V53: =V46-U46 -> 2686 | W53: =W46-V46 -> 2617 | Z53: =SUM(E53:H53) -> 6068 | AA53: =SUM(I53:L53) -> 6829 | AB53: =SUM(M53:P53) -> 7906 | AC53: =SUM(Q53:T53) -> 9038
A54: Other SBC | E54: =E47 -> 1318 | F54: =F47-E47 -> -281 | G54: =G47-F47 -> 1288 | H54: =H47-G47 -> -289 | I54: =I47 -> 1377 | J54: =J47-I47 -> -241 | K54: =K47-J47 -> 1668 | L54: =L47-K47 -> -50 | M54: =M47 -> 2861 | N54: =N47-M47 -> 299 | O54: =O47-N47 -> 2695 | P54: =P47-O47 -> 701 | Q54: =Q47 -> 2888 | R54: =R47-Q47 -> 330 | S54: =S47-R47 -> 2697 | T54: =T47-S47 -> 308 | U54: =U47 -> 2316 | V54: =V47-U47 -> 418 | W54: =W47-V47 -> 2385 | Z54: =SUM(E54:H54) -> 2036 | AA54: =SUM(I54:L54) -> 2754 | AB54: =SUM(M54:P54) -> 6556 | AC54: =SUM(Q54:T54) -> 6223
A55: Capex | E55: =E48 -> 3355 | F55: =F48-E48 -> 2363 | G55: =G48-F48 -> 2000 | H55: =H48-G48 -> 2777 | I55: =I48 -> 2107 | J55: =J48-I48 -> 1853 | K55: =K48-J48 -> 1565 | L55: =L48-K48 -> 1784 | M55: =M48 -> 3500 | N55: =N48-M48 -> 2269 | O55: =O48-N48 -> 2093 | P55: =P48-O48 -> 3223 | Q55: =Q48 -> 2803 | R55: =R48-Q48 -> 2514 | S55: =S48-R48 -> 2102 | T55: =T48-S48 -> 3289 | U55: =U48 -> 3787 | V55: =V48-U48 -> 2916 | W55: =W48-V48 -> 2093 | Z55: =SUM(E55:H55) -> 10495 | AA55: =SUM(I55:L55) -> 7309 | AB55: =SUM(M55:P55) -> 11085 | AC55: =SUM(Q55:T55) -> 10708
A56: Divs | E56: =E49 -> 3568 | F56: =F49-E49 -> 3443 | G56: =G49-F49 -> 3629 | H56: =H49-G49 -> 3479 | I56: =I49 -> 3539 | J56: =J49-I49 -> 3375 | K56: =K49-J49 -> 3656 | L56: =L49-K49 -> 3511 | M56: =M49 -> 3613 | N56: =N49-M49 -> 3447 | O56: =O49-N49 -> 3767 | P56: =P49-O49 -> 3640 | Q56: =Q49 -> 3732 | R56: =R49-Q49 -> 3595 | S56: =S49-R49 -> 3811 | T56: =T49-S49 -> 3703 | U56: =U49 -> 3768 | V56: =V49-U49 -> 3650 | W56: =W49-V49 -> 3849 | Z56: =SUM(E56:H56) -> 14119 | AA56: =SUM(I56:L56) -> 14081 | AB56: =SUM(M56:P56) -> 14467 | AC56: =SUM(Q56:T56) -> 14841
A57: Repurch | E57: =E50 -> 8796 | F57: =F50-E50 -> 23702 | G57: =G50-F50 -> 16965 | H57: =H50-G50 -> 17434 | I57: =I50 -> 20706 | J57: =J50-I50 -> 18574 | K57: =K50-J50 -> 15891 | L57: =L50-K50 -> 17187 | M57: =M50 -> 24775 | N57: =N50-M50 -> 18548 | O57: =O50-N50 -> 22900 | P57: =P50-O50 -> 19748 | Q57: =Q50 -> 20478 | R57: =R50-Q50 -> 22631 | S57: =S50-R50 -> 21865 | T57: =T50-S50 -> 24428 | U57: =U50 -> 19475 | V57: =V50-U50 -> 19594 | W57: =W50-V50 -> 17478 | Z57: =SUM(E57:H57) -> 66897 | AA57: =SUM(I57:L57) -> 72358 | AB57: =SUM(M57:P57) -> 85971 | AC57: =SUM(Q57:T57) -> 89402
J63: -1
