Workbook
Name Sectors: '[1]Sector Impact'!$K$4:$K$16
Name Sectors: 'Sector Impact'!$K$4:$K$16

Sheet OP
B2: (Date of last update) | C2: Team 1 | D2: (Date of next Quarter/Annual Report) | E2: =Inputs!H3 -> #VALUE! | L2: {=_FV(E2,"Exchange")} -> London Stock Exchange | M2: SIC:
B3: #VALUE! | D3: COMPANY DESCRIPTION | H3: CEO & BOARD OF DIRECTORS
D4: {=_FV(Inputs!H3,"Description")} -> NEXT plc is a United Kingdom-based retailer selling clothing, homeware, and beauty products. The Company’s segments include NEXT Online, NEXT Finance, NEXT Retail, Total Platform, and Other Business Activities. The NEXT Online segment includes NEXT Online (UK) and NEXT Online (International). Its Total Platform brands include Reiss, FatFace and Joules. Other Business Activities (all other segments) which include the Property Management segment which holds property and property leases. The Company’s subsidiaries include Agratech Limited, Bridgetown Holdco Limited, Lipsy Limited, Next Beauty Limited, Next Brand Limited, Next Distribution Limited, Next Holdings Limited, Next Manufacturing Limited, Next Near East Limited, Next Properties Limited, Next Retail Limited, The Next Directory Limited, and Project Norwich Limited. | H4: Name, Age and Tenure | I4: Gender | J4: Executive? | L4: Other roles
H5: Lord Simon A. Wolfson, 56, 2001 | I5: M | J5: Y | L5: CEO & Executive Director
H6: Richard S V. Papp,57, 2018 | I6: M | J6: Y | L6: Group Merchandise & Operations Director and Executive Director
H7: Jeremy Stakol, 54, 2023 | I7: M | J7: Y | L7: Group Investments, Acquisitions & Third Party Brands Director and Executive Director
H8: Jane Shields, 60, 2013 | I8: F | J8: Y | L8: Group Sales, Marketing and HR Director
H9: Venetia Butterfield, 54, 2024 | I9: F | J9: N | L9: Independent Non-executive Director
H10: Jonathan Blanchard FCCA, 59, 2024 | I10: M | J10: Y | L10: CFO & Director
H11: Soumen Das, 48, 2021 | I11: M | J11: N | L11: Independent Non-Executive Director
H12: Michael Roney, 70, 2017 | I12: M | J12: Y | L12: Chairman
H13: Amy Stirling, 55 , 2024 | I13: F | J13: N | L13: Independent Non-executive Director
H14: Dame Tristia Harrison, 51, 2018 | I14: F | J14: N | L14: Independent Non-Executive Director
H15: Tom Hall, 57, 2020 | I15: M | J15: N | L15: Independent Non-Executive Director
B16: {=_FV(E2,"Currency")&" MILLIONS"} -> GBp MILLIONS | H16: Jonathan Bewes, 59, 2016 | I16: M | J16: N | L16: Senior Independent Director
B17: COMPANY OVERVIEW
B18: Stock | D18: Liquidity and Solvency | F18: Segments | I18: ="Profitability ("&J19&")" -> Profitability (2023) | L18: Multiples
B19: Last Price | C19: {=_FV(E2,"Price")} -> 13435 | D19: Total Assets | E19: =_xlfn.XLOOKUP(D19,'Fin. Data'!A:A,'Fin. Data'!B:B,,0) -> 4724.3 | F19: Regions | H19: % Sales | I19: Reporting Year | J19: 2023 | L19: Float | M19: =IF(Inputs!B82 <> "",Inputs!B82,"") -> 0.88814229
B20: Outstanding Shares | C20: {=_FV(E2,"Shares outstanding",TRUE)} -> 122436600 | D20: Total Liabilities | E20: =_xlfn.XLOOKUP(D20,'Fin. Data'!A:A,'Fin. Data'!B:B,,0) -> 3212.4 | F20: =Segments!C5 -> United Kingdom | H20: =Segments!B5 -> 0.83784374 | I20: End of Year | J20: 45291 | L20: Insiders Own | M20: =IF(Inputs!B83 <> "",Inputs!B83,"") -> 0.0699
B21: Market Cap. | C21: =C19*C20/1000000 -> 1644935.7 | D21: Cash/Share | E21: =_xlfn.XLOOKUP("Cash & Eq.",'Fin. Data'!A:A,'Fin. Data'!B:B,,0)*1000000/C20 -> 1.5379388 | F21: =Segments!C6 -> Rest of Europe | H21: =Segments!B6 -> 0.09504644 | I21: EBITDA | K21: =_xlfn.XLOOKUP(I21,'Fin. Data'!A:A,'Fin. Data'!B:B,,0) -> 1101.5 | L21: b (Yahoo) | M21: {=IF(_FV(E2,"Beta") <> "",_FV(E2,"Beta"),"")} -> 1.3444
B22: +Total Debt | C22: ='Fin. Data'!B58 -> 1916.7 | D22: EBITDA/Net Financial Cost (NFC) | E22: =IFERROR(_xlfn.XLOOKUP("EBITDA",'Fin. Data'!A:A,'Fin. Data'!B:B,,0)/_xlfn.XLOOKUP("Net Financial Cost",'Fin. Data'!A:A,'Fin. Data'!B:B,,0),"") -> -13.649318 | F22: =Segments!C7 -> Middle East | H22: =Segments!B7 -> 0.046439628 | I22: Depreciation & Amortization | K22: =_xlfn.XLOOKUP(I22,'Fin. Data'!A:A,'Fin. Data'!B:B,,0) -> 246.8 | L22: Score (S&P) | M22: =IF(Inputs!B84 <> "",Inputs!B84,"") -> BBB
B23: -Cash | C23: ='Fin. Data'!B39 -> 188.3 | D23: Debt/EBITDA | E23: =IFERROR(_xlfn.XLOOKUP("Total Debt",'Fin. Data'!A:A,'Fin. Data'!B:B,,0)/_xlfn.XLOOKUP("EBITDA",'Fin. Data'!A:A,'Fin. Data'!B:B,,0),"") -> 1.7400817 | F23: =Segments!C8 -> Asia | H23: =Segments!B8 -> 0.0076306684 | I23: EBIT | K23: =_xlfn.XLOOKUP(I23,'Fin. Data'!A:A,'Fin. Data'!B:B,,0) -> 854.7 | L23: Price/Book Value | M23: =IFERROR((C19*C20/(E19-E20))/1000000,"") -> 1087.9924
B24: =Enterprise Value | C24: =C21+C22-C23 -> 1646664.1 | D24: "Others Assets"/Asset | E24: =IFERROR(_xlfn.XLOOKUP("Other Assets",'Fin. Data'!A:A,'Fin. Data'!B:B,,0)/_xlfn.XLOOKUP("Total Assets",'Fin. Data'!A:A,'Fin. Data'!B:B,,0),"") -> 0.21982093 | F24: =Segments!C9 -> Rest of world | H24: =Segments!B9 -> 0.013039519 | I24: Net Income | K24: =_xlfn.XLOOKUP(I24,'Fin. Data'!A:A,'Fin. Data'!B:B,,0) -> 800.5 | L24: NCF(3y avg)/Asset | M24: =IFERROR(K30/E19,"") -> -0.016595051
B25: Holdings (nac/int'l) | C25: - | D25: Debt/Assets | E25: =_xlfn.XLOOKUP(D25,'Fin. Data'!A:A,'Fin. Data'!B:B,,0) -> 0.4057109 | F25: Categories | H25: % Sales | I25: EPS | K25: =1000000*K24/C20 -> 6.5380777 | L25: Price/Net Inc. (3y avg) | M25: =IFERROR(C21/K29,"") -> 2254.675
B26: t liq. (Holdings/Vol.) | C26: - | D26: EBITDA Margin (average) | E26: =IFERROR(AVERAGE(_xlfn.XLOOKUP("EBITDA Margin",'Fin. Data'!A:A,'Fin. Data'!B:D,,0)),"") -> 0.2222314 | F26: =Segments!C18 -> NEXT Online | H26: =Segments!B18 -> 0.52839191 | I26: ROA | K26: =IFERROR(K24/E19,"") -> 0.16944309 | L26: EV/Asset | M26: =IFERROR(C24/E19,"") -> 348.55198
B27: % Short | C27: 0 | D27: Operating Margin (average) | E27: =IFERROR(AVERAGE(_xlfn.XLOOKUP("Operating Margin",'Fin. Data'!A:A,'Fin. Data'!B:D,,0)),"") -> 0.18770746 | I27: ROIC | K27: =IFERROR(Peers!C18,"") -> 0.23796645 | L27: EV/Ebitda (3y average) | M27: =IFERROR(C24/K28,"") -> 1474.5806
B28: Traffic ESG | D28: Net Income Margin (average) | E28: =IFERROR(AVERAGE(_xlfn.XLOOKUP("Net Income Margin",'Fin. Data'!A:A,'Fin. Data'!B:D,,0)),"") -> 0.14447399 | F28: =Segments!C19 -> NEXT Retail | H28: =Segments!B19 -> 0.33576762 | I28: EBITDA (3y average) | K28: =AVERAGE(_xlfn.XLOOKUP("EBITDA",'Fin. Data'!A:A,'Fin. Data'!B:D,,0)) -> 1116.7 | L28: Price/NCF (3y average) | M28: =IFERROR(C21/K30,"") -> -20981.323
B29: E | I29: Net Income (3y average) | K29: =AVERAGE(_xlfn.XLOOKUP("Net Income",'Fin. Data'!A:A,'Fin. Data'!B:D,,0)) -> 729.56667 | L29: Bonds 1,3,5a (USD) | M29: -
B30: S | D30: Net Financial Cost/Avg Net Debt | E30: =IFERROR(-_xlfn.XLOOKUP("Net Financial Cost",'Fin. Data'!A:A,'Fin. Data'!B:B,,0)/AVERAGE(_xlfn.XLOOKUP("Net Debt",'Fin. Data'!A:A,'Fin. Data'!B:D,,0)),"") -> 0.046846882 | F30: =Segments!C20 -> NEXT Finance | H30: =Segments!B20 -> 0.053305409 | I30: NCF (3y average) | K30: =AVERAGE(_xlfn.XLOOKUP("Net Financial Cost",'Fin. Data'!A:A,'Fin. Data'!B:D,,0)) -> -78.4 | L30: Div+Rep.(3y avg)/Price | M30: =-IFERROR(SUM(E51:E53)/(3*C21),"") -> 0.0002522287
B31: G | F31: =Segments!C21 -> Other | H31: =Segments!B21 -> 0.082535057 | L31: Div. Yield | M31: =-IFERROR(L52/C21,"") -> 0.00015094815
B32: INVESTMENT THESIS
B33: Pillars of Recommendation | H33: Recommendation | I33: Valuation Assumptions
B34: Pillar | C34: Explanation | H34: Hold | I34: Check DCF
B35: Board resilience | C35: The leadership team shifted their focus away from retail growth after recognizing that online sales were the primary driver of the company's future growth. As another example, they also adapted their distribution strategy, leading to significant changes in how the warehouses operated. These decisions illustrate the CEO’s ability to identify key growth drivers and respond with strategic adjustments.
B36: E-commerce and digital | C36: E-commerce and digital will drive growth, meet changing consumer demands and expand its market reach in an increasingly digital retail environment.
B37: Strategic partnerships and product expansion | C37: Strategic partnerships and product expansion will diversify NEXT's revenue streams and enhance market reach, allowing the company to tap into new customer segments and boost overall sales growth.
B38: Risks of Investment | H38: Price Target | I38: Valuation
B39: Risk | C39: Explanation | H39: =IFERROR(DCF!D75,"") -> 9796.5195 | I39: Discount Rate | J39: =DCF!F50 -> 0.085 | L39: Price M. Upside | M39: =IFERROR(#REF!,"")
B40: Heavy dependence on the UK market | C40: Heavy dependence on the UK market exposes NEXT to local economic downturns.
B41: Intense competition either in Retail or ecommerce | C41: Intense competition from established retail and e-commerce players puts pressure on NEXT’s which could lead to margin erosion and impact its ability to maintain strong financial performance. | I41: Upside | J41: =IFERROR(DCF!D74,"") -> -0.27082103 | L41: EV M. Upside | M41: =IFERROR(#REF!,"")
B42: Changes in consumer preferences | C42: Rapid changes in consumer preferences would make it challenging for the company to keep its product offerings relevant. Failing to adapt quickly could result in inventory issues and reduced customer loyalty.
B43: FINANCIAL PERFORMANCE
B44: Year | C44: Net Sales | D44: Operating Margin | E44: Dividends + Share Buyback | F44: Net Cash Flow | G44: Debt/Assets | H44: Depreciation & Amortization | I44: Capex + Investments | J44: Cash Flow
B45: =B46-1 -> 2015 | C45: {=_xlfn.SORTBY(TRANSPOSE(_xlfn.XLOOKUP(C$44,'Fin. Data'!$A:$A,'Fin. Data'!$B:$J,,0)),$B$45:$B$53,-1)} -> 4176.9 | D45: {=_xlfn.SORTBY(TRANSPOSE(_xlfn.XLOOKUP(D$44,'Fin. Data'!$A:$A,'Fin. Data'!$B:$J,,0)),$B$45:$B$53,-1)} -> 0.2089588 | E45: {=_xlfn.SORTBY(TRANSPOSE(_xlfn.XLOOKUP(E$44,'Fin. Data'!$A:$A,'Fin. Data'!$B:$J,,0)),$B$45:$B$53,-1)} -> -718.2 | F45: =Inputs!J77 -> -220.2 | G45: {=_xlfn.SORTBY(TRANSPOSE(_xlfn.XLOOKUP(G$44,'Fin. Data'!$A:$A,'Fin. Data'!$B:$J,,0)),$B$45:$B$53,-1)} -> 0.41088365 | H45: {=_xlfn.SORTBY(TRANSPOSE(_xlfn.XLOOKUP(H$44,'Fin. Data'!$A:$A,'Fin. Data'!$B:$J,,0)),$B$45:$B$53,-1)} -> 118 | I45: {=_xlfn.SORTBY(TRANSPOSE(_xlfn.XLOOKUP(I$44,'Fin. Data'!$A:$A,'Fin. Data'!$B:$J,,0)),$B$45:$B$53,-1)} -> -147.3 | L45: =J19 -> 2023 | M45: =L45-1 -> 2022
B46: =B47-1 -> 2016 | C46: 4097.3 | D46: 0.20198667 | E46: -501.7 | F46: =Inputs!I77 -> -39.2 | G46: 0.39454424 | H46: 116.7 | I46: -154.3 | J46: Net Income | L46: =_xlfn.XLOOKUP($J46,'Fin. Data'!$A:$A,'Fin. Data'!B:B,,0) -> 800.5 | M46: =_xlfn.XLOOKUP($J46,'Fin. Data'!$A:$A,'Fin. Data'!C:C,,0) -> 710.7 | N46: =(C46/C45)-1 -> -0.019057196 | O46: =(D46/D45)-1 -> -0.033366018
B47: =B48-1 -> 2017 | C47: 4055.5 | D47: 0.18764641 | E47: -584.8 | F47: =Inputs!H77 -> -4.6 | G47: 0.42494632 | H47: 123 | I47: -111.4 | J47: Operating CF | L47: =_xlfn.XLOOKUP($J47,'Fin. Data'!$A:$A,'Fin. Data'!B:B,,0) -> 1120.3 | M47: =_xlfn.XLOOKUP($J47,'Fin. Data'!$A:$A,'Fin. Data'!C:C,,0) -> 798.8 | N47: =(C47/C46)-1 -> -0.01020184 | O47: =(D47/D46)-1 -> -0.07099611 | Q47: =F47/F46-1 -> -0.88265306 | R47: =H47/H46-1 -> 0.053984576 | S47: =I47/I46-1 -> -0.27802981
B48: =B49-1 -> 2018 | C48: 4167.4 | D48: 0.20149254 | E48: -540.7 | F48: =Inputs!G77 -> 24.5 | G48: 0.34267621 | H48: 260.6 | I48: -122.9 | J48: Investing CF | L48: =_xlfn.XLOOKUP($J48,'Fin. Data'!$A:$A,'Fin. Data'!B:B,,0) -> -334.4 | M48: =_xlfn.XLOOKUP($J48,'Fin. Data'!$A:$A,'Fin. Data'!C:C,,0) -> -271.4 | N48: =(C48/C47)-1 -> 0.027592159 | O48: =(D48/D47)-1 -> 0.073788417 | Q48: =F48/F47-1 -> -6.326087 | R48: =H48/H47-1 -> 1.1186992 | S48: =I48/I47-1 -> 0.1032316
B49: =B50-1 -> 2019 | C49: 4266.2 | D49: 0.20050631 | E49: -513.8 | F49: =Inputs!F77 -> 18.9 | G49: 0.33686331 | H49: 263 | I49: -139.1 | J49: Net Capex | L49: =_xlfn.XLOOKUP($J49,'Fin. Data'!$A:$A,'Fin. Data'!B:B,,0) -> -125.7 | M49: =_xlfn.XLOOKUP($J49,'Fin. Data'!$A:$A,'Fin. Data'!C:C,,0) -> -163.4 | N49: =(C49/C48)-1 -> 0.023707827 | O49: =(D49/D48)-1 -> -0.0048946326 | Q49: =F49/F48-1 -> -0.22857143 | R49: =H49/H48-1 -> 0.0092095165 | S49: =I49/I48-1 -> 0.13181448
B50: =B51-1 -> 2020 | C50: 3534.4 | D50: 0.12613173 | E50: -19.3 | F50: =Inputs!E77 -> 462.2 | G50: 0.64978712 | H50: 333.8 | I50: -118.1 | J50: Investments & Acquisitions | L50: =_xlfn.XLOOKUP($J50,'Fin. Data'!$A:$A,'Fin. Data'!B:B,,0) -> -153.2 | M50: =_xlfn.XLOOKUP($J50,'Fin. Data'!$A:$A,'Fin. Data'!C:C,,0) -> -95.4 | N50: =(C50/C49)-1 -> -0.17153439 | O50: =(D50/D49)-1 -> -0.37093383 | Q50: =F50/F49-1 -> 23.455026 | R50: =H50/H49-1 -> 0.26920152 | S50: =I50/I49-1 -> -0.15097052
B51: =B52-1 -> 2021 | C51: 4625.9 | D51: 0.19518364 | E51: -353.2 | F51: =Inputs!D77 -> -314.5 | G51: 0.51773067 | H51: 207.2 | I51: -259 | J51: Financing CF | L51: =_xlfn.XLOOKUP($J51,'Fin. Data'!$A:$A,'Fin. Data'!B:B,,0) -> -663.3 | M51: =_xlfn.XLOOKUP($J51,'Fin. Data'!$A:$A,'Fin. Data'!C:C,,0) -> -727.1 | N51: =(C51/C50)-1 -> 0.30882187 | O51: =(D51/D50)-1 -> 0.54745863 | Q51: =F51/F50-1 -> -1.6804414 | R51: =H51/H50-1 -> -0.37926902 | S51: =I51/I50-1 -> 1.1930567
B52: =B53-1 -> 2022 | C52: 5034 | D52: 0.19026619 | E52: -465.9 | F52: =Inputs!C$77 -> -199.7 | G52: 0.48094784 | H52: 166.9 | I52: -258.8 | J52: Dividends | L52: =_xlfn.XLOOKUP($J52,'Fin. Data'!$A:$A,'Fin. Data'!B:B,,0) -> -248.3 | M52: =_xlfn.XLOOKUP($J52,'Fin. Data'!$A:$A,'Fin. Data'!C:C,,0) -> -237.4 | N52: =(C52/C51)-1 -> 0.088220671 | O52: =(D52/D51)-1 -> -0.025193966 | Q52: =F52/F51-1 -> -0.36502385 | R52: =H52/H51-1 -> -0.19449807 | S52: =I52/I51-1 -> -0.00077220077
B53: =J19 -> 2023 | C53: 5491 | D53: 0.17767256 | E53: -425.6 | F53: =Inputs!B77 -> 122.6 | G53: 0.4057109 | H53: 246.8 | I53: -278.9 | J53: Share Buyback | L53: =_xlfn.XLOOKUP($J53,'Fin. Data'!$A:$A,'Fin. Data'!B:B,,0) -> -177.3 | M53: =_xlfn.XLOOKUP($J53,'Fin. Data'!$A:$A,'Fin. Data'!C:C,,0) -> -228.5 | N53: =(C53/C52)-1 -> 0.090782678 | O53: =(D53/D52)-1 -> -0.066189557 | Q53: =F53/F52-1 -> -1.6139209 | R53: =H53/H52-1 -> 0.47872978 | S53: =I53/I52-1 -> 0.077666151
B54: Annual Growth Rate | C54: =IFERROR((C53/C45)^(1/8)-1,"") -> 0.034783918 | D54: =IFERROR((D53/D45)^(1/8)-1,"") -> -0.020070209 | F54: =IFERROR((F53/F45)^(1/8)-1,"") | H54: =IFERROR((H53/H45)^(1/8)-1,"") -> 0.096624372 | J54: FX | L54: =_xlfn.XLOOKUP($J54,'Fin. Data'!$A:$A,'Fin. Data'!B:B,,0) -> 0 | M54: =_xlfn.XLOOKUP($J54,'Fin. Data'!$A:$A,'Fin. Data'!C:C,,0) -> 0 | N54: =(C54/C53)-1 -> -0.99999367 | O54: =(D54/D53)-1 -> -1.1129618
B55: Average Growth Rate | C55: =IFERROR(AVERAGE(N46:N53),"") -> 0.042291472 | D55: =IFERROR(AVERAGE(O46:O53),"") -> 0.0062091167 | F55: =IFERROR(AVERAGE(Q46:Q53),"") -> 1.7654756 | H55: =IFERROR(AVERAGE(S46:S53),"") -> 0.15371378 | J55: Changes in Cash | L55: =L47-L48+L51-L52-L53 -> 1217 | M55: =M47-M48+M51-M52-M53 -> 809
B56: CVAR | C56: =IFERROR(STDEV(C46:C53)/AVERAGE(C46:C53),"") -> 0.14018825 | D56: =IFERROR(STDEV(D45:D53)/AVERAGE(D45:D53),"") -> 0.13266868 | F56: =IFERROR(STDEV(F45:F53)/AVERAGE(F45:F53),"") -> -13.681336 | H56: =IFERROR(STDEV(H45:H53)/AVERAGE(H45:H53),"") -> 0.3810048 | J56: Inventory/D Revenues | L56: =IFERROR(SUM(I50:I53)/(C53-C49),"") -> -0.74689745 | M56: =IFERROR((SUM(I50:I53)-SUM(H50:H53))/(C53-C49),"") -> -1.5263717
B57: Last Year | C57: =IFERROR(C53/C52-1,"") -> 0.090782678 | D57: =IFERROR(D53/D52-1,"") -> -0.066189557 | F57: =IFERROR(1-(F53/F52),"") -> 1.6139209 | H57: =IFERROR(1-(H53/H52),"") -> -0.47872978 | J57: t inversiones; t adq. neto dep. | L57: =IFERROR(L56/E26,"") -> -3.3608998 | M57: =IFERROR(M56/E26,"") -> -6.8683888
B58: QUALITATIVE ANALYSIS
B59: SWOT ANALYSIS | J59: HOLDERS
B60: Pros | E60: Cons | J60: Name | M60: % Stake
B61: Diversified product range; Exclusive Collaborations & Third-Party Brands;Strong Brand Reputation; Experienced management; Tech Investment in Online Shopping Experience; | E61: Over-reliance on the UK market; High allowance for doubtfull debts and impairment losses; Controversial Supplier Payments; Equal Pay Controversy; | J61: BlackRock Investment Management (UK) Ltd. | M61: 0.1009
J62: Capital Research Global Investors | M62: 0.0521
J63: INVESCO Asset Management Limited | M63: 0.0507
J64: Next ESOP Trust | M64: 0.0499
J65: Fidelity Management & Research Company LLC | M65: 0.0499
J66: Artemis Investment Management LLP | M66: 0.0307
J67: Norges Bank Investment Management (NBIM) | M67: 0.0307
J68: The Vanguard Group, Inc. | M68: 0.027
J69: BlackRock Institutional Trust Company, N.A. | M69: 0.0247
J70: Orbis Investment Management Ltd. | M70: 0.0205
B71: Opportunities | E71: Risks | J71: T. Rowe Price Associates, Inc. | M71: 0.0186
B72: Internacional Expansion; Acquisitions; | E72: Intense competition in the fashion retail industry,Capital Allocation Risks, Economic downturn | J72: BlackRock Advisors (UK) Limited | M72: 0.0151
J73: Invesco Advisers, Inc. | M73: 0.015
J74: Trinity Street Asset Management LLP | M74: 0.0117
J75: Lord Simon Adam Wolfson of Aspley Guise | M75: 0.0112
J76: Schroder Investment Management Ltd. (SIM) | M76: 0.0111
J77: Legal & General Investment Management Ltd. | M77: 0.0097
J78: State Street Global Advisors (UK) Ltd. | M78: 0.0091
J79: M&G Investment Management Ltd. [Activist] | M79: 0.0082
J80: MFS Investment Management | M80: 0.67%
J81: TOTAL | M81: =SUM(M61:M80) -> 0.5468
B82: NOTES | G82: STOCK PERFORMANCE (5 years)
G107: =E2 -> #VALUE! | I107: =Peers!C2 -> #VALUE! | J107: =Peers!C4 -> #VALUE! | L107: =Peers!C3 -> #VALUE! | M107: =Peers!C5 -> #VALUE!

Sheet Segments
B2: ="Regions "&"("&OP!$J$19&")" -> Regions (2023) | Q2: Products
D3: Nominal value | K3: YoY Growth
B4: Weight | C4: Region | D4: =OP!J19 -> 2023 | E4: =D4-1 -> 2022 | F4: =E4-1 -> 2021 | G4: =F4-1 -> 2020 | H4: =G4-1 -> 2019 | I4: =H4-1 -> 2018 | K4: =OP!J19 -> 2023 | L4: =K4-1 -> 2022 | M4: =L4-1 -> 2021 | N4: =M4-1 -> 2020 | O4: =N4-1 -> 2019 | P4: =O4-1 -> 2018
B5: =IFERROR(D5/$D$13,"") -> 0.83784374 | C5: United Kingdom | D5: 4600.6 | E5: 4290.7 | F5: 3837.5 | G5: 2931.5 | H5: 3665 | I5: 3656.9 | K5: =(D5-E5)/E5 -> 0.072225977 | L5: =(E5-F5)/F5 -> 0.11809772 | M5: =(F5-G5)/G5 -> 0.3090568 | N5: =(G5-H5)/H5 -> -0.20013643 | O5: =(H5-I5)/I5 -> 0.0022149908 | P5: -
B6: =IFERROR(D6/$D$13,"") -> 0.09504644 | C6: Rest of Europe | D6: 521.9 | E6: 415.3 | F6: 447 | G6: 311.6 | H6: 317.6 | I6: 279.2 | K6: =(D6-E6)/E6 -> 0.25668192 | L6: =(E6-F6)/F6 -> -0.070917226 | M6: =(F6-G6)/G6 -> 0.43453145 | N6: =(G6-H6)/H6 -> -0.018891688 | O6: =(H6-I6)/I6 -> 0.13753582 | P6: -
B7: =IFERROR(D7/$D$13,"") -> 0.046439628 | C7: Middle East | D7: 255 | E7: 235.6 | F7: 247 | G7: 215.8 | H7: 189.9 | I7: 138.7 | K7: =(D7-E7)/E7 -> 0.082342954 | L7: =(E7-F7)/F7 -> -0.046153846 | M7: =(F7-G7)/G7 -> 0.14457831 | N7: =(G7-H7)/H7 -> 0.13638757 | O7: =(H7-I7)/I7 -> 0.36914203 | P7: -
B8: =IFERROR(D8/$D$13,"") -> 0.0076306684 | C8: Asia | D8: 41.9 | E8: 48.5 | F8: 53 | G8: 43.3 | H8: 58.3 | I8: 56.1 | K8: =(D8-E8)/E8 -> -0.13608247 | L8: =(E8-F8)/F8 -> -0.08490566 | M8: =(F8-G8)/G8 -> 0.22401848 | N8: =(G8-H8)/H8 -> -0.25728988 | O8: =(H8-I8)/I8 -> 0.039215686 | P8: -
B9: =IFERROR(D9/$D$13,"") -> 0.013039519 | C9: Rest of world | D9: 71.6 | E9: 43.9 | F9: 41.4 | G9: 32.2 | H9: 35.4 | I9: 36.5 | K9: =(D9-E9)/E9 -> 0.6309795 | L9: =(E9-F9)/F9 -> 0.060386473 | M9: =(F9-G9)/G9 -> 0.28571429 | N9: =(G9-H9)/H9 -> -0.09039548 | O9: =(H9-I9)/I9 -> -0.030136986 | P9: -
B10: =IFERROR(D10/$D$13,"") -> 0 | K10: =(D10-E10)/E10 -> #DIV/0! | L10: =(E10-F10)/F10 -> #DIV/0! | M10: =(F10-G10)/G10 -> #DIV/0! | N10: =(G10-H10)/H10 -> #DIV/0! | O10: =(H10-I10)/I10 -> #DIV/0! | P10: -
B11: =IFERROR(D11/$D$13,"") -> 0
B12: =IFERROR(D12/$D$13,"") -> 0
B13: =SUM(B5:B12) -> 1 | C13: TOTAL | D13: =SUM(D5:D12) -> 5491 | E13: =SUM(E5:E12) -> 5034 | F13: =SUM(F5:F12) -> 4625.9 | G13: =SUM(G5:G12) -> 3534.4 | H13: =SUM(H5:H12) -> 4266.2 | I13: =SUM(I5:I12) -> 4167.4 | K13: =(D13-E13)/E13 -> 0.090782678 | L13: =(E13-F13)/F13 -> 0.088220671 | M13: =(F13-G13)/G13 -> 0.30882187 | N13: =(G13-H13)/H13 -> -0.17153439 | O13: =(H13-I13)/I13 -> 0.023707827 | P13: -
B15: ="Categories "&"("&OP!$J$19&")" -> Categories (2023)
D16: Nominal value | K16: YoY Growth
B17: Weight | C17: Category | D17: =OP!J19 -> 2023 | E17: =D17-1 -> 2022 | F17: =E17-1 -> 2021 | G17: =F17-1 -> 2020 | H17: =G17-1 -> 2019 | I17: =H17-1 -> 2018 | K17: =OP!J19 -> 2023 | L17: =K17-1 -> 2022 | M17: =L17-1 -> 2021 | N17: =M17-1 -> 2020 | O17: =N17-1 -> 2019 | P17: =O17-1 -> 2018
B18: =IFERROR(D18/$D$22,"") -> 0.52839191 | C18: NEXT Online | D18: =2911.9-10.5 -> 2901.4 | E18: =2744.2-0.6 -> 2743.6 | F18: =2874.4 -> 2874.4 | G18: =2279.5 -> 2279.5 | H18: =2056.3-1.6 -> 2054.7 | I18: =1864.6 -> 1864.6 | K18: =(D18-E18)/E18 -> 0.057515673 | L18: =(E18-F18)/F18 -> -0.045505149 | M18: =(F18-G18)/G18 -> 0.26097828 | N18: =(G18-H18)/H18 -> 0.1094077 | O18: =(H18-I18)/I18 -> 0.10195216 | P18: -
B19: =IFERROR(D19/$D$22,"") -> 0.33576762 | C19: NEXT Retail | D19: =1844.6-0.9 -> 1843.7 | E19: =1849.5-0.4 -> 1849.1 | F19: =1426.1-0.2+49.2 -> 1475.1 | G19: =952.2-0.3+33.2 -> 985.1 | H19: =1851.5-3.3+56.9 -> 1905.1 | I19: =1960.5-4.6+62.2 -> 2018.1 | K19: =(D19-E19)/E19 -> -0.0029203396 | L19: =(E19-F19)/F19 -> 0.25354213 | M19: =(F19-G19)/G19 -> 0.49741143 | N19: =(G19-H19)/H19 -> -0.48291428 | O19: =(H19-I19)/I19 -> -0.055993261 | P19: -
B20: =IFERROR(D20/$D$22,"") -> 0.053305409 | C20: NEXT Finance | D20: =292.7 -> 292.7 | E20: =274.4 -> 274.4 | F20: 249.4 | G20: 250.3 | H20: 268.7 | I20: =250.3 -> 250.3 | K20: =(D20-E20)/E20 -> 0.066690962 | L20: =(E20-F20)/F20 -> 0.10024058 | M20: =(F20-G20)/G20 -> -0.0035956852 | N20: =(G20-H20)/H20 -> -0.068477856 | O20: =(H20-I20)/I20 -> 0.073511786 | P20: -
B21: =IFERROR(D21/$D$22,"") -> 0.082535057 | C21: Other | D21: =363.8+192.4+543.8-170.9-475.9 -> 453.2 | E21: =75.7+175+602.5-156.1-530.2 -> 166.9 | F21: =134.1-130.3+1-0.8+180-167.3+495.5-485.2 -> 27 | G21: =401.4-394.6+79.3-74.1+0.7-0.6+200.6-193.2 -> 19.5 | H21: =542.9-533.4+94.9-81.8+211.3-196.2 -> 37.7 | I21: =550.1-543.2+95.4-80.4+215.4-202.9 -> 34.4 | K21: =(D21-E21)/E21 -> 1.7153984 | L21: =(E21-F21)/F21 -> 5.1814815 | M21: =(F21-G21)/G21 -> 0.38461538 | N21: =(G21-H21)/H21 -> -0.48275862 | O21: =(H21-I21)/I21 -> 0.095930233 | P21: -
B22: =SUM(B18:B21) -> 1 | C22: TOTAL | D22: =SUM(D18:D21) -> 5491 | E22: =SUM(E18:E21) -> 5034 | F22: =SUM(F18:F21) -> 4625.9 | G22: =SUM(G18:G21) -> 3534.4 | H22: =SUM(H18:H21) -> 4266.2 | I22: =SUM(I18:I21) -> 4167.4 | K22: =(D22-E22)/E22 -> 0.090782678 | L22: =(E22-F22)/F22 -> 0.088220671 | M22: =(F22-G22)/G22 -> 0.30882187 | N22: =(G22-H22)/H22 -> -0.17153439 | O22: =(H22-I22)/I22 -> 0.023707827 | P22: -
B24: Adjusted Profit of each category
D25: Nominal value | K25: YoY Growth
B26: Weight | C26: Category | D26: 2023 | E26: =D26-1 -> 2022 | F26: =E26-1 -> 2021 | G26: =F26-1 -> 2020 | H26: =G26-1 -> 2019 | I26: =H26-1 -> 2018 | K26: 2023 | L26: =K26-1 -> 2022 | M26: =L26-1 -> 2021 | N26: =M26-1 -> 2020 | O26: =N26-1 -> 2019 | P26: =O26-1 -> 2018
B27: =IFERROR(D27/$D$31,"") -> 0.52163825 | C27: NEXT Online | D27: 517.1 | E27: =467.3 -> 467.3 | F27: 588.5 | G27: 472.1 | H27: 399.6 | I27: 352.6 | K27: =(D27-E27)/E27 -> 0.10656966 | L27: =(E27-F27)/F27 -> -0.20594732 | M27: =(F27-G27)/G27 -> 0.24655793 | N27: =(G27-H27)/H27 -> 0.18143143 | O27: =(H27-I27)/I27 -> 0.13329552 | P27: -
B28: =IFERROR(D28/$D$31,"") -> 0.24684757 | C28: NEXT Retail | D28: 244.7 | E28: 240.5 | F28: =107+5.7 -> 112.7 | G28: =-205.9+3.4 -> -202.5 | H28: =163.9+6.2 -> 170.1 | I28: =212.3+6.2 -> 218.5 | K28: =(D28-E28)/E28 -> 0.017463617 | L28: =(E28-F28)/F28 -> 1.133984 | M28: =(F28-G28)/G28 -> -1.5565432 | N28: =(G28-H28)/H28 -> -2.1904762 | O28: =(H28-I28)/I28 -> -0.2215103 | P28: -
B29: =IFERROR(D29/$D$31,"") -> 0.16483406 | C29: NEXT Finance | D29: 163.4 | E29: 170.5 | F29: 141.8 | G29: 112.4 | H29: =127.3 -> 127.3 | I29: 127.3 | K29: =(D29-E29)/E29 -> -0.041642229 | L29: =(E29-F29)/F29 -> 0.20239774 | M29: =(F29-G29)/G29 -> 0.26156584 | N29: =(G29-H29)/H29 -> -0.11704635 | O29: =(H29-I29)/I29 -> 0 | P29: -
B30: =IFERROR(D30/$D$31,"") -> 0.066680117 | C30: Other | D30: =31.2+1.7+33.2 -> 66.1 | E30: =15.2+37+28.1 -> 80.3 | F30: =28+20.5+10.8 -> 59.3 | G30: =17.8+5.2-39.9 -> -16.9 | H30: =32+13-2.2 -> 42.8 | I30: =29.6+11+6.7 -> 47.3 | K30: =(D30-E30)/E30 -> -0.17683686 | L30: =(E30-F30)/F30 -> 0.35413153 | M30: =(F30-G30)/G30 -> -4.5088757 | N30: =(G30-H30)/H30 -> -1.3948598 | O30: =(H30-I30)/I30 -> -0.095137421 | P30: -
B31: =SUM(B27:B30) -> 1 | C31: TOTAL | D31: =SUM(D27:D30) -> 991.3 | E31: =SUM(E27:E30) -> 958.6 | F31: =SUM(F27:F30) -> 902.3 | G31: =SUM(G27:G30) -> 365.1 | H31: =SUM(H27:H30) -> 739.8 | I31: =SUM(I27:I30) -> 745.7 | K31: =(D31-E31)/E31 -> 0.034112247 | L31: =(E31-F31)/F31 -> 0.062396099 | M31: =(F31-G31)/G31 -> 1.4713777 | N31: =(G31-H31)/H31 -> -0.50648824 | O31: =(H31-I31)/I31 -> -0.007912029 | P31: -
B33: Categories | D33: Description | I33: Graphs
B34: NEXT Online | D34: The NEXT online segment offers a wide range of products via its digital platforms. It supports over 7.6 million UK customers and 1.7 million international customers, allowing them to shop from an extensive selection of NEXT-branded products and third-party brands. The segment integrates digital marketing systems, advanced warehousing, and distribution networks, ensuring efficient customer service and delivery. Additionally, NEXT stores play a complementary role by facilitating customer collections and returns .
B37: NEXT Retail | D37: The NEXT Retail segment encompasses the company's physical stores across the UK. It plays a vital role in supporting the brand’s omnichannel strategy, allowing customers to browse and purchase items in person, as well as facilitating collections and returns for online orders. The segment also includes a variety of store formats such as standalone retail outlets, shopping center locations, and retail park stores .
B38: NEXT Finance | D38: The NEXT Finance segment provides customers with flexible credit services. These credit accounts enable customers to purchase items from NEXT and spread payments over time, with interest applied. The segment plays a critical role in driving online and in-store sales by offering financing options and generating revenue through interest income. It also supports customer retention by providing a convenient purchasing method.
B39: Other | D39: The "Other" segment brings together several distinct operations under NEXT. It includes Total Platform, which offers comprehensive services such as e-commerce, warehousing, and logistics for partner brands like Reiss and FatFace, as well as third-party clients. Property management is another key component, managing and leasing properties that support both NEXT’s retail operations and external tenants. Additionally, the segment covers Franchise, Sourcing, and Other activities, focusing on global sourcing operations and franchise agreements to distribute NEXT products through international partnerships.
B41: Industry | J41: Graphs (Industry Forecasts)
B42: Drivers | D42: Description
B43: Digital Expansion and Ecommerce | D43: NEXT plc has significantly invested in its online platform, which has become a crucial pillar for growth. The company has developed a robust ecommerce infrastructure, including fast delivery services and options for in-store pickup. Additionally, NEXT has expanded its digital presence through a marketplace model, allowing other brands to sell through its platform. This strategy diversifies its product offerings and attracts a broader customer base, driving online sales, which now represent an increasingly large portion of the company’s total revenue.
B44: Product Expansion and Strategic Partnerships | D44: NEXT has formed partnerships with other brands and explored licensing opportunities, which helps it attract new market segments and expand its product offerings. These partnerships enable NEXT to reach a wider audience and enhance its market presence.
B45: Diversification of Revenue Streams + Leveraging Digital Infrastructure for Global Reach | D45: Expanding internationally would enable NEXT plc to diversify its revenue streams beyond the UK market, leverage its robust digital infrastructure for global reach, form strategic partnerships to adapt to local markets, and tap into the long-term potential of emerging regions as purchasing power increases.
B46: Sales forecast
B47: Source | D47: Market Growth CAGR | G47: Period
B48: Mordor intelligence | D48: 0.0765 | G48: 2024-2029
B49: Research and markets | D49: 0.081 | G49: 2024-2028
B50: Verified Market Research | D50: 0.0769 | G50: 2023-2030
B51: Average | D51: =AVERAGE(D48:F50) -> 0.078133333
B52: Company's Strategy / Extra Notes
B53: The company is focusing on increasing sales in Europe and the Middle East, where brand recognition is higher, and logistics are more manageable. To boost its presence in these regions, NEXT has invested in local infrastructure, such as a new warehouse in the UAE, which significantly reduces delivery times and enhances customer satisfaction. In more distant markets like the Americas and Asia, NEXT is exploring franchise and wholesale partnerships to mitigate risks and utilize local retailers' established infrastructure.
B54: The company is prioritizing digital and Total Platform expansion, leveraging its robust e-commerce infrastructure to support partner brands like Joules and MADE. This initiative allows NEXT to generate additional revenue through service fees while maximizing the use of its advanced online capabilities and distribution networks. By offering a comprehensive digital retail solution, NEXT aims to solidify its role as a leading player in the e-commerce space.
B55: NEXT is heavily investing in infrastructure and technology improvements, aiming to boost operational efficiency and customer service. The company is enhancing its warehouse capabilities with automation technologies and modernizing its online systems to offer better personalization in marketing. These initiatives are expected to increase capacity, reduce costs, and improve the overall shopping experience for customers.
B56: Sustainability is a key focus, as the company strives to reduce its environmental impact across its operations. Efforts include improving sustainable sourcing, minimizing waste, and implementing eco-friendly practices in its supply chain. By aligning its operations with long-term environmental goals, NEXT aims to meet growing consumer expectations for corporate responsibility and drive sustainable growth.
B57: The company is enhancing its product offerings by focusing on quality and expanding its price range to cater to a broader customer base. Additionally, NEXT is diversifying through acquisitions and the creation of new brands, increasing its stake in companies like Reiss and acquiring Cath Kidston. These moves help the company expand its market reach and offer a wider array of products to meet different customer preferences.
B59: Total PPE & Software for each category
D60: Nominal value | K60: YoY Growth
B61: Weight | C61: Category | D61: 2018 | E61: =D61+1 -> 2019 | F61: =E61+1 -> 2020 | G61: =F61+1 -> 2021 | H61: =G61+1 -> 2022 | I61: =H61+1 -> 2023 | K61: 2018 | L61: =K61+1 -> 2019 | M61: =L61+1 -> 2020 | N61: =M61+1 -> 2021 | O61: =N61+1 -> 2022 | P61: =O61+1 -> 2023
B62: =IFERROR(I62/$I$66,"") -> 0.62417326 | C62: NEXT Online | D62: =Y1048541 -> 95 | E62: =U1048541 -> 127.9 | F62: =Q1048541 -> 238.9 | G62: =M1048541 -> 336.6 | H62: =I1048541 -> 445.1 | I62: =E1048541 -> 481.3 | K62: - | L62: =E62/D62-1 -> 0.34631579 | M62: =F62/E62-1 -> 0.86786552 | N62: =G62/F62-1 -> 0.40895772 | O62: =H62/G62-1 -> 0.32234106 | P62: =I62/H62-1 -> 0.081330038
B63: =IFERROR(I63/$I$66,"") -> 0.27311633 | C63: NEXT Retail | D63: =Y1048542 -> 383.4 | E63: =U1048542 -> 345.4 | F63: =Q1048542 -> 239.9 | G63: =M1048542 -> 213.2 | H63: =I1048542 -> 205.7 | I63: =E1048542 -> 210.6 | K63: - | L63: =E63/D63-1 -> -0.099113198 | M63: =F63/E63-1 -> -0.30544296 | N63: =G63/F63-1 -> -0.11129637 | O63: =H63/G63-1 -> -0.035178236 | P63: =I63/H63-1 -> 0.023821099
B64: =IFERROR(I64/$I$66,"") -> 0 | C64: NEXT Finance | D64: =Y1048543 -> 0 | E64: =U1048543 -> 0 | F64: =Q1048543 -> 0 | G64: =M1048543 -> 0 | H64: =I1048543 -> 0 | I64: =E1048543 -> 0 | K64: - | L64: - | M64: - | N64: - | O64: - | P64: -
B65: =IFERROR(I65/$I$66,"") -> 0.10271041 | C65: Other | D65: =Y1048544 -> 86.5 | E65: =U1048544 -> 105.2 | F65: =Q1048544 -> 12.2 | G65: =M1048544 -> 86.6 | H65: =I1048544 -> 65.4 | I65: =E1048544 -> 79.2 | K65: - | L65: =E65/D65-1 -> 0.21618497 | M65: =F65/E65-1 -> -0.88403042 | N65: =G65/F65-1 -> 6.0983607 | O65: =H65/G65-1 -> -0.2448037 | P65: =I65/H65-1 -> 0.21100917
B66: =IFERROR(I66/$I$66,"") -> 1 | C66: TOTAL | D66: =Y1048545 -> 564.9 | E66: =U1048545 -> 578.5 | F66: =Q1048545 -> 491 | G66: =M1048545 -> 636.4 | H66: =I1048545 -> 716.2 | I66: =E1048545 -> 771.1 | K66: - | L66: =E66/D66-1 -> 0.024075058 | M66: =F66/E66-1 -> -0.15125324 | N66: =G66/F66-1 -> 0.29613035 | O66: =H66/G66-1 -> 0.12539283 | P66: =I66/H66-1 -> 0.076654566
B68: Right-of-use assets for each category
D69: Nominal value | K69: YoY Growth
B70: Weight | C70: Category | D70: 2018 | E70: =D70+1 -> 2019 | F70: =E70+1 -> 2020 | G70: =F70+1 -> 2021 | H70: =G70+1 -> 2022 | I70: =H70+1 -> 2023 | K70: 2018 | L70: =K70+1 -> 2019 | M70: =L70+1 -> 2020 | N70: =M70+1 -> 2021 | O70: =N70+1 -> 2022 | P70: =O70+1 -> 2023
B71: =IFERROR(I71/$I$75,"") -> 0.20841274 | C71: NEXT Online | D71: =Z1048541 -> N/A | E71: =V1048541 -> N/A | F71: =R1048541 -> 111.3 | G71: =N1048541 -> 94.9 | H71: =J1048541 -> 132.8 | I71: =F1048541 -> 153.1 | K71: - | L71: - | M71: - | N71: =G71/F71-1 -> -0.14734951 | O71: =H71/G71-1 -> 0.39936776 | P71: =I71/H71-1 -> 0.15286145
B72: =IFERROR(I72/$I$75,"") -> 0.66526001 | C72: NEXT Retail | D72: =Z1048542 -> N/A | E72: =V1048542 -> N/A | F72: =R1048542 -> 593 | G72: =N1048542 -> 534.6 | H72: =J1048542 -> 521 | I72: =F1048542 -> 488.7 | K72: - | L72: - | M72: - | N72: =G72/F72-1 -> -0.098482293 | O72: =H72/G72-1 -> -0.025439581 | P72: =I72/H72-1 -> -0.061996161
B73: =IFERROR(I73/$I$75,"") -> 0 | C73: NEXT Finance | D73: =Z1048543 -> N/A | E73: =V1048543 -> N/A | F73: =R1048543 -> 0 | G73: =N1048543 -> 0 | H73: =J1048543 -> 0 | I73: =F1048543 -> 0 | K73: - | L73: - | M73: - | N73: - | O73: - | P73: -
B74: =IFERROR(I74/$I$75,"") -> 0.12632725 | C74: Other | D74: =Z1048544 -> N/A | E74: =V1048544 -> N/A | F74: =R1048544 -> 15.8 | G74: =N1048544 -> 9.6 | H74: =J1048544 -> 8.2 | I74: =F1048544 -> 92.8 | K74: - | L74: - | M74: - | N74: =G74/F74-1 -> -0.39240506 | O74: =H74/G74-1 -> -0.14583333 | P74: =I74/H74-1 -> 10.317073
B75: =IFERROR(I75/$I$75,"") -> 1 | C75: TOTAL | D75: =Z1048545 -> N/A | E75: =V1048545 -> N/A | F75: =R1048545 -> 720.1 | G75: =N1048545 -> 639.1 | H75: =J1048545 -> 662 | I75: =F1048545 -> 734.6 | K75: - | L75: - | M75: - | N75: =G75/F75-1 -> -0.11248438 | O75: =H75/G75-1 -> 0.035831638 | P75: =I75/H75-1 -> 0.10966767
B77: CAPEX including software for each category
D78: Nominal value | K78: YoY Growth
B79: Weight | C79: Category | D79: 2018 | E79: =D79+1 -> 2019 | F79: =E79+1 -> 2020 | G79: =F79+1 -> 2021 | H79: =G79+1 -> 2022 | I79: =H79+1 -> 2023 | K79: 2018 | L79: =K79+1 -> 2019 | M79: =L79+1 -> 2020 | N79: =M79+1 -> 2021 | O79: =N79+1 -> 2022 | P79: =O79+1 -> 2023
B80: =IFERROR(I80/$I$84,"") -> 0.42632613 | C80: NEXT Online | D80: =AA1048541 -> 31.8 | E80: =W1048541 -> 52.3 | F80: =S1048541 -> 97.3 | G80: =O1048541 -> 130.2 | H80: =K1048541 -> 144.9 | I80: =G1048541 -> 86.8 | K80: - | L80: =E80/D80-1 -> 0.64465409 | M80: =F80/E80-1 -> 0.86042065 | N80: =G80/F80-1 -> 0.3381295 | O80: =H80/G80-1 -> 0.11290323 | P80: =I80/H80-1 -> -0.40096618
B81: =IFERROR(I81/$I$84,"") -> 0.36198428 | C81: NEXT Retail | D81: =AA1048542 -> 93.1 | E81: =W1048542 -> 68.8 | F81: =S1048542 -> 49.6 | G81: =O1048542 -> 50.3 | H81: =K1048542 -> 63.9 | I81: =G1048542 -> 73.7 | K81: - | L81: =E81/D81-1 -> -0.26100967 | M81: =F81/E81-1 -> -0.27906977 | N81: =G81/F81-1 -> 0.014112903 | O81: =H81/G81-1 -> 0.27037773 | P81: =I81/H81-1 -> 0.15336463
B82: =IFERROR(I82/$I$84,"") -> 0 | C82: NEXT Finance | D82: =AA1048543 -> 0 | E82: =W1048543 -> 0 | F82: =S1048543 -> 0 | G82: =O1048543 -> 0 | H82: =K1048543 -> 0 | I82: =G1048543 -> 0 | K82: - | L82: - | M82: - | N82: - | O82: - | P82: -
B83: =IFERROR(I83/$I$84,"") -> 0.21168959 | C83: Other | D83: =AA1048544 -> 3.7 | E83: =W1048544 -> 17.7 | F83: =S1048544 -> 15.9 | G83: =O1048544 -> 81.4 | H83: =K1048544 -> 39.6 | I83: =G1048544 -> 43.1 | K83: - | L83: =E83/D83-1 -> 3.7837838 | M83: =F83/E83-1 -> -0.10169492 | N83: =G83/F83-1 -> 4.1194969 | O83: =H83/G83-1 -> -0.51351351 | P83: =I83/H83-1 -> 0.088383838
B84: =IFERROR(I84/$I$84,"") -> 1 | C84: TOTAL | D84: =AA1048545 -> 128.6 | E84: =W1048545 -> 138.8 | F84: =S1048545 -> 162.8 | G84: =O1048545 -> 261.9 | H84: =K1048545 -> 248.4 | I84: =G1048545 -> 203.6 | K84: - | L84: =E84/D84-1 -> 0.079315708 | M84: =F84/E84-1 -> 0.17291066 | N84: =G84/F84-1 -> 0.60872236 | O84: =H84/G84-1 -> -0.051546392 | P84: =I84/H84-1 -> -0.18035427
AH139: =HYPERLINK("#Segments!A1","Back to segments") -> Back to segments | AM139: Evolution of the weight of revenue by segment category over total revenue (2018-2023)
BH339: =HYPERLINK("#Segments!A1","Back to segments") -> Back to segments
CH539: =HYPERLINK("#Segments!A1","Back to segments") -> Back to segments
DH739: =HYPERLINK("#Segments!A1","Back to segments") -> Back to segments
C1048537: Segment assets, right-of-use assets, capital expenditure and depreciation
E1048538: Nominal value
E1048539: 2023 | I1048539: 2022 | M1048539: 2021 | Q1048539: 2020 | U1048539: 2019 | Y1048539: 2018
C1048540: Weight (PPE & Soft.) | D1048540: Category | E1048540: PPE & Software | F1048540: Right-of-use assets | G1048540: CAPEX including software | H1048540: Dep. & Amort. | I1048540: PPE & Software | J1048540: Right-of-use assets | K1048540: CAPEX including software | L1048540: Dep. & Amort. | M1048540: PPE & Software | N1048540: Right-of-use assets | O1048540: CAPEX including software | P1048540: Dep. & Amort. | Q1048540: PPE & Software | R1048540: Right-of-use assets | S1048540: CAPEX including software | T1048540: Dep. & Amort. | U1048540: PPE & Software | V1048540: Right-of-use assets | W1048540: CAPEX including software | X1048540: Dep. & Amort. | Y1048540: PPE & Software | Z1048540: Right-of-use assets | AA1048540: CAPEX including software | AB1048540: Dep. & Amort.
C1048541: =IFERROR(E1048541/$E$1048545,"") -> 0.62417326 | D1048541: NEXT Online | E1048541: 481.3 | F1048541: 153.1 | G1048541: =86.8 -> 86.8 | H1048541: =54.7 -> 54.7 | I1048541: =445.1 -> 445.1 | J1048541: =132.8 -> 132.8 | K1048541: =144.9 -> 144.9 | L1048541: =46.8 -> 46.8 | M1048541: 336.6 | N1048541: 94.9 | O1048541: 130.2 | P1048541: 36 | Q1048541: 238.9 | R1048541: 111.3 | S1048541: =97.3 -> 97.3 | T1048541: 31.5 | U1048541: =127.4+0.5 -> 127.9 | V1048541: N/A | W1048541: 52.3 | X1048541: =19.8 -> 19.8 | Y1048541: 95 | Z1048541: N/A | AA1048541: =31.8 -> 31.8 | AB1048541: 18.4
C1048542: =IFERROR(E1048542/$E$1048545,"") -> 0.27311633 | D1048542: NEXT Retail | E1048542: 210.6 | F1048542: =488.7 -> 488.7 | G1048542: =73.7 -> 73.7 | H1048542: =163.1 -> 163.1 | I1048542: 205.7 | J1048542: =521 -> 521 | K1048542: 63.9 | L1048542: 168 | M1048542: 213.2 | N1048542: 534.6 | O1048542: =50.3 -> 50.3 | P1048542: 181.1 | Q1048542: 239.9 | R1048542: =592.3+0.7 -> 593 | S1048542: 49.6 | T1048542: =217.9+0.6 -> 218.5 | U1048542: 345.4 | V1048542: N/A | W1048542: 68.8 | X1048542: =96.8+0.1 -> 96.9 | Y1048542: =382.6+0.8 -> 383.4 | Z1048542: N/A | AA1048542: =93+0.1 -> 93.1 | AB1048542: =99.1+0.3 -> 99.4
C1048543: =IFERROR(E1048543/$E$1048545,"") -> 0 | D1048543: NEXT Finance | E1048543: 0 | F1048543: =0 -> 0 | G1048543: 0 | H1048543: 0 | I1048543: 0 | J1048543: 0 | K1048543: 0 | L1048543: 0 | M1048543: 0 | N1048543: 0 | O1048543: 0 | P1048543: 0 | Q1048543: 0 | R1048543: 0 | S1048543: 0 | T1048543: 0 | U1048543: 0 | V1048543: N/A | W1048543: 0 | X1048543: 0 | Y1048543: 0 | Z1048543: N/A | AA1048543: 0 | AB1048543: 0
C1048544: =IFERROR(E1048544/$E$1048545,"") -> 0.10271041 | D1048544: Other | E1048544: =53.3+1.9+24 -> 79.2 | F1048544: =90+2.8 -> 92.8 | G1048544: =5.4+36.7+1 -> 43.1 | H1048544: =28.4+2.6 -> 31 | I1048544: =8.3+55.6+1.5 -> 65.4 | J1048544: =5.3+2.9 -> 8.2 | K1048544: =0.5+38.5+0.6 -> 39.6 | L1048544: =1.1+0.3+3.8 -> 5.2 | M1048544: =83.7+0.9+2 -> 86.6 | N1048544: =4.6+5 -> 9.6 | O1048544: =79.8+0.6+1 -> 81.4 | P1048544: =3.6+0.3-0.3 -> 3.6 | Q1048544: =2+0.5+9.7 -> 12.2 | R1048544: =3.6+2.1+10.1 -> 15.8 | S1048544: =0.5+15.4 -> 15.9 | T1048544: =3.3+1.6+0.7 -> 5.6 | U1048544: =2.6+2.4+100.2 -> 105.2 | V1048544: N/A | W1048544: =16.5+0.1+1.1 -> 17.7 | X1048544: =1.1+0.9+0.3 -> 2.3 | Y1048544: =2.5+3.8+80.2 -> 86.5 | Z1048544: N/A | AA1048544: =0.9+1.3+1.5 -> 3.7 | AB1048544: =1.1+0.3+0.9 -> 2.3
C1048545: =SUM(C1048541:C1048544) -> 1 | D1048545: TOTAL | E1048545: =SUM(E1048541:E1048544) -> 771.1 | F1048545: =SUM(F1048541:F1048544) -> 734.6 | G1048545: =SUM(G1048541:G1048544) -> 203.6 | H1048545: =SUM(H1048541:H1048544) -> 248.8 | I1048545: =SUM(I1048541:I1048544) -> 716.2 | J1048545: =SUM(J1048541:J1048544) -> 662 | K1048545: =SUM(K1048541:K1048544) -> 248.4 | L1048545: =SUM(L1048541:L1048544) -> 220 | ... U1048545: =SUM(U1048541:U1048544) -> 578.5 | V1048545: N/A | W1048545: =SUM(W1048541:W1048544) -> 138.8 | X1048545: =SUM(X1048541:X1048544) -> 119 | Y1048545: =SUM(Y1048541:Y1048544) -> 564.9 | Z1048545: N/A | AA1048545: =SUM(AA1048541:AA1048544) -> 128.6 | AB1048545: =SUM(AB1048541:AB1048544) -> 120.1

Sheet Peers
B1: Peer Logo | C1: Peer Name | D1: Description
C2: #VALUE! | D2: Leading British retailer with over 900 stores, mostly UK and Ireland. Founded in 1884, M&S sells clothing, beauty products, home goods, and food. In 2023 company employed over 72,000 people and reported an annual revenue of £11.931 billion. Company is known for it´s high-quality own-brand products, focus on sustainability through iniciatives. Is listed on the stock market exchange.
C3: #VALUE! | D3: Global retailer of sports fashion and outdoor brands, offers a wide range of products including apparel, footwear and accesories from diverse brands. Company was founded in 1981 by John Wardle and David Makin. In 2023 counted with 3400 stores across 38 territories, employing 90 000 individuals worlswide. Company is known for it´s competitive spirit and commitment to ethical practices.
C4: #VALUE! | D4: Polish multinational company with 2000 across all Europe, Asia and Africa. LP employes 30 000 individuals wordwide. Company was founded in 1991 by Marek Piechocki and Jerzy Lubianiec. LPP offers a wide range of products throught its five fashion brands, Reserved, House, Cropp and Sinsay. The company is known for its innovative designs and commitment for sustainability. Company is listed on the Warsaw stock exchange.
C5: #VALUE! | D5: H&M, a global fashion retailer with over 4000 stores in more than 75 markets,was founded in 1974 by Erlin Persson and emplys 100 000 individuals worldwide. Company offers a wide range of products like pieces of clothing, acessories, footwear, cosmetics and home textils. H&M has a bussiness of fast fashion and has a constant commitment to sustainability.
B8: In Millions USD | C8: =OP!E2 -> #VALUE! | D8: =C2 -> #VALUE! | E8: =C3 -> #VALUE! | F8: =C4 -> #VALUE! | G8: =C5 -> #VALUE! | I8: AVERAGE | J8: Deviation from Average
B9: Company Info | I9: =IFERROR(AVERAGE(C9:H9),"") | L9: TRAFFIC
B10: Market Cap | C10: {=_FV(C8,"Market cap",TRUE)/1000000} -> 16223.82 | D10: {=_FV(D8,"Market cap",TRUE)/1000000} -> 8356.428 | E10: {=_FV(E8,"Market cap",TRUE)/1000000} -> 4946.957 | F10: {=_FV(F8,"Market cap",TRUE)/1000000} -> 32199.69 | G10: {=_FV(G8,"Market cap",TRUE)/1000000} -> 251207.8 | I10: =IFERROR(AVERAGE(C10:H10),"") -> 62586.939 | J10: =SQRT((C10-I10)^2) -> 46363.119 | M10: Best Value
B11: Net Sales (current) | C11: =C59 -> 5491 | D11: =D59 -> 13040.1 | E11: =E59 -> 10397.2 | F11: =F59 -> 3419.324 | G11: =G59 -> 17945.741 | I11: =IFERROR(AVERAGE(C11:H11),"") -> 10058.673 | J11: =SQRT((C11-I11)^2) -> 4567.673
B12: Profitability | I12: =IFERROR(AVERAGE(C12:H12),"") | M12: Important Value
B13: Sales Growth (ttm) | C13: =C59/C58-1 -> 0.090782678 | D13: =D59/D57-1 -> 0.19850556 | E13: =E59/E58-1 -> 0.026883951 | F13: =F59/F58-1 -> 0.15092134 | G13: =G59/G58-1 -> 0.01626924 | I13: =IFERROR(AVERAGE(C13:H13),"") -> 0.096672553 | J13: =SQRT((C13-I13)^2) -> 0.005889875
B14: Sales Growth (36m) | C14: =C59/C57-1 -> 0.5535876 | D14: =D59/D57-1 -> 0.19850556 | E14: =E59/E57-1 -> 0.057561055 | F14: =F59/F57-1 -> 0.53919188 | G14: =G59/G57-1 -> -0.0906613 | I14: =IFERROR(AVERAGE(C14:H14),"") -> 0.25163696 | J14: =SQRT((C14-I14)^2) -> 0.30195064 | M14: Worst Value
B15: Operating Margin | C15: =C62/C59 -> 0.17767256 | D15: =D62/D59 -> 0.054769519 | E15: =E62/E59 -> 0.0029334821 | F15: =F62/F59 -> 0.058701895 | G15: =G62/G59 -> 0.083174106 | I15: =IFERROR(AVERAGE(C15:H15),"") -> 0.075450311 | J15: =SQRT((C15-I15)^2) -> 0.10222224
B16: Net Income Margin | C16: =C65/C59 -> 0.14578401 | D16: =D65/D59 -> 0.054769519 | E16: =E65/E59 -> 0.051821644 | F16: =F65/F59 -> 0.058701895 | G16: =G65/G59 -> 0.01835321 | I16: =IFERROR(AVERAGE(C16:H16),"") -> 0.065886056 | J16: =SQRT((C16-I16)^2) -> 0.079897954
B17: Return on Equity (RoE) | C17: =C65/C77 -> 0.57797834 | D17: =D65/D77 -> 0.25235857 | E17: =E65/E77 -> 0.18783991 | F17: =F65/F77 -> 0.23833955 | G17: =G65/G77 -> 0.091006491 | I17: =IFERROR(AVERAGE(C17:H17),"") -> 0.26950457 | J17: =SQRT((C17-I17)^2) -> 0.30847377
B18: Return on Invested Capital (ROIC) | C18: =(1+C64/(C62+C63))*C62/(C76+C77-C68) -> 0.23796645 | D18: =(1+D64/(D62+D63))*D62/(D76+D77-D68) -> 0.52728242 | E18: =(1+E64/(E62+E63))*E62/(E76+E77-E68) -> 0.0094420573 | F18: =(1+F64/(F62+F63))*F62/(F76+F77-F68) -> 0.33786385 | G18: =(1+G64/(G62+G63))*G62/(G76+G77-G68) -> 0.34040151 | I18: =IFERROR(AVERAGE(C18:H18),"") -> 0.29059126 | J18: =SQRT((C18-I18)^2) -> 0.052624806
B19: Solvency | I19: =IFERROR(AVERAGE(C19:H19),"")
B20: Debt/Assets | C20: =C76/C73 -> 0.4057109 | D20: =D76/D73 -> 0.0013475847 | E20: =E76/E73 -> 0.14059059 | F20: =F76/F73 -> 0.01658044 | G20: =G76/G73 -> 1.5960859 | I20: =IFERROR(AVERAGE(C20:H20),"") -> 0.43206308 | J20: =SQRT((C20-I20)^2) -> 0.026352184
B21: Net Debt/EBITDA | C21: =(C76-C68)/C61 -> 1.569133 | D21: =(D76-D68)/D61 -> -3.7712687 | E21: =(E76-E68)/E61 -> 1.0659857 | F21: =(F76-F68)/F61 -> -0.28211524 | G21: =(G76-G68)/G61 -> 0.49186734 | I21: =IFERROR(AVERAGE(C21:H21),"") -> -0.18527958 | J21: =SQRT((C21-I21)^2) -> 1.7544126
B22: Interest Coverage Ratio | C22: =-C61/C63 -> 13.649318 | D22: =-D61/D63 -> -42.539683 | E22: =-E61/E63 -> -2.4844167 | F22: =-F61/F63 -> -1.04619 | G22: =-G61/G63 -> -47.228182 | I22: =IFERROR(AVERAGE(C22:H22),"") -> -15.929831 | J22: =SQRT((C22-I22)^2) -> 29.579149
B23: Liquidity
B24: Current Ratio | C24: =C71/C75 -> 1.9649193 | D24: =D71/D75 -> 0.85577458 | E24: =E71/E75 -> 1.5241673 | F24: =F71/F75 -> 0.90857646 | G24: =G71/G75 -> 0.24692685 | I24: =IFERROR(AVERAGE(C24:H24),"") -> 1.1000729 | J24: =SQRT((C24-I24)^2) -> 0.86484642
B25: Quick Ratio | C25: =(C68+C69)/C75 -> 1.1693827 | D25: =(D68+D69)/D75 -> 0.66811064 | E25: =(E68+E69)/E75 -> 0.39539194 | F25: =(F68+F69)/F75 -> 0.22044769 | G25: =(G68+G69)/G75 -> 0.46386562 | I25: =IFERROR(AVERAGE(C25:H25),"") -> 0.58343971 | J25: =SQRT((C25-I25)^2) -> 0.58594296
B26: Activity | I26: =IFERROR(AVERAGE(C26:H26),"")
B27: Inventory Turnover | C27: =C60/C70 -> 3.9928479 | D27: =D60/D70 -> 0.0069507015 | E27: =E60/E70 -> 3.4494883 | F27: =F60/F70 -> 1.2476312 | G27: =G60/G70 -> 0.68046052 | I27: =IFERROR(AVERAGE(C27:H27),"") -> 1.8754757 | J27: =SQRT((C27-I27)^2) -> 2.1173721
B28: Acc. Receivable Turnover | C28: =C59/C69 -> 4.329076 | D28: =D59/D69 -> 19.796721 | E28: =E59/E69 -> 41.095652 | F28: =F59/F69 -> 48.904494 | G28: =G59/G69 -> 46.181765 | I28: =IFERROR(AVERAGE(C28:H28),"") -> 32.061542 | J28: =SQRT((C28-I28)^2) -> 27.732466
A29: Price/Sales | B29: Payables Turnover | C29: =C60/C74 -> 3.0958863 | D29: =D60/D74 -> 0.0025617914 | E29: =E60/E74 -> -3.799184 | F29: =F60/F74 -> 64.96 | G29: =G60/G74 -> 0.29795025 | I29: =IFERROR(AVERAGE(C29:H29),"") -> 12.911443 | J29: =SQRT((C29-I29)^2) -> 9.8155566
B30: Fixed Asset Turnover | C30: =C59/C72 -> 7.9869091 | D30: =D59/D72 -> 1.997289 | E30: =E59/E72 -> 2.0781931 | F30: =F59/F72 -> 1.9743706 | G30: =G59/G72 -> 485.66872 | I30: =IFERROR(AVERAGE(C30:H30),"") -> 99.941097 | J30: =SQRT((C30-I30)^2) -> 91.954188
B31: Total Asset Turnover | C31: =C59/C73 -> 1.1622886 | D31: =D59/D73 -> 1.501935 | E31: =E59/E73 -> 1.2921876 | F31: =F59/F73 -> 1.0852085 | G31: =G59/G73 -> 7.2516821 | I31: =IFERROR(AVERAGE(C31:H31),"") -> 2.4586604 | J31: =SQRT((C31-I31)^2) -> 1.2963718
B32: Valuation | I32: =IFERROR(AVERAGE(C32:H32),"")
B33: Price/Earnings | C33: =C10/C65 -> 20.267108 | D33: 10.7 | E33: 14.61 | F33: 5.44 | G33: 6.7 | I33: =IFERROR(AVERAGE(C33:H33),"") -> 11.543422 | J33: =SQRT((C33-I33)^2) -> 8.7236864
B34: Price/Sales | C34: =C10/C59 -> 2.9546203 | D34: =D10/D59 -> 0.64082545 | E34: =E10/E59 -> 0.47579704 | F34: =F10/F59 -> 9.4169754 | G34: =G10/G59 -> 13.998185 | I34: =IFERROR(AVERAGE(C34:H34),"") -> 5.4972806 | J34: =SQRT((C34-I34)^2) -> 2.5426603
B35: Price/Book | C35: =C10/C77 -> 11.713949 | D35: =D10/D77 -> 2.9526971 | E35: =E10/E77 -> 1.7246399 | F35: =F10/F77 -> 38.234501 | G35: =G10/G77 -> 69.4116 | I35: =IFERROR(AVERAGE(C35:H35),"") -> 24.807477 | J35: =SQRT((C35-I35)^2) -> 13.093528
B36: EV/Sales | C36: =(C76+C10-C68)/C59 -> 3.2693899 | D36: =(D76+D10-D68)/D59 -> 0.56331838 | E36: =(E76+E10-E68)/E59 -> 0.53300667 | F36: =(F76+F10-F68)/F59 -> 9.3520127 | G36: =(G76+G10-G68)/G59 -> 14.106444 | I36: =IFERROR(AVERAGE(C36:H36),"") -> 5.5648344 | J36: =SQRT((C36-I36)^2) -> 2.2954445
B37: EV/EBITDA | C37: 9.39 | D37: 6.61 | E37: =(E76+E10-E68)/E61 -> 9.9315 | F37: =(F76+F10-F68)/F61 -> 40.613256 | G37: =(G76+G10-G68)/G61 -> 64.091443 | I37: =IFERROR(AVERAGE(C37:H37),"") -> 31.00655 | J37: =SQRT((C37-I37)^2) -> 21.61655
B38: Stock Info | I38: =IFERROR(AVERAGE(C38:H38),"")
B39: Float | C39: =OP!M19 -> 0.88814229 | D39: 0.946 | E39: 0.477 | F39: 0.597 | G39: 0.37 | I39: =IFERROR(AVERAGE(C39:H39),"") -> 0.65562846 | J39: =SQRT((C39-I39)^2) -> 0.23251383
B40: b (Yahoo) | C40: =OP!M21 -> 1.3444 | D40: 1.62 | E40: 1.65 | F40: 1.14 | G40: 1.25 | I40: =IFERROR(AVERAGE(C40:H40),"") -> 1.40088 | J40: =SQRT((C40-I40)^2) -> 0.05648
B41: Dividend Yield (yahoo finance) | C41: =OP!M31 -> 0.00015094815 | D41: 0,80% | E41: 0.0058 | F41: 0.056 | G41: 0.0379 | I41: =IFERROR(AVERAGE(C41:H41),"") -> 0.024962737 | J41: =SQRT((C41-I41)^2) -> 0.024811789
B42: Stock Performance
B43: 1y | C43: 0.3378 | D43: 0.6424 | E43: 0.3949 | F43: 0.2939 | G43: -0.0142 | I43: =IFERROR(AVERAGE(C43:H43),"") -> 0.33096 | J43: =SQRT((C43-I43)^2) -> 0.00684
B44: 3y | C44: 0.56 | D44: 0.7315 | E44: 0.4574 | F44: 1.8425 | G44: 0.4378 | I44: =IFERROR(AVERAGE(C44:H44),"") -> 0.80584 | J44: =SQRT((C44-I44)^2) -> 0.24584
B45: Current Price | C45: {=_FV(C8,"Price")} -> 13435 | D45: 3.68 | E45: {=_FV(E8,"Price")} -> 1.28 | F45: {=_FV(F8,"Price")} -> 17285 | G45: {=_FV(G8,"Price")} -> 180.1 | I45: =IFERROR(AVERAGE(C45:H45),"") -> 6181.012 | J45: =SQRT((C45-I45)^2) -> 7253.988
B46: Average Target Price | C46: 10115 | D46: 3.37 | E46: 1.69 | F46: 18545 | G46: 185.5 | I46: =IFERROR(AVERAGE(C46:H46),"") -> 5770.112 | J46: =SQRT((C46-I46)^2) -> 4344.888
B47: Upside/Downside | C47: =C46/C45-1 -> -0.24711574 | D47: =D46/D45-1 -> -0.08423913 | E47: =E46/E45-1 -> 0.3203125 | F47: =F46/F45-1 -> 0.072895574 | G47: =G46/G45-1 -> 0.029983343 | I47: =IFERROR(AVERAGE(C47:H47),"") -> 0.018367309 | J47: =SQRT((C47-I47)^2) -> 0.26548305
B48: Extra | I48: =IFERROR(AVERAGE(C48:H48),"")
B49: 3y Operating Cash Flow | C49: =(Inputs!B59-Inputs!E59)/Inputs!E59 -> 0.35826867 | D49: =1029.9/513 -> 2.0076023 | E49: =59521/42544 -> 1.3990457 | F49: =4343.3/1074.533 -> 4.042035 | G49: =33949/25900 -> 1.3107722 | I49: =IFERROR(AVERAGE(C49:H49),"") -> 1.8235448 | J49: =SQRT((C49-I49)^2) -> 1.4652761
B50: R&D/Net Sales | C50: =C66/C11 -> 0 | D50: =D66/D11 -> 0 | E50: =E66/E11 -> 0 | F50: =F66/F11 -> 0 | G50: =G66/G11 -> 0 | I50: =IFERROR(AVERAGE(C50:H50),"") -> 0 | J50: =SQRT((C50-I50)^2) -> 0
B51: Revenues from UK | I51: =IFERROR(AVERAGE(C51:H51),"")
B52: Weight over total revenues | C52: =C79/C59 -> 0.83784374 | D52: =D79/D59 -> 0.92556806 | E52: =E79/E59 -> 0.031912438 | F52: =F79/F59 -> 0.14543366 | G52: =G79/G59 -> 0.33490372 | I52: =IFERROR(AVERAGE(C52:H52),"") -> 0.45513232 | J52: =SQRT((C52-I52)^2) -> 0.38271142
B53: Total revenues from UK | C53: =C79 -> 4600.6 | D53: =D79 -> 12069.5 | E53: =E79 -> 331.8 | F53: =F79 -> 497.2848 | G53: =G79 -> 6010.0955 | I53: =IFERROR(AVERAGE(C53:H53),"") -> 4701.8561 | J53: =SQRT((C53-I53)^2) -> 101.25605
B55: Financial Data | C55: =OP!E2 -> #VALUE! | D55: =D8 -> #VALUE! | E55: =E8 -> #VALUE! | F55: =F8 -> #VALUE! | G55: =G8 -> #VALUE!
B56: IS
B57: Net Sales (36m ago) | C57: ='Fin. Data'!E5 -> 3534.4 | D57: 10880.3 | E57: 9831.3 | F57: =11340*F88 -> 2221.506 | G57: =G88*223600 -> 19734.936
B58: Net Sales (12m ago) | C58: ='Fin. Data'!C5 -> 5034 | D58: 11.9313 | E58: 10125 | F58: =15930*F87 -> 2970.945 | G58: =G87*223553 -> 17658.451
B59: Net Sales (current) | C59: ='Fin. Data'!B5 -> 5491 | D59: 13040.1 | E59: 10397.2 | F59: =F86*17410 -> 3419.324 | G59: =G86*236035 -> 17945.741
B60: COGS | C60: ='Fin. Data'!B5-'Fin. Data'!B7 -> 3070.5 | D60: 5.4 | E60: 5494 | F60: =F86*4872 -> 956.8608 | G60: =G86*6265 -> 476.32795
B61: EBITDA | C61: ='Fin. Data'!B19 -> 1101.5 | D61: 268 | E61: 558 | F61: =F86*4009 -> 787.3676 | G61: =G86*51951 -> 3949.8345
B62: Operating Income | C62: ='Fin. Data'!B11 -> 975.6 | D62: 714.2 | E62: 30.5 | F62: =F86*1022 -> 200.7208 | G62: =G86*19632 -> 1492.621
B63: Net Financial Cost | C63: ='Fin. Data'!B14 -> -80.7 | D63: 6.3 | E63: 224.6 | F63: =F86*3832 -> 752.6048 | G63: =G86*1100 -> 83.633
B64: Taxes | C64: ='Fin. Data'!B21 -> -215.3 | D64: 247.3 | E64: 18.4 | F64: =F86*212 -> 41.6368 | G64: =G86*5565 -> 423.10695
B65: Net Income | C65: ='Fin. Data'!B23 -> 800.5 | D65: 714.2 | E65: 538.8 | F65: =F86*1022 -> 200.7208 | G65: =G86*4332 -> 329.36196
B66: R&D
B67: BS
B68: Cash & Eq. | C68: ='Fin. Data'!B39 -> 188.3 | D68: 1022.4 | E68: 536.4 | F68: =F86*1397 -> 274.3708 | G68: =G86*26398 -> 2007.0399
B69: Acc. Receivables | C69: ='Fin. Data'!B40 -> 1268.4 | D69: 658.7 | E69: 253 | F69: =F86*356 -> 69.9184 | G69: =G86*5111 -> 388.58933
B70: Inventory | C70: ='Fin. Data'!B41 -> 769 | D70: 776.9 | E70: 1592.7 | F70: =F86*3905 -> 766.942 | G70: =G86*9207 -> 700.00821
B71: Current Assets | C71: =Inputs!B27 -> 2447.7 | D71: 2153.3 | E71: 3043 | F71: =F86*7225 -> 1418.99 | G71: =G86*16773 -> 1275.2512
B72: Fixed Assets | C72: ='Fin. Data'!B42 -> 687.5 | D72: 6528.9 | E72: 5003 | F72: =F86*8818 -> 1731.8552 | G72: =G86*486 -> 36.95058
B73: Total Assets | C73: ='Fin. Data'!B44 -> 4724.3 | D73: 8682.2 | E73: 8046.2 | F73: =F86*16043 -> 3150.8452 | G73: =G86*32549 -> 2474.7005
B74: Acc. Payable | C74: =Inputs!B43 -> 991.8 | D74: 2107.9 | E74: -1446.1 | F74: =F86*75 -> 14.73 | G74: =G86*21027 -> 1598.6828
B75: Current Liabilities | C75: =Inputs!B42 -> 1245.7 | D75: 2516.2 | E75: 1996.5 | F75: =F86*7952 -> 1561.7728 | G75: =G86*67927 -> 5164.4898
B76: Total Debt | C76: ='Fin. Data'!B58 -> 1916.7 | D76: 11.7 | E76: 1131.22 | F76: =F86*266 -> 52.2424 | G76: =G86*51951 -> 3949.8345
B77: Total Equity | C77: ='Fin. Data'!B64 -> 1385 | D77: 2830.1 | E77: 2868.4 | F77: =F86*4288 -> 842.1632 | G77: =G86*47601 -> 3619.104
B78: Revenue from geographic segmentation
B79: Total revenue from UK | C79: =Segments!D5 -> 4600.6 | D79: 12069.5 | E79: 331.8 | F79: =F86*2532 -> 497.2848 | G79: =G86*79049 -> 6010.0955
C81: Currency Exchange Values
B83: Company | C83: =C8 -> #VALUE! | D83: =D8 -> #VALUE! | E83: =E8 -> #VALUE! | F83: =F8 -> #VALUE! | G83: =G8 -> #VALUE!
B84: Currency Reported | C84: £ (GBP) | D84: £ (GBP) | E84: ¥ (CNY) | F84: zł (PLN) | G84: kr (SEK)
B85: Report Date | C85: - | D85: - | E85: dd/04/yyyy | F85: 31/01/yyyy | G85: 30/11/yyyy
B86: 2024 Report date Exchange to € | C86: - | D86: - | E86: 0.1109 | F86: 0.1964 | G86: 0.07603
B87: 2023 Report date Exchange to € | C87: - | D87: - | E87: 0.1169 | F87: 0.1865 | G87: 0.07899
B88: 2021 Report date Exchange to € | C88: - | D88: - | E88: 0.1112 | F88: 0.1959 | G88: 0.08826

Sheet Acuerdo
A1: Invertir
A2: NO invertir
A3: Mantener sin elevar posición
A4: Mantener (y seguir comprando)
A5: Liquidar
A6: PENDIENTE

Sheet ESG
B1: Company GICS Sector: | T1: Yes
B2: Consumer Discretionary | C2: <- Select Industry | T2: No
B3: ESG Analysis | K3: Relative ESG Analysis | T3: 2019 | U3: 2020 | V3: 2021 | W3: 2022 | X3: 2023 | Y3: 2019 | Z3: 2020 | AA3: 2021 | AB3: 2022 | AC3: 2023
B4: Parameters | C4: Impact | D4: Do they report? | E4: Ranking | F4: Mitigation Plan | G4: Traffic Lights | H4: Improvement over time? | I4: Targets / Goals? | J4: Comments | K4: Parameters | L4: =Peers!C8 -> #VALUE! | M4: =Peers!D8 -> #VALUE! | N4: =Peers!E8 -> #VALUE! | O4: =Peers!F8 -> #VALUE! | P4: =Peers!G8 -> #VALUE! | Q4: =Peers!H8 -> 0 | R4: AVERAGE | T4: 46.911 | U4: 45.739 | V4: 36.914 | W4: 42.616 | X4: 43.165 | Y4: 340.088 | Z4: 356.383 | AA4: 290.963 | AB4: 430.423 | AC4: 295.837
B5: Environmental | K5: Ratios
A6: 1 | B6: CO2 Direct Emissions | C6: =VLOOKUP($B$2,'Sector Impact'!$K$4:$AA$16,A6+1,FALSE) -> Low | K6: CO2 Emissions/$M Sales | L6: =L12/L$11 -> 7.4422414 | M6: =M12/M$11 -> 15.285326 | N6: =N12/N$11 -> 0.60634921 | O6: =O12/O$11 -> 3.7265096 | P6: =P12/P$11 -> 0.7274911 | Q6: =Q12/Q$11 -> 0.69087204 | R6: =IFERROR(AVERAGE(L6:Q6),"") -> 4.7464649
A7: 2 | B7: Total Water Consumption | C7: =VLOOKUP($B$2,'Sector Impact'!$K$4:$AA$16,A7+1,FALSE) -> Low | K7: Water Consumption/$M Sales | L7: =L13/L$11 -> 51.005172 | M7: =M13/M$11 -> #VALUE! | N7: =N13/N$11 -> #VALUE! | O7: =O13/O$11 -> #VALUE! | P7: =P13/P$11 -> #VALUE! | Q7: =Q13/Q$11 -> 44.57727 | R7: =IFERROR(AVERAGE(L7:Q7),"")
A8: 3 | B8: Total Energy Consumption | C8: =VLOOKUP($B$2,'Sector Impact'!$K$4:$AA$16,A8+1,FALSE) -> Medium | D8: Yes | E8: Medium | F8: Yes | J8: It's mentioned investment in measures, like LED light for the retail stores and the instalment of solar panels | K8: Energy Consumption/$M Sales | L8: =L14/L$11 -> 248.32345 | M8: =M14/M$11 -> 359.8784 | N8: =N14/N$11 -> 89.395397 | O8: =O14/O$11 -> 111.02762 | P8: =P14/P$11 -> 193.06206 | Q8: =Q14/Q$11 -> 58.540638 | R8: =IFERROR(AVERAGE(L8:Q8),"") -> 176.70459
A9: 4 | B9: Waste Management | C9: =VLOOKUP($B$2,'Sector Impact'!$K$4:$AA$16,A9+1,FALSE) -> Medium | D9: Yes | E9: Medium High | F9: Yes | J9: Usage of textile leftovers in Bangladesh | K9: Waste Production/$M Sales | L9: =L15/L$11 -> 5.8643103 | M9: =M15/M$11 -> 4.6875 | N9: =N15/N$11 -> 0.41880952 | O9: =O15/O$11 -> #VALUE! | P9: =P15/P$11 -> #VALUE! | Q9: =Q15/Q$11 -> 0.87736767 | R9: =IFERROR(AVERAGE(L9:Q9),"")
A10: 5 | B10: Land Degradation/Deforestation/Biodiversity loss/Animal sufering/… | C10: =VLOOKUP($B$2,'Sector Impact'!$K$4:$AA$16,A10+1,FALSE) -> Low | K10: Inputs
B11: Social | K11: Net Sales ($M) | L11: 5.8 | M11: 14.72 | N11: 12.6 | O11: 3.693 | P11: 22.48 | Q11: 21.593
A12: 6 | B12: Employee Turnover % | C12: =VLOOKUP($B$2,'Sector Impact'!$K$4:$AA$16,A12+1,FALSE) -> Medium | D12: No | E12: Medium | F12: Yes | J12: The employee turnover isn't reported, it is only mentioned that the employee turnover is monitored | K12: CO2 Emissions Total (Tonnes) | L12: 43.165 | M12: 225 | N12: 7.64 | O12: 13.762 | P12: 16.354 | Q12: 14.918
A13: 7 | B13: Salaries & Compensation | C13: =VLOOKUP($B$2,'Sector Impact'!$K$4:$AA$16,A13+1,FALSE) -> Medium | D13: No | E13: Medium | F13: No | J13: From what I found, only 40% of people think are fairly paid | K13: Water Consumption Total (Cubic Meters) | L13: 295.83 | M13: - | N13: ="-" -> - | O13: ="-" -> - | P13: ="-" -> - | Q13: 962.557
A14: 8 | B14: Reputation | C14: =VLOOKUP($B$2,'Sector Impact'!$K$4:$AA$16,A14+1,FALSE) -> Low | K14: Energy Consumption Total (Gigajoules) | L14: 1440.276 | M14: 5297.41 | N14: 1126.382 | O14: 410.025 | P14: 4340.035 | Q14: 1264.068
A15: 9 | B15: Discrimination Events | C15: =VLOOKUP($B$2,'Sector Impact'!$K$4:$AA$16,A15+1,FALSE) -> Low | F15: Yes | K15: Waste Production Total (Tonnes) | L15: 34.013 | M15: 69 | N15: 5.277 | O15: ="-" -> - | P15: ="-" -> - | Q15: 18.945
A16: 10 | B16: Work Safety | C16: =VLOOKUP($B$2,'Sector Impact'!$K$4:$AA$16,A16+1,FALSE) -> Medium | D16: Yes | E16: Medium High | F16: No | J16: Mentioned first-aid training, and a great concern for the safety of the employees | K16: ESG Scores
A17: 11 | B17: Damage to consumer health | C17: =VLOOKUP($B$2,'Sector Impact'!$K$4:$AA$16,A17+1,FALSE) -> Medium | D17: No | E17: "Best in class" | F17: No | K17: Refinitiv | L17: 71 (79/70/69) | M17: 72 (61/83/64) | N17: 34 (63/39/14) | O17: 69(89/69/58) | P17: 78 (92/75/74) | Q17: 77 (96/86/57) | S17: 2019 | T17: 2020 | U17: 2021 | V17: 2022 | W17: 2023
A18: 12 | B18: PXP? | C18: =VLOOKUP($B$2,'Sector Impact'!$K$4:$AA$16,A18+1,FALSE) -> Medium | D18: Yes | E18: Medium High | F18: No | J18: "The defined contribution section is administered by a Legal & General Master Trust... Members pay 5% of their pensionable earnings which is matched by the Company." | K18: Sustainalytics | L18: 18.7 (low risk) | M18: ="-" -> - | N18: 12.6 (low risk) | O18: 19.0 (low risk) | P18: 20.2 (medium risk) | Q18: 10.0 (low risk) | S18: 1039.954 | T18: 977.085 | U18: 823.319 | V18: 1434.492 | W18: 1440.276
A19: 13 | B19: Supply chain | C19: =VLOOKUP($B$2,'Sector Impact'!$K$4:$AA$16,A19+1,FALSE) -> High | D19: Yes | E19: Medium High | F19: Yes | J19: "NEXT has a well-established supply chain that is supported by our overseas sourcing operation, NEXT Sourcing Limited (NSL)... Tier 1 supply chain comprises circa 1.2 million workers." "Our commitment: We focus on ethical trading, traceability and responsible sourcing to ensure our products are made by workers who are treated fairly and whose safety, human rights and wellbeing are respected." | K19: ISS | L19: C+ | M19: C+ | N19: C | O19: C- | P19: B- | Q19: B | Y19: 2019 | Z19: 2020 | AA19: 2021 | AB19: 2022 | AC19: 2023
A20: 14 | B20: Community involvement | C20: =VLOOKUP($B$2,'Sector Impact'!$K$4:$AA$16,A20+1,FALSE) -> Low | K20: CDP | L20: B/C/B- | M20: B/F/F | N20: A-/C/B | O20: C/C | P20: A-/(C/D/C)/B | Q20: A/(A/A-)/A | Y20: 29.031 | Z20: 30.227 | AA20: 21.753 | AB20: 31.634 | AC20: 34.013
A21: 15 | B21: Public Sector | C21: =VLOOKUP($B$2,'Sector Impact'!$K$4:$AA$16,A21+1,FALSE) -> High | D21: Yes | E21: "Best in class" | F21: No
A22: 16 | B22: Litigation | C22: =VLOOKUP($B$2,'Sector Impact'!$K$4:$AA$16,A22+1,FALSE) -> Low | D22: Yes
B23: Corporate Governance | K23: PARAMETERS
A24: 17 | B24: Diversity (Gender, Age, Industry, Region) | E24: Medium | F24: Yes | J24: At the end of 2023, the board was composed of 4 women, and sevem men, all but one of its member is White British or other White (the other member is Asian/Asian British) | K24: IMPACT | L24: RANKING | M24: MITIGATION PLAN | O24: TRAFFIC
A25: 18 | B25: % Independence | E25: Medium High | F25: No | J25: Only one of the board members is not independent. | K25: Low | L25: "Best in class" | M25: Is there evidence of a plan/program ?
A26: 19 | B26: average time as independent directors | E26: Medium | F26: No | J26: The average time as director is 8,27 years, this is not because of a usual 8 years rotation, but because there are some directors that are in the position for a long time and others that are in the positions just for a couple of years. | K26: Medium | L26: Medium High
A27: 20 | B27: Recent departures of directors / C-level executives? | E27: "Best in class" | F27: No | J27: Amanda James was the only C-Level to leave, but because she is retiring. | K27: High | L27: Medium
A28: 21 | B28: CEO/Chairman duality | E28: "Best in class" | F28: No | K28: Very high | L28: "Villain"
A29: 22 | B29: Transparency (ESG, segments, acquisitions, other) | E29: "Best in class" | F29: No
A30: 23 | B30: Time taken to report after the end of the quarter / year | E30: "Best in class" | F30: No | J30: Realeased their 2023 report in January 2024
A31: 24 | B31: Additional participation of the CEO in other boards or excessive participation of Ch. | E31: Medium | F31: No | J31: The CEO only operates in the company, but the chairman is also Chairma of Grafton Group plc until 2 May 2024 and a Non-Executive Director of BrownForman Corporation (US firm)
A32: 25 | B32: Audit / Consulting | D32: Yes | E32: Medium High | F32: No | J32: "During the year FIT was paid circa £29k and Deloitte was paid circa £5k for the services described above, charged at their standard hourly rates." Their audit is made by an independent comitee.
A33: 26 | B33: ESG-compensation related | D33: No | E33: "Villain" | F33: No | J33: There is no ESG related compensation
A34: 27 | B34: Management compensation schemes | D34: Yes | E34: "Best in class" | F34: No | J34: In case of good performance, the board may approve compensation.

Sheet DCF
A1: VALUATION MODEL
G3: Short Term | K3: Long Term
A4: Section | B4: Line # | C4: ITEM | D4: 2021 (Real) | E4: 2022 (Real) | F4: 2023 (Real) | G4: 2024 | H4: =G4+1 -> 2025 | I4: =H4+1 -> 2026 | J4: =I4+1 -> 2027 | K4: =J4+1 -> 2028 | L4: =K4+1 -> 2029 | M4: =L4+1 -> 2030 | N4: =M4+1 -> 2031 | O4: =N4+1 -> 2032 | ... AF4: =AE4+1 -> 2049
A5: INCOME STATEMENT | B5: 1 | C5: Growth | D5: ='Fin. Data'!D6 -> 0.30882187 | E5: =+E6/D6-1 -> 0.088220671 | F5: =+F6/E6-1 -> 0.090782678 | G5: =Assumptions!D67 -> 0.065336915 | H5: =Assumptions!E67 -> 0.084694022 | I5: =Assumptions!F67 -> 0.05316128 | J5: =Assumptions!G67 -> 0.03756694 | K5: =Assumptions!H67 -> 0.028079378 | L5: =Assumptions!I67 -> 0.022427318 | M5: =Assumptions!J67 -> 0.022482329 | N5: =Assumptions!K67 -> 0.022537342 | ... AF5: =Assumptions!AC67 -> 0.015526513
B6: 2 | C6: Revenues/Sales | D6: =Inputs!D6 -> 4625.9 | E6: =Inputs!C6 -> 5034 | F6: =Inputs!B6 -> 5491 | G6: =Assumptions!D68 -> 5849.765 | H6: =Assumptions!E68 -> 6345.2051 | I6: =Assumptions!F68 -> 6682.5244 | J6: =Assumptions!G68 -> 6933.5663 | K6: =Assumptions!H68 -> 7128.2566 | L6: =Assumptions!I68 -> 7288.1243 | M6: =Assumptions!J68 -> 7451.9783 | N6: =Assumptions!K68 -> 7619.9261 | ... AF6: =Assumptions!AC68 -> 10318.748
B7: 3 | C7: EBIT/Operating Margin | D7: =D8/D6 -> 0.19518364 | E7: =E8/E6 -> 0.19026619 | F7: =F8/F6 -> 0.17767256 | G7: =Assumptions!D50 -> 0.18 | H7: =Assumptions!E50 -> 0.18 | I7: =Assumptions!F50 -> 0.18 | J7: =Assumptions!G50 -> 0.18 | K7: =Assumptions!H50 -> 0.18 | L7: =Assumptions!I50 -> 0.18 | M7: =Assumptions!J50 -> 0.18 | N7: =Assumptions!K50 -> 0.18 | ... AF7: =Assumptions!AC50 -> 0.18
B8: 4 | C8: EBIT | D8: ='Fin. Data'!D11 -> 902.9 | E8: ='Fin. Data'!C11 -> 957.8 | F8: ='Fin. Data'!B11 -> 975.6 | G8: =G7*G6 -> 1052.9577 | H8: =H7*H6 -> 1142.1369 | I8: =I7*I6 -> 1202.8544 | J8: =J7*J6 -> 1248.0419 | K8: =K7*K6 -> 1283.0862 | L8: =L7*L6 -> 1311.8624 | M8: =M7*M6 -> 1341.3561 | N8: =N7*N6 -> 1371.5867 | ... AF8: =AF7*AF6 -> 1857.3746
B9: 5a | C9: (Dep) | D9: -217.5 | E9: -208.1 | F9: -212.6 | G9: =$D$53*DCF!F40 -> -206.2045 | H9: =$D$53*DCF!G40 -> -240.13314 | I9: =$D$53*DCF!H40 -> -276.93533 | J9: =$D$53*DCF!I40 -> -315.69397 | K9: =$E$53*DCF!J40 -> -343.63594 | L9: =$E$53*DCF!K40 -> -381.55827 | M9: =$E$53*DCF!L40 -> -420.33109 | N9: =$E$53*DCF!M40 -> -459.97561 | O9: =$E$53*DCF!N40 -> -500.51362 | P9: =$E$53*DCF!O40 -> -541.96747 | Q9: =$E$53*DCF!P40 -> -584.36015 | R9: =$E$53*DCF!Q40 -> -627.71524 | ... AF9: =$E$53*DCF!AE40 -> -1314.216 | AG9: =SUM(D9:AF9) -> -19304.1
B10: 5b | C10: (Amort) | D10: -3.2 | E10: -11.9 | F10: -36.2 | G10: =F38*$D$54 -> -40.78 | H10: =G38*$D$54 -> -42.819 | I10: =H38*$D$54 -> -44.95995 | J10: =I38*$D$54 -> -47.207948 | K10: =J38*$E$54 -> -39.654676 | L10: =K38*$E$54 -> -41.240863 | M10: =L38*$E$54 -> -42.890497 | N10: =M38*$E$54 -> -44.606117 | O10: =N38*$E$54 -> -46.390362 | P10: =O38*$E$54 -> -48.245977 | Q10: =P38*$E$54 -> -50.175816 | R10: =Q38*$E$54 -> -52.182848 | ... AF10: =AE38*$E$54 -> -90.363809
B11: 5c | C11: (Stock based compensation) | D11: =D20 -> 0 | E11: =E20 -> 0 | F11: =F20 -> 0 | G11: =G6*$D$55 -> 0 | H11: =H6*$D$55 -> 0 | I11: =I6*$D$55 -> 0 | J11: =J6*$D$55 -> 0 | K11: =K6*$D$55 -> 0 | L11: =L6*$D$55 -> 0 | M11: =M6*$D$55 -> 0 | N11: =N6*$D$55 -> 0 | ... AF11: =AF6*$D$55 -> 0
B12: 6 | C12: EBITDA | D12: =D8-D9-D10 -> 1123.6 | E12: =E8-E9-E10 -> 1177.8 | F12: =F8-F9-F10 -> 1224.4 | G12: =G8-G9-G10 -> 1299.9422 | H12: =H8-H9-H10 -> 1425.0891 | I12: =I8-I9-I10 -> 1524.7497 | J12: =J8-J9-J10 -> 1610.9439 | K12: =K8-K9-K10 -> 1666.3768 | ... AF12: =AF8-AF9-AF10 -> 3261.9544
B13: 7 | C13: (Net financing cost) | D13: ='Fin. Data'!D14 -> -82.3 | E13: ='Fin. Data'!C14 -> -72.2 | F13: ='Fin. Data'!B14 -> -80.7 | G13: =F43*$D$58-F44*$D$57 -> -73.8208 | H13: =G43*$D$58-G44*$D$57 -> -71.577377 | I13: =H43*$D$58-H44*$D$57 -> -71.779398 | J13: =I43*$D$58-I44*$D$57 -> -73.551811 | K13: =J43*$E$58-J44*$E$57 -> -73.749169 | L13: =K43*$E$58-K44*$E$57 -> -83.442493 | M13: =L43*$E$58-L44*$E$57 -> -84.196456 | N13: =M43*$E$58-M44*$E$57 -> -86.324667 | O13: =N43*$E$58-N44*$E$57 -> -92.996445 | P13: =O43*$E$58-O44*$E$57 -> -93.042524 | Q13: =P43*$E$58-P44*$E$57 -> -84.823074 | R13: =Q43*$E$58-Q44*$E$57 -> -84.279417 | ... AF13: =AE43*$E$58-AE44*$E$57 -> 29.705304
B14: 8 | C14: Other income/(cost) | D14: ='Fin. Data'!D15 -> 2.5 | E14: ='Fin. Data'!C15 -> -16.3 | F14: ='Fin. Data'!B15 -> 120.9 | G14: =AVERAGE(D14:F14)*(1+G5) -> 38.032528 | H14: =AVERAGE(E14:G14)*(1+H5) -> 51.570883 | I14: =AVERAGE(F14:H14)*(1+I5) -> 73.898014 | J14: =AVERAGE(G14:I14)*(1+J5) -> 56.547891 | K14: =AVERAGE(H14:J14)*(1+K5) -> 62.375902 | L14: =AVERAGE(I14:K14)*(1+L5) -> 65.715428 | M14: =AVERAGE(J14:L14)*(1+M5) -> 62.930114 | N14: =AVERAGE(K14:M14)*(1+N5) -> 65.108853 | ... AF14: =AVERAGE(AC14:AE14)*(1+AF5) -> 75.443308
B15: 9 | C15: Earnings before taxes | D15: =D8+D13+D14 -> 823.1 | E15: =E8+E13+E14 -> 869.3 | F15: =F8+F13+F14 -> 1015.8 | G15: =G8+G13+G14 -> 1017.1694 | H15: =H8+H13+H14 -> 1122.1304 | I15: =I8+I13+I14 -> 1204.973 | J15: =J8+J13+J14 -> 1231.038 | K15: =K8+K13+K14 -> 1271.7129 | ... AF15: =AF8+AF13+AF14 -> 1962.5232
B16: 10 | C16: (Income tax) | D16: ='Fin. Data'!D21 -> -145.6 | E16: ='Fin. Data'!C21 -> -158.6 | F16: ='Fin. Data'!B21 -> -215.3 | G16: =-$D$56*G15 -> -305.15083 | H16: =-$D$56*H15 -> -336.63913 | I16: =-$D$56*I15 -> -361.4919 | J16: =-$D$56*J15 -> -369.31141 | K16: =-$E$56*K15 -> -381.51388 | L16: =-$E$56*L15 -> -388.24059 | M16: =-$E$56*M15 -> -396.02692 | N16: =-$E$56*N15 -> -405.11126 | O16: =-$E$56*O15 -> -412.68646 | P16: =-$E$56*P15 -> -422.23667 | Q16: =-$E$56*Q15 -> -434.80269 | R16: =-$E$56*R15 -> -445.20209 | ... AF16: =-$E$56*AF15 -> -588.75696
B17: 11 | C17: Net income | D17: ='Fin. Data'!D23 -> 677.5 | E17: ='Fin. Data'!C23 -> 710.7 | F17: ='Fin. Data'!B23 -> 800.5 | G17: =G16+G15 -> 712.0186 | H17: =H16+H15 -> 785.4913 | I17: =I16+I15 -> 843.4811 | J17: =J16+J15 -> 861.72662 | K17: =K16+K15 -> 890.19904 | L17: =L16+L15 -> 905.89471 | M17: =M16+M15 -> 924.06282 | N17: =N16+N15 -> 945.25961 | ... AF17: =AF16+AF15 -> 1373.7662
A19: CASH FLOW STATEMENT | B19: 12 | C19: Operating cash flows before WK | D19: =Inputs!D59-D20-D21 -> 671.6 | E19: =Inputs!C59-E20-E21 -> 608.3 | F19: =Inputs!B59-DCF!F20-DCF!F21 -> 1069.2 | G19: =G17-G10-G9-G11 -> 959.0031 | H19: =H17-H10-H9-H11 -> 1068.4434 | I19: =I17-I10-I9-I11 -> 1165.3764 | J19: =J17-J10-J9-J11 -> 1224.6285 | K19: =K17-K10-K9-K11 -> 1273.4897 | L19: =L17-L10-L9-L11 -> 1328.6938 | M19: =M17-M10-M9-M11 -> 1387.2844 | N19: =N17-N10-N9-N11 -> 1449.8413 | ... AF19: =AF17-AF10-AF9-AF11 -> 2778.3461
B20: 13 | C20: (Stock-based compensation) | D20: 0 | E20: 0 | F20: 0 | G20: =G11 -> 0 | H20: =H11 -> 0 | I20: =I11 -> 0 | J20: =J11 -> 0 | K20: =K11 -> 0 | L20: =L11 -> 0 | M20: =M11 -> 0 | N20: =N11 -> 0 | ... AF20: =AF11 -> 0
B21: 14 | C21: (Working Capital Flows) | D21: =Inputs!D62 -> 299.8 | E21: =Inputs!C62 -> 190.5 | F21: =Inputs!B62 -> 51.1 | G21: =$D$60*(G6-F6) -> 71.753 | H21: =$D$60*(H6-G6) -> 99.088025 | I21: =$D$60*(I6-H6) -> 67.463846 | J21: =$D$60*(J6-I6) -> 50.208398 | K21: =$E$60*(K6-J6) -> 38.938047 | L21: =$E$60*(L6-K6) -> 31.973536 | M21: =$E$60*(M6-L6) -> 32.770802 | N21: =$E$60*(N6-M6) -> 33.589557 | O21: =$E$60*(O6-N6) -> 34.430409 | P21: =$E$60*(P6-O6) -> 35.293984 | Q21: =$E$60*(Q6-P6) -> 36.180926 | R21: =$E$60*(R6-Q6) -> 37.091899 | ... AF21: =$E$60*(AF6-AE6) -> 31.552927
B22: 15 | C22: -Total Operating Cash Flow | D22: =D19+D20+D21 -> 971.4 | E22: =E19+E20+E21 -> 798.8 | F22: =F19+F20+F21 -> 1120.3 | G22: =G19+G20+G21 -> 1030.7561 | H22: =H19+H20+H21 -> 1167.5315 | I22: =I19+I20+I21 -> 1232.8402 | J22: =J19+J20+J21 -> 1274.8369 | K22: =K19+K20+K21 -> 1312.4277 | ... AF22: =AF19+AF20+AF21 -> 2809.899
B23: 16 | C23: (CAPEX) | D23: ='Fin. Data'!D32 -> -224.7 | E23: ='Fin. Data'!C32 -> -163.4 | F23: ='Fin. Data'!B32 -> -125.7 | G23: =G6*$D$62 -> -233.9906 | H23: =H6*$D$62 -> -253.80821 | I23: =I6*$D$62 -> -267.30097 | J23: =J6*$D$62 -> -277.34265 | K23: =K6*$E$62 -> -270.87375 | L23: =L6*$E$62 -> -276.94872 | M23: =M6*$E$62 -> -283.17517 | N23: =N6*$E$62 -> -289.55719 | O23: =O6*$E$62 -> -296.09897 | P23: =P6*$E$62 -> -302.80482 | Q23: =Q6*$E$62 -> -309.6792 | R23: =R6*$E$62 -> -316.72666 | ... AF23: =AF6*$E$62 -> -392.11241 | AG23: =SUM(D23:AF23) -> -8871.0697
B24: 17 | C24: Adq | D24: =Inputs!D66 -> -34.3 | E24: ='Fin. Data'!C33 -> -95.4 | F24: ='Fin. Data'!B33 -> -153.2 | G24: =G6*$D$63 -> -116.9953 | H24: =H6*$D$63 -> -126.9041 | I24: =I6*$D$63 -> -133.65049 | J24: =J6*$D$63 -> -138.67133 | K24: =K6*$E$63 -> -71.282566 | L24: =L6*$E$63 -> -72.881243 | M24: =M6*$E$63 -> -74.519783 | N24: =N6*$E$63 -> -76.199261 | O24: =O6*$E$63 -> -77.920781 | P24: =P6*$E$63 -> -79.68548 | Q24: =Q6*$E$63 -> -81.494526 | R24: =R6*$E$63 -> -83.349121 | ... AF24: =AF6*$E$63 -> -103.18748 | AH24: =AG9-AG23 -> -10433.03
B25: 18 | C25: (Other investing flows) | D25: =Inputs!D67 -> -33.5 | E25: =Inputs!C67 -> -12.6 | F25: =Inputs!B67 -> -55.5 | G25: =(1+G5)*AVERAGE(D25:F25) -> -36.07941 | H25: =(1+H5)*AVERAGE(E25:G25) -> -37.667594 | I25: =(1+I5)*AVERAGE(F25:H25) -> -45.372647 | J25: =(1+J5)*AVERAGE(G25:I25) -> -41.198204 | K25: =(1+K5)*AVERAGE(H25:J25) -> -42.575661 | L25: =(1+L5)*AVERAGE(I25:K25) -> -44.014307 | M25: =(1+M5)*AVERAGE(J25:L25) -> -43.553716 | N25: =(1+N5)*AVERAGE(K25:M25) -> -44.358926 | ... AF25: =(1+AF5)*AVERAGE(AC25:AE25) -> -51.516233
B26: 19 | C26: -Total Investing Flows | D26: =D23+D24+D25 -> -292.5 | E26: =E23+E24+E25 -> -271.4 | F26: =F23+F24+F25 -> -334.4 | G26: =G23+G24+G25 -> -387.06531 | H26: =H23+H24+H25 -> -418.3799 | I26: =I23+I24+I25 -> -446.32411 | J26: =J23+J24+J25 -> -457.21218 | K26: =K23+K24+K25 -> -384.73198 | ... AF26: =AF23+AF24+AF25 -> -546.81612
B27: 20 | C27: (Flows related to leases) | D27: =Inputs!D71+Inputs!D72 -> -172.3 | E27: =Inputs!C71+Inputs!C72 -> -157 | F27: =Inputs!B71+Inputs!B72 -> -156.1 | G27: =G6*$D$66 -> -146.24413 | H27: =H6*$D$66 -> -158.63013 | I27: =I6*$D$66 -> -167.06311 | J27: =J6*$D$66 -> -173.33916 | K27: =$E$66*K6 -> -142.56513 | L27: =$E$66*L6 -> -145.76249 | M27: =$E$66*M6 -> -149.03957 | N27: =$E$66*N6 -> -152.39852 | O27: =$E$66*O6 -> -155.84156 | P27: =$E$66*P6 -> -159.37096 | Q27: =$E$66*Q6 -> -162.98905 | R27: =$E$66*R6 -> -166.69824 | ... AF27: =$E$66*AF6 -> -206.37495
B28: 21 | C28: Flows related to debt | D28: =+SUM(Inputs!D69:D70) -> -325 | E28: =+SUM(Inputs!C69:C70) -> 0 | F28: =+SUM(Inputs!B69:B70) -> -2.5 | G28: =G44-F44 -> -91.7 | H28: =H44-G44 -> 0 | I28: =I44-H44 -> 50 | J28: =J44-I44 -> 0 | K28: =K44-J44 -> 275 | L28: =L44-K44 -> 0 | M28: =M44-L44 -> 50 | N28: =N44-M44 -> 200 | ... AF28: =AF44-AE44 -> 0
B29: 22 | C29: (Repurchases)/Issuance of stock | D29: ='Fin. Data'!D28 -> -8.7 | E29: ='Fin. Data'!C28 -> -228.5 | F29: ='Fin. Data'!B28 -> -177.3 | G29: =-G6*$D$65 -> -233.9906 | H29: =-H6*$D$65 -> -253.80821 | I29: =-I6*$D$65 -> -267.30097 | J29: =-J6*$D$65 -> -277.34265 | K29: =-1*K6*$E$65 -> -427.69539 | L29: =-1*L6*$E$65 -> -437.28746 | M29: =-1*M6*$E$65 -> -447.1187 | N29: =-1*N6*$E$65 -> -457.19556 | O29: =-1*O6*$E$65 -> -467.52469 | P29: =-1*P6*$E$65 -> -478.11288 | Q29: =-1*Q6*$E$65 -> -488.96716 | R29: =-1*R6*$E$65 -> -500.09473 | ... AF29: =-1*AF6*$E$65 -> -619.12486
B30: 23 | C30: (Dividends) | D30: ='Fin. Data'!D27 -> -344.5 | E30: ='Fin. Data'!C27 -> -237.4 | F30: ='Fin. Data'!B27 -> -248.3 | G30: =-$D$64*G6 -> -233.9906 | H30: =-$D$64*H6 -> -253.80821 | I30: =-$D$64*I6 -> -267.30097 | J30: =-$D$64*J6 -> -277.34265 | K30: =-$E$64*K6 -> -356.41283 | L30: =-$E$64*L6 -> -364.40621 | M30: =-$E$64*M6 -> -372.59891 | N30: =-$E$64*N6 -> -380.9963 | O30: =-$E$64*O6 -> -389.6039 | P30: =-$E$64*P6 -> -398.4274 | Q30: =-$E$64*Q6 -> -407.47263 | R30: =-$E$64*R6 -> -416.74561 | ... AF30: =-$E$64*AF6 -> -515.93738
B31: 24 | C31: Other financing flows | D31: =Inputs!D75 -> -142.9 | E31: =Inputs!C75 -> -104.2 | F31: =Inputs!B75 -> -79.1 | G31: =(1+G5)*AVERAGE(D31:F31) -> -115.83763 | H31: =(1+H5)*AVERAGE(E31:G31) -> -108.1576 | I31: =(1+I5)*AVERAGE(F31:H31) -> -106.40272 | J31: =(1+J5)*AVERAGE(G31:I31) -> -114.27 | K31: =(1+K5)*AVERAGE(H31:J31) -> -112.68789 | L31: =(1+L5)*AVERAGE(I31:K31) -> -113.61233 | M31: =(1+M5)*AVERAGE(J31:L31) -> -116.07568 | N31: =(1+N5)*AVERAGE(K31:M31) -> -116.69738 | ... AF31: =(1+AF5)*AVERAGE(AC31:AE31) -> -135.68308
B32: 25 | C32: -Total Financing flows | D32: =D27+D28+D29+D30+D31 -> -993.4 | E32: =E27+E28+E29+E30+E31 -> -727.1 | F32: =F27+F28+F29+F30+F31 -> -663.3 | G32: =G27+G28+G29+G30+G31 -> -821.76296 | H32: =H27+H28+H29+H30+H31 -> -774.40414 | I32: =I27+I28+I29+I30+I31 -> -758.06778 | J32: =J27+J28+J29+J30+J31 -> -842.29447 | K32: =K27+K28+K29+K30+K31 -> -764.36125 | ... AF32: =AF27+AF28+AF29+AF30+AF31 -> -1477.1203
A34: SUMMARY | B34: 26 | C34: Cash before shareholder returns | D34: =D22+D26+D27+D28+D31 -> 38.7 | E34: =E22+E26+E27+E28+E31 -> 266.2 | F34: =F22+F26+F27+F28+F31 -> 548.2 | G34: =G22+G26+G27+G28+G31 -> 289.90903 | H34: =H22+H26+H27+H28+H31 -> 482.36383 | I34: =I22+I26+I27+I28+I31 -> 563.05028 | J34: =J22+J26+J27+J28+J31 -> 530.01559 | K34: =K22+K26+K27+K28+K31 -> 947.44271 | ... AF34: =AF22+AF26+AF27+AF28+AF31 -> 1921.0248
B35: 27 | C35: Returns to shareholders | D35: =-1*(D29+D30) -> 353.2 | E35: =-1*(E29+E30) -> 465.9 | F35: =-1*(F29+F30) -> 425.6 | G35: =-1*(G29+G30) -> 467.9812 | H35: =-1*(H29+H30) -> 507.61641 | I35: =-1*(I29+I30) -> 534.60195 | J35: =-1*(J29+J30) -> 554.68531 | K35: =-1*(K29+K30) -> 784.10822 | ... AF35: =-1*(AF29+AF30) -> 1135.0622
B36: 28 | C36: Excess cash acumulation | D36: =D34-D35 -> -314.5 | E36: =E34-E35 -> -199.7 | F36: =F34-F35 -> 122.6 | G36: =G34-G35 -> -178.07217 | H36: =H34-H35 -> -25.252579 | I36: =I34-I35 -> 28.448335 | J36: =J34-J35 -> -24.669721 | K36: =K34-K35 -> 163.33448 | ... AF36: =AF34-AF35 -> 785.96259
A38: BALANCE SHEET | B38: 29 | C38: Intangible assets | D38: 89.2 | E38: 159.2 | F38: 815.6 | G38: =+F38+(-G10) -> 856.38 | H38: =+G38+(-H10) -> 899.199 | I38: =+H38+(-I10) -> 944.15895 | J38: =+I38+(-J10) -> 991.3669 | K38: =+J38+(-K10) -> 1031.0216 | L38: =+K38+(-L10) -> 1072.2624 | M38: =+L38+(-M10) -> 1115.1529 | N38: =+M38+(-N10) -> 1159.7591 | ... AF38: =+AE38+(-AF10) -> 2349.459 | AG38: =SUM(G38:AF38) -> 39001.501
B39: 30 | C39: Accumulated amortization | D39: 9.9 | E39: =D39+E10 -> -2 | F39: =E39+F10 -> -38.2 | G39: =F39-G10 -> 2.58 | H39: =G39-H10 -> 45.399 | I39: =H39-I10 -> 90.35895 | J39: =I39-J10 -> 137.5669 | K39: =J39-K10 -> 177.22157 | L39: =K39-L10 -> 218.46244 | M39: =L39-M10 -> 261.35293 | N39: =M39-N10 -> 305.95905 | ... AF39: =AE39-AF10 -> 1495.659 | AG39: =SUM(G39:AF39) -> 16802.701
B40: 31 | C40: PPE+Right of use Assets | D40: 1240.2 | E40: 1306.8 | F40: 1422.1 | G40: =F40+(-G23) -> 1656.0906 | H40: =G40+(-H23) -> 1909.8988 | I40: =H40+(-I23) -> 2177.1998 | J40: =I40+(-J23) -> 2454.5424 | K40: =J40+(-K23) -> 2725.4162 | L40: =K40+(-L23) -> 3002.3649 | M40: =L40+(-M23) -> 3285.5401 | N40: =M40+(-N23) -> 3575.0973 | ... AF40: =AE40+(-AF23) -> 9779.3697 | AG40: =SUM(G40:AF40) -> 141429.22
B41: 32 | C41: Accumulated depreciation | D41: 1451.2 | E41: =D41+E9 -> 1243.1 | F41: =E41+F9 -> 1030.5 | G41: =F41-G9 -> 1236.7045 | H41: =G41-H9 -> 1476.8376 | I41: =H41-I9 -> 1753.773 | J41: =I41-J9 -> 2069.4669 | K41: =J41-K9 -> 2413.1029 | L41: =K41-L9 -> 2794.6611 | M41: =L41-M9 -> 3214.9922 | N41: =M41-N9 -> 3674.9678 | ... AF41: =AE41-AF9 -> 19696.4 | AG41: =SUM(G41:AF41) -> 213792.23
A43: CASH & DEBT & DISCOUNTING | B43: 33 | C43: Ending cash balance | D43: ='Fin. Data'!D39 -> 433 | E43: =E36+D43 -> 233.3 | F43: =F36+E43 -> 355.9 | G43: =G36+F43 -> 177.82783 | H43: =H36+G43 -> 152.57525 | I43: =I36+H43 -> 181.02359 | J43: =J36+I43 -> 156.35387 | K43: =K36+J43 -> 319.68835 | L43: =L36+K43 -> 225.44297 | ... AF43: =AF36+AE43 -> 4499.1256
B44: 34 | C44: Total Debt | D44: ='Fin. Data'!D58 -> 2061.5 | E44: ='Fin. Data'!C58 -> 1916 | F44: ='Fin. Data'!B58 -> 1916.7 | G44: =Assumptions!C287 -> 1825 | H44: =Assumptions!D287 -> 1825 | I44: =Assumptions!E287 -> 1875 | J44: =Assumptions!F287 -> 1875 | K44: =Assumptions!G287 -> 2150 | L44: =Assumptions!H287 -> 2150 | M44: =Assumptions!I287 -> 2200 | N44: =Assumptions!J287 -> 2400 | ... AF44: =Assumptions!AB287 -> 0
B45: 35 | C45: Discount factor | F45: =1/((1+$F$50)^G50) -> 1 | G45: =1/((1+$F$50)^G49) -> 0.92165899 | H45: =1/((1+$F$50)^H49) -> 0.84945529 | I45: =1/((1+$F$50)^I49) -> 0.7829081 | J45: =1/((1+$F$50)^J49) -> 0.72157428 | K45: =1/((1+$F$50)^K49) -> 0.66504542 | L45: =1/((1+$F$50)^L49) -> 0.61294509 | M45: =1/((1+$F$50)^M49) -> 0.56492635 | N45: =1/((1+$F$50)^N49) -> 0.52066945 | ... AF45: =1/((1+$F$50)^AF49) -> 0.1199021
B46: 36 | C46: DF + 0.1% | E46: +0.1% | F46: =1/((1+$F$50+0.001)^G50) -> 1 | G46: =1/((1+$F$50+0.001)^G49) -> 0.92081031 | H46: =1/((1+$F$50+0.001)^H49) -> 0.84789163 | I46: =1/((1+$F$50+0.001)^I49) -> 0.78074736 | J46: =1/((1+$F$50+0.001)^J49) -> 0.71892022 | K46: =1/((1+$F$50+0.001)^K49) -> 0.66198915 | L46: =1/((1+$F$50+0.001)^L49) -> 0.60956644 | M46: =1/((1+$F$50+0.001)^M49) -> 0.56129506 | N46: =1/((1+$F$50+0.001)^N49) -> 0.51684628 | ... AF46: =1/((1+$F$50+0.001)^AF49) -> 0.11706432
B47: 37 | C47: DF+0.5% | E47: +0.5% | F47: =1/((1+$F$50+0.005)^G50) -> 1 | G47: =1/((1+$F$50+0.005)^G49) -> 0.91743119 | H47: =1/((1+$F$50+0.005)^H49) -> 0.84167999 | I47: =1/((1+$F$50+0.005)^I49) -> 0.77218348 | J47: =1/((1+$F$50+0.005)^J49) -> 0.70842521 | K47: =1/((1+$F$50+0.005)^K49) -> 0.64993139 | L47: =1/((1+$F$50+0.005)^L49) -> 0.59626733 | M47: =1/((1+$F$50+0.005)^M49) -> 0.54703424 | N47: =1/((1+$F$50+0.005)^N49) -> 0.50186628 | ... AF47: =1/((1+$F$50+0.005)^AF49) -> 0.10639251
A49: Discount Rate | C49: Risk free rate | D49: Equity premium | E49: Firm premium | F49: Total | G49: 1 | H49: 2 | I49: 3 | J49: 4 | K49: 5 | L49: 6 | M49: 7 | N49: 8 | O49: 9 | P49: 10 | Q49: 11 | R49: 12 | S49: 13 | T49: 14 | U49: 15 | V49: 16 | W49: 17 | X49: 18 | Y49: 19 | Z49: 20 | AA49: 21 | AB49: 22 | AC49: 23 | AD49: 24 | AE49: 25 | AF49: 26
C50: 0.04 | D50: 0.04 | E50: 0.005 | F50: =C50+D50+E50 -> 0.085 | G50: 0
A52: Modelling factors | D52: Short Term | E52: Long Term | F52: Reference (line)
C53: Depreciation factor | D53: =Assumptions!R17 -> -0.145 | E53: =Assumptions!S17 -> -0.14 | F53: =Assumptions!U17 -> % PPE
C54: Amortization factor | D54: =Assumptions!R18 -> -0.05 | E54: =Assumptions!S18 -> -0.04 | F54: =Assumptions!U18 -> % IA
C55: Stock-based comp | D55: =Assumptions!R19 -> 0 | E55: =Assumptions!S19 -> 0 | F55: =Assumptions!U19 -> % Revenue
C56: Tax Rate | D56: =Assumptions!R20 -> 0.3 | E56: =Assumptions!S20 -> 0.3 | F56: =Assumptions!U20 -> % EBT
C57: Interest Rate on debt | D57: =Assumptions!R21 -> 0.04 | E57: =Assumptions!S21 -> 0.04 | F57: =Assumptions!U21 -> % Debt
C58: Interest Rate on cash | D58: =Assumptions!R22 -> 0.008 | E58: =Assumptions!S22 -> 0.008 | F58: =Assumptions!U22 -> % Cash
C59: PPE+ROA | D59: =Assumptions!R23 -> - - | E59: =Assumptions!S23 -> - - | F59: =Assumptions!U23 -> Growing with CAPEX
C60: Working capital flows | D60: =Assumptions!R24 -> 0.2 | E60: =Assumptions!S24 -> 0.2 | F60: =Assumptions!U24 -> % Change in Revenues
C61: Intangible Assets | D61: =Assumptions!R25 -> - - | E61: =Assumptions!S25 -> - - | F61: =Assumptions!U25 -> Growing with Amortization
C62: Capex | D62: =Assumptions!R26 -> -0.04 | E62: =Assumptions!S26 -> -0.038 | F62: =Assumptions!U26 -> % Revenue
C63: Acquisition factor | D63: =Assumptions!R27 -> -0.02 | E63: =Assumptions!S27 -> -0.01 | F63: =Assumptions!U27 -> % Revenue
C64: Dividends | D64: =Assumptions!R28 -> 0.04 | E64: =Assumptions!S28 -> 0.05 | F64: =Assumptions!U28 -> % Net Income
... C67: Total Debt | D67: =Assumptions!R31 -> 0 | E67: =Assumptions!S31 -> 0 | F67: =Assumptions!U31 -> x EBITDA
A69: Valuation | D69: £ millions
C70: Value of flows | D70: =SUMPRODUCT(G35:AF35,G45:AF45)+((AF43-AF44)*AF45) -> 8679.0891 | E70: =D70/D72 -> 0.72358754
C71: Value of perpetuity | D71: =(AF34/(F50-AF5))*AF45 -> 3315.4363 | E71: =D71/D72 -> 0.27641246
C72: Total Value | D72: =D70+D71 -> 11994.525
C73: Actual share price | D73: =OP!C19 -> 13435
C74: Total value vs Mkt Cap | D74: =D75/D73-1 -> -0.27082103
C75: Estimated NPV per share | D75: =D72*100000000/OP!C20 -> 9796.5195
A77: Sensibility | C77: Sensitivity +0.1% | D77: =(SUMPRODUCT(G35:AF35,G45:AF45)+((AF43-AF44)*AF45)+(AF34/(F50+0.001-AF5))*AF45)*1000000/OP!C20 -> 97.580954 | E77: =D77/D75-1 -> -0.99003922
C78: Sensitivity +0.5% | D78: =(SUMPRODUCT(G35:AF35,G45:AF45)+((AF43-AF44)*AF45)+(AF34/(F50+0.005-AF5))*AF45)*1000000/OP!C20 -> 96.147179 | E78: =D78/D75-1 -> -0.99018558
A80: Notes | C80: Price where it'd be a "BUY" | D80: =D75/1.15 -> 8518.7126

Sheet Assumptions
B2: Assumptions
B4: Prospects:
B6: Links:
D8: 2023 | E8: =D8-1 -> 2022 | F8: =E8-1 -> 2021 | G8: =F8-1 -> 2020 | H8: =G8-1 -> 2019 | I8: =H8-1 -> 2018 | J8: =I8-1 -> 2017 | K8: =J8-1 -> 2016 | L8: =K8-1 -> 2015 | N8: 9Y Average | O8: 5Y Average | P8: 3Y Average | R8: Short Term Forecast | S8: Long Term Forecast
B9: Revenue growth | D9: =(Inputs!B6-Inputs!C6)/Inputs!C6 -> 0.090782678 | E9: =(Inputs!C6-Inputs!D6)/Inputs!D6 -> 0.088220671 | F9: =(Inputs!D6-Inputs!E6)/Inputs!E6 -> 0.30882187 | G9: =(Inputs!E6-Inputs!F6)/Inputs!F6 -> -0.17153439 | H9: =(Inputs!F6-Inputs!G6)/Inputs!G6 -> 0.023707827 | I9: =(Inputs!G6-Inputs!H6)/Inputs!H6 -> 0.027592159 | J9: =(Inputs!H6-Inputs!I6)/Inputs!I6 -> -0.01020184 | K9: =(Inputs!I6-Inputs!J6)/Inputs!J6 -> -0.019057196 | L9: =(Inputs!J6-Inputs!K6)/Inputs!K6 -> 0.044277214 | N9: =AVERAGE(D9:L9) -> 0.04251211 | O9: =AVERAGE(D9:H9) -> 0.067999731 | P9: =AVERAGE(D9:F9) -> 0.1626084 | R9: 0.0574 | S9: 0.03
B10: Operating Margin | D10: =Inputs!B8/Inputs!B6 -> 0.17767256 | E10: =Inputs!C8/Inputs!C6 -> 0.19026619 | F10: =Inputs!D8/Inputs!D6 -> 0.19518364 | G10: =Inputs!E8/Inputs!E6 -> 0.12613173 | H10: =Inputs!F8/Inputs!F6 -> 0.20050631 | I10: =Inputs!G8/Inputs!G6 -> 0.20149254 | J10: =Inputs!H8/Inputs!H6 -> 0.18764641 | K10: =Inputs!I8/Inputs!I6 -> 0.20198667 | L10: =Inputs!J8/Inputs!J6 -> 0.2089588 | N10: =AVERAGE(D10:L10) -> 0.18776054 | O10: =AVERAGE(D10:H10) -> 0.17795208 | P10: =AVERAGE(D10:F10) -> 0.18770746
B13: Modelling Factors
D15: Last 9 years | Z15: Values in M. | AA15: 2023 | AB15: =AA15-1 -> 2022 | AC15: =AB15-1 -> 2021 | AD15: =AC15-1 -> 2020 | AE15: =AD15-1 -> 2019 | AF15: =AE15-1 -> 2018 | AG15: =AF15-1 -> 2017 | AH15: =AG15-1 -> 2016 | AI15: =AH15-1 -> 2015 | ... AK15: =AJ15-1 -> 2013
D16: =D8 -> 2023 | E16: =E8 -> 2022 | F16: =F8 -> 2021 | G16: =G8 -> 2020 | H16: =H8 -> 2019 | I16: =I8 -> 2018 | J16: =J8 -> 2017 | K16: =K8 -> 2016 | L16: =L8 -> 2015 | N16: =N8 -> 9Y Average | O16: =O8 -> 5Y Average | P16: =P8 -> 3Y Average | R16: Short Term Forecast | S16: Long Term Forecast | U16: Reference | Z16: Depreciation | AA16: 212.6 | AB16: 208.1 | AC16: 217.5 | AD16: 255.2 | AE16: 259.5 | AF16: 120.1 | AG16: 118.6 | AH16: 114.3 | AI16: 112.6 | AJ16: 112.6 | AK16: 112.6
B17: Depreciation factor | D17: =AA16/AA19 -> 0.14949722 | E17: =AB16/AB19 -> 0.15924395 | F17: =AC16/AC19 -> 0.17537494 | G17: =AD16/AD19 -> 0.21357436 | H17: =AE16/AE19 -> 0.18131638 | I17: =AF16/AF19 -> 0.212604 | J17: =AG16/AG19 -> 0.21220254 | K17: =AH16/AH19 -> 0.1975458 | L17: =AI16/AI19 -> 0.20991797 | N17: =AVERAGE(D17:L17) -> 0.19014191 | O17: =AVERAGE(D17:H17) -> 0.17580137 | P17: =AVERAGE(D17:F17) -> 0.16137204 | R17: -0.145 | S17: -0.14 | U17: % PPE | Z17: Amortization | AA17: 36.3 | AB17: 12.2 | AC17: 3.9 | AD17: 0.4 | AE17: 0 | AF17: 0.3 | AG17: 0.4 | AH17: 0.4 | AI17: 0.3 | AJ17: 0.3 | AK17: 0.3
B18: Amortization factor | D18: =AA17/AA18 -> 0.04452895 | E18: =AB17/AB18 -> 0.076633166 | F18: =AC17/AC18 -> 0.043721973 | G18: =AD17/AD18 -> 0.0060150376 | H18: =AE17/AE18 -> 0 | I18: =AF17/AF18 -> 0.0062240664 | J18: =AG17/AG18 -> 0.0082987552 | K18: =AH17/AH18 -> 0.0082987552 | L18: =AI17/AI18 -> 0.0059760956 | N18: =AVERAGE(D18:L18) -> 0.022188533 | O18: =AVERAGE(D18:H18) -> 0.034179825 | P18: =AVERAGE(D18:F18) -> 0.054961363 | R18: -0.05 | S18: -0.04 | U18: % IA | Z18: Intangible Assets (Gross) | AA18: 815.2 | AB18: 159.2 | AC18: 89.2 | AD18: 66.5 | AE18: 49.8 | AF18: 48.2 | AG18: 48.2 | AH18: 48.2 | AI18: 50.2 | AJ18: 50.2 | AK18: 50.2
B19: Stock-based comp | D19: =AA20/Inputs!B6 -> 0 | E19: =AB20/Inputs!C6 -> 0 | F19: =AC20/Inputs!D6 -> 0 | G19: =AD20/Inputs!E6 -> 0 | H19: =AE20/Inputs!F6 -> 0 | I19: =AF20/Inputs!G6 -> 0 | J19: =AG20/Inputs!H6 -> 0 | K19: =AH20/Inputs!I6 -> 0 | L19: =AI20/Inputs!J6 -> 0 | N19: =AVERAGE(D19:L19) -> 0 | O19: =AVERAGE(D19:H19) -> 0 | P19: =AVERAGE(D19:F19) -> 0 | R19: 0 | S19: 0 | U19: % Revenue | Z19: PPE+ROA (Gross) | AA19: 1422.1 | AB19: 1306.8 | AC19: 1240.2 | AD19: 1194.9 | AE19: 1431.2 | AF19: 564.9 | AG19: 558.9 | AH19: 578.6 | AI19: 536.4 | AJ19: 536.4 | AK19: 536.4
B20: Tax Rate | D20: ='Fin. Data'!B21/('Fin. Data'!B21+'Fin. Data'!B23) -> -0.36790841 | E20: ='Fin. Data'!C21/('Fin. Data'!C21+'Fin. Data'!C23) -> -0.2872668 | F20: ='Fin. Data'!D21/('Fin. Data'!D21+'Fin. Data'!D23) -> -0.27373566 | G20: ='Fin. Data'!E21/('Fin. Data'!E21+'Fin. Data'!E23) -> -0.24112554 | H20: ='Fin. Data'!F21/('Fin. Data'!F21+'Fin. Data'!F23) -> -0.29307057 | I20: ='Fin. Data'!G21/('Fin. Data'!G21+'Fin. Data'!G23) -> -0.28949634 | J20: ='Fin. Data'!H21/('Fin. Data'!H21+'Fin. Data'!H23) -> -0.29355191 | K20: ='Fin. Data'!I21/('Fin. Data'!I21+'Fin. Data'!I23) -> -0.32243963 | L20: ='Fin. Data'!J21/('Fin. Data'!J21+'Fin. Data'!J23) -> -0.34030151 | N20: =AVERAGE(D20:L20) -> -0.30098849 | O20: =AVERAGE(D20:H20) -> -0.2926214 | P20: =AVERAGE(D20:F20) -> -0.30963696 | R20: 0.3 | S20: 0.3 | U20: % EBT | Z20: Stock Based Compensation
B21: Interest Rate on debt | D21: 0.0366 | E21: 0.0366 | F21: 0.0406 | G21: 0.0406 | H21: 0.0483 | I21: 0.0483 | J21: 0.0483 | K21: - | L21: - | N21: =AVERAGE(D21:L21) -> 0.042757143 | O21: =AVERAGE(D21:H21) -> 0.04054 | P21: =AVERAGE(D21:F21) -> 0.037933333 | R21: 0.04 | S21: 0.04 | U21: % Debt | Z21: Interest expenses
B22: Interest Rate on cash | D22: 0.025 | E22: 0.001 | F22: 0.006 | G22: 0.004 | H22: 0.001 | I22: 0.001 | J22: 0.001 | K22: 0.002 | L22: 0.005 | N22: =AVERAGE(D22:L22) -> 0.0051111111 | O22: =AVERAGE(D22:H22) -> 0.0074 | P22: =AVERAGE(D22:F22) -> 0.010666667 | R22: 0.008 | S22: 0.008 | U22: % Cash | Z22: Interest income
B23: PPE+ROA | D23: =Inputs!B33/Inputs!C33-1 -> 0.066222084 | E23: =Inputs!C33/Inputs!D33-1 -> 0.07270005 | F23: =Inputs!D33/Inputs!E33-1 -> 0.26600674 | G23: =Inputs!E33/Inputs!F33-1 -> -0.1792567 | H23: =Inputs!F33/Inputs!G33-1 -> 0.024075058 | I23: =Inputs!G33/Inputs!H33-1 -> 0.010735373 | J23: =Inputs!H33/Inputs!I33-1 -> -0.034047701 | K23: =Inputs!I33/Inputs!J33-1 -> 0.078672632 | L23: =Inputs!J33/Inputs!K33-1 -> 0.065765945 | N23: =AVERAGE(D23:L23) -> 0.041208165 | O23: =AVERAGE(D23:H23) -> 0.049949447 | P23: =AVERAGE(D23:F23) -> 0.13497629 | R23: - - | S23: - - | U23: Growing with CAPEX | Z23: Total Debt
B24: Working capital flows | D24: =Inputs!B62/(Inputs!B6-Inputs!C6) -> 0.11181619 | E24: =Inputs!C62/(Inputs!C6-Inputs!D6) -> 0.46679735 | F24: =Inputs!D62/(Inputs!D6-Inputs!E6) -> 0.27466789 | G24: =Inputs!E62/(Inputs!E6-Inputs!F6) -> 0.36389724 | H24: =Inputs!F62/(Inputs!F6-Inputs!G6) -> -0.67307692 | I24: 0.14 | J24: =Inputs!H62/(Inputs!H6-Inputs!I6) -> 2.3397129 | K24: =Inputs!I62/(Inputs!I6-Inputs!J6) -> 10.523869 | L24: =Inputs!J62/(Inputs!J6-Inputs!K6) -> -1.3416149 | N24: =AVERAGE(D24:L24) -> 1.3562299 | O24: =AVERAGE(D24:H24) -> 0.10882035 | P24: =AVERAGE(D24:F24) -> 0.28442714 | R24: 0.2 | S24: 0.2 | U24: % Change in Revenues
B25: Intangible Assets | D25: 4.523 | E25: 0.736 | F25: 0.311 | G25: 0.362 | H25: 0.0375 | I25: -0.007 | J25: -0.0092 | K25: -0.0092 | L25: -0.0068 | N25: =AVERAGE(D25:L25) -> 0.6597 | O25: =AVERAGE(D25:H25) -> 1.1939 | P25: =AVERAGE(D25:F25) -> 1.8566667 | R25: - - | S25: - - | U25: Growing with Amortization
B26: CAPEX | D26: =Inputs!B65/Inputs!B6 -> -0.022892005 | E26: =Inputs!C65/Inputs!C6 -> -0.032459277 | F26: =Inputs!D65/Inputs!D6 -> -0.048574331 | G26: =Inputs!E65/Inputs!E6 -> -0.032735401 | H26: =Inputs!F65/Inputs!F6 -> -0.031901927 | I26: =Inputs!G65/Inputs!G6 -> -0.02949081 | J26: =Inputs!H65/Inputs!H6 -> -0.027567501 | K26: =Inputs!I65/Inputs!I6 -> -0.037658946 | L26: =Inputs!J65/Inputs!J6 -> -0.035265388 | N26: =AVERAGE(D26:L26) -> -0.033171732 | O26: =AVERAGE(D26:H26) -> -0.033712588 | P26: =AVERAGE(D26:F26) -> -0.034641871 | R26: -0.04 | S26: -0.038 | U26: % Revenue
B27: Acquisition factor | D27: =Inputs!B66/Inputs!B6 -> -0.0279002 | E27: =Inputs!C66/Inputs!C6 -> -0.018951132 | F27: =Inputs!D66/Inputs!D6 -> -0.0074147733 | G27: =Inputs!E66/Inputs!E6 -> -0.00067904029 | H27: =Inputs!F66/Inputs!F6 -> -0.00070320191 | I27: =Inputs!G66/Inputs!G6 -> 0 | J27: =Inputs!H66/Inputs!H6 -> 9.8631488e-05 | K27: =Inputs!I66/Inputs!I6 -> 0 | L27: =Inputs!J66/Inputs!J6 -> 0 | N27: =AVERAGE(D27:L27) -> -0.0061721907 | O27: =AVERAGE(D27:H27) -> -0.01112967 | P27: =AVERAGE(D27:F27) -> -0.018088702 | R27: -0.02 | S27: -0.01 | U27: % Revenue
B28: Dividends | D28: =Inputs!B73/Inputs!B6 -> -0.04521945 | E28: =Inputs!C73/Inputs!C6 -> -0.047159317 | F28: =Inputs!D73/Inputs!D6 -> -0.074471995 | G28: =Inputs!E73/Inputs!E6 -> 0 | H28: =Inputs!F73/Inputs!F6 -> -0.050067976 | I28: =Inputs!G73/Inputs!G6 -> -0.05175889 | J28: =Inputs!H73/Inputs!H6 -> -0.11828381 | K28: =Inputs!I73/Inputs!I6 -> -0.07666024 | L28: =Inputs!J73/Inputs!J6 -> -0.13586631 | N28: =AVERAGE(D28:L28) -> -0.066609777 | O28: =AVERAGE(D28:H28) -> -0.043383747 | P28: =AVERAGE(D28:F28) -> -0.05561692 | R28: 0.04 | S28: 0.05 | U28: % Net Income
B29: Repurchases | D29: =Inputs!B74/Inputs!B6 -> -0.032289201 | E29: =Inputs!E74/Inputs!E6 -> -0.0054606157 | F29: =Inputs!F74/Inputs!F6 -> -0.070367071 | G29: =Inputs!G74/Inputs!G6 -> -0.077986274 | H29: =Inputs!H74/Inputs!H6 -> -0.025915423 | I29: =Inputs!I74/Inputs!I6 -> -0.045786249 | J29: =Inputs!J74/Inputs!J6 -> -0.036079389 | K29: =Inputs!K74/Inputs!K6 -> -0.034476724 | L29: =Inputs!L74/Inputs!L6 -> -0.079090909 | N29: =AVERAGE(D29:L29) -> -0.045272429 | O29: =AVERAGE(D29:H29) -> -0.042403717 | P29: =AVERAGE(D29:F29) -> -0.036038963 | R29: 0.04 | S29: 0.06 | U29: % Net Income
B30: Leases | D30: =Inputs!B72/Inputs!B6 -> -0.028428337 | E30: =Inputs!C72/Inputs!C6 -> -0.031207787 | F30: =Inputs!D72/Inputs!D6 -> -0.037246806 | G30: =Inputs!E72/Inputs!E6 -> -0.048381621 | H30: =Inputs!F72/Inputs!F6 -> -0.038113544 | I30: =Inputs!G72/Inputs!G6 -> -0.03505783 | J30: =Inputs!H72/Inputs!H6 -> 0 | K30: =Inputs!I72/Inputs!I6 -> 0 | L30: =Inputs!J72/Inputs!J6 -> 0 | N30: =AVERAGE(D30:L30) -> -0.024270658 | O30: =AVERAGE(D30:H30) -> -0.036675619 | P30: =AVERAGE(D30:F30) -> -0.03229431 | R30: -0.025 | S30: -0.02 | U30: % Revenue
B31: Total Debt | D31: ='Fin. Data'!B58/'Fin. Data'!B19 -> 1.7400817 | E31: ='Fin. Data'!C58/'Fin. Data'!C19 -> 1.6792287 | F31: ='Fin. Data'!D58/'Fin. Data'!D19 -> 1.8612315 | G31: ='Fin. Data'!E58/'Fin. Data'!E19 -> 3.1270329 | H31: ='Fin. Data'!F58/'Fin. Data'!F19 -> 1.1049201 | I31: ='Fin. Data'!G58/'Fin. Data'!G19 -> 1.1670762 | J31: ='Fin. Data'!H58/'Fin. Data'!H19 -> 1.2298045 | K31: ='Fin. Data'!I58/'Fin. Data'!I19 -> 1.0048718 | L31: ='Fin. Data'!J58/'Fin. Data'!J19 -> 0.96085909 | N31: =AVERAGE(D31:L31) -> 1.5416785 | O31: =AVERAGE(D31:H31) -> 1.902499 | P31: =AVERAGE(D31:F31) -> 1.7601806 | U31: x EBITDA
B34: Forecasts
B36: Growth forecast (%)
D38: Next plc | E38: Industry
C39: 2024-29 | D39: =AVERAGE(DCF!G5:L5) -> 0.048544309 | E39: 0.0328
C40: 2020-25 | D40: 0.0791 | E40: 0.1806 | F40: fonte (industry - general retail): pages.stern.nyu.edu Damodaran
B44: EBIT (% revenue)
C46: 2023 | D46: 2022 | E46: 2021 | F46: 2020 | G46: 2019 | H46: 2018 | I46: 2017 | K46: Average (7y) | L46: =AVERAGE(C47:I47) -> 0.17967143
B47: EBIT (% revenue) | C47: 0.16 | D47: 0.187 | E47: 0.1956 | F47: 0.1259 | G47: 0.2 | H47: 0.2018 | I47: 0.1874 | K47: Average (3y) | L47: =AVERAGE(C47:E47) -> 0.18086667
D49: 2024 | E49: 2025 | F49: 2026 | G49: 2027 | H49: 2028 | I49: 2029 | J49: 2030 | K49: 2031 | L49: 2032 | M49: 2033 | N49: 2034 | O49: 2035 | P49: 2036 | Q49: 2037 | R49: 2038 | S49: 2039 | T49: 2040 | U49: 2041 | V49: 2042 | W49: 2043 | X49: 2044 | Y49: 2045 | Z49: 2046 | AA49: 2047 | AB49: 2048 | AC49: 2049
B50: EBIT forecast (% revenue) | D50: 0.18 | E50: 0.18 | F50: 0.18 | G50: 0.18 | H50: 0.18 | I50: 0.18 | J50: 0.18 | K50: 0.18 | L50: 0.18 | M50: 0.18 | N50: 0.18 | O50: 0.18 | P50: 0.18 | Q50: 0.18 | R50: 0.18 | S50: 0.18 | T50: 0.18 | U50: 0.18 | V50: 0.18 | W50: 0.18 | X50: 0.18 | Y50: 0.18 | Z50: 0.18 | AA50: 0.18 | AB50: 0.18 | AC50: 0.18
B64: Revenues forecast (Base scenario)
B66: Base scenario | C66: Time period | D66: 2024 | E66: 2025 | F66: 2026 | G66: 2027 | H66: 2028 | I66: 2029 | J66: 2030 | K66: 2031 | L66: 2032 | M66: 2033 | N66: 2034 | O66: 2035 | P66: 2036 | Q66: 2037 | R66: 2038 | S66: 2039 | T66: 2040 | U66: 2041 | V66: 2042 | W66: 2043 | X66: 2044 | Y66: 2045 | Z66: 2046 | AA66: 2047 | AB66: 2048 | AC66: 2049
C67: Forecasted Revenues Growth | D67: =C92 -> 0.065336915 | E67: =D92 -> 0.084694022 | F67: =E92 -> 0.05316128 | G67: =F92 -> 0.03756694 | H67: =H92 -> 0.028079378 | I67: =I92 -> 0.022427318 | J67: =J92 -> 0.022482329 | K67: =K92 -> 0.022537342 | L67: =L92 -> 0.022592351 | M67: =M92 -> 0.02264735 | N67: =N92 -> 0.022702333 | O67: =O92 -> 0.022757294 | ... AC67: =AC92 -> 0.015526513
C68: Forecasted Yearly Revenues | D68: =C91 -> 5849.765 | E68: =D91 -> 6345.2051 | F68: =E91 -> 6682.5244 | G68: =F91 -> 6933.5663 | H68: =H91 -> 7128.2566 | I68: =I91 -> 7288.1243 | J68: =J91 -> 7451.9783 | K68: =K91 -> 7619.9261 | L68: =L91 -> 7792.0781 | M68: =M91 -> 7968.548 | N68: =N91 -> 8149.4526 | O68: =O91 -> 8334.9121 | ... AC68: =AC91 -> 10318.748
C69: Forecasted operating margin | D69: 0.18 | E69: 0.18 | F69: 0.18 | G69: 0.18 | H69: 0.18 | I69: 0.18 | J69: 0.18 | K69: 0.18 | L69: 0.18 | M69: 0.18 | N69: 0.18 | O69: 0.18 | P69: 0.18 | Q69: 0.18 | R69: 0.18 | S69: 0.18 | T69: 0.18 | U69: 0.18 | V69: 0.18 | W69: 0.18 | X69: 0.18 | Y69: 0.18 | Z69: 0.18 | AA69: 0.18 | AB69: 0.18 | AC69: 0.18
B72: SHORT TERM REVENUE GROWTH FORECAST | H72: LONG TERM REVENUE GROWTH FORECAST
C74: 2024 | D74: 2025 | E74: 2026 | F74: 2027 | H74: 2028-2035 | J74: 2035-2049
B75: NEXT Online | C75: 0.05 | D75: 0.045 | E75: 0.04 | F75: 0.035 | H75: 0.03 | J75: 0.02
B76: NEXT Retail | C76: 0.03 | D76: 0.025 | E76: 0.02 | F76: 0.015 | H76: 0.015 | J76: 0.01
B77: NEXT Finance | C77: 0.02 | D77: 0.02 | E77: 0.02 | F77: 0.02 | H77: 0.02 | J77: 0.02
B78: TP (and label partners) | C78: 0.6 | D78: 0.4 | E78: 0.2 | F78: 0.1 | H78: 0.05 | J78: 0.02
B79: Property Manag. | C79: 0.1 | D79: 0.075 | E79: 0.05 | F79: 0.025 | H79: 0.03 | J79: 0.02
B80: Sourcing, Franchise | C80: 0.02 | D80: 0.015 | E80: 0.01 | F80: 0.01 | H80: 0.01 | J80: 0.01
B82: SHORT TERM YEARLY REVENUE FORECAST
C84: 2024 | D84: 2025 | E84: 2026 | F84: 2027 | H84: 2028 | I84: =H84+1 -> 2029 | J84: =I84+1 -> 2030 | K84: =J84+1 -> 2031 | L84: =K84+1 -> 2032 | M84: =L84+1 -> 2033 | N84: =M84+1 -> 2034 | O84: =N84+1 -> 2035 | P84: =O84+1 -> 2036 | ... AC84: =AB84+1 -> 2049
B85: NEXT Online | C85: =C222*(1+C75) -> 3046.47 | D85: =3046.47*(1+D75) -> 3183.5611 | E85: =D85*(1+E75) -> 3310.9036 | F85: =E85*(1+F75) -> 3426.7852 | H85: =F85*($H$75+1) -> 3529.5888 | I85: =H85*($H$75+1) -> 3635.4764 | J85: =I85*($H$75+1) -> 3744.5407 | K85: =J85*($H$75+1) -> 3856.877 | L85: =K85*($H$75+1) -> 3972.5833 | M85: =L85*($H$75+1) -> 4091.7608 | N85: =M85*($H$75+1) -> 4214.5136 | O85: =N85*($H$75+1) -> 4340.949 | P85: =O85*($J$75+1) -> 4427.768 | Q85: =P85*($J$75+1) -> 4516.3233 | R85: =Q85*($J$75+1) -> 4606.6498 | S85: =R85*($J$75+1) -> 4698.7828 | T85: =S85*($J$75+1) -> 4792.7585 | U85: =T85*($J$75+1) -> 4888.6136 | V85: =U85*($J$75+1) -> 4986.3859 | W85: =V85*($J$75+1) -> 5086.1136 | ... AC85: =AB85*($J$75+1) -> 5727.79
B86: NEXT Retail | C86: =C223*(1+C76) -> 1899.011 | D86: =C86*(1+D76) -> 1946.4863 | E86: =D86*(1+E76) -> 1985.416 | F86: =E86*(1+F76) -> 2015.1972 | H86: =F86*(1+H76) -> 2045.4252 | I86: =H86*(1+$H$76) -> 2076.1066 | J86: =I86*(1+$H$76) -> 2107.2482 | K86: =J86*(1+$H$76) -> 2138.8569 | L86: =K86*(1+$H$76) -> 2170.9398 | M86: =L86*(1+$H$76) -> 2203.5038 | N86: =M86*(1+$H$76) -> 2236.5564 | O86: =N86*(1+$H$76) -> 2270.1048 | P86: =O86*(1+$J$76) -> 2292.8058 | Q86: =P86*(1+$J$76) -> 2315.7339 | R86: =Q86*(1+$J$76) -> 2338.8912 | S86: =R86*(1+$J$76) -> 2362.2801 | T86: =S86*(1+$J$76) -> 2385.9029 | U86: =T86*(1+$J$76) -> 2409.7619 | V86: =U86*(1+$J$76) -> 2433.8596 | W86: =V86*(1+$J$76) -> 2458.1982 | ... AC86: =AB86*(1+$J$76) -> 2609.4269
B87: NEXT Finance | C87: =C224*(1+C77) -> 298.554 | D87: =C87*(1+D77) -> 304.52508 | E87: =D87*(1+E77) -> 310.61558 | F87: =E87*(1+F77) -> 316.82789 | H87: =F87*(1+H77) -> 323.16445 | I87: =H87*(1+$H$76) -> 328.01192 | J87: =I87*(1+$H$76) -> 332.9321 | K87: =J87*(1+$H$76) -> 337.92608 | L87: =K87*(1+$H$76) -> 342.99497 | M87: =L87*(1+$H$76) -> 348.13989 | N87: =M87*(1+$H$76) -> 353.36199 | O87: =N87*(1+$H$76) -> 358.66242 | P87: =O87*(1+$J$76) -> 362.24905 | Q87: =P87*(1+$J$76) -> 365.87154 | R87: =Q87*(1+$J$76) -> 369.53025 | S87: =R87*(1+$J$76) -> 373.22555 | T87: =S87*(1+$J$76) -> 376.95781 | U87: =T87*(1+$J$76) -> 380.72739 | V87: =U87*(1+$J$76) -> 384.53466 | W87: =V87*(1+$J$76) -> 388.38001 | ... AC87: =AB87*(1+$J$76) -> 412.27321
B88: TP (and label partners) | C88: =C225*(1+C78) -> 582.08 | D88: =C88*(1+D78) -> 814.912 | E88: =D88*(1+E78) -> 977.8944 | F88: =E88*(1+F78) -> 1075.6838 | H88: =F88*(1+H78) -> 1129.468 | I88: =H88*(1+$H$76) -> 1146.4101 | J88: =I88*(1+$H$76) -> 1163.6062 | K88: =J88*(1+$H$76) -> 1181.0603 | L88: =K88*(1+$H$76) -> 1198.7762 | M88: =L88*(1+$H$76) -> 1216.7578 | N88: =M88*(1+$H$76) -> 1235.0092 | O88: =N88*(1+$H$76) -> 1253.5343 | P88: =O88*(1+$J$76) -> 1266.0697 | Q88: =P88*(1+$J$76) -> 1278.7304 | R88: =Q88*(1+$J$76) -> 1291.5177 | S88: =R88*(1+$J$76) -> 1304.4329 | T88: =S88*(1+$J$76) -> 1317.4772 | U88: =T88*(1+$J$76) -> 1330.652 | V88: =U88*(1+$J$76) -> 1343.9585 | W88: =V88*(1+$J$76) -> 1357.3981 | ... AC88: =AB88*(1+$J$76) -> 1440.9054
B89: Property Manag. | C89: =C226*(1+C79) -> 23.65 | D89: =C89*(1+D79) -> 25.42375 | E89: =D89*(1+E79) -> 26.694938 | F89: =E89*(1+F79) -> 27.362311 | H89: =F89*(1+H79) -> 28.18318 | I89: =H89*(1+$H$76) -> 28.605928 | J89: =I89*(1+$H$76) -> 29.035017 | K89: =J89*(1+$H$76) -> 29.470542 | L89: =K89*(1+$H$76) -> 29.9126 | M89: =L89*(1+$H$76) -> 30.361289 | N89: =M89*(1+$H$76) -> 30.816709 | O89: =N89*(1+$H$76) -> 31.278959 | P89: =O89*(1+$J$76) -> 31.591749 | Q89: =P89*(1+$J$76) -> 31.907666 | R89: =Q89*(1+$J$76) -> 32.226743 | S89: =R89*(1+$J$76) -> 32.54901 | T89: =S89*(1+$J$76) -> 32.874501 | U89: =T89*(1+$J$76) -> 33.203246 | V89: =U89*(1+$J$76) -> 33.535278 | W89: =V89*(1+$J$76) -> 33.870631 | ... AC89: =AB89*(1+$J$76) -> 35.954357
B90: Sourcing, Franchise | C90: =C227*(1+C80) -> 69.258 | D90: =C90*(1+D80) -> 70.29687 | E90: =D90*(1+E80) -> 70.999839 | F90: =E90*(1+F80) -> 71.709837 | H90: =F90*(1+H80) -> 72.426935 | I90: =H90*(1+$H$76) -> 73.513339 | J90: =I90*(1+$H$76) -> 74.61604 | K90: =J90*(1+$H$76) -> 75.73528 | L90: =K90*(1+$H$76) -> 76.871309 | M90: =L90*(1+$H$76) -> 78.024379 | N90: =M90*(1+$H$76) -> 79.194745 | O90: =N90*(1+$H$76) -> 80.382666 | P90: =O90*(1+$J$76) -> 81.186493 | Q90: =P90*(1+$J$76) -> 81.998357 | R90: =Q90*(1+$J$76) -> 82.818341 | S90: =R90*(1+$J$76) -> 83.646524 | T90: =S90*(1+$J$76) -> 84.48299 | U90: =T90*(1+$J$76) -> 85.32782 | V90: =U90*(1+$J$76) -> 86.181098 | W90: =V90*(1+$J$76) -> 87.042909 | ... AC90: =AB90*(1+$J$76) -> 92.397802
B91: Total | C91: =SUM(C85:C89) -> 5849.765 | D91: =SUM(D85:D90) -> 6345.2051 | E91: =SUM(E85:E90) -> 6682.5244 | F91: =SUM(F85:F90) -> 6933.5663 | H91: =SUM(H85:H90) -> 7128.2566 | I91: =SUM(I85:I90) -> 7288.1243 | J91: =SUM(J85:J90) -> 7451.9783 | K91: =SUM(K85:K90) -> 7619.9261 | L91: =SUM(L85:L90) -> 7792.0781 | M91: =SUM(M85:M90) -> 7968.548 | N91: =SUM(N85:N90) -> 8149.4526 | O91: =SUM(O85:O90) -> 8334.9121 | ... AC91: =SUM(AC85:AC90) -> 10318.748
B92: Total Revenue Growth | C92: =C91/C228-1 -> 0.065336915 | D92: =D91/C91-1 -> 0.084694022 | E92: =E91/D91-1 -> 0.05316128 | F92: =F91/E91-1 -> 0.03756694 | H92: =H91/F91-1 -> 0.028079378 | I92: =I91/H91-1 -> 0.022427318 | J92: =J91/I91-1 -> 0.022482329 | K92: =K91/J91-1 -> 0.022537342 | L92: =L91/K91-1 -> 0.022592351 | M92: =M91/L91-1 -> 0.02264735 | N92: =N91/M91-1 -> 0.022702333 | O92: =O91/N91-1 -> 0.022757294 | P92: =P91/O91-1 -> 0.015208152 | ... AC92: =AC91/AB91-1 -> 0.015526513
B96: ASSUMPTIONS & INFORMATION FOR BASE SCENARIO
B97: Next PLC is able to increase their brand global reach in a moderate way, and reaches a warehousing limit after sometime. The company is not so focused on this branch, even though they keep improving their distribution and product quality. We keep this forecast conservative. TP is expected to grow at a more accelerated pace, and Franchise is conservativly expected to keep at current high levels, given the undergoing negotiations to expand thus branch into USA and India, with Nordstrom, a big US retailer.
B108: Revenues forecast (Bullish scenario)
B110: Bullish Scenario | C110: Time period | D110: 2024 | E110: 2025 | F110: 2026 | G110: 2027 | H110: 2028 | I110: 2029 | J110: 2030 | K110: 2031 | L110: 2032 | M110: 2033 | N110: 2034 | O110: 2035 | P110: 2036 | Q110: 2037 | R110: 2038 | S110: 2039 | T110: 2040 | U110: 2041 | V110: 2042 | W110: 2043 | X110: 2044 | Y110: 2045 | Z110: 2046 | AA110: 2047 | AB110: 2048 | AC110: 2049
C111: Forecasted Revenues Growth | D111: =C136 -> 0.11039774 | E111: =D136 -> 0.10201524 | F111: =E136 -> 0.07873922 | G111: =F136 -> 0.062724877 | H111: =H136 -> 0.03949333 | I111: =I136 -> 0.039587865 | J111: =J136 -> 0.039681824 | K111: =K136 -> 0.039775198 | L111: =L136 -> 0.039867975 | M111: =M136 -> 0.039960144 | N111: =N136 -> 0.040051694 | O111: =O136 -> 0.040142616 | ... AC111: =AC136 -> 0.029535798
C112: Forecasted Yearly Revenues | D112: =C135 -> 6097.194 | E112: =D135 -> 6719.2007 | F112: =E135 -> 7248.2653 | G112: =F135 -> 7702.9119 | H112: =H135 -> 8007.1255 | I112: =I135 -> 8324.1105 | J112: =J135 -> 8654.4264 | K112: =K135 -> 8998.6579 | L112: =L135 -> 9357.4162 | M112: =M135 -> 9731.3399 | N112: =N135 -> 10121.097 | O112: =O135 -> 10527.384 | ... AC112: =AC135 -> 15627.037
C113: Forecasted operating margin | D113: 0.18 | E113: 0.18 | F113: 0.18 | G113: 0.18 | H113: 0.18 | I113: 0.18 | J113: 0.18 | K113: 0.18 | L113: 0.18 | M113: 0.18 | N113: 0.18 | O113: 0.18 | P113: 0.18 | Q113: 0.18 | R113: 0.18 | S113: 0.18 | T113: 0.18 | U113: 0.18 | V113: 0.18 | W113: 0.18 | X113: 0.18 | Y113: 0.18 | Z113: 0.18 | AA113: 0.18 | AB113: 0.18 | AC113: 0.18
B116: SHORT TERM REVENUE GROWTH FORECAST | H116: LONG TERM REVENUE GROWTH FORECAST
C118: 2024 | D118: 2025 | E118: 2026 | F118: 2027 | H118: 2028-2035 | J118: 2035-2049
B119: NEXT Online | C119: 0.07 | D119: 0.065 | E119: 0.06 | F119: 0.055 | H119: 0.045 | J119: 0.02
B120: NEXT Retail | C120: 0.05 | D120: 0.04 | E120: 0.035 | F120: 0.03 | H120: 0.025 | J120: 0.02
B121: NEXT Finance | C121: 0.03 | D121: 0.03 | E121: 0.03 | F121: 0.03 | H121: 0.03 | J121: 0.02
B122: TP (and label partners) | C122: 0.8 | D122: 0.5 | E122: 0.25 | F122: 0.15 | H122: 0.05 | J122: 0.02
B123: Property Manag. | C123: 0.2 | D123: 0.1 | E123: 0.05 | F123: 0.05 | H123: 0.035 | J123: 0.02
B124: Sourcing, Franchise | C124: 0.1 | D124: 0.05 | E124: 0.05 | F124: 0.05 | H124: 0.03 | J124: 0.02
B126: SHORT TERM YEARLY REVENUE FORECAST
C128: 2024 | D128: 2025 | E128: 2026 | F128: 2027 | H128: 2028 | I128: =H128+1 -> 2029 | J128: =I128+1 -> 2030 | K128: =J128+1 -> 2031 | L128: =K128+1 -> 2032 | M128: =L128+1 -> 2033 | N128: =M128+1 -> 2034 | O128: =N128+1 -> 2035 | P128: =O128+1 -> 2036 | ... AC128: =AB128+1 -> 2049
B129: NEXT Online | C129: =2901.4*(1+C119) -> 3104.498 | D129: =C129*(1+D119) -> 3306.2904 | E129: =D129*(1+E119) -> 3504.6678 | F129: =E129*(1+F119) -> 3697.4245 | H129: =F129*(1+$H$119) -> 3863.8086 | I129: =H129*(1+H119) -> 4037.68 | J129: =I129*(1+$H$119) -> 4219.3756 | K129: =J129*(1+$H$119) -> 4409.2475 | L129: =K129*(1+$H$119) -> 4607.6637 | M129: =L129*(1+$H$119) -> 4815.0085 | N129: =M129*(1+$H$119) -> 5031.6839 | O129: =N129*(1+$H$119) -> 5258.1097 | P129: =O129*(1+$J$119) -> 5363.2719 | Q129: =P129*(1+$J$119) -> 5470.5373 | R129: =Q129*(1+$J$119) -> 5579.9481 | S129: =R129*(1+$J$119) -> 5691.547 | T129: =S129*(1+$J$119) -> 5805.378 | U129: =T129*(1+$J$119) -> 5921.4855 | V129: =U129*(1+$J$119) -> 6039.9152 | W129: =V129*(1+$J$119) -> 6160.7135 | ... AC129: =AB129*(1+$J$119) -> 6937.9641
B130: NEXT Retail | C130: =1843.7*(1+C120) -> 1935.885 | D130: =C130*(1+D120) -> 2013.3204 | E130: =D130*(1+E120) -> 2083.7866 | F130: =E130*(1+F120) -> 2146.3002 | H130: =F130*(1+$H$120) -> 2199.9577 | I130: =H130*(1+$H$120) -> 2254.9567 | J130: =I130*(1+$H$120) -> 2311.3306 | K130: =J130*(1+$H$120) -> 2369.1138 | L130: =K130*(1+$H$120) -> 2428.3417 | M130: =L130*(1+$H$120) -> 2489.0502 | N130: =M130*(1+$H$120) -> 2551.2765 | O130: =N130*(1+$H$120) -> 2615.0584 | P130: =O130*(1+$H$120) -> 2680.4349 | ... AC130: =AB130*(1+$H$120) -> 3695.0091
B131: NEXT Finance | C131: =292.7*(1+C121) -> 301.481 | D131: =C131*(1+D121) -> 310.52543 | E131: =D131*(1+E121) -> 319.84119 | F131: =E131*(1+F121) -> 329.43643 | H131: =F131*(1+$H$121) -> 339.31952 | I131: =H131*(1+$H$121) -> 349.49911 | J131: =I131*(1+$H$121) -> 359.98408 | K131: =J131*(1+$H$121) -> 370.7836 | L131: =K131*(1+$H$121) -> 381.90711 | M131: =L131*(1+$H$121) -> 393.36432 | N131: =M131*(1+$H$121) -> 405.16525 | O131: =N131*(1+$H$121) -> 417.32021 | P131: =O131*(1+$H$121) -> 429.83982 | ... AC131: =AB131*(1+$H$121) -> 631.23426
B132: TP (and label partners) | C132: =363.8*(1+C122) -> 654.84 | D132: =C132*(1+D122) -> 982.26 | E132: =D132*(1+E122) -> 1227.825 | F132: =E132*(1+F122) -> 1411.9987 | H132: =F132*(1+$H$122) -> 1482.5987 | I132: =H132*(1+$H$122) -> 1556.7286 | J132: =I132*(1+$H$122) -> 1634.5651 | K132: =J132*(1+$H$122) -> 1716.2933 | L132: =K132*(1+$H$122) -> 1802.108 | M132: =L132*(1+$H$122) -> 1892.2134 | N132: =M132*(1+$H$122) -> 1986.824 | O132: =N132*(1+$H$122) -> 2086.1652 | P132: =O132*(1+$H$122) -> 2190.4735 | ... AC132: =AB132*(1+$H$122) -> 4130.4645
B133: Property Manag. | C133: =21.5*(1+C123) -> 25.8 | D133: =C133*(1+D123) -> 28.38 | E133: =D133*(1+E123) -> 29.799 | F133: =E133*(1+F123) -> 31.28895 | H133: =F133*(1+$H$123) -> 32.384063 | I133: =H133*(1+$H$123) -> 33.517505 | J133: =I133*(1+$H$123) -> 34.690618 | K133: =J133*(1+$H$123) -> 35.90479 | L133: =K133*(1+$H$123) -> 37.161457 | M133: =L133*(1+$H$123) -> 38.462108 | N133: =M133*(1+$H$123) -> 39.808282 | O133: =N133*(1+$H$123) -> 41.201572 | P133: =O133*(1+$H$123) -> 42.643627 | ... AC133: =AB133*(1+$H$123) -> 66.692759
B134: Sourcing, Franchise | C134: =67.9*(1+C124) -> 74.69 | D134: =C134*(1+D124) -> 78.4245 | E134: =D134*(1+E124) -> 82.345725 | F134: =E134*(1+F124) -> 86.463011 | H134: =F134*(1+$H$124) -> 89.056902 | I134: =H134*(1+$H$124) -> 91.728609 | J134: =I134*(1+$H$124) -> 94.480467 | K134: =J134*(1+$H$124) -> 97.314881 | L134: =K134*(1+$H$124) -> 100.23433 | M134: =L134*(1+$H$124) -> 103.24136 | N134: =M134*(1+$H$124) -> 106.3386 | O134: =N134*(1+$H$124) -> 109.52876 | P134: =O134*(1+$H$124) -> 112.81462 | ... AC134: =AB134*(1+$H$124) -> 165.67207
B135: Total | C135: =SUM(C129:C134) -> 6097.194 | D135: =SUM(D129:D134) -> 6719.2007 | E135: =SUM(E129:E134) -> 7248.2653 | F135: =SUM(F129:F134) -> 7702.9119 | H135: =SUM(H129:H134) -> 8007.1255 | I135: =SUM(I129:I134) -> 8324.1105 | J135: =SUM(J129:J134) -> 8654.4264 | K135: =SUM(K129:K134) -> 8998.6579 | L135: =SUM(L129:L134) -> 9357.4162 | M135: =SUM(M129:M134) -> 9731.3399 | N135: =SUM(N129:N134) -> 10121.097 | O135: =SUM(O129:O134) -> 10527.384 | ... AC135: =SUM(AC129:AC134) -> 15627.037
B136: Total Revenue Growth | C136: =C135/5491-1 -> 0.11039774 | D136: =D135/C135-1 -> 0.10201524 | E136: =E135/D135-1 -> 0.07873922 | F136: =F135/E135-1 -> 0.062724877 | H136: =H135/F135-1 -> 0.03949333 | I136: =I135/H135-1 -> 0.039587865 | J136: =J135/I135-1 -> 0.039681824 | K136: =K135/J135-1 -> 0.039775198 | L136: =L135/K135-1 -> 0.039867975 | M136: =M135/L135-1 -> 0.039960144 | N136: =N135/M135-1 -> 0.040051694 | O136: =O135/N135-1 -> 0.040142616 | P136: =P135/O135-1 -> 0.027746156 | ... AC136: =AC135/AB135-1 -> 0.029535798
B140: ASSUMPTIONS & INFORMATION FOR BULLISH SCENARIO
B141: The bullish scenario is related to the possibility of Next being able to improve their brand global reach in a way that gets them into global markets with more presence, reflected in a high online sales growth; Retail not losing a lot of momentum. TP growing at a faster pace than expected, and the Franchise deals with Nordstrom going outstandingly well.
B152: Revenues forecast (Bearish scenario)
B154: Bearish Scenario | C154: Time period | D154: 2024 | E154: 2025 | F154: 2026 | G154: 2027 | H154: 2028 | I154: 2029 | J154: 2030 | K154: 2031 | L154: 2032 | M154: 2033 | N154: 2034 | O154: 2035 | P154: 2036 | Q154: 2037 | R154: 2038 | S154: 2039 | T154: 2040 | U154: 2041 | V154: 2042 | W154: 2043 | X154: 2044 | Y154: 2045 | Z154: 2046 | AA154: 2047 | AB154: 2048 | AC154: 2049
C155: Forecasted Revenues Growth | D155: =C180 -> 0.048456019 | E155: =D180 -> 0.034564657 | F155: =E180 -> 0.026765102 | G155: =F180 -> 0.021601811 | H155: =H180 -> 0.01557318 | I155: =I180 -> 0.015642766 | J155: =J180 -> 0.015711737 | K155: =K180 -> 0.015780617 | L155: =L180 -> 0.0158494 | M155: =M180 -> 0.015918083 | N155: =N180 -> 0.015986659 | O155: =O180 -> 0.016055123 | ... AC155: =AC180 -> 0.016999261
C156: Forecasted Yearly Revenues | D156: =C179 -> 5757.072 | E156: =D179 -> 5956.0632 | F156: =E179 -> 6115.4779 | G156: =F179 -> 6247.5833 | H156: =H179 -> 6344.878 | I156: =I179 -> 6444.1294 | J156: =J179 -> 6545.3779 | K156: =K179 -> 6648.668 | L156: =L179 -> 6754.0454 | M156: =M179 -> 6861.5569 | N156: =N179 -> 6971.2502 | O156: =O179 -> 7083.1745 | ... AC156: =AC179 -> 8914.7647
C157: Forecasted operating margin | D157: 0.18 | E157: 0.18 | F157: 0.18 | G157: 0.18 | H157: 0.18 | I157: 0.18 | J157: 0.18 | K157: 0.18 | L157: 0.18 | M157: 0.18 | N157: 0.18 | O157: 0.18 | P157: 0.18 | Q157: 0.18 | R157: 0.18 | S157: 0.18 | T157: 0.18 | U157: 0.18 | V157: 0.18 | W157: 0.18 | X157: 0.18 | Y157: 0.18 | Z157: 0.18 | AA157: 0.18 | AB157: 0.18 | AC157: 0.18
B160: SHORT TERM REVENUE GROWTH FORECAST | H160: LONG TERM REVENUE GROWTH FORECAST
C162: 2024 | D162: 2025 | E162: 2026 | F162: 2027 | H162: 2028-2035 | J162: 2035-2049
B163: NEXT Online | C163: 0.04 | D163: 0.035 | E163: 0.03 | F163: 0.025 | H163: 0.02 | J163: 0.01
B164: NEXT Retail | C164: 0.02 | D164: 0.01 | E164: 0.01 | F164: 0.01 | H164: 0.005 | J164: 0.0025
B165: NEXT Finance | C165: 0.01 | D165: 0.01 | E165: 0.01 | F165: 0.01 | H165: 0.01 | J165: 0.005
B166: TP (and label partners) | C166: 0.3 | D166: 0.15 | E166: 0.08 | F166: 0.05 | H166: 0.03 | J166: 0.02
B167: Property Manag. | C167: 0.05 | D167: 0.03 | E167: 0.01 | F167: 0.005 | H167: 0.005 | J167: 0.005
B168: Sourcing, Franchise | C168: 0 | D168: 0 | E168: 0 | F168: 0 | H168: 0 | J168: 0
B170: SHORT TERM YEARLY REVENUE FORECAST
C172: 2024 | D172: 2025 | E172: 2026 | F172: 2027 | H172: 2028 | I172: =H172+1 -> 2029 | J172: =I172+1 -> 2030 | K172: =J172+1 -> 2031 | L172: =K172+1 -> 2032 | M172: =L172+1 -> 2033 | N172: =M172+1 -> 2034 | O172: =N172+1 -> 2035 | P172: =O172+1 -> 2036 | ... AC172: =AB172+1 -> 2049
B173: NEXT Online | C173: =2901.4*(1+C163) -> 3017.456 | D173: =C173*(1+D163) -> 3123.067 | E173: =D173*(1+E163) -> 3216.759 | F173: =E173*(1+F163) -> 3297.1779 | H173: =3297.18*(1+$H$163) -> 3363.1236 | I173: =H173*(1+$H$163) -> 3430.3861 | J173: =I173*(1+$H$163) -> 3498.9938 | K173: =J173*(1+$H$163) -> 3568.9737 | L173: =K173*(1+$H$163) -> 3640.3531 | M173: =L173*(1+$H$163) -> 3713.1602 | N173: =M173*(1+$H$163) -> 3787.4234 | O173: =N173*(1+$H$163) -> 3863.1719 | P173: =O173*(1+$H$163) -> 3940.4353 | ... AC173: =AB173*(1+$H$163) -> 5097.3733
...

Sheet Fin. Data
A1: =Inputs!H3 -> #VALUE!
A2: =Inputs!G2 -> Figures in Millions of USD
A3: Results
B4: =OP!J19 -> 2023 | C4: =B4-1 -> 2022 | D4: =C4-1 -> 2021 | E4: =D4-1 -> 2020 | F4: =E4-1 -> 2019 | G4: =F4-1 -> 2018 | H4: =G4-1 -> 2017 | I4: =H4-1 -> 2016 | J4: =I4-1 -> 2015 | ... M4: =L4-1 -> 2012
A5: Net Sales | B5: =_xlfn.XLOOKUP($A5,Inputs!$A:$A,Inputs!B:B,,0) -> 5491 | C5: =_xlfn.XLOOKUP($A5,Inputs!$A:$A,Inputs!C:C,,0) -> 5034 | D5: =_xlfn.XLOOKUP($A5,Inputs!$A:$A,Inputs!D:D,,0) -> 4625.9 | E5: =_xlfn.XLOOKUP($A5,Inputs!$A:$A,Inputs!E:E,,0) -> 3534.4 | F5: =_xlfn.XLOOKUP($A5,Inputs!$A:$A,Inputs!F:F,,0) -> 4266.2 | G5: =_xlfn.XLOOKUP($A5,Inputs!$A:$A,Inputs!G:G,,0) -> 4167.4 | H5: =_xlfn.XLOOKUP($A5,Inputs!$A:$A,Inputs!H:H,,0) -> 4055.5 | I5: =_xlfn.XLOOKUP($A5,Inputs!$A:$A,Inputs!I:I,,0) -> 4097.3 | J5: =_xlfn.XLOOKUP($A5,Inputs!$A:$A,Inputs!J:J,,0) -> 4176.9 | K5: =_xlfn.XLOOKUP($A5,Inputs!$A:$A,Inputs!K:K,,0) -> 3999.8 | L5: =_xlfn.XLOOKUP($A5,Inputs!$A:$A,Inputs!L:L,,0) -> 3740 | M5: =_xlfn.XLOOKUP($A5,Inputs!$A:$A,Inputs!M:M,,0) -> 3562.8
A6: Growth vs. Previous year | B6: =IFERROR(B5/C5-1,"-") -> 0.090782678 | C6: =IFERROR(C5/D5-1,"-") -> 0.088220671 | D6: =IFERROR(D5/E5-1,"-") -> 0.30882187 | E6: =IFERROR(E5/F5-1,"-") -> -0.17153439 | F6: =IFERROR(F5/G5-1,"-") -> 0.023707827 | G6: =IFERROR(G5/H5-1,"-") -> 0.027592159 | H6: =IFERROR(H5/I5-1,"-") -> -0.01020184 | I6: =IFERROR(I5/J5-1,"-") -> -0.019057196 | ... L6: =IFERROR(L5/M5-1,"-") -> 0.049736163 | M6: =IFERROR(M5/#REF!-1,"-") -> -
A7: Gross Profit | B7: =_xlfn.XLOOKUP($A7,Inputs!$A:$A,Inputs!B:B,,0) -> 2420.5 | C7: =_xlfn.XLOOKUP($A7,Inputs!$A:$A,Inputs!C:C,,0) -> 2175.3 | D7: =_xlfn.XLOOKUP($A7,Inputs!$A:$A,Inputs!D:D,,0) -> 1972 | E7: =_xlfn.XLOOKUP($A7,Inputs!$A:$A,Inputs!E:E,,0) -> 1247.9 | F7: =_xlfn.XLOOKUP($A7,Inputs!$A:$A,Inputs!F:F,,0) -> 1640.5 | G7: =_xlfn.XLOOKUP($A7,Inputs!$A:$A,Inputs!G:G,,0) -> 1552.5 | H7: =_xlfn.XLOOKUP($A7,Inputs!$A:$A,Inputs!H:H,,0) -> 1356.2 | I7: =_xlfn.XLOOKUP($A7,Inputs!$A:$A,Inputs!I:I,,0) -> 1386.6 | J7: =_xlfn.XLOOKUP($A7,Inputs!$A:$A,Inputs!J:J,,0) -> 1452.7 | K7: =_xlfn.XLOOKUP($A7,Inputs!$A:$A,Inputs!K:K,,0) -> 1343.4 | L7: =_xlfn.XLOOKUP($A7,Inputs!$A:$A,Inputs!L:L,,0) -> 1240.1 | M7: =_xlfn.XLOOKUP($A7,Inputs!$A:$A,Inputs!M:M,,0) -> 1125.8
A8: % over sales | B8: =IFERROR(B7/B$5,"-") -> 0.44081224 | C8: =IFERROR(C7/C$5,"-") -> 0.43212157 | D8: =IFERROR(D7/D$5,"-") -> 0.42629542 | E8: =IFERROR(E7/E$5,"-") -> 0.35307266 | F8: =IFERROR(F7/F$5,"-") -> 0.38453425 | G8: =IFERROR(G7/G$5,"-") -> 0.37253443 | H8: =IFERROR(H7/H$5,"-") -> 0.33441006 | I8: =IFERROR(I7/I$5,"-") -> 0.33841798 | ... M8: =IFERROR(M7/M$5,"-") -> 0.31598743
A9: Operating expenses | B9: =B5-B11 -> 4515.4 | C9: =C5-C11 -> 4076.2 | D9: =D5-D11 -> 3723 | E9: =E5-E11 -> 3088.6 | F9: =F5-F11 -> 3410.8 | G9: =G5-G11 -> 3327.7 | H9: =H5-H11 -> 3294.5 | I9: =I5-I11 -> 3269.7 | ... M9: =M5-M11 -> 2906.9
A10: % over sales | B10: =IFERROR(B9/B$5,"-") -> 0.82232744 | C10: =IFERROR(C9/C$5,"-") -> 0.80973381 | D10: =IFERROR(D9/D$5,"-") -> 0.80481636 | E10: =IFERROR(E9/E$5,"-") -> 0.87386827 | F10: =IFERROR(F9/F$5,"-") -> 0.79949369 | G10: =IFERROR(G9/G$5,"-") -> 0.79850746 | H10: =IFERROR(H9/H$5,"-") -> 0.81235359 | I10: =IFERROR(I9/I$5,"-") -> 0.79801333 | ... M10: =IFERROR(M9/M$5,"-") -> 0.81590322
A11: Operating Income | B11: =_xlfn.XLOOKUP($A11,Inputs!$A:$A,Inputs!B:B,,0) -> 975.6 | C11: =_xlfn.XLOOKUP($A11,Inputs!$A:$A,Inputs!C:C,,0) -> 957.8 | D11: =_xlfn.XLOOKUP($A11,Inputs!$A:$A,Inputs!D:D,,0) -> 902.9 | E11: =_xlfn.XLOOKUP($A11,Inputs!$A:$A,Inputs!E:E,,0) -> 445.8 | F11: =_xlfn.XLOOKUP($A11,Inputs!$A:$A,Inputs!F:F,,0) -> 855.4 | G11: =_xlfn.XLOOKUP($A11,Inputs!$A:$A,Inputs!G:G,,0) -> 839.7 | H11: =_xlfn.XLOOKUP($A11,Inputs!$A:$A,Inputs!H:H,,0) -> 761 | I11: =_xlfn.XLOOKUP($A11,Inputs!$A:$A,Inputs!I:I,,0) -> 827.6 | J11: =_xlfn.XLOOKUP($A11,Inputs!$A:$A,Inputs!J:J,,0) -> 872.8 | K11: =_xlfn.XLOOKUP($A11,Inputs!$A:$A,Inputs!K:K,,0) -> 803.2 | L11: =_xlfn.XLOOKUP($A11,Inputs!$A:$A,Inputs!L:L,,0) -> 728.7 | M11: =_xlfn.XLOOKUP($A11,Inputs!$A:$A,Inputs!M:M,,0) -> 655.9
A12: Operating Margin | B12: =IFERROR(B11/B$5,"-") -> 0.17767256 | C12: =IFERROR(C11/C$5,"-") -> 0.19026619 | D12: =IFERROR(D11/D$5,"-") -> 0.19518364 | E12: =IFERROR(E11/E$5,"-") -> 0.12613173 | F12: =IFERROR(F11/F$5,"-") -> 0.20050631 | G12: =IFERROR(G11/G$5,"-") -> 0.20149254 | H12: =IFERROR(H11/H$5,"-") -> 0.18764641 | I12: =IFERROR(I11/I$5,"-") -> 0.20198667 | ... M12: =IFERROR(M11/M$5,"-") -> 0.18409678
A13: Growth vs. Previous year | B13: =IFERROR(B12/C12-1,"-") -> -0.066189557 | C13: =IFERROR(C12/D12-1,"-") -> -0.025193966 | D13: =IFERROR(D12/E12-1,"-") -> 0.54745863 | E13: =IFERROR(E12/F12-1,"-") -> -0.37093383 | F13: =IFERROR(F12/G12-1,"-") -> -0.0048946326 | G13: =IFERROR(G12/H12-1,"-") -> 0.073788417 | H13: =IFERROR(H12/I12-1,"-") -> -0.07099611 | I13: =IFERROR(I12/J12-1,"-") -> -0.033366018 | ... L13: =IFERROR(L12/M12-1,"-") -> 0.05835406 | M13: =IFERROR(M12/#REF!-1,"-") -> -
A14: Net Financial Cost | B14: =_xlfn.XLOOKUP($A14,Inputs!$A:$A,Inputs!B:B,,0) -> -80.7 | C14: =_xlfn.XLOOKUP($A14,Inputs!$A:$A,Inputs!C:C,,0) -> -72.2 | D14: =_xlfn.XLOOKUP($A14,Inputs!$A:$A,Inputs!D:D,,0) -> -82.3 | E14: =_xlfn.XLOOKUP($A14,Inputs!$A:$A,Inputs!E:E,,0) -> -102.1 | F14: =_xlfn.XLOOKUP($A14,Inputs!$A:$A,Inputs!F:F,,0) -> -105.4 | G14: =_xlfn.XLOOKUP($A14,Inputs!$A:$A,Inputs!G:G,,0) -> -107.5 | H14: =_xlfn.XLOOKUP($A14,Inputs!$A:$A,Inputs!H:H,,0) -> -33.8 | I14: =_xlfn.XLOOKUP($A14,Inputs!$A:$A,Inputs!I:I,,0) -> -37.5 | J14: =_xlfn.XLOOKUP($A14,Inputs!$A:$A,Inputs!J:J,,0) -> -31.1 | K14: =_xlfn.XLOOKUP($A14,Inputs!$A:$A,Inputs!K:K,,0) -> -29.9 | L14: =_xlfn.XLOOKUP($A14,Inputs!$A:$A,Inputs!L:L,,0) -> -27.6 | M14: =_xlfn.XLOOKUP($A14,Inputs!$A:$A,Inputs!M:M,,0) -> -28.6
A15: Other Expenses (Revenues) | B15: =_xlfn.XLOOKUP($A15,Inputs!$A:$A,Inputs!B:B,,0) -> 120.9 | C15: =_xlfn.XLOOKUP($A15,Inputs!$A:$A,Inputs!C:C,,0) -> -16.3 | D15: =_xlfn.XLOOKUP($A15,Inputs!$A:$A,Inputs!D:D,,0) -> 2.5 | E15: =_xlfn.XLOOKUP($A15,Inputs!$A:$A,Inputs!E:E,,0) -> -1.3 | F15: =_xlfn.XLOOKUP($A15,Inputs!$A:$A,Inputs!F:F,,0) -> -1.5 | G15: =_xlfn.XLOOKUP($A15,Inputs!$A:$A,Inputs!G:G,,0) -> 1.4 | H15: =_xlfn.XLOOKUP($A15,Inputs!$A:$A,Inputs!H:H,,0) -> -1.1 | I15: =_xlfn.XLOOKUP($A15,Inputs!$A:$A,Inputs!I:I,,0) -> 0.1 | J15: =_xlfn.XLOOKUP($A15,Inputs!$A:$A,Inputs!J:J,,0) -> -5.6 | K15: =_xlfn.XLOOKUP($A15,Inputs!$A:$A,Inputs!K:K,,0) -> 21.5 | L15: =_xlfn.XLOOKUP($A15,Inputs!$A:$A,Inputs!L:L,,0) -> -5.9 | M15: =_xlfn.XLOOKUP($A15,Inputs!$A:$A,Inputs!M:M,,0) -> 39.2
A16: EBIT | B16: =B11-B15 -> 854.7 | C16: =C11-C15 -> 974.1 | D16: =D11-D15 -> 900.4 | E16: =E11-E15 -> 447.1 | F16: =F11-F15 -> 856.9 | G16: =G11-G15 -> 838.3 | H16: =H11-H15 -> 762.1 | I16: =I11-I15 -> 827.5 | ... M16: =M11-M15 -> 616.7
A17: Depreciation & Amortization | B17: =_xlfn.XLOOKUP($A17,Inputs!$A:$A,Inputs!B:B,,0) -> 246.8 | C17: =_xlfn.XLOOKUP($A17,Inputs!$A:$A,Inputs!C:C,,0) -> 166.9 | D17: =_xlfn.XLOOKUP($A17,Inputs!$A:$A,Inputs!D:D,,0) -> 207.2 | E17: =_xlfn.XLOOKUP($A17,Inputs!$A:$A,Inputs!E:E,,0) -> 333.8 | F17: =_xlfn.XLOOKUP($A17,Inputs!$A:$A,Inputs!F:F,,0) -> 263 | G17: =_xlfn.XLOOKUP($A17,Inputs!$A:$A,Inputs!G:G,,0) -> 260.6 | H17: =_xlfn.XLOOKUP($A17,Inputs!$A:$A,Inputs!H:H,,0) -> 123 | I17: =_xlfn.XLOOKUP($A17,Inputs!$A:$A,Inputs!I:I,,0) -> 116.7 | J17: =_xlfn.XLOOKUP($A17,Inputs!$A:$A,Inputs!J:J,,0) -> 118 | K17: =_xlfn.XLOOKUP($A17,Inputs!$A:$A,Inputs!K:K,,0) -> 114.8 | L17: =_xlfn.XLOOKUP($A17,Inputs!$A:$A,Inputs!L:L,,0) -> 117.4 | M17: =_xlfn.XLOOKUP($A17,Inputs!$A:$A,Inputs!M:M,,0) -> 117.2
A18: Changes Net Working Capital | B18: =_xlfn.XLOOKUP($A18,Inputs!$A:$A,Inputs!B:B,,0) -> -22.5 | C18: =_xlfn.XLOOKUP($A18,Inputs!$A:$A,Inputs!C:C,,0) -> 270.1 | D18: =_xlfn.XLOOKUP($A18,Inputs!$A:$A,Inputs!D:D,,0) -> 282.5 | E18: =_xlfn.XLOOKUP($A18,Inputs!$A:$A,Inputs!E:E,,0) -> -435.4 | F18: =_xlfn.XLOOKUP($A18,Inputs!$A:$A,Inputs!F:F,,0) -> 341.2 | G18: =_xlfn.XLOOKUP($A18,Inputs!$A:$A,Inputs!G:G,,0) -> -251.4 | H18: =_xlfn.XLOOKUP($A18,Inputs!$A:$A,Inputs!H:H,,0) -> -56.7 | I18: =_xlfn.XLOOKUP($A18,Inputs!$A:$A,Inputs!I:I,,0) -> 480.6 | J18: =_xlfn.XLOOKUP($A18,Inputs!$A:$A,Inputs!J:J,,0) -> -48.6 | K18: =_xlfn.XLOOKUP($A18,Inputs!$A:$A,Inputs!K:K,,0) -> -1575.4 | L18: =_xlfn.XLOOKUP($A18,Inputs!$A:$A,Inputs!L:L,,0) -> 141.8 | M18: =_xlfn.XLOOKUP($A18,Inputs!$A:$A,Inputs!M:M,,0) -> 1887.5
A19: EBITDA | B19: =B11-B15+B17 -> 1101.5 | C19: =C11-C15+C17 -> 1141 | D19: =D11-D15+D17 -> 1107.6 | E19: =E11-E15+E17 -> 780.9 | F19: =F11-F15+F17 -> 1119.9 | G19: =G11-G15+G17 -> 1098.9 | H19: =H11-H15+H17 -> 885.1 | I19: =I11-I15+I17 -> 944.2 | ... M19: =M11-M15+M17 -> 733.9
A20: EBITDA Margin | B20: =IFERROR(B19/B$5,"-") -> 0.20060098 | C20: =IFERROR(C19/C$5,"-") -> 0.22665872 | D20: =IFERROR(D19/D$5,"-") -> 0.23943449 | E20: =IFERROR(E19/E$5,"-") -> 0.22094273 | F20: =IFERROR(F19/F$5,"-") -> 0.26250527 | G20: =IFERROR(G19/G$5,"-") -> 0.26368959 | H20: =IFERROR(H19/H$5,"-") -> 0.21824683 | I20: =IFERROR(I19/I$5,"-") -> 0.23044444 | ... M20: =IFERROR(M19/M$5,"-") -> 0.20598967
A21: Taxes | B21: =_xlfn.XLOOKUP($A21,Inputs!$A:$A,Inputs!B:B,,0) -> -215.3 | C21: =_xlfn.XLOOKUP($A21,Inputs!$A:$A,Inputs!C:C,,0) -> -158.6 | D21: =_xlfn.XLOOKUP($A21,Inputs!$A:$A,Inputs!D:D,,0) -> -145.6 | E21: =_xlfn.XLOOKUP($A21,Inputs!$A:$A,Inputs!E:E,,0) -> -55.7 | F21: =_xlfn.XLOOKUP($A21,Inputs!$A:$A,Inputs!F:F,,0) -> -138.3 | G21: =_xlfn.XLOOKUP($A21,Inputs!$A:$A,Inputs!G:G,,0) -> -134.5 | H21: =_xlfn.XLOOKUP($A21,Inputs!$A:$A,Inputs!H:H,,0) -> -134.3 | I21: =_xlfn.XLOOKUP($A21,Inputs!$A:$A,Inputs!I:I,,0) -> -154.9 | J21: =_xlfn.XLOOKUP($A21,Inputs!$A:$A,Inputs!J:J,,0) -> -169.3 | K21: =_xlfn.XLOOKUP($A21,Inputs!$A:$A,Inputs!K:K,,0) -> -159.9 | L21: =_xlfn.XLOOKUP($A21,Inputs!$A:$A,Inputs!L:L,,0) -> -142 | M21: =_xlfn.XLOOKUP($A21,Inputs!$A:$A,Inputs!M:M,,0) -> -157.9
A22: % Tax | B22: =IFERROR(B21/B$5,"-") -> -0.039209616 | C22: =IFERROR(C21/C$5,"-") -> -0.031505761 | D22: =IFERROR(D21/D$5,"-") -> -0.031474956 | E22: =IFERROR(E21/E$5,"-") -> -0.015759393 | F22: =IFERROR(F21/F$5,"-") -> -0.032417608 | G22: =IFERROR(G21/G$5,"-") -> -0.03227432 | H22: =IFERROR(H21/H$5,"-") -> -0.033115522 | I22: =IFERROR(I21/I$5,"-") -> -0.037805384 | ... M22: =IFERROR(M21/M$5,"-") -> -0.044319075
A23: Net Income | B23: =_xlfn.XLOOKUP($A23,Inputs!$A:$A,Inputs!B:B,,0) -> 800.5 | C23: =_xlfn.XLOOKUP($A23,Inputs!$A:$A,Inputs!C:C,,0) -> 710.7 | D23: =_xlfn.XLOOKUP($A23,Inputs!$A:$A,Inputs!D:D,,0) -> 677.5 | E23: =_xlfn.XLOOKUP($A23,Inputs!$A:$A,Inputs!E:E,,0) -> 286.7 | F23: =_xlfn.XLOOKUP($A23,Inputs!$A:$A,Inputs!F:F,,0) -> 610.2 | G23: =_xlfn.XLOOKUP($A23,Inputs!$A:$A,Inputs!G:G,,0) -> 599.1 | H23: =_xlfn.XLOOKUP($A23,Inputs!$A:$A,Inputs!H:H,,0) -> 591.8 | I23: =_xlfn.XLOOKUP($A23,Inputs!$A:$A,Inputs!I:I,,0) -> 635.3 | J23: =_xlfn.XLOOKUP($A23,Inputs!$A:$A,Inputs!J:J,,0) -> 666.8 | K23: =_xlfn.XLOOKUP($A23,Inputs!$A:$A,Inputs!K:K,,0) -> 634.9 | L23: =_xlfn.XLOOKUP($A23,Inputs!$A:$A,Inputs!L:L,,0) -> 553.2 | M23: =_xlfn.XLOOKUP($A23,Inputs!$A:$A,Inputs!M:M,,0) -> 508.6
A24: Net Income Margin | B24: =IFERROR(B23/B$5,"-") -> 0.14578401 | C24: =IFERROR(C23/C$5,"-") -> 0.14117998 | D24: =IFERROR(D23/D$5,"-") -> 0.14645799 | E24: =IFERROR(E23/E$5,"-") -> 0.081117021 | F24: =IFERROR(F23/F$5,"-") -> 0.14303127 | G24: =IFERROR(G23/G$5,"-") -> 0.1437587 | H24: =IFERROR(H23/H$5,"-") -> 0.14592529 | I24: =IFERROR(I23/I$5,"-") -> 0.15505333 | ... M24: =IFERROR(M23/M$5,"-") -> 0.14275289
A25: Growth vs. Previous year | B25: =IFERROR(B24/C24-1,"-") -> 0.032611098 | C25: =IFERROR(C24/D24-1,"-") -> -0.03603771 | D25: =IFERROR(D24/E24-1,"-") -> 0.80551485 | E25: =IFERROR(E24/F24-1,"-") -> -0.43287211 | F25: =IFERROR(F24/G24-1,"-") -> -0.0050600724 | G25: =IFERROR(G24/H24-1,"-") -> -0.014847243 | H25: =IFERROR(H24/I24-1,"-") -> -0.058870334 | I25: =IFERROR(I24/J24-1,"-") -> -0.028730886 | ... L25: =IFERROR(L24/M24-1,"-") -> 0.036157219 | M25: =IFERROR(M24/#REF!-1,"-") -> -
A26: Cash Generated | B26: =B39-C39 -> 83.3 | C26: =C39-D39 -> -328 | D26: =D39-E39 -> -175.2 | E26: =E39-F39 -> 521.6 | F26: =F39-G39 -> -69.7 | G26: =G39-H39 -> 102.8 | H26: =H39-I39 -> 3.8 | I26: =I39-J39 -> -16.6 | ... M26: =M39-N39 -> 136.3
A27: Dividends | B27: =_xlfn.XLOOKUP($A27,Inputs!$A:$A,Inputs!B:B,,0) -> -248.3 | C27: =_xlfn.XLOOKUP($A27,Inputs!$A:$A,Inputs!C:C,,0) -> -237.4 | D27: =_xlfn.XLOOKUP($A27,Inputs!$A:$A,Inputs!D:D,,0) -> -344.5 | E27: =_xlfn.XLOOKUP($A27,Inputs!$A:$A,Inputs!E:E,,0) -> 0 | F27: =_xlfn.XLOOKUP($A27,Inputs!$A:$A,Inputs!F:F,,0) -> -213.6 | G27: =_xlfn.XLOOKUP($A27,Inputs!$A:$A,Inputs!G:G,,0) -> -215.7 | H27: =_xlfn.XLOOKUP($A27,Inputs!$A:$A,Inputs!H:H,,0) -> -479.7 | I27: =_xlfn.XLOOKUP($A27,Inputs!$A:$A,Inputs!I:I,,0) -> -314.1 | J27: =_xlfn.XLOOKUP($A27,Inputs!$A:$A,Inputs!J:J,,0) -> -567.5 | K27: =_xlfn.XLOOKUP($A27,Inputs!$A:$A,Inputs!K:K,,0) -> -434.4 | L27: =_xlfn.XLOOKUP($A27,Inputs!$A:$A,Inputs!L:L,,0) -> -164.8 | M27: =_xlfn.XLOOKUP($A27,Inputs!$A:$A,Inputs!M:M,,0) -> -147.7
A28: Share buyback | B28: =_xlfn.XLOOKUP($A28,Inputs!$A:$A,Inputs!B:B,,0) -> -177.3 | C28: =_xlfn.XLOOKUP($A28,Inputs!$A:$A,Inputs!C:C,,0) -> -228.5 | D28: =_xlfn.XLOOKUP($A28,Inputs!$A:$A,Inputs!D:D,,0) -> -8.7 | E28: =_xlfn.XLOOKUP($A28,Inputs!$A:$A,Inputs!E:E,,0) -> -19.3 | F28: =_xlfn.XLOOKUP($A28,Inputs!$A:$A,Inputs!F:F,,0) -> -300.2 | G28: =_xlfn.XLOOKUP($A28,Inputs!$A:$A,Inputs!G:G,,0) -> -325 | H28: =_xlfn.XLOOKUP($A28,Inputs!$A:$A,Inputs!H:H,,0) -> -105.1 | I28: =_xlfn.XLOOKUP($A28,Inputs!$A:$A,Inputs!I:I,,0) -> -187.6 | J28: =_xlfn.XLOOKUP($A28,Inputs!$A:$A,Inputs!J:J,,0) -> -150.7 | K28: =_xlfn.XLOOKUP($A28,Inputs!$A:$A,Inputs!K:K,,0) -> -137.9 | L28: =_xlfn.XLOOKUP($A28,Inputs!$A:$A,Inputs!L:L,,0) -> -295.8 | M28: =_xlfn.XLOOKUP($A28,Inputs!$A:$A,Inputs!M:M,,0) -> -241.9
A29: Net Cash Flow | B29: =SUM(B26:B28) -> -342.3 | C29: =SUM(C26:C28) -> -793.9 | D29: =SUM(D26:D28) -> -528.4 | E29: =SUM(E26:E28) -> 502.3 | F29: =SUM(F26:F28) -> -583.5 | G29: =SUM(G26:G28) -> -437.9 | H29: =SUM(H26:H28) -> -581 | I29: =SUM(I26:I28) -> -518.3 | ... M29: =SUM(M26:M28) -> -253.3
A30: FNP'' | B30: =+B29-(B58-C29) -> -3052.9 | C30: =+C29-(C58-D29) -> -3238.3 | D30: =+D29-(D58-E29) -> -2087.6 | E30: =+E29-(E58-F29) -> -2523.1 | F30: =+F29-(F58-G29) -> -2258.8 | G30: =+G29-(G58-H29) -> -2301.4 | H30: =+H29-(H58-I29) -> -2187.8 | I30: =+I29-(I58-J29) -> -2394.5 | ... M30: =+M29-(M58-N29) -> -913.1
A31: FNP' | B31: =+B30+B33 -> -3206.1 | C31: =+C30+C33 -> -3333.7 | D31: =+D30+D33 -> -2121.9 | E31: =+E30+E33 -> -2525.5 | F31: =+F30+F33 -> -2261.8 | G31: =+G30+G33 -> -2301.4 | H31: =+H30+H33 -> -2187.4 | I31: =+I30+I33 -> -2394.5 | ... M31: =+M30+M33 -> -913.1
A32: Net Capex | B32: =_xlfn.XLOOKUP($A32,Inputs!$A:$A,Inputs!B:B,,0) -> -125.7 | C32: =_xlfn.XLOOKUP($A32,Inputs!$A:$A,Inputs!C:C,,0) -> -163.4 | D32: =_xlfn.XLOOKUP($A32,Inputs!$A:$A,Inputs!D:D,,0) -> -224.7 | E32: =_xlfn.XLOOKUP($A32,Inputs!$A:$A,Inputs!E:E,,0) -> -115.7 | F32: =_xlfn.XLOOKUP($A32,Inputs!$A:$A,Inputs!F:F,,0) -> -136.1 | G32: =_xlfn.XLOOKUP($A32,Inputs!$A:$A,Inputs!G:G,,0) -> -122.9 | H32: =_xlfn.XLOOKUP($A32,Inputs!$A:$A,Inputs!H:H,,0) -> -111.8 | I32: =_xlfn.XLOOKUP($A32,Inputs!$A:$A,Inputs!I:I,,0) -> -154.3 | J32: =_xlfn.XLOOKUP($A32,Inputs!$A:$A,Inputs!J:J,,0) -> -147.3 | K32: =_xlfn.XLOOKUP($A32,Inputs!$A:$A,Inputs!K:K,,0) -> -111.6 | L32: =_xlfn.XLOOKUP($A32,Inputs!$A:$A,Inputs!L:L,,0) -> -102.5 | M32: =_xlfn.XLOOKUP($A32,Inputs!$A:$A,Inputs!M:M,,0) -> -85.6
A33: Investments & Acquisitions | B33: =_xlfn.XLOOKUP($A33,Inputs!$A:$A,Inputs!B:B,,0) -> -153.2 | C33: =_xlfn.XLOOKUP($A33,Inputs!$A:$A,Inputs!C:C,,0) -> -95.4 | D33: =_xlfn.XLOOKUP($A33,Inputs!$A:$A,Inputs!D:D,,0) -> -34.3 | E33: =_xlfn.XLOOKUP($A33,Inputs!$A:$A,Inputs!E:E,,0) -> -2.4 | F33: =_xlfn.XLOOKUP($A33,Inputs!$A:$A,Inputs!F:F,,0) -> -3 | G33: =_xlfn.XLOOKUP($A33,Inputs!$A:$A,Inputs!G:G,,0) -> 0 | H33: =_xlfn.XLOOKUP($A33,Inputs!$A:$A,Inputs!H:H,,0) -> 0.4 | I33: =_xlfn.XLOOKUP($A33,Inputs!$A:$A,Inputs!I:I,,0) -> 0 | J33: =_xlfn.XLOOKUP($A33,Inputs!$A:$A,Inputs!J:J,,0) -> 0 | K33: =_xlfn.XLOOKUP($A33,Inputs!$A:$A,Inputs!K:K,,0) -> 0 | L33: =_xlfn.XLOOKUP($A33,Inputs!$A:$A,Inputs!L:L,,0) -> -0.1 | M33: =_xlfn.XLOOKUP($A33,Inputs!$A:$A,Inputs!M:M,,0) -> 0
A34: Capex + Investments | B34: =+B32+B33 -> -278.9 | C34: =+C32+C33 -> -258.8 | D34: =+D32+D33 -> -259 | E34: =+E32+E33 -> -118.1 | F34: =+F32+F33 -> -139.1 | G34: =+G32+G33 -> -122.9 | H34: =+H32+H33 -> -111.4 | I34: =+I32+I33 -> -154.3 | ... M34: =+M32+M33 -> -85.6
A35: Dividends + Share Buyback | B35: =+B27+B28 -> -425.6 | C35: =+C27+C28 -> -465.9 | D35: =+D27+D28 -> -353.2 | E35: =+E27+E28 -> -19.3 | F35: =+F27+F28 -> -513.8 | G35: =+G27+G28 -> -540.7 | H35: =+H27+H28 -> -584.8 | I35: =+I27+I28 -> -501.7 | ... M35: =+M27+M28 -> -389.6
A36: Payout Ratio | B36: =IFERROR(B35/B23,"-") -> -0.53166771 | C36: =IFERROR(C35/C23,"-") -> -0.65555087 | D36: =IFERROR(D35/D23,"-") -> -0.52132841 | E36: =IFERROR(E35/E23,"-") -> -0.067317754 | F36: =IFERROR(F35/F23,"-") -> -0.84201901 | G36: =IFERROR(G35/G23,"-") -> -0.90252045 | H36: =IFERROR(H35/H23,"-") -> -0.98817168 | I36: =IFERROR(I35/I23,"-") -> -0.78970565 | ... M36: =IFERROR(M35/M23,"-") -> -0.76602438
A38: Assets
A39: Cash & Eq. | B39: =_xlfn.XLOOKUP($A39,Inputs!$A:$A,Inputs!B:B,,0) -> 188.3 | C39: =_xlfn.XLOOKUP($A39,Inputs!$A:$A,Inputs!C:C,,0) -> 105 | D39: =_xlfn.XLOOKUP($A39,Inputs!$A:$A,Inputs!D:D,,0) -> 433 | E39: =_xlfn.XLOOKUP($A39,Inputs!$A:$A,Inputs!E:E,,0) -> 608.2 | F39: =_xlfn.XLOOKUP($A39,Inputs!$A:$A,Inputs!F:F,,0) -> 86.6 | G39: =_xlfn.XLOOKUP($A39,Inputs!$A:$A,Inputs!G:G,,0) -> 156.3 | H39: =_xlfn.XLOOKUP($A39,Inputs!$A:$A,Inputs!H:H,,0) -> 53.5 | I39: =_xlfn.XLOOKUP($A39,Inputs!$A:$A,Inputs!I:I,,0) -> 49.7 | J39: =_xlfn.XLOOKUP($A39,Inputs!$A:$A,Inputs!J:J,,0) -> 66.3 | K39: =_xlfn.XLOOKUP($A39,Inputs!$A:$A,Inputs!K:K,,0) -> 275.5 | L39: =_xlfn.XLOOKUP($A39,Inputs!$A:$A,Inputs!L:L,,0) -> 273.3 | M39: =_xlfn.XLOOKUP($A39,Inputs!$A:$A,Inputs!M:M,,0) -> 136.3
A40: Accounts Receivable | B40: =_xlfn.XLOOKUP($A40,Inputs!$A:$A,Inputs!B:B,,0) -> 1268.4 | C40: =_xlfn.XLOOKUP($A40,Inputs!$A:$A,Inputs!C:C,,0) -> 1254.4 | D40: =_xlfn.XLOOKUP($A40,Inputs!$A:$A,Inputs!D:D,,0) -> 1162.2 | E40: =_xlfn.XLOOKUP($A40,Inputs!$A:$A,Inputs!E:E,,0) -> 1027.5 | F40: =_xlfn.XLOOKUP($A40,Inputs!$A:$A,Inputs!F:F,,0) -> 1233.6 | G40: =_xlfn.XLOOKUP($A40,Inputs!$A:$A,Inputs!G:G,,0) -> 1206.7 | H40: =_xlfn.XLOOKUP($A40,Inputs!$A:$A,Inputs!H:H,,0) -> 1116.8 | I40: =_xlfn.XLOOKUP($A40,Inputs!$A:$A,Inputs!I:I,,0) -> 1001.5 | J40: =_xlfn.XLOOKUP($A40,Inputs!$A:$A,Inputs!J:J,,0) -> 941.9 | K40: =_xlfn.XLOOKUP($A40,Inputs!$A:$A,Inputs!K:K,,0) -> 728.9 | L40: =_xlfn.XLOOKUP($A40,Inputs!$A:$A,Inputs!L:L,,0) -> 692.4 | M40: =_xlfn.XLOOKUP($A40,Inputs!$A:$A,Inputs!M:M,,0) -> 610.1
A41: Inventory | B41: =_xlfn.XLOOKUP($A41,Inputs!$A:$A,Inputs!B:B,,0) -> 769 | C41: =_xlfn.XLOOKUP($A41,Inputs!$A:$A,Inputs!C:C,,0) -> 662.2 | D41: =_xlfn.XLOOKUP($A41,Inputs!$A:$A,Inputs!D:D,,0) -> 633 | E41: =_xlfn.XLOOKUP($A41,Inputs!$A:$A,Inputs!E:E,,0) -> 536.9 | F41: =_xlfn.XLOOKUP($A41,Inputs!$A:$A,Inputs!F:F,,0) -> 527.6 | G41: =_xlfn.XLOOKUP($A41,Inputs!$A:$A,Inputs!G:G,,0) -> 502.8 | H41: =_xlfn.XLOOKUP($A41,Inputs!$A:$A,Inputs!H:H,,0) -> 490.1 | I41: =_xlfn.XLOOKUP($A41,Inputs!$A:$A,Inputs!I:I,,0) -> 451.1 | J41: =_xlfn.XLOOKUP($A41,Inputs!$A:$A,Inputs!J:J,,0) -> 486.5 | K41: =_xlfn.XLOOKUP($A41,Inputs!$A:$A,Inputs!K:K,,0) -> 416.8 | L41: =_xlfn.XLOOKUP($A41,Inputs!$A:$A,Inputs!L:L,,0) -> 385.6 | M41: =_xlfn.XLOOKUP($A41,Inputs!$A:$A,Inputs!M:M,,0) -> 331.8
A42: Property, Plant and Equipment | B42: =_xlfn.XLOOKUP($A42,Inputs!$A:$A,Inputs!B:B,,0) -> 687.5 | C42: =_xlfn.XLOOKUP($A42,Inputs!$A:$A,Inputs!C:C,,0) -> 644.8 | D42: =_xlfn.XLOOKUP($A42,Inputs!$A:$A,Inputs!D:D,,0) -> 601.1 | E42: =_xlfn.XLOOKUP($A42,Inputs!$A:$A,Inputs!E:E,,0) -> 474.8 | F42: =_xlfn.XLOOKUP($A42,Inputs!$A:$A,Inputs!F:F,,0) -> 578.5 | G42: =_xlfn.XLOOKUP($A42,Inputs!$A:$A,Inputs!G:G,,0) -> 564.9 | H42: =_xlfn.XLOOKUP($A42,Inputs!$A:$A,Inputs!H:H,,0) -> 558.9 | I42: =_xlfn.XLOOKUP($A42,Inputs!$A:$A,Inputs!I:I,,0) -> 578.6 | J42: =_xlfn.XLOOKUP($A42,Inputs!$A:$A,Inputs!J:J,,0) -> 536.4 | K42: =_xlfn.XLOOKUP($A42,Inputs!$A:$A,Inputs!K:K,,0) -> 503.3 | L42: =_xlfn.XLOOKUP($A42,Inputs!$A:$A,Inputs!L:L,,0) -> 509.2 | M42: =_xlfn.XLOOKUP($A42,Inputs!$A:$A,Inputs!M:M,,0) -> 537.3
A43: Other Assets | B43: =_xlfn.XLOOKUP($A43,Inputs!$A:$A,Inputs!B:B,,0) -> 1038.5 | C43: =_xlfn.XLOOKUP($A43,Inputs!$A:$A,Inputs!C:C,,0) -> 1203 | D43: =_xlfn.XLOOKUP($A43,Inputs!$A:$A,Inputs!D:D,,0) -> 1106.3 | E43: =_xlfn.XLOOKUP($A43,Inputs!$A:$A,Inputs!E:E,,0) -> 1105.6 | F43: =_xlfn.XLOOKUP($A43,Inputs!$A:$A,Inputs!F:F,,0) -> 1242 | G43: =_xlfn.XLOOKUP($A43,Inputs!$A:$A,Inputs!G:G,,0) -> 1306.8 | H43: =_xlfn.XLOOKUP($A43,Inputs!$A:$A,Inputs!H:H,,0) -> 340.1 | I43: =_xlfn.XLOOKUP($A43,Inputs!$A:$A,Inputs!I:I,,0) -> 321.8 | J43: =_xlfn.XLOOKUP($A43,Inputs!$A:$A,Inputs!J:J,,0) -> 296.8 | K43: =_xlfn.XLOOKUP($A43,Inputs!$A:$A,Inputs!K:K,,0) -> 355.7 | L43: =_xlfn.XLOOKUP($A43,Inputs!$A:$A,Inputs!L:L,,0) -> 276.2 | M43: =_xlfn.XLOOKUP($A43,Inputs!$A:$A,Inputs!M:M,,0) -> 270.9
A44: Total Assets | B44: =_xlfn.XLOOKUP($A44,Inputs!$A:$A,Inputs!B:B,,0) -> 4724.3 | C44: =_xlfn.XLOOKUP($A44,Inputs!$A:$A,Inputs!C:C,,0) -> 3983.8 | D44: =_xlfn.XLOOKUP($A44,Inputs!$A:$A,Inputs!D:D,,0) -> 3981.8 | E44: =_xlfn.XLOOKUP($A44,Inputs!$A:$A,Inputs!E:E,,0) -> 3758 | F44: =_xlfn.XLOOKUP($A44,Inputs!$A:$A,Inputs!F:F,,0) -> 3673.3 | G44: =_xlfn.XLOOKUP($A44,Inputs!$A:$A,Inputs!G:G,,0) -> 3742.6 | H44: =_xlfn.XLOOKUP($A44,Inputs!$A:$A,Inputs!H:H,,0) -> 2561.5 | I44: =_xlfn.XLOOKUP($A44,Inputs!$A:$A,Inputs!I:I,,0) -> 2404.8 | J44: =_xlfn.XLOOKUP($A44,Inputs!$A:$A,Inputs!J:J,,0) -> 2330.1 | K44: =_xlfn.XLOOKUP($A44,Inputs!$A:$A,Inputs!K:K,,0) -> 2282.3 | L44: =_xlfn.XLOOKUP($A44,Inputs!$A:$A,Inputs!L:L,,0) -> 2144.6 | M44: =_xlfn.XLOOKUP($A44,Inputs!$A:$A,Inputs!M:M,,0) -> 1893.6
A47: Liabilities
A48: Current Liabilities | B48: =_xlfn.XLOOKUP($A48,Inputs!$A:$A,Inputs!B:B,,0) -> 1245.7 | C48: =_xlfn.XLOOKUP($A48,Inputs!$A:$A,Inputs!C:C,,0) -> 1093.3 | D48: =_xlfn.XLOOKUP($A48,Inputs!$A:$A,Inputs!D:D,,0) -> 1208.1 | E48: =_xlfn.XLOOKUP($A48,Inputs!$A:$A,Inputs!E:E,,0) -> 1196.8 | F48: =_xlfn.XLOOKUP($A48,Inputs!$A:$A,Inputs!F:F,,0) -> 949.8 | G48: =_xlfn.XLOOKUP($A48,Inputs!$A:$A,Inputs!G:G,,0) -> 1243.7 | H48: =_xlfn.XLOOKUP($A48,Inputs!$A:$A,Inputs!H:H,,0) -> 914.8 | I48: =_xlfn.XLOOKUP($A48,Inputs!$A:$A,Inputs!I:I,,0) -> 725 | J48: =_xlfn.XLOOKUP($A48,Inputs!$A:$A,Inputs!J:J,,0) -> 1170.6 | K48: =_xlfn.XLOOKUP($A48,Inputs!$A:$A,Inputs!K:K,,0) -> 886.6 | L48: =_xlfn.XLOOKUP($A48,Inputs!$A:$A,Inputs!L:L,,0) -> -834.5 | M48: =_xlfn.XLOOKUP($A48,Inputs!$A:$A,Inputs!M:M,,0) -> -816
A49: Short-Term Debt | B49: =_xlfn.XLOOKUP($A49,Inputs!$A:$A,Inputs!B:B,,0) -> 58.7 | C49: =_xlfn.XLOOKUP($A49,Inputs!$A:$A,Inputs!C:C,,0) -> 102.3 | D49: =_xlfn.XLOOKUP($A49,Inputs!$A:$A,Inputs!D:D,,0) -> 233.1 | E49: =_xlfn.XLOOKUP($A49,Inputs!$A:$A,Inputs!E:E,,0) -> 93.4 | F49: =_xlfn.XLOOKUP($A49,Inputs!$A:$A,Inputs!F:F,,0) -> 73.7 | G49: =_xlfn.XLOOKUP($A49,Inputs!$A:$A,Inputs!G:G,,0) -> 377.3 | H49: =_xlfn.XLOOKUP($A49,Inputs!$A:$A,Inputs!H:H,,0) -> 180 | I49: =_xlfn.XLOOKUP($A49,Inputs!$A:$A,Inputs!I:I,,0) -> 35.3 | J49: =_xlfn.XLOOKUP($A49,Inputs!$A:$A,Inputs!J:J,,0) -> 128.6 | K49: =_xlfn.XLOOKUP($A49,Inputs!$A:$A,Inputs!K:K,,0) -> 2.8 | L49: =_xlfn.XLOOKUP($A49,Inputs!$A:$A,Inputs!L:L,,0) -> 2.6 | M49: =_xlfn.XLOOKUP($A49,Inputs!$A:$A,Inputs!M:M,,0) -> 5.4
A50: Short-Term Leases | B50: =_xlfn.XLOOKUP($A50,Inputs!$A:$A,Inputs!B:B,,0) -> 167.8 | C50: =_xlfn.XLOOKUP($A50,Inputs!$A:$A,Inputs!C:C,,0) -> 146.2 | D50: =_xlfn.XLOOKUP($A50,Inputs!$A:$A,Inputs!D:D,,0) -> 162.6 | E50: =_xlfn.XLOOKUP($A50,Inputs!$A:$A,Inputs!E:E,,0) -> 170.1 | F50: =_xlfn.XLOOKUP($A50,Inputs!$A:$A,Inputs!F:F,,0) -> 0 | G50: =_xlfn.XLOOKUP($A50,Inputs!$A:$A,Inputs!G:G,,0) -> 0 | H50: =_xlfn.XLOOKUP($A50,Inputs!$A:$A,Inputs!H:H,,0) -> 0 | I50: =_xlfn.XLOOKUP($A50,Inputs!$A:$A,Inputs!I:I,,0) -> 0 | J50: =_xlfn.XLOOKUP($A50,Inputs!$A:$A,Inputs!J:J,,0) -> 0 | K50: =_xlfn.XLOOKUP($A50,Inputs!$A:$A,Inputs!K:K,,0) -> 0 | L50: =_xlfn.XLOOKUP($A50,Inputs!$A:$A,Inputs!L:L,,0) -> 0 | M50: =_xlfn.XLOOKUP($A50,Inputs!$A:$A,Inputs!M:M,,0) -> 0
A51: Other current liabilities | B51: =_xlfn.XLOOKUP($A51,Inputs!$A:$A,Inputs!B:B,,0) -> 86.1 | C51: =_xlfn.XLOOKUP($A51,Inputs!$A:$A,Inputs!C:C,,0) -> 53.7 | D51: =_xlfn.XLOOKUP($A51,Inputs!$A:$A,Inputs!D:D,,0) -> 14 | E51: =_xlfn.XLOOKUP($A51,Inputs!$A:$A,Inputs!E:E,,0) -> 378 | F51: =_xlfn.XLOOKUP($A51,Inputs!$A:$A,Inputs!F:F,,0) -> 284.1 | G51: =_xlfn.XLOOKUP($A51,Inputs!$A:$A,Inputs!G:G,,0) -> 270.1 | H51: =_xlfn.XLOOKUP($A51,Inputs!$A:$A,Inputs!H:H,,0) -> 154.6 | I51: =_xlfn.XLOOKUP($A51,Inputs!$A:$A,Inputs!I:I,,0) -> 73.9 | J51: =_xlfn.XLOOKUP($A51,Inputs!$A:$A,Inputs!J:J,,0) -> 368.5 | K51: =_xlfn.XLOOKUP($A51,Inputs!$A:$A,Inputs!K:K,,0) -> 247.3 | L51: =_xlfn.XLOOKUP($A51,Inputs!$A:$A,Inputs!L:L,,0) -> -1431.1 | M51: =_xlfn.XLOOKUP($A51,Inputs!$A:$A,Inputs!M:M,,0) -> -1358.6
A52: Non-current Liabilities | B52: =_xlfn.XLOOKUP($A52,Inputs!$A:$A,Inputs!B:B,,0) -> 1966.7 | C52: =_xlfn.XLOOKUP($A52,Inputs!$A:$A,Inputs!C:C,,0) -> 1730 | D52: =_xlfn.XLOOKUP($A52,Inputs!$A:$A,Inputs!D:D,,0) -> 1763.7 | E52: =_xlfn.XLOOKUP($A52,Inputs!$A:$A,Inputs!E:E,,0) -> 1900.3 | F52: =_xlfn.XLOOKUP($A52,Inputs!$A:$A,Inputs!F:F,,0) -> 2282 | G52: =_xlfn.XLOOKUP($A52,Inputs!$A:$A,Inputs!G:G,,0) -> 2132.7 | H52: =_xlfn.XLOOKUP($A52,Inputs!$A:$A,Inputs!H:H,,0) -> 1164.1 | I52: =_xlfn.XLOOKUP($A52,Inputs!$A:$A,Inputs!I:I,,0) -> 1169.3 | J52: =_xlfn.XLOOKUP($A52,Inputs!$A:$A,Inputs!J:J,,0) -> 847.7 | K52: =_xlfn.XLOOKUP($A52,Inputs!$A:$A,Inputs!K:K,,0) -> 1073.7 | L52: =_xlfn.XLOOKUP($A52,Inputs!$A:$A,Inputs!L:L,,0) -> -1023.9 | M52: =_xlfn.XLOOKUP($A52,Inputs!$A:$A,Inputs!M:M,,0) -> -792
A53: Long-Term Debt | B53: =_xlfn.XLOOKUP($A53,Inputs!$A:$A,Inputs!B:B,,0) -> 820.3 | C53: =_xlfn.XLOOKUP($A53,Inputs!$A:$A,Inputs!C:C,,0) -> 790.7 | D53: =_xlfn.XLOOKUP($A53,Inputs!$A:$A,Inputs!D:D,,0) -> 815.7 | E53: =_xlfn.XLOOKUP($A53,Inputs!$A:$A,Inputs!E:E,,0) -> 1163 | F53: =_xlfn.XLOOKUP($A53,Inputs!$A:$A,Inputs!F:F,,0) -> 1163.7 | G53: =_xlfn.XLOOKUP($A53,Inputs!$A:$A,Inputs!G:G,,0) -> 905.2 | H53: =_xlfn.XLOOKUP($A53,Inputs!$A:$A,Inputs!H:H,,0) -> 908.5 | I53: =_xlfn.XLOOKUP($A53,Inputs!$A:$A,Inputs!I:I,,0) -> 913.5 | J53: =_xlfn.XLOOKUP($A53,Inputs!$A:$A,Inputs!J:J,,0) -> 828.8 | K53: =_xlfn.XLOOKUP($A53,Inputs!$A:$A,Inputs!K:K,,0) -> 838.2 | L53: =_xlfn.XLOOKUP($A53,Inputs!$A:$A,Inputs!L:L,,0) -> 800.8 | M53: =_xlfn.XLOOKUP($A53,Inputs!$A:$A,Inputs!M:M,,0) -> 654.4
A54: Long-Term Leases | B54: =_xlfn.XLOOKUP($A54,Inputs!$A:$A,Inputs!B:B,,0) -> 869.9 | C54: =_xlfn.XLOOKUP($A54,Inputs!$A:$A,Inputs!C:C,,0) -> 877.1 | D54: =_xlfn.XLOOKUP($A54,Inputs!$A:$A,Inputs!D:D,,0) -> 894.9 | E54: =_xlfn.XLOOKUP($A54,Inputs!$A:$A,Inputs!E:E,,0) -> 1,015.8 | F54: =_xlfn.XLOOKUP($A54,Inputs!$A:$A,Inputs!F:F,,0) -> 0 | G54: =_xlfn.XLOOKUP($A54,Inputs!$A:$A,Inputs!G:G,,0) -> 0 | H54: =_xlfn.XLOOKUP($A54,Inputs!$A:$A,Inputs!H:H,,0) -> 0 | I54: =_xlfn.XLOOKUP($A54,Inputs!$A:$A,Inputs!I:I,,0) -> 0 | J54: =_xlfn.XLOOKUP($A54,Inputs!$A:$A,Inputs!J:J,,0) -> 0 | K54: =_xlfn.XLOOKUP($A54,Inputs!$A:$A,Inputs!K:K,,0) -> 0 | L54: =_xlfn.XLOOKUP($A54,Inputs!$A:$A,Inputs!L:L,,0) -> 0 | M54: =_xlfn.XLOOKUP($A54,Inputs!$A:$A,Inputs!M:M,,0) -> 0
A55: Other non-current liabilities | B55: =_xlfn.XLOOKUP($A55,Inputs!$A:$A,Inputs!B:B,,0) -> 276.5 | C55: =_xlfn.XLOOKUP($A55,Inputs!$A:$A,Inputs!C:C,,0) -> 62.2 | D55: =_xlfn.XLOOKUP($A55,Inputs!$A:$A,Inputs!D:D,,0) -> 948 | E55: =_xlfn.XLOOKUP($A55,Inputs!$A:$A,Inputs!E:E,,0) -> 737.3 | F55: =_xlfn.XLOOKUP($A55,Inputs!$A:$A,Inputs!F:F,,0) -> 1118.3 | G55: =_xlfn.XLOOKUP($A55,Inputs!$A:$A,Inputs!G:G,,0) -> 1227.5 | H55: =_xlfn.XLOOKUP($A55,Inputs!$A:$A,Inputs!H:H,,0) -> 255.6 | I55: =_xlfn.XLOOKUP($A55,Inputs!$A:$A,Inputs!I:I,,0) -> 255.8 | J55: =_xlfn.XLOOKUP($A55,Inputs!$A:$A,Inputs!J:J,,0) -> 18.9 | K55: =_xlfn.XLOOKUP($A55,Inputs!$A:$A,Inputs!K:K,,0) -> 235.5 | L55: =_xlfn.XLOOKUP($A55,Inputs!$A:$A,Inputs!L:L,,0) -> -1824.7 | M55: =_xlfn.XLOOKUP($A55,Inputs!$A:$A,Inputs!M:M,,0) -> -1446.4
A56: Total Liabilities | B56: =_xlfn.XLOOKUP($A56,Inputs!$A:$A,Inputs!B:B,,0) -> 3212.4 | C56: =_xlfn.XLOOKUP($A56,Inputs!$A:$A,Inputs!C:C,,0) -> 2823.3 | D56: =_xlfn.XLOOKUP($A56,Inputs!$A:$A,Inputs!D:D,,0) -> 2971.8 | E56: =_xlfn.XLOOKUP($A56,Inputs!$A:$A,Inputs!E:E,,0) -> 3097.1 | F56: =_xlfn.XLOOKUP($A56,Inputs!$A:$A,Inputs!F:F,,0) -> 3231.8 | G56: =_xlfn.XLOOKUP($A56,Inputs!$A:$A,Inputs!G:G,,0) -> 3376.4 | H56: =_xlfn.XLOOKUP($A56,Inputs!$A:$A,Inputs!H:H,,0) -> 2078.9 | I56: =_xlfn.XLOOKUP($A56,Inputs!$A:$A,Inputs!I:I,,0) -> 1894.3 | J56: =_xlfn.XLOOKUP($A56,Inputs!$A:$A,Inputs!J:J,,0) -> 2018.3 | K56: =_xlfn.XLOOKUP($A56,Inputs!$A:$A,Inputs!K:K,,0) -> 1960.3 | L56: =_xlfn.XLOOKUP($A56,Inputs!$A:$A,Inputs!L:L,,0) -> -1858.4 | M56: =_xlfn.XLOOKUP($A56,Inputs!$A:$A,Inputs!M:M,,0) -> -1608
A58: Total Debt | B58: 1916.7 | C58: 1916 | D58: 2061.5 | E58: 2441.9 | F58: =F49+F53+F50+F54 -> 1237.4 | G58: =G49+G53+G50+G54 -> 1282.5 | H58: =H49+H53+H50+H54 -> 1088.5 | I58: =I49+I53+I50+I54 -> 948.8 | J58: =J49+J53+J50+J54 -> 957.4 | K58: =K49+K53+K50+K54 -> 841 | L58: =L49+L53+L50+L54 -> 803.4 | M58: =M49+M53+M50+M54 -> 659.8
A59: Debt/Assets | B59: =IFERROR(B58/B44,"-") -> 0.4057109 | C59: =IFERROR(C58/C44,"-") -> 0.48094784 | D59: =IFERROR(D58/D44,"-") -> 0.51773067 | E59: =IFERROR(E58/E44,"-") -> 0.64978712 | F59: =IFERROR(F58/F44,"-") -> 0.33686331 | G59: =IFERROR(G58/G44,"-") -> 0.34267621 | H59: =IFERROR(H58/H44,"-") -> 0.42494632 | I59: =IFERROR(I58/I44,"-") -> 0.39454424 | ... M59: =IFERROR(M58/M44,"-") -> 0.34843684
A60: Net Debt | B60: =B58-B39 -> 1728.4 | C60: =C58-C39 -> 1811 | D60: =D58-D39 -> 1628.5 | E60: =E58-E39 -> 1833.7 | F60: =F58-F39 -> 1150.8 | G60: =G58-G39 -> 1126.2 | H60: =H58-H39 -> 1035 | I60: =I58-I39 -> 899.1 | ... M60: =M58-M39 -> 523.5
A62: Minority Interest | B62: =_xlfn.XLOOKUP($A62,Inputs!$A:$A,Inputs!B:B,,0) -> 126.9 | C62: =_xlfn.XLOOKUP($A62,Inputs!$A:$A,Inputs!C:C,,0) -> 4.6 | D62: =_xlfn.XLOOKUP($A62,Inputs!$A:$A,Inputs!D:D,,0) -> 0 | E62: =_xlfn.XLOOKUP($A62,Inputs!$A:$A,Inputs!E:E,,0) -> 0 | F62: =_xlfn.XLOOKUP($A62,Inputs!$A:$A,Inputs!F:F,,0) -> 0 | G62: =_xlfn.XLOOKUP($A62,Inputs!$A:$A,Inputs!G:G,,0) -> 0 | H62: =_xlfn.XLOOKUP($A62,Inputs!$A:$A,Inputs!H:H,,0) -> 0 | I62: =_xlfn.XLOOKUP($A62,Inputs!$A:$A,Inputs!I:I,,0) -> 0 | J62: =_xlfn.XLOOKUP($A62,Inputs!$A:$A,Inputs!J:J,,0) -> 0 | K62: =_xlfn.XLOOKUP($A62,Inputs!$A:$A,Inputs!K:K,,0) -> -0.1 | L62: =_xlfn.XLOOKUP($A62,Inputs!$A:$A,Inputs!L:L,,0) -> 0 | M62: =_xlfn.XLOOKUP($A62,Inputs!$A:$A,Inputs!M:M,,0) -> 0
A64: Shareholder's Equity | B64: =_xlfn.XLOOKUP($A64,Inputs!$A:$A,Inputs!B:B,,0) -> 1385 | C64: =_xlfn.XLOOKUP($A64,Inputs!$A:$A,Inputs!C:C,,0) -> 1155.9 | D64: =_xlfn.XLOOKUP($A64,Inputs!$A:$A,Inputs!D:D,,0) -> 1010 | E64: =_xlfn.XLOOKUP($A64,Inputs!$A:$A,Inputs!E:E,,0) -> 660.9 | F64: =_xlfn.XLOOKUP($A64,Inputs!$A:$A,Inputs!F:F,,0) -> 441.5 | G64: =_xlfn.XLOOKUP($A64,Inputs!$A:$A,Inputs!G:G,,0) -> 366.2 | H64: =_xlfn.XLOOKUP($A64,Inputs!$A:$A,Inputs!H:H,,0) -> 482.6 | I64: =_xlfn.XLOOKUP($A64,Inputs!$A:$A,Inputs!I:I,,0) -> 510.5 | J64: =_xlfn.XLOOKUP($A64,Inputs!$A:$A,Inputs!J:J,,0) -> 311.8 | K64: =_xlfn.XLOOKUP($A64,Inputs!$A:$A,Inputs!K:K,,0) -> 322.1 | L64: =_xlfn.XLOOKUP($A64,Inputs!$A:$A,Inputs!L:L,,0) -> 4003 | M64: =_xlfn.XLOOKUP($A64,Inputs!$A:$A,Inputs!M:M,,0) -> 3501.6
A66: Cash Flow
A67: Operating CF | B67: =_xlfn.XLOOKUP($A67,Inputs!$A:$A,Inputs!B:B,,0) -> 1120.3 | C67: =_xlfn.XLOOKUP($A67,Inputs!$A:$A,Inputs!C:C,,0) -> 798.8 | D67: =_xlfn.XLOOKUP($A67,Inputs!$A:$A,Inputs!D:D,,0) -> 971.4 | E67: =_xlfn.XLOOKUP($A67,Inputs!$A:$A,Inputs!E:E,,0) -> 824.8 | F67: =_xlfn.XLOOKUP($A67,Inputs!$A:$A,Inputs!F:F,,0) -> 927.2 | G67: =_xlfn.XLOOKUP($A67,Inputs!$A:$A,Inputs!G:G,,0) -> 868.8 | H67: =_xlfn.XLOOKUP($A67,Inputs!$A:$A,Inputs!H:H,,0) -> 615.2 | I67: =_xlfn.XLOOKUP($A67,Inputs!$A:$A,Inputs!I:I,,0) -> 699.5 | J67: =_xlfn.XLOOKUP($A67,Inputs!$A:$A,Inputs!J:J,,0) -> 608.3 | K67: =_xlfn.XLOOKUP($A67,Inputs!$A:$A,Inputs!K:K,,0) -> 743.2 | L67: =_xlfn.XLOOKUP($A67,Inputs!$A:$A,Inputs!L:L,,0) -> 614.8 | M67: =_xlfn.XLOOKUP($A67,Inputs!$A:$A,Inputs!M:M,,0) -> 659
A68: Investing CF | B68: =_xlfn.XLOOKUP($A68,Inputs!$A:$A,Inputs!B:B,,0) -> -334.4 | C68: =_xlfn.XLOOKUP($A68,Inputs!$A:$A,Inputs!C:C,,0) -> -271.4 | D68: =_xlfn.XLOOKUP($A68,Inputs!$A:$A,Inputs!D:D,,0) -> -292.5 | E68: =_xlfn.XLOOKUP($A68,Inputs!$A:$A,Inputs!E:E,,0) -> -130.9 | F68: =_xlfn.XLOOKUP($A68,Inputs!$A:$A,Inputs!F:F,,0) -> -139.1 | G68: =_xlfn.XLOOKUP($A68,Inputs!$A:$A,Inputs!G:G,,0) -> -125.9 | H68: =_xlfn.XLOOKUP($A68,Inputs!$A:$A,Inputs!H:H,,0) -> -112.2 | I68: =_xlfn.XLOOKUP($A68,Inputs!$A:$A,Inputs!I:I,,0) -> -154.3 | J68: =_xlfn.XLOOKUP($A68,Inputs!$A:$A,Inputs!J:J,,0) -> -139.3 | K68: =_xlfn.XLOOKUP($A68,Inputs!$A:$A,Inputs!K:K,,0) -> -106 | L68: =_xlfn.XLOOKUP($A68,Inputs!$A:$A,Inputs!L:L,,0) -> -102.6 | M68: =_xlfn.XLOOKUP($A68,Inputs!$A:$A,Inputs!M:M,,0) -> -85.7
A69: Net Capex | B69: =_xlfn.XLOOKUP($A69,Inputs!$A:$A,Inputs!B:B,,0) -> -125.7 | C69: =_xlfn.XLOOKUP($A69,Inputs!$A:$A,Inputs!C:C,,0) -> -163.4 | D69: =_xlfn.XLOOKUP($A69,Inputs!$A:$A,Inputs!D:D,,0) -> -224.7 | E69: =_xlfn.XLOOKUP($A69,Inputs!$A:$A,Inputs!E:E,,0) -> -115.7 | F69: =_xlfn.XLOOKUP($A69,Inputs!$A:$A,Inputs!F:F,,0) -> -136.1 | G69: =_xlfn.XLOOKUP($A69,Inputs!$A:$A,Inputs!G:G,,0) -> -122.9 | H69: =_xlfn.XLOOKUP($A69,Inputs!$A:$A,Inputs!H:H,,0) -> -111.8 | I69: =_xlfn.XLOOKUP($A69,Inputs!$A:$A,Inputs!I:I,,0) -> -154.3 | J69: =_xlfn.XLOOKUP($A69,Inputs!$A:$A,Inputs!J:J,,0) -> -147.3 | K69: =_xlfn.XLOOKUP($A69,Inputs!$A:$A,Inputs!K:K,,0) -> -111.6 | L69: =_xlfn.XLOOKUP($A69,Inputs!$A:$A,Inputs!L:L,,0) -> -102.5 | M69: =_xlfn.XLOOKUP($A69,Inputs!$A:$A,Inputs!M:M,,0) -> -85.6
A70: Investments & Acquisitions | B70: =_xlfn.XLOOKUP($A70,Inputs!$A:$A,Inputs!B:B,,0) -> -153.2 | C70: =_xlfn.XLOOKUP($A70,Inputs!$A:$A,Inputs!C:C,,0) -> -95.4 | D70: =_xlfn.XLOOKUP($A70,Inputs!$A:$A,Inputs!D:D,,0) -> -34.3 | E70: =_xlfn.XLOOKUP($A70,Inputs!$A:$A,Inputs!E:E,,0) -> -2.4 | F70: =_xlfn.XLOOKUP($A70,Inputs!$A:$A,Inputs!F:F,,0) -> -3 | G70: =_xlfn.XLOOKUP($A70,Inputs!$A:$A,Inputs!G:G,,0) -> 0 | H70: =_xlfn.XLOOKUP($A70,Inputs!$A:$A,Inputs!H:H,,0) -> 0.4 | I70: =_xlfn.XLOOKUP($A70,Inputs!$A:$A,Inputs!I:I,,0) -> 0 | J70: =_xlfn.XLOOKUP($A70,Inputs!$A:$A,Inputs!J:J,,0) -> 0 | K70: =_xlfn.XLOOKUP($A70,Inputs!$A:$A,Inputs!K:K,,0) -> 0 | L70: =_xlfn.XLOOKUP($A70,Inputs!$A:$A,Inputs!L:L,,0) -> -0.1 | M70: =_xlfn.XLOOKUP($A70,Inputs!$A:$A,Inputs!M:M,,0) -> 0
A71: Financing CF | B71: =_xlfn.XLOOKUP($A71,Inputs!$A:$A,Inputs!B:B,,0) -> -663.3 | C71: =_xlfn.XLOOKUP($A71,Inputs!$A:$A,Inputs!C:C,,0) -> -727.1 | D71: =_xlfn.XLOOKUP($A71,Inputs!$A:$A,Inputs!D:D,,0) -> -993.4 | E71: =_xlfn.XLOOKUP($A71,Inputs!$A:$A,Inputs!E:E,,0) -> -231.7 | F71: =_xlfn.XLOOKUP($A71,Inputs!$A:$A,Inputs!F:F,,0) -> -769.2 | G71: =_xlfn.XLOOKUP($A71,Inputs!$A:$A,Inputs!G:G,,0) -> -718.4 | H71: =_xlfn.XLOOKUP($A71,Inputs!$A:$A,Inputs!H:H,,0) -> -507.6 | I71: =_xlfn.XLOOKUP($A71,Inputs!$A:$A,Inputs!I:I,,0) -> -584.4 | J71: =_xlfn.XLOOKUP($A71,Inputs!$A:$A,Inputs!J:J,,0) -> -689.2 | K71: =_xlfn.XLOOKUP($A71,Inputs!$A:$A,Inputs!K:K,,0) -> -636.1 | L71: =_xlfn.XLOOKUP($A71,Inputs!$A:$A,Inputs!L:L,,0) -> -371.8 | M71: =_xlfn.XLOOKUP($A71,Inputs!$A:$A,Inputs!M:M,,0) -> -491.1
A72: Dividends | B72: =_xlfn.XLOOKUP($A72,Inputs!$A:$A,Inputs!B:B,,0) -> -248.3 | C72: =_xlfn.XLOOKUP($A72,Inputs!$A:$A,Inputs!C:C,,0) -> -237.4 | D72: =_xlfn.XLOOKUP($A72,Inputs!$A:$A,Inputs!D:D,,0) -> -344.5 | E72: =_xlfn.XLOOKUP($A72,Inputs!$A:$A,Inputs!E:E,,0) -> 0 | F72: =_xlfn.XLOOKUP($A72,Inputs!$A:$A,Inputs!F:F,,0) -> -213.6 | G72: =_xlfn.XLOOKUP($A72,Inputs!$A:$A,Inputs!G:G,,0) -> -215.7 | H72: =_xlfn.XLOOKUP($A72,Inputs!$A:$A,Inputs!H:H,,0) -> -479.7 | I72: =_xlfn.XLOOKUP($A72,Inputs!$A:$A,Inputs!I:I,,0) -> -314.1 | J72: =_xlfn.XLOOKUP($A72,Inputs!$A:$A,Inputs!J:J,,0) -> -567.5 | K72: =_xlfn.XLOOKUP($A72,Inputs!$A:$A,Inputs!K:K,,0) -> -434.4 | L72: =_xlfn.XLOOKUP($A72,Inputs!$A:$A,Inputs!L:L,,0) -> -164.8 | M72: =_xlfn.XLOOKUP($A72,Inputs!$A:$A,Inputs!M:M,,0) -> -147.7
A73: Share buyback | B73: =_xlfn.XLOOKUP($A73,Inputs!$A:$A,Inputs!B:B,,0) -> -177.3 | C73: =_xlfn.XLOOKUP($A73,Inputs!$A:$A,Inputs!C:C,,0) -> -228.5 | D73: =_xlfn.XLOOKUP($A73,Inputs!$A:$A,Inputs!D:D,,0) -> -8.7 | E73: =_xlfn.XLOOKUP($A73,Inputs!$A:$A,Inputs!E:E,,0) -> -19.3 | F73: =_xlfn.XLOOKUP($A73,Inputs!$A:$A,Inputs!F:F,,0) -> -300.2 | G73: =_xlfn.XLOOKUP($A73,Inputs!$A:$A,Inputs!G:G,,0) -> -325 | H73: =_xlfn.XLOOKUP($A73,Inputs!$A:$A,Inputs!H:H,,0) -> -105.1 | I73: =_xlfn.XLOOKUP($A73,Inputs!$A:$A,Inputs!I:I,,0) -> -187.6 | J73: =_xlfn.XLOOKUP($A73,Inputs!$A:$A,Inputs!J:J,,0) -> -150.7 | K73: =_xlfn.XLOOKUP($A73,Inputs!$A:$A,Inputs!K:K,,0) -> -137.9 | L73: =_xlfn.XLOOKUP($A73,Inputs!$A:$A,Inputs!L:L,,0) -> -295.8 | M73: =_xlfn.XLOOKUP($A73,Inputs!$A:$A,Inputs!M:M,,0) -> -241.9
A74: FX | B74: =_xlfn.XLOOKUP($A74,Inputs!$A:$A,Inputs!B:B,,0) -> 0 | C74: =_xlfn.XLOOKUP($A74,Inputs!$A:$A,Inputs!C:C,,0) -> 0 | D74: =_xlfn.XLOOKUP($A74,Inputs!$A:$A,Inputs!D:D,,0) -> 0 | E74: =_xlfn.XLOOKUP($A74,Inputs!$A:$A,Inputs!E:E,,0) -> 0 | F74: =_xlfn.XLOOKUP($A74,Inputs!$A:$A,Inputs!F:F,,0) -> 0 | G74: =_xlfn.XLOOKUP($A74,Inputs!$A:$A,Inputs!G:G,,0) -> 0 | H74: =_xlfn.XLOOKUP($A74,Inputs!$A:$A,Inputs!H:H,,0) -> 0 | I74: =_xlfn.XLOOKUP($A74,Inputs!$A:$A,Inputs!I:I,,0) -> 0 | J74: =_xlfn.XLOOKUP($A74,Inputs!$A:$A,Inputs!J:J,,0) -> 0 | K74: =_xlfn.XLOOKUP($A74,Inputs!$A:$A,Inputs!K:K,,0) -> 0 | L74: =_xlfn.XLOOKUP($A74,Inputs!$A:$A,Inputs!L:L,,0) -> 0 | M74: =_xlfn.XLOOKUP($A74,Inputs!$A:$A,Inputs!M:M,,0) -> 0
A75: Changes in cash | B75: =_xlfn.XLOOKUP($A75,Inputs!$A:$A,Inputs!B:B,,0) -> 122.6 | C75: =_xlfn.XLOOKUP($A75,Inputs!$A:$A,Inputs!C:C,,0) -> -199.7 | D75: =_xlfn.XLOOKUP($A75,Inputs!$A:$A,Inputs!D:D,,0) -> -314.5 | E75: =_xlfn.XLOOKUP($A75,Inputs!$A:$A,Inputs!E:E,,0) -> 462.2 | F75: =_xlfn.XLOOKUP($A75,Inputs!$A:$A,Inputs!F:F,,0) -> 18.9 | G75: =_xlfn.XLOOKUP($A75,Inputs!$A:$A,Inputs!G:G,,0) -> 24.5 | H75: =_xlfn.XLOOKUP($A75,Inputs!$A:$A,Inputs!H:H,,0) -> -4.6 | I75: =_xlfn.XLOOKUP($A75,Inputs!$A:$A,Inputs!I:I,,0) -> -39.2 | J75: =_xlfn.XLOOKUP($A75,Inputs!$A:$A,Inputs!J:J,,0) -> -220.2 | K75: =_xlfn.XLOOKUP($A75,Inputs!$A:$A,Inputs!K:K,,0) -> 1.1 | L75: =_xlfn.XLOOKUP($A75,Inputs!$A:$A,Inputs!L:L,,0) -> 140.4 | M75: =_xlfn.XLOOKUP($A75,Inputs!$A:$A,Inputs!M:M,,0) -> 82.2
A77: Other Data
A78: Number of employees | B78: =_xlfn.XLOOKUP($A78,Inputs!$A:$A,Inputs!B:B,,0) -> #N/A | C78: =_xlfn.XLOOKUP($A78,Inputs!$A:$A,Inputs!C:C,,0) -> #N/A | D78: =_xlfn.XLOOKUP($A78,Inputs!$A:$A,Inputs!D:D,,0) -> #N/A | E78: =_xlfn.XLOOKUP($A78,Inputs!$A:$A,Inputs!E:E,,0) -> #N/A | F78: =_xlfn.XLOOKUP($A78,Inputs!$A:$A,Inputs!F:F,,0) -> #N/A | G78: =_xlfn.XLOOKUP($A78,Inputs!$A:$A,Inputs!G:G,,0) -> #N/A | H78: =_xlfn.XLOOKUP($A78,Inputs!$A:$A,Inputs!H:H,,0) -> #N/A | I78: =_xlfn.XLOOKUP($A78,Inputs!$A:$A,Inputs!I:I,,0) -> #N/A | J78: =_xlfn.XLOOKUP($A78,Inputs!$A:$A,Inputs!J:J,,0) -> #N/A | K78: =_xlfn.XLOOKUP($A78,Inputs!$A:$A,Inputs!K:K,,0) -> #N/A | L78: =_xlfn.XLOOKUP($A78,Inputs!$A:$A,Inputs!L:L,,0) -> #N/A | M78: =_xlfn.XLOOKUP($A78,Inputs!$A:$A,Inputs!M:M,,0) -> #N/A
A79: Shares Outstanding | B79: =_xlfn.XLOOKUP($A79,Inputs!$A:$A,Inputs!B:B,,0) -> #N/A | C79: =_xlfn.XLOOKUP($A79,Inputs!$A:$A,Inputs!C:C,,0) -> #N/A | D79: =_xlfn.XLOOKUP($A79,Inputs!$A:$A,Inputs!D:D,,0) -> #N/A | E79: =_xlfn.XLOOKUP($A79,Inputs!$A:$A,Inputs!E:E,,0) -> #N/A | F79: =_xlfn.XLOOKUP($A79,Inputs!$A:$A,Inputs!F:F,,0) -> #N/A | G79: =_xlfn.XLOOKUP($A79,Inputs!$A:$A,Inputs!G:G,,0) -> #N/A | H79: =_xlfn.XLOOKUP($A79,Inputs!$A:$A,Inputs!H:H,,0) -> #N/A | I79: =_xlfn.XLOOKUP($A79,Inputs!$A:$A,Inputs!I:I,,0) -> #N/A | J79: =_xlfn.XLOOKUP($A79,Inputs!$A:$A,Inputs!J:J,,0) -> #N/A | K79: =_xlfn.XLOOKUP($A79,Inputs!$A:$A,Inputs!K:K,,0) -> #N/A | L79: =_xlfn.XLOOKUP($A79,Inputs!$A:$A,Inputs!L:L,,0) -> #N/A | M79: =_xlfn.XLOOKUP($A79,Inputs!$A:$A,Inputs!M:M,,0) -> #N/A
A80: Float | B80: =_xlfn.XLOOKUP($A80,Inputs!$A:$A,Inputs!B:B,,0) -> 0.88814229 | C80: =_xlfn.XLOOKUP($A80,Inputs!$A:$A,Inputs!C:C,,0) -> Yahoo finance | D80: =_xlfn.XLOOKUP($A80,Inputs!$A:$A,Inputs!D:D,,0) -> 0 | E80: =_xlfn.XLOOKUP($A80,Inputs!$A:$A,Inputs!E:E,,0) -> 0 | F80: =_xlfn.XLOOKUP($A80,Inputs!$A:$A,Inputs!F:F,,0) -> 0 | G80: =_xlfn.XLOOKUP($A80,Inputs!$A:$A,Inputs!G:G,,0) -> 0 | H80: =_xlfn.XLOOKUP($A80,Inputs!$A:$A,Inputs!H:H,,0) -> 0 | I80: =_xlfn.XLOOKUP($A80,Inputs!$A:$A,Inputs!I:I,,0) -> 0 | J80: =_xlfn.XLOOKUP($A80,Inputs!$A:$A,Inputs!J:J,,0) -> 0 | K80: =_xlfn.XLOOKUP($A80,Inputs!$A:$A,Inputs!K:K,,0) -> 0 | L80: =_xlfn.XLOOKUP($A80,Inputs!$A:$A,Inputs!L:L,,0) -> 0 | M80: =_xlfn.XLOOKUP($A80,Inputs!$A:$A,Inputs!M:M,,0) -> 0
A81: Insiders Own | B81: =_xlfn.XLOOKUP($A81,Inputs!$A:$A,Inputs!B:B,,0) -> 0.0699 | C81: =_xlfn.XLOOKUP($A81,Inputs!$A:$A,Inputs!C:C,,0) -> Yahoo finance | D81: =_xlfn.XLOOKUP($A81,Inputs!$A:$A,Inputs!D:D,,0) -> 0 | E81: =_xlfn.XLOOKUP($A81,Inputs!$A:$A,Inputs!E:E,,0) -> 0 | F81: =_xlfn.XLOOKUP($A81,Inputs!$A:$A,Inputs!F:F,,0) -> 0 | G81: =_xlfn.XLOOKUP($A81,Inputs!$A:$A,Inputs!G:G,,0) -> 0 | H81: =_xlfn.XLOOKUP($A81,Inputs!$A:$A,Inputs!H:H,,0) -> 0 | I81: =_xlfn.XLOOKUP($A81,Inputs!$A:$A,Inputs!I:I,,0) -> 0 | J81: =_xlfn.XLOOKUP($A81,Inputs!$A:$A,Inputs!J:J,,0) -> 0 | K81: =_xlfn.XLOOKUP($A81,Inputs!$A:$A,Inputs!K:K,,0) -> 0 | L81: =_xlfn.XLOOKUP($A81,Inputs!$A:$A,Inputs!L:L,,0) -> 0 | M81: =_xlfn.XLOOKUP($A81,Inputs!$A:$A,Inputs!M:M,,0) -> 0
A82: Fitch/ S&P Rating | B82: =_xlfn.XLOOKUP($A82,Inputs!$A:$A,Inputs!B:B,,0) -> BBB | C82: =_xlfn.XLOOKUP($A82,Inputs!$A:$A,Inputs!C:C,,0) -> 10-K | D82: =_xlfn.XLOOKUP($A82,Inputs!$A:$A,Inputs!D:D,,0) -> 0 | E82: =_xlfn.XLOOKUP($A82,Inputs!$A:$A,Inputs!E:E,,0) -> 0 | F82: =_xlfn.XLOOKUP($A82,Inputs!$A:$A,Inputs!F:F,,0) -> 0 | G82: =_xlfn.XLOOKUP($A82,Inputs!$A:$A,Inputs!G:G,,0) -> 0 | H82: =_xlfn.XLOOKUP($A82,Inputs!$A:$A,Inputs!H:H,,0) -> 0 | I82: =_xlfn.XLOOKUP($A82,Inputs!$A:$A,Inputs!I:I,,0) -> 0 | J82: =_xlfn.XLOOKUP($A82,Inputs!$A:$A,Inputs!J:J,,0) -> 0 | K82: =_xlfn.XLOOKUP($A82,Inputs!$A:$A,Inputs!K:K,,0) -> 0 | L82: =_xlfn.XLOOKUP($A82,Inputs!$A:$A,Inputs!L:L,,0) -> 0 | M82: =_xlfn.XLOOKUP($A82,Inputs!$A:$A,Inputs!M:M,,0) -> 0
A83: Dividend Yield | B83: =_xlfn.XLOOKUP($A83,Inputs!$A:$A,Inputs!B:B,,0) -> #N/A | C83: =_xlfn.XLOOKUP($A83,Inputs!$A:$A,Inputs!C:C,,0) -> #N/A | D83: =_xlfn.XLOOKUP($A83,Inputs!$A:$A,Inputs!D:D,,0) -> #N/A | E83: =_xlfn.XLOOKUP($A83,Inputs!$A:$A,Inputs!E:E,,0) -> #N/A | F83: =_xlfn.XLOOKUP($A83,Inputs!$A:$A,Inputs!F:F,,0) -> #N/A | G83: =_xlfn.XLOOKUP($A83,Inputs!$A:$A,Inputs!G:G,,0) -> #N/A | H83: =_xlfn.XLOOKUP($A83,Inputs!$A:$A,Inputs!H:H,,0) -> #N/A | I83: =_xlfn.XLOOKUP($A83,Inputs!$A:$A,Inputs!I:I,,0) -> #N/A | J83: =_xlfn.XLOOKUP($A83,Inputs!$A:$A,Inputs!J:J,,0) -> #N/A | K83: =_xlfn.XLOOKUP($A83,Inputs!$A:$A,Inputs!K:K,,0) -> #N/A | L83: =_xlfn.XLOOKUP($A83,Inputs!$A:$A,Inputs!L:L,,0) -> #N/A | M83: =_xlfn.XLOOKUP($A83,Inputs!$A:$A,Inputs!M:M,,0) -> #N/A
A84: Daily Volume in Millions of USD | B84: =_xlfn.XLOOKUP($A84,Inputs!$A:$A,Inputs!B:B,,0) -> 0 | C84: =_xlfn.XLOOKUP($A84,Inputs!$A:$A,Inputs!C:C,,0) -> Yahoo Finance | D84: =_xlfn.XLOOKUP($A84,Inputs!$A:$A,Inputs!D:D,,0) -> 0 | E84: =_xlfn.XLOOKUP($A84,Inputs!$A:$A,Inputs!E:E,,0) -> 0 | F84: =_xlfn.XLOOKUP($A84,Inputs!$A:$A,Inputs!F:F,,0) -> 0 | G84: =_xlfn.XLOOKUP($A84,Inputs!$A:$A,Inputs!G:G,,0) -> 0 | H84: =_xlfn.XLOOKUP($A84,Inputs!$A:$A,Inputs!H:H,,0) -> 0 | I84: =_xlfn.XLOOKUP($A84,Inputs!$A:$A,Inputs!I:I,,0) -> 0 | J84: =_xlfn.XLOOKUP($A84,Inputs!$A:$A,Inputs!J:J,,0) -> 0 | K84: =_xlfn.XLOOKUP($A84,Inputs!$A:$A,Inputs!K:K,,0) -> 0 | L84: =_xlfn.XLOOKUP($A84,Inputs!$A:$A,Inputs!L:L,,0) -> 0 | M84: =_xlfn.XLOOKUP($A84,Inputs!$A:$A,Inputs!M:M,,0) -> 0
B86: 2020 | C86: 2021 | D86: 2022
A87: Short % of Float | B87: 0 | C87: 0 | D87: 0
A88: EPS | B88: 0 | C88: 0 | D88: 0
A90: Corporate Bonds 3, 5 Y 10 | B90: Average Price | C90: Moody's | D90: YTM | E90: DIVISA
B91: =VLOOKUP($A91,Inputs!$A$5:$M$98,MATCH(B$4,Inputs!$B$5:$M$5,0)+1,FALSE) -> #N/A | C91: =VLOOKUP($A91,Inputs!$A$5:$M$98,MATCH(C$4,Inputs!$B$5:$M$5,0)+1,FALSE) -> #N/A | D91: =VLOOKUP($A91,Inputs!$A$5:$M$98,MATCH(D$4,Inputs!$B$5:$M$5,0)+1,FALSE) -> #N/A | E91: =VLOOKUP($A91,Inputs!$A$5:$M$98,MATCH(E$4,Inputs!$B$5:$M$5,0)+1,FALSE) -> #N/A

Sheet Inputs
G2: Figures in Millions of USD
G3: Company | H3: #VALUE!
D4: Report in millions
A5: RESULTS | B5: 2023 | C5: =B5-1 -> 2022 | D5: =C5-1 -> 2021 | E5: =D5-1 -> 2020 | F5: =E5-1 -> 2019 | G5: =F5-1 -> 2018 | H5: =G5-1 -> 2017 | I5: =H5-1 -> 2016 | J5: =I5-1 -> 2015 | ... M5: =L5-1 -> 2012 | Q5: Hoja | R5: Nombre campo Bloomberg | T5: Cambio de signo | Z5: 2016 | AA5: 2015 | AB5: 2014 | AC5: 2013 | AD5: 2012 | AE5: 2011 | AF5: 2010 | AG5: 2009
A6: Net Sales | B6: 5491 | C6: 5034 | D6: 4625.9 | E6: 3534.4 | F6: 4266.2 | G6: 4167.4 | H6: 4055.5 | I6: 4097.3 | J6: 4176.9 | K6: 3999.8 | L6: 3740 | M6: 3562.8 | N6: Income Statement | O6: Sales | Q6: Ingreso | R6: Ingreso | Z6: 38537 | AA6: 47011 | AB6: 55184 | AC6: 55656 | AD6: 65875 | AE6: 60138 | AF6: 42588 | AG6: 32396
A7: Gross Profit | B7: 2420.5 | C7: 2175.3 | D7: 1972 | E7: 1247.9 | F7: 1640.5 | G7: 1552.5 | H7: 1356.2 | I7: 1386.6 | J7: 1452.7 | K7: 1343.4 | L7: 1240.1 | M7: 1125.8 | N7: Income Statement | O7: =+A7 -> Gross Profit | Q7: Ingreso | R7: + Coste de bienes y servicios | Z7: =Z6-28044 -> 10493 | AA7: =AA6-33546 -> 13465 | AB7: =AB6-40718 -> 14466 | AC7: =AC6-40727 -> 14929 | AD7: =+AD6-47055 -> 18820 | AE7: =+AE6-43578 -> 16560 | AF7: =+AF6-30367 -> 12221 | AG7: =+AG6-23886 -> 8510
A8: Operating Income | B8: =987.9-12.3 -> 975.6 | C8: =941.5+16.3 -> 957.8 | D8: =905.4-2.5 -> 902.9 | E8: =444.5+1.3 -> 445.8 | F8: =853.9+1.5 -> 855.4 | G8: =841.1-1.4 -> 839.7 | H8: =759.9+1.1 -> 761 | I8: =827.7-0.1 -> 827.6 | J8: =867.2+5.6 -> 872.8 | K8: =812.1-8.9 -> 803.2 | L8: =722.8+5.9 -> 728.7 | M8: =695.1-39.2 -> 655.9 | N8: Income Statement | O8: Operating Income | Q8: Ingreso | R8: + Ventas, generales y admin | Z8: =Z7-4383 -> 6110 | AA8: =AA7-4951 -> 8514 | AB8: =AB7-6529 -> 7937 | AC8: =AC7-5547 -> 9382 | AD8: =AD7-5919-2466-797-580-485 -> 8573 | AE8: =+AE7-5203-2297-826-1081 -> 7153 | AF8: =+AF7-4248-1905-914-1191 -> 3963 | AG8: =+AG7-3645-1421-1045-1822 -> 577
A9: Other Expenses (Revenues) | B9: =108.6+12.3 -> 120.9 | C9: -16.3 | D9: 2.5 | E9: -1.3 | F9: -1.5 | G9: 1.4 | H9: -1.1 | I9: 0.1 | J9: -5.6 | K9: =8.9+12.6 -> 21.5 | L9: -5.9 | M9: 39.2 | N9: Income Statement | O9: investment income+other income expense+income loss+minority interest+non controlling interest+share onf net profit+gain8losses) on equity investments+share of result from associates nd joint ventures+non operating profit+ | Q9: Ingreso | R9: + Investigación y desarrollo | S9: + Coste de financiación de beneficio | T9: + Otro gasto operativo | U9: - Beneficio (pérdida) de filiales | V9: - Minoritarios | Z9: =1853+596+595+1904+6+8 -> 4962 | AA9: =2119+587+2023+11 -> 4740 | AB9: =2380+624+1619-8+16 -> 4631 | AC9: =2046+727+981+6+14 -> 3774 | AD9: =-14+41 -> 27 | AE9: 53 | AF9: =58+24 -> 82 | AG9: =12-68 -> -56
A10: Net Financial Cost | B10: -80.7 | C10: -72.2 | D10: -82.3 | E10: -102.1 | F10: -105.4 | G10: -107.5 | H10: -33.8 | I10: -37.5 | J10: -31.1 | K10: -29.9 | L10: -27.6 | M10: -28.6 | N10: Income Statement | O10: interest expense+financial income and expenses+other financial expense-income+interest and other net+ | Q10: Ingreso | R10: - Ingreso (pérdida) no operacional | Z10: =505+518 -> 1023 | AA10: =507-161 -> 346 | AB10: =484-322 -> 162 | AC10: =465+35 -> 500 | AD10: =467-130 -> 337 | AE10: =396+32 -> 428 | AF10: =343-130 -> 213 | AG10: =389-381 -> 8
A11: Taxes | B11: -215.3 | C11: -158.6 | D11: -145.6 | E11: -55.7 | F11: -138.3 | G11: -134.5 | H11: -134.3 | I11: -154.9 | J11: -169.3 | K11: -159.9 | L11: -142 | M11: -157.9 | N11: Income Statement | O11: Taxes | Q11: Ingreso | R11: - Gasto de impuesto a la renta (Beneficio) | Z11: 192 | AA11: 916 | AB11: 692 | AC11: 1319 | AD11: =2528 -> 2528 | AE11: =1720 -> 1720 | AF11: =968 -> 968 | AG11: =-270 -> -270
A12: Net Income | B12: 800.5 | C12: 710.7 | D12: 677.5 | E12: 286.7 | F12: 610.2 | G12: 599.1 | H12: 591.8 | I12: 635.3 | J12: 666.8 | K12: 634.9 | L12: 553.2 | M12: 508.6 | N12: Income Statement | O12: Net Income | Q12: Flujo de caja | R12: + Ingreso neto | Z12: -67 | AA12: 2512 | AB12: 2452 | AC12: 3789 | AD12: 5681 | AE12: =4928+24 -> 4952 | AF12: 2700 | AG12: 895
B13: =SUM(B8:B11) -> 800.5 | C13: =SUM(C8:C11) -> 710.7 | D13: =SUM(D8:D11) -> 677.5 | E13: =SUM(E8:E11) -> 286.7 | F13: =SUM(F8:F11) -> 610.2 | G13: =SUM(G8:G11) -> 599.1 | H13: =SUM(H8:H11) -> 591.8 | I13: =SUM(I8:I11) -> 635.3 | ... M13: =SUM(M8:M11) -> 508.6 | Z13: =Z8-Z10-Z9-Z11 -> -67 | AA13: =AA8-AA10-AA9-AA11 -> 2512 | AB13: =AB8-AB10-AB9-AB11 -> 2452 | AC13: =AC8-AC10-AC9-AC11 -> 3789 | AD13: =AD8-AD10-AD9-AD11 -> 5681 | AE13: =AE8-AE10-AE9-AE11 -> 4952 | AF13: =AF8-AF10-AF9-AF11 -> 2700 | AG13: =AG8-AG10-AG9-AG11 -> 895
A14: FINANCIAL POSITION | B14: =B12-B13 -> 0 | C14: =C12-C13 -> 0 | D14: =D12-D13 -> 0 | E14: =E12-E13 -> 0 | F14: =F12-F13 -> 0 | G14: =G12-G13 -> 0 | H14: =H12-H13 -> 0 | I14: =I12-I13 -> 0 | ... M14: =M12-M13 -> 0 | Z14: =Z12-Z13 -> 0 | AA14: =AA12-AA13 -> 0 | AB14: =AB12-AB13 -> 0 | AC14: =AC12-AC13 -> 0 | AD14: =AD12-AD13 -> 0 | AE14: =AE12-AE13 -> 0 | AF14: =AF12-AF13 -> 0 | AG14: =AG12-AG13 -> 0
A16: Weighted Average Shares (Basic NI) | B16: 121.3 | C16: 124.1 | D16: 127.6 | E16: 128.4 | F16: 129.2 | G16: 135.6 | H16: 142 | I16: 144 | J16: 148 | K16: 148.3 | L16: 151.1 | M16: 158.9
A17: Weighted Average Shares (Diluted NI) | B17: 122.4 | C17: 124.7 | D17: 129.3 | E17: 129.2 | F17: 130.2 | G17: 136.3 | H17: 142.4 | I17: 145 | J17: 150.5 | K17: 151.9 | L17: 155.6 | M17: 163.2
A19: Net gains (losses) from ForEx | B19: -3.8 | C19: 1.2 | D19: -2.4 | E19: -2.5 | F19: 2 | G19: -5.3 | H19: 7.8 | I19: 0.3 | J19: -3.1 | K19: -6.6 | L19: 3 | M19: 0
A20: Total Comprehensive Income | B20: 719.6 | C20: 771.5 | D20: 746.9 | E20: 226 | F20: 622.3 | G20: 669.9 | H20: 566.5 | I20: 630.2 | J20: 657.9 | K20: 660.2 | L20: 525.6 | M20: 492.6
A22: Changes Net Working Capital | B22: =B23-C23 -> -22.5 | C22: =C23-D23 -> 270.1 | D22: =D23-E23 -> 282.5 | E22: =E23-F23 -> -435.4 | F22: =F23-G23 -> 341.2 | G22: =G23-H23 -> -251.4 | H22: =H23-I23 -> -56.7 | I22: =I23-J23 -> 480.6 | ... M22: =M23-N23 -> 1887.5 | N22: cash flows | O22: NWC | Q22: Flujo de caja
A23: Net Working Capital | B23: =B27-B42-B28 -> 1013.7 | C23: =C27-C42-C28 -> 1036.2 | D23: =D27-D42-D28 -> 766.1 | E23: =E27-E42-E28 -> 483.6 | F23: =F27-F42-F28 -> 919 | G23: =G27-G42-G28 -> 577.8 | H23: =H27-H42-H28 -> 829.2 | I23: =I27-I42-I28 -> 885.9 | ... M23: =M27-M42-M28 -> 1887.5
A24: 2625 | B24: 2625 | C24: 2625 | D24: 2625 | E24: 2625 | F24: 2625 | G24: 2625 | H24: 2625 | I24: 2625 | J24: 2625 | K24: 2625 | L24: 2625 | M24: 2625 | N24: 2625 | Q24: Flujo de caja | R24: + Dividendos pagados | T24: Cambiar signo | Z24: 1799 | AA24: 1757 | AB24: 1620 | AC24: 1111 | AD24: 1617 | AE24: 1159 | AF24: 1084 | AG24: 1029
A25: BALANCE SHEET | B25: 2625 | C25: 2625 | D25: 2625 | E25: 2625 | F25: 2625 | G25: 2625 | H25: 2625 | I25: 2625 | J25: 2625 | K25: 2625 | L25: 2625 | M25: 2625 | N25: 2625 | Q25: Flujo de caja | R25: + Aumento en capital | S25: + Baja en capital | T25: Cambiar signo y hacer suma | Z25: 23 | AA25: =-33+2025 -> 1992 | AB25: 3817 | AC25: 1776 | AD25: -244 | AE25: -312 | AF25: -449 | AG25: -110
A26: ASSETS | N26: 1922 | O26: 2625
A27: Current | B27: 2447.7 | C27: 2234.5 | D27: 2407.2 | E27: 2288.6 | F27: 1955.4 | G27: 1977.8 | H27: 1797.5 | I27: 1660.6 | J27: 1642.2 | K27: 1616 | L27: 1468.1 | M27: 1207.8
A28: Cash & Eq. | B28: 188.3 | C28: 105 | D28: 433 | E28: 608.2 | F28: 86.6 | G28: 156.3 | H28: 53.5 | I28: 49.7 | J28: 66.3 | K28: 275.5 | L28: 273.3 | M28: 136.3 | N28: Balance Sheet | O28: Cash & Eq.
A29: Accounts Receivable | B29: =1333.3-64.9 -> 1268.4 | C29: =1297.3-42.9 -> 1254.4 | D29: =1187.1-24.9 -> 1162.2 | E29: =1041.5-14 -> 1027.5 | F29: =1260-26.4 -> 1233.6 | G29: =1230.5-23.8 -> 1206.7 | H29: =1138.5-21.7 -> 1116.8 | I29: =1025.1-23.6 -> 1001.5 | J29: =1050.5-86.1-22.5 -> 941.9 | K29: =844.3-89.9-25.5 -> 728.9 | L29: =808-94-21.6 -> 692.4 | M29: =718.1-86.8-21.2 -> 610.1 | N29: Balance Sheet | O29: Accounts Receivable
A30: Inventory | B30: 769 | C30: 662.2 | D30: 633 | E30: 536.9 | F30: 527.6 | G30: 502.8 | H30: 490.1 | I30: 451.1 | J30: 486.5 | K30: 416.8 | L30: 385.6 | M30: 331.8 | N30: Balance Sheet | O30: Inventory | Q30: Balance | R30: + Efectivo, equivalentes y STI | Z30: 7168 | AA30: 6460 | AB30: 7341 | AC30: 6081 | AD30: 5490 | AE30: 3057 | AF30: 3592 | AG30: 4867
A31: Other Current Assets | B31: =B27-SUM(B28:B30) -> 222 | C31: =C27-SUM(C28:C30) -> 875.1 | D31: =D27-SUM(D28:D30) -> 179 | E31: =E27-SUM(E28:E30) -> 116 | F31: =F27-SUM(F28:F30) -> 107.6 | G31: =G27-SUM(G28:G30) -> 112 | H31: =H27-SUM(H28:H30) -> 137.1 | I31: =I27-SUM(I28:I30) -> 158.3 | ... M31: =M27-SUM(M28:M30) -> 129.6 | N31: Balance Sheet | O31: Inventory | Q31: Balance | R31: + Cuentas y notas por cobrar | S31: + Activos derivados y de cobertura | T31: + Inversiones y cuentas por cobrar a LP | Z31: =5981+8522+1029+13556 -> 29088 | AA31: =6695+8991+1170+13651 -> 30507 | AB31: =7737+9027+1364+14644 -> 32772 | AC31: 33499 | AD31: 33911 | AE31: 31031 | AF31: 28849 | AG31: 27162
A32: Non-current | B32: =B38-B27 -> 2276.6 | C32: =C38-C27 -> 1749.3 | D32: =D38-D27 -> 1574.6 | E32: =E38-E27 -> 1469.4 | F32: =F38-F27 -> 1717.9 | G32: =G38-G27 -> 1764.8 | H32: =H38-H27 -> 764 | I32: =I38-I27 -> 744.2 | ... M32: =M38-M27 -> 685.8
A33: Property, Plant and Equipment | B33: 687.5 | C33: 644.8 | D33: 601.1 | E33: 474.8 | F33: 578.5 | G33: 564.9 | H33: 558.9 | I33: 578.6 | J33: 536.4 | K33: 503.3 | L33: 509.2 | M33: 537.3 | Q33: Balance | R33: + Inventarios | Z33: 8614 | AA33: 9700 | AB33: 12205 | AC33: 12625 | AD33: 15547 | AE33: 14544 | AF33: 9587 | AG33: 6360
A34: Operating leases | B34: 734.6 | C34: 662 | D34: 639.1 | E34: 720.1 | F34: 852.7 | G34: 943.8 | H34: 0 | I34: 0 | J34: 0 | K34: 0 | L34: 0 | M34: 0
A35: Equity Method Investments | B35: 38 | C35: 114.6 | D35: 46.2 | E35: 5 | F35: 5 | G35: 5.1 | H35: 2.1 | I35: 2.1 | J35: 2.2 | K35: 2.1 | L35: 7.9 | M35: 7.2
A36: Other Non-Current Assets | B36: =B32-SUM(B33:B35) -> 816.5 | C36: =C32-SUM(C33:C35) -> 327.9 | D36: =D32-SUM(D33:D35) -> 927.3 | E36: =E32-SUM(E33:E35) -> 989.6 | F36: =F32-SUM(F33:F35) -> 1134.4 | G36: =G32-SUM(G33:G35) -> 1194.8 | H36: =H32-SUM(H33:H35) -> 203 | I36: =I32-SUM(I33:I35) -> 163.5 | ... M36: =M32-SUM(M33:M35) -> 141.3 | N36: Balance Sheet | O36: Property, Plant and Equipment
A37: Other Assets | B37: =B31+B36 -> 1038.5 | C37: =C31+C36 -> 1203 | D37: =D31+D36 -> 1106.3 | E37: =E31+E36 -> 1105.6 | F37: =F31+F36 -> 1242 | G37: =G31+G36 -> 1306.8 | H37: =H31+H36 -> 340.1 | I37: =I31+I36 -> 321.8 | ... M37: =M31+M36 -> 270.9 | N37: Balance Sheet
A38: Total Assets | B38: 4724.3 | C38: 3983.8 | D38: 3981.8 | E38: 3758 | F38: 3673.3 | G38: 3742.6 | H38: 2561.5 | I38: 2404.8 | J38: 2330.1 | K38: 2282.3 | L38: 2144.6 | M38: 1893.6 | N38: Balance Sheet | O38: Total Assets | Q38: Balance | R38: + Propiedad, planta y equipo; neto | Z38: 15322 | AA38: 16090 | AB38: =16577 -> 16577 | AC38: 17075 | AD38: 16461 | AE38: 14395 | AF38: 12539 | AG38: 12386
N39: Balance Sheet | Z39: =Z40-SUM(Z30:Z38) -> 14512 | AA39: =AA40-SUM(AA30:AA38) -> 15585 | AB39: =AB40-SUM(AB30:AB38) -> 15786 | AC39: =AC40-SUM(AC30:AC38) -> 15616 | AD39: =AD40-SUM(AD30:AD38) -> 17947 | AE39: =AE40-SUM(AE30:AE38) -> 18419 | AF39: =AF40-SUM(AF30:AF38) -> 9453 | AG39: =AG40-SUM(AG30:AG38) -> 9263
N40: Balance Sheet | Q40: Balance | R40: Activos totales | Z40: 74704 | AA40: 78342 | AB40: 84681 | AC40: 84896 | AD40: 89356 | AE40: 81446 | AF40: 64020 | AG40: 60038
A41: LIABILITIES | N41: Balance Sheet
A42: Current Liabilities | B42: 1245.7 | C42: 1093.3 | D42: 1208.1 | E42: 1196.8 | F42: 949.8 | G42: 1243.7 | H42: 914.8 | I42: 725 | J42: 1170.6 | K42: 886.6 | L42: -834.5 | M42: -816 | N42: Balance Sheet | O42: Current Liabilities
A43: Payables | B43: 991.8 | C43: 791.1 | D43: 798.4 | E43: 555.3 | F43: 592 | G43: 596.3 | H43: 580.2 | I43: 615.8 | J43: 673.5 | K43: 636.5 | L43: 594 | M43: 537.2
A44: Short-Term Debt | B44: 58.7 | C44: 102.3 | D44: 233.1 | E44: 93.4 | F44: 73.7 | G44: 377.3 | H44: 180 | I44: 35.3 | J44: 128.6 | K44: 2.8 | L44: 2.6 | M44: 5.4 | N44: Balance Sheet | O44: Short term Debt | Q44: Balance | R44: Pasivos totales corrientes | Z44: 26132 | AA44: 26242 | AB44: 27877 | AC44: 27297 | AD44: 29415 | AE44: =93+3895+8161+3386+2410+2691+298+1967+558+5102 -> 28561 | AF44: =204+3852+5856+2880+1670+1831+281+1521+495+3430 -> 22020 | AG44: =433+3650+2993+3351+797+1217+262+888+302+5399 -> 19292
A45: Short-Term Leases | B45: 167.8 | C45: 146.2 | D45: 162.6 | E45: 170.1 | F45: 0 | G45: 0 | H45: 0 | I45: 0 | J45: 0 | K45: 0 | L45: 0 | M45: 0
A46: Other current liabilities | B46: =B42-SUM(B43:B45) -> 86.1 | C46: =C42-SUM(C43:C45) -> 53.7 | D46: =D42-SUM(D43:D45) -> 14 | E46: =E42-SUM(E43:E45) -> 378 | F46: =F42-SUM(F43:F45) -> 284.1 | G46: =G42-SUM(G43:G45) -> 270.1 | H46: =H42-SUM(H43:H45) -> 154.6 | I46: =I42-SUM(I43:I45) -> 73.9 | ... M46: =M42-SUM(M43:M45) -> -1358.6 | N46: Balance Sheet | R46: + Préstamos CP | Z46: 7303 | AA46: 6967 | AB46: 4708 | AC46: 3679 | AD46: 5287 | AE46: 5660 | AF46: 3925 | AG46: 5701
A47: Non-current Liabilities | B47: =B51-B42 -> 1966.7 | C47: =C51-C42 -> 1730 | D47: =D51-D42 -> 1763.7 | E47: =E51-E42 -> 1900.3 | F47: =F51-F42 -> 2282 | G47: =G51-G42 -> 2132.7 | H47: =H51-H42 -> 1164.1 | I47: =I51-I42 -> 1169.3 | ... M47: =M51-M42 -> -792 | N47: Balance Sheet | O47: Total non current liabilities
A48: Long-Term Debt | B48: 820.3 | C48: 790.7 | D48: 815.7 | E48: 1163 | F48: 1163.7 | G48: 905.2 | H48: 908.5 | I48: 913.5 | J48: 828.8 | K48: 838.2 | L48: 800.8 | M48: 654.4 | N48: Balance Sheet | O48: Long term debt | Z48: =Z44-Z46 -> 18829 | AA48: =AA44-AA46 -> 19275 | AB48: =AB44-AB46 -> 23169 | AC48: =AC44-AC46 -> 23618 | AD48: =AD44-AD46 -> 24128 | AE48: =AE44-AE46 -> 22901 | AF48: =AF44-AF46 -> 18095 | AG48: =AG44-AG46 -> 13591
A49: Long-Term Leases | B49: 869.9 | C49: 877.1 | D49: 894.9 | E49: 1,015.8 | F49: 0 | G49: 0 | H49: 0 | I49: 0 | J49: 0 | K49: 0 | L49: 0 | M49: 0 | Q49: Balance | R49: Pasivos totales no corrientes | Z49: =61491-Z44 -> 35359 | AA49: =63457-AA44 -> 37215 | AB49: =67855-AB44 -> 39978 | AC49: 36721 | AD49: 41973 | AE49: =8415+16529+10956+3583 -> 39483 | AF49: =4505+15932+7584+2654 -> 30675 | AG49: =5652+16195+7420+2179 -> 31446
A50: Other non-current liabilities | B50: =B47-SUM(B48:B49) -> 276.5 | C50: =C47-SUM(C48:C49) -> 62.2 | D50: =D47-SUM(D48:D49) -> 948 | E50: =E47-SUM(E48:E49) -> 737.3 | F50: =F47-SUM(F48:F49) -> 1118.3 | G50: =G47-SUM(G48:G49) -> 1227.5 | H50: =H47-SUM(H48:H49) -> 255.6 | I50: =I47-SUM(I48:I49) -> 255.8 | ... M50: =M47-SUM(M48:M49) -> -1446.4 | N50: Balance Sheet | O50: Other non current Liabilities | R50: + Préstamos a largo plazo | Z50: 22818 | AA50: 25169 | AB50: 27784 | AC50: 26719 | AD50: 27752 | AE50: 24944 | AF50: 20437 | AG50: 21847
A51: Total Liabilities | B51: 3212.4 | C51: 2823.3 | D51: 2971.8 | E51: 3097.1 | F51: 3231.8 | G51: 3376.4 | H51: 2078.9 | I51: 1894.3 | J51: 2018.3 | K51: 1960.3 | L51: -1858.4 | M51: -1608 | N51: Balance Sheet | O51: Total Liabilities
N52: Balance Sheet | Z52: =Z49-Z50 -> 12541 | AA52: =AA49-AA50 -> 12046 | AB52: =AB49-AB50 -> 12194 | AC52: =AC49-AC50 -> 10002 | AD52: =AD49-AD50 -> 14221 | AE52: =AE49-AE50 -> 14539 | AF52: =AF49-AF50 -> 10238 | AG52: =AG49-AG50 -> 9599
N53: Balance Sheet | Z53: =+Z49+Z44 -> 61491 | AA53: =+AA49+AA44 -> 63457 | AB53: =+AB49+AB44 -> 67855 | AC53: =AC44+AC49 -> 64018 | AD53: =AD49+AD44 -> 71388 | AE53: =AE49+AE44 -> 68044 | AF53: =AF49+AF44 -> 52695 | AG53: =AG49+AG44 -> 50738
A54: Minority Interest | B54: 126.9 | C54: 4.6 | D54: 0 | E54: 0 | F54: 0 | G54: 0 | H54: 0 | I54: 0 | J54: 0 | K54: -0.1 | N54: Balance Sheet | O54: Minority Interest
N55: Balance Sheet
A56: Shareholder's Equity | B56: =B38-B51-B54 -> 1385 | C56: =C38-C51-C54 -> 1155.9 | D56: =D38-D51-D54 -> 1010 | E56: =E38-E51-E54 -> 660.9 | F56: =F38-F51-F54 -> 441.5 | G56: =G38-G51-G54 -> 366.2 | H56: =H38-H51-H54 -> 482.6 | I56: =I38-I51-I54 -> 510.5 | ... M56: =M38-M51-M54 -> 3501.6 | N56: Balance Sheet | Q56: Balance | R56: + Participación minoritaria/no dominante
A58: CASH FLOW
A59: Operating CF | B59: 1120.3 | C59: 798.8 | D59: 971.4 | E59: 824.8 | F59: 927.2 | G59: 868.8 | H59: 615.2 | I59: 699.5 | J59: 608.3 | K59: 743.2 | L59: 614.8 | M59: 659
A60: Net Income | B60: =B12 -> 800.5 | C60: =C12 -> 710.7 | D60: =D12 -> 677.5 | E60: =E12 -> 286.7 | F60: =F12 -> 610.2 | G60: =G12 -> 599.1 | H60: =H12 -> 591.8 | I60: =I12 -> 635.3 | ... M60: =M12 -> 508.6
A61: Depreciation & Amortization | B61: 246.8 | C61: =80.6+72.7+12.5+1.1 -> 166.9 | D61: =90.3+112.6+4.3 -> 207.2 | E61: =136.8+196.6+0.4 -> 333.8 | F61: =124.9+138.1 -> 263 | G61: =122.3+138+0.3 -> 260.6 | H61: =122.6+0.4 -> 123 | I61: =116.3+0.4 -> 116.7 | J61: =117.7+0.3 -> 118 | K61: 114.8 | L61: 117.4 | M61: 117.2
A62: Changes in assets and liabilities | B62: =-15.5+15.3+3.7+47.6 -> 51.1 | C62: =-0.8+22.8+156.5+12 -> 190.5 | D62: =-1.6-96.5+165.4+235.2-2.7 -> 299.8 | E62: =1.1-9.6-205.4-29.5-22.9 -> -266.3 | F62: =1.7-25.6-34-3.3-5.3 -> -66.5 | G62: =-4.3-36.2-97.6+35.8-0.2 -> -102.5 | H62: =6.1+39-126-16.9 -> -97.8 | I62: =0.3-35.3-733.7-49.7-19.3 -> -837.7 | J62: =2.9-57-214.5+29.4+1.6 -> -237.6 | K62: =-15.9-43.9-28.9+49.1-2.3 -> -41.9 | L62: =9.3+53.8-90.9+50.7-17.3 -> 5.6 | M62: =-3.2-40.1-21.7+7.4-50.2 -> -107.8
A63: Other Adjustments | B63: =B59-B60-B61-B62 -> 21.9 | C63: =C59-C60-C61-C62 -> -269.3 | D63: =D59-D60-D61-D62 -> -213.1 | E63: =E59-E60-E61-E62 -> 470.6 | F63: =F59-F60-F61-F62 -> 120.5 | G63: =G59-G60-G61-G62 -> 111.6 | H63: =H59-H60-H61-H62 -> -1.8 | I63: =I59-I60-I61-I62 -> 785.2 | ... M63: =M59-M60-M61-M62 -> 141
A64: Investing CF | B64: -334.4 | C64: -271.4 | D64: -292.5 | E64: -130.9 | F64: -139.1 | G64: -125.9 | H64: -112.2 | I64: -154.3 | J64: -139.3 | K64: -106 | L64: -102.6 | M64: -85.7
A65: Net Capex | B65: =-131+2+3.3 -> -125.7 | C65: =-205.1+41.7 -> -163.4 | D65: =-243.6+3.4+15.5 -> -224.7 | E65: =-144.6+0.5+28.4 -> -115.7 | F65: =-136.4+0.3 -> -136.1 | G65: =-123.2+0.3 -> -122.9 | H65: =-112.8+1 -> -111.8 | I65: =-157+2.7 -> -154.3 | J65: =-147.5+0.2 -> -147.3 | K65: =-113.5+1.9 -> -111.6 | L65: =-102.9+0.4 -> -102.5 | M65: =-92.4+1.5+5.3 -> -85.6
A66: Investments & Acquisitions | B66: =-152.3-0.9 -> -153.2 | C66: =-28.8-64.7-1.9 -> -95.4 | D66: -34.3 | E66: -2.4 | F66: -3 | G66: 0 | H66: 0.4 | I66: 0 | J66: 0 | K66: 0 | L66: -0.1 | M66: 0
A67: Other Inflows (Outflows) | B67: =B64-B65-B66 -> -55.5 | C67: =C64-C65-C66 -> -12.6 | D67: =D64-D65-D66 -> -33.5 | E67: =E64-E65-E66 -> -12.8 | F67: =F64-F65-F66 -> 0 | G67: =G64-G65-G66 -> -3 | H67: =H64-H65-H66 -> -0.8 | I67: =I64-I65-I66 -> 0 | ... M67: =M64-M65-M66 -> -0.1
A68: Financing CF | B68: -663.3 | C68: -727.1 | D68: -993.4 | E68: -231.7 | F68: -769.2 | G68: -718.4 | H68: -507.6 | I68: -584.4 | J68: -689.2 | K68: -636.1 | L68: -371.8 | M68: -491.1
A69: Debt Borrowing | B69: 0 | C69: 0 | D69: 0 | E69: 0 | F69: 250.2 | G69: 0 | H69: 0 | I69: 297.3 | J69: 0 | K69: 0 | L69: 250 | M69: 0
A70: Debt Repayment | B70: -2.5 | C70: 0 | D70: -325 | E70: 0 | F70: 0 | G70: 0 | H70: 0 | I70: -212.6 | J70: 0 | K70: 0 | L70: -85.5 | M70: 0
A71: Lease Increases | B71: 0 | C71: 0.1 | D71: 0 | E71: 0 | F71: 0 | G71: 0 | H71: 0 | I71: 0 | J71: 0 | K71: 0 | L71: 0 | M71: 0
A72: Lease Payments | B72: -156.1 | C72: -157.1 | D72: -172.3 | E72: -171 | F72: -162.6 | G72: -146.1 | H72: 0 | I72: 0 | J72: 0 | K72: 0 | L72: 0 | M72: 0
A73: Dividends | B73: -248.3 | C73: -237.4 | D73: -344.5 | E73: 0 | F73: -213.6 | G73: -215.7 | H73: -479.7 | I73: -314.1 | J73: -567.5 | K73: -434.4 | L73: -164.8 | M73: -147.7 | N73: cash flows FINANCING | O73: Dividends paid
A74: Share buyback | B74: -177.3 | C74: -228.5 | D74: -8.7 | E74: -19.3 | F74: -300.2 | G74: -325 | H74: -105.1 | I74: -187.6 | J74: -150.7 | K74: -137.9 | L74: -295.8 | M74: -241.9 | N74: cash flows FINANCING | O74: =+A74 -> Share buyback
A75: Other Inflows (Outflows) | B75: =B68-B69-B70-B71-B72-B73-B74 -> -79.1 | C75: =C68-C69-C70-C71-C72-C73-C74 -> -104.2 | D75: =D68-D69-D70-D71-D72-D73-D74 -> -142.9 | E75: =E68-E69-E70-E71-E72-E73-E74 -> -41.4 | F75: =F68-F69-F70-F71-F72-F73-F74 -> -343 | G75: =G68-G69-G70-G71-G72-G73-G74 -> -31.6 | H75: =H68-H69-H70-H71-H72-H73-H74 -> 77.2 | I75: =I68-I69-I70-I71-I72-I73-I74 -> -167.4 | ... M75: =M68-M69-M70-M71-M72-M73-M74 -> -101.5
A76: FX
A77: Changes in cash | B77: =B59+B64+B68+B76 -> 122.6 | C77: =C59+C64+C68+C76 -> -199.7 | D77: =D59+D64+D68+D76 -> -314.5 | E77: =E59+E64+E68+E76 -> 462.2 | F77: =F59+F64+F68+F76 -> 18.9 | G77: =G59+G64+G68+G76 -> 24.5 | H77: =H59+H64+H68+H76 -> -4.6 | I77: =I59+I64+I68+I76 -> -39.2 | ... M77: =M59+M64+M68+M76 -> 82.2
O78: (Vitalis will later fill this info)
A79: Other Data | E79: Corporate Bonds 3, 5 Y 10 | H79: Average Price | J79: Moody's | K79: YTM | L79: DIVISA
A80: Number of employees | B80: 48417 | C80: 10-K | N80: bloomberg
A81: Shares Outstanding (Thousands) | B81: 116610 | C81: Yahoo finance | N81: bloomberg
A82: Float | B82: =(112.35/126.5)*100% -> 0.88814229 | C82: Yahoo finance | N82: bloomberg
A83: Insiders Own | B83: 0.0699 | C83: Yahoo finance | N83: bloomberg
A84: Fitch/ S&P Rating | B84: BBB | C84: 10-K | N84: bloomberg
A85: Dividend Yield(Yahoo Finance) | B85: 0.0227 | C85: Yahoo finance | N85: bloomberg
A86: Daily Volume in Millions of USD | C86: Yahoo Finance | N86: bloomberg
B87: =B5 -> 2023 | C87: =C5 -> 2022 | D87: =D5 -> 2021
A88: Short % of Float | B88: - | C88: - | D88: - | E88: Yahoo Finance
A89: EPS | B89: 6.62 | C89: 5.51 | D89: 5.1 | E89: Yahoo Finance

Sheet Sector Impact
E2: Sector | F2: Sub-Industry | H2: Low | K2: Sector | L2: Environment | Q2: Social
E3: Communication Services | F3: Interactive Home Entertainment | H3: Medium | L3: CO2 | M3: Water | N3: Energy | O3: Waste | P3: Degradation | Q3: Turnover | R3: Compensation | S3: Reputation | T3: Discrimination | U3: Security | V3: Damage | W3: Pension | X3: Supply | Y3: Community | Z3: Public | AA3: Litigation
E4: Communication Services | F4: Interactive Media & Services | H4: High | K4: Communication Services | L4: Low | M4: Low | N4: Medium | O4: Low | P4: Low | Q4: Medium | R4: Medium | S4: Low | T4: Low | U4: High | V4: Low | W4: Low | X4: Low | Y4: Low | Z4: Low | AA4: Medium
B5: Environmental | E5: Communication Services | F5: Integrated Telecommunication Services | H5: Very High | K5: Consumer Discretionary | L5: Low | M5: Low | N5: Medium | O5: Medium | P5: Low | Q5: Medium | R5: Medium | S5: Low | T5: Low | U5: Medium | V5: Medium | W5: Medium | X5: High | Y5: Low | Z5: High | AA5: Low
B6: Direct CO2 emissions | E6: Communication Services | F6: Cable & Satellite | K6: Consumer Staples | L6: High | M6: Very High | N6: High | O6: High | P6: High | Q6: Medium | R6: High | S6: High | T6: Low | U6: Medium | V6: Medium | W6: Low | X6: High | Y6: Low | Z6: Very High | AA6: Low
B7: Total Water Use | E7: Communication Services | F7: Broadcasting | K7: Energy | L7: Very High | M7: Very High | N7: Medium | O7: Very High | P7: High | Q7: High | R7: Medium | S7: Medium | T7: Medium | U7: Medium | V7: High | W7: Medium | X7: Medium | Y7: High | Z7: High | AA7: Low
K8: Renewable Energy | L8: Low | M8: Low | N8: Low | O8: Medium | P8: Medium | Q8: Low | R8: Medium | S8: Medium | T8: High | U8: Medium | V8: Low | W8: Low | X8: Medium | Y8: Medium | Z8: High | AA8: Low
B9: Total Energy Consumption | E9: Communication Services | F9: Movies & Entertainment | K9: Financials | L9: Low | M9: Low | N9: Low | O9: Low | P9: Low | Q9: Low | R9: Low | S9: Medium | T9: High | U9: Medium | V9: Low | W9: Low | X9: Low | Y9: Low | Z9: Medium | AA9: Low
K10: Forestry | L10: Low | M10: Medium | N10: Low | O10: Medium | P10: High | Q10: Low | R10: Low | S10: Low | T10: Low | U10: Low | V10: Low | W10: Low | X10: Low | Y10: Medium | Z10: Low | AA10: Low
B11: Waste Management | E11: Communication Services | F11: Advertising | K11: Health Care | L11: Low | M11: Medium | N11: Low | O11: Low | P11: Low | Q11: Low | R11: Low | S11: Medium | T11: Low | U11: High | V11: Low | W11: Low | X11: Low | Y11: Low | Z11: Low | AA11: Low
B12: Land Degradation/Deforestation/Biodiversity loss/Animal sufering/... | E12: Communication Services | F12: Alternative Carriers | K12: Industrials | L12: Very High | M12: Very High | N12: Very High | O12: High | P12: High | Q12: Low | R12: Medium | S12: High | T12: Very High | U12: Medium | V12: Very High | W12: Medium | X12: Very High | Y12: Very High | Z12: Very High | AA12: High
B13: Social | E13: Communication Services | F13: Publishing | K13: Information Technology | L13: Medium | M13: Low | N13: High | O13: Low | P13: Low | Q13: Low | R13: Low | S13: Low | T13: Low | U13: High | V13: Low | W13: Low | X13: Low | Y13: Low | Z13: Medium | AA13: Very High
B14: Employee turnover | E14: Communication Services | F14: Wireless Telecommunication Services | K14: Materials | L14: Very High | M14: Very High | N14: Very High | O14: Very High | P14: High | Q14: High | R14: High | S14: Medium | T14: High | U14: Low | V14: Very High | W14: Medium | X14: Medium | Y14: Very High | Z14: High | AA14: Medium
B15: Salaries and compensation | E15: Consumer Discretionary | F15: Automotive Retail | K15: Real Estate | L15: Low | M15: Low | N15: Medium | O15: Low | P15: Low | Q15: Medium | R15: Low | S15: Low | T15: Low | U15: High | V15: Low | W15: Medium | X15: Low | Y15: Medium | Z15: Low | AA15: Low
B16: Reputational issues | E16: Consumer Discretionary | F16: Internet & Direct Marketing Retail | K16: Utilities | L16: Very High | M16: High | N16: High | O16: Medium | P16: High | Q16: Low | R16: Medium | S16: Medium | T16: Low | U16: Medium | V16: Medium | W16: Medium | X16: Medium | Y16: Low | Z16: Medium | AA16: Low
B17: Discrimination issues | E17: Consumer Discretionary | F17: Auto Parts & Equipment
B18: Job security | E18: Consumer Discretionary | F18: Specialty Stores
B19: Health injuries | E19: Consumer Discretionary | F19: Computer & Electronics Retail | L19: Communication Services | M19: Consumer Discretionary | N19: Consumer Staples | O19: Energy | P19: Financials | Q19: Health Care | R19: Industrials | S19: Information Technology | T19: Materials | U19: Real Estate | V19: Utilities
B20: PXP? | E20: Consumer Discretionary | F20: Hotels, Resorts & Cruise Lines | L20: Interactive Home Entertainment | M20: Automotive Retail | N20: Tobacco | O20: Oil & Gas Exploration & Production | P20: Life & Health Insurance | Q20: Health Care Equipment | R20: Industrial Conglomerates | S20: IT Consulting & Other Services | T20: Industrial Gases | U20: Office REITs | V20: Independent Power Producers & Energy Traders
B21: Supply chain | E21: Consumer Discretionary | F21: Restaurants | L21: Interactive Media & Services | M21: Internet & Direct Marketing Retail | N21: Agricultural Products | O21: Oil & Gas Equipment & Services | P21: Property & Casualty Insurance | Q21: Pharmaceuticals | R21: Airlines | S21: Application Software | T21: Specialty Chemicals | U21: Specialized REITs | V21: Electric Utilities
B22: Community involvement | E22: Consumer Discretionary | F22: Homebuilding | L22: Integrated Telecommunication Services | M22: Auto Parts & Equipment | N22: Distillers & Vintners | O22: Integrated Oil & Gas | P22: Consumer Finance | Q22: Health Care Supplies | R22: Building Products | S22: Semiconductors | T22: Paper Packaging | U22: Residential REITs | V22: Multi-Utilities
B23: Public Sector | E23: Consumer Discretionary | F23: General Merchandise Stores | L23: Cable & Satellite | M23: Specialty Stores | N23: Packaged Foods & Meats | O23: Oil & Gas Refining & Marketing | P23: Asset Management & Custody Banks | Q23: Health Care Distributors | R23: Electrical Components & Equipment | S23: Internet Services & Infrastructure | T23: Metal & Glass Containers | U23: Real Estate Services | V23: Water Utilities
B24: Litigation | E24: Consumer Discretionary | F24: Automobile Manufacturers | L24: Broadcasting | M24: Computer & Electronics Retail | N24: Household Products | O24: Oil & Gas Storage & Transportation | P24: Insurance Brokers | Q24: Biotechnology | R24: Aerospace & Defense | S24: Electronic Components | T24: Fertilizers & Agricultural Chemicals | U24: Industrial REITs | V24: Gas Utilities
E25: Consumer Discretionary | F25: Apparel Retail | L25: Movies & Entertainment | M25: Hotels, Resorts & Cruise Lines | N25: Soft Drinks | P25: Multi-line Insurance | Q25: Managed Health Care | R25: Air Freight & Logistics | S25: Technology Hardware, Storage & Peripherals | T25: Commodity Chemicals | U25: Retail REITs
E26: Consumer Discretionary | F26: Consumer Electronics | L26: Advertising | M26: Restaurants | N26: Hypermarkets & Super Centers | P26: Diversified Banks | Q26: Life Sciences Tools & Services | R26: Construction Machinery & Heavy Trucks | S26: Semiconductor Equipment | T26: Diversified Chemicals | U26: Health Care REITs
E27: Consumer Discretionary | F27: Apparel, Accessories & Luxury Goods | L27: Alternative Carriers | M27: Homebuilding | N27: Personal Products | P27: Multi-Sector Holdings | Q27: Health Care Technology | R27: Diversified Support Services | S27: Communications Equipment | T27: Copper | U27: Hotel & Resort REITs
E28: Consumer Discretionary | F28: Leisure Products | L28: Publishing | M28: General Merchandise Stores | N28: Food Retail | P28: Financial Exchanges & Data | Q28: Health Care Services | R28: Railroads | S28: Data Processing & Outsourced Services | T28: Construction Materials
E29: Consumer Discretionary | F29: Home Improvement Retail | L29: Wireless Telecommunication Services | M29: Automobile Manufacturers | N29: Brewers | P29: Investment Banking & Brokerage | Q29: Health Care Facilities | R29: Industrial Machinery | S29: Technology Distributors | T29: Gold
E30: Consumer Discretionary | F30: Casinos & Gaming | M30: Apparel Retail | N30: Food Distributors | P30: Regional Banks | R30: Agricultural & Farm Machinery | S30: Electronic Equipment & Instruments | T30: Steel
E31: Consumer Discretionary | F31: Home Furnishings | M31: Consumer Electronics | N31: Drug Retail | P31: Reinsurance | R31: Research & Consulting Services | S31: Systems Software
E32: Consumer Discretionary | F32: Distributors | M32: Apparel, Accessories & Luxury Goods | P32: Thrifts & Mortgage Finance | R32: Construction & Engineering | S32: Electronic Manufacturing Services
E33: Consumer Discretionary | F33: Housewares & Specialties | M33: Leisure Products | R33: Trucking
E34: Consumer Discretionary | F34: Household Appliances | M34: Home Improvement Retail | R34: Environmental & Facilities Services
E35: Consumer Staples | F35: Tobacco | M35: Casinos & Gaming | R35: Human Resource & Employment Services
E36: Consumer Staples | F36: Agricultural Products | M36: Home Furnishings | R36: Trading Companies & Distributors
E37: Consumer Staples | F37: Distillers & Vintners | M37: Distributors
E38: Consumer Staples | F38: Packaged Foods & Meats | M38: Housewares & Specialties
E39: Consumer Staples | F39: Household Products | M39: Household Appliances
E40: Consumer Staples | F40: Soft Drinks
E41: Consumer Staples | F41: Hypermarkets & Super Centers
E42: Consumer Staples | F42: Personal Products
E43: Consumer Staples | F43: Food Retail
E44: Consumer Staples | F44: Brewers
E45: Consumer Staples | F45: Food Distributors
E46: Consumer Staples | F46: Drug Retail
E47: Energy | F47: Oil & Gas Exploration & Production
E48: Energy | F48: Oil & Gas Equipment & Services
E49: Energy | F49: Integrated Oil & Gas
E50: Energy | F50: Oil & Gas Refining & Marketing
E51: Energy | F51: Oil & Gas Storage & Transportation
... E128: Utilities | F128: Gas Utilities
