Workbook
Name Sectors: '[1]Sector Impact'!$K$4:$K$16
Name Sectors: 'Sector Impact'!$K$4:$K$16

Sheet OP
B2: (Date of last update) | C2: Team 1 | D2: (Date of next Quarter/Annual Report) | E2: =Inputs!H3 -> #VALUE! | L2: {=_FV(E2,"Exchange")} -> New York Stock Exchange | M2: SIC:
B3: #VALUE! | D3: COMPANY DESCRIPTION | H3: CEO & BOARD OF DIRECTORS
D4: Nucor Corporation is a manufacturer of steel and steel products, with operating facilities in the United States, Canada and Mexico. Its segments include steel mills, steel products, raw materials, and Nucor Data Systems. The Steel Mills segment produces sheet steel (hot-rolled, cold-rolled and galvanized), plate steel, structural steel (wide-flange beams, beam blanks, H-piling, and sheet piling) and bar steel (blooms, billets, concrete reinforcing bar, merchant bar and engineered special bar quality. The Steel products segment produces steel joists and joist girders, steel deck, galvanized torque tubes used in solar arrays, hollow structural section (HSS) steel tubing, electrical conduit, fabricated concrete reinforcing steel, cold finished steel, and steel fasteners. The Raw materials segment produces direct reduced iron (DRI), brokers ferrous and nonferrous metals, and pig iron. Nucor Data Systems serves its customers in the data center infrastructure industry. | H4: Name, Age and Tenure | I4: Gender | J4: Executive? | L4: Other roles
H5: Leon J. Topalian, 56, 2020 | I5: M | J5: Y | L5: President, CEO & Chairman of the Board
H6: Stephen D. Laxton,52 2022 | I6: M | J6: Y | L6: CFO, Treasurer & Executive VP
H7: David A. Sumoski, 57, 2021 | I7: M | J7: N | L7: Chief Operating Officer
H8: K. Rex Query, 58, 2021 | I8: M | J8: Y | L8: Executive Vice President of Sheet, Tubular Products & Talent Resources
H9: Norma B. Clayton, 66, 2021 | I9: W | J9: N | L9: Retired Vice President The Boeing Company
H10: Patrick J. Dempsey, 59, 2016 | I10: M | J10: N | L10: Retired President & CEO of Barnes Group Inc.
H11: Nicholas C. Gangestad, 56, 2023 | I11: M | J11: N | L11: Senior Vice President & Chief Financial Officer of Rockwell Automation, Inc.
H12: Christopher J. Kearney, 68, 2007 | I12: M | J12: N | L12: Lead Director of Nucor Corporation and Retired Chairman, CEO & President SPX FLOW, Inc.
H13: Laurette T. Koellner, 69, 2015 | I13: W | J13: N | L13: Retired President of Boeing International
H14: Michael W. Lamach, 60, 2022 | I14: M | J14: N | L14: Retired Executive Chair & CEO of Trane Technologies plc
B15: {=_FV(E2,"Currency")&" MILLIONS"} -> USD MILLIONS | H15: Nadja Y. West | I15: W | J15: N | L15: Lieutenant General, U.S. Army (Retired) & Former Commander of U.S. Army Medical Command
B18: COMPANY OVERVIEW
B19: Stock | D19: Liquidity and Solvency | F19: Segments | I19: ="Profitability ("&J20&")" -> Profitability (2023) | L19: Multiples
B20: Last Price | C20: {=_FV(E2,"Price")} -> 137.63 | D20: Total Assets | E20: =_xlfn.XLOOKUP(D20,'Fin. Data'!A:A,'Fin. Data'!B:B,,0) -> 35340.5 | F20: Regions | H20: % Sales | I20: Reporting Year | J20: 2023 | L20: Float | M20: =IF(Inputs!B80 <> "",Inputs!B80,"") -> 0.99169967
B21: Outstanding Shares | C21: {=_FV(E2,"Shares outstanding",TRUE)} -> 229535400 | D21: Total Liabilities | E21: =_xlfn.XLOOKUP(D21,'Fin. Data'!A:A,'Fin. Data'!B:B,,0) -> 13216.75 | F21: N/A | H21: =Segments!B5 -> NA | I21: End of Year | J21: 45291 | L21: Insiders Own | M21: =IF(Inputs!B81 <> "",Inputs!B81,"") -> 0.0051
B22: Market Cap. | C22: =C20*C21/1000000 -> 31590.957 | D22: Cash/Share | E22: =_xlfn.XLOOKUP("Cash & Eq.",'Fin. Data'!A:A,'Fin. Data'!B:B,,0)*1000000/C21 -> 27.809654 | I22: EBITDA | K22: =_xlfn.XLOOKUP(I22,'Fin. Data'!A:A,'Fin. Data'!B:B,,0) -> 7411.503 | L22: b (Yahoo) | M22: {=IF(_FV(E2,"Beta") <> "",_FV(E2,"Beta"),"")} -> 1.7855
B23: +Total Debt | C23: ='Fin. Data'!B63 -> 6842.183 | D23: EBITDA/Net Financial Cost (NFC) | E23: =IFERROR(_xlfn.XLOOKUP("EBITDA",'Fin. Data'!A:A,'Fin. Data'!B:B,,0)/_xlfn.XLOOKUP("Net Financial Cost",'Fin. Data'!A:A,'Fin. Data'!B:B,,0),"") -> 250.11822 | I23: Depreciation & Amortization | K23: =_xlfn.XLOOKUP(I23,'Fin. Data'!A:A,'Fin. Data'!B:B,,0) -> 1168.32 | L23: Score (S&P) | M23: =IF(Inputs!B82 <> "",Inputs!B82,"") -> A-
B24: -Cash | C24: ='Fin. Data'!B41 -> 6383.3 | D24: Debt/EBITDA | E24: =IFERROR(_xlfn.XLOOKUP("Total Debt",'Fin. Data'!A:A,'Fin. Data'!B:B,,0)/_xlfn.XLOOKUP("EBITDA",'Fin. Data'!A:A,'Fin. Data'!B:B,,0),"") -> 0.92318427 | I24: EBIT | K24: =_xlfn.XLOOKUP(I24,'Fin. Data'!A:A,'Fin. Data'!B:B,,0) -> 6243.183 | L24: Price/Book Value | M24: =IFERROR((C20*C21/(E20-E21))/1000000,"") -> 1.4279205
B25: =Enterprise Value | C25: =C22+C23-C24 -> 32049.84 | D25: "Others Assets"/Asset | E25: =IFERROR(_xlfn.XLOOKUP("Other Assets",'Fin. Data'!A:A,'Fin. Data'!B:B,,0)/_xlfn.XLOOKUP("Total Assets",'Fin. Data'!A:A,'Fin. Data'!B:B,,0),"") -> 0.26531487 | I25: Net Income | K25: =_xlfn.XLOOKUP(I25,'Fin. Data'!A:A,'Fin. Data'!B:B,,0) -> 4524.849 | L25: NCF(3y avg)/Asset | M25: =IFERROR(K31/E20,"") -> -0.0028243139
B26: Holdings (nac/int'l) | C26: - | D26: Debt/Assets | E26: =_xlfn.XLOOKUP(D26,'Fin. Data'!A:A,'Fin. Data'!B:B,,0) -> 0.19360742 | F26: Categories | H26: % Sales | I26: EPS | K26: =1000000*K25/C21 -> 19.713077 | L26: Price/Net Inc. (3y avg) | M26: =IFERROR(C22/K30,"") -> 4.9986635
B27: t liq. (Holdings/Vol.) | C27: - | D27: EBITDA Margin (average) | E27: =IFERROR(AVERAGE(_xlfn.XLOOKUP("EBITDA Margin",'Fin. Data'!A:A,'Fin. Data'!B:D,,0)),"") -> 0.256734 | F27: =Segments!C18 -> Steel mills | H27: =Segments!B18 -> 0.57881405 | I27: ROA | K27: =IFERROR(K25/E20,"") -> 0.12803579 | L27: EV/Asset | M27: =IFERROR(C25/E20,"") -> 0.906887
B28: % Short | C28: 0.0267 | D28: Operating Margin (average) | E28: =IFERROR(AVERAGE(_xlfn.XLOOKUP("Operating Margin",'Fin. Data'!A:A,'Fin. Data'!B:D,,0)),"") -> 0.22932636 | I28: ROIC | K28: =IFERROR(Peers!C18,"") -> 0.22789616 | L28: EV/Ebitda (3y average) | M28: =IFERROR(C25/K29,"") -> 3.3027171
D29: Net Income Margin (average) | E29: =IFERROR(AVERAGE(_xlfn.XLOOKUP("Net Income Margin",'Fin. Data'!A:A,'Fin. Data'!B:D,,0)),"") -> 0.16691229 | F29: =Segments!C19 -> Steel products | H29: =Segments!B19 -> 0.36754976 | I29: EBITDA (3y average) | K29: =AVERAGE(_xlfn.XLOOKUP("EBITDA",'Fin. Data'!A:A,'Fin. Data'!B:D,,0)) -> 9704.0827 | L29: Price/NCF (3y average) | M29: =IFERROR(C22/K31,"") -> -316.50249
B30: E | I30: Net Income (3y average) | K30: =AVERAGE(_xlfn.XLOOKUP("Net Income",'Fin. Data'!A:A,'Fin. Data'!B:D,,0)) -> 6319.8807 | L30: Bonds 1,3,5a (USD) | M30: -
B31: S | D31: Net Financial Cost/Avg Net Debt | E31: =IFERROR(-_xlfn.XLOOKUP("Net Financial Cost",'Fin. Data'!A:A,'Fin. Data'!B:B,,0)/AVERAGE(_xlfn.XLOOKUP("Net Debt",'Fin. Data'!A:A,'Fin. Data'!B:D,,0)),"") -> -0.014279817 | F31: =Segments!C20 -> Raw materials | H31: =Segments!B20 -> 0.053636192 | I31: NCF (3y average) | K31: =AVERAGE(_xlfn.XLOOKUP("Net Financial Cost",'Fin. Data'!A:A,'Fin. Data'!B:D,,0)) -> -99.812667 | L31: Div+Rep.(3y avg)/Price | M31: =-IFERROR(SUM(E52:E54)/(3*C22),"") -> 0.096346137
B32: G | L32: Div. Yield | M32: =-IFERROR(L53/C22,"") -> 0.016287256
B33: INVESTMENT THESIS
B34: Pillars of Recommendation | H34: Recommendation | I34: Valuation Assumptions
B35: Pillar | C35: Explanation | H35: HOLD | I35: Check DCF
B36: Market Leadership in the Steel Industry | C36: Nucor is the largest steel producer in the United States, benefiting from economies of scale, a vertically integrated business model, and operational efficiency.
B37: Sustainability and Innovation | C37: Nucor leads the industry in sustainable steel, leveraging electric arc furnace technology to produce steel with one of the lowest carbon footprints in the sector.
B38: Diversified Revenue Streams | C38: Nucor's product portfolio includes not only raw steel but also value-added steel products, ensuring more stability during fluctuations in specific sectors like automotive or construction.
B39: Risks of Investment | H39: Price Target | I39: Valuation
B40: Risk | C40: Explanation | H40: =IFERROR(DCF!D75,"") -> 203.10745 | I40: Discount Rate | L40: =DCF!F50 -> 0.1
B41: Volatility in Steel Prices | C41: Steel prices are highly cyclical, driven by global supply and demand dynamics, drops in steel prices adversely impact Nucor’s margins and revenue
B42: Competition from Chinese Steel Producers | C42: China is the world's largest steel producer and exporter, producing cheaper steel and potentially driving down prices and eroding profit margins. | I42: Upside | L42: =IFERROR(DCF!D74,"") -> 0.47574985
B43: Trade Policies and Tariffs | C43: Changes in trade policies, such as the removal of tariffs on imported steel, could increase competition from international producers
B44: FINANCIAL PERFORMANCE
B45: Year | C45: Net Sales | D45: Operating Margin | E45: Dividends + Share Buyback | F45: Net Cash Flow | G45: Debt/Assets | H45: Depreciation & Amortization | I45: Capex + Investments | J45: Cash Flow
B46: =B47-1 -> 2015 | C46: {=_xlfn.SORTBY(TRANSPOSE(_xlfn.XLOOKUP(C$45,'Fin. Data'!$A:$A,'Fin. Data'!$B:$J,,0)),$B$46:$B$54,-1)} -> 16439.276 | D46: {=_xlfn.SORTBY(TRANSPOSE(_xlfn.XLOOKUP(D$45,'Fin. Data'!$A:$A,'Fin. Data'!$B:$J,,0)),$B$46:$B$54,-1)} -> 0.039843604 | E46: {=_xlfn.SORTBY(TRANSPOSE(_xlfn.XLOOKUP(E$45,'Fin. Data'!$A:$A,'Fin. Data'!$B:$J,,0)),$B$46:$B$54,-1)} -> -545.9 | F46: =Inputs!J75 -> 925.6 | G46: {=_xlfn.SORTBY(TRANSPOSE(_xlfn.XLOOKUP(G$45,'Fin. Data'!$A:$A,'Fin. Data'!$B:$J,,0)),$B$46:$B$54,-1)} -> - | H46: {=_xlfn.SORTBY(TRANSPOSE(_xlfn.XLOOKUP(H$45,'Fin. Data'!$A:$A,'Fin. Data'!$B:$J,,0)),$B$46:$B$54,-1)} -> 944.9 | I46: {=_xlfn.SORTBY(TRANSPOSE(_xlfn.XLOOKUP(I$45,'Fin. Data'!$A:$A,'Fin. Data'!$B:$J,,0)),$B$46:$B$54,-1)} -> -444.6 | L46: =J20 -> 2023 | M46: =L46-1 -> 2022
B47: =B48-1 -> 2016 | C47: 16208.122 | D47: 0.088165674 | E47: -480.19 | F47: =Inputs!I75 -> 98.45 | G47: - | H47: 687.05 | I47: -1174.27 | J47: Net Income | L47: =_xlfn.XLOOKUP($J47,'Fin. Data'!$A:$A,'Fin. Data'!B:B,,0) -> 4524.849 | M47: =_xlfn.XLOOKUP($J47,'Fin. Data'!$A:$A,'Fin. Data'!C:C,,0) -> 7607.818 | N47: =(C47/C46)-1 -> -0.014061082 | O47: =(D47/D46)-1 -> 1.2127937
B48: =B49-1 -> 2017 | C48: 20252.393 | D48: 0.09292729 | E48: -582.96 | F48: =Inputs!H75 -> -1105.9 | G48: - | H48: 727.06 | I48: -926.24 | J48: Operating CF | L48: =_xlfn.XLOOKUP($J48,'Fin. Data'!$A:$A,'Fin. Data'!B:B,,0) -> 7111.9 | M48: =_xlfn.XLOOKUP($J48,'Fin. Data'!$A:$A,'Fin. Data'!C:C,,0) -> 10072 | N48: =(C48/C47)-1 -> 0.24952126 | O48: =(D48/D47)-1 -> 0.054007597 | Q48: =F48/F47-1 -> -12.233113 | R48: =H48/H47-1 -> 0.058234481 | S48: =I48/I47-1 -> -0.21122059
B49: =B50-1 -> 2018 | C49: 25067.279 | D49: 0.13699133 | E49: -1337.4 | F49: =Inputs!G75 -> 455.75 | G49: 0.23945325 | H49: 719.64 | I49: -933.963 | J49: Investing CF | L49: =_xlfn.XLOOKUP($J49,'Fin. Data'!$A:$A,'Fin. Data'!B:B,,0) -> -2496.43 | M49: =_xlfn.XLOOKUP($J49,'Fin. Data'!$A:$A,'Fin. Data'!C:C,,0) -> -5702.71 | N49: =(C49/C48)-1 -> 0.23774405 | O49: =(D49/D48)-1 -> 0.47417765 | Q49: =F49/F48-1 -> -1.4121078 | R49: =H49/H48-1 -> -0.010205485 | S49: =I49/I48-1 -> 0.0083380117
B50: =B51-1 -> 2019 | C50: 22588.858 | D50: 0.087126582 | E50: -799.5 | F50: =Inputs!F75 -> 134.8 | G50: 0.23892683 | H50: 734.65 | I50: -1818.846 | J50: Net Capex | L50: =_xlfn.XLOOKUP($J50,'Fin. Data'!$A:$A,'Fin. Data'!B:B,,0) -> -2199.3 | M50: =_xlfn.XLOOKUP($J50,'Fin. Data'!$A:$A,'Fin. Data'!C:C,,0) -> -1915.6 | N50: =(C50/C49)-1 -> -0.098870763 | O50: =(D50/D49)-1 -> -0.36399932 | Q50: =F50/F49-1 -> -0.70422381 | R50: =H50/H49-1 -> 0.020857651 | S50: =I50/I49-1 -> 0.94744974
B51: =B52-1 -> 2020 | C51: 20140 | D51: 0.080086892 | E51: -538.42 | F51: =Inputs!E75 -> 1218.46 | G51: 0.2653661 | H51: 785.47 | I51: -1686.71 | J51: Investments & Acquisitions | L51: =_xlfn.XLOOKUP($J51,'Fin. Data'!$A:$A,'Fin. Data'!B:B,,0) -> -225.044 | M51: =_xlfn.XLOOKUP($J51,'Fin. Data'!$A:$A,'Fin. Data'!C:C,,0) -> -3876.916 | N51: =(C51/C50)-1 -> -0.10841 | O51: =(D51/D50)-1 -> -0.080798426 | Q51: =F51/F50-1 -> 8.0390208 | R51: =H51/H50-1 -> 0.069175798 | S51: =I51/I50-1 -> -0.072648262
B52: =B53-1 -> 2021 | C52: 36484 | D52: 0.25541087 | E52: -3687.56 | F52: =Inputs!D75 -> -245.93 | G52: 0.22153963 | H52: 864.56 | I52: -2874.026 | J52: Financing CF | L52: =_xlfn.XLOOKUP($J52,'Fin. Data'!$A:$A,'Fin. Data'!B:B,,0) -> -2592.81 | M52: =_xlfn.XLOOKUP($J52,'Fin. Data'!$A:$A,'Fin. Data'!C:C,,0) -> -2510.86 | N52: =(C52/C51)-1 -> 0.81151936 | O52: =(D52/D51)-1 -> 2.1891719 | Q52: =F52/F51-1 -> -1.2018367 | R52: =H52/H51-1 -> 0.10069131 | S52: =I52/I51-1 -> 0.70392421
B53: =B54-1 -> 2022 | C53: 41512 | D53: 0.25309019 | E53: -3337.39 | F53: =Inputs!C$75 -> 1858.43 | G53: 0.20602007 | H53: 1061.63 | I53: -5792.516 | J53: Dividends | L53: =_xlfn.XLOOKUP($J53,'Fin. Data'!$A:$A,'Fin. Data'!B:B,,0) -> -514.53 | M53: =_xlfn.XLOOKUP($J53,'Fin. Data'!$A:$A,'Fin. Data'!C:C,,0) -> -533.59 | N53: =(C53/C52)-1 -> 0.13781384 | O53: =(D53/D52)-1 -> -0.0090860436 | Q53: =F53/F52-1 -> -8.5567438 | R53: =H53/H52-1 -> 0.22794254 | S53: =I53/I52-1 -> 1.015471
B54: =J20 -> 2023 | C54: 34714 | D54: 0.17947802 | E54: -2106.05 | F54: =Inputs!B75 -> 2022.66 | G54: 0.19360742 | H54: 1168.32 | I54: -2424.344 | J54: Share Buyback | L54: =_xlfn.XLOOKUP($J54,'Fin. Data'!$A:$A,'Fin. Data'!B:B,,0) -> -1591.52 | M54: =_xlfn.XLOOKUP($J54,'Fin. Data'!$A:$A,'Fin. Data'!C:C,,0) -> -2803.8 | N54: =(C54/C53)-1 -> -0.16375988 | O54: =(D54/D53)-1 -> -0.29085351 | Q54: =F54/F53-1 -> 0.088370291 | R54: =H54/H53-1 -> 0.10049641 | S54: =I54/I53-1 -> -0.58146961
B55: Annual Growth Rate | C55: =IFERROR((C54/C46)^(1/8)-1,"") -> 0.097937823 | D55: =IFERROR((D54/D46)^(1/8)-1,"") -> 0.20699809 | F55: =IFERROR((F54/F46)^(1/8)-1,"") -> 0.10264939 | H55: =IFERROR((H54/H46)^(1/8)-1,"") -> 0.026885438 | J55: FX | L55: =_xlfn.XLOOKUP($J55,'Fin. Data'!$A:$A,'Fin. Data'!B:B,,0) -> 0 | M55: =_xlfn.XLOOKUP($J55,'Fin. Data'!$A:$A,'Fin. Data'!C:C,,0) -> 0 | N55: =(C55/C54)-1 -> -0.99999718 | O55: =(D55/D54)-1 -> 0.15333392
B56: Average Growth Rate | C56: =IFERROR(AVERAGE(N47:N54),"") -> 0.1314371 | D56: =IFERROR(AVERAGE(O47:O54),"") -> 0.39817669 | F56: =IFERROR(AVERAGE(Q47:Q54),"") -> -2.2829478 | H56: =IFERROR(AVERAGE(S47:S54),"") -> 0.25854921 | J56: Changes in Cash | L56: =L48-L49+L52-L53-L54 -> 9121.57 | M56: =M48-M49+M52-M53-M54 -> 16601.24
B57: CVAR | C57: =IFERROR(STDEV(C47:C54)/AVERAGE(C47:C54),"") -> 0.33913715 | D57: =IFERROR(STDEV(D46:D54)/AVERAGE(D46:D54),"") -> 0.5791457 | F57: =IFERROR(STDEV(F46:F54)/AVERAGE(F46:F54),"") -> 1.7003077 | H57: =IFERROR(STDEV(H46:H54)/AVERAGE(H46:H54),"") -> 0.19889859 | J57: Inventory/D Revenues | L57: =IFERROR(SUM(I51:I54)/(C54-C50),"") -> -1.05381 | M57: =IFERROR((SUM(I51:I54)-SUM(H51:H54))/(C54-C50),"") -> -1.3738046
B58: Last Year | C58: =IFERROR(C54/C53-1,"") -> -0.16375988 | D58: =IFERROR(D54/D53-1,"") -> -0.29085351 | F58: =IFERROR(1-(F54/F53),"") -> -0.088370291 | H58: =IFERROR(1-(H54/H53),"") -> -0.10049641 | J58: t inversiones; t adq. neto dep. | L58: =IFERROR(L57/E27,"") -> -4.1046765 | M58: =IFERROR(M57/E27,"") -> -5.3510817
B59: QUALITATIVE ANALYSIS
B60: SWOT ANALYSIS | J60: HOLDERS
B61: Pros | E61: Cons | J61: Name | M61: % Stake
B62: Market Leadership Operational Efficiency and Financial Resilience | E62: Limited International Presence | J62: The Vanguard Group, Inc. | M62: 0.12
J63: State Farm Insurance Companies | M63: 0.104
J64: BlackRock Institutional Trust Company, N.A. | M64: 0.0534
J65: State Street Global Advisors (US) | M65: 0.0468
J66: Geode Capital Management, L.L.C. | M66: 0.0244
J67: Fidelity Management & Research Company LLC | M67: 0.0219
J68: Dimensional Fund Advisors, L.P. | M68: 0.0165
J69: Capital World Investors | M69: 0.0159
J70: Pacer Advisors, Inc. | M70: 0.0122
J71: Norges Bank Investment Management (NBIM) | M71: 0.0118
B72: Opportunities | E72: Risks | J72: Northern Trust Investments, Inc. | M72: 0.0104
B73: International Expansion Environmental and Sustainable Initiatives | E73: Recessions and Global Economic Fluctuations; Inflation and Rising Operational Costs; Intense Competition in the Domestic and International Markets | J73: BlackRock Investment Management (UK) Ltd. | M73: 0.0103
J74: T. Rowe Price International Ltd | M74: 0.0098
J75: Legal & General Investment Management Ltd. | M75: 0.0091
J76: BlackRock Asset Management Ireland Limited | M76: 0.0085
J77: First Trust Advisors L.P. | M77: 0.0069
J78: Invesco Capital Management LLC | M78: 0.0069
J79: Charles Schwab Investment Management, Inc. | M79: 0.0066
J80: Nordea Funds Oy | M80: 0.0057
J81: TOTAL | M81: =SUM(M62:M80) -> 0.5011
B82: NOTES | G82: STOCK PERFORMANCE (5 years)
G107: =E2 -> #VALUE! | I107: =Peers!C2 -> #VALUE! | J107: =Peers!C4 -> #VALUE! | L107: =Peers!C5 -> #VALUE! | M107: =Peers!C3 -> #VALUE!

Sheet Segments
B2: ="Regions "&"("&OP!$J$20&")" -> Regions (2023) | Q2: Products
D3: Nominal value | K3: YoY Growth
B4: Weight | C4: Region | D4: =OP!J20 -> 2023 | E4: =D4-1 -> 2022 | F4: =E4-1 -> 2021 | G4: =F4-1 -> 2020 | H4: =G4-1 -> 2019 | I4: =H4-1 -> 2018 | K4: =OP!J20 -> 2023 | L4: =K4-1 -> 2022 | M4: =L4-1 -> 2021 | N4: =M4-1 -> 2020 | O4: =N4-1 -> 2019 | P4: =O4-1 -> 2018
B5: NA | C5: NA | D5: NA | E5: NA | F5: NA | G5: NA | H5: NA | I5: NA | K5: NA | L5: NA | M5: NA | N5: NA | O5: NA | P5: NA
P6: -
P7: -
P8: -
P9: -
P10: -
C13: TOTAL | P13: -
B15: ="Categories "&"("&OP!$J$20&")" -> Categories (2023)
D16: Nominal value | K16: YoY Growth
B17: Weight | C17: Category | D17: =OP!J20 -> 2023 | E17: =D17-1 -> 2022 | F17: =E17-1 -> 2021 | G17: =F17-1 -> 2020 | H17: =G17-1 -> 2019 | I17: =H17-1 -> 2018 | K17: =OP!J20 -> 2023 | L17: =K17-1 -> 2022 | M17: =L17-1 -> 2021 | N17: =M17-1 -> 2020 | O17: =N17-1 -> 2019 | P17: =O17-1 -> 2018
B18: =IFERROR(D18/$D$24,"") -> 0.57881405 | C18: Steel mills | D18: 20092662 | E18: 24189858 | F18: 24145396 | G18: 20139658 | H18: 22588858 | I18: 25067279 | K18: =(D18-E18)/E18 -> -0.1693766 | L18: =(E18-F18)/F18 -> 0.0018414277 | M18: =(F18-G18)/G18 -> 0.19889802 | N18: =(G18-H18)/H18 -> -0.10842514 | O18: =(H18-I18)/I18 -> -0.098870763 | P18: -
B19: =IFERROR(D19/$D$24,"") -> 0.36754976 | C19: Steel products | D19: 12758939 | E19: 15060328 | F19: 9727943 | G19: 6623068 | H19: 6990064 | I19: 6796501 | K19: =(D19-E19)/E19 -> -0.15281135 | L19: =(E19-F19)/F19 -> 0.54815134 | M19: =(F19-G19)/G19 -> 0.46879709 | N19: =(G19-H19)/H19 -> -0.052502524 | O19: =(H19-I19)/I19 -> 0.028479802 | P19: -
B20: =IFERROR(D20/$D$24,"") -> 0.053636192 | C20: Raw materials | D20: 1861900 | E20: 2262281 | F20: 2610600 | G20: 1407283 | H20: 1664844 | I20: 2025560 | K20: =(D20-E20)/E20 -> -0.17698111 | L20: =(E20-F20)/F20 -> -0.13342488 | M20: =(F20-G20)/G20 -> 0.85506398 | N20: =(G20-H20)/H20 -> -0.15470579 | O20: =(H20-I20)/I20 -> -0.17808211 | P20: -
B24: =SUM(B18:B23) -> 1 | C24: TOTAL | D24: =SUM(D18:D23) -> 34713501 | E24: =SUM(E18:E23) -> 41512467 | F24: =SUM(F18:F23) -> 36483939 | G24: =SUM(G18:G23) -> 28170009 | H24: =SUM(H18:H23) -> 31243766 | I24: =SUM(I18:I23) -> 33889340 | K24: =(D24-E24)/E24 -> -0.1637813 | L24: =(E24-F24)/F24 -> 0.13782854 | M24: =(F24-G24)/G24 -> 0.29513409 | N24: =(G24-H24)/H24 -> -0.09837985 | O24: =(H24-I24)/I24 -> -0.078065079 | P24: -
B26: ="Categories "&"("&OP!$J$20&")" -> Categories (2023) | I26: Graphs
C27: % of Sales
B28: Category | C28: 2023 | D28: 2022 | E28: 2021 | F28: 2020 | G28: 2019 | H28: 2018
B29: Steel mills | C29: =D18/$D$24 -> 0.57881405 | D29: =E18/$E$24 -> 0.58271309 | E29: =F18/$F$24 -> 0.66180891 | F29: =G18/$G$24 -> 0.71493261 | G29: =H18/$H$24 -> 0.72298768 | H29: =I18/$I$24 -> 0.73968035
B30: Steel products | C30: =D19/$D$24 -> 0.36754976 | D30: =E19/$E$24 -> 0.36279048 | E30: =F19/$F$24 -> 0.26663631 | F30: =G19/$G$24 -> 0.23511061 | G30: =H19/$H$24 -> 0.22372668 | H30: =I19/$I$24 -> 0.20054982
B31: Raw materials | C31: =D20/$D$24 -> 0.053636192 | D31: =E20/$E$24 -> 0.054496424 | E31: =F20/$F$24 -> 0.071554774 | F31: =G20/$G$24 -> 0.049956782 | G31: =H20/$H$24 -> 0.053285638 | H31: =I20/$I$24 -> 0.059769827
B35: TOTAL | C35: =SUM(C29:C34) -> 1 | D35: =SUM(D29:D34) -> 1 | E35: =SUM(E29:E34) -> 1 | F35: =SUM(F29:F34) -> 1 | G35: =SUM(G29:G34) -> 1 | H35: =SUM(H29:H34) -> 1
B37: Categories | D37: Description
B38: Steel mills | D38: Production of sheet steel, plate steel, structural steel and others mainly from scrap steel
B39: Steel products | D39: Steel structures ready to deliver to consumer markets, such as metal builoding systems, insulated metal panels, structures for communications and energy transmission, steel mesh and fasteners, etc.
B40: Raw Materials | D40: Scrap recycling and brokerage operations, direct reduced iron operations (focused providing value for steelmaking operations rather selling)
B45: Industry | J45: Graphs (Industry Forecasts)
B46: Drivers | D46: Description
B47: Urbanization and infrastructure | D47: Increasing demand for steel in urban housing and infrastructure projects
B48: Automotive industry | D48: Rising demand for lightweight, durable and costumised steel products in electrict vehicles
B49: Sales forecast
B50: Source | D50: Market Growth CAGR | G50: Period
B51: Precision Business Insights | D51: 0.029 | G51: 2024-2030
B52: Future Market Insights | D52: 0.033 | G52: 2023-2033
B53: Markets and Markets | D53: 0.038 | G53: 2022-2027
B54: Average | D54: =AVERAGE(D51:F53) -> 0.033333333
B55: Company's Strategy / Extra Notes
B56: The company is divisting from it's steel meels segment and shifting to steel products, which have a higher margin and growth expectations given the growth in Evs, datacenters, renewable energy, and others. This is complemented with strategic acquisitions as a way of gaining exposure to these businesses.
B74: Note: precision business insights is the one that best reflects the market for Nucor's products, while others refer to the whole steel industry
C77: Assets | D77: Nominal value | K77: YoY Growth
B78: Weight | C78: Category | D78: 2023 | E78: 2022 | F78: 2021 | G78: 2020 | H78: 2019 | I78: 2018 | K78: 2023 | L78: 2022 | M78: 2021 | N78: 2020 | O78: 2019 | P78: 2018
B79: =IFERROR(D79/$D$24,"") -> 0.44384074 | C79: Steel mills | D79: 15407266 | E79: 14157229 | F79: 13235463 | G79: 9708260 | H79: 9283216 | I79: 9244086 | K79: =(D79-E79)/E79 -> 0.088296728 | L79: =(E79-F79)/F79 -> 0.069643654 | M79: =(F79-G79)/G79 -> 0.36331979 | N79: =(G79-H79)/H79 -> 0.045786288 | O79: =(H79-I79)/I79 -> 0.0042329766 | P79: -
B80: =IFERROR(D80/$D$24,"") -> 0.31442723 | C80: Steel products | D80: 10914870 | E80: 12087145 | F80: 7845010 | G80: 4461042 | H80: 4610628 | I80: 4734636 | K80: =(D80-E80)/E80 -> -0.096985268 | L80: =(E80-F80)/F80 -> 0.5407431 | M80: =(F80-G80)/G80 -> 0.75856 | N80: =(G80-H80)/H80 -> -0.032443737 | O80: =(H80-I80)/I80 -> -0.026191665 | P80: -
B81: =IFERROR(D81/$D$24,"") -> 0.10217232 | C81: Raw materials | D81: 3546759 | E81: 3383114 | F81: 3870806 | G81: 3324489 | H81: 3316479 | I81: 3492126 | K81: =(D81-E81)/E81 -> 0.048371116 | L81: =(E81-F81)/F81 -> -0.12599236 | M81: =(F81-G81)/G81 -> 0.16433112 | N81: =(G81-H81)/H81 -> 0.002415212 | O81: =(H81-I81)/I81 -> -0.050298013 | P81: -
B85: =SUM(B79:B84) -> 0.86044029 | C85: TOTAL | D85: =SUM(D79:D84) -> 29868895 | E85: =SUM(E79:E84) -> 29627488 | F85: =SUM(F79:F84) -> 24951279 | G85: =SUM(G79:G84) -> 17493791 | H85: =SUM(H79:H84) -> 17210323 | I85: =SUM(I79:I84) -> 17470848 | K85: =(D85-E85)/E85 -> 0.0081480752 | L85: =(E85-F85)/F85 -> 0.1874136 | M85: =(F85-G85)/G85 -> 0.42629342 | N85: =(G85-H85)/H85 -> 0.016470812 | O85: =(H85-I85)/I85 -> -0.014911984 | P85: -
C89: Assets Turnover | D89: Nominal value | K89: YoY Growth
C90: Category | D90: 2023 | E90: 2022 | F90: 2021 | G90: 2020 | H90: 2019 | I90: 2018 | K90: 2023 | L90: 2022 | M90: 2021 | N90: 2020 | O90: 2019 | P90: 2018
C91: Steel mills | D91: =D18/D79 -> 1.304103 | E91: =E18/E79 -> 1.7086577 | F91: =F18/F79 -> 1.8242955 | G91: =G18/G79 -> 2.0744869 | H91: =H18/H79 -> 2.4333009 | I91: =I18/I79 -> 2.7117098 | K91: =(D91-E91)/E91 -> -0.23676753 | L91: =(E91-F91)/F91 -> -0.063387677 | M91: =(F91-G91)/G91 -> -0.12060397 | N91: =(G91-H91)/H91 -> -0.14745979 | O91: =(H91-I91)/I91 -> -0.10266914 | P91: -
C92: Steel products | D92: =D19/D80 -> 1.1689502 | E92: =E19/E80 -> 1.2459789 | F92: =F19/F80 -> 1.2400166 | G92: =G19/G80 -> 1.484646 | H92: =H19/H80 -> 1.5160763 | I92: =I19/I80 -> 1.4354854 | K92: =(D92-E92)/E92 -> -0.061821891 | L92: =(E92-F92)/F92 -> 0.0048082282 | M92: =(F92-G92)/G92 -> -0.16477283 | N92: =(G92-H92)/H92 -> -0.020731391 | O92: =(H92-I92)/I92 -> 0.056141917 | P92: -
C93: Raw materials | D93: =D20/D81 -> 0.52495814 | E93: =E20/E81 -> 0.66869783 | F93: =F20/F81 -> 0.67443318 | G93: =G20/G81 -> 0.42330806 | H93: =H20/H81 -> 0.50199142 | I93: =I20/I81 -> 0.58003634 | K93: =(D93-E93)/E93 -> -0.21495463 | L93: =(E93-F93)/F93 -> -0.0085039518 | M93: =(F93-G93)/G93 -> 0.59324435 | N93: =(G93-H93)/H93 -> -0.15674243 | O93: =(H93-I93)/I93 -> -0.13455178 | P93: -
C97: Average | D97: =AVERAGE(D91:D93) -> 0.9993371 | E97: =AVERAGE(E91:E93) -> 1.2077781 | F97: =AVERAGE(F91:F93) -> 1.2462485 | G97: =AVERAGE(G91:G93) -> 1.3274803 | H97: =AVERAGE(H91:H93) -> 1.4837896 | I97: =AVERAGE(I91:I93) -> 1.5757439 | K97: =(D97-E97)/E97 -> -0.17258223 | L97: =(E97-F97)/F97 -> -0.03086889 | M97: =(F97-G97)/G97 -> -0.061192508 | N97: =(G97-H97)/H97 -> -0.10534462 | O97: =(H97-I97)/I97 -> -0.058356131 | P97: -
C100: Depreciation expense | D100: Nominal value | K100: YoY Growth
C101: Category | D101: 2023 | E101: 2022 | F101: 2021 | G101: 2020 | H101: 2019 | I101: 2018 | K101: 2023 | L101: 2022 | M101: 2021 | N101: 2020 | O101: 2019 | P101: 2018
C102: Steel mills | D102: 610510 | E102: 529005 | F102: 465733 | G102: 449290 | H102: 401609 | I102: 378146 | K102: =(D102-E102)/E102 -> 0.15407227 | L102: =(E102-F102)/F102 -> 0.13585466 | M102: =(F102-G102)/G102 -> 0.036597743 | N102: =(G102-H102)/H102 -> 0.11872493 | O102: =(H102-I102)/I102 -> 0.062047463 | P102: -
C103: Steel products | D103: 131189 | E103: 115501 | F103: 99248 | G103: 93184 | H103: 85276 | I103: 80681 | K103: =(D103-E103)/E103 -> 0.13582566 | L103: =(E103-F103)/F103 -> 0.16376149 | M103: =(F103-G103)/G103 -> 0.065075549 | N103: =(G103-H103)/H103 -> 0.092734181 | O103: =(H103-I103)/I103 -> 0.05695269 | P103: -
C104: Raw materials | D104: 173657 | E104: 171060 | F104: 159886 | G104: 150474 | H104: 151124 | I104: 161666 | K104: =(D104-E104)/E104 -> 0.015181808 | L104: =(E104-F104)/F104 -> 0.069887295 | M104: =(F104-G104)/G104 -> 0.062549012 | N104: =(G104-H104)/H104 -> -0.0043011037 | O104: =(H104-I104)/I104 -> -0.065208516 | P104: -
C105: Corporate | D105: 15229 | E105: 11126 | F105: 10539 | G105: 9163 | H105: 10902 | I105: 10386
C108: Average | D108: =SUM(D102:D105) -> 930585 | E108: =SUM(E102:E105) -> 826692 | F108: =SUM(F102:F105) -> 735406 | G108: =SUM(G102:G105) -> 702111 | H108: =SUM(H102:H105) -> 648911 | I108: =SUM(I102:I105) -> 630879 | K108: =(D108-E108)/E108 -> 0.12567316 | L108: =(E108-F108)/F108 -> 0.12413007 | M108: =(F108-G108)/G108 -> 0.047421277 | N108: =(G108-H108)/H108 -> 0.081983508 | O108: =(H108-I108)/I108 -> 0.028582343 | P108: -
C111: Amortization | D111: Nominal value | K111: YoY Growth
C112: Category | D112: 2023 | E112: 2022 | F112: 2021 | G112: 2020 | H112: 2019 | I112: 2018 | K112: 2023 | L112: 2022 | M112: 2021 | N112: 2020 | O112: 2019 | P112: 2018
C113: Steel mills | D113: 7829 | E113: 7829 | F113: 7829 | G113: 7334 | H113: 8624 | I113: 9400 | K113: =(D113-E113)/E113 -> 0 | L113: =(E113-F113)/F113 -> 0 | M113: =(F113-G113)/G113 -> 0.067493864 | N113: =(G113-H113)/H113 -> -0.14958256 | O113: =(H113-I113)/I113 -> -0.082553191 | P113: -
C114: Steel products | D114: 202129 | E114: 199379 | F114: 93160 | G114: 47773 | H114: 49914 | I114: 51997 | K114: =(D114-E114)/E114 -> 0.013792827 | L114: =(E114-F114)/F114 -> 1.1401782 | M114: =(F114-G114)/G114 -> 0.95005547 | N114: =(G114-H114)/H114 -> -0.042893777 | O114: =(H114-I114)/I114 -> -0.040060003 | P114: -
C115: Raw materials | D115: 27772 | E115: 27734 | F115: 28168 | G115: 28249 | H115: 27204 | I115: 27361 | K115: =(D115-E115)/E115 -> 0.0013701594 | L115: =(E115-F115)/F115 -> -0.015407555 | M115: =(F115-G115)/G115 -> -0.0028673581 | N115: =(G115-H115)/H115 -> 0.038413469 | O115: =(H115-I115)/I115 -> -0.0057380944 | P115: -
C119: Average | D119: =SUM(D113:D115) -> 237730 | E119: =SUM(E113:E115) -> 234942 | F119: =SUM(F113:F115) -> 129157 | G119: =SUM(G113:G115) -> 83356 | H119: =SUM(H113:H115) -> 85742 | I119: =SUM(I113:I115) -> 88758 | K119: =(D119-E119)/E119 -> 0.011866759 | L119: =(E119-F119)/F119 -> 0.81904194 | M119: =(F119-G119)/G119 -> 0.54946255 | N119: =(G119-H119)/H119 -> -0.027827669 | O119: =(H119-I119)/I119 -> -0.033980036 | P119: -
C124: Extra notes: China accounts for over half the global steel consumption, and it's the largest producer.
C126: Company got exposure to automotive market by acquiring a 50% stake in NuMit, through which processes the flat steel products into costumer
C127: specified needs (applicable to several industries such as automotive, agricultural, consumer goods and ohters)
C130: Takeaway: The company is increasing it's exposure to steel products while decrease steel mills
C131: over the years

Sheet Acuerdo
A1: Invertir
A2: NO invertir
A3: Mantener sin elevar posición
A4: Mantener (y seguir comprando)
A5: Liquidar
A6: PENDIENTE

Sheet Peers
B1: Peer Logo | C1: Peer Name | D1: Description
C2: #VALUE! | D2: One of the largest U.S. steel producers and metal recyclers, founded in 1993 and headquartered in Fort Wayne, Indiana. The company operates through steel production, metals recycling, and steel fabrication, serving industries like automotive and construction. Known for its sustainability efforts, SDI uses Electric Arc Furnace (EAF) technology to recycle scrap steel, reducing environmental impact. Its vertically integrated structure ensures efficiency across its supply chain, while OmniSource, its metals recycling arm, is one of North America's largest. SDI emphasizes innovation, safety, and environmental responsibility.
C3: #VALUE! | D3: Founded in 1901, U.S. Steel is one of the largest steel producers in the U.S., headquartered in Pittsburgh, Pennsylvania. It operates integrated steel mills and produces a variety of steel products for industries such as automotive, construction, and energy. U.S. Steel is focused on innovation and sustainability, including the use of advanced manufacturing processes and clean energy solutions. The company is known for its legacy as a key player in America's industrial growth and its ongoing commitment to sustainable steelmaking practices.
C4: #VALUE! | D4: Founded in 1915 and headquartered in Irving, Texas, is a global leader in recycling, manufacturing, and fabricating steel and metal products. CMC operates through a network of steel mills, recycling facilities, and fabrication plants, primarily serving construction, infrastructure, and industrial markets. With a focus on sustainability, CMC heavily relies on Electric Arc Furnace (EAF) technology to recycle scrap metal into new steel products, reducing environmental impact and promoting resource efficiency.
C5: #VALUE! | D5: Founded in 1847 and headquartered in Cleveland, Ohio, is the largest flat-rolled steel producer and iron ore pellet supplier in North America. Originally focused on mining, the company expanded into steel production through acquisitions of AK Steel and ArcelorMittal USA. Cleveland-Cliffs is vertically integrated, from mining raw materials to producing steel for the automotive, infrastructure, and manufacturing industries. The company emphasizes sustainability, innovation, and reducing carbon emissions through advanced steelmaking technologies.
D6: {=_FV(C6,"Description")} -> #VALUE!
B8: In Millions USD | C8: =OP!E2 -> #VALUE! | D8: =C2 -> #VALUE! | E8: =C3 -> #VALUE! | F8: =C4 -> #VALUE! | G8: =C5 -> #VALUE! | H8: =C6 -> 0 | I8: AVERAGE | J8: Deviation from Average
B9: Company Info | I9: =IFERROR(AVERAGE(C9:H9),"") | L9: TRAFFIC
B10: Market Cap | C10: {=_FV(C8,"Market cap",TRUE)/1000000} -> 31590.957 | D10: {=_FV(D8,"Capitalização de mercado",TRUE)/1000000} -> 20721.256 | E10: {=_FV(E8,"Capitalização de mercado",TRUE)/1000000} -> 12416.823 | F10: {=_FV(F8,"Capitalização de mercado",TRUE)/1000000} -> 6733.1792 | G10: {=_FV(G8,"Capitalização de mercado",TRUE)/1000000} -> 5654.3673 | H10: {=_FV(H8,"Capitalização de mercado",TRUE)/1000000} -> #VALUE! | I10: =IFERROR(AVERAGE(C10:G10),"") -> 15423.317 | J10: =_xlfn.STDEV.S(C10:G10) -> 10833.405 | M10: Best Value
B11: Net Sales (current) | C11: =C56 -> 34714 | D11: =D56 -> 18795.316 | E11: =E56 -> 18053 | F11: =F56 -> 8799.533 | G11: =G56 -> 21996 | H11: =H56 -> 0 | I11: =IFERROR(AVERAGE(C11:H11),"") -> 17059.641 | J11: =_xlfn.STDEV.S(C11:G11) -> 9355.0315
B12: Profitability | I12: =IFERROR(AVERAGE(C12:H12),"") | M12: Important Value
B13: Sales Growth (ttm) | C13: =C56/C55-1 -> -0.16375988 | D13: =D56/D55-1 -> -0.15567554 | E13: =E56/E55-1 -> -0.142986 | F13: =F56/F55-1 -> -0.012783782 | G13: =G56/G55-1 -> -0.043194571 | H13: =H56/H55-1 -> #DIV/0! | I13: =AVERAGE(C13:G13) -> -0.10367995 | J13: =_xlfn.STDEV.S(C13:G13) -> 0.07031838
B14: Sales Growth (36m) | C14: =C56/C54-1 -> 0.72363456 | D14: =D56/D54-1 -> 0.96035896 | E14: =E56/E54-1 -> 1.0596691 | F14: =F56/F54-1 -> 0.30755525 | G14: =G56/G54-1 -> 3.1353638 | H14: =H56/H54-1 -> #DIV/0! | I14: =AVERAGE(C14:G14) -> 1.2373163 | J14: =_xlfn.STDEV.S(C14:G14) -> 1.099906 | M14: Worst Value
B15: Operating Margin | C15: =C59/C56 -> 0.17947802 | D15: =D59/D56 -> 0.16765778 | E15: =E59/E56 -> 0.044258572 | F15: =F59/F56 -> 0.13206314 | G15: =G59/G56 -> 0.030778323 | H15: =H59/H56 -> #DIV/0! | I15: =AVERAGE(C15:G15) -> 0.11084717 | J15: =_xlfn.STDEV.S(C15:G15) -> 0.069341219
B16: Net Income Margin | C16: =C62/C56 -> 0.13034652 | D16: =D62/D56 -> 0.13039855 | E16: =E62/E56 -> 0.056832659 | F16: =F62/F56 -> 0.097618817 | G16: =G62/G56 -> 0.018139662 | H16: =H62/H56 -> #DIV/0! | I16: =AVERAGE(C16:G16) -> 0.086667242 | J16: =_xlfn.STDEV.S(C16:G16) -> 0.048801576
B17: Return on Equity (RoE) | C17: =C62/C74 -> 0.21607968 | D17: =D62/D74 -> 0.2827403 | E17: =E62/E74 -> 0.092875894 | F17: =F62/F74 -> 0.20843879 | G17: =G62/G74 -> 0.049125831 | H17: =H62/H74 -> #DIV/0! | I17: =AVERAGE(C17:G17) -> 0.1698521 | J17: =_xlfn.STDEV.S(C17:G17) -> 0.096007599
B18: Return on Invested Capital (ROIC) | C18: =(1+C61/(C59+C60))*C59/(C73+C74-C65) -> 0.22789616 | D18: =(1+D61/(D59+D60))*D59/(D73+D74-D65) -> 0.22964938 | E18: =(1+E61/(E59+E60))*E59/(E73+E74-E65) -> 0.055732666 | F18: =(1+F61/(F59+F60))*F59/(F73+F74-F65) -> 0.1897214 | G18: =(1+G61/(G59+G60))*G59/(G73+G74-G65) -> 0.037672084 | H18: =(1+H61/(H59+H60))*H59/(H73+H74-H65) -> #DIV/0! | I18: =AVERAGE(C18:G18) -> 0.14813434 | J18: =_xlfn.STDEV.S(C18:G18) -> 0.094175519
B19: Solvency | I19: =IFERROR(AVERAGE(C19:H19),"")
B20: Debt/Assets | C20: =C73/C70 -> 0.19360742 | D20: =D73/D70 -> 0.20793619 | E20: =E73/E70 -> 0.20321745 | F20: =F73/F70 -> 0.17547439 | G20: =G73/G70 -> 0.18201517 | H20: =H73/H70 -> #DIV/0! | I20: =AVERAGE(C20:G20) -> 0.19245012 | J20: =_xlfn.STDEV.S(C20:G20) -> 0.013730954
B21: Net Debt/EBITDA | C21: =(C73-C65)/C58 -> 0.061914972 | D21: =(D73-D65)/D58 -> 0.47342438 | E21: =(E73-E65)/E58 -> 0.70437318 | F21: =(F73-F65)/F58 -> 0.41469263 | G21: =(G73-G65)/G58 -> 1.566719 | H21: =(H73-H65)/H58 -> #DIV/0! | I21: =AVERAGE(C21:G21) -> 0.64422483 | J21: =_xlfn.STDEV.S(C21:G21) -> 0.56470256
B22: Interest Coverage Ratio | C22: =-C58/C60 -> -250.11822 | D22: =-D58/D60 -> 46.924651 | E22: =-E58/E60 -> -6.9153226 | F22: =-F58/F60 -> 34.413836 | G22: =-G58/G60 -> 6.6124567 | H22: =-H58/H60 -> #DIV/0! | I22: =AVERAGE(C22:G22) -> -33.816519 | J22: =_xlfn.STDEV.S(C22:G22) -> 122.79975
B23: Liquidity
B24: Current Ratio | C24: =C68/C72 -> 3.5663999 | D24: =D68/D72 -> 2.9103621 | E24: =E68/E72 -> 1.758612 | F24: =F68/F72 -> 3.7265649 | G24: =G68/G72 -> 1.8916762 | H24: =H68/H72 -> #DIV/0! | I24: =AVERAGE(C24:G24) -> 2.770723 | J24: =_xlfn.STDEV.S(C24:G24) -> 0.91696874
B25: Quick Ratio | C25: =(C65+C66)/C72 -> 2.0321231 | D25: =(D65+D66)/D72 -> 1.2902282 | E25: =(E65+E66)/E72 -> 1.1388045 | F25: =(F65+F66)/F72 -> 2.1720026 | G25: =(G65+G66)/G72 -> 0.58095781 | H25: =(H65+H66)/H72 -> #DIV/0! | I25: =AVERAGE(C25:G25) -> 1.4428232 | J25: =_xlfn.STDEV.S(C25:G25) -> 0.65907162
B26: Activity | I26: =IFERROR(AVERAGE(C26:H26),"")
B27: Inventory Turnover | C27: =C57/C67 -> 4.8226528 | D27: =D57/D67 -> 5.0954432 | E27: =E57/E67 -> 7.4262218 | F27: =F57/F67 -> 6.7475275 | G27: =G57/G67 -> 4.6199552 | H27: =H57/H67 -> #DIV/0! | I27: =AVERAGE(C27:G27) -> 5.7423601 | J27: =_xlfn.STDEV.S(C27:G27) -> 1.2619338
B28: Acc. Receivable Turnover | C28: =C56/C66 -> 11.754269 | D28: =D56/D66 -> 11.686398 | E28: =E56/E66 -> 11.662145 | F28: =F56/F66 -> 7.0951559 | G28: =G56/G66 -> 11.954348 | H28: =H56/H66 -> #DIV/0! | I28: =AVERAGE(C28:G28) -> 10.830463 | J28: =_xlfn.STDEV.S(C28:G28) -> 2.091254
A29: Price/Sales | B29: Payables Turnover | C29: =C57/C71 -> 13.314722 | D29: =D57/D71 -> 13.552354 | E29: =E57/E71 -> 5.2189564 | F29: =F57/F71 -> 19.176207 | G29: =G57/G71 -> 9.8165793 | H29: =H57/H71 -> #DIV/0! | I29: =AVERAGE(C29:G29) -> 12.215764 | J29: =_xlfn.STDEV.S(C29:G29) -> 5.1515374
B30: Fixed Asset Turnover | C30: =C56/C69 -> 3.1416039 | D30: =D56/D69 -> 2.7910169 | E30: =E56/E69 -> 1.7370345 | F30: =F56/F69 -> 1.9408621 | G30: =G56/G69 -> 2.4728499 | H30: =H56/H69 -> #DIV/0! | I30: =AVERAGE(C30:G30) -> 2.4166735 | J30: =_xlfn.STDEV.S(C30:G30) -> 0.58247712
B31: Total Asset Turnover | C31: =C56/C70 -> 0.98227246 | D31: =D56/D70 -> 1.2607182 | E31: =E56/E70 -> 0.88274412 | F31: =F56/F70 -> 1.3254117 | G31: =G56/G70 -> 1.2542624 | H31: =H56/H70 -> #DIV/0! | I31: =AVERAGE(C31:G31) -> 1.1410818 | J31: =_xlfn.STDEV.S(C31:G31) -> 0.19561377
B32: Valuation | I32: =IFERROR(AVERAGE(C32:H32),"")
B33: Price/Earnings | C33: =C10/C62 -> 6.98166 | D33: =D10/D62 -> 8.4546117 | E33: =E10/E62 -> 12.102167 | F33: =F10/F62 -> 7.8383926 | G33: =G10/G62 -> 14.171347 | H33: =H10/H62 -> #VALUE! | I33: =AVERAGE(C33:G33) -> 9.9096356 | J33: =_xlfn.STDEV.S(C33:G33) -> 3.0801606
B34: Price/Sales | C34: =C10/C56 -> 0.91003506 | D34: =D10/D56 -> 1.1024691 | E34: =E10/E56 -> 0.68779834 | F34: =F10/F56 -> 0.76517461 | G34: =G10/G56 -> 0.25706343 | H34: =H10/H56 -> #VALUE! | I34: =AVERAGE(C34:G34) -> 0.74450811 | J34: =_xlfn.STDEV.S(C34:G34) -> 0.31495264
B35: Price/Book | C35: =C10/C74 -> 1.5085949 | D35: =D10/D74 -> 2.3904595 | E35: =E10/E74 -> 1.1239996 | F35: =F10/F74 -> 1.633825 | G35: =G10/G74 -> 0.69617918 | H35: =H10/H74 -> #VALUE! | I35: =AVERAGE(C35:G35) -> 1.4706116 | J35: =_xlfn.STDEV.S(C35:G35) -> 0.63128577
B36: EV/Sales | C36: =(C73+C10-C65)/C56 -> 0.92325402 | D36: =(D73+D10-D65)/D56 -> 1.19287 | E36: =(E73+E10-E65)/E56 -> 0.75471243 | F36: =(F73+F10-F65)/F56 -> 0.83025295 | G36: =(G73+G10-G65)/G56 -> 0.39317909 | H36: =(H73+H10-H65)/H56 -> #VALUE! | I36: =AVERAGE(C36:G36) -> 0.8188537 | J36: =_xlfn.STDEV.S(C36:G36) -> 0.28992695
B37: EV/EBITDA | C37: =(C73+C10-C65)/C58 -> 4.3243375 | D37: =(D73+D10-D65)/D58 -> 6.2469942 | E37: =(E73+E10-E65)/E58 -> 7.9445035 | F37: =(F73+F10-F65)/F58 -> 5.2905433 | G37: =(G73+G10-G65)/G58 -> 4.5255716 | H37: =(H73+H10-H65)/H58 -> #VALUE! | I37: =AVERAGE(C37:G37) -> 5.66639 | J37: =_xlfn.STDEV.S(C37:G37) -> 1.4807713
B38: Stock Info | I38: =IFERROR(AVERAGE(C38:H38),"")
B39: Float | C39: =OP!M20 -> 0.99169967 | D39: =143.93/154.3 -> 0.93279326 | E39: =202.58/224.96 -> 0.90051565 | F39: =114.03/114.99 -> 0.99165145 | G39: =458.79/468.04 -> 0.98023673 | I39: =IFERROR(AVERAGE(C39:H39),"") -> 0.95937935 | J39: =_xlfn.STDEV.S(C39:G39) -> 0.040905004
B40: b (Yahoo) | C40: =OP!M22 -> 1.7855 | D40: 1.97 | E40: 1.87 | F40: 1.14 | G40: 1.97 | I40: =IFERROR(AVERAGE(C40:H40),"") -> 1.7471 | J40: =_xlfn.STDEV.S(C40:G40) -> 0.34803671
B41: Dividend Yield (yahoo finance) | C41: =OP!M32 -> 0.016287256 | D41: 0 | E41: 0.0054 | F41: 0.0136 | G41: 0 | I41: =IFERROR(AVERAGE(C41:H41),"") -> 0.0070574512 | J41: =_xlfn.STDEV.S(C41:G41) -> 0.0075887518
B42: Stock Performance
B43: 1y | C43: 0.0311 | D43: 0.2129 | E43: 0.1119 | F43: 0.2298 | G43: -0.1504 | I43: =AVERAGE(C43:G43) -> 0.08706 | J43: =_xlfn.STDEV.S(C43:G43) -> 0.15519843
B44: 3y | C44: 1.9314 | D44: 3.334 | E44: 2.3127 | F44: 1.8309 | G44: 0.7964 | I44: =AVERAGE(C44:G44) -> 2.04108 | J44: =_xlfn.STDEV.S(C44:G44) -> 0.91526679
B45: Current Price | C45: {=_FV(C8,"Price")} -> 137.63 | D45: {=_FV(D8,"Preço")} -> 140.765 | E45: {=_FV(E8,"Preço")} -> 54.84 | F45: {=_FV(F8,"Preço")} -> 60.155 | G45: {=_FV(G8,"Preço")} -> 11.43 | H45: {=_FV(H8,"Preço")} -> #VALUE! | I45: =AVERAGE(C45:G45) -> 80.964 | J45: =_xlfn.STDEV.S(C45:G45) -> 56.430599
B46: Average Target Price | C46: 166.47 | D46: 132.3 | E46: 41.87 | F46: 63.42 | G46: 14.61 | I46: =AVERAGE(C46:G46) -> 83.734 | J46: =_xlfn.STDEV.S(C46:G46) -> 63.535979
B47: Upside/Downside | C47: =C46/C45-1 -> 0.20954734 | D47: =D46/D45-1 -> -0.060135687 | E47: =E46/E45-1 -> -0.2365062 | F47: =F46/F45-1 -> 0.054276452 | G47: =G46/G45-1 -> 0.27821522 | H47: =H46/H45-1 -> #VALUE! | I47: =AVERAGE(C47:G47) -> 0.049079425 | J47: =_xlfn.STDEV.S(C47:G47) -> 0.20722407
B48: Extra | I48: =IFERROR(AVERAGE(C48:H48),"")
B49: 3y Operating Cash Flow | C49: =(Inputs!B58-Inputs!E58)/Inputs!E58 -> 1.6370648 | D49: =3519/987 -> 3.5653495 | E49: =2100/138 -> 15.217391 | F49: =7925.972/791.204 -> 10.017609 | G49: =21996/5354 -> 4.1083302 | I49: =IFERROR(AVERAGE(C49:H49),"") -> 6.9091489 | J49: =_xlfn.STDEV.S(C49:G49) -> 5.6015592
B50: R&D/Net Sales | C50: =C63/C11 -> 0.0038582416 | D50: =D63/D11 -> 0 | E50: =E63/E11 -> 0 | F50: =F63/F11 -> 0 | G50: =G63/G11 -> 0 | H50: =H63/H11 -> #DIV/0! | I50: =AVERAGE(C50:G50) -> 0.00077164833 | J50: =_xlfn.STDEV.S(C50:G50) -> 0.0017254581
B52: Financial Data | C52: =OP!E2 -> #VALUE! | D52: =D8 -> #VALUE! | E52: =E8 -> #VALUE! | F52: =F8 -> #VALUE! | G52: =G8 -> #VALUE! | H52: =H8 -> 0
B53: IS
B54: Net Sales (36m ago) | C54: ='Fin. Data'!E5 -> 20140 | D54: 9587.691 | E54: 8765 | F54: 6729.76 | G54: 5319
B55: Net Sales (12m ago) | C55: ='Fin. Data'!C5 -> 41512 | D55: 22260.774 | E55: 21065 | F55: 8913.481 | G55: 22989
B56: Net Sales (current) | C56: ='Fin. Data'!B5 -> 34714 | D56: 18795.316 | E56: 18053 | F56: 8799.533 | G56: 21996
B57: COGS | C57: ='Fin. Data'!B5-'Fin. Data'!B7 -> 26899.6 | D57: 14749.433 | E57: 15803 | F57: 6987.618 | G57: 20605
B58: EBITDA | C58: ='Fin. Data'!B19 -> 7411.503 | D58: =437.804+3151.181 -> 3588.985 | E58: =799+916 -> 1715 | F58: =F59+218.83 -> 1380.924 | G58: 1911
B59: Operating Income | C59: ='Fin. Data'!B11 -> 6230.4 | D59: 3151.181 | E59: 799 | F59: =1121.967+40.127 -> 1162.094 | G59: 677
B60: Net Financial Cost | C60: ='Fin. Data'!B14 -> 29.632 | D60: -76.484 | E60: 248 | F60: -40.127 | G60: -289
B61: Taxes | C61: ='Fin. Data'!B21 -> -1359.966 | D61: -751.611 | E61: -152 | F61: -262.207 | G61: -148
B62: Net Income | C62: ='Fin. Data'!B23 -> 4524.849 | D62: 2450.882 | E62: 1026 | F62: 859 | G62: 399
B63: R&D | C63: 133.935
B64: BS
B65: Cash & Eq. | C65: ='Fin. Data'!B41 -> 6383.3 | D65: 1400.887 | E65: 2948 | F65: 592.332 | G65: 198
B66: Acc. Receivables | C66: ='Fin. Data'!B42 -> 2953.31 | D66: =1535.062+73.245 -> 1608.307 | E66: =1390+158 -> 1548 | F66: 1240.217 | G66: 1840
B67: Inventory | C67: ='Fin. Data'!B43 -> 5577.76 | D67: 2894.632 | E67: 2128 | F67: 1035.582 | G67: 4460
B68: Current Assets | C68: =Inputs!B27 -> 16385.86 | D68: 6787.826 | E68: 6943 | F68: 3144.155 | G68: 6636
B69: Fixed Assets | C69: ='Fin. Data'!B44 -> 11049.77 | D69: 6734.218 | E69: 10393 | F69: 4533.827 | G69: 8895
B70: Total Assets | C70: ='Fin. Data'!B46 -> 35340.5 | D70: 14908.42 | E70: 20451 | F70: 6639.094 | G70: 17537
B71: Acc. Payable | C71: =Inputs!B43 -> 2020.29 | D71: =1078.645+9.685 -> 1088.33 | E71: =2889+139 -> 3028 | F71: 364.39 | G71: 2099
B72: Current Liabilities | C72: =Inputs!B42 -> 4594.51 | D72: 2332.296 | E72: 3948 | F72: 843.714 | G72: 3508
B73: Total Debt | C73: ='Fin. Data'!B63 -> 6842.183 | D73: 3100 | E73: 4156 | F73: 1164.991 | G73: 3192
B74: Total Equity | C74: ='Fin. Data'!B69 -> 20940.65 | D74: 8668.315 | E74: 11047 | F74: 4121.114 | G74: 8122

Sheet ESG
B1: Company GICS Sector: | T1: Yes
B2: Materials | C2: <- Select Industry | T2: No
B3: ESG Analysis | K3: Relative ESG Analysis
B4: Parameters | C4: Impact | D4: Do they report? | E4: Ranking | F4: Mitigation Plan | G4: Traffic Lights | H4: Improvement over time? | I4: Targets / Goals? | J4: Comments | K4: Parameters | L4: =Peers!C8 -> #VALUE! | M4: =Peers!D8 -> #VALUE! | N4: =Peers!E8 -> #VALUE! | O4: =Peers!F8 -> #VALUE! | P4: =Peers!G8 -> #VALUE! | Q4: =Peers!H8 -> 0 | R4: AVERAGE
B5: Environmental | K5: Ratios
A6: 1 | B6: CO2 Direct Emissions | C6: =VLOOKUP($B$2,'Sector Impact'!$K$4:$AA$16,A6+1,FALSE) -> Very High | E6: Medium | K6: CO2 Emissions/$M Sales | L6: =L12/L$11 -> 195.88639 | M6: =M12/M$11 -> 109.415 | N6: =N12/N$11 -> 1508.3366 | O6: =O12/O$11 -> 120.0217 | P6: =P12/P$11 -> 1268.4124 | Q6: =Q12/Q$11 -> #VALUE! | R6: =IFERROR(AVERAGE(L6:P6),"") -> 640.41442 | Z6: 2018 | AA6: 2019 | AB6: 2020 | AC6: 2021 | AD6: 2022 | AE6: 2023
A7: 2 | B7: Total Water Consumption | C7: =VLOOKUP($B$2,'Sector Impact'!$K$4:$AA$16,A7+1,FALSE) -> Very High | E7: Medium High | K7: Water Consumption/$M Sales | L7: =L13/L$11 -> 863.05237 | M7: =M13/M$11 -> 971.90742 | N7: =N14/N$11 -> 19081.815 | O7: =O13/O$11 -> 722.1417 | P7: =P13/P$11 -> 47.291189 | Q7: =Q13/Q$11 -> #VALUE! | R7: =IFERROR(AVERAGE(L7:P7),"") -> 4337.2415 | Y7: CO2 Emissions Total (Tonnes) | Z7: 22417073 | AA7: 21208537 | AB7: 21208537 | AC7: 12800000 | AD7: 11500000 | AE7: =6.8*10^6 -> 6800000
A8: 3 | B8: Total Energy Consumption | C8: =VLOOKUP($B$2,'Sector Impact'!$K$4:$AA$16,A8+1,FALSE) -> Very High | E8: Medium | K8: Energy Consumption/$M Sales | L8: =L14/L$11 -> 3364.003 | M8: =M14/M$11 -> 2861.3269 | N8: =N14/N$11 -> 19081.815 | O8: =O14/O$11 -> 2232.5109 | P8: =P14/P$11 -> 18392.533 | Q8: =Q14/Q$11 -> #VALUE! | R8: =IFERROR(AVERAGE(L8:P8),"") -> 9186.4377 | Y8: Water Consumption Total (Cubic Meters) | Z8: 25000000 | AA8: 27000000 | AB8: 27000000 | AC8: 28000000 | AD8: 31000000 | AE8: 29960000
A9: 4 | B9: Waste Management | C9: =VLOOKUP($B$2,'Sector Impact'!$K$4:$AA$16,A9+1,FALSE) -> Very High | E9: Medium High | K9: Waste Production/$M Sales | L9: =L15/L$11 -> 37.045572 | M9: =M15/M$11 -> 22.923277 | N9: =N15/N$11 -> 126.84734 | O9: =O15/O$11 -> 116.60602 | P9: =P15/P$11 -> 99.06192 | Q9: =Q15/Q$11 -> #VALUE! | R9: =IFERROR(AVERAGE(L9:P9),"") -> 80.496826 | Y9: Energy Consumption Total (Gigajoules) | Z9: 120000000 | AA9: 112000000 | AB9: 112000000 | AC9: -- | AD9: -- | AE9: 116778000
A10: 5 | B10: Land Degradation/Deforestation/Biodiversity loss/Animal sufering/… | C10: =VLOOKUP($B$2,'Sector Impact'!$K$4:$AA$16,A10+1,FALSE) -> High | K10: Inputs | Y10: Waste Production Total (Tonnes) | AE10: 1286000
B11: Social | K11: Net Sales ($M) | L11: 34714 | M11: 18795 | N11: 18053 | O11: 8800 | P11: 21996 | Q11: ="-" -> -
A12: 6 | B12: Employee Turnover % | C12: =VLOOKUP($B$2,'Sector Impact'!$K$4:$AA$16,A12+1,FALSE) -> High | K12: CO2 Emissions Total (Tonnes) | L12: =6.8*10^6 -> 6800000 | M12: 2056455 | N12: =27.23*10^6 -> 27230000 | O12: 1056191 | P12: =27.9*10^6 -> 27900000 | Q12: ="-" -> -
A13: 7 | B13: Salaries & Compensation | C13: =VLOOKUP($B$2,'Sector Impact'!$K$4:$AA$16,A13+1,FALSE) -> High | K13: Water Consumption Total (Cubic Meters) | L13: 29960000 | M13: 18267000 | N13: 1162679000 | O13: 6354847 | P13: 1040217 | Q13: ="-" -> -
A14: 8 | B14: Reputation | C14: =VLOOKUP($B$2,'Sector Impact'!$K$4:$AA$16,A14+1,FALSE) -> Medium | K14: Energy Consumption Total (Gigajoules) | L14: 116778000 | M14: 53778640 | N14: 344484000 | O14: 19646096 | P14: 404562156 | Q14: ="-" -> -
A15: 9 | B15: Discrimination Events | C15: =VLOOKUP($B$2,'Sector Impact'!$K$4:$AA$16,A15+1,FALSE) -> High | F15: Yes | K15: Waste Production Total (Tonnes) | L15: 1286000 | M15: 430843 | N15: =2087486+202489 -> 2289975 | O15: 1026133 | P15: =561933+1617033 -> 2178966 | Q15: ="-" -> -
A16: 10 | B16: Work Safety | C16: =VLOOKUP($B$2,'Sector Impact'!$K$4:$AA$16,A16+1,FALSE) -> Low | K16: ESG Scores
A17: 11 | B17: Damage to consumer health | C17: =VLOOKUP($B$2,'Sector Impact'!$K$4:$AA$16,A17+1,FALSE) -> Very High | K17: Refinitiv | L17: 54 (55/66/35) | M17: 59 (65/45/73) | N17: 60 (62/63/53) | O17: 71 (74/68/74) | P17: 67 (71/55/83) | Q17: ="-" -> -
A18: 12 | B18: PXP? | C18: =VLOOKUP($B$2,'Sector Impact'!$K$4:$AA$16,A18+1,FALSE) -> Medium | K18: Sustainalytics | L18: 31.9 (high risk) | M18: 31.5 (high risk) | N18: 33.1 (high risk) | O18: 25.9 (medium risk) | P18: 36.6 (high risk) | Q18: ="-" -> -
A19: 13 | B19: Supply chain | C19: =VLOOKUP($B$2,'Sector Impact'!$K$4:$AA$16,A19+1,FALSE) -> Medium | K19: ISS | L19: C | M19: C | N19: C- | O19: B- | P19: C+ | Q19: ="-" -> -
A20: 14 | B20: Community involvement | C20: =VLOOKUP($B$2,'Sector Impact'!$K$4:$AA$16,A20+1,FALSE) -> Very High | K20: CDP | L20: F/D | M20: F/B- | N20: B/A- | O20: F/F | P20: B/B | Q20: ="-" -> -
A21: 15 | B21: Public Sector | C21: =VLOOKUP($B$2,'Sector Impact'!$K$4:$AA$16,A21+1,FALSE) -> High
A22: 16 | B22: Litigation | C22: =VLOOKUP($B$2,'Sector Impact'!$K$4:$AA$16,A22+1,FALSE) -> Medium | D22: Yes
B23: Corporate Governance | K23: PARAMETERS
A24: 17 | B24: Diversity (Gender, Age, Industry, Region) | K24: IMPACT | L24: RANKING | M24: MITIGATION PLAN | O24: TRAFFIC
A25: 18 | B25: % Independence | K25: Low | L25: "Best in class" | M25: Is there evidence of a plan/program ?
A26: 19 | B26: average time as independent directors | K26: Medium | L26: Medium High
A27: 20 | B27: Recent departures of directors / C-level executives? | K27: High | L27: Medium
A28: 21 | B28: CEO/Chairman duality | K28: Very high | L28: "Villain"
A29: 22 | B29: Transparency (ESG, segments, acquisitions, other)
A30: 23 | B30: Time taken to report after the end of the quarter / year
A31: 24 | B31: Additional participation of the CEO in other boards or excessive participation of Ch.
A32: 25 | B32: Audit / Consulting
A33: 26 | B33: ESG-compensation related
A34: 27 | B34: Management compensation schemes

Sheet DCF
A1: VALUATION MODEL
G3: Short Term | K3: Long Term
A4: Section | B4: Line # | C4: ITEM | D4: 2021 (Real) | E4: 2022 (Real) | F4: 2023 (Real) | G4: 2024 | H4: =G4+1 -> 2025 | I4: =H4+1 -> 2026 | J4: =I4+1 -> 2027 | K4: =J4+1 -> 2028 | L4: =K4+1 -> 2029 | M4: =L4+1 -> 2030 | N4: =M4+1 -> 2031 | O4: =N4+1 -> 2032 | ... AF4: =AE4+1 -> 2049
A5: INCOME STATEMENT | B5: 1 | C5: Growth | D5: ='Fin. Data'!D6 -> 0.81151936 | E5: =+E6/D6-1 -> 0.13781384 | F5: =+F6/E6-1 -> -0.16375988 | G5: =+G6/F6-1 -> -0.10541209 | H5: =+H6/G6-1 -> -0.035996523 | I5: =+I6/H6-1 -> -0.013013248 | J5: =+J6/I6-1 -> -0.012944607 | K5: =+K6/J6-1 -> 0.020795344 | L5: =+L6/K6-1 -> 0.020441751 | ... AE5: =+AE6/AD6-1 -> 0.055876363 | AF5: 0.02
B6: 2 | C6: Revenues/Sales | D6: =Inputs!D6 -> 36484 | E6: =Inputs!C6 -> 41512 | F6: =Inputs!B6 -> 34714 | G6: =Assumptions!K170 -> 31054.725 | H6: =Assumptions!L170 -> 29936.863 | I6: =Assumptions!M170 -> 29547.287 | J6: =Assumptions!N170 -> 29164.809 | K6: =Assumptions!O170 -> 29771.301 | L6: =Assumptions!P170 -> 30379.879 | M6: =Assumptions!Q170 -> 31097.595 | N6: =Assumptions!R170 -> 32453.664 | ... AE6: =Assumptions!AI170 -> 74563.147 | AF6: =AE6*(1+AF5) -> 76054.41
B7: 3 | C7: EBIT/Operating Margin | D7: =D8/D6 -> 0.25541087 | E7: =E8/E6 -> 0.25309019 | F7: =F8/F6 -> 0.17947802 | G7: =Assumptions!K181 -> 0.12904278 | H7: =Assumptions!L181 -> 0.14099639 | I7: =Assumptions!M181 -> 0.16202048 | J7: =Assumptions!N181 -> 0.17579154 | K7: =Assumptions!O181 -> 0.17640177 | L7: =Assumptions!P181 -> 0.17674056 | M7: =Assumptions!Q181 -> 0.1642265 | N7: =Assumptions!R181 -> 0.15697337 | ... AF7: =Assumptions!AJ181 -> 0.18831415
B8: 4 | C8: EBIT | D8: ='Fin. Data'!D11 -> 9318.41 | E8: ='Fin. Data'!C11 -> 10506.28 | F8: ='Fin. Data'!B11 -> 6230.4 | G8: =G7*G6 -> 4007.388 | H8: =H7*H6 -> 4220.9895 | I8: =I7*I6 -> 4787.2657 | J8: =J7*J6 -> 5126.9267 | K8: =K7*K6 -> 5251.7103 | L8: =L7*L6 -> 5369.3568 | M8: =M7*M6 -> 5107.0491 | N8: =N7*N6 -> 5094.3612 | ... AF8: =AF7*AF6 -> 14322.121
B9: 5a | C9: (Dep) | D9: 735.406 | E9: 826.692 | F9: 930.585 | G9: =$D$53*DCF!F40 -> -455.25052 | H9: =$D$53*DCF!G40 -> -544.81235 | I9: =$D$53*DCF!H40 -> -631.15026 | J9: =$D$53*DCF!I40 -> -716.36464 | K9: =$E$53*DCF!J40 -> -800.47595 | L9: =$E$53*DCF!K40 -> -861.80483 | M9: =$E$53*DCF!L40 -> -924.38738 | N9: =$E$53*DCF!M40 -> -988.44842 | O9: =$E$53*DCF!N40 -> -1055.303 | P9: =$E$53*DCF!O40 -> -1125.111 | Q9: =$E$53*DCF!P40 -> -1198.0656 | R9: =$E$53*DCF!Q40 -> -1274.3747 | ... AF9: =$E$53*DCF!AE40 -> -2844.9917 | AG9: =SUM(D9:AF9) -> -36428.82
B10: 5b | C10: (Amort) | D10: 129.154 | E10: 234.938 | F10: 237.735 | G10: =F38*$D$54 -> -353.8431 | H10: =G38*$D$54 -> -371.53526 | I10: =H38*$D$54 -> -390.11202 | J10: =I38*$D$54 -> -409.61762 | K10: =J38*$E$54 -> -387.08865 | L10: =K38*$E$54 -> -404.50764 | M10: =L38*$E$54 -> -422.71048 | N10: =M38*$E$54 -> -441.73245 | O10: =N38*$E$54 -> -461.61041 | P10: =O38*$E$54 -> -482.38288 | Q10: =P38*$E$54 -> -504.09011 | R10: =Q38*$E$54 -> -526.77417 | ... AF10: =AE38*$E$54 -> -975.55675
B11: 5c | C11: (Stock based compensation) | D11: 135.775 | E11: 136.834 | F11: 130.162 | G11: =G6*$D$55 -> -114.90248 | H11: =H6*$D$55 -> -110.76639 | I11: =I6*$D$55 -> -109.32496 | J11: =J6*$D$55 -> -107.90979 | K11: =K6*$D$55 -> -110.15381 | L11: =L6*$D$55 -> -112.40555 | M11: =M6*$D$55 -> -115.0611 | N11: =N6*$D$55 -> -120.07856 | ... AF11: =AF6*$D$55 -> -281.40132
B12: 6 | C12: EBITDA | D12: =D8-D9-D10 -> 8453.85 | E12: =E8-E9-E10 -> 9444.65 | F12: =F8-F9-F10 -> 5062.08 | G12: =G8-G9-G10 -> 4816.4816 | H12: =H8-H9-H10 -> 5137.3371 | I12: =I8-I9-I10 -> 5808.528 | J12: =J8-J9-J10 -> 6252.909 | K12: =K8-K9-K10 -> 6439.2749 | ... AF12: =AF8-AF9-AF10 -> 18142.67
B13: 7 | C13: (Net financing cost) | D13: ='Fin. Data'!D14 -> -158.854 | E13: ='Fin. Data'!C14 -> -170.216 | F13: ='Fin. Data'!B14 -> 29.632 | G13: 129.96314 | H13: =G43*$D$58-G44*$D$57 -> 451.85564 | I13: =H43*$D$58-H44*$D$57 -> 507.92127 | J13: =I43*$D$58-I44*$D$57 -> 620.12052 | K13: =J43*$E$58-J44*$E$57 -> 577.48263 | L13: =K43*$E$58-K44*$E$57 -> 542.0755 | M13: =L43*$E$58-L44*$E$57 -> 586.25829 | N13: =M43*$E$58-M44*$E$57 -> 613.64467 | O13: =N43*$E$58-N44*$E$57 -> 651.64939 | P13: =O43*$E$58-O44*$E$57 -> 706.84399 | Q13: =P43*$E$58-P44*$E$57 -> 767.28826 | R13: =Q43*$E$58-Q44*$E$57 -> 826.79829 | ... AF13: =AE43*$E$58-AE44*$E$57 -> 2199.0332
B14: 8 | C14: Other income/(cost) | D14: ='Fin. Data'!D15 -> -40.907 | E14: ='Fin. Data'!C15 -> 91.042 | F14: ='Fin. Data'!B15 -> -12.783 | G14: =AVERAGE(D14:F14)*(1+G5) -> 11.138216 | H14: =AVERAGE(E14:G14)*(1+H5) -> 28.726409 | I14: =AVERAGE(F14:H14)*(1+I5) -> 8.909735 | J14: =AVERAGE(G14:I14)*(1+J5) -> 16.047665 | K14: =AVERAGE(H14:J14)*(1+K5) -> 18.266727 | L14: =AVERAGE(I14:K14)*(1+L5) -> 14.702568 | M14: =AVERAGE(J14:L14)*(1+M5) -> 16.724991 | N14: =AVERAGE(K14:M14)*(1+N5) -> 17.2871 | ... AF14: =AVERAGE(AC14:AE14)*(1+AF5) -> 25.576067
B15: 9 | C15: Earnings before taxes | D15: =D8+D13+D14 -> 9118.649 | E15: =E8+E13+E14 -> 10427.106 | F15: =F8+F13+F14 -> 6247.249 | G15: =G8+G13+G14 -> 4148.4893 | H15: =H8+H13+H14 -> 4701.5715 | I15: =I8+I13+I14 -> 5304.0967 | J15: =J8+J13+J14 -> 5763.0949 | K15: =K8+K13+K14 -> 5847.4597 | ... AF15: =AF8+AF13+AF14 -> 16546.731
B16: 10 | C16: (Income tax) | D16: ='Fin. Data'!D21 -> -2078.488 | E16: ='Fin. Data'!C21 -> -2165.204 | F16: ='Fin. Data'!B21 -> -1359.966 | G16: =-$D$56*G15 -> -871.18276 | H16: =-$D$56*H15 -> -987.33002 | I16: =-$D$56*I15 -> -1113.8603 | J16: =-$D$56*J15 -> -1210.2499 | K16: =-$E$56*K15 -> -1227.9665 | L16: =-$E$56*L15 -> -1244.4883 | M16: =-$E$56*M15 -> -1199.1068 | N16: =-$E$56*N15 -> -1202.3115 | O16: =-$E$56*O15 -> -1280.0389 | P16: =-$E$56*P15 -> -1371.6445 | Q16: =-$E$56*Q15 -> -1446.2224 | R16: =-$E$56*R15 -> -1530.4897 | ... AF16: =-$E$56*AF15 -> -3474.8134
B17: 11 | C17: Net income | D17: ='Fin. Data'!D23 -> 6826.975 | E17: ='Fin. Data'!C23 -> 7607.818 | F17: ='Fin. Data'!B23 -> 4524.849 | G17: =G16+G15 -> 3277.3066 | H17: =H16+H15 -> 3714.2415 | I17: =I16+I15 -> 4190.2364 | J17: =J16+J15 -> 4552.845 | K17: =K16+K15 -> 4619.4931 | L17: =L16+L15 -> 4681.6466 | M17: =M16+M15 -> 4510.9256 | N17: =N16+N15 -> 4522.9815 | ... AF17: =AF16+AF15 -> 13071.917
A19: CASH FLOW STATEMENT | B19: 12 | C19: Operating cash flows before WK | D19: =Inputs!D59+Inputs!D60+Inputs!D62 -> 8093.69 | E19: =Inputs!C59+Inputs!C60+Inputs!C62 -> 9194.56 | F19: =Inputs!B59+Inputs!B60+Inputs!B62 -> 6253.49 | G19: =G17-G10-G9-G11 -> 4201.3027 | H19: =H17-H10-H9-H11 -> 4741.3555 | I19: =I17-I10-I9-I11 -> 5320.8236 | J19: =J17-J10-J9-J11 -> 5786.737 | K19: =K17-K10-K9-K11 -> 5917.2115 | L19: =L17-L10-L9-L11 -> 6060.3646 | M19: =M17-M10-M9-M11 -> 5973.0845 | N19: =N17-N10-N9-N11 -> 6073.2409 | ... AF19: =AF17-AF10-AF9-AF11 -> 17173.867
B20: 13 | C20: (Stock-based compensation) | D20: 135.775 | E20: 136.834 | F20: 130.162 | G20: =G11 -> -114.90248 | H20: =H11 -> -110.76639 | I20: =I11 -> -109.32496 | J20: =J11 -> -107.90979 | K20: =K11 -> -110.15381 | L20: =L11 -> -112.40555 | M20: =M11 -> -115.0611 | N20: =N11 -> -120.07856 | ... AF20: =AF11 -> -281.40132
B21: 14 | C21: (Working Capital Flows) | D21: =Inputs!D61 -> -1862.89 | E21: =Inputs!C61 -> 877.44 | F21: =Inputs!B61 -> 858.41 | G21: =G6*$D$60 -> 931.64174 | H21: =H6*$D$60 -> 898.10588 | I21: =I6*$D$60 -> 886.4186 | J21: =J6*$D$60 -> 874.94426 | K21: =K6*$E$60 -> 744.28253 | L21: =L6*$E$60 -> 759.49696 | M21: =M6*$E$60 -> 777.43988 | N21: =N6*$E$60 -> 811.34161 | O21: =O6*$E$60 -> 847.18523 | P21: =P6*$E$60 -> 885.37059 | Q21: =Q6*$E$60 -> 926.08154 | R21: =R6*$E$60 -> 969.51737 | ... AF21: =AF6*$E$60 -> 1901.3602
B22: 15 | C22: -Total Operating Cash Flow | D22: =D19+D20+D21 -> 6366.575 | E22: =E19+E20+E21 -> 10208.834 | F22: =F19+F20+F21 -> 7242.062 | G22: =G19+G20+G21 -> 5018.0419 | H22: =H19+H20+H21 -> 5528.695 | I22: =I19+I20+I21 -> 6097.9173 | J22: =J19+J20+J21 -> 6553.7715 | K22: =K19+K20+K21 -> 6551.3403 | ... AF22: =AF19+AF20+AF21 -> 18793.826
B23: 16 | C23: (CAPEX) | D23: ='Fin. Data'!D32 -> -1602.6 | E23: ='Fin. Data'!C32 -> -1915.6 | F23: ='Fin. Data'!B32 -> -2199.3 | G23: =G6*$D$62 -> -2173.8307 | H23: =H6*$D$62 -> -2095.5804 | I23: =I6*$D$62 -> -2068.3101 | J23: =J6*$D$62 -> -2041.5366 | K23: =K6*$E$62 -> -1488.5651 | L23: =L6*$E$62 -> -1518.9939 | M23: =M6*$E$62 -> -1554.8798 | N23: =N6*$E$62 -> -1622.6832 | O23: =O6*$E$62 -> -1694.3705 | P23: =P6*$E$62 -> -1770.7412 | Q23: =Q6*$E$62 -> -1852.1631 | R23: =R6*$E$62 -> -1939.0347 | ... AF23: =AF6*$E$62 -> -3802.7205 | AG23: =SUM(D23:AF23) -> -67523.648
B24: 17 | C24: Adq | D24: =Inputs!D65 -> -1271.426 | E24: ='Fin. Data'!C33 -> -3876.916 | F24: ='Fin. Data'!B33 -> -225.044 | G24: =G6*$D$63 -> -931.64174 | H24: =H6*$D$63 -> -898.10588 | I24: =I6*$D$63 -> -886.4186 | J24: =J6*$D$63 -> -874.94426 | K24: =K6*$E$63 -> -744.28253 | L24: =L6*$E$63 -> -759.49696 | M24: =M6*$E$63 -> -777.43988 | N24: =N6*$E$63 -> -811.34161 | O24: =O6*$E$63 -> -847.18523 | P24: =P6*$E$63 -> -885.37059 | Q24: =Q6*$E$63 -> -926.08154 | R24: =R6*$E$63 -> -969.51737 | ... AF24: =AF6*$E$63 -> -1901.3602 | AH24: =AG9-AG23 -> 31094.828
B25: 18 | C25: (Other investing flows) | D25: =Inputs!D66 -> 0.176 | E25: =Inputs!C66 -> 89.806 | F25: =Inputs!B66 -> -72.086 | G25: =(1+G5)*AVERAGE(D25:F25) -> 5.3365151 | H25: =(1+H5)*AVERAGE(E25:G25) -> 7.4088536 | I25: =(1+I5)*AVERAGE(F25:H25) -> -19.522806 | J25: =(1+J5)*AVERAGE(G25:I25) -> -2.2299019 | K25: =(1+K5)*AVERAGE(H25:J25) -> -4.8807131 | L25: =(1+L5)*AVERAGE(I25:K25) -> -9.0592848 | M25: =(1+M5)*AVERAGE(J25:L25) -> -5.5173032 | N25: =(1+N5)*AVERAGE(K25:M25) -> -6.7685912 | ... AF25: =(1+AF5)*AVERAGE(AC25:AE25) -> -10.341614
B26: 19 | C26: -Total Investing Flows | D26: =D23+D24+D25 -> -2873.85 | E26: =E23+E24+E25 -> -5702.71 | F26: =F23+F24+F25 -> -2496.43 | G26: =G23+G24+G25 -> -3100.136 | H26: =H23+H24+H25 -> -2986.2774 | I26: =I23+I24+I25 -> -2974.2515 | J26: =J23+J24+J25 -> -2918.7108 | K26: =K23+K24+K25 -> -2237.7283 | ... AF26: =AF23+AF24+AF25 -> -5714.4224
B27: 20 | C27: (Flows related to leases) | D27: =Inputs!D69+Inputs!D70 -> 11.425 | E27: =Inputs!C69+Inputs!C70 -> 16.008 | F27: =Inputs!B69+Inputs!B70 -> 16.84 | G27: =G6*$D$66 -> -15.527362 | H27: =H6*$D$66 -> -14.968431 | I27: =I6*$D$66 -> -14.773643 | J27: =J6*$D$66 -> -14.582404 | K27: =$E$66*K6 -> -14.885651 | L27: =$E$66*L6 -> -15.189939 | M27: =$E$66*M6 -> -15.548798 | N27: =$E$66*N6 -> -16.226832 | O27: =$E$66*O6 -> -16.943705 | P27: =$E$66*P6 -> -17.707412 | Q27: =$E$66*Q6 -> -18.521631 | R27: =$E$66*R6 -> -19.390347 | ... AF27: =$E$66*AF6 -> -38.027205
B28: 21 | C28: Flows related to debt | D28: =+SUM(Inputs!D68:D68) -> 246.81 | E28: =+SUM(Inputs!C68:C68) -> 922.29 | F28: =+SUM(Inputs!B68:B68) -> -34.87 | G28: =G44-F44 -> -580.75691 | H28: =H44-G44 -> 417.11212 | I28: 2500 | J28: =J44-I44 -> 577.69532 | K28: =K44-J44 -> -1689.5068 | L28: =L44-K44 -> 196.39437 | M28: =M44-L44 -> -181.52233 | N28: =N44-M44 -> 70.395156 | O28: =O44-N44 -> 419.18965 | P28: =P44-O44 -> 470.80357 | Q28: =Q44-P44 -> 388.97603 | ... AF28: =AF44-AE44 -> 834.63707
B29: 22 | C29: (Repurchases)/Issuance of stock | D29: ='Fin. Data'!D28 -> -3204.09 | E29: ='Fin. Data'!C28 -> -2803.8 | F29: ='Fin. Data'!B28 -> -1591.52 | G29: =G34*$D$65 -> -493.54477 | H29: =H34*$D$65 -> -1208.598 | I29: =I34*$D$65 -> -2383.0045 | J29: =J34*$D$65 -> -1771.1801 | K29: =K34*$E$65 -> -1162.6626 | L29: =L34*$E$65 -> -2154.3873 | M29: =M34*$E$65 -> -1907.235 | N29: =N34*$E$65 -> -2038.9531 | O29: =O34*$E$65 -> -2363.5054 | P29: =P34*$E$65 -> -2566.1572 | Q29: =Q34*$E$65 -> -2667.0758 | R29: =R34*$E$65 -> -2853.2878 | ... AF29: =AF34*$E$65 -> -6712.3366
B30: 23 | C30: (Dividends) | D30: ='Fin. Data'!D27 -> -483.47 | E30: ='Fin. Data'!C27 -> -533.59 | F30: ='Fin. Data'!B27 -> -514.53 | G30: =G34*$D$64 -> -109.67662 | H30: =H34*$D$64 -> -268.57734 | I30: =I34*$D$64 -> -529.55655 | J30: =J34*$D$64 -> -393.59558 | K30: =K34*$E$64 -> -348.79879 | L30: =L34*$E$64 -> -646.31618 | M30: =M34*$E$64 -> -572.17049 | N30: =N34*$E$64 -> -611.68592 | O30: =O34*$E$64 -> -709.05161 | P30: =P34*$E$64 -> -769.84717 | Q30: =Q34*$E$64 -> -800.12275 | R30: =R34*$E$64 -> -855.98634 | ... AF30: =AF34*$E$64 -> -2013.701
B31: 24 | C31: Other financing flows | D31: =Inputs!D73 -> -173.555 | E31: =Inputs!C73 -> -111.768 | F31: =Inputs!B73 -> -468.73 | G31: =(1+G5)*AVERAGE(D31:F31) -> -224.85557 | H31: =(1+H5)*AVERAGE(E31:G31) -> -258.78788 | I31: =(1+I5)*AVERAGE(F31:H31) -> -313.32666 | J31: =(1+J5)*AVERAGE(G31:I31) -> -262.21788 | K31: =(1+K5)*AVERAGE(H31:J31) -> -283.89422 | L31: =(1+L5)*AVERAGE(I31:K31) -> -292.33573 | M31: =(1+M5)*AVERAGE(J31:L31) -> -286.08531 | N31: =(1+N5)*AVERAGE(K31:M31) -> -299.97271 | ... AF31: =(1+AF5)*AVERAGE(AC31:AE31) -> -451.34026
B32: 25 | C32: -Total Financing flows | D32: =D27+D28+D29+D30+D31 -> -3602.88 | E32: =E27+E28+E29+E30+E31 -> -2510.86 | F32: =F27+F28+F29+F30+F31 -> -2592.81 | G32: =G27+G28+G29+G30+G31 -> -1424.3612 | H32: =H27+H28+H29+H30+H31 -> -1333.8196 | I32: =I27+I28+I29+I30+I31 -> -740.66133 | J32: =J27+J28+J29+J30+J31 -> -1863.8806 | K32: =K27+K28+K29+K30+K31 -> -3499.7481 | ... AF32: =AF27+AF28+AF29+AF30+AF31 -> -8380.768
A34: SUMMARY | B34: 26 | C34: Cash before shareholder returns | D34: =D22+D26+D27+D28+D31 -> 3577.405 | E34: =E22+E26+E27+E28+E31 -> 5332.654 | F34: =F22+F26+F27+F28+F31 -> 4258.872 | G34: =G22+G26+G27+G28+G31 -> 1096.7662 | H34: =H22+H26+H27+H28+H31 -> 2685.7734 | I34: =I22+I26+I27+I28+I31 -> 5295.5655 | J34: =J22+J26+J27+J28+J31 -> 3935.9558 | K34: =K22+K26+K27+K28+K31 -> 2325.3253 | ... AF34: =AF22+AF26+AF27+AF28+AF31 -> 13424.673
B35: 27 | C35: Returns to shareholders | D35: =-1*(D29+D30) -> 3687.56 | E35: =-1*(E29+E30) -> 3337.39 | F35: =-1*(F29+F30) -> 2106.05 | G35: =-1*(G29+G30) -> 603.22139 | H35: =-1*(H29+H30) -> 1477.1754 | I35: =-1*(I29+I30) -> 2912.561 | J35: =-1*(J29+J30) -> 2164.7757 | K35: =-1*(K29+K30) -> 1511.4614 | ... AF35: =-1*(AF29+AF30) -> 8726.0376
B36: 28 | C36: Excess cash acumulation | D36: =D34-D35 -> -110.155 | E36: =E34-E35 -> 1995.264 | F36: =F34-F35 -> 2152.822 | G36: =G34-G35 -> 493.54477 | H36: =H34-H35 -> 1208.598 | I36: =I34-I35 -> 2383.0045 | J36: =J34-J35 -> 1771.1801 | K36: =K34-K35 -> 813.86385 | ... AF36: =AF34-AF35 -> 4698.6356
A38: BALANCE SHEET | B38: 29 | C38: Intangible assets | D38: ='Fin. Data'!D49 -> 3931.003 | E38: ='Fin. Data'!C49 -> 7242.325 | F38: ='Fin. Data'!B49 -> 7076.862 | G38: =+F38+(-G10) -> 7430.7051 | H38: =+G38+(-H10) -> 7802.2404 | I38: =+H38+(-I10) -> 8192.3524 | J38: =+I38+(-J10) -> 8601.97 | K38: =+J38+(-K10) -> 8989.0586 | L38: =+K38+(-L10) -> 9393.5663 | M38: =+L38+(-M10) -> 9816.2768 | N38: =+M38+(-N10) -> 10258.009 | ... AF38: =+AE38+(-AF10) -> 22654.596 | AG38: =SUM(G38:AF38) -> 358360.46
B39: 30 | C39: Accumulated amortization | D39: 1091.366 | E39: 1326.311 | F39: 1564.041 | G39: =F39-G10 -> 1917.8841 | H39: =G39-H10 -> 2289.4194 | I39: =H39-I10 -> 2679.5314 | J39: =I39-J10 -> 3089.149 | K39: =J39-K10 -> 3476.2376 | L39: =K39-L10 -> 3880.7453 | M39: =L39-M10 -> 4303.4558 | N39: =M39-N10 -> 4745.1882 | ... AF39: =AE39-AF10 -> 17141.775 | AG39: =SUM(G39:AF39) -> 215027.12
B40: 31 | C40: PPE+Right of use Assets | D40: =Inputs!D33 -> 8114.82 | E40: =Inputs!C33 -> 9616.92 | F40: =Inputs!B33 -> 11049.77 | G40: =F40+(-G23) -> 13223.601 | H40: =G40+(-H23) -> 15319.181 | I40: =H40+(-I23) -> 17387.491 | J40: =I40+(-J23) -> 19429.028 | K40: =J40+(-K23) -> 20917.593 | L40: =K40+(-L23) -> 22436.587 | M40: =L40+(-M23) -> 23991.467 | N40: =M40+(-N23) -> 25614.15 | ... AF40: =AE40+(-AF23) -> 72855.918 | AG40: =SUM(G40:AF40) -> 1006502.8
B41: 32 | C41: Accumulated depreciation | D41: 10389.649 | E41: 11115.127 | F41: 11788.982 | G41: =F41-G9 -> 12244.233 | H41: =G41-H9 -> 12789.045 | I41: =H41-I9 -> 13420.195 | J41: =I41-J9 -> 14136.56 | K41: =J41-K9 -> 14937.036 | L41: =K41-L9 -> 15798.841 | M41: =L41-M9 -> 16723.228 | N41: =M41-N9 -> 17711.676 | ... AF41: =AE41-AF9 -> 50710.485 | AG41: =SUM(G41:AF41) -> 699665.53
A43: CASH & DEBT & DISCOUNTING | B43: 33 | C43: Ending cash balance | D43: ='Fin. Data'!D41 -> 2364.9 | E43: =E36+D43 -> 4360.164 | F43: =F36+E43 -> 6512.986 | G43: =G36+F43 -> 7006.5308 | H43: =H36+G43 -> 8215.1288 | I43: =I36+H43 -> 10598.133 | J43: =J36+I43 -> 12369.313 | K43: =K36+J43 -> 13183.177 | L43: =L36+K43 -> 14691.248 | ... AF43: =AF36+AE43 -> 69813.362
B44: 34 | C44: Total Debt | D44: ='Fin. Data'!D63 -> 5720.84 | E44: ='Fin. Data'!C63 -> 6691.367 | F44: ='Fin. Data'!B63 -> 6842.183 | G44: =G12*$D$67 -> 6261.4261 | H44: =H12*$D$67 -> 6678.5382 | I44: =I12*$D$67 -> 7551.0864 | J44: =J12*$D$67 -> 8128.7817 | K44: =K12*$E$67 -> 6439.2749 | L44: =L12*$E$67 -> 6635.6693 | M44: =M12*$E$67 -> 6454.1469 | N44: =N12*$E$67 -> 6524.5421 | O44: =O12*$E$67 -> 6943.7318 | P44: =P12*$E$67 -> 7414.5353 | Q44: =Q12*$E$67 -> 7803.5113 | R44: =R12*$E$67 -> 8243.957 | ... AF44: =AF12*$E$67 -> 18142.67
B45: 35 | C45: Discount factor | F45: =1/((1+$F$50)^G50) -> 1 | G45: =1/((1+$F$50)^G49) -> 0.90909091 | H45: =1/((1+$F$50)^H49) -> 0.82644628 | I45: =1/((1+$F$50)^I49) -> 0.7513148 | J45: =1/((1+$F$50)^J49) -> 0.68301346 | K45: =1/((1+$F$50)^K49) -> 0.62092132 | L45: =1/((1+$F$50)^L49) -> 0.56447393 | M45: =1/((1+$F$50)^M49) -> 0.51315812 | N45: =1/((1+$F$50)^N49) -> 0.46650738 | ... AF45: =1/((1+$F$50)^AF49) -> 0.083905453
B46: 36 | C46: DF + 0.1% | E46: +0.1% | F46: =1/((1+$F$50+0.001)^G50) -> 1 | G46: =1/((1+$F$50+0.001)^G49) -> 0.90826521 | H46: =1/((1+$F$50+0.001)^H49) -> 0.8249457 | I46: =1/((1+$F$50+0.001)^I49) -> 0.74926948 | J46: =1/((1+$F$50+0.001)^J49) -> 0.6805354 | K46: =1/((1+$F$50+0.001)^K49) -> 0.61810663 | L46: =1/((1+$F$50+0.001)^L49) -> 0.56140475 | M46: =1/((1+$F$50+0.001)^M49) -> 0.50990441 | N46: =1/((1+$F$50+0.001)^N49) -> 0.46312844 | ... AF46: =1/((1+$F$50+0.001)^AF49) -> 0.081946367
B47: 37 | C47: DF+0.5% | E47: +0.5% | F47: =1/((1+$F$50+0.005)^G50) -> 1 | G47: =1/((1+$F$50+0.005)^H50) -> 1 | H47: =1/((1+$F$50+0.005)^H49) -> 0.81898405 | I47: =1/((1+$F$50+0.005)^I49) -> 0.74116204 | J47: =1/((1+$F$50+0.005)^J49) -> 0.67073487 | K47: =1/((1+$F$50+0.005)^K49) -> 0.60699989 | L47: =1/((1+$F$50+0.005)^L49) -> 0.54932116 | M47: =1/((1+$F$50+0.005)^M49) -> 0.49712323 | N47: =1/((1+$F$50+0.005)^N49) -> 0.44988527 | O47: =1/((1+$F$50+0.005)^O49) -> 0.40713599 | ... AF47: =1/((1+$F$50+0.005)^AF49) -> 0.074572855
A49: Discount Rate | C49: Risk free rate | D49: Equity premium | E49: Firm premium | F49: Total | G49: 1 | H49: 2 | I49: 3 | J49: 4 | K49: 5 | L49: 6 | M49: 7 | N49: 8 | O49: 9 | P49: 10 | Q49: 11 | R49: 12 | S49: 13 | T49: 14 | U49: 15 | V49: 16 | W49: 17 | X49: 18 | Y49: 19 | Z49: 20 | AA49: 21 | AB49: 22 | AC49: 23 | AD49: 24 | AE49: 25 | AF49: 26
C50: 0.04 | D50: 0.04 | E50: 0.02 | F50: =E50+D50+C50 -> 0.1 | G50: 0
H51: Implied DEBT/EBITDA | I51: =I44/I12 -> 1.3 | J51: =J44/J12 -> 1.3 | K51: =K44/K12 -> 1 | L51: =L44/L12 -> 1 | M51: =M44/M12 -> 1 | N51: =N44/N12 -> 1 | O51: =O44/O12 -> 1 | P51: =P44/P12 -> 1 | ... AF51: =AF44/AF12 -> 1
A52: Modelling factors | D52: Short Term | E52: Long Term | F52: Reference (line)
C53: Depreciation factor | D53: =Assumptions!L17 -> -0.0412 | E53: =Assumptions!M17 -> -0.0412 | F53: =Assumptions!O17 -> % PPE | H53: Cash/Operational Costs | I53: =I43/(I6-I8) -> 0.4280341 | J53: =J43/(J6-J8) -> 0.51457584 | K53: =K43/(K6-K8) -> 0.53765894 | L53: =L43/(L6-L8) -> 0.58740271 | M53: =M43/(M6-M8) -> 0.61662086 | N53: =N43/(N6-N8) -> 0.63793949 | O53: =O43/(O6-O8) -> 0.6713857 | P53: =P43/(P6-P8) -> 0.7060422 | ... AF53: =AF43/(AF6-AF8) -> 1.1309051
C54: Amortization factor | D54: =Assumptions!L18 -> -0.05 | E54: =Assumptions!M18 -> -0.045 | F54: =Assumptions!O18 -> % IA
C55: Stock-based comp | D55: =Assumptions!L19 -> -0.0037 | E55: =Assumptions!M19 -> -0.0037 | F55: =Assumptions!O19 -> % Revenue | H55: Cash/Sales | I55: =I43/I6 -> 0.35868381 | J55: =J43/J6 -> 0.42411776 | K55: =K43/K6 -> 0.44281495 | L55: =L43/L6 -> 0.48358483 | M55: =M43/M6 -> 0.51535538 | N55: =N43/N6 -> 0.53779997 | O55: =O43/O6 -> 0.56386824 | P55: =P43/P6 -> 0.59027101 | ... AF55: =AF43/AF6 -> 0.9179397
C56: Tax Rate | D56: =Assumptions!L20 -> 0.21 | E56: =Assumptions!M20 -> 0.21 | F56: =Assumptions!O20 -> % EBT
C57: Interest Rate on debt | D57: =Assumptions!L21 -> -0.033 | E57: =Assumptions!M21 -> -0.033 | F57: =Assumptions!O21 -> % Debt | H57: Long-term CAGR | I57: =(AF6/G6)^(1/26)-1 -> 0.035050197
C58: Interest Rate on cash | D58: =Assumptions!L22 -> 0.035 | E58: =Assumptions!M22 -> 0.025 | F58: =Assumptions!O22 -> % Cash
C59: PPE+ROA | D59: =Assumptions!L23 -> - - | E59: =Assumptions!M23 -> - - | F59: =Assumptions!O23 -> Growing with CAPEX | H59: return to shareholders | I59: =I35/I17 -> 0.69508275 | J59: =J35/J17 -> 0.47547757 | K59: =K35/K17 -> 0.32719205 | L59: =L35/L17 -> 0.59823043 | M59: =M35/M17 -> 0.54964451 | N59: =N35/N17 -> 0.58603799 | O59: =O35/O17 -> 0.63807096 | P59: =P35/P17 -> 0.64651299 | ... AF59: =AF35/AF17 -> 0.66754076
C60: Working capital flows | D60: =Assumptions!O266 -> 0.03 | E60: =Assumptions!P266 -> 0.025 | F60: % Revenue
C61: Intangible Assets | D61: =Assumptions!L25 -> - - | E61: =Assumptions!M25 -> - - | F61: =Assumptions!O25 -> Growing with Amortization
C62: Capex | D62: =Assumptions!L26 -> -0.07 | E62: =Assumptions!M26 -> -0.05 | F62: =Assumptions!O26 -> % Revenue
C63: Acquisition factor | D63: =Assumptions!N302 -> -0.03 | E63: =Assumptions!O302 -> -0.025 | F63: =Assumptions!O27 -> % Revenue
C64: Dividends | D64: =Assumptions!L28 -> -0.1 | E64: =Assumptions!M28 -> -0.15 | F64: =Assumptions!O28 -> % Cash before shareholder returns
C65: Repurchases | D65: =Assumptions!L29 -> -0.45 | E65: =Assumptions!M29 -> -0.5 | F65: =Assumptions!O29 -> % Cash before shareholder returns
C66: Leases | D66: =Assumptions!L30 -> -0.0005 | E66: =Assumptions!M30 -> -0.0005 | F66: =Assumptions!O30 -> % Revenue
C67: Total Debt | D67: =Assumptions!L31 -> 1.3 | E67: =Assumptions!M31 -> 1 | F67: Debt Schedule
A69: Valuation | D69: $ millions
C70: Value of flows | D70: =SUMPRODUCT(G35:AF35,G45:AF45)+((AF43-AF44)*AF45) -> 32540.309 | E70: =D70/D72 -> 0.69798509
C71: Value of perpetuity | D71: =(AF34/(F50-AF5))*AF45 -> 14080.041 | E71: =D71/D72 -> 0.30201491
C72: Total Value | D72: =D70+D71 -> 46620.35
C73: Actual share price | D73: =OP!C20 -> 137.63
C74: Total value vs Mkt Cap | D74: =D75/D73-1 -> 0.47574985
C75: Estimated NPV per share | D75: =D72*1000000/OP!C21 -> 203.10745
A77: Sensibility | C77: Sensitivity +0.1% | D77: =(SUMPRODUCT(G35:AF35,G45:AF45)+((AF43-AF44)*AF45)+(AF34/(F50+0.001-AF5))*AF45)*1000000/OP!C21 -> 202.35015 | E77: =D77/D75-1 -> -0.0037285792
C78: Sensitivity +0.5% | D78: =(SUMPRODUCT(G35:AF35,G45:AF45)+((AF43-AF44)*AF45)+(AF34/(F50+0.005-AF5))*AF45)*1000000/OP!C21 -> 199.49913 | E78: =D78/D75-1 -> -0.017765583
A80: Notes | C80: Price where it'd be a "BUY" | D80: =D75/1.15 -> 176.61518

Sheet Assumptions
B2: Assumptions
B4: Prospects:
B6: Links:
C8: 2023 | D8: =C8-1 -> 2022 | E8: =D8-1 -> 2021 | F8: =E8-1 -> 2020 | G8: =F8-1 -> 2019 | H8: =G8-1 -> 2018 | I8: =H8-1 -> 2017 | J8: =I8-1 -> 2016 | K8: =J8-1 -> 2015 | ... M8: =L8-1 -> 2013 | O8: 10Y Average | P8: 5Y Average | Q8: 3Y Average | S8: Short Term Forecast | T8: Long Term Forecast | V8: 0.025
B9: Revenue growth | C9: =(Inputs!B6-Inputs!C6)/Inputs!C6 -> -0.16375988 | D9: =(Inputs!C6-Inputs!D6)/Inputs!D6 -> 0.13781384 | E9: =(Inputs!D6-Inputs!E6)/Inputs!E6 -> 0.81151936 | F9: =(Inputs!E6-Inputs!F6)/Inputs!F6 -> -0.10841 | G9: =(Inputs!F6-Inputs!G6)/Inputs!G6 -> -0.098870763 | H9: =(Inputs!G6-Inputs!H6)/Inputs!H6 -> 0.23774405 | I9: =(Inputs!H6-Inputs!I6)/Inputs!I6 -> 0.24952126 | J9: =(Inputs!I6-Inputs!J6)/Inputs!J6 -> -0.014061082 | ... M9: =(Inputs!L6-Inputs!M6)/Inputs!M6 -> -0.019401616 | O9: =AVERAGE(C9:M9) -> 0.083525495 | P9: =AVERAGE(C9:G9) -> 0.11565851 | Q9: =AVERAGE(C9:E9) -> 0.26185777 | V9: 0.07
B10: Operating Margin | C10: =Inputs!B8/Inputs!B6 -> 0.17947802 | D10: =Inputs!C8/Inputs!C6 -> 0.25309019 | E10: =Inputs!D8/Inputs!D6 -> 0.25541087 | F10: =Inputs!E8/Inputs!E6 -> 0.080086892 | G10: =Inputs!F8/Inputs!F6 -> 0.087126582 | H10: =Inputs!G8/Inputs!G6 -> 0.13699133 | I10: =Inputs!H8/Inputs!H6 -> 0.09292729 | J10: =Inputs!I8/Inputs!I6 -> 0.088165674 | ... M10: =Inputs!L8/Inputs!L6 -> 0.049495996 | O10: =AVERAGE(C10:M10) -> 0.12050359 | P10: =AVERAGE(C10:G10) -> 0.17103851 | Q10: =AVERAGE(C10:E10) -> 0.22932636
B13: Modelling Factors
C15: Last 6 Years
C16: =C8 -> 2023 | D16: =D8 -> 2022 | E16: =E8 -> 2021 | F16: =F8 -> 2020 | G16: =G8 -> 2019 | H16: =H8 -> 2018 | J16: Average | L16: Short Term Forecast | M16: Long Term Forecast | O16: Reference
B17: Depreciation factor | C17: =B85 -> 0.040745883 | D17: =C85 -> 0.039875078 | E17: =D85 -> 0.03974208 | F17: =E85 -> 0.041905499 | G17: =F85 -> 0.041610777 | H17: =G85 -> 0.043433786 | J17: =AVERAGE(C17:H17) -> 0.041218851 | L17: -0.0412 | M17: -0.0412 | O17: % PPE
B18: Amortization factor | C18: =B79 -> 0.05088445 | D18: =C79 -> 0.050539778 | E18: =D79 -> 0.058836741 | F18: =E79 -> 0.050577951 | G18: =F79 -> 0.052313563 | H18: =G79 -> 0.05340241 | J18: =AVERAGE(C18:H18) -> 0.052759149 | L18: -0.05 | M18: -0.045 | O18: % IA
B19: Stock-based comp | C19: =B72 -> -0.0037495535 | D19: =C72 -> -0.0032962517 | E19: =D72 -> -0.0037214944 | F19: =E72 -> -0.0036669811 | G19: =F72 -> -0.004000158 | H19: =G72 -> -0.0029289976 | J19: =AVERAGE(C19:H19) -> -0.0035605727 | L19: -0.0037 | M19: -0.0037 | O19: % Revenue
B20: Tax Rate | C20: ='Fin. Data'!B21/('Fin. Data'!B21-'Fin. Data'!B23) -> 0.23109749 | D20: ='Fin. Data'!C21/('Fin. Data'!C21-'Fin. Data'!C23) -> 0.22154908 | E20: ='Fin. Data'!D21/('Fin. Data'!D21-'Fin. Data'!D23) -> 0.23339472 | F20: ='Fin. Data'!E21/('Fin. Data'!E21-'Fin. Data'!E23) -> -0.00068000872 | G20: ='Fin. Data'!F21/('Fin. Data'!F21-'Fin. Data'!F23) -> 0.24473103 | H20: ='Fin. Data'!G21/('Fin. Data'!G21-'Fin. Data'!G23) -> 0.24071342 | J20: =AVERAGE(C20:H20) -> 0.19513429 | L20: 0.21 | M20: 0.21 | O20: % EBT
B21: Interest Rate on debt | C21: =B90 -> 0.035946715 | D21: =C90 -> 0.032715438 | E21: =D90 -> 0.02851347 | F21: =E90 -> 0.031197437 | G21: =F90 -> 0.035901558 | H21: =G90 -> 0.037578773 | J21: =AVERAGE(C21:H21) -> 0.033642232 | L21: -0.033 | M21: -0.033 | O21: % Debt
B22: Interest Rate on cash | C22: =B95 -> 0.043172967 | D22: =C95 -> 0.011374945 | E22: =D95 -> 0.0018043046 | F22: =E95 -> 0.0050820169 | G22: =F95 -> 0.023415222 | H22: =G95 -> 0.018386589 | J22: =AVERAGE(C22:H22) -> 0.017206007 | L22: 0.035 | M22: 0.025 | O22: % Cash
B23: PPE+ROA | C23: =Inputs!B33/Inputs!C33-1 -> 0.14899261 | D23: =Inputs!C33/Inputs!D33-1 -> 0.18510577 | E23: =Inputs!D33/Inputs!E33-1 -> 0.17621258 | F23: =Inputs!E33/Inputs!F33-1 -> 0.11662102 | G23: =Inputs!F33/Inputs!G33-1 -> 0.15817236 | H23: =Inputs!G33/Inputs!H33-1 -> 0.047436262 | J23: =AVERAGE(C23:H23) -> 0.13875677 | L23: - - | M23: - - | O23: Growing with CAPEX
B24: Working capital flows | C24: =D108 -> 0 | D24: =E108 -> 0 | E24: =F108 -> 0 | F24: =G108 -> 0 | G24: =H108 -> 0 | H24: =I108 -> 0 | J24: =AVERAGE(C24:H24) -> 0 | O24: % Change in Revenues
B25: Intangible Assets | C25: =B77/C77-1 -> 0.0050510092 | D25: =C77/D77-1 -> 1.1176817 | E25: =D77/E77-1 -> 0.33187291 | F25: =E77/F77-1 -> 0.0056164213 | G25: =F77/G77-1 -> -0.013941265 | J25: =AVERAGE(C25:H25) -> 0.28925615 | L25: - - | M25: - - | O25: Growing with Amortization
B26: CAPEX | C26: =Inputs!B64/Inputs!B6 -> -0.063354842 | D26: =Inputs!C64/Inputs!C6 -> -0.046145693 | E26: =Inputs!D64/Inputs!D6 -> -0.043926105 | F26: =Inputs!E64/Inputs!E6 -> -0.07459285 | G26: =Inputs!F64/Inputs!F6 -> -0.063557883 | H26: =Inputs!G64/Inputs!G6 -> -0.037933914 | J26: =AVERAGE(C26:H26) -> -0.054918548 | L26: -0.07 | M26: -0.05 | O26: % Revenue
B27: Acquisition factor | C27: =Inputs!B65/Inputs!B6 -> -0.0064828023 | D27: =Inputs!C65/Inputs!C6 -> -0.093392658 | E27: =Inputs!D65/Inputs!D6 -> -0.034848865 | F27: =Inputs!E65/Inputs!E6 -> -0.0091564052 | G27: =Inputs!F65/Inputs!F6 -> -0.016961725 | H27: =Inputs!G65/Inputs!G6 -> 0.00067566169 | J27: =AVERAGE(C27:H27) -> -0.026694466 | O27: % Revenue
B28: Dividends | C28: =B257 -> -0.14382772 | D28: =C257 -> -0.10006087 | E28: =D257 -> -0.11352067 | J28: =AVERAGE(C28:H28) -> -0.11913642 | L28: -0.1 | M28: -0.15 | O28: % Cash before shareholder returns
B29: Repurchases | C29: =B248 -> -0.44488114 | D29: =C248 -> -0.52577947 | E29: =D248 -> -0.75233301 | L29: -0.45 | M29: -0.5 | O29: % Cash before shareholder returns
B30: Leases | C30: =Inputs!B70/Inputs!B6 -> 0.00048510687 | D30: =Inputs!C70/Inputs!C6 -> 0.00038562343 | E30: =Inputs!D70/Inputs!D6 -> 0.00031315097 | F30: =Inputs!E70/Inputs!E6 -> 0.00047373386 | G30: =Inputs!F70/Inputs!F6 -> 0.00040435864 | H30: =Inputs!G70/Inputs!G6 -> 0 | J30: =AVERAGE(C30:H30) -> 0.0003436623 | L30: -0.0005 | M30: -0.0005 | O30: % Revenue
B31: Total Debt | C31: ='Fin. Data'!B63/'Fin. Data'!B19 -> 0.92318427 | D31: ='Fin. Data'!C63/'Fin. Data'!C19 -> 0.58303075 | E31: ='Fin. Data'!D63/'Fin. Data'!D19 -> 0.55955681 | F31: ='Fin. Data'!E63/'Fin. Data'!E19 -> 3.0100651 | G31: ='Fin. Data'!F63/'Fin. Data'!F19 -> 1.660787 | H31: ='Fin. Data'!G63/'Fin. Data'!G19 -> 1.0507522 | J31: =AVERAGE(C31:H31) -> 1.297896 | L31: 1.3 | M31: 1 | O31: % EBITDA
B34: Forecasts
B37: 2023 | C37: 2022 | D37: 2021 | E37: 2020 | F37: 2019 | G37: 2018 | H37: 2017 | I37: 2016 | J37: 2015 | K37: 2014 | L37: 2013 | M37: 2012
A38: Net Sales | B38: 34714 | C38: 41512 | D38: 36484 | E38: 20140 | F38: 22588.858 | G38: 25067.279 | H38: 20252.393 | I38: 16208.122 | J38: 16439.276 | K38: 21105.141 | L38: 19052.046 | M38: 19429
A39: COGS | B39: =B38-B40 -> 26899.6 | C39: =C38-C40 -> 29008.72 | D39: =D38-D40 -> 25458.59 | E39: =E38-E40 -> 17912.05 | F39: =F38-F40 -> 19909.768 | G39: =G38-G40 -> 20772.279 | H39: =H38-H40 -> 17682.393 | I39: =I38-I40 -> 14182.122 | ... M39: =M38-M40 -> 17915.46
A40: Gross Profit | B40: 7814.4 | C40: 12503.28 | D40: 11025.41 | E40: 2227.95 | F40: 2679.09 | G40: 4295 | H40: 2570 | I40: 2026 | J40: 1114 | K40: 1849 | L40: 1411 | M40: 1513.54
B43: Crude oil prices | C43: 2024 | D43: 2023 | E43: 2022 | F43: 2021 | G43: 2020 | H43: 2019 | I43: 2018
C44: 70.49 | D44: 71.33 | E44: 80.51 | F44: 75.21 | G44: 48.52 | H44: 61.14 | I44: 45.15
C45: =C44/D44-1 -> -0.011776251 | D45: =D44/E44-1 -> -0.1140231 | E45: =E44/F44-1 -> 0.070469352 | F45: =F44/G44-1 -> 0.55008244 | G45: =G44/H44-1 -> -0.20641151 | H45: =H44/I44-1 -> 0.35415282
B46: COGS | D46: =B39 -> 26899.6 | E46: =C39 -> 29008.72 | F46: =D39 -> 25458.59 | G46: =E39 -> 17912.05 | H46: =F39 -> 19909.768 | I46: =G39 -> 20772.279
D47: =D46/E46-1 -> -0.072706414 | E47: =E46/F46-1 -> 0.13944724 | F47: =F46/G46-1 -> 0.42131079 | G47: =G46/H46-1 -> -0.10033859 | H47: =H46/I46-1 -> -0.041522213
B48: Correl | C48: =CORREL(D46:I46,D44:I44) -> 0.89265961
B50: NYSE Amercian Steel Index
C51: 1Q | D51: 2Q | E51: 3Q | F51: 4Q | G51: average
B52: 2024 | C52: 2168 | D52: 1979 | E52: 2087 | G52: =AVERAGE(C52:F52) -> 2078 | H52: =G52/G54-1 -> 0.046719557 | O52: US motor vehicle production (million units)
C53: =C52/F54-1 -> -0.025179856 | D53: =D52/C52-1 -> -0.087177122 | E53: =E52/D52-1 -> 0.054573017 | O53: Year | P53: 2023 | Q53: 2022 | R53: 2021 | S53: 2020 | T53: 2019 | U53: 2018 | V53: 2017 | W53: 2016
B54: 2023 | C54: 1900 | D54: 1891 | E54: 1926 | F54: 2224 | G54: =AVERAGE(C54:F54) -> 1985.25 | H54: =G54/G56-1 -> 0.21607963 | P54: 10.61 | Q54: 10.06 | R54: 9.16 | S54: 8.82 | T54: 10.89 | U54: 11.3 | V54: 11.19 | W54: 12.18
C55: =C54/F56-1 -> 0.097631427 | D55: =D54/C54-1 -> -0.0047368421 | E55: =E54/D54-1 -> 0.018508726 | F55: =F54/E54-1 -> 0.15472482 | P55: =P54/Q54-1 -> 0.054671968 | Q55: =Q54/R54-1 -> 0.098253275 | R55: =R54/S54-1 -> 0.038548753 | S55: =S54/T54-1 -> -0.19008264 | T55: =T54/U54-1 -> -0.036283186 | U55: =U54/V54-1 -> 0.0098302055 | V55: =V54/W54-1 -> -0.081280788
B56: 2022 | C56: 1986 | D56: 1441 | E56: 1372 | F56: 1731 | G56: =AVERAGE(C56:F56) -> 1632.5 | H56: =G56/G58-1 -> 0.0075605616
C57: =C56/F58-1 -> 0.25696203 | D57: =D56/C56-1 -> -0.27442095 | E57: =E56/D56-1 -> -0.047883414 | F57: =F56/E56-1 -> 0.26166181 | O57: Non residential construction spending in the U.S. (millions $)
B58: 2021 | C58: 1600 | D58: 1766 | E58: 1535 | F58: 1580 | G58: =AVERAGE(C58:F58) -> 1620.25 | H58: =G58/G60-1 -> 0.80278164 | O58: Year | P58: Q1 | Q58: Q2 | R58: Q3 | S58: Q4 | T58: Total
C59: =C58/F60-1 -> 0.23839009 | D59: =D58/C58-1 -> 0.10375 | E59: =E58/D58-1 -> -0.13080408 | F59: =F58/E58-1 -> 0.029315961 | O59: 2024 | P59: 3626929 | Q59: 3649221 | T59: =SUM(P59:S59) -> 7276150
B60: 2020 | C60: 630 | D60: 791 | E60: 882 | F60: 1292 | G60: =AVERAGE(C60:F60) -> 898.75 | H60: =G60/G62-1 -> -0.17146808 | O60: 2023 | P60: 3261219 | Q60: 3421672 | R60: 3468928 | S60: 3587545 | T60: =SUM(P60:S60) -> 13739364 | U60: =T60/T61-1 -> 0.18243705
C61: =C60/F62-1 -> -0.42675159 | D61: =D60/C60-1 -> 0.25555556 | E61: =E60/D60-1 -> 0.11504425 | F61: =F60/E60-1 -> 0.46485261 | O61: 2022 | P61: 2706090 | Q61: 2830594 | R61: 2983330 | S61: 3099517 | T61: =SUM(P61:S61) -> 11619531 | U61: =T61/T62-1 -> 0.14587397
B62: 2019 | C62: 1154 | D62: 1121 | E62: 965 | F62: 1099 | G62: =AVERAGE(C62:F62) -> 1084.75 | H62: =G62/G64-1 -> -0.096606288 | O62: 2021 | P62: 2524841 | Q62: 2515566 | R62: 2528858 | S62: 2571057 | T62: =SUM(P62:S62) -> 10140322 | U62: =T62/T63-1 -> -0.012619375
C63: =C62/F64-1 -> 0.13919052 | D63: =D62/C62-1 -> -0.028596187 | E63: =E62/D62-1 -> -0.13916146 | F63: =F62/E62-1 -> 0.1388601 | O63: 2020 | P63: 2648350 | Q63: 2574115 | R63: 2530360 | S63: 2517097 | T63: =SUM(P63:S63) -> 10269922 | U63: =T63/#REF!-1 -> #REF!
B64: 2018 | C64: 1272 | D64: 1254 | E64: 1264 | F64: 1013 | G64: =AVERAGE(C64:F64) -> 1200.75
A67: MF
A69: Stock-based compensation
B70: 2023 | C70: 2022 | D70: 2021 | E70: 2020 | F70: 2019 | G70: 2018 | H70: 2017
A71: SBC | B71: -130.162 | C71: -136.834 | D71: -135.775 | E71: -73.853 | F71: -90.359 | G71: -73.422 | H71: -64.176
A72: %revenues | B72: =B71/'Fin. Data'!B5 -> -0.0037495535 | C72: =C71/'Fin. Data'!C5 -> -0.0032962517 | D72: =D71/'Fin. Data'!D5 -> -0.0037214944 | E72: =E71/'Fin. Data'!E5 -> -0.0036669811 | F72: =F71/'Fin. Data'!F5 -> -0.004000158 | G72: =G71/'Fin. Data'!G5 -> -0.0029289976 | H72: =H71/'Fin. Data'!H5 -> -0.0031688107
A74: Amortization factor
B75: 2023 | C75: 2022 | D75: 2021 | E75: 2020 | F75: 2019 | G75: 2018 | I75: Goodwill is not amortized
A76: Amortization | B76: 237.735 | C76: 234.938 | D76: 129.154 | E76: 83.36 | F76: 85.739 | G76: 88.761 | I76: Estimated amortization
A77: Gross IA | B77: 4672.056 | C77: 4648.576 | D77: 2195.125 | E77: 1648.149 | F77: 1638.944 | G77: 1662.116 | I77: 2024 | J77: 2025 | K77: 2026 | L77: 2027 | M77: 2028
B78: =B77/C77-1 -> 0.0050510092 | C78: =C77/D77-1 -> 1.1176817 | D78: =D77/E77-1 -> 0.33187291 | E78: =E77/F77-1 -> 0.0056164213 | F78: =F77/G77-1 -> -0.013941265 | I78: 235.1 | J78: 234.1 | K78: 231.1 | L78: 227.9 | M78: 204.6
A79: Am factor | B79: =B76/B77 -> 0.05088445 | C79: =C76/C77 -> 0.050539778 | D79: =D76/D77 -> 0.058836741 | E79: =E76/E77 -> 0.050577951 | F79: =F76/F77 -> 0.052313563 | G79: =G76/G77 -> 0.05340241 | I79: =B77*1.005 -> 4695.4163 | J79: =I79*1.005 -> 4718.8934 | K79: =J79*1.005 -> 4742.4878 | L79: =K79*1.005 -> 4766.2003 | M79: =L79*1.005 -> 4790.0313 | N79: IA growing 0,5% a year
I80: =I78/I79 -> 0.050070108 | J80: =J78/J79 -> 0.049609089 | K80: =K78/K79 -> 0.048729698 | L80: =L78/L79 -> 0.047815867 | M80: =M78/M79 -> 0.042713709
A81: Depreciation factor
B82: 2023 | C82: 2022 | D82: 2021 | E82: 2020 | F82: 2019 | G82: 2018
A83: Depreciation | B83: 930.585 | C83: 826.692 | D83: 735.406 | E83: 702.11 | F83: 648.911 | G83: 630.879
A84: Gross PPE | B84: 22838.749 | C84: 20732.047 | D84: 18504.467 | E84: 16754.603 | F84: 15594.782 | G84: 14525.075
A85: %PPE | B85: =B83/B84 -> 0.040745883 | C85: =C83/C84 -> 0.039875078 | D85: =D83/D84 -> 0.03974208 | E85: =E83/E84 -> 0.041905499 | F85: =F83/F84 -> 0.041610777 | G85: =G83/G84 -> 0.043433786
B87: 2023 | C87: 2022 | D87: 2021 | E87: 2020 | F87: 2019 | G87: 2018
A88: Interest | B88: 245.954 | C88: 218.911 | D88: 163.121 | E88: 166.613 | F88: 157.358 | G88: 161.256
A89: debt | B89: ='Fin. Data'!B63 -> 6842.183 | C89: ='Fin. Data'!C63 -> 6691.367 | D89: ='Fin. Data'!D63 -> 5720.84 | E89: ='Fin. Data'!E63 -> 5340.599 | F89: ='Fin. Data'!F63 -> 4383.041 | G89: ='Fin. Data'!G63 -> 4291.146
A90: Interest Rate on debt | B90: =B88/B89 -> 0.035946715 | C90: =C88/C89 -> 0.032715438 | D90: =D88/D89 -> 0.02851347 | E90: =E88/E89 -> 0.031197437 | F90: =F88/F89 -> 0.035901558 | G90: =G88/G89 -> 0.037578773
B92: 2023 | C92: 2022 | D92: 2021 | E92: 2020 | F92: 2019 | G92: 2018
A93: Interest income | B93: 275.586 | C93: 48.695 | D93: 4.267 | E93: 13.415 | F93: 35.933 | G93: 25.721
A94: Cash | B94: ='Fin. Data'!B41 -> 6383.3 | C94: ='Fin. Data'!C41 -> 4280.9 | D94: ='Fin. Data'!D41 -> 2364.9 | E94: ='Fin. Data'!E41 -> 2639.7 | F94: ='Fin. Data'!F41 -> 1534.6 | G94: ='Fin. Data'!G41 -> 1398.9
A95: Interest Rate on cash | B95: =B93/B94 -> 0.043172967 | C95: =C93/C94 -> 0.011374945 | D95: =D93/D94 -> 0.0018043046 | E95: =E93/E94 -> 0.0050820169 | F95: =F93/F94 -> 0.023415222 | G95: =G93/G94 -> 0.018386589
B98: 2023 | C98: 2022 | D98: 2021 | E98: 2020 | F98: 2019
A99: (Increase) decrease in accounts receivable | B99: ='Fin. Data'!B42-'Fin. Data'!C42 -> -637.72 | C99: ='Fin. Data'!C42-'Fin. Data'!D42 -> -262.94 | D99: ='Fin. Data'!D42-'Fin. Data'!E42 -> 1555.12 | E99: ='Fin. Data'!E42-'Fin. Data'!F42 -> 138.75 | F99: ='Fin. Data'!F42-'Fin. Data'!G42 -> -345.47
A100: (Increase) decrease in inventories | B100: ='Fin. Data'!B43-'Fin. Data'!C43 -> 124.23 | C100: ='Fin. Data'!C43-'Fin. Data'!D43 -> -557.65 | D100: ='Fin. Data'!D43-'Fin. Data'!E43 -> 2442.09 | E100: ='Fin. Data'!E43-'Fin. Data'!F43 -> -273.01 | F100: ='Fin. Data'!F43-'Fin. Data'!G43 -> -711.4
A101: Decrease (increase) in other current assets | B101: =Inputs!B31-Inputs!C31 -> 105.27 | C101: =Inputs!C31-Inputs!D31 -> 796.71 | D101: =Inputs!D31-Inputs!E31 -> -411.51 | E101: =Inputs!E31-Inputs!F31 -> 291.45 | F101: =Inputs!F31-Inputs!G31 -> 511.27
A102: Increase (decrease) in accounts payable | B102: =Inputs!B43-Inputs!C43 -> 370.77 | C102: =Inputs!C43-Inputs!D43 -> -324.52 | D102: =Inputs!D43-Inputs!E43 -> 541.88 | E102: =Inputs!E43-Inputs!F43 -> 230.46 | F102: =Inputs!F43-Inputs!G43 -> -226.49
A103: Increase (decrease) in accrued expenses | B103: ='Fin. Data'!B56-'Fin. Data'!C56 -> 106.169 | C103: ='Fin. Data'!C56-'Fin. Data'!D56 -> -16.457 | D103: ='Fin. Data'!D56-'Fin. Data'!E56 -> 300.622 | E103: ='Fin. Data'!E56-'Fin. Data'!F56 -> 4.659 | F103: ='Fin. Data'!F56-'Fin. Data'!G56 -> -49.873
A127: SALES FORECAST
C129: 2018 | D129: 2019 | E129: 2020 | F129: 2021 | G129: 2022 | H129: 2023 | I129: average
B130: Sales | C130: 25067.279 | D130: 22588.858 | E130: 20140 | F130: 36484 | G130: 41512 | H130: 34714
B131: YoY | D131: =D130/C130 -> 0.90112924 | E131: =E130/D130 -> 0.89159 | F131: =F130/E130 -> 1.8115194 | G131: =G130/F130 -> 1.1378138 | H131: =H130/G130 -> 0.83624012 | I131: =AVERAGE(D131:H131) -> 1.1156585
B132: Sales volume | C132: 4.846 | D132: =4.814 -> 4.814 | E132: =4.794 -> 4.794 | F132: =4.979 -> 4.979 | G132: =5.015 -> 5.015 | H132: =4.486 -> 4.486
B133: YoY | D133: =D132/C132-1 -> -0.0066033842 | E133: =E132/D132-1 -> -0.0041545492 | F133: =F132/E132-1 -> 0.038589904 | G133: =G132/F132-1 -> 0.0072303675 | H133: =H132/G132-1 -> -0.10548355 | I133: =AVERAGE(D133:H133) -> -0.014084242
B134: Sales per volume | C134: =C130/C132 -> 5172.7773 | D134: =D130/D132 -> 4692.3261 | E134: =E130/E132 -> 4201.0847 | F134: =F130/F132 -> 7327.5758 | G134: =G130/G132 -> 8277.5673 | H134: =H130/H132 -> 7738.2969
D135: =D134/C134-1 -> -0.092880706 | E135: =E134/D134-1 -> -0.10469039 | F135: =F134/E134-1 -> 0.74421045 | G135: =G134/F134-1 -> 0.12964608 | H135: =H134/G134-1 -> -0.065148413 | I135: =AVERAGE(D135:H135) -> 0.1222274
B136: Revenue growth | C136: =C9 -> -0.16375988 | D136: =D9 -> 0.13781384 | E136: =E9 -> 0.81151936 | F136: =F9 -> -0.10841 | G136: =G9 -> -0.098870763 | H136: =H9 -> 0.23774405 | I136: =AVERAGE(C136:H136) -> 0.1360061
C138: 2023 | D138: 2022 | E138: 2021 | F138: 2020 | G138: 2019 | H138: 2018
B139: Average sales price per ton | C139: 2.845 | D139: 3.003 | E139: 1.292 | F139: 0.789 | G139: 0.851 | H139: 0.899 | I139: =AVERAGE(C139:H139) -> 1.6131667
B140: YoY | C140: =C139/D139-1 -> -0.052614053 | D140: =D139/E139-1 -> 1.3243034 | E140: =E139/F139-1 -> 0.63751584 | F140: =F139/G139-1 -> -0.072855464 | G140: =G139/H139-1 -> -0.053392659 | I140: =AVERAGE(C140:G140) -> 0.35659141
B142: Weight | C142: Category | D142: 2018 | E142: 2022 | F142: 2021 | G142: 2020 | H142: 2019 | I142: 2023 | J142: average | K142: 2024(FWD) | L142: 2025(FWD) | M142: 2026 | N142: 2027 | O142: 2028 | P142: 2029 | Q142: 2030 | R142: 2031 | S142: 2032 | T142: 2033 | U142: 2034 | V142: 2035 | W142: 2036 | X142: 2037 | Y142: 2038 | Z142: 2039 | AA142: 2040 | AB142: 2041 | AC142: 2042 | AD142: 2043 | AE142: 2044 | AF142: 2045 | AG142: 2046 | AH142: 2047 | AI142: 2048 | AJ142: 2049
B143: 0.57869569 | C143: Steel mills | D143: 16.24522 | E143: 24.189858 | F143: 24.145396 | G143: 12.10886 | H143: 13.93395 | I143: 20.092662 | K143: =K145*K147*1000 -> 18515.616 | L143: =L145*L147*1000 -> 18407.465 | M143: =M145*M147*1000 -> 18265.911 | N143: =N145*N147*1000 -> 18125.446 | O143: =O145*O147*1000 -> 18489.315 | P143: =P145*P147*1000 -> 18860.488 | Q143: =Q145*Q147*1000 -> 19334.829 | R143: =R145*R147*1000 -> 19821.1 | ... AJ143: =AJ145*AJ147*1000 -> 30995.685
C144: YoY | E144: =E143/F143-1 -> 0.0018414277 | F144: =F143/G143-1 -> 0.99402718 | G144: =G143/H143-1 -> -0.13098152 | H144: =H143/D143-1 -> -0.14227385 | I144: =I143/E143-1 -> -0.1693766 | K144: =K143/I143-1 -> 920.51134 | L144: =L143/K143-1 -> -0.0058410757 | M144: =M143/L143-1 -> -0.00769 | N144: =N143/M143-1 -> -0.00769 | O144: =O143/N143-1 -> 0.020075 | P144: =P143/O143-1 -> 0.020075 | Q144: =Q143/P143-1 -> 0.02515 | R144: =R143/Q143-1 -> 0.02515 | S144: =S143/R143-1 -> 0.02515 | ... AJ144: =AJ143/AI143-1 -> 0.02515
C145: sales volume | D145: 19.89 | E145: 18.2 | F145: 20.296 | G145: 18.049 | H145: 18.585 | I145: 18.552 | K145: =Table1[[#This Row],[2023]]*(1+K146) -> 18.36648 | L145: 19.02 | M145: =Table1[[#This Row],[2025(FWD)]]*(1+M146) -> 19.45746 | N145: =Table1[[#This Row],[2026]]*(1+N146) -> 19.904982 | O145: =Table1[[#This Row],[2027]]*(1+O146) -> 20.004506 | P145: =Table1[[#This Row],[2028]]*(1+P146) -> 20.104529 | Q145: =Table1[[#This Row],[2029]]*(1+Q146) -> 20.305574 | R145: =Table1[[#This Row],[2030]]*(1+R146) -> 20.50863 | S145: =Table1[[#This Row],[2031]]*(1+S146) -> 20.713716 | T145: =Table1[[#This Row],[2032]]*(1+T146) -> 20.920854 | U145: =Table1[[#This Row],[2033]]*(1+U146) -> 21.130062 | V145: =Table1[[#This Row],[2034]]*(1+V146) -> 21.341363 | W145: =Table1[[#This Row],[2035]]*(1+W146) -> 21.554776 | X145: =Table1[[#This Row],[2036]]*(1+X146) -> 21.770324 | Y145: =Table1[[#This Row],[2037]]*(1+Y146) -> 21.988027 | Z145: =Table1[[#This Row],[2038]]*(1+Z146) -> 22.207908 | AA145: =Table1[[#This Row],[2039]]*(1+AA146) -> 22.429987 | AB145: =Table1[[#This Row],[2040]]*(1+AB146) -> 22.654287 | AC145: =Table1[[#This Row],[2041]]*(1+AC146) -> 22.880829 | AD145: =Table1[[#This Row],[2042]]*(1+AD146) -> 23.109638 | AE145: =Table1[[#This Row],[2043]]*(1+AE146) -> 23.340734 | AF145: =Table1[[#This Row],[2044]]*(1+AF146) -> 23.574141 | AG145: =Table1[[#This Row],[2045]]*(1+AG146) -> 23.809883 | AH145: =Table1[[#This Row],[2046]]*(1+AH146) -> 24.047982 | AI145: =Table1[[#This Row],[2047]]*(1+AI146) -> 24.288461 | AJ145: =Table1[[#This Row],[2048]]*(1+AJ146) -> 24.531346
C146: YoY | E146: =E145/F145-1 -> -0.10327158 | F146: =F145/G145-1 -> 0.12449443 | G146: =G145/H145-1 -> -0.028840463 | H146: =H145/D145-1 -> -0.06561086 | I146: =I145/E145-1 -> 0.019340659 | J146: =AVERAGE(Table1[[#This Row],[2018]:[2023]]) -> -0.010777562 | K146: -0.01 | L146: =L145/K145-1 -> 0.035582213 | M146: 0.023 | N146: 0.023 | O146: 0.005 | P146: 0.005 | Q146: 0.01 | R146: 0.01 | S146: 0.01 | T146: 0.01 | U146: 0.01 | V146: 0.01 | W146: 0.01 | X146: 0.01 | Y146: 0.01 | Z146: 0.01 | AA146: 0.01 | AB146: 0.01 | AC146: 0.01 | AD146: 0.01 | AE146: 0.01 | AF146: 0.01 | AG146: 0.01 | AH146: 0.01 | AI146: 0.01 | AJ146: 0.01
C147: Average sales price/ton | D147: 0.817 | E147: 1.324 | F147: 1.195 | G147: 0.671 | H147: 0.748 | I147: 1.084 | K147: =Table1[[#This Row],[2023]]*(1+K148) -> 1.00812 | L147: =Table1[[#This Row],[2024(FWD)]]*(1+L148) -> 0.9677952 | M147: =Table1[[#This Row],[2025(FWD)]]*(1+M148) -> 0.93876134 | N147: =Table1[[#This Row],[2026]]*(1+N148) -> 0.9105985 | O147: =Table1[[#This Row],[2027]]*(1+O148) -> 0.92425748 | P147: =Table1[[#This Row],[2028]]*(1+P148) -> 0.93812134 | Q147: =Table1[[#This Row],[2029]]*(1+Q148) -> 0.95219316 | R147: =Table1[[#This Row],[2030]]*(1+R148) -> 0.96647606 | S147: =Table1[[#This Row],[2031]]*(1+S148) -> 0.9809732 | T147: =Table1[[#This Row],[2032]]*(1+T148) -> 0.9956878 | U147: =Table1[[#This Row],[2033]]*(1+U148) -> 1.0106231 | V147: =Table1[[#This Row],[2034]]*(1+V148) -> 1.0257825 | W147: =Table1[[#This Row],[2035]]*(1+W148) -> 1.0411692 | X147: =Table1[[#This Row],[2036]]*(1+X148) -> 1.0567867 | Y147: =Table1[[#This Row],[2037]]*(1+Y148) -> 1.0726385 | Z147: =Table1[[#This Row],[2038]]*(1+Z148) -> 1.0887281 | AA147: =Table1[[#This Row],[2039]]*(1+AA148) -> 1.105059 | AB147: =Table1[[#This Row],[2040]]*(1+AB148) -> 1.1216349 | AC147: =Table1[[#This Row],[2041]]*(1+AC148) -> 1.1384594 | AD147: =Table1[[#This Row],[2042]]*(1+AD148) -> 1.1555363 | AE147: =Table1[[#This Row],[2043]]*(1+AE148) -> 1.1728694 | AF147: =Table1[[#This Row],[2044]]*(1+AF148) -> 1.1904624 | AG147: =Table1[[#This Row],[2045]]*(1+AG148) -> 1.2083194 | AH147: =Table1[[#This Row],[2046]]*(1+AH148) -> 1.2264442 | AI147: =Table1[[#This Row],[2047]]*(1+AI148) -> 1.2448408 | AJ147: =Table1[[#This Row],[2048]]*(1+AJ148) -> 1.2635134
C148: YoY | E148: =E147/F147-1 -> 0.10794979 | F148: =F147/G147-1 -> 0.78092399 | G148: =G147/H147-1 -> -0.10294118 | H148: =H147/D147-1 -> -0.084455324 | I148: =I147/E147-1 -> -0.18126888 | J148: =AVERAGE(Table1[[#This Row],[2018]:[2023]]) -> 0.10404168 | K148: -0.07 | L148: -0.04 | M148: -0.03 | N148: -0.03 | O148: 0.015 | P148: 0.015 | Q148: 0.015 | R148: 0.015 | S148: 0.015 | T148: 0.015 | U148: 0.015 | V148: 0.015 | W148: 0.015 | X148: 0.015 | Y148: 0.015 | Z148: 0.015 | AA148: 0.015 | AB148: 0.015 | AC148: 0.015 | AD148: 0.015 | AE148: 0.015 | AF148: 0.015 | AG148: 0.015 | AH148: 0.015 | AI148: 0.015 | AJ148: 0.015
...

Sheet Fin. Data
A1: =Inputs!H3 -> #VALUE!
A2: =Inputs!G2 -> Figures in Millions of USD
A3: Results
B4: =OP!J20 -> 2023 | C4: =B4-1 -> 2022 | D4: =C4-1 -> 2021 | E4: =D4-1 -> 2020 | F4: =E4-1 -> 2019 | G4: =F4-1 -> 2018 | H4: =G4-1 -> 2017 | I4: =H4-1 -> 2016 | J4: =I4-1 -> 2015 | ... M4: =L4-1 -> 2012
A5: Net Sales | B5: =_xlfn.XLOOKUP($A5,Inputs!$A:$A,Inputs!B:B,,0) -> 34714 | C5: =_xlfn.XLOOKUP($A5,Inputs!$A:$A,Inputs!C:C,,0) -> 41512 | D5: =_xlfn.XLOOKUP($A5,Inputs!$A:$A,Inputs!D:D,,0) -> 36484 | E5: =_xlfn.XLOOKUP($A5,Inputs!$A:$A,Inputs!E:E,,0) -> 20140 | F5: =_xlfn.XLOOKUP($A5,Inputs!$A:$A,Inputs!F:F,,0) -> 22588.858 | G5: =_xlfn.XLOOKUP($A5,Inputs!$A:$A,Inputs!G:G,,0) -> 25067.279 | H5: =_xlfn.XLOOKUP($A5,Inputs!$A:$A,Inputs!H:H,,0) -> 20252.393 | I5: =_xlfn.XLOOKUP($A5,Inputs!$A:$A,Inputs!I:I,,0) -> 16208.122 | J5: =_xlfn.XLOOKUP($A5,Inputs!$A:$A,Inputs!J:J,,0) -> 16439.276 | K5: =_xlfn.XLOOKUP($A5,Inputs!$A:$A,Inputs!K:K,,0) -> 21105.141 | L5: =_xlfn.XLOOKUP($A5,Inputs!$A:$A,Inputs!L:L,,0) -> 19052.046 | M5: =_xlfn.XLOOKUP($A5,Inputs!$A:$A,Inputs!M:M,,0) -> 19429
A6: Growth vs. Previous year | B6: =IFERROR(B5/C5-1,"-") -> -0.16375988 | C6: =IFERROR(C5/D5-1,"-") -> 0.13781384 | D6: =IFERROR(D5/E5-1,"-") -> 0.81151936 | E6: =IFERROR(E5/F5-1,"-") -> -0.10841 | F6: =IFERROR(F5/G5-1,"-") -> -0.098870763 | G6: =IFERROR(G5/H5-1,"-") -> 0.23774405 | H6: =IFERROR(H5/I5-1,"-") -> 0.24952126 | I6: =IFERROR(I5/J5-1,"-") -> -0.014061082 | ... L6: =IFERROR(L5/M5-1,"-") -> -0.019401616 | M6: =IFERROR(M5/#REF!-1,"-") -> -
A7: Gross Profit | B7: =_xlfn.XLOOKUP($A7,Inputs!$A:$A,Inputs!B:B,,0) -> 7814.4 | C7: =_xlfn.XLOOKUP($A7,Inputs!$A:$A,Inputs!C:C,,0) -> 12503.28 | D7: =_xlfn.XLOOKUP($A7,Inputs!$A:$A,Inputs!D:D,,0) -> 11025.41 | E7: =_xlfn.XLOOKUP($A7,Inputs!$A:$A,Inputs!E:E,,0) -> 2227.95 | F7: =_xlfn.XLOOKUP($A7,Inputs!$A:$A,Inputs!F:F,,0) -> 2679.09 | G7: =_xlfn.XLOOKUP($A7,Inputs!$A:$A,Inputs!G:G,,0) -> 4295 | H7: =_xlfn.XLOOKUP($A7,Inputs!$A:$A,Inputs!H:H,,0) -> 2570 | I7: =_xlfn.XLOOKUP($A7,Inputs!$A:$A,Inputs!I:I,,0) -> 2026 | J7: =_xlfn.XLOOKUP($A7,Inputs!$A:$A,Inputs!J:J,,0) -> 1114 | K7: =_xlfn.XLOOKUP($A7,Inputs!$A:$A,Inputs!K:K,,0) -> 1849 | L7: =_xlfn.XLOOKUP($A7,Inputs!$A:$A,Inputs!L:L,,0) -> 1411 | M7: =_xlfn.XLOOKUP($A7,Inputs!$A:$A,Inputs!M:M,,0) -> 1513.54
A8: % over sales | B8: =IFERROR(B7/B$5,"-") -> 0.22510803 | C8: =IFERROR(C7/C$5,"-") -> 0.30119676 | D8: =IFERROR(D7/D$5,"-") -> 0.3021985 | E8: =IFERROR(E7/E$5,"-") -> 0.11062314 | F8: =IFERROR(F7/F$5,"-") -> 0.11860228 | G8: =IFERROR(G7/G$5,"-") -> 0.1713389 | H8: =IFERROR(H7/H$5,"-") -> 0.12689858 | I8: =IFERROR(I7/I$5,"-") -> 0.12499906 | ... M8: =IFERROR(M7/M$5,"-") -> 0.077901076
A9: Operating expenses | B9: =B5-B11 -> 28483.6 | C9: =C5-C11 -> 31005.72 | D9: =D5-D11 -> 27165.59 | E9: =E5-E11 -> 18527.05 | F9: =F5-F11 -> 20620.768 | G9: =G5-G11 -> 21633.279 | H9: =H5-H11 -> 18370.393 | I9: =I5-I11 -> 14779.122 | ... M9: =M5-M11 -> 18352.46
A10: % over sales | B10: =IFERROR(B9/B$5,"-") -> 0.82052198 | C10: =IFERROR(C9/C$5,"-") -> 0.74690981 | D10: =IFERROR(D9/D$5,"-") -> 0.74458913 | E10: =IFERROR(E9/E$5,"-") -> 0.91991311 | F10: =IFERROR(F9/F$5,"-") -> 0.91287342 | G10: =IFERROR(G9/G$5,"-") -> 0.86300867 | H10: =IFERROR(H9/H$5,"-") -> 0.90707271 | I10: =IFERROR(I9/I$5,"-") -> 0.91183433 | ... M10: =IFERROR(M9/M$5,"-") -> 0.94459108
A11: Operating Income | B11: =Inputs!B8 -> 6230.4 | C11: =Inputs!C8 -> 10506.28 | D11: =Inputs!D8 -> 9318.41 | E11: =Inputs!E8 -> 1612.95 | F11: =Inputs!F8 -> 1968.09 | G11: =Inputs!G8 -> 3434 | H11: =Inputs!H8 -> 1882 | I11: =Inputs!I8 -> 1429 | ... M11: =Inputs!M8 -> 1076.54
A12: Operating Margin | B12: =IFERROR(B11/B$5,"-") -> 0.17947802 | C12: =IFERROR(C11/C$5,"-") -> 0.25309019 | D12: =IFERROR(D11/D$5,"-") -> 0.25541087 | E12: =IFERROR(E11/E$5,"-") -> 0.080086892 | F12: =IFERROR(F11/F$5,"-") -> 0.087126582 | G12: =IFERROR(G11/G$5,"-") -> 0.13699133 | H12: =IFERROR(H11/H$5,"-") -> 0.09292729 | I12: =IFERROR(I11/I$5,"-") -> 0.088165674 | ... M12: =IFERROR(M11/M$5,"-") -> 0.055408925
A13: Growth vs. Previous year | B13: =IFERROR(B12/C12-1,"-") -> -0.29085351 | C13: =IFERROR(C12/D12-1,"-") -> -0.0090860436 | D13: =IFERROR(D12/E12-1,"-") -> 2.1891719 | E13: =IFERROR(E12/F12-1,"-") -> -0.080798426 | F13: =IFERROR(F12/G12-1,"-") -> -0.36399932 | G13: =IFERROR(G12/H12-1,"-") -> 0.47417765 | H13: =IFERROR(H12/I12-1,"-") -> 0.054007597 | I13: =IFERROR(I12/J12-1,"-") -> 1.2127937 | ... L13: =IFERROR(L12/M12-1,"-") -> -0.10671437 | M13: =IFERROR(M12/#REF!-1,"-") -> -
A14: Net Financial Cost | B14: =_xlfn.XLOOKUP($A14,Inputs!$A:$A,Inputs!B:B,,0) -> 29.632 | C14: =_xlfn.XLOOKUP($A14,Inputs!$A:$A,Inputs!C:C,,0) -> -170.216 | D14: =_xlfn.XLOOKUP($A14,Inputs!$A:$A,Inputs!D:D,,0) -> -158.854 | E14: =_xlfn.XLOOKUP($A14,Inputs!$A:$A,Inputs!E:E,,0) -> -153.198 | F14: =_xlfn.XLOOKUP($A14,Inputs!$A:$A,Inputs!F:F,,0) -> -121.425 | G14: =_xlfn.XLOOKUP($A14,Inputs!$A:$A,Inputs!G:G,,0) -> -135.535 | H14: =_xlfn.XLOOKUP($A14,Inputs!$A:$A,Inputs!H:H,,0) -> -173.58 | I14: =_xlfn.XLOOKUP($A14,Inputs!$A:$A,Inputs!I:I,,0) -> -169.244 | J14: =_xlfn.XLOOKUP($A14,Inputs!$A:$A,Inputs!J:J,,0) -> -173.531 | K14: =_xlfn.XLOOKUP($A14,Inputs!$A:$A,Inputs!K:K,,0) -> -169.256 | L14: =_xlfn.XLOOKUP($A14,Inputs!$A:$A,Inputs!L:L,,0) -> -146.895 | M14: =_xlfn.XLOOKUP($A14,Inputs!$A:$A,Inputs!M:M,,0) -> -162.375
A15: Other Expenses (Revenues) | B15: =Inputs!B9 -> -12.783 | C15: =Inputs!C9 -> 91.042 | D15: =Inputs!D9 -> -40.907 | E15: =Inputs!E9 -> 624.173 | F15: =Inputs!F9 -> 63.605 | G15: =Inputs!G9 -> 69.76 | H15: =Inputs!H9 -> -41.661 | I15: =Inputs!I9 -> -38.757 | ... M15: =Inputs!M9 -> 60.886
A16: EBIT | B16: =B11-B15 -> 6243.183 | C16: =C11-C15 -> 10415.238 | D16: =D11-D15 -> 9359.317 | E16: =E11-E15 -> 988.777 | F16: =F11-F15 -> 1904.485 | G16: =G11-G15 -> 3364.24 | H16: =H11-H15 -> 1923.661 | I16: =I11-I15 -> 1467.757 | ... M16: =M11-M15 -> 1015.654
A17: Depreciation & Amortization | B17: =_xlfn.XLOOKUP($A17,Inputs!$A:$A,Inputs!B:B,,0) -> 1168.32 | C17: =_xlfn.XLOOKUP($A17,Inputs!$A:$A,Inputs!C:C,,0) -> 1061.63 | D17: =_xlfn.XLOOKUP($A17,Inputs!$A:$A,Inputs!D:D,,0) -> 864.56 | E17: =_xlfn.XLOOKUP($A17,Inputs!$A:$A,Inputs!E:E,,0) -> 785.47 | F17: =_xlfn.XLOOKUP($A17,Inputs!$A:$A,Inputs!F:F,,0) -> 734.65 | G17: =_xlfn.XLOOKUP($A17,Inputs!$A:$A,Inputs!G:G,,0) -> 719.64 | H17: =_xlfn.XLOOKUP($A17,Inputs!$A:$A,Inputs!H:H,,0) -> 727.06 | I17: =_xlfn.XLOOKUP($A17,Inputs!$A:$A,Inputs!I:I,,0) -> 687.05 | J17: =_xlfn.XLOOKUP($A17,Inputs!$A:$A,Inputs!J:J,,0) -> 944.9 | K17: =_xlfn.XLOOKUP($A17,Inputs!$A:$A,Inputs!K:K,,0) -> 749.8 | L17: =_xlfn.XLOOKUP($A17,Inputs!$A:$A,Inputs!L:L,,0) -> 624.2 | M17: =_xlfn.XLOOKUP($A17,Inputs!$A:$A,Inputs!M:M,,0) -> 624.6
A18: Changes Net Working Capital | B18: 858.406 | C18: 877.44 | D18: -1862.89 | E18: 204 | F18: 413.27 | G18: =_xlfn.XLOOKUP($A18,Inputs!$A:$A,Inputs!G:G,,0) -> 1380.51 | H18: =_xlfn.XLOOKUP($A18,Inputs!$A:$A,Inputs!H:H,,0) -> 980.14 | I18: =_xlfn.XLOOKUP($A18,Inputs!$A:$A,Inputs!I:I,,0) -> -459.28 | J18: =_xlfn.XLOOKUP($A18,Inputs!$A:$A,Inputs!J:J,,0) -> -790.3 | K18: =_xlfn.XLOOKUP($A18,Inputs!$A:$A,Inputs!K:K,,0) -> 353.5 | L18: =_xlfn.XLOOKUP($A18,Inputs!$A:$A,Inputs!L:L,,0) -> 387.6 | M18: =_xlfn.XLOOKUP($A18,Inputs!$A:$A,Inputs!M:M,,0) -> 2578.9
A19: EBITDA | B19: =B11-B15+B17 -> 7411.503 | C19: =C11-C15+C17 -> 11476.868 | D19: =D11-D15+D17 -> 10223.877 | E19: =E11-E15+E17 -> 1774.247 | F19: =F11-F15+F17 -> 2639.135 | G19: =G11-G15+G17 -> 4083.88 | H19: =H11-H15+H17 -> 2650.721 | I19: =I11-I15+I17 -> 2154.807 | ... M19: =M11-M15+M17 -> 1640.254
A20: EBITDA Margin | B20: =IFERROR(B19/B$5,"-") -> 0.21350184 | C20: =IFERROR(C19/C$5,"-") -> 0.27647109 | D20: =IFERROR(D19/D$5,"-") -> 0.28022906 | E20: =IFERROR(E19/E$5,"-") -> 0.08809568 | F20: =IFERROR(F19/F$5,"-") -> 0.11683348 | G20: =IFERROR(G19/G$5,"-") -> 0.16291676 | H20: =IFERROR(H19/H$5,"-") -> 0.13088434 | I20: =IFERROR(I19/I$5,"-") -> 0.13294612 | ... M20: =IFERROR(M19/M$5,"-") -> 0.084422976
A21: Taxes | B21: =_xlfn.XLOOKUP($A21,Inputs!$A:$A,Inputs!B:B,,0) -> -1359.966 | C21: =_xlfn.XLOOKUP($A21,Inputs!$A:$A,Inputs!C:C,,0) -> -2165.204 | D21: =_xlfn.XLOOKUP($A21,Inputs!$A:$A,Inputs!D:D,,0) -> -2078.488 | E21: =_xlfn.XLOOKUP($A21,Inputs!$A:$A,Inputs!E:E,,0) -> 0.49 | F21: =_xlfn.XLOOKUP($A21,Inputs!$A:$A,Inputs!F:F,,0) -> -411.897 | G21: =_xlfn.XLOOKUP($A21,Inputs!$A:$A,Inputs!G:G,,0) -> -748.307 | H21: =_xlfn.XLOOKUP($A21,Inputs!$A:$A,Inputs!H:H,,0) -> -369.386 | I21: =_xlfn.XLOOKUP($A21,Inputs!$A:$A,Inputs!I:I,,0) -> -398.243 | J21: =_xlfn.XLOOKUP($A21,Inputs!$A:$A,Inputs!J:J,,0) -> -48.836 | K21: =_xlfn.XLOOKUP($A21,Inputs!$A:$A,Inputs!K:K,,0) -> -368.724 | L21: =_xlfn.XLOOKUP($A21,Inputs!$A:$A,Inputs!L:L,,0) -> -205.594 | M21: =_xlfn.XLOOKUP($A21,Inputs!$A:$A,Inputs!M:M,,0) -> -259.814
A22: % Tax | B22: =IFERROR(B21/B$5,"-") -> -0.039176298 | C22: =IFERROR(C21/C$5,"-") -> -0.052158508 | D22: =IFERROR(D21/D$5,"-") -> -0.05696985 | E22: =IFERROR(E21/E$5,"-") -> 2.4329692e-05 | F22: =IFERROR(F21/F$5,"-") -> -0.018234521 | G22: =IFERROR(G21/G$5,"-") -> -0.029851944 | H22: =IFERROR(H21/H$5,"-") -> -0.018239129 | I22: =IFERROR(I21/I$5,"-") -> -0.024570583 | ... M22: =IFERROR(M21/M$5,"-") -> -0.013372484
A23: Net Income | B23: =_xlfn.XLOOKUP($A23,Inputs!$A:$A,Inputs!B:B,,0) -> 4524.849 | C23: =_xlfn.XLOOKUP($A23,Inputs!$A:$A,Inputs!C:C,,0) -> 7607.818 | D23: =_xlfn.XLOOKUP($A23,Inputs!$A:$A,Inputs!D:D,,0) -> 6826.975 | E23: =_xlfn.XLOOKUP($A23,Inputs!$A:$A,Inputs!E:E,,0) -> 721.069 | F23: =_xlfn.XLOOKUP($A23,Inputs!$A:$A,Inputs!F:F,,0) -> 1271.163 | G23: =_xlfn.XLOOKUP($A23,Inputs!$A:$A,Inputs!G:G,,0) -> 2360.398 | H23: =_xlfn.XLOOKUP($A23,Inputs!$A:$A,Inputs!H:H,,0) -> 1318.695 | I23: =_xlfn.XLOOKUP($A23,Inputs!$A:$A,Inputs!I:I,,0) -> 796.27 | J23: =_xlfn.XLOOKUP($A23,Inputs!$A:$A,Inputs!J:J,,0) -> 81.129 | K23: =_xlfn.XLOOKUP($A23,Inputs!$A:$A,Inputs!K:K,,0) -> 679.132 | L23: =_xlfn.XLOOKUP($A23,Inputs!$A:$A,Inputs!L:L,,0) -> 487.808 | M23: =_xlfn.XLOOKUP($A23,Inputs!$A:$A,Inputs!M:M,,0) -> 504.465
A24: Net Income Margin | B24: =IFERROR(B23/B$5,"-") -> 0.13034652 | C24: =IFERROR(C23/C$5,"-") -> 0.18326792 | D24: =IFERROR(D23/D$5,"-") -> 0.18712244 | E24: =IFERROR(E23/E$5,"-") -> 0.03580283 | F24: =IFERROR(F23/F$5,"-") -> 0.056273894 | G24: =IFERROR(G23/G$5,"-") -> 0.094162514 | H24: =IFERROR(H23/H$5,"-") -> 0.065113046 | I24: =IFERROR(I23/I$5,"-") -> 0.049127838 | ... M24: =IFERROR(M23/M$5,"-") -> 0.025964538
A25: Growth vs. Previous year | B25: =IFERROR(B24/C24-1,"-") -> -0.28876524 | C25: =IFERROR(C24/D24-1,"-") -> -0.020598891 | D25: =IFERROR(D24/E24-1,"-") -> 4.2264705 | E25: =IFERROR(E24/F24-1,"-") -> -0.3637755 | F25: =IFERROR(F24/G24-1,"-") -> -0.40237477 | G25: =IFERROR(G24/H24-1,"-") -> 0.44613897 | H25: =IFERROR(H24/I24-1,"-") -> 0.32537983 | I25: =IFERROR(I24/J24-1,"-") -> 8.9548385 | ... L25: =IFERROR(L24/M24-1,"-") -> -0.013886952 | M25: =IFERROR(M24/#REF!-1,"-") -> -
A26: Cash Generated | B26: =B41-C41 -> 2102.4 | C26: =C41-D41 -> 1916 | D26: =D41-E41 -> -274.8 | E26: =E41-F41 -> 1105.1 | F26: =F41-G41 -> 135.7 | G26: =G41-H41 -> 449.8 | H26: =H41-I41 -> -1096.9 | I26: =I41-J41 -> 106.5 | ... M26: =M41-N41 -> 1052.9
A27: Dividends | B27: =_xlfn.XLOOKUP($A27,Inputs!$A:$A,Inputs!B:B,,0) -> -514.53 | C27: =_xlfn.XLOOKUP($A27,Inputs!$A:$A,Inputs!C:C,,0) -> -533.59 | D27: =_xlfn.XLOOKUP($A27,Inputs!$A:$A,Inputs!D:D,,0) -> -483.47 | E27: =_xlfn.XLOOKUP($A27,Inputs!$A:$A,Inputs!E:E,,0) -> -491.66 | F27: =_xlfn.XLOOKUP($A27,Inputs!$A:$A,Inputs!F:F,,0) -> -492.06 | G27: =_xlfn.XLOOKUP($A27,Inputs!$A:$A,Inputs!G:G,,0) -> -485.38 | H27: =_xlfn.XLOOKUP($A27,Inputs!$A:$A,Inputs!H:H,,0) -> -485.32 | I27: =_xlfn.XLOOKUP($A27,Inputs!$A:$A,Inputs!I:I,,0) -> -481.08 | J27: =_xlfn.XLOOKUP($A27,Inputs!$A:$A,Inputs!J:J,,0) -> -479.4 | K27: =_xlfn.XLOOKUP($A27,Inputs!$A:$A,Inputs!K:K,,0) -> -475.1 | L27: =_xlfn.XLOOKUP($A27,Inputs!$A:$A,Inputs!L:L,,0) -> -471 | M27: =_xlfn.XLOOKUP($A27,Inputs!$A:$A,Inputs!M:M,,0) -> -466.4
A28: Share buyback | B28: =_xlfn.XLOOKUP($A28,Inputs!$A:$A,Inputs!B:B,,0) -> -1591.52 | C28: =_xlfn.XLOOKUP($A28,Inputs!$A:$A,Inputs!C:C,,0) -> -2803.8 | D28: =_xlfn.XLOOKUP($A28,Inputs!$A:$A,Inputs!D:D,,0) -> -3204.09 | E28: =_xlfn.XLOOKUP($A28,Inputs!$A:$A,Inputs!E:E,,0) -> -46.76 | F28: =_xlfn.XLOOKUP($A28,Inputs!$A:$A,Inputs!F:F,,0) -> -307.44 | G28: =_xlfn.XLOOKUP($A28,Inputs!$A:$A,Inputs!G:G,,0) -> -852.02 | H28: =_xlfn.XLOOKUP($A28,Inputs!$A:$A,Inputs!H:H,,0) -> -97.64 | I28: =_xlfn.XLOOKUP($A28,Inputs!$A:$A,Inputs!I:I,,0) -> 0.89 | J28: =_xlfn.XLOOKUP($A28,Inputs!$A:$A,Inputs!J:J,,0) -> -66.5 | K28: =_xlfn.XLOOKUP($A28,Inputs!$A:$A,Inputs!K:K,,0) -> 0 | L28: =_xlfn.XLOOKUP($A28,Inputs!$A:$A,Inputs!L:L,,0) -> 0 | M28: =_xlfn.XLOOKUP($A28,Inputs!$A:$A,Inputs!M:M,,0) -> 0
A29: Net Cash Flow | B29: =SUM(B26:B28) -> -3.65 | C29: =SUM(C26:C28) -> -1421.39 | D29: =SUM(D26:D28) -> -3962.36 | E29: =SUM(E26:E28) -> 566.68 | F29: =SUM(F26:F28) -> -663.8 | G29: =SUM(G26:G28) -> -887.6 | H29: =SUM(H26:H28) -> -1679.86 | I29: =SUM(I26:I28) -> -373.69 | ... M29: =SUM(M26:M28) -> 586.5
A30: FNP'' | B30: =+B29-(B63-C29) -> -8267.223 | C30: =+C29-(C63-D29) -> -12075.117 | D30: =+D29-(D63-E29) -> -9116.52 | E30: =+E29-(E63-F29) -> -5437.719 | F30: =+F29-(F63-G29) -> -5934.441 | G30: =+G29-(G63-H29) -> -6858.606 | H30: =+H29-(H63-I29) -> #N/A | I30: =+I29-(I63-J29) -> #N/A | ... M30: =+M29-(M63-N29) -> #N/A
A31: FNP' | B31: =+B30+B33 -> -8492.267 | C31: =+C30+C33 -> -15952.033 | D31: =+D30+D33 -> -10387.946 | E31: =+E30+E33 -> -5622.129 | F31: =+F30+F33 -> -6317.587 | G31: =+G30+G33 -> -6841.669 | H31: =+H30+H33 -> #N/A | I31: =+I30+I33 -> #N/A | ... M31: =+M30+M33 -> #N/A
A32: Net Capex | B32: =_xlfn.XLOOKUP($A32,Inputs!$A:$A,Inputs!B:B,,0) -> -2199.3 | C32: =_xlfn.XLOOKUP($A32,Inputs!$A:$A,Inputs!C:C,,0) -> -1915.6 | D32: =_xlfn.XLOOKUP($A32,Inputs!$A:$A,Inputs!D:D,,0) -> -1602.6 | E32: =_xlfn.XLOOKUP($A32,Inputs!$A:$A,Inputs!E:E,,0) -> -1502.3 | F32: =_xlfn.XLOOKUP($A32,Inputs!$A:$A,Inputs!F:F,,0) -> -1435.7 | G32: =_xlfn.XLOOKUP($A32,Inputs!$A:$A,Inputs!G:G,,0) -> -950.9 | H32: =_xlfn.XLOOKUP($A32,Inputs!$A:$A,Inputs!H:H,,0) -> -423.2 | I32: =_xlfn.XLOOKUP($A32,Inputs!$A:$A,Inputs!I:I,,0) -> -586.3 | J32: =_xlfn.XLOOKUP($A32,Inputs!$A:$A,Inputs!J:J,,0) -> -344.7 | K32: =_xlfn.XLOOKUP($A32,Inputs!$A:$A,Inputs!K:K,,0) -> -631.4 | L32: =_xlfn.XLOOKUP($A32,Inputs!$A:$A,Inputs!L:L,,0) -> -1162.9 | M32: =_xlfn.XLOOKUP($A32,Inputs!$A:$A,Inputs!M:M,,0) -> -896.6
A33: Investments & Acquisitions | B33: =_xlfn.XLOOKUP($A33,Inputs!$A:$A,Inputs!B:B,,0) -> -225.044 | C33: =_xlfn.XLOOKUP($A33,Inputs!$A:$A,Inputs!C:C,,0) -> -3876.916 | D33: =_xlfn.XLOOKUP($A33,Inputs!$A:$A,Inputs!D:D,,0) -> -1271.426 | E33: =_xlfn.XLOOKUP($A33,Inputs!$A:$A,Inputs!E:E,,0) -> -184.41 | F33: =_xlfn.XLOOKUP($A33,Inputs!$A:$A,Inputs!F:F,,0) -> -383.146 | G33: =_xlfn.XLOOKUP($A33,Inputs!$A:$A,Inputs!G:G,,0) -> 16.937 | H33: =_xlfn.XLOOKUP($A33,Inputs!$A:$A,Inputs!H:H,,0) -> -503.04 | I33: =_xlfn.XLOOKUP($A33,Inputs!$A:$A,Inputs!I:I,,0) -> -587.97 | J33: =_xlfn.XLOOKUP($A33,Inputs!$A:$A,Inputs!J:J,,0) -> -99.9 | K33: =_xlfn.XLOOKUP($A33,Inputs!$A:$A,Inputs!K:K,,0) -> -938.9 | L33: =_xlfn.XLOOKUP($A33,Inputs!$A:$A,Inputs!L:L,,0) -> 137.1 | M33: =_xlfn.XLOOKUP($A33,Inputs!$A:$A,Inputs!M:M,,0) -> 675.7
A34: Capex + Investments | B34: =+B32+B33 -> -2424.344 | C34: =+C32+C33 -> -5792.516 | D34: =+D32+D33 -> -2874.026 | E34: =+E32+E33 -> -1686.71 | F34: =+F32+F33 -> -1818.846 | G34: =+G32+G33 -> -933.963 | H34: =+H32+H33 -> -926.24 | I34: =+I32+I33 -> -1174.27 | ... M34: =+M32+M33 -> -220.9
A35: Dividends + Share Buyback | B35: =+B27+B28 -> -2106.05 | C35: =+C27+C28 -> -3337.39 | D35: =+D27+D28 -> -3687.56 | E35: =+E27+E28 -> -538.42 | F35: =+F27+F28 -> -799.5 | G35: =+G27+G28 -> -1337.4 | H35: =+H27+H28 -> -582.96 | I35: =+I27+I28 -> -480.19 | ... M35: =+M27+M28 -> -466.4
A36: Payout Ratio | B36: =IFERROR(B35/B23,"-") -> -0.46544095 | C36: =IFERROR(C35/C23,"-") -> -0.438679 | D36: =IFERROR(D35/D23,"-") -> -0.54014553 | E36: =IFERROR(E35/E23,"-") -> -0.74669692 | F36: =IFERROR(F35/F23,"-") -> -0.6289516 | G36: =IFERROR(G35/G23,"-") -> -0.56659936 | H36: =IFERROR(H35/H23,"-") -> -0.44207341 | I36: =IFERROR(I35/I23,"-") -> -0.60304922 | ... M36: =IFERROR(M35/M23,"-") -> -0.92454382
A37: Depreciation | B37: 930.585 | C37: 826.692 | D37: 735.406 | E37: 702.11 | F37: 648.911 | G37: 630.879 | H37: 635.833 | I37: 613.192 | J37: 625.757
A38: amortization | B38: =B17-B37 -> 237.735 | C38: =C17-C37 -> 234.938 | D38: =D17-D37 -> 129.154 | E38: =E17-E37 -> 83.36 | F38: =F17-F37 -> 85.739 | G38: =G17-G37 -> 88.761 | H38: =H17-H37 -> 91.227 | I38: =I17-I37 -> 73.858 | J38: =J17-J37 -> 319.143
A39: Other current assets | B39: 724.012 | C39: 789.325 | D39: 316.54 | E39: 573.048 | F39: 389.528 | G39: 178.311
A40: Assets
A41: Cash & Eq. | B41: =_xlfn.XLOOKUP($A41,Inputs!$A:$A,Inputs!B:B,,0) -> 6383.3 | C41: =_xlfn.XLOOKUP($A41,Inputs!$A:$A,Inputs!C:C,,0) -> 4280.9 | D41: =_xlfn.XLOOKUP($A41,Inputs!$A:$A,Inputs!D:D,,0) -> 2364.9 | E41: =_xlfn.XLOOKUP($A41,Inputs!$A:$A,Inputs!E:E,,0) -> 2639.7 | F41: =_xlfn.XLOOKUP($A41,Inputs!$A:$A,Inputs!F:F,,0) -> 1534.6 | G41: =_xlfn.XLOOKUP($A41,Inputs!$A:$A,Inputs!G:G,,0) -> 1398.9 | H41: =_xlfn.XLOOKUP($A41,Inputs!$A:$A,Inputs!H:H,,0) -> 949.1 | I41: =_xlfn.XLOOKUP($A41,Inputs!$A:$A,Inputs!I:I,,0) -> 2046 | J41: =_xlfn.XLOOKUP($A41,Inputs!$A:$A,Inputs!J:J,,0) -> 1939.5 | K41: =_xlfn.XLOOKUP($A41,Inputs!$A:$A,Inputs!K:K,,0) -> 1024.1 | L41: =_xlfn.XLOOKUP($A41,Inputs!$A:$A,Inputs!L:L,,0) -> 1483.3 | M41: =_xlfn.XLOOKUP($A41,Inputs!$A:$A,Inputs!M:M,,0) -> 1052.9
A42: Accounts Receivable | B42: =_xlfn.XLOOKUP($A42,Inputs!$A:$A,Inputs!B:B,,0) -> 2953.31 | C42: =_xlfn.XLOOKUP($A42,Inputs!$A:$A,Inputs!C:C,,0) -> 3591.03 | D42: =_xlfn.XLOOKUP($A42,Inputs!$A:$A,Inputs!D:D,,0) -> 3853.97 | E42: =_xlfn.XLOOKUP($A42,Inputs!$A:$A,Inputs!E:E,,0) -> 2298.85 | F42: =_xlfn.XLOOKUP($A42,Inputs!$A:$A,Inputs!F:F,,0) -> 2160.1 | G42: =_xlfn.XLOOKUP($A42,Inputs!$A:$A,Inputs!G:G,,0) -> 2505.57 | H42: =_xlfn.XLOOKUP($A42,Inputs!$A:$A,Inputs!H:H,,0) -> 2028.55 | I42: =_xlfn.XLOOKUP($A42,Inputs!$A:$A,Inputs!I:I,,0) -> 1631.68 | J42: =_xlfn.XLOOKUP($A42,Inputs!$A:$A,Inputs!J:J,,0) -> 1383.8 | K42: =_xlfn.XLOOKUP($A42,Inputs!$A:$A,Inputs!K:K,,0) -> 2068.3 | L42: =_xlfn.XLOOKUP($A42,Inputs!$A:$A,Inputs!L:L,,0) -> 1881 | M42: =_xlfn.XLOOKUP($A42,Inputs!$A:$A,Inputs!M:M,,0) -> 1707.3
A43: Inventory | B43: =_xlfn.XLOOKUP($A43,Inputs!$A:$A,Inputs!B:B,,0) -> 5577.76 | C43: =_xlfn.XLOOKUP($A43,Inputs!$A:$A,Inputs!C:C,,0) -> 5453.53 | D43: =_xlfn.XLOOKUP($A43,Inputs!$A:$A,Inputs!D:D,,0) -> 6011.18 | E43: =_xlfn.XLOOKUP($A43,Inputs!$A:$A,Inputs!E:E,,0) -> 3569.09 | F43: =_xlfn.XLOOKUP($A43,Inputs!$A:$A,Inputs!F:F,,0) -> 3842.1 | G43: =_xlfn.XLOOKUP($A43,Inputs!$A:$A,Inputs!G:G,,0) -> 4553.5 | H43: =_xlfn.XLOOKUP($A43,Inputs!$A:$A,Inputs!H:H,,0) -> 3461.69 | I43: =_xlfn.XLOOKUP($A43,Inputs!$A:$A,Inputs!I:I,,0) -> 2479.96 | J43: =_xlfn.XLOOKUP($A43,Inputs!$A:$A,Inputs!J:J,,0) -> 2245.5 | K43: =_xlfn.XLOOKUP($A43,Inputs!$A:$A,Inputs!K:K,,0) -> 2745 | L43: =_xlfn.XLOOKUP($A43,Inputs!$A:$A,Inputs!L:L,,0) -> 2605.6 | M43: =_xlfn.XLOOKUP($A43,Inputs!$A:$A,Inputs!M:M,,0) -> 2323.6
A44: Property, Plant and Equipment | B44: =_xlfn.XLOOKUP($A44,Inputs!$A:$A,Inputs!B:B,,0) -> 11049.77 | C44: =_xlfn.XLOOKUP($A44,Inputs!$A:$A,Inputs!C:C,,0) -> 9616.92 | D44: =_xlfn.XLOOKUP($A44,Inputs!$A:$A,Inputs!D:D,,0) -> 8114.82 | E44: =_xlfn.XLOOKUP($A44,Inputs!$A:$A,Inputs!E:E,,0) -> 6899.11 | F44: =_xlfn.XLOOKUP($A44,Inputs!$A:$A,Inputs!F:F,,0) -> 6178.56 | G44: =_xlfn.XLOOKUP($A44,Inputs!$A:$A,Inputs!G:G,,0) -> 5334.75 | H44: =_xlfn.XLOOKUP($A44,Inputs!$A:$A,Inputs!H:H,,0) -> 5093.15 | I44: =_xlfn.XLOOKUP($A44,Inputs!$A:$A,Inputs!I:I,,0) -> 5078.65 | J44: =_xlfn.XLOOKUP($A44,Inputs!$A:$A,Inputs!J:J,,0) -> 4891.2 | K44: =_xlfn.XLOOKUP($A44,Inputs!$A:$A,Inputs!K:K,,0) -> 5287.6 | L44: =_xlfn.XLOOKUP($A44,Inputs!$A:$A,Inputs!L:L,,0) -> 4917 | M44: =_xlfn.XLOOKUP($A44,Inputs!$A:$A,Inputs!M:M,,0) -> 4283.1
A45: Other Assets | B45: =_xlfn.XLOOKUP($A45,Inputs!$A:$A,Inputs!B:B,,0) -> 9376.36 | C45: =_xlfn.XLOOKUP($A45,Inputs!$A:$A,Inputs!C:C,,0) -> 9536.82 | D45: =_xlfn.XLOOKUP($A45,Inputs!$A:$A,Inputs!D:D,,0) -> 5478.23 | E45: =_xlfn.XLOOKUP($A45,Inputs!$A:$A,Inputs!E:E,,0) -> 4718.65 | F45: =_xlfn.XLOOKUP($A45,Inputs!$A:$A,Inputs!F:F,,0) -> 4629.34 | G45: =_xlfn.XLOOKUP($A45,Inputs!$A:$A,Inputs!G:G,,0) -> 4127.88 | H45: =_xlfn.XLOOKUP($A45,Inputs!$A:$A,Inputs!H:H,,0) -> 4308.81 | I45: =_xlfn.XLOOKUP($A45,Inputs!$A:$A,Inputs!I:I,,0) -> 3987.21 | J45: =_xlfn.XLOOKUP($A45,Inputs!$A:$A,Inputs!J:J,,0) -> 3867 | K45: =_xlfn.XLOOKUP($A45,Inputs!$A:$A,Inputs!K:K,,0) -> 4490.9 | L45: =_xlfn.XLOOKUP($A45,Inputs!$A:$A,Inputs!L:L,,0) -> 4316.4 | M45: =_xlfn.XLOOKUP($A45,Inputs!$A:$A,Inputs!M:M,,0) -> 4785.2
A46: Total Assets | B46: =_xlfn.XLOOKUP($A46,Inputs!$A:$A,Inputs!B:B,,0) -> 35340.5 | C46: =_xlfn.XLOOKUP($A46,Inputs!$A:$A,Inputs!C:C,,0) -> 32479.2 | D46: =_xlfn.XLOOKUP($A46,Inputs!$A:$A,Inputs!D:D,,0) -> 25823.1 | E46: =_xlfn.XLOOKUP($A46,Inputs!$A:$A,Inputs!E:E,,0) -> 20125.4 | F46: =_xlfn.XLOOKUP($A46,Inputs!$A:$A,Inputs!F:F,,0) -> 18344.7 | G46: =_xlfn.XLOOKUP($A46,Inputs!$A:$A,Inputs!G:G,,0) -> 17920.6 | H46: =_xlfn.XLOOKUP($A46,Inputs!$A:$A,Inputs!H:H,,0) -> 15841.3 | I46: =_xlfn.XLOOKUP($A46,Inputs!$A:$A,Inputs!I:I,,0) -> 15223.5 | J46: =_xlfn.XLOOKUP($A46,Inputs!$A:$A,Inputs!J:J,,0) -> 14327 | K46: =_xlfn.XLOOKUP($A46,Inputs!$A:$A,Inputs!K:K,,0) -> 15615.9 | L46: =_xlfn.XLOOKUP($A46,Inputs!$A:$A,Inputs!L:L,,0) -> 15203.3 | M46: =_xlfn.XLOOKUP($A46,Inputs!$A:$A,Inputs!M:M,,0) -> 14152.1
A47: Goodwill | B47: 3968.847 | C47: 3920.06 | D47: 2827.244 | E47: 2229.672 | F47: 2201.063 | G47: 2184.336
A48: Other IA | B48: 3108.015 | C48: 3322.265 | D48: 1103.759 | E48: 668.021 | F48: 742.186 | G48: 828.504
A49: Total IA | B49: =SUM(B47:B48) -> 7076.862 | C49: =SUM(C47:C48) -> 7242.325 | D49: =SUM(D47:D48) -> 3931.003 | E49: =SUM(E47:E48) -> 2897.693 | F49: =SUM(F47:F48) -> 2943.249 | G49: =SUM(G47:G48) -> 3012.84
A50: Liabilities
A51: Current Liabilities | B51: =_xlfn.XLOOKUP($A51,Inputs!$A:$A,Inputs!B:B,,0) -> 4594.51 | C51: =_xlfn.XLOOKUP($A51,Inputs!$A:$A,Inputs!C:C,,0) -> 4329.74 | D51: =_xlfn.XLOOKUP($A51,Inputs!$A:$A,Inputs!D:D,,0) -> 5157.41 | E51: =_xlfn.XLOOKUP($A51,Inputs!$A:$A,Inputs!E:E,,0) -> 2627.86 | F51: =_xlfn.XLOOKUP($A51,Inputs!$A:$A,Inputs!F:F,,0) -> 2463.77 | G51: =_xlfn.XLOOKUP($A51,Inputs!$A:$A,Inputs!G:G,,0) -> 2806.3 | H51: =_xlfn.XLOOKUP($A51,Inputs!$A:$A,Inputs!H:H,,0) -> 2824.76 | I51: =_xlfn.XLOOKUP($A51,Inputs!$A:$A,Inputs!I:I,,0) -> 2389.97 | J51: =_xlfn.XLOOKUP($A51,Inputs!$A:$A,Inputs!J:J,,0) -> 1385.2 | K51: =_xlfn.XLOOKUP($A51,Inputs!$A:$A,Inputs!K:K,,0) -> 2097.8 | L51: =_xlfn.XLOOKUP($A51,Inputs!$A:$A,Inputs!L:L,,0) -> 1960.2 | M51: =_xlfn.XLOOKUP($A51,Inputs!$A:$A,Inputs!M:M,,0) -> 2029.6
A52: Short-Term Debt | B52: =_xlfn.XLOOKUP($A52,Inputs!$A:$A,Inputs!B:B,,0) -> 119.21 | C52: =_xlfn.XLOOKUP($A52,Inputs!$A:$A,Inputs!C:C,,0) -> 49.08 | D52: =_xlfn.XLOOKUP($A52,Inputs!$A:$A,Inputs!D:D,,0) -> 107.72 | E52: =_xlfn.XLOOKUP($A52,Inputs!$A:$A,Inputs!E:E,,0) -> 57.91 | F52: =_xlfn.XLOOKUP($A52,Inputs!$A:$A,Inputs!F:F,,0) -> 62.44 | G52: =_xlfn.XLOOKUP($A52,Inputs!$A:$A,Inputs!G:G,,0) -> 57.87 | H52: =_xlfn.XLOOKUP($A52,Inputs!$A:$A,Inputs!H:H,,0) -> 52.83 | I52: =_xlfn.XLOOKUP($A52,Inputs!$A:$A,Inputs!I:I,,0) -> 17.96 | J52: =_xlfn.XLOOKUP($A52,Inputs!$A:$A,Inputs!J:J,,0) -> 51.3 | K52: =_xlfn.XLOOKUP($A52,Inputs!$A:$A,Inputs!K:K,,0) -> 207.5 | L52: =_xlfn.XLOOKUP($A52,Inputs!$A:$A,Inputs!L:L,,0) -> 29.2 | M52: =_xlfn.XLOOKUP($A52,Inputs!$A:$A,Inputs!M:M,,0) -> 29.9
A53: Short-Term Leases | B53: =_xlfn.XLOOKUP($A53,Inputs!$A:$A,Inputs!B:B,,0) -> 74.1 | C53: =_xlfn.XLOOKUP($A53,Inputs!$A:$A,Inputs!C:C,,0) -> 28.6 | D53: =_xlfn.XLOOKUP($A53,Inputs!$A:$A,Inputs!D:D,,0) -> 651.7 | E53: =_xlfn.XLOOKUP($A53,Inputs!$A:$A,Inputs!E:E,,0) -> 10.9 | F53: =_xlfn.XLOOKUP($A53,Inputs!$A:$A,Inputs!F:F,,0) -> 29.3 | G53: =_xlfn.XLOOKUP($A53,Inputs!$A:$A,Inputs!G:G,,0) -> 0 | H53: =_xlfn.XLOOKUP($A53,Inputs!$A:$A,Inputs!H:H,,0) -> 500 | I53: =_xlfn.XLOOKUP($A53,Inputs!$A:$A,Inputs!I:I,,0) -> 600 | J53: =_xlfn.XLOOKUP($A53,Inputs!$A:$A,Inputs!J:J,,0) -> 0 | K53: =_xlfn.XLOOKUP($A53,Inputs!$A:$A,Inputs!K:K,,0) -> 16.3 | L53: =_xlfn.XLOOKUP($A53,Inputs!$A:$A,Inputs!L:L,,0) -> 3.3 | M53: =_xlfn.XLOOKUP($A53,Inputs!$A:$A,Inputs!M:M,,0) -> 250
A54: Other current liabilities | B54: =_xlfn.XLOOKUP($A54,Inputs!$A:$A,Inputs!B:B,,0) -> 2380.91 | C54: =_xlfn.XLOOKUP($A54,Inputs!$A:$A,Inputs!C:C,,0) -> 2602.54 | D54: =_xlfn.XLOOKUP($A54,Inputs!$A:$A,Inputs!D:D,,0) -> 2423.95 | E54: =_xlfn.XLOOKUP($A54,Inputs!$A:$A,Inputs!E:E,,0) -> 1126.89 | F54: =_xlfn.XLOOKUP($A54,Inputs!$A:$A,Inputs!F:F,,0) -> 1170.33 | G54: =_xlfn.XLOOKUP($A54,Inputs!$A:$A,Inputs!G:G,,0) -> 1320.24 | H54: =_xlfn.XLOOKUP($A54,Inputs!$A:$A,Inputs!H:H,,0) -> 1090.58 | I54: =_xlfn.XLOOKUP($A54,Inputs!$A:$A,Inputs!I:I,,0) -> 933.9 | J54: =_xlfn.XLOOKUP($A54,Inputs!$A:$A,Inputs!J:J,,0) -> 767.4 | K54: =_xlfn.XLOOKUP($A54,Inputs!$A:$A,Inputs!K:K,,0) -> 880.1 | L54: =_xlfn.XLOOKUP($A54,Inputs!$A:$A,Inputs!L:L,,0) -> 810.6 | M54: =_xlfn.XLOOKUP($A54,Inputs!$A:$A,Inputs!M:M,,0) -> 703
A55: Accounts payable | B55: =Inputs!B43 -> 2020.29 | C55: =Inputs!C43 -> 1649.52 | D55: =Inputs!D43 -> 1974.04 | E55: =Inputs!E43 -> 1432.16 | F55: =Inputs!F43 -> 1201.7 | G55: =Inputs!G43 -> 1428.19 | H55: =Inputs!H43 -> 1181.35 | I55: =Inputs!I43 -> 838.11 | J55: =Inputs!J43 -> 566.5
A56: Accrued expenses | B56: 1054.517 | C56: 948.348 | D56: 964.805 | E56: 664.183 | F56: 659.524 | G56: 709.397
A57: Non-current Liabilities | B57: =_xlfn.XLOOKUP($A57,Inputs!$A:$A,Inputs!B:B,,0) -> 8622.24 | C57: =_xlfn.XLOOKUP($A57,Inputs!$A:$A,Inputs!C:C,,0) -> 8579.56 | D57: =_xlfn.XLOOKUP($A57,Inputs!$A:$A,Inputs!D:D,,0) -> 6061.87 | E57: =_xlfn.XLOOKUP($A57,Inputs!$A:$A,Inputs!E:E,,0) -> 6265.67 | F57: =_xlfn.XLOOKUP($A57,Inputs!$A:$A,Inputs!F:F,,0) -> 5089.72 | G57: =_xlfn.XLOOKUP($A57,Inputs!$A:$A,Inputs!G:G,,0) -> 4912.32 | H57: =_xlfn.XLOOKUP($A57,Inputs!$A:$A,Inputs!H:H,,0) -> 3931.71 | I57: =_xlfn.XLOOKUP($A57,Inputs!$A:$A,Inputs!I:I,,0) -> 4578.84 | J57: =_xlfn.XLOOKUP($A57,Inputs!$A:$A,Inputs!J:J,,0) -> 5091.9 | K57: =_xlfn.XLOOKUP($A57,Inputs!$A:$A,Inputs!K:K,,0) -> 5443 | L57: =_xlfn.XLOOKUP($A57,Inputs!$A:$A,Inputs!L:L,,0) -> 5332.8 | M57: =_xlfn.XLOOKUP($A57,Inputs!$A:$A,Inputs!M:M,,0) -> 4237.1
A58: Long-Term Debt and fin leases | B58: 6648.873 | C58: 6613.687 | D58: 4961.42 | E58: 5271.789 | F58: 4291.301 | G58: 4233.276 | H58: =_xlfn.XLOOKUP($A58,Inputs!$A:$A,Inputs!H:H,,0) -> #N/A | I58: =_xlfn.XLOOKUP($A58,Inputs!$A:$A,Inputs!I:I,,0) -> #N/A | J58: =_xlfn.XLOOKUP($A58,Inputs!$A:$A,Inputs!J:J,,0) -> #N/A | K58: =_xlfn.XLOOKUP($A58,Inputs!$A:$A,Inputs!K:K,,0) -> #N/A | L58: =_xlfn.XLOOKUP($A58,Inputs!$A:$A,Inputs!L:L,,0) -> #N/A | M58: =_xlfn.XLOOKUP($A58,Inputs!$A:$A,Inputs!M:M,,0) -> #N/A
A59: Long-Term Leases | H59: =_xlfn.XLOOKUP($A59,Inputs!$A:$A,Inputs!H:H,,0) -> #N/A | I59: =_xlfn.XLOOKUP($A59,Inputs!$A:$A,Inputs!I:I,,0) -> #N/A | J59: =_xlfn.XLOOKUP($A59,Inputs!$A:$A,Inputs!J:J,,0) -> #N/A | K59: =_xlfn.XLOOKUP($A59,Inputs!$A:$A,Inputs!K:K,,0) -> #N/A | L59: =_xlfn.XLOOKUP($A59,Inputs!$A:$A,Inputs!L:L,,0) -> #N/A | M59: =_xlfn.XLOOKUP($A59,Inputs!$A:$A,Inputs!M:M,,0) -> #N/A
A60: Other non-current liabilities | B60: =_xlfn.XLOOKUP($A60,Inputs!$A:$A,Inputs!B:B,,0) -> 1973.37 | C60: =_xlfn.XLOOKUP($A60,Inputs!$A:$A,Inputs!C:C,,0) -> 1965.87 | D60: =_xlfn.XLOOKUP($A60,Inputs!$A:$A,Inputs!D:D,,0) -> 1100.46 | E60: =_xlfn.XLOOKUP($A60,Inputs!$A:$A,Inputs!E:E,,0) -> 993.88 | F60: =_xlfn.XLOOKUP($A60,Inputs!$A:$A,Inputs!F:F,,0) -> 798.42 | G60: =_xlfn.XLOOKUP($A60,Inputs!$A:$A,Inputs!G:G,,0) -> 679.04 | H60: =_xlfn.XLOOKUP($A60,Inputs!$A:$A,Inputs!H:H,,0) -> 689.47 | I60: =_xlfn.XLOOKUP($A60,Inputs!$A:$A,Inputs!I:I,,0) -> 839.7 | J60: =_xlfn.XLOOKUP($A60,Inputs!$A:$A,Inputs!J:J,,0) -> 754.8 | K60: =_xlfn.XLOOKUP($A60,Inputs!$A:$A,Inputs!K:K,,0) -> 1082.4 | L60: =_xlfn.XLOOKUP($A60,Inputs!$A:$A,Inputs!L:L,,0) -> 955.9 | M60: =_xlfn.XLOOKUP($A60,Inputs!$A:$A,Inputs!M:M,,0) -> 856.9
A61: Total Liabilities | B61: =_xlfn.XLOOKUP($A61,Inputs!$A:$A,Inputs!B:B,,0) -> 13216.75 | C61: =_xlfn.XLOOKUP($A61,Inputs!$A:$A,Inputs!C:C,,0) -> 12909.3 | D61: =_xlfn.XLOOKUP($A61,Inputs!$A:$A,Inputs!D:D,,0) -> 11219.28 | E61: =_xlfn.XLOOKUP($A61,Inputs!$A:$A,Inputs!E:E,,0) -> 8893.53 | F61: =_xlfn.XLOOKUP($A61,Inputs!$A:$A,Inputs!F:F,,0) -> 7553.49 | G61: =_xlfn.XLOOKUP($A61,Inputs!$A:$A,Inputs!G:G,,0) -> 7718.62 | H61: =_xlfn.XLOOKUP($A61,Inputs!$A:$A,Inputs!H:H,,0) -> 6756.47 | I61: =_xlfn.XLOOKUP($A61,Inputs!$A:$A,Inputs!I:I,,0) -> 6968.81 | J61: =_xlfn.XLOOKUP($A61,Inputs!$A:$A,Inputs!J:J,,0) -> 6477.1 | K61: =_xlfn.XLOOKUP($A61,Inputs!$A:$A,Inputs!K:K,,0) -> 7540.8 | L61: =_xlfn.XLOOKUP($A61,Inputs!$A:$A,Inputs!L:L,,0) -> 7293 | M61: =_xlfn.XLOOKUP($A61,Inputs!$A:$A,Inputs!M:M,,0) -> 6266.7
A63: Total Debt | B63: =B52+B58+B53+B59 -> 6842.183 | C63: =C52+C58+C53+C59 -> 6691.367 | D63: =D52+D58+D53+D59 -> 5720.84 | E63: =E52+E58+E53+E59 -> 5340.599 | F63: =F52+F58+F53+F59 -> 4383.041 | G63: =G52+G58+G53+G59 -> 4291.146 | H63: =H52+H58+H53+H59 -> #N/A | I63: =I52+I58+I53+I59 -> #N/A | ... M63: =M52+M58+M53+M59 -> #N/A
A64: Debt/Assets | B64: =IFERROR(B63/B46,"-") -> 0.19360742 | C64: =IFERROR(C63/C46,"-") -> 0.20602007 | D64: =IFERROR(D63/D46,"-") -> 0.22153963 | E64: =IFERROR(E63/E46,"-") -> 0.2653661 | F64: =IFERROR(F63/F46,"-") -> 0.23892683 | G64: =IFERROR(G63/G46,"-") -> 0.23945325 | H64: =IFERROR(H63/H46,"-") -> - | I64: =IFERROR(I63/I46,"-") -> - | ... M64: =IFERROR(M63/M46,"-") -> -
A65: Net Debt | B65: =B63-B41 -> 458.883 | C65: =C63-C41 -> 2410.467 | D65: =D63-D41 -> 3355.94 | E65: =E63-E41 -> 2700.899 | F65: =F63-F41 -> 2848.441 | G65: =G63-G41 -> 2892.246 | H65: =H63-H41 -> #N/A | I65: =I63-I41 -> #N/A | ... M65: =M63-M41 -> #N/A
A67: Minority Interest | B67: =_xlfn.XLOOKUP($A67,Inputs!$A:$A,Inputs!B:B,,0) -> 1183.1 | C67: =_xlfn.XLOOKUP($A67,Inputs!$A:$A,Inputs!C:C,,0) -> 1155.2 | D67: =_xlfn.XLOOKUP($A67,Inputs!$A:$A,Inputs!D:D,,0) -> 587.4 | E67: =_xlfn.XLOOKUP($A67,Inputs!$A:$A,Inputs!E:E,,0) -> 443.2 | F67: =_xlfn.XLOOKUP($A67,Inputs!$A:$A,Inputs!F:F,,0) -> 433.3 | G67: =_xlfn.XLOOKUP($A67,Inputs!$A:$A,Inputs!G:G,,0) -> 409.9 | H67: =_xlfn.XLOOKUP($A67,Inputs!$A:$A,Inputs!H:H,,0) -> 345.8 | I67: =_xlfn.XLOOKUP($A67,Inputs!$A:$A,Inputs!I:I,,0) -> 374.8 | J67: =_xlfn.XLOOKUP($A67,Inputs!$A:$A,Inputs!J:J,,0) -> 372.1 | K67: =_xlfn.XLOOKUP($A67,Inputs!$A:$A,Inputs!K:K,,0) -> 302.7 | L67: =_xlfn.XLOOKUP($A67,Inputs!$A:$A,Inputs!L:L,,0) -> 264.5 | M67: =_xlfn.XLOOKUP($A67,Inputs!$A:$A,Inputs!M:M,,0) -> 243.8
A69: Shareholder's Equity | B69: =_xlfn.XLOOKUP($A69,Inputs!$A:$A,Inputs!B:B,,0) -> 20940.65 | C69: =_xlfn.XLOOKUP($A69,Inputs!$A:$A,Inputs!C:C,,0) -> 18414.7 | D69: =_xlfn.XLOOKUP($A69,Inputs!$A:$A,Inputs!D:D,,0) -> 14016.42 | E69: =_xlfn.XLOOKUP($A69,Inputs!$A:$A,Inputs!E:E,,0) -> 10788.67 | F69: =_xlfn.XLOOKUP($A69,Inputs!$A:$A,Inputs!F:F,,0) -> 10357.91 | G69: =_xlfn.XLOOKUP($A69,Inputs!$A:$A,Inputs!G:G,,0) -> 9792.08 | H69: =_xlfn.XLOOKUP($A69,Inputs!$A:$A,Inputs!H:H,,0) -> 8739.03 | I69: =_xlfn.XLOOKUP($A69,Inputs!$A:$A,Inputs!I:I,,0) -> 7879.89 | J69: =_xlfn.XLOOKUP($A69,Inputs!$A:$A,Inputs!J:J,,0) -> 7477.8 | K69: =_xlfn.XLOOKUP($A69,Inputs!$A:$A,Inputs!K:K,,0) -> 7772.4 | L69: =_xlfn.XLOOKUP($A69,Inputs!$A:$A,Inputs!L:L,,0) -> 7645.8 | M69: =_xlfn.XLOOKUP($A69,Inputs!$A:$A,Inputs!M:M,,0) -> 7641.6
A71: Cash Flow
A72: Operating CF | B72: =_xlfn.XLOOKUP($A72,Inputs!$A:$A,Inputs!B:B,,0) -> 7111.9 | C72: =_xlfn.XLOOKUP($A72,Inputs!$A:$A,Inputs!C:C,,0) -> 10072 | D72: =_xlfn.XLOOKUP($A72,Inputs!$A:$A,Inputs!D:D,,0) -> 6230.8 | E72: =_xlfn.XLOOKUP($A72,Inputs!$A:$A,Inputs!E:E,,0) -> 2696.9 | F72: =_xlfn.XLOOKUP($A72,Inputs!$A:$A,Inputs!F:F,,0) -> 2809.4 | G72: =_xlfn.XLOOKUP($A72,Inputs!$A:$A,Inputs!G:G,,0) -> 2394 | H72: =_xlfn.XLOOKUP($A72,Inputs!$A:$A,Inputs!H:H,,0) -> 1055.3 | I72: =_xlfn.XLOOKUP($A72,Inputs!$A:$A,Inputs!I:I,,0) -> 1750 | J72: =_xlfn.XLOOKUP($A72,Inputs!$A:$A,Inputs!J:J,,0) -> 2168.8 | K72: =_xlfn.XLOOKUP($A72,Inputs!$A:$A,Inputs!K:K,,0) -> 1342.9 | L72: =_xlfn.XLOOKUP($A72,Inputs!$A:$A,Inputs!L:L,,0) -> 1078 | M72: =_xlfn.XLOOKUP($A72,Inputs!$A:$A,Inputs!M:M,,0) -> 1200.4
A73: Investing CF | B73: =_xlfn.XLOOKUP($A73,Inputs!$A:$A,Inputs!B:B,,0) -> -2496.43 | C73: =_xlfn.XLOOKUP($A73,Inputs!$A:$A,Inputs!C:C,,0) -> -5702.71 | D73: =_xlfn.XLOOKUP($A73,Inputs!$A:$A,Inputs!D:D,,0) -> -2873.85 | E73: =_xlfn.XLOOKUP($A73,Inputs!$A:$A,Inputs!E:E,,0) -> -1764.29 | F73: =_xlfn.XLOOKUP($A73,Inputs!$A:$A,Inputs!F:F,,0) -> -1794.19 | G73: =_xlfn.XLOOKUP($A73,Inputs!$A:$A,Inputs!G:G,,0) -> -1030.07 | H73: =_xlfn.XLOOKUP($A73,Inputs!$A:$A,Inputs!H:H,,0) -> -918.89 | I73: =_xlfn.XLOOKUP($A73,Inputs!$A:$A,Inputs!I:I,,0) -> -1025.12 | J73: =_xlfn.XLOOKUP($A73,Inputs!$A:$A,Inputs!J:J,,0) -> -441.7 | K73: =_xlfn.XLOOKUP($A73,Inputs!$A:$A,Inputs!K:K,,0) -> -1438.1 | L73: =_xlfn.XLOOKUP($A73,Inputs!$A:$A,Inputs!L:L,,0) -> -840 | M73: =_xlfn.XLOOKUP($A73,Inputs!$A:$A,Inputs!M:M,,0) -> -204
A74: Net Capex | B74: =_xlfn.XLOOKUP($A74,Inputs!$A:$A,Inputs!B:B,,0) -> -2199.3 | C74: =_xlfn.XLOOKUP($A74,Inputs!$A:$A,Inputs!C:C,,0) -> -1915.6 | D74: =_xlfn.XLOOKUP($A74,Inputs!$A:$A,Inputs!D:D,,0) -> -1602.6 | E74: =_xlfn.XLOOKUP($A74,Inputs!$A:$A,Inputs!E:E,,0) -> -1502.3 | F74: =_xlfn.XLOOKUP($A74,Inputs!$A:$A,Inputs!F:F,,0) -> -1435.7 | G74: =_xlfn.XLOOKUP($A74,Inputs!$A:$A,Inputs!G:G,,0) -> -950.9 | H74: =_xlfn.XLOOKUP($A74,Inputs!$A:$A,Inputs!H:H,,0) -> -423.2 | I74: =_xlfn.XLOOKUP($A74,Inputs!$A:$A,Inputs!I:I,,0) -> -586.3 | J74: =_xlfn.XLOOKUP($A74,Inputs!$A:$A,Inputs!J:J,,0) -> -344.7 | K74: =_xlfn.XLOOKUP($A74,Inputs!$A:$A,Inputs!K:K,,0) -> -631.4 | L74: =_xlfn.XLOOKUP($A74,Inputs!$A:$A,Inputs!L:L,,0) -> -1162.9 | M74: =_xlfn.XLOOKUP($A74,Inputs!$A:$A,Inputs!M:M,,0) -> -896.6
A75: Investments & Acquisitions | B75: =_xlfn.XLOOKUP($A75,Inputs!$A:$A,Inputs!B:B,,0) -> -225.044 | C75: =_xlfn.XLOOKUP($A75,Inputs!$A:$A,Inputs!C:C,,0) -> -3876.916 | D75: =_xlfn.XLOOKUP($A75,Inputs!$A:$A,Inputs!D:D,,0) -> -1271.426 | E75: =_xlfn.XLOOKUP($A75,Inputs!$A:$A,Inputs!E:E,,0) -> -184.41 | F75: =_xlfn.XLOOKUP($A75,Inputs!$A:$A,Inputs!F:F,,0) -> -383.146 | G75: =_xlfn.XLOOKUP($A75,Inputs!$A:$A,Inputs!G:G,,0) -> 16.937 | H75: =_xlfn.XLOOKUP($A75,Inputs!$A:$A,Inputs!H:H,,0) -> -503.04 | I75: =_xlfn.XLOOKUP($A75,Inputs!$A:$A,Inputs!I:I,,0) -> -587.97 | J75: =_xlfn.XLOOKUP($A75,Inputs!$A:$A,Inputs!J:J,,0) -> -99.9 | K75: =_xlfn.XLOOKUP($A75,Inputs!$A:$A,Inputs!K:K,,0) -> -938.9 | L75: =_xlfn.XLOOKUP($A75,Inputs!$A:$A,Inputs!L:L,,0) -> 137.1 | M75: =_xlfn.XLOOKUP($A75,Inputs!$A:$A,Inputs!M:M,,0) -> 675.7
A76: Financing CF | B76: =_xlfn.XLOOKUP($A76,Inputs!$A:$A,Inputs!B:B,,0) -> -2592.81 | C76: =_xlfn.XLOOKUP($A76,Inputs!$A:$A,Inputs!C:C,,0) -> -2510.86 | D76: =_xlfn.XLOOKUP($A76,Inputs!$A:$A,Inputs!D:D,,0) -> -3602.88 | E76: =_xlfn.XLOOKUP($A76,Inputs!$A:$A,Inputs!E:E,,0) -> 285.85 | F76: =_xlfn.XLOOKUP($A76,Inputs!$A:$A,Inputs!F:F,,0) -> -880.41 | G76: =_xlfn.XLOOKUP($A76,Inputs!$A:$A,Inputs!G:G,,0) -> -908.18 | H76: =_xlfn.XLOOKUP($A76,Inputs!$A:$A,Inputs!H:H,,0) -> -1242.31 | I76: =_xlfn.XLOOKUP($A76,Inputs!$A:$A,Inputs!I:I,,0) -> -626.43 | J76: =_xlfn.XLOOKUP($A76,Inputs!$A:$A,Inputs!J:J,,0) -> -801.5 | K76: =_xlfn.XLOOKUP($A76,Inputs!$A:$A,Inputs!K:K,,0) -> -359 | L76: =_xlfn.XLOOKUP($A76,Inputs!$A:$A,Inputs!L:L,,0) -> 196 | M76: =_xlfn.XLOOKUP($A76,Inputs!$A:$A,Inputs!M:M,,0) -> -1146.9
A77: Dividends | B77: =_xlfn.XLOOKUP($A77,Inputs!$A:$A,Inputs!B:B,,0) -> -514.53 | C77: =_xlfn.XLOOKUP($A77,Inputs!$A:$A,Inputs!C:C,,0) -> -533.59 | D77: =_xlfn.XLOOKUP($A77,Inputs!$A:$A,Inputs!D:D,,0) -> -483.47 | E77: =_xlfn.XLOOKUP($A77,Inputs!$A:$A,Inputs!E:E,,0) -> -491.66 | F77: =_xlfn.XLOOKUP($A77,Inputs!$A:$A,Inputs!F:F,,0) -> -492.06 | G77: =_xlfn.XLOOKUP($A77,Inputs!$A:$A,Inputs!G:G,,0) -> -485.38 | H77: =_xlfn.XLOOKUP($A77,Inputs!$A:$A,Inputs!H:H,,0) -> -485.32 | I77: =_xlfn.XLOOKUP($A77,Inputs!$A:$A,Inputs!I:I,,0) -> -481.08 | J77: =_xlfn.XLOOKUP($A77,Inputs!$A:$A,Inputs!J:J,,0) -> -479.4 | K77: =_xlfn.XLOOKUP($A77,Inputs!$A:$A,Inputs!K:K,,0) -> -475.1 | L77: =_xlfn.XLOOKUP($A77,Inputs!$A:$A,Inputs!L:L,,0) -> -471 | M77: =_xlfn.XLOOKUP($A77,Inputs!$A:$A,Inputs!M:M,,0) -> -466.4
A78: Share buyback | B78: =_xlfn.XLOOKUP($A78,Inputs!$A:$A,Inputs!B:B,,0) -> -1591.52 | C78: =_xlfn.XLOOKUP($A78,Inputs!$A:$A,Inputs!C:C,,0) -> -2803.8 | D78: =_xlfn.XLOOKUP($A78,Inputs!$A:$A,Inputs!D:D,,0) -> -3204.09 | E78: =_xlfn.XLOOKUP($A78,Inputs!$A:$A,Inputs!E:E,,0) -> -46.76 | F78: =_xlfn.XLOOKUP($A78,Inputs!$A:$A,Inputs!F:F,,0) -> -307.44 | G78: -127 | H78: =_xlfn.XLOOKUP($A78,Inputs!$A:$A,Inputs!H:H,,0) -> -97.64 | I78: =_xlfn.XLOOKUP($A78,Inputs!$A:$A,Inputs!I:I,,0) -> 0.89 | J78: =_xlfn.XLOOKUP($A78,Inputs!$A:$A,Inputs!J:J,,0) -> -66.5 | K78: =_xlfn.XLOOKUP($A78,Inputs!$A:$A,Inputs!K:K,,0) -> 0 | L78: =_xlfn.XLOOKUP($A78,Inputs!$A:$A,Inputs!L:L,,0) -> 0 | M78: =_xlfn.XLOOKUP($A78,Inputs!$A:$A,Inputs!M:M,,0) -> 0
A79: FX | B79: =_xlfn.XLOOKUP($A79,Inputs!$A:$A,Inputs!B:B,,0) -> 0 | C79: =_xlfn.XLOOKUP($A79,Inputs!$A:$A,Inputs!C:C,,0) -> 0 | D79: =_xlfn.XLOOKUP($A79,Inputs!$A:$A,Inputs!D:D,,0) -> 0 | E79: =_xlfn.XLOOKUP($A79,Inputs!$A:$A,Inputs!E:E,,0) -> 0 | F79: =_xlfn.XLOOKUP($A79,Inputs!$A:$A,Inputs!F:F,,0) -> 0 | G79: =_xlfn.XLOOKUP($A79,Inputs!$A:$A,Inputs!G:G,,0) -> 0 | H79: =_xlfn.XLOOKUP($A79,Inputs!$A:$A,Inputs!H:H,,0) -> 0 | I79: =_xlfn.XLOOKUP($A79,Inputs!$A:$A,Inputs!I:I,,0) -> 0 | J79: =_xlfn.XLOOKUP($A79,Inputs!$A:$A,Inputs!J:J,,0) -> 0 | K79: =_xlfn.XLOOKUP($A79,Inputs!$A:$A,Inputs!K:K,,0) -> 0 | L79: =_xlfn.XLOOKUP($A79,Inputs!$A:$A,Inputs!L:L,,0) -> 0 | M79: =_xlfn.XLOOKUP($A79,Inputs!$A:$A,Inputs!M:M,,0) -> 0
A80: Changes in cash | B80: =_xlfn.XLOOKUP($A80,Inputs!$A:$A,Inputs!B:B,,0) -> 2022.66 | C80: =_xlfn.XLOOKUP($A80,Inputs!$A:$A,Inputs!C:C,,0) -> 1858.43 | D80: =_xlfn.XLOOKUP($A80,Inputs!$A:$A,Inputs!D:D,,0) -> -245.93 | E80: =_xlfn.XLOOKUP($A80,Inputs!$A:$A,Inputs!E:E,,0) -> 1218.46 | F80: =_xlfn.XLOOKUP($A80,Inputs!$A:$A,Inputs!F:F,,0) -> 134.8 | G80: =_xlfn.XLOOKUP($A80,Inputs!$A:$A,Inputs!G:G,,0) -> 455.75 | H80: =_xlfn.XLOOKUP($A80,Inputs!$A:$A,Inputs!H:H,,0) -> -1105.9 | I80: =_xlfn.XLOOKUP($A80,Inputs!$A:$A,Inputs!I:I,,0) -> 98.45 | J80: =_xlfn.XLOOKUP($A80,Inputs!$A:$A,Inputs!J:J,,0) -> 925.6 | K80: =_xlfn.XLOOKUP($A80,Inputs!$A:$A,Inputs!K:K,,0) -> -454.2 | L80: =_xlfn.XLOOKUP($A80,Inputs!$A:$A,Inputs!L:L,,0) -> 434 | M80: =_xlfn.XLOOKUP($A80,Inputs!$A:$A,Inputs!M:M,,0) -> -150.5
A82: Other Data
A83: Number of employees | B83: =_xlfn.XLOOKUP($A83,Inputs!$A:$A,Inputs!B:B,,0) -> #N/A | C83: =_xlfn.XLOOKUP($A83,Inputs!$A:$A,Inputs!C:C,,0) -> #N/A | D83: =_xlfn.XLOOKUP($A83,Inputs!$A:$A,Inputs!D:D,,0) -> #N/A | E83: =_xlfn.XLOOKUP($A83,Inputs!$A:$A,Inputs!E:E,,0) -> #N/A | F83: =_xlfn.XLOOKUP($A83,Inputs!$A:$A,Inputs!F:F,,0) -> #N/A | G83: =_xlfn.XLOOKUP($A83,Inputs!$A:$A,Inputs!G:G,,0) -> #N/A | H83: =_xlfn.XLOOKUP($A83,Inputs!$A:$A,Inputs!H:H,,0) -> #N/A | I83: =_xlfn.XLOOKUP($A83,Inputs!$A:$A,Inputs!I:I,,0) -> #N/A | J83: =_xlfn.XLOOKUP($A83,Inputs!$A:$A,Inputs!J:J,,0) -> #N/A | K83: =_xlfn.XLOOKUP($A83,Inputs!$A:$A,Inputs!K:K,,0) -> #N/A | L83: =_xlfn.XLOOKUP($A83,Inputs!$A:$A,Inputs!L:L,,0) -> #N/A | M83: =_xlfn.XLOOKUP($A83,Inputs!$A:$A,Inputs!M:M,,0) -> #N/A
A84: Shares Outstanding | B84: =_xlfn.XLOOKUP($A84,Inputs!$A:$A,Inputs!B:B,,0) -> #N/A | C84: =_xlfn.XLOOKUP($A84,Inputs!$A:$A,Inputs!C:C,,0) -> #N/A | D84: =_xlfn.XLOOKUP($A84,Inputs!$A:$A,Inputs!D:D,,0) -> #N/A | E84: =_xlfn.XLOOKUP($A84,Inputs!$A:$A,Inputs!E:E,,0) -> #N/A | F84: =_xlfn.XLOOKUP($A84,Inputs!$A:$A,Inputs!F:F,,0) -> #N/A | G84: =_xlfn.XLOOKUP($A84,Inputs!$A:$A,Inputs!G:G,,0) -> #N/A | H84: =_xlfn.XLOOKUP($A84,Inputs!$A:$A,Inputs!H:H,,0) -> #N/A | I84: =_xlfn.XLOOKUP($A84,Inputs!$A:$A,Inputs!I:I,,0) -> #N/A | J84: =_xlfn.XLOOKUP($A84,Inputs!$A:$A,Inputs!J:J,,0) -> #N/A | K84: =_xlfn.XLOOKUP($A84,Inputs!$A:$A,Inputs!K:K,,0) -> #N/A | L84: =_xlfn.XLOOKUP($A84,Inputs!$A:$A,Inputs!L:L,,0) -> #N/A | M84: =_xlfn.XLOOKUP($A84,Inputs!$A:$A,Inputs!M:M,,0) -> #N/A
A85: Float | B85: =_xlfn.XLOOKUP($A85,Inputs!$A:$A,Inputs!B:B,,0) -> 0.99169967 | C85: =_xlfn.XLOOKUP($A85,Inputs!$A:$A,Inputs!C:C,,0) -> Yahoo finance | D85: =_xlfn.XLOOKUP($A85,Inputs!$A:$A,Inputs!D:D,,0) -> 0 | E85: =_xlfn.XLOOKUP($A85,Inputs!$A:$A,Inputs!E:E,,0) -> 0 | F85: =_xlfn.XLOOKUP($A85,Inputs!$A:$A,Inputs!F:F,,0) -> 0 | G85: =_xlfn.XLOOKUP($A85,Inputs!$A:$A,Inputs!G:G,,0) -> 0 | H85: =_xlfn.XLOOKUP($A85,Inputs!$A:$A,Inputs!H:H,,0) -> 0 | I85: =_xlfn.XLOOKUP($A85,Inputs!$A:$A,Inputs!I:I,,0) -> 0 | J85: =_xlfn.XLOOKUP($A85,Inputs!$A:$A,Inputs!J:J,,0) -> 0 | K85: =_xlfn.XLOOKUP($A85,Inputs!$A:$A,Inputs!K:K,,0) -> 0 | L85: =_xlfn.XLOOKUP($A85,Inputs!$A:$A,Inputs!L:L,,0) -> 0 | M85: =_xlfn.XLOOKUP($A85,Inputs!$A:$A,Inputs!M:M,,0) -> 0
A86: Insiders Own | B86: =_xlfn.XLOOKUP($A86,Inputs!$A:$A,Inputs!B:B,,0) -> 0.0051 | C86: =_xlfn.XLOOKUP($A86,Inputs!$A:$A,Inputs!C:C,,0) -> Yahoo finance | D86: =_xlfn.XLOOKUP($A86,Inputs!$A:$A,Inputs!D:D,,0) -> 0 | E86: =_xlfn.XLOOKUP($A86,Inputs!$A:$A,Inputs!E:E,,0) -> 0 | F86: =_xlfn.XLOOKUP($A86,Inputs!$A:$A,Inputs!F:F,,0) -> 0 | G86: =_xlfn.XLOOKUP($A86,Inputs!$A:$A,Inputs!G:G,,0) -> 0 | H86: =_xlfn.XLOOKUP($A86,Inputs!$A:$A,Inputs!H:H,,0) -> 0 | I86: =_xlfn.XLOOKUP($A86,Inputs!$A:$A,Inputs!I:I,,0) -> 0 | J86: =_xlfn.XLOOKUP($A86,Inputs!$A:$A,Inputs!J:J,,0) -> 0 | K86: =_xlfn.XLOOKUP($A86,Inputs!$A:$A,Inputs!K:K,,0) -> 0 | L86: =_xlfn.XLOOKUP($A86,Inputs!$A:$A,Inputs!L:L,,0) -> 0 | M86: =_xlfn.XLOOKUP($A86,Inputs!$A:$A,Inputs!M:M,,0) -> 0
A87: Fitch/ S&P Rating | B87: =_xlfn.XLOOKUP($A87,Inputs!$A:$A,Inputs!B:B,,0) -> A- | C87: =_xlfn.XLOOKUP($A87,Inputs!$A:$A,Inputs!C:C,,0) -> 10-K | D87: =_xlfn.XLOOKUP($A87,Inputs!$A:$A,Inputs!D:D,,0) -> 0 | E87: =_xlfn.XLOOKUP($A87,Inputs!$A:$A,Inputs!E:E,,0) -> 0 | F87: =_xlfn.XLOOKUP($A87,Inputs!$A:$A,Inputs!F:F,,0) -> 0 | G87: =_xlfn.XLOOKUP($A87,Inputs!$A:$A,Inputs!G:G,,0) -> 0 | H87: =_xlfn.XLOOKUP($A87,Inputs!$A:$A,Inputs!H:H,,0) -> 0 | I87: =_xlfn.XLOOKUP($A87,Inputs!$A:$A,Inputs!I:I,,0) -> 0 | J87: =_xlfn.XLOOKUP($A87,Inputs!$A:$A,Inputs!J:J,,0) -> 0 | K87: =_xlfn.XLOOKUP($A87,Inputs!$A:$A,Inputs!K:K,,0) -> 0 | L87: =_xlfn.XLOOKUP($A87,Inputs!$A:$A,Inputs!L:L,,0) -> 0 | M87: =_xlfn.XLOOKUP($A87,Inputs!$A:$A,Inputs!M:M,,0) -> 0
A88: Dividend Yield | B88: =_xlfn.XLOOKUP($A88,Inputs!$A:$A,Inputs!B:B,,0) -> #N/A | C88: =_xlfn.XLOOKUP($A88,Inputs!$A:$A,Inputs!C:C,,0) -> #N/A | D88: =_xlfn.XLOOKUP($A88,Inputs!$A:$A,Inputs!D:D,,0) -> #N/A | E88: =_xlfn.XLOOKUP($A88,Inputs!$A:$A,Inputs!E:E,,0) -> #N/A | F88: =_xlfn.XLOOKUP($A88,Inputs!$A:$A,Inputs!F:F,,0) -> #N/A | G88: =_xlfn.XLOOKUP($A88,Inputs!$A:$A,Inputs!G:G,,0) -> #N/A | H88: =_xlfn.XLOOKUP($A88,Inputs!$A:$A,Inputs!H:H,,0) -> #N/A | I88: =_xlfn.XLOOKUP($A88,Inputs!$A:$A,Inputs!I:I,,0) -> #N/A | J88: =_xlfn.XLOOKUP($A88,Inputs!$A:$A,Inputs!J:J,,0) -> #N/A | K88: =_xlfn.XLOOKUP($A88,Inputs!$A:$A,Inputs!K:K,,0) -> #N/A | L88: =_xlfn.XLOOKUP($A88,Inputs!$A:$A,Inputs!L:L,,0) -> #N/A | M88: =_xlfn.XLOOKUP($A88,Inputs!$A:$A,Inputs!M:M,,0) -> #N/A
A89: Daily Volume in Millions of USD | B89: =_xlfn.XLOOKUP($A89,Inputs!$A:$A,Inputs!B:B,,0) -> 1.94 | C89: =_xlfn.XLOOKUP($A89,Inputs!$A:$A,Inputs!C:C,,0) -> Yahoo Finance | D89: =_xlfn.XLOOKUP($A89,Inputs!$A:$A,Inputs!D:D,,0) -> 0 | E89: =_xlfn.XLOOKUP($A89,Inputs!$A:$A,Inputs!E:E,,0) -> 0 | F89: =_xlfn.XLOOKUP($A89,Inputs!$A:$A,Inputs!F:F,,0) -> 0 | G89: =_xlfn.XLOOKUP($A89,Inputs!$A:$A,Inputs!G:G,,0) -> 0 | H89: =_xlfn.XLOOKUP($A89,Inputs!$A:$A,Inputs!H:H,,0) -> 0 | I89: =_xlfn.XLOOKUP($A89,Inputs!$A:$A,Inputs!I:I,,0) -> 0 | J89: =_xlfn.XLOOKUP($A89,Inputs!$A:$A,Inputs!J:J,,0) -> 0 | K89: =_xlfn.XLOOKUP($A89,Inputs!$A:$A,Inputs!K:K,,0) -> 0 | L89: =_xlfn.XLOOKUP($A89,Inputs!$A:$A,Inputs!L:L,,0) -> 0 | M89: =_xlfn.XLOOKUP($A89,Inputs!$A:$A,Inputs!M:M,,0) -> 0
B91: 2020 | C91: 2021 | D91: 2022
A92: Short % of Float | B92: 0 | C92: 0 | D92: 0
A93: EPS | B93: 0 | C93: 0 | D93: 0
A95: Corporate Bonds 3, 5 Y 10 | B95: Average Price | C95: Moody's | D95: YTM | E95: DIVISA
B96: =VLOOKUP($A96,Inputs!$A$5:$M$100,MATCH(B$4,Inputs!$B$5:$M$5,0)+1,FALSE) -> #N/A | C96: =VLOOKUP($A96,Inputs!$A$5:$M$100,MATCH(C$4,Inputs!$B$5:$M$5,0)+1,FALSE) -> #N/A | D96: =VLOOKUP($A96,Inputs!$A$5:$M$100,MATCH(D$4,Inputs!$B$5:$M$5,0)+1,FALSE) -> #N/A | E96: =VLOOKUP($A96,Inputs!$A$5:$M$100,MATCH(E$4,Inputs!$B$5:$M$5,0)+1,FALSE) -> #N/A

Sheet Sector Impact
E2: Sector | F2: Sub-Industry | H2: Low | K2: Sector | L2: Environment | Q2: Social
E3: Communication Services | F3: Interactive Home Entertainment | H3: Medium | L3: CO2 | M3: Water | N3: Energy | O3: Waste | P3: Degradation | Q3: Turnover | R3: Compensation | S3: Reputation | T3: Discrimination | U3: Security | V3: Damage | W3: Pension | X3: Supply | Y3: Community | Z3: Public | AA3: Litigation
E4: Communication Services | F4: Interactive Media & Services | H4: High | K4: Communication Services | L4: Low | M4: Low | N4: Medium | O4: Low | P4: Low | Q4: Medium | R4: Medium | S4: Low | T4: Low | U4: High | V4: Low | W4: Low | X4: Low | Y4: Low | Z4: Low | AA4: Medium
B5: Environmental | E5: Communication Services | F5: Integrated Telecommunication Services | H5: Very High | K5: Consumer Discretionary | L5: Low | M5: Low | N5: Medium | O5: Medium | P5: Low | Q5: Medium | R5: Medium | S5: Low | T5: Low | U5: Medium | V5: Medium | W5: Medium | X5: High | Y5: Low | Z5: High | AA5: Low
B6: Direct CO2 emissions | E6: Communication Services | F6: Cable & Satellite | K6: Consumer Staples | L6: High | M6: Very High | N6: High | O6: High | P6: High | Q6: Medium | R6: High | S6: High | T6: Low | U6: Medium | V6: Medium | W6: Low | X6: High | Y6: Low | Z6: Very High | AA6: Low
B7: Total Water Use | E7: Communication Services | F7: Broadcasting | K7: Energy | L7: Very High | M7: Very High | N7: Medium | O7: Very High | P7: High | Q7: High | R7: Medium | S7: Medium | T7: Medium | U7: Medium | V7: High | W7: Medium | X7: Medium | Y7: High | Z7: High | AA7: Low
K8: Renewable Energy | L8: Low | M8: Low | N8: Low | O8: Medium | P8: Medium | Q8: Low | R8: Medium | S8: Medium | T8: High | U8: Medium | V8: Low | W8: Low | X8: Medium | Y8: Medium | Z8: High | AA8: Low
B9: Total Energy Consumption | E9: Communication Services | F9: Movies & Entertainment | K9: Financials | L9: Low | M9: Low | N9: Low | O9: Low | P9: Low | Q9: Low | R9: Low | S9: Medium | T9: High | U9: Medium | V9: Low | W9: Low | X9: Low | Y9: Low | Z9: Medium | AA9: Low
K10: Forestry | L10: Low | M10: Medium | N10: Low | O10: Medium | P10: High | Q10: Low | R10: Low | S10: Low | T10: Low | U10: Low | V10: Low | W10: Low | X10: Low | Y10: Medium | Z10: Low | AA10: Low
B11: Waste Management | E11: Communication Services | F11: Advertising | K11: Health Care | L11: Low | M11: Medium | N11: Low | O11: Low | P11: Low | Q11: Low | R11: Low | S11: Medium | T11: Low | U11: High | V11: Low | W11: Low | X11: Low | Y11: Low | Z11: Low | AA11: Low
B12: Land Degradation/Deforestation/Biodiversity loss/Animal sufering/... | E12: Communication Services | F12: Alternative Carriers | K12: Industrials | L12: Very High | M12: Very High | N12: Very High | O12: High | P12: High | Q12: Low | R12: Medium | S12: High | T12: Very High | U12: Medium | V12: Very High | W12: Medium | X12: Very High | Y12: Very High | Z12: Very High | AA12: High
B13: Social | E13: Communication Services | F13: Publishing | K13: Information Technology | L13: Medium | M13: Low | N13: High | O13: Low | P13: Low | Q13: Low | R13: Low | S13: Low | T13: Low | U13: High | V13: Low | W13: Low | X13: Low | Y13: Low | Z13: Medium | AA13: Very High
B14: Employee turnover | E14: Communication Services | F14: Wireless Telecommunication Services | K14: Materials | L14: Very High | M14: Very High | N14: Very High | O14: Very High | P14: High | Q14: High | R14: High | S14: Medium | T14: High | U14: Low | V14: Very High | W14: Medium | X14: Medium | Y14: Very High | Z14: High | AA14: Medium
B15: Salaries and compensation | E15: Consumer Discretionary | F15: Automotive Retail | K15: Real Estate | L15: Low | M15: Low | N15: Medium | O15: Low | P15: Low | Q15: Medium | R15: Low | S15: Low | T15: Low | U15: High | V15: Low | W15: Medium | X15: Low | Y15: Medium | Z15: Low | AA15: Low
B16: Reputational issues | E16: Consumer Discretionary | F16: Internet & Direct Marketing Retail | K16: Utilities | L16: Very High | M16: High | N16: High | O16: Medium | P16: High | Q16: Low | R16: Medium | S16: Medium | T16: Low | U16: Medium | V16: Medium | W16: Medium | X16: Medium | Y16: Low | Z16: Medium | AA16: Low
B17: Discrimination issues | E17: Consumer Discretionary | F17: Auto Parts & Equipment
B18: Job security | E18: Consumer Discretionary | F18: Specialty Stores
B19: Health injuries | E19: Consumer Discretionary | F19: Computer & Electronics Retail | L19: Communication Services | M19: Consumer Discretionary | N19: Consumer Staples | O19: Energy | P19: Financials | Q19: Health Care | R19: Industrials | S19: Information Technology | T19: Materials | U19: Real Estate | V19: Utilities
B20: PXP? | E20: Consumer Discretionary | F20: Hotels, Resorts & Cruise Lines | L20: Interactive Home Entertainment | M20: Automotive Retail | N20: Tobacco | O20: Oil & Gas Exploration & Production | P20: Life & Health Insurance | Q20: Health Care Equipment | R20: Industrial Conglomerates | S20: IT Consulting & Other Services | T20: Industrial Gases | U20: Office REITs | V20: Independent Power Producers & Energy Traders
B21: Supply chain | E21: Consumer Discretionary | F21: Restaurants | L21: Interactive Media & Services | M21: Internet & Direct Marketing Retail | N21: Agricultural Products | O21: Oil & Gas Equipment & Services | P21: Property & Casualty Insurance | Q21: Pharmaceuticals | R21: Airlines | S21: Application Software | T21: Specialty Chemicals | U21: Specialized REITs | V21: Electric Utilities
B22: Community involvement | E22: Consumer Discretionary | F22: Homebuilding | L22: Integrated Telecommunication Services | M22: Auto Parts & Equipment | N22: Distillers & Vintners | O22: Integrated Oil & Gas | P22: Consumer Finance | Q22: Health Care Supplies | R22: Building Products | S22: Semiconductors | T22: Paper Packaging | U22: Residential REITs | V22: Multi-Utilities
B23: Public Sector | E23: Consumer Discretionary | F23: General Merchandise Stores | L23: Cable & Satellite | M23: Specialty Stores | N23: Packaged Foods & Meats | O23: Oil & Gas Refining & Marketing | P23: Asset Management & Custody Banks | Q23: Health Care Distributors | R23: Electrical Components & Equipment | S23: Internet Services & Infrastructure | T23: Metal & Glass Containers | U23: Real Estate Services | V23: Water Utilities
B24: Litigation | E24: Consumer Discretionary | F24: Automobile Manufacturers | L24: Broadcasting | M24: Computer & Electronics Retail | N24: Household Products | O24: Oil & Gas Storage & Transportation | P24: Insurance Brokers | Q24: Biotechnology | R24: Aerospace & Defense | S24: Electronic Components | T24: Fertilizers & Agricultural Chemicals | U24: Industrial REITs | V24: Gas Utilities
E25: Consumer Discretionary | F25: Apparel Retail | L25: Movies & Entertainment | M25: Hotels, Resorts & Cruise Lines | N25: Soft Drinks | P25: Multi-line Insurance | Q25: Managed Health Care | R25: Air Freight & Logistics | S25: Technology Hardware, Storage & Peripherals | T25: Commodity Chemicals | U25: Retail REITs
E26: Consumer Discretionary | F26: Consumer Electronics | L26: Advertising | M26: Restaurants | N26: Hypermarkets & Super Centers | P26: Diversified Banks | Q26: Life Sciences Tools & Services | R26: Construction Machinery & Heavy Trucks | S26: Semiconductor Equipment | T26: Diversified Chemicals | U26: Health Care REITs
E27: Consumer Discretionary | F27: Apparel, Accessories & Luxury Goods | L27: Alternative Carriers | M27: Homebuilding | N27: Personal Products | P27: Multi-Sector Holdings | Q27: Health Care Technology | R27: Diversified Support Services | S27: Communications Equipment | T27: Copper | U27: Hotel & Resort REITs
E28: Consumer Discretionary | F28: Leisure Products | L28: Publishing | M28: General Merchandise Stores | N28: Food Retail | P28: Financial Exchanges & Data | Q28: Health Care Services | R28: Railroads | S28: Data Processing & Outsourced Services | T28: Construction Materials
E29: Consumer Discretionary | F29: Home Improvement Retail | L29: Wireless Telecommunication Services | M29: Automobile Manufacturers | N29: Brewers | P29: Investment Banking & Brokerage | Q29: Health Care Facilities | R29: Industrial Machinery | S29: Technology Distributors | T29: Gold
E30: Consumer Discretionary | F30: Casinos & Gaming | M30: Apparel Retail | N30: Food Distributors | P30: Regional Banks | R30: Agricultural & Farm Machinery | S30: Electronic Equipment & Instruments | T30: Steel
E31: Consumer Discretionary | F31: Home Furnishings | M31: Consumer Electronics | N31: Drug Retail | P31: Reinsurance | R31: Research & Consulting Services | S31: Systems Software
E32: Consumer Discretionary | F32: Distributors | M32: Apparel, Accessories & Luxury Goods | P32: Thrifts & Mortgage Finance | R32: Construction & Engineering | S32: Electronic Manufacturing Services
E33: Consumer Discretionary | F33: Housewares & Specialties | M33: Leisure Products | R33: Trucking
E34: Consumer Discretionary | F34: Household Appliances | M34: Home Improvement Retail | R34: Environmental & Facilities Services
E35: Consumer Staples | F35: Tobacco | M35: Casinos & Gaming | R35: Human Resource & Employment Services
E36: Consumer Staples | F36: Agricultural Products | M36: Home Furnishings | R36: Trading Companies & Distributors
E37: Consumer Staples | F37: Distillers & Vintners | M37: Distributors
E38: Consumer Staples | F38: Packaged Foods & Meats | M38: Housewares & Specialties
E39: Consumer Staples | F39: Household Products | M39: Household Appliances
E40: Consumer Staples | F40: Soft Drinks
E41: Consumer Staples | F41: Hypermarkets & Super Centers
E42: Consumer Staples | F42: Personal Products
E43: Consumer Staples | F43: Food Retail
E44: Consumer Staples | F44: Brewers
E45: Consumer Staples | F45: Food Distributors
E46: Consumer Staples | F46: Drug Retail
E47: Energy | F47: Oil & Gas Exploration & Production
E48: Energy | F48: Oil & Gas Equipment & Services
E49: Energy | F49: Integrated Oil & Gas
E50: Energy | F50: Oil & Gas Refining & Marketing
E51: Energy | F51: Oil & Gas Storage & Transportation
... E128: Utilities | F128: Gas Utilities

Sheet Inputs
B1: 26899.107 | C1: 29009.187
G2: Figures in Millions of USD
B3: =B6-B1 -> 7814.893 | C3: =C6-C1 -> 12502.813 | D3: 12502.813 | G3: Company | H3: #VALUE!
D4: Report in millions
A5: RESULTS | B5: 2023 | C5: =B5-1 -> 2022 | D5: =C5-1 -> 2021 | E5: =D5-1 -> 2020 | F5: =E5-1 -> 2019 | G5: =F5-1 -> 2018 | H5: =G5-1 -> 2017 | I5: =H5-1 -> 2016 | J5: =I5-1 -> 2015 | ... M5: =L5-1 -> 2012 | O5: Note: IS includes all accounts | Q5: Hoja | R5: Nombre campo Bloomberg | T5: Cambio de signo | Z5: 2016 | AA5: 2015 | AB5: 2014 | AC5: 2013 | AD5: 2012 | AE5: 2011 | AF5: 2010 | AG5: 2009
A6: Net Sales | B6: 34714 | C6: 41512 | D6: 36484 | E6: 20140 | F6: 22588.858 | G6: 25067.279 | H6: 20252.393 | I6: 16208.122 | J6: 16439.276 | K6: 21105.141 | L6: 19052.046 | M6: 19429 | Q6: Ingreso | R6: Ingreso | Z6: 38537 | AA6: 47011 | AB6: 55184 | AC6: 55656 | AD6: 65875 | AE6: 60138 | AF6: 42588 | AG6: 32396
A7: Gross Profit | B7: 7814.4 | C7: 12503.28 | D7: 11025.41 | E7: 2227.95 | F7: 2679.09 | G7: 4295 | H7: 2570 | I7: 2026 | J7: 1114 | K7: 1849 | L7: 1411 | M7: 1513.54 | Q7: Ingreso | R7: + Coste de bienes y servicios | Z7: =Z6-28044 -> 10493 | AA7: =AA6-33546 -> 13465 | AB7: =AB6-40718 -> 14466 | AC7: =AC6-40727 -> 14929 | AD7: =+AD6-47055 -> 18820 | AE7: =+AE6-43578 -> 16560 | AF7: =+AF6-30367 -> 12221 | AG7: =+AG6-23886 -> 8510
A8: Operating Income | B8: 6230.4 | C8: 10506.28 | D8: 9318.41 | E8: 1612.95 | F8: 1968.09 | G8: 3434 | H8: 1882 | I8: 1429 | J8: 655 | K8: 1328 | L8: 943 | M8: 1076.54 | Q8: Ingreso | R8: + Ventas, generales y admin | Z8: =Z7-4383 -> 6110 | AA8: =AA7-4951 -> 8514 | AB8: =AB7-6529 -> 7937 | AC8: =AC7-5547 -> 9382 | AD8: =AD7-5919-2466-797-580-485 -> 8573 | AE8: =+AE7-5203-2297-826-1081 -> 7153 | AF8: =+AF7-4248-1905-914-1191 -> 3963 | AG8: =+AG7-3645-1421-1045-1822 -> 577
A9: Other Operating Expenses (Revenues) | B9: =-12.783 -> -12.783 | C9: =-10.714+101.756 -> 91.042 | D9: =-103.068+62.161 -> -40.907 | E9: =10.533+613.64 -> 624.173 | F9: =-3.311+66.916 -> 63.605 | G9: =-40.24+110 -> 69.76 | H9: =-41.661 -> -41.661 | I9: -38.757 | J9: =-5.329+244.833 -> 239.504 | K9: =-13.505+25.393 -> 11.888 | L9: =-9.297+14 -> 4.703 | M9: =13.323+47.563 -> 60.886 | N9: Income Statement | O9: investment income+other income expense+income loss+minority interest+non controlling interest+share onf net profit+gain8losses) on equity investments+share of result from associates nd joint ventures+non operating profit+ | Q9: Ingreso | R9: + Investigación y desarrollo | S9: + Coste de financiación de beneficio | T9: + Otro gasto operativo | U9: - Beneficio (pérdida) de filiales | V9: - Minoritarios | Z9: =1853+596+595+1904+6+8 -> 4962 | AA9: =2119+587+2023+11 -> 4740 | AB9: =2380+624+1619-8+16 -> 4631 | AC9: =2046+727+981+6+14 -> 3774 | AD9: =-14+41 -> 27 | AE9: 53 | AF9: =58+24 -> 82 | AG9: =12-68 -> -56
A10: Net Financial Cost | B10: 29.632 | C10: -170.216 | D10: -158.854 | E10: -153.198 | F10: -121.425 | G10: -135.535 | H10: -173.58 | I10: -169.244 | J10: -173.531 | K10: -169.256 | L10: -146.895 | M10: -162.375 | N10: Income Statement | O10: interest expense+financial income and expenses+other financial expense-income+interest and other net+ | Q10: Ingreso | R10: - Ingreso (pérdida) no operacional | Z10: =505+518 -> 1023 | AA10: =507-161 -> 346 | AB10: =484-322 -> 162 | AC10: =465+35 -> 500 | AD10: =467-130 -> 337 | AE10: =396+32 -> 428 | AF10: =343-130 -> 213 | AG10: =389-381 -> 8
A11: Taxes | B11: -1359.966 | C11: -2165.204 | D11: -2078.488 | E11: 0.49 | F11: -411.897 | G11: -748.307 | H11: -369.386 | I11: -398.243 | J11: -48.836 | K11: -368.724 | L11: -205.594 | M11: -259.814 | N11: Income Statement | O11: Taxes | Q11: Ingreso | R11: - Gasto de impuesto a la renta (Beneficio) | Z11: 192 | AA11: 916 | AB11: 692 | AC11: 1319 | AD11: =2528 -> 2528 | AE11: =1720 -> 1720 | AF11: =968 -> 968 | AG11: =-270 -> -270
A12: Net Income | B12: =(B8-B9)+B10+B11-388 -> 4524.849 | C12: =(C8-C9)+C10+C11-472 -> 7607.818 | D12: =(D8-D9)+D10+D11-295 -> 6826.975 | E12: =(E8-E9)+E10+E11-115 -> 721.069 | F12: =(F8-F9)+F10+F11-100 -> 1271.163 | G12: =(G8-G9)+G10+G11-120 -> 2360.398 | H12: =(H8-H9)+H10+H11-62 -> 1318.695 | I12: =(I8-I9)+I10+I11-104 -> 796.27 | J12: =(J8-J9)+J10+J11-112 -> 81.129 | K12: =(K8-K9)+K10+K11-99 -> 679.132 | L12: =(L8-L9)+L10+L11-98 -> 487.808 | M12: =(M8-M9)+M10+M11-89 -> 504.465 | N12: Income Statement | O12: Net Income | Q12: Flujo de caja | R12: + Ingreso neto | Z12: -67 | AA12: 2512 | AB12: 2452 | AC12: 3789 | AD12: 5681 | AE12: =4928+24 -> 4952 | AF12: 2700 | AG12: 895
B13: 4524.807 | C13: 7607.337 | D13: 6827.457 | E13: 721.47 | F13: 1271.148 | G13: 2360.767 | H13: 1318.688 | I13: 796.271 | J13: 80.724 | K13: 679.337 | L13: 488.025 | M13: 504.621 | Z13: =Z8-Z10-Z9-Z11 -> -67 | AA13: =AA8-AA10-AA9-AA11 -> 2512 | AB13: =AB8-AB10-AB9-AB11 -> 2452 | AC13: =AC8-AC10-AC9-AC11 -> 3789 | AD13: =AD8-AD10-AD9-AD11 -> 5681 | AE13: =AE8-AE10-AE9-AE11 -> 4952 | AF13: =AF8-AF10-AF9-AF11 -> 2700 | AG13: =AG8-AG10-AG9-AG11 -> 895
A14: FINANCIAL POSITION | B14: =B12-B13 -> 0.042 | C14: =C12-C13 -> 0.481 | D14: =D12-D13 -> -0.482 | E14: =E12-E13 -> -0.401 | F14: =F12-F13 -> 0.015 | G14: =G12-G13 -> -0.369 | H14: =H12-H13 -> 0.007 | I14: =I12-I13 -> -0.001 | ... M14: =M12-M13 -> -0.156 | Z14: =Z12-Z13 -> 0 | AA14: =AA12-AA13 -> 0 | AB14: =AB12-AB13 -> 0 | AC14: =AC12-AC13 -> 0 | AD14: =AD12-AD13 -> 0 | AE14: =AE12-AE13 -> 0 | AF14: =AF12-AF13 -> 0 | AG14: =AG12-AG13 -> 0
A16: Weighted Average Shares (Basic NI) | B16: 249.8 | C16: 0 | D16: 0 | E16: 0 | F16: 0 | G16: 305 | H16: 315.9 | I16: 320 | J16: 319.6 | K16: 320.6 | L16: 319.8 | M16: 318.2
A17: Weighted Average Shares (Diluted NI) | B17: 250.4 | C17: 0 | D17: 0 | E17: 0 | F17: 305.5 | G17: 316.7 | H17: 320.8 | I17: 319.8 | J17: 320.7 | K17: 320.1 | L17: 319.3 | M17: 318.2
A19: Net gains (losses) from ForEx | B19: 21.041 | C19: -55.348 | D19: -4.041 | E19: 17.306 | F19: 7.873 | G19: -47.133 | H19: 68.657 | I19: 25.495 | J19: -205.4 | K19: -141.5 | L19: -53.6 | M19: 58.6
A20: Total Comprehensive Income | B20: 4500.246 | C20: 7585.102 | D20: 6831.04 | E20: 905.575 | F20: 1270.425 | G20: 2311.315 | H20: 1381.85 | I20: 829.79 | J20: -124.9 | K20: 524.5 | L20: 440.3 | M20: 599.8
A22: Changes Net Working Capital | B22: =B23-C23 -> -672.99 | C22: =C23-D23 -> 803.79 | D22: =D23-E23 -> 1056.15 | E22: =E23-F23 -> -6.9 | F22: =F23-G23 -> -203.07 | G22: =G23-H23 -> 1380.51 | H22: =H23-I23 -> 980.14 | I22: =I23-J23 -> -459.28 | ... M22: =M23-N23 -> 2578.9 | N22: cash flows | O22: NWC | Q22: Flujo de caja
A23: Net Working Capital | B23: =B27-B42-B28 -> 5408.05 | C23: =C27-C42-C28 -> 6081.04 | D23: =D27-D42-D28 -> 5277.25 | E23: =E27-E42-E28 -> 4221.1 | F23: =F27-F42-F28 -> 4228 | G23: =G27-G42-G28 -> 4431.07 | H23: =H27-H42-H28 -> 3050.56 | I23: =I27-I42-I28 -> 2070.42 | ... M23: =M27-M42-M28 -> 2578.9
A24: 2625 | B24: 2625 | C24: 2625 | D24: 2625 | E24: 2625 | F24: 2625 | G24: 2625 | H24: 2625 | I24: 2625 | J24: 2625 | K24: 2625 | L24: 2625 | M24: 2625 | N24: 2625 | Q24: Flujo de caja | R24: + Dividendos pagados | T24: Cambiar signo | Z24: 1799 | AA24: 1757 | AB24: 1620 | AC24: 1111 | AD24: 1617 | AE24: 1159 | AF24: 1084 | AG24: 1029
A25: BALANCE SHEET | B25: 2625 | C25: 2625 | D25: 2625 | E25: 2625 | F25: 2625 | G25: 2625 | H25: 2625 | I25: 2625 | J25: 2625 | K25: 2625 | L25: 2625 | M25: 2625 | N25: 2625 | Q25: Flujo de caja | R25: + Aumento en capital | S25: + Baja en capital | T25: Cambiar signo y hacer suma | Z25: 23 | AA25: =-33+2025 -> 1992 | AB25: 3817 | AC25: 1776 | AD25: -244 | AE25: -312 | AF25: -449 | AG25: -110
A26: ASSETS | N26: 1922 | O26: 2625
A27: Current | B27: 16385.86 | C27: 14691.68 | D27: 12799.56 | E27: 9488.66 | F27: 8226.37 | G27: 8636.27 | H27: 6824.42 | I27: 6506.39 | J27: 5854.4 | K27: 6441.9 | L27: 6410 | M27: 5661.4
A28: Cash & Eq. | B28: 6383.3 | C28: 4280.9 | D28: 2364.9 | E28: 2639.7 | F28: 1534.6 | G28: 1398.9 | H28: 949.1 | I28: 2046 | J28: 1939.5 | K28: 1024.1 | L28: 1483.3 | M28: 1052.9
A29: Accounts Receivable | B29: 2953.31 | C29: 3591.03 | D29: 3853.97 | E29: 2298.85 | F29: 2160.1 | G29: 2505.57 | H29: 2028.55 | I29: 1631.68 | J29: 1383.8 | K29: 2068.3 | L29: 1881 | M29: 1707.3 | N29: Balance Sheet | O29: Accounts Receivable
A30: Inventory | B30: 5577.76 | C30: 5453.53 | D30: 6011.18 | E30: 3569.09 | F30: 3842.1 | G30: 4553.5 | H30: 3461.69 | I30: 2479.96 | J30: 2245.5 | K30: 2745 | L30: 2605.6 | M30: 2323.6 | N30: Balance Sheet | O30: Inventory | Q30: Balance | R30: + Efectivo, equivalentes y STI | Z30: 7168 | AA30: 6460 | AB30: 7341 | AC30: 6081 | AD30: 5490 | AE30: 3057 | AF30: 3592 | AG30: 4867
A31: Other Current Assets | B31: =B27-SUM(B28:B30) -> 1471.49 | C31: =C27-SUM(C28:C30) -> 1366.22 | D31: =D27-SUM(D28:D30) -> 569.51 | E31: =E27-SUM(E28:E30) -> 981.02 | F31: =F27-SUM(F28:F30) -> 689.57 | G31: =G27-SUM(G28:G30) -> 178.3 | H31: =H27-SUM(H28:H30) -> 385.08 | I31: =I27-SUM(I28:I30) -> 348.75 | ... M31: =M27-SUM(M28:M30) -> 577.6 | N31: Balance Sheet | O31: Inventory | Q31: Balance | R31: + Cuentas y notas por cobrar | S31: + Activos derivados y de cobertura | T31: + Inversiones y cuentas por cobrar a LP | Z31: =5981+8522+1029+13556 -> 29088 | AA31: =6695+8991+1170+13651 -> 30507 | AB31: =7737+9027+1364+14644 -> 32772 | AC31: 33499 | AD31: 33911 | AE31: 31031 | AF31: 28849 | AG31: 27162
A32: Non-current | B32: =B38-B27 -> 18954.64 | C32: =C38-C27 -> 17787.52 | D32: =D38-D27 -> 13023.54 | E32: =E38-E27 -> 10636.74 | F32: =F38-F27 -> 10118.33 | G32: =G38-G27 -> 9284.33 | H32: =H38-H27 -> 9016.88 | I32: =I38-I27 -> 8717.11 | ... M32: =M38-M27 -> 8490.7
A33: Property, Plant and Equipment | B33: 11049.77 | C33: 9616.92 | D33: 8114.82 | E33: 6899.11 | F33: 6178.56 | G33: 5334.75 | H33: 5093.15 | I33: 5078.65 | J33: 4891.2 | K33: 5287.6 | L33: 4917 | M33: 4283.1 | Q33: Balance | R33: + Inventarios | Z33: 8614 | AA33: 9700 | AB33: 12205 | AC33: 12625 | AD33: 15547 | AE33: 14544 | AF33: 9587 | AG33: 6360
A34: Operating leases | B34: 0 | C34: 0 | D34: 0 | E34: 0 | F34: 0 | G34: 0 | H34: 0 | I34: 0 | J34: 0 | K34: 0 | L34: 0 | M34: 0
A35: Equity Method Investments | B35: 0 | C35: 0 | D35: 0 | E35: 0 | F35: 0 | G35: 0 | H35: 0 | I35: 0 | J35: 0 | K35: 0 | L35: 0 | M35: 0
A36: Other Non-Current Assets | B36: =B32-SUM(B33:B35) -> 7904.87 | C36: =C32-SUM(C33:C35) -> 8170.6 | D36: =D32-SUM(D33:D35) -> 4908.72 | E36: =E32-SUM(E33:E35) -> 3737.63 | F36: =F32-SUM(F33:F35) -> 3939.77 | G36: =G32-SUM(G33:G35) -> 3949.58 | H36: =H32-SUM(H33:H35) -> 3923.73 | I36: =I32-SUM(I33:I35) -> 3638.46 | ... M36: =M32-SUM(M33:M35) -> 4207.6 | N36: Balance Sheet | O36: Property, Plant and Equipment
A37: Other Assets | B37: =B31+B36 -> 9376.36 | C37: =C31+C36 -> 9536.82 | D37: =D31+D36 -> 5478.23 | E37: =E31+E36 -> 4718.65 | F37: =F31+F36 -> 4629.34 | G37: =G31+G36 -> 4127.88 | H37: =H31+H36 -> 4308.81 | I37: =I31+I36 -> 3987.21 | ... M37: =M31+M36 -> 4785.2 | N37: Balance Sheet
A38: Total Assets | B38: 35340.5 | C38: 32479.2 | D38: 25823.1 | E38: 20125.4 | F38: 18344.7 | G38: 17920.6 | H38: 15841.3 | I38: 15223.5 | J38: 14327 | K38: 15615.9 | L38: 15203.3 | M38: 14152.1 | N38: Balance Sheet | O38: Total Assets | Q38: Balance | R38: + Propiedad, planta y equipo; neto | Z38: 15322 | AA38: 16090 | AB38: =16577 -> 16577 | AC38: 17075 | AD38: 16461 | AE38: 14395 | AF38: 12539 | AG38: 12386
N39: Balance Sheet | Z39: =Z40-SUM(Z30:Z38) -> 14512 | AA39: =AA40-SUM(AA30:AA38) -> 15585 | AB39: =AB40-SUM(AB30:AB38) -> 15786 | AC39: =AC40-SUM(AC30:AC38) -> 15616 | AD39: =AD40-SUM(AD30:AD38) -> 17947 | AE39: =AE40-SUM(AE30:AE38) -> 18419 | AF39: =AF40-SUM(AF30:AF38) -> 9453 | AG39: =AG40-SUM(AG30:AG38) -> 9263
N40: Balance Sheet | Q40: Balance | R40: Activos totales | Z40: 74704 | AA40: 78342 | AB40: 84681 | AC40: 84896 | AD40: 89356 | AE40: 81446 | AF40: 64020 | AG40: 60038
A41: LIABILITIES | N41: Balance Sheet
A42: Current Liabilities | B42: 4594.51 | C42: 4329.74 | D42: 5157.41 | E42: 2627.86 | F42: 2463.77 | G42: 2806.3 | H42: 2824.76 | I42: 2389.97 | J42: 1385.2 | K42: 2097.8 | L42: 1960.2 | M42: 2029.6 | N42: Balance Sheet | O42: Current Liabilities
A43: Payables | B43: 2020.29 | C43: 1649.52 | D43: 1974.04 | E43: 1432.16 | F43: 1201.7 | G43: 1428.19 | H43: 1181.35 | I43: 838.11 | J43: 566.5 | K43: 993.9 | L43: 1117.1 | M43: 1046.7
A44: Short-Term Debt | B44: 119.21 | C44: 49.08 | D44: 107.72 | E44: 57.91 | F44: 62.44 | G44: 57.87 | H44: 52.83 | I44: 17.96 | J44: 51.3 | K44: 207.5 | L44: 29.2 | M44: 29.9 | N44: Balance Sheet | O44: Short term Debt | Q44: Balance | R44: Pasivos totales corrientes | Z44: 26132 | AA44: 26242 | AB44: 27877 | AC44: 27297 | AD44: 29415 | AE44: =93+3895+8161+3386+2410+2691+298+1967+558+5102 -> 28561 | AF44: =204+3852+5856+2880+1670+1831+281+1521+495+3430 -> 22020 | AG44: =433+3650+2993+3351+797+1217+262+888+302+5399 -> 19292
A45: Short-Term Leases | B45: 74.1 | C45: 28.6 | D45: 651.7 | E45: 10.9 | F45: 29.3 | G45: 0 | H45: 500 | I45: 600 | J45: 0 | K45: 16.3 | L45: 3.3 | M45: 250
A46: Other current liabilities | B46: =B42-SUM(B43:B45) -> 2380.91 | C46: =C42-SUM(C43:C45) -> 2602.54 | D46: =D42-SUM(D43:D45) -> 2423.95 | E46: =E42-SUM(E43:E45) -> 1126.89 | F46: =F42-SUM(F43:F45) -> 1170.33 | G46: =G42-SUM(G43:G45) -> 1320.24 | H46: =H42-SUM(H43:H45) -> 1090.58 | I46: =I42-SUM(I43:I45) -> 933.9 | ... M46: =M42-SUM(M43:M45) -> 703 | N46: Balance Sheet | R46: + Préstamos CP | Z46: 7303 | AA46: 6967 | AB46: 4708 | AC46: 3679 | AD46: 5287 | AE46: 5660 | AF46: 3925 | AG46: 5701
A47: Non-current Liabilities | B47: =B50-B42 -> 8622.24 | C47: =C50-C42 -> 8579.56 | D47: =D50-D42 -> 6061.87 | E47: =E50-E42 -> 6265.67 | F47: =F50-F42 -> 5089.72 | G47: =G50-G42 -> 4912.32 | H47: =H50-H42 -> 3931.71 | I47: =I50-I42 -> 4578.84 | ... M47: =M50-M42 -> 4237.1 | N47: Balance Sheet | O47: Total non current liabilities
A48: Long-term debt and finance lease obligations | B48: 6648.87 | C48: 6613.69 | D48: 4961.41 | E48: 5271.79 | F48: 4291.3 | G48: 4233.28 | H48: 3242.24 | I48: 3739.14 | J48: 4337.1 | K48: 4360.6 | L48: 4376.9 | M48: 3380.2 | N48: Balance Sheet | O48: Long term debt | Z48: =Z44-Z46 -> 18829 | AA48: =AA44-AA46 -> 19275 | AB48: =AB44-AB46 -> 23169 | AC48: =AC44-AC46 -> 23618 | AD48: =AD44-AD46 -> 24128 | AE48: =AE44-AE46 -> 22901 | AF48: =AF44-AF46 -> 18095 | AG48: =AG44-AG46 -> 13591
A49: Other non-current liabilities | B49: =B47-SUM(B48:B48) -> 1973.37 | C49: =C47-SUM(C48:C48) -> 1965.87 | D49: =D47-SUM(D48:D48) -> 1100.46 | E49: =E47-SUM(E48:E48) -> 993.88 | F49: =F47-SUM(F48:F48) -> 798.42 | G49: =G47-SUM(G48:G48) -> 679.04 | H49: =H47-SUM(H48:H48) -> 689.47 | I49: =I47-SUM(I48:I48) -> 839.7 | ... M49: =M47-SUM(M48:M48) -> 856.9 | N49: Balance Sheet | O49: Other non current Liabilities | R49: + Préstamos a largo plazo | Z49: 22818 | AA49: 25169 | AB49: 27784 | AC49: 26719 | AD49: 27752 | AE49: 24944 | AF49: 20437 | AG49: 21847
A50: Total Liabilities | B50: 13216.75 | C50: 12909.3 | D50: 11219.28 | E50: 8893.53 | F50: 7553.49 | G50: 7718.62 | H50: 6756.47 | I50: 6968.81 | J50: 6477.1 | K50: 7540.8 | L50: 7293 | M50: 6266.7 | N50: Balance Sheet | O50: Total Liabilities
N51: Balance Sheet | Z51: =#REF!-Z49 -> #REF! | AA51: =#REF!-AA49 -> #REF! | AB51: =#REF!-AB49 -> #REF! | AC51: =#REF!-AC49 -> #REF! | AD51: =#REF!-AD49 -> #REF! | AE51: =#REF!-AE49 -> #REF! | AF51: =#REF!-AF49 -> #REF! | AG51: =#REF!-AG49 -> #REF!
N52: Balance Sheet | Z52: =+#REF!+Z44 -> #REF! | AA52: =+#REF!+AA44 -> #REF! | AB52: =+#REF!+AB44 -> #REF! | AC52: =AC44+#REF! -> #REF! | AD52: =#REF!+AD44 -> #REF! | AE52: =#REF!+AE44 -> #REF! | AF52: =#REF!+AF44 -> #REF! | AG52: =#REF!+AG44 -> #REF!
A53: Minority Interest | B53: 1183.1 | C53: 1155.2 | D53: 587.4 | E53: 443.2 | F53: 433.3 | G53: 409.9 | H53: 345.8 | I53: 374.8 | J53: 372.1 | K53: 302.7 | L53: 264.5 | M53: 243.8
N54: Balance Sheet
A55: Shareholder's Equity | B55: =B38-B50-B53 -> 20940.65 | C55: =C38-C50-C53 -> 18414.7 | D55: =D38-D50-D53 -> 14016.42 | E55: =E38-E50-E53 -> 10788.67 | F55: =F38-F50-F53 -> 10357.91 | G55: =G38-G50-G53 -> 9792.08 | H55: =H38-H50-H53 -> 8739.03 | I55: =I38-I50-I53 -> 7879.89 | ... M55: =M38-M50-M53 -> 7641.6 | N55: Balance Sheet | Q55: Balance | R55: + Participación minoritaria/no dominante
A57: CASH FLOW
A58: Operating CF | B58: 7111.9 | C58: 10072 | D58: 6230.8 | E58: 2696.9 | F58: 2809.4 | G58: 2394 | H58: 1055.3 | I58: 1750 | J58: 2168.8 | K58: 1342.9 | L58: 1078 | M58: 1200.4
A59: Net Income | B59: =B12 -> 4524.849 | C59: =C12 -> 7607.818 | D59: =D12 -> 6826.975 | E59: =E12 -> 721.069 | F59: =F12 -> 1271.163 | G59: =G12 -> 2360.398 | H59: =H12 -> 1318.695 | I59: =I12 -> 796.27 | ... M59: =M12 -> 504.465
A60: Depreciation & Amortization | B60: 1168.32 | C60: 1061.63 | D60: 864.56 | E60: 785.47 | F60: 734.65 | G60: 719.64 | H60: 727.06 | I60: 687.05 | J60: 944.9 | K60: 749.8 | L60: 624.2 | M60: 624.6
A61: Changes in assets and liabilities | B61: 858.41 | C61: 877.44 | D61: -1862.89 | E61: 203.99 | F61: 413.26 | G61: -983.16 | H61: -902.93 | I61: 32.73 | J61: 1538.9 | K61: -257.9 | L61: -272.3 | M61: -74.2
A62: Other Adjustments | B62: =B58-B59-B60-B61 -> 560.321 | C62: =C58-C59-C60-C61 -> 525.112 | D62: =D58-D59-D60-D61 -> 402.155 | E62: =E58-E59-E60-E61 -> 986.371 | F62: =F58-F59-F60-F61 -> 390.327 | G62: =G58-G59-G60-G61 -> 297.122 | H62: =H58-H59-H60-H61 -> -87.525 | I62: =I58-I59-I60-I61 -> 233.95 | ... M62: =M58-M59-M60-M61 -> 145.535
A63: Investing CF | B63: -2496.43 | C63: -5702.71 | D63: -2873.85 | E63: -1764.29 | F63: -1794.19 | G63: -1030.07 | H63: -918.89 | I63: -1025.12 | J63: -441.7 | K63: -1438.1 | L63: -840 | M63: -204
A64: Net Capex | B64: -2199.3 | C64: -1915.6 | D64: -1602.6 | E64: -1502.3 | F64: -1435.7 | G64: -950.9 | H64: -423.2 | I64: -586.3 | J64: -344.7 | K64: -631.4 | L64: -1162.9 | M64: -896.6
A65: Investments & Acquisitions | B65: -225.044 | C65: -3876.916 | D65: -1271.426 | E65: -184.41 | F65: -383.146 | G65: 16.937 | H65: -503.04 | I65: -587.97 | J65: -99.9 | K65: -938.9 | L65: 137.1 | M65: 675.7
A66: Other Inflows (Outflows) | B66: =B63-B64-B65 -> -72.086 | C66: =C63-C64-C65 -> 89.806 | D66: =D63-D64-D65 -> 0.176 | E66: =E63-E64-E65 -> -77.58 | F66: =F63-F64-F65 -> 24.656 | G66: =G63-G64-G65 -> -96.107 | H66: =H63-H64-H65 -> 7.35 | I66: =I63-I64-I65 -> 149.15 | ... M66: =M63-M64-M65 -> 16.9
A67: Financing CF | B67: -2592.81 | C67: -2510.86 | D67: -3602.88 | E67: 285.85 | F67: -880.41 | G67: -908.18 | H67: -1242.31 | I67: -626.43 | J67: -801.5 | K67: -359 | L67: 196 | M67: -1146.9
A68: Increase/Decrease in Borrowings | B68: -34.87 | C68: 922.29 | D68: 246.81 | E68: 1135.95 | F68: 4.57 | G68: 500.75 | H68: -565.13 | I68: -33.36 | J68: =-155.8-16.3 -> -172.1 | K68: =178.3-5.4 -> 172.9 | L68: =-0.7+999.1-250 -> 748.4 | M68: =-650+27.9 -> -622.1
A69: Lease Increases | B69: 0 | C69: 0 | D69: 0 | E69: 0 | F69: 0 | G69: 0 | H69: 0 | I69: 0 | J69: 0 | K69: 0 | L69: 0 | M69: 0
A70: Lease Payments | B70: 16.84 | C70: 16.008 | D70: 11.425 | E70: 9.541 | F70: 9.134 | G70: 0 | H70: 0 | I70: 0 | J70: 0 | K70: 0 | L70: 0 | M70: 0
A71: Dividends | B71: -514.53 | C71: -533.59 | D71: -483.47 | E71: -491.66 | F71: -492.06 | G71: -485.38 | H71: -485.32 | I71: -481.08 | J71: -479.4 | K71: -475.1 | L71: -471 | M71: -466.4 | N71: cash flows FINANCING | O71: Dividends paid
A72: Share buyback | B72: -1591.52 | C72: -2803.8 | D72: -3204.09 | E72: -46.76 | F72: -307.44 | G72: -852.02 | H72: -97.64 | I72: 0.89 | J72: -66.5 | K72: 0 | L72: 0 | M72: 0 | N72: cash flows FINANCING | O72: =+A72 -> Share buyback
A73: Other Inflows (Outflows) | B73: =B67-B68-B69-B70-B71-B72 -> -468.73 | C73: =C67-C68-C69-C70-C71-C72 -> -111.768 | D73: =D67-D68-D69-D70-D71-D72 -> -173.555 | E73: =E67-E68-E69-E70-E71-E72 -> -321.221 | F73: =F67-F68-F69-F70-F71-F72 -> -94.614 | G73: =G67-G68-G69-G70-G71-G72 -> -71.53 | H73: =H67-H68-H69-H70-H71-H72 -> -94.22 | I73: =I67-I68-I69-I70-I71-I72 -> -112.88 | ... M73: =M67-M68-M69-M70-M71-M72 -> -58.4
A74: FX
A75: Changes in cash | B75: =B58+B63+B67+B74 -> 2022.66 | C75: =C58+C63+C67+C74 -> 1858.43 | D75: =D58+D63+D67+D74 -> -245.93 | E75: =E58+E63+E67+E74 -> 1218.46 | F75: =F58+F63+F67+F74 -> 134.8 | G75: =G58+G63+G67+G74 -> 455.75 | H75: =H58+H63+H67+H74 -> -1105.9 | I75: =I58+I63+I67+I74 -> 98.45 | ... M75: =M58+M63+M67+M74 -> -150.5
O76: (Vitalis will later fill this info)
A77: Other Data | E77: Corporate Bonds 3, 5 Y 10 | H77: Average Price | J77: Moody's | K77: YTM | L77: DIVISA
A78: Number of employees | B78: 32000 | C78: 10-K | N78: bloomberg
A79: Shares Outstanding (Thousands) | B79: 237340 | C79: Yahoo finance | N79: bloomberg
A80: Float | B80: =235.37/237.34 -> 0.99169967 | C80: Yahoo finance | N80: bloomberg
A81: Insiders Own | B81: 0.0051 | C81: Yahoo finance | N81: bloomberg
A82: Fitch/ S&P Rating | B82: A- | C82: 10-K | N82: bloomberg
A83: Dividend Yield(Yahoo Finance) | B83: 0.0148 | C83: Yahoo finance | N83: bloomberg
A84: Daily Volume in Millions of USD | B84: 1.94 | C84: Yahoo Finance | N84: bloomberg
B85: =B5 -> 2023 | C85: =C5 -> 2022 | D85: =D5 -> 2021
A86: Short % of Float | B86: 0.0292 | E86: Yahoo Finance
A87: EPS | B87: 18 | C87: 28.79 | D87: 23.43 | E87: Yahoo Finance
B92: 2024E | C92: 2023 | D92: 2022 | E92: 2021 | F92: 2020 | G92: 2019 | H92: 2018 | I92: Average | J92: Standard deviation
A93: Sales | B93: 30426.75 | C93: 34714 | D93: 41512 | E93: 36484 | F93: 20140 | G93: 22588.858 | H93: 25067.279
A94: Acquisitions (net of cash acquired) | B94: -334.949 | C94: -70.824 | D94: -3553.191 | E94: -1426.424 | F94: -88.071 | G94: -83.106 | H94: -33.063
A95: % of revenues | B95: =B94/B93 -> -0.011008373 | C95: =C94/C93 -> -0.0020402143 | D95: =D94/D93 -> -0.08559431 | E95: =E94/E93 -> -0.039097248 | F95: =F94/F93 -> -0.0043729394 | G95: =G94/G93 -> -0.0036790705 | H95: =H94/H93 -> -0.0013189704 | I95: =AVERAGE(C95:H95) -> -0.022683792 | J95: =_xlfn.STDEV.S(C95:H95) -> 0.034077014
A96: Purchase of investments | B96: -886.892 | C96: -1471.528 | D96: -913.898 | E96: -493.889 | F96: -488.517 | G96: -367.741 | H96: 0
A97: Sale of investments | B97: 855.965 | C97: 1317.308 | D97: 590.173 | E97: 648.887 | F97: 392.178 | G97: 67.701 | H97: 50
A98: Investments (net) | B98: =B96+B97 -> -30.927 | C98: =C96+C97 -> -154.22 | D98: =D96+D97 -> -323.725 | E98: =E96+E97 -> 154.998 | F98: =F96+F97 -> -96.339 | G98: =G96+G97 -> -300.04 | H98: =H96+H97 -> 50
A99: % of sales | B99: =B98/B93 -> -0.0010164411 | C99: =C98/C93 -> -0.004442588 | D99: =D98/D93 -> -0.0077983475 | E99: =E98/E93 -> 0.0042483829 | F99: =F98/F93 -> -0.0047834657 | G99: =G98/G93 -> -0.013282655 | H99: =H98/H93 -> 0.0019946321 | I99: =AVERAGE(C99:H99) -> -0.0040106735 | J99: =_xlfn.STDEV.S(C99:H99) -> 0.006408987
A100: Acquisitions and investments (net) | B100: =B98+B94 -> -365.876 | C100: =C98+C94 -> -225.044 | D100: =D98+D94 -> -3876.916 | E100: =E98+E94 -> -1271.426 | F100: =F98+F94 -> -184.41 | G100: =G98+G94 -> -383.146 | H100: =H98+H94 -> 16.937
A101: % of revenues | B101: =B100/B93 -> -0.012024814 | C101: =C100/C93 -> -0.0064828023 | D101: =D100/D93 -> -0.093392658 | E101: =E100/E93 -> -0.034848865 | F101: =F100/F93 -> -0.0091564052 | G101: =G100/G93 -> -0.016961725 | H101: =H100/H93 -> 0.00067566169 | I101: =AVERAGE(C101:H101) -> -0.026694466 | J101: =_xlfn.STDEV.S(C101:H101) -> 0.034857103

Sheet Sheet1
C6: Net Sales | D6: 34714 | E6: 41512 | F6: 36484 | G6: 20140 | H6: 22588.858 | I6: 25067.279 | J6: 20252.393 | K6: 16208.122 | L6: 16439.276 | M6: 21105.141 | N6: 19052.046 | O6: 19429
C7: COGS | D7: 26899.6 | E7: 29008.72 | F7: 25458.59 | G7: 17912.05 | H7: 19909.768 | I7: 20771.871 | J7: 17682.986 | K7: 14182.215 | L7: 15325.386 | M7: 19255.904 | N7: 17641.421 | O7: 17915.46
C8: Gross Profit | D8: 7814.4 | E8: 12503.28 | F8: 11025.41 | G8: 2227.95 | H8: 2679.09 | I8: 4295.408 | J8: 2569.407 | K8: 2025.907 | L8: 1113.89 | M8: 1849.237 | N8: 1410.625 | O8: 1513.54
C9: Gross Profit Margin | D9: 0.22510803 | E9: 0.30119676 | F9: 0.3021985 | G9: 0.11062314 | H9: 0.11860228 | I9: 0.17135518 | J9: 0.1268693 | K9: 0.12499332 | L9: 0.06775785 | M9: 0.087620215
C10: Marketing, admin | D10: -1584.052 | E10: -1997.178 | F10: -1706.609 | G10: -615.041 | H10: -711.248 | I10: -860.722 | J10: -687.531 | K10: -596.761 | L10: -458.989 | M10: -520.805 | N10: -467.904 | O10: -437.337
C11: Operating Income | D11: 6230.348 | E11: 10506.102 | F11: 9318.801 | G11: 1612.909 | H11: 1967.842 | I11: 3434.686 | J11: 1881.876 | K11: 1429.146 | L11: 654.901 | M11: 1328.432 | N11: 942.721 | O11: 1076.203
C12: Other Operating Expenses (Revenues) | D12: -12.783 | E12: 91.042 | F12: -40.907 | G12: 624.173 | H12: 63.605 | I12: 69.76 | J12: -41.661 | K12: -38.757 | L12: 239.504 | M12: 11.888 | N12: 4.703 | O12: 60.886
C13: EBIT | D13: 6243.131 | E13: 10415.06 | F13: 9359.708 | G13: 988.736 | H13: 1904.237 | I13: 3364.926 | J13: 1923.537 | K13: 1467.903 | L13: 415.397 | M13: 1316.544 | N13: 938.018 | O13: 1015.317
C14: Net Financial Cost | D14: 29.632 | E14: -170.216 | F14: -158.854 | G14: -153.198 | H14: -121.425 | I14: -135.535 | J14: -173.58 | K14: -169.244 | L14: -173.531 | M14: -169.256 | N14: -146.895 | O14: -162.375
C15: EBT | D15: 6272.763 | E15: 10244.844 | F15: 9200.854 | G15: 835.538 | H15: 1782.812 | I15: 3229.391 | J15: 1749.957 | K15: 1298.659 | L15: 241.866 | M15: 1147.288 | N15: 791.123 | O15: 852.942
C16: Taxes | D16: -1359.966 | E16: -2165.204 | F16: -2078.488 | G16: 0.49 | H16: -411.897 | I16: -748.307 | J16: -369.386 | K16: -398.243 | L16: -48.836 | M16: -368.724 | N16: -205.594 | O16: -259.814
C17: Net Income common stockholders | D17: 4912.797 | E17: 8079.64 | F17: 7122.366 | G17: 836.028 | H17: 1370.915 | I17: 2481.084 | J17: 1380.571 | K17: 900.416 | L17: 193.03 | M17: 778.564 | N17: 585.529 | O17: 593.128
C18: Non-controlling interests | D18: -387.99 | E18: -472.303 | F18: -294.909 | G18: -114.558 | H18: -99.767 | I18: -120.317 | J18: -61.883 | K18: -104.145 | L18: -112.306 | M18: -99.227 | N18: -97.504 | O18: -88.507
C19: Net Income | D19: 4524.807 | E19: 7607.337 | F19: 6827.457 | G19: 721.47 | H19: 1271.148 | I19: 2360.767 | J19: 1318.688 | K19: 796.271 | L19: 80.724 | M19: 679.337 | N19: 488.025 | O19: 504.621
