Workbook
Name Sectors: '[1]Sector Impact'!$K$4:$K$16
Name Sectors: 'Sector Impact'!$K$4:$K$16

Sheet OP
B2: 45620 | C2: Team 1 | D2: 45657 | E2: =Inputs!H3 -> UNITED PARCEL SERVICE, INC. (XNYS:UPS) | L2: {=_FV(E2,"Exchange")} -> #VALUE! | M2: SIC:
D3: COMPANY DESCRIPTION | H3: CEO & BOARD OF DIRECTORS
D4: {=_FV(Inputs!H3,"Description")} -> #VALUE! | H4: Name, Age and Tenure | I4: Gender | J4: Executive? | L4: Other roles
H5: Carol Tome, 67, 2003 | I5: F | J5: Y | L5: Director at Verizon Communications
H6: Rodney Adkins, 65, 2013 | I6: M | J6: Y | L6: President of RRAM Group LLC
H7: Eva Boratto, 57, 2020 | I7: F | J7: N | L7: CFO Bath Body Works, Inc.
H8: Michael Burns, 72, 2005 | I8: M | J8: N | L8: -
H9: Wayne Hewett, 59, 2020 | I9: M | J9: N | L9: Senior Advisor to Permira
H10: Angela Hwang, 58, 2020 | I10: F | J10: N | L10: Advisor at Pfizer
H11: Kate Johnson, 56, 2020 | I11: F | J11: N | L11: President, CFO at Lumen Technologies Inc.
H12: William Johnson, 75, 2009 | I12: M | J12: Y | L12: Director at Sovos
H13: Franck Moison, 70, 2017 | I13: M | J13: N | L13: Chairman of Advisory Board of EDHEC BS
H14: Christiana Shi, 64, 2018 | I14: F | J14: N | L14: Director at Hanes Brand and SES France
H15: Russel Stokes, 52, 2020 | I15: M | J15: N | L15: CFO at GE AeroSpace
H16: Kevin Warsh, 53, 2012 | I16: M | J16: N | L16: Lecturer at Stanford Graduate School of Business
B17: {=_FV(E2,"Currency")&" MILLIONS"} -> #VALUE!
B18: COMPANY OVERVIEW
B19: Stock | D19: Liquidity and Solvency | F19: Segments | I19: ="Profitability ("&J20&")" -> Profitability (2023) | L19: Multiples
B20: Last Price | C20: {=_FV(E2,"Price")} -> #VALUE! | D20: Total Assets | E20: =_xlfn.XLOOKUP(D20,'Fin. Data'!A:A,'Fin. Data'!B:B,,0) -> 70857 | F20: Regions | H20: % Sales | I20: Reporting Year | J20: 2023 | L20: Float | M20: =IF(Inputs!B82 <> "",Inputs!B82,"") -> 0.99896
B21: Outstanding Shares | C21: {=_FV(E2,"Shares outstanding",TRUE)} -> #VALUE! | D21: Total Liabilities | E21: =_xlfn.XLOOKUP(D21,'Fin. Data'!A:A,'Fin. Data'!B:B,,0) -> 53543 | F21: =Segments!C5 -> U.S. | H21: =Segments!B5 -> 0.78881462 | I21: End of Year | J21: 45291 | L21: Insiders Own | M21: =IF(Inputs!B83 <> "",Inputs!B83,"") -> 0.0001
B22: Market Cap. | C22: =C20*C21/1000000 -> #VALUE! | D22: Cash/Share | E22: =_xlfn.XLOOKUP("Cash & Eq.",'Fin. Data'!A:A,'Fin. Data'!B:B,,0)*1000000/C21 -> #VALUE! | I22: EBITDA | K22: =_xlfn.XLOOKUP(I22,'Fin. Data'!A:A,'Fin. Data'!B:B,,0) -> 12507 | L22: b (Yahoo) | M22: {=IF(_FV(E2,"Beta") <> "",_FV(E2,"Beta"),"")} -> #VALUE!
B23: +Total Debt | C23: ='Fin. Data'!B58 -> 26729 | D23: EBITDA/Net Financial Cost (NFC) | E23: =IFERROR(_xlfn.XLOOKUP("EBITDA",'Fin. Data'!A:A,'Fin. Data'!B:B,,0)/_xlfn.XLOOKUP("Net Financial Cost",'Fin. Data'!A:A,'Fin. Data'!B:B,,0),"") -> -22.019366 | I23: Depreciation & Amortization | K23: =_xlfn.XLOOKUP(I23,'Fin. Data'!A:A,'Fin. Data'!B:B,,0) -> 3366 | L23: Score (S&P) | M23: =IF(Inputs!B84 <> "",Inputs!B84,"") -> A
B24: -Cash | C24: ='Fin. Data'!B39 -> 3206 | D24: Debt/EBITDA | E24: =IFERROR(_xlfn.XLOOKUP("Total Debt",'Fin. Data'!A:A,'Fin. Data'!B:B,,0)/_xlfn.XLOOKUP("EBITDA",'Fin. Data'!A:A,'Fin. Data'!B:B,,0),"") -> 2.1371232 | F24: =Segments!C6 -> Non-U.S. | H24: =Segments!B6 -> 0.21118538 | I24: EBIT | K24: =_xlfn.XLOOKUP(I24,'Fin. Data'!A:A,'Fin. Data'!B:B,,0) -> 9141 | L24: Price/Book Value | M24: =IFERROR((C20*C21/(E20-E21))/1000000,"")
B25: =Enterprise Value | C25: =C22+C23-C24 -> #VALUE! | D25: "Others Assets"/Asset | E25: =IFERROR(_xlfn.XLOOKUP("Other Assets",'Fin. Data'!A:A,'Fin. Data'!B:B,,0)/_xlfn.XLOOKUP("Total Assets",'Fin. Data'!A:A,'Fin. Data'!B:B,,0),"") -> 0.19928871 | I25: Net Income | K25: =_xlfn.XLOOKUP(I25,'Fin. Data'!A:A,'Fin. Data'!B:B,,0) -> 6708 | L25: NCF(3y avg)/Asset | M25: =IFERROR(K31/E20,"") -> -0.0092486746
B26: Holdings (nac/int'l) | C26: - | D26: Debt/Assets | E26: =_xlfn.XLOOKUP(D26,'Fin. Data'!A:A,'Fin. Data'!B:B,,0) -> 0.37722455 | F26: Categories | H26: % Sales | I26: EPS | K26: =1000000*K25/C21 -> #VALUE! | L26: Price/Net Inc. (3y avg) | M26: =IFERROR(C22/K30,"")
B27: t liq. (Holdings/Vol.) | C27: - | D27: EBITDA Margin (average) | E27: =IFERROR(AVERAGE(_xlfn.XLOOKUP("EBITDA Margin",'Fin. Data'!A:A,'Fin. Data'!B:D,,0)),"") -> 0.13049776 | F27: =Segments!C14 -> US Domestic Package | H27: =Segments!B14 -> 0.65918336 | I27: ROA | K27: =IFERROR(K25/E20,"") -> 0.094669546 | L27: EV/Asset | M27: =IFERROR(C25/E20,"")
B28: % Short | C28: 1,63% | D28: Operating Margin (average) | E28: =IFERROR(AVERAGE(_xlfn.XLOOKUP("Operating Margin",'Fin. Data'!A:A,'Fin. Data'!B:D,,0)),"") -> 0.12088937 | I28: ROIC | K28: =IFERROR(Peers!C18,"") -> 0.17517705 | L28: EV/Ebitda (3y average) | M28: =IFERROR(C25/K29,"")
B29: Traffic ESG | D29: Net Income Margin (average) | E29: =IFERROR(AVERAGE(_xlfn.XLOOKUP("Net Income Margin",'Fin. Data'!A:A,'Fin. Data'!B:D,,0)),"") -> 0.1071113 | F29: =Segments!C15 -> International Package | H29: =Segments!B15 -> 0.19603553 | I29: EBITDA (3y average) | K29: =AVERAGE(_xlfn.XLOOKUP("EBITDA",'Fin. Data'!A:A,'Fin. Data'!B:D,,0)) -> 12546 | L29: Price/NCF (3y average) | M29: =IFERROR(C22/K31,"")
B30: E | I30: Net Income (3y average) | K30: =AVERAGE(_xlfn.XLOOKUP("Net Income",'Fin. Data'!A:A,'Fin. Data'!B:D,,0)) -> 10382 | L30: Bonds 1,3,5a (USD) | M30: -
B31: S | D31: Net Financial Cost/Avg Net Debt | E31: =IFERROR(-_xlfn.XLOOKUP("Net Financial Cost",'Fin. Data'!A:A,'Fin. Data'!B:B,,0)/AVERAGE(_xlfn.XLOOKUP("Net Debt",'Fin. Data'!A:A,'Fin. Data'!B:D,,0)),"") -> 0.030098031 | F31: =Segments!C16 -> Supply Chain Solutions | H31: =Segments!B16 -> 0.14478111 | I31: NCF (3y average) | K31: =AVERAGE(_xlfn.XLOOKUP("Net Financial Cost",'Fin. Data'!A:A,'Fin. Data'!B:D,,0)) -> -655.33333 | L31: Div+Rep.(3y avg)/Price | M31: =-IFERROR(SUM(E52:E54)/(3*C22),"") -> #VALUE!
B32: G | L32: Div. Yield | M32: =-IFERROR(L53/C22,"") -> #VALUE!
B33: INVESTMENT THESIS
B34: Pillars of Recommendation | H34: Recommendation | I34: Valuation Assumptions
B35: Pillar | C35: Explanation | H35: BUY | I35: Check DCF
B36: Innovation | C36: Sofisticated systems optmizitation helps margins and revenue, and UPS is implementing this, in the robotization of its network.
B37: Global Presence | C37: UPS is an industry leader and has a strong reputation
B38: Ambitious Goals | C38: The revenue forecast is positive and the company is not stagnating in known markets. They are expanding into the healthcare market, for example, where they are striving to become leaders.
B39: Risks of Investment | H39: Price Target | I39: Valuation
B40: Risk | C40: Explanation | H40: =IFERROR(DCF!D75,"") | I40: Discount Rate | J40: =DCF!F50 -> 0.085 | L40: Upside | M40: =IFERROR(DCF!D74,"")
B41: Macroec. Outlook | C41: UPS revenue is extremely dependant on global consumer general consumption, which is something very volatile given differents phases of the economic cicle.
B42: Geopolitical tensions | C42: Present tensions can impact the globality of UPS' network and set restrictions to its movements.
B43: Commodity prices | C43: Volatile commodities like oil, have a great impact on UPS margins.
B44: FINANCIAL PERFORMANCE
B45: Year | C45: Net Sales | D45: Operating Margin | E45: Dividends + Share Buyback | F45: Net Cash Flow | G45: Debt/Assets | H45: Depreciation & Amortization | I45: Capex + Investments | J45: Cash Flow
B46: =B47-1 -> 2015 | C46: {=_xlfn.SORTBY(TRANSPOSE(_xlfn.XLOOKUP(C$45,'Fin. Data'!$A:$A,'Fin. Data'!$B:$J,,0)),$B$46:$B$54,-1)} -> 58363 | D46: {=_xlfn.SORTBY(TRANSPOSE(_xlfn.XLOOKUP(D$45,'Fin. Data'!$A:$A,'Fin. Data'!$B:$J,,0)),$B$46:$B$54,-1)} -> 0.13138461 | E46: {=_xlfn.SORTBY(TRANSPOSE(_xlfn.XLOOKUP(E$45,'Fin. Data'!$A:$A,'Fin. Data'!$B:$J,,0)),$B$46:$B$54,-1)} -> -5227 | F46: =Inputs!J77 -> 556 | G46: {=_xlfn.SORTBY(TRANSPOSE(_xlfn.XLOOKUP(G$45,'Fin. Data'!$A:$A,'Fin. Data'!$B:$J,,0)),$B$46:$B$54,-1)} -> 0.37414842 | H46: {=_xlfn.SORTBY(TRANSPOSE(_xlfn.XLOOKUP(H$45,'Fin. Data'!$A:$A,'Fin. Data'!$B:$J,,0)),$B$46:$B$54,-1)} -> 2084 | I46: {=_xlfn.SORTBY(TRANSPOSE(_xlfn.XLOOKUP(I$45,'Fin. Data'!$A:$A,'Fin. Data'!$B:$J,,0)),$B$46:$B$54,-1)} -> -2409 | L46: =J20 -> 2023 | M46: =L46-1 -> 2022
B47: =B48-1 -> 2016 | C47: 60906 | D47: 0.089761271 | E47: -5321 | F47: =Inputs!I77 -> 767 | G47: 0.39812269 | H47: 2224 | I47: -3512 | J47: Net Income | L47: =_xlfn.XLOOKUP($J47,'Fin. Data'!$A:$A,'Fin. Data'!B:B,,0) -> 6708 | M47: =_xlfn.XLOOKUP($J47,'Fin. Data'!$A:$A,'Fin. Data'!C:C,,0) -> 11548 | N47: =(C47/C46)-1 -> 0.043572126 | O47: =(D47/D46)-1 -> -0.31680528
B48: =B49-1 -> 2017 | C48: 65872 | D48: 0.11429743 | E48: -4584 | F48: =Inputs!H77 -> -209 | G48: 0.53496465 | H48: 2282 | I48: -5361 | J48: Operating CF | L48: =_xlfn.XLOOKUP($J48,'Fin. Data'!$A:$A,'Fin. Data'!B:B,,0) -> 10238 | M48: =_xlfn.XLOOKUP($J48,'Fin. Data'!$A:$A,'Fin. Data'!C:C,,0) -> 14104 | N48: =(C48/C47)-1 -> 0.081535481 | O48: =(D48/D47)-1 -> 0.273349 | Q48: =F48/F47-1 -> -1.2724902 | R48: =H48/H47-1 -> 0.026079137 | S48: =I48/I47-1 -> 0.52648064
B49: =B50-1 -> 2018 | C49: 71861 | D49: 0.097744256 | E49: -4022 | F49: =Inputs!G77 -> 689 | G49: 0.45457454 | H49: 2207 | I49: -6240 | J49: Investing CF | L49: =_xlfn.XLOOKUP($J49,'Fin. Data'!$A:$A,'Fin. Data'!B:B,,0) -> -7133 | M49: =_xlfn.XLOOKUP($J49,'Fin. Data'!$A:$A,'Fin. Data'!C:C,,0) -> -7472 | N49: =(C49/C48)-1 -> 0.090918752 | O49: =(D49/D48)-1 -> -0.14482539 | Q49: =F49/F48-1 -> -4.2966507 | R49: =H49/H48-1 -> -0.032865907 | S49: =I49/I48-1 -> 0.16396195
B50: =B51-1 -> 2019 | C50: 74094 | D50: 0.10524469 | E50: -4198 | F50: =Inputs!F77 -> 851 | G50: 0.48683824 | H50: 2360 | I50: -6386 | J50: Net Capex | L50: =_xlfn.XLOOKUP($J50,'Fin. Data'!$A:$A,'Fin. Data'!B:B,,0) -> -5158 | M50: =_xlfn.XLOOKUP($J50,'Fin. Data'!$A:$A,'Fin. Data'!C:C,,0) -> -4769 | N50: =(C50/C49)-1 -> 0.031073879 | O50: =(D50/D49)-1 -> 0.07673528 | Q50: =F50/F49-1 -> 0.23512337 | R50: =H50/H49-1 -> 0.069324875 | S50: =I50/I49-1 -> 0.023397436
B51: =B52-1 -> 2020 | C51: 84628 | D51: 0.090797372 | E51: -3598 | F51: =Inputs!E77 -> 659 | G51: 0.44471863 | H51: 2698 | I51: -5432 | J51: Investments & Acquisitions | L51: =_xlfn.XLOOKUP($J51,'Fin. Data'!$A:$A,'Fin. Data'!B:B,,0) -> -1329 | M51: =_xlfn.XLOOKUP($J51,'Fin. Data'!$A:$A,'Fin. Data'!C:C,,0) -> -755 | N51: =(C51/C50)-1 -> 0.14217076 | O51: =(D51/D50)-1 -> -0.1372736 | Q51: =F51/F50-1 -> -0.22561692 | R51: =H51/H50-1 -> 0.14322034 | S51: =I51/I50-1 -> -0.14938929
B52: =B53-1 -> 2021 | C52: 97287 | D52: 0.13167227 | E52: -3937 | F52: =Inputs!D77 -> 4366 | G52: 0.36781212 | H52: 2953 | I52: -4796 | J52: Financing CF | L52: =_xlfn.XLOOKUP($J52,'Fin. Data'!$A:$A,'Fin. Data'!B:B,,0) -> -5534 | M52: =_xlfn.XLOOKUP($J52,'Fin. Data'!$A:$A,'Fin. Data'!C:C,,0) -> -11185 | N52: =(C52/C51)-1 -> 0.14958406 | O52: =(D52/D51)-1 -> 0.45017709 | Q52: =F52/F51-1 -> 5.6251897 | R52: =H52/H51-1 -> 0.094514455 | S52: =I52/I51-1 -> -0.11708395
B53: =B54-1 -> 2022 | C53: 100338 | D53: 0.13049891 | E53: -8614 | F53: =Inputs!C$77 -> -4553 | G53: 0.32929813 | H53: 3188 | I53: -5524 | J53: Dividends | L53: =_xlfn.XLOOKUP($J53,'Fin. Data'!$A:$A,'Fin. Data'!B:B,,0) -> -5372 | M53: =_xlfn.XLOOKUP($J53,'Fin. Data'!$A:$A,'Fin. Data'!C:C,,0) -> -5114 | N53: =(C53/C52)-1 -> 0.031360819 | O53: =(D53/D52)-1 -> -0.0089111776 | Q53: =F53/F52-1 -> -2.042831 | R53: =H53/H52-1 -> 0.079580088 | S53: =I53/I52-1 -> 0.15179316
B54: =J20 -> 2023 | C54: 90958 | D54: 0.10049693 | E54: -7622 | F54: =Inputs!B77 -> -2429 | G54: 0.37722455 | H54: 3366 | I54: -6487 | J54: Share Buyback | L54: =_xlfn.XLOOKUP($J54,'Fin. Data'!$A:$A,'Fin. Data'!B:B,,0) -> -2250 | M54: =_xlfn.XLOOKUP($J54,'Fin. Data'!$A:$A,'Fin. Data'!C:C,,0) -> -3500 | N54: =(C54/C53)-1 -> -0.093484024 | O54: =(D54/D53)-1 -> -0.22990215 | Q54: =F54/F53-1 -> -0.4665056 | R54: =H54/H53-1 -> 0.055834379 | S54: =I54/I53-1 -> 0.1743302
B55: Annual Growth Rate | C55: =IFERROR((C54/C46)^(1/8)-1,"") -> 0.057031457 | D55: =IFERROR((D54/D46)^(1/8)-1,"") -> -0.032945303 | F55: =IFERROR((F54/F46)^(1/8)-1,"") | H55: =IFERROR((H54/H46)^(1/8)-1,"") -> 0.061761686 | J55: FX | L55: =_xlfn.XLOOKUP($J55,'Fin. Data'!$A:$A,'Fin. Data'!B:B,,0) -> 0 | M55: =_xlfn.XLOOKUP($J55,'Fin. Data'!$A:$A,'Fin. Data'!C:C,,0) -> 0 | N55: =(C55/C54)-1 -> -0.99999937 | O55: =(D55/D54)-1 -> -1.327824
B56: Average Growth Rate | C56: =IFERROR(AVERAGE(N47:N54),"") -> 0.059591481 | D56: =IFERROR(AVERAGE(O47:O54),"") -> -0.0046820287 | F56: =IFERROR(AVERAGE(Q47:Q54),"") -> -0.34911163 | H56: =IFERROR(AVERAGE(S47:S54),"") -> 0.11049859 | J56: Changes in Cash | L56: =L48-L49+L52-L53-L54 -> 19459 | M56: =M48-M49+M52-M53-M54 -> 19005
B57: CVAR | C57: =IFERROR(STDEV(C47:C54)/AVERAGE(C47:C54),"") -> 0.18219326 | D57: =IFERROR(STDEV(D46:D54)/AVERAGE(D46:D54),"") -> 0.15737822 | F57: =IFERROR(STDEV(F46:F54)/AVERAGE(F46:F54),"") -> 31.698808 | H57: =IFERROR(STDEV(H46:H54)/AVERAGE(H46:H54),"") -> 0.18209299 | J57: Inventory/D Revenues | L57: =IFERROR(SUM(I51:I54)/(C54-C50),"") -> -1.3187263 | M57: =IFERROR((SUM(I51:I54)-SUM(H51:H54))/(C54-C50),"") -> -2.0424573
B58: Last Year | C58: =IFERROR(C54/C53-1,"") -> -0.093484024 | D58: =IFERROR(D54/D53-1,"") -> -0.22990215 | F58: =IFERROR(1-(F54/F53),"") -> 0.4665056 | H58: =IFERROR(1-(H54/H53),"") -> -0.055834379 | J58: t inversiones; t adq. neto dep. | L58: =IFERROR(L57/E27,"") -> -10.105355 | M58: =IFERROR(M57/E27,"") -> -15.651282
B59: QUALITATIVE ANALYSIS
B60: SWOT ANALYSIS | J60: HOLDERS
B61: Pros | E61: Cons | J61: Name | M61: % Stake
B62: Global Presence: UPS is an industry leader and the brand has a good reputation. Integrated Network: Extensive integrated air and ground delivery network. Technological Advancements: Sofisticated systems optimize network efficiency, and improve the service provided to customers, and how their own customers react. Financial Strenght and Strong Rating: This helps UPS make sustainable acquisitions (past ones were made with free cash flow) and makes it possible for the company to contract debt at lower interest rates, leading to a higher ROIC. | E62: Customer Concentratrion Risk: Heavy reliance on some customers, like Amazon, that accounts for over 11% of UPS revenue. Margins are subject to commodity prices: Volatile commodity prices like gasoline can negatively impact UPS margins and increase costs. | J62: Vanguard Group Inc. | M62: 0.0873
J64: Blackrock Inc. | M64: 0.0756
J66: State Street Corp. | M66: 0.0396
J68: JP Morgan & Chase | M68: 0.0324
J70: Charles Schwab IM, Inc. | M70: 0.0281
B72: Opportunities | E72: Risks | J72: Wellington Management Group, LLP | M72: 0.0261
B73: E-commerce boom: UPS is well-positioned to capitalize on the increasing demand for online delivery services. Entering new markets, like Healthcare: The growing need for specialized logistics in the healthcare sector, including the transportation of medical supplies and vaccines, offers UPS a chance to expand into high-margin markets. Sustainability Initiatives: Opportunity to improve brand's reputation. | E73: Changes in macroeconomic conditions, national and international: consumer expending is extremely dependant on macroeconomic instable factors, and directly affetcs all the actors in e-commerce. Rapidly evolving industry: Causes the need to constantly keep up with technological improvements Geopolitical tensions: this may reduce economic activities between two major participants, China (a major producer) and USA (a major consumer). Commodity prices: Gasoline, jet fuel are commodities of which prices can impact UPS profit greatly. They are also very volatile, due to geopolitical tensions.
J74: Geode Capital Management | M74: 0.0204
J76: Bank of America Corp. | M76: 0.0172
J78: Franklin Resources | M78: 0.0144
J80: FMR | M80: 0.014
J81: TOTAL | M81: =SUM(M62:M80) -> 0.3551
G82: STOCK PERFORMANCE (5 years)
G107: =E2 -> UNITED PARCEL SERVICE, INC. (XNYS:UPS) | I107: =Peers!C2 -> #VALUE! | K107: =Peers!C3 -> #VALUE! | M107: =Peers!C4 -> #VALUE!

Sheet Segments
B2: ="Regions "&"("&OP!$J$20&")" -> Regions (2023) | Q2: Products
D3: Nominal value | K3: YoY Growth
B4: Weight | C4: Region | D4: =OP!J20 -> 2023 | E4: =D4-1 -> 2022 | F4: =E4-1 -> 2021 | G4: =F4-1 -> 2020 | H4: =G4-1 -> 2019 | I4: =H4-1 -> 2018 | K4: =OP!J20 -> 2023 | L4: =K4-1 -> 2022 | M4: =L4-1 -> 2021 | N4: =M4-1 -> 2020 | O4: =N4-1 -> 2019 | P4: =O4-1 -> 2018
B5: =IFERROR(D5/$D$9,"") -> 0.78881462 | C5: U.S. | D5: 71749 | E5: 78110 | F5: 74376 | G5: 66580 | H5: 58699 | I5: 56115 | K5: =(D5-E5)/E5 -> -0.081436436 | L5: =(E5-F5)/F5 -> 0.050204367 | M5: =(F5-G5)/G5 -> 0.11709222 | N5: =(G5-H5)/H5 -> 0.13426123 | O5: =(H5-I5)/I5 -> 0.046048294 | P5: -
B6: =IFERROR(D6/$D$9,"") -> 0.21118538 | C6: Non-U.S. | D6: 19209 | E6: 22228 | F6: 22911 | G6: 18048 | H6: 15395 | I6: 15746 | K6: =(D6-E6)/E6 -> -0.13581969 | L6: =(E6-F6)/F6 -> -0.029811008 | M6: =(F6-G6)/G6 -> 0.26944814 | N6: =(G6-H6)/H6 -> 0.17232868 | O6: =(H6-I6)/I6 -> -0.022291376 | P6: -
B7: =IFERROR(D7/$D$9,"") -> 0
B8: =IFERROR(D8/$D$9,"") -> 0
B9: =SUM(B5:B8) -> 1 | C9: TOTAL | D9: =SUM(D5:D8) -> 90958 | E9: =SUM(E5:E8) -> 100338 | F9: =SUM(F5:F8) -> 97287 | G9: =SUM(G5:G8) -> 84628 | H9: =SUM(H5:H8) -> 74094 | I9: =SUM(I5:I8) -> 71861 | K9: =(D9-E9)/E9 -> -0.093484024 | L9: =(E9-F9)/F9 -> 0.031360819 | M9: =(F9-G9)/G9 -> 0.14958406 | N9: =(G9-H9)/H9 -> 0.14217076 | O9: =(H9-I9)/I9 -> 0.031073879 | P9: -
B11: ="Categories "&"("&OP!$J$20&")" -> Categories (2023)
D12: Nominal value | K12: YoY Growth
B13: Weight | C13: Category | D13: =OP!J20 -> 2023 | E13: =D13-1 -> 2022 | F13: =E13-1 -> 2021 | G13: =F13-1 -> 2020 | H13: =G13-1 -> 2019 | I13: =H13-1 -> 2018 | K13: =OP!J20 -> 2023 | L13: =K13-1 -> 2022 | M13: =L13-1 -> 2021 | N13: =M13-1 -> 2020 | O13: =N13-1 -> 2019 | P13: =O13-1 -> 2018
B14: =IFERROR(D14/$D$17,"") -> 0.65918336 | C14: US Domestic Package | D14: 59958 | E14: 64209 | F14: 60137 | G14: 53499 | H14: 46493 | I14: 43593 | K14: =(D14-E14)/E14 -> -0.066205672 | L14: =(E14-F14)/F14 -> 0.067712057 | M14: =(F14-G14)/G14 -> 0.12407709 | N14: =(G14-H14)/H14 -> 0.15068935 | O14: =(H14-I14)/I14 -> 0.066524442 | P14: -
B15: =IFERROR(D15/$D$17,"") -> 0.19603553 | C15: International Package | D15: 17831 | E15: 19698 | F15: 19541 | G15: 15945 | H15: 14220 | I15: 14442 | K15: =(D15-E15)/E15 -> -0.094781196 | L15: =(E15-F15)/F15 -> 0.0080343892 | M15: =(F15-G15)/G15 -> 0.22552524 | N15: =(G15-H15)/H15 -> 0.12130802 | O15: =(H15-I15)/I15 -> -0.015371832 | P15: -
B16: =IFERROR(D16/$D$17,"") -> 0.14478111 | C16: Supply Chain Solutions | D16: 13169 | E16: 16431 | F16: 17429 | G16: 15184 | H16: 13381 | I16: 13826 | K16: =(D16-E16)/E16 -> -0.19852717 | L16: =(E16-F16)/F16 -> -0.057260887 | M16: =(F16-G16)/G16 -> 0.147853 | N16: =(G16-H16)/H16 -> 0.13474329 | O16: =(H16-I16)/I16 -> -0.032185737 | P16: -
B17: =SUM(B14:B16) -> 1 | C17: TOTAL | D17: =SUM(D14:D16) -> 90958 | E17: =SUM(E14:E16) -> 100338 | F17: =SUM(F14:F16) -> 97107 | G17: =SUM(G14:G16) -> 84628 | H17: =SUM(H14:H16) -> 74094 | I17: =SUM(I14:I16) -> 71861 | K17: =(D17-E17)/E17 -> -0.093484024 | L17: =(E17-F17)/F17 -> 0.033272576 | M17: =(F17-G17)/G17 -> 0.14745711 | N17: =(G17-H17)/H17 -> 0.14217076 | O17: =(H17-I17)/I17 -> 0.031073879 | P17: -
B19: Categories | D19: Description | I19: Graphs
B20: =C14 -> US Domestic Package | D20: U.S. Domestic Package operations include the time-definite delivery of letters, documents and packages throughout the United States. It includes a variety of services that cater to different shipping speeds, delivery times, and customer preferences.
B21: =C15 -> International Package | D21: International Package operations include delivery to more than 200 countries and territories worldwide, including shipments wholly outside the United States, as well as shipments with either origin or destination outside the United States. Our International Package reporting segment includes our operations in Europe, the Indian sub-continent, Middle East and Africa (together "EMEA"), Canada and Latin America (together "Americas") and Asia.
B22: =C16 -> Supply Chain Solutions | D22: Supply Chain Solutions includes Forwarding, Logistics, digital and other businesses. The Forwarding and Logistics businesses provide services in more than 200 countries and territories worldwide and include international air and ocean freight forwarding, truckload brokerage, customs brokerage, mail services, healthcare logistics, distribution and post-sales services. The digital businesses leverage technology to enable a range of on-demand services such as same-day delivery, end-to-end return services and integrated supply chain and high-value shipment insurance solutions.
B24: Industry | J24: Graphs (Industry Forecasts)
B25: Drivers | D25: Description
B26: E-commerce Growth | D26: The growth of e-commerce increases demand for fast deliveries and logistical efficiency, prompting the industry to adapt to meet customer expectations.
B27: Technological Advances | D27: Technological Advances sush as automation and robotics, AI and machine learning are crucial for this industry and enable cost reduction, higher efficiency and improved customer satisfaction.
B28: Supply Chain Trends | D28: Supply chain complexity increases the need for logistics providers that can manage global networks, promoting integrated logistics services and end-to-end solutions from manufacturing to last-mile delivery.
B29: Sales forecast
B30: Source | D30: Market Growth CAGR | G30: Period
B31: Statista | D31: 0.0839 | G31: 2023 - 2028
B32: Grand View Reseacrh | D32: 0.072 | G32: 2023 - 2030
B33: Precedence Research | D33: 0.0935 | G33: 2024 - 2033
B34: Average | D34: =AVERAGE(D31:F33) -> 0.083133333
B35: Company's Strategy / Extra Notes
B38: UPS reports that its strategy is rooted in the guiding principles - Customer First, People Led, Innovation Driven. This approach reflects the company’s commitment to enhancing customer experience while also emphasizing the importance of its workforce and the role of technological advancements in driving efficiency. In that sense, Costumer First focuses on meeting customers’ expectations and needs. UPS aims to provide customers with improved service delivery, by enhancing service seep and reliability, offering proactive customer support channels. The company also intends to grow its healthcare logistics, aspiring to become the leading provider of complex healthcare logistics in the world. Additionally, it aims to support small & medium business (SMBs), providing customized shipping solutions and strengthening customer relationships and loyalty. This is particularly important to UPS response to the post-pandemic slowdown in e-commerce while preparing for future challenges in the logistics market. Equally important to UPS’ strategy, People Led emphasizes its focus on its employees. The company believes that, by fostering a culture that prioritizes employee satisfaction and attracting and retaining talent, it can provide industry-leading services to their customers. Lastly, Innovation Driven summarizes the company’s focus and investments in automation, AI and machine learning, enabling them to optimize load planning, scheduling and volume flows. Such advancements are crucial to streamlining operations and improving cost efficiency, adapting to market changes and enhancing service delivery.

Sheet Acuerdo
A1: Invertir
A2: NO invertir
A3: Mantener sin elevar posición
A4: Mantener (y seguir comprando)
A5: Liquidar
A6: PENDIENTE

Sheet Peers
B1: Peer Logo | C1: Peer Name | D1: Description
C2: #VALUE! | D2: FedEx Corporation provides transportation, e-commerce, and business services in the United States and internationally. It operates through FedEx Express, FedEx Ground, FedEx Freight, and FedEx Services segments. The FedEx Express segment offers express transportation, small-package ground delivery, and freight transportation services; and time-critical transportation services. The FedEx Ground segment provides small-package ground delivery services. The FedEx Freight segment offers less-than-truckload freight transportation services. The FedEx Services segment provides sales, marketing, information technology, communications, customer service, technical support, billing and collection, and back-office support services. In addition, the company offers supply chain management solutions; and air and ocean freight forwarding and cargo transportation, specialty transportation, customs brokerage, third party logistics and supply chain, and document and business solutions, as well as provides trade management tools and data. The company was founded in 1971 and is headquartered in Memphis, Tennessee.
C3: #VALUE! | D3: Deutsche Post AG operates as a mail and logistics company in Germany, rest of Europe, the Americas, the Asia Pacific, the Middle East, and Africa. The company operates through five segments: Express; Global Forwarding, Freight; Supply Chain; eCommerce; and Post & Parcel Germany. The Express segment offers time-definite express services to business and private customers. The Global Forwarding, Freight segment provides air, ocean, and overland freight forwarding services; and offers multimodal and sector-specific solutions. The Supply Chain segment delivers customized logistics services and supply chain solutions to its customers. The eCommerce segment provides parcel delivery and non-time definite international cross-border services. The Post & Parcel Germany segment transports, sorts, and delivers mail communication, physical and hybrid letters, and goods; and offers additional services, such as registered mail, cash on delivery, and insured items. Deutsche Post AG is headquartered in Bonn, Germany.
C4: #VALUE! | D4: XPO, Inc. provides freight transportation services in the United States, rest of North America, France, the United Kingdom, rest of Europe, and internationally. The company operates in two segments, North American LTL and European Transportation. The North American LTL segment provides customers with less-than-truckload (LTL) services, such as geographic density and day-definite domestic services. This segment also offers cross-border U.S., Mexico, Canada, and the Caribbean, as well as engages in the operation of trailer manufacturing. The European Transportation segment offers dedicated truckload, LTL, truck brokerage, managed transportation, last mile, freight forwarding and multimodal solutions, such as road-rail and road-short sea combinations. It provides its services to customers in various industries, such as industrial and manufacturing, retail and e-commerce, food and beverage, logistics and transportation, and consumer goods. XPO, Inc. was incorporated in 2000 and is based in Greenwich, Connecticut.
C5: #VALUE! | D5: C.H. Robinson Worldwide, Inc provides freight transportation services, and related logistics and supply chain services in the United States and internationally. It operates through two segments: North American Surface Transportation and Global Forwarding. The company provides transportation and logistics services, including truckload and less-than-truckload brokerage, intermodal transportation and non-vessel operating common carrier and freight forwarding. It also offers air shipments, door-to-door services, customs brokerage, and other logistics solutions such as managed services, warehousing, and small parcel services. The company partners with around 45,000 transportation providers, including motor carriers, railroads, and ocean and air carriers. Additionally, under the Robinson Fresh brand, it buys, sells, and markets fresh produce for grocery retailers, restaurants, wholesalers, and foodservice distributors. The company was founded in 1905 and is headquartered in Eden Prairie, Minnesota.
D6: {=_FV(C6,"Description")} -> #VALUE!
B8: In Millions USD | C8: =OP!E2 -> UNITED PARCEL SERVICE, INC. (XNYS:UPS) | D8: =C2 -> #VALUE! | E8: =C3 -> #VALUE! | F8: =C4 -> #VALUE! | G8: =C5 -> #VALUE! | H8: =C6 -> 0 | I8: AVERAGE | J8: Deviation from Average
B9: Company Info | I9: =IFERROR(AVERAGE(C9:H9),"") | L9: TRAFFIC
B10: Market Cap | C10: {=_FV(C8,"Market cap",TRUE)/1000000} -> #VALUE! | D10: 65676 | E10: 43701 | F10: 12772 | G10: 12770 | H10: {=_FV(H8,"Market cap",TRUE)/1000000} -> #VALUE! | I10: =IFERROR(AVERAGE(C10:G10),"") | J10: =SQRT((C10-I10)^2) -> #VALUE! | M10: Best Value
B11: Net Sales (current) | C11: =C56 -> 90958 | D11: =D56 -> 87693 | E11: =E56 -> 90391.645 | F11: =F56 -> 7744 | G11: =G56 -> 17596 | H11: =H56 -> 0 | I11: =IFERROR(AVERAGE(C11:G11),"") -> 58876.529 | J11: =SQRT((C11-I11)^2) -> 32081.471
B12: Profitability | M12: Important Value
B13: Sales Growth (ttm) | C13: =C56/C55-1 -> -0.093484024 | D13: =D56/D55-1 -> -0.027308524 | E13: =E56/E55-1 -> -0.10711419 | F13: =F56/F55-1 -> 0.0033687484 | G13: =G56/G55-1 -> -0.2875248 | H13: =H56/H55-1 -> #DIV/0! | I13: =IFERROR(AVERAGE(C13:G13),"") -> -0.10241256 | J13: =SQRT((C13-I13)^2) -> 0.0089285345
B14: Sales Growth (36m) | C14: =C56/C54-1 -> 0.074797939 | D14: =D56/D54-1 -> 0.044474089 | E14: =E56/E54-1 -> 0.10909632 | F14: =F56/F54-1 -> 0.25551232 | G14: =G56/G54-1 -> 0.085703708 | H14: =H56/H54-1 -> #DIV/0! | I14: =IFERROR(AVERAGE(C14:G14),"") -> 0.11391688 | J14: =SQRT((C14-I14)^2) -> 0.039118937 | M14: Worst Value
B15: Operating Margin | C15: =C59/C56 -> 0.10049693 | D15: =D59/D56 -> 0.063391605 | E15: =E59/E56 -> 0.06803004 | F15: =F59/F56 -> 0.070118802 | G15: =G59/G56 -> 0.029268015 | H15: =H59/H56 -> #DIV/0! | I15: =IFERROR(AVERAGE(C15:G15),"") -> 0.066261079 | J15: =SQRT((C15-I15)^2) -> 0.034235854
B16: Net Income Margin | C16: =C62/C56 -> 0.073748323 | D16: =D62/D56 -> 0.049388207 | E16: =E62/E56 -> 0.048129847 | F16: =F62/F56 -> 0.024405992 | G16: =G62/G56 -> 0.053478063 | H16: =H62/H56 -> #DIV/0! | I16: =IFERROR(AVERAGE(C16:G16),"") -> 0.049830086 | J16: =SQRT((C16-I16)^2) -> 0.023918237
B17: Return on Equity (RoE) | C17: =C62/C74 -> 0.38759444 | D17: =D62/D74 -> 0.1570227 | E17: =E62/E74 -> 0.17190913 | F17: =F62/F74 -> 0.1492891 | G17: =G62/G74 -> 0.66314306 | H17: =H62/H74 -> #DIV/0! | I17: =IFERROR(AVERAGE(C17:G17),"") -> 0.30579168 | J17: =SQRT((C17-I17)^2) -> 0.081802752
B18: Return on Invested Capital (ROIC) | C18: =(1+C61/(C59+C60))*C59/(C73+C74-C65) -> 0.17517705 | D18: =(1+D61/(D59+D60))*D59/(D73+D74-D65) -> 0.067094071 | E18: =(1+E61/(E59+E60))*E59/(E73+E74-E65) -> 0.093277211 | F18: =(1+F61/(F59+F60))*F59/(F73+F74-F65) -> 0.089497886 | G18: =(1+G61/(G59+G60))*G59/(G73+G74-G65) -> 0.071621305 | H18: =(1+H61/(H59+H60))*H59/(H73+H74-H65) -> #DIV/0! | I18: =IFERROR(AVERAGE(C18:G18),"") -> 0.099333505 | J18: =SQRT((C18-I18)^2) -> 0.075843549
B19: Solvency
B20: Debt/Assets | C20: =C73/C70 -> 0.37722455 | D20: =D73/D70 -> 0.43351684 | E20: =E73/E70 -> 0.31174604 | F20: =F73/F70 -> 0.54898558 | G20: =G73/G70 -> 0.3737799 | H20: =H73/H70 -> #DIV/0! | I20: =IFERROR(AVERAGE(C20:G20),"") -> 0.40905058 | J20: =SQRT((C20-I20)^2) -> 0.031826034
B21: Net Debt/EBITDA | C21: =(C73-C65)/C58 -> 1.8807868 | D21: =(D73-D65)/D58 -> 2.8724696 | E21: =(E73-E65)/E58 -> 1.5848708 | F21: =(F73-F65)/F58 -> 4.3034884 | G21: =(G73-G65)/G58 -> 2.9446254 | H21: =(H73-H65)/H58 -> #DIV/0! | I21: =IFERROR(AVERAGE(C21:G21),"") -> 2.7172482 | J21: =SQRT((C21-I21)^2) -> 0.83646145
B22: Interest Coverage Ratio | C22: =-C58/C60 -> 22.019366 | D22: =-D58/D60 -> 28.981333 | E22: =-E58/E60 -> 14.609164 | F22: =-F58/F60 -> 5.1190476 | G22: =-G58/G60 -> 5.847619 | H22: =-H58/H60 -> #DIV/0! | I22: =IFERROR(AVERAGE(C22:G22),"") -> 15.315306 | J22: =SQRT((C22-I22)^2) -> 6.7040601
B23: Liquidity
B24: Current Ratio | C24: =C68/C72 -> 1.0982688 | D24: =D68/D72 -> 1.3633096 | E24: =E68/E72 -> 0.9454286 | F24: =F68/F72 -> 1.0018868 | G24: =G68/G72 -> 1.4035088 | H24: =H68/H72 -> #DIV/0! | I24: =IFERROR(AVERAGE(C24:G24),"") -> 1.1624805 | J24: =SQRT((C24-I24)^2) -> 0.064211686
B25: Quick Ratio | C25: =(C65+C66)/C72 -> 0.82303689 | D25: =(D65+D66)/D72 -> 1.2420816 | E25: =(E65+E66)/E72 -> 0.69806121 | F25: =(F65+F66)/F72 -> 0.87106918 | G25: =(G65+G66)/G72 -> 1.2314815 | H25: =(H65+H66)/H72 -> #DIV/0! | I25: =IFERROR(AVERAGE(C25:G25),"") -> 0.97314608 | J25: =SQRT((C25-I25)^2) -> 0.15010919
B26: Activity
B27: Inventory Turnover | C27: =C57/C67 -> 87.504813 | D27: =D57/D67 -> 111.95603 | E27: =E57/E67 -> 63.660697 | F27: N/A | G27: N/A | H27: =H57/H67 -> #DIV/0! | I27: =IFERROR(AVERAGE(C27:G27),"") -> 87.707179 | J27: =SQRT((C27-I27)^2) -> 0.20236595
B28: Acc. Receivable Turnover | C28: =C56/C66 -> 8.0195733 | D28: =D56/D66 -> 8.6936651 | E28: =E56/E66 -> 7.7591345 | F28: =F56/F66 -> 7.95889 | G28: =G56/G66 -> 7.3870697 | H28: =H56/H66 -> #DIV/0! | I28: =IFERROR(AVERAGE(C28:G28),"") -> 7.9636665 | J28: =SQRT((C28-I28)^2) -> 0.055906752
A29: Price/Sales | B29: Payables Turnover | C29: =C57/C71 -> 12.90489 | D29: =D57/D71 -> 21.55566 | E29: =E57/E71 -> 7.9660337 | F29: =F57/F71 -> 13.109023 | G29: =G57/G71 -> 13.099693 | H29: =H57/H71 -> #DIV/0! | I29: =IFERROR(AVERAGE(C29:G29),"") -> 13.72706 | J29: =SQRT((C29-I29)^2) -> 0.82217025
B30: Fixed Asset Turnover | C30: =C56/C69 -> 2.461984 | D30: =D56/D69 -> 3.2111392 | E30: =E56/E69 -> 1.717569 | F30: =F56/F69 -> 1.3127649 | G30: =G56/G69 -> 7.5036247 | H30: =H56/H69 -> #DIV/0! | I30: =IFERROR(AVERAGE(C30:G30),"") -> 3.2414164 | J30: =SQRT((C30-I30)^2) -> 0.77943233
B31: Total Asset Turnover | C31: =C56/C70 -> 1.283684 | D31: =D56/D70 -> 1.0078844 | E31: =E56/E70 -> 1.2236657 | F31: =F56/F70 -> 1.0336359 | G31: =G56/G70 -> 3.3676555 | H31: =H56/H70 -> #DIV/0! | I31: =IFERROR(AVERAGE(C31:G31),"") -> 1.5833051 | J31: =SQRT((C31-I31)^2) -> 0.29962107
B32: Valuation
B33: Price/Earnings | C33: =C10/C62 -> #VALUE! | D33: =D10/D62 -> 15.164165 | E33: =E10/E62 -> 10.044969 | F33: =F10/F62 -> 67.57672 | G33: =G10/G62 -> 13.57067 | H33: =H10/H62 -> #VALUE! | I33: =IFERROR(AVERAGE(C33:G33),"") | J33: =SQRT((C33-I33)^2) -> #VALUE!
B34: Price/Sales | C34: =C10/C56 -> #VALUE! | D34: =D10/D56 -> 0.74893093 | E34: =E10/E56 -> 0.48346283 | F34: =F10/F56 -> 1.6492769 | G34: =G10/G56 -> 0.72573312 | H34: =H10/H56 -> #VALUE! | I34: =IFERROR(AVERAGE(C34:G34),"") | J34: =SQRT((C34-I34)^2) -> #VALUE!
B35: Price/Book | C35: =C10/C74 -> #VALUE! | D35: =D10/D74 -> 2.3811181 | E35: =E10/E74 -> 1.7268219 | F35: =F10/F74 -> 10.088468 | G35: =G10/G74 -> 8.9992953 | H35: =H10/H74 -> #VALUE! | I35: =IFERROR(AVERAGE(C35:G35),"") | J35: =SQRT((C35-I35)^2) -> #VALUE!
B36: EV/Sales | C36: =(C73+C10-C65)/C56 -> #VALUE! | D36: =(D73+D10-D65)/D56 -> 1.1049229 | E36: =(E73+E10-E65)/E56 -> 0.69359517 | F36: =(F73+F10-F65)/F56 -> 2.1271952 | G36: =(G73+G10-G65)/G56 -> 0.82848375 | H36: =(H73+H10-H65)/H56 -> #VALUE! | I36: =IFERROR(AVERAGE(C36:G36),"") | J36: =SQRT((C36-I36)^2) -> #VALUE!
B37: EV/EBITDA | C37: =(C73+C10-C65)/C58 -> #VALUE! | D37: =(D73+D10-D65)/D58 -> 8.9155318 | E37: =(E73+E10-E65)/E58 -> 5.2312688 | F37: =(F73+F10-F65)/F58 -> 19.154651 | G37: =(G73+G10-G65)/G58 -> 23.742671 | H37: =(H73+H10-H65)/H58 -> #VALUE! | I37: =IFERROR(AVERAGE(C37:G37),"") | J37: =SQRT((C37-I37)^2) -> #VALUE!
B38: Stock Info
B39: Float | C39: =OP!M20 -> 0.99896 | D39: 0.917 | E39: 0.804 | F39: 0.8926 | G39: 0.997 | I39: =IFERROR(AVERAGE(C39:G39),"") -> 0.921912 | J39: =SQRT((C39-I39)^2) -> 0.077048
B40: b (Yahoo) | C40: =OP!M22 -> #VALUE! | D40: 1.18 | E40: 1.07 | F40: 1.96 | G40: 0.83 | I40: =IFERROR(AVERAGE(C40:G40),"") | J40: =SQRT((C40-I40)^2) -> #VALUE!
B41: Dividend Yield (yahoo finance) | C41: =OP!M32 -> #VALUE! | D41: 0.0225 | E41: 0.0486 | F41: 0 | G41: 0.0206 | I41: =IFERROR(AVERAGE(C41:G41),"") | J41: =SQRT((C41-I41)^2) -> #VALUE!
B42: Stock Performance
B43: 1y | C43: -0.1408 | D43: 0.1117 | E43: -0.0094 | F43: 0.5153 | G43: 0.2702 | I43: =IFERROR(AVERAGE(C43:G43),"") -> 0.1494 | J43: =SQRT((C43-I43)^2) -> 0.2902
B44: 3y | C44: -0.356 | D44: 0.1449 | E44: -0.307 | F44: 1.13 | G44: 0.0843 | I44: =IFERROR(AVERAGE(C44:G44),"") -> 0.13924 | J44: =SQRT((C44-I44)^2) -> 0.49524
B45: Current Price | C45: {=_FV(C8,"Price")} -> #VALUE! | D45: 265.92 | E45: 41.25 | F45: 115.37 | G45: 109.1 | H45: {=_FV(H8,"Price")} -> #VALUE! | I45: =IFERROR(AVERAGE(C45:G45),"") | J45: =SQRT((C45-I45)^2) -> #VALUE!
B46: Average Target Price | C46: 144.53 | D46: 306.76 | E46: 46.2 | F46: 131.95 | G46: 104.3 | I46: =IFERROR(AVERAGE(C46:G46),"") -> 146.748 | J46: =SQRT((C46-I46)^2) -> 2.218
B47: Upside/Downside | C47: =C46/C45-1 -> #VALUE! | D47: =D46/D45-1 -> 0.15358002 | E47: =E46/E45-1 -> 0.12 | F47: =F46/F45-1 -> 0.14371154 | G47: =G46/G45-1 -> -0.043996334 | H47: =H46/H45-1 -> #VALUE! | I47: =IFERROR(AVERAGE(C47:G47),"") | J47: =SQRT((C47-I47)^2) -> #VALUE!
B48: Extra
B49: 3y Operating Cash Flow | C49: =(Inputs!B59-Inputs!E59)/Inputs!E59 -> -0.021130127 | D49: =(8312-10135)/10135 -> -0.17987173 | E49: =(9258-7699)/7699 -> 0.20249383 | F49: =(682-885)/885 -> -0.22937853 | G49: =(731946-449191)/449191 -> 0.6294761 | I49: =IFERROR(AVERAGE(C49:G49),"") -> 0.080317909 | J49: =SQRT((C49-I49)^2) -> 0.10144804
B50: R&D/Net Sales | C50: =C63/C11 -> 0 | D50: =D63/D11 -> 0 | E50: =E63/E11 -> 0 | F50: =F63/F11 -> 0 | G50: =G63/G11 -> 0 | H50: =H63/H11 -> #DIV/0! | I50: =IFERROR(AVERAGE(C50:G50),"") -> 0 | J50: =SQRT((C50-I50)^2) -> 0
B52: Financial Data | C52: =OP!E2 -> UNITED PARCEL SERVICE, INC. (XNYS:UPS) | D52: =D8 -> #VALUE! | E52: =E8 -> #VALUE! | F52: =F8 -> #VALUE! | G52: =G8 -> #VALUE! | H52: =H8 -> 0
B53: IS
B54: Net Sales (36m ago) | C54: ='Fin. Data'!E5 -> 84628 | D54: 83959 | E54: =66716*1.2216 -> 81500.266 | F54: 6168 | G54: 16207
B55: Net Sales (12m ago) | C55: ='Fin. Data'!C5 -> 100338 | D55: 90155 | E55: =94436*1.072 -> 101235.39 | F55: 7718 | G55: 24697
B56: Net Sales (current) | C56: ='Fin. Data'!B5 -> 90958 | D56: =87693 -> 87693 | E56: =81758*1.1056 -> 90391.645 | F56: 7744 | G56: 17596
B57: COGS | C57: ='Fin. Data'!B5-'Fin. Data'!B7 -> 81817 | D57: 68741 | E57: =67544*1.1056 -> 74676.646 | F57: 6974 | G57: 17082
B58: EBITDA | C58: ='Fin. Data'!B19 -> 12507 | D58: 10868 | E58: =10840*1.1056 -> 11984.704 | F58: 860 | G58: 614
B59: Operating Income | C59: ='Fin. Data'!B11 -> 9141 | D59: 5559 | E59: =5562*1.1056 -> 6149.3472 | F59: 543 | G59: 515
B60: Net Financial Cost | C60: ='Fin. Data'!B14 -> -568 | D60: -375 | E60: =-742*1.1056 -> -820.3552 | F60: -168 | G60: -105
B61: Taxes | C61: ='Fin. Data'!B21 -> -1865 | D61: -1505 | E61: =-1581*1.1056 -> -1747.9536 | F61: -68 | G61: -226
B62: Net Income | C62: ='Fin. Data'!B23 -> 6708 | D62: 4331 | E62: =3935*1.1056 -> 4350.536 | F62: 189 | G62: 941
B63: R&D
B64: BS
B65: Cash & Eq. | C65: ='Fin. Data'!B39 -> 3206 | D65: 6501 | E65: =3649*1.1056 -> 4034.3344 | F65: 412 | G65: 145
B66: Acc. Receivables | C66: ='Fin. Data'!B40 -> 11342 | D66: 10087 | E66: =10537*1.1056 -> 11649.707 | F66: 973 | G66: 2382
B67: Inventory | C67: ='Fin. Data'!B41 -> 935 | D67: 614 | E67: =1061*1.1056 -> 1173.0416 | F67: N/A | G67: N/A
B68: Current Assets | C68: =Inputs!B27 -> 19413 | D68: 18207 | E68: =19213*1.1056 -> 21241.893 | F68: 1593 | G68: 2880
B69: Fixed Assets | C69: ='Fin. Data'!B42 -> 36945 | D69: 27309 | E69: =47601*1.1056 -> 52627.666 | F69: 5899 | G69: =G70-G68 -> 2345
B70: Total Assets | C70: ='Fin. Data'!B44 -> 70857 | D70: 87007 | E70: =66814*1.1056 -> 73869.558 | F70: 7492 | G70: 5225
B71: Acc. Payable | C71: =Inputs!B43 -> 6340 | D71: 3189 | E71: =8479*1.1056 -> 9374.3824 | F71: 532 | G71: 1304
B72: Current Liabilities | C72: =Inputs!B42 -> 17676 | D72: 13355 | E72: =20322*1.1056 -> 22468.003 | F72: 1590 | G72: 2052
B73: Total Debt | C73: ='Fin. Data'!B58 -> 26729 | D73: 37719 | E73: =1.1056*20829 -> 23028.542 | F73: 4113 | G73: 1953
B74: Total Equity | C74: ='Fin. Data'!B64 -> 17306.75 | D74: 27582 | E74: =22890*1.1056 -> 25307.184 | F74: 1266 | G74: 1419
B75: Revenues by Geografical Segmentation
B76: Total Revenue from US | C76: 71749 | D76: 63531 | E76: =17815*1.1056 -> 19696.264 | F76: 4572 | G76: 14796

Sheet ESG
B1: Company GICS Sector: | S1: Yes
B2: Industrials | C2: <- Select Industry | S2: No
B3: ESG Analysis | K3: Relative ESG Analysis
B4: Parameters | C4: Impact | D4: Do they report? | E4: Ranking | F4: Mitigation Plan | G4: Traffic Lights | H4: Improvement over time? | I4: Targets / Goals? | J4: Comments | K4: Parameters | L4: =Peers!C8 -> UNITED PARCEL SERVICE, INC. (XNYS:UPS) | M4: =Peers!D8 -> #VALUE! | N4: =Peers!E8 -> #VALUE! | O4: =Peers!F8 -> #VALUE! | P4: =Peers!G8 -> #VALUE! | Q4: AVERAGE | S4: 2018 | T4: 2019 | U4: 2020 | V4: 2021 | W4: 2022 | X4: 2023
B5: Environmental | K5: Ratios | S5: 13851000 | T5: 14223000 | U5: 15088000 | V5: 15668000 | W5: 15845000 | X5: 14499000
A6: 1 | B6: CO2 Direct Emissions | C6: =VLOOKUP($B$2,'Sector Impact'!$K$4:$AA$16,A6+1,FALSE) -> Very High | D6: Yes | E6: "Villain" | F6: Yes | H6: 8.5% reduction in scope 1 emissions in 2023 compared to 2022. | I6: "40% alternative fuel in ground operations" by 2025 (current 28.8%); "50% reduction in CO₂e per global small package (2020 baseline)" by 2035; Reach carbon neutrality by 2050. | J6: Ranked 127 of 130 companies in Refinitiv. | K6: CO2 Emissions/$M Sales | L6: =L12/L$11 -> 159.40324 | M6: =M12/M$11 -> 178.5241 | N6: =N12/N$11 -> 81.421024 | O6: N/A | P6: =P12/P$11 -> 426.68788 | Q6: =IFERROR(AVERAGE(L6:P6),"") -> 211.50906
A7: 2 | B7: Total Water Consumption | C7: =VLOOKUP($B$2,'Sector Impact'!$K$4:$AA$16,A7+1,FALSE) -> Very High | D7: No | K7: Water Consumption/$M Sales | L7: N/A | M7: N/A | N7: N/A | O7: N/A | P7: N/A | Q7: =IFERROR(AVERAGE(L7:P7),"")
A8: 3 | B8: Total Energy Consumption | C8: =VLOOKUP($B$2,'Sector Impact'!$K$4:$AA$16,A8+1,FALSE) -> Very High | D8: Yes | E8: "Villain" | F8: Yes | H8: 7.8% reduction ir direct energy use in 2023 compared with 2022. | I8: 25% renewable electricity powering their facilities by 2025 reaching 100% in 2035 (current is 10.9%). | J8: Ranked 118 of 121 companies in Refinitiv. | K8: Energy Consumption/$M Sales | L8: =L14/L$11 -> 2346.4896 | M8: =M14/M$11 -> 3468.6805 | N8: =N14/N$11 -> 1244.0028 | O8: N/A | P8: =P14/P$11 -> 19.370766 | Q8: =IFERROR(AVERAGE(L8:P8),"") -> 1769.6359
A9: 4 | B9: Waste Management | C9: =VLOOKUP($B$2,'Sector Impact'!$K$4:$AA$16,A9+1,FALSE) -> High | D9: No | F9: No | H9: N/A | I9: N/A | J9: The waste in operations is considered not relevant in the report and is not reported. | K9: Waste Production/$M Sales | L9: N/A | M9: =M15/M$11 -> 6.4448474 | N9: =N14/N$11 -> 1244.0028 | O9: N/A | P9: N/A | Q9: =IFERROR(AVERAGE(L9:P9),"") -> 625.22384
A10: 5 | B10: Land Degradation/Deforestation/Biodiversity loss/Animal sufering/… | C10: =VLOOKUP($B$2,'Sector Impact'!$K$4:$AA$16,A10+1,FALSE) -> High | D10: No | F10: No | H10: N/A | I10: N/A | K10: Inputs
B11: Social | K11: Net Sales ($M) | L11: 90958 | M11: 87693 | N11: 101448 | O11: 7744 | P11: 17596
A12: 6 | B12: Employee Turnover % | C12: =VLOOKUP($B$2,'Sector Impact'!$K$4:$AA$16,A12+1,FALSE) -> Low | H12: N/A | I12: N/A | J12: "Global turnover rate = 25%" | K12: CO2 Emissions Total (Tonnes) | L12: 14499000 | M12: 15655314 | N12: 8260000 | O12: ="-" -> - | P12: =7.508 *10^6 -> 7508000
A13: 7 | B13: Salaries & Compensation | C13: =VLOOKUP($B$2,'Sector Impact'!$K$4:$AA$16,A13+1,FALSE) -> Medium | D13: No | E13: Medium | F13: No | H13: N/A | I13: N/A | J13: It's mentioned on the report that UPS offers competitive salaries with "industry-leading pay and benefits". It's also mentioned that UPS provides "for equal remuneration irrespective of gender or any other protected class". 53% think they are paid fairly (indeed.com). | K13: Water Consumption Total (Cubic Meters) | L13: ="-" -> - | M13: ="-" -> - | N13: 1400000 | O13: ="-" -> - | P13: ="-" -> - | R13: 2018 | S13: 2019 | T13: 2020 | U13: 2021 | V13: 2022 | W13: 2023
A14: 8 | B14: Reputation | C14: =VLOOKUP($B$2,'Sector Impact'!$K$4:$AA$16,A14+1,FALSE) -> High | D14: No | E14: Medium High | F14: No | H14: N/A | I14: N/A | J14: N/A | K14: Energy Consumption Total (Gigajoules) | L14: 213432000 | M14: 304179000 | N14: 126201600 | O14: ="-" -> - | P14: 340848 | R14: 198420000 | S14: 203929000 | T14: 216422000 | U14: 225544000 | V14: 229653000 | W14: 213432000
A15: 9 | B15: Discrimination Events | C15: =VLOOKUP($B$2,'Sector Impact'!$K$4:$AA$16,A15+1,FALSE) -> Very High | D15: Yes | E15: Medium High | F15: Yes | H15: N/A | I15: By 2025 UPS aims to have 40% ethnically diverse company management in the U.S. (current is 39%), 30% women in full-time management globally (current is 27%) and 1M volunteer hours dedicated to underserved Black communities (current is 983k) | J15: "UPS does not discriminate against any applicant for employment or any employee in any aspect of their employment at UPS because of age, race, religion, sex, disability, sexual orientation, gender identity" | K15: Waste Production Total (Tonnes) | L15: ="-" -> - | M15: 565168 | N15: ="-" -> - | O15: ="-" -> - | P15: ="-" -> -
A16: 10 | B16: Work Safety | C16: =VLOOKUP($B$2,'Sector Impact'!$K$4:$AA$16,A16+1,FALSE) -> Medium | D16: Yes | E16: Medium High | F16: Yes | H16: "The insights gained from incidents and audits are integrated into our broader global safety strategy, making the approach thorough and continually improving" | I16: N/A | J16: "UPS's health and safety programs are comprehensive and focus on building a culture of health and safety by: • Identifying and assessing risk, and auditing for compliance • Investing in safety training and new safety technology • Promoting well-being for all employees • Offering benefits that promote employee safety in the workplace and beyond" | K16: ESG Scores
A17: 11 | B17: Damage to consumer health | C17: =VLOOKUP($B$2,'Sector Impact'!$K$4:$AA$16,A17+1,FALSE) -> Very High | D17: No | E17: Medium | F17: No | H17: N/A | I17: N/A | J17: N/A | K17: Refinitiv | L17: 57 (48/63/71) | M17: 70 (74/65/71) | N17: 73 (73/71/76) | O17: 72 (51/80/88) | P17: 41(41/57/21)
A18: 12 | B18: PXP? | C18: =VLOOKUP($B$2,'Sector Impact'!$K$4:$AA$16,A18+1,FALSE) -> Medium | D18: Yes | E18: Medium High | F18: No | H18: N/A | I18: N/A | J18: "UPS offers comprehensive retirement plans, including pension plans for full-time employees and 401(k) plans with company contributions for part-time employees. The company remains committed to providing sustainable and competitive pension options for its workforce"​ | K18: Sustainalytics | L18: 18.8 (low risk) | M18: 19.0 (low risk) | N18: 13.1 (low risk) | O18: 24.0 (medium risk) | P18: 17.5 (low risk)
A19: 13 | B19: Supply chain | C19: =VLOOKUP($B$2,'Sector Impact'!$K$4:$AA$16,A19+1,FALSE) -> Very High | D19: Yes | E19: Medium High | F19: No | H19: N/A | I19: N/A | J19: "Our supply chain partners tend to be other service providers, rather than raw material or finished goods suppliers. Supply chain partners can be broadly grouped into three categories: Production Suppliers, Capacity Suppliers, and Support Suppliers"​ | K19: ISS | L19: C | M19: D+ | N19: C+ | O19: D+ | P19: D
A20: 14 | B20: Community involvement | C20: =VLOOKUP($B$2,'Sector Impact'!$K$4:$AA$16,A20+1,FALSE) -> Very High | D20: Yes | E20: Medium High | F20: Yes | H20: N/A | I20: N/A | J20: "232M+ lives positively impacted 175M+ vaccines delivered including lifesaving early childhood vaccine 342K volunteer hours recorded for underserved Black communities 50+ disasters and humanitarian crises supported around the world 35% of charitable funding spent in underserved and marginalized communities 1.9M volunteer hours recorded $60M provided in charitable contributions 12K+ small business owners trained through UPS’s Women Exporters Program 6M trees planted by UPSers" | K20: CDP | L20: B- | M20: C | N20: B | O20: F | P20: B
A21: 15 | B21: Public Sector | C21: =VLOOKUP($B$2,'Sector Impact'!$K$4:$AA$16,A21+1,FALSE) -> Very High | D21: No | E21: "Villain" | F21: No | H21: N/A | I21: N/A | J21: "Donated to federal lawmakers who opposed voting rights legislation during the 2022 election cycle Donated to federal lawmakers who objected to certifying the 2020 presidential election Donated to federal lawmakers who opposed creating a Congressional January 6th investigation Donated to state officials who voted for anti-voter legislation during the 2022 election cycle Donated to state officials who supported 2020 election audits Key company staff made large donations to anti-democracy federal legislators during the 2022 election cycle Is a member of the U.S. Chamber of Commerce, which opposed recent federal voting legislation" (American Democracy Scorecard)
A22: 16 | B22: Litigation | C22: =VLOOKUP($B$2,'Sector Impact'!$K$4:$AA$16,A22+1,FALSE) -> High | D22: No | E22: Medium | F22: No | H22: N/A | I22: N/A | J22: Found several litigation cases involving racial discrimination, hazardous residues and work safety violations. All of the cases are recent, the racial discrimination case occured this month.
B23: Corporate Governance | K23: PARAMETERS
A24: 17 | B24: Diversity (Gender, Age, Industry, Region) | E24: Medium | F24: No | H24: N/A | I24: N/A | J24: 42% of the directors are Female and 33% are Ethnically diverse. They have different bacgrounds in diverse areas of business. | K24: IMPACT | L24: RANKING | M24: MITIGATION PLAN | O24: TRAFFIC
A25: 18 | B25: % Independence | E25: Medium High | F25: No | H25: N/A | I25: N/A | J25: 92% of the directors are independent. | K25: Low | L25: "Best in class" | M25: Is there evidence of a plan/program ?
A26: 19 | B26: average time as independent directors | E26: Medium High | F26: No | H26: N/A | I26: N/A | J26: The average tenuere as a director is 8,9 years. | K26: Medium | L26: Medium High
A27: 20 | B27: Recent departures of directors / C-level executives? | E27: "Best in class" | F27: No | H27: N/A | I27: N/A | J27: There were 5 directors that retired since 2020. | K27: High | L27: Medium
A28: 21 | B28: CEO/Chairman duality | E28: "Best in class" | F28: No | H28: N/A | I28: N/A | J28: The roles of Chairman and CEO were separated in 2020. Carol Tomé is the CEO and Bill Johnson serves as the chairman. | K28: Very high | L28: "Villain"
A29: 22 | B29: Transparency (ESG, segments, acquisitions, other) | E29: Medium High | F29: No | H29: N/A | I29: N/A | J29: One of the things that makes me not giving "Best in class" in this category is that the waste is considered not relevant but there is litigations involving hazardous residues.
A30: 23 | B30: Time taken to report after the end of the quarter / year | E30: Medium | F30: No | H30: N/A | I30: N/A | J30: The proxy report was issued in March 18, 2024 and the ESG report was issued in March 20, 2024.
A31: 24 | B31: Additional participation of the CEO in other boards or excessive participation of Ch. | E31: Medium | F31: No | H31: N/A | I31: N/A | J31: The ceo participates in another board.
A32: 25 | B32: Audit / Consulting | D32: Yes | E32: Medium High | F32: No | H32: N/A | I32: N/A | J32: Deloitte & Touche LLP audited the ESG Report.
A33: 26 | B33: ESG-compensation related | D33: Yes | E33: Medium | F33: No | H33: N/A | I33: N/A | J33: N/A
A34: 27 | B34: Management compensation schemes | D34: Yes | E34: Medium High | F34: No | H34: N/A | I34: N/A | J34: N/A

Sheet DCF
A1: VALUATION MODEL
G3: Short Term | K3: Long Term
A4: Section | B4: Line # | C4: ITEM | D4: 2021 (Real) | E4: 2022 (Real) | F4: 2023 (Real) | G4: 2024 | H4: =G4+1 -> 2025 | I4: =H4+1 -> 2026 | J4: =I4+1 -> 2027 | K4: =J4+1 -> 2028 | L4: =K4+1 -> 2029 | M4: =L4+1 -> 2030 | N4: =M4+1 -> 2031 | O4: =N4+1 -> 2032 | ... AF4: =AE4+1 -> 2049
A5: INCOME STATEMENT | B5: 1 | C5: Growth | D5: ='Fin. Data'!D6 -> 0.14958406 | E5: =+E6/D6-1 -> 0.031360819 | F5: =+F6/E6-1 -> -0.093484024 | G5: =+G6/F6-1 -> 0.0015611601 | H5: =+H6/G6-1 -> 0.097694841 | I5: =+I6/H6-1 -> 0.1 | J5: =+J6/I6-1 -> 0.05 | K5: =+K6/J6-1 -> 0.05 | L5: =+L6/K6-1 -> 0.05 | ... AF5: =+AF6/AE6-1 -> 0.02
B6: 2 | C6: Revenues/Sales | D6: =Inputs!D6 -> 97287 | E6: =Inputs!C6 -> 100338 | F6: =Inputs!B6 -> 90958 | G6: =Assumptions!E43 -> 91100 | H6: =Assumptions!F43 -> 100000 | I6: =Assumptions!G43 -> 110000 | J6: =Assumptions!H43 -> 115500 | K6: =Assumptions!I43 -> 121275 | L6: =Assumptions!J43 -> 127338.75 | M6: =Assumptions!K43 -> 133705.69 | N6: =Assumptions!L43 -> 140390.97 | ... AF6: =Assumptions!AD43 -> 222087.19
B7: 3 | C7: EBIT/Operating Margin | D7: =D8/D6 -> 0.13167227 | E7: =E8/E6 -> 0.13049891 | F7: =F8/F6 -> 0.10049693 | G7: 0.096 | H7: =Assumptions!F44 -> 0.11 | I7: =Assumptions!G44 -> 0.13 | J7: 0.11 | K7: =Assumptions!I44 -> 0.11 | L7: =Assumptions!J44 -> 0.11 | M7: =Assumptions!K44 -> 0.11 | N7: =Assumptions!L44 -> 0.11 | O7: =Assumptions!M44 -> 0.11 | P7: =Assumptions!N44 -> 0.11 | Q7: =Assumptions!O44 -> 0.11 | R7: =Assumptions!P44 -> 0.11 | ... AF7: =Assumptions!AD44 -> 0.11
B8: 4 | C8: EBIT | D8: ='Fin. Data'!D11 -> 12810 | E8: ='Fin. Data'!C11 -> 13094 | F8: ='Fin. Data'!B11 -> 9141 | G8: =G7*G6 -> 8745.6 | H8: =H7*H6 -> 11000 | I8: =I7*I6 -> 14300 | J8: =J7*J6 -> 12705 | K8: =K7*K6 -> 13340.25 | L8: =L7*L6 -> 14007.263 | M8: =M7*M6 -> 14707.626 | N8: =N7*N6 -> 15443.007 | ... AF8: =AF7*AF6 -> 24429.591
B9: 5a | C9: (Dep) | D9: -3366 | E9: -3188 | F9: -2953 | G9: =$D$53*DCF!F40 -> -3217.734 | H9: =$D$53*DCF!G40 -> -3612.1059 | I9: =$D$53*DCF!H40 -> -4045.0059 | J9: =$D$53*DCF!I40 -> -4521.1959 | K9: =$E$53*DCF!J40 -> -5021.1954 | L9: =$E$53*DCF!K40 -> -5546.1949 | M9: =$E$53*DCF!L40 -> -6097.4443 | N9: =$E$53*DCF!M40 -> -6676.2562 | O9: =$E$53*DCF!N40 -> -7284.0088 | P9: =$E$53*DCF!O40 -> -7913.0326 | Q9: =$E$53*DCF!P40 -> -8564.0723 | R9: =$E$53*DCF!Q40 -> -9237.8984 | ... AF9: =$E$53*DCF!AE40 -> -20813.438 | AG9: =SUM(D9:AF9) -> -293279.68
B10: 5b | C10: (Amort) | D10: =-Assumptions!AB23 -> -294 | E10: =-Assumptions!AA23 -> -292 | F10: =-Assumptions!Z23 -> -500 | G10: =F38*$D$54 -> -312.45 | H10: =G38*$D$54 -> -328.0725 | I10: =H38*$D$54 -> -344.47613 | J10: =I38*$D$54 -> -361.69993 | K10: =J38*$E$54 -> -379.78493 | L10: =K38*$E$54 -> -398.77417 | M10: =L38*$E$54 -> -418.71288 | N10: =M38*$E$54 -> -439.64853 | O10: =N38*$E$54 -> -461.63095 | P10: =O38*$E$54 -> -484.7125 | Q10: =P38*$E$54 -> -508.94813 | R10: =Q38*$E$54 -> -534.39553 | ... AF10: =AE38*$E$54 -> -1058.0666
B11: 5c | C11: (Stock based compensation) | D11: =D20 -> 0 | E11: =E20 -> 0 | F11: =F20 -> 0 | G11: =G6*$D$55 -> 0 | H11: =H6*$D$55 -> 0 | I11: =I6*$D$55 -> 0 | J11: =J6*$D$55 -> 0 | K11: =K6*$D$55 -> 0 | L11: =L6*$D$55 -> 0 | M11: =M6*$D$55 -> 0 | N11: =N6*$D$55 -> 0 | ... AF11: =AF6*$D$55 -> 0
B12: 6 | C12: EBITDA | D12: =D8-D9-D10 -> 16470 | E12: =E8-E9-E10 -> 16574 | F12: =F8-F9-F10 -> 12594 | G12: =G8-G9-G10 -> 12275.784 | H12: =H8-H9-H10 -> 14940.178 | I12: =I8-I9-I10 -> 18689.482 | J12: =J8-J9-J10 -> 17587.896 | K12: =K8-K9-K10 -> 18741.23 | ... AF12: =AF8-AF9-AF10 -> 46301.096
B13: 7 | C13: (Net financing cost) | D13: ='Fin. Data'!D14 -> -694 | E13: ='Fin. Data'!C14 -> -704 | F13: ='Fin. Data'!B14 -> -568 | G13: =F43*$D$58-F44*$D$57 -> -649.9495 | H13: =G43*$D$58-G44*$D$57 -> -678.53227 | I13: =H43*$D$58-H44*$D$57 -> -724.68801 | J13: =I43*$D$58-I44*$D$57 -> -725.48048 | K13: =J43*$E$58-J44*$E$57 -> -703.30838 | L13: =K43*$E$58-K44*$E$57 -> -734.95833 | M13: =L43*$E$58-L44*$E$57 -> -762.57745 | N13: =M43*$E$58-M44*$E$57 -> -785.26243 | O13: =N43*$E$58-N44*$E$57 -> -803.42029 | P13: =O43*$E$58-O44*$E$57 -> -810.73871 | Q13: =P43*$E$58-P44*$E$57 -> -809.04804 | R13: =Q43*$E$58-Q44*$E$57 -> -797.93537 | ... AF13: =AE43*$E$58-AE44*$E$57 -> 906.63448
B14: 8 | C14: Other income/(cost) | D14: ='Fin. Data'!D15 -> 4479 | E14: ='Fin. Data'!C15 -> 2435 | F14: ='Fin. Data'!B15 -> 0 | G14: =AVERAGE(D14:F14)*(1+G5) -> 2308.2646 | H14: =AVERAGE(E14:G14)*(1+H5) -> 1735.5524 | I14: =AVERAGE(F14:H14)*(1+I5) -> 1482.7329 | J14: =AVERAGE(G14:I14)*(1+J5) -> 1934.2925 | K14: =AVERAGE(H14:J14)*(1+K5) -> 1803.4022 | L14: =AVERAGE(I14:K14)*(1+L5) -> 1827.1496 | M14: =AVERAGE(J14:L14)*(1+M5) -> 1947.6955 | N14: =AVERAGE(K14:M14)*(1+N5) -> 1952.3866 | ... AF14: =AVERAGE(AC14:AE14)*(1+AF5) -> 2444.5682
B15: 9 | C15: Earnings before taxes | D15: =D8+D13+D14 -> 16595 | E15: =E8+E13+E14 -> 14825 | F15: =F8+F13+F14 -> 8573 | G15: =G8+G13+G14 -> 10403.915 | H15: =H8+H13+H14 -> 12057.02 | I15: =I8+I13+I14 -> 15058.045 | J15: =J8+J13+J14 -> 13913.812 | K15: =K8+K13+K14 -> 14440.344 | ... AF15: =AF8+AF13+AF14 -> 27780.794
B16: 10 | C16: (Income tax) | D16: ='Fin. Data'!D21 -> -3705 | E16: ='Fin. Data'!C21 -> -3277 | F16: ='Fin. Data'!B21 -> -1865 | G16: =-$D$56*G15 -> -2288.8613 | H16: =-$D$56*H15 -> -2652.5444 | I16: =-$D$56*I15 -> -3312.7699 | J16: =-$D$56*J15 -> -3061.0386 | K16: =-$E$56*K15 -> -3754.4894 | L16: =-$E$56*L15 -> -3925.858 | M16: =-$E$56*M15 -> -4132.1134 | N16: =-$E$56*N15 -> -4318.6341 | O16: =-$E$56*O15 -> -4460.5566 | P16: =-$E$56*P15 -> -4617.4462 | Q16: =-$E$56*Q15 -> -4775.5591 | R16: =-$E$56*R15 -> -4943.4306 | ... AF16: =-$E$56*AF15 -> -7223.0065
B17: 11 | C17: Net income | D17: ='Fin. Data'!D23 -> 12890 | E17: ='Fin. Data'!C23 -> 11548 | F17: ='Fin. Data'!B23 -> 6708 | G17: =G16+G15 -> 8115.0538 | H17: =H16+H15 -> 9404.4757 | I17: =I16+I15 -> 11745.275 | J17: =J16+J15 -> 10852.773 | K17: =K16+K15 -> 10685.854 | L17: =L16+L15 -> 11173.596 | M17: =M16+M15 -> 11760.63 | N17: =N16+N15 -> 12291.497 | ... AF17: =AF16+AF15 -> 20557.788
A19: CASH FLOW STATEMENT | B19: 12 | C19: Operating cash flows before WK | D19: =Inputs!D59-D20-D21 -> 15649 | E19: =Inputs!C59-E20-E21 -> 14467 | F19: =Inputs!B59-F20-F21 -> 10752 | G19: =G17-G10-G9-G11 -> 11645.238 | H19: =H17-H10-H9-H11 -> 13344.654 | I19: =I17-I10-I9-I11 -> 16134.757 | J19: =J17-J10-J9-J11 -> 15735.669 | K19: =K17-K10-K9-K11 -> 16086.835 | L19: =L17-L10-L9-L11 -> 17118.565 | M19: =M17-M10-M9-M11 -> 18276.788 | N19: =N17-N10-N9-N11 -> 19407.402 | ... AF19: =AF17-AF10-AF9-AF11 -> 42429.292
B20: 13 | C20: (Stock-based compensation) | E20: 0 | F20: 0 | G20: =G11 -> 0 | H20: =H11 -> 0 | I20: =I11 -> 0 | J20: =J11 -> 0 | K20: =K11 -> 0 | L20: =L11 -> 0 | M20: =M11 -> 0 | N20: =N11 -> 0 | ... AF20: =AF11 -> 0
B21: 14 | C21: (Working Capital Flows) | D21: =Inputs!D62 -> -642 | E21: =Inputs!C62 -> -363 | F21: =Inputs!B62 -> -514 | G21: =$D$60*(G6-F6) -> -5.396 | H21: =$D$60*(H6-G6) -> -338.2 | I21: =$D$60*(I6-H6) -> -380 | J21: =$D$60*(J6-I6) -> -209 | K21: =$E$60*(K6-J6) -> -173.25 | L21: =$E$60*(L6-K6) -> -181.9125 | M21: =$E$60*(M6-L6) -> -191.00813 | N21: =$E$60*(N6-M6) -> -200.55853 | O21: =$E$60*(O6-N6) -> -147.41052 | P21: =$E$60*(P6-O6) -> -152.56989 | Q21: =$E$60*(Q6-P6) -> -157.90983 | R21: =$E$60*(R6-Q6) -> -163.43668 | ... AF21: =$E$60*(AF6-AE6) -> -130.63953
B22: 15 | C22: -Total Operating Cash Flow | D22: =D19+D20+D21 -> 15007 | E22: =E19+E20+E21 -> 14104 | F22: =F19+F20+F21 -> 10238 | G22: =G19+G20+G21 -> 11639.842 | H22: =H19+H20+H21 -> 13006.454 | I22: =I19+I20+I21 -> 15754.757 | J22: =J19+J20+J21 -> 15526.669 | K22: =K19+K20+K21 -> 15913.585 | ... AF22: =AF19+AF20+AF21 -> 42298.653
B23: 16 | C23: (CAPEX) | D23: ='Fin. Data'!D32 -> -4194 | E23: ='Fin. Data'!C32 -> -4769 | F23: ='Fin. Data'!B32 -> -5158 | G23: =G6*$D$62 -> -5056.05 | H23: =H6*$D$62 -> -5550 | I23: =I6*$D$62 -> -6105 | J23: =J6*$D$62 -> -6410.25 | K23: =K6*$E$62 -> -6730.7625 | L23: =L6*$E$62 -> -7067.3006 | M23: =M6*$E$62 -> -7420.6657 | N23: =N6*$E$62 -> -7791.6989 | O23: =O6*$E$62 -> -8064.4084 | P23: =P6*$E$62 -> -8346.6627 | Q23: =Q6*$E$62 -> -8638.7959 | R23: =R6*$E$62 -> -8941.1537 | ... AF23: =AF6*$E$62 -> -12325.839 | AG23: =SUM(D23:AF23) -> -252032.79
B24: 17 | C24: Adq | D24: =Inputs!D66 -> -602 | E24: ='Fin. Data'!C33 -> -755 | F24: ='Fin. Data'!B33 -> -1329 | G24: =G6*$D$63 -> -1366.5 | H24: =H6*$D$63 -> -1500 | I24: =I6*$D$63 -> -1650 | J24: =J6*$D$63 -> -1732.5 | K24: =K6*$E$63 -> -1819.125 | L24: =L6*$E$63 -> -1910.0812 | M24: =M6*$E$63 -> -2005.5853 | N24: =N6*$E$63 -> -2105.8646 | O24: =O6*$E$63 -> -2179.5698 | P24: =P6*$E$63 -> -2255.8548 | Q24: =Q6*$E$63 -> -2334.8097 | R24: =R6*$E$63 -> -2416.528 | ... AF24: =AF6*$E$63 -> -3331.3079 | AH24: =AG9-AG23 -> -41246.896
B25: 18 | C25: (Other investing flows) | D25: =Inputs!D67 -> 978 | E25: =Inputs!C67 -> -1948 | F25: =Inputs!B67 -> -646 | G25: =(1+G5)*AVERAGE(D25:F25) -> -539.50761 | H25: =(1+H5)*AVERAGE(E25:G25) -> -1146.545 | I25: =(1+I5)*AVERAGE(F25:H25) -> -855.08597 | J25: =(1+J5)*AVERAGE(G25:I25) -> -889.39852 | K25: =(1+K5)*AVERAGE(H25:J25) -> -1011.8603 | L25: =(1+L5)*AVERAGE(I25:K25) -> -964.72069 | M25: =(1+M5)*AVERAGE(J25:L25) -> -1003.0928 | N25: =(1+N5)*AVERAGE(K25:M25) -> -1042.8859 | ... AF25: =(1+AF5)*AVERAGE(AC25:AE25) -> -1287.593
B26: 19 | C26: -Total Investing Flows | D26: =D23+D24+D25 -> -3818 | E26: =E23+E24+E25 -> -7472 | F26: =F23+F24+F25 -> -7133 | G26: =G23+G24+G25 -> -6962.0576 | H26: =H23+H24+H25 -> -8196.545 | I26: =I23+I24+I25 -> -8610.086 | J26: =J23+J24+J25 -> -9032.1485 | K26: =K23+K24+K25 -> -9561.7478 | ... AF26: =AF23+AF24+AF25 -> -16944.74
B27: 20 | C27: (Flows related to leases) | D27: =Inputs!D71+Inputs!D72 -> 0 | E27: =Inputs!C71+Inputs!C72 -> 0 | F27: =Inputs!B71+Inputs!B72 -> 0 | G27: =G6*$D$66 -> 0 | H27: =H6*$D$66 -> 0 | I27: =I6*$D$66 -> 0 | J27: =J6*$D$66 -> 0 | K27: =$E$66*K6 -> 0 | L27: =$E$66*L6 -> 0 | M27: =$E$66*M6 -> 0 | N27: =$E$66*N6 -> 0 | O27: =$E$66*O6 -> 0 | P27: =$E$66*P6 -> 0 | Q27: =$E$66*Q6 -> 0 | R27: =$E$66*R6 -> 0 | ... AF27: =$E$66*AF6 -> 0
B28: 21 | C28: Flows related to debt | D28: =+SUM(Inputs!D69:D70) -> -2773 | E28: =+SUM(Inputs!C69:C70) -> -2304 | F28: =+SUM(Inputs!B69:B70) -> 1000 | G28: =G44-F44 -> -1563.6428 | H28: =H44-G44 -> 4714.9996 | I28: =I44-H44 -> 7498.6073 | J28: =J44-I44 -> -2203.1724 | K28: =K44-J44 -> 432.54596 | L28: =L44-K44 -> 2300.9023 | M28: =M44-L44 -> 2415.9474 | N28: =N44-M44 -> 2536.7448 | ... AF28: =AF44-AE44 -> 2796.7238
B29: 22 | C29: (Repurchases)/Issuance of stock | D29: ='Fin. Data'!D28 -> -500 | E29: ='Fin. Data'!C28 -> -3500 | F29: ='Fin. Data'!B28 -> -2250 | G29: =G6*$D$65 -> -1548.7 | H29: =H6*$D$65 -> -1700 | I29: =I6*$D$65 -> -1870 | J29: =J6*$D$65 -> -1963.5 | K29: =K6*$D$65 -> -2061.675 | L29: =L6*$D$65 -> -2164.7587 | M29: =M6*$D$65 -> -2272.9967 | N29: =N6*$D$65 -> -2386.6465 | ... AF29: =AF6*$D$65 -> -3775.4823
B30: 23 | C30: (Dividends) | D30: ='Fin. Data'!D27 -> -3437 | E30: ='Fin. Data'!C27 -> -5114 | F30: ='Fin. Data'!B27 -> -5372 | G30: =$D$64*G6 -> -4555 | H30: =$D$64*H6 -> -5000 | I30: =$D$64*I6 -> -5500 | J30: =$D$64*J6 -> -5775 | K30: =$D$64*K6 -> -6063.75 | L30: =$D$64*L6 -> -6366.9375 | M30: =$D$64*M6 -> -6685.2844 | N30: =$D$64*N6 -> -7019.5486 | ... AF30: =$D$64*AF6 -> -11104.36
B31: 24 | C31: Other financing flows | D31: =Inputs!D75 -> -113 | E31: =Inputs!C75 -> -267 | F31: =Inputs!B75 -> 1088 | G31: =(1+G5)*AVERAGE(D31:F31) -> 236.36843 | H31: =(1+H5)*AVERAGE(E31:G31) -> 386.88929 | I31: =(1+I5)*AVERAGE(F31:H31) -> 627.46117 | J31: =(1+J5)*AVERAGE(G31:I31) -> 437.75161 | K31: =(1+K5)*AVERAGE(H31:J31) -> 508.23572 | L31: =(1+L5)*AVERAGE(I31:K31) -> 550.70698 | M31: =(1+M5)*AVERAGE(J31:L31) -> 523.84301 | N31: =(1+N5)*AVERAGE(K31:M31) -> 553.975 | ... AF31: =(1+AF5)*AVERAGE(AC31:AE31) -> 688.3241
B32: 25 | C32: -Total Financing flows | D32: =D27+D28+D29+D30+D31 -> -6823 | E32: =E27+E28+E29+E30+E31 -> -11185 | F32: =F27+F28+F29+F30+F31 -> -5534 | G32: =G27+G28+G29+G30+G31 -> -7430.9744 | H32: =H27+H28+H29+H30+H31 -> -1598.1111 | I32: =I27+I28+I29+I30+I31 -> 756.06842 | J32: =J27+J28+J29+J30+J31 -> -9503.9208 | K32: =K27+K28+K29+K30+K31 -> -7184.6433 | ... AF32: =AF27+AF28+AF29+AF30+AF31 -> -11394.794
A34: SUMMARY | B34: 26 | C34: Cash before shareholder returns | D34: =D22+D26+D27+D28+D31 -> 8303 | E34: =E22+E26+E27+E28+E31 -> 4061 | F34: =F22+F26+F27+F28+F31 -> 5193 | G34: =G22+G26+G27+G28+G31 -> 3350.5098 | H34: =H22+H26+H27+H28+H31 -> 9911.7979 | I34: =I22+I26+I27+I28+I31 -> 15270.739 | J34: =J22+J26+J27+J28+J31 -> 4729.0999 | K34: =K22+K26+K27+K28+K31 -> 7292.6186 | ... AF34: =AF22+AF26+AF27+AF28+AF31 -> 28838.96
B35: 27 | C35: Returns to shareholders | D35: =-1*(D29+D30) -> 3937 | E35: =-1*(E29+E30) -> 8614 | F35: =-1*(F29+F30) -> 7622 | G35: =-1*(G29+G30) -> 6103.7 | H35: =-1*(H29+H30) -> 6700 | I35: =-1*(I29+I30) -> 7370 | J35: =-1*(J29+J30) -> 7738.5 | K35: =-1*(K29+K30) -> 8125.425 | ... AF35: =-1*(AF29+AF30) -> 14879.842
B36: 28 | C36: Excess cash acumulation | D36: =D34-D35 -> 4366 | E36: =E34-E35 -> -4553 | F36: =F34-F35 -> -2429 | G36: =G34-G35 -> -2753.1902 | H36: =H34-H35 -> 3211.7979 | I36: =I34-I35 -> 7900.7395 | J36: =J34-J35 -> -3009.4001 | K36: =K34-K35 -> -832.8064 | ... AF36: =AF34-AF35 -> 13959.118
A38: BALANCE SHEET | B38: 29 | C38: Intangible assets | D38: 7860 | E38: 6851 | F38: 6249 | G38: =+F38+(-G10) -> 6561.45 | H38: =+G38+(-H10) -> 6889.5225 | I38: =+H38+(-I10) -> 7233.9986 | J38: =+I38+(-J10) -> 7595.6986 | K38: =+J38+(-K10) -> 7975.4835 | L38: =+K38+(-L10) -> 8374.2577 | M38: =+L38+(-M10) -> 8792.9705 | N38: =+M38+(-N10) -> 9232.6191 | ... AF38: =+AE38+(-AF10) -> 22219.399 | AG38: =SUM(G38:AF38) -> 335378.37
B39: 30 | C39: Accumulated amortization | D39: =Assumptions!C101 -> 0 | E39: =Assumptions!Y18 -> PPE | F39: =Assumptions!Z18 -> 36945 | G39: =F39-G10 -> 37257.45 | H39: =G39-H10 -> 37585.522 | I39: =H39-I10 -> 37929.999 | J39: =I39-J10 -> 38291.699 | K39: =J39-K10 -> 38671.483 | L39: =K39-L10 -> 39070.258 | M39: =L39-M10 -> 39488.971 | N39: =M39-N10 -> 39928.619 | ... AF39: =AE39-AF10 -> 52915.399 | AG39: =SUM(G39:AF39) -> 1133474.4
B40: 31 | C40: PPE+Right of use Assets | D40: 37037 | E40: 38474 | F40: 41253 | G40: =F40+(-G23) -> 46309.05 | H40: =G40+(-H23) -> 51859.05 | I40: =H40+(-I23) -> 57964.05 | J40: =I40+(-J23) -> 64374.3 | K40: =J40+(-K23) -> 71105.062 | L40: =K40+(-L23) -> 78172.363 | M40: =L40+(-M23) -> 85593.029 | N40: =M40+(-N23) -> 93384.728 | ... AF40: =AE40+(-AF23) -> 279164.79 | AG40: =SUM(G40:AF40) -> 3876023.1
B41: 32 | C41: Accumulated depreciation | D41: =('[2]Income Statement'!$B$164-'[2]Income Statement'!$B$166)-D9 -> 5927.24 | E41: =D41-E9 -> 9115.24 | F41: =E41-F9 -> 12068.24 | G41: =F41-G9 -> 15285.974 | H41: =G41-H9 -> 18898.08 | I41: =H41-I9 -> 22943.086 | J41: =I41-J9 -> 27464.282 | K41: =J41-K9 -> 32485.477 | L41: =K41-L9 -> 38031.672 | ... AF41: =AE41-AF9 -> 295840.92 | AG41: =SUM(G41:AF41) -> 3105542.7
A43: CASH & DEBT & DISCOUNTING | B43: 33 | C43: Ending cash balance | D43: ='Fin. Data'!D39 -> 10255 | E43: =E36+D43 -> 5702 | F43: =F36+E43 -> 3273 | G43: =G36+F43 -> 519.80982 | H43: =H36+G43 -> 3731.6077 | I43: =I36+H43 -> 11632.347 | J43: =J36+I43 -> 8622.9471 | K43: =K36+J43 -> 7790.1407 | L43: =L36+K43 -> 9104.6035 | ... AF43: =AF36+AE43 -> 141354.78
B44: 34 | C44: Total Debt | D44: ='Fin. Data'!D58 -> 25528 | E44: ='Fin. Data'!C58 -> 23421 | F44: ='Fin. Data'!B58 -> 26729 | G44: =G12*($D$67+5%) -> 25165.357 | H44: =H12*$D$67 -> 29880.357 | I44: =I12*$D$67 -> 37378.964 | J44: =J12*$D$67 -> 35175.792 | K44: =K12*$E$67 -> 35608.338 | L44: =L12*$E$67 -> 37909.24 | M44: =M12*$E$67 -> 40325.187 | N44: =N12*$E$67 -> 42861.932 | O44: =O12*$E$67 -> 45085.389 | P44: =P12*$E$67 -> 47387.292 | Q44: =Q12*$E$67 -> 49770.421 | R44: =R12*$E$67 -> 52237.649 | ... AF44: =AF12*$E$67 -> 87972.082
B45: 35 | C45: Discount factor | F45: =1/((1+$F$50)^G50) -> 1 | G45: =1/((1+$F$50)^G49) -> 0.92165899 | H45: =1/((1+$F$50)^H49) -> 0.84945529 | I45: =1/((1+$F$50)^I49) -> 0.7829081 | J45: =1/((1+$F$50)^J49) -> 0.72157428 | K45: =1/((1+$F$50)^K49) -> 0.66504542 | L45: =1/((1+$F$50)^L49) -> 0.61294509 | M45: =1/((1+$F$50)^M49) -> 0.56492635 | N45: =1/((1+$F$50)^N49) -> 0.52066945 | ... AF45: =1/((1+$F$50)^AF49) -> 0.1199021
B46: 36 | C46: DF + 0.1% | E46: +0.1% | F46: =1/((1+$F$50+0.001)^G50) -> 1 | G46: =1/((1+$F$50+0.001)^G49) -> 0.92081031 | H46: =1/((1+$F$50+0.001)^H49) -> 0.84789163 | I46: =1/((1+$F$50+0.001)^I49) -> 0.78074736 | J46: =1/((1+$F$50+0.001)^J49) -> 0.71892022 | K46: =1/((1+$F$50+0.001)^K49) -> 0.66198915 | L46: =1/((1+$F$50+0.001)^L49) -> 0.60956644 | M46: =1/((1+$F$50+0.001)^M49) -> 0.56129506 | N46: =1/((1+$F$50+0.001)^N49) -> 0.51684628 | ... AF46: =1/((1+$F$50+0.001)^AF49) -> 0.11706432
B47: 37 | C47: DF+0.5% | E47: +0.5% | F47: =1/((1+$F$50+0.005)^G50) -> 1 | G47: =1/((1+$F$50+0.005)^G49) -> 0.91743119 | H47: =1/((1+$F$50+0.005)^H49) -> 0.84167999 | I47: =1/((1+$F$50+0.005)^I49) -> 0.77218348 | J47: =1/((1+$F$50+0.005)^J49) -> 0.70842521 | K47: =1/((1+$F$50+0.005)^K49) -> 0.64993139 | L47: =1/((1+$F$50+0.005)^L49) -> 0.59626733 | M47: =1/((1+$F$50+0.005)^M49) -> 0.54703424 | N47: =1/((1+$F$50+0.005)^N49) -> 0.50186628 | ... AF47: =1/((1+$F$50+0.005)^AF49) -> 0.10639251
A49: Discount Rate | C49: Risk free rate | D49: Equity premium | E49: Firm premium | F49: Total | G49: 1 | H49: 2 | I49: 3 | J49: 4 | K49: 5 | L49: 6 | M49: 7 | N49: 8 | O49: 9 | P49: 10 | Q49: 11 | R49: 12 | S49: 13 | T49: 14 | U49: 15 | V49: 16 | W49: 17 | X49: 18 | Y49: 19 | Z49: 20 | AA49: 21 | AB49: 22 | AC49: 23 | AD49: 24 | AE49: 25 | AF49: 26
C50: 0.04 | D50: 0.04 | E50: 0.005 | F50: =E50+D50+C50 -> 0.085 | G50: 0
A52: Modelling factors | D52: Short Term | E52: Long Term | F52: Reference (line)
C53: Depreciation factor | D53: =Assumptions!S17 -> -0.078 | E53: -0.078 | F53: =Assumptions!V17 -> % PPE
C54: Amortization factor | D54: =Assumptions!S18 -> -0.05 | E54: -0.05 | F54: =Assumptions!V18 -> % IA
C55: Stock-based comp | D55: =Assumptions!S19 -> 0 | E55: =Assumptions!T19 -> 0.03 | F55: =Assumptions!V19 -> % Revenue
C56: Tax Rate | D56: =Assumptions!S20 -> 0.22 | E56: =Assumptions!T20 -> 0.26 | F56: =Assumptions!V20 -> % EBT
C57: Interest Rate on debt | D57: =Assumptions!S21 -> 0.0275 | E57: =Assumptions!T21 -> 0.026 | F57: =Assumptions!V21 -> % Debt
C58: Interest Rate on cash | D58: 0.026 | E58: 0.0245 | F58: =Assumptions!V22 -> % Cash
C59: PPE+ROA | D59: =Assumptions!S23 -> - - | E59: =Assumptions!T23 -> - - | F59: =Assumptions!V23 -> Growing with CAPEX
C60: Working capital flows | D60: =Assumptions!S24 -> -0.038 | E60: =Assumptions!T24 -> -0.03 | F60: =Assumptions!V24 -> % Change in Revenues
C61: Intangible Assets | D61: =Assumptions!S25 -> - - | E61: =Assumptions!T25 -> - - | F61: =Assumptions!V25 -> Growing with Amortization
C62: Capex | D62: =Assumptions!S26 -> -0.0555 | E62: -0.0555 | F62: =Assumptions!V26 -> % Revenue
C63: Acquisition factor | D63: =Assumptions!S27 -> -0.015 | E63: -0.015 | F63: =Assumptions!V27 -> % Revenue
C64: Dividends | D64: =Assumptions!S28 -> -0.05 | E64: =Assumptions!T28 -> -0.07 | F64: =Assumptions!V28 -> % Revenue
C65: Repurchases | D65: =Assumptions!S29 -> -0.017 | E65: =Assumptions!T29 -> -0.025 | F65: =Assumptions!V29 -> % Revenue
C66: Leases | D66: =Assumptions!S30 -> 0 | E66: =Assumptions!T30 -> 0 | F66: =Assumptions!V30 -> % Revenue
C67: Total Debt | D67: =Assumptions!S31 -> 2 | E67: 1.9 | F67: =Assumptions!V31 -> % EBITDA
A69: Valuation | D69: $ millions
C70: Value of flows | D70: =SUMPRODUCT(G35:AF35,G45:AF45)+((AF43-AF44)*AF45) -> 105417.25 | E70: =D70/D72 -> 0.66461097
C71: Value of perpetuity | D71: =(AF34/(F50-AF5))*AF45 -> 53197.724 | E71: =D71/D72 -> 0.33538903
C72: Total Value | D72: =D70+D71 -> 158614.98
C73: Actual share price | D73: =OP!C20 -> #VALUE!
C74: Total value vs Mkt Cap | D74: =D75/D73-1 -> #VALUE!
C75: Estimated NPV per share | D75: =D72*1000000/OP!C21 -> #VALUE!
A77: Sensibility | C77: Sensitivity +0.1% | D77: =(SUMPRODUCT(G35:AF35,G45:AF45)+((AF43-AF44)*AF45)+(AF34/(F50+0.001-AF5))*AF45)*1000000/OP!C21 -> #VALUE! | E77: =D77/D75-1 -> #VALUE!
C78: Sensitivity +0.5% | D78: =(SUMPRODUCT(G35:AF35,G45:AF45)+((AF43-AF44)*AF45)+(AF34/(F50+0.005-AF5))*AF45)*1000000/OP!C21 -> #VALUE! | E78: =D78/D75-1 -> #VALUE!
A80: Notes | C80: Price where it'd be a "BUY" | D80: =D75/1.15 -> #VALUE!

Sheet Assumptions
B2: Assumptions
B4: Prospects:
B6: Links:
C8: 2023 | D8: =C8-1 -> 2022 | E8: =D8-1 -> 2021 | F8: =E8-1 -> 2020 | G8: =F8-1 -> 2019 | H8: =G8-1 -> 2018 | I8: =H8-1 -> 2017 | J8: =I8-1 -> 2016 | K8: =J8-1 -> 2015 | ... M8: =L8-1 -> 2013 | O8: 10Y Average | P8: 5Y Average | Q8: 3Y Average | S8: Short Term Forecast | T8: Long Term Forecast
B9: Revenue growth | C9: =(Inputs!B6-Inputs!C6)/Inputs!C6 -> -0.093484024 | D9: =(Inputs!C6-Inputs!D6)/Inputs!D6 -> 0.031360819 | E9: =(Inputs!D6-Inputs!E6)/Inputs!E6 -> 0.14958406 | F9: =(Inputs!E6-Inputs!F6)/Inputs!F6 -> 0.14217076 | G9: =(Inputs!F6-Inputs!G6)/Inputs!G6 -> 0.031073879 | H9: =(Inputs!G6-Inputs!H6)/Inputs!H6 -> 0.090918752 | I9: =(Inputs!H6-Inputs!I6)/Inputs!I6 -> 0.081535481 | J9: =(Inputs!I6-Inputs!J6)/Inputs!J6 -> 0.043572126 | ... M9: =(Inputs!L6-Inputs!M6)/Inputs!M6 -> 0.024220814 | O9: =AVERAGE(C9:M9) -> 0.050327357 | P9: =AVERAGE(C9:G9) -> 0.052141098 | Q9: =AVERAGE(C9:E9) -> 0.029153619 | S9: 0.035 | T9: 0.05
B10: Operating Margin | C10: =Inputs!B8/Inputs!B6 -> 0.10049693 | D10: =Inputs!C8/Inputs!C6 -> 0.13049891 | E10: =Inputs!D8/Inputs!D6 -> 0.13167227 | F10: =Inputs!E8/Inputs!E6 -> 0.090797372 | G10: =Inputs!F8/Inputs!F6 -> 0.10524469 | H10: =Inputs!G8/Inputs!G6 -> 0.097744256 | I10: =Inputs!H8/Inputs!H6 -> 0.11429743 | J10: =Inputs!I8/Inputs!I6 -> 0.089761271 | ... M10: =Inputs!L8/Inputs!L6 -> 0.12688048 | O10: =AVERAGE(C10:M10) -> 0.10946292 | P10: =AVERAGE(C10:G10) -> 0.11174204 | Q10: =AVERAGE(C10:E10) -> 0.12088937 | S10: 0.116 | T10: 0.108
B13: Modelling Factors
C15: Last 10 Years
C16: =C8 -> 2023 | D16: =D8 -> 2022 | E16: =E8 -> 2021 | F16: =F8 -> 2020 | G16: =G8 -> 2019 | H16: =H8 -> 2018 | I16: =I8 -> 2017 | J16: =J8 -> 2016 | ... M16: =M8 -> 2013 | O16: =O8 -> 10Y Average | P16: =P8 -> 5Y Average | Q16: =Q8 -> 3Y Average | S16: Short Term Forecast | T16: Long Term Forecast | V16: Reference
B17: Depreciation factor | C17: =DCF!F9/DCF!F40 -> -0.071582673 | D17: =DCF!E9/DCF!E40 -> -0.082861153 | E17: =DCF!D9/DCF!D40 -> -0.090882091 | F17: =-('[2]Income Statement'!$B$164-'[2]Income Statement'!$B$166)/'Fin. Data'!B42 -> -0.069325754 | G17: =-('[2]Income Statement'!$B$164-'[2]Income Statement'!$B$166)/'Fin. Data'!C42 -> -0.073770558 | H17: =-('[2]Income Statement'!$B$164-'[2]Income Statement'!$B$166)/'Fin. Data'!D42 -> -0.076512024 | I17: =-('[2]Income Statement'!$B$164-'[2]Income Statement'!$B$166)/'Fin. Data'!E42 -> -0.079408445 | J17: =-('[2]Income Statement'!$B$164-'[2]Income Statement'!$B$166)/'Fin. Data'!F42 -> -0.08402467 | K17: =-('[2]Income Statement'!$B$164-'[2]Income Statement'!$B$166)/'Fin. Data'!G42 -> -0.096374172 | L17: =-('[2]Income Statement'!$B$164-'[2]Income Statement'!$B$166)/'Fin. Data'!H42 -> -0.1157989 | M17: =-('[2]Income Statement'!$B$164-'[2]Income Statement'!$B$166)/'Fin. Data'!I42 -> -0.13623617 | O17: =AVERAGE(C17:M17) -> -0.088797873 | P17: =AVERAGE(C17:G17) -> -0.077684446 | Q17: =AVERAGE(C17:E17) -> -0.081775306 | S17: -0.078 | T17: -0.085 | V17: % PPE | Z17: 2023 | AA17: 2022 | AB17: 2021 | AC17: 2020 | AD17: 2019 | AE17: 2018 | AF17: 2017 | AG17: 2016 | AI17: 2015 | AJ17: 2014 | AK17: 2013 | AL17: 2012
B18: Amortization factor | C18: =-Z23/Z21 -> -0.063613232 | D18: =-AA23/AA21 -> -0.042621515 | E18: =-AB23/AB21 -> -0.047047528 | F18: =-AC23/AC21 -> -0.050322131 | G18: =-AD23/AD21 -> -0.058537498 | H18: =-AE23/AE21 -> -0.051183492 | I18: =-AF23/AF21 -> -0.041284404 | J18: =-AG23/AG21 -> -0.035620368 | K18: - | L18: =-AJ23/AJ21 -> -0.046340684 | M18: =-AK23/AK21 -> -0.04532967 | O18: =AVERAGE(C18:M18) -> -0.048190052 | P18: =AVERAGE(C18:G18) -> -0.052428381 | Q18: =AVERAGE(C18:E18) -> -0.051094091 | S18: -0.05 | T18: -0.047 | V18: % IA | Y18: PPE | Z18: 36945 | AA18: 34719 | AB18: 33475 | AC18: 32245 | AD18: 30842 | AE18: 26576 | AF18: 22118 | AG18: 18800 | AI18: 18352 | AJ18: 18281 | AK18: 17961
B19: Stock-based comp | C19: =DCF!F11/DCF!F6 -> 0 | D19: =DCF!E11/DCF!E6 -> 0 | E19: =DCF!D11/DCF!D6 -> 0 | F19: 0 | G19: 0 | H19: 0 | I19: 0 | J19: 0 | K19: 0 | L19: 0 | M19: 0 | O19: =AVERAGE(C19:M19) -> 0 | P19: =AVERAGE(C19:G19) -> 0 | Q19: =AVERAGE(C19:E19) -> 0 | S19: 0 | T19: 0.03 | V19: % Revenue | Y19: ROA | Z19: 4308 | AA19: 3755 | AB19: 3562 | AC19: 3073 | AD19: 3073 | AE19: 3073 | AF19: 3073 | AG19: - | AI19: - | AJ19: - | AK19: - | AL19: -
B20: Tax Rate | C20: 0.218 | D20: 0.221 | E20: 0.223 | F20: 0.272 | G20: 0.214 | H20: 0.204 | I20: 0.313 | J20: 0.332 | K20: 0.34 | L20: 0.346 | M20: 0.345 | O20: =AVERAGE(C20:M20) -> 0.27527273 | P20: =AVERAGE(C20:G20) -> 0.2296 | Q20: =AVERAGE(C20:E20) -> 0.22066667 | S20: 0.22 | T20: 0.26 | V20: % EBT | Y20: Dep | Z20: =Z24-Z23 -> -500
B21: Interest Rate on debt | C21: =785/'Fin. Data'!B58 -> 0.02936885 | D21: =704/'Fin. Data'!C58 -> 0.030058495 | E21: =694/'Fin. Data'!D58 -> 0.027185835 | F21: =701/'Fin. Data'!E58 -> 0.025257621 | G21: =653/'Fin. Data'!F58 -> 0.023183158 | H21: =605/'Fin. Data'!G58 -> 0.026609782 | I21: =453/'Fin. Data'!H58 -> 0.018650418 | J21: =381/'Fin. Data'!I58 -> 0.0237014 | K21: =341/'Fin. Data'!J58 -> 0.023789591 | L21: =353/'Fin. Data'!K58 -> 0.032724576 | M21: =380/'Fin. Data'!L58 -> 0.034952171 | O21: =AVERAGE(C21:M21) -> 0.02686199 | P21: =AVERAGE(C21:G21) -> 0.027010792 | Q21: =AVERAGE(C21:E21) -> 0.02887106 | S21: 0.0275 | T21: 0.026 | V21: % Debt | Y21: Intang. Assets | Z21: 7860 | AA21: 6851 | AB21: 6249 | AC21: 5743 | AD21: 5347 | AE21: 4943 | AF21: 4578 | AG21: 4183 | AI21: 3825 | AJ21: 3129 | AK21: 2912 | AL21: 2608
B22: Interest Rate on cash | C22: 0 | D22: 0 | E22: 0 | F22: 0 | G22: 0 | H22: 0 | I22: 0 | J22: 0 | K22: 0 | L22: 0 | M22: 0 | O22: =AVERAGE(C22:M22) -> 0 | P22: =AVERAGE(C22:G22) -> 0 | Q22: =AVERAGE(C22:E22) -> 0 | S22: 0 | T22: 0 | V22: % Cash | Y22: Amort. accumulated | Z22: 4555 | AA22: 4055 | AB22: 3763 | AC22: 3469 | AD22: 3180 | AE22: 2867 | AF22: 2614 | AG22: 2425 | AI22: 2276 | AJ22: 2282 | AK22: 2137 | AL22: 2005
B23: PPE+ROA | C23: =Inputs!B33/Inputs!C33-1 -> 0.06411475 | D23: =Inputs!C33/Inputs!D33-1 -> 0.037162061 | E23: =Inputs!D33/Inputs!E33-1 -> 0.03785577 | F23: =Inputs!E33/Inputs!F33-1 -> 0.058132668 | G23: =Inputs!F33/Inputs!G33-1 -> 0.14697471 | H23: =Inputs!G33/Inputs!H33-1 -> 0.20155529 | I23: =Inputs!H33/Inputs!I33-1 -> 0.17648936 | J23: =Inputs!I33/Inputs!J33-1 -> 0.024411508 | ... M23: =Inputs!L33/Inputs!M33-1 -> 0.0037442718 | O23: =AVERAGE(C23:M23) -> 0.070194599 | P23: =AVERAGE(C23:G23) -> 0.068847993 | Q23: =AVERAGE(C23:E23) -> 0.046377527 | S23: - - | T23: - - | V23: Growing with CAPEX | Y23: Amort. | Z23: =Z22-AA22 -> 500 | AA23: =AA22-AB22 -> 292 | AB23: =AB22-AC22 -> 294 | AC23: =AC22-AD22 -> 289 | AD23: =AD22-AE22 -> 313 | AE23: =AE22-AF22 -> 253 | AF23: =2614-2425 -> 189 | AG23: =2425-2276 -> 149 | AI23: =AI22-AJ22 -> -6 | AJ23: =AJ22-AK22 -> 145 | AK23: =AK22-AL22 -> 132
B24: Working capital flows | C24: =Inputs!B62/(Inputs!B6-Inputs!C6) -> 0.054797441 | D24: =Inputs!C62/(Inputs!C6-Inputs!D6) -> -0.11897738 | E24: =Inputs!D62/(Inputs!D6-Inputs!E6) -> -0.050714906 | F24: =Inputs!E62/(Inputs!E6-Inputs!F6) -> 0.10062654 | G24: =Inputs!F62/(Inputs!F6-Inputs!G6) -> 0.069861173 | H24: =Inputs!G62/(Inputs!G6-Inputs!H6) -> 0.34362999 | I24: =Inputs!H62/(Inputs!H6-Inputs!I6) -> -0.28453484 | J24: =Inputs!I62/(Inputs!I6-Inputs!J6) -> -0.28863547 | ... M24: =Inputs!L62/(Inputs!L6-Inputs!M6) -> -0.13272311 | O24: =AVERAGE(C24:M24) -> -0.23044864 | P24: =AVERAGE(C24:G24) -> 0.011118573 | Q24: =AVERAGE(C24:E24) -> -0.038298283 | S24: -0.038 | T24: -0.03 | V24: % Change in Revenues | Y24: Dep & Amort
B25: Intangible Assets | C25: =DCF!F38/DCF!E38-1 -> -0.087870384 | D25: =DCF!E38/DCF!D38-1 -> -0.1283715 | E25: =AB21/AC21-1 -> 0.088107261 | F25: =AC21/AD21-1 -> 0.074060221 | G25: =AD21/AE21-1 -> 0.081731742 | H25: =AE21/AF21-1 -> 0.079729139 | I25: =AF21/AG21-1 -> 0.094429835 | J25: =AG21/AI21-1 -> 0.093594771 | K25: =AI21/AJ21-1 -> 0.22243528 | L25: =AJ21/AK21-1 -> 0.074519231 | M25: =AK21/AL21-1 -> 0.11656442 | O25: =AVERAGE(C25:M25) -> 0.064448183 | P25: =AVERAGE(C25:G25) -> 0.0055314677 | Q25: =AVERAGE(C25:E25) -> -0.042711541 | S25: - - | T25: - - | V25: Growing with Amortization
B26: CAPEX | C26: =Inputs!B65/Inputs!B6 -> -0.056707491 | D26: =Inputs!C65/Inputs!C6 -> -0.047529351 | E26: =Inputs!D65/Inputs!D6 -> -0.043109562 | F26: =Inputs!E65/Inputs!E6 -> -0.063950466 | G26: =Inputs!F65/Inputs!F6 -> -0.086106837 | H26: =Inputs!G65/Inputs!G6 -> -0.086806474 | I26: =Inputs!H65/Inputs!H6 -> -0.079350862 | J26: =Inputs!I65/Inputs!I6 -> -0.048681575 | ... M26: =Inputs!L65/Inputs!L6 -> -0.037248818 | O26: =AVERAGE(C26:M26) -> -0.05729378 | P26: =AVERAGE(C26:G26) -> -0.059480741 | Q26: =AVERAGE(C26:E26) -> -0.049115468 | S26: -0.0555 | T26: -0.07 | V26: % Revenue
B27: Acquisition factor | C27: =Inputs!B66/Inputs!B6 -> -0.014611139 | D27: =Inputs!C66/Inputs!C6 -> -0.007524567 | E27: =Inputs!D66/Inputs!D6 -> -0.0061878771 | F27: =Inputs!E66/Inputs!E6 -> -0.0002363284 | G27: =Inputs!F66/Inputs!F6 -> -8.0978217e-05 | H27: =Inputs!G66/Inputs!G6 -> -2.7831508e-05 | I27: =Inputs!H66/Inputs!H6 -> -0.0020342482 | J27: =Inputs!I66/Inputs!I6 -> -0.0089810528 | ... M27: =Inputs!L66/Inputs!L6 -> -0.0032288322 | O27: =AVERAGE(C27:M27) -> -0.0040462508 | P27: =AVERAGE(C27:G27) -> -0.005728178 | Q27: =AVERAGE(C27:E27) -> -0.0094411944 | S27: -0.015 | T27: -0.03 | V27: % Revenue
B28: Dividends | C28: =Inputs!B73/Inputs!B6 -> -0.059060226 | D28: =Inputs!C73/Inputs!C6 -> -0.050967729 | E28: =Inputs!D73/Inputs!D6 -> -0.035328461 | F28: =Inputs!E73/Inputs!E6 -> -0.039868601 | G28: =Inputs!F73/Inputs!F6 -> -0.043107404 | H28: =Inputs!G73/Inputs!G6 -> -0.041900335 | I28: =Inputs!H73/Inputs!H6 -> -0.042066432 | J28: =Inputs!I73/Inputs!I6 -> -0.043394739 | ... M28: =Inputs!L73/Inputs!L6 -> -0.040766261 | O28: =AVERAGE(C28:M28) -> -0.043668589 | P28: =AVERAGE(C28:G28) -> -0.045666484 | Q28: =AVERAGE(C28:E28) -> -0.048452139 | S28: -0.05 | T28: -0.07 | V28: % Revenue
B29: Repurchases | C29: =Inputs!B74/Inputs!B6 -> -0.024736692 | D29: =Inputs!C74/Inputs!C6 -> -0.034882099 | E29: =Inputs!D74/Inputs!D6 -> -0.0051394328 | F29: =Inputs!E74/Inputs!E6 -> -0.0026468781 | G29: =Inputs!F74/Inputs!F6 -> -0.013550355 | H29: =Inputs!G74/Inputs!G6 -> -0.014068827 | I29: =Inputs!H74/Inputs!H6 -> -0.027523075 | J29: =Inputs!I74/Inputs!I6 -> -0.043969395 | ... M29: =Inputs!L74/Inputs!L6 -> -0.069230492 | O29: =AVERAGE(C29:M29) -> -0.029847645 | P29: =AVERAGE(C29:G29) -> -0.016191091 | Q29: =AVERAGE(C29:E29) -> -0.021586074 | S29: -0.017 | T29: -0.025 | V29: % Revenue
B30: Leases | C30: =Inputs!B72/Inputs!B6 -> 0 | D30: =Inputs!C72/Inputs!C6 -> 0 | E30: =Inputs!D72/Inputs!D6 -> 0 | F30: =Inputs!E72/Inputs!E6 -> 0 | G30: =Inputs!F72/Inputs!F6 -> 0 | H30: =Inputs!G72/Inputs!G6 -> 0 | I30: =Inputs!H72/Inputs!H6 -> 0 | J30: =Inputs!I72/Inputs!I6 -> 0 | ... M30: =Inputs!L72/Inputs!L6 -> 0 | O30: =AVERAGE(C30:M30) -> 0 | P30: =AVERAGE(C30:G30) -> 0 | Q30: =AVERAGE(C30:E30) -> 0 | S30: 0 | T30: 0 | V30: % Revenue
B31: Total Debt | C31: ='Fin. Data'!B58/'Fin. Data'!B19 -> 2.1371232 | D31: ='Fin. Data'!C58/'Fin. Data'!C19 -> 1.6914133 | E31: ='Fin. Data'!D58/'Fin. Data'!D19 -> 2.2623183 | F31: ='Fin. Data'!E58/'Fin. Data'!E19 -> 1.788158 | G31: ='Fin. Data'!F58/'Fin. Data'!F19 -> 2.4175607 | H31: ='Fin. Data'!G58/'Fin. Data'!G19 -> 2.3607102 | I31: ='Fin. Data'!H58/'Fin. Data'!H19 -> 2.4939932 | J31: ='Fin. Data'!I58/'Fin. Data'!I19 -> 2.1037822 | ... M31: ='Fin. Data'!L58/'Fin. Data'!L19 -> 1.2241865 | O31: =AVERAGE(C31:M31) -> 1.9565228 | P31: =AVERAGE(C31:G31) -> 2.0593147 | Q31: =AVERAGE(C31:E31) -> 2.0302849 | S31: 2 | T31: 1.95 | V31: % EBITDA
B34: Forecasts
B41: Base Scenario | C41: Time Period (Years) | E41: 2024 | F41: =E41+1 -> 2025 | G41: =F41+1 -> 2026 | H41: =G41+1 -> 2027 | I41: =H41+1 -> 2028 | J41: =I41+1 -> 2029 | K41: =J41+1 -> 2030 | L41: =K41+1 -> 2031 | M41: =L41+1 -> 2032 | ... AD41: =AC41+1 -> 2049
C42: Forecasted Revenues Growth | E42: =E43/DCF!F6-1 -> 0.0015611601 | F42: =F43/E43-1 -> 0.097694841 | G42: =G43/F43-1 -> 0.1 | H42: 0.05 | I42: 0.05 | J42: 0.05 | K42: 0.05 | L42: 0.05 | M42: 0.035 | N42: 0.035 | O42: 0.035 | P42: 0.035 | Q42: 0.035 | R42: 0.035 | S42: 0.035 | T42: 0.02 | U42: 0.02 | V42: 0.02 | W42: 0.02 | X42: 0.02 | Y42: 0.02 | Z42: 0.02 | AA42: 0.02 | AB42: 0.02 | AC42: 0.02 | AD42: 0.02
C43: Forecasted Yearly Revenues | E43: 91100 | F43: 100000 | G43: 110000 | H43: =G43*(1+H42) -> 115500 | I43: =H43*(1+I42) -> 121275 | J43: =I43*(1+J42) -> 127338.75 | K43: =J43*(1+K42) -> 133705.69 | L43: =K43*(1+L42) -> 140390.97 | M43: =L43*(1+M42) -> 145304.66 | N43: =M43*(1+N42) -> 150390.32 | O43: =N43*(1+O42) -> 155653.98 | ... AD43: =AC43*(1+AD42) -> 222087.19
C44: Forecasted Operating Margin | E44: 0.096 | F44: 0.11 | G44: 0.13 | H44: 0.11 | I44: 0.11 | J44: 0.11 | K44: 0.11 | L44: 0.11 | M44: 0.11 | N44: 0.11 | O44: 0.11 | P44: 0.11 | Q44: 0.11 | R44: 0.11 | S44: 0.11 | T44: 0.11 | U44: 0.11 | V44: 0.11 | W44: 0.11 | X44: 0.11 | Y44: 0.11 | Z44: 0.11 | AA44: 0.11 | AB44: 0.11 | AC44: 0.11 | AD44: 0.11
B46: Bullish Scenario | C46: Time Period (Years) | E46: 2024 | F46: =E46+1 -> 2025 | G46: =F46+1 -> 2026 | H46: =G46+1 -> 2027 | I46: =H46+1 -> 2028 | J46: =I46+1 -> 2029 | K46: =J46+1 -> 2030 | L46: =K46+1 -> 2031 | M46: =L46+1 -> 2032 | ... AD46: =AC46+1 -> 2049
C47: Forecasted Yearly Revenues | E47: 0.03 | F47: 0.12 | G47: 0.125 | H47: 0.08 | I47: 0.08 | J47: 0.08 | K47: 0.08 | L47: 0.08 | M47: 0.05 | N47: 0.05 | O47: 0.05 | P47: 0.05 | Q47: 0.05 | R47: 0.05 | S47: 0.05 | T47: 0.03 | U47: 0.03 | V47: 0.03 | W47: 0.03 | X47: 0.03 | Y47: 0.03 | Z47: 0.03 | AA47: 0.03 | AB47: 0.03 | AC47: 0.03 | AD47: 0.03
C48: Forecasted Revenues Growth | E48: 100000 | F48: =E48*(1+F47) -> 112000 | G48: =F48*(1+G47) -> 126000 | H48: =G48*(1+H47) -> 136080 | I48: =H48*(1+I47) -> 146966.4 | J48: =I48*(1+J47) -> 158723.71 | K48: =J48*(1+K47) -> 171421.61 | L48: =K48*(1+L47) -> 185135.34 | M48: =L48*(1+M47) -> 194392.1 | ... AD48: =AC48*(1+AD47) -> 360598.48
C49: Forecasted Operating Margin | E49: 0.11 | F49: 0.13 | G49: 0.15 | H49: 0.13 | I49: 0.13 | J49: 0.13 | K49: 0.13 | L49: 0.13 | M49: 0.13 | N49: 0.13 | O49: 0.13 | P49: 0.13 | Q49: 0.13 | R49: 0.13 | S49: 0.13 | T49: 0.13 | U49: 0.13 | V49: 0.13 | W49: 0.13 | X49: 0.13 | Y49: 0.13 | Z49: 0.13 | AA49: 0.13 | AB49: 0.13 | AC49: 0.13 | AD49: 0.13
B51: Bearish Scenario | C51: Time Period (Years) | E51: 2024 | F51: =E51+1 -> 2025 | G51: =F51+1 -> 2026 | H51: =G51+1 -> 2027 | I51: =H51+1 -> 2028 | J51: =I51+1 -> 2029 | K51: =J51+1 -> 2030 | L51: =K51+1 -> 2031 | M51: =L51+1 -> 2032 | ... AD51: =AC51+1 -> 2049
C52: Forecasted Yearly Revenues | E52: 0 | F52: 0.07 | G52: 0.06 | H52: 0.03 | I52: 0.03 | J52: 0.03 | K52: 0.03 | L52: 0.03 | M52: 0.02 | N52: 0.02 | O52: 0.02 | P52: 0.02 | Q52: 0.02 | R52: 0.02 | S52: 0.02 | T52: 0.01 | U52: 0.01 | V52: 0.01 | W52: 0.01 | X52: 0.01 | Y52: 0.01 | Z52: 0.01 | AA52: 0.01 | AB52: 0.005 | AC52: 0.005 | AD52: 0.005
C53: Forecasted Revenues Growth | E53: 80000 | F53: =E53*(1+F52) -> 85600 | G53: =F53*(1+G52) -> 90736 | H53: =G53*(1+H52) -> 93458.08 | I53: =H53*(1+I52) -> 96261.822 | J53: =I53*(1+J52) -> 99149.677 | K53: =J53*(1+K52) -> 102124.17 | L53: =K53*(1+L52) -> 105187.89 | M53: =L53*(1+M52) -> 107291.65 | ... AD53: =AC53*(1+AD52) -> 132811.64
C54: Forecasted Operating Margin | E54: 0.08 | F54: 0.09 | G54: 0.1 | H54: 0.05 | I54: 0.05 | J54: 0.05 | K54: 0.05 | L54: 0.05 | M54: 0.05 | N54: 0.05 | O54: 0.05 | P54: 0.05 | Q54: 0.05 | R54: 0.05 | S54: 0.05 | T54: 0.05 | U54: 0.05 | V54: 0.05 | W54: 0.05 | X54: 0.05 | Y54: 0.05 | Z54: 0.05 | AA54: 0.05 | AB54: 0.05 | AC54: 0.05 | AD54: 0.05
B57: Maturity Year | C57: 2024 | D57: 2025 | E57: 2026 | F57: 2027 | G57: 2028 | H57: 2029 | I57: 2030 | J57: 2031 | L57: 2032 | M57: 2033 | N57: 2034 | O57: 2035 | P57: 2036 | Q57: 2037 | R57: 2038 | S57: 2039 | T57: 2040 | U57: 2041 | V57: 2042 | W57: 2043 | X57: 2044 | Y57: 2045 | Z57: 2046 | AA57: 2047 | AB57: 2048 | AC57: 2049 | AD57: 2050 | AE57: 2051 | AF57: 2052 | AG57: 2053 | AH57: 2054
B58: Bonds | C58: =SUM(E65:G66)+E89 -> 1467 | D58: =E67+E86 -> 1775 | E58: =E68 -> 500 | F58: =E69 -> 1000 | G58: =E87 -> 554 | H58: =E70+E71 -> 1150 | I58: =E72 -> 750 | J58: =E84 -> 85 | L58: =E88 -> 554 | M58: =E73 -> 900 | N58: 0 | O58: 0 | P58: 0 | Q58: 0 | R58: =E74 -> 1500 | S58: 0 | T58: =SUM(E75:G76) -> 1000 | U58: 0 | V58: =E77 -> 375 | W58: 0 | X58: 0 | Y58: 0 | Z58: =E78 -> 500 | AA58: =E79 -> 1150 | AB58: 0 | AC58: =SUM(E80:G81) -> 1450 | AD58: =E82+E85 -> 1829 | AE58: 0 | AF58: 0 | AG58: =E83 -> 1100 | AH58: 0
B59: Loans
B60: Forecasted Debt
B61: Expected Interest Expenses | C61: =J90 -> 684.4225 | D61: =C61-SUM(J65:K66)-J89 -> 649.57375 | E61: =D61-J67-J86 -> 597.98 | F61: =E61-J68 -> 585.98 | G61: =F61-J69 -> 555.48 | H61: =G61-J87 -> 549.94 | I61: =H61-SUM(J70:K71) -> 514.44 | J61: =I61-J72 -> 481.1025 | L61: =J61-J84 -> 476.4275 | M61: =L61-J88 -> 468.1175 | N61: =M61-J73 -> 424.2425 | O61: =N61 -> 424.2425 | P61: =O61 -> 424.2425 | Q61: =P61 -> 424.2425 | R61: =Q61 -> 424.2425 | S61: =R61-J74 -> 331.2425 | T61: =S61 -> 331.2425 | U61: =T61-SUM(J75:K76) -> 280.8675 | V61: =U61 -> 280.8675 | W61: =V61-J77 -> 267.27375 | X61: =W61 -> 267.27375 | Y61: =X61 -> 267.27375 | Z61: =Y61 -> 267.27375 | AA61: =Z61-J78 -> 250.27375 | AB61: =AA61-J79 -> 207.14875 | AC61: =AB61-L78 -> 207.14875 | AD61: =AC61-J80-J81 -> 151.47375 | AE61: =AD61-J82-J85 -> 55.55 | AF61: =AE61 -> 55.55 | AG61: =AF61 -> 55.55 | AH61: =AG61-J83 -> -6.3948846e-14
B62: Total Debt | C62: =E90 -> 17639 | D62: =C62-D58 -> 15864 | E62: =D62-E58 -> 15364 | F62: =E62-F58 -> 14364 | G62: =F62-G58 -> 13810 | H62: =G62-H58 -> 12660 | I62: =H62-I58 -> 11910 | J62: =I62-J58 -> 11825 | L62: =J62-L58 -> 11271 | M62: =L62-M58 -> 10371 | N62: =M62-N58 -> 10371 | O62: =N62-O58 -> 10371 | P62: =O62-P58 -> 10371 | Q62: =P62-Q58 -> 10371 | R62: =Q62-R58 -> 8871 | S62: =R62-S58 -> 8871 | T62: =S62-T58 -> 7871 | ... AH62: =AG62-AH58 -> 1467
B64: Maturity Date | C64: Amount Outstanding | E64: Issued Amount | H64: Interest Rate (%) | J64: Interest Expense | L64: (millions)
B65: 2024 | E65: 500 | H65: 0.028 | J65: =H65*E65 -> 14
B66: 2024 | E66: 400 | H66: 0.022 | J66: =H66*E66 -> 8.8
B67: 2025 | E67: 1000 | H67: 0.039 | J67: =H67*E67 -> 39
B68: 2026 | E68: 500 | H68: 0.024 | J68: =H68*E68 -> 12
B69: 2027 | E69: 1000 | H69: 0.0305 | J69: =H69*E69 -> 30.5
B70: 2029 | E70: 750 | H70: 0.034 | J70: 0
B71: 2029 | E71: 400 | H71: 0.025 | J71: 35.5
B72: 2030 | E72: 750 | H72: 0.04445 | J72: =H72*E72 -> 33.3375
B73: 2033 | E73: 900 | H73: 0.04875 | J73: =H73*E73 -> 43.875
B74: 2038 | E74: 1500 | H74: 0.062 | J74: =H74*E74 -> 93
B75: 2040 | E75: 500 | H75: 0.052 | J75: =H75*E75 -> 26
B76: 2040 | E76: 500 | H76: 0.04875 | J76: =H76*E76 -> 24.375
B77: 2042 | E77: 375 | H77: 0.03625 | J77: =H77*E77 -> 13.59375
B78: 2046 | E78: 500 | H78: 0.034 | J78: =H78*E78 -> 17
B79: 2047 | E79: 1150 | H79: 0.0375 | J79: =H79*E79 -> 43.125
B80: 2049 | E80: 750 | H80: 0.0425 | J80: =H80*E80 -> 31.875
B81: 2049 | E81: 700 | H81: 0.034 | J81: =H81*E81 -> 23.8
B82: 2050 | E82: 1250 | H82: 0.053 | J82: =H82*E82 -> 66.25
B83: 2053 | E83: 1100 | H83: 0.0505 | J83: =H83*E83 -> 55.55
A84: GBP | B84: 2031 | E84: 85 | H84: 0.055 | J84: =H84*E84 -> 4.675
B85: 2050 | E85: 579 | H85: 0.05125 | J85: =H85*E85 -> 29.67375
A86: EUR | B86: 2025 | E86: 775 | H86: 0.01625 | J86: =H86*E86 -> 12.59375
B87: 2028 | E87: 554 | H87: 0.01 | J87: =H87*E87 -> 5.54
B88: 2032 | E88: 554 | H88: 0.015 | J88: =H88*E88 -> 8.31
A89: CAD | B89: 2024 | E89: 567 | H89: 0.02125 | J89: =H89*E89 -> 12.04875
B90: Total | E90: =SUM(E65:G89) -> 17639 | H90: =SUM(H65:I89) -> 0.91495 | J90: =SUM(J65:K89) -> 684.4225
B113: Revenue per Segment
B116: % of Total Revenue | J116: REVENUES PROSPECTS
J117: New techonogy big aquisitions, mainly robots, which will decrease costs and increase immensely productivity: plan "Network of the Future": 6B each year, for 3 years total. Decrease in oil prices. Biggest healthcare logistics supplier worldwide : aquisitions.
C118: 2023 | D118: 2022 | E118: 2021 | F118: 2020 | G118: 2019 | H118: Average 5y
B119: US Domestic Package | C119: =C130/C133 -> 0.65918336 | D119: =D130/D133 -> 0.63992705 | E119: =E130/E133 -> 0.61999034 | F119: =F130/F133 -> 0.63216666 | G119: =G130/G133 -> 0.62748671 | H119: =SUM(C119:G119)/5 -> 0.63575082
B120: International Package | C120: =C131/C133 -> 0.19603553 | D120: =D131/D133 -> 0.19631645 | E120: =E131/E133 -> 0.20085931 | F120: =F131/F133 -> 0.18841282 | G120: =G131/G133 -> 0.19191837 | H120: =SUM(C120:G120)/5 -> 0.1947085
B121: Supply Chain Solutions | C121: =C132/C133 -> 0.14478111 | D121: =D132/D133 -> 0.1637565 | E121: =E132/E133 -> 0.17915035 | F121: =F132/F133 -> 0.17942052 | G121: =G132/G133 -> 0.18059492 | H121: =SUM(C121:G121)/5 -> 0.16954068
B127: Revenue per Segment | J127: SEGMENTS DRIVERS
J128: US Domestic Package: The growth of e-commerce increases demand for fast deliveries and logistical efficiency, prompting the industry to adapt to meet customer expectations.
C129: 2023 | D129: 2022 | E129: 2021 | F129: 2020 | G129: 2019 | H129: 2018
B130: US Domestic Package | C130: 59958 | D130: 64209 | E130: 60317 | F130: 53499 | G130: 46493 | H130: 43593
B131: International Package | C131: 17831 | D131: 19698 | E131: 19541 | F131: 15945 | G131: 14220 | H131: 14442
B132: Supply Chain Solutions | C132: 13169 | D132: 16431 | E132: 17429 | F132: 15184 | G132: 13381 | H132: 13826 | J132: International Package: Supply chain complexity increases the need for logistics providers that can manage global networks, promoting integrated logistics services and end-to-end solutions from manufacturing to last-mile delivery.
B133: Total | C133: =SUM(C130:C132) -> 90958 | D133: =SUM(D130:D132) -> 100338 | E133: =SUM(E130:E132) -> 97287 | F133: =SUM(F130:F132) -> 84628 | G133: =SUM(G130:G132) -> 74094 | H133: 71861
B134: Total's Growth | C134: =C133/D133-1 -> -0.093484024 | D134: =D133/E133-1 -> 0.031360819 | E134: =E133/F133-1 -> 0.14958406 | F134: =F133/G133-1 -> 0.14217076 | G134: =G133/H133-1 -> 0.031073879
J136: Supply Chain Solution: Technological Advances sush as automation and robotics, AI and machine learning are crucial for this industry and enable cost reduction, higher efficiency and improved customer satisfaction.
B140: Revenue per Segment Growth
C142: 2023 | D142: 2022 | E142: 2021 | F142: 2020 | G142: 2019 | H142: Average 5y
B143: US Domestic Package | C143: =C130/D130-1 -> -0.066205672 | D143: =D130/E130-1 -> 0.064525756 | E143: =E130/F130-1 -> 0.12744163 | F143: =F130/G130-1 -> 0.15068935 | G143: =G130/H130-1 -> 0.066524442 | H143: =SUM(C143:G143)/5 -> 0.068595102
B144: International Package | C144: =C131/D131-1 -> -0.094781196 | D144: =D131/E131-1 -> 0.0080343892 | E144: =E131/F131-1 -> 0.22552524 | F144: =F131/G131-1 -> 0.12130802 | G144: =G131/H131-1 -> -0.015371832 | H144: =SUM(C144:G144)/5 -> 0.048942924
B145: Supply Chain Solutions | C145: =C132/D132-1 -> -0.19852717 | D145: =D132/E132-1 -> -0.057260887 | E145: =E132/F132-1 -> 0.147853 | F145: =F132/G132-1 -> 0.13474329 | G145: =G132/H132-1 -> -0.032185737 | H145: =SUM(C145:G145)/5 -> -0.0010755005
BP388: 2023 | BQ388: 2022 | BR388: 2021 | BS388: 2020 | BT388: 2019 | BU388: 2018 | BV388: 2017 | BW388: 2016 | BY388: 2015 | BZ388: 2014 | CA388: 2013 | CB388: 2012
BO389: PPE | BP389: 36945 | BQ389: 34719 | BR389: 33475 | BS389: 32245 | BT389: 30842 | BU389: 26576 | BV389: 22118 | BW389: 18800 | BY389: 18352 | BZ389: 18281 | CA389: 17961
BO390: ROA | BP390: 4308 | BQ390: 3755 | BR390: 3562 | BS390: 3073 | BT390: 3073 | BU390: 3073 | BV390: 3073 | BW390: - | BY390: - | BZ390: - | CA390: - | CB390: -
BO391: Dep | BP391: =BP395-BP394 -> -500
BO392: Intang. Assets | BP392: 7860 | BQ392: 6851 | BR392: 6249 | BS392: 5743 | BT392: 5347 | BU392: 4943 | BV392: 4578 | BW392: 4183 | BY392: 3825 | BZ392: 3129 | CA392: 2912 | CB392: 2608
BO393: Amort. accumulated | BP393: 4555 | BQ393: 4055 | BR393: 3763 | BS393: 3469 | BT393: 3180 | BU393: 2867 | BV393: 2614 | BW393: 2425 | BY393: 2276 | BZ393: 2282 | CA393: 2137 | CB393: 2005
BO394: Amort. | BP394: =BP393-BQ393 -> 500 | BQ394: =BQ393-BR393 -> 292 | BR394: =BR393-BS393 -> 294 | BS394: =BS393-BT393 -> 289 | BT394: =BT393-BU393 -> 313 | BU394: =BU393-BV393 -> 253 | BV394: =2614-2425 -> 189 | BW394: =2425-2276 -> 149 | BY394: =BY393-BZ393 -> -6 | BZ394: =BZ393-CA393 -> 145 | CA394: =CA393-CB393 -> 132
BO395: Dep & Amort

Sheet Fin. Data
A1: =Inputs!H3 -> UNITED PARCEL SERVICE, INC. (XNYS:UPS)
A2: =Inputs!G2 -> Figures in Millions of USD
A3: Results
B4: =OP!J20 -> 2023 | C4: =B4-1 -> 2022 | D4: =C4-1 -> 2021 | E4: =D4-1 -> 2020 | F4: =E4-1 -> 2019 | G4: =F4-1 -> 2018 | H4: =G4-1 -> 2017 | I4: =H4-1 -> 2016 | J4: =I4-1 -> 2015 | ... M4: =L4-1 -> 2012
A5: Net Sales | B5: =_xlfn.XLOOKUP($A5,Inputs!$A:$A,Inputs!B:B,,0) -> 90958 | C5: =_xlfn.XLOOKUP($A5,Inputs!$A:$A,Inputs!C:C,,0) -> 100338 | D5: =_xlfn.XLOOKUP($A5,Inputs!$A:$A,Inputs!D:D,,0) -> 97287 | E5: =_xlfn.XLOOKUP($A5,Inputs!$A:$A,Inputs!E:E,,0) -> 84628 | F5: =_xlfn.XLOOKUP($A5,Inputs!$A:$A,Inputs!F:F,,0) -> 74094 | G5: =_xlfn.XLOOKUP($A5,Inputs!$A:$A,Inputs!G:G,,0) -> 71861 | H5: =_xlfn.XLOOKUP($A5,Inputs!$A:$A,Inputs!H:H,,0) -> 65872 | I5: =_xlfn.XLOOKUP($A5,Inputs!$A:$A,Inputs!I:I,,0) -> 60906 | J5: =_xlfn.XLOOKUP($A5,Inputs!$A:$A,Inputs!J:J,,0) -> 58363 | K5: =_xlfn.XLOOKUP($A5,Inputs!$A:$A,Inputs!K:K,,0) -> 58232 | L5: =_xlfn.XLOOKUP($A5,Inputs!$A:$A,Inputs!L:L,,0) -> 55438 | M5: =_xlfn.XLOOKUP($A5,Inputs!$A:$A,Inputs!M:M,,0) -> 54127
A6: Growth vs. Previous year | B6: =IFERROR(B5/C5-1,"-") -> -0.093484024 | C6: =IFERROR(C5/D5-1,"-") -> 0.031360819 | D6: =IFERROR(D5/E5-1,"-") -> 0.14958406 | E6: =IFERROR(E5/F5-1,"-") -> 0.14217076 | F6: =IFERROR(F5/G5-1,"-") -> 0.031073879 | G6: =IFERROR(G5/H5-1,"-") -> 0.090918752 | H6: =IFERROR(H5/I5-1,"-") -> 0.081535481 | I6: =IFERROR(I5/J5-1,"-") -> 0.043572126 | ... L6: =IFERROR(L5/M5-1,"-") -> 0.024220814 | M6: =IFERROR(M5/#REF!-1,"-") -> -
A7: Gross Profit | B7: =_xlfn.XLOOKUP($A7,Inputs!$A:$A,Inputs!B:B,,0) -> 9141 | C7: =_xlfn.XLOOKUP($A7,Inputs!$A:$A,Inputs!C:C,,0) -> 13094 | D7: =_xlfn.XLOOKUP($A7,Inputs!$A:$A,Inputs!D:D,,0) -> 12810 | E7: =_xlfn.XLOOKUP($A7,Inputs!$A:$A,Inputs!E:E,,0) -> 7684 | F7: =_xlfn.XLOOKUP($A7,Inputs!$A:$A,Inputs!F:F,,0) -> 7798 | G7: =_xlfn.XLOOKUP($A7,Inputs!$A:$A,Inputs!G:G,,0) -> 7024 | H7: =_xlfn.XLOOKUP($A7,Inputs!$A:$A,Inputs!H:H,,0) -> 7529 | I7: =_xlfn.XLOOKUP($A7,Inputs!$A:$A,Inputs!I:I,,0) -> 5467 | J7: =_xlfn.XLOOKUP($A7,Inputs!$A:$A,Inputs!J:J,,0) -> 7668 | K7: =_xlfn.XLOOKUP($A7,Inputs!$A:$A,Inputs!K:K,,0) -> 4968 | L7: =_xlfn.XLOOKUP($A7,Inputs!$A:$A,Inputs!L:L,,0) -> 7034 | M7: =_xlfn.XLOOKUP($A7,Inputs!$A:$A,Inputs!M:M,,0) -> 1343
A8: % over sales | B8: =IFERROR(B7/B$5,"-") -> 0.10049693 | C8: =IFERROR(C7/C$5,"-") -> 0.13049891 | D8: =IFERROR(D7/D$5,"-") -> 0.13167227 | E8: =IFERROR(E7/E$5,"-") -> 0.090797372 | F8: =IFERROR(F7/F$5,"-") -> 0.10524469 | G8: =IFERROR(G7/G$5,"-") -> 0.097744256 | H8: =IFERROR(H7/H$5,"-") -> 0.11429743 | I8: =IFERROR(I7/I$5,"-") -> 0.089761271 | ... M8: =IFERROR(M7/M$5,"-") -> 0.024812016
A9: Operating expenses | B9: =B5-B11 -> 81817 | C9: =C5-C11 -> 87244 | D9: =D5-D11 -> 84477 | E9: =E5-E11 -> 76944 | F9: =F5-F11 -> 66296 | G9: =G5-G11 -> 64837 | H9: =H5-H11 -> 58343 | I9: =I5-I11 -> 55439 | ... M9: =M5-M11 -> 52784
A10: % over sales | B10: =IFERROR(B9/B$5,"-") -> 0.89950307 | C10: =IFERROR(C9/C$5,"-") -> 0.86950109 | D10: =IFERROR(D9/D$5,"-") -> 0.86832773 | E10: =IFERROR(E9/E$5,"-") -> 0.90920263 | F10: =IFERROR(F9/F$5,"-") -> 0.89475531 | G10: =IFERROR(G9/G$5,"-") -> 0.90225574 | H10: =IFERROR(H9/H$5,"-") -> 0.88570257 | I10: =IFERROR(I9/I$5,"-") -> 0.91023873 | ... M10: =IFERROR(M9/M$5,"-") -> 0.97518798
A11: Operating Income | B11: =_xlfn.XLOOKUP($A11,Inputs!$A:$A,Inputs!B:B,,0) -> 9141 | C11: =_xlfn.XLOOKUP($A11,Inputs!$A:$A,Inputs!C:C,,0) -> 13094 | D11: =_xlfn.XLOOKUP($A11,Inputs!$A:$A,Inputs!D:D,,0) -> 12810 | E11: =_xlfn.XLOOKUP($A11,Inputs!$A:$A,Inputs!E:E,,0) -> 7684 | F11: =_xlfn.XLOOKUP($A11,Inputs!$A:$A,Inputs!F:F,,0) -> 7798 | G11: =_xlfn.XLOOKUP($A11,Inputs!$A:$A,Inputs!G:G,,0) -> 7024 | H11: =_xlfn.XLOOKUP($A11,Inputs!$A:$A,Inputs!H:H,,0) -> 7529 | I11: =_xlfn.XLOOKUP($A11,Inputs!$A:$A,Inputs!I:I,,0) -> 5467 | J11: =_xlfn.XLOOKUP($A11,Inputs!$A:$A,Inputs!J:J,,0) -> 7668 | K11: =_xlfn.XLOOKUP($A11,Inputs!$A:$A,Inputs!K:K,,0) -> 4968 | L11: =_xlfn.XLOOKUP($A11,Inputs!$A:$A,Inputs!L:L,,0) -> 7034 | M11: =_xlfn.XLOOKUP($A11,Inputs!$A:$A,Inputs!M:M,,0) -> 1343
A12: Operating Margin | B12: =IFERROR(B11/B$5,"-") -> 0.10049693 | C12: =IFERROR(C11/C$5,"-") -> 0.13049891 | D12: =IFERROR(D11/D$5,"-") -> 0.13167227 | E12: =IFERROR(E11/E$5,"-") -> 0.090797372 | F12: =IFERROR(F11/F$5,"-") -> 0.10524469 | G12: =IFERROR(G11/G$5,"-") -> 0.097744256 | H12: =IFERROR(H11/H$5,"-") -> 0.11429743 | I12: =IFERROR(I11/I$5,"-") -> 0.089761271 | ... M12: =IFERROR(M11/M$5,"-") -> 0.024812016
A13: Growth vs. Previous year | B13: =IFERROR(B12/C12-1,"-") -> -0.22990215 | C13: =IFERROR(C12/D12-1,"-") -> -0.0089111776 | D13: =IFERROR(D12/E12-1,"-") -> 0.45017709 | E13: =IFERROR(E12/F12-1,"-") -> -0.1372736 | F13: =IFERROR(F12/G12-1,"-") -> 0.07673528 | G13: =IFERROR(G12/H12-1,"-") -> -0.14482539 | H13: =IFERROR(H12/I12-1,"-") -> 0.273349 | I13: =IFERROR(I12/J12-1,"-") -> -0.31680528 | ... L13: =IFERROR(L12/M12-1,"-") -> 4.1136707 | M13: =IFERROR(M12/#REF!-1,"-") -> -
A14: Net Financial Cost | B14: =_xlfn.XLOOKUP($A14,Inputs!$A:$A,Inputs!B:B,,0) -> -568 | C14: =_xlfn.XLOOKUP($A14,Inputs!$A:$A,Inputs!C:C,,0) -> -704 | D14: =_xlfn.XLOOKUP($A14,Inputs!$A:$A,Inputs!D:D,,0) -> -694 | E14: =_xlfn.XLOOKUP($A14,Inputs!$A:$A,Inputs!E:E,,0) -> -701 | F14: =_xlfn.XLOOKUP($A14,Inputs!$A:$A,Inputs!F:F,,0) -> -653 | G14: =_xlfn.XLOOKUP($A14,Inputs!$A:$A,Inputs!G:G,,0) -> -605 | H14: =_xlfn.XLOOKUP($A14,Inputs!$A:$A,Inputs!H:H,,0) -> -453 | I14: =_xlfn.XLOOKUP($A14,Inputs!$A:$A,Inputs!I:I,,0) -> -381 | J14: =_xlfn.XLOOKUP($A14,Inputs!$A:$A,Inputs!J:J,,0) -> -341 | K14: =_xlfn.XLOOKUP($A14,Inputs!$A:$A,Inputs!K:K,,0) -> -353 | L14: =_xlfn.XLOOKUP($A14,Inputs!$A:$A,Inputs!L:L,,0) -> -380 | M14: =_xlfn.XLOOKUP($A14,Inputs!$A:$A,Inputs!M:M,,0) -> -393
A15: Other Expenses (Revenues) | B15: =_xlfn.XLOOKUP($A15,Inputs!$A:$A,Inputs!B:B,,0) -> 0 | C15: =_xlfn.XLOOKUP($A15,Inputs!$A:$A,Inputs!C:C,,0) -> 2435 | D15: =_xlfn.XLOOKUP($A15,Inputs!$A:$A,Inputs!D:D,,0) -> 4479 | E15: =_xlfn.XLOOKUP($A15,Inputs!$A:$A,Inputs!E:E,,0) -> -5139 | F15: =_xlfn.XLOOKUP($A15,Inputs!$A:$A,Inputs!F:F,,0) -> -1493 | G15: =_xlfn.XLOOKUP($A15,Inputs!$A:$A,Inputs!G:G,,0) -> -400 | H15: =_xlfn.XLOOKUP($A15,Inputs!$A:$A,Inputs!H:H,,0) -> 72 | I15: =_xlfn.XLOOKUP($A15,Inputs!$A:$A,Inputs!I:I,,0) -> 50 | J15: =_xlfn.XLOOKUP($A15,Inputs!$A:$A,Inputs!J:J,,0) -> 15 | K15: =_xlfn.XLOOKUP($A15,Inputs!$A:$A,Inputs!K:K,,0) -> 22 | L15: =_xlfn.XLOOKUP($A15,Inputs!$A:$A,Inputs!L:L,,0) -> 20 | M15: =_xlfn.XLOOKUP($A15,Inputs!$A:$A,Inputs!M:M,,0) -> 24
A16: EBIT | B16: =B11-B15 -> 9141 | C16: =C11-C15 -> 10659 | D16: =D11-D15 -> 8331 | E16: =E11-E15 -> 12823 | F16: =F11-F15 -> 9291 | G16: =G11-G15 -> 7424 | H16: =H11-H15 -> 7457 | I16: =I11-I15 -> 5417 | ... M16: =M11-M15 -> 1319
A17: Depreciation & Amortization | B17: =_xlfn.XLOOKUP($A17,Inputs!$A:$A,Inputs!B:B,,0) -> 3366 | C17: =_xlfn.XLOOKUP($A17,Inputs!$A:$A,Inputs!C:C,,0) -> 3188 | D17: =_xlfn.XLOOKUP($A17,Inputs!$A:$A,Inputs!D:D,,0) -> 2953 | E17: =_xlfn.XLOOKUP($A17,Inputs!$A:$A,Inputs!E:E,,0) -> 2698 | F17: =_xlfn.XLOOKUP($A17,Inputs!$A:$A,Inputs!F:F,,0) -> 2360 | G17: =_xlfn.XLOOKUP($A17,Inputs!$A:$A,Inputs!G:G,,0) -> 2207 | H17: =_xlfn.XLOOKUP($A17,Inputs!$A:$A,Inputs!H:H,,0) -> 2282 | I17: =_xlfn.XLOOKUP($A17,Inputs!$A:$A,Inputs!I:I,,0) -> 2224 | J17: =_xlfn.XLOOKUP($A17,Inputs!$A:$A,Inputs!J:J,,0) -> 2084 | K17: =_xlfn.XLOOKUP($A17,Inputs!$A:$A,Inputs!K:K,,0) -> 1923 | L17: =_xlfn.XLOOKUP($A17,Inputs!$A:$A,Inputs!L:L,,0) -> 1867 | M17: =_xlfn.XLOOKUP($A17,Inputs!$A:$A,Inputs!M:M,,0) -> 1858
A18: Changes Net Working Capital | B18: =_xlfn.XLOOKUP($A18,Inputs!$A:$A,Inputs!B:B,,0) -> 56 | C18: =_xlfn.XLOOKUP($A18,Inputs!$A:$A,Inputs!C:C,,0) -> 1365 | D18: =_xlfn.XLOOKUP($A18,Inputs!$A:$A,Inputs!D:D,,0) -> -189 | E18: =_xlfn.XLOOKUP($A18,Inputs!$A:$A,Inputs!E:E,,0) -> 847 | F18: =_xlfn.XLOOKUP($A18,Inputs!$A:$A,Inputs!F:F,,0) -> -1446 | G18: =_xlfn.XLOOKUP($A18,Inputs!$A:$A,Inputs!G:G,,0) -> -1622 | H18: =_xlfn.XLOOKUP($A18,Inputs!$A:$A,Inputs!H:H,,0) -> 877 | I18: =_xlfn.XLOOKUP($A18,Inputs!$A:$A,Inputs!I:I,,0) -> -1139 | J18: =_xlfn.XLOOKUP($A18,Inputs!$A:$A,Inputs!J:J,,0) -> -1096 | K18: =_xlfn.XLOOKUP($A18,Inputs!$A:$A,Inputs!K:K,,0) -> -713 | L18: =_xlfn.XLOOKUP($A18,Inputs!$A:$A,Inputs!L:L,,0) -> 1717 | M18: =_xlfn.XLOOKUP($A18,Inputs!$A:$A,Inputs!M:M,,0) -> 0
A19: EBITDA | B19: =B11-B15+B17 -> 12507 | C19: =C11-C15+C17 -> 13847 | D19: =D11-D15+D17 -> 11284 | E19: =E11-E15+E17 -> 15521 | F19: =F11-F15+F17 -> 11651 | G19: =G11-G15+G17 -> 9631 | H19: =H11-H15+H17 -> 9739 | I19: =I11-I15+I17 -> 7641 | ... M19: =M11-M15+M17 -> 3177
A20: EBITDA Margin | B20: =IFERROR(B19/B$5,"-") -> 0.13750302 | C20: =IFERROR(C19/C$5,"-") -> 0.13800355 | D20: =IFERROR(D19/D$5,"-") -> 0.11598672 | E20: =IFERROR(E19/E$5,"-") -> 0.18340266 | F20: =IFERROR(F19/F$5,"-") -> 0.1572462 | G20: =IFERROR(G19/G$5,"-") -> 0.13402263 | H20: =IFERROR(H19/H$5,"-") -> 0.14784734 | I20: =IFERROR(I19/I$5,"-") -> 0.12545562 | ... M20: =IFERROR(M19/M$5,"-") -> 0.058695291
A21: Taxes | B21: =_xlfn.XLOOKUP($A21,Inputs!$A:$A,Inputs!B:B,,0) -> -1865 | C21: =_xlfn.XLOOKUP($A21,Inputs!$A:$A,Inputs!C:C,,0) -> -3277 | D21: =_xlfn.XLOOKUP($A21,Inputs!$A:$A,Inputs!D:D,,0) -> -3705 | E21: =_xlfn.XLOOKUP($A21,Inputs!$A:$A,Inputs!E:E,,0) -> -501 | F21: =_xlfn.XLOOKUP($A21,Inputs!$A:$A,Inputs!F:F,,0) -> -1212 | G21: =_xlfn.XLOOKUP($A21,Inputs!$A:$A,Inputs!G:G,,0) -> -1228 | H21: =_xlfn.XLOOKUP($A21,Inputs!$A:$A,Inputs!H:H,,0) -> -2238 | I21: =_xlfn.XLOOKUP($A21,Inputs!$A:$A,Inputs!I:I,,0) -> -1705 | J21: =_xlfn.XLOOKUP($A21,Inputs!$A:$A,Inputs!J:J,,0) -> -2498 | K21: =_xlfn.XLOOKUP($A21,Inputs!$A:$A,Inputs!K:K,,0) -> -1605 | L21: =_xlfn.XLOOKUP($A21,Inputs!$A:$A,Inputs!L:L,,0) -> -2302 | M21: =_xlfn.XLOOKUP($A21,Inputs!$A:$A,Inputs!M:M,,0) -> -167
A22: % Tax | B22: =IFERROR(B21/B$5,"-") -> -0.020503969 | C22: =IFERROR(C21/C$5,"-") -> -0.032659611 | D22: =IFERROR(D21/D$5,"-") -> -0.038083197 | E22: =IFERROR(E21/E$5,"-") -> -0.0059200265 | F22: =IFERROR(F21/F$5,"-") -> -0.0163576 | G22: =IFERROR(G21/G$5,"-") -> -0.017088546 | H22: =IFERROR(H21/H$5,"-") -> -0.033974982 | I22: =IFERROR(I21/I$5,"-") -> -0.027993958 | ... M22: =IFERROR(M21/M$5,"-") -> -0.0030853363
A23: Net Income | B23: =_xlfn.XLOOKUP($A23,Inputs!$A:$A,Inputs!B:B,,0) -> 6708 | C23: =_xlfn.XLOOKUP($A23,Inputs!$A:$A,Inputs!C:C,,0) -> 11548 | D23: =_xlfn.XLOOKUP($A23,Inputs!$A:$A,Inputs!D:D,,0) -> 12890 | E23: =_xlfn.XLOOKUP($A23,Inputs!$A:$A,Inputs!E:E,,0) -> 1343 | F23: =_xlfn.XLOOKUP($A23,Inputs!$A:$A,Inputs!F:F,,0) -> 4440 | G23: =_xlfn.XLOOKUP($A23,Inputs!$A:$A,Inputs!G:G,,0) -> 4791 | H23: =_xlfn.XLOOKUP($A23,Inputs!$A:$A,Inputs!H:H,,0) -> 4910 | I23: =_xlfn.XLOOKUP($A23,Inputs!$A:$A,Inputs!I:I,,0) -> 3431 | J23: =_xlfn.XLOOKUP($A23,Inputs!$A:$A,Inputs!J:J,,0) -> 4844 | K23: =_xlfn.XLOOKUP($A23,Inputs!$A:$A,Inputs!K:K,,0) -> 3032 | L23: =_xlfn.XLOOKUP($A23,Inputs!$A:$A,Inputs!L:L,,0) -> 4372 | M23: =_xlfn.XLOOKUP($A23,Inputs!$A:$A,Inputs!M:M,,0) -> 807
A24: Net Income Margin | B24: =IFERROR(B23/B$5,"-") -> 0.073748323 | C24: =IFERROR(C23/C$5,"-") -> 0.11509099 | D24: =IFERROR(D23/D$5,"-") -> 0.13249458 | E24: =IFERROR(E23/E$5,"-") -> 0.015869452 | F24: =IFERROR(F23/F$5,"-") -> 0.05992388 | G24: =IFERROR(G23/G$5,"-") -> 0.066670378 | H24: =IFERROR(H23/H$5,"-") -> 0.074538499 | I24: =IFERROR(I23/I$5,"-") -> 0.056332709 | ... M24: =IFERROR(M23/M$5,"-") -> 0.01490938
A25: Growth vs. Previous year | B25: =IFERROR(B24/C24-1,"-") -> -0.35921724 | C25: =IFERROR(C24/D24-1,"-") -> -0.13135319 | D25: =IFERROR(D24/E24-1,"-") -> 7.3490329 | E25: =IFERROR(E24/F24-1,"-") -> -0.73517316 | F25: =IFERROR(F24/G24-1,"-") -> -0.10119182 | G25: =IFERROR(G24/H24-1,"-") -> -0.10555782 | H25: =IFERROR(H24/I24-1,"-") -> 0.32318327 | I25: =IFERROR(I24/J24-1,"-") -> -0.32127458 | ... L25: =IFERROR(L24/M24-1,"-") -> 4.2894805 | M25: =IFERROR(M24/#REF!-1,"-") -> -
A26: Cash Generated | B26: =B39-C39 -> -2396 | C26: =C39-D39 -> -4653 | D26: =D39-E39 -> 4354 | E26: =E39-F39 -> 663 | F26: =F39-G39 -> 1013 | G26: =G39-H39 -> 905 | H26: =H39-I39 -> -156 | I26: =I39-J39 -> 746 | ... M26: =M39-N39 -> 7327
A27: Dividends | B27: =_xlfn.XLOOKUP($A27,Inputs!$A:$A,Inputs!B:B,,0) -> -5372 | C27: =_xlfn.XLOOKUP($A27,Inputs!$A:$A,Inputs!C:C,,0) -> -5114 | D27: =_xlfn.XLOOKUP($A27,Inputs!$A:$A,Inputs!D:D,,0) -> -3437 | E27: =_xlfn.XLOOKUP($A27,Inputs!$A:$A,Inputs!E:E,,0) -> -3374 | F27: =_xlfn.XLOOKUP($A27,Inputs!$A:$A,Inputs!F:F,,0) -> -3194 | G27: =_xlfn.XLOOKUP($A27,Inputs!$A:$A,Inputs!G:G,,0) -> -3011 | H27: =_xlfn.XLOOKUP($A27,Inputs!$A:$A,Inputs!H:H,,0) -> -2771 | I27: =_xlfn.XLOOKUP($A27,Inputs!$A:$A,Inputs!I:I,,0) -> -2643 | J27: =_xlfn.XLOOKUP($A27,Inputs!$A:$A,Inputs!J:J,,0) -> -2525 | K27: =_xlfn.XLOOKUP($A27,Inputs!$A:$A,Inputs!K:K,,0) -> -2366 | L27: =_xlfn.XLOOKUP($A27,Inputs!$A:$A,Inputs!L:L,,0) -> -2260 | M27: =_xlfn.XLOOKUP($A27,Inputs!$A:$A,Inputs!M:M,,0) -> -2130
A28: Share buyback | B28: =_xlfn.XLOOKUP($A28,Inputs!$A:$A,Inputs!B:B,,0) -> -2250 | C28: =_xlfn.XLOOKUP($A28,Inputs!$A:$A,Inputs!C:C,,0) -> -3500 | D28: =_xlfn.XLOOKUP($A28,Inputs!$A:$A,Inputs!D:D,,0) -> -500 | E28: =_xlfn.XLOOKUP($A28,Inputs!$A:$A,Inputs!E:E,,0) -> -224 | F28: =_xlfn.XLOOKUP($A28,Inputs!$A:$A,Inputs!F:F,,0) -> -1004 | G28: =_xlfn.XLOOKUP($A28,Inputs!$A:$A,Inputs!G:G,,0) -> -1011 | H28: =_xlfn.XLOOKUP($A28,Inputs!$A:$A,Inputs!H:H,,0) -> -1813 | I28: =_xlfn.XLOOKUP($A28,Inputs!$A:$A,Inputs!I:I,,0) -> -2678 | J28: =_xlfn.XLOOKUP($A28,Inputs!$A:$A,Inputs!J:J,,0) -> -2702 | K28: =_xlfn.XLOOKUP($A28,Inputs!$A:$A,Inputs!K:K,,0) -> -2695 | L28: =_xlfn.XLOOKUP($A28,Inputs!$A:$A,Inputs!L:L,,0) -> -3838 | M28: =_xlfn.XLOOKUP($A28,Inputs!$A:$A,Inputs!M:M,,0) -> -1621
A29: Net Cash Flow | B29: =SUM(B26:B28) -> -10018 | C29: =SUM(C26:C28) -> -13267 | D29: =SUM(D26:D28) -> 417 | E29: =SUM(E26:E28) -> -2935 | F29: =SUM(F26:F28) -> -3185 | G29: =SUM(G26:G28) -> -3117 | H29: =SUM(H26:H28) -> -4740 | I29: =SUM(I26:I28) -> -4575 | ... M29: =SUM(M26:M28) -> 3576
A30: FNP'' | B30: =+B29-(B58-C29) -> -50014 | C30: =+C29-(C58-D29) -> -36271 | D30: =+D29-(D58-E29) -> -28046 | E30: =+E29-(E58-F29) -> -33874 | F30: =+F29-(F58-G29) -> -34469 | G30: =+G29-(G58-H29) -> -30593 | H30: =+H29-(H58-I29) -> -33604 | I30: =+I29-(I58-J29) -> -25438 | ... M30: =+M29-(M58-N29) -> -9294
A31: FNP' | B31: =+B30+B33 -> -51343 | C31: =+C30+C33 -> -37026 | D31: =+D30+D33 -> -28648 | E31: =+E30+E33 -> -33894 | F31: =+F30+F33 -> -34475 | G31: =+G30+G33 -> -30595 | H31: =+H30+H33 -> -33738 | I31: =+I30+I33 -> -25985 | ... M31: =+M30+M33 -> -9394
A32: Net Capex | B32: =_xlfn.XLOOKUP($A32,Inputs!$A:$A,Inputs!B:B,,0) -> -5158 | C32: =_xlfn.XLOOKUP($A32,Inputs!$A:$A,Inputs!C:C,,0) -> -4769 | D32: =_xlfn.XLOOKUP($A32,Inputs!$A:$A,Inputs!D:D,,0) -> -4194 | E32: =_xlfn.XLOOKUP($A32,Inputs!$A:$A,Inputs!E:E,,0) -> -5412 | F32: =_xlfn.XLOOKUP($A32,Inputs!$A:$A,Inputs!F:F,,0) -> -6380 | G32: =_xlfn.XLOOKUP($A32,Inputs!$A:$A,Inputs!G:G,,0) -> -6238 | H32: =_xlfn.XLOOKUP($A32,Inputs!$A:$A,Inputs!H:H,,0) -> -5227 | I32: =_xlfn.XLOOKUP($A32,Inputs!$A:$A,Inputs!I:I,,0) -> -2965 | J32: =_xlfn.XLOOKUP($A32,Inputs!$A:$A,Inputs!J:J,,0) -> -2379 | K32: =_xlfn.XLOOKUP($A32,Inputs!$A:$A,Inputs!K:K,,0) -> -2328 | L32: =_xlfn.XLOOKUP($A32,Inputs!$A:$A,Inputs!L:L,,0) -> -2065 | M32: =_xlfn.XLOOKUP($A32,Inputs!$A:$A,Inputs!M:M,,0) -> -2153
A33: Investments & Acquisitions | B33: =_xlfn.XLOOKUP($A33,Inputs!$A:$A,Inputs!B:B,,0) -> -1329 | C33: =_xlfn.XLOOKUP($A33,Inputs!$A:$A,Inputs!C:C,,0) -> -755 | D33: =_xlfn.XLOOKUP($A33,Inputs!$A:$A,Inputs!D:D,,0) -> -602 | E33: =_xlfn.XLOOKUP($A33,Inputs!$A:$A,Inputs!E:E,,0) -> -20 | F33: =_xlfn.XLOOKUP($A33,Inputs!$A:$A,Inputs!F:F,,0) -> -6 | G33: =_xlfn.XLOOKUP($A33,Inputs!$A:$A,Inputs!G:G,,0) -> -2 | H33: =_xlfn.XLOOKUP($A33,Inputs!$A:$A,Inputs!H:H,,0) -> -134 | I33: =_xlfn.XLOOKUP($A33,Inputs!$A:$A,Inputs!I:I,,0) -> -547 | J33: =_xlfn.XLOOKUP($A33,Inputs!$A:$A,Inputs!J:J,,0) -> -30 | K33: =_xlfn.XLOOKUP($A33,Inputs!$A:$A,Inputs!K:K,,0) -> -63 | L33: =_xlfn.XLOOKUP($A33,Inputs!$A:$A,Inputs!L:L,,0) -> -179 | M33: =_xlfn.XLOOKUP($A33,Inputs!$A:$A,Inputs!M:M,,0) -> -100
A34: Capex + Investments | B34: =+B32+B33 -> -6487 | C34: =+C32+C33 -> -5524 | D34: =+D32+D33 -> -4796 | E34: =+E32+E33 -> -5432 | F34: =+F32+F33 -> -6386 | G34: =+G32+G33 -> -6240 | H34: =+H32+H33 -> -5361 | I34: =+I32+I33 -> -3512 | ... M34: =+M32+M33 -> -2253
A35: Dividends + Share Buyback | B35: =+B27+B28 -> -7622 | C35: =+C27+C28 -> -8614 | D35: =+D27+D28 -> -3937 | E35: =+E27+E28 -> -3598 | F35: =+F27+F28 -> -4198 | G35: =+G27+G28 -> -4022 | H35: =+H27+H28 -> -4584 | I35: =+I27+I28 -> -5321 | ... M35: =+M27+M28 -> -3751
A36: Payout Ratio | B36: =IFERROR(B35/B23,"-") -> -1.1362552 | C36: =IFERROR(C35/C23,"-") -> -0.74593003 | D36: =IFERROR(D35/D23,"-") -> -0.30543057 | E36: =IFERROR(E35/E23,"-") -> -2.6790767 | F36: =IFERROR(F35/F23,"-") -> -0.9454955 | G36: =IFERROR(G35/G23,"-") -> -0.83949071 | H36: =IFERROR(H35/H23,"-") -> -0.93360489 | I36: =IFERROR(I35/I23,"-") -> -1.5508598 | ... M36: =IFERROR(M35/M23,"-") -> -4.6480793
A38: Assets
A39: Cash & Eq. | B39: =_xlfn.XLOOKUP($A39,Inputs!$A:$A,Inputs!B:B,,0) -> 3206 | C39: =_xlfn.XLOOKUP($A39,Inputs!$A:$A,Inputs!C:C,,0) -> 5602 | D39: =_xlfn.XLOOKUP($A39,Inputs!$A:$A,Inputs!D:D,,0) -> 10255 | E39: =_xlfn.XLOOKUP($A39,Inputs!$A:$A,Inputs!E:E,,0) -> 5901 | F39: =_xlfn.XLOOKUP($A39,Inputs!$A:$A,Inputs!F:F,,0) -> 5238 | G39: =_xlfn.XLOOKUP($A39,Inputs!$A:$A,Inputs!G:G,,0) -> 4225 | H39: =_xlfn.XLOOKUP($A39,Inputs!$A:$A,Inputs!H:H,,0) -> 3320 | I39: =_xlfn.XLOOKUP($A39,Inputs!$A:$A,Inputs!I:I,,0) -> 3476 | J39: =_xlfn.XLOOKUP($A39,Inputs!$A:$A,Inputs!J:J,,0) -> 2730 | K39: =_xlfn.XLOOKUP($A39,Inputs!$A:$A,Inputs!K:K,,0) -> 2291 | L39: =_xlfn.XLOOKUP($A39,Inputs!$A:$A,Inputs!L:L,,0) -> 4665 | M39: =_xlfn.XLOOKUP($A39,Inputs!$A:$A,Inputs!M:M,,0) -> 7327
A40: Accounts Receivable | B40: =_xlfn.XLOOKUP($A40,Inputs!$A:$A,Inputs!B:B,,0) -> 11342 | C40: =_xlfn.XLOOKUP($A40,Inputs!$A:$A,Inputs!C:C,,0) -> 12729 | D40: =_xlfn.XLOOKUP($A40,Inputs!$A:$A,Inputs!D:D,,0) -> 10255 | E40: =_xlfn.XLOOKUP($A40,Inputs!$A:$A,Inputs!E:E,,0) -> 5910 | F40: =_xlfn.XLOOKUP($A40,Inputs!$A:$A,Inputs!F:F,,0) -> 5238 | G40: =_xlfn.XLOOKUP($A40,Inputs!$A:$A,Inputs!G:G,,0) -> 8958 | H40: =_xlfn.XLOOKUP($A40,Inputs!$A:$A,Inputs!H:H,,0) -> 8773 | I40: =_xlfn.XLOOKUP($A40,Inputs!$A:$A,Inputs!I:I,,0) -> 7695 | J40: =_xlfn.XLOOKUP($A40,Inputs!$A:$A,Inputs!J:J,,0) -> 7134 | K40: =_xlfn.XLOOKUP($A40,Inputs!$A:$A,Inputs!K:K,,0) -> 6661 | L40: =_xlfn.XLOOKUP($A40,Inputs!$A:$A,Inputs!L:L,,0) -> 6502 | M40: =_xlfn.XLOOKUP($A40,Inputs!$A:$A,Inputs!M:M,,0) -> 6111
A41: Inventory | B41: =_xlfn.XLOOKUP($A41,Inputs!$A:$A,Inputs!B:B,,0) -> 935 | C41: =_xlfn.XLOOKUP($A41,Inputs!$A:$A,Inputs!C:C,,0) -> 889 | D41: =_xlfn.XLOOKUP($A41,Inputs!$A:$A,Inputs!D:D,,0) -> 717 | E41: =_xlfn.XLOOKUP($A41,Inputs!$A:$A,Inputs!E:E,,0) -> 620 | F41: =_xlfn.XLOOKUP($A41,Inputs!$A:$A,Inputs!F:F,,0) -> 511 | G41: =_xlfn.XLOOKUP($A41,Inputs!$A:$A,Inputs!G:G,,0) -> 421 | H41: =_xlfn.XLOOKUP($A41,Inputs!$A:$A,Inputs!H:H,,0) -> 404 | I41: =_xlfn.XLOOKUP($A41,Inputs!$A:$A,Inputs!I:I,,0) -> 342 | J41: =_xlfn.XLOOKUP($A41,Inputs!$A:$A,Inputs!J:J,,0) -> 308 | K41: =_xlfn.XLOOKUP($A41,Inputs!$A:$A,Inputs!K:K,,0) -> 344 | L41: =_xlfn.XLOOKUP($A41,Inputs!$A:$A,Inputs!L:L,,0) -> 403 | M41: =_xlfn.XLOOKUP($A41,Inputs!$A:$A,Inputs!M:M,,0) -> 393
A42: Property, Plant and Equipment | B42: =_xlfn.XLOOKUP($A42,Inputs!$A:$A,Inputs!B:B,,0) -> 36945 | C42: =_xlfn.XLOOKUP($A42,Inputs!$A:$A,Inputs!C:C,,0) -> 34719 | D42: =_xlfn.XLOOKUP($A42,Inputs!$A:$A,Inputs!D:D,,0) -> 33475 | E42: =_xlfn.XLOOKUP($A42,Inputs!$A:$A,Inputs!E:E,,0) -> 32254 | F42: =_xlfn.XLOOKUP($A42,Inputs!$A:$A,Inputs!F:F,,0) -> 30482 | G42: =_xlfn.XLOOKUP($A42,Inputs!$A:$A,Inputs!G:G,,0) -> 26576 | H42: =_xlfn.XLOOKUP($A42,Inputs!$A:$A,Inputs!H:H,,0) -> 22118 | I42: =_xlfn.XLOOKUP($A42,Inputs!$A:$A,Inputs!I:I,,0) -> 18800 | J42: =_xlfn.XLOOKUP($A42,Inputs!$A:$A,Inputs!J:J,,0) -> 18352 | K42: =_xlfn.XLOOKUP($A42,Inputs!$A:$A,Inputs!K:K,,0) -> 18281 | L42: =_xlfn.XLOOKUP($A42,Inputs!$A:$A,Inputs!L:L,,0) -> 17961 | M42: =_xlfn.XLOOKUP($A42,Inputs!$A:$A,Inputs!M:M,,0) -> 17894
A43: Other Assets | B43: =_xlfn.XLOOKUP($A43,Inputs!$A:$A,Inputs!B:B,,0) -> 14121 | C43: =_xlfn.XLOOKUP($A43,Inputs!$A:$A,Inputs!C:C,,0) -> 13430 | D43: =_xlfn.XLOOKUP($A43,Inputs!$A:$A,Inputs!D:D,,0) -> 11141 | E43: =_xlfn.XLOOKUP($A43,Inputs!$A:$A,Inputs!E:E,,0) -> 14650 | F43: =_xlfn.XLOOKUP($A43,Inputs!$A:$A,Inputs!F:F,,0) -> 13532 | G43: =_xlfn.XLOOKUP($A43,Inputs!$A:$A,Inputs!G:G,,0) -> 8182 | H43: =_xlfn.XLOOKUP($A43,Inputs!$A:$A,Inputs!H:H,,0) -> 9132 | I43: =_xlfn.XLOOKUP($A43,Inputs!$A:$A,Inputs!I:I,,0) -> 8411 | J43: =_xlfn.XLOOKUP($A43,Inputs!$A:$A,Inputs!J:J,,0) -> 8066 | K43: =_xlfn.XLOOKUP($A43,Inputs!$A:$A,Inputs!K:K,,0) -> 6103 | L43: =_xlfn.XLOOKUP($A43,Inputs!$A:$A,Inputs!L:L,,0) -> 4887 | M43: =_xlfn.XLOOKUP($A43,Inputs!$A:$A,Inputs!M:M,,0) -> 5334
A44: Total Assets | B44: =_xlfn.XLOOKUP($A44,Inputs!$A:$A,Inputs!B:B,,0) -> 70857 | C44: =_xlfn.XLOOKUP($A44,Inputs!$A:$A,Inputs!C:C,,0) -> 71124 | D44: =_xlfn.XLOOKUP($A44,Inputs!$A:$A,Inputs!D:D,,0) -> 69405 | E44: =_xlfn.XLOOKUP($A44,Inputs!$A:$A,Inputs!E:E,,0) -> 62408 | F44: =_xlfn.XLOOKUP($A44,Inputs!$A:$A,Inputs!F:F,,0) -> 57857 | G44: =_xlfn.XLOOKUP($A44,Inputs!$A:$A,Inputs!G:G,,0) -> 50016 | H44: =_xlfn.XLOOKUP($A44,Inputs!$A:$A,Inputs!H:H,,0) -> 45403 | I44: =_xlfn.XLOOKUP($A44,Inputs!$A:$A,Inputs!I:I,,0) -> 40377 | J44: =_xlfn.XLOOKUP($A44,Inputs!$A:$A,Inputs!J:J,,0) -> 38311 | K44: =_xlfn.XLOOKUP($A44,Inputs!$A:$A,Inputs!K:K,,0) -> 35471 | L44: =_xlfn.XLOOKUP($A44,Inputs!$A:$A,Inputs!L:L,,0) -> 36212 | M44: =_xlfn.XLOOKUP($A44,Inputs!$A:$A,Inputs!M:M,,0) -> 38863
A47: Liabilities
A48: Current Liabilities | B48: =_xlfn.XLOOKUP($A48,Inputs!$A:$A,Inputs!B:B,,0) -> 17676 | C48: =_xlfn.XLOOKUP($A48,Inputs!$A:$A,Inputs!C:C,,0) -> 18140 | D48: =_xlfn.XLOOKUP($A48,Inputs!$A:$A,Inputs!D:D,,0) -> 17569 | E48: =_xlfn.XLOOKUP($A48,Inputs!$A:$A,Inputs!E:E,,0) -> 17016 | F48: =_xlfn.XLOOKUP($A48,Inputs!$A:$A,Inputs!F:F,,0) -> 15413 | G48: =_xlfn.XLOOKUP($A48,Inputs!$A:$A,Inputs!G:G,,0) -> 14087 | H48: =_xlfn.XLOOKUP($A48,Inputs!$A:$A,Inputs!H:H,,0) -> 12708 | I48: =_xlfn.XLOOKUP($A48,Inputs!$A:$A,Inputs!I:I,,0) -> 11730 | J48: =_xlfn.XLOOKUP($A48,Inputs!$A:$A,Inputs!J:J,,0) -> 10696 | K48: =_xlfn.XLOOKUP($A48,Inputs!$A:$A,Inputs!K:K,,0) -> 8639 | L48: =_xlfn.XLOOKUP($A48,Inputs!$A:$A,Inputs!L:L,,0) -> 7131 | M48: =_xlfn.XLOOKUP($A48,Inputs!$A:$A,Inputs!M:M,,0) -> 8390
A49: Short-Term Debt | B49: =_xlfn.XLOOKUP($A49,Inputs!$A:$A,Inputs!B:B,,0) -> 3348 | C49: =_xlfn.XLOOKUP($A49,Inputs!$A:$A,Inputs!C:C,,0) -> 2241 | D49: =_xlfn.XLOOKUP($A49,Inputs!$A:$A,Inputs!D:D,,0) -> 2131 | E49: =_xlfn.XLOOKUP($A49,Inputs!$A:$A,Inputs!E:E,,0) -> 2623 | F49: =_xlfn.XLOOKUP($A49,Inputs!$A:$A,Inputs!F:F,,0) -> 3420 | G49: =_xlfn.XLOOKUP($A49,Inputs!$A:$A,Inputs!G:G,,0) -> 2805 | H49: =_xlfn.XLOOKUP($A49,Inputs!$A:$A,Inputs!H:H,,0) -> 4011 | I49: =_xlfn.XLOOKUP($A49,Inputs!$A:$A,Inputs!I:I,,0) -> 3681 | J49: =_xlfn.XLOOKUP($A49,Inputs!$A:$A,Inputs!J:J,,0) -> 3018 | K49: =_xlfn.XLOOKUP($A49,Inputs!$A:$A,Inputs!K:K,,0) -> 923 | L49: =_xlfn.XLOOKUP($A49,Inputs!$A:$A,Inputs!L:L,,0) -> 48 | M49: =_xlfn.XLOOKUP($A49,Inputs!$A:$A,Inputs!M:M,,0) -> 1781
A50: Short-Term Leases | B50: =_xlfn.XLOOKUP($A50,Inputs!$A:$A,Inputs!B:B,,0) -> 709 | C50: =_xlfn.XLOOKUP($A50,Inputs!$A:$A,Inputs!C:C,,0) -> 621 | D50: =_xlfn.XLOOKUP($A50,Inputs!$A:$A,Inputs!D:D,,0) -> 580 | E50: =_xlfn.XLOOKUP($A50,Inputs!$A:$A,Inputs!E:E,,0) -> 560 | F50: =_xlfn.XLOOKUP($A50,Inputs!$A:$A,Inputs!F:F,,0) -> 538 | G50: =_xlfn.XLOOKUP($A50,Inputs!$A:$A,Inputs!G:G,,0) -> 0 | H50: =_xlfn.XLOOKUP($A50,Inputs!$A:$A,Inputs!H:H,,0) -> 0 | I50: =_xlfn.XLOOKUP($A50,Inputs!$A:$A,Inputs!I:I,,0) -> 0 | J50: =_xlfn.XLOOKUP($A50,Inputs!$A:$A,Inputs!J:J,,0) -> 0 | K50: =_xlfn.XLOOKUP($A50,Inputs!$A:$A,Inputs!K:K,,0) -> 0 | L50: =_xlfn.XLOOKUP($A50,Inputs!$A:$A,Inputs!L:L,,0) -> 0 | M50: =_xlfn.XLOOKUP($A50,Inputs!$A:$A,Inputs!M:M,,0) -> 0
A51: Other current liabilities | B51: =_xlfn.XLOOKUP($A51,Inputs!$A:$A,Inputs!B:B,,0) -> 7279 | C51: =_xlfn.XLOOKUP($A51,Inputs!$A:$A,Inputs!C:C,,0) -> 7763 | D51: =_xlfn.XLOOKUP($A51,Inputs!$A:$A,Inputs!D:D,,0) -> 7335 | E51: =_xlfn.XLOOKUP($A51,Inputs!$A:$A,Inputs!E:E,,0) -> 7378 | F51: =_xlfn.XLOOKUP($A51,Inputs!$A:$A,Inputs!F:F,,0) -> 5900 | G51: =_xlfn.XLOOKUP($A51,Inputs!$A:$A,Inputs!G:G,,0) -> 6094 | H51: =_xlfn.XLOOKUP($A51,Inputs!$A:$A,Inputs!H:H,,0) -> 4825 | I51: =_xlfn.XLOOKUP($A51,Inputs!$A:$A,Inputs!I:I,,0) -> 5007 | J51: =_xlfn.XLOOKUP($A51,Inputs!$A:$A,Inputs!J:J,,0) -> 5091 | K51: =_xlfn.XLOOKUP($A51,Inputs!$A:$A,Inputs!K:K,,0) -> 4962 | L51: =_xlfn.XLOOKUP($A51,Inputs!$A:$A,Inputs!L:L,,0) -> 4605 | M51: =_xlfn.XLOOKUP($A51,Inputs!$A:$A,Inputs!M:M,,0) -> 4331
A52: Non-current Liabilities | B52: =_xlfn.XLOOKUP($A52,Inputs!$A:$A,Inputs!B:B,,0) -> 35867 | C52: =_xlfn.XLOOKUP($A52,Inputs!$A:$A,Inputs!C:C,,0) -> 33181 | D52: =_xlfn.XLOOKUP($A52,Inputs!$A:$A,Inputs!D:D,,0) -> 37567 | E52: =_xlfn.XLOOKUP($A52,Inputs!$A:$A,Inputs!E:E,,0) -> 44723 | F52: =_xlfn.XLOOKUP($A52,Inputs!$A:$A,Inputs!F:F,,0) -> 39161 | G52: =_xlfn.XLOOKUP($A52,Inputs!$A:$A,Inputs!G:G,,0) -> 32892 | H52: =_xlfn.XLOOKUP($A52,Inputs!$A:$A,Inputs!H:H,,0) -> 31665 | I52: =_xlfn.XLOOKUP($A52,Inputs!$A:$A,Inputs!I:I,,0) -> 28218 | J52: =_xlfn.XLOOKUP($A52,Inputs!$A:$A,Inputs!J:J,,0) -> 25124 | K52: =_xlfn.XLOOKUP($A52,Inputs!$A:$A,Inputs!K:K,,0) -> 24494 | L52: =_xlfn.XLOOKUP($A52,Inputs!$A:$A,Inputs!L:L,,0) -> 22593 | M52: =_xlfn.XLOOKUP($A52,Inputs!$A:$A,Inputs!M:M,,0) -> 25740
A53: Long-Term Debt | B53: =_xlfn.XLOOKUP($A53,Inputs!$A:$A,Inputs!B:B,,0) -> 18916 | C53: =_xlfn.XLOOKUP($A53,Inputs!$A:$A,Inputs!C:C,,0) -> 17321 | D53: =_xlfn.XLOOKUP($A53,Inputs!$A:$A,Inputs!D:D,,0) -> 19784 | E53: =_xlfn.XLOOKUP($A53,Inputs!$A:$A,Inputs!E:E,,0) -> 22031 | F53: =_xlfn.XLOOKUP($A53,Inputs!$A:$A,Inputs!F:F,,0) -> 21818 | G53: =_xlfn.XLOOKUP($A53,Inputs!$A:$A,Inputs!G:G,,0) -> 19931 | H53: =_xlfn.XLOOKUP($A53,Inputs!$A:$A,Inputs!H:H,,0) -> 20278 | I53: =_xlfn.XLOOKUP($A53,Inputs!$A:$A,Inputs!I:I,,0) -> 12394 | J53: =_xlfn.XLOOKUP($A53,Inputs!$A:$A,Inputs!J:J,,0) -> 11316 | K53: =_xlfn.XLOOKUP($A53,Inputs!$A:$A,Inputs!K:K,,0) -> 9864 | L53: =_xlfn.XLOOKUP($A53,Inputs!$A:$A,Inputs!L:L,,0) -> 10824 | M53: =_xlfn.XLOOKUP($A53,Inputs!$A:$A,Inputs!M:M,,0) -> 11089
A54: Long-Term Leases | B54: =_xlfn.XLOOKUP($A54,Inputs!$A:$A,Inputs!B:B,,0) -> 3756 | C54: =_xlfn.XLOOKUP($A54,Inputs!$A:$A,Inputs!C:C,,0) -> 3238 | D54: =_xlfn.XLOOKUP($A54,Inputs!$A:$A,Inputs!D:D,,0) -> 3033 | E54: =_xlfn.XLOOKUP($A54,Inputs!$A:$A,Inputs!E:E,,0) -> 2540 | F54: =_xlfn.XLOOKUP($A54,Inputs!$A:$A,Inputs!F:F,,0) -> 2391 | G54: =_xlfn.XLOOKUP($A54,Inputs!$A:$A,Inputs!G:G,,0) -> 0 | H54: =_xlfn.XLOOKUP($A54,Inputs!$A:$A,Inputs!H:H,,0) -> 0 | I54: =_xlfn.XLOOKUP($A54,Inputs!$A:$A,Inputs!I:I,,0) -> 0 | J54: =_xlfn.XLOOKUP($A54,Inputs!$A:$A,Inputs!J:J,,0) -> 0 | K54: =_xlfn.XLOOKUP($A54,Inputs!$A:$A,Inputs!K:K,,0) -> 0 | L54: =_xlfn.XLOOKUP($A54,Inputs!$A:$A,Inputs!L:L,,0) -> 0 | M54: =_xlfn.XLOOKUP($A54,Inputs!$A:$A,Inputs!M:M,,0) -> 0
A55: Other non-current liabilities | B55: =_xlfn.XLOOKUP($A55,Inputs!$A:$A,Inputs!B:B,,0) -> 13195 | C55: =_xlfn.XLOOKUP($A55,Inputs!$A:$A,Inputs!C:C,,0) -> 12622 | D55: =_xlfn.XLOOKUP($A55,Inputs!$A:$A,Inputs!D:D,,0) -> 14750 | E55: =_xlfn.XLOOKUP($A55,Inputs!$A:$A,Inputs!E:E,,0) -> 20152 | F55: =_xlfn.XLOOKUP($A55,Inputs!$A:$A,Inputs!F:F,,0) -> 14952 | G55: =_xlfn.XLOOKUP($A55,Inputs!$A:$A,Inputs!G:G,,0) -> 12961 | H55: =_xlfn.XLOOKUP($A55,Inputs!$A:$A,Inputs!H:H,,0) -> 11387 | I55: =_xlfn.XLOOKUP($A55,Inputs!$A:$A,Inputs!I:I,,0) -> 15824 | J55: =_xlfn.XLOOKUP($A55,Inputs!$A:$A,Inputs!J:J,,0) -> 13808 | K55: =_xlfn.XLOOKUP($A55,Inputs!$A:$A,Inputs!K:K,,0) -> 14630 | L55: =_xlfn.XLOOKUP($A55,Inputs!$A:$A,Inputs!L:L,,0) -> 11769 | M55: =_xlfn.XLOOKUP($A55,Inputs!$A:$A,Inputs!M:M,,0) -> 14651
A56: Total Liabilities | B56: =_xlfn.XLOOKUP($A56,Inputs!$A:$A,Inputs!B:B,,0) -> 53543 | C56: =_xlfn.XLOOKUP($A56,Inputs!$A:$A,Inputs!C:C,,0) -> 51321 | D56: =_xlfn.XLOOKUP($A56,Inputs!$A:$A,Inputs!D:D,,0) -> 55136 | E56: =_xlfn.XLOOKUP($A56,Inputs!$A:$A,Inputs!E:E,,0) -> 61739 | F56: =_xlfn.XLOOKUP($A56,Inputs!$A:$A,Inputs!F:F,,0) -> 54574 | G56: =_xlfn.XLOOKUP($A56,Inputs!$A:$A,Inputs!G:G,,0) -> 46979 | H56: =_xlfn.XLOOKUP($A56,Inputs!$A:$A,Inputs!H:H,,0) -> 44373 | I56: =_xlfn.XLOOKUP($A56,Inputs!$A:$A,Inputs!I:I,,0) -> 39948 | J56: =_xlfn.XLOOKUP($A56,Inputs!$A:$A,Inputs!J:J,,0) -> 35820 | K56: =_xlfn.XLOOKUP($A56,Inputs!$A:$A,Inputs!K:K,,0) -> 33133 | L56: =_xlfn.XLOOKUP($A56,Inputs!$A:$A,Inputs!L:L,,0) -> 29724 | M56: =_xlfn.XLOOKUP($A56,Inputs!$A:$A,Inputs!M:M,,0) -> 34130
A58: Total Debt | B58: =B49+B53+B50+B54 -> 26729 | C58: =C49+C53+C50+C54 -> 23421 | D58: =D49+D53+D50+D54 -> 25528 | E58: =E49+E53+E50+E54 -> 27754 | F58: =F49+F53+F50+F54 -> 28167 | G58: =G49+G53+G50+G54 -> 22736 | H58: =H49+H53+H50+H54 -> 24289 | I58: =I49+I53+I50+I54 -> 16075 | ... M58: =M49+M53+M50+M54 -> 12870
A59: Debt/Assets | B59: =IFERROR(B58/B44,"-") -> 0.37722455 | C59: =IFERROR(C58/C44,"-") -> 0.32929813 | D59: =IFERROR(D58/D44,"-") -> 0.36781212 | E59: =IFERROR(E58/E44,"-") -> 0.44471863 | F59: =IFERROR(F58/F44,"-") -> 0.48683824 | G59: =IFERROR(G58/G44,"-") -> 0.45457454 | H59: =IFERROR(H58/H44,"-") -> 0.53496465 | I59: =IFERROR(I58/I44,"-") -> 0.39812269 | ... M59: =IFERROR(M58/M44,"-") -> 0.33116332
A60: Net Debt | B60: =B58-B39 -> 23523 | C60: =C58-C39 -> 17819 | D60: =D58-D39 -> 15273 | E60: =E58-E39 -> 21853 | F60: =F58-F39 -> 22929 | G60: =G58-G39 -> 18511 | H60: =H58-H39 -> 20969 | I60: =I58-I39 -> 12599 | ... M60: =M58-M39 -> 5543
A62: Minority Interest | B62: =_xlfn.XLOOKUP($A62,Inputs!$A:$A,Inputs!B:B,,0) -> 7.25 | C62: =_xlfn.XLOOKUP($A62,Inputs!$A:$A,Inputs!C:C,,0) -> 15.88 | D62: =_xlfn.XLOOKUP($A62,Inputs!$A:$A,Inputs!D:D,,0) -> 14.07 | E62: =_xlfn.XLOOKUP($A62,Inputs!$A:$A,Inputs!E:E,,0) -> 9.83 | F62: =_xlfn.XLOOKUP($A62,Inputs!$A:$A,Inputs!F:F,,0) -> 14.27 | G62: =_xlfn.XLOOKUP($A62,Inputs!$A:$A,Inputs!G:G,,0) -> 13.95 | H62: =_xlfn.XLOOKUP($A62,Inputs!$A:$A,Inputs!H:H,,0) -> 25.01 | I62: =_xlfn.XLOOKUP($A62,Inputs!$A:$A,Inputs!I:I,,0) -> 22.83 | J62: =_xlfn.XLOOKUP($A62,Inputs!$A:$A,Inputs!J:J,,0) -> 19.34 | K62: =_xlfn.XLOOKUP($A62,Inputs!$A:$A,Inputs!K:K,,0) -> 14.05 | L62: =_xlfn.XLOOKUP($A62,Inputs!$A:$A,Inputs!L:L,,0) -> 10.19 | M62: =_xlfn.XLOOKUP($A62,Inputs!$A:$A,Inputs!M:M,,0) -> 60.63
A64: Shareholder's Equity | B64: =_xlfn.XLOOKUP($A64,Inputs!$A:$A,Inputs!B:B,,0) -> 17306.75 | C64: =_xlfn.XLOOKUP($A64,Inputs!$A:$A,Inputs!C:C,,0) -> 19787.12 | D64: =_xlfn.XLOOKUP($A64,Inputs!$A:$A,Inputs!D:D,,0) -> 14254.93 | E64: =_xlfn.XLOOKUP($A64,Inputs!$A:$A,Inputs!E:E,,0) -> 659.17 | F64: =_xlfn.XLOOKUP($A64,Inputs!$A:$A,Inputs!F:F,,0) -> 3268.73 | G64: =_xlfn.XLOOKUP($A64,Inputs!$A:$A,Inputs!G:G,,0) -> 3023.05 | H64: =_xlfn.XLOOKUP($A64,Inputs!$A:$A,Inputs!H:H,,0) -> 1004.99 | I64: =_xlfn.XLOOKUP($A64,Inputs!$A:$A,Inputs!I:I,,0) -> 406.17 | J64: =_xlfn.XLOOKUP($A64,Inputs!$A:$A,Inputs!J:J,,0) -> 2471.66 | K64: =_xlfn.XLOOKUP($A64,Inputs!$A:$A,Inputs!K:K,,0) -> 2323.95 | L64: =_xlfn.XLOOKUP($A64,Inputs!$A:$A,Inputs!L:L,,0) -> 6477.81 | M64: =_xlfn.XLOOKUP($A64,Inputs!$A:$A,Inputs!M:M,,0) -> 4672.37
A66: Cash Flow
A67: Operating CF | B67: =_xlfn.XLOOKUP($A67,Inputs!$A:$A,Inputs!B:B,,0) -> 10238 | C67: =_xlfn.XLOOKUP($A67,Inputs!$A:$A,Inputs!C:C,,0) -> 14104 | D67: =_xlfn.XLOOKUP($A67,Inputs!$A:$A,Inputs!D:D,,0) -> 15007 | E67: =_xlfn.XLOOKUP($A67,Inputs!$A:$A,Inputs!E:E,,0) -> 10459 | F67: =_xlfn.XLOOKUP($A67,Inputs!$A:$A,Inputs!F:F,,0) -> 8639 | G67: =_xlfn.XLOOKUP($A67,Inputs!$A:$A,Inputs!G:G,,0) -> 12711 | H67: =_xlfn.XLOOKUP($A67,Inputs!$A:$A,Inputs!H:H,,0) -> 1479 | I67: =_xlfn.XLOOKUP($A67,Inputs!$A:$A,Inputs!I:I,,0) -> 6473 | J67: =_xlfn.XLOOKUP($A67,Inputs!$A:$A,Inputs!J:J,,0) -> 7430 | K67: =_xlfn.XLOOKUP($A67,Inputs!$A:$A,Inputs!K:K,,0) -> 5726 | L67: =_xlfn.XLOOKUP($A67,Inputs!$A:$A,Inputs!L:L,,0) -> 7304 | M67: =_xlfn.XLOOKUP($A67,Inputs!$A:$A,Inputs!M:M,,0) -> 7216
A68: Investing CF | B68: =_xlfn.XLOOKUP($A68,Inputs!$A:$A,Inputs!B:B,,0) -> -7133 | C68: =_xlfn.XLOOKUP($A68,Inputs!$A:$A,Inputs!C:C,,0) -> -7472 | D68: =_xlfn.XLOOKUP($A68,Inputs!$A:$A,Inputs!D:D,,0) -> -3818 | E68: =_xlfn.XLOOKUP($A68,Inputs!$A:$A,Inputs!E:E,,0) -> -5283 | F68: =_xlfn.XLOOKUP($A68,Inputs!$A:$A,Inputs!F:F,,0) -> -6061 | G68: =_xlfn.XLOOKUP($A68,Inputs!$A:$A,Inputs!G:G,,0) -> -6330 | H68: =_xlfn.XLOOKUP($A68,Inputs!$A:$A,Inputs!H:H,,0) -> -4975 | I68: =_xlfn.XLOOKUP($A68,Inputs!$A:$A,Inputs!I:I,,0) -> -2566 | J68: =_xlfn.XLOOKUP($A68,Inputs!$A:$A,Inputs!J:J,,0) -> -5309 | K68: =_xlfn.XLOOKUP($A68,Inputs!$A:$A,Inputs!K:K,,0) -> -2801 | L68: =_xlfn.XLOOKUP($A68,Inputs!$A:$A,Inputs!L:L,,0) -> -2114 | M68: =_xlfn.XLOOKUP($A68,Inputs!$A:$A,Inputs!M:M,,0) -> -1335
A69: Net Capex | B69: =_xlfn.XLOOKUP($A69,Inputs!$A:$A,Inputs!B:B,,0) -> -5158 | C69: =_xlfn.XLOOKUP($A69,Inputs!$A:$A,Inputs!C:C,,0) -> -4769 | D69: =_xlfn.XLOOKUP($A69,Inputs!$A:$A,Inputs!D:D,,0) -> -4194 | E69: =_xlfn.XLOOKUP($A69,Inputs!$A:$A,Inputs!E:E,,0) -> -5412 | F69: =_xlfn.XLOOKUP($A69,Inputs!$A:$A,Inputs!F:F,,0) -> -6380 | G69: =_xlfn.XLOOKUP($A69,Inputs!$A:$A,Inputs!G:G,,0) -> -6238 | H69: =_xlfn.XLOOKUP($A69,Inputs!$A:$A,Inputs!H:H,,0) -> -5227 | I69: =_xlfn.XLOOKUP($A69,Inputs!$A:$A,Inputs!I:I,,0) -> -2965 | J69: =_xlfn.XLOOKUP($A69,Inputs!$A:$A,Inputs!J:J,,0) -> -2379 | K69: =_xlfn.XLOOKUP($A69,Inputs!$A:$A,Inputs!K:K,,0) -> -2328 | L69: =_xlfn.XLOOKUP($A69,Inputs!$A:$A,Inputs!L:L,,0) -> -2065 | M69: =_xlfn.XLOOKUP($A69,Inputs!$A:$A,Inputs!M:M,,0) -> -2153
A70: Investments & Acquisitions | B70: =_xlfn.XLOOKUP($A70,Inputs!$A:$A,Inputs!B:B,,0) -> -1329 | C70: =_xlfn.XLOOKUP($A70,Inputs!$A:$A,Inputs!C:C,,0) -> -755 | D70: =_xlfn.XLOOKUP($A70,Inputs!$A:$A,Inputs!D:D,,0) -> -602 | E70: =_xlfn.XLOOKUP($A70,Inputs!$A:$A,Inputs!E:E,,0) -> -20 | F70: =_xlfn.XLOOKUP($A70,Inputs!$A:$A,Inputs!F:F,,0) -> -6 | G70: =_xlfn.XLOOKUP($A70,Inputs!$A:$A,Inputs!G:G,,0) -> -2 | H70: =_xlfn.XLOOKUP($A70,Inputs!$A:$A,Inputs!H:H,,0) -> -134 | I70: =_xlfn.XLOOKUP($A70,Inputs!$A:$A,Inputs!I:I,,0) -> -547 | J70: =_xlfn.XLOOKUP($A70,Inputs!$A:$A,Inputs!J:J,,0) -> -30 | K70: =_xlfn.XLOOKUP($A70,Inputs!$A:$A,Inputs!K:K,,0) -> -63 | L70: =_xlfn.XLOOKUP($A70,Inputs!$A:$A,Inputs!L:L,,0) -> -179 | M70: =_xlfn.XLOOKUP($A70,Inputs!$A:$A,Inputs!M:M,,0) -> -100
A71: Financing CF | B71: =_xlfn.XLOOKUP($A71,Inputs!$A:$A,Inputs!B:B,,0) -> -5534 | C71: =_xlfn.XLOOKUP($A71,Inputs!$A:$A,Inputs!C:C,,0) -> -11185 | D71: =_xlfn.XLOOKUP($A71,Inputs!$A:$A,Inputs!D:D,,0) -> -6823 | E71: =_xlfn.XLOOKUP($A71,Inputs!$A:$A,Inputs!E:E,,0) -> -4517 | F71: =_xlfn.XLOOKUP($A71,Inputs!$A:$A,Inputs!F:F,,0) -> -1727 | G71: =_xlfn.XLOOKUP($A71,Inputs!$A:$A,Inputs!G:G,,0) -> -5692 | H71: =_xlfn.XLOOKUP($A71,Inputs!$A:$A,Inputs!H:H,,0) -> 3287 | I71: =_xlfn.XLOOKUP($A71,Inputs!$A:$A,Inputs!I:I,,0) -> -3140 | J71: =_xlfn.XLOOKUP($A71,Inputs!$A:$A,Inputs!J:J,,0) -> -1565 | K71: =_xlfn.XLOOKUP($A71,Inputs!$A:$A,Inputs!K:K,,0) -> -5161 | L71: =_xlfn.XLOOKUP($A71,Inputs!$A:$A,Inputs!L:L,,0) -> -7807 | M71: =_xlfn.XLOOKUP($A71,Inputs!$A:$A,Inputs!M:M,,0) -> -1817
A72: Dividends | B72: =_xlfn.XLOOKUP($A72,Inputs!$A:$A,Inputs!B:B,,0) -> -5372 | C72: =_xlfn.XLOOKUP($A72,Inputs!$A:$A,Inputs!C:C,,0) -> -5114 | D72: =_xlfn.XLOOKUP($A72,Inputs!$A:$A,Inputs!D:D,,0) -> -3437 | E72: =_xlfn.XLOOKUP($A72,Inputs!$A:$A,Inputs!E:E,,0) -> -3374 | F72: =_xlfn.XLOOKUP($A72,Inputs!$A:$A,Inputs!F:F,,0) -> -3194 | G72: =_xlfn.XLOOKUP($A72,Inputs!$A:$A,Inputs!G:G,,0) -> -3011 | H72: =_xlfn.XLOOKUP($A72,Inputs!$A:$A,Inputs!H:H,,0) -> -2771 | I72: =_xlfn.XLOOKUP($A72,Inputs!$A:$A,Inputs!I:I,,0) -> -2643 | J72: =_xlfn.XLOOKUP($A72,Inputs!$A:$A,Inputs!J:J,,0) -> -2525 | K72: =_xlfn.XLOOKUP($A72,Inputs!$A:$A,Inputs!K:K,,0) -> -2366 | L72: =_xlfn.XLOOKUP($A72,Inputs!$A:$A,Inputs!L:L,,0) -> -2260 | M72: =_xlfn.XLOOKUP($A72,Inputs!$A:$A,Inputs!M:M,,0) -> -2130
A73: Share buyback | B73: =_xlfn.XLOOKUP($A73,Inputs!$A:$A,Inputs!B:B,,0) -> -2250 | C73: =_xlfn.XLOOKUP($A73,Inputs!$A:$A,Inputs!C:C,,0) -> -3500 | D73: =_xlfn.XLOOKUP($A73,Inputs!$A:$A,Inputs!D:D,,0) -> -500 | E73: =_xlfn.XLOOKUP($A73,Inputs!$A:$A,Inputs!E:E,,0) -> -224 | F73: =_xlfn.XLOOKUP($A73,Inputs!$A:$A,Inputs!F:F,,0) -> -1004 | G73: =_xlfn.XLOOKUP($A73,Inputs!$A:$A,Inputs!G:G,,0) -> -1011 | H73: =_xlfn.XLOOKUP($A73,Inputs!$A:$A,Inputs!H:H,,0) -> -1813 | I73: =_xlfn.XLOOKUP($A73,Inputs!$A:$A,Inputs!I:I,,0) -> -2678 | J73: =_xlfn.XLOOKUP($A73,Inputs!$A:$A,Inputs!J:J,,0) -> -2702 | K73: =_xlfn.XLOOKUP($A73,Inputs!$A:$A,Inputs!K:K,,0) -> -2695 | L73: =_xlfn.XLOOKUP($A73,Inputs!$A:$A,Inputs!L:L,,0) -> -3838 | M73: =_xlfn.XLOOKUP($A73,Inputs!$A:$A,Inputs!M:M,,0) -> -1621
A74: FX | B74: =_xlfn.XLOOKUP($A74,Inputs!$A:$A,Inputs!B:B,,0) -> 0 | C74: =_xlfn.XLOOKUP($A74,Inputs!$A:$A,Inputs!C:C,,0) -> 0 | D74: =_xlfn.XLOOKUP($A74,Inputs!$A:$A,Inputs!D:D,,0) -> 0 | E74: =_xlfn.XLOOKUP($A74,Inputs!$A:$A,Inputs!E:E,,0) -> 0 | F74: =_xlfn.XLOOKUP($A74,Inputs!$A:$A,Inputs!F:F,,0) -> 0 | G74: =_xlfn.XLOOKUP($A74,Inputs!$A:$A,Inputs!G:G,,0) -> 0 | H74: =_xlfn.XLOOKUP($A74,Inputs!$A:$A,Inputs!H:H,,0) -> 0 | I74: =_xlfn.XLOOKUP($A74,Inputs!$A:$A,Inputs!I:I,,0) -> 0 | J74: =_xlfn.XLOOKUP($A74,Inputs!$A:$A,Inputs!J:J,,0) -> 0 | K74: =_xlfn.XLOOKUP($A74,Inputs!$A:$A,Inputs!K:K,,0) -> 0 | L74: =_xlfn.XLOOKUP($A74,Inputs!$A:$A,Inputs!L:L,,0) -> 0 | M74: =_xlfn.XLOOKUP($A74,Inputs!$A:$A,Inputs!M:M,,0) -> 0
A75: Changes in cash | B75: =_xlfn.XLOOKUP($A75,Inputs!$A:$A,Inputs!B:B,,0) -> -2429 | C75: =_xlfn.XLOOKUP($A75,Inputs!$A:$A,Inputs!C:C,,0) -> -4553 | D75: =_xlfn.XLOOKUP($A75,Inputs!$A:$A,Inputs!D:D,,0) -> 4366 | E75: =_xlfn.XLOOKUP($A75,Inputs!$A:$A,Inputs!E:E,,0) -> 659 | F75: =_xlfn.XLOOKUP($A75,Inputs!$A:$A,Inputs!F:F,,0) -> 851 | G75: =_xlfn.XLOOKUP($A75,Inputs!$A:$A,Inputs!G:G,,0) -> 689 | H75: =_xlfn.XLOOKUP($A75,Inputs!$A:$A,Inputs!H:H,,0) -> -209 | I75: =_xlfn.XLOOKUP($A75,Inputs!$A:$A,Inputs!I:I,,0) -> 767 | J75: =_xlfn.XLOOKUP($A75,Inputs!$A:$A,Inputs!J:J,,0) -> 556 | K75: =_xlfn.XLOOKUP($A75,Inputs!$A:$A,Inputs!K:K,,0) -> -2236 | L75: =_xlfn.XLOOKUP($A75,Inputs!$A:$A,Inputs!L:L,,0) -> -2617 | M75: =_xlfn.XLOOKUP($A75,Inputs!$A:$A,Inputs!M:M,,0) -> 4064
A77: Other Data
A78: Number of employees | B78: =_xlfn.XLOOKUP($A78,Inputs!$A:$A,Inputs!B:B,,0) -> #N/A | C78: =_xlfn.XLOOKUP($A78,Inputs!$A:$A,Inputs!C:C,,0) -> #N/A | D78: =_xlfn.XLOOKUP($A78,Inputs!$A:$A,Inputs!D:D,,0) -> #N/A | E78: =_xlfn.XLOOKUP($A78,Inputs!$A:$A,Inputs!E:E,,0) -> #N/A | F78: =_xlfn.XLOOKUP($A78,Inputs!$A:$A,Inputs!F:F,,0) -> #N/A | G78: =_xlfn.XLOOKUP($A78,Inputs!$A:$A,Inputs!G:G,,0) -> #N/A | H78: =_xlfn.XLOOKUP($A78,Inputs!$A:$A,Inputs!H:H,,0) -> #N/A | I78: =_xlfn.XLOOKUP($A78,Inputs!$A:$A,Inputs!I:I,,0) -> #N/A | J78: =_xlfn.XLOOKUP($A78,Inputs!$A:$A,Inputs!J:J,,0) -> #N/A | K78: =_xlfn.XLOOKUP($A78,Inputs!$A:$A,Inputs!K:K,,0) -> #N/A | L78: =_xlfn.XLOOKUP($A78,Inputs!$A:$A,Inputs!L:L,,0) -> #N/A | M78: =_xlfn.XLOOKUP($A78,Inputs!$A:$A,Inputs!M:M,,0) -> #N/A
A79: Shares Outstanding | B79: =_xlfn.XLOOKUP($A79,Inputs!$A:$A,Inputs!B:B,,0) -> #N/A | C79: =_xlfn.XLOOKUP($A79,Inputs!$A:$A,Inputs!C:C,,0) -> #N/A | D79: =_xlfn.XLOOKUP($A79,Inputs!$A:$A,Inputs!D:D,,0) -> #N/A | E79: =_xlfn.XLOOKUP($A79,Inputs!$A:$A,Inputs!E:E,,0) -> #N/A | F79: =_xlfn.XLOOKUP($A79,Inputs!$A:$A,Inputs!F:F,,0) -> #N/A | G79: =_xlfn.XLOOKUP($A79,Inputs!$A:$A,Inputs!G:G,,0) -> #N/A | H79: =_xlfn.XLOOKUP($A79,Inputs!$A:$A,Inputs!H:H,,0) -> #N/A | I79: =_xlfn.XLOOKUP($A79,Inputs!$A:$A,Inputs!I:I,,0) -> #N/A | J79: =_xlfn.XLOOKUP($A79,Inputs!$A:$A,Inputs!J:J,,0) -> #N/A | K79: =_xlfn.XLOOKUP($A79,Inputs!$A:$A,Inputs!K:K,,0) -> #N/A | L79: =_xlfn.XLOOKUP($A79,Inputs!$A:$A,Inputs!L:L,,0) -> #N/A | M79: =_xlfn.XLOOKUP($A79,Inputs!$A:$A,Inputs!M:M,,0) -> #N/A
A80: Float | B80: =_xlfn.XLOOKUP($A80,Inputs!$A:$A,Inputs!B:B,,0) -> 0.99896 | C80: =_xlfn.XLOOKUP($A80,Inputs!$A:$A,Inputs!C:C,,0) -> Yahoo finance | D80: =_xlfn.XLOOKUP($A80,Inputs!$A:$A,Inputs!D:D,,0) -> 0 | E80: =_xlfn.XLOOKUP($A80,Inputs!$A:$A,Inputs!E:E,,0) -> 0 | F80: =_xlfn.XLOOKUP($A80,Inputs!$A:$A,Inputs!F:F,,0) -> 0 | G80: =_xlfn.XLOOKUP($A80,Inputs!$A:$A,Inputs!G:G,,0) -> 0 | H80: =_xlfn.XLOOKUP($A80,Inputs!$A:$A,Inputs!H:H,,0) -> 0 | I80: =_xlfn.XLOOKUP($A80,Inputs!$A:$A,Inputs!I:I,,0) -> 0 | J80: =_xlfn.XLOOKUP($A80,Inputs!$A:$A,Inputs!J:J,,0) -> 0 | K80: =_xlfn.XLOOKUP($A80,Inputs!$A:$A,Inputs!K:K,,0) -> 0 | L80: =_xlfn.XLOOKUP($A80,Inputs!$A:$A,Inputs!L:L,,0) -> 0 | M80: =_xlfn.XLOOKUP($A80,Inputs!$A:$A,Inputs!M:M,,0) -> 0
A81: Insiders Own | B81: =_xlfn.XLOOKUP($A81,Inputs!$A:$A,Inputs!B:B,,0) -> 0.0001 | C81: =_xlfn.XLOOKUP($A81,Inputs!$A:$A,Inputs!C:C,,0) -> Yahoo finance | D81: =_xlfn.XLOOKUP($A81,Inputs!$A:$A,Inputs!D:D,,0) -> 0 | E81: =_xlfn.XLOOKUP($A81,Inputs!$A:$A,Inputs!E:E,,0) -> 0 | F81: =_xlfn.XLOOKUP($A81,Inputs!$A:$A,Inputs!F:F,,0) -> 0 | G81: =_xlfn.XLOOKUP($A81,Inputs!$A:$A,Inputs!G:G,,0) -> 0 | H81: =_xlfn.XLOOKUP($A81,Inputs!$A:$A,Inputs!H:H,,0) -> 0 | I81: =_xlfn.XLOOKUP($A81,Inputs!$A:$A,Inputs!I:I,,0) -> 0 | J81: =_xlfn.XLOOKUP($A81,Inputs!$A:$A,Inputs!J:J,,0) -> 0 | K81: =_xlfn.XLOOKUP($A81,Inputs!$A:$A,Inputs!K:K,,0) -> 0 | L81: =_xlfn.XLOOKUP($A81,Inputs!$A:$A,Inputs!L:L,,0) -> 0 | M81: =_xlfn.XLOOKUP($A81,Inputs!$A:$A,Inputs!M:M,,0) -> 0
A82: Fitch/ S&P Rating | B82: =_xlfn.XLOOKUP($A82,Inputs!$A:$A,Inputs!B:B,,0) -> A | C82: =_xlfn.XLOOKUP($A82,Inputs!$A:$A,Inputs!C:C,,0) -> 10-K | D82: =_xlfn.XLOOKUP($A82,Inputs!$A:$A,Inputs!D:D,,0) -> 0 | E82: =_xlfn.XLOOKUP($A82,Inputs!$A:$A,Inputs!E:E,,0) -> 0 | F82: =_xlfn.XLOOKUP($A82,Inputs!$A:$A,Inputs!F:F,,0) -> 0 | G82: =_xlfn.XLOOKUP($A82,Inputs!$A:$A,Inputs!G:G,,0) -> 0 | H82: =_xlfn.XLOOKUP($A82,Inputs!$A:$A,Inputs!H:H,,0) -> 0 | I82: =_xlfn.XLOOKUP($A82,Inputs!$A:$A,Inputs!I:I,,0) -> 0 | J82: =_xlfn.XLOOKUP($A82,Inputs!$A:$A,Inputs!J:J,,0) -> 0 | K82: =_xlfn.XLOOKUP($A82,Inputs!$A:$A,Inputs!K:K,,0) -> 0 | L82: =_xlfn.XLOOKUP($A82,Inputs!$A:$A,Inputs!L:L,,0) -> 0 | M82: =_xlfn.XLOOKUP($A82,Inputs!$A:$A,Inputs!M:M,,0) -> 0
A83: Dividend Yield | B83: =_xlfn.XLOOKUP($A83,Inputs!$A:$A,Inputs!B:B,,0) -> #N/A | C83: =_xlfn.XLOOKUP($A83,Inputs!$A:$A,Inputs!C:C,,0) -> #N/A | D83: =_xlfn.XLOOKUP($A83,Inputs!$A:$A,Inputs!D:D,,0) -> #N/A | E83: =_xlfn.XLOOKUP($A83,Inputs!$A:$A,Inputs!E:E,,0) -> #N/A | F83: =_xlfn.XLOOKUP($A83,Inputs!$A:$A,Inputs!F:F,,0) -> #N/A | G83: =_xlfn.XLOOKUP($A83,Inputs!$A:$A,Inputs!G:G,,0) -> #N/A | H83: =_xlfn.XLOOKUP($A83,Inputs!$A:$A,Inputs!H:H,,0) -> #N/A | I83: =_xlfn.XLOOKUP($A83,Inputs!$A:$A,Inputs!I:I,,0) -> #N/A | J83: =_xlfn.XLOOKUP($A83,Inputs!$A:$A,Inputs!J:J,,0) -> #N/A | K83: =_xlfn.XLOOKUP($A83,Inputs!$A:$A,Inputs!K:K,,0) -> #N/A | L83: =_xlfn.XLOOKUP($A83,Inputs!$A:$A,Inputs!L:L,,0) -> #N/A | M83: =_xlfn.XLOOKUP($A83,Inputs!$A:$A,Inputs!M:M,,0) -> #N/A
A84: Daily Volume in Millions of USD | B84: =_xlfn.XLOOKUP($A84,Inputs!$A:$A,Inputs!B:B,,0) -> 4.9 | C84: =_xlfn.XLOOKUP($A84,Inputs!$A:$A,Inputs!C:C,,0) -> Yahoo Finance | D84: =_xlfn.XLOOKUP($A84,Inputs!$A:$A,Inputs!D:D,,0) -> 0 | E84: =_xlfn.XLOOKUP($A84,Inputs!$A:$A,Inputs!E:E,,0) -> 0 | F84: =_xlfn.XLOOKUP($A84,Inputs!$A:$A,Inputs!F:F,,0) -> 0 | G84: =_xlfn.XLOOKUP($A84,Inputs!$A:$A,Inputs!G:G,,0) -> 0 | H84: =_xlfn.XLOOKUP($A84,Inputs!$A:$A,Inputs!H:H,,0) -> 0 | I84: =_xlfn.XLOOKUP($A84,Inputs!$A:$A,Inputs!I:I,,0) -> 0 | J84: =_xlfn.XLOOKUP($A84,Inputs!$A:$A,Inputs!J:J,,0) -> 0 | K84: =_xlfn.XLOOKUP($A84,Inputs!$A:$A,Inputs!K:K,,0) -> 0 | L84: =_xlfn.XLOOKUP($A84,Inputs!$A:$A,Inputs!L:L,,0) -> 0 | M84: =_xlfn.XLOOKUP($A84,Inputs!$A:$A,Inputs!M:M,,0) -> 0
B86: 2020 | C86: 2021 | D86: 2022
A87: Short % of Float | B87: 0 | C87: 0 | D87: 0
A88: EPS | B88: 0 | C88: 0 | D88: 0
A90: Corporate Bonds 3, 5 Y 10 | B90: Average Price | C90: Moody's | D90: YTM | E90: DIVISA
B91: =VLOOKUP($A91,Inputs!$A$5:$M$98,MATCH(B$4,Inputs!$B$5:$M$5,0)+1,FALSE) -> #N/A | C91: =VLOOKUP($A91,Inputs!$A$5:$M$98,MATCH(C$4,Inputs!$B$5:$M$5,0)+1,FALSE) -> #N/A | D91: =VLOOKUP($A91,Inputs!$A$5:$M$98,MATCH(D$4,Inputs!$B$5:$M$5,0)+1,FALSE) -> #N/A | E91: =VLOOKUP($A91,Inputs!$A$5:$M$98,MATCH(E$4,Inputs!$B$5:$M$5,0)+1,FALSE) -> #N/A

Sheet Sector Impact
E2: Sector | F2: Sub-Industry | H2: Low | K2: Sector | L2: Environment | Q2: Social
E3: Communication Services | F3: Interactive Home Entertainment | H3: Medium | L3: CO2 | M3: Water | N3: Energy | O3: Waste | P3: Degradation | Q3: Turnover | R3: Compensation | S3: Reputation | T3: Discrimination | U3: Security | V3: Damage | W3: Pension | X3: Supply | Y3: Community | Z3: Public | AA3: Litigation
E4: Communication Services | F4: Interactive Media & Services | H4: High | K4: Communication Services | L4: Low | M4: Low | N4: Medium | O4: Low | P4: Low | Q4: Medium | R4: Medium | S4: Low | T4: Low | U4: High | V4: Low | W4: Low | X4: Low | Y4: Low | Z4: Low | AA4: Medium
B5: Environmental | E5: Communication Services | F5: Integrated Telecommunication Services | H5: Very High | K5: Consumer Discretionary | L5: Low | M5: Low | N5: Medium | O5: Medium | P5: Low | Q5: Medium | R5: Medium | S5: Low | T5: Low | U5: Medium | V5: Medium | W5: Medium | X5: High | Y5: Low | Z5: High | AA5: Low
B6: Direct CO2 emissions | E6: Communication Services | F6: Cable & Satellite | K6: Consumer Staples | L6: High | M6: Very High | N6: High | O6: High | P6: High | Q6: Medium | R6: High | S6: High | T6: Low | U6: Medium | V6: Medium | W6: Low | X6: High | Y6: Low | Z6: Very High | AA6: Low
B7: Total Water Use | E7: Communication Services | F7: Broadcasting | K7: Energy | L7: Very High | M7: Very High | N7: Medium | O7: Very High | P7: High | Q7: High | R7: Medium | S7: Medium | T7: Medium | U7: Medium | V7: High | W7: Medium | X7: Medium | Y7: High | Z7: High | AA7: Low
K8: Renewable Energy | L8: Low | M8: Low | N8: Low | O8: Medium | P8: Medium | Q8: Low | R8: Medium | S8: Medium | T8: High | U8: Medium | V8: Low | W8: Low | X8: Medium | Y8: Medium | Z8: High | AA8: Low
B9: Total Energy Consumption | E9: Communication Services | F9: Movies & Entertainment | K9: Financials | L9: Low | M9: Low | N9: Low | O9: Low | P9: Low | Q9: Low | R9: Low | S9: Medium | T9: High | U9: Medium | V9: Low | W9: Low | X9: Low | Y9: Low | Z9: Medium | AA9: Low
K10: Forestry | L10: Low | M10: Medium | N10: Low | O10: Medium | P10: High | Q10: Low | R10: Low | S10: Low | T10: Low | U10: Low | V10: Low | W10: Low | X10: Low | Y10: Medium | Z10: Low | AA10: Low
B11: Waste Management | E11: Communication Services | F11: Advertising | K11: Health Care | L11: Low | M11: Medium | N11: Low | O11: Low | P11: Low | Q11: Low | R11: Low | S11: Medium | T11: Low | U11: High | V11: Low | W11: Low | X11: Low | Y11: Low | Z11: Low | AA11: Low
B12: Land Degradation/Deforestation/Biodiversity loss/Animal sufering/... | E12: Communication Services | F12: Alternative Carriers | K12: Industrials | L12: Very High | M12: Very High | N12: Very High | O12: High | P12: High | Q12: Low | R12: Medium | S12: High | T12: Very High | U12: Medium | V12: Very High | W12: Medium | X12: Very High | Y12: Very High | Z12: Very High | AA12: High
B13: Social | E13: Communication Services | F13: Publishing | K13: Information Technology | L13: Medium | M13: Low | N13: High | O13: Low | P13: Low | Q13: Low | R13: Low | S13: Low | T13: Low | U13: High | V13: Low | W13: Low | X13: Low | Y13: Low | Z13: Medium | AA13: Very High
B14: Employee turnover | E14: Communication Services | F14: Wireless Telecommunication Services | K14: Materials | L14: Very High | M14: Very High | N14: Very High | O14: Very High | P14: High | Q14: High | R14: High | S14: Medium | T14: High | U14: Low | V14: Very High | W14: Medium | X14: Medium | Y14: Very High | Z14: High | AA14: Medium
B15: Salaries and compensation | E15: Consumer Discretionary | F15: Automotive Retail | K15: Real Estate | L15: Low | M15: Low | N15: Medium | O15: Low | P15: Low | Q15: Medium | R15: Low | S15: Low | T15: Low | U15: High | V15: Low | W15: Medium | X15: Low | Y15: Medium | Z15: Low | AA15: Low
B16: Reputational issues | E16: Consumer Discretionary | F16: Internet & Direct Marketing Retail | K16: Utilities | L16: Very High | M16: High | N16: High | O16: Medium | P16: High | Q16: Low | R16: Medium | S16: Medium | T16: Low | U16: Medium | V16: Medium | W16: Medium | X16: Medium | Y16: Low | Z16: Medium | AA16: Low
B17: Discrimination issues | E17: Consumer Discretionary | F17: Auto Parts & Equipment
B18: Job security | E18: Consumer Discretionary | F18: Specialty Stores
B19: Health injuries | E19: Consumer Discretionary | F19: Computer & Electronics Retail | L19: Communication Services | M19: Consumer Discretionary | N19: Consumer Staples | O19: Energy | P19: Financials | Q19: Health Care | R19: Industrials | S19: Information Technology | T19: Materials | U19: Real Estate | V19: Utilities
B20: PXP? | E20: Consumer Discretionary | F20: Hotels, Resorts & Cruise Lines | L20: Interactive Home Entertainment | M20: Automotive Retail | N20: Tobacco | O20: Oil & Gas Exploration & Production | P20: Life & Health Insurance | Q20: Health Care Equipment | R20: Industrial Conglomerates | S20: IT Consulting & Other Services | T20: Industrial Gases | U20: Office REITs | V20: Independent Power Producers & Energy Traders
B21: Supply chain | E21: Consumer Discretionary | F21: Restaurants | L21: Interactive Media & Services | M21: Internet & Direct Marketing Retail | N21: Agricultural Products | O21: Oil & Gas Equipment & Services | P21: Property & Casualty Insurance | Q21: Pharmaceuticals | R21: Airlines | S21: Application Software | T21: Specialty Chemicals | U21: Specialized REITs | V21: Electric Utilities
B22: Community involvement | E22: Consumer Discretionary | F22: Homebuilding | L22: Integrated Telecommunication Services | M22: Auto Parts & Equipment | N22: Distillers & Vintners | O22: Integrated Oil & Gas | P22: Consumer Finance | Q22: Health Care Supplies | R22: Building Products | S22: Semiconductors | T22: Paper Packaging | U22: Residential REITs | V22: Multi-Utilities
B23: Public Sector | E23: Consumer Discretionary | F23: General Merchandise Stores | L23: Cable & Satellite | M23: Specialty Stores | N23: Packaged Foods & Meats | O23: Oil & Gas Refining & Marketing | P23: Asset Management & Custody Banks | Q23: Health Care Distributors | R23: Electrical Components & Equipment | S23: Internet Services & Infrastructure | T23: Metal & Glass Containers | U23: Real Estate Services | V23: Water Utilities
B24: Litigation | E24: Consumer Discretionary | F24: Automobile Manufacturers | L24: Broadcasting | M24: Computer & Electronics Retail | N24: Household Products | O24: Oil & Gas Storage & Transportation | P24: Insurance Brokers | Q24: Biotechnology | R24: Aerospace & Defense | S24: Electronic Components | T24: Fertilizers & Agricultural Chemicals | U24: Industrial REITs | V24: Gas Utilities
E25: Consumer Discretionary | F25: Apparel Retail | L25: Movies & Entertainment | M25: Hotels, Resorts & Cruise Lines | N25: Soft Drinks | P25: Multi-line Insurance | Q25: Managed Health Care | R25: Air Freight & Logistics | S25: Technology Hardware, Storage & Peripherals | T25: Commodity Chemicals | U25: Retail REITs
E26: Consumer Discretionary | F26: Consumer Electronics | L26: Advertising | M26: Restaurants | N26: Hypermarkets & Super Centers | P26: Diversified Banks | Q26: Life Sciences Tools & Services | R26: Construction Machinery & Heavy Trucks | S26: Semiconductor Equipment | T26: Diversified Chemicals | U26: Health Care REITs
E27: Consumer Discretionary | F27: Apparel, Accessories & Luxury Goods | L27: Alternative Carriers | M27: Homebuilding | N27: Personal Products | P27: Multi-Sector Holdings | Q27: Health Care Technology | R27: Diversified Support Services | S27: Communications Equipment | T27: Copper | U27: Hotel & Resort REITs
E28: Consumer Discretionary | F28: Leisure Products | L28: Publishing | M28: General Merchandise Stores | N28: Food Retail | P28: Financial Exchanges & Data | Q28: Health Care Services | R28: Railroads | S28: Data Processing & Outsourced Services | T28: Construction Materials
E29: Consumer Discretionary | F29: Home Improvement Retail | L29: Wireless Telecommunication Services | M29: Automobile Manufacturers | N29: Brewers | P29: Investment Banking & Brokerage | Q29: Health Care Facilities | R29: Industrial Machinery | S29: Technology Distributors | T29: Gold
E30: Consumer Discretionary | F30: Casinos & Gaming | M30: Apparel Retail | N30: Food Distributors | P30: Regional Banks | R30: Agricultural & Farm Machinery | S30: Electronic Equipment & Instruments | T30: Steel
E31: Consumer Discretionary | F31: Home Furnishings | M31: Consumer Electronics | N31: Drug Retail | P31: Reinsurance | R31: Research & Consulting Services | S31: Systems Software
E32: Consumer Discretionary | F32: Distributors | M32: Apparel, Accessories & Luxury Goods | P32: Thrifts & Mortgage Finance | R32: Construction & Engineering | S32: Electronic Manufacturing Services
E33: Consumer Discretionary | F33: Housewares & Specialties | M33: Leisure Products | R33: Trucking
E34: Consumer Discretionary | F34: Household Appliances | M34: Home Improvement Retail | R34: Environmental & Facilities Services
E35: Consumer Staples | F35: Tobacco | M35: Casinos & Gaming | R35: Human Resource & Employment Services
E36: Consumer Staples | F36: Agricultural Products | M36: Home Furnishings | R36: Trading Companies & Distributors
E37: Consumer Staples | F37: Distillers & Vintners | M37: Distributors
E38: Consumer Staples | F38: Packaged Foods & Meats | M38: Housewares & Specialties
E39: Consumer Staples | F39: Household Products | M39: Household Appliances
E40: Consumer Staples | F40: Soft Drinks
E41: Consumer Staples | F41: Hypermarkets & Super Centers
E42: Consumer Staples | F42: Personal Products
E43: Consumer Staples | F43: Food Retail
E44: Consumer Staples | F44: Brewers
E45: Consumer Staples | F45: Food Distributors
E46: Consumer Staples | F46: Drug Retail
E47: Energy | F47: Oil & Gas Exploration & Production
E48: Energy | F48: Oil & Gas Equipment & Services
E49: Energy | F49: Integrated Oil & Gas
E50: Energy | F50: Oil & Gas Refining & Marketing
E51: Energy | F51: Oil & Gas Storage & Transportation
... E128: Utilities | F128: Gas Utilities

Sheet Inputs
G2: Figures in Millions of USD
G3: Company | H3: UNITED PARCEL SERVICE, INC. (XNYS:UPS)
D4: Report in millions USD
A5: RESULTS | B5: 2023 | C5: =B5-1 -> 2022 | D5: =C5-1 -> 2021 | E5: =D5-1 -> 2020 | F5: =E5-1 -> 2019 | G5: =F5-1 -> 2018 | H5: =G5-1 -> 2017 | I5: =H5-1 -> 2016 | J5: =I5-1 -> 2015 | ... M5: =L5-1 -> 2012 | Q5: Hoja | R5: Nombre campo Bloomberg | T5: Cambio de signo | Z5: 2016 | AA5: 2015 | AB5: 2014 | AC5: 2013 | AD5: 2012 | AE5: 2011 | AF5: 2010 | AG5: 2009
A6: Net Sales | B6: 90958 | C6: 100338 | D6: 97287 | E6: 84628 | F6: 74094 | G6: 71861 | H6: 65872 | I6: 60906 | J6: 58363 | K6: 58232 | L6: 55438 | M6: 54127 | N6: Income Statement | O6: Sales | Q6: Ingreso | R6: Ingreso | Z6: 38537 | AA6: 47011 | AB6: 55184 | AC6: 55656 | AD6: 65875 | AE6: 60138 | AF6: 42588 | AG6: 32396
A7: Gross Profit | B7: =B8 -> 9141 | C7: =C8 -> 13094 | D7: =D8 -> 12810 | E7: =E8 -> 7684 | F7: =F8 -> 7798 | G7: =G8 -> 7024 | H7: =H8 -> 7529 | I7: =I8 -> 5467 | ... M7: =M8 -> 1343 | N7: Income Statement | O7: =+A7 -> Gross Profit | Q7: Ingreso | R7: + Coste de bienes y servicios | Z7: =Z6-28044 -> 10493 | AA7: =AA6-33546 -> 13465 | AB7: =AB6-40718 -> 14466 | AC7: =AC6-40727 -> 14929 | AD7: =+AD6-47055 -> 18820 | AE7: =+AE6-43578 -> 16560 | AF7: =+AF6-30367 -> 12221 | AG7: =+AG6-23886 -> 8510
A8: Operating Income | B8: 9141 | C8: 13094 | D8: 12810 | E8: 7684 | F8: 7798 | G8: 7024 | H8: 7529 | I8: 5467 | J8: 7668 | K8: 4968 | L8: 7034 | M8: 1343 | N8: Income Statement | O8: Operating Income | Q8: Ingreso | R8: + Ventas, generales y admin | Z8: =Z7-4383 -> 6110 | AA8: =AA7-4951 -> 8514 | AB8: =AB7-6529 -> 7937 | AC8: =AC7-5547 -> 9382 | AD8: =AD7-5919-2466-797-580-485 -> 8573 | AE8: =+AE7-5203-2297-826-1081 -> 7153 | AF8: =+AF7-4248-1905-914-1191 -> 3963 | AG8: =+AG7-3645-1421-1045-1822 -> 577
A9: Other Expenses (Revenues) | B9: 0 | C9: 2435 | D9: 4479 | E9: -5139 | F9: -1493 | G9: -400 | H9: 72 | I9: 50 | J9: 15 | K9: 22 | L9: 20 | M9: 24 | N9: Income Statement | O9: investment income+other income expense+income loss+minority interest+non controlling interest+share onf net profit+gain8losses) on equity investments+share of result from associates nd joint ventures+non operating profit+ | Q9: Ingreso | R9: + Investigación y desarrollo | S9: + Coste de financiación de beneficio | T9: + Otro gasto operativo | U9: - Beneficio (pérdida) de filiales | V9: - Minoritarios | Z9: =1853+596+595+1904+6+8 -> 4962 | AA9: =2119+587+2023+11 -> 4740 | AB9: =2380+624+1619-8+16 -> 4631 | AC9: =2046+727+981+6+14 -> 3774 | AD9: =-14+41 -> 27 | AE9: 53 | AF9: =58+24 -> 82 | AG9: =12-68 -> -56
A10: Net Financial Cost | B10: -568 | C10: -704 | D10: -694 | E10: -701 | F10: -653 | G10: -605 | H10: -453 | I10: -381 | J10: -341 | K10: -353 | L10: -380 | M10: -393 | N10: Income Statement | O10: interest expense+financial income and expenses+other financial expense-income+interest and other net+ | Q10: Ingreso | R10: - Ingreso (pérdida) no operacional | Z10: =505+518 -> 1023 | AA10: =507-161 -> 346 | AB10: =484-322 -> 162 | AC10: =465+35 -> 500 | AD10: =467-130 -> 337 | AE10: =396+32 -> 428 | AF10: =343-130 -> 213 | AG10: =389-381 -> 8
A11: Taxes | B11: -1865 | C11: -3277 | D11: -3705 | E11: -501 | F11: -1212 | G11: -1228 | H11: -2238 | I11: -1705 | J11: -2498 | K11: -1605 | L11: -2302 | M11: -167 | N11: Income Statement | O11: Taxes | Q11: Ingreso | R11: - Gasto de impuesto a la renta (Beneficio) | Z11: 192 | AA11: 916 | AB11: 692 | AC11: 1319 | AD11: =2528 -> 2528 | AE11: =1720 -> 1720 | AF11: =968 -> 968 | AG11: =-270 -> -270
A12: Net Income | B12: 6708 | C12: 11548 | D12: 12890 | E12: 1343 | F12: 4440 | G12: 4791 | H12: 4910 | I12: 3431 | J12: 4844 | K12: 3032 | L12: 4372 | M12: 807 | N12: Income Statement | O12: Net Income | Q12: Flujo de caja | R12: + Ingreso neto | Z12: -67 | AA12: 2512 | AB12: 2452 | AC12: 3789 | AD12: 5681 | AE12: =4928+24 -> 4952 | AF12: 2700 | AG12: 895
B13: =SUM(B8:B11) -> 6708 | C13: =SUM(C8:C11) -> 11548 | D13: =SUM(D8:D11) -> 12890 | E13: =SUM(E8:E11) -> 1343 | F13: =SUM(F8:F11) -> 4440 | G13: =SUM(G8:G11) -> 4791 | H13: =SUM(H8:H11) -> 4910 | I13: =SUM(I8:I11) -> 3431 | ... M13: =SUM(M8:M11) -> 807 | Z13: =Z8-Z10-Z9-Z11 -> -67 | AA13: =AA8-AA10-AA9-AA11 -> 2512 | AB13: =AB8-AB10-AB9-AB11 -> 2452 | AC13: =AC8-AC10-AC9-AC11 -> 3789 | AD13: =AD8-AD10-AD9-AD11 -> 5681 | AE13: =AE8-AE10-AE9-AE11 -> 4952 | AF13: =AF8-AF10-AF9-AF11 -> 2700 | AG13: =AG8-AG10-AG9-AG11 -> 895
A14: FINANCIAL POSITION | B14: =B12-B13 -> 0 | C14: =C12-C13 -> 0 | D14: =D12-D13 -> 0 | E14: =E12-E13 -> 0 | F14: =F12-F13 -> 0 | G14: =G12-G13 -> 0 | H14: =H12-H13 -> 0 | I14: =I12-I13 -> 0 | ... M14: =M12-M13 -> 0 | Z14: =Z12-Z13 -> 0 | AA14: =AA12-AA13 -> 0 | AB14: =AB12-AB13 -> 0 | AC14: =AC12-AC13 -> 0 | AD14: =AD12-AD13 -> 0 | AE14: =AE12-AE13 -> 0 | AF14: =AF12-AF13 -> 0 | AG14: =AG12-AG13 -> 0
A16: Weighted Average Shares (Basic NI) | B16: 13.26 | C16: 14.75 | D16: 1.55 | E16: 5.14 | F16: 5.53 | G16: 5.63 | H16: 5.64 | I16: 3.89 | J16: 5.38 | K16: 3.31 | L16: 4.65 | M16: 0.84
A17: Weighted Average Shares (Diluted NI) | B17: 13.2 | C17: 14.68 | D17: 1.54 | E17: 5.11 | F17: 5.51 | G17: 5.61 | H17: 5.61 | I17: 3.87 | J17: 5.35 | K17: 3.28 | L17: 4.61 | M17: 0.81
A19: Net gains (losses) from ForEx | B19: 33 | C19: -100 | D19: -21 | E19: 13 | F19: 20 | G19: -91 | H19: 53 | I19: -21 | J19: -117 | K19: -138 | L19: -45 | M19: 229
A20: Total Comprehensive Income | B20: 4499 | C20: 13277 | D20: 16725 | E20: 227 | F20: 3437 | G20: 5399 | H20: 4526 | I20: 2488 | J20: 4898 | K20: -102 | L20: 7266 | M20: 556
A22: Changes Net Working Capital | B22: =B23-C23 -> 56 | C22: =C23-D23 -> 1365 | D22: =D23-E23 -> -189 | E22: =E23-F23 -> 847 | F22: =F23-G23 -> -1446 | G22: =G23-H23 -> -1622 | H22: =H23-I23 -> 877 | I22: =I23-J23 -> -1139 | ... L22: =L23-M23 -> 1717 | N22: cash flows | O22: NWC | Q22: Flujo de caja
A23: Net Working Capital | B23: =B27-B42-B28 -> -1469 | C23: =C27-C42-C28 -> -1525 | D23: =D27-D42-D28 -> -2890 | E23: =E27-E42-E28 -> -2701 | F23: =F27-F42-F28 -> -3548 | G23: =G27-G42-G28 -> -2102 | H23: =H27-H42-H28 -> -480 | I23: =I27-I42-I28 -> -1357 | ... M23: =M27-M42-M28 -> -126
A24: 2625 | B24: 2625 | C24: 2625 | D24: 2625 | E24: 2625 | F24: 2625 | G24: 2625 | H24: 2625 | I24: 2625 | J24: 2625 | K24: 2625 | L24: 2625 | M24: 2625 | N24: 2625 | Q24: Flujo de caja | R24: + Dividendos pagados | T24: Cambiar signo | Z24: 1799 | AA24: 1757 | AB24: 1620 | AC24: 1111 | AD24: 1617 | AE24: 1159 | AF24: 1084 | AG24: 1029
A25: BALANCE SHEET | B25: 2625 | C25: 2625 | D25: 2625 | E25: 2625 | F25: 2625 | G25: 2625 | H25: 2625 | I25: 2625 | J25: 2625 | K25: 2625 | L25: 2625 | M25: 2625 | N25: 2625 | Q25: Flujo de caja | R25: + Aumento en capital | S25: + Baja en capital | T25: Cambiar signo y hacer suma | Z25: 23 | AA25: =-33+2025 -> 1992 | AB25: 3817 | AC25: 1776 | AD25: -244 | AE25: -312 | AF25: -449 | AG25: -110
A26: ASSETS | O26: 2625
A27: Current | B27: 19413 | C27: 22217 | D27: 24934 | E27: 20216 | F27: 17103 | G27: 16210 | H27: 15548 | I27: 13849 | J27: 13208 | K27: 11808 | L27: 13387 | M27: 15591
A28: Cash & Eq. | B28: 3206 | C28: 5602 | D28: 10255 | E28: 5901 | F28: 5238 | G28: 4225 | H28: 3320 | I28: 3476 | J28: 2730 | K28: 2291 | L28: 4665 | M28: 7327 | N28: Balance Sheet | O28: Cash & Eq.
A29: Accounts Receivable | B29: 11342 | C29: 12729 | D29: 10255 | E29: 5910 | F29: 5238 | G29: 8958 | H29: 8773 | I29: 7695 | J29: 7134 | K29: 6661 | L29: 6502 | M29: 6111 | N29: Balance Sheet | O29: Accounts Receivable
A30: Inventory | B30: 935 | C30: 889 | D30: 717 | E30: 620 | F30: 511 | G30: 421 | H30: 404 | I30: 342 | J30: 308 | K30: 344 | L30: 403 | M30: 393 | N30: Balance Sheet | O30: Inventory | Q30: Balance | R30: + Efectivo, equivalentes y STI | Z30: 7168 | AA30: 6460 | AB30: 7341 | AC30: 6081 | AD30: 5490 | AE30: 3057 | AF30: 3592 | AG30: 4867
A31: Other Current Assets | B31: =B27-SUM(B28:B30) -> 3930 | C31: =C27-SUM(C28:C30) -> 2997 | D31: =D27-SUM(D28:D30) -> 3707 | E31: =E27-SUM(E28:E30) -> 7785 | F31: =F27-SUM(F28:F30) -> 6116 | G31: =G27-SUM(G28:G30) -> 2606 | H31: =H27-SUM(H28:H30) -> 3051 | I31: =I27-SUM(I28:I30) -> 2336 | ... M31: =M27-SUM(M28:M30) -> 1760 | N31: Balance Sheet | O31: Inventory | Q31: Balance | R31: + Cuentas y notas por cobrar | S31: + Activos derivados y de cobertura | T31: + Inversiones y cuentas por cobrar a LP | Z31: =5981+8522+1029+13556 -> 29088 | AA31: =6695+8991+1170+13651 -> 30507 | AB31: =7737+9027+1364+14644 -> 32772 | AC31: 33499 | AD31: 33911 | AE31: 31031 | AF31: 28849 | AG31: 27162
A32: Non-current | B32: =B38-B27 -> 51444 | C32: =C38-C27 -> 48907 | D32: =D38-D27 -> 44471 | E32: =E38-E27 -> 42192 | F32: =F38-F27 -> 40754 | G32: =G38-G27 -> 33806 | H32: =H38-H27 -> 29855 | I32: =I38-I27 -> 26528 | ... M32: =M38-M27 -> 23272
A33: Property, Plant and Equipment | B33: 36945 | C33: 34719 | D33: 33475 | E33: 32254 | F33: 30482 | G33: 26576 | H33: 22118 | I33: 18800 | J33: 18352 | K33: 18281 | L33: 17961 | M33: 17894 | Q33: Balance | R33: + Inventarios | Z33: 8614 | AA33: 9700 | AB33: 12205 | AC33: 12625 | AD33: 15547 | AE33: 14544 | AF33: 9587 | AG33: 6360
A34: Operating leases | B34: 4308 | C34: 3755 | D34: 3562 | E34: 3073 | F34: 2856 | G34: 1654 | H34: 1656 | I34: 1653 | J34: 1721 | K34: 1791 | L34: 1794 | M34: 1804
A35: Equity Method Investments | B35: 0 | C35: 0 | D35: 0 | E35: 0 | F35: 0 | G35: 0 | H35: 0 | I35: 0 | J35: 0 | K35: 0 | L35: 0 | M35: 0
A36: Other Non-Current Assets | B36: =B32-SUM(B33:B35) -> 10191 | C36: =C32-SUM(C33:C35) -> 10433 | D36: =D32-SUM(D33:D35) -> 7434 | E36: =E32-SUM(E33:E35) -> 6865 | F36: =F32-SUM(F33:F35) -> 7416 | G36: =G32-SUM(G33:G35) -> 5576 | H36: =H32-SUM(H33:H35) -> 6081 | I36: =I32-SUM(I33:I35) -> 6075 | ... M36: =M32-SUM(M33:M35) -> 3574 | N36: Balance Sheet | O36: Property, Plant and Equipment
A37: Other Assets | B37: =B31+B36 -> 14121 | C37: =C31+C36 -> 13430 | D37: =D31+D36 -> 11141 | E37: =E31+E36 -> 14650 | F37: =F31+F36 -> 13532 | G37: =G31+G36 -> 8182 | H37: =H31+H36 -> 9132 | I37: =I31+I36 -> 8411 | ... M37: =M31+M36 -> 5334 | N37: Balance Sheet
A38: Total Assets | B38: 70857 | C38: 71124 | D38: 69405 | E38: 62408 | F38: 57857 | G38: 50016 | H38: 45403 | I38: 40377 | J38: 38311 | K38: 35471 | L38: 36212 | M38: 38863 | N38: Balance Sheet | O38: Total Assets | Q38: Balance | R38: + Propiedad, planta y equipo; neto | Z38: 15322 | AA38: 16090 | AB38: =16577 -> 16577 | AC38: 17075 | AD38: 16461 | AE38: 14395 | AF38: 12539 | AG38: 12386
N39: Balance Sheet | Z39: =Z40-SUM(Z30:Z38) -> 14512 | AA39: =AA40-SUM(AA30:AA38) -> 15585 | AB39: =AB40-SUM(AB30:AB38) -> 15786 | AC39: =AC40-SUM(AC30:AC38) -> 15616 | AD39: =AD40-SUM(AD30:AD38) -> 17947 | AE39: =AE40-SUM(AE30:AE38) -> 18419 | AF39: =AF40-SUM(AF30:AF38) -> 9453 | AG39: =AG40-SUM(AG30:AG38) -> 9263
N40: Balance Sheet | Q40: Balance | R40: Activos totales | Z40: 74704 | AA40: 78342 | AB40: 84681 | AC40: 84896 | AD40: 89356 | AE40: 81446 | AF40: 64020 | AG40: 60038
A41: LIABILITIES | N41: Balance Sheet
A42: Current Liabilities | B42: 17676 | C42: 18140 | D42: 17569 | E42: 17016 | F42: 15413 | G42: 14087 | H42: 12708 | I42: 11730 | J42: 10696 | K42: 8639 | L42: 7131 | M42: 8390 | N42: Balance Sheet | O42: Current Liabilities
A43: Payables | B43: 6340 | C43: 7515 | D43: 7523 | E43: 6455 | F43: 5555 | G43: 5188 | H43: 3872 | I43: 3042 | J43: 2587 | K43: 2754 | L43: 2478 | M43: 2278
A44: Short-Term Debt | B44: 3348 | C44: 2241 | D44: 2131 | E44: 2623 | F44: 3420 | G44: 2805 | H44: 4011 | I44: 3681 | J44: 3018 | K44: 923 | L44: 48 | M44: 1781 | N44: Balance Sheet | O44: Short term Debt | Q44: Balance | R44: Pasivos totales corrientes | Z44: 26132 | AA44: 26242 | AB44: 27877 | AC44: 27297 | AD44: 29415 | AE44: =93+3895+8161+3386+2410+2691+298+1967+558+5102 -> 28561 | AF44: =204+3852+5856+2880+1670+1831+281+1521+495+3430 -> 22020 | AG44: =433+3650+2993+3351+797+1217+262+888+302+5399 -> 19292
A45: Short-Term Leases | B45: 709 | C45: 621 | D45: 580 | E45: 560 | F45: 538 | G45: 0 | H45: 0 | I45: 0 | J45: 0 | K45: 0 | L45: 0 | M45: 0
A46: Other current liabilities | B46: =B42-SUM(B43:B45) -> 7279 | C46: =C42-SUM(C43:C45) -> 7763 | D46: =D42-SUM(D43:D45) -> 7335 | E46: =E42-SUM(E43:E45) -> 7378 | F46: =F42-SUM(F43:F45) -> 5900 | G46: =G42-SUM(G43:G45) -> 6094 | H46: =H42-SUM(H43:H45) -> 4825 | I46: =I42-SUM(I43:I45) -> 5007 | ... M46: =M42-SUM(M43:M45) -> 4331 | N46: Balance Sheet | R46: + Préstamos CP | Z46: 7303 | AA46: 6967 | AB46: 4708 | AC46: 3679 | AD46: 5287 | AE46: 5660 | AF46: 3925 | AG46: 5701
A47: Non-current Liabilities | B47: =B51-B42 -> 35867 | C47: =C51-C42 -> 33181 | D47: =D51-D42 -> 37567 | E47: =E51-E42 -> 44723 | F47: =F51-F42 -> 39161 | G47: =G51-G42 -> 32892 | H47: =H51-H42 -> 31665 | I47: =I51-I42 -> 28218 | ... M47: =M51-M42 -> 25740 | N47: Balance Sheet | O47: Total non current liabilities
A48: Long-Term Debt | B48: 18916 | C48: 17321 | D48: 19784 | E48: 22031 | F48: 21818 | G48: 19931 | H48: 20278 | I48: 12394 | J48: 11316 | K48: 9864 | L48: 10824 | M48: 11089 | N48: Balance Sheet | O48: Long term debt | Z48: =Z44-Z46 -> 18829 | AA48: =AA44-AA46 -> 19275 | AB48: =AB44-AB46 -> 23169 | AC48: =AC44-AC46 -> 23618 | AD48: =AD44-AD46 -> 24128 | AE48: =AE44-AE46 -> 22901 | AF48: =AF44-AF46 -> 18095 | AG48: =AG44-AG46 -> 13591
A49: Long-Term Leases | B49: 3756 | C49: 3238 | D49: 3033 | E49: 2540 | F49: 2391 | G49: 0 | H49: 0 | I49: 0 | J49: 0 | K49: 0 | L49: 0 | M49: 0 | Q49: Balance | R49: Pasivos totales no corrientes | Z49: =61491-Z44 -> 35359 | AA49: =63457-AA44 -> 37215 | AB49: =67855-AB44 -> 39978 | AC49: 36721 | AD49: 41973 | AE49: =8415+16529+10956+3583 -> 39483 | AF49: =4505+15932+7584+2654 -> 30675 | AG49: =5652+16195+7420+2179 -> 31446
A50: Other non-current liabilities | B50: =B47-SUM(B48:B49) -> 13195 | C50: =C47-SUM(C48:C49) -> 12622 | D50: =D47-SUM(D48:D49) -> 14750 | E50: =E47-SUM(E48:E49) -> 20152 | F50: =F47-SUM(F48:F49) -> 14952 | G50: =G47-SUM(G48:G49) -> 12961 | H50: =H47-SUM(H48:H49) -> 11387 | I50: =I47-SUM(I48:I49) -> 15824 | ... M50: =M47-SUM(M48:M49) -> 14651 | N50: Balance Sheet | O50: Other non current Liabilities | R50: + Préstamos a largo plazo | Z50: 22818 | AA50: 25169 | AB50: 27784 | AC50: 26719 | AD50: 27752 | AE50: 24944 | AF50: 20437 | AG50: 21847
A51: Total Liabilities | B51: 53543 | C51: 51321 | D51: 55136 | E51: 61739 | F51: 54574 | G51: 46979 | H51: 44373 | I51: 39948 | J51: 35820 | K51: 33133 | L51: 29724 | M51: 34130 | N51: Balance Sheet | O51: Total Liabilities
N52: Balance Sheet | Z52: =Z49-Z50 -> 12541 | AA52: =AA49-AA50 -> 12046 | AB52: =AB49-AB50 -> 12194 | AC52: =AC49-AC50 -> 10002 | AD52: =AD49-AD50 -> 14221 | AE52: =AE49-AE50 -> 14539 | AF52: =AF49-AF50 -> 10238 | AG52: =AG49-AG50 -> 9599
N53: Balance Sheet | Z53: =+Z49+Z44 -> 61491 | AA53: =+AA49+AA44 -> 63457 | AB53: =+AB49+AB44 -> 67855 | AC53: =AC44+AC49 -> 64018 | AD53: =AD49+AD44 -> 71388 | AE53: =AE49+AE44 -> 68044 | AF53: =AF49+AF44 -> 52695 | AG53: =AG49+AG44 -> 50738
A54: Minority Interest | B54: 7.25 | C54: 15.88 | D54: 14.07 | E54: 9.83 | F54: 14.27 | G54: 13.95 | H54: 25.01 | I54: 22.83 | J54: 19.34 | K54: 14.05 | L54: 10.19 | M54: 60.63 | N54: Balance Sheet
N55: Balance Sheet
A56: Shareholder's Equity | B56: =B38-B51-B54 -> 17306.75 | C56: =C38-C51-C54 -> 19787.12 | D56: =D38-D51-D54 -> 14254.93 | E56: =E38-E51-E54 -> 659.17 | F56: =F38-F51-F54 -> 3268.73 | G56: =G38-G51-G54 -> 3023.05 | H56: =H38-H51-H54 -> 1004.99 | I56: =I38-I51-I54 -> 406.17 | ... M56: =M38-M51-M54 -> 4672.37 | N56: Balance Sheet | Q56: Balance | R56: + Participación minoritaria/no dominante
A58: CASH FLOW
A59: Operating CF | B59: 10238 | C59: 14104 | D59: 15007 | E59: 10459 | F59: 8639 | G59: 12711 | H59: 1479 | I59: 6473 | J59: 7430 | K59: 5726 | L59: 7304 | M59: 7216
A60: Net Income | B60: =B12 -> 6708 | C60: =C12 -> 11548 | D60: =D12 -> 12890 | E60: =E12 -> 1343 | F60: =F12 -> 4440 | G60: =G12 -> 4791 | H60: =H12 -> 4910 | I60: =I12 -> 3431 | ... M60: =M12 -> 807
A61: Depreciation & Amortization | B61: 3366 | C61: 3188 | D61: 2953 | E61: 2698 | F61: 2360 | G61: 2207 | H61: 2282 | I61: 2224 | J61: 2084 | K61: 1923 | L61: 1867 | M61: 1858
A62: Changes in assets and liabilities | B62: -514 | C62: -363 | D62: -642 | E62: 1060 | F62: 156 | G62: 2058 | H62: -1413 | I62: -734 | J62: -307 | K62: 322 | L62: -174 | M62: 13
A63: Other Adjustments | B63: =B59-B60-B61-B62 -> 678 | C63: =C59-C60-C61-C62 -> -269 | D63: =D59-D60-D61-D62 -> -194 | E63: =E59-E60-E61-E62 -> 5358 | F63: =F59-F60-F61-F62 -> 1683 | G63: =G59-G60-G61-G62 -> 3655 | H63: =H59-H60-H61-H62 -> -4300 | I63: =I59-I60-I61-I62 -> 1552 | ... M63: =M59-M60-M61-M62 -> 4538
A64: Investing CF | B64: -7133 | C64: -7472 | D64: -3818 | E64: -5283 | F64: -6061 | G64: -6330 | H64: -4975 | I64: -2566 | J64: -5309 | K64: -2801 | L64: -2114 | M64: -1335
A65: Net Capex | B65: -5158 | C65: -4769 | D65: -4194 | E65: -5412 | F65: -6380 | G65: -6238 | H65: -5227 | I65: -2965 | J65: -2379 | K65: -2328 | L65: -2065 | M65: -2153
A66: Investments & Acquisitions | B66: -1329 | C66: -755 | D66: -602 | E66: -20 | F66: -6 | G66: -2 | H66: -134 | I66: -547 | J66: -30 | K66: -63 | L66: -179 | M66: -100
A67: Other Inflows (Outflows) | B67: =B64-B65-B66 -> -646 | C67: =C64-C65-C66 -> -1948 | D67: =D64-D65-D66 -> 978 | E67: =E64-E65-E66 -> 149 | F67: =F64-F65-F66 -> 325 | G67: =G64-G65-G66 -> -90 | H67: =H64-H65-H66 -> 386 | I67: =I64-I65-I66 -> 946 | ... M67: =M64-M65-M66 -> 918
A68: Financing CF | B68: -5534 | C68: -11185 | D68: -6823 | E68: -4517 | F68: -1727 | G68: -5692 | H68: 3287 | I68: -3140 | J68: -1565 | K68: -5161 | L68: -7807 | M68: -1817
A69: Debt Borrowing | B69: 3429 | C69: 0 | D69: 0 | E69: 5003 | F69: 5205 | G69: 1202 | H69: 12016 | I69: 5927 | J69: 3783 | K69: 1525 | L69: 100 | M69: 1745
A70: Debt Repayment | B70: -2429 | C70: -2304 | D70: -2773 | E70: -3392 | F70: -3096 | G70: -2887 | H70: -3939 | I70: -3805 | J70: -2724 | K70: -1694 | L70: -1875 | M70: -16
A71: Lease Increases | B71: 0 | C71: 0 | D71: 0 | E71: 0 | F71: 0 | G71: 0 | H71: 0 | I71: 0 | J71: 0 | K71: 0 | L71: 0 | M71: 0
A72: Lease Payments | B72: 0 | C72: 0 | D72: 0 | E72: 0 | F72: 0 | G72: 0 | H72: 0 | I72: 0 | J72: 0 | K72: 0 | L72: 0 | M72: 0
A73: Dividends | B73: -5372 | C73: -5114 | D73: -3437 | E73: -3374 | F73: -3194 | G73: -3011 | H73: -2771 | I73: -2643 | J73: -2525 | K73: -2366 | L73: -2260 | M73: -2130 | N73: cash flows FINANCING | O73: Dividends paid
A74: Share buyback | B74: -2250 | C74: -3500 | D74: -500 | E74: -224 | F74: -1004 | G74: -1011 | H74: -1813 | I74: -2678 | J74: -2702 | K74: -2695 | L74: -3838 | M74: -1621 | N74: cash flows FINANCING | O74: =+A74 -> Share buyback
A75: Other Inflows (Outflows) | B75: =B68-B69-B70-B71-B72-B73-B74 -> 1088 | C75: =C68-C69-C70-C71-C72-C73-C74 -> -267 | D75: =D68-D69-D70-D71-D72-D73-D74 -> -113 | E75: =E68-E69-E70-E71-E72-E73-E74 -> -2530 | F75: =F68-F69-F70-F71-F72-F73-F74 -> 362 | G75: =G68-G69-G70-G71-G72-G73-G74 -> 15 | H75: =H68-H69-H70-H71-H72-H73-H74 -> -206 | I75: =I68-I69-I70-I71-I72-I73-I74 -> 59 | ... M75: =M68-M69-M70-M71-M72-M73-M74 -> 205
A76: FX
A77: Changes in cash | B77: =B59+B64+B68+B76 -> -2429 | C77: =C59+C64+C68+C76 -> -4553 | D77: =D59+D64+D68+D76 -> 4366 | E77: =E59+E64+E68+E76 -> 659 | F77: =F59+F64+F68+F76 -> 851 | G77: =G59+G64+G68+G76 -> 689 | H77: =H59+H64+H68+H76 -> -209 | I77: =I59+I64+I68+I76 -> 767 | ... M77: =M59+M64+M68+M76 -> 4064
O78: (Vitalis will later fill this info)
A79: Other Data | E79: Corporate Bonds 3, 5 Y 10 | H79: Average Price | J79: Moody's | K79: YTM | L79: DIVISA
A80: Number of employees | B80: 500000 | C80: 10-K | N80: bloomberg
A81: Shares Outstanding (Thousands) | B81: 732510 | C81: Yahoo finance | N81: bloomberg
A82: Float | B82: 0.99896 | C82: Yahoo finance | N82: bloomberg
A83: Insiders Own | B83: 0.0001 | C83: Yahoo finance | N83: bloomberg
A84: Fitch/ S&P Rating | B84: A | C84: 10-K | N84: bloomberg
A85: Dividend Yield(Yahoo Finance) | B85: 0.0489 | C85: Yahoo finance | N85: bloomberg
A86: Daily Volume in Millions of USD | B86: 4.9 | C86: Yahoo Finance | N86: bloomberg
B87: =B5 -> 2023 | C87: =C5 -> 2022 | D87: =D5 -> 2021
A88: Short % of Float | E88: Yahoo Finance
A89: EPS | E89: Yahoo Finance
