Workbook
Name Benchmark: [1]ControlsH!$B$3
Name BestConsOv: #REF!
Name Broker_Name: OFFSET(#REF!,0,0,[1]ControlsH!$E$5, 1)
Name calCODE: [1]ControlsH!$C$4
Name Chart_Benchmark_100_Size: OFFSET(#REF!, 0, 0, [1]ControlsH!$E$3, 1)
Name Chart_Date_Size: OFFSET(#REF!, 0, 0, [1]ControlsH!$E$3, 1)
Name Chart_Date_VAL1_Size: OFFSET(#REF!, 0, 0, [1]ControlsH!$I$3, 1)
Name Chart_Date_VAL2_Size: OFFSET(#REF!, 0, 0, [1]ControlsH!$I$5, 1)
Name Chart_Peer_100_Size: OFFSET(#REF!, 0, 0, [1]ControlsH!$E$3, 1)
Name Chart_Price_100_Size: OFFSET(#REF!, 0, 0, [1]ControlsH!$E$3, 1)
Name Chart_Price_Size: OFFSET(#REF!, 0, 0, [1]ControlsH!$E$3, 1)
Name Chart_VAL1_FY1_Size: OFFSET(#REF!, 0, 0, [1]ControlsH!$F$3, 1)
Name Chart_VAL1_FY2_Size: OFFSET(#REF!, 0, 0, [1]ControlsH!$G$3, 1)
Name Chart_VAL1_FY3_Size: OFFSET(#REF!, 0, 0, [1]ControlsH!$H$3, 1)
Name Chart_VAL2_FY1_Size: OFFSET(#REF!, 0, 0, [1]ControlsH!$F$5, 1)
Name Chart_VAL2_FY2_Size: OFFSET(#REF!, 0, 0, [1]ControlsH!$G$5, 1)
Name Chart_VAL2_FY3_Size: OFFSET(#REF!, 0, 0, [1]ControlsH!$H$5, 1)
Name Chart_Volume_Size: OFFSET(#REF!, 0, 0, [1]ControlsH!$E$3, 1)
Name compNAME: [1]ControlsH!$B$6
Name CURRENCY: [1]ControlsH!$B$9
Name currPRICE: [1]Overview!$E$19
Name custBenchmark: [1]Overview!$C$9
Name custED: #REF!
Name custSD: #REF!
Name dayCODE: [1]ControlsH!$C$5
Name ED: [1]ControlsH!$B$5
Name ESTBrokersItem: #REF!
Name ESTBrokersPeriod: #REF!
Name ESTDetailBroker: #REF!
Name ESTDetailBroker2: #REF!
Name ESTDetailPeriod: #REF!
Name EstDetPerO: #REF!
Name EstDetPerT: #REF!
Name FinancialsPeriod: #REF!
Name fundTICKER: [1]ControlsH!$B$15
Name GraphValRatio1: #REF!
Name GraphValRatio2: #REF!
Name Index1: #REF!
Name Lang: [1]Overview!$D$11
Name newCrncy: [1]ControlsH!$B$21:$B$199
Name newEstBrokerPeriod: #REF!
Name newEstBrokersItem: #REF!
Name newEstDetailBroker: #REF!
Name newEstDetailBroker2: #REF!
Name newEstDetailPeriod: #REF!
Name newFinancialsPeriod: #REF!
Name newOverviewCon: #REF!
Name newOverviewYear: #REF!
Name newOwners: #REF!
Name newPeersRatio: #REF!
Name newPeriod: #REF!
Name newValRatio1: #REF!
Name newValRatio2: #REF!
Name OverviewValRatioPeriod: [1]Overview!$D$30
Name PeerDate1: [1]Peers!$S$11
Name peerHist1: #REF!
Name PeerIndex: [1]ControlsH!$F$35:$F$36
Name Peers: OFFSET([1]Peers!$C$18,0,0,MAX(COUNTA([1]Peers!$C$18:$C$47),1),1)
Name peersWEIGHT: [1]ControlsH!$B$13
Name PERIODICITY: [1]ControlsH!$C$3

Sheet COVID-19 impact
A1: https://www.apple.com/newsroom/2020/03/apples-covid-19-response/ | G1: https://glg.it/articles/how-might-the-wuhan-coronavirus-impact-apples-supply-chain/ | N1: https://www.cnbc.com/2020/02/18/the-significance-of-apples-coronavirus-warning.html
A2: March 13 | G2: January 29 | N2: Ferbuary 18
A23: Otros:
A24: https://www.macrumors.com/guide/covid-19-coronavirus/

Sheet OP
B2: (date of last modification) | C2: Analista: Research | D2: Report (quarter): 2024/11/07 | E2: #VALUE! | K2: NYSE | L2: SIC: Sí
B3: #VALUE! | D3: DESCRIPTION: YETI Holdings, Inc. is an American company specializing in premium outdoor lifestyle products, including high-performance coolers, drinkware, bags, and accessories. Founded in 2006, YETI is known for its durable, high-quality designs catering to outdoor enthusiasts, travelers, and professionals.
D4: CEO&BOARD: Robert K. Shearer (Ch; 69yo; dir. s. 2018; ex CFO of VF Corporation, Director at Church & Dwight Co., Inc.) ; Matthew J. Reintjes (President & CEO; 48yo; dir. s. 2016; ex Executive at Vista Outdoor Inc., President of Bushnell Outdoor Products); Alison Dean (60yo; dir.s. 2020; ex EVP, CFO & Treasurer at iRobot Corporation, Director at Everbridge, Inc.) ; Alison Dean (60yo; dir.s. 2020; ex EVP, CFO & Treasurer at iRobot Corporation, Director at Everbridge, Inc.); Dustan E. McCoy (75yo; dir.s. 2018; ex Chairman & CEO of Brunswick Corporation, Director at Freeport-McMoRan Inc.) ; Mary Lou Kelley (57yo; board member since 2019; ex President of eCommerce at Best Buy Co., Inc., Director at Vera Bradley, Inc.); Frank D. Gibeau (56yo; dir.s. 2020; CEO of Zynga Inc., ex EVP at Electronic Arts Inc.) ; Elizabeth Axelrod ( 61yo; dir.s. 2023; ex Global Head of Employee Experience at Airbnb, SVP of Human Resources at eBay.) ; Robert Katz (57yo; board member since 2023; Executive Chairperson of Vail Resorts, Inc., ex CEO of Vail Resorts).
B5: Millones de USD
B6: Acción | D6: Liquidez y Solvencia | F6: =[3]Segments!B2 -> Regions in Thousands (2023) | I6: Rentabilidad (2023) | K6: Múltiplos
B7: Último Precio | C7: {=_FV(E2,"price")} -> 37.12 | D7: Activo: | E7: =Cifras_Originales!B27 -> 1297.192 | H7: %Vts; %Op.Mg.; D | I7: Año termina: | J7: 45291 | K7: Float: | L7: =83.44/84.83 -> 0.98361429
B8: Outstanding Shares | C8: {=_FV(E2,"Shares outstanding",TRUE)} -> 84825450 | D8: Pasivo: | E8: =Cifras_Originales!B39 -> 573.582 | F8: =[2]Segments!B4 -> United States | H8: =+Segments!J4 -> 84%; -; 0% | K8: Insiders Own: | L8: 0.0052
B9: Market Cap. | C9: =C7*C8/1000000 -> 3148.7207 | D9: Cash/Precio | E9: =1000000*C11/C8 -> 5.174862 | F9: =[2]Segments!B5 -> Internacional | H9: =+Segments!J5 -> 16%; -; 29% | I9: EBIT | J9: =Cifras_Originales!B19+Cifras_Originales!B15+Cifras_Originales!B9 -> 224.028 | K9: b (Bloomberg; Yahoo) | L9: 2.14 | R9: 2023 | S9: 2022 | T9: 2021
B10: +Deuda Total | C10: =Cifras_en_Millones!C60 -> 176.113 | D10: Ebidta/CIF | E10: =(Cifras_Originales!B19-Cifras_Originales!B11-Cifras_Originales!B9-Cifras_Originales!B15)/Cifras_Originales!B9 -> -172.16136 | F10: =[2]Segments!B6 -> 0 | H10: =+[2]Segments!J6 | I10: +Dep&Amort | J10: =Cifras_Originales!B11 -> -46.434 | K10: Calificación (S&P) | L10: 0.33 | Q10: Operating margin | R10: =[3]Cifras_Originales!B8/[3]Cifras_Originales!B6 -> 0.13592345 | S10: =[3]Cifras_Originales!C8/[3]Cifras_Originales!C6 -> 0.079212172 | T10: =[3]Cifras_Originales!D8/[3]Cifras_Originales!D6 -> 0.19485481
B11: -Cash | C11: =Cifras_en_Millones!C40 -> 438.96 | D11: Deuda/Ebidta | E11: =(Cifras_Originales!B32+Cifras_Originales!B36)/(Cifras_Originales!B19-Cifras_Originales!B15-Cifras_Originales!B9-Cifras_Originales!B11) -> 0.52550316 | F11: =[2]Segments!B7 -> 0 | H11: =+[2]Segments!J7 | I11: =EBIDTA | J11: =J9+J10 -> 177.594 | K11: Precio/Valor en libros | L11: =((C7*C8)/1000000)/(E7-E8) -> 4.3514057 | Q11: Net income margin | R11: =[3]Cifras_Originales!B19/[3]Cifras_Originales!B6 -> 0.10241977 | S11: =[3]Cifras_Originales!C19/[3]Cifras_Originales!C6 -> 0.05622603 | T11: =[3]Cifras_Originales!D19/[3]Cifras_Originales!D6 -> 0.15067587
B12: =Enterprise Value | C12: =C9+C10-C11 -> 2885.8737 | D12: "Otros activos"/Activo | E12: =Cifras_Originales!B26/Cifras_Originales!B27 -> 0.2270566 | F12: =[2]Segments!B8 -> 0 | H12: =+[2]Segments!J8 | I12: Utilidad Neta | J12: =Cifras_Originales!B19 -> 169.885 | K12: FNP(p)/Activos | L12: =J18/E7 -> 0.047712546 | Q12: EBITDA | R12: =[3]Cifras_Originales!B19+[3]Cifras_Originales!B15+[3]Cifras_Originales!B11+[3]Cifras_Originales!B9 -> 177594 | S12: =[3]Cifras_Originales!C19+[3]Cifras_Originales!C15+[3]Cifras_Originales!C11+[3]Cifras_Originales!C9 -> 80796 | T12: =[3]Cifras_Originales!D19+[3]Cifras_Originales!D15+[3]Cifras_Originales!D11+[3]Cifras_Originales!D9 -> 239679
B13: Tenencia % (nac/int'l) | C13: - | D13: Deuda/Activo | E13: =C10/E7 -> 0.13576479 | F13: =[3]Segments!B15 -> Products in Thousands (2023) | I13: UPA | J13: =1000000*J12/C8 -> 2.0027598 | K13: Precio/Utilidad(p) | L13: =C9/J17 -> 20.005426 | N13: =C10/J11 -> 0.99166075 | Q13: EBITDA/net income | R13: =R12/[3]Cifras_Originales!B19 -> 1.0453778 | S13: =S12/[3]Cifras_Originales!C19 -> 0.90080608 | T13: =T12/[3]Cifras_Originales!D19 -> 1.12736
B14: t liq. (Pos prom./Vol.) | C14: - | D14: Margen de Operación (p) | E14: =AVERAGE(R10:T10) -> 0.13666348 | H14: %Vts; D | I14: ROA | J14: =J12/E7 -> 0.13096365 | K14: EV/Activos | L14: =C12/E7 -> 2.2247082 | Q14: NFC | R14: =[3]Cifras_Originales!B9 -> -942 | S14: =[3]Cifras_Originales!C9 -> -4466 | T14: =[3]Cifras_Originales!D9 -> -3339
B15: % Short | C15: =9.87/83.84 -> 0.11772424 | D15: Margen neto (p) | E15: =AVERAGE(R11:T11) -> 0.10310722 | F15: =[3]Segments!B17 -> Coolers & Equipment | H15: =+Segments!J17 -> 36%; -; -2% | I15: ROIC | J15: =J12/(E7-(E8-C10)) -> 0.18881923 | K15: EV/Ebidta (p) | L15: =C12/J16 -> 17.382373 | Q15: Net debt | R15: =[3]Cifras_en_Millones!B59 -> 132217 | S15: =[3]Cifras_en_Millones!C59 -> -70664 | T15: =[3]Cifras_en_Millones!D59 -> -125781
B16: Semáforo ESG | D16: Ebidta/Ingresos(p) | E16: =AVERAGE(R13:T13) -> 1.0245146 | F16: =[3]Segments!B18 -> Drinkware | H16: =+Segments!J18 -> 62%; -; 8% | I16: Ebidta(p) | J16: =AVERAGE(Cifras_en_Millones!C19:E19) -> 166.023 | K16: Precio/FNP (p) | L16: =C9/J18 -> 50.874164
B17: E | D17: CIF/Deuda Neta Promedio | E17: =AVERAGE(R15:T15) -> -21409.333 | F17: =[3]Segments!B19 -> Others | H17: =++Segments!J19 -> 2%; -; 8% | I17: Utilidad Neta (p) | J17: =AVERAGE(Cifras_en_Millones!C23:E23) -> 157.39333 | K17: Bonos 1;5;40a (USD) | L17: N/A | N17: 12
B18: S | F18: =[2]Segments!B20 -> 0 | H18: =+[2]Segments!J20 | I18: FNP (p) | J18: =SUM(F35:F37)/3 -> 61.892333 | K18: TDY(p)/Precio | L18: =SUM(E35:E37)/(3*C9) -> 0
B19: G | F19: =[2]Segments!B21 -> 0 | H19: =+[2]Segments!J21 | I19: Tax (p) últ. 5a | J19: 0.16 | K19: Div. Yield: | L19: =K33/C9 -> 0
B20: Tesis de inversión | H20: Acuerdo | I20: Supuestos de valuación | L20: DCF Value
B21: YETI Holdings is a premium brand with strong customer loyalty, expanding beyond coolers into outdoor gear. Its omnichannel strategy and global expansion drive growth, backed by solid financials. Key risks include competition, economic downturns, and supply chain challenges. Overall, YETI's premium positioning and market expansion make it a compelling long-term investment. | H21: Mantener sin elevar posición | I21: VER DCF | L21: =DCFF!D67 -> 330.44079
B23: KSF | H23: PO / Precio Stand By | L23: =DCFF!D66 -> 7.9019609
H24: =[2]DCFF!D71 -> 0 | I24: Tasa de descuento: | J24: =DCFF!D48 -> 0.085
B25: Año | C25: Ingresos | D25: Margen Operativo | E25: Div.+Recompra | F25: FNP | G25: Deuda/Activo | H25: Depreciación | I25: Capex + Adq | J25: Cash Flow
B26: 2012 | C26: N/A | D26: N/A | E26: N/A | F26: N/A | G26: N/A | H26: N/A | I26: N/A | K26: 2023 | L26: =K26-1 -> 2022
B27: =B26+1 -> 2013 | C27: =Cifras_Originales!L6 -> 89.9 | D27: =Cifras_Originales!L$8/OP!C27 -> 0.16907675 | E27: N/A | F27: N/A | G27: N/A | H27: N/A | I27: N/A | J27: Profit | K27: =Cifras_Originales!B19 -> 169.885 | L27: =Cifras_Originales!C19 -> 89.693 | N27: =C27/C26-1 -> #VALUE! | O27: =D27/D26-1 -> #VALUE!
B28: =B27+1 -> 2014 | C28: =Cifras_Originales!K6 -> 147.7 | D28: =Cifras_Originales!K$8/OP!C28 -> 0.17400135 | E28: N/A | F28: N/A | G28: N/A | H28: N/A | I28: N/A | J28: Cash Flow from Operations (BWC) | K28: 285.942 | L28: 100.894 | N28: =C28/C27-1 -> 0.6429366 | O28: =D28/D27-1 -> 0.02912643 | P28: =E28/E27-1 -> #VALUE! | Q28: =F28/#REF!-1 -> #VALUE! | R28: =H28/H27-1 -> #VALUE! | S28: =I28/I27-1 -> #VALUE! | BT28: 4303
B29: =B28+1 -> 2015 | C29: =Cifras_Originales!J6 -> 468.946 | D29: =Cifras_Originales!J$8/OP!C29 -> 0.27273929 | E29: N/A | F29: N/A | G29: N/A | H29: N/A | I29: N/A | J29: Working Capital | K29: =Cifras_Originales!B12 -> 31.698 | L29: =Cifras_Originales!C12 -> -28.037 | N29: =C29/C28-1 -> 2.1749898 | O29: =D29/D28-1 -> 0.567455 | P29: =E29/E28-1 -> #VALUE! | Q29: =F29/F28-1 -> #VALUE! | R29: =H29/H28-1 -> #VALUE! | S29: =I29/I28-1 -> #VALUE! | BT29: 3066
B30: =B29+1 -> 2016 | C30: =Cifras_Originales!I6 -> 818.914 | D30: =Cifras_Originales!I$8/OP!C30 -> 0.10771217 | E30: =[2]Cifras_Originales!I17+[2]Cifras_Originales!I18 -> 0 | F30: N/A | G30: N/A | H30: 6.3 | I30: =Cifras_Originales!I13+Cifras_Originales!I14 -> -35.588 | J30: Investing Activities | K30: =K31+K32 -> -72.824 | L30: =L31+L32 -> -56.91 | N30: =C30/C29-1 -> 0.74628635 | O30: =D30/D29-1 -> -0.6050728 | P30: =E30/E29-1 -> #VALUE! | Q30: =F30/F29-1 -> #VALUE! | R30: =H30/H29-1 -> #VALUE! | S30: =I30/I29-1 -> #VALUE! | BT30: 3283
B31: =B30+1 -> 2017 | C31: =Cifras_Originales!H6 -> 639.239 | D31: =Cifras_Originales!H$8/OP!C31 -> 0.10006742 | E31: =[2]Cifras_Originales!H17+[2]Cifras_Originales!H18 -> 0 | F31: =Cifras_Originales!H22-Cifras_Originales!I22+Cifras_Originales!H18+Cifras_Originales!H17 -> 32.359 | G31: =Cifras_en_Millones!I60/Cifras_en_Millones!I45 -> 0.92110211 | H31: 15.4 | I31: =Cifras_Originales!H13+Cifras_Originales!H14 -> -42.197 | J31: Capex | K31: -50.672 | L31: -45.929 | N31: =C31/C30-1 -> -0.21940643 | O31: =D31/D30-1 -> -0.070973796 | P31: =E31/E30-1 -> #DIV/0! | Q31: =F31/F30-1 -> #VALUE! | R31: =H31/H30-1 -> 1.4444444 | S31: =I31/I30-1 -> 0.18570867
B32: =B31+1 -> 2018 | C32: =Cifras_Originales!G6 -> 778.833 | D32: =Cifras_Originales!G$8/OP!C32 -> 0.13116547 | E32: =[2]Cifras_Originales!G17+[2]Cifras_Originales!G18 -> 0 | F32: =Cifras_Originales!G22-Cifras_Originales!H22+Cifras_Originales!G17+Cifras_Originales!G18 -> 26.401 | G32: =Cifras_en_Millones!H60/Cifras_en_Millones!H45 -> 0.63789519 | H32: 19.5 | I32: =Cifras_Originales!G13+Cifras_Originales!G14 -> -20.86 | J32: Adquisiones | K32: =-22.152 -> -22.152 | L32: -10.981 | N32: =C32/C31-1 -> 0.21837529 | O32: =D32/D31-1 -> 0.31077097 | P32: =E32/E31-1 -> #DIV/0! | Q32: =F32/F31-1 -> -0.18412188 | R32: =H32/H31-1 -> 0.26623377 | S32: =I32/I31-1 -> -0.50565206
B33: =B32+1 -> 2019 | C33: =Cifras_Originales!F6 -> 913.734 | D33: =Cifras_Originales!F$8/OP!C33 -> 0.098246317 | E33: =[2]Cifras_Originales!F17 -> 0 | F33: =Cifras_Originales!F22-Cifras_Originales!G22+Cifras_Originales!F18+Cifras_Originales!F17 -> -7.536 | G33: =Cifras_en_Millones!G60/Cifras_en_Millones!G45 -> 0.55098731 | H33: 23.2 | I33: =Cifras_Originales!F13+Cifras_Originales!F14 -> -32.077 | J33: Dividends | K33: 0 | L33: 0 | N33: =C33/C32-1 -> 0.17320915 | O33: =D33/D32-1 -> -0.25097426 | P33: =E33/E32-1 -> #DIV/0! | Q33: =F33/F32-1 -> -1.2854437 | R33: =H33/H32-1 -> 0.18974359 | S33: =I33/I32-1 -> 0.53772771
B34: =B33+1 -> 2020 | C34: =Cifras_Originales!E6 -> 1091.721 | D34: =Cifras_Originales!E$8/OP!C34 -> 0.1962342 | E34: 0 | F34: =Cifras_Originales!E22-Cifras_Originales!F22+Cifras_Originales!E18+Cifras_Originales!E17 -> 180.768 | G34: =Cifras_en_Millones!F60/Cifras_en_Millones!F45 -> 0.24218558 | H34: 24.6 | I34: =Cifras_Originales!E13+Cifras_Originales!E14 -> -15.566 | J34: Stock Repurchases | K34: =Cifras_Originales!B18 -> 0 | L34: =[2]Cifras_Originales!C18 -> 0 | N34: =C34/C33-1 -> 0.19479083 | O34: =D34/D33-1 -> 0.99736956 | P34: =E34/E33-1 -> #DIV/0! | Q34: =F34/F33-1 -> -24.987261 | R34: =H34/H33-1 -> 0.060344828 | S34: =I34/I33-1 -> -0.51473018
B35: =B34+1 -> 2021 | C35: =Cifras_Originales!D6 -> 1410.989 | D35: =Cifras_Originales!D$8/OP!C35 -> 0.19485481 | E35: 0 | F35: =Cifras_Originales!D22-Cifras_Originales!E22+Cifras_Originales!D17+Cifras_Originales!D18 -> 58.906 | G35: =Cifras_en_Millones!E60/Cifras_en_Millones!E45 -> 0.17002382 | H35: 25.7 | I35: =Cifras_Originales!D13+Cifras_Originales!D14 -> -56.121 | J35: Endeudamiento Neto | K35: =Cifras_en_Millones!C59 -> -262.847 | L35: =Cifras_en_Millones!D59 -> -70.664 | N35: =C35/C34-1 -> 0.29244468 | O35: =D35/D34-1 -> -0.007029295 | P35: =E35/E34-1 -> #DIV/0! | Q35: =F35/F34-1 -> -0.6741348 | R35: =H35/H34-1 -> 0.044715447 | S35: =I35/I34-1 -> 2.6053578
B36: =B35+1 -> 2022 | C36: =Cifras_Originales!C6 -> 1595.222 | D36: =Cifras_Originales!C$8/OP!C36 -> 0.079212172 | E36: 0 | F36: =Cifras_Originales!C22-Cifras_Originales!D22+Cifras_Originales!D17+Cifras_Originales!D18 -> -77.448 | G36: =Cifras_en_Millones!D60/Cifras_en_Millones!D45 -> 0.15237958 | H36: 32.8 | I36: =Cifras_Originales!C13+Cifras_Originales!C14 -> -45.929 | J36: Otros Financiemientos | N36: =C36/C35-1 -> 0.13057012 | O36: =D36/D35-1 -> -0.59348106
B37: =B36+1 -> 2023 | C37: =Cifras_Originales!B6 -> 1658.713 | D37: =Cifras_Originales!B$8/OP!C37 -> 0.13592345 | E37: 0 | F37: =Cifras_Originales!B22-Cifras_Originales!C22+Cifras_Originales!B17+Cifras_Originales!B18 -> 204.219 | G37: =Cifras_en_Millones!C60/Cifras_en_Millones!C45 -> 0.13576479 | H37: 41.2 | I37: =Cifras_Originales!B13+Cifras_Originales!B14 -> -50.672 | N37: =C37/C36-1 -> 0.03980073 | O37: =D37/D36-1 -> 0.7159415
B38: 2024 Est. | C38: =DCFF!H7 -> 1829.873 | D38: =DCFF!H8 -> 0.16
B39: CAGR | C39: =(C37/C32)^(1/5)-1 -> 0.16322943 | D39: =(D37/D30)^(1/7)-1 -> 0.033791142 | J39: FX
B40: AAG | C40: =AVERAGE(N30:N37) -> 0.19700884 | D40: =AVERAGE(O31:O37) -> 0.1573748 | J40: D Cash and Equivalents | K40: =K28+K29+K30+K33+K34+K35+K36+K39 -> -18.031 | L40: =L28+L29+L30+L33+L34+L35+L36+L39 -> -54.717
B41: CVAR | C41: =STDEV(C26:C37)/AVERAGE(C26:C37) -> 0.61048712 | D41: =STDEV(D26:D37)/AVERAGE(D26:D37) -> 0.37893357 | J41: Inv/D Vts | K41: =SUM(I33:I37)/(C37-C32) -> -0.22771855 | L41: =(SUM(I33:I37)-SUM(H33:H37))/(C37-C32) -> -0.39535505
B42: Último Año | C42: =C37/C36-1 -> 0.03980073 | D42: =D37/D36-1 -> 0.7159415 | J42: t inversiones; t adq. neto dep. | K42: =K41/E14 -> -1.6662722 | L42: =L41/E14 -> -2.8929093
B43: Pros | I43: (historical stock price of the company and its peers; source: Bloomberg)
B44: Omnichannel Presence - The company effectively utilizes Direct-to-Consumer sales, retail partnerships, and e-commerce to reach a broad audience. Strong Brand Recognition - YETI is a premium brand known for high-quality outdoor products, particularly in coolers and drinkware goods. Diverse growth strategies - Yeti has been growing not only organically with increasing margins, but also through strategic M&As such as acquisition of Mystery ranch (designs and manufactures durable loadbearing backpacks, bags, and pack accessories)
B45: Cons
B46: Dependence on U.S. Market - 84% of YETI's net income in 2023 comes from the U.S., making it vulnerable to domestic economic flunctuations. Limited Product Diversification - YETI t is heavily reliant on coolers and drinkware although it has expanded its products in these.
B47: Riesgos
B48: Supply chain risks - Many of YETI's core products are manufactured in China, the Philippines, Vietnam, Taiwan, Poland, Mexico, Thailand, and Malaysia. Dependence on overseas manufacturing exposes the company to potential disruptions and rising costs.
B49: Oportunidades
B50: Sustainability Initiatives – Demand for eco-friendly products is rising, and YETI can leverage its reputation with its sustainable product lines.
B51: CHECKLIST
B52: Crecimiento | C52: Riesgos claros | D52: ESG | E52: Peer Analysis | F52: Consenso | G52: KSF | H52: PO/Stand By | I52: Stanley Black & Decker Inc, Newell Brands Inc
B53: (p) = Promedio de últimos 3 años
B54: NOTES:
B55: International sales grew 30% YoY for FY 2024, ending the year at 18% of adjusted net sales
B56: DTC sales grew +9% YoY for FY 2024 with growth across Ecommerce, Amazon, Corporate Sales, and YETI Retail
B57: Launched 24 new products in 2024, with broadening of legacy categories and expansion into new categories
B58: Although its dependence on U.S. market is a current com of the company, it has been expanding to international channels and its historical international mix has been steadily increasing.

Sheet Segments
B2: Regions in Thousands (2023) | L2: Proyectado | N2: Escenario de estrés | X2: Escenario de estrés
C3: 2023 | D3: =C3-1 -> 2022 | E3: Ut. Operativa | F3: % Vts | G3: Margen | H3: Crec | L3: Crecimiento | M3: 2021 (Real) | N3: 2022 (Real) | O3: 2023 (Real) | P3: 2024 (Est) | Q3: 2025 | R3: 2026 | S3: 2027 | T3: 2028 | V3: Márgenes (regional) | W3: 2021 (Real) | X3: 2022 (Real) | Y3: 2023 (Real) | Z3: 2024 (Est) | AA3: 2025 | AB3: 2026 | AC3: 2027 | AD3: 2028
B4: United States | C4: 1398925 | D4: 1394026 | F4: =$C$4/$C$14 -> 0.84337978 | G4: - | H4: =C4/D4-1 -> 0.0035142817 | J4: =IF(C4="","",IF(F4=0,"NA",TEXT(F4,"0%"))&"; "&IF(G4=0,"NA",TEXT(G4,"0.0%"))&"; "&IF(H4=0,"NA",TEXT(H4,"0%"))) -> 84%; -; 0% | L4: =B17 -> Coolers & Equipment | M4: 551861 | N4: 612525 | O4: 597511 | V4: =B4 -> United States | W4: 1277177 | X4: 1394026 | Y4: 1398925
B5: Internacional | C5: 259788 | D5: 201196 | F5: =$C$5/$C$14 -> 0.15662022 | G5: - | H5: =C5/D5-1 -> 0.29121851 | J5: =IF(C5="","",IF(F5=0,"NA",TEXT(F5,"0%"))&"; "&IF(G5=0,"NA",TEXT(G5,"0.0%"))&"; "&IF(H5=0,"NA",TEXT(H5,"0%"))) -> 16%; -; 29% | L5: =B18 -> Drinkware | M5: 832428 | N5: 947221 | O5: 1022982 | V5: =B5 -> Internacional | W5: 133812 | X5: 201196 | Y5: 259788
J6: =IF(C6="","",IF(F6=0,"NA",TEXT(F6,"0%"))&"; "&IF(G6=0,"NA",TEXT(G6,"0.0%"))&"; "&IF(H6=0,"NA",TEXT(H6,"0%"))) | L6: =B19 -> Others | M6: 26700 | N6: 35476 | O6: 38220 | V6: =B6 -> 0
J7: =IF(C7="","",IF(F7=0,"NA",TEXT(F7,"0%"))&"; "&IF(G7=0,"NA",TEXT(G7,"0.0%"))&"; "&IF(H7=0,"NA",TEXT(H7,"0%"))) | L7: =B20 -> 0 | V7: =B7 -> 0
J8: =IF(C8="","",IF(F8=0,"NA",TEXT(F8,"0%"))&"; "&IF(G8=0,"NA",TEXT(G8,"0.0%"))&"; "&IF(H8=0,"NA",TEXT(H8,"0%"))) | L8: =B21 -> 0 | V8: =B8 -> 0
J9: =IF(C9="","",IF(F9=0,"NA",TEXT(F9,"0%"))&"; "&IF(G9=0,"NA",TEXT(G9,"0.0%"))&"; "&IF(H9=0,"NA",TEXT(H9,"0%"))) | L9: % vts. | V9: Margen Operativp | W9: =(W4*W12+W5*W13+W6*W14+W7*W15+W8*W16)/SUM(W12:W16)+W10 -> 1176876.9 | X9: =(#REF!*#REF!+#REF!*#REF!+X6*X14+X7*X15+X8*X16)/SUM(X12:X16)+X10 -> #REF! | Y9: =(X4*X12+X5*X13+Y6*Y14+Y7*Y15+Y8*Y16)/SUM(Y12:Y16)+Y10 -> 1243581.3 | Z9: =(Y4*Y12+Y5*Y13+Z6*Z14+Z7*Z15+Z8*Z16)/SUM(Z12:Z16)+Z10 -> #DIV/0! | AA9: =(AA4*AA12+AA5*AA13+AA6*AA14+AA7*AA15+AA8*AA16)/SUM(AA12:AA16)+AA10 -> #DIV/0! | AB9: =(AB4*AB12+AB5*AB13+AB6*AB14+AB7*AB15+AB8*AB16)/SUM(AB12:AB16)+AB10 -> #DIV/0! | AC9: =(AC4*AC12+AC5*AC13+AC6*AC14+AC7*AC15+AC8*AC16)/SUM(AC12:AC16)+AC10 -> #DIV/0! | AD9: =(AD4*AD12+AD5*AD13+AD6*AD14+AD7*AD15+AD8*AD16)/SUM(AD12:AD16)+AD10 -> #DIV/0!
J10: =IF(C10="","",IF(F10=0,"NA",TEXT(F10,"0%"))&"; "&IF(G10=0,"NA",TEXT(G10,"0.0%"))&"; "&IF(H10=0,"NA",TEXT(H10,"0%"))) | L10: =B17 -> Coolers & Equipment | N10: =$D$17/$D$27 -> 0.38397477 | O10: =$C$17/$C$27 -> 0.36022567 | V10: Ajuste R&D | W10: =(-6200-18752)/274515 -> -0.090894851 | X10: =(-6143-21914)/365817 -> -0.076696818 | Y10: =(-7207-26251)/394328 -> -0.084848147 | Z10: -0.1 | AA10: -0.1 | AB10: -0.1 | AC10: -0.1 | AD10: -0.1
J11: =IF(C11="","",IF(F11=0,"NA",TEXT(F11,"0%"))&"; "&IF(G11=0,"NA",TEXT(G11,"0.0%"))&"; "&IF(H11=0,"NA",TEXT(H11,"0%"))) | L11: =B18 -> Drinkware | N11: =$D$18/$D$27 -> 0.59378632 | O11: =$C$18/$C$27 -> 0.61673237 | V11: % vts.
J12: =IF(C12="","",IF(F12=0,"NA",TEXT(F12,"0%"))&"; "&IF(G12=0,"NA",TEXT(G12,"0.0%"))&"; "&IF(H12=0,"NA",TEXT(H12,"0%"))) | L12: =B19 -> Others | N12: =$D$19/$D$27 -> 0.022238911 | O12: =$C$19/$C$27 -> 0.023041961 | V12: =V4 -> United States | W12: =1277177/1410989 -> 0.90516439 | X12: =$D$4/$D$14 -> 0.87387586 | Y12: =$C$4/C$14 -> 0.84337978
J13: =IF(C13="","",IF(F13=0,"NA",TEXT(F13,"0%"))&"; "&IF(G13=0,"NA",TEXT(G13,"0.0%"))&"; "&IF(H13=0,"NA",TEXT(H13,"0%"))) | L13: =B20 -> 0 | V13: =V5 -> Internacional | W13: =122812/1410989 -> 0.087039658 | X13: =$D$5/$D$14 -> 0.12612414 | Y13: =$C$5/$C$14 -> 0.15662022
B14: TOTAL | C14: =SUM(C4:C12) -> 1658713 | D14: =SUM(D4:D12) -> 1595222 | E14: 225458 | F14: =C14/SUM($C$4:$C$13) -> 1 | G14: =E14/C14 -> 0.13592345 | H14: =C14/D14-1 -> 0.03980073 | L14: =B21 -> 0 | V14: =V6 -> 0
B15: Products in Thousands (2023) | M15: =SUM(#REF!) -> #REF! | N15: =SUM(N10:N14) -> 1 | O15: =SUM(O10:O14) -> 1 | P15: =SUM(P10:P14) -> 0 | Q15: =SUM(Q10:Q14) -> 0 | R15: =SUM(R10:R14) -> 0 | S15: =SUM(S10:S14) -> 0 | T15: =SUM(T10:T14) -> 0 | V15: =V7 -> 0
C16: =C3 -> 2023 | D16: =C16-1 -> 2022 | E16: Ut. Op. | F16: % Vts | G16: Margen | H16: Crec | N16: =N15/M15-1 -> #REF! | O16: =O15/N15-1 -> 0 | P16: =P15/O15-1 -> -1 | Q16: =Q15/P15-1 -> #DIV/0! | R16: =R15/Q15-1 -> #DIV/0! | S16: =S15/R15-1 -> #DIV/0! | T16: =T15/S15-1 -> #DIV/0! | V16: =V8 -> 0
B17: Coolers & Equipment | C17: 597511 | D17: 612525 | F17: =$C$17/$C$27 -> 0.36022567 | G17: - | H17: =C17/D17-1 -> -0.024511653 | J17: =IF(C17="","",IF(F17=0,"NA",TEXT(F17,"0%"))&"; "&IF(G17=0,"NA",TEXT(G17,"0.0%"))&"; "&IF(H17=0,"NA",TEXT(H17,"0%"))) -> 36%; -; -2% | W17: =SUM(W12:W16) -> 0.99220405 | X17: =SUM(X12:X16) -> 1 | Y17: =SUM(Y12:Y16) -> 1 | Z17: =SUM(Z12:Z16) -> 0 | AA17: =SUM(AA12:AA16) -> 0 | AB17: =SUM(AB12:AB16) -> 0 | AC17: =SUM(AC12:AC16) -> 0 | AD17: =SUM(AD12:AD16) -> 0
B18: Drinkware | C18: 1022982 | D18: 947221 | F18: =$C$18/$C$27 -> 0.61673237 | G18: - | H18: =C18/D18-1 -> 0.079982391 | J18: =IF(C18="","",IF(F18=0,"NA",TEXT(F18,"0%"))&"; "&IF(G18=0,"NA",TEXT(G18,"0.0%"))&"; "&IF(H18=0,"NA",TEXT(H18,"0%"))) -> 62%; -; 8%
B19: Others | C19: 38220 | D19: 35476 | F19: =$C$19/$C$27 -> 0.023041961 | G19: - | H19: =C19/D19-1 -> 0.077348066 | J19: =IF(C19="","",IF(F19=0,"NA",TEXT(F19,"0%"))&"; "&IF(G19=0,"NA",TEXT(G19,"0.0%"))&"; "&IF(H19=0,"NA",TEXT(H19,"0%"))) -> 2%; -; 8%
J20: =IF(C20="","",IF(F20=0,"NA",TEXT(F20,"0%"))&"; "&IF(G20=0,"NA",TEXT(G20,"0.0%"))&"; "&IF(H20=0,"NA",TEXT(H20,"0%")))
J21: =IF(C21="","",IF(F21=0,"NA",TEXT(F21,"0%"))&"; "&IF(G21=0,"NA",TEXT(G21,"0.0%"))&"; "&IF(H21=0,"NA",TEXT(H21,"0%")))
J22: =IF(C22="","",IF(F22=0,"NA",TEXT(F22,"0%"))&"; "&IF(G22=0,"NA",TEXT(G22,"0.0%"))&"; "&IF(H22=0,"NA",TEXT(H22,"0%")))
J23: =IF(C23="","",IF(F23=0,"NA",TEXT(F23,"0%"))&"; "&IF(G23=0,"NA",TEXT(G23,"0.0%"))&"; "&IF(H23=0,"NA",TEXT(H23,"0%")))
J24: =IF(C24="","",IF(F24=0,"NA",TEXT(F24,"0%"))&"; "&IF(G24=0,"NA",TEXT(G24,"0.0%"))&"; "&IF(H24=0,"NA",TEXT(H24,"0%")))
J25: =IF(C25="","",IF(F25=0,"NA",TEXT(F25,"0%"))&"; "&IF(G25=0,"NA",TEXT(G25,"0.0%"))&"; "&IF(H25=0,"NA",TEXT(H25,"0%")))
J26: =IF(C26="","",IF(F26=0,"NA",TEXT(F26,"0%"))&"; "&IF(G26=0,"NA",TEXT(G26,"0.0%"))&"; "&IF(H26=0,"NA",TEXT(H26,"0%")))
B27: TOTAL | C27: =SUM(C17:C26) -> 1658713 | D27: =SUM(D17:D26) -> 1595222 | E27: 225458 | F27: =C27/SUM(C17:C26) -> 1 | G27: =E27/C27 -> 0.13592345 | H27: =C27/D27-1 -> 0.03980073

Sheet Peers
A2: Multiplos (USD) | B2: #VALUE! | C2: #VALUE! | D2: #VALUE! | E2: VSTO
B3: Yeti Holdings, Inc. | C3: Domestic Group AB | D3: Acushnet Holdings Corp. | E3: Vista Outdoor Inc.
A4: Ventas 2024 | B4: =B27 -> 1658.713 | C4: =C27 -> 27775 | D4: =D27 -> 2381.995 | E4: =E27 -> 2746.063
A5: Crecimiento 2024 | B5: =B28/B29-1 -> 0.03980073 | C5: =C28/C29-1 -> -0.066825695 | D5: =D28/D29-1 -> 0.049181707 | E5: =E28/E29-1 -> -0.10836523
A6: Crecimiento (48 meses) | B6: =B28/B31-1 -> 0.51935614 | C6: =C28/C31-1 -> 0.71376566 | D6: =D28/D31-1 -> 0.47750949 | E6: =E28/E31-1 -> 0.56393209
A7: Deuda/Activos | B7: 122278 | C7: 122278 | D7: 122278 | E7: 122278
A8: Deuda/EBITDA | B8: 323888 | C8: 323888 | D8: 323888 | E8: 323888
A9: (Capex + Adq.)/Revenue | B9: =-(B35+B36)/B28 -> -0.043903918 | C9: =-(C35+C36)/C28 -> -0.010513051 | D9: =-(D35+D36)/D28 -> -0.042233086 | E9: =-(E35+E36)/E28 -> -0.017119782
A10: ROA (p) | B10: =B37/B33 -> 0.13096365 | C10: =C37/C33 -> 0.023216886 | D10: =D37/D33 -> 0.090331853 | E10: =E37/E33 -> -0.0022914776
A11: ROIC (p) | B11: =B38/B35 -> 3.3430099 | C11: =C38/C35 -> 0.75899281 | D11: =D38/D35 -> 3.2152221 | E11: =E38/E35 -> 1.9464204
A12: Margen Operativo (p) | B12: =AVERAGE(B39:B41) -> 0.13666348 | C12: =AVERAGE(C39:C41) -> 0.13610568 | D12: =AVERAGE(D39:D41) -> 0.11647496 | E12: =AVERAGE(E39:E41) -> 0.088547764
A13: Margen Operativo 2023 | B13: =B39 -> 0.13592345 | C13: =C39 -> 0.11866787 | D13: =D39 -> 0.11977565 | E13: =E39 -> 0.018372849
A14: Float | B14: =B42 -> 0.98361429 | C14: =C42 -> 0.93020344 | D14: =D42 -> 0.45509868 | E14: N/A
A15: b | B15: =B43 -> 2.14 | C15: =C43 -> 1.68 | D15: =D43 -> 0.87 | E15: N/A
A16: Precio/Utilidad | B16: 18.98 | C16: 15.72 | D16: 21.05 | E16: NA
A17: Precio/Ventas | B17: {=_FV(B2,"Market cap",TRUE)/(1000000*B4)} -> 1.8982914 | C17: {=_FV(C2,"Market cap",TRUE)/(1000000*C4)} -> 0.041496346 | D17: {=_FV(D2,"Market cap",TRUE)/(1000000*D4)} -> 1.6877832 | E17: N/A
A18: EV/Activos | B18: =B45/B33 -> 3.3765241 | C18: =C45/C33 -> 1.9379272 | D18: =D45/D33 -> 0.21259481 | E18: N/A
A19: EV/EBITDA | B19: =B45/B34 -> 16.080476 | C19: =C45/C34 -> 51.289157 | D19: =D45/D34 -> 1.3979274 | E19: N/A
A20: Div. Yield | B20: =B46 -> N/A | C20: =C46 -> 0.0351 | D20: =D46 -> 0.0131 | E20: N/A
A21: Año Fiscal | B21: 12-2023 | C21: 12-2023 | D21: 12-2023 | E21: 03-2024
B23: *p = average for the last 3 years
B24: **in USD
C25: In millions SEK
A26: in millions USD | B26: YETI holdings | C26: Dometic Group AB | D26: =D3 -> Acushnet Holdings Corp. | E26: =E3 -> Vista Outdoor Inc.
A27: Total Revenue | B27: 1658.713 | C27: 27775 | D27: 2381.995 | E27: 2746.063
A28: Revenue from 23 | B28: 1658.713 | C28: 27775 | D28: 2381.995 | E28: 2746.063
A29: Revenue from 22 | B29: 1595.222 | C29: 29764 | D29: 2270.336 | E29: 3079.807
A30: Revenue from 21 | B30: 1410.989 | C30: 21516 | D30: 2147.93 | E30: 3044.621
A31: Revenue from 20 | B31: 1091.721 | C31: 16207 | D31: 1612.169 | E31: 1755.871
A32: Debt | B32: 78.645 | C32: 12029 | D32: 701.167 | E32: 717.238
A33: Assets | B33: 1297.192 | C33: 2196.677 | D33: 2196.667 | E33: 2402.38
A34: EBITDA | B34: =169.885+56.061+46.434 -> 272.38 | C34: 83 | D34: =198.429+42.993+41.288+51.356 -> 334.066 | E34: =-5.505-8.979+62.949+49.145+50.146 -> 147.756
A35: CAPEX | B35: 50.672 | C35: 278 | D35: 75.364 | E35: 30.534
A36: Acquisitions | B36: 22.152 | C36: 14 | D36: 25.235 | E36: 16.478
A37: Net income | B37: 169.885 | C37: 51 | D37: 198.429 | E37: -5.505
A38: net operating profit after taxes | B38: =225.458-56.061 -> 169.397 | C38: =242-31 -> 211 | D38: =285.305-42.993 -> 242.312 | E38: =50.453+8.979 -> 59.432
A39: Operating margin 23 | B39: =225.458/1658.713 -> 0.13592345 | C39: =3296/C28 -> 0.11866787 | D39: =285.305/D28 -> 0.11977565 | E39: =50.453/E28 -> 0.018372849
A40: Operating margin 2022 | B40: =126.361/1595.222 -> 0.079212172 | C40: =3399/C29 -> 0.11419836 | D40: =259.435/D29 -> 0.11427163 | E40: =107.855/E29 -> 0.035020052
A41: Operating margin 21 | B41: =274.938/B30 -> 0.19485481 | C41: =3775/C30 -> 0.17545083 | D41: =247.823/D30 -> 0.1153776 | E41: =646.222/E30 -> 0.21225039
A42: float | B42: =83.44/84.83 -> 0.98361429 | C42: =297.2/319.5 -> 0.93020344 | D42: =27.67/60.8 -> 0.45509868
A43: beta | B43: 2.14 | C43: 1.68 | D43: 0.87
A44: price
A45: EV | B45: 4380 | C45: 4257 | D45: 467
A46: Div yield | B46: N/A | C46: 0.0351 | D46: 0.0131

Sheet Acuerdo
A1: Invertir
A2: NO invertir
A3: Mantener sin elevar posición
A4: Mantener (y seguir comprando)
A5: Liquidar
A6: PENDIENTE

Sheet DCF
A1: Discounted Cash Flow
A3: Ventas | E3: Margen Operativo
A16: Inversiones | E16: Utilidad Neta
D31: 0.001 | E31: =1/((1+$B$59+$D31)^(E35-2021)) -> 0.92250923 | F31: =1/((1+$B$59+$D31)^(F35-2021)) -> 0.85102327 | G31: =1/((1+$B$59+$D31)^(G35-2021)) -> 0.78507682 | H31: =1/((1+$B$59+$D31)^(H35-2021)) -> 0.72424061 | I31: =1/((1+$B$59+$D31)^(I35-2021)) -> 0.66811864 | J31: =1/((1+$B$59+$D31)^(J35-2021)) -> 0.61634561 | K31: =1/((1+$B$59+$D31)^(K35-2021)) -> 0.56858451 | L31: =1/((1+$B$59+$D31)^(L35-2021)) -> 0.52452446 | ... AC31: =1/((1+$B$59+$D31)^(AC35-2021)) -> 0.13312755
D32: 0.005 | E32: =1/((1+$B$59+$D32)^(E35-2021)) -> 0.91911765 | F32: =1/((1+$B$59+$D32)^(F35-2021)) -> 0.84477725 | G32: =1/((1+$B$59+$D32)^(G35-2021)) -> 0.77644968 | H32: =1/((1+$B$59+$D32)^(H35-2021)) -> 0.7136486 | I32: =1/((1+$B$59+$D32)^(I35-2021)) -> 0.65592702 | J32: =1/((1+$B$59+$D32)^(J35-2021)) -> 0.6028741 | K32: =1/((1+$B$59+$D32)^(K35-2021)) -> 0.55411223 | L32: =1/((1+$B$59+$D32)^(L35-2021)) -> 0.50929433 | ... AC32: =1/((1+$B$59+$D32)^(AC35-2021)) -> 0.12141647
D33: Normal | E33: =1/((1+$B$59)^(E35-2021)) -> 0.92336103 | F33: =1/((1+$B$59)^(F35-2021)) -> 0.8525956 | G33: =1/((1+$B$59)^(G35-2021)) -> 0.78725355 | H33: =1/((1+$B$59)^(H35-2021)) -> 0.72691926 | I33: =1/((1+$B$59)^(I35-2021)) -> 0.67120892 | J33: =1/((1+$B$59)^(J35-2021)) -> 0.61976816 | K33: =1/((1+$B$59)^(K35-2021)) -> 0.57226977 | L33: =1/((1+$B$59)^(L35-2021)) -> 0.5284116 | ... AC33: =1/((1+$B$59)^(AC35-2021)) -> 0.13623496
B35: 2019 (Real) | C35: 2020 (Real) | D35: 2021 | E35: =D35+1 -> 2022 | F35: =E35+1 -> 2023 | G35: =F35+1 -> 2024 | H35: =G35+1 -> 2025 | I35: =H35+1 -> 2026 | J35: =I35+1 -> 2027 | K35: =J35+1 -> 2028 | L35: =K35+1 -> 2029 | ... AC35: =AB35+1 -> 2046
A36: Crecimiento | B36: =#REF! -> #REF! | C36: =#REF! -> #REF! | D36: 0.35 | E36: 0.034 | F36: 0.095 | G36: 0.095 | H36: 0.095 | I36: 0.095 | J36: 0.095 | K36: 0.08 | L36: 0.06 | M36: 0.05 | N36: 0.04 | O36: 0.035 | P36: 0.035 | Q36: 0.035 | R36: 0.035 | S36: 0.035 | T36: 0.035 | U36: 0.035 | V36: 0.035 | W36: 0.035 | X36: 0.035 | Y36: 0.035 | Z36: 0.035 | AA36: 0.035 | AB36: 0.035 | AC36: 0.035
A37: Ventas | B37: =#REF! -> #REF! | C37: =#REF! -> #REF! | D37: =#REF!*(1+D36) -> #REF! | E37: =D37*(1+E36) -> #REF! | F37: =E37*(1+F36) -> #REF! | G37: =F37*(1+G36) -> #REF! | H37: =G37*(1+H36) -> #REF! | I37: =H37*(1+I36) -> #REF! | J37: =I37*(1+J36) -> #REF! | K37: =J37*(1+K36) -> #REF! | L37: =K37*(1+L36) -> #REF! | ... AC37: =AB37*(1+AC36) -> #REF!
A38: Margen Operativo | B38: =+#REF! -> #REF! | C38: =+#REF! -> #REF! | D38: =108166.4/365513.2 -> 0.29593022 | E38: =108162.8/377959.8 -> 0.28617541 | F38: 0.27 | G38: 0.275 | H38: 0.26 | I38: 0.255 | J38: 0.25 | K38: 0.25 | L38: 0.25 | M38: 0.25 | N38: 0.25 | O38: 0.25 | P38: 0.25 | Q38: 0.25 | R38: 0.25 | S38: 0.25 | T38: 0.25 | U38: 0.25 | V38: 0.25 | W38: 0.25 | X38: 0.25 | Y38: 0.25 | Z38: 0.25 | AA38: 0.25 | AB38: 0.25 | AC38: 0.25
A39: EBIT | B39: 63930 | C39: 66288 | D39: =D37*D38 -> #REF! | E39: =E37*E38 -> #REF! | F39: =F37*F38 -> #REF! | G39: =G37*G38 -> #REF! | H39: =H37*H38 -> #REF! | I39: =I37*I38 -> #REF! | J39: =J37*J38 -> #REF! | K39: =K37*K38 -> #REF! | ... AC39: =AC37*AC38 -> #REF!
A40: Dep&Amort | B40: =#REF! -> #REF! | C40: =#REF! -> #REF! | D40: 11000 | E40: =D40*(1+E36*$H$59) -> 11374 | F40: =E40*(1+F36*$H$59) -> 12454.53 | G40: =F40*(1+G36*$H$59) -> 13637.71 | H40: =G40*(1+H36*$H$59) -> 14933.293 | I40: =H40*(1+I36*$I$59) -> 16351.956 | J40: =I40*(1+J36*$I$59) -> 17905.391 | K40: =J40*(1+K36*$I$59) -> 19337.823 | L40: =K40*(1+L36*$I$59) -> 20498.092 | M40: =L40*(1+M36*$I$59) -> 21522.997 | N40: =M40*(1+N36*$I$59) -> 22383.917 | O40: =N40*(1+O36*$I$59) -> 23167.354 | P40: =O40*(1+P36*$I$59) -> 23978.211 | ... AC40: =AB40*(1+AC36*$I$59) -> 37500.868
A41: EBIDTA | B41: =+B39+B40 -> #REF! | C41: =+C39+C40 -> #REF! | D41: =D39+D40 -> #REF! | E41: =E39+E40 -> #REF! | F41: =F39+F40 -> #REF! | G41: =G39+G40 -> #REF! | H41: =H39+H40 -> #REF! | I41: =I39+I40 -> #REF! | J41: =J39+J40 -> #REF! | K41: =K39+K40 -> #REF! | ... AC41: =AC39+AC40 -> #REF!
A42: CIF | B42: -1385 | C42: -890 | D42: =(C48)*$H$60 -> -1124.36 | E42: =(D48)*$H$60 -> -1113.1164 | F42: =(E48)*$H$60 -> -1113.1164 | G42: =(F48)*$H$60 -> -1113.1164 | H42: =(G48)*$H$60 -> -1113.1164 | I42: =(H48)*$H$60 -> -1113.1164 | J42: =(I48)*$H$60 -> -1113.1164 | K42: =(J48)*$H$60 -> -1113.1164 | ... AC42: =(AB48)*$H$60 -> -1113.1164
A43: Otros Gastos | B43: =-422-2817 -> -3239 | C43: =87-3634 -> -3547 | D43: =-C43*(1+D36) -> 4788.45 | E43: =D43*(1+E36*0.5) -> 4869.8537 | F43: =E43*(1+F36*0.5) -> 5101.1717 | G43: =F43*(1+G36*0.5) -> 5343.4774 | H43: =G43*(1+H36*0.5) -> 5597.2925 | I43: =H43*(1+I36*0.5) -> 5863.1639 | J43: =I43*(1+J36*0.5) -> 6141.6642 | K43: =J43*(1+K36*0.5) -> 6387.3308 | L43: =K43*(1+L36*0.5) -> 6578.9507 | ... AC43: =AB43*(1+AC36*0.5) -> 8922.7133
A44: Utilidad antes de Impuestos | B44: =B39-B42-B43 -> 68554 | C44: =C39-C42-C43 -> 70725 | D44: =D39-D42-D43 -> #REF! | E44: =E39-E42-E43 -> #REF! | F44: =F39-F42-F43 -> #REF! | G44: =G39-G42-G43 -> #REF! | H44: =H39-H42-H43 -> #REF! | I44: =I39-I42-I43 -> #REF! | ... AC44: =AC39-AC42-AC43 -> #REF!
A45: ISR & PTU | B45: 10481 | C45: 9680 | D45: =$H$61*D44 -> #REF! | E45: =$H$61*E44 -> #REF! | F45: =$H$61*F44 -> #REF! | G45: =$I$61*G44 -> #REF! | H45: =$I$61*H44 -> #REF! | I45: =$I$61*I44 -> #REF! | J45: =$I$61*J44 -> #REF! | K45: =$I$61*K44 -> #REF! | L45: =$I$61*L44 -> #REF! | M45: =$I$61*M44 -> #REF! | N45: =$I$61*N44 -> #REF! | ... AC45: =$I$61*AC44 -> #REF!
A46: Utilidad Neta | B46: =B44-B45 -> 58073 | C46: =C44-C45 -> 61045 | D46: =D44-D45 -> #REF! | E46: =E44-E45 -> #REF! | F46: =F44-F45 -> #REF! | G46: =G44-G45 -> #REF! | H46: =H44-H45 -> #REF! | I46: =I44-I45 -> #REF! | ... AC46: =AC44-AC45 -> #REF!
A47: Inversiones y Capex | B47: =#REF! -> #REF! | C47: =#REF! -> #REF! | D47: 10000 | E47: =D47*(1+E36*$H$62) -> 10408 | F47: =E47*(1+F36*$H$62) -> 11594.512 | G47: =F47*(1+G36*$H$62) -> 12916.286 | H47: =G47*(1+H36*$H$62) -> 14388.743 | I47: =H47*(1+I36*$H$62) -> 16029.06 | J47: =I47*(1+J36*$H$62) -> 17856.373 | K47: =J47*(1+K36*$H$62) -> 19570.584 | L47: =K47*(1+L36*$H$62) -> 20979.666 | ... AC47: =AB47*(1+AC36*$H$62) -> 43199.777
A48: Deuda + Lease Liabilities | B48: 108047 | C48: 112436 | D48: =C48*0.99 -> 111311.64 | E48: =D48 -> 111311.64 | F48: =E48 -> 111311.64 | G48: =F48 -> 111311.64 | H48: =G48 -> 111311.64 | I48: =H48 -> 111311.64 | J48: =I48 -> 111311.64 | K48: =J48 -> 111311.64 | L48: =K48 -> 111311.64 | ... AC48: =AB48 -> 111311.64
A49: Deuda/EBITDA | B49: =B48/B41 -> #REF! | C49: =C48/C41 -> #REF! | D49: =D48/D41 -> #REF! | E49: =E48/E41 -> #REF!
A50: FNP | B50: =#REF! -> #REF! | C50: =#REF! -> #REF! | D50: =D41-D42-D43-D45-D47+D48-C48 -> #REF! | E50: =E41-E42-E43-E45-E47+E48-D48 -> #REF! | F50: =F41-F42-F43-F45-F47+F48-E48 -> #REF! | G50: =G41-G42-G43-G45-G47+G48-F48 -> #REF! | H50: =H41-H42-H43-H45-H47+H48-G48 -> #REF! | I50: =I41-I42-I43-I45-I47+I48-H48 -> #REF! | J50: =J41-J42-J43-J45-J47+J48-I48 -> #REF! | K50: =K41-K42-K43-K45-K47+K48-J48 -> #REF! | ... AC50: =AC41-AC42-AC43-AC45-AC47+AC48-AB48 -> #REF!
A51: F(t) | B51: 0 | C51: 0 | D51: =C51*(1+$B$59)+D50 -> #REF! | E51: =D51*(1+$B$59)+E50 -> #REF! | F51: =E51*(1+$B$59)+F50 -> #REF! | G51: =F51*(1+$B$59)+G50 -> #REF! | H51: =G51*(1+$B$59)+H50 -> #REF! | I51: =H51*(1+$B$59)+I50 -> #REF! | J51: =I51*(1+$B$59)+J50 -> #REF! | K51: =J51*(1+$B$59)+K50 -> #REF! | ... AC51: =AB51*(1+$B$59)+AC50 -> #REF!
AB52: =AB51-AB48 -> #REF! | AC52: =AC50/(B59-AC36) -> #REF!
A53: EPS | C53: =1000000*C46/#REF! -> #REF! | D53: =1000000*D46/#REF! -> #REF! | E53: =1000000*E46/#REF! -> #REF! | F53: =1000000*F46/#REF! -> #REF!
A54: Consenso EPS | C54: 3.3 | D54: 5.6 | E54: 5.6
A55: E$/UN | D55: =$B$61/D46 -> #REF! | E55: =$B$61/E46 -> #REF! | F55: =$B$61/F46 -> #REF!
A56: EEV/EBIDA | D56: =($B$61+D48-D51)/D41 -> #REF! | E56: =($B$61+E48-E51)/E41 -> #REF! | F56: =($B$61+F48-F51)/F41 -> #REF!
C58: "TELP" | D58: CER | E58: D Analista | H58: CP | I58: LP
A59: Tasa de descuento: | B59: =SUM(C59:E59) -> 0.083 | C59: 0.0307 | D59: 0.0523 | E59: 0 | G59: Factor D&A | H59: 1 | I59: 1
G60: Factor CIF | H60: -0.01
A61: VPN*@i% | B61: =C62+C63 -> #REF! | C61: Normal | D61: =D31 -> 0.001 | E61: =D32 -> 0.005 | G61: Factor ISR | H61: 0.21 | I61: 0.23
A62: DCF 25Y | B62: =C62/B61 -> #REF! | C62: =AB52/(1+B59)^25 -> #REF! | D62: =SUMPRODUCT(E50:AB50,E31:AB31) -> #REF! | E62: =SUMPRODUCT(E50:AB50,E32:AB32) -> #REF! | G62: Factor inv | H62: 1.2
A63: Perpetuidad | B63: =1-B62 -> #REF! | C63: =AC52/(1+B59)^25 -> #REF! | D63: =(AC50/($B$59+D31-$AC$36))*AC31 -> #REF! | E63: =(AC50/($B$59+D32-$AC$36))*AC32 -> #REF! | G63: Suma D&A | H63: =SUM(40:40) -> #REF!
A64: VPN/Acción | B64: =1000000*B61/#REF! -> #REF! | D64: =1000000*SUM(D62:D63)/#REF! -> #REF! | E64: =1000000*SUM(E62:E63)/#REF! -> #REF! | G64: Suma Inv. | H64: =SUM(47:47) -> #REF!
B65: =B64/#REF!-1 -> #REF! | D65: =D64/B64-1 -> #REF! | E65: =E64/B64-1 -> #REF! | G65: Inv.+Goodwill | H65: =SUM(47:47)+(#REF!*#REF!) -> #REF!
A67: Duración | B67: =B62*D68+B63*D69 -> #REF! | E67: 1 | F67: 2 | G67: 3 | H67: 4 | I67: 5 | J67: 6 | K67: 7 | L67: 8 | M67: 9 | N67: 10 | O67: 11 | P67: 12 | Q67: 13 | R67: 14 | S67: 15 | T67: 16 | U67: 17 | V67: 18 | W67: 19 | X67: 20 | Y67: 21 | Z67: 22 | AA67: 23 | AB67: 24 | AC67: 25
A68: 0.001 | B68: =-$B$67*A68 -> #REF! | D68: =SUM(E68:AB68)/SUMPRODUCT(E50:AB50,E33:AB33) -> #REF! | E68: =E67*E50*E33 -> #REF! | F68: =F67*F50*F33 -> #REF! | G68: =G67*G50*G33 -> #REF! | H68: =H67*H50*H33 -> #REF! | I68: =I67*I50*I33 -> #REF! | J68: =J67*J50*J33 -> #REF! | K68: =K67*K50*K33 -> #REF! | L68: =L67*L50*L33 -> #REF! | ... AC68: =AC67*AC50*AC33 -> #REF!
A69: 0.005 | B69: =-$B$67*A69 -> #REF! | D69: =(1+B59)/B59+AC67 -> 38.048193

Sheet ESG
B2: Análisis ESG | J2: PARÁMETROS
C3: Impacto | D3: ¿Reporta? | E3: Ranking | F3: Mitigación | G3: Semáforo | H3: Comentarios | J3: IMPACTO | L3: RANKING | M3: MITIGACIÓN
B4: Ambiental | J4: NONE | K4: 0 | L4: "Best in class" | M4: Is there evidence of progam/plan/etc…
B5: Emisiones directas CO2 | C5: Low | D5: Yes | E5: Medium High | F5: Yes | H5: Scope 1 and 2 has been declining for the past 3 years | J5: LOW | K5: 1 | L5: Medium high
B6: Uso total de agua | C6: High | D6: Yes | E6: Medium | F6: No | H6: No mention of measures regarding. | J6: MEDIUM | K6: 2 | L6: Medium
B7: Total Energy Consumption | C7: Medium | D7: Yes | E7: Medium High | F7: Yes | H7: U.S operations are powered through 100% renewable energy. Globally, are purchasing REC's (Renewable Energy Certificates). In 2023, Renewable Energy makes 56% of total in use within the organization. | J7: HIGH | K7: 3 | L7: "Villain"
B8: Waste Management | C8: Medium | D8: Yes | E8: Medium | F8: Yes | H8: Has been decreasing since 2020 due to waste reduction efforts
B9: Land Degradation/Deforestation/Biodiversity loss/Animal sufering/… | C9: High | D9: No | E9: Medium | F9: No | H9: No policies in place | J9: TRAFFIC LIGHTS
B10: Social
B11: % Rotación de empleados | C11: Medium | D11: No | E11: Medium | F11: No | H11: Specifics are not disclosed, but is seen as a derirable employeer.
B12: Sueldos y compensaciones | C12: Low | D12: No | E12: Medium High | F12: Yes | H12: Provides market-competitive compensation, healthcare, 401(k) program, paid time off, bonding leave, as well as health, wellness, and financial planning programs.
B13: Temas de reputación | C13: Low | D13: N/A | E13: "Best in Class" | F13: Yes | H13: Selected as one of the Best Places to Work in 2024 by Glassdor.
B14: Temas de discriminación | C14: Medium | D14: Yes | E14: Medium | F14: Yes | H14: The company provides Employee Resource Groups that actively educate and discuss topics, widening perspetives. However, higher-up management positions are male dominated (only 30% women).
B15: Seguridad laboral | C15: Low | D15: Yes | E15: Medium High | F15: Yes | H15: Since 2021, 100% of U.S. employees in offices, stores and warehouses are covered by occupational health and safety management system. They also "report a 93% completion rate of safety training for relevant employees in the U.S."
B16: Daños a la salud | C16: Medium | D16: Yes | E16: Medium High | F16: Yes | H16: Cases of facilities not being compliant with expectations have risen in the past 4 years, with non-compliances becoming more and more severe (comparing critical and non-priority), with the biggest issue being Health, Safety, & Hygiene.
B17: PXP? | D17: Yes | E17: Medium High | F17: Yes | H17: "We provide a 401(k)-defined contribution plan covering substantially all our employees (…). Our contributions totaled approximately $2.0 million, $1.5 million, and $1.2 million for 2023, 2022, and 2021, respectively."
B18: Supply chain | C18: High | D18: Yes | E18: Medium | F18: No | H18: Yeti does not own any of the manufacturing facilities, having third-parties in China (the biggest), the Philippines, Vietnam, Taiwan, Poland, Mexico, Thailand and Malaysia.
B19: Community involvement | C19: Low | D19: Yes | E19: "Best in Class" | F19: Yes | H19: Has partherships with many foundations, promoting activities ranging from beach clean-ups, conservation and restoration programs; Donated $2.3 million to support organizations and individuals working to preserve the wild.
B20: Public Sector | C20: Medium | D20: Yes | E20: Medium High | F20: Yes | H20: No political contribuitions, corruption or customer privacy violations.
B21: Litigios | C21: Low | D21: Yes | E21: Medium | F21: Yes | H21: The company had to recall more than 1.9 million coolers and cases as their magnets could detach, posing a deadly risk if swallowed. No injuries were reported, refunds and replacements were offered (March, 2023).Yeti sued TerraCycle US, who instead of destroying and recycling branded merchandise, illicitly sold them (July, 2023).
B22: Gobierno
B23: Diversidad (Género, edad, industria, región) | E23: Medium | F23: Yes | H23: As of 2023. out of all 11 directors, 10 are non executives and independent, 4 women on board, lacking in non-white representation.
B24: % independientes | E24: Medium High | F24: Yes | H24: 0.9091
B25: tiempo promedio como consejeros independientes | E25: Medium High | F25: Yes | H25: Average Director Tenure is 3.75 years.
B26: Salidas recientes de consejeros/C-level executives? | E26: Medium High | F26: Yes | H26: In 2022, Yeti announced the departure of the long-time CFO, this transition being part of a planned succession strategy
B27: CEO/Chairman | E27: Medium High | F27: Yes | H27: Stable leadership
B28: Transparencia (segmentos, fuente de riqueza, adquisiciones, otros) | E28: Medium | F28: No | H28: In the Sustainability Report, Water Use and Employee Turnover were not present. The 10k lacks certain detailed metrics.
B29: Tiempo que tardan en reportar luego del final del trimestre/año | E29: Medium High | F29: Yes | H29: Within expected window (3 months)
B30: Participación adicional del CEO en otros consejos o excesiva del Ch. | E30: "Best in Class" | F30: Yes | H30: No external commitments
B31: Auditoría/Consultoría | D31: Yes | E31: Medium High | F31: Yes | H31: PricewaterhouseCoopers LLp (one of the Big 4, stellar reputation) has been Yeti's auditor since 2021. No over-riliance on external consultants.
B32: Esquemas de compensación al management | C32: Low | D32: Yes | E32: Medium High | F32: Yes | H32: Pay-for-performance aligment (Cash/Short Term - net sales/operating income targets; Equity/Long term PBRSUs [Performance-Based Restricted Stock Units] requiring 90% target performance, with 200% cap, excludes stock options to reduce excessive risk taking)

Sheet DCFF
C1: VALUATION MODEL
H3: SHORT TERM | M3: MEDIUM TERM | W3: LONG TERM
D4: =D20/D7 -> 0.0082521084 | E4: =E20/E7 -> 0.010966776 | F4: =F20/F7 -> 0.011157695 | G4: =G20/G7 -> 0.017965736 | H4: =H20/H7 -> 0.022252364 | I4: =I20/I7 -> 0.02 | J4: =J20/J7 -> 0.02 | K4: =K20/K7 -> 0.02 | ... AF4: =AF20/AF7 -> 0.015
A5: Section | B5: Line # | C5: ITEM | D5: 2020 (Real) | E5: 2021 (Real) | F5: 2022 (Real) | G5: 2023 (Real) | H5: 2024 | I5: =+H5+1 -> 2025 | J5: =+I5+1 -> 2026 | K5: =+J5+1 -> 2027 | L5: =+K5+1 -> 2028 | M5: =+L5+1 -> 2029 | N5: =+M5+1 -> 2030 | O5: =+N5+1 -> 2031 | P5: =+O5+1 -> 2032 | ... AF5: =+AE5+1 -> 2048 | AG5: Notes
A6: INCOME STATEMENT | B6: 1 | C6: Growth | D6: =Cifras_en_Millones!F6 -> 0.19479083 | E6: =Cifras_en_Millones!E6 -> 0.29244468 | F6: =Cifras_en_Millones!D6 -> 0.13057012 | G6: =Cifras_en_Millones!C6 -> 0.03980073 | H6: 0.10318844 | I6: 0.18 | J6: 0.16 | K6: 0.14 | L6: 0.13 | M6: 0.11 | N6: 0.1 | O6: 0.09 | P6: 0.08 | Q6: 0.07 | R6: 0.07 | S6: 0.07 | T6: 0.06 | U6: 0.06 | V6: 0.05 | W6: 0.05 | X6: 0.05 | Y6: 0.05 | Z6: 0.04 | AA6: 0.04 | AB6: 0.04 | AC6: 0.04 | AD6: 0.03 | AE6: 0.03 | AF6: 0.03
B7: 2 | C7: Revenues/Sales | D7: =Cifras_Originales!E6 -> 1091.721 | E7: =Cifras_Originales!D6 -> 1410.989 | F7: =Cifras_Originales!C6 -> 1595.222 | G7: =Cifras_Originales!B6 -> 1658.713 | H7: =G7*(1+H6) -> 1829.873 | I7: =H7*(1+I6) -> 2159.2501 | J7: =I7*(1+J6) -> 2504.7302 | K7: =J7*(1+K6) -> 2855.3924 | L7: =K7*(1+L6) -> 3226.5934 | M7: =L7*(1+M6) -> 3581.5187 | N7: =M7*(1+N6) -> 3939.6705 | O7: =N7*(1+O6) -> 4294.2409 | ... AF7: =AE7*(1+AF6) -> 9919.1726
B8: 3 | C8: EBIT/Operating Margin | D8: 0.1972 | E8: 0.1982 | F8: 0.1608 | G8: 0.1398 | H8: 0.16 | I8: 0.16 | J8: 0.16 | K8: 0.16 | L8: 0.16 | M8: 0.16 | N8: 0.16 | O8: 0.16 | P8: 0.16 | Q8: 0.16 | R8: 0.16 | S8: 0.16 | T8: 0.16 | U8: 0.16 | V8: 0.16 | W8: 0.16 | X8: 0.16 | Y8: 0.16 | Z8: 0.16 | AA8: 0.16 | AB8: 0.16 | AC8: 0.16 | AD8: 0.16 | AE8: 0.16 | AF8: 0.16
B9: 4 | C9: EBIT | D9: =D7*D8 -> 215.28738 | E9: =E7*E8 -> 279.65802 | F9: =F7*F8 -> 256.5117 | G9: =G8*G7 -> 231.88808 | H9: =H8*H7 -> 292.77968 | I9: =I8*I7 -> 345.48002 | J9: =J8*J7 -> 400.75683 | K9: =K8*K7 -> 456.86278 | L9: =L8*L7 -> 516.25494 | M9: =M8*M7 -> 573.04299 | N9: =N8*N7 -> 630.34729 | ... AF9: =AF8*AF7 -> 1587.0676
B10: 5a | C10: (Dep&Amort) | D10: =Cifras_Originales!E11 -> -30.535 | E10: =Cifras_Originales!D11 -> -32.07 | F10: =Cifras_Originales!C11 -> -39.847 | G10: =Cifras_Originales!B11 -> -46.434 | H10: -48.132 | I10: {=H10*0.7+0.3*(-$D$51*AVERAGE(-1*(E23:H23)))} -> -44.07471 | J10: {=I10*0.7+0.3*(-$D$51*AVERAGE(-1*(F23:I23)))} -> -42.595812 | K10: {=J10*0.7+0.3*(-$D$51*AVERAGE(-1*(G23:J23)))} -> -44.002293 | L10: {=K10*0.7+0.3*(-$D$51*AVERAGE(-1*(H23:K23)))} -> -47.846296 | M10: {=L10*0.7+0.3*(-$D$51*AVERAGE(-1*(I23:L23)))} -> -52.835146 | N10: {=M10*0.7+0.3*(-$D$51*AVERAGE(-1*(J23:M23)))} -> -62.110791 | O10: {=N10*0.7+0.3*(-$D$51*AVERAGE(-1*(K23:N23)))} -> -74.732339 | P10: {=O10*0.7+0.3*(-$D$51*AVERAGE(-1*(L23:O23)))} -> -90.022167 | ... V10: {=U10*0.7+0.3*(-$D$51*AVERAGE(-1*(R23:U23)))} -> -179.35383 | W10: {=V10*0.7+0.3*(-$F$51*AVERAGE(-1*(S23:V23)))} -> -192.48191 | X10: {=W10*0.7+0.3*(-$F$51*AVERAGE(-1*(T23:W23)))} -> -211.66852 | Y10: {=X10*0.7+0.3*(-$F$51*AVERAGE(-1*(U23:X23)))} -> -235.44255 | Z10: {=Y10*0.7+0.3*(-$F$51*AVERAGE(-1*(V23:Y23)))} -> -262.78234 | AA10: {=Z10*0.7+0.3*(-$F$51*AVERAGE(-1*(W23:Z23)))} -> -292.87372 | AB10: {=AA10*0.7+0.3*(-$F$51*AVERAGE(-1*(X23:AA23)))} -> -318.81413 | AC10: {=AB10*0.7+0.3*(-$F$51*AVERAGE(-1*(Y23:AB23)))} -> -341.79056 | AD10: {=AC10*0.7+0.3*(-$F$51*AVERAGE(-1*(Z23:AC23)))} -> -362.61889 | ... AF10: {=AE10*0.7+0.3*(-$F$51*AVERAGE(-1*(AB23:AE23)))} -> -399.69346
B11: 5b | C11: (Stock based compensation) | D11: =-D20 -> -9.009 | E11: =-E20 -> -15.474 | F11: =-F20 -> -17.799 | G11: =-G20 -> -29.8 | H11: -40.719 | I11: =-$D$52*I7 -> -43.185003 | J11: =-$D$52*J7 -> -50.094603 | K11: =-$D$52*K7 -> -57.107848 | L11: =-$D$52*L7 -> -64.531868 | M11: =-$E$52*M7 -> -35.815187 | N11: =-$E$52*N7 -> -39.396705 | O11: =-$E$52*O7 -> -42.942409 | P11: =-$E$52*P7 -> -46.377802 | Q11: =-$E$52*Q7 -> -49.624248 | R11: =-$E$52*R7 -> -53.097945 | S11: =-$E$52*S7 -> -56.814801 | T11: =-$E$52*T7 -> -60.223689 | ... V11: =-$E$52*V7 -> -67.028966 | W11: =-$F$52*W7 -> -105.57062 | X11: =-$F$52*X7 -> -110.84915 | Y11: =-$F$52*Y7 -> -116.39161 | Z11: =-$F$52*Z7 -> -121.04727 | AA11: =-$F$52*AA7 -> -125.88917 | AB11: =-$F$52*AB7 -> -130.92473 | AC11: =-$F$52*AC7 -> -136.16172 | AD11: =-$F$52*AD7 -> -140.24657 | ... AF11: =-$F$52*AF7 -> -148.78759
B12: 6 | C12: EBIDTA | D12: =-D10+D9 -> 245.82238 | E12: =-E10+E9 -> 311.72802 | F12: =-F10+F9 -> 296.3587 | G12: =-G10+G9 -> 278.32208 | H12: =-H10+H9 -> 340.91168 | I12: =-I10+I9 -> 389.55473 | J12: =-J10+J9 -> 443.35264 | K12: =-K10+K9 -> 500.86507 | ... AF12: =-AF10+AF9 -> 1986.7611
B13: 7 | C13: (Net financing cost) | D13: =Cifras_Originales!E9 -> -9.155 | E13: =Cifras_Originales!D9 -> -3.339 | F13: =Cifras_Originales!C9 -> -4.466 | G13: =Cifras_Originales!B9 -> -0.942 | H13: =-$D$54*G38+G37*$D$55 -> -3.52226 | I13: =-$D$54*H38+H37*$D$55 -> -3.52226 | J13: =-$D$54*I38+I37*$D$55 -> -3.43786 | K13: =-$D$54*J38+J37*$D$55 -> -9.35346 | L13: =-$D$54*K38+K37*$D$55 -> -8.66906 | M13: =-$E$54*L38+L37*$E$55 -> -4.5547199 | N13: =-$E$54*M38+M37*$E$55 -> -3.3424452 | O13: =-$E$54*N38+N37*$E$55 -> -1.6066142 | P13: =-$E$54*O38+O37*$E$55 -> 1.4076075 | Q13: =-$E$54*P38+P37*$E$55 -> 1.7253311 | R13: =-$E$54*Q38+Q37*$E$55 -> 2.2732944 | S13: =-$E$54*R38+R37*$E$55 -> 2.5010553 | T13: =-$E$54*S38+S37*$E$55 -> 3.1580184 | ... V13: =-$E$54*U38+U37*$E$55 -> 5.2753978 | W13: =-$F$54*V38+V37*$F$55 -> 13.4803 | X13: =-$F$54*W38+W37*$F$55 -> 15.623977 | Y13: =-$F$54*X38+X37*$F$55 -> 18.148062 | Z13: =-$F$54*Y38+Y37*$F$55 -> 21.111599 | AA13: =-$F$54*Z38+Z37*$F$55 -> 24.675564 | AB13: =-$F$54*AA38+AA37*$F$55 -> 28.432466 | AC13: =-$F$54*AB38+AB37*$F$55 -> 32.450094 | AD13: =-$F$54*AC38+AC37*$F$55 -> 36.708902 | ... AF13: =-$F$54*AE38+AE37*$F$55 -> 45.822157
B14: 8 | C14: Other income/(cost) | D14: =Cifras_Originales!E10 -> 0.123 | E14: =Cifras_Originales!D10 -> 3.189 | F14: =Cifras_Originales!C10 -> 5.718 | G14: =Cifras_Originales!B10 -> 1.43 | H14: =AVERAGE(E14:G14)*(1+H6) -> 3.8012196 | I14: =AVERAGE(F14:H14)*(1+I6) -> 4.3066931 | J14: =AVERAGE(G14:I14)*(1+J6) -> 3.6879929 | K14: =AVERAGE(H14:J14)*(1+K6) -> 4.4824441 | L14: =AVERAGE(I14:K14)*(1+L6) -> 4.699719 | M14: =AVERAGE(J14:L14)*(1+M6) -> 4.7619577 | N14: =AVERAGE(K14:M14)*(1+N6) -> 5.1128443 | O14: =AVERAGE(L14:N14)*(1+O6) -> 5.2954093 | ... AF14: =AVERAGE(AC14:AE14)*(1+AF6) -> 7.9139693
B15: 9 | C15: Earnings before taxes | D15: =D9+D13+D14 -> 206.25538 | E15: =E9+E13+E14 -> 279.50802 | F15: =F9+F13+F14 -> 257.7637 | G15: =G9+G13+G14 -> 232.37608 | H15: =H9+H13+H14 -> 293.05864 | I15: =I9+I13+I14 -> 346.26446 | J15: =J9+J13+J14 -> 401.00696 | K15: =K9+K13+K14 -> 451.99177 | ... AF15: =AF9+AF13+AF14 -> 1640.8037
B16: 10 | C16: (Income tax) | D16: -49.4 | E16: -55.808 | F16: -26.484 | G16: -56.061 | H16: =(-1*$D$53)*H15 -> -58.611728 | I16: =(-1*$D$53)*I15 -> -69.252891 | J16: =(-1*$D$53)*J15 -> -80.201392 | K16: =(-1*$D$53)*K15 -> -90.398353 | L16: =(-1*$E$53)*L15 -> -102.45712 | M16: =(-1*$E$53)*M15 -> -114.65004 | N16: =(-1*$E$53)*N15 -> -126.42354 | O16: =(-1*$E$53)*O15 -> -138.15347 | P16: =(-1*$E$53)*P15 -> -149.78274 | Q16: =(-1*$E$53)*Q15 -> -160.27469 | R16: =(-1*$E$53)*R15 -> -171.53915 | S16: =(-1*$E$53)*S15 -> -183.51858 | ... V16: =(-1*$E$53)*V15 -> -216.85433 | W16: =(-1*$F$53)*W15 -> -229.25339 | X16: =(-1*$F$53)*X15 -> -240.97742 | Y16: =(-1*$F$53)*Y15 -> -253.33907 | Z16: =(-1*$F$53)*Z15 -> -263.88539 | AA16: =(-1*$F$53)*AA15 -> -274.95837 | AB16: =(-1*$F$53)*AB15 -> -286.48185 | AC16: =(-1*$F$53)*AC15 -> -298.48601 | AD16: =(-1*$F$53)*AD15 -> -308.06801 | ... AF16: =(-1*$F$53)*AF15 -> -328.16075
B17: 11 | C17: Net income | D17: =D15+D16 -> 156.85538 | E17: =E15+E16 -> 223.70002 | F17: =F15+F16 -> 231.2797 | G17: =G15+G16 -> 176.31508 | H17: =H15+H16 -> 234.44691 | I17: =I15+I16 -> 277.01156 | J17: =J15+J16 -> 320.80557 | K17: =K15+K16 -> 361.59341 | ... AF17: =AF15+AF16 -> 1312.643
A19: CASH FLOW STATEMENT | B19: 12 | C19: Operating cash flows before WK | D19: =155.801+30.535+0.935-3.827+1.051+1.064-0.074 -> 185.485 | E19: =212.602+32.07+0.679+5.147+2.473+1.022 -> 253.993 | F19: =89.693+39.847+0.601-0.403+1.229+97.176+2.039 -> 230.182 | G19: =169.885+46.434+0.604+25.561+2.927+0.33+1.895-6.163 -> 241.473 | H19: =H12+H13+H14+H16 -> 282.57891 | I19: =I12+I13+I14+I16 -> 321.08627 | J19: =J12+J13+J14+J16 -> 363.40138 | K19: =K12+K13+K14+K16 -> 405.59571 | L19: =L12+L13+L14+L16 -> 457.67478 | M19: =M12+M13+M14+M16 -> 511.43533 | N19: =N12+N13+N14+N16 -> 567.80494 | O19: =O12+O13+O14+O16 -> 627.34621 | ... AF19: =AF12+AF13+AF14+AF16 -> 1712.3365
B20: 13 | C20: (Stock-based compensation) | D20: 9.009 | E20: 15.474 | F20: 17.799 | G20: 29.8 | H20: =-H11 -> 40.719 | I20: =-I11 -> 43.185003 | J20: =-J11 -> 50.094603 | K20: =-K11 -> 57.107848 | L20: =-L11 -> 64.531868 | M20: =-M11 -> 35.815187 | N20: =-N11 -> 39.396705 | O20: =-O11 -> 42.942409 | ... AF20: =-AF11 -> 148.78759
B21: 14 | C21: (Working Capital Flows) | D21: =16.353+46.052+1.982+89.125+14.943+3.478 -> 171.933 | E21: =-44.681-179.803-10.587+112.773-3.781+3.132 -> -122.947 | F21: =30.448-91.624-2.187-86.242+0.439+2.079 -> -147.087 | G21: =-15.683+33.675-7.933-15.144+18.156+1.598 -> 14.669 | H21: -16.692 | I21: =$D$57*(I7-H7) -> -98.813142 | J21: =$D$57*(J7-I7) -> -103.64401 | K21: =$D$57*(K7-J7) -> -105.19867 | L21: =$E$57*(L7-K7) -> -92.800253 | M21: =$E$57*(M7-L7) -> -88.731318 | N21: =$E$57*(N7-M7) -> -89.537967 | O21: =$E$57*(O7-N7) -> -88.642587 | P21: =$E$57*(P7-O7) -> -85.884818 | Q21: =$E$57*(Q7-P7) -> -81.161153 | R21: =$E$57*(R7-Q7) -> -86.842433 | S21: =$E$57*(S7-R7) -> -92.921404 | ... V21: =$E$57*(V7-U7) -> -79.796388 | W21: =$F$57*(W7-V7) -> -67.028966 | X21: =$F$57*(X7-W7) -> -70.380414 | Y21: =$F$57*(Y7-X7) -> -73.899435 | Z21: =$F$57*(Z7-Y7) -> -62.075525 | AA21: =$F$57*(AA7-Z7) -> -64.558547 | AB21: =$F$57*(AB7-AA7) -> -67.140888 | AC21: =$F$57*(AC7-AB7) -> -69.826524 | AD21: =$F$57*(AD7-AC7) -> -54.464689 | ... AF21: =$F$57*(AF7-AE7) -> -57.781588
B22: 15 | C22: -Total Operating Cash Flow | D22: =D19+D20+D21 -> 366.427 | E22: =E19+E20+E21 -> 146.52 | F22: =F19+F20+F21 -> 100.894 | G22: =G19+G20+G21 -> 285.942 | H22: =H19+H20+H21 -> 306.60591 | I22: =I19+I20+I21 -> 265.45814 | J22: =J19+J20+J21 -> 309.85198 | K22: =K19+K20+K21 -> 357.50489 | ... AF22: =AF19+AF20+AF21 -> 1803.3425
B23: 16 | C23: (CAPEX and Acquisitions) | D23: =Cifras_Originales!E13 -> -15.566 | E23: =Cifras_Originales!D13 -> -56.121 | F23: =Cifras_Originales!C13 -> -45.929 | G23: =Cifras_Originales!B13 -> -50.672 | H23: =-41.832-36.164 -> -77.996 | I23: =-$D$58*I7 -> -86.370006 | J23: =-$D$58*J7 -> -100.18921 | K23: =-$D$58*K7 -> -114.2157 | L23: =-$D$58*L7 -> -129.06374 | M23: =-$E$58*M7 -> -214.89112 | N23: =-$E$58*N7 -> -236.38023 | O23: =-$E$58*O7 -> -257.65445 | P23: =-$E$58*P7 -> -278.26681 | Q23: =-$E$58*Q7 -> -297.74549 | R23: =-$E$58*R7 -> -318.58767 | S23: =-$E$58*S7 -> -340.88881 | T23: =-$E$58*T7 -> -361.34214 | ... V23: =-$E$58*V7 -> -402.1738 | W23: =-$F$58*W7 -> -563.04332 | X23: =-$F$58*X7 -> -591.19548 | Y23: =-$F$58*Y7 -> -620.75525 | Z23: =-$F$58*Z7 -> -645.58547 | AA23: =-$F$58*AA7 -> -671.40888 | AB23: =-$F$58*AB7 -> -698.26524 | AC23: =-$F$58*AC7 -> -726.19585 | AD23: =-$F$58*AD7 -> -747.98172 | ... AF23: =-$F$58*AF7 -> -793.53381
B24: 17 | C24: (Other investing flows) | D24: -7.378 | E24: -9.635 | F24: -10.981 | G24: -22.152 | H24: -53.452 | I24: =(1+I6)*AVERAGE(F24:H24) -> -34.056767 | J24: =(1+J6)*AVERAGE(G24:I24) -> -42.402163 | K24: =(1+K6)*AVERAGE(H24:J24) -> -49.366153 | L24: =(1+L6)*AVERAGE(I24:K24) -> -47.394115 | M24: =(1+M6)*AVERAGE(J24:L24) -> -51.490099 | N24: =(1+N6)*AVERAGE(K24:M24) -> -54.358468 | O24: =(1+O6)*AVERAGE(L24:N24) -> -55.678175 | P24: =(1+P6)*AVERAGE(M24:O24) -> -58.149627 | ... AF24: =(1+AF6)*AVERAGE(AC24:AE24) -> -83.894545
B25: 18 | C25: -Total Investing Flows | D25: =D23+D24 -> -22.944 | E25: =E23+E24 -> -65.756 | F25: =F23+F24 -> -56.91 | G25: =G23+G24 -> -72.824 | H25: 131.448 | I25: =I23+I24 -> -120.42677 | J25: =J23+J24 -> -142.59137 | K25: =K23+K24 -> -163.58185 | L25: =L23+L24 -> -176.45785 | M25: =M23+M24 -> -266.38122 | N25: =N23+N24 -> -290.7387 | O25: =O23+O24 -> -313.33263 | P25: =P23+P24 -> -336.41644 | ... AF25: =AF23+AF24 -> -877.42836
B26: 19 | C26: (Flows related to leases) | D26: -0.185 | E26: -1.108 | F26: -2.063 | G26: -2.13 | H26: 0 | I26: 0 | J26: -300 | K26: 0 | L26: 0 | M26: 0 | N26: 0 | O26: 0 | P26: 0 | Q26: 0 | R26: 0 | S26: 0 | T26: 0 | U26: 0 | V26: 0 | W26: 0 | X26: 0 | Y26: 0 | Z26: 0 | AA26: 0 | AB26: 0 | AC26: 0 | AD26: 0 | AE26: 0 | AF26: 0
B27: 20 | C27: Flows related to debt | D27: -165 | E27: -22.5 | F27: -22.5 | G27: -7.734 | H27: -4.219 | I27: =(I38-H38) -> -4.22 | J27: =(J38-I38) -> 295.78 | K27: =(K38-J38) -> -34.22 | L27: =(L38-K38) -> -115.39 | M27: =(M38-L38) -> -50 | N27: =(N38-M38) -> -90 | O27: =(O38-N38) -> -178.063 | P27: =(P38-O38) -> 0.003 | ... AF27: =(AF38-AE38) -> 0
B28: 21 | C28: (Respurchases)/Issuance of stock | D28: 0 | E28: 0 | F28: -100 | G28: 0 | H28: -200 | I28: -250 | J28: -300 | K28: -200 | L28: -150 | M28: -100 | N28: -150 | O28: -200 | P28: -250 | Q28: -250 | R28: -150 | S28: -100 | T28: -75 | U28: -75 | V28: -50 | W28: -50 | X28: -50 | Y28: -50 | Z28: -50 | AA28: -50 | AB28: -50 | AC28: -50 | AD28: -50 | AE28: -50 | AF28: -50
B29: 22 | C29: (Dividends) | D29: 0 | E29: 0 | F29: 0 | G29: 0 | H29: 0 | I29: 0 | J29: 0 | K29: 0 | L29: 0 | M29: 0 | N29: 0 | O29: 0 | P29: 0 | Q29: 0 | R29: -200 | S29: -200 | T29: -200 | U29: -220 | V29: -220 | W29: -250 | X29: -250 | Y29: -250 | Z29: -250 | AA29: -280 | AB29: -300 | AC29: -320 | AD29: -350 | AE29: -380 | AF29: -400
B30: 23 | C30: Other financing flows | D30: =3.022-1.028+50-50 -> 1.994 | E30: =4.095-3.506-0 -> 0.589 | F30: =3.821-1.861-0 -> 1.96 | G30: =1.573-2.481-2.824 -> -3.732 | H30: =-1.169 -> -1.169 | I30: =(1+I6)*(AVERAGE(E30:F30,H30)) -> 0.5428 | J30: =(1+J6)*AVERAGE(F30,H30:I30) -> 0.515736 | K30: =(1+K6)*AVERAGE(H30:J30) -> -0.04197632 | L30: =(1+L6)*AVERAGE(I30:K30) -> 0.38290415 | M30: =(1+M6)*AVERAGE(J30:L30) -> 0.31696562 | N30: =(1+N6)*AVERAGE(K30:M30) -> 0.2412276 | O30: =(1+O6)*AVERAGE(L30:N30) -> 0.34193204 | P30: =(1+P6)*AVERAGE(M30:O30) -> 0.32404509 | Q30: =(1+Q6)*AVERAGE(N30:P30) -> 0.32356969 | R30: =(1+R6)*AVERAGE(O30:Q30) -> 0.35293836 | ... AF30: =(1+AF6)*AVERAGE(AC30:AE30) -> 0.46766331
B31: 24 | C31: -Total Financing flows | D31: =SUM(D26:D30) -> -163.191 | E31: =SUM(E26:E30) -> -23.019 | F31: =SUM(F26:F30) -> -122.603 | G31: =SUM(G26:G30) -> -13.596 | H31: =SUM(H26:H30) -> -205.388 | I31: =SUM(I26:I30) -> -253.6772 | J31: =SUM(J26:J30) -> -303.70426 | K31: =SUM(K26:K30) -> -234.26198 | ... AF31: =SUM(AF26:AF30) -> -449.53234
A33: SUMMARY | B33: 25 | C33: Cash before shareholder returns | D33: =D22+D25+D26+D27+D30 -> 180.292 | E33: =E22+E25+E26+E27+E30 -> 57.745 | F33: =F22+F25+F26+F27+F30 -> 21.381 | G33: =G22+G25+G26+G27+G30 -> 199.522 | H33: =H22+H25+H26+H27+H30 -> 432.66591 | I33: =I22+I25+I26+I27+I30 -> 141.35416 | J33: =J22+J25+J26+J27+J30 -> 163.55634 | K33: =K22+K25+K26+K27+K30 -> 159.66106 | ... AF33: =AF22+AF25+AF26+AF27+AF30 -> 926.38177
B34: 26 | C34: Returns to shareholders | D34: =-1*(D28+D29) -> 0 | E34: =-1*(E28+E29) -> 0 | F34: =-1*(F28+F29) -> 100 | G34: =-1*(G28+G29) -> 0 | H34: =-1*(H28+H29) -> 200 | I34: =-1*(I28+I29) -> 250 | J34: =-1*(J28+J29) -> 300 | K34: =-1*(K28+K29) -> 200 | ... AF34: =-1*(AF28+AF29) -> 450
B35: 27 | C35: Excess cash acumulation | D35: =D33-D34 -> 180.292 | E35: =E33-E34 -> 57.745 | F35: =F33-F34 -> -78.619 | G35: =G33-G34 -> 199.522 | H35: =H33-H34 -> 232.66591 | I35: =I33-I34 -> -108.64584 | J35: =J33-J34 -> -136.44366 | K35: =K33-K34 -> -40.338938 | ... AF35: =AF33-AF34 -> 476.38177
A37: CASH & DEBT & DISCOUNTING | B37: 28 | C37: Ending cash balance | D37: =Cifras_Originales!E22 -> 253.283 | E37: 312.189 | F37: 234.741 | G37: 438.96 | H37: 358.795 | I37: =H37+I35 -> 250.14916 | J37: =I37+J35+300 -> 413.70551 | K37: =J37+K35 -> 373.36657 | L37: =K37+L35 -> 361.30801 | M37: =L37+M35 -> 403.76295 | N37: =M37+N35 -> 390.92916 | O37: =N37+O35 -> 281.52149 | P37: =O37+P35 -> 345.07822 | Q37: =P37+Q35 -> 454.67089 | R37: =Q37+R35 -> 500.21106 | ... AF37: =AE37+AF35 -> 5058.5975
B38: 29 | C38: Total Debt | D38: =Cifras_en_Millones!F60 -> 178.507 | E38: =Cifras_en_Millones!E60 -> 186.408 | F38: =Cifras_en_Millones!D60 -> 164.077 | G38: =Cifras_en_Millones!C60 -> 176.113 | H38: =G38 -> 176.113 | I38: 171.893 | J38: 467.673 | K38: 433.453 | L38: 318.063 | M38: 268.063 | N38: 178.063 | O38: 0 | P38: 0.003 | Q38: 0.003 | R38: 0 | S38: 0 | T38: 0 | U38: 0 | V38: 0 | W38: 0 | X38: 0 | Y38: 0 | Z38: 0 | AA38: 0 | AB38: 0 | AC38: 0 | AD38: 0 | AE38: 0 | AF38: 0
B39: 30 | C39: Discount factor | G39: =1/((1+$D$48)^G4) -> 0.99853543 | H39: =1/((1+$D$48)^H4) -> 0.9981863 | I39: =1/((1+$D$48)^I3) -> 1 | J39: =1/((1+$D$48)^J3) -> 1 | K39: =1/((1+$D$48)^K3) -> 1 | L39: =1/((1+$D$48)^L3) -> 1 | M39: =1/((1+$E$48)^M4) -> 0.99960787 | N39: =1/((1+$E$48)^N4) -> 0.99960787 | O39: =1/((1+$E$48)^O4) -> 0.99960787 | P39: =1/((1+$E$48)^P4) -> 0.99960787 | Q39: =1/((1+$E$48)^Q4) -> 0.99960787 | R39: =1/((1+$E$48)^R4) -> 0.99960787 | S39: =1/((1+$E$48)^S4) -> 0.99960787 | T39: =1/((1+$E$48)^T4) -> 0.99960787 | ... V39: =1/((1+$E$48)^V4) -> 0.99960787 | W39: =1/((1+$F$48)^W4) -> 0.99941186 | X39: =1/((1+$F$48)^X4) -> 0.99941186 | Y39: =1/((1+$F$48)^Y4) -> 0.99941186 | Z39: =1/((1+$F$48)^Z4) -> 0.99941186 | AA39: =1/((1+$F$48)^AA4) -> 0.99941186 | AB39: =1/((1+$F$48)^AB4) -> 0.99941186 | AC39: =1/((1+$F$48)^AC4) -> 0.99941186 | AD39: =1/((1+$F$48)^AD4) -> 0.99941186 | ... AF39: =1/((1+$F$48)^AF4) -> 0.99941186
F40: =1/((1+$D$49+0.001)^F$4) -> 0.99998885 | G40: =1/((1+$D$48+0.001)^G$4) -> 0.9985189 | H40: =1/((1+$D$48+0.001)^H$4) -> 0.99816584 | I40: =1/((1+$D$48+0.001)^I$3) -> 1 | J40: =1/((1+$D$48+0.001)^J$3) -> 1 | K40: =1/((1+$D$48+0.001)^K$3) -> 1 | L40: =1/((1+$D$48+0.001)^L$3) -> 1 | M40: =1/((1+$E$48+0.001)^M$4) -> 0.99959826 | N40: =1/((1+$E$48+0.001)^N$4) -> 0.99959826 | O40: =1/((1+$E$48+0.001)^O$4) -> 0.99959826 | P40: =1/((1+$E$48+0.001)^P$4) -> 0.99959826 | Q40: =1/((1+$E$48+0.001)^Q$4) -> 0.99959826 | R40: =1/((1+$E$48+0.001)^R$4) -> 0.99959826 | S40: =1/((1+$E$48+0.001)^S$4) -> 0.99959826 | T40: =1/((1+$E$48+0.001)^T$4) -> 0.99959826 | ... V40: =1/((1+$E$48+0.001)^V$4) -> 0.99959826 | W40: =1/((1+$F$48+0.001)^W$4) -> 0.99939745 | X40: =1/((1+$F$48+0.001)^X$4) -> 0.99939745 | Y40: =1/((1+$F$48+0.001)^Y$4) -> 0.99939745 | Z40: =1/((1+$F$48+0.001)^Z$4) -> 0.99939745 | AA40: =1/((1+$F$48+0.001)^AA$4) -> 0.99939745 | AB40: =1/((1+$F$48+0.001)^AB$4) -> 0.99939745 | AC40: =1/((1+$F$48+0.001)^AC$4) -> 0.99939745 | AD40: =1/((1+$F$48+0.001)^AD$4) -> 0.99939745 | AE40: =1/((1+$F$48+0.001)^AE$4) -> 0.99939745
F41: =1/((1+$D$49+0.005)^F$4) -> 0.99994435 | G41: =1/((1+$D$48+0.005)^G$4) -> 0.99845295 | H41: =1/((1+$D$48+0.005)^H$4) -> 0.99808418 | I41: =1/((1+$D$48+0.005)^I$3) -> 1 | J41: =1/((1+$D$48+0.005)^J$3) -> 1 | K41: =1/((1+$D$48+0.005)^K$3) -> 1 | L41: =1/((1+$D$48+0.005)^L$3) -> 1 | M41: =1/((1+$E$48+0.005)^M$4) -> 0.99955993 | N41: =1/((1+$E$48+0.005)^N$4) -> 0.99955993 | O41: =1/((1+$E$48+0.005)^O$4) -> 0.99955993 | P41: =1/((1+$E$48+0.005)^P$4) -> 0.99955993 | Q41: =1/((1+$E$48+0.005)^Q$4) -> 0.99955993 | R41: =1/((1+$E$48+0.005)^R$4) -> 0.99955993 | S41: =1/((1+$E$48+0.005)^S$4) -> 0.99955993 | T41: =1/((1+$E$48+0.005)^T$4) -> 0.99955993 | ... V41: =1/((1+$E$48+0.005)^V$4) -> 0.99955993 | W41: =1/((1+$F$48+0.005)^W$4) -> 0.99933996 | X41: =1/((1+$F$48+0.005)^X$4) -> 0.99933996 | Y41: =1/((1+$F$48+0.005)^Y$4) -> 0.99933996 | Z41: =1/((1+$F$48+0.005)^Z$4) -> 0.99933996 | AA41: =1/((1+$F$48+0.005)^AA$4) -> 0.99933996 | AB41: =1/((1+$F$48+0.005)^AB$4) -> 0.99933996 | AC41: =1/((1+$F$48+0.005)^AC$4) -> 0.99933996 | AD41: =1/((1+$F$48+0.005)^AD$4) -> 0.99933996 | AE41: =1/((1+$F$48+0.005)^AE$4) -> 0.99933996
C43: EPS | H43: =1000000*H17/OP!C8 -> 2.7638747 | I43: =1000000*I17/OP!$C8 -> 3.2656657 | J43: =1000000*J17/OP!$C8 -> 3.7819495
C44: Consenso EPS
C45: E$/UN | H45: =$D$65/H17 -> 119.55708 | I45: =$D$65/I17 -> 101.18635
A47: Discount rate | D47: Total | E47: Risk free rate | F47: Equity premium | G47: Firm premium
C48: Discount Rate | D48: =SUM(E48:G48) -> 0.085 | E48: 0.04 | F48: 0.04 | G48: 0.005
D50: Short Term | E50: Medium term | F50: Long Term | G50: Reference (line)
A51: Modelling factors | C51: Depreciation factor | D51: 0.6 | E51: 0.6 | F51: 0.6 | G51: % Capex/Adq (l16) | H51: =SUM(H23:AG23)/SUM(H10:AG10) -> 2.3844485
C52: Stock-based comp | D52: 0.02 | E52: 0.01 | F52: 0.015 | G52: % revenue (l2) | H52: =-SUM(E11:G11)/SUM(E7:G7) -> 0.013520692
C53: Tax Rate | D53: 0.2 | E53: 0.2 | F53: 0.2 | G53: % (line 9)
C54: Interest Rate on debt | D54: 0.02 | E54: 0.02 | F54: 0.01 | G54: % debt (l29)
C55: Interest Rate on cash | D55: 0 | E55: 0.005 | F55: 0.01 | G55: % of cash (l28)
C56: Net SBC | D56: 0.02 | E56: 0.01 | F56: 0.015 | G56: % revenue (l2)
C57: Working capital flows | D57: -0.3 | E57: -0.25 | F57: -0.2 | G57: % of change revenues (l2)
C58: Capex / Adq | D58: 0.04 | E58: 0.06 | F58: 0.08 | G58: % revenue (l2)
C59: Dividends | D59: 0 | E59: 0.6 | F59: 0.8 | G59: Growth rate
C60: Other financing flows | D60: -0.01 | E60: 0.01 | F60: 0.01 | G60: % of debt (l29)
A62: Valuation | D62: $ millions | E62: % | F62: Notes | AE62: =((AE37-AE38)*AE39) -> 4579.5207
C63: Value of flows | D63: =SUMPRODUCT(G34:AE34,G39:AE39)+((AE37-AE38)*AE39) -> 11196.39 | E63: =D63/D65 -> 0.3994461 | F63: Present value of flows (l27), plus cash minus debt | AE63: =AE55+AE62 -> 4579.5207
C64: Value of perpetuity | D64: =(AF33/(D48-AF6))*AF39 -> 16833.399 | E64: =D64/D65 -> 0.6005539 | F64: Present value of perpetuity (column AF flow, dividend by growth minus discount rate)
C65: Total Value | D65: =D63+D64 -> 28029.788 | F65: Final market value of firm's equity, compare to its mkt cap
C66: Total value vs share value | D66: =D67/D68-1 -> 7.9019609 | F66: Gives degree of undervaluation (if positive, meaning it's worth more than what the market thinks) or overvaluation (negative, worth less than what the market thinks)
C67: Estimated NPV per share | D67: =1000000*D65/OP!C8 -> 330.44079 | F67: If we divide total value by # of shares, we get the estimated share value
C68: Actual share price | D68: =OP!C7 -> 37.12 | F68: Actual share price

Sheet Cifras_en_Millones
A1: =Cifras_Originales!G3 -> YETI HOLDINGS, INC. ((XNYS:YETI))
A2: =Cifras_Originales!C2 -> Cifras en Millones de USD
A4: Resultados | B4: 2024 | C4: =Cifras_Originales!B5 -> 2023 | D4: =Cifras_Originales!C5 -> 2022 | E4: =Cifras_Originales!D5 -> 2021 | F4: =Cifras_Originales!E5 -> 2020 | G4: =Cifras_Originales!F5 -> 2019 | H4: =Cifras_Originales!G5 -> 2018 | I4: =Cifras_Originales!H5 -> 2017 | J4: =Cifras_Originales!I5 -> 2016 | ... M4: =Cifras_Originales!L5 -> 2013
A5: Ventas Netas | C5: =Cifras_Originales!B6 -> 1658.713 | D5: =Cifras_Originales!C6 -> 1595.222 | E5: =Cifras_Originales!D6 -> 1410.989 | F5: =Cifras_Originales!E6 -> 1091.721 | G5: =Cifras_Originales!F6 -> 913.734 | H5: =Cifras_Originales!G6 -> 778.833 | I5: =Cifras_Originales!H6 -> 639.239 | J5: =Cifras_Originales!I6 -> 818.914 | ... M5: =Cifras_Originales!L6 -> 89.9
A6: Crecimiento vs. Año pasado | B6: =B5/C5-1 -> -1 | C6: =C5/D5-1 -> 0.03980073 | D6: =D5/E5-1 -> 0.13057012 | E6: =E5/F5-1 -> 0.29244468 | F6: =F5/G5-1 -> 0.19479083 | G6: =G5/H5-1 -> 0.17320915 | H6: =H5/I5-1 -> 0.21837529 | I6: =I5/J5-1 -> -0.21940643 | ... L6: =L5/M5-1 -> 0.6429366
A7: Utilidad Bruta | C7: =Cifras_Originales!B7 -> 943.186 | D7: =Cifras_Originales!C7 -> 763.401 | E7: =Cifras_Originales!D7 -> 816.113 | F7: =Cifras_Originales!E7 -> 628.803 | G7: =Cifras_Originales!F7 -> 475.314 | H7: =Cifras_Originales!G7 -> 383.128 | I7: =Cifras_Originales!H7 -> 294.601 | J7: =Cifras_Originales!I7 -> 413.961 | ... M7: =Cifras_Originales!L7 -> 44.4
A8: porcentaje sobre ventas | B8: =B7/B5 -> #DIV/0! | C8: =C7/C5 -> 0.56862519 | D8: =D7/D5 -> 0.47855471 | E8: =E7/E5 -> 0.57839785 | F8: =F7/F5 -> 0.57597408 | G8: =G7/G5 -> 0.52018859 | H8: =H7/H5 -> 0.49192574 | I8: =I7/I5 -> 0.46086206 | ... M8: =M7/M5 -> 0.49388209
A9: Gastos de Operación | B9: =B5-B11 -> 0 | C9: =C5-C11 -> 1433.255 | D9: =D5-D11 -> 1468.861 | E9: =E5-E11 -> 1136.051 | F9: =F5-F11 -> 877.488 | G9: =G5-G11 -> 823.963 | H9: =H5-H11 -> 676.677 | I9: =I5-I11 -> 575.272 | ... M9: =M5-M11 -> 74.7
A10: porcentaje sobre ventas | B10: =B9/B5 -> #DIV/0! | C10: =C9/C5 -> 0.86407655 | D10: =D9/D5 -> 0.92078783 | E10: =E9/E5 -> 0.80514519 | F10: =F9/F5 -> 0.8037658 | G10: =G9/G5 -> 0.90175368 | H10: =H9/H5 -> 0.86883453 | I10: =I9/I5 -> 0.89993258 | ... M10: =M9/M5 -> 0.83092325
A11: Utilidad de Operación | C11: =Cifras_Originales!B8 -> 225.458 | D11: =Cifras_Originales!C8 -> 126.361 | E11: =Cifras_Originales!D8 -> 274.938 | F11: =Cifras_Originales!E8 -> 214.233 | G11: =Cifras_Originales!F8 -> 89.771 | H11: =Cifras_Originales!G8 -> 102.156 | I11: =Cifras_Originales!H8 -> 63.967 | J11: =Cifras_Originales!I8 -> 88.207 | ... M11: =Cifras_Originales!L8 -> 15.2
A12: porcentaje sobre ventas | B12: =B11/B5 -> #DIV/0! | C12: =C11/C5 -> 0.13592345 | D12: =D11/D5 -> 0.079212172 | E12: =E11/E5 -> 0.19485481 | F12: =F11/F5 -> 0.1962342 | G12: =G11/G5 -> 0.098246317 | H12: =H11/H5 -> 0.13116547 | I12: =I11/I5 -> 0.10006742 | ... M12: =M11/M5 -> 0.16907675
A13: Crecimiento vs año anterior | B13: =B11/C11-1 -> -1 | C13: =C11/D11-1 -> 0.78423723 | D13: =D11/E11-1 -> -0.54040184 | E13: =E11/F11-1 -> 0.28335971 | F13: =F11/G11-1 -> 1.3864388 | G13: =G11/H11-1 -> -0.12123615 | H13: =H11/I11-1 -> 0.59701096 | I13: =I11/J11-1 -> -0.27480812 | ... L13: =L11/M11-1 -> 0.69078947
A14: CIF (Productos Financieros) | C14: =Cifras_Originales!B9 -> -0.942 | D14: =Cifras_Originales!C9 -> -4.466 | E14: =Cifras_Originales!D9 -> -3.339 | F14: =Cifras_Originales!E9 -> -9.155 | G14: =Cifras_Originales!F9 -> -21.779 | H14: =Cifras_Originales!G9 -> -3.128 | I14: =Cifras_Originales!H9 -> -32.607 | J14: =Cifras_Originales!I9 -> 21.7 | ... M14: =Cifras_Originales!L9 -> 3.9
A15: Otros Gastos (Productos) | C15: =Cifras_Originales!B10 -> 1.43 | D15: =Cifras_Originales!C10 -> 5.718 | E15: =Cifras_Originales!D10 -> 3.189 | F15: =Cifras_Originales!E10 -> 0.123 | G15: =Cifras_Originales!F10 -> -0.734 | H15: =Cifras_Originales!G10 -> -1.261 | I15: =Cifras_Originales!H10 -> 0.699 | J15: =Cifras_Originales!I10 -> -1.242 | ... M15: =Cifras_Originales!L10 -> 0.2
A16: Utilidad antes de Impuestos y partidas extra. | B16: =B11-B14-B15 -> 0 | C16: =C11-C14-C15 -> 224.97 | D16: =D11-D14-D15 -> 125.109 | E16: =E11-E14-E15 -> 275.088 | F16: =F11-F14-F15 -> 223.265 | G16: =G11-G14-G15 -> 112.284 | H16: =H11-H14-H15 -> 106.545 | I16: =I11-I14-I15 -> 95.875 | ... M16: =M11-M14-M15 -> 11.1
A17: Depreciación y amortización del ejercicio | C17: =Cifras_Originales!B11 -> -46.434 | D17: =Cifras_Originales!C11 -> -39.847 | E17: =Cifras_Originales!D11 -> -32.07 | F17: =Cifras_Originales!E11 -> -30.535 | G17: =Cifras_Originales!F11 -> -28.959 | H17: =Cifras_Originales!G11 -> -24.777 | I17: =Cifras_Originales!H11 -> -20.769 | J17: =Cifras_Originales!I11 -> -11.675 | ... M17: =Cifras_Originales!L11 -> -5.7
A18: Capital de Trabajo | C18: =Cifras_Originales!B12 -> 31.698 | D18: =Cifras_Originales!C12 -> -28.037 | E18: =Cifras_Originales!D12 -> 290.564 | F18: =Cifras_Originales!E12 -> -23.062 | G18: =Cifras_Originales!F12 -> 78.723 | H18: =Cifras_Originales!G12 -> -9.104 | I18: =Cifras_Originales!H12 -> -20.127 | J18: =Cifras_Originales!I12 -> 125.519 | ... M18: =Cifras_Originales!L12 -> N/A
A19: EBITDA (flujo operativo) | B19: =B11-B15+B17 -> 0 | C19: =C11-C15+C17 -> 177.594 | D19: =D11-D15+D17 -> 80.796 | E19: =E11-E15+E17 -> 239.679 | F19: =F11-F15+F17 -> 183.575 | G19: =G11-G15+G17 -> 61.546 | H19: =H11-H15+H17 -> 78.64 | I19: =I11-I15+I17 -> 42.499 | ... M19: =M11-M15+M17 -> 9.3
A20: porcentaje sobre ventas | B20: =B19/B5 -> #DIV/0! | C20: =C19/C5 -> 0.10706735 | D20: =D19/D5 -> 0.05064875 | E20: =E19/E5 -> 0.16986596 | F20: =F19/F5 -> 0.16815194 | G20: =G19/G5 -> 0.067356583 | H20: =H19/H5 -> 0.10097158 | I20: =I19/I5 -> 0.066483741 | ... M20: =M19/M5 -> 0.10344828
A21: I.S.R Y P.T.U. | C21: =Cifras_Originales!B15 -> 55.085 | D21: =Cifras_Originales!C15 -> 35.416 | E21: =Cifras_Originales!D15 -> 62.486 | F21: =Cifras_Originales!E15 -> 67.464 | G21: =Cifras_Originales!F15 -> 61.85 | H21: =Cifras_Originales!G15 -> 48.782 | I21: =Cifras_Originales!H15 -> 80.474 | J21: =Cifras_Originales!I15 -> 19.772 | ... M21: =Cifras_Originales!L15 -> 3.8
A22: % Tax | B22: =+B21/B16 -> #DIV/0! | C22: =+C21/C16 -> 0.24485487 | D22: =+D21/D16 -> 0.28308115 | E22: =+E21/E16 -> 0.22714913 | F22: =+F21/F16 -> 0.30217007 | G22: =+G21/G16 -> 0.55083538 | H22: =+H21/H16 -> 0.45785349 | I22: =+I21/I16 -> 0.83936375 | ... M22: =+M21/M16 -> 0.34234234
A23: Utilidad Neta | C23: =Cifras_Originales!B16 -> 169.885 | D23: =Cifras_Originales!C16 -> 89.693 | E23: =Cifras_Originales!D16 -> 212.602 | F23: =Cifras_Originales!E16 -> 155.801 | G23: =Cifras_Originales!F16 -> 50.434 | H23: =Cifras_Originales!G16 -> 57.763 | I23: =Cifras_Originales!H16 -> 15.401 | J23: =Cifras_Originales!I16 -> 47.977 | ... M23: =Cifras_Originales!L16 -> 7.3
A24: porcentaje sobre ventas | B24: =B23/B5 -> #DIV/0! | C24: =C23/C5 -> 0.10241977 | D24: =D23/D5 -> 0.05622603 | E24: =E23/E5 -> 0.15067587 | F24: =F23/F5 -> 0.14271137 | G24: =G23/G5 -> 0.055195495 | H24: =H23/H5 -> 0.074166092 | I24: =I23/I5 -> 0.02409271 | ... M24: =M23/M5 -> 0.081201335
A25: Crecimiento vs año anterior | B25: =B23/C23-1 -> -1 | C25: =C23/D23-1 -> 0.894072 | D25: =D23/E23-1 -> -0.5781178 | E25: =E23/F23-1 -> 0.36457404 | F25: =F23/G23-1 -> 2.0892057 | G25: =G23/H23-1 -> -0.12688053 | H25: =H23/I23-1 -> 2.7506006 | I25: =I23/J23-1 -> -0.67899202 | ... L25: =L23/M23-1 -> 0.94520548
A26: Efectivo Generado | B26: =B40-C40 -> -438.96 | C26: =C40-D40 -> 204.219 | D26: =D40-E40 -> -77.448 | E26: =E40-F40 -> 58.906 | F26: =F40-G40 -> 180.768 | G26: =G40-H40 -> -7.536 | H26: =H40-I40 -> 26.401 | I26: =I40-J40 -> 32.359 | ... M26: =M40-N40 -> #VALUE!
A27: Dividendos | C27: =Cifras_Originales!B17 -> 0 | D27: =Cifras_Originales!C17 -> 0 | E27: =Cifras_Originales!D17 -> 0 | F27: =Cifras_Originales!E17 -> 0 | G27: =Cifras_Originales!F17 -> 0 | H27: =Cifras_Originales!G17 -> 0 | I27: =Cifras_Originales!H17 -> 0 | J27: =Cifras_Originales!I17 -> 0 | ... M27: =Cifras_Originales!L17 -> N/A
B28: =B27/C27-1 -> #DIV/0! | C28: =C27/D27-1 -> #DIV/0! | D28: =D27/E27-1 -> #DIV/0! | E28: =E27/F27-1 -> #DIV/0! | F28: =F27/G27-1 -> #DIV/0! | G28: =G27/H27-1 -> #DIV/0! | H28: =H27/I27-1 -> #DIV/0! | I28: =I27/J27-1 -> #DIV/0! | ... L28: =L27/M27-1 -> #VALUE!
A29: Recompra de Acciones | C29: =Cifras_Originales!B18 -> 0 | D29: =Cifras_Originales!C18 -> 0 | E29: =Cifras_Originales!D18 -> 0 | F29: =Cifras_Originales!E18 -> 0 | G29: =Cifras_Originales!F18 -> 0 | H29: =Cifras_Originales!G18 -> 0 | I29: =Cifras_Originales!H18 -> 0 | J29: =Cifras_Originales!I18 -> 0 | ... M29: =Cifras_Originales!L18 -> N/A
A30: FNP | B30: =SUM(B26:B29) -> #DIV/0! | C30: =SUM(C26:C29) -> #DIV/0! | D30: =SUM(D26:D29) -> #DIV/0! | E30: =SUM(E26:E29) -> #DIV/0! | F30: =SUM(F26:F29) -> #DIV/0! | G30: =SUM(G26:G29) -> #DIV/0! | H30: =SUM(H26:H29) -> #DIV/0! | I30: =SUM(I26:I29) -> #DIV/0! | ... M30: =SUM(M26:M29) -> #VALUE!
A31: FNP (ajustado por deuda) | B31: =B30-(B60-C60) -> #DIV/0! | C31: =C30-(C60-D60) -> #DIV/0! | D31: =D30-(D60-E60) -> #DIV/0! | E31: =E30-(E60-F60) -> #DIV/0! | F31: =F30-(F60-G60) -> #DIV/0! | G31: =G30-(G60-H60) -> #DIV/0! | H31: =H30-(H60-I60) -> #DIV/0! | I31: =I30-(I60-J60) -> #DIV/0! | ... M31: =M30-(M60-N60) -> #VALUE!
A32: FNP (ajustado por inversiones) | B32: =B31+B34 -> #DIV/0! | C32: =C31+C34 -> #DIV/0! | D32: =D31+D34 -> #DIV/0! | E32: =E31+E34 -> #DIV/0! | F32: =F31+F34 -> #DIV/0! | G32: =G31+G34 -> #DIV/0! | H32: =H31+H34 -> #DIV/0! | I32: =I31+I34 -> #DIV/0! | ... M32: =M31+M34 -> #VALUE!
A33: Capex | C33: =Cifras_Originales!B13 -> -50.672 | D33: =Cifras_Originales!C13 -> -45.929 | E33: =Cifras_Originales!D13 -> -56.121 | F33: =Cifras_Originales!E13 -> -15.566 | G33: =Cifras_Originales!F13 -> -32.077 | H33: =Cifras_Originales!G13 -> -20.86 | I33: =Cifras_Originales!H13 -> -42.197 | J33: =Cifras_Originales!I13 -> -35.588 | ... M33: =Cifras_Originales!L13 -> -4.7
A34: Inversiones | C34: =Cifras_Originales!B14 -> 0 | D34: =Cifras_Originales!C14 -> 0 | E34: =Cifras_Originales!D14 -> 0 | F34: =Cifras_Originales!E14 -> 0 | G34: =Cifras_Originales!F14 -> 0 | H34: =Cifras_Originales!G14 -> 0 | I34: =Cifras_Originales!H14 -> 0 | J34: =Cifras_Originales!I14 -> 0 | ... M34: =Cifras_Originales!L14 -> 0
A35: Capex + Inversiones | B35: =+B34+B33 -> 0 | C35: =+C34+C33 -> -50.672 | D35: =+D34+D33 -> -45.929 | E35: =+E34+E33 -> -56.121 | F35: =+F34+F33 -> -15.566 | G35: =+G34+G33 -> -32.077 | H35: =+H34+H33 -> -20.86 | I35: =+I34+I33 -> -42.197 | ... M35: =+M34+M33 -> -4.7
B36: =+B35/B5 -> #DIV/0! | C36: =+C35/C5 -> -0.030548986 | D36: =+D35/D5 -> -0.028791604 | E36: =+E35/E5 -> -0.039774229 | F36: =+F35/F5 -> -0.014258222 | G36: =+G35/G5 -> -0.035105403 | H36: =+H35/H5 -> -0.026783662 | I36: =+I35/I5 -> -0.066011304 | ... M36: =+M35/M5 -> -0.052280311
A37: Dividendos + Recompra de Acciones | B37: =SUM(B27:B29) -> #DIV/0! | C37: =SUM(C27:C29) -> #DIV/0! | D37: =SUM(D27:D29) -> #DIV/0! | E37: =SUM(E27:E29) -> #DIV/0! | F37: =SUM(F27:F29) -> #DIV/0! | G37: =SUM(G27:G29) -> #DIV/0! | H37: =SUM(H27:H29) -> #DIV/0! | I37: =SUM(I27:I29) -> #DIV/0! | ... M37: =SUM(M27:M29) -> 0
A39: Activo
A40: Caja | C40: =Cifras_Originales!B22 -> 438.96 | D40: =Cifras_Originales!C22 -> 234.741 | E40: =Cifras_Originales!D22 -> 312.189 | F40: =Cifras_Originales!E22 -> 253.283 | G40: =Cifras_Originales!F22 -> 72.515 | H40: =Cifras_Originales!G22 -> 80.051 | I40: =Cifras_Originales!H22 -> 53.65 | J40: =Cifras_Originales!I22 -> 21.291 | ... M40: =Cifras_Originales!L22 -> N/A
A41: Cuentas y documentos por cobrar | C41: =Cifras_Originales!B23 -> 95.774 | D41: =Cifras_Originales!C23 -> 79.446 | E41: =Cifras_Originales!D23 -> 109.53 | F41: =Cifras_Originales!E23 -> 65.417 | G41: =Cifras_Originales!F23 -> 82.688 | H41: =Cifras_Originales!G23 -> 59.328 | I41: =Cifras_Originales!H23 -> 67.152 | J41: =Cifras_Originales!I23 -> 37.2 | ... M41: =Cifras_Originales!L23 -> N/A
A42: Inventarios | C42: =Cifras_Originales!B24 -> 337.208 | D42: =Cifras_Originales!C24 -> 371.412 | E42: =Cifras_Originales!D24 -> 318.864 | F42: =Cifras_Originales!E24 -> 140.111 | G42: =Cifras_Originales!F24 -> 185.7 | H42: =Cifras_Originales!G24 -> 145.423 | I42: =Cifras_Originales!H24 -> 175.098 | J42: =Cifras_Originales!I24 -> 246.119 | ... M42: =Cifras_Originales!L24 -> N/A
A43: Activos Fijos (Net Plant) | C43: =Cifras_Originales!B25 -> 130.714 | D43: =Cifras_Originales!C25 -> 124.587 | E43: =Cifras_Originales!D25 -> 119.044 | F43: =Cifras_Originales!E25 -> 78.075 | G43: =Cifras_Originales!F25 -> 82.61 | H43: =Cifras_Originales!G25 -> 74.097 | I43: =Cifras_Originales!H25 -> 73.783 | J43: =Cifras_Originales!I25 -> 47.1 | ... M43: =Cifras_Originales!L25 -> N/A
A44: Otros Activos | B44: =B45-SUM(B40:B43) -> 0 | C44: =Cifras_Originales!B26 -> 294.536 | D44: =Cifras_Originales!C26 -> 266.579 | E44: =Cifras_Originales!D26 -> 236.737 | F44: =Cifras_Originales!E26 -> 200.181 | G44: =Cifras_Originales!F26 -> 206.026 | H44: =Cifras_Originales!G26 -> 155.314 | I44: =Cifras_Originales!H26 -> 146.744 | J44: =Cifras_Originales!I26 -> 184.397 | ... M44: =Cifras_Originales!L26 -> #VALUE!
A45: Total Activo | C45: =Cifras_Originales!B27 -> 1297.192 | D45: =Cifras_Originales!C27 -> 1076.765 | E45: =Cifras_Originales!D27 -> 1096.364 | F45: =Cifras_Originales!E27 -> 737.067 | G45: =Cifras_Originales!F27 -> 629.539 | H45: =Cifras_Originales!G27 -> 514.213 | I45: =Cifras_Originales!H27 -> 516.427 | J45: =Cifras_Originales!I27 -> 536.107 | ... M45: =Cifras_Originales!L27 -> N/A
A48: Pasivo
A49: Pasivo Corto Plazo | C49: =Cifras_Originales!B31 -> 398.353 | D49: =Cifras_Originales!C31 -> 409.04 | E49: =Cifras_Originales!D31 -> 403.713 | F49: =Cifras_Originales!E31 -> 287.759 | G49: =Cifras_Originales!F31 -> 170.312 | H49: =Cifras_Originales!G31 -> 187.338 | I49: =Cifras_Originales!H31 -> 151.898 | J49: =Cifras_Originales!I31 -> 137.9 | ... M49: =Cifras_Originales!L31 -> N/A
A50: Deuda a corto plazo | C50: =Cifras_Originales!B32 -> 6.579 | D50: =Cifras_Originales!C32 -> 24.611 | E50: =Cifras_Originales!D32 -> 24.56 | F50: =Cifras_Originales!E32 -> 22.697 | G50: =Cifras_Originales!F32 -> 15.185 | H50: =Cifras_Originales!G32 -> 43.638 | I50: =Cifras_Originales!H32 -> 47.05 | J50: =Cifras_Originales!I32 -> 45.6 | ... M50: =Cifras_Originales!L32 -> N/A
A51: Short-Term Leases | C51: =Cifras_Originales!B33 -> 14.726 | D51: =Cifras_Originales!C33 -> 12.076 | E51: =Cifras_Originales!D33 -> 10.167 | F51: =Cifras_Originales!E33 -> 8.247 | G51: =Cifras_Originales!F33 -> 7.768 | H51: =Cifras_Originales!G33 -> 0 | I51: =Cifras_Originales!H33 -> 0 | J51: =Cifras_Originales!I33 -> N/A | ... M51: =Cifras_Originales!L33 -> N/A
A52: Otros Pasivos a Corto Plazo | C52: =Cifras_Originales!B34 -> 377.048 | D52: =Cifras_Originales!C34 -> 372.353 | E52: =Cifras_Originales!D34 -> 368.986 | F52: =Cifras_Originales!E34 -> 256.815 | G52: =Cifras_Originales!F34 -> 147.359 | H52: =Cifras_Originales!G34 -> 143.7 | I52: =Cifras_Originales!H34 -> 104.848 | J52: =Cifras_Originales!I34 -> #VALUE! | ... M52: =Cifras_Originales!L34 -> #VALUE!
A53: Pasivo Largo Plazo | C53: =Cifras_Originales!B35 -> 175.229 | D53: =Cifras_Originales!C35 -> 141.248 | E53: =Cifras_Originales!D35 -> 174.828 | F53: =Cifras_Originales!E35 -> 160.89 | G53: =Cifras_Originales!F35 -> 337.222 | H53: =Cifras_Originales!G35 -> 297.904 | I53: =Cifras_Originales!H35 -> 440.76 | J53: =Cifras_Originales!I35 -> 493.3 | ... M53: =Cifras_Originales!L35 -> N/A
A54: Deuda a largo plazo | C54: =Cifras_Originales!B36 -> 78.645 | D54: =Cifras_Originales!C36 -> 71.741 | E54: =Cifras_Originales!D36 -> 95.741 | F54: =Cifras_Originales!E36 -> 111.017 | G54: =Cifras_Originales!F36 -> 281.715 | H54: =Cifras_Originales!G36 -> 284.376 | I54: =Cifras_Originales!H36 -> 428.632 | J54: =Cifras_Originales!I36 -> 491.7 | ... M54: =Cifras_Originales!L36 -> N/A
A55: Long-Term Leases | C55: =Cifras_Originales!B37 -> 76.163 | D55: =Cifras_Originales!C37 -> 55.649 | E55: =Cifras_Originales!D37 -> 55.94 | F55: =Cifras_Originales!E37 -> 36.546 | G55: =Cifras_Originales!F37 -> 42.2 | H55: =Cifras_Originales!G37 -> 0 | I55: =Cifras_Originales!H37 -> 0 | J55: =Cifras_Originales!I37 -> N/A | ... M55: =Cifras_Originales!L37 -> N/A
A56: Otros Pasivos a Largo Plazo | B56: =B53-SUM(B54:B55) -> 0 | C56: =Cifras_Originales!B38 -> 20.421 | D56: =Cifras_Originales!C38 -> 13.858 | E56: =Cifras_Originales!D38 -> 23.147 | F56: =Cifras_Originales!E38 -> 13.327 | G56: =Cifras_Originales!F38 -> 13.307 | H56: =Cifras_Originales!G38 -> 13.528 | I56: =Cifras_Originales!H38 -> 12.128 | J56: =Cifras_Originales!I38 -> #VALUE! | ... M56: =Cifras_Originales!L38 -> #VALUE!
A57: Total pasivos | C57: =Cifras_Originales!B39 -> 573.582 | D57: =Cifras_Originales!C39 -> 550.288 | E57: =Cifras_Originales!D39 -> 578.541 | F57: =Cifras_Originales!E39 -> 448.649 | G57: =Cifras_Originales!F39 -> 507.534 | H57: =Cifras_Originales!G39 -> 485.242 | I57: =Cifras_Originales!H39 -> 592.658 | J57: =Cifras_Originales!I39 -> 631.2 | ... M57: =Cifras_Originales!L39 -> #VALUE!
A59: Deuda Neta | B59: =B60-B40 -> 0 | C59: =C60-C40 -> -262.847 | D59: =D60-D40 -> -70.664 | E59: =E60-E40 -> -125.781 | F59: =F60-F40 -> -74.776 | G59: =G60-G40 -> 274.353 | H59: =H60-H40 -> 247.963 | I59: =I60-I40 -> 422.032 | ... M59: =M60-M40 -> #VALUE!
A60: Deuda | B60: =B50+B51+B54+B55 -> 0 | C60: =C50+C51+C54+C55 -> 176.113 | D60: =D50+D51+D54+D55 -> 164.077 | E60: =E50+E51+E54+E55 -> 186.408 | F60: =F50+F51+F54+F55 -> 178.507 | G60: =G50+G51+G54+G55 -> 346.868 | H60: =H50+H51+H54+H55 -> 328.014 | I60: =I50+I51+I54+I55 -> 475.682 | ... M60: =M50+M51+M54+M55 -> #VALUE!
B61: =B60/B45 -> #DIV/0! | C61: =C60/C45 -> 0.13576479 | D61: =D60/D45 -> 0.15237958 | E61: =E60/E45 -> 0.17002382 | F61: =F60/F45 -> 0.24218558 | G61: =G60/G45 -> 0.55098731 | H61: =H60/H45 -> 0.63789519 | I61: =I60/I45 -> 0.92110211 | ... M61: =M60/M45 -> #VALUE!
A63: Interés Minoritario | B63: 0 | C63: =Cifras_Originales!B42 -> 0 | D63: =Cifras_Originales!C42 -> 0 | E63: =Cifras_Originales!D42 -> 0 | F63: =Cifras_Originales!E42 -> 0 | G63: =Cifras_Originales!F42 -> 0 | H63: =Cifras_Originales!G42 -> 0 | I63: =Cifras_Originales!H42 -> 0 | J63: =Cifras_Originales!I42 -> 2.2 | ... M63: =Cifras_Originales!L42 -> N/A
A66: Capital Contable | B66: =B45-B57-B63 -> 0 | C66: =C45-C57-C63 -> 723.61 | D66: =D45-D57-D63 -> 526.477 | E66: =E45-E57-E63 -> 517.823 | F66: =F45-F57-F63 -> 288.418 | G66: =G45-G57-G63 -> 122.005 | H66: =H45-H57-H63 -> 28.971 | I66: =I45-I57-I63 -> -76.231 | ... M66: =M45-M57-M63 -> #VALUE!
A69: OTROS DATOS AL FIN DE AÑO
A70: Numero deEmpleados | C70: =Cifras_Originales!B47 -> 0 | D70: =Cifras_Originales!C47 -> 0 | E70: =Cifras_Originales!D47 -> 0 | F70: =Cifras_Originales!E47 -> 0 | G70: =Cifras_Originales!F47 -> 0 | H70: =Cifras_Originales!G47 -> 0 | I70: =Cifras_Originales!H47 -> 0 | J70: =Cifras_Originales!I47 -> 0 | ... M70: =Cifras_Originales!L47 -> 0
A71: Acciones en circulación (millones) | C71: =+Cifras_Originales!B48 -> 0 | D71: =+Cifras_Originales!C48 -> 0 | E71: =+Cifras_Originales!D48 -> 0 | F71: =+Cifras_Originales!E48 -> 0 | G71: =+Cifras_Originales!F48 -> 0 | H71: =+Cifras_Originales!G48 -> 0 | I71: =+Cifras_Originales!H48 -> 0 | J71: =+Cifras_Originales!I48 -> 0 | ... M71: =+Cifras_Originales!L48 -> 0
A72: Float | C72: =Cifras_Originales!B49 -> 0 | D72: =Cifras_Originales!C49 -> 0 | E72: =Cifras_Originales!D49 -> 0 | F72: =Cifras_Originales!E49 -> 0 | G72: =Cifras_Originales!F49 -> 0 | H72: =Cifras_Originales!G49 -> 0 | I72: =Cifras_Originales!H49 -> 0 | J72: =Cifras_Originales!I49 -> 0 | ... M72: =Cifras_Originales!L49 -> 0
A73: Insiders Own | C73: =Cifras_Originales!B50 -> 0 | D73: =Cifras_Originales!C50 -> 0 | E73: =Cifras_Originales!D50 -> 0 | F73: =Cifras_Originales!E50 -> 0 | G73: =Cifras_Originales!F50 -> 0 | H73: =Cifras_Originales!G50 -> 0 | I73: =Cifras_Originales!H50 -> 0 | J73: =Cifras_Originales!I50 -> 0 | ... M73: =Cifras_Originales!L50 -> 0
A74: S&P | C74: =+Cifras_Originales!B51 -> 0 | D74: =+Cifras_Originales!C51 -> 0 | E74: =+Cifras_Originales!D51 -> 0 | F74: =+Cifras_Originales!E51 -> 0 | G74: =+Cifras_Originales!F51 -> 0 | H74: =+Cifras_Originales!G51 -> 0 | I74: =+Cifras_Originales!H51 -> 0 | J74: =+Cifras_Originales!I51 -> 0 | ... M74: =+Cifras_Originales!L51 -> 0
A75: =Cifras_Originales!A52 -> Vol. Diario en Millones USD | C75: =Cifras_Originales!B52 -> 0 | D75: =Cifras_Originales!C52 -> 0 | E75: =Cifras_Originales!D52 -> 0 | F75: =Cifras_Originales!E52 -> 0 | G75: =Cifras_Originales!F52 -> 0 | H75: =Cifras_Originales!G52 -> 0 | I75: =Cifras_Originales!H52 -> 0 | J75: =Cifras_Originales!I52 -> 0 | ... M75: =Cifras_Originales!L52 -> 0 | IH75: =Cifras_Originales!GM52 -> 0
B77: =+Cifras_Originales!B53 -> 2021 | C77: =+Cifras_Originales!C53 -> 2022 | D77: =+Cifras_Originales!D53 -> 2023
A78: =Cifras_Originales!A54 -> Posicion en Corto (%) | B78: =Cifras_Originales!B54 -> 0
A79: =Cifras_Originales!A55 -> EPS | B79: =Cifras_Originales!B55 -> 0 | C79: =Cifras_Originales!C55 -> 0 | D79: =Cifras_Originales!D55 -> 0
A81: =+Cifras_Originales!A57 -> BONOS DE LA EMISORA A 3, 5 Y 10 | B81: Precio Medio | C81: Moody's | D81: YTM | E81: DIVISA
A82: =+Cifras_Originales!A58 -> 0 | B82: =+Cifras_Originales!B58 -> 0 | C82: =+Cifras_Originales!C58 -> 0 | D82: =+Cifras_Originales!D58 -> 0 | E82: =+Cifras_Originales!E58 -> 0
A83: =+Cifras_Originales!A59 -> 0 | B83: =+Cifras_Originales!B59 -> 0 | C83: =+Cifras_Originales!C59 -> 0 | D83: =+Cifras_Originales!D59 -> 0 | E83: =+Cifras_Originales!E59 -> 0
A84: =+Cifras_Originales!A60 -> 0 | B84: =+Cifras_Originales!B60 -> 0 | C84: =+Cifras_Originales!C60 -> 0 | D84: =+Cifras_Originales!D60 -> 0 | E84: =+Cifras_Originales!E60 -> 0
A85: =+Cifras_Originales!A61 -> 0 | B85: =+Cifras_Originales!B61 -> 0 | C85: =+Cifras_Originales!C61 -> 0 | D85: =+Cifras_Originales!D61 -> 0 | E85: =+Cifras_Originales!E61 -> 0

Sheet Cifras_Originales
A1: USD
A2: Millones | C2: ="Cifras en "&A2&" de "&A1 -> Cifras en Millones de USD
A3: YETI HOLDINGS, INC. | G3: =A3&" ("&A4&")" -> YETI HOLDINGS, INC. ((XNYS:YETI))
A4: (XNYS:YETI)
A5: RESULTADOS | B5: 2023 | C5: =B5-1 -> 2022 | D5: =C5-1 -> 2021 | E5: =D5-1 -> 2020 | F5: =E5-1 -> 2019 | G5: =F5-1 -> 2018 | H5: =G5-1 -> 2017 | I5: =H5-1 -> 2016 | J5: =I5-1 -> 2015 | ... M5: =L5-1 -> 2012
A6: Ventas Netas | B6: 1658.713 | C6: 1595.222 | D6: 1410.989 | E6: 1091.721 | F6: 913.734 | G6: 778.833 | H6: 639.239 | I6: 818.914 | J6: 468.946 | K6: 147.7 | L6: 89.9 | M6: N/A
A7: Utilidad Bruta | B7: 943.186 | C7: 763.401 | D7: 816.113 | E7: 628.803 | F7: 475.314 | G7: 383.128 | H7: 294.601 | I7: 413.961 | J7: 218.701 | K7: 67.2 | L7: 44.4 | M7: N/A
A8: Utilidad de Operación | B8: 225.458 | C8: 126.361 | D8: 274.938 | E8: 214.233 | F8: 89.771 | G8: 102.156 | H8: 63.967 | I8: 88.207 | J8: 127.9 | K8: 25.7 | L8: 15.2 | M8: N/A
A9: CIF (Poductos) | B9: -0.942 | C9: -4.466 | D9: -3.339 | E9: -9.155 | F9: -21.779 | G9: -3.128 | H9: -32.607 | I9: 21.7 | J9: 6.1 | K9: 3.5 | L9: 3.9 | M9: N/A | R9: =B5 -> 2023 | S9: =C5 -> 2022 | T9: =D5 -> 2021 | U9: =E5 -> 2020 | V9: =F5 -> 2019 | W9: =G5 -> 2018 | X9: =H5 -> 2017 | Y9: =I5 -> 2016 | ... AB9: =L5 -> 2013
A10: Otros Gastos (Ingresos) | B10: 1.43 | C10: 5.718 | D10: 3.189 | E10: 0.123 | F10: -0.734 | G10: -1.261 | H10: 0.699 | I10: -1.242 | J10: 6.5 | K10: 0.2 | L10: 0.2 | M10: N/A | Q10: Inventories | R10: =B24 -> 337.208 | S10: =C24 -> 371.412 | T10: =D24 -> 318.864 | U10: =E24 -> 140.111 | V10: =F24 -> 185.7 | W10: =G24 -> 145.423 | X10: =H24 -> 175.098 | Y10: =I24 -> 246.119 | ... AB10: =L24 -> N/A
A11: Depreciación y amortización | B11: -46.434 | C11: -39.847 | D11: -32.07 | E11: -30.535 | F11: -28.959 | G11: -24.777 | H11: -20.769 | I11: -11.675 | J11: -7.5 | K11: -6.8 | L11: -5.7 | M11: N/A | Q11: Por cobrar | R11: =B23 -> 95.774 | S11: =C23 -> 79.446 | T11: =D23 -> 109.53 | U11: =E23 -> 65.417 | V11: =F23 -> 82.688 | W11: =G23 -> 59.328 | X11: =H23 -> 67.152 | Y11: =I23 -> 37.2 | ... AB11: =L23 -> N/A
A12: Capital de Trabajo | B12: =R17 -> 31.698 | C12: =S17 -> -28.037 | D12: =T17 -> 290.564 | E12: =U17 -> -23.062 | F12: =V17 -> 78.723 | G12: =W17 -> -9.104 | H12: =X17 -> -20.127 | I12: =Y17 -> 125.519 | J12: =Z17 -> 129.7 | K12: N/A | L12: N/A | M12: N/A | Q12: Por pagar | R12: 190.392 | S12: 140.818 | T12: 191.319 | U12: 123.621 | V12: 83.823 | W12: 68.737 | X12: 40.342 | Y12: 19.4 | Z12: 24.9 | AA12: 12.9 | AB12: N/A
A13: Capex | B13: -50.672 | C13: -45.929 | D13: -56.121 | E13: -15.566 | F13: -32.077 | G13: -20.86 | H13: -42.197 | I13: -35.588 | J13: -8.9 | K13: -3.8 | L13: -4.7 | M13: N/A
A14: Inversiones | B14: 0 | C14: 0 | D14: 0 | E14: 0 | F14: 0 | G14: 0 | H14: 0 | I14: 0 | J14: 0 | K14: 0 | L14: 0 | M14: N/A | R14: =(R10-S10) -> -34.204 | S14: =(S10-T10) -> 52.548 | T14: =(T10-U10) -> 178.753 | U14: =(U10-V10) -> -45.589 | V14: =(V10-W10) -> 40.277 | W14: =(W10-X10) -> -29.675 | X14: =(X10-Y10) -> -71.021 | Y14: =(Y10-Z10) -> 157.819 | ... AB14: =(AB10-AC10) -> #VALUE!
A15: I.S.R Y P.T.U. | B15: =-(B16-B8+B9+B10) -> 55.085 | C15: =-(C16-C8+C9+C10) -> 35.416 | D15: =-(D16-D8+D9+D10) -> 62.486 | E15: =-(E16-E8+E9+E10) -> 67.464 | F15: =-(F16-F8+F9+F10) -> 61.85 | G15: =-(G16-G8+G9+G10) -> 48.782 | H15: =-(H16-H8+H9+H10) -> 80.474 | I15: =-(I16-I8+I9+I10) -> 19.772 | ... L15: =-(L16-L8+L9+L10) -> 3.8 | M15: N/A | R15: =(R11-S11) -> 16.328 | S15: =(S11-T11) -> -30.084 | T15: =(T11-U11) -> 44.113 | U15: =(U11-V11) -> -17.271 | V15: =(V11-W11) -> 23.36 | W15: =(W11-X11) -> -7.824 | X15: =(X11-Y11) -> 29.952 | Y15: =(Y11-Z11) -> -26.8 | ... AB15: =(AB11-AC11) -> #VALUE!
A16: Utilidad Neta | B16: 169.885 | C16: 89.693 | D16: 212.602 | E16: 155.801 | F16: 50.434 | G16: 57.763 | H16: 15.401 | I16: 47.977 | J16: 74.2 | K16: 14.2 | L16: 7.3 | M16: N/A | R16: =(R12-S12) -> 49.574 | S16: =(S12-T12) -> -50.501 | T16: =(T12-U12) -> 67.698 | U16: =(U12-V12) -> 39.798 | V16: =(V12-W12) -> 15.086 | W16: =(W12-X12) -> 28.395 | X16: =(X12-Y12) -> 20.942 | Y16: =(Y12-Z12) -> -5.5 | ... AB16: =(AB12-AC12) -> #VALUE!
A17: Dividendos | B17: 0 | C17: 0 | D17: 0 | E17: 0 | F17: 0 | G17: 0 | H17: 0 | I17: 0 | J17: N/A | K17: N/A | L17: N/A | M17: N/A | Q17: Capital de trabajo | R17: =SUM(R14:R16) -> 31.698 | S17: =SUM(S14:S16) -> -28.037 | T17: =SUM(T14:T16) -> 290.564 | U17: =SUM(U14:U16) -> -23.062 | V17: =SUM(V14:V16) -> 78.723 | W17: =SUM(W14:W16) -> -9.104 | X17: =SUM(X14:X16) -> -20.127 | Y17: =SUM(Y14:Y16) -> 125.519 | ... AB17: =SUM(AB14:AB16) -> #VALUE!
A18: Compra de Acciones | B18: 0 | C18: 0 | D18: 0 | E18: 0 | F18: 0 | G18: 0 | H18: 0 | I18: 0 | J18: N/A | K18: N/A | L18: N/A | M18: N/A
B19: =B8-B9-B10-B15 -> 169.885 | C19: =C8-C9-C10-C15 -> 89.693 | D19: =D8-D9-D10-D15 -> 212.602 | E19: =E8-E9-E10-E15 -> 155.801 | F19: =F8-F9-F10-F15 -> 50.434 | G19: =G8-G9-G10-G15 -> 57.763 | H19: =H8-H9-H10-H15 -> 15.401 | I19: =I8-I9-I10-I15 -> 47.977 | ... M19: =M8-M9-M10-M15 -> #VALUE!
A20: POSICIÓN FINANCIERA | B20: =B16-B19 -> 0 | C20: =C16-C19 -> 0 | D20: =D16-D19 -> 0 | E20: =E16-E19 -> 0 | F20: =F16-F19 -> 0 | G20: =G16-G19 -> 0 | H20: =H16-H19 -> 0 | I20: =I16-I19 -> 0 | ... M20: =M16-M19 -> #VALUE!
A21: Activo
A22: Caja | B22: 438.96 | C22: 234.741 | D22: 312.189 | E22: 253.283 | F22: 72.515 | G22: 80.051 | H22: 53.65 | I22: 21.291 | J22: 40.3 | K22: 8.9 | L22: N/A | M22: N/A
A23: Cuentas y documentos por cobrar | B23: 95.774 | C23: 79.446 | D23: 109.53 | E23: 65.417 | F23: 82.688 | G23: 59.328 | H23: 67.152 | I23: 37.2 | J23: 64 | K23: 16.9 | L23: N/A | M23: N/A
A24: Inventarios | B24: 337.208 | C24: 371.412 | D24: 318.864 | E24: 140.111 | F24: 185.7 | G24: 145.423 | H24: 175.098 | I24: 246.119 | J24: 88.3 | K24: 17.7 | L24: N/A | M24: N/A
A25: Activos Fijos (Net Plant) | B25: 130.714 | C25: 124.587 | D25: 119.044 | E25: 78.075 | F25: 82.61 | G25: 74.097 | H25: 73.783 | I25: 47.1 | J25: 14.8 | K25: 9.1 | L25: N/A | M25: N/A
A26: Otros Activos | B26: =B27-SUM(B22:B25) -> 294.536 | C26: =C27-SUM(C22:C25) -> 266.579 | D26: =D27-SUM(D22:D25) -> 236.737 | E26: =E27-SUM(E22:E25) -> 200.181 | F26: =F27-SUM(F22:F25) -> 206.026 | G26: =G27-SUM(G22:G25) -> 155.314 | H26: =H27-SUM(H22:H25) -> 146.744 | I26: =I27-SUM(I22:I25) -> 184.397 | ... M26: =M27-SUM(M22:M25) -> #VALUE!
A27: Total Activo | B27: 1297.192 | C27: 1076.765 | D27: 1096.364 | E27: 737.067 | F27: 629.539 | G27: 514.213 | H27: 516.427 | I27: 536.107 | J27: 346 | K27: 181.5 | L27: N/A | M27: N/A
A30: Pasivo
A31: Pasivo Corto Plazo | B31: 398.353 | C31: 409.04 | D31: 403.713 | E31: 287.759 | F31: 170.312 | G31: 187.338 | H31: 151.898 | I31: 137.9 | J31: 81.8 | K31: 21.8 | L31: N/A | M31: N/A
A32: Deuda a corto plazo | B32: 6.579 | C32: 24.611 | D32: 24.56 | E32: 22.697 | F32: 15.185 | G32: 43.638 | H32: 47.05 | I32: 45.6 | J32: 2 | K32: 2 | L32: N/A | M32: N/A
A33: Short-Term Leases | B33: 14.726 | C33: 12.076 | D33: 10.167 | E33: 8.247 | F33: 7.768 | G33: 0 | H33: 0 | I33: N/A | J33: N/A | K33: N/A | L33: N/A | M33: N/A
A34: Otros Pasivos a Corto Plazo | B34: =B31-B32-B33 -> 377.048 | C34: =C31-C32-C33 -> 372.353 | D34: =D31-D32-D33 -> 368.986 | E34: =E31-E32-E33 -> 256.815 | F34: =F31-F32-F33 -> 147.359 | G34: =G31-G32-G33 -> 143.7 | H34: =H31-H32-H33 -> 104.848 | I34: =I31-I32-I33 -> #VALUE! | ... M34: =M31-M32-M33 -> #VALUE!
A35: Pasivo Largo Plazo | B35: =B39-B31 -> 175.229 | C35: =C39-C31 -> 141.248 | D35: =D39-D31 -> 174.828 | E35: =E39-E31 -> 160.89 | F35: =F39-F31 -> 337.222 | G35: =G39-G31 -> 297.904 | H35: =H39-H31 -> 440.76 | I35: =I39-I31 -> 493.3 | ... K35: =K39-K31 -> 35.2 | L35: N/A | M35: N/A
A36: Deuda a largo plazo | B36: 78.645 | C36: 71.741 | D36: 95.741 | E36: 111.017 | F36: 281.715 | G36: 284.376 | H36: 428.632 | I36: 491.7 | J36: 59.7 | K36: 26.7 | L36: N/A | M36: N/A
A37: Long-Term Leases | B37: 76.163 | C37: 55.649 | D37: 55.94 | E37: 36.546 | F37: 42.2 | G37: 0 | H37: 0 | I37: N/A | J37: N/A | K37: N/A | L37: N/A | M37: N/A
A38: Otros Pasivos a Largo Plazo | B38: =B35-B36-B37 -> 20.421 | C38: =C35-C36-C37 -> 13.858 | D38: =D35-D36-D37 -> 23.147 | E38: =E35-E36-E37 -> 13.327 | F38: =F35-F36-F37 -> 13.307 | G38: =G35-G36-G37 -> 13.528 | H38: =H35-H36-H37 -> 12.128 | I38: =I35-I36-I37 -> #VALUE! | ... M38: =M35-M36-M37 -> #VALUE!
A39: Total pasivos | B39: 573.582 | C39: 550.288 | D39: 578.541 | E39: 448.649 | F39: 507.534 | G39: 485.242 | H39: 592.658 | I39: 631.2 | J39: 145.1 | K39: 57 | L39: =L35+L31 -> #VALUE! | M39: =M35+M31 -> #VALUE!
A42: Interés Minoritario | B42: 0 | C42: 0 | D42: 0 | E42: 0 | F42: 0 | G42: 0 | H42: 0 | I42: 2.2 | J42: 0 | K42: 0 | L42: N/A | M42: N/A
A44: Capital Contable | B44: =B27-B39-B42 -> 723.61 | C44: =C27-C39-C42 -> 526.477 | D44: =D27-D39-D42 -> 517.823 | E44: =E27-E39-E42 -> 288.418 | F44: =F27-F39-F42 -> 122.005 | G44: =G27-G39-G42 -> 28.971 | H44: =H27-H39-H42 -> -76.231 | I44: =I27-I39-I42 -> -97.293 | ... M44: =M27-M39-M42 -> #VALUE!
A46: OTROS DATOS AL FIN DE AÑO
A47: Numero de Empleados
A48: Acciones en circulación (millones)
A49: Float
A50: Insiders Own
A51: S&P
A52: ="Vol. Diario en Millones "&A1 -> Vol. Diario en Millones USD
B53: 2021 | C53: =B53+1 -> 2022 | D53: =C53+1 -> 2023
A54: Posicion en Corto (%)
A55: EPS
A57: BONOS DE LA EMISORA A 3, 5 Y 10 | B57: Precio Medio | C57: S&P | D57: YTM (%) | E57: DIVISA

Sheet Assumptions
B2: Assumptions
B4: Prospects:
C8: Last 10 Years
C9: 2023 | D9: 2022 | E9: 2021 | F9: 2020 | G9: 2019 | H9: 2018 | I9: 2017 | J9: 2016 | K9: 2015 | L9: 2016 | N9: 10Y AVERAGE | O9: 5Y AVERAGE | P9: 3Y AVERAGE | R9: Short Term Forecast | S9: Long Term Forecast
B10: Revenue growth | C10: =(Cifras_Originales!B6-Cifras_Originales!C6)/Cifras_Originales!C6 -> 0.03980073 | D10: =(Cifras_Originales!C6-Cifras_Originales!D6)/Cifras_Originales!D6 -> 0.13057012 | E10: =(Cifras_Originales!D6-Cifras_Originales!E6)/Cifras_Originales!E6 -> 0.29244468 | F10: =(Cifras_Originales!E6-Cifras_Originales!F6)/Cifras_Originales!F6 -> 0.19479083 | G10: =(Cifras_Originales!F6-Cifras_Originales!G6)/Cifras_Originales!G6 -> 0.17320915 | H10: =(Cifras_Originales!G6-Cifras_Originales!H6)/Cifras_Originales!H6 -> 0.21837529 | I10: =(Cifras_Originales!H6-Cifras_Originales!I6)/Cifras_Originales!I6 -> -0.21940643 | J10: =(Cifras_Originales!I6-Cifras_Originales!J6)/Cifras_Originales!J6 -> 0.74628635 | ... L10: =(Cifras_Originales!K6-Cifras_Originales!L6)/Cifras_Originales!L6 -> 0.6429366 | N10: =AVERAGE(C10:L10) -> 0.43939971 | O10: =AVERAGE(C10:G10) -> 0.1661631 | P10: =AVERAGE(C10:E10) -> 0.15427184 | R10: — | S10: —
B11: Operating Margin | C11: 0.1398 | D11: 0.168 | E11: 0.1982 | F11: 0.1972 | G11: 0.1012 | H11: 0.1361 | I11: 0.1001 | J11: 0.1121 | K11: 0.2888 | L11: 0.1803 | N11: =AVERAGE(C11:L11) -> 0.16218 | O11: =AVERAGE(C11:G11) -> 0.16088 | P11: =AVERAGE(C11:E11) -> 0.16866667 | R11: 0.16 | S11: 0.16
B13: Modelling Factors
D15: Last 10 Years
B16: Reference | D16: 2023 | E16: 2022 | F16: 2021 | G16: 2020 | H16: 2019 | I16: 2018 | J16: 2017 | K16: 2016 | L16: 2015 | M16: 2014 | O16: 6-10Y AVERAGE | P16: 3Y AVERAGE | R16: Short Term | S16: Long Term | T16: Reference (line)
B17: % Capex/Adq | C17: Depreciation factor | D17: =C56/C63 -> 0.81307231 | E17: =D56/D63 -> 0.71414575 | F17: =E56/E63 -> 0.4579391 | G17: =F56/F63 -> 1.5803675 | H17: =G56/G63 -> 0.72325966 | I17: =H56/H63 -> 0.93480345 | J17: =I56/I63 -> 0.36495485 | K17: =J56/J63 -> 0.15173654 | L17: =K56/K63 -> 0.34831461 | M17: =L56/L62 -> -0.13333333 | O17: =AVERAGE(D17:M17) -> 0.59552604 | P17: =AVERAGE(D17:F17) -> 0.66171905 | R17: 0.65 | S17: 0.55 | T17: % Capex/Adq (l16)
B18: % revenue | C18: Stock-based comp | D18: =C57/Cifras_Originales!B6 -> 0.017965736 | E18: =D57/Cifras_Originales!C6 -> 0.011157695 | F18: =E57/Cifras_Originales!D6 -> 0.010966776 | G18: =F57/Cifras_Originales!E6 -> 0.0082521084 | H18: =G57/Cifras_Originales!F6 -> 0.057237664 | I18: =H57/Cifras_Originales!G6 -> 0.016948434 | J18: =I57/Cifras_Originales!H6 -> 0.020962426 | K18: =J57/Cifras_Originales!I6 -> 0.14238369 | ... M18: =L57/Cifras_Originales!K6 -> 0.0013540961 | O18: =AVERAGE(D18:M18) -> 0.028850809 | P18: =AVERAGE(D18:F18) -> 0.013363402 | R18: 0.01 | S18: 0.02 | T18: % revenue (l2)
B19: % EBT | C19: Tax Rate | D19: =C58/DCFF!G15 -> -0.24125117 | E19: =D58/DCFF!F15 -> -0.10274527 | F19: =E58/DCFF!E15 -> -0.19966511 | G19: =F58/DCFF!D15 -> -0.2395089 | H19: =G58/G67 -> -0.14983435 | I19: =H58/H67 -> -0.11123938 | J19: =I58/I67 -> -0.17374707 | K19: =J58/J67 -> -0.24350175 | L19: =Assumptions!K58/Assumptions!K67 -> -0.35646141 | M19: =L58/L67 -> 0.35 | O19: =AVERAGE(D19:M19) -> -0.14679544 | P19: =AVERAGE(D19:F19) -> -0.18122052 | R19: 0.2 | S19: 0.2 | T19: % (line 9)
B20: % of debt | C20: Interest Rate on debt | D20: =C59/C73 -> 0.0053488385 | E20: =D59/D73 -> 0.027218928 | F20: =E59/E73 -> 0.017912321 | G20: =F59/F73 -> 0.051286504 | H20: =G59/G73 -> 0.062787573 | I20: =H59/H73 -> 0.0095361783 | J20: =I59/I73 -> 0.068547895 | K20: N/A | L20: N/A | M20: N/A | O20: =AVERAGE(D20:J20) -> 0.034662606 | P20: =AVERAGE(D20:F20) -> 0.016826696 | R20: 0.02 | S20: 0.03 | T20: % debt (l29)
B21: % of cash | C21: Interest Rate on cash | D21: N/A | E21: =D60/Cifras_Originales!C22 -> 0 | F21: =E60/Cifras_Originales!D22 -> 0 | G21: =F60/Cifras_Originales!E22 -> 0 | H21: =G60/Cifras_Originales!F22 -> 0 | I21: =H60/Cifras_Originales!G22 -> 0 | J21: =I60/Cifras_Originales!H22 -> 0 | K21: =J60/Cifras_Originales!I22 -> 0 | L21: =K60/Cifras_Originales!J22 -> 0 | M21: =L60/Cifras_Originales!K22 -> 0 | O21: =AVERAGE(E21:M21) -> 0 | P21: =AVERAGE(D21:F21) -> 0 | R21: 0 | S21: 0 | T21: % of cash (l28)
B22: % revenue | C22: Net SBC | D22: 0.017965736 | E22: 0.011157695 | F22: 0.010966776 | G22: 0.0082521084 | H22: 0.057237664 | I22: 0.016948434 | J22: 0.020962426 | K22: 0.14238369 | L22: 0.001279465 | M22: 0.0013540961 | O22: =AVERAGE(D22:M22) -> 0.028850809 | P22: =AVERAGE(D22:F22) -> 0.013363402 | R22: 0.01 | S22: 0.02 | T22: % revenue (l2)
B23: % of change revenues | C23: Working capital flows | D23: =C62/C83 -> -1.2709236 | E23: =D62/D83 -> -2.0849209 | F23: =E62/E83 -> -1.0469099 | G23: =F62/F83 -> 2.2409285 | H23: =G62/G83 -> -1.8836969 | I23: =H62/H83 -> 2.6724915 | J23: --- | K23: --- | L23: --- | M23: --- | O23: =AVERAGE(D23:I23) -> -0.22883854 | P23: =AVERAGE(D23:F23) -> -1.4675848 | R23: -0.3 | S23: -0.3 | T23: % of change revenues (l2)
B24: % revenue | C24: Capex / Adq | D24: =C63/Cifras_Originales!B6 -> 0.030548986 | E24: =D63/Cifras_Originales!C6 -> 0.028791604 | F24: =E63/Cifras_Originales!D6 -> 0.039774229 | G24: =F63/Cifras_Originales!E6 -> 0.014258222 | H24: =G63/Cifras_Originales!F6 -> 0.035105403 | I24: =H63/Cifras_Originales!G6 -> 0.026783662 | J24: =I63/Cifras_Originales!H6 -> 0.066011304 | K24: =Assumptions!J63/Cifras_Originales!I6 -> 0.043457555 | L24: =K63/Cifras_Originales!J6 -> 0.018978731 | M24: =L63/Cifras_Originales!K6 -> 0.025727827 | O24: =AVERAGE(D24:M24) -> 0.032943752 | P24: =AVERAGE(D24:F24) -> 0.033038273 | R24: 0.03 | S24: 0.04 | T24: % revenue (l2)
B25: Growth rate | C25: Dividends | D25: 0 | E25: 0 | F25: 0 | G25: 0 | H25: 0 | I25: 0 | J25: 0 | K25: 0 | L25: 0 | M25: 0 | O25: =AVERAGE(D25:M25) -> 0 | P25: =AVERAGE(D25:F25) -> 0 | R25: 0 | S25: 0 | T25: Growth rate
B26: % of debt | C26: Other financing flows | D26: =C65/Cifras_en_Millones!C60 -> -0.02119094 | E26: =D65/Cifras_en_Millones!D60 -> 0.011945611 | F26: =E65/Cifras_en_Millones!E60 -> 0.0031597356 | G26: =F65/Cifras_en_Millones!F60 -> 0.01117043 | H26: =G65/Cifras_en_Millones!G60 -> -0.034854757 | I26: =H65/Cifras_en_Millones!H60 -> 0.11672673 | J26: =I65/Cifras_en_Millones!I60 -> -0.0081483008 | K26: N/A | L26: N/A | M26: N/A | O26: =AVERAGE(D26:J26) -> 0.011258358 | P26: =AVERAGE(D26:F26) -> -0.0020285311 | R26: -0.01 | S26: 0.01 | T26: % of debt (l29)
B34: FORECASTS
B36: Revenue Growth
B38: Base scenario | C38: Time period | D38: 2024 | E38: 2025 | F38: 2026 | G38: 2027 | H38: 2028 | I38: 2029 | J38: 2030 | K38: 2031 | L38: 2032 | M38: 2033 | N38: 2034 | O38: 2035 | P38: 2036 | Q38: 2037 | R38: 2038 | S38: 2039 | T38: 2040 | U38: 2041 | V38: 2042 | W38: 2043 | X38: 2044 | Y38: 2045 | Z38: 2046 | AA38: 2047 | AB38: 2048
C39: Forecasted revenue growth (%) | D39: 0.10318844 | E39: 0.18 | F39: 0.16 | G39: 0.14 | H39: 0.13 | I39: 0.11 | J39: 0.1 | K39: 0.09 | L39: 0.08 | M39: 0.07 | N39: 0.07 | O39: 0.07 | P39: 0.06 | Q39: 0.06 | R39: 0.05 | S39: 0.05 | T39: 0.05 | U39: 0.05 | V39: 0.04 | W39: 0.04 | X39: 0.04 | Y39: 0.04 | Z39: 0.03 | AA39: 0.03 | AB39: 0.03
C40: Forecasted revenues | D40: =Cifras_Originales!$B$6*(1+Assumptions!D39) -> 1829.873 | E40: =D40*(1+Assumptions!E39) -> 2159.2501 | F40: =E40*(1+Assumptions!F39) -> 2504.7302 | G40: =F40*(1+Assumptions!G39) -> 2855.3924 | H40: =G40*(1+Assumptions!H39) -> 3226.5934 | I40: =H40*(1+Assumptions!I39) -> 3581.5187 | J40: =I40*(1+Assumptions!J39) -> 3939.6705 | K40: =J40*(1+Assumptions!K39) -> 4294.2409 | L40: =K40*(1+Assumptions!L39) -> 4637.7802 | ... AB40: =AA40*(1+Assumptions!AB39) -> 9919.1726
C41: Forecasted operating margin | D41: 0.16 | E41: 0.16 | F41: 0.16 | G41: 0.16 | H41: 0.16 | I41: 0.16 | J41: 0.16 | K41: 0.16 | L41: 0.16 | M41: 0.16 | N41: 0.16 | O41: 0.16 | P41: 0.16 | Q41: 0.16 | R41: 0.16 | S41: 0.16 | T41: 0.16 | U41: 0.16 | V41: 0.16 | W41: 0.16 | X41: 0.16 | Y41: 0.16 | Z41: 0.16 | AA41: 0.16 | AB41: 0.16
B43: Bullish scenario | C43: Time period | D43: 2024 | E43: 2025 | F43: 2026 | G43: 2027 | H43: 2028 | I43: 2029 | J43: 2030 | K43: 2031 | L43: 2032 | M43: 2033 | N43: 2034 | O43: 2035 | P43: 2036 | Q43: 2037 | R43: 2038 | S43: 2039 | T43: 2040 | U43: 2041 | V43: 2042 | W43: 2043 | X43: 2044 | Y43: 2045 | Z43: 2046 | AA43: 2047 | AB43: 2048
C44: Forecasted revenue growth (%) | D44: 0.13 | E44: 0.21 | F44: 0.19 | G44: 0.18 | H44: 0.16 | I44: 0.14 | J44: 0.13 | K44: 0.12 | L44: 0.11 | M44: 0.1 | N44: 0.09 | O44: 0.09 | P44: 0.08 | Q44: 0.08 | R44: 0.07 | S44: 0.07 | T44: 0.07 | U44: 0.07 | V44: 0.06 | W44: 0.06 | X44: 0.06 | Y44: 0.06 | Z44: 0.05 | AA44: 0.05 | AB44: 0.05
C45: Forecasted revenues | D45: =Cifras_Originales!$B$6*(1+D44) -> 1874.3457 | E45: =Cifras_Originales!$B$6*(1+E44) -> 2007.0427 | F45: =Cifras_Originales!$B$6*(1+F44) -> 1973.8685 | G45: =Cifras_Originales!$B$6*(1+G44) -> 1957.2813 | H45: =Cifras_Originales!$B$6*(1+H44) -> 1924.1071 | I45: =Cifras_Originales!$B$6*(1+I44) -> 1890.9328 | J45: =Cifras_Originales!$B$6*(1+J44) -> 1874.3457 | K45: =Cifras_Originales!$B$6*(1+K44) -> 1857.7586 | ... AB45: =Cifras_Originales!$B$6*(1+AB44) -> 1741.6487
C46: Forecasted operating margin | D46: 0.16 | E46: 0.16 | F46: 0.16 | G46: 0.16 | H46: 0.16 | I46: 0.16 | J46: 0.16 | K46: 0.16 | L46: 0.16 | M46: 0.16 | N46: 0.16 | O46: 0.16 | P46: 0.16 | Q46: 0.16 | R46: 0.16 | S46: 0.16 | T46: 0.16 | U46: 0.16 | V46: 0.16 | W46: 0.16 | X46: 0.16 | Y46: 0.16 | Z46: 0.16 | AA46: 0.16 | AB46: 0.16
B48: Bearish scenario | C48: Time period | D48: 2024 | E48: 2025 | F48: 2026 | G48: 2027 | H48: 2028 | I48: 2029 | J48: 2030 | K48: 2031 | L48: 2032 | M48: 2033 | N48: 2034 | O48: 2035 | P48: 2036 | Q48: 2037 | R48: 2038 | S48: 2039 | T48: 2040 | U48: 2041 | V48: 2042 | W48: 2043 | X48: 2044 | Y48: 2045 | Z48: 2046 | AA48: 2047 | AB48: 2048
C49: Forecasted revenue growth (%) | D49: 0.08 | E49: 0.14 | F49: 0.13 | G49: 0.12 | H49: 0.11 | I49: 0.09 | J49: 0.08 | K49: 0.07 | L49: 0.06 | M49: 0.05 | N49: 0.05 | O49: 0.05 | P49: 0.04 | Q49: 0.04 | R49: 0.03 | S49: 0.03 | T49: 0.03 | U49: 0.03 | V49: 0.02 | W49: 0.02 | X49: 0.02 | Y49: 0.02 | Z49: 0.015 | AA49: 0.015 | AB49: 0.015
C50: Forecasted revenues | D50: =Cifras_Originales!$B$6*(1+D49) -> 1791.41 | E50: =Cifras_Originales!$B$6*(1+E49) -> 1890.9328 | F50: =Cifras_Originales!$B$6*(1+F49) -> 1874.3457 | G50: =Cifras_Originales!$B$6*(1+G49) -> 1857.7586 | H50: =Cifras_Originales!$B$6*(1+H49) -> 1841.1714 | I50: =Cifras_Originales!$B$6*(1+I49) -> 1807.9972 | J50: =Cifras_Originales!$B$6*(1+J49) -> 1791.41 | K50: =Cifras_Originales!$B$6*(1+K49) -> 1774.8229 | ... AB50: =Cifras_Originales!$B$6*(1+AB49) -> 1683.5937
C51: Forecasted operating margin | D51: 0.16 | E51: 0.16 | F51: 0.16 | G51: 0.16 | H51: 0.16 | I51: 0.16 | J51: 0.16 | K51: 0.16 | L51: 0.16 | M51: 0.16 | N51: 0.16 | O51: 0.16 | P51: 0.16 | Q51: 0.16 | R51: 0.16 | S51: 0.16 | T51: 0.16 | U51: 0.16 | V51: 0.16 | W51: 0.16 | X51: 0.16 | Y51: 0.16 | Z51: 0.16 | AA51: 0.16 | AB51: 0.16
C55: 2023 | D55: 2022 | E55: 2021 | F55: 2020 | G55: 2019 | H55: 2018 | I55: 2017 | J55: 2016 | K55: 2015 | L55: 2014
B56: Depreciation | C56: 41.2 | D56: 32.8 | E56: 25.7 | F56: 24.6 | G56: 23.2 | H56: 19.5 | I56: 15.4 | J56: 5.4 | K56: 3.1 | L56: 2.4
B57: Stock-based comp | C57: 29.8 | D57: 17.799 | E57: 15.474 | F57: 9.009 | G57: 52.3 | H57: 13.2 | I57: 13.4 | J57: 116.6 | K57: 0.6 | L57: 0.2
B58: Income Tax Expense | C58: -56.061 | D58: -26.484 | E58: -55.808 | F58: -49.4 | G58: -16.824 | H58: -11.852 | I58: -16.658 | J58: -16.497 | K58: -41.1 | L58: 7.7
B59: Interest expense | C59: 0.942 | D59: 4.466 | E59: 3.339 | F59: 9.155 | G59: 21.779 | H59: 3.128 | I59: 32.607 | J59: 21.7 | K59: 6.1 | L59: 3.5
B60: Interest income | C60: --- | D60: 0 | E60: 0 | F60: 0 | G60: 0 | H60: 0 | I60: 0 | J60: 0 | K60: 0 | L60: 0
B61: Net SBC | C61: --- | D61: --- | E61: --- | F61: --- | G61: --- | H61: --- | I61: --- | J61: --- | K61: --- | L61: ---
B62: Working capital flows | C62: 14.669 | D62: -147.087 | E62: -122.947 | F62: 171.933 | G62: -63.895 | H62: 71.727 | I62: 86.738 | J62: -135.4 | K62: -79.3 | L62: -18
B63: Capex / Adq | C63: 50.672 | D63: 45.929 | E63: 56.121 | F63: 15.566 | G63: 32.077 | H63: 20.86 | I63: 42.197 | J63: 35.588 | K63: 8.9 | L63: 3.8
B64: Dividends | C64: 0 | D64: 0 | E64: 0 | F64: 0 | G64: 0 | H64: 0 | I64: 0 | J64: 0 | K64: 0 | L64: 0
B65: Other financing flows | C65: -3.732 | D65: 1.96 | E65: 0.589 | F65: 1.994 | G65: -12.09 | H65: 38.288 | I65: -3.876 | J65: -23.63 | K65: --- | L65: ---
F67: EBT | G67: =Cifras_en_Millones!G16 -> 112.284 | H67: =Cifras_en_Millones!H16 -> 106.545 | I67: =Cifras_en_Millones!I16 -> 95.875 | J67: =Cifras_en_Millones!J16 -> 67.749 | K67: =Cifras_en_Millones!K16 -> 115.3 | L67: =Cifras_en_Millones!L16 -> 22
C70: Last 10 years
C71: 2023 | D71: 2022 | E71: 2021 | F71: 2020 | G71: 2019 | H71: 2018 | I71: 2017 | J71: 2016 | K71: 2015 | L71: 2014
B72: Debt payment | C72: 9.9 | D72: 24.6 | E72: 23.6 | F72: 165.2 | G72: 33 | H72: 151.8 | I72: 65.6 | J72: 485.5 | K72: 33 | L72: 1.5
B73: Total debt | C73: =Cifras_Originales!B32+Cifras_Originales!B33+Cifras_Originales!B36+Cifras_Originales!B37 -> 176.113 | D73: =Cifras_Originales!C32+Cifras_Originales!C33+Cifras_Originales!C36+Cifras_Originales!C37 -> 164.077 | E73: =Cifras_Originales!D32+Cifras_Originales!D33+Cifras_Originales!D36+Cifras_Originales!D37 -> 186.408 | F73: =Cifras_Originales!E32+Cifras_Originales!E33+Cifras_Originales!E36+Cifras_Originales!E37 -> 178.507 | G73: =Cifras_Originales!F32+Cifras_Originales!F33+Cifras_Originales!F36+Cifras_Originales!F37 -> 346.868 | H73: =Cifras_Originales!G32+Cifras_Originales!G36 -> 328.014 | I73: =Cifras_Originales!H32+Cifras_Originales!H36 -> 475.682 | J73: --- | K73: --- | L73: --- | N73: 7Y AVERAGE | O73: 3Y AVERAGE
B74: % | C74: =C72/C73 -> 0.056213908 | D74: =D72/D73 -> 0.14992961 | E74: =E72/E73 -> 0.12660401 | F74: =F72/F73 -> 0.9254539 | G74: =G72/G73 -> 0.095137055 | H74: =H72/H73 -> 0.46278513 | I74: =I72/I73 -> 0.13790726 | J74: --- | K74: --- | L74: --- | N74: =AVERAGE(C74:I74) -> 0.27914727 | O74: =AVERAGE(C74:E74) -> 0.11091584
C76: Last 7 years
C77: 2023 | D77: 2022 | E77: 2021 | F77: 2020 | G77: 2019 | H77: 2018 | I77: 2017
B78: Segments revenue
B79: Coolers & Equipment | C79: 597.5 | D79: 612.5 | E79: 551.9 | F79: 446.6 | G79: 368.9 | H79: 331.2 | I79: 312.2
B80: Drinkwear | C80: 10.23 | D80: 9.472 | E80: 8.324 | F80: 6.286 | G80: 5.262 | H80: 4.242 | I80: 3.103
B81: Others | C81: 38.2 | D81: 35.5 | E81: 26.7 | F81: 16.6 | G81: 18.6 | H81: 23.4 | I81: 16.7
B82: Total segments revenue | C82: =C79+C80+C81 -> 645.93 | D82: =D79+D80+D81 -> 657.472 | E82: =E79+E80+E81 -> 586.924 | F82: =F79+F80+F81 -> 469.486 | G82: =G79+G80+G81 -> 392.762 | H82: =H79+H80+H81 -> 358.842 | I82: =I79+I80+I81 -> 332.003
B83: Change revenues | C83: =C82-D82 -> -11.542 | D83: =D82-E82 -> 70.548 | E83: =E82-F82 -> 117.438 | F83: =F82-G82 -> 76.724 | G83: =G82-H82 -> 33.92 | H83: =H82-I82 -> 26.839 | I83: ---
C85: Last 10 years
C86: 2023 | D86: 2022 | E86: 2021 | F86: 2020 | G86: 2019 | H86: 2018 | I86: 2017 | J86: 2016 | K86: 2015 | L86: 2014
B87: Cash | C87: 438.96 | D87: 234.741 | E87: 312.189 | F87: 253.283 | G87: 72.515 | H87: 80.051 | I87: 53.65 | J87: 21.291 | K87: 40.3 | L87: 8.9 | N87: 10Y AVERAGE | O87: 3Y AVERAGE
B88: Cash/Revenue | C88: =C87/Cifras_Originales!B6 -> 0.26463891 | D88: =D87/Cifras_Originales!C6 -> 0.14715256 | E88: =E87/Cifras_Originales!D6 -> 0.22125545 | F88: =F87/Cifras_Originales!E6 -> 0.23200341 | G88: =G87/Cifras_Originales!F6 -> 0.079361171 | H88: =H87/Cifras_Originales!G6 -> 0.10278327 | I88: =I87/Cifras_Originales!H6 -> 0.083927921 | J88: =J87/Cifras_Originales!I6 -> 0.025999067 | ... L88: =L87/Cifras_Originales!K6 -> 0.060257278 | N88: =AVERAGE(C88:L88) -> 0.13033164 | O88: =AVERAGE(C88:E88) -> 0.21101564
B91: Debt Structure (from Bloomberg)
C134: 2024 | D134: =+C134+1 -> 2025 | E134: =+D134+1 -> 2026 | F134: =+E134+1 -> 2027 | G134: =+F134+1 -> 2028 | H134: =+G134+1 -> 2029 | I134: =+H134+1 -> 2030 | J134: =+I134+1 -> 2031 | K134: =+J134+1 -> 2032 | ... AA134: =+Z134+1 -> 2048
B135: Repayment debt | D135: 4.22 | E135: 4.22 | F135: =4.22+30 -> 34.22 | G135: =65.39+50 -> 115.39 | H135: 50 | I135: 90 | J135: 178.06 | M135: =L137-M137 -> 0.003 | N135: =M137-N137 -> 0 | O135: =N137-O137 -> 0 | P135: =O137-P137 -> 0 | Q135: =P137-Q137 -> 0 | R135: =Q137-R137 -> 0 | S135: =R137-S137 -> 0 | T135: =S137-T137 -> 0 | ... AA135: =Z137-AA137 -> 0
B136: Forecasted debt
B137: Total debt | C137: =DCFF!G38 -> 176.113 | D137: =C137-D135 -> 171.893 | E137: =D137-E135+E142 -> 467.673 | F137: =E137-F135 -> 433.453 | G137: =F137-G135 -> 318.063 | H137: =G137-H135 -> 268.063 | I137: =H137-I135 -> 178.063 | J137: =I137-J135 -> 0.003 | K137: =J137-K135 -> 0.003 | L137: =K137-L135 -> 0.003 | M137: =L137-M135 -> 0.003 | ... AA137: =Z137-AA135 -> 0.003
B138: Interest expense
B139: Cash % sales | C139: =DCFF!H37/DCFF!H7 -> 0.19607645 | D139: =DCFF!I37/DCFF!I7 -> 0.11585002 | E139: =DCFF!J37/DCFF!J7 -> 0.16516969 | F139: =DCFF!K37/DCFF!K7 -> 0.13075841 | G139: =DCFF!L37/DCFF!L7 -> 0.11197817 | H139: =DCFF!M37/DCFF!M7 -> 0.11273512 | I139: =DCFF!N37/DCFF!N7 -> 0.099228896 | J139: =DCFF!O37/DCFF!O7 -> 0.065557919 | ... AA139: =DCFF!AF37/DCFF!AF7 -> 0.5099818
B140: Cash/revenue | C140: =DCFF!H7*C139 -> 358.795 | D140: =DCFF!I7*D139 -> 250.14916 | E140: =DCFF!J7*E139 -> 413.70551 | F140: =DCFF!K7*F139 -> 373.36657 | G140: =DCFF!L7*G139 -> 361.30801 | H140: =DCFF!M7*H139 -> 403.76295 | I140: =DCFF!N7*I139 -> 390.92916 | J140: =DCFF!O7*J139 -> 281.52149 | ... AA140: =DCFF!AF7*AA139 -> 5058.5975
B141: Loans
E142: 300
B155: Forecasted debt
B156: Maturity year | C156: Issued year | D156: Amount
B157: 2025
C160: 2024 | D160: =+C160+1 -> 2025 | E160: =+D160+1 -> 2026 | F160: =+E160+1 -> 2027 | G160: =+F160+1 -> 2028 | H160: =+G160+1 -> 2029 | I160: =+H160+1 -> 2030 | J160: =+I160+1 -> 2031 | K160: =+J160+1 -> 2032 | ... AA160: =+Z160+1 -> 2048
B161: Share buyback | C161: -200 | D161: -250 | E161: -300 | F161: -200 | G161: -150 | H161: -100 | I161: -75 | J161: -50 | K161: -50 | L161: -50 | M161: -50 | N161: -50 | O161: -50 | P161: -50 | Q161: -50 | R161: -50 | S161: -50 | T161: -50 | U161: -50 | V161: -50 | W161: -50 | X161: -50 | Y161: -50 | Z161: -50 | AA161: -50
B162: Dividends
C171: Short Term | D171: Medium term | E171: Long Term | F171: Reference (line)
B172: Depreciation factor | C172: 0.65 | D172: 0.55 | E172: 0.55 | F172: % Capex/Adq (l16)
B173: Stock-based comp | C173: 0.01 | D173: 0.02 | E173: 0.02 | F173: % revenue (l2)
B174: Tax Rate | C174: 0.2 | D174: 0.2 | E174: 0.2 | F174: % (line 9)
B175: Interest Rate on debt | C175: 0.02 | D175: 0.03 | E175: 0.03 | F175: % debt (l29)
B176: Interest Rate on cash | C176: 0 | D176: 0 | E176: 0 | F176: % of cash (l28)
B177: Net SBC | C177: 0.01 | D177: 0.02 | E177: 0.02 | F177: % revenue (l2)
B178: Working capital flows | C178: -0.3 | D178: -0.3 | E178: -0.3 | F178: % of change revenues (l2)
B179: Capex / Adq | C179: 0.08 | D179: 0.06 | E179: 0.04 | F179: % revenue (l2)
B180: Dividends | C180: 0 | D180: 0 | E180: 0 | F180: Growth rate
B181: Other financing flows | C181: -0.01 | D181: 0.01 | E181: 0.01 | F181: % of debt (l29)
B187: 1829.873 | C187: 2159.2501 | D187: 2504.7302 | E187: 2855.3924 | F187: 3226.5934 | G187: 3581.5187 | H187: 3939.6705 | I187: 4294.2409 | J187: 4637.7802 | K187: 4962.4248 | L187: 5309.7945 | M187: 5681.4801 | N187: 6022.3689 | O187: 6383.7111 | P187: 6702.8966 | Q187: 7038.0414 | R187: 7389.9435 | S187: 7759.4407 | T187: 8069.8183 | U187: 8392.611 | V187: 8728.3155 | W187: 9077.4481 | X187: 9349.7716 | Y187: 9630.2647 | Z187: 9919.1726
B188: 0 | C188: 0 | D188: 0 | E188: 0 | F188: 0 | G188: 0 | H188: 0 | I188: 0 | J188: 0 | K188: 0 | L188: 200 | M188: 200 | N188: 200 | O188: 220 | P188: 220 | Q188: 250 | R188: 250 | S188: 250 | T188: 250 | U188: 280 | V188: 300 | W188: 320 | X188: 350 | Y188: 380 | Z188: 400
B189: 0.10318844 | C189: 0.18 | D189: 0.16 | E189: 0.14 | F189: 0.13 | G189: 0.11 | H189: 0.1 | I189: 0.09 | J189: 0.08 | K189: 0.07 | L189: 0.07 | M189: 0.07 | N189: 0.06 | O189: 0.06 | P189: 0.05 | Q189: 0.05 | R189: 0.05 | S189: 0.05 | T189: 0.04 | U189: 0.04 | V189: 0.04 | W189: 0.04 | X189: 0.03 | Y189: 0.03 | Z189: 0.03
L192: =K187*L189 -> 347.36973 | M192: =L187*M189 -> 371.68561 | N192: =M187*N189 -> 340.88881 | O192: =N187*O189 -> 361.34214 | P192: =O187*P189 -> 319.18555 | Q192: =P187*Q189 -> 335.14483 | R192: =Q187*R189 -> 351.90207 | S192: =R187*S189 -> 369.49718 | ... Z192: =Y187*Z189 -> 288.90794
L194: =L188/L192 -> 0.5757554 | M194: =L188/M192 -> 0.53808916 | N194: =M188/N192 -> 0.58670158 | O194: =N188/O192 -> 0.55349205 | P194: =O188/P192 -> 0.68925425 | Q194: =P188/Q192 -> 0.65643262 | R194: =Q188/R192 -> 0.71042492 | S194: =R188/S192 -> 0.67659516 | T194: =S188/T192 -> 0.80547043 | ... Z194: =Y188/Z192 -> 1.3152979
L196: =AVERAGE(L194:P194) -> 0.58865849 | Q196: =AVERAGE(Q194:Z194) -> 0.90549267
